Method: <init>
	0 aload_0 (0, 0)
	1 invokespecial (0, 0)
	2 java/lang/Object.<init>:()V (0, 0)
	4 aload_1 (2, 1)
	5 iconst_0 (2, 1)
	6 aaload (2, 1)
	7 ifnonnull (2, 1)
	8 18 (2, 1)
	10 new (2, 1)
	11 org/apache/commons/math3/exception/MathIllegalArgumentException (2, 1)
	13 dup (2, 1)
	14 getstatic (2, 1)
	15 org/apache/commons/math3/exception/util/LocalizedFormats.OUTLINE_BOUNDARY_LOOP_OPEN:Lorg/apache/commons/math3/exception/util/LocalizedFormats; (2, 1)
	17 iconst_0 (2, 1)
	18 anewarray (2, 1)
	19 java/lang/Object (2, 1)
	21 invokespecial (2, 1)
	22 org/apache/commons/math3/exception/MathIllegalArgumentException.<init>:(Lorg/apache/commons/math3/exception/util/Localizable;[Ljava/lang/Object;)V (2, 1)
	24 athrow (2, 1)
	25 aload_0 (0, 0)
	26 aload_1 (0, 0)
	27 putfield (0, 0)
	28 org/apache/commons/math3/geometry/euclidean/twod/NestedLoops.loop:[Lorg/apache/commons/math3/geometry/euclidean/twod/Vector2D; (0, 0)
	30 aload_0 (0, 0)
	31 new (0, 0)
	32 java/util/ArrayList (0, 0)
	34 dup (0, 0)
	35 invokespecial (0, 0)
	36 java/util/ArrayList.<init>:()V (0, 0)
	38 putfield (0, 0)
	39 org/apache/commons/math3/geometry/euclidean/twod/NestedLoops.surrounded:Ljava/util/List; (0, 0)
	41 aload_0 (0, 0)
	42 dload_2 (0, 0)
	43 putfield (0, 0)
	44 org/apache/commons/math3/geometry/euclidean/twod/NestedLoops.tolerance:D (0, 0)
	46 new (0, 0)
	47 java/util/ArrayList (0, 0)
	49 dup (0, 0)
	50 invokespecial (0, 0)
	51 java/util/ArrayList.<init>:()V (0, 0)
	53 astore (0, 0)
	54 #4 (0, 0)
	55 aload_1 (0, 0)
	56 aload_1 (0, 0)
	57 arraylength (0, 0)
	58 iconst_1 (0, 0)
	59 isub (0, 0)
	60 aaload (0, 0)
	61 astore (0, 0)
	62 #5 (0, 0)
	63 iconst_0 (2, 4)
	64 istore (2, 4)
	65 #6 (2, 4)
	66 iload (2, 4)
	67 #6 (2, 4)
	68 aload_1 (2, 4)
	69 arraylength (2, 4)
	70 if_icmpge (2, 4)
	71 80 (2, 4)
	73 aload (2, 4)
	74 #5 (2, 4)
	75 astore (2, 4)
	76 #7 (2, 4)
	77 aload_1 (2, 4)
	78 iload (2, 4)
	79 #6 (2, 4)
	80 aaload (2, 4)
	81 astore (2, 4)
	82 #5 (2, 4)
	83 new (2, 4)
	84 org/apache/commons/math3/geometry/euclidean/twod/Line (2, 4)
	86 dup (2, 4)
	87 aload (2, 4)
	88 #7 (2, 4)
	89 aload (2, 4)
	90 #5 (2, 4)
	91 dload_2 (2, 4)
	92 invokespecial (2, 4)
	93 org/apache/commons/math3/geometry/euclidean/twod/Line.<init>:(Lorg/apache/commons/math3/geometry/euclidean/twod/Vector2D;Lorg/apache/commons/math3/geometry/euclidean/twod/Vector2D;D)V (2, 4)
	95 astore (2, 4)
	96 #8 (2, 4)
	97 new (2, 4)
	98 org/apache/commons/math3/geometry/euclidean/oned/IntervalsSet (2, 4)
	100 dup (2, 4)
	101 aload (2, 4)
	102 #8 (2, 4)
	103 aload (2, 4)
	104 #7 (2, 4)
	105 invokevirtual (2, 4)
	106 org/apache/commons/math3/geometry/euclidean/twod/Line.toSubSpace:(Lorg/apache/commons/math3/geometry/Point;)Lorg/apache/commons/math3/geometry/euclidean/oned/Vector1D; (2, 4)
	108 invokevirtual (2, 4)
	109 org/apache/commons/math3/geometry/euclidean/oned/Vector1D.getX:()D (2, 4)
	111 aload (2, 4)
	112 #8 (2, 4)
	113 aload (2, 4)
	114 #5 (2, 4)
	115 invokevirtual (2, 4)
	116 org/apache/commons/math3/geometry/euclidean/twod/Line.toSubSpace:(Lorg/apache/commons/math3/geometry/Point;)Lorg/apache/commons/math3/geometry/euclidean/oned/Vector1D; (2, 4)
	118 invokevirtual (2, 4)
	119 org/apache/commons/math3/geometry/euclidean/oned/Vector1D.getX:()D (2, 4)
	121 dload_2 (2, 4)
	122 invokespecial (2, 4)
	123 org/apache/commons/math3/geometry/euclidean/oned/IntervalsSet.<init>:(DDD)V (2, 4)
	125 astore (2, 4)
	126 #9 (2, 4)
	127 aload (2, 4)
	128 #4 (2, 4)
	129 new (2, 4)
	130 org/apache/commons/math3/geometry/euclidean/twod/SubLine (2, 4)
	132 dup (2, 4)
	133 aload (2, 4)
	134 #8 (2, 4)
	135 aload (2, 4)
	136 #9 (2, 4)
	137 invokespecial (2, 4)
	138 org/apache/commons/math3/geometry/euclidean/twod/SubLine.<init>:(Lorg/apache/commons/math3/geometry/partitioning/Hyperplane;Lorg/apache/commons/math3/geometry/partitioning/Region;)V (2, 4)
	140 invokevirtual (2, 4)
	141 java/util/ArrayList.add:(Ljava/lang/Object;)Z (2, 4)
	143 pop (2, 4)
	144 iinc (2, 4)
	145 #6 (2, 4)
	146 -89 (2, 4)
	147 goto (2, 4)
	148 -81 (2, 4)
	150 aload_0 (0, 0)
	151 new (0, 0)
	152 org/apache/commons/math3/geometry/euclidean/twod/PolygonsSet (0, 0)
	154 dup (0, 0)
	155 aload (0, 0)
	156 #4 (0, 0)
	157 dload_2 (0, 0)
	158 invokespecial (0, 0)
	159 org/apache/commons/math3/geometry/euclidean/twod/PolygonsSet.<init>:(Ljava/util/Collection;D)V (0, 0)
	161 putfield (0, 0)
	162 org/apache/commons/math3/geometry/euclidean/twod/NestedLoops.polygon:Lorg/apache/commons/math3/geometry/partitioning/Region; (0, 0)
	164 aload_0 (2, 1)
	165 getfield (2, 1)
	166 org/apache/commons/math3/geometry/euclidean/twod/NestedLoops.polygon:Lorg/apache/commons/math3/geometry/partitioning/Region; (2, 1)
	168 invokeinterface (2, 1)
	169 org/apache/commons/math3/geometry/partitioning/Region.java/lang/Double (2, 1)
	171 0 (2, 1)
	173 invokestatic (2, 1)
	174 java/lang/Double.isInfinite:(D)Z (2, 1)
	176 ifeq (2, 1)
	177 29 (2, 1)
	179 aload_0 (2, 1)
	180 new (2, 1)
	181 org/apache/commons/math3/geometry/partitioning/RegionFactory (2, 1)
	183 dup (2, 1)
	184 invokespecial (2, 1)
	185 org/apache/commons/math3/geometry/partitioning/RegionFactory.<init>:()V (2, 1)
	187 aload_0 (2, 1)
	188 getfield (2, 1)
	189 org/apache/commons/math3/geometry/euclidean/twod/NestedLoops.polygon:Lorg/apache/commons/math3/geometry/partitioning/Region; (2, 1)
	191 invokevirtual (2, 1)
	192 org/apache/commons/math3/geometry/partitioning/RegionFactory.getComplement:(Lorg/apache/commons/math3/geometry/partitioning/Region;)Lorg/apache/commons/math3/geometry/partitioning/Region; (2, 1)
	194 putfield (2, 1)
	195 org/apache/commons/math3/geometry/euclidean/twod/NestedLoops.polygon:Lorg/apache/commons/math3/geometry/partitioning/Region; (2, 1)
	197 aload_0 (2, 1)
	198 iconst_0 (2, 1)
	199 putfield (2, 1)
	200 org/apache/commons/math3/geometry/euclidean/twod/NestedLoops.originalIsClockwise:Z (2, 1)
	202 goto (2, 1)
	203 8 (2, 1)
	205 aload_0 (2, 2)
	206 iconst_1 (2, 2)
	207 putfield (2, 2)
	208 org/apache/commons/math3/geometry/euclidean/twod/NestedLoops.originalIsClockwise:Z (2, 2)
	210 return (0, 0)

Method: add
	0 aload_0 (1, 4)
	1 getfield (1, 4)
	2 org/apache/commons/math3/geometry/euclidean/twod/NestedLoops.surrounded:Ljava/util/List; (1, 4)
	4 invokeinterface (1, 4)
	5 java/util/List.java/util/Iterator (1, 4)
	7 0 (1, 4)
	9 astore_2 (1, 4)
	10 aload_2 (1, 4)
	11 invokeinterface (1, 4)
	12 java/util/Iterator.next:()Ljava/lang/Object; (1, 4)
	14 0 (1, 4)
	16 ifeq (1, 4)
	17 38 (1, 4)
	19 aload_2 (1, 4)
	20 invokeinterface (1, 4)
	21 java/util/Iterator.contains:(Lorg/apache/commons/math3/geometry/partitioning/Region;)Z (1, 4)
	23 0 (1, 4)
	25 checkcast (1, 4)
	26 org/apache/commons/math3/geometry/euclidean/twod/NestedLoops (1, 4)
	28 astore_3 (1, 4)
	29 aload_3 (2, 1)
	30 getfield (2, 1)
	31 org/apache/commons/math3/geometry/euclidean/twod/NestedLoops.polygon:Lorg/apache/commons/math3/geometry/partitioning/Region; (2, 1)
	33 aload_1 (2, 1)
	34 getfield (2, 1)
	35 org/apache/commons/math3/geometry/euclidean/twod/NestedLoops.polygon:Lorg/apache/commons/math3/geometry/partitioning/Region; (2, 1)
	37 invokeinterface (2, 1)
	38 org/apache/commons/math3/geometry/partitioning/Region.remove:()V (2, 1)
	40 0 (2, 1)
	42 ifeq (2, 1)
	43 9 (2, 1)
	45 aload_3 (2, 1)
	46 aload_1 (2, 1)
	47 invokespecial (2, 1)
	48 org/apache/commons/math3/geometry/euclidean/twod/NestedLoops.add:(Lorg/apache/commons/math3/geometry/euclidean/twod/NestedLoops;)V (2, 1)
	50 return (2, 1)
	51 goto (0, 0)
	52 -41 (0, 0)
	54 aload_0 (1, 4)
	55 getfield (1, 4)
	56 org/apache/commons/math3/geometry/euclidean/twod/NestedLoops.surrounded:Ljava/util/List; (1, 4)
	58 invokeinterface (1, 4)
	59 java/util/List.java/util/Iterator (1, 4)
	61 0 (1, 4)
	63 astore_2 (1, 4)
	64 aload_2 (1, 4)
	65 invokeinterface (1, 4)
	66 java/util/Iterator.next:()Ljava/lang/Object; (1, 4)
	68 0 (1, 4)
	70 ifeq (1, 4)
	71 49 (1, 4)
	73 aload_2 (1, 4)
	74 invokeinterface (1, 4)
	75 java/util/Iterator.contains:(Lorg/apache/commons/math3/geometry/partitioning/Region;)Z (1, 4)
	77 0 (1, 4)
	79 checkcast (1, 4)
	80 org/apache/commons/math3/geometry/euclidean/twod/NestedLoops (1, 4)
	82 astore_3 (1, 4)
	83 aload_1 (2, 1)
	84 getfield (2, 1)
	85 org/apache/commons/math3/geometry/euclidean/twod/NestedLoops.polygon:Lorg/apache/commons/math3/geometry/partitioning/Region; (2, 1)
	87 aload_3 (2, 1)
	88 getfield (2, 1)
	89 org/apache/commons/math3/geometry/euclidean/twod/NestedLoops.polygon:Lorg/apache/commons/math3/geometry/partitioning/Region; (2, 1)
	91 invokeinterface (2, 1)
	92 org/apache/commons/math3/geometry/partitioning/Region.remove:()V (2, 1)
	94 0 (2, 1)
	96 ifeq (2, 1)
	97 20 (2, 1)
	99 aload_1 (2, 1)
	100 getfield (2, 1)
	101 org/apache/commons/math3/geometry/euclidean/twod/NestedLoops.surrounded:Ljava/util/List; (2, 1)
	103 aload_3 (2, 1)
	104 invokeinterface (2, 1)
	105 java/util/List.org/apache/commons/math3/geometry/euclidean/twod/PolygonsSet (2, 1)
	107 0 (2, 1)
	109 pop (2, 1)
	110 aload_2 (2, 1)
	111 invokeinterface (2, 1)
	112 java/util/Iterator.intersection:(Lorg/apache/commons/math3/geometry/partitioning/Region;Lorg/apache/commons/math3/geometry/partitioning/Region;)Lorg/apache/commons/math3/geometry/partitioning/Region; (2, 1)
	114 0 (2, 1)
	116 goto (0, 1)
	117 -52 (0, 1)
	119 new (0, 1)
	120 org/apache/commons/math3/geometry/partitioning/RegionFactory (0, 1)
	122 dup (0, 1)
	123 invokespecial (0, 1)
	124 org/apache/commons/math3/geometry/partitioning/RegionFactory.<init>:()V (0, 1)
	126 astore_2 (0, 1)
	127 aload_0 (1, 4)
	128 getfield (1, 4)
	129 org/apache/commons/math3/geometry/euclidean/twod/NestedLoops.surrounded:Ljava/util/List; (1, 4)
	131 invokeinterface (1, 4)
	132 java/util/List.java/util/Iterator (1, 4)
	134 0 (1, 4)
	136 astore_3 (1, 4)
	137 aload_3 (1, 4)
	138 invokeinterface (1, 4)
	139 java/util/Iterator.next:()Ljava/lang/Object; (1, 4)
	141 0 (1, 4)
	143 ifeq (1, 4)
	144 53 (1, 4)
	146 aload_3 (1, 4)
	147 invokeinterface (1, 4)
	148 java/util/Iterator.contains:(Lorg/apache/commons/math3/geometry/partitioning/Region;)Z (1, 4)
	150 0 (1, 4)
	152 checkcast (1, 4)
	153 org/apache/commons/math3/geometry/euclidean/twod/NestedLoops (1, 4)
	155 astore (1, 4)
	156 #4 (1, 4)
	157 aload_2 (2, 1)
	158 aload_1 (2, 1)
	159 getfield (2, 1)
	160 org/apache/commons/math3/geometry/euclidean/twod/NestedLoops.polygon:Lorg/apache/commons/math3/geometry/partitioning/Region; (2, 1)
	162 aload (2, 1)
	163 #4 (2, 1)
	164 getfield (2, 1)
	165 org/apache/commons/math3/geometry/euclidean/twod/NestedLoops.polygon:Lorg/apache/commons/math3/geometry/partitioning/Region; (2, 1)
	167 invokevirtual (2, 1)
	168 org/apache/commons/math3/geometry/partitioning/RegionFactory.intersection:(Lorg/apache/commons/math3/geometry/partitioning/Region;Lorg/apache/commons/math3/geometry/partitioning/Region;)Lorg/apache/commons/math3/geometry/partitioning/Region; (2, 1)
	170 invokeinterface (2, 1)
	171 org/apache/commons/math3/geometry/partitioning/Region.CROSSING_BOUNDARY_LOOPS:Lorg/apache/commons/math3/exception/util/LocalizedFormats; (2, 1)
	173 0 (2, 1)
	175 ifne (2, 1)
	176 18 (2, 1)
	178 new (2, 1)
	179 org/apache/commons/math3/exception/MathIllegalArgumentException (2, 1)
	181 dup (2, 1)
	182 getstatic (2, 1)
	183 org/apache/commons/math3/exception/util/LocalizedFormats.CROSSING_BOUNDARY_LOOPS:Lorg/apache/commons/math3/exception/util/LocalizedFormats; (2, 1)
	185 iconst_0 (2, 1)
	186 anewarray (2, 1)
	187 java/lang/Object (2, 1)
	189 invokespecial (2, 1)
	190 org/apache/commons/math3/exception/MathIllegalArgumentException.<init>:(Lorg/apache/commons/math3/exception/util/Localizable;[Ljava/lang/Object;)V (2, 1)
	192 athrow (2, 1)
	193 goto (0, 1)
	194 -56 (0, 1)
	196 aload_0 (0, 1)
	197 getfield (0, 1)
	198 org/apache/commons/math3/geometry/euclidean/twod/NestedLoops.surrounded:Ljava/util/List; (0, 1)
	200 aload_1 (0, 1)
	201 invokeinterface (0, 1)
	202 java/util/List.org/apache/commons/math3/geometry/euclidean/twod/PolygonsSet (0, 1)
	204 0 (0, 1)
	206 pop (0, 1)
	207 return (0, 1)

Method: correctOrientation
	0 aload_0 (1, 4)
	1 getfield (1, 4)
	2 org/apache/commons/math3/geometry/euclidean/twod/NestedLoops.surrounded:Ljava/util/List; (1, 4)
	4 invokeinterface (1, 4)
	5 java/util/List.java/util/Iterator (1, 4)
	7 0 (1, 4)
	9 astore_1 (1, 4)
	10 aload_1 (1, 4)
	11 invokeinterface (1, 4)
	12 java/util/Iterator.next:()Ljava/lang/Object; (1, 4)
	14 0 (1, 4)
	16 ifeq (1, 4)
	17 21 (1, 4)
	19 aload_1 (1, 4)
	20 invokeinterface (1, 4)
	21 java/util/Iterator.contains:(Lorg/apache/commons/math3/geometry/partitioning/Region;)Z (1, 4)
	23 0 (1, 4)
	25 checkcast (1, 4)
	26 org/apache/commons/math3/geometry/euclidean/twod/NestedLoops (1, 4)
	28 astore_2 (1, 4)
	29 aload_2 (1, 4)
	30 iconst_1 (1, 4)
	31 invokespecial (1, 4)
	32 org/apache/commons/math3/geometry/euclidean/twod/NestedLoops.setClockWise:(Z)V (1, 4)
	34 goto (0, 0)
	35 -24 (0, 0)
	37 return (0, 0)

Method: setClockWise
	0 aload_0 (1, 1)
	1 getfield (1, 1)
	2 org/apache/commons/math3/geometry/euclidean/twod/NestedLoops.originalIsClockwise:Z (1, 1)
	4 iload_1 (1, 1)
	5 ixor (1, 1)
	6 ifeq (1, 1)
	7 53 (1, 1)
	9 iconst_m1 (1, 1)
	10 istore_2 (1, 1)
	11 aload_0 (1, 1)
	12 getfield (1, 1)
	13 org/apache/commons/math3/geometry/euclidean/twod/NestedLoops.loop:[Lorg/apache/commons/math3/geometry/euclidean/twod/Vector2D; (1, 1)
	15 arraylength (1, 1)
	16 istore_3 (1, 1)
	17 iinc (2, 3)
	18 #2 (2, 3)
	19 28 (2, 3)
	20 iload_2 (2, 3)
	21 iinc (2, 3)
	22 #3 (2, 3)
	23 29 (2, 3)
	24 iload_3 (2, 3)
	25 if_icmpge (2, 3)
	26 34 (2, 3)
	28 aload_0 (2, 3)
	29 getfield (2, 3)
	30 org/apache/commons/math3/geometry/euclidean/twod/NestedLoops.loop:[Lorg/apache/commons/math3/geometry/euclidean/twod/Vector2D; (2, 3)
	32 iload_2 (2, 3)
	33 aaload (2, 3)
	34 astore (2, 3)
	35 #4 (2, 3)
	36 aload_0 (2, 3)
	37 getfield (2, 3)
	38 org/apache/commons/math3/geometry/euclidean/twod/NestedLoops.loop:[Lorg/apache/commons/math3/geometry/euclidean/twod/Vector2D; (2, 3)
	40 iload_2 (2, 3)
	41 aload_0 (2, 3)
	42 getfield (2, 3)
	43 org/apache/commons/math3/geometry/euclidean/twod/NestedLoops.loop:[Lorg/apache/commons/math3/geometry/euclidean/twod/Vector2D; (2, 3)
	45 iload_3 (2, 3)
	46 aaload (2, 3)
	47 aastore (2, 3)
	48 aload_0 (2, 3)
	49 getfield (2, 3)
	50 org/apache/commons/math3/geometry/euclidean/twod/NestedLoops.loop:[Lorg/apache/commons/math3/geometry/euclidean/twod/Vector2D; (2, 3)
	52 iload_3 (2, 3)
	53 aload (2, 3)
	54 #4 (2, 3)
	55 aastore (2, 3)
	56 goto (1, 1)
	57 -39 (1, 1)
	59 aload_0 (1, 4)
	60 getfield (1, 4)
	61 org/apache/commons/math3/geometry/euclidean/twod/NestedLoops.surrounded:Ljava/util/List; (1, 4)
	63 invokeinterface (1, 4)
	64 java/util/List.java/util/Iterator (1, 4)
	66 0 (1, 4)
	68 astore_2 (1, 4)
	69 aload_2 (1, 4)
	70 invokeinterface (1, 4)
	71 java/util/Iterator.next:()Ljava/lang/Object; (1, 4)
	73 0 (1, 4)
	75 ifeq (1, 4)
	76 29 (1, 4)
	78 aload_2 (1, 4)
	79 invokeinterface (1, 4)
	80 java/util/Iterator.contains:(Lorg/apache/commons/math3/geometry/partitioning/Region;)Z (1, 4)
	82 0 (1, 4)
	84 checkcast (1, 4)
	85 org/apache/commons/math3/geometry/euclidean/twod/NestedLoops (1, 4)
	87 astore_3 (1, 4)
	88 aload_3 (1, 4)
	89 iload_1 (1, 4)
	90 ifne (1, 4)
	91 7 (1, 4)
	93 iconst_1 (1, 4)
	94 goto (1, 4)
	95 4 (1, 4)
	97 iconst_0 (1, 4)
	98 invokespecial (1, 4)
	99 org/apache/commons/math3/geometry/euclidean/twod/NestedLoops.setClockWise:(Z)V (1, 4)
	101 goto (0, 0)
	102 -32 (0, 0)
	104 return (0, 0)

