Method: <init>
	0 aload_0 (0, 0)
	1 invokespecial (0, 0)
	2 java/lang/Object.<init>:()V (0, 0)
	4 aload_0 (0, 0)
	5 aload_1 (0, 0)
	6 putfield (0, 0)
	7 org/apache/commons/math3/geometry/euclidean/twod/PolygonsSet$Edge.start:Lorg/apache/commons/math3/geometry/euclidean/twod/PolygonsSet$Vertex; (0, 0)
	9 aload_0 (0, 0)
	10 aload_2 (0, 0)
	11 putfield (0, 0)
	12 org/apache/commons/math3/geometry/euclidean/twod/PolygonsSet$Edge.end:Lorg/apache/commons/math3/geometry/euclidean/twod/PolygonsSet$Vertex; (0, 0)
	14 aload_0 (0, 0)
	15 aload_3 (0, 0)
	16 putfield (0, 0)
	17 org/apache/commons/math3/geometry/euclidean/twod/PolygonsSet$Edge.line:Lorg/apache/commons/math3/geometry/euclidean/twod/Line; (0, 0)
	19 aload_0 (0, 0)
	20 aconst_null (0, 0)
	21 putfield (0, 0)
	22 org/apache/commons/math3/geometry/euclidean/twod/PolygonsSet$Edge.node:Lorg/apache/commons/math3/geometry/partitioning/BSPTree; (0, 0)
	24 aload_1 (0, 0)
	25 aload_0 (0, 0)
	26 invokevirtual (0, 0)
	27 org/apache/commons/math3/geometry/euclidean/twod/PolygonsSet$Vertex.setOutgoing:(Lorg/apache/commons/math3/geometry/euclidean/twod/PolygonsSet$Edge;)V (0, 0)
	29 aload_2 (0, 0)
	30 aload_0 (0, 0)
	31 invokevirtual (0, 0)
	32 org/apache/commons/math3/geometry/euclidean/twod/PolygonsSet$Vertex.setIncoming:(Lorg/apache/commons/math3/geometry/euclidean/twod/PolygonsSet$Edge;)V (0, 0)
	34 return (0, 0)

Method: getStart
	0 aload_0 (0, 0)
	1 getfield (0, 0)
	2 org/apache/commons/math3/geometry/euclidean/twod/PolygonsSet$Edge.start:Lorg/apache/commons/math3/geometry/euclidean/twod/PolygonsSet$Vertex; (0, 0)
	4 areturn (0, 0)

Method: getEnd
	0 aload_0 (0, 0)
	1 getfield (0, 0)
	2 org/apache/commons/math3/geometry/euclidean/twod/PolygonsSet$Edge.end:Lorg/apache/commons/math3/geometry/euclidean/twod/PolygonsSet$Vertex; (0, 0)
	4 areturn (0, 0)

Method: getLine
	0 aload_0 (0, 0)
	1 getfield (0, 0)
	2 org/apache/commons/math3/geometry/euclidean/twod/PolygonsSet$Edge.line:Lorg/apache/commons/math3/geometry/euclidean/twod/Line; (0, 0)
	4 areturn (0, 0)

Method: setNode
	0 aload_0 (0, 0)
	1 aload_1 (0, 0)
	2 putfield (0, 0)
	3 org/apache/commons/math3/geometry/euclidean/twod/PolygonsSet$Edge.node:Lorg/apache/commons/math3/geometry/partitioning/BSPTree; (0, 0)
	5 return (0, 0)

Method: getNode
	0 aload_0 (0, 0)
	1 getfield (0, 0)
	2 org/apache/commons/math3/geometry/euclidean/twod/PolygonsSet$Edge.node:Lorg/apache/commons/math3/geometry/partitioning/BSPTree; (0, 0)
	4 areturn (0, 0)

Method: split
	0 new (0, 0)
	1 org/apache/commons/math3/geometry/euclidean/twod/PolygonsSet$Vertex (0, 0)
	3 dup (0, 0)
	4 aload_0 (0, 0)
	5 getfield (0, 0)
	6 org/apache/commons/math3/geometry/euclidean/twod/PolygonsSet$Edge.line:Lorg/apache/commons/math3/geometry/euclidean/twod/Line; (0, 0)
	8 aload_1 (0, 0)
	9 invokevirtual (0, 0)
	10 org/apache/commons/math3/geometry/euclidean/twod/Line.intersection:(Lorg/apache/commons/math3/geometry/euclidean/twod/Line;)Lorg/apache/commons/math3/geometry/euclidean/twod/Vector2D; (0, 0)
	12 invokespecial (0, 0)
	13 org/apache/commons/math3/geometry/euclidean/twod/PolygonsSet$Vertex.<init>:(Lorg/apache/commons/math3/geometry/euclidean/twod/Vector2D;)V (0, 0)
	15 astore_2 (0, 0)
	16 aload_2 (0, 0)
	17 aload_1 (0, 0)
	18 invokevirtual (0, 0)
	19 org/apache/commons/math3/geometry/euclidean/twod/PolygonsSet$Vertex.bindWith:(Lorg/apache/commons/math3/geometry/euclidean/twod/Line;)V (0, 0)
	21 new (0, 0)
	22 org/apache/commons/math3/geometry/euclidean/twod/PolygonsSet$Edge (0, 0)
	24 dup (0, 0)
	25 aload_0 (0, 0)
	26 getfield (0, 0)
	27 org/apache/commons/math3/geometry/euclidean/twod/PolygonsSet$Edge.start:Lorg/apache/commons/math3/geometry/euclidean/twod/PolygonsSet$Vertex; (0, 0)
	29 aload_2 (0, 0)
	30 aload_0 (0, 0)
	31 getfield (0, 0)
	32 org/apache/commons/math3/geometry/euclidean/twod/PolygonsSet$Edge.line:Lorg/apache/commons/math3/geometry/euclidean/twod/Line; (0, 0)
	34 invokespecial (0, 0)
	35 org/apache/commons/math3/geometry/euclidean/twod/PolygonsSet$Edge.<init>:(Lorg/apache/commons/math3/geometry/euclidean/twod/PolygonsSet$Vertex;Lorg/apache/commons/math3/geometry/euclidean/twod/PolygonsSet$Vertex;Lorg/apache/commons/math3/geometry/euclidean/twod/Line;)V (0, 0)
	37 astore_3 (0, 0)
	38 new (0, 0)
	39 org/apache/commons/math3/geometry/euclidean/twod/PolygonsSet$Edge (0, 0)
	41 dup (0, 0)
	42 aload_2 (0, 0)
	43 aload_0 (0, 0)
	44 getfield (0, 0)
	45 org/apache/commons/math3/geometry/euclidean/twod/PolygonsSet$Edge.end:Lorg/apache/commons/math3/geometry/euclidean/twod/PolygonsSet$Vertex; (0, 0)
	47 aload_0 (0, 0)
	48 getfield (0, 0)
	49 org/apache/commons/math3/geometry/euclidean/twod/PolygonsSet$Edge.line:Lorg/apache/commons/math3/geometry/euclidean/twod/Line; (0, 0)
	51 invokespecial (0, 0)
	52 org/apache/commons/math3/geometry/euclidean/twod/PolygonsSet$Edge.<init>:(Lorg/apache/commons/math3/geometry/euclidean/twod/PolygonsSet$Vertex;Lorg/apache/commons/math3/geometry/euclidean/twod/PolygonsSet$Vertex;Lorg/apache/commons/math3/geometry/euclidean/twod/Line;)V (0, 0)
	54 astore (0, 0)
	55 #4 (0, 0)
	56 aload_3 (0, 0)
	57 aload_0 (0, 0)
	58 getfield (0, 0)
	59 org/apache/commons/math3/geometry/euclidean/twod/PolygonsSet$Edge.node:Lorg/apache/commons/math3/geometry/partitioning/BSPTree; (0, 0)
	61 putfield (0, 0)
	62 org/apache/commons/math3/geometry/euclidean/twod/PolygonsSet$Edge.node:Lorg/apache/commons/math3/geometry/partitioning/BSPTree; (0, 0)
	64 aload (0, 0)
	65 #4 (0, 0)
	66 aload_0 (0, 0)
	67 getfield (0, 0)
	68 org/apache/commons/math3/geometry/euclidean/twod/PolygonsSet$Edge.node:Lorg/apache/commons/math3/geometry/partitioning/BSPTree; (0, 0)
	70 putfield (0, 0)
	71 org/apache/commons/math3/geometry/euclidean/twod/PolygonsSet$Edge.node:Lorg/apache/commons/math3/geometry/partitioning/BSPTree; (0, 0)
	73 aload_2 (0, 0)
	74 areturn (0, 0)

