Method: <init>
	0 aload_0 (0, 0)
	1 invokespecial (0, 0)
	2 java/lang/Object.<init>:()V (0, 0)
	4 aload_0 (0, 0)
	5 dload_1 (0, 0)
	6 putfield (0, 0)
	7 org/apache/commons/math3/geometry/euclidean/twod/PolygonsSet$SegmentsBuilder.tolerance:D (0, 0)
	9 aload_0 (0, 0)
	10 new (0, 0)
	11 java/util/ArrayList (0, 0)
	13 dup (0, 0)
	14 invokespecial (0, 0)
	15 java/util/ArrayList.<init>:()V (0, 0)
	17 putfield (0, 0)
	18 org/apache/commons/math3/geometry/euclidean/twod/PolygonsSet$SegmentsBuilder.segments:Ljava/util/List; (0, 0)
	20 return (0, 0)

Method: visitOrder
	0 getstatic (0, 0)
	1 org/apache/commons/math3/geometry/partitioning/BSPTreeVisitor$Order.MINUS_SUB_PLUS:Lorg/apache/commons/math3/geometry/partitioning/BSPTreeVisitor$Order; (0, 0)
	3 areturn (0, 0)

Method: visitInternalNode
	0 aload_1 (0, 0)
	1 invokevirtual (0, 0)
	2 org/apache/commons/math3/geometry/partitioning/BSPTree.getAttribute:()Ljava/lang/Object; (0, 0)
	4 checkcast (0, 0)
	5 org/apache/commons/math3/geometry/partitioning/BoundaryAttribute (0, 0)
	7 astore_2 (0, 0)
	8 aload_2 (0, 0)
	9 invokevirtual (0, 0)
	10 org/apache/commons/math3/geometry/partitioning/BoundaryAttribute.getSplitters:()Lorg/apache/commons/math3/geometry/partitioning/NodesSet; (0, 0)
	12 astore_3 (0, 0)
	13 aload_2 (1, 1)
	14 invokevirtual (1, 1)
	15 org/apache/commons/math3/geometry/partitioning/BoundaryAttribute.getPlusOutside:()Lorg/apache/commons/math3/geometry/partitioning/SubHyperplane; (1, 1)
	17 ifnull (1, 1)
	18 14 (1, 1)
	20 aload_0 (1, 1)
	21 aload_2 (1, 1)
	22 invokevirtual (1, 1)
	23 org/apache/commons/math3/geometry/partitioning/BoundaryAttribute.getPlusOutside:()Lorg/apache/commons/math3/geometry/partitioning/SubHyperplane; (1, 1)
	25 aload_1 (1, 1)
	26 aload_3 (1, 1)
	27 iconst_0 (1, 1)
	28 invokespecial (1, 1)
	29 org/apache/commons/math3/geometry/euclidean/twod/PolygonsSet$SegmentsBuilder.addContribution:(Lorg/apache/commons/math3/geometry/partitioning/SubHyperplane;Lorg/apache/commons/math3/geometry/partitioning/BSPTree;Ljava/lang/Iterable;Z)V (1, 1)
	31 aload_2 (1, 1)
	32 invokevirtual (1, 1)
	33 org/apache/commons/math3/geometry/partitioning/BoundaryAttribute.getPlusInside:()Lorg/apache/commons/math3/geometry/partitioning/SubHyperplane; (1, 1)
	35 ifnull (1, 1)
	36 14 (1, 1)
	38 aload_0 (1, 1)
	39 aload_2 (1, 1)
	40 invokevirtual (1, 1)
	41 org/apache/commons/math3/geometry/partitioning/BoundaryAttribute.getPlusInside:()Lorg/apache/commons/math3/geometry/partitioning/SubHyperplane; (1, 1)
	43 aload_1 (1, 1)
	44 aload_3 (1, 1)
	45 iconst_1 (1, 1)
	46 invokespecial (1, 1)
	47 org/apache/commons/math3/geometry/euclidean/twod/PolygonsSet$SegmentsBuilder.addContribution:(Lorg/apache/commons/math3/geometry/partitioning/SubHyperplane;Lorg/apache/commons/math3/geometry/partitioning/BSPTree;Ljava/lang/Iterable;Z)V (1, 1)
	49 return (0, 0)

Method: visitLeafNode
	0 return (0, 0)

Method: addContribution
	0 aload_1 (0, 0)
	1 checkcast (0, 0)
	2 org/apache/commons/math3/geometry/partitioning/AbstractSubHyperplane (0, 0)
	4 astore (0, 0)
	5 #5 (0, 0)
	6 aload_1 (0, 0)
	7 invokeinterface (0, 0)
	8 org/apache/commons/math3/geometry/partitioning/SubHyperplane.org/apache/commons/math3/geometry/euclidean/twod/Line (0, 0)
	10 0 (0, 0)
	12 checkcast (0, 0)
	13 org/apache/commons/math3/geometry/euclidean/twod/Line (0, 0)
	15 astore (0, 0)
	16 #6 (0, 0)
	17 aload (0, 0)
	18 #5 (0, 0)
	19 invokevirtual (0, 0)
	20 org/apache/commons/math3/geometry/partitioning/AbstractSubHyperplane.getRemainingRegion:()Lorg/apache/commons/math3/geometry/partitioning/Region; (0, 0)
	22 checkcast (0, 0)
	23 org/apache/commons/math3/geometry/euclidean/oned/IntervalsSet (0, 0)
	25 invokevirtual (0, 0)
	26 org/apache/commons/math3/geometry/euclidean/oned/IntervalsSet.asList:()Ljava/util/List; (0, 0)
	28 astore (0, 0)
	29 #7 (0, 0)
	30 aload (1, 4)
	31 #7 (1, 4)
	32 invokeinterface (1, 4)
	33 java/util/List.java/util/Iterator (1, 4)
	35 0 (1, 4)
	37 astore (1, 4)
	38 #8 (1, 4)
	39 aload (1, 4)
	40 #8 (1, 4)
	41 invokeinterface (1, 4)
	42 java/util/Iterator.next:()Ljava/lang/Object; (1, 4)
	44 0 (1, 4)
	46 ifeq (1, 4)
	47 171 (1, 4)
	49 aload (1, 4)
	50 #8 (1, 4)
	51 invokeinterface (1, 4)
	52 java/util/Iterator.org/apache/commons/math3/geometry/euclidean/oned/Interval (1, 4)
	54 0 (1, 4)
	56 checkcast (1, 4)
	57 org/apache/commons/math3/geometry/euclidean/oned/Interval (1, 4)
	59 astore (1, 4)
	60 #9 (1, 4)
	61 aload (1, 4)
	62 #9 (1, 4)
	63 invokevirtual (1, 4)
	64 org/apache/commons/math3/geometry/euclidean/oned/Interval.getInf:()D (1, 4)
	66 invokestatic (1, 4)
	67 java/lang/Double.isInfinite:(D)Z (1, 4)
	69 ifeq (1, 4)
	70 7 (1, 4)
	72 aconst_null (1, 4)
	73 goto (1, 4)
	74 20 (1, 4)
	76 aload (1, 4)
	77 #6 (1, 4)
	78 new (1, 4)
	79 org/apache/commons/math3/geometry/euclidean/oned/Vector1D (1, 4)
	81 dup (1, 4)
	82 aload (1, 4)
	83 #9 (1, 4)
	84 invokevirtual (1, 4)
	85 org/apache/commons/math3/geometry/euclidean/oned/Interval.getInf:()D (1, 4)
	87 invokespecial (1, 4)
	88 org/apache/commons/math3/geometry/euclidean/oned/Vector1D.<init>:(D)V (1, 4)
	90 invokevirtual (1, 4)
	91 org/apache/commons/math3/geometry/euclidean/twod/Line.toSpace:(Lorg/apache/commons/math3/geometry/Point;)Lorg/apache/commons/math3/geometry/euclidean/twod/Vector2D; (1, 4)
	93 astore (1, 4)
	94 #10 (1, 4)
	95 aload (1, 4)
	96 #9 (1, 4)
	97 invokevirtual (1, 4)
	98 org/apache/commons/math3/geometry/euclidean/oned/Interval.getSup:()D (1, 4)
	100 invokestatic (1, 4)
	101 java/lang/Double.isInfinite:(D)Z (1, 4)
	103 ifeq (1, 4)
	104 7 (1, 4)
	106 aconst_null (1, 4)
	107 goto (1, 4)
	108 20 (1, 4)
	110 aload (1, 4)
	111 #6 (1, 4)
	112 new (1, 4)
	113 org/apache/commons/math3/geometry/euclidean/oned/Vector1D (1, 4)
	115 dup (1, 4)
	116 aload (1, 4)
	117 #9 (1, 4)
	118 invokevirtual (1, 4)
	119 org/apache/commons/math3/geometry/euclidean/oned/Interval.getSup:()D (1, 4)
	121 invokespecial (1, 4)
	122 org/apache/commons/math3/geometry/euclidean/oned/Vector1D.<init>:(D)V (1, 4)
	124 invokevirtual (1, 4)
	125 org/apache/commons/math3/geometry/euclidean/twod/Line.toSpace:(Lorg/apache/commons/math3/geometry/Point;)Lorg/apache/commons/math3/geometry/euclidean/twod/Vector2D; (1, 4)
	127 astore (1, 4)
	128 #11 (1, 4)
	129 aload_0 (1, 4)
	130 aload (1, 4)
	131 #10 (1, 4)
	132 aload_3 (1, 4)
	133 invokespecial (1, 4)
	134 org/apache/commons/math3/geometry/euclidean/twod/PolygonsSet$SegmentsBuilder.selectClosest:(Lorg/apache/commons/math3/geometry/euclidean/twod/Vector2D;Ljava/lang/Iterable;)Lorg/apache/commons/math3/geometry/partitioning/BSPTree; (1, 4)
	136 astore (1, 4)
	137 #12 (1, 4)
	138 aload_0 (1, 4)
	139 aload (1, 4)
	140 #11 (1, 4)
	141 aload_3 (1, 4)
	142 invokespecial (1, 4)
	143 org/apache/commons/math3/geometry/euclidean/twod/PolygonsSet$SegmentsBuilder.selectClosest:(Lorg/apache/commons/math3/geometry/euclidean/twod/Vector2D;Ljava/lang/Iterable;)Lorg/apache/commons/math3/geometry/partitioning/BSPTree; (1, 4)
	145 astore (1, 4)
	146 #13 (1, 4)
	147 iload (2, 1)
	148 #4 (2, 1)
	149 ifeq (2, 1)
	150 37 (2, 1)
	152 aload_0 (2, 1)
	153 getfield (2, 1)
	154 org/apache/commons/math3/geometry/euclidean/twod/PolygonsSet$SegmentsBuilder.segments:Ljava/util/List; (2, 1)
	156 new (2, 1)
	157 org/apache/commons/math3/geometry/euclidean/twod/PolygonsSet$ConnectableSegment (2, 1)
	159 dup (2, 1)
	160 aload (2, 1)
	161 #11 (2, 1)
	162 aload (2, 1)
	163 #10 (2, 1)
	164 aload (2, 1)
	165 #6 (2, 1)
	166 invokevirtual (2, 1)
	167 org/apache/commons/math3/geometry/euclidean/twod/Line.getReverse:()Lorg/apache/commons/math3/geometry/euclidean/twod/Line; (2, 1)
	169 aload_2 (2, 1)
	170 aload (2, 1)
	171 #13 (2, 1)
	172 aload (2, 1)
	173 #12 (2, 1)
	174 invokespecial (2, 1)
	175 org/apache/commons/math3/geometry/euclidean/twod/PolygonsSet$ConnectableSegment.<init>:(Lorg/apache/commons/math3/geometry/euclidean/twod/Vector2D;Lorg/apache/commons/math3/geometry/euclidean/twod/Vector2D;Lorg/apache/commons/math3/geometry/euclidean/twod/Line;Lorg/apache/commons/math3/geometry/partitioning/BSPTree;Lorg/apache/commons/math3/geometry/partitioning/BSPTree;Lorg/apache/commons/math3/geometry/partitioning/BSPTree;)V (2, 1)
	177 invokeinterface (2, 1)
	178 java/util/List.java/lang/Double (2, 1)
	180 0 (2, 1)
	182 pop (2, 1)
	183 goto (2, 1)
	184 31 (2, 1)
	186 aload_0 (2, 2)
	187 getfield (2, 2)
	188 org/apache/commons/math3/geometry/euclidean/twod/PolygonsSet$SegmentsBuilder.segments:Ljava/util/List; (2, 2)
	190 new (2, 2)
	191 org/apache/commons/math3/geometry/euclidean/twod/PolygonsSet$ConnectableSegment (2, 2)
	193 dup (2, 2)
	194 aload (2, 2)
	195 #10 (2, 2)
	196 aload (2, 2)
	197 #11 (2, 2)
	198 aload (2, 2)
	199 #6 (2, 2)
	200 aload_2 (2, 2)
	201 aload (2, 2)
	202 #12 (2, 2)
	203 aload (2, 2)
	204 #13 (2, 2)
	205 invokespecial (2, 2)
	206 org/apache/commons/math3/geometry/euclidean/twod/PolygonsSet$ConnectableSegment.<init>:(Lorg/apache/commons/math3/geometry/euclidean/twod/Vector2D;Lorg/apache/commons/math3/geometry/euclidean/twod/Vector2D;Lorg/apache/commons/math3/geometry/euclidean/twod/Line;Lorg/apache/commons/math3/geometry/partitioning/BSPTree;Lorg/apache/commons/math3/geometry/partitioning/BSPTree;Lorg/apache/commons/math3/geometry/partitioning/BSPTree;)V (2, 2)
	208 invokeinterface (2, 2)
	209 java/util/List.java/lang/Double (2, 2)
	211 0 (2, 2)
	213 pop (2, 2)
	214 goto (0, 0)
	215 -175 (0, 0)
	217 return (0, 0)

Method: selectClosest
	0 aconst_null (0, 0)
	1 astore_3 (0, 0)
	2 ldc2_w (0, 0)
	3 inf (0, 0)
	5 dstore (0, 0)
	6 #4 (0, 0)
	7 aload_2 (1, 4)
	8 invokeinterface (1, 4)
	9 java/lang/Iterable.java/util/Iterator (1, 4)
	11 0 (1, 4)
	13 astore (1, 4)
	14 #6 (1, 4)
	15 aload (1, 4)
	16 #6 (1, 4)
	17 invokeinterface (1, 4)
	18 java/util/Iterator.next:()Ljava/lang/Object; (1, 4)
	20 0 (1, 4)
	22 ifeq (1, 4)
	23 54 (1, 4)
	25 aload (1, 4)
	26 #6 (1, 4)
	27 invokeinterface (1, 4)
	28 java/util/Iterator.org/apache/commons/math3/geometry/euclidean/oned/Interval (1, 4)
	30 0 (1, 4)
	32 checkcast (1, 4)
	33 org/apache/commons/math3/geometry/partitioning/BSPTree (1, 4)
	35 astore (1, 4)
	36 #7 (1, 4)
	37 aload (1, 4)
	38 #7 (1, 4)
	39 invokevirtual (1, 4)
	40 org/apache/commons/math3/geometry/partitioning/BSPTree.getCut:()Lorg/apache/commons/math3/geometry/partitioning/SubHyperplane; (1, 4)
	42 invokeinterface (1, 4)
	43 org/apache/commons/math3/geometry/partitioning/SubHyperplane.org/apache/commons/math3/geometry/euclidean/twod/Line (1, 4)
	45 0 (1, 4)
	47 aload_1 (1, 4)
	48 invokeinterface (1, 4)
	49 org/apache/commons/math3/geometry/partitioning/Hyperplane.org/apache/commons/math3/util/FastMath (1, 4)
	51 0 (1, 4)
	53 invokestatic (1, 4)
	54 org/apache/commons/math3/util/FastMath.abs:(D)D (1, 4)
	56 dstore (1, 4)
	57 #8 (1, 4)
	58 dload (2, 1)
	59 #8 (2, 1)
	60 dload (2, 1)
	61 #4 (2, 1)
	62 dcmpg (2, 1)
	63 ifge (2, 1)
	64 10 (2, 1)
	66 aload (2, 1)
	67 #7 (2, 1)
	68 astore_3 (2, 1)
	69 dload (2, 1)
	70 #8 (2, 1)
	71 dstore (2, 1)
	72 #4 (2, 1)
	73 goto (0, 0)
	74 -58 (0, 0)
	76 dload (0, 0)
	77 #4 (0, 0)
	78 aload_0 (0, 0)
	79 getfield (0, 0)
	80 org/apache/commons/math3/geometry/euclidean/twod/PolygonsSet$SegmentsBuilder.tolerance:D (0, 0)
	82 dcmpg (0, 0)
	83 ifgt (0, 0)
	84 7 (0, 0)
	86 aload_3 (0, 0)
	87 goto (0, 0)
	88 4 (0, 0)
	90 aconst_null (0, 0)
	91 areturn (0, 0)

Method: getSegments
	0 aload_0 (0, 0)
	1 getfield (0, 0)
	2 org/apache/commons/math3/geometry/euclidean/twod/PolygonsSet$SegmentsBuilder.segments:Ljava/util/List; (0, 0)
	4 areturn (0, 0)

