Method: <init>
	0 aload_0 (0, 0)
	1 dload_1 (0, 0)
	2 dload_3 (0, 0)
	3 dload (0, 0)
	4 #5 (0, 0)
	5 dload (0, 0)
	6 #7 (0, 0)
	7 ldc2_w (0, 0)
	8 1e-10 (0, 0)
	10 invokespecial (0, 0)
	11 org/apache/commons/math3/geometry/euclidean/twod/PolygonsSet.<init>:(DDDDD)V (0, 0)
	13 return (0, 0)

Method: boxBoundary
	0 dload_0 (1, 1)
	1 dload_2 (1, 1)
	2 dload (1, 1)
	3 #8 (1, 1)
	4 dsub (1, 1)
	5 dcmpl (1, 1)
	6 ifge (1, 1)
	7 14 (1, 1)
	9 dload (1, 1)
	10 #4 (1, 1)
	11 dload (1, 1)
	12 #6 (1, 1)
	13 dload (1, 1)
	14 #8 (1, 1)
	15 dsub (1, 1)
	16 dcmpl (1, 1)
	17 iflt (1, 1)
	18 5 (1, 1)
	20 aconst_null (1, 1)
	21 areturn (1, 1)
	22 new (0, 0)
	23 org/apache/commons/math3/geometry/euclidean/twod/Vector2D (0, 0)
	25 dup (0, 0)
	26 dload_0 (0, 0)
	27 dload (0, 0)
	28 #4 (0, 0)
	29 invokespecial (0, 0)
	30 org/apache/commons/math3/geometry/euclidean/twod/Vector2D.<init>:(DD)V (0, 0)
	32 astore (0, 0)
	33 #10 (0, 0)
	34 new (0, 0)
	35 org/apache/commons/math3/geometry/euclidean/twod/Vector2D (0, 0)
	37 dup (0, 0)
	38 dload_0 (0, 0)
	39 dload (0, 0)
	40 #6 (0, 0)
	41 invokespecial (0, 0)
	42 org/apache/commons/math3/geometry/euclidean/twod/Vector2D.<init>:(DD)V (0, 0)
	44 astore (0, 0)
	45 #11 (0, 0)
	46 new (0, 0)
	47 org/apache/commons/math3/geometry/euclidean/twod/Vector2D (0, 0)
	49 dup (0, 0)
	50 dload_2 (0, 0)
	51 dload (0, 0)
	52 #4 (0, 0)
	53 invokespecial (0, 0)
	54 org/apache/commons/math3/geometry/euclidean/twod/Vector2D.<init>:(DD)V (0, 0)
	56 astore (0, 0)
	57 #12 (0, 0)
	58 new (0, 0)
	59 org/apache/commons/math3/geometry/euclidean/twod/Vector2D (0, 0)
	61 dup (0, 0)
	62 dload_2 (0, 0)
	63 dload (0, 0)
	64 #6 (0, 0)
	65 invokespecial (0, 0)
	66 org/apache/commons/math3/geometry/euclidean/twod/Vector2D.<init>:(DD)V (0, 0)
	68 astore (0, 0)
	69 #13 (0, 0)
	70 iconst_4 (0, 0)
	71 anewarray (0, 0)
	72 org/apache/commons/math3/geometry/euclidean/twod/Line (0, 0)
	74 dup (0, 0)
	75 iconst_0 (0, 0)
	76 new (0, 0)
	77 org/apache/commons/math3/geometry/euclidean/twod/Line (0, 0)
	79 dup (0, 0)
	80 aload (0, 0)
	81 #10 (0, 0)
	82 aload (0, 0)
	83 #12 (0, 0)
	84 dload (0, 0)
	85 #8 (0, 0)
	86 invokespecial (0, 0)
	87 org/apache/commons/math3/geometry/euclidean/twod/Line.<init>:(Lorg/apache/commons/math3/geometry/euclidean/twod/Vector2D;Lorg/apache/commons/math3/geometry/euclidean/twod/Vector2D;D)V (0, 0)
	89 aastore (0, 0)
	90 dup (0, 0)
	91 iconst_1 (0, 0)
	92 new (0, 0)
	93 org/apache/commons/math3/geometry/euclidean/twod/Line (0, 0)
	95 dup (0, 0)
	96 aload (0, 0)
	97 #12 (0, 0)
	98 aload (0, 0)
	99 #13 (0, 0)
	100 dload (0, 0)
	101 #8 (0, 0)
	102 invokespecial (0, 0)
	103 org/apache/commons/math3/geometry/euclidean/twod/Line.<init>:(Lorg/apache/commons/math3/geometry/euclidean/twod/Vector2D;Lorg/apache/commons/math3/geometry/euclidean/twod/Vector2D;D)V (0, 0)
	105 aastore (0, 0)
	106 dup (0, 0)
	107 iconst_2 (0, 0)
	108 new (0, 0)
	109 org/apache/commons/math3/geometry/euclidean/twod/Line (0, 0)
	111 dup (0, 0)
	112 aload (0, 0)
	113 #13 (0, 0)
	114 aload (0, 0)
	115 #11 (0, 0)
	116 dload (0, 0)
	117 #8 (0, 0)
	118 invokespecial (0, 0)
	119 org/apache/commons/math3/geometry/euclidean/twod/Line.<init>:(Lorg/apache/commons/math3/geometry/euclidean/twod/Vector2D;Lorg/apache/commons/math3/geometry/euclidean/twod/Vector2D;D)V (0, 0)
	121 aastore (0, 0)
	122 dup (0, 0)
	123 iconst_3 (0, 0)
	124 new (0, 0)
	125 org/apache/commons/math3/geometry/euclidean/twod/Line (0, 0)
	127 dup (0, 0)
	128 aload (0, 0)
	129 #11 (0, 0)
	130 aload (0, 0)
	131 #10 (0, 0)
	132 dload (0, 0)
	133 #8 (0, 0)
	134 invokespecial (0, 0)
	135 org/apache/commons/math3/geometry/euclidean/twod/Line.<init>:(Lorg/apache/commons/math3/geometry/euclidean/twod/Vector2D;Lorg/apache/commons/math3/geometry/euclidean/twod/Vector2D;D)V (0, 0)
	137 aastore (0, 0)
	138 areturn (0, 0)

Method: verticesToTree
	0 aload_2 (0, 0)
	1 arraylength (0, 0)
	2 istore_3 (0, 0)
	3 iload_3 (1, 1)
	4 ifne (1, 1)
	5 14 (1, 1)
	7 new (1, 1)
	8 org/apache/commons/math3/geometry/partitioning/BSPTree (1, 1)
	10 dup (1, 1)
	11 getstatic (1, 1)
	12 java/lang/Boolean.TRUE:Ljava/lang/Boolean; (1, 1)
	14 invokespecial (1, 1)
	15 org/apache/commons/math3/geometry/partitioning/BSPTree.<init>:(Ljava/lang/Object;)V (1, 1)
	17 areturn (1, 1)
	18 iload_3 (0, 0)
	19 anewarray (0, 0)
	20 org/apache/commons/math3/geometry/euclidean/twod/PolygonsSet$Vertex (0, 0)
	22 astore (0, 0)
	23 #4 (0, 0)
	24 iconst_0 (1, 4)
	25 istore (1, 4)
	26 #5 (1, 4)
	27 iload (1, 4)
	28 #5 (1, 4)
	29 iload_3 (1, 4)
	30 if_icmpge (1, 4)
	31 25 (1, 4)
	33 aload (1, 4)
	34 #4 (1, 4)
	35 iload (1, 4)
	36 #5 (1, 4)
	37 new (1, 4)
	38 org/apache/commons/math3/geometry/euclidean/twod/PolygonsSet$Vertex (1, 4)
	40 dup (1, 4)
	41 aload_2 (1, 4)
	42 iload (1, 4)
	43 #5 (1, 4)
	44 aaload (1, 4)
	45 invokespecial (1, 4)
	46 org/apache/commons/math3/geometry/euclidean/twod/PolygonsSet$Vertex.<init>:(Lorg/apache/commons/math3/geometry/euclidean/twod/Vector2D;)V (1, 4)
	48 aastore (1, 4)
	49 iinc (1, 4)
	50 #5 (1, 4)
	51 -89 (1, 4)
	52 goto (1, 4)
	53 -25 (1, 4)
	55 new (0, 0)
	56 java/util/ArrayList (0, 0)
	58 dup (0, 0)
	59 iload_3 (0, 0)
	60 invokespecial (0, 0)
	61 java/util/ArrayList.<init>:(I)V (0, 0)
	63 astore (0, 0)
	64 #5 (0, 0)
	65 iconst_0 (1, 4)
	66 istore (1, 4)
	67 #6 (1, 4)
	68 iload (1, 4)
	69 #6 (1, 4)
	70 iload_3 (1, 4)
	71 if_icmpge (1, 4)
	72 153 (1, 4)
	74 aload (1, 4)
	75 #4 (1, 4)
	76 iload (1, 4)
	77 #6 (1, 4)
	78 aaload (1, 4)
	79 astore (1, 4)
	80 #7 (1, 4)
	81 aload (1, 4)
	82 #4 (1, 4)
	83 iload (1, 4)
	84 #6 (1, 4)
	85 iconst_1 (1, 4)
	86 iadd (1, 4)
	87 iload_3 (1, 4)
	88 irem (1, 4)
	89 aaload (1, 4)
	90 astore (1, 4)
	91 #8 (1, 4)
	92 aload (1, 1)
	93 #7 (1, 1)
	94 aload (1, 1)
	95 #8 (1, 1)
	96 invokevirtual (1, 1)
	97 org/apache/commons/math3/geometry/euclidean/twod/PolygonsSet$Vertex.sharedLineWith:(Lorg/apache/commons/math3/geometry/euclidean/twod/PolygonsSet$Vertex;)Lorg/apache/commons/math3/geometry/euclidean/twod/Line; (1, 1)
	99 astore (1, 1)
	100 #9 (1, 1)
	101 aload (2, 1)
	102 #9 (2, 1)
	103 ifnonnull (2, 1)
	104 23 (2, 1)
	106 new (2, 1)
	107 org/apache/commons/math3/geometry/euclidean/twod/Line (2, 1)
	109 dup (2, 1)
	110 aload (2, 1)
	111 #7 (2, 1)
	112 invokevirtual (2, 1)
	113 org/apache/commons/math3/geometry/euclidean/twod/PolygonsSet$Vertex.getLocation:()Lorg/apache/commons/math3/geometry/euclidean/twod/Vector2D; (2, 1)
	115 aload (2, 1)
	116 #8 (2, 1)
	117 invokevirtual (2, 1)
	118 org/apache/commons/math3/geometry/euclidean/twod/PolygonsSet$Vertex.getLocation:()Lorg/apache/commons/math3/geometry/euclidean/twod/Vector2D; (2, 1)
	120 dload_0 (2, 1)
	121 invokespecial (2, 1)
	122 org/apache/commons/math3/geometry/euclidean/twod/Line.<init>:(Lorg/apache/commons/math3/geometry/euclidean/twod/Vector2D;Lorg/apache/commons/math3/geometry/euclidean/twod/Vector2D;D)V (2, 1)
	124 astore (2, 1)
	125 #9 (2, 1)
	126 aload (1, 1)
	127 #5 (1, 1)
	128 new (1, 1)
	129 org/apache/commons/math3/geometry/euclidean/twod/PolygonsSet$Edge (1, 1)
	131 dup (1, 1)
	132 aload (1, 1)
	133 #7 (1, 1)
	134 aload (1, 1)
	135 #8 (1, 1)
	136 aload (1, 1)
	137 #9 (1, 1)
	138 invokespecial (1, 1)
	139 org/apache/commons/math3/geometry/euclidean/twod/PolygonsSet$Edge.<init>:(Lorg/apache/commons/math3/geometry/euclidean/twod/PolygonsSet$Vertex;Lorg/apache/commons/math3/geometry/euclidean/twod/PolygonsSet$Vertex;Lorg/apache/commons/math3/geometry/euclidean/twod/Line;)V (1, 1)
	141 invokeinterface (1, 1)
	142 java/util/List.getOffset:(Lorg/apache/commons/math3/geometry/Point;)D (1, 1)
	144 0 (1, 1)
	146 pop (1, 1)
	147 aload (2, 4)
	148 #4 (2, 4)
	149 astore (2, 4)
	150 #10 (2, 4)
	151 aload (2, 4)
	152 #10 (2, 4)
	153 arraylength (2, 4)
	154 istore (2, 4)
	155 #11 (2, 4)
	156 iconst_0 (2, 4)
	157 istore (2, 4)
	158 #12 (2, 4)
	159 iload (2, 4)
	160 #12 (2, 4)
	161 iload (2, 4)
	162 #11 (2, 4)
	163 if_icmpge (2, 4)
	164 55 (2, 4)
	166 aload (2, 4)
	167 #10 (2, 4)
	168 iload (2, 4)
	169 #12 (2, 4)
	170 aaload (2, 4)
	171 astore (2, 4)
	172 #13 (2, 4)
	173 aload (2, 1)
	174 #13 (2, 1)
	175 aload (2, 1)
	176 #7 (2, 1)
	177 if_acmpeq (2, 1)
	178 35 (2, 1)
	180 aload (2, 1)
	181 #13 (2, 1)
	182 aload (2, 1)
	183 #8 (2, 1)
	184 if_acmpeq (2, 1)
	185 28 (2, 1)
	187 aload (2, 1)
	188 #9 (2, 1)
	189 aload (2, 1)
	190 #13 (2, 1)
	191 invokevirtual (2, 1)
	192 org/apache/commons/math3/geometry/euclidean/twod/PolygonsSet$Vertex.getLocation:()Lorg/apache/commons/math3/geometry/euclidean/twod/Vector2D; (2, 1)
	194 invokevirtual (2, 1)
	195 org/apache/commons/math3/geometry/euclidean/twod/Line.getOffset:(Lorg/apache/commons/math3/geometry/Point;)D (2, 1)
	197 invokestatic (2, 1)
	198 org/apache/commons/math3/util/FastMath.abs:(D)D (2, 1)
	200 dload_0 (2, 1)
	201 dcmpg (2, 1)
	202 ifgt (2, 1)
	203 10 (2, 1)
	205 aload (2, 1)
	206 #13 (2, 1)
	207 aload (2, 1)
	208 #9 (2, 1)
	209 invokevirtual (2, 1)
	210 org/apache/commons/math3/geometry/euclidean/twod/PolygonsSet$Vertex.bindWith:(Lorg/apache/commons/math3/geometry/euclidean/twod/Line;)V (2, 1)
	212 iinc (2, 1)
	213 #12 (2, 1)
	214 -89 (2, 1)
	215 goto (2, 1)
	216 -56 (2, 1)
	218 iinc (2, 1)
	219 #6 (2, 1)
	220 -89 (2, 1)
	221 goto (2, 1)
	222 -153 (2, 1)
	224 new (2, 1)
	225 org/apache/commons/math3/geometry/partitioning/BSPTree (2, 1)
	227 dup (2, 1)
	228 invokespecial (2, 1)
	229 org/apache/commons/math3/geometry/partitioning/BSPTree.<init>:()V (2, 1)
	231 astore (2, 1)
	232 #6 (2, 1)
	233 dload_0 (2, 1)
	234 aload (2, 1)
	235 #6 (2, 1)
	236 aload (2, 1)
	237 #5 (2, 1)
	238 invokestatic (2, 1)
	239 org/apache/commons/math3/geometry/euclidean/twod/PolygonsSet.insertEdges:(DLorg/apache/commons/math3/geometry/partitioning/BSPTree;Ljava/util/List;)V (2, 1)
	241 aload (2, 1)
	242 #6 (2, 1)
	243 areturn (2, 1)

Method: insertEdges
	0 iconst_0 (0, 0)
	1 istore (0, 0)
	2 #4 (0, 0)
	3 aconst_null (0, 0)
	4 astore (0, 0)
	5 #5 (0, 0)
	6 aload (1, 3)
	7 #5 (1, 3)
	8 ifnonnull (1, 3)
	9 71 (1, 3)
	11 iload (1, 3)
	12 #4 (1, 3)
	13 aload_3 (1, 3)
	14 invokeinterface (1, 3)
	15 java/util/List.get:(I)Ljava/lang/Object; (1, 3)
	17 0 (1, 3)
	19 if_icmpge (1, 3)
	20 60 (1, 3)
	22 aload_3 (1, 3)
	23 iload (1, 3)
	24 #4 (1, 3)
	25 iinc (1, 3)
	26 #4 (1, 3)
	27 -71 (1, 3)
	28 invokeinterface (1, 3)
	29 java/util/List.getNode:()Lorg/apache/commons/math3/geometry/partitioning/BSPTree; (1, 3)
	31 0 (1, 3)
	33 checkcast (1, 3)
	34 org/apache/commons/math3/geometry/euclidean/twod/PolygonsSet$Edge (1, 3)
	36 astore (1, 3)
	37 #5 (1, 3)
	38 aload (2, 1)
	39 #5 (2, 1)
	40 invokevirtual (2, 1)
	41 org/apache/commons/math3/geometry/euclidean/twod/PolygonsSet$Edge.getNode:()Lorg/apache/commons/math3/geometry/partitioning/BSPTree; (2, 1)
	43 ifnonnull (2, 1)
	44 30 (2, 1)
	46 aload_2 (3, 1)
	47 aload (3, 1)
	48 #5 (3, 1)
	49 invokevirtual (3, 1)
	50 org/apache/commons/math3/geometry/euclidean/twod/PolygonsSet$Edge.getLine:()Lorg/apache/commons/math3/geometry/euclidean/twod/Line; (3, 1)
	52 invokevirtual (3, 1)
	53 org/apache/commons/math3/geometry/partitioning/BSPTree.insertCut:(Lorg/apache/commons/math3/geometry/partitioning/Hyperplane;)Z (3, 1)
	55 ifeq (3, 1)
	56 12 (3, 1)
	58 aload (3, 1)
	59 #5 (3, 1)
	60 aload_2 (3, 1)
	61 invokevirtual (3, 1)
	62 org/apache/commons/math3/geometry/euclidean/twod/PolygonsSet$Edge.setNode:(Lorg/apache/commons/math3/geometry/partitioning/BSPTree;)V (3, 1)
	64 goto (3, 1)
	65 -58 (3, 1)
	67 aconst_null (3, 2)
	68 astore (3, 2)
	69 #5 (3, 2)
	70 goto (3, 2)
	71 -64 (3, 2)
	73 aconst_null (2, 2)
	74 astore (2, 2)
	75 #5 (2, 2)
	76 goto (2, 2)
	77 -70 (2, 2)
	79 aload (1, 1)
	80 #5 (1, 1)
	81 ifnonnull (1, 1)
	82 41 (1, 1)
	84 aload_2 (1, 1)
	85 invokevirtual (1, 1)
	86 org/apache/commons/math3/geometry/partitioning/BSPTree.getParent:()Lorg/apache/commons/math3/geometry/partitioning/BSPTree; (1, 1)
	88 astore (1, 1)
	89 #6 (1, 1)
	90 aload (2, 1)
	91 #6 (2, 1)
	92 ifnull (2, 1)
	93 12 (2, 1)
	95 aload_2 (2, 1)
	96 aload (2, 1)
	97 #6 (2, 1)
	98 invokevirtual (2, 1)
	99 org/apache/commons/math3/geometry/partitioning/BSPTree.getMinus:()Lorg/apache/commons/math3/geometry/partitioning/BSPTree; (2, 1)
	101 if_acmpne (2, 1)
	102 13 (2, 1)
	104 aload_2 (2, 1)
	105 getstatic (2, 1)
	106 java/lang/Boolean.TRUE:Ljava/lang/Boolean; (2, 1)
	108 invokevirtual (2, 1)
	109 org/apache/commons/math3/geometry/partitioning/BSPTree.setAttribute:(Ljava/lang/Object;)V (2, 1)
	111 goto (2, 1)
	112 10 (2, 1)
	114 aload_2 (2, 2)
	115 getstatic (2, 2)
	116 java/lang/Boolean.FALSE:Ljava/lang/Boolean; (2, 2)
	118 invokevirtual (2, 2)
	119 org/apache/commons/math3/geometry/partitioning/BSPTree.setAttribute:(Ljava/lang/Object;)V (2, 2)
	121 return (1, 1)
	122 new (0, 0)
	123 java/util/ArrayList (0, 0)
	125 dup (0, 0)
	126 invokespecial (0, 0)
	127 java/util/ArrayList.<init>:()V (0, 0)
	129 astore (0, 0)
	130 #6 (0, 0)
	131 new (0, 0)
	132 java/util/ArrayList (0, 0)
	134 dup (0, 0)
	135 invokespecial (0, 0)
	136 java/util/ArrayList.<init>:()V (0, 0)
	138 astore (0, 0)
	139 #7 (0, 0)
	140 aload_3 (1, 4)
	141 invokeinterface (1, 4)
	142 java/util/List.java/util/Iterator (1, 4)
	144 0 (1, 4)
	146 astore (1, 4)
	147 #8 (1, 4)
	148 aload (1, 4)
	149 #8 (1, 4)
	150 invokeinterface (1, 4)
	151 java/util/Iterator.next:()Ljava/lang/Object; (1, 4)
	153 0 (1, 4)
	155 ifeq (1, 4)
	156 327 (1, 4)
	158 aload (1, 4)
	159 #8 (1, 4)
	160 invokeinterface (1, 4)
	161 java/util/Iterator.getStart:()Lorg/apache/commons/math3/geometry/euclidean/twod/PolygonsSet$Vertex; (1, 4)
	163 0 (1, 4)
	165 checkcast (1, 4)
	166 org/apache/commons/math3/geometry/euclidean/twod/PolygonsSet$Edge (1, 4)
	168 astore (1, 4)
	169 #9 (1, 4)
	170 aload (2, 1)
	171 #9 (2, 1)
	172 aload (2, 1)
	173 #5 (2, 1)
	174 if_acmpeq (2, 1)
	175 305 (2, 1)
	177 aload (2, 1)
	178 #5 (2, 1)
	179 invokevirtual (2, 1)
	180 org/apache/commons/math3/geometry/euclidean/twod/PolygonsSet$Edge.getLine:()Lorg/apache/commons/math3/geometry/euclidean/twod/Line; (2, 1)
	182 aload (2, 1)
	183 #9 (2, 1)
	184 invokevirtual (2, 1)
	185 org/apache/commons/math3/geometry/euclidean/twod/PolygonsSet$Edge.getStart:()Lorg/apache/commons/math3/geometry/euclidean/twod/PolygonsSet$Vertex; (2, 1)
	187 invokevirtual (2, 1)
	188 org/apache/commons/math3/geometry/euclidean/twod/PolygonsSet$Vertex.getLocation:()Lorg/apache/commons/math3/geometry/euclidean/twod/Vector2D; (2, 1)
	190 invokevirtual (2, 1)
	191 org/apache/commons/math3/geometry/euclidean/twod/Line.getOffset:(Lorg/apache/commons/math3/geometry/Point;)D (2, 1)
	193 dstore (2, 1)
	194 #10 (2, 1)
	195 aload (2, 1)
	196 #5 (2, 1)
	197 invokevirtual (2, 1)
	198 org/apache/commons/math3/geometry/euclidean/twod/PolygonsSet$Edge.getLine:()Lorg/apache/commons/math3/geometry/euclidean/twod/Line; (2, 1)
	200 aload (2, 1)
	201 #9 (2, 1)
	202 invokevirtual (2, 1)
	203 org/apache/commons/math3/geometry/euclidean/twod/PolygonsSet$Edge.getEnd:()Lorg/apache/commons/math3/geometry/euclidean/twod/PolygonsSet$Vertex; (2, 1)
	205 invokevirtual (2, 1)
	206 org/apache/commons/math3/geometry/euclidean/twod/PolygonsSet$Vertex.getLocation:()Lorg/apache/commons/math3/geometry/euclidean/twod/Vector2D; (2, 1)
	208 invokevirtual (2, 1)
	209 org/apache/commons/math3/geometry/euclidean/twod/Line.getOffset:(Lorg/apache/commons/math3/geometry/Point;)D (2, 1)
	211 dstore (2, 1)
	212 #12 (2, 1)
	213 dload (2, 1)
	214 #10 (2, 1)
	215 invokestatic (2, 1)
	216 org/apache/commons/math3/util/FastMath.abs:(D)D (2, 1)
	218 dload_0 (2, 1)
	219 dcmpg (2, 1)
	220 ifgt (2, 1)
	221 9 (2, 1)
	223 getstatic (2, 1)
	224 org/apache/commons/math3/geometry/partitioning/Side.HYPER:Lorg/apache/commons/math3/geometry/partitioning/Side; (2, 1)
	226 goto (2, 1)
	227 19 (2, 1)
	229 dload (2, 1)
	230 #10 (2, 1)
	231 dconst_0 (2, 1)
	232 dcmpg (2, 1)
	233 ifge (2, 1)
	234 9 (2, 1)
	236 getstatic (2, 1)
	237 org/apache/commons/math3/geometry/partitioning/Side.MINUS:Lorg/apache/commons/math3/geometry/partitioning/Side; (2, 1)
	239 goto (2, 1)
	240 6 (2, 1)
	242 getstatic (2, 1)
	243 org/apache/commons/math3/geometry/partitioning/Side.PLUS:Lorg/apache/commons/math3/geometry/partitioning/Side; (2, 1)
	245 astore (2, 1)
	246 #14 (2, 1)
	247 dload (2, 1)
	248 #12 (2, 1)
	249 invokestatic (2, 1)
	250 org/apache/commons/math3/util/FastMath.abs:(D)D (2, 1)
	252 dload_0 (2, 1)
	253 dcmpg (2, 1)
	254 ifgt (2, 1)
	255 9 (2, 1)
	257 getstatic (2, 1)
	258 org/apache/commons/math3/geometry/partitioning/Side.HYPER:Lorg/apache/commons/math3/geometry/partitioning/Side; (2, 1)
	260 goto (2, 1)
	261 19 (2, 1)
	263 dload (2, 1)
	264 #12 (2, 1)
	265 dconst_0 (2, 1)
	266 dcmpg (2, 1)
	267 ifge (2, 1)
	268 9 (2, 1)
	270 getstatic (2, 1)
	271 org/apache/commons/math3/geometry/partitioning/Side.MINUS:Lorg/apache/commons/math3/geometry/partitioning/Side; (2, 1)
	273 goto (2, 1)
	274 6 (2, 1)
	276 getstatic (2, 1)
	277 org/apache/commons/math3/geometry/partitioning/Side.PLUS:Lorg/apache/commons/math3/geometry/partitioning/Side; (2, 1)
	279 astore (2, 1)
	280 #15 (2, 1)
	281 getstatic (3, 5)
	282 org/apache/commons/math3/geometry/euclidean/twod/PolygonsSet$1.$SwitchMap$org$apache$commons$math3$geometry$partitioning$Side:[I (3, 5)
	284 aload (3, 5)
	285 #14 (3, 5)
	286 invokevirtual (3, 5)
	287 org/apache/commons/math3/geometry/partitioning/Side.ordinal:()I (3, 5)
	289 iaload (3, 5)
	290 lookupswitch (3, 5)
	291 1: 316 (3, 5)
	295 2: 378 (3, 5)
	316 aload (4, 1)
	317 #15 (4, 1)
	318 getstatic (4, 1)
	319 org/apache/commons/math3/geometry/partitioning/Side.MINUS:Lorg/apache/commons/math3/geometry/partitioning/Side; (4, 1)
	321 if_acmpne (4, 1)
	322 44 (4, 1)
	324 aload (4, 1)
	325 #9 (4, 1)
	326 aload (4, 1)
	327 #5 (4, 1)
	328 invokevirtual (4, 1)
	329 org/apache/commons/math3/geometry/euclidean/twod/PolygonsSet$Edge.getLine:()Lorg/apache/commons/math3/geometry/euclidean/twod/Line; (4, 1)
	331 invokevirtual (4, 1)
	332 org/apache/commons/math3/geometry/euclidean/twod/PolygonsSet$Edge.split:(Lorg/apache/commons/math3/geometry/euclidean/twod/Line;)Lorg/apache/commons/math3/geometry/euclidean/twod/PolygonsSet$Vertex; (4, 1)
	334 astore (4, 1)
	335 #16 (4, 1)
	336 aload (4, 1)
	337 #7 (4, 1)
	338 aload (4, 1)
	339 #16 (4, 1)
	340 invokevirtual (4, 1)
	341 org/apache/commons/math3/geometry/euclidean/twod/PolygonsSet$Vertex.getOutgoing:()Lorg/apache/commons/math3/geometry/euclidean/twod/PolygonsSet$Edge; (4, 1)
	343 invokeinterface (4, 1)
	344 java/util/List.getOffset:(Lorg/apache/commons/math3/geometry/Point;)D (4, 1)
	346 0 (4, 1)
	348 pop (4, 1)
	349 aload (4, 1)
	350 #6 (4, 1)
	351 aload (4, 1)
	352 #16 (4, 1)
	353 invokevirtual (4, 1)
	354 org/apache/commons/math3/geometry/euclidean/twod/PolygonsSet$Vertex.getIncoming:()Lorg/apache/commons/math3/geometry/euclidean/twod/PolygonsSet$Edge; (4, 1)
	356 invokeinterface (4, 1)
	357 java/util/List.getOffset:(Lorg/apache/commons/math3/geometry/Point;)D (4, 1)
	359 0 (4, 1)
	361 pop (4, 1)
	362 goto (4, 2)
	363 117 (4, 2)
	365 aload (4, 2)
	366 #6 (4, 2)
	367 aload (4, 2)
	368 #9 (4, 2)
	369 invokeinterface (4, 2)
	370 java/util/List.getOffset:(Lorg/apache/commons/math3/geometry/Point;)D (4, 2)
	372 0 (4, 2)
	374 pop (4, 2)
	375 goto (3, 5)
	376 104 (3, 5)
	378 aload (4, 1)
	379 #15 (4, 1)
	380 getstatic (4, 1)
	381 org/apache/commons/math3/geometry/partitioning/Side.PLUS:Lorg/apache/commons/math3/geometry/partitioning/Side; (4, 1)
	383 if_acmpne (4, 1)
	384 44 (4, 1)
	386 aload (4, 1)
	387 #9 (4, 1)
	388 aload (4, 1)
	389 #5 (4, 1)
	390 invokevirtual (4, 1)
	391 org/apache/commons/math3/geometry/euclidean/twod/PolygonsSet$Edge.getLine:()Lorg/apache/commons/math3/geometry/euclidean/twod/Line; (4, 1)
	393 invokevirtual (4, 1)
	394 org/apache/commons/math3/geometry/euclidean/twod/PolygonsSet$Edge.split:(Lorg/apache/commons/math3/geometry/euclidean/twod/Line;)Lorg/apache/commons/math3/geometry/euclidean/twod/PolygonsSet$Vertex; (4, 1)
	396 astore (4, 1)
	397 #16 (4, 1)
	398 aload (4, 1)
	399 #7 (4, 1)
	400 aload (4, 1)
	401 #16 (4, 1)
	402 invokevirtual (4, 1)
	403 org/apache/commons/math3/geometry/euclidean/twod/PolygonsSet$Vertex.getIncoming:()Lorg/apache/commons/math3/geometry/euclidean/twod/PolygonsSet$Edge; (4, 1)
	405 invokeinterface (4, 1)
	406 java/util/List.getOffset:(Lorg/apache/commons/math3/geometry/Point;)D (4, 1)
	408 0 (4, 1)
	410 pop (4, 1)
	411 aload (4, 1)
	412 #6 (4, 1)
	413 aload (4, 1)
	414 #16 (4, 1)
	415 invokevirtual (4, 1)
	416 org/apache/commons/math3/geometry/euclidean/twod/PolygonsSet$Vertex.getOutgoing:()Lorg/apache/commons/math3/geometry/euclidean/twod/PolygonsSet$Edge; (4, 1)
	418 invokeinterface (4, 1)
	419 java/util/List.getOffset:(Lorg/apache/commons/math3/geometry/Point;)D (4, 1)
	421 0 (4, 1)
	423 pop (4, 1)
	424 goto (4, 2)
	425 55 (4, 2)
	427 aload (4, 2)
	428 #7 (4, 2)
	429 aload (4, 2)
	430 #9 (4, 2)
	431 invokeinterface (4, 2)
	432 java/util/List.getOffset:(Lorg/apache/commons/math3/geometry/Point;)D (4, 2)
	434 0 (4, 2)
	436 pop (4, 2)
	437 goto (3, 5)
	438 42 (3, 5)
	440 aload (4, 1)
	441 #15 (4, 1)
	442 getstatic (4, 1)
	443 org/apache/commons/math3/geometry/partitioning/Side.PLUS:Lorg/apache/commons/math3/geometry/partitioning/Side; (4, 1)
	445 if_acmpne (4, 1)
	446 16 (4, 1)
	448 aload (4, 1)
	449 #6 (4, 1)
	450 aload (4, 1)
	451 #9 (4, 1)
	452 invokeinterface (4, 1)
	453 java/util/List.getOffset:(Lorg/apache/commons/math3/geometry/Point;)D (4, 1)
	455 0 (4, 1)
	457 pop (4, 1)
	458 goto (4, 1)
	459 21 (4, 1)
	461 aload (4, 1)
	462 #15 (4, 1)
	463 getstatic (4, 1)
	464 org/apache/commons/math3/geometry/partitioning/Side.MINUS:Lorg/apache/commons/math3/geometry/partitioning/Side; (4, 1)
	466 if_acmpne (4, 1)
	467 13 (4, 1)
	469 aload (4, 1)
	470 #7 (4, 1)
	471 aload (4, 1)
	472 #9 (4, 1)
	473 invokeinterface (4, 1)
	474 java/util/List.getOffset:(Lorg/apache/commons/math3/geometry/Point;)D (4, 1)
	476 0 (4, 1)
	478 pop (4, 1)
	479 goto (0, 0)
	480 -331 (0, 0)
	482 aload (1, 1)
	483 #6 (1, 1)
	484 invokeinterface (1, 1)
	485 java/util/List.getPlus:()Lorg/apache/commons/math3/geometry/partitioning/BSPTree; (1, 1)
	487 0 (1, 1)
	489 ifne (1, 1)
	490 16 (1, 1)
	492 dload_0 (1, 1)
	493 aload_2 (1, 1)
	494 invokevirtual (1, 1)
	495 org/apache/commons/math3/geometry/partitioning/BSPTree.getPlus:()Lorg/apache/commons/math3/geometry/partitioning/BSPTree; (1, 1)
	497 aload (1, 1)
	498 #6 (1, 1)
	499 invokestatic (1, 1)
	500 org/apache/commons/math3/geometry/euclidean/twod/PolygonsSet.insertEdges:(DLorg/apache/commons/math3/geometry/partitioning/BSPTree;Ljava/util/List;)V (1, 1)
	502 goto (1, 1)
	503 13 (1, 1)
	505 aload_2 (1, 2)
	506 invokevirtual (1, 2)
	507 org/apache/commons/math3/geometry/partitioning/BSPTree.getPlus:()Lorg/apache/commons/math3/geometry/partitioning/BSPTree; (1, 2)
	509 getstatic (1, 2)
	510 java/lang/Boolean.FALSE:Ljava/lang/Boolean; (1, 2)
	512 invokevirtual (1, 2)
	513 org/apache/commons/math3/geometry/partitioning/BSPTree.setAttribute:(Ljava/lang/Object;)V (1, 2)
	515 aload (1, 1)
	516 #7 (1, 1)
	517 invokeinterface (1, 1)
	518 java/util/List.getPlus:()Lorg/apache/commons/math3/geometry/partitioning/BSPTree; (1, 1)
	520 0 (1, 1)
	522 ifne (1, 1)
	523 16 (1, 1)
	525 dload_0 (1, 1)
	526 aload_2 (1, 1)
	527 invokevirtual (1, 1)
	528 org/apache/commons/math3/geometry/partitioning/BSPTree.getMinus:()Lorg/apache/commons/math3/geometry/partitioning/BSPTree; (1, 1)
	530 aload (1, 1)
	531 #7 (1, 1)
	532 invokestatic (1, 1)
	533 org/apache/commons/math3/geometry/euclidean/twod/PolygonsSet.insertEdges:(DLorg/apache/commons/math3/geometry/partitioning/BSPTree;Ljava/util/List;)V (1, 1)
	535 goto (1, 1)
	536 13 (1, 1)
	538 aload_2 (1, 2)
	539 invokevirtual (1, 2)
	540 org/apache/commons/math3/geometry/partitioning/BSPTree.getMinus:()Lorg/apache/commons/math3/geometry/partitioning/BSPTree; (1, 2)
	542 getstatic (1, 2)
	543 java/lang/Boolean.TRUE:Ljava/lang/Boolean; (1, 2)
	545 invokevirtual (1, 2)
	546 org/apache/commons/math3/geometry/partitioning/BSPTree.setAttribute:(Ljava/lang/Object;)V (1, 2)
	548 return (0, 0)

Method: buildNew
	0 aload_0 (0, 0)
	1 aload_1 (0, 0)
	2 invokevirtual (0, 0)
	3 org/apache/commons/math3/geometry/euclidean/twod/PolygonsSet.buildNew:(Lorg/apache/commons/math3/geometry/partitioning/BSPTree;)Lorg/apache/commons/math3/geometry/euclidean/twod/PolygonsSet; (0, 0)
	5 areturn (0, 0)

Method: computeGeometricalProperties
	0 aload_0 (0, 0)
	1 invokevirtual (0, 0)
	2 org/apache/commons/math3/geometry/euclidean/twod/PolygonsSet.getVertices:()[[Lorg/apache/commons/math3/geometry/euclidean/twod/Vector2D; (0, 0)
	4 astore_1 (0, 0)
	5 aload_1 (1, 1)
	6 arraylength (1, 1)
	7 ifne (1, 1)
	8 67 (1, 1)
	10 aload_0 (1, 1)
	11 iconst_0 (1, 1)
	12 invokevirtual (1, 1)
	13 org/apache/commons/math3/geometry/euclidean/twod/PolygonsSet.getTree:(Z)Lorg/apache/commons/math3/geometry/partitioning/BSPTree; (1, 1)
	15 astore_2 (1, 1)
	16 aload_2 (2, 1)
	17 invokevirtual (2, 1)
	18 org/apache/commons/math3/geometry/partitioning/BSPTree.getCut:()Lorg/apache/commons/math3/geometry/partitioning/SubHyperplane; (2, 1)
	20 ifnonnull (2, 1)
	21 33 (2, 1)
	23 aload_2 (2, 1)
	24 invokevirtual (2, 1)
	25 org/apache/commons/math3/geometry/partitioning/BSPTree.getAttribute:()Ljava/lang/Object; (2, 1)
	27 checkcast (2, 1)
	28 java/lang/Boolean (2, 1)
	30 invokevirtual (2, 1)
	31 java/lang/Boolean.booleanValue:()Z (2, 1)
	33 ifeq (2, 1)
	34 20 (2, 1)
	36 aload_0 (2, 1)
	37 ldc2_w (2, 1)
	38 inf (2, 1)
	40 invokevirtual (2, 1)
	41 org/apache/commons/math3/geometry/euclidean/twod/PolygonsSet.setSize:(D)V (2, 1)
	43 aload_0 (2, 1)
	44 getstatic (2, 1)
	45 org/apache/commons/math3/geometry/euclidean/twod/Vector2D.NaN:Lorg/apache/commons/math3/geometry/euclidean/twod/Vector2D; (2, 1)
	47 invokevirtual (2, 1)
	48 org/apache/commons/math3/geometry/euclidean/twod/PolygonsSet.setBarycenter:(Lorg/apache/commons/math3/geometry/Point;)V (2, 1)
	50 goto (2, 1)
	51 21 (2, 1)
	53 aload_0 (2, 2)
	54 dconst_0 (2, 2)
	55 invokevirtual (2, 2)
	56 org/apache/commons/math3/geometry/euclidean/twod/PolygonsSet.setSize:(D)V (2, 2)
	58 aload_0 (2, 2)
	59 new (2, 2)
	60 org/apache/commons/math3/geometry/euclidean/twod/Vector2D (2, 2)
	62 dup (2, 2)
	63 dconst_0 (2, 2)
	64 dconst_0 (2, 2)
	65 invokespecial (2, 2)
	66 org/apache/commons/math3/geometry/euclidean/twod/Vector2D.<init>:(DD)V (2, 2)
	68 invokevirtual (2, 2)
	69 org/apache/commons/math3/geometry/euclidean/twod/PolygonsSet.setBarycenter:(Lorg/apache/commons/math3/geometry/Point;)V (2, 2)
	71 goto (1, 1)
	72 250 (1, 1)
	74 aload_1 (1, 1)
	75 iconst_0 (1, 1)
	76 aaload (1, 1)
	77 iconst_0 (1, 1)
	78 aaload (1, 1)
	79 ifnonnull (1, 1)
	80 20 (1, 1)
	82 aload_0 (1, 1)
	83 ldc2_w (1, 1)
	84 inf (1, 1)
	86 invokevirtual (1, 1)
	87 org/apache/commons/math3/geometry/euclidean/twod/PolygonsSet.setSize:(D)V (1, 1)
	89 aload_0 (1, 1)
	90 getstatic (1, 1)
	91 org/apache/commons/math3/geometry/euclidean/twod/Vector2D.NaN:Lorg/apache/commons/math3/geometry/euclidean/twod/Vector2D; (1, 1)
	93 invokevirtual (1, 1)
	94 org/apache/commons/math3/geometry/euclidean/twod/PolygonsSet.setBarycenter:(Lorg/apache/commons/math3/geometry/Point;)V (1, 1)
	96 goto (1, 1)
	97 225 (1, 1)
	99 dconst_0 (1, 2)
	100 dstore_2 (1, 2)
	101 dconst_0 (1, 2)
	102 dstore (1, 2)
	103 #4 (1, 2)
	104 dconst_0 (1, 2)
	105 dstore (1, 2)
	106 #6 (1, 2)
	107 aload_1 (2, 4)
	108 astore (2, 4)
	109 #8 (2, 4)
	110 aload (2, 4)
	111 #8 (2, 4)
	112 arraylength (2, 4)
	113 istore (2, 4)
	114 #9 (2, 4)
	115 iconst_0 (2, 4)
	116 istore (2, 4)
	117 #10 (2, 4)
	118 iload (2, 4)
	119 #10 (2, 4)
	120 iload (2, 4)
	121 #9 (2, 4)
	122 if_icmpge (2, 4)
	123 140 (2, 4)
	125 aload (2, 4)
	126 #8 (2, 4)
	127 iload (2, 4)
	128 #10 (2, 4)
	129 aaload (2, 4)
	130 astore (2, 4)
	131 #11 (2, 4)
	132 aload (2, 4)
	133 #11 (2, 4)
	134 aload (2, 4)
	135 #11 (2, 4)
	136 arraylength (2, 4)
	137 iconst_1 (2, 4)
	138 isub (2, 4)
	139 aaload (2, 4)
	140 invokevirtual (2, 4)
	141 org/apache/commons/math3/geometry/euclidean/twod/Vector2D.getX:()D (2, 4)
	143 dstore (2, 4)
	144 #12 (2, 4)
	145 aload (2, 4)
	146 #11 (2, 4)
	147 aload (2, 4)
	148 #11 (2, 4)
	149 arraylength (2, 4)
	150 iconst_1 (2, 4)
	151 isub (2, 4)
	152 aaload (2, 4)
	153 invokevirtual (2, 4)
	154 org/apache/commons/math3/geometry/euclidean/twod/Vector2D.getY:()D (2, 4)
	156 dstore (2, 4)
	157 #14 (2, 4)
	158 aload (3, 4)
	159 #11 (3, 4)
	160 astore (3, 4)
	161 #16 (3, 4)
	162 aload (3, 4)
	163 #16 (3, 4)
	164 arraylength (3, 4)
	165 istore (3, 4)
	166 #17 (3, 4)
	167 iconst_0 (3, 4)
	168 istore (3, 4)
	169 #18 (3, 4)
	170 iload (3, 4)
	171 #18 (3, 4)
	172 iload (3, 4)
	173 #17 (3, 4)
	174 if_icmpge (3, 4)
	175 82 (3, 4)
	177 aload (3, 4)
	178 #16 (3, 4)
	179 iload (3, 4)
	180 #18 (3, 4)
	181 aaload (3, 4)
	182 astore (3, 4)
	183 #19 (3, 4)
	184 dload (3, 4)
	185 #12 (3, 4)
	186 dstore (3, 4)
	187 #20 (3, 4)
	188 dload (3, 4)
	189 #14 (3, 4)
	190 dstore (3, 4)
	191 #22 (3, 4)
	192 aload (3, 4)
	193 #19 (3, 4)
	194 invokevirtual (3, 4)
	195 org/apache/commons/math3/geometry/euclidean/twod/Vector2D.getX:()D (3, 4)
	197 dstore (3, 4)
	198 #12 (3, 4)
	199 aload (3, 4)
	200 #19 (3, 4)
	201 invokevirtual (3, 4)
	202 org/apache/commons/math3/geometry/euclidean/twod/Vector2D.getY:()D (3, 4)
	204 dstore (3, 4)
	205 #14 (3, 4)
	206 dload (3, 4)
	207 #20 (3, 4)
	208 dload (3, 4)
	209 #14 (3, 4)
	210 dmul (3, 4)
	211 dload (3, 4)
	212 #22 (3, 4)
	213 dload (3, 4)
	214 #12 (3, 4)
	215 dmul (3, 4)
	216 dsub (3, 4)
	217 dstore (3, 4)
	218 #24 (3, 4)
	219 dload_2 (3, 4)
	220 dload (3, 4)
	221 #24 (3, 4)
	222 dadd (3, 4)
	223 dstore_2 (3, 4)
	224 dload (3, 4)
	225 #4 (3, 4)
	226 dload (3, 4)
	227 #24 (3, 4)
	228 dload (3, 4)
	229 #20 (3, 4)
	230 dload (3, 4)
	231 #12 (3, 4)
	232 dadd (3, 4)
	233 dmul (3, 4)
	234 dadd (3, 4)
	235 dstore (3, 4)
	236 #4 (3, 4)
	237 dload (3, 4)
	238 #6 (3, 4)
	239 dload (3, 4)
	240 #24 (3, 4)
	241 dload (3, 4)
	242 #22 (3, 4)
	243 dload (3, 4)
	244 #14 (3, 4)
	245 dadd (3, 4)
	246 dmul (3, 4)
	247 dadd (3, 4)
	248 dstore (3, 4)
	249 #6 (3, 4)
	250 iinc (3, 4)
	251 #18 (3, 4)
	252 -89 (3, 4)
	253 goto (3, 4)
	254 -83 (3, 4)
	256 iinc (3, 4)
	257 #10 (3, 4)
	258 -89 (3, 4)
	259 goto (3, 4)
	260 -141 (3, 4)
	262 dload_2 (3, 1)
	263 dconst_0 (3, 1)
	264 dcmpg (3, 1)
	265 ifge (3, 1)
	266 20 (3, 1)
	268 aload_0 (3, 1)
	269 ldc2_w (3, 1)
	270 inf (3, 1)
	272 invokevirtual (3, 1)
	273 org/apache/commons/math3/geometry/euclidean/twod/PolygonsSet.setSize:(D)V (3, 1)
	275 aload_0 (3, 1)
	276 getstatic (3, 1)
	277 org/apache/commons/math3/geometry/euclidean/twod/Vector2D.NaN:Lorg/apache/commons/math3/geometry/euclidean/twod/Vector2D; (3, 1)
	279 invokevirtual (3, 1)
	280 org/apache/commons/math3/geometry/euclidean/twod/PolygonsSet.setBarycenter:(Lorg/apache/commons/math3/geometry/Point;)V (3, 1)
	282 goto (3, 1)
	283 39 (3, 1)
	285 aload_0 (3, 2)
	286 dload_2 (3, 2)
	287 ldc2_w (3, 2)
	288 2.0 (3, 2)
	290 ddiv (3, 2)
	291 invokevirtual (3, 2)
	292 org/apache/commons/math3/geometry/euclidean/twod/PolygonsSet.setSize:(D)V (3, 2)
	294 aload_0 (3, 2)
	295 new (3, 2)
	296 org/apache/commons/math3/geometry/euclidean/twod/Vector2D (3, 2)
	298 dup (3, 2)
	299 dload (3, 2)
	300 #4 (3, 2)
	301 ldc2_w (3, 2)
	302 3.0 (3, 2)
	304 dload_2 (3, 2)
	305 dmul (3, 2)
	306 ddiv (3, 2)
	307 dload (3, 2)
	308 #6 (3, 2)
	309 ldc2_w (3, 2)
	310 3.0 (3, 2)
	312 dload_2 (3, 2)
	313 dmul (3, 2)
	314 ddiv (3, 2)
	315 invokespecial (3, 2)
	316 org/apache/commons/math3/geometry/euclidean/twod/Vector2D.<init>:(DD)V (3, 2)
	318 invokevirtual (3, 2)
	319 org/apache/commons/math3/geometry/euclidean/twod/PolygonsSet.setBarycenter:(Lorg/apache/commons/math3/geometry/Point;)V (3, 2)
	321 return (0, 0)

Method: getVertices
	0 aload_0 (1, 1)
	1 getfield (1, 1)
	2 org/apache/commons/math3/geometry/euclidean/twod/PolygonsSet.vertices:[[Lorg/apache/commons/math3/geometry/euclidean/twod/Vector2D; (1, 1)
	4 ifnonnull (1, 1)
	5 672 (1, 1)
	7 aload_0 (2, 1)
	8 iconst_0 (2, 1)
	9 invokevirtual (2, 1)
	10 org/apache/commons/math3/geometry/euclidean/twod/PolygonsSet.getTree:(Z)Lorg/apache/commons/math3/geometry/partitioning/BSPTree; (2, 1)
	12 invokevirtual (2, 1)
	13 org/apache/commons/math3/geometry/partitioning/BSPTree.getCut:()Lorg/apache/commons/math3/geometry/partitioning/SubHyperplane; (2, 1)
	15 ifnonnull (2, 1)
	16 14 (2, 1)
	18 aload_0 (2, 1)
	19 iconst_0 (2, 1)
	20 anewarray (2, 1)
	21 [Lorg/apache/commons/math3/geometry/euclidean/twod/Vector2D; (2, 1)
	23 putfield (2, 1)
	24 org/apache/commons/math3/geometry/euclidean/twod/PolygonsSet.vertices:[[Lorg/apache/commons/math3/geometry/euclidean/twod/Vector2D; (2, 1)
	26 goto (2, 1)
	27 650 (2, 1)
	29 new (2, 2)
	30 org/apache/commons/math3/geometry/euclidean/twod/PolygonsSet$SegmentsBuilder (2, 2)
	32 dup (2, 2)
	33 aload_0 (2, 2)
	34 invokevirtual (2, 2)
	35 org/apache/commons/math3/geometry/euclidean/twod/PolygonsSet.getTolerance:()D (2, 2)
	37 invokespecial (2, 2)
	38 org/apache/commons/math3/geometry/euclidean/twod/PolygonsSet$SegmentsBuilder.<init>:(D)V (2, 2)
	40 astore_1 (2, 2)
	41 aload_0 (2, 2)
	42 iconst_1 (2, 2)
	43 invokevirtual (2, 2)
	44 org/apache/commons/math3/geometry/euclidean/twod/PolygonsSet.getTree:(Z)Lorg/apache/commons/math3/geometry/partitioning/BSPTree; (2, 2)
	46 aload_1 (2, 2)
	47 invokevirtual (2, 2)
	48 org/apache/commons/math3/geometry/partitioning/BSPTree.visit:(Lorg/apache/commons/math3/geometry/partitioning/BSPTreeVisitor;)V (2, 2)
	50 aload_1 (2, 2)
	51 invokevirtual (2, 2)
	52 org/apache/commons/math3/geometry/euclidean/twod/PolygonsSet$SegmentsBuilder.getSegments:()Ljava/util/List; (2, 2)
	54 astore_2 (2, 2)
	55 aload_2 (2, 2)
	56 invokeinterface (2, 2)
	57 java/util/List.get:(I)Ljava/lang/Object; (2, 2)
	59 0 (2, 2)
	61 istore_3 (2, 2)
	62 iload_3 (2, 2)
	63 aload_0 (2, 2)
	64 aload_2 (2, 2)
	65 invokespecial (2, 2)
	66 org/apache/commons/math3/geometry/euclidean/twod/PolygonsSet.naturalFollowerConnections:(Ljava/util/List;)I (2, 2)
	68 isub (2, 2)
	69 istore_3 (2, 2)
	70 iload_3 (3, 1)
	71 ifle (3, 1)
	72 11 (3, 1)
	74 iload_3 (3, 1)
	75 aload_0 (3, 1)
	76 aload_2 (3, 1)
	77 invokespecial (3, 1)
	78 org/apache/commons/math3/geometry/euclidean/twod/PolygonsSet.splitEdgeConnections:(Ljava/util/List;)I (3, 1)
	80 isub (3, 1)
	81 istore_3 (3, 1)
	82 iload_3 (3, 1)
	83 ifle (3, 1)
	84 11 (3, 1)
	86 iload_3 (3, 1)
	87 aload_0 (3, 1)
	88 aload_2 (3, 1)
	89 invokespecial (3, 1)
	90 org/apache/commons/math3/geometry/euclidean/twod/PolygonsSet.closeVerticesConnections:(Ljava/util/List;)I (3, 1)
	92 isub (3, 1)
	93 istore_3 (3, 1)
	94 new (2, 2)
	95 java/util/ArrayList (2, 2)
	97 dup (2, 2)
	98 invokespecial (2, 2)
	99 java/util/ArrayList.<init>:()V (2, 2)
	101 astore (2, 2)
	102 #4 (2, 2)
	103 aload_0 (3, 4)
	104 aload_2 (3, 4)
	105 invokespecial (3, 4)
	106 org/apache/commons/math3/geometry/euclidean/twod/PolygonsSet.getUnprocessed:(Ljava/util/List;)Lorg/apache/commons/math3/geometry/euclidean/twod/PolygonsSet$ConnectableSegment; (3, 4)
	108 astore (3, 4)
	109 #5 (3, 4)
	110 aload (3, 4)
	111 #5 (3, 4)
	112 ifnull (3, 4)
	113 62 (3, 4)
	115 aload_0 (3, 4)
	116 aload (3, 4)
	117 #5 (3, 4)
	118 invokespecial (3, 4)
	119 org/apache/commons/math3/geometry/euclidean/twod/PolygonsSet.followLoop:(Lorg/apache/commons/math3/geometry/euclidean/twod/PolygonsSet$ConnectableSegment;)Ljava/util/List; (3, 4)
	121 astore (3, 4)
	122 #6 (3, 4)
	123 aload (4, 1)
	124 #6 (4, 1)
	125 ifnull (4, 1)
	126 39 (4, 1)
	128 aload (5, 1)
	129 #6 (5, 1)
	130 iconst_0 (5, 1)
	131 invokeinterface (5, 1)
	132 java/util/List.getNode:()Lorg/apache/commons/math3/geometry/partitioning/BSPTree; (5, 1)
	134 0 (5, 1)
	136 checkcast (5, 1)
	137 org/apache/commons/math3/geometry/euclidean/twod/Segment (5, 1)
	139 invokevirtual (5, 1)
	140 org/apache/commons/math3/geometry/euclidean/twod/Segment.getStart:()Lorg/apache/commons/math3/geometry/euclidean/twod/Vector2D; (5, 1)
	142 ifnonnull (5, 1)
	143 14 (5, 1)
	145 aload (5, 1)
	146 #4 (5, 1)
	147 iconst_0 (5, 1)
	148 aload (5, 1)
	149 #6 (5, 1)
	150 invokevirtual (5, 1)
	151 java/util/ArrayList.add:(ILjava/lang/Object;)V (5, 1)
	153 goto (5, 1)
	154 11 (5, 1)
	156 aload (5, 2)
	157 #4 (5, 2)
	158 aload (5, 2)
	159 #6 (5, 2)
	160 invokevirtual (5, 2)
	161 java/util/ArrayList.add:(Ljava/lang/Object;)Z (5, 2)
	163 pop (5, 2)
	164 aload_0 (5, 2)
	165 aload_2 (5, 2)
	166 invokespecial (5, 2)
	167 org/apache/commons/math3/geometry/euclidean/twod/PolygonsSet.getUnprocessed:(Ljava/util/List;)Lorg/apache/commons/math3/geometry/euclidean/twod/PolygonsSet$ConnectableSegment; (5, 2)
	169 astore (5, 2)
	170 #5 (5, 2)
	171 goto (5, 2)
	172 -61 (5, 2)
	174 aload_0 (4, 4)
	175 aload (4, 4)
	176 #4 (4, 4)
	177 invokevirtual (4, 4)
	178 java/util/ArrayList.size:()I (4, 4)
	180 anewarray (4, 4)
	181 [Lorg/apache/commons/math3/geometry/euclidean/twod/Vector2D; (4, 4)
	183 putfield (4, 4)
	184 org/apache/commons/math3/geometry/euclidean/twod/PolygonsSet.vertices:[[Lorg/apache/commons/math3/geometry/euclidean/twod/Vector2D; (4, 4)
	186 iconst_0 (4, 4)
	187 istore (4, 4)
	188 #5 (4, 4)
	189 aload (5, 4)
	190 #4 (5, 4)
	191 invokevirtual (5, 4)
	192 java/util/ArrayList.iterator:()Ljava/util/Iterator; (5, 4)
	194 astore (5, 4)
	195 #6 (5, 4)
	196 aload (5, 4)
	197 #6 (5, 4)
	198 invokeinterface (5, 4)
	199 java/util/Iterator.next:()Ljava/lang/Object; (5, 4)
	201 0 (5, 4)
	203 ifeq (5, 4)
	204 473 (5, 4)
	206 aload (5, 4)
	207 #6 (5, 4)
	208 invokeinterface (5, 4)
	209 java/util/Iterator.getStart:()Lorg/apache/commons/math3/geometry/euclidean/twod/PolygonsSet$Vertex; (5, 4)
	211 0 (5, 4)
	213 checkcast (5, 4)
	214 java/util/List (5, 4)
	216 astore (5, 4)
	217 #7 (5, 4)
	218 aload (5, 1)
	219 #7 (5, 1)
	220 invokeinterface (5, 1)
	221 java/util/List.get:(I)Ljava/lang/Object; (5, 1)
	223 0 (5, 1)
	225 iconst_2 (5, 1)
	226 if_icmplt (5, 1)
	227 48 (5, 1)
	229 aload (5, 1)
	230 #7 (5, 1)
	231 invokeinterface (5, 1)
	232 java/util/List.get:(I)Ljava/lang/Object; (5, 1)
	234 0 (5, 1)
	236 iconst_2 (5, 1)
	237 if_icmpne (5, 1)
	238 110 (5, 1)
	240 aload (5, 1)
	241 #7 (5, 1)
	242 iconst_0 (5, 1)
	243 invokeinterface (5, 1)
	244 java/util/List.getNode:()Lorg/apache/commons/math3/geometry/partitioning/BSPTree; (5, 1)
	246 0 (5, 1)
	248 checkcast (5, 1)
	249 org/apache/commons/math3/geometry/euclidean/twod/Segment (5, 1)
	251 invokevirtual (5, 1)
	252 org/apache/commons/math3/geometry/euclidean/twod/Segment.getStart:()Lorg/apache/commons/math3/geometry/euclidean/twod/Vector2D; (5, 1)
	254 ifnonnull (5, 1)
	255 93 (5, 1)
	257 aload (5, 1)
	258 #7 (5, 1)
	259 iconst_1 (5, 1)
	260 invokeinterface (5, 1)
	261 java/util/List.getNode:()Lorg/apache/commons/math3/geometry/partitioning/BSPTree; (5, 1)
	263 0 (5, 1)
	265 checkcast (5, 1)
	266 org/apache/commons/math3/geometry/euclidean/twod/Segment (5, 1)
	268 invokevirtual (5, 1)
	269 org/apache/commons/math3/geometry/euclidean/twod/Segment.getEnd:()Lorg/apache/commons/math3/geometry/euclidean/twod/Vector2D; (5, 1)
	271 ifnonnull (5, 1)
	272 76 (5, 1)
	274 aload (5, 1)
	275 #7 (5, 1)
	276 iconst_0 (5, 1)
	277 invokeinterface (5, 1)
	278 java/util/List.getNode:()Lorg/apache/commons/math3/geometry/partitioning/BSPTree; (5, 1)
	280 0 (5, 1)
	282 checkcast (5, 1)
	283 org/apache/commons/math3/geometry/euclidean/twod/Segment (5, 1)
	285 invokevirtual (5, 1)
	286 org/apache/commons/math3/geometry/euclidean/twod/Segment.getLine:()Lorg/apache/commons/math3/geometry/euclidean/twod/Line; (5, 1)
	288 astore (5, 1)
	289 #8 (5, 1)
	290 aload_0 (5, 1)
	291 getfield (5, 1)
	292 org/apache/commons/math3/geometry/euclidean/twod/PolygonsSet.vertices:[[Lorg/apache/commons/math3/geometry/euclidean/twod/Vector2D; (5, 1)
	294 iload (5, 1)
	295 #5 (5, 1)
	296 iinc (5, 1)
	297 #5 (5, 1)
	298 6 (5, 1)
	299 iconst_3 (5, 1)
	300 anewarray (5, 1)
	301 org/apache/commons/math3/geometry/euclidean/twod/Vector2D (5, 1)
	303 dup (5, 1)
	304 iconst_0 (5, 1)
	305 aconst_null (5, 1)
	306 aastore (5, 1)
	307 dup (5, 1)
	308 iconst_1 (5, 1)
	309 aload (5, 1)
	310 #8 (5, 1)
	311 new (5, 1)
	312 org/apache/commons/math3/geometry/euclidean/oned/Vector1D (5, 1)
	314 dup (5, 1)
	315 ldc2_w (5, 1)
	316 -3.4028234663852886e+38 (5, 1)
	318 invokespecial (5, 1)
	319 org/apache/commons/math3/geometry/euclidean/oned/Vector1D.<init>:(D)V (5, 1)
	321 invokevirtual (5, 1)
	322 org/apache/commons/math3/geometry/euclidean/twod/Line.toSpace:(Lorg/apache/commons/math3/geometry/Point;)Lorg/apache/commons/math3/geometry/euclidean/twod/Vector2D; (5, 1)
	324 aastore (5, 1)
	325 dup (5, 1)
	326 iconst_2 (5, 1)
	327 aload (5, 1)
	328 #8 (5, 1)
	329 new (5, 1)
	330 org/apache/commons/math3/geometry/euclidean/oned/Vector1D (5, 1)
	332 dup (5, 1)
	333 ldc2_w (5, 1)
	334 3.4028234663852886e+38 (5, 1)
	336 invokespecial (5, 1)
	337 org/apache/commons/math3/geometry/euclidean/oned/Vector1D.<init>:(D)V (5, 1)
	339 invokevirtual (5, 1)
	340 org/apache/commons/math3/geometry/euclidean/twod/Line.toSpace:(Lorg/apache/commons/math3/geometry/Point;)Lorg/apache/commons/math3/geometry/euclidean/twod/Vector2D; (5, 1)
	342 aastore (5, 1)
	343 aastore (5, 1)
	344 goto (6, 1)
	345 329 (6, 1)
	347 aload (6, 1)
	348 #7 (6, 1)
	349 iconst_0 (6, 1)
	350 invokeinterface (6, 1)
	351 java/util/List.getNode:()Lorg/apache/commons/math3/geometry/partitioning/BSPTree; (6, 1)
	353 0 (6, 1)
	355 checkcast (6, 1)
	356 org/apache/commons/math3/geometry/euclidean/twod/Segment (6, 1)
	358 invokevirtual (6, 1)
	359 org/apache/commons/math3/geometry/euclidean/twod/Segment.getStart:()Lorg/apache/commons/math3/geometry/euclidean/twod/Vector2D; (6, 1)
	361 ifnonnull (6, 1)
	362 238 (6, 1)
	364 aload (6, 1)
	365 #7 (6, 1)
	366 invokeinterface (6, 1)
	367 java/util/List.get:(I)Ljava/lang/Object; (6, 1)
	369 0 (6, 1)
	371 iconst_2 (6, 1)
	372 iadd (6, 1)
	373 anewarray (6, 1)
	374 org/apache/commons/math3/geometry/euclidean/twod/Vector2D (6, 1)
	376 astore (6, 1)
	377 #8 (6, 1)
	378 iconst_0 (6, 1)
	379 istore (6, 1)
	380 #9 (6, 1)
	381 aload (7, 4)
	382 #7 (7, 4)
	383 invokeinterface (7, 4)
	384 java/util/List.java/util/Iterator (7, 4)
	386 0 (7, 4)
	388 astore (7, 4)
	389 #10 (7, 4)
	390 aload (7, 4)
	391 #10 (7, 4)
	392 invokeinterface (7, 4)
	393 java/util/Iterator.next:()Ljava/lang/Object; (7, 4)
	395 0 (7, 4)
	397 ifeq (7, 4)
	398 187 (7, 4)
	400 aload (7, 4)
	401 #10 (7, 4)
	402 invokeinterface (7, 4)
	403 java/util/Iterator.getStart:()Lorg/apache/commons/math3/geometry/euclidean/twod/PolygonsSet$Vertex; (7, 4)
	405 0 (7, 4)
	407 checkcast (7, 4)
	408 org/apache/commons/math3/geometry/euclidean/twod/Segment (7, 4)
	410 astore (7, 4)
	411 #11 (7, 4)
	412 iload (8, 1)
	413 #9 (8, 1)
	414 ifne (8, 1)
	415 73 (8, 1)
	417 aload (8, 1)
	418 #11 (8, 1)
	419 invokevirtual (8, 1)
	420 org/apache/commons/math3/geometry/euclidean/twod/Segment.getLine:()Lorg/apache/commons/math3/geometry/euclidean/twod/Line; (8, 1)
	422 aload (8, 1)
	423 #11 (8, 1)
	424 invokevirtual (8, 1)
	425 org/apache/commons/math3/geometry/euclidean/twod/Segment.getEnd:()Lorg/apache/commons/math3/geometry/euclidean/twod/Vector2D; (8, 1)
	427 invokevirtual (8, 1)
	428 org/apache/commons/math3/geometry/euclidean/twod/Line.toSubSpace:(Lorg/apache/commons/math3/geometry/Point;)Lorg/apache/commons/math3/geometry/euclidean/oned/Vector1D; (8, 1)
	430 invokevirtual (8, 1)
	431 org/apache/commons/math3/geometry/euclidean/oned/Vector1D.getX:()D (8, 1)
	433 dstore (8, 1)
	434 #12 (8, 1)
	435 dload (8, 1)
	436 #12 (8, 1)
	437 dconst_1 (8, 1)
	438 dload (8, 1)
	439 #12 (8, 1)
	440 ldc2_w (8, 1)
	441 2.0 (8, 1)
	443 ddiv (8, 1)
	444 invokestatic (8, 1)
	445 org/apache/commons/math3/util/FastMath.abs:(D)D (8, 1)
	447 invokestatic (8, 1)
	448 org/apache/commons/math3/util/FastMath.max:(DD)D (8, 1)
	450 dsub (8, 1)
	451 dstore (8, 1)
	452 #12 (8, 1)
	453 aload (8, 1)
	454 #8 (8, 1)
	455 iload (8, 1)
	456 #9 (8, 1)
	457 iinc (8, 1)
	458 #9 (8, 1)
	459 1 (8, 1)
	460 aconst_null (8, 1)
	461 aastore (8, 1)
	462 aload (8, 1)
	463 #8 (8, 1)
	464 iload (8, 1)
	465 #9 (8, 1)
	466 iinc (8, 1)
	467 #9 (8, 1)
	468 25 (8, 1)
	469 aload (8, 1)
	470 #11 (8, 1)
	471 invokevirtual (8, 1)
	472 org/apache/commons/math3/geometry/euclidean/twod/Segment.getLine:()Lorg/apache/commons/math3/geometry/euclidean/twod/Line; (8, 1)
	474 new (8, 1)
	475 org/apache/commons/math3/geometry/euclidean/oned/Vector1D (8, 1)
	477 dup (8, 1)
	478 dload (8, 1)
	479 #12 (8, 1)
	480 invokespecial (8, 1)
	481 org/apache/commons/math3/geometry/euclidean/oned/Vector1D.<init>:(D)V (8, 1)
	483 invokevirtual (8, 1)
	484 org/apache/commons/math3/geometry/euclidean/twod/Line.toSpace:(Lorg/apache/commons/math3/geometry/Point;)Lorg/apache/commons/math3/geometry/euclidean/twod/Vector2D; (8, 1)
	486 aastore (8, 1)
	487 iload (8, 1)
	488 #9 (8, 1)
	489 aload (8, 1)
	490 #8 (8, 1)
	491 arraylength (8, 1)
	492 iconst_1 (8, 1)
	493 isub (8, 1)
	494 if_icmpge (8, 1)
	495 16 (8, 1)
	497 aload (8, 1)
	498 #8 (8, 1)
	499 iload (8, 1)
	500 #9 (8, 1)
	501 iinc (8, 1)
	502 #9 (8, 1)
	503 25 (8, 1)
	504 aload (8, 1)
	505 #11 (8, 1)
	506 invokevirtual (8, 1)
	507 org/apache/commons/math3/geometry/euclidean/twod/Segment.getEnd:()Lorg/apache/commons/math3/geometry/euclidean/twod/Vector2D; (8, 1)
	509 aastore (8, 1)
	510 iload (8, 1)
	511 #9 (8, 1)
	512 aload (8, 1)
	513 #8 (8, 1)
	514 arraylength (8, 1)
	515 iconst_1 (8, 1)
	516 isub (8, 1)
	517 if_icmpne (8, 1)
	518 64 (8, 1)
	520 aload (8, 1)
	521 #11 (8, 1)
	522 invokevirtual (8, 1)
	523 org/apache/commons/math3/geometry/euclidean/twod/Segment.getLine:()Lorg/apache/commons/math3/geometry/euclidean/twod/Line; (8, 1)
	525 aload (8, 1)
	526 #11 (8, 1)
	527 invokevirtual (8, 1)
	528 org/apache/commons/math3/geometry/euclidean/twod/Segment.getStart:()Lorg/apache/commons/math3/geometry/euclidean/twod/Vector2D; (8, 1)
	530 invokevirtual (8, 1)
	531 org/apache/commons/math3/geometry/euclidean/twod/Line.toSubSpace:(Lorg/apache/commons/math3/geometry/Point;)Lorg/apache/commons/math3/geometry/euclidean/oned/Vector1D; (8, 1)
	533 invokevirtual (8, 1)
	534 org/apache/commons/math3/geometry/euclidean/oned/Vector1D.getX:()D (8, 1)
	536 dstore (8, 1)
	537 #12 (8, 1)
	538 dload (8, 1)
	539 #12 (8, 1)
	540 dconst_1 (8, 1)
	541 dload (8, 1)
	542 #12 (8, 1)
	543 ldc2_w (8, 1)
	544 2.0 (8, 1)
	546 ddiv (8, 1)
	547 invokestatic (8, 1)
	548 org/apache/commons/math3/util/FastMath.abs:(D)D (8, 1)
	550 invokestatic (8, 1)
	551 org/apache/commons/math3/util/FastMath.max:(DD)D (8, 1)
	553 dadd (8, 1)
	554 dstore (8, 1)
	555 #12 (8, 1)
	556 aload (8, 1)
	557 #8 (8, 1)
	558 iload (8, 1)
	559 #9 (8, 1)
	560 iinc (8, 1)
	561 #9 (8, 1)
	562 25 (8, 1)
	563 aload (8, 1)
	564 #11 (8, 1)
	565 invokevirtual (8, 1)
	566 org/apache/commons/math3/geometry/euclidean/twod/Segment.getLine:()Lorg/apache/commons/math3/geometry/euclidean/twod/Line; (8, 1)
	568 new (8, 1)
	569 org/apache/commons/math3/geometry/euclidean/oned/Vector1D (8, 1)
	571 dup (8, 1)
	572 dload (8, 1)
	573 #12 (8, 1)
	574 invokespecial (8, 1)
	575 org/apache/commons/math3/geometry/euclidean/oned/Vector1D.<init>:(D)V (8, 1)
	577 invokevirtual (8, 1)
	578 org/apache/commons/math3/geometry/euclidean/twod/Line.toSpace:(Lorg/apache/commons/math3/geometry/Point;)Lorg/apache/commons/math3/geometry/euclidean/twod/Vector2D; (8, 1)
	580 aastore (8, 1)
	581 goto (6, 1)
	582 -191 (6, 1)
	584 aload_0 (6, 1)
	585 getfield (6, 1)
	586 org/apache/commons/math3/geometry/euclidean/twod/PolygonsSet.vertices:[[Lorg/apache/commons/math3/geometry/euclidean/twod/Vector2D; (6, 1)
	588 iload (6, 1)
	589 #5 (6, 1)
	590 iinc (6, 1)
	591 #5 (6, 1)
	592 25 (6, 1)
	593 aload (6, 1)
	594 #8 (6, 1)
	595 aastore (6, 1)
	596 goto (6, 2)
	597 77 (6, 2)
	599 aload (6, 2)
	600 #7 (6, 2)
	601 invokeinterface (6, 2)
	602 java/util/List.get:(I)Ljava/lang/Object; (6, 2)
	604 0 (6, 2)
	606 anewarray (6, 2)
	607 org/apache/commons/math3/geometry/euclidean/twod/Vector2D (6, 2)
	609 astore (6, 2)
	610 #8 (6, 2)
	611 iconst_0 (6, 2)
	612 istore (6, 2)
	613 #9 (6, 2)
	614 aload (7, 4)
	615 #7 (7, 4)
	616 invokeinterface (7, 4)
	617 java/util/List.java/util/Iterator (7, 4)
	619 0 (7, 4)
	621 astore (7, 4)
	622 #10 (7, 4)
	623 aload (7, 4)
	624 #10 (7, 4)
	625 invokeinterface (7, 4)
	626 java/util/Iterator.next:()Ljava/lang/Object; (7, 4)
	628 0 (7, 4)
	630 ifeq (7, 4)
	631 31 (7, 4)
	633 aload (7, 4)
	634 #10 (7, 4)
	635 invokeinterface (7, 4)
	636 java/util/Iterator.getStart:()Lorg/apache/commons/math3/geometry/euclidean/twod/PolygonsSet$Vertex; (7, 4)
	638 0 (7, 4)
	640 checkcast (7, 4)
	641 org/apache/commons/math3/geometry/euclidean/twod/Segment (7, 4)
	643 astore (7, 4)
	644 #11 (7, 4)
	645 aload (7, 4)
	646 #8 (7, 4)
	647 iload (7, 4)
	648 #9 (7, 4)
	649 iinc (7, 4)
	650 #9 (7, 4)
	651 25 (7, 4)
	652 aload (7, 4)
	653 #11 (7, 4)
	654 invokevirtual (7, 4)
	655 org/apache/commons/math3/geometry/euclidean/twod/Segment.getStart:()Lorg/apache/commons/math3/geometry/euclidean/twod/Vector2D; (7, 4)
	657 aastore (7, 4)
	658 goto (6, 2)
	659 -35 (6, 2)
	661 aload_0 (6, 2)
	662 getfield (6, 2)
	663 org/apache/commons/math3/geometry/euclidean/twod/PolygonsSet.vertices:[[Lorg/apache/commons/math3/geometry/euclidean/twod/Vector2D; (6, 2)
	665 iload (6, 2)
	666 #5 (6, 2)
	667 iinc (6, 2)
	668 #5 (6, 2)
	669 25 (6, 2)
	670 aload (6, 2)
	671 #8 (6, 2)
	672 aastore (6, 2)
	673 goto (4, 4)
	674 -477 (4, 4)
	676 aload_0 (2, 2)
	677 getfield (2, 2)
	678 org/apache/commons/math3/geometry/euclidean/twod/PolygonsSet.vertices:[[Lorg/apache/commons/math3/geometry/euclidean/twod/Vector2D; (2, 2)
	680 invokevirtual (2, 2)
	681 [[Lorg/apache/commons/math3/geometry/euclidean/twod/Vector2D;.clone:()Ljava/lang/Object; (2, 2)
	683 checkcast (2, 2)
	684 [[Lorg/apache/commons/math3/geometry/euclidean/twod/Vector2D; (2, 2)
	686 areturn (2, 2)

Method: naturalFollowerConnections
	0 iconst_0 (0, 0)
	1 istore_2 (0, 0)
	2 aload_1 (1, 4)
	3 invokeinterface (1, 4)
	4 java/util/List.java/util/Iterator (1, 4)
	6 0 (1, 4)
	8 astore_3 (1, 4)
	9 aload_3 (1, 4)
	10 invokeinterface (1, 4)
	11 java/util/Iterator.next:()Ljava/lang/Object; (1, 4)
	13 0 (1, 4)
	15 ifeq (1, 4)
	16 120 (1, 4)
	18 aload_3 (1, 4)
	19 invokeinterface (1, 4)
	20 java/util/Iterator.getStart:()Lorg/apache/commons/math3/geometry/euclidean/twod/PolygonsSet$Vertex; (1, 4)
	22 0 (1, 4)
	24 checkcast (1, 4)
	25 org/apache/commons/math3/geometry/euclidean/twod/PolygonsSet$ConnectableSegment (1, 4)
	27 astore (1, 4)
	28 #4 (1, 4)
	29 aload (2, 1)
	30 #4 (2, 1)
	31 invokevirtual (2, 1)
	32 org/apache/commons/math3/geometry/euclidean/twod/PolygonsSet$ConnectableSegment.getNext:()Lorg/apache/commons/math3/geometry/euclidean/twod/PolygonsSet$ConnectableSegment; (2, 1)
	34 ifnonnull (2, 1)
	35 98 (2, 1)
	37 aload (2, 1)
	38 #4 (2, 1)
	39 invokevirtual (2, 1)
	40 org/apache/commons/math3/geometry/euclidean/twod/PolygonsSet$ConnectableSegment.getNode:()Lorg/apache/commons/math3/geometry/partitioning/BSPTree; (2, 1)
	42 astore (2, 1)
	43 #5 (2, 1)
	44 aload (2, 1)
	45 #4 (2, 1)
	46 invokevirtual (2, 1)
	47 org/apache/commons/math3/geometry/euclidean/twod/PolygonsSet$ConnectableSegment.getEndNode:()Lorg/apache/commons/math3/geometry/partitioning/BSPTree; (2, 1)
	49 astore (2, 1)
	50 #6 (2, 1)
	51 aload_1 (3, 4)
	52 invokeinterface (3, 4)
	53 java/util/List.java/util/Iterator (3, 4)
	55 0 (3, 4)
	57 astore (3, 4)
	58 #7 (3, 4)
	59 aload (3, 4)
	60 #7 (3, 4)
	61 invokeinterface (3, 4)
	62 java/util/Iterator.next:()Ljava/lang/Object; (3, 4)
	64 0 (3, 4)
	66 ifeq (3, 4)
	67 66 (3, 4)
	69 aload (3, 4)
	70 #7 (3, 4)
	71 invokeinterface (3, 4)
	72 java/util/Iterator.getStart:()Lorg/apache/commons/math3/geometry/euclidean/twod/PolygonsSet$Vertex; (3, 4)
	74 0 (3, 4)
	76 checkcast (3, 4)
	77 org/apache/commons/math3/geometry/euclidean/twod/PolygonsSet$ConnectableSegment (3, 4)
	79 astore (3, 4)
	80 #8 (3, 4)
	81 aload (3, 1)
	82 #8 (3, 1)
	83 invokevirtual (3, 1)
	84 org/apache/commons/math3/geometry/euclidean/twod/PolygonsSet$ConnectableSegment.getPrevious:()Lorg/apache/commons/math3/geometry/euclidean/twod/PolygonsSet$ConnectableSegment; (3, 1)
	86 ifnonnull (3, 1)
	87 43 (3, 1)
	89 aload (3, 1)
	90 #8 (3, 1)
	91 invokevirtual (3, 1)
	92 org/apache/commons/math3/geometry/euclidean/twod/PolygonsSet$ConnectableSegment.getNode:()Lorg/apache/commons/math3/geometry/partitioning/BSPTree; (3, 1)
	94 aload (3, 1)
	95 #6 (3, 1)
	96 if_acmpne (3, 1)
	97 33 (3, 1)
	99 aload (3, 1)
	100 #8 (3, 1)
	101 invokevirtual (3, 1)
	102 org/apache/commons/math3/geometry/euclidean/twod/PolygonsSet$ConnectableSegment.getStartNode:()Lorg/apache/commons/math3/geometry/partitioning/BSPTree; (3, 1)
	104 aload (3, 1)
	105 #5 (3, 1)
	106 if_acmpne (3, 1)
	107 23 (3, 1)
	109 aload (3, 1)
	110 #4 (3, 1)
	111 aload (3, 1)
	112 #8 (3, 1)
	113 invokevirtual (3, 1)
	114 org/apache/commons/math3/geometry/euclidean/twod/PolygonsSet$ConnectableSegment.setNext:(Lorg/apache/commons/math3/geometry/euclidean/twod/PolygonsSet$ConnectableSegment;)V (3, 1)
	116 aload (3, 1)
	117 #8 (3, 1)
	118 aload (3, 1)
	119 #4 (3, 1)
	120 invokevirtual (3, 1)
	121 org/apache/commons/math3/geometry/euclidean/twod/PolygonsSet$ConnectableSegment.setPrevious:(Lorg/apache/commons/math3/geometry/euclidean/twod/PolygonsSet$ConnectableSegment;)V (3, 1)
	123 iinc (3, 1)
	124 #2 (3, 1)
	125 -89 (3, 1)
	126 goto (3, 1)
	127 6 (3, 1)
	129 goto (2, 1)
	130 -70 (2, 1)
	132 goto (0, 0)
	133 -123 (0, 0)
	135 iload_2 (0, 0)
	136 ireturn (0, 0)

Method: splitEdgeConnections
	0 iconst_0 (0, 0)
	1 istore_2 (0, 0)
	2 aload_1 (1, 4)
	3 invokeinterface (1, 4)
	4 java/util/List.java/util/Iterator (1, 4)
	6 0 (1, 4)
	8 astore_3 (1, 4)
	9 aload_3 (1, 4)
	10 invokeinterface (1, 4)
	11 java/util/Iterator.next:()Ljava/lang/Object; (1, 4)
	13 0 (1, 4)
	15 ifeq (1, 4)
	16 136 (1, 4)
	18 aload_3 (1, 4)
	19 invokeinterface (1, 4)
	20 java/util/Iterator.getStart:()Lorg/apache/commons/math3/geometry/euclidean/twod/PolygonsSet$Vertex; (1, 4)
	22 0 (1, 4)
	24 checkcast (1, 4)
	25 org/apache/commons/math3/geometry/euclidean/twod/PolygonsSet$ConnectableSegment (1, 4)
	27 astore (1, 4)
	28 #4 (1, 4)
	29 aload (2, 1)
	30 #4 (2, 1)
	31 invokevirtual (2, 1)
	32 org/apache/commons/math3/geometry/euclidean/twod/PolygonsSet$ConnectableSegment.getNext:()Lorg/apache/commons/math3/geometry/euclidean/twod/PolygonsSet$ConnectableSegment; (2, 1)
	34 ifnonnull (2, 1)
	35 114 (2, 1)
	37 aload (2, 1)
	38 #4 (2, 1)
	39 invokevirtual (2, 1)
	40 org/apache/commons/math3/geometry/euclidean/twod/PolygonsSet$ConnectableSegment.getNode:()Lorg/apache/commons/math3/geometry/partitioning/BSPTree; (2, 1)
	42 invokevirtual (2, 1)
	43 org/apache/commons/math3/geometry/partitioning/BSPTree.getCut:()Lorg/apache/commons/math3/geometry/partitioning/SubHyperplane; (2, 1)
	45 invokeinterface (2, 1)
	46 org/apache/commons/math3/geometry/partitioning/SubHyperplane.distance:(Lorg/apache/commons/math3/geometry/euclidean/twod/Vector2D;Lorg/apache/commons/math3/geometry/euclidean/twod/Vector2D;)D (2, 1)
	48 0 (2, 1)
	50 astore (2, 1)
	51 #5 (2, 1)
	52 aload (2, 1)
	53 #4 (2, 1)
	54 invokevirtual (2, 1)
	55 org/apache/commons/math3/geometry/euclidean/twod/PolygonsSet$ConnectableSegment.getEndNode:()Lorg/apache/commons/math3/geometry/partitioning/BSPTree; (2, 1)
	57 astore (2, 1)
	58 #6 (2, 1)
	59 aload_1 (3, 4)
	60 invokeinterface (3, 4)
	61 java/util/List.java/util/Iterator (3, 4)
	63 0 (3, 4)
	65 astore (3, 4)
	66 #7 (3, 4)
	67 aload (3, 4)
	68 #7 (3, 4)
	69 invokeinterface (3, 4)
	70 java/util/Iterator.next:()Ljava/lang/Object; (3, 4)
	72 0 (3, 4)
	74 ifeq (3, 4)
	75 74 (3, 4)
	77 aload (3, 4)
	78 #7 (3, 4)
	79 invokeinterface (3, 4)
	80 java/util/Iterator.getStart:()Lorg/apache/commons/math3/geometry/euclidean/twod/PolygonsSet$Vertex; (3, 4)
	82 0 (3, 4)
	84 checkcast (3, 4)
	85 org/apache/commons/math3/geometry/euclidean/twod/PolygonsSet$ConnectableSegment (3, 4)
	87 astore (3, 4)
	88 #8 (3, 4)
	89 aload (3, 1)
	90 #8 (3, 1)
	91 invokevirtual (3, 1)
	92 org/apache/commons/math3/geometry/euclidean/twod/PolygonsSet$ConnectableSegment.getPrevious:()Lorg/apache/commons/math3/geometry/euclidean/twod/PolygonsSet$ConnectableSegment; (3, 1)
	94 ifnonnull (3, 1)
	95 51 (3, 1)
	97 aload (3, 1)
	98 #8 (3, 1)
	99 invokevirtual (3, 1)
	100 org/apache/commons/math3/geometry/euclidean/twod/PolygonsSet$ConnectableSegment.getNode:()Lorg/apache/commons/math3/geometry/partitioning/BSPTree; (3, 1)
	102 invokevirtual (3, 1)
	103 org/apache/commons/math3/geometry/partitioning/BSPTree.getCut:()Lorg/apache/commons/math3/geometry/partitioning/SubHyperplane; (3, 1)
	105 invokeinterface (3, 1)
	106 org/apache/commons/math3/geometry/partitioning/SubHyperplane.distance:(Lorg/apache/commons/math3/geometry/euclidean/twod/Vector2D;Lorg/apache/commons/math3/geometry/euclidean/twod/Vector2D;)D (3, 1)
	108 0 (3, 1)
	110 aload (3, 1)
	111 #5 (3, 1)
	112 if_acmpne (3, 1)
	113 33 (3, 1)
	115 aload (3, 1)
	116 #8 (3, 1)
	117 invokevirtual (3, 1)
	118 org/apache/commons/math3/geometry/euclidean/twod/PolygonsSet$ConnectableSegment.getStartNode:()Lorg/apache/commons/math3/geometry/partitioning/BSPTree; (3, 1)
	120 aload (3, 1)
	121 #6 (3, 1)
	122 if_acmpne (3, 1)
	123 23 (3, 1)
	125 aload (3, 1)
	126 #4 (3, 1)
	127 aload (3, 1)
	128 #8 (3, 1)
	129 invokevirtual (3, 1)
	130 org/apache/commons/math3/geometry/euclidean/twod/PolygonsSet$ConnectableSegment.setNext:(Lorg/apache/commons/math3/geometry/euclidean/twod/PolygonsSet$ConnectableSegment;)V (3, 1)
	132 aload (3, 1)
	133 #8 (3, 1)
	134 aload (3, 1)
	135 #4 (3, 1)
	136 invokevirtual (3, 1)
	137 org/apache/commons/math3/geometry/euclidean/twod/PolygonsSet$ConnectableSegment.setPrevious:(Lorg/apache/commons/math3/geometry/euclidean/twod/PolygonsSet$ConnectableSegment;)V (3, 1)
	139 iinc (3, 1)
	140 #2 (3, 1)
	141 -89 (3, 1)
	142 goto (3, 1)
	143 6 (3, 1)
	145 goto (2, 1)
	146 -78 (2, 1)
	148 goto (0, 0)
	149 -139 (0, 0)
	151 iload_2 (0, 0)
	152 ireturn (0, 0)

Method: closeVerticesConnections
	0 iconst_0 (0, 0)
	1 istore_2 (0, 0)
	2 aload_1 (1, 4)
	3 invokeinterface (1, 4)
	4 java/util/List.java/util/Iterator (1, 4)
	6 0 (1, 4)
	8 astore_3 (1, 4)
	9 aload_3 (1, 4)
	10 invokeinterface (1, 4)
	11 java/util/Iterator.next:()Ljava/lang/Object; (1, 4)
	13 0 (1, 4)
	15 ifeq (1, 4)
	16 152 (1, 4)
	18 aload_3 (1, 4)
	19 invokeinterface (1, 4)
	20 java/util/Iterator.getStart:()Lorg/apache/commons/math3/geometry/euclidean/twod/PolygonsSet$Vertex; (1, 4)
	22 0 (1, 4)
	24 checkcast (1, 4)
	25 org/apache/commons/math3/geometry/euclidean/twod/PolygonsSet$ConnectableSegment (1, 4)
	27 astore (1, 4)
	28 #4 (1, 4)
	29 aload (2, 1)
	30 #4 (2, 1)
	31 invokevirtual (2, 1)
	32 org/apache/commons/math3/geometry/euclidean/twod/PolygonsSet$ConnectableSegment.getNext:()Lorg/apache/commons/math3/geometry/euclidean/twod/PolygonsSet$ConnectableSegment; (2, 1)
	34 ifnonnull (2, 1)
	35 130 (2, 1)
	37 aload (2, 1)
	38 #4 (2, 1)
	39 invokevirtual (2, 1)
	40 org/apache/commons/math3/geometry/euclidean/twod/PolygonsSet$ConnectableSegment.getEnd:()Lorg/apache/commons/math3/geometry/euclidean/twod/Vector2D; (2, 1)
	42 ifnull (2, 1)
	43 122 (2, 1)
	45 aload (2, 1)
	46 #4 (2, 1)
	47 invokevirtual (2, 1)
	48 org/apache/commons/math3/geometry/euclidean/twod/PolygonsSet$ConnectableSegment.getEnd:()Lorg/apache/commons/math3/geometry/euclidean/twod/Vector2D; (2, 1)
	50 astore (2, 1)
	51 #5 (2, 1)
	52 aconst_null (2, 1)
	53 astore (2, 1)
	54 #6 (2, 1)
	55 ldc2_w (2, 1)
	56 inf (2, 1)
	58 dstore (2, 1)
	59 #7 (2, 1)
	60 aload_1 (3, 4)
	61 invokeinterface (3, 4)
	62 java/util/List.java/util/Iterator (3, 4)
	64 0 (3, 4)
	66 astore (3, 4)
	67 #9 (3, 4)
	68 aload (3, 4)
	69 #9 (3, 4)
	70 invokeinterface (3, 4)
	71 java/util/Iterator.next:()Ljava/lang/Object; (3, 4)
	73 0 (3, 4)
	75 ifeq (3, 4)
	76 62 (3, 4)
	78 aload (3, 4)
	79 #9 (3, 4)
	80 invokeinterface (3, 4)
	81 java/util/Iterator.getStart:()Lorg/apache/commons/math3/geometry/euclidean/twod/PolygonsSet$Vertex; (3, 4)
	83 0 (3, 4)
	85 checkcast (3, 4)
	86 org/apache/commons/math3/geometry/euclidean/twod/PolygonsSet$ConnectableSegment (3, 4)
	88 astore (3, 4)
	89 #10 (3, 4)
	90 aload (4, 1)
	91 #10 (4, 1)
	92 invokevirtual (4, 1)
	93 org/apache/commons/math3/geometry/euclidean/twod/PolygonsSet$ConnectableSegment.getPrevious:()Lorg/apache/commons/math3/geometry/euclidean/twod/PolygonsSet$ConnectableSegment; (4, 1)
	95 ifnonnull (4, 1)
	96 39 (4, 1)
	98 aload (4, 1)
	99 #10 (4, 1)
	100 invokevirtual (4, 1)
	101 org/apache/commons/math3/geometry/euclidean/twod/PolygonsSet$ConnectableSegment.getStart:()Lorg/apache/commons/math3/geometry/euclidean/twod/Vector2D; (4, 1)
	103 ifnull (4, 1)
	104 31 (4, 1)
	106 aload (4, 1)
	107 #5 (4, 1)
	108 aload (4, 1)
	109 #10 (4, 1)
	110 invokevirtual (4, 1)
	111 org/apache/commons/math3/geometry/euclidean/twod/PolygonsSet$ConnectableSegment.getStart:()Lorg/apache/commons/math3/geometry/euclidean/twod/Vector2D; (4, 1)
	113 invokestatic (4, 1)
	114 org/apache/commons/math3/geometry/euclidean/twod/Vector2D.distance:(Lorg/apache/commons/math3/geometry/euclidean/twod/Vector2D;Lorg/apache/commons/math3/geometry/euclidean/twod/Vector2D;)D (4, 1)
	116 dstore (4, 1)
	117 #11 (4, 1)
	118 dload (5, 1)
	119 #11 (5, 1)
	120 dload (5, 1)
	121 #7 (5, 1)
	122 dcmpg (5, 1)
	123 ifge (5, 1)
	124 11 (5, 1)
	126 aload (5, 1)
	127 #10 (5, 1)
	128 astore (5, 1)
	129 #6 (5, 1)
	130 dload (5, 1)
	131 #11 (5, 1)
	132 dstore (5, 1)
	133 #7 (5, 1)
	134 goto (2, 1)
	135 -66 (2, 1)
	137 dload (3, 1)
	138 #7 (3, 1)
	139 aload_0 (3, 1)
	140 invokevirtual (3, 1)
	141 org/apache/commons/math3/geometry/euclidean/twod/PolygonsSet.getTolerance:()D (3, 1)
	143 dcmpg (3, 1)
	144 ifgt (3, 1)
	145 20 (3, 1)
	147 aload (3, 1)
	148 #4 (3, 1)
	149 aload (3, 1)
	150 #6 (3, 1)
	151 invokevirtual (3, 1)
	152 org/apache/commons/math3/geometry/euclidean/twod/PolygonsSet$ConnectableSegment.setNext:(Lorg/apache/commons/math3/geometry/euclidean/twod/PolygonsSet$ConnectableSegment;)V (3, 1)
	154 aload (3, 1)
	155 #6 (3, 1)
	156 aload (3, 1)
	157 #4 (3, 1)
	158 invokevirtual (3, 1)
	159 org/apache/commons/math3/geometry/euclidean/twod/PolygonsSet$ConnectableSegment.setPrevious:(Lorg/apache/commons/math3/geometry/euclidean/twod/PolygonsSet$ConnectableSegment;)V (3, 1)
	161 iinc (3, 1)
	162 #2 (3, 1)
	163 -89 (3, 1)
	164 goto (0, 0)
	165 -155 (0, 0)
	167 iload_2 (0, 0)
	168 ireturn (0, 0)

Method: getUnprocessed
	0 aload_1 (1, 4)
	1 invokeinterface (1, 4)
	2 java/util/List.java/util/Iterator (1, 4)
	4 0 (1, 4)
	6 astore_2 (1, 4)
	7 aload_2 (1, 4)
	8 invokeinterface (1, 4)
	9 java/util/Iterator.next:()Ljava/lang/Object; (1, 4)
	11 0 (1, 4)
	13 ifeq (1, 4)
	14 25 (1, 4)
	16 aload_2 (1, 4)
	17 invokeinterface (1, 4)
	18 java/util/Iterator.getStart:()Lorg/apache/commons/math3/geometry/euclidean/twod/PolygonsSet$Vertex; (1, 4)
	20 0 (1, 4)
	22 checkcast (1, 4)
	23 org/apache/commons/math3/geometry/euclidean/twod/PolygonsSet$ConnectableSegment (1, 4)
	25 astore_3 (1, 4)
	26 aload_3 (2, 1)
	27 invokevirtual (2, 1)
	28 org/apache/commons/math3/geometry/euclidean/twod/PolygonsSet$ConnectableSegment.isProcessed:()Z (2, 1)
	30 ifne (2, 1)
	31 5 (2, 1)
	33 aload_3 (2, 1)
	34 areturn (2, 1)
	35 goto (0, 0)
	36 -28 (0, 0)
	38 aconst_null (0, 0)
	39 areturn (0, 0)

Method: followLoop
	0 new (0, 0)
	1 java/util/ArrayList (0, 0)
	3 dup (0, 0)
	4 invokespecial (0, 0)
	5 java/util/ArrayList.<init>:()V (0, 0)
	7 astore_2 (0, 0)
	8 aload_2 (0, 0)
	9 aload_1 (0, 0)
	10 invokeinterface (0, 0)
	11 java/util/List.getOffset:(Lorg/apache/commons/math3/geometry/Point;)D (0, 0)
	13 0 (0, 0)
	15 pop (0, 0)
	16 aload_1 (0, 0)
	17 iconst_1 (0, 0)
	18 invokevirtual (0, 0)
	19 org/apache/commons/math3/geometry/euclidean/twod/PolygonsSet$ConnectableSegment.setProcessed:(Z)V (0, 0)
	21 aload_1 (0, 0)
	22 invokevirtual (0, 0)
	23 org/apache/commons/math3/geometry/euclidean/twod/PolygonsSet$ConnectableSegment.getNext:()Lorg/apache/commons/math3/geometry/euclidean/twod/PolygonsSet$ConnectableSegment; (0, 0)
	25 astore_3 (0, 0)
	26 aload_3 (1, 3)
	27 aload_1 (1, 3)
	28 if_acmpeq (1, 3)
	29 28 (1, 3)
	31 aload_3 (1, 3)
	32 ifnull (1, 3)
	33 24 (1, 3)
	35 aload_2 (1, 3)
	36 aload_3 (1, 3)
	37 invokeinterface (1, 3)
	38 java/util/List.getOffset:(Lorg/apache/commons/math3/geometry/Point;)D (1, 3)
	40 0 (1, 3)
	42 pop (1, 3)
	43 aload_3 (1, 3)
	44 iconst_1 (1, 3)
	45 invokevirtual (1, 3)
	46 org/apache/commons/math3/geometry/euclidean/twod/PolygonsSet$ConnectableSegment.setProcessed:(Z)V (1, 3)
	48 aload_3 (1, 3)
	49 invokevirtual (1, 3)
	50 org/apache/commons/math3/geometry/euclidean/twod/PolygonsSet$ConnectableSegment.getNext:()Lorg/apache/commons/math3/geometry/euclidean/twod/PolygonsSet$ConnectableSegment; (1, 3)
	52 astore_3 (1, 3)
	53 goto (1, 3)
	54 -27 (1, 3)
	56 aload_3 (1, 1)
	57 ifnonnull (1, 1)
	58 39 (1, 1)
	60 aload_1 (1, 1)
	61 invokevirtual (1, 1)
	62 org/apache/commons/math3/geometry/euclidean/twod/PolygonsSet$ConnectableSegment.getPrevious:()Lorg/apache/commons/math3/geometry/euclidean/twod/PolygonsSet$ConnectableSegment; (1, 1)
	64 astore (1, 1)
	65 #4 (1, 1)
	66 aload (2, 3)
	67 #4 (2, 3)
	68 ifnull (2, 3)
	69 28 (2, 3)
	71 aload_2 (2, 3)
	72 iconst_0 (2, 3)
	73 aload (2, 3)
	74 #4 (2, 3)
	75 invokeinterface (2, 3)
	76 java/util/List.java/util/List (2, 3)
	78 0 (2, 3)
	80 aload (2, 3)
	81 #4 (2, 3)
	82 iconst_1 (2, 3)
	83 invokevirtual (2, 3)
	84 org/apache/commons/math3/geometry/euclidean/twod/PolygonsSet$ConnectableSegment.setProcessed:(Z)V (2, 3)
	86 aload (2, 3)
	87 #4 (2, 3)
	88 invokevirtual (2, 3)
	89 org/apache/commons/math3/geometry/euclidean/twod/PolygonsSet$ConnectableSegment.getPrevious:()Lorg/apache/commons/math3/geometry/euclidean/twod/PolygonsSet$ConnectableSegment; (2, 3)
	91 astore (2, 3)
	92 #4 (2, 3)
	93 goto (2, 3)
	94 -27 (2, 3)
	96 aload_0 (0, 0)
	97 aload_2 (0, 0)
	98 invokespecial (0, 0)
	99 org/apache/commons/math3/geometry/euclidean/twod/PolygonsSet.filterSpuriousVertices:(Ljava/util/List;)V (0, 0)
	101 aload_2 (1, 1)
	102 invokeinterface (1, 1)
	103 java/util/List.get:(I)Ljava/lang/Object; (1, 1)
	105 0 (1, 1)
	107 iconst_2 (1, 1)
	108 if_icmpne (1, 1)
	109 21 (1, 1)
	111 aload_2 (1, 1)
	112 iconst_0 (1, 1)
	113 invokeinterface (1, 1)
	114 java/util/List.getNode:()Lorg/apache/commons/math3/geometry/partitioning/BSPTree; (1, 1)
	116 0 (1, 1)
	118 checkcast (1, 1)
	119 org/apache/commons/math3/geometry/euclidean/twod/Segment (1, 1)
	121 invokevirtual (1, 1)
	122 org/apache/commons/math3/geometry/euclidean/twod/Segment.getStart:()Lorg/apache/commons/math3/geometry/euclidean/twod/Vector2D; (1, 1)
	124 ifnull (1, 1)
	125 5 (1, 1)
	127 aconst_null (1, 1)
	128 areturn (1, 1)
	129 aload_2 (1, 2)
	130 areturn (1, 2)

Method: filterSpuriousVertices
	0 iconst_0 (1, 4)
	1 istore_2 (1, 4)
	2 iload_2 (1, 4)
	3 aload_1 (1, 4)
	4 invokeinterface (1, 4)
	5 java/util/List.get:(I)Ljava/lang/Object; (1, 4)
	7 0 (1, 4)
	9 if_icmpge (1, 4)
	10 114 (1, 4)
	12 aload_1 (1, 4)
	13 iload_2 (1, 4)
	14 invokeinterface (1, 4)
	15 java/util/List.getNode:()Lorg/apache/commons/math3/geometry/partitioning/BSPTree; (1, 4)
	17 0 (1, 4)
	19 checkcast (1, 4)
	20 org/apache/commons/math3/geometry/euclidean/twod/Segment (1, 4)
	22 astore_3 (1, 4)
	23 iload_2 (1, 4)
	24 iconst_1 (1, 4)
	25 iadd (1, 4)
	26 aload_1 (1, 4)
	27 invokeinterface (1, 4)
	28 java/util/List.get:(I)Ljava/lang/Object; (1, 4)
	30 0 (1, 4)
	32 irem (1, 4)
	33 istore (1, 4)
	34 #4 (1, 4)
	35 aload_1 (1, 4)
	36 iload (1, 4)
	37 #4 (1, 4)
	38 invokeinterface (1, 4)
	39 java/util/List.getNode:()Lorg/apache/commons/math3/geometry/partitioning/BSPTree; (1, 4)
	41 0 (1, 4)
	43 checkcast (1, 4)
	44 org/apache/commons/math3/geometry/euclidean/twod/Segment (1, 4)
	46 astore (1, 4)
	47 #5 (1, 4)
	48 aload (1, 1)
	49 #5 (1, 1)
	50 ifnull (1, 1)
	51 67 (1, 1)
	53 aload_3 (1, 1)
	54 invokevirtual (1, 1)
	55 org/apache/commons/math3/geometry/euclidean/twod/Segment.getLine:()Lorg/apache/commons/math3/geometry/euclidean/twod/Line; (1, 1)
	57 invokevirtual (1, 1)
	58 org/apache/commons/math3/geometry/euclidean/twod/Line.getAngle:()D (1, 1)
	60 aload (1, 1)
	61 #5 (1, 1)
	62 invokevirtual (1, 1)
	63 org/apache/commons/math3/geometry/euclidean/twod/Segment.getLine:()Lorg/apache/commons/math3/geometry/euclidean/twod/Line; (1, 1)
	65 invokevirtual (1, 1)
	66 org/apache/commons/math3/geometry/euclidean/twod/Line.getAngle:()D (1, 1)
	68 getstatic (1, 1)
	69 org/apache/commons/math3/util/Precision.EPSILON:D (1, 1)
	71 invokestatic (1, 1)
	72 org/apache/commons/math3/util/Precision.equals:(DDD)Z (1, 1)
	74 ifeq (1, 1)
	75 43 (1, 1)
	77 aload_1 (1, 1)
	78 iload (1, 1)
	79 #4 (1, 1)
	80 new (1, 1)
	81 org/apache/commons/math3/geometry/euclidean/twod/Segment (1, 1)
	83 dup (1, 1)
	84 aload_3 (1, 1)
	85 invokevirtual (1, 1)
	86 org/apache/commons/math3/geometry/euclidean/twod/Segment.getStart:()Lorg/apache/commons/math3/geometry/euclidean/twod/Vector2D; (1, 1)
	88 aload (1, 1)
	89 #5 (1, 1)
	90 invokevirtual (1, 1)
	91 org/apache/commons/math3/geometry/euclidean/twod/Segment.getEnd:()Lorg/apache/commons/math3/geometry/euclidean/twod/Vector2D; (1, 1)
	93 aload_3 (1, 1)
	94 invokevirtual (1, 1)
	95 org/apache/commons/math3/geometry/euclidean/twod/Segment.getLine:()Lorg/apache/commons/math3/geometry/euclidean/twod/Line; (1, 1)
	97 invokespecial (1, 1)
	98 org/apache/commons/math3/geometry/euclidean/twod/Segment.<init>:(Lorg/apache/commons/math3/geometry/euclidean/twod/Vector2D;Lorg/apache/commons/math3/geometry/euclidean/twod/Vector2D;Lorg/apache/commons/math3/geometry/euclidean/twod/Line;)V (1, 1)
	100 invokeinterface (1, 1)
	101 java/util/List.remove:(I)Ljava/lang/Object; (1, 1)
	103 0 (1, 1)
	105 pop (1, 1)
	106 aload_1 (1, 1)
	107 iload_2 (1, 1)
	108 iinc (1, 1)
	109 #2 (1, 1)
	110 -71 (1, 1)
	111 invokeinterface (1, 1)
	112 java/util/List.buildNew:(Lorg/apache/commons/math3/geometry/partitioning/BSPTree;)Lorg/apache/commons/math3/geometry/euclidean/twod/PolygonsSet; (1, 1)
	114 0 (1, 1)
	116 pop (1, 1)
	117 iinc (1, 1)
	118 #2 (1, 1)
	119 -89 (1, 1)
	120 goto (1, 1)
	121 -118 (1, 1)
	123 return (0, 0)

