Method: <init>
	0 aload_0 (0, 0)
	1 invokespecial (0, 0)
	2 java/lang/Object.<init>:()V (0, 0)
	4 aload_0 (0, 0)
	5 aload_1 (0, 0)
	6 putfield (0, 0)
	7 org/apache/commons/math3/geometry/euclidean/twod/Segment.start:Lorg/apache/commons/math3/geometry/euclidean/twod/Vector2D; (0, 0)
	9 aload_0 (0, 0)
	10 aload_2 (0, 0)
	11 putfield (0, 0)
	12 org/apache/commons/math3/geometry/euclidean/twod/Segment.end:Lorg/apache/commons/math3/geometry/euclidean/twod/Vector2D; (0, 0)
	14 aload_0 (0, 0)
	15 aload_3 (0, 0)
	16 putfield (0, 0)
	17 org/apache/commons/math3/geometry/euclidean/twod/Segment.line:Lorg/apache/commons/math3/geometry/euclidean/twod/Line; (0, 0)
	19 return (0, 0)

Method: getStart
	0 aload_0 (0, 0)
	1 getfield (0, 0)
	2 org/apache/commons/math3/geometry/euclidean/twod/Segment.start:Lorg/apache/commons/math3/geometry/euclidean/twod/Vector2D; (0, 0)
	4 areturn (0, 0)

Method: getEnd
	0 aload_0 (0, 0)
	1 getfield (0, 0)
	2 org/apache/commons/math3/geometry/euclidean/twod/Segment.end:Lorg/apache/commons/math3/geometry/euclidean/twod/Vector2D; (0, 0)
	4 areturn (0, 0)

Method: getLine
	0 aload_0 (0, 0)
	1 getfield (0, 0)
	2 org/apache/commons/math3/geometry/euclidean/twod/Segment.line:Lorg/apache/commons/math3/geometry/euclidean/twod/Line; (0, 0)
	4 areturn (0, 0)

Method: distance
	0 aload_0 (0, 0)
	1 getfield (0, 0)
	2 org/apache/commons/math3/geometry/euclidean/twod/Segment.end:Lorg/apache/commons/math3/geometry/euclidean/twod/Vector2D; (0, 0)
	4 invokevirtual (0, 0)
	5 org/apache/commons/math3/geometry/euclidean/twod/Vector2D.getX:()D (0, 0)
	7 aload_0 (0, 0)
	8 getfield (0, 0)
	9 org/apache/commons/math3/geometry/euclidean/twod/Segment.start:Lorg/apache/commons/math3/geometry/euclidean/twod/Vector2D; (0, 0)
	11 invokevirtual (0, 0)
	12 org/apache/commons/math3/geometry/euclidean/twod/Vector2D.getX:()D (0, 0)
	14 dsub (0, 0)
	15 dstore_2 (0, 0)
	16 aload_0 (0, 0)
	17 getfield (0, 0)
	18 org/apache/commons/math3/geometry/euclidean/twod/Segment.end:Lorg/apache/commons/math3/geometry/euclidean/twod/Vector2D; (0, 0)
	20 invokevirtual (0, 0)
	21 org/apache/commons/math3/geometry/euclidean/twod/Vector2D.getY:()D (0, 0)
	23 aload_0 (0, 0)
	24 getfield (0, 0)
	25 org/apache/commons/math3/geometry/euclidean/twod/Segment.start:Lorg/apache/commons/math3/geometry/euclidean/twod/Vector2D; (0, 0)
	27 invokevirtual (0, 0)
	28 org/apache/commons/math3/geometry/euclidean/twod/Vector2D.getY:()D (0, 0)
	30 dsub (0, 0)
	31 dstore (0, 0)
	32 #4 (0, 0)
	33 aload_1 (0, 0)
	34 invokevirtual (0, 0)
	35 org/apache/commons/math3/geometry/euclidean/twod/Vector2D.getX:()D (0, 0)
	37 aload_0 (0, 0)
	38 getfield (0, 0)
	39 org/apache/commons/math3/geometry/euclidean/twod/Segment.start:Lorg/apache/commons/math3/geometry/euclidean/twod/Vector2D; (0, 0)
	41 invokevirtual (0, 0)
	42 org/apache/commons/math3/geometry/euclidean/twod/Vector2D.getX:()D (0, 0)
	44 dsub (0, 0)
	45 dload_2 (0, 0)
	46 dmul (0, 0)
	47 aload_1 (0, 0)
	48 invokevirtual (0, 0)
	49 org/apache/commons/math3/geometry/euclidean/twod/Vector2D.getY:()D (0, 0)
	51 aload_0 (0, 0)
	52 getfield (0, 0)
	53 org/apache/commons/math3/geometry/euclidean/twod/Segment.start:Lorg/apache/commons/math3/geometry/euclidean/twod/Vector2D; (0, 0)
	55 invokevirtual (0, 0)
	56 org/apache/commons/math3/geometry/euclidean/twod/Vector2D.getY:()D (0, 0)
	58 dsub (0, 0)
	59 dload (0, 0)
	60 #4 (0, 0)
	61 dmul (0, 0)
	62 dadd (0, 0)
	63 dload_2 (0, 0)
	64 dload_2 (0, 0)
	65 dmul (0, 0)
	66 dload (0, 0)
	67 #4 (0, 0)
	68 dload (0, 0)
	69 #4 (0, 0)
	70 dmul (0, 0)
	71 dadd (0, 0)
	72 ddiv (0, 0)
	73 dstore (0, 0)
	74 #6 (0, 0)
	75 dload (1, 1)
	76 #6 (1, 1)
	77 dconst_0 (1, 1)
	78 dcmpg (1, 1)
	79 iflt (1, 1)
	80 10 (1, 1)
	82 dload (1, 1)
	83 #6 (1, 1)
	84 dconst_1 (1, 1)
	85 dcmpl (1, 1)
	86 ifle (1, 1)
	87 31 (1, 1)
	89 aload_0 (1, 1)
	90 invokevirtual (1, 1)
	91 org/apache/commons/math3/geometry/euclidean/twod/Segment.getStart:()Lorg/apache/commons/math3/geometry/euclidean/twod/Vector2D; (1, 1)
	93 aload_1 (1, 1)
	94 invokevirtual (1, 1)
	95 org/apache/commons/math3/geometry/euclidean/twod/Vector2D.distance:(Lorg/apache/commons/math3/geometry/Point;)D (1, 1)
	97 dstore (1, 1)
	98 #8 (1, 1)
	99 aload_0 (1, 1)
	100 invokevirtual (1, 1)
	101 org/apache/commons/math3/geometry/euclidean/twod/Segment.getEnd:()Lorg/apache/commons/math3/geometry/euclidean/twod/Vector2D; (1, 1)
	103 aload_1 (1, 1)
	104 invokevirtual (1, 1)
	105 org/apache/commons/math3/geometry/euclidean/twod/Vector2D.distance:(Lorg/apache/commons/math3/geometry/Point;)D (1, 1)
	107 dstore (1, 1)
	108 #10 (1, 1)
	109 dload (1, 1)
	110 #8 (1, 1)
	111 dload (1, 1)
	112 #10 (1, 1)
	113 invokestatic (1, 1)
	114 org/apache/commons/math3/util/FastMath.min:(DD)D (1, 1)
	116 dreturn (1, 1)
	117 aload_0 (1, 1)
	118 getfield (1, 1)
	119 org/apache/commons/math3/geometry/euclidean/twod/Segment.start:Lorg/apache/commons/math3/geometry/euclidean/twod/Vector2D; (1, 1)
	121 invokevirtual (1, 1)
	122 org/apache/commons/math3/geometry/euclidean/twod/Vector2D.getX:()D (1, 1)
	124 dload (1, 1)
	125 #6 (1, 1)
	126 dload_2 (1, 1)
	127 dmul (1, 1)
	128 dadd (1, 1)
	129 dstore (1, 1)
	130 #8 (1, 1)
	131 aload_0 (1, 1)
	132 getfield (1, 1)
	133 org/apache/commons/math3/geometry/euclidean/twod/Segment.start:Lorg/apache/commons/math3/geometry/euclidean/twod/Vector2D; (1, 1)
	135 invokevirtual (1, 1)
	136 org/apache/commons/math3/geometry/euclidean/twod/Vector2D.getY:()D (1, 1)
	138 dload (1, 1)
	139 #6 (1, 1)
	140 dload (1, 1)
	141 #4 (1, 1)
	142 dmul (1, 1)
	143 dadd (1, 1)
	144 dstore (1, 1)
	145 #10 (1, 1)
	146 new (1, 1)
	147 org/apache/commons/math3/geometry/euclidean/twod/Vector2D (1, 1)
	149 dup (1, 1)
	150 dload (1, 1)
	151 #8 (1, 1)
	152 dload (1, 1)
	153 #10 (1, 1)
	154 invokespecial (1, 1)
	155 org/apache/commons/math3/geometry/euclidean/twod/Vector2D.<init>:(DD)V (1, 1)
	157 astore (1, 1)
	158 #12 (1, 1)
	159 aload (1, 1)
	160 #12 (1, 1)
	161 aload_1 (1, 1)
	162 invokevirtual (1, 1)
	163 org/apache/commons/math3/geometry/euclidean/twod/Vector2D.distance:(Lorg/apache/commons/math3/geometry/Point;)D (1, 1)
	165 dreturn (1, 1)

