Method: <init>
	0 aload_0 (0, 0)
	1 aload_1 (0, 0)
	2 invokevirtual (0, 0)
	3 org/apache/commons/math3/geometry/euclidean/twod/Segment.getLine:()Lorg/apache/commons/math3/geometry/euclidean/twod/Line; (0, 0)
	5 aload_1 (0, 0)
	6 invokevirtual (0, 0)
	7 org/apache/commons/math3/geometry/euclidean/twod/Segment.getStart:()Lorg/apache/commons/math3/geometry/euclidean/twod/Vector2D; (0, 0)
	9 aload_1 (0, 0)
	10 invokevirtual (0, 0)
	11 org/apache/commons/math3/geometry/euclidean/twod/Segment.getEnd:()Lorg/apache/commons/math3/geometry/euclidean/twod/Vector2D; (0, 0)
	13 aload_1 (0, 0)
	14 invokevirtual (0, 0)
	15 org/apache/commons/math3/geometry/euclidean/twod/Segment.getLine:()Lorg/apache/commons/math3/geometry/euclidean/twod/Line; (0, 0)
	17 invokevirtual (0, 0)
	18 org/apache/commons/math3/geometry/euclidean/twod/Line.getTolerance:()D (0, 0)
	20 invokestatic (0, 0)
	21 org/apache/commons/math3/geometry/euclidean/twod/SubLine.buildIntervalSet:(Lorg/apache/commons/math3/geometry/euclidean/twod/Vector2D;Lorg/apache/commons/math3/geometry/euclidean/twod/Vector2D;D)Lorg/apache/commons/math3/geometry/euclidean/oned/IntervalsSet; (0, 0)
	23 invokespecial (0, 0)
	24 org/apache/commons/math3/geometry/partitioning/AbstractSubHyperplane.<init>:(Lorg/apache/commons/math3/geometry/partitioning/Hyperplane;Lorg/apache/commons/math3/geometry/partitioning/Region;)V (0, 0)
	26 return (0, 0)

Method: getSegments
	0 aload_0 (0, 0)
	1 invokevirtual (0, 0)
	2 org/apache/commons/math3/geometry/euclidean/twod/SubLine.getHyperplane:()Lorg/apache/commons/math3/geometry/partitioning/Hyperplane; (0, 0)
	4 checkcast (0, 0)
	5 org/apache/commons/math3/geometry/euclidean/twod/Line (0, 0)
	7 astore_1 (0, 0)
	8 aload_0 (0, 0)
	9 invokevirtual (0, 0)
	10 org/apache/commons/math3/geometry/euclidean/twod/SubLine.getRemainingRegion:()Lorg/apache/commons/math3/geometry/partitioning/Region; (0, 0)
	12 checkcast (0, 0)
	13 org/apache/commons/math3/geometry/euclidean/oned/IntervalsSet (0, 0)
	15 invokevirtual (0, 0)
	16 org/apache/commons/math3/geometry/euclidean/oned/IntervalsSet.asList:()Ljava/util/List; (0, 0)
	18 astore_2 (0, 0)
	19 new (0, 0)
	20 java/util/ArrayList (0, 0)
	22 dup (0, 0)
	23 aload_2 (0, 0)
	24 invokeinterface (0, 0)
	25 java/util/List.<init>:(I)V (0, 0)
	27 0 (0, 0)
	29 invokespecial (0, 0)
	30 java/util/ArrayList.<init>:(I)V (0, 0)
	32 astore_3 (0, 0)
	33 aload_2 (1, 4)
	34 invokeinterface (1, 4)
	35 java/util/List.java/util/Iterator (1, 4)
	37 0 (1, 4)
	39 astore (1, 4)
	40 #4 (1, 4)
	41 aload (1, 4)
	42 #4 (1, 4)
	43 invokeinterface (1, 4)
	44 java/util/Iterator.next:()Ljava/lang/Object; (1, 4)
	46 0 (1, 4)
	48 ifeq (1, 4)
	49 73 (1, 4)
	51 aload (1, 4)
	52 #4 (1, 4)
	53 invokeinterface (1, 4)
	54 java/util/Iterator.org/apache/commons/math3/geometry/euclidean/oned/Interval (1, 4)
	56 0 (1, 4)
	58 checkcast (1, 4)
	59 org/apache/commons/math3/geometry/euclidean/oned/Interval (1, 4)
	61 astore (1, 4)
	62 #5 (1, 4)
	63 aload_1 (1, 4)
	64 new (1, 4)
	65 org/apache/commons/math3/geometry/euclidean/oned/Vector1D (1, 4)
	67 dup (1, 4)
	68 aload (1, 4)
	69 #5 (1, 4)
	70 invokevirtual (1, 4)
	71 org/apache/commons/math3/geometry/euclidean/oned/Interval.getInf:()D (1, 4)
	73 invokespecial (1, 4)
	74 org/apache/commons/math3/geometry/euclidean/oned/Vector1D.<init>:(D)V (1, 4)
	76 invokevirtual (1, 4)
	77 org/apache/commons/math3/geometry/euclidean/twod/Line.toSpace:(Lorg/apache/commons/math3/geometry/Point;)Lorg/apache/commons/math3/geometry/euclidean/twod/Vector2D; (1, 4)
	79 astore (1, 4)
	80 #6 (1, 4)
	81 aload_1 (1, 4)
	82 new (1, 4)
	83 org/apache/commons/math3/geometry/euclidean/oned/Vector1D (1, 4)
	85 dup (1, 4)
	86 aload (1, 4)
	87 #5 (1, 4)
	88 invokevirtual (1, 4)
	89 org/apache/commons/math3/geometry/euclidean/oned/Interval.getSup:()D (1, 4)
	91 invokespecial (1, 4)
	92 org/apache/commons/math3/geometry/euclidean/oned/Vector1D.<init>:(D)V (1, 4)
	94 invokevirtual (1, 4)
	95 org/apache/commons/math3/geometry/euclidean/twod/Line.toSpace:(Lorg/apache/commons/math3/geometry/Point;)Lorg/apache/commons/math3/geometry/euclidean/twod/Vector2D; (1, 4)
	97 astore (1, 4)
	98 #7 (1, 4)
	99 aload_3 (1, 4)
	100 new (1, 4)
	101 org/apache/commons/math3/geometry/euclidean/twod/Segment (1, 4)
	103 dup (1, 4)
	104 aload (1, 4)
	105 #6 (1, 4)
	106 aload (1, 4)
	107 #7 (1, 4)
	108 aload_1 (1, 4)
	109 invokespecial (1, 4)
	110 org/apache/commons/math3/geometry/euclidean/twod/Segment.<init>:(Lorg/apache/commons/math3/geometry/euclidean/twod/Vector2D;Lorg/apache/commons/math3/geometry/euclidean/twod/Vector2D;Lorg/apache/commons/math3/geometry/euclidean/twod/Line;)V (1, 4)
	112 invokeinterface (1, 4)
	113 java/util/List.intersection:(Lorg/apache/commons/math3/geometry/euclidean/twod/Line;)Lorg/apache/commons/math3/geometry/euclidean/twod/Vector2D; (1, 4)
	115 0 (1, 4)
	117 pop (1, 4)
	118 goto (0, 0)
	119 -77 (0, 0)
	121 aload_3 (0, 0)
	122 areturn (0, 0)

Method: intersection
	0 aload_0 (0, 0)
	1 invokevirtual (0, 0)
	2 org/apache/commons/math3/geometry/euclidean/twod/SubLine.getHyperplane:()Lorg/apache/commons/math3/geometry/partitioning/Hyperplane; (0, 0)
	4 checkcast (0, 0)
	5 org/apache/commons/math3/geometry/euclidean/twod/Line (0, 0)
	7 astore_3 (0, 0)
	8 aload_1 (0, 0)
	9 invokevirtual (0, 0)
	10 org/apache/commons/math3/geometry/euclidean/twod/SubLine.getHyperplane:()Lorg/apache/commons/math3/geometry/partitioning/Hyperplane; (0, 0)
	12 checkcast (0, 0)
	13 org/apache/commons/math3/geometry/euclidean/twod/Line (0, 0)
	15 astore (0, 0)
	16 #4 (0, 0)
	17 aload_3 (0, 0)
	18 aload (0, 0)
	19 #4 (0, 0)
	20 invokevirtual (0, 0)
	21 org/apache/commons/math3/geometry/euclidean/twod/Line.intersection:(Lorg/apache/commons/math3/geometry/euclidean/twod/Line;)Lorg/apache/commons/math3/geometry/euclidean/twod/Vector2D; (0, 0)
	23 astore (0, 0)
	24 #5 (0, 0)
	25 aload (1, 1)
	26 #5 (1, 1)
	27 ifnonnull (1, 1)
	28 5 (1, 1)
	30 aconst_null (1, 1)
	31 areturn (1, 1)
	32 aload_0 (0, 0)
	33 invokevirtual (0, 0)
	34 org/apache/commons/math3/geometry/euclidean/twod/SubLine.getRemainingRegion:()Lorg/apache/commons/math3/geometry/partitioning/Region; (0, 0)
	36 aload_3 (0, 0)
	37 aload (0, 0)
	38 #5 (0, 0)
	39 invokevirtual (0, 0)
	40 org/apache/commons/math3/geometry/euclidean/twod/Line.toSubSpace:(Lorg/apache/commons/math3/geometry/Point;)Lorg/apache/commons/math3/geometry/euclidean/oned/Vector1D; (0, 0)
	42 invokeinterface (0, 0)
	43 org/apache/commons/math3/geometry/partitioning/Region.OUTSIDE:Lorg/apache/commons/math3/geometry/partitioning/Region$Location; (0, 0)
	45 0 (0, 0)
	47 astore (0, 0)
	48 #6 (0, 0)
	49 aload_1 (0, 0)
	50 invokevirtual (0, 0)
	51 org/apache/commons/math3/geometry/euclidean/twod/SubLine.getRemainingRegion:()Lorg/apache/commons/math3/geometry/partitioning/Region; (0, 0)
	53 aload (0, 0)
	54 #4 (0, 0)
	55 aload (0, 0)
	56 #5 (0, 0)
	57 invokevirtual (0, 0)
	58 org/apache/commons/math3/geometry/euclidean/twod/Line.toSubSpace:(Lorg/apache/commons/math3/geometry/Point;)Lorg/apache/commons/math3/geometry/euclidean/oned/Vector1D; (0, 0)
	60 invokeinterface (0, 0)
	61 org/apache/commons/math3/geometry/partitioning/Region.OUTSIDE:Lorg/apache/commons/math3/geometry/partitioning/Region$Location; (0, 0)
	63 0 (0, 0)
	65 astore (0, 0)
	66 #7 (0, 0)
	67 iload_2 (1, 1)
	68 ifeq (1, 1)
	69 26 (1, 1)
	71 aload (1, 1)
	72 #6 (1, 1)
	73 getstatic (1, 1)
	74 org/apache/commons/math3/geometry/partitioning/Region$Location.OUTSIDE:Lorg/apache/commons/math3/geometry/partitioning/Region$Location; (1, 1)
	76 if_acmpeq (1, 1)
	77 16 (1, 1)
	79 aload (1, 1)
	80 #7 (1, 1)
	81 getstatic (1, 1)
	82 org/apache/commons/math3/geometry/partitioning/Region$Location.OUTSIDE:Lorg/apache/commons/math3/geometry/partitioning/Region$Location; (1, 1)
	84 if_acmpeq (1, 1)
	85 8 (1, 1)
	87 aload (1, 1)
	88 #5 (1, 1)
	89 goto (1, 1)
	90 4 (1, 1)
	92 aconst_null (1, 1)
	93 areturn (1, 1)
	94 aload (1, 2)
	95 #6 (1, 2)
	96 getstatic (1, 2)
	97 org/apache/commons/math3/geometry/partitioning/Region$Location.INSIDE:Lorg/apache/commons/math3/geometry/partitioning/Region$Location; (1, 2)
	99 if_acmpne (1, 2)
	100 16 (1, 2)
	102 aload (1, 2)
	103 #7 (1, 2)
	104 getstatic (1, 2)
	105 org/apache/commons/math3/geometry/partitioning/Region$Location.INSIDE:Lorg/apache/commons/math3/geometry/partitioning/Region$Location; (1, 2)
	107 if_acmpne (1, 2)
	108 8 (1, 2)
	110 aload (1, 2)
	111 #5 (1, 2)
	112 goto (1, 2)
	113 4 (1, 2)
	115 aconst_null (1, 2)
	116 areturn (1, 2)

Method: buildIntervalSet
	0 new (0, 0)
	1 org/apache/commons/math3/geometry/euclidean/twod/Line (0, 0)
	3 dup (0, 0)
	4 aload_0 (0, 0)
	5 aload_1 (0, 0)
	6 dload_2 (0, 0)
	7 invokespecial (0, 0)
	8 org/apache/commons/math3/geometry/euclidean/twod/Line.<init>:(Lorg/apache/commons/math3/geometry/euclidean/twod/Vector2D;Lorg/apache/commons/math3/geometry/euclidean/twod/Vector2D;D)V (0, 0)
	10 astore (0, 0)
	11 #4 (0, 0)
	12 new (0, 0)
	13 org/apache/commons/math3/geometry/euclidean/oned/IntervalsSet (0, 0)
	15 dup (0, 0)
	16 aload (0, 0)
	17 #4 (0, 0)
	18 aload_0 (0, 0)
	19 invokevirtual (0, 0)
	20 org/apache/commons/math3/geometry/euclidean/twod/Line.toSubSpace:(Lorg/apache/commons/math3/geometry/Point;)Lorg/apache/commons/math3/geometry/euclidean/oned/Vector1D; (0, 0)
	22 invokevirtual (0, 0)
	23 org/apache/commons/math3/geometry/euclidean/oned/Vector1D.getX:()D (0, 0)
	25 aload (0, 0)
	26 #4 (0, 0)
	27 aload_1 (0, 0)
	28 invokevirtual (0, 0)
	29 org/apache/commons/math3/geometry/euclidean/twod/Line.toSubSpace:(Lorg/apache/commons/math3/geometry/Point;)Lorg/apache/commons/math3/geometry/euclidean/oned/Vector1D; (0, 0)
	31 invokevirtual (0, 0)
	32 org/apache/commons/math3/geometry/euclidean/oned/Vector1D.getX:()D (0, 0)
	34 dload_2 (0, 0)
	35 invokespecial (0, 0)
	36 org/apache/commons/math3/geometry/euclidean/oned/IntervalsSet.<init>:(DDD)V (0, 0)
	38 areturn (0, 0)

Method: buildNew
	0 new (0, 0)
	1 org/apache/commons/math3/geometry/euclidean/twod/SubLine (0, 0)
	3 dup (0, 0)
	4 aload_1 (0, 0)
	5 aload_2 (0, 0)
	6 invokespecial (0, 0)
	7 org/apache/commons/math3/geometry/euclidean/twod/SubLine.<init>:(Lorg/apache/commons/math3/geometry/partitioning/Hyperplane;Lorg/apache/commons/math3/geometry/partitioning/Region;)V (0, 0)
	9 areturn (0, 0)

Method: split
	0 aload_0 (0, 0)
	1 invokevirtual (0, 0)
	2 org/apache/commons/math3/geometry/euclidean/twod/SubLine.getHyperplane:()Lorg/apache/commons/math3/geometry/partitioning/Hyperplane; (0, 0)
	4 checkcast (0, 0)
	5 org/apache/commons/math3/geometry/euclidean/twod/Line (0, 0)
	7 astore_2 (0, 0)
	8 aload_1 (0, 0)
	9 checkcast (0, 0)
	10 org/apache/commons/math3/geometry/euclidean/twod/Line (0, 0)
	12 astore_3 (0, 0)
	13 aload_2 (0, 0)
	14 aload_3 (0, 0)
	15 invokevirtual (0, 0)
	16 org/apache/commons/math3/geometry/euclidean/twod/Line.intersection:(Lorg/apache/commons/math3/geometry/euclidean/twod/Line;)Lorg/apache/commons/math3/geometry/euclidean/twod/Vector2D; (0, 0)
	18 astore (0, 0)
	19 #4 (0, 0)
	20 aload_2 (0, 0)
	21 invokevirtual (0, 0)
	22 org/apache/commons/math3/geometry/euclidean/twod/Line.getTolerance:()D (0, 0)
	24 dstore (0, 0)
	25 #5 (0, 0)
	26 aload (1, 1)
	27 #4 (1, 1)
	28 ifnonnull (1, 1)
	29 57 (1, 1)
	31 aload_3 (1, 1)
	32 aload_2 (1, 1)
	33 invokevirtual (1, 1)
	34 org/apache/commons/math3/geometry/euclidean/twod/Line.getOffset:(Lorg/apache/commons/math3/geometry/euclidean/twod/Line;)D (1, 1)
	36 dstore (1, 1)
	37 #7 (1, 1)
	38 dload (2, 1)
	39 #7 (2, 1)
	40 dload (2, 1)
	41 #5 (2, 1)
	42 dneg (2, 1)
	43 dcmpg (2, 1)
	44 ifge (2, 1)
	45 13 (2, 1)
	47 new (2, 1)
	48 org/apache/commons/math3/geometry/partitioning/SubHyperplane$SplitSubHyperplane (2, 1)
	50 dup (2, 1)
	51 aconst_null (2, 1)
	52 aload_0 (2, 1)
	53 invokespecial (2, 1)
	54 org/apache/commons/math3/geometry/partitioning/SubHyperplane$SplitSubHyperplane.<init>:(Lorg/apache/commons/math3/geometry/partitioning/SubHyperplane;Lorg/apache/commons/math3/geometry/partitioning/SubHyperplane;)V (2, 1)
	56 areturn (2, 1)
	57 dload (2, 1)
	58 #7 (2, 1)
	59 dload (2, 1)
	60 #5 (2, 1)
	61 dcmpl (2, 1)
	62 ifle (2, 1)
	63 13 (2, 1)
	65 new (2, 1)
	66 org/apache/commons/math3/geometry/partitioning/SubHyperplane$SplitSubHyperplane (2, 1)
	68 dup (2, 1)
	69 aload_0 (2, 1)
	70 aconst_null (2, 1)
	71 invokespecial (2, 1)
	72 org/apache/commons/math3/geometry/partitioning/SubHyperplane$SplitSubHyperplane.<init>:(Lorg/apache/commons/math3/geometry/partitioning/SubHyperplane;Lorg/apache/commons/math3/geometry/partitioning/SubHyperplane;)V (2, 1)
	74 areturn (2, 1)
	75 new (2, 2)
	76 org/apache/commons/math3/geometry/partitioning/SubHyperplane$SplitSubHyperplane (2, 2)
	78 dup (2, 2)
	79 aconst_null (2, 2)
	80 aconst_null (2, 2)
	81 invokespecial (2, 2)
	82 org/apache/commons/math3/geometry/partitioning/SubHyperplane$SplitSubHyperplane.<init>:(Lorg/apache/commons/math3/geometry/partitioning/SubHyperplane;Lorg/apache/commons/math3/geometry/partitioning/SubHyperplane;)V (2, 2)
	84 areturn (2, 2)
	85 aload_2 (0, 0)
	86 invokevirtual (0, 0)
	87 org/apache/commons/math3/geometry/euclidean/twod/Line.getAngle:()D (0, 0)
	89 aload_3 (0, 0)
	90 invokevirtual (0, 0)
	91 org/apache/commons/math3/geometry/euclidean/twod/Line.getAngle:()D (0, 0)
	93 dsub (0, 0)
	94 invokestatic (0, 0)
	95 org/apache/commons/math3/util/FastMath.sin:(D)D (0, 0)
	97 dconst_0 (0, 0)
	98 dcmpg (0, 0)
	99 ifge (0, 0)
	100 7 (0, 0)
	102 iconst_1 (0, 0)
	103 goto (0, 0)
	104 4 (0, 0)
	106 iconst_0 (0, 0)
	107 istore (0, 0)
	108 #7 (0, 0)
	109 aload_2 (0, 0)
	110 aload (0, 0)
	111 #4 (0, 0)
	112 invokevirtual (0, 0)
	113 org/apache/commons/math3/geometry/euclidean/twod/Line.toSubSpace:(Lorg/apache/commons/math3/geometry/Point;)Lorg/apache/commons/math3/geometry/euclidean/oned/Vector1D; (0, 0)
	115 astore (0, 0)
	116 #8 (0, 0)
	117 new (0, 0)
	118 org/apache/commons/math3/geometry/euclidean/oned/OrientedPoint (0, 0)
	120 dup (0, 0)
	121 aload (0, 0)
	122 #8 (0, 0)
	123 iload (0, 0)
	124 #7 (0, 0)
	125 ifne (0, 0)
	126 7 (0, 0)
	128 iconst_1 (0, 0)
	129 goto (0, 0)
	130 4 (0, 0)
	132 iconst_0 (0, 0)
	133 dload (0, 0)
	134 #5 (0, 0)
	135 invokespecial (0, 0)
	136 org/apache/commons/math3/geometry/euclidean/oned/OrientedPoint.<init>:(Lorg/apache/commons/math3/geometry/euclidean/oned/Vector1D;ZD)V (0, 0)
	138 invokevirtual (0, 0)
	139 org/apache/commons/math3/geometry/euclidean/oned/OrientedPoint.wholeHyperplane:()Lorg/apache/commons/math3/geometry/euclidean/oned/SubOrientedPoint; (0, 0)
	141 astore (0, 0)
	142 #9 (0, 0)
	143 new (0, 0)
	144 org/apache/commons/math3/geometry/euclidean/oned/OrientedPoint (0, 0)
	146 dup (0, 0)
	147 aload (0, 0)
	148 #8 (0, 0)
	149 iload (0, 0)
	150 #7 (0, 0)
	151 dload (0, 0)
	152 #5 (0, 0)
	153 invokespecial (0, 0)
	154 org/apache/commons/math3/geometry/euclidean/oned/OrientedPoint.<init>:(Lorg/apache/commons/math3/geometry/euclidean/oned/Vector1D;ZD)V (0, 0)
	156 invokevirtual (0, 0)
	157 org/apache/commons/math3/geometry/euclidean/oned/OrientedPoint.wholeHyperplane:()Lorg/apache/commons/math3/geometry/euclidean/oned/SubOrientedPoint; (0, 0)
	159 astore (0, 0)
	160 #10 (0, 0)
	161 aload_0 (0, 0)
	162 invokevirtual (0, 0)
	163 org/apache/commons/math3/geometry/euclidean/twod/SubLine.getRemainingRegion:()Lorg/apache/commons/math3/geometry/partitioning/Region; (0, 0)
	165 iconst_0 (0, 0)
	166 invokeinterface (0, 0)
	167 org/apache/commons/math3/geometry/partitioning/Region.split:(Lorg/apache/commons/math3/geometry/partitioning/SubHyperplane;)Lorg/apache/commons/math3/geometry/partitioning/BSPTree; (0, 0)
	169 0 (0, 0)
	171 aload (0, 0)
	172 #10 (0, 0)
	173 invokevirtual (0, 0)
	174 org/apache/commons/math3/geometry/partitioning/BSPTree.split:(Lorg/apache/commons/math3/geometry/partitioning/SubHyperplane;)Lorg/apache/commons/math3/geometry/partitioning/BSPTree; (0, 0)
	176 astore (0, 0)
	177 #11 (0, 0)
	178 aload_0 (0, 0)
	179 invokevirtual (0, 0)
	180 org/apache/commons/math3/geometry/euclidean/twod/SubLine.getRemainingRegion:()Lorg/apache/commons/math3/geometry/partitioning/Region; (0, 0)
	182 aload (0, 0)
	183 #11 (0, 0)
	184 invokevirtual (0, 0)
	185 org/apache/commons/math3/geometry/partitioning/BSPTree.getPlus:()Lorg/apache/commons/math3/geometry/partitioning/BSPTree; (0, 0)
	187 invokeinterface (0, 0)
	188 org/apache/commons/math3/geometry/partitioning/Region.org/apache/commons/math3/geometry/partitioning/BSPTree (0, 0)
	190 0 (0, 0)
	192 ifeq (0, 0)
	193 16 (0, 0)
	195 new (0, 0)
	196 org/apache/commons/math3/geometry/partitioning/BSPTree (0, 0)
	198 dup (0, 0)
	199 getstatic (0, 0)
	200 java/lang/Boolean.FALSE:Ljava/lang/Boolean; (0, 0)
	202 invokespecial (0, 0)
	203 org/apache/commons/math3/geometry/partitioning/BSPTree.<init>:(Ljava/lang/Object;)V (0, 0)
	205 goto (0, 0)
	206 28 (0, 0)
	208 new (0, 0)
	209 org/apache/commons/math3/geometry/partitioning/BSPTree (0, 0)
	211 dup (0, 0)
	212 aload (0, 0)
	213 #9 (0, 0)
	214 new (0, 0)
	215 org/apache/commons/math3/geometry/partitioning/BSPTree (0, 0)
	217 dup (0, 0)
	218 getstatic (0, 0)
	219 java/lang/Boolean.FALSE:Ljava/lang/Boolean; (0, 0)
	221 invokespecial (0, 0)
	222 org/apache/commons/math3/geometry/partitioning/BSPTree.<init>:(Ljava/lang/Object;)V (0, 0)
	224 aload (0, 0)
	225 #11 (0, 0)
	226 invokevirtual (0, 0)
	227 org/apache/commons/math3/geometry/partitioning/BSPTree.getPlus:()Lorg/apache/commons/math3/geometry/partitioning/BSPTree; (0, 0)
	229 aconst_null (0, 0)
	230 invokespecial (0, 0)
	231 org/apache/commons/math3/geometry/partitioning/BSPTree.<init>:(Lorg/apache/commons/math3/geometry/partitioning/SubHyperplane;Lorg/apache/commons/math3/geometry/partitioning/BSPTree;Lorg/apache/commons/math3/geometry/partitioning/BSPTree;Ljava/lang/Object;)V (0, 0)
	233 astore (0, 0)
	234 #12 (0, 0)
	235 aload_0 (0, 0)
	236 invokevirtual (0, 0)
	237 org/apache/commons/math3/geometry/euclidean/twod/SubLine.getRemainingRegion:()Lorg/apache/commons/math3/geometry/partitioning/Region; (0, 0)
	239 aload (0, 0)
	240 #11 (0, 0)
	241 invokevirtual (0, 0)
	242 org/apache/commons/math3/geometry/partitioning/BSPTree.getMinus:()Lorg/apache/commons/math3/geometry/partitioning/BSPTree; (0, 0)
	244 invokeinterface (0, 0)
	245 org/apache/commons/math3/geometry/partitioning/Region.org/apache/commons/math3/geometry/partitioning/BSPTree (0, 0)
	247 0 (0, 0)
	249 ifeq (0, 0)
	250 16 (0, 0)
	252 new (0, 0)
	253 org/apache/commons/math3/geometry/partitioning/BSPTree (0, 0)
	255 dup (0, 0)
	256 getstatic (0, 0)
	257 java/lang/Boolean.FALSE:Ljava/lang/Boolean; (0, 0)
	259 invokespecial (0, 0)
	260 org/apache/commons/math3/geometry/partitioning/BSPTree.<init>:(Ljava/lang/Object;)V (0, 0)
	262 goto (0, 0)
	263 28 (0, 0)
	265 new (0, 0)
	266 org/apache/commons/math3/geometry/partitioning/BSPTree (0, 0)
	268 dup (0, 0)
	269 aload (0, 0)
	270 #10 (0, 0)
	271 new (0, 0)
	272 org/apache/commons/math3/geometry/partitioning/BSPTree (0, 0)
	274 dup (0, 0)
	275 getstatic (0, 0)
	276 java/lang/Boolean.FALSE:Ljava/lang/Boolean; (0, 0)
	278 invokespecial (0, 0)
	279 org/apache/commons/math3/geometry/partitioning/BSPTree.<init>:(Ljava/lang/Object;)V (0, 0)
	281 aload (0, 0)
	282 #11 (0, 0)
	283 invokevirtual (0, 0)
	284 org/apache/commons/math3/geometry/partitioning/BSPTree.getMinus:()Lorg/apache/commons/math3/geometry/partitioning/BSPTree; (0, 0)
	286 aconst_null (0, 0)
	287 invokespecial (0, 0)
	288 org/apache/commons/math3/geometry/partitioning/BSPTree.<init>:(Lorg/apache/commons/math3/geometry/partitioning/SubHyperplane;Lorg/apache/commons/math3/geometry/partitioning/BSPTree;Lorg/apache/commons/math3/geometry/partitioning/BSPTree;Ljava/lang/Object;)V (0, 0)
	290 astore (0, 0)
	291 #13 (0, 0)
	292 new (0, 0)
	293 org/apache/commons/math3/geometry/partitioning/SubHyperplane$SplitSubHyperplane (0, 0)
	295 dup (0, 0)
	296 new (0, 0)
	297 org/apache/commons/math3/geometry/euclidean/twod/SubLine (0, 0)
	299 dup (0, 0)
	300 aload_2 (0, 0)
	301 invokevirtual (0, 0)
	302 org/apache/commons/math3/geometry/euclidean/twod/Line.copySelf:()Lorg/apache/commons/math3/geometry/euclidean/twod/Line; (0, 0)
	304 new (0, 0)
	305 org/apache/commons/math3/geometry/euclidean/oned/IntervalsSet (0, 0)
	307 dup (0, 0)
	308 aload (0, 0)
	309 #12 (0, 0)
	310 dload (0, 0)
	311 #5 (0, 0)
	312 invokespecial (0, 0)
	313 org/apache/commons/math3/geometry/euclidean/oned/IntervalsSet.<init>:(Lorg/apache/commons/math3/geometry/partitioning/BSPTree;D)V (0, 0)
	315 invokespecial (0, 0)
	316 org/apache/commons/math3/geometry/euclidean/twod/SubLine.<init>:(Lorg/apache/commons/math3/geometry/partitioning/Hyperplane;Lorg/apache/commons/math3/geometry/partitioning/Region;)V (0, 0)
	318 new (0, 0)
	319 org/apache/commons/math3/geometry/euclidean/twod/SubLine (0, 0)
	321 dup (0, 0)
	322 aload_2 (0, 0)
	323 invokevirtual (0, 0)
	324 org/apache/commons/math3/geometry/euclidean/twod/Line.copySelf:()Lorg/apache/commons/math3/geometry/euclidean/twod/Line; (0, 0)
	326 new (0, 0)
	327 org/apache/commons/math3/geometry/euclidean/oned/IntervalsSet (0, 0)
	329 dup (0, 0)
	330 aload (0, 0)
	331 #13 (0, 0)
	332 dload (0, 0)
	333 #5 (0, 0)
	334 invokespecial (0, 0)
	335 org/apache/commons/math3/geometry/euclidean/oned/IntervalsSet.<init>:(Lorg/apache/commons/math3/geometry/partitioning/BSPTree;D)V (0, 0)
	337 invokespecial (0, 0)
	338 org/apache/commons/math3/geometry/euclidean/twod/SubLine.<init>:(Lorg/apache/commons/math3/geometry/partitioning/Hyperplane;Lorg/apache/commons/math3/geometry/partitioning/Region;)V (0, 0)
	340 invokespecial (0, 0)
	341 org/apache/commons/math3/geometry/partitioning/SubHyperplane$SplitSubHyperplane.<init>:(Lorg/apache/commons/math3/geometry/partitioning/SubHyperplane;Lorg/apache/commons/math3/geometry/partitioning/SubHyperplane;)V (0, 0)
	343 areturn (0, 0)

