Method: <init>
	0 aload_0 (0, 0)
	1 invokespecial (0, 0)
	2 java/lang/Object.<init>:()V (0, 0)
	4 aload_0 (0, 0)
	5 dload_1 (0, 0)
	6 aload_3 (0, 0)
	7 getfield (0, 0)
	8 org/apache/commons/math3/geometry/euclidean/twod/Vector2D.x:D (0, 0)
	10 dmul (0, 0)
	11 dload (0, 0)
	12 #4 (0, 0)
	13 aload (0, 0)
	14 #6 (0, 0)
	15 getfield (0, 0)
	16 org/apache/commons/math3/geometry/euclidean/twod/Vector2D.x:D (0, 0)
	18 dmul (0, 0)
	19 dadd (0, 0)
	20 dload (0, 0)
	21 #7 (0, 0)
	22 aload (0, 0)
	23 #9 (0, 0)
	24 getfield (0, 0)
	25 org/apache/commons/math3/geometry/euclidean/twod/Vector2D.x:D (0, 0)
	27 dmul (0, 0)
	28 dadd (0, 0)
	29 putfield (0, 0)
	30 org/apache/commons/math3/geometry/euclidean/twod/Vector2D.x:D (0, 0)
	32 aload_0 (0, 0)
	33 dload_1 (0, 0)
	34 aload_3 (0, 0)
	35 getfield (0, 0)
	36 org/apache/commons/math3/geometry/euclidean/twod/Vector2D.y:D (0, 0)
	38 dmul (0, 0)
	39 dload (0, 0)
	40 #4 (0, 0)
	41 aload (0, 0)
	42 #6 (0, 0)
	43 getfield (0, 0)
	44 org/apache/commons/math3/geometry/euclidean/twod/Vector2D.y:D (0, 0)
	46 dmul (0, 0)
	47 dadd (0, 0)
	48 dload (0, 0)
	49 #7 (0, 0)
	50 aload (0, 0)
	51 #9 (0, 0)
	52 getfield (0, 0)
	53 org/apache/commons/math3/geometry/euclidean/twod/Vector2D.y:D (0, 0)
	55 dmul (0, 0)
	56 dadd (0, 0)
	57 putfield (0, 0)
	58 org/apache/commons/math3/geometry/euclidean/twod/Vector2D.y:D (0, 0)
	60 return (0, 0)

