Method: <init>
	0 aload_0 (0, 0)
	1 dload_1 (0, 0)
	2 dload_3 (0, 0)
	3 dload (0, 0)
	4 #5 (0, 0)
	5 invokespecial (0, 0)
	6 org/apache/commons/math3/analysis/solvers/BaseAbstractUnivariateSolver.<init>:(DDD)V (0, 0)
	8 return (0, 0)

Method: computeObjectiveValueAndDerivative
	0 aload_0 (0, 0)
	1 invokevirtual (0, 0)
	2 org/apache/commons/math3/analysis/solvers/AbstractUnivariateDifferentiableSolver.incrementEvaluationCount:()V (0, 0)
	4 aload_0 (0, 0)
	5 getfield (0, 0)
	6 org/apache/commons/math3/analysis/solvers/AbstractUnivariateDifferentiableSolver.function:Lorg/apache/commons/math3/analysis/differentiation/UnivariateDifferentiableFunction; (0, 0)
	8 new (0, 0)
	9 org/apache/commons/math3/analysis/differentiation/DerivativeStructure (0, 0)
	11 dup (0, 0)
	12 iconst_1 (0, 0)
	13 iconst_1 (0, 0)
	14 iconst_0 (0, 0)
	15 dload_1 (0, 0)
	16 invokespecial (0, 0)
	17 org/apache/commons/math3/analysis/differentiation/DerivativeStructure.<init>:(IIID)V (0, 0)
	19 invokeinterface (0, 0)
	20 org/apache/commons/math3/analysis/differentiation/UnivariateDifferentiableFunction.setup:(ILorg/apache/commons/math3/analysis/UnivariateFunction;DDD)V (0, 0)
	22 0 (0, 0)
	24 areturn (0, 0)

Method: setup
	0 aload_0 (0, 1)
	1 iload_1 (0, 1)
	2 aload_2 (0, 1)
	3 checkcast (0, 1)
	4 org/apache/commons/math3/analysis/differentiation/UnivariateDifferentiableFunction (0, 1)
	6 dload_3 (0, 1)
	7 dload (0, 1)
	8 #5 (0, 1)
	9 dload (0, 1)
	10 #7 (0, 1)
	11 invokevirtual (0, 1)
	12 org/apache/commons/math3/analysis/solvers/AbstractUnivariateDifferentiableSolver.setup:(ILorg/apache/commons/math3/analysis/differentiation/UnivariateDifferentiableFunction;DDD)V (0, 1)
	14 return (0, 1)

