Method: values
	0 getstatic (0, 0)
	1 org/apache/commons/math3/analysis/solvers/AllowedSolution.$VALUES:[Lorg/apache/commons/math3/analysis/solvers/AllowedSolution; (0, 0)
	3 invokevirtual (0, 0)
	4 [Lorg/apache/commons/math3/analysis/solvers/AllowedSolution;.clone:()Ljava/lang/Object; (0, 0)
	6 checkcast (0, 0)
	7 [Lorg/apache/commons/math3/analysis/solvers/AllowedSolution; (0, 0)
	9 areturn (0, 0)

Method: valueOf
	0 ldc (0, 0)
	1 org/apache/commons/math3/analysis/solvers/AllowedSolution (0, 0)
	2 aload_0 (0, 0)
	3 invokestatic (0, 0)
	4 java/lang/Enum.valueOf:(Ljava/lang/Class;Ljava/lang/String;)Ljava/lang/Enum; (0, 0)
	6 checkcast (0, 0)
	7 org/apache/commons/math3/analysis/solvers/AllowedSolution (0, 0)
	9 areturn (0, 0)

Method: <clinit>
	0 new (0, 0)
	1 org/apache/commons/math3/analysis/solvers/AllowedSolution (0, 0)
	3 dup (0, 0)
	4 ldc (0, 0)
	5 ANY_SIDE (0, 0)
	6 iconst_0 (0, 0)
	7 invokespecial (0, 0)
	8 org/apache/commons/math3/analysis/solvers/AllowedSolution.<init>:(Ljava/lang/String;I)V (0, 0)
	10 putstatic (0, 0)
	11 org/apache/commons/math3/analysis/solvers/AllowedSolution.ANY_SIDE:Lorg/apache/commons/math3/analysis/solvers/AllowedSolution; (0, 0)
	13 new (2, 1)
	14 org/apache/commons/math3/analysis/solvers/AllowedSolution (2, 1)
	16 dup (2, 1)
	17 ldc (2, 1)
	18 LEFT_SIDE (2, 1)
	19 iconst_1 (2, 1)
	20 invokespecial (2, 1)
	21 org/apache/commons/math3/analysis/solvers/AllowedSolution.<init>:(Ljava/lang/String;I)V (2, 1)
	23 putstatic (2, 1)
	24 org/apache/commons/math3/analysis/solvers/AllowedSolution.LEFT_SIDE:Lorg/apache/commons/math3/analysis/solvers/AllowedSolution; (2, 1)
	26 new (4, 1)
	27 org/apache/commons/math3/analysis/solvers/AllowedSolution (4, 1)
	29 dup (4, 1)
	30 ldc (4, 1)
	31 RIGHT_SIDE (4, 1)
	32 iconst_2 (4, 1)
	33 invokespecial (4, 1)
	34 org/apache/commons/math3/analysis/solvers/AllowedSolution.<init>:(Ljava/lang/String;I)V (4, 1)
	36 putstatic (4, 1)
	37 org/apache/commons/math3/analysis/solvers/AllowedSolution.RIGHT_SIDE:Lorg/apache/commons/math3/analysis/solvers/AllowedSolution; (4, 1)
	39 new (6, 1)
	40 org/apache/commons/math3/analysis/solvers/AllowedSolution (6, 1)
	42 dup (6, 1)
	43 ldc (6, 1)
	44 BELOW_SIDE (6, 1)
	45 iconst_3 (6, 1)
	46 invokespecial (6, 1)
	47 org/apache/commons/math3/analysis/solvers/AllowedSolution.<init>:(Ljava/lang/String;I)V (6, 1)
	49 putstatic (6, 1)
	50 org/apache/commons/math3/analysis/solvers/AllowedSolution.BELOW_SIDE:Lorg/apache/commons/math3/analysis/solvers/AllowedSolution; (6, 1)
	52 new (8, 1)
	53 org/apache/commons/math3/analysis/solvers/AllowedSolution (8, 1)
	55 dup (8, 1)
	56 ldc (8, 1)
	57 ABOVE_SIDE (8, 1)
	58 iconst_4 (8, 1)
	59 invokespecial (8, 1)
	60 org/apache/commons/math3/analysis/solvers/AllowedSolution.<init>:(Ljava/lang/String;I)V (8, 1)
	62 putstatic (8, 1)
	63 org/apache/commons/math3/analysis/solvers/AllowedSolution.ABOVE_SIDE:Lorg/apache/commons/math3/analysis/solvers/AllowedSolution; (8, 1)
	65 iconst_5 (8, 1)
	66 anewarray (8, 1)
	67 org/apache/commons/math3/analysis/solvers/AllowedSolution (8, 1)
	69 dup (8, 1)
	70 iconst_0 (8, 1)
	71 getstatic (8, 1)
	72 org/apache/commons/math3/analysis/solvers/AllowedSolution.ANY_SIDE:Lorg/apache/commons/math3/analysis/solvers/AllowedSolution; (8, 1)
	74 aastore (8, 1)
	75 dup (8, 1)
	76 iconst_1 (8, 1)
	77 getstatic (8, 1)
	78 org/apache/commons/math3/analysis/solvers/AllowedSolution.LEFT_SIDE:Lorg/apache/commons/math3/analysis/solvers/AllowedSolution; (8, 1)
	80 aastore (8, 1)
	81 dup (8, 1)
	82 iconst_2 (8, 1)
	83 getstatic (8, 1)
	84 org/apache/commons/math3/analysis/solvers/AllowedSolution.RIGHT_SIDE:Lorg/apache/commons/math3/analysis/solvers/AllowedSolution; (8, 1)
	86 aastore (8, 1)
	87 dup (8, 1)
	88 iconst_3 (8, 1)
	89 getstatic (8, 1)
	90 org/apache/commons/math3/analysis/solvers/AllowedSolution.BELOW_SIDE:Lorg/apache/commons/math3/analysis/solvers/AllowedSolution; (8, 1)
	92 aastore (8, 1)
	93 dup (8, 1)
	94 iconst_4 (8, 1)
	95 getstatic (8, 1)
	96 org/apache/commons/math3/analysis/solvers/AllowedSolution.ABOVE_SIDE:Lorg/apache/commons/math3/analysis/solvers/AllowedSolution; (8, 1)
	98 aastore (8, 1)
	99 putstatic (8, 1)
	100 org/apache/commons/math3/analysis/solvers/AllowedSolution.$VALUES:[Lorg/apache/commons/math3/analysis/solvers/AllowedSolution; (8, 1)
	102 return (0, 1)

