Method: <init>
	0 aload_0 (0, 0)
	1 dload_1 (0, 0)
	2 dload_3 (0, 0)
	3 dload (0, 0)
	4 #5 (0, 0)
	5 invokespecial (0, 0)
	6 org/apache/commons/math3/analysis/solvers/AbstractUnivariateSolver.<init>:(DDD)V (0, 0)
	8 aload_0 (0, 0)
	9 getstatic (0, 0)
	10 org/apache/commons/math3/analysis/solvers/AllowedSolution.ANY_SIDE:Lorg/apache/commons/math3/analysis/solvers/AllowedSolution; (0, 0)
	12 putfield (0, 0)
	13 org/apache/commons/math3/analysis/solvers/BaseSecantSolver.allowed:Lorg/apache/commons/math3/analysis/solvers/AllowedSolution; (0, 0)
	15 aload_0 (0, 0)
	16 aload (0, 0)
	17 #7 (0, 0)
	18 putfield (0, 0)
	19 org/apache/commons/math3/analysis/solvers/BaseSecantSolver.method:Lorg/apache/commons/math3/analysis/solvers/BaseSecantSolver$Method; (0, 0)
	21 return (0, 0)

Method: solve
	0 aload_0 (0, 0)
	1 iload_1 (0, 0)
	2 aload_2 (0, 0)
	3 dload_3 (0, 0)
	4 dload (0, 0)
	5 #5 (0, 0)
	6 dload (0, 0)
	7 #7 (0, 0)
	8 getstatic (0, 0)
	9 org/apache/commons/math3/analysis/solvers/AllowedSolution.ANY_SIDE:Lorg/apache/commons/math3/analysis/solvers/AllowedSolution; (0, 0)
	11 invokevirtual (0, 0)
	12 org/apache/commons/math3/analysis/solvers/BaseSecantSolver.solve:(ILorg/apache/commons/math3/analysis/UnivariateFunction;DDDLorg/apache/commons/math3/analysis/solvers/AllowedSolution;)D (0, 0)
	14 dreturn (0, 0)

Method: doSolve
	0 aload_0 (0, 0)
	1 invokevirtual (0, 0)
	2 org/apache/commons/math3/analysis/solvers/BaseSecantSolver.getMin:()D (0, 0)
	4 dstore_1 (0, 0)
	5 aload_0 (0, 0)
	6 invokevirtual (0, 0)
	7 org/apache/commons/math3/analysis/solvers/BaseSecantSolver.getMax:()D (0, 0)
	9 dstore_3 (0, 0)
	10 aload_0 (0, 0)
	11 dload_1 (0, 0)
	12 invokevirtual (0, 0)
	13 org/apache/commons/math3/analysis/solvers/BaseSecantSolver.computeObjectiveValue:(D)D (0, 0)
	15 dstore (0, 0)
	16 #5 (0, 0)
	17 aload_0 (0, 0)
	18 dload_3 (0, 0)
	19 invokevirtual (0, 0)
	20 org/apache/commons/math3/analysis/solvers/BaseSecantSolver.computeObjectiveValue:(D)D (0, 0)
	22 dstore (0, 0)
	23 #7 (0, 0)
	24 dload (1, 1)
	25 #5 (1, 1)
	26 dconst_0 (1, 1)
	27 dcmpl (1, 1)
	28 ifne (1, 1)
	29 5 (1, 1)
	31 dload_1 (1, 1)
	32 dreturn (1, 1)
	33 dload (1, 1)
	34 #7 (1, 1)
	35 dconst_0 (1, 1)
	36 dcmpl (1, 1)
	37 ifne (1, 1)
	38 5 (1, 1)
	40 dload_3 (1, 1)
	41 dreturn (1, 1)
	42 aload_0 (2, 1)
	43 dload_1 (2, 1)
	44 dload_3 (2, 1)
	45 invokevirtual (2, 1)
	46 org/apache/commons/math3/analysis/solvers/BaseSecantSolver.verifyBracketing:(DD)V (2, 1)
	48 aload_0 (2, 1)
	49 invokevirtual (2, 1)
	50 org/apache/commons/math3/analysis/solvers/BaseSecantSolver.getFunctionValueAccuracy:()D (2, 1)
	52 dstore (2, 1)
	53 #9 (2, 1)
	54 aload_0 (2, 1)
	55 invokevirtual (2, 1)
	56 org/apache/commons/math3/analysis/solvers/BaseSecantSolver.getAbsoluteAccuracy:()D (2, 1)
	58 dstore (2, 1)
	59 #11 (2, 1)
	60 aload_0 (2, 1)
	61 invokevirtual (2, 1)
	62 org/apache/commons/math3/analysis/solvers/BaseSecantSolver.getRelativeAccuracy:()D (2, 1)
	64 dstore (2, 1)
	65 #13 (2, 1)
	66 iconst_0 (2, 1)
	67 istore (2, 1)
	68 #15 (2, 1)
	69 dload_3 (3, 3)
	70 dload (3, 3)
	71 #7 (3, 3)
	72 dload_3 (3, 3)
	73 dload_1 (3, 3)
	74 dsub (3, 3)
	75 dmul (3, 3)
	76 dload (3, 3)
	77 #7 (3, 3)
	78 dload (3, 3)
	79 #5 (3, 3)
	80 dsub (3, 3)
	81 ddiv (3, 3)
	82 dsub (3, 3)
	83 dstore (3, 3)
	84 #16 (3, 3)
	85 aload_0 (3, 3)
	86 dload (3, 3)
	87 #16 (3, 3)
	88 invokevirtual (3, 3)
	89 org/apache/commons/math3/analysis/solvers/BaseSecantSolver.computeObjectiveValue:(D)D (3, 3)
	91 dstore (3, 3)
	92 #18 (3, 3)
	93 dload (4, 1)
	94 #18 (4, 1)
	95 dconst_0 (4, 1)
	96 dcmpl (4, 1)
	97 ifne (4, 1)
	98 6 (4, 1)
	100 dload (4, 1)
	101 #16 (4, 1)
	102 dreturn (4, 1)
	103 dload (4, 1)
	104 #7 (4, 1)
	105 dload (4, 1)
	106 #18 (4, 1)
	107 dmul (4, 1)
	108 dconst_0 (4, 1)
	109 dcmpg (4, 1)
	110 ifge (4, 1)
	111 24 (4, 1)
	113 dload_3 (5, 5)
	114 dstore_1 (5, 5)
	115 dload (5, 5)
	116 #7 (5, 5)
	117 dstore (5, 5)
	118 #5 (5, 5)
	119 iload (5, 5)
	120 #15 (5, 5)
	121 ifne (5, 5)
	122 7 (5, 5)
	124 iconst_1 (5, 5)
	125 goto (5, 5)
	126 4 (5, 5)
	128 iconst_0 (5, 5)
	129 istore (5, 5)
	130 #15 (5, 5)
	131 goto (5, 5)
	132 91 (5, 5)
	134 getstatic (7, 5)
	135 org/apache/commons/math3/analysis/solvers/BaseSecantSolver$1.$SwitchMap$org$apache$commons$math3$analysis$solvers$BaseSecantSolver$Method:[I (7, 5)
	137 aload_0 (7, 5)
	138 getfield (7, 5)
	139 org/apache/commons/math3/analysis/solvers/BaseSecantSolver.method:Lorg/apache/commons/math3/analysis/solvers/BaseSecantSolver$Method; (7, 5)
	141 invokevirtual (7, 5)
	142 org/apache/commons/math3/analysis/solvers/BaseSecantSolver$Method.ordinal:()I (7, 5)
	144 iaload (7, 5)
	145 tableswitch (7, 5)
	146 1 172 (7, 5)
	150 2 183 (7, 5)
	154 3 199 (7, 5)
	172 dload (7, 5)
	173 #5 (7, 5)
	174 ldc2_w (7, 5)
	175 0.5 (7, 5)
	177 dmul (7, 5)
	178 dstore (7, 5)
	179 #5 (7, 5)
	180 goto (7, 5)
	181 42 (7, 5)
	183 dload (7, 5)
	184 #5 (7, 5)
	185 dload (7, 5)
	186 #7 (7, 5)
	187 dload (7, 5)
	188 #7 (7, 5)
	189 dload (7, 5)
	190 #18 (7, 5)
	191 dadd (7, 5)
	192 ddiv (7, 5)
	193 dmul (7, 5)
	194 dstore (7, 5)
	195 #5 (7, 5)
	196 goto (7, 5)
	197 26 (7, 5)
	199 dload (9, 1)
	200 #16 (9, 1)
	201 dload_3 (9, 1)
	202 dcmpl (9, 1)
	203 ifne (9, 1)
	204 19 (9, 1)
	206 new (9, 1)
	207 org/apache/commons/math3/exception/ConvergenceException (9, 1)
	209 dup (9, 1)
	210 invokespecial (9, 1)
	211 org/apache/commons/math3/exception/ConvergenceException.<init>:()V (9, 1)
	213 athrow (9, 1)
	214 new (8, 4)
	215 org/apache/commons/math3/exception/MathInternalError (8, 4)
	217 dup (8, 4)
	218 invokespecial (8, 4)
	219 org/apache/commons/math3/exception/MathInternalError.<init>:()V (8, 4)
	221 athrow (8, 4)
	222 dload (3, 3)
	223 #16 (3, 3)
	224 dstore_3 (3, 3)
	225 dload (3, 3)
	226 #18 (3, 3)
	227 dstore (3, 3)
	228 #7 (3, 3)
	229 dload (4, 1)
	230 #7 (4, 1)
	231 invokestatic (4, 1)
	232 org/apache/commons/math3/util/FastMath.abs:(D)D (4, 1)
	234 dload (4, 1)
	235 #9 (4, 1)
	236 dcmpg (4, 1)
	237 ifgt (4, 1)
	238 89 (4, 1)
	240 getstatic (5, 5)
	241 org/apache/commons/math3/analysis/solvers/BaseSecantSolver$1.$SwitchMap$org$apache$commons$math3$analysis$solvers$AllowedSolution:[I (5, 5)
	243 aload_0 (5, 5)
	244 getfield (5, 5)
	245 org/apache/commons/math3/analysis/solvers/BaseSecantSolver.allowed:Lorg/apache/commons/math3/analysis/solvers/AllowedSolution; (5, 5)
	247 invokevirtual (5, 5)
	248 org/apache/commons/math3/analysis/solvers/AllowedSolution.ordinal:()I (5, 5)
	250 iaload (5, 5)
	251 tableswitch (5, 5)
	252 1 284 (5, 5)
	256 2 286 (5, 5)
	260 3 293 (5, 5)
	264 4 300 (5, 5)
	268 5 309 (5, 5)
	284 dload_3 (5, 5)
	285 dreturn (5, 5)
	286 iload (6, 1)
	287 #15 (6, 1)
	288 ifeq (6, 1)
	289 38 (6, 1)
	291 dload_3 (6, 1)
	292 dreturn (6, 1)
	293 iload (6, 1)
	294 #15 (6, 1)
	295 ifne (6, 1)
	296 31 (6, 1)
	298 dload_3 (6, 1)
	299 dreturn (6, 1)
	300 dload (6, 1)
	301 #7 (6, 1)
	302 dconst_0 (6, 1)
	303 dcmpg (6, 1)
	304 ifgt (6, 1)
	305 22 (6, 1)
	307 dload_3 (6, 1)
	308 dreturn (6, 1)
	309 dload (6, 1)
	310 #7 (6, 1)
	311 dconst_0 (6, 1)
	312 dcmpl (6, 1)
	313 iflt (6, 1)
	314 13 (6, 1)
	316 dload_3 (6, 1)
	317 dreturn (6, 1)
	318 new (5, 5)
	319 org/apache/commons/math3/exception/MathInternalError (5, 5)
	321 dup (5, 5)
	322 invokespecial (5, 5)
	323 org/apache/commons/math3/exception/MathInternalError.<init>:()V (5, 5)
	325 athrow (5, 5)
	326 dload_3 (4, 1)
	327 dload_1 (4, 1)
	328 dsub (4, 1)
	329 invokestatic (4, 1)
	330 org/apache/commons/math3/util/FastMath.abs:(D)D (4, 1)
	332 dload (4, 1)
	333 #13 (4, 1)
	334 dload_3 (4, 1)
	335 invokestatic (4, 1)
	336 org/apache/commons/math3/util/FastMath.abs:(D)D (4, 1)
	338 dmul (4, 1)
	339 dload (4, 1)
	340 #11 (4, 1)
	341 invokestatic (4, 1)
	342 org/apache/commons/math3/util/FastMath.max:(DD)D (4, 1)
	344 dcmpg (4, 1)
	345 ifge (4, 1)
	346 105 (4, 1)
	348 getstatic (5, 5)
	349 org/apache/commons/math3/analysis/solvers/BaseSecantSolver$1.$SwitchMap$org$apache$commons$math3$analysis$solvers$AllowedSolution:[I (5, 5)
	351 aload_0 (5, 5)
	352 getfield (5, 5)
	353 org/apache/commons/math3/analysis/solvers/BaseSecantSolver.allowed:Lorg/apache/commons/math3/analysis/solvers/AllowedSolution; (5, 5)
	355 invokevirtual (5, 5)
	356 org/apache/commons/math3/analysis/solvers/AllowedSolution.ordinal:()I (5, 5)
	358 iaload (5, 5)
	359 tableswitch (5, 5)
	360 1 392 (5, 5)
	364 2 394 (5, 5)
	368 3 405 (5, 5)
	372 4 416 (5, 5)
	376 5 429 (5, 5)
	392 dload_3 (5, 5)
	393 dreturn (5, 5)
	394 iload (5, 5)
	395 #15 (5, 5)
	396 ifeq (5, 5)
	397 7 (5, 5)
	399 dload_3 (5, 5)
	400 goto (5, 5)
	401 4 (5, 5)
	403 dload_1 (5, 5)
	404 dreturn (5, 5)
	405 iload (5, 5)
	406 #15 (5, 5)
	407 ifeq (5, 5)
	408 7 (5, 5)
	410 dload_1 (5, 5)
	411 goto (5, 5)
	412 4 (5, 5)
	414 dload_3 (5, 5)
	415 dreturn (5, 5)
	416 dload (5, 5)
	417 #7 (5, 5)
	418 dconst_0 (5, 5)
	419 dcmpg (5, 5)
	420 ifgt (5, 5)
	421 7 (5, 5)
	423 dload_3 (5, 5)
	424 goto (5, 5)
	425 4 (5, 5)
	427 dload_1 (5, 5)
	428 dreturn (5, 5)
	429 dload (5, 5)
	430 #7 (5, 5)
	431 dconst_0 (5, 5)
	432 dcmpl (5, 5)
	433 iflt (5, 5)
	434 7 (5, 5)
	436 dload_3 (5, 5)
	437 goto (5, 5)
	438 4 (5, 5)
	440 dload_1 (5, 5)
	441 dreturn (5, 5)
	442 new (5, 5)
	443 org/apache/commons/math3/exception/MathInternalError (5, 5)
	445 dup (5, 5)
	446 invokespecial (5, 5)
	447 org/apache/commons/math3/exception/MathInternalError.<init>:()V (5, 5)
	449 athrow (5, 5)
	450 goto (0, 1)
	451 -381 (2, 1)

