Method: <init>
	0 aload_0 (0, 0)
	1 invokespecial (0, 0)
	2 java/lang/Object.<init>:()V (0, 0)
	4 aload_0 (0, 0)
	5 dload_3 (0, 0)
	6 putfield (0, 0)
	7 org/apache/commons/math3/analysis/solvers/BaseAbstractUnivariateSolver.absoluteAccuracy:D (0, 0)
	9 aload_0 (0, 0)
	10 dload_1 (0, 0)
	11 putfield (0, 0)
	12 org/apache/commons/math3/analysis/solvers/BaseAbstractUnivariateSolver.relativeAccuracy:D (0, 0)
	14 aload_0 (0, 0)
	15 dload (0, 0)
	16 #5 (0, 0)
	17 putfield (0, 0)
	18 org/apache/commons/math3/analysis/solvers/BaseAbstractUnivariateSolver.functionValueAccuracy:D (0, 0)
	20 aload_0 (0, 0)
	21 invokestatic (0, 0)
	22 org/apache/commons/math3/util/IntegerSequence$Incrementor.create:()Lorg/apache/commons/math3/util/IntegerSequence$Incrementor; (0, 0)
	24 putfield (0, 0)
	25 org/apache/commons/math3/analysis/solvers/BaseAbstractUnivariateSolver.evaluations:Lorg/apache/commons/math3/util/IntegerSequence$Incrementor; (0, 0)
	27 return (0, 0)

Method: getMaxEvaluations
	0 aload_0 (0, 0)
	1 getfield (0, 0)
	2 org/apache/commons/math3/analysis/solvers/BaseAbstractUnivariateSolver.evaluations:Lorg/apache/commons/math3/util/IntegerSequence$Incrementor; (0, 0)
	4 invokevirtual (0, 0)
	5 org/apache/commons/math3/util/IntegerSequence$Incrementor.getMaximalCount:()I (0, 0)
	7 ireturn (0, 0)

Method: getEvaluations
	0 aload_0 (0, 0)
	1 getfield (0, 0)
	2 org/apache/commons/math3/analysis/solvers/BaseAbstractUnivariateSolver.evaluations:Lorg/apache/commons/math3/util/IntegerSequence$Incrementor; (0, 0)
	4 invokevirtual (0, 0)
	5 org/apache/commons/math3/util/IntegerSequence$Incrementor.getCount:()I (0, 0)
	7 ireturn (0, 0)

Method: getMin
	0 aload_0 (0, 0)
	1 getfield (0, 0)
	2 org/apache/commons/math3/analysis/solvers/BaseAbstractUnivariateSolver.searchMin:D (0, 0)
	4 dreturn (0, 0)

Method: getMax
	0 aload_0 (0, 0)
	1 getfield (0, 0)
	2 org/apache/commons/math3/analysis/solvers/BaseAbstractUnivariateSolver.searchMax:D (0, 0)
	4 dreturn (0, 0)

Method: getStartValue
	0 aload_0 (0, 0)
	1 getfield (0, 0)
	2 org/apache/commons/math3/analysis/solvers/BaseAbstractUnivariateSolver.searchStart:D (0, 0)
	4 dreturn (0, 0)

Method: getAbsoluteAccuracy
	0 aload_0 (0, 0)
	1 getfield (0, 0)
	2 org/apache/commons/math3/analysis/solvers/BaseAbstractUnivariateSolver.absoluteAccuracy:D (0, 0)
	4 dreturn (0, 0)

Method: getRelativeAccuracy
	0 aload_0 (0, 0)
	1 getfield (0, 0)
	2 org/apache/commons/math3/analysis/solvers/BaseAbstractUnivariateSolver.relativeAccuracy:D (0, 0)
	4 dreturn (0, 0)

Method: getFunctionValueAccuracy
	0 aload_0 (0, 0)
	1 getfield (0, 0)
	2 org/apache/commons/math3/analysis/solvers/BaseAbstractUnivariateSolver.functionValueAccuracy:D (0, 0)
	4 dreturn (0, 0)

Method: computeObjectiveValue
	0 aload_0 (0, 0)
	1 invokevirtual (0, 0)
	2 org/apache/commons/math3/analysis/solvers/BaseAbstractUnivariateSolver.incrementEvaluationCount:()V (0, 0)
	4 aload_0 (0, 0)
	5 getfield (0, 0)
	6 org/apache/commons/math3/analysis/solvers/BaseAbstractUnivariateSolver.function:Lorg/apache/commons/math3/analysis/UnivariateFunction; (0, 0)
	8 dload_1 (0, 0)
	9 invokeinterface (0, 0)
	10 org/apache/commons/math3/analysis/UnivariateFunction.org/apache/commons/math3/util/MathUtils (0, 0)
	12 0 (0, 0)
	14 dreturn (0, 0)

Method: setup
	0 aload_2 (0, 0)
	1 invokestatic (0, 0)
	2 org/apache/commons/math3/util/MathUtils.checkNotNull:(Ljava/lang/Object;)V (0, 0)
	4 aload_0 (0, 0)
	5 dload_3 (0, 0)
	6 putfield (0, 0)
	7 org/apache/commons/math3/analysis/solvers/BaseAbstractUnivariateSolver.searchMin:D (0, 0)
	9 aload_0 (0, 0)
	10 dload (0, 0)
	11 #5 (0, 0)
	12 putfield (0, 0)
	13 org/apache/commons/math3/analysis/solvers/BaseAbstractUnivariateSolver.searchMax:D (0, 0)
	15 aload_0 (0, 0)
	16 dload (0, 0)
	17 #7 (0, 0)
	18 putfield (0, 0)
	19 org/apache/commons/math3/analysis/solvers/BaseAbstractUnivariateSolver.searchStart:D (0, 0)
	21 aload_0 (0, 0)
	22 aload_2 (0, 0)
	23 putfield (0, 0)
	24 org/apache/commons/math3/analysis/solvers/BaseAbstractUnivariateSolver.function:Lorg/apache/commons/math3/analysis/UnivariateFunction; (0, 0)
	26 aload_0 (0, 0)
	27 aload_0 (0, 0)
	28 getfield (0, 0)
	29 org/apache/commons/math3/analysis/solvers/BaseAbstractUnivariateSolver.evaluations:Lorg/apache/commons/math3/util/IntegerSequence$Incrementor; (0, 0)
	31 iload_1 (0, 0)
	32 invokevirtual (0, 0)
	33 org/apache/commons/math3/util/IntegerSequence$Incrementor.withMaximalCount:(I)Lorg/apache/commons/math3/util/IntegerSequence$Incrementor; (0, 0)
	35 iconst_0 (0, 0)
	36 invokevirtual (0, 0)
	37 org/apache/commons/math3/util/IntegerSequence$Incrementor.withStart:(I)Lorg/apache/commons/math3/util/IntegerSequence$Incrementor; (0, 0)
	39 putfield (0, 0)
	40 org/apache/commons/math3/analysis/solvers/BaseAbstractUnivariateSolver.evaluations:Lorg/apache/commons/math3/util/IntegerSequence$Incrementor; (0, 0)
	42 return (0, 0)

Method: solve
	0 aload_0 (0, 0)
	1 iload_1 (0, 0)
	2 aload_2 (0, 0)
	3 ldc2_w (0, 0)
	4 nan (0, 0)
	6 ldc2_w (0, 0)
	7 nan (0, 0)
	9 dload_3 (0, 0)
	10 invokevirtual (0, 0)
	11 org/apache/commons/math3/analysis/solvers/BaseAbstractUnivariateSolver.solve:(ILorg/apache/commons/math3/analysis/UnivariateFunction;DDD)D (0, 0)
	13 dreturn (0, 0)

Method: isBracketing
	0 aload_0 (0, 0)
	1 getfield (0, 0)
	2 org/apache/commons/math3/analysis/solvers/BaseAbstractUnivariateSolver.function:Lorg/apache/commons/math3/analysis/UnivariateFunction; (0, 0)
	4 dload_1 (0, 0)
	5 dload_3 (0, 0)
	6 invokestatic (0, 0)
	7 org/apache/commons/math3/analysis/solvers/UnivariateSolverUtils.isBracketing:(Lorg/apache/commons/math3/analysis/UnivariateFunction;DD)Z (0, 0)
	9 ireturn (0, 0)

Method: isSequence
	0 dload_1 (0, 0)
	1 dload_3 (0, 0)
	2 dload (0, 0)
	3 #5 (0, 0)
	4 invokestatic (0, 0)
	5 org/apache/commons/math3/analysis/solvers/UnivariateSolverUtils.isSequence:(DDD)Z (0, 0)
	7 ireturn (0, 0)

Method: verifyInterval
	0 dload_1 (1, 1)
	1 dload_3 (1, 1)
	2 invokestatic (1, 1)
	3 org/apache/commons/math3/analysis/solvers/UnivariateSolverUtils.verifyInterval:(DD)V (1, 1)
	5 return (0, 1)

Method: verifySequence
	0 dload_1 (1, 1)
	1 dload_3 (1, 1)
	2 dload (1, 1)
	3 #5 (1, 1)
	4 invokestatic (1, 1)
	5 org/apache/commons/math3/analysis/solvers/UnivariateSolverUtils.verifySequence:(DDD)V (1, 1)
	7 return (0, 1)

Method: verifyBracketing
	0 aload_0 (1, 1)
	1 getfield (1, 1)
	2 org/apache/commons/math3/analysis/solvers/BaseAbstractUnivariateSolver.function:Lorg/apache/commons/math3/analysis/UnivariateFunction; (1, 1)
	4 dload_1 (1, 1)
	5 dload_3 (1, 1)
	6 invokestatic (1, 1)
	7 org/apache/commons/math3/analysis/solvers/UnivariateSolverUtils.verifyBracketing:(Lorg/apache/commons/math3/analysis/UnivariateFunction;DD)V (1, 1)
	9 return (0, 1)

Method: incrementEvaluationCount
	0 aload_0 (0, 0)
	1 getfield (0, 0)
	2 org/apache/commons/math3/analysis/solvers/BaseAbstractUnivariateSolver.evaluations:Lorg/apache/commons/math3/util/IntegerSequence$Incrementor; (0, 0)
	4 invokevirtual (0, 0)
	5 org/apache/commons/math3/util/IntegerSequence$Incrementor.increment:()V (0, 0)
	7 goto (0, 0)
	8 16 (0, 0)
	10 astore_1 (0, 0)
	11 new (0, 0)
	12 org/apache/commons/math3/exception/TooManyEvaluationsException (0, 0)
	14 dup (0, 0)
	15 aload_1 (0, 0)
	16 invokevirtual (0, 0)
	17 org/apache/commons/math3/exception/MaxCountExceededException.getMax:()Ljava/lang/Number; (0, 0)
	19 invokespecial (0, 0)
	20 org/apache/commons/math3/exception/TooManyEvaluationsException.<init>:(Ljava/lang/Number;)V (0, 0)
	22 athrow (0, 0)
	23 return (0, 0)

