Method: <clinit>
	0 invokestatic (1, 5)
	3 arraylength (1, 5)
	4 newarray (1, 5)
	6 putstatic (1, 5)
	9 getstatic (1, 5)
	12 getstatic (1, 5)
	15 invokevirtual (1, 5)
	18 iconst_1 (1, 5)
	19 iastore (1, 5)
	20 goto (1, 5)
	23 astore_0 (1, 5)
	24 getstatic (1, 5)
	27 getstatic (1, 5)
	30 invokevirtual (1, 5)
	33 iconst_2 (1, 5)
	34 iastore (1, 5)
	35 goto (1, 5)
	38 astore_0 (1, 5)
	39 getstatic (1, 5)
	42 getstatic (1, 5)
	45 invokevirtual (1, 5)
	48 iconst_3 (1, 5)
	49 iastore (1, 5)
	50 goto (1, 5)
	53 astore_0 (1, 5)
	54 getstatic (1, 5)
	57 getstatic (1, 5)
	60 invokevirtual (1, 5)
	63 iconst_4 (1, 5)
	64 iastore (1, 5)
	65 goto (1, 5)
	68 astore_0 (1, 5)
	69 getstatic (1, 5)
	72 getstatic (1, 5)
	75 invokevirtual (1, 5)
	78 iconst_5 (1, 5)
	79 iastore (1, 5)
	80 goto (1, 5)
	83 astore_0 (1, 5)
	84 invokestatic (1, 5)
	87 arraylength (1, 5)
	88 newarray (1, 5)
	90 putstatic (1, 5)
	93 getstatic (1, 5)
	96 getstatic (1, 5)
	99 invokevirtual (1, 5)
	102 iconst_1 (1, 5)
	103 iastore (1, 5)
	104 goto (1, 5)
	107 astore_0 (1, 5)
	108 getstatic (1, 5)
	111 getstatic (1, 5)
	114 invokevirtual (1, 5)
	117 iconst_2 (1, 5)
	118 iastore (1, 5)
	119 goto (1, 5)
	122 astore_0 (1, 5)
	123 getstatic (1, 5)
	126 getstatic (1, 5)
	129 invokevirtual (1, 5)
	132 iconst_3 (1, 5)
	133 iastore (1, 5)
	134 goto (1, 5)
	137 astore_0 (1, 5)
	138 return (1, 5)

