Method: <init>
	0 aload_0 (0, 0)
	1 dload_1 (0, 0)
	2 dload_3 (0, 0)
	3 dload (0, 0)
	4 #5 (0, 0)
	5 invokespecial (0, 0)
	6 org/apache/commons/math3/analysis/solvers/AbstractUnivariateSolver.<init>:(DDD)V (0, 0)
	8 iload (1, 1)
	9 #7 (1, 1)
	10 iconst_2 (1, 1)
	11 if_icmpge (1, 1)
	12 21 (1, 1)
	14 new (1, 1)
	15 org/apache/commons/math3/exception/NumberIsTooSmallException (1, 1)
	17 dup (1, 1)
	18 iload (1, 1)
	19 #7 (1, 1)
	20 invokestatic (1, 1)
	21 java/lang/Integer.valueOf:(I)Ljava/lang/Integer; (1, 1)
	23 iconst_2 (1, 1)
	24 invokestatic (1, 1)
	25 java/lang/Integer.valueOf:(I)Ljava/lang/Integer; (1, 1)
	27 iconst_1 (1, 1)
	28 invokespecial (1, 1)
	29 org/apache/commons/math3/exception/NumberIsTooSmallException.<init>:(Ljava/lang/Number;Ljava/lang/Number;Z)V (1, 1)
	31 athrow (1, 1)
	32 aload_0 (0, 0)
	33 iload (0, 0)
	34 #7 (0, 0)
	35 putfield (0, 0)
	36 org/apache/commons/math3/analysis/solvers/BracketingNthOrderBrentSolver.maximalOrder:I (0, 0)
	38 aload_0 (0, 0)
	39 getstatic (0, 0)
	40 org/apache/commons/math3/analysis/solvers/AllowedSolution.ANY_SIDE:Lorg/apache/commons/math3/analysis/solvers/AllowedSolution; (0, 0)
	42 putfield (0, 0)
	43 org/apache/commons/math3/analysis/solvers/BracketingNthOrderBrentSolver.allowed:Lorg/apache/commons/math3/analysis/solvers/AllowedSolution; (0, 0)
	45 return (0, 0)

Method: getMaximalOrder
	0 aload_0 (0, 0)
	1 getfield (0, 0)
	2 org/apache/commons/math3/analysis/solvers/BracketingNthOrderBrentSolver.maximalOrder:I (0, 0)
	4 ireturn (0, 0)

Method: doSolve
	0 aload_0 (0, 0)
	1 getfield (0, 0)
	2 org/apache/commons/math3/analysis/solvers/BracketingNthOrderBrentSolver.maximalOrder:I (0, 0)
	4 iconst_1 (0, 0)
	5 iadd (0, 0)
	6 newarray (0, 0)
	7 7 (0, 0)
	8 astore_1 (0, 0)
	9 aload_0 (0, 0)
	10 getfield (0, 0)
	11 org/apache/commons/math3/analysis/solvers/BracketingNthOrderBrentSolver.maximalOrder:I (0, 0)
	13 iconst_1 (0, 0)
	14 iadd (0, 0)
	15 newarray (0, 0)
	16 7 (0, 0)
	17 astore_2 (0, 0)
	18 aload_1 (0, 0)
	19 iconst_0 (0, 0)
	20 aload_0 (0, 0)
	21 invokevirtual (0, 0)
	22 org/apache/commons/math3/analysis/solvers/BracketingNthOrderBrentSolver.getMin:()D (0, 0)
	24 dastore (0, 0)
	25 aload_1 (0, 0)
	26 iconst_1 (0, 0)
	27 aload_0 (0, 0)
	28 invokevirtual (0, 0)
	29 org/apache/commons/math3/analysis/solvers/BracketingNthOrderBrentSolver.getStartValue:()D (0, 0)
	31 dastore (0, 0)
	32 aload_1 (0, 0)
	33 iconst_2 (0, 0)
	34 aload_0 (0, 0)
	35 invokevirtual (0, 0)
	36 org/apache/commons/math3/analysis/solvers/BracketingNthOrderBrentSolver.getMax:()D (0, 0)
	38 dastore (0, 0)
	39 aload_0 (0, 1)
	40 aload_1 (0, 1)
	41 iconst_0 (0, 1)
	42 daload (0, 1)
	43 aload_1 (0, 1)
	44 iconst_1 (0, 1)
	45 daload (0, 1)
	46 aload_1 (0, 1)
	47 iconst_2 (0, 1)
	48 daload (0, 1)
	49 invokevirtual (0, 1)
	50 org/apache/commons/math3/analysis/solvers/BracketingNthOrderBrentSolver.verifySequence:(DDD)V (0, 1)
	52 aload_2 (0, 1)
	53 iconst_1 (0, 1)
	54 aload_0 (0, 1)
	55 aload_1 (0, 1)
	56 iconst_1 (0, 1)
	57 daload (0, 1)
	58 invokevirtual (0, 1)
	59 org/apache/commons/math3/analysis/solvers/BracketingNthOrderBrentSolver.computeObjectiveValue:(D)D (0, 1)
	61 dastore (0, 1)
	62 aload_2 (1, 1)
	63 iconst_1 (1, 1)
	64 daload (1, 1)
	65 dconst_0 (1, 1)
	66 iconst_1 (1, 1)
	67 invokestatic (1, 1)
	68 org/apache/commons/math3/util/Precision.equals:(DDI)Z (1, 1)
	70 ifeq (1, 1)
	71 7 (1, 1)
	73 aload_1 (1, 1)
	74 iconst_1 (1, 1)
	75 daload (1, 1)
	76 dreturn (1, 1)
	77 aload_2 (0, 1)
	78 iconst_0 (0, 1)
	79 aload_0 (0, 1)
	80 aload_1 (0, 1)
	81 iconst_0 (0, 1)
	82 daload (0, 1)
	83 invokevirtual (0, 1)
	84 org/apache/commons/math3/analysis/solvers/BracketingNthOrderBrentSolver.computeObjectiveValue:(D)D (0, 1)
	86 dastore (0, 1)
	87 aload_2 (1, 1)
	88 iconst_0 (1, 1)
	89 daload (1, 1)
	90 dconst_0 (1, 1)
	91 iconst_1 (1, 1)
	92 invokestatic (1, 1)
	93 org/apache/commons/math3/util/Precision.equals:(DDI)Z (1, 1)
	95 ifeq (1, 1)
	96 7 (1, 1)
	98 aload_1 (1, 1)
	99 iconst_0 (1, 1)
	100 daload (1, 1)
	101 dreturn (1, 1)
	102 aload_2 (1, 1)
	103 iconst_0 (1, 1)
	104 daload (1, 1)
	105 aload_2 (1, 1)
	106 iconst_1 (1, 1)
	107 daload (1, 1)
	108 dmul (1, 1)
	109 dconst_0 (1, 1)
	110 dcmpg (1, 1)
	111 ifge (1, 1)
	112 11 (1, 1)
	114 iconst_2 (1, 1)
	115 istore_3 (1, 1)
	116 iconst_1 (1, 1)
	117 istore (1, 1)
	118 #4 (1, 1)
	119 goto (1, 1)
	120 68 (1, 1)
	122 aload_2 (1, 2)
	123 iconst_2 (1, 2)
	124 aload_0 (1, 2)
	125 aload_1 (1, 2)
	126 iconst_2 (1, 2)
	127 daload (1, 2)
	128 invokevirtual (1, 2)
	129 org/apache/commons/math3/analysis/solvers/BracketingNthOrderBrentSolver.computeObjectiveValue:(D)D (1, 2)
	131 dastore (1, 2)
	132 aload_2 (2, 1)
	133 iconst_2 (2, 1)
	134 daload (2, 1)
	135 dconst_0 (2, 1)
	136 iconst_1 (2, 1)
	137 invokestatic (2, 1)
	138 org/apache/commons/math3/util/Precision.equals:(DDI)Z (2, 1)
	140 ifeq (2, 1)
	141 7 (2, 1)
	143 aload_1 (2, 1)
	144 iconst_2 (2, 1)
	145 daload (2, 1)
	146 dreturn (2, 1)
	147 aload_2 (2, 1)
	148 iconst_1 (2, 1)
	149 daload (2, 1)
	150 aload_2 (2, 1)
	151 iconst_2 (2, 1)
	152 daload (2, 1)
	153 dmul (2, 1)
	154 dconst_0 (2, 1)
	155 dcmpg (2, 1)
	156 ifge (2, 1)
	157 11 (2, 1)
	159 iconst_3 (2, 4)
	160 istore_3 (2, 4)
	161 iconst_2 (2, 4)
	162 istore (2, 4)
	163 #4 (2, 4)
	164 goto (2, 4)
	165 23 (2, 4)
	167 new (2, 2)
	168 org/apache/commons/math3/exception/NoBracketingException (2, 2)
	170 dup (2, 2)
	171 aload_1 (2, 2)
	172 iconst_0 (2, 2)
	173 daload (2, 2)
	174 aload_1 (2, 2)
	175 iconst_2 (2, 2)
	176 daload (2, 2)
	177 aload_2 (2, 2)
	178 iconst_0 (2, 2)
	179 daload (2, 2)
	180 aload_2 (2, 2)
	181 iconst_2 (2, 2)
	182 daload (2, 2)
	183 invokespecial (2, 2)
	184 org/apache/commons/math3/exception/NoBracketingException.<init>:(DDDD)V (2, 2)
	186 athrow (2, 2)
	187 aload_1 (0, 4)
	188 arraylength (0, 4)
	189 newarray (0, 4)
	190 7 (0, 4)
	191 astore (0, 4)
	192 #5 (0, 4)
	193 aload_1 (0, 4)
	194 iload (0, 4)
	195 #4 (0, 4)
	196 iconst_1 (0, 4)
	197 isub (0, 4)
	198 daload (0, 4)
	199 dstore (0, 4)
	200 #6 (0, 4)
	201 aload_2 (0, 4)
	202 iload (0, 4)
	203 #4 (0, 4)
	204 iconst_1 (0, 4)
	205 isub (0, 4)
	206 daload (0, 4)
	207 dstore (0, 4)
	208 #8 (0, 4)
	209 dload (0, 4)
	210 #8 (0, 4)
	211 invokestatic (0, 4)
	212 org/apache/commons/math3/util/FastMath.abs:(D)D (0, 4)
	214 dstore (0, 4)
	215 #10 (0, 4)
	216 iconst_0 (0, 4)
	217 istore (0, 4)
	218 #12 (0, 4)
	219 aload_1 (0, 4)
	220 iload (0, 4)
	221 #4 (0, 4)
	222 daload (0, 4)
	223 dstore (0, 4)
	224 #13 (0, 4)
	225 aload_2 (0, 4)
	226 iload (0, 4)
	227 #4 (0, 4)
	228 daload (0, 4)
	229 dstore (0, 4)
	230 #15 (0, 4)
	231 dload (0, 4)
	232 #15 (0, 4)
	233 invokestatic (0, 4)
	234 org/apache/commons/math3/util/FastMath.abs:(D)D (0, 4)
	236 dstore (0, 4)
	237 #17 (0, 4)
	238 iconst_0 (0, 4)
	239 istore (0, 4)
	240 #19 (0, 4)
	241 aload_0 (1, 3)
	242 invokevirtual (1, 3)
	243 org/apache/commons/math3/analysis/solvers/BracketingNthOrderBrentSolver.getAbsoluteAccuracy:()D (1, 3)
	245 aload_0 (1, 3)
	246 invokevirtual (1, 3)
	247 org/apache/commons/math3/analysis/solvers/BracketingNthOrderBrentSolver.getRelativeAccuracy:()D (1, 3)
	249 dload (1, 3)
	250 #6 (1, 3)
	251 invokestatic (1, 3)
	252 org/apache/commons/math3/util/FastMath.abs:(D)D (1, 3)
	254 dload (1, 3)
	255 #13 (1, 3)
	256 invokestatic (1, 3)
	257 org/apache/commons/math3/util/FastMath.abs:(D)D (1, 3)
	259 invokestatic (1, 3)
	260 org/apache/commons/math3/util/FastMath.max:(DD)D (1, 3)
	262 dmul (1, 3)
	263 dadd (1, 3)
	264 dstore (1, 3)
	265 #20 (1, 3)
	266 dload (2, 1)
	267 #13 (2, 1)
	268 dload (2, 1)
	269 #6 (2, 1)
	270 dsub (2, 1)
	271 dload (2, 1)
	272 #20 (2, 1)
	273 dcmpg (2, 1)
	274 ifle (2, 1)
	275 18 (2, 1)
	277 dload (2, 1)
	278 #10 (2, 1)
	279 dload (2, 1)
	280 #17 (2, 1)
	281 invokestatic (2, 1)
	282 org/apache/commons/math3/util/FastMath.max:(DD)D (2, 1)
	284 aload_0 (2, 1)
	285 invokevirtual (2, 1)
	286 org/apache/commons/math3/analysis/solvers/BracketingNthOrderBrentSolver.getFunctionValueAccuracy:()D (2, 1)
	288 dcmpg (2, 1)
	289 ifge (2, 1)
	290 107 (2, 1)
	292 getstatic (3, 5)
	293 org/apache/commons/math3/analysis/solvers/BracketingNthOrderBrentSolver$1.$SwitchMap$org$apache$commons$math3$analysis$solvers$AllowedSolution:[I (3, 5)
	295 aload_0 (3, 5)
	296 getfield (3, 5)
	297 org/apache/commons/math3/analysis/solvers/BracketingNthOrderBrentSolver.allowed:Lorg/apache/commons/math3/analysis/solvers/AllowedSolution; (3, 5)
	299 invokevirtual (3, 5)
	300 org/apache/commons/math3/analysis/solvers/AllowedSolution.ordinal:()I (3, 5)
	302 iaload (3, 5)
	303 tableswitch (3, 5)
	304 1 336 (3, 5)
	308 2 352 (3, 5)
	312 3 355 (3, 5)
	316 4 358 (3, 5)
	320 5 373 (3, 5)
	336 dload (3, 5)
	337 #10 (3, 5)
	338 dload (3, 5)
	339 #17 (3, 5)
	340 dcmpg (3, 5)
	341 ifge (3, 5)
	342 8 (3, 5)
	344 dload (3, 5)
	345 #6 (3, 5)
	346 goto (3, 5)
	347 5 (3, 5)
	349 dload (3, 5)
	350 #13 (3, 5)
	351 dreturn (3, 5)
	352 dload (3, 5)
	353 #6 (3, 5)
	354 dreturn (3, 5)
	355 dload (3, 5)
	356 #13 (3, 5)
	357 dreturn (3, 5)
	358 dload (3, 5)
	359 #8 (3, 5)
	360 dconst_0 (3, 5)
	361 dcmpg (3, 5)
	362 ifgt (3, 5)
	363 8 (3, 5)
	365 dload (3, 5)
	366 #6 (3, 5)
	367 goto (3, 5)
	368 5 (3, 5)
	370 dload (3, 5)
	371 #13 (3, 5)
	372 dreturn (3, 5)
	373 dload (3, 5)
	374 #8 (3, 5)
	375 dconst_0 (3, 5)
	376 dcmpg (3, 5)
	377 ifge (3, 5)
	378 8 (3, 5)
	380 dload (3, 5)
	381 #13 (3, 5)
	382 goto (3, 5)
	383 5 (3, 5)
	385 dload (3, 5)
	386 #6 (3, 5)
	387 dreturn (3, 5)
	388 new (3, 5)
	389 org/apache/commons/math3/exception/MathInternalError (3, 5)
	391 dup (3, 5)
	392 invokespecial (3, 5)
	393 org/apache/commons/math3/exception/MathInternalError.<init>:()V (3, 5)
	395 athrow (3, 5)
	396 iload (2, 1)
	397 #12 (2, 1)
	398 iconst_2 (2, 1)
	399 if_icmplt (2, 1)
	400 51 (2, 1)
	402 iload (2, 1)
	403 #12 (2, 1)
	404 iconst_2 (2, 1)
	405 isub (2, 1)
	406 istore (2, 1)
	407 #24 (2, 1)
	408 iconst_1 (2, 1)
	409 iload (2, 1)
	410 #24 (2, 1)
	411 ishl (2, 1)
	412 iconst_1 (2, 1)
	413 isub (2, 1)
	414 i2d (2, 1)
	415 dstore (2, 1)
	416 #25 (2, 1)
	417 iload (2, 1)
	418 #24 (2, 1)
	419 iconst_1 (2, 1)
	420 iadd (2, 1)
	421 i2d (2, 1)
	422 dstore (2, 1)
	423 #27 (2, 1)
	424 dload (2, 1)
	425 #25 (2, 1)
	426 dload (2, 1)
	427 #8 (2, 1)
	428 dmul (2, 1)
	429 dload (2, 1)
	430 #27 (2, 1)
	431 ldc2_w (2, 1)
	432 0.0625 (2, 1)
	434 dmul (2, 1)
	435 dload (2, 1)
	436 #15 (2, 1)
	437 dmul (2, 1)
	438 dsub (2, 1)
	439 dload (2, 1)
	440 #25 (2, 1)
	441 dload (2, 1)
	442 #27 (2, 1)
	443 dadd (2, 1)
	444 ddiv (2, 1)
	445 dstore (2, 1)
	446 #22 (2, 1)
	447 goto (2, 1)
	448 60 (2, 1)
	450 iload (2, 1)
	451 #19 (2, 1)
	452 iconst_2 (2, 1)
	453 if_icmplt (2, 1)
	454 51 (2, 1)
	456 iload (2, 1)
	457 #19 (2, 1)
	458 iconst_2 (2, 1)
	459 isub (2, 1)
	460 istore (2, 1)
	461 #24 (2, 1)
	462 iload (2, 1)
	463 #24 (2, 1)
	464 iconst_1 (2, 1)
	465 iadd (2, 1)
	466 i2d (2, 1)
	467 dstore (2, 1)
	468 #25 (2, 1)
	469 iconst_1 (2, 1)
	470 iload (2, 1)
	471 #24 (2, 1)
	472 ishl (2, 1)
	473 iconst_1 (2, 1)
	474 isub (2, 1)
	475 i2d (2, 1)
	476 dstore (2, 1)
	477 #27 (2, 1)
	478 dload (2, 1)
	479 #27 (2, 1)
	480 dload (2, 1)
	481 #15 (2, 1)
	482 dmul (2, 1)
	483 dload (2, 1)
	484 #25 (2, 1)
	485 ldc2_w (2, 1)
	486 0.0625 (2, 1)
	488 dmul (2, 1)
	489 dload (2, 1)
	490 #8 (2, 1)
	491 dmul (2, 1)
	492 dsub (2, 1)
	493 dload (2, 1)
	494 #25 (2, 1)
	495 dload (2, 1)
	496 #27 (2, 1)
	497 dadd (2, 1)
	498 ddiv (2, 1)
	499 dstore (2, 1)
	500 #22 (2, 1)
	501 goto (2, 2)
	502 6 (2, 2)
	504 dconst_0 (2, 2)
	505 dstore (2, 2)
	506 #22 (2, 2)
	507 iconst_0 (1, 4)
	508 istore (1, 4)
	509 #26 (1, 4)
	510 iload_3 (1, 4)
	511 istore (1, 4)
	512 #27 (1, 4)
	513 aload_1 (2, 4)
	514 iload (2, 4)
	515 #26 (2, 4)
	516 aload (2, 4)
	517 #5 (2, 4)
	518 iload (2, 4)
	519 #26 (2, 4)
	520 iload (2, 4)
	521 #27 (2, 4)
	522 iload (2, 4)
	523 #26 (2, 4)
	524 isub (2, 4)
	525 invokestatic (2, 4)
	526 java/lang/System.arraycopy:(Ljava/lang/Object;ILjava/lang/Object;II)V (2, 4)
	528 aload_0 (2, 4)
	529 dload (2, 4)
	530 #22 (2, 4)
	531 aload (2, 4)
	532 #5 (2, 4)
	533 aload_2 (2, 4)
	534 iload (2, 4)
	535 #26 (2, 4)
	536 iload (2, 4)
	537 #27 (2, 4)
	538 invokespecial (2, 4)
	539 org/apache/commons/math3/analysis/solvers/BracketingNthOrderBrentSolver.guessX:(D[D[DII)D (2, 4)
	541 dstore (2, 4)
	542 #24 (2, 4)
	543 dload (3, 1)
	544 #24 (3, 1)
	545 dload (3, 1)
	546 #6 (3, 1)
	547 dcmpl (3, 1)
	548 ifle (3, 1)
	549 11 (3, 1)
	551 dload (3, 1)
	552 #24 (3, 1)
	553 dload (3, 1)
	554 #13 (3, 1)
	555 dcmpg (3, 1)
	556 iflt (3, 1)
	557 30 (3, 1)
	559 iload (4, 1)
	560 #4 (4, 1)
	561 iload (4, 1)
	562 #26 (4, 1)
	563 isub (4, 1)
	564 iload (4, 1)
	565 #27 (4, 1)
	566 iload (4, 1)
	567 #4 (4, 1)
	568 isub (4, 1)
	569 if_icmplt (4, 1)
	570 9 (4, 1)
	572 iinc (4, 4)
	573 #26 (4, 4)
	574 -89 (4, 4)
	575 goto (4, 4)
	576 6 (4, 4)
	578 iinc (4, 2)
	579 #27 (4, 2)
	580 20 (4, 2)
	581 ldc2_w (3, 1)
	582 nan (3, 1)
	584 dstore (3, 1)
	585 #24 (3, 1)
	586 dload (1, 3)
	587 #24 (1, 3)
	588 invokestatic (1, 3)
	589 java/lang/Double.isNaN:(D)Z (1, 3)
	591 ifeq (1, 3)
	592 12 (1, 3)
	594 iload (1, 3)
	595 #27 (1, 3)
	596 iload (1, 3)
	597 #26 (1, 3)
	598 isub (1, 3)
	599 iconst_1 (1, 3)
	600 if_icmpgt (1, 3)
	601 -87 (1, 3)
	603 dload (2, 1)
	604 #24 (2, 1)
	605 invokestatic (2, 1)
	606 java/lang/Double.isNaN:(D)Z (2, 1)
	608 ifeq (2, 1)
	609 27 (2, 1)
	611 dload (2, 1)
	612 #6 (2, 1)
	613 ldc2_w (2, 1)
	614 0.5 (2, 1)
	616 dload (2, 1)
	617 #13 (2, 1)
	618 dload (2, 1)
	619 #6 (2, 1)
	620 dsub (2, 1)
	621 dmul (2, 1)
	622 dadd (2, 1)
	623 dstore (2, 1)
	624 #24 (2, 1)
	625 iload (2, 1)
	626 #4 (2, 1)
	627 iconst_1 (2, 1)
	628 isub (2, 1)
	629 istore (2, 1)
	630 #26 (2, 1)
	631 iload (2, 1)
	632 #4 (2, 1)
	633 istore (2, 1)
	634 #27 (2, 1)
	635 aload_0 (1, 3)
	636 dload (1, 3)
	637 #24 (1, 3)
	638 invokevirtual (1, 3)
	639 org/apache/commons/math3/analysis/solvers/BracketingNthOrderBrentSolver.computeObjectiveValue:(D)D (1, 3)
	641 dstore (1, 3)
	642 #28 (1, 3)
	643 dload (2, 1)
	644 #28 (2, 1)
	645 dconst_0 (2, 1)
	646 iconst_1 (2, 1)
	647 invokestatic (2, 1)
	648 org/apache/commons/math3/util/Precision.equals:(DDI)Z (2, 1)
	650 ifeq (2, 1)
	651 6 (2, 1)
	653 dload (2, 1)
	654 #24 (2, 1)
	655 dreturn (2, 1)
	656 iload_3 (2, 1)
	657 iconst_2 (2, 1)
	658 if_icmple (2, 1)
	659 46 (2, 1)
	661 iload (2, 1)
	662 #27 (2, 1)
	663 iload (2, 1)
	664 #26 (2, 1)
	665 isub (2, 1)
	666 iload_3 (2, 1)
	667 if_icmpeq (2, 1)
	668 37 (2, 1)
	670 iload (2, 4)
	671 #27 (2, 4)
	672 iload (2, 4)
	673 #26 (2, 4)
	674 isub (2, 4)
	675 istore_3 (2, 4)
	676 aload_1 (2, 4)
	677 iload (2, 4)
	678 #26 (2, 4)
	679 aload_1 (2, 4)
	680 iconst_0 (2, 4)
	681 iload_3 (2, 4)
	682 invokestatic (2, 4)
	683 java/lang/System.arraycopy:(Ljava/lang/Object;ILjava/lang/Object;II)V (2, 4)
	685 aload_2 (2, 4)
	686 iload (2, 4)
	687 #26 (2, 4)
	688 aload_2 (2, 4)
	689 iconst_0 (2, 4)
	690 iload_3 (2, 4)
	691 invokestatic (2, 4)
	692 java/lang/System.arraycopy:(Ljava/lang/Object;ILjava/lang/Object;II)V (2, 4)
	694 iload (2, 4)
	695 #4 (2, 4)
	696 iload (2, 4)
	697 #26 (2, 4)
	698 isub (2, 4)
	699 istore (2, 4)
	700 #4 (2, 4)
	701 goto (2, 4)
	702 42 (2, 4)
	704 iload_3 (2, 1)
	705 aload_1 (2, 1)
	706 arraylength (2, 1)
	707 if_icmpne (2, 1)
	708 36 (2, 1)
	710 iinc (2, 1)
	711 #3 (2, 1)
	712 21 (2, 1)
	713 iload (3, 1)
	714 #4 (3, 1)
	715 aload_1 (3, 1)
	716 arraylength (3, 1)
	717 iconst_1 (3, 1)
	718 iadd (3, 1)
	719 iconst_2 (3, 1)
	720 idiv (3, 1)
	721 if_icmplt (3, 1)
	722 22 (3, 1)
	724 aload_1 (3, 1)
	725 iconst_1 (3, 1)
	726 aload_1 (3, 1)
	727 iconst_0 (3, 1)
	728 iload_3 (3, 1)
	729 invokestatic (3, 1)
	730 java/lang/System.arraycopy:(Ljava/lang/Object;ILjava/lang/Object;II)V (3, 1)
	732 aload_2 (3, 1)
	733 iconst_1 (3, 1)
	734 aload_2 (3, 1)
	735 iconst_0 (3, 1)
	736 iload_3 (3, 1)
	737 invokestatic (3, 1)
	738 java/lang/System.arraycopy:(Ljava/lang/Object;ILjava/lang/Object;II)V (3, 1)
	740 iinc (3, 1)
	741 #4 (3, 1)
	742 43 (3, 1)
	743 aload_1 (1, 3)
	744 iload (1, 3)
	745 #4 (1, 3)
	746 aload_1 (1, 3)
	747 iload (1, 3)
	748 #4 (1, 3)
	749 iconst_1 (1, 3)
	750 iadd (1, 3)
	751 iload_3 (1, 3)
	752 iload (1, 3)
	753 #4 (1, 3)
	754 isub (1, 3)
	755 invokestatic (1, 3)
	756 java/lang/System.arraycopy:(Ljava/lang/Object;ILjava/lang/Object;II)V (1, 3)
	758 aload_1 (1, 3)
	759 iload (1, 3)
	760 #4 (1, 3)
	761 dload (1, 3)
	762 #24 (1, 3)
	763 dastore (1, 3)
	764 aload_2 (1, 3)
	765 iload (1, 3)
	766 #4 (1, 3)
	767 aload_2 (1, 3)
	768 iload (1, 3)
	769 #4 (1, 3)
	770 iconst_1 (1, 3)
	771 iadd (1, 3)
	772 iload_3 (1, 3)
	773 iload (1, 3)
	774 #4 (1, 3)
	775 isub (1, 3)
	776 invokestatic (1, 3)
	777 java/lang/System.arraycopy:(Ljava/lang/Object;ILjava/lang/Object;II)V (1, 3)
	779 aload_2 (1, 3)
	780 iload (1, 3)
	781 #4 (1, 3)
	782 dload (1, 3)
	783 #28 (1, 3)
	784 dastore (1, 3)
	785 iinc (1, 3)
	786 #3 (1, 3)
	787 24 (1, 3)
	788 dload (2, 1)
	789 #28 (2, 1)
	790 dload (2, 1)
	791 #8 (2, 1)
	792 dmul (2, 1)
	793 dconst_0 (2, 1)
	794 dcmpg (2, 1)
	795 ifgt (2, 1)
	796 27 (2, 1)
	798 dload (2, 4)
	799 #24 (2, 4)
	800 dstore (2, 4)
	801 #13 (2, 4)
	802 dload (2, 4)
	803 #28 (2, 4)
	804 dstore (2, 4)
	805 #15 (2, 4)
	806 dload (2, 4)
	807 #15 (2, 4)
	808 invokestatic (2, 4)
	809 org/apache/commons/math3/util/FastMath.abs:(D)D (2, 4)
	811 dstore (2, 4)
	812 #17 (2, 4)
	813 iinc (2, 4)
	814 #12 (2, 4)
	815 3 (2, 4)
	816 iconst_0 (2, 4)
	817 istore (2, 4)
	818 #19 (2, 4)
	819 goto (2, 4)
	820 27 (2, 4)
	822 dload (2, 2)
	823 #24 (2, 2)
	824 dstore (2, 2)
	825 #6 (2, 2)
	826 dload (2, 2)
	827 #28 (2, 2)
	828 dstore (2, 2)
	829 #8 (2, 2)
	830 dload (2, 2)
	831 #8 (2, 2)
	832 invokestatic (2, 2)
	833 org/apache/commons/math3/util/FastMath.abs:(D)D (2, 2)
	835 dstore (2, 2)
	836 #10 (2, 2)
	837 iconst_0 (2, 2)
	838 istore (2, 2)
	839 #12 (2, 2)
	840 iinc (2, 2)
	841 #19 (2, 2)
	842 -124 (2, 2)
	843 iinc (2, 2)
	844 #4 (2, 2)
	845 -89 (2, 2)
	846 goto (0, 4)
	847 -605 (0, 4)

Method: guessX
	0 iload (1, 4)
	1 #5 (1, 4)
	2 istore (1, 4)
	3 #7 (1, 4)
	4 iload (1, 4)
	5 #7 (1, 4)
	6 iload (1, 4)
	7 #6 (1, 4)
	8 iconst_1 (1, 4)
	9 isub (1, 4)
	10 if_icmpge (1, 4)
	11 67 (1, 4)
	13 iload (1, 4)
	14 #7 (1, 4)
	15 iconst_1 (1, 4)
	16 iadd (1, 4)
	17 iload (1, 4)
	18 #5 (1, 4)
	19 isub (1, 4)
	20 istore (1, 4)
	21 #8 (1, 4)
	22 iload (2, 4)
	23 #6 (2, 4)
	24 iconst_1 (2, 4)
	25 isub (2, 4)
	26 istore (2, 4)
	27 #9 (2, 4)
	28 iload (2, 4)
	29 #9 (2, 4)
	30 iload (2, 4)
	31 #7 (2, 4)
	32 if_icmple (2, 4)
	33 39 (2, 4)
	35 aload_3 (2, 4)
	36 iload (2, 4)
	37 #9 (2, 4)
	38 aload_3 (2, 4)
	39 iload (2, 4)
	40 #9 (2, 4)
	41 daload (2, 4)
	42 aload_3 (2, 4)
	43 iload (2, 4)
	44 #9 (2, 4)
	45 iconst_1 (2, 4)
	46 isub (2, 4)
	47 daload (2, 4)
	48 dsub (2, 4)
	49 aload (2, 4)
	50 #4 (2, 4)
	51 iload (2, 4)
	52 #9 (2, 4)
	53 daload (2, 4)
	54 aload (2, 4)
	55 #4 (2, 4)
	56 iload (2, 4)
	57 #9 (2, 4)
	58 iload (2, 4)
	59 #8 (2, 4)
	60 isub (2, 4)
	61 daload (2, 4)
	62 dsub (2, 4)
	63 ddiv (2, 4)
	64 dastore (2, 4)
	65 iinc (2, 4)
	66 #9 (2, 4)
	67 -89 (2, 4)
	68 goto (2, 4)
	69 -40 (2, 4)
	71 iinc (2, 4)
	72 #7 (2, 4)
	73 -89 (2, 4)
	74 goto (2, 4)
	75 -70 (2, 4)
	77 dconst_0 (1, 4)
	78 dstore (1, 4)
	79 #7 (1, 4)
	80 iload (2, 4)
	81 #6 (2, 4)
	82 iconst_1 (2, 4)
	83 isub (2, 4)
	84 istore (2, 4)
	85 #9 (2, 4)
	86 iload (2, 4)
	87 #9 (2, 4)
	88 iload (2, 4)
	89 #5 (2, 4)
	90 if_icmplt (2, 4)
	91 26 (2, 4)
	93 aload_3 (2, 4)
	94 iload (2, 4)
	95 #9 (2, 4)
	96 daload (2, 4)
	97 dload (2, 4)
	98 #7 (2, 4)
	99 dload_1 (2, 4)
	100 aload (2, 4)
	101 #4 (2, 4)
	102 iload (2, 4)
	103 #9 (2, 4)
	104 daload (2, 4)
	105 dsub (2, 4)
	106 dmul (2, 4)
	107 dadd (2, 4)
	108 dstore (2, 4)
	109 #7 (2, 4)
	110 iinc (2, 4)
	111 #9 (2, 4)
	112 -89 (2, 4)
	113 goto (2, 4)
	114 -27 (2, 4)
	116 dload (1, 4)
	117 #7 (1, 4)
	118 dreturn (1, 4)

Method: solve
	0 aload_0 (0, 0)
	1 aload (0, 0)
	2 #9 (0, 0)
	3 putfield (0, 0)
	4 org/apache/commons/math3/analysis/solvers/BracketingNthOrderBrentSolver.allowed:Lorg/apache/commons/math3/analysis/solvers/AllowedSolution; (0, 0)
	6 aload_0 (0, 0)
	7 iload_1 (0, 0)
	8 aload_2 (0, 0)
	9 dload_3 (0, 0)
	10 dload (0, 0)
	11 #5 (0, 0)
	12 dload (0, 0)
	13 #7 (0, 0)
	14 invokespecial (0, 0)
	15 org/apache/commons/math3/analysis/solvers/AbstractUnivariateSolver.solve:(ILorg/apache/commons/math3/analysis/UnivariateFunction;DDD)D (0, 0)
	17 dreturn (0, 0)

