Method: <init>
	0 aload_0 (0, 0)
	1 dload_1 (0, 0)
	2 dload_3 (0, 0)
	3 dload (0, 0)
	4 #5 (0, 0)
	5 invokespecial (0, 0)
	6 org/apache/commons/math3/analysis/solvers/AbstractUnivariateSolver.<init>:(DDD)V (0, 0)
	8 return (0, 0)

Method: doSolve
	0 aload_0 (0, 0)
	1 invokevirtual (0, 0)
	2 org/apache/commons/math3/analysis/solvers/BrentSolver.getMin:()D (0, 0)
	4 dstore_1 (0, 0)
	5 aload_0 (0, 0)
	6 invokevirtual (0, 0)
	7 org/apache/commons/math3/analysis/solvers/BrentSolver.getMax:()D (0, 0)
	9 dstore_3 (0, 0)
	10 aload_0 (0, 0)
	11 invokevirtual (0, 0)
	12 org/apache/commons/math3/analysis/solvers/BrentSolver.getStartValue:()D (0, 0)
	14 dstore (0, 0)
	15 #5 (0, 0)
	16 aload_0 (0, 0)
	17 invokevirtual (0, 0)
	18 org/apache/commons/math3/analysis/solvers/BrentSolver.getFunctionValueAccuracy:()D (0, 0)
	20 dstore (0, 0)
	21 #7 (0, 0)
	22 aload_0 (1, 1)
	23 dload_1 (1, 1)
	24 dload (1, 1)
	25 #5 (1, 1)
	26 dload_3 (1, 1)
	27 invokevirtual (1, 1)
	28 org/apache/commons/math3/analysis/solvers/BrentSolver.verifySequence:(DDD)V (1, 1)
	30 aload_0 (2, 1)
	31 dload (2, 1)
	32 #5 (2, 1)
	33 invokevirtual (2, 1)
	34 org/apache/commons/math3/analysis/solvers/BrentSolver.computeObjectiveValue:(D)D (2, 1)
	36 dstore (2, 1)
	37 #9 (2, 1)
	38 dload (3, 1)
	39 #9 (3, 1)
	40 invokestatic (3, 1)
	41 org/apache/commons/math3/util/FastMath.abs:(D)D (3, 1)
	43 dload (3, 1)
	44 #7 (3, 1)
	45 dcmpg (3, 1)
	46 ifgt (3, 1)
	47 6 (3, 1)
	49 dload (3, 1)
	50 #5 (3, 1)
	51 dreturn (3, 1)
	52 aload_0 (3, 1)
	53 dload_1 (3, 1)
	54 invokevirtual (3, 1)
	55 org/apache/commons/math3/analysis/solvers/BrentSolver.computeObjectiveValue:(D)D (3, 1)
	57 dstore (3, 1)
	58 #11 (3, 1)
	59 dload (4, 1)
	60 #11 (4, 1)
	61 invokestatic (4, 1)
	62 org/apache/commons/math3/util/FastMath.abs:(D)D (4, 1)
	64 dload (4, 1)
	65 #7 (4, 1)
	66 dcmpg (4, 1)
	67 ifgt (4, 1)
	68 5 (4, 1)
	70 dload_1 (4, 1)
	71 dreturn (4, 1)
	72 dload (5, 1)
	73 #9 (5, 1)
	74 dload (5, 1)
	75 #11 (5, 1)
	76 dmul (5, 1)
	77 dconst_0 (5, 1)
	78 dcmpg (5, 1)
	79 ifge (5, 1)
	80 15 (5, 1)
	82 aload_0 (5, 1)
	83 dload_1 (5, 1)
	84 dload (5, 1)
	85 #5 (5, 1)
	86 dload (5, 1)
	87 #11 (5, 1)
	88 dload (5, 1)
	89 #9 (5, 1)
	90 invokespecial (5, 1)
	91 org/apache/commons/math3/analysis/solvers/BrentSolver.brent:(DDDD)D (5, 1)
	93 dreturn (5, 1)
	94 aload_0 (5, 1)
	95 dload_3 (5, 1)
	96 invokevirtual (5, 1)
	97 org/apache/commons/math3/analysis/solvers/BrentSolver.computeObjectiveValue:(D)D (5, 1)
	99 dstore (5, 1)
	100 #13 (5, 1)
	101 dload (6, 1)
	102 #13 (6, 1)
	103 invokestatic (6, 1)
	104 org/apache/commons/math3/util/FastMath.abs:(D)D (6, 1)
	106 dload (6, 1)
	107 #7 (6, 1)
	108 dcmpg (6, 1)
	109 ifgt (6, 1)
	110 5 (6, 1)
	112 dload_3 (6, 1)
	113 dreturn (6, 1)
	114 dload (7, 1)
	115 #9 (7, 1)
	116 dload (7, 1)
	117 #13 (7, 1)
	118 dmul (7, 1)
	119 dconst_0 (7, 1)
	120 dcmpg (7, 1)
	121 ifge (7, 1)
	122 15 (7, 1)
	124 aload_0 (7, 1)
	125 dload (7, 1)
	126 #5 (7, 1)
	127 dload_3 (7, 1)
	128 dload (7, 1)
	129 #9 (7, 1)
	130 dload (7, 1)
	131 #13 (7, 1)
	132 invokespecial (7, 1)
	133 org/apache/commons/math3/analysis/solvers/BrentSolver.brent:(DDDD)D (7, 1)
	135 dreturn (7, 1)
	136 new (6, 1)
	137 org/apache/commons/math3/exception/NoBracketingException (6, 1)
	139 dup (6, 1)
	140 dload_1 (6, 1)
	141 dload_3 (6, 1)
	142 dload (6, 1)
	143 #11 (6, 1)
	144 dload (6, 1)
	145 #13 (6, 1)
	146 invokespecial (6, 1)
	147 org/apache/commons/math3/exception/NoBracketingException.<init>:(DDDD)V (6, 1)
	149 athrow (0, 1)

Method: brent
	0 dload_1 (0, 0)
	1 dstore (0, 0)
	2 #9 (0, 0)
	3 dload (0, 0)
	4 #5 (0, 0)
	5 dstore (0, 0)
	6 #11 (0, 0)
	7 dload_3 (0, 0)
	8 dstore (0, 0)
	9 #13 (0, 0)
	10 dload (0, 0)
	11 #7 (0, 0)
	12 dstore (0, 0)
	13 #15 (0, 0)
	14 dload (0, 0)
	15 #9 (0, 0)
	16 dstore (0, 0)
	17 #17 (0, 0)
	18 dload (0, 0)
	19 #11 (0, 0)
	20 dstore (0, 0)
	21 #19 (0, 0)
	22 dload (0, 0)
	23 #13 (0, 0)
	24 dload (0, 0)
	25 #9 (0, 0)
	26 dsub (0, 0)
	27 dstore (0, 0)
	28 #21 (0, 0)
	29 dload (0, 0)
	30 #21 (0, 0)
	31 dstore (0, 0)
	32 #23 (0, 0)
	33 aload_0 (0, 0)
	34 invokevirtual (0, 0)
	35 org/apache/commons/math3/analysis/solvers/BrentSolver.getAbsoluteAccuracy:()D (0, 0)
	37 dstore (0, 0)
	38 #25 (0, 0)
	39 aload_0 (0, 0)
	40 invokevirtual (0, 0)
	41 org/apache/commons/math3/analysis/solvers/BrentSolver.getRelativeAccuracy:()D (0, 0)
	43 dstore (0, 0)
	44 #27 (0, 0)
	45 dload (2, 1)
	46 #19 (2, 1)
	47 invokestatic (2, 1)
	48 org/apache/commons/math3/util/FastMath.abs:(D)D (2, 1)
	50 dload (2, 1)
	51 #15 (2, 1)
	52 invokestatic (2, 1)
	53 org/apache/commons/math3/util/FastMath.abs:(D)D (2, 1)
	55 dcmpg (2, 1)
	56 ifge (2, 1)
	57 27 (2, 1)
	59 dload (2, 1)
	60 #13 (2, 1)
	61 dstore (2, 1)
	62 #9 (2, 1)
	63 dload (2, 1)
	64 #17 (2, 1)
	65 dstore (2, 1)
	66 #13 (2, 1)
	67 dload (2, 1)
	68 #9 (2, 1)
	69 dstore (2, 1)
	70 #17 (2, 1)
	71 dload (2, 1)
	72 #15 (2, 1)
	73 dstore (2, 1)
	74 #11 (2, 1)
	75 dload (2, 1)
	76 #19 (2, 1)
	77 dstore (2, 1)
	78 #15 (2, 1)
	79 dload (2, 1)
	80 #11 (2, 1)
	81 dstore (2, 1)
	82 #19 (2, 1)
	83 ldc2_w (1, 3)
	84 2.0 (1, 3)
	86 dload (1, 3)
	87 #27 (1, 3)
	88 dmul (1, 3)
	89 dload (1, 3)
	90 #13 (1, 3)
	91 invokestatic (1, 3)
	92 org/apache/commons/math3/util/FastMath.abs:(D)D (1, 3)
	94 dmul (1, 3)
	95 dload (1, 3)
	96 #25 (1, 3)
	97 dadd (1, 3)
	98 dstore (1, 3)
	99 #29 (1, 3)
	100 ldc2_w (1, 3)
	101 0.5 (1, 3)
	103 dload (1, 3)
	104 #17 (1, 3)
	105 dload (1, 3)
	106 #13 (1, 3)
	107 dsub (1, 3)
	108 dmul (1, 3)
	109 dstore (1, 3)
	110 #31 (1, 3)
	111 dload (2, 1)
	112 #31 (2, 1)
	113 invokestatic (2, 1)
	114 org/apache/commons/math3/util/FastMath.abs:(D)D (2, 1)
	116 dload (2, 1)
	117 #29 (2, 1)
	118 dcmpg (2, 1)
	119 ifle (2, 1)
	120 12 (2, 1)
	122 dload (2, 1)
	123 #15 (2, 1)
	124 dconst_0 (2, 1)
	125 invokestatic (2, 1)
	126 org/apache/commons/math3/util/Precision.equals:(DD)Z (2, 1)
	128 ifeq (2, 1)
	129 6 (2, 1)
	131 dload (2, 1)
	132 #13 (2, 1)
	133 dreturn (2, 1)
	134 dload (3, 1)
	135 #23 (3, 1)
	136 invokestatic (3, 1)
	137 org/apache/commons/math3/util/FastMath.abs:(D)D (3, 1)
	139 dload (3, 1)
	140 #29 (3, 1)
	141 dcmpg (3, 1)
	142 iflt (3, 1)
	143 17 (3, 1)
	145 dload (3, 1)
	146 #11 (3, 1)
	147 invokestatic (3, 1)
	148 org/apache/commons/math3/util/FastMath.abs:(D)D (3, 1)
	150 dload (3, 1)
	151 #15 (3, 1)
	152 invokestatic (3, 1)
	153 org/apache/commons/math3/util/FastMath.abs:(D)D (3, 1)
	155 dcmpg (3, 1)
	156 ifgt (3, 1)
	157 14 (3, 1)
	159 dload (3, 1)
	160 #31 (3, 1)
	161 dstore (3, 1)
	162 #21 (3, 1)
	163 dload (3, 1)
	164 #21 (3, 1)
	165 dstore (3, 1)
	166 #23 (3, 1)
	167 goto (3, 1)
	168 187 (3, 1)
	170 dload (4, 2)
	171 #15 (4, 2)
	172 dload (4, 2)
	173 #11 (4, 2)
	174 ddiv (4, 2)
	175 dstore (4, 2)
	176 #33 (4, 2)
	177 dload (5, 1)
	178 #9 (5, 1)
	179 dload (5, 1)
	180 #17 (5, 1)
	181 dcmpl (5, 1)
	182 ifne (5, 1)
	183 23 (5, 1)
	185 ldc2_w (5, 1)
	186 2.0 (5, 1)
	188 dload (5, 1)
	189 #31 (5, 1)
	190 dmul (5, 1)
	191 dload (5, 1)
	192 #33 (5, 1)
	193 dmul (5, 1)
	194 dstore (5, 1)
	195 #35 (5, 1)
	196 dconst_1 (5, 1)
	197 dload (5, 1)
	198 #33 (5, 1)
	199 dsub (5, 1)
	200 dstore (5, 1)
	201 #37 (5, 1)
	202 goto (5, 1)
	203 64 (5, 1)
	205 dload (6, 2)
	206 #11 (6, 2)
	207 dload (6, 2)
	208 #19 (6, 2)
	209 ddiv (6, 2)
	210 dstore (6, 2)
	211 #37 (6, 2)
	212 dload (6, 2)
	213 #15 (6, 2)
	214 dload (6, 2)
	215 #19 (6, 2)
	216 ddiv (6, 2)
	217 dstore (6, 2)
	218 #39 (6, 2)
	219 dload (6, 2)
	220 #33 (6, 2)
	221 ldc2_w (6, 2)
	222 2.0 (6, 2)
	224 dload (6, 2)
	225 #31 (6, 2)
	226 dmul (6, 2)
	227 dload (6, 2)
	228 #37 (6, 2)
	229 dmul (6, 2)
	230 dload (6, 2)
	231 #37 (6, 2)
	232 dload (6, 2)
	233 #39 (6, 2)
	234 dsub (6, 2)
	235 dmul (6, 2)
	236 dload (6, 2)
	237 #13 (6, 2)
	238 dload (6, 2)
	239 #9 (6, 2)
	240 dsub (6, 2)
	241 dload (6, 2)
	242 #39 (6, 2)
	243 dconst_1 (6, 2)
	244 dsub (6, 2)
	245 dmul (6, 2)
	246 dsub (6, 2)
	247 dmul (6, 2)
	248 dstore (6, 2)
	249 #35 (6, 2)
	250 dload (6, 2)
	251 #37 (6, 2)
	252 dconst_1 (6, 2)
	253 dsub (6, 2)
	254 dload (6, 2)
	255 #39 (6, 2)
	256 dconst_1 (6, 2)
	257 dsub (6, 2)
	258 dmul (6, 2)
	259 dload (6, 2)
	260 #33 (6, 2)
	261 dconst_1 (6, 2)
	262 dsub (6, 2)
	263 dmul (6, 2)
	264 dstore (6, 2)
	265 #37 (6, 2)
	266 dload (5, 1)
	267 #35 (5, 1)
	268 dconst_0 (5, 1)
	269 dcmpl (5, 1)
	270 ifle (5, 1)
	271 11 (5, 1)
	273 dload (5, 1)
	274 #37 (5, 1)
	275 dneg (5, 1)
	276 dstore (5, 1)
	277 #37 (5, 1)
	278 goto (5, 1)
	279 8 (5, 1)
	281 dload (6, 2)
	282 #35 (6, 2)
	283 dneg (6, 2)
	284 dstore (6, 2)
	285 #35 (6, 2)
	286 dload (4, 2)
	287 #23 (4, 2)
	288 dstore (4, 2)
	289 #33 (4, 2)
	290 dload (4, 2)
	291 #21 (4, 2)
	292 dstore (4, 2)
	293 #23 (4, 2)
	294 dload (5, 1)
	295 #35 (5, 1)
	296 ldc2_w (5, 1)
	297 1.5 (5, 1)
	299 dload (5, 1)
	300 #31 (5, 1)
	301 dmul (5, 1)
	302 dload (5, 1)
	303 #37 (5, 1)
	304 dmul (5, 1)
	305 dload (5, 1)
	306 #29 (5, 1)
	307 dload (5, 1)
	308 #37 (5, 1)
	309 dmul (5, 1)
	310 invokestatic (5, 1)
	311 org/apache/commons/math3/util/FastMath.abs:(D)D (5, 1)
	313 dsub (5, 1)
	314 dcmpl (5, 1)
	315 ifge (5, 1)
	316 21 (5, 1)
	318 dload (5, 1)
	319 #35 (5, 1)
	320 ldc2_w (5, 1)
	321 0.5 (5, 1)
	323 dload (5, 1)
	324 #33 (5, 1)
	325 dmul (5, 1)
	326 dload (5, 1)
	327 #37 (5, 1)
	328 dmul (5, 1)
	329 invokestatic (5, 1)
	330 org/apache/commons/math3/util/FastMath.abs:(D)D (5, 1)
	332 dcmpl (5, 1)
	333 iflt (5, 1)
	334 14 (5, 1)
	336 dload (5, 1)
	337 #31 (5, 1)
	338 dstore (5, 1)
	339 #21 (5, 1)
	340 dload (5, 1)
	341 #21 (5, 1)
	342 dstore (5, 1)
	343 #23 (5, 1)
	344 goto (5, 1)
	345 10 (5, 1)
	347 dload (6, 2)
	348 #35 (6, 2)
	349 dload (6, 2)
	350 #37 (6, 2)
	351 ddiv (6, 2)
	352 dstore (6, 2)
	353 #21 (6, 2)
	354 dload (3, 1)
	355 #13 (3, 1)
	356 dstore (3, 1)
	357 #9 (3, 1)
	358 dload (3, 1)
	359 #15 (3, 1)
	360 dstore (3, 1)
	361 #11 (3, 1)
	362 dload (4, 1)
	363 #21 (4, 1)
	364 invokestatic (4, 1)
	365 org/apache/commons/math3/util/FastMath.abs:(D)D (4, 1)
	367 dload (4, 1)
	368 #29 (4, 1)
	369 dcmpl (4, 1)
	370 ifle (4, 1)
	371 13 (4, 1)
	373 dload (4, 1)
	374 #13 (4, 1)
	375 dload (4, 1)
	376 #21 (4, 1)
	377 dadd (4, 1)
	378 dstore (4, 1)
	379 #13 (4, 1)
	380 goto (4, 1)
	381 27 (4, 1)
	383 dload (5, 1)
	384 #31 (5, 1)
	385 dconst_0 (5, 1)
	386 dcmpl (5, 1)
	387 ifle (5, 1)
	388 13 (5, 1)
	390 dload (5, 1)
	391 #13 (5, 1)
	392 dload (5, 1)
	393 #29 (5, 1)
	394 dadd (5, 1)
	395 dstore (5, 1)
	396 #13 (5, 1)
	397 goto (5, 1)
	398 10 (5, 1)
	400 dload (6, 2)
	401 #13 (6, 2)
	402 dload (6, 2)
	403 #29 (6, 2)
	404 dsub (6, 2)
	405 dstore (6, 2)
	406 #13 (6, 2)
	407 aload_0 (3, 1)
	408 dload (3, 1)
	409 #13 (3, 1)
	410 invokevirtual (3, 1)
	411 org/apache/commons/math3/analysis/solvers/BrentSolver.computeObjectiveValue:(D)D (3, 1)
	413 dstore (3, 1)
	414 #15 (3, 1)
	415 dload (4, 1)
	416 #15 (4, 1)
	417 dconst_0 (4, 1)
	418 dcmpl (4, 1)
	419 ifle (4, 1)
	420 10 (4, 1)
	422 dload (4, 1)
	423 #19 (4, 1)
	424 dconst_0 (4, 1)
	425 dcmpl (4, 1)
	426 ifgt (4, 1)
	427 17 (4, 1)
	429 dload (4, 1)
	430 #15 (4, 1)
	431 dconst_0 (4, 1)
	432 dcmpg (4, 1)
	433 ifgt (4, 1)
	434 29 (4, 1)
	436 dload (4, 1)
	437 #19 (4, 1)
	438 dconst_0 (4, 1)
	439 dcmpg (4, 1)
	440 ifgt (4, 1)
	441 22 (4, 1)
	443 dload (4, 1)
	444 #9 (4, 1)
	445 dstore (4, 1)
	446 #17 (4, 1)
	447 dload (4, 1)
	448 #11 (4, 1)
	449 dstore (4, 1)
	450 #19 (4, 1)
	451 dload (4, 1)
	452 #13 (4, 1)
	453 dload (4, 1)
	454 #9 (4, 1)
	455 dsub (4, 1)
	456 dstore (4, 1)
	457 #21 (4, 1)
	458 dload (4, 1)
	459 #21 (4, 1)
	460 dstore (4, 1)
	461 #23 (4, 1)
	462 goto (0, 0)
	463 -417 (0, 0)

