Method: <init>
	0 aload_0 (0, 0)
	1 invokespecial (0, 0)
	2 java/lang/Object.<init>:()V (0, 0)
	4 iload (1, 1)
	5 #4 (1, 1)
	6 iconst_2 (1, 1)
	7 if_icmpge (1, 1)
	8 21 (1, 1)
	10 new (1, 1)
	11 org/apache/commons/math3/exception/NumberIsTooSmallException (1, 1)
	13 dup (1, 1)
	14 iload (1, 1)
	15 #4 (1, 1)
	16 invokestatic (1, 1)
	17 java/lang/Integer.valueOf:(I)Ljava/lang/Integer; (1, 1)
	19 iconst_2 (1, 1)
	20 invokestatic (1, 1)
	21 java/lang/Integer.valueOf:(I)Ljava/lang/Integer; (1, 1)
	23 iconst_1 (1, 1)
	24 invokespecial (1, 1)
	25 org/apache/commons/math3/exception/NumberIsTooSmallException.<init>:(Ljava/lang/Number;Ljava/lang/Number;Z)V (1, 1)
	27 athrow (1, 1)
	28 aload_0 (0, 0)
	29 aload_1 (0, 0)
	30 invokeinterface (0, 0)
	31 org/apache/commons/math3/RealFieldElement.field:Lorg/apache/commons/math3/Field; (0, 0)
	33 0 (0, 0)
	35 putfield (0, 0)
	36 org/apache/commons/math3/analysis/solvers/FieldBracketingNthOrderBrentSolver.field:Lorg/apache/commons/math3/Field; (0, 0)
	38 aload_0 (0, 0)
	39 iload (0, 0)
	40 #4 (0, 0)
	41 putfield (0, 0)
	42 org/apache/commons/math3/analysis/solvers/FieldBracketingNthOrderBrentSolver.maximalOrder:I (0, 0)
	44 aload_0 (0, 0)
	45 aload_2 (0, 0)
	46 putfield (0, 0)
	47 org/apache/commons/math3/analysis/solvers/FieldBracketingNthOrderBrentSolver.absoluteAccuracy:Lorg/apache/commons/math3/RealFieldElement; (0, 0)
	49 aload_0 (0, 0)
	50 aload_1 (0, 0)
	51 putfield (0, 0)
	52 org/apache/commons/math3/analysis/solvers/FieldBracketingNthOrderBrentSolver.relativeAccuracy:Lorg/apache/commons/math3/RealFieldElement; (0, 0)
	54 aload_0 (0, 0)
	55 aload_3 (0, 0)
	56 putfield (0, 0)
	57 org/apache/commons/math3/analysis/solvers/FieldBracketingNthOrderBrentSolver.functionValueAccuracy:Lorg/apache/commons/math3/RealFieldElement; (0, 0)
	59 aload_0 (0, 0)
	60 invokestatic (0, 0)
	61 org/apache/commons/math3/util/IntegerSequence$Incrementor.create:()Lorg/apache/commons/math3/util/IntegerSequence$Incrementor; (0, 0)
	63 putfield (0, 0)
	64 org/apache/commons/math3/analysis/solvers/FieldBracketingNthOrderBrentSolver.evaluations:Lorg/apache/commons/math3/util/IntegerSequence$Incrementor; (0, 0)
	66 return (0, 0)

Method: getMaximalOrder
	0 aload_0 (0, 0)
	1 getfield (0, 0)
	2 org/apache/commons/math3/analysis/solvers/FieldBracketingNthOrderBrentSolver.maximalOrder:I (0, 0)
	4 ireturn (0, 0)

Method: getMaxEvaluations
	0 aload_0 (0, 0)
	1 getfield (0, 0)
	2 org/apache/commons/math3/analysis/solvers/FieldBracketingNthOrderBrentSolver.evaluations:Lorg/apache/commons/math3/util/IntegerSequence$Incrementor; (0, 0)
	4 invokevirtual (0, 0)
	5 org/apache/commons/math3/util/IntegerSequence$Incrementor.getMaximalCount:()I (0, 0)
	7 ireturn (0, 0)

Method: getEvaluations
	0 aload_0 (0, 0)
	1 getfield (0, 0)
	2 org/apache/commons/math3/analysis/solvers/FieldBracketingNthOrderBrentSolver.evaluations:Lorg/apache/commons/math3/util/IntegerSequence$Incrementor; (0, 0)
	4 invokevirtual (0, 0)
	5 org/apache/commons/math3/util/IntegerSequence$Incrementor.getCount:()I (0, 0)
	7 ireturn (0, 0)

Method: getAbsoluteAccuracy
	0 aload_0 (0, 0)
	1 getfield (0, 0)
	2 org/apache/commons/math3/analysis/solvers/FieldBracketingNthOrderBrentSolver.absoluteAccuracy:Lorg/apache/commons/math3/RealFieldElement; (0, 0)
	4 areturn (0, 0)

Method: getRelativeAccuracy
	0 aload_0 (0, 0)
	1 getfield (0, 0)
	2 org/apache/commons/math3/analysis/solvers/FieldBracketingNthOrderBrentSolver.relativeAccuracy:Lorg/apache/commons/math3/RealFieldElement; (0, 0)
	4 areturn (0, 0)

Method: getFunctionValueAccuracy
	0 aload_0 (0, 0)
	1 getfield (0, 0)
	2 org/apache/commons/math3/analysis/solvers/FieldBracketingNthOrderBrentSolver.functionValueAccuracy:Lorg/apache/commons/math3/RealFieldElement; (0, 0)
	4 areturn (0, 0)

Method: solve
	0 aload_2 (0, 0)
	1 invokestatic (0, 0)
	2 org/apache/commons/math3/util/MathUtils.checkNotNull:(Ljava/lang/Object;)V (0, 0)
	4 aload_0 (0, 0)
	5 aload_0 (0, 0)
	6 getfield (0, 0)
	7 org/apache/commons/math3/analysis/solvers/FieldBracketingNthOrderBrentSolver.evaluations:Lorg/apache/commons/math3/util/IntegerSequence$Incrementor; (0, 0)
	9 iload_1 (0, 0)
	10 invokevirtual (0, 0)
	11 org/apache/commons/math3/util/IntegerSequence$Incrementor.withMaximalCount:(I)Lorg/apache/commons/math3/util/IntegerSequence$Incrementor; (0, 0)
	13 iconst_0 (0, 0)
	14 invokevirtual (0, 0)
	15 org/apache/commons/math3/util/IntegerSequence$Incrementor.withStart:(I)Lorg/apache/commons/math3/util/IntegerSequence$Incrementor; (0, 0)
	17 putfield (0, 0)
	18 org/apache/commons/math3/analysis/solvers/FieldBracketingNthOrderBrentSolver.evaluations:Lorg/apache/commons/math3/util/IntegerSequence$Incrementor; (0, 0)
	20 aload_0 (0, 0)
	21 getfield (0, 0)
	22 org/apache/commons/math3/analysis/solvers/FieldBracketingNthOrderBrentSolver.field:Lorg/apache/commons/math3/Field; (0, 0)
	24 invokeinterface (0, 0)
	25 org/apache/commons/math3/Field.java/lang/Double (0, 0)
	27 0 (0, 0)
	29 checkcast (0, 0)
	30 org/apache/commons/math3/RealFieldElement (0, 0)
	32 astore (0, 0)
	33 #7 (0, 0)
	34 aload (0, 0)
	35 #7 (0, 0)
	36 ldc2_w (0, 0)
	37 nan (0, 0)
	39 invokeinterface (0, 0)
	40 org/apache/commons/math3/RealFieldElement.org/apache/commons/math3/util/MathArrays (0, 0)
	42 0 (0, 0)
	44 checkcast (0, 0)
	45 org/apache/commons/math3/RealFieldElement (0, 0)
	47 astore (0, 0)
	48 #8 (0, 0)
	49 aload_0 (0, 0)
	50 getfield (0, 0)
	51 org/apache/commons/math3/analysis/solvers/FieldBracketingNthOrderBrentSolver.field:Lorg/apache/commons/math3/Field; (0, 0)
	53 aload_0 (0, 0)
	54 getfield (0, 0)
	55 org/apache/commons/math3/analysis/solvers/FieldBracketingNthOrderBrentSolver.maximalOrder:I (0, 0)
	57 iconst_1 (0, 0)
	58 iadd (0, 0)
	59 invokestatic (0, 0)
	60 org/apache/commons/math3/util/MathArrays.buildArray:(Lorg/apache/commons/math3/Field;I)[Ljava/lang/Object; (0, 0)
	62 checkcast (0, 0)
	63 [Lorg/apache/commons/math3/RealFieldElement; (0, 0)
	65 astore (0, 0)
	66 #9 (0, 0)
	67 aload_0 (0, 0)
	68 getfield (0, 0)
	69 org/apache/commons/math3/analysis/solvers/FieldBracketingNthOrderBrentSolver.field:Lorg/apache/commons/math3/Field; (0, 0)
	71 aload_0 (0, 0)
	72 getfield (0, 0)
	73 org/apache/commons/math3/analysis/solvers/FieldBracketingNthOrderBrentSolver.maximalOrder:I (0, 0)
	75 iconst_1 (0, 0)
	76 iadd (0, 0)
	77 invokestatic (0, 0)
	78 org/apache/commons/math3/util/MathArrays.buildArray:(Lorg/apache/commons/math3/Field;I)[Ljava/lang/Object; (0, 0)
	80 checkcast (0, 0)
	81 [Lorg/apache/commons/math3/RealFieldElement; (0, 0)
	83 astore (0, 0)
	84 #10 (0, 0)
	85 aload (0, 0)
	86 #9 (0, 0)
	87 iconst_0 (0, 0)
	88 aload_3 (0, 0)
	89 aastore (0, 0)
	90 aload (0, 0)
	91 #9 (0, 0)
	92 iconst_1 (0, 0)
	93 aload (0, 0)
	94 #5 (0, 0)
	95 aastore (0, 0)
	96 aload (0, 0)
	97 #9 (0, 0)
	98 iconst_2 (0, 0)
	99 aload (0, 0)
	100 #4 (0, 0)
	101 aastore (0, 0)
	102 aload_0 (0, 0)
	103 getfield (0, 0)
	104 org/apache/commons/math3/analysis/solvers/FieldBracketingNthOrderBrentSolver.evaluations:Lorg/apache/commons/math3/util/IntegerSequence$Incrementor; (0, 0)
	106 invokevirtual (0, 0)
	107 org/apache/commons/math3/util/IntegerSequence$Incrementor.increment:()V (0, 0)
	109 aload (0, 0)
	110 #10 (0, 0)
	111 iconst_1 (0, 0)
	112 aload_2 (0, 0)
	113 aload (0, 0)
	114 #9 (0, 0)
	115 iconst_1 (0, 0)
	116 aaload (0, 0)
	117 invokeinterface (0, 0)
	118 org/apache/commons/math3/analysis/RealFieldUnivariateFunction.getReal:()D (0, 0)
	120 0 (0, 0)
	122 aastore (0, 0)
	123 aload (1, 1)
	124 #10 (1, 1)
	125 iconst_1 (1, 1)
	126 aaload (1, 1)
	127 invokeinterface (1, 1)
	128 org/apache/commons/math3/RealFieldElement.org/apache/commons/math3/util/Precision (1, 1)
	130 0 (1, 1)
	132 dconst_0 (1, 1)
	133 iconst_1 (1, 1)
	134 invokestatic (1, 1)
	135 org/apache/commons/math3/util/Precision.equals:(DDI)Z (1, 1)
	137 ifeq (1, 1)
	138 8 (1, 1)
	140 aload (2, 1)
	141 #9 (2, 1)
	142 iconst_1 (2, 1)
	143 aaload (2, 1)
	144 areturn (2, 1)
	145 aload_0 (0, 0)
	146 getfield (0, 0)
	147 org/apache/commons/math3/analysis/solvers/FieldBracketingNthOrderBrentSolver.evaluations:Lorg/apache/commons/math3/util/IntegerSequence$Incrementor; (0, 0)
	149 invokevirtual (0, 0)
	150 org/apache/commons/math3/util/IntegerSequence$Incrementor.increment:()V (0, 0)
	152 aload (0, 0)
	153 #10 (0, 0)
	154 iconst_0 (0, 0)
	155 aload_2 (0, 0)
	156 aload (0, 0)
	157 #9 (0, 0)
	158 iconst_0 (0, 0)
	159 aaload (0, 0)
	160 invokeinterface (0, 0)
	161 org/apache/commons/math3/analysis/RealFieldUnivariateFunction.getReal:()D (0, 0)
	163 0 (0, 0)
	165 aastore (0, 0)
	166 aload (1, 1)
	167 #10 (1, 1)
	168 iconst_0 (1, 1)
	169 aaload (1, 1)
	170 invokeinterface (1, 1)
	171 org/apache/commons/math3/RealFieldElement.org/apache/commons/math3/util/Precision (1, 1)
	173 0 (1, 1)
	175 dconst_0 (1, 1)
	176 iconst_1 (1, 1)
	177 invokestatic (1, 1)
	178 org/apache/commons/math3/util/Precision.equals:(DDI)Z (1, 1)
	180 ifeq (1, 1)
	181 8 (1, 1)
	183 aload (2, 1)
	184 #9 (2, 1)
	185 iconst_0 (2, 1)
	186 aaload (2, 1)
	187 areturn (2, 1)
	188 aload (1, 1)
	189 #10 (1, 1)
	190 iconst_0 (1, 1)
	191 aaload (1, 1)
	192 aload (1, 1)
	193 #10 (1, 1)
	194 iconst_1 (1, 1)
	195 aaload (1, 1)
	196 invokeinterface (1, 1)
	197 org/apache/commons/math3/RealFieldElement.org/apache/commons/math3/exception/NoBracketingException (1, 1)
	199 0 (1, 1)
	201 checkcast (1, 1)
	202 org/apache/commons/math3/RealFieldElement (1, 1)
	204 invokeinterface (1, 1)
	205 org/apache/commons/math3/RealFieldElement.org/apache/commons/math3/util/Precision (1, 1)
	207 0 (1, 1)
	209 dconst_0 (1, 1)
	210 dcmpg (1, 1)
	211 ifge (1, 1)
	212 12 (1, 1)
	214 iconst_2 (2, 1)
	215 istore (2, 1)
	216 #11 (2, 1)
	217 iconst_1 (2, 1)
	218 istore (2, 1)
	219 #12 (2, 1)
	220 goto (2, 1)
	221 125 (2, 1)
	223 aload_0 (3, 2)
	224 getfield (3, 2)
	225 org/apache/commons/math3/analysis/solvers/FieldBracketingNthOrderBrentSolver.evaluations:Lorg/apache/commons/math3/util/IntegerSequence$Incrementor; (3, 2)
	227 invokevirtual (3, 2)
	228 org/apache/commons/math3/util/IntegerSequence$Incrementor.increment:()V (3, 2)
	230 aload (3, 2)
	231 #10 (3, 2)
	232 iconst_2 (3, 2)
	233 aload_2 (3, 2)
	234 aload (3, 2)
	235 #9 (3, 2)
	236 iconst_2 (3, 2)
	237 aaload (3, 2)
	238 invokeinterface (3, 2)
	239 org/apache/commons/math3/analysis/RealFieldUnivariateFunction.getReal:()D (3, 2)
	241 0 (3, 2)
	243 aastore (3, 2)
	244 aload (4, 1)
	245 #10 (4, 1)
	246 iconst_2 (4, 1)
	247 aaload (4, 1)
	248 invokeinterface (4, 1)
	249 org/apache/commons/math3/RealFieldElement.org/apache/commons/math3/util/Precision (4, 1)
	251 0 (4, 1)
	253 dconst_0 (4, 1)
	254 iconst_1 (4, 1)
	255 invokestatic (4, 1)
	256 org/apache/commons/math3/util/Precision.equals:(DDI)Z (4, 1)
	258 ifeq (4, 1)
	259 8 (4, 1)
	261 aload (5, 1)
	262 #9 (5, 1)
	263 iconst_2 (5, 1)
	264 aaload (5, 1)
	265 areturn (5, 1)
	266 aload (4, 1)
	267 #10 (4, 1)
	268 iconst_1 (4, 1)
	269 aaload (4, 1)
	270 aload (4, 1)
	271 #10 (4, 1)
	272 iconst_2 (4, 1)
	273 aaload (4, 1)
	274 invokeinterface (4, 1)
	275 org/apache/commons/math3/RealFieldElement.org/apache/commons/math3/exception/NoBracketingException (4, 1)
	277 0 (4, 1)
	279 checkcast (4, 1)
	280 org/apache/commons/math3/RealFieldElement (4, 1)
	282 invokeinterface (4, 1)
	283 org/apache/commons/math3/RealFieldElement.org/apache/commons/math3/util/Precision (4, 1)
	285 0 (4, 1)
	287 dconst_0 (4, 1)
	288 dcmpg (4, 1)
	289 ifge (4, 1)
	290 12 (4, 1)
	292 iconst_3 (5, 4)
	293 istore (5, 4)
	294 #11 (5, 4)
	295 iconst_2 (5, 4)
	296 istore (5, 4)
	297 #12 (5, 4)
	298 goto (5, 4)
	299 47 (5, 4)
	301 new (6, 2)
	302 org/apache/commons/math3/exception/NoBracketingException (6, 2)
	304 dup (6, 2)
	305 aload (6, 2)
	306 #9 (6, 2)
	307 iconst_0 (6, 2)
	308 aaload (6, 2)
	309 invokeinterface (6, 2)
	310 org/apache/commons/math3/RealFieldElement.org/apache/commons/math3/util/Precision (6, 2)
	312 0 (6, 2)
	314 aload (6, 2)
	315 #9 (6, 2)
	316 iconst_2 (6, 2)
	317 aaload (6, 2)
	318 invokeinterface (6, 2)
	319 org/apache/commons/math3/RealFieldElement.org/apache/commons/math3/util/Precision (6, 2)
	321 0 (6, 2)
	323 aload (6, 2)
	324 #10 (6, 2)
	325 iconst_0 (6, 2)
	326 aaload (6, 2)
	327 invokeinterface (6, 2)
	328 org/apache/commons/math3/RealFieldElement.org/apache/commons/math3/util/Precision (6, 2)
	330 0 (6, 2)
	332 aload (6, 2)
	333 #10 (6, 2)
	334 iconst_2 (6, 2)
	335 aaload (6, 2)
	336 invokeinterface (6, 2)
	337 org/apache/commons/math3/RealFieldElement.org/apache/commons/math3/util/Precision (6, 2)
	339 0 (6, 2)
	341 invokespecial (6, 2)
	342 org/apache/commons/math3/exception/NoBracketingException.<init>:(DDDD)V (6, 2)
	344 athrow (6, 2)
	345 aload_0 (1, 4)
	346 getfield (1, 4)
	347 org/apache/commons/math3/analysis/solvers/FieldBracketingNthOrderBrentSolver.field:Lorg/apache/commons/math3/Field; (1, 4)
	349 aload (1, 4)
	350 #9 (1, 4)
	351 arraylength (1, 4)
	352 invokestatic (1, 4)
	353 org/apache/commons/math3/util/MathArrays.buildArray:(Lorg/apache/commons/math3/Field;I)[Ljava/lang/Object; (1, 4)
	355 checkcast (1, 4)
	356 [Lorg/apache/commons/math3/RealFieldElement; (1, 4)
	358 astore (1, 4)
	359 #13 (1, 4)
	360 aload (1, 4)
	361 #9 (1, 4)
	362 iload (1, 4)
	363 #12 (1, 4)
	364 iconst_1 (1, 4)
	365 isub (1, 4)
	366 aaload (1, 4)
	367 astore (1, 4)
	368 #14 (1, 4)
	369 aload (1, 4)
	370 #10 (1, 4)
	371 iload (1, 4)
	372 #12 (1, 4)
	373 iconst_1 (1, 4)
	374 isub (1, 4)
	375 aaload (1, 4)
	376 astore (1, 4)
	377 #15 (1, 4)
	378 aload (1, 4)
	379 #14 (1, 4)
	380 invokeinterface (1, 4)
	381 org/apache/commons/math3/RealFieldElement.subtract:(Ljava/lang/Object;)Ljava/lang/Object; (1, 4)
	383 0 (1, 4)
	385 checkcast (1, 4)
	386 org/apache/commons/math3/RealFieldElement (1, 4)
	388 astore (1, 4)
	389 #16 (1, 4)
	390 aload (1, 4)
	391 #15 (1, 4)
	392 invokeinterface (1, 4)
	393 org/apache/commons/math3/RealFieldElement.subtract:(Ljava/lang/Object;)Ljava/lang/Object; (1, 4)
	395 0 (1, 4)
	397 checkcast (1, 4)
	398 org/apache/commons/math3/RealFieldElement (1, 4)
	400 astore (1, 4)
	401 #17 (1, 4)
	402 iconst_0 (1, 4)
	403 istore (1, 4)
	404 #18 (1, 4)
	405 aload (1, 4)
	406 #9 (1, 4)
	407 iload (1, 4)
	408 #12 (1, 4)
	409 aaload (1, 4)
	410 astore (1, 4)
	411 #19 (1, 4)
	412 aload (1, 4)
	413 #10 (1, 4)
	414 iload (1, 4)
	415 #12 (1, 4)
	416 aaload (1, 4)
	417 astore (1, 4)
	418 #20 (1, 4)
	419 aload (1, 4)
	420 #19 (1, 4)
	421 invokeinterface (1, 4)
	422 org/apache/commons/math3/RealFieldElement.subtract:(Ljava/lang/Object;)Ljava/lang/Object; (1, 4)
	424 0 (1, 4)
	426 checkcast (1, 4)
	427 org/apache/commons/math3/RealFieldElement (1, 4)
	429 astore (1, 4)
	430 #21 (1, 4)
	431 aload (1, 4)
	432 #20 (1, 4)
	433 invokeinterface (1, 4)
	434 org/apache/commons/math3/RealFieldElement.subtract:(Ljava/lang/Object;)Ljava/lang/Object; (1, 4)
	436 0 (1, 4)
	438 checkcast (1, 4)
	439 org/apache/commons/math3/RealFieldElement (1, 4)
	441 astore (1, 4)
	442 #22 (1, 4)
	443 iconst_0 (1, 4)
	444 istore (1, 4)
	445 #23 (1, 4)
	446 aload (2, 3)
	447 #16 (2, 3)
	448 aload (2, 3)
	449 #21 (2, 3)
	450 invokeinterface (2, 3)
	451 org/apache/commons/math3/RealFieldElement.$SwitchMap$org$apache$commons$math3$analysis$solvers$AllowedSolution:[I (2, 3)
	453 0 (2, 3)
	455 checkcast (2, 3)
	456 org/apache/commons/math3/RealFieldElement (2, 3)
	458 invokeinterface (2, 3)
	459 org/apache/commons/math3/RealFieldElement.org/apache/commons/math3/util/Precision (2, 3)
	461 0 (2, 3)
	463 dconst_0 (2, 3)
	464 dcmpg (2, 3)
	465 ifge (2, 3)
	466 8 (2, 3)
	468 aload (2, 3)
	469 #21 (2, 3)
	470 goto (2, 3)
	471 5 (2, 3)
	473 aload (2, 3)
	474 #16 (2, 3)
	475 astore (2, 3)
	476 #24 (2, 3)
	477 aload (2, 3)
	478 #17 (2, 3)
	479 aload (2, 3)
	480 #22 (2, 3)
	481 invokeinterface (2, 3)
	482 org/apache/commons/math3/RealFieldElement.$SwitchMap$org$apache$commons$math3$analysis$solvers$AllowedSolution:[I (2, 3)
	484 0 (2, 3)
	486 checkcast (2, 3)
	487 org/apache/commons/math3/RealFieldElement (2, 3)
	489 invokeinterface (2, 3)
	490 org/apache/commons/math3/RealFieldElement.org/apache/commons/math3/util/Precision (2, 3)
	492 0 (2, 3)
	494 dconst_0 (2, 3)
	495 dcmpg (2, 3)
	496 ifge (2, 3)
	497 8 (2, 3)
	499 aload (2, 3)
	500 #22 (2, 3)
	501 goto (2, 3)
	502 5 (2, 3)
	504 aload (2, 3)
	505 #17 (2, 3)
	506 astore (2, 3)
	507 #25 (2, 3)
	508 aload_0 (2, 3)
	509 getfield (2, 3)
	510 org/apache/commons/math3/analysis/solvers/FieldBracketingNthOrderBrentSolver.absoluteAccuracy:Lorg/apache/commons/math3/RealFieldElement; (2, 3)
	512 aload_0 (2, 3)
	513 getfield (2, 3)
	514 org/apache/commons/math3/analysis/solvers/FieldBracketingNthOrderBrentSolver.relativeAccuracy:Lorg/apache/commons/math3/RealFieldElement; (2, 3)
	516 aload (2, 3)
	517 #24 (2, 3)
	518 invokeinterface (2, 3)
	519 org/apache/commons/math3/RealFieldElement.org/apache/commons/math3/exception/NoBracketingException (2, 3)
	521 0 (2, 3)
	523 invokeinterface (2, 3)
	524 org/apache/commons/math3/RealFieldElement.org/apache/commons/math3/RealFieldElement (2, 3)
	526 0 (2, 3)
	528 checkcast (2, 3)
	529 org/apache/commons/math3/RealFieldElement (2, 3)
	531 astore (2, 3)
	532 #26 (2, 3)
	533 aload (3, 1)
	534 #19 (3, 1)
	535 aload (3, 1)
	536 #14 (3, 1)
	537 invokeinterface (3, 1)
	538 org/apache/commons/math3/RealFieldElement.$SwitchMap$org$apache$commons$math3$analysis$solvers$AllowedSolution:[I (3, 1)
	540 0 (3, 1)
	542 checkcast (3, 1)
	543 org/apache/commons/math3/RealFieldElement (3, 1)
	545 aload (3, 1)
	546 #26 (3, 1)
	547 invokeinterface (3, 1)
	548 org/apache/commons/math3/RealFieldElement.$SwitchMap$org$apache$commons$math3$analysis$solvers$AllowedSolution:[I (3, 1)
	550 0 (3, 1)
	552 checkcast (3, 1)
	553 org/apache/commons/math3/RealFieldElement (3, 1)
	555 invokeinterface (3, 1)
	556 org/apache/commons/math3/RealFieldElement.org/apache/commons/math3/util/Precision (3, 1)
	558 0 (3, 1)
	560 dconst_0 (3, 1)
	561 dcmpg (3, 1)
	562 ifle (3, 1)
	563 27 (3, 1)
	565 aload (3, 1)
	566 #25 (3, 1)
	567 aload_0 (3, 1)
	568 getfield (3, 1)
	569 org/apache/commons/math3/analysis/solvers/FieldBracketingNthOrderBrentSolver.functionValueAccuracy:Lorg/apache/commons/math3/RealFieldElement; (3, 1)
	571 invokeinterface (3, 1)
	572 org/apache/commons/math3/RealFieldElement.$SwitchMap$org$apache$commons$math3$analysis$solvers$AllowedSolution:[I (3, 1)
	574 0 (3, 1)
	576 checkcast (3, 1)
	577 org/apache/commons/math3/RealFieldElement (3, 1)
	579 invokeinterface (3, 1)
	580 org/apache/commons/math3/RealFieldElement.org/apache/commons/math3/util/Precision (3, 1)
	582 0 (3, 1)
	584 dconst_0 (3, 1)
	585 dcmpg (3, 1)
	586 ifge (3, 1)
	587 131 (3, 1)
	589 getstatic (4, 5)
	590 org/apache/commons/math3/analysis/solvers/FieldBracketingNthOrderBrentSolver$1.$SwitchMap$org$apache$commons$math3$analysis$solvers$AllowedSolution:[I (4, 5)
	592 aload (4, 5)
	593 #6 (4, 5)
	594 invokevirtual (4, 5)
	595 org/apache/commons/math3/analysis/solvers/AllowedSolution.ordinal:()I (4, 5)
	597 iaload (4, 5)
	598 tableswitch (4, 5)
	599 1 632 (4, 5)
	603 2 662 (4, 5)
	607 3 665 (4, 5)
	611 4 668 (4, 5)
	615 5 688 (4, 5)
	632 aload (4, 5)
	633 #17 (4, 5)
	634 aload (4, 5)
	635 #22 (4, 5)
	636 invokeinterface (4, 5)
	637 org/apache/commons/math3/RealFieldElement.$SwitchMap$org$apache$commons$math3$analysis$solvers$AllowedSolution:[I (4, 5)
	639 0 (4, 5)
	641 checkcast (4, 5)
	642 org/apache/commons/math3/RealFieldElement (4, 5)
	644 invokeinterface (4, 5)
	645 org/apache/commons/math3/RealFieldElement.org/apache/commons/math3/util/Precision (4, 5)
	647 0 (4, 5)
	649 dconst_0 (4, 5)
	650 dcmpg (4, 5)
	651 ifge (4, 5)
	652 8 (4, 5)
	654 aload (4, 5)
	655 #14 (4, 5)
	656 goto (4, 5)
	657 5 (4, 5)
	659 aload (4, 5)
	660 #19 (4, 5)
	661 areturn (4, 5)
	662 aload (4, 5)
	663 #14 (4, 5)
	664 areturn (4, 5)
	665 aload (4, 5)
	666 #19 (4, 5)
	667 areturn (4, 5)
	668 aload (4, 5)
	669 #15 (4, 5)
	670 invokeinterface (4, 5)
	671 org/apache/commons/math3/RealFieldElement.org/apache/commons/math3/util/Precision (4, 5)
	673 0 (4, 5)
	675 dconst_0 (4, 5)
	676 dcmpg (4, 5)
	677 ifgt (4, 5)
	678 8 (4, 5)
	680 aload (4, 5)
	681 #14 (4, 5)
	682 goto (4, 5)
	683 5 (4, 5)
	685 aload (4, 5)
	686 #19 (4, 5)
	687 areturn (4, 5)
	688 aload (4, 5)
	689 #15 (4, 5)
	690 invokeinterface (4, 5)
	691 org/apache/commons/math3/RealFieldElement.org/apache/commons/math3/util/Precision (4, 5)
	693 0 (4, 5)
	695 dconst_0 (4, 5)
	696 dcmpg (4, 5)
	697 ifge (4, 5)
	698 8 (4, 5)
	700 aload (4, 5)
	701 #19 (4, 5)
	702 goto (4, 5)
	703 5 (4, 5)
	705 aload (4, 5)
	706 #14 (4, 5)
	707 areturn (4, 5)
	708 new (4, 5)
	709 org/apache/commons/math3/exception/MathInternalError (4, 5)
	711 dup (4, 5)
	712 aconst_null (4, 5)
	713 invokespecial (4, 5)
	714 org/apache/commons/math3/exception/MathInternalError.<init>:(Ljava/lang/Throwable;)V (4, 5)
	716 athrow (4, 5)
	717 iload (5, 1)
	718 #18 (5, 1)
	719 iconst_2 (5, 1)
	720 if_icmplt (5, 1)
	721 29 (5, 1)
	723 aload (5, 1)
	724 #20 (5, 1)
	725 ldc2_w (5, 1)
	726 16.0 (5, 1)
	728 invokeinterface (5, 1)
	729 org/apache/commons/math3/RealFieldElement.solve:(ILorg/apache/commons/math3/analysis/RealFieldUnivariateFunction;Lorg/apache/commons/math3/RealFieldElement;Lorg/apache/commons/math3/RealFieldElement;Lorg/apache/commons/math3/RealFieldElement;Lorg/apache/commons/math3/analysis/solvers/AllowedSolution;)Lorg/apache/commons/math3/RealFieldElement; (5, 1)
	731 0 (5, 1)
	733 checkcast (5, 1)
	734 org/apache/commons/math3/RealFieldElement (5, 1)
	736 invokeinterface (5, 1)
	737 org/apache/commons/math3/RealFieldElement.java/lang/System (5, 1)
	739 0 (5, 1)
	741 checkcast (5, 1)
	742 org/apache/commons/math3/RealFieldElement (5, 1)
	744 astore (5, 1)
	745 #27 (5, 1)
	746 goto (5, 1)
	747 39 (5, 1)
	749 iload (6, 1)
	750 #23 (6, 1)
	751 iconst_2 (6, 1)
	752 if_icmplt (6, 1)
	753 29 (6, 1)
	755 aload (6, 1)
	756 #15 (6, 1)
	757 ldc2_w (6, 1)
	758 16.0 (6, 1)
	760 invokeinterface (6, 1)
	761 org/apache/commons/math3/RealFieldElement.solve:(ILorg/apache/commons/math3/analysis/RealFieldUnivariateFunction;Lorg/apache/commons/math3/RealFieldElement;Lorg/apache/commons/math3/RealFieldElement;Lorg/apache/commons/math3/RealFieldElement;Lorg/apache/commons/math3/analysis/solvers/AllowedSolution;)Lorg/apache/commons/math3/RealFieldElement; (6, 1)
	763 0 (6, 1)
	765 checkcast (6, 1)
	766 org/apache/commons/math3/RealFieldElement (6, 1)
	768 invokeinterface (6, 1)
	769 org/apache/commons/math3/RealFieldElement.java/lang/System (6, 1)
	771 0 (6, 1)
	773 checkcast (6, 1)
	774 org/apache/commons/math3/RealFieldElement (6, 1)
	776 astore (6, 1)
	777 #27 (6, 1)
	778 goto (6, 1)
	779 7 (6, 1)
	781 aload (7, 2)
	782 #7 (7, 2)
	783 astore (7, 2)
	784 #27 (7, 2)
	785 iconst_0 (4, 4)
	786 istore (4, 4)
	787 #29 (4, 4)
	788 iload (4, 4)
	789 #11 (4, 4)
	790 istore (4, 4)
	791 #30 (4, 4)
	792 aload (5, 4)
	793 #9 (5, 4)
	794 iload (5, 4)
	795 #29 (5, 4)
	796 aload (5, 4)
	797 #13 (5, 4)
	798 iload (5, 4)
	799 #29 (5, 4)
	800 iload (5, 4)
	801 #30 (5, 4)
	802 iload (5, 4)
	803 #29 (5, 4)
	804 isub (5, 4)
	805 invokestatic (5, 4)
	806 java/lang/System.arraycopy:(Ljava/lang/Object;ILjava/lang/Object;II)V (5, 4)
	808 aload_0 (5, 4)
	809 aload (5, 4)
	810 #27 (5, 4)
	811 aload (5, 4)
	812 #13 (5, 4)
	813 aload (5, 4)
	814 #10 (5, 4)
	815 iload (5, 4)
	816 #29 (5, 4)
	817 iload (5, 4)
	818 #30 (5, 4)
	819 invokespecial (5, 4)
	820 org/apache/commons/math3/analysis/solvers/FieldBracketingNthOrderBrentSolver.guessX:(Lorg/apache/commons/math3/RealFieldElement;[Lorg/apache/commons/math3/RealFieldElement;[Lorg/apache/commons/math3/RealFieldElement;II)Lorg/apache/commons/math3/RealFieldElement; (5, 4)
	822 astore (5, 4)
	823 #28 (5, 4)
	824 aload (6, 1)
	825 #28 (6, 1)
	826 aload (6, 1)
	827 #14 (6, 1)
	828 invokeinterface (6, 1)
	829 org/apache/commons/math3/RealFieldElement.$SwitchMap$org$apache$commons$math3$analysis$solvers$AllowedSolution:[I (6, 1)
	831 0 (6, 1)
	833 checkcast (6, 1)
	834 org/apache/commons/math3/RealFieldElement (6, 1)
	836 invokeinterface (6, 1)
	837 org/apache/commons/math3/RealFieldElement.org/apache/commons/math3/util/Precision (6, 1)
	839 0 (6, 1)
	841 dconst_0 (6, 1)
	842 dcmpl (6, 1)
	843 ifle (6, 1)
	844 25 (6, 1)
	846 aload (6, 1)
	847 #28 (6, 1)
	848 aload (6, 1)
	849 #19 (6, 1)
	850 invokeinterface (6, 1)
	851 org/apache/commons/math3/RealFieldElement.$SwitchMap$org$apache$commons$math3$analysis$solvers$AllowedSolution:[I (6, 1)
	853 0 (6, 1)
	855 checkcast (6, 1)
	856 org/apache/commons/math3/RealFieldElement (6, 1)
	858 invokeinterface (6, 1)
	859 org/apache/commons/math3/RealFieldElement.org/apache/commons/math3/util/Precision (6, 1)
	861 0 (6, 1)
	863 dconst_0 (6, 1)
	864 dcmpg (6, 1)
	865 iflt (6, 1)
	866 29 (6, 1)
	868 iload (7, 1)
	869 #12 (7, 1)
	870 iload (7, 1)
	871 #29 (7, 1)
	872 isub (7, 1)
	873 iload (7, 1)
	874 #30 (7, 1)
	875 iload (7, 1)
	876 #12 (7, 1)
	877 isub (7, 1)
	878 if_icmplt (7, 1)
	879 9 (7, 1)
	881 iinc (8, 4)
	882 #29 (8, 4)
	883 -89 (8, 4)
	884 goto (8, 4)
	885 6 (8, 4)
	887 iinc (9, 2)
	888 #30 (9, 2)
	889 25 (9, 2)
	890 aload (6, 1)
	891 #8 (6, 1)
	892 astore (6, 1)
	893 #28 (6, 1)
	894 aload (6, 3)
	895 #28 (6, 3)
	896 invokeinterface (6, 3)
	897 org/apache/commons/math3/RealFieldElement.org/apache/commons/math3/util/Precision (6, 3)
	899 0 (6, 3)
	901 invokestatic (6, 3)
	902 java/lang/Double.isNaN:(D)Z (6, 3)
	904 ifeq (6, 3)
	905 12 (6, 3)
	907 iload (6, 3)
	908 #30 (6, 3)
	909 iload (6, 3)
	910 #29 (6, 3)
	911 isub (6, 3)
	912 iconst_1 (6, 3)
	913 if_icmpgt (6, 3)
	914 -121 (6, 3)
	916 aload (7, 1)
	917 #28 (7, 1)
	918 invokeinterface (7, 1)
	919 org/apache/commons/math3/RealFieldElement.org/apache/commons/math3/util/Precision (7, 1)
	921 0 (7, 1)
	923 invokestatic (7, 1)
	924 java/lang/Double.isNaN:(D)Z (7, 1)
	926 ifeq (7, 1)
	927 45 (7, 1)
	929 aload (7, 1)
	930 #14 (7, 1)
	931 aload (7, 1)
	932 #19 (7, 1)
	933 aload (7, 1)
	934 #14 (7, 1)
	935 invokeinterface (7, 1)
	936 org/apache/commons/math3/RealFieldElement.$SwitchMap$org$apache$commons$math3$analysis$solvers$AllowedSolution:[I (7, 1)
	938 0 (7, 1)
	940 checkcast (7, 1)
	941 org/apache/commons/math3/RealFieldElement (7, 1)
	943 ldc2_w (7, 1)
	944 2.0 (7, 1)
	946 invokeinterface (7, 1)
	947 org/apache/commons/math3/RealFieldElement.solve:(ILorg/apache/commons/math3/analysis/RealFieldUnivariateFunction;Lorg/apache/commons/math3/RealFieldElement;Lorg/apache/commons/math3/RealFieldElement;Lorg/apache/commons/math3/RealFieldElement;Lorg/apache/commons/math3/analysis/solvers/AllowedSolution;)Lorg/apache/commons/math3/RealFieldElement; (7, 1)
	949 0 (7, 1)
	951 invokeinterface (7, 1)
	952 org/apache/commons/math3/RealFieldElement.org/apache/commons/math3/RealFieldElement (7, 1)
	954 0 (7, 1)
	956 checkcast (7, 1)
	957 org/apache/commons/math3/RealFieldElement (7, 1)
	959 astore (7, 1)
	960 #28 (7, 1)
	961 iload (7, 1)
	962 #12 (7, 1)
	963 iconst_1 (7, 1)
	964 isub (7, 1)
	965 istore (7, 1)
	966 #29 (7, 1)
	967 iload (7, 1)
	968 #12 (7, 1)
	969 istore (7, 1)
	970 #30 (7, 1)
	971 aload_0 (6, 3)
	972 getfield (6, 3)
	973 org/apache/commons/math3/analysis/solvers/FieldBracketingNthOrderBrentSolver.evaluations:Lorg/apache/commons/math3/util/IntegerSequence$Incrementor; (6, 3)
	975 invokevirtual (6, 3)
	976 org/apache/commons/math3/util/IntegerSequence$Incrementor.increment:()V (6, 3)
	978 aload_2 (6, 3)
	979 aload (6, 3)
	980 #28 (6, 3)
	981 invokeinterface (6, 3)
	982 org/apache/commons/math3/analysis/RealFieldUnivariateFunction.getReal:()D (6, 3)
	984 0 (6, 3)
	986 astore (6, 3)
	987 #31 (6, 3)
	988 aload (7, 1)
	989 #31 (7, 1)
	990 invokeinterface (7, 1)
	991 org/apache/commons/math3/RealFieldElement.org/apache/commons/math3/util/Precision (7, 1)
	993 0 (7, 1)
	995 dconst_0 (7, 1)
	996 iconst_1 (7, 1)
	997 invokestatic (7, 1)
	998 org/apache/commons/math3/util/Precision.equals:(DDI)Z (7, 1)
	1000 ifeq (7, 1)
	1001 6 (7, 1)
	1003 aload (7, 1)
	1004 #28 (7, 1)
	1005 areturn (7, 1)
	1006 iload (7, 1)
	1007 #11 (7, 1)
	1008 iconst_2 (7, 1)
	1009 if_icmple (7, 1)
	1010 54 (7, 1)
	1012 iload (7, 1)
	1013 #30 (7, 1)
	1014 iload (7, 1)
	1015 #29 (7, 1)
	1016 isub (7, 1)
	1017 iload (7, 1)
	1018 #11 (7, 1)
	1019 if_icmpeq (7, 1)
	1020 44 (7, 1)
	1022 iload (8, 4)
	1023 #30 (8, 4)
	1024 iload (8, 4)
	1025 #29 (8, 4)
	1026 isub (8, 4)
	1027 istore (8, 4)
	1028 #11 (8, 4)
	1029 aload (8, 4)
	1030 #9 (8, 4)
	1031 iload (8, 4)
	1032 #29 (8, 4)
	1033 aload (8, 4)
	1034 #9 (8, 4)
	1035 iconst_0 (8, 4)
	1036 iload (8, 4)
	1037 #11 (8, 4)
	1038 invokestatic (8, 4)
	1039 java/lang/System.arraycopy:(Ljava/lang/Object;ILjava/lang/Object;II)V (8, 4)
	1041 aload (8, 4)
	1042 #10 (8, 4)
	1043 iload (8, 4)
	1044 #29 (8, 4)
	1045 aload (8, 4)
	1046 #10 (8, 4)
	1047 iconst_0 (8, 4)
	1048 iload (8, 4)
	1049 #11 (8, 4)
	1050 invokestatic (8, 4)
	1051 java/lang/System.arraycopy:(Ljava/lang/Object;ILjava/lang/Object;II)V (8, 4)
	1053 iload (8, 4)
	1054 #12 (8, 4)
	1055 iload (8, 4)
	1056 #29 (8, 4)
	1057 isub (8, 4)
	1058 istore (8, 4)
	1059 #12 (8, 4)
	1060 goto (8, 4)
	1061 51 (8, 4)
	1063 iload (9, 1)
	1064 #11 (9, 1)
	1065 aload (9, 1)
	1066 #9 (9, 1)
	1067 arraylength (9, 1)
	1068 if_icmpne (9, 1)
	1069 43 (9, 1)
	1071 iinc (9, 1)
	1072 #11 (9, 1)
	1073 21 (9, 1)
	1074 iload (10, 1)
	1075 #12 (10, 1)
	1076 aload (10, 1)
	1077 #9 (10, 1)
	1078 arraylength (10, 1)
	1079 iconst_1 (10, 1)
	1080 iadd (10, 1)
	1081 iconst_2 (10, 1)
	1082 idiv (10, 1)
	1083 if_icmplt (10, 1)
	1084 28 (10, 1)
	1086 aload (11, 1)
	1087 #9 (11, 1)
	1088 iconst_1 (11, 1)
	1089 aload (11, 1)
	1090 #9 (11, 1)
	1091 iconst_0 (11, 1)
	1092 iload (11, 1)
	1093 #11 (11, 1)
	1094 invokestatic (11, 1)
	1095 java/lang/System.arraycopy:(Ljava/lang/Object;ILjava/lang/Object;II)V (11, 1)
	1097 aload (11, 1)
	1098 #10 (11, 1)
	1099 iconst_1 (11, 1)
	1100 aload (11, 1)
	1101 #10 (11, 1)
	1102 iconst_0 (11, 1)
	1103 iload (11, 1)
	1104 #11 (11, 1)
	1105 invokestatic (11, 1)
	1106 java/lang/System.arraycopy:(Ljava/lang/Object;ILjava/lang/Object;II)V (11, 1)
	1108 iinc (11, 1)
	1109 #12 (11, 1)
	1110 25 (11, 1)
	1111 aload (6, 3)
	1112 #9 (6, 3)
	1113 iload (6, 3)
	1114 #12 (6, 3)
	1115 aload (6, 3)
	1116 #9 (6, 3)
	1117 iload (6, 3)
	1118 #12 (6, 3)
	1119 iconst_1 (6, 3)
	1120 iadd (6, 3)
	1121 iload (6, 3)
	1122 #11 (6, 3)
	1123 iload (6, 3)
	1124 #12 (6, 3)
	1125 isub (6, 3)
	1126 invokestatic (6, 3)
	1127 java/lang/System.arraycopy:(Ljava/lang/Object;ILjava/lang/Object;II)V (6, 3)
	1129 aload (6, 3)
	1130 #9 (6, 3)
	1131 iload (6, 3)
	1132 #12 (6, 3)
	1133 aload (6, 3)
	1134 #28 (6, 3)
	1135 aastore (6, 3)
	1136 aload (6, 3)
	1137 #10 (6, 3)
	1138 iload (6, 3)
	1139 #12 (6, 3)
	1140 aload (6, 3)
	1141 #10 (6, 3)
	1142 iload (6, 3)
	1143 #12 (6, 3)
	1144 iconst_1 (6, 3)
	1145 iadd (6, 3)
	1146 iload (6, 3)
	1147 #11 (6, 3)
	1148 iload (6, 3)
	1149 #12 (6, 3)
	1150 isub (6, 3)
	1151 invokestatic (6, 3)
	1152 java/lang/System.arraycopy:(Ljava/lang/Object;ILjava/lang/Object;II)V (6, 3)
	1154 aload (6, 3)
	1155 #10 (6, 3)
	1156 iload (6, 3)
	1157 #12 (6, 3)
	1158 aload (6, 3)
	1159 #31 (6, 3)
	1160 aastore (6, 3)
	1161 iinc (6, 3)
	1162 #11 (6, 3)
	1163 25 (6, 3)
	1164 aload (7, 1)
	1165 #31 (7, 1)
	1166 aload (7, 1)
	1167 #15 (7, 1)
	1168 invokeinterface (7, 1)
	1169 org/apache/commons/math3/RealFieldElement.org/apache/commons/math3/exception/NoBracketingException (7, 1)
	1171 0 (7, 1)
	1173 checkcast (7, 1)
	1174 org/apache/commons/math3/RealFieldElement (7, 1)
	1176 invokeinterface (7, 1)
	1177 org/apache/commons/math3/RealFieldElement.org/apache/commons/math3/util/Precision (7, 1)
	1179 0 (7, 1)
	1181 dconst_0 (7, 1)
	1182 dcmpg (7, 1)
	1183 ifgt (7, 1)
	1184 32 (7, 1)
	1186 aload (8, 4)
	1187 #28 (8, 4)
	1188 astore (8, 4)
	1189 #19 (8, 4)
	1190 aload (8, 4)
	1191 #31 (8, 4)
	1192 astore (8, 4)
	1193 #20 (8, 4)
	1194 aload (8, 4)
	1195 #20 (8, 4)
	1196 invokeinterface (8, 4)
	1197 org/apache/commons/math3/RealFieldElement.subtract:(Ljava/lang/Object;)Ljava/lang/Object; (8, 4)
	1199 0 (8, 4)
	1201 checkcast (8, 4)
	1202 org/apache/commons/math3/RealFieldElement (8, 4)
	1204 astore (8, 4)
	1205 #22 (8, 4)
	1206 iinc (8, 4)
	1207 #18 (8, 4)
	1208 3 (8, 4)
	1209 iconst_0 (8, 4)
	1210 istore (8, 4)
	1211 #23 (8, 4)
	1212 goto (8, 4)
	1213 32 (8, 4)
	1215 aload (9, 2)
	1216 #28 (9, 2)
	1217 astore (9, 2)
	1218 #14 (9, 2)
	1219 aload (9, 2)
	1220 #31 (9, 2)
	1221 astore (9, 2)
	1222 #15 (9, 2)
	1223 aload (9, 2)
	1224 #15 (9, 2)
	1225 invokeinterface (9, 2)
	1226 org/apache/commons/math3/RealFieldElement.subtract:(Ljava/lang/Object;)Ljava/lang/Object; (9, 2)
	1228 0 (9, 2)
	1230 checkcast (9, 2)
	1231 org/apache/commons/math3/RealFieldElement (9, 2)
	1233 astore (9, 2)
	1234 #17 (9, 2)
	1235 iconst_0 (9, 2)
	1236 istore (9, 2)
	1237 #18 (9, 2)
	1238 iinc (9, 2)
	1239 #23 (9, 2)
	1240 -124 (9, 2)
	1241 iinc (9, 2)
	1242 #12 (9, 2)
	1243 -89 (9, 2)
	1244 goto (0, 4)
	1245 -798 (1, 4)

Method: guessX
	0 iload (1, 4)
	1 #4 (1, 4)
	2 istore (1, 4)
	3 #6 (1, 4)
	4 iload (1, 4)
	5 #6 (1, 4)
	6 iload (1, 4)
	7 #5 (1, 4)
	8 iconst_1 (1, 4)
	9 isub (1, 4)
	10 if_icmpge (1, 4)
	11 83 (1, 4)
	13 iload (1, 4)
	14 #6 (1, 4)
	15 iconst_1 (1, 4)
	16 iadd (1, 4)
	17 iload (1, 4)
	18 #4 (1, 4)
	19 isub (1, 4)
	20 istore (1, 4)
	21 #7 (1, 4)
	22 iload (2, 4)
	23 #5 (2, 4)
	24 iconst_1 (2, 4)
	25 isub (2, 4)
	26 istore (2, 4)
	27 #8 (2, 4)
	28 iload (2, 4)
	29 #8 (2, 4)
	30 iload (2, 4)
	31 #6 (2, 4)
	32 if_icmple (2, 4)
	33 55 (2, 4)
	35 aload_2 (2, 4)
	36 iload (2, 4)
	37 #8 (2, 4)
	38 aload_2 (2, 4)
	39 iload (2, 4)
	40 #8 (2, 4)
	41 aaload (2, 4)
	42 aload_2 (2, 4)
	43 iload (2, 4)
	44 #8 (2, 4)
	45 iconst_1 (2, 4)
	46 isub (2, 4)
	47 aaload (2, 4)
	48 invokeinterface (2, 4)
	49 org/apache/commons/math3/RealFieldElement.$SwitchMap$org$apache$commons$math3$analysis$solvers$AllowedSolution:[I (2, 4)
	51 0 (2, 4)
	53 checkcast (2, 4)
	54 org/apache/commons/math3/RealFieldElement (2, 4)
	56 aload_3 (2, 4)
	57 iload (2, 4)
	58 #8 (2, 4)
	59 aaload (2, 4)
	60 aload_3 (2, 4)
	61 iload (2, 4)
	62 #8 (2, 4)
	63 iload (2, 4)
	64 #7 (2, 4)
	65 isub (2, 4)
	66 aaload (2, 4)
	67 invokeinterface (2, 4)
	68 org/apache/commons/math3/RealFieldElement.$SwitchMap$org$apache$commons$math3$analysis$solvers$AllowedSolution:[I (2, 4)
	70 0 (2, 4)
	72 invokeinterface (2, 4)
	73 org/apache/commons/math3/RealFieldElement.java/lang/Object (2, 4)
	75 0 (2, 4)
	77 checkcast (2, 4)
	78 org/apache/commons/math3/RealFieldElement (2, 4)
	80 aastore (2, 4)
	81 iinc (2, 4)
	82 #8 (2, 4)
	83 -89 (2, 4)
	84 goto (2, 4)
	85 -56 (2, 4)
	87 iinc (2, 4)
	88 #6 (2, 4)
	89 -89 (2, 4)
	90 goto (2, 4)
	91 -86 (2, 4)
	93 aload_0 (1, 4)
	94 getfield (1, 4)
	95 org/apache/commons/math3/analysis/solvers/FieldBracketingNthOrderBrentSolver.field:Lorg/apache/commons/math3/Field; (1, 4)
	97 invokeinterface (1, 4)
	98 org/apache/commons/math3/Field.java/lang/Double (1, 4)
	100 0 (1, 4)
	102 checkcast (1, 4)
	103 org/apache/commons/math3/RealFieldElement (1, 4)
	105 astore (1, 4)
	106 #6 (1, 4)
	107 iload (2, 4)
	108 #5 (2, 4)
	109 iconst_1 (2, 4)
	110 isub (2, 4)
	111 istore (2, 4)
	112 #7 (2, 4)
	113 iload (2, 4)
	114 #7 (2, 4)
	115 iload (2, 4)
	116 #4 (2, 4)
	117 if_icmplt (2, 4)
	118 40 (2, 4)
	120 aload_2 (2, 4)
	121 iload (2, 4)
	122 #7 (2, 4)
	123 aaload (2, 4)
	124 aload (2, 4)
	125 #6 (2, 4)
	126 aload_1 (2, 4)
	127 aload_3 (2, 4)
	128 iload (2, 4)
	129 #7 (2, 4)
	130 aaload (2, 4)
	131 invokeinterface (2, 4)
	132 org/apache/commons/math3/RealFieldElement.$SwitchMap$org$apache$commons$math3$analysis$solvers$AllowedSolution:[I (2, 4)
	134 0 (2, 4)
	136 invokeinterface (2, 4)
	137 org/apache/commons/math3/RealFieldElement.org/apache/commons/math3/exception/NoBracketingException (2, 4)
	139 0 (2, 4)
	141 invokeinterface (2, 4)
	142 org/apache/commons/math3/RealFieldElement.org/apache/commons/math3/RealFieldElement (2, 4)
	144 0 (2, 4)
	146 checkcast (2, 4)
	147 org/apache/commons/math3/RealFieldElement (2, 4)
	149 astore (2, 4)
	150 #6 (2, 4)
	151 iinc (2, 4)
	152 #7 (2, 4)
	153 -89 (2, 4)
	154 goto (2, 4)
	155 -41 (2, 4)
	157 aload (1, 4)
	158 #6 (1, 4)
	159 areturn (1, 4)

