Method: <init>
	0 aload_0 (0, 0)
	1 invokespecial (0, 0)
	4 iload (1, 1)
	6 iconst_2 (1, 1)
	7 if_icmpge (1, 1)
	10 new (1, 1)
	13 dup (1, 1)
	14 iload (1, 1)
	16 invokestatic (1, 1)
	19 iconst_2 (1, 1)
	20 invokestatic (1, 1)
	23 iconst_1 (1, 1)
	24 invokespecial (1, 1)
	27 athrow (1, 1)
	28 aload_0 (0, 0)
	29 aload_1 (0, 0)
	30 invokeinterface (0, 0)
	35 putfield (0, 0)
	38 aload_0 (0, 0)
	39 iload (0, 0)
	41 putfield (0, 0)
	44 aload_0 (0, 0)
	45 aload_2 (0, 0)
	46 putfield (0, 0)
	49 aload_0 (0, 0)
	50 aload_1 (0, 0)
	51 putfield (0, 0)
	54 aload_0 (0, 0)
	55 aload_3 (0, 0)
	56 putfield (0, 0)
	59 aload_0 (0, 0)
	60 invokestatic (0, 0)
	63 putfield (0, 0)
	66 return (0, 0)

Method: getMaximalOrder
	0 aload_0 (0, 0)
	1 getfield (0, 0)
	4 ireturn (0, 0)

Method: getMaxEvaluations
	0 aload_0 (0, 0)
	1 getfield (0, 0)
	4 invokevirtual (0, 0)
	7 ireturn (0, 0)

Method: getEvaluations
	0 aload_0 (0, 0)
	1 getfield (0, 0)
	4 invokevirtual (0, 0)
	7 ireturn (0, 0)

Method: getAbsoluteAccuracy
	0 aload_0 (0, 0)
	1 getfield (0, 0)
	4 areturn (0, 0)

Method: getRelativeAccuracy
	0 aload_0 (0, 0)
	1 getfield (0, 0)
	4 areturn (0, 0)

Method: getFunctionValueAccuracy
	0 aload_0 (0, 0)
	1 getfield (0, 0)
	4 areturn (0, 0)

Method: solve
	0 aload_2 (0, 0)
	1 invokestatic (0, 0)
	4 aload_0 (0, 0)
	5 aload_0 (0, 0)
	6 getfield (0, 0)
	9 iload_1 (0, 0)
	10 invokevirtual (0, 0)
	13 iconst_0 (0, 0)
	14 invokevirtual (0, 0)
	17 putfield (0, 0)
	20 aload_0 (0, 0)
	21 getfield (0, 0)
	24 invokeinterface (0, 0)
	29 checkcast (0, 0)
	32 astore (0, 0)
	34 aload (0, 0)
	36 ldc2_w (0, 0)
	39 invokeinterface (0, 0)
	44 checkcast (0, 0)
	47 astore (0, 0)
	49 aload_0 (0, 0)
	50 getfield (0, 0)
	53 aload_0 (0, 0)
	54 getfield (0, 0)
	57 iconst_1 (0, 0)
	58 iadd (0, 0)
	59 invokestatic (0, 0)
	62 checkcast (0, 0)
	65 astore (0, 0)
	67 aload_0 (0, 0)
	68 getfield (0, 0)
	71 aload_0 (0, 0)
	72 getfield (0, 0)
	75 iconst_1 (0, 0)
	76 iadd (0, 0)
	77 invokestatic (0, 0)
	80 checkcast (0, 0)
	83 astore (0, 0)
	85 aload (0, 0)
	87 iconst_0 (0, 0)
	88 aload_3 (0, 0)
	89 aastore (0, 0)
	90 aload (0, 0)
	92 iconst_1 (0, 0)
	93 aload (0, 0)
	95 aastore (0, 0)
	96 aload (0, 0)
	98 iconst_2 (0, 0)
	99 aload (0, 0)
	101 aastore (0, 0)
	102 aload_0 (0, 0)
	103 getfield (0, 0)
	106 invokevirtual (0, 0)
	109 aload (0, 0)
	111 iconst_1 (0, 0)
	112 aload_2 (0, 0)
	113 aload (0, 0)
	115 iconst_1 (0, 0)
	116 aaload (0, 0)
	117 invokeinterface (0, 0)
	122 aastore (0, 0)
	123 aload (1, 1)
	125 iconst_1 (1, 1)
	126 aaload (1, 1)
	127 invokeinterface (1, 1)
	132 dconst_0 (1, 1)
	133 iconst_1 (1, 1)
	134 invokestatic (1, 1)
	137 ifeq (1, 1)
	140 aload (1, 1)
	142 iconst_1 (1, 1)
	143 aaload (1, 1)
	144 areturn (1, 1)
	145 aload_0 (0, 1)
	146 getfield (0, 1)
	149 invokevirtual (0, 1)
	152 aload (0, 1)
	154 iconst_0 (0, 1)
	155 aload_2 (0, 1)
	156 aload (0, 1)
	158 iconst_0 (0, 1)
	159 aaload (0, 1)
	160 invokeinterface (0, 1)
	165 aastore (0, 1)
	166 aload (1, 1)
	168 iconst_0 (1, 1)
	169 aaload (1, 1)
	170 invokeinterface (1, 1)
	175 dconst_0 (1, 1)
	176 iconst_1 (1, 1)
	177 invokestatic (1, 1)
	180 ifeq (1, 1)
	183 aload (1, 1)
	185 iconst_0 (1, 1)
	186 aaload (1, 1)
	187 areturn (1, 1)
	188 aload (1, 1)
	190 iconst_0 (1, 1)
	191 aaload (1, 1)
	192 aload (1, 1)
	194 iconst_1 (1, 1)
	195 aaload (1, 1)
	196 invokeinterface (1, 1)
	201 checkcast (1, 1)
	204 invokeinterface (1, 1)
	209 dconst_0 (1, 1)
	210 dcmpg (1, 1)
	211 ifge (1, 1)
	214 iconst_2 (1, 1)
	215 istore (1, 1)
	217 iconst_1 (1, 1)
	218 istore (1, 1)
	220 goto (1, 1)
	223 aload_0 (1, 2)
	224 getfield (1, 2)
	227 invokevirtual (1, 2)
	230 aload (1, 2)
	232 iconst_2 (1, 2)
	233 aload_2 (1, 2)
	234 aload (1, 2)
	236 iconst_2 (1, 2)
	237 aaload (1, 2)
	238 invokeinterface (1, 2)
	243 aastore (1, 2)
	244 aload (2, 1)
	246 iconst_2 (2, 1)
	247 aaload (2, 1)
	248 invokeinterface (2, 1)
	253 dconst_0 (2, 1)
	254 iconst_1 (2, 1)
	255 invokestatic (2, 1)
	258 ifeq (2, 1)
	261 aload (2, 1)
	263 iconst_2 (2, 1)
	264 aaload (2, 1)
	265 areturn (2, 1)
	266 aload (2, 1)
	268 iconst_1 (2, 1)
	269 aaload (2, 1)
	270 aload (2, 1)
	272 iconst_2 (2, 1)
	273 aaload (2, 1)
	274 invokeinterface (2, 1)
	279 checkcast (2, 1)
	282 invokeinterface (2, 1)
	287 dconst_0 (2, 1)
	288 dcmpg (2, 1)
	289 ifge (2, 1)
	292 iconst_3 (2, 4)
	293 istore (2, 4)
	295 iconst_2 (2, 4)
	296 istore (2, 4)
	298 goto (2, 4)
	301 new (2, 2)
	304 dup (2, 2)
	305 aload (2, 2)
	307 iconst_0 (2, 2)
	308 aaload (2, 2)
	309 invokeinterface (2, 2)
	314 aload (2, 2)
	316 iconst_2 (2, 2)
	317 aaload (2, 2)
	318 invokeinterface (2, 2)
	323 aload (2, 2)
	325 iconst_0 (2, 2)
	326 aaload (2, 2)
	327 invokeinterface (2, 2)
	332 aload (2, 2)
	334 iconst_2 (2, 2)
	335 aaload (2, 2)
	336 invokeinterface (2, 2)
	341 invokespecial (2, 2)
	344 athrow (2, 2)
	345 aload_0 (0, 4)
	346 getfield (0, 4)
	349 aload (0, 4)
	351 arraylength (0, 4)
	352 invokestatic (0, 4)
	355 checkcast (0, 4)
	358 astore (0, 4)
	360 aload (0, 4)
	362 iload (0, 4)
	364 iconst_1 (0, 4)
	365 isub (0, 4)
	366 aaload (0, 4)
	367 astore (0, 4)
	369 aload (0, 4)
	371 iload (0, 4)
	373 iconst_1 (0, 4)
	374 isub (0, 4)
	375 aaload (0, 4)
	376 astore (0, 4)
	378 aload (0, 4)
	380 invokeinterface (0, 4)
	385 checkcast (0, 4)
	388 astore (0, 4)
	390 aload (0, 4)
	392 invokeinterface (0, 4)
	397 checkcast (0, 4)
	400 astore (0, 4)
	402 iconst_0 (0, 4)
	403 istore (0, 4)
	405 aload (0, 4)
	407 iload (0, 4)
	409 aaload (0, 4)
	410 astore (0, 4)
	412 aload (0, 4)
	414 iload (0, 4)
	416 aaload (0, 4)
	417 astore (0, 4)
	419 aload (0, 4)
	421 invokeinterface (0, 4)
	426 checkcast (0, 4)
	429 astore (0, 4)
	431 aload (0, 4)
	433 invokeinterface (0, 4)
	438 checkcast (0, 4)
	441 astore (0, 4)
	443 iconst_0 (0, 4)
	444 istore (0, 4)
	446 aload (1, 3)
	448 aload (1, 3)
	450 invokeinterface (1, 3)
	455 checkcast (1, 3)
	458 invokeinterface (1, 3)
	463 dconst_0 (1, 3)
	464 dcmpg (1, 3)
	465 ifge (1, 3)
	468 aload (1, 3)
	470 goto (1, 3)
	473 aload (1, 3)
	475 astore (1, 3)
	477 aload (1, 3)
	479 aload (1, 3)
	481 invokeinterface (1, 3)
	486 checkcast (1, 3)
	489 invokeinterface (1, 3)
	494 dconst_0 (1, 3)
	495 dcmpg (1, 3)
	496 ifge (1, 3)
	499 aload (1, 3)
	501 goto (1, 3)
	504 aload (1, 3)
	506 astore (1, 3)
	508 aload_0 (1, 3)
	509 getfield (1, 3)
	512 aload_0 (1, 3)
	513 getfield (1, 3)
	516 aload (1, 3)
	518 invokeinterface (1, 3)
	523 invokeinterface (1, 3)
	528 checkcast (1, 3)
	531 astore (1, 3)
	533 aload (1, 1)
	535 aload (1, 1)
	537 invokeinterface (1, 1)
	542 checkcast (1, 1)
	545 aload (1, 1)
	547 invokeinterface (1, 1)
	552 checkcast (1, 1)
	555 invokeinterface (1, 1)
	560 dconst_0 (1, 1)
	561 dcmpg (1, 1)
	562 ifle (1, 1)
	565 aload (1, 1)
	567 aload_0 (1, 1)
	568 getfield (1, 1)
	571 invokeinterface (2, 1)
	576 checkcast (2, 1)
	579 invokeinterface (2, 1)
	584 dconst_0 (2, 1)
	585 dcmpg (2, 1)
	586 ifge (2, 1)
	589 getstatic (3, 5)
	592 aload (3, 5)
	594 invokevirtual (3, 5)
	597 iaload (3, 5)
	598 tableswitch (3, 5)
	632 aload (3, 5)
	634 aload (3, 5)
	636 invokeinterface (3, 5)
	641 checkcast (3, 5)
	644 invokeinterface (3, 5)
	649 dconst_0 (3, 5)
	650 dcmpg (3, 5)
	651 ifge (3, 5)
	654 aload (3, 5)
	656 goto (3, 5)
	659 aload (3, 5)
	661 areturn (3, 5)
	662 aload (3, 5)
	664 areturn (3, 5)
	665 aload (3, 5)
	667 areturn (3, 5)
	668 aload (3, 5)
	670 invokeinterface (3, 5)
	675 dconst_0 (3, 5)
	676 dcmpg (3, 5)
	677 ifgt (3, 5)
	680 aload (3, 5)
	682 goto (3, 5)
	685 aload (3, 5)
	687 areturn (3, 5)
	688 aload (3, 5)
	690 invokeinterface (3, 5)
	695 dconst_0 (3, 5)
	696 dcmpg (3, 5)
	697 ifge (3, 5)
	700 aload (3, 5)
	702 goto (3, 5)
	705 aload (3, 5)
	707 areturn (3, 5)
	708 new (3, 5)
	711 dup (3, 5)
	712 aconst_null (3, 5)
	713 invokespecial (3, 5)
	716 athrow (3, 5)
	717 iload (2, 1)
	719 iconst_2 (2, 1)
	720 if_icmplt (2, 1)
	723 aload (2, 1)
	725 ldc2_w (2, 1)
	728 invokeinterface (2, 1)
	733 checkcast (2, 1)
	736 invokeinterface (2, 1)
	741 checkcast (2, 1)
	744 astore (2, 1)
	746 goto (2, 1)
	749 iload (2, 1)
	751 iconst_2 (2, 1)
	752 if_icmplt (2, 1)
	755 aload (2, 1)
	757 ldc2_w (2, 1)
	760 invokeinterface (2, 1)
	765 checkcast (2, 1)
	768 invokeinterface (2, 1)
	773 checkcast (2, 1)
	776 astore (2, 1)
	778 goto (2, 1)
	781 aload (2, 2)
	783 astore (2, 2)
	785 iconst_0 (1, 1)
	786 istore (1, 1)
	788 iload (1, 1)
	790 istore (1, 1)
	792 aload (2, 4)
	794 iload (2, 4)
	796 aload (2, 4)
	798 iload (2, 4)
	800 iload (2, 4)
	802 iload (2, 4)
	804 isub (2, 4)
	805 invokestatic (2, 4)
	808 aload_0 (2, 4)
	809 aload (2, 4)
	811 aload (2, 4)
	813 aload (2, 4)
	815 iload (2, 4)
	817 iload (2, 4)
	819 invokespecial (2, 4)
	822 astore (2, 4)
	824 aload (3, 1)
	826 aload (3, 1)
	828 invokeinterface (3, 1)
	833 checkcast (3, 1)
	836 invokeinterface (3, 1)
	841 dconst_0 (3, 1)
	842 dcmpl (3, 1)
	843 ifle (3, 1)
	846 aload (3, 1)
	848 aload (3, 1)
	850 invokeinterface (3, 1)
	855 checkcast (3, 1)
	858 invokeinterface (3, 1)
	863 dconst_0 (3, 1)
	864 dcmpg (3, 1)
	865 iflt (3, 1)
	868 iload (4, 1)
	870 iload (4, 1)
	872 isub (4, 1)
	873 iload (4, 1)
	875 iload (4, 1)
	877 isub (4, 1)
	878 if_icmplt (4, 1)
	881 iinc (4, 4)
	884 goto (4, 4)
	887 iinc (4, 2)
	890 aload (3, 4)
	892 astore (3, 4)
	894 aload (1, 1)
	896 invokeinterface (1, 1)
	901 invokestatic (1, 1)
	904 ifeq (1, 1)
	907 iload (1, 1)
	909 iload (1, 1)
	911 isub (1, 1)
	912 iconst_1 (1, 1)
	913 if_icmpgt (1, 1)
	916 aload (2, 1)
	918 invokeinterface (2, 1)
	923 invokestatic (2, 1)
	926 ifeq (2, 1)
	929 aload (2, 1)
	931 aload (2, 1)
	933 aload (2, 1)
	935 invokeinterface (2, 1)
	940 checkcast (2, 1)
	943 ldc2_w (2, 1)
	946 invokeinterface (2, 1)
	951 invokeinterface (2, 1)
	956 checkcast (2, 1)
	959 astore (2, 1)
	961 iload (2, 1)
	963 iconst_1 (2, 1)
	964 isub (2, 1)
	965 istore (2, 1)
	967 iload (2, 1)
	969 istore (2, 1)
	971 aload_0 (1, 1)
	972 getfield (1, 1)
	975 invokevirtual (1, 1)
	978 aload_2 (1, 1)
	979 aload (1, 1)
	981 invokeinterface (1, 1)
	986 astore (1, 1)
	988 aload (2, 1)
	990 invokeinterface (2, 1)
	995 dconst_0 (2, 1)
	996 iconst_1 (2, 1)
	997 invokestatic (2, 1)
	1000 ifeq (2, 1)
	1003 aload (2, 1)
	1005 areturn (2, 1)
	1006 iload (2, 1)
	1008 iconst_2 (2, 1)
	1009 if_icmple (2, 1)
	1012 iload (2, 1)
	1014 iload (2, 1)
	1016 isub (2, 1)
	1017 iload (2, 1)
	1019 if_icmpeq (2, 1)
	1022 iload (2, 4)
	1024 iload (2, 4)
	1026 isub (2, 4)
	1027 istore (2, 4)
	1029 aload (2, 4)
	1031 iload (2, 4)
	1033 aload (2, 4)
	1035 iconst_0 (2, 4)
	1036 iload (2, 4)
	1038 invokestatic (2, 4)
	1041 aload (2, 4)
	1043 iload (2, 4)
	1045 aload (2, 4)
	1047 iconst_0 (2, 4)
	1048 iload (2, 4)
	1050 invokestatic (2, 4)
	1053 iload (2, 4)
	1055 iload (2, 4)
	1057 isub (2, 4)
	1058 istore (2, 4)
	1060 goto (2, 4)
	1063 iload (2, 1)
	1065 aload (2, 1)
	1067 arraylength (2, 1)
	1068 if_icmpne (2, 1)
	1071 iinc (2, 1)
	1074 iload (3, 1)
	1076 aload (3, 1)
	1078 arraylength (3, 1)
	1079 iconst_1 (3, 1)
	1080 iadd (3, 1)
	1081 iconst_2 (3, 1)
	1082 idiv (3, 1)
	1083 if_icmplt (3, 1)
	1086 aload (3, 1)
	1088 iconst_1 (3, 1)
	1089 aload (3, 1)
	1091 iconst_0 (3, 1)
	1092 iload (3, 1)
	1094 invokestatic (3, 1)
	1097 aload (3, 1)
	1099 iconst_1 (3, 1)
	1100 aload (3, 1)
	1102 iconst_0 (3, 1)
	1103 iload (3, 1)
	1105 invokestatic (3, 1)
	1108 iinc (3, 1)
	1111 aload (1, 1)
	1113 iload (1, 1)
	1115 aload (1, 1)
	1117 iload (1, 1)
	1119 iconst_1 (1, 1)
	1120 iadd (1, 1)
	1121 iload (1, 1)
	1123 iload (1, 1)
	1125 isub (1, 1)
	1126 invokestatic (1, 1)
	1129 aload (1, 1)
	1131 iload (1, 1)
	1133 aload (1, 1)
	1135 aastore (1, 1)
	1136 aload (1, 1)
	1138 iload (1, 1)
	1140 aload (1, 1)
	1142 iload (1, 1)
	1144 iconst_1 (1, 1)
	1145 iadd (1, 1)
	1146 iload (1, 1)
	1148 iload (1, 1)
	1150 isub (1, 1)
	1151 invokestatic (1, 1)
	1154 aload (1, 1)
	1156 iload (1, 1)
	1158 aload (1, 1)
	1160 aastore (1, 1)
	1161 iinc (1, 1)
	1164 aload (2, 1)
	1166 aload (2, 1)
	1168 invokeinterface (2, 1)
	1173 checkcast (2, 1)
	1176 invokeinterface (2, 1)
	1181 dconst_0 (2, 1)
	1182 dcmpg (2, 1)
	1183 ifgt (2, 1)
	1186 aload (2, 4)
	1188 astore (2, 4)
	1190 aload (2, 4)
	1192 astore (2, 4)
	1194 aload (2, 4)
	1196 invokeinterface (2, 4)
	1201 checkcast (2, 4)
	1204 astore (2, 4)
	1206 iinc (2, 4)
	1209 iconst_0 (2, 4)
	1210 istore (2, 4)
	1212 goto (2, 4)
	1215 aload (2, 2)
	1217 astore (2, 2)
	1219 aload (2, 2)
	1221 astore (2, 2)
	1223 aload (2, 2)
	1225 invokeinterface (2, 2)
	1230 checkcast (2, 2)
	1233 astore (2, 2)
	1235 iconst_0 (2, 2)
	1236 istore (2, 2)
	1238 iinc (2, 2)
	1241 iinc (2, 2)
	1244 goto (0, 1)

Method: guessX
	0 iload (1, 4)
	2 istore (1, 4)
	4 iload (1, 4)
	6 iload (1, 4)
	8 iconst_1 (1, 4)
	9 isub (1, 4)
	10 if_icmpge (1, 4)
	13 iload (1, 4)
	15 iconst_1 (1, 4)
	16 iadd (1, 4)
	17 iload (1, 4)
	19 isub (1, 4)
	20 istore (1, 4)
	22 iload (2, 4)
	24 iconst_1 (2, 4)
	25 isub (2, 4)
	26 istore (2, 4)
	28 iload (2, 4)
	30 iload (2, 4)
	32 if_icmple (2, 4)
	35 aload_2 (2, 4)
	36 iload (2, 4)
	38 aload_2 (2, 4)
	39 iload (2, 4)
	41 aaload (2, 4)
	42 aload_2 (2, 4)
	43 iload (2, 4)
	45 iconst_1 (2, 4)
	46 isub (2, 4)
	47 aaload (2, 4)
	48 invokeinterface (2, 4)
	53 checkcast (2, 4)
	56 aload_3 (2, 4)
	57 iload (2, 4)
	59 aaload (2, 4)
	60 aload_3 (2, 4)
	61 iload (2, 4)
	63 iload (2, 4)
	65 isub (2, 4)
	66 aaload (2, 4)
	67 invokeinterface (2, 4)
	72 invokeinterface (2, 4)
	77 checkcast (2, 4)
	80 aastore (2, 4)
	81 iinc (2, 4)
	84 goto (2, 4)
	87 iinc (2, 4)
	90 goto (2, 4)
	93 aload_0 (1, 4)
	94 getfield (1, 4)
	97 invokeinterface (1, 4)
	102 checkcast (1, 4)
	105 astore (1, 4)
	107 iload (2, 4)
	109 iconst_1 (2, 4)
	110 isub (2, 4)
	111 istore (2, 4)
	113 iload (2, 4)
	115 iload (2, 4)
	117 if_icmplt (2, 4)
	120 aload_2 (2, 4)
	121 iload (2, 4)
	123 aaload (2, 4)
	124 aload (2, 4)
	126 aload_1 (2, 4)
	127 aload_3 (2, 4)
	128 iload (2, 4)
	130 aaload (2, 4)
	131 invokeinterface (2, 4)
	136 invokeinterface (2, 4)
	141 invokeinterface (2, 4)
	146 checkcast (2, 4)
	149 astore (2, 4)
	151 iinc (2, 4)
	154 goto (2, 4)
	157 aload (1, 4)
	159 areturn (1, 4)

