Method: isRoot
	0 aload_0 (1, 1)
	1 getfield (1, 1)
	2 org/apache/commons/math3/analysis/solvers/LaguerreSolver$ComplexSolver.this$0:Lorg/apache/commons/math3/analysis/solvers/LaguerreSolver; (1, 1)
	4 dload_1 (1, 1)
	5 aload (1, 1)
	6 #5 (1, 1)
	7 invokevirtual (1, 1)
	8 org/apache/commons/math3/complex/Complex.getReal:()D (1, 1)
	10 dload_3 (1, 1)
	11 invokevirtual (1, 1)
	12 org/apache/commons/math3/analysis/solvers/LaguerreSolver.isSequence:(DDD)Z (1, 1)
	14 ifeq (1, 1)
	15 64 (1, 1)
	17 aload_0 (1, 1)
	18 getfield (1, 1)
	19 org/apache/commons/math3/analysis/solvers/LaguerreSolver$ComplexSolver.this$0:Lorg/apache/commons/math3/analysis/solvers/LaguerreSolver; (1, 1)
	21 invokevirtual (1, 1)
	22 org/apache/commons/math3/analysis/solvers/LaguerreSolver.getRelativeAccuracy:()D (1, 1)
	24 aload (1, 1)
	25 #5 (1, 1)
	26 invokevirtual (1, 1)
	27 org/apache/commons/math3/complex/Complex.abs:()D (1, 1)
	29 dmul (1, 1)
	30 aload_0 (1, 1)
	31 getfield (1, 1)
	32 org/apache/commons/math3/analysis/solvers/LaguerreSolver$ComplexSolver.this$0:Lorg/apache/commons/math3/analysis/solvers/LaguerreSolver; (1, 1)
	34 invokevirtual (1, 1)
	35 org/apache/commons/math3/analysis/solvers/LaguerreSolver.getAbsoluteAccuracy:()D (1, 1)
	37 invokestatic (1, 1)
	38 org/apache/commons/math3/util/FastMath.max:(DD)D (1, 1)
	40 dstore (1, 1)
	41 #6 (1, 1)
	42 aload (1, 1)
	43 #5 (1, 1)
	44 invokevirtual (1, 1)
	45 org/apache/commons/math3/complex/Complex.getImaginary:()D (1, 1)
	47 invokestatic (1, 1)
	48 org/apache/commons/math3/util/FastMath.abs:(D)D (1, 1)
	50 dload (1, 1)
	51 #6 (1, 1)
	52 dcmpg (1, 1)
	53 ifle (1, 1)
	54 19 (1, 1)
	56 aload (1, 1)
	57 #5 (1, 1)
	58 invokevirtual (1, 1)
	59 org/apache/commons/math3/complex/Complex.abs:()D (1, 1)
	61 aload_0 (1, 1)
	62 getfield (1, 1)
	63 org/apache/commons/math3/analysis/solvers/LaguerreSolver$ComplexSolver.this$0:Lorg/apache/commons/math3/analysis/solvers/LaguerreSolver; (1, 1)
	65 invokevirtual (1, 1)
	66 org/apache/commons/math3/analysis/solvers/LaguerreSolver.getFunctionValueAccuracy:()D (1, 1)
	68 dcmpg (1, 1)
	69 ifgt (1, 1)
	70 7 (1, 1)
	72 iconst_1 (1, 1)
	73 goto (1, 1)
	74 4 (1, 1)
	76 iconst_0 (1, 1)
	77 ireturn (1, 1)
	78 iconst_0 (0, 0)
	79 ireturn (0, 0)

Method: solveAll
	0 aload_1 (1, 1)
	1 ifnonnull (1, 1)
	2 11 (1, 1)
	4 new (1, 1)
	5 org/apache/commons/math3/exception/NullArgumentException (1, 1)
	7 dup (1, 1)
	8 invokespecial (1, 1)
	9 org/apache/commons/math3/exception/NullArgumentException.<init>:()V (1, 1)
	11 athrow (1, 1)
	12 aload_1 (0, 0)
	13 arraylength (0, 0)
	14 iconst_1 (0, 0)
	15 isub (0, 0)
	16 istore_3 (0, 0)
	17 iload_3 (1, 1)
	18 ifne (1, 1)
	19 14 (1, 1)
	21 new (1, 1)
	22 org/apache/commons/math3/exception/NoDataException (1, 1)
	24 dup (1, 1)
	25 getstatic (1, 1)
	26 org/apache/commons/math3/exception/util/LocalizedFormats.POLYNOMIAL:Lorg/apache/commons/math3/exception/util/LocalizedFormats; (1, 1)
	28 invokespecial (1, 1)
	29 org/apache/commons/math3/exception/NoDataException.<init>:(Lorg/apache/commons/math3/exception/util/Localizable;)V (1, 1)
	31 athrow (1, 1)
	32 iload_3 (1, 4)
	33 iconst_1 (1, 4)
	34 iadd (1, 4)
	35 anewarray (1, 4)
	36 org/apache/commons/math3/complex/Complex (1, 4)
	38 astore (1, 4)
	39 #4 (1, 4)
	40 iconst_0 (2, 4)
	41 istore (2, 4)
	42 #5 (2, 4)
	43 iload (2, 4)
	44 #5 (2, 4)
	45 iload_3 (2, 4)
	46 if_icmpgt (2, 4)
	47 18 (2, 4)
	49 aload (2, 4)
	50 #4 (2, 4)
	51 iload (2, 4)
	52 #5 (2, 4)
	53 aload_1 (2, 4)
	54 iload (2, 4)
	55 #5 (2, 4)
	56 aaload (2, 4)
	57 aastore (2, 4)
	58 iinc (2, 4)
	59 #5 (2, 4)
	60 -89 (2, 4)
	61 goto (2, 4)
	62 -18 (2, 4)
	64 iload_3 (1, 4)
	65 anewarray (1, 4)
	66 org/apache/commons/math3/complex/Complex (1, 4)
	68 astore (1, 4)
	69 #5 (1, 4)
	70 iconst_0 (2, 4)
	71 istore (2, 4)
	72 #6 (2, 4)
	73 iload (2, 4)
	74 #6 (2, 4)
	75 iload_3 (2, 4)
	76 if_icmpge (2, 4)
	77 106 (2, 4)
	79 iload_3 (2, 4)
	80 iload (2, 4)
	81 #6 (2, 4)
	82 isub (2, 4)
	83 iconst_1 (2, 4)
	84 iadd (2, 4)
	85 anewarray (2, 4)
	86 org/apache/commons/math3/complex/Complex (2, 4)
	88 astore (2, 4)
	89 #7 (2, 4)
	90 aload (2, 4)
	91 #4 (2, 4)
	92 iconst_0 (2, 4)
	93 aload (2, 4)
	94 #7 (2, 4)
	95 iconst_0 (2, 4)
	96 aload (2, 4)
	97 #7 (2, 4)
	98 arraylength (2, 4)
	99 invokestatic (2, 4)
	100 java/lang/System.arraycopy:(Ljava/lang/Object;ILjava/lang/Object;II)V (2, 4)
	102 aload (2, 4)
	103 #5 (2, 4)
	104 iload (2, 4)
	105 #6 (2, 4)
	106 aload_0 (2, 4)
	107 aload (2, 4)
	108 #7 (2, 4)
	109 aload_2 (2, 4)
	110 invokevirtual (2, 4)
	111 org/apache/commons/math3/analysis/solvers/LaguerreSolver$ComplexSolver.solve:([Lorg/apache/commons/math3/complex/Complex;Lorg/apache/commons/math3/complex/Complex;)Lorg/apache/commons/math3/complex/Complex; (2, 4)
	113 aastore (2, 4)
	114 aload (2, 4)
	115 #4 (2, 4)
	116 iload_3 (2, 4)
	117 iload (2, 4)
	118 #6 (2, 4)
	119 isub (2, 4)
	120 aaload (2, 4)
	121 astore (2, 4)
	122 #8 (2, 4)
	123 aconst_null (2, 4)
	124 astore (2, 4)
	125 #9 (2, 4)
	126 iload_3 (3, 4)
	127 iload (3, 4)
	128 #6 (3, 4)
	129 isub (3, 4)
	130 iconst_1 (3, 4)
	131 isub (3, 4)
	132 istore (3, 4)
	133 #10 (3, 4)
	134 iload (3, 4)
	135 #10 (3, 4)
	136 iflt (3, 4)
	137 40 (3, 4)
	139 aload (3, 4)
	140 #4 (3, 4)
	141 iload (3, 4)
	142 #10 (3, 4)
	143 aaload (3, 4)
	144 astore (3, 4)
	145 #9 (3, 4)
	146 aload (3, 4)
	147 #4 (3, 4)
	148 iload (3, 4)
	149 #10 (3, 4)
	150 aload (3, 4)
	151 #8 (3, 4)
	152 aastore (3, 4)
	153 aload (3, 4)
	154 #9 (3, 4)
	155 aload (3, 4)
	156 #8 (3, 4)
	157 aload (3, 4)
	158 #5 (3, 4)
	159 iload (3, 4)
	160 #6 (3, 4)
	161 aaload (3, 4)
	162 invokevirtual (3, 4)
	163 org/apache/commons/math3/complex/Complex.multiply:(Lorg/apache/commons/math3/complex/Complex;)Lorg/apache/commons/math3/complex/Complex; (3, 4)
	165 invokevirtual (3, 4)
	166 org/apache/commons/math3/complex/Complex.add:(Lorg/apache/commons/math3/complex/Complex;)Lorg/apache/commons/math3/complex/Complex; (3, 4)
	168 astore (3, 4)
	169 #8 (3, 4)
	170 iinc (3, 4)
	171 #10 (3, 4)
	172 -89 (3, 4)
	173 goto (3, 4)
	174 -39 (3, 4)
	176 iinc (3, 4)
	177 #6 (3, 4)
	178 -89 (3, 4)
	179 goto (3, 4)
	180 -106 (3, 4)
	182 aload (2, 4)
	183 #5 (2, 4)
	184 areturn (1, 4)

Method: solve
	0 aload_1 (1, 1)
	1 ifnonnull (1, 1)
	2 11 (1, 1)
	4 new (1, 1)
	5 org/apache/commons/math3/exception/NullArgumentException (1, 1)
	7 dup (1, 1)
	8 invokespecial (1, 1)
	9 org/apache/commons/math3/exception/NullArgumentException.<init>:()V (1, 1)
	11 athrow (1, 1)
	12 aload_1 (0, 0)
	13 arraylength (0, 0)
	14 iconst_1 (0, 0)
	15 isub (0, 0)
	16 istore_3 (0, 0)
	17 iload_3 (1, 1)
	18 ifne (1, 1)
	19 14 (1, 1)
	21 new (1, 1)
	22 org/apache/commons/math3/exception/NoDataException (1, 1)
	24 dup (1, 1)
	25 getstatic (1, 1)
	26 org/apache/commons/math3/exception/util/LocalizedFormats.POLYNOMIAL:Lorg/apache/commons/math3/exception/util/LocalizedFormats; (1, 1)
	28 invokespecial (1, 1)
	29 org/apache/commons/math3/exception/NoDataException.<init>:(Lorg/apache/commons/math3/exception/util/Localizable;)V (1, 1)
	31 athrow (1, 1)
	32 aload_0 (0, 0)
	33 getfield (0, 0)
	34 org/apache/commons/math3/analysis/solvers/LaguerreSolver$ComplexSolver.this$0:Lorg/apache/commons/math3/analysis/solvers/LaguerreSolver; (0, 0)
	36 invokevirtual (0, 0)
	37 org/apache/commons/math3/analysis/solvers/LaguerreSolver.getAbsoluteAccuracy:()D (0, 0)
	39 dstore (0, 0)
	40 #4 (0, 0)
	41 aload_0 (0, 0)
	42 getfield (0, 0)
	43 org/apache/commons/math3/analysis/solvers/LaguerreSolver$ComplexSolver.this$0:Lorg/apache/commons/math3/analysis/solvers/LaguerreSolver; (0, 0)
	45 invokevirtual (0, 0)
	46 org/apache/commons/math3/analysis/solvers/LaguerreSolver.getRelativeAccuracy:()D (0, 0)
	48 dstore (0, 0)
	49 #6 (0, 0)
	50 aload_0 (0, 0)
	51 getfield (0, 0)
	52 org/apache/commons/math3/analysis/solvers/LaguerreSolver$ComplexSolver.this$0:Lorg/apache/commons/math3/analysis/solvers/LaguerreSolver; (0, 0)
	54 invokevirtual (0, 0)
	55 org/apache/commons/math3/analysis/solvers/LaguerreSolver.getFunctionValueAccuracy:()D (0, 0)
	57 dstore (0, 0)
	58 #8 (0, 0)
	59 new (0, 0)
	60 org/apache/commons/math3/complex/Complex (0, 0)
	62 dup (0, 0)
	63 iload_3 (0, 0)
	64 i2d (0, 0)
	65 dconst_0 (0, 0)
	66 invokespecial (0, 0)
	67 org/apache/commons/math3/complex/Complex.<init>:(DD)V (0, 0)
	69 astore (0, 0)
	70 #10 (0, 0)
	71 new (0, 0)
	72 org/apache/commons/math3/complex/Complex (0, 0)
	74 dup (0, 0)
	75 iload_3 (0, 0)
	76 iconst_1 (0, 0)
	77 isub (0, 0)
	78 i2d (0, 0)
	79 dconst_0 (0, 0)
	80 invokespecial (0, 0)
	81 org/apache/commons/math3/complex/Complex.<init>:(DD)V (0, 0)
	83 astore (0, 0)
	84 #11 (0, 0)
	85 aload_2 (0, 0)
	86 astore (0, 0)
	87 #12 (0, 0)
	88 new (0, 0)
	89 org/apache/commons/math3/complex/Complex (0, 0)
	91 dup (0, 0)
	92 ldc2_w (0, 0)
	93 inf (0, 0)
	95 ldc2_w (0, 0)
	96 inf (0, 0)
	98 invokespecial (0, 0)
	99 org/apache/commons/math3/complex/Complex.<init>:(DD)V (0, 0)
	101 astore (0, 0)
	102 #13 (0, 0)
	103 aload_1 (1, 3)
	104 iload_3 (1, 3)
	105 aaload (1, 3)
	106 astore (1, 3)
	107 #14 (1, 3)
	108 getstatic (1, 3)
	109 org/apache/commons/math3/complex/Complex.ZERO:Lorg/apache/commons/math3/complex/Complex; (1, 3)
	111 astore (1, 3)
	112 #15 (1, 3)
	113 getstatic (1, 3)
	114 org/apache/commons/math3/complex/Complex.ZERO:Lorg/apache/commons/math3/complex/Complex; (1, 3)
	116 astore (1, 3)
	117 #16 (1, 3)
	118 iload_3 (2, 4)
	119 iconst_1 (2, 4)
	120 isub (2, 4)
	121 istore (2, 4)
	122 #17 (2, 4)
	123 iload (2, 4)
	124 #17 (2, 4)
	125 iflt (2, 4)
	126 53 (2, 4)
	128 aload (2, 4)
	129 #15 (2, 4)
	130 aload (2, 4)
	131 #12 (2, 4)
	132 aload (2, 4)
	133 #16 (2, 4)
	134 invokevirtual (2, 4)
	135 org/apache/commons/math3/complex/Complex.multiply:(Lorg/apache/commons/math3/complex/Complex;)Lorg/apache/commons/math3/complex/Complex; (2, 4)
	137 invokevirtual (2, 4)
	138 org/apache/commons/math3/complex/Complex.add:(Lorg/apache/commons/math3/complex/Complex;)Lorg/apache/commons/math3/complex/Complex; (2, 4)
	140 astore (2, 4)
	141 #16 (2, 4)
	142 aload (2, 4)
	143 #14 (2, 4)
	144 aload (2, 4)
	145 #12 (2, 4)
	146 aload (2, 4)
	147 #15 (2, 4)
	148 invokevirtual (2, 4)
	149 org/apache/commons/math3/complex/Complex.multiply:(Lorg/apache/commons/math3/complex/Complex;)Lorg/apache/commons/math3/complex/Complex; (2, 4)
	151 invokevirtual (2, 4)
	152 org/apache/commons/math3/complex/Complex.add:(Lorg/apache/commons/math3/complex/Complex;)Lorg/apache/commons/math3/complex/Complex; (2, 4)
	154 astore (2, 4)
	155 #15 (2, 4)
	156 aload_1 (2, 4)
	157 iload (2, 4)
	158 #17 (2, 4)
	159 aaload (2, 4)
	160 aload (2, 4)
	161 #12 (2, 4)
	162 aload (2, 4)
	163 #14 (2, 4)
	164 invokevirtual (2, 4)
	165 org/apache/commons/math3/complex/Complex.multiply:(Lorg/apache/commons/math3/complex/Complex;)Lorg/apache/commons/math3/complex/Complex; (2, 4)
	167 invokevirtual (2, 4)
	168 org/apache/commons/math3/complex/Complex.add:(Lorg/apache/commons/math3/complex/Complex;)Lorg/apache/commons/math3/complex/Complex; (2, 4)
	170 astore (2, 4)
	171 #14 (2, 4)
	172 iinc (2, 4)
	173 #17 (2, 4)
	174 -89 (2, 4)
	175 goto (2, 4)
	176 -52 (2, 4)
	178 aload (1, 3)
	179 #16 (1, 3)
	180 new (1, 3)
	181 org/apache/commons/math3/complex/Complex (1, 3)
	183 dup (1, 3)
	184 ldc2_w (1, 3)
	185 2.0 (1, 3)
	187 dconst_0 (1, 3)
	188 invokespecial (1, 3)
	189 org/apache/commons/math3/complex/Complex.<init>:(DD)V (1, 3)
	191 invokevirtual (1, 3)
	192 org/apache/commons/math3/complex/Complex.multiply:(Lorg/apache/commons/math3/complex/Complex;)Lorg/apache/commons/math3/complex/Complex; (1, 3)
	194 astore (1, 3)
	195 #16 (1, 3)
	196 dload (2, 4)
	197 #6 (2, 4)
	198 aload (2, 4)
	199 #12 (2, 4)
	200 invokevirtual (2, 4)
	201 org/apache/commons/math3/complex/Complex.abs:()D (2, 4)
	203 dmul (2, 4)
	204 dload (2, 4)
	205 #4 (2, 4)
	206 invokestatic (2, 4)
	207 org/apache/commons/math3/util/FastMath.max:(DD)D (2, 4)
	209 dstore (2, 4)
	210 #17 (2, 4)
	211 aload (3, 1)
	212 #12 (3, 1)
	213 aload (3, 1)
	214 #13 (3, 1)
	215 invokevirtual (3, 1)
	216 org/apache/commons/math3/complex/Complex.subtract:(Lorg/apache/commons/math3/complex/Complex;)Lorg/apache/commons/math3/complex/Complex; (3, 1)
	218 invokevirtual (3, 1)
	219 org/apache/commons/math3/complex/Complex.abs:()D (3, 1)
	221 dload (3, 1)
	222 #17 (3, 1)
	223 dcmpg (3, 1)
	224 ifgt (3, 1)
	225 6 (3, 1)
	227 aload (3, 1)
	228 #12 (3, 1)
	229 areturn (3, 1)
	230 aload (3, 1)
	231 #14 (3, 1)
	232 invokevirtual (3, 1)
	233 org/apache/commons/math3/complex/Complex.abs:()D (3, 1)
	235 dload (3, 1)
	236 #8 (3, 1)
	237 dcmpg (3, 1)
	238 ifgt (3, 1)
	239 6 (3, 1)
	241 aload (3, 1)
	242 #12 (3, 1)
	243 areturn (3, 1)
	244 aload (2, 4)
	245 #15 (2, 4)
	246 aload (2, 4)
	247 #14 (2, 4)
	248 invokevirtual (2, 4)
	249 org/apache/commons/math3/complex/Complex.divide:(Lorg/apache/commons/math3/complex/Complex;)Lorg/apache/commons/math3/complex/Complex; (2, 4)
	251 astore (2, 4)
	252 #19 (2, 4)
	253 aload (2, 4)
	254 #19 (2, 4)
	255 aload (2, 4)
	256 #19 (2, 4)
	257 invokevirtual (2, 4)
	258 org/apache/commons/math3/complex/Complex.multiply:(Lorg/apache/commons/math3/complex/Complex;)Lorg/apache/commons/math3/complex/Complex; (2, 4)
	260 astore (2, 4)
	261 #20 (2, 4)
	262 aload (2, 4)
	263 #20 (2, 4)
	264 aload (2, 4)
	265 #16 (2, 4)
	266 aload (2, 4)
	267 #14 (2, 4)
	268 invokevirtual (2, 4)
	269 org/apache/commons/math3/complex/Complex.divide:(Lorg/apache/commons/math3/complex/Complex;)Lorg/apache/commons/math3/complex/Complex; (2, 4)
	271 invokevirtual (2, 4)
	272 org/apache/commons/math3/complex/Complex.subtract:(Lorg/apache/commons/math3/complex/Complex;)Lorg/apache/commons/math3/complex/Complex; (2, 4)
	274 astore (2, 4)
	275 #21 (2, 4)
	276 aload (2, 4)
	277 #11 (2, 4)
	278 aload (2, 4)
	279 #10 (2, 4)
	280 aload (2, 4)
	281 #21 (2, 4)
	282 invokevirtual (2, 4)
	283 org/apache/commons/math3/complex/Complex.multiply:(Lorg/apache/commons/math3/complex/Complex;)Lorg/apache/commons/math3/complex/Complex; (2, 4)
	285 aload (2, 4)
	286 #20 (2, 4)
	287 invokevirtual (2, 4)
	288 org/apache/commons/math3/complex/Complex.subtract:(Lorg/apache/commons/math3/complex/Complex;)Lorg/apache/commons/math3/complex/Complex; (2, 4)
	290 invokevirtual (2, 4)
	291 org/apache/commons/math3/complex/Complex.multiply:(Lorg/apache/commons/math3/complex/Complex;)Lorg/apache/commons/math3/complex/Complex; (2, 4)
	293 astore (2, 4)
	294 #22 (2, 4)
	295 aload (2, 4)
	296 #22 (2, 4)
	297 invokevirtual (2, 4)
	298 org/apache/commons/math3/complex/Complex.sqrt:()Lorg/apache/commons/math3/complex/Complex; (2, 4)
	300 astore (2, 4)
	301 #23 (2, 4)
	302 aload (2, 4)
	303 #19 (2, 4)
	304 aload (2, 4)
	305 #23 (2, 4)
	306 invokevirtual (2, 4)
	307 org/apache/commons/math3/complex/Complex.add:(Lorg/apache/commons/math3/complex/Complex;)Lorg/apache/commons/math3/complex/Complex; (2, 4)
	309 astore (2, 4)
	310 #24 (2, 4)
	311 aload (2, 4)
	312 #19 (2, 4)
	313 aload (2, 4)
	314 #23 (2, 4)
	315 invokevirtual (2, 4)
	316 org/apache/commons/math3/complex/Complex.subtract:(Lorg/apache/commons/math3/complex/Complex;)Lorg/apache/commons/math3/complex/Complex; (2, 4)
	318 astore (2, 4)
	319 #25 (2, 4)
	320 aload (2, 4)
	321 #24 (2, 4)
	322 invokevirtual (2, 4)
	323 org/apache/commons/math3/complex/Complex.abs:()D (2, 4)
	325 aload (2, 4)
	326 #25 (2, 4)
	327 invokevirtual (2, 4)
	328 org/apache/commons/math3/complex/Complex.abs:()D (2, 4)
	330 dcmpl (2, 4)
	331 ifle (2, 4)
	332 8 (2, 4)
	334 aload (2, 4)
	335 #24 (2, 4)
	336 goto (2, 4)
	337 5 (2, 4)
	339 aload (2, 4)
	340 #25 (2, 4)
	341 astore (2, 4)
	342 #26 (2, 4)
	343 aload (4, 1)
	344 #26 (4, 1)
	345 new (4, 1)
	346 org/apache/commons/math3/complex/Complex (4, 1)
	348 dup (4, 1)
	349 dconst_0 (4, 1)
	350 dconst_0 (4, 1)
	351 invokespecial (4, 1)
	352 org/apache/commons/math3/complex/Complex.<init>:(DD)V (4, 1)
	354 invokevirtual (4, 1)
	355 org/apache/commons/math3/complex/Complex.equals:(Ljava/lang/Object;)Z (4, 1)
	357 ifeq (4, 1)
	358 39 (4, 1)
	360 aload (4, 1)
	361 #12 (4, 1)
	362 new (4, 1)
	363 org/apache/commons/math3/complex/Complex (4, 1)
	365 dup (4, 1)
	366 dload (4, 1)
	367 #4 (4, 1)
	368 dload (4, 1)
	369 #4 (4, 1)
	370 invokespecial (4, 1)
	371 org/apache/commons/math3/complex/Complex.<init>:(DD)V (4, 1)
	373 invokevirtual (4, 1)
	374 org/apache/commons/math3/complex/Complex.add:(Lorg/apache/commons/math3/complex/Complex;)Lorg/apache/commons/math3/complex/Complex; (4, 1)
	376 astore (4, 1)
	377 #12 (4, 1)
	378 new (4, 1)
	379 org/apache/commons/math3/complex/Complex (4, 1)
	381 dup (4, 1)
	382 ldc2_w (4, 1)
	383 inf (4, 1)
	385 ldc2_w (4, 1)
	386 inf (4, 1)
	388 invokespecial (4, 1)
	389 org/apache/commons/math3/complex/Complex.<init>:(DD)V (4, 1)
	391 astore (4, 1)
	392 #13 (4, 1)
	393 goto (4, 1)
	394 21 (4, 1)
	396 aload (5, 2)
	397 #12 (5, 2)
	398 astore (5, 2)
	399 #13 (5, 2)
	400 aload (5, 2)
	401 #12 (5, 2)
	402 aload (5, 2)
	403 #10 (5, 2)
	404 aload (5, 2)
	405 #26 (5, 2)
	406 invokevirtual (5, 2)
	407 org/apache/commons/math3/complex/Complex.divide:(Lorg/apache/commons/math3/complex/Complex;)Lorg/apache/commons/math3/complex/Complex; (5, 2)
	409 invokevirtual (5, 2)
	410 org/apache/commons/math3/complex/Complex.subtract:(Lorg/apache/commons/math3/complex/Complex;)Lorg/apache/commons/math3/complex/Complex; (5, 2)
	412 astore (5, 2)
	413 #12 (5, 2)
	414 aload_0 (3, 1)
	415 getfield (3, 1)
	416 org/apache/commons/math3/analysis/solvers/LaguerreSolver$ComplexSolver.this$0:Lorg/apache/commons/math3/analysis/solvers/LaguerreSolver; (3, 1)
	418 invokevirtual (3, 1)
	419 org/apache/commons/math3/analysis/solvers/LaguerreSolver.incrementEvaluationCount:()V (3, 1)
	421 goto (0, 0)
	422 -318 (0, 0)

