Method: <init>
	0 aload_0 (0, 0)
	1 dload_1 (0, 0)
	2 dload_3 (0, 0)
	3 dload (0, 0)
	4 #5 (0, 0)
	5 invokespecial (0, 0)
	6 org/apache/commons/math3/analysis/solvers/AbstractPolynomialSolver.<init>:(DDD)V (0, 0)
	8 aload_0 (0, 0)
	9 new (0, 0)
	10 org/apache/commons/math3/analysis/solvers/LaguerreSolver$ComplexSolver (0, 0)
	12 dup (0, 0)
	13 aload_0 (0, 0)
	14 aconst_null (0, 0)
	15 invokespecial (0, 0)
	16 org/apache/commons/math3/analysis/solvers/LaguerreSolver$ComplexSolver.<init>:(Lorg/apache/commons/math3/analysis/solvers/LaguerreSolver;Lorg/apache/commons/math3/analysis/solvers/LaguerreSolver$1;)V (0, 0)
	18 putfield (0, 0)
	19 org/apache/commons/math3/analysis/solvers/LaguerreSolver.complexSolver:Lorg/apache/commons/math3/analysis/solvers/LaguerreSolver$ComplexSolver; (0, 0)
	21 return (0, 0)

Method: doSolve
	0 aload_0 (0, 0)
	1 invokevirtual (0, 0)
	2 org/apache/commons/math3/analysis/solvers/LaguerreSolver.getMin:()D (0, 0)
	4 dstore_1 (0, 0)
	5 aload_0 (0, 0)
	6 invokevirtual (0, 0)
	7 org/apache/commons/math3/analysis/solvers/LaguerreSolver.getMax:()D (0, 0)
	9 dstore_3 (0, 0)
	10 aload_0 (0, 0)
	11 invokevirtual (0, 0)
	12 org/apache/commons/math3/analysis/solvers/LaguerreSolver.getStartValue:()D (0, 0)
	14 dstore (0, 0)
	15 #5 (0, 0)
	16 aload_0 (0, 0)
	17 invokevirtual (0, 0)
	18 org/apache/commons/math3/analysis/solvers/LaguerreSolver.getFunctionValueAccuracy:()D (0, 0)
	20 dstore (0, 0)
	21 #7 (0, 0)
	22 aload_0 (1, 1)
	23 dload_1 (1, 1)
	24 dload (1, 1)
	25 #5 (1, 1)
	26 dload_3 (1, 1)
	27 invokevirtual (1, 1)
	28 org/apache/commons/math3/analysis/solvers/LaguerreSolver.verifySequence:(DDD)V (1, 1)
	30 aload_0 (2, 1)
	31 dload (2, 1)
	32 #5 (2, 1)
	33 invokevirtual (2, 1)
	34 org/apache/commons/math3/analysis/solvers/LaguerreSolver.computeObjectiveValue:(D)D (2, 1)
	36 dstore (2, 1)
	37 #9 (2, 1)
	38 dload (3, 1)
	39 #9 (3, 1)
	40 invokestatic (3, 1)
	41 org/apache/commons/math3/util/FastMath.abs:(D)D (3, 1)
	43 dload (3, 1)
	44 #7 (3, 1)
	45 dcmpg (3, 1)
	46 ifgt (3, 1)
	47 6 (3, 1)
	49 dload (3, 1)
	50 #5 (3, 1)
	51 dreturn (3, 1)
	52 aload_0 (3, 1)
	53 dload_1 (3, 1)
	54 invokevirtual (3, 1)
	55 org/apache/commons/math3/analysis/solvers/LaguerreSolver.computeObjectiveValue:(D)D (3, 1)
	57 dstore (3, 1)
	58 #11 (3, 1)
	59 dload (4, 1)
	60 #11 (4, 1)
	61 invokestatic (4, 1)
	62 org/apache/commons/math3/util/FastMath.abs:(D)D (4, 1)
	64 dload (4, 1)
	65 #7 (4, 1)
	66 dcmpg (4, 1)
	67 ifgt (4, 1)
	68 5 (4, 1)
	70 dload_1 (4, 1)
	71 dreturn (4, 1)
	72 dload (5, 1)
	73 #9 (5, 1)
	74 dload (5, 1)
	75 #11 (5, 1)
	76 dmul (5, 1)
	77 dconst_0 (5, 1)
	78 dcmpg (5, 1)
	79 ifge (5, 1)
	80 15 (5, 1)
	82 aload_0 (5, 1)
	83 dload_1 (5, 1)
	84 dload (5, 1)
	85 #5 (5, 1)
	86 dload (5, 1)
	87 #11 (5, 1)
	88 dload (5, 1)
	89 #9 (5, 1)
	90 invokevirtual (5, 1)
	91 org/apache/commons/math3/analysis/solvers/LaguerreSolver.laguerre:(DDDD)D (5, 1)
	93 dreturn (5, 1)
	94 aload_0 (5, 1)
	95 dload_3 (5, 1)
	96 invokevirtual (5, 1)
	97 org/apache/commons/math3/analysis/solvers/LaguerreSolver.computeObjectiveValue:(D)D (5, 1)
	99 dstore (5, 1)
	100 #13 (5, 1)
	101 dload (6, 1)
	102 #13 (6, 1)
	103 invokestatic (6, 1)
	104 org/apache/commons/math3/util/FastMath.abs:(D)D (6, 1)
	106 dload (6, 1)
	107 #7 (6, 1)
	108 dcmpg (6, 1)
	109 ifgt (6, 1)
	110 5 (6, 1)
	112 dload_3 (6, 1)
	113 dreturn (6, 1)
	114 dload (7, 1)
	115 #9 (7, 1)
	116 dload (7, 1)
	117 #13 (7, 1)
	118 dmul (7, 1)
	119 dconst_0 (7, 1)
	120 dcmpg (7, 1)
	121 ifge (7, 1)
	122 15 (7, 1)
	124 aload_0 (7, 1)
	125 dload (7, 1)
	126 #5 (7, 1)
	127 dload_3 (7, 1)
	128 dload (7, 1)
	129 #9 (7, 1)
	130 dload (7, 1)
	131 #13 (7, 1)
	132 invokevirtual (7, 1)
	133 org/apache/commons/math3/analysis/solvers/LaguerreSolver.laguerre:(DDDD)D (7, 1)
	135 dreturn (7, 1)
	136 new (6, 1)
	137 org/apache/commons/math3/exception/NoBracketingException (6, 1)
	139 dup (6, 1)
	140 dload_1 (6, 1)
	141 dload_3 (6, 1)
	142 dload (6, 1)
	143 #11 (6, 1)
	144 dload (6, 1)
	145 #13 (6, 1)
	146 invokespecial (6, 1)
	147 org/apache/commons/math3/exception/NoBracketingException.<init>:(DDDD)V (6, 1)
	149 athrow (0, 1)

Method: laguerre
	0 aload_0 (0, 0)
	1 invokevirtual (0, 0)
	2 org/apache/commons/math3/analysis/solvers/LaguerreSolver.getCoefficients:()[D (0, 0)
	4 invokestatic (0, 0)
	5 org/apache/commons/math3/complex/ComplexUtils.convertToComplex:([D)[Lorg/apache/commons/math3/complex/Complex; (0, 0)
	7 astore (0, 0)
	8 #9 (0, 0)
	9 new (0, 0)
	10 org/apache/commons/math3/complex/Complex (0, 0)
	12 dup (0, 0)
	13 ldc2_w (0, 0)
	14 0.5 (0, 0)
	16 dload_1 (0, 0)
	17 dload_3 (0, 0)
	18 dadd (0, 0)
	19 dmul (0, 0)
	20 dconst_0 (0, 0)
	21 invokespecial (0, 0)
	22 org/apache/commons/math3/complex/Complex.<init>:(DD)V (0, 0)
	24 astore (0, 0)
	25 #10 (0, 0)
	26 aload_0 (0, 0)
	27 getfield (0, 0)
	28 org/apache/commons/math3/analysis/solvers/LaguerreSolver.complexSolver:Lorg/apache/commons/math3/analysis/solvers/LaguerreSolver$ComplexSolver; (0, 0)
	30 aload (0, 0)
	31 #9 (0, 0)
	32 aload (0, 0)
	33 #10 (0, 0)
	34 invokevirtual (0, 0)
	35 org/apache/commons/math3/analysis/solvers/LaguerreSolver$ComplexSolver.solve:([Lorg/apache/commons/math3/complex/Complex;Lorg/apache/commons/math3/complex/Complex;)Lorg/apache/commons/math3/complex/Complex; (0, 0)
	37 astore (0, 0)
	38 #11 (0, 0)
	39 aload_0 (1, 1)
	40 getfield (1, 1)
	41 org/apache/commons/math3/analysis/solvers/LaguerreSolver.complexSolver:Lorg/apache/commons/math3/analysis/solvers/LaguerreSolver$ComplexSolver; (1, 1)
	43 dload_1 (1, 1)
	44 dload_3 (1, 1)
	45 aload (1, 1)
	46 #11 (1, 1)
	47 invokevirtual (1, 1)
	48 org/apache/commons/math3/analysis/solvers/LaguerreSolver$ComplexSolver.isRoot:(DDLorg/apache/commons/math3/complex/Complex;)Z (1, 1)
	50 ifeq (1, 1)
	51 9 (1, 1)
	53 aload (1, 1)
	54 #11 (1, 1)
	55 invokevirtual (1, 1)
	56 org/apache/commons/math3/complex/Complex.getReal:()D (1, 1)
	58 dreturn (1, 1)
	59 ldc2_w (2, 2)
	60 nan (2, 2)
	62 dstore (2, 2)
	63 #12 (2, 2)
	64 aload_0 (2, 2)
	65 getfield (2, 2)
	66 org/apache/commons/math3/analysis/solvers/LaguerreSolver.complexSolver:Lorg/apache/commons/math3/analysis/solvers/LaguerreSolver$ComplexSolver; (2, 2)
	68 aload (2, 2)
	69 #9 (2, 2)
	70 aload (2, 2)
	71 #10 (2, 2)
	72 invokevirtual (2, 2)
	73 org/apache/commons/math3/analysis/solvers/LaguerreSolver$ComplexSolver.solveAll:([Lorg/apache/commons/math3/complex/Complex;Lorg/apache/commons/math3/complex/Complex;)[Lorg/apache/commons/math3/complex/Complex; (2, 2)
	75 astore (2, 2)
	76 #14 (2, 2)
	77 iconst_0 (3, 4)
	78 istore (3, 4)
	79 #15 (3, 4)
	80 iload (3, 4)
	81 #15 (3, 4)
	82 aload (3, 4)
	83 #14 (3, 4)
	84 arraylength (3, 4)
	85 if_icmpge (3, 4)
	86 39 (3, 4)
	88 aload_0 (4, 1)
	89 getfield (4, 1)
	90 org/apache/commons/math3/analysis/solvers/LaguerreSolver.complexSolver:Lorg/apache/commons/math3/analysis/solvers/LaguerreSolver$ComplexSolver; (4, 1)
	92 dload_1 (4, 1)
	93 dload_3 (4, 1)
	94 aload (4, 1)
	95 #14 (4, 1)
	96 iload (4, 1)
	97 #15 (4, 1)
	98 aaload (4, 1)
	99 invokevirtual (4, 1)
	100 org/apache/commons/math3/analysis/solvers/LaguerreSolver$ComplexSolver.isRoot:(DDLorg/apache/commons/math3/complex/Complex;)Z (4, 1)
	102 ifeq (4, 1)
	103 16 (4, 1)
	105 aload (4, 1)
	106 #14 (4, 1)
	107 iload (4, 1)
	108 #15 (4, 1)
	109 aaload (4, 1)
	110 invokevirtual (4, 1)
	111 org/apache/commons/math3/complex/Complex.getReal:()D (4, 1)
	113 dstore (4, 1)
	114 #12 (4, 1)
	115 goto (4, 1)
	116 9 (4, 1)
	118 iinc (4, 1)
	119 #15 (4, 1)
	120 -89 (4, 1)
	121 goto (4, 1)
	122 -41 (4, 1)
	124 dload (3, 4)
	125 #12 (3, 4)
	126 dreturn (2, 4)

Method: solveAllComplex
	0 aload_0 (0, 0)
	1 iload (0, 0)
	2 #4 (0, 0)
	3 new (0, 0)
	4 org/apache/commons/math3/analysis/polynomials/PolynomialFunction (0, 0)
	6 dup (0, 0)
	7 aload_1 (0, 0)
	8 invokespecial (0, 0)
	9 org/apache/commons/math3/analysis/polynomials/PolynomialFunction.<init>:([D)V (0, 0)
	11 ldc2_w (0, 0)
	12 -inf (0, 0)
	14 ldc2_w (0, 0)
	15 inf (0, 0)
	17 dload_2 (0, 0)
	18 invokevirtual (0, 0)
	19 org/apache/commons/math3/analysis/solvers/LaguerreSolver.setup:(ILorg/apache/commons/math3/analysis/polynomials/PolynomialFunction;DDD)V (0, 0)
	21 aload_0 (0, 0)
	22 getfield (0, 0)
	23 org/apache/commons/math3/analysis/solvers/LaguerreSolver.complexSolver:Lorg/apache/commons/math3/analysis/solvers/LaguerreSolver$ComplexSolver; (0, 0)
	25 aload_1 (0, 0)
	26 invokestatic (0, 0)
	27 org/apache/commons/math3/complex/ComplexUtils.convertToComplex:([D)[Lorg/apache/commons/math3/complex/Complex; (0, 0)
	29 new (0, 0)
	30 org/apache/commons/math3/complex/Complex (0, 0)
	32 dup (0, 0)
	33 dload_2 (0, 0)
	34 dconst_0 (0, 0)
	35 invokespecial (0, 0)
	36 org/apache/commons/math3/complex/Complex.<init>:(DD)V (0, 0)
	38 invokevirtual (0, 0)
	39 org/apache/commons/math3/analysis/solvers/LaguerreSolver$ComplexSolver.solveAll:([Lorg/apache/commons/math3/complex/Complex;Lorg/apache/commons/math3/complex/Complex;)[Lorg/apache/commons/math3/complex/Complex; (0, 0)
	41 areturn (0, 0)

Method: solveComplex
	0 aload_0 (0, 0)
	1 iload (0, 0)
	2 #4 (0, 0)
	3 new (0, 0)
	4 org/apache/commons/math3/analysis/polynomials/PolynomialFunction (0, 0)
	6 dup (0, 0)
	7 aload_1 (0, 0)
	8 invokespecial (0, 0)
	9 org/apache/commons/math3/analysis/polynomials/PolynomialFunction.<init>:([D)V (0, 0)
	11 ldc2_w (0, 0)
	12 -inf (0, 0)
	14 ldc2_w (0, 0)
	15 inf (0, 0)
	17 dload_2 (0, 0)
	18 invokevirtual (0, 0)
	19 org/apache/commons/math3/analysis/solvers/LaguerreSolver.setup:(ILorg/apache/commons/math3/analysis/polynomials/PolynomialFunction;DDD)V (0, 0)
	21 aload_0 (0, 0)
	22 getfield (0, 0)
	23 org/apache/commons/math3/analysis/solvers/LaguerreSolver.complexSolver:Lorg/apache/commons/math3/analysis/solvers/LaguerreSolver$ComplexSolver; (0, 0)
	25 aload_1 (0, 0)
	26 invokestatic (0, 0)
	27 org/apache/commons/math3/complex/ComplexUtils.convertToComplex:([D)[Lorg/apache/commons/math3/complex/Complex; (0, 0)
	29 new (0, 0)
	30 org/apache/commons/math3/complex/Complex (0, 0)
	32 dup (0, 0)
	33 dload_2 (0, 0)
	34 dconst_0 (0, 0)
	35 invokespecial (0, 0)
	36 org/apache/commons/math3/complex/Complex.<init>:(DD)V (0, 0)
	38 invokevirtual (0, 0)
	39 org/apache/commons/math3/analysis/solvers/LaguerreSolver$ComplexSolver.solve:([Lorg/apache/commons/math3/complex/Complex;Lorg/apache/commons/math3/complex/Complex;)Lorg/apache/commons/math3/complex/Complex; (0, 0)
	41 areturn (0, 0)

