Method: <init>
	0 aload_0 (0, 0)
	1 dload_1 (0, 0)
	2 dload_3 (0, 0)
	3 invokespecial (0, 0)
	4 org/apache/commons/math3/analysis/solvers/AbstractUnivariateSolver.<init>:(DD)V (0, 0)
	6 return (0, 0)

Method: doSolve
	0 aload_0 (0, 0)
	1 invokevirtual (0, 0)
	2 org/apache/commons/math3/analysis/solvers/MullerSolver.getMin:()D (0, 0)
	4 dstore_1 (0, 0)
	5 aload_0 (0, 0)
	6 invokevirtual (0, 0)
	7 org/apache/commons/math3/analysis/solvers/MullerSolver.getMax:()D (0, 0)
	9 dstore_3 (0, 0)
	10 aload_0 (0, 0)
	11 invokevirtual (0, 0)
	12 org/apache/commons/math3/analysis/solvers/MullerSolver.getStartValue:()D (0, 0)
	14 dstore (0, 0)
	15 #5 (0, 0)
	16 aload_0 (0, 0)
	17 invokevirtual (0, 0)
	18 org/apache/commons/math3/analysis/solvers/MullerSolver.getFunctionValueAccuracy:()D (0, 0)
	20 dstore (0, 0)
	21 #7 (0, 0)
	22 aload_0 (1, 1)
	23 dload_1 (1, 1)
	24 dload (1, 1)
	25 #5 (1, 1)
	26 dload_3 (1, 1)
	27 invokevirtual (1, 1)
	28 org/apache/commons/math3/analysis/solvers/MullerSolver.verifySequence:(DDD)V (1, 1)
	30 aload_0 (2, 1)
	31 dload_1 (2, 1)
	32 invokevirtual (2, 1)
	33 org/apache/commons/math3/analysis/solvers/MullerSolver.computeObjectiveValue:(D)D (2, 1)
	35 dstore (2, 1)
	36 #9 (2, 1)
	37 dload (3, 1)
	38 #9 (3, 1)
	39 invokestatic (3, 1)
	40 org/apache/commons/math3/util/FastMath.abs:(D)D (3, 1)
	42 dload (3, 1)
	43 #7 (3, 1)
	44 dcmpg (3, 1)
	45 ifge (3, 1)
	46 5 (3, 1)
	48 dload_1 (3, 1)
	49 dreturn (3, 1)
	50 aload_0 (2, 1)
	51 dload_3 (2, 1)
	52 invokevirtual (2, 1)
	53 org/apache/commons/math3/analysis/solvers/MullerSolver.computeObjectiveValue:(D)D (2, 1)
	55 dstore (2, 1)
	56 #11 (2, 1)
	57 dload (3, 1)
	58 #11 (3, 1)
	59 invokestatic (3, 1)
	60 org/apache/commons/math3/util/FastMath.abs:(D)D (3, 1)
	62 dload (3, 1)
	63 #7 (3, 1)
	64 dcmpg (3, 1)
	65 ifge (3, 1)
	66 5 (3, 1)
	68 dload_3 (3, 1)
	69 dreturn (3, 1)
	70 aload_0 (2, 1)
	71 dload (2, 1)
	72 #5 (2, 1)
	73 invokevirtual (2, 1)
	74 org/apache/commons/math3/analysis/solvers/MullerSolver.computeObjectiveValue:(D)D (2, 1)
	76 dstore (2, 1)
	77 #13 (2, 1)
	78 dload (3, 1)
	79 #13 (3, 1)
	80 invokestatic (3, 1)
	81 org/apache/commons/math3/util/FastMath.abs:(D)D (3, 1)
	83 dload (3, 1)
	84 #7 (3, 1)
	85 dcmpg (3, 1)
	86 ifge (3, 1)
	87 6 (3, 1)
	89 dload (3, 1)
	90 #5 (3, 1)
	91 dreturn (3, 1)
	92 aload_0 (3, 1)
	93 dload_1 (3, 1)
	94 dload_3 (3, 1)
	95 invokevirtual (3, 1)
	96 org/apache/commons/math3/analysis/solvers/MullerSolver.verifyBracketing:(DD)V (3, 1)
	98 aload_0 (4, 1)
	99 dload_1 (4, 1)
	100 dload (4, 1)
	101 #5 (4, 1)
	102 invokevirtual (4, 1)
	103 org/apache/commons/math3/analysis/solvers/MullerSolver.isBracketing:(DD)Z (4, 1)
	105 ifeq (4, 1)
	106 15 (4, 1)
	108 aload_0 (4, 1)
	109 dload_1 (4, 1)
	110 dload (4, 1)
	111 #5 (4, 1)
	112 dload (4, 1)
	113 #9 (4, 1)
	114 dload (4, 1)
	115 #13 (4, 1)
	116 invokespecial (4, 1)
	117 org/apache/commons/math3/analysis/solvers/MullerSolver.solve:(DDDD)D (4, 1)
	119 dreturn (4, 1)
	120 aload_0 (5, 2)
	121 dload (5, 2)
	122 #5 (5, 2)
	123 dload_3 (5, 2)
	124 dload (5, 2)
	125 #13 (5, 2)
	126 dload (5, 2)
	127 #11 (5, 2)
	128 invokespecial (5, 2)
	129 org/apache/commons/math3/analysis/solvers/MullerSolver.solve:(DDDD)D (5, 2)
	131 dreturn (1, 2)

Method: solve
	0 aload_0 (0, 0)
	1 invokevirtual (0, 0)
	2 org/apache/commons/math3/analysis/solvers/MullerSolver.getRelativeAccuracy:()D (0, 0)
	4 dstore (0, 0)
	5 #9 (0, 0)
	6 aload_0 (0, 0)
	7 invokevirtual (0, 0)
	8 org/apache/commons/math3/analysis/solvers/MullerSolver.getAbsoluteAccuracy:()D (0, 0)
	10 dstore (0, 0)
	11 #11 (0, 0)
	12 aload_0 (0, 0)
	13 invokevirtual (0, 0)
	14 org/apache/commons/math3/analysis/solvers/MullerSolver.getFunctionValueAccuracy:()D (0, 0)
	16 dstore (0, 0)
	17 #13 (0, 0)
	18 dload_1 (2, 1)
	19 dstore (2, 1)
	20 #15 (2, 1)
	21 dload (2, 1)
	22 #5 (2, 1)
	23 dstore (2, 1)
	24 #17 (2, 1)
	25 dload_3 (2, 1)
	26 dstore (2, 1)
	27 #19 (2, 1)
	28 dload (2, 1)
	29 #7 (2, 1)
	30 dstore (2, 1)
	31 #21 (2, 1)
	32 ldc2_w (2, 1)
	33 0.5 (2, 1)
	35 dload (2, 1)
	36 #15 (2, 1)
	37 dload (2, 1)
	38 #19 (2, 1)
	39 dadd (2, 1)
	40 dmul (2, 1)
	41 dstore (2, 1)
	42 #23 (2, 1)
	43 aload_0 (2, 1)
	44 dload (2, 1)
	45 #23 (2, 1)
	46 invokevirtual (2, 1)
	47 org/apache/commons/math3/analysis/solvers/MullerSolver.computeObjectiveValue:(D)D (2, 1)
	49 dstore (2, 1)
	50 #25 (2, 1)
	51 ldc2_w (2, 1)
	52 inf (2, 1)
	54 dstore (2, 1)
	55 #27 (2, 1)
	56 dload (3, 3)
	57 #25 (3, 3)
	58 dload (3, 3)
	59 #17 (3, 3)
	60 dsub (3, 3)
	61 dload (3, 3)
	62 #23 (3, 3)
	63 dload (3, 3)
	64 #15 (3, 3)
	65 dsub (3, 3)
	66 ddiv (3, 3)
	67 dstore (3, 3)
	68 #29 (3, 3)
	69 dload (3, 3)
	70 #21 (3, 3)
	71 dload (3, 3)
	72 #25 (3, 3)
	73 dsub (3, 3)
	74 dload (3, 3)
	75 #19 (3, 3)
	76 dload (3, 3)
	77 #23 (3, 3)
	78 dsub (3, 3)
	79 ddiv (3, 3)
	80 dstore (3, 3)
	81 #31 (3, 3)
	82 dload (3, 3)
	83 #31 (3, 3)
	84 dload (3, 3)
	85 #29 (3, 3)
	86 dsub (3, 3)
	87 dload (3, 3)
	88 #19 (3, 3)
	89 dload (3, 3)
	90 #15 (3, 3)
	91 dsub (3, 3)
	92 ddiv (3, 3)
	93 dstore (3, 3)
	94 #33 (3, 3)
	95 dload (3, 3)
	96 #29 (3, 3)
	97 dload (3, 3)
	98 #23 (3, 3)
	99 dload (3, 3)
	100 #15 (3, 3)
	101 dsub (3, 3)
	102 dload (3, 3)
	103 #33 (3, 3)
	104 dmul (3, 3)
	105 dadd (3, 3)
	106 dstore (3, 3)
	107 #35 (3, 3)
	108 dload (3, 3)
	109 #35 (3, 3)
	110 dload (3, 3)
	111 #35 (3, 3)
	112 dmul (3, 3)
	113 ldc2_w (3, 3)
	114 4.0 (3, 3)
	116 dload (3, 3)
	117 #25 (3, 3)
	118 dmul (3, 3)
	119 dload (3, 3)
	120 #33 (3, 3)
	121 dmul (3, 3)
	122 dsub (3, 3)
	123 dstore (3, 3)
	124 #37 (3, 3)
	125 dload (3, 3)
	126 #23 (3, 3)
	127 ldc2_w (3, 3)
	128 -2.0 (3, 3)
	130 dload (3, 3)
	131 #25 (3, 3)
	132 dmul (3, 3)
	133 dload (3, 3)
	134 #35 (3, 3)
	135 dload (3, 3)
	136 #37 (3, 3)
	137 invokestatic (3, 3)
	138 org/apache/commons/math3/util/FastMath.sqrt:(D)D (3, 3)
	140 dadd (3, 3)
	141 ddiv (3, 3)
	142 dadd (3, 3)
	143 dstore (3, 3)
	144 #39 (3, 3)
	145 dload (3, 3)
	146 #23 (3, 3)
	147 ldc2_w (3, 3)
	148 -2.0 (3, 3)
	150 dload (3, 3)
	151 #25 (3, 3)
	152 dmul (3, 3)
	153 dload (3, 3)
	154 #35 (3, 3)
	155 dload (3, 3)
	156 #37 (3, 3)
	157 invokestatic (3, 3)
	158 org/apache/commons/math3/util/FastMath.sqrt:(D)D (3, 3)
	160 dsub (3, 3)
	161 ddiv (3, 3)
	162 dadd (3, 3)
	163 dstore (3, 3)
	164 #41 (3, 3)
	165 aload_0 (3, 3)
	166 dload (3, 3)
	167 #15 (3, 3)
	168 dload (3, 3)
	169 #39 (3, 3)
	170 dload (3, 3)
	171 #19 (3, 3)
	172 invokevirtual (3, 3)
	173 org/apache/commons/math3/analysis/solvers/MullerSolver.isSequence:(DDD)Z (3, 3)
	175 ifeq (3, 3)
	176 8 (3, 3)
	178 dload (3, 3)
	179 #39 (3, 3)
	180 goto (3, 3)
	181 5 (3, 3)
	183 dload (3, 3)
	184 #41 (3, 3)
	185 dstore (3, 3)
	186 #43 (3, 3)
	187 aload_0 (3, 3)
	188 dload (3, 3)
	189 #43 (3, 3)
	190 invokevirtual (3, 3)
	191 org/apache/commons/math3/analysis/solvers/MullerSolver.computeObjectiveValue:(D)D (3, 3)
	193 dstore (3, 3)
	194 #45 (3, 3)
	195 dload (4, 4)
	196 #9 (4, 4)
	197 dload (4, 4)
	198 #43 (4, 4)
	199 invokestatic (4, 4)
	200 org/apache/commons/math3/util/FastMath.abs:(D)D (4, 4)
	202 dmul (4, 4)
	203 dload (4, 4)
	204 #11 (4, 4)
	205 invokestatic (4, 4)
	206 org/apache/commons/math3/util/FastMath.max:(DD)D (4, 4)
	208 dstore (4, 4)
	209 #47 (4, 4)
	210 dload (5, 1)
	211 #43 (5, 1)
	212 dload (5, 1)
	213 #27 (5, 1)
	214 dsub (5, 1)
	215 invokestatic (5, 1)
	216 org/apache/commons/math3/util/FastMath.abs:(D)D (5, 1)
	218 dload (5, 1)
	219 #47 (5, 1)
	220 dcmpg (5, 1)
	221 ifle (5, 1)
	222 14 (5, 1)
	224 dload (5, 1)
	225 #45 (5, 1)
	226 invokestatic (5, 1)
	227 org/apache/commons/math3/util/FastMath.abs:(D)D (5, 1)
	229 dload (5, 1)
	230 #13 (5, 1)
	231 dcmpg (5, 1)
	232 ifgt (5, 1)
	233 6 (5, 1)
	235 dload (5, 1)
	236 #43 (5, 1)
	237 dreturn (5, 1)
	238 dload (6, 1)
	239 #43 (6, 1)
	240 dload (6, 1)
	241 #23 (6, 1)
	242 dcmpg (6, 1)
	243 ifge (6, 1)
	244 21 (6, 1)
	246 dload (6, 1)
	247 #23 (6, 1)
	248 dload (6, 1)
	249 #15 (6, 1)
	250 dsub (6, 1)
	251 ldc2_w (6, 1)
	252 0.95 (6, 1)
	254 dload (6, 1)
	255 #19 (6, 1)
	256 dload (6, 1)
	257 #15 (6, 1)
	258 dsub (6, 1)
	259 dmul (6, 1)
	260 dcmpl (6, 1)
	261 ifgt (6, 1)
	262 37 (6, 1)
	264 dload (6, 1)
	265 #43 (6, 1)
	266 dload (6, 1)
	267 #23 (6, 1)
	268 dcmpl (6, 1)
	269 ifle (6, 1)
	270 21 (6, 1)
	272 dload (6, 1)
	273 #19 (6, 1)
	274 dload (6, 1)
	275 #23 (6, 1)
	276 dsub (6, 1)
	277 ldc2_w (6, 1)
	278 0.95 (6, 1)
	280 dload (6, 1)
	281 #19 (6, 1)
	282 dload (6, 1)
	283 #15 (6, 1)
	284 dsub (6, 1)
	285 dmul (6, 1)
	286 dcmpl (6, 1)
	287 ifgt (6, 1)
	288 11 (6, 1)
	290 dload (6, 1)
	291 #43 (6, 1)
	292 dload (6, 1)
	293 #23 (6, 1)
	294 dcmpl (6, 1)
	295 ifne (6, 1)
	296 7 (6, 1)
	298 iconst_1 (6, 1)
	299 goto (6, 1)
	300 4 (6, 1)
	302 iconst_0 (6, 1)
	303 istore (6, 1)
	304 #49 (6, 1)
	305 iload (8, 1)
	306 #49 (8, 1)
	307 ifne (8, 1)
	308 86 (8, 1)
	310 dload (8, 1)
	311 #43 (8, 1)
	312 dload (8, 1)
	313 #23 (8, 1)
	314 dcmpg (8, 1)
	315 ifge (8, 1)
	316 8 (8, 1)
	318 dload (8, 1)
	319 #15 (8, 1)
	320 goto (8, 1)
	321 5 (8, 1)
	323 dload (8, 1)
	324 #23 (8, 1)
	325 dstore (8, 1)
	326 #15 (8, 1)
	327 dload (8, 1)
	328 #43 (8, 1)
	329 dload (8, 1)
	330 #23 (8, 1)
	331 dcmpg (8, 1)
	332 ifge (8, 1)
	333 8 (8, 1)
	335 dload (8, 1)
	336 #17 (8, 1)
	337 goto (8, 1)
	338 5 (8, 1)
	340 dload (8, 1)
	341 #25 (8, 1)
	342 dstore (8, 1)
	343 #17 (8, 1)
	344 dload (8, 1)
	345 #43 (8, 1)
	346 dload (8, 1)
	347 #23 (8, 1)
	348 dcmpl (8, 1)
	349 ifle (8, 1)
	350 8 (8, 1)
	352 dload (8, 1)
	353 #19 (8, 1)
	354 goto (8, 1)
	355 5 (8, 1)
	357 dload (8, 1)
	358 #23 (8, 1)
	359 dstore (8, 1)
	360 #19 (8, 1)
	361 dload (8, 1)
	362 #43 (8, 1)
	363 dload (8, 1)
	364 #23 (8, 1)
	365 dcmpl (8, 1)
	366 ifle (8, 1)
	367 8 (8, 1)
	369 dload (8, 1)
	370 #21 (8, 1)
	371 goto (8, 1)
	372 5 (8, 1)
	374 dload (8, 1)
	375 #25 (8, 1)
	376 dstore (8, 1)
	377 #21 (8, 1)
	378 dload (8, 1)
	379 #43 (8, 1)
	380 dstore (8, 1)
	381 #23 (8, 1)
	382 dload (8, 1)
	383 #45 (8, 1)
	384 dstore (8, 1)
	385 #25 (8, 1)
	386 dload (8, 1)
	387 #43 (8, 1)
	388 dstore (8, 1)
	389 #27 (8, 1)
	390 goto (8, 1)
	391 81 (8, 1)
	393 ldc2_w (9, 2)
	394 0.5 (9, 2)
	396 dload (9, 2)
	397 #15 (9, 2)
	398 dload (9, 2)
	399 #19 (9, 2)
	400 dadd (9, 2)
	401 dmul (9, 2)
	402 dstore (9, 2)
	403 #50 (9, 2)
	404 aload_0 (9, 2)
	405 dload (9, 2)
	406 #50 (9, 2)
	407 invokevirtual (9, 2)
	408 org/apache/commons/math3/analysis/solvers/MullerSolver.computeObjectiveValue:(D)D (9, 2)
	410 dstore (9, 2)
	411 #52 (9, 2)
	412 dload (10, 1)
	413 #17 (10, 1)
	414 invokestatic (10, 1)
	415 org/apache/commons/math3/util/FastMath.signum:(D)D (10, 1)
	417 dload (10, 1)
	418 #52 (10, 1)
	419 invokestatic (10, 1)
	420 org/apache/commons/math3/util/FastMath.signum:(D)D (10, 1)
	422 dadd (10, 1)
	423 dconst_0 (10, 1)
	424 dcmpl (10, 1)
	425 ifne (10, 1)
	426 14 (10, 1)
	428 dload (10, 1)
	429 #50 (10, 1)
	430 dstore (10, 1)
	431 #19 (10, 1)
	432 dload (10, 1)
	433 #52 (10, 1)
	434 dstore (10, 1)
	435 #21 (10, 1)
	436 goto (10, 1)
	437 11 (10, 1)
	439 dload (11, 2)
	440 #50 (11, 2)
	441 dstore (11, 2)
	442 #15 (11, 2)
	443 dload (11, 2)
	444 #52 (11, 2)
	445 dstore (11, 2)
	446 #17 (11, 2)
	447 ldc2_w (9, 2)
	448 0.5 (9, 2)
	450 dload (9, 2)
	451 #15 (9, 2)
	452 dload (9, 2)
	453 #19 (9, 2)
	454 dadd (9, 2)
	455 dmul (9, 2)
	456 dstore (9, 2)
	457 #23 (9, 2)
	458 aload_0 (9, 2)
	459 dload (9, 2)
	460 #23 (9, 2)
	461 invokevirtual (9, 2)
	462 org/apache/commons/math3/analysis/solvers/MullerSolver.computeObjectiveValue:(D)D (9, 2)
	464 dstore (9, 2)
	465 #25 (9, 2)
	466 ldc2_w (9, 2)
	467 inf (9, 2)
	469 dstore (9, 2)
	470 #27 (9, 2)
	471 goto (0, 1)
	472 -415 (2, 1)

