Method: <init>
	0 aload_0 (0, 0)
	1 dload_1 (0, 0)
	2 invokespecial (0, 0)
	3 org/apache/commons/math3/analysis/solvers/AbstractUnivariateDifferentiableSolver.<init>:(D)V (0, 0)
	5 return (0, 0)

Method: solve
	0 aload_0 (1, 1)
	1 iload_1 (1, 1)
	2 aload_2 (1, 1)
	3 checkcast (1, 1)
	4 org/apache/commons/math3/analysis/differentiation/UnivariateDifferentiableFunction (1, 1)
	6 dload_3 (1, 1)
	7 dload (1, 1)
	8 #5 (1, 1)
	9 invokevirtual (1, 1)
	10 org/apache/commons/math3/analysis/solvers/NewtonRaphsonSolver.solve:(ILorg/apache/commons/math3/analysis/differentiation/UnivariateDifferentiableFunction;DD)D (1, 1)
	12 dreturn (1, 1)

Method: doSolve
	0 aload_0 (0, 0)
	1 invokevirtual (0, 0)
	2 org/apache/commons/math3/analysis/solvers/NewtonRaphsonSolver.getStartValue:()D (0, 0)
	4 dstore_1 (0, 0)
	5 aload_0 (0, 0)
	6 invokevirtual (0, 0)
	7 org/apache/commons/math3/analysis/solvers/NewtonRaphsonSolver.getAbsoluteAccuracy:()D (0, 0)
	9 dstore_3 (0, 0)
	10 dload_1 (0, 0)
	11 dstore (0, 0)
	12 #5 (0, 0)
	13 aload_0 (1, 3)
	14 dload (1, 3)
	15 #5 (1, 3)
	16 invokevirtual (1, 3)
	17 org/apache/commons/math3/analysis/solvers/NewtonRaphsonSolver.computeObjectiveValueAndDerivative:(D)Lorg/apache/commons/math3/analysis/differentiation/DerivativeStructure; (1, 3)
	19 astore (1, 3)
	20 #9 (1, 3)
	21 dload (1, 3)
	22 #5 (1, 3)
	23 aload (1, 3)
	24 #9 (1, 3)
	25 invokevirtual (1, 3)
	26 org/apache/commons/math3/analysis/differentiation/DerivativeStructure.getValue:()D (1, 3)
	28 aload (1, 3)
	29 #9 (1, 3)
	30 iconst_1 (1, 3)
	31 newarray (1, 3)
	32 10 (1, 3)
	33 dup (1, 3)
	34 iconst_0 (1, 3)
	35 iconst_1 (1, 3)
	36 iastore (1, 3)
	37 invokevirtual (1, 3)
	38 org/apache/commons/math3/analysis/differentiation/DerivativeStructure.getPartialDerivative:([I)D (1, 3)
	40 ddiv (1, 3)
	41 dsub (1, 3)
	42 dstore (1, 3)
	43 #7 (1, 3)
	44 dload (2, 1)
	45 #7 (2, 1)
	46 dload (2, 1)
	47 #5 (2, 1)
	48 dsub (2, 1)
	49 invokestatic (2, 1)
	50 org/apache/commons/math3/util/FastMath.abs:(D)D (2, 1)
	52 dload_3 (2, 1)
	53 dcmpg (2, 1)
	54 ifgt (2, 1)
	55 6 (2, 1)
	57 dload (2, 1)
	58 #7 (2, 1)
	59 dreturn (2, 1)
	60 dload (1, 3)
	61 #7 (1, 3)
	62 dstore (1, 3)
	63 #5 (1, 3)
	64 goto (0, 0)
	65 -51 (0, 0)

