Method: solve
	0 aload_0 (1, 1)
	1 ifnonnull (1, 1)
	2 18 (1, 1)
	4 new (1, 1)
	5 org/apache/commons/math3/exception/NullArgumentException (1, 1)
	7 dup (1, 1)
	8 getstatic (1, 1)
	9 org/apache/commons/math3/exception/util/LocalizedFormats.FUNCTION:Lorg/apache/commons/math3/exception/util/LocalizedFormats; (1, 1)
	11 iconst_0 (1, 1)
	12 anewarray (1, 1)
	13 java/lang/Object (1, 1)
	15 invokespecial (1, 1)
	16 org/apache/commons/math3/exception/NullArgumentException.<init>:(Lorg/apache/commons/math3/exception/util/Localizable;[Ljava/lang/Object;)V (1, 1)
	18 athrow (1, 1)
	19 new (0, 0)
	20 org/apache/commons/math3/analysis/solvers/BrentSolver (0, 0)
	22 dup (0, 0)
	23 dload (0, 0)
	24 #5 (0, 0)
	25 invokespecial (0, 0)
	26 org/apache/commons/math3/analysis/solvers/BrentSolver.<init>:(D)V (0, 0)
	28 astore (0, 0)
	29 #7 (0, 0)
	30 aload (0, 0)
	31 #7 (0, 0)
	32 ldc (0, 0)
	33 2147483647 (0, 0)
	34 aload_0 (0, 0)
	35 dload_1 (0, 0)
	36 dload_3 (0, 0)
	37 invokeinterface (0, 0)
	38 org/apache/commons/math3/analysis/solvers/UnivariateSolver.<init>:(D)V (0, 0)
	40 0 (0, 0)
	42 dreturn (0, 0)

Method: forceSide
	0 aload (1, 1)
	1 #9 (1, 1)
	2 getstatic (1, 1)
	3 org/apache/commons/math3/analysis/solvers/AllowedSolution.ANY_SIDE:Lorg/apache/commons/math3/analysis/solvers/AllowedSolution; (1, 1)
	5 if_acmpne (1, 1)
	6 5 (1, 1)
	8 dload_3 (1, 1)
	9 dreturn (1, 1)
	10 aload_2 (0, 0)
	11 invokeinterface (0, 0)
	12 org/apache/commons/math3/analysis/solvers/BracketedUnivariateSolver.getRelativeAccuracy:()D (0, 0)
	14 0 (0, 0)
	16 dload_3 (0, 0)
	17 aload_2 (0, 0)
	18 invokeinterface (0, 0)
	19 org/apache/commons/math3/analysis/solvers/BracketedUnivariateSolver.org/apache/commons/math3/util/FastMath (0, 0)
	21 0 (0, 0)
	23 dmul (0, 0)
	24 invokestatic (0, 0)
	25 org/apache/commons/math3/util/FastMath.abs:(D)D (0, 0)
	27 invokestatic (0, 0)
	28 org/apache/commons/math3/util/FastMath.max:(DD)D (0, 0)
	30 dstore (0, 0)
	31 #10 (0, 0)
	32 dload (0, 0)
	33 #5 (0, 0)
	34 dload_3 (0, 0)
	35 dload (0, 0)
	36 #10 (0, 0)
	37 dsub (0, 0)
	38 invokestatic (0, 0)
	39 org/apache/commons/math3/util/FastMath.max:(DD)D (0, 0)
	41 dstore (0, 0)
	42 #12 (0, 0)
	43 aload_1 (0, 0)
	44 dload (0, 0)
	45 #12 (0, 0)
	46 invokeinterface (0, 0)
	47 org/apache/commons/math3/analysis/UnivariateFunction.min:(DD)D (0, 0)
	49 0 (0, 0)
	51 dstore (0, 0)
	52 #14 (0, 0)
	53 dload (0, 0)
	54 #7 (0, 0)
	55 dload_3 (0, 0)
	56 dload (0, 0)
	57 #10 (0, 0)
	58 dadd (0, 0)
	59 invokestatic (0, 0)
	60 org/apache/commons/math3/util/FastMath.min:(DD)D (0, 0)
	62 dstore (0, 0)
	63 #16 (0, 0)
	64 aload_1 (0, 0)
	65 dload (0, 0)
	66 #16 (0, 0)
	67 invokeinterface (0, 0)
	68 org/apache/commons/math3/analysis/UnivariateFunction.min:(DD)D (0, 0)
	70 0 (0, 0)
	72 dstore (0, 0)
	73 #18 (0, 0)
	74 iload_0 (0, 0)
	75 iconst_2 (0, 0)
	76 isub (0, 0)
	77 istore (0, 0)
	78 #20 (0, 0)
	79 iload (1, 3)
	80 #20 (1, 3)
	81 ifle (1, 3)
	82 177 (1, 3)
	84 dload (2, 1)
	85 #14 (2, 1)
	86 dconst_0 (2, 1)
	87 dcmpl (2, 1)
	88 iflt (2, 1)
	89 10 (2, 1)
	91 dload (2, 1)
	92 #18 (2, 1)
	93 dconst_0 (2, 1)
	94 dcmpg (2, 1)
	95 ifle (2, 1)
	96 17 (2, 1)
	98 dload (2, 1)
	99 #14 (2, 1)
	100 dconst_0 (2, 1)
	101 dcmpg (2, 1)
	102 ifgt (2, 1)
	103 27 (2, 1)
	105 dload (2, 1)
	106 #18 (2, 1)
	107 dconst_0 (2, 1)
	108 dcmpl (2, 1)
	109 iflt (2, 1)
	110 20 (2, 1)
	112 aload_2 (2, 1)
	113 iload (2, 1)
	114 #20 (2, 1)
	115 aload_1 (2, 1)
	116 dload (2, 1)
	117 #12 (2, 1)
	118 dload (2, 1)
	119 #16 (2, 1)
	120 dload_3 (2, 1)
	121 aload (2, 1)
	122 #9 (2, 1)
	123 invokeinterface (2, 1)
	124 org/apache/commons/math3/analysis/solvers/BracketedUnivariateSolver.org/apache/commons/math3/exception/NoBracketingException (2, 1)
	126 0 (2, 1)
	128 dreturn (2, 1)
	129 iconst_0 (1, 3)
	130 istore (1, 3)
	131 #21 (1, 3)
	132 iconst_0 (1, 3)
	133 istore (1, 3)
	134 #22 (1, 3)
	135 dload (2, 1)
	136 #14 (2, 1)
	137 dload (2, 1)
	138 #18 (2, 1)
	139 dcmpg (2, 1)
	140 ifge (2, 1)
	141 22 (2, 1)
	143 dload (3, 1)
	144 #14 (3, 1)
	145 dconst_0 (3, 1)
	146 dcmpl (3, 1)
	147 iflt (3, 1)
	148 9 (3, 1)
	150 iconst_1 (3, 1)
	151 istore (3, 1)
	152 #21 (3, 1)
	153 goto (3, 1)
	154 42 (3, 1)
	156 iconst_1 (3, 2)
	157 istore (3, 2)
	158 #22 (3, 2)
	159 goto (3, 2)
	160 36 (3, 2)
	162 dload (2, 1)
	163 #14 (2, 1)
	164 dload (2, 1)
	165 #18 (2, 1)
	166 dcmpl (2, 1)
	167 ifle (2, 1)
	168 22 (2, 1)
	170 dload (3, 1)
	171 #14 (3, 1)
	172 dconst_0 (3, 1)
	173 dcmpg (3, 1)
	174 ifgt (3, 1)
	175 9 (3, 1)
	177 iconst_1 (3, 1)
	178 istore (3, 1)
	179 #21 (3, 1)
	180 goto (3, 1)
	181 15 (3, 1)
	183 iconst_1 (3, 2)
	184 istore (3, 2)
	185 #22 (3, 2)
	186 goto (3, 2)
	187 9 (3, 2)
	189 iconst_1 (2, 2)
	190 istore (2, 2)
	191 #21 (2, 2)
	192 iconst_1 (2, 2)
	193 istore (2, 2)
	194 #22 (2, 2)
	195 iload (2, 1)
	196 #21 (2, 1)
	197 ifeq (2, 1)
	198 28 (2, 1)
	200 dload (2, 1)
	201 #5 (2, 1)
	202 dload (2, 1)
	203 #12 (2, 1)
	204 dload (2, 1)
	205 #10 (2, 1)
	206 dsub (2, 1)
	207 invokestatic (2, 1)
	208 org/apache/commons/math3/util/FastMath.max:(DD)D (2, 1)
	210 dstore (2, 1)
	211 #12 (2, 1)
	212 aload_1 (2, 1)
	213 dload (2, 1)
	214 #12 (2, 1)
	215 invokeinterface (2, 1)
	216 org/apache/commons/math3/analysis/UnivariateFunction.min:(DD)D (2, 1)
	218 0 (2, 1)
	220 dstore (2, 1)
	221 #14 (2, 1)
	222 iinc (2, 1)
	223 #20 (2, 1)
	224 21 (2, 1)
	225 iload (2, 1)
	226 #22 (2, 1)
	227 ifeq (2, 1)
	228 28 (2, 1)
	230 dload (2, 1)
	231 #7 (2, 1)
	232 dload (2, 1)
	233 #16 (2, 1)
	234 dload (2, 1)
	235 #10 (2, 1)
	236 dadd (2, 1)
	237 invokestatic (2, 1)
	238 org/apache/commons/math3/util/FastMath.min:(DD)D (2, 1)
	240 dstore (2, 1)
	241 #16 (2, 1)
	242 aload_1 (2, 1)
	243 dload (2, 1)
	244 #16 (2, 1)
	245 invokeinterface (2, 1)
	246 org/apache/commons/math3/analysis/UnivariateFunction.min:(DD)D (2, 1)
	248 0 (2, 1)
	250 dstore (2, 1)
	251 #18 (2, 1)
	252 iinc (2, 1)
	253 #20 (2, 1)
	254 -89 (2, 1)
	255 goto (0, 0)
	256 -176 (0, 0)
	258 new (0, 0)
	259 org/apache/commons/math3/exception/NoBracketingException (0, 0)
	261 dup (0, 0)
	262 getstatic (0, 0)
	263 org/apache/commons/math3/exception/util/LocalizedFormats.FAILED_BRACKETING:Lorg/apache/commons/math3/exception/util/LocalizedFormats; (0, 0)
	265 dload (0, 0)
	266 #12 (0, 0)
	267 dload (0, 0)
	268 #16 (0, 0)
	269 dload (0, 0)
	270 #14 (0, 0)
	271 dload (0, 0)
	272 #18 (0, 0)
	273 iconst_5 (0, 0)
	274 anewarray (0, 0)
	275 java/lang/Object (0, 0)
	277 dup (0, 0)
	278 iconst_0 (0, 0)
	279 iload_0 (0, 0)
	280 iload (0, 0)
	281 #20 (0, 0)
	282 isub (0, 0)
	283 invokestatic (0, 0)
	284 java/lang/Integer.valueOf:(I)Ljava/lang/Integer; (0, 0)
	286 aastore (0, 0)
	287 dup (0, 0)
	288 iconst_1 (0, 0)
	289 iload_0 (0, 0)
	290 invokestatic (0, 0)
	291 java/lang/Integer.valueOf:(I)Ljava/lang/Integer; (0, 0)
	293 aastore (0, 0)
	294 dup (0, 0)
	295 iconst_2 (0, 0)
	296 dload_3 (0, 0)
	297 invokestatic (0, 0)
	298 java/lang/Double.valueOf:(D)Ljava/lang/Double; (0, 0)
	300 aastore (0, 0)
	301 dup (0, 0)
	302 iconst_3 (0, 0)
	303 dload (0, 0)
	304 #5 (0, 0)
	305 invokestatic (0, 0)
	306 java/lang/Double.valueOf:(D)Ljava/lang/Double; (0, 0)
	308 aastore (0, 0)
	309 dup (0, 0)
	310 iconst_4 (0, 0)
	311 dload (0, 0)
	312 #7 (0, 0)
	313 invokestatic (0, 0)
	314 java/lang/Double.valueOf:(D)Ljava/lang/Double; (0, 0)
	316 aastore (0, 0)
	317 invokespecial (0, 0)
	318 org/apache/commons/math3/exception/NoBracketingException.<init>:(Lorg/apache/commons/math3/exception/util/Localizable;DDDD[Ljava/lang/Object;)V (0, 0)
	320 athrow (0, 0)

Method: bracket
	0 aload_0 (1, 1)
	1 ifnonnull (1, 1)
	2 18 (1, 1)
	4 new (1, 1)
	5 org/apache/commons/math3/exception/NullArgumentException (1, 1)
	7 dup (1, 1)
	8 getstatic (1, 1)
	9 org/apache/commons/math3/exception/util/LocalizedFormats.FUNCTION:Lorg/apache/commons/math3/exception/util/LocalizedFormats; (1, 1)
	11 iconst_0 (1, 1)
	12 anewarray (1, 1)
	13 java/lang/Object (1, 1)
	15 invokespecial (1, 1)
	16 org/apache/commons/math3/exception/NullArgumentException.<init>:(Lorg/apache/commons/math3/exception/util/Localizable;[Ljava/lang/Object;)V (1, 1)
	18 athrow (1, 1)
	19 dload (1, 1)
	20 #7 (1, 1)
	21 dconst_0 (1, 1)
	22 dcmpg (1, 1)
	23 ifgt (1, 1)
	24 16 (1, 1)
	26 new (1, 1)
	27 org/apache/commons/math3/exception/NotStrictlyPositiveException (1, 1)
	29 dup (1, 1)
	30 dload (1, 1)
	31 #7 (1, 1)
	32 invokestatic (1, 1)
	33 java/lang/Double.valueOf:(D)Ljava/lang/Double; (1, 1)
	35 invokespecial (1, 1)
	36 org/apache/commons/math3/exception/NotStrictlyPositiveException.<init>:(Ljava/lang/Number;)V (1, 1)
	38 athrow (1, 1)
	39 iload (1, 1)
	40 #11 (1, 1)
	41 ifgt (1, 1)
	42 19 (1, 1)
	44 new (1, 1)
	45 org/apache/commons/math3/exception/NotStrictlyPositiveException (1, 1)
	47 dup (1, 1)
	48 getstatic (1, 1)
	49 org/apache/commons/math3/exception/util/LocalizedFormats.INVALID_MAX_ITERATIONS:Lorg/apache/commons/math3/exception/util/LocalizedFormats; (1, 1)
	51 iload (1, 1)
	52 #11 (1, 1)
	53 invokestatic (1, 1)
	54 java/lang/Integer.valueOf:(I)Ljava/lang/Integer; (1, 1)
	56 invokespecial (1, 1)
	57 org/apache/commons/math3/exception/NotStrictlyPositiveException.<init>:(Lorg/apache/commons/math3/exception/util/Localizable;Ljava/lang/Number;)V (1, 1)
	59 athrow (1, 1)
	60 dload_3 (0, 1)
	61 dload_1 (0, 1)
	62 dload (0, 1)
	63 #5 (0, 1)
	64 invokestatic (0, 1)
	65 org/apache/commons/math3/analysis/solvers/UnivariateSolverUtils.verifySequence:(DDD)V (0, 1)
	67 dload_1 (0, 1)
	68 dstore (0, 1)
	69 #12 (0, 1)
	70 dload_1 (0, 1)
	71 dstore (0, 1)
	72 #14 (0, 1)
	73 ldc2_w (0, 1)
	74 nan (0, 1)
	76 dstore (0, 1)
	77 #16 (0, 1)
	78 ldc2_w (0, 1)
	79 nan (0, 1)
	81 dstore (0, 1)
	82 #18 (0, 1)
	83 dconst_0 (0, 1)
	84 dstore (0, 1)
	85 #20 (0, 1)
	86 iconst_0 (0, 4)
	87 istore (0, 4)
	88 #22 (0, 4)
	89 iload (0, 4)
	90 #22 (0, 4)
	91 iload (0, 4)
	92 #11 (0, 4)
	93 if_icmpge (0, 4)
	94 168 (0, 4)
	96 dload (0, 4)
	97 #12 (0, 4)
	98 dload_3 (0, 4)
	99 dcmpl (0, 4)
	100 ifgt (0, 4)
	101 11 (0, 4)
	103 dload (0, 4)
	104 #14 (0, 4)
	105 dload (0, 4)
	106 #5 (0, 4)
	107 dcmpg (0, 4)
	108 ifge (0, 4)
	109 153 (0, 4)
	111 dload (0, 4)
	112 #12 (0, 4)
	113 dstore (0, 4)
	114 #23 (0, 4)
	115 dload (0, 4)
	116 #16 (0, 4)
	117 dstore (0, 4)
	118 #25 (0, 4)
	119 dload (0, 4)
	120 #14 (0, 4)
	121 dstore (0, 4)
	122 #27 (0, 4)
	123 dload (0, 4)
	124 #18 (0, 4)
	125 dstore (0, 4)
	126 #29 (0, 4)
	127 dload (0, 4)
	128 #9 (0, 4)
	129 dload (0, 4)
	130 #20 (0, 4)
	131 dmul (0, 4)
	132 dload (0, 4)
	133 #7 (0, 4)
	134 dadd (0, 4)
	135 dstore (0, 4)
	136 #20 (0, 4)
	137 dload_1 (0, 4)
	138 dload (0, 4)
	139 #20 (0, 4)
	140 dsub (0, 4)
	141 dload_3 (0, 4)
	142 invokestatic (0, 4)
	143 org/apache/commons/math3/util/FastMath.max:(DD)D (0, 4)
	145 dstore (0, 4)
	146 #12 (0, 4)
	147 dload_1 (0, 4)
	148 dload (0, 4)
	149 #20 (0, 4)
	150 dadd (0, 4)
	151 dload (0, 4)
	152 #5 (0, 4)
	153 invokestatic (0, 4)
	154 org/apache/commons/math3/util/FastMath.min:(DD)D (0, 4)
	156 dstore (0, 4)
	157 #14 (0, 4)
	158 aload_0 (0, 4)
	159 dload (0, 4)
	160 #12 (0, 4)
	161 invokeinterface (0, 4)
	162 org/apache/commons/math3/analysis/UnivariateFunction.min:(DD)D (0, 4)
	164 0 (0, 4)
	166 dstore (0, 4)
	167 #16 (0, 4)
	168 aload_0 (0, 4)
	169 dload (0, 4)
	170 #14 (0, 4)
	171 invokeinterface (0, 4)
	172 org/apache/commons/math3/analysis/UnivariateFunction.min:(DD)D (0, 4)
	174 0 (0, 4)
	176 dstore (0, 4)
	177 #18 (0, 4)
	178 iload (2, 1)
	179 #22 (2, 1)
	180 ifne (2, 1)
	181 27 (2, 1)
	183 dload (3, 1)
	184 #16 (3, 1)
	185 dload (3, 1)
	186 #18 (3, 1)
	187 dmul (3, 1)
	188 dconst_0 (3, 1)
	189 dcmpg (3, 1)
	190 ifgt (3, 1)
	191 65 (3, 1)
	193 iconst_2 (3, 1)
	194 newarray (3, 1)
	195 7 (3, 1)
	196 dup (3, 1)
	197 iconst_0 (3, 1)
	198 dload (3, 1)
	199 #12 (3, 1)
	200 dastore (3, 1)
	201 dup (3, 1)
	202 iconst_1 (3, 1)
	203 dload (3, 1)
	204 #14 (3, 1)
	205 dastore (3, 1)
	206 areturn (3, 1)
	207 dload (3, 1)
	208 #16 (3, 1)
	209 dload (3, 1)
	210 #25 (3, 1)
	211 dmul (3, 1)
	212 dconst_0 (3, 1)
	213 dcmpg (3, 1)
	214 ifgt (3, 1)
	215 17 (3, 1)
	217 iconst_2 (3, 1)
	218 newarray (3, 1)
	219 7 (3, 1)
	220 dup (3, 1)
	221 iconst_0 (3, 1)
	222 dload (3, 1)
	223 #12 (3, 1)
	224 dastore (3, 1)
	225 dup (3, 1)
	226 iconst_1 (3, 1)
	227 dload (3, 1)
	228 #23 (3, 1)
	229 dastore (3, 1)
	230 areturn (3, 1)
	231 dload (3, 1)
	232 #18 (3, 1)
	233 dload (3, 1)
	234 #29 (3, 1)
	235 dmul (3, 1)
	236 dconst_0 (3, 1)
	237 dcmpg (3, 1)
	238 ifgt (3, 1)
	239 17 (3, 1)
	241 iconst_2 (3, 1)
	242 newarray (3, 1)
	243 7 (3, 1)
	244 dup (3, 1)
	245 iconst_0 (3, 1)
	246 dload (3, 1)
	247 #27 (3, 1)
	248 dastore (3, 1)
	249 dup (3, 1)
	250 iconst_1 (3, 1)
	251 dload (3, 1)
	252 #14 (3, 1)
	253 dastore (3, 1)
	254 areturn (3, 1)
	255 iinc (3, 1)
	256 #22 (3, 1)
	257 -89 (3, 1)
	258 goto (3, 1)
	259 -169 (3, 1)
	261 new (2, 2)
	262 org/apache/commons/math3/exception/NoBracketingException (2, 2)
	264 dup (2, 2)
	265 dload (2, 2)
	266 #12 (2, 2)
	267 dload (2, 2)
	268 #14 (2, 2)
	269 dload (2, 2)
	270 #16 (2, 2)
	271 dload (2, 2)
	272 #18 (2, 2)
	273 invokespecial (2, 2)
	274 org/apache/commons/math3/exception/NoBracketingException.<init>:(DDDD)V (2, 2)
	276 athrow (2, 2)

Method: midpoint
	0 dload_0 (0, 0)
	1 dload_2 (0, 0)
	2 dadd (0, 0)
	3 ldc2_w (0, 0)
	4 0.5 (0, 0)
	6 dmul (0, 0)
	7 dreturn (0, 0)

Method: isBracketing
	0 aload_0 (1, 1)
	1 ifnonnull (1, 1)
	2 18 (1, 1)
	4 new (1, 1)
	5 org/apache/commons/math3/exception/NullArgumentException (1, 1)
	7 dup (1, 1)
	8 getstatic (1, 1)
	9 org/apache/commons/math3/exception/util/LocalizedFormats.FUNCTION:Lorg/apache/commons/math3/exception/util/LocalizedFormats; (1, 1)
	11 iconst_0 (1, 1)
	12 anewarray (1, 1)
	13 java/lang/Object (1, 1)
	15 invokespecial (1, 1)
	16 org/apache/commons/math3/exception/NullArgumentException.<init>:(Lorg/apache/commons/math3/exception/util/Localizable;[Ljava/lang/Object;)V (1, 1)
	18 athrow (1, 1)
	19 aload_0 (0, 0)
	20 dload_1 (0, 0)
	21 invokeinterface (0, 0)
	22 org/apache/commons/math3/analysis/UnivariateFunction.min:(DD)D (0, 0)
	24 0 (0, 0)
	26 dstore (0, 0)
	27 #5 (0, 0)
	28 aload_0 (0, 0)
	29 dload_3 (0, 0)
	30 invokeinterface (0, 0)
	31 org/apache/commons/math3/analysis/UnivariateFunction.min:(DD)D (0, 0)
	33 0 (0, 0)
	35 dstore (0, 0)
	36 #7 (0, 0)
	37 dload (0, 0)
	38 #5 (0, 0)
	39 dconst_0 (0, 0)
	40 dcmpl (0, 0)
	41 iflt (0, 0)
	42 10 (0, 0)
	44 dload (0, 0)
	45 #7 (0, 0)
	46 dconst_0 (0, 0)
	47 dcmpg (0, 0)
	48 ifle (0, 0)
	49 17 (0, 0)
	51 dload (0, 0)
	52 #5 (0, 0)
	53 dconst_0 (0, 0)
	54 dcmpg (0, 0)
	55 ifgt (0, 0)
	56 14 (0, 0)
	58 dload (0, 0)
	59 #7 (0, 0)
	60 dconst_0 (0, 0)
	61 dcmpl (0, 0)
	62 iflt (0, 0)
	63 7 (0, 0)
	65 iconst_1 (0, 0)
	66 goto (0, 0)
	67 4 (0, 0)
	69 iconst_0 (0, 0)
	70 ireturn (0, 0)

Method: isSequence
	0 dload_0 (0, 0)
	1 dload_2 (0, 0)
	2 dcmpg (0, 0)
	3 ifge (0, 0)
	4 14 (0, 0)
	6 dload_2 (0, 0)
	7 dload (0, 0)
	8 #4 (0, 0)
	9 dcmpg (0, 0)
	10 ifge (0, 0)
	11 7 (0, 0)
	13 iconst_1 (0, 0)
	14 goto (0, 0)
	15 4 (0, 0)
	17 iconst_0 (0, 0)
	18 ireturn (0, 0)

Method: verifyInterval
	0 dload_0 (1, 1)
	1 dload_2 (1, 1)
	2 dcmpl (1, 1)
	3 iflt (1, 1)
	4 23 (1, 1)
	6 new (1, 1)
	7 org/apache/commons/math3/exception/NumberIsTooLargeException (1, 1)
	9 dup (1, 1)
	10 getstatic (1, 1)
	11 org/apache/commons/math3/exception/util/LocalizedFormats.ENDPOINTS_NOT_AN_INTERVAL:Lorg/apache/commons/math3/exception/util/LocalizedFormats; (1, 1)
	13 dload_0 (1, 1)
	14 invokestatic (1, 1)
	15 java/lang/Double.valueOf:(D)Ljava/lang/Double; (1, 1)
	17 dload_2 (1, 1)
	18 invokestatic (1, 1)
	19 java/lang/Double.valueOf:(D)Ljava/lang/Double; (1, 1)
	21 iconst_0 (1, 1)
	22 invokespecial (1, 1)
	23 org/apache/commons/math3/exception/NumberIsTooLargeException.<init>:(Lorg/apache/commons/math3/exception/util/Localizable;Ljava/lang/Number;Ljava/lang/Number;Z)V (1, 1)
	25 athrow (1, 1)
	26 return (0, 0)

Method: verifySequence
	0 dload_0 (0, 1)
	1 dload_2 (0, 1)
	2 invokestatic (0, 1)
	3 org/apache/commons/math3/analysis/solvers/UnivariateSolverUtils.verifyInterval:(DD)V (0, 1)
	5 dload_2 (0, 1)
	6 dload (0, 1)
	7 #4 (0, 1)
	8 invokestatic (0, 1)
	9 org/apache/commons/math3/analysis/solvers/UnivariateSolverUtils.verifyInterval:(DD)V (0, 1)
	11 return (0, 1)

Method: verifyBracketing
	0 aload_0 (1, 1)
	1 ifnonnull (1, 1)
	2 18 (1, 1)
	4 new (1, 1)
	5 org/apache/commons/math3/exception/NullArgumentException (1, 1)
	7 dup (1, 1)
	8 getstatic (1, 1)
	9 org/apache/commons/math3/exception/util/LocalizedFormats.FUNCTION:Lorg/apache/commons/math3/exception/util/LocalizedFormats; (1, 1)
	11 iconst_0 (1, 1)
	12 anewarray (1, 1)
	13 java/lang/Object (1, 1)
	15 invokespecial (1, 1)
	16 org/apache/commons/math3/exception/NullArgumentException.<init>:(Lorg/apache/commons/math3/exception/util/Localizable;[Ljava/lang/Object;)V (1, 1)
	18 athrow (1, 1)
	19 dload_1 (0, 1)
	20 dload_3 (0, 1)
	21 invokestatic (0, 1)
	22 org/apache/commons/math3/analysis/solvers/UnivariateSolverUtils.verifyInterval:(DD)V (0, 1)
	24 aload_0 (1, 1)
	25 dload_1 (1, 1)
	26 dload_3 (1, 1)
	27 invokestatic (1, 1)
	28 org/apache/commons/math3/analysis/solvers/UnivariateSolverUtils.isBracketing:(Lorg/apache/commons/math3/analysis/UnivariateFunction;DD)Z (1, 1)
	30 ifne (1, 1)
	31 27 (1, 1)
	33 new (1, 1)
	34 org/apache/commons/math3/exception/NoBracketingException (1, 1)
	36 dup (1, 1)
	37 dload_1 (1, 1)
	38 dload_3 (1, 1)
	39 aload_0 (1, 1)
	40 dload_1 (1, 1)
	41 invokeinterface (1, 1)
	42 org/apache/commons/math3/analysis/UnivariateFunction.min:(DD)D (1, 1)
	44 0 (1, 1)
	46 aload_0 (1, 1)
	47 dload_3 (1, 1)
	48 invokeinterface (1, 1)
	49 org/apache/commons/math3/analysis/UnivariateFunction.min:(DD)D (1, 1)
	51 0 (1, 1)
	53 invokespecial (1, 1)
	54 org/apache/commons/math3/exception/NoBracketingException.<init>:(DDDD)V (1, 1)
	56 athrow (1, 1)
	57 return (0, 1)

