Method: <init>
	0 aload_0 (0, 0)
	1 aload_2 (0, 0)
	2 invokespecial (0, 0)
	3 org/apache/commons/math3/optim/nonlinear/scalar/GradientMultivariateOptimizer.<init>:(Lorg/apache/commons/math3/optim/ConvergenceChecker;)V (0, 0)
	5 aload_0 (0, 0)
	6 aload_1 (0, 0)
	7 putfield (0, 0)
	8 org/apache/commons/math3/optim/nonlinear/scalar/gradient/NonLinearConjugateGradientOptimizer.updateFormula:Lorg/apache/commons/math3/optim/nonlinear/scalar/gradient/NonLinearConjugateGradientOptimizer$Formula; (0, 0)
	10 aload_0 (0, 0)
	11 aload (0, 0)
	12 #9 (0, 0)
	13 putfield (0, 0)
	14 org/apache/commons/math3/optim/nonlinear/scalar/gradient/NonLinearConjugateGradientOptimizer.preconditioner:Lorg/apache/commons/math3/optim/nonlinear/scalar/gradient/Preconditioner; (0, 0)
	16 aload_0 (0, 0)
	17 new (0, 0)
	18 org/apache/commons/math3/optim/nonlinear/scalar/LineSearch (0, 0)
	20 dup (0, 0)
	21 aload_0 (0, 0)
	22 dload_3 (0, 0)
	23 dload (0, 0)
	24 #5 (0, 0)
	25 dload (0, 0)
	26 #7 (0, 0)
	27 invokespecial (0, 0)
	28 org/apache/commons/math3/optim/nonlinear/scalar/LineSearch.<init>:(Lorg/apache/commons/math3/optim/nonlinear/scalar/MultivariateOptimizer;DDD)V (0, 0)
	30 putfield (0, 0)
	31 org/apache/commons/math3/optim/nonlinear/scalar/gradient/NonLinearConjugateGradientOptimizer.line:Lorg/apache/commons/math3/optim/nonlinear/scalar/LineSearch; (0, 0)
	33 return (0, 0)

Method: optimize
	0 aload_0 (0, 0)
	1 aload_1 (0, 0)
	2 invokevirtual (0, 0)
	3 org/apache/commons/math3/optim/nonlinear/scalar/gradient/NonLinearConjugateGradientOptimizer.optimize:([Lorg/apache/commons/math3/optim/OptimizationData;)Lorg/apache/commons/math3/optim/PointValuePair; (0, 0)
	5 areturn (0, 0)

Method: doOptimize
	0 aload_0 (0, 0)
	1 invokevirtual (0, 0)
	2 org/apache/commons/math3/optim/nonlinear/scalar/gradient/NonLinearConjugateGradientOptimizer.doOptimize:()Lorg/apache/commons/math3/optim/PointValuePair; (0, 0)
	4 areturn (0, 0)

Method: parseOptimizationData
	0 aload_0 (0, 0)
	1 aload_1 (0, 0)
	2 invokespecial (0, 0)
	3 org/apache/commons/math3/optim/nonlinear/scalar/GradientMultivariateOptimizer.parseOptimizationData:([Lorg/apache/commons/math3/optim/OptimizationData;)V (0, 0)
	5 aload_0 (0, 0)
	6 invokespecial (0, 0)
	7 org/apache/commons/math3/optim/nonlinear/scalar/gradient/NonLinearConjugateGradientOptimizer.checkParameters:()V (0, 0)
	9 return (0, 0)

Method: checkParameters
	0 aload_0 (0, 1)
	1 invokevirtual (0, 1)
	2 org/apache/commons/math3/optim/nonlinear/scalar/gradient/NonLinearConjugateGradientOptimizer.getLowerBound:()[D (0, 1)
	4 ifnonnull (0, 1)
	5 10 (0, 1)
	7 aload_0 (0, 1)
	8 invokevirtual (0, 1)
	9 org/apache/commons/math3/optim/nonlinear/scalar/gradient/NonLinearConjugateGradientOptimizer.getUpperBound:()[D (0, 1)
	11 ifnull (0, 1)
	12 18 (0, 1)
	14 new (0, 1)
	15 org/apache/commons/math3/exception/MathUnsupportedOperationException (0, 1)
	17 dup (0, 1)
	18 getstatic (0, 1)
	19 org/apache/commons/math3/exception/util/LocalizedFormats.CONSTRAINT:Lorg/apache/commons/math3/exception/util/LocalizedFormats; (0, 1)
	21 iconst_0 (0, 1)
	22 anewarray (0, 1)
	23 java/lang/Object (0, 1)
	25 invokespecial (0, 1)
	26 org/apache/commons/math3/exception/MathUnsupportedOperationException.<init>:(Lorg/apache/commons/math3/exception/util/Localizable;[Ljava/lang/Object;)V (0, 1)
	28 athrow (0, 1)
	29 return (0, 1)

