Method: <init>
	0 aload_0 (0, 0)
	1 iload_1 (0, 0)
	2 ldc2_w (0, 0)
	3 1e-06 (0, 0)
	5 ldc2_w (0, 0)
	6 1e-15 (0, 0)
	8 iload_2 (0, 0)
	9 iload_3 (0, 0)
	10 invokespecial (0, 0)
	11 org/apache/commons/math3/analysis/integration/IterativeLegendreGaussIntegrator.<init>:(IDDII)V (0, 0)
	13 return (0, 0)

Method: doIntegrate
	0 aload_0 (0, 0)
	1 iconst_1 (0, 0)
	2 invokespecial (0, 0)
	3 org/apache/commons/math3/analysis/integration/IterativeLegendreGaussIntegrator.stage:(I)D (0, 0)
	5 dstore_1 (0, 0)
	6 iconst_2 (0, 0)
	7 istore_3 (0, 0)
	8 aload_0 (1, 3)
	9 iload_3 (1, 3)
	10 invokespecial (1, 3)
	11 org/apache/commons/math3/analysis/integration/IterativeLegendreGaussIntegrator.stage:(I)D (1, 3)
	13 dstore (1, 3)
	14 #4 (1, 3)
	15 dload (1, 3)
	16 #4 (1, 3)
	17 dload_1 (1, 3)
	18 dsub (1, 3)
	19 invokestatic (1, 3)
	20 org/apache/commons/math3/util/FastMath.abs:(D)D (1, 3)
	22 dstore (1, 3)
	23 #6 (1, 3)
	24 aload_0 (1, 3)
	25 invokevirtual (1, 3)
	26 org/apache/commons/math3/analysis/integration/IterativeLegendreGaussIntegrator.getAbsoluteAccuracy:()D (1, 3)
	28 aload_0 (1, 3)
	29 invokevirtual (1, 3)
	30 org/apache/commons/math3/analysis/integration/IterativeLegendreGaussIntegrator.getRelativeAccuracy:()D (1, 3)
	32 dload_1 (1, 3)
	33 invokestatic (1, 3)
	34 org/apache/commons/math3/util/FastMath.abs:(D)D (1, 3)
	36 dload (1, 3)
	37 #4 (1, 3)
	38 invokestatic (1, 3)
	39 org/apache/commons/math3/util/FastMath.abs:(D)D (1, 3)
	41 dadd (1, 3)
	42 dmul (1, 3)
	43 ldc2_w (1, 3)
	44 0.5 (1, 3)
	46 dmul (1, 3)
	47 invokestatic (1, 3)
	48 org/apache/commons/math3/util/FastMath.max:(DD)D (1, 3)
	50 dstore (1, 3)
	51 #8 (1, 3)
	52 aload_0 (2, 1)
	53 invokevirtual (2, 1)
	54 org/apache/commons/math3/analysis/integration/IterativeLegendreGaussIntegrator.getIterations:()I (2, 1)
	56 iconst_1 (2, 1)
	57 iadd (2, 1)
	58 aload_0 (2, 1)
	59 invokevirtual (2, 1)
	60 org/apache/commons/math3/analysis/integration/IterativeLegendreGaussIntegrator.getMinimalIterationCount:()I (2, 1)
	62 if_icmplt (2, 1)
	63 14 (2, 1)
	65 dload (2, 1)
	66 #6 (2, 1)
	67 dload (2, 1)
	68 #8 (2, 1)
	69 dcmpg (2, 1)
	70 ifgt (2, 1)
	71 6 (2, 1)
	73 dload (2, 1)
	74 #4 (2, 1)
	75 dreturn (2, 1)
	76 ldc2_w (2, 1)
	77 4.0 (2, 1)
	79 dload (2, 1)
	80 #6 (2, 1)
	81 dload (2, 1)
	82 #8 (2, 1)
	83 ddiv (2, 1)
	84 ldc2_w (2, 1)
	85 0.5 (2, 1)
	87 aload_0 (2, 1)
	88 getfield (2, 1)
	89 org/apache/commons/math3/analysis/integration/IterativeLegendreGaussIntegrator.numberOfPoints:I (2, 1)
	91 i2d (2, 1)
	92 ddiv (2, 1)
	93 invokestatic (2, 1)
	94 org/apache/commons/math3/util/FastMath.pow:(DD)D (2, 1)
	96 invokestatic (2, 1)
	97 org/apache/commons/math3/util/FastMath.min:(DD)D (2, 1)
	99 dstore (2, 1)
	100 #10 (2, 1)
	101 dload (2, 1)
	102 #10 (2, 1)
	103 iload_3 (2, 1)
	104 i2d (2, 1)
	105 dmul (2, 1)
	106 d2i (2, 1)
	107 iload_3 (2, 1)
	108 iconst_1 (2, 1)
	109 iadd (2, 1)
	110 invokestatic (2, 1)
	111 org/apache/commons/math3/util/FastMath.max:(II)I (2, 1)
	113 istore_3 (2, 1)
	114 dload (2, 1)
	115 #4 (2, 1)
	116 dstore_1 (2, 1)
	117 aload_0 (2, 1)
	118 invokevirtual (2, 1)
	119 org/apache/commons/math3/analysis/integration/IterativeLegendreGaussIntegrator.incrementCount:()V (2, 1)
	121 goto (0, 0)
	122 -113 (0, 0)

Method: stage
	0 new (0, 0)
	1 org/apache/commons/math3/analysis/integration/IterativeLegendreGaussIntegrator$1 (0, 0)
	3 dup (0, 0)
	4 aload_0 (0, 0)
	5 invokespecial (0, 0)
	6 org/apache/commons/math3/analysis/integration/IterativeLegendreGaussIntegrator$1.<init>:(Lorg/apache/commons/math3/analysis/integration/IterativeLegendreGaussIntegrator;)V (0, 0)
	8 astore_2 (0, 0)
	9 aload_0 (0, 0)
	10 invokevirtual (0, 0)
	11 org/apache/commons/math3/analysis/integration/IterativeLegendreGaussIntegrator.getMin:()D (0, 0)
	13 dstore_3 (0, 0)
	14 aload_0 (0, 0)
	15 invokevirtual (0, 0)
	16 org/apache/commons/math3/analysis/integration/IterativeLegendreGaussIntegrator.getMax:()D (0, 0)
	18 dstore (0, 0)
	19 #5 (0, 0)
	20 dload (0, 0)
	21 #5 (0, 0)
	22 dload_3 (0, 0)
	23 dsub (0, 0)
	24 iload_1 (0, 0)
	25 i2d (0, 0)
	26 ddiv (0, 0)
	27 dstore (0, 0)
	28 #7 (0, 0)
	29 dconst_0 (0, 0)
	30 dstore (0, 0)
	31 #9 (0, 0)
	32 iconst_0 (1, 4)
	33 istore (1, 4)
	34 #11 (1, 4)
	35 iload (1, 4)
	36 #11 (1, 4)
	37 iload_1 (1, 4)
	38 if_icmpge (1, 4)
	39 53 (1, 4)
	41 dload_3 (1, 4)
	42 iload (1, 4)
	43 #11 (1, 4)
	44 i2d (1, 4)
	45 dload (1, 4)
	46 #7 (1, 4)
	47 dmul (1, 4)
	48 dadd (1, 4)
	49 dstore (1, 4)
	50 #12 (1, 4)
	51 dload (1, 4)
	52 #12 (1, 4)
	53 dload (1, 4)
	54 #7 (1, 4)
	55 dadd (1, 4)
	56 dstore (1, 4)
	57 #14 (1, 4)
	58 getstatic (1, 4)
	59 org/apache/commons/math3/analysis/integration/IterativeLegendreGaussIntegrator.FACTORY:Lorg/apache/commons/math3/analysis/integration/gauss/GaussIntegratorFactory; (1, 4)
	61 aload_0 (1, 4)
	62 getfield (1, 4)
	63 org/apache/commons/math3/analysis/integration/IterativeLegendreGaussIntegrator.numberOfPoints:I (1, 4)
	65 dload (1, 4)
	66 #12 (1, 4)
	67 dload (1, 4)
	68 #14 (1, 4)
	69 invokevirtual (1, 4)
	70 org/apache/commons/math3/analysis/integration/gauss/GaussIntegratorFactory.legendreHighPrecision:(IDD)Lorg/apache/commons/math3/analysis/integration/gauss/GaussIntegrator; (1, 4)
	72 astore (1, 4)
	73 #16 (1, 4)
	74 dload (1, 4)
	75 #9 (1, 4)
	76 aload (1, 4)
	77 #16 (1, 4)
	78 aload_2 (1, 4)
	79 invokevirtual (1, 4)
	80 org/apache/commons/math3/analysis/integration/gauss/GaussIntegrator.integrate:(Lorg/apache/commons/math3/analysis/UnivariateFunction;)D (1, 4)
	82 dadd (1, 4)
	83 dstore (1, 4)
	84 #9 (1, 4)
	85 iinc (1, 4)
	86 #11 (1, 4)
	87 -89 (1, 4)
	88 goto (1, 4)
	89 -53 (1, 4)
	91 dload (0, 0)
	92 #9 (0, 0)
	93 dreturn (0, 0)

Method: <clinit>
	0 new (0, 0)
	1 org/apache/commons/math3/analysis/integration/gauss/GaussIntegratorFactory (0, 0)
	3 dup (0, 0)
	4 invokespecial (0, 0)
	5 org/apache/commons/math3/analysis/integration/gauss/GaussIntegratorFactory.<init>:()V (0, 0)
	7 putstatic (0, 0)
	8 org/apache/commons/math3/analysis/integration/IterativeLegendreGaussIntegrator.FACTORY:Lorg/apache/commons/math3/analysis/integration/gauss/GaussIntegratorFactory; (0, 0)
	10 return (0, 0)

