Method: <init>
	0 aload_0 (0, 0)
	1 iload_1 (0, 0)
	2 ldc2_w (0, 0)
	3 1e-06 (0, 0)
	5 ldc2_w (0, 0)
	6 1e-15 (0, 0)
	8 iload_2 (0, 0)
	9 iload_3 (0, 0)
	10 invokespecial (0, 0)
	11 org/apache/commons/math3/analysis/integration/LegendreGaussIntegrator.<init>:(IDDII)V (0, 0)
	13 return (0, 0)

Method: doIntegrate
	0 aload_0 (0, 0)
	1 iconst_1 (0, 0)
	2 invokespecial (0, 0)
	3 org/apache/commons/math3/analysis/integration/LegendreGaussIntegrator.stage:(I)D (0, 0)
	5 dstore_1 (0, 0)
	6 iconst_2 (0, 0)
	7 istore_3 (0, 0)
	8 aload_0 (1, 3)
	9 iload_3 (1, 3)
	10 invokespecial (1, 3)
	11 org/apache/commons/math3/analysis/integration/LegendreGaussIntegrator.stage:(I)D (1, 3)
	13 dstore (1, 3)
	14 #4 (1, 3)
	15 dload (1, 3)
	16 #4 (1, 3)
	17 dload_1 (1, 3)
	18 dsub (1, 3)
	19 invokestatic (1, 3)
	20 org/apache/commons/math3/util/FastMath.abs:(D)D (1, 3)
	22 dstore (1, 3)
	23 #6 (1, 3)
	24 aload_0 (1, 3)
	25 invokevirtual (1, 3)
	26 org/apache/commons/math3/analysis/integration/LegendreGaussIntegrator.getAbsoluteAccuracy:()D (1, 3)
	28 aload_0 (1, 3)
	29 invokevirtual (1, 3)
	30 org/apache/commons/math3/analysis/integration/LegendreGaussIntegrator.getRelativeAccuracy:()D (1, 3)
	32 dload_1 (1, 3)
	33 invokestatic (1, 3)
	34 org/apache/commons/math3/util/FastMath.abs:(D)D (1, 3)
	36 dload (1, 3)
	37 #4 (1, 3)
	38 invokestatic (1, 3)
	39 org/apache/commons/math3/util/FastMath.abs:(D)D (1, 3)
	41 dadd (1, 3)
	42 dmul (1, 3)
	43 ldc2_w (1, 3)
	44 0.5 (1, 3)
	46 dmul (1, 3)
	47 invokestatic (1, 3)
	48 org/apache/commons/math3/util/FastMath.max:(DD)D (1, 3)
	50 dstore (1, 3)
	51 #8 (1, 3)
	52 aload_0 (2, 1)
	53 invokevirtual (2, 1)
	54 org/apache/commons/math3/analysis/integration/LegendreGaussIntegrator.getIterations:()I (2, 1)
	56 iconst_1 (2, 1)
	57 iadd (2, 1)
	58 aload_0 (2, 1)
	59 invokevirtual (2, 1)
	60 org/apache/commons/math3/analysis/integration/LegendreGaussIntegrator.getMinimalIterationCount:()I (2, 1)
	62 if_icmplt (2, 1)
	63 14 (2, 1)
	65 dload (2, 1)
	66 #6 (2, 1)
	67 dload (2, 1)
	68 #8 (2, 1)
	69 dcmpg (2, 1)
	70 ifgt (2, 1)
	71 6 (2, 1)
	73 dload (2, 1)
	74 #4 (2, 1)
	75 dreturn (2, 1)
	76 ldc2_w (1, 3)
	77 4.0 (1, 3)
	79 dload (1, 3)
	80 #6 (1, 3)
	81 dload (1, 3)
	82 #8 (1, 3)
	83 ddiv (1, 3)
	84 ldc2_w (1, 3)
	85 0.5 (1, 3)
	87 aload_0 (1, 3)
	88 getfield (1, 3)
	89 org/apache/commons/math3/analysis/integration/LegendreGaussIntegrator.abscissas:[D (1, 3)
	91 arraylength (1, 3)
	92 i2d (1, 3)
	93 ddiv (1, 3)
	94 invokestatic (1, 3)
	95 org/apache/commons/math3/util/FastMath.pow:(DD)D (1, 3)
	97 invokestatic (1, 3)
	98 org/apache/commons/math3/util/FastMath.min:(DD)D (1, 3)
	100 dstore (1, 3)
	101 #10 (1, 3)
	102 dload (1, 3)
	103 #10 (1, 3)
	104 iload_3 (1, 3)
	105 i2d (1, 3)
	106 dmul (1, 3)
	107 d2i (1, 3)
	108 iload_3 (1, 3)
	109 iconst_1 (1, 3)
	110 iadd (1, 3)
	111 invokestatic (1, 3)
	112 org/apache/commons/math3/util/FastMath.max:(II)I (1, 3)
	114 istore_3 (1, 3)
	115 dload (1, 3)
	116 #4 (1, 3)
	117 dstore_1 (1, 3)
	118 aload_0 (1, 3)
	119 invokevirtual (1, 3)
	120 org/apache/commons/math3/analysis/integration/LegendreGaussIntegrator.incrementCount:()V (1, 3)
	122 goto (0, 0)
	123 -114 (0, 0)

Method: stage
	0 aload_0 (0, 0)
	1 invokevirtual (0, 0)
	2 org/apache/commons/math3/analysis/integration/LegendreGaussIntegrator.getMax:()D (0, 0)
	4 aload_0 (0, 0)
	5 invokevirtual (0, 0)
	6 org/apache/commons/math3/analysis/integration/LegendreGaussIntegrator.getMin:()D (0, 0)
	8 dsub (0, 0)
	9 iload_1 (0, 0)
	10 i2d (0, 0)
	11 ddiv (0, 0)
	12 dstore_2 (0, 0)
	13 dload_2 (0, 0)
	14 ldc2_w (0, 0)
	15 2.0 (0, 0)
	17 ddiv (0, 0)
	18 dstore (0, 0)
	19 #4 (0, 0)
	20 aload_0 (0, 0)
	21 invokevirtual (0, 0)
	22 org/apache/commons/math3/analysis/integration/LegendreGaussIntegrator.getMin:()D (0, 0)
	24 dload (0, 0)
	25 #4 (0, 0)
	26 dadd (0, 0)
	27 dstore (0, 0)
	28 #6 (0, 0)
	29 dconst_0 (0, 0)
	30 dstore (0, 0)
	31 #8 (0, 0)
	32 iconst_0 (1, 4)
	33 istore (1, 4)
	34 #10 (1, 4)
	35 iload (1, 4)
	36 #10 (1, 4)
	37 iload_1 (1, 4)
	38 if_icmpge (1, 4)
	39 64 (1, 4)
	41 iconst_0 (2, 4)
	42 istore (2, 4)
	43 #11 (2, 4)
	44 iload (2, 4)
	45 #11 (2, 4)
	46 aload_0 (2, 4)
	47 getfield (2, 4)
	48 org/apache/commons/math3/analysis/integration/LegendreGaussIntegrator.abscissas:[D (2, 4)
	50 arraylength (2, 4)
	51 if_icmpge (2, 4)
	52 39 (2, 4)
	54 dload (2, 4)
	55 #8 (2, 4)
	56 aload_0 (2, 4)
	57 getfield (2, 4)
	58 org/apache/commons/math3/analysis/integration/LegendreGaussIntegrator.weights:[D (2, 4)
	60 iload (2, 4)
	61 #11 (2, 4)
	62 daload (2, 4)
	63 aload_0 (2, 4)
	64 dload (2, 4)
	65 #6 (2, 4)
	66 dload (2, 4)
	67 #4 (2, 4)
	68 aload_0 (2, 4)
	69 getfield (2, 4)
	70 org/apache/commons/math3/analysis/integration/LegendreGaussIntegrator.abscissas:[D (2, 4)
	72 iload (2, 4)
	73 #11 (2, 4)
	74 daload (2, 4)
	75 dmul (2, 4)
	76 dadd (2, 4)
	77 invokevirtual (2, 4)
	78 org/apache/commons/math3/analysis/integration/LegendreGaussIntegrator.computeObjectiveValue:(D)D (2, 4)
	80 dmul (2, 4)
	81 dadd (2, 4)
	82 dstore (2, 4)
	83 #8 (2, 4)
	84 iinc (2, 4)
	85 #11 (2, 4)
	86 -89 (2, 4)
	87 goto (2, 4)
	88 -43 (2, 4)
	90 dload (1, 4)
	91 #6 (1, 4)
	92 dload_2 (1, 4)
	93 dadd (1, 4)
	94 dstore (1, 4)
	95 #6 (1, 4)
	96 iinc (1, 4)
	97 #10 (1, 4)
	98 -89 (1, 4)
	99 goto (1, 4)
	100 -64 (1, 4)
	102 dload (0, 0)
	103 #4 (0, 0)
	104 dload (0, 0)
	105 #8 (0, 0)
	106 dmul (0, 0)
	107 dreturn (0, 0)

Method: <clinit>
	0 iconst_2 (0, 0)
	1 newarray (0, 0)
	2 7 (0, 0)
	3 dup (0, 0)
	4 iconst_0 (0, 0)
	5 ldc2_w (0, 0)
	6 -1.0 (0, 0)
	8 ldc2_w (0, 0)
	9 3.0 (0, 0)
	11 invokestatic (0, 0)
	12 org/apache/commons/math3/util/FastMath.sqrt:(D)D (0, 0)
	14 ddiv (0, 0)
	15 dastore (0, 0)
	16 dup (0, 0)
	17 iconst_1 (0, 0)
	18 dconst_1 (0, 0)
	19 ldc2_w (0, 0)
	20 3.0 (0, 0)
	22 invokestatic (0, 0)
	23 org/apache/commons/math3/util/FastMath.sqrt:(D)D (0, 0)
	25 ddiv (0, 0)
	26 dastore (0, 0)
	27 putstatic (0, 0)
	28 org/apache/commons/math3/analysis/integration/LegendreGaussIntegrator.ABSCISSAS_2:[D (0, 0)
	30 iconst_2 (1, 4)
	31 newarray (1, 4)
	32 7 (1, 4)
	33 dup (1, 4)
	34 iconst_0 (1, 4)
	35 dconst_1 (1, 4)
	36 dastore (1, 4)
	37 dup (1, 4)
	38 iconst_1 (1, 4)
	39 dconst_1 (1, 4)
	40 dastore (1, 4)
	41 putstatic (1, 4)
	42 org/apache/commons/math3/analysis/integration/LegendreGaussIntegrator.WEIGHTS_2:[D (1, 4)
	44 iconst_3 (2, 4)
	45 newarray (2, 4)
	46 7 (2, 4)
	47 dup (2, 4)
	48 iconst_0 (2, 4)
	49 ldc2_w (2, 4)
	50 0.6 (2, 4)
	52 invokestatic (2, 4)
	53 org/apache/commons/math3/util/FastMath.sqrt:(D)D (2, 4)
	55 dneg (2, 4)
	56 dastore (2, 4)
	57 dup (2, 4)
	58 iconst_1 (2, 4)
	59 dconst_0 (2, 4)
	60 dastore (2, 4)
	61 dup (2, 4)
	62 iconst_2 (2, 4)
	63 ldc2_w (2, 4)
	64 0.6 (2, 4)
	66 invokestatic (2, 4)
	67 org/apache/commons/math3/util/FastMath.sqrt:(D)D (2, 4)
	69 dastore (2, 4)
	70 putstatic (2, 4)
	71 org/apache/commons/math3/analysis/integration/LegendreGaussIntegrator.ABSCISSAS_3:[D (2, 4)
	73 iconst_3 (3, 4)
	74 newarray (3, 4)
	75 7 (3, 4)
	76 dup (3, 4)
	77 iconst_0 (3, 4)
	78 ldc2_w (3, 4)
	79 0.5555555555555556 (3, 4)
	81 dastore (3, 4)
	82 dup (3, 4)
	83 iconst_1 (3, 4)
	84 ldc2_w (3, 4)
	85 0.8888888888888888 (3, 4)
	87 dastore (3, 4)
	88 dup (3, 4)
	89 iconst_2 (3, 4)
	90 ldc2_w (3, 4)
	91 0.5555555555555556 (3, 4)
	93 dastore (3, 4)
	94 putstatic (3, 4)
	95 org/apache/commons/math3/analysis/integration/LegendreGaussIntegrator.WEIGHTS_3:[D (3, 4)
	97 iconst_4 (4, 4)
	98 newarray (4, 4)
	99 7 (4, 4)
	100 dup (4, 4)
	101 iconst_0 (4, 4)
	102 ldc2_w (4, 4)
	103 15.0 (4, 4)
	105 ldc2_w (4, 4)
	106 2.0 (4, 4)
	108 ldc2_w (4, 4)
	109 30.0 (4, 4)
	111 invokestatic (4, 4)
	112 org/apache/commons/math3/util/FastMath.sqrt:(D)D (4, 4)
	114 dmul (4, 4)
	115 dadd (4, 4)
	116 ldc2_w (4, 4)
	117 35.0 (4, 4)
	119 ddiv (4, 4)
	120 invokestatic (4, 4)
	121 org/apache/commons/math3/util/FastMath.sqrt:(D)D (4, 4)
	123 dneg (4, 4)
	124 dastore (4, 4)
	125 dup (4, 4)
	126 iconst_1 (4, 4)
	127 ldc2_w (4, 4)
	128 15.0 (4, 4)
	130 ldc2_w (4, 4)
	131 2.0 (4, 4)
	133 ldc2_w (4, 4)
	134 30.0 (4, 4)
	136 invokestatic (4, 4)
	137 org/apache/commons/math3/util/FastMath.sqrt:(D)D (4, 4)
	139 dmul (4, 4)
	140 dsub (4, 4)
	141 ldc2_w (4, 4)
	142 35.0 (4, 4)
	144 ddiv (4, 4)
	145 invokestatic (4, 4)
	146 org/apache/commons/math3/util/FastMath.sqrt:(D)D (4, 4)
	148 dneg (4, 4)
	149 dastore (4, 4)
	150 dup (4, 4)
	151 iconst_2 (4, 4)
	152 ldc2_w (4, 4)
	153 15.0 (4, 4)
	155 ldc2_w (4, 4)
	156 2.0 (4, 4)
	158 ldc2_w (4, 4)
	159 30.0 (4, 4)
	161 invokestatic (4, 4)
	162 org/apache/commons/math3/util/FastMath.sqrt:(D)D (4, 4)
	164 dmul (4, 4)
	165 dsub (4, 4)
	166 ldc2_w (4, 4)
	167 35.0 (4, 4)
	169 ddiv (4, 4)
	170 invokestatic (4, 4)
	171 org/apache/commons/math3/util/FastMath.sqrt:(D)D (4, 4)
	173 dastore (4, 4)
	174 dup (4, 4)
	175 iconst_3 (4, 4)
	176 ldc2_w (4, 4)
	177 15.0 (4, 4)
	179 ldc2_w (4, 4)
	180 2.0 (4, 4)
	182 ldc2_w (4, 4)
	183 30.0 (4, 4)
	185 invokestatic (4, 4)
	186 org/apache/commons/math3/util/FastMath.sqrt:(D)D (4, 4)
	188 dmul (4, 4)
	189 dadd (4, 4)
	190 ldc2_w (4, 4)
	191 35.0 (4, 4)
	193 ddiv (4, 4)
	194 invokestatic (4, 4)
	195 org/apache/commons/math3/util/FastMath.sqrt:(D)D (4, 4)
	197 dastore (4, 4)
	198 putstatic (4, 4)
	199 org/apache/commons/math3/analysis/integration/LegendreGaussIntegrator.ABSCISSAS_4:[D (4, 4)
	201 iconst_4 (5, 4)
	202 newarray (5, 4)
	203 7 (5, 4)
	204 dup (5, 4)
	205 iconst_0 (5, 4)
	206 ldc2_w (5, 4)
	207 90.0 (5, 4)
	209 ldc2_w (5, 4)
	210 5.0 (5, 4)
	212 ldc2_w (5, 4)
	213 30.0 (5, 4)
	215 invokestatic (5, 4)
	216 org/apache/commons/math3/util/FastMath.sqrt:(D)D (5, 4)
	218 dmul (5, 4)
	219 dsub (5, 4)
	220 ldc2_w (5, 4)
	221 180.0 (5, 4)
	223 ddiv (5, 4)
	224 dastore (5, 4)
	225 dup (5, 4)
	226 iconst_1 (5, 4)
	227 ldc2_w (5, 4)
	228 90.0 (5, 4)
	230 ldc2_w (5, 4)
	231 5.0 (5, 4)
	233 ldc2_w (5, 4)
	234 30.0 (5, 4)
	236 invokestatic (5, 4)
	237 org/apache/commons/math3/util/FastMath.sqrt:(D)D (5, 4)
	239 dmul (5, 4)
	240 dadd (5, 4)
	241 ldc2_w (5, 4)
	242 180.0 (5, 4)
	244 ddiv (5, 4)
	245 dastore (5, 4)
	246 dup (5, 4)
	247 iconst_2 (5, 4)
	248 ldc2_w (5, 4)
	249 90.0 (5, 4)
	251 ldc2_w (5, 4)
	252 5.0 (5, 4)
	254 ldc2_w (5, 4)
	255 30.0 (5, 4)
	257 invokestatic (5, 4)
	258 org/apache/commons/math3/util/FastMath.sqrt:(D)D (5, 4)
	260 dmul (5, 4)
	261 dadd (5, 4)
	262 ldc2_w (5, 4)
	263 180.0 (5, 4)
	265 ddiv (5, 4)
	266 dastore (5, 4)
	267 dup (5, 4)
	268 iconst_3 (5, 4)
	269 ldc2_w (5, 4)
	270 90.0 (5, 4)
	272 ldc2_w (5, 4)
	273 5.0 (5, 4)
	275 ldc2_w (5, 4)
	276 30.0 (5, 4)
	278 invokestatic (5, 4)
	279 org/apache/commons/math3/util/FastMath.sqrt:(D)D (5, 4)
	281 dmul (5, 4)
	282 dsub (5, 4)
	283 ldc2_w (5, 4)
	284 180.0 (5, 4)
	286 ddiv (5, 4)
	287 dastore (5, 4)
	288 putstatic (5, 4)
	289 org/apache/commons/math3/analysis/integration/LegendreGaussIntegrator.WEIGHTS_4:[D (5, 4)
	291 iconst_5 (6, 4)
	292 newarray (6, 4)
	293 7 (6, 4)
	294 dup (6, 4)
	295 iconst_0 (6, 4)
	296 ldc2_w (6, 4)
	297 35.0 (6, 4)
	299 ldc2_w (6, 4)
	300 2.0 (6, 4)
	302 ldc2_w (6, 4)
	303 70.0 (6, 4)
	305 invokestatic (6, 4)
	306 org/apache/commons/math3/util/FastMath.sqrt:(D)D (6, 4)
	308 dmul (6, 4)
	309 dadd (6, 4)
	310 ldc2_w (6, 4)
	311 63.0 (6, 4)
	313 ddiv (6, 4)
	314 invokestatic (6, 4)
	315 org/apache/commons/math3/util/FastMath.sqrt:(D)D (6, 4)
	317 dneg (6, 4)
	318 dastore (6, 4)
	319 dup (6, 4)
	320 iconst_1 (6, 4)
	321 ldc2_w (6, 4)
	322 35.0 (6, 4)
	324 ldc2_w (6, 4)
	325 2.0 (6, 4)
	327 ldc2_w (6, 4)
	328 70.0 (6, 4)
	330 invokestatic (6, 4)
	331 org/apache/commons/math3/util/FastMath.sqrt:(D)D (6, 4)
	333 dmul (6, 4)
	334 dsub (6, 4)
	335 ldc2_w (6, 4)
	336 63.0 (6, 4)
	338 ddiv (6, 4)
	339 invokestatic (6, 4)
	340 org/apache/commons/math3/util/FastMath.sqrt:(D)D (6, 4)
	342 dneg (6, 4)
	343 dastore (6, 4)
	344 dup (6, 4)
	345 iconst_2 (6, 4)
	346 dconst_0 (6, 4)
	347 dastore (6, 4)
	348 dup (6, 4)
	349 iconst_3 (6, 4)
	350 ldc2_w (6, 4)
	351 35.0 (6, 4)
	353 ldc2_w (6, 4)
	354 2.0 (6, 4)
	356 ldc2_w (6, 4)
	357 70.0 (6, 4)
	359 invokestatic (6, 4)
	360 org/apache/commons/math3/util/FastMath.sqrt:(D)D (6, 4)
	362 dmul (6, 4)
	363 dsub (6, 4)
	364 ldc2_w (6, 4)
	365 63.0 (6, 4)
	367 ddiv (6, 4)
	368 invokestatic (6, 4)
	369 org/apache/commons/math3/util/FastMath.sqrt:(D)D (6, 4)
	371 dastore (6, 4)
	372 dup (6, 4)
	373 iconst_4 (6, 4)
	374 ldc2_w (6, 4)
	375 35.0 (6, 4)
	377 ldc2_w (6, 4)
	378 2.0 (6, 4)
	380 ldc2_w (6, 4)
	381 70.0 (6, 4)
	383 invokestatic (6, 4)
	384 org/apache/commons/math3/util/FastMath.sqrt:(D)D (6, 4)
	386 dmul (6, 4)
	387 dadd (6, 4)
	388 ldc2_w (6, 4)
	389 63.0 (6, 4)
	391 ddiv (6, 4)
	392 invokestatic (6, 4)
	393 org/apache/commons/math3/util/FastMath.sqrt:(D)D (6, 4)
	395 dastore (6, 4)
	396 putstatic (6, 4)
	397 org/apache/commons/math3/analysis/integration/LegendreGaussIntegrator.ABSCISSAS_5:[D (6, 4)
	399 iconst_5 (7, 4)
	400 newarray (7, 4)
	401 7 (7, 4)
	402 dup (7, 4)
	403 iconst_0 (7, 4)
	404 ldc2_w (7, 4)
	405 322.0 (7, 4)
	407 ldc2_w (7, 4)
	408 13.0 (7, 4)
	410 ldc2_w (7, 4)
	411 70.0 (7, 4)
	413 invokestatic (7, 4)
	414 org/apache/commons/math3/util/FastMath.sqrt:(D)D (7, 4)
	416 dmul (7, 4)
	417 dsub (7, 4)
	418 ldc2_w (7, 4)
	419 900.0 (7, 4)
	421 ddiv (7, 4)
	422 dastore (7, 4)
	423 dup (7, 4)
	424 iconst_1 (7, 4)
	425 ldc2_w (7, 4)
	426 322.0 (7, 4)
	428 ldc2_w (7, 4)
	429 13.0 (7, 4)
	431 ldc2_w (7, 4)
	432 70.0 (7, 4)
	434 invokestatic (7, 4)
	435 org/apache/commons/math3/util/FastMath.sqrt:(D)D (7, 4)
	437 dmul (7, 4)
	438 dadd (7, 4)
	439 ldc2_w (7, 4)
	440 900.0 (7, 4)
	442 ddiv (7, 4)
	443 dastore (7, 4)
	444 dup (7, 4)
	445 iconst_2 (7, 4)
	446 ldc2_w (7, 4)
	447 0.5688888888888889 (7, 4)
	449 dastore (7, 4)
	450 dup (7, 4)
	451 iconst_3 (7, 4)
	452 ldc2_w (7, 4)
	453 322.0 (7, 4)
	455 ldc2_w (7, 4)
	456 13.0 (7, 4)
	458 ldc2_w (7, 4)
	459 70.0 (7, 4)
	461 invokestatic (7, 4)
	462 org/apache/commons/math3/util/FastMath.sqrt:(D)D (7, 4)
	464 dmul (7, 4)
	465 dadd (7, 4)
	466 ldc2_w (7, 4)
	467 900.0 (7, 4)
	469 ddiv (7, 4)
	470 dastore (7, 4)
	471 dup (7, 4)
	472 iconst_4 (7, 4)
	473 ldc2_w (7, 4)
	474 322.0 (7, 4)
	476 ldc2_w (7, 4)
	477 13.0 (7, 4)
	479 ldc2_w (7, 4)
	480 70.0 (7, 4)
	482 invokestatic (7, 4)
	483 org/apache/commons/math3/util/FastMath.sqrt:(D)D (7, 4)
	485 dmul (7, 4)
	486 dsub (7, 4)
	487 ldc2_w (7, 4)
	488 900.0 (7, 4)
	490 ddiv (7, 4)
	491 dastore (7, 4)
	492 putstatic (7, 4)
	493 org/apache/commons/math3/analysis/integration/LegendreGaussIntegrator.WEIGHTS_5:[D (7, 4)
	495 return (0, 4)

