Method: <init>
	0 aload_0 (0, 0)
	1 iconst_3 (0, 0)
	2 bipush (0, 0)
	3 32 (0, 0)
	4 invokespecial (0, 0)
	5 org/apache/commons/math3/analysis/integration/BaseAbstractUnivariateIntegrator.<init>:(II)V (0, 0)
	7 return (0, 0)

Method: doIntegrate
	0 aload_0 (0, 0)
	1 invokevirtual (0, 0)
	2 org/apache/commons/math3/analysis/integration/RombergIntegrator.getMaximalIterationCount:()I (0, 0)
	4 iconst_1 (0, 0)
	5 iadd (0, 0)
	6 istore_1 (0, 0)
	7 iload_1 (0, 0)
	8 newarray (0, 0)
	9 7 (0, 0)
	10 astore_2 (0, 0)
	11 iload_1 (0, 0)
	12 newarray (0, 0)
	13 7 (0, 0)
	14 astore_3 (0, 0)
	15 new (0, 0)
	16 org/apache/commons/math3/analysis/integration/TrapezoidIntegrator (0, 0)
	18 dup (0, 0)
	19 invokespecial (0, 0)
	20 org/apache/commons/math3/analysis/integration/TrapezoidIntegrator.<init>:()V (0, 0)
	22 astore (0, 0)
	23 #4 (0, 0)
	24 aload_3 (0, 0)
	25 iconst_0 (0, 0)
	26 aload (0, 0)
	27 #4 (0, 0)
	28 aload_0 (0, 0)
	29 iconst_0 (0, 0)
	30 invokevirtual (0, 0)
	31 org/apache/commons/math3/analysis/integration/TrapezoidIntegrator.stage:(Lorg/apache/commons/math3/analysis/integration/BaseAbstractUnivariateIntegrator;I)D (0, 0)
	33 dastore (0, 0)
	34 aload_0 (0, 0)
	35 invokevirtual (0, 0)
	36 org/apache/commons/math3/analysis/integration/RombergIntegrator.incrementCount:()V (0, 0)
	38 aload_3 (0, 0)
	39 iconst_0 (0, 0)
	40 daload (0, 0)
	41 dstore (0, 0)
	42 #5 (0, 0)
	43 aload_0 (1, 3)
	44 invokevirtual (1, 3)
	45 org/apache/commons/math3/analysis/integration/RombergIntegrator.getIterations:()I (1, 3)
	47 istore (1, 3)
	48 #7 (1, 3)
	49 aload_2 (2, 5)
	50 astore (2, 5)
	51 #8 (2, 5)
	52 aload_3 (2, 5)
	53 astore_2 (2, 5)
	54 aload (2, 5)
	55 #8 (2, 5)
	56 astore_3 (2, 5)
	57 aload_3 (2, 5)
	58 iconst_0 (2, 5)
	59 aload (2, 5)
	60 #4 (2, 5)
	61 aload_0 (2, 5)
	62 iload (2, 5)
	63 #7 (2, 5)
	64 invokevirtual (2, 5)
	65 org/apache/commons/math3/analysis/integration/TrapezoidIntegrator.stage:(Lorg/apache/commons/math3/analysis/integration/BaseAbstractUnivariateIntegrator;I)D (2, 5)
	67 dastore (2, 5)
	68 aload_0 (2, 5)
	69 invokevirtual (2, 5)
	70 org/apache/commons/math3/analysis/integration/RombergIntegrator.incrementCount:()V (2, 5)
	72 iconst_1 (3, 4)
	73 istore (3, 4)
	74 #9 (3, 4)
	75 iload (3, 4)
	76 #9 (3, 4)
	77 iload (3, 4)
	78 #7 (3, 4)
	79 if_icmpgt (3, 4)
	80 47 (3, 4)
	82 lconst_1 (3, 4)
	83 iconst_2 (3, 4)
	84 iload (3, 4)
	85 #9 (3, 4)
	86 imul (3, 4)
	87 lshl (3, 4)
	88 lconst_1 (3, 4)
	89 lsub (3, 4)
	90 l2d (3, 4)
	91 dstore (3, 4)
	92 #10 (3, 4)
	93 aload_3 (3, 4)
	94 iload (3, 4)
	95 #9 (3, 4)
	96 iconst_1 (3, 4)
	97 isub (3, 4)
	98 daload (3, 4)
	99 dstore (3, 4)
	100 #12 (3, 4)
	101 aload_3 (3, 4)
	102 iload (3, 4)
	103 #9 (3, 4)
	104 dload (3, 4)
	105 #12 (3, 4)
	106 dload (3, 4)
	107 #12 (3, 4)
	108 aload_2 (3, 4)
	109 iload (3, 4)
	110 #9 (3, 4)
	111 iconst_1 (3, 4)
	112 isub (3, 4)
	113 daload (3, 4)
	114 dsub (3, 4)
	115 dload (3, 4)
	116 #10 (3, 4)
	117 ddiv (3, 4)
	118 dadd (3, 4)
	119 dastore (3, 4)
	120 iinc (3, 4)
	121 #9 (3, 4)
	122 -89 (3, 4)
	123 goto (3, 4)
	124 -48 (3, 4)
	126 aload_3 (2, 5)
	127 iload (2, 5)
	128 #7 (2, 5)
	129 daload (2, 5)
	130 dstore (2, 5)
	131 #9 (2, 5)
	132 iload (3, 1)
	133 #7 (3, 1)
	134 aload_0 (3, 1)
	135 invokevirtual (3, 1)
	136 org/apache/commons/math3/analysis/integration/RombergIntegrator.getMinimalIterationCount:()I (3, 1)
	138 if_icmplt (3, 1)
	139 56 (3, 1)
	141 dload (3, 1)
	142 #9 (3, 1)
	143 dload (3, 1)
	144 #5 (3, 1)
	145 dsub (3, 1)
	146 invokestatic (3, 1)
	147 org/apache/commons/math3/util/FastMath.abs:(D)D (3, 1)
	149 dstore (3, 1)
	150 #11 (3, 1)
	151 aload_0 (3, 1)
	152 invokevirtual (3, 1)
	153 org/apache/commons/math3/analysis/integration/RombergIntegrator.getRelativeAccuracy:()D (3, 1)
	155 dload (3, 1)
	156 #5 (3, 1)
	157 invokestatic (3, 1)
	158 org/apache/commons/math3/util/FastMath.abs:(D)D (3, 1)
	160 dload (3, 1)
	161 #9 (3, 1)
	162 invokestatic (3, 1)
	163 org/apache/commons/math3/util/FastMath.abs:(D)D (3, 1)
	165 dadd (3, 1)
	166 dmul (3, 1)
	167 ldc2_w (3, 1)
	168 0.5 (3, 1)
	170 dmul (3, 1)
	171 dstore (3, 1)
	172 #13 (3, 1)
	173 dload (4, 1)
	174 #11 (4, 1)
	175 dload (4, 1)
	176 #13 (4, 1)
	177 dcmpg (4, 1)
	178 ifle (4, 1)
	179 13 (4, 1)
	181 dload (4, 1)
	182 #11 (4, 1)
	183 aload_0 (4, 1)
	184 invokevirtual (4, 1)
	185 org/apache/commons/math3/analysis/integration/RombergIntegrator.getAbsoluteAccuracy:()D (4, 1)
	187 dcmpg (4, 1)
	188 ifgt (4, 1)
	189 6 (4, 1)
	191 dload (4, 1)
	192 #9 (4, 1)
	193 dreturn (4, 1)
	194 dload (2, 5)
	195 #9 (2, 5)
	196 dstore (2, 5)
	197 #5 (2, 5)
	198 goto (0, 0)
	199 -155 (0, 0)

