Method: <init>
	0 aload_0 (0, 0)
	1 iconst_3 (0, 0)
	2 bipush (0, 0)
	3 64 (0, 0)
	4 invokespecial (0, 0)
	5 org/apache/commons/math3/analysis/integration/BaseAbstractUnivariateIntegrator.<init>:(II)V (0, 0)
	7 return (0, 0)

Method: stage
	0 iload_2 (1, 1)
	1 ifne (1, 1)
	2 44 (1, 1)
	4 aload_1 (1, 1)
	5 invokevirtual (1, 1)
	6 org/apache/commons/math3/analysis/integration/BaseAbstractUnivariateIntegrator.getMax:()D (1, 1)
	8 dstore_3 (1, 1)
	9 aload_1 (1, 1)
	10 invokevirtual (1, 1)
	11 org/apache/commons/math3/analysis/integration/BaseAbstractUnivariateIntegrator.getMin:()D (1, 1)
	13 dstore (1, 1)
	14 #5 (1, 1)
	15 aload_0 (1, 1)
	16 ldc2_w (1, 1)
	17 0.5 (1, 1)
	19 dload_3 (1, 1)
	20 dload (1, 1)
	21 #5 (1, 1)
	22 dsub (1, 1)
	23 dmul (1, 1)
	24 aload_1 (1, 1)
	25 dload (1, 1)
	26 #5 (1, 1)
	27 invokevirtual (1, 1)
	28 org/apache/commons/math3/analysis/integration/BaseAbstractUnivariateIntegrator.computeObjectiveValue:(D)D (1, 1)
	30 aload_1 (1, 1)
	31 dload_3 (1, 1)
	32 invokevirtual (1, 1)
	33 org/apache/commons/math3/analysis/integration/BaseAbstractUnivariateIntegrator.computeObjectiveValue:(D)D (1, 1)
	35 dadd (1, 1)
	36 dmul (1, 1)
	37 putfield (1, 1)
	38 org/apache/commons/math3/analysis/integration/TrapezoidIntegrator.s:D (1, 1)
	40 aload_0 (1, 1)
	41 getfield (1, 1)
	42 org/apache/commons/math3/analysis/integration/TrapezoidIntegrator.s:D (1, 1)
	44 dreturn (1, 1)
	45 lconst_1 (2, 2)
	46 iload_2 (2, 2)
	47 iconst_1 (2, 2)
	48 isub (2, 2)
	49 lshl (2, 2)
	50 lstore_3 (2, 2)
	51 dconst_0 (2, 2)
	52 dstore (2, 2)
	53 #5 (2, 2)
	54 aload_1 (2, 2)
	55 invokevirtual (2, 2)
	56 org/apache/commons/math3/analysis/integration/BaseAbstractUnivariateIntegrator.getMax:()D (2, 2)
	58 dstore (2, 2)
	59 #7 (2, 2)
	60 aload_1 (2, 2)
	61 invokevirtual (2, 2)
	62 org/apache/commons/math3/analysis/integration/BaseAbstractUnivariateIntegrator.getMin:()D (2, 2)
	64 dstore (2, 2)
	65 #9 (2, 2)
	66 dload (2, 2)
	67 #7 (2, 2)
	68 dload (2, 2)
	69 #9 (2, 2)
	70 dsub (2, 2)
	71 lload_3 (2, 2)
	72 l2d (2, 2)
	73 ddiv (2, 2)
	74 dstore (2, 2)
	75 #11 (2, 2)
	76 dload (2, 2)
	77 #9 (2, 2)
	78 ldc2_w (2, 2)
	79 0.5 (2, 2)
	81 dload (2, 2)
	82 #11 (2, 2)
	83 dmul (2, 2)
	84 dadd (2, 2)
	85 dstore (2, 2)
	86 #13 (2, 2)
	87 lconst_0 (3, 4)
	88 lstore (3, 4)
	89 #15 (3, 4)
	90 lload (3, 4)
	91 #15 (3, 4)
	92 lload_3 (3, 4)
	93 lcmp (3, 4)
	94 ifge (3, 4)
	95 30 (3, 4)
	97 dload (3, 4)
	98 #5 (3, 4)
	99 aload_1 (3, 4)
	100 dload (3, 4)
	101 #13 (3, 4)
	102 invokevirtual (3, 4)
	103 org/apache/commons/math3/analysis/integration/BaseAbstractUnivariateIntegrator.computeObjectiveValue:(D)D (3, 4)
	105 dadd (3, 4)
	106 dstore (3, 4)
	107 #5 (3, 4)
	108 dload (3, 4)
	109 #13 (3, 4)
	110 dload (3, 4)
	111 #11 (3, 4)
	112 dadd (3, 4)
	113 dstore (3, 4)
	114 #13 (3, 4)
	115 lload (3, 4)
	116 #15 (3, 4)
	117 lconst_1 (3, 4)
	118 ladd (3, 4)
	119 lstore (3, 4)
	120 #15 (3, 4)
	121 goto (3, 4)
	122 -31 (3, 4)
	124 aload_0 (2, 2)
	125 ldc2_w (2, 2)
	126 0.5 (2, 2)
	128 aload_0 (2, 2)
	129 getfield (2, 2)
	130 org/apache/commons/math3/analysis/integration/TrapezoidIntegrator.s:D (2, 2)
	132 dload (2, 2)
	133 #5 (2, 2)
	134 dload (2, 2)
	135 #11 (2, 2)
	136 dmul (2, 2)
	137 dadd (2, 2)
	138 dmul (2, 2)
	139 putfield (2, 2)
	140 org/apache/commons/math3/analysis/integration/TrapezoidIntegrator.s:D (2, 2)
	142 aload_0 (2, 2)
	143 getfield (2, 2)
	144 org/apache/commons/math3/analysis/integration/TrapezoidIntegrator.s:D (2, 2)
	146 dreturn (1, 2)

Method: doIntegrate
	0 aload_0 (0, 0)
	1 aload_0 (0, 0)
	2 iconst_0 (0, 0)
	3 invokevirtual (0, 0)
	4 org/apache/commons/math3/analysis/integration/TrapezoidIntegrator.stage:(Lorg/apache/commons/math3/analysis/integration/BaseAbstractUnivariateIntegrator;I)D (0, 0)
	6 dstore_1 (0, 0)
	7 aload_0 (0, 0)
	8 invokevirtual (0, 0)
	9 org/apache/commons/math3/analysis/integration/TrapezoidIntegrator.incrementCount:()V (0, 0)
	11 aload_0 (1, 3)
	12 invokevirtual (1, 3)
	13 org/apache/commons/math3/analysis/integration/TrapezoidIntegrator.getIterations:()I (1, 3)
	15 istore_3 (1, 3)
	16 aload_0 (1, 3)
	17 aload_0 (1, 3)
	18 iload_3 (1, 3)
	19 invokevirtual (1, 3)
	20 org/apache/commons/math3/analysis/integration/TrapezoidIntegrator.stage:(Lorg/apache/commons/math3/analysis/integration/BaseAbstractUnivariateIntegrator;I)D (1, 3)
	22 dstore (1, 3)
	23 #4 (1, 3)
	24 iload_3 (2, 1)
	25 aload_0 (2, 1)
	26 invokevirtual (2, 1)
	27 org/apache/commons/math3/analysis/integration/TrapezoidIntegrator.getMinimalIterationCount:()I (2, 1)
	29 if_icmplt (2, 1)
	30 54 (2, 1)
	32 dload (2, 1)
	33 #4 (2, 1)
	34 dload_1 (2, 1)
	35 dsub (2, 1)
	36 invokestatic (2, 1)
	37 org/apache/commons/math3/util/FastMath.abs:(D)D (2, 1)
	39 dstore (2, 1)
	40 #6 (2, 1)
	41 aload_0 (2, 1)
	42 invokevirtual (2, 1)
	43 org/apache/commons/math3/analysis/integration/TrapezoidIntegrator.getRelativeAccuracy:()D (2, 1)
	45 dload_1 (2, 1)
	46 invokestatic (2, 1)
	47 org/apache/commons/math3/util/FastMath.abs:(D)D (2, 1)
	49 dload (2, 1)
	50 #4 (2, 1)
	51 invokestatic (2, 1)
	52 org/apache/commons/math3/util/FastMath.abs:(D)D (2, 1)
	54 dadd (2, 1)
	55 dmul (2, 1)
	56 ldc2_w (2, 1)
	57 0.5 (2, 1)
	59 dmul (2, 1)
	60 dstore (2, 1)
	61 #8 (2, 1)
	62 dload (3, 1)
	63 #6 (3, 1)
	64 dload (3, 1)
	65 #8 (3, 1)
	66 dcmpg (3, 1)
	67 ifle (3, 1)
	68 13 (3, 1)
	70 dload (3, 1)
	71 #6 (3, 1)
	72 aload_0 (3, 1)
	73 invokevirtual (3, 1)
	74 org/apache/commons/math3/analysis/integration/TrapezoidIntegrator.getAbsoluteAccuracy:()D (3, 1)
	76 dcmpg (3, 1)
	77 ifgt (3, 1)
	78 6 (3, 1)
	80 dload (3, 1)
	81 #4 (3, 1)
	82 dreturn (3, 1)
	83 dload (1, 3)
	84 #4 (1, 3)
	85 dstore_1 (1, 3)
	86 aload_0 (1, 3)
	87 invokevirtual (1, 3)
	88 org/apache/commons/math3/analysis/integration/TrapezoidIntegrator.incrementCount:()V (1, 3)
	90 goto (0, 0)
	91 -79 (0, 0)

