Method: <init>
	0 aload_0 (0, 0)
	1 invokespecial (0, 0)
	4 aload_0 (0, 0)
	5 dload_1 (0, 0)
	6 dload_3 (0, 0)
	7 dload (0, 0)
	9 invokespecial (0, 0)
	12 aload_0 (0, 0)
	13 dload_1 (0, 0)
	14 putfield (0, 0)
	17 aload_0 (0, 0)
	18 dload_3 (0, 0)
	19 putfield (0, 0)
	22 aload_0 (0, 0)
	23 dload (0, 0)
	25 putfield (0, 0)
	28 return (0, 0)

Method: getLowerBound
	0 aload_0 (0, 0)
	1 getfield (0, 0)
	4 dreturn (0, 0)

Method: getUpperBound
	0 aload_0 (0, 0)
	1 getfield (0, 0)
	4 dreturn (0, 0)

Method: getConfidenceLevel
	0 aload_0 (0, 0)
	1 getfield (0, 0)
	4 dreturn (0, 0)

Method: toString
	0 new (0, 0)
	3 dup (0, 0)
	4 invokespecial (0, 0)
	7 ldc (0, 0)
	9 invokevirtual (0, 0)
	12 aload_0 (0, 0)
	13 getfield (0, 0)
	16 invokevirtual (0, 0)
	19 ldc (0, 0)
	21 invokevirtual (0, 0)
	24 aload_0 (0, 0)
	25 getfield (0, 0)
	28 invokevirtual (0, 0)
	31 ldc (0, 0)
	33 invokevirtual (0, 0)
	36 aload_0 (0, 0)
	37 getfield (0, 0)
	40 invokevirtual (0, 0)
	43 ldc (0, 0)
	45 invokevirtual (0, 0)
	48 invokevirtual (0, 0)
	51 areturn (0, 0)

Method: checkParameters
	0 dload_1 (1, 1)
	1 dload_3 (1, 1)
	2 dcmpl (1, 1)
	3 iflt (1, 1)
	6 new (1, 1)
	9 dup (1, 1)
	10 getstatic (1, 1)
	13 iconst_2 (1, 1)
	14 anewarray (1, 1)
	17 dup (1, 1)
	18 iconst_0 (1, 1)
	19 dload_1 (1, 1)
	20 invokestatic (1, 1)
	23 aastore (1, 1)
	24 dup (1, 1)
	25 iconst_1 (1, 1)
	26 dload_3 (1, 1)
	27 invokestatic (1, 1)
	30 aastore (1, 1)
	31 invokespecial (1, 1)
	34 athrow (1, 1)
	35 dload (1, 1)
	37 dconst_0 (1, 1)
	38 dcmpg (1, 1)
	39 ifle (1, 1)
	42 dload (1, 1)
	44 dconst_1 (1, 1)
	45 dcmpl (1, 1)
	46 iflt (1, 1)
	49 new (1, 1)
	52 dup (1, 1)
	53 getstatic (1, 1)
	56 iconst_3 (1, 1)
	57 anewarray (1, 1)
	60 dup (1, 1)
	61 iconst_0 (1, 1)
	62 dload (1, 1)
	64 invokestatic (1, 1)
	67 aastore (1, 1)
	68 dup (1, 1)
	69 iconst_1 (1, 1)
	70 iconst_0 (1, 1)
	71 invokestatic (1, 1)
	74 aastore (1, 1)
	75 dup (1, 1)
	76 iconst_2 (1, 1)
	77 iconst_1 (1, 1)
	78 invokestatic (1, 1)
	81 aastore (1, 1)
	82 invokespecial (1, 1)
	85 athrow (1, 1)
	86 return (0, 0)

