Method: <init>
	0 aload_0 (0, 0)
	1 invokespecial (0, 0)
	4 return (0, 0)

Method: getAgrestiCoullInterval
	0 getstatic (0, 0)
	3 iload_0 (0, 0)
	4 iload_1 (0, 0)
	5 dload_2 (0, 0)
	6 invokeinterface (0, 0)
	11 areturn (0, 0)

Method: getClopperPearsonInterval
	0 getstatic (0, 0)
	3 iload_0 (0, 0)
	4 iload_1 (0, 0)
	5 dload_2 (0, 0)
	6 invokeinterface (0, 0)
	11 areturn (0, 0)

Method: getNormalApproximationInterval
	0 getstatic (0, 0)
	3 iload_0 (0, 0)
	4 iload_1 (0, 0)
	5 dload_2 (0, 0)
	6 invokeinterface (0, 0)
	11 areturn (0, 0)

Method: getWilsonScoreInterval
	0 getstatic (0, 0)
	3 iload_0 (0, 0)
	4 iload_1 (0, 0)
	5 dload_2 (0, 0)
	6 invokeinterface (0, 0)
	11 areturn (0, 0)

Method: checkParameters
	0 iload_0 (1, 1)
	1 ifgt (1, 1)
	4 new (1, 1)
	7 dup (1, 1)
	8 getstatic (1, 1)
	11 iload_0 (1, 1)
	12 invokestatic (1, 1)
	15 invokespecial (1, 1)
	18 athrow (1, 1)
	19 iload_1 (1, 1)
	20 ifge (1, 1)
	23 new (1, 1)
	26 dup (1, 1)
	27 getstatic (1, 1)
	30 iload_1 (1, 1)
	31 invokestatic (1, 1)
	34 invokespecial (1, 1)
	37 athrow (1, 1)
	38 iload_1 (1, 1)
	39 iload_0 (1, 1)
	40 if_icmple (1, 1)
	43 new (1, 1)
	46 dup (1, 1)
	47 getstatic (1, 1)
	50 iload_1 (1, 1)
	51 invokestatic (1, 1)
	54 iload_0 (1, 1)
	55 invokestatic (1, 1)
	58 iconst_1 (1, 1)
	59 invokespecial (1, 1)
	62 athrow (1, 1)
	63 dload_2 (1, 1)
	64 dconst_0 (1, 1)
	65 dcmpg (1, 1)
	66 ifle (1, 1)
	69 dload_2 (1, 1)
	70 dconst_1 (1, 1)
	71 dcmpl (1, 1)
	72 iflt (1, 1)
	75 new (1, 1)
	78 dup (1, 1)
	79 getstatic (1, 1)
	82 dload_2 (1, 1)
	83 invokestatic (1, 1)
	86 iconst_0 (1, 1)
	87 invokestatic (1, 1)
	90 iconst_1 (1, 1)
	91 invokestatic (1, 1)
	94 invokespecial (1, 1)
	97 athrow (1, 1)
	98 return (0, 0)

Method: <clinit>
	0 new (0, 0)
	3 dup (0, 0)
	4 invokespecial (0, 0)
	7 putstatic (0, 0)
	10 new (0, 0)
	13 dup (0, 0)
	14 invokespecial (0, 0)
	17 putstatic (0, 0)
	20 new (0, 0)
	23 dup (0, 0)
	24 invokespecial (0, 0)
	27 putstatic (0, 0)
	30 new (0, 0)
	33 dup (0, 0)
	34 invokespecial (0, 0)
	37 putstatic (0, 0)
	40 return (0, 0)

