Method: createInterval
	0 iload_1 (0, 0)
	1 iload_2 (0, 0)
	2 dload_3 (0, 0)
	3 invokestatic (0, 0)
	4 org/apache/commons/math3/stat/interval/IntervalUtils.checkParameters:(IID)V (0, 0)
	6 dconst_1 (0, 0)
	7 dload_3 (0, 0)
	8 dsub (0, 0)
	9 ldc2_w (0, 0)
	10 2.0 (0, 0)
	12 ddiv (0, 0)
	13 dstore (0, 0)
	14 #5 (0, 0)
	15 new (0, 0)
	16 org/apache/commons/math3/distribution/NormalDistribution (0, 0)
	18 dup (0, 0)
	19 invokespecial (0, 0)
	20 org/apache/commons/math3/distribution/NormalDistribution.<init>:()V (0, 0)
	22 astore (0, 0)
	23 #7 (0, 0)
	24 aload (0, 0)
	25 #7 (0, 0)
	26 dconst_1 (0, 0)
	27 dload (0, 0)
	28 #5 (0, 0)
	29 dsub (0, 0)
	30 invokevirtual (0, 0)
	31 org/apache/commons/math3/distribution/NormalDistribution.inverseCumulativeProbability:(D)D (0, 0)
	33 dstore (0, 0)
	34 #8 (0, 0)
	35 dload (0, 0)
	36 #8 (0, 0)
	37 iconst_2 (0, 0)
	38 invokestatic (0, 0)
	39 org/apache/commons/math3/util/FastMath.pow:(DI)D (0, 0)
	41 dstore (0, 0)
	42 #10 (0, 0)
	43 iload_2 (0, 0)
	44 i2d (0, 0)
	45 iload_1 (0, 0)
	46 i2d (0, 0)
	47 ddiv (0, 0)
	48 dstore (0, 0)
	49 #12 (0, 0)
	50 dconst_1 (0, 0)
	51 dconst_1 (0, 0)
	52 dconst_1 (0, 0)
	53 iload_1 (0, 0)
	54 i2d (0, 0)
	55 ddiv (0, 0)
	56 dload (0, 0)
	57 #10 (0, 0)
	58 dmul (0, 0)
	59 dadd (0, 0)
	60 ddiv (0, 0)
	61 dstore (0, 0)
	62 #14 (0, 0)
	63 dload (0, 1)
	64 #12 (0, 1)
	65 dconst_1 (0, 1)
	66 iconst_2 (0, 1)
	67 iload_1 (0, 1)
	68 imul (0, 1)
	69 i2d (0, 1)
	70 ddiv (0, 1)
	71 dload (0, 1)
	72 #10 (0, 1)
	73 dmul (0, 1)
	74 dadd (0, 1)
	75 dstore (0, 1)
	76 #16 (0, 1)
	77 dload (0, 1)
	78 #8 (0, 1)
	79 dconst_1 (0, 1)
	80 iload_1 (0, 1)
	81 i2d (0, 1)
	82 ddiv (0, 1)
	83 dload (0, 1)
	84 #12 (0, 1)
	85 dmul (0, 1)
	86 dconst_1 (0, 1)
	87 dload (0, 1)
	88 #12 (0, 1)
	89 dsub (0, 1)
	90 dmul (0, 1)
	91 dconst_1 (0, 1)
	92 ldc2_w (0, 1)
	93 4.0 (0, 1)
	95 iload_1 (0, 1)
	96 i2d (0, 1)
	97 iconst_2 (0, 1)
	98 invokestatic (0, 1)
	99 org/apache/commons/math3/util/FastMath.pow:(DI)D (0, 1)
	101 dmul (0, 1)
	102 ddiv (0, 1)
	103 dload (0, 1)
	104 #10 (0, 1)
	105 dmul (0, 1)
	106 dadd (0, 1)
	107 invokestatic (0, 1)
	108 org/apache/commons/math3/util/FastMath.sqrt:(D)D (0, 1)
	110 dmul (0, 1)
	111 dstore (0, 1)
	112 #18 (0, 1)
	113 dload (0, 1)
	114 #14 (0, 1)
	115 dload (0, 1)
	116 #16 (0, 1)
	117 dload (0, 1)
	118 #18 (0, 1)
	119 dsub (0, 1)
	120 dmul (0, 1)
	121 dstore (0, 1)
	122 #20 (0, 1)
	123 dload (0, 1)
	124 #14 (0, 1)
	125 dload (0, 1)
	126 #16 (0, 1)
	127 dload (0, 1)
	128 #18 (0, 1)
	129 dadd (0, 1)
	130 dmul (0, 1)
	131 dstore (0, 1)
	132 #22 (0, 1)
	133 new (0, 1)
	134 org/apache/commons/math3/stat/interval/ConfidenceInterval (0, 1)
	136 dup (0, 1)
	137 dload (0, 1)
	138 #20 (0, 1)
	139 dload (0, 1)
	140 #22 (0, 1)
	141 dload_3 (0, 1)
	142 invokespecial (0, 1)
	143 org/apache/commons/math3/stat/interval/ConfidenceInterval.<init>:(DDD)V (0, 1)
	145 areturn (0, 1)

