Method: <init>
	0 aload_0 (0, 0)
	1 invokespecial (0, 0)
	2 java/lang/Object.<init>:()V (0, 0)
	4 aload_0 (0, 0)
	5 dload_1 (0, 0)
	6 putfield (0, 0)
	7 org/apache/commons/math3/fitting/leastsquares/EvaluationRmsChecker.relTol:D (0, 0)
	9 aload_0 (0, 0)
	10 dload_3 (0, 0)
	11 putfield (0, 0)
	12 org/apache/commons/math3/fitting/leastsquares/EvaluationRmsChecker.absTol:D (0, 0)
	14 return (0, 0)

Method: converged
	0 aload_0 (0, 0)
	1 iload_1 (0, 0)
	2 aload_2 (0, 0)
	3 checkcast (0, 0)
	4 org/apache/commons/math3/fitting/leastsquares/LeastSquaresProblem$Evaluation (0, 0)
	6 aload_3 (0, 0)
	7 checkcast (0, 0)
	8 org/apache/commons/math3/fitting/leastsquares/LeastSquaresProblem$Evaluation (0, 0)
	10 invokevirtual (0, 0)
	11 org/apache/commons/math3/fitting/leastsquares/EvaluationRmsChecker.converged:(ILorg/apache/commons/math3/fitting/leastsquares/LeastSquaresProblem$Evaluation;Lorg/apache/commons/math3/fitting/leastsquares/LeastSquaresProblem$Evaluation;)Z (0, 0)
	13 ireturn (0, 0)

