Method: <init>
	0 aload_0 (0, 0)
	1 invokespecial (0, 0)
	4 aload_0 (0, 0)
	5 aload_1 (0, 0)
	6 putfield (0, 0)
	9 return (0, 0)

Method: getDecomposition
	0 aload_0 (0, 0)
	1 getfield (0, 0)
	4 areturn (0, 0)

Method: withDecomposition
	0 new (0, 0)
	3 dup (0, 0)
	4 aload_1 (0, 0)
	5 invokespecial (0, 0)
	8 areturn (0, 0)

Method: optimize
	0 aload_1 (0, 0)
	1 invokeinterface (0, 0)
	6 astore_2 (0, 0)
	7 aload_1 (0, 0)
	8 invokeinterface (0, 0)
	13 astore_3 (0, 0)
	14 aload_1 (0, 0)
	15 invokeinterface (0, 0)
	20 astore (0, 0)
	22 aload (1, 1)
	24 ifnonnull (1, 1)
	27 new (1, 1)
	30 dup (1, 1)
	31 invokespecial (1, 1)
	34 athrow (1, 1)
	35 aload_1 (0, 4)
	36 invokeinterface (0, 4)
	41 astore (0, 4)
	43 aconst_null (0, 4)
	44 astore (0, 4)
	46 aload_3 (1, 3)
	47 invokevirtual (1, 3)
	50 aload (1, 3)
	52 astore (1, 3)
	54 aload_2 (1, 3)
	55 invokevirtual (1, 3)
	58 aload_1 (1, 3)
	59 aload (1, 3)
	61 invokeinterface (1, 3)
	66 astore (1, 3)
	68 aload (1, 3)
	70 invokeinterface (1, 3)
	75 astore (1, 3)
	77 aload (1, 3)
	79 invokeinterface (1, 3)
	84 astore (1, 3)
	86 aload (1, 3)
	88 invokeinterface (1, 3)
	93 astore (1, 3)
	95 aload (1, 1)
	97 ifnull (1, 1)
	100 aload (1, 1)
	102 aload_3 (1, 1)
	103 invokevirtual (2, 1)
	106 aload (2, 1)
	108 aload (2, 1)
	110 invokeinterface (2, 1)
	115 ifeq (2, 1)
	118 new (2, 1)
	121 dup (2, 1)
	122 aload (2, 1)
	124 aload_2 (2, 1)
	125 invokevirtual (2, 1)
	128 aload_3 (2, 1)
	129 invokevirtual (2, 1)
	132 invokespecial (2, 1)
	135 areturn (2, 1)
	136 aload_0 (1, 3)
	137 getfield (1, 3)
	140 aload (1, 3)
	142 aload (1, 3)
	144 invokevirtual (1, 3)
	147 astore (1, 3)
	149 aload (1, 3)
	151 aload (1, 3)
	153 invokevirtual (1, 3)
	156 astore (1, 3)
	158 goto (0, 4)

Method: toString
	0 new (0, 0)
	3 dup (0, 0)
	4 invokespecial (0, 0)
	7 ldc (0, 0)
	9 invokevirtual (0, 0)
	12 aload_0 (0, 0)
	13 getfield (0, 0)
	16 invokevirtual (0, 0)
	19 bipush (0, 0)
	21 invokevirtual (0, 0)
	24 invokevirtual (0, 0)
	27 areturn (0, 0)

Method: computeNormalMatrix
	0 aload_0 (0, 0)
	1 invokeinterface (0, 0)
	6 istore_2 (0, 0)
	7 aload_0 (0, 0)
	8 invokeinterface (0, 0)
	13 istore_3 (0, 0)
	14 iload_3 (0, 4)
	15 iload_3 (0, 4)
	16 invokestatic (0, 4)
	19 astore (0, 4)
	21 new (0, 4)
	24 dup (0, 4)
	25 iload_3 (0, 4)
	26 invokespecial (0, 4)
	29 astore (0, 4)
	31 iconst_0 (1, 4)
	32 istore (1, 4)
	34 iload (1, 4)
	36 iload_2 (1, 4)
	37 if_icmpge (1, 4)
	40 iconst_0 (2, 4)
	41 istore (2, 4)
	43 iload (2, 4)
	45 iload_3 (2, 4)
	46 if_icmpge (2, 4)
	49 aload (2, 4)
	51 iload (2, 4)
	53 aload (2, 4)
	55 iload (2, 4)
	57 invokevirtual (2, 4)
	60 aload_1 (2, 4)
	61 iload (2, 4)
	63 invokevirtual (2, 4)
	66 aload_0 (2, 4)
	67 iload (2, 4)
	69 iload (2, 4)
	71 invokeinterface (2, 4)
	76 dmul (2, 4)
	77 dadd (2, 4)
	78 invokevirtual (2, 4)
	81 iinc (2, 4)
	84 goto (2, 4)
	87 iconst_0 (2, 4)
	88 istore (2, 4)
	90 iload (2, 4)
	92 iload_3 (2, 4)
	93 if_icmpge (2, 4)
	96 iload (3, 4)
	98 istore (3, 4)
	100 iload (3, 4)
	102 iload_3 (3, 4)
	103 if_icmpge (3, 4)
	106 aload (3, 4)
	108 iload (3, 4)
	110 iload (3, 4)
	112 aload (3, 4)
	114 iload (3, 4)
	116 iload (3, 4)
	118 invokeinterface (3, 4)
	123 aload_0 (3, 4)
	124 iload (3, 4)
	126 iload (3, 4)
	128 invokeinterface (3, 4)
	133 aload_0 (3, 4)
	134 iload (3, 4)
	136 iload (3, 4)
	138 invokeinterface (3, 4)
	143 dmul (3, 4)
	144 dadd (3, 4)
	145 invokeinterface (3, 4)
	150 iinc (3, 4)
	153 goto (3, 4)
	156 iinc (3, 4)
	159 goto (3, 4)
	162 iinc (3, 4)
	165 goto (3, 4)
	168 iconst_0 (3, 4)
	169 istore (3, 4)
	171 iload (3, 4)
	173 iload_3 (3, 4)
	174 if_icmpge (3, 4)
	177 iconst_0 (4, 4)
	178 istore (4, 4)
	180 iload (4, 4)
	182 iload (4, 4)
	184 if_icmpge (4, 4)
	187 aload (4, 4)
	189 iload (4, 4)
	191 iload (4, 4)
	193 aload (4, 4)
	195 iload (4, 4)
	197 iload (4, 4)
	199 invokeinterface (4, 4)
	204 invokeinterface (4, 4)
	209 iinc (4, 4)
	212 goto (4, 4)
	215 iinc (4, 4)
	218 goto (4, 4)
	221 new (3, 4)
	224 dup (3, 4)
	225 aload (3, 4)
	227 aload (3, 4)
	229 invokespecial (3, 4)
	232 areturn (3, 4)

Method: access$100
	0 aload_0 (0, 0)
	1 aload_1 (0, 0)
	2 invokestatic (0, 0)
	5 areturn (0, 0)

