Method: solve
	0 new (0, 0)
	1 org/apache/commons/math3/linear/SingularValueDecomposition (0, 0)
	3 dup (0, 0)
	4 aload_1 (0, 0)
	5 invokespecial (0, 0)
	6 org/apache/commons/math3/linear/SingularValueDecomposition.<init>:(Lorg/apache/commons/math3/linear/RealMatrix;)V (0, 0)
	8 invokevirtual (0, 0)
	9 org/apache/commons/math3/linear/SingularValueDecomposition.getSolver:()Lorg/apache/commons/math3/linear/DecompositionSolver; (0, 0)
	11 aload_2 (0, 0)
	12 invokeinterface (0, 0)
	13 org/apache/commons/math3/linear/DecompositionSolver.org/apache/commons/math3/fitting/leastsquares/GaussNewtonOptimizer$Decomposition$4 (0, 0)
	15 0 (0, 0)
	17 areturn (0, 0)

