Method: <init>
	0 aload_0 (0, 0)
	1 invokespecial (0, 0)
	2 java/lang/Object.<init>:()V (0, 0)
	4 aload_0 (0, 0)
	5 aload_1 (0, 0)
	6 putfield (0, 0)
	7 org/apache/commons/math3/fitting/leastsquares/GaussNewtonOptimizer.decomposition:Lorg/apache/commons/math3/fitting/leastsquares/GaussNewtonOptimizer$Decomposition; (0, 0)
	9 return (0, 0)

Method: getDecomposition
	0 aload_0 (0, 0)
	1 getfield (0, 0)
	2 org/apache/commons/math3/fitting/leastsquares/GaussNewtonOptimizer.decomposition:Lorg/apache/commons/math3/fitting/leastsquares/GaussNewtonOptimizer$Decomposition; (0, 0)
	4 areturn (0, 0)

Method: withDecomposition
	0 new (0, 0)
	1 org/apache/commons/math3/fitting/leastsquares/GaussNewtonOptimizer (0, 0)
	3 dup (0, 0)
	4 aload_1 (0, 0)
	5 invokespecial (0, 0)
	6 org/apache/commons/math3/fitting/leastsquares/GaussNewtonOptimizer.<init>:(Lorg/apache/commons/math3/fitting/leastsquares/GaussNewtonOptimizer$Decomposition;)V (0, 0)
	8 areturn (0, 0)

Method: optimize
	0 aload_1 (0, 0)
	1 invokeinterface (0, 0)
	2 org/apache/commons/math3/fitting/leastsquares/LeastSquaresProblem.getIterationCounter:()Lorg/apache/commons/math3/util/Incrementor; (0, 0)
	4 0 (0, 0)
	6 astore_2 (0, 0)
	7 aload_1 (0, 0)
	8 invokeinterface (0, 0)
	9 org/apache/commons/math3/fitting/leastsquares/LeastSquaresProblem.getConvergenceChecker:()Lorg/apache/commons/math3/optim/ConvergenceChecker; (0, 0)
	11 0 (0, 0)
	13 astore_3 (0, 0)
	14 aload_1 (0, 0)
	15 invokeinterface (0, 0)
	16 org/apache/commons/math3/fitting/leastsquares/LeastSquaresProblem.org/apache/commons/math3/exception/NullArgumentException (0, 0)
	18 0 (0, 0)
	20 astore (0, 0)
	21 #4 (0, 0)
	22 aload (1, 1)
	23 #4 (1, 1)
	24 ifnonnull (1, 1)
	25 11 (1, 1)
	27 new (1, 1)
	28 org/apache/commons/math3/exception/NullArgumentException (1, 1)
	30 dup (1, 1)
	31 invokespecial (1, 1)
	32 org/apache/commons/math3/exception/NullArgumentException.<init>:()V (1, 1)
	34 athrow (1, 1)
	35 aload_1 (0, 4)
	36 invokeinterface (0, 4)
	37 org/apache/commons/math3/fitting/leastsquares/LeastSquaresProblem.org/apache/commons/math3/util/Incrementor (0, 4)
	39 0 (0, 4)
	41 astore (0, 4)
	42 #5 (0, 4)
	43 aconst_null (0, 4)
	44 astore (0, 4)
	45 #6 (0, 4)
	46 aload_3 (1, 3)
	47 invokevirtual (1, 3)
	48 org/apache/commons/math3/util/Incrementor.incrementCount:()V (1, 3)
	50 aload (1, 3)
	51 #6 (1, 3)
	52 astore (1, 3)
	53 #7 (1, 3)
	54 aload_2 (1, 3)
	55 invokevirtual (1, 3)
	56 org/apache/commons/math3/util/Incrementor.incrementCount:()V (1, 3)
	58 aload_1 (1, 3)
	59 aload (1, 3)
	60 #5 (1, 3)
	61 invokeinterface (1, 3)
	62 org/apache/commons/math3/fitting/leastsquares/LeastSquaresProblem.getResiduals:()Lorg/apache/commons/math3/linear/RealVector; (1, 3)
	64 0 (1, 3)
	66 astore (1, 3)
	67 #6 (1, 3)
	68 aload (1, 3)
	69 #6 (1, 3)
	70 invokeinterface (1, 3)
	71 org/apache/commons/math3/fitting/leastsquares/LeastSquaresProblem$Evaluation.getJacobian:()Lorg/apache/commons/math3/linear/RealMatrix; (1, 3)
	73 0 (1, 3)
	75 astore (1, 3)
	76 #8 (1, 3)
	77 aload (1, 3)
	78 #6 (1, 3)
	79 invokeinterface (1, 3)
	80 org/apache/commons/math3/fitting/leastsquares/LeastSquaresProblem$Evaluation.getPoint:()Lorg/apache/commons/math3/linear/RealVector; (1, 3)
	82 0 (1, 3)
	84 astore (1, 3)
	85 #9 (1, 3)
	86 aload (1, 3)
	87 #6 (1, 3)
	88 invokeinterface (1, 3)
	89 org/apache/commons/math3/fitting/leastsquares/LeastSquaresProblem$Evaluation.getCount:()I (1, 3)
	91 0 (1, 3)
	93 astore (1, 3)
	94 #5 (1, 3)
	95 aload (1, 1)
	96 #7 (1, 1)
	97 ifnull (1, 1)
	98 39 (1, 1)
	100 aload (1, 1)
	101 #4 (1, 1)
	102 aload_3 (1, 1)
	103 invokevirtual (1, 1)
	104 org/apache/commons/math3/util/Incrementor.getCount:()I (1, 1)
	106 aload (1, 1)
	107 #7 (1, 1)
	108 aload (1, 1)
	109 #6 (1, 1)
	110 invokeinterface (1, 1)
	111 org/apache/commons/math3/optim/ConvergenceChecker.org/apache/commons/math3/fitting/leastsquares/OptimumImpl (1, 1)
	113 0 (1, 1)
	115 ifeq (1, 1)
	116 21 (1, 1)
	118 new (1, 1)
	119 org/apache/commons/math3/fitting/leastsquares/OptimumImpl (1, 1)
	121 dup (1, 1)
	122 aload (1, 1)
	123 #6 (1, 1)
	124 aload_2 (1, 1)
	125 invokevirtual (1, 1)
	126 org/apache/commons/math3/util/Incrementor.getCount:()I (1, 1)
	128 aload_3 (1, 1)
	129 invokevirtual (1, 1)
	130 org/apache/commons/math3/util/Incrementor.getCount:()I (1, 1)
	132 invokespecial (1, 1)
	133 org/apache/commons/math3/fitting/leastsquares/OptimumImpl.<init>:(Lorg/apache/commons/math3/fitting/leastsquares/LeastSquaresProblem$Evaluation;II)V (1, 1)
	135 areturn (1, 1)
	136 aload_0 (1, 1)
	137 getfield (1, 1)
	138 org/apache/commons/math3/fitting/leastsquares/GaussNewtonOptimizer.decomposition:Lorg/apache/commons/math3/fitting/leastsquares/GaussNewtonOptimizer$Decomposition; (1, 1)
	140 aload (1, 1)
	141 #9 (1, 1)
	142 aload (1, 1)
	143 #8 (1, 1)
	144 invokevirtual (1, 1)
	145 org/apache/commons/math3/fitting/leastsquares/GaussNewtonOptimizer$Decomposition.solve:(Lorg/apache/commons/math3/linear/RealMatrix;Lorg/apache/commons/math3/linear/RealVector;)Lorg/apache/commons/math3/linear/RealVector; (1, 1)
	147 astore (1, 1)
	148 #10 (1, 1)
	149 aload (1, 1)
	150 #5 (1, 1)
	151 aload (1, 1)
	152 #10 (1, 1)
	153 invokevirtual (1, 1)
	154 org/apache/commons/math3/linear/RealVector.add:(Lorg/apache/commons/math3/linear/RealVector;)Lorg/apache/commons/math3/linear/RealVector; (1, 1)
	156 astore (1, 1)
	157 #5 (1, 1)
	158 goto (0, 4)
	159 -112 (0, 4)

Method: toString
	0 new (0, 0)
	1 java/lang/StringBuilder (0, 0)
	3 dup (0, 0)
	4 invokespecial (0, 0)
	5 java/lang/StringBuilder.<init>:()V (0, 0)
	7 ldc (0, 0)
	8 GaussNewtonOptimizer{decomposition= (0, 0)
	9 invokevirtual (0, 0)
	10 java/lang/StringBuilder.append:(Ljava/lang/String;)Ljava/lang/StringBuilder; (0, 0)
	12 aload_0 (0, 0)
	13 getfield (0, 0)
	14 org/apache/commons/math3/fitting/leastsquares/GaussNewtonOptimizer.decomposition:Lorg/apache/commons/math3/fitting/leastsquares/GaussNewtonOptimizer$Decomposition; (0, 0)
	16 invokevirtual (0, 0)
	17 java/lang/StringBuilder.append:(Ljava/lang/Object;)Ljava/lang/StringBuilder; (0, 0)
	19 bipush (0, 0)
	20 125 (0, 0)
	21 invokevirtual (0, 0)
	22 java/lang/StringBuilder.append:(C)Ljava/lang/StringBuilder; (0, 0)
	24 invokevirtual (0, 0)
	25 java/lang/StringBuilder.toString:()Ljava/lang/String; (0, 0)
	27 areturn (0, 0)

Method: computeNormalMatrix
	0 aload_0 (0, 0)
	1 invokeinterface (0, 0)
	2 org/apache/commons/math3/linear/RealMatrix.getColumnDimension:()I (0, 0)
	4 0 (0, 0)
	6 istore_2 (0, 0)
	7 aload_0 (0, 0)
	8 invokeinterface (0, 0)
	9 org/apache/commons/math3/linear/RealMatrix.org/apache/commons/math3/linear/MatrixUtils (0, 0)
	11 0 (0, 0)
	13 istore_3 (0, 0)
	14 iload_3 (0, 4)
	15 iload_3 (0, 4)
	16 invokestatic (0, 4)
	17 org/apache/commons/math3/linear/MatrixUtils.createRealMatrix:(II)Lorg/apache/commons/math3/linear/RealMatrix; (0, 4)
	19 astore (0, 4)
	20 #4 (0, 4)
	21 new (0, 4)
	22 org/apache/commons/math3/linear/ArrayRealVector (0, 4)
	24 dup (0, 4)
	25 iload_3 (0, 4)
	26 invokespecial (0, 4)
	27 org/apache/commons/math3/linear/ArrayRealVector.<init>:(I)V (0, 4)
	29 astore (0, 4)
	30 #5 (0, 4)
	31 iconst_0 (1, 4)
	32 istore (1, 4)
	33 #6 (1, 4)
	34 iload (1, 4)
	35 #6 (1, 4)
	36 iload_2 (1, 4)
	37 if_icmpge (1, 4)
	38 131 (1, 4)
	40 iconst_0 (2, 4)
	41 istore (2, 4)
	42 #7 (2, 4)
	43 iload (2, 4)
	44 #7 (2, 4)
	45 iload_3 (2, 4)
	46 if_icmpge (2, 4)
	47 41 (2, 4)
	49 aload (2, 4)
	50 #5 (2, 4)
	51 iload (2, 4)
	52 #7 (2, 4)
	53 aload (2, 4)
	54 #5 (2, 4)
	55 iload (2, 4)
	56 #7 (2, 4)
	57 invokevirtual (2, 4)
	58 org/apache/commons/math3/linear/RealVector.getEntry:(I)D (2, 4)
	60 aload_1 (2, 4)
	61 iload (2, 4)
	62 #6 (2, 4)
	63 invokevirtual (2, 4)
	64 org/apache/commons/math3/linear/RealVector.getEntry:(I)D (2, 4)
	66 aload_0 (2, 4)
	67 iload (2, 4)
	68 #6 (2, 4)
	69 iload (2, 4)
	70 #7 (2, 4)
	71 invokeinterface (2, 4)
	72 org/apache/commons/math3/linear/RealMatrix.setEntry:(ID)V (2, 4)
	74 0 (2, 4)
	76 dmul (2, 4)
	77 dadd (2, 4)
	78 invokevirtual (2, 4)
	79 org/apache/commons/math3/linear/RealVector.setEntry:(ID)V (2, 4)
	81 iinc (2, 4)
	82 #7 (2, 4)
	83 -89 (2, 4)
	84 goto (2, 4)
	85 -41 (2, 4)
	87 iconst_0 (2, 4)
	88 istore (2, 4)
	89 #7 (2, 4)
	90 iload (2, 4)
	91 #7 (2, 4)
	92 iload_3 (2, 4)
	93 if_icmpge (2, 4)
	94 69 (2, 4)
	96 iload (3, 4)
	97 #7 (3, 4)
	98 istore (3, 4)
	99 #8 (3, 4)
	100 iload (3, 4)
	101 #8 (3, 4)
	102 iload_3 (3, 4)
	103 if_icmpge (3, 4)
	104 53 (3, 4)
	106 aload (3, 4)
	107 #4 (3, 4)
	108 iload (3, 4)
	109 #7 (3, 4)
	110 iload (3, 4)
	111 #8 (3, 4)
	112 aload (3, 4)
	113 #4 (3, 4)
	114 iload (3, 4)
	115 #7 (3, 4)
	116 iload (3, 4)
	117 #8 (3, 4)
	118 invokeinterface (3, 4)
	119 org/apache/commons/math3/linear/RealMatrix.setEntry:(ID)V (3, 4)
	121 0 (3, 4)
	123 aload_0 (3, 4)
	124 iload (3, 4)
	125 #6 (3, 4)
	126 iload (3, 4)
	127 #7 (3, 4)
	128 invokeinterface (3, 4)
	129 org/apache/commons/math3/linear/RealMatrix.setEntry:(ID)V (3, 4)
	131 0 (3, 4)
	133 aload_0 (3, 4)
	134 iload (3, 4)
	135 #6 (3, 4)
	136 iload (3, 4)
	137 #8 (3, 4)
	138 invokeinterface (3, 4)
	139 org/apache/commons/math3/linear/RealMatrix.setEntry:(ID)V (3, 4)
	141 0 (3, 4)
	143 dmul (3, 4)
	144 dadd (3, 4)
	145 invokeinterface (3, 4)
	146 org/apache/commons/math3/linear/RealMatrix.org/apache/commons/math3/util/Pair (3, 4)
	148 0 (3, 4)
	150 iinc (3, 4)
	151 #8 (3, 4)
	152 -89 (3, 4)
	153 goto (3, 4)
	154 -53 (3, 4)
	156 iinc (3, 4)
	157 #7 (3, 4)
	158 -89 (3, 4)
	159 goto (3, 4)
	160 -69 (3, 4)
	162 iinc (3, 4)
	163 #6 (3, 4)
	164 -89 (3, 4)
	165 goto (3, 4)
	166 -131 (3, 4)
	168 iconst_0 (3, 4)
	169 istore (3, 4)
	170 #6 (3, 4)
	171 iload (3, 4)
	172 #6 (3, 4)
	173 iload_3 (3, 4)
	174 if_icmpge (3, 4)
	175 47 (3, 4)
	177 iconst_0 (4, 4)
	178 istore (4, 4)
	179 #7 (4, 4)
	180 iload (4, 4)
	181 #7 (4, 4)
	182 iload (4, 4)
	183 #6 (4, 4)
	184 if_icmpge (4, 4)
	185 31 (4, 4)
	187 aload (4, 4)
	188 #4 (4, 4)
	189 iload (4, 4)
	190 #6 (4, 4)
	191 iload (4, 4)
	192 #7 (4, 4)
	193 aload (4, 4)
	194 #4 (4, 4)
	195 iload (4, 4)
	196 #7 (4, 4)
	197 iload (4, 4)
	198 #6 (4, 4)
	199 invokeinterface (4, 4)
	200 org/apache/commons/math3/linear/RealMatrix.setEntry:(ID)V (4, 4)
	202 0 (4, 4)
	204 invokeinterface (4, 4)
	205 org/apache/commons/math3/linear/RealMatrix.org/apache/commons/math3/util/Pair (4, 4)
	207 0 (4, 4)
	209 iinc (4, 4)
	210 #7 (4, 4)
	211 -89 (4, 4)
	212 goto (4, 4)
	213 -32 (4, 4)
	215 iinc (4, 4)
	216 #6 (4, 4)
	217 -89 (4, 4)
	218 goto (4, 4)
	219 -47 (4, 4)
	221 new (3, 4)
	222 org/apache/commons/math3/util/Pair (3, 4)
	224 dup (3, 4)
	225 aload (3, 4)
	226 #4 (3, 4)
	227 aload (3, 4)
	228 #5 (3, 4)
	229 invokespecial (3, 4)
	230 org/apache/commons/math3/util/Pair.<init>:(Ljava/lang/Object;Ljava/lang/Object;)V (3, 4)
	232 areturn (3, 4)

Method: access$100
	0 aload_0 (0, 0)
	1 aload_1 (0, 0)
	2 invokestatic (0, 0)
	3 org/apache/commons/math3/fitting/leastsquares/GaussNewtonOptimizer.computeNormalMatrix:(Lorg/apache/commons/math3/linear/RealMatrix;Lorg/apache/commons/math3/linear/RealVector;)Lorg/apache/commons/math3/util/Pair; (0, 0)
	5 areturn (0, 0)

