Method: solve
	0 new (0, 0)
	1 org/apache/commons/math3/linear/QRDecomposition (0, 0)
	3 dup (0, 0)
	4 aload_1 (0, 0)
	5 ldc2_w (0, 0)
	6 1e-11 (0, 0)
	8 invokespecial (0, 0)
	9 org/apache/commons/math3/linear/QRDecomposition.<init>:(Lorg/apache/commons/math3/linear/RealMatrix;D)V (0, 0)
	11 invokevirtual (0, 0)
	12 org/apache/commons/math3/linear/QRDecomposition.getSolver:()Lorg/apache/commons/math3/linear/DecompositionSolver; (0, 0)
	14 aload_2 (0, 0)
	15 invokeinterface (0, 0)
	16 org/apache/commons/math3/linear/DecompositionSolver.org/apache/commons/math3/linear/SingularMatrixException (0, 0)
	18 0 (0, 0)
	20 areturn (0, 0)
	21 astore_3 (0, 0)
	22 new (0, 0)
	23 org/apache/commons/math3/exception/ConvergenceException (0, 0)
	25 dup (0, 0)
	26 getstatic (0, 0)
	27 org/apache/commons/math3/exception/util/LocalizedFormats.UNABLE_TO_SOLVE_SINGULAR_PROBLEM:Lorg/apache/commons/math3/exception/util/LocalizedFormats; (0, 0)
	29 iconst_1 (0, 0)
	30 anewarray (0, 0)
	31 java/lang/Object (0, 0)
	33 dup (0, 0)
	34 iconst_0 (0, 0)
	35 aload_3 (0, 0)
	36 aastore (0, 0)
	37 invokespecial (0, 0)
	38 org/apache/commons/math3/exception/ConvergenceException.<init>:(Lorg/apache/commons/math3/exception/util/Localizable;[Ljava/lang/Object;)V (0, 0)
	40 athrow (0, 0)

