Method: <init>
	0 aload_0 (0, 0)
	1 invokespecial (0, 0)
	2 java/lang/Object.<init>:()V (0, 0)
	4 aload_0 (0, 0)
	5 aload_1 (0, 0)
	6 putfield (0, 0)
	7 org/apache/commons/math3/fitting/leastsquares/LeastSquaresAdapter.problem:Lorg/apache/commons/math3/fitting/leastsquares/LeastSquaresProblem; (0, 0)
	9 return (0, 0)

Method: getStart
	0 aload_0 (0, 0)
	1 getfield (0, 0)
	2 org/apache/commons/math3/fitting/leastsquares/LeastSquaresAdapter.problem:Lorg/apache/commons/math3/fitting/leastsquares/LeastSquaresProblem; (0, 0)
	4 invokeinterface (0, 0)
	5 org/apache/commons/math3/fitting/leastsquares/LeastSquaresProblem.getObservationSize:()I (0, 0)
	7 0 (0, 0)
	9 areturn (0, 0)

Method: getObservationSize
	0 aload_0 (0, 0)
	1 getfield (0, 0)
	2 org/apache/commons/math3/fitting/leastsquares/LeastSquaresAdapter.problem:Lorg/apache/commons/math3/fitting/leastsquares/LeastSquaresProblem; (0, 0)
	4 invokeinterface (0, 0)
	5 org/apache/commons/math3/fitting/leastsquares/LeastSquaresProblem.getParameterSize:()I (0, 0)
	7 0 (0, 0)
	9 ireturn (0, 0)

Method: getParameterSize
	0 aload_0 (0, 0)
	1 getfield (0, 0)
	2 org/apache/commons/math3/fitting/leastsquares/LeastSquaresAdapter.problem:Lorg/apache/commons/math3/fitting/leastsquares/LeastSquaresProblem; (0, 0)
	4 invokeinterface (0, 0)
	5 org/apache/commons/math3/fitting/leastsquares/LeastSquaresProblem.evaluate:(Lorg/apache/commons/math3/linear/RealVector;)Lorg/apache/commons/math3/fitting/leastsquares/LeastSquaresProblem$Evaluation; (0, 0)
	7 0 (0, 0)
	9 ireturn (0, 0)

Method: evaluate
	0 aload_0 (0, 0)
	1 getfield (0, 0)
	2 org/apache/commons/math3/fitting/leastsquares/LeastSquaresAdapter.problem:Lorg/apache/commons/math3/fitting/leastsquares/LeastSquaresProblem; (0, 0)
	4 aload_1 (0, 0)
	5 invokeinterface (0, 0)
	6 org/apache/commons/math3/fitting/leastsquares/LeastSquaresProblem.getEvaluationCounter:()Lorg/apache/commons/math3/util/Incrementor; (0, 0)
	8 0 (0, 0)
	10 areturn (0, 0)

Method: getEvaluationCounter
	0 aload_0 (0, 0)
	1 getfield (0, 0)
	2 org/apache/commons/math3/fitting/leastsquares/LeastSquaresAdapter.problem:Lorg/apache/commons/math3/fitting/leastsquares/LeastSquaresProblem; (0, 0)
	4 invokeinterface (0, 0)
	5 org/apache/commons/math3/fitting/leastsquares/LeastSquaresProblem.getIterationCounter:()Lorg/apache/commons/math3/util/Incrementor; (0, 0)
	7 0 (0, 0)
	9 areturn (0, 0)

Method: getIterationCounter
	0 aload_0 (0, 0)
	1 getfield (0, 0)
	2 org/apache/commons/math3/fitting/leastsquares/LeastSquaresAdapter.problem:Lorg/apache/commons/math3/fitting/leastsquares/LeastSquaresProblem; (0, 0)
	4 invokeinterface (0, 0)
	5 org/apache/commons/math3/fitting/leastsquares/LeastSquaresProblem.getConvergenceChecker:()Lorg/apache/commons/math3/optim/ConvergenceChecker; (0, 0)
	7 0 (0, 0)
	9 areturn (0, 0)

Method: getConvergenceChecker
	0 aload_0 (0, 0)
	1 getfield (0, 0)
	2 org/apache/commons/math3/fitting/leastsquares/LeastSquaresAdapter.problem:Lorg/apache/commons/math3/fitting/leastsquares/LeastSquaresProblem; (0, 0)
	4 invokeinterface (0, 0)
	5 org/apache/commons/math3/fitting/leastsquares/LeastSquaresProblem.org/apache/commons/math3/fitting/leastsquares/LeastSquaresAdapter (0, 0)
	7 0 (0, 0)
	9 areturn (0, 0)

