Method: <init>
	0 aload_0 (0, 0)
	1 aload_2 (0, 0)
	2 invokevirtual (0, 0)
	3 org/apache/commons/math3/linear/RealVector.getDimension:()I (0, 0)
	5 invokespecial (0, 0)
	6 org/apache/commons/math3/fitting/leastsquares/AbstractEvaluation.<init>:(I)V (0, 0)
	8 aload_0 (0, 0)
	9 aload_1 (0, 0)
	10 putfield (0, 0)
	11 org/apache/commons/math3/fitting/leastsquares/LeastSquaresFactory$LocalLeastSquaresProblem$LazyUnweightedEvaluation.model:Lorg/apache/commons/math3/fitting/leastsquares/ValueAndJacobianFunction; (0, 0)
	13 aload_0 (0, 0)
	14 aload_3 (0, 0)
	15 putfield (0, 0)
	16 org/apache/commons/math3/fitting/leastsquares/LeastSquaresFactory$LocalLeastSquaresProblem$LazyUnweightedEvaluation.point:Lorg/apache/commons/math3/linear/RealVector; (0, 0)
	18 aload_0 (0, 0)
	19 aload_2 (0, 0)
	20 putfield (0, 0)
	21 org/apache/commons/math3/fitting/leastsquares/LeastSquaresFactory$LocalLeastSquaresProblem$LazyUnweightedEvaluation.target:Lorg/apache/commons/math3/linear/RealVector; (0, 0)
	23 return (0, 0)

Method: getJacobian
	0 aload_0 (0, 0)
	1 getfield (0, 0)
	2 org/apache/commons/math3/fitting/leastsquares/LeastSquaresFactory$LocalLeastSquaresProblem$LazyUnweightedEvaluation.model:Lorg/apache/commons/math3/fitting/leastsquares/ValueAndJacobianFunction; (0, 0)
	4 aload_0 (0, 0)
	5 getfield (0, 0)
	6 org/apache/commons/math3/fitting/leastsquares/LeastSquaresFactory$LocalLeastSquaresProblem$LazyUnweightedEvaluation.point:Lorg/apache/commons/math3/linear/RealVector; (0, 0)
	8 invokevirtual (0, 0)
	9 org/apache/commons/math3/linear/RealVector.toArray:()[D (0, 0)
	11 invokeinterface (0, 0)
	12 org/apache/commons/math3/fitting/leastsquares/ValueAndJacobianFunction.computeValue:([D)Lorg/apache/commons/math3/linear/RealVector; (0, 0)
	14 0 (0, 0)
	16 areturn (0, 0)

Method: getPoint
	0 aload_0 (0, 0)
	1 getfield (0, 0)
	2 org/apache/commons/math3/fitting/leastsquares/LeastSquaresFactory$LocalLeastSquaresProblem$LazyUnweightedEvaluation.point:Lorg/apache/commons/math3/linear/RealVector; (0, 0)
	4 areturn (0, 0)

Method: getResiduals
	0 aload_0 (0, 0)
	1 getfield (0, 0)
	2 org/apache/commons/math3/fitting/leastsquares/LeastSquaresFactory$LocalLeastSquaresProblem$LazyUnweightedEvaluation.target:Lorg/apache/commons/math3/linear/RealVector; (0, 0)
	4 aload_0 (0, 0)
	5 getfield (0, 0)
	6 org/apache/commons/math3/fitting/leastsquares/LeastSquaresFactory$LocalLeastSquaresProblem$LazyUnweightedEvaluation.model:Lorg/apache/commons/math3/fitting/leastsquares/ValueAndJacobianFunction; (0, 0)
	8 aload_0 (0, 0)
	9 getfield (0, 0)
	10 org/apache/commons/math3/fitting/leastsquares/LeastSquaresFactory$LocalLeastSquaresProblem$LazyUnweightedEvaluation.point:Lorg/apache/commons/math3/linear/RealVector; (0, 0)
	12 invokevirtual (0, 0)
	13 org/apache/commons/math3/linear/RealVector.toArray:()[D (0, 0)
	15 invokeinterface (0, 0)
	16 org/apache/commons/math3/fitting/leastsquares/ValueAndJacobianFunction.subtract:(Lorg/apache/commons/math3/linear/RealVector;)Lorg/apache/commons/math3/linear/RealVector; (0, 0)
	18 0 (0, 0)
	20 invokevirtual (0, 0)
	21 org/apache/commons/math3/linear/RealVector.subtract:(Lorg/apache/commons/math3/linear/RealVector;)Lorg/apache/commons/math3/linear/RealVector; (0, 0)
	23 areturn (0, 0)

