Method: create
	0 aload_0 (0, 0)
	1 aload_1 (0, 0)
	2 invokestatic (0, 0)
	5 new (0, 0)
	8 dup (0, 0)
	9 aload_2 (0, 0)
	10 iconst_0 (0, 0)
	11 invokespecial (0, 0)
	14 new (0, 0)
	17 dup (0, 0)
	18 aload_3 (0, 0)
	19 iconst_0 (0, 0)
	20 invokespecial (0, 0)
	23 aload (0, 0)
	25 aload (0, 0)
	27 iload (0, 0)
	29 iload (0, 0)
	31 invokestatic (0, 0)
	34 areturn (0, 0)

Method: weightMatrix
	0 aload_1 (0, 0)
	1 invokestatic (0, 0)
	4 astore_2 (0, 0)
	5 new (0, 0)
	8 dup (0, 0)
	9 aload_0 (0, 0)
	10 aload_2 (0, 0)
	11 invokespecial (0, 0)
	14 areturn (0, 0)

Method: weightDiagonal
	0 aload_0 (0, 0)
	1 new (0, 0)
	4 dup (0, 0)
	5 aload_1 (0, 0)
	6 invokevirtual (0, 0)
	9 invokespecial (0, 0)
	12 invokestatic (0, 0)
	15 areturn (0, 0)

Method: countEvaluations
	0 new (0, 0)
	3 dup (0, 0)
	4 aload_0 (0, 0)
	5 aload_1 (0, 0)
	6 invokespecial (0, 0)
	9 areturn (0, 0)

Method: evaluationChecker
	0 new (0, 0)
	3 dup (0, 0)
	4 aload_0 (0, 0)
	5 invokespecial (0, 0)
	8 areturn (0, 0)

Method: squareRoot
	0 aload_0 (1, 1)
	1 instanceof (1, 1)
	4 ifeq (1, 1)
	7 aload_0 (1, 1)
	8 invokeinterface (1, 1)
	13 istore_1 (1, 1)
	14 new (1, 1)
	17 dup (1, 1)
	18 iload_1 (1, 1)
	19 invokespecial (1, 1)
	22 astore_2 (1, 1)
	23 iconst_0 (2, 4)
	24 istore_3 (2, 4)
	25 iload_3 (2, 4)
	26 iload_1 (2, 4)
	27 if_icmpge (2, 4)
	30 aload_2 (2, 4)
	31 iload_3 (2, 4)
	32 iload_3 (2, 4)
	33 aload_0 (2, 4)
	34 iload_3 (2, 4)
	35 iload_3 (2, 4)
	36 invokeinterface (2, 4)
	41 invokestatic (2, 4)
	44 invokeinterface (2, 4)
	49 iinc (2, 4)
	52 goto (2, 4)
	55 aload_2 (1, 1)
	56 areturn (1, 1)
	57 new (1, 2)
	60 dup (1, 2)
	61 aload_0 (1, 2)
	62 invokespecial (1, 2)
	65 astore_1 (1, 2)
	66 aload_1 (1, 2)
	67 invokevirtual (1, 2)
	70 areturn (1, 2)

Method: model
	0 new (0, 0)
	3 dup (0, 0)
	4 aload_0 (0, 0)
	5 aload_1 (0, 0)
	6 invokespecial (0, 0)
	9 areturn (0, 0)

