Method: <init>
	0 aload_0 (0, 0)
	1 invokespecial (0, 0)
	4 aload_0 (0, 0)
	5 aload_1 (0, 0)
	6 putfield (0, 0)
	9 aload_0 (0, 0)
	10 aload_2 (0, 0)
	11 putfield (0, 0)
	14 return (0, 0)

Method: value
	0 aload_1 (0, 0)
	1 invokevirtual (0, 0)
	4 astore_2 (0, 0)
	5 new (0, 0)
	8 dup (0, 0)
	9 aload_0 (0, 0)
	10 aload_2 (0, 0)
	11 invokevirtual (0, 0)
	14 aload_0 (0, 0)
	15 aload_2 (0, 0)
	16 invokevirtual (0, 0)
	19 invokespecial (0, 0)
	22 areturn (0, 0)

Method: computeValue
	0 new (0, 0)
	3 dup (0, 0)
	4 aload_0 (0, 0)
	5 getfield (0, 0)
	8 aload_1 (0, 0)
	9 invokeinterface (0, 0)
	14 iconst_0 (0, 0)
	15 invokespecial (0, 0)
	18 areturn (0, 0)

Method: computeJacobian
	0 new (0, 0)
	3 dup (0, 0)
	4 aload_0 (0, 0)
	5 getfield (0, 0)
	8 aload_1 (0, 0)
	9 invokeinterface (0, 0)
	14 iconst_0 (0, 0)
	15 invokespecial (0, 0)
	18 areturn (0, 0)

