Method: <init>
	0 aload_0 (0, 0)
	1 iload (0, 0)
	3 iload (0, 0)
	5 aload (0, 0)
	7 invokespecial (0, 0)
	10 aload_0 (0, 0)
	11 aload_2 (0, 0)
	12 putfield (0, 0)
	15 aload_0 (0, 0)
	16 aload_1 (0, 0)
	17 putfield (0, 0)
	20 aload_0 (0, 0)
	21 aload_3 (0, 0)
	22 putfield (0, 0)
	25 aload_0 (0, 0)
	26 iload (0, 0)
	28 putfield (0, 0)
	31 aload_0 (0, 0)
	32 aload (0, 0)
	34 putfield (0, 0)
	37 iload (0, 1)
	39 ifeq (0, 1)
	42 aload_1 (0, 1)
	43 instanceof (0, 1)
	46 ifne (0, 1)
	49 new (1, 1)
	52 dup (1, 1)
	53 getstatic (1, 1)
	56 iconst_1 (1, 1)
	57 anewarray (1, 1)
	60 dup (1, 1)
	61 iconst_0 (1, 1)
	62 aload_1 (1, 1)
	63 invokevirtual (1, 1)
	66 invokevirtual (1, 1)
	69 aastore (1, 1)
	70 invokespecial (1, 1)
	73 athrow (1, 1)
	74 return (0, 0)

Method: getObservationSize
	0 aload_0 (0, 0)
	1 getfield (0, 0)
	4 invokevirtual (0, 0)
	7 ireturn (0, 0)

Method: getParameterSize
	0 aload_0 (0, 0)
	1 getfield (0, 0)
	4 invokevirtual (0, 0)
	7 ireturn (0, 0)

Method: getStart
	0 aload_0 (0, 0)
	1 getfield (0, 0)
	4 ifnonnull (0, 0)
	7 aconst_null (0, 0)
	8 goto (0, 0)
	11 aload_0 (0, 0)
	12 getfield (0, 0)
	15 invokevirtual (0, 0)
	18 areturn (0, 0)

Method: evaluate
	0 aload_0 (0, 0)
	1 getfield (0, 0)
	4 ifnonnull (0, 0)
	7 aload_1 (0, 0)
	8 invokevirtual (0, 0)
	11 goto (0, 0)
	14 aload_0 (0, 0)
	15 getfield (0, 0)
	18 aload_1 (0, 0)
	19 invokevirtual (0, 0)
	22 invokeinterface (0, 0)
	27 astore_2 (0, 0)
	28 aload_0 (1, 1)
	29 getfield (1, 1)
	32 ifeq (1, 1)
	35 new (1, 1)
	38 dup (1, 1)
	39 aload_0 (1, 1)
	40 getfield (1, 1)
	43 checkcast (1, 1)
	46 aload_0 (1, 1)
	47 getfield (1, 1)
	50 aload_2 (1, 1)
	51 aconst_null (1, 1)
	52 invokespecial (1, 1)
	55 areturn (1, 1)
	56 aload_0 (1, 2)
	57 getfield (1, 2)
	60 aload_2 (1, 2)
	61 invokeinterface (1, 2)
	66 astore_3 (1, 2)
	67 new (1, 2)
	70 dup (1, 2)
	71 aload_3 (1, 2)
	72 invokevirtual (1, 2)
	75 checkcast (1, 2)
	78 aload_3 (1, 2)
	79 invokevirtual (1, 2)
	82 checkcast (1, 2)
	85 aload_0 (1, 2)
	86 getfield (1, 2)
	89 aload_2 (1, 2)
	90 aconst_null (1, 2)
	91 invokespecial (1, 2)
	94 areturn (1, 2)

