Method: create
	0 aload_0 (0, 0)
	1 aload_1 (0, 0)
	2 invokestatic (0, 0)
	3 org/apache/commons/math3/fitting/leastsquares/LeastSquaresFactory.model:(Lorg/apache/commons/math3/analysis/MultivariateVectorFunction;Lorg/apache/commons/math3/analysis/MultivariateMatrixFunction;)Lorg/apache/commons/math3/fitting/leastsquares/MultivariateJacobianFunction; (0, 0)
	5 new (0, 0)
	6 org/apache/commons/math3/linear/ArrayRealVector (0, 0)
	8 dup (0, 0)
	9 aload_2 (0, 0)
	10 iconst_0 (0, 0)
	11 invokespecial (0, 0)
	12 org/apache/commons/math3/linear/ArrayRealVector.<init>:([DZ)V (0, 0)
	14 new (0, 0)
	15 org/apache/commons/math3/linear/ArrayRealVector (0, 0)
	17 dup (0, 0)
	18 aload_3 (0, 0)
	19 iconst_0 (0, 0)
	20 invokespecial (0, 0)
	21 org/apache/commons/math3/linear/ArrayRealVector.<init>:([DZ)V (0, 0)
	23 aload (0, 0)
	24 #4 (0, 0)
	25 aload (0, 0)
	26 #5 (0, 0)
	27 iload (0, 0)
	28 #6 (0, 0)
	29 iload (0, 0)
	30 #7 (0, 0)
	31 invokestatic (0, 0)
	32 org/apache/commons/math3/fitting/leastsquares/LeastSquaresFactory.create:(Lorg/apache/commons/math3/fitting/leastsquares/MultivariateJacobianFunction;Lorg/apache/commons/math3/linear/RealVector;Lorg/apache/commons/math3/linear/RealVector;Lorg/apache/commons/math3/linear/RealMatrix;Lorg/apache/commons/math3/optim/ConvergenceChecker;II)Lorg/apache/commons/math3/fitting/leastsquares/LeastSquaresProblem; (0, 0)
	34 areturn (0, 0)

Method: weightMatrix
	0 aload_1 (0, 0)
	1 invokestatic (0, 0)
	2 org/apache/commons/math3/fitting/leastsquares/LeastSquaresFactory.squareRoot:(Lorg/apache/commons/math3/linear/RealMatrix;)Lorg/apache/commons/math3/linear/RealMatrix; (0, 0)
	4 astore_2 (0, 0)
	5 new (0, 0)
	6 org/apache/commons/math3/fitting/leastsquares/LeastSquaresFactory$1 (0, 0)
	8 dup (0, 0)
	9 aload_0 (0, 0)
	10 aload_2 (0, 0)
	11 invokespecial (0, 0)
	12 org/apache/commons/math3/fitting/leastsquares/LeastSquaresFactory$1.<init>:(Lorg/apache/commons/math3/fitting/leastsquares/LeastSquaresProblem;Lorg/apache/commons/math3/linear/RealMatrix;)V (0, 0)
	14 areturn (0, 0)

Method: weightDiagonal
	0 aload_0 (0, 0)
	1 new (0, 0)
	2 org/apache/commons/math3/linear/DiagonalMatrix (0, 0)
	4 dup (0, 0)
	5 aload_1 (0, 0)
	6 invokevirtual (0, 0)
	7 org/apache/commons/math3/linear/RealVector.toArray:()[D (0, 0)
	9 invokespecial (0, 0)
	10 org/apache/commons/math3/linear/DiagonalMatrix.<init>:([D)V (0, 0)
	12 invokestatic (0, 0)
	13 org/apache/commons/math3/fitting/leastsquares/LeastSquaresFactory.weightMatrix:(Lorg/apache/commons/math3/fitting/leastsquares/LeastSquaresProblem;Lorg/apache/commons/math3/linear/RealMatrix;)Lorg/apache/commons/math3/fitting/leastsquares/LeastSquaresProblem; (0, 0)
	15 areturn (0, 0)

Method: countEvaluations
	0 new (0, 0)
	1 org/apache/commons/math3/fitting/leastsquares/LeastSquaresFactory$2 (0, 0)
	3 dup (0, 0)
	4 aload_0 (0, 0)
	5 aload_1 (0, 0)
	6 invokespecial (0, 0)
	7 org/apache/commons/math3/fitting/leastsquares/LeastSquaresFactory$2.<init>:(Lorg/apache/commons/math3/fitting/leastsquares/LeastSquaresProblem;Lorg/apache/commons/math3/util/Incrementor;)V (0, 0)
	9 areturn (0, 0)

Method: evaluationChecker
	0 new (0, 0)
	1 org/apache/commons/math3/fitting/leastsquares/LeastSquaresFactory$3 (0, 0)
	3 dup (0, 0)
	4 aload_0 (0, 0)
	5 invokespecial (0, 0)
	6 org/apache/commons/math3/fitting/leastsquares/LeastSquaresFactory$3.<init>:(Lorg/apache/commons/math3/optim/ConvergenceChecker;)V (0, 0)
	8 areturn (0, 0)

Method: squareRoot
	0 aload_0 (1, 1)
	1 instanceof (1, 1)
	2 org/apache/commons/math3/linear/DiagonalMatrix (1, 1)
	4 ifeq (1, 1)
	5 53 (1, 1)
	7 aload_0 (1, 1)
	8 invokeinterface (1, 1)
	9 org/apache/commons/math3/linear/RealMatrix.<init>:(I)V (1, 1)
	11 0 (1, 1)
	13 istore_1 (1, 1)
	14 new (1, 1)
	15 org/apache/commons/math3/linear/DiagonalMatrix (1, 1)
	17 dup (1, 1)
	18 iload_1 (1, 1)
	19 invokespecial (1, 1)
	20 org/apache/commons/math3/linear/DiagonalMatrix.<init>:(I)V (1, 1)
	22 astore_2 (1, 1)
	23 iconst_0 (2, 4)
	24 istore_3 (2, 4)
	25 iload_3 (2, 4)
	26 iload_1 (2, 4)
	27 if_icmpge (2, 4)
	28 28 (2, 4)
	30 aload_2 (2, 4)
	31 iload_3 (2, 4)
	32 iload_3 (2, 4)
	33 aload_0 (2, 4)
	34 iload_3 (2, 4)
	35 iload_3 (2, 4)
	36 invokeinterface (2, 4)
	37 org/apache/commons/math3/linear/RealMatrix.org/apache/commons/math3/util/FastMath (2, 4)
	39 0 (2, 4)
	41 invokestatic (2, 4)
	42 org/apache/commons/math3/util/FastMath.sqrt:(D)D (2, 4)
	44 invokeinterface (2, 4)
	45 org/apache/commons/math3/linear/RealMatrix.org/apache/commons/math3/linear/EigenDecomposition (2, 4)
	47 0 (2, 4)
	49 iinc (2, 4)
	50 #3 (2, 4)
	51 -89 (2, 4)
	52 goto (2, 4)
	53 -27 (2, 4)
	55 aload_2 (1, 1)
	56 areturn (1, 1)
	57 new (1, 2)
	58 org/apache/commons/math3/linear/EigenDecomposition (1, 2)
	60 dup (1, 2)
	61 aload_0 (1, 2)
	62 invokespecial (1, 2)
	63 org/apache/commons/math3/linear/EigenDecomposition.<init>:(Lorg/apache/commons/math3/linear/RealMatrix;)V (1, 2)
	65 astore_1 (1, 2)
	66 aload_1 (1, 2)
	67 invokevirtual (1, 2)
	68 org/apache/commons/math3/linear/EigenDecomposition.getSquareRoot:()Lorg/apache/commons/math3/linear/RealMatrix; (1, 2)
	70 areturn (1, 2)

Method: model
	0 new (0, 0)
	1 org/apache/commons/math3/fitting/leastsquares/LeastSquaresFactory$LocalValueAndJacobianFunction (0, 0)
	3 dup (0, 0)
	4 aload_0 (0, 0)
	5 aload_1 (0, 0)
	6 invokespecial (0, 0)
	7 org/apache/commons/math3/fitting/leastsquares/LeastSquaresFactory$LocalValueAndJacobianFunction.<init>:(Lorg/apache/commons/math3/analysis/MultivariateVectorFunction;Lorg/apache/commons/math3/analysis/MultivariateMatrixFunction;)V (0, 0)
	9 areturn (0, 0)

