Method: <init>
	0 aload_0 (0, 0)
	1 iload (0, 0)
	2 #5 (0, 0)
	3 iload (0, 0)
	4 #6 (0, 0)
	5 aload (0, 0)
	6 #4 (0, 0)
	7 invokespecial (0, 0)
	8 org/apache/commons/math3/optim/AbstractOptimizationProblem.<init>:(IILorg/apache/commons/math3/optim/ConvergenceChecker;)V (0, 0)
	10 aload_0 (0, 0)
	11 aload_2 (0, 0)
	12 putfield (0, 0)
	13 org/apache/commons/math3/fitting/leastsquares/LeastSquaresFactory$LocalLeastSquaresProblem.target:Lorg/apache/commons/math3/linear/RealVector; (0, 0)
	15 aload_0 (0, 0)
	16 aload_1 (0, 0)
	17 putfield (0, 0)
	18 org/apache/commons/math3/fitting/leastsquares/LeastSquaresFactory$LocalLeastSquaresProblem.model:Lorg/apache/commons/math3/fitting/leastsquares/MultivariateJacobianFunction; (0, 0)
	20 aload_0 (0, 0)
	21 aload_3 (0, 0)
	22 putfield (0, 0)
	23 org/apache/commons/math3/fitting/leastsquares/LeastSquaresFactory$LocalLeastSquaresProblem.start:Lorg/apache/commons/math3/linear/RealVector; (0, 0)
	25 aload_0 (0, 0)
	26 iload (0, 0)
	27 #7 (0, 0)
	28 putfield (0, 0)
	29 org/apache/commons/math3/fitting/leastsquares/LeastSquaresFactory$LocalLeastSquaresProblem.lazyEvaluation:Z (0, 0)
	31 aload_0 (0, 0)
	32 aload (0, 0)
	33 #8 (0, 0)
	34 putfield (0, 0)
	35 org/apache/commons/math3/fitting/leastsquares/LeastSquaresFactory$LocalLeastSquaresProblem.paramValidator:Lorg/apache/commons/math3/fitting/leastsquares/ParameterValidator; (0, 0)
	37 iload (0, 1)
	38 #7 (0, 1)
	39 ifeq (0, 1)
	40 35 (0, 1)
	42 aload_1 (0, 1)
	43 instanceof (0, 1)
	44 org/apache/commons/math3/fitting/leastsquares/ValueAndJacobianFunction (0, 1)
	46 ifne (0, 1)
	47 28 (0, 1)
	49 new (0, 1)
	50 org/apache/commons/math3/exception/MathIllegalStateException (0, 1)
	52 dup (0, 1)
	53 getstatic (0, 1)
	54 org/apache/commons/math3/exception/util/LocalizedFormats.INVALID_IMPLEMENTATION:Lorg/apache/commons/math3/exception/util/LocalizedFormats; (0, 1)
	56 iconst_1 (0, 1)
	57 anewarray (0, 1)
	58 java/lang/Object (0, 1)
	60 dup (0, 1)
	61 iconst_0 (0, 1)
	62 aload_1 (0, 1)
	63 invokevirtual (0, 1)
	64 java/lang/Object.getClass:()Ljava/lang/Class; (0, 1)
	66 invokevirtual (0, 1)
	67 java/lang/Class.getName:()Ljava/lang/String; (0, 1)
	69 aastore (0, 1)
	70 invokespecial (0, 1)
	71 org/apache/commons/math3/exception/MathIllegalStateException.<init>:(Lorg/apache/commons/math3/exception/util/Localizable;[Ljava/lang/Object;)V (0, 1)
	73 athrow (0, 1)
	74 return (0, 1)

Method: getObservationSize
	0 aload_0 (0, 0)
	1 getfield (0, 0)
	2 org/apache/commons/math3/fitting/leastsquares/LeastSquaresFactory$LocalLeastSquaresProblem.target:Lorg/apache/commons/math3/linear/RealVector; (0, 0)
	4 invokevirtual (0, 0)
	5 org/apache/commons/math3/linear/RealVector.getDimension:()I (0, 0)
	7 ireturn (0, 0)

Method: getParameterSize
	0 aload_0 (0, 0)
	1 getfield (0, 0)
	2 org/apache/commons/math3/fitting/leastsquares/LeastSquaresFactory$LocalLeastSquaresProblem.start:Lorg/apache/commons/math3/linear/RealVector; (0, 0)
	4 invokevirtual (0, 0)
	5 org/apache/commons/math3/linear/RealVector.getDimension:()I (0, 0)
	7 ireturn (0, 0)

Method: getStart
	0 aload_0 (0, 0)
	1 getfield (0, 0)
	2 org/apache/commons/math3/fitting/leastsquares/LeastSquaresFactory$LocalLeastSquaresProblem.start:Lorg/apache/commons/math3/linear/RealVector; (0, 0)
	4 ifnonnull (0, 0)
	5 7 (0, 0)
	7 aconst_null (0, 0)
	8 goto (0, 0)
	9 10 (0, 0)
	11 aload_0 (0, 0)
	12 getfield (0, 0)
	13 org/apache/commons/math3/fitting/leastsquares/LeastSquaresFactory$LocalLeastSquaresProblem.start:Lorg/apache/commons/math3/linear/RealVector; (0, 0)
	15 invokevirtual (0, 0)
	16 org/apache/commons/math3/linear/RealVector.copy:()Lorg/apache/commons/math3/linear/RealVector; (0, 0)
	18 areturn (0, 0)

Method: evaluate
	0 aload_0 (0, 0)
	1 getfield (0, 0)
	2 org/apache/commons/math3/fitting/leastsquares/LeastSquaresFactory$LocalLeastSquaresProblem.paramValidator:Lorg/apache/commons/math3/fitting/leastsquares/ParameterValidator; (0, 0)
	4 ifnonnull (0, 0)
	5 10 (0, 0)
	7 aload_1 (0, 0)
	8 invokevirtual (0, 0)
	9 org/apache/commons/math3/linear/RealVector.copy:()Lorg/apache/commons/math3/linear/RealVector; (0, 0)
	11 goto (0, 0)
	12 16 (0, 0)
	14 aload_0 (0, 0)
	15 getfield (0, 0)
	16 org/apache/commons/math3/fitting/leastsquares/LeastSquaresFactory$LocalLeastSquaresProblem.paramValidator:Lorg/apache/commons/math3/fitting/leastsquares/ParameterValidator; (0, 0)
	18 aload_1 (0, 0)
	19 invokevirtual (0, 0)
	20 org/apache/commons/math3/linear/RealVector.copy:()Lorg/apache/commons/math3/linear/RealVector; (0, 0)
	22 invokeinterface (0, 0)
	23 org/apache/commons/math3/fitting/leastsquares/ParameterValidator.org/apache/commons/math3/fitting/leastsquares/LeastSquaresFactory$LocalLeastSquaresProblem$LazyUnweightedEvaluation (0, 0)
	25 0 (0, 0)
	27 astore_2 (0, 0)
	28 aload_0 (1, 1)
	29 getfield (1, 1)
	30 org/apache/commons/math3/fitting/leastsquares/LeastSquaresFactory$LocalLeastSquaresProblem.lazyEvaluation:Z (1, 1)
	32 ifeq (1, 1)
	33 24 (1, 1)
	35 new (1, 1)
	36 org/apache/commons/math3/fitting/leastsquares/LeastSquaresFactory$LocalLeastSquaresProblem$LazyUnweightedEvaluation (1, 1)
	38 dup (1, 1)
	39 aload_0 (1, 1)
	40 getfield (1, 1)
	41 org/apache/commons/math3/fitting/leastsquares/LeastSquaresFactory$LocalLeastSquaresProblem.model:Lorg/apache/commons/math3/fitting/leastsquares/MultivariateJacobianFunction; (1, 1)
	43 checkcast (1, 1)
	44 org/apache/commons/math3/fitting/leastsquares/ValueAndJacobianFunction (1, 1)
	46 aload_0 (1, 1)
	47 getfield (1, 1)
	48 org/apache/commons/math3/fitting/leastsquares/LeastSquaresFactory$LocalLeastSquaresProblem.target:Lorg/apache/commons/math3/linear/RealVector; (1, 1)
	50 aload_2 (1, 1)
	51 aconst_null (1, 1)
	52 invokespecial (1, 1)
	53 org/apache/commons/math3/fitting/leastsquares/LeastSquaresFactory$LocalLeastSquaresProblem$LazyUnweightedEvaluation.<init>:(Lorg/apache/commons/math3/fitting/leastsquares/ValueAndJacobianFunction;Lorg/apache/commons/math3/linear/RealVector;Lorg/apache/commons/math3/linear/RealVector;Lorg/apache/commons/math3/fitting/leastsquares/LeastSquaresFactory$1;)V (1, 1)
	55 areturn (1, 1)
	56 aload_0 (1, 2)
	57 getfield (1, 2)
	58 org/apache/commons/math3/fitting/leastsquares/LeastSquaresFactory$LocalLeastSquaresProblem.model:Lorg/apache/commons/math3/fitting/leastsquares/MultivariateJacobianFunction; (1, 2)
	60 aload_2 (1, 2)
	61 invokeinterface (1, 2)
	62 org/apache/commons/math3/fitting/leastsquares/MultivariateJacobianFunction.org/apache/commons/math3/fitting/leastsquares/LeastSquaresFactory$LocalLeastSquaresProblem$UnweightedEvaluation (1, 2)
	64 0 (1, 2)
	66 astore_3 (1, 2)
	67 new (1, 2)
	68 org/apache/commons/math3/fitting/leastsquares/LeastSquaresFactory$LocalLeastSquaresProblem$UnweightedEvaluation (1, 2)
	70 dup (1, 2)
	71 aload_3 (1, 2)
	72 invokevirtual (1, 2)
	73 org/apache/commons/math3/util/Pair.getFirst:()Ljava/lang/Object; (1, 2)
	75 checkcast (1, 2)
	76 org/apache/commons/math3/linear/RealVector (1, 2)
	78 aload_3 (1, 2)
	79 invokevirtual (1, 2)
	80 org/apache/commons/math3/util/Pair.getSecond:()Ljava/lang/Object; (1, 2)
	82 checkcast (1, 2)
	83 org/apache/commons/math3/linear/RealMatrix (1, 2)
	85 aload_0 (1, 2)
	86 getfield (1, 2)
	87 org/apache/commons/math3/fitting/leastsquares/LeastSquaresFactory$LocalLeastSquaresProblem.target:Lorg/apache/commons/math3/linear/RealVector; (1, 2)
	89 aload_2 (1, 2)
	90 aconst_null (1, 2)
	91 invokespecial (1, 2)
	92 org/apache/commons/math3/fitting/leastsquares/LeastSquaresFactory$LocalLeastSquaresProblem$UnweightedEvaluation.<init>:(Lorg/apache/commons/math3/linear/RealVector;Lorg/apache/commons/math3/linear/RealMatrix;Lorg/apache/commons/math3/linear/RealVector;Lorg/apache/commons/math3/linear/RealVector;Lorg/apache/commons/math3/fitting/leastsquares/LeastSquaresFactory$1;)V (1, 2)
	94 areturn (1, 2)

