Method: <init>
	0 aload_0 (0, 0)
	1 invokespecial (0, 0)
	2 java/lang/Object.<init>:()V (0, 0)
	4 aload_0 (0, 0)
	5 dload_1 (0, 0)
	6 putfield (0, 0)
	7 org/apache/commons/math3/fitting/leastsquares/LevenbergMarquardtOptimizer.initialStepBoundFactor:D (0, 0)
	9 aload_0 (0, 0)
	10 dload_3 (0, 0)
	11 putfield (0, 0)
	12 org/apache/commons/math3/fitting/leastsquares/LevenbergMarquardtOptimizer.costRelativeTolerance:D (0, 0)
	14 aload_0 (0, 0)
	15 dload (0, 0)
	16 #5 (0, 0)
	17 putfield (0, 0)
	18 org/apache/commons/math3/fitting/leastsquares/LevenbergMarquardtOptimizer.parRelativeTolerance:D (0, 0)
	20 aload_0 (0, 0)
	21 dload (0, 0)
	22 #7 (0, 0)
	23 putfield (0, 0)
	24 org/apache/commons/math3/fitting/leastsquares/LevenbergMarquardtOptimizer.orthoTolerance:D (0, 0)
	26 aload_0 (0, 0)
	27 dload (0, 0)
	28 #9 (0, 0)
	29 putfield (0, 0)
	30 org/apache/commons/math3/fitting/leastsquares/LevenbergMarquardtOptimizer.qrRankingThreshold:D (0, 0)
	32 return (0, 0)

Method: withInitialStepBoundFactor
	0 new (0, 0)
	1 org/apache/commons/math3/fitting/leastsquares/LevenbergMarquardtOptimizer (0, 0)
	3 dup (0, 0)
	4 dload_1 (0, 0)
	5 aload_0 (0, 0)
	6 getfield (0, 0)
	7 org/apache/commons/math3/fitting/leastsquares/LevenbergMarquardtOptimizer.costRelativeTolerance:D (0, 0)
	9 aload_0 (0, 0)
	10 getfield (0, 0)
	11 org/apache/commons/math3/fitting/leastsquares/LevenbergMarquardtOptimizer.parRelativeTolerance:D (0, 0)
	13 aload_0 (0, 0)
	14 getfield (0, 0)
	15 org/apache/commons/math3/fitting/leastsquares/LevenbergMarquardtOptimizer.orthoTolerance:D (0, 0)
	17 aload_0 (0, 0)
	18 getfield (0, 0)
	19 org/apache/commons/math3/fitting/leastsquares/LevenbergMarquardtOptimizer.qrRankingThreshold:D (0, 0)
	21 invokespecial (0, 0)
	22 org/apache/commons/math3/fitting/leastsquares/LevenbergMarquardtOptimizer.<init>:(DDDDD)V (0, 0)
	24 areturn (0, 0)

Method: withCostRelativeTolerance
	0 new (0, 0)
	1 org/apache/commons/math3/fitting/leastsquares/LevenbergMarquardtOptimizer (0, 0)
	3 dup (0, 0)
	4 aload_0 (0, 0)
	5 getfield (0, 0)
	6 org/apache/commons/math3/fitting/leastsquares/LevenbergMarquardtOptimizer.initialStepBoundFactor:D (0, 0)
	8 dload_1 (0, 0)
	9 aload_0 (0, 0)
	10 getfield (0, 0)
	11 org/apache/commons/math3/fitting/leastsquares/LevenbergMarquardtOptimizer.parRelativeTolerance:D (0, 0)
	13 aload_0 (0, 0)
	14 getfield (0, 0)
	15 org/apache/commons/math3/fitting/leastsquares/LevenbergMarquardtOptimizer.orthoTolerance:D (0, 0)
	17 aload_0 (0, 0)
	18 getfield (0, 0)
	19 org/apache/commons/math3/fitting/leastsquares/LevenbergMarquardtOptimizer.qrRankingThreshold:D (0, 0)
	21 invokespecial (0, 0)
	22 org/apache/commons/math3/fitting/leastsquares/LevenbergMarquardtOptimizer.<init>:(DDDDD)V (0, 0)
	24 areturn (0, 0)

Method: withParameterRelativeTolerance
	0 new (0, 0)
	1 org/apache/commons/math3/fitting/leastsquares/LevenbergMarquardtOptimizer (0, 0)
	3 dup (0, 0)
	4 aload_0 (0, 0)
	5 getfield (0, 0)
	6 org/apache/commons/math3/fitting/leastsquares/LevenbergMarquardtOptimizer.initialStepBoundFactor:D (0, 0)
	8 aload_0 (0, 0)
	9 getfield (0, 0)
	10 org/apache/commons/math3/fitting/leastsquares/LevenbergMarquardtOptimizer.costRelativeTolerance:D (0, 0)
	12 dload_1 (0, 0)
	13 aload_0 (0, 0)
	14 getfield (0, 0)
	15 org/apache/commons/math3/fitting/leastsquares/LevenbergMarquardtOptimizer.orthoTolerance:D (0, 0)
	17 aload_0 (0, 0)
	18 getfield (0, 0)
	19 org/apache/commons/math3/fitting/leastsquares/LevenbergMarquardtOptimizer.qrRankingThreshold:D (0, 0)
	21 invokespecial (0, 0)
	22 org/apache/commons/math3/fitting/leastsquares/LevenbergMarquardtOptimizer.<init>:(DDDDD)V (0, 0)
	24 areturn (0, 0)

Method: withOrthoTolerance
	0 new (0, 0)
	1 org/apache/commons/math3/fitting/leastsquares/LevenbergMarquardtOptimizer (0, 0)
	3 dup (0, 0)
	4 aload_0 (0, 0)
	5 getfield (0, 0)
	6 org/apache/commons/math3/fitting/leastsquares/LevenbergMarquardtOptimizer.initialStepBoundFactor:D (0, 0)
	8 aload_0 (0, 0)
	9 getfield (0, 0)
	10 org/apache/commons/math3/fitting/leastsquares/LevenbergMarquardtOptimizer.costRelativeTolerance:D (0, 0)
	12 aload_0 (0, 0)
	13 getfield (0, 0)
	14 org/apache/commons/math3/fitting/leastsquares/LevenbergMarquardtOptimizer.parRelativeTolerance:D (0, 0)
	16 dload_1 (0, 0)
	17 aload_0 (0, 0)
	18 getfield (0, 0)
	19 org/apache/commons/math3/fitting/leastsquares/LevenbergMarquardtOptimizer.qrRankingThreshold:D (0, 0)
	21 invokespecial (0, 0)
	22 org/apache/commons/math3/fitting/leastsquares/LevenbergMarquardtOptimizer.<init>:(DDDDD)V (0, 0)
	24 areturn (0, 0)

Method: withRankingThreshold
	0 new (0, 0)
	1 org/apache/commons/math3/fitting/leastsquares/LevenbergMarquardtOptimizer (0, 0)
	3 dup (0, 0)
	4 aload_0 (0, 0)
	5 getfield (0, 0)
	6 org/apache/commons/math3/fitting/leastsquares/LevenbergMarquardtOptimizer.initialStepBoundFactor:D (0, 0)
	8 aload_0 (0, 0)
	9 getfield (0, 0)
	10 org/apache/commons/math3/fitting/leastsquares/LevenbergMarquardtOptimizer.costRelativeTolerance:D (0, 0)
	12 aload_0 (0, 0)
	13 getfield (0, 0)
	14 org/apache/commons/math3/fitting/leastsquares/LevenbergMarquardtOptimizer.parRelativeTolerance:D (0, 0)
	16 aload_0 (0, 0)
	17 getfield (0, 0)
	18 org/apache/commons/math3/fitting/leastsquares/LevenbergMarquardtOptimizer.orthoTolerance:D (0, 0)
	20 dload_1 (0, 0)
	21 invokespecial (0, 0)
	22 org/apache/commons/math3/fitting/leastsquares/LevenbergMarquardtOptimizer.<init>:(DDDDD)V (0, 0)
	24 areturn (0, 0)

Method: getInitialStepBoundFactor
	0 aload_0 (0, 0)
	1 getfield (0, 0)
	2 org/apache/commons/math3/fitting/leastsquares/LevenbergMarquardtOptimizer.initialStepBoundFactor:D (0, 0)
	4 dreturn (0, 0)

Method: getCostRelativeTolerance
	0 aload_0 (0, 0)
	1 getfield (0, 0)
	2 org/apache/commons/math3/fitting/leastsquares/LevenbergMarquardtOptimizer.costRelativeTolerance:D (0, 0)
	4 dreturn (0, 0)

Method: getParameterRelativeTolerance
	0 aload_0 (0, 0)
	1 getfield (0, 0)
	2 org/apache/commons/math3/fitting/leastsquares/LevenbergMarquardtOptimizer.parRelativeTolerance:D (0, 0)
	4 dreturn (0, 0)

Method: getOrthoTolerance
	0 aload_0 (0, 0)
	1 getfield (0, 0)
	2 org/apache/commons/math3/fitting/leastsquares/LevenbergMarquardtOptimizer.orthoTolerance:D (0, 0)
	4 dreturn (0, 0)

Method: getRankingThreshold
	0 aload_0 (0, 0)
	1 getfield (0, 0)
	2 org/apache/commons/math3/fitting/leastsquares/LevenbergMarquardtOptimizer.qrRankingThreshold:D (0, 0)
	4 dreturn (0, 0)

Method: optimize
	0 aload_1 (0, 0)
	1 invokeinterface (0, 0)
	2 org/apache/commons/math3/fitting/leastsquares/LeastSquaresProblem.getParameterSize:()I (0, 0)
	4 0 (0, 0)
	6 istore_2 (0, 0)
	7 aload_1 (0, 0)
	8 invokeinterface (0, 0)
	9 org/apache/commons/math3/fitting/leastsquares/LeastSquaresProblem.getIterationCounter:()Lorg/apache/commons/math3/util/Incrementor; (0, 0)
	11 0 (0, 0)
	13 istore_3 (0, 0)
	14 aload_1 (0, 0)
	15 invokeinterface (0, 0)
	16 org/apache/commons/math3/fitting/leastsquares/LeastSquaresProblem.getEvaluationCounter:()Lorg/apache/commons/math3/util/Incrementor; (0, 0)
	18 0 (0, 0)
	20 astore (0, 0)
	21 #4 (0, 0)
	22 aload_1 (0, 0)
	23 invokeinterface (0, 0)
	24 org/apache/commons/math3/fitting/leastsquares/LeastSquaresProblem.getConvergenceChecker:()Lorg/apache/commons/math3/optim/ConvergenceChecker; (0, 0)
	26 0 (0, 0)
	28 astore (0, 0)
	29 #5 (0, 0)
	30 aload_1 (0, 0)
	31 invokeinterface (0, 0)
	32 org/apache/commons/math3/fitting/leastsquares/LeastSquaresProblem.org/apache/commons/math3/util/FastMath (0, 0)
	34 0 (0, 0)
	36 astore (0, 0)
	37 #6 (0, 0)
	38 iload_2 (0, 0)
	39 iload_3 (0, 0)
	40 invokestatic (0, 0)
	41 org/apache/commons/math3/util/FastMath.min:(II)I (0, 0)
	43 istore (0, 0)
	44 #7 (0, 0)
	45 iload_3 (0, 0)
	46 newarray (0, 0)
	47 7 (0, 0)
	48 astore (0, 0)
	49 #8 (0, 0)
	50 dconst_0 (0, 0)
	51 dstore (0, 0)
	52 #9 (0, 0)
	53 dconst_0 (0, 0)
	54 dstore (0, 0)
	55 #11 (0, 0)
	56 dconst_0 (0, 0)
	57 dstore (0, 0)
	58 #13 (0, 0)
	59 iload_3 (0, 0)
	60 newarray (0, 0)
	61 7 (0, 0)
	62 astore (0, 0)
	63 #15 (0, 0)
	64 iload_3 (0, 0)
	65 newarray (0, 0)
	66 7 (0, 0)
	67 astore (0, 0)
	68 #16 (0, 0)
	69 iload_2 (0, 0)
	70 newarray (0, 0)
	71 7 (0, 0)
	72 astore (0, 0)
	73 #17 (0, 0)
	74 iload_2 (0, 0)
	75 newarray (0, 0)
	76 7 (0, 0)
	77 astore (0, 0)
	78 #18 (0, 0)
	79 iload_3 (0, 0)
	80 newarray (0, 0)
	81 7 (0, 0)
	82 astore (0, 0)
	83 #19 (0, 0)
	84 iload_3 (0, 0)
	85 newarray (0, 0)
	86 7 (0, 0)
	87 astore (0, 0)
	88 #20 (0, 0)
	89 iload_3 (0, 0)
	90 newarray (0, 0)
	91 7 (0, 0)
	92 astore (0, 0)
	93 #21 (0, 0)
	94 aload (0, 0)
	95 #5 (0, 0)
	96 invokevirtual (0, 0)
	97 org/apache/commons/math3/util/Incrementor.incrementCount:()V (0, 0)
	99 aload_1 (0, 0)
	100 aload_1 (0, 0)
	101 invokeinterface (0, 0)
	102 org/apache/commons/math3/fitting/leastsquares/LeastSquaresProblem.evaluate:(Lorg/apache/commons/math3/linear/RealVector;)Lorg/apache/commons/math3/fitting/leastsquares/LeastSquaresProblem$Evaluation; (0, 0)
	104 0 (0, 0)
	106 invokeinterface (0, 0)
	107 org/apache/commons/math3/fitting/leastsquares/LeastSquaresProblem.getResiduals:()Lorg/apache/commons/math3/linear/RealVector; (0, 0)
	109 0 (0, 0)
	111 astore (0, 0)
	112 #22 (0, 0)
	113 aload (0, 0)
	114 #22 (0, 0)
	115 invokeinterface (0, 0)
	116 org/apache/commons/math3/fitting/leastsquares/LeastSquaresProblem$Evaluation.org/apache/commons/math3/linear/RealVector (0, 0)
	118 0 (0, 0)
	120 invokevirtual (0, 0)
	121 org/apache/commons/math3/linear/RealVector.toArray:()[D (0, 0)
	123 astore (0, 0)
	124 #23 (0, 0)
	125 aload (0, 0)
	126 #22 (0, 0)
	127 invokeinterface (0, 0)
	128 org/apache/commons/math3/fitting/leastsquares/LeastSquaresProblem$Evaluation.getPoint:()Lorg/apache/commons/math3/linear/RealVector; (0, 0)
	130 0 (0, 0)
	132 dstore (0, 0)
	133 #24 (0, 0)
	134 aload (0, 0)
	135 #22 (0, 0)
	136 invokeinterface (0, 0)
	137 org/apache/commons/math3/fitting/leastsquares/LeastSquaresProblem$Evaluation.getJacobian:()Lorg/apache/commons/math3/linear/RealMatrix; (0, 0)
	139 0 (0, 0)
	141 invokevirtual (0, 0)
	142 org/apache/commons/math3/linear/RealVector.toArray:()[D (0, 0)
	144 astore (0, 0)
	145 #26 (0, 0)
	146 iconst_1 (0, 0)
	147 istore (0, 0)
	148 #27 (0, 0)
	149 aload (1, 3)
	150 #4 (1, 3)
	151 invokevirtual (1, 3)
	152 org/apache/commons/math3/util/Incrementor.incrementCount:()V (1, 3)
	154 aload (1, 3)
	155 #22 (1, 3)
	156 astore (1, 3)
	157 #28 (1, 3)
	158 aload_0 (1, 3)
	159 aload (1, 3)
	160 #22 (1, 3)
	161 invokeinterface (1, 3)
	162 org/apache/commons/math3/fitting/leastsquares/LeastSquaresProblem$Evaluation.qrDecomposition:(Lorg/apache/commons/math3/linear/RealMatrix;I)Lorg/apache/commons/math3/fitting/leastsquares/LevenbergMarquardtOptimizer$InternalData; (1, 3)
	164 0 (1, 3)
	166 iload (1, 3)
	167 #7 (1, 3)
	168 invokespecial (1, 3)
	169 org/apache/commons/math3/fitting/leastsquares/LevenbergMarquardtOptimizer.qrDecomposition:(Lorg/apache/commons/math3/linear/RealMatrix;I)Lorg/apache/commons/math3/fitting/leastsquares/LevenbergMarquardtOptimizer$InternalData; (1, 3)
	171 astore (1, 3)
	172 #29 (1, 3)
	173 aload (1, 3)
	174 #29 (1, 3)
	175 invokestatic (1, 3)
	176 org/apache/commons/math3/fitting/leastsquares/LevenbergMarquardtOptimizer$InternalData.access$000:(Lorg/apache/commons/math3/fitting/leastsquares/LevenbergMarquardtOptimizer$InternalData;)[[D (1, 3)
	178 astore (1, 3)
	179 #30 (1, 3)
	180 aload (1, 3)
	181 #29 (1, 3)
	182 invokestatic (1, 3)
	183 org/apache/commons/math3/fitting/leastsquares/LevenbergMarquardtOptimizer$InternalData.access$100:(Lorg/apache/commons/math3/fitting/leastsquares/LevenbergMarquardtOptimizer$InternalData;)[I (1, 3)
	185 astore (1, 3)
	186 #31 (1, 3)
	187 aload (1, 3)
	188 #29 (1, 3)
	189 invokestatic (1, 3)
	190 org/apache/commons/math3/fitting/leastsquares/LevenbergMarquardtOptimizer$InternalData.access$200:(Lorg/apache/commons/math3/fitting/leastsquares/LevenbergMarquardtOptimizer$InternalData;)[D (1, 3)
	192 astore (1, 3)
	193 #32 (1, 3)
	194 aload (1, 3)
	195 #29 (1, 3)
	196 invokestatic (1, 3)
	197 org/apache/commons/math3/fitting/leastsquares/LevenbergMarquardtOptimizer$InternalData.access$300:(Lorg/apache/commons/math3/fitting/leastsquares/LevenbergMarquardtOptimizer$InternalData;)[D (1, 3)
	199 astore (1, 3)
	200 #33 (1, 3)
	201 aload (1, 3)
	202 #23 (1, 3)
	203 astore (1, 3)
	204 #34 (1, 3)
	205 iconst_0 (2, 4)
	206 istore (2, 4)
	207 #35 (2, 4)
	208 iload (2, 4)
	209 #35 (2, 4)
	210 iload_2 (2, 4)
	211 if_icmpge (2, 4)
	212 19 (2, 4)
	214 aload (2, 4)
	215 #18 (2, 4)
	216 iload (2, 4)
	217 #35 (2, 4)
	218 aload (2, 4)
	219 #34 (2, 4)
	220 iload (2, 4)
	221 #35 (2, 4)
	222 daload (2, 4)
	223 dastore (2, 4)
	224 iinc (2, 4)
	225 #35 (2, 4)
	226 -89 (2, 4)
	227 goto (2, 4)
	228 -19 (2, 4)
	230 aload_0 (1, 3)
	231 aload (1, 3)
	232 #18 (1, 3)
	233 aload (1, 3)
	234 #29 (1, 3)
	235 invokespecial (1, 3)
	236 org/apache/commons/math3/fitting/leastsquares/LevenbergMarquardtOptimizer.qTy:([DLorg/apache/commons/math3/fitting/leastsquares/LevenbergMarquardtOptimizer$InternalData;)V (1, 3)
	238 iconst_0 (2, 4)
	239 istore (2, 4)
	240 #35 (2, 4)
	241 iload (2, 4)
	242 #35 (2, 4)
	243 iload (2, 4)
	244 #7 (2, 4)
	245 if_icmpge (2, 4)
	246 29 (2, 4)
	248 aload (2, 4)
	249 #31 (2, 4)
	250 iload (2, 4)
	251 #35 (2, 4)
	252 iaload (2, 4)
	253 istore (2, 4)
	254 #36 (2, 4)
	255 aload (2, 4)
	256 #30 (2, 4)
	257 iload (2, 4)
	258 #35 (2, 4)
	259 aaload (2, 4)
	260 iload (2, 4)
	261 #36 (2, 4)
	262 aload (2, 4)
	263 #32 (2, 4)
	264 iload (2, 4)
	265 #36 (2, 4)
	266 daload (2, 4)
	267 dastore (2, 4)
	268 iinc (2, 4)
	269 #35 (2, 4)
	270 -89 (2, 4)
	271 goto (2, 4)
	272 -30 (2, 4)
	274 iload (2, 1)
	275 #27 (2, 1)
	276 ifeq (2, 1)
	277 95 (2, 1)
	279 dconst_0 (2, 1)
	280 dstore (2, 1)
	281 #13 (2, 1)
	282 iconst_0 (3, 4)
	283 istore (3, 4)
	284 #35 (3, 4)
	285 iload (3, 4)
	286 #35 (3, 4)
	287 iload_3 (3, 4)
	288 if_icmpge (3, 4)
	289 53 (3, 4)
	291 aload (3, 4)
	292 #33 (3, 4)
	293 iload (3, 4)
	294 #35 (3, 4)
	295 daload (3, 4)
	296 dstore (3, 4)
	297 #36 (3, 4)
	298 dload (4, 1)
	299 #36 (4, 1)
	300 dconst_0 (4, 1)
	301 dcmpl (4, 1)
	302 ifne (4, 1)
	303 6 (4, 1)
	305 dconst_1 (4, 1)
	306 dstore (4, 1)
	307 #36 (4, 1)
	308 dload (3, 4)
	309 #36 (3, 4)
	310 aload (3, 4)
	311 #26 (3, 4)
	312 iload (3, 4)
	313 #35 (3, 4)
	314 daload (3, 4)
	315 dmul (3, 4)
	316 dstore (3, 4)
	317 #38 (3, 4)
	318 dload (3, 4)
	319 #13 (3, 4)
	320 dload (3, 4)
	321 #38 (3, 4)
	322 dload (3, 4)
	323 #38 (3, 4)
	324 dmul (3, 4)
	325 dadd (3, 4)
	326 dstore (3, 4)
	327 #13 (3, 4)
	328 aload (3, 4)
	329 #15 (3, 4)
	330 iload (3, 4)
	331 #35 (3, 4)
	332 dload (3, 4)
	333 #36 (3, 4)
	334 dastore (3, 4)
	335 iinc (3, 4)
	336 #35 (3, 4)
	337 -89 (3, 4)
	338 goto (3, 4)
	339 -53 (3, 4)
	341 dload (2, 1)
	342 #13 (2, 1)
	343 invokestatic (2, 1)
	344 org/apache/commons/math3/util/FastMath.sqrt:(D)D (2, 1)
	346 dstore (2, 1)
	347 #13 (2, 1)
	348 dload (2, 1)
	349 #13 (2, 1)
	350 dconst_0 (2, 1)
	351 dcmpl (2, 1)
	352 ifne (2, 1)
	353 10 (2, 1)
	355 aload_0 (2, 1)
	356 getfield (2, 1)
	357 org/apache/commons/math3/fitting/leastsquares/LevenbergMarquardtOptimizer.initialStepBoundFactor:D (2, 1)
	359 goto (2, 1)
	360 10 (2, 1)
	362 aload_0 (2, 1)
	363 getfield (2, 1)
	364 org/apache/commons/math3/fitting/leastsquares/LevenbergMarquardtOptimizer.initialStepBoundFactor:D (2, 1)
	366 dload (2, 1)
	367 #13 (2, 1)
	368 dmul (2, 1)
	369 dstore (2, 1)
	370 #11 (2, 1)
	371 dconst_0 (1, 3)
	372 dstore (1, 3)
	373 #35 (1, 3)
	374 dload (2, 1)
	375 #24 (2, 1)
	376 dconst_0 (2, 1)
	377 dcmpl (2, 1)
	378 ifeq (2, 1)
	379 96 (2, 1)
	381 iconst_0 (3, 4)
	382 istore (3, 4)
	383 #37 (3, 4)
	384 iload (3, 4)
	385 #37 (3, 4)
	386 iload (3, 4)
	387 #7 (3, 4)
	388 if_icmpge (3, 4)
	389 86 (3, 4)
	391 aload (3, 4)
	392 #31 (3, 4)
	393 iload (3, 4)
	394 #37 (3, 4)
	395 iaload (3, 4)
	396 istore (3, 4)
	397 #38 (3, 4)
	398 aload (3, 4)
	399 #33 (3, 4)
	400 iload (3, 4)
	401 #38 (3, 4)
	402 daload (3, 4)
	403 dstore (3, 4)
	404 #39 (3, 4)
	405 dload (4, 1)
	406 #39 (4, 1)
	407 dconst_0 (4, 1)
	408 dcmpl (4, 1)
	409 ifeq (4, 1)
	410 59 (4, 1)
	412 dconst_0 (4, 1)
	413 dstore (4, 1)
	414 #41 (4, 1)
	415 iconst_0 (5, 4)
	416 istore (5, 4)
	417 #43 (5, 4)
	418 iload (5, 4)
	419 #43 (5, 4)
	420 iload (5, 4)
	421 #37 (5, 4)
	422 if_icmpgt (5, 4)
	423 28 (5, 4)
	425 dload (5, 4)
	426 #41 (5, 4)
	427 aload (5, 4)
	428 #30 (5, 4)
	429 iload (5, 4)
	430 #43 (5, 4)
	431 aaload (5, 4)
	432 iload (5, 4)
	433 #38 (5, 4)
	434 daload (5, 4)
	435 aload (5, 4)
	436 #18 (5, 4)
	437 iload (5, 4)
	438 #43 (5, 4)
	439 daload (5, 4)
	440 dmul (5, 4)
	441 dadd (5, 4)
	442 dstore (5, 4)
	443 #41 (5, 4)
	444 iinc (5, 4)
	445 #43 (5, 4)
	446 -89 (5, 4)
	447 goto (5, 4)
	448 -29 (5, 4)
	450 dload (4, 1)
	451 #35 (4, 1)
	452 dload (4, 1)
	453 #41 (4, 1)
	454 invokestatic (4, 1)
	455 org/apache/commons/math3/util/FastMath.abs:(D)D (4, 1)
	457 dload (4, 1)
	458 #39 (4, 1)
	459 dload (4, 1)
	460 #24 (4, 1)
	461 dmul (4, 1)
	462 ddiv (4, 1)
	463 invokestatic (4, 1)
	464 org/apache/commons/math3/util/FastMath.max:(DD)D (4, 1)
	466 dstore (4, 1)
	467 #35 (4, 1)
	468 iinc (4, 1)
	469 #37 (4, 1)
	470 -89 (4, 1)
	471 goto (4, 1)
	472 -87 (4, 1)
	474 dload (3, 1)
	475 #35 (3, 1)
	476 aload_0 (3, 1)
	477 getfield (3, 1)
	478 org/apache/commons/math3/fitting/leastsquares/LevenbergMarquardtOptimizer.orthoTolerance:D (3, 1)
	480 dcmpg (3, 1)
	481 ifgt (3, 1)
	482 23 (3, 1)
	484 new (3, 1)
	485 org/apache/commons/math3/fitting/leastsquares/OptimumImpl (3, 1)
	487 dup (3, 1)
	488 aload (3, 1)
	489 #22 (3, 1)
	490 aload (3, 1)
	491 #5 (3, 1)
	492 invokevirtual (3, 1)
	493 org/apache/commons/math3/util/Incrementor.getCount:()I (3, 1)
	495 aload (3, 1)
	496 #4 (3, 1)
	497 invokevirtual (3, 1)
	498 org/apache/commons/math3/util/Incrementor.getCount:()I (3, 1)
	500 invokespecial (3, 1)
	501 org/apache/commons/math3/fitting/leastsquares/OptimumImpl.<init>:(Lorg/apache/commons/math3/fitting/leastsquares/LeastSquaresProblem$Evaluation;II)V (3, 1)
	503 areturn (3, 1)
	504 iconst_0 (4, 4)
	505 istore (4, 4)
	506 #37 (4, 4)
	507 iload (4, 4)
	508 #37 (4, 4)
	509 iload_3 (4, 4)
	510 if_icmpge (4, 4)
	511 27 (4, 4)
	513 aload (4, 4)
	514 #15 (4, 4)
	515 iload (4, 4)
	516 #37 (4, 4)
	517 aload (4, 4)
	518 #15 (4, 4)
	519 iload (4, 4)
	520 #37 (4, 4)
	521 daload (4, 4)
	522 aload (4, 4)
	523 #33 (4, 4)
	524 iload (4, 4)
	525 #37 (4, 4)
	526 daload (4, 4)
	527 invokestatic (4, 4)
	528 org/apache/commons/math3/util/FastMath.max:(DD)D (4, 4)
	530 dastore (4, 4)
	531 iinc (4, 4)
	532 #37 (4, 4)
	533 -89 (4, 4)
	534 goto (4, 4)
	535 -27 (4, 4)
	537 dconst_0 (4, 4)
	538 dstore (4, 4)
	539 #37 (4, 4)
	540 dload (4, 4)
	541 #37 (4, 4)
	542 ldc2_w (4, 4)
	543 0.0001 (4, 4)
	545 dcmpg (4, 4)
	546 ifge (4, 4)
	547 908 (4, 4)
	549 iconst_0 (5, 4)
	550 istore (5, 4)
	551 #39 (5, 4)
	552 iload (5, 4)
	553 #39 (5, 4)
	554 iload (5, 4)
	555 #7 (5, 4)
	556 if_icmpge (5, 4)
	557 26 (5, 4)
	559 aload (5, 4)
	560 #31 (5, 4)
	561 iload (5, 4)
	562 #39 (5, 4)
	563 iaload (5, 4)
	564 istore (5, 4)
	565 #40 (5, 4)
	566 aload (5, 4)
	567 #16 (5, 4)
	568 iload (5, 4)
	569 #40 (5, 4)
	570 aload (5, 4)
	571 #26 (5, 4)
	572 iload (5, 4)
	573 #40 (5, 4)
	574 daload (5, 4)
	575 dastore (5, 4)
	576 iinc (5, 4)
	577 #39 (5, 4)
	578 -89 (5, 4)
	579 goto (5, 4)
	580 -27 (5, 4)
	582 dload (4, 4)
	583 #24 (4, 4)
	584 dstore (4, 4)
	585 #39 (4, 4)
	586 aload (4, 4)
	587 #34 (4, 4)
	588 astore (4, 4)
	589 #41 (4, 4)
	590 aload (4, 4)
	591 #17 (4, 4)
	592 astore (4, 4)
	593 #34 (4, 4)
	594 aload (4, 4)
	595 #41 (4, 4)
	596 astore (4, 4)
	597 #17 (4, 4)
	598 aload_0 (4, 4)
	599 aload (4, 4)
	600 #18 (4, 4)
	601 dload (4, 4)
	602 #11 (4, 4)
	603 aload (4, 4)
	604 #15 (4, 4)
	605 aload (4, 4)
	606 #29 (4, 4)
	607 iload (4, 4)
	608 #7 (4, 4)
	609 aload (4, 4)
	610 #19 (4, 4)
	611 aload (4, 4)
	612 #20 (4, 4)
	613 aload (4, 4)
	614 #21 (4, 4)
	615 aload (4, 4)
	616 #8 (4, 4)
	617 dload (4, 4)
	618 #9 (4, 4)
	619 invokespecial (4, 4)
	620 org/apache/commons/math3/fitting/leastsquares/LevenbergMarquardtOptimizer.determineLMParameter:([DD[DLorg/apache/commons/math3/fitting/leastsquares/LevenbergMarquardtOptimizer$InternalData;I[D[D[D[DD)D (4, 4)
	622 dstore (4, 4)
	623 #9 (4, 4)
	624 dconst_0 (4, 4)
	625 dstore (4, 4)
	626 #42 (4, 4)
	627 iconst_0 (5, 4)
	628 istore (5, 4)
	629 #44 (5, 4)
	630 iload (5, 4)
	631 #44 (5, 4)
	632 iload (5, 4)
	633 #7 (5, 4)
	634 if_icmpge (5, 4)
	635 66 (5, 4)
	637 aload (5, 4)
	638 #31 (5, 4)
	639 iload (5, 4)
	640 #44 (5, 4)
	641 iaload (5, 4)
	642 istore (5, 4)
	643 #45 (5, 4)
	644 aload (5, 4)
	645 #8 (5, 4)
	646 iload (5, 4)
	647 #45 (5, 4)
	648 aload (5, 4)
	649 #8 (5, 4)
	650 iload (5, 4)
	651 #45 (5, 4)
	652 daload (5, 4)
	653 dneg (5, 4)
	654 dastore (5, 4)
	655 aload (5, 4)
	656 #26 (5, 4)
	657 iload (5, 4)
	658 #45 (5, 4)
	659 aload (5, 4)
	660 #16 (5, 4)
	661 iload (5, 4)
	662 #45 (5, 4)
	663 daload (5, 4)
	664 aload (5, 4)
	665 #8 (5, 4)
	666 iload (5, 4)
	667 #45 (5, 4)
	668 daload (5, 4)
	669 dadd (5, 4)
	670 dastore (5, 4)
	671 aload (5, 4)
	672 #15 (5, 4)
	673 iload (5, 4)
	674 #45 (5, 4)
	675 daload (5, 4)
	676 aload (5, 4)
	677 #8 (5, 4)
	678 iload (5, 4)
	679 #45 (5, 4)
	680 daload (5, 4)
	681 dmul (5, 4)
	682 dstore (5, 4)
	683 #46 (5, 4)
	684 dload (5, 4)
	685 #42 (5, 4)
	686 dload (5, 4)
	687 #46 (5, 4)
	688 dload (5, 4)
	689 #46 (5, 4)
	690 dmul (5, 4)
	691 dadd (5, 4)
	692 dstore (5, 4)
	693 #42 (5, 4)
	694 iinc (5, 4)
	695 #44 (5, 4)
	696 -89 (5, 4)
	697 goto (5, 4)
	698 -67 (5, 4)
	700 dload (4, 4)
	701 #42 (4, 4)
	702 invokestatic (4, 4)
	703 org/apache/commons/math3/util/FastMath.sqrt:(D)D (4, 4)
	705 dstore (4, 4)
	706 #42 (4, 4)
	707 iload (5, 1)
	708 #27 (5, 1)
	709 ifeq (5, 1)
	710 12 (5, 1)
	712 dload (5, 1)
	713 #11 (5, 1)
	714 dload (5, 1)
	715 #42 (5, 1)
	716 invokestatic (5, 1)
	717 org/apache/commons/math3/util/FastMath.min:(DD)D (5, 1)
	719 dstore (5, 1)
	720 #11 (5, 1)
	721 aload (4, 4)
	722 #5 (4, 4)
	723 invokevirtual (4, 4)
	724 org/apache/commons/math3/util/Incrementor.incrementCount:()V (4, 4)
	726 aload_1 (4, 4)
	727 new (4, 4)
	728 org/apache/commons/math3/linear/ArrayRealVector (4, 4)
	730 dup (4, 4)
	731 aload (4, 4)
	732 #26 (4, 4)
	733 invokespecial (4, 4)
	734 org/apache/commons/math3/linear/ArrayRealVector.<init>:([D)V (4, 4)
	736 invokeinterface (4, 4)
	737 org/apache/commons/math3/fitting/leastsquares/LeastSquaresProblem.getResiduals:()Lorg/apache/commons/math3/linear/RealVector; (4, 4)
	739 0 (4, 4)
	741 astore (4, 4)
	742 #22 (4, 4)
	743 aload (4, 4)
	744 #22 (4, 4)
	745 invokeinterface (4, 4)
	746 org/apache/commons/math3/fitting/leastsquares/LeastSquaresProblem$Evaluation.org/apache/commons/math3/linear/RealVector (4, 4)
	748 0 (4, 4)
	750 invokevirtual (4, 4)
	751 org/apache/commons/math3/linear/RealVector.toArray:()[D (4, 4)
	753 astore (4, 4)
	754 #23 (4, 4)
	755 aload (4, 4)
	756 #22 (4, 4)
	757 invokeinterface (4, 4)
	758 org/apache/commons/math3/fitting/leastsquares/LeastSquaresProblem$Evaluation.getPoint:()Lorg/apache/commons/math3/linear/RealVector; (4, 4)
	760 0 (4, 4)
	762 dstore (4, 4)
	763 #24 (4, 4)
	764 aload (4, 4)
	765 #22 (4, 4)
	766 invokeinterface (4, 4)
	767 org/apache/commons/math3/fitting/leastsquares/LeastSquaresProblem$Evaluation.getJacobian:()Lorg/apache/commons/math3/linear/RealMatrix; (4, 4)
	769 0 (4, 4)
	771 invokevirtual (4, 4)
	772 org/apache/commons/math3/linear/RealVector.toArray:()[D (4, 4)
	774 astore (4, 4)
	775 #26 (4, 4)
	776 ldc2_w (4, 4)
	777 -1.0 (4, 4)
	779 dstore (4, 4)
	780 #44 (4, 4)
	781 ldc2_w (5, 1)
	782 0.1 (5, 1)
	784 dload (5, 1)
	785 #24 (5, 1)
	786 dmul (5, 1)
	787 dload (5, 1)
	788 #39 (5, 1)
	789 dcmpg (5, 1)
	790 ifge (5, 1)
	791 19 (5, 1)
	793 dload (5, 1)
	794 #24 (5, 1)
	795 dload (5, 1)
	796 #39 (5, 1)
	797 ddiv (5, 1)
	798 dstore (5, 1)
	799 #46 (5, 1)
	800 dconst_1 (5, 1)
	801 dload (5, 1)
	802 #46 (5, 1)
	803 dload (5, 1)
	804 #46 (5, 1)
	805 dmul (5, 1)
	806 dsub (5, 1)
	807 dstore (5, 1)
	808 #44 (5, 1)
	809 iconst_0 (5, 4)
	810 istore (5, 4)
	811 #46 (5, 4)
	812 iload (5, 4)
	813 #46 (5, 4)
	814 iload (5, 4)
	815 #7 (5, 4)
	816 if_icmpge (5, 4)
	817 64 (5, 4)
	819 aload (5, 4)
	820 #31 (5, 4)
	821 iload (5, 4)
	822 #46 (5, 4)
	823 iaload (5, 4)
	824 istore (5, 4)
	825 #47 (5, 4)
	826 aload (5, 4)
	827 #8 (5, 4)
	828 iload (5, 4)
	829 #47 (5, 4)
	830 daload (5, 4)
	831 dstore (5, 4)
	832 #48 (5, 4)
	833 aload (5, 4)
	834 #19 (5, 4)
	835 iload (5, 4)
	836 #46 (5, 4)
	837 dconst_0 (5, 4)
	838 dastore (5, 4)
	839 iconst_0 (6, 4)
	840 istore (6, 4)
	841 #50 (6, 4)
	842 iload (6, 4)
	843 #50 (6, 4)
	844 iload (6, 4)
	845 #46 (6, 4)
	846 if_icmpgt (6, 4)
	847 28 (6, 4)
	849 aload (6, 4)
	850 #19 (6, 4)
	851 iload (6, 4)
	852 #50 (6, 4)
	853 dup2 (6, 4)
	854 daload (6, 4)
	855 aload (6, 4)
	856 #30 (6, 4)
	857 iload (6, 4)
	858 #50 (6, 4)
	859 aaload (6, 4)
	860 iload (6, 4)
	861 #47 (6, 4)
	862 daload (6, 4)
	863 dload (6, 4)
	864 #48 (6, 4)
	865 dmul (6, 4)
	866 dadd (6, 4)
	867 dastore (6, 4)
	868 iinc (6, 4)
	869 #50 (6, 4)
	870 -89 (6, 4)
	871 goto (6, 4)
	872 -29 (6, 4)
	874 iinc (6, 4)
	875 #46 (6, 4)
	876 -89 (6, 4)
	877 goto (6, 4)
	878 -65 (6, 4)
	880 dconst_0 (5, 4)
	881 dstore (5, 4)
	882 #46 (5, 4)
	883 iconst_0 (6, 4)
	884 istore (6, 4)
	885 #48 (6, 4)
	886 iload (6, 4)
	887 #48 (6, 4)
	888 iload (6, 4)
	889 #7 (6, 4)
	890 if_icmpge (6, 4)
	891 25 (6, 4)
	893 dload (6, 4)
	894 #46 (6, 4)
	895 aload (6, 4)
	896 #19 (6, 4)
	897 iload (6, 4)
	898 #48 (6, 4)
	899 daload (6, 4)
	900 aload (6, 4)
	901 #19 (6, 4)
	902 iload (6, 4)
	903 #48 (6, 4)
	904 daload (6, 4)
	905 dmul (6, 4)
	906 dadd (6, 4)
	907 dstore (6, 4)
	908 #46 (6, 4)
	909 iinc (6, 4)
	910 #48 (6, 4)
	911 -89 (6, 4)
	912 goto (6, 4)
	913 -26 (6, 4)
	915 dload (5, 4)
	916 #39 (5, 4)
	917 dload (5, 4)
	918 #39 (5, 4)
	919 dmul (5, 4)
	920 dstore (5, 4)
	921 #48 (5, 4)
	922 dload (5, 4)
	923 #46 (5, 4)
	924 dload (5, 4)
	925 #48 (5, 4)
	926 ddiv (5, 4)
	927 dstore (5, 4)
	928 #46 (5, 4)
	929 dload (5, 4)
	930 #9 (5, 4)
	931 dload (5, 4)
	932 #42 (5, 4)
	933 dmul (5, 4)
	934 dload (5, 4)
	935 #42 (5, 4)
	936 dmul (5, 4)
	937 dload (5, 4)
	938 #48 (5, 4)
	939 ddiv (5, 4)
	940 dstore (5, 4)
	941 #50 (5, 4)
	942 dload (5, 4)
	943 #46 (5, 4)
	944 ldc2_w (5, 4)
	945 2.0 (5, 4)
	947 dload (5, 4)
	948 #50 (5, 4)
	949 dmul (5, 4)
	950 dadd (5, 4)
	951 dstore (5, 4)
	952 #52 (5, 4)
	953 dload (5, 4)
	954 #46 (5, 4)
	955 dload (5, 4)
	956 #50 (5, 4)
	957 dadd (5, 4)
	958 dneg (5, 4)
	959 dstore (5, 4)
	960 #54 (5, 4)
	961 dload (5, 4)
	962 #52 (5, 4)
	963 dconst_0 (5, 4)
	964 dcmpl (5, 4)
	965 ifne (5, 4)
	966 7 (5, 4)
	968 dconst_0 (5, 4)
	969 goto (5, 4)
	970 8 (5, 4)
	972 dload (5, 4)
	973 #44 (5, 4)
	974 dload (5, 4)
	975 #52 (5, 4)
	976 ddiv (5, 4)
	977 dstore (5, 4)
	978 #37 (5, 4)
	979 dload (6, 1)
	980 #37 (6, 1)
	981 ldc2_w (6, 1)
	982 0.25 (6, 1)
	984 dcmpg (6, 1)
	985 ifgt (6, 1)
	986 86 (6, 1)
	988 dload (6, 1)
	989 #44 (6, 1)
	990 dconst_0 (6, 1)
	991 dcmpg (6, 1)
	992 ifge (6, 1)
	993 22 (6, 1)
	995 ldc2_w (6, 1)
	996 0.5 (6, 1)
	998 dload (6, 1)
	999 #54 (6, 1)
	1000 dmul (6, 1)
	1001 dload (6, 1)
	1002 #54 (6, 1)
	1003 ldc2_w (6, 1)
	1004 0.5 (6, 1)
	1006 dload (6, 1)
	1007 #44 (6, 1)
	1008 dmul (6, 1)
	1009 dadd (6, 1)
	1010 ddiv (6, 1)
	1011 goto (6, 1)
	1012 6 (6, 1)
	1014 ldc2_w (6, 1)
	1015 0.5 (6, 1)
	1017 dstore (6, 1)
	1018 #56 (6, 1)
	1019 ldc2_w (7, 1)
	1020 0.1 (7, 1)
	1022 dload (7, 1)
	1023 #24 (7, 1)
	1024 dmul (7, 1)
	1025 dload (7, 1)
	1026 #39 (7, 1)
	1027 dcmpl (7, 1)
	1028 ifge (7, 1)
	1029 12 (7, 1)
	1031 dload (7, 1)
	1032 #56 (7, 1)
	1033 ldc2_w (7, 1)
	1034 0.1 (7, 1)
	1036 dcmpg (7, 1)
	1037 ifge (7, 1)
	1038 8 (7, 1)
	1040 ldc2_w (7, 1)
	1041 0.1 (7, 1)
	1043 dstore (7, 1)
	1044 #56 (7, 1)
	1045 dload (6, 1)
	1046 #56 (6, 1)
	1047 dload (6, 1)
	1048 #11 (6, 1)
	1049 ldc2_w (6, 1)
	1050 10.0 (6, 1)
	1052 dload (6, 1)
	1053 #42 (6, 1)
	1054 dmul (6, 1)
	1055 invokestatic (6, 1)
	1056 org/apache/commons/math3/util/FastMath.min:(DD)D (6, 1)
	1058 dmul (6, 1)
	1059 dstore (6, 1)
	1060 #11 (6, 1)
	1061 dload (6, 1)
	1062 #9 (6, 1)
	1063 dload (6, 1)
	1064 #56 (6, 1)
	1065 ddiv (6, 1)
	1066 dstore (6, 1)
	1067 #9 (6, 1)
	1068 goto (7, 1)
	1069 35 (7, 1)
	1071 dload (7, 1)
	1072 #9 (7, 1)
	1073 dconst_0 (7, 1)
	1074 dcmpl (7, 1)
	1075 ifeq (7, 1)
	1076 12 (7, 1)
	1078 dload (7, 1)
	1079 #37 (7, 1)
	1080 ldc2_w (7, 1)
	1081 0.75 (7, 1)
	1083 dcmpl (7, 1)
	1084 iflt (7, 1)
	1085 19 (7, 1)
	1087 ldc2_w (7, 1)
	1088 2.0 (7, 1)
	1090 dload (7, 1)
	1091 #42 (7, 1)
	1092 dmul (7, 1)
	1093 dstore (7, 1)
	1094 #11 (7, 1)
	1095 dload (7, 1)
	1096 #9 (7, 1)
	1097 ldc2_w (7, 1)
	1098 0.5 (7, 1)
	1100 dmul (7, 1)
	1101 dstore (7, 1)
	1102 #9 (7, 1)
	1103 dload (7, 1)
	1104 #37 (7, 1)
	1105 ldc2_w (7, 1)
	1106 0.0001 (7, 1)
	1108 dcmpl (7, 1)
	1109 iflt (7, 1)
	1110 98 (7, 1)
	1112 iconst_0 (7, 1)
	1113 istore (7, 1)
	1114 #27 (7, 1)
	1115 dconst_0 (7, 1)
	1116 dstore (7, 1)
	1117 #13 (7, 1)
	1118 iconst_0 (8, 4)
	1119 istore (8, 4)
	1120 #56 (8, 4)
	1121 iload (8, 4)
	1122 #56 (8, 4)
	1123 iload_3 (8, 4)
	1124 if_icmpge (8, 4)
	1125 32 (8, 4)
	1127 aload (8, 4)
	1128 #15 (8, 4)
	1129 iload (8, 4)
	1130 #56 (8, 4)
	1131 daload (8, 4)
	1132 aload (8, 4)
	1133 #26 (8, 4)
	1134 iload (8, 4)
	1135 #56 (8, 4)
	1136 daload (8, 4)
	1137 dmul (8, 4)
	1138 dstore (8, 4)
	1139 #57 (8, 4)
	1140 dload (8, 4)
	1141 #13 (8, 4)
	1142 dload (8, 4)
	1143 #57 (8, 4)
	1144 dload (8, 4)
	1145 #57 (8, 4)
	1146 dmul (8, 4)
	1147 dadd (8, 4)
	1148 dstore (8, 4)
	1149 #13 (8, 4)
	1150 iinc (8, 4)
	1151 #56 (8, 4)
	1152 -89 (8, 4)
	1153 goto (8, 4)
	1154 -32 (8, 4)
	1156 dload (7, 1)
	1157 #13 (7, 1)
	1158 invokestatic (7, 1)
	1159 org/apache/commons/math3/util/FastMath.sqrt:(D)D (7, 1)
	1161 dstore (7, 1)
	1162 #13 (7, 1)
	1163 aload (9, 1)
	1164 #6 (9, 1)
	1165 ifnull (9, 1)
	1166 95 (9, 1)
	1168 aload (9, 1)
	1169 #6 (9, 1)
	1170 aload (9, 1)
	1171 #4 (9, 1)
	1172 invokevirtual (9, 1)
	1173 org/apache/commons/math3/util/Incrementor.getCount:()I (9, 1)
	1175 aload (9, 1)
	1176 #28 (9, 1)
	1177 aload (9, 1)
	1178 #22 (9, 1)
	1179 invokeinterface (9, 1)
	1180 org/apache/commons/math3/optim/ConvergenceChecker.TWO_EPS:D (9, 1)
	1182 0 (9, 1)
	1184 ifeq (9, 1)
	1185 76 (9, 1)
	1187 new (9, 1)
	1188 org/apache/commons/math3/fitting/leastsquares/OptimumImpl (9, 1)
	1190 dup (9, 1)
	1191 aload (9, 1)
	1192 #22 (9, 1)
	1193 aload (9, 1)
	1194 #5 (9, 1)
	1195 invokevirtual (9, 1)
	1196 org/apache/commons/math3/util/Incrementor.getCount:()I (9, 1)
	1198 aload (9, 1)
	1199 #4 (9, 1)
	1200 invokevirtual (9, 1)
	1201 org/apache/commons/math3/util/Incrementor.getCount:()I (9, 1)
	1203 invokespecial (9, 1)
	1204 org/apache/commons/math3/fitting/leastsquares/OptimumImpl.<init>:(Lorg/apache/commons/math3/fitting/leastsquares/LeastSquaresProblem$Evaluation;II)V (9, 1)
	1206 areturn (9, 1)
	1207 dload (9, 2)
	1208 #39 (9, 2)
	1209 dstore (9, 2)
	1210 #24 (9, 2)
	1211 iconst_0 (10, 4)
	1212 istore (10, 4)
	1213 #56 (10, 4)
	1214 iload (10, 4)
	1215 #56 (10, 4)
	1216 iload (10, 4)
	1217 #7 (10, 4)
	1218 if_icmpge (10, 4)
	1219 26 (10, 4)
	1221 aload (10, 4)
	1222 #31 (10, 4)
	1223 iload (10, 4)
	1224 #56 (10, 4)
	1225 iaload (10, 4)
	1226 istore (10, 4)
	1227 #57 (10, 4)
	1228 aload (10, 4)
	1229 #26 (10, 4)
	1230 iload (10, 4)
	1231 #57 (10, 4)
	1232 aload (10, 4)
	1233 #16 (10, 4)
	1234 iload (10, 4)
	1235 #57 (10, 4)
	1236 daload (10, 4)
	1237 dastore (10, 4)
	1238 iinc (10, 4)
	1239 #56 (10, 4)
	1240 -89 (10, 4)
	1241 goto (10, 4)
	1242 -27 (10, 4)
	1244 aload (9, 2)
	1245 #34 (9, 2)
	1246 astore (9, 2)
	1247 #41 (9, 2)
	1248 aload (9, 2)
	1249 #17 (9, 2)
	1250 astore (9, 2)
	1251 #34 (9, 2)
	1252 aload (9, 2)
	1253 #41 (9, 2)
	1254 astore (9, 2)
	1255 #17 (9, 2)
	1256 aload (9, 2)
	1257 #28 (9, 2)
	1258 astore (9, 2)
	1259 #22 (9, 2)
	1260 dload (7, 1)
	1261 #44 (7, 1)
	1262 invokestatic (7, 1)
	1263 org/apache/commons/math3/util/FastMath.abs:(D)D (7, 1)
	1265 aload_0 (7, 1)
	1266 getfield (7, 1)
	1267 org/apache/commons/math3/fitting/leastsquares/LevenbergMarquardtOptimizer.costRelativeTolerance:D (7, 1)
	1269 dcmpg (7, 1)
	1270 ifgt (7, 1)
	1271 22 (7, 1)
	1273 dload (7, 1)
	1274 #52 (7, 1)
	1275 aload_0 (7, 1)
	1276 getfield (7, 1)
	1277 org/apache/commons/math3/fitting/leastsquares/LevenbergMarquardtOptimizer.costRelativeTolerance:D (7, 1)
	1279 dcmpg (7, 1)
	1280 ifgt (7, 1)
	1281 12 (7, 1)
	1283 dload (7, 1)
	1284 #37 (7, 1)
	1285 ldc2_w (7, 1)
	1286 2.0 (7, 1)
	1288 dcmpg (7, 1)
	1289 ifle (7, 1)
	1290 16 (7, 1)
	1292 dload (7, 1)
	1293 #11 (7, 1)
	1294 aload_0 (7, 1)
	1295 getfield (7, 1)
	1296 org/apache/commons/math3/fitting/leastsquares/LevenbergMarquardtOptimizer.parRelativeTolerance:D (7, 1)
	1298 dload (7, 1)
	1299 #13 (7, 1)
	1300 dmul (7, 1)
	1301 dcmpg (7, 1)
	1302 ifgt (7, 1)
	1303 23 (7, 1)
	1305 new (7, 1)
	1306 org/apache/commons/math3/fitting/leastsquares/OptimumImpl (7, 1)
	1308 dup (7, 1)
	1309 aload (7, 1)
	1310 #22 (7, 1)
	1311 aload (7, 1)
	1312 #5 (7, 1)
	1313 invokevirtual (7, 1)
	1314 org/apache/commons/math3/util/Incrementor.getCount:()I (7, 1)
	1316 aload (7, 1)
	1317 #4 (7, 1)
	1318 invokevirtual (7, 1)
	1319 org/apache/commons/math3/util/Incrementor.getCount:()I (7, 1)
	1321 invokespecial (7, 1)
	1322 org/apache/commons/math3/fitting/leastsquares/OptimumImpl.<init>:(Lorg/apache/commons/math3/fitting/leastsquares/LeastSquaresProblem$Evaluation;II)V (7, 1)
	1324 areturn (7, 1)
	1325 dload (9, 1)
	1326 #44 (9, 1)
	1327 invokestatic (9, 1)
	1328 org/apache/commons/math3/util/FastMath.abs:(D)D (9, 1)
	1330 getstatic (9, 1)
	1331 org/apache/commons/math3/fitting/leastsquares/LevenbergMarquardtOptimizer.TWO_EPS:D (9, 1)
	1333 dcmpg (9, 1)
	1334 ifgt (9, 1)
	1335 46 (9, 1)
	1337 dload (9, 1)
	1338 #52 (9, 1)
	1339 getstatic (9, 1)
	1340 org/apache/commons/math3/fitting/leastsquares/LevenbergMarquardtOptimizer.TWO_EPS:D (9, 1)
	1342 dcmpg (9, 1)
	1343 ifgt (9, 1)
	1344 37 (9, 1)
	1346 dload (9, 1)
	1347 #37 (9, 1)
	1348 ldc2_w (9, 1)
	1349 2.0 (9, 1)
	1351 dcmpg (9, 1)
	1352 ifgt (9, 1)
	1353 28 (9, 1)
	1355 new (9, 1)
	1356 org/apache/commons/math3/exception/ConvergenceException (9, 1)
	1358 dup (9, 1)
	1359 getstatic (9, 1)
	1360 org/apache/commons/math3/exception/util/LocalizedFormats.TOO_SMALL_COST_RELATIVE_TOLERANCE:Lorg/apache/commons/math3/exception/util/LocalizedFormats; (9, 1)
	1362 iconst_1 (9, 1)
	1363 anewarray (9, 1)
	1364 java/lang/Object (9, 1)
	1366 dup (9, 1)
	1367 iconst_0 (9, 1)
	1368 aload_0 (9, 1)
	1369 getfield (9, 1)
	1370 org/apache/commons/math3/fitting/leastsquares/LevenbergMarquardtOptimizer.costRelativeTolerance:D (9, 1)
	1372 invokestatic (9, 1)
	1373 java/lang/Double.valueOf:(D)Ljava/lang/Double; (9, 1)
	1375 aastore (9, 1)
	1376 invokespecial (9, 1)
	1377 org/apache/commons/math3/exception/ConvergenceException.<init>:(Lorg/apache/commons/math3/exception/util/Localizable;[Ljava/lang/Object;)V (9, 1)
	1379 athrow (9, 1)
	1380 dload (10, 1)
	1381 #11 (10, 1)
	1382 getstatic (10, 1)
	1383 org/apache/commons/math3/fitting/leastsquares/LevenbergMarquardtOptimizer.TWO_EPS:D (10, 1)
	1385 dload (10, 1)
	1386 #13 (10, 1)
	1387 dmul (10, 1)
	1388 dcmpg (10, 1)
	1389 ifgt (10, 1)
	1390 28 (10, 1)
	1392 new (10, 1)
	1393 org/apache/commons/math3/exception/ConvergenceException (10, 1)
	1395 dup (10, 1)
	1396 getstatic (10, 1)
	1397 org/apache/commons/math3/exception/util/LocalizedFormats.TOO_SMALL_PARAMETERS_RELATIVE_TOLERANCE:Lorg/apache/commons/math3/exception/util/LocalizedFormats; (10, 1)
	1399 iconst_1 (10, 1)
	1400 anewarray (10, 1)
	1401 java/lang/Object (10, 1)
	1403 dup (10, 1)
	1404 iconst_0 (10, 1)
	1405 aload_0 (10, 1)
	1406 getfield (10, 1)
	1407 org/apache/commons/math3/fitting/leastsquares/LevenbergMarquardtOptimizer.parRelativeTolerance:D (10, 1)
	1409 invokestatic (10, 1)
	1410 java/lang/Double.valueOf:(D)Ljava/lang/Double; (10, 1)
	1412 aastore (10, 1)
	1413 invokespecial (10, 1)
	1414 org/apache/commons/math3/exception/ConvergenceException.<init>:(Lorg/apache/commons/math3/exception/util/Localizable;[Ljava/lang/Object;)V (10, 1)
	1416 athrow (10, 1)
	1417 dload (11, 1)
	1418 #35 (11, 1)
	1419 getstatic (11, 1)
	1420 org/apache/commons/math3/fitting/leastsquares/LevenbergMarquardtOptimizer.TWO_EPS:D (11, 1)
	1422 dcmpg (11, 1)
	1423 ifgt (11, 1)
	1424 28 (11, 1)
	1426 new (11, 1)
	1427 org/apache/commons/math3/exception/ConvergenceException (11, 1)
	1429 dup (11, 1)
	1430 getstatic (11, 1)
	1431 org/apache/commons/math3/exception/util/LocalizedFormats.TOO_SMALL_ORTHOGONALITY_TOLERANCE:Lorg/apache/commons/math3/exception/util/LocalizedFormats; (11, 1)
	1433 iconst_1 (11, 1)
	1434 anewarray (11, 1)
	1435 java/lang/Object (11, 1)
	1437 dup (11, 1)
	1438 iconst_0 (11, 1)
	1439 aload_0 (11, 1)
	1440 getfield (11, 1)
	1441 org/apache/commons/math3/fitting/leastsquares/LevenbergMarquardtOptimizer.orthoTolerance:D (11, 1)
	1443 invokestatic (11, 1)
	1444 java/lang/Double.valueOf:(D)Ljava/lang/Double; (11, 1)
	1446 aastore (11, 1)
	1447 invokespecial (11, 1)
	1448 org/apache/commons/math3/exception/ConvergenceException.<init>:(Lorg/apache/commons/math3/exception/util/Localizable;[Ljava/lang/Object;)V (11, 1)
	1450 athrow (11, 1)
	1451 goto (4, 4)
	1452 -911 (4, 4)
	1454 goto (2, 1)
	1455 -1305 (3, 1)

Method: determineLMParameter
	0 aload (0, 0)
	1 #5 (0, 0)
	2 invokestatic (0, 0)
	3 org/apache/commons/math3/fitting/leastsquares/LevenbergMarquardtOptimizer$InternalData.access$000:(Lorg/apache/commons/math3/fitting/leastsquares/LevenbergMarquardtOptimizer$InternalData;)[[D (0, 0)
	5 astore (0, 0)
	6 #13 (0, 0)
	7 aload (0, 0)
	8 #5 (0, 0)
	9 invokestatic (0, 0)
	10 org/apache/commons/math3/fitting/leastsquares/LevenbergMarquardtOptimizer$InternalData.access$100:(Lorg/apache/commons/math3/fitting/leastsquares/LevenbergMarquardtOptimizer$InternalData;)[I (0, 0)
	12 astore (0, 0)
	13 #14 (0, 0)
	14 aload (0, 0)
	15 #5 (0, 0)
	16 invokestatic (0, 0)
	17 org/apache/commons/math3/fitting/leastsquares/LevenbergMarquardtOptimizer$InternalData.access$400:(Lorg/apache/commons/math3/fitting/leastsquares/LevenbergMarquardtOptimizer$InternalData;)I (0, 0)
	19 istore (0, 0)
	20 #15 (0, 0)
	21 aload (0, 0)
	22 #5 (0, 0)
	23 invokestatic (0, 0)
	24 org/apache/commons/math3/fitting/leastsquares/LevenbergMarquardtOptimizer$InternalData.access$200:(Lorg/apache/commons/math3/fitting/leastsquares/LevenbergMarquardtOptimizer$InternalData;)[D (0, 0)
	26 astore (0, 0)
	27 #16 (0, 0)
	28 aload (0, 0)
	29 #13 (0, 0)
	30 iconst_0 (0, 0)
	31 aaload (0, 0)
	32 arraylength (0, 0)
	33 istore (0, 0)
	34 #17 (0, 0)
	35 iconst_0 (2, 4)
	36 istore (2, 4)
	37 #18 (2, 4)
	38 iload (2, 4)
	39 #18 (2, 4)
	40 iload (2, 4)
	41 #15 (2, 4)
	42 if_icmpge (2, 4)
	43 21 (2, 4)
	45 aload (2, 4)
	46 #10 (2, 4)
	47 aload (2, 4)
	48 #14 (2, 4)
	49 iload (2, 4)
	50 #18 (2, 4)
	51 iaload (2, 4)
	52 aload_1 (2, 4)
	53 iload (2, 4)
	54 #18 (2, 4)
	55 daload (2, 4)
	56 dastore (2, 4)
	57 iinc (2, 4)
	58 #18 (2, 4)
	59 -89 (2, 4)
	60 goto (2, 4)
	61 -22 (2, 4)
	63 iload (2, 4)
	64 #15 (2, 4)
	65 istore (2, 4)
	66 #18 (2, 4)
	67 iload (2, 4)
	68 #18 (2, 4)
	69 iload (2, 4)
	70 #17 (2, 4)
	71 if_icmpge (2, 4)
	72 18 (2, 4)
	74 aload (2, 4)
	75 #10 (2, 4)
	76 aload (2, 4)
	77 #14 (2, 4)
	78 iload (2, 4)
	79 #18 (2, 4)
	80 iaload (2, 4)
	81 dconst_0 (2, 4)
	82 dastore (2, 4)
	83 iinc (2, 4)
	84 #18 (2, 4)
	85 -89 (2, 4)
	86 goto (2, 4)
	87 -19 (2, 4)
	89 iload (2, 4)
	90 #15 (2, 4)
	91 iconst_1 (2, 4)
	92 isub (2, 4)
	93 istore (2, 4)
	94 #18 (2, 4)
	95 iload (2, 4)
	96 #18 (2, 4)
	97 iflt (2, 4)
	98 74 (2, 4)
	100 aload (2, 4)
	101 #14 (2, 4)
	102 iload (2, 4)
	103 #18 (2, 4)
	104 iaload (2, 4)
	105 istore (2, 4)
	106 #19 (2, 4)
	107 aload (2, 4)
	108 #10 (2, 4)
	109 iload (2, 4)
	110 #19 (2, 4)
	111 daload (2, 4)
	112 aload (2, 4)
	113 #16 (2, 4)
	114 iload (2, 4)
	115 #19 (2, 4)
	116 daload (2, 4)
	117 ddiv (2, 4)
	118 dstore (2, 4)
	119 #20 (2, 4)
	120 iconst_0 (3, 4)
	121 istore (3, 4)
	122 #22 (3, 4)
	123 iload (3, 4)
	124 #22 (3, 4)
	125 iload (3, 4)
	126 #18 (3, 4)
	127 if_icmpge (3, 4)
	128 31 (3, 4)
	130 aload (3, 4)
	131 #10 (3, 4)
	132 aload (3, 4)
	133 #14 (3, 4)
	134 iload (3, 4)
	135 #22 (3, 4)
	136 iaload (3, 4)
	137 dup2 (3, 4)
	138 daload (3, 4)
	139 dload (3, 4)
	140 #20 (3, 4)
	141 aload (3, 4)
	142 #13 (3, 4)
	143 iload (3, 4)
	144 #22 (3, 4)
	145 aaload (3, 4)
	146 iload (3, 4)
	147 #19 (3, 4)
	148 daload (3, 4)
	149 dmul (3, 4)
	150 dsub (3, 4)
	151 dastore (3, 4)
	152 iinc (3, 4)
	153 #22 (3, 4)
	154 -89 (3, 4)
	155 goto (3, 4)
	156 -32 (3, 4)
	158 aload (2, 4)
	159 #10 (2, 4)
	160 iload (2, 4)
	161 #19 (2, 4)
	162 dload (2, 4)
	163 #20 (2, 4)
	164 dastore (2, 4)
	165 iinc (2, 4)
	166 #18 (2, 4)
	167 -89 (2, 4)
	168 goto (2, 4)
	169 -73 (2, 4)
	171 dconst_0 (2, 4)
	172 dstore (2, 4)
	173 #18 (2, 4)
	174 iconst_0 (3, 4)
	175 istore (3, 4)
	176 #20 (3, 4)
	177 iload (3, 4)
	178 #20 (3, 4)
	179 iload (3, 4)
	180 #6 (3, 4)
	181 if_icmpge (3, 4)
	182 46 (3, 4)
	184 aload (3, 4)
	185 #14 (3, 4)
	186 iload (3, 4)
	187 #20 (3, 4)
	188 iaload (3, 4)
	189 istore (3, 4)
	190 #21 (3, 4)
	191 aload (3, 4)
	192 #4 (3, 4)
	193 iload (3, 4)
	194 #21 (3, 4)
	195 daload (3, 4)
	196 aload (3, 4)
	197 #10 (3, 4)
	198 iload (3, 4)
	199 #21 (3, 4)
	200 daload (3, 4)
	201 dmul (3, 4)
	202 dstore (3, 4)
	203 #22 (3, 4)
	204 aload (3, 4)
	205 #7 (3, 4)
	206 iload (3, 4)
	207 #21 (3, 4)
	208 dload (3, 4)
	209 #22 (3, 4)
	210 dastore (3, 4)
	211 dload (3, 4)
	212 #18 (3, 4)
	213 dload (3, 4)
	214 #22 (3, 4)
	215 dload (3, 4)
	216 #22 (3, 4)
	217 dmul (3, 4)
	218 dadd (3, 4)
	219 dstore (3, 4)
	220 #18 (3, 4)
	221 iinc (3, 4)
	222 #20 (3, 4)
	223 -89 (3, 4)
	224 goto (3, 4)
	225 -47 (3, 4)
	227 dload (2, 4)
	228 #18 (2, 4)
	229 invokestatic (2, 4)
	230 org/apache/commons/math3/util/FastMath.sqrt:(D)D (2, 4)
	232 dstore (2, 4)
	233 #18 (2, 4)
	234 dload (2, 4)
	235 #18 (2, 4)
	236 dload_2 (2, 4)
	237 dsub (2, 4)
	238 dstore (2, 4)
	239 #20 (2, 4)
	240 dload (3, 1)
	241 #20 (3, 1)
	242 ldc2_w (3, 1)
	243 0.1 (3, 1)
	245 dload_2 (3, 1)
	246 dmul (3, 1)
	247 dcmpg (3, 1)
	248 ifgt (3, 1)
	249 9 (3, 1)
	251 dconst_0 (3, 1)
	252 dstore (3, 1)
	253 #11 (3, 1)
	254 dload (3, 1)
	255 #11 (3, 1)
	256 dreturn (3, 1)
	257 dconst_0 (4, 4)
	258 dstore (4, 4)
	259 #24 (4, 4)
	260 iload (5, 1)
	261 #15 (5, 1)
	262 iload (5, 1)
	263 #6 (5, 1)
	264 if_icmpne (5, 1)
	265 151 (5, 1)
	267 iconst_0 (6, 4)
	268 istore (6, 4)
	269 #26 (6, 4)
	270 iload (6, 4)
	271 #26 (6, 4)
	272 iload (6, 4)
	273 #6 (6, 4)
	274 if_icmpge (6, 4)
	275 32 (6, 4)
	277 aload (6, 4)
	278 #14 (6, 4)
	279 iload (6, 4)
	280 #26 (6, 4)
	281 iaload (6, 4)
	282 istore (6, 4)
	283 #27 (6, 4)
	284 aload (6, 4)
	285 #7 (6, 4)
	286 iload (6, 4)
	287 #27 (6, 4)
	288 dup2 (6, 4)
	289 daload (6, 4)
	290 aload (6, 4)
	291 #4 (6, 4)
	292 iload (6, 4)
	293 #27 (6, 4)
	294 daload (6, 4)
	295 dload (6, 4)
	296 #18 (6, 4)
	297 ddiv (6, 4)
	298 dmul (6, 4)
	299 dastore (6, 4)
	300 iinc (6, 4)
	301 #26 (6, 4)
	302 -89 (6, 4)
	303 goto (6, 4)
	304 -33 (6, 4)
	306 dconst_0 (5, 1)
	307 dstore (5, 1)
	308 #22 (5, 1)
	309 iconst_0 (6, 4)
	310 istore (6, 4)
	311 #26 (6, 4)
	312 iload (6, 4)
	313 #26 (6, 4)
	314 iload (6, 4)
	315 #6 (6, 4)
	316 if_icmpge (6, 4)
	317 90 (6, 4)
	319 aload (6, 4)
	320 #14 (6, 4)
	321 iload (6, 4)
	322 #26 (6, 4)
	323 iaload (6, 4)
	324 istore (6, 4)
	325 #27 (6, 4)
	326 dconst_0 (6, 4)
	327 dstore (6, 4)
	328 #28 (6, 4)
	329 iconst_0 (7, 4)
	330 istore (7, 4)
	331 #30 (7, 4)
	332 iload (7, 4)
	333 #30 (7, 4)
	334 iload (7, 4)
	335 #26 (7, 4)
	336 if_icmpge (7, 4)
	337 31 (7, 4)
	339 dload (7, 4)
	340 #28 (7, 4)
	341 aload (7, 4)
	342 #13 (7, 4)
	343 iload (7, 4)
	344 #30 (7, 4)
	345 aaload (7, 4)
	346 iload (7, 4)
	347 #27 (7, 4)
	348 daload (7, 4)
	349 aload (7, 4)
	350 #7 (7, 4)
	351 aload (7, 4)
	352 #14 (7, 4)
	353 iload (7, 4)
	354 #30 (7, 4)
	355 iaload (7, 4)
	356 daload (7, 4)
	357 dmul (7, 4)
	358 dadd (7, 4)
	359 dstore (7, 4)
	360 #28 (7, 4)
	361 iinc (7, 4)
	362 #30 (7, 4)
	363 -89 (7, 4)
	364 goto (7, 4)
	365 -32 (7, 4)
	367 aload (6, 4)
	368 #7 (6, 4)
	369 iload (6, 4)
	370 #27 (6, 4)
	371 daload (6, 4)
	372 dload (6, 4)
	373 #28 (6, 4)
	374 dsub (6, 4)
	375 aload (6, 4)
	376 #16 (6, 4)
	377 iload (6, 4)
	378 #27 (6, 4)
	379 daload (6, 4)
	380 ddiv (6, 4)
	381 dstore (6, 4)
	382 #30 (6, 4)
	383 aload (6, 4)
	384 #7 (6, 4)
	385 iload (6, 4)
	386 #27 (6, 4)
	387 dload (6, 4)
	388 #30 (6, 4)
	389 dastore (6, 4)
	390 dload (6, 4)
	391 #22 (6, 4)
	392 dload (6, 4)
	393 #30 (6, 4)
	394 dload (6, 4)
	395 #30 (6, 4)
	396 dmul (6, 4)
	397 dadd (6, 4)
	398 dstore (6, 4)
	399 #22 (6, 4)
	400 iinc (6, 4)
	401 #26 (6, 4)
	402 -89 (6, 4)
	403 goto (6, 4)
	404 -91 (6, 4)
	406 dload (5, 1)
	407 #20 (5, 1)
	408 dload_2 (5, 1)
	409 dload (5, 1)
	410 #22 (5, 1)
	411 dmul (5, 1)
	412 ddiv (5, 1)
	413 dstore (5, 1)
	414 #24 (5, 1)
	415 dconst_0 (5, 4)
	416 dstore (5, 4)
	417 #22 (5, 4)
	418 iconst_0 (6, 4)
	419 istore (6, 4)
	420 #26 (6, 4)
	421 iload (6, 4)
	422 #26 (6, 4)
	423 iload (6, 4)
	424 #6 (6, 4)
	425 if_icmpge (6, 4)
	426 73 (6, 4)
	428 aload (6, 4)
	429 #14 (6, 4)
	430 iload (6, 4)
	431 #26 (6, 4)
	432 iaload (6, 4)
	433 istore (6, 4)
	434 #27 (6, 4)
	435 dconst_0 (6, 4)
	436 dstore (6, 4)
	437 #28 (6, 4)
	438 iconst_0 (7, 4)
	439 istore (7, 4)
	440 #30 (7, 4)
	441 iload (7, 4)
	442 #30 (7, 4)
	443 iload (7, 4)
	444 #26 (7, 4)
	445 if_icmpgt (7, 4)
	446 27 (7, 4)
	448 dload (7, 4)
	449 #28 (7, 4)
	450 aload (7, 4)
	451 #13 (7, 4)
	452 iload (7, 4)
	453 #30 (7, 4)
	454 aaload (7, 4)
	455 iload (7, 4)
	456 #27 (7, 4)
	457 daload (7, 4)
	458 aload_1 (7, 4)
	459 iload (7, 4)
	460 #30 (7, 4)
	461 daload (7, 4)
	462 dmul (7, 4)
	463 dadd (7, 4)
	464 dstore (7, 4)
	465 #28 (7, 4)
	466 iinc (7, 4)
	467 #30 (7, 4)
	468 -89 (7, 4)
	469 goto (7, 4)
	470 -28 (7, 4)
	472 dload (6, 4)
	473 #28 (6, 4)
	474 aload (6, 4)
	475 #4 (6, 4)
	476 iload (6, 4)
	477 #27 (6, 4)
	478 daload (6, 4)
	479 ddiv (6, 4)
	480 dstore (6, 4)
	481 #28 (6, 4)
	482 dload (6, 4)
	483 #22 (6, 4)
	484 dload (6, 4)
	485 #28 (6, 4)
	486 dload (6, 4)
	487 #28 (6, 4)
	488 dmul (6, 4)
	489 dadd (6, 4)
	490 dstore (6, 4)
	491 #22 (6, 4)
	492 iinc (6, 4)
	493 #26 (6, 4)
	494 -89 (6, 4)
	495 goto (6, 4)
	496 -74 (6, 4)
	498 dload (5, 4)
	499 #22 (5, 4)
	500 invokestatic (5, 4)
	501 org/apache/commons/math3/util/FastMath.sqrt:(D)D (5, 4)
	503 dstore (5, 4)
	504 #26 (5, 4)
	505 dload (5, 4)
	506 #26 (5, 4)
	507 dload_2 (5, 4)
	508 ddiv (5, 4)
	509 dstore (5, 4)
	510 #28 (5, 4)
	511 dload (6, 1)
	512 #28 (6, 1)
	513 dconst_0 (6, 1)
	514 dcmpl (6, 1)
	515 ifne (6, 1)
	516 16 (6, 1)
	518 getstatic (6, 1)
	519 org/apache/commons/math3/util/Precision.SAFE_MIN:D (6, 1)
	521 dload_2 (6, 1)
	522 ldc2_w (6, 1)
	523 0.1 (6, 1)
	525 invokestatic (6, 1)
	526 org/apache/commons/math3/util/FastMath.min:(DD)D (6, 1)
	528 ddiv (6, 1)
	529 dstore (6, 1)
	530 #28 (6, 1)
	531 dload (6, 1)
	532 #28 (6, 1)
	533 dload (6, 1)
	534 #11 (6, 1)
	535 dload (6, 1)
	536 #24 (6, 1)
	537 invokestatic (6, 1)
	538 org/apache/commons/math3/util/FastMath.max:(DD)D (6, 1)
	540 invokestatic (6, 1)
	541 org/apache/commons/math3/util/FastMath.min:(DD)D (6, 1)
	543 dstore (6, 1)
	544 #11 (6, 1)
	545 dload (7, 1)
	546 #11 (7, 1)
	547 dconst_0 (7, 1)
	548 dcmpl (7, 1)
	549 ifne (7, 1)
	550 10 (7, 1)
	552 dload (7, 1)
	553 #26 (7, 1)
	554 dload (7, 1)
	555 #18 (7, 1)
	556 ddiv (7, 1)
	557 dstore (7, 1)
	558 #11 (7, 1)
	559 bipush (7, 4)
	560 10 (7, 4)
	561 istore (7, 4)
	562 #30 (7, 4)
	563 iload (7, 4)
	564 #30 (7, 4)
	565 iflt (7, 4)
	566 423 (7, 4)
	568 dload (8, 1)
	569 #11 (8, 1)
	570 dconst_0 (8, 1)
	571 dcmpl (8, 1)
	572 ifne (8, 1)
	573 17 (8, 1)
	575 getstatic (8, 1)
	576 org/apache/commons/math3/util/Precision.SAFE_MIN:D (8, 1)
	578 ldc2_w (8, 1)
	579 0.001 (8, 1)
	581 dload (8, 1)
	582 #28 (8, 1)
	583 dmul (8, 1)
	584 invokestatic (8, 1)
	585 org/apache/commons/math3/util/FastMath.max:(DD)D (8, 1)
	587 dstore (8, 1)
	588 #11 (8, 1)
	589 dload (7, 4)
	590 #11 (7, 4)
	591 invokestatic (7, 4)
	592 org/apache/commons/math3/util/FastMath.sqrt:(D)D (7, 4)
	594 dstore (7, 4)
	595 #31 (7, 4)
	596 iconst_0 (8, 4)
	597 istore (8, 4)
	598 #33 (8, 4)
	599 iload (8, 4)
	600 #33 (8, 4)
	601 iload (8, 4)
	602 #6 (8, 4)
	603 if_icmpge (8, 4)
	604 29 (8, 4)
	606 aload (8, 4)
	607 #14 (8, 4)
	608 iload (8, 4)
	609 #33 (8, 4)
	610 iaload (8, 4)
	611 istore (8, 4)
	612 #34 (8, 4)
	613 aload (8, 4)
	614 #7 (8, 4)
	615 iload (8, 4)
	616 #34 (8, 4)
	617 dload (8, 4)
	618 #31 (8, 4)
	619 aload (8, 4)
	620 #4 (8, 4)
	621 iload (8, 4)
	622 #34 (8, 4)
	623 daload (8, 4)
	624 dmul (8, 4)
	625 dastore (8, 4)
	626 iinc (8, 4)
	627 #33 (8, 4)
	628 -89 (8, 4)
	629 goto (8, 4)
	630 -30 (8, 4)
	632 aload_0 (7, 4)
	633 aload_1 (7, 4)
	634 aload (7, 4)
	635 #7 (7, 4)
	636 aload (7, 4)
	637 #8 (7, 4)
	638 aload (7, 4)
	639 #5 (7, 4)
	640 iload (7, 4)
	641 #6 (7, 4)
	642 aload (7, 4)
	643 #9 (7, 4)
	644 aload (7, 4)
	645 #10 (7, 4)
	646 invokespecial (7, 4)
	647 org/apache/commons/math3/fitting/leastsquares/LevenbergMarquardtOptimizer.determineLMDirection:([D[D[DLorg/apache/commons/math3/fitting/leastsquares/LevenbergMarquardtOptimizer$InternalData;I[D[D)V (7, 4)
	649 dconst_0 (7, 4)
	650 dstore (7, 4)
	651 #18 (7, 4)
	652 iconst_0 (8, 4)
	653 istore (8, 4)
	654 #33 (8, 4)
	655 iload (8, 4)
	656 #33 (8, 4)
	657 iload (8, 4)
	658 #6 (8, 4)
	659 if_icmpge (8, 4)
	660 46 (8, 4)
	662 aload (8, 4)
	663 #14 (8, 4)
	664 iload (8, 4)
	665 #33 (8, 4)
	666 iaload (8, 4)
	667 istore (8, 4)
	668 #34 (8, 4)
	669 aload (8, 4)
	670 #4 (8, 4)
	671 iload (8, 4)
	672 #34 (8, 4)
	673 daload (8, 4)
	674 aload (8, 4)
	675 #10 (8, 4)
	676 iload (8, 4)
	677 #34 (8, 4)
	678 daload (8, 4)
	679 dmul (8, 4)
	680 dstore (8, 4)
	681 #35 (8, 4)
	682 aload (8, 4)
	683 #9 (8, 4)
	684 iload (8, 4)
	685 #34 (8, 4)
	686 dload (8, 4)
	687 #35 (8, 4)
	688 dastore (8, 4)
	689 dload (8, 4)
	690 #18 (8, 4)
	691 dload (8, 4)
	692 #35 (8, 4)
	693 dload (8, 4)
	694 #35 (8, 4)
	695 dmul (8, 4)
	696 dadd (8, 4)
	697 dstore (8, 4)
	698 #18 (8, 4)
	699 iinc (8, 4)
	700 #33 (8, 4)
	701 -89 (8, 4)
	702 goto (8, 4)
	703 -47 (8, 4)
	705 dload (7, 4)
	706 #18 (7, 4)
	707 invokestatic (7, 4)
	708 org/apache/commons/math3/util/FastMath.sqrt:(D)D (7, 4)
	710 dstore (7, 4)
	711 #18 (7, 4)
	712 dload (7, 4)
	713 #20 (7, 4)
	714 dstore (7, 4)
	715 #33 (7, 4)
	716 dload (7, 4)
	717 #18 (7, 4)
	718 dload_2 (7, 4)
	719 dsub (7, 4)
	720 dstore (7, 4)
	721 #20 (7, 4)
	722 dload (10, 1)
	723 #20 (10, 1)
	724 invokestatic (10, 1)
	725 org/apache/commons/math3/util/FastMath.abs:(D)D (10, 1)
	727 ldc2_w (10, 1)
	728 0.1 (10, 1)
	730 dload_2 (10, 1)
	731 dmul (10, 1)
	732 dcmpg (10, 1)
	733 ifle (10, 1)
	734 25 (10, 1)
	736 dload (10, 1)
	737 #24 (10, 1)
	738 dconst_0 (10, 1)
	739 dcmpl (10, 1)
	740 ifne (10, 1)
	741 21 (10, 1)
	743 dload (10, 1)
	744 #20 (10, 1)
	745 dload (10, 1)
	746 #33 (10, 1)
	747 dcmpg (10, 1)
	748 ifgt (10, 1)
	749 13 (10, 1)
	751 dload (10, 1)
	752 #33 (10, 1)
	753 dconst_0 (10, 1)
	754 dcmpg (10, 1)
	755 ifge (10, 1)
	756 6 (10, 1)
	758 dload (10, 1)
	759 #11 (10, 1)
	760 dreturn (10, 1)
	761 iconst_0 (11, 4)
	762 istore (11, 4)
	763 #35 (11, 4)
	764 iload (11, 4)
	765 #35 (11, 4)
	766 iload (11, 4)
	767 #6 (11, 4)
	768 if_icmpge (11, 4)
	769 35 (11, 4)
	771 aload (11, 4)
	772 #14 (11, 4)
	773 iload (11, 4)
	774 #35 (11, 4)
	775 iaload (11, 4)
	776 istore (11, 4)
	777 #36 (11, 4)
	778 aload (11, 4)
	779 #7 (11, 4)
	780 iload (11, 4)
	781 #36 (11, 4)
	782 aload (11, 4)
	783 #9 (11, 4)
	784 iload (11, 4)
	785 #36 (11, 4)
	786 daload (11, 4)
	787 aload (11, 4)
	788 #4 (11, 4)
	789 iload (11, 4)
	790 #36 (11, 4)
	791 daload (11, 4)
	792 dmul (11, 4)
	793 dload (11, 4)
	794 #18 (11, 4)
	795 ddiv (11, 4)
	796 dastore (11, 4)
	797 iinc (11, 4)
	798 #35 (11, 4)
	799 -89 (11, 4)
	800 goto (11, 4)
	801 -36 (11, 4)
	803 iconst_0 (11, 4)
	804 istore (11, 4)
	805 #35 (11, 4)
	806 iload (11, 4)
	807 #35 (11, 4)
	808 iload (11, 4)
	809 #6 (11, 4)
	810 if_icmpge (11, 4)
	811 77 (11, 4)
	813 aload (11, 4)
	814 #14 (11, 4)
	815 iload (11, 4)
	816 #35 (11, 4)
	817 iaload (11, 4)
	818 istore (11, 4)
	819 #36 (11, 4)
	820 aload (11, 4)
	821 #7 (11, 4)
	822 iload (11, 4)
	823 #36 (11, 4)
	824 dup2 (11, 4)
	825 daload (11, 4)
	826 aload (11, 4)
	827 #8 (11, 4)
	828 iload (11, 4)
	829 #35 (11, 4)
	830 daload (11, 4)
	831 ddiv (11, 4)
	832 dastore (11, 4)
	833 aload (11, 4)
	834 #7 (11, 4)
	835 iload (11, 4)
	836 #36 (11, 4)
	837 daload (11, 4)
	838 dstore (11, 4)
	839 #37 (11, 4)
	840 iload (12, 4)
	841 #35 (12, 4)
	842 iconst_1 (12, 4)
	843 iadd (12, 4)
	844 istore (12, 4)
	845 #39 (12, 4)
	846 iload (12, 4)
	847 #39 (12, 4)
	848 iload (12, 4)
	849 #6 (12, 4)
	850 if_icmpge (12, 4)
	851 31 (12, 4)
	853 aload (12, 4)
	854 #7 (12, 4)
	855 aload (12, 4)
	856 #14 (12, 4)
	857 iload (12, 4)
	858 #39 (12, 4)
	859 iaload (12, 4)
	860 dup2 (12, 4)
	861 daload (12, 4)
	862 aload (12, 4)
	863 #13 (12, 4)
	864 iload (12, 4)
	865 #39 (12, 4)
	866 aaload (12, 4)
	867 iload (12, 4)
	868 #36 (12, 4)
	869 daload (12, 4)
	870 dload (12, 4)
	871 #37 (12, 4)
	872 dmul (12, 4)
	873 dsub (12, 4)
	874 dastore (12, 4)
	875 iinc (12, 4)
	876 #39 (12, 4)
	877 -89 (12, 4)
	878 goto (12, 4)
	879 -32 (12, 4)
	881 iinc (12, 4)
	882 #35 (12, 4)
	883 -89 (12, 4)
	884 goto (12, 4)
	885 -78 (12, 4)
	887 dconst_0 (11, 4)
	888 dstore (11, 4)
	889 #22 (11, 4)
	890 iconst_0 (12, 4)
	891 istore (12, 4)
	892 #35 (12, 4)
	893 iload (12, 4)
	894 #35 (12, 4)
	895 iload (12, 4)
	896 #6 (12, 4)
	897 if_icmpge (12, 4)
	898 29 (12, 4)
	900 aload (12, 4)
	901 #7 (12, 4)
	902 aload (12, 4)
	903 #14 (12, 4)
	904 iload (12, 4)
	905 #35 (12, 4)
	906 iaload (12, 4)
	907 daload (12, 4)
	908 dstore (12, 4)
	909 #36 (12, 4)
	910 dload (12, 4)
	911 #22 (12, 4)
	912 dload (12, 4)
	913 #36 (12, 4)
	914 dload (12, 4)
	915 #36 (12, 4)
	916 dmul (12, 4)
	917 dadd (12, 4)
	918 dstore (12, 4)
	919 #22 (12, 4)
	920 iinc (12, 4)
	921 #35 (12, 4)
	922 -89 (12, 4)
	923 goto (12, 4)
	924 -30 (12, 4)
	926 dload (11, 4)
	927 #20 (11, 4)
	928 dload_2 (11, 4)
	929 dload (11, 4)
	930 #22 (11, 4)
	931 dmul (11, 4)
	932 ddiv (11, 4)
	933 dstore (11, 4)
	934 #35 (11, 4)
	935 dload (12, 1)
	936 #20 (12, 1)
	937 dconst_0 (12, 1)
	938 dcmpl (12, 1)
	939 ifle (12, 1)
	940 15 (12, 1)
	942 dload (12, 1)
	943 #24 (12, 1)
	944 dload (12, 1)
	945 #11 (12, 1)
	946 invokestatic (12, 1)
	947 org/apache/commons/math3/util/FastMath.max:(DD)D (12, 1)
	949 dstore (12, 1)
	950 #24 (12, 1)
	951 goto (12, 1)
	952 19 (12, 1)
	954 dload (13, 1)
	955 #20 (13, 1)
	956 dconst_0 (13, 1)
	957 dcmpg (13, 1)
	958 ifge (13, 1)
	959 12 (13, 1)
	961 dload (13, 1)
	962 #28 (13, 1)
	963 dload (13, 1)
	964 #11 (13, 1)
	965 invokestatic (13, 1)
	966 org/apache/commons/math3/util/FastMath.min:(DD)D (13, 1)
	968 dstore (13, 1)
	969 #28 (13, 1)
	970 dload (12, 4)
	971 #24 (12, 4)
	972 dload (12, 4)
	973 #11 (12, 4)
	974 dload (12, 4)
	975 #35 (12, 4)
	976 dadd (12, 4)
	977 invokestatic (12, 4)
	978 org/apache/commons/math3/util/FastMath.max:(DD)D (12, 4)
	980 dstore (12, 4)
	981 #11 (12, 4)
	982 iinc (12, 4)
	983 #30 (12, 4)
	984 -89 (12, 4)
	985 goto (12, 4)
	986 -422 (12, 4)
	988 dload (10, 1)
	989 #11 (10, 1)
	990 dreturn (1, 1)

Method: determineLMDirection
	0 aload (0, 0)
	1 #4 (0, 0)
	2 invokestatic (0, 0)
	3 org/apache/commons/math3/fitting/leastsquares/LevenbergMarquardtOptimizer$InternalData.access$100:(Lorg/apache/commons/math3/fitting/leastsquares/LevenbergMarquardtOptimizer$InternalData;)[I (0, 0)
	5 astore (0, 0)
	6 #8 (0, 0)
	7 aload (0, 0)
	8 #4 (0, 0)
	9 invokestatic (0, 0)
	10 org/apache/commons/math3/fitting/leastsquares/LevenbergMarquardtOptimizer$InternalData.access$000:(Lorg/apache/commons/math3/fitting/leastsquares/LevenbergMarquardtOptimizer$InternalData;)[[D (0, 0)
	12 astore (0, 0)
	13 #9 (0, 0)
	14 aload (0, 0)
	15 #4 (0, 0)
	16 invokestatic (0, 0)
	17 org/apache/commons/math3/fitting/leastsquares/LevenbergMarquardtOptimizer$InternalData.access$200:(Lorg/apache/commons/math3/fitting/leastsquares/LevenbergMarquardtOptimizer$InternalData;)[D (0, 0)
	19 astore (0, 0)
	20 #10 (0, 0)
	21 iconst_0 (1, 4)
	22 istore (1, 4)
	23 #11 (1, 4)
	24 iload (1, 4)
	25 #11 (1, 4)
	26 iload (1, 4)
	27 #5 (1, 4)
	28 if_icmpge (1, 4)
	29 73 (1, 4)
	31 aload (1, 4)
	32 #8 (1, 4)
	33 iload (1, 4)
	34 #11 (1, 4)
	35 iaload (1, 4)
	36 istore (1, 4)
	37 #12 (1, 4)
	38 iload (2, 4)
	39 #11 (2, 4)
	40 iconst_1 (2, 4)
	41 iadd (2, 4)
	42 istore (2, 4)
	43 #13 (2, 4)
	44 iload (2, 4)
	45 #13 (2, 4)
	46 iload (2, 4)
	47 #5 (2, 4)
	48 if_icmpge (2, 4)
	49 28 (2, 4)
	51 aload (2, 4)
	52 #9 (2, 4)
	53 iload (2, 4)
	54 #13 (2, 4)
	55 aaload (2, 4)
	56 iload (2, 4)
	57 #12 (2, 4)
	58 aload (2, 4)
	59 #9 (2, 4)
	60 iload (2, 4)
	61 #11 (2, 4)
	62 aaload (2, 4)
	63 aload (2, 4)
	64 #8 (2, 4)
	65 iload (2, 4)
	66 #13 (2, 4)
	67 iaload (2, 4)
	68 daload (2, 4)
	69 dastore (2, 4)
	70 iinc (2, 4)
	71 #13 (2, 4)
	72 -89 (2, 4)
	73 goto (2, 4)
	74 -29 (2, 4)
	76 aload (1, 4)
	77 #7 (1, 4)
	78 iload (1, 4)
	79 #11 (1, 4)
	80 aload (1, 4)
	81 #10 (1, 4)
	82 iload (1, 4)
	83 #12 (1, 4)
	84 daload (1, 4)
	85 dastore (1, 4)
	86 aload (1, 4)
	87 #6 (1, 4)
	88 iload (1, 4)
	89 #11 (1, 4)
	90 aload_1 (1, 4)
	91 iload (1, 4)
	92 #11 (1, 4)
	93 daload (1, 4)
	94 dastore (1, 4)
	95 iinc (1, 4)
	96 #11 (1, 4)
	97 -89 (1, 4)
	98 goto (1, 4)
	99 -74 (1, 4)
	101 iconst_0 (1, 4)
	102 istore (1, 4)
	103 #11 (1, 4)
	104 iload (1, 4)
	105 #11 (1, 4)
	106 iload (1, 4)
	107 #5 (1, 4)
	108 if_icmpge (1, 4)
	109 335 (1, 4)
	111 aload (1, 4)
	112 #8 (1, 4)
	113 iload (1, 4)
	114 #11 (1, 4)
	115 iaload (1, 4)
	116 istore (1, 4)
	117 #12 (1, 4)
	118 aload_2 (1, 4)
	119 iload (1, 4)
	120 #12 (1, 4)
	121 daload (1, 4)
	122 dstore (1, 4)
	123 #13 (1, 4)
	124 dload (2, 1)
	125 #13 (2, 1)
	126 dconst_0 (2, 1)
	127 dcmpl (2, 1)
	128 ifeq (2, 1)
	129 14 (2, 1)
	131 aload_3 (2, 1)
	132 iload (2, 1)
	133 #11 (2, 1)
	134 iconst_1 (2, 1)
	135 iadd (2, 1)
	136 aload_3 (2, 1)
	137 arraylength (2, 1)
	138 dconst_0 (2, 1)
	139 invokestatic (2, 1)
	140 java/util/Arrays.fill:([DIID)V (2, 1)
	142 aload_3 (1, 4)
	143 iload (1, 4)
	144 #11 (1, 4)
	145 dload (1, 4)
	146 #13 (1, 4)
	147 dastore (1, 4)
	148 dconst_0 (3, 1)
	149 dstore (3, 1)
	150 #15 (3, 1)
	151 iload (4, 4)
	152 #11 (4, 4)
	153 istore (4, 4)
	154 #17 (4, 4)
	155 iload (4, 4)
	156 #17 (4, 4)
	157 iload (4, 4)
	158 #5 (4, 4)
	159 if_icmpge (4, 4)
	160 247 (4, 4)
	162 aload (4, 4)
	163 #8 (4, 4)
	164 iload (4, 4)
	165 #17 (4, 4)
	166 iaload (4, 4)
	167 istore (4, 4)
	168 #18 (4, 4)
	169 aload_3 (5, 1)
	170 iload (5, 1)
	171 #17 (5, 1)
	172 daload (5, 1)
	173 dconst_0 (5, 1)
	174 dcmpl (5, 1)
	175 ifeq (5, 1)
	176 225 (5, 1)
	178 aload (5, 1)
	179 #9 (5, 1)
	180 iload (5, 1)
	181 #17 (5, 1)
	182 aaload (5, 1)
	183 iload (5, 1)
	184 #18 (5, 1)
	185 daload (5, 1)
	186 dstore (5, 1)
	187 #23 (5, 1)
	188 dload (6, 1)
	189 #23 (6, 1)
	190 invokestatic (6, 1)
	191 org/apache/commons/math3/util/FastMath.abs:(D)D (6, 1)
	193 aload_3 (6, 1)
	194 iload (6, 1)
	195 #17 (6, 1)
	196 daload (6, 1)
	197 invokestatic (6, 1)
	198 org/apache/commons/math3/util/FastMath.abs:(D)D (6, 1)
	200 dcmpg (6, 1)
	201 ifge (6, 1)
	202 36 (6, 1)
	204 dload (6, 1)
	205 #23 (6, 1)
	206 aload_3 (6, 1)
	207 iload (6, 1)
	208 #17 (6, 1)
	209 daload (6, 1)
	210 ddiv (6, 1)
	211 dstore (6, 1)
	212 #25 (6, 1)
	213 dconst_1 (6, 1)
	214 dconst_1 (6, 1)
	215 dload (6, 1)
	216 #25 (6, 1)
	217 dload (6, 1)
	218 #25 (6, 1)
	219 dmul (6, 1)
	220 dadd (6, 1)
	221 invokestatic (6, 1)
	222 org/apache/commons/math3/util/FastMath.sqrt:(D)D (6, 1)
	224 ddiv (6, 1)
	225 dstore (6, 1)
	226 #19 (6, 1)
	227 dload (6, 1)
	228 #19 (6, 1)
	229 dload (6, 1)
	230 #25 (6, 1)
	231 dmul (6, 1)
	232 dstore (6, 1)
	233 #21 (6, 1)
	234 goto (7, 2)
	235 33 (7, 2)
	237 aload_3 (7, 2)
	238 iload (7, 2)
	239 #17 (7, 2)
	240 daload (7, 2)
	241 dload (7, 2)
	242 #23 (7, 2)
	243 ddiv (7, 2)
	244 dstore (7, 2)
	245 #25 (7, 2)
	246 dconst_1 (7, 2)
	247 dconst_1 (7, 2)
	248 dload (7, 2)
	249 #25 (7, 2)
	250 dload (7, 2)
	251 #25 (7, 2)
	252 dmul (7, 2)
	253 dadd (7, 2)
	254 invokestatic (7, 2)
	255 org/apache/commons/math3/util/FastMath.sqrt:(D)D (7, 2)
	257 ddiv (7, 2)
	258 dstore (7, 2)
	259 #21 (7, 2)
	260 dload (7, 2)
	261 #21 (7, 2)
	262 dload (7, 2)
	263 #25 (7, 2)
	264 dmul (7, 2)
	265 dstore (7, 2)
	266 #19 (7, 2)
	267 aload (7, 1)
	268 #9 (7, 1)
	269 iload (7, 1)
	270 #17 (7, 1)
	271 aaload (7, 1)
	272 iload (7, 1)
	273 #18 (7, 1)
	274 dload (7, 1)
	275 #21 (7, 1)
	276 dload (7, 1)
	277 #23 (7, 1)
	278 dmul (7, 1)
	279 dload (7, 1)
	280 #19 (7, 1)
	281 aload_3 (7, 1)
	282 iload (7, 1)
	283 #17 (7, 1)
	284 daload (7, 1)
	285 dmul (7, 1)
	286 dadd (7, 1)
	287 dastore (7, 1)
	288 dload (7, 1)
	289 #21 (7, 1)
	290 aload (7, 1)
	291 #6 (7, 1)
	292 iload (7, 1)
	293 #17 (7, 1)
	294 daload (7, 1)
	295 dmul (7, 1)
	296 dload (7, 1)
	297 #19 (7, 1)
	298 dload (7, 1)
	299 #15 (7, 1)
	300 dmul (7, 1)
	301 dadd (7, 1)
	302 dstore (7, 1)
	303 #25 (7, 1)
	304 dload (7, 1)
	305 #19 (7, 1)
	306 dneg (7, 1)
	307 aload (7, 1)
	308 #6 (7, 1)
	309 iload (7, 1)
	310 #17 (7, 1)
	311 daload (7, 1)
	312 dmul (7, 1)
	313 dload (7, 1)
	314 #21 (7, 1)
	315 dload (7, 1)
	316 #15 (7, 1)
	317 dmul (7, 1)
	318 dadd (7, 1)
	319 dstore (7, 1)
	320 #15 (7, 1)
	321 aload (7, 1)
	322 #6 (7, 1)
	323 iload (7, 1)
	324 #17 (7, 1)
	325 dload (7, 1)
	326 #25 (7, 1)
	327 dastore (7, 1)
	328 iload (9, 4)
	329 #17 (9, 4)
	330 iconst_1 (9, 4)
	331 iadd (9, 4)
	332 istore (9, 4)
	333 #27 (9, 4)
	334 iload (9, 4)
	335 #27 (9, 4)
	336 iload (9, 4)
	337 #5 (9, 4)
	338 if_icmpge (9, 4)
	339 62 (9, 4)
	341 aload (9, 4)
	342 #9 (9, 4)
	343 iload (9, 4)
	344 #27 (9, 4)
	345 aaload (9, 4)
	346 iload (9, 4)
	347 #18 (9, 4)
	348 daload (9, 4)
	349 dstore (9, 4)
	350 #28 (9, 4)
	351 dload (9, 4)
	352 #21 (9, 4)
	353 dload (9, 4)
	354 #28 (9, 4)
	355 dmul (9, 4)
	356 dload (9, 4)
	357 #19 (9, 4)
	358 aload_3 (9, 4)
	359 iload (9, 4)
	360 #27 (9, 4)
	361 daload (9, 4)
	362 dmul (9, 4)
	363 dadd (9, 4)
	364 dstore (9, 4)
	365 #30 (9, 4)
	366 aload_3 (9, 4)
	367 iload (9, 4)
	368 #27 (9, 4)
	369 dload (9, 4)
	370 #19 (9, 4)
	371 dneg (9, 4)
	372 dload (9, 4)
	373 #28 (9, 4)
	374 dmul (9, 4)
	375 dload (9, 4)
	376 #21 (9, 4)
	377 aload_3 (9, 4)
	378 iload (9, 4)
	379 #27 (9, 4)
	380 daload (9, 4)
	381 dmul (9, 4)
	382 dadd (9, 4)
	383 dastore (9, 4)
	384 aload (9, 4)
	385 #9 (9, 4)
	386 iload (9, 4)
	387 #27 (9, 4)
	388 aaload (9, 4)
	389 iload (9, 4)
	390 #18 (9, 4)
	391 dload (9, 4)
	392 #30 (9, 4)
	393 dastore (9, 4)
	394 iinc (9, 4)
	395 #27 (9, 4)
	396 -89 (9, 4)
	397 goto (9, 4)
	398 -63 (9, 4)
	400 iinc (9, 4)
	401 #17 (9, 4)
	402 -89 (9, 4)
	403 goto (9, 4)
	404 -248 (9, 4)
	406 aload_3 (8, 4)
	407 iload (8, 4)
	408 #11 (8, 4)
	409 aload (8, 4)
	410 #9 (8, 4)
	411 iload (8, 4)
	412 #11 (8, 4)
	413 aaload (8, 4)
	414 aload (8, 4)
	415 #8 (8, 4)
	416 iload (8, 4)
	417 #11 (8, 4)
	418 iaload (8, 4)
	419 daload (8, 4)
	420 dastore (8, 4)
	421 aload (8, 4)
	422 #9 (8, 4)
	423 iload (8, 4)
	424 #11 (8, 4)
	425 aaload (8, 4)
	426 aload (8, 4)
	427 #8 (8, 4)
	428 iload (8, 4)
	429 #11 (8, 4)
	430 iaload (8, 4)
	431 aload (8, 4)
	432 #7 (8, 4)
	433 iload (8, 4)
	434 #11 (8, 4)
	435 daload (8, 4)
	436 dastore (8, 4)
	437 iinc (8, 4)
	438 #11 (8, 4)
	439 -89 (8, 4)
	440 goto (8, 4)
	441 -336 (8, 4)
	443 iload (5, 1)
	444 #5 (5, 1)
	445 istore (5, 1)
	446 #11 (5, 1)
	447 iconst_0 (6, 4)
	448 istore (6, 4)
	449 #12 (6, 4)
	450 iload (6, 4)
	451 #12 (6, 4)
	452 iload (6, 4)
	453 #5 (6, 4)
	454 if_icmpge (6, 4)
	455 42 (6, 4)
	457 aload_3 (7, 1)
	458 iload (7, 1)
	459 #12 (7, 1)
	460 daload (7, 1)
	461 dconst_0 (7, 1)
	462 dcmpl (7, 1)
	463 ifne (7, 1)
	464 14 (7, 1)
	466 iload (7, 1)
	467 #11 (7, 1)
	468 iload (7, 1)
	469 #5 (7, 1)
	470 if_icmpne (7, 1)
	471 7 (7, 1)
	473 iload (7, 1)
	474 #12 (7, 1)
	475 istore (7, 1)
	476 #11 (7, 1)
	477 iload (7, 1)
	478 #11 (7, 1)
	479 iload (7, 1)
	480 #5 (7, 1)
	481 if_icmpge (7, 1)
	482 9 (7, 1)
	484 aload (7, 1)
	485 #6 (7, 1)
	486 iload (7, 1)
	487 #12 (7, 1)
	488 dconst_0 (7, 1)
	489 dastore (7, 1)
	490 iinc (7, 1)
	491 #12 (7, 1)
	492 -89 (7, 1)
	493 goto (7, 1)
	494 -43 (7, 1)
	496 iload (7, 1)
	497 #11 (7, 1)
	498 ifle (7, 1)
	499 86 (7, 1)
	501 iload (8, 4)
	502 #11 (8, 4)
	503 iconst_1 (8, 4)
	504 isub (8, 4)
	505 istore (8, 4)
	506 #12 (8, 4)
	507 iload (8, 4)
	508 #12 (8, 4)
	509 iflt (8, 4)
	510 75 (8, 4)
	512 aload (8, 4)
	513 #8 (8, 4)
	514 iload (8, 4)
	515 #12 (8, 4)
	516 iaload (8, 4)
	517 istore (8, 4)
	518 #13 (8, 4)
	519 dconst_0 (8, 4)
	520 dstore (8, 4)
	521 #14 (8, 4)
	522 iload (9, 4)
	523 #12 (9, 4)
	524 iconst_1 (9, 4)
	525 iadd (9, 4)
	526 istore (9, 4)
	527 #16 (9, 4)
	528 iload (9, 4)
	529 #16 (9, 4)
	530 iload (9, 4)
	531 #11 (9, 4)
	532 if_icmpge (9, 4)
	533 28 (9, 4)
	535 dload (9, 4)
	536 #14 (9, 4)
	537 aload (9, 4)
	538 #9 (9, 4)
	539 iload (9, 4)
	540 #16 (9, 4)
	541 aaload (9, 4)
	542 iload (9, 4)
	543 #13 (9, 4)
	544 daload (9, 4)
	545 aload (9, 4)
	546 #6 (9, 4)
	547 iload (9, 4)
	548 #16 (9, 4)
	549 daload (9, 4)
	550 dmul (9, 4)
	551 dadd (9, 4)
	552 dstore (9, 4)
	553 #14 (9, 4)
	554 iinc (9, 4)
	555 #16 (9, 4)
	556 -89 (9, 4)
	557 goto (9, 4)
	558 -29 (9, 4)
	560 aload (8, 4)
	561 #6 (8, 4)
	562 iload (8, 4)
	563 #12 (8, 4)
	564 aload (8, 4)
	565 #6 (8, 4)
	566 iload (8, 4)
	567 #12 (8, 4)
	568 daload (8, 4)
	569 dload (8, 4)
	570 #14 (8, 4)
	571 dsub (8, 4)
	572 aload_3 (8, 4)
	573 iload (8, 4)
	574 #12 (8, 4)
	575 daload (8, 4)
	576 ddiv (8, 4)
	577 dastore (8, 4)
	578 iinc (8, 4)
	579 #12 (8, 4)
	580 -89 (8, 4)
	581 goto (8, 4)
	582 -74 (8, 4)
	584 iconst_0 (7, 4)
	585 istore (7, 4)
	586 #12 (7, 4)
	587 iload (7, 4)
	588 #12 (7, 4)
	589 aload (7, 4)
	590 #7 (7, 4)
	591 arraylength (7, 4)
	592 if_icmpge (7, 4)
	593 22 (7, 4)
	595 aload (7, 4)
	596 #7 (7, 4)
	597 aload (7, 4)
	598 #8 (7, 4)
	599 iload (7, 4)
	600 #12 (7, 4)
	601 iaload (7, 4)
	602 aload (7, 4)
	603 #6 (7, 4)
	604 iload (7, 4)
	605 #12 (7, 4)
	606 daload (7, 4)
	607 dastore (7, 4)
	608 iinc (7, 4)
	609 #12 (7, 4)
	610 -89 (7, 4)
	611 goto (7, 4)
	612 -24 (7, 4)
	614 return (2, 1)

Method: qrDecomposition
	0 aload_1 (0, 0)
	1 ldc2_w (0, 0)
	2 -1.0 (0, 0)
	4 invokeinterface (0, 0)
	5 org/apache/commons/math3/linear/RealMatrix.getData:()[[D (0, 0)
	7 0 (0, 0)
	9 invokeinterface (0, 0)
	10 org/apache/commons/math3/linear/RealMatrix.java/lang/Double (0, 0)
	12 0 (0, 0)
	14 astore_3 (0, 0)
	15 aload_3 (0, 0)
	16 arraylength (0, 0)
	17 istore (0, 0)
	18 #4 (0, 0)
	19 aload_3 (0, 0)
	20 iconst_0 (0, 0)
	21 aaload (0, 0)
	22 arraylength (0, 0)
	23 istore (0, 0)
	24 #5 (0, 0)
	25 iload (0, 0)
	26 #5 (0, 0)
	27 newarray (0, 0)
	28 10 (0, 0)
	29 astore (0, 0)
	30 #6 (0, 0)
	31 iload (0, 0)
	32 #5 (0, 0)
	33 newarray (0, 0)
	34 7 (0, 0)
	35 astore (0, 0)
	36 #7 (0, 0)
	37 iload (0, 0)
	38 #5 (0, 0)
	39 newarray (0, 0)
	40 7 (0, 0)
	41 astore (0, 0)
	42 #8 (0, 0)
	43 iload (0, 0)
	44 #5 (0, 0)
	45 newarray (0, 0)
	46 7 (0, 0)
	47 astore (0, 0)
	48 #9 (0, 0)
	49 iconst_0 (1, 4)
	50 istore (1, 4)
	51 #10 (1, 4)
	52 iload (1, 4)
	53 #10 (1, 4)
	54 iload (1, 4)
	55 #5 (1, 4)
	56 if_icmpge (1, 4)
	57 64 (1, 4)
	59 aload (1, 4)
	60 #6 (1, 4)
	61 iload (1, 4)
	62 #10 (1, 4)
	63 iload (1, 4)
	64 #10 (1, 4)
	65 iastore (1, 4)
	66 dconst_0 (1, 4)
	67 dstore (1, 4)
	68 #11 (1, 4)
	69 iconst_0 (2, 4)
	70 istore (2, 4)
	71 #13 (2, 4)
	72 iload (2, 4)
	73 #13 (2, 4)
	74 iload (2, 4)
	75 #4 (2, 4)
	76 if_icmpge (2, 4)
	77 28 (2, 4)
	79 aload_3 (2, 4)
	80 iload (2, 4)
	81 #13 (2, 4)
	82 aaload (2, 4)
	83 iload (2, 4)
	84 #10 (2, 4)
	85 daload (2, 4)
	86 dstore (2, 4)
	87 #14 (2, 4)
	88 dload (2, 4)
	89 #11 (2, 4)
	90 dload (2, 4)
	91 #14 (2, 4)
	92 dload (2, 4)
	93 #14 (2, 4)
	94 dmul (2, 4)
	95 dadd (2, 4)
	96 dstore (2, 4)
	97 #11 (2, 4)
	98 iinc (2, 4)
	99 #13 (2, 4)
	100 -89 (2, 4)
	101 goto (2, 4)
	102 -29 (2, 4)
	104 aload (1, 4)
	105 #8 (1, 4)
	106 iload (1, 4)
	107 #10 (1, 4)
	108 dload (1, 4)
	109 #11 (1, 4)
	110 invokestatic (1, 4)
	111 org/apache/commons/math3/util/FastMath.sqrt:(D)D (1, 4)
	113 dastore (1, 4)
	114 iinc (1, 4)
	115 #10 (1, 4)
	116 -89 (1, 4)
	117 goto (1, 4)
	118 -65 (1, 4)
	120 iconst_0 (2, 4)
	121 istore (2, 4)
	122 #10 (2, 4)
	123 iload (2, 4)
	124 #10 (2, 4)
	125 iload (2, 4)
	126 #5 (2, 4)
	127 if_icmpge (2, 4)
	128 378 (2, 4)
	130 iconst_m1 (2, 4)
	131 istore (2, 4)
	132 #11 (2, 4)
	133 ldc2_w (2, 4)
	134 -inf (2, 4)
	136 dstore (2, 4)
	137 #12 (2, 4)
	138 iload (3, 4)
	139 #10 (3, 4)
	140 istore (3, 4)
	141 #14 (3, 4)
	142 iload (3, 4)
	143 #14 (3, 4)
	144 iload (3, 4)
	145 #5 (3, 4)
	146 if_icmpge (3, 4)
	147 114 (3, 4)
	149 dconst_0 (3, 4)
	150 dstore (3, 4)
	151 #15 (3, 4)
	152 iload (4, 4)
	153 #10 (4, 4)
	154 istore (4, 4)
	155 #17 (4, 4)
	156 iload (4, 4)
	157 #17 (4, 4)
	158 iload (4, 4)
	159 #4 (4, 4)
	160 if_icmpge (4, 4)
	161 31 (4, 4)
	163 aload_3 (4, 4)
	164 iload (4, 4)
	165 #17 (4, 4)
	166 aaload (4, 4)
	167 aload (4, 4)
	168 #6 (4, 4)
	169 iload (4, 4)
	170 #14 (4, 4)
	171 iaload (4, 4)
	172 daload (4, 4)
	173 dstore (4, 4)
	174 #18 (4, 4)
	175 dload (4, 4)
	176 #15 (4, 4)
	177 dload (4, 4)
	178 #18 (4, 4)
	179 dload (4, 4)
	180 #18 (4, 4)
	181 dmul (4, 4)
	182 dadd (4, 4)
	183 dstore (4, 4)
	184 #15 (4, 4)
	185 iinc (4, 4)
	186 #17 (4, 4)
	187 -89 (4, 4)
	188 goto (4, 4)
	189 -32 (4, 4)
	191 dload (4, 1)
	192 #15 (4, 1)
	193 invokestatic (4, 1)
	194 java/lang/Double.isInfinite:(D)Z (4, 1)
	196 ifne (4, 1)
	197 11 (4, 1)
	199 dload (4, 1)
	200 #15 (4, 1)
	201 invokestatic (4, 1)
	202 java/lang/Double.isNaN:(D)Z (4, 1)
	204 ifeq (4, 1)
	205 34 (4, 1)
	207 new (4, 1)
	208 org/apache/commons/math3/exception/ConvergenceException (4, 1)
	210 dup (4, 1)
	211 getstatic (4, 1)
	212 org/apache/commons/math3/exception/util/LocalizedFormats.UNABLE_TO_PERFORM_QR_DECOMPOSITION_ON_JACOBIAN:Lorg/apache/commons/math3/exception/util/LocalizedFormats; (4, 1)
	214 iconst_2 (4, 1)
	215 anewarray (4, 1)
	216 java/lang/Object (4, 1)
	218 dup (4, 1)
	219 iconst_0 (4, 1)
	220 iload (4, 1)
	221 #4 (4, 1)
	222 invokestatic (4, 1)
	223 java/lang/Integer.valueOf:(I)Ljava/lang/Integer; (4, 1)
	225 aastore (4, 1)
	226 dup (4, 1)
	227 iconst_1 (4, 1)
	228 iload (4, 1)
	229 #5 (4, 1)
	230 invokestatic (4, 1)
	231 java/lang/Integer.valueOf:(I)Ljava/lang/Integer; (4, 1)
	233 aastore (4, 1)
	234 invokespecial (4, 1)
	235 org/apache/commons/math3/exception/ConvergenceException.<init>:(Lorg/apache/commons/math3/exception/util/Localizable;[Ljava/lang/Object;)V (4, 1)
	237 athrow (4, 1)
	238 dload (4, 1)
	239 #15 (4, 1)
	240 dload (4, 1)
	241 #12 (4, 1)
	242 dcmpl (4, 1)
	243 ifle (4, 1)
	244 11 (4, 1)
	246 iload (4, 1)
	247 #14 (4, 1)
	248 istore (4, 1)
	249 #11 (4, 1)
	250 dload (4, 1)
	251 #15 (4, 1)
	252 dstore (4, 1)
	253 #12 (4, 1)
	254 iinc (4, 1)
	255 #14 (4, 1)
	256 -89 (4, 1)
	257 goto (4, 1)
	258 -115 (4, 1)
	260 dload (4, 1)
	261 #12 (4, 1)
	262 aload_0 (4, 1)
	263 getfield (4, 1)
	264 org/apache/commons/math3/fitting/leastsquares/LevenbergMarquardtOptimizer.qrRankingThreshold:D (4, 1)
	266 dcmpg (4, 1)
	267 ifgt (4, 1)
	268 22 (4, 1)
	270 new (4, 1)
	271 org/apache/commons/math3/fitting/leastsquares/LevenbergMarquardtOptimizer$InternalData (4, 1)
	273 dup (4, 1)
	274 aload_3 (4, 1)
	275 aload (4, 1)
	276 #6 (4, 1)
	277 iload (4, 1)
	278 #10 (4, 1)
	279 aload (4, 1)
	280 #7 (4, 1)
	281 aload (4, 1)
	282 #8 (4, 1)
	283 aload (4, 1)
	284 #9 (4, 1)
	285 invokespecial (4, 1)
	286 org/apache/commons/math3/fitting/leastsquares/LevenbergMarquardtOptimizer$InternalData.<init>:([[D[II[D[D[D)V (4, 1)
	288 areturn (4, 1)
	289 aload (3, 4)
	290 #6 (3, 4)
	291 iload (3, 4)
	292 #11 (3, 4)
	293 iaload (3, 4)
	294 istore (3, 4)
	295 #14 (3, 4)
	296 aload (3, 4)
	297 #6 (3, 4)
	298 iload (3, 4)
	299 #11 (3, 4)
	300 aload (3, 4)
	301 #6 (3, 4)
	302 iload (3, 4)
	303 #10 (3, 4)
	304 iaload (3, 4)
	305 iastore (3, 4)
	306 aload (3, 4)
	307 #6 (3, 4)
	308 iload (3, 4)
	309 #10 (3, 4)
	310 iload (3, 4)
	311 #14 (3, 4)
	312 iastore (3, 4)
	313 aload_3 (3, 4)
	314 iload (3, 4)
	315 #10 (3, 4)
	316 aaload (3, 4)
	317 iload (3, 4)
	318 #14 (3, 4)
	319 daload (3, 4)
	320 dstore (3, 4)
	321 #15 (3, 4)
	322 dload (3, 4)
	323 #15 (3, 4)
	324 dconst_0 (3, 4)
	325 dcmpl (3, 4)
	326 ifle (3, 4)
	327 12 (3, 4)
	329 dload (3, 4)
	330 #12 (3, 4)
	331 invokestatic (3, 4)
	332 org/apache/commons/math3/util/FastMath.sqrt:(D)D (3, 4)
	334 dneg (3, 4)
	335 goto (3, 4)
	336 8 (3, 4)
	338 dload (3, 4)
	339 #12 (3, 4)
	340 invokestatic (3, 4)
	341 org/apache/commons/math3/util/FastMath.sqrt:(D)D (3, 4)
	343 dstore (3, 4)
	344 #17 (3, 4)
	345 dconst_1 (3, 4)
	346 dload (3, 4)
	347 #12 (3, 4)
	348 dload (3, 4)
	349 #15 (3, 4)
	350 dload (3, 4)
	351 #17 (3, 4)
	352 dmul (3, 4)
	353 dsub (3, 4)
	354 ddiv (3, 4)
	355 dstore (3, 4)
	356 #19 (3, 4)
	357 aload (3, 4)
	358 #9 (3, 4)
	359 iload (3, 4)
	360 #14 (3, 4)
	361 dload (3, 4)
	362 #19 (3, 4)
	363 dastore (3, 4)
	364 aload (4, 4)
	365 #7 (4, 4)
	366 iload (4, 4)
	367 #14 (4, 4)
	368 dload (4, 4)
	369 #17 (4, 4)
	370 dastore (4, 4)
	371 aload_3 (4, 4)
	372 iload (4, 4)
	373 #10 (4, 4)
	374 aaload (4, 4)
	375 iload (4, 4)
	376 #14 (4, 4)
	377 dup2 (4, 4)
	378 daload (4, 4)
	379 dload (4, 4)
	380 #17 (4, 4)
	381 dsub (4, 4)
	382 dastore (4, 4)
	383 iload (6, 4)
	384 #5 (6, 4)
	385 iconst_1 (6, 4)
	386 isub (6, 4)
	387 iload (6, 4)
	388 #10 (6, 4)
	389 isub (6, 4)
	390 istore (6, 4)
	391 #21 (6, 4)
	392 iload (6, 4)
	393 #21 (6, 4)
	394 ifle (6, 4)
	395 105 (6, 4)
	397 dconst_0 (6, 4)
	398 dstore (6, 4)
	399 #22 (6, 4)
	400 iload (7, 4)
	401 #10 (7, 4)
	402 istore (7, 4)
	403 #24 (7, 4)
	404 iload (7, 4)
	405 #24 (7, 4)
	406 iload (7, 4)
	407 #4 (7, 4)
	408 if_icmpge (7, 4)
	409 35 (7, 4)
	411 dload (7, 4)
	412 #22 (7, 4)
	413 aload_3 (7, 4)
	414 iload (7, 4)
	415 #24 (7, 4)
	416 aaload (7, 4)
	417 iload (7, 4)
	418 #14 (7, 4)
	419 daload (7, 4)
	420 aload_3 (7, 4)
	421 iload (7, 4)
	422 #24 (7, 4)
	423 aaload (7, 4)
	424 aload (7, 4)
	425 #6 (7, 4)
	426 iload (7, 4)
	427 #10 (7, 4)
	428 iload (7, 4)
	429 #21 (7, 4)
	430 iadd (7, 4)
	431 iaload (7, 4)
	432 daload (7, 4)
	433 dmul (7, 4)
	434 dadd (7, 4)
	435 dstore (7, 4)
	436 #22 (7, 4)
	437 iinc (7, 4)
	438 #24 (7, 4)
	439 -89 (7, 4)
	440 goto (7, 4)
	441 -36 (7, 4)
	443 dload (6, 4)
	444 #22 (6, 4)
	445 dload (6, 4)
	446 #19 (6, 4)
	447 dmul (6, 4)
	448 dstore (6, 4)
	449 #22 (6, 4)
	450 iload (7, 4)
	451 #10 (7, 4)
	452 istore (7, 4)
	453 #24 (7, 4)
	454 iload (7, 4)
	455 #24 (7, 4)
	456 iload (7, 4)
	457 #4 (7, 4)
	458 if_icmpge (7, 4)
	459 35 (7, 4)
	461 aload_3 (7, 4)
	462 iload (7, 4)
	463 #24 (7, 4)
	464 aaload (7, 4)
	465 aload (7, 4)
	466 #6 (7, 4)
	467 iload (7, 4)
	468 #10 (7, 4)
	469 iload (7, 4)
	470 #21 (7, 4)
	471 iadd (7, 4)
	472 iaload (7, 4)
	473 dup2 (7, 4)
	474 daload (7, 4)
	475 dload (7, 4)
	476 #22 (7, 4)
	477 aload_3 (7, 4)
	478 iload (7, 4)
	479 #24 (7, 4)
	480 aaload (7, 4)
	481 iload (7, 4)
	482 #14 (7, 4)
	483 daload (7, 4)
	484 dmul (7, 4)
	485 dsub (7, 4)
	486 dastore (7, 4)
	487 iinc (7, 4)
	488 #24 (7, 4)
	489 -89 (7, 4)
	490 goto (7, 4)
	491 -36 (7, 4)
	493 iinc (7, 4)
	494 #21 (7, 4)
	495 -89 (7, 4)
	496 goto (7, 4)
	497 -104 (7, 4)
	499 iinc (7, 4)
	500 #10 (7, 4)
	501 -89 (7, 4)
	502 goto (7, 4)
	503 -379 (7, 4)
	505 new (6, 4)
	506 org/apache/commons/math3/fitting/leastsquares/LevenbergMarquardtOptimizer$InternalData (6, 4)
	508 dup (6, 4)
	509 aload_3 (6, 4)
	510 aload (6, 4)
	511 #6 (6, 4)
	512 iload_2 (6, 4)
	513 aload (6, 4)
	514 #7 (6, 4)
	515 aload (6, 4)
	516 #8 (6, 4)
	517 aload (6, 4)
	518 #9 (6, 4)
	519 invokespecial (6, 4)
	520 org/apache/commons/math3/fitting/leastsquares/LevenbergMarquardtOptimizer$InternalData.<init>:([[D[II[D[D[D)V (6, 4)
	522 areturn (3, 4)

Method: qTy
	0 aload_2 (0, 0)
	1 invokestatic (0, 0)
	2 org/apache/commons/math3/fitting/leastsquares/LevenbergMarquardtOptimizer$InternalData.access$000:(Lorg/apache/commons/math3/fitting/leastsquares/LevenbergMarquardtOptimizer$InternalData;)[[D (0, 0)
	4 astore_3 (0, 0)
	5 aload_2 (0, 0)
	6 invokestatic (0, 0)
	7 org/apache/commons/math3/fitting/leastsquares/LevenbergMarquardtOptimizer$InternalData.access$100:(Lorg/apache/commons/math3/fitting/leastsquares/LevenbergMarquardtOptimizer$InternalData;)[I (0, 0)
	9 astore (0, 0)
	10 #4 (0, 0)
	11 aload_2 (0, 0)
	12 invokestatic (0, 0)
	13 org/apache/commons/math3/fitting/leastsquares/LevenbergMarquardtOptimizer$InternalData.access$500:(Lorg/apache/commons/math3/fitting/leastsquares/LevenbergMarquardtOptimizer$InternalData;)[D (0, 0)
	15 astore (0, 0)
	16 #5 (0, 0)
	17 aload_3 (0, 0)
	18 arraylength (0, 0)
	19 istore (0, 0)
	20 #6 (0, 0)
	21 aload_3 (0, 0)
	22 iconst_0 (0, 0)
	23 aaload (0, 0)
	24 arraylength (0, 0)
	25 istore (0, 0)
	26 #7 (0, 0)
	27 iconst_0 (1, 4)
	28 istore (1, 4)
	29 #8 (1, 4)
	30 iload (1, 4)
	31 #8 (1, 4)
	32 iload (1, 4)
	33 #7 (1, 4)
	34 if_icmpge (1, 4)
	35 97 (1, 4)
	37 aload (1, 4)
	38 #4 (1, 4)
	39 iload (1, 4)
	40 #8 (1, 4)
	41 iaload (1, 4)
	42 istore (1, 4)
	43 #9 (1, 4)
	44 dconst_0 (1, 4)
	45 dstore (1, 4)
	46 #10 (1, 4)
	47 iload (2, 4)
	48 #8 (2, 4)
	49 istore (2, 4)
	50 #12 (2, 4)
	51 iload (2, 4)
	52 #12 (2, 4)
	53 iload (2, 4)
	54 #6 (2, 4)
	55 if_icmpge (2, 4)
	56 26 (2, 4)
	58 dload (2, 4)
	59 #10 (2, 4)
	60 aload_3 (2, 4)
	61 iload (2, 4)
	62 #12 (2, 4)
	63 aaload (2, 4)
	64 iload (2, 4)
	65 #9 (2, 4)
	66 daload (2, 4)
	67 aload_1 (2, 4)
	68 iload (2, 4)
	69 #12 (2, 4)
	70 daload (2, 4)
	71 dmul (2, 4)
	72 dadd (2, 4)
	73 dstore (2, 4)
	74 #10 (2, 4)
	75 iinc (2, 4)
	76 #12 (2, 4)
	77 -89 (2, 4)
	78 goto (2, 4)
	79 -27 (2, 4)
	81 dload (1, 4)
	82 #10 (1, 4)
	83 aload (1, 4)
	84 #5 (1, 4)
	85 iload (1, 4)
	86 #9 (1, 4)
	87 daload (1, 4)
	88 dmul (1, 4)
	89 dstore (1, 4)
	90 #10 (1, 4)
	91 iload (2, 4)
	92 #8 (2, 4)
	93 istore (2, 4)
	94 #12 (2, 4)
	95 iload (2, 4)
	96 #12 (2, 4)
	97 iload (2, 4)
	98 #6 (2, 4)
	99 if_icmpge (2, 4)
	100 26 (2, 4)
	102 aload_1 (2, 4)
	103 iload (2, 4)
	104 #12 (2, 4)
	105 dup2 (2, 4)
	106 daload (2, 4)
	107 dload (2, 4)
	108 #10 (2, 4)
	109 aload_3 (2, 4)
	110 iload (2, 4)
	111 #12 (2, 4)
	112 aaload (2, 4)
	113 iload (2, 4)
	114 #9 (2, 4)
	115 daload (2, 4)
	116 dmul (2, 4)
	117 dsub (2, 4)
	118 dastore (2, 4)
	119 iinc (2, 4)
	120 #12 (2, 4)
	121 -89 (2, 4)
	122 goto (2, 4)
	123 -27 (2, 4)
	125 iinc (2, 4)
	126 #8 (2, 4)
	127 -89 (2, 4)
	128 goto (2, 4)
	129 -98 (2, 4)
	131 return (0, 0)

Method: <clinit>
	0 ldc2_w (0, 0)
	1 2.0 (0, 0)
	3 getstatic (0, 0)
	4 org/apache/commons/math3/util/Precision.EPSILON:D (0, 0)
	6 dmul (0, 0)
	7 putstatic (0, 0)
	8 org/apache/commons/math3/fitting/leastsquares/LevenbergMarquardtOptimizer.TWO_EPS:D (0, 0)
	10 return (0, 0)

