Method: <init>
	0 aload_0 (0, 0)
	1 aload_2 (0, 0)
	2 invokespecial (0, 0)
	3 org/apache/commons/math3/optim/nonlinear/vector/jacobian/AbstractLeastSquaresOptimizer.<init>:(Lorg/apache/commons/math3/optim/ConvergenceChecker;)V (0, 0)
	5 aload_0 (0, 0)
	6 iload_1 (0, 0)
	7 putfield (0, 0)
	8 org/apache/commons/math3/optim/nonlinear/vector/jacobian/GaussNewtonOptimizer.useLU:Z (0, 0)
	10 return (0, 0)

Method: doOptimize
	0 aload_0 (0, 0)
	1 invokevirtual (0, 0)
	2 org/apache/commons/math3/optim/nonlinear/vector/jacobian/GaussNewtonOptimizer.doOptimize:()Lorg/apache/commons/math3/optim/PointVectorValuePair; (0, 0)
	4 areturn (0, 0)

Method: checkParameters
	0 aload_0 (1, 1)
	1 invokevirtual (1, 1)
	2 org/apache/commons/math3/optim/nonlinear/vector/jacobian/GaussNewtonOptimizer.getLowerBound:()[D (1, 1)
	4 ifnonnull (1, 1)
	5 10 (1, 1)
	7 aload_0 (1, 1)
	8 invokevirtual (1, 1)
	9 org/apache/commons/math3/optim/nonlinear/vector/jacobian/GaussNewtonOptimizer.getUpperBound:()[D (1, 1)
	11 ifnull (1, 1)
	12 18 (1, 1)
	14 new (1, 1)
	15 org/apache/commons/math3/exception/MathUnsupportedOperationException (1, 1)
	17 dup (1, 1)
	18 getstatic (1, 1)
	19 org/apache/commons/math3/exception/util/LocalizedFormats.CONSTRAINT:Lorg/apache/commons/math3/exception/util/LocalizedFormats; (1, 1)
	21 iconst_0 (1, 1)
	22 anewarray (1, 1)
	23 java/lang/Object (1, 1)
	25 invokespecial (1, 1)
	26 org/apache/commons/math3/exception/MathUnsupportedOperationException.<init>:(Lorg/apache/commons/math3/exception/util/Localizable;[Ljava/lang/Object;)V (1, 1)
	28 athrow (1, 1)
	29 return (0, 1)

