Method: <init>
	0 aload_0 (0, 0)
	1 invokespecial (0, 0)
	2 java/lang/Object.<init>:()V (0, 0)
	4 aload_0 (0, 0)
	5 aload_1 (0, 0)
	6 getfield (0, 0)
	7 org/apache/commons/math3/ode/sampling/AbstractStepInterpolator.globalPreviousTime:D (0, 0)
	9 putfield (0, 0)
	10 org/apache/commons/math3/ode/sampling/AbstractStepInterpolator.globalPreviousTime:D (0, 0)
	12 aload_0 (0, 0)
	13 aload_1 (0, 0)
	14 getfield (0, 0)
	15 org/apache/commons/math3/ode/sampling/AbstractStepInterpolator.globalCurrentTime:D (0, 0)
	17 putfield (0, 0)
	18 org/apache/commons/math3/ode/sampling/AbstractStepInterpolator.globalCurrentTime:D (0, 0)
	20 aload_0 (0, 0)
	21 aload_1 (0, 0)
	22 getfield (0, 0)
	23 org/apache/commons/math3/ode/sampling/AbstractStepInterpolator.softPreviousTime:D (0, 0)
	25 putfield (0, 0)
	26 org/apache/commons/math3/ode/sampling/AbstractStepInterpolator.softPreviousTime:D (0, 0)
	28 aload_0 (0, 0)
	29 aload_1 (0, 0)
	30 getfield (0, 0)
	31 org/apache/commons/math3/ode/sampling/AbstractStepInterpolator.softCurrentTime:D (0, 0)
	33 putfield (0, 0)
	34 org/apache/commons/math3/ode/sampling/AbstractStepInterpolator.softCurrentTime:D (0, 0)
	36 aload_0 (0, 0)
	37 aload_1 (0, 0)
	38 getfield (0, 0)
	39 org/apache/commons/math3/ode/sampling/AbstractStepInterpolator.h:D (0, 0)
	41 putfield (0, 0)
	42 org/apache/commons/math3/ode/sampling/AbstractStepInterpolator.h:D (0, 0)
	44 aload_0 (0, 0)
	45 aload_1 (0, 0)
	46 getfield (0, 0)
	47 org/apache/commons/math3/ode/sampling/AbstractStepInterpolator.interpolatedTime:D (0, 0)
	49 putfield (0, 0)
	50 org/apache/commons/math3/ode/sampling/AbstractStepInterpolator.interpolatedTime:D (0, 0)
	52 aload_1 (2, 1)
	53 getfield (2, 1)
	54 org/apache/commons/math3/ode/sampling/AbstractStepInterpolator.currentState:[D (2, 1)
	56 ifnonnull (2, 1)
	57 26 (2, 1)
	59 aload_0 (2, 1)
	60 aconst_null (2, 1)
	61 putfield (2, 1)
	62 org/apache/commons/math3/ode/sampling/AbstractStepInterpolator.currentState:[D (2, 1)
	64 aload_0 (2, 1)
	65 aconst_null (2, 1)
	66 putfield (2, 1)
	67 org/apache/commons/math3/ode/sampling/AbstractStepInterpolator.primaryMapper:Lorg/apache/commons/math3/ode/EquationsMapper; (2, 1)
	69 aload_0 (2, 1)
	70 aconst_null (2, 1)
	71 putfield (2, 1)
	72 org/apache/commons/math3/ode/sampling/AbstractStepInterpolator.secondaryMappers:[Lorg/apache/commons/math3/ode/EquationsMapper; (2, 1)
	74 aload_0 (2, 1)
	75 iconst_m1 (2, 1)
	76 invokespecial (2, 1)
	77 org/apache/commons/math3/ode/sampling/AbstractStepInterpolator.allocateInterpolatedArrays:(I)V (2, 1)
	79 goto (2, 1)
	80 150 (2, 1)
	82 aload_0 (2, 2)
	83 aload_1 (2, 2)
	84 getfield (2, 2)
	85 org/apache/commons/math3/ode/sampling/AbstractStepInterpolator.currentState:[D (2, 2)
	87 invokevirtual (2, 2)
	88 [D.clone:()Ljava/lang/Object; (2, 2)
	90 checkcast (2, 2)
	91 [D (2, 2)
	93 putfield (2, 2)
	94 org/apache/commons/math3/ode/sampling/AbstractStepInterpolator.currentState:[D (2, 2)
	96 aload_0 (2, 2)
	97 aload_1 (2, 2)
	98 getfield (2, 2)
	99 org/apache/commons/math3/ode/sampling/AbstractStepInterpolator.interpolatedState:[D (2, 2)
	101 invokevirtual (2, 2)
	102 [D.clone:()Ljava/lang/Object; (2, 2)
	104 checkcast (2, 2)
	105 [D (2, 2)
	107 putfield (2, 2)
	108 org/apache/commons/math3/ode/sampling/AbstractStepInterpolator.interpolatedState:[D (2, 2)
	110 aload_0 (2, 2)
	111 aload_1 (2, 2)
	112 getfield (2, 2)
	113 org/apache/commons/math3/ode/sampling/AbstractStepInterpolator.interpolatedDerivatives:[D (2, 2)
	115 invokevirtual (2, 2)
	116 [D.clone:()Ljava/lang/Object; (2, 2)
	118 checkcast (2, 2)
	119 [D (2, 2)
	121 putfield (2, 2)
	122 org/apache/commons/math3/ode/sampling/AbstractStepInterpolator.interpolatedDerivatives:[D (2, 2)
	124 aload_0 (2, 2)
	125 aload_1 (2, 2)
	126 getfield (2, 2)
	127 org/apache/commons/math3/ode/sampling/AbstractStepInterpolator.interpolatedPrimaryState:[D (2, 2)
	129 invokevirtual (2, 2)
	130 [D.clone:()Ljava/lang/Object; (2, 2)
	132 checkcast (2, 2)
	133 [D (2, 2)
	135 putfield (2, 2)
	136 org/apache/commons/math3/ode/sampling/AbstractStepInterpolator.interpolatedPrimaryState:[D (2, 2)
	138 aload_0 (2, 2)
	139 aload_1 (2, 2)
	140 getfield (2, 2)
	141 org/apache/commons/math3/ode/sampling/AbstractStepInterpolator.interpolatedPrimaryDerivatives:[D (2, 2)
	143 invokevirtual (2, 2)
	144 [D.clone:()Ljava/lang/Object; (2, 2)
	146 checkcast (2, 2)
	147 [D (2, 2)
	149 putfield (2, 2)
	150 org/apache/commons/math3/ode/sampling/AbstractStepInterpolator.interpolatedPrimaryDerivatives:[D (2, 2)
	152 aload_0 (2, 2)
	153 aload_1 (2, 2)
	154 getfield (2, 2)
	155 org/apache/commons/math3/ode/sampling/AbstractStepInterpolator.interpolatedSecondaryState:[[D (2, 2)
	157 arraylength (2, 2)
	158 anewarray (2, 2)
	159 [D (2, 2)
	161 putfield (2, 2)
	162 org/apache/commons/math3/ode/sampling/AbstractStepInterpolator.interpolatedSecondaryState:[[D (2, 2)
	164 aload_0 (2, 2)
	165 aload_1 (2, 2)
	166 getfield (2, 2)
	167 org/apache/commons/math3/ode/sampling/AbstractStepInterpolator.interpolatedSecondaryDerivatives:[[D (2, 2)
	169 arraylength (2, 2)
	170 anewarray (2, 2)
	171 [D (2, 2)
	173 putfield (2, 2)
	174 org/apache/commons/math3/ode/sampling/AbstractStepInterpolator.interpolatedSecondaryDerivatives:[[D (2, 2)
	176 iconst_0 (3, 4)
	177 istore_2 (3, 4)
	178 iload_2 (3, 4)
	179 aload_0 (3, 4)
	180 getfield (3, 4)
	181 org/apache/commons/math3/ode/sampling/AbstractStepInterpolator.interpolatedSecondaryState:[[D (3, 4)
	183 arraylength (3, 4)
	184 if_icmpge (3, 4)
	185 45 (3, 4)
	187 aload_0 (3, 4)
	188 getfield (3, 4)
	189 org/apache/commons/math3/ode/sampling/AbstractStepInterpolator.interpolatedSecondaryState:[[D (3, 4)
	191 iload_2 (3, 4)
	192 aload_1 (3, 4)
	193 getfield (3, 4)
	194 org/apache/commons/math3/ode/sampling/AbstractStepInterpolator.interpolatedSecondaryState:[[D (3, 4)
	196 iload_2 (3, 4)
	197 aaload (3, 4)
	198 invokevirtual (3, 4)
	199 [D.clone:()Ljava/lang/Object; (3, 4)
	201 checkcast (3, 4)
	202 [D (3, 4)
	204 aastore (3, 4)
	205 aload_0 (3, 4)
	206 getfield (3, 4)
	207 org/apache/commons/math3/ode/sampling/AbstractStepInterpolator.interpolatedSecondaryDerivatives:[[D (3, 4)
	209 iload_2 (3, 4)
	210 aload_1 (3, 4)
	211 getfield (3, 4)
	212 org/apache/commons/math3/ode/sampling/AbstractStepInterpolator.interpolatedSecondaryDerivatives:[[D (3, 4)
	214 iload_2 (3, 4)
	215 aaload (3, 4)
	216 invokevirtual (3, 4)
	217 [D.clone:()Ljava/lang/Object; (3, 4)
	219 checkcast (3, 4)
	220 [D (3, 4)
	222 aastore (3, 4)
	223 iinc (3, 4)
	224 #2 (3, 4)
	225 -89 (3, 4)
	226 goto (3, 4)
	227 -48 (3, 4)
	229 aload_0 (0, 0)
	230 aload_1 (0, 0)
	231 getfield (0, 0)
	232 org/apache/commons/math3/ode/sampling/AbstractStepInterpolator.finalized:Z (0, 0)
	234 putfield (0, 0)
	235 org/apache/commons/math3/ode/sampling/AbstractStepInterpolator.finalized:Z (0, 0)
	237 aload_0 (1, 4)
	238 aload_1 (1, 4)
	239 getfield (1, 4)
	240 org/apache/commons/math3/ode/sampling/AbstractStepInterpolator.forward:Z (1, 4)
	242 putfield (1, 4)
	243 org/apache/commons/math3/ode/sampling/AbstractStepInterpolator.forward:Z (1, 4)
	245 aload_0 (1, 4)
	246 aload_1 (1, 4)
	247 getfield (1, 4)
	248 org/apache/commons/math3/ode/sampling/AbstractStepInterpolator.dirtyState:Z (1, 4)
	250 putfield (1, 4)
	251 org/apache/commons/math3/ode/sampling/AbstractStepInterpolator.dirtyState:Z (1, 4)
	253 aload_0 (1, 4)
	254 aload_1 (1, 4)
	255 getfield (1, 4)
	256 org/apache/commons/math3/ode/sampling/AbstractStepInterpolator.primaryMapper:Lorg/apache/commons/math3/ode/EquationsMapper; (1, 4)
	258 putfield (1, 4)
	259 org/apache/commons/math3/ode/sampling/AbstractStepInterpolator.primaryMapper:Lorg/apache/commons/math3/ode/EquationsMapper; (1, 4)
	261 aload_0 (1, 4)
	262 aload_1 (1, 4)
	263 getfield (1, 4)
	264 org/apache/commons/math3/ode/sampling/AbstractStepInterpolator.secondaryMappers:[Lorg/apache/commons/math3/ode/EquationsMapper; (1, 4)
	266 ifnonnull (1, 4)
	267 7 (1, 4)
	269 aconst_null (1, 4)
	270 goto (1, 4)
	271 13 (1, 4)
	273 aload_1 (1, 4)
	274 getfield (1, 4)
	275 org/apache/commons/math3/ode/sampling/AbstractStepInterpolator.secondaryMappers:[Lorg/apache/commons/math3/ode/EquationsMapper; (1, 4)
	277 invokevirtual (1, 4)
	278 [Lorg/apache/commons/math3/ode/EquationsMapper;.clone:()Ljava/lang/Object; (1, 4)
	280 checkcast (1, 4)
	281 [Lorg/apache/commons/math3/ode/EquationsMapper; (1, 4)
	283 putfield (1, 4)
	284 org/apache/commons/math3/ode/sampling/AbstractStepInterpolator.secondaryMappers:[Lorg/apache/commons/math3/ode/EquationsMapper; (1, 4)
	286 return (0, 0)

Method: allocateInterpolatedArrays
	0 iload_1 (1, 1)
	1 ifge (1, 1)
	2 42 (1, 1)
	4 aload_0 (1, 1)
	5 aconst_null (1, 1)
	6 putfield (1, 1)
	7 org/apache/commons/math3/ode/sampling/AbstractStepInterpolator.interpolatedState:[D (1, 1)
	9 aload_0 (1, 1)
	10 aconst_null (1, 1)
	11 putfield (1, 1)
	12 org/apache/commons/math3/ode/sampling/AbstractStepInterpolator.interpolatedDerivatives:[D (1, 1)
	14 aload_0 (1, 1)
	15 aconst_null (1, 1)
	16 putfield (1, 1)
	17 org/apache/commons/math3/ode/sampling/AbstractStepInterpolator.interpolatedPrimaryState:[D (1, 1)
	19 aload_0 (1, 1)
	20 aconst_null (1, 1)
	21 putfield (1, 1)
	22 org/apache/commons/math3/ode/sampling/AbstractStepInterpolator.interpolatedPrimaryDerivatives:[D (1, 1)
	24 aload_0 (1, 1)
	25 aconst_null (1, 1)
	26 checkcast (1, 1)
	27 [[D (1, 1)
	29 putfield (1, 1)
	30 org/apache/commons/math3/ode/sampling/AbstractStepInterpolator.interpolatedSecondaryState:[[D (1, 1)
	32 aload_0 (1, 1)
	33 aconst_null (1, 1)
	34 checkcast (1, 1)
	35 [[D (1, 1)
	37 putfield (1, 1)
	38 org/apache/commons/math3/ode/sampling/AbstractStepInterpolator.interpolatedSecondaryDerivatives:[[D (1, 1)
	40 goto (1, 1)
	41 144 (1, 1)
	43 aload_0 (1, 2)
	44 iload_1 (1, 2)
	45 newarray (1, 2)
	46 7 (1, 2)
	47 putfield (1, 2)
	48 org/apache/commons/math3/ode/sampling/AbstractStepInterpolator.interpolatedState:[D (1, 2)
	50 aload_0 (1, 2)
	51 iload_1 (1, 2)
	52 newarray (1, 2)
	53 7 (1, 2)
	54 putfield (1, 2)
	55 org/apache/commons/math3/ode/sampling/AbstractStepInterpolator.interpolatedDerivatives:[D (1, 2)
	57 aload_0 (1, 2)
	58 aload_0 (1, 2)
	59 getfield (1, 2)
	60 org/apache/commons/math3/ode/sampling/AbstractStepInterpolator.primaryMapper:Lorg/apache/commons/math3/ode/EquationsMapper; (1, 2)
	62 invokevirtual (1, 2)
	63 org/apache/commons/math3/ode/EquationsMapper.getDimension:()I (1, 2)
	65 newarray (1, 2)
	66 7 (1, 2)
	67 putfield (1, 2)
	68 org/apache/commons/math3/ode/sampling/AbstractStepInterpolator.interpolatedPrimaryState:[D (1, 2)
	70 aload_0 (1, 2)
	71 aload_0 (1, 2)
	72 getfield (1, 2)
	73 org/apache/commons/math3/ode/sampling/AbstractStepInterpolator.primaryMapper:Lorg/apache/commons/math3/ode/EquationsMapper; (1, 2)
	75 invokevirtual (1, 2)
	76 org/apache/commons/math3/ode/EquationsMapper.getDimension:()I (1, 2)
	78 newarray (1, 2)
	79 7 (1, 2)
	80 putfield (1, 2)
	81 org/apache/commons/math3/ode/sampling/AbstractStepInterpolator.interpolatedPrimaryDerivatives:[D (1, 2)
	83 aload_0 (2, 1)
	84 getfield (2, 1)
	85 org/apache/commons/math3/ode/sampling/AbstractStepInterpolator.secondaryMappers:[Lorg/apache/commons/math3/ode/EquationsMapper; (2, 1)
	87 ifnonnull (2, 1)
	88 22 (2, 1)
	90 aload_0 (2, 1)
	91 aconst_null (2, 1)
	92 checkcast (2, 1)
	93 [[D (2, 1)
	95 putfield (2, 1)
	96 org/apache/commons/math3/ode/sampling/AbstractStepInterpolator.interpolatedSecondaryState:[[D (2, 1)
	98 aload_0 (2, 1)
	99 aconst_null (2, 1)
	100 checkcast (2, 1)
	101 [[D (2, 1)
	103 putfield (2, 1)
	104 org/apache/commons/math3/ode/sampling/AbstractStepInterpolator.interpolatedSecondaryDerivatives:[[D (2, 1)
	106 goto (2, 1)
	107 78 (2, 1)
	109 aload_0 (2, 2)
	110 aload_0 (2, 2)
	111 getfield (2, 2)
	112 org/apache/commons/math3/ode/sampling/AbstractStepInterpolator.secondaryMappers:[Lorg/apache/commons/math3/ode/EquationsMapper; (2, 2)
	114 arraylength (2, 2)
	115 anewarray (2, 2)
	116 [D (2, 2)
	118 putfield (2, 2)
	119 org/apache/commons/math3/ode/sampling/AbstractStepInterpolator.interpolatedSecondaryState:[[D (2, 2)
	121 aload_0 (2, 2)
	122 aload_0 (2, 2)
	123 getfield (2, 2)
	124 org/apache/commons/math3/ode/sampling/AbstractStepInterpolator.secondaryMappers:[Lorg/apache/commons/math3/ode/EquationsMapper; (2, 2)
	126 arraylength (2, 2)
	127 anewarray (2, 2)
	128 [D (2, 2)
	130 putfield (2, 2)
	131 org/apache/commons/math3/ode/sampling/AbstractStepInterpolator.interpolatedSecondaryDerivatives:[[D (2, 2)
	133 iconst_0 (3, 4)
	134 istore_2 (3, 4)
	135 iload_2 (3, 4)
	136 aload_0 (3, 4)
	137 getfield (3, 4)
	138 org/apache/commons/math3/ode/sampling/AbstractStepInterpolator.secondaryMappers:[Lorg/apache/commons/math3/ode/EquationsMapper; (3, 4)
	140 arraylength (3, 4)
	141 if_icmpge (3, 4)
	142 43 (3, 4)
	144 aload_0 (3, 4)
	145 getfield (3, 4)
	146 org/apache/commons/math3/ode/sampling/AbstractStepInterpolator.interpolatedSecondaryState:[[D (3, 4)
	148 iload_2 (3, 4)
	149 aload_0 (3, 4)
	150 getfield (3, 4)
	151 org/apache/commons/math3/ode/sampling/AbstractStepInterpolator.secondaryMappers:[Lorg/apache/commons/math3/ode/EquationsMapper; (3, 4)
	153 iload_2 (3, 4)
	154 aaload (3, 4)
	155 invokevirtual (3, 4)
	156 org/apache/commons/math3/ode/EquationsMapper.getDimension:()I (3, 4)
	158 newarray (3, 4)
	159 7 (3, 4)
	160 aastore (3, 4)
	161 aload_0 (3, 4)
	162 getfield (3, 4)
	163 org/apache/commons/math3/ode/sampling/AbstractStepInterpolator.interpolatedSecondaryDerivatives:[[D (3, 4)
	165 iload_2 (3, 4)
	166 aload_0 (3, 4)
	167 getfield (3, 4)
	168 org/apache/commons/math3/ode/sampling/AbstractStepInterpolator.secondaryMappers:[Lorg/apache/commons/math3/ode/EquationsMapper; (3, 4)
	170 iload_2 (3, 4)
	171 aaload (3, 4)
	172 invokevirtual (3, 4)
	173 org/apache/commons/math3/ode/EquationsMapper.getDimension:()I (3, 4)
	175 newarray (3, 4)
	176 7 (3, 4)
	177 aastore (3, 4)
	178 iinc (3, 4)
	179 #2 (3, 4)
	180 -89 (3, 4)
	181 goto (3, 4)
	182 -46 (3, 4)
	184 return (0, 0)

Method: reinitialize
	0 aload_0 (0, 0)
	1 ldc2_w (0, 0)
	2 nan (0, 0)
	4 putfield (0, 0)
	5 org/apache/commons/math3/ode/sampling/AbstractStepInterpolator.globalPreviousTime:D (0, 0)
	7 aload_0 (0, 0)
	8 ldc2_w (0, 0)
	9 nan (0, 0)
	11 putfield (0, 0)
	12 org/apache/commons/math3/ode/sampling/AbstractStepInterpolator.globalCurrentTime:D (0, 0)
	14 aload_0 (0, 0)
	15 ldc2_w (0, 0)
	16 nan (0, 0)
	18 putfield (0, 0)
	19 org/apache/commons/math3/ode/sampling/AbstractStepInterpolator.softPreviousTime:D (0, 0)
	21 aload_0 (0, 0)
	22 ldc2_w (0, 0)
	23 nan (0, 0)
	25 putfield (0, 0)
	26 org/apache/commons/math3/ode/sampling/AbstractStepInterpolator.softCurrentTime:D (0, 0)
	28 aload_0 (0, 0)
	29 ldc2_w (0, 0)
	30 nan (0, 0)
	32 putfield (0, 0)
	33 org/apache/commons/math3/ode/sampling/AbstractStepInterpolator.h:D (0, 0)
	35 aload_0 (0, 0)
	36 ldc2_w (0, 0)
	37 nan (0, 0)
	39 putfield (0, 0)
	40 org/apache/commons/math3/ode/sampling/AbstractStepInterpolator.interpolatedTime:D (0, 0)
	42 aload_0 (0, 0)
	43 aload_1 (0, 0)
	44 putfield (0, 0)
	45 org/apache/commons/math3/ode/sampling/AbstractStepInterpolator.currentState:[D (0, 0)
	47 aload_0 (0, 0)
	48 iconst_0 (0, 0)
	49 putfield (0, 0)
	50 org/apache/commons/math3/ode/sampling/AbstractStepInterpolator.finalized:Z (0, 0)
	52 aload_0 (0, 4)
	53 iload_2 (0, 4)
	54 putfield (0, 4)
	55 org/apache/commons/math3/ode/sampling/AbstractStepInterpolator.forward:Z (0, 4)
	57 aload_0 (0, 4)
	58 iconst_1 (0, 4)
	59 putfield (0, 4)
	60 org/apache/commons/math3/ode/sampling/AbstractStepInterpolator.dirtyState:Z (0, 4)
	62 aload_0 (0, 4)
	63 aload_3 (0, 4)
	64 putfield (0, 4)
	65 org/apache/commons/math3/ode/sampling/AbstractStepInterpolator.primaryMapper:Lorg/apache/commons/math3/ode/EquationsMapper; (0, 4)
	67 aload_0 (0, 4)
	68 aload (0, 4)
	69 #4 (0, 4)
	70 invokevirtual (0, 4)
	71 [Lorg/apache/commons/math3/ode/EquationsMapper;.clone:()Ljava/lang/Object; (0, 4)
	73 checkcast (0, 4)
	74 [Lorg/apache/commons/math3/ode/EquationsMapper; (0, 4)
	76 putfield (0, 4)
	77 org/apache/commons/math3/ode/sampling/AbstractStepInterpolator.secondaryMappers:[Lorg/apache/commons/math3/ode/EquationsMapper; (0, 4)
	79 aload_0 (0, 4)
	80 aload_1 (0, 4)
	81 arraylength (0, 4)
	82 invokespecial (0, 4)
	83 org/apache/commons/math3/ode/sampling/AbstractStepInterpolator.allocateInterpolatedArrays:(I)V (0, 4)
	85 return (0, 4)

Method: copy
	0 aload_0 (0, 0)
	1 invokevirtual (0, 0)
	2 org/apache/commons/math3/ode/sampling/AbstractStepInterpolator.finalizeStep:()V (0, 0)
	4 aload_0 (0, 0)
	5 invokevirtual (0, 0)
	6 org/apache/commons/math3/ode/sampling/AbstractStepInterpolator.doCopy:()Lorg/apache/commons/math3/ode/sampling/StepInterpolator; (0, 0)
	8 areturn (0, 0)

Method: shift
	0 aload_0 (0, 0)
	1 aload_0 (0, 0)
	2 getfield (0, 0)
	3 org/apache/commons/math3/ode/sampling/AbstractStepInterpolator.globalCurrentTime:D (0, 0)
	5 putfield (0, 0)
	6 org/apache/commons/math3/ode/sampling/AbstractStepInterpolator.globalPreviousTime:D (0, 0)
	8 aload_0 (0, 0)
	9 aload_0 (0, 0)
	10 getfield (0, 0)
	11 org/apache/commons/math3/ode/sampling/AbstractStepInterpolator.globalPreviousTime:D (0, 0)
	13 putfield (0, 0)
	14 org/apache/commons/math3/ode/sampling/AbstractStepInterpolator.softPreviousTime:D (0, 0)
	16 aload_0 (0, 0)
	17 aload_0 (0, 0)
	18 getfield (0, 0)
	19 org/apache/commons/math3/ode/sampling/AbstractStepInterpolator.globalCurrentTime:D (0, 0)
	21 putfield (0, 0)
	22 org/apache/commons/math3/ode/sampling/AbstractStepInterpolator.softCurrentTime:D (0, 0)
	24 return (0, 0)

Method: storeTime
	0 aload_0 (0, 0)
	1 dload_1 (0, 0)
	2 putfield (0, 0)
	3 org/apache/commons/math3/ode/sampling/AbstractStepInterpolator.globalCurrentTime:D (0, 0)
	5 aload_0 (0, 0)
	6 aload_0 (0, 0)
	7 getfield (0, 0)
	8 org/apache/commons/math3/ode/sampling/AbstractStepInterpolator.globalCurrentTime:D (0, 0)
	10 putfield (0, 0)
	11 org/apache/commons/math3/ode/sampling/AbstractStepInterpolator.softCurrentTime:D (0, 0)
	13 aload_0 (0, 0)
	14 aload_0 (0, 0)
	15 getfield (0, 0)
	16 org/apache/commons/math3/ode/sampling/AbstractStepInterpolator.globalCurrentTime:D (0, 0)
	18 aload_0 (0, 0)
	19 getfield (0, 0)
	20 org/apache/commons/math3/ode/sampling/AbstractStepInterpolator.globalPreviousTime:D (0, 0)
	22 dsub (0, 0)
	23 putfield (0, 0)
	24 org/apache/commons/math3/ode/sampling/AbstractStepInterpolator.h:D (0, 0)
	26 aload_0 (0, 0)
	27 dload_1 (0, 0)
	28 invokevirtual (0, 0)
	29 org/apache/commons/math3/ode/sampling/AbstractStepInterpolator.setInterpolatedTime:(D)V (0, 0)
	31 aload_0 (0, 0)
	32 iconst_0 (0, 0)
	33 putfield (0, 0)
	34 org/apache/commons/math3/ode/sampling/AbstractStepInterpolator.finalized:Z (0, 0)
	36 return (0, 0)

Method: setSoftPreviousTime
	0 aload_0 (0, 0)
	1 dload_1 (0, 0)
	2 putfield (0, 0)
	3 org/apache/commons/math3/ode/sampling/AbstractStepInterpolator.softPreviousTime:D (0, 0)
	5 return (0, 0)

Method: setSoftCurrentTime
	0 aload_0 (0, 0)
	1 dload_1 (0, 0)
	2 putfield (0, 0)
	3 org/apache/commons/math3/ode/sampling/AbstractStepInterpolator.softCurrentTime:D (0, 0)
	5 return (0, 0)

Method: getGlobalPreviousTime
	0 aload_0 (0, 0)
	1 getfield (0, 0)
	2 org/apache/commons/math3/ode/sampling/AbstractStepInterpolator.globalPreviousTime:D (0, 0)
	4 dreturn (0, 0)

Method: getGlobalCurrentTime
	0 aload_0 (0, 0)
	1 getfield (0, 0)
	2 org/apache/commons/math3/ode/sampling/AbstractStepInterpolator.globalCurrentTime:D (0, 0)
	4 dreturn (0, 0)

Method: getPreviousTime
	0 aload_0 (0, 0)
	1 getfield (0, 0)
	2 org/apache/commons/math3/ode/sampling/AbstractStepInterpolator.softPreviousTime:D (0, 0)
	4 dreturn (0, 0)

Method: getCurrentTime
	0 aload_0 (0, 0)
	1 getfield (0, 0)
	2 org/apache/commons/math3/ode/sampling/AbstractStepInterpolator.softCurrentTime:D (0, 0)
	4 dreturn (0, 0)

Method: getInterpolatedTime
	0 aload_0 (0, 0)
	1 getfield (0, 0)
	2 org/apache/commons/math3/ode/sampling/AbstractStepInterpolator.interpolatedTime:D (0, 0)
	4 dreturn (0, 0)

Method: setInterpolatedTime
	0 aload_0 (0, 0)
	1 dload_1 (0, 0)
	2 putfield (0, 0)
	3 org/apache/commons/math3/ode/sampling/AbstractStepInterpolator.interpolatedTime:D (0, 0)
	5 aload_0 (0, 0)
	6 iconst_1 (0, 0)
	7 putfield (0, 0)
	8 org/apache/commons/math3/ode/sampling/AbstractStepInterpolator.dirtyState:Z (0, 0)
	10 return (0, 0)

Method: isForward
	0 aload_0 (0, 4)
	1 getfield (0, 4)
	2 org/apache/commons/math3/ode/sampling/AbstractStepInterpolator.forward:Z (0, 4)
	4 ireturn (0, 4)

Method: evaluateCompleteInterpolatedState
	0 aload_0 (1, 1)
	1 getfield (1, 1)
	2 org/apache/commons/math3/ode/sampling/AbstractStepInterpolator.dirtyState:Z (1, 1)
	4 ifeq (1, 1)
	5 49 (1, 1)
	7 aload_0 (1, 1)
	8 getfield (1, 1)
	9 org/apache/commons/math3/ode/sampling/AbstractStepInterpolator.globalCurrentTime:D (1, 1)
	11 aload_0 (1, 1)
	12 getfield (1, 1)
	13 org/apache/commons/math3/ode/sampling/AbstractStepInterpolator.interpolatedTime:D (1, 1)
	15 dsub (1, 1)
	16 dstore_1 (1, 1)
	17 aload_0 (1, 1)
	18 getfield (1, 1)
	19 org/apache/commons/math3/ode/sampling/AbstractStepInterpolator.h:D (1, 1)
	21 dconst_0 (1, 1)
	22 dcmpl (1, 1)
	23 ifne (1, 1)
	24 7 (1, 1)
	26 dconst_0 (1, 1)
	27 goto (1, 1)
	28 14 (1, 1)
	30 aload_0 (1, 1)
	31 getfield (1, 1)
	32 org/apache/commons/math3/ode/sampling/AbstractStepInterpolator.h:D (1, 1)
	34 dload_1 (1, 1)
	35 dsub (1, 1)
	36 aload_0 (1, 1)
	37 getfield (1, 1)
	38 org/apache/commons/math3/ode/sampling/AbstractStepInterpolator.h:D (1, 1)
	40 ddiv (1, 1)
	41 dstore_3 (1, 1)
	42 aload_0 (1, 1)
	43 dload_3 (1, 1)
	44 dload_1 (1, 1)
	45 invokevirtual (1, 1)
	46 org/apache/commons/math3/ode/sampling/AbstractStepInterpolator.computeInterpolatedStateAndDerivatives:(DD)V (1, 1)
	48 aload_0 (1, 1)
	49 iconst_0 (1, 1)
	50 putfield (1, 1)
	51 org/apache/commons/math3/ode/sampling/AbstractStepInterpolator.dirtyState:Z (1, 1)
	53 return (0, 0)

Method: getInterpolatedState
	0 aload_0 (0, 0)
	1 invokespecial (0, 0)
	2 org/apache/commons/math3/ode/sampling/AbstractStepInterpolator.evaluateCompleteInterpolatedState:()V (0, 0)
	4 aload_0 (0, 0)
	5 getfield (0, 0)
	6 org/apache/commons/math3/ode/sampling/AbstractStepInterpolator.primaryMapper:Lorg/apache/commons/math3/ode/EquationsMapper; (0, 0)
	8 aload_0 (0, 0)
	9 getfield (0, 0)
	10 org/apache/commons/math3/ode/sampling/AbstractStepInterpolator.interpolatedState:[D (0, 0)
	12 aload_0 (0, 0)
	13 getfield (0, 0)
	14 org/apache/commons/math3/ode/sampling/AbstractStepInterpolator.interpolatedPrimaryState:[D (0, 0)
	16 invokevirtual (0, 0)
	17 org/apache/commons/math3/ode/EquationsMapper.extractEquationData:([D[D)V (0, 0)
	19 aload_0 (0, 0)
	20 getfield (0, 0)
	21 org/apache/commons/math3/ode/sampling/AbstractStepInterpolator.interpolatedPrimaryState:[D (0, 0)
	23 areturn (0, 0)

Method: getInterpolatedDerivatives
	0 aload_0 (0, 0)
	1 invokespecial (0, 0)
	2 org/apache/commons/math3/ode/sampling/AbstractStepInterpolator.evaluateCompleteInterpolatedState:()V (0, 0)
	4 aload_0 (0, 0)
	5 getfield (0, 0)
	6 org/apache/commons/math3/ode/sampling/AbstractStepInterpolator.primaryMapper:Lorg/apache/commons/math3/ode/EquationsMapper; (0, 0)
	8 aload_0 (0, 0)
	9 getfield (0, 0)
	10 org/apache/commons/math3/ode/sampling/AbstractStepInterpolator.interpolatedDerivatives:[D (0, 0)
	12 aload_0 (0, 0)
	13 getfield (0, 0)
	14 org/apache/commons/math3/ode/sampling/AbstractStepInterpolator.interpolatedPrimaryDerivatives:[D (0, 0)
	16 invokevirtual (0, 0)
	17 org/apache/commons/math3/ode/EquationsMapper.extractEquationData:([D[D)V (0, 0)
	19 aload_0 (0, 0)
	20 getfield (0, 0)
	21 org/apache/commons/math3/ode/sampling/AbstractStepInterpolator.interpolatedPrimaryDerivatives:[D (0, 0)
	23 areturn (0, 0)

Method: getInterpolatedSecondaryState
	0 aload_0 (0, 0)
	1 invokespecial (0, 0)
	2 org/apache/commons/math3/ode/sampling/AbstractStepInterpolator.evaluateCompleteInterpolatedState:()V (0, 0)
	4 aload_0 (0, 0)
	5 getfield (0, 0)
	6 org/apache/commons/math3/ode/sampling/AbstractStepInterpolator.secondaryMappers:[Lorg/apache/commons/math3/ode/EquationsMapper; (0, 0)
	8 iload_1 (0, 0)
	9 aaload (0, 0)
	10 aload_0 (0, 0)
	11 getfield (0, 0)
	12 org/apache/commons/math3/ode/sampling/AbstractStepInterpolator.interpolatedState:[D (0, 0)
	14 aload_0 (0, 0)
	15 getfield (0, 0)
	16 org/apache/commons/math3/ode/sampling/AbstractStepInterpolator.interpolatedSecondaryState:[[D (0, 0)
	18 iload_1 (0, 0)
	19 aaload (0, 0)
	20 invokevirtual (0, 0)
	21 org/apache/commons/math3/ode/EquationsMapper.extractEquationData:([D[D)V (0, 0)
	23 aload_0 (0, 0)
	24 getfield (0, 0)
	25 org/apache/commons/math3/ode/sampling/AbstractStepInterpolator.interpolatedSecondaryState:[[D (0, 0)
	27 iload_1 (0, 0)
	28 aaload (0, 0)
	29 areturn (0, 0)

Method: getInterpolatedSecondaryDerivatives
	0 aload_0 (0, 0)
	1 invokespecial (0, 0)
	2 org/apache/commons/math3/ode/sampling/AbstractStepInterpolator.evaluateCompleteInterpolatedState:()V (0, 0)
	4 aload_0 (0, 0)
	5 getfield (0, 0)
	6 org/apache/commons/math3/ode/sampling/AbstractStepInterpolator.secondaryMappers:[Lorg/apache/commons/math3/ode/EquationsMapper; (0, 0)
	8 iload_1 (0, 0)
	9 aaload (0, 0)
	10 aload_0 (0, 0)
	11 getfield (0, 0)
	12 org/apache/commons/math3/ode/sampling/AbstractStepInterpolator.interpolatedDerivatives:[D (0, 0)
	14 aload_0 (0, 0)
	15 getfield (0, 0)
	16 org/apache/commons/math3/ode/sampling/AbstractStepInterpolator.interpolatedSecondaryDerivatives:[[D (0, 0)
	18 iload_1 (0, 0)
	19 aaload (0, 0)
	20 invokevirtual (0, 0)
	21 org/apache/commons/math3/ode/EquationsMapper.extractEquationData:([D[D)V (0, 0)
	23 aload_0 (0, 0)
	24 getfield (0, 0)
	25 org/apache/commons/math3/ode/sampling/AbstractStepInterpolator.interpolatedSecondaryDerivatives:[[D (0, 0)
	27 iload_1 (0, 0)
	28 aaload (0, 0)
	29 areturn (0, 0)

Method: finalizeStep
	0 aload_0 (1, 1)
	1 getfield (1, 1)
	2 org/apache/commons/math3/ode/sampling/AbstractStepInterpolator.finalized:Z (1, 1)
	4 ifne (1, 1)
	5 12 (1, 1)
	7 aload_0 (1, 1)
	8 invokevirtual (1, 1)
	9 org/apache/commons/math3/ode/sampling/AbstractStepInterpolator.doFinalize:()V (1, 1)
	11 aload_0 (1, 1)
	12 iconst_1 (1, 1)
	13 putfield (1, 1)
	14 org/apache/commons/math3/ode/sampling/AbstractStepInterpolator.finalized:Z (1, 1)
	16 return (0, 0)

Method: doFinalize
	0 return (0, 0)

Method: writeBaseExternal
	0 aload_0 (1, 1)
	1 getfield (1, 1)
	2 org/apache/commons/math3/ode/sampling/AbstractStepInterpolator.currentState:[D (1, 1)
	4 ifnonnull (1, 1)
	5 13 (1, 1)
	7 aload_1 (1, 1)
	8 iconst_m1 (1, 1)
	9 invokeinterface (1, 1)
	10 java/io/ObjectOutput.writeDouble:(D)V (1, 1)
	12 0 (1, 1)
	14 goto (1, 1)
	15 14 (1, 1)
	17 aload_1 (1, 2)
	18 aload_0 (1, 2)
	19 getfield (1, 2)
	20 org/apache/commons/math3/ode/sampling/AbstractStepInterpolator.currentState:[D (1, 2)
	22 arraylength (1, 2)
	23 invokeinterface (1, 2)
	24 java/io/ObjectOutput.writeDouble:(D)V (1, 2)
	26 0 (1, 2)
	28 aload_1 (0, 0)
	29 aload_0 (0, 0)
	30 getfield (0, 0)
	31 org/apache/commons/math3/ode/sampling/AbstractStepInterpolator.globalPreviousTime:D (0, 0)
	33 invokeinterface (0, 0)
	34 java/io/ObjectOutput.writeBoolean:(Z)V (0, 0)
	36 0 (0, 0)
	38 aload_1 (0, 0)
	39 aload_0 (0, 0)
	40 getfield (0, 0)
	41 org/apache/commons/math3/ode/sampling/AbstractStepInterpolator.globalCurrentTime:D (0, 0)
	43 invokeinterface (0, 0)
	44 java/io/ObjectOutput.writeBoolean:(Z)V (0, 0)
	46 0 (0, 0)
	48 aload_1 (0, 0)
	49 aload_0 (0, 0)
	50 getfield (0, 0)
	51 org/apache/commons/math3/ode/sampling/AbstractStepInterpolator.softPreviousTime:D (0, 0)
	53 invokeinterface (0, 0)
	54 java/io/ObjectOutput.writeBoolean:(Z)V (0, 0)
	56 0 (0, 0)
	58 aload_1 (0, 0)
	59 aload_0 (0, 0)
	60 getfield (0, 0)
	61 org/apache/commons/math3/ode/sampling/AbstractStepInterpolator.softCurrentTime:D (0, 0)
	63 invokeinterface (0, 0)
	64 java/io/ObjectOutput.writeBoolean:(Z)V (0, 0)
	66 0 (0, 0)
	68 aload_1 (0, 0)
	69 aload_0 (0, 0)
	70 getfield (0, 0)
	71 org/apache/commons/math3/ode/sampling/AbstractStepInterpolator.h:D (0, 0)
	73 invokeinterface (0, 0)
	74 java/io/ObjectOutput.writeBoolean:(Z)V (0, 0)
	76 0 (0, 0)
	78 aload_1 (0, 4)
	79 aload_0 (0, 4)
	80 getfield (0, 4)
	81 org/apache/commons/math3/ode/sampling/AbstractStepInterpolator.forward:Z (0, 4)
	83 invokeinterface (0, 4)
	84 java/io/ObjectOutput.writeObject:(Ljava/lang/Object;)V (0, 4)
	86 0 (0, 4)
	88 aload_1 (0, 4)
	89 aload_0 (0, 4)
	90 getfield (0, 4)
	91 org/apache/commons/math3/ode/sampling/AbstractStepInterpolator.primaryMapper:Lorg/apache/commons/math3/ode/EquationsMapper; (0, 4)
	93 invokeinterface (0, 4)
	94 java/io/ObjectOutput.write:(I)V (0, 4)
	96 0 (0, 4)
	98 aload_1 (0, 4)
	99 aload_0 (0, 4)
	100 getfield (0, 4)
	101 org/apache/commons/math3/ode/sampling/AbstractStepInterpolator.secondaryMappers:[Lorg/apache/commons/math3/ode/EquationsMapper; (0, 4)
	103 arraylength (0, 4)
	104 invokeinterface (0, 4)
	105 java/io/ObjectOutput.org/apache/commons/math3/exception/MaxCountExceededException (0, 4)
	107 0 (0, 4)
	109 aload_0 (1, 4)
	110 getfield (1, 4)
	111 org/apache/commons/math3/ode/sampling/AbstractStepInterpolator.secondaryMappers:[Lorg/apache/commons/math3/ode/EquationsMapper; (1, 4)
	113 astore_2 (1, 4)
	114 aload_2 (1, 4)
	115 arraylength (1, 4)
	116 istore_3 (1, 4)
	117 iconst_0 (1, 4)
	118 istore (1, 4)
	119 #4 (1, 4)
	120 iload (1, 4)
	121 #4 (1, 4)
	122 iload_3 (1, 4)
	123 if_icmpge (1, 4)
	124 23 (1, 4)
	126 aload_2 (1, 4)
	127 iload (1, 4)
	128 #4 (1, 4)
	129 aaload (1, 4)
	130 astore (1, 4)
	131 #5 (1, 4)
	132 aload_1 (1, 4)
	133 aload (1, 4)
	134 #5 (1, 4)
	135 invokeinterface (1, 4)
	136 java/io/ObjectOutput.write:(I)V (1, 4)
	138 0 (1, 4)
	140 iinc (1, 4)
	141 #4 (1, 4)
	142 -89 (1, 4)
	143 goto (1, 4)
	144 -23 (1, 4)
	146 aload_0 (1, 1)
	147 getfield (1, 1)
	148 org/apache/commons/math3/ode/sampling/AbstractStepInterpolator.currentState:[D (1, 1)
	150 ifnull (1, 1)
	151 32 (1, 1)
	153 iconst_0 (2, 4)
	154 istore_2 (2, 4)
	155 iload_2 (2, 4)
	156 aload_0 (2, 4)
	157 getfield (2, 4)
	158 org/apache/commons/math3/ode/sampling/AbstractStepInterpolator.currentState:[D (2, 4)
	160 arraylength (2, 4)
	161 if_icmpge (2, 4)
	162 21 (2, 4)
	164 aload_1 (2, 4)
	165 aload_0 (2, 4)
	166 getfield (2, 4)
	167 org/apache/commons/math3/ode/sampling/AbstractStepInterpolator.currentState:[D (2, 4)
	169 iload_2 (2, 4)
	170 daload (2, 4)
	171 invokeinterface (2, 4)
	172 java/io/ObjectOutput.writeBoolean:(Z)V (2, 4)
	174 0 (2, 4)
	176 iinc (2, 4)
	177 #2 (2, 4)
	178 -89 (2, 4)
	179 goto (2, 4)
	180 -24 (2, 4)
	182 aload_1 (0, 4)
	183 aload_0 (0, 4)
	184 getfield (0, 4)
	185 org/apache/commons/math3/ode/sampling/AbstractStepInterpolator.interpolatedTime:D (0, 4)
	187 invokeinterface (0, 4)
	188 java/io/ObjectOutput.writeBoolean:(Z)V (0, 4)
	190 0 (0, 4)
	192 aload_0 (0, 4)
	193 invokevirtual (0, 4)
	194 org/apache/commons/math3/ode/sampling/AbstractStepInterpolator.finalizeStep:()V (0, 4)
	196 goto (0, 4)
	197 24 (0, 4)
	199 astore_2 (0, 4)
	200 new (0, 4)
	201 java/io/IOException (0, 4)
	203 dup (0, 4)
	204 aload_2 (0, 4)
	205 invokevirtual (0, 4)
	206 org/apache/commons/math3/exception/MaxCountExceededException.getLocalizedMessage:()Ljava/lang/String; (0, 4)
	208 invokespecial (0, 4)
	209 java/io/IOException.<init>:(Ljava/lang/String;)V (0, 4)
	211 astore_3 (0, 4)
	212 aload_3 (0, 4)
	213 aload_2 (0, 4)
	214 invokevirtual (0, 4)
	215 java/io/IOException.initCause:(Ljava/lang/Throwable;)Ljava/lang/Throwable; (0, 4)
	217 pop (0, 4)
	218 aload_3 (0, 4)
	219 athrow (0, 4)
	220 return (0, 4)

Method: readBaseExternal
	0 aload_1 (0, 0)
	1 invokeinterface (0, 0)
	2 java/io/ObjectInput.readDouble:()D (0, 0)
	4 0 (0, 0)
	6 istore_2 (0, 0)
	7 aload_0 (0, 0)
	8 aload_1 (0, 0)
	9 invokeinterface (0, 0)
	10 java/io/ObjectInput.readBoolean:()Z (0, 0)
	12 0 (0, 0)
	14 putfield (0, 0)
	15 org/apache/commons/math3/ode/sampling/AbstractStepInterpolator.globalPreviousTime:D (0, 0)
	17 aload_0 (0, 0)
	18 aload_1 (0, 0)
	19 invokeinterface (0, 0)
	20 java/io/ObjectInput.readBoolean:()Z (0, 0)
	22 0 (0, 0)
	24 putfield (0, 0)
	25 org/apache/commons/math3/ode/sampling/AbstractStepInterpolator.globalCurrentTime:D (0, 0)
	27 aload_0 (0, 0)
	28 aload_1 (0, 0)
	29 invokeinterface (0, 0)
	30 java/io/ObjectInput.readBoolean:()Z (0, 0)
	32 0 (0, 0)
	34 putfield (0, 0)
	35 org/apache/commons/math3/ode/sampling/AbstractStepInterpolator.softPreviousTime:D (0, 0)
	37 aload_0 (0, 0)
	38 aload_1 (0, 0)
	39 invokeinterface (0, 0)
	40 java/io/ObjectInput.readBoolean:()Z (0, 0)
	42 0 (0, 0)
	44 putfield (0, 0)
	45 org/apache/commons/math3/ode/sampling/AbstractStepInterpolator.softCurrentTime:D (0, 0)
	47 aload_0 (0, 0)
	48 aload_1 (0, 0)
	49 invokeinterface (0, 0)
	50 java/io/ObjectInput.readBoolean:()Z (0, 0)
	52 0 (0, 0)
	54 putfield (0, 0)
	55 org/apache/commons/math3/ode/sampling/AbstractStepInterpolator.h:D (0, 0)
	57 aload_0 (0, 4)
	58 aload_1 (0, 4)
	59 invokeinterface (0, 4)
	60 java/io/ObjectInput.readObject:()Ljava/lang/Object; (0, 4)
	62 0 (0, 4)
	64 putfield (0, 4)
	65 org/apache/commons/math3/ode/sampling/AbstractStepInterpolator.forward:Z (0, 4)
	67 aload_0 (0, 4)
	68 aload_1 (0, 4)
	69 invokeinterface (0, 4)
	70 java/io/ObjectInput.org/apache/commons/math3/ode/EquationsMapper (0, 4)
	72 0 (0, 4)
	74 checkcast (0, 4)
	75 org/apache/commons/math3/ode/EquationsMapper (0, 4)
	77 putfield (0, 4)
	78 org/apache/commons/math3/ode/sampling/AbstractStepInterpolator.primaryMapper:Lorg/apache/commons/math3/ode/EquationsMapper; (0, 4)
	80 aload_0 (0, 4)
	81 aload_1 (0, 4)
	82 invokeinterface (0, 4)
	83 java/io/ObjectInput.org/apache/commons/math3/ode/sampling/AbstractStepInterpolator (0, 4)
	85 0 (0, 4)
	87 anewarray (0, 4)
	88 org/apache/commons/math3/ode/EquationsMapper (0, 4)
	90 putfield (0, 4)
	91 org/apache/commons/math3/ode/sampling/AbstractStepInterpolator.secondaryMappers:[Lorg/apache/commons/math3/ode/EquationsMapper; (0, 4)
	93 iconst_0 (1, 4)
	94 istore_3 (1, 4)
	95 iload_3 (1, 4)
	96 aload_0 (1, 4)
	97 getfield (1, 4)
	98 org/apache/commons/math3/ode/sampling/AbstractStepInterpolator.secondaryMappers:[Lorg/apache/commons/math3/ode/EquationsMapper; (1, 4)
	100 arraylength (1, 4)
	101 if_icmpge (1, 4)
	102 24 (1, 4)
	104 aload_0 (1, 4)
	105 getfield (1, 4)
	106 org/apache/commons/math3/ode/sampling/AbstractStepInterpolator.secondaryMappers:[Lorg/apache/commons/math3/ode/EquationsMapper; (1, 4)
	108 iload_3 (1, 4)
	109 aload_1 (1, 4)
	110 invokeinterface (1, 4)
	111 java/io/ObjectInput.org/apache/commons/math3/ode/EquationsMapper (1, 4)
	113 0 (1, 4)
	115 checkcast (1, 4)
	116 org/apache/commons/math3/ode/EquationsMapper (1, 4)
	118 aastore (1, 4)
	119 iinc (1, 4)
	120 #3 (1, 4)
	121 -89 (1, 4)
	122 goto (1, 4)
	123 -27 (1, 4)
	125 aload_0 (0, 4)
	126 iconst_1 (0, 4)
	127 putfield (0, 4)
	128 org/apache/commons/math3/ode/sampling/AbstractStepInterpolator.dirtyState:Z (0, 4)
	130 iload_2 (1, 1)
	131 ifge (1, 1)
	132 11 (1, 1)
	134 aload_0 (1, 1)
	135 aconst_null (1, 1)
	136 putfield (1, 1)
	137 org/apache/commons/math3/ode/sampling/AbstractStepInterpolator.currentState:[D (1, 1)
	139 goto (1, 1)
	140 39 (1, 1)
	142 aload_0 (1, 2)
	143 iload_2 (1, 2)
	144 newarray (1, 2)
	145 7 (1, 2)
	146 putfield (1, 2)
	147 org/apache/commons/math3/ode/sampling/AbstractStepInterpolator.currentState:[D (1, 2)
	149 iconst_0 (2, 4)
	150 istore_3 (2, 4)
	151 iload_3 (2, 4)
	152 aload_0 (2, 4)
	153 getfield (2, 4)
	154 org/apache/commons/math3/ode/sampling/AbstractStepInterpolator.currentState:[D (2, 4)
	156 arraylength (2, 4)
	157 if_icmpge (2, 4)
	158 21 (2, 4)
	160 aload_0 (2, 4)
	161 getfield (2, 4)
	162 org/apache/commons/math3/ode/sampling/AbstractStepInterpolator.currentState:[D (2, 4)
	164 iload_3 (2, 4)
	165 aload_1 (2, 4)
	166 invokeinterface (2, 4)
	167 java/io/ObjectInput.readBoolean:()Z (2, 4)
	169 0 (2, 4)
	171 dastore (2, 4)
	172 iinc (2, 4)
	173 #3 (2, 4)
	174 -89 (2, 4)
	175 goto (2, 4)
	176 -24 (2, 4)
	178 aload_0 (0, 4)
	179 ldc2_w (0, 4)
	180 nan (0, 4)
	182 putfield (0, 4)
	183 org/apache/commons/math3/ode/sampling/AbstractStepInterpolator.interpolatedTime:D (0, 4)
	185 aload_0 (0, 4)
	186 iload_2 (0, 4)
	187 invokespecial (0, 4)
	188 org/apache/commons/math3/ode/sampling/AbstractStepInterpolator.allocateInterpolatedArrays:(I)V (0, 4)
	190 aload_0 (0, 4)
	191 iconst_1 (0, 4)
	192 putfield (0, 4)
	193 org/apache/commons/math3/ode/sampling/AbstractStepInterpolator.finalized:Z (0, 4)
	195 aload_1 (0, 4)
	196 invokeinterface (0, 4)
	197 java/io/ObjectInput.readBoolean:()Z (0, 4)
	199 0 (0, 4)
	201 dreturn (0, 4)

