Method: <init>
	0 aload_0 (0, 0)
	1 invokespecial (0, 0)
	4 aload_0 (0, 0)
	5 aload_1 (0, 0)
	6 getfield (0, 0)
	9 putfield (0, 0)
	12 aload_0 (0, 0)
	13 aload_1 (0, 0)
	14 getfield (0, 0)
	17 putfield (0, 0)
	20 aload_0 (0, 0)
	21 aload_1 (0, 0)
	22 getfield (0, 0)
	25 putfield (0, 0)
	28 aload_0 (0, 0)
	29 aload_1 (0, 0)
	30 getfield (0, 0)
	33 putfield (0, 0)
	36 aload_0 (0, 0)
	37 aload_1 (0, 0)
	38 getfield (0, 0)
	41 putfield (0, 0)
	44 aload_0 (0, 0)
	45 aload_1 (0, 0)
	46 getfield (0, 0)
	49 putfield (0, 0)
	52 aload_1 (1, 1)
	53 getfield (1, 1)
	56 ifnonnull (1, 1)
	59 aload_0 (1, 1)
	60 aconst_null (1, 1)
	61 putfield (1, 1)
	64 aload_0 (1, 1)
	65 aconst_null (1, 1)
	66 putfield (1, 1)
	69 aload_0 (1, 1)
	70 aconst_null (1, 1)
	71 putfield (1, 1)
	74 aload_0 (1, 1)
	75 iconst_m1 (1, 1)
	76 invokespecial (1, 1)
	79 goto (1, 1)
	82 aload_0 (1, 2)
	83 aload_1 (1, 2)
	84 getfield (1, 2)
	87 invokevirtual (1, 2)
	90 checkcast (1, 2)
	93 putfield (1, 2)
	96 aload_0 (1, 2)
	97 aload_1 (1, 2)
	98 getfield (1, 2)
	101 invokevirtual (1, 2)
	104 checkcast (1, 2)
	107 putfield (1, 2)
	110 aload_0 (1, 2)
	111 aload_1 (1, 2)
	112 getfield (1, 2)
	115 invokevirtual (1, 2)
	118 checkcast (1, 2)
	121 putfield (1, 2)
	124 aload_0 (1, 2)
	125 aload_1 (1, 2)
	126 getfield (1, 2)
	129 invokevirtual (1, 2)
	132 checkcast (1, 2)
	135 putfield (1, 2)
	138 aload_0 (1, 2)
	139 aload_1 (1, 2)
	140 getfield (1, 2)
	143 invokevirtual (1, 2)
	146 checkcast (1, 2)
	149 putfield (1, 2)
	152 aload_0 (1, 2)
	153 aload_1 (1, 2)
	154 getfield (1, 2)
	157 arraylength (1, 2)
	158 anewarray (1, 2)
	161 putfield (1, 2)
	164 aload_0 (1, 2)
	165 aload_1 (1, 2)
	166 getfield (1, 2)
	169 arraylength (1, 2)
	170 anewarray (1, 2)
	173 putfield (1, 2)
	176 iconst_0 (2, 4)
	177 istore_2 (2, 4)
	178 iload_2 (2, 4)
	179 aload_0 (2, 4)
	180 getfield (2, 4)
	183 arraylength (2, 4)
	184 if_icmpge (2, 4)
	187 aload_0 (2, 4)
	188 getfield (2, 4)
	191 iload_2 (2, 4)
	192 aload_1 (2, 4)
	193 getfield (2, 4)
	196 iload_2 (2, 4)
	197 aaload (2, 4)
	198 invokevirtual (2, 4)
	201 checkcast (2, 4)
	204 aastore (2, 4)
	205 aload_0 (2, 4)
	206 getfield (2, 4)
	209 iload_2 (2, 4)
	210 aload_1 (2, 4)
	211 getfield (2, 4)
	214 iload_2 (2, 4)
	215 aaload (2, 4)
	216 invokevirtual (2, 4)
	219 checkcast (2, 4)
	222 aastore (2, 4)
	223 iinc (2, 4)
	226 goto (2, 4)
	229 aload_0 (0, 1)
	230 aload_1 (0, 1)
	231 getfield (0, 1)
	234 putfield (0, 1)
	237 aload_0 (0, 4)
	238 aload_1 (0, 4)
	239 getfield (0, 4)
	242 putfield (0, 4)
	245 aload_0 (0, 4)
	246 aload_1 (0, 4)
	247 getfield (0, 4)
	250 putfield (0, 4)
	253 aload_0 (0, 4)
	254 aload_1 (0, 4)
	255 getfield (0, 4)
	258 putfield (0, 4)
	261 aload_0 (0, 4)
	262 aload_1 (0, 4)
	263 getfield (0, 4)
	266 ifnonnull (0, 4)
	269 aconst_null (0, 4)
	270 goto (0, 4)
	273 aload_1 (0, 4)
	274 getfield (0, 4)
	277 invokevirtual (0, 4)
	280 checkcast (0, 4)
	283 putfield (0, 4)
	286 return (0, 1)

Method: allocateInterpolatedArrays
	0 iload_1 (1, 1)
	1 ifge (1, 1)
	4 aload_0 (1, 1)
	5 aconst_null (1, 1)
	6 putfield (1, 1)
	9 aload_0 (1, 1)
	10 aconst_null (1, 1)
	11 putfield (1, 1)
	14 aload_0 (1, 1)
	15 aconst_null (1, 1)
	16 putfield (1, 1)
	19 aload_0 (1, 1)
	20 aconst_null (1, 1)
	21 putfield (1, 1)
	24 aload_0 (1, 1)
	25 aconst_null (1, 1)
	26 checkcast (1, 1)
	29 putfield (1, 1)
	32 aload_0 (1, 1)
	33 aconst_null (1, 1)
	34 checkcast (1, 1)
	37 putfield (1, 1)
	40 goto (1, 1)
	43 aload_0 (1, 2)
	44 iload_1 (1, 2)
	45 newarray (1, 2)
	47 putfield (1, 2)
	50 aload_0 (1, 2)
	51 iload_1 (1, 2)
	52 newarray (1, 2)
	54 putfield (1, 2)
	57 aload_0 (1, 2)
	58 aload_0 (1, 2)
	59 getfield (1, 2)
	62 invokevirtual (1, 2)
	65 newarray (1, 2)
	67 putfield (1, 2)
	70 aload_0 (1, 2)
	71 aload_0 (1, 2)
	72 getfield (1, 2)
	75 invokevirtual (1, 2)
	78 newarray (1, 2)
	80 putfield (1, 2)
	83 aload_0 (2, 1)
	84 getfield (2, 1)
	87 ifnonnull (2, 1)
	90 aload_0 (2, 1)
	91 aconst_null (2, 1)
	92 checkcast (2, 1)
	95 putfield (2, 1)
	98 aload_0 (2, 1)
	99 aconst_null (2, 1)
	100 checkcast (2, 1)
	103 putfield (2, 1)
	106 goto (2, 1)
	109 aload_0 (2, 2)
	110 aload_0 (2, 2)
	111 getfield (2, 2)
	114 arraylength (2, 2)
	115 anewarray (2, 2)
	118 putfield (2, 2)
	121 aload_0 (2, 2)
	122 aload_0 (2, 2)
	123 getfield (2, 2)
	126 arraylength (2, 2)
	127 anewarray (2, 2)
	130 putfield (2, 2)
	133 iconst_0 (3, 4)
	134 istore_2 (3, 4)
	135 iload_2 (3, 4)
	136 aload_0 (3, 4)
	137 getfield (3, 4)
	140 arraylength (3, 4)
	141 if_icmpge (3, 4)
	144 aload_0 (3, 4)
	145 getfield (3, 4)
	148 iload_2 (3, 4)
	149 aload_0 (3, 4)
	150 getfield (3, 4)
	153 iload_2 (3, 4)
	154 aaload (3, 4)
	155 invokevirtual (3, 4)
	158 newarray (3, 4)
	160 aastore (3, 4)
	161 aload_0 (3, 4)
	162 getfield (3, 4)
	165 iload_2 (3, 4)
	166 aload_0 (3, 4)
	167 getfield (3, 4)
	170 iload_2 (3, 4)
	171 aaload (3, 4)
	172 invokevirtual (3, 4)
	175 newarray (3, 4)
	177 aastore (3, 4)
	178 iinc (3, 4)
	181 goto (3, 4)
	184 return (0, 1)

Method: reinitialize
	0 aload_0 (0, 0)
	1 ldc2_w (0, 0)
	4 putfield (0, 0)
	7 aload_0 (0, 0)
	8 ldc2_w (0, 0)
	11 putfield (0, 0)
	14 aload_0 (0, 0)
	15 ldc2_w (0, 0)
	18 putfield (0, 0)
	21 aload_0 (0, 0)
	22 ldc2_w (0, 0)
	25 putfield (0, 0)
	28 aload_0 (0, 0)
	29 ldc2_w (0, 0)
	32 putfield (0, 0)
	35 aload_0 (0, 0)
	36 ldc2_w (0, 0)
	39 putfield (0, 0)
	42 aload_0 (0, 0)
	43 aload_1 (0, 0)
	44 putfield (0, 0)
	47 aload_0 (0, 0)
	48 iconst_0 (0, 0)
	49 putfield (0, 0)
	52 aload_0 (0, 4)
	53 iload_2 (0, 4)
	54 putfield (0, 4)
	57 aload_0 (0, 4)
	58 iconst_1 (0, 4)
	59 putfield (0, 4)
	62 aload_0 (0, 4)
	63 aload_3 (0, 4)
	64 putfield (0, 4)
	67 aload_0 (0, 4)
	68 aload (0, 4)
	70 invokevirtual (0, 4)
	73 checkcast (0, 4)
	76 putfield (0, 4)
	79 aload_0 (0, 4)
	80 aload_1 (0, 4)
	81 arraylength (0, 4)
	82 invokespecial (0, 4)
	85 return (0, 0)

Method: copy
	0 aload_0 (0, 0)
	1 invokevirtual (0, 0)
	4 aload_0 (0, 0)
	5 invokevirtual (0, 0)
	8 areturn (0, 0)

Method: shift
	0 aload_0 (0, 0)
	1 aload_0 (0, 0)
	2 getfield (0, 0)
	5 putfield (0, 0)
	8 aload_0 (0, 0)
	9 aload_0 (0, 0)
	10 getfield (0, 0)
	13 putfield (0, 0)
	16 aload_0 (0, 0)
	17 aload_0 (0, 0)
	18 getfield (0, 0)
	21 putfield (0, 0)
	24 return (0, 0)

Method: storeTime
	0 aload_0 (0, 0)
	1 dload_1 (0, 0)
	2 putfield (0, 0)
	5 aload_0 (0, 0)
	6 aload_0 (0, 0)
	7 getfield (0, 0)
	10 putfield (0, 0)
	13 aload_0 (0, 0)
	14 aload_0 (0, 0)
	15 getfield (0, 0)
	18 aload_0 (0, 0)
	19 getfield (0, 0)
	22 dsub (0, 0)
	23 putfield (0, 0)
	26 aload_0 (0, 0)
	27 dload_1 (0, 0)
	28 invokevirtual (0, 0)
	31 aload_0 (0, 0)
	32 iconst_0 (0, 0)
	33 putfield (0, 0)
	36 return (0, 0)

Method: setSoftPreviousTime
	0 aload_0 (0, 0)
	1 dload_1 (0, 0)
	2 putfield (0, 0)
	5 return (0, 0)

Method: setSoftCurrentTime
	0 aload_0 (0, 0)
	1 dload_1 (0, 0)
	2 putfield (0, 0)
	5 return (0, 0)

Method: getGlobalPreviousTime
	0 aload_0 (0, 0)
	1 getfield (0, 0)
	4 dreturn (0, 0)

Method: getGlobalCurrentTime
	0 aload_0 (0, 0)
	1 getfield (0, 0)
	4 dreturn (0, 0)

Method: getPreviousTime
	0 aload_0 (0, 0)
	1 getfield (0, 0)
	4 dreturn (0, 0)

Method: getCurrentTime
	0 aload_0 (0, 0)
	1 getfield (0, 0)
	4 dreturn (0, 0)

Method: getInterpolatedTime
	0 aload_0 (0, 0)
	1 getfield (0, 0)
	4 dreturn (0, 0)

Method: setInterpolatedTime
	0 aload_0 (0, 0)
	1 dload_1 (0, 0)
	2 putfield (0, 0)
	5 aload_0 (0, 0)
	6 iconst_1 (0, 0)
	7 putfield (0, 0)
	10 return (0, 0)

Method: isForward
	0 aload_0 (0, 4)
	1 getfield (0, 4)
	4 ireturn (0, 4)

Method: evaluateCompleteInterpolatedState
	0 aload_0 (1, 1)
	1 getfield (1, 1)
	4 ifeq (1, 1)
	7 aload_0 (1, 1)
	8 getfield (1, 1)
	11 aload_0 (1, 1)
	12 getfield (1, 1)
	15 dsub (1, 1)
	16 dstore_1 (1, 1)
	17 aload_0 (1, 1)
	18 getfield (1, 1)
	21 dconst_0 (1, 1)
	22 dcmpl (1, 1)
	23 ifne (1, 1)
	26 dconst_0 (1, 1)
	27 goto (1, 1)
	30 aload_0 (1, 1)
	31 getfield (1, 1)
	34 dload_1 (1, 1)
	35 dsub (1, 1)
	36 aload_0 (1, 1)
	37 getfield (1, 1)
	40 ddiv (1, 1)
	41 dstore_3 (1, 1)
	42 aload_0 (1, 1)
	43 dload_3 (1, 1)
	44 dload_1 (1, 1)
	45 invokevirtual (1, 1)
	48 aload_0 (1, 1)
	49 iconst_0 (1, 1)
	50 putfield (1, 1)
	53 return (0, 0)

Method: getInterpolatedState
	0 aload_0 (0, 0)
	1 invokespecial (0, 0)
	4 aload_0 (0, 0)
	5 getfield (0, 0)
	8 aload_0 (0, 0)
	9 getfield (0, 0)
	12 aload_0 (0, 0)
	13 getfield (0, 0)
	16 invokevirtual (0, 0)
	19 aload_0 (0, 0)
	20 getfield (0, 0)
	23 areturn (0, 0)

Method: getInterpolatedDerivatives
	0 aload_0 (0, 0)
	1 invokespecial (0, 0)
	4 aload_0 (0, 0)
	5 getfield (0, 0)
	8 aload_0 (0, 0)
	9 getfield (0, 0)
	12 aload_0 (0, 0)
	13 getfield (0, 0)
	16 invokevirtual (0, 0)
	19 aload_0 (0, 0)
	20 getfield (0, 0)
	23 areturn (0, 0)

Method: getInterpolatedSecondaryState
	0 aload_0 (0, 0)
	1 invokespecial (0, 0)
	4 aload_0 (0, 0)
	5 getfield (0, 0)
	8 iload_1 (0, 0)
	9 aaload (0, 0)
	10 aload_0 (0, 0)
	11 getfield (0, 0)
	14 aload_0 (0, 0)
	15 getfield (0, 0)
	18 iload_1 (0, 0)
	19 aaload (0, 0)
	20 invokevirtual (0, 0)
	23 aload_0 (0, 0)
	24 getfield (0, 0)
	27 iload_1 (0, 0)
	28 aaload (0, 0)
	29 areturn (0, 0)

Method: getInterpolatedSecondaryDerivatives
	0 aload_0 (0, 0)
	1 invokespecial (0, 0)
	4 aload_0 (0, 0)
	5 getfield (0, 0)
	8 iload_1 (0, 0)
	9 aaload (0, 0)
	10 aload_0 (0, 0)
	11 getfield (0, 0)
	14 aload_0 (0, 0)
	15 getfield (0, 0)
	18 iload_1 (0, 0)
	19 aaload (0, 0)
	20 invokevirtual (0, 0)
	23 aload_0 (0, 0)
	24 getfield (0, 0)
	27 iload_1 (0, 0)
	28 aaload (0, 0)
	29 areturn (0, 0)

Method: finalizeStep
	0 aload_0 (1, 1)
	1 getfield (1, 1)
	4 ifne (1, 1)
	7 aload_0 (1, 1)
	8 invokevirtual (1, 1)
	11 aload_0 (1, 1)
	12 iconst_1 (1, 1)
	13 putfield (1, 1)
	16 return (0, 0)

Method: doFinalize
	0 return (0, 0)

Method: writeBaseExternal
	0 aload_0 (1, 1)
	1 getfield (1, 1)
	4 ifnonnull (1, 1)
	7 aload_1 (1, 1)
	8 iconst_m1 (1, 1)
	9 invokeinterface (1, 1)
	14 goto (1, 1)
	17 aload_1 (1, 2)
	18 aload_0 (1, 2)
	19 getfield (1, 2)
	22 arraylength (1, 2)
	23 invokeinterface (1, 2)
	28 aload_1 (0, 1)
	29 aload_0 (0, 1)
	30 getfield (0, 1)
	33 invokeinterface (0, 1)
	38 aload_1 (0, 1)
	39 aload_0 (0, 1)
	40 getfield (0, 1)
	43 invokeinterface (0, 1)
	48 aload_1 (0, 1)
	49 aload_0 (0, 1)
	50 getfield (0, 1)
	53 invokeinterface (0, 1)
	58 aload_1 (0, 1)
	59 aload_0 (0, 1)
	60 getfield (0, 1)
	63 invokeinterface (0, 1)
	68 aload_1 (0, 1)
	69 aload_0 (0, 1)
	70 getfield (0, 1)
	73 invokeinterface (0, 1)
	78 aload_1 (0, 4)
	79 aload_0 (0, 4)
	80 getfield (0, 4)
	83 invokeinterface (0, 4)
	88 aload_1 (0, 4)
	89 aload_0 (0, 4)
	90 getfield (0, 4)
	93 invokeinterface (0, 4)
	98 aload_1 (0, 4)
	99 aload_0 (0, 4)
	100 getfield (0, 4)
	103 arraylength (0, 4)
	104 invokeinterface (0, 4)
	109 aload_0 (1, 4)
	110 getfield (1, 4)
	113 astore_2 (1, 4)
	114 aload_2 (1, 4)
	115 arraylength (1, 4)
	116 istore_3 (1, 4)
	117 iconst_0 (1, 4)
	118 istore (1, 4)
	120 iload (1, 4)
	122 iload_3 (1, 4)
	123 if_icmpge (1, 4)
	126 aload_2 (1, 4)
	127 iload (1, 4)
	129 aaload (1, 4)
	130 astore (1, 4)
	132 aload_1 (1, 4)
	133 aload (1, 4)
	135 invokeinterface (1, 4)
	140 iinc (1, 4)
	143 goto (1, 4)
	146 aload_0 (1, 1)
	147 getfield (1, 1)
	150 ifnull (1, 1)
	153 iconst_0 (2, 4)
	154 istore_2 (2, 4)
	155 iload_2 (2, 4)
	156 aload_0 (2, 4)
	157 getfield (2, 4)
	160 arraylength (2, 4)
	161 if_icmpge (2, 4)
	164 aload_1 (2, 4)
	165 aload_0 (2, 4)
	166 getfield (2, 4)
	169 iload_2 (2, 4)
	170 daload (2, 4)
	171 invokeinterface (2, 4)
	176 iinc (2, 4)
	179 goto (2, 4)
	182 aload_1 (0, 4)
	183 aload_0 (0, 4)
	184 getfield (0, 4)
	187 invokeinterface (0, 4)
	192 aload_0 (1, 4)
	193 invokevirtual (1, 4)
	196 goto (0, 1)
	199 astore_2 (0, 1)
	200 new (0, 1)
	203 dup (0, 1)
	204 aload_2 (0, 1)
	205 invokevirtual (0, 1)
	208 invokespecial (0, 1)
	211 astore_3 (0, 1)
	212 aload_3 (0, 1)
	213 aload_2 (0, 1)
	214 invokevirtual (0, 1)
	217 pop (0, 1)
	218 aload_3 (0, 1)
	219 athrow (0, 1)
	220 return (0, 0)

Method: readBaseExternal
	0 aload_1 (0, 0)
	1 invokeinterface (0, 0)
	6 istore_2 (0, 0)
	7 aload_0 (0, 0)
	8 aload_1 (0, 0)
	9 invokeinterface (0, 0)
	14 putfield (0, 0)
	17 aload_0 (0, 0)
	18 aload_1 (0, 0)
	19 invokeinterface (0, 0)
	24 putfield (0, 0)
	27 aload_0 (0, 0)
	28 aload_1 (0, 0)
	29 invokeinterface (0, 0)
	34 putfield (0, 0)
	37 aload_0 (0, 0)
	38 aload_1 (0, 0)
	39 invokeinterface (0, 0)
	44 putfield (0, 0)
	47 aload_0 (0, 0)
	48 aload_1 (0, 0)
	49 invokeinterface (0, 0)
	54 putfield (0, 0)
	57 aload_0 (0, 4)
	58 aload_1 (0, 4)
	59 invokeinterface (0, 4)
	64 putfield (0, 4)
	67 aload_0 (0, 4)
	68 aload_1 (0, 4)
	69 invokeinterface (0, 4)
	74 checkcast (0, 4)
	77 putfield (0, 4)
	80 aload_0 (0, 4)
	81 aload_1 (0, 4)
	82 invokeinterface (0, 4)
	87 anewarray (0, 4)
	90 putfield (0, 4)
	93 iconst_0 (1, 4)
	94 istore_3 (1, 4)
	95 iload_3 (1, 4)
	96 aload_0 (1, 4)
	97 getfield (1, 4)
	100 arraylength (1, 4)
	101 if_icmpge (1, 4)
	104 aload_0 (1, 4)
	105 getfield (1, 4)
	108 iload_3 (1, 4)
	109 aload_1 (1, 4)
	110 invokeinterface (1, 4)
	115 checkcast (1, 4)
	118 aastore (1, 4)
	119 iinc (1, 4)
	122 goto (1, 4)
	125 aload_0 (0, 4)
	126 iconst_1 (0, 4)
	127 putfield (0, 4)
	130 iload_2 (1, 1)
	131 ifge (1, 1)
	134 aload_0 (1, 1)
	135 aconst_null (1, 1)
	136 putfield (1, 1)
	139 goto (1, 1)
	142 aload_0 (1, 2)
	143 iload_2 (1, 2)
	144 newarray (1, 2)
	146 putfield (1, 2)
	149 iconst_0 (2, 4)
	150 istore_3 (2, 4)
	151 iload_3 (2, 4)
	152 aload_0 (2, 4)
	153 getfield (2, 4)
	156 arraylength (2, 4)
	157 if_icmpge (2, 4)
	160 aload_0 (2, 4)
	161 getfield (2, 4)
	164 iload_3 (2, 4)
	165 aload_1 (2, 4)
	166 invokeinterface (2, 4)
	171 dastore (2, 4)
	172 iinc (2, 4)
	175 goto (2, 4)
	178 aload_0 (0, 1)
	179 ldc2_w (0, 1)
	182 putfield (0, 1)
	185 aload_0 (0, 1)
	186 iload_2 (0, 1)
	187 invokespecial (0, 1)
	190 aload_0 (0, 1)
	191 iconst_1 (0, 1)
	192 putfield (0, 1)
	195 aload_1 (0, 1)
	196 invokeinterface (0, 1)
	201 dreturn (0, 1)

