Method: <init>
	0 aload_0 (0, 0)
	1 invokespecial (0, 0)
	4 aload_0 (0, 4)
	5 iload_1 (0, 4)
	6 putfield (0, 4)
	9 aload_0 (0, 4)
	10 aload_2 (0, 4)
	11 putfield (0, 4)
	14 aload_0 (0, 4)
	15 aload_3 (0, 4)
	16 putfield (0, 4)
	19 aload_0 (0, 4)
	20 aload (0, 4)
	22 putfield (0, 4)
	25 aload_0 (0, 4)
	26 aload (0, 4)
	28 putfield (0, 4)
	31 aload_0 (0, 4)
	32 aload (0, 4)
	34 putfield (0, 4)
	37 return (0, 0)

Method: restrictStep
	0 aload_0 (0, 4)
	1 aload_0 (0, 4)
	2 getfield (0, 4)
	5 aload_0 (0, 4)
	6 getfield (0, 4)
	9 aload_0 (0, 4)
	10 getfield (0, 4)
	13 aload_1 (0, 4)
	14 aload_2 (0, 4)
	15 aload_0 (0, 4)
	16 getfield (0, 4)
	19 invokevirtual (0, 4)
	22 areturn (0, 4)

Method: getGlobalPreviousState
	0 aload_0 (0, 0)
	1 getfield (0, 0)
	4 areturn (0, 0)

Method: getGlobalCurrentState
	0 aload_0 (0, 0)
	1 getfield (0, 0)
	4 areturn (0, 0)

Method: getPreviousState
	0 aload_0 (0, 0)
	1 getfield (0, 0)
	4 areturn (0, 0)

Method: getCurrentState
	0 aload_0 (0, 0)
	1 getfield (0, 0)
	4 areturn (0, 0)

Method: getInterpolatedState
	0 aload_1 (0, 0)
	1 aload_0 (0, 0)
	2 getfield (0, 0)
	5 invokevirtual (0, 0)
	8 invokeinterface (0, 0)
	13 checkcast (0, 0)
	16 astore_2 (0, 0)
	17 aload_0 (0, 0)
	18 getfield (0, 0)
	21 invokevirtual (0, 0)
	24 aload_1 (0, 0)
	25 invokeinterface (0, 0)
	30 checkcast (0, 0)
	33 astore_3 (0, 0)
	34 aload_2 (0, 0)
	35 aload_0 (0, 0)
	36 getfield (0, 0)
	39 invokevirtual (0, 0)
	42 aload_0 (0, 0)
	43 getfield (0, 0)
	46 invokevirtual (0, 0)
	49 invokeinterface (0, 0)
	54 invokeinterface (0, 0)
	59 checkcast (0, 0)
	62 astore (0, 0)
	64 aload_0 (0, 0)
	65 aload_0 (0, 0)
	66 getfield (0, 0)
	69 aload_1 (0, 0)
	70 aload (0, 0)
	72 aload_2 (0, 0)
	73 aload_3 (0, 0)
	74 invokevirtual (0, 0)
	77 areturn (0, 0)

Method: isForward
	0 aload_0 (0, 4)
	1 getfield (0, 4)
	4 ireturn (0, 4)

