Method: <init>
	0 aload_0 (0, 0)
	1 invokespecial (0, 0)
	2 java/lang/Object.<init>:()V (0, 0)
	4 aload_0 (0, 0)
	5 dload_1 (0, 0)
	6 invokestatic (0, 0)
	7 org/apache/commons/math3/util/FastMath.abs:(D)D (0, 0)
	9 putfield (0, 0)
	10 org/apache/commons/math3/ode/sampling/FieldStepNormalizer.h:D (0, 0)
	12 aload_0 (0, 0)
	13 aload_3 (0, 0)
	14 putfield (0, 0)
	15 org/apache/commons/math3/ode/sampling/FieldStepNormalizer.handler:Lorg/apache/commons/math3/ode/sampling/FieldFixedStepHandler; (0, 0)
	17 aload_0 (0, 0)
	18 aload (0, 0)
	19 #4 (0, 0)
	20 putfield (0, 0)
	21 org/apache/commons/math3/ode/sampling/FieldStepNormalizer.mode:Lorg/apache/commons/math3/ode/sampling/StepNormalizerMode; (0, 0)
	23 aload_0 (0, 0)
	24 aload (0, 0)
	25 #5 (0, 0)
	26 putfield (0, 0)
	27 org/apache/commons/math3/ode/sampling/FieldStepNormalizer.bounds:Lorg/apache/commons/math3/ode/sampling/StepNormalizerBounds; (0, 0)
	29 aload_0 (0, 0)
	30 aconst_null (0, 0)
	31 putfield (0, 0)
	32 org/apache/commons/math3/ode/sampling/FieldStepNormalizer.first:Lorg/apache/commons/math3/ode/FieldODEStateAndDerivative; (0, 0)
	34 aload_0 (0, 0)
	35 aconst_null (0, 0)
	36 putfield (0, 0)
	37 org/apache/commons/math3/ode/sampling/FieldStepNormalizer.last:Lorg/apache/commons/math3/ode/FieldODEStateAndDerivative; (0, 0)
	39 aload_0 (1, 4)
	40 iconst_1 (1, 4)
	41 putfield (1, 4)
	42 org/apache/commons/math3/ode/sampling/FieldStepNormalizer.forward:Z (1, 4)
	44 return (0, 0)

Method: init
	0 aload_0 (0, 0)
	1 aconst_null (0, 0)
	2 putfield (0, 0)
	3 org/apache/commons/math3/ode/sampling/FieldStepNormalizer.first:Lorg/apache/commons/math3/ode/FieldODEStateAndDerivative; (0, 0)
	5 aload_0 (0, 0)
	6 aconst_null (0, 0)
	7 putfield (0, 0)
	8 org/apache/commons/math3/ode/sampling/FieldStepNormalizer.last:Lorg/apache/commons/math3/ode/FieldODEStateAndDerivative; (0, 0)
	10 aload_0 (1, 4)
	11 iconst_1 (1, 4)
	12 putfield (1, 4)
	13 org/apache/commons/math3/ode/sampling/FieldStepNormalizer.forward:Z (1, 4)
	15 aload_0 (1, 4)
	16 getfield (1, 4)
	17 org/apache/commons/math3/ode/sampling/FieldStepNormalizer.handler:Lorg/apache/commons/math3/ode/sampling/FieldFixedStepHandler; (1, 4)
	19 aload_1 (1, 4)
	20 aload_2 (1, 4)
	21 invokeinterface (1, 4)
	22 org/apache/commons/math3/ode/sampling/FieldFixedStepHandler.org/apache/commons/math3/ode/sampling/FieldStepInterpolator (1, 4)
	24 0 (1, 4)
	26 return (0, 4)

Method: handleStep
	0 aload_0 (1, 1)
	1 getfield (1, 1)
	2 org/apache/commons/math3/ode/sampling/FieldStepNormalizer.last:Lorg/apache/commons/math3/ode/FieldODEStateAndDerivative; (1, 1)
	4 ifnonnull (1, 1)
	5 47 (1, 1)
	7 aload_0 (1, 1)
	8 aload_1 (1, 1)
	9 invokeinterface (1, 1)
	10 org/apache/commons/math3/ode/sampling/FieldStepInterpolator.isForward:()Z (1, 1)
	12 0 (1, 1)
	14 putfield (1, 1)
	15 org/apache/commons/math3/ode/sampling/FieldStepNormalizer.first:Lorg/apache/commons/math3/ode/FieldODEStateAndDerivative; (1, 1)
	17 aload_0 (1, 1)
	18 aload_0 (1, 1)
	19 getfield (1, 1)
	20 org/apache/commons/math3/ode/sampling/FieldStepNormalizer.first:Lorg/apache/commons/math3/ode/FieldODEStateAndDerivative; (1, 1)
	22 putfield (1, 1)
	23 org/apache/commons/math3/ode/sampling/FieldStepNormalizer.last:Lorg/apache/commons/math3/ode/FieldODEStateAndDerivative; (1, 1)
	25 aload_0 (2, 4)
	26 aload_1 (2, 4)
	27 invokeinterface (2, 4)
	28 org/apache/commons/math3/ode/sampling/FieldStepInterpolator.org/apache/commons/math3/ode/FieldODEStateAndDerivative (2, 4)
	30 0 (2, 4)
	32 putfield (2, 4)
	33 org/apache/commons/math3/ode/sampling/FieldStepNormalizer.forward:Z (2, 4)
	35 aload_0 (3, 1)
	36 getfield (3, 1)
	37 org/apache/commons/math3/ode/sampling/FieldStepNormalizer.forward:Z (3, 1)
	39 ifne (3, 1)
	40 12 (3, 1)
	42 aload_0 (3, 1)
	43 aload_0 (3, 1)
	44 getfield (3, 1)
	45 org/apache/commons/math3/ode/sampling/FieldStepNormalizer.h:D (3, 1)
	47 dneg (3, 1)
	48 putfield (3, 1)
	49 org/apache/commons/math3/ode/sampling/FieldStepNormalizer.h:D (3, 1)
	51 aload_0 (0, 0)
	52 getfield (0, 0)
	53 org/apache/commons/math3/ode/sampling/FieldStepNormalizer.mode:Lorg/apache/commons/math3/ode/sampling/StepNormalizerMode; (0, 0)
	55 getstatic (0, 0)
	56 org/apache/commons/math3/ode/sampling/StepNormalizerMode.INCREMENT:Lorg/apache/commons/math3/ode/sampling/StepNormalizerMode; (0, 0)
	58 if_acmpne (0, 0)
	59 25 (0, 0)
	61 aload_0 (0, 0)
	62 getfield (0, 0)
	63 org/apache/commons/math3/ode/sampling/FieldStepNormalizer.last:Lorg/apache/commons/math3/ode/FieldODEStateAndDerivative; (0, 0)
	65 invokevirtual (0, 0)
	66 org/apache/commons/math3/ode/FieldODEStateAndDerivative.getTime:()Lorg/apache/commons/math3/RealFieldElement; (0, 0)
	68 aload_0 (0, 0)
	69 getfield (0, 0)
	70 org/apache/commons/math3/ode/sampling/FieldStepNormalizer.h:D (0, 0)
	72 invokeinterface (0, 0)
	73 org/apache/commons/math3/RealFieldElement.org/apache/commons/math3/RealFieldElement (0, 0)
	75 0 (0, 0)
	77 checkcast (0, 0)
	78 org/apache/commons/math3/RealFieldElement (0, 0)
	80 goto (0, 0)
	81 58 (0, 0)
	83 aload_0 (0, 0)
	84 getfield (0, 0)
	85 org/apache/commons/math3/ode/sampling/FieldStepNormalizer.last:Lorg/apache/commons/math3/ode/FieldODEStateAndDerivative; (0, 0)
	87 invokevirtual (0, 0)
	88 org/apache/commons/math3/ode/FieldODEStateAndDerivative.getTime:()Lorg/apache/commons/math3/RealFieldElement; (0, 0)
	90 invokeinterface (0, 0)
	91 org/apache/commons/math3/RealFieldElement.org/apache/commons/math3/Field (0, 0)
	93 0 (0, 0)
	95 invokeinterface (0, 0)
	96 org/apache/commons/math3/Field.getReal:()D (0, 0)
	98 0 (0, 0)
	100 checkcast (0, 0)
	101 org/apache/commons/math3/RealFieldElement (0, 0)
	103 aload_0 (0, 0)
	104 getfield (0, 0)
	105 org/apache/commons/math3/ode/sampling/FieldStepNormalizer.last:Lorg/apache/commons/math3/ode/FieldODEStateAndDerivative; (0, 0)
	107 invokevirtual (0, 0)
	108 org/apache/commons/math3/ode/FieldODEStateAndDerivative.getTime:()Lorg/apache/commons/math3/RealFieldElement; (0, 0)
	110 invokeinterface (0, 0)
	111 org/apache/commons/math3/RealFieldElement.floor:(D)D (0, 0)
	113 0 (0, 0)
	115 aload_0 (0, 0)
	116 getfield (0, 0)
	117 org/apache/commons/math3/ode/sampling/FieldStepNormalizer.h:D (0, 0)
	119 ddiv (0, 0)
	120 invokestatic (0, 0)
	121 org/apache/commons/math3/util/FastMath.floor:(D)D (0, 0)
	123 dconst_1 (0, 0)
	124 dadd (0, 0)
	125 aload_0 (0, 0)
	126 getfield (0, 0)
	127 org/apache/commons/math3/ode/sampling/FieldStepNormalizer.h:D (0, 0)
	129 dmul (0, 0)
	130 invokeinterface (0, 0)
	131 org/apache/commons/math3/RealFieldElement.org/apache/commons/math3/RealFieldElement (0, 0)
	133 0 (0, 0)
	135 checkcast (0, 0)
	136 org/apache/commons/math3/RealFieldElement (0, 0)
	138 astore_3 (0, 0)
	139 aload_0 (1, 1)
	140 getfield (1, 1)
	141 org/apache/commons/math3/ode/sampling/FieldStepNormalizer.mode:Lorg/apache/commons/math3/ode/sampling/StepNormalizerMode; (1, 1)
	143 getstatic (1, 1)
	144 org/apache/commons/math3/ode/sampling/StepNormalizerMode.MULTIPLES:Lorg/apache/commons/math3/ode/sampling/StepNormalizerMode; (1, 1)
	146 if_acmpne (1, 1)
	147 42 (1, 1)
	149 aload_3 (1, 1)
	150 invokeinterface (1, 1)
	151 org/apache/commons/math3/RealFieldElement.floor:(D)D (1, 1)
	153 0 (1, 1)
	155 aload_0 (1, 1)
	156 getfield (1, 1)
	157 org/apache/commons/math3/ode/sampling/FieldStepNormalizer.last:Lorg/apache/commons/math3/ode/FieldODEStateAndDerivative; (1, 1)
	159 invokevirtual (1, 1)
	160 org/apache/commons/math3/ode/FieldODEStateAndDerivative.getTime:()Lorg/apache/commons/math3/RealFieldElement; (1, 1)
	162 invokeinterface (1, 1)
	163 org/apache/commons/math3/RealFieldElement.floor:(D)D (1, 1)
	165 0 (1, 1)
	167 iconst_1 (1, 1)
	168 invokestatic (1, 1)
	169 org/apache/commons/math3/util/Precision.equals:(DDI)Z (1, 1)
	171 ifeq (1, 1)
	172 17 (1, 1)
	174 aload_3 (1, 1)
	175 aload_0 (1, 1)
	176 getfield (1, 1)
	177 org/apache/commons/math3/ode/sampling/FieldStepNormalizer.h:D (1, 1)
	179 invokeinterface (1, 1)
	180 org/apache/commons/math3/RealFieldElement.org/apache/commons/math3/RealFieldElement (1, 1)
	182 0 (1, 1)
	184 checkcast (1, 1)
	185 org/apache/commons/math3/RealFieldElement (1, 1)
	187 astore_3 (1, 1)
	188 aload_0 (1, 1)
	189 aload_3 (1, 1)
	190 aload_1 (1, 1)
	191 invokespecial (1, 1)
	192 org/apache/commons/math3/ode/sampling/FieldStepNormalizer.isNextInStep:(Lorg/apache/commons/math3/RealFieldElement;Lorg/apache/commons/math3/ode/sampling/FieldStepInterpolator;)Z (1, 1)
	194 istore (1, 1)
	195 #4 (1, 1)
	196 iload (2, 3)
	197 #4 (2, 3)
	198 ifeq (2, 3)
	199 44 (2, 3)
	201 aload_0 (2, 3)
	202 iconst_0 (2, 3)
	203 invokespecial (2, 3)
	204 org/apache/commons/math3/ode/sampling/FieldStepNormalizer.doNormalizedStep:(Z)V (2, 3)
	206 aload_0 (2, 3)
	207 aload_1 (2, 3)
	208 aload_3 (2, 3)
	209 invokeinterface (2, 3)
	210 org/apache/commons/math3/ode/sampling/FieldStepInterpolator.lastIncluded:()Z (2, 3)
	212 0 (2, 3)
	214 putfield (2, 3)
	215 org/apache/commons/math3/ode/sampling/FieldStepNormalizer.last:Lorg/apache/commons/math3/ode/FieldODEStateAndDerivative; (2, 3)
	217 aload_3 (2, 3)
	218 aload_0 (2, 3)
	219 getfield (2, 3)
	220 org/apache/commons/math3/ode/sampling/FieldStepNormalizer.h:D (2, 3)
	222 invokeinterface (2, 3)
	223 org/apache/commons/math3/RealFieldElement.org/apache/commons/math3/RealFieldElement (2, 3)
	225 0 (2, 3)
	227 checkcast (2, 3)
	228 org/apache/commons/math3/RealFieldElement (2, 3)
	230 astore_3 (2, 3)
	231 aload_0 (2, 3)
	232 aload_3 (2, 3)
	233 aload_1 (2, 3)
	234 invokespecial (2, 3)
	235 org/apache/commons/math3/ode/sampling/FieldStepNormalizer.isNextInStep:(Lorg/apache/commons/math3/RealFieldElement;Lorg/apache/commons/math3/ode/sampling/FieldStepInterpolator;)Z (2, 3)
	237 istore (2, 3)
	238 #4 (2, 3)
	239 goto (2, 3)
	240 -43 (2, 3)
	242 iload_2 (2, 1)
	243 ifeq (2, 1)
	244 84 (2, 1)
	246 aload_0 (2, 1)
	247 getfield (2, 1)
	248 org/apache/commons/math3/ode/sampling/FieldStepNormalizer.bounds:Lorg/apache/commons/math3/ode/sampling/StepNormalizerBounds; (2, 1)
	250 invokevirtual (2, 1)
	251 org/apache/commons/math3/ode/sampling/StepNormalizerBounds.lastIncluded:()Z (2, 1)
	253 ifeq (2, 1)
	254 37 (2, 1)
	256 aload_0 (2, 1)
	257 getfield (2, 1)
	258 org/apache/commons/math3/ode/sampling/FieldStepNormalizer.last:Lorg/apache/commons/math3/ode/FieldODEStateAndDerivative; (2, 1)
	260 invokevirtual (2, 1)
	261 org/apache/commons/math3/ode/FieldODEStateAndDerivative.getTime:()Lorg/apache/commons/math3/RealFieldElement; (2, 1)
	263 invokeinterface (2, 1)
	264 org/apache/commons/math3/RealFieldElement.floor:(D)D (2, 1)
	266 0 (2, 1)
	268 aload_1 (2, 1)
	269 invokeinterface (2, 1)
	270 org/apache/commons/math3/ode/sampling/FieldStepInterpolator.firstIncluded:()Z (2, 1)
	272 0 (2, 1)
	274 invokevirtual (2, 1)
	275 org/apache/commons/math3/ode/FieldODEStateAndDerivative.getTime:()Lorg/apache/commons/math3/RealFieldElement; (2, 1)
	277 invokeinterface (2, 1)
	278 org/apache/commons/math3/RealFieldElement.floor:(D)D (2, 1)
	280 0 (2, 1)
	282 dcmpl (2, 1)
	283 ifeq (2, 1)
	284 7 (2, 1)
	286 iconst_1 (2, 1)
	287 goto (2, 1)
	288 4 (2, 1)
	290 iconst_0 (2, 1)
	291 istore (2, 1)
	292 #5 (2, 1)
	293 aload_0 (2, 1)
	294 iload (2, 1)
	295 #5 (2, 1)
	296 ifne (2, 1)
	297 7 (2, 1)
	299 iconst_1 (2, 1)
	300 goto (2, 1)
	301 4 (2, 1)
	303 iconst_0 (2, 1)
	304 invokespecial (2, 1)
	305 org/apache/commons/math3/ode/sampling/FieldStepNormalizer.doNormalizedStep:(Z)V (2, 1)
	307 iload (3, 1)
	308 #5 (3, 1)
	309 ifeq (3, 1)
	310 18 (3, 1)
	312 aload_0 (3, 1)
	313 aload_1 (3, 1)
	314 invokeinterface (3, 1)
	315 org/apache/commons/math3/ode/sampling/FieldStepInterpolator.firstIncluded:()Z (3, 1)
	317 0 (3, 1)
	319 putfield (3, 1)
	320 org/apache/commons/math3/ode/sampling/FieldStepNormalizer.last:Lorg/apache/commons/math3/ode/FieldODEStateAndDerivative; (3, 1)
	322 aload_0 (3, 1)
	323 iconst_1 (3, 1)
	324 invokespecial (3, 1)
	325 org/apache/commons/math3/ode/sampling/FieldStepNormalizer.doNormalizedStep:(Z)V (3, 1)
	327 return (0, 1)

Method: isNextInStep
	0 aload_0 (1, 4)
	1 getfield (1, 4)
	2 org/apache/commons/math3/ode/sampling/FieldStepNormalizer.forward:Z (1, 4)
	4 ifeq (1, 4)
	5 35 (1, 4)
	7 aload_1 (1, 4)
	8 invokeinterface (1, 4)
	9 org/apache/commons/math3/RealFieldElement.floor:(D)D (1, 4)
	11 0 (1, 4)
	13 aload_2 (1, 4)
	14 invokeinterface (1, 4)
	15 org/apache/commons/math3/ode/sampling/FieldStepInterpolator.firstIncluded:()Z (1, 4)
	17 0 (1, 4)
	19 invokevirtual (1, 4)
	20 org/apache/commons/math3/ode/FieldODEStateAndDerivative.getTime:()Lorg/apache/commons/math3/RealFieldElement; (1, 4)
	22 invokeinterface (1, 4)
	23 org/apache/commons/math3/RealFieldElement.floor:(D)D (1, 4)
	25 0 (1, 4)
	27 dcmpg (1, 4)
	28 ifgt (1, 4)
	29 7 (1, 4)
	31 iconst_1 (1, 4)
	32 goto (1, 4)
	33 36 (1, 4)
	35 iconst_0 (1, 4)
	36 goto (1, 4)
	37 32 (1, 4)
	39 aload_1 (1, 4)
	40 invokeinterface (1, 4)
	41 org/apache/commons/math3/RealFieldElement.floor:(D)D (1, 4)
	43 0 (1, 4)
	45 aload_2 (1, 4)
	46 invokeinterface (1, 4)
	47 org/apache/commons/math3/ode/sampling/FieldStepInterpolator.firstIncluded:()Z (1, 4)
	49 0 (1, 4)
	51 invokevirtual (1, 4)
	52 org/apache/commons/math3/ode/FieldODEStateAndDerivative.getTime:()Lorg/apache/commons/math3/RealFieldElement; (1, 4)
	54 invokeinterface (1, 4)
	55 org/apache/commons/math3/RealFieldElement.floor:(D)D (1, 4)
	57 0 (1, 4)
	59 dcmpl (1, 4)
	60 iflt (1, 4)
	61 7 (1, 4)
	63 iconst_1 (1, 4)
	64 goto (1, 4)
	65 4 (1, 4)
	67 iconst_0 (1, 4)
	68 ireturn (0, 4)

Method: doNormalizedStep
	0 aload_0 (1, 1)
	1 getfield (1, 1)
	2 org/apache/commons/math3/ode/sampling/FieldStepNormalizer.bounds:Lorg/apache/commons/math3/ode/sampling/StepNormalizerBounds; (1, 1)
	4 invokevirtual (1, 1)
	5 org/apache/commons/math3/ode/sampling/StepNormalizerBounds.firstIncluded:()Z (1, 1)
	7 ifne (1, 1)
	8 32 (1, 1)
	10 aload_0 (1, 1)
	11 getfield (1, 1)
	12 org/apache/commons/math3/ode/sampling/FieldStepNormalizer.first:Lorg/apache/commons/math3/ode/FieldODEStateAndDerivative; (1, 1)
	14 invokevirtual (1, 1)
	15 org/apache/commons/math3/ode/FieldODEStateAndDerivative.getTime:()Lorg/apache/commons/math3/RealFieldElement; (1, 1)
	17 invokeinterface (1, 1)
	18 org/apache/commons/math3/RealFieldElement.floor:(D)D (1, 1)
	20 0 (1, 1)
	22 aload_0 (1, 1)
	23 getfield (1, 1)
	24 org/apache/commons/math3/ode/sampling/FieldStepNormalizer.last:Lorg/apache/commons/math3/ode/FieldODEStateAndDerivative; (1, 1)
	26 invokevirtual (1, 1)
	27 org/apache/commons/math3/ode/FieldODEStateAndDerivative.getTime:()Lorg/apache/commons/math3/RealFieldElement; (1, 1)
	29 invokeinterface (1, 1)
	30 org/apache/commons/math3/RealFieldElement.floor:(D)D (1, 1)
	32 0 (1, 1)
	34 dcmpl (1, 1)
	35 ifne (1, 1)
	36 4 (1, 1)
	38 return (1, 1)
	39 aload_0 (0, 0)
	40 getfield (0, 0)
	41 org/apache/commons/math3/ode/sampling/FieldStepNormalizer.handler:Lorg/apache/commons/math3/ode/sampling/FieldFixedStepHandler; (0, 0)
	43 aload_0 (0, 0)
	44 getfield (0, 0)
	45 org/apache/commons/math3/ode/sampling/FieldStepNormalizer.last:Lorg/apache/commons/math3/ode/FieldODEStateAndDerivative; (0, 0)
	47 iload_1 (0, 0)
	48 invokeinterface (0, 0)
	49 org/apache/commons/math3/ode/sampling/FieldFixedStepHandler.org/apache/commons/math3/ode/sampling/FieldStepNormalizer (0, 0)
	51 0 (0, 0)
	53 return (0, 0)

