Method: <init>
	0 aload_0 (0, 0)
	1 invokespecial (0, 0)
	4 aload_0 (0, 0)
	5 dload_1 (0, 0)
	6 invokestatic (0, 0)
	9 putfield (0, 0)
	12 aload_0 (0, 0)
	13 aload_3 (0, 0)
	14 putfield (0, 0)
	17 aload_0 (0, 0)
	18 aload (0, 0)
	20 putfield (0, 0)
	23 aload_0 (0, 0)
	24 aload (0, 0)
	26 putfield (0, 0)
	29 aload_0 (0, 0)
	30 aconst_null (0, 0)
	31 putfield (0, 0)
	34 aload_0 (0, 0)
	35 aconst_null (0, 0)
	36 putfield (0, 0)
	39 aload_0 (0, 4)
	40 iconst_1 (0, 4)
	41 putfield (0, 4)
	44 return (0, 0)

Method: init
	0 aload_0 (0, 0)
	1 aconst_null (0, 0)
	2 putfield (0, 0)
	5 aload_0 (0, 0)
	6 aconst_null (0, 0)
	7 putfield (0, 0)
	10 aload_0 (0, 4)
	11 iconst_1 (0, 4)
	12 putfield (0, 4)
	15 aload_0 (0, 4)
	16 getfield (0, 4)
	19 aload_1 (0, 4)
	20 aload_2 (0, 4)
	21 invokeinterface (0, 4)
	26 return (0, 0)

Method: handleStep
	0 aload_0 (1, 1)
	1 getfield (1, 1)
	4 ifnonnull (1, 1)
	7 aload_0 (1, 1)
	8 aload_1 (1, 1)
	9 invokeinterface (1, 1)
	14 putfield (1, 1)
	17 aload_0 (1, 1)
	18 aload_0 (1, 1)
	19 getfield (1, 1)
	22 putfield (1, 1)
	25 aload_0 (1, 4)
	26 aload_1 (1, 4)
	27 invokeinterface (1, 4)
	32 putfield (1, 4)
	35 aload_0 (2, 1)
	36 getfield (2, 1)
	39 ifne (2, 1)
	42 aload_0 (2, 1)
	43 aload_0 (2, 1)
	44 getfield (2, 1)
	47 dneg (2, 1)
	48 putfield (2, 1)
	51 aload_0 (0, 1)
	52 getfield (0, 1)
	55 getstatic (0, 1)
	58 if_acmpne (0, 1)
	61 aload_0 (0, 1)
	62 getfield (0, 1)
	65 invokevirtual (0, 1)
	68 aload_0 (0, 1)
	69 getfield (0, 1)
	72 invokeinterface (0, 1)
	77 checkcast (0, 1)
	80 goto (0, 1)
	83 aload_0 (0, 1)
	84 getfield (0, 1)
	87 invokevirtual (0, 1)
	90 invokeinterface (0, 1)
	95 invokeinterface (0, 1)
	100 checkcast (0, 1)
	103 aload_0 (0, 1)
	104 getfield (0, 1)
	107 invokevirtual (0, 1)
	110 invokeinterface (0, 1)
	115 aload_0 (0, 1)
	116 getfield (0, 1)
	119 ddiv (0, 1)
	120 invokestatic (0, 1)
	123 dconst_1 (0, 1)
	124 dadd (0, 1)
	125 aload_0 (0, 1)
	126 getfield (0, 1)
	129 dmul (0, 1)
	130 invokeinterface (0, 1)
	135 checkcast (0, 1)
	138 astore_3 (0, 1)
	139 aload_0 (0, 1)
	140 getfield (0, 1)
	143 getstatic (0, 1)
	146 if_acmpne (0, 1)
	149 aload_3 (0, 1)
	150 invokeinterface (1, 1)
	155 aload_0 (1, 1)
	156 getfield (1, 1)
	159 invokevirtual (1, 1)
	162 invokeinterface (1, 1)
	167 iconst_1 (1, 1)
	168 invokestatic (1, 1)
	171 ifeq (1, 1)
	174 aload_3 (1, 1)
	175 aload_0 (1, 1)
	176 getfield (1, 1)
	179 invokeinterface (1, 1)
	184 checkcast (1, 1)
	187 astore_3 (1, 1)
	188 aload_0 (0, 1)
	189 aload_3 (0, 1)
	190 aload_1 (0, 1)
	191 invokespecial (0, 1)
	194 istore (0, 1)
	196 iload (1, 3)
	198 ifeq (1, 3)
	201 aload_0 (1, 3)
	202 iconst_0 (1, 3)
	203 invokespecial (1, 3)
	206 aload_0 (1, 3)
	207 aload_1 (1, 3)
	208 aload_3 (1, 3)
	209 invokeinterface (1, 3)
	214 putfield (1, 3)
	217 aload_3 (1, 3)
	218 aload_0 (1, 3)
	219 getfield (1, 3)
	222 invokeinterface (1, 3)
	227 checkcast (1, 3)
	230 astore_3 (1, 3)
	231 aload_0 (1, 3)
	232 aload_3 (1, 3)
	233 aload_1 (1, 3)
	234 invokespecial (1, 3)
	237 istore (1, 3)
	239 goto (1, 3)
	242 iload_2 (1, 1)
	243 ifeq (1, 1)
	246 aload_0 (1, 1)
	247 getfield (1, 1)
	250 invokevirtual (1, 1)
	253 ifeq (1, 1)
	256 aload_0 (1, 1)
	257 getfield (1, 1)
	260 invokevirtual (1, 1)
	263 invokeinterface (1, 1)
	268 aload_1 (1, 1)
	269 invokeinterface (1, 1)
	274 invokevirtual (1, 1)
	277 invokeinterface (1, 1)
	282 dcmpl (1, 1)
	283 ifeq (1, 1)
	286 iconst_1 (1, 1)
	287 goto (1, 1)
	290 iconst_0 (1, 1)
	291 istore (1, 1)
	293 aload_0 (1, 1)
	294 iload (1, 1)
	296 ifne (1, 1)
	299 iconst_1 (1, 1)
	300 goto (1, 1)
	303 iconst_0 (1, 1)
	304 invokespecial (1, 1)
	307 iload (2, 1)
	309 ifeq (2, 1)
	312 aload_0 (2, 1)
	313 aload_1 (2, 1)
	314 invokeinterface (2, 1)
	319 putfield (2, 1)
	322 aload_0 (2, 1)
	323 iconst_1 (2, 1)
	324 invokespecial (2, 1)
	327 return (0, 0)

Method: isNextInStep
	0 aload_0 (0, 4)
	1 getfield (0, 4)
	4 ifeq (0, 4)
	7 aload_1 (0, 4)
	8 invokeinterface (0, 4)
	13 aload_2 (0, 4)
	14 invokeinterface (0, 4)
	19 invokevirtual (0, 4)
	22 invokeinterface (0, 4)
	27 dcmpg (0, 4)
	28 ifgt (0, 4)
	31 iconst_1 (0, 4)
	32 goto (0, 4)
	35 iconst_0 (0, 4)
	36 goto (0, 4)
	39 aload_1 (0, 4)
	40 invokeinterface (0, 4)
	45 aload_2 (0, 4)
	46 invokeinterface (0, 4)
	51 invokevirtual (0, 4)
	54 invokeinterface (0, 4)
	59 dcmpl (0, 4)
	60 iflt (0, 4)
	63 iconst_1 (0, 4)
	64 goto (0, 4)
	67 iconst_0 (0, 4)
	68 ireturn (0, 4)

Method: doNormalizedStep
	0 aload_0 (1, 1)
	1 getfield (1, 1)
	4 invokevirtual (1, 1)
	7 ifne (1, 1)
	10 aload_0 (1, 1)
	11 getfield (1, 1)
	14 invokevirtual (1, 1)
	17 invokeinterface (1, 1)
	22 aload_0 (1, 1)
	23 getfield (1, 1)
	26 invokevirtual (1, 1)
	29 invokeinterface (1, 1)
	34 dcmpl (1, 1)
	35 ifne (1, 1)
	38 return (1, 1)
	39 aload_0 (0, 0)
	40 getfield (0, 0)
	43 aload_0 (0, 0)
	44 getfield (0, 0)
	47 iload_1 (0, 0)
	48 invokeinterface (0, 0)
	53 return (0, 0)

