Method: <init>
	0 aload_0 (0, 0)
	1 aload_1 (0, 0)
	2 invokespecial (0, 0)
	3 org/apache/commons/math3/ode/sampling/AbstractStepInterpolator.<init>:(Lorg/apache/commons/math3/ode/sampling/AbstractStepInterpolator;)V (0, 0)
	5 aload_0 (0, 0)
	6 aload_1 (0, 0)
	7 getfield (0, 0)
	8 org/apache/commons/math3/ode/sampling/NordsieckStepInterpolator.scalingH:D (0, 0)
	10 putfield (0, 0)
	11 org/apache/commons/math3/ode/sampling/NordsieckStepInterpolator.scalingH:D (0, 0)
	13 aload_0 (0, 0)
	14 aload_1 (0, 0)
	15 getfield (0, 0)
	16 org/apache/commons/math3/ode/sampling/NordsieckStepInterpolator.referenceTime:D (0, 0)
	18 putfield (0, 0)
	19 org/apache/commons/math3/ode/sampling/NordsieckStepInterpolator.referenceTime:D (0, 0)
	21 aload_1 (1, 1)
	22 getfield (1, 1)
	23 org/apache/commons/math3/ode/sampling/NordsieckStepInterpolator.scaled:[D (1, 1)
	25 ifnull (1, 1)
	26 17 (1, 1)
	28 aload_0 (1, 1)
	29 aload_1 (1, 1)
	30 getfield (1, 1)
	31 org/apache/commons/math3/ode/sampling/NordsieckStepInterpolator.scaled:[D (1, 1)
	33 invokevirtual (1, 1)
	34 [D.clone:()Ljava/lang/Object; (1, 1)
	36 checkcast (1, 1)
	37 [D (1, 1)
	39 putfield (1, 1)
	40 org/apache/commons/math3/ode/sampling/NordsieckStepInterpolator.scaled:[D (1, 1)
	42 aload_1 (1, 1)
	43 getfield (1, 1)
	44 org/apache/commons/math3/ode/sampling/NordsieckStepInterpolator.nordsieck:Lorg/apache/commons/math3/linear/Array2DRowRealMatrix; (1, 1)
	46 ifnull (1, 1)
	47 22 (1, 1)
	49 aload_0 (1, 1)
	50 new (1, 1)
	51 org/apache/commons/math3/linear/Array2DRowRealMatrix (1, 1)
	53 dup (1, 1)
	54 aload_1 (1, 1)
	55 getfield (1, 1)
	56 org/apache/commons/math3/ode/sampling/NordsieckStepInterpolator.nordsieck:Lorg/apache/commons/math3/linear/Array2DRowRealMatrix; (1, 1)
	58 invokevirtual (1, 1)
	59 org/apache/commons/math3/linear/Array2DRowRealMatrix.getDataRef:()[[D (1, 1)
	61 iconst_1 (1, 1)
	62 invokespecial (1, 1)
	63 org/apache/commons/math3/linear/Array2DRowRealMatrix.<init>:([[DZ)V (1, 1)
	65 putfield (1, 1)
	66 org/apache/commons/math3/ode/sampling/NordsieckStepInterpolator.nordsieck:Lorg/apache/commons/math3/linear/Array2DRowRealMatrix; (1, 1)
	68 aload_1 (1, 1)
	69 getfield (1, 1)
	70 org/apache/commons/math3/ode/sampling/NordsieckStepInterpolator.stateVariation:[D (1, 1)
	72 ifnull (1, 1)
	73 17 (1, 1)
	75 aload_0 (1, 1)
	76 aload_1 (1, 1)
	77 getfield (1, 1)
	78 org/apache/commons/math3/ode/sampling/NordsieckStepInterpolator.stateVariation:[D (1, 1)
	80 invokevirtual (1, 1)
	81 [D.clone:()Ljava/lang/Object; (1, 1)
	83 checkcast (1, 1)
	84 [D (1, 1)
	86 putfield (1, 1)
	87 org/apache/commons/math3/ode/sampling/NordsieckStepInterpolator.stateVariation:[D (1, 1)
	89 return (0, 0)

Method: doCopy
	0 new (0, 0)
	1 org/apache/commons/math3/ode/sampling/NordsieckStepInterpolator (0, 0)
	3 dup (0, 0)
	4 aload_0 (0, 0)
	5 invokespecial (0, 0)
	6 org/apache/commons/math3/ode/sampling/NordsieckStepInterpolator.<init>:(Lorg/apache/commons/math3/ode/sampling/NordsieckStepInterpolator;)V (0, 0)
	8 areturn (0, 0)

Method: reinitialize
	0 aload_0 (0, 0)
	1 dload_1 (0, 0)
	2 putfield (0, 0)
	3 org/apache/commons/math3/ode/sampling/NordsieckStepInterpolator.referenceTime:D (0, 0)
	5 aload_0 (0, 0)
	6 dload_3 (0, 0)
	7 putfield (0, 0)
	8 org/apache/commons/math3/ode/sampling/NordsieckStepInterpolator.scalingH:D (0, 0)
	10 aload_0 (0, 0)
	11 aload (0, 0)
	12 #5 (0, 0)
	13 putfield (0, 0)
	14 org/apache/commons/math3/ode/sampling/NordsieckStepInterpolator.scaled:[D (0, 0)
	16 aload_0 (0, 0)
	17 aload (0, 0)
	18 #6 (0, 0)
	19 putfield (0, 0)
	20 org/apache/commons/math3/ode/sampling/NordsieckStepInterpolator.nordsieck:Lorg/apache/commons/math3/linear/Array2DRowRealMatrix; (0, 0)
	22 aload_0 (0, 0)
	23 aload_0 (0, 0)
	24 invokevirtual (0, 0)
	25 org/apache/commons/math3/ode/sampling/NordsieckStepInterpolator.getInterpolatedTime:()D (0, 0)
	27 invokevirtual (0, 0)
	28 org/apache/commons/math3/ode/sampling/NordsieckStepInterpolator.setInterpolatedTime:(D)V (0, 0)
	30 return (0, 0)

Method: rescale
	0 dload_1 (0, 0)
	1 aload_0 (0, 0)
	2 getfield (0, 0)
	3 org/apache/commons/math3/ode/sampling/NordsieckStepInterpolator.scalingH:D (0, 0)
	5 ddiv (0, 0)
	6 dstore_3 (0, 0)
	7 iconst_0 (1, 4)
	8 istore (1, 4)
	9 #5 (1, 4)
	10 iload (1, 4)
	11 #5 (1, 4)
	12 aload_0 (1, 4)
	13 getfield (1, 4)
	14 org/apache/commons/math3/ode/sampling/NordsieckStepInterpolator.scaled:[D (1, 4)
	16 arraylength (1, 4)
	17 if_icmpge (1, 4)
	18 20 (1, 4)
	20 aload_0 (1, 4)
	21 getfield (1, 4)
	22 org/apache/commons/math3/ode/sampling/NordsieckStepInterpolator.scaled:[D (1, 4)
	24 iload (1, 4)
	25 #5 (1, 4)
	26 dup2 (1, 4)
	27 daload (1, 4)
	28 dload_3 (1, 4)
	29 dmul (1, 4)
	30 dastore (1, 4)
	31 iinc (1, 4)
	32 #5 (1, 4)
	33 -89 (1, 4)
	34 goto (1, 4)
	35 -24 (1, 4)
	37 aload_0 (0, 0)
	38 getfield (0, 0)
	39 org/apache/commons/math3/ode/sampling/NordsieckStepInterpolator.nordsieck:Lorg/apache/commons/math3/linear/Array2DRowRealMatrix; (0, 0)
	41 invokevirtual (0, 0)
	42 org/apache/commons/math3/linear/Array2DRowRealMatrix.getDataRef:()[[D (0, 0)
	44 astore (0, 0)
	45 #5 (0, 0)
	46 dload_3 (0, 0)
	47 dstore (0, 0)
	48 #6 (0, 0)
	49 iconst_0 (1, 4)
	50 istore (1, 4)
	51 #8 (1, 4)
	52 iload (1, 4)
	53 #8 (1, 4)
	54 aload (1, 4)
	55 #5 (1, 4)
	56 arraylength (1, 4)
	57 if_icmpge (1, 4)
	58 49 (1, 4)
	60 dload (1, 4)
	61 #6 (1, 4)
	62 dload_3 (1, 4)
	63 dmul (1, 4)
	64 dstore (1, 4)
	65 #6 (1, 4)
	66 aload (1, 4)
	67 #5 (1, 4)
	68 iload (1, 4)
	69 #8 (1, 4)
	70 aaload (1, 4)
	71 astore (1, 4)
	72 #9 (1, 4)
	73 iconst_0 (2, 4)
	74 istore (2, 4)
	75 #10 (2, 4)
	76 iload (2, 4)
	77 #10 (2, 4)
	78 aload (2, 4)
	79 #9 (2, 4)
	80 arraylength (2, 4)
	81 if_icmpge (2, 4)
	82 19 (2, 4)
	84 aload (2, 4)
	85 #9 (2, 4)
	86 iload (2, 4)
	87 #10 (2, 4)
	88 dup2 (2, 4)
	89 daload (2, 4)
	90 dload (2, 4)
	91 #6 (2, 4)
	92 dmul (2, 4)
	93 dastore (2, 4)
	94 iinc (2, 4)
	95 #10 (2, 4)
	96 -89 (2, 4)
	97 goto (2, 4)
	98 -21 (2, 4)
	100 iinc (2, 4)
	101 #8 (2, 4)
	102 -89 (2, 4)
	103 goto (2, 4)
	104 -51 (2, 4)
	106 aload_0 (1, 4)
	107 dload_1 (1, 4)
	108 putfield (1, 4)
	109 org/apache/commons/math3/ode/sampling/NordsieckStepInterpolator.scalingH:D (1, 4)
	111 return (0, 0)

Method: getInterpolatedStateVariation
	0 aload_0 (0, 0)
	1 invokevirtual (0, 0)
	2 org/apache/commons/math3/ode/sampling/NordsieckStepInterpolator.getInterpolatedState:()[D (0, 0)
	4 pop (0, 0)
	5 aload_0 (0, 0)
	6 getfield (0, 0)
	7 org/apache/commons/math3/ode/sampling/NordsieckStepInterpolator.stateVariation:[D (0, 0)
	9 areturn (0, 0)

Method: computeInterpolatedStateAndDerivatives
	0 aload_0 (0, 0)
	1 getfield (0, 0)
	2 org/apache/commons/math3/ode/sampling/NordsieckStepInterpolator.interpolatedTime:D (0, 0)
	4 aload_0 (0, 0)
	5 getfield (0, 0)
	6 org/apache/commons/math3/ode/sampling/NordsieckStepInterpolator.referenceTime:D (0, 0)
	8 dsub (0, 0)
	9 dstore (0, 0)
	10 #5 (0, 0)
	11 dload (0, 0)
	12 #5 (0, 0)
	13 aload_0 (0, 0)
	14 getfield (0, 0)
	15 org/apache/commons/math3/ode/sampling/NordsieckStepInterpolator.scalingH:D (0, 0)
	17 ddiv (0, 0)
	18 dstore (0, 0)
	19 #7 (0, 0)
	20 aload_0 (0, 0)
	21 getfield (0, 0)
	22 org/apache/commons/math3/ode/sampling/NordsieckStepInterpolator.stateVariation:[D (0, 0)
	24 dconst_0 (0, 0)
	25 invokestatic (0, 0)
	26 java/util/Arrays.fill:([DD)V (0, 0)
	28 aload_0 (0, 0)
	29 getfield (0, 0)
	30 org/apache/commons/math3/ode/sampling/NordsieckStepInterpolator.interpolatedDerivatives:[D (0, 0)
	32 dconst_0 (0, 0)
	33 invokestatic (0, 0)
	34 java/util/Arrays.fill:([DD)V (0, 0)
	36 aload_0 (2, 4)
	37 getfield (2, 4)
	38 org/apache/commons/math3/ode/sampling/NordsieckStepInterpolator.nordsieck:Lorg/apache/commons/math3/linear/Array2DRowRealMatrix; (2, 4)
	40 invokevirtual (2, 4)
	41 org/apache/commons/math3/linear/Array2DRowRealMatrix.getDataRef:()[[D (2, 4)
	43 astore (2, 4)
	44 #9 (2, 4)
	45 aload (3, 4)
	46 #9 (3, 4)
	47 arraylength (3, 4)
	48 iconst_1 (3, 4)
	49 isub (3, 4)
	50 istore (3, 4)
	51 #10 (3, 4)
	52 iload (3, 4)
	53 #10 (3, 4)
	54 iflt (3, 4)
	55 86 (3, 4)
	57 iload (3, 4)
	58 #10 (3, 4)
	59 iconst_2 (3, 4)
	60 iadd (3, 4)
	61 istore (3, 4)
	62 #11 (3, 4)
	63 aload (3, 4)
	64 #9 (3, 4)
	65 iload (3, 4)
	66 #10 (3, 4)
	67 aaload (3, 4)
	68 astore (3, 4)
	69 #12 (3, 4)
	70 dload (3, 4)
	71 #7 (3, 4)
	72 iload (3, 4)
	73 #11 (3, 4)
	74 invokestatic (3, 4)
	75 org/apache/commons/math3/util/FastMath.pow:(DI)D (3, 4)
	77 dstore (3, 4)
	78 #13 (3, 4)
	79 iconst_0 (4, 4)
	80 istore (4, 4)
	81 #15 (4, 4)
	82 iload (4, 4)
	83 #15 (4, 4)
	84 aload (4, 4)
	85 #12 (4, 4)
	86 arraylength (4, 4)
	87 if_icmpge (4, 4)
	88 47 (4, 4)
	90 aload (4, 4)
	91 #12 (4, 4)
	92 iload (4, 4)
	93 #15 (4, 4)
	94 daload (4, 4)
	95 dload (4, 4)
	96 #13 (4, 4)
	97 dmul (4, 4)
	98 dstore (4, 4)
	99 #16 (4, 4)
	100 aload_0 (4, 4)
	101 getfield (4, 4)
	102 org/apache/commons/math3/ode/sampling/NordsieckStepInterpolator.stateVariation:[D (4, 4)
	104 iload (4, 4)
	105 #15 (4, 4)
	106 dup2 (4, 4)
	107 daload (4, 4)
	108 dload (4, 4)
	109 #16 (4, 4)
	110 dadd (4, 4)
	111 dastore (4, 4)
	112 aload_0 (4, 4)
	113 getfield (4, 4)
	114 org/apache/commons/math3/ode/sampling/NordsieckStepInterpolator.interpolatedDerivatives:[D (4, 4)
	116 iload (4, 4)
	117 #15 (4, 4)
	118 dup2 (4, 4)
	119 daload (4, 4)
	120 iload (4, 4)
	121 #11 (4, 4)
	122 i2d (4, 4)
	123 dload (4, 4)
	124 #16 (4, 4)
	125 dmul (4, 4)
	126 dadd (4, 4)
	127 dastore (4, 4)
	128 iinc (4, 4)
	129 #15 (4, 4)
	130 -89 (4, 4)
	131 goto (4, 4)
	132 -49 (4, 4)
	134 iinc (4, 4)
	135 #10 (4, 4)
	136 -89 (4, 4)
	137 goto (4, 4)
	138 -85 (4, 4)
	140 iconst_0 (4, 4)
	141 istore (4, 4)
	142 #10 (4, 4)
	143 iload (4, 4)
	144 #10 (4, 4)
	145 aload_0 (4, 4)
	146 getfield (4, 4)
	147 org/apache/commons/math3/ode/sampling/NordsieckStepInterpolator.currentState:[D (4, 4)
	149 arraylength (4, 4)
	150 if_icmpge (4, 4)
	151 79 (4, 4)
	153 aload_0 (4, 4)
	154 getfield (4, 4)
	155 org/apache/commons/math3/ode/sampling/NordsieckStepInterpolator.stateVariation:[D (4, 4)
	157 iload (4, 4)
	158 #10 (4, 4)
	159 dup2 (4, 4)
	160 daload (4, 4)
	161 aload_0 (4, 4)
	162 getfield (4, 4)
	163 org/apache/commons/math3/ode/sampling/NordsieckStepInterpolator.scaled:[D (4, 4)
	165 iload (4, 4)
	166 #10 (4, 4)
	167 daload (4, 4)
	168 dload (4, 4)
	169 #7 (4, 4)
	170 dmul (4, 4)
	171 dadd (4, 4)
	172 dastore (4, 4)
	173 aload_0 (4, 4)
	174 getfield (4, 4)
	175 org/apache/commons/math3/ode/sampling/NordsieckStepInterpolator.interpolatedState:[D (4, 4)
	177 iload (4, 4)
	178 #10 (4, 4)
	179 aload_0 (4, 4)
	180 getfield (4, 4)
	181 org/apache/commons/math3/ode/sampling/NordsieckStepInterpolator.currentState:[D (4, 4)
	183 iload (4, 4)
	184 #10 (4, 4)
	185 daload (4, 4)
	186 aload_0 (4, 4)
	187 getfield (4, 4)
	188 org/apache/commons/math3/ode/sampling/NordsieckStepInterpolator.stateVariation:[D (4, 4)
	190 iload (4, 4)
	191 #10 (4, 4)
	192 daload (4, 4)
	193 dadd (4, 4)
	194 dastore (4, 4)
	195 aload_0 (4, 4)
	196 getfield (4, 4)
	197 org/apache/commons/math3/ode/sampling/NordsieckStepInterpolator.interpolatedDerivatives:[D (4, 4)
	199 iload (4, 4)
	200 #10 (4, 4)
	201 aload_0 (4, 4)
	202 getfield (4, 4)
	203 org/apache/commons/math3/ode/sampling/NordsieckStepInterpolator.interpolatedDerivatives:[D (4, 4)
	205 iload (4, 4)
	206 #10 (4, 4)
	207 daload (4, 4)
	208 aload_0 (4, 4)
	209 getfield (4, 4)
	210 org/apache/commons/math3/ode/sampling/NordsieckStepInterpolator.scaled:[D (4, 4)
	212 iload (4, 4)
	213 #10 (4, 4)
	214 daload (4, 4)
	215 dload (4, 4)
	216 #7 (4, 4)
	217 dmul (4, 4)
	218 dadd (4, 4)
	219 dload (4, 4)
	220 #5 (4, 4)
	221 ddiv (4, 4)
	222 dastore (4, 4)
	223 iinc (4, 4)
	224 #10 (4, 4)
	225 -89 (4, 4)
	226 goto (4, 4)
	227 -83 (4, 4)
	229 return (0, 4)

Method: writeExternal
	0 aload_0 (0, 0)
	1 aload_1 (0, 0)
	2 invokevirtual (0, 0)
	3 org/apache/commons/math3/ode/sampling/NordsieckStepInterpolator.writeBaseExternal:(Ljava/io/ObjectOutput;)V (0, 0)
	5 aload_1 (0, 0)
	6 aload_0 (0, 0)
	7 getfield (0, 0)
	8 org/apache/commons/math3/ode/sampling/NordsieckStepInterpolator.scalingH:D (0, 0)
	10 invokeinterface (0, 0)
	11 java/io/ObjectOutput.writeBoolean:(Z)V (0, 0)
	13 0 (0, 0)
	15 aload_1 (0, 0)
	16 aload_0 (0, 0)
	17 getfield (0, 0)
	18 org/apache/commons/math3/ode/sampling/NordsieckStepInterpolator.referenceTime:D (0, 0)
	20 invokeinterface (0, 0)
	21 java/io/ObjectOutput.writeBoolean:(Z)V (0, 0)
	23 0 (0, 0)
	25 aload_0 (0, 0)
	26 getfield (0, 0)
	27 org/apache/commons/math3/ode/sampling/NordsieckStepInterpolator.currentState:[D (0, 0)
	29 ifnonnull (0, 0)
	30 7 (0, 0)
	32 iconst_m1 (0, 0)
	33 goto (0, 0)
	34 8 (0, 0)
	36 aload_0 (0, 0)
	37 getfield (0, 0)
	38 org/apache/commons/math3/ode/sampling/NordsieckStepInterpolator.currentState:[D (0, 0)
	40 arraylength (0, 0)
	41 istore_2 (0, 0)
	42 aload_0 (1, 1)
	43 getfield (1, 1)
	44 org/apache/commons/math3/ode/sampling/NordsieckStepInterpolator.scaled:[D (1, 1)
	46 ifnonnull (1, 1)
	47 13 (1, 1)
	49 aload_1 (1, 1)
	50 iconst_0 (1, 1)
	51 invokeinterface (1, 1)
	52 java/io/ObjectOutput.writeObject:(Ljava/lang/Object;)V (1, 1)
	54 0 (1, 1)
	56 goto (1, 1)
	57 35 (1, 1)
	59 aload_1 (2, 2)
	60 iconst_1 (2, 2)
	61 invokeinterface (2, 2)
	62 java/io/ObjectOutput.writeObject:(Ljava/lang/Object;)V (2, 2)
	64 0 (2, 2)
	66 iconst_0 (3, 4)
	67 istore_3 (3, 4)
	68 iload_3 (3, 4)
	69 iload_2 (3, 4)
	70 if_icmpge (3, 4)
	71 21 (3, 4)
	73 aload_1 (3, 4)
	74 aload_0 (3, 4)
	75 getfield (3, 4)
	76 org/apache/commons/math3/ode/sampling/NordsieckStepInterpolator.scaled:[D (3, 4)
	78 iload_3 (3, 4)
	79 daload (3, 4)
	80 invokeinterface (3, 4)
	81 java/io/ObjectOutput.writeBoolean:(Z)V (3, 4)
	83 0 (3, 4)
	85 iinc (3, 4)
	86 #3 (3, 4)
	87 -89 (3, 4)
	88 goto (3, 4)
	89 -20 (3, 4)
	91 aload_0 (1, 1)
	92 getfield (1, 1)
	93 org/apache/commons/math3/ode/sampling/NordsieckStepInterpolator.nordsieck:Lorg/apache/commons/math3/linear/Array2DRowRealMatrix; (1, 1)
	95 ifnonnull (1, 1)
	96 13 (1, 1)
	98 aload_1 (1, 1)
	99 iconst_0 (1, 1)
	100 invokeinterface (1, 1)
	101 java/io/ObjectOutput.writeObject:(Ljava/lang/Object;)V (1, 1)
	103 0 (1, 1)
	105 goto (1, 1)
	106 20 (1, 1)
	108 aload_1 (2, 2)
	109 iconst_1 (2, 2)
	110 invokeinterface (2, 2)
	111 java/io/ObjectOutput.writeObject:(Ljava/lang/Object;)V (2, 2)
	113 0 (2, 2)
	115 aload_1 (2, 2)
	116 aload_0 (2, 2)
	117 getfield (2, 2)
	118 org/apache/commons/math3/ode/sampling/NordsieckStepInterpolator.nordsieck:Lorg/apache/commons/math3/linear/Array2DRowRealMatrix; (2, 2)
	120 invokeinterface (2, 2)
	121 java/io/ObjectOutput.readBaseExternal:(Ljava/io/ObjectInput;)D (2, 2)
	123 0 (2, 2)
	125 return (0, 0)

Method: readExternal
	0 aload_0 (0, 0)
	1 aload_1 (0, 0)
	2 invokevirtual (0, 0)
	3 org/apache/commons/math3/ode/sampling/NordsieckStepInterpolator.readBaseExternal:(Ljava/io/ObjectInput;)D (0, 0)
	5 dstore_2 (0, 0)
	6 aload_0 (0, 0)
	7 aload_1 (0, 0)
	8 invokeinterface (0, 0)
	9 java/io/ObjectInput.readBoolean:()Z (0, 0)
	11 0 (0, 0)
	13 putfield (0, 0)
	14 org/apache/commons/math3/ode/sampling/NordsieckStepInterpolator.scalingH:D (0, 0)
	16 aload_0 (0, 0)
	17 aload_1 (0, 0)
	18 invokeinterface (0, 0)
	19 java/io/ObjectInput.readBoolean:()Z (0, 0)
	21 0 (0, 0)
	23 putfield (0, 0)
	24 org/apache/commons/math3/ode/sampling/NordsieckStepInterpolator.referenceTime:D (0, 0)
	26 aload_0 (0, 0)
	27 getfield (0, 0)
	28 org/apache/commons/math3/ode/sampling/NordsieckStepInterpolator.currentState:[D (0, 0)
	30 ifnonnull (0, 0)
	31 7 (0, 0)
	33 iconst_m1 (0, 0)
	34 goto (0, 0)
	35 8 (0, 0)
	37 aload_0 (0, 0)
	38 getfield (0, 0)
	39 org/apache/commons/math3/ode/sampling/NordsieckStepInterpolator.currentState:[D (0, 0)
	41 arraylength (0, 0)
	42 istore (0, 0)
	43 #4 (0, 0)
	44 aload_1 (0, 0)
	45 invokeinterface (0, 0)
	46 java/io/ObjectInput.readObject:()Ljava/lang/Object; (0, 0)
	48 0 (0, 0)
	50 istore (0, 0)
	51 #5 (0, 0)
	52 iload (1, 1)
	53 #5 (1, 1)
	54 ifeq (1, 1)
	55 43 (1, 1)
	57 aload_0 (1, 1)
	58 iload (1, 1)
	59 #4 (1, 1)
	60 newarray (1, 1)
	61 7 (1, 1)
	62 putfield (1, 1)
	63 org/apache/commons/math3/ode/sampling/NordsieckStepInterpolator.scaled:[D (1, 1)
	65 iconst_0 (2, 4)
	66 istore (2, 4)
	67 #6 (2, 4)
	68 iload (2, 4)
	69 #6 (2, 4)
	70 iload (2, 4)
	71 #4 (2, 4)
	72 if_icmpge (2, 4)
	73 22 (2, 4)
	75 aload_0 (2, 4)
	76 getfield (2, 4)
	77 org/apache/commons/math3/ode/sampling/NordsieckStepInterpolator.scaled:[D (2, 4)
	79 iload (2, 4)
	80 #6 (2, 4)
	81 aload_1 (2, 4)
	82 invokeinterface (2, 4)
	83 java/io/ObjectInput.readBoolean:()Z (2, 4)
	85 0 (2, 4)
	87 dastore (2, 4)
	88 iinc (2, 4)
	89 #6 (2, 4)
	90 -89 (2, 4)
	91 goto (2, 4)
	92 -23 (2, 4)
	94 goto (2, 4)
	95 8 (2, 4)
	97 aload_0 (2, 2)
	98 aconst_null (2, 2)
	99 putfield (2, 2)
	100 org/apache/commons/math3/ode/sampling/NordsieckStepInterpolator.scaled:[D (2, 2)
	102 aload_1 (0, 0)
	103 invokeinterface (0, 0)
	104 java/io/ObjectInput.readObject:()Ljava/lang/Object; (0, 0)
	106 0 (0, 0)
	108 istore (0, 0)
	109 #6 (0, 0)
	110 iload (1, 1)
	111 #6 (1, 1)
	112 ifeq (1, 1)
	113 19 (1, 1)
	115 aload_0 (1, 1)
	116 aload_1 (1, 1)
	117 invokeinterface (1, 1)
	118 java/io/ObjectInput.org/apache/commons/math3/ode/sampling/AbstractStepInterpolator (1, 1)
	120 0 (1, 1)
	122 checkcast (1, 1)
	123 org/apache/commons/math3/linear/Array2DRowRealMatrix (1, 1)
	125 putfield (1, 1)
	126 org/apache/commons/math3/ode/sampling/NordsieckStepInterpolator.nordsieck:Lorg/apache/commons/math3/linear/Array2DRowRealMatrix; (1, 1)
	128 goto (1, 1)
	129 8 (1, 1)
	131 aload_0 (2, 2)
	132 aconst_null (2, 2)
	133 putfield (2, 2)
	134 org/apache/commons/math3/ode/sampling/NordsieckStepInterpolator.nordsieck:Lorg/apache/commons/math3/linear/Array2DRowRealMatrix; (2, 2)
	136 iload (1, 1)
	137 #5 (1, 1)
	138 ifeq (1, 1)
	139 24 (1, 1)
	141 iload (1, 1)
	142 #6 (1, 1)
	143 ifeq (1, 1)
	144 19 (1, 1)
	146 aload_0 (1, 1)
	147 iload (1, 1)
	148 #4 (1, 1)
	149 newarray (1, 1)
	150 7 (1, 1)
	151 putfield (1, 1)
	152 org/apache/commons/math3/ode/sampling/NordsieckStepInterpolator.stateVariation:[D (1, 1)
	154 aload_0 (1, 1)
	155 dload_2 (1, 1)
	156 invokevirtual (1, 1)
	157 org/apache/commons/math3/ode/sampling/NordsieckStepInterpolator.setInterpolatedTime:(D)V (1, 1)
	159 goto (1, 1)
	160 8 (1, 1)
	162 aload_0 (2, 2)
	163 aconst_null (2, 2)
	164 putfield (2, 2)
	165 org/apache/commons/math3/ode/sampling/NordsieckStepInterpolator.stateVariation:[D (2, 2)
	167 return (0, 0)

