Method: values
	0 getstatic (0, 0)
	1 org/apache/commons/math3/ode/sampling/StepNormalizerBounds.$VALUES:[Lorg/apache/commons/math3/ode/sampling/StepNormalizerBounds; (0, 0)
	3 invokevirtual (0, 0)
	4 [Lorg/apache/commons/math3/ode/sampling/StepNormalizerBounds;.clone:()Ljava/lang/Object; (0, 0)
	6 checkcast (0, 0)
	7 [Lorg/apache/commons/math3/ode/sampling/StepNormalizerBounds; (0, 0)
	9 areturn (0, 0)

Method: valueOf
	0 ldc (0, 0)
	1 org/apache/commons/math3/ode/sampling/StepNormalizerBounds (0, 0)
	2 aload_0 (0, 0)
	3 invokestatic (0, 0)
	4 java/lang/Enum.valueOf:(Ljava/lang/Class;Ljava/lang/String;)Ljava/lang/Enum; (0, 0)
	6 checkcast (0, 0)
	7 org/apache/commons/math3/ode/sampling/StepNormalizerBounds (0, 0)
	9 areturn (0, 0)

Method: <init>
	0 aload_0 (0, 0)
	1 aload_1 (0, 0)
	2 iload_2 (0, 0)
	3 invokespecial (0, 0)
	4 java/lang/Enum.<init>:(Ljava/lang/String;I)V (0, 0)
	6 aload_0 (0, 0)
	7 iload_3 (0, 0)
	8 putfield (0, 0)
	9 org/apache/commons/math3/ode/sampling/StepNormalizerBounds.first:Z (0, 0)
	11 aload_0 (0, 0)
	12 iload (0, 0)
	13 #4 (0, 0)
	14 putfield (0, 0)
	15 org/apache/commons/math3/ode/sampling/StepNormalizerBounds.last:Z (0, 0)
	17 return (0, 0)

Method: firstIncluded
	0 aload_0 (0, 0)
	1 getfield (0, 0)
	2 org/apache/commons/math3/ode/sampling/StepNormalizerBounds.first:Z (0, 0)
	4 ireturn (0, 0)

Method: lastIncluded
	0 aload_0 (0, 0)
	1 getfield (0, 0)
	2 org/apache/commons/math3/ode/sampling/StepNormalizerBounds.last:Z (0, 0)
	4 ireturn (0, 0)

Method: <clinit>
	0 new (0, 0)
	1 org/apache/commons/math3/ode/sampling/StepNormalizerBounds (0, 0)
	3 dup (0, 0)
	4 ldc (0, 0)
	5 NEITHER (0, 0)
	6 iconst_0 (0, 0)
	7 iconst_0 (0, 0)
	8 iconst_0 (0, 0)
	9 invokespecial (0, 0)
	10 org/apache/commons/math3/ode/sampling/StepNormalizerBounds.<init>:(Ljava/lang/String;IZZ)V (0, 0)
	12 putstatic (0, 0)
	13 org/apache/commons/math3/ode/sampling/StepNormalizerBounds.NEITHER:Lorg/apache/commons/math3/ode/sampling/StepNormalizerBounds; (0, 0)
	15 new (0, 0)
	16 org/apache/commons/math3/ode/sampling/StepNormalizerBounds (0, 0)
	18 dup (0, 0)
	19 ldc (0, 0)
	20 FIRST (0, 0)
	21 iconst_1 (0, 0)
	22 iconst_1 (0, 0)
	23 iconst_0 (0, 0)
	24 invokespecial (0, 0)
	25 org/apache/commons/math3/ode/sampling/StepNormalizerBounds.<init>:(Ljava/lang/String;IZZ)V (0, 0)
	27 putstatic (0, 0)
	28 org/apache/commons/math3/ode/sampling/StepNormalizerBounds.FIRST:Lorg/apache/commons/math3/ode/sampling/StepNormalizerBounds; (0, 0)
	30 new (0, 0)
	31 org/apache/commons/math3/ode/sampling/StepNormalizerBounds (0, 0)
	33 dup (0, 0)
	34 ldc (0, 0)
	35 LAST (0, 0)
	36 iconst_2 (0, 0)
	37 iconst_0 (0, 0)
	38 iconst_1 (0, 0)
	39 invokespecial (0, 0)
	40 org/apache/commons/math3/ode/sampling/StepNormalizerBounds.<init>:(Ljava/lang/String;IZZ)V (0, 0)
	42 putstatic (0, 0)
	43 org/apache/commons/math3/ode/sampling/StepNormalizerBounds.LAST:Lorg/apache/commons/math3/ode/sampling/StepNormalizerBounds; (0, 0)
	45 new (0, 0)
	46 org/apache/commons/math3/ode/sampling/StepNormalizerBounds (0, 0)
	48 dup (0, 0)
	49 ldc (0, 0)
	50 BOTH (0, 0)
	51 iconst_3 (0, 0)
	52 iconst_1 (0, 0)
	53 iconst_1 (0, 0)
	54 invokespecial (0, 0)
	55 org/apache/commons/math3/ode/sampling/StepNormalizerBounds.<init>:(Ljava/lang/String;IZZ)V (0, 0)
	57 putstatic (0, 0)
	58 org/apache/commons/math3/ode/sampling/StepNormalizerBounds.BOTH:Lorg/apache/commons/math3/ode/sampling/StepNormalizerBounds; (0, 0)
	60 iconst_4 (0, 0)
	61 anewarray (0, 0)
	62 org/apache/commons/math3/ode/sampling/StepNormalizerBounds (0, 0)
	64 dup (0, 0)
	65 iconst_0 (0, 0)
	66 getstatic (0, 0)
	67 org/apache/commons/math3/ode/sampling/StepNormalizerBounds.NEITHER:Lorg/apache/commons/math3/ode/sampling/StepNormalizerBounds; (0, 0)
	69 aastore (0, 0)
	70 dup (0, 0)
	71 iconst_1 (0, 0)
	72 getstatic (0, 0)
	73 org/apache/commons/math3/ode/sampling/StepNormalizerBounds.FIRST:Lorg/apache/commons/math3/ode/sampling/StepNormalizerBounds; (0, 0)
	75 aastore (0, 0)
	76 dup (0, 0)
	77 iconst_2 (0, 0)
	78 getstatic (0, 0)
	79 org/apache/commons/math3/ode/sampling/StepNormalizerBounds.LAST:Lorg/apache/commons/math3/ode/sampling/StepNormalizerBounds; (0, 0)
	81 aastore (0, 0)
	82 dup (0, 0)
	83 iconst_3 (0, 0)
	84 getstatic (0, 0)
	85 org/apache/commons/math3/ode/sampling/StepNormalizerBounds.BOTH:Lorg/apache/commons/math3/ode/sampling/StepNormalizerBounds; (0, 0)
	87 aastore (0, 0)
	88 putstatic (0, 0)
	89 org/apache/commons/math3/ode/sampling/StepNormalizerBounds.$VALUES:[Lorg/apache/commons/math3/ode/sampling/StepNormalizerBounds; (0, 0)
	91 return (0, 0)

