Method: compare
	0 aload_0 (0, 0)
	1 aload_1 (0, 0)
	2 checkcast (0, 0)
	3 org/apache/commons/math3/optimization/PointVectorValuePair (0, 0)
	5 aload_2 (0, 0)
	6 checkcast (0, 0)
	7 org/apache/commons/math3/optimization/PointVectorValuePair (0, 0)
	9 invokevirtual (0, 0)
	10 org/apache/commons/math3/optimization/BaseMultivariateVectorMultiStartOptimizer$1.compare:(Lorg/apache/commons/math3/optimization/PointVectorValuePair;Lorg/apache/commons/math3/optimization/PointVectorValuePair;)I (0, 0)
	12 ireturn (0, 0)

Method: weightedResidual
	0 aload_1 (0, 0)
	1 invokevirtual (0, 0)
	2 org/apache/commons/math3/optimization/PointVectorValuePair.getValueRef:()[D (0, 0)
	4 astore_2 (0, 0)
	5 dconst_0 (0, 0)
	6 dstore_3 (0, 0)
	7 iconst_0 (1, 4)
	8 istore (1, 4)
	9 #5 (1, 4)
	10 iload (1, 4)
	11 #5 (1, 4)
	12 aload_2 (1, 4)
	13 arraylength (1, 4)
	14 if_icmpge (1, 4)
	15 39 (1, 4)
	17 aload_2 (1, 4)
	18 iload (1, 4)
	19 #5 (1, 4)
	20 daload (1, 4)
	21 aload_0 (1, 4)
	22 getfield (1, 4)
	23 org/apache/commons/math3/optimization/BaseMultivariateVectorMultiStartOptimizer$1.val$target:[D (1, 4)
	25 iload (1, 4)
	26 #5 (1, 4)
	27 daload (1, 4)
	28 dsub (1, 4)
	29 dstore (1, 4)
	30 #6 (1, 4)
	31 dload_3 (1, 4)
	32 aload_0 (1, 4)
	33 getfield (1, 4)
	34 org/apache/commons/math3/optimization/BaseMultivariateVectorMultiStartOptimizer$1.val$weights:[D (1, 4)
	36 iload (1, 4)
	37 #5 (1, 4)
	38 daload (1, 4)
	39 dload (1, 4)
	40 #6 (1, 4)
	41 dmul (1, 4)
	42 dload (1, 4)
	43 #6 (1, 4)
	44 dmul (1, 4)
	45 dadd (1, 4)
	46 dstore_3 (1, 4)
	47 iinc (1, 4)
	48 #5 (1, 4)
	49 -89 (1, 4)
	50 goto (1, 4)
	51 -40 (1, 4)
	53 dload_3 (0, 0)
	54 dreturn (0, 0)

