Method: <init>
	0 aload_0 (0, 0)
	1 invokespecial (0, 0)
	2 java/lang/Object.<init>:()V (0, 0)
	4 aload_1 (1, 1)
	5 ifnull (1, 1)
	6 7 (1, 1)
	8 aload_3 (1, 1)
	9 ifnonnull (1, 1)
	10 11 (1, 1)
	12 new (1, 1)
	13 org/apache/commons/math3/exception/NullArgumentException (1, 1)
	15 dup (1, 1)
	16 invokespecial (1, 1)
	17 org/apache/commons/math3/exception/NullArgumentException.<init>:()V (1, 1)
	19 athrow (1, 1)
	20 iload_2 (2, 1)
	21 iconst_1 (2, 1)
	22 if_icmpge (2, 1)
	23 15 (2, 1)
	25 new (2, 1)
	26 org/apache/commons/math3/exception/NotStrictlyPositiveException (2, 1)
	28 dup (2, 1)
	29 iload_2 (2, 1)
	30 invokestatic (2, 1)
	31 java/lang/Integer.valueOf:(I)Ljava/lang/Integer; (2, 1)
	33 invokespecial (2, 1)
	34 org/apache/commons/math3/exception/NotStrictlyPositiveException.<init>:(Ljava/lang/Number;)V (2, 1)
	36 athrow (2, 1)
	37 aload_0 (1, 1)
	38 aload_1 (1, 1)
	39 putfield (1, 1)
	40 org/apache/commons/math3/optimization/BaseMultivariateVectorMultiStartOptimizer.optimizer:Lorg/apache/commons/math3/optimization/BaseMultivariateVectorOptimizer; (1, 1)
	42 aload_0 (1, 1)
	43 iload_2 (1, 1)
	44 putfield (1, 1)
	45 org/apache/commons/math3/optimization/BaseMultivariateVectorMultiStartOptimizer.starts:I (1, 1)
	47 aload_0 (1, 1)
	48 aload_3 (1, 1)
	49 putfield (1, 1)
	50 org/apache/commons/math3/optimization/BaseMultivariateVectorMultiStartOptimizer.generator:Lorg/apache/commons/math3/random/RandomVectorGenerator; (1, 1)
	52 return (0, 0)

Method: getOptima
	0 aload_0 (1, 1)
	1 getfield (1, 1)
	2 org/apache/commons/math3/optimization/BaseMultivariateVectorMultiStartOptimizer.optima:[Lorg/apache/commons/math3/optimization/PointVectorValuePair; (1, 1)
	4 ifnonnull (1, 1)
	5 18 (1, 1)
	7 new (1, 1)
	8 org/apache/commons/math3/exception/MathIllegalStateException (1, 1)
	10 dup (1, 1)
	11 getstatic (1, 1)
	12 org/apache/commons/math3/exception/util/LocalizedFormats.NO_OPTIMUM_COMPUTED_YET:Lorg/apache/commons/math3/exception/util/LocalizedFormats; (1, 1)
	14 iconst_0 (1, 1)
	15 anewarray (1, 1)
	16 java/lang/Object (1, 1)
	18 invokespecial (1, 1)
	19 org/apache/commons/math3/exception/MathIllegalStateException.<init>:(Lorg/apache/commons/math3/exception/util/Localizable;[Ljava/lang/Object;)V (1, 1)
	21 athrow (1, 1)
	22 aload_0 (0, 0)
	23 getfield (0, 0)
	24 org/apache/commons/math3/optimization/BaseMultivariateVectorMultiStartOptimizer.optima:[Lorg/apache/commons/math3/optimization/PointVectorValuePair; (0, 0)
	26 invokevirtual (0, 0)
	27 [Lorg/apache/commons/math3/optimization/PointVectorValuePair;.clone:()Ljava/lang/Object; (0, 0)
	29 checkcast (0, 0)
	30 [Lorg/apache/commons/math3/optimization/PointVectorValuePair; (0, 0)
	32 areturn (0, 0)

Method: getMaxEvaluations
	0 aload_0 (0, 0)
	1 getfield (0, 0)
	2 org/apache/commons/math3/optimization/BaseMultivariateVectorMultiStartOptimizer.maxEvaluations:I (0, 0)
	4 ireturn (0, 0)

Method: getEvaluations
	0 aload_0 (0, 0)
	1 getfield (0, 0)
	2 org/apache/commons/math3/optimization/BaseMultivariateVectorMultiStartOptimizer.totalEvaluations:I (0, 0)
	4 ireturn (0, 0)

Method: getConvergenceChecker
	0 aload_0 (0, 0)
	1 getfield (0, 0)
	2 org/apache/commons/math3/optimization/BaseMultivariateVectorMultiStartOptimizer.optimizer:Lorg/apache/commons/math3/optimization/BaseMultivariateVectorOptimizer; (0, 0)
	4 invokeinterface (0, 0)
	5 org/apache/commons/math3/optimization/BaseMultivariateVectorOptimizer.org/apache/commons/math3/optimization/PointVectorValuePair (0, 0)
	7 0 (0, 0)
	9 areturn (0, 0)

Method: optimize
	0 aload_0 (0, 0)
	1 iload_1 (0, 0)
	2 putfield (0, 0)
	3 org/apache/commons/math3/optimization/BaseMultivariateVectorMultiStartOptimizer.maxEvaluations:I (0, 0)
	5 aconst_null (0, 0)
	6 astore (0, 0)
	7 #6 (0, 0)
	8 aload_0 (0, 0)
	9 aload_0 (0, 0)
	10 getfield (0, 0)
	11 org/apache/commons/math3/optimization/BaseMultivariateVectorMultiStartOptimizer.starts:I (0, 0)
	13 anewarray (0, 0)
	14 org/apache/commons/math3/optimization/PointVectorValuePair (0, 0)
	16 putfield (0, 0)
	17 org/apache/commons/math3/optimization/BaseMultivariateVectorMultiStartOptimizer.optima:[Lorg/apache/commons/math3/optimization/PointVectorValuePair; (0, 0)
	19 aload_0 (0, 0)
	20 iconst_0 (0, 0)
	21 putfield (0, 0)
	22 org/apache/commons/math3/optimization/BaseMultivariateVectorMultiStartOptimizer.totalEvaluations:I (0, 0)
	24 iconst_0 (1, 4)
	25 istore (1, 4)
	26 #7 (1, 4)
	27 iload (1, 4)
	28 #7 (1, 4)
	29 aload_0 (1, 4)
	30 getfield (1, 4)
	31 org/apache/commons/math3/optimization/BaseMultivariateVectorMultiStartOptimizer.starts:I (1, 4)
	33 if_icmpge (1, 4)
	34 102 (1, 4)
	36 aload_0 (1, 4)
	37 getfield (1, 4)
	38 org/apache/commons/math3/optimization/BaseMultivariateVectorMultiStartOptimizer.optima:[Lorg/apache/commons/math3/optimization/PointVectorValuePair; (1, 4)
	40 iload (1, 4)
	41 #7 (1, 4)
	42 aload_0 (1, 4)
	43 getfield (1, 4)
	44 org/apache/commons/math3/optimization/BaseMultivariateVectorMultiStartOptimizer.optimizer:Lorg/apache/commons/math3/optimization/BaseMultivariateVectorOptimizer; (1, 4)
	46 iload_1 (1, 4)
	47 aload_0 (1, 4)
	48 getfield (1, 4)
	49 org/apache/commons/math3/optimization/BaseMultivariateVectorMultiStartOptimizer.totalEvaluations:I (1, 4)
	51 isub (1, 4)
	52 aload_2 (1, 4)
	53 aload_3 (1, 4)
	54 aload (1, 4)
	55 #4 (1, 4)
	56 iload (1, 4)
	57 #7 (1, 4)
	58 ifne (1, 4)
	59 8 (1, 4)
	61 aload (1, 4)
	62 #5 (1, 4)
	63 goto (1, 4)
	64 12 (1, 4)
	66 aload_0 (1, 4)
	67 getfield (1, 4)
	68 org/apache/commons/math3/optimization/BaseMultivariateVectorMultiStartOptimizer.generator:Lorg/apache/commons/math3/random/RandomVectorGenerator; (1, 4)
	70 invokeinterface (1, 4)
	71 org/apache/commons/math3/random/RandomVectorGenerator.optimize:(ILorg/apache/commons/math3/analysis/MultivariateVectorFunction;[D[D[D)Lorg/apache/commons/math3/optimization/PointVectorValuePair; (1, 4)
	73 0 (1, 4)
	75 invokeinterface (1, 4)
	76 org/apache/commons/math3/optimization/BaseMultivariateVectorOptimizer.org/apache/commons/math3/exception/ConvergenceException (1, 4)
	78 0 (1, 4)
	80 aastore (1, 4)
	81 goto (1, 4)
	82 30 (1, 4)
	84 astore (1, 4)
	85 #8 (1, 4)
	86 aload_0 (1, 4)
	87 getfield (1, 4)
	88 org/apache/commons/math3/optimization/BaseMultivariateVectorMultiStartOptimizer.optima:[Lorg/apache/commons/math3/optimization/PointVectorValuePair; (1, 4)
	90 iload (1, 4)
	91 #7 (1, 4)
	92 aconst_null (1, 4)
	93 aastore (1, 4)
	94 goto (0, 0)
	95 17 (0, 0)
	97 astore (0, 0)
	98 #8 (0, 0)
	99 aload (0, 0)
	100 #8 (0, 0)
	101 astore (0, 0)
	102 #6 (0, 0)
	103 aload_0 (0, 0)
	104 getfield (0, 0)
	105 org/apache/commons/math3/optimization/BaseMultivariateVectorMultiStartOptimizer.optima:[Lorg/apache/commons/math3/optimization/PointVectorValuePair; (0, 0)
	107 iload (0, 0)
	108 #7 (0, 0)
	109 aconst_null (0, 0)
	110 aastore (0, 0)
	111 aload_0 (0, 0)
	112 dup (0, 0)
	113 getfield (0, 0)
	114 org/apache/commons/math3/optimization/BaseMultivariateVectorMultiStartOptimizer.totalEvaluations:I (0, 0)
	116 aload_0 (0, 0)
	117 getfield (0, 0)
	118 org/apache/commons/math3/optimization/BaseMultivariateVectorMultiStartOptimizer.optimizer:Lorg/apache/commons/math3/optimization/BaseMultivariateVectorOptimizer; (0, 0)
	120 invokeinterface (0, 0)
	121 org/apache/commons/math3/optimization/BaseMultivariateVectorOptimizer.sortPairs:([D[D)V (0, 0)
	123 0 (0, 0)
	125 iadd (0, 0)
	126 putfield (0, 0)
	127 org/apache/commons/math3/optimization/BaseMultivariateVectorMultiStartOptimizer.totalEvaluations:I (0, 0)
	129 iinc (0, 0)
	130 #7 (0, 0)
	131 -89 (0, 0)
	132 goto (0, 0)
	133 -105 (0, 0)
	135 aload_0 (0, 0)
	136 aload_3 (0, 0)
	137 aload (0, 0)
	138 #4 (0, 0)
	139 invokespecial (0, 0)
	140 org/apache/commons/math3/optimization/BaseMultivariateVectorMultiStartOptimizer.sortPairs:([D[D)V (0, 0)
	142 aload_0 (1, 1)
	143 getfield (1, 1)
	144 org/apache/commons/math3/optimization/BaseMultivariateVectorMultiStartOptimizer.optima:[Lorg/apache/commons/math3/optimization/PointVectorValuePair; (1, 1)
	146 iconst_0 (1, 1)
	147 aaload (1, 1)
	148 ifnonnull (1, 1)
	149 6 (1, 1)
	151 aload (2, 1)
	152 #6 (2, 1)
	153 athrow (2, 1)
	154 aload_0 (0, 0)
	155 getfield (0, 0)
	156 org/apache/commons/math3/optimization/BaseMultivariateVectorMultiStartOptimizer.optima:[Lorg/apache/commons/math3/optimization/PointVectorValuePair; (0, 0)
	158 iconst_0 (0, 0)
	159 aaload (0, 0)
	160 areturn (0, 0)

Method: sortPairs
	0 aload_0 (0, 0)
	1 getfield (0, 0)
	2 org/apache/commons/math3/optimization/BaseMultivariateVectorMultiStartOptimizer.optima:[Lorg/apache/commons/math3/optimization/PointVectorValuePair; (0, 0)
	4 new (0, 0)
	5 org/apache/commons/math3/optimization/BaseMultivariateVectorMultiStartOptimizer$1 (0, 0)
	7 dup (0, 0)
	8 aload_0 (0, 0)
	9 aload_1 (0, 0)
	10 aload_2 (0, 0)
	11 invokespecial (0, 0)
	12 org/apache/commons/math3/optimization/BaseMultivariateVectorMultiStartOptimizer$1.<init>:(Lorg/apache/commons/math3/optimization/BaseMultivariateVectorMultiStartOptimizer;[D[D)V (0, 0)
	14 invokestatic (0, 0)
	15 java/util/Arrays.sort:([Ljava/lang/Object;Ljava/util/Comparator;)V (0, 0)
	17 return (0, 0)

