Method: <init>
	0 aload_0 (0, 0)
	1 aload (0, 0)
	2 #4 (0, 0)
	3 invokespecial (0, 0)
	4 org/apache/commons/math3/ml/clustering/Clusterer.<init>:(Lorg/apache/commons/math3/ml/distance/DistanceMeasure;)V (0, 0)
	6 dload_1 (1, 1)
	7 dconst_0 (1, 1)
	8 dcmpg (1, 1)
	9 ifge (1, 1)
	10 15 (1, 1)
	12 new (1, 1)
	13 org/apache/commons/math3/exception/NotPositiveException (1, 1)
	15 dup (1, 1)
	16 dload_1 (1, 1)
	17 invokestatic (1, 1)
	18 java/lang/Double.valueOf:(D)Ljava/lang/Double; (1, 1)
	20 invokespecial (1, 1)
	21 org/apache/commons/math3/exception/NotPositiveException.<init>:(Ljava/lang/Number;)V (1, 1)
	23 athrow (1, 1)
	24 iload_3 (1, 1)
	25 ifge (1, 1)
	26 15 (1, 1)
	28 new (1, 1)
	29 org/apache/commons/math3/exception/NotPositiveException (1, 1)
	31 dup (1, 1)
	32 iload_3 (1, 1)
	33 invokestatic (1, 1)
	34 java/lang/Integer.valueOf:(I)Ljava/lang/Integer; (1, 1)
	36 invokespecial (1, 1)
	37 org/apache/commons/math3/exception/NotPositiveException.<init>:(Ljava/lang/Number;)V (1, 1)
	39 athrow (1, 1)
	40 aload_0 (0, 0)
	41 dload_1 (0, 0)
	42 putfield (0, 0)
	43 org/apache/commons/math3/ml/clustering/DBSCANClusterer.eps:D (0, 0)
	45 aload_0 (0, 0)
	46 iload_3 (0, 0)
	47 putfield (0, 0)
	48 org/apache/commons/math3/ml/clustering/DBSCANClusterer.minPts:I (0, 0)
	50 return (0, 0)

Method: getEps
	0 aload_0 (0, 0)
	1 getfield (0, 0)
	2 org/apache/commons/math3/ml/clustering/DBSCANClusterer.eps:D (0, 0)
	4 dreturn (0, 0)

Method: getMinPts
	0 aload_0 (0, 0)
	1 getfield (0, 0)
	2 org/apache/commons/math3/ml/clustering/DBSCANClusterer.minPts:I (0, 0)
	4 ireturn (0, 0)

Method: cluster
	0 aload_1 (0, 0)
	1 invokestatic (0, 0)
	2 org/apache/commons/math3/util/MathUtils.checkNotNull:(Ljava/lang/Object;)V (0, 0)
	4 new (0, 0)
	5 java/util/ArrayList (0, 0)
	7 dup (0, 0)
	8 invokespecial (0, 0)
	9 java/util/ArrayList.<init>:()V (0, 0)
	11 astore_2 (0, 0)
	12 new (0, 0)
	13 java/util/HashMap (0, 0)
	15 dup (0, 0)
	16 invokespecial (0, 0)
	17 java/util/HashMap.<init>:()V (0, 0)
	19 astore_3 (0, 0)
	20 aload_1 (1, 4)
	21 invokeinterface (1, 4)
	22 java/util/Collection.java/util/Iterator (1, 4)
	24 0 (1, 4)
	26 astore (1, 4)
	27 #4 (1, 4)
	28 aload (1, 4)
	29 #4 (1, 4)
	30 invokeinterface (1, 4)
	31 java/util/Iterator.next:()Ljava/lang/Object; (1, 4)
	33 0 (1, 4)
	35 ifeq (1, 4)
	36 98 (1, 4)
	38 aload (1, 4)
	39 #4 (1, 4)
	40 invokeinterface (1, 4)
	41 java/util/Iterator.org/apache/commons/math3/ml/clustering/Clusterable (1, 4)
	43 0 (1, 4)
	45 checkcast (1, 4)
	46 org/apache/commons/math3/ml/clustering/Clusterable (1, 4)
	48 astore (1, 4)
	49 #5 (1, 4)
	50 aload_3 (2, 1)
	51 aload (2, 1)
	52 #5 (2, 1)
	53 invokeinterface (2, 1)
	54 java/util/Map.getNeighbors:(Lorg/apache/commons/math3/ml/clustering/Clusterable;Ljava/util/Collection;)Ljava/util/List; (2, 1)
	56 0 (2, 1)
	58 ifnull (2, 1)
	59 6 (2, 1)
	61 goto (2, 1)
	62 -33 (2, 1)
	64 aload_0 (1, 4)
	65 aload (1, 4)
	66 #5 (1, 4)
	67 aload_1 (1, 4)
	68 invokespecial (1, 4)
	69 org/apache/commons/math3/ml/clustering/DBSCANClusterer.getNeighbors:(Lorg/apache/commons/math3/ml/clustering/Clusterable;Ljava/util/Collection;)Ljava/util/List; (1, 4)
	71 astore (1, 4)
	72 #6 (1, 4)
	73 aload (2, 1)
	74 #6 (2, 1)
	75 invokeinterface (2, 1)
	76 java/util/List.org/apache/commons/math3/ml/clustering/Cluster (2, 1)
	78 0 (2, 1)
	80 aload_0 (2, 1)
	81 getfield (2, 1)
	82 org/apache/commons/math3/ml/clustering/DBSCANClusterer.minPts:I (2, 1)
	84 if_icmplt (2, 1)
	85 34 (2, 1)
	87 new (2, 1)
	88 org/apache/commons/math3/ml/clustering/Cluster (2, 1)
	90 dup (2, 1)
	91 invokespecial (2, 1)
	92 org/apache/commons/math3/ml/clustering/Cluster.<init>:()V (2, 1)
	94 astore (2, 1)
	95 #7 (2, 1)
	96 aload_2 (2, 1)
	97 aload_0 (2, 1)
	98 aload (2, 1)
	99 #7 (2, 1)
	100 aload (2, 1)
	101 #5 (2, 1)
	102 aload (2, 1)
	103 #6 (2, 1)
	104 aload_1 (2, 1)
	105 aload_3 (2, 1)
	106 invokespecial (2, 1)
	107 org/apache/commons/math3/ml/clustering/DBSCANClusterer.expandCluster:(Lorg/apache/commons/math3/ml/clustering/Cluster;Lorg/apache/commons/math3/ml/clustering/Clusterable;Ljava/util/List;Ljava/util/Collection;Ljava/util/Map;)Lorg/apache/commons/math3/ml/clustering/Cluster; (2, 1)
	109 invokeinterface (2, 1)
	110 java/util/List.NOISE:Lorg/apache/commons/math3/ml/clustering/DBSCANClusterer$PointStatus; (2, 1)
	112 0 (2, 1)
	114 pop (2, 1)
	115 goto (2, 2)
	116 15 (2, 2)
	118 aload_3 (2, 2)
	119 aload (2, 2)
	120 #5 (2, 2)
	121 getstatic (2, 2)
	122 org/apache/commons/math3/ml/clustering/DBSCANClusterer$PointStatus.NOISE:Lorg/apache/commons/math3/ml/clustering/DBSCANClusterer$PointStatus; (2, 2)
	124 invokeinterface (2, 2)
	125 java/util/Map.addPoint:(Lorg/apache/commons/math3/ml/clustering/Clusterable;)V (2, 2)
	127 0 (2, 2)
	129 pop (2, 2)
	130 goto (0, 0)
	131 -102 (0, 0)
	133 aload_2 (0, 0)
	134 areturn (0, 0)

Method: expandCluster
	0 aload_1 (0, 0)
	1 aload_2 (0, 0)
	2 invokevirtual (0, 0)
	3 org/apache/commons/math3/ml/clustering/Cluster.addPoint:(Lorg/apache/commons/math3/ml/clustering/Clusterable;)V (0, 0)
	5 aload (0, 0)
	6 #5 (0, 0)
	7 aload_2 (0, 0)
	8 getstatic (0, 0)
	9 org/apache/commons/math3/ml/clustering/DBSCANClusterer$PointStatus.PART_OF_CLUSTER:Lorg/apache/commons/math3/ml/clustering/DBSCANClusterer$PointStatus; (0, 0)
	11 invokeinterface (0, 0)
	12 java/util/Map.addPoint:(Lorg/apache/commons/math3/ml/clustering/Clusterable;)V (0, 0)
	14 0 (0, 0)
	16 pop (0, 0)
	17 new (0, 0)
	18 java/util/ArrayList (0, 0)
	20 dup (0, 0)
	21 aload_3 (0, 0)
	22 invokespecial (0, 0)
	23 java/util/ArrayList.<init>:(Ljava/util/Collection;)V (0, 0)
	25 astore (0, 0)
	26 #6 (0, 0)
	27 iconst_0 (0, 0)
	28 istore (0, 0)
	29 #7 (0, 0)
	30 iload (1, 3)
	31 #7 (1, 3)
	32 aload (1, 3)
	33 #6 (1, 3)
	34 invokeinterface (1, 3)
	35 java/util/List.org/apache/commons/math3/ml/clustering/Cluster (1, 3)
	37 0 (1, 3)
	39 if_icmpge (1, 3)
	40 103 (1, 3)
	42 aload (1, 3)
	43 #6 (1, 3)
	44 iload (1, 3)
	45 #7 (1, 3)
	46 invokeinterface (1, 3)
	47 java/util/List.org/apache/commons/math3/ml/clustering/DBSCANClusterer$PointStatus (1, 3)
	49 0 (1, 3)
	51 checkcast (1, 3)
	52 org/apache/commons/math3/ml/clustering/Clusterable (1, 3)
	54 astore (1, 3)
	55 #8 (1, 3)
	56 aload (1, 3)
	57 #5 (1, 3)
	58 aload (1, 3)
	59 #8 (1, 3)
	60 invokeinterface (1, 3)
	61 java/util/Map.getNeighbors:(Lorg/apache/commons/math3/ml/clustering/Clusterable;Ljava/util/Collection;)Ljava/util/List; (1, 3)
	63 0 (1, 3)
	65 checkcast (1, 3)
	66 org/apache/commons/math3/ml/clustering/DBSCANClusterer$PointStatus (1, 3)
	68 astore (1, 3)
	69 #9 (1, 3)
	70 aload (2, 1)
	71 #9 (2, 1)
	72 ifnonnull (2, 1)
	73 37 (2, 1)
	75 aload_0 (2, 1)
	76 aload (2, 1)
	77 #8 (2, 1)
	78 aload (2, 1)
	79 #4 (2, 1)
	80 invokespecial (2, 1)
	81 org/apache/commons/math3/ml/clustering/DBSCANClusterer.getNeighbors:(Lorg/apache/commons/math3/ml/clustering/Clusterable;Ljava/util/Collection;)Ljava/util/List; (2, 1)
	83 astore (2, 1)
	84 #10 (2, 1)
	85 aload (3, 1)
	86 #10 (3, 1)
	87 invokeinterface (3, 1)
	88 java/util/List.org/apache/commons/math3/ml/clustering/Cluster (3, 1)
	90 0 (3, 1)
	92 aload_0 (3, 1)
	93 getfield (3, 1)
	94 org/apache/commons/math3/ml/clustering/DBSCANClusterer.minPts:I (3, 1)
	96 if_icmplt (3, 1)
	97 13 (3, 1)
	99 aload_0 (3, 1)
	100 aload (3, 1)
	101 #6 (3, 1)
	102 aload (3, 1)
	103 #10 (3, 1)
	104 invokespecial (3, 1)
	105 org/apache/commons/math3/ml/clustering/DBSCANClusterer.merge:(Ljava/util/List;Ljava/util/List;)Ljava/util/List; (3, 1)
	107 astore (3, 1)
	108 #6 (3, 1)
	109 aload (2, 1)
	110 #9 (2, 1)
	111 getstatic (2, 1)
	112 org/apache/commons/math3/ml/clustering/DBSCANClusterer$PointStatus.PART_OF_CLUSTER:Lorg/apache/commons/math3/ml/clustering/DBSCANClusterer$PointStatus; (2, 1)
	114 if_acmpeq (2, 1)
	115 22 (2, 1)
	117 aload (2, 1)
	118 #5 (2, 1)
	119 aload (2, 1)
	120 #8 (2, 1)
	121 getstatic (2, 1)
	122 org/apache/commons/math3/ml/clustering/DBSCANClusterer$PointStatus.PART_OF_CLUSTER:Lorg/apache/commons/math3/ml/clustering/DBSCANClusterer$PointStatus; (2, 1)
	124 invokeinterface (2, 1)
	125 java/util/Map.addPoint:(Lorg/apache/commons/math3/ml/clustering/Clusterable;)V (2, 1)
	127 0 (2, 1)
	129 pop (2, 1)
	130 aload_1 (2, 1)
	131 aload (2, 1)
	132 #8 (2, 1)
	133 invokevirtual (2, 1)
	134 org/apache/commons/math3/ml/clustering/Cluster.addPoint:(Lorg/apache/commons/math3/ml/clustering/Clusterable;)V (2, 1)
	136 iinc (1, 3)
	137 #7 (1, 3)
	138 -89 (1, 3)
	139 goto (0, 0)
	140 -109 (0, 0)
	142 aload_1 (0, 0)
	143 areturn (0, 0)

Method: getNeighbors
	0 new (0, 0)
	1 java/util/ArrayList (0, 0)
	3 dup (0, 0)
	4 invokespecial (0, 0)
	5 java/util/ArrayList.<init>:()V (0, 0)
	7 astore_3 (0, 0)
	8 aload_2 (1, 4)
	9 invokeinterface (1, 4)
	10 java/util/Collection.java/util/Iterator (1, 4)
	12 0 (1, 4)
	14 astore (1, 4)
	15 #4 (1, 4)
	16 aload (1, 4)
	17 #4 (1, 4)
	18 invokeinterface (1, 4)
	19 java/util/Iterator.next:()Ljava/lang/Object; (1, 4)
	21 0 (1, 4)
	23 ifeq (1, 4)
	24 48 (1, 4)
	26 aload (1, 4)
	27 #4 (1, 4)
	28 invokeinterface (1, 4)
	29 java/util/Iterator.org/apache/commons/math3/ml/clustering/Clusterable (1, 4)
	31 0 (1, 4)
	33 checkcast (1, 4)
	34 org/apache/commons/math3/ml/clustering/Clusterable (1, 4)
	36 astore (1, 4)
	37 #5 (1, 4)
	38 aload_1 (2, 1)
	39 aload (2, 1)
	40 #5 (2, 1)
	41 if_acmpeq (2, 1)
	42 27 (2, 1)
	44 aload_0 (2, 1)
	45 aload (2, 1)
	46 #5 (2, 1)
	47 aload_1 (2, 1)
	48 invokevirtual (2, 1)
	49 org/apache/commons/math3/ml/clustering/DBSCANClusterer.distance:(Lorg/apache/commons/math3/ml/clustering/Clusterable;Lorg/apache/commons/math3/ml/clustering/Clusterable;)D (2, 1)
	51 aload_0 (2, 1)
	52 getfield (2, 1)
	53 org/apache/commons/math3/ml/clustering/DBSCANClusterer.eps:D (2, 1)
	55 dcmpg (2, 1)
	56 ifgt (2, 1)
	57 12 (2, 1)
	59 aload_3 (2, 1)
	60 aload (2, 1)
	61 #5 (2, 1)
	62 invokeinterface (2, 1)
	63 java/util/List.NOISE:Lorg/apache/commons/math3/ml/clustering/DBSCANClusterer$PointStatus; (2, 1)
	65 0 (2, 1)
	67 pop (2, 1)
	68 goto (0, 0)
	69 -52 (0, 0)
	71 aload_3 (0, 0)
	72 areturn (0, 0)

Method: merge
	0 new (0, 0)
	1 java/util/HashSet (0, 0)
	3 dup (0, 0)
	4 aload_1 (0, 0)
	5 invokespecial (0, 0)
	6 java/util/HashSet.<init>:(Ljava/util/Collection;)V (0, 0)
	8 astore_3 (0, 0)
	9 aload_2 (1, 4)
	10 invokeinterface (1, 4)
	11 java/util/List.java/util/Iterator (1, 4)
	13 0 (1, 4)
	15 astore (1, 4)
	16 #4 (1, 4)
	17 aload (1, 4)
	18 #4 (1, 4)
	19 invokeinterface (1, 4)
	20 java/util/Iterator.next:()Ljava/lang/Object; (1, 4)
	22 0 (1, 4)
	24 ifeq (1, 4)
	25 38 (1, 4)
	27 aload (1, 4)
	28 #4 (1, 4)
	29 invokeinterface (1, 4)
	30 java/util/Iterator.org/apache/commons/math3/ml/clustering/Clusterable (1, 4)
	32 0 (1, 4)
	34 checkcast (1, 4)
	35 org/apache/commons/math3/ml/clustering/Clusterable (1, 4)
	37 astore (1, 4)
	38 #5 (1, 4)
	39 aload_3 (2, 1)
	40 aload (2, 1)
	41 #5 (2, 1)
	42 invokeinterface (2, 1)
	43 java/util/Set.org/apache/commons/math3/ml/clustering/DBSCANClusterer (2, 1)
	45 0 (2, 1)
	47 ifne (2, 1)
	48 12 (2, 1)
	50 aload_1 (2, 1)
	51 aload (2, 1)
	52 #5 (2, 1)
	53 invokeinterface (2, 1)
	54 java/util/List.NOISE:Lorg/apache/commons/math3/ml/clustering/DBSCANClusterer$PointStatus; (2, 1)
	56 0 (2, 1)
	58 pop (2, 1)
	59 goto (0, 0)
	60 -42 (0, 0)
	62 aload_1 (0, 0)
	63 areturn (0, 0)

