Method: <init>
	0 aload_0 (0, 0)
	1 invokespecial (0, 0)
	2 java/lang/Object.<init>:()V (0, 0)
	4 aload_0 (0, 0)
	5 aload_1 (0, 0)
	6 arraylength (0, 0)
	7 newarray (0, 0)
	8 7 (0, 0)
	9 putfield (0, 0)
	10 org/apache/commons/math3/ml/clustering/DoublePoint.point:[D (0, 0)
	12 iconst_0 (2, 4)
	13 istore_2 (2, 4)
	14 iload_2 (2, 4)
	15 aload_1 (2, 4)
	16 arraylength (2, 4)
	17 if_icmpge (2, 4)
	18 19 (2, 4)
	20 aload_0 (2, 4)
	21 getfield (2, 4)
	22 org/apache/commons/math3/ml/clustering/DoublePoint.point:[D (2, 4)
	24 iload_2 (2, 4)
	25 aload_1 (2, 4)
	26 iload_2 (2, 4)
	27 iaload (2, 4)
	28 i2d (2, 4)
	29 dastore (2, 4)
	30 iinc (2, 4)
	31 #2 (2, 4)
	32 -89 (2, 4)
	33 goto (2, 4)
	34 -19 (2, 4)
	36 return (0, 0)

Method: getPoint
	0 aload_0 (0, 0)
	1 getfield (0, 0)
	2 org/apache/commons/math3/ml/clustering/DoublePoint.point:[D (0, 0)
	4 areturn (0, 0)

Method: equals
	0 aload_1 (1, 1)
	1 instanceof (1, 1)
	2 org/apache/commons/math3/ml/clustering/DoublePoint (1, 1)
	4 ifne (1, 1)
	5 5 (1, 1)
	7 iconst_0 (1, 1)
	8 ireturn (1, 1)
	9 aload_0 (0, 0)
	10 getfield (0, 0)
	11 org/apache/commons/math3/ml/clustering/DoublePoint.point:[D (0, 0)
	13 aload_1 (0, 0)
	14 checkcast (0, 0)
	15 org/apache/commons/math3/ml/clustering/DoublePoint (0, 0)
	17 getfield (0, 0)
	18 org/apache/commons/math3/ml/clustering/DoublePoint.point:[D (0, 0)
	20 invokestatic (0, 0)
	21 java/util/Arrays.equals:([D[D)Z (0, 0)
	23 ireturn (0, 0)

Method: hashCode
	0 aload_0 (0, 0)
	1 getfield (0, 0)
	2 org/apache/commons/math3/ml/clustering/DoublePoint.point:[D (0, 0)
	4 invokestatic (0, 0)
	5 java/util/Arrays.hashCode:([D)I (0, 0)
	7 ireturn (0, 0)

Method: toString
	0 aload_0 (0, 0)
	1 getfield (0, 0)
	2 org/apache/commons/math3/ml/clustering/DoublePoint.point:[D (0, 0)
	4 invokestatic (0, 0)
	5 java/util/Arrays.toString:([D)Ljava/lang/String; (0, 0)
	7 areturn (0, 0)

