Method: <init>
	0 aload_0 (0, 0)
	1 aload_3 (0, 0)
	2 invokespecial (0, 0)
	3 org/apache/commons/math3/ml/clustering/Clusterer.<init>:(Lorg/apache/commons/math3/ml/distance/DistanceMeasure;)V (0, 0)
	5 aload_0 (0, 0)
	6 iload_1 (0, 0)
	7 putfield (0, 0)
	8 org/apache/commons/math3/ml/clustering/KMeansPlusPlusClusterer.k:I (0, 0)
	10 aload_0 (0, 0)
	11 iload_2 (0, 0)
	12 putfield (0, 0)
	13 org/apache/commons/math3/ml/clustering/KMeansPlusPlusClusterer.maxIterations:I (0, 0)
	15 aload_0 (0, 0)
	16 aload (0, 0)
	17 #4 (0, 0)
	18 putfield (0, 0)
	19 org/apache/commons/math3/ml/clustering/KMeansPlusPlusClusterer.random:Lorg/apache/commons/math3/random/RandomGenerator; (0, 0)
	21 aload_0 (0, 0)
	22 aload (0, 0)
	23 #5 (0, 0)
	24 putfield (0, 0)
	25 org/apache/commons/math3/ml/clustering/KMeansPlusPlusClusterer.emptyStrategy:Lorg/apache/commons/math3/ml/clustering/KMeansPlusPlusClusterer$EmptyClusterStrategy; (0, 0)
	27 return (0, 0)

Method: getK
	0 aload_0 (0, 0)
	1 getfield (0, 0)
	2 org/apache/commons/math3/ml/clustering/KMeansPlusPlusClusterer.k:I (0, 0)
	4 ireturn (0, 0)

Method: getMaxIterations
	0 aload_0 (0, 0)
	1 getfield (0, 0)
	2 org/apache/commons/math3/ml/clustering/KMeansPlusPlusClusterer.maxIterations:I (0, 0)
	4 ireturn (0, 0)

Method: getRandomGenerator
	0 aload_0 (0, 0)
	1 getfield (0, 0)
	2 org/apache/commons/math3/ml/clustering/KMeansPlusPlusClusterer.random:Lorg/apache/commons/math3/random/RandomGenerator; (0, 0)
	4 areturn (0, 0)

Method: getEmptyClusterStrategy
	0 aload_0 (0, 0)
	1 getfield (0, 0)
	2 org/apache/commons/math3/ml/clustering/KMeansPlusPlusClusterer.emptyStrategy:Lorg/apache/commons/math3/ml/clustering/KMeansPlusPlusClusterer$EmptyClusterStrategy; (0, 0)
	4 areturn (0, 0)

Method: cluster
	0 aload_1 (0, 0)
	1 invokestatic (0, 0)
	2 org/apache/commons/math3/util/MathUtils.checkNotNull:(Ljava/lang/Object;)V (0, 0)
	4 aload_1 (1, 1)
	5 invokeinterface (1, 1)
	6 java/util/Collection.org/apache/commons/math3/exception/NumberIsTooSmallException (1, 1)
	8 0 (1, 1)
	10 aload_0 (1, 1)
	11 getfield (1, 1)
	12 org/apache/commons/math3/ml/clustering/KMeansPlusPlusClusterer.k:I (1, 1)
	14 if_icmpge (1, 1)
	15 28 (1, 1)
	17 new (1, 1)
	18 org/apache/commons/math3/exception/NumberIsTooSmallException (1, 1)
	20 dup (1, 1)
	21 aload_1 (1, 1)
	22 invokeinterface (1, 1)
	23 java/util/Collection.org/apache/commons/math3/exception/NumberIsTooSmallException (1, 1)
	25 0 (1, 1)
	27 invokestatic (1, 1)
	28 java/lang/Integer.valueOf:(I)Ljava/lang/Integer; (1, 1)
	30 aload_0 (1, 1)
	31 getfield (1, 1)
	32 org/apache/commons/math3/ml/clustering/KMeansPlusPlusClusterer.k:I (1, 1)
	34 invokestatic (1, 1)
	35 java/lang/Integer.valueOf:(I)Ljava/lang/Integer; (1, 1)
	37 iconst_0 (1, 1)
	38 invokespecial (1, 1)
	39 org/apache/commons/math3/exception/NumberIsTooSmallException.<init>:(Ljava/lang/Number;Ljava/lang/Number;Z)V (1, 1)
	41 athrow (1, 1)
	42 aload_0 (0, 0)
	43 aload_1 (0, 0)
	44 invokespecial (0, 0)
	45 org/apache/commons/math3/ml/clustering/KMeansPlusPlusClusterer.chooseInitialCenters:(Ljava/util/Collection;)Ljava/util/List; (0, 0)
	47 astore_2 (0, 0)
	48 aload_1 (0, 0)
	49 invokeinterface (0, 0)
	50 java/util/Collection.org/apache/commons/math3/exception/NumberIsTooSmallException (0, 0)
	52 0 (0, 0)
	54 newarray (0, 0)
	55 10 (0, 0)
	56 astore_3 (0, 0)
	57 aload_0 (0, 0)
	58 aload_2 (0, 0)
	59 aload_1 (0, 0)
	60 aload_3 (0, 0)
	61 invokespecial (0, 0)
	62 org/apache/commons/math3/ml/clustering/KMeansPlusPlusClusterer.assignPointsToClusters:(Ljava/util/List;Ljava/util/Collection;[I)I (0, 0)
	64 pop (0, 0)
	65 aload_0 (0, 0)
	66 getfield (0, 0)
	67 org/apache/commons/math3/ml/clustering/KMeansPlusPlusClusterer.maxIterations:I (0, 0)
	69 ifge (0, 0)
	70 8 (0, 0)
	72 ldc (0, 0)
	73 2147483647 (0, 0)
	74 goto (0, 0)
	75 7 (0, 0)
	77 aload_0 (0, 0)
	78 getfield (0, 0)
	79 org/apache/commons/math3/ml/clustering/KMeansPlusPlusClusterer.maxIterations:I (0, 0)
	81 istore (0, 0)
	82 #4 (0, 0)
	83 iconst_0 (1, 4)
	84 istore (1, 4)
	85 #5 (1, 4)
	86 iload (1, 4)
	87 #5 (1, 4)
	88 iload (1, 4)
	89 #4 (1, 4)
	90 if_icmpge (1, 4)
	91 218 (1, 4)
	93 iconst_0 (1, 4)
	94 istore (1, 4)
	95 #6 (1, 4)
	96 new (1, 4)
	97 java/util/ArrayList (1, 4)
	99 dup (1, 4)
	100 invokespecial (1, 4)
	101 java/util/ArrayList.<init>:()V (1, 4)
	103 astore (1, 4)
	104 #7 (1, 4)
	105 aload_2 (2, 4)
	106 invokeinterface (2, 4)
	107 java/util/List.java/util/Iterator (2, 4)
	109 0 (2, 4)
	111 astore (2, 4)
	112 #8 (2, 4)
	113 aload (2, 4)
	114 #8 (2, 4)
	115 invokeinterface (2, 4)
	116 java/util/Iterator.next:()Ljava/lang/Object; (2, 4)
	118 0 (2, 4)
	120 ifeq (2, 4)
	121 157 (2, 4)
	123 aload (2, 4)
	124 #8 (2, 4)
	125 invokeinterface (2, 4)
	126 java/util/Iterator.org/apache/commons/math3/ml/clustering/CentroidCluster (2, 4)
	128 0 (2, 4)
	130 checkcast (2, 4)
	131 org/apache/commons/math3/ml/clustering/CentroidCluster (2, 4)
	133 astore (2, 4)
	134 #9 (2, 4)
	135 aload (3, 1)
	136 #9 (3, 1)
	137 invokevirtual (3, 1)
	138 org/apache/commons/math3/ml/clustering/CentroidCluster.getPoints:()Ljava/util/List; (3, 1)
	140 invokeinterface (3, 1)
	141 java/util/List.$SwitchMap$org$apache$commons$math3$ml$clustering$KMeansPlusPlusClusterer$EmptyClusterStrategy:[I (3, 1)
	143 0 (3, 1)
	145 ifeq (3, 1)
	146 90 (3, 1)
	148 getstatic (4, 5)
	149 org/apache/commons/math3/ml/clustering/KMeansPlusPlusClusterer$1.$SwitchMap$org$apache$commons$math3$ml$clustering$KMeansPlusPlusClusterer$EmptyClusterStrategy:[I (4, 5)
	151 aload_0 (4, 5)
	152 getfield (4, 5)
	153 org/apache/commons/math3/ml/clustering/KMeansPlusPlusClusterer.emptyStrategy:Lorg/apache/commons/math3/ml/clustering/KMeansPlusPlusClusterer$EmptyClusterStrategy; (4, 5)
	155 invokevirtual (4, 5)
	156 org/apache/commons/math3/ml/clustering/KMeansPlusPlusClusterer$EmptyClusterStrategy.ordinal:()I (4, 5)
	158 iaload (4, 5)
	159 tableswitch (4, 5)
	160 1 184 (4, 5)
	164 2 194 (4, 5)
	168 3 204 (4, 5)
	184 aload_0 (4, 5)
	185 aload_2 (4, 5)
	186 invokespecial (4, 5)
	187 org/apache/commons/math3/ml/clustering/KMeansPlusPlusClusterer.getPointFromLargestVarianceCluster:(Ljava/util/Collection;)Lorg/apache/commons/math3/ml/clustering/Clusterable; (4, 5)
	189 astore (4, 5)
	190 #10 (4, 5)
	191 goto (4, 5)
	192 38 (4, 5)
	194 aload_0 (4, 5)
	195 aload_2 (4, 5)
	196 invokespecial (4, 5)
	197 org/apache/commons/math3/ml/clustering/KMeansPlusPlusClusterer.getPointFromLargestNumberCluster:(Ljava/util/Collection;)Lorg/apache/commons/math3/ml/clustering/Clusterable; (4, 5)
	199 astore (4, 5)
	200 #10 (4, 5)
	201 goto (4, 5)
	202 28 (4, 5)
	204 aload_0 (4, 5)
	205 aload_2 (4, 5)
	206 invokespecial (4, 5)
	207 org/apache/commons/math3/ml/clustering/KMeansPlusPlusClusterer.getFarthestPoint:(Ljava/util/Collection;)Lorg/apache/commons/math3/ml/clustering/Clusterable; (4, 5)
	209 astore (4, 5)
	210 #10 (4, 5)
	211 goto (4, 5)
	212 18 (4, 5)
	214 new (4, 5)
	215 org/apache/commons/math3/exception/ConvergenceException (4, 5)
	217 dup (4, 5)
	218 getstatic (4, 5)
	219 org/apache/commons/math3/exception/util/LocalizedFormats.EMPTY_CLUSTER_IN_K_MEANS:Lorg/apache/commons/math3/exception/util/LocalizedFormats; (4, 5)
	221 iconst_0 (4, 5)
	222 anewarray (4, 5)
	223 java/lang/Object (4, 5)
	225 invokespecial (4, 5)
	226 org/apache/commons/math3/exception/ConvergenceException.<init>:(Lorg/apache/commons/math3/exception/util/Localizable;[Ljava/lang/Object;)V (4, 5)
	228 athrow (4, 5)
	229 iconst_1 (3, 1)
	230 istore (3, 1)
	231 #6 (3, 1)
	232 goto (3, 1)
	233 25 (3, 1)
	235 aload_0 (4, 2)
	236 aload (4, 2)
	237 #9 (4, 2)
	238 invokevirtual (4, 2)
	239 org/apache/commons/math3/ml/clustering/CentroidCluster.getPoints:()Ljava/util/List; (4, 2)
	241 aload (4, 2)
	242 #9 (4, 2)
	243 invokevirtual (4, 2)
	244 org/apache/commons/math3/ml/clustering/CentroidCluster.getCenter:()Lorg/apache/commons/math3/ml/clustering/Clusterable; (4, 2)
	246 invokeinterface (4, 2)
	247 org/apache/commons/math3/ml/clustering/Clusterable.centroidOf:(Ljava/util/Collection;I)Lorg/apache/commons/math3/ml/clustering/Clusterable; (4, 2)
	249 0 (4, 2)
	251 arraylength (4, 2)
	252 invokespecial (4, 2)
	253 org/apache/commons/math3/ml/clustering/KMeansPlusPlusClusterer.centroidOf:(Ljava/util/Collection;I)Lorg/apache/commons/math3/ml/clustering/Clusterable; (4, 2)
	255 astore (4, 2)
	256 #10 (4, 2)
	257 aload (2, 4)
	258 #7 (2, 4)
	259 new (2, 4)
	260 org/apache/commons/math3/ml/clustering/CentroidCluster (2, 4)
	262 dup (2, 4)
	263 aload (2, 4)
	264 #10 (2, 4)
	265 invokespecial (2, 4)
	266 org/apache/commons/math3/ml/clustering/CentroidCluster.<init>:(Lorg/apache/commons/math3/ml/clustering/Clusterable;)V (2, 4)
	268 invokeinterface (2, 4)
	269 java/util/List.org/apache/commons/math3/ml/clustering/Clusterable (2, 4)
	271 0 (2, 4)
	273 pop (2, 4)
	274 goto (1, 4)
	275 -161 (1, 4)
	277 aload_0 (1, 4)
	278 aload (1, 4)
	279 #7 (1, 4)
	280 aload_1 (1, 4)
	281 aload_3 (1, 4)
	282 invokespecial (1, 4)
	283 org/apache/commons/math3/ml/clustering/KMeansPlusPlusClusterer.assignPointsToClusters:(Ljava/util/List;Ljava/util/Collection;[I)I (1, 4)
	285 istore (1, 4)
	286 #8 (1, 4)
	287 aload (1, 4)
	288 #7 (1, 4)
	289 astore_2 (1, 4)
	290 iload (3, 1)
	291 #8 (3, 1)
	292 ifne (3, 1)
	293 10 (3, 1)
	295 iload (3, 1)
	296 #6 (3, 1)
	297 ifne (3, 1)
	298 5 (3, 1)
	300 aload_2 (3, 1)
	301 areturn (3, 1)
	302 iinc (3, 1)
	303 #5 (3, 1)
	304 -89 (3, 1)
	305 goto (3, 1)
	306 -219 (3, 1)
	308 aload_2 (2, 1)
	309 areturn (1, 1)

Method: assignPointsToClusters
	0 iconst_0 (1, 1)
	1 istore (1, 1)
	2 #4 (1, 1)
	3 iconst_0 (1, 1)
	4 istore (1, 1)
	5 #5 (1, 1)
	6 aload_2 (2, 4)
	7 invokeinterface (2, 4)
	8 java/util/Collection.java/util/Iterator (2, 4)
	10 0 (2, 4)
	12 astore (2, 4)
	13 #6 (2, 4)
	14 aload (2, 4)
	15 #6 (2, 4)
	16 invokeinterface (2, 4)
	17 java/util/Iterator.next:()Ljava/lang/Object; (2, 4)
	19 0 (2, 4)
	21 ifeq (2, 4)
	22 68 (2, 4)
	24 aload (2, 4)
	25 #6 (2, 4)
	26 invokeinterface (2, 4)
	27 java/util/Iterator.org/apache/commons/math3/ml/clustering/CentroidCluster (2, 4)
	29 0 (2, 4)
	31 checkcast (2, 4)
	32 org/apache/commons/math3/ml/clustering/Clusterable (2, 4)
	34 astore (2, 4)
	35 #7 (2, 4)
	36 aload_0 (2, 4)
	37 aload_1 (2, 4)
	38 aload (2, 4)
	39 #7 (2, 4)
	40 invokespecial (2, 4)
	41 org/apache/commons/math3/ml/clustering/KMeansPlusPlusClusterer.getNearestCluster:(Ljava/util/Collection;Lorg/apache/commons/math3/ml/clustering/Clusterable;)I (2, 4)
	43 istore (2, 4)
	44 #8 (2, 4)
	45 iload (3, 1)
	46 #8 (3, 1)
	47 aload_3 (3, 1)
	48 iload (3, 1)
	49 #5 (3, 1)
	50 iaload (3, 1)
	51 if_icmpeq (3, 1)
	52 6 (3, 1)
	54 iinc (4, 1)
	55 #4 (4, 1)
	56 43 (4, 1)
	57 aload_1 (2, 4)
	58 iload (2, 4)
	59 #8 (2, 4)
	60 invokeinterface (2, 4)
	61 java/util/List.addPoint:(Lorg/apache/commons/math3/ml/clustering/Clusterable;)V (2, 4)
	63 0 (2, 4)
	65 checkcast (2, 4)
	66 org/apache/commons/math3/ml/clustering/CentroidCluster (2, 4)
	68 astore (2, 4)
	69 #9 (2, 4)
	70 aload (2, 4)
	71 #9 (2, 4)
	72 aload (2, 4)
	73 #7 (2, 4)
	74 invokevirtual (2, 4)
	75 org/apache/commons/math3/ml/clustering/CentroidCluster.addPoint:(Lorg/apache/commons/math3/ml/clustering/Clusterable;)V (2, 4)
	77 aload_3 (2, 4)
	78 iload (2, 4)
	79 #5 (2, 4)
	80 iinc (2, 4)
	81 #5 (2, 4)
	82 21 (2, 4)
	83 iload (2, 4)
	84 #8 (2, 4)
	85 iastore (2, 4)
	86 goto (1, 1)
	87 -72 (1, 1)
	89 iload (2, 1)
	90 #4 (2, 1)
	91 ireturn (0, 1)

Method: chooseInitialCenters
	0 new (1, 1)
	1 java/util/ArrayList (1, 1)
	3 dup (1, 1)
	4 aload_1 (1, 1)
	5 invokespecial (1, 1)
	6 java/util/ArrayList.<init>:(Ljava/util/Collection;)V (1, 1)
	8 invokestatic (1, 1)
	9 java/util/Collections.unmodifiableList:(Ljava/util/List;)Ljava/util/List; (1, 1)
	11 astore_2 (1, 1)
	12 aload_2 (1, 1)
	13 invokeinterface (1, 1)
	14 java/util/List.org/apache/commons/math3/exception/NumberIsTooSmallException (1, 1)
	16 0 (1, 1)
	18 istore_3 (1, 1)
	19 iload_3 (1, 1)
	20 newarray (1, 1)
	21 4 (1, 1)
	22 astore (1, 1)
	23 #4 (1, 1)
	24 new (1, 1)
	25 java/util/ArrayList (1, 1)
	27 dup (1, 1)
	28 invokespecial (1, 1)
	29 java/util/ArrayList.<init>:()V (1, 1)
	31 astore (1, 1)
	32 #5 (1, 1)
	33 aload_0 (2, 1)
	34 getfield (2, 1)
	35 org/apache/commons/math3/ml/clustering/KMeansPlusPlusClusterer.random:Lorg/apache/commons/math3/random/RandomGenerator; (2, 1)
	37 iload_3 (2, 1)
	38 invokeinterface (2, 1)
	39 org/apache/commons/math3/random/RandomGenerator.distance:(Lorg/apache/commons/math3/ml/clustering/Clusterable;Lorg/apache/commons/math3/ml/clustering/Clusterable;)D (2, 1)
	41 0 (2, 1)
	43 istore (2, 1)
	44 #6 (2, 1)
	45 aload_2 (2, 1)
	46 iload (2, 1)
	47 #6 (2, 1)
	48 invokeinterface (2, 1)
	49 java/util/List.addPoint:(Lorg/apache/commons/math3/ml/clustering/Clusterable;)V (2, 1)
	51 0 (2, 1)
	53 checkcast (2, 1)
	54 org/apache/commons/math3/ml/clustering/Clusterable (2, 1)
	56 astore (2, 1)
	57 #7 (2, 1)
	58 aload (2, 1)
	59 #5 (2, 1)
	60 new (2, 1)
	61 org/apache/commons/math3/ml/clustering/CentroidCluster (2, 1)
	63 dup (2, 1)
	64 aload (2, 1)
	65 #7 (2, 1)
	66 invokespecial (2, 1)
	67 org/apache/commons/math3/ml/clustering/CentroidCluster.<init>:(Lorg/apache/commons/math3/ml/clustering/Clusterable;)V (2, 1)
	69 invokeinterface (2, 1)
	70 java/util/List.org/apache/commons/math3/ml/clustering/Clusterable (2, 1)
	72 0 (2, 1)
	74 pop (2, 1)
	75 aload (2, 1)
	76 #4 (2, 1)
	77 iload (2, 1)
	78 #6 (2, 1)
	79 iconst_1 (2, 1)
	80 bastore (2, 1)
	81 iload_3 (2, 1)
	82 newarray (2, 1)
	83 7 (2, 1)
	84 astore (2, 1)
	85 #8 (2, 1)
	86 iconst_0 (3, 4)
	87 istore (3, 4)
	88 #9 (3, 4)
	89 iload (3, 4)
	90 #9 (3, 4)
	91 iload_3 (3, 4)
	92 if_icmpge (3, 4)
	93 45 (3, 4)
	95 iload (4, 1)
	96 #9 (4, 1)
	97 iload (4, 1)
	98 #6 (4, 1)
	99 if_icmpeq (4, 1)
	100 32 (4, 1)
	102 aload_0 (4, 1)
	103 aload (4, 1)
	104 #7 (4, 1)
	105 aload_2 (4, 1)
	106 iload (4, 1)
	107 #9 (4, 1)
	108 invokeinterface (4, 1)
	109 java/util/List.addPoint:(Lorg/apache/commons/math3/ml/clustering/Clusterable;)V (4, 1)
	111 0 (4, 1)
	113 checkcast (4, 1)
	114 org/apache/commons/math3/ml/clustering/Clusterable (4, 1)
	116 invokevirtual (4, 1)
	117 org/apache/commons/math3/ml/clustering/KMeansPlusPlusClusterer.distance:(Lorg/apache/commons/math3/ml/clustering/Clusterable;Lorg/apache/commons/math3/ml/clustering/Clusterable;)D (4, 1)
	119 dstore (4, 1)
	120 #10 (4, 1)
	121 aload (4, 1)
	122 #8 (4, 1)
	123 iload (4, 1)
	124 #9 (4, 1)
	125 dload (4, 1)
	126 #10 (4, 1)
	127 dload (4, 1)
	128 #10 (4, 1)
	129 dmul (4, 1)
	130 dastore (4, 1)
	131 iinc (4, 1)
	132 #9 (4, 1)
	133 -89 (4, 1)
	134 goto (4, 1)
	135 -45 (4, 1)
	137 aload (4, 3)
	138 #5 (4, 3)
	139 invokeinterface (4, 3)
	140 java/util/List.org/apache/commons/math3/exception/NumberIsTooSmallException (4, 3)
	142 0 (4, 3)
	144 aload_0 (4, 3)
	145 getfield (4, 3)
	146 org/apache/commons/math3/ml/clustering/KMeansPlusPlusClusterer.k:I (4, 3)
	148 if_icmpge (4, 3)
	149 269 (4, 3)
	151 dconst_0 (5, 4)
	152 dstore (5, 4)
	153 #9 (5, 4)
	154 iconst_0 (6, 4)
	155 istore (6, 4)
	156 #11 (6, 4)
	157 iload (6, 4)
	158 #11 (6, 4)
	159 iload_3 (6, 4)
	160 if_icmpge (6, 4)
	161 27 (6, 4)
	163 aload (7, 1)
	164 #4 (7, 1)
	165 iload (7, 1)
	166 #11 (7, 1)
	167 baload (7, 1)
	168 ifne (7, 1)
	169 13 (7, 1)
	171 dload (7, 1)
	172 #9 (7, 1)
	173 aload (7, 1)
	174 #8 (7, 1)
	175 iload (7, 1)
	176 #11 (7, 1)
	177 daload (7, 1)
	178 dadd (7, 1)
	179 dstore (7, 1)
	180 #9 (7, 1)
	181 iinc (7, 1)
	182 #11 (7, 1)
	183 -89 (7, 1)
	184 goto (7, 1)
	185 -27 (7, 1)
	187 aload_0 (6, 4)
	188 getfield (6, 4)
	189 org/apache/commons/math3/ml/clustering/KMeansPlusPlusClusterer.random:Lorg/apache/commons/math3/random/RandomGenerator; (6, 4)
	191 invokeinterface (6, 4)
	192 org/apache/commons/math3/random/RandomGenerator.java/lang/Double (6, 4)
	194 0 (6, 4)
	196 dload (6, 4)
	197 #9 (6, 4)
	198 dmul (6, 4)
	199 dstore (6, 4)
	200 #11 (6, 4)
	201 iconst_m1 (6, 4)
	202 istore (6, 4)
	203 #13 (6, 4)
	204 dconst_0 (6, 4)
	205 dstore (6, 4)
	206 #14 (6, 4)
	207 iconst_0 (7, 4)
	208 istore (7, 4)
	209 #16 (7, 4)
	210 iload (7, 4)
	211 #16 (7, 4)
	212 iload_3 (7, 4)
	213 if_icmpge (7, 4)
	214 42 (7, 4)
	216 aload (8, 1)
	217 #4 (8, 1)
	218 iload (8, 1)
	219 #16 (8, 1)
	220 baload (8, 1)
	221 ifne (8, 1)
	222 28 (8, 1)
	224 dload (8, 1)
	225 #14 (8, 1)
	226 aload (8, 1)
	227 #8 (8, 1)
	228 iload (8, 1)
	229 #16 (8, 1)
	230 daload (8, 1)
	231 dadd (8, 1)
	232 dstore (8, 1)
	233 #14 (8, 1)
	234 dload (9, 1)
	235 #14 (9, 1)
	236 dload (9, 1)
	237 #11 (9, 1)
	238 dcmpl (9, 1)
	239 iflt (9, 1)
	240 10 (9, 1)
	242 iload (9, 1)
	243 #16 (9, 1)
	244 istore (9, 1)
	245 #13 (9, 1)
	246 goto (9, 1)
	247 9 (9, 1)
	249 iinc (9, 1)
	250 #16 (9, 1)
	251 -89 (9, 1)
	252 goto (9, 1)
	253 -42 (9, 1)
	255 iload (10, 1)
	256 #13 (10, 1)
	257 iconst_m1 (10, 1)
	258 if_icmpne (10, 1)
	259 34 (10, 1)
	261 iload_3 (11, 4)
	262 iconst_1 (11, 4)
	263 isub (11, 4)
	264 istore (11, 4)
	265 #16 (11, 4)
	266 iload (11, 4)
	267 #16 (11, 4)
	268 iflt (11, 4)
	269 24 (11, 4)
	271 aload (12, 1)
	272 #4 (12, 1)
	273 iload (12, 1)
	274 #16 (12, 1)
	275 baload (12, 1)
	276 ifne (12, 1)
	277 10 (12, 1)
	279 iload (12, 1)
	280 #16 (12, 1)
	281 istore (12, 1)
	282 #13 (12, 1)
	283 goto (12, 1)
	284 9 (12, 1)
	286 iinc (12, 1)
	287 #16 (12, 1)
	288 -89 (12, 1)
	289 goto (12, 1)
	290 -23 (12, 1)
	292 iload (11, 1)
	293 #13 (11, 1)
	294 iflt (11, 1)
	295 123 (11, 1)
	297 aload_2 (11, 1)
	298 iload (11, 1)
	299 #13 (11, 1)
	300 invokeinterface (11, 1)
	301 java/util/List.addPoint:(Lorg/apache/commons/math3/ml/clustering/Clusterable;)V (11, 1)
	303 0 (11, 1)
	305 checkcast (11, 1)
	306 org/apache/commons/math3/ml/clustering/Clusterable (11, 1)
	308 astore (11, 1)
	309 #16 (11, 1)
	310 aload (11, 1)
	311 #5 (11, 1)
	312 new (11, 1)
	313 org/apache/commons/math3/ml/clustering/CentroidCluster (11, 1)
	315 dup (11, 1)
	316 aload (11, 1)
	317 #16 (11, 1)
	318 invokespecial (11, 1)
	319 org/apache/commons/math3/ml/clustering/CentroidCluster.<init>:(Lorg/apache/commons/math3/ml/clustering/Clusterable;)V (11, 1)
	321 invokeinterface (11, 1)
	322 java/util/List.org/apache/commons/math3/ml/clustering/Clusterable (11, 1)
	324 0 (11, 1)
	326 pop (11, 1)
	327 aload (11, 1)
	328 #4 (11, 1)
	329 iload (11, 1)
	330 #13 (11, 1)
	331 iconst_1 (11, 1)
	332 bastore (11, 1)
	333 aload (12, 1)
	334 #5 (12, 1)
	335 invokeinterface (12, 1)
	336 java/util/List.org/apache/commons/math3/exception/NumberIsTooSmallException (12, 1)
	338 0 (12, 1)
	340 aload_0 (12, 1)
	341 getfield (12, 1)
	342 org/apache/commons/math3/ml/clustering/KMeansPlusPlusClusterer.k:I (12, 1)
	344 if_icmpge (12, 1)
	345 70 (12, 1)
	347 iconst_0 (13, 4)
	348 istore (13, 4)
	349 #17 (13, 4)
	350 iload (13, 4)
	351 #17 (13, 4)
	352 iload_3 (13, 4)
	353 if_icmpge (13, 4)
	354 61 (13, 4)
	356 aload (14, 1)
	357 #4 (14, 1)
	358 iload (14, 1)
	359 #17 (14, 1)
	360 baload (14, 1)
	361 ifne (14, 1)
	362 47 (14, 1)
	364 aload_0 (14, 1)
	365 aload (14, 1)
	366 #16 (14, 1)
	367 aload_2 (14, 1)
	368 iload (14, 1)
	369 #17 (14, 1)
	370 invokeinterface (14, 1)
	371 java/util/List.addPoint:(Lorg/apache/commons/math3/ml/clustering/Clusterable;)V (14, 1)
	373 0 (14, 1)
	375 checkcast (14, 1)
	376 org/apache/commons/math3/ml/clustering/Clusterable (14, 1)
	378 invokevirtual (14, 1)
	379 org/apache/commons/math3/ml/clustering/KMeansPlusPlusClusterer.distance:(Lorg/apache/commons/math3/ml/clustering/Clusterable;Lorg/apache/commons/math3/ml/clustering/Clusterable;)D (14, 1)
	381 dstore (14, 1)
	382 #18 (14, 1)
	383 dload (14, 1)
	384 #18 (14, 1)
	385 dload (14, 1)
	386 #18 (14, 1)
	387 dmul (14, 1)
	388 dstore (14, 1)
	389 #20 (14, 1)
	390 dload (15, 1)
	391 #20 (15, 1)
	392 aload (15, 1)
	393 #8 (15, 1)
	394 iload (15, 1)
	395 #17 (15, 1)
	396 daload (15, 1)
	397 dcmpg (15, 1)
	398 ifge (15, 1)
	399 10 (15, 1)
	401 aload (15, 1)
	402 #8 (15, 1)
	403 iload (15, 1)
	404 #17 (15, 1)
	405 dload (15, 1)
	406 #20 (15, 1)
	407 dastore (15, 1)
	408 iinc (15, 1)
	409 #17 (15, 1)
	410 -89 (15, 1)
	411 goto (15, 1)
	412 -61 (15, 1)
	414 goto (11, 1)
	415 -277 (11, 1)
	417 aload (11, 1)
	418 #5 (11, 1)
	419 areturn (7, 1)

Method: getPointFromLargestVarianceCluster
	0 ldc2_w (0, 0)
	1 -inf (0, 0)
	3 dstore_2 (0, 0)
	4 aconst_null (0, 0)
	5 astore (0, 0)
	6 #4 (0, 0)
	7 aload_1 (1, 4)
	8 invokeinterface (1, 4)
	9 java/util/Collection.java/util/Iterator (1, 4)
	11 0 (1, 4)
	13 astore (1, 4)
	14 #5 (1, 4)
	15 aload (1, 4)
	16 #5 (1, 4)
	17 invokeinterface (1, 4)
	18 java/util/Iterator.next:()Ljava/lang/Object; (1, 4)
	20 0 (1, 4)
	22 ifeq (1, 4)
	23 118 (1, 4)
	25 aload (1, 4)
	26 #5 (1, 4)
	27 invokeinterface (1, 4)
	28 java/util/Iterator.org/apache/commons/math3/ml/clustering/CentroidCluster (1, 4)
	30 0 (1, 4)
	32 checkcast (1, 4)
	33 org/apache/commons/math3/ml/clustering/CentroidCluster (1, 4)
	35 astore (1, 4)
	36 #6 (1, 4)
	37 aload (2, 1)
	38 #6 (2, 1)
	39 invokevirtual (2, 1)
	40 org/apache/commons/math3/ml/clustering/CentroidCluster.getPoints:()Ljava/util/List; (2, 1)
	42 invokeinterface (2, 1)
	43 java/util/List.$SwitchMap$org$apache$commons$math3$ml$clustering$KMeansPlusPlusClusterer$EmptyClusterStrategy:[I (2, 1)
	45 0 (2, 1)
	47 ifne (2, 1)
	48 90 (2, 1)
	50 aload (2, 1)
	51 #6 (2, 1)
	52 invokevirtual (2, 1)
	53 org/apache/commons/math3/ml/clustering/CentroidCluster.getCenter:()Lorg/apache/commons/math3/ml/clustering/Clusterable; (2, 1)
	55 astore (2, 1)
	56 #7 (2, 1)
	57 new (2, 1)
	58 org/apache/commons/math3/stat/descriptive/moment/Variance (2, 1)
	60 dup (2, 1)
	61 invokespecial (2, 1)
	62 org/apache/commons/math3/stat/descriptive/moment/Variance.<init>:()V (2, 1)
	64 astore (2, 1)
	65 #8 (2, 1)
	66 aload (3, 4)
	67 #6 (3, 4)
	68 invokevirtual (3, 4)
	69 org/apache/commons/math3/ml/clustering/CentroidCluster.getPoints:()Ljava/util/List; (3, 4)
	71 invokeinterface (3, 4)
	72 java/util/List.java/util/Iterator (3, 4)
	74 0 (3, 4)
	76 astore (3, 4)
	77 #9 (3, 4)
	78 aload (3, 4)
	79 #9 (3, 4)
	80 invokeinterface (3, 4)
	81 java/util/Iterator.next:()Ljava/lang/Object; (3, 4)
	83 0 (3, 4)
	85 ifeq (3, 4)
	86 31 (3, 4)
	88 aload (3, 4)
	89 #9 (3, 4)
	90 invokeinterface (3, 4)
	91 java/util/Iterator.org/apache/commons/math3/ml/clustering/CentroidCluster (3, 4)
	93 0 (3, 4)
	95 checkcast (3, 4)
	96 org/apache/commons/math3/ml/clustering/Clusterable (3, 4)
	98 astore (3, 4)
	99 #10 (3, 4)
	100 aload (3, 4)
	101 #8 (3, 4)
	102 aload_0 (3, 4)
	103 aload (3, 4)
	104 #10 (3, 4)
	105 aload (3, 4)
	106 #7 (3, 4)
	107 invokevirtual (3, 4)
	108 org/apache/commons/math3/ml/clustering/KMeansPlusPlusClusterer.distance:(Lorg/apache/commons/math3/ml/clustering/Clusterable;Lorg/apache/commons/math3/ml/clustering/Clusterable;)D (3, 4)
	110 invokevirtual (3, 4)
	111 org/apache/commons/math3/stat/descriptive/moment/Variance.increment:(D)V (3, 4)
	113 goto (2, 1)
	114 -35 (2, 1)
	116 aload (2, 1)
	117 #8 (2, 1)
	118 invokevirtual (2, 1)
	119 org/apache/commons/math3/stat/descriptive/moment/Variance.getResult:()D (2, 1)
	121 dstore (2, 1)
	122 #9 (2, 1)
	123 dload (3, 1)
	124 #9 (3, 1)
	125 dload_2 (3, 1)
	126 dcmpl (3, 1)
	127 ifle (3, 1)
	128 10 (3, 1)
	130 dload (3, 1)
	131 #9 (3, 1)
	132 dstore_2 (3, 1)
	133 aload (3, 1)
	134 #6 (3, 1)
	135 astore (3, 1)
	136 #4 (3, 1)
	137 goto (0, 0)
	138 -122 (0, 0)
	140 aload (1, 1)
	141 #4 (1, 1)
	142 ifnonnull (1, 1)
	143 18 (1, 1)
	145 new (1, 1)
	146 org/apache/commons/math3/exception/ConvergenceException (1, 1)
	148 dup (1, 1)
	149 getstatic (1, 1)
	150 org/apache/commons/math3/exception/util/LocalizedFormats.EMPTY_CLUSTER_IN_K_MEANS:Lorg/apache/commons/math3/exception/util/LocalizedFormats; (1, 1)
	152 iconst_0 (1, 1)
	153 anewarray (1, 1)
	154 java/lang/Object (1, 1)
	156 invokespecial (1, 1)
	157 org/apache/commons/math3/exception/ConvergenceException.<init>:(Lorg/apache/commons/math3/exception/util/Localizable;[Ljava/lang/Object;)V (1, 1)
	159 athrow (1, 1)
	160 aload (0, 0)
	161 #4 (0, 0)
	162 invokevirtual (0, 0)
	163 org/apache/commons/math3/ml/clustering/Cluster.getPoints:()Ljava/util/List; (0, 0)
	165 astore (0, 0)
	166 #5 (0, 0)
	167 aload (0, 0)
	168 #5 (0, 0)
	169 aload_0 (0, 0)
	170 getfield (0, 0)
	171 org/apache/commons/math3/ml/clustering/KMeansPlusPlusClusterer.random:Lorg/apache/commons/math3/random/RandomGenerator; (0, 0)
	173 aload (0, 0)
	174 #5 (0, 0)
	175 invokeinterface (0, 0)
	176 java/util/List.org/apache/commons/math3/exception/NumberIsTooSmallException (0, 0)
	178 0 (0, 0)
	180 invokeinterface (0, 0)
	181 org/apache/commons/math3/random/RandomGenerator.distance:(Lorg/apache/commons/math3/ml/clustering/Clusterable;Lorg/apache/commons/math3/ml/clustering/Clusterable;)D (0, 0)
	183 0 (0, 0)
	185 invokeinterface (0, 0)
	186 java/util/List.org/apache/commons/math3/ml/clustering/Cluster (0, 0)
	188 0 (0, 0)
	190 checkcast (0, 0)
	191 org/apache/commons/math3/ml/clustering/Clusterable (0, 0)
	193 areturn (0, 0)

Method: getPointFromLargestNumberCluster
	0 iconst_0 (0, 0)
	1 istore_2 (0, 0)
	2 aconst_null (0, 0)
	3 astore_3 (0, 0)
	4 aload_1 (1, 4)
	5 invokeinterface (1, 4)
	6 java/util/Collection.java/util/Iterator (1, 4)
	8 0 (1, 4)
	10 astore (1, 4)
	11 #4 (1, 4)
	12 aload (1, 4)
	13 #4 (1, 4)
	14 invokeinterface (1, 4)
	15 java/util/Iterator.next:()Ljava/lang/Object; (1, 4)
	17 0 (1, 4)
	19 ifeq (1, 4)
	20 42 (1, 4)
	22 aload (1, 4)
	23 #4 (1, 4)
	24 invokeinterface (1, 4)
	25 java/util/Iterator.org/apache/commons/math3/ml/clustering/CentroidCluster (1, 4)
	27 0 (1, 4)
	29 checkcast (1, 4)
	30 org/apache/commons/math3/ml/clustering/Cluster (1, 4)
	32 astore (1, 4)
	33 #5 (1, 4)
	34 aload (1, 4)
	35 #5 (1, 4)
	36 invokevirtual (1, 4)
	37 org/apache/commons/math3/ml/clustering/Cluster.getPoints:()Ljava/util/List; (1, 4)
	39 invokeinterface (1, 4)
	40 java/util/List.org/apache/commons/math3/exception/NumberIsTooSmallException (1, 4)
	42 0 (1, 4)
	44 istore (1, 4)
	45 #6 (1, 4)
	46 iload (2, 1)
	47 #6 (2, 1)
	48 iload_2 (2, 1)
	49 if_icmple (2, 1)
	50 9 (2, 1)
	52 iload (2, 1)
	53 #6 (2, 1)
	54 istore_2 (2, 1)
	55 aload (2, 1)
	56 #5 (2, 1)
	57 astore_3 (2, 1)
	58 goto (0, 0)
	59 -46 (0, 0)
	61 aload_3 (1, 1)
	62 ifnonnull (1, 1)
	63 18 (1, 1)
	65 new (1, 1)
	66 org/apache/commons/math3/exception/ConvergenceException (1, 1)
	68 dup (1, 1)
	69 getstatic (1, 1)
	70 org/apache/commons/math3/exception/util/LocalizedFormats.EMPTY_CLUSTER_IN_K_MEANS:Lorg/apache/commons/math3/exception/util/LocalizedFormats; (1, 1)
	72 iconst_0 (1, 1)
	73 anewarray (1, 1)
	74 java/lang/Object (1, 1)
	76 invokespecial (1, 1)
	77 org/apache/commons/math3/exception/ConvergenceException.<init>:(Lorg/apache/commons/math3/exception/util/Localizable;[Ljava/lang/Object;)V (1, 1)
	79 athrow (1, 1)
	80 aload_3 (0, 0)
	81 invokevirtual (0, 0)
	82 org/apache/commons/math3/ml/clustering/Cluster.getPoints:()Ljava/util/List; (0, 0)
	84 astore (0, 0)
	85 #4 (0, 0)
	86 aload (0, 0)
	87 #4 (0, 0)
	88 aload_0 (0, 0)
	89 getfield (0, 0)
	90 org/apache/commons/math3/ml/clustering/KMeansPlusPlusClusterer.random:Lorg/apache/commons/math3/random/RandomGenerator; (0, 0)
	92 aload (0, 0)
	93 #4 (0, 0)
	94 invokeinterface (0, 0)
	95 java/util/List.org/apache/commons/math3/exception/NumberIsTooSmallException (0, 0)
	97 0 (0, 0)
	99 invokeinterface (0, 0)
	100 org/apache/commons/math3/random/RandomGenerator.distance:(Lorg/apache/commons/math3/ml/clustering/Clusterable;Lorg/apache/commons/math3/ml/clustering/Clusterable;)D (0, 0)
	102 0 (0, 0)
	104 invokeinterface (0, 0)
	105 java/util/List.org/apache/commons/math3/ml/clustering/Cluster (0, 0)
	107 0 (0, 0)
	109 checkcast (0, 0)
	110 org/apache/commons/math3/ml/clustering/Clusterable (0, 0)
	112 areturn (0, 0)

Method: getFarthestPoint
	0 ldc2_w (0, 0)
	1 -inf (0, 0)
	3 dstore_2 (0, 0)
	4 aconst_null (0, 0)
	5 astore (0, 0)
	6 #4 (0, 0)
	7 iconst_m1 (0, 0)
	8 istore (0, 0)
	9 #5 (0, 0)
	10 aload_1 (1, 4)
	11 invokeinterface (1, 4)
	12 java/util/Collection.java/util/Iterator (1, 4)
	14 0 (1, 4)
	16 astore (1, 4)
	17 #6 (1, 4)
	18 aload (1, 4)
	19 #6 (1, 4)
	20 invokeinterface (1, 4)
	21 java/util/Iterator.next:()Ljava/lang/Object; (1, 4)
	23 0 (1, 4)
	25 ifeq (1, 4)
	26 91 (1, 4)
	28 aload (1, 4)
	29 #6 (1, 4)
	30 invokeinterface (1, 4)
	31 java/util/Iterator.org/apache/commons/math3/ml/clustering/CentroidCluster (1, 4)
	33 0 (1, 4)
	35 checkcast (1, 4)
	36 org/apache/commons/math3/ml/clustering/CentroidCluster (1, 4)
	38 astore (1, 4)
	39 #7 (1, 4)
	40 aload (1, 4)
	41 #7 (1, 4)
	42 invokevirtual (1, 4)
	43 org/apache/commons/math3/ml/clustering/CentroidCluster.getCenter:()Lorg/apache/commons/math3/ml/clustering/Clusterable; (1, 4)
	45 astore (1, 4)
	46 #8 (1, 4)
	47 aload (1, 4)
	48 #7 (1, 4)
	49 invokevirtual (1, 4)
	50 org/apache/commons/math3/ml/clustering/CentroidCluster.getPoints:()Ljava/util/List; (1, 4)
	52 astore (1, 4)
	53 #9 (1, 4)
	54 iconst_0 (2, 4)
	55 istore (2, 4)
	56 #10 (2, 4)
	57 iload (2, 4)
	58 #10 (2, 4)
	59 aload (2, 4)
	60 #9 (2, 4)
	61 invokeinterface (2, 4)
	62 java/util/List.org/apache/commons/math3/exception/NumberIsTooSmallException (2, 4)
	64 0 (2, 4)
	66 if_icmpge (2, 4)
	67 47 (2, 4)
	69 aload_0 (2, 4)
	70 aload (2, 4)
	71 #9 (2, 4)
	72 iload (2, 4)
	73 #10 (2, 4)
	74 invokeinterface (2, 4)
	75 java/util/List.addPoint:(Lorg/apache/commons/math3/ml/clustering/Clusterable;)V (2, 4)
	77 0 (2, 4)
	79 checkcast (2, 4)
	80 org/apache/commons/math3/ml/clustering/Clusterable (2, 4)
	82 aload (2, 4)
	83 #8 (2, 4)
	84 invokevirtual (2, 4)
	85 org/apache/commons/math3/ml/clustering/KMeansPlusPlusClusterer.distance:(Lorg/apache/commons/math3/ml/clustering/Clusterable;Lorg/apache/commons/math3/ml/clustering/Clusterable;)D (2, 4)
	87 dstore (2, 4)
	88 #11 (2, 4)
	89 dload (3, 1)
	90 #11 (3, 1)
	91 dload_2 (3, 1)
	92 dcmpl (3, 1)
	93 ifle (3, 1)
	94 14 (3, 1)
	96 dload (3, 1)
	97 #11 (3, 1)
	98 dstore_2 (3, 1)
	99 aload (3, 1)
	100 #7 (3, 1)
	101 astore (3, 1)
	102 #4 (3, 1)
	103 iload (3, 1)
	104 #10 (3, 1)
	105 istore (3, 1)
	106 #5 (3, 1)
	107 iinc (3, 1)
	108 #10 (3, 1)
	109 -89 (3, 1)
	110 goto (3, 1)
	111 -53 (3, 1)
	113 goto (1, 4)
	114 -95 (1, 4)
	116 aload (2, 1)
	117 #4 (2, 1)
	118 ifnonnull (2, 1)
	119 18 (2, 1)
	121 new (2, 1)
	122 org/apache/commons/math3/exception/ConvergenceException (2, 1)
	124 dup (2, 1)
	125 getstatic (2, 1)
	126 org/apache/commons/math3/exception/util/LocalizedFormats.EMPTY_CLUSTER_IN_K_MEANS:Lorg/apache/commons/math3/exception/util/LocalizedFormats; (2, 1)
	128 iconst_0 (2, 1)
	129 anewarray (2, 1)
	130 java/lang/Object (2, 1)
	132 invokespecial (2, 1)
	133 org/apache/commons/math3/exception/ConvergenceException.<init>:(Lorg/apache/commons/math3/exception/util/Localizable;[Ljava/lang/Object;)V (2, 1)
	135 athrow (2, 1)
	136 aload (1, 4)
	137 #4 (1, 4)
	138 invokevirtual (1, 4)
	139 org/apache/commons/math3/ml/clustering/Cluster.getPoints:()Ljava/util/List; (1, 4)
	141 iload (1, 4)
	142 #5 (1, 4)
	143 invokeinterface (1, 4)
	144 java/util/List.org/apache/commons/math3/ml/clustering/Cluster (1, 4)
	146 0 (1, 4)
	148 checkcast (1, 4)
	149 org/apache/commons/math3/ml/clustering/Clusterable (1, 4)
	151 areturn (1, 4)

Method: getNearestCluster
	0 ldc2_w (0, 0)
	1 1.7976931348623157e+308 (0, 0)
	3 dstore_3 (0, 0)
	4 iconst_0 (0, 0)
	5 istore (0, 0)
	6 #5 (0, 0)
	7 iconst_0 (0, 0)
	8 istore (0, 0)
	9 #6 (0, 0)
	10 aload_1 (1, 4)
	11 invokeinterface (1, 4)
	12 java/util/Collection.java/util/Iterator (1, 4)
	14 0 (1, 4)
	16 astore (1, 4)
	17 #7 (1, 4)
	18 aload (1, 4)
	19 #7 (1, 4)
	20 invokeinterface (1, 4)
	21 java/util/Iterator.next:()Ljava/lang/Object; (1, 4)
	23 0 (1, 4)
	25 ifeq (1, 4)
	26 47 (1, 4)
	28 aload (1, 4)
	29 #7 (1, 4)
	30 invokeinterface (1, 4)
	31 java/util/Iterator.org/apache/commons/math3/ml/clustering/CentroidCluster (1, 4)
	33 0 (1, 4)
	35 checkcast (1, 4)
	36 org/apache/commons/math3/ml/clustering/CentroidCluster (1, 4)
	38 astore (1, 4)
	39 #8 (1, 4)
	40 aload_0 (1, 4)
	41 aload_2 (1, 4)
	42 aload (1, 4)
	43 #8 (1, 4)
	44 invokevirtual (1, 4)
	45 org/apache/commons/math3/ml/clustering/CentroidCluster.getCenter:()Lorg/apache/commons/math3/ml/clustering/Clusterable; (1, 4)
	47 invokevirtual (1, 4)
	48 org/apache/commons/math3/ml/clustering/KMeansPlusPlusClusterer.distance:(Lorg/apache/commons/math3/ml/clustering/Clusterable;Lorg/apache/commons/math3/ml/clustering/Clusterable;)D (1, 4)
	50 dstore (1, 4)
	51 #9 (1, 4)
	52 dload (2, 1)
	53 #9 (2, 1)
	54 dload_3 (2, 1)
	55 dcmpg (2, 1)
	56 ifge (2, 1)
	57 10 (2, 1)
	59 dload (2, 1)
	60 #9 (2, 1)
	61 dstore_3 (2, 1)
	62 iload (2, 1)
	63 #5 (2, 1)
	64 istore (2, 1)
	65 #6 (2, 1)
	66 iinc (1, 4)
	67 #5 (1, 4)
	68 -89 (1, 4)
	69 goto (0, 0)
	70 -51 (0, 0)
	72 iload (0, 0)
	73 #6 (0, 0)
	74 ireturn (0, 0)

Method: centroidOf
	0 iload_2 (0, 0)
	1 newarray (0, 0)
	2 7 (0, 0)
	3 astore_3 (0, 0)
	4 aload_1 (1, 4)
	5 invokeinterface (1, 4)
	6 java/util/Collection.java/util/Iterator (1, 4)
	8 0 (1, 4)
	10 astore (1, 4)
	11 #4 (1, 4)
	12 aload (1, 4)
	13 #4 (1, 4)
	14 invokeinterface (1, 4)
	15 java/util/Iterator.next:()Ljava/lang/Object; (1, 4)
	17 0 (1, 4)
	19 ifeq (1, 4)
	20 55 (1, 4)
	22 aload (1, 4)
	23 #4 (1, 4)
	24 invokeinterface (1, 4)
	25 java/util/Iterator.org/apache/commons/math3/ml/clustering/CentroidCluster (1, 4)
	27 0 (1, 4)
	29 checkcast (1, 4)
	30 org/apache/commons/math3/ml/clustering/Clusterable (1, 4)
	32 astore (1, 4)
	33 #5 (1, 4)
	34 aload (1, 4)
	35 #5 (1, 4)
	36 invokeinterface (1, 4)
	37 org/apache/commons/math3/ml/clustering/Clusterable.centroidOf:(Ljava/util/Collection;I)Lorg/apache/commons/math3/ml/clustering/Clusterable; (1, 4)
	39 0 (1, 4)
	41 astore (1, 4)
	42 #6 (1, 4)
	43 iconst_0 (2, 4)
	44 istore (2, 4)
	45 #7 (2, 4)
	46 iload (2, 4)
	47 #7 (2, 4)
	48 aload_3 (2, 4)
	49 arraylength (2, 4)
	50 if_icmpge (2, 4)
	51 21 (2, 4)
	53 aload_3 (2, 4)
	54 iload (2, 4)
	55 #7 (2, 4)
	56 dup2 (2, 4)
	57 daload (2, 4)
	58 aload (2, 4)
	59 #6 (2, 4)
	60 iload (2, 4)
	61 #7 (2, 4)
	62 daload (2, 4)
	63 dadd (2, 4)
	64 dastore (2, 4)
	65 iinc (2, 4)
	66 #7 (2, 4)
	67 -89 (2, 4)
	68 goto (2, 4)
	69 -22 (2, 4)
	71 goto (0, 0)
	72 -59 (0, 0)
	74 iconst_0 (1, 4)
	75 istore (1, 4)
	76 #4 (1, 4)
	77 iload (1, 4)
	78 #4 (1, 4)
	79 aload_3 (1, 4)
	80 arraylength (1, 4)
	81 if_icmpge (1, 4)
	82 23 (1, 4)
	84 aload_3 (1, 4)
	85 iload (1, 4)
	86 #4 (1, 4)
	87 dup2 (1, 4)
	88 daload (1, 4)
	89 aload_1 (1, 4)
	90 invokeinterface (1, 4)
	91 java/util/Collection.org/apache/commons/math3/exception/NumberIsTooSmallException (1, 4)
	93 0 (1, 4)
	95 i2d (1, 4)
	96 ddiv (1, 4)
	97 dastore (1, 4)
	98 iinc (1, 4)
	99 #4 (1, 4)
	100 -89 (1, 4)
	101 goto (1, 4)
	102 -24 (1, 4)
	104 new (0, 0)
	105 org/apache/commons/math3/ml/clustering/DoublePoint (0, 0)
	107 dup (0, 0)
	108 aload_3 (0, 0)
	109 invokespecial (0, 0)
	110 org/apache/commons/math3/ml/clustering/DoublePoint.<init>:([D)V (0, 0)
	112 areturn (0, 0)

