Method: <init>
	0 aload_0 (0, 0)
	1 aload_1 (0, 0)
	2 invokespecial (0, 0)
	5 return (0, 0)

Method: score
	0 dconst_0 (0, 0)
	1 dstore_2 (0, 0)
	2 aload_1 (1, 4)
	3 invokeinterface (1, 4)
	8 astore (1, 4)
	10 aload (1, 4)
	12 invokeinterface (1, 4)
	17 ifeq (1, 4)
	20 aload (1, 4)
	22 invokeinterface (1, 4)
	27 checkcast (1, 4)
	30 astore (1, 4)
	32 aload (2, 1)
	34 invokevirtual (2, 1)
	37 invokeinterface (2, 1)
	42 ifne (2, 1)
	45 aload_0 (2, 1)
	46 aload (2, 1)
	48 invokevirtual (2, 1)
	51 astore (2, 1)
	53 new (2, 1)
	56 dup (2, 1)
	57 invokespecial (2, 1)
	60 astore (2, 1)
	62 aload (3, 4)
	64 invokevirtual (3, 4)
	67 invokeinterface (3, 4)
	72 astore (3, 4)
	74 aload (3, 4)
	76 invokeinterface (3, 4)
	81 ifeq (3, 4)
	84 aload (3, 4)
	86 invokeinterface (3, 4)
	91 checkcast (3, 4)
	94 astore (3, 4)
	96 aload (3, 4)
	98 aload_0 (3, 4)
	99 aload (3, 4)
	101 aload (3, 4)
	103 invokevirtual (3, 4)
	106 invokevirtual (3, 4)
	109 goto (2, 1)
	112 dload_2 (2, 1)
	113 aload (2, 1)
	115 invokevirtual (2, 1)
	118 dadd (2, 1)
	119 dstore_2 (2, 1)
	120 goto (0, 0)
	123 dload_2 (0, 0)
	124 dreturn (0, 0)

