Method: <init>
	0 aload_0 (0, 0)
	1 aload_1 (0, 0)
	2 invokespecial (0, 0)
	3 org/apache/commons/math3/ml/clustering/evaluation/ClusterEvaluator.<init>:(Lorg/apache/commons/math3/ml/distance/DistanceMeasure;)V (0, 0)
	5 return (0, 0)

Method: score
	0 dconst_0 (0, 0)
	1 dstore_2 (0, 0)
	2 aload_1 (1, 4)
	3 invokeinterface (1, 4)
	4 java/util/List.java/util/Iterator (1, 4)
	6 0 (1, 4)
	8 astore (1, 4)
	9 #4 (1, 4)
	10 aload (1, 4)
	11 #4 (1, 4)
	12 invokeinterface (1, 4)
	13 java/util/Iterator.next:()Ljava/lang/Object; (1, 4)
	15 0 (1, 4)
	17 ifeq (1, 4)
	18 106 (1, 4)
	20 aload (1, 4)
	21 #4 (1, 4)
	22 invokeinterface (1, 4)
	23 java/util/Iterator.org/apache/commons/math3/ml/clustering/Cluster (1, 4)
	25 0 (1, 4)
	27 checkcast (1, 4)
	28 org/apache/commons/math3/ml/clustering/Cluster (1, 4)
	30 astore (1, 4)
	31 #5 (1, 4)
	32 aload (2, 1)
	33 #5 (2, 1)
	34 invokevirtual (2, 1)
	35 org/apache/commons/math3/ml/clustering/Cluster.getPoints:()Ljava/util/List; (2, 1)
	37 invokeinterface (2, 1)
	38 java/util/List.centroidOf:(Lorg/apache/commons/math3/ml/clustering/Cluster;)Lorg/apache/commons/math3/ml/clustering/Clusterable; (2, 1)
	40 0 (2, 1)
	42 ifne (2, 1)
	43 78 (2, 1)
	45 aload_0 (2, 1)
	46 aload (2, 1)
	47 #5 (2, 1)
	48 invokevirtual (2, 1)
	49 org/apache/commons/math3/ml/clustering/evaluation/SumOfClusterVariances.centroidOf:(Lorg/apache/commons/math3/ml/clustering/Cluster;)Lorg/apache/commons/math3/ml/clustering/Clusterable; (2, 1)
	51 astore (2, 1)
	52 #6 (2, 1)
	53 new (2, 1)
	54 org/apache/commons/math3/stat/descriptive/moment/Variance (2, 1)
	56 dup (2, 1)
	57 invokespecial (2, 1)
	58 org/apache/commons/math3/stat/descriptive/moment/Variance.<init>:()V (2, 1)
	60 astore (2, 1)
	61 #7 (2, 1)
	62 aload (3, 4)
	63 #5 (3, 4)
	64 invokevirtual (3, 4)
	65 org/apache/commons/math3/ml/clustering/Cluster.getPoints:()Ljava/util/List; (3, 4)
	67 invokeinterface (3, 4)
	68 java/util/List.java/util/Iterator (3, 4)
	70 0 (3, 4)
	72 astore (3, 4)
	73 #8 (3, 4)
	74 aload (3, 4)
	75 #8 (3, 4)
	76 invokeinterface (3, 4)
	77 java/util/Iterator.next:()Ljava/lang/Object; (3, 4)
	79 0 (3, 4)
	81 ifeq (3, 4)
	82 31 (3, 4)
	84 aload (3, 4)
	85 #8 (3, 4)
	86 invokeinterface (3, 4)
	87 java/util/Iterator.org/apache/commons/math3/ml/clustering/Cluster (3, 4)
	89 0 (3, 4)
	91 checkcast (3, 4)
	92 org/apache/commons/math3/ml/clustering/Clusterable (3, 4)
	94 astore (3, 4)
	95 #9 (3, 4)
	96 aload (3, 4)
	97 #7 (3, 4)
	98 aload_0 (3, 4)
	99 aload (3, 4)
	100 #9 (3, 4)
	101 aload (3, 4)
	102 #6 (3, 4)
	103 invokevirtual (3, 4)
	104 org/apache/commons/math3/ml/clustering/evaluation/SumOfClusterVariances.distance:(Lorg/apache/commons/math3/ml/clustering/Clusterable;Lorg/apache/commons/math3/ml/clustering/Clusterable;)D (3, 4)
	106 invokevirtual (3, 4)
	107 org/apache/commons/math3/stat/descriptive/moment/Variance.increment:(D)V (3, 4)
	109 goto (2, 1)
	110 -35 (2, 1)
	112 dload_2 (2, 1)
	113 aload (2, 1)
	114 #7 (2, 1)
	115 invokevirtual (2, 1)
	116 org/apache/commons/math3/stat/descriptive/moment/Variance.getResult:()D (2, 1)
	118 dadd (2, 1)
	119 dstore_2 (2, 1)
	120 goto (0, 0)
	121 -110 (0, 0)
	123 dload_2 (0, 0)
	124 dreturn (0, 0)

