Method: <init>
	0 aload_0 (0, 0)
	1 invokespecial (0, 0)
	2 java/lang/Object.<init>:()V (0, 0)
	4 aload_0 (0, 4)
	5 dload (0, 4)
	6 #5 (0, 4)
	7 putfield (0, 4)
	8 org/apache/commons/math3/geometry/spherical/oned/Arc.tolerance:D (0, 4)
	10 dload_1 (0, 4)
	11 dload_3 (0, 4)
	12 iconst_0 (0, 4)
	13 invokestatic (0, 4)
	14 org/apache/commons/math3/util/Precision.equals:(DDI)Z (0, 4)
	16 ifne (0, 4)
	17 13 (0, 4)
	19 dload_3 (0, 4)
	20 dload_1 (0, 4)
	21 dsub (0, 4)
	22 ldc2_w (0, 4)
	23 6.283185307179586 (0, 4)
	25 dcmpl (0, 4)
	26 iflt (0, 4)
	27 25 (0, 4)
	29 aload_0 (0, 4)
	30 dconst_0 (0, 4)
	31 putfield (0, 4)
	32 org/apache/commons/math3/geometry/spherical/oned/Arc.lower:D (0, 4)
	34 aload_0 (0, 4)
	35 ldc2_w (0, 4)
	36 6.283185307179586 (0, 4)
	38 putfield (0, 4)
	39 org/apache/commons/math3/geometry/spherical/oned/Arc.upper:D (0, 4)
	41 aload_0 (0, 4)
	42 ldc2_w (0, 4)
	43 3.141592653589793 (0, 4)
	45 putfield (0, 4)
	46 org/apache/commons/math3/geometry/spherical/oned/Arc.middle:D (0, 4)
	48 goto (0, 4)
	49 72 (0, 4)
	51 dload_1 (0, 1)
	52 dload_3 (0, 1)
	53 dcmpg (0, 1)
	54 ifgt (0, 1)
	55 46 (0, 1)
	57 aload_0 (0, 1)
	58 dload_1 (0, 1)
	59 ldc2_w (0, 1)
	60 3.141592653589793 (0, 1)
	62 invokestatic (0, 1)
	63 org/apache/commons/math3/util/MathUtils.normalizeAngle:(DD)D (0, 1)
	65 putfield (0, 1)
	66 org/apache/commons/math3/geometry/spherical/oned/Arc.lower:D (0, 1)
	68 aload_0 (0, 1)
	69 aload_0 (0, 1)
	70 getfield (0, 1)
	71 org/apache/commons/math3/geometry/spherical/oned/Arc.lower:D (0, 1)
	73 dload_3 (0, 1)
	74 dload_1 (0, 1)
	75 dsub (0, 1)
	76 dadd (0, 1)
	77 putfield (0, 1)
	78 org/apache/commons/math3/geometry/spherical/oned/Arc.upper:D (0, 1)
	80 aload_0 (0, 1)
	81 ldc2_w (0, 1)
	82 0.5 (0, 1)
	84 aload_0 (0, 1)
	85 getfield (0, 1)
	86 org/apache/commons/math3/geometry/spherical/oned/Arc.lower:D (0, 1)
	88 aload_0 (0, 1)
	89 getfield (0, 1)
	90 org/apache/commons/math3/geometry/spherical/oned/Arc.upper:D (0, 1)
	92 dadd (0, 1)
	93 dmul (0, 1)
	94 putfield (0, 1)
	95 org/apache/commons/math3/geometry/spherical/oned/Arc.middle:D (0, 1)
	97 goto (0, 1)
	98 23 (0, 1)
	100 new (0, 1)
	101 org/apache/commons/math3/exception/NumberIsTooLargeException (0, 1)
	103 dup (0, 1)
	104 getstatic (0, 1)
	105 org/apache/commons/math3/exception/util/LocalizedFormats.ENDPOINTS_NOT_AN_INTERVAL:Lorg/apache/commons/math3/exception/util/LocalizedFormats; (0, 1)
	107 dload_1 (0, 1)
	108 invokestatic (0, 1)
	109 java/lang/Double.valueOf:(D)Ljava/lang/Double; (0, 1)
	111 dload_3 (0, 1)
	112 invokestatic (0, 1)
	113 java/lang/Double.valueOf:(D)Ljava/lang/Double; (0, 1)
	115 iconst_1 (0, 1)
	116 invokespecial (0, 1)
	117 org/apache/commons/math3/exception/NumberIsTooLargeException.<init>:(Lorg/apache/commons/math3/exception/util/Localizable;Ljava/lang/Number;Ljava/lang/Number;Z)V (0, 1)
	119 athrow (0, 1)
	120 return (0, 1)

Method: getInf
	0 aload_0 (0, 0)
	1 getfield (0, 0)
	2 org/apache/commons/math3/geometry/spherical/oned/Arc.lower:D (0, 0)
	4 dreturn (0, 0)

Method: getSup
	0 aload_0 (0, 0)
	1 getfield (0, 0)
	2 org/apache/commons/math3/geometry/spherical/oned/Arc.upper:D (0, 0)
	4 dreturn (0, 0)

Method: getSize
	0 aload_0 (0, 4)
	1 getfield (0, 4)
	2 org/apache/commons/math3/geometry/spherical/oned/Arc.upper:D (0, 4)
	4 aload_0 (0, 4)
	5 getfield (0, 4)
	6 org/apache/commons/math3/geometry/spherical/oned/Arc.lower:D (0, 4)
	8 dsub (0, 4)
	9 dreturn (0, 4)

Method: getBarycenter
	0 aload_0 (0, 0)
	1 getfield (0, 0)
	2 org/apache/commons/math3/geometry/spherical/oned/Arc.middle:D (0, 0)
	4 dreturn (0, 0)

Method: getTolerance
	0 aload_0 (0, 1)
	1 getfield (0, 1)
	2 org/apache/commons/math3/geometry/spherical/oned/Arc.tolerance:D (0, 1)
	4 dreturn (0, 1)

Method: checkPoint
	0 dload_1 (0, 0)
	1 aload_0 (0, 0)
	2 getfield (0, 0)
	3 org/apache/commons/math3/geometry/spherical/oned/Arc.middle:D (0, 0)
	5 invokestatic (0, 0)
	6 org/apache/commons/math3/util/MathUtils.normalizeAngle:(DD)D (0, 0)
	8 dstore_3 (0, 0)
	9 dload_3 (0, 0)
	10 aload_0 (0, 0)
	11 getfield (0, 0)
	12 org/apache/commons/math3/geometry/spherical/oned/Arc.lower:D (0, 0)
	14 aload_0 (0, 0)
	15 getfield (0, 0)
	16 org/apache/commons/math3/geometry/spherical/oned/Arc.tolerance:D (0, 0)
	18 dsub (0, 0)
	19 dcmpg (0, 0)
	20 iflt (0, 0)
	21 17 (0, 0)
	23 dload_3 (0, 0)
	24 aload_0 (0, 0)
	25 getfield (0, 0)
	26 org/apache/commons/math3/geometry/spherical/oned/Arc.upper:D (0, 0)
	28 aload_0 (0, 0)
	29 getfield (0, 0)
	30 org/apache/commons/math3/geometry/spherical/oned/Arc.tolerance:D (0, 0)
	32 dadd (0, 0)
	33 dcmpl (0, 0)
	34 ifle (0, 0)
	35 7 (0, 0)
	37 getstatic (0, 0)
	38 org/apache/commons/math3/geometry/partitioning/Region$Location.OUTSIDE:Lorg/apache/commons/math3/geometry/partitioning/Region$Location; (0, 0)
	40 areturn (0, 0)
	41 dload_3 (0, 0)
	42 aload_0 (0, 0)
	43 getfield (0, 0)
	44 org/apache/commons/math3/geometry/spherical/oned/Arc.lower:D (0, 0)
	46 aload_0 (0, 0)
	47 getfield (0, 0)
	48 org/apache/commons/math3/geometry/spherical/oned/Arc.tolerance:D (0, 0)
	50 dadd (0, 0)
	51 dcmpl (0, 0)
	52 ifle (0, 0)
	53 21 (0, 0)
	55 dload_3 (0, 0)
	56 aload_0 (0, 0)
	57 getfield (0, 0)
	58 org/apache/commons/math3/geometry/spherical/oned/Arc.upper:D (0, 0)
	60 aload_0 (0, 0)
	61 getfield (0, 0)
	62 org/apache/commons/math3/geometry/spherical/oned/Arc.tolerance:D (0, 0)
	64 dsub (0, 0)
	65 dcmpg (0, 0)
	66 ifge (0, 0)
	67 7 (0, 0)
	69 getstatic (0, 0)
	70 org/apache/commons/math3/geometry/partitioning/Region$Location.INSIDE:Lorg/apache/commons/math3/geometry/partitioning/Region$Location; (0, 0)
	72 areturn (0, 0)
	73 aload_0 (0, 1)
	74 invokevirtual (0, 1)
	75 org/apache/commons/math3/geometry/spherical/oned/Arc.getSize:()D (0, 1)
	77 ldc2_w (0, 1)
	78 6.283185307179586 (0, 1)
	80 aload_0 (0, 1)
	81 getfield (0, 1)
	82 org/apache/commons/math3/geometry/spherical/oned/Arc.tolerance:D (0, 1)
	84 dsub (0, 1)
	85 dcmpl (0, 1)
	86 iflt (0, 1)
	87 9 (0, 1)
	89 getstatic (0, 1)
	90 org/apache/commons/math3/geometry/partitioning/Region$Location.INSIDE:Lorg/apache/commons/math3/geometry/partitioning/Region$Location; (0, 1)
	92 goto (0, 1)
	93 6 (0, 1)
	95 getstatic (0, 1)
	96 org/apache/commons/math3/geometry/partitioning/Region$Location.BOUNDARY:Lorg/apache/commons/math3/geometry/partitioning/Region$Location; (0, 1)
	98 areturn (0, 1)

