Method: <init>
	0 aload_0 (0, 0)
	1 aload_1 (0, 0)
	2 putfield (0, 0)
	3 org/apache/commons/math3/geometry/spherical/oned/ArcsSet$SubArcsIterator.this$0:Lorg/apache/commons/math3/geometry/spherical/oned/ArcsSet; (0, 0)
	5 aload_0 (0, 0)
	6 invokespecial (0, 0)
	7 java/lang/Object.<init>:()V (0, 0)
	9 aload_0 (0, 0)
	10 aload_1 (0, 0)
	11 invokestatic (0, 0)
	12 org/apache/commons/math3/geometry/spherical/oned/ArcsSet.access$000:(Lorg/apache/commons/math3/geometry/spherical/oned/ArcsSet;)Lorg/apache/commons/math3/geometry/partitioning/BSPTree; (0, 0)
	14 putfield (0, 0)
	15 org/apache/commons/math3/geometry/spherical/oned/ArcsSet$SubArcsIterator.firstStart:Lorg/apache/commons/math3/geometry/partitioning/BSPTree; (0, 0)
	17 aload_0 (0, 0)
	18 aload_0 (0, 0)
	19 getfield (0, 0)
	20 org/apache/commons/math3/geometry/spherical/oned/ArcsSet$SubArcsIterator.firstStart:Lorg/apache/commons/math3/geometry/partitioning/BSPTree; (0, 0)
	22 putfield (0, 0)
	23 org/apache/commons/math3/geometry/spherical/oned/ArcsSet$SubArcsIterator.current:Lorg/apache/commons/math3/geometry/partitioning/BSPTree; (0, 0)
	25 aload_0 (1, 1)
	26 getfield (1, 1)
	27 org/apache/commons/math3/geometry/spherical/oned/ArcsSet$SubArcsIterator.firstStart:Lorg/apache/commons/math3/geometry/partitioning/BSPTree; (1, 1)
	29 ifnonnull (1, 1)
	30 52 (1, 1)
	32 aload_1 (2, 1)
	33 aload_1 (2, 1)
	34 iconst_0 (2, 1)
	35 invokevirtual (2, 1)
	36 org/apache/commons/math3/geometry/spherical/oned/ArcsSet.getTree:(Z)Lorg/apache/commons/math3/geometry/partitioning/BSPTree; (2, 1)
	38 invokestatic (2, 1)
	39 org/apache/commons/math3/geometry/spherical/oned/ArcsSet.access$100:(Lorg/apache/commons/math3/geometry/spherical/oned/ArcsSet;Lorg/apache/commons/math3/geometry/partitioning/BSPTree;)Lorg/apache/commons/math3/geometry/partitioning/BSPTree; (2, 1)
	41 invokevirtual (2, 1)
	42 org/apache/commons/math3/geometry/partitioning/BSPTree.getAttribute:()Ljava/lang/Object; (2, 1)
	44 checkcast (2, 1)
	45 java/lang/Boolean (2, 1)
	47 invokevirtual (2, 1)
	48 java/lang/Boolean.booleanValue:()Z (2, 1)
	50 ifeq (2, 1)
	51 23 (2, 1)
	53 aload_0 (2, 1)
	54 iconst_2 (2, 1)
	55 newarray (2, 1)
	56 7 (2, 1)
	57 dup (2, 1)
	58 iconst_0 (2, 1)
	59 dconst_0 (2, 1)
	60 dastore (2, 1)
	61 dup (2, 1)
	62 iconst_1 (2, 1)
	63 ldc2_w (2, 1)
	64 6.283185307179586 (2, 1)
	66 dastore (2, 1)
	67 putfield (2, 1)
	68 org/apache/commons/math3/geometry/spherical/oned/ArcsSet$SubArcsIterator.pending:[D (2, 1)
	70 goto (2, 1)
	71 15 (2, 1)
	73 aload_0 (3, 2)
	74 aconst_null (3, 2)
	75 putfield (3, 2)
	76 org/apache/commons/math3/geometry/spherical/oned/ArcsSet$SubArcsIterator.pending:[D (3, 2)
	78 goto (3, 2)
	79 7 (3, 2)
	81 aload_0 (2, 2)
	82 invokespecial (2, 2)
	83 org/apache/commons/math3/geometry/spherical/oned/ArcsSet$SubArcsIterator.selectPending:()V (2, 2)
	85 return (0, 0)

Method: selectPending
	0 aload_0 (0, 0)
	1 getfield (0, 0)
	2 org/apache/commons/math3/geometry/spherical/oned/ArcsSet$SubArcsIterator.current:Lorg/apache/commons/math3/geometry/partitioning/BSPTree; (0, 0)
	4 astore_1 (0, 0)
	5 aload_1 (1, 3)
	6 ifnull (1, 3)
	7 26 (1, 3)
	9 aload_0 (1, 3)
	10 getfield (1, 3)
	11 org/apache/commons/math3/geometry/spherical/oned/ArcsSet$SubArcsIterator.this$0:Lorg/apache/commons/math3/geometry/spherical/oned/ArcsSet; (1, 3)
	13 aload_1 (1, 3)
	14 invokestatic (1, 3)
	15 org/apache/commons/math3/geometry/spherical/oned/ArcsSet.access$200:(Lorg/apache/commons/math3/geometry/spherical/oned/ArcsSet;Lorg/apache/commons/math3/geometry/partitioning/BSPTree;)Z (1, 3)
	17 ifne (1, 3)
	18 15 (1, 3)
	20 aload_0 (1, 3)
	21 getfield (1, 3)
	22 org/apache/commons/math3/geometry/spherical/oned/ArcsSet$SubArcsIterator.this$0:Lorg/apache/commons/math3/geometry/spherical/oned/ArcsSet; (1, 3)
	24 aload_1 (1, 3)
	25 invokestatic (1, 3)
	26 org/apache/commons/math3/geometry/spherical/oned/ArcsSet.access$300:(Lorg/apache/commons/math3/geometry/spherical/oned/ArcsSet;Lorg/apache/commons/math3/geometry/partitioning/BSPTree;)Lorg/apache/commons/math3/geometry/partitioning/BSPTree; (1, 3)
	28 astore_1 (1, 3)
	29 goto (1, 3)
	30 -24 (1, 3)
	32 aload_1 (1, 1)
	33 ifnonnull (1, 1)
	34 14 (1, 1)
	36 aload_0 (1, 1)
	37 aconst_null (1, 1)
	38 putfield (1, 1)
	39 org/apache/commons/math3/geometry/spherical/oned/ArcsSet$SubArcsIterator.current:Lorg/apache/commons/math3/geometry/partitioning/BSPTree; (1, 1)
	41 aload_0 (1, 1)
	42 aconst_null (1, 1)
	43 putfield (1, 1)
	44 org/apache/commons/math3/geometry/spherical/oned/ArcsSet$SubArcsIterator.pending:[D (1, 1)
	46 return (1, 1)
	47 aload_1 (1, 4)
	48 astore_2 (1, 4)
	49 aload_2 (2, 3)
	50 ifnull (2, 3)
	51 26 (2, 3)
	53 aload_0 (2, 3)
	54 getfield (2, 3)
	55 org/apache/commons/math3/geometry/spherical/oned/ArcsSet$SubArcsIterator.this$0:Lorg/apache/commons/math3/geometry/spherical/oned/ArcsSet; (2, 3)
	57 aload_2 (2, 3)
	58 invokestatic (2, 3)
	59 org/apache/commons/math3/geometry/spherical/oned/ArcsSet.access$400:(Lorg/apache/commons/math3/geometry/spherical/oned/ArcsSet;Lorg/apache/commons/math3/geometry/partitioning/BSPTree;)Z (2, 3)
	61 ifne (2, 3)
	62 15 (2, 3)
	64 aload_0 (2, 3)
	65 getfield (2, 3)
	66 org/apache/commons/math3/geometry/spherical/oned/ArcsSet$SubArcsIterator.this$0:Lorg/apache/commons/math3/geometry/spherical/oned/ArcsSet; (2, 3)
	68 aload_2 (2, 3)
	69 invokestatic (2, 3)
	70 org/apache/commons/math3/geometry/spherical/oned/ArcsSet.access$300:(Lorg/apache/commons/math3/geometry/spherical/oned/ArcsSet;Lorg/apache/commons/math3/geometry/partitioning/BSPTree;)Lorg/apache/commons/math3/geometry/partitioning/BSPTree; (2, 3)
	72 astore_2 (2, 3)
	73 goto (2, 3)
	74 -24 (2, 3)
	76 aload_2 (2, 1)
	77 ifnull (2, 1)
	78 40 (2, 1)
	80 aload_0 (3, 1)
	81 iconst_2 (3, 1)
	82 newarray (3, 1)
	83 7 (3, 1)
	84 dup (3, 1)
	85 iconst_0 (3, 1)
	86 aload_0 (3, 1)
	87 getfield (3, 1)
	88 org/apache/commons/math3/geometry/spherical/oned/ArcsSet$SubArcsIterator.this$0:Lorg/apache/commons/math3/geometry/spherical/oned/ArcsSet; (3, 1)
	90 aload_1 (3, 1)
	91 invokestatic (3, 1)
	92 org/apache/commons/math3/geometry/spherical/oned/ArcsSet.access$500:(Lorg/apache/commons/math3/geometry/spherical/oned/ArcsSet;Lorg/apache/commons/math3/geometry/partitioning/BSPTree;)D (3, 1)
	94 dastore (3, 1)
	95 dup (3, 1)
	96 iconst_1 (3, 1)
	97 aload_0 (3, 1)
	98 getfield (3, 1)
	99 org/apache/commons/math3/geometry/spherical/oned/ArcsSet$SubArcsIterator.this$0:Lorg/apache/commons/math3/geometry/spherical/oned/ArcsSet; (3, 1)
	101 aload_2 (3, 1)
	102 invokestatic (3, 1)
	103 org/apache/commons/math3/geometry/spherical/oned/ArcsSet.access$500:(Lorg/apache/commons/math3/geometry/spherical/oned/ArcsSet;Lorg/apache/commons/math3/geometry/partitioning/BSPTree;)D (3, 1)
	105 dastore (3, 1)
	106 putfield (3, 1)
	107 org/apache/commons/math3/geometry/spherical/oned/ArcsSet$SubArcsIterator.pending:[D (3, 1)
	109 aload_0 (4, 4)
	110 aload_2 (4, 4)
	111 putfield (4, 4)
	112 org/apache/commons/math3/geometry/spherical/oned/ArcsSet$SubArcsIterator.current:Lorg/apache/commons/math3/geometry/partitioning/BSPTree; (4, 4)
	114 goto (4, 4)
	115 85 (4, 4)
	117 aload_0 (6, 4)
	118 getfield (6, 4)
	119 org/apache/commons/math3/geometry/spherical/oned/ArcsSet$SubArcsIterator.firstStart:Lorg/apache/commons/math3/geometry/partitioning/BSPTree; (6, 4)
	121 astore_2 (6, 4)
	122 aload_2 (7, 3)
	123 ifnull (7, 3)
	124 26 (7, 3)
	126 aload_0 (7, 3)
	127 getfield (7, 3)
	128 org/apache/commons/math3/geometry/spherical/oned/ArcsSet$SubArcsIterator.this$0:Lorg/apache/commons/math3/geometry/spherical/oned/ArcsSet; (7, 3)
	130 aload_2 (7, 3)
	131 invokestatic (7, 3)
	132 org/apache/commons/math3/geometry/spherical/oned/ArcsSet.access$400:(Lorg/apache/commons/math3/geometry/spherical/oned/ArcsSet;Lorg/apache/commons/math3/geometry/partitioning/BSPTree;)Z (7, 3)
	134 ifne (7, 3)
	135 15 (7, 3)
	137 aload_0 (7, 3)
	138 getfield (7, 3)
	139 org/apache/commons/math3/geometry/spherical/oned/ArcsSet$SubArcsIterator.this$0:Lorg/apache/commons/math3/geometry/spherical/oned/ArcsSet; (7, 3)
	141 aload_2 (7, 3)
	142 invokestatic (7, 3)
	143 org/apache/commons/math3/geometry/spherical/oned/ArcsSet.access$600:(Lorg/apache/commons/math3/geometry/spherical/oned/ArcsSet;Lorg/apache/commons/math3/geometry/partitioning/BSPTree;)Lorg/apache/commons/math3/geometry/partitioning/BSPTree; (7, 3)
	145 astore_2 (7, 3)
	146 goto (7, 3)
	147 -24 (7, 3)
	149 aload_2 (7, 1)
	150 ifnonnull (7, 1)
	151 11 (7, 1)
	153 new (7, 1)
	154 org/apache/commons/math3/exception/MathInternalError (7, 1)
	156 dup (7, 1)
	157 invokespecial (7, 1)
	158 org/apache/commons/math3/exception/MathInternalError.<init>:()V (7, 1)
	160 athrow (7, 1)
	161 aload_0 (7, 1)
	162 iconst_2 (7, 1)
	163 newarray (7, 1)
	164 7 (7, 1)
	165 dup (7, 1)
	166 iconst_0 (7, 1)
	167 aload_0 (7, 1)
	168 getfield (7, 1)
	169 org/apache/commons/math3/geometry/spherical/oned/ArcsSet$SubArcsIterator.this$0:Lorg/apache/commons/math3/geometry/spherical/oned/ArcsSet; (7, 1)
	171 aload_1 (7, 1)
	172 invokestatic (7, 1)
	173 org/apache/commons/math3/geometry/spherical/oned/ArcsSet.access$500:(Lorg/apache/commons/math3/geometry/spherical/oned/ArcsSet;Lorg/apache/commons/math3/geometry/partitioning/BSPTree;)D (7, 1)
	175 dastore (7, 1)
	176 dup (7, 1)
	177 iconst_1 (7, 1)
	178 aload_0 (7, 1)
	179 getfield (7, 1)
	180 org/apache/commons/math3/geometry/spherical/oned/ArcsSet$SubArcsIterator.this$0:Lorg/apache/commons/math3/geometry/spherical/oned/ArcsSet; (7, 1)
	182 aload_2 (7, 1)
	183 invokestatic (7, 1)
	184 org/apache/commons/math3/geometry/spherical/oned/ArcsSet.access$500:(Lorg/apache/commons/math3/geometry/spherical/oned/ArcsSet;Lorg/apache/commons/math3/geometry/partitioning/BSPTree;)D (7, 1)
	186 ldc2_w (7, 1)
	187 6.283185307179586 (7, 1)
	189 dadd (7, 1)
	190 dastore (7, 1)
	191 putfield (7, 1)
	192 org/apache/commons/math3/geometry/spherical/oned/ArcsSet$SubArcsIterator.pending:[D (7, 1)
	194 aload_0 (7, 1)
	195 aconst_null (7, 1)
	196 putfield (7, 1)
	197 org/apache/commons/math3/geometry/spherical/oned/ArcsSet$SubArcsIterator.current:Lorg/apache/commons/math3/geometry/partitioning/BSPTree; (7, 1)
	199 return (0, 4)

Method: hasNext
	0 aload_0 (0, 0)
	1 getfield (0, 0)
	2 org/apache/commons/math3/geometry/spherical/oned/ArcsSet$SubArcsIterator.pending:[D (0, 0)
	4 ifnull (0, 0)
	5 7 (0, 0)
	7 iconst_1 (0, 0)
	8 goto (0, 0)
	9 4 (0, 0)
	11 iconst_0 (0, 0)
	12 ireturn (0, 0)

Method: next
	0 aload_0 (0, 0)
	1 invokevirtual (0, 0)
	2 org/apache/commons/math3/geometry/spherical/oned/ArcsSet$SubArcsIterator.next:()[D (0, 0)
	4 areturn (0, 0)

Method: remove
	0 new (0, 0)
	1 java/lang/UnsupportedOperationException (0, 0)
	3 dup (0, 0)
	4 invokespecial (0, 0)
	5 java/lang/UnsupportedOperationException.<init>:()V (0, 0)
	7 athrow (0, 0)

