Method: <init>
	0 aload_0 (0, 0)
	1 aload_1 (0, 0)
	2 dload_2 (0, 0)
	3 invokespecial (0, 0)
	6 aload_0 (0, 0)
	7 invokespecial (0, 0)
	10 return (0, 0)

Method: buildTree
	0 dload_0 (1, 1)
	1 dload_2 (1, 1)
	2 iconst_0 (1, 1)
	3 invokestatic (1, 1)
	6 ifne (1, 1)
	9 dload_2 (1, 1)
	10 dload_0 (1, 1)
	11 dsub (1, 1)
	12 ldc2_w (1, 1)
	15 dcmpl (1, 1)
	16 iflt (1, 1)
	19 new (1, 1)
	22 dup (1, 1)
	23 getstatic (1, 1)
	26 invokespecial (1, 1)
	29 areturn (1, 1)
	30 dload_0 (1, 1)
	31 dload_2 (1, 1)
	32 dcmpl (1, 1)
	33 ifle (1, 1)
	36 new (1, 1)
	39 dup (1, 1)
	40 getstatic (1, 1)
	43 dload_0 (1, 1)
	44 invokestatic (1, 1)
	47 dload_2 (1, 1)
	48 invokestatic (1, 1)
	51 iconst_1 (1, 1)
	52 invokespecial (1, 1)
	55 athrow (1, 1)
	56 dload_0 (0, 1)
	57 ldc2_w (0, 1)
	60 invokestatic (0, 1)
	63 dstore (0, 1)
	65 dload (0, 1)
	67 dload_2 (0, 1)
	68 dload_0 (0, 1)
	69 dsub (0, 1)
	70 dadd (0, 1)
	71 dstore (0, 1)
	73 new (0, 1)
	76 dup (0, 1)
	77 new (0, 1)
	80 dup (0, 1)
	81 dload (0, 1)
	83 invokespecial (0, 1)
	86 iconst_0 (0, 1)
	87 dload (0, 1)
	89 invokespecial (0, 1)
	92 invokevirtual (0, 1)
	95 astore (0, 1)
	97 dload (1, 1)
	99 ldc2_w (1, 1)
	102 dcmpg (1, 1)
	103 ifgt (1, 1)
	106 new (1, 4)
	109 dup (1, 4)
	110 new (1, 4)
	113 dup (1, 4)
	114 dload (1, 4)
	116 invokespecial (1, 4)
	119 iconst_1 (1, 4)
	120 dload (1, 4)
	122 invokespecial (1, 4)
	125 invokevirtual (1, 4)
	128 astore (1, 4)
	130 new (1, 4)
	133 dup (1, 4)
	134 aload (1, 4)
	136 new (1, 4)
	139 dup (1, 4)
	140 getstatic (1, 4)
	143 invokespecial (1, 4)
	146 new (1, 4)
	149 dup (1, 4)
	150 aload (1, 4)
	152 new (1, 4)
	155 dup (1, 4)
	156 getstatic (1, 4)
	159 invokespecial (1, 4)
	162 new (1, 4)
	165 dup (1, 4)
	166 getstatic (1, 4)
	169 invokespecial (1, 4)
	172 aconst_null (1, 4)
	173 invokespecial (1, 4)
	176 aconst_null (1, 4)
	177 invokespecial (1, 4)
	180 areturn (1, 4)
	181 new (1, 2)
	184 dup (1, 2)
	185 new (1, 2)
	188 dup (1, 2)
	189 dload (1, 2)
	191 ldc2_w (1, 2)
	194 dsub (1, 2)
	195 invokespecial (1, 2)
	198 iconst_1 (1, 2)
	199 dload (1, 2)
	201 invokespecial (1, 2)
	204 invokevirtual (1, 2)
	207 astore (1, 2)
	209 new (1, 2)
	212 dup (1, 2)
	213 aload (1, 2)
	215 new (1, 2)
	218 dup (1, 2)
	219 aload (1, 2)
	221 new (1, 2)
	224 dup (1, 2)
	225 getstatic (1, 2)
	228 invokespecial (1, 2)
	231 new (1, 2)
	234 dup (1, 2)
	235 getstatic (1, 2)
	238 invokespecial (1, 2)
	241 aconst_null (1, 2)
	242 invokespecial (1, 2)
	245 new (1, 2)
	248 dup (1, 2)
	249 getstatic (1, 2)
	252 invokespecial (1, 2)
	255 aconst_null (1, 2)
	256 invokespecial (1, 2)
	259 areturn (1, 2)

Method: check2PiConsistency
	0 aload_0 (0, 0)
	1 iconst_0 (0, 0)
	2 invokevirtual (0, 0)
	5 astore_1 (0, 0)
	6 aload_1 (1, 1)
	7 invokevirtual (1, 1)
	10 ifnonnull (1, 1)
	13 return (1, 1)
	14 aload_0 (0, 4)
	15 aload_1 (0, 4)
	16 invokespecial (0, 4)
	19 invokevirtual (0, 4)
	22 checkcast (0, 4)
	25 astore_2 (0, 4)
	26 aload_0 (0, 4)
	27 aload_1 (0, 4)
	28 invokespecial (0, 4)
	31 invokevirtual (0, 4)
	34 checkcast (0, 4)
	37 astore_3 (0, 4)
	38 aload_2 (1, 1)
	39 invokevirtual (1, 1)
	42 aload_3 (1, 1)
	43 invokevirtual (1, 1)
	46 ixor (1, 1)
	47 ifeq (1, 1)
	50 new (1, 1)
	53 dup (1, 1)
	54 invokespecial (1, 1)
	57 athrow (1, 1)
	58 return (0, 4)

Method: getFirstLeaf
	0 aload_1 (1, 1)
	1 invokevirtual (1, 1)
	4 ifnonnull (1, 1)
	7 aload_1 (1, 1)
	8 areturn (1, 1)
	9 aconst_null (0, 0)
	10 astore_2 (0, 0)
	11 aload_1 (1, 4)
	12 astore_3 (1, 4)
	13 aload_3 (1, 4)
	14 ifnull (1, 4)
	17 aload_3 (1, 4)
	18 astore_2 (1, 4)
	19 aload_0 (1, 4)
	20 aload_3 (1, 4)
	21 invokespecial (1, 4)
	24 astore_3 (1, 4)
	25 goto (1, 4)
	28 aload_0 (0, 4)
	29 aload_2 (0, 4)
	30 invokespecial (0, 4)
	33 areturn (0, 4)

Method: getLastLeaf
	0 aload_1 (1, 1)
	1 invokevirtual (1, 1)
	4 ifnonnull (1, 1)
	7 aload_1 (1, 1)
	8 areturn (1, 1)
	9 aconst_null (0, 0)
	10 astore_2 (0, 0)
	11 aload_1 (1, 4)
	12 astore_3 (1, 4)
	13 aload_3 (1, 4)
	14 ifnull (1, 4)
	17 aload_3 (1, 4)
	18 astore_2 (1, 4)
	19 aload_0 (1, 4)
	20 aload_3 (1, 4)
	21 invokespecial (1, 4)
	24 astore_3 (1, 4)
	25 goto (1, 4)
	28 aload_0 (0, 0)
	29 aload_2 (0, 0)
	30 invokespecial (0, 0)
	33 areturn (0, 0)

Method: getFirstArcStart
	0 aload_0 (0, 0)
	1 iconst_0 (0, 0)
	2 invokevirtual (0, 0)
	5 astore_1 (0, 0)
	6 aload_1 (1, 1)
	7 invokevirtual (1, 1)
	10 ifnonnull (1, 1)
	13 aconst_null (1, 1)
	14 areturn (1, 1)
	15 aload_0 (0, 0)
	16 aload_1 (0, 0)
	17 invokespecial (0, 0)
	20 invokevirtual (0, 0)
	23 astore_1 (0, 0)
	24 aload_1 (1, 3)
	25 ifnull (1, 3)
	28 aload_0 (1, 3)
	29 aload_1 (1, 3)
	30 invokespecial (1, 3)
	33 ifne (1, 3)
	36 aload_0 (1, 3)
	37 aload_1 (1, 3)
	38 invokespecial (1, 3)
	41 astore_1 (1, 3)
	42 goto (1, 3)
	45 aload_1 (0, 0)
	46 areturn (0, 0)

Method: isArcStart
	0 aload_0 (1, 1)
	1 aload_1 (1, 1)
	2 invokespecial (1, 1)
	5 invokevirtual (1, 1)
	8 checkcast (1, 1)
	11 invokevirtual (1, 1)
	14 ifeq (1, 1)
	17 iconst_0 (1, 4)
	18 ireturn (1, 4)
	19 aload_0 (1, 1)
	20 aload_1 (1, 1)
	21 invokespecial (1, 1)
	24 invokevirtual (1, 1)
	27 checkcast (1, 1)
	30 invokevirtual (1, 1)
	33 ifne (1, 1)
	36 iconst_0 (1, 1)
	37 ireturn (1, 1)
	38 iconst_1 (0, 4)
	39 ireturn (0, 4)

Method: isArcEnd
	0 aload_0 (1, 1)
	1 aload_1 (1, 1)
	2 invokespecial (1, 1)
	5 invokevirtual (1, 1)
	8 checkcast (1, 1)
	11 invokevirtual (1, 1)
	14 ifne (1, 1)
	17 iconst_0 (1, 4)
	18 ireturn (1, 4)
	19 aload_0 (1, 1)
	20 aload_1 (1, 1)
	21 invokespecial (1, 1)
	24 invokevirtual (1, 1)
	27 checkcast (1, 1)
	30 invokevirtual (1, 1)
	33 ifeq (1, 1)
	36 iconst_0 (1, 1)
	37 ireturn (1, 1)
	38 iconst_1 (0, 4)
	39 ireturn (0, 4)

Method: nextInternalNode
	0 aload_0 (1, 1)
	1 aload_1 (1, 1)
	2 invokespecial (1, 1)
	5 invokevirtual (1, 1)
	8 ifnull (1, 1)
	11 aload_0 (1, 1)
	12 aload_1 (1, 1)
	13 invokespecial (1, 1)
	16 invokevirtual (1, 1)
	19 areturn (1, 1)
	20 aload_0 (1, 3)
	21 aload_1 (1, 3)
	22 invokespecial (1, 3)
	25 ifeq (1, 3)
	28 aload_1 (1, 3)
	29 invokevirtual (1, 3)
	32 astore_1 (1, 3)
	33 goto (1, 3)
	36 aload_1 (0, 0)
	37 invokevirtual (0, 0)
	40 areturn (0, 0)

Method: previousInternalNode
	0 aload_0 (1, 1)
	1 aload_1 (1, 1)
	2 invokespecial (1, 1)
	5 invokevirtual (1, 1)
	8 ifnull (1, 1)
	11 aload_0 (1, 4)
	12 aload_1 (1, 4)
	13 invokespecial (1, 4)
	16 invokevirtual (1, 4)
	19 areturn (1, 4)
	20 aload_0 (1, 3)
	21 aload_1 (1, 3)
	22 invokespecial (1, 3)
	25 ifeq (1, 3)
	28 aload_1 (1, 3)
	29 invokevirtual (1, 3)
	32 astore_1 (1, 3)
	33 goto (1, 3)
	36 aload_1 (0, 1)
	37 invokevirtual (0, 1)
	40 areturn (0, 1)

Method: leafBefore
	0 aload_0 (0, 4)
	1 aload_1 (0, 4)
	2 invokespecial (0, 4)
	5 astore_1 (0, 4)
	6 aload_1 (1, 3)
	7 invokevirtual (1, 3)
	10 ifnull (1, 3)
	13 aload_0 (1, 3)
	14 aload_1 (1, 3)
	15 invokespecial (1, 3)
	18 astore_1 (1, 3)
	19 goto (1, 3)
	22 aload_1 (0, 4)
	23 areturn (0, 4)

Method: leafAfter
	0 aload_0 (0, 0)
	1 aload_1 (0, 0)
	2 invokespecial (0, 0)
	5 astore_1 (0, 0)
	6 aload_1 (1, 3)
	7 invokevirtual (1, 3)
	10 ifnull (1, 3)
	13 aload_0 (1, 4)
	14 aload_1 (1, 4)
	15 invokespecial (1, 4)
	18 astore_1 (1, 4)
	19 goto (1, 4)
	22 aload_1 (0, 3)
	23 areturn (0, 3)

Method: isBeforeParent
	0 aload_1 (0, 0)
	1 invokevirtual (0, 0)
	4 astore_2 (0, 0)
	5 aload_2 (1, 1)
	6 ifnonnull (1, 1)
	9 iconst_0 (1, 1)
	10 ireturn (1, 1)
	11 aload_1 (1, 4)
	12 aload_0 (1, 4)
	13 aload_2 (1, 4)
	14 invokespecial (1, 4)
	17 if_acmpne (1, 4)
	20 iconst_1 (1, 4)
	21 goto (1, 4)
	24 iconst_0 (1, 4)
	25 ireturn (1, 4)

Method: isAfterParent
	0 aload_1 (0, 0)
	1 invokevirtual (0, 0)
	4 astore_2 (0, 0)
	5 aload_2 (1, 1)
	6 ifnonnull (1, 1)
	9 iconst_0 (1, 1)
	10 ireturn (1, 1)
	11 aload_1 (1, 2)
	12 aload_0 (1, 2)
	13 aload_2 (1, 2)
	14 invokespecial (1, 2)
	17 if_acmpne (1, 2)
	20 iconst_1 (1, 2)
	21 goto (1, 2)
	24 iconst_0 (1, 2)
	25 ireturn (1, 2)

Method: childBefore
	0 aload_0 (1, 1)
	1 aload_1 (1, 1)
	2 invokespecial (1, 1)
	5 ifeq (1, 1)
	8 aload_1 (1, 1)
	9 invokevirtual (1, 1)
	12 areturn (1, 1)
	13 aload_1 (1, 2)
	14 invokevirtual (1, 2)
	17 areturn (1, 2)

Method: childAfter
	0 aload_0 (1, 1)
	1 aload_1 (1, 1)
	2 invokespecial (1, 1)
	5 ifeq (1, 1)
	8 aload_1 (1, 1)
	9 invokevirtual (1, 1)
	12 areturn (1, 1)
	13 aload_1 (1, 2)
	14 invokevirtual (1, 2)
	17 areturn (1, 2)

Method: isDirect
	0 aload_1 (0, 0)
	1 invokevirtual (0, 0)
	4 invokeinterface (0, 0)
	9 checkcast (0, 0)
	12 invokevirtual (0, 0)
	15 ireturn (0, 0)

Method: getAngle
	0 aload_1 (0, 0)
	1 invokevirtual (0, 0)
	4 invokeinterface (0, 0)
	9 checkcast (0, 0)
	12 invokevirtual (0, 0)
	15 invokevirtual (0, 0)
	18 dreturn (0, 0)

Method: buildNew
	0 aload_0 (0, 0)
	1 aload_1 (0, 0)
	2 invokevirtual (0, 0)
	5 areturn (0, 0)

Method: computeGeometricalProperties
	0 aload_0 (1, 1)
	1 iconst_0 (1, 1)
	2 invokevirtual (1, 1)
	5 invokevirtual (1, 1)
	8 ifnonnull (1, 1)
	11 aload_0 (1, 1)
	12 getstatic (1, 1)
	15 invokevirtual (1, 1)
	18 aload_0 (1, 1)
	19 aload_0 (1, 1)
	20 iconst_0 (1, 1)
	21 invokevirtual (1, 1)
	24 invokevirtual (1, 1)
	27 checkcast (1, 1)
	30 invokevirtual (1, 1)
	33 ifeq (1, 1)
	36 ldc2_w (1, 1)
	39 goto (1, 1)
	42 dconst_0 (1, 1)
	43 invokevirtual (1, 1)
	46 goto (1, 1)
	49 dconst_0 (1, 2)
	50 dstore_1 (1, 2)
	51 dconst_0 (1, 2)
	52 dstore_3 (1, 2)
	53 aload_0 (2, 4)
	54 invokevirtual (2, 4)
	57 astore (2, 4)
	59 aload (2, 4)
	61 invokeinterface (2, 4)
	66 ifeq (2, 4)
	69 aload (2, 4)
	71 invokeinterface (2, 4)
	76 checkcast (2, 4)
	79 astore (2, 4)
	81 aload (2, 4)
	83 iconst_1 (2, 4)
	84 daload (2, 4)
	85 aload (2, 4)
	87 iconst_0 (2, 4)
	88 daload (2, 4)
	89 dsub (2, 4)
	90 dstore (2, 4)
	92 dload_1 (2, 4)
	93 dload (2, 4)
	95 dadd (2, 4)
	96 dstore_1 (2, 4)
	97 dload_3 (2, 4)
	98 dload (2, 4)
	100 aload (2, 4)
	102 iconst_0 (2, 4)
	103 daload (2, 4)
	104 aload (2, 4)
	106 iconst_1 (2, 4)
	107 daload (2, 4)
	108 dadd (2, 4)
	109 dmul (2, 4)
	110 dadd (2, 4)
	111 dstore_3 (2, 4)
	112 goto (1, 2)
	115 aload_0 (1, 2)
	116 dload_1 (1, 2)
	117 invokevirtual (1, 2)
	120 dload_1 (2, 1)
	121 ldc2_w (2, 1)
	124 iconst_0 (2, 1)
	125 invokestatic (2, 1)
	128 ifeq (2, 1)
	131 aload_0 (2, 1)
	132 getstatic (2, 1)
	135 invokevirtual (2, 1)
	138 goto (2, 1)
	141 dload_1 (2, 1)
	142 getstatic (2, 1)
	145 dcmpl (2, 1)
	146 iflt (2, 1)
	149 aload_0 (2, 1)
	150 new (2, 1)
	153 dup (2, 1)
	154 dload_3 (2, 1)
	155 ldc2_w (2, 1)
	158 dload_1 (2, 1)
	159 dmul (2, 1)
	160 ddiv (2, 1)
	161 invokespecial (2, 1)
	164 invokevirtual (2, 1)
	167 goto (2, 1)
	170 aload_0 (2, 2)
	171 iconst_0 (2, 2)
	172 invokevirtual (2, 2)
	175 invokevirtual (2, 2)
	178 invokeinterface (2, 2)
	183 checkcast (2, 2)
	186 astore (2, 2)
	188 aload_0 (2, 2)
	189 aload (2, 2)
	191 invokevirtual (2, 2)
	194 invokevirtual (2, 2)
	197 return (0, 2)

Method: projectToBoundary
	0 aload_1 (0, 0)
	1 checkcast (0, 0)
	4 invokevirtual (0, 0)
	7 dstore_2 (0, 0)
	8 iconst_0 (0, 0)
	9 istore (0, 0)
	11 ldc2_w (0, 0)
	14 dstore (0, 0)
	16 ldc2_w (0, 0)
	19 dstore (0, 0)
	21 aload_0 (1, 4)
	22 invokevirtual (1, 4)
	25 astore (1, 4)
	27 aload (1, 4)
	29 invokeinterface (1, 4)
	34 ifeq (1, 4)
	37 aload (1, 4)
	39 invokeinterface (1, 4)
	44 checkcast (1, 4)
	47 astore (1, 4)
	49 dload (2, 1)
	51 invokestatic (2, 1)
	54 ifeq (2, 1)
	57 aload (2, 1)
	59 iconst_0 (2, 1)
	60 daload (2, 1)
	61 dstore (2, 1)
	63 iload (2, 1)
	65 ifne (2, 1)
	68 dload_2 (3, 1)
	69 aload (3, 1)
	71 iconst_0 (3, 1)
	72 daload (3, 1)
	73 dcmpg (3, 1)
	74 ifge (3, 1)
	77 dload (4, 1)
	79 invokestatic (4, 1)
	82 ifeq (4, 1)
	85 iconst_1 (4, 1)
	86 istore (4, 1)
	88 goto (4, 1)
	91 dload_2 (4, 2)
	92 dload (4, 2)
	94 dsub (4, 2)
	95 dstore (4, 2)
	97 aload (4, 2)
	99 iconst_0 (4, 2)
	100 daload (4, 2)
	101 dload_2 (4, 2)
	102 dsub (4, 2)
	103 dstore (4, 2)
	105 dload (5, 1)
	107 dload (5, 1)
	109 dcmpg (5, 1)
	110 ifge (5, 1)
	113 new (5, 1)
	116 dup (5, 1)
	117 aload_1 (5, 1)
	118 new (5, 1)
	121 dup (5, 1)
	122 dload (5, 1)
	124 invokespecial (5, 1)
	127 dload (5, 1)
	129 invokespecial (5, 1)
	132 areturn (5, 1)
	133 new (5, 2)
	136 dup (5, 2)
	137 aload_1 (5, 2)
	138 new (5, 2)
	141 dup (5, 2)
	142 aload (5, 2)
	144 iconst_0 (5, 2)
	145 daload (5, 2)
	146 invokespecial (5, 2)
	149 dload (5, 2)
	151 invokespecial (5, 2)
	154 areturn (5, 2)
	155 dload_2 (3, 1)
	156 aload (3, 1)
	158 iconst_1 (3, 1)
	159 daload (3, 1)
	160 dcmpg (3, 1)
	161 ifgt (3, 1)
	164 aload (3, 1)
	166 iconst_0 (3, 1)
	167 daload (3, 1)
	168 dload_2 (3, 1)
	169 dsub (3, 1)
	170 dstore (3, 1)
	172 dload_2 (3, 1)
	173 aload (3, 1)
	175 iconst_1 (3, 1)
	176 daload (3, 1)
	177 dsub (3, 1)
	178 dstore (3, 1)
	180 dload (4, 1)
	182 dload (4, 1)
	184 dcmpg (4, 1)
	185 ifge (4, 1)
	188 new (4, 1)
	191 dup (4, 1)
	192 aload_1 (4, 1)
	193 new (4, 1)
	196 dup (4, 1)
	197 aload (4, 1)
	199 iconst_1 (4, 1)
	200 daload (4, 1)
	201 invokespecial (4, 1)
	204 dload (4, 1)
	206 invokespecial (4, 1)
	209 areturn (4, 1)
	210 new (4, 2)
	213 dup (4, 2)
	214 aload_1 (4, 2)
	215 new (4, 2)
	218 dup (4, 2)
	219 aload (4, 2)
	221 iconst_0 (4, 2)
	222 daload (4, 2)
	223 invokespecial (4, 2)
	226 dload (4, 2)
	228 invokespecial (4, 2)
	231 areturn (4, 2)
	232 aload (1, 2)
	234 iconst_1 (1, 2)
	235 daload (1, 2)
	236 dstore (1, 2)
	238 goto (0, 1)
	241 dload (1, 1)
	243 invokestatic (1, 1)
	246 ifeq (1, 1)
	249 new (1, 1)
	252 dup (1, 1)
	253 aload_1 (1, 1)
	254 aconst_null (1, 1)
	255 ldc2_w (1, 1)
	258 invokespecial (1, 1)
	261 areturn (1, 1)
	262 iload (2, 1)
	264 ifeq (2, 1)
	267 dload_2 (2, 1)
	268 dload (2, 1)
	270 ldc2_w (2, 1)
	273 dsub (2, 1)
	274 dsub (2, 1)
	275 dstore (2, 1)
	277 dload (2, 1)
	279 dload_2 (2, 1)
	280 dsub (2, 1)
	281 dstore (2, 1)
	283 dload (3, 1)
	285 dload (3, 1)
	287 dcmpg (3, 1)
	288 ifge (3, 1)
	291 new (3, 1)
	294 dup (3, 1)
	295 aload_1 (3, 1)
	296 new (3, 1)
	299 dup (3, 1)
	300 dload (3, 1)
	302 invokespecial (3, 1)
	305 dload (3, 1)
	307 invokespecial (3, 1)
	310 areturn (3, 1)
	311 new (3, 2)
	314 dup (3, 2)
	315 aload_1 (3, 2)
	316 new (3, 2)
	319 dup (3, 2)
	320 dload (3, 2)
	322 invokespecial (3, 2)
	325 dload (3, 2)
	327 invokespecial (3, 2)
	330 areturn (3, 2)
	331 dload_2 (2, 2)
	332 dload (2, 2)
	334 dsub (2, 2)
	335 dstore (2, 2)
	337 dload (2, 2)
	339 ldc2_w (2, 2)
	342 dadd (2, 2)
	343 dload_2 (2, 2)
	344 dsub (2, 2)
	345 dstore (2, 2)
	347 dload (3, 1)
	349 dload (3, 1)
	351 dcmpg (3, 1)
	352 ifge (3, 1)
	355 new (3, 1)
	358 dup (3, 1)
	359 aload_1 (3, 1)
	360 new (3, 1)
	363 dup (3, 1)
	364 dload (3, 1)
	366 invokespecial (3, 1)
	369 dload (3, 1)
	371 invokespecial (3, 1)
	374 areturn (3, 1)
	375 new (3, 2)
	378 dup (3, 2)
	379 aload_1 (3, 2)
	380 new (3, 2)
	383 dup (3, 2)
	384 dload (3, 2)
	386 invokespecial (3, 2)
	389 dload (3, 2)
	391 invokespecial (3, 2)
	394 areturn (3, 2)

Method: asList
	0 new (0, 0)
	3 dup (0, 0)
	4 invokespecial (0, 0)
	7 astore_1 (0, 0)
	8 aload_0 (1, 4)
	9 invokevirtual (1, 4)
	12 astore_2 (1, 4)
	13 aload_2 (1, 4)
	14 invokeinterface (1, 4)
	19 ifeq (1, 4)
	22 aload_2 (1, 4)
	23 invokeinterface (1, 4)
	28 checkcast (1, 4)
	31 astore_3 (1, 4)
	32 aload_1 (1, 4)
	33 new (1, 4)
	36 dup (1, 4)
	37 aload_3 (1, 4)
	38 iconst_0 (1, 4)
	39 daload (1, 4)
	40 aload_3 (1, 4)
	41 iconst_1 (1, 4)
	42 daload (1, 4)
	43 aload_0 (1, 4)
	44 invokevirtual (1, 4)
	47 invokespecial (1, 4)
	50 invokeinterface (1, 4)
	55 pop (1, 4)
	56 goto (0, 0)
	59 aload_1 (0, 0)
	60 areturn (0, 0)

Method: iterator
	0 new (0, 0)
	3 dup (0, 0)
	4 aload_0 (0, 0)
	5 invokespecial (0, 0)
	8 areturn (0, 0)

Method: side
	0 aload_0 (0, 0)
	1 aload_1 (0, 0)
	2 invokevirtual (0, 0)
	5 invokevirtual (0, 0)
	8 areturn (0, 0)

Method: split
	0 new (0, 0)
	3 dup (0, 0)
	4 invokespecial (0, 0)
	7 astore_2 (0, 0)
	8 new (0, 0)
	11 dup (0, 0)
	12 invokespecial (0, 0)
	15 astore_3 (0, 0)
	16 ldc2_w (0, 0)
	19 aload_1 (0, 0)
	20 invokevirtual (0, 0)
	23 dadd (0, 0)
	24 dstore (0, 0)
	26 aload_1 (0, 0)
	27 invokevirtual (0, 0)
	30 aload_1 (0, 0)
	31 invokevirtual (0, 0)
	34 dsub (0, 0)
	35 dstore (0, 0)
	37 aload_0 (1, 4)
	38 invokevirtual (1, 4)
	41 astore (1, 4)
	43 aload (1, 4)
	45 invokeinterface (1, 4)
	50 ifeq (1, 4)
	53 aload (1, 4)
	55 invokeinterface (1, 4)
	60 checkcast (1, 4)
	63 astore (1, 4)
	65 aload (1, 4)
	67 iconst_0 (1, 4)
	68 daload (1, 4)
	69 dload (1, 4)
	71 invokestatic (1, 4)
	74 aload_1 (1, 4)
	75 invokevirtual (1, 4)
	78 dsub (1, 4)
	79 dstore (1, 4)
	81 aload (1, 4)
	83 iconst_0 (1, 4)
	84 daload (1, 4)
	85 dload (1, 4)
	87 dsub (1, 4)
	88 dstore (1, 4)
	90 aload (1, 4)
	92 iconst_1 (1, 4)
	93 daload (1, 4)
	94 dload (1, 4)
	96 dsub (1, 4)
	97 dstore (1, 4)
	99 dload (2, 1)
	101 dload (2, 1)
	103 dcmpg (2, 1)
	104 ifge (2, 1)
	107 aload_2 (2, 1)
	108 aload (2, 1)
	110 iconst_0 (2, 1)
	111 daload (2, 1)
	112 invokestatic (2, 1)
	115 invokeinterface (2, 1)
	120 pop (2, 1)
	121 dload (3, 1)
	123 dload (3, 1)
	125 dcmpl (3, 1)
	126 ifle (3, 1)
	129 dload (3, 1)
	131 dload (3, 1)
	133 dadd (3, 1)
	134 dstore (3, 1)
	136 aload_2 (3, 1)
	137 dload (3, 1)
	139 invokestatic (3, 1)
	142 invokeinterface (3, 1)
	147 pop (3, 1)
	148 aload_3 (3, 1)
	149 dload (3, 1)
	151 invokestatic (3, 1)
	154 invokeinterface (3, 1)
	159 pop (3, 1)
	160 dload (4, 1)
	162 ldc2_w (4, 1)
	165 dcmpl (4, 1)
	166 ifle (4, 1)
	169 ldc2_w (4, 1)
	172 dload (4, 1)
	174 dadd (4, 1)
	175 dstore (4, 1)
	177 aload_3 (4, 1)
	178 dload (4, 1)
	180 invokestatic (4, 1)
	183 invokeinterface (4, 1)
	188 pop (4, 1)
	189 aload_2 (4, 1)
	190 dload (4, 1)
	192 invokestatic (4, 1)
	195 invokeinterface (4, 1)
	200 pop (4, 1)
	201 aload_2 (4, 1)
	202 aload (4, 1)
	204 iconst_1 (4, 1)
	205 daload (4, 1)
	206 invokestatic (4, 1)
	209 invokeinterface (4, 1)
	214 pop (4, 1)
	215 goto (4, 2)
	218 aload_3 (4, 2)
	219 aload (4, 2)
	221 iconst_1 (4, 2)
	222 daload (4, 2)
	223 invokestatic (4, 2)
	226 invokeinterface (4, 2)
	231 pop (4, 2)
	232 goto (3, 2)
	235 aload_2 (3, 2)
	236 aload (3, 2)
	238 iconst_1 (3, 2)
	239 daload (3, 2)
	240 invokestatic (3, 2)
	243 invokeinterface (3, 2)
	248 pop (3, 2)
	249 goto (3, 2)
	252 aload_3 (2, 2)
	253 aload (2, 2)
	255 iconst_0 (2, 2)
	256 daload (2, 2)
	257 invokestatic (2, 2)
	260 invokeinterface (2, 2)
	265 pop (2, 2)
	266 dload (3, 1)
	268 ldc2_w (3, 1)
	271 dcmpl (3, 1)
	272 ifle (3, 1)
	275 ldc2_w (3, 1)
	278 dload (3, 1)
	280 dadd (3, 1)
	281 dstore (3, 1)
	283 aload_3 (3, 1)
	284 dload (3, 1)
	286 invokestatic (3, 1)
	289 invokeinterface (3, 1)
	294 pop (3, 1)
	295 aload_2 (3, 1)
	296 dload (3, 1)
	298 invokestatic (3, 1)
	301 invokeinterface (3, 1)
	306 pop (3, 1)
	307 dload (4, 1)
	309 ldc2_w (4, 1)
	312 dload (4, 1)
	314 dadd (4, 1)
	315 dcmpl (4, 1)
	316 ifle (4, 1)
	319 ldc2_w (4, 1)
	322 dload (4, 1)
	324 dadd (4, 1)
	325 dload (4, 1)
	327 dadd (4, 1)
	328 dstore (4, 1)
	330 aload_2 (4, 1)
	331 dload (4, 1)
	333 invokestatic (4, 1)
	336 invokeinterface (4, 1)
	341 pop (4, 1)
	342 aload_3 (4, 1)
	343 dload (4, 1)
	345 invokestatic (4, 1)
	348 invokeinterface (4, 1)
	353 pop (4, 1)
	354 aload_3 (4, 1)
	355 aload (4, 1)
	357 iconst_1 (4, 1)
	358 daload (4, 1)
	359 invokestatic (4, 1)
	362 invokeinterface (4, 1)
	367 pop (4, 1)
	368 goto (4, 2)
	371 aload_2 (4, 2)
	372 aload (4, 2)
	374 iconst_1 (4, 2)
	375 daload (4, 2)
	376 invokestatic (4, 2)
	379 invokeinterface (4, 2)
	384 pop (4, 2)
	385 goto (3, 2)
	388 aload_3 (3, 2)
	389 aload (3, 2)
	391 iconst_1 (3, 2)
	392 daload (3, 2)
	393 invokestatic (3, 2)
	396 invokeinterface (3, 2)
	401 pop (3, 2)
	402 goto (0, 2)
	405 new (0, 2)
	408 dup (0, 2)
	409 aload_0 (0, 2)
	410 aload_3 (0, 2)
	411 invokespecial (0, 2)
	414 aload_0 (0, 2)
	415 aload_2 (0, 2)
	416 invokespecial (0, 2)
	419 aconst_null (0, 2)
	420 invokespecial (0, 2)
	423 areturn (0, 2)

Method: addArcLimit
	0 new (0, 0)
	3 dup (0, 0)
	4 new (0, 0)
	7 dup (0, 0)
	8 dload_2 (0, 0)
	9 invokespecial (0, 0)
	12 iload (0, 0)
	14 ifne (0, 0)
	17 iconst_1 (0, 0)
	18 goto (0, 0)
	21 iconst_0 (0, 0)
	22 aload_0 (0, 0)
	23 invokevirtual (0, 0)
	26 invokespecial (0, 0)
	29 astore (0, 0)
	31 aload_1 (0, 0)
	32 aload (0, 0)
	34 invokevirtual (0, 0)
	37 aload_0 (0, 0)
	38 invokevirtual (0, 0)
	41 invokevirtual (0, 0)
	44 astore (0, 0)
	46 aload (1, 1)
	48 invokevirtual (1, 1)
	51 ifnull (1, 1)
	54 new (1, 1)
	57 dup (1, 1)
	58 invokespecial (1, 1)
	61 athrow (1, 1)
	62 aload (0, 0)
	64 aload (0, 0)
	66 invokevirtual (0, 0)
	69 pop (0, 0)
	70 aload (0, 0)
	72 aconst_null (0, 0)
	73 invokevirtual (0, 0)
	76 aload (0, 0)
	78 invokevirtual (0, 0)
	81 getstatic (0, 0)
	84 invokevirtual (0, 0)
	87 aload (0, 0)
	89 invokevirtual (0, 0)
	92 getstatic (0, 0)
	95 invokevirtual (0, 0)
	98 return (0, 0)

Method: createSplitPart
	0 aload_1 (1, 1)
	1 invokeinterface (1, 1)
	6 ifeq (1, 1)
	9 aconst_null (1, 1)
	10 areturn (1, 1)
	11 iconst_0 (2, 4)
	12 istore_2 (2, 4)
	13 iload_2 (2, 4)
	14 aload_1 (2, 4)
	15 invokeinterface (2, 4)
	20 if_icmpge (2, 4)
	23 iload_2 (2, 4)
	24 iconst_1 (2, 4)
	25 iadd (2, 4)
	26 aload_1 (2, 4)
	27 invokeinterface (2, 4)
	32 irem (2, 4)
	33 istore_3 (2, 4)
	34 aload_1 (2, 4)
	35 iload_2 (2, 4)
	36 invokeinterface (2, 4)
	41 checkcast (2, 4)
	44 invokevirtual (2, 4)
	47 dstore (2, 4)
	49 aload_1 (2, 4)
	50 iload_3 (2, 4)
	51 invokeinterface (2, 4)
	56 checkcast (2, 4)
	59 invokevirtual (2, 4)
	62 dload (2, 4)
	64 invokestatic (2, 4)
	67 dstore (2, 4)
	69 dload (3, 1)
	71 dload (3, 1)
	73 dsub (3, 1)
	74 invokestatic (3, 1)
	77 aload_0 (3, 1)
	78 invokevirtual (3, 1)
	81 dcmpg (3, 1)
	82 ifgt (3, 1)
	85 iload_3 (4, 1)
	86 ifle (4, 1)
	89 aload_1 (4, 1)
	90 iload_3 (4, 1)
	91 invokeinterface (4, 1)
	96 pop (4, 1)
	97 aload_1 (4, 1)
	98 iload_2 (4, 1)
	99 invokeinterface (4, 1)
	104 pop (4, 1)
	105 iload_2 (4, 1)
	106 iconst_1 (4, 1)
	107 isub (4, 1)
	108 istore_2 (4, 1)
	109 goto (4, 1)
	112 aload_1 (4, 2)
	113 aload_1 (4, 2)
	114 invokeinterface (4, 2)
	119 iconst_1 (4, 2)
	120 isub (4, 2)
	121 invokeinterface (4, 2)
	126 checkcast (4, 2)
	129 invokevirtual (4, 2)
	132 dstore (4, 2)
	134 aload_1 (4, 2)
	135 iconst_0 (4, 2)
	136 invokeinterface (4, 2)
	141 checkcast (4, 2)
	144 invokevirtual (4, 2)
	147 dstore (4, 2)
	149 aload_1 (5, 1)
	150 invokeinterface (5, 1)
	155 ifeq (5, 1)
	158 dload (6, 1)
	160 dload (6, 1)
	162 dsub (6, 1)
	163 ldc2_w (6, 1)
	166 dcmpl (6, 1)
	167 ifle (6, 1)
	170 new (6, 1)
	173 dup (6, 1)
	174 new (6, 1)
	177 dup (6, 1)
	178 getstatic (6, 1)
	181 invokespecial (6, 1)
	184 aload_0 (6, 1)
	185 invokevirtual (6, 1)
	188 invokespecial (6, 1)
	191 areturn (6, 1)
	192 aconst_null (6, 2)
	193 areturn (6, 2)
	194 aload_1 (5, 2)
	195 aload_1 (5, 2)
	196 iconst_0 (5, 2)
	197 invokeinterface (5, 2)
	202 checkcast (5, 2)
	205 invokevirtual (5, 2)
	208 ldc2_w (5, 2)
	211 dadd (5, 2)
	212 invokestatic (5, 2)
	215 invokeinterface (5, 2)
	220 pop (5, 2)
	221 iinc (5, 2)
	224 goto (5, 2)
	227 new (4, 1)
	230 dup (4, 1)
	231 getstatic (4, 1)
	234 invokespecial (4, 1)
	237 astore_2 (4, 1)
	238 iconst_0 (5, 4)
	239 istore_3 (5, 4)
	240 iload_3 (5, 4)
	241 aload_1 (5, 4)
	242 invokeinterface (5, 4)
	247 iconst_1 (5, 4)
	248 isub (5, 4)
	249 if_icmpge (5, 4)
	252 aload_0 (5, 4)
	253 aload_2 (5, 4)
	254 aload_1 (5, 4)
	255 iload_3 (5, 4)
	256 invokeinterface (5, 4)
	261 checkcast (5, 4)
	264 invokevirtual (5, 4)
	267 iconst_1 (5, 4)
	268 invokespecial (5, 4)
	271 aload_0 (5, 4)
	272 aload_2 (5, 4)
	273 aload_1 (5, 4)
	274 iload_3 (5, 4)
	275 iconst_1 (5, 4)
	276 iadd (5, 4)
	277 invokeinterface (5, 4)
	282 checkcast (5, 4)
	285 invokevirtual (5, 4)
	288 iconst_0 (5, 4)
	289 invokespecial (5, 4)
	292 iinc (5, 4)
	295 goto (5, 4)
	298 aload_2 (5, 1)
	299 invokevirtual (5, 1)
	302 ifnonnull (5, 1)
	305 aconst_null (5, 1)
	306 areturn (5, 1)
	307 new (4, 1)
	310 dup (4, 1)
	311 aload_2 (4, 1)
	312 aload_0 (4, 1)
	313 invokevirtual (4, 1)
	316 invokespecial (4, 1)
	319 areturn (4, 1)

Method: access$000
	0 aload_0 (0, 0)
	1 invokespecial (0, 0)
	4 areturn (0, 0)

Method: access$100
	0 aload_0 (0, 0)
	1 aload_1 (0, 0)
	2 invokespecial (0, 0)
	5 areturn (0, 0)

Method: access$200
	0 aload_0 (0, 0)
	1 aload_1 (0, 0)
	2 invokespecial (0, 0)
	5 ireturn (0, 0)

Method: access$300
	0 aload_0 (0, 0)
	1 aload_1 (0, 0)
	2 invokespecial (0, 0)
	5 areturn (0, 0)

Method: access$400
	0 aload_0 (0, 0)
	1 aload_1 (0, 0)
	2 invokespecial (0, 0)
	5 ireturn (0, 0)

Method: access$500
	0 aload_0 (0, 0)
	1 aload_1 (0, 0)
	2 invokespecial (0, 0)
	5 dreturn (0, 0)

Method: access$600
	0 aload_0 (0, 0)
	1 aload_1 (0, 0)
	2 invokespecial (0, 0)
	5 areturn (0, 0)

