Method: <init>
	0 aload_0 (0, 0)
	1 invokespecial (0, 0)
	4 aload_0 (0, 0)
	5 aload_1 (0, 0)
	6 aload (0, 0)
	8 invokevirtual (0, 0)
	11 putfield (0, 0)
	14 aload_0 (0, 0)
	15 aload (0, 0)
	17 putfield (0, 0)
	20 aload_0 (0, 0)
	21 dload (0, 0)
	23 dload_2 (0, 0)
	24 dsub (0, 0)
	25 putfield (0, 0)
	28 return (0, 0)

Method: getCoefficients
	0 aload_0 (0, 0)
	1 getfield (0, 0)
	4 areturn (0, 0)

Method: getRelationship
	0 aload_0 (0, 0)
	1 getfield (0, 0)
	4 areturn (0, 0)

Method: getValue
	0 aload_0 (0, 0)
	1 getfield (0, 0)
	4 dreturn (0, 0)

Method: equals
	0 aload_0 (1, 1)
	1 aload_1 (1, 1)
	2 if_acmpne (1, 1)
	5 iconst_1 (1, 1)
	6 ireturn (1, 1)
	7 aload_1 (1, 1)
	8 instanceof (1, 1)
	11 ifeq (1, 1)
	14 aload_1 (1, 1)
	15 checkcast (1, 1)
	18 astore_2 (1, 1)
	19 aload_0 (1, 1)
	20 getfield (1, 1)
	23 aload_2 (1, 1)
	24 getfield (1, 1)
	27 if_acmpne (1, 1)
	30 aload_0 (1, 1)
	31 getfield (1, 1)
	34 aload_2 (1, 1)
	35 getfield (1, 1)
	38 dcmpl (1, 1)
	39 ifne (1, 1)
	42 aload_0 (1, 1)
	43 getfield (1, 1)
	46 aload_2 (1, 1)
	47 getfield (1, 1)
	50 invokevirtual (1, 1)
	53 ifeq (1, 1)
	56 iconst_1 (1, 1)
	57 goto (1, 1)
	60 iconst_0 (1, 1)
	61 ireturn (1, 1)
	62 iconst_0 (0, 0)
	63 ireturn (0, 0)

Method: hashCode
	0 aload_0 (0, 0)
	1 getfield (0, 0)
	4 invokevirtual (0, 0)
	7 aload_0 (0, 0)
	8 getfield (0, 0)
	11 invokestatic (0, 0)
	14 invokevirtual (0, 0)
	17 ixor (0, 0)
	18 aload_0 (0, 0)
	19 getfield (0, 0)
	22 invokevirtual (0, 0)
	25 ixor (0, 0)
	26 ireturn (0, 0)

Method: writeObject
	0 aload_1 (0, 0)
	1 invokevirtual (0, 0)
	4 aload_0 (0, 0)
	5 getfield (0, 0)
	8 aload_1 (0, 0)
	9 invokestatic (0, 0)
	12 return (0, 0)

Method: readObject
	0 aload_1 (0, 0)
	1 invokevirtual (0, 0)
	4 aload_0 (0, 0)
	5 ldc (0, 0)
	7 aload_1 (0, 0)
	8 invokestatic (0, 0)
	11 return (0, 0)

