Method: <init>
	0 aload_0 (0, 0)
	1 invokespecial (0, 0)
	2 java/lang/Object.<init>:()V (0, 0)
	4 aload_0 (0, 0)
	5 aload_1 (0, 0)
	6 putfield (0, 0)
	7 org/apache/commons/math3/optim/linear/LinearObjectiveFunction.coefficients:Lorg/apache/commons/math3/linear/RealVector; (0, 0)
	9 aload_0 (0, 0)
	10 dload_2 (0, 0)
	11 putfield (0, 0)
	12 org/apache/commons/math3/optim/linear/LinearObjectiveFunction.constantTerm:D (0, 0)
	14 return (0, 0)

Method: getCoefficients
	0 aload_0 (0, 0)
	1 getfield (0, 0)
	2 org/apache/commons/math3/optim/linear/LinearObjectiveFunction.coefficients:Lorg/apache/commons/math3/linear/RealVector; (0, 0)
	4 areturn (0, 0)

Method: getConstantTerm
	0 aload_0 (0, 0)
	1 getfield (0, 0)
	2 org/apache/commons/math3/optim/linear/LinearObjectiveFunction.constantTerm:D (0, 0)
	4 dreturn (0, 0)

Method: value
	0 aload_0 (0, 0)
	1 getfield (0, 0)
	2 org/apache/commons/math3/optim/linear/LinearObjectiveFunction.coefficients:Lorg/apache/commons/math3/linear/RealVector; (0, 0)
	4 aload_1 (0, 0)
	5 invokevirtual (0, 0)
	6 org/apache/commons/math3/linear/RealVector.dotProduct:(Lorg/apache/commons/math3/linear/RealVector;)D (0, 0)
	8 aload_0 (0, 0)
	9 getfield (0, 0)
	10 org/apache/commons/math3/optim/linear/LinearObjectiveFunction.constantTerm:D (0, 0)
	12 dadd (0, 0)
	13 dreturn (0, 0)

Method: equals
	0 aload_0 (1, 1)
	1 aload_1 (1, 1)
	2 if_acmpne (1, 1)
	3 5 (1, 1)
	5 iconst_1 (1, 1)
	6 ireturn (1, 1)
	7 aload_1 (1, 1)
	8 instanceof (1, 1)
	9 org/apache/commons/math3/optim/linear/LinearObjectiveFunction (1, 1)
	11 ifeq (1, 1)
	12 40 (1, 1)
	14 aload_1 (1, 1)
	15 checkcast (1, 1)
	16 org/apache/commons/math3/optim/linear/LinearObjectiveFunction (1, 1)
	18 astore_2 (1, 1)
	19 aload_0 (1, 1)
	20 getfield (1, 1)
	21 org/apache/commons/math3/optim/linear/LinearObjectiveFunction.constantTerm:D (1, 1)
	23 aload_2 (1, 1)
	24 getfield (1, 1)
	25 org/apache/commons/math3/optim/linear/LinearObjectiveFunction.constantTerm:D (1, 1)
	27 dcmpl (1, 1)
	28 ifne (1, 1)
	29 21 (1, 1)
	31 aload_0 (1, 1)
	32 getfield (1, 1)
	33 org/apache/commons/math3/optim/linear/LinearObjectiveFunction.coefficients:Lorg/apache/commons/math3/linear/RealVector; (1, 1)
	35 aload_2 (1, 1)
	36 getfield (1, 1)
	37 org/apache/commons/math3/optim/linear/LinearObjectiveFunction.coefficients:Lorg/apache/commons/math3/linear/RealVector; (1, 1)
	39 invokevirtual (1, 1)
	40 org/apache/commons/math3/linear/RealVector.equals:(Ljava/lang/Object;)Z (1, 1)
	42 ifeq (1, 1)
	43 7 (1, 1)
	45 iconst_1 (1, 1)
	46 goto (1, 1)
	47 4 (1, 1)
	49 iconst_0 (1, 1)
	50 ireturn (1, 1)
	51 iconst_0 (0, 0)
	52 ireturn (0, 0)

Method: hashCode
	0 aload_0 (0, 0)
	1 getfield (0, 0)
	2 org/apache/commons/math3/optim/linear/LinearObjectiveFunction.constantTerm:D (0, 0)
	4 invokestatic (0, 0)
	5 java/lang/Double.valueOf:(D)Ljava/lang/Double; (0, 0)
	7 invokevirtual (0, 0)
	8 java/lang/Double.hashCode:()I (0, 0)
	10 aload_0 (0, 0)
	11 getfield (0, 0)
	12 org/apache/commons/math3/optim/linear/LinearObjectiveFunction.coefficients:Lorg/apache/commons/math3/linear/RealVector; (0, 0)
	14 invokevirtual (0, 0)
	15 org/apache/commons/math3/linear/RealVector.hashCode:()I (0, 0)
	17 ixor (0, 0)
	18 ireturn (0, 0)

Method: writeObject
	0 aload_1 (0, 0)
	1 invokevirtual (0, 0)
	2 java/io/ObjectOutputStream.defaultWriteObject:()V (0, 0)
	4 aload_0 (0, 0)
	5 getfield (0, 0)
	6 org/apache/commons/math3/optim/linear/LinearObjectiveFunction.coefficients:Lorg/apache/commons/math3/linear/RealVector; (0, 0)
	8 aload_1 (0, 0)
	9 invokestatic (0, 0)
	10 org/apache/commons/math3/linear/MatrixUtils.serializeRealVector:(Lorg/apache/commons/math3/linear/RealVector;Ljava/io/ObjectOutputStream;)V (0, 0)
	12 return (0, 0)

Method: readObject
	0 aload_1 (0, 0)
	1 invokevirtual (0, 0)
	2 java/io/ObjectInputStream.defaultReadObject:()V (0, 0)
	4 aload_0 (0, 0)
	5 ldc (0, 0)
	6 coefficients (0, 0)
	7 aload_1 (0, 0)
	8 invokestatic (0, 0)
	9 org/apache/commons/math3/linear/MatrixUtils.deserializeRealVector:(Ljava/lang/Object;Ljava/lang/String;Ljava/io/ObjectInputStream;)V (0, 0)
	11 return (0, 0)

