Method: <init>
	0 aload_0 (0, 0)
	1 aconst_null (0, 0)
	2 invokespecial (0, 0)
	3 org/apache/commons/math3/optim/nonlinear/scalar/MultivariateOptimizer.<init>:(Lorg/apache/commons/math3/optim/ConvergenceChecker;)V (0, 0)
	5 return (0, 0)

Method: isRestrictedToNonNegative
	0 aload_0 (0, 0)
	1 getfield (0, 0)
	2 org/apache/commons/math3/optim/linear/LinearOptimizer.nonNegative:Z (0, 0)
	4 ireturn (0, 0)

Method: getFunction
	0 aload_0 (0, 0)
	1 getfield (0, 0)
	2 org/apache/commons/math3/optim/linear/LinearOptimizer.function:Lorg/apache/commons/math3/optim/linear/LinearObjectiveFunction; (0, 0)
	4 areturn (0, 0)

Method: getConstraints
	0 aload_0 (1, 1)
	1 getfield (1, 1)
	2 org/apache/commons/math3/optim/linear/LinearOptimizer.linearConstraints:Ljava/util/Collection; (1, 1)
	4 invokestatic (1, 1)
	5 java/util/Collections.unmodifiableCollection:(Ljava/util/Collection;)Ljava/util/Collection; (1, 1)
	7 areturn (0, 1)

Method: optimize
	0 aload_0 (0, 0)
	1 aload_1 (0, 0)
	2 invokevirtual (0, 0)
	3 org/apache/commons/math3/optim/linear/LinearOptimizer.optimize:([Lorg/apache/commons/math3/optim/OptimizationData;)Lorg/apache/commons/math3/optim/PointValuePair; (0, 0)
	5 areturn (0, 0)

Method: parseOptimizationData
	0 aload_0 (0, 0)
	1 aload_1 (0, 0)
	2 invokespecial (0, 0)
	3 org/apache/commons/math3/optim/nonlinear/scalar/MultivariateOptimizer.parseOptimizationData:([Lorg/apache/commons/math3/optim/OptimizationData;)V (0, 0)
	5 aload_1 (2, 4)
	6 astore_2 (2, 4)
	7 aload_2 (2, 4)
	8 arraylength (2, 4)
	9 istore_3 (2, 4)
	10 iconst_0 (2, 4)
	11 istore (2, 4)
	12 #4 (2, 4)
	13 iload (2, 4)
	14 #4 (2, 4)
	15 iload_3 (2, 4)
	16 if_icmpge (2, 4)
	17 81 (2, 4)
	19 aload_2 (2, 4)
	20 iload (2, 4)
	21 #4 (2, 4)
	22 aaload (2, 4)
	23 astore (2, 4)
	24 #5 (2, 4)
	25 aload (3, 1)
	26 #5 (3, 1)
	27 instanceof (3, 1)
	28 org/apache/commons/math3/optim/linear/LinearObjectiveFunction (3, 1)
	30 ifeq (3, 1)
	31 15 (3, 1)
	33 aload_0 (3, 1)
	34 aload (3, 1)
	35 #5 (3, 1)
	36 checkcast (3, 1)
	37 org/apache/commons/math3/optim/linear/LinearObjectiveFunction (3, 1)
	39 putfield (3, 1)
	40 org/apache/commons/math3/optim/linear/LinearOptimizer.function:Lorg/apache/commons/math3/optim/linear/LinearObjectiveFunction; (3, 1)
	42 goto (3, 1)
	43 49 (3, 1)
	45 aload (3, 1)
	46 #5 (3, 1)
	47 instanceof (3, 1)
	48 org/apache/commons/math3/optim/linear/LinearConstraintSet (3, 1)
	50 ifeq (3, 1)
	51 18 (3, 1)
	53 aload_0 (3, 1)
	54 aload (3, 1)
	55 #5 (3, 1)
	56 checkcast (3, 1)
	57 org/apache/commons/math3/optim/linear/LinearConstraintSet (3, 1)
	59 invokevirtual (3, 1)
	60 org/apache/commons/math3/optim/linear/LinearConstraintSet.getConstraints:()Ljava/util/Collection; (3, 1)
	62 putfield (3, 1)
	63 org/apache/commons/math3/optim/linear/LinearOptimizer.linearConstraints:Ljava/util/Collection; (3, 1)
	65 goto (3, 1)
	66 26 (3, 1)
	68 aload (3, 1)
	69 #5 (3, 1)
	70 instanceof (3, 1)
	71 org/apache/commons/math3/optim/linear/NonNegativeConstraint (3, 1)
	73 ifeq (3, 1)
	74 18 (3, 1)
	76 aload_0 (3, 1)
	77 aload (3, 1)
	78 #5 (3, 1)
	79 checkcast (3, 1)
	80 org/apache/commons/math3/optim/linear/NonNegativeConstraint (3, 1)
	82 invokevirtual (3, 1)
	83 org/apache/commons/math3/optim/linear/NonNegativeConstraint.isRestrictedToNonNegative:()Z (3, 1)
	85 putfield (3, 1)
	86 org/apache/commons/math3/optim/linear/LinearOptimizer.nonNegative:Z (3, 1)
	88 goto (3, 1)
	89 3 (3, 1)
	91 iinc (3, 1)
	92 #4 (3, 1)
	93 -89 (3, 1)
	94 goto (3, 1)
	95 -81 (3, 1)
	97 return (0, 1)

