Method: <init>
	0 aload_0 (0, 0)
	1 invokespecial (0, 0)
	4 aload_0 (0, 0)
	5 new (0, 0)
	8 dup (0, 0)
	9 invokespecial (0, 0)
	12 putfield (0, 0)
	15 aload_0 (1, 4)
	16 aload_1 (1, 4)
	17 putfield (1, 4)
	20 aload_0 (1, 4)
	21 aload_0 (1, 4)
	22 aload_2 (1, 4)
	23 invokevirtual (1, 4)
	26 putfield (1, 4)
	29 aload_0 (1, 4)
	30 iload (1, 4)
	32 putfield (1, 4)
	35 aload_0 (1, 4)
	36 dload (1, 4)
	38 putfield (1, 4)
	41 aload_0 (1, 4)
	42 iload (1, 4)
	44 putfield (1, 4)
	47 aload_0 (1, 4)
	48 aload_1 (1, 4)
	49 invokevirtual (1, 4)
	52 invokevirtual (1, 4)
	55 iload (1, 4)
	57 ifeq (1, 4)
	60 iconst_0 (1, 4)
	61 goto (1, 4)
	64 iconst_1 (1, 4)
	65 iadd (1, 4)
	66 putfield (1, 4)
	69 aload_0 (1, 4)
	70 aload_0 (1, 4)
	71 getstatic (1, 4)
	74 invokespecial (1, 4)
	77 aload_0 (1, 4)
	78 getstatic (1, 4)
	81 invokespecial (1, 4)
	84 iadd (1, 4)
	85 putfield (1, 4)
	88 aload_0 (1, 1)
	89 aload_0 (1, 1)
	90 getstatic (1, 1)
	93 invokespecial (1, 1)
	96 aload_0 (1, 1)
	97 getstatic (1, 1)
	100 invokespecial (1, 1)
	103 iadd (1, 1)
	104 putfield (1, 1)
	107 aload_0 (1, 1)
	108 aload_0 (1, 1)
	109 aload_3 (1, 1)
	110 getstatic (1, 1)
	113 if_acmpne (1, 1)
	116 iconst_1 (1, 1)
	117 goto (1, 1)
	120 iconst_0 (1, 1)
	121 invokevirtual (1, 1)
	124 putfield (1, 1)
	127 aload_0 (1, 1)
	128 aload_0 (1, 1)
	129 invokevirtual (1, 1)
	132 invokespecial (1, 1)
	135 aload_0 (1, 1)
	136 invokevirtual (1, 1)
	139 return (0, 4)

Method: initializeColumnLabels
	0 aload_0 (1, 1)
	1 invokevirtual (1, 1)
	4 iconst_2 (1, 1)
	5 if_icmpne (1, 1)
	8 aload_0 (1, 1)
	9 getfield (1, 1)
	12 ldc (1, 1)
	14 invokeinterface (1, 1)
	19 pop (1, 1)
	20 aload_0 (0, 0)
	21 getfield (0, 0)
	24 ldc (0, 0)
	26 invokeinterface (0, 0)
	31 pop (0, 0)
	32 iconst_0 (1, 4)
	33 istore_1 (1, 4)
	34 iload_1 (1, 4)
	35 aload_0 (1, 4)
	36 invokevirtual (1, 4)
	39 if_icmpge (1, 4)
	42 aload_0 (1, 4)
	43 getfield (1, 4)
	46 new (1, 4)
	49 dup (1, 4)
	50 invokespecial (1, 4)
	53 ldc (1, 4)
	55 invokevirtual (1, 4)
	58 iload_1 (1, 4)
	59 invokevirtual (1, 4)
	62 invokevirtual (1, 4)
	65 invokeinterface (1, 4)
	70 pop (1, 4)
	71 iinc (1, 4)
	74 goto (1, 4)
	77 aload_0 (1, 1)
	78 getfield (1, 1)
	81 ifne (1, 1)
	84 aload_0 (1, 1)
	85 getfield (1, 1)
	88 ldc (1, 1)
	90 invokeinterface (1, 1)
	95 pop (1, 1)
	96 iconst_0 (1, 4)
	97 istore_1 (1, 4)
	98 iload_1 (1, 4)
	99 aload_0 (1, 4)
	100 invokevirtual (1, 4)
	103 if_icmpge (1, 4)
	106 aload_0 (1, 4)
	107 getfield (1, 4)
	110 new (1, 4)
	113 dup (1, 4)
	114 invokespecial (1, 4)
	117 ldc (1, 4)
	119 invokevirtual (1, 4)
	122 iload_1 (1, 4)
	123 invokevirtual (1, 4)
	126 invokevirtual (1, 4)
	129 invokeinterface (1, 4)
	134 pop (1, 4)
	135 iinc (1, 4)
	138 goto (1, 4)
	141 iconst_0 (1, 1)
	142 istore_1 (1, 1)
	143 iload_1 (1, 1)
	144 aload_0 (1, 1)
	145 invokevirtual (1, 1)
	148 if_icmpge (1, 1)
	151 aload_0 (1, 1)
	152 getfield (1, 1)
	155 new (1, 1)
	158 dup (1, 1)
	159 invokespecial (1, 1)
	162 ldc (1, 1)
	164 invokevirtual (1, 1)
	167 iload_1 (1, 1)
	168 invokevirtual (1, 1)
	171 invokevirtual (1, 1)
	174 invokeinterface (1, 1)
	179 pop (1, 1)
	180 iinc (1, 1)
	183 goto (1, 1)
	186 aload_0 (0, 0)
	187 getfield (0, 0)
	190 ldc (0, 0)
	192 invokeinterface (0, 0)
	197 pop (0, 0)
	198 return (0, 0)

Method: createTableau
	0 aload_0 (0, 0)
	1 getfield (0, 0)
	4 aload_0 (0, 0)
	5 getfield (0, 0)
	8 iadd (0, 0)
	9 aload_0 (0, 0)
	10 getfield (0, 0)
	13 iadd (0, 0)
	14 aload_0 (0, 0)
	15 invokevirtual (0, 1)
	18 iadd (0, 1)
	19 iconst_1 (0, 1)
	20 iadd (0, 1)
	21 istore_2 (0, 1)
	22 aload_0 (0, 1)
	23 getfield (0, 1)
	26 invokeinterface (0, 1)
	31 aload_0 (0, 1)
	32 invokevirtual (0, 1)
	35 iadd (0, 1)
	36 istore_3 (0, 1)
	37 new (0, 1)
	40 dup (0, 1)
	41 iload_3 (0, 1)
	42 iload_2 (0, 1)
	43 invokespecial (0, 1)
	46 astore (0, 1)
	48 aload_0 (1, 1)
	49 invokevirtual (1, 1)
	52 iconst_2 (1, 1)
	53 if_icmpne (1, 1)
	56 aload (1, 1)
	58 iconst_0 (1, 1)
	59 iconst_0 (1, 1)
	60 ldc2_w (1, 1)
	63 invokevirtual (1, 1)
	66 aload_0 (0, 1)
	67 invokevirtual (0, 1)
	70 iconst_1 (0, 1)
	71 if_icmpne (0, 1)
	74 iconst_0 (0, 1)
	75 goto (0, 1)
	78 iconst_1 (0, 1)
	79 istore (0, 1)
	81 aload (0, 1)
	83 iload (0, 1)
	85 iload (0, 1)
	87 iload_1 (0, 1)
	88 ifeq (0, 1)
	91 dconst_1 (0, 1)
	92 goto (0, 1)
	95 ldc2_w (0, 1)
	98 invokevirtual (0, 1)
	101 iload_1 (0, 1)
	102 ifeq (0, 1)
	105 aload_0 (0, 1)
	106 getfield (0, 1)
	109 invokevirtual (0, 1)
	112 ldc2_w (0, 1)
	115 invokevirtual (0, 1)
	118 goto (0, 1)
	121 aload_0 (0, 1)
	122 getfield (0, 1)
	125 invokevirtual (0, 1)
	128 astore (0, 1)
	130 aload_0 (0, 1)
	131 aload (0, 1)
	133 invokevirtual (0, 1)
	136 aload (0, 1)
	138 invokevirtual (0, 1)
	141 iload (0, 1)
	143 aaload (0, 1)
	144 invokespecial (0, 1)
	147 aload (0, 1)
	149 iload (0, 1)
	151 iload_2 (0, 1)
	152 iconst_1 (0, 1)
	153 isub (0, 1)
	154 iload_1 (0, 1)
	155 ifeq (0, 1)
	158 aload_0 (0, 1)
	159 getfield (0, 1)
	162 invokevirtual (0, 1)
	165 goto (0, 1)
	168 ldc2_w (0, 1)
	171 aload_0 (0, 1)
	172 getfield (0, 1)
	175 invokevirtual (0, 1)
	178 dmul (0, 1)
	179 invokevirtual (0, 1)
	182 aload_0 (1, 1)
	183 getfield (1, 1)
	186 ifne (1, 1)
	189 aload (1, 1)
	191 iload (1, 1)
	193 aload_0 (1, 1)
	194 invokevirtual (1, 1)
	197 iconst_1 (1, 1)
	198 isub (1, 1)
	199 aload (1, 1)
	201 invokestatic (1, 1)
	204 invokevirtual (1, 1)
	207 iconst_0 (0, 1)
	208 istore (0, 1)
	210 iconst_0 (0, 1)
	211 istore (0, 1)
	213 iconst_0 (1, 4)
	214 istore (1, 4)
	216 iload (1, 4)
	218 aload_0 (1, 4)
	219 getfield (1, 4)
	222 invokeinterface (1, 4)
	227 if_icmpge (1, 4)
	230 aload_0 (1, 4)
	231 getfield (1, 4)
	234 iload (1, 4)
	236 invokeinterface (1, 4)
	241 checkcast (1, 4)
	244 astore (1, 4)
	246 aload_0 (1, 4)
	247 invokevirtual (1, 4)
	250 iload (1, 4)
	252 iadd (1, 4)
	253 istore (1, 4)
	255 aload_0 (1, 4)
	256 aload (1, 4)
	258 invokevirtual (1, 4)
	261 invokevirtual (1, 4)
	264 aload (1, 4)
	266 invokevirtual (1, 4)
	269 iload (1, 4)
	271 aaload (1, 4)
	272 invokespecial (1, 4)
	275 aload_0 (2, 1)
	276 getfield (2, 1)
	279 ifne (2, 1)
	282 aload (2, 1)
	284 iload (2, 1)
	286 aload_0 (2, 1)
	287 invokevirtual (2, 1)
	290 iconst_1 (2, 1)
	291 isub (2, 1)
	292 aload (2, 1)
	294 invokevirtual (2, 1)
	297 invokestatic (2, 1)
	300 invokevirtual (2, 1)
	303 aload (1, 4)
	305 iload (1, 4)
	307 iload_2 (1, 4)
	308 iconst_1 (1, 4)
	309 isub (1, 4)
	310 aload (1, 4)
	312 invokevirtual (1, 4)
	315 invokevirtual (1, 4)
	318 aload (2, 1)
	320 invokevirtual (2, 1)
	323 getstatic (2, 1)
	326 if_acmpne (2, 1)
	329 aload (2, 1)
	331 iload (2, 1)
	333 aload_0 (2, 1)
	334 invokevirtual (2, 1)
	337 iload (2, 1)
	339 iinc (2, 1)
	342 iadd (2, 1)
	343 dconst_1 (2, 1)
	344 invokevirtual (2, 1)
	347 goto (2, 1)
	350 aload (2, 1)
	352 invokevirtual (2, 1)
	355 getstatic (2, 1)
	358 if_acmpne (2, 1)
	361 aload (2, 1)
	363 iload (2, 1)
	365 aload_0 (2, 1)
	366 invokevirtual (2, 1)
	369 iload (2, 1)
	371 iinc (2, 1)
	374 iadd (2, 1)
	375 ldc2_w (2, 1)
	378 invokevirtual (2, 1)
	381 aload (1, 1)
	383 invokevirtual (1, 1)
	386 getstatic (1, 1)
	389 if_acmpeq (1, 1)
	392 aload (1, 1)
	394 invokevirtual (2, 1)
	397 getstatic (2, 1)
	400 if_acmpne (2, 1)
	403 aload (2, 1)
	405 iconst_0 (2, 1)
	406 aload_0 (2, 1)
	407 invokevirtual (2, 1)
	410 iload (2, 1)
	412 iadd (2, 1)
	413 dconst_1 (2, 1)
	414 invokevirtual (2, 1)
	417 aload (2, 1)
	419 iload (2, 1)
	421 aload_0 (2, 1)
	422 invokevirtual (2, 1)
	425 iload (2, 1)
	427 iinc (2, 1)
	430 iadd (2, 1)
	431 dconst_1 (2, 1)
	432 invokevirtual (2, 1)
	435 aload (2, 1)
	437 iconst_0 (2, 1)
	438 aload (2, 1)
	440 iconst_0 (2, 1)
	441 invokevirtual (2, 1)
	444 aload (2, 1)
	446 iload (2, 1)
	448 invokevirtual (2, 1)
	451 invokevirtual (2, 1)
	454 invokevirtual (2, 1)
	457 iinc (2, 1)
	460 goto (2, 1)
	463 aload (1, 1)
	465 areturn (1, 1)

Method: normalizeConstraints
	0 new (0, 0)
	3 dup (0, 0)
	4 aload_1 (0, 0)
	5 invokeinterface (0, 0)
	10 invokespecial (0, 0)
	13 astore_2 (0, 0)
	14 aload_1 (1, 4)
	15 invokeinterface (1, 4)
	20 astore_3 (1, 4)
	21 aload_3 (1, 4)
	22 invokeinterface (1, 4)
	27 ifeq (1, 4)
	30 aload_3 (1, 4)
	31 invokeinterface (1, 4)
	36 checkcast (1, 4)
	39 astore (1, 4)
	41 aload_2 (1, 4)
	42 aload_0 (1, 4)
	43 aload (1, 4)
	45 invokespecial (1, 4)
	48 invokeinterface (1, 4)
	53 pop (1, 4)
	54 goto (0, 0)
	57 aload_2 (0, 0)
	58 areturn (0, 0)

Method: normalize
	0 aload_1 (1, 1)
	1 invokevirtual (1, 1)
	4 dconst_0 (1, 1)
	5 dcmpg (1, 1)
	6 ifge (1, 1)
	9 new (1, 1)
	12 dup (1, 1)
	13 aload_1 (1, 1)
	14 invokevirtual (1, 1)
	17 ldc2_w (1, 1)
	20 invokevirtual (1, 1)
	23 aload_1 (1, 1)
	24 invokevirtual (1, 1)
	27 invokevirtual (1, 1)
	30 ldc2_w (1, 1)
	33 aload_1 (1, 1)
	34 invokevirtual (1, 1)
	37 dmul (1, 1)
	38 invokespecial (1, 1)
	41 areturn (1, 1)
	42 new (0, 0)
	45 dup (0, 0)
	46 aload_1 (0, 0)
	47 invokevirtual (0, 0)
	50 aload_1 (0, 0)
	51 invokevirtual (0, 0)
	54 aload_1 (0, 0)
	55 invokevirtual (0, 0)
	58 invokespecial (0, 0)
	61 areturn (0, 0)

Method: getNumObjectiveFunctions
	0 aload_0 (0, 1)
	1 getfield (0, 1)
	4 ifle (0, 1)
	7 iconst_2 (0, 1)
	8 goto (0, 1)
	11 iconst_1 (0, 1)
	12 ireturn (0, 1)

Method: getConstraintTypeCounts
	0 iconst_0 (0, 0)
	1 istore_2 (0, 0)
	2 aload_0 (1, 4)
	3 getfield (1, 4)
	6 invokeinterface (1, 4)
	11 astore_3 (1, 4)
	12 aload_3 (1, 4)
	13 invokeinterface (1, 4)
	18 ifeq (1, 4)
	21 aload_3 (1, 4)
	22 invokeinterface (1, 4)
	27 checkcast (1, 4)
	30 astore (1, 4)
	32 aload (2, 1)
	34 invokevirtual (2, 1)
	37 aload_1 (2, 1)
	38 if_acmpne (2, 1)
	41 iinc (2, 1)
	44 goto (0, 0)
	47 iload_2 (0, 0)
	48 ireturn (0, 0)

Method: getInvertedCoefficientSum
	0 dconst_0 (0, 0)
	1 dstore_1 (0, 0)
	2 aload_0 (1, 4)
	3 invokevirtual (1, 4)
	6 astore_3 (1, 4)
	7 aload_3 (1, 4)
	8 arraylength (1, 4)
	9 istore (1, 4)
	11 iconst_0 (1, 4)
	12 istore (1, 4)
	14 iload (1, 4)
	16 iload (1, 4)
	18 if_icmpge (1, 4)
	21 aload_3 (1, 4)
	22 iload (1, 4)
	24 daload (1, 4)
	25 dstore (1, 4)
	27 dload_1 (1, 4)
	28 dload (1, 4)
	30 dsub (1, 4)
	31 dstore_1 (1, 4)
	32 iinc (1, 4)
	35 goto (1, 4)
	38 dload_1 (0, 0)
	39 dreturn (0, 0)

Method: getBasicRow
	0 aload_0 (0, 0)
	1 getfield (0, 0)
	4 iload_1 (0, 0)
	5 iaload (0, 0)
	6 istore_2 (0, 0)
	7 iload_2 (0, 0)
	8 iconst_m1 (0, 0)
	9 if_icmpne (0, 0)
	12 aconst_null (0, 0)
	13 goto (0, 0)
	16 iload_2 (0, 0)
	17 invokestatic (0, 0)
	20 areturn (0, 0)

Method: getBasicVariable
	0 aload_0 (0, 0)
	1 getfield (0, 0)
	4 iload_1 (0, 0)
	5 iaload (0, 0)
	6 ireturn (0, 0)

Method: initializeBasicVariables
	0 aload_0 (0, 0)
	1 aload_0 (0, 0)
	2 invokevirtual (0, 0)
	5 iconst_1 (0, 0)
	6 isub (0, 0)
	7 newarray (0, 0)
	9 putfield (0, 0)
	12 aload_0 (0, 0)
	13 aload_0 (0, 0)
	14 invokevirtual (0, 0)
	17 newarray (0, 0)
	19 putfield (0, 0)
	22 aload_0 (0, 0)
	23 getfield (0, 0)
	26 iconst_m1 (0, 0)
	27 invokestatic (0, 0)
	30 iload_1 (1, 4)
	31 istore_2 (1, 4)
	32 iload_2 (1, 4)
	33 aload_0 (1, 4)
	34 invokevirtual (1, 4)
	37 iconst_1 (1, 4)
	38 isub (1, 4)
	39 if_icmpge (1, 4)
	42 aload_0 (1, 4)
	43 iload_2 (1, 4)
	44 invokespecial (1, 4)
	47 astore_3 (1, 4)
	48 aload_3 (2, 1)
	49 ifnull (2, 1)
	52 aload_0 (2, 1)
	53 getfield (2, 1)
	56 iload_2 (2, 1)
	57 aload_3 (2, 1)
	58 invokevirtual (2, 1)
	61 iastore (2, 1)
	62 aload_0 (2, 1)
	63 getfield (2, 1)
	66 aload_3 (2, 1)
	67 invokevirtual (2, 1)
	70 iload_2 (2, 1)
	71 iastore (2, 1)
	72 iinc (2, 1)
	75 goto (2, 1)
	78 return (0, 0)

Method: findBasicRow
	0 aconst_null (0, 0)
	1 astore_2 (0, 0)
	2 iconst_0 (1, 4)
	3 istore_3 (1, 4)
	4 iload_3 (1, 4)
	5 aload_0 (1, 4)
	6 invokevirtual (1, 4)
	9 if_icmpge (1, 4)
	12 aload_0 (1, 4)
	13 iload_3 (1, 4)
	14 iload_1 (1, 4)
	15 invokevirtual (1, 4)
	18 dstore (1, 4)
	20 dload (2, 1)
	22 dconst_1 (2, 1)
	23 aload_0 (2, 1)
	24 getfield (2, 1)
	27 invokestatic (2, 1)
	30 ifeq (2, 1)
	33 aload_2 (2, 1)
	34 ifnonnull (2, 1)
	37 iload_3 (2, 1)
	38 invokestatic (2, 1)
	41 astore_2 (2, 1)
	42 goto (2, 1)
	45 dload (2, 1)
	47 dconst_0 (2, 1)
	48 aload_0 (2, 1)
	49 getfield (2, 1)
	52 invokestatic (2, 1)
	55 ifne (2, 1)
	58 aconst_null (2, 1)
	59 areturn (2, 1)
	60 iinc (2, 1)
	63 goto (2, 1)
	66 aload_2 (1, 1)
	67 areturn (1, 1)

Method: dropPhase1Objective
	0 aload_0 (1, 1)
	1 invokevirtual (1, 1)
	4 iconst_1 (1, 1)
	5 if_icmpne (1, 1)
	8 return (1, 1)
	9 new (0, 0)
	12 dup (0, 0)
	13 invokespecial (0, 0)
	16 astore_1 (0, 0)
	17 aload_1 (0, 0)
	18 iconst_0 (0, 0)
	19 invokestatic (0, 0)
	22 invokeinterface (0, 0)
	27 pop (0, 0)
	28 aload_0 (1, 1)
	29 invokevirtual (1, 1)
	32 istore_2 (1, 1)
	33 iload_2 (1, 1)
	34 aload_0 (1, 1)
	35 invokevirtual (1, 1)
	38 if_icmpge (1, 1)
	41 aload_0 (1, 1)
	42 iconst_0 (1, 1)
	43 iload_2 (1, 1)
	44 invokevirtual (1, 1)
	47 dstore_3 (1, 1)
	48 dload_3 (2, 1)
	49 dconst_0 (2, 1)
	50 aload_0 (2, 1)
	51 getfield (2, 1)
	54 invokestatic (2, 1)
	57 ifle (2, 1)
	60 aload_1 (2, 1)
	61 iload_2 (2, 1)
	62 invokestatic (2, 1)
	65 invokeinterface (2, 1)
	70 pop (2, 1)
	71 iinc (2, 1)
	74 goto (2, 1)
	77 iconst_0 (2, 1)
	78 istore_2 (2, 1)
	79 iload_2 (2, 1)
	80 aload_0 (2, 1)
	81 invokevirtual (2, 1)
	84 if_icmpge (2, 1)
	87 iload_2 (2, 1)
	88 aload_0 (2, 1)
	89 invokevirtual (2, 1)
	92 iadd (2, 1)
	93 istore_3 (2, 1)
	94 aload_0 (3, 1)
	95 iload_3 (3, 1)
	96 invokevirtual (3, 1)
	99 ifnonnull (3, 1)
	102 aload_1 (3, 1)
	103 iload_3 (3, 1)
	104 invokestatic (3, 1)
	107 invokeinterface (3, 1)
	112 pop (3, 1)
	113 iinc (3, 1)
	116 goto (3, 1)
	119 aload_0 (2, 1)
	120 invokevirtual (2, 1)
	123 iconst_1 (2, 1)
	124 isub (2, 1)
	125 aload_0 (2, 1)
	126 invokevirtual (2, 1)
	129 aload_1 (2, 1)
	130 invokeinterface (2, 1)
	135 isub (2, 1)
	136 multianewarray (2, 1)
	140 astore_2 (2, 1)
	141 iconst_1 (3, 4)
	142 istore_3 (3, 4)
	143 iload_3 (3, 4)
	144 aload_0 (3, 4)
	145 invokevirtual (3, 4)
	148 if_icmpge (3, 4)
	151 iconst_0 (3, 4)
	152 istore (3, 4)
	154 iconst_0 (4, 4)
	155 istore (4, 4)
	157 iload (4, 4)
	159 aload_0 (4, 4)
	160 invokevirtual (4, 4)
	163 if_icmpge (4, 4)
	166 aload_1 (5, 1)
	167 iload (5, 1)
	169 invokestatic (5, 1)
	172 invokeinterface (5, 1)
	177 ifne (5, 1)
	180 aload_2 (5, 1)
	181 iload_3 (5, 1)
	182 iconst_1 (5, 1)
	183 isub (5, 1)
	184 aaload (5, 1)
	185 iload (5, 1)
	187 iinc (5, 1)
	190 aload_0 (5, 1)
	191 iload_3 (5, 1)
	192 iload (5, 1)
	194 invokevirtual (5, 1)
	197 dastore (5, 1)
	198 iinc (5, 1)
	201 goto (5, 1)
	204 iinc (5, 1)
	207 goto (5, 1)
	210 aload_1 (4, 4)
	211 aload_1 (4, 4)
	212 invokeinterface (4, 4)
	217 anewarray (4, 4)
	220 invokeinterface (4, 4)
	225 checkcast (4, 4)
	228 astore_3 (4, 4)
	229 aload_3 (5, 4)
	230 arraylength (5, 4)
	231 iconst_1 (5, 4)
	232 isub (5, 4)
	233 istore (5, 4)
	235 iload (5, 4)
	237 iflt (5, 4)
	240 aload_0 (5, 4)
	241 getfield (5, 4)
	244 aload_3 (5, 4)
	245 iload (5, 4)
	247 aaload (5, 4)
	248 invokevirtual (5, 4)
	251 invokeinterface (5, 4)
	256 pop (5, 4)
	257 iinc (5, 4)
	260 goto (5, 4)
	263 aload_0 (4, 4)
	264 new (4, 4)
	267 dup (4, 4)
	268 aload_2 (4, 4)
	269 invokespecial (4, 4)
	272 putfield (4, 4)
	275 aload_0 (4, 1)
	276 iconst_0 (4, 1)
	277 putfield (4, 1)
	280 aload_0 (4, 1)
	281 aload_0 (4, 1)
	282 invokevirtual (4, 1)
	285 invokespecial (4, 1)
	288 return (3, 4)

Method: copyArray
	0 aload_1 (0, 0)
	1 iconst_0 (0, 0)
	2 aload_2 (0, 0)
	3 aload_0 (0, 0)
	4 invokevirtual (0, 0)
	7 aload_1 (0, 0)
	8 arraylength (0, 0)
	9 invokestatic (0, 0)
	12 return (0, 0)

Method: isOptimal
	0 aload_0 (0, 0)
	1 iconst_0 (0, 0)
	2 invokevirtual (0, 0)
	5 astore_1 (0, 0)
	6 aload_0 (0, 0)
	7 invokevirtual (0, 0)
	10 istore_2 (0, 0)
	11 aload_0 (1, 4)
	12 invokevirtual (1, 4)
	15 istore_3 (1, 4)
	16 iload_3 (1, 4)
	17 iload_2 (1, 4)
	18 if_icmpge (1, 4)
	21 aload_1 (1, 4)
	22 iload_3 (1, 4)
	23 daload (1, 4)
	24 dstore (1, 4)
	26 dload (2, 1)
	28 dconst_0 (2, 1)
	29 aload_0 (2, 1)
	30 getfield (2, 1)
	33 invokestatic (2, 1)
	36 ifge (2, 1)
	39 iconst_0 (2, 1)
	40 ireturn (2, 1)
	41 iinc (2, 1)
	44 goto (2, 1)
	47 iconst_1 (1, 4)
	48 ireturn (1, 4)

Method: getSolution
	0 aload_0 (0, 0)
	1 getfield (0, 0)
	4 ldc (0, 0)
	6 invokeinterface (0, 0)
	11 istore_1 (0, 0)
	12 iload_1 (0, 0)
	13 ifle (0, 0)
	16 aload_0 (0, 0)
	17 iload_1 (0, 0)
	18 invokevirtual (0, 0)
	21 goto (0, 0)
	24 aconst_null (0, 0)
	25 astore_2 (0, 0)
	26 aload_2 (0, 0)
	27 ifnonnull (0, 0)
	30 dconst_0 (0, 0)
	31 goto (0, 0)
	34 aload_0 (0, 0)
	35 aload_2 (0, 0)
	36 invokevirtual (0, 0)
	39 aload_0 (0, 0)
	40 invokevirtual (0, 0)
	43 invokevirtual (0, 0)
	46 dstore_3 (0, 0)
	47 new (0, 0)
	50 dup (0, 0)
	51 invokespecial (0, 0)
	54 astore (0, 0)
	56 aload_0 (0, 0)
	57 invokevirtual (0, 0)
	60 newarray (0, 0)
	62 astore (0, 0)
	64 iconst_0 (1, 4)
	65 istore (1, 4)
	67 iload (1, 4)
	69 aload (1, 4)
	71 arraylength (1, 4)
	72 if_icmpge (1, 4)
	75 aload_0 (1, 4)
	76 getfield (1, 4)
	79 new (1, 4)
	82 dup (1, 4)
	83 invokespecial (1, 4)
	86 ldc (1, 4)
	88 invokevirtual (1, 4)
	91 iload (1, 4)
	93 invokevirtual (1, 4)
	96 invokevirtual (1, 4)
	99 invokeinterface (1, 4)
	104 istore (1, 4)
	106 iload (2, 1)
	108 ifge (2, 1)
	111 aload (2, 1)
	113 iload (2, 1)
	115 dconst_0 (2, 1)
	116 dastore (2, 1)
	117 goto (2, 1)
	120 aload_0 (1, 4)
	121 iload (1, 4)
	123 invokevirtual (1, 4)
	126 astore (1, 4)
	128 aload (2, 1)
	130 ifnull (2, 1)
	133 aload (2, 1)
	135 invokevirtual (2, 1)
	138 ifne (2, 1)
	141 aload (2, 1)
	143 iload (2, 1)
	145 dconst_0 (2, 1)
	146 dastore (2, 1)
	147 goto (2, 1)
	150 aload (2, 1)
	152 aload (2, 1)
	154 invokeinterface (2, 1)
	159 ifeq (2, 1)
	162 aload (2, 1)
	164 iload (2, 1)
	166 dconst_0 (2, 1)
	167 aload_0 (2, 1)
	168 getfield (2, 1)
	171 ifeq (2, 1)
	174 dconst_0 (2, 1)
	175 goto (2, 1)
	178 dload_3 (2, 1)
	179 dsub (2, 1)
	180 dastore (2, 1)
	181 goto (2, 1)
	184 aload (2, 2)
	186 aload (2, 2)
	188 invokeinterface (2, 2)
	193 pop (2, 2)
	194 aload (2, 2)
	196 iload (2, 2)
	198 aload (2, 2)
	200 ifnonnull (2, 2)
	203 dconst_0 (2, 2)
	204 goto (2, 2)
	207 aload_0 (2, 2)
	208 aload (2, 2)
	210 invokevirtual (2, 2)
	213 aload_0 (2, 2)
	214 invokevirtual (2, 2)
	217 invokevirtual (2, 2)
	220 aload_0 (2, 2)
	221 getfield (2, 2)
	224 ifeq (2, 2)
	227 dconst_0 (2, 2)
	228 goto (2, 2)
	231 dload_3 (2, 2)
	232 dsub (2, 2)
	233 dastore (2, 2)
	234 iinc (2, 2)
	237 goto (2, 2)
	240 new (1, 1)
	243 dup (1, 1)
	244 aload (1, 1)
	246 aload_0 (1, 1)
	247 getfield (1, 1)
	250 aload (1, 1)
	252 invokevirtual (1, 1)
	255 invokespecial (1, 1)
	258 areturn (1, 1)

Method: performRowOperations
	0 aload_0 (0, 0)
	1 iload_2 (0, 0)
	2 iload_1 (0, 0)
	3 invokevirtual (0, 0)
	6 dstore_3 (0, 0)
	7 aload_0 (0, 0)
	8 iload_2 (0, 0)
	9 dload_3 (0, 0)
	10 invokevirtual (0, 0)
	13 iconst_0 (1, 4)
	14 istore (1, 4)
	16 iload (1, 4)
	18 aload_0 (1, 4)
	19 invokevirtual (1, 4)
	22 if_icmpge (1, 4)
	25 iload (2, 1)
	27 iload_2 (2, 1)
	28 if_icmpeq (2, 1)
	31 aload_0 (2, 1)
	32 iload (2, 1)
	34 iload_1 (2, 1)
	35 invokevirtual (2, 1)
	38 dstore (2, 1)
	40 dload (3, 1)
	42 dconst_0 (3, 1)
	43 dcmpl (3, 1)
	44 ifeq (3, 1)
	47 aload_0 (3, 1)
	48 iload (3, 1)
	50 iload_2 (3, 1)
	51 dload (3, 1)
	53 invokevirtual (3, 1)
	56 iinc (3, 1)
	59 goto (3, 1)
	62 aload_0 (2, 1)
	63 iload_2 (2, 1)
	64 invokevirtual (2, 1)
	67 istore (2, 1)
	69 aload_0 (2, 1)
	70 getfield (2, 1)
	73 iload (2, 1)
	75 iconst_m1 (2, 1)
	76 iastore (2, 1)
	77 aload_0 (2, 1)
	78 getfield (2, 1)
	81 iload_1 (2, 1)
	82 iload_2 (2, 1)
	83 iastore (2, 1)
	84 aload_0 (2, 1)
	85 getfield (2, 1)
	88 iload_2 (2, 1)
	89 iload_1 (2, 1)
	90 iastore (2, 1)
	91 return (1, 4)

Method: divideRow
	0 aload_0 (0, 0)
	1 iload_1 (0, 0)
	2 invokevirtual (0, 0)
	5 astore (0, 0)
	7 iconst_0 (1, 4)
	8 istore (1, 4)
	10 iload (1, 4)
	12 aload_0 (1, 4)
	13 invokevirtual (1, 4)
	16 if_icmpge (1, 4)
	19 aload (1, 4)
	21 iload (1, 4)
	23 dup2 (1, 4)
	24 daload (1, 4)
	25 dload_2 (1, 4)
	26 ddiv (1, 4)
	27 dastore (1, 4)
	28 iinc (1, 4)
	31 goto (1, 4)
	34 return (0, 0)

Method: subtractRow
	0 aload_0 (0, 0)
	1 iload_1 (0, 0)
	2 invokevirtual (0, 0)
	5 astore (0, 0)
	7 aload_0 (0, 0)
	8 iload_2 (0, 0)
	9 invokevirtual (0, 0)
	12 astore (0, 0)
	14 iconst_0 (1, 4)
	15 istore (1, 4)
	17 iload (1, 4)
	19 aload_0 (1, 4)
	20 invokevirtual (1, 4)
	23 if_icmpge (1, 4)
	26 aload (1, 4)
	28 iload (1, 4)
	30 dup2 (1, 4)
	31 daload (1, 4)
	32 aload (1, 4)
	34 iload (1, 4)
	36 daload (1, 4)
	37 dload_3 (1, 4)
	38 dmul (1, 4)
	39 dsub (1, 4)
	40 dastore (1, 4)
	41 iinc (1, 4)
	44 goto (1, 4)
	47 return (0, 0)

Method: getWidth
	0 aload_0 (0, 0)
	1 getfield (0, 0)
	4 invokevirtual (0, 0)
	7 ireturn (0, 0)

Method: getHeight
	0 aload_0 (0, 0)
	1 getfield (0, 0)
	4 invokevirtual (0, 0)
	7 ireturn (0, 0)

Method: getEntry
	0 aload_0 (0, 0)
	1 getfield (0, 0)
	4 iload_1 (0, 0)
	5 iload_2 (0, 0)
	6 invokevirtual (0, 0)
	9 dreturn (0, 0)

Method: setEntry
	0 aload_0 (0, 0)
	1 getfield (0, 0)
	4 iload_1 (0, 0)
	5 iload_2 (0, 0)
	6 dload_3 (0, 0)
	7 invokevirtual (0, 0)
	10 return (0, 0)

Method: getSlackVariableOffset
	0 aload_0 (0, 0)
	1 invokevirtual (0, 0)
	4 aload_0 (0, 0)
	5 getfield (0, 0)
	8 iadd (0, 0)
	9 ireturn (0, 0)

Method: getArtificialVariableOffset
	0 aload_0 (0, 0)
	1 invokevirtual (0, 0)
	4 aload_0 (0, 0)
	5 getfield (0, 0)
	8 iadd (0, 0)
	9 aload_0 (0, 0)
	10 getfield (0, 0)
	13 iadd (0, 0)
	14 ireturn (0, 0)

Method: getRhsOffset
	0 aload_0 (0, 0)
	1 invokevirtual (0, 0)
	4 iconst_1 (0, 0)
	5 isub (0, 0)
	6 ireturn (0, 0)

Method: getNumDecisionVariables
	0 aload_0 (0, 0)
	1 getfield (0, 0)
	4 ireturn (0, 0)

Method: getOriginalNumDecisionVariables
	0 aload_0 (0, 0)
	1 getfield (0, 0)
	4 invokevirtual (0, 0)
	7 invokevirtual (0, 0)
	10 ireturn (0, 0)

Method: getNumSlackVariables
	0 aload_0 (0, 0)
	1 getfield (0, 0)
	4 ireturn (0, 0)

Method: getNumArtificialVariables
	0 aload_0 (0, 1)
	1 getfield (0, 1)
	4 ireturn (0, 1)

Method: getRow
	0 aload_0 (0, 0)
	1 getfield (0, 0)
	4 invokevirtual (0, 0)
	7 iload_1 (0, 0)
	8 aaload (0, 0)
	9 areturn (0, 0)

Method: getData
	0 aload_0 (0, 0)
	1 getfield (0, 0)
	4 invokevirtual (0, 0)
	7 areturn (0, 0)

Method: equals
	0 aload_0 (1, 1)
	1 aload_1 (1, 1)
	2 if_acmpne (1, 1)
	5 iconst_1 (1, 1)
	6 ireturn (1, 1)
	7 aload_1 (1, 1)
	8 instanceof (1, 1)
	11 ifeq (1, 1)
	14 aload_1 (1, 1)
	15 checkcast (1, 1)
	18 astore_2 (1, 1)
	19 aload_0 (1, 1)
	20 getfield (1, 1)
	23 aload_2 (1, 1)
	24 getfield (1, 1)
	27 if_icmpne (1, 1)
	30 aload_0 (1, 1)
	31 getfield (1, 1)
	34 aload_2 (1, 1)
	35 getfield (1, 1)
	38 if_icmpne (1, 1)
	41 aload_0 (1, 1)
	42 getfield (1, 1)
	45 aload_2 (1, 1)
	46 getfield (1, 1)
	49 if_icmpne (1, 1)
	52 aload_0 (1, 1)
	53 getfield (1, 1)
	56 aload_2 (1, 1)
	57 getfield (1, 1)
	60 if_icmpne (1, 1)
	63 aload_0 (1, 1)
	64 getfield (1, 1)
	67 aload_2 (1, 1)
	68 getfield (1, 1)
	71 dcmpl (1, 1)
	72 ifne (1, 1)
	75 aload_0 (1, 1)
	76 getfield (1, 1)
	79 aload_2 (1, 1)
	80 getfield (1, 1)
	83 if_icmpne (1, 1)
	86 aload_0 (1, 1)
	87 getfield (1, 1)
	90 aload_2 (1, 1)
	91 getfield (1, 1)
	94 invokevirtual (1, 1)
	97 ifeq (1, 1)
	100 aload_0 (1, 1)
	101 getfield (1, 1)
	104 aload_2 (1, 1)
	105 getfield (1, 1)
	108 invokeinterface (1, 1)
	113 ifeq (1, 1)
	116 aload_0 (1, 1)
	117 getfield (1, 1)
	120 aload_2 (1, 1)
	121 getfield (1, 1)
	124 invokevirtual (1, 1)
	127 ifeq (1, 1)
	130 iconst_1 (1, 1)
	131 goto (1, 1)
	134 iconst_0 (1, 1)
	135 ireturn (1, 1)
	136 iconst_0 (0, 1)
	137 ireturn (0, 1)

Method: hashCode
	0 aload_0 (0, 0)
	1 getfield (0, 0)
	4 invokestatic (0, 0)
	7 invokevirtual (0, 0)
	10 aload_0 (0, 0)
	11 getfield (0, 0)
	14 ixor (0, 0)
	15 aload_0 (0, 0)
	16 getfield (0, 0)
	19 ixor (0, 0)
	20 aload_0 (0, 0)
	21 getfield (0, 0)
	24 ixor (0, 0)
	25 aload_0 (0, 0)
	26 getfield (0, 0)
	29 invokestatic (0, 1)
	32 invokevirtual (0, 1)
	35 ixor (0, 1)
	36 aload_0 (0, 1)
	37 getfield (0, 1)
	40 ixor (0, 1)
	41 aload_0 (0, 1)
	42 getfield (0, 1)
	45 invokevirtual (0, 1)
	48 ixor (0, 1)
	49 aload_0 (0, 1)
	50 getfield (0, 1)
	53 invokeinterface (0, 1)
	58 ixor (0, 1)
	59 aload_0 (0, 1)
	60 getfield (0, 1)
	63 invokevirtual (0, 1)
	66 ixor (0, 1)
	67 ireturn (0, 1)

Method: writeObject
	0 aload_1 (0, 0)
	1 invokevirtual (0, 0)
	4 aload_0 (0, 0)
	5 getfield (0, 0)
	8 aload_1 (0, 0)
	9 invokestatic (0, 0)
	12 return (0, 0)

Method: readObject
	0 aload_1 (0, 0)
	1 invokevirtual (0, 0)
	4 aload_0 (0, 0)
	5 ldc (0, 0)
	7 aload_1 (0, 0)
	8 invokestatic (0, 0)
	11 return (0, 0)

