Method: <init>
	0 aload_0 (0, 0)
	1 invokespecial (0, 0)
	2 org/apache/commons/math3/optim/linear/LinearOptimizer.<init>:()V (0, 0)
	4 aload_0 (0, 0)
	5 dload_1 (0, 0)
	6 putfield (0, 0)
	7 org/apache/commons/math3/optim/linear/SimplexSolver.epsilon:D (0, 0)
	9 aload_0 (0, 0)
	10 iload_3 (0, 0)
	11 putfield (0, 0)
	12 org/apache/commons/math3/optim/linear/SimplexSolver.maxUlps:I (0, 0)
	14 aload_0 (0, 0)
	15 dload (0, 0)
	16 #4 (0, 0)
	17 putfield (0, 0)
	18 org/apache/commons/math3/optim/linear/SimplexSolver.cutOff:D (0, 0)
	20 aload_0 (0, 0)
	21 getstatic (0, 0)
	22 org/apache/commons/math3/optim/linear/PivotSelectionRule.DANTZIG:Lorg/apache/commons/math3/optim/linear/PivotSelectionRule; (0, 0)
	24 putfield (0, 0)
	25 org/apache/commons/math3/optim/linear/SimplexSolver.pivotSelection:Lorg/apache/commons/math3/optim/linear/PivotSelectionRule; (0, 0)
	27 return (0, 0)

Method: optimize
	0 aload_0 (0, 0)
	1 aload_1 (0, 0)
	2 invokevirtual (0, 0)
	3 org/apache/commons/math3/optim/linear/SimplexSolver.optimize:([Lorg/apache/commons/math3/optim/OptimizationData;)Lorg/apache/commons/math3/optim/PointValuePair; (0, 0)
	5 areturn (0, 0)

Method: parseOptimizationData
	0 aload_0 (0, 0)
	1 aload_1 (0, 0)
	2 invokespecial (0, 0)
	3 org/apache/commons/math3/optim/linear/LinearOptimizer.parseOptimizationData:([Lorg/apache/commons/math3/optim/OptimizationData;)V (0, 0)
	5 aload_0 (1, 4)
	6 aconst_null (1, 4)
	7 putfield (1, 4)
	8 org/apache/commons/math3/optim/linear/SimplexSolver.solutionCallback:Lorg/apache/commons/math3/optim/linear/SolutionCallback; (1, 4)
	10 aload_1 (2, 4)
	11 astore_2 (2, 4)
	12 aload_2 (2, 4)
	13 arraylength (2, 4)
	14 istore_3 (2, 4)
	15 iconst_0 (2, 4)
	16 istore (2, 4)
	17 #4 (2, 4)
	18 iload (2, 4)
	19 #4 (2, 4)
	20 iload_3 (2, 4)
	21 if_icmpge (2, 4)
	22 55 (2, 4)
	24 aload_2 (2, 4)
	25 iload (2, 4)
	26 #4 (2, 4)
	27 aaload (2, 4)
	28 astore (2, 4)
	29 #5 (2, 4)
	30 aload (3, 1)
	31 #5 (3, 1)
	32 instanceof (3, 1)
	33 org/apache/commons/math3/optim/linear/SolutionCallback (3, 1)
	35 ifeq (3, 1)
	36 15 (3, 1)
	38 aload_0 (3, 1)
	39 aload (3, 1)
	40 #5 (3, 1)
	41 checkcast (3, 1)
	42 org/apache/commons/math3/optim/linear/SolutionCallback (3, 1)
	44 putfield (3, 1)
	45 org/apache/commons/math3/optim/linear/SimplexSolver.solutionCallback:Lorg/apache/commons/math3/optim/linear/SolutionCallback; (3, 1)
	47 goto (3, 1)
	48 23 (3, 1)
	50 aload (3, 1)
	51 #5 (3, 1)
	52 instanceof (3, 1)
	53 org/apache/commons/math3/optim/linear/PivotSelectionRule (3, 1)
	55 ifeq (3, 1)
	56 15 (3, 1)
	58 aload_0 (3, 1)
	59 aload (3, 1)
	60 #5 (3, 1)
	61 checkcast (3, 1)
	62 org/apache/commons/math3/optim/linear/PivotSelectionRule (3, 1)
	64 putfield (3, 1)
	65 org/apache/commons/math3/optim/linear/SimplexSolver.pivotSelection:Lorg/apache/commons/math3/optim/linear/PivotSelectionRule; (3, 1)
	67 goto (3, 1)
	68 3 (3, 1)
	70 iinc (3, 1)
	71 #4 (3, 1)
	72 -89 (3, 1)
	73 goto (3, 1)
	74 -55 (3, 1)
	76 return (0, 4)

Method: getPivotColumn
	0 dconst_0 (0, 0)
	1 dstore_2 (0, 0)
	2 aconst_null (0, 0)
	3 astore (0, 0)
	4 #4 (0, 0)
	5 aload_1 (1, 4)
	6 invokevirtual (1, 4)
	7 org/apache/commons/math3/optim/linear/SimplexTableau.getNumObjectiveFunctions:()I (1, 4)
	9 istore (1, 4)
	10 #5 (1, 4)
	11 iload (1, 4)
	12 #5 (1, 4)
	13 aload_1 (1, 4)
	14 invokevirtual (1, 4)
	15 org/apache/commons/math3/optim/linear/SimplexTableau.getWidth:()I (1, 4)
	17 iconst_1 (1, 4)
	18 isub (1, 4)
	19 if_icmpge (1, 4)
	20 58 (1, 4)
	22 aload_1 (1, 4)
	23 iconst_0 (1, 4)
	24 iload (1, 4)
	25 #5 (1, 4)
	26 invokevirtual (1, 4)
	27 org/apache/commons/math3/optim/linear/SimplexTableau.getEntry:(II)D (1, 4)
	29 dstore (1, 4)
	30 #6 (1, 4)
	31 dload (3, 1)
	32 #6 (3, 1)
	33 dload_2 (3, 1)
	34 dcmpg (3, 1)
	35 ifge (3, 1)
	36 36 (3, 1)
	38 dload (3, 1)
	39 #6 (3, 1)
	40 dstore_2 (3, 1)
	41 iload (3, 1)
	42 #5 (3, 1)
	43 invokestatic (3, 1)
	44 java/lang/Integer.valueOf:(I)Ljava/lang/Integer; (3, 1)
	46 astore (3, 1)
	47 #4 (3, 1)
	48 aload_0 (4, 1)
	49 getfield (4, 1)
	50 org/apache/commons/math3/optim/linear/SimplexSolver.pivotSelection:Lorg/apache/commons/math3/optim/linear/PivotSelectionRule; (4, 1)
	52 getstatic (4, 1)
	53 org/apache/commons/math3/optim/linear/PivotSelectionRule.BLAND:Lorg/apache/commons/math3/optim/linear/PivotSelectionRule; (4, 1)
	55 if_acmpne (4, 1)
	56 16 (4, 1)
	58 aload_0 (4, 1)
	59 aload_1 (4, 1)
	60 iload (4, 1)
	61 #5 (4, 1)
	62 invokespecial (4, 1)
	63 org/apache/commons/math3/optim/linear/SimplexSolver.isValidPivotColumn:(Lorg/apache/commons/math3/optim/linear/SimplexTableau;I)Z (4, 1)
	65 ifeq (4, 1)
	66 6 (4, 1)
	68 goto (4, 1)
	69 9 (4, 1)
	71 iinc (4, 1)
	72 #5 (4, 1)
	73 -89 (4, 1)
	74 goto (4, 1)
	75 -63 (4, 1)
	77 aload (3, 1)
	78 #4 (3, 1)
	79 areturn (2, 1)

Method: isValidPivotColumn
	0 aload_1 (1, 4)
	1 invokevirtual (1, 4)
	2 org/apache/commons/math3/optim/linear/SimplexTableau.getNumObjectiveFunctions:()I (1, 4)
	4 istore_3 (1, 4)
	5 iload_3 (1, 4)
	6 aload_1 (1, 4)
	7 invokevirtual (1, 4)
	8 org/apache/commons/math3/optim/linear/SimplexTableau.getHeight:()I (1, 4)
	10 if_icmpge (1, 4)
	11 32 (1, 4)
	13 aload_1 (1, 4)
	14 iload_3 (1, 4)
	15 iload_2 (1, 4)
	16 invokevirtual (1, 4)
	17 org/apache/commons/math3/optim/linear/SimplexTableau.getEntry:(II)D (1, 4)
	19 dstore (1, 4)
	20 #4 (1, 4)
	21 dload (2, 1)
	22 #4 (2, 1)
	23 dconst_0 (2, 1)
	24 aload_0 (2, 1)
	25 getfield (2, 1)
	26 org/apache/commons/math3/optim/linear/SimplexSolver.cutOff:D (2, 1)
	28 invokestatic (2, 1)
	29 org/apache/commons/math3/util/Precision.compareTo:(DDD)I (2, 1)
	31 ifle (2, 1)
	32 5 (2, 1)
	34 iconst_1 (2, 1)
	35 ireturn (2, 1)
	36 iinc (2, 1)
	37 #3 (2, 1)
	38 -89 (2, 1)
	39 goto (2, 1)
	40 -34 (2, 1)
	42 iconst_0 (1, 4)
	43 ireturn (1, 4)

Method: getPivotRow
	0 new (0, 0)
	1 java/util/ArrayList (0, 0)
	3 dup (0, 0)
	4 invokespecial (0, 0)
	5 java/util/ArrayList.<init>:()V (0, 0)
	7 astore_3 (0, 0)
	8 ldc2_w (0, 0)
	9 1.7976931348623157e+308 (0, 0)
	11 dstore (0, 0)
	12 #4 (0, 0)
	13 aload_1 (1, 4)
	14 invokevirtual (1, 4)
	15 org/apache/commons/math3/optim/linear/SimplexTableau.getNumObjectiveFunctions:()I (1, 4)
	17 istore (1, 4)
	18 #6 (1, 4)
	19 iload (1, 4)
	20 #6 (1, 4)
	21 aload_1 (1, 4)
	22 invokevirtual (1, 4)
	23 org/apache/commons/math3/optim/linear/SimplexTableau.getHeight:()I (1, 4)
	25 if_icmpge (1, 4)
	26 111 (1, 4)
	28 aload_1 (1, 4)
	29 iload (1, 4)
	30 #6 (1, 4)
	31 aload_1 (1, 4)
	32 invokevirtual (1, 4)
	33 org/apache/commons/math3/optim/linear/SimplexTableau.getWidth:()I (1, 4)
	35 iconst_1 (1, 4)
	36 isub (1, 4)
	37 invokevirtual (1, 4)
	38 org/apache/commons/math3/optim/linear/SimplexTableau.getEntry:(II)D (1, 4)
	40 dstore (1, 4)
	41 #7 (1, 4)
	42 aload_1 (1, 4)
	43 iload (1, 4)
	44 #6 (1, 4)
	45 iload_2 (1, 4)
	46 invokevirtual (1, 4)
	47 org/apache/commons/math3/optim/linear/SimplexTableau.getEntry:(II)D (1, 4)
	49 dstore (1, 4)
	50 #9 (1, 4)
	51 dload (2, 1)
	52 #9 (2, 1)
	53 dconst_0 (2, 1)
	54 aload_0 (2, 1)
	55 getfield (2, 1)
	56 org/apache/commons/math3/optim/linear/SimplexSolver.cutOff:D (2, 1)
	58 invokestatic (2, 1)
	59 org/apache/commons/math3/util/Precision.compareTo:(DDD)I (2, 1)
	61 ifle (2, 1)
	62 69 (2, 1)
	64 dload (2, 1)
	65 #7 (2, 1)
	66 dload (2, 1)
	67 #9 (2, 1)
	68 ddiv (2, 1)
	69 invokestatic (2, 1)
	70 org/apache/commons/math3/util/FastMath.abs:(D)D (2, 1)
	72 dstore (2, 1)
	73 #11 (2, 1)
	74 dload (3, 1)
	75 #11 (3, 1)
	76 dload (3, 1)
	77 #4 (3, 1)
	78 invokestatic (3, 1)
	79 java/lang/Double.compare:(DD)I (3, 1)
	81 istore (3, 1)
	82 #13 (3, 1)
	83 iload (4, 1)
	84 #13 (4, 1)
	85 ifne (4, 1)
	86 18 (4, 1)
	88 aload_3 (4, 1)
	89 iload (4, 1)
	90 #6 (4, 1)
	91 invokestatic (4, 1)
	92 java/lang/Integer.valueOf:(I)Ljava/lang/Integer; (4, 1)
	94 invokeinterface (4, 1)
	95 java/util/List.clear:()V (4, 1)
	97 0 (4, 1)
	99 pop (4, 1)
	100 goto (4, 1)
	101 30 (4, 1)
	103 iload (5, 1)
	104 #13 (5, 1)
	105 ifge (5, 1)
	106 25 (5, 1)
	108 dload (5, 1)
	109 #11 (5, 1)
	110 dstore (5, 1)
	111 #4 (5, 1)
	112 aload_3 (5, 1)
	113 invokeinterface (5, 1)
	114 java/util/List.size:()I (5, 1)
	116 0 (5, 1)
	118 aload_3 (5, 1)
	119 iload (5, 1)
	120 #6 (5, 1)
	121 invokestatic (5, 1)
	122 java/lang/Integer.valueOf:(I)Ljava/lang/Integer; (5, 1)
	124 invokeinterface (5, 1)
	125 java/util/List.clear:()V (5, 1)
	127 0 (5, 1)
	129 pop (5, 1)
	130 iinc (5, 1)
	131 #6 (5, 1)
	132 -89 (5, 1)
	133 goto (5, 1)
	134 -114 (5, 1)
	136 aload_3 (4, 1)
	137 invokeinterface (4, 1)
	138 java/util/List.getNumArtificialVariables:()I (4, 1)
	140 0 (4, 1)
	142 ifne (4, 1)
	143 5 (4, 1)
	145 aconst_null (4, 1)
	146 areturn (4, 1)
	147 aload_3 (5, 1)
	148 invokeinterface (5, 1)
	149 java/util/List.getNumArtificialVariables:()I (5, 1)
	151 0 (5, 1)
	153 iconst_1 (5, 1)
	154 if_icmple (5, 1)
	155 184 (5, 1)
	157 aload_1 (7, 1)
	158 invokevirtual (7, 1)
	159 org/apache/commons/math3/optim/linear/SimplexTableau.getNumArtificialVariables:()I (7, 1)
	161 ifle (7, 1)
	162 106 (7, 1)
	164 aload_3 (8, 4)
	165 invokeinterface (8, 4)
	166 java/util/List.java/util/Iterator (8, 4)
	168 0 (8, 4)
	170 astore (8, 4)
	171 #6 (8, 4)
	172 aload (8, 4)
	173 #6 (8, 4)
	174 invokeinterface (8, 4)
	175 java/util/Iterator.next:()Ljava/lang/Object; (8, 4)
	177 0 (8, 4)
	179 ifeq (8, 4)
	180 88 (8, 4)
	182 aload (8, 4)
	183 #6 (8, 4)
	184 invokeinterface (8, 4)
	185 java/util/Iterator.java/lang/Integer (8, 4)
	187 0 (8, 4)
	189 checkcast (8, 4)
	190 java/lang/Integer (8, 4)
	192 astore (8, 4)
	193 #7 (8, 4)
	194 iconst_0 (9, 1)
	195 istore (9, 1)
	196 #8 (9, 1)
	197 iload (9, 1)
	198 #8 (9, 1)
	199 aload_1 (9, 1)
	200 invokevirtual (9, 1)
	201 org/apache/commons/math3/optim/linear/SimplexTableau.getNumArtificialVariables:()I (9, 1)
	203 if_icmpge (9, 1)
	204 61 (9, 1)
	206 iload (10, 1)
	207 #8 (10, 1)
	208 aload_1 (10, 1)
	209 invokevirtual (10, 1)
	210 org/apache/commons/math3/optim/linear/SimplexTableau.getArtificialVariableOffset:()I (10, 1)
	212 iadd (10, 1)
	213 istore (10, 1)
	214 #9 (10, 1)
	215 aload_1 (10, 1)
	216 aload (10, 1)
	217 #7 (10, 1)
	218 invokevirtual (10, 1)
	219 java/lang/Integer.intValue:()I (10, 1)
	221 iload (10, 1)
	222 #9 (10, 1)
	223 invokevirtual (10, 1)
	224 org/apache/commons/math3/optim/linear/SimplexTableau.getEntry:(II)D (10, 1)
	226 dstore (10, 1)
	227 #10 (10, 1)
	228 dload (11, 1)
	229 #10 (11, 1)
	230 dconst_1 (11, 1)
	231 aload_0 (11, 1)
	232 getfield (11, 1)
	233 org/apache/commons/math3/optim/linear/SimplexSolver.maxUlps:I (11, 1)
	235 invokestatic (11, 1)
	236 org/apache/commons/math3/util/Precision.equals:(DDI)Z (11, 1)
	238 ifeq (11, 1)
	239 20 (11, 1)
	241 aload (11, 1)
	242 #7 (11, 1)
	243 aload_1 (11, 1)
	244 iload (11, 1)
	245 #9 (11, 1)
	246 invokevirtual (11, 1)
	247 org/apache/commons/math3/optim/linear/SimplexTableau.getBasicRow:(I)Ljava/lang/Integer; (11, 1)
	249 invokevirtual (11, 1)
	250 java/lang/Integer.equals:(Ljava/lang/Object;)Z (11, 1)
	252 ifeq (11, 1)
	253 6 (11, 1)
	255 aload (11, 1)
	256 #7 (11, 1)
	257 areturn (11, 1)
	258 iinc (11, 1)
	259 #8 (11, 1)
	260 -89 (11, 1)
	261 goto (11, 1)
	262 -64 (11, 1)
	264 goto (8, 4)
	265 -92 (8, 4)
	267 aconst_null (9, 4)
	268 astore (9, 4)
	269 #6 (9, 4)
	270 aload_1 (9, 4)
	271 invokevirtual (9, 4)
	272 org/apache/commons/math3/optim/linear/SimplexTableau.getWidth:()I (9, 4)
	274 istore (9, 4)
	275 #7 (9, 4)
	276 aload_3 (10, 4)
	277 invokeinterface (10, 4)
	278 java/util/List.java/util/Iterator (10, 4)
	280 0 (10, 4)
	282 astore (10, 4)
	283 #8 (10, 4)
	284 aload (10, 4)
	285 #8 (10, 4)
	286 invokeinterface (10, 4)
	287 java/util/Iterator.next:()Ljava/lang/Object; (10, 4)
	289 0 (10, 4)
	291 ifeq (10, 4)
	292 44 (10, 4)
	294 aload (10, 4)
	295 #8 (10, 4)
	296 invokeinterface (10, 4)
	297 java/util/Iterator.java/lang/Integer (10, 4)
	299 0 (10, 4)
	301 checkcast (10, 4)
	302 java/lang/Integer (10, 4)
	304 astore (10, 4)
	305 #9 (10, 4)
	306 aload_1 (10, 4)
	307 aload (10, 4)
	308 #9 (10, 4)
	309 invokevirtual (10, 4)
	310 java/lang/Integer.intValue:()I (10, 4)
	312 invokevirtual (10, 4)
	313 org/apache/commons/math3/optim/linear/SimplexTableau.getBasicVariable:(I)I (10, 4)
	315 istore (10, 4)
	316 #10 (10, 4)
	317 iload (11, 1)
	318 #10 (11, 1)
	319 iload (11, 1)
	320 #7 (11, 1)
	321 if_icmpge (11, 1)
	322 11 (11, 1)
	324 iload (11, 1)
	325 #10 (11, 1)
	326 istore (11, 1)
	327 #7 (11, 1)
	328 aload (11, 1)
	329 #9 (11, 1)
	330 astore (11, 1)
	331 #6 (11, 1)
	332 goto (9, 4)
	333 -48 (9, 4)
	335 aload (9, 4)
	336 #6 (9, 4)
	337 areturn (9, 4)
	338 aload_3 (6, 1)
	339 iconst_0 (6, 1)
	340 invokeinterface (6, 1)
	341 java/util/List.incrementIterationCount:()V (6, 1)
	343 0 (6, 1)
	345 checkcast (6, 1)
	346 java/lang/Integer (6, 1)
	348 areturn (3, 1)

Method: doIteration
	0 aload_0 (0, 0)
	1 invokevirtual (0, 0)
	2 org/apache/commons/math3/optim/linear/SimplexSolver.incrementIterationCount:()V (0, 0)
	4 aload_0 (0, 0)
	5 aload_1 (0, 0)
	6 invokespecial (0, 0)
	7 org/apache/commons/math3/optim/linear/SimplexSolver.getPivotColumn:(Lorg/apache/commons/math3/optim/linear/SimplexTableau;)Ljava/lang/Integer; (0, 0)
	9 astore_2 (0, 0)
	10 aload_0 (0, 0)
	11 aload_1 (0, 0)
	12 aload_2 (0, 0)
	13 invokevirtual (0, 0)
	14 java/lang/Integer.intValue:()I (0, 0)
	16 invokespecial (0, 0)
	17 org/apache/commons/math3/optim/linear/SimplexSolver.getPivotRow:(Lorg/apache/commons/math3/optim/linear/SimplexTableau;I)Ljava/lang/Integer; (0, 0)
	19 astore_3 (0, 0)
	20 aload_3 (1, 1)
	21 ifnonnull (1, 1)
	22 11 (1, 1)
	24 new (1, 1)
	25 org/apache/commons/math3/optim/linear/UnboundedSolutionException (1, 1)
	27 dup (1, 1)
	28 invokespecial (1, 1)
	29 org/apache/commons/math3/optim/linear/UnboundedSolutionException.<init>:()V (1, 1)
	31 athrow (1, 1)
	32 aload_1 (1, 4)
	33 aload_2 (1, 4)
	34 invokevirtual (1, 4)
	35 java/lang/Integer.intValue:()I (1, 4)
	37 aload_3 (1, 4)
	38 invokevirtual (1, 4)
	39 java/lang/Integer.intValue:()I (1, 4)
	41 invokevirtual (1, 4)
	42 org/apache/commons/math3/optim/linear/SimplexTableau.performRowOperations:(II)V (1, 4)
	44 return (0, 4)

Method: solvePhase1
	0 aload_1 (1, 1)
	1 invokevirtual (1, 1)
	2 org/apache/commons/math3/optim/linear/SimplexTableau.getNumArtificialVariables:()I (1, 1)
	4 ifne (1, 1)
	5 4 (1, 1)
	7 return (1, 1)
	8 aload_1 (1, 3)
	9 invokevirtual (1, 3)
	10 org/apache/commons/math3/optim/linear/SimplexTableau.isOptimal:()Z (1, 3)
	12 ifne (1, 3)
	13 11 (1, 3)
	15 aload_0 (1, 3)
	16 aload_1 (1, 3)
	17 invokevirtual (1, 3)
	18 org/apache/commons/math3/optim/linear/SimplexSolver.doIteration:(Lorg/apache/commons/math3/optim/linear/SimplexTableau;)V (1, 3)
	20 goto (1, 3)
	21 -12 (1, 3)
	23 aload_1 (2, 1)
	24 iconst_0 (2, 1)
	25 aload_1 (2, 1)
	26 invokevirtual (2, 1)
	27 org/apache/commons/math3/optim/linear/SimplexTableau.getRhsOffset:()I (2, 1)
	29 invokevirtual (2, 1)
	30 org/apache/commons/math3/optim/linear/SimplexTableau.getEntry:(II)D (2, 1)
	32 dconst_0 (2, 1)
	33 aload_0 (2, 1)
	34 getfield (2, 1)
	35 org/apache/commons/math3/optim/linear/SimplexSolver.epsilon:D (2, 1)
	37 invokestatic (2, 1)
	38 org/apache/commons/math3/util/Precision.equals:(DDD)Z (2, 1)
	40 ifne (2, 1)
	41 11 (2, 1)
	43 new (2, 1)
	44 org/apache/commons/math3/optim/linear/NoFeasibleSolutionException (2, 1)
	46 dup (2, 1)
	47 invokespecial (2, 1)
	48 org/apache/commons/math3/optim/linear/NoFeasibleSolutionException.<init>:()V (2, 1)
	50 athrow (2, 1)
	51 return (0, 1)

Method: doOptimize
	0 aload_0 (0, 0)
	1 invokevirtual (0, 0)
	2 org/apache/commons/math3/optim/linear/SimplexSolver.doOptimize:()Lorg/apache/commons/math3/optim/PointValuePair; (0, 0)
	4 areturn (0, 0)

