Method: setTableau
	0 aload_0 (0, 0)
	1 aload_1 (0, 0)
	2 putfield (0, 0)
	3 org/apache/commons/math3/optim/linear/SolutionCallback.tableau:Lorg/apache/commons/math3/optim/linear/SimplexTableau; (0, 0)
	5 return (0, 0)

Method: getSolution
	0 aload_0 (0, 0)
	1 getfield (0, 0)
	2 org/apache/commons/math3/optim/linear/SolutionCallback.tableau:Lorg/apache/commons/math3/optim/linear/SimplexTableau; (0, 0)
	4 ifnull (0, 0)
	5 13 (0, 0)
	7 aload_0 (0, 0)
	8 getfield (0, 0)
	9 org/apache/commons/math3/optim/linear/SolutionCallback.tableau:Lorg/apache/commons/math3/optim/linear/SimplexTableau; (0, 0)
	11 invokevirtual (0, 0)
	12 org/apache/commons/math3/optim/linear/SimplexTableau.getSolution:()Lorg/apache/commons/math3/optim/PointValuePair; (0, 0)
	14 goto (0, 0)
	15 4 (0, 0)
	17 aconst_null (0, 0)
	18 areturn (0, 0)

Method: isSolutionOptimal
	0 aload_0 (0, 0)
	1 getfield (0, 0)
	2 org/apache/commons/math3/optim/linear/SolutionCallback.tableau:Lorg/apache/commons/math3/optim/linear/SimplexTableau; (0, 0)
	4 ifnull (0, 0)
	5 13 (0, 0)
	7 aload_0 (0, 0)
	8 getfield (0, 0)
	9 org/apache/commons/math3/optim/linear/SolutionCallback.tableau:Lorg/apache/commons/math3/optim/linear/SimplexTableau; (0, 0)
	11 invokevirtual (0, 0)
	12 org/apache/commons/math3/optim/linear/SimplexTableau.isOptimal:()Z (0, 0)
	14 goto (0, 0)
	15 4 (0, 0)
	17 iconst_0 (0, 0)
	18 ireturn (0, 0)

