Method: <init>
	0 aload_0 (0, 0)
	1 aload_1 (0, 0)
	2 aload_2 (0, 0)
	3 iload_3 (0, 0)
	4 iload (0, 0)
	6 dload (0, 0)
	8 dload (0, 0)
	10 aload (0, 0)
	12 aload (0, 0)
	14 invokespecial (0, 0)
	17 aload_0 (0, 4)
	18 aload_1 (0, 4)
	19 iload_3 (0, 4)
	20 invokestatic (0, 4)
	23 putfield (0, 4)
	26 return (0, 0)

Method: initializeHighOrderDerivatives
	0 aload_0 (0, 4)
	1 getfield (0, 4)
	4 aload_1 (0, 4)
	5 aload_2 (0, 4)
	6 aload_3 (0, 4)
	7 aload (0, 4)
	9 invokevirtual (0, 4)
	12 areturn (0, 4)

Method: updateHighOrderDerivativesPhase1
	0 aload_0 (0, 4)
	1 getfield (0, 4)
	4 aload_1 (0, 4)
	5 invokevirtual (0, 4)
	8 areturn (0, 4)

Method: updateHighOrderDerivativesPhase2
	0 aload_0 (0, 4)
	1 getfield (0, 4)
	4 aload_1 (0, 4)
	5 aload_2 (0, 4)
	6 aload_3 (0, 4)
	7 invokevirtual (0, 4)
	10 return (0, 0)

