Method: <init>
	0 aload_0 (1, 4)
	1 invokespecial (1, 4)
	2 java/lang/Object.<init>:()V (1, 4)
	4 aload_0 (1, 4)
	5 aload_1 (1, 4)
	6 putfield (1, 4)
	7 org/apache/commons/math3/ode/nonstiff/AdamsNordsieckFieldTransformer.field:Lorg/apache/commons/math3/Field; (1, 4)
	9 iload_2 (1, 4)
	10 iconst_1 (1, 4)
	11 isub (1, 4)
	12 istore_3 (1, 4)
	13 aload_0 (1, 4)
	14 iload_3 (1, 4)
	15 invokespecial (1, 4)
	16 org/apache/commons/math3/ode/nonstiff/AdamsNordsieckFieldTransformer.buildP:(I)Lorg/apache/commons/math3/linear/FieldMatrix; (1, 4)
	18 astore (1, 4)
	19 #4 (1, 4)
	20 new (1, 4)
	21 org/apache/commons/math3/linear/FieldLUDecomposition (1, 4)
	23 dup (1, 4)
	24 aload (1, 4)
	25 #4 (1, 4)
	26 invokespecial (1, 4)
	27 org/apache/commons/math3/linear/FieldLUDecomposition.<init>:(Lorg/apache/commons/math3/linear/FieldMatrix;)V (1, 4)
	29 invokevirtual (1, 4)
	30 org/apache/commons/math3/linear/FieldLUDecomposition.getSolver:()Lorg/apache/commons/math3/linear/FieldDecompositionSolver; (1, 4)
	32 astore (1, 4)
	33 #5 (1, 4)
	34 aload_1 (1, 4)
	35 iload_3 (1, 4)
	36 invokestatic (1, 4)
	37 org/apache/commons/math3/util/MathArrays.buildArray:(Lorg/apache/commons/math3/Field;I)[Ljava/lang/Object; (1, 4)
	39 checkcast (1, 4)
	40 [Lorg/apache/commons/math3/RealFieldElement; (1, 4)
	42 astore (1, 4)
	43 #6 (1, 4)
	44 aload (1, 4)
	45 #6 (1, 4)
	46 aload_1 (1, 4)
	47 invokeinterface (1, 4)
	48 org/apache/commons/math3/Field.java/util/Arrays (1, 4)
	50 0 (1, 4)
	52 invokestatic (1, 4)
	53 java/util/Arrays.fill:([Ljava/lang/Object;Ljava/lang/Object;)V (1, 4)
	55 aload_0 (1, 4)
	56 aload (1, 4)
	57 #5 (1, 4)
	58 new (1, 4)
	59 org/apache/commons/math3/linear/ArrayFieldVector (1, 4)
	61 dup (1, 4)
	62 aload (1, 4)
	63 #6 (1, 4)
	64 iconst_0 (1, 4)
	65 invokespecial (1, 4)
	66 org/apache/commons/math3/linear/ArrayFieldVector.<init>:([Lorg/apache/commons/math3/FieldElement;Z)V (1, 4)
	68 invokeinterface (1, 4)
	69 org/apache/commons/math3/linear/FieldDecompositionSolver.org/apache/commons/math3/linear/FieldVector (1, 4)
	71 0 (1, 4)
	73 invokeinterface (1, 4)
	74 org/apache/commons/math3/linear/FieldVector.c1:[Lorg/apache/commons/math3/RealFieldElement; (1, 4)
	76 0 (1, 4)
	78 checkcast (1, 4)
	79 [Lorg/apache/commons/math3/RealFieldElement; (1, 4)
	81 putfield (1, 4)
	82 org/apache/commons/math3/ode/nonstiff/AdamsNordsieckFieldTransformer.c1:[Lorg/apache/commons/math3/RealFieldElement; (1, 4)
	84 aload (1, 1)
	85 #4 (1, 1)
	86 invokeinterface (1, 1)
	87 org/apache/commons/math3/linear/FieldMatrix.getZero:()Ljava/lang/Object; (1, 1)
	89 0 (1, 1)
	91 checkcast (1, 1)
	92 [[Lorg/apache/commons/math3/RealFieldElement; (1, 1)
	94 astore (1, 1)
	95 #7 (1, 1)
	96 aload (2, 1)
	97 #7 (2, 1)
	98 arraylength (2, 1)
	99 iconst_1 (2, 1)
	100 isub (2, 1)
	101 istore (2, 1)
	102 #8 (2, 1)
	103 iload (2, 1)
	104 #8 (2, 1)
	105 ifle (2, 1)
	106 21 (2, 1)
	108 aload (2, 1)
	109 #7 (2, 1)
	110 iload (2, 1)
	111 #8 (2, 1)
	112 aload (2, 1)
	113 #7 (2, 1)
	114 iload (2, 1)
	115 #8 (2, 1)
	116 iconst_1 (2, 1)
	117 isub (2, 1)
	118 aaload (2, 1)
	119 aastore (2, 1)
	120 iinc (2, 1)
	121 #8 (2, 1)
	122 -89 (2, 1)
	123 goto (2, 1)
	124 -20 (2, 1)
	126 aload (1, 1)
	127 #7 (1, 1)
	128 iconst_0 (1, 1)
	129 aload_1 (1, 1)
	130 iload_3 (1, 1)
	131 invokestatic (1, 1)
	132 org/apache/commons/math3/util/MathArrays.buildArray:(Lorg/apache/commons/math3/Field;I)[Ljava/lang/Object; (1, 1)
	134 checkcast (1, 1)
	135 [Lorg/apache/commons/math3/RealFieldElement; (1, 1)
	137 aastore (1, 1)
	138 aload (1, 1)
	139 #7 (1, 1)
	140 iconst_0 (1, 1)
	141 aaload (1, 1)
	142 aload_1 (1, 1)
	143 invokeinterface (1, 1)
	144 org/apache/commons/math3/Field.org/apache/commons/math3/linear/Array2DRowFieldMatrix (1, 1)
	146 0 (1, 1)
	148 invokestatic (1, 1)
	149 java/util/Arrays.fill:([Ljava/lang/Object;Ljava/lang/Object;)V (1, 1)
	151 aload_0 (1, 1)
	152 new (1, 1)
	153 org/apache/commons/math3/linear/Array2DRowFieldMatrix (1, 1)
	155 dup (1, 1)
	156 aload (1, 1)
	157 #5 (1, 1)
	158 new (1, 1)
	159 org/apache/commons/math3/linear/Array2DRowFieldMatrix (1, 1)
	161 dup (1, 1)
	162 aload (1, 1)
	163 #7 (1, 1)
	164 iconst_0 (1, 1)
	165 invokespecial (1, 1)
	166 org/apache/commons/math3/linear/Array2DRowFieldMatrix.<init>:([[Lorg/apache/commons/math3/FieldElement;Z)V (1, 1)
	168 invokeinterface (1, 1)
	169 org/apache/commons/math3/linear/FieldDecompositionSolver.<init>:([[Lorg/apache/commons/math3/FieldElement;)V (1, 1)
	171 0 (1, 1)
	173 invokeinterface (1, 1)
	174 org/apache/commons/math3/linear/FieldMatrix.getZero:()Ljava/lang/Object; (1, 1)
	176 0 (1, 1)
	178 invokespecial (1, 1)
	179 org/apache/commons/math3/linear/Array2DRowFieldMatrix.<init>:([[Lorg/apache/commons/math3/FieldElement;)V (1, 1)
	181 putfield (1, 1)
	182 org/apache/commons/math3/ode/nonstiff/AdamsNordsieckFieldTransformer.update:Lorg/apache/commons/math3/linear/Array2DRowFieldMatrix; (1, 1)
	184 return (0, 0)

Method: getInstance
	0 getstatic (0, 0)
	1 org/apache/commons/math3/ode/nonstiff/AdamsNordsieckFieldTransformer.CACHE:Ljava/util/Map; (0, 0)
	3 dup (0, 0)
	4 astore_2 (0, 0)
	5 monitorenter (0, 0)
	6 getstatic (1, 4)
	7 org/apache/commons/math3/ode/nonstiff/AdamsNordsieckFieldTransformer.CACHE:Ljava/util/Map; (1, 4)
	9 iload_1 (1, 4)
	10 invokestatic (1, 4)
	11 java/lang/Integer.valueOf:(I)Ljava/lang/Integer; (1, 4)
	13 invokeinterface (1, 4)
	14 java/util/Map.java/util/Map (1, 4)
	16 0 (1, 4)
	18 checkcast (1, 4)
	19 java/util/Map (1, 4)
	21 astore_3 (1, 4)
	22 aload_3 (2, 1)
	23 ifnonnull (2, 1)
	24 25 (2, 1)
	26 new (2, 1)
	27 java/util/HashMap (2, 1)
	29 dup (2, 1)
	30 invokespecial (2, 1)
	31 java/util/HashMap.<init>:()V (2, 1)
	33 astore_3 (2, 1)
	34 getstatic (2, 4)
	35 org/apache/commons/math3/ode/nonstiff/AdamsNordsieckFieldTransformer.CACHE:Ljava/util/Map; (2, 4)
	37 iload_1 (2, 4)
	38 invokestatic (2, 4)
	39 java/lang/Integer.valueOf:(I)Ljava/lang/Integer; (2, 4)
	41 aload_3 (2, 4)
	42 invokeinterface (2, 4)
	43 java/util/Map.org/apache/commons/math3/ode/nonstiff/AdamsNordsieckFieldTransformer (2, 4)
	45 0 (2, 4)
	47 pop (2, 4)
	48 aload_3 (1, 4)
	49 aload_0 (1, 4)
	50 invokeinterface (1, 4)
	51 java/util/Map.java/util/Map (1, 4)
	53 0 (1, 4)
	55 checkcast (1, 4)
	56 org/apache/commons/math3/ode/nonstiff/AdamsNordsieckFieldTransformer (1, 4)
	58 astore (1, 4)
	59 #4 (1, 4)
	60 aload (2, 1)
	61 #4 (2, 1)
	62 ifnonnull (2, 1)
	63 24 (2, 1)
	65 new (2, 4)
	66 org/apache/commons/math3/ode/nonstiff/AdamsNordsieckFieldTransformer (2, 4)
	68 dup (2, 4)
	69 aload_0 (2, 4)
	70 iload_1 (2, 4)
	71 invokespecial (2, 4)
	72 org/apache/commons/math3/ode/nonstiff/AdamsNordsieckFieldTransformer.<init>:(Lorg/apache/commons/math3/Field;I)V (2, 4)
	74 astore (2, 4)
	75 #4 (2, 4)
	76 aload_3 (2, 4)
	77 aload_0 (2, 4)
	78 aload (2, 4)
	79 #4 (2, 4)
	80 invokeinterface (2, 4)
	81 java/util/Map.org/apache/commons/math3/ode/nonstiff/AdamsNordsieckFieldTransformer (2, 4)
	83 0 (2, 4)
	85 pop (2, 4)
	86 aload (1, 4)
	87 #4 (1, 4)
	88 aload_2 (1, 4)
	89 monitorexit (1, 4)
	90 areturn (1, 4)
	91 astore (0, 0)
	92 #5 (0, 0)
	93 aload_2 (0, 0)
	94 monitorexit (0, 0)
	95 aload (0, 0)
	96 #5 (0, 0)
	97 athrow (0, 0)

Method: buildP
	0 aload_0 (0, 0)
	1 getfield (0, 0)
	2 org/apache/commons/math3/ode/nonstiff/AdamsNordsieckFieldTransformer.field:Lorg/apache/commons/math3/Field; (0, 0)
	4 iload_1 (0, 0)
	5 iload_1 (0, 0)
	6 invokestatic (0, 0)
	7 org/apache/commons/math3/util/MathArrays.buildArray:(Lorg/apache/commons/math3/Field;II)[[Ljava/lang/Object; (0, 0)
	9 checkcast (0, 0)
	10 [[Lorg/apache/commons/math3/RealFieldElement; (0, 0)
	12 astore_2 (0, 0)
	13 iconst_1 (1, 4)
	14 istore_3 (1, 4)
	15 iload_3 (1, 4)
	16 aload_2 (1, 4)
	17 arraylength (1, 4)
	18 if_icmpgt (1, 4)
	19 97 (1, 4)
	21 aload_2 (1, 4)
	22 iload_3 (1, 4)
	23 iconst_1 (1, 4)
	24 isub (1, 4)
	25 aaload (1, 4)
	26 astore (1, 4)
	27 #4 (1, 4)
	28 iload_3 (1, 4)
	29 ineg (1, 4)
	30 istore (1, 4)
	31 #5 (1, 4)
	32 aload_0 (1, 4)
	33 getfield (1, 4)
	34 org/apache/commons/math3/ode/nonstiff/AdamsNordsieckFieldTransformer.field:Lorg/apache/commons/math3/Field; (1, 4)
	36 invokeinterface (1, 4)
	37 org/apache/commons/math3/Field.org/apache/commons/math3/linear/Array2DRowFieldMatrix (1, 4)
	39 0 (1, 4)
	41 checkcast (1, 4)
	42 org/apache/commons/math3/RealFieldElement (1, 4)
	44 iload (1, 4)
	45 #5 (1, 4)
	46 i2d (1, 4)
	47 invokeinterface (1, 4)
	48 org/apache/commons/math3/RealFieldElement.multiply:(I)Ljava/lang/Object; (1, 4)
	50 0 (1, 4)
	52 checkcast (1, 4)
	53 org/apache/commons/math3/RealFieldElement (1, 4)
	55 astore (1, 4)
	56 #6 (1, 4)
	57 iconst_1 (2, 4)
	58 istore (2, 4)
	59 #7 (2, 4)
	60 iload (2, 4)
	61 #7 (2, 4)
	62 aload (2, 4)
	63 #4 (2, 4)
	64 arraylength (2, 4)
	65 if_icmpgt (2, 4)
	66 44 (2, 4)
	68 aload (2, 4)
	69 #4 (2, 4)
	70 iload (2, 4)
	71 #7 (2, 4)
	72 iconst_1 (2, 4)
	73 isub (2, 4)
	74 aload (2, 4)
	75 #6 (2, 4)
	76 iload (2, 4)
	77 #7 (2, 4)
	78 iconst_1 (2, 4)
	79 iadd (2, 4)
	80 invokeinterface (2, 4)
	81 org/apache/commons/math3/RealFieldElement.subtract:(Ljava/lang/Object;)Ljava/lang/Object; (2, 4)
	83 0 (2, 4)
	85 checkcast (2, 4)
	86 org/apache/commons/math3/RealFieldElement (2, 4)
	88 aastore (2, 4)
	89 aload (2, 4)
	90 #6 (2, 4)
	91 iload (2, 4)
	92 #5 (2, 4)
	93 invokeinterface (2, 4)
	94 org/apache/commons/math3/RealFieldElement.subtract:(Ljava/lang/Object;)Ljava/lang/Object; (2, 4)
	96 0 (2, 4)
	98 checkcast (2, 4)
	99 org/apache/commons/math3/RealFieldElement (2, 4)
	101 astore (2, 4)
	102 #6 (2, 4)
	103 iinc (2, 4)
	104 #7 (2, 4)
	105 -89 (2, 4)
	106 goto (2, 4)
	107 -46 (2, 4)
	109 iinc (2, 4)
	110 #3 (2, 4)
	111 -89 (2, 4)
	112 goto (2, 4)
	113 -97 (2, 4)
	115 new (1, 4)
	116 org/apache/commons/math3/linear/Array2DRowFieldMatrix (1, 4)
	118 dup (1, 4)
	119 aload_2 (1, 4)
	120 iconst_0 (1, 4)
	121 invokespecial (1, 4)
	122 org/apache/commons/math3/linear/Array2DRowFieldMatrix.<init>:([[Lorg/apache/commons/math3/FieldElement;Z)V (1, 4)
	124 areturn (1, 4)

Method: initializeHighOrderDerivatives
	0 aload_0 (0, 0)
	1 getfield (0, 0)
	2 org/apache/commons/math3/ode/nonstiff/AdamsNordsieckFieldTransformer.field:Lorg/apache/commons/math3/Field; (0, 0)
	4 aload_0 (0, 0)
	5 getfield (0, 0)
	6 org/apache/commons/math3/ode/nonstiff/AdamsNordsieckFieldTransformer.c1:[Lorg/apache/commons/math3/RealFieldElement; (0, 0)
	8 arraylength (0, 0)
	9 iconst_1 (0, 0)
	10 iadd (0, 0)
	11 aload_0 (0, 0)
	12 getfield (0, 0)
	13 org/apache/commons/math3/ode/nonstiff/AdamsNordsieckFieldTransformer.c1:[Lorg/apache/commons/math3/RealFieldElement; (0, 0)
	15 arraylength (0, 0)
	16 iconst_1 (0, 0)
	17 iadd (0, 0)
	18 invokestatic (0, 0)
	19 org/apache/commons/math3/util/MathArrays.buildArray:(Lorg/apache/commons/math3/Field;II)[[Ljava/lang/Object; (0, 0)
	21 checkcast (0, 0)
	22 [[Lorg/apache/commons/math3/RealFieldElement; (0, 0)
	24 astore (0, 0)
	25 #5 (0, 0)
	26 aload_0 (0, 0)
	27 getfield (0, 0)
	28 org/apache/commons/math3/ode/nonstiff/AdamsNordsieckFieldTransformer.field:Lorg/apache/commons/math3/Field; (0, 0)
	30 aload_0 (0, 0)
	31 getfield (0, 0)
	32 org/apache/commons/math3/ode/nonstiff/AdamsNordsieckFieldTransformer.c1:[Lorg/apache/commons/math3/RealFieldElement; (0, 0)
	34 arraylength (0, 0)
	35 iconst_1 (0, 0)
	36 iadd (0, 0)
	37 aload_3 (0, 0)
	38 iconst_0 (0, 0)
	39 aaload (0, 0)
	40 arraylength (0, 0)
	41 invokestatic (0, 0)
	42 org/apache/commons/math3/util/MathArrays.buildArray:(Lorg/apache/commons/math3/Field;II)[[Ljava/lang/Object; (0, 0)
	44 checkcast (0, 0)
	45 [[Lorg/apache/commons/math3/RealFieldElement; (0, 0)
	47 astore (0, 0)
	48 #6 (0, 0)
	49 aload_3 (0, 0)
	50 iconst_0 (0, 0)
	51 aaload (0, 0)
	52 astore (0, 0)
	53 #7 (0, 0)
	54 aload (0, 0)
	55 #4 (0, 0)
	56 iconst_0 (0, 0)
	57 aaload (0, 0)
	58 astore (0, 0)
	59 #8 (0, 0)
	60 iconst_1 (1, 4)
	61 istore (1, 4)
	62 #9 (1, 4)
	63 iload (1, 4)
	64 #9 (1, 4)
	65 aload_3 (1, 4)
	66 arraylength (1, 4)
	67 if_icmpge (1, 4)
	68 299 (1, 4)
	70 aload_2 (1, 4)
	71 iload (1, 4)
	72 #9 (1, 4)
	73 aaload (1, 4)
	74 aload_2 (1, 4)
	75 iconst_0 (1, 4)
	76 aaload (1, 4)
	77 invokeinterface (1, 4)
	78 org/apache/commons/math3/RealFieldElement.divide:(Ljava/lang/Object;)Ljava/lang/Object; (1, 4)
	80 0 (1, 4)
	82 checkcast (1, 4)
	83 org/apache/commons/math3/RealFieldElement (1, 4)
	85 astore (1, 4)
	86 #10 (1, 4)
	87 aload (1, 4)
	88 #10 (1, 4)
	89 aload_1 (1, 4)
	90 invokeinterface (1, 4)
	91 org/apache/commons/math3/RealFieldElement.reciprocal:()Ljava/lang/Object; (1, 4)
	93 0 (1, 4)
	95 checkcast (1, 4)
	96 org/apache/commons/math3/RealFieldElement (1, 4)
	98 astore (1, 4)
	99 #11 (1, 4)
	100 aload_1 (1, 4)
	101 invokeinterface (1, 4)
	102 org/apache/commons/math3/RealFieldElement.multiply:(Ljava/lang/Object;)Ljava/lang/Object; (1, 4)
	104 0 (1, 4)
	106 checkcast (1, 4)
	107 org/apache/commons/math3/RealFieldElement (1, 4)
	109 astore (1, 4)
	110 #12 (1, 4)
	111 aload (1, 4)
	112 #5 (1, 4)
	113 iconst_2 (1, 4)
	114 iload (1, 4)
	115 #9 (1, 4)
	116 imul (1, 4)
	117 iconst_2 (1, 4)
	118 isub (1, 4)
	119 aaload (1, 4)
	120 astore (1, 4)
	121 #13 (1, 4)
	122 iconst_2 (1, 4)
	123 iload (1, 4)
	124 #9 (1, 4)
	125 imul (1, 4)
	126 iconst_1 (1, 4)
	127 isub (1, 4)
	128 aload (1, 4)
	129 #5 (1, 4)
	130 arraylength (1, 4)
	131 if_icmpge (1, 4)
	132 15 (1, 4)
	134 aload (1, 4)
	135 #5 (1, 4)
	136 iconst_2 (1, 4)
	137 iload (1, 4)
	138 #9 (1, 4)
	139 imul (1, 4)
	140 iconst_1 (1, 4)
	141 isub (1, 4)
	142 aaload (1, 4)
	143 goto (1, 4)
	144 4 (1, 4)
	146 aconst_null (1, 4)
	147 astore (1, 4)
	148 #14 (1, 4)
	149 iconst_0 (2, 4)
	150 istore (2, 4)
	151 #15 (2, 4)
	152 iload (2, 4)
	153 #15 (2, 4)
	154 aload (2, 4)
	155 #13 (2, 4)
	156 arraylength (2, 4)
	157 if_icmpge (2, 4)
	158 64 (2, 4)
	160 aload (2, 4)
	161 #12 (2, 4)
	162 aload (2, 4)
	163 #11 (2, 4)
	164 invokeinterface (2, 4)
	165 org/apache/commons/math3/RealFieldElement.getRowDimension:()I (2, 4)
	167 0 (2, 4)
	169 checkcast (2, 4)
	170 org/apache/commons/math3/RealFieldElement (2, 4)
	172 astore (2, 4)
	173 #12 (2, 4)
	174 aload (2, 4)
	175 #13 (2, 4)
	176 iload (2, 4)
	177 #15 (2, 4)
	178 aload (2, 4)
	179 #10 (2, 4)
	180 aload (2, 4)
	181 #12 (2, 4)
	182 invokeinterface (2, 4)
	183 org/apache/commons/math3/RealFieldElement.getRowDimension:()I (2, 4)
	185 0 (2, 4)
	187 checkcast (2, 4)
	188 org/apache/commons/math3/RealFieldElement (2, 4)
	190 aastore (2, 4)
	191 aload (3, 1)
	192 #14 (3, 1)
	193 ifnull (3, 1)
	194 22 (3, 1)
	196 aload (3, 1)
	197 #14 (3, 1)
	198 iload (3, 1)
	199 #15 (3, 1)
	200 aload (3, 1)
	201 #12 (3, 1)
	202 iload (3, 1)
	203 #15 (3, 1)
	204 iconst_2 (3, 1)
	205 iadd (3, 1)
	206 invokeinterface (3, 1)
	207 org/apache/commons/math3/RealFieldElement.subtract:(Ljava/lang/Object;)Ljava/lang/Object; (3, 1)
	209 0 (3, 1)
	211 checkcast (3, 1)
	212 org/apache/commons/math3/RealFieldElement (3, 1)
	214 aastore (3, 1)
	215 iinc (3, 1)
	216 #15 (3, 1)
	217 -89 (3, 1)
	218 goto (3, 1)
	219 -66 (3, 1)
	221 aload_3 (2, 4)
	222 iload (2, 4)
	223 #9 (2, 4)
	224 aaload (2, 4)
	225 astore (2, 4)
	226 #15 (2, 4)
	227 aload (2, 4)
	228 #4 (2, 4)
	229 iload (2, 4)
	230 #9 (2, 4)
	231 aaload (2, 4)
	232 astore (2, 4)
	233 #16 (2, 4)
	234 aload (2, 4)
	235 #6 (2, 4)
	236 iconst_2 (2, 4)
	237 iload (2, 4)
	238 #9 (2, 4)
	239 imul (2, 4)
	240 iconst_2 (2, 4)
	241 isub (2, 4)
	242 aaload (2, 4)
	243 astore (2, 4)
	244 #17 (2, 4)
	245 iconst_2 (2, 4)
	246 iload (2, 4)
	247 #9 (2, 4)
	248 imul (2, 4)
	249 iconst_1 (2, 4)
	250 isub (2, 4)
	251 aload (2, 4)
	252 #6 (2, 4)
	253 arraylength (2, 4)
	254 if_icmpge (2, 4)
	255 15 (2, 4)
	257 aload (2, 4)
	258 #6 (2, 4)
	259 iconst_2 (2, 4)
	260 iload (2, 4)
	261 #9 (2, 4)
	262 imul (2, 4)
	263 iconst_1 (2, 4)
	264 isub (2, 4)
	265 aaload (2, 4)
	266 goto (2, 4)
	267 4 (2, 4)
	269 aconst_null (2, 4)
	270 astore (2, 4)
	271 #18 (2, 4)
	272 iconst_0 (3, 4)
	273 istore (3, 4)
	274 #19 (3, 4)
	275 iload (3, 4)
	276 #19 (3, 4)
	277 aload (3, 4)
	278 #15 (3, 4)
	279 arraylength (3, 4)
	280 if_icmpge (3, 4)
	281 80 (3, 4)
	283 aload (3, 4)
	284 #17 (3, 4)
	285 iload (3, 4)
	286 #19 (3, 4)
	287 aload (3, 4)
	288 #15 (3, 4)
	289 iload (3, 4)
	290 #19 (3, 4)
	291 aaload (3, 4)
	292 aload (3, 4)
	293 #7 (3, 4)
	294 iload (3, 4)
	295 #19 (3, 4)
	296 aaload (3, 4)
	297 invokeinterface (3, 4)
	298 org/apache/commons/math3/RealFieldElement.divide:(Ljava/lang/Object;)Ljava/lang/Object; (3, 4)
	300 0 (3, 4)
	302 checkcast (3, 4)
	303 org/apache/commons/math3/RealFieldElement (3, 4)
	305 aload (3, 4)
	306 #10 (3, 4)
	307 aload (3, 4)
	308 #8 (3, 4)
	309 iload (3, 4)
	310 #19 (3, 4)
	311 aaload (3, 4)
	312 invokeinterface (3, 4)
	313 org/apache/commons/math3/RealFieldElement.getRowDimension:()I (3, 4)
	315 0 (3, 4)
	317 invokeinterface (3, 4)
	318 org/apache/commons/math3/RealFieldElement.divide:(Ljava/lang/Object;)Ljava/lang/Object; (3, 4)
	320 0 (3, 4)
	322 checkcast (3, 4)
	323 org/apache/commons/math3/RealFieldElement (3, 4)
	325 aastore (3, 4)
	326 aload (4, 1)
	327 #18 (4, 1)
	328 ifnull (4, 1)
	329 26 (4, 1)
	331 aload (4, 1)
	332 #18 (4, 1)
	333 iload (4, 1)
	334 #19 (4, 1)
	335 aload (4, 1)
	336 #16 (4, 1)
	337 iload (4, 1)
	338 #19 (4, 1)
	339 aaload (4, 1)
	340 aload (4, 1)
	341 #8 (4, 1)
	342 iload (4, 1)
	343 #19 (4, 1)
	344 aaload (4, 1)
	345 invokeinterface (4, 1)
	346 org/apache/commons/math3/RealFieldElement.divide:(Ljava/lang/Object;)Ljava/lang/Object; (4, 1)
	348 0 (4, 1)
	350 checkcast (4, 1)
	351 org/apache/commons/math3/RealFieldElement (4, 1)
	353 aastore (4, 1)
	354 iinc (4, 1)
	355 #19 (4, 1)
	356 -89 (4, 1)
	357 goto (4, 1)
	358 -82 (4, 1)
	360 iinc (4, 1)
	361 #9 (4, 1)
	362 -89 (4, 1)
	363 goto (4, 1)
	364 -300 (4, 1)
	366 new (3, 4)
	367 org/apache/commons/math3/linear/FieldLUDecomposition (3, 4)
	369 dup (3, 4)
	370 new (3, 4)
	371 org/apache/commons/math3/linear/Array2DRowFieldMatrix (3, 4)
	373 dup (3, 4)
	374 aload (3, 4)
	375 #5 (3, 4)
	376 iconst_0 (3, 4)
	377 invokespecial (3, 4)
	378 org/apache/commons/math3/linear/Array2DRowFieldMatrix.<init>:([[Lorg/apache/commons/math3/FieldElement;Z)V (3, 4)
	380 invokespecial (3, 4)
	381 org/apache/commons/math3/linear/FieldLUDecomposition.<init>:(Lorg/apache/commons/math3/linear/FieldMatrix;)V (3, 4)
	383 astore (3, 4)
	384 #9 (3, 4)
	385 aload (3, 4)
	386 #9 (3, 4)
	387 invokevirtual (3, 4)
	388 org/apache/commons/math3/linear/FieldLUDecomposition.getSolver:()Lorg/apache/commons/math3/linear/FieldDecompositionSolver; (3, 4)
	390 new (3, 4)
	391 org/apache/commons/math3/linear/Array2DRowFieldMatrix (3, 4)
	393 dup (3, 4)
	394 aload (3, 4)
	395 #6 (3, 4)
	396 iconst_0 (3, 4)
	397 invokespecial (3, 4)
	398 org/apache/commons/math3/linear/Array2DRowFieldMatrix.<init>:([[Lorg/apache/commons/math3/FieldElement;Z)V (3, 4)
	400 invokeinterface (3, 4)
	401 org/apache/commons/math3/linear/FieldDecompositionSolver.<init>:([[Lorg/apache/commons/math3/FieldElement;)V (3, 4)
	403 0 (3, 4)
	405 astore (3, 4)
	406 #10 (3, 4)
	407 new (3, 4)
	408 org/apache/commons/math3/linear/Array2DRowFieldMatrix (3, 4)
	410 dup (3, 4)
	411 aload_0 (3, 4)
	412 getfield (3, 4)
	413 org/apache/commons/math3/ode/nonstiff/AdamsNordsieckFieldTransformer.field:Lorg/apache/commons/math3/Field; (3, 4)
	415 aload (3, 4)
	416 #10 (3, 4)
	417 invokeinterface (3, 4)
	418 org/apache/commons/math3/linear/FieldMatrix.getColumnDimension:()I (3, 4)
	420 0 (3, 4)
	422 iconst_1 (3, 4)
	423 isub (3, 4)
	424 aload (3, 4)
	425 #10 (3, 4)
	426 invokeinterface (3, 4)
	427 org/apache/commons/math3/linear/FieldMatrix.<init>:(Lorg/apache/commons/math3/Field;II)V (3, 4)
	429 0 (3, 4)
	431 invokespecial (3, 4)
	432 org/apache/commons/math3/linear/Array2DRowFieldMatrix.<init>:(Lorg/apache/commons/math3/Field;II)V (3, 4)
	434 astore (3, 4)
	435 #11 (3, 4)
	436 iconst_0 (4, 4)
	437 istore (4, 4)
	438 #12 (4, 4)
	439 iload (4, 4)
	440 #12 (4, 4)
	441 aload (4, 4)
	442 #11 (4, 4)
	443 invokevirtual (4, 4)
	444 org/apache/commons/math3/linear/Array2DRowFieldMatrix.getRowDimension:()I (4, 4)
	446 if_icmpge (4, 4)
	447 48 (4, 4)
	449 iconst_0 (5, 4)
	450 istore (5, 4)
	451 #13 (5, 4)
	452 iload (5, 4)
	453 #13 (5, 4)
	454 aload (5, 4)
	455 #11 (5, 4)
	456 invokevirtual (5, 4)
	457 org/apache/commons/math3/linear/Array2DRowFieldMatrix.getColumnDimension:()I (5, 4)
	459 if_icmpge (5, 4)
	460 29 (5, 4)
	462 aload (5, 4)
	463 #11 (5, 4)
	464 iload (5, 4)
	465 #12 (5, 4)
	466 iload (5, 4)
	467 #13 (5, 4)
	468 aload (5, 4)
	469 #10 (5, 4)
	470 iload (5, 4)
	471 #12 (5, 4)
	472 iload (5, 4)
	473 #13 (5, 4)
	474 invokeinterface (5, 4)
	475 org/apache/commons/math3/linear/FieldMatrix.setEntry:(IILorg/apache/commons/math3/FieldElement;)V (5, 4)
	477 0 (5, 4)
	479 invokevirtual (5, 4)
	480 org/apache/commons/math3/linear/Array2DRowFieldMatrix.setEntry:(IILorg/apache/commons/math3/FieldElement;)V (5, 4)
	482 iinc (5, 4)
	483 #13 (5, 4)
	484 -89 (5, 4)
	485 goto (5, 4)
	486 -33 (5, 4)
	488 iinc (5, 4)
	489 #12 (5, 4)
	490 -89 (5, 4)
	491 goto (5, 4)
	492 -52 (5, 4)
	494 aload (4, 4)
	495 #11 (4, 4)
	496 areturn (4, 4)

Method: updateHighOrderDerivativesPhase1
	0 aload_0 (0, 0)
	1 getfield (0, 0)
	2 org/apache/commons/math3/ode/nonstiff/AdamsNordsieckFieldTransformer.update:Lorg/apache/commons/math3/linear/Array2DRowFieldMatrix; (0, 0)
	4 aload_1 (0, 0)
	5 invokevirtual (0, 0)
	6 org/apache/commons/math3/linear/Array2DRowFieldMatrix.multiply:(Lorg/apache/commons/math3/linear/Array2DRowFieldMatrix;)Lorg/apache/commons/math3/linear/Array2DRowFieldMatrix; (0, 0)
	8 areturn (0, 0)

Method: updateHighOrderDerivativesPhase2
	0 aload_3 (0, 0)
	1 invokevirtual (0, 0)
	2 org/apache/commons/math3/linear/Array2DRowFieldMatrix.getDataRef:()[[Lorg/apache/commons/math3/FieldElement; (0, 0)
	4 checkcast (0, 0)
	5 [[Lorg/apache/commons/math3/RealFieldElement; (0, 0)
	7 astore (0, 0)
	8 #4 (0, 0)
	9 iconst_0 (1, 4)
	10 istore (1, 4)
	11 #5 (1, 4)
	12 iload (1, 4)
	13 #5 (1, 4)
	14 aload (1, 4)
	15 #4 (1, 4)
	16 arraylength (1, 4)
	17 if_icmpge (1, 4)
	18 80 (1, 4)
	20 aload (1, 4)
	21 #4 (1, 4)
	22 iload (1, 4)
	23 #5 (1, 4)
	24 aaload (1, 4)
	25 astore (1, 4)
	26 #6 (1, 4)
	27 aload_0 (1, 4)
	28 getfield (1, 4)
	29 org/apache/commons/math3/ode/nonstiff/AdamsNordsieckFieldTransformer.c1:[Lorg/apache/commons/math3/RealFieldElement; (1, 4)
	31 iload (1, 4)
	32 #5 (1, 4)
	33 aaload (1, 4)
	34 astore (1, 4)
	35 #7 (1, 4)
	36 iconst_0 (2, 4)
	37 istore (2, 4)
	38 #8 (2, 4)
	39 iload (2, 4)
	40 #8 (2, 4)
	41 aload (2, 4)
	42 #6 (2, 4)
	43 arraylength (2, 4)
	44 if_icmpge (2, 4)
	45 47 (2, 4)
	47 aload (2, 4)
	48 #6 (2, 4)
	49 iload (2, 4)
	50 #8 (2, 4)
	51 aload (2, 4)
	52 #6 (2, 4)
	53 iload (2, 4)
	54 #8 (2, 4)
	55 aaload (2, 4)
	56 aload (2, 4)
	57 #7 (2, 4)
	58 aload_1 (2, 4)
	59 iload (2, 4)
	60 #8 (2, 4)
	61 aaload (2, 4)
	62 aload_2 (2, 4)
	63 iload (2, 4)
	64 #8 (2, 4)
	65 aaload (2, 4)
	66 invokeinterface (2, 4)
	67 org/apache/commons/math3/RealFieldElement.divide:(Ljava/lang/Object;)Ljava/lang/Object; (2, 4)
	69 0 (2, 4)
	71 invokeinterface (2, 4)
	72 org/apache/commons/math3/RealFieldElement.getRowDimension:()I (2, 4)
	74 0 (2, 4)
	76 invokeinterface (2, 4)
	77 org/apache/commons/math3/RealFieldElement.java/lang/Object (2, 4)
	79 0 (2, 4)
	81 checkcast (2, 4)
	82 org/apache/commons/math3/RealFieldElement (2, 4)
	84 aastore (2, 4)
	85 iinc (2, 4)
	86 #8 (2, 4)
	87 -89 (2, 4)
	88 goto (2, 4)
	89 -49 (2, 4)
	91 iinc (2, 4)
	92 #5 (2, 4)
	93 -89 (2, 4)
	94 goto (2, 4)
	95 -82 (2, 4)
	97 return (0, 0)

Method: <clinit>
	0 new (0, 4)
	1 java/util/HashMap (0, 4)
	3 dup (0, 4)
	4 invokespecial (0, 4)
	5 java/util/HashMap.<init>:()V (0, 4)
	7 putstatic (0, 4)
	8 org/apache/commons/math3/ode/nonstiff/AdamsNordsieckFieldTransformer.CACHE:Ljava/util/Map; (0, 4)
	10 return (0, 4)

