Method: <init>
	0 aload_0 (0, 0)
	1 aload_1 (0, 0)
	2 aload_2 (0, 0)
	3 iload_3 (0, 0)
	4 iload (0, 0)
	5 #4 (0, 0)
	6 dload (0, 0)
	7 #5 (0, 0)
	8 dload (0, 0)
	9 #7 (0, 0)
	10 aload (0, 0)
	11 #9 (0, 0)
	12 aload (0, 0)
	13 #10 (0, 0)
	14 invokespecial (0, 0)
	15 org/apache/commons/math3/ode/MultistepFieldIntegrator.<init>:(Lorg/apache/commons/math3/Field;Ljava/lang/String;IIDD[D[D)V (0, 0)
	17 aload_0 (1, 4)
	18 aload_1 (1, 4)
	19 iload_3 (1, 4)
	20 invokestatic (1, 4)
	21 org/apache/commons/math3/ode/nonstiff/AdamsNordsieckFieldTransformer.getInstance:(Lorg/apache/commons/math3/Field;I)Lorg/apache/commons/math3/ode/nonstiff/AdamsNordsieckFieldTransformer; (1, 4)
	23 putfield (1, 4)
	24 org/apache/commons/math3/ode/nonstiff/AdamsFieldIntegrator.transformer:Lorg/apache/commons/math3/ode/nonstiff/AdamsNordsieckFieldTransformer; (1, 4)
	26 return (0, 4)

Method: initializeHighOrderDerivatives
	0 aload_0 (1, 4)
	1 getfield (1, 4)
	2 org/apache/commons/math3/ode/nonstiff/AdamsFieldIntegrator.transformer:Lorg/apache/commons/math3/ode/nonstiff/AdamsNordsieckFieldTransformer; (1, 4)
	4 aload_1 (1, 4)
	5 aload_2 (1, 4)
	6 aload_3 (1, 4)
	7 aload (1, 4)
	8 #4 (1, 4)
	9 invokevirtual (1, 4)
	10 org/apache/commons/math3/ode/nonstiff/AdamsNordsieckFieldTransformer.initializeHighOrderDerivatives:(Lorg/apache/commons/math3/RealFieldElement;[Lorg/apache/commons/math3/RealFieldElement;[[Lorg/apache/commons/math3/RealFieldElement;[[Lorg/apache/commons/math3/RealFieldElement;)Lorg/apache/commons/math3/linear/Array2DRowFieldMatrix; (1, 4)
	12 areturn (0, 4)

Method: updateHighOrderDerivativesPhase1
	0 aload_0 (1, 4)
	1 getfield (1, 4)
	2 org/apache/commons/math3/ode/nonstiff/AdamsFieldIntegrator.transformer:Lorg/apache/commons/math3/ode/nonstiff/AdamsNordsieckFieldTransformer; (1, 4)
	4 aload_1 (1, 4)
	5 invokevirtual (1, 4)
	6 org/apache/commons/math3/ode/nonstiff/AdamsNordsieckFieldTransformer.updateHighOrderDerivativesPhase1:(Lorg/apache/commons/math3/linear/Array2DRowFieldMatrix;)Lorg/apache/commons/math3/linear/Array2DRowFieldMatrix; (1, 4)
	8 areturn (0, 4)

Method: updateHighOrderDerivativesPhase2
	0 aload_0 (1, 4)
	1 getfield (1, 4)
	2 org/apache/commons/math3/ode/nonstiff/AdamsFieldIntegrator.transformer:Lorg/apache/commons/math3/ode/nonstiff/AdamsNordsieckFieldTransformer; (1, 4)
	4 aload_1 (1, 4)
	5 aload_2 (1, 4)
	6 aload_3 (1, 4)
	7 invokevirtual (1, 4)
	8 org/apache/commons/math3/ode/nonstiff/AdamsNordsieckFieldTransformer.updateHighOrderDerivativesPhase2:([Lorg/apache/commons/math3/RealFieldElement;[Lorg/apache/commons/math3/RealFieldElement;Lorg/apache/commons/math3/linear/Array2DRowFieldMatrix;)V (1, 4)
	10 return (0, 4)

