Method: <init>
	0 aload_0 (0, 0)
	1 aload_1 (0, 0)
	2 iload_2 (0, 0)
	3 iload_3 (0, 0)
	4 dload (0, 0)
	5 #4 (0, 0)
	6 dload (0, 0)
	7 #6 (0, 0)
	8 aload (0, 0)
	9 #8 (0, 0)
	10 aload (0, 0)
	11 #9 (0, 0)
	12 invokespecial (0, 0)
	13 org/apache/commons/math3/ode/MultistepIntegrator.<init>:(Ljava/lang/String;IIDD[D[D)V (0, 0)
	15 aload_0 (1, 4)
	16 iload_2 (1, 4)
	17 invokestatic (1, 4)
	18 org/apache/commons/math3/ode/nonstiff/AdamsNordsieckTransformer.getInstance:(I)Lorg/apache/commons/math3/ode/nonstiff/AdamsNordsieckTransformer; (1, 4)
	20 putfield (1, 4)
	21 org/apache/commons/math3/ode/nonstiff/AdamsIntegrator.transformer:Lorg/apache/commons/math3/ode/nonstiff/AdamsNordsieckTransformer; (1, 4)
	23 return (0, 4)

Method: initializeHighOrderDerivatives
	0 aload_0 (1, 4)
	1 getfield (1, 4)
	2 org/apache/commons/math3/ode/nonstiff/AdamsIntegrator.transformer:Lorg/apache/commons/math3/ode/nonstiff/AdamsNordsieckTransformer; (1, 4)
	4 dload_1 (1, 4)
	5 aload_3 (1, 4)
	6 aload (1, 4)
	7 #4 (1, 4)
	8 aload (1, 4)
	9 #5 (1, 4)
	10 invokevirtual (1, 4)
	11 org/apache/commons/math3/ode/nonstiff/AdamsNordsieckTransformer.initializeHighOrderDerivatives:(D[D[[D[[D)Lorg/apache/commons/math3/linear/Array2DRowRealMatrix; (1, 4)
	13 areturn (0, 4)

Method: updateHighOrderDerivativesPhase1
	0 aload_0 (1, 4)
	1 getfield (1, 4)
	2 org/apache/commons/math3/ode/nonstiff/AdamsIntegrator.transformer:Lorg/apache/commons/math3/ode/nonstiff/AdamsNordsieckTransformer; (1, 4)
	4 aload_1 (1, 4)
	5 invokevirtual (1, 4)
	6 org/apache/commons/math3/ode/nonstiff/AdamsNordsieckTransformer.updateHighOrderDerivativesPhase1:(Lorg/apache/commons/math3/linear/Array2DRowRealMatrix;)Lorg/apache/commons/math3/linear/Array2DRowRealMatrix; (1, 4)
	8 areturn (0, 4)

Method: updateHighOrderDerivativesPhase2
	0 aload_0 (1, 4)
	1 getfield (1, 4)
	2 org/apache/commons/math3/ode/nonstiff/AdamsIntegrator.transformer:Lorg/apache/commons/math3/ode/nonstiff/AdamsNordsieckTransformer; (1, 4)
	4 aload_1 (1, 4)
	5 aload_2 (1, 4)
	6 aload_3 (1, 4)
	7 invokevirtual (1, 4)
	8 org/apache/commons/math3/ode/nonstiff/AdamsNordsieckTransformer.updateHighOrderDerivativesPhase2:([D[DLorg/apache/commons/math3/linear/Array2DRowRealMatrix;)V (1, 4)
	10 return (0, 4)

