Method: <init>
	0 aload_0 (0, 0)
	1 aload_1 (0, 0)
	2 putfield (0, 0)
	3 org/apache/commons/math3/ode/nonstiff/AdamsMoultonFieldIntegrator$Corrector.this$0:Lorg/apache/commons/math3/ode/nonstiff/AdamsMoultonFieldIntegrator; (0, 0)
	5 aload_0 (0, 0)
	6 invokespecial (0, 0)
	7 java/lang/Object.<init>:()V (0, 0)
	9 aload_0 (0, 0)
	10 aload_2 (0, 0)
	11 putfield (0, 0)
	12 org/apache/commons/math3/ode/nonstiff/AdamsMoultonFieldIntegrator$Corrector.previous:[Lorg/apache/commons/math3/RealFieldElement; (0, 0)
	14 aload_0 (0, 0)
	15 aload_3 (0, 0)
	16 putfield (0, 0)
	17 org/apache/commons/math3/ode/nonstiff/AdamsMoultonFieldIntegrator$Corrector.scaled:[Lorg/apache/commons/math3/RealFieldElement; (0, 0)
	19 aload_0 (0, 0)
	20 aload (0, 0)
	21 #4 (0, 0)
	22 putfield (0, 0)
	23 org/apache/commons/math3/ode/nonstiff/AdamsMoultonFieldIntegrator$Corrector.after:[Lorg/apache/commons/math3/RealFieldElement; (0, 0)
	25 aload_0 (1, 4)
	26 aload (1, 4)
	27 #4 (1, 4)
	28 invokevirtual (1, 4)
	29 [Lorg/apache/commons/math3/RealFieldElement;.clone:()Ljava/lang/Object; (1, 4)
	31 checkcast (1, 4)
	32 [Lorg/apache/commons/math3/RealFieldElement; (1, 4)
	34 putfield (1, 4)
	35 org/apache/commons/math3/ode/nonstiff/AdamsMoultonFieldIntegrator$Corrector.before:[Lorg/apache/commons/math3/RealFieldElement; (1, 4)
	37 return (0, 0)

Method: start
	0 aload_0 (0, 0)
	1 getfield (0, 0)
	2 org/apache/commons/math3/ode/nonstiff/AdamsMoultonFieldIntegrator$Corrector.after:[Lorg/apache/commons/math3/RealFieldElement; (0, 0)
	4 aload_0 (0, 0)
	5 getfield (0, 0)
	6 org/apache/commons/math3/ode/nonstiff/AdamsMoultonFieldIntegrator$Corrector.this$0:Lorg/apache/commons/math3/ode/nonstiff/AdamsMoultonFieldIntegrator; (0, 0)
	8 invokevirtual (0, 0)
	9 org/apache/commons/math3/ode/nonstiff/AdamsMoultonFieldIntegrator.getField:()Lorg/apache/commons/math3/Field; (0, 0)
	11 invokeinterface (0, 0)
	12 org/apache/commons/math3/Field.java/util/Arrays (0, 0)
	14 0 (0, 0)
	16 invokestatic (0, 0)
	17 java/util/Arrays.fill:([Ljava/lang/Object;Ljava/lang/Object;)V (0, 0)
	19 return (0, 0)

Method: visit
	0 aload_0 (0, 0)
	1 iload_1 (0, 0)
	2 iload_2 (0, 0)
	3 aload_3 (0, 0)
	4 checkcast (0, 0)
	5 org/apache/commons/math3/RealFieldElement (0, 0)
	7 invokevirtual (0, 0)
	8 org/apache/commons/math3/ode/nonstiff/AdamsMoultonFieldIntegrator$Corrector.visit:(IILorg/apache/commons/math3/RealFieldElement;)V (0, 0)
	10 return (0, 0)

Method: end
	0 aload_0 (0, 0)
	1 invokevirtual (0, 0)
	2 org/apache/commons/math3/ode/nonstiff/AdamsMoultonFieldIntegrator$Corrector.end:()Lorg/apache/commons/math3/RealFieldElement; (0, 0)
	4 areturn (0, 0)

