Method: <init>
	0 aload_0 (0, 0)
	1 ldc (0, 0)
	2 Adams-Bashforth (0, 0)
	3 iload_1 (0, 0)
	4 iload_1 (0, 0)
	5 dload_2 (0, 0)
	6 dload (0, 0)
	7 #4 (0, 0)
	8 aload (0, 0)
	9 #6 (0, 0)
	10 aload (0, 0)
	11 #7 (0, 0)
	12 invokespecial (0, 0)
	13 org/apache/commons/math3/ode/nonstiff/AdamsIntegrator.<init>:(Ljava/lang/String;IIDD[D[D)V (0, 0)
	15 return (0, 0)

Method: errorEstimation
	0 dconst_0 (0, 0)
	1 dstore (0, 0)
	2 #5 (0, 0)
	3 iconst_0 (1, 4)
	4 istore (1, 4)
	5 #7 (1, 4)
	6 iload (1, 4)
	7 #7 (1, 4)
	8 aload_0 (1, 4)
	9 getfield (1, 4)
	10 org/apache/commons/math3/ode/nonstiff/AdamsBashforthIntegrator.mainSetDimension:I (1, 4)
	12 if_icmpge (1, 4)
	13 165 (1, 4)
	15 aload_2 (1, 4)
	16 iload (1, 4)
	17 #7 (1, 4)
	18 daload (1, 4)
	19 invokestatic (1, 4)
	20 org/apache/commons/math3/util/FastMath.abs:(D)D (1, 4)
	22 dstore (1, 4)
	23 #8 (1, 4)
	24 aload_0 (1, 4)
	25 getfield (1, 4)
	26 org/apache/commons/math3/ode/nonstiff/AdamsBashforthIntegrator.vecAbsoluteTolerance:[D (1, 4)
	28 ifnonnull (1, 4)
	29 18 (1, 4)
	31 aload_0 (1, 4)
	32 getfield (1, 4)
	33 org/apache/commons/math3/ode/nonstiff/AdamsBashforthIntegrator.scalAbsoluteTolerance:D (1, 4)
	35 aload_0 (1, 4)
	36 getfield (1, 4)
	37 org/apache/commons/math3/ode/nonstiff/AdamsBashforthIntegrator.scalRelativeTolerance:D (1, 4)
	39 dload (1, 4)
	40 #8 (1, 4)
	41 dmul (1, 4)
	42 dadd (1, 4)
	43 goto (1, 4)
	44 21 (1, 4)
	46 aload_0 (1, 4)
	47 getfield (1, 4)
	48 org/apache/commons/math3/ode/nonstiff/AdamsBashforthIntegrator.vecAbsoluteTolerance:[D (1, 4)
	50 iload (1, 4)
	51 #7 (1, 4)
	52 daload (1, 4)
	53 aload_0 (1, 4)
	54 getfield (1, 4)
	55 org/apache/commons/math3/ode/nonstiff/AdamsBashforthIntegrator.vecRelativeTolerance:[D (1, 4)
	57 iload (1, 4)
	58 #7 (1, 4)
	59 daload (1, 4)
	60 dload (1, 4)
	61 #8 (1, 4)
	62 dmul (1, 4)
	63 dadd (1, 4)
	64 dstore (1, 4)
	65 #10 (1, 4)
	66 dconst_0 (1, 4)
	67 dstore (1, 4)
	68 #12 (1, 4)
	69 aload (1, 4)
	70 #4 (1, 4)
	71 invokeinterface (1, 4)
	72 org/apache/commons/math3/linear/RealMatrix.getEntry:(II)D (1, 4)
	74 0 (1, 4)
	76 iconst_2 (1, 4)
	77 irem (1, 4)
	78 ifne (1, 4)
	79 7 (1, 4)
	81 iconst_m1 (1, 4)
	82 goto (1, 4)
	83 4 (1, 4)
	85 iconst_1 (1, 4)
	86 istore (1, 4)
	87 #14 (1, 4)
	88 aload (2, 4)
	89 #4 (2, 4)
	90 invokeinterface (2, 4)
	91 org/apache/commons/math3/linear/RealMatrix.getEntry:(II)D (2, 4)
	93 0 (2, 4)
	95 iconst_1 (2, 4)
	96 isub (2, 4)
	97 istore (2, 4)
	98 #15 (2, 4)
	99 iload (2, 4)
	100 #15 (2, 4)
	101 iflt (2, 4)
	102 34 (2, 4)
	104 dload (2, 4)
	105 #12 (2, 4)
	106 iload (2, 4)
	107 #14 (2, 4)
	108 i2d (2, 4)
	109 aload (2, 4)
	110 #4 (2, 4)
	111 iload (2, 4)
	112 #15 (2, 4)
	113 iload (2, 4)
	114 #7 (2, 4)
	115 invokeinterface (2, 4)
	116 org/apache/commons/math3/linear/RealMatrix.sqrt:(D)D (2, 4)
	118 0 (2, 4)
	120 dmul (2, 4)
	121 dadd (2, 4)
	122 dstore (2, 4)
	123 #12 (2, 4)
	124 iload (2, 4)
	125 #14 (2, 4)
	126 ineg (2, 4)
	127 istore (2, 4)
	128 #14 (2, 4)
	129 iinc (2, 4)
	130 #15 (2, 4)
	131 -89 (2, 4)
	132 goto (2, 4)
	133 -33 (2, 4)
	135 dload (1, 4)
	136 #12 (1, 4)
	137 aload_3 (1, 4)
	138 iload (1, 4)
	139 #7 (1, 4)
	140 daload (1, 4)
	141 dsub (1, 4)
	142 dstore (1, 4)
	143 #12 (1, 4)
	144 aload_2 (1, 4)
	145 iload (1, 4)
	146 #7 (1, 4)
	147 daload (1, 4)
	148 aload_1 (1, 4)
	149 iload (1, 4)
	150 #7 (1, 4)
	151 daload (1, 4)
	152 dsub (1, 4)
	153 dload (1, 4)
	154 #12 (1, 4)
	155 dadd (1, 4)
	156 dload (1, 4)
	157 #10 (1, 4)
	158 ddiv (1, 4)
	159 dstore (1, 4)
	160 #15 (1, 4)
	161 dload (1, 4)
	162 #5 (1, 4)
	163 dload (1, 4)
	164 #15 (1, 4)
	165 dload (1, 4)
	166 #15 (1, 4)
	167 dmul (1, 4)
	168 dadd (1, 4)
	169 dstore (1, 4)
	170 #5 (1, 4)
	171 iinc (1, 4)
	172 #7 (1, 4)
	173 -89 (1, 4)
	174 goto (1, 4)
	175 -168 (1, 4)
	177 dload (0, 0)
	178 #5 (0, 0)
	179 aload_0 (0, 0)
	180 getfield (0, 0)
	181 org/apache/commons/math3/ode/nonstiff/AdamsBashforthIntegrator.mainSetDimension:I (0, 0)
	183 i2d (0, 0)
	184 ddiv (0, 0)
	185 invokestatic (0, 0)
	186 org/apache/commons/math3/util/FastMath.sqrt:(D)D (0, 0)
	188 dreturn (0, 0)

Method: integrate
	0 aload_0 (0, 0)
	1 aload_1 (0, 0)
	2 dload_2 (0, 0)
	3 invokevirtual (0, 0)
	4 org/apache/commons/math3/ode/nonstiff/AdamsBashforthIntegrator.sanityChecks:(Lorg/apache/commons/math3/ode/ExpandableStatefulODE;D)V (0, 0)
	6 aload_0 (0, 0)
	7 aload_1 (0, 0)
	8 invokevirtual (0, 0)
	9 org/apache/commons/math3/ode/nonstiff/AdamsBashforthIntegrator.setEquations:(Lorg/apache/commons/math3/ode/ExpandableStatefulODE;)V (0, 0)
	11 dload_2 (0, 4)
	12 aload_1 (0, 4)
	13 invokevirtual (0, 4)
	14 org/apache/commons/math3/ode/ExpandableStatefulODE.getTime:()D (0, 4)
	16 dcmpl (0, 4)
	17 ifle (0, 4)
	18 7 (0, 4)
	20 iconst_1 (0, 4)
	21 goto (0, 4)
	22 4 (0, 4)
	24 iconst_0 (0, 4)
	25 istore (0, 4)
	26 #4 (0, 4)
	27 aload_1 (0, 4)
	28 invokevirtual (0, 4)
	29 org/apache/commons/math3/ode/ExpandableStatefulODE.getCompleteState:()[D (0, 4)
	31 astore (0, 4)
	32 #5 (0, 4)
	33 aload (0, 4)
	34 #5 (0, 4)
	35 arraylength (0, 4)
	36 newarray (0, 4)
	37 7 (0, 4)
	38 astore (0, 4)
	39 #6 (0, 4)
	40 new (0, 4)
	41 org/apache/commons/math3/ode/sampling/NordsieckStepInterpolator (0, 4)
	43 dup (0, 4)
	44 invokespecial (0, 4)
	45 org/apache/commons/math3/ode/sampling/NordsieckStepInterpolator.<init>:()V (0, 4)
	47 astore (0, 4)
	48 #7 (0, 4)
	49 aload (0, 4)
	50 #7 (0, 4)
	51 aload (0, 4)
	52 #5 (0, 4)
	53 iload (0, 4)
	54 #4 (0, 4)
	55 aload_1 (0, 4)
	56 invokevirtual (0, 4)
	57 org/apache/commons/math3/ode/ExpandableStatefulODE.getPrimaryMapper:()Lorg/apache/commons/math3/ode/EquationsMapper; (0, 4)
	59 aload_1 (0, 4)
	60 invokevirtual (0, 4)
	61 org/apache/commons/math3/ode/ExpandableStatefulODE.getSecondaryMappers:()[Lorg/apache/commons/math3/ode/EquationsMapper; (0, 4)
	63 invokevirtual (0, 4)
	64 org/apache/commons/math3/ode/sampling/NordsieckStepInterpolator.reinitialize:([DZLorg/apache/commons/math3/ode/EquationsMapper;[Lorg/apache/commons/math3/ode/EquationsMapper;)V (0, 4)
	66 aload_0 (0, 4)
	67 aload_1 (0, 4)
	68 invokevirtual (0, 4)
	69 org/apache/commons/math3/ode/ExpandableStatefulODE.getTime:()D (0, 4)
	71 aload (0, 4)
	72 #5 (0, 4)
	73 dload_2 (0, 4)
	74 invokevirtual (0, 4)
	75 org/apache/commons/math3/ode/nonstiff/AdamsBashforthIntegrator.initIntegration:(D[DD)V (0, 4)
	77 aload_0 (0, 4)
	78 aload_1 (0, 4)
	79 invokevirtual (0, 4)
	80 org/apache/commons/math3/ode/ExpandableStatefulODE.getTime:()D (0, 4)
	82 aload (0, 4)
	83 #5 (0, 4)
	84 dload_2 (0, 4)
	85 invokevirtual (0, 4)
	86 org/apache/commons/math3/ode/nonstiff/AdamsBashforthIntegrator.start:(D[DD)V (0, 4)
	88 aload (0, 4)
	89 #7 (0, 4)
	90 aload_0 (0, 4)
	91 getfield (0, 4)
	92 org/apache/commons/math3/ode/nonstiff/AdamsBashforthIntegrator.stepStart:D (0, 4)
	94 aload_0 (0, 4)
	95 getfield (0, 4)
	96 org/apache/commons/math3/ode/nonstiff/AdamsBashforthIntegrator.stepSize:D (0, 4)
	98 aload_0 (0, 4)
	99 getfield (0, 4)
	100 org/apache/commons/math3/ode/nonstiff/AdamsBashforthIntegrator.scaled:[D (0, 4)
	102 aload_0 (0, 4)
	103 getfield (0, 4)
	104 org/apache/commons/math3/ode/nonstiff/AdamsBashforthIntegrator.nordsieck:Lorg/apache/commons/math3/linear/Array2DRowRealMatrix; (0, 4)
	106 invokevirtual (0, 4)
	107 org/apache/commons/math3/ode/sampling/NordsieckStepInterpolator.reinitialize:(DD[DLorg/apache/commons/math3/linear/Array2DRowRealMatrix;)V (0, 4)
	109 aload (0, 4)
	110 #7 (0, 4)
	111 aload_0 (0, 4)
	112 getfield (0, 4)
	113 org/apache/commons/math3/ode/nonstiff/AdamsBashforthIntegrator.stepStart:D (0, 4)
	115 invokevirtual (0, 4)
	116 org/apache/commons/math3/ode/sampling/NordsieckStepInterpolator.storeTime:(D)V (0, 4)
	118 aload_0 (0, 4)
	119 getfield (0, 4)
	120 org/apache/commons/math3/ode/nonstiff/AdamsBashforthIntegrator.stepSize:D (0, 4)
	122 dstore (0, 4)
	123 #8 (0, 4)
	124 aload (0, 4)
	125 #7 (0, 4)
	126 dload (0, 4)
	127 #8 (0, 4)
	128 invokevirtual (0, 4)
	129 org/apache/commons/math3/ode/sampling/NordsieckStepInterpolator.rescale:(D)V (0, 4)
	131 aload_0 (0, 4)
	132 iconst_0 (0, 4)
	133 putfield (0, 4)
	134 org/apache/commons/math3/ode/nonstiff/AdamsBashforthIntegrator.isLastStep:Z (0, 4)
	136 aload (1, 1)
	137 #7 (1, 1)
	138 invokevirtual (1, 1)
	139 org/apache/commons/math3/ode/sampling/NordsieckStepInterpolator.shift:()V (1, 1)
	141 aload (1, 1)
	142 #5 (1, 1)
	143 arraylength (1, 1)
	144 newarray (1, 1)
	145 7 (1, 1)
	146 astore (1, 1)
	147 #10 (1, 1)
	148 aload (1, 1)
	149 #5 (1, 1)
	150 arraylength (1, 1)
	151 newarray (1, 1)
	152 7 (1, 1)
	153 astore (1, 1)
	154 #11 (1, 1)
	155 aconst_null (1, 1)
	156 astore (1, 1)
	157 #12 (1, 1)
	158 ldc2_w (1, 1)
	159 10.0 (1, 1)
	161 dstore (1, 1)
	162 #13 (1, 1)
	163 dload (2, 3)
	164 #13 (2, 3)
	165 dconst_1 (2, 3)
	166 dcmpl (2, 3)
	167 iflt (2, 3)
	168 214 (2, 3)
	170 aload_0 (2, 3)
	171 getfield (2, 3)
	172 org/apache/commons/math3/ode/nonstiff/AdamsBashforthIntegrator.stepStart:D (2, 3)
	174 dload (2, 3)
	175 #8 (2, 3)
	176 dadd (2, 3)
	177 dstore (2, 3)
	178 #15 (2, 3)
	179 aload (2, 3)
	180 #7 (2, 3)
	181 dload (2, 3)
	182 #15 (2, 3)
	183 invokevirtual (2, 3)
	184 org/apache/commons/math3/ode/sampling/NordsieckStepInterpolator.storeTime:(D)V (2, 3)
	186 aload_0 (2, 3)
	187 invokevirtual (2, 3)
	188 org/apache/commons/math3/ode/nonstiff/AdamsBashforthIntegrator.getExpandable:()Lorg/apache/commons/math3/ode/ExpandableStatefulODE; (2, 3)
	190 astore (2, 3)
	191 #17 (2, 3)
	192 aload (2, 3)
	193 #17 (2, 3)
	194 invokevirtual (2, 3)
	195 org/apache/commons/math3/ode/ExpandableStatefulODE.getPrimaryMapper:()Lorg/apache/commons/math3/ode/EquationsMapper; (2, 3)
	197 astore (2, 3)
	198 #18 (2, 3)
	199 aload (2, 3)
	200 #18 (2, 3)
	201 aload (2, 3)
	202 #7 (2, 3)
	203 invokevirtual (2, 3)
	204 org/apache/commons/math3/ode/sampling/NordsieckStepInterpolator.getInterpolatedState:()[D (2, 3)
	206 aload (2, 3)
	207 #10 (2, 3)
	208 invokevirtual (2, 3)
	209 org/apache/commons/math3/ode/EquationsMapper.insertEquationData:([D[D)V (2, 3)
	211 iconst_0 (2, 3)
	212 istore (2, 3)
	213 #19 (2, 3)
	214 aload (3, 4)
	215 #17 (3, 4)
	216 invokevirtual (3, 4)
	217 org/apache/commons/math3/ode/ExpandableStatefulODE.getSecondaryMappers:()[Lorg/apache/commons/math3/ode/EquationsMapper; (3, 4)
	219 astore (3, 4)
	220 #20 (3, 4)
	221 aload (3, 4)
	222 #20 (3, 4)
	223 arraylength (3, 4)
	224 istore (3, 4)
	225 #21 (3, 4)
	226 iconst_0 (3, 4)
	227 istore (3, 4)
	228 #22 (3, 4)
	229 iload (3, 4)
	230 #22 (3, 4)
	231 iload (3, 4)
	232 #21 (3, 4)
	233 if_icmpge (3, 4)
	234 33 (3, 4)
	236 aload (3, 4)
	237 #20 (3, 4)
	238 iload (3, 4)
	239 #22 (3, 4)
	240 aaload (3, 4)
	241 astore (3, 4)
	242 #23 (3, 4)
	243 aload (3, 4)
	244 #23 (3, 4)
	245 aload (3, 4)
	246 #7 (3, 4)
	247 iload (3, 4)
	248 #19 (3, 4)
	249 invokevirtual (3, 4)
	250 org/apache/commons/math3/ode/sampling/NordsieckStepInterpolator.getInterpolatedSecondaryState:(I)[D (3, 4)
	252 aload (3, 4)
	253 #10 (3, 4)
	254 invokevirtual (3, 4)
	255 org/apache/commons/math3/ode/EquationsMapper.insertEquationData:([D[D)V (3, 4)
	257 iinc (3, 4)
	258 #19 (3, 4)
	259 -124 (3, 4)
	260 iinc (3, 4)
	261 #22 (3, 4)
	262 -89 (3, 4)
	263 goto (3, 4)
	264 -34 (3, 4)
	266 aload_0 (2, 3)
	267 dload (2, 3)
	268 #15 (2, 3)
	269 aload (2, 3)
	270 #10 (2, 3)
	271 aload (2, 3)
	272 #6 (2, 3)
	273 invokevirtual (2, 3)
	274 org/apache/commons/math3/ode/nonstiff/AdamsBashforthIntegrator.computeDerivatives:(D[D[D)V (2, 3)
	276 iconst_0 (3, 4)
	277 istore (3, 4)
	278 #20 (3, 4)
	279 iload (3, 4)
	280 #20 (3, 4)
	281 aload (3, 4)
	282 #11 (3, 4)
	283 arraylength (3, 4)
	284 if_icmpge (3, 4)
	285 22 (3, 4)
	287 aload (3, 4)
	288 #11 (3, 4)
	289 iload (3, 4)
	290 #20 (3, 4)
	291 dload (3, 4)
	292 #8 (3, 4)
	293 aload (3, 4)
	294 #6 (3, 4)
	295 iload (3, 4)
	296 #20 (3, 4)
	297 daload (3, 4)
	298 dmul (3, 4)
	299 dastore (3, 4)
	300 iinc (3, 4)
	301 #20 (3, 4)
	302 -89 (3, 4)
	303 goto (3, 4)
	304 -24 (3, 4)
	306 aload_0 (2, 3)
	307 aload_0 (2, 3)
	308 getfield (2, 3)
	309 org/apache/commons/math3/ode/nonstiff/AdamsBashforthIntegrator.nordsieck:Lorg/apache/commons/math3/linear/Array2DRowRealMatrix; (2, 3)
	311 invokevirtual (2, 3)
	312 org/apache/commons/math3/ode/nonstiff/AdamsBashforthIntegrator.updateHighOrderDerivativesPhase1:(Lorg/apache/commons/math3/linear/Array2DRowRealMatrix;)Lorg/apache/commons/math3/linear/Array2DRowRealMatrix; (2, 3)
	314 astore (2, 3)
	315 #12 (2, 3)
	316 aload_0 (2, 3)
	317 aload_0 (2, 3)
	318 getfield (2, 3)
	319 org/apache/commons/math3/ode/nonstiff/AdamsBashforthIntegrator.scaled:[D (2, 3)
	321 aload (2, 3)
	322 #11 (2, 3)
	323 aload (2, 3)
	324 #12 (2, 3)
	325 invokevirtual (2, 3)
	326 org/apache/commons/math3/ode/nonstiff/AdamsBashforthIntegrator.updateHighOrderDerivativesPhase2:([D[DLorg/apache/commons/math3/linear/Array2DRowRealMatrix;)V (2, 3)
	328 aload_0 (2, 3)
	329 aload (2, 3)
	330 #5 (2, 3)
	331 aload (2, 3)
	332 #10 (2, 3)
	333 aload (2, 3)
	334 #11 (2, 3)
	335 aload (2, 3)
	336 #12 (2, 3)
	337 invokespecial (2, 3)
	338 org/apache/commons/math3/ode/nonstiff/AdamsBashforthIntegrator.errorEstimation:([D[D[DLorg/apache/commons/math3/linear/RealMatrix;)D (2, 3)
	340 dstore (2, 3)
	341 #13 (2, 3)
	342 dload (3, 1)
	343 #13 (3, 1)
	344 dconst_1 (3, 1)
	345 dcmpl (3, 1)
	346 iflt (3, 1)
	347 32 (3, 1)
	349 aload_0 (3, 1)
	350 dload (3, 1)
	351 #13 (3, 1)
	352 invokevirtual (3, 1)
	353 org/apache/commons/math3/ode/nonstiff/AdamsBashforthIntegrator.computeStepGrowShrinkFactor:(D)D (3, 1)
	355 dstore (3, 1)
	356 #20 (3, 1)
	357 aload_0 (3, 4)
	358 dload (3, 4)
	359 #8 (3, 4)
	360 dload (3, 4)
	361 #20 (3, 4)
	362 dmul (3, 4)
	363 iload (3, 4)
	364 #4 (3, 4)
	365 iconst_0 (3, 4)
	366 invokevirtual (3, 4)
	367 org/apache/commons/math3/ode/nonstiff/AdamsBashforthIntegrator.filterStep:(DZZ)D (3, 4)
	369 dstore (3, 4)
	370 #8 (3, 4)
	371 aload (3, 4)
	372 #7 (3, 4)
	373 dload (3, 4)
	374 #8 (3, 4)
	375 invokevirtual (3, 4)
	376 org/apache/commons/math3/ode/sampling/NordsieckStepInterpolator.rescale:(D)V (3, 4)
	378 goto (1, 1)
	379 -215 (1, 1)
	381 aload_0 (1, 1)
	382 dload (1, 1)
	383 #8 (1, 1)
	384 putfield (1, 1)
	385 org/apache/commons/math3/ode/nonstiff/AdamsBashforthIntegrator.stepSize:D (1, 1)
	387 aload_0 (1, 1)
	388 getfield (1, 1)
	389 org/apache/commons/math3/ode/nonstiff/AdamsBashforthIntegrator.stepStart:D (1, 1)
	391 aload_0 (1, 1)
	392 getfield (1, 1)
	393 org/apache/commons/math3/ode/nonstiff/AdamsBashforthIntegrator.stepSize:D (1, 1)
	395 dadd (1, 1)
	396 dstore (1, 1)
	397 #15 (1, 1)
	398 aload (1, 1)
	399 #7 (1, 1)
	400 dload (1, 1)
	401 #15 (1, 1)
	402 aload_0 (1, 1)
	403 getfield (1, 1)
	404 org/apache/commons/math3/ode/nonstiff/AdamsBashforthIntegrator.stepSize:D (1, 1)
	406 aload (1, 1)
	407 #11 (1, 1)
	408 aload (1, 1)
	409 #12 (1, 1)
	410 invokevirtual (1, 1)
	411 org/apache/commons/math3/ode/sampling/NordsieckStepInterpolator.reinitialize:(DD[DLorg/apache/commons/math3/linear/Array2DRowRealMatrix;)V (1, 1)
	413 aload (1, 1)
	414 #7 (1, 1)
	415 dload (1, 1)
	416 #15 (1, 1)
	417 invokevirtual (1, 1)
	418 org/apache/commons/math3/ode/sampling/NordsieckStepInterpolator.storeTime:(D)V (1, 1)
	420 aload (1, 1)
	421 #10 (1, 1)
	422 iconst_0 (1, 1)
	423 aload (1, 1)
	424 #5 (1, 1)
	425 iconst_0 (1, 1)
	426 aload (1, 1)
	427 #5 (1, 1)
	428 arraylength (1, 1)
	429 invokestatic (1, 1)
	430 java/lang/System.arraycopy:(Ljava/lang/Object;ILjava/lang/Object;II)V (1, 1)
	432 aload_0 (1, 1)
	433 aload_0 (1, 1)
	434 aload (1, 1)
	435 #7 (1, 1)
	436 aload (1, 1)
	437 #5 (1, 1)
	438 aload (1, 1)
	439 #6 (1, 1)
	440 dload_2 (1, 1)
	441 invokevirtual (1, 1)
	442 org/apache/commons/math3/ode/nonstiff/AdamsBashforthIntegrator.acceptStep:(Lorg/apache/commons/math3/ode/sampling/AbstractStepInterpolator;[D[DD)D (1, 1)
	444 putfield (1, 1)
	445 org/apache/commons/math3/ode/nonstiff/AdamsBashforthIntegrator.stepStart:D (1, 1)
	447 aload_0 (1, 1)
	448 aload (1, 1)
	449 #11 (1, 1)
	450 putfield (1, 1)
	451 org/apache/commons/math3/ode/nonstiff/AdamsBashforthIntegrator.scaled:[D (1, 1)
	453 aload_0 (1, 1)
	454 aload (1, 1)
	455 #12 (1, 1)
	456 putfield (1, 1)
	457 org/apache/commons/math3/ode/nonstiff/AdamsBashforthIntegrator.nordsieck:Lorg/apache/commons/math3/linear/Array2DRowRealMatrix; (1, 1)
	459 aload (1, 1)
	460 #7 (1, 1)
	461 dload (1, 1)
	462 #15 (1, 1)
	463 aload_0 (1, 1)
	464 getfield (1, 1)
	465 org/apache/commons/math3/ode/nonstiff/AdamsBashforthIntegrator.stepSize:D (1, 1)
	467 aload_0 (1, 1)
	468 getfield (1, 1)
	469 org/apache/commons/math3/ode/nonstiff/AdamsBashforthIntegrator.scaled:[D (1, 1)
	471 aload_0 (1, 1)
	472 getfield (1, 1)
	473 org/apache/commons/math3/ode/nonstiff/AdamsBashforthIntegrator.nordsieck:Lorg/apache/commons/math3/linear/Array2DRowRealMatrix; (1, 1)
	475 invokevirtual (1, 1)
	476 org/apache/commons/math3/ode/sampling/NordsieckStepInterpolator.reinitialize:(DD[DLorg/apache/commons/math3/linear/Array2DRowRealMatrix;)V (1, 1)
	478 aload_0 (2, 1)
	479 getfield (2, 1)
	480 org/apache/commons/math3/ode/nonstiff/AdamsBashforthIntegrator.isLastStep:Z (2, 1)
	482 ifne (2, 1)
	483 186 (2, 1)
	485 aload (2, 1)
	486 #7 (2, 1)
	487 aload_0 (2, 1)
	488 getfield (2, 1)
	489 org/apache/commons/math3/ode/nonstiff/AdamsBashforthIntegrator.stepStart:D (2, 1)
	491 invokevirtual (2, 1)
	492 org/apache/commons/math3/ode/sampling/NordsieckStepInterpolator.storeTime:(D)V (2, 1)
	494 aload_0 (3, 1)
	495 getfield (3, 1)
	496 org/apache/commons/math3/ode/nonstiff/AdamsBashforthIntegrator.resetOccurred:Z (3, 1)
	498 ifeq (3, 1)
	499 35 (3, 1)
	501 aload_0 (3, 1)
	502 aload_0 (3, 1)
	503 getfield (3, 1)
	504 org/apache/commons/math3/ode/nonstiff/AdamsBashforthIntegrator.stepStart:D (3, 1)
	506 aload (3, 1)
	507 #5 (3, 1)
	508 dload_2 (3, 1)
	509 invokevirtual (3, 1)
	510 org/apache/commons/math3/ode/nonstiff/AdamsBashforthIntegrator.start:(D[DD)V (3, 1)
	512 aload (3, 1)
	513 #7 (3, 1)
	514 aload_0 (3, 1)
	515 getfield (3, 1)
	516 org/apache/commons/math3/ode/nonstiff/AdamsBashforthIntegrator.stepStart:D (3, 1)
	518 aload_0 (3, 1)
	519 getfield (3, 1)
	520 org/apache/commons/math3/ode/nonstiff/AdamsBashforthIntegrator.stepSize:D (3, 1)
	522 aload_0 (3, 1)
	523 getfield (3, 1)
	524 org/apache/commons/math3/ode/nonstiff/AdamsBashforthIntegrator.scaled:[D (3, 1)
	526 aload_0 (3, 1)
	527 getfield (3, 1)
	528 org/apache/commons/math3/ode/nonstiff/AdamsBashforthIntegrator.nordsieck:Lorg/apache/commons/math3/linear/Array2DRowRealMatrix; (3, 1)
	530 invokevirtual (3, 1)
	531 org/apache/commons/math3/ode/sampling/NordsieckStepInterpolator.reinitialize:(DD[DLorg/apache/commons/math3/linear/Array2DRowRealMatrix;)V (3, 1)
	533 aload_0 (2, 4)
	534 dload (2, 4)
	535 #13 (2, 4)
	536 invokevirtual (2, 4)
	537 org/apache/commons/math3/ode/nonstiff/AdamsBashforthIntegrator.computeStepGrowShrinkFactor:(D)D (2, 4)
	539 dstore (2, 4)
	540 #17 (2, 4)
	541 aload_0 (2, 4)
	542 getfield (2, 4)
	543 org/apache/commons/math3/ode/nonstiff/AdamsBashforthIntegrator.stepSize:D (2, 4)
	545 dload (2, 4)
	546 #17 (2, 4)
	547 dmul (2, 4)
	548 dstore (2, 4)
	549 #19 (2, 4)
	550 aload_0 (2, 4)
	551 getfield (2, 4)
	552 org/apache/commons/math3/ode/nonstiff/AdamsBashforthIntegrator.stepStart:D (2, 4)
	554 dload (2, 4)
	555 #19 (2, 4)
	556 dadd (2, 4)
	557 dstore (2, 4)
	558 #21 (2, 4)
	559 iload (2, 4)
	560 #4 (2, 4)
	561 ifeq (2, 4)
	562 18 (2, 4)
	564 dload (2, 4)
	565 #21 (2, 4)
	566 dload_2 (2, 4)
	567 dcmpl (2, 4)
	568 iflt (2, 4)
	569 7 (2, 4)
	571 iconst_1 (2, 4)
	572 goto (2, 4)
	573 19 (2, 4)
	575 iconst_0 (2, 4)
	576 goto (2, 4)
	577 15 (2, 4)
	579 dload (2, 4)
	580 #21 (2, 4)
	581 dload_2 (2, 4)
	582 dcmpg (2, 4)
	583 ifgt (2, 4)
	584 7 (2, 4)
	586 iconst_1 (2, 4)
	587 goto (2, 4)
	588 4 (2, 4)
	590 iconst_0 (2, 4)
	591 istore (2, 4)
	592 #23 (2, 4)
	593 aload_0 (2, 4)
	594 dload (2, 4)
	595 #19 (2, 4)
	596 iload (2, 4)
	597 #4 (2, 4)
	598 iload (2, 4)
	599 #23 (2, 4)
	600 invokevirtual (2, 4)
	601 org/apache/commons/math3/ode/nonstiff/AdamsBashforthIntegrator.filterStep:(DZZ)D (2, 4)
	603 dstore (2, 4)
	604 #8 (2, 4)
	605 aload_0 (2, 4)
	606 getfield (2, 4)
	607 org/apache/commons/math3/ode/nonstiff/AdamsBashforthIntegrator.stepStart:D (2, 4)
	609 dload (2, 4)
	610 #8 (2, 4)
	611 dadd (2, 4)
	612 dstore (2, 4)
	613 #24 (2, 4)
	614 iload (2, 4)
	615 #4 (2, 4)
	616 ifeq (2, 4)
	617 18 (2, 4)
	619 dload (2, 4)
	620 #24 (2, 4)
	621 dload_2 (2, 4)
	622 dcmpl (2, 4)
	623 iflt (2, 4)
	624 7 (2, 4)
	626 iconst_1 (2, 4)
	627 goto (2, 4)
	628 19 (2, 4)
	630 iconst_0 (2, 4)
	631 goto (2, 4)
	632 15 (2, 4)
	634 dload (2, 4)
	635 #24 (2, 4)
	636 dload_2 (2, 4)
	637 dcmpg (2, 4)
	638 ifgt (2, 4)
	639 7 (2, 4)
	641 iconst_1 (2, 4)
	642 goto (2, 4)
	643 4 (2, 4)
	645 iconst_0 (2, 4)
	646 istore (2, 4)
	647 #26 (2, 4)
	648 iload (3, 1)
	649 #26 (3, 1)
	650 ifeq (3, 1)
	651 11 (3, 1)
	653 dload_2 (3, 1)
	654 aload_0 (3, 1)
	655 getfield (3, 1)
	656 org/apache/commons/math3/ode/nonstiff/AdamsBashforthIntegrator.stepStart:D (3, 1)
	658 dsub (3, 1)
	659 dstore (3, 1)
	660 #8 (3, 1)
	661 aload (2, 4)
	662 #7 (2, 4)
	663 dload (2, 4)
	664 #8 (2, 4)
	665 invokevirtual (2, 4)
	666 org/apache/commons/math3/ode/sampling/NordsieckStepInterpolator.rescale:(D)V (2, 4)
	668 aload_0 (0, 3)
	669 getfield (0, 3)
	670 org/apache/commons/math3/ode/nonstiff/AdamsBashforthIntegrator.isLastStep:Z (0, 3)
	672 ifeq (0, 3)
	673 -536 (0, 3)
	675 aload_1 (0, 3)
	676 aload_0 (0, 3)
	677 getfield (0, 3)
	678 org/apache/commons/math3/ode/nonstiff/AdamsBashforthIntegrator.stepStart:D (0, 3)
	680 invokevirtual (0, 3)
	681 org/apache/commons/math3/ode/ExpandableStatefulODE.setTime:(D)V (0, 3)
	683 aload_1 (0, 3)
	684 aload (0, 3)
	685 #5 (0, 3)
	686 invokevirtual (0, 3)
	687 org/apache/commons/math3/ode/ExpandableStatefulODE.setCompleteState:([D)V (0, 3)
	689 aload_0 (0, 3)
	690 invokevirtual (0, 3)
	691 org/apache/commons/math3/ode/nonstiff/AdamsBashforthIntegrator.resetInternalState:()V (0, 3)
	693 return (0, 3)

