Method: <init>
	0 aload_0 (0, 0)
	1 ldc (0, 0)
	2 Adams-Moulton (0, 0)
	3 iload_1 (0, 0)
	4 iload_1 (0, 0)
	5 iconst_1 (0, 0)
	6 iadd (0, 0)
	7 dload_2 (0, 0)
	8 dload (0, 0)
	9 #4 (0, 0)
	10 aload (0, 0)
	11 #6 (0, 0)
	12 aload (0, 0)
	13 #7 (0, 0)
	14 invokespecial (0, 0)
	15 org/apache/commons/math3/ode/nonstiff/AdamsIntegrator.<init>:(Ljava/lang/String;IIDD[D[D)V (0, 0)
	17 return (0, 0)

Method: integrate
	0 aload_0 (0, 0)
	1 aload_1 (0, 0)
	2 dload_2 (0, 0)
	3 invokevirtual (0, 0)
	4 org/apache/commons/math3/ode/nonstiff/AdamsMoultonIntegrator.sanityChecks:(Lorg/apache/commons/math3/ode/ExpandableStatefulODE;D)V (0, 0)
	6 aload_0 (0, 0)
	7 aload_1 (0, 0)
	8 invokevirtual (0, 0)
	9 org/apache/commons/math3/ode/nonstiff/AdamsMoultonIntegrator.setEquations:(Lorg/apache/commons/math3/ode/ExpandableStatefulODE;)V (0, 0)
	11 dload_2 (1, 4)
	12 aload_1 (1, 4)
	13 invokevirtual (1, 4)
	14 org/apache/commons/math3/ode/ExpandableStatefulODE.getTime:()D (1, 4)
	16 dcmpl (1, 4)
	17 ifle (1, 4)
	18 7 (1, 4)
	20 iconst_1 (1, 4)
	21 goto (1, 4)
	22 4 (1, 4)
	24 iconst_0 (1, 4)
	25 istore (1, 4)
	26 #4 (1, 4)
	27 aload_1 (1, 4)
	28 invokevirtual (1, 4)
	29 org/apache/commons/math3/ode/ExpandableStatefulODE.getCompleteState:()[D (1, 4)
	31 astore (1, 4)
	32 #5 (1, 4)
	33 aload (1, 4)
	34 #5 (1, 4)
	35 invokevirtual (1, 4)
	36 [D.clone:()Ljava/lang/Object; (1, 4)
	38 checkcast (1, 4)
	39 [D (1, 4)
	41 astore (1, 4)
	42 #6 (1, 4)
	43 aload (1, 4)
	44 #6 (1, 4)
	45 arraylength (1, 4)
	46 newarray (1, 4)
	47 7 (1, 4)
	48 astore (1, 4)
	49 #7 (1, 4)
	50 aload (1, 4)
	51 #6 (1, 4)
	52 arraylength (1, 4)
	53 newarray (1, 4)
	54 7 (1, 4)
	55 astore (1, 4)
	56 #8 (1, 4)
	57 aload (1, 4)
	58 #6 (1, 4)
	59 arraylength (1, 4)
	60 newarray (1, 4)
	61 7 (1, 4)
	62 astore (1, 4)
	63 #9 (1, 4)
	64 aconst_null (1, 4)
	65 astore (1, 4)
	66 #10 (1, 4)
	67 new (1, 4)
	68 org/apache/commons/math3/ode/sampling/NordsieckStepInterpolator (1, 4)
	70 dup (1, 4)
	71 invokespecial (1, 4)
	72 org/apache/commons/math3/ode/sampling/NordsieckStepInterpolator.<init>:()V (1, 4)
	74 astore (1, 4)
	75 #11 (1, 4)
	76 aload (2, 4)
	77 #11 (2, 4)
	78 aload (2, 4)
	79 #6 (2, 4)
	80 iload (2, 4)
	81 #4 (2, 4)
	82 aload_1 (2, 4)
	83 invokevirtual (2, 4)
	84 org/apache/commons/math3/ode/ExpandableStatefulODE.getPrimaryMapper:()Lorg/apache/commons/math3/ode/EquationsMapper; (2, 4)
	86 aload_1 (2, 4)
	87 invokevirtual (2, 4)
	88 org/apache/commons/math3/ode/ExpandableStatefulODE.getSecondaryMappers:()[Lorg/apache/commons/math3/ode/EquationsMapper; (2, 4)
	90 invokevirtual (2, 4)
	91 org/apache/commons/math3/ode/sampling/NordsieckStepInterpolator.reinitialize:([DZLorg/apache/commons/math3/ode/EquationsMapper;[Lorg/apache/commons/math3/ode/EquationsMapper;)V (2, 4)
	93 aload_0 (2, 4)
	94 aload_1 (2, 4)
	95 invokevirtual (2, 4)
	96 org/apache/commons/math3/ode/ExpandableStatefulODE.getTime:()D (2, 4)
	98 aload (2, 4)
	99 #5 (2, 4)
	100 dload_2 (2, 4)
	101 invokevirtual (2, 4)
	102 org/apache/commons/math3/ode/nonstiff/AdamsMoultonIntegrator.initIntegration:(D[DD)V (2, 4)
	104 aload_0 (2, 4)
	105 aload_1 (2, 4)
	106 invokevirtual (2, 4)
	107 org/apache/commons/math3/ode/ExpandableStatefulODE.getTime:()D (2, 4)
	109 aload (2, 4)
	110 #6 (2, 4)
	111 dload_2 (2, 4)
	112 invokevirtual (2, 4)
	113 org/apache/commons/math3/ode/nonstiff/AdamsMoultonIntegrator.start:(D[DD)V (2, 4)
	115 aload (2, 4)
	116 #11 (2, 4)
	117 aload_0 (2, 4)
	118 getfield (2, 4)
	119 org/apache/commons/math3/ode/nonstiff/AdamsMoultonIntegrator.stepStart:D (2, 4)
	121 aload_0 (2, 4)
	122 getfield (2, 4)
	123 org/apache/commons/math3/ode/nonstiff/AdamsMoultonIntegrator.stepSize:D (2, 4)
	125 aload_0 (2, 4)
	126 getfield (2, 4)
	127 org/apache/commons/math3/ode/nonstiff/AdamsMoultonIntegrator.scaled:[D (2, 4)
	129 aload_0 (2, 4)
	130 getfield (2, 4)
	131 org/apache/commons/math3/ode/nonstiff/AdamsMoultonIntegrator.nordsieck:Lorg/apache/commons/math3/linear/Array2DRowRealMatrix; (2, 4)
	133 invokevirtual (2, 4)
	134 org/apache/commons/math3/ode/sampling/NordsieckStepInterpolator.reinitialize:(DD[DLorg/apache/commons/math3/linear/Array2DRowRealMatrix;)V (2, 4)
	136 aload (2, 4)
	137 #11 (2, 4)
	138 aload_0 (2, 4)
	139 getfield (2, 4)
	140 org/apache/commons/math3/ode/nonstiff/AdamsMoultonIntegrator.stepStart:D (2, 4)
	142 invokevirtual (2, 4)
	143 org/apache/commons/math3/ode/sampling/NordsieckStepInterpolator.storeTime:(D)V (2, 4)
	145 aload_0 (2, 4)
	146 getfield (2, 4)
	147 org/apache/commons/math3/ode/nonstiff/AdamsMoultonIntegrator.stepSize:D (2, 4)
	149 dstore (2, 4)
	150 #12 (2, 4)
	151 aload (2, 4)
	152 #11 (2, 4)
	153 dload (2, 4)
	154 #12 (2, 4)
	155 invokevirtual (2, 4)
	156 org/apache/commons/math3/ode/sampling/NordsieckStepInterpolator.rescale:(D)V (2, 4)
	158 aload_0 (2, 4)
	159 iconst_0 (2, 4)
	160 putfield (2, 4)
	161 org/apache/commons/math3/ode/nonstiff/AdamsMoultonIntegrator.isLastStep:Z (2, 4)
	163 ldc2_w (2, 4)
	164 10.0 (2, 4)
	166 dstore (2, 4)
	167 #14 (2, 4)
	168 dload (3, 3)
	169 #14 (3, 3)
	170 dconst_1 (3, 3)
	171 dcmpl (3, 3)
	172 iflt (3, 3)
	173 233 (3, 3)
	175 aload_0 (3, 3)
	176 dload (3, 3)
	177 #12 (3, 3)
	178 putfield (3, 3)
	179 org/apache/commons/math3/ode/nonstiff/AdamsMoultonIntegrator.stepSize:D (3, 3)
	181 aload_0 (3, 3)
	182 getfield (3, 3)
	183 org/apache/commons/math3/ode/nonstiff/AdamsMoultonIntegrator.stepStart:D (3, 3)
	185 aload_0 (3, 3)
	186 getfield (3, 3)
	187 org/apache/commons/math3/ode/nonstiff/AdamsMoultonIntegrator.stepSize:D (3, 3)
	189 dadd (3, 3)
	190 dstore (3, 3)
	191 #16 (3, 3)
	192 aload (3, 3)
	193 #11 (3, 3)
	194 dload (3, 3)
	195 #16 (3, 3)
	196 invokevirtual (3, 3)
	197 org/apache/commons/math3/ode/sampling/NordsieckStepInterpolator.setInterpolatedTime:(D)V (3, 3)
	199 aload_0 (3, 3)
	200 invokevirtual (3, 3)
	201 org/apache/commons/math3/ode/nonstiff/AdamsMoultonIntegrator.getExpandable:()Lorg/apache/commons/math3/ode/ExpandableStatefulODE; (3, 3)
	203 astore (3, 3)
	204 #18 (3, 3)
	205 aload (3, 3)
	206 #18 (3, 3)
	207 invokevirtual (3, 3)
	208 org/apache/commons/math3/ode/ExpandableStatefulODE.getPrimaryMapper:()Lorg/apache/commons/math3/ode/EquationsMapper; (3, 3)
	210 astore (3, 3)
	211 #19 (3, 3)
	212 aload (3, 3)
	213 #19 (3, 3)
	214 aload (3, 3)
	215 #11 (3, 3)
	216 invokevirtual (3, 3)
	217 org/apache/commons/math3/ode/sampling/NordsieckStepInterpolator.getInterpolatedState:()[D (3, 3)
	219 aload (3, 3)
	220 #8 (3, 3)
	221 invokevirtual (3, 3)
	222 org/apache/commons/math3/ode/EquationsMapper.insertEquationData:([D[D)V (3, 3)
	224 iconst_0 (3, 3)
	225 istore (3, 3)
	226 #20 (3, 3)
	227 aload (4, 4)
	228 #18 (4, 4)
	229 invokevirtual (4, 4)
	230 org/apache/commons/math3/ode/ExpandableStatefulODE.getSecondaryMappers:()[Lorg/apache/commons/math3/ode/EquationsMapper; (4, 4)
	232 astore (4, 4)
	233 #21 (4, 4)
	234 aload (4, 4)
	235 #21 (4, 4)
	236 arraylength (4, 4)
	237 istore (4, 4)
	238 #22 (4, 4)
	239 iconst_0 (4, 4)
	240 istore (4, 4)
	241 #23 (4, 4)
	242 iload (4, 4)
	243 #23 (4, 4)
	244 iload (4, 4)
	245 #22 (4, 4)
	246 if_icmpge (4, 4)
	247 33 (4, 4)
	249 aload (4, 4)
	250 #21 (4, 4)
	251 iload (4, 4)
	252 #23 (4, 4)
	253 aaload (4, 4)
	254 astore (4, 4)
	255 #24 (4, 4)
	256 aload (4, 4)
	257 #24 (4, 4)
	258 aload (4, 4)
	259 #11 (4, 4)
	260 iload (4, 4)
	261 #20 (4, 4)
	262 invokevirtual (4, 4)
	263 org/apache/commons/math3/ode/sampling/NordsieckStepInterpolator.getInterpolatedSecondaryState:(I)[D (4, 4)
	265 aload (4, 4)
	266 #8 (4, 4)
	267 invokevirtual (4, 4)
	268 org/apache/commons/math3/ode/EquationsMapper.insertEquationData:([D[D)V (4, 4)
	270 iinc (4, 4)
	271 #20 (4, 4)
	272 -124 (4, 4)
	273 iinc (4, 4)
	274 #23 (4, 4)
	275 -89 (4, 4)
	276 goto (4, 4)
	277 -34 (4, 4)
	279 aload_0 (3, 3)
	280 dload (3, 3)
	281 #16 (3, 3)
	282 aload (3, 3)
	283 #8 (3, 3)
	284 aload (3, 3)
	285 #7 (3, 3)
	286 invokevirtual (3, 3)
	287 org/apache/commons/math3/ode/nonstiff/AdamsMoultonIntegrator.computeDerivatives:(D[D[D)V (3, 3)
	289 iconst_0 (4, 4)
	290 istore (4, 4)
	291 #21 (4, 4)
	292 iload (4, 4)
	293 #21 (4, 4)
	294 aload (4, 4)
	295 #5 (4, 4)
	296 arraylength (4, 4)
	297 if_icmpge (4, 4)
	298 24 (4, 4)
	300 aload (4, 4)
	301 #9 (4, 4)
	302 iload (4, 4)
	303 #21 (4, 4)
	304 aload_0 (4, 4)
	305 getfield (4, 4)
	306 org/apache/commons/math3/ode/nonstiff/AdamsMoultonIntegrator.stepSize:D (4, 4)
	308 aload (4, 4)
	309 #7 (4, 4)
	310 iload (4, 4)
	311 #21 (4, 4)
	312 daload (4, 4)
	313 dmul (4, 4)
	314 dastore (4, 4)
	315 iinc (4, 4)
	316 #21 (4, 4)
	317 -89 (4, 4)
	318 goto (4, 4)
	319 -26 (4, 4)
	321 aload_0 (3, 3)
	322 aload_0 (3, 3)
	323 getfield (3, 3)
	324 org/apache/commons/math3/ode/nonstiff/AdamsMoultonIntegrator.nordsieck:Lorg/apache/commons/math3/linear/Array2DRowRealMatrix; (3, 3)
	326 invokevirtual (3, 3)
	327 org/apache/commons/math3/ode/nonstiff/AdamsMoultonIntegrator.updateHighOrderDerivativesPhase1:(Lorg/apache/commons/math3/linear/Array2DRowRealMatrix;)Lorg/apache/commons/math3/linear/Array2DRowRealMatrix; (3, 3)
	329 astore (3, 3)
	330 #10 (3, 3)
	331 aload_0 (3, 3)
	332 aload_0 (3, 3)
	333 getfield (3, 3)
	334 org/apache/commons/math3/ode/nonstiff/AdamsMoultonIntegrator.scaled:[D (3, 3)
	336 aload (3, 3)
	337 #9 (3, 3)
	338 aload (3, 3)
	339 #10 (3, 3)
	340 invokevirtual (3, 3)
	341 org/apache/commons/math3/ode/nonstiff/AdamsMoultonIntegrator.updateHighOrderDerivativesPhase2:([D[DLorg/apache/commons/math3/linear/Array2DRowRealMatrix;)V (3, 3)
	343 aload (3, 3)
	344 #10 (3, 3)
	345 new (3, 3)
	346 org/apache/commons/math3/ode/nonstiff/AdamsMoultonIntegrator$Corrector (3, 3)
	348 dup (3, 3)
	349 aload_0 (3, 3)
	350 aload (3, 3)
	351 #6 (3, 3)
	352 aload (3, 3)
	353 #9 (3, 3)
	354 aload (3, 3)
	355 #8 (3, 3)
	356 invokespecial (3, 3)
	357 org/apache/commons/math3/ode/nonstiff/AdamsMoultonIntegrator$Corrector.<init>:(Lorg/apache/commons/math3/ode/nonstiff/AdamsMoultonIntegrator;[D[D[D)V (3, 3)
	359 invokevirtual (3, 3)
	360 org/apache/commons/math3/linear/Array2DRowRealMatrix.walkInOptimizedOrder:(Lorg/apache/commons/math3/linear/RealMatrixPreservingVisitor;)D (3, 3)
	362 dstore (3, 3)
	363 #14 (3, 3)
	364 dload (4, 1)
	365 #14 (4, 1)
	366 dconst_1 (4, 1)
	367 dcmpl (4, 1)
	368 iflt (4, 1)
	369 34 (4, 1)
	371 aload_0 (4, 1)
	372 dload (4, 1)
	373 #14 (4, 1)
	374 invokevirtual (4, 1)
	375 org/apache/commons/math3/ode/nonstiff/AdamsMoultonIntegrator.computeStepGrowShrinkFactor:(D)D (4, 1)
	377 dstore (4, 1)
	378 #21 (4, 1)
	379 aload_0 (5, 4)
	380 aload_0 (5, 4)
	381 getfield (5, 4)
	382 org/apache/commons/math3/ode/nonstiff/AdamsMoultonIntegrator.stepSize:D (5, 4)
	384 dload (5, 4)
	385 #21 (5, 4)
	386 dmul (5, 4)
	387 iload (5, 4)
	388 #4 (5, 4)
	389 iconst_0 (5, 4)
	390 invokevirtual (5, 4)
	391 org/apache/commons/math3/ode/nonstiff/AdamsMoultonIntegrator.filterStep:(DZZ)D (5, 4)
	393 dstore (5, 4)
	394 #12 (5, 4)
	395 aload (5, 4)
	396 #11 (5, 4)
	397 dload (5, 4)
	398 #12 (5, 4)
	399 invokevirtual (5, 4)
	400 org/apache/commons/math3/ode/sampling/NordsieckStepInterpolator.rescale:(D)V (5, 4)
	402 goto (2, 4)
	403 -234 (2, 4)
	405 aload_0 (2, 4)
	406 getfield (2, 4)
	407 org/apache/commons/math3/ode/nonstiff/AdamsMoultonIntegrator.stepStart:D (2, 4)
	409 aload_0 (2, 4)
	410 getfield (2, 4)
	411 org/apache/commons/math3/ode/nonstiff/AdamsMoultonIntegrator.stepSize:D (2, 4)
	413 dadd (2, 4)
	414 dstore (2, 4)
	415 #16 (2, 4)
	416 aload_0 (2, 4)
	417 dload (2, 4)
	418 #16 (2, 4)
	419 aload (2, 4)
	420 #8 (2, 4)
	421 aload (2, 4)
	422 #7 (2, 4)
	423 invokevirtual (2, 4)
	424 org/apache/commons/math3/ode/nonstiff/AdamsMoultonIntegrator.computeDerivatives:(D[D[D)V (2, 4)
	426 aload (2, 4)
	427 #5 (2, 4)
	428 arraylength (2, 4)
	429 newarray (2, 4)
	430 7 (2, 4)
	431 astore (2, 4)
	432 #18 (2, 4)
	433 iconst_0 (3, 4)
	434 istore (3, 4)
	435 #19 (3, 4)
	436 iload (3, 4)
	437 #19 (3, 4)
	438 aload (3, 4)
	439 #5 (3, 4)
	440 arraylength (3, 4)
	441 if_icmpge (3, 4)
	442 24 (3, 4)
	444 aload (3, 4)
	445 #18 (3, 4)
	446 iload (3, 4)
	447 #19 (3, 4)
	448 aload_0 (3, 4)
	449 getfield (3, 4)
	450 org/apache/commons/math3/ode/nonstiff/AdamsMoultonIntegrator.stepSize:D (3, 4)
	452 aload (3, 4)
	453 #7 (3, 4)
	454 iload (3, 4)
	455 #19 (3, 4)
	456 daload (3, 4)
	457 dmul (3, 4)
	458 dastore (3, 4)
	459 iinc (3, 4)
	460 #19 (3, 4)
	461 -89 (3, 4)
	462 goto (3, 4)
	463 -26 (3, 4)
	465 aload_0 (2, 4)
	466 aload (2, 4)
	467 #9 (2, 4)
	468 aload (2, 4)
	469 #18 (2, 4)
	470 aload (2, 4)
	471 #10 (2, 4)
	472 invokevirtual (2, 4)
	473 org/apache/commons/math3/ode/nonstiff/AdamsMoultonIntegrator.updateHighOrderDerivativesPhase2:([D[DLorg/apache/commons/math3/linear/Array2DRowRealMatrix;)V (2, 4)
	475 aload (2, 4)
	476 #8 (2, 4)
	477 iconst_0 (2, 4)
	478 aload (2, 4)
	479 #6 (2, 4)
	480 iconst_0 (2, 4)
	481 aload (2, 4)
	482 #6 (2, 4)
	483 arraylength (2, 4)
	484 invokestatic (2, 4)
	485 java/lang/System.arraycopy:(Ljava/lang/Object;ILjava/lang/Object;II)V (2, 4)
	487 aload (2, 4)
	488 #11 (2, 4)
	489 dload (2, 4)
	490 #16 (2, 4)
	491 aload_0 (2, 4)
	492 getfield (2, 4)
	493 org/apache/commons/math3/ode/nonstiff/AdamsMoultonIntegrator.stepSize:D (2, 4)
	495 aload (2, 4)
	496 #18 (2, 4)
	497 aload (2, 4)
	498 #10 (2, 4)
	499 invokevirtual (2, 4)
	500 org/apache/commons/math3/ode/sampling/NordsieckStepInterpolator.reinitialize:(DD[DLorg/apache/commons/math3/linear/Array2DRowRealMatrix;)V (2, 4)
	502 aload (2, 4)
	503 #11 (2, 4)
	504 aload_0 (2, 4)
	505 getfield (2, 4)
	506 org/apache/commons/math3/ode/nonstiff/AdamsMoultonIntegrator.stepStart:D (2, 4)
	508 invokevirtual (2, 4)
	509 org/apache/commons/math3/ode/sampling/NordsieckStepInterpolator.storeTime:(D)V (2, 4)
	511 aload (3, 1)
	512 #11 (3, 1)
	513 invokevirtual (3, 1)
	514 org/apache/commons/math3/ode/sampling/NordsieckStepInterpolator.shift:()V (3, 1)
	516 aload (3, 1)
	517 #11 (3, 1)
	518 dload (3, 1)
	519 #16 (3, 1)
	520 invokevirtual (3, 1)
	521 org/apache/commons/math3/ode/sampling/NordsieckStepInterpolator.storeTime:(D)V (3, 1)
	523 aload_0 (3, 1)
	524 aload_0 (3, 1)
	525 aload (3, 1)
	526 #11 (3, 1)
	527 aload (3, 1)
	528 #6 (3, 1)
	529 aload (3, 1)
	530 #7 (3, 1)
	531 dload_2 (3, 1)
	532 invokevirtual (3, 1)
	533 org/apache/commons/math3/ode/nonstiff/AdamsMoultonIntegrator.acceptStep:(Lorg/apache/commons/math3/ode/sampling/AbstractStepInterpolator;[D[DD)D (3, 1)
	535 putfield (3, 1)
	536 org/apache/commons/math3/ode/nonstiff/AdamsMoultonIntegrator.stepStart:D (3, 1)
	538 aload_0 (3, 1)
	539 aload (3, 1)
	540 #18 (3, 1)
	541 putfield (3, 1)
	542 org/apache/commons/math3/ode/nonstiff/AdamsMoultonIntegrator.scaled:[D (3, 1)
	544 aload_0 (3, 1)
	545 aload (3, 1)
	546 #10 (3, 1)
	547 putfield (3, 1)
	548 org/apache/commons/math3/ode/nonstiff/AdamsMoultonIntegrator.nordsieck:Lorg/apache/commons/math3/linear/Array2DRowRealMatrix; (3, 1)
	550 aload_0 (4, 1)
	551 getfield (4, 1)
	552 org/apache/commons/math3/ode/nonstiff/AdamsMoultonIntegrator.isLastStep:Z (4, 1)
	554 ifne (4, 1)
	555 186 (4, 1)
	557 aload (4, 1)
	558 #11 (4, 1)
	559 aload_0 (4, 1)
	560 getfield (4, 1)
	561 org/apache/commons/math3/ode/nonstiff/AdamsMoultonIntegrator.stepStart:D (4, 1)
	563 invokevirtual (4, 1)
	564 org/apache/commons/math3/ode/sampling/NordsieckStepInterpolator.storeTime:(D)V (4, 1)
	566 aload_0 (5, 1)
	567 getfield (5, 1)
	568 org/apache/commons/math3/ode/nonstiff/AdamsMoultonIntegrator.resetOccurred:Z (5, 1)
	570 ifeq (5, 1)
	571 35 (5, 1)
	573 aload_0 (5, 1)
	574 aload_0 (5, 1)
	575 getfield (5, 1)
	576 org/apache/commons/math3/ode/nonstiff/AdamsMoultonIntegrator.stepStart:D (5, 1)
	578 aload (5, 1)
	579 #6 (5, 1)
	580 dload_2 (5, 1)
	581 invokevirtual (5, 1)
	582 org/apache/commons/math3/ode/nonstiff/AdamsMoultonIntegrator.start:(D[DD)V (5, 1)
	584 aload (5, 1)
	585 #11 (5, 1)
	586 aload_0 (5, 1)
	587 getfield (5, 1)
	588 org/apache/commons/math3/ode/nonstiff/AdamsMoultonIntegrator.stepStart:D (5, 1)
	590 aload_0 (5, 1)
	591 getfield (5, 1)
	592 org/apache/commons/math3/ode/nonstiff/AdamsMoultonIntegrator.stepSize:D (5, 1)
	594 aload_0 (5, 1)
	595 getfield (5, 1)
	596 org/apache/commons/math3/ode/nonstiff/AdamsMoultonIntegrator.scaled:[D (5, 1)
	598 aload_0 (5, 1)
	599 getfield (5, 1)
	600 org/apache/commons/math3/ode/nonstiff/AdamsMoultonIntegrator.nordsieck:Lorg/apache/commons/math3/linear/Array2DRowRealMatrix; (5, 1)
	602 invokevirtual (5, 1)
	603 org/apache/commons/math3/ode/sampling/NordsieckStepInterpolator.reinitialize:(DD[DLorg/apache/commons/math3/linear/Array2DRowRealMatrix;)V (5, 1)
	605 aload_0 (5, 4)
	606 dload (5, 4)
	607 #14 (5, 4)
	608 invokevirtual (5, 4)
	609 org/apache/commons/math3/ode/nonstiff/AdamsMoultonIntegrator.computeStepGrowShrinkFactor:(D)D (5, 4)
	611 dstore (5, 4)
	612 #19 (5, 4)
	613 aload_0 (5, 4)
	614 getfield (5, 4)
	615 org/apache/commons/math3/ode/nonstiff/AdamsMoultonIntegrator.stepSize:D (5, 4)
	617 dload (5, 4)
	618 #19 (5, 4)
	619 dmul (5, 4)
	620 dstore (5, 4)
	621 #21 (5, 4)
	622 aload_0 (5, 4)
	623 getfield (5, 4)
	624 org/apache/commons/math3/ode/nonstiff/AdamsMoultonIntegrator.stepStart:D (5, 4)
	626 dload (5, 4)
	627 #21 (5, 4)
	628 dadd (5, 4)
	629 dstore (5, 4)
	630 #23 (5, 4)
	631 iload (6, 4)
	632 #4 (6, 4)
	633 ifeq (6, 4)
	634 18 (6, 4)
	636 dload (6, 4)
	637 #23 (6, 4)
	638 dload_2 (6, 4)
	639 dcmpl (6, 4)
	640 iflt (6, 4)
	641 7 (6, 4)
	643 iconst_1 (6, 4)
	644 goto (6, 4)
	645 19 (6, 4)
	647 iconst_0 (6, 4)
	648 goto (6, 4)
	649 15 (6, 4)
	651 dload (6, 4)
	652 #23 (6, 4)
	653 dload_2 (6, 4)
	654 dcmpg (6, 4)
	655 ifgt (6, 4)
	656 7 (6, 4)
	658 iconst_1 (6, 4)
	659 goto (6, 4)
	660 4 (6, 4)
	662 iconst_0 (6, 4)
	663 istore (6, 4)
	664 #25 (6, 4)
	665 aload_0 (7, 4)
	666 dload (7, 4)
	667 #21 (7, 4)
	668 iload (7, 4)
	669 #4 (7, 4)
	670 iload (7, 4)
	671 #25 (7, 4)
	672 invokevirtual (7, 4)
	673 org/apache/commons/math3/ode/nonstiff/AdamsMoultonIntegrator.filterStep:(DZZ)D (7, 4)
	675 dstore (7, 4)
	676 #12 (7, 4)
	677 aload_0 (7, 4)
	678 getfield (7, 4)
	679 org/apache/commons/math3/ode/nonstiff/AdamsMoultonIntegrator.stepStart:D (7, 4)
	681 dload (7, 4)
	682 #12 (7, 4)
	683 dadd (7, 4)
	684 dstore (7, 4)
	685 #26 (7, 4)
	686 iload (8, 4)
	687 #4 (8, 4)
	688 ifeq (8, 4)
	689 18 (8, 4)
	691 dload (8, 4)
	692 #26 (8, 4)
	693 dload_2 (8, 4)
	694 dcmpl (8, 4)
	695 iflt (8, 4)
	696 7 (8, 4)
	698 iconst_1 (8, 4)
	699 goto (8, 4)
	700 19 (8, 4)
	702 iconst_0 (8, 4)
	703 goto (8, 4)
	704 15 (8, 4)
	706 dload (8, 4)
	707 #26 (8, 4)
	708 dload_2 (8, 4)
	709 dcmpg (8, 4)
	710 ifgt (8, 4)
	711 7 (8, 4)
	713 iconst_1 (8, 4)
	714 goto (8, 4)
	715 4 (8, 4)
	717 iconst_0 (8, 4)
	718 istore (8, 4)
	719 #28 (8, 4)
	720 iload (9, 1)
	721 #28 (9, 1)
	722 ifeq (9, 1)
	723 11 (9, 1)
	725 dload_2 (9, 1)
	726 aload_0 (9, 1)
	727 getfield (9, 1)
	728 org/apache/commons/math3/ode/nonstiff/AdamsMoultonIntegrator.stepStart:D (9, 1)
	730 dsub (9, 1)
	731 dstore (9, 1)
	732 #12 (9, 1)
	733 aload (8, 4)
	734 #11 (8, 4)
	735 dload (8, 4)
	736 #12 (8, 4)
	737 invokevirtual (8, 4)
	738 org/apache/commons/math3/ode/sampling/NordsieckStepInterpolator.rescale:(D)V (8, 4)
	740 aload_0 (4, 3)
	741 getfield (4, 3)
	742 org/apache/commons/math3/ode/nonstiff/AdamsMoultonIntegrator.isLastStep:Z (4, 3)
	744 ifeq (4, 3)
	745 -581 (4, 3)
	747 aload_1 (4, 3)
	748 aload_0 (4, 3)
	749 getfield (4, 3)
	750 org/apache/commons/math3/ode/nonstiff/AdamsMoultonIntegrator.stepStart:D (4, 3)
	752 invokevirtual (4, 3)
	753 org/apache/commons/math3/ode/ExpandableStatefulODE.setTime:(D)V (4, 3)
	755 aload_1 (4, 3)
	756 aload (4, 3)
	757 #6 (4, 3)
	758 invokevirtual (4, 3)
	759 org/apache/commons/math3/ode/ExpandableStatefulODE.setCompleteState:([D)V (4, 3)
	761 aload_0 (4, 3)
	762 invokevirtual (4, 3)
	763 org/apache/commons/math3/ode/nonstiff/AdamsMoultonIntegrator.resetInternalState:()V (4, 3)
	765 return (0, 3)

