Method: <init>
	0 aload_0 (0, 0)
	1 iload (0, 0)
	2 #5 (0, 0)
	3 aload (0, 0)
	4 #6 (0, 0)
	5 aload (0, 0)
	6 #7 (0, 0)
	7 aload (0, 0)
	8 #8 (0, 0)
	9 aload (0, 0)
	10 #9 (0, 0)
	11 aload (0, 0)
	12 #10 (0, 0)
	13 invokespecial (0, 0)
	14 org/apache/commons/math3/ode/sampling/AbstractFieldStepInterpolator.<init>:(ZLorg/apache/commons/math3/ode/FieldODEStateAndDerivative;Lorg/apache/commons/math3/ode/FieldODEStateAndDerivative;Lorg/apache/commons/math3/ode/FieldODEStateAndDerivative;Lorg/apache/commons/math3/ode/FieldODEStateAndDerivative;Lorg/apache/commons/math3/ode/FieldEquationsMapper;)V (0, 0)
	16 aload_0 (0, 0)
	17 aload_1 (0, 0)
	18 putfield (0, 0)
	19 org/apache/commons/math3/ode/nonstiff/AdamsFieldStepInterpolator.scalingH:Lorg/apache/commons/math3/RealFieldElement; (0, 0)
	21 aload_0 (0, 0)
	22 aload_2 (0, 0)
	23 putfield (0, 0)
	24 org/apache/commons/math3/ode/nonstiff/AdamsFieldStepInterpolator.reference:Lorg/apache/commons/math3/ode/FieldODEStateAndDerivative; (0, 0)
	26 aload_0 (0, 0)
	27 aload_3 (0, 0)
	28 invokevirtual (0, 0)
	29 [Lorg/apache/commons/math3/RealFieldElement;.clone:()Ljava/lang/Object; (0, 0)
	31 checkcast (0, 0)
	32 [Lorg/apache/commons/math3/RealFieldElement; (0, 0)
	34 putfield (0, 0)
	35 org/apache/commons/math3/ode/nonstiff/AdamsFieldStepInterpolator.scaled:[Lorg/apache/commons/math3/RealFieldElement; (0, 0)
	37 aload_0 (0, 0)
	38 new (0, 0)
	39 org/apache/commons/math3/linear/Array2DRowFieldMatrix (0, 0)
	41 dup (0, 0)
	42 aload (0, 0)
	43 #4 (0, 0)
	44 invokevirtual (0, 0)
	45 org/apache/commons/math3/linear/Array2DRowFieldMatrix.getData:()[[Lorg/apache/commons/math3/FieldElement; (0, 0)
	47 iconst_0 (0, 0)
	48 invokespecial (0, 0)
	49 org/apache/commons/math3/linear/Array2DRowFieldMatrix.<init>:([[Lorg/apache/commons/math3/FieldElement;Z)V (0, 0)
	51 putfield (0, 0)
	52 org/apache/commons/math3/ode/nonstiff/AdamsFieldStepInterpolator.nordsieck:Lorg/apache/commons/math3/linear/Array2DRowFieldMatrix; (0, 0)
	54 return (0, 0)

Method: create
	0 aload_0 (0, 0)
	1 iload_1 (0, 0)
	2 aload_2 (0, 0)
	3 aload_3 (0, 0)
	4 aload (0, 0)
	5 #4 (0, 0)
	6 aload (0, 0)
	7 #5 (0, 0)
	8 aload (0, 0)
	9 #6 (0, 0)
	10 invokevirtual (0, 0)
	11 org/apache/commons/math3/ode/nonstiff/AdamsFieldStepInterpolator.create:(ZLorg/apache/commons/math3/ode/FieldODEStateAndDerivative;Lorg/apache/commons/math3/ode/FieldODEStateAndDerivative;Lorg/apache/commons/math3/ode/FieldODEStateAndDerivative;Lorg/apache/commons/math3/ode/FieldODEStateAndDerivative;Lorg/apache/commons/math3/ode/FieldEquationsMapper;)Lorg/apache/commons/math3/ode/nonstiff/AdamsFieldStepInterpolator; (0, 0)
	13 areturn (0, 0)

Method: computeInterpolatedStateAndDerivatives
	0 aload_0 (0, 0)
	1 getfield (0, 0)
	2 org/apache/commons/math3/ode/nonstiff/AdamsFieldStepInterpolator.reference:Lorg/apache/commons/math3/ode/FieldODEStateAndDerivative; (0, 0)
	4 aload_2 (0, 0)
	5 aload_0 (0, 0)
	6 getfield (0, 0)
	7 org/apache/commons/math3/ode/nonstiff/AdamsFieldStepInterpolator.scalingH:Lorg/apache/commons/math3/RealFieldElement; (0, 0)
	9 aload_0 (0, 0)
	10 getfield (0, 0)
	11 org/apache/commons/math3/ode/nonstiff/AdamsFieldStepInterpolator.scaled:[Lorg/apache/commons/math3/RealFieldElement; (0, 0)
	13 aload_0 (0, 0)
	14 getfield (0, 0)
	15 org/apache/commons/math3/ode/nonstiff/AdamsFieldStepInterpolator.nordsieck:Lorg/apache/commons/math3/linear/Array2DRowFieldMatrix; (0, 0)
	17 invokestatic (0, 0)
	18 org/apache/commons/math3/ode/nonstiff/AdamsFieldStepInterpolator.taylor:(Lorg/apache/commons/math3/ode/FieldODEStateAndDerivative;Lorg/apache/commons/math3/RealFieldElement;Lorg/apache/commons/math3/RealFieldElement;[Lorg/apache/commons/math3/RealFieldElement;Lorg/apache/commons/math3/linear/Array2DRowFieldMatrix;)Lorg/apache/commons/math3/ode/FieldODEStateAndDerivative; (0, 0)
	20 areturn (0, 0)

Method: taylor
	0 aload_1 (0, 0)
	1 aload_0 (0, 0)
	2 invokevirtual (0, 0)
	3 org/apache/commons/math3/ode/FieldODEStateAndDerivative.getTime:()Lorg/apache/commons/math3/RealFieldElement; (0, 0)
	5 invokeinterface (0, 0)
	6 org/apache/commons/math3/RealFieldElement.org/apache/commons/math3/RealFieldElement (0, 0)
	8 0 (0, 0)
	10 checkcast (0, 0)
	11 org/apache/commons/math3/RealFieldElement (0, 0)
	13 astore (0, 0)
	14 #5 (0, 0)
	15 aload (0, 0)
	16 #5 (0, 0)
	17 aload_2 (0, 0)
	18 invokeinterface (0, 0)
	19 org/apache/commons/math3/RealFieldElement.getField:()Lorg/apache/commons/math3/Field; (0, 0)
	21 0 (0, 0)
	23 checkcast (0, 0)
	24 org/apache/commons/math3/RealFieldElement (0, 0)
	26 astore (0, 0)
	27 #6 (0, 0)
	28 aload_1 (0, 0)
	29 invokeinterface (0, 0)
	30 org/apache/commons/math3/RealFieldElement.org/apache/commons/math3/util/MathArrays (0, 0)
	32 0 (0, 0)
	34 aload_3 (0, 0)
	35 arraylength (0, 0)
	36 invokestatic (0, 0)
	37 org/apache/commons/math3/util/MathArrays.buildArray:(Lorg/apache/commons/math3/Field;I)[Ljava/lang/Object; (0, 0)
	39 checkcast (0, 0)
	40 [Lorg/apache/commons/math3/RealFieldElement; (0, 0)
	42 astore (0, 0)
	43 #7 (0, 0)
	44 aload (0, 0)
	45 #7 (0, 0)
	46 aload_1 (0, 0)
	47 invokeinterface (0, 0)
	48 org/apache/commons/math3/RealFieldElement.org/apache/commons/math3/util/MathArrays (0, 0)
	50 0 (0, 0)
	52 invokeinterface (0, 0)
	53 org/apache/commons/math3/Field.java/util/Arrays (0, 0)
	55 0 (0, 0)
	57 invokestatic (0, 0)
	58 java/util/Arrays.fill:([Ljava/lang/Object;Ljava/lang/Object;)V (0, 0)
	60 aload_1 (0, 0)
	61 invokeinterface (0, 0)
	62 org/apache/commons/math3/RealFieldElement.org/apache/commons/math3/util/MathArrays (0, 0)
	64 0 (0, 0)
	66 aload_3 (0, 0)
	67 arraylength (0, 0)
	68 invokestatic (0, 0)
	69 org/apache/commons/math3/util/MathArrays.buildArray:(Lorg/apache/commons/math3/Field;I)[Ljava/lang/Object; (0, 0)
	71 checkcast (0, 0)
	72 [Lorg/apache/commons/math3/RealFieldElement; (0, 0)
	74 astore (0, 0)
	75 #8 (0, 0)
	76 aload (0, 0)
	77 #8 (0, 0)
	78 aload_1 (0, 0)
	79 invokeinterface (0, 0)
	80 org/apache/commons/math3/RealFieldElement.org/apache/commons/math3/util/MathArrays (0, 0)
	82 0 (0, 0)
	84 invokeinterface (0, 0)
	85 org/apache/commons/math3/Field.java/util/Arrays (0, 0)
	87 0 (0, 0)
	89 invokestatic (0, 0)
	90 java/util/Arrays.fill:([Ljava/lang/Object;Ljava/lang/Object;)V (0, 0)
	92 aload (2, 4)
	93 #4 (2, 4)
	94 invokevirtual (2, 4)
	95 org/apache/commons/math3/linear/Array2DRowFieldMatrix.getDataRef:()[[Lorg/apache/commons/math3/FieldElement; (2, 4)
	97 checkcast (2, 4)
	98 [[Lorg/apache/commons/math3/RealFieldElement; (2, 4)
	100 astore (2, 4)
	101 #9 (2, 4)
	102 aload (3, 4)
	103 #9 (3, 4)
	104 arraylength (3, 4)
	105 iconst_1 (3, 4)
	106 isub (3, 4)
	107 istore (3, 4)
	108 #10 (3, 4)
	109 iload (3, 4)
	110 #10 (3, 4)
	111 iflt (3, 4)
	112 117 (3, 4)
	114 iload (3, 4)
	115 #10 (3, 4)
	116 iconst_2 (3, 4)
	117 iadd (3, 4)
	118 istore (3, 4)
	119 #11 (3, 4)
	120 aload (3, 4)
	121 #9 (3, 4)
	122 iload (3, 4)
	123 #10 (3, 4)
	124 aaload (3, 4)
	125 astore (3, 4)
	126 #12 (3, 4)
	127 aload (3, 4)
	128 #6 (3, 4)
	129 iload (3, 4)
	130 #11 (3, 4)
	131 invokeinterface (3, 4)
	132 org/apache/commons/math3/RealFieldElement.multiply:(Ljava/lang/Object;)Ljava/lang/Object; (3, 4)
	134 0 (3, 4)
	136 checkcast (3, 4)
	137 org/apache/commons/math3/RealFieldElement (3, 4)
	139 astore (3, 4)
	140 #13 (3, 4)
	141 iconst_0 (4, 4)
	142 istore (4, 4)
	143 #14 (4, 4)
	144 iload (4, 4)
	145 #14 (4, 4)
	146 aload (4, 4)
	147 #12 (4, 4)
	148 arraylength (4, 4)
	149 if_icmpge (4, 4)
	150 73 (4, 4)
	152 aload (4, 4)
	153 #12 (4, 4)
	154 iload (4, 4)
	155 #14 (4, 4)
	156 aaload (4, 4)
	157 aload (4, 4)
	158 #13 (4, 4)
	159 invokeinterface (4, 4)
	160 org/apache/commons/math3/RealFieldElement.add:(Ljava/lang/Object;)Ljava/lang/Object; (4, 4)
	162 0 (4, 4)
	164 checkcast (4, 4)
	165 org/apache/commons/math3/RealFieldElement (4, 4)
	167 astore (4, 4)
	168 #15 (4, 4)
	169 aload (4, 4)
	170 #7 (4, 4)
	171 iload (4, 4)
	172 #14 (4, 4)
	173 aload (4, 4)
	174 #7 (4, 4)
	175 iload (4, 4)
	176 #14 (4, 4)
	177 aaload (4, 4)
	178 aload (4, 4)
	179 #15 (4, 4)
	180 invokeinterface (4, 4)
	181 org/apache/commons/math3/RealFieldElement.multiply:(I)Ljava/lang/Object; (4, 4)
	183 0 (4, 4)
	185 checkcast (4, 4)
	186 org/apache/commons/math3/RealFieldElement (4, 4)
	188 aastore (4, 4)
	189 aload (4, 4)
	190 #8 (4, 4)
	191 iload (4, 4)
	192 #14 (4, 4)
	193 aload (4, 4)
	194 #8 (4, 4)
	195 iload (4, 4)
	196 #14 (4, 4)
	197 aaload (4, 4)
	198 aload (4, 4)
	199 #15 (4, 4)
	200 iload (4, 4)
	201 #11 (4, 4)
	202 invokeinterface (4, 4)
	203 org/apache/commons/math3/RealFieldElement.getState:()[Lorg/apache/commons/math3/RealFieldElement; (4, 4)
	205 0 (4, 4)
	207 invokeinterface (4, 4)
	208 org/apache/commons/math3/RealFieldElement.multiply:(I)Ljava/lang/Object; (4, 4)
	210 0 (4, 4)
	212 checkcast (4, 4)
	213 org/apache/commons/math3/RealFieldElement (4, 4)
	215 aastore (4, 4)
	216 iinc (4, 4)
	217 #14 (4, 4)
	218 -89 (4, 4)
	219 goto (4, 4)
	220 -75 (4, 4)
	222 iinc (4, 4)
	223 #10 (4, 4)
	224 -89 (4, 4)
	225 goto (4, 4)
	226 -116 (4, 4)
	228 aload_0 (3, 4)
	229 invokevirtual (3, 4)
	230 org/apache/commons/math3/ode/FieldODEStateAndDerivative.getState:()[Lorg/apache/commons/math3/RealFieldElement; (3, 4)
	232 astore (3, 4)
	233 #10 (3, 4)
	234 iconst_0 (4, 4)
	235 istore (4, 4)
	236 #11 (4, 4)
	237 iload (4, 4)
	238 #11 (4, 4)
	239 aload (4, 4)
	240 #7 (4, 4)
	241 arraylength (4, 4)
	242 if_icmpge (4, 4)
	243 100 (4, 4)
	245 aload (4, 4)
	246 #7 (4, 4)
	247 iload (4, 4)
	248 #11 (4, 4)
	249 aload (4, 4)
	250 #7 (4, 4)
	251 iload (4, 4)
	252 #11 (4, 4)
	253 aaload (4, 4)
	254 aload_3 (4, 4)
	255 iload (4, 4)
	256 #11 (4, 4)
	257 aaload (4, 4)
	258 aload (4, 4)
	259 #6 (4, 4)
	260 invokeinterface (4, 4)
	261 org/apache/commons/math3/RealFieldElement.add:(Ljava/lang/Object;)Ljava/lang/Object; (4, 4)
	263 0 (4, 4)
	265 invokeinterface (4, 4)
	266 org/apache/commons/math3/RealFieldElement.multiply:(I)Ljava/lang/Object; (4, 4)
	268 0 (4, 4)
	270 checkcast (4, 4)
	271 org/apache/commons/math3/RealFieldElement (4, 4)
	273 aastore (4, 4)
	274 aload (4, 4)
	275 #10 (4, 4)
	276 iload (4, 4)
	277 #11 (4, 4)
	278 aload (4, 4)
	279 #10 (4, 4)
	280 iload (4, 4)
	281 #11 (4, 4)
	282 aaload (4, 4)
	283 aload (4, 4)
	284 #7 (4, 4)
	285 iload (4, 4)
	286 #11 (4, 4)
	287 aaload (4, 4)
	288 invokeinterface (4, 4)
	289 org/apache/commons/math3/RealFieldElement.multiply:(I)Ljava/lang/Object; (4, 4)
	291 0 (4, 4)
	293 checkcast (4, 4)
	294 org/apache/commons/math3/RealFieldElement (4, 4)
	296 aastore (4, 4)
	297 aload (4, 4)
	298 #8 (4, 4)
	299 iload (4, 4)
	300 #11 (4, 4)
	301 aload (4, 4)
	302 #8 (4, 4)
	303 iload (4, 4)
	304 #11 (4, 4)
	305 aaload (4, 4)
	306 aload_3 (4, 4)
	307 iload (4, 4)
	308 #11 (4, 4)
	309 aaload (4, 4)
	310 aload (4, 4)
	311 #6 (4, 4)
	312 invokeinterface (4, 4)
	313 org/apache/commons/math3/RealFieldElement.add:(Ljava/lang/Object;)Ljava/lang/Object; (4, 4)
	315 0 (4, 4)
	317 invokeinterface (4, 4)
	318 org/apache/commons/math3/RealFieldElement.multiply:(I)Ljava/lang/Object; (4, 4)
	320 0 (4, 4)
	322 checkcast (4, 4)
	323 org/apache/commons/math3/RealFieldElement (4, 4)
	325 aload (4, 4)
	326 #5 (4, 4)
	327 invokeinterface (4, 4)
	328 org/apache/commons/math3/RealFieldElement.getField:()Lorg/apache/commons/math3/Field; (4, 4)
	330 0 (4, 4)
	332 checkcast (4, 4)
	333 org/apache/commons/math3/RealFieldElement (4, 4)
	335 aastore (4, 4)
	336 iinc (4, 4)
	337 #11 (4, 4)
	338 -89 (4, 4)
	339 goto (4, 4)
	340 -102 (4, 4)
	342 new (3, 4)
	343 org/apache/commons/math3/ode/FieldODEStateAndDerivative (3, 4)
	345 dup (3, 4)
	346 aload_1 (3, 4)
	347 aload (3, 4)
	348 #10 (3, 4)
	349 aload (3, 4)
	350 #8 (3, 4)
	351 invokespecial (3, 4)
	352 org/apache/commons/math3/ode/FieldODEStateAndDerivative.<init>:(Lorg/apache/commons/math3/RealFieldElement;[Lorg/apache/commons/math3/RealFieldElement;[Lorg/apache/commons/math3/RealFieldElement;)V (3, 4)
	354 areturn (1, 4)

