Method: <init>
	0 aload_0 (1, 4)
	1 invokespecial (1, 4)
	4 aload_0 (1, 4)
	5 aload_1 (1, 4)
	6 putfield (1, 4)
	9 iload_2 (1, 4)
	10 iconst_1 (1, 4)
	11 isub (1, 4)
	12 istore_3 (1, 4)
	13 aload_0 (1, 4)
	14 iload_3 (1, 4)
	15 invokespecial (1, 4)
	18 astore (1, 4)
	20 new (1, 4)
	23 dup (1, 4)
	24 aload (1, 4)
	26 invokespecial (1, 4)
	29 invokevirtual (1, 4)
	32 astore (1, 4)
	34 aload_1 (1, 4)
	35 iload_3 (1, 4)
	36 invokestatic (1, 4)
	39 checkcast (1, 4)
	42 astore (1, 4)
	44 aload (1, 4)
	46 aload_1 (1, 4)
	47 invokeinterface (1, 4)
	52 invokestatic (1, 4)
	55 aload_0 (1, 4)
	56 aload (1, 4)
	58 new (1, 4)
	61 dup (1, 4)
	62 aload (1, 4)
	64 iconst_0 (1, 4)
	65 invokespecial (1, 4)
	68 invokeinterface (1, 4)
	73 invokeinterface (1, 4)
	78 checkcast (1, 4)
	81 putfield (1, 4)
	84 aload (1, 1)
	86 invokeinterface (1, 1)
	91 checkcast (1, 1)
	94 astore (1, 1)
	96 aload (2, 1)
	98 arraylength (2, 1)
	99 iconst_1 (2, 1)
	100 isub (2, 1)
	101 istore (2, 1)
	103 iload (2, 1)
	105 ifle (2, 1)
	108 aload (2, 1)
	110 iload (2, 1)
	112 aload (2, 1)
	114 iload (2, 1)
	116 iconst_1 (2, 1)
	117 isub (2, 1)
	118 aaload (2, 1)
	119 aastore (2, 1)
	120 iinc (2, 1)
	123 goto (2, 1)
	126 aload (1, 1)
	128 iconst_0 (1, 1)
	129 aload_1 (1, 1)
	130 iload_3 (1, 1)
	131 invokestatic (1, 1)
	134 checkcast (1, 1)
	137 aastore (1, 1)
	138 aload (1, 1)
	140 iconst_0 (1, 1)
	141 aaload (1, 1)
	142 aload_1 (1, 1)
	143 invokeinterface (1, 1)
	148 invokestatic (1, 1)
	151 aload_0 (1, 1)
	152 new (1, 1)
	155 dup (1, 1)
	156 aload (1, 1)
	158 new (1, 1)
	161 dup (1, 1)
	162 aload (1, 1)
	164 iconst_0 (1, 1)
	165 invokespecial (1, 1)
	168 invokeinterface (1, 1)
	173 invokeinterface (1, 1)
	178 invokespecial (1, 1)
	181 putfield (1, 1)
	184 return (0, 1)

Method: getInstance
	0 getstatic (0, 0)
	3 dup (0, 0)
	4 astore_2 (0, 0)
	5 monitorenter (0, 0)
	6 getstatic (0, 4)
	9 iload_1 (0, 4)
	10 invokestatic (0, 4)
	13 invokeinterface (0, 4)
	18 checkcast (0, 4)
	21 astore_3 (0, 4)
	22 aload_3 (1, 1)
	23 ifnonnull (1, 1)
	26 new (1, 1)
	29 dup (1, 1)
	30 invokespecial (1, 1)
	33 astore_3 (1, 1)
	34 getstatic (1, 4)
	37 iload_1 (1, 4)
	38 invokestatic (1, 4)
	41 aload_3 (1, 4)
	42 invokeinterface (1, 4)
	47 pop (1, 4)
	48 aload_3 (0, 4)
	49 aload_0 (0, 4)
	50 invokeinterface (0, 4)
	55 checkcast (0, 4)
	58 astore (0, 4)
	60 aload (1, 1)
	62 ifnonnull (1, 1)
	65 new (1, 4)
	68 dup (1, 4)
	69 aload_0 (1, 4)
	70 iload_1 (1, 4)
	71 invokespecial (1, 4)
	74 astore (1, 4)
	76 aload_3 (1, 4)
	77 aload_0 (1, 4)
	78 aload (1, 4)
	80 invokeinterface (1, 4)
	85 pop (1, 4)
	86 aload (0, 4)
	88 aload_2 (0, 4)
	89 monitorexit (0, 4)
	90 areturn (0, 4)
	91 astore (-1, 4)
	93 aload_2 (-1, 4)
	94 monitorexit (-1, 4)
	95 aload (-1, 4)
	97 athrow (0, 4)

Method: buildP
	0 aload_0 (0, 0)
	1 getfield (0, 0)
	4 iload_1 (0, 0)
	5 iload_1 (0, 0)
	6 invokestatic (0, 0)
	9 checkcast (0, 0)
	12 astore_2 (0, 0)
	13 iconst_1 (1, 4)
	14 istore_3 (1, 4)
	15 iload_3 (1, 4)
	16 aload_2 (1, 4)
	17 arraylength (1, 4)
	18 if_icmpgt (1, 4)
	21 aload_2 (1, 4)
	22 iload_3 (1, 4)
	23 iconst_1 (1, 4)
	24 isub (1, 4)
	25 aaload (1, 4)
	26 astore (1, 4)
	28 iload_3 (1, 4)
	29 ineg (1, 4)
	30 istore (1, 4)
	32 aload_0 (1, 4)
	33 getfield (1, 4)
	36 invokeinterface (1, 4)
	41 checkcast (1, 4)
	44 iload (1, 4)
	46 i2d (1, 4)
	47 invokeinterface (1, 4)
	52 checkcast (1, 4)
	55 astore (1, 4)
	57 iconst_1 (2, 4)
	58 istore (2, 4)
	60 iload (2, 4)
	62 aload (2, 4)
	64 arraylength (2, 4)
	65 if_icmpgt (2, 4)
	68 aload (2, 4)
	70 iload (2, 4)
	72 iconst_1 (2, 4)
	73 isub (2, 4)
	74 aload (2, 4)
	76 iload (2, 4)
	78 iconst_1 (2, 4)
	79 iadd (2, 4)
	80 invokeinterface (2, 4)
	85 checkcast (2, 4)
	88 aastore (2, 4)
	89 aload (2, 4)
	91 iload (2, 4)
	93 invokeinterface (2, 4)
	98 checkcast (2, 4)
	101 astore (2, 4)
	103 iinc (2, 4)
	106 goto (2, 4)
	109 iinc (2, 4)
	112 goto (2, 4)
	115 new (1, 4)
	118 dup (1, 4)
	119 aload_2 (1, 4)
	120 iconst_0 (1, 4)
	121 invokespecial (1, 4)
	124 areturn (1, 4)

Method: initializeHighOrderDerivatives
	0 aload_0 (0, 0)
	1 getfield (0, 0)
	4 aload_0 (0, 0)
	5 getfield (0, 0)
	8 arraylength (0, 0)
	9 iconst_1 (0, 0)
	10 iadd (0, 0)
	11 aload_0 (0, 0)
	12 getfield (0, 0)
	15 arraylength (0, 0)
	16 iconst_1 (0, 0)
	17 iadd (0, 0)
	18 invokestatic (0, 0)
	21 checkcast (0, 0)
	24 astore (0, 0)
	26 aload_0 (0, 0)
	27 getfield (0, 0)
	30 aload_0 (0, 0)
	31 getfield (0, 0)
	34 arraylength (0, 0)
	35 iconst_1 (0, 0)
	36 iadd (0, 0)
	37 aload_3 (0, 0)
	38 iconst_0 (0, 0)
	39 aaload (0, 0)
	40 arraylength (0, 0)
	41 invokestatic (0, 0)
	44 checkcast (0, 0)
	47 astore (0, 0)
	49 aload_3 (0, 0)
	50 iconst_0 (0, 0)
	51 aaload (0, 0)
	52 astore (0, 0)
	54 aload (0, 0)
	56 iconst_0 (0, 0)
	57 aaload (0, 0)
	58 astore (0, 0)
	60 iconst_1 (1, 4)
	61 istore (1, 4)
	63 iload (1, 4)
	65 aload_3 (1, 4)
	66 arraylength (1, 4)
	67 if_icmpge (1, 4)
	70 aload_2 (1, 4)
	71 iload (1, 4)
	73 aaload (1, 4)
	74 aload_2 (1, 4)
	75 iconst_0 (1, 4)
	76 aaload (1, 4)
	77 invokeinterface (1, 4)
	82 checkcast (1, 4)
	85 astore (1, 4)
	87 aload (1, 4)
	89 aload_1 (1, 4)
	90 invokeinterface (1, 4)
	95 checkcast (1, 4)
	98 astore (1, 4)
	100 aload_1 (1, 4)
	101 invokeinterface (1, 4)
	106 checkcast (1, 4)
	109 astore (1, 4)
	111 aload (1, 4)
	113 iconst_2 (1, 4)
	114 iload (1, 4)
	116 imul (1, 4)
	117 iconst_2 (1, 4)
	118 isub (1, 4)
	119 aaload (1, 4)
	120 astore (1, 4)
	122 iconst_2 (1, 4)
	123 iload (1, 4)
	125 imul (1, 4)
	126 iconst_1 (1, 4)
	127 isub (1, 4)
	128 aload (1, 4)
	130 arraylength (1, 4)
	131 if_icmpge (1, 4)
	134 aload (1, 4)
	136 iconst_2 (1, 4)
	137 iload (1, 4)
	139 imul (1, 4)
	140 iconst_1 (1, 4)
	141 isub (1, 4)
	142 aaload (1, 4)
	143 goto (1, 4)
	146 aconst_null (1, 4)
	147 astore (1, 4)
	149 iconst_0 (2, 4)
	150 istore (2, 4)
	152 iload (2, 4)
	154 aload (2, 4)
	156 arraylength (2, 4)
	157 if_icmpge (2, 4)
	160 aload (2, 4)
	162 aload (2, 4)
	164 invokeinterface (2, 4)
	169 checkcast (2, 4)
	172 astore (2, 4)
	174 aload (2, 4)
	176 iload (2, 4)
	178 aload (2, 4)
	180 aload (2, 4)
	182 invokeinterface (2, 4)
	187 checkcast (2, 4)
	190 aastore (2, 4)
	191 aload (3, 1)
	193 ifnull (3, 1)
	196 aload (3, 1)
	198 iload (3, 1)
	200 aload (3, 1)
	202 iload (3, 1)
	204 iconst_2 (3, 1)
	205 iadd (3, 1)
	206 invokeinterface (3, 1)
	211 checkcast (3, 1)
	214 aastore (3, 1)
	215 iinc (3, 1)
	218 goto (3, 1)
	221 aload_3 (2, 4)
	222 iload (2, 4)
	224 aaload (2, 4)
	225 astore (2, 4)
	227 aload (2, 4)
	229 iload (2, 4)
	231 aaload (2, 4)
	232 astore (2, 4)
	234 aload (2, 4)
	236 iconst_2 (2, 4)
	237 iload (2, 4)
	239 imul (2, 4)
	240 iconst_2 (2, 4)
	241 isub (2, 4)
	242 aaload (2, 4)
	243 astore (2, 4)
	245 iconst_2 (2, 4)
	246 iload (2, 4)
	248 imul (2, 4)
	249 iconst_1 (2, 4)
	250 isub (2, 4)
	251 aload (2, 4)
	253 arraylength (2, 4)
	254 if_icmpge (2, 4)
	257 aload (2, 4)
	259 iconst_2 (2, 4)
	260 iload (2, 4)
	262 imul (2, 4)
	263 iconst_1 (2, 4)
	264 isub (2, 4)
	265 aaload (2, 4)
	266 goto (2, 4)
	269 aconst_null (2, 4)
	270 astore (2, 4)
	272 iconst_0 (3, 4)
	273 istore (3, 4)
	275 iload (3, 4)
	277 aload (3, 4)
	279 arraylength (3, 4)
	280 if_icmpge (3, 4)
	283 aload (3, 4)
	285 iload (3, 4)
	287 aload (3, 4)
	289 iload (3, 4)
	291 aaload (3, 4)
	292 aload (3, 4)
	294 iload (3, 4)
	296 aaload (3, 4)
	297 invokeinterface (3, 4)
	302 checkcast (3, 4)
	305 aload (3, 4)
	307 aload (3, 4)
	309 iload (3, 4)
	311 aaload (3, 4)
	312 invokeinterface (3, 4)
	317 invokeinterface (3, 4)
	322 checkcast (3, 4)
	325 aastore (3, 4)
	326 aload (4, 1)
	328 ifnull (4, 1)
	331 aload (4, 1)
	333 iload (4, 1)
	335 aload (4, 1)
	337 iload (4, 1)
	339 aaload (4, 1)
	340 aload (4, 1)
	342 iload (4, 1)
	344 aaload (4, 1)
	345 invokeinterface (4, 1)
	350 checkcast (4, 1)
	353 aastore (4, 1)
	354 iinc (4, 1)
	357 goto (4, 1)
	360 iinc (4, 1)
	363 goto (4, 1)
	366 new (3, 4)
	369 dup (3, 4)
	370 new (3, 4)
	373 dup (3, 4)
	374 aload (3, 4)
	376 iconst_0 (3, 4)
	377 invokespecial (3, 4)
	380 invokespecial (3, 4)
	383 astore (3, 4)
	385 aload (3, 4)
	387 invokevirtual (3, 4)
	390 new (3, 4)
	393 dup (3, 4)
	394 aload (3, 4)
	396 iconst_0 (3, 4)
	397 invokespecial (3, 4)
	400 invokeinterface (3, 4)
	405 astore (3, 4)
	407 new (3, 4)
	410 dup (3, 4)
	411 aload_0 (3, 4)
	412 getfield (3, 4)
	415 aload (3, 4)
	417 invokeinterface (3, 4)
	422 iconst_1 (3, 4)
	423 isub (3, 4)
	424 aload (3, 4)
	426 invokeinterface (3, 4)
	431 invokespecial (3, 4)
	434 astore (3, 4)
	436 iconst_0 (4, 4)
	437 istore (4, 4)
	439 iload (4, 4)
	441 aload (4, 4)
	443 invokevirtual (4, 4)
	446 if_icmpge (4, 4)
	449 iconst_0 (5, 4)
	450 istore (5, 4)
	452 iload (5, 4)
	454 aload (5, 4)
	456 invokevirtual (5, 4)
	459 if_icmpge (5, 4)
	462 aload (5, 4)
	464 iload (5, 4)
	466 iload (5, 4)
	468 aload (5, 4)
	470 iload (5, 4)
	472 iload (5, 4)
	474 invokeinterface (5, 4)
	479 invokevirtual (5, 4)
	482 iinc (5, 4)
	485 goto (5, 4)
	488 iinc (5, 4)
	491 goto (5, 4)
	494 aload (4, 4)
	496 areturn (4, 4)

Method: updateHighOrderDerivativesPhase1
	0 aload_0 (0, 0)
	1 getfield (0, 0)
	4 aload_1 (0, 0)
	5 invokevirtual (0, 0)
	8 areturn (0, 0)

Method: updateHighOrderDerivativesPhase2
	0 aload_3 (0, 0)
	1 invokevirtual (0, 0)
	4 checkcast (0, 0)
	7 astore (0, 0)
	9 iconst_0 (1, 4)
	10 istore (1, 4)
	12 iload (1, 4)
	14 aload (1, 4)
	16 arraylength (1, 4)
	17 if_icmpge (1, 4)
	20 aload (1, 4)
	22 iload (1, 4)
	24 aaload (1, 4)
	25 astore (1, 4)
	27 aload_0 (1, 4)
	28 getfield (1, 4)
	31 iload (1, 4)
	33 aaload (1, 4)
	34 astore (1, 4)
	36 iconst_0 (2, 4)
	37 istore (2, 4)
	39 iload (2, 4)
	41 aload (2, 4)
	43 arraylength (2, 4)
	44 if_icmpge (2, 4)
	47 aload (2, 4)
	49 iload (2, 4)
	51 aload (2, 4)
	53 iload (2, 4)
	55 aaload (2, 4)
	56 aload (2, 4)
	58 aload_1 (2, 4)
	59 iload (2, 4)
	61 aaload (2, 4)
	62 aload_2 (2, 4)
	63 iload (2, 4)
	65 aaload (2, 4)
	66 invokeinterface (2, 4)
	71 invokeinterface (2, 4)
	76 invokeinterface (2, 4)
	81 checkcast (2, 4)
	84 aastore (2, 4)
	85 iinc (2, 4)
	88 goto (2, 4)
	91 iinc (2, 4)
	94 goto (2, 4)
	97 return (0, 0)

Method: <clinit>
	0 new (0, 4)
	3 dup (0, 4)
	4 invokespecial (0, 4)
	7 putstatic (0, 4)
	10 return (0, 4)

