Method: <init>
	0 aload_0 (1, 4)
	1 invokespecial (1, 4)
	2 java/lang/Object.<init>:()V (1, 4)
	4 iload_1 (1, 4)
	5 iconst_1 (1, 4)
	6 isub (1, 4)
	7 istore_2 (1, 4)
	8 aload_0 (1, 4)
	9 iload_2 (1, 4)
	10 invokespecial (1, 4)
	11 org/apache/commons/math3/ode/nonstiff/AdamsNordsieckTransformer.buildP:(I)Lorg/apache/commons/math3/linear/FieldMatrix; (1, 4)
	13 astore_3 (1, 4)
	14 new (1, 4)
	15 org/apache/commons/math3/linear/FieldLUDecomposition (1, 4)
	17 dup (1, 4)
	18 aload_3 (1, 4)
	19 invokespecial (1, 4)
	20 org/apache/commons/math3/linear/FieldLUDecomposition.<init>:(Lorg/apache/commons/math3/linear/FieldMatrix;)V (1, 4)
	22 invokevirtual (1, 4)
	23 org/apache/commons/math3/linear/FieldLUDecomposition.getSolver:()Lorg/apache/commons/math3/linear/FieldDecompositionSolver; (1, 4)
	25 astore (1, 4)
	26 #4 (1, 4)
	27 iload_2 (1, 4)
	28 anewarray (1, 4)
	29 org/apache/commons/math3/fraction/BigFraction (1, 4)
	31 astore (1, 4)
	32 #5 (1, 4)
	33 aload (1, 4)
	34 #5 (1, 4)
	35 getstatic (1, 4)
	36 org/apache/commons/math3/fraction/BigFraction.ONE:Lorg/apache/commons/math3/fraction/BigFraction; (1, 4)
	38 invokestatic (1, 4)
	39 java/util/Arrays.fill:([Ljava/lang/Object;Ljava/lang/Object;)V (1, 4)
	41 aload (1, 4)
	42 #4 (1, 4)
	43 new (1, 4)
	44 org/apache/commons/math3/linear/ArrayFieldVector (1, 4)
	46 dup (1, 4)
	47 aload (1, 4)
	48 #5 (1, 4)
	49 iconst_0 (1, 4)
	50 invokespecial (1, 4)
	51 org/apache/commons/math3/linear/ArrayFieldVector.<init>:([Lorg/apache/commons/math3/FieldElement;Z)V (1, 4)
	53 invokeinterface (1, 4)
	54 org/apache/commons/math3/linear/FieldDecompositionSolver.org/apache/commons/math3/linear/FieldVector (1, 4)
	56 0 (1, 4)
	58 invokeinterface (1, 4)
	59 org/apache/commons/math3/linear/FieldVector.org/apache/commons/math3/linear/FieldMatrix (1, 4)
	61 0 (1, 4)
	63 checkcast (1, 4)
	64 [Lorg/apache/commons/math3/fraction/BigFraction; (1, 4)
	66 astore (1, 4)
	67 #6 (1, 4)
	68 aload_3 (1, 1)
	69 invokeinterface (1, 1)
	70 org/apache/commons/math3/linear/FieldMatrix.ZERO:Lorg/apache/commons/math3/fraction/BigFraction; (1, 1)
	72 0 (1, 1)
	74 checkcast (1, 1)
	75 [[Lorg/apache/commons/math3/fraction/BigFraction; (1, 1)
	77 astore (1, 1)
	78 #7 (1, 1)
	79 aload (2, 1)
	80 #7 (2, 1)
	81 arraylength (2, 1)
	82 iconst_1 (2, 1)
	83 isub (2, 1)
	84 istore (2, 1)
	85 #8 (2, 1)
	86 iload (2, 1)
	87 #8 (2, 1)
	88 ifle (2, 1)
	89 21 (2, 1)
	91 aload (2, 1)
	92 #7 (2, 1)
	93 iload (2, 1)
	94 #8 (2, 1)
	95 aload (2, 1)
	96 #7 (2, 1)
	97 iload (2, 1)
	98 #8 (2, 1)
	99 iconst_1 (2, 1)
	100 isub (2, 1)
	101 aaload (2, 1)
	102 aastore (2, 1)
	103 iinc (2, 1)
	104 #8 (2, 1)
	105 -89 (2, 1)
	106 goto (2, 1)
	107 -20 (2, 1)
	109 aload (1, 1)
	110 #7 (1, 1)
	111 iconst_0 (1, 1)
	112 iload_2 (1, 1)
	113 anewarray (1, 1)
	114 org/apache/commons/math3/fraction/BigFraction (1, 1)
	116 aastore (1, 1)
	117 aload (1, 1)
	118 #7 (1, 1)
	119 iconst_0 (1, 1)
	120 aaload (1, 1)
	121 getstatic (1, 1)
	122 org/apache/commons/math3/fraction/BigFraction.ZERO:Lorg/apache/commons/math3/fraction/BigFraction; (1, 1)
	124 invokestatic (1, 1)
	125 java/util/Arrays.fill:([Ljava/lang/Object;Ljava/lang/Object;)V (1, 1)
	127 aload (1, 1)
	128 #4 (1, 1)
	129 new (1, 1)
	130 org/apache/commons/math3/linear/Array2DRowFieldMatrix (1, 1)
	132 dup (1, 1)
	133 aload (1, 1)
	134 #7 (1, 1)
	135 iconst_0 (1, 1)
	136 invokespecial (1, 1)
	137 org/apache/commons/math3/linear/Array2DRowFieldMatrix.<init>:([[Lorg/apache/commons/math3/FieldElement;Z)V (1, 1)
	139 invokeinterface (1, 1)
	140 org/apache/commons/math3/linear/FieldDecompositionSolver.org/apache/commons/math3/linear/MatrixUtils (1, 1)
	142 0 (1, 1)
	144 astore (1, 1)
	145 #8 (1, 1)
	146 aload_0 (1, 1)
	147 aload (1, 1)
	148 #8 (1, 1)
	149 invokestatic (1, 1)
	150 org/apache/commons/math3/linear/MatrixUtils.bigFractionMatrixToRealMatrix:(Lorg/apache/commons/math3/linear/FieldMatrix;)Lorg/apache/commons/math3/linear/Array2DRowRealMatrix; (1, 1)
	152 putfield (1, 1)
	153 org/apache/commons/math3/ode/nonstiff/AdamsNordsieckTransformer.update:Lorg/apache/commons/math3/linear/Array2DRowRealMatrix; (1, 1)
	155 aload_0 (1, 1)
	156 iload_2 (1, 1)
	157 newarray (1, 1)
	158 7 (1, 1)
	159 putfield (1, 1)
	160 org/apache/commons/math3/ode/nonstiff/AdamsNordsieckTransformer.c1:[D (1, 1)
	162 iconst_0 (2, 4)
	163 istore (2, 4)
	164 #9 (2, 4)
	165 iload (2, 4)
	166 #9 (2, 4)
	167 iload_2 (2, 4)
	168 if_icmpge (2, 4)
	169 24 (2, 4)
	171 aload_0 (2, 4)
	172 getfield (2, 4)
	173 org/apache/commons/math3/ode/nonstiff/AdamsNordsieckTransformer.c1:[D (2, 4)
	175 iload (2, 4)
	176 #9 (2, 4)
	177 aload (2, 4)
	178 #6 (2, 4)
	179 iload (2, 4)
	180 #9 (2, 4)
	181 aaload (2, 4)
	182 invokevirtual (2, 4)
	183 org/apache/commons/math3/fraction/BigFraction.doubleValue:()D (2, 4)
	185 dastore (2, 4)
	186 iinc (2, 4)
	187 #9 (2, 4)
	188 -89 (2, 4)
	189 goto (2, 4)
	190 -24 (2, 4)
	192 return (0, 0)

Method: getInstance
	0 getstatic (0, 0)
	1 org/apache/commons/math3/ode/nonstiff/AdamsNordsieckTransformer.CACHE:Ljava/util/Map; (0, 0)
	3 dup (0, 0)
	4 astore_1 (0, 0)
	5 monitorenter (0, 0)
	6 getstatic (1, 4)
	7 org/apache/commons/math3/ode/nonstiff/AdamsNordsieckTransformer.CACHE:Ljava/util/Map; (1, 4)
	9 iload_0 (1, 4)
	10 invokestatic (1, 4)
	11 java/lang/Integer.valueOf:(I)Ljava/lang/Integer; (1, 4)
	13 invokeinterface (1, 4)
	14 java/util/Map.org/apache/commons/math3/ode/nonstiff/AdamsNordsieckTransformer (1, 4)
	16 0 (1, 4)
	18 checkcast (1, 4)
	19 org/apache/commons/math3/ode/nonstiff/AdamsNordsieckTransformer (1, 4)
	21 astore_2 (1, 4)
	22 aload_2 (2, 1)
	23 ifnonnull (2, 1)
	24 26 (2, 1)
	26 new (2, 4)
	27 org/apache/commons/math3/ode/nonstiff/AdamsNordsieckTransformer (2, 4)
	29 dup (2, 4)
	30 iload_0 (2, 4)
	31 invokespecial (2, 4)
	32 org/apache/commons/math3/ode/nonstiff/AdamsNordsieckTransformer.<init>:(I)V (2, 4)
	34 astore_2 (2, 4)
	35 getstatic (2, 4)
	36 org/apache/commons/math3/ode/nonstiff/AdamsNordsieckTransformer.CACHE:Ljava/util/Map; (2, 4)
	38 iload_0 (2, 4)
	39 invokestatic (2, 4)
	40 java/lang/Integer.valueOf:(I)Ljava/lang/Integer; (2, 4)
	42 aload_2 (2, 4)
	43 invokeinterface (2, 4)
	44 java/util/Map.org/apache/commons/math3/linear/QRDecomposition (2, 4)
	46 0 (2, 4)
	48 pop (2, 4)
	49 aload_2 (1, 4)
	50 aload_1 (1, 4)
	51 monitorexit (1, 4)
	52 areturn (1, 4)
	53 astore_3 (0, 0)
	54 aload_1 (0, 0)
	55 monitorexit (0, 0)
	56 aload_3 (0, 0)
	57 athrow (0, 0)

Method: getNSteps
	0 aload_0 (0, 0)
	1 getfield (0, 0)
	2 org/apache/commons/math3/ode/nonstiff/AdamsNordsieckTransformer.c1:[D (0, 0)
	4 arraylength (0, 0)
	5 ireturn (0, 0)

Method: buildP
	0 iload_1 (0, 0)
	1 iload_1 (0, 0)
	2 multianewarray (0, 0)
	3 [[Lorg/apache/commons/math3/fraction/BigFraction; (0, 0)
	5 77 (0, 0)
	6 astore_2 (0, 0)
	7 iconst_1 (1, 4)
	8 istore_3 (1, 4)
	9 iload_3 (1, 4)
	10 aload_2 (1, 4)
	11 arraylength (1, 4)
	12 if_icmpgt (1, 4)
	13 69 (1, 4)
	15 aload_2 (1, 4)
	16 iload_3 (1, 4)
	17 iconst_1 (1, 4)
	18 isub (1, 4)
	19 aaload (1, 4)
	20 astore (1, 4)
	21 #4 (1, 4)
	22 iload_3 (1, 4)
	23 ineg (1, 4)
	24 istore (1, 4)
	25 #5 (1, 4)
	26 iload (1, 4)
	27 #5 (1, 4)
	28 istore (1, 4)
	29 #6 (1, 4)
	30 iconst_1 (2, 4)
	31 istore (2, 4)
	32 #7 (2, 4)
	33 iload (2, 4)
	34 #7 (2, 4)
	35 aload (2, 4)
	36 #4 (2, 4)
	37 arraylength (2, 4)
	38 if_icmpgt (2, 4)
	39 37 (2, 4)
	41 aload (2, 4)
	42 #4 (2, 4)
	43 iload (2, 4)
	44 #7 (2, 4)
	45 iconst_1 (2, 4)
	46 isub (2, 4)
	47 new (2, 4)
	48 org/apache/commons/math3/fraction/BigFraction (2, 4)
	50 dup (2, 4)
	51 iload (2, 4)
	52 #6 (2, 4)
	53 iload (2, 4)
	54 #7 (2, 4)
	55 iconst_1 (2, 4)
	56 iadd (2, 4)
	57 imul (2, 4)
	58 invokespecial (2, 4)
	59 org/apache/commons/math3/fraction/BigFraction.<init>:(I)V (2, 4)
	61 aastore (2, 4)
	62 iload (2, 4)
	63 #6 (2, 4)
	64 iload (2, 4)
	65 #5 (2, 4)
	66 imul (2, 4)
	67 istore (2, 4)
	68 #6 (2, 4)
	69 iinc (2, 4)
	70 #7 (2, 4)
	71 -89 (2, 4)
	72 goto (2, 4)
	73 -39 (2, 4)
	75 iinc (2, 4)
	76 #3 (2, 4)
	77 -89 (2, 4)
	78 goto (2, 4)
	79 -69 (2, 4)
	81 new (1, 4)
	82 org/apache/commons/math3/linear/Array2DRowFieldMatrix (1, 4)
	84 dup (1, 4)
	85 aload_2 (1, 4)
	86 iconst_0 (1, 4)
	87 invokespecial (1, 4)
	88 org/apache/commons/math3/linear/Array2DRowFieldMatrix.<init>:([[Lorg/apache/commons/math3/FieldElement;Z)V (1, 4)
	90 areturn (1, 4)

Method: initializeHighOrderDerivatives
	0 aload_0 (0, 0)
	1 getfield (0, 0)
	2 org/apache/commons/math3/ode/nonstiff/AdamsNordsieckTransformer.c1:[D (0, 0)
	4 arraylength (0, 0)
	5 iconst_1 (0, 0)
	6 iadd (0, 0)
	7 aload_0 (0, 0)
	8 getfield (0, 0)
	9 org/apache/commons/math3/ode/nonstiff/AdamsNordsieckTransformer.c1:[D (0, 0)
	11 arraylength (0, 0)
	12 iconst_1 (0, 0)
	13 iadd (0, 0)
	14 multianewarray (0, 0)
	15 [[D (0, 0)
	17 58 (0, 0)
	18 astore (0, 0)
	19 #6 (0, 0)
	20 aload_0 (0, 0)
	21 getfield (0, 0)
	22 org/apache/commons/math3/ode/nonstiff/AdamsNordsieckTransformer.c1:[D (0, 0)
	24 arraylength (0, 0)
	25 iconst_1 (0, 0)
	26 iadd (0, 0)
	27 aload (0, 0)
	28 #4 (0, 0)
	29 iconst_0 (0, 0)
	30 aaload (0, 0)
	31 arraylength (0, 0)
	32 multianewarray (0, 0)
	33 [[D (0, 0)
	35 58 (0, 0)
	36 astore (0, 0)
	37 #7 (0, 0)
	38 aload (0, 0)
	39 #4 (0, 0)
	40 iconst_0 (0, 0)
	41 aaload (0, 0)
	42 astore (0, 0)
	43 #8 (0, 0)
	44 aload (0, 0)
	45 #5 (0, 0)
	46 iconst_0 (0, 0)
	47 aaload (0, 0)
	48 astore (0, 0)
	49 #9 (0, 0)
	50 iconst_1 (1, 4)
	51 istore (1, 4)
	52 #10 (1, 4)
	53 iload (1, 4)
	54 #10 (1, 4)
	55 aload (1, 4)
	56 #4 (1, 4)
	57 arraylength (1, 4)
	58 if_icmpge (1, 4)
	59 235 (1, 4)
	61 aload_3 (1, 4)
	62 iload (1, 4)
	63 #10 (1, 4)
	64 daload (1, 4)
	65 aload_3 (1, 4)
	66 iconst_0 (1, 4)
	67 daload (1, 4)
	68 dsub (1, 4)
	69 dstore (1, 4)
	70 #11 (1, 4)
	71 dload (1, 4)
	72 #11 (1, 4)
	73 dload_1 (1, 4)
	74 ddiv (1, 4)
	75 dstore (1, 4)
	76 #13 (1, 4)
	77 dconst_1 (1, 4)
	78 dload_1 (1, 4)
	79 ddiv (1, 4)
	80 dstore (1, 4)
	81 #15 (1, 4)
	82 aload (1, 4)
	83 #6 (1, 4)
	84 iconst_2 (1, 4)
	85 iload (1, 4)
	86 #10 (1, 4)
	87 imul (1, 4)
	88 iconst_2 (1, 4)
	89 isub (1, 4)
	90 aaload (1, 4)
	91 astore (1, 4)
	92 #17 (1, 4)
	93 iconst_2 (1, 4)
	94 iload (1, 4)
	95 #10 (1, 4)
	96 imul (1, 4)
	97 iconst_1 (1, 4)
	98 isub (1, 4)
	99 aload (1, 4)
	100 #6 (1, 4)
	101 arraylength (1, 4)
	102 if_icmpge (1, 4)
	103 15 (1, 4)
	105 aload (1, 4)
	106 #6 (1, 4)
	107 iconst_2 (1, 4)
	108 iload (1, 4)
	109 #10 (1, 4)
	110 imul (1, 4)
	111 iconst_1 (1, 4)
	112 isub (1, 4)
	113 aaload (1, 4)
	114 goto (1, 4)
	115 4 (1, 4)
	117 aconst_null (1, 4)
	118 astore (1, 4)
	119 #18 (1, 4)
	120 iconst_0 (2, 4)
	121 istore (2, 4)
	122 #19 (2, 4)
	123 iload (2, 4)
	124 #19 (2, 4)
	125 aload (2, 4)
	126 #17 (2, 4)
	127 arraylength (2, 4)
	128 if_icmpge (2, 4)
	129 44 (2, 4)
	131 dload (2, 4)
	132 #15 (2, 4)
	133 dload (2, 4)
	134 #13 (2, 4)
	135 dmul (2, 4)
	136 dstore (2, 4)
	137 #15 (2, 4)
	138 aload (2, 4)
	139 #17 (2, 4)
	140 iload (2, 4)
	141 #19 (2, 4)
	142 dload (2, 4)
	143 #11 (2, 4)
	144 dload (2, 4)
	145 #15 (2, 4)
	146 dmul (2, 4)
	147 dastore (2, 4)
	148 aload (3, 1)
	149 #18 (3, 1)
	150 ifnull (3, 1)
	151 16 (3, 1)
	153 aload (3, 1)
	154 #18 (3, 1)
	155 iload (3, 1)
	156 #19 (3, 1)
	157 iload (3, 1)
	158 #19 (3, 1)
	159 iconst_2 (3, 1)
	160 iadd (3, 1)
	161 i2d (3, 1)
	162 dload (3, 1)
	163 #15 (3, 1)
	164 dmul (3, 1)
	165 dastore (3, 1)
	166 iinc (3, 1)
	167 #19 (3, 1)
	168 -89 (3, 1)
	169 goto (3, 1)
	170 -46 (3, 1)
	172 aload (2, 4)
	173 #4 (2, 4)
	174 iload (2, 4)
	175 #10 (2, 4)
	176 aaload (2, 4)
	177 astore (2, 4)
	178 #19 (2, 4)
	179 aload (2, 4)
	180 #5 (2, 4)
	181 iload (2, 4)
	182 #10 (2, 4)
	183 aaload (2, 4)
	184 astore (2, 4)
	185 #20 (2, 4)
	186 aload (2, 4)
	187 #7 (2, 4)
	188 iconst_2 (2, 4)
	189 iload (2, 4)
	190 #10 (2, 4)
	191 imul (2, 4)
	192 iconst_2 (2, 4)
	193 isub (2, 4)
	194 aaload (2, 4)
	195 astore (2, 4)
	196 #21 (2, 4)
	197 iconst_2 (2, 4)
	198 iload (2, 4)
	199 #10 (2, 4)
	200 imul (2, 4)
	201 iconst_1 (2, 4)
	202 isub (2, 4)
	203 aload (2, 4)
	204 #7 (2, 4)
	205 arraylength (2, 4)
	206 if_icmpge (2, 4)
	207 15 (2, 4)
	209 aload (2, 4)
	210 #7 (2, 4)
	211 iconst_2 (2, 4)
	212 iload (2, 4)
	213 #10 (2, 4)
	214 imul (2, 4)
	215 iconst_1 (2, 4)
	216 isub (2, 4)
	217 aaload (2, 4)
	218 goto (2, 4)
	219 4 (2, 4)
	221 aconst_null (2, 4)
	222 astore (2, 4)
	223 #22 (2, 4)
	224 iconst_0 (3, 4)
	225 istore (3, 4)
	226 #23 (3, 4)
	227 iload (3, 4)
	228 #23 (3, 4)
	229 aload (3, 4)
	230 #19 (3, 4)
	231 arraylength (3, 4)
	232 if_icmpge (3, 4)
	233 55 (3, 4)
	235 aload (3, 4)
	236 #21 (3, 4)
	237 iload (3, 4)
	238 #23 (3, 4)
	239 aload (3, 4)
	240 #19 (3, 4)
	241 iload (3, 4)
	242 #23 (3, 4)
	243 daload (3, 4)
	244 aload (3, 4)
	245 #8 (3, 4)
	246 iload (3, 4)
	247 #23 (3, 4)
	248 daload (3, 4)
	249 dsub (3, 4)
	250 dload (3, 4)
	251 #11 (3, 4)
	252 aload (3, 4)
	253 #9 (3, 4)
	254 iload (3, 4)
	255 #23 (3, 4)
	256 daload (3, 4)
	257 dmul (3, 4)
	258 dsub (3, 4)
	259 dastore (3, 4)
	260 aload (4, 1)
	261 #22 (4, 1)
	262 ifnull (4, 1)
	263 19 (4, 1)
	265 aload (4, 1)
	266 #22 (4, 1)
	267 iload (4, 1)
	268 #23 (4, 1)
	269 aload (4, 1)
	270 #20 (4, 1)
	271 iload (4, 1)
	272 #23 (4, 1)
	273 daload (4, 1)
	274 aload (4, 1)
	275 #9 (4, 1)
	276 iload (4, 1)
	277 #23 (4, 1)
	278 daload (4, 1)
	279 dsub (4, 1)
	280 dastore (4, 1)
	281 iinc (4, 1)
	282 #23 (4, 1)
	283 -89 (4, 1)
	284 goto (4, 1)
	285 -57 (4, 1)
	287 iinc (4, 1)
	288 #10 (4, 1)
	289 -89 (4, 1)
	290 goto (4, 1)
	291 -237 (4, 1)
	293 new (3, 4)
	294 org/apache/commons/math3/linear/QRDecomposition (3, 4)
	296 dup (3, 4)
	297 new (3, 4)
	298 org/apache/commons/math3/linear/Array2DRowRealMatrix (3, 4)
	300 dup (3, 4)
	301 aload (3, 4)
	302 #6 (3, 4)
	303 iconst_0 (3, 4)
	304 invokespecial (3, 4)
	305 org/apache/commons/math3/linear/Array2DRowRealMatrix.<init>:([[DZ)V (3, 4)
	307 invokespecial (3, 4)
	308 org/apache/commons/math3/linear/QRDecomposition.<init>:(Lorg/apache/commons/math3/linear/RealMatrix;)V (3, 4)
	310 astore (3, 4)
	311 #10 (3, 4)
	312 aload (3, 4)
	313 #10 (3, 4)
	314 invokevirtual (3, 4)
	315 org/apache/commons/math3/linear/QRDecomposition.getSolver:()Lorg/apache/commons/math3/linear/DecompositionSolver; (3, 4)
	317 new (3, 4)
	318 org/apache/commons/math3/linear/Array2DRowRealMatrix (3, 4)
	320 dup (3, 4)
	321 aload (3, 4)
	322 #7 (3, 4)
	323 iconst_0 (3, 4)
	324 invokespecial (3, 4)
	325 org/apache/commons/math3/linear/Array2DRowRealMatrix.<init>:([[DZ)V (3, 4)
	327 invokeinterface (3, 4)
	328 org/apache/commons/math3/linear/DecompositionSolver.org/apache/commons/math3/linear/RealMatrix (3, 4)
	330 0 (3, 4)
	332 astore (3, 4)
	333 #11 (3, 4)
	334 new (3, 4)
	335 org/apache/commons/math3/linear/Array2DRowRealMatrix (3, 4)
	337 dup (3, 4)
	338 aload (3, 4)
	339 #11 (3, 4)
	340 invokeinterface (3, 4)
	341 org/apache/commons/math3/linear/RealMatrix.getColumnDimension:()I (3, 4)
	343 0 (3, 4)
	345 iconst_1 (3, 4)
	346 isub (3, 4)
	347 aload (3, 4)
	348 #11 (3, 4)
	349 invokeinterface (3, 4)
	350 org/apache/commons/math3/linear/RealMatrix.<init>:(II)V (3, 4)
	352 0 (3, 4)
	354 invokespecial (3, 4)
	355 org/apache/commons/math3/linear/Array2DRowRealMatrix.<init>:(II)V (3, 4)
	357 astore (3, 4)
	358 #12 (3, 4)
	359 iconst_0 (4, 4)
	360 istore (4, 4)
	361 #13 (4, 4)
	362 iload (4, 4)
	363 #13 (4, 4)
	364 aload (4, 4)
	365 #12 (4, 4)
	366 invokevirtual (4, 4)
	367 org/apache/commons/math3/linear/Array2DRowRealMatrix.getRowDimension:()I (4, 4)
	369 if_icmpge (4, 4)
	370 48 (4, 4)
	372 iconst_0 (5, 4)
	373 istore (5, 4)
	374 #14 (5, 4)
	375 iload (5, 4)
	376 #14 (5, 4)
	377 aload (5, 4)
	378 #12 (5, 4)
	379 invokevirtual (5, 4)
	380 org/apache/commons/math3/linear/Array2DRowRealMatrix.getColumnDimension:()I (5, 4)
	382 if_icmpge (5, 4)
	383 29 (5, 4)
	385 aload (5, 4)
	386 #12 (5, 4)
	387 iload (5, 4)
	388 #13 (5, 4)
	389 iload (5, 4)
	390 #14 (5, 4)
	391 aload (5, 4)
	392 #11 (5, 4)
	393 iload (5, 4)
	394 #13 (5, 4)
	395 iload (5, 4)
	396 #14 (5, 4)
	397 invokeinterface (5, 4)
	398 org/apache/commons/math3/linear/RealMatrix.setEntry:(IID)V (5, 4)
	400 0 (5, 4)
	402 invokevirtual (5, 4)
	403 org/apache/commons/math3/linear/Array2DRowRealMatrix.setEntry:(IID)V (5, 4)
	405 iinc (5, 4)
	406 #14 (5, 4)
	407 -89 (5, 4)
	408 goto (5, 4)
	409 -33 (5, 4)
	411 iinc (5, 4)
	412 #13 (5, 4)
	413 -89 (5, 4)
	414 goto (5, 4)
	415 -52 (5, 4)
	417 aload (4, 4)
	418 #12 (4, 4)
	419 areturn (4, 4)

Method: updateHighOrderDerivativesPhase1
	0 aload_0 (0, 0)
	1 getfield (0, 0)
	2 org/apache/commons/math3/ode/nonstiff/AdamsNordsieckTransformer.update:Lorg/apache/commons/math3/linear/Array2DRowRealMatrix; (0, 0)
	4 aload_1 (0, 0)
	5 invokevirtual (0, 0)
	6 org/apache/commons/math3/linear/Array2DRowRealMatrix.multiply:(Lorg/apache/commons/math3/linear/Array2DRowRealMatrix;)Lorg/apache/commons/math3/linear/Array2DRowRealMatrix; (0, 0)
	8 areturn (0, 0)

Method: updateHighOrderDerivativesPhase2
	0 aload_3 (0, 0)
	1 invokevirtual (0, 0)
	2 org/apache/commons/math3/linear/Array2DRowRealMatrix.getDataRef:()[[D (0, 0)
	4 astore (0, 0)
	5 #4 (0, 0)
	6 iconst_0 (1, 4)
	7 istore (1, 4)
	8 #5 (1, 4)
	9 iload (1, 4)
	10 #5 (1, 4)
	11 aload (1, 4)
	12 #4 (1, 4)
	13 arraylength (1, 4)
	14 if_icmpge (1, 4)
	15 62 (1, 4)
	17 aload (1, 4)
	18 #4 (1, 4)
	19 iload (1, 4)
	20 #5 (1, 4)
	21 aaload (1, 4)
	22 astore (1, 4)
	23 #6 (1, 4)
	24 aload_0 (1, 4)
	25 getfield (1, 4)
	26 org/apache/commons/math3/ode/nonstiff/AdamsNordsieckTransformer.c1:[D (1, 4)
	28 iload (1, 4)
	29 #5 (1, 4)
	30 daload (1, 4)
	31 dstore (1, 4)
	32 #7 (1, 4)
	33 iconst_0 (2, 4)
	34 istore (2, 4)
	35 #9 (2, 4)
	36 iload (2, 4)
	37 #9 (2, 4)
	38 aload (2, 4)
	39 #6 (2, 4)
	40 arraylength (2, 4)
	41 if_icmpge (2, 4)
	42 29 (2, 4)
	44 aload (2, 4)
	45 #6 (2, 4)
	46 iload (2, 4)
	47 #9 (2, 4)
	48 dup2 (2, 4)
	49 daload (2, 4)
	50 dload (2, 4)
	51 #7 (2, 4)
	52 aload_1 (2, 4)
	53 iload (2, 4)
	54 #9 (2, 4)
	55 daload (2, 4)
	56 aload_2 (2, 4)
	57 iload (2, 4)
	58 #9 (2, 4)
	59 daload (2, 4)
	60 dsub (2, 4)
	61 dmul (2, 4)
	62 dadd (2, 4)
	63 dastore (2, 4)
	64 iinc (2, 4)
	65 #9 (2, 4)
	66 -89 (2, 4)
	67 goto (2, 4)
	68 -31 (2, 4)
	70 iinc (2, 4)
	71 #5 (2, 4)
	72 -89 (2, 4)
	73 goto (2, 4)
	74 -64 (2, 4)
	76 return (0, 0)

Method: <clinit>
	0 new (0, 4)
	1 java/util/HashMap (0, 4)
	3 dup (0, 4)
	4 invokespecial (0, 4)
	5 java/util/HashMap.<init>:()V (0, 4)
	7 putstatic (0, 4)
	8 org/apache/commons/math3/ode/nonstiff/AdamsNordsieckTransformer.CACHE:Ljava/util/Map; (0, 4)
	10 return (0, 4)

