Method: <init>
	0 aload_0 (0, 0)
	1 aload_1 (0, 0)
	2 putfield (0, 0)
	3 org/apache/commons/math3/ode/nonstiff/AdamsMoultonIntegrator$Corrector.this$0:Lorg/apache/commons/math3/ode/nonstiff/AdamsMoultonIntegrator; (0, 0)
	5 aload_0 (0, 0)
	6 invokespecial (0, 0)
	7 java/lang/Object.<init>:()V (0, 0)
	9 aload_0 (0, 0)
	10 aload_2 (0, 0)
	11 putfield (0, 0)
	12 org/apache/commons/math3/ode/nonstiff/AdamsMoultonIntegrator$Corrector.previous:[D (0, 0)
	14 aload_0 (0, 0)
	15 aload_3 (0, 0)
	16 putfield (0, 0)
	17 org/apache/commons/math3/ode/nonstiff/AdamsMoultonIntegrator$Corrector.scaled:[D (0, 0)
	19 aload_0 (0, 0)
	20 aload (0, 0)
	21 #4 (0, 0)
	22 putfield (0, 0)
	23 org/apache/commons/math3/ode/nonstiff/AdamsMoultonIntegrator$Corrector.after:[D (0, 0)
	25 aload_0 (1, 4)
	26 aload (1, 4)
	27 #4 (1, 4)
	28 invokevirtual (1, 4)
	29 [D.clone:()Ljava/lang/Object; (1, 4)
	31 checkcast (1, 4)
	32 [D (1, 4)
	34 putfield (1, 4)
	35 org/apache/commons/math3/ode/nonstiff/AdamsMoultonIntegrator$Corrector.before:[D (1, 4)
	37 return (0, 0)

Method: start
	0 aload_0 (0, 0)
	1 getfield (0, 0)
	2 org/apache/commons/math3/ode/nonstiff/AdamsMoultonIntegrator$Corrector.after:[D (0, 0)
	4 dconst_0 (0, 0)
	5 invokestatic (0, 0)
	6 java/util/Arrays.fill:([DD)V (0, 0)
	8 return (0, 0)

Method: visit
	0 iload_1 (1, 1)
	1 iconst_1 (1, 1)
	2 iand (1, 1)
	3 ifne (1, 1)
	4 16 (1, 1)
	6 aload_0 (1, 1)
	7 getfield (1, 1)
	8 org/apache/commons/math3/ode/nonstiff/AdamsMoultonIntegrator$Corrector.after:[D (1, 1)
	10 iload_2 (1, 1)
	11 dup2 (1, 1)
	12 daload (1, 1)
	13 dload_3 (1, 1)
	14 dsub (1, 1)
	15 dastore (1, 1)
	16 goto (1, 1)
	17 13 (1, 1)
	19 aload_0 (1, 2)
	20 getfield (1, 2)
	21 org/apache/commons/math3/ode/nonstiff/AdamsMoultonIntegrator$Corrector.after:[D (1, 2)
	23 iload_2 (1, 2)
	24 dup2 (1, 2)
	25 daload (1, 2)
	26 dload_3 (1, 2)
	27 dadd (1, 2)
	28 dastore (1, 2)
	29 return (0, 0)

Method: end
	0 dconst_0 (0, 0)
	1 dstore_1 (0, 0)
	2 iconst_0 (1, 4)
	3 istore_3 (1, 4)
	4 iload_3 (1, 4)
	5 aload_0 (1, 4)
	6 getfield (1, 4)
	7 org/apache/commons/math3/ode/nonstiff/AdamsMoultonIntegrator$Corrector.after:[D (1, 4)
	9 arraylength (1, 4)
	10 if_icmpge (1, 4)
	11 146 (1, 4)
	13 aload_0 (1, 4)
	14 getfield (1, 4)
	15 org/apache/commons/math3/ode/nonstiff/AdamsMoultonIntegrator$Corrector.after:[D (1, 4)
	17 iload_3 (1, 4)
	18 dup2 (1, 4)
	19 daload (1, 4)
	20 aload_0 (1, 4)
	21 getfield (1, 4)
	22 org/apache/commons/math3/ode/nonstiff/AdamsMoultonIntegrator$Corrector.previous:[D (1, 4)
	24 iload_3 (1, 4)
	25 daload (1, 4)
	26 aload_0 (1, 4)
	27 getfield (1, 4)
	28 org/apache/commons/math3/ode/nonstiff/AdamsMoultonIntegrator$Corrector.scaled:[D (1, 4)
	30 iload_3 (1, 4)
	31 daload (1, 4)
	32 dadd (1, 4)
	33 dadd (1, 4)
	34 dastore (1, 4)
	35 iload_3 (2, 1)
	36 aload_0 (2, 1)
	37 getfield (2, 1)
	38 org/apache/commons/math3/ode/nonstiff/AdamsMoultonIntegrator$Corrector.this$0:Lorg/apache/commons/math3/ode/nonstiff/AdamsMoultonIntegrator; (2, 1)
	40 getfield (2, 1)
	41 org/apache/commons/math3/ode/nonstiff/AdamsMoultonIntegrator.mainSetDimension:I (2, 1)
	43 if_icmpge (2, 1)
	44 107 (2, 1)
	46 aload_0 (2, 1)
	47 getfield (2, 1)
	48 org/apache/commons/math3/ode/nonstiff/AdamsMoultonIntegrator$Corrector.previous:[D (2, 1)
	50 iload_3 (2, 1)
	51 daload (2, 1)
	52 invokestatic (2, 1)
	53 org/apache/commons/math3/util/FastMath.abs:(D)D (2, 1)
	55 aload_0 (2, 1)
	56 getfield (2, 1)
	57 org/apache/commons/math3/ode/nonstiff/AdamsMoultonIntegrator$Corrector.after:[D (2, 1)
	59 iload_3 (2, 1)
	60 daload (2, 1)
	61 invokestatic (2, 1)
	62 org/apache/commons/math3/util/FastMath.abs:(D)D (2, 1)
	64 invokestatic (2, 1)
	65 org/apache/commons/math3/util/FastMath.max:(DD)D (2, 1)
	67 dstore (2, 1)
	68 #4 (2, 1)
	69 aload_0 (2, 1)
	70 getfield (2, 1)
	71 org/apache/commons/math3/ode/nonstiff/AdamsMoultonIntegrator$Corrector.this$0:Lorg/apache/commons/math3/ode/nonstiff/AdamsMoultonIntegrator; (2, 1)
	73 getfield (2, 1)
	74 org/apache/commons/math3/ode/nonstiff/AdamsMoultonIntegrator.vecAbsoluteTolerance:[D (2, 1)
	76 ifnonnull (2, 1)
	77 24 (2, 1)
	79 aload_0 (2, 1)
	80 getfield (2, 1)
	81 org/apache/commons/math3/ode/nonstiff/AdamsMoultonIntegrator$Corrector.this$0:Lorg/apache/commons/math3/ode/nonstiff/AdamsMoultonIntegrator; (2, 1)
	83 getfield (2, 1)
	84 org/apache/commons/math3/ode/nonstiff/AdamsMoultonIntegrator.scalAbsoluteTolerance:D (2, 1)
	86 aload_0 (2, 1)
	87 getfield (2, 1)
	88 org/apache/commons/math3/ode/nonstiff/AdamsMoultonIntegrator$Corrector.this$0:Lorg/apache/commons/math3/ode/nonstiff/AdamsMoultonIntegrator; (2, 1)
	90 getfield (2, 1)
	91 org/apache/commons/math3/ode/nonstiff/AdamsMoultonIntegrator.scalRelativeTolerance:D (2, 1)
	93 dload (2, 1)
	94 #4 (2, 1)
	95 dmul (2, 1)
	96 dadd (2, 1)
	97 goto (2, 1)
	98 25 (2, 1)
	100 aload_0 (2, 1)
	101 getfield (2, 1)
	102 org/apache/commons/math3/ode/nonstiff/AdamsMoultonIntegrator$Corrector.this$0:Lorg/apache/commons/math3/ode/nonstiff/AdamsMoultonIntegrator; (2, 1)
	104 getfield (2, 1)
	105 org/apache/commons/math3/ode/nonstiff/AdamsMoultonIntegrator.vecAbsoluteTolerance:[D (2, 1)
	107 iload_3 (2, 1)
	108 daload (2, 1)
	109 aload_0 (2, 1)
	110 getfield (2, 1)
	111 org/apache/commons/math3/ode/nonstiff/AdamsMoultonIntegrator$Corrector.this$0:Lorg/apache/commons/math3/ode/nonstiff/AdamsMoultonIntegrator; (2, 1)
	113 getfield (2, 1)
	114 org/apache/commons/math3/ode/nonstiff/AdamsMoultonIntegrator.vecRelativeTolerance:[D (2, 1)
	116 iload_3 (2, 1)
	117 daload (2, 1)
	118 dload (2, 1)
	119 #4 (2, 1)
	120 dmul (2, 1)
	121 dadd (2, 1)
	122 dstore (2, 1)
	123 #6 (2, 1)
	124 aload_0 (2, 4)
	125 getfield (2, 4)
	126 org/apache/commons/math3/ode/nonstiff/AdamsMoultonIntegrator$Corrector.after:[D (2, 4)
	128 iload_3 (2, 4)
	129 daload (2, 4)
	130 aload_0 (2, 4)
	131 getfield (2, 4)
	132 org/apache/commons/math3/ode/nonstiff/AdamsMoultonIntegrator$Corrector.before:[D (2, 4)
	134 iload_3 (2, 4)
	135 daload (2, 4)
	136 dsub (2, 4)
	137 dload (2, 4)
	138 #6 (2, 4)
	139 ddiv (2, 4)
	140 dstore (2, 4)
	141 #8 (2, 4)
	142 dload_1 (2, 4)
	143 dload (2, 4)
	144 #8 (2, 4)
	145 dload (2, 4)
	146 #8 (2, 4)
	147 dmul (2, 4)
	148 dadd (2, 4)
	149 dstore_1 (2, 4)
	150 iinc (2, 4)
	151 #3 (2, 4)
	152 -89 (2, 4)
	153 goto (2, 4)
	154 -149 (2, 4)
	156 dload_1 (1, 4)
	157 aload_0 (1, 4)
	158 getfield (1, 4)
	159 org/apache/commons/math3/ode/nonstiff/AdamsMoultonIntegrator$Corrector.this$0:Lorg/apache/commons/math3/ode/nonstiff/AdamsMoultonIntegrator; (1, 4)
	161 getfield (1, 4)
	162 org/apache/commons/math3/ode/nonstiff/AdamsMoultonIntegrator.mainSetDimension:I (1, 4)
	164 i2d (1, 4)
	165 ddiv (1, 4)
	166 invokestatic (1, 4)
	167 org/apache/commons/math3/util/FastMath.sqrt:(D)D (1, 4)
	169 dreturn (1, 4)

