Method: <init>
	0 aload_0 (0, 0)
	1 aload_1 (0, 0)
	2 ldc (0, 0)
	3 Adams-Bashforth (0, 0)
	4 iload_2 (0, 0)
	5 iload_2 (0, 0)
	6 dload_3 (0, 0)
	7 dload (0, 0)
	8 #5 (0, 0)
	9 aload (0, 0)
	10 #7 (0, 0)
	11 aload (0, 0)
	12 #8 (0, 0)
	13 invokespecial (0, 0)
	14 org/apache/commons/math3/ode/nonstiff/AdamsFieldIntegrator.<init>:(Lorg/apache/commons/math3/Field;Ljava/lang/String;IIDD[D[D)V (0, 0)
	16 return (0, 0)

Method: errorEstimation
	0 aload_0 (0, 0)
	1 invokevirtual (0, 0)
	2 org/apache/commons/math3/ode/nonstiff/AdamsBashforthFieldIntegrator.getField:()Lorg/apache/commons/math3/Field; (0, 0)
	4 invokeinterface (0, 0)
	5 org/apache/commons/math3/Field.org/apache/commons/math3/RealFieldElement (0, 0)
	7 0 (0, 0)
	9 checkcast (0, 0)
	10 org/apache/commons/math3/RealFieldElement (0, 0)
	12 astore (0, 0)
	13 #5 (0, 0)
	14 iconst_0 (1, 4)
	15 istore (1, 4)
	16 #6 (1, 4)
	17 iload (1, 4)
	18 #6 (1, 4)
	19 aload_0 (1, 4)
	20 getfield (1, 4)
	21 org/apache/commons/math3/ode/nonstiff/AdamsBashforthFieldIntegrator.mainSetDimension:I (1, 4)
	23 if_icmpge (1, 4)
	24 261 (1, 4)
	26 aload_2 (1, 4)
	27 iload (1, 4)
	28 #6 (1, 4)
	29 aaload (1, 4)
	30 invokeinterface (1, 4)
	31 org/apache/commons/math3/RealFieldElement.vecAbsoluteTolerance:[D (1, 4)
	33 0 (1, 4)
	35 checkcast (1, 4)
	36 org/apache/commons/math3/RealFieldElement (1, 4)
	38 astore (1, 4)
	39 #7 (1, 4)
	40 aload_0 (1, 4)
	41 getfield (1, 4)
	42 org/apache/commons/math3/ode/nonstiff/AdamsBashforthFieldIntegrator.vecAbsoluteTolerance:[D (1, 4)
	44 ifnonnull (1, 4)
	45 32 (1, 4)
	47 aload (1, 4)
	48 #7 (1, 4)
	49 aload_0 (1, 4)
	50 getfield (1, 4)
	51 org/apache/commons/math3/ode/nonstiff/AdamsBashforthFieldIntegrator.scalRelativeTolerance:D (1, 4)
	53 invokeinterface (1, 4)
	54 org/apache/commons/math3/RealFieldElement.scalAbsoluteTolerance:D (1, 4)
	56 0 (1, 4)
	58 checkcast (1, 4)
	59 org/apache/commons/math3/RealFieldElement (1, 4)
	61 aload_0 (1, 4)
	62 getfield (1, 4)
	63 org/apache/commons/math3/ode/nonstiff/AdamsBashforthFieldIntegrator.scalAbsoluteTolerance:D (1, 4)
	65 invokeinterface (1, 4)
	66 org/apache/commons/math3/RealFieldElement.vecRelativeTolerance:[D (1, 4)
	68 0 (1, 4)
	70 checkcast (1, 4)
	71 org/apache/commons/math3/RealFieldElement (1, 4)
	73 goto (1, 4)
	74 35 (1, 4)
	76 aload (1, 4)
	77 #7 (1, 4)
	78 aload_0 (1, 4)
	79 getfield (1, 4)
	80 org/apache/commons/math3/ode/nonstiff/AdamsBashforthFieldIntegrator.vecRelativeTolerance:[D (1, 4)
	82 iload (1, 4)
	83 #6 (1, 4)
	84 daload (1, 4)
	85 invokeinterface (1, 4)
	86 org/apache/commons/math3/RealFieldElement.scalAbsoluteTolerance:D (1, 4)
	88 0 (1, 4)
	90 checkcast (1, 4)
	91 org/apache/commons/math3/RealFieldElement (1, 4)
	93 aload_0 (1, 4)
	94 getfield (1, 4)
	95 org/apache/commons/math3/ode/nonstiff/AdamsBashforthFieldIntegrator.vecAbsoluteTolerance:[D (1, 4)
	97 iload (1, 4)
	98 #6 (1, 4)
	99 daload (1, 4)
	100 invokeinterface (1, 4)
	101 org/apache/commons/math3/RealFieldElement.vecRelativeTolerance:[D (1, 4)
	103 0 (1, 4)
	105 checkcast (1, 4)
	106 org/apache/commons/math3/RealFieldElement (1, 4)
	108 astore (1, 4)
	109 #8 (1, 4)
	110 aload_0 (1, 4)
	111 invokevirtual (1, 4)
	112 org/apache/commons/math3/ode/nonstiff/AdamsBashforthFieldIntegrator.getField:()Lorg/apache/commons/math3/Field; (1, 4)
	114 invokeinterface (1, 4)
	115 org/apache/commons/math3/Field.org/apache/commons/math3/RealFieldElement (1, 4)
	117 0 (1, 4)
	119 checkcast (1, 4)
	120 org/apache/commons/math3/RealFieldElement (1, 4)
	122 astore (1, 4)
	123 #9 (1, 4)
	124 aload (1, 4)
	125 #4 (1, 4)
	126 invokeinterface (1, 4)
	127 org/apache/commons/math3/linear/FieldMatrix.getEntry:(II)Lorg/apache/commons/math3/FieldElement; (1, 4)
	129 0 (1, 4)
	131 iconst_2 (1, 4)
	132 irem (1, 4)
	133 ifne (1, 4)
	134 7 (1, 4)
	136 iconst_m1 (1, 4)
	137 goto (1, 4)
	138 4 (1, 4)
	140 iconst_1 (1, 4)
	141 istore (1, 4)
	142 #10 (1, 4)
	143 aload (2, 4)
	144 #4 (2, 4)
	145 invokeinterface (2, 4)
	146 org/apache/commons/math3/linear/FieldMatrix.getEntry:(II)Lorg/apache/commons/math3/FieldElement; (2, 4)
	148 0 (2, 4)
	150 iconst_1 (2, 4)
	151 isub (2, 4)
	152 istore (2, 4)
	153 #11 (2, 4)
	154 iload (2, 4)
	155 #11 (2, 4)
	156 iflt (2, 4)
	157 47 (2, 4)
	159 aload (2, 4)
	160 #9 (2, 4)
	161 aload (2, 4)
	162 #4 (2, 4)
	163 iload (2, 4)
	164 #11 (2, 4)
	165 iload (2, 4)
	166 #6 (2, 4)
	167 invokeinterface (2, 4)
	168 org/apache/commons/math3/linear/FieldMatrix.multiply:(I)Ljava/lang/Object; (2, 4)
	170 0 (2, 4)
	172 checkcast (2, 4)
	173 org/apache/commons/math3/RealFieldElement (2, 4)
	175 iload (2, 4)
	176 #10 (2, 4)
	177 invokeinterface (2, 4)
	178 org/apache/commons/math3/RealFieldElement.add:(Ljava/lang/Object;)Ljava/lang/Object; (2, 4)
	180 0 (2, 4)
	182 invokeinterface (2, 4)
	183 org/apache/commons/math3/RealFieldElement.subtract:(Ljava/lang/Object;)Ljava/lang/Object; (2, 4)
	185 0 (2, 4)
	187 checkcast (2, 4)
	188 org/apache/commons/math3/RealFieldElement (2, 4)
	190 astore (2, 4)
	191 #9 (2, 4)
	192 iload (2, 4)
	193 #10 (2, 4)
	194 ineg (2, 4)
	195 istore (2, 4)
	196 #10 (2, 4)
	197 iinc (2, 4)
	198 #11 (2, 4)
	199 -89 (2, 4)
	200 goto (2, 4)
	201 -46 (2, 4)
	203 aload (1, 4)
	204 #9 (1, 4)
	205 aload_3 (1, 4)
	206 iload (1, 4)
	207 #6 (1, 4)
	208 aaload (1, 4)
	209 invokeinterface (1, 4)
	210 org/apache/commons/math3/RealFieldElement.divide:(Ljava/lang/Object;)Ljava/lang/Object; (1, 4)
	212 0 (1, 4)
	214 checkcast (1, 4)
	215 org/apache/commons/math3/RealFieldElement (1, 4)
	217 astore (1, 4)
	218 #9 (1, 4)
	219 aload_2 (1, 4)
	220 iload (1, 4)
	221 #6 (1, 4)
	222 aaload (1, 4)
	223 aload_1 (1, 4)
	224 iload (1, 4)
	225 #6 (1, 4)
	226 aaload (1, 4)
	227 invokeinterface (1, 4)
	228 org/apache/commons/math3/RealFieldElement.divide:(Ljava/lang/Object;)Ljava/lang/Object; (1, 4)
	230 0 (1, 4)
	232 checkcast (1, 4)
	233 org/apache/commons/math3/RealFieldElement (1, 4)
	235 aload (1, 4)
	236 #9 (1, 4)
	237 invokeinterface (1, 4)
	238 org/apache/commons/math3/RealFieldElement.subtract:(Ljava/lang/Object;)Ljava/lang/Object; (1, 4)
	240 0 (1, 4)
	242 checkcast (1, 4)
	243 org/apache/commons/math3/RealFieldElement (1, 4)
	245 aload (1, 4)
	246 #8 (1, 4)
	247 invokeinterface (1, 4)
	248 org/apache/commons/math3/RealFieldElement.multiply:(Ljava/lang/Object;)Ljava/lang/Object; (1, 4)
	250 0 (1, 4)
	252 checkcast (1, 4)
	253 org/apache/commons/math3/RealFieldElement (1, 4)
	255 astore (1, 4)
	256 #11 (1, 4)
	257 aload (1, 4)
	258 #5 (1, 4)
	259 aload (1, 4)
	260 #11 (1, 4)
	261 aload (1, 4)
	262 #11 (1, 4)
	263 invokeinterface (1, 4)
	264 org/apache/commons/math3/RealFieldElement.divide:(D)Ljava/lang/Object; (1, 4)
	266 0 (1, 4)
	268 invokeinterface (1, 4)
	269 org/apache/commons/math3/RealFieldElement.subtract:(Ljava/lang/Object;)Ljava/lang/Object; (1, 4)
	271 0 (1, 4)
	273 checkcast (1, 4)
	274 org/apache/commons/math3/RealFieldElement (1, 4)
	276 astore (1, 4)
	277 #5 (1, 4)
	278 iinc (1, 4)
	279 #6 (1, 4)
	280 -89 (1, 4)
	281 goto (1, 4)
	282 -264 (1, 4)
	284 aload (0, 0)
	285 #5 (0, 0)
	286 aload_0 (0, 0)
	287 getfield (0, 0)
	288 org/apache/commons/math3/ode/nonstiff/AdamsBashforthFieldIntegrator.mainSetDimension:I (0, 0)
	290 i2d (0, 0)
	291 invokeinterface (0, 0)
	292 org/apache/commons/math3/RealFieldElement.sqrt:()Ljava/lang/Object; (0, 0)
	294 0 (0, 0)
	296 checkcast (0, 0)
	297 org/apache/commons/math3/RealFieldElement (0, 0)
	299 invokeinterface (0, 0)
	300 org/apache/commons/math3/RealFieldElement.sanityChecks:(Lorg/apache/commons/math3/ode/FieldODEState;Lorg/apache/commons/math3/RealFieldElement;)V (0, 0)
	302 0 (0, 0)
	304 checkcast (0, 0)
	305 org/apache/commons/math3/RealFieldElement (0, 0)
	307 areturn (0, 0)

Method: integrate
	0 aload_0 (0, 0)
	1 aload_2 (0, 0)
	2 aload_3 (0, 0)
	3 invokevirtual (0, 0)
	4 org/apache/commons/math3/ode/nonstiff/AdamsBashforthFieldIntegrator.sanityChecks:(Lorg/apache/commons/math3/ode/FieldODEState;Lorg/apache/commons/math3/RealFieldElement;)V (0, 0)
	6 aload_2 (0, 0)
	7 invokevirtual (0, 0)
	8 org/apache/commons/math3/ode/FieldODEState.getTime:()Lorg/apache/commons/math3/RealFieldElement; (0, 0)
	10 astore (0, 0)
	11 #4 (0, 0)
	12 aload_1 (0, 0)
	13 invokevirtual (0, 0)
	14 org/apache/commons/math3/ode/FieldExpandableODE.getMapper:()Lorg/apache/commons/math3/ode/FieldEquationsMapper; (0, 0)
	16 aload_2 (0, 0)
	17 invokevirtual (0, 0)
	18 org/apache/commons/math3/ode/FieldEquationsMapper.mapState:(Lorg/apache/commons/math3/ode/FieldODEState;)[Lorg/apache/commons/math3/RealFieldElement; (0, 0)
	20 astore (0, 0)
	21 #5 (0, 0)
	22 aload_0 (0, 0)
	23 aload_0 (0, 0)
	24 aload_1 (0, 0)
	25 aload (0, 0)
	26 #4 (0, 0)
	27 aload (0, 0)
	28 #5 (0, 0)
	29 aload_3 (0, 0)
	30 invokevirtual (0, 0)
	31 org/apache/commons/math3/ode/nonstiff/AdamsBashforthFieldIntegrator.initIntegration:(Lorg/apache/commons/math3/ode/FieldExpandableODE;Lorg/apache/commons/math3/RealFieldElement;[Lorg/apache/commons/math3/RealFieldElement;Lorg/apache/commons/math3/RealFieldElement;)Lorg/apache/commons/math3/ode/FieldODEStateAndDerivative; (0, 0)
	33 invokevirtual (0, 0)
	34 org/apache/commons/math3/ode/nonstiff/AdamsBashforthFieldIntegrator.setStepStart:(Lorg/apache/commons/math3/ode/FieldODEStateAndDerivative;)V (0, 0)
	36 aload_3 (0, 4)
	37 aload_2 (0, 4)
	38 invokevirtual (0, 4)
	39 org/apache/commons/math3/ode/FieldODEState.getTime:()Lorg/apache/commons/math3/RealFieldElement; (0, 4)
	41 invokeinterface (0, 4)
	42 org/apache/commons/math3/RealFieldElement.divide:(Ljava/lang/Object;)Ljava/lang/Object; (0, 4)
	44 0 (0, 4)
	46 checkcast (0, 4)
	47 org/apache/commons/math3/RealFieldElement (0, 4)
	49 invokeinterface (0, 4)
	50 org/apache/commons/math3/RealFieldElement.getStepStart:()Lorg/apache/commons/math3/ode/FieldODEStateAndDerivative; (0, 4)
	52 0 (0, 4)
	54 dconst_0 (0, 4)
	55 dcmpl (0, 4)
	56 ifle (0, 4)
	57 7 (0, 4)
	59 iconst_1 (0, 4)
	60 goto (0, 4)
	61 4 (0, 4)
	63 iconst_0 (0, 4)
	64 istore (0, 4)
	65 #6 (0, 4)
	66 aload_0 (0, 4)
	67 aload_1 (0, 4)
	68 aload_0 (0, 4)
	69 invokevirtual (0, 4)
	70 org/apache/commons/math3/ode/nonstiff/AdamsBashforthFieldIntegrator.getStepStart:()Lorg/apache/commons/math3/ode/FieldODEStateAndDerivative; (0, 4)
	72 aload_3 (0, 4)
	73 invokevirtual (0, 4)
	74 org/apache/commons/math3/ode/nonstiff/AdamsBashforthFieldIntegrator.start:(Lorg/apache/commons/math3/ode/FieldExpandableODE;Lorg/apache/commons/math3/ode/FieldODEState;Lorg/apache/commons/math3/RealFieldElement;)V (0, 4)
	76 aload_0 (0, 4)
	77 invokevirtual (0, 4)
	78 org/apache/commons/math3/ode/nonstiff/AdamsBashforthFieldIntegrator.getStepStart:()Lorg/apache/commons/math3/ode/FieldODEStateAndDerivative; (0, 4)
	80 astore (0, 4)
	81 #7 (0, 4)
	82 aload (0, 4)
	83 #7 (0, 4)
	84 aload (0, 4)
	85 #7 (0, 4)
	86 invokevirtual (0, 4)
	87 org/apache/commons/math3/ode/FieldODEStateAndDerivative.getTime:()Lorg/apache/commons/math3/RealFieldElement; (0, 4)
	89 aload_0 (0, 4)
	90 invokevirtual (0, 4)
	91 org/apache/commons/math3/ode/nonstiff/AdamsBashforthFieldIntegrator.getStepSize:()Lorg/apache/commons/math3/RealFieldElement; (0, 4)
	93 invokeinterface (0, 4)
	94 org/apache/commons/math3/RealFieldElement.subtract:(Ljava/lang/Object;)Ljava/lang/Object; (0, 4)
	96 0 (0, 4)
	98 checkcast (0, 4)
	99 org/apache/commons/math3/RealFieldElement (0, 4)
	101 aload_0 (0, 4)
	102 invokevirtual (0, 4)
	103 org/apache/commons/math3/ode/nonstiff/AdamsBashforthFieldIntegrator.getStepSize:()Lorg/apache/commons/math3/RealFieldElement; (0, 4)
	105 aload_0 (0, 4)
	106 getfield (0, 4)
	107 org/apache/commons/math3/ode/nonstiff/AdamsBashforthFieldIntegrator.scaled:[Lorg/apache/commons/math3/RealFieldElement; (0, 4)
	109 aload_0 (0, 4)
	110 getfield (0, 4)
	111 org/apache/commons/math3/ode/nonstiff/AdamsBashforthFieldIntegrator.nordsieck:Lorg/apache/commons/math3/linear/Array2DRowFieldMatrix; (0, 4)
	113 invokestatic (0, 4)
	114 org/apache/commons/math3/ode/nonstiff/AdamsFieldStepInterpolator.taylor:(Lorg/apache/commons/math3/ode/FieldODEStateAndDerivative;Lorg/apache/commons/math3/RealFieldElement;Lorg/apache/commons/math3/RealFieldElement;[Lorg/apache/commons/math3/RealFieldElement;Lorg/apache/commons/math3/linear/Array2DRowFieldMatrix;)Lorg/apache/commons/math3/ode/FieldODEStateAndDerivative; (0, 4)
	116 astore (0, 4)
	117 #8 (0, 4)
	118 aload_0 (0, 4)
	119 iconst_0 (0, 4)
	120 invokevirtual (0, 4)
	121 org/apache/commons/math3/ode/nonstiff/AdamsBashforthFieldIntegrator.setIsLastStep:(Z)V (0, 4)
	123 aconst_null (0, 4)
	124 astore (0, 4)
	125 #9 (0, 4)
	126 aload_0 (0, 4)
	127 invokevirtual (0, 4)
	128 org/apache/commons/math3/ode/nonstiff/AdamsBashforthFieldIntegrator.getField:()Lorg/apache/commons/math3/Field; (0, 4)
	130 aload (0, 4)
	131 #5 (0, 4)
	132 arraylength (0, 4)
	133 invokestatic (0, 4)
	134 org/apache/commons/math3/util/MathArrays.buildArray:(Lorg/apache/commons/math3/Field;I)[Ljava/lang/Object; (0, 4)
	136 checkcast (0, 4)
	137 [Lorg/apache/commons/math3/RealFieldElement; (0, 4)
	139 astore (0, 4)
	140 #10 (0, 4)
	141 aconst_null (0, 4)
	142 astore (0, 4)
	143 #11 (0, 4)
	144 aload_0 (0, 4)
	145 invokevirtual (0, 4)
	146 org/apache/commons/math3/ode/nonstiff/AdamsBashforthFieldIntegrator.getField:()Lorg/apache/commons/math3/Field; (0, 4)
	148 invokeinterface (0, 4)
	149 org/apache/commons/math3/Field.org/apache/commons/math3/RealFieldElement (0, 4)
	151 0 (0, 4)
	153 checkcast (0, 4)
	154 org/apache/commons/math3/RealFieldElement (0, 4)
	156 ldc2_w (0, 4)
	157 10.0 (0, 4)
	159 invokeinterface (0, 4)
	160 org/apache/commons/math3/RealFieldElement.vecRelativeTolerance:[D (0, 4)
	162 0 (0, 4)
	164 checkcast (0, 4)
	165 org/apache/commons/math3/RealFieldElement (0, 4)
	167 astore (0, 4)
	168 #12 (0, 4)
	169 aload (2, 3)
	170 #12 (2, 3)
	171 dconst_1 (2, 3)
	172 invokeinterface (2, 3)
	173 org/apache/commons/math3/RealFieldElement.getState:()[Lorg/apache/commons/math3/RealFieldElement; (2, 3)
	175 0 (2, 3)
	177 checkcast (2, 3)
	178 org/apache/commons/math3/RealFieldElement (2, 3)
	180 invokeinterface (2, 3)
	181 org/apache/commons/math3/RealFieldElement.getStepStart:()Lorg/apache/commons/math3/ode/FieldODEStateAndDerivative; (2, 3)
	183 0 (2, 3)
	185 dconst_0 (2, 3)
	186 dcmpl (2, 3)
	187 iflt (2, 3)
	188 195 (2, 3)
	190 aload (2, 3)
	191 #8 (2, 3)
	192 invokevirtual (2, 3)
	193 org/apache/commons/math3/ode/FieldODEStateAndDerivative.getState:()[Lorg/apache/commons/math3/RealFieldElement; (2, 3)
	195 astore (2, 3)
	196 #9 (2, 3)
	197 aload_0 (2, 3)
	198 aload (2, 3)
	199 #8 (2, 3)
	200 invokevirtual (2, 3)
	201 org/apache/commons/math3/ode/FieldODEStateAndDerivative.getTime:()Lorg/apache/commons/math3/RealFieldElement; (2, 3)
	203 aload (2, 3)
	204 #9 (2, 3)
	205 invokevirtual (2, 3)
	206 org/apache/commons/math3/ode/nonstiff/AdamsBashforthFieldIntegrator.computeDerivatives:(Lorg/apache/commons/math3/RealFieldElement;[Lorg/apache/commons/math3/RealFieldElement;)[Lorg/apache/commons/math3/RealFieldElement; (2, 3)
	208 astore (2, 3)
	209 #13 (2, 3)
	210 iconst_0 (3, 4)
	211 istore (3, 4)
	212 #14 (3, 4)
	213 iload (3, 4)
	214 #14 (3, 4)
	215 aload (3, 4)
	216 #10 (3, 4)
	217 arraylength (3, 4)
	218 if_icmpge (3, 4)
	219 31 (3, 4)
	221 aload (3, 4)
	222 #10 (3, 4)
	223 iload (3, 4)
	224 #14 (3, 4)
	225 aload_0 (3, 4)
	226 invokevirtual (3, 4)
	227 org/apache/commons/math3/ode/nonstiff/AdamsBashforthFieldIntegrator.getStepSize:()Lorg/apache/commons/math3/RealFieldElement; (3, 4)
	229 aload (3, 4)
	230 #13 (3, 4)
	231 iload (3, 4)
	232 #14 (3, 4)
	233 aaload (3, 4)
	234 invokeinterface (3, 4)
	235 org/apache/commons/math3/RealFieldElement.divide:(D)Ljava/lang/Object; (3, 4)
	237 0 (3, 4)
	239 checkcast (3, 4)
	240 org/apache/commons/math3/RealFieldElement (3, 4)
	242 aastore (3, 4)
	243 iinc (3, 4)
	244 #14 (3, 4)
	245 -89 (3, 4)
	246 goto (3, 4)
	247 -33 (3, 4)
	249 aload_0 (2, 3)
	250 aload_0 (2, 3)
	251 getfield (2, 3)
	252 org/apache/commons/math3/ode/nonstiff/AdamsBashforthFieldIntegrator.nordsieck:Lorg/apache/commons/math3/linear/Array2DRowFieldMatrix; (2, 3)
	254 invokevirtual (2, 3)
	255 org/apache/commons/math3/ode/nonstiff/AdamsBashforthFieldIntegrator.updateHighOrderDerivativesPhase1:(Lorg/apache/commons/math3/linear/Array2DRowFieldMatrix;)Lorg/apache/commons/math3/linear/Array2DRowFieldMatrix; (2, 3)
	257 astore (2, 3)
	258 #11 (2, 3)
	259 aload_0 (2, 3)
	260 aload_0 (2, 3)
	261 getfield (2, 3)
	262 org/apache/commons/math3/ode/nonstiff/AdamsBashforthFieldIntegrator.scaled:[Lorg/apache/commons/math3/RealFieldElement; (2, 3)
	264 aload (2, 3)
	265 #10 (2, 3)
	266 aload (2, 3)
	267 #11 (2, 3)
	268 invokevirtual (2, 3)
	269 org/apache/commons/math3/ode/nonstiff/AdamsBashforthFieldIntegrator.updateHighOrderDerivativesPhase2:([Lorg/apache/commons/math3/RealFieldElement;[Lorg/apache/commons/math3/RealFieldElement;Lorg/apache/commons/math3/linear/Array2DRowFieldMatrix;)V (2, 3)
	271 aload_0 (2, 3)
	272 aload (2, 3)
	273 #5 (2, 3)
	274 aload (2, 3)
	275 #9 (2, 3)
	276 aload (2, 3)
	277 #10 (2, 3)
	278 aload (2, 3)
	279 #11 (2, 3)
	280 invokespecial (2, 3)
	281 org/apache/commons/math3/ode/nonstiff/AdamsBashforthFieldIntegrator.errorEstimation:([Lorg/apache/commons/math3/RealFieldElement;[Lorg/apache/commons/math3/RealFieldElement;[Lorg/apache/commons/math3/RealFieldElement;Lorg/apache/commons/math3/linear/FieldMatrix;)Lorg/apache/commons/math3/RealFieldElement; (2, 3)
	283 astore (2, 3)
	284 #12 (2, 3)
	285 aload (3, 1)
	286 #12 (3, 1)
	287 dconst_1 (3, 1)
	288 invokeinterface (3, 1)
	289 org/apache/commons/math3/RealFieldElement.getState:()[Lorg/apache/commons/math3/RealFieldElement; (3, 1)
	291 0 (3, 1)
	293 checkcast (3, 1)
	294 org/apache/commons/math3/RealFieldElement (3, 1)
	296 invokeinterface (3, 1)
	297 org/apache/commons/math3/RealFieldElement.getStepStart:()Lorg/apache/commons/math3/ode/FieldODEStateAndDerivative; (3, 1)
	299 0 (3, 1)
	301 dconst_0 (3, 1)
	302 dcmpl (3, 1)
	303 iflt (3, 1)
	304 76 (3, 1)
	306 aload_0 (3, 1)
	307 aload (3, 1)
	308 #12 (3, 1)
	309 invokevirtual (3, 1)
	310 org/apache/commons/math3/ode/nonstiff/AdamsBashforthFieldIntegrator.computeStepGrowShrinkFactor:(Lorg/apache/commons/math3/RealFieldElement;)Lorg/apache/commons/math3/RealFieldElement; (3, 1)
	312 astore (3, 1)
	313 #14 (3, 1)
	314 aload_0 (3, 4)
	315 aload_0 (3, 4)
	316 aload_0 (3, 4)
	317 invokevirtual (3, 4)
	318 org/apache/commons/math3/ode/nonstiff/AdamsBashforthFieldIntegrator.getStepSize:()Lorg/apache/commons/math3/RealFieldElement; (3, 4)
	320 aload (3, 4)
	321 #14 (3, 4)
	322 invokeinterface (3, 4)
	323 org/apache/commons/math3/RealFieldElement.divide:(D)Ljava/lang/Object; (3, 4)
	325 0 (3, 4)
	327 checkcast (3, 4)
	328 org/apache/commons/math3/RealFieldElement (3, 4)
	330 iload (3, 4)
	331 #6 (3, 4)
	332 iconst_0 (3, 4)
	333 invokevirtual (3, 4)
	334 org/apache/commons/math3/ode/nonstiff/AdamsBashforthFieldIntegrator.filterStep:(Lorg/apache/commons/math3/RealFieldElement;ZZ)Lorg/apache/commons/math3/RealFieldElement; (3, 4)
	336 invokevirtual (3, 4)
	337 org/apache/commons/math3/ode/nonstiff/AdamsBashforthFieldIntegrator.rescale:(Lorg/apache/commons/math3/RealFieldElement;)V (3, 4)
	339 aload_0 (3, 4)
	340 invokevirtual (3, 4)
	341 org/apache/commons/math3/ode/nonstiff/AdamsBashforthFieldIntegrator.getStepStart:()Lorg/apache/commons/math3/ode/FieldODEStateAndDerivative; (3, 4)
	343 aload_0 (3, 4)
	344 invokevirtual (3, 4)
	345 org/apache/commons/math3/ode/nonstiff/AdamsBashforthFieldIntegrator.getStepStart:()Lorg/apache/commons/math3/ode/FieldODEStateAndDerivative; (3, 4)
	347 invokevirtual (3, 4)
	348 org/apache/commons/math3/ode/FieldODEStateAndDerivative.getTime:()Lorg/apache/commons/math3/RealFieldElement; (3, 4)
	350 aload_0 (3, 4)
	351 invokevirtual (3, 4)
	352 org/apache/commons/math3/ode/nonstiff/AdamsBashforthFieldIntegrator.getStepSize:()Lorg/apache/commons/math3/RealFieldElement; (3, 4)
	354 invokeinterface (3, 4)
	355 org/apache/commons/math3/RealFieldElement.subtract:(Ljava/lang/Object;)Ljava/lang/Object; (3, 4)
	357 0 (3, 4)
	359 checkcast (3, 4)
	360 org/apache/commons/math3/RealFieldElement (3, 4)
	362 aload_0 (3, 4)
	363 invokevirtual (3, 4)
	364 org/apache/commons/math3/ode/nonstiff/AdamsBashforthFieldIntegrator.getStepSize:()Lorg/apache/commons/math3/RealFieldElement; (3, 4)
	366 aload_0 (3, 4)
	367 getfield (3, 4)
	368 org/apache/commons/math3/ode/nonstiff/AdamsBashforthFieldIntegrator.scaled:[Lorg/apache/commons/math3/RealFieldElement; (3, 4)
	370 aload_0 (3, 4)
	371 getfield (3, 4)
	372 org/apache/commons/math3/ode/nonstiff/AdamsBashforthFieldIntegrator.nordsieck:Lorg/apache/commons/math3/linear/Array2DRowFieldMatrix; (3, 4)
	374 invokestatic (3, 4)
	375 org/apache/commons/math3/ode/nonstiff/AdamsFieldStepInterpolator.taylor:(Lorg/apache/commons/math3/ode/FieldODEStateAndDerivative;Lorg/apache/commons/math3/RealFieldElement;Lorg/apache/commons/math3/RealFieldElement;[Lorg/apache/commons/math3/RealFieldElement;Lorg/apache/commons/math3/linear/Array2DRowFieldMatrix;)Lorg/apache/commons/math3/ode/FieldODEStateAndDerivative; (3, 4)
	377 astore (3, 4)
	378 #8 (3, 4)
	379 goto (0, 4)
	380 -210 (0, 4)
	382 aload_0 (0, 4)
	383 aload_0 (0, 4)
	384 new (0, 4)
	385 org/apache/commons/math3/ode/nonstiff/AdamsFieldStepInterpolator (0, 4)
	387 dup (0, 4)
	388 aload_0 (0, 4)
	389 invokevirtual (0, 4)
	390 org/apache/commons/math3/ode/nonstiff/AdamsBashforthFieldIntegrator.getStepSize:()Lorg/apache/commons/math3/RealFieldElement; (0, 4)
	392 aload (0, 4)
	393 #8 (0, 4)
	394 aload (0, 4)
	395 #10 (0, 4)
	396 aload (0, 4)
	397 #11 (0, 4)
	398 iload (0, 4)
	399 #6 (0, 4)
	400 aload_0 (0, 4)
	401 invokevirtual (1, 4)
	402 org/apache/commons/math3/ode/nonstiff/AdamsBashforthFieldIntegrator.getStepStart:()Lorg/apache/commons/math3/ode/FieldODEStateAndDerivative; (1, 4)
	404 aload (1, 4)
	405 #8 (1, 4)
	406 aload_1 (1, 4)
	407 invokevirtual (1, 4)
	408 org/apache/commons/math3/ode/FieldExpandableODE.getMapper:()Lorg/apache/commons/math3/ode/FieldEquationsMapper; (1, 4)
	410 invokespecial (1, 4)
	411 org/apache/commons/math3/ode/nonstiff/AdamsFieldStepInterpolator.<init>:(Lorg/apache/commons/math3/RealFieldElement;Lorg/apache/commons/math3/ode/FieldODEStateAndDerivative;[Lorg/apache/commons/math3/RealFieldElement;Lorg/apache/commons/math3/linear/Array2DRowFieldMatrix;ZLorg/apache/commons/math3/ode/FieldODEStateAndDerivative;Lorg/apache/commons/math3/ode/FieldODEStateAndDerivative;Lorg/apache/commons/math3/ode/FieldEquationsMapper;)V (1, 4)
	413 aload_3 (1, 4)
	414 invokevirtual (1, 4)
	415 org/apache/commons/math3/ode/nonstiff/AdamsBashforthFieldIntegrator.acceptStep:(Lorg/apache/commons/math3/ode/sampling/AbstractFieldStepInterpolator;Lorg/apache/commons/math3/RealFieldElement;)Lorg/apache/commons/math3/ode/FieldODEStateAndDerivative; (1, 4)
	417 invokevirtual (1, 4)
	418 org/apache/commons/math3/ode/nonstiff/AdamsBashforthFieldIntegrator.setStepStart:(Lorg/apache/commons/math3/ode/FieldODEStateAndDerivative;)V (1, 4)
	420 aload_0 (1, 4)
	421 aload (1, 4)
	422 #10 (1, 4)
	423 putfield (1, 4)
	424 org/apache/commons/math3/ode/nonstiff/AdamsBashforthFieldIntegrator.scaled:[Lorg/apache/commons/math3/RealFieldElement; (1, 4)
	426 aload_0 (1, 4)
	427 aload (1, 4)
	428 #11 (1, 4)
	429 putfield (1, 4)
	430 org/apache/commons/math3/ode/nonstiff/AdamsBashforthFieldIntegrator.nordsieck:Lorg/apache/commons/math3/linear/Array2DRowFieldMatrix; (1, 4)
	432 aload_0 (2, 1)
	433 invokevirtual (2, 1)
	434 org/apache/commons/math3/ode/nonstiff/AdamsBashforthFieldIntegrator.isLastStep:()Z (2, 1)
	436 ifne (2, 1)
	437 299 (2, 1)
	439 aload (2, 1)
	440 #9 (2, 1)
	441 iconst_0 (2, 1)
	442 aload (2, 1)
	443 #5 (2, 1)
	444 iconst_0 (2, 1)
	445 aload (2, 1)
	446 #5 (2, 1)
	447 arraylength (2, 1)
	448 invokestatic (2, 1)
	449 java/lang/System.arraycopy:(Ljava/lang/Object;ILjava/lang/Object;II)V (2, 1)
	451 aload_0 (3, 1)
	452 invokevirtual (3, 1)
	453 org/apache/commons/math3/ode/nonstiff/AdamsBashforthFieldIntegrator.resetOccurred:()Z (3, 1)
	455 ifeq (3, 1)
	456 13 (3, 1)
	458 aload_0 (3, 1)
	459 aload_1 (3, 1)
	460 aload_0 (3, 1)
	461 invokevirtual (3, 1)
	462 org/apache/commons/math3/ode/nonstiff/AdamsBashforthFieldIntegrator.getStepStart:()Lorg/apache/commons/math3/ode/FieldODEStateAndDerivative; (3, 1)
	464 aload_3 (3, 1)
	465 invokevirtual (3, 1)
	466 org/apache/commons/math3/ode/nonstiff/AdamsBashforthFieldIntegrator.start:(Lorg/apache/commons/math3/ode/FieldExpandableODE;Lorg/apache/commons/math3/ode/FieldODEState;Lorg/apache/commons/math3/RealFieldElement;)V (3, 1)
	468 aload_0 (2, 4)
	469 aload (2, 4)
	470 #12 (2, 4)
	471 invokevirtual (2, 4)
	472 org/apache/commons/math3/ode/nonstiff/AdamsBashforthFieldIntegrator.computeStepGrowShrinkFactor:(Lorg/apache/commons/math3/RealFieldElement;)Lorg/apache/commons/math3/RealFieldElement; (2, 4)
	474 astore (2, 4)
	475 #13 (2, 4)
	476 aload_0 (2, 4)
	477 invokevirtual (2, 4)
	478 org/apache/commons/math3/ode/nonstiff/AdamsBashforthFieldIntegrator.getStepSize:()Lorg/apache/commons/math3/RealFieldElement; (2, 4)
	480 aload (2, 4)
	481 #13 (2, 4)
	482 invokeinterface (2, 4)
	483 org/apache/commons/math3/RealFieldElement.divide:(D)Ljava/lang/Object; (2, 4)
	485 0 (2, 4)
	487 checkcast (2, 4)
	488 org/apache/commons/math3/RealFieldElement (2, 4)
	490 astore (2, 4)
	491 #14 (2, 4)
	492 aload_0 (2, 4)
	493 invokevirtual (2, 4)
	494 org/apache/commons/math3/ode/nonstiff/AdamsBashforthFieldIntegrator.getStepStart:()Lorg/apache/commons/math3/ode/FieldODEStateAndDerivative; (2, 4)
	496 invokevirtual (2, 4)
	497 org/apache/commons/math3/ode/FieldODEStateAndDerivative.getTime:()Lorg/apache/commons/math3/RealFieldElement; (2, 4)
	499 aload (2, 4)
	500 #14 (2, 4)
	501 invokeinterface (2, 4)
	502 org/apache/commons/math3/RealFieldElement.subtract:(Ljava/lang/Object;)Ljava/lang/Object; (2, 4)
	504 0 (2, 4)
	506 checkcast (2, 4)
	507 org/apache/commons/math3/RealFieldElement (2, 4)
	509 astore (2, 4)
	510 #15 (2, 4)
	511 iload (2, 4)
	512 #6 (2, 4)
	513 ifeq (2, 4)
	514 32 (2, 4)
	516 aload (2, 4)
	517 #15 (2, 4)
	518 aload_3 (2, 4)
	519 invokeinterface (2, 4)
	520 org/apache/commons/math3/RealFieldElement.divide:(Ljava/lang/Object;)Ljava/lang/Object; (2, 4)
	522 0 (2, 4)
	524 checkcast (2, 4)
	525 org/apache/commons/math3/RealFieldElement (2, 4)
	527 invokeinterface (2, 4)
	528 org/apache/commons/math3/RealFieldElement.getStepStart:()Lorg/apache/commons/math3/ode/FieldODEStateAndDerivative; (2, 4)
	530 0 (2, 4)
	532 dconst_0 (2, 4)
	533 dcmpl (2, 4)
	534 iflt (2, 4)
	535 7 (2, 4)
	537 iconst_1 (2, 4)
	538 goto (2, 4)
	539 33 (2, 4)
	541 iconst_0 (2, 4)
	542 goto (2, 4)
	543 29 (2, 4)
	545 aload (2, 4)
	546 #15 (2, 4)
	547 aload_3 (2, 4)
	548 invokeinterface (2, 4)
	549 org/apache/commons/math3/RealFieldElement.divide:(Ljava/lang/Object;)Ljava/lang/Object; (2, 4)
	551 0 (2, 4)
	553 checkcast (2, 4)
	554 org/apache/commons/math3/RealFieldElement (2, 4)
	556 invokeinterface (2, 4)
	557 org/apache/commons/math3/RealFieldElement.getStepStart:()Lorg/apache/commons/math3/ode/FieldODEStateAndDerivative; (2, 4)
	559 0 (2, 4)
	561 dconst_0 (2, 4)
	562 dcmpg (2, 4)
	563 ifgt (2, 4)
	564 7 (2, 4)
	566 iconst_1 (2, 4)
	567 goto (2, 4)
	568 4 (2, 4)
	570 iconst_0 (2, 4)
	571 istore (2, 4)
	572 #16 (2, 4)
	573 aload_0 (2, 4)
	574 aload (2, 4)
	575 #14 (2, 4)
	576 iload (2, 4)
	577 #6 (2, 4)
	578 iload (2, 4)
	579 #16 (2, 4)
	580 invokevirtual (2, 4)
	581 org/apache/commons/math3/ode/nonstiff/AdamsBashforthFieldIntegrator.filterStep:(Lorg/apache/commons/math3/RealFieldElement;ZZ)Lorg/apache/commons/math3/RealFieldElement; (2, 4)
	583 astore (2, 4)
	584 #17 (2, 4)
	585 aload_0 (2, 4)
	586 invokevirtual (2, 4)
	587 org/apache/commons/math3/ode/nonstiff/AdamsBashforthFieldIntegrator.getStepStart:()Lorg/apache/commons/math3/ode/FieldODEStateAndDerivative; (2, 4)
	589 invokevirtual (2, 4)
	590 org/apache/commons/math3/ode/FieldODEStateAndDerivative.getTime:()Lorg/apache/commons/math3/RealFieldElement; (2, 4)
	592 aload (2, 4)
	593 #17 (2, 4)
	594 invokeinterface (2, 4)
	595 org/apache/commons/math3/RealFieldElement.subtract:(Ljava/lang/Object;)Ljava/lang/Object; (2, 4)
	597 0 (2, 4)
	599 checkcast (2, 4)
	600 org/apache/commons/math3/RealFieldElement (2, 4)
	602 astore (2, 4)
	603 #18 (2, 4)
	604 iload (2, 4)
	605 #6 (2, 4)
	606 ifeq (2, 4)
	607 32 (2, 4)
	609 aload (2, 4)
	610 #18 (2, 4)
	611 aload_3 (2, 4)
	612 invokeinterface (2, 4)
	613 org/apache/commons/math3/RealFieldElement.divide:(Ljava/lang/Object;)Ljava/lang/Object; (2, 4)
	615 0 (2, 4)
	617 checkcast (2, 4)
	618 org/apache/commons/math3/RealFieldElement (2, 4)
	620 invokeinterface (2, 4)
	621 org/apache/commons/math3/RealFieldElement.getStepStart:()Lorg/apache/commons/math3/ode/FieldODEStateAndDerivative; (2, 4)
	623 0 (2, 4)
	625 dconst_0 (2, 4)
	626 dcmpl (2, 4)
	627 iflt (2, 4)
	628 7 (2, 4)
	630 iconst_1 (2, 4)
	631 goto (2, 4)
	632 33 (2, 4)
	634 iconst_0 (2, 4)
	635 goto (2, 4)
	636 29 (2, 4)
	638 aload (2, 4)
	639 #18 (2, 4)
	640 aload_3 (2, 4)
	641 invokeinterface (2, 4)
	642 org/apache/commons/math3/RealFieldElement.divide:(Ljava/lang/Object;)Ljava/lang/Object; (2, 4)
	644 0 (2, 4)
	646 checkcast (2, 4)
	647 org/apache/commons/math3/RealFieldElement (2, 4)
	649 invokeinterface (2, 4)
	650 org/apache/commons/math3/RealFieldElement.getStepStart:()Lorg/apache/commons/math3/ode/FieldODEStateAndDerivative; (2, 4)
	652 0 (2, 4)
	654 dconst_0 (2, 4)
	655 dcmpg (2, 4)
	656 ifgt (2, 4)
	657 7 (2, 4)
	659 iconst_1 (2, 4)
	660 goto (2, 4)
	661 4 (2, 4)
	663 iconst_0 (2, 4)
	664 istore (2, 4)
	665 #19 (2, 4)
	666 iload (3, 1)
	667 #19 (3, 1)
	668 ifeq (3, 1)
	669 21 (3, 1)
	671 aload_3 (3, 1)
	672 aload_0 (3, 1)
	673 invokevirtual (3, 1)
	674 org/apache/commons/math3/ode/nonstiff/AdamsBashforthFieldIntegrator.getStepStart:()Lorg/apache/commons/math3/ode/FieldODEStateAndDerivative; (3, 1)
	676 invokevirtual (3, 1)
	677 org/apache/commons/math3/ode/FieldODEStateAndDerivative.getTime:()Lorg/apache/commons/math3/RealFieldElement; (3, 1)
	679 invokeinterface (3, 1)
	680 org/apache/commons/math3/RealFieldElement.divide:(Ljava/lang/Object;)Ljava/lang/Object; (3, 1)
	682 0 (3, 1)
	684 checkcast (3, 1)
	685 org/apache/commons/math3/RealFieldElement (3, 1)
	687 astore (3, 1)
	688 #17 (3, 1)
	689 aload_0 (2, 4)
	690 aload (2, 4)
	691 #17 (2, 4)
	692 invokevirtual (2, 4)
	693 org/apache/commons/math3/ode/nonstiff/AdamsBashforthFieldIntegrator.rescale:(Lorg/apache/commons/math3/RealFieldElement;)V (2, 4)
	695 aload_0 (2, 4)
	696 invokevirtual (2, 4)
	697 org/apache/commons/math3/ode/nonstiff/AdamsBashforthFieldIntegrator.getStepStart:()Lorg/apache/commons/math3/ode/FieldODEStateAndDerivative; (2, 4)
	699 aload_0 (2, 4)
	700 invokevirtual (2, 4)
	701 org/apache/commons/math3/ode/nonstiff/AdamsBashforthFieldIntegrator.getStepStart:()Lorg/apache/commons/math3/ode/FieldODEStateAndDerivative; (2, 4)
	703 invokevirtual (2, 4)
	704 org/apache/commons/math3/ode/FieldODEStateAndDerivative.getTime:()Lorg/apache/commons/math3/RealFieldElement; (2, 4)
	706 aload_0 (2, 4)
	707 invokevirtual (2, 4)
	708 org/apache/commons/math3/ode/nonstiff/AdamsBashforthFieldIntegrator.getStepSize:()Lorg/apache/commons/math3/RealFieldElement; (2, 4)
	710 invokeinterface (2, 4)
	711 org/apache/commons/math3/RealFieldElement.subtract:(Ljava/lang/Object;)Ljava/lang/Object; (2, 4)
	713 0 (2, 4)
	715 checkcast (2, 4)
	716 org/apache/commons/math3/RealFieldElement (2, 4)
	718 aload_0 (2, 4)
	719 invokevirtual (2, 4)
	720 org/apache/commons/math3/ode/nonstiff/AdamsBashforthFieldIntegrator.getStepSize:()Lorg/apache/commons/math3/RealFieldElement; (2, 4)
	722 aload_0 (2, 4)
	723 getfield (2, 4)
	724 org/apache/commons/math3/ode/nonstiff/AdamsBashforthFieldIntegrator.scaled:[Lorg/apache/commons/math3/RealFieldElement; (2, 4)
	726 aload_0 (2, 4)
	727 getfield (2, 4)
	728 org/apache/commons/math3/ode/nonstiff/AdamsBashforthFieldIntegrator.nordsieck:Lorg/apache/commons/math3/linear/Array2DRowFieldMatrix; (2, 4)
	730 invokestatic (2, 4)
	731 org/apache/commons/math3/ode/nonstiff/AdamsFieldStepInterpolator.taylor:(Lorg/apache/commons/math3/ode/FieldODEStateAndDerivative;Lorg/apache/commons/math3/RealFieldElement;Lorg/apache/commons/math3/RealFieldElement;[Lorg/apache/commons/math3/RealFieldElement;Lorg/apache/commons/math3/linear/Array2DRowFieldMatrix;)Lorg/apache/commons/math3/ode/FieldODEStateAndDerivative; (2, 4)
	733 astore (2, 4)
	734 #8 (2, 4)
	735 aload_0 (0, 3)
	736 invokevirtual (0, 3)
	737 org/apache/commons/math3/ode/nonstiff/AdamsBashforthFieldIntegrator.isLastStep:()Z (0, 3)
	739 ifeq (0, 3)
	740 -616 (0, 3)
	742 aload_0 (0, 3)
	743 invokevirtual (0, 3)
	744 org/apache/commons/math3/ode/nonstiff/AdamsBashforthFieldIntegrator.getStepStart:()Lorg/apache/commons/math3/ode/FieldODEStateAndDerivative; (0, 3)
	746 astore (0, 3)
	747 #9 (0, 3)
	748 aload_0 (0, 3)
	749 aconst_null (0, 3)
	750 invokevirtual (0, 3)
	751 org/apache/commons/math3/ode/nonstiff/AdamsBashforthFieldIntegrator.setStepStart:(Lorg/apache/commons/math3/ode/FieldODEStateAndDerivative;)V (0, 3)
	753 aload_0 (0, 3)
	754 aconst_null (0, 3)
	755 invokevirtual (0, 3)
	756 org/apache/commons/math3/ode/nonstiff/AdamsBashforthFieldIntegrator.setStepSize:(Lorg/apache/commons/math3/RealFieldElement;)V (0, 3)
	758 aload (0, 3)
	759 #9 (0, 3)
	760 areturn (0, 3)

