Method: <init>
	0 aload_0 (0, 0)
	1 aload_1 (0, 0)
	2 aload_2 (0, 0)
	3 invokespecial (0, 0)
	4 org/apache/commons/math3/ode/AbstractFieldIntegrator.<init>:(Lorg/apache/commons/math3/Field;Ljava/lang/String;)V (0, 0)
	6 aload_0 (0, 0)
	7 dload_3 (0, 0)
	8 dload (0, 0)
	9 #5 (0, 0)
	10 aload (0, 0)
	11 #7 (0, 0)
	12 aload (0, 0)
	13 #8 (0, 0)
	14 invokevirtual (0, 0)
	15 org/apache/commons/math3/ode/nonstiff/AdaptiveStepsizeFieldIntegrator.setStepSizeControl:(DD[D[D)V (0, 0)
	17 aload_0 (0, 0)
	18 invokevirtual (0, 0)
	19 org/apache/commons/math3/ode/nonstiff/AdaptiveStepsizeFieldIntegrator.resetInternalState:()V (0, 0)
	21 return (0, 0)

Method: setStepSizeControl
	0 aload_0 (0, 0)
	1 aload_0 (0, 0)
	2 invokevirtual (0, 0)
	3 org/apache/commons/math3/ode/nonstiff/AdaptiveStepsizeFieldIntegrator.getField:()Lorg/apache/commons/math3/Field; (0, 0)
	5 invokeinterface (0, 0)
	6 org/apache/commons/math3/Field.org/apache/commons/math3/RealFieldElement (0, 0)
	8 0 (0, 0)
	10 checkcast (0, 0)
	11 org/apache/commons/math3/RealFieldElement (0, 0)
	13 dload_1 (0, 0)
	14 invokestatic (0, 0)
	15 org/apache/commons/math3/util/FastMath.abs:(D)D (0, 0)
	17 invokeinterface (0, 0)
	18 org/apache/commons/math3/RealFieldElement.minStep:Lorg/apache/commons/math3/RealFieldElement; (0, 0)
	20 0 (0, 0)
	22 checkcast (0, 0)
	23 org/apache/commons/math3/RealFieldElement (0, 0)
	25 putfield (0, 0)
	26 org/apache/commons/math3/ode/nonstiff/AdaptiveStepsizeFieldIntegrator.minStep:Lorg/apache/commons/math3/RealFieldElement; (0, 0)
	28 aload_0 (0, 0)
	29 aload_0 (0, 0)
	30 invokevirtual (0, 0)
	31 org/apache/commons/math3/ode/nonstiff/AdaptiveStepsizeFieldIntegrator.getField:()Lorg/apache/commons/math3/Field; (0, 0)
	33 invokeinterface (0, 0)
	34 org/apache/commons/math3/Field.org/apache/commons/math3/RealFieldElement (0, 0)
	36 0 (0, 0)
	38 checkcast (0, 0)
	39 org/apache/commons/math3/RealFieldElement (0, 0)
	41 dload_3 (0, 0)
	42 invokestatic (0, 0)
	43 org/apache/commons/math3/util/FastMath.abs:(D)D (0, 0)
	45 invokeinterface (0, 0)
	46 org/apache/commons/math3/RealFieldElement.minStep:Lorg/apache/commons/math3/RealFieldElement; (0, 0)
	48 0 (0, 0)
	50 checkcast (0, 0)
	51 org/apache/commons/math3/RealFieldElement (0, 0)
	53 putfield (0, 0)
	54 org/apache/commons/math3/ode/nonstiff/AdaptiveStepsizeFieldIntegrator.maxStep:Lorg/apache/commons/math3/RealFieldElement; (0, 0)
	56 aload_0 (0, 0)
	57 aload_0 (0, 0)
	58 invokevirtual (0, 0)
	59 org/apache/commons/math3/ode/nonstiff/AdaptiveStepsizeFieldIntegrator.getField:()Lorg/apache/commons/math3/Field; (0, 0)
	61 invokeinterface (0, 0)
	62 org/apache/commons/math3/Field.negate:()Ljava/lang/Object; (0, 0)
	64 0 (0, 0)
	66 checkcast (0, 0)
	67 org/apache/commons/math3/RealFieldElement (0, 0)
	69 invokeinterface (0, 0)
	70 org/apache/commons/math3/RealFieldElement.initialStep:Lorg/apache/commons/math3/RealFieldElement; (0, 0)
	72 0 (0, 0)
	74 checkcast (0, 0)
	75 org/apache/commons/math3/RealFieldElement (0, 0)
	77 putfield (0, 0)
	78 org/apache/commons/math3/ode/nonstiff/AdaptiveStepsizeFieldIntegrator.initialStep:Lorg/apache/commons/math3/RealFieldElement; (0, 0)
	80 aload_0 (0, 0)
	81 dconst_0 (0, 0)
	82 putfield (0, 0)
	83 org/apache/commons/math3/ode/nonstiff/AdaptiveStepsizeFieldIntegrator.scalAbsoluteTolerance:D (0, 0)
	85 aload_0 (0, 0)
	86 dconst_0 (0, 0)
	87 putfield (0, 0)
	88 org/apache/commons/math3/ode/nonstiff/AdaptiveStepsizeFieldIntegrator.scalRelativeTolerance:D (0, 0)
	90 aload_0 (0, 0)
	91 aload (0, 0)
	92 #5 (0, 0)
	93 invokevirtual (0, 0)
	94 [D.clone:()Ljava/lang/Object; (0, 0)
	96 checkcast (0, 0)
	97 [D (0, 0)
	99 putfield (0, 0)
	100 org/apache/commons/math3/ode/nonstiff/AdaptiveStepsizeFieldIntegrator.vecAbsoluteTolerance:[D (0, 0)
	102 aload_0 (0, 0)
	103 aload (0, 0)
	104 #6 (0, 0)
	105 invokevirtual (0, 0)
	106 [D.clone:()Ljava/lang/Object; (0, 0)
	108 checkcast (0, 0)
	109 [D (0, 0)
	111 putfield (0, 0)
	112 org/apache/commons/math3/ode/nonstiff/AdaptiveStepsizeFieldIntegrator.vecRelativeTolerance:[D (0, 0)
	114 return (0, 0)

Method: setInitialStepSize
	0 aload_1 (0, 1)
	1 aload_0 (0, 1)
	2 getfield (0, 1)
	3 org/apache/commons/math3/ode/nonstiff/AdaptiveStepsizeFieldIntegrator.minStep:Lorg/apache/commons/math3/RealFieldElement; (0, 1)
	5 invokeinterface (0, 1)
	6 org/apache/commons/math3/RealFieldElement.getReal:()D (0, 1)
	8 0 (0, 1)
	10 checkcast (0, 1)
	11 org/apache/commons/math3/RealFieldElement (0, 1)
	13 invokeinterface (0, 1)
	14 org/apache/commons/math3/RealFieldElement.sanityChecks:(Lorg/apache/commons/math3/ode/FieldODEState;Lorg/apache/commons/math3/RealFieldElement;)V (0, 1)
	16 0 (0, 1)
	18 dconst_0 (0, 1)
	19 dcmpg (0, 1)
	20 iflt (0, 1)
	21 26 (0, 1)
	23 aload_1 (0, 1)
	24 aload_0 (0, 1)
	25 getfield (0, 1)
	26 org/apache/commons/math3/ode/nonstiff/AdaptiveStepsizeFieldIntegrator.maxStep:Lorg/apache/commons/math3/RealFieldElement; (0, 1)
	28 invokeinterface (0, 1)
	29 org/apache/commons/math3/RealFieldElement.getReal:()D (0, 1)
	31 0 (0, 1)
	33 checkcast (0, 1)
	34 org/apache/commons/math3/RealFieldElement (0, 1)
	36 invokeinterface (0, 1)
	37 org/apache/commons/math3/RealFieldElement.sanityChecks:(Lorg/apache/commons/math3/ode/FieldODEState;Lorg/apache/commons/math3/RealFieldElement;)V (0, 1)
	39 0 (0, 1)
	41 dconst_0 (0, 1)
	42 dcmpl (0, 1)
	43 ifle (0, 1)
	44 30 (0, 1)
	46 aload_0 (0, 1)
	47 aload_0 (0, 1)
	48 invokevirtual (0, 1)
	49 org/apache/commons/math3/ode/nonstiff/AdaptiveStepsizeFieldIntegrator.getField:()Lorg/apache/commons/math3/Field; (0, 1)
	51 invokeinterface (0, 1)
	52 org/apache/commons/math3/Field.negate:()Ljava/lang/Object; (0, 1)
	54 0 (0, 1)
	56 checkcast (0, 1)
	57 org/apache/commons/math3/RealFieldElement (0, 1)
	59 invokeinterface (0, 1)
	60 org/apache/commons/math3/RealFieldElement.initialStep:Lorg/apache/commons/math3/RealFieldElement; (0, 1)
	62 0 (0, 1)
	64 checkcast (0, 1)
	65 org/apache/commons/math3/RealFieldElement (0, 1)
	67 putfield (0, 1)
	68 org/apache/commons/math3/ode/nonstiff/AdaptiveStepsizeFieldIntegrator.initialStep:Lorg/apache/commons/math3/RealFieldElement; (0, 1)
	70 goto (0, 1)
	71 8 (0, 1)
	73 aload_0 (1, 2)
	74 aload_1 (1, 2)
	75 putfield (1, 2)
	76 org/apache/commons/math3/ode/nonstiff/AdaptiveStepsizeFieldIntegrator.initialStep:Lorg/apache/commons/math3/RealFieldElement; (1, 2)
	78 return (0, 1)

Method: sanityChecks
	0 aload_0 (0, 0)
	1 aload_1 (0, 0)
	2 aload_2 (0, 0)
	3 invokespecial (0, 0)
	4 org/apache/commons/math3/ode/AbstractFieldIntegrator.sanityChecks:(Lorg/apache/commons/math3/ode/FieldODEState;Lorg/apache/commons/math3/RealFieldElement;)V (0, 0)
	6 aload_0 (0, 0)
	7 aload_1 (0, 0)
	8 invokevirtual (0, 0)
	9 org/apache/commons/math3/ode/FieldODEState.getStateDimension:()I (0, 0)
	11 putfield (0, 0)
	12 org/apache/commons/math3/ode/nonstiff/AdaptiveStepsizeFieldIntegrator.mainSetDimension:I (0, 0)
	14 aload_0 (1, 1)
	15 getfield (1, 1)
	16 org/apache/commons/math3/ode/nonstiff/AdaptiveStepsizeFieldIntegrator.vecAbsoluteTolerance:[D (1, 1)
	18 ifnull (1, 1)
	19 32 (1, 1)
	21 aload_0 (1, 1)
	22 getfield (1, 1)
	23 org/apache/commons/math3/ode/nonstiff/AdaptiveStepsizeFieldIntegrator.vecAbsoluteTolerance:[D (1, 1)
	25 arraylength (1, 1)
	26 aload_0 (1, 1)
	27 getfield (1, 1)
	28 org/apache/commons/math3/ode/nonstiff/AdaptiveStepsizeFieldIntegrator.mainSetDimension:I (1, 1)
	30 if_icmpeq (1, 1)
	31 20 (1, 1)
	33 new (1, 1)
	34 org/apache/commons/math3/exception/DimensionMismatchException (1, 1)
	36 dup (1, 1)
	37 aload_0 (1, 1)
	38 getfield (1, 1)
	39 org/apache/commons/math3/ode/nonstiff/AdaptiveStepsizeFieldIntegrator.mainSetDimension:I (1, 1)
	41 aload_0 (1, 1)
	42 getfield (1, 1)
	43 org/apache/commons/math3/ode/nonstiff/AdaptiveStepsizeFieldIntegrator.vecAbsoluteTolerance:[D (1, 1)
	45 arraylength (1, 1)
	46 invokespecial (1, 1)
	47 org/apache/commons/math3/exception/DimensionMismatchException.<init>:(II)V (1, 1)
	49 athrow (1, 1)
	50 aload_0 (1, 1)
	51 getfield (1, 1)
	52 org/apache/commons/math3/ode/nonstiff/AdaptiveStepsizeFieldIntegrator.vecRelativeTolerance:[D (1, 1)
	54 ifnull (1, 1)
	55 32 (1, 1)
	57 aload_0 (1, 1)
	58 getfield (1, 1)
	59 org/apache/commons/math3/ode/nonstiff/AdaptiveStepsizeFieldIntegrator.vecRelativeTolerance:[D (1, 1)
	61 arraylength (1, 1)
	62 aload_0 (1, 1)
	63 getfield (1, 1)
	64 org/apache/commons/math3/ode/nonstiff/AdaptiveStepsizeFieldIntegrator.mainSetDimension:I (1, 1)
	66 if_icmpeq (1, 1)
	67 20 (1, 1)
	69 new (1, 1)
	70 org/apache/commons/math3/exception/DimensionMismatchException (1, 1)
	72 dup (1, 1)
	73 aload_0 (1, 1)
	74 getfield (1, 1)
	75 org/apache/commons/math3/ode/nonstiff/AdaptiveStepsizeFieldIntegrator.mainSetDimension:I (1, 1)
	77 aload_0 (1, 1)
	78 getfield (1, 1)
	79 org/apache/commons/math3/ode/nonstiff/AdaptiveStepsizeFieldIntegrator.vecRelativeTolerance:[D (1, 1)
	81 arraylength (1, 1)
	82 invokespecial (1, 1)
	83 org/apache/commons/math3/exception/DimensionMismatchException.<init>:(II)V (1, 1)
	85 athrow (1, 1)
	86 return (0, 0)

Method: initializeStep
	0 aload_0 (1, 1)
	1 getfield (1, 1)
	2 org/apache/commons/math3/ode/nonstiff/AdaptiveStepsizeFieldIntegrator.initialStep:Lorg/apache/commons/math3/RealFieldElement; (1, 1)
	4 invokeinterface (1, 1)
	5 org/apache/commons/math3/RealFieldElement.sanityChecks:(Lorg/apache/commons/math3/ode/FieldODEState;Lorg/apache/commons/math3/RealFieldElement;)V (1, 1)
	7 0 (1, 1)
	9 dconst_0 (1, 1)
	10 dcmpl (1, 1)
	11 ifle (1, 1)
	12 27 (1, 1)
	14 iload_1 (1, 4)
	15 ifeq (1, 4)
	16 10 (1, 4)
	18 aload_0 (1, 4)
	19 getfield (1, 4)
	20 org/apache/commons/math3/ode/nonstiff/AdaptiveStepsizeFieldIntegrator.initialStep:Lorg/apache/commons/math3/RealFieldElement; (1, 4)
	22 goto (1, 4)
	23 15 (1, 4)
	25 aload_0 (1, 4)
	26 getfield (1, 4)
	27 org/apache/commons/math3/ode/nonstiff/AdaptiveStepsizeFieldIntegrator.initialStep:Lorg/apache/commons/math3/RealFieldElement; (1, 4)
	29 invokeinterface (1, 4)
	30 org/apache/commons/math3/RealFieldElement.initialStep:Lorg/apache/commons/math3/RealFieldElement; (1, 4)
	32 0 (1, 4)
	34 checkcast (1, 4)
	35 org/apache/commons/math3/RealFieldElement (1, 4)
	37 areturn (1, 4)
	38 aload (0, 4)
	39 #5 (0, 4)
	40 aload (0, 4)
	41 #4 (0, 4)
	42 invokevirtual (0, 4)
	43 org/apache/commons/math3/ode/FieldEquationsMapper.mapState:(Lorg/apache/commons/math3/ode/FieldODEState;)[Lorg/apache/commons/math3/RealFieldElement; (0, 4)
	45 astore (0, 4)
	46 #6 (0, 4)
	47 aload (0, 4)
	48 #5 (0, 4)
	49 aload (0, 4)
	50 #4 (0, 4)
	51 invokevirtual (0, 4)
	52 org/apache/commons/math3/ode/FieldEquationsMapper.mapDerivative:(Lorg/apache/commons/math3/ode/FieldODEStateAndDerivative;)[Lorg/apache/commons/math3/RealFieldElement; (0, 4)
	54 astore (0, 4)
	55 #7 (0, 4)
	56 aload_0 (0, 4)
	57 invokevirtual (0, 4)
	58 org/apache/commons/math3/ode/nonstiff/AdaptiveStepsizeFieldIntegrator.getField:()Lorg/apache/commons/math3/Field; (0, 4)
	60 invokeinterface (0, 4)
	61 org/apache/commons/math3/Field.org/apache/commons/math3/RealFieldElement (0, 4)
	63 0 (0, 4)
	65 checkcast (0, 4)
	66 org/apache/commons/math3/RealFieldElement (0, 4)
	68 astore (0, 4)
	69 #8 (0, 4)
	70 aload_0 (0, 4)
	71 invokevirtual (0, 4)
	72 org/apache/commons/math3/ode/nonstiff/AdaptiveStepsizeFieldIntegrator.getField:()Lorg/apache/commons/math3/Field; (0, 4)
	74 invokeinterface (0, 4)
	75 org/apache/commons/math3/Field.org/apache/commons/math3/RealFieldElement (0, 4)
	77 0 (0, 4)
	79 checkcast (0, 4)
	80 org/apache/commons/math3/RealFieldElement (0, 4)
	82 astore (0, 4)
	83 #9 (0, 4)
	84 iconst_0 (1, 4)
	85 istore (1, 4)
	86 #10 (1, 4)
	87 iload (1, 4)
	88 #10 (1, 4)
	89 aload_3 (1, 4)
	90 arraylength (1, 4)
	91 if_icmpge (1, 4)
	92 89 (1, 4)
	94 aload (1, 4)
	95 #6 (1, 4)
	96 iload (1, 4)
	97 #10 (1, 4)
	98 aaload (1, 4)
	99 aload_3 (1, 4)
	100 iload (1, 4)
	101 #10 (1, 4)
	102 aaload (1, 4)
	103 invokeinterface (1, 4)
	104 org/apache/commons/math3/RealFieldElement.multiply:(Ljava/lang/Object;)Ljava/lang/Object; (1, 4)
	106 0 (1, 4)
	108 checkcast (1, 4)
	109 org/apache/commons/math3/RealFieldElement (1, 4)
	111 astore (1, 4)
	112 #11 (1, 4)
	113 aload (1, 4)
	114 #8 (1, 4)
	115 aload (1, 4)
	116 #11 (1, 4)
	117 aload (1, 4)
	118 #11 (1, 4)
	119 invokeinterface (1, 4)
	120 org/apache/commons/math3/RealFieldElement.add:(Ljava/lang/Object;)Ljava/lang/Object; (1, 4)
	122 0 (1, 4)
	124 invokeinterface (1, 4)
	125 org/apache/commons/math3/RealFieldElement.sqrt:()Ljava/lang/Object; (1, 4)
	127 0 (1, 4)
	129 checkcast (1, 4)
	130 org/apache/commons/math3/RealFieldElement (1, 4)
	132 astore (1, 4)
	133 #8 (1, 4)
	134 aload (1, 4)
	135 #7 (1, 4)
	136 iload (1, 4)
	137 #10 (1, 4)
	138 aaload (1, 4)
	139 aload_3 (1, 4)
	140 iload (1, 4)
	141 #10 (1, 4)
	142 aaload (1, 4)
	143 invokeinterface (1, 4)
	144 org/apache/commons/math3/RealFieldElement.multiply:(Ljava/lang/Object;)Ljava/lang/Object; (1, 4)
	146 0 (1, 4)
	148 checkcast (1, 4)
	149 org/apache/commons/math3/RealFieldElement (1, 4)
	151 astore (1, 4)
	152 #12 (1, 4)
	153 aload (1, 4)
	154 #9 (1, 4)
	155 aload (1, 4)
	156 #12 (1, 4)
	157 aload (1, 4)
	158 #12 (1, 4)
	159 invokeinterface (1, 4)
	160 org/apache/commons/math3/RealFieldElement.add:(Ljava/lang/Object;)Ljava/lang/Object; (1, 4)
	162 0 (1, 4)
	164 invokeinterface (1, 4)
	165 org/apache/commons/math3/RealFieldElement.sqrt:()Ljava/lang/Object; (1, 4)
	167 0 (1, 4)
	169 checkcast (1, 4)
	170 org/apache/commons/math3/RealFieldElement (1, 4)
	172 astore (1, 4)
	173 #9 (1, 4)
	174 iinc (1, 4)
	175 #10 (1, 4)
	176 -89 (1, 4)
	177 goto (1, 4)
	178 -90 (1, 4)
	180 aload (0, 4)
	181 #8 (0, 4)
	182 invokeinterface (0, 4)
	183 org/apache/commons/math3/RealFieldElement.sanityChecks:(Lorg/apache/commons/math3/ode/FieldODEState;Lorg/apache/commons/math3/RealFieldElement;)V (0, 4)
	185 0 (0, 4)
	187 ldc2_w (0, 4)
	188 1e-10 (0, 4)
	190 dcmpg (0, 4)
	191 iflt (0, 4)
	192 17 (0, 4)
	194 aload (0, 4)
	195 #9 (0, 4)
	196 invokeinterface (0, 4)
	197 org/apache/commons/math3/RealFieldElement.sanityChecks:(Lorg/apache/commons/math3/ode/FieldODEState;Lorg/apache/commons/math3/RealFieldElement;)V (0, 4)
	199 0 (0, 4)
	201 ldc2_w (0, 4)
	202 1e-10 (0, 4)
	204 dcmpg (0, 4)
	205 ifge (0, 4)
	206 29 (0, 4)
	208 aload_0 (0, 4)
	209 invokevirtual (0, 4)
	210 org/apache/commons/math3/ode/nonstiff/AdaptiveStepsizeFieldIntegrator.getField:()Lorg/apache/commons/math3/Field; (0, 4)
	212 invokeinterface (0, 4)
	213 org/apache/commons/math3/Field.org/apache/commons/math3/RealFieldElement (0, 4)
	215 0 (0, 4)
	217 checkcast (0, 4)
	218 org/apache/commons/math3/RealFieldElement (0, 4)
	220 ldc2_w (0, 4)
	221 1e-06 (0, 4)
	223 invokeinterface (0, 4)
	224 org/apache/commons/math3/RealFieldElement.minStep:Lorg/apache/commons/math3/RealFieldElement; (0, 4)
	226 0 (0, 4)
	228 checkcast (0, 4)
	229 org/apache/commons/math3/RealFieldElement (0, 4)
	231 goto (0, 4)
	232 34 (0, 4)
	234 aload (0, 4)
	235 #8 (0, 4)
	236 aload (0, 4)
	237 #9 (0, 4)
	238 invokeinterface (0, 4)
	239 org/apache/commons/math3/RealFieldElement.multiply:(Ljava/lang/Object;)Ljava/lang/Object; (0, 4)
	241 0 (0, 4)
	243 checkcast (0, 4)
	244 org/apache/commons/math3/RealFieldElement (0, 4)
	246 invokeinterface (0, 4)
	247 org/apache/commons/math3/RealFieldElement.multiply:(D)Ljava/lang/Object; (0, 4)
	249 0 (0, 4)
	251 checkcast (0, 4)
	252 org/apache/commons/math3/RealFieldElement (0, 4)
	254 ldc2_w (0, 4)
	255 0.01 (0, 4)
	257 invokeinterface (0, 4)
	258 org/apache/commons/math3/RealFieldElement.org/apache/commons/math3/util/MathArrays (0, 4)
	260 0 (0, 4)
	262 checkcast (0, 4)
	263 org/apache/commons/math3/RealFieldElement (0, 4)
	265 astore (0, 4)
	266 #10 (0, 4)
	267 iload_1 (1, 1)
	268 ifne (1, 1)
	269 15 (1, 1)
	271 aload (1, 1)
	272 #10 (1, 1)
	273 invokeinterface (1, 1)
	274 org/apache/commons/math3/RealFieldElement.initialStep:Lorg/apache/commons/math3/RealFieldElement; (1, 1)
	276 0 (1, 1)
	278 checkcast (1, 1)
	279 org/apache/commons/math3/RealFieldElement (1, 1)
	281 astore (1, 1)
	282 #10 (1, 1)
	283 aload_0 (0, 4)
	284 invokevirtual (0, 4)
	285 org/apache/commons/math3/ode/nonstiff/AdaptiveStepsizeFieldIntegrator.getField:()Lorg/apache/commons/math3/Field; (0, 4)
	287 aload (0, 4)
	288 #6 (0, 4)
	289 arraylength (0, 4)
	290 invokestatic (0, 4)
	291 org/apache/commons/math3/util/MathArrays.buildArray:(Lorg/apache/commons/math3/Field;I)[Ljava/lang/Object; (0, 4)
	293 checkcast (0, 4)
	294 [Lorg/apache/commons/math3/RealFieldElement; (0, 4)
	296 astore (0, 4)
	297 #11 (0, 4)
	298 iconst_0 (1, 4)
	299 istore (1, 4)
	300 #12 (1, 4)
	301 iload (1, 4)
	302 #12 (1, 4)
	303 aload (1, 4)
	304 #6 (1, 4)
	305 arraylength (1, 4)
	306 if_icmpge (1, 4)
	307 39 (1, 4)
	309 aload (1, 4)
	310 #11 (1, 4)
	311 iload (1, 4)
	312 #12 (1, 4)
	313 aload (1, 4)
	314 #6 (1, 4)
	315 iload (1, 4)
	316 #12 (1, 4)
	317 aaload (1, 4)
	318 aload (1, 4)
	319 #7 (1, 4)
	320 iload (1, 4)
	321 #12 (1, 4)
	322 aaload (1, 4)
	323 aload (1, 4)
	324 #10 (1, 4)
	325 invokeinterface (1, 4)
	326 org/apache/commons/math3/RealFieldElement.add:(Ljava/lang/Object;)Ljava/lang/Object; (1, 4)
	328 0 (1, 4)
	330 invokeinterface (1, 4)
	331 org/apache/commons/math3/RealFieldElement.sqrt:()Ljava/lang/Object; (1, 4)
	333 0 (1, 4)
	335 checkcast (1, 4)
	336 org/apache/commons/math3/RealFieldElement (1, 4)
	338 aastore (1, 4)
	339 iinc (1, 4)
	340 #12 (1, 4)
	341 -89 (1, 4)
	342 goto (1, 4)
	343 -41 (1, 4)
	345 aload_0 (0, 4)
	346 aload (0, 4)
	347 #4 (0, 4)
	348 invokevirtual (0, 4)
	349 org/apache/commons/math3/ode/FieldODEStateAndDerivative.getTime:()Lorg/apache/commons/math3/RealFieldElement; (0, 4)
	351 aload (0, 4)
	352 #10 (0, 4)
	353 invokeinterface (0, 4)
	354 org/apache/commons/math3/RealFieldElement.sqrt:()Ljava/lang/Object; (0, 4)
	356 0 (0, 4)
	358 checkcast (0, 4)
	359 org/apache/commons/math3/RealFieldElement (0, 4)
	361 aload (0, 4)
	362 #11 (0, 4)
	363 invokevirtual (0, 4)
	364 org/apache/commons/math3/ode/nonstiff/AdaptiveStepsizeFieldIntegrator.computeDerivatives:(Lorg/apache/commons/math3/RealFieldElement;[Lorg/apache/commons/math3/RealFieldElement;)[Lorg/apache/commons/math3/RealFieldElement; (0, 4)
	366 astore (0, 4)
	367 #12 (0, 4)
	368 aload_0 (0, 4)
	369 invokevirtual (0, 4)
	370 org/apache/commons/math3/ode/nonstiff/AdaptiveStepsizeFieldIntegrator.getField:()Lorg/apache/commons/math3/Field; (0, 4)
	372 invokeinterface (0, 4)
	373 org/apache/commons/math3/Field.org/apache/commons/math3/RealFieldElement (0, 4)
	375 0 (0, 4)
	377 checkcast (0, 4)
	378 org/apache/commons/math3/RealFieldElement (0, 4)
	380 astore (0, 4)
	381 #13 (0, 4)
	382 iconst_0 (1, 4)
	383 istore (1, 4)
	384 #14 (1, 4)
	385 iload (1, 4)
	386 #14 (1, 4)
	387 aload_3 (1, 4)
	388 arraylength (1, 4)
	389 if_icmpge (1, 4)
	390 62 (1, 4)
	392 aload (1, 4)
	393 #12 (1, 4)
	394 iload (1, 4)
	395 #14 (1, 4)
	396 aaload (1, 4)
	397 aload (1, 4)
	398 #7 (1, 4)
	399 iload (1, 4)
	400 #14 (1, 4)
	401 aaload (1, 4)
	402 invokeinterface (1, 4)
	403 org/apache/commons/math3/RealFieldElement.getReal:()D (1, 4)
	405 0 (1, 4)
	407 checkcast (1, 4)
	408 org/apache/commons/math3/RealFieldElement (1, 4)
	410 aload_3 (1, 4)
	411 iload (1, 4)
	412 #14 (1, 4)
	413 aaload (1, 4)
	414 invokeinterface (1, 4)
	415 org/apache/commons/math3/RealFieldElement.multiply:(Ljava/lang/Object;)Ljava/lang/Object; (1, 4)
	417 0 (1, 4)
	419 checkcast (1, 4)
	420 org/apache/commons/math3/RealFieldElement (1, 4)
	422 astore (1, 4)
	423 #15 (1, 4)
	424 aload (1, 4)
	425 #13 (1, 4)
	426 aload (1, 4)
	427 #15 (1, 4)
	428 aload (1, 4)
	429 #15 (1, 4)
	430 invokeinterface (1, 4)
	431 org/apache/commons/math3/RealFieldElement.add:(Ljava/lang/Object;)Ljava/lang/Object; (1, 4)
	433 0 (1, 4)
	435 invokeinterface (1, 4)
	436 org/apache/commons/math3/RealFieldElement.sqrt:()Ljava/lang/Object; (1, 4)
	438 0 (1, 4)
	440 checkcast (1, 4)
	441 org/apache/commons/math3/RealFieldElement (1, 4)
	443 astore (1, 4)
	444 #13 (1, 4)
	445 iinc (1, 4)
	446 #14 (1, 4)
	447 -89 (1, 4)
	448 goto (1, 4)
	449 -63 (1, 4)
	451 aload (0, 4)
	452 #13 (0, 4)
	453 invokeinterface (0, 4)
	454 org/apache/commons/math3/RealFieldElement.multiply:(D)Ljava/lang/Object; (0, 4)
	456 0 (0, 4)
	458 checkcast (0, 4)
	459 org/apache/commons/math3/RealFieldElement (0, 4)
	461 aload (0, 4)
	462 #10 (0, 4)
	463 invokeinterface (0, 4)
	464 org/apache/commons/math3/RealFieldElement.multiply:(Ljava/lang/Object;)Ljava/lang/Object; (0, 4)
	466 0 (0, 4)
	468 checkcast (0, 4)
	469 org/apache/commons/math3/RealFieldElement (0, 4)
	471 astore (0, 4)
	472 #13 (0, 4)
	473 aload (0, 4)
	474 #9 (0, 4)
	475 invokeinterface (0, 4)
	476 org/apache/commons/math3/RealFieldElement.multiply:(D)Ljava/lang/Object; (0, 4)
	478 0 (0, 4)
	480 checkcast (0, 4)
	481 org/apache/commons/math3/RealFieldElement (0, 4)
	483 aload (0, 4)
	484 #13 (0, 4)
	485 invokestatic (0, 4)
	486 org/apache/commons/math3/util/MathUtils.max:(Lorg/apache/commons/math3/RealFieldElement;Lorg/apache/commons/math3/RealFieldElement;)Lorg/apache/commons/math3/RealFieldElement; (0, 4)
	488 astore (0, 4)
	489 #14 (0, 4)
	490 aload (0, 4)
	491 #14 (0, 4)
	492 invokeinterface (0, 4)
	493 org/apache/commons/math3/RealFieldElement.sanityChecks:(Lorg/apache/commons/math3/ode/FieldODEState;Lorg/apache/commons/math3/RealFieldElement;)V (0, 4)
	495 0 (0, 4)
	497 ldc2_w (0, 4)
	498 1e-15 (0, 4)
	500 dcmpg (0, 4)
	501 ifge (0, 4)
	502 53 (0, 4)
	504 aload_0 (0, 4)
	505 invokevirtual (0, 4)
	506 org/apache/commons/math3/ode/nonstiff/AdaptiveStepsizeFieldIntegrator.getField:()Lorg/apache/commons/math3/Field; (0, 4)
	508 invokeinterface (0, 4)
	509 org/apache/commons/math3/Field.org/apache/commons/math3/RealFieldElement (0, 4)
	511 0 (0, 4)
	513 checkcast (0, 4)
	514 org/apache/commons/math3/RealFieldElement (0, 4)
	516 ldc2_w (0, 4)
	517 1e-06 (0, 4)
	519 invokeinterface (0, 4)
	520 org/apache/commons/math3/RealFieldElement.minStep:Lorg/apache/commons/math3/RealFieldElement; (0, 4)
	522 0 (0, 4)
	524 checkcast (0, 4)
	525 org/apache/commons/math3/RealFieldElement (0, 4)
	527 aload (0, 4)
	528 #10 (0, 4)
	529 invokeinterface (0, 4)
	530 org/apache/commons/math3/RealFieldElement.multiply:(I)Ljava/lang/Object; (0, 4)
	532 0 (0, 4)
	534 checkcast (0, 4)
	535 org/apache/commons/math3/RealFieldElement (0, 4)
	537 ldc2_w (0, 4)
	538 0.001 (0, 4)
	540 invokeinterface (0, 4)
	541 org/apache/commons/math3/RealFieldElement.org/apache/commons/math3/util/MathArrays (0, 4)
	543 0 (0, 4)
	545 checkcast (0, 4)
	546 org/apache/commons/math3/RealFieldElement (0, 4)
	548 invokestatic (0, 4)
	549 org/apache/commons/math3/util/MathUtils.max:(Lorg/apache/commons/math3/RealFieldElement;Lorg/apache/commons/math3/RealFieldElement;)Lorg/apache/commons/math3/RealFieldElement; (0, 4)
	551 goto (0, 4)
	552 35 (0, 4)
	554 aload (0, 4)
	555 #14 (0, 4)
	556 bipush (0, 4)
	557 100 (0, 4)
	558 invokeinterface (0, 4)
	559 org/apache/commons/math3/RealFieldElement.reciprocal:()Ljava/lang/Object; (0, 4)
	561 0 (0, 4)
	563 checkcast (0, 4)
	564 org/apache/commons/math3/RealFieldElement (0, 4)
	566 invokeinterface (0, 4)
	567 org/apache/commons/math3/RealFieldElement.pow:(D)Ljava/lang/Object; (0, 4)
	569 0 (0, 4)
	571 checkcast (0, 4)
	572 org/apache/commons/math3/RealFieldElement (0, 4)
	574 dconst_1 (0, 4)
	575 iload_2 (0, 4)
	576 i2d (0, 4)
	577 ddiv (0, 4)
	578 invokeinterface (0, 4)
	579 org/apache/commons/math3/RealFieldElement.min:(Lorg/apache/commons/math3/RealFieldElement;Lorg/apache/commons/math3/RealFieldElement;)Lorg/apache/commons/math3/RealFieldElement; (0, 4)
	581 0 (0, 4)
	583 checkcast (0, 4)
	584 org/apache/commons/math3/RealFieldElement (0, 4)
	586 astore (0, 4)
	587 #15 (0, 4)
	588 aload (0, 4)
	589 #10 (0, 4)
	590 invokeinterface (0, 4)
	591 org/apache/commons/math3/RealFieldElement.multiply:(I)Ljava/lang/Object; (0, 4)
	593 0 (0, 4)
	595 checkcast (0, 4)
	596 org/apache/commons/math3/RealFieldElement (0, 4)
	598 bipush (0, 4)
	599 100 (0, 4)
	600 invokeinterface (0, 4)
	601 org/apache/commons/math3/RealFieldElement.reciprocal:()Ljava/lang/Object; (0, 4)
	603 0 (0, 4)
	605 checkcast (0, 4)
	606 org/apache/commons/math3/RealFieldElement (0, 4)
	608 aload (0, 4)
	609 #15 (0, 4)
	610 invokestatic (0, 4)
	611 org/apache/commons/math3/util/MathUtils.min:(Lorg/apache/commons/math3/RealFieldElement;Lorg/apache/commons/math3/RealFieldElement;)Lorg/apache/commons/math3/RealFieldElement; (0, 4)
	613 astore (0, 4)
	614 #10 (0, 4)
	615 aload (0, 4)
	616 #10 (0, 4)
	617 aload (0, 4)
	618 #4 (0, 4)
	619 invokevirtual (0, 4)
	620 org/apache/commons/math3/ode/FieldODEStateAndDerivative.getTime:()Lorg/apache/commons/math3/RealFieldElement; (0, 4)
	622 invokeinterface (0, 4)
	623 org/apache/commons/math3/RealFieldElement.multiply:(I)Ljava/lang/Object; (0, 4)
	625 0 (0, 4)
	627 checkcast (0, 4)
	628 org/apache/commons/math3/RealFieldElement (0, 4)
	630 ldc2_w (0, 4)
	631 1e-12 (0, 4)
	633 invokeinterface (0, 4)
	634 org/apache/commons/math3/RealFieldElement.org/apache/commons/math3/util/MathArrays (0, 4)
	636 0 (0, 4)
	638 checkcast (0, 4)
	639 org/apache/commons/math3/RealFieldElement (0, 4)
	641 invokestatic (0, 4)
	642 org/apache/commons/math3/util/MathUtils.max:(Lorg/apache/commons/math3/RealFieldElement;Lorg/apache/commons/math3/RealFieldElement;)Lorg/apache/commons/math3/RealFieldElement; (0, 4)
	644 astore (0, 4)
	645 #10 (0, 4)
	646 aload_0 (0, 4)
	647 getfield (0, 4)
	648 org/apache/commons/math3/ode/nonstiff/AdaptiveStepsizeFieldIntegrator.minStep:Lorg/apache/commons/math3/RealFieldElement; (0, 4)
	650 aload_0 (0, 4)
	651 getfield (0, 4)
	652 org/apache/commons/math3/ode/nonstiff/AdaptiveStepsizeFieldIntegrator.maxStep:Lorg/apache/commons/math3/RealFieldElement; (0, 4)
	654 aload (0, 4)
	655 #10 (0, 4)
	656 invokestatic (0, 4)
	657 org/apache/commons/math3/util/MathUtils.min:(Lorg/apache/commons/math3/RealFieldElement;Lorg/apache/commons/math3/RealFieldElement;)Lorg/apache/commons/math3/RealFieldElement; (0, 4)
	659 invokestatic (0, 4)
	660 org/apache/commons/math3/util/MathUtils.max:(Lorg/apache/commons/math3/RealFieldElement;Lorg/apache/commons/math3/RealFieldElement;)Lorg/apache/commons/math3/RealFieldElement; (0, 4)
	662 astore (0, 4)
	663 #10 (0, 4)
	664 iload_1 (1, 1)
	665 ifne (1, 1)
	666 15 (1, 1)
	668 aload (1, 1)
	669 #10 (1, 1)
	670 invokeinterface (1, 1)
	671 org/apache/commons/math3/RealFieldElement.initialStep:Lorg/apache/commons/math3/RealFieldElement; (1, 1)
	673 0 (1, 1)
	675 checkcast (1, 1)
	676 org/apache/commons/math3/RealFieldElement (1, 1)
	678 astore (1, 1)
	679 #10 (1, 1)
	680 aload (0, 4)
	681 #10 (0, 4)
	682 areturn (0, 4)

Method: filterStep
	0 aload_1 (0, 0)
	1 astore (0, 0)
	2 #4 (0, 0)
	3 aload_1 (1, 1)
	4 invokeinterface (1, 1)
	5 org/apache/commons/math3/RealFieldElement.multiply:(I)Ljava/lang/Object; (1, 1)
	7 0 (1, 1)
	9 checkcast (1, 1)
	10 org/apache/commons/math3/RealFieldElement (1, 1)
	12 aload_0 (1, 1)
	13 getfield (1, 1)
	14 org/apache/commons/math3/ode/nonstiff/AdaptiveStepsizeFieldIntegrator.minStep:Lorg/apache/commons/math3/RealFieldElement; (1, 1)
	16 invokeinterface (1, 1)
	17 org/apache/commons/math3/RealFieldElement.getReal:()D (1, 1)
	19 0 (1, 1)
	21 checkcast (1, 1)
	22 org/apache/commons/math3/RealFieldElement (1, 1)
	24 invokeinterface (1, 1)
	25 org/apache/commons/math3/RealFieldElement.sanityChecks:(Lorg/apache/commons/math3/ode/FieldODEState;Lorg/apache/commons/math3/RealFieldElement;)V (1, 1)
	27 0 (1, 1)
	29 dconst_0 (1, 1)
	30 dcmpg (1, 1)
	31 ifge (1, 1)
	32 76 (1, 1)
	34 iload_3 (2, 1)
	35 ifeq (2, 1)
	36 31 (2, 1)
	38 iload_2 (2, 4)
	39 ifeq (2, 4)
	40 10 (2, 4)
	42 aload_0 (2, 4)
	43 getfield (2, 4)
	44 org/apache/commons/math3/ode/nonstiff/AdaptiveStepsizeFieldIntegrator.minStep:Lorg/apache/commons/math3/RealFieldElement; (2, 4)
	46 goto (2, 4)
	47 15 (2, 4)
	49 aload_0 (2, 4)
	50 getfield (2, 4)
	51 org/apache/commons/math3/ode/nonstiff/AdaptiveStepsizeFieldIntegrator.minStep:Lorg/apache/commons/math3/RealFieldElement; (2, 4)
	53 invokeinterface (2, 4)
	54 org/apache/commons/math3/RealFieldElement.initialStep:Lorg/apache/commons/math3/RealFieldElement; (2, 4)
	56 0 (2, 4)
	58 checkcast (2, 4)
	59 org/apache/commons/math3/RealFieldElement (2, 4)
	61 astore (2, 4)
	62 #4 (2, 4)
	63 goto (2, 4)
	64 44 (2, 4)
	66 new (2, 2)
	67 org/apache/commons/math3/exception/NumberIsTooSmallException (2, 2)
	69 dup (2, 2)
	70 getstatic (2, 2)
	71 org/apache/commons/math3/exception/util/LocalizedFormats.MINIMAL_STEPSIZE_REACHED_DURING_INTEGRATION:Lorg/apache/commons/math3/exception/util/LocalizedFormats; (2, 2)
	73 aload_1 (2, 2)
	74 invokeinterface (2, 2)
	75 org/apache/commons/math3/RealFieldElement.multiply:(I)Ljava/lang/Object; (2, 2)
	77 0 (2, 2)
	79 checkcast (2, 2)
	80 org/apache/commons/math3/RealFieldElement (2, 2)
	82 invokeinterface (2, 2)
	83 org/apache/commons/math3/RealFieldElement.sanityChecks:(Lorg/apache/commons/math3/ode/FieldODEState;Lorg/apache/commons/math3/RealFieldElement;)V (2, 2)
	85 0 (2, 2)
	87 invokestatic (2, 2)
	88 java/lang/Double.valueOf:(D)Ljava/lang/Double; (2, 2)
	90 aload_0 (2, 2)
	91 getfield (2, 2)
	92 org/apache/commons/math3/ode/nonstiff/AdaptiveStepsizeFieldIntegrator.minStep:Lorg/apache/commons/math3/RealFieldElement; (2, 2)
	94 invokeinterface (2, 2)
	95 org/apache/commons/math3/RealFieldElement.sanityChecks:(Lorg/apache/commons/math3/ode/FieldODEState;Lorg/apache/commons/math3/RealFieldElement;)V (2, 2)
	97 0 (2, 2)
	99 invokestatic (2, 2)
	100 java/lang/Double.valueOf:(D)Ljava/lang/Double; (2, 2)
	102 iconst_1 (2, 2)
	103 invokespecial (2, 2)
	104 org/apache/commons/math3/exception/NumberIsTooSmallException.<init>:(Lorg/apache/commons/math3/exception/util/Localizable;Ljava/lang/Number;Ljava/lang/Number;Z)V (2, 2)
	106 athrow (2, 2)
	107 aload (1, 1)
	108 #4 (1, 1)
	109 aload_0 (1, 1)
	110 getfield (1, 1)
	111 org/apache/commons/math3/ode/nonstiff/AdaptiveStepsizeFieldIntegrator.maxStep:Lorg/apache/commons/math3/RealFieldElement; (1, 1)
	113 invokeinterface (1, 1)
	114 org/apache/commons/math3/RealFieldElement.getReal:()D (1, 1)
	116 0 (1, 1)
	118 checkcast (1, 1)
	119 org/apache/commons/math3/RealFieldElement (1, 1)
	121 invokeinterface (1, 1)
	122 org/apache/commons/math3/RealFieldElement.sanityChecks:(Lorg/apache/commons/math3/ode/FieldODEState;Lorg/apache/commons/math3/RealFieldElement;)V (1, 1)
	124 0 (1, 1)
	126 dconst_0 (1, 1)
	127 dcmpl (1, 1)
	128 ifle (1, 1)
	129 12 (1, 1)
	131 aload_0 (1, 1)
	132 getfield (1, 1)
	133 org/apache/commons/math3/ode/nonstiff/AdaptiveStepsizeFieldIntegrator.maxStep:Lorg/apache/commons/math3/RealFieldElement; (1, 1)
	135 astore (1, 1)
	136 #4 (1, 1)
	137 goto (1, 1)
	138 41 (1, 1)
	140 aload (1, 1)
	141 #4 (1, 1)
	142 aload_0 (1, 1)
	143 getfield (1, 1)
	144 org/apache/commons/math3/ode/nonstiff/AdaptiveStepsizeFieldIntegrator.maxStep:Lorg/apache/commons/math3/RealFieldElement; (1, 1)
	146 invokeinterface (1, 1)
	147 org/apache/commons/math3/RealFieldElement.sqrt:()Ljava/lang/Object; (1, 1)
	149 0 (1, 1)
	151 checkcast (1, 1)
	152 org/apache/commons/math3/RealFieldElement (1, 1)
	154 invokeinterface (1, 1)
	155 org/apache/commons/math3/RealFieldElement.sanityChecks:(Lorg/apache/commons/math3/ode/FieldODEState;Lorg/apache/commons/math3/RealFieldElement;)V (1, 1)
	157 0 (1, 1)
	159 dconst_0 (1, 1)
	160 dcmpg (1, 1)
	161 ifge (1, 1)
	162 17 (1, 1)
	164 aload_0 (1, 1)
	165 getfield (1, 1)
	166 org/apache/commons/math3/ode/nonstiff/AdaptiveStepsizeFieldIntegrator.maxStep:Lorg/apache/commons/math3/RealFieldElement; (1, 1)
	168 invokeinterface (1, 1)
	169 org/apache/commons/math3/RealFieldElement.initialStep:Lorg/apache/commons/math3/RealFieldElement; (1, 1)
	171 0 (1, 1)
	173 checkcast (1, 1)
	174 org/apache/commons/math3/RealFieldElement (1, 1)
	176 astore (1, 1)
	177 #4 (1, 1)
	178 aload (0, 0)
	179 #4 (0, 0)
	180 areturn (0, 0)

Method: resetInternalState
	0 aload_0 (0, 0)
	1 aconst_null (0, 0)
	2 invokevirtual (0, 0)
	3 org/apache/commons/math3/ode/nonstiff/AdaptiveStepsizeFieldIntegrator.setStepStart:(Lorg/apache/commons/math3/ode/FieldODEStateAndDerivative;)V (0, 0)
	5 aload_0 (0, 0)
	6 aload_0 (0, 0)
	7 getfield (0, 0)
	8 org/apache/commons/math3/ode/nonstiff/AdaptiveStepsizeFieldIntegrator.minStep:Lorg/apache/commons/math3/RealFieldElement; (0, 0)
	10 aload_0 (0, 0)
	11 getfield (0, 0)
	12 org/apache/commons/math3/ode/nonstiff/AdaptiveStepsizeFieldIntegrator.maxStep:Lorg/apache/commons/math3/RealFieldElement; (0, 0)
	14 invokeinterface (0, 0)
	15 org/apache/commons/math3/RealFieldElement.add:(Ljava/lang/Object;)Ljava/lang/Object; (0, 0)
	17 0 (0, 0)
	19 checkcast (0, 0)
	20 org/apache/commons/math3/RealFieldElement (0, 0)
	22 invokeinterface (0, 0)
	23 org/apache/commons/math3/RealFieldElement.multiply:(D)Ljava/lang/Object; (0, 0)
	25 0 (0, 0)
	27 checkcast (0, 0)
	28 org/apache/commons/math3/RealFieldElement (0, 0)
	30 invokevirtual (0, 0)
	31 org/apache/commons/math3/ode/nonstiff/AdaptiveStepsizeFieldIntegrator.setStepSize:(Lorg/apache/commons/math3/RealFieldElement;)V (0, 0)
	33 return (0, 0)

Method: getMinStep
	0 aload_0 (0, 0)
	1 getfield (0, 0)
	2 org/apache/commons/math3/ode/nonstiff/AdaptiveStepsizeFieldIntegrator.minStep:Lorg/apache/commons/math3/RealFieldElement; (0, 0)
	4 areturn (0, 0)

Method: getMaxStep
	0 aload_0 (0, 0)
	1 getfield (0, 0)
	2 org/apache/commons/math3/ode/nonstiff/AdaptiveStepsizeFieldIntegrator.maxStep:Lorg/apache/commons/math3/RealFieldElement; (0, 0)
	4 areturn (0, 0)

