Method: <init>
	0 aload_0 (0, 0)
	1 aload_1 (0, 0)
	2 invokespecial (0, 0)
	3 org/apache/commons/math3/ode/AbstractIntegrator.<init>:(Ljava/lang/String;)V (0, 0)
	5 aload_0 (0, 0)
	6 dload_2 (0, 0)
	7 dload (0, 0)
	8 #4 (0, 0)
	9 aload (0, 0)
	10 #6 (0, 0)
	11 aload (0, 0)
	12 #7 (0, 0)
	13 invokevirtual (0, 0)
	14 org/apache/commons/math3/ode/nonstiff/AdaptiveStepsizeIntegrator.setStepSizeControl:(DD[D[D)V (0, 0)
	16 aload_0 (0, 0)
	17 invokevirtual (0, 0)
	18 org/apache/commons/math3/ode/nonstiff/AdaptiveStepsizeIntegrator.resetInternalState:()V (0, 0)
	20 return (0, 0)

Method: setStepSizeControl
	0 aload_0 (0, 0)
	1 dload_1 (0, 0)
	2 invokestatic (0, 0)
	3 org/apache/commons/math3/util/FastMath.abs:(D)D (0, 0)
	5 putfield (0, 0)
	6 org/apache/commons/math3/ode/nonstiff/AdaptiveStepsizeIntegrator.minStep:D (0, 0)
	8 aload_0 (0, 0)
	9 dload_3 (0, 0)
	10 invokestatic (0, 0)
	11 org/apache/commons/math3/util/FastMath.abs:(D)D (0, 0)
	13 putfield (0, 0)
	14 org/apache/commons/math3/ode/nonstiff/AdaptiveStepsizeIntegrator.maxStep:D (0, 0)
	16 aload_0 (0, 0)
	17 ldc2_w (0, 0)
	18 -1.0 (0, 0)
	20 putfield (0, 0)
	21 org/apache/commons/math3/ode/nonstiff/AdaptiveStepsizeIntegrator.initialStep:D (0, 0)
	23 aload_0 (0, 0)
	24 dconst_0 (0, 0)
	25 putfield (0, 0)
	26 org/apache/commons/math3/ode/nonstiff/AdaptiveStepsizeIntegrator.scalAbsoluteTolerance:D (0, 0)
	28 aload_0 (0, 0)
	29 dconst_0 (0, 0)
	30 putfield (0, 0)
	31 org/apache/commons/math3/ode/nonstiff/AdaptiveStepsizeIntegrator.scalRelativeTolerance:D (0, 0)
	33 aload_0 (0, 0)
	34 aload (0, 0)
	35 #5 (0, 0)
	36 invokevirtual (0, 0)
	37 [D.clone:()Ljava/lang/Object; (0, 0)
	39 checkcast (0, 0)
	40 [D (0, 0)
	42 putfield (0, 0)
	43 org/apache/commons/math3/ode/nonstiff/AdaptiveStepsizeIntegrator.vecAbsoluteTolerance:[D (0, 0)
	45 aload_0 (0, 0)
	46 aload (0, 0)
	47 #6 (0, 0)
	48 invokevirtual (0, 0)
	49 [D.clone:()Ljava/lang/Object; (0, 0)
	51 checkcast (0, 0)
	52 [D (0, 0)
	54 putfield (0, 0)
	55 org/apache/commons/math3/ode/nonstiff/AdaptiveStepsizeIntegrator.vecRelativeTolerance:[D (0, 0)
	57 return (0, 0)

Method: setInitialStepSize
	0 dload_1 (1, 1)
	1 aload_0 (1, 1)
	2 getfield (1, 1)
	3 org/apache/commons/math3/ode/nonstiff/AdaptiveStepsizeIntegrator.minStep:D (1, 1)
	5 dcmpg (1, 1)
	6 iflt (1, 1)
	7 12 (1, 1)
	9 dload_1 (1, 1)
	10 aload_0 (1, 1)
	11 getfield (1, 1)
	12 org/apache/commons/math3/ode/nonstiff/AdaptiveStepsizeIntegrator.maxStep:D (1, 1)
	14 dcmpl (1, 1)
	15 ifle (1, 1)
	16 13 (1, 1)
	18 aload_0 (1, 1)
	19 ldc2_w (1, 1)
	20 -1.0 (1, 1)
	22 putfield (1, 1)
	23 org/apache/commons/math3/ode/nonstiff/AdaptiveStepsizeIntegrator.initialStep:D (1, 1)
	25 goto (1, 1)
	26 8 (1, 1)
	28 aload_0 (2, 2)
	29 dload_1 (2, 2)
	30 putfield (2, 2)
	31 org/apache/commons/math3/ode/nonstiff/AdaptiveStepsizeIntegrator.initialStep:D (2, 2)
	33 return (0, 0)

Method: sanityChecks
	0 aload_0 (0, 0)
	1 aload_1 (0, 0)
	2 dload_2 (0, 0)
	3 invokespecial (0, 0)
	4 org/apache/commons/math3/ode/AbstractIntegrator.sanityChecks:(Lorg/apache/commons/math3/ode/ExpandableStatefulODE;D)V (0, 0)
	6 aload_0 (0, 0)
	7 aload_1 (0, 0)
	8 invokevirtual (0, 0)
	9 org/apache/commons/math3/ode/ExpandableStatefulODE.getPrimaryMapper:()Lorg/apache/commons/math3/ode/EquationsMapper; (0, 0)
	11 invokevirtual (0, 0)
	12 org/apache/commons/math3/ode/EquationsMapper.getDimension:()I (0, 0)
	14 putfield (0, 0)
	15 org/apache/commons/math3/ode/nonstiff/AdaptiveStepsizeIntegrator.mainSetDimension:I (0, 0)
	17 aload_0 (1, 1)
	18 getfield (1, 1)
	19 org/apache/commons/math3/ode/nonstiff/AdaptiveStepsizeIntegrator.vecAbsoluteTolerance:[D (1, 1)
	21 ifnull (1, 1)
	22 32 (1, 1)
	24 aload_0 (1, 1)
	25 getfield (1, 1)
	26 org/apache/commons/math3/ode/nonstiff/AdaptiveStepsizeIntegrator.vecAbsoluteTolerance:[D (1, 1)
	28 arraylength (1, 1)
	29 aload_0 (1, 1)
	30 getfield (1, 1)
	31 org/apache/commons/math3/ode/nonstiff/AdaptiveStepsizeIntegrator.mainSetDimension:I (1, 1)
	33 if_icmpeq (1, 1)
	34 20 (1, 1)
	36 new (1, 1)
	37 org/apache/commons/math3/exception/DimensionMismatchException (1, 1)
	39 dup (1, 1)
	40 aload_0 (1, 1)
	41 getfield (1, 1)
	42 org/apache/commons/math3/ode/nonstiff/AdaptiveStepsizeIntegrator.mainSetDimension:I (1, 1)
	44 aload_0 (1, 1)
	45 getfield (1, 1)
	46 org/apache/commons/math3/ode/nonstiff/AdaptiveStepsizeIntegrator.vecAbsoluteTolerance:[D (1, 1)
	48 arraylength (1, 1)
	49 invokespecial (1, 1)
	50 org/apache/commons/math3/exception/DimensionMismatchException.<init>:(II)V (1, 1)
	52 athrow (1, 1)
	53 aload_0 (1, 1)
	54 getfield (1, 1)
	55 org/apache/commons/math3/ode/nonstiff/AdaptiveStepsizeIntegrator.vecRelativeTolerance:[D (1, 1)
	57 ifnull (1, 1)
	58 32 (1, 1)
	60 aload_0 (1, 1)
	61 getfield (1, 1)
	62 org/apache/commons/math3/ode/nonstiff/AdaptiveStepsizeIntegrator.vecRelativeTolerance:[D (1, 1)
	64 arraylength (1, 1)
	65 aload_0 (1, 1)
	66 getfield (1, 1)
	67 org/apache/commons/math3/ode/nonstiff/AdaptiveStepsizeIntegrator.mainSetDimension:I (1, 1)
	69 if_icmpeq (1, 1)
	70 20 (1, 1)
	72 new (1, 1)
	73 org/apache/commons/math3/exception/DimensionMismatchException (1, 1)
	75 dup (1, 1)
	76 aload_0 (1, 1)
	77 getfield (1, 1)
	78 org/apache/commons/math3/ode/nonstiff/AdaptiveStepsizeIntegrator.mainSetDimension:I (1, 1)
	80 aload_0 (1, 1)
	81 getfield (1, 1)
	82 org/apache/commons/math3/ode/nonstiff/AdaptiveStepsizeIntegrator.vecRelativeTolerance:[D (1, 1)
	84 arraylength (1, 1)
	85 invokespecial (1, 1)
	86 org/apache/commons/math3/exception/DimensionMismatchException.<init>:(II)V (1, 1)
	88 athrow (1, 1)
	89 return (0, 0)

Method: initializeStep
	0 aload_0 (1, 1)
	1 getfield (1, 1)
	2 org/apache/commons/math3/ode/nonstiff/AdaptiveStepsizeIntegrator.initialStep:D (1, 1)
	4 dconst_0 (1, 1)
	5 dcmpl (1, 1)
	6 ifle (1, 1)
	7 20 (1, 1)
	9 iload_1 (2, 4)
	10 ifeq (2, 4)
	11 10 (2, 4)
	13 aload_0 (2, 4)
	14 getfield (2, 4)
	15 org/apache/commons/math3/ode/nonstiff/AdaptiveStepsizeIntegrator.initialStep:D (2, 4)
	17 goto (2, 4)
	18 8 (2, 4)
	20 aload_0 (2, 4)
	21 getfield (2, 4)
	22 org/apache/commons/math3/ode/nonstiff/AdaptiveStepsizeIntegrator.initialStep:D (2, 4)
	24 dneg (2, 4)
	25 dreturn (2, 4)
	26 dconst_0 (1, 4)
	27 dstore (1, 4)
	28 #12 (1, 4)
	29 dconst_0 (1, 4)
	30 dstore (1, 4)
	31 #14 (1, 4)
	32 iconst_0 (2, 4)
	33 istore (2, 4)
	34 #16 (2, 4)
	35 iload (2, 4)
	36 #16 (2, 4)
	37 aload_3 (2, 4)
	38 arraylength (2, 4)
	39 if_icmpge (2, 4)
	40 53 (2, 4)
	42 aload (2, 4)
	43 #6 (2, 4)
	44 iload (2, 4)
	45 #16 (2, 4)
	46 daload (2, 4)
	47 aload_3 (2, 4)
	48 iload (2, 4)
	49 #16 (2, 4)
	50 daload (2, 4)
	51 ddiv (2, 4)
	52 dstore (2, 4)
	53 #10 (2, 4)
	54 dload (2, 4)
	55 #12 (2, 4)
	56 dload (2, 4)
	57 #10 (2, 4)
	58 dload (2, 4)
	59 #10 (2, 4)
	60 dmul (2, 4)
	61 dadd (2, 4)
	62 dstore (2, 4)
	63 #12 (2, 4)
	64 aload (2, 4)
	65 #7 (2, 4)
	66 iload (2, 4)
	67 #16 (2, 4)
	68 daload (2, 4)
	69 aload_3 (2, 4)
	70 iload (2, 4)
	71 #16 (2, 4)
	72 daload (2, 4)
	73 ddiv (2, 4)
	74 dstore (2, 4)
	75 #10 (2, 4)
	76 dload (2, 4)
	77 #14 (2, 4)
	78 dload (2, 4)
	79 #10 (2, 4)
	80 dload (2, 4)
	81 #10 (2, 4)
	82 dmul (2, 4)
	83 dadd (2, 4)
	84 dstore (2, 4)
	85 #14 (2, 4)
	86 iinc (2, 4)
	87 #16 (2, 4)
	88 -89 (2, 4)
	89 goto (2, 4)
	90 -54 (2, 4)
	92 dload (1, 4)
	93 #12 (1, 4)
	94 ldc2_w (1, 4)
	95 1e-10 (1, 4)
	97 dcmpg (1, 4)
	98 iflt (1, 4)
	99 12 (1, 4)
	101 dload (1, 4)
	102 #14 (1, 4)
	103 ldc2_w (1, 4)
	104 1e-10 (1, 4)
	106 dcmpg (1, 4)
	107 ifge (1, 4)
	108 9 (1, 4)
	110 ldc2_w (1, 4)
	111 1e-06 (1, 4)
	113 goto (1, 4)
	114 15 (1, 4)
	116 ldc2_w (1, 4)
	117 0.01 (1, 4)
	119 dload (1, 4)
	120 #12 (1, 4)
	121 dload (1, 4)
	122 #14 (1, 4)
	123 ddiv (1, 4)
	124 invokestatic (1, 4)
	125 org/apache/commons/math3/util/FastMath.sqrt:(D)D (1, 4)
	127 dmul (1, 4)
	128 dstore (1, 4)
	129 #16 (1, 4)
	130 iload_1 (2, 1)
	131 ifne (2, 1)
	132 8 (2, 1)
	134 dload (2, 1)
	135 #16 (2, 1)
	136 dneg (2, 1)
	137 dstore (2, 1)
	138 #16 (2, 1)
	139 iconst_0 (3, 4)
	140 istore (3, 4)
	141 #18 (3, 4)
	142 iload (3, 4)
	143 #18 (3, 4)
	144 aload (3, 4)
	145 #6 (3, 4)
	146 arraylength (3, 4)
	147 if_icmpge (3, 4)
	148 28 (3, 4)
	150 aload (3, 4)
	151 #8 (3, 4)
	152 iload (3, 4)
	153 #18 (3, 4)
	154 aload (3, 4)
	155 #6 (3, 4)
	156 iload (3, 4)
	157 #18 (3, 4)
	158 daload (3, 4)
	159 dload (3, 4)
	160 #16 (3, 4)
	161 aload (3, 4)
	162 #7 (3, 4)
	163 iload (3, 4)
	164 #18 (3, 4)
	165 daload (3, 4)
	166 dmul (3, 4)
	167 dadd (3, 4)
	168 dastore (3, 4)
	169 iinc (3, 4)
	170 #18 (3, 4)
	171 -89 (3, 4)
	172 goto (3, 4)
	173 -30 (3, 4)
	175 aload_0 (2, 4)
	176 dload (2, 4)
	177 #4 (2, 4)
	178 dload (2, 4)
	179 #16 (2, 4)
	180 dadd (2, 4)
	181 aload (2, 4)
	182 #8 (2, 4)
	183 aload (2, 4)
	184 #9 (2, 4)
	185 invokevirtual (2, 4)
	186 org/apache/commons/math3/ode/nonstiff/AdaptiveStepsizeIntegrator.computeDerivatives:(D[D[D)V (2, 4)
	188 dconst_0 (2, 4)
	189 dstore (2, 4)
	190 #18 (2, 4)
	191 iconst_0 (3, 4)
	192 istore (3, 4)
	193 #20 (3, 4)
	194 iload (3, 4)
	195 #20 (3, 4)
	196 aload_3 (3, 4)
	197 arraylength (3, 4)
	198 if_icmpge (3, 4)
	199 37 (3, 4)
	201 aload (3, 4)
	202 #9 (3, 4)
	203 iload (3, 4)
	204 #20 (3, 4)
	205 daload (3, 4)
	206 aload (3, 4)
	207 #7 (3, 4)
	208 iload (3, 4)
	209 #20 (3, 4)
	210 daload (3, 4)
	211 dsub (3, 4)
	212 aload_3 (3, 4)
	213 iload (3, 4)
	214 #20 (3, 4)
	215 daload (3, 4)
	216 ddiv (3, 4)
	217 dstore (3, 4)
	218 #10 (3, 4)
	219 dload (3, 4)
	220 #18 (3, 4)
	221 dload (3, 4)
	222 #10 (3, 4)
	223 dload (3, 4)
	224 #10 (3, 4)
	225 dmul (3, 4)
	226 dadd (3, 4)
	227 dstore (3, 4)
	228 #18 (3, 4)
	229 iinc (3, 4)
	230 #20 (3, 4)
	231 -89 (3, 4)
	232 goto (3, 4)
	233 -38 (3, 4)
	235 dload (2, 4)
	236 #18 (2, 4)
	237 invokestatic (2, 4)
	238 org/apache/commons/math3/util/FastMath.sqrt:(D)D (2, 4)
	240 dload (2, 4)
	241 #16 (2, 4)
	242 ddiv (2, 4)
	243 dstore (2, 4)
	244 #18 (2, 4)
	245 dload (2, 4)
	246 #14 (2, 4)
	247 invokestatic (2, 4)
	248 org/apache/commons/math3/util/FastMath.sqrt:(D)D (2, 4)
	250 dload (2, 4)
	251 #18 (2, 4)
	252 invokestatic (2, 4)
	253 org/apache/commons/math3/util/FastMath.max:(DD)D (2, 4)
	255 dstore (2, 4)
	256 #20 (2, 4)
	257 dload (2, 4)
	258 #20 (2, 4)
	259 ldc2_w (2, 4)
	260 1e-15 (2, 4)
	262 dcmpg (2, 4)
	263 ifge (2, 4)
	264 21 (2, 4)
	266 ldc2_w (2, 4)
	267 1e-06 (2, 4)
	269 ldc2_w (2, 4)
	270 0.001 (2, 4)
	272 dload (2, 4)
	273 #16 (2, 4)
	274 invokestatic (2, 4)
	275 org/apache/commons/math3/util/FastMath.abs:(D)D (2, 4)
	277 dmul (2, 4)
	278 invokestatic (2, 4)
	279 org/apache/commons/math3/util/FastMath.max:(DD)D (2, 4)
	281 goto (2, 4)
	282 16 (2, 4)
	284 ldc2_w (2, 4)
	285 0.01 (2, 4)
	287 dload (2, 4)
	288 #20 (2, 4)
	289 ddiv (2, 4)
	290 dconst_1 (2, 4)
	291 iload_2 (2, 4)
	292 i2d (2, 4)
	293 ddiv (2, 4)
	294 invokestatic (2, 4)
	295 org/apache/commons/math3/util/FastMath.pow:(DD)D (2, 4)
	297 dstore (2, 4)
	298 #22 (2, 4)
	299 ldc2_w (2, 4)
	300 100.0 (2, 4)
	302 dload (2, 4)
	303 #16 (2, 4)
	304 invokestatic (2, 4)
	305 org/apache/commons/math3/util/FastMath.abs:(D)D (2, 4)
	307 dmul (2, 4)
	308 dload (2, 4)
	309 #22 (2, 4)
	310 invokestatic (2, 4)
	311 org/apache/commons/math3/util/FastMath.min:(DD)D (2, 4)
	313 dstore (2, 4)
	314 #16 (2, 4)
	315 dload (2, 4)
	316 #16 (2, 4)
	317 ldc2_w (2, 4)
	318 1e-12 (2, 4)
	320 dload (2, 4)
	321 #4 (2, 4)
	322 invokestatic (2, 4)
	323 org/apache/commons/math3/util/FastMath.abs:(D)D (2, 4)
	325 dmul (2, 4)
	326 invokestatic (2, 4)
	327 org/apache/commons/math3/util/FastMath.max:(DD)D (2, 4)
	329 dstore (2, 4)
	330 #16 (2, 4)
	331 dload (3, 1)
	332 #16 (3, 1)
	333 aload_0 (3, 1)
	334 invokevirtual (3, 1)
	335 org/apache/commons/math3/ode/nonstiff/AdaptiveStepsizeIntegrator.getMinStep:()D (3, 1)
	337 dcmpg (3, 1)
	338 ifge (3, 1)
	339 9 (3, 1)
	341 aload_0 (3, 1)
	342 invokevirtual (3, 1)
	343 org/apache/commons/math3/ode/nonstiff/AdaptiveStepsizeIntegrator.getMinStep:()D (3, 1)
	345 dstore (3, 1)
	346 #16 (3, 1)
	347 dload (3, 1)
	348 #16 (3, 1)
	349 aload_0 (3, 1)
	350 invokevirtual (3, 1)
	351 org/apache/commons/math3/ode/nonstiff/AdaptiveStepsizeIntegrator.getMaxStep:()D (3, 1)
	353 dcmpl (3, 1)
	354 ifle (3, 1)
	355 9 (3, 1)
	357 aload_0 (3, 1)
	358 invokevirtual (3, 1)
	359 org/apache/commons/math3/ode/nonstiff/AdaptiveStepsizeIntegrator.getMaxStep:()D (3, 1)
	361 dstore (3, 1)
	362 #16 (3, 1)
	363 iload_1 (3, 1)
	364 ifne (3, 1)
	365 8 (3, 1)
	367 dload (3, 1)
	368 #16 (3, 1)
	369 dneg (3, 1)
	370 dstore (3, 1)
	371 #16 (3, 1)
	372 dload (2, 4)
	373 #16 (2, 4)
	374 dreturn (0, 4)

Method: filterStep
	0 dload_1 (0, 0)
	1 dstore (0, 0)
	2 #5 (0, 0)
	3 dload_1 (1, 1)
	4 invokestatic (1, 1)
	5 org/apache/commons/math3/util/FastMath.abs:(D)D (1, 1)
	7 aload_0 (1, 1)
	8 getfield (1, 1)
	9 org/apache/commons/math3/ode/nonstiff/AdaptiveStepsizeIntegrator.minStep:D (1, 1)
	11 dcmpg (1, 1)
	12 ifge (1, 1)
	13 55 (1, 1)
	15 iload (2, 1)
	16 #4 (2, 1)
	17 ifeq (2, 1)
	18 24 (2, 1)
	20 iload_3 (3, 4)
	21 ifeq (3, 4)
	22 10 (3, 4)
	24 aload_0 (3, 4)
	25 getfield (3, 4)
	26 org/apache/commons/math3/ode/nonstiff/AdaptiveStepsizeIntegrator.minStep:D (3, 4)
	28 goto (3, 4)
	29 8 (3, 4)
	31 aload_0 (3, 4)
	32 getfield (3, 4)
	33 org/apache/commons/math3/ode/nonstiff/AdaptiveStepsizeIntegrator.minStep:D (3, 4)
	35 dneg (3, 4)
	36 dstore (3, 4)
	37 #5 (3, 4)
	38 goto (3, 4)
	39 29 (3, 4)
	41 new (4, 2)
	42 org/apache/commons/math3/exception/NumberIsTooSmallException (4, 2)
	44 dup (4, 2)
	45 getstatic (4, 2)
	46 org/apache/commons/math3/exception/util/LocalizedFormats.MINIMAL_STEPSIZE_REACHED_DURING_INTEGRATION:Lorg/apache/commons/math3/exception/util/LocalizedFormats; (4, 2)
	48 dload_1 (4, 2)
	49 invokestatic (4, 2)
	50 org/apache/commons/math3/util/FastMath.abs:(D)D (4, 2)
	52 invokestatic (4, 2)
	53 java/lang/Double.valueOf:(D)Ljava/lang/Double; (4, 2)
	55 aload_0 (4, 2)
	56 getfield (4, 2)
	57 org/apache/commons/math3/ode/nonstiff/AdaptiveStepsizeIntegrator.minStep:D (4, 2)
	59 invokestatic (4, 2)
	60 java/lang/Double.valueOf:(D)Ljava/lang/Double; (4, 2)
	62 iconst_1 (4, 2)
	63 invokespecial (4, 2)
	64 org/apache/commons/math3/exception/NumberIsTooSmallException.<init>:(Lorg/apache/commons/math3/exception/util/Localizable;Ljava/lang/Number;Ljava/lang/Number;Z)V (4, 2)
	66 athrow (4, 2)
	67 dload (1, 1)
	68 #5 (1, 1)
	69 aload_0 (1, 1)
	70 getfield (1, 1)
	71 org/apache/commons/math3/ode/nonstiff/AdaptiveStepsizeIntegrator.maxStep:D (1, 1)
	73 dcmpl (1, 1)
	74 ifle (1, 1)
	75 12 (1, 1)
	77 aload_0 (1, 1)
	78 getfield (1, 1)
	79 org/apache/commons/math3/ode/nonstiff/AdaptiveStepsizeIntegrator.maxStep:D (1, 1)
	81 dstore (1, 1)
	82 #5 (1, 1)
	83 goto (1, 1)
	84 21 (1, 1)
	86 dload (2, 1)
	87 #5 (2, 1)
	88 aload_0 (2, 1)
	89 getfield (2, 1)
	90 org/apache/commons/math3/ode/nonstiff/AdaptiveStepsizeIntegrator.maxStep:D (2, 1)
	92 dneg (2, 1)
	93 dcmpg (2, 1)
	94 ifge (2, 1)
	95 10 (2, 1)
	97 aload_0 (2, 1)
	98 getfield (2, 1)
	99 org/apache/commons/math3/ode/nonstiff/AdaptiveStepsizeIntegrator.maxStep:D (2, 1)
	101 dneg (2, 1)
	102 dstore (2, 1)
	103 #5 (2, 1)
	104 dload (0, 0)
	105 #5 (0, 0)
	106 dreturn (0, 0)

Method: getCurrentStepStart
	0 aload_0 (0, 0)
	1 getfield (0, 0)
	2 org/apache/commons/math3/ode/nonstiff/AdaptiveStepsizeIntegrator.stepStart:D (0, 0)
	4 dreturn (0, 0)

Method: resetInternalState
	0 aload_0 (0, 0)
	1 ldc2_w (0, 0)
	2 nan (0, 0)
	4 putfield (0, 0)
	5 org/apache/commons/math3/ode/nonstiff/AdaptiveStepsizeIntegrator.stepStart:D (0, 0)
	7 aload_0 (0, 0)
	8 aload_0 (0, 0)
	9 getfield (0, 0)
	10 org/apache/commons/math3/ode/nonstiff/AdaptiveStepsizeIntegrator.minStep:D (0, 0)
	12 aload_0 (0, 0)
	13 getfield (0, 0)
	14 org/apache/commons/math3/ode/nonstiff/AdaptiveStepsizeIntegrator.maxStep:D (0, 0)
	16 dmul (0, 0)
	17 invokestatic (0, 0)
	18 org/apache/commons/math3/util/FastMath.sqrt:(D)D (0, 0)
	20 putfield (0, 0)
	21 org/apache/commons/math3/ode/nonstiff/AdaptiveStepsizeIntegrator.stepSize:D (0, 0)
	23 return (0, 0)

Method: getMinStep
	0 aload_0 (0, 0)
	1 getfield (0, 0)
	2 org/apache/commons/math3/ode/nonstiff/AdaptiveStepsizeIntegrator.minStep:D (0, 0)
	4 dreturn (0, 0)

Method: getMaxStep
	0 aload_0 (0, 0)
	1 getfield (0, 0)
	2 org/apache/commons/math3/ode/nonstiff/AdaptiveStepsizeIntegrator.maxStep:D (0, 0)
	4 dreturn (0, 0)

