Method: <init>
	0 aload_0 (0, 4)
	1 aload_1 (0, 4)
	2 iload_2 (0, 4)
	3 aload_3 (0, 4)
	4 aload (0, 4)
	6 aload (0, 4)
	8 aload (0, 4)
	10 aload (0, 4)
	12 aload (0, 4)
	14 invokespecial (0, 4)
	17 aload_0 (0, 4)
	18 aload_1 (0, 4)
	19 bipush (0, 4)
	21 bipush (0, 4)
	23 invokestatic (0, 4)
	26 checkcast (0, 4)
	29 putfield (0, 4)
	32 aload_0 (0, 4)
	33 getfield (0, 4)
	36 iconst_0 (0, 4)
	37 aaload (0, 4)
	38 iconst_0 (0, 4)
	39 aload_0 (0, 4)
	40 aload_1 (0, 4)
	41 ldc2_w (0, 4)
	44 ldc2_w (0, 4)
	47 invokespecial (0, 4)
	50 aastore (0, 4)
	51 aload_0 (0, 4)
	52 getfield (0, 4)
	55 iconst_0 (0, 4)
	56 aaload (0, 4)
	57 iconst_1 (0, 4)
	58 aload_1 (0, 4)
	59 invokeinterface (0, 4)
	64 checkcast (0, 4)
	67 aastore (0, 4)
	68 aload_0 (0, 4)
	69 getfield (0, 4)
	72 iconst_0 (0, 4)
	73 aaload (0, 4)
	74 iconst_2 (0, 4)
	75 aload_1 (0, 4)
	76 invokeinterface (0, 4)
	81 checkcast (0, 4)
	84 aastore (0, 4)
	85 aload_0 (0, 4)
	86 getfield (0, 4)
	89 iconst_0 (0, 4)
	90 aaload (0, 4)
	91 iconst_3 (0, 4)
	92 aload_1 (0, 4)
	93 invokeinterface (0, 4)
	98 checkcast (0, 4)
	101 aastore (0, 4)
	102 aload_0 (0, 4)
	103 getfield (0, 4)
	106 iconst_0 (0, 4)
	107 aaload (0, 4)
	108 iconst_4 (0, 4)
	109 aload_1 (0, 4)
	110 invokeinterface (0, 4)
	115 checkcast (0, 4)
	118 aastore (0, 4)
	119 aload_0 (0, 4)
	120 getfield (0, 4)
	123 iconst_0 (0, 4)
	124 aaload (0, 4)
	125 iconst_5 (0, 4)
	126 aload_0 (0, 4)
	127 aload_1 (0, 4)
	128 ldc2_w (0, 4)
	131 ldc2_w (0, 4)
	134 invokespecial (0, 4)
	137 aastore (0, 4)
	138 aload_0 (0, 4)
	139 getfield (0, 4)
	142 iconst_0 (0, 4)
	143 aaload (0, 4)
	144 bipush (0, 4)
	146 aload_0 (0, 4)
	147 aload_1 (0, 4)
	148 ldc2_w (0, 4)
	151 ldc2_w (0, 4)
	154 invokespecial (0, 4)
	157 aastore (0, 4)
	158 aload_0 (0, 4)
	159 getfield (0, 4)
	162 iconst_0 (0, 4)
	163 aaload (0, 4)
	164 bipush (0, 4)
	166 aload_0 (0, 4)
	167 aload_1 (0, 4)
	168 ldc2_w (0, 4)
	171 ldc2_w (0, 4)
	174 invokespecial (0, 4)
	177 aastore (0, 4)
	178 aload_0 (0, 4)
	179 getfield (0, 4)
	182 iconst_0 (0, 4)
	183 aaload (0, 4)
	184 bipush (0, 4)
	186 aload_0 (0, 4)
	187 aload_1 (0, 4)
	188 ldc2_w (0, 4)
	191 ldc2_w (0, 4)
	194 invokespecial (0, 4)
	197 aastore (0, 4)
	198 aload_0 (0, 4)
	199 getfield (0, 4)
	202 iconst_0 (0, 4)
	203 aaload (0, 4)
	204 bipush (0, 4)
	206 aload_0 (0, 4)
	207 aload_1 (0, 4)
	208 ldc2_w (0, 4)
	211 ldc2_w (0, 4)
	214 invokespecial (0, 4)
	217 aastore (0, 4)
	218 aload_0 (0, 4)
	219 getfield (0, 4)
	222 iconst_0 (0, 4)
	223 aaload (0, 4)
	224 bipush (0, 4)
	226 aload_0 (0, 4)
	227 aload_1 (0, 4)
	228 ldc2_w (0, 4)
	231 ldc2_w (0, 4)
	234 invokespecial (0, 4)
	237 aastore (0, 4)
	238 aload_0 (0, 4)
	239 getfield (0, 4)
	242 iconst_0 (0, 4)
	243 aaload (0, 4)
	244 bipush (0, 4)
	246 aload_0 (0, 4)
	247 aload_1 (0, 4)
	248 ldc2_w (0, 4)
	251 ldc2_w (0, 4)
	254 invokespecial (0, 4)
	257 aastore (0, 4)
	258 aload_0 (0, 4)
	259 getfield (0, 4)
	262 iconst_0 (0, 4)
	263 aaload (0, 4)
	264 bipush (0, 4)
	266 aload_1 (0, 4)
	267 invokeinterface (0, 4)
	272 checkcast (0, 4)
	275 aastore (0, 4)
	276 aload_0 (0, 4)
	277 getfield (0, 4)
	280 iconst_0 (0, 4)
	281 aaload (0, 4)
	282 bipush (0, 4)
	284 aload_1 (0, 4)
	285 invokeinterface (0, 4)
	290 checkcast (0, 4)
	293 aastore (0, 4)
	294 aload_0 (0, 4)
	295 getfield (0, 4)
	298 iconst_0 (0, 4)
	299 aaload (0, 4)
	300 bipush (0, 4)
	302 aload_1 (0, 4)
	303 invokeinterface (0, 4)
	308 checkcast (0, 4)
	311 aastore (0, 4)
	312 aload_0 (0, 4)
	313 getfield (0, 4)
	316 iconst_0 (0, 4)
	317 aaload (0, 4)
	318 bipush (0, 4)
	320 aload_1 (0, 4)
	321 invokeinterface (0, 4)
	326 checkcast (0, 4)
	329 aastore (0, 4)
	330 aload_0 (0, 4)
	331 getfield (0, 4)
	334 iconst_1 (0, 4)
	335 aaload (0, 4)
	336 iconst_0 (0, 4)
	337 aload_0 (0, 4)
	338 getfield (0, 4)
	341 iconst_0 (0, 4)
	342 aaload (0, 4)
	343 iconst_0 (0, 4)
	344 aaload (0, 4)
	345 invokeinterface (0, 4)
	350 checkcast (0, 4)
	353 dconst_1 (0, 4)
	354 invokeinterface (0, 4)
	359 checkcast (0, 4)
	362 aastore (0, 4)
	363 aload_0 (0, 4)
	364 getfield (0, 4)
	367 iconst_1 (0, 4)
	368 aaload (0, 4)
	369 iconst_1 (0, 4)
	370 aload_0 (0, 4)
	371 getfield (0, 4)
	374 iconst_0 (0, 4)
	375 aaload (0, 4)
	376 iconst_1 (0, 4)
	377 aaload (0, 4)
	378 invokeinterface (0, 4)
	383 checkcast (0, 4)
	386 aastore (0, 4)
	387 aload_0 (0, 4)
	388 getfield (0, 4)
	391 iconst_1 (0, 4)
	392 aaload (0, 4)
	393 iconst_2 (0, 4)
	394 aload_0 (0, 4)
	395 getfield (0, 4)
	398 iconst_0 (0, 4)
	399 aaload (0, 4)
	400 iconst_2 (0, 4)
	401 aaload (0, 4)
	402 invokeinterface (0, 4)
	407 checkcast (0, 4)
	410 aastore (0, 4)
	411 aload_0 (0, 4)
	412 getfield (0, 4)
	415 iconst_1 (0, 4)
	416 aaload (0, 4)
	417 iconst_3 (0, 4)
	418 aload_0 (0, 4)
	419 getfield (0, 4)
	422 iconst_0 (0, 4)
	423 aaload (0, 4)
	424 iconst_3 (0, 4)
	425 aaload (0, 4)
	426 invokeinterface (0, 4)
	431 checkcast (0, 4)
	434 aastore (0, 4)
	435 aload_0 (0, 4)
	436 getfield (0, 4)
	439 iconst_1 (0, 4)
	440 aaload (0, 4)
	441 iconst_4 (0, 4)
	442 aload_0 (0, 4)
	443 getfield (0, 4)
	446 iconst_0 (0, 4)
	447 aaload (0, 4)
	448 iconst_4 (0, 4)
	449 aaload (0, 4)
	450 invokeinterface (0, 4)
	455 checkcast (0, 4)
	458 aastore (0, 4)
	459 aload_0 (0, 4)
	460 getfield (0, 4)
	463 iconst_1 (0, 4)
	464 aaload (0, 4)
	465 iconst_5 (0, 4)
	466 aload_0 (0, 4)
	467 getfield (0, 4)
	470 iconst_0 (0, 4)
	471 aaload (0, 4)
	472 iconst_5 (0, 4)
	473 aaload (0, 4)
	474 invokeinterface (0, 4)
	479 checkcast (0, 4)
	482 aastore (0, 4)
	483 aload_0 (0, 4)
	484 getfield (0, 4)
	487 iconst_1 (0, 4)
	488 aaload (0, 4)
	489 bipush (0, 4)
	491 aload_0 (0, 4)
	492 getfield (0, 4)
	495 iconst_0 (0, 4)
	496 aaload (0, 4)
	497 bipush (0, 4)
	499 aaload (0, 4)
	500 invokeinterface (0, 4)
	505 checkcast (0, 4)
	508 aastore (0, 4)
	509 aload_0 (0, 4)
	510 getfield (0, 4)
	513 iconst_1 (0, 4)
	514 aaload (0, 4)
	515 bipush (0, 4)
	517 aload_0 (0, 4)
	518 getfield (0, 4)
	521 iconst_0 (0, 4)
	522 aaload (0, 4)
	523 bipush (0, 4)
	525 aaload (0, 4)
	526 invokeinterface (0, 4)
	531 checkcast (0, 4)
	534 aastore (0, 4)
	535 aload_0 (0, 4)
	536 getfield (0, 4)
	539 iconst_1 (0, 4)
	540 aaload (0, 4)
	541 bipush (0, 4)
	543 aload_0 (0, 4)
	544 getfield (0, 4)
	547 iconst_0 (0, 4)
	548 aaload (0, 4)
	549 bipush (0, 4)
	551 aaload (0, 4)
	552 invokeinterface (0, 4)
	557 checkcast (0, 4)
	560 aastore (0, 4)
	561 aload_0 (0, 4)
	562 getfield (0, 4)
	565 iconst_1 (0, 4)
	566 aaload (0, 4)
	567 bipush (0, 4)
	569 aload_0 (0, 4)
	570 getfield (0, 4)
	573 iconst_0 (0, 4)
	574 aaload (0, 4)
	575 bipush (0, 4)
	577 aaload (0, 4)
	578 invokeinterface (0, 4)
	583 checkcast (0, 4)
	586 aastore (0, 4)
	587 aload_0 (0, 4)
	588 getfield (0, 4)
	591 iconst_1 (0, 4)
	592 aaload (0, 4)
	593 bipush (0, 4)
	595 aload_0 (0, 4)
	596 getfield (0, 4)
	599 iconst_0 (0, 4)
	600 aaload (0, 4)
	601 bipush (0, 4)
	603 aaload (0, 4)
	604 invokeinterface (0, 4)
	609 checkcast (0, 4)
	612 aastore (0, 4)
	613 aload_0 (0, 4)
	614 getfield (0, 4)
	617 iconst_1 (0, 4)
	618 aaload (0, 4)
	619 bipush (0, 4)
	621 aload_0 (0, 4)
	622 getfield (0, 4)
	625 iconst_0 (0, 4)
	626 aaload (0, 4)
	627 bipush (0, 4)
	629 aaload (0, 4)
	630 invokeinterface (0, 4)
	635 checkcast (0, 4)
	638 aastore (0, 4)
	639 aload_0 (0, 4)
	640 getfield (0, 4)
	643 iconst_1 (0, 4)
	644 aaload (0, 4)
	645 bipush (0, 4)
	647 aload_0 (0, 4)
	648 getfield (0, 4)
	651 iconst_0 (0, 4)
	652 aaload (0, 4)
	653 bipush (0, 4)
	655 aaload (0, 4)
	656 invokeinterface (0, 4)
	661 checkcast (0, 4)
	664 aastore (0, 4)
	665 aload_0 (0, 4)
	666 getfield (0, 4)
	669 iconst_1 (0, 4)
	670 aaload (0, 4)
	671 bipush (0, 4)
	673 aload_0 (0, 4)
	674 getfield (0, 4)
	677 iconst_0 (0, 4)
	678 aaload (0, 4)
	679 bipush (0, 4)
	681 aaload (0, 4)
	682 invokeinterface (0, 4)
	687 checkcast (0, 4)
	690 aastore (0, 4)
	691 aload_0 (0, 4)
	692 getfield (0, 4)
	695 iconst_1 (0, 4)
	696 aaload (0, 4)
	697 bipush (0, 4)
	699 aload_0 (0, 4)
	700 getfield (0, 4)
	703 iconst_0 (0, 4)
	704 aaload (0, 4)
	705 bipush (0, 4)
	707 aaload (0, 4)
	708 invokeinterface (0, 4)
	713 checkcast (0, 4)
	716 aastore (0, 4)
	717 aload_0 (0, 4)
	718 getfield (0, 4)
	721 iconst_1 (0, 4)
	722 aaload (0, 4)
	723 bipush (0, 4)
	725 aload_0 (0, 4)
	726 getfield (0, 4)
	729 iconst_0 (0, 4)
	730 aaload (0, 4)
	731 bipush (0, 4)
	733 aaload (0, 4)
	734 invokeinterface (0, 4)
	739 checkcast (0, 4)
	742 aastore (0, 4)
	743 aload_0 (0, 4)
	744 getfield (0, 4)
	747 iconst_2 (0, 4)
	748 aaload (0, 4)
	749 iconst_0 (0, 4)
	750 aload_0 (0, 4)
	751 getfield (0, 4)
	754 iconst_0 (0, 4)
	755 aaload (0, 4)
	756 iconst_0 (0, 4)
	757 aaload (0, 4)
	758 iconst_2 (0, 4)
	759 invokeinterface (0, 4)
	764 checkcast (0, 4)
	767 dconst_1 (0, 4)
	768 invokeinterface (0, 4)
	773 checkcast (0, 4)
	776 aastore (0, 4)
	777 aload_0 (0, 4)
	778 getfield (0, 4)
	781 iconst_2 (0, 4)
	782 aaload (0, 4)
	783 iconst_1 (0, 4)
	784 aload_0 (0, 4)
	785 getfield (0, 4)
	788 iconst_0 (0, 4)
	789 aaload (0, 4)
	790 iconst_1 (0, 4)
	791 aaload (0, 4)
	792 iconst_2 (0, 4)
	793 invokeinterface (0, 4)
	798 checkcast (0, 4)
	801 aastore (0, 4)
	802 aload_0 (0, 4)
	803 getfield (0, 4)
	806 iconst_2 (0, 4)
	807 aaload (0, 4)
	808 iconst_2 (0, 4)
	809 aload_0 (0, 4)
	810 getfield (0, 4)
	813 iconst_0 (0, 4)
	814 aaload (0, 4)
	815 iconst_2 (0, 4)
	816 aaload (0, 4)
	817 iconst_2 (0, 4)
	818 invokeinterface (0, 4)
	823 checkcast (0, 4)
	826 aastore (0, 4)
	827 aload_0 (0, 4)
	828 getfield (0, 4)
	831 iconst_2 (0, 4)
	832 aaload (0, 4)
	833 iconst_3 (0, 4)
	834 aload_0 (0, 4)
	835 getfield (0, 4)
	838 iconst_0 (0, 4)
	839 aaload (0, 4)
	840 iconst_3 (0, 4)
	841 aaload (0, 4)
	842 iconst_2 (0, 4)
	843 invokeinterface (0, 4)
	848 checkcast (0, 4)
	851 aastore (0, 4)
	852 aload_0 (0, 4)
	853 getfield (0, 4)
	856 iconst_2 (0, 4)
	857 aaload (0, 4)
	858 iconst_4 (0, 4)
	859 aload_0 (0, 4)
	860 getfield (0, 4)
	863 iconst_0 (0, 4)
	864 aaload (0, 4)
	865 iconst_4 (0, 4)
	866 aaload (0, 4)
	867 iconst_2 (0, 4)
	868 invokeinterface (0, 4)
	873 checkcast (0, 4)
	876 aastore (0, 4)
	877 aload_0 (0, 4)
	878 getfield (0, 4)
	881 iconst_2 (0, 4)
	882 aaload (0, 4)
	883 iconst_5 (0, 4)
	884 aload_0 (0, 4)
	885 getfield (0, 4)
	888 iconst_0 (0, 4)
	889 aaload (0, 4)
	890 iconst_5 (0, 4)
	891 aaload (0, 4)
	892 iconst_2 (0, 4)
	893 invokeinterface (0, 4)
	898 checkcast (0, 4)
	901 aastore (0, 4)
	902 aload_0 (0, 4)
	903 getfield (0, 4)
	906 iconst_2 (0, 4)
	907 aaload (0, 4)
	908 bipush (0, 4)
	910 aload_0 (0, 4)
	911 getfield (0, 4)
	914 iconst_0 (0, 4)
	915 aaload (0, 4)
	916 bipush (0, 4)
	918 aaload (0, 4)
	919 iconst_2 (0, 4)
	920 invokeinterface (0, 4)
	925 checkcast (0, 4)
	928 aastore (0, 4)
	929 aload_0 (0, 4)
	930 getfield (0, 4)
	933 iconst_2 (0, 4)
	934 aaload (0, 4)
	935 bipush (0, 4)
	937 aload_0 (0, 4)
	938 getfield (0, 4)
	941 iconst_0 (0, 4)
	942 aaload (0, 4)
	943 bipush (0, 4)
	945 aaload (0, 4)
	946 iconst_2 (0, 4)
	947 invokeinterface (0, 4)
	952 checkcast (0, 4)
	955 aastore (0, 4)
	956 aload_0 (0, 4)
	957 getfield (0, 4)
	960 iconst_2 (0, 4)
	961 aaload (0, 4)
	962 bipush (0, 4)
	964 aload_0 (0, 4)
	965 getfield (0, 4)
	968 iconst_0 (0, 4)
	969 aaload (0, 4)
	970 bipush (0, 4)
	972 aaload (0, 4)
	973 iconst_2 (0, 4)
	974 invokeinterface (0, 4)
	979 checkcast (0, 4)
	982 aastore (0, 4)
	983 aload_0 (0, 4)
	984 getfield (0, 4)
	987 iconst_2 (0, 4)
	988 aaload (0, 4)
	989 bipush (0, 4)
	991 aload_0 (0, 4)
	992 getfield (0, 4)
	995 iconst_0 (0, 4)
	996 aaload (0, 4)
	997 bipush (0, 4)
	999 aaload (0, 4)
	1000 iconst_2 (0, 4)
	1001 invokeinterface (0, 4)
	1006 checkcast (0, 4)
	1009 aastore (0, 4)
	1010 aload_0 (0, 4)
	1011 getfield (0, 4)
	1014 iconst_2 (0, 4)
	1015 aaload (0, 4)
	1016 bipush (0, 4)
	1018 aload_0 (0, 4)
	1019 getfield (0, 4)
	1022 iconst_0 (0, 4)
	1023 aaload (0, 4)
	1024 bipush (0, 4)
	1026 aaload (0, 4)
	1027 iconst_2 (0, 4)
	1028 invokeinterface (0, 4)
	1033 checkcast (0, 4)
	1036 aastore (0, 4)
	1037 aload_0 (0, 4)
	1038 getfield (0, 4)
	1041 iconst_2 (0, 4)
	1042 aaload (0, 4)
	1043 bipush (0, 4)
	1045 aload_0 (0, 4)
	1046 getfield (0, 4)
	1049 iconst_0 (0, 4)
	1050 aaload (0, 4)
	1051 bipush (0, 4)
	1053 aaload (0, 4)
	1054 iconst_2 (0, 4)
	1055 invokeinterface (0, 4)
	1060 checkcast (0, 4)
	1063 aastore (0, 4)
	1064 aload_0 (0, 4)
	1065 getfield (0, 4)
	1068 iconst_2 (0, 4)
	1069 aaload (0, 4)
	1070 bipush (0, 4)
	1072 aload_0 (0, 4)
	1073 getfield (0, 4)
	1076 iconst_0 (0, 4)
	1077 aaload (0, 4)
	1078 bipush (0, 4)
	1080 aaload (0, 4)
	1081 iconst_2 (0, 4)
	1082 invokeinterface (0, 4)
	1087 checkcast (0, 4)
	1090 dconst_1 (0, 4)
	1091 invokeinterface (0, 4)
	1096 checkcast (0, 4)
	1099 aastore (0, 4)
	1100 aload_0 (0, 4)
	1101 getfield (0, 4)
	1104 iconst_2 (0, 4)
	1105 aaload (0, 4)
	1106 bipush (0, 4)
	1108 aload_0 (0, 4)
	1109 getfield (0, 4)
	1112 iconst_0 (0, 4)
	1113 aaload (0, 4)
	1114 bipush (0, 4)
	1116 aaload (0, 4)
	1117 iconst_2 (0, 4)
	1118 invokeinterface (0, 4)
	1123 checkcast (0, 4)
	1126 aastore (0, 4)
	1127 aload_0 (0, 4)
	1128 getfield (0, 4)
	1131 iconst_2 (0, 4)
	1132 aaload (0, 4)
	1133 bipush (0, 4)
	1135 aload_0 (0, 4)
	1136 getfield (0, 4)
	1139 iconst_0 (0, 4)
	1140 aaload (0, 4)
	1141 bipush (0, 4)
	1143 aaload (0, 4)
	1144 iconst_2 (0, 4)
	1145 invokeinterface (0, 4)
	1150 checkcast (0, 4)
	1153 aastore (0, 4)
	1154 aload_0 (0, 4)
	1155 getfield (0, 4)
	1158 iconst_2 (0, 4)
	1159 aaload (0, 4)
	1160 bipush (0, 4)
	1162 aload_0 (0, 4)
	1163 getfield (0, 4)
	1166 iconst_0 (0, 4)
	1167 aaload (0, 4)
	1168 bipush (0, 4)
	1170 aaload (0, 4)
	1171 iconst_2 (0, 4)
	1172 invokeinterface (0, 4)
	1177 checkcast (0, 4)
	1180 aastore (0, 4)
	1181 aload_0 (0, 4)
	1182 getfield (0, 4)
	1185 iconst_3 (0, 4)
	1186 aaload (0, 4)
	1187 iconst_0 (0, 4)
	1188 aload_0 (0, 4)
	1189 aload_1 (0, 4)
	1190 ldc2_w (0, 4)
	1193 ldc2_w (0, 4)
	1196 invokespecial (0, 4)
	1199 aastore (0, 4)
	1200 aload_0 (0, 4)
	1201 getfield (0, 4)
	1204 iconst_3 (0, 4)
	1205 aaload (0, 4)
	1206 iconst_1 (0, 4)
	1207 aload_1 (0, 4)
	1208 invokeinterface (0, 4)
	1213 checkcast (0, 4)
	1216 aastore (0, 4)
	1217 aload_0 (0, 4)
	1218 getfield (0, 4)
	1221 iconst_3 (0, 4)
	1222 aaload (0, 4)
	1223 iconst_2 (0, 4)
	1224 aload_1 (0, 4)
	1225 invokeinterface (0, 4)
	1230 checkcast (0, 4)
	1233 aastore (0, 4)
	1234 aload_0 (0, 4)
	1235 getfield (0, 4)
	1238 iconst_3 (0, 4)
	1239 aaload (0, 4)
	1240 iconst_3 (0, 4)
	1241 aload_1 (0, 4)
	1242 invokeinterface (0, 4)
	1247 checkcast (0, 4)
	1250 aastore (0, 4)
	1251 aload_0 (0, 4)
	1252 getfield (0, 4)
	1255 iconst_3 (0, 4)
	1256 aaload (0, 4)
	1257 iconst_4 (0, 4)
	1258 aload_1 (0, 4)
	1259 invokeinterface (0, 4)
	1264 checkcast (0, 4)
	1267 aastore (0, 4)
	1268 aload_0 (0, 4)
	1269 getfield (0, 4)
	1272 iconst_3 (0, 4)
	1273 aaload (0, 4)
	1274 iconst_5 (0, 4)
	1275 aload_0 (0, 4)
	1276 aload_1 (0, 4)
	1277 ldc2_w (0, 4)
	1280 ldc2_w (0, 4)
	1283 invokespecial (0, 4)
	1286 aastore (0, 4)
	1287 aload_0 (0, 4)
	1288 getfield (0, 4)
	1291 iconst_3 (0, 4)
	1292 aaload (0, 4)
	1293 bipush (0, 4)
	1295 aload_0 (0, 4)
	1296 aload_1 (0, 4)
	1297 ldc2_w (0, 4)
	1300 ldc2_w (0, 4)
	1303 invokespecial (0, 4)
	1306 aastore (0, 4)
	1307 aload_0 (0, 4)
	1308 getfield (0, 4)
	1311 iconst_3 (0, 4)
	1312 aaload (0, 4)
	1313 bipush (0, 4)
	1315 aload_0 (0, 4)
	1316 aload_1 (0, 4)
	1317 ldc2_w (0, 4)
	1320 ldc2_w (0, 4)
	1323 invokespecial (0, 4)
	1326 aastore (0, 4)
	1327 aload_0 (0, 4)
	1328 getfield (0, 4)
	1331 iconst_3 (0, 4)
	1332 aaload (0, 4)
	1333 bipush (0, 4)
	1335 aload_0 (0, 4)
	1336 aload_1 (0, 4)
	1337 ldc2_w (0, 4)
	1340 ldc2_w (0, 4)
	1343 invokespecial (0, 4)
	1346 aastore (0, 4)
	1347 aload_0 (0, 4)
	1348 getfield (0, 4)
	1351 iconst_3 (0, 4)
	1352 aaload (0, 4)
	1353 bipush (0, 4)
	1355 aload_0 (0, 4)
	1356 aload_1 (0, 4)
	1357 ldc2_w (0, 4)
	1360 ldc2_w (0, 4)
	1363 invokespecial (0, 4)
	1366 aastore (0, 4)
	1367 aload_0 (0, 4)
	1368 getfield (0, 4)
	1371 iconst_3 (0, 4)
	1372 aaload (0, 4)
	1373 bipush (0, 4)
	1375 aload_0 (0, 4)
	1376 aload_1 (0, 4)
	1377 ldc2_w (0, 4)
	1380 ldc2_w (0, 4)
	1383 invokespecial (0, 4)
	1386 aastore (0, 4)
	1387 aload_0 (0, 4)
	1388 getfield (0, 4)
	1391 iconst_3 (0, 4)
	1392 aaload (0, 4)
	1393 bipush (0, 4)
	1395 aload_0 (0, 4)
	1396 aload_1 (0, 4)
	1397 ldc2_w (0, 4)
	1400 ldc2_w (0, 4)
	1403 invokespecial (0, 4)
	1406 aastore (0, 4)
	1407 aload_0 (0, 4)
	1408 getfield (0, 4)
	1411 iconst_3 (0, 4)
	1412 aaload (0, 4)
	1413 bipush (0, 4)
	1415 aload_0 (0, 4)
	1416 aload_1 (0, 4)
	1417 ldc2_w (0, 4)
	1420 ldc2_w (0, 4)
	1423 invokespecial (0, 4)
	1426 aastore (0, 4)
	1427 aload_0 (0, 4)
	1428 getfield (0, 4)
	1431 iconst_3 (0, 4)
	1432 aaload (0, 4)
	1433 bipush (0, 4)
	1435 aload_0 (0, 4)
	1436 aload_1 (0, 4)
	1437 ldc2_w (0, 4)
	1440 ldc2_w (0, 4)
	1443 invokespecial (0, 4)
	1446 aastore (0, 4)
	1447 aload_0 (0, 4)
	1448 getfield (0, 4)
	1451 iconst_3 (0, 4)
	1452 aaload (0, 4)
	1453 bipush (0, 4)
	1455 aload_0 (0, 4)
	1456 aload_1 (0, 4)
	1457 ldc2_w (0, 4)
	1460 ldc2_w (0, 4)
	1463 invokespecial (0, 4)
	1466 aastore (0, 4)
	1467 aload_0 (0, 4)
	1468 getfield (0, 4)
	1471 iconst_3 (0, 4)
	1472 aaload (0, 4)
	1473 bipush (0, 4)
	1475 aload_0 (0, 4)
	1476 aload_1 (0, 4)
	1477 ldc2_w (0, 4)
	1480 ldc2_w (0, 4)
	1483 invokespecial (0, 4)
	1486 aastore (0, 4)
	1487 aload_0 (0, 4)
	1488 getfield (0, 4)
	1491 iconst_4 (0, 4)
	1492 aaload (0, 4)
	1493 iconst_0 (0, 4)
	1494 aload_0 (0, 4)
	1495 aload_1 (0, 4)
	1496 ldc2_w (0, 4)
	1499 ldc2_w (0, 4)
	1502 invokespecial (0, 4)
	1505 aastore (0, 4)
	1506 aload_0 (0, 4)
	1507 getfield (0, 4)
	1510 iconst_4 (0, 4)
	1511 aaload (0, 4)
	1512 iconst_1 (0, 4)
	1513 aload_1 (0, 4)
	1514 invokeinterface (0, 4)
	1519 checkcast (0, 4)
	1522 aastore (0, 4)
	1523 aload_0 (0, 4)
	1524 getfield (0, 4)
	1527 iconst_4 (0, 4)
	1528 aaload (0, 4)
	1529 iconst_2 (0, 4)
	1530 aload_1 (0, 4)
	1531 invokeinterface (0, 4)
	1536 checkcast (0, 4)
	1539 aastore (0, 4)
	1540 aload_0 (0, 4)
	1541 getfield (0, 4)
	1544 iconst_4 (0, 4)
	1545 aaload (0, 4)
	1546 iconst_3 (0, 4)
	1547 aload_1 (0, 4)
	1548 invokeinterface (0, 4)
	1553 checkcast (0, 4)
	1556 aastore (0, 4)
	1557 aload_0 (0, 4)
	1558 getfield (0, 4)
	1561 iconst_4 (0, 4)
	1562 aaload (0, 4)
	1563 iconst_4 (0, 4)
	1564 aload_1 (0, 4)
	1565 invokeinterface (0, 4)
	1570 checkcast (0, 4)
	1573 aastore (0, 4)
	1574 aload_0 (0, 4)
	1575 getfield (0, 4)
	1578 iconst_4 (0, 4)
	1579 aaload (0, 4)
	1580 iconst_5 (0, 4)
	1581 aload_0 (0, 4)
	1582 aload_1 (0, 4)
	1583 ldc2_w (0, 4)
	1586 ldc2_w (0, 4)
	1589 invokespecial (0, 4)
	1592 aastore (0, 4)
	1593 aload_0 (0, 4)
	1594 getfield (0, 4)
	1597 iconst_4 (0, 4)
	1598 aaload (0, 4)
	1599 bipush (0, 4)
	1601 aload_0 (0, 4)
	1602 aload_1 (0, 4)
	1603 ldc2_w (0, 4)
	1606 ldc2_w (0, 4)
	1609 invokespecial (0, 4)
	1612 aastore (0, 4)
	1613 aload_0 (0, 4)
	1614 getfield (0, 4)
	1617 iconst_4 (0, 4)
	1618 aaload (0, 4)
	1619 bipush (0, 4)
	1621 aload_0 (0, 4)
	1622 aload_1 (0, 4)
	1623 ldc2_w (0, 4)
	1626 ldc2_w (0, 4)
	1629 invokespecial (0, 4)
	1632 aastore (0, 4)
	1633 aload_0 (0, 4)
	1634 getfield (0, 4)
	1637 iconst_4 (0, 4)
	1638 aaload (0, 4)
	1639 bipush (0, 4)
	1641 aload_0 (0, 4)
	1642 aload_1 (0, 4)
	1643 ldc2_w (0, 4)
	1646 ldc2_w (0, 4)
	1649 invokespecial (0, 4)
	1652 aastore (0, 4)
	1653 aload_0 (0, 4)
	1654 getfield (0, 4)
	1657 iconst_4 (0, 4)
	1658 aaload (0, 4)
	1659 bipush (0, 4)
	1661 aload_0 (0, 4)
	1662 aload_1 (0, 4)
	1663 ldc2_w (0, 4)
	1666 ldc2_w (0, 4)
	1669 invokespecial (0, 4)
	1672 aastore (0, 4)
	1673 aload_0 (0, 4)
	1674 getfield (0, 4)
	1677 iconst_4 (0, 4)
	1678 aaload (0, 4)
	1679 bipush (0, 4)
	1681 aload_0 (0, 4)
	1682 aload_1 (0, 4)
	1683 ldc2_w (0, 4)
	1686 ldc2_w (0, 4)
	1689 invokespecial (0, 4)
	1692 aastore (0, 4)
	1693 aload_0 (0, 4)
	1694 getfield (0, 4)
	1697 iconst_4 (0, 4)
	1698 aaload (0, 4)
	1699 bipush (0, 4)
	1701 aload_0 (0, 4)
	1702 aload_1 (0, 4)
	1703 ldc2_w (0, 4)
	1706 ldc2_w (0, 4)
	1709 invokespecial (0, 4)
	1712 aastore (0, 4)
	1713 aload_0 (0, 4)
	1714 getfield (0, 4)
	1717 iconst_4 (0, 4)
	1718 aaload (0, 4)
	1719 bipush (0, 4)
	1721 aload_0 (0, 4)
	1722 aload_1 (0, 4)
	1723 ldc2_w (0, 4)
	1726 ldc2_w (0, 4)
	1729 invokespecial (0, 4)
	1732 aastore (0, 4)
	1733 aload_0 (0, 4)
	1734 getfield (0, 4)
	1737 iconst_4 (0, 4)
	1738 aaload (0, 4)
	1739 bipush (0, 4)
	1741 aload_0 (0, 4)
	1742 aload_1 (0, 4)
	1743 ldc2_w (0, 4)
	1746 ldc2_w (0, 4)
	1749 invokespecial (0, 4)
	1752 aastore (0, 4)
	1753 aload_0 (0, 4)
	1754 getfield (0, 4)
	1757 iconst_4 (0, 4)
	1758 aaload (0, 4)
	1759 bipush (0, 4)
	1761 aload_0 (0, 4)
	1762 aload_1 (0, 4)
	1763 ldc2_w (0, 4)
	1766 ldc2_w (0, 4)
	1769 invokespecial (0, 4)
	1772 aastore (0, 4)
	1773 aload_0 (0, 4)
	1774 getfield (0, 4)
	1777 iconst_4 (0, 4)
	1778 aaload (0, 4)
	1779 bipush (0, 4)
	1781 aload_0 (0, 4)
	1782 aload_1 (0, 4)
	1783 ldc2_w (0, 4)
	1786 ldc2_w (0, 4)
	1789 invokespecial (0, 4)
	1792 aastore (0, 4)
	1793 aload_0 (0, 4)
	1794 getfield (0, 4)
	1797 iconst_5 (0, 4)
	1798 aaload (0, 4)
	1799 iconst_0 (0, 4)
	1800 aload_0 (0, 4)
	1801 aload_1 (0, 4)
	1802 ldc2_w (0, 4)
	1805 ldc2_w (0, 4)
	1808 invokespecial (0, 4)
	1811 aastore (0, 4)
	1812 aload_0 (0, 4)
	1813 getfield (0, 4)
	1816 iconst_5 (0, 4)
	1817 aaload (0, 4)
	1818 iconst_1 (0, 4)
	1819 aload_1 (0, 4)
	1820 invokeinterface (0, 4)
	1825 checkcast (0, 4)
	1828 aastore (0, 4)
	1829 aload_0 (0, 4)
	1830 getfield (0, 4)
	1833 iconst_5 (0, 4)
	1834 aaload (0, 4)
	1835 iconst_2 (0, 4)
	1836 aload_1 (0, 4)
	1837 invokeinterface (0, 4)
	1842 checkcast (0, 4)
	1845 aastore (0, 4)
	1846 aload_0 (0, 4)
	1847 getfield (0, 4)
	1850 iconst_5 (0, 4)
	1851 aaload (0, 4)
	1852 iconst_3 (0, 4)
	1853 aload_1 (0, 4)
	1854 invokeinterface (0, 4)
	1859 checkcast (0, 4)
	1862 aastore (0, 4)
	1863 aload_0 (0, 4)
	1864 getfield (0, 4)
	1867 iconst_5 (0, 4)
	1868 aaload (0, 4)
	1869 iconst_4 (0, 4)
	1870 aload_1 (0, 4)
	1871 invokeinterface (0, 4)
	1876 checkcast (0, 4)
	1879 aastore (0, 4)
	1880 aload_0 (0, 4)
	1881 getfield (0, 4)
	1884 iconst_5 (0, 4)
	1885 aaload (0, 4)
	1886 iconst_5 (0, 4)
	1887 aload_0 (0, 4)
	1888 aload_1 (0, 4)
	1889 ldc2_w (0, 4)
	1892 ldc2_w (0, 4)
	1895 invokespecial (0, 4)
	1898 aastore (0, 4)
	1899 aload_0 (0, 4)
	1900 getfield (0, 4)
	1903 iconst_5 (0, 4)
	1904 aaload (0, 4)
	1905 bipush (0, 4)
	1907 aload_0 (0, 4)
	1908 aload_1 (0, 4)
	1909 ldc2_w (0, 4)
	1912 ldc2_w (0, 4)
	1915 invokespecial (0, 4)
	1918 aastore (0, 4)
	1919 aload_0 (0, 4)
	1920 getfield (0, 4)
	1923 iconst_5 (0, 4)
	1924 aaload (0, 4)
	1925 bipush (0, 4)
	1927 aload_0 (0, 4)
	1928 aload_1 (0, 4)
	1929 ldc2_w (0, 4)
	1932 ldc2_w (0, 4)
	1935 invokespecial (0, 4)
	1938 aastore (0, 4)
	1939 aload_0 (0, 4)
	1940 getfield (0, 4)
	1943 iconst_5 (0, 4)
	1944 aaload (0, 4)
	1945 bipush (0, 4)
	1947 aload_0 (0, 4)
	1948 aload_1 (0, 4)
	1949 ldc2_w (0, 4)
	1952 ldc2_w (0, 4)
	1955 invokespecial (0, 4)
	1958 aastore (0, 4)
	1959 aload_0 (0, 4)
	1960 getfield (0, 4)
	1963 iconst_5 (0, 4)
	1964 aaload (0, 4)
	1965 bipush (0, 4)
	1967 aload_0 (0, 4)
	1968 aload_1 (0, 4)
	1969 ldc2_w (0, 4)
	1972 ldc2_w (0, 4)
	1975 invokespecial (0, 4)
	1978 aastore (0, 4)
	1979 aload_0 (0, 4)
	1980 getfield (0, 4)
	1983 iconst_5 (0, 4)
	1984 aaload (0, 4)
	1985 bipush (0, 4)
	1987 aload_0 (0, 4)
	1988 aload_1 (0, 4)
	1989 ldc2_w (0, 4)
	1992 ldc2_w (0, 4)
	1995 invokespecial (0, 4)
	1998 aastore (0, 4)
	1999 aload_0 (0, 4)
	2000 getfield (0, 4)
	2003 iconst_5 (0, 4)
	2004 aaload (0, 4)
	2005 bipush (0, 4)
	2007 aload_0 (0, 4)
	2008 aload_1 (0, 4)
	2009 ldc2_w (0, 4)
	2012 ldc2_w (0, 4)
	2015 invokespecial (0, 4)
	2018 aastore (0, 4)
	2019 aload_0 (0, 4)
	2020 getfield (0, 4)
	2023 iconst_5 (0, 4)
	2024 aaload (0, 4)
	2025 bipush (0, 4)
	2027 aload_0 (0, 4)
	2028 aload_1 (0, 4)
	2029 ldc2_w (0, 4)
	2032 ldc2_w (0, 4)
	2035 invokespecial (0, 4)
	2038 aastore (0, 4)
	2039 aload_0 (0, 4)
	2040 getfield (0, 4)
	2043 iconst_5 (0, 4)
	2044 aaload (0, 4)
	2045 bipush (0, 4)
	2047 aload_0 (0, 4)
	2048 aload_1 (0, 4)
	2049 ldc2_w (0, 4)
	2052 ldc2_w (0, 4)
	2055 invokespecial (0, 4)
	2058 aastore (0, 4)
	2059 aload_0 (0, 4)
	2060 getfield (0, 4)
	2063 iconst_5 (0, 4)
	2064 aaload (0, 4)
	2065 bipush (0, 4)
	2067 aload_0 (0, 4)
	2068 aload_1 (0, 4)
	2069 ldc2_w (0, 4)
	2072 ldc2_w (0, 4)
	2075 invokespecial (0, 4)
	2078 aastore (0, 4)
	2079 aload_0 (0, 4)
	2080 getfield (0, 4)
	2083 iconst_5 (0, 4)
	2084 aaload (0, 4)
	2085 bipush (0, 4)
	2087 aload_0 (0, 4)
	2088 aload_1 (0, 4)
	2089 ldc2_w (0, 4)
	2092 ldc2_w (0, 4)
	2095 invokespecial (0, 4)
	2098 aastore (0, 4)
	2099 aload_0 (0, 4)
	2100 getfield (0, 4)
	2103 bipush (0, 4)
	2105 aaload (0, 4)
	2106 iconst_0 (0, 4)
	2107 aload_0 (0, 4)
	2108 aload_1 (0, 4)
	2109 ldc2_w (0, 4)
	2112 ldc2_w (0, 4)
	2115 invokespecial (0, 4)
	2118 aastore (0, 4)
	2119 aload_0 (0, 4)
	2120 getfield (0, 4)
	2123 bipush (0, 4)
	2125 aaload (0, 4)
	2126 iconst_1 (0, 4)
	2127 aload_1 (0, 4)
	2128 invokeinterface (0, 4)
	2133 checkcast (0, 4)
	2136 aastore (0, 4)
	2137 aload_0 (0, 4)
	2138 getfield (0, 4)
	2141 bipush (0, 4)
	2143 aaload (0, 4)
	2144 iconst_2 (0, 4)
	2145 aload_1 (0, 4)
	2146 invokeinterface (0, 4)
	2151 checkcast (0, 4)
	2154 aastore (0, 4)
	2155 aload_0 (0, 4)
	2156 getfield (0, 4)
	2159 bipush (0, 4)
	2161 aaload (0, 4)
	2162 iconst_3 (0, 4)
	2163 aload_1 (0, 4)
	2164 invokeinterface (0, 4)
	2169 checkcast (0, 4)
	2172 aastore (0, 4)
	2173 aload_0 (0, 4)
	2174 getfield (0, 4)
	2177 bipush (0, 4)
	2179 aaload (0, 4)
	2180 iconst_4 (0, 4)
	2181 aload_1 (0, 4)
	2182 invokeinterface (0, 4)
	2187 checkcast (0, 4)
	2190 aastore (0, 4)
	2191 aload_0 (0, 4)
	2192 getfield (0, 4)
	2195 bipush (0, 4)
	2197 aaload (0, 4)
	2198 iconst_5 (0, 4)
	2199 aload_0 (0, 4)
	2200 aload_1 (0, 4)
	2201 ldc2_w (0, 4)
	2204 ldc2_w (0, 4)
	2207 invokespecial (0, 4)
	2210 aastore (0, 4)
	2211 aload_0 (0, 4)
	2212 getfield (0, 4)
	2215 bipush (0, 4)
	2217 aaload (0, 4)
	2218 bipush (0, 4)
	2220 aload_0 (0, 4)
	2221 aload_1 (0, 4)
	2222 ldc2_w (0, 4)
	2225 ldc2_w (0, 4)
	2228 invokespecial (0, 4)
	2231 aastore (0, 4)
	2232 aload_0 (0, 4)
	2233 getfield (0, 4)
	2236 bipush (0, 4)
	2238 aaload (0, 4)
	2239 bipush (0, 4)
	2241 aload_0 (0, 4)
	2242 aload_1 (0, 4)
	2243 ldc2_w (0, 4)
	2246 ldc2_w (0, 4)
	2249 invokespecial (0, 4)
	2252 aastore (0, 4)
	2253 aload_0 (0, 4)
	2254 getfield (0, 4)
	2257 bipush (0, 4)
	2259 aaload (0, 4)
	2260 bipush (0, 4)
	2262 aload_0 (0, 4)
	2263 aload_1 (0, 4)
	2264 ldc2_w (0, 4)
	2267 ldc2_w (0, 4)
	2270 invokespecial (0, 4)
	2273 aastore (0, 4)
	2274 aload_0 (0, 4)
	2275 getfield (0, 4)
	2278 bipush (0, 4)
	2280 aaload (0, 4)
	2281 bipush (0, 4)
	2283 aload_0 (0, 4)
	2284 aload_1 (0, 4)
	2285 ldc2_w (0, 4)
	2288 ldc2_w (0, 4)
	2291 invokespecial (0, 4)
	2294 aastore (0, 4)
	2295 aload_0 (0, 4)
	2296 getfield (0, 4)
	2299 bipush (0, 4)
	2301 aaload (0, 4)
	2302 bipush (0, 4)
	2304 aload_0 (0, 4)
	2305 aload_1 (0, 4)
	2306 ldc2_w (0, 4)
	2309 ldc2_w (0, 4)
	2312 invokespecial (0, 4)
	2315 aastore (0, 4)
	2316 aload_0 (0, 4)
	2317 getfield (0, 4)
	2320 bipush (0, 4)
	2322 aaload (0, 4)
	2323 bipush (0, 4)
	2325 aload_0 (0, 4)
	2326 aload_1 (0, 4)
	2327 ldc2_w (0, 4)
	2330 ldc2_w (0, 4)
	2333 invokespecial (0, 4)
	2336 aastore (0, 4)
	2337 aload_0 (0, 4)
	2338 getfield (0, 4)
	2341 bipush (0, 4)
	2343 aaload (0, 4)
	2344 bipush (0, 4)
	2346 aload_0 (0, 4)
	2347 aload_1 (0, 4)
	2348 ldc2_w (0, 4)
	2351 ldc2_w (0, 4)
	2354 invokespecial (0, 4)
	2357 aastore (0, 4)
	2358 aload_0 (0, 4)
	2359 getfield (0, 4)
	2362 bipush (0, 4)
	2364 aaload (0, 4)
	2365 bipush (0, 4)
	2367 aload_0 (0, 4)
	2368 aload_1 (0, 4)
	2369 ldc2_w (0, 4)
	2372 ldc2_w (0, 4)
	2375 invokespecial (0, 4)
	2378 aastore (0, 4)
	2379 aload_0 (0, 4)
	2380 getfield (0, 4)
	2383 bipush (0, 4)
	2385 aaload (0, 4)
	2386 bipush (0, 4)
	2388 aload_0 (0, 4)
	2389 aload_1 (0, 4)
	2390 ldc2_w (0, 4)
	2393 ldc2_w (0, 4)
	2396 invokespecial (0, 4)
	2399 aastore (0, 4)
	2400 aload_0 (0, 4)
	2401 getfield (0, 4)
	2404 bipush (0, 4)
	2406 aaload (0, 4)
	2407 bipush (0, 4)
	2409 aload_0 (0, 4)
	2410 aload_1 (0, 4)
	2411 ldc2_w (0, 4)
	2414 ldc2_w (0, 4)
	2417 invokespecial (0, 4)
	2420 aastore (0, 4)
	2421 return (0, 0)

Method: create
	0 aload_0 (0, 0)
	1 aload_1 (0, 0)
	2 iload_2 (0, 0)
	3 aload_3 (0, 0)
	4 aload (0, 0)
	6 aload (0, 0)
	8 aload (0, 0)
	10 aload (0, 0)
	12 aload (0, 0)
	14 invokevirtual (0, 0)
	17 areturn (0, 0)

Method: fraction
	0 aload_1 (0, 0)
	1 invokeinterface (0, 0)
	6 checkcast (0, 0)
	9 dload_2 (0, 0)
	10 invokeinterface (0, 0)
	15 checkcast (0, 0)
	18 dload (0, 0)
	20 invokeinterface (0, 0)
	25 checkcast (0, 0)
	28 areturn (0, 0)

Method: computeInterpolatedStateAndDerivatives
	0 aload_2 (0, 0)
	1 invokeinterface (0, 0)
	6 invokeinterface (0, 0)
	11 checkcast (0, 0)
	14 astore (0, 0)
	16 aload (0, 0)
	18 aload_3 (0, 0)
	19 invokeinterface (0, 0)
	24 checkcast (0, 0)
	27 astore (0, 0)
	29 aload_3 (0, 0)
	30 iconst_2 (0, 0)
	31 invokeinterface (0, 0)
	36 checkcast (0, 0)
	39 astore (0, 0)
	41 aload_3 (0, 0)
	42 aload_3 (0, 0)
	43 invokeinterface (0, 0)
	48 checkcast (0, 0)
	51 astore (0, 0)
	53 aload (0, 0)
	55 aload (0, 0)
	57 invokeinterface (0, 0)
	62 checkcast (0, 0)
	65 astore (0, 0)
	67 aload_3 (0, 0)
	68 aload_3 (0, 0)
	69 bipush (0, 0)
	71 invokeinterface (0, 0)
	76 checkcast (0, 0)
	79 ldc2_w (0, 0)
	82 invokeinterface (0, 0)
	87 invokeinterface (0, 0)
	92 checkcast (0, 0)
	95 astore (0, 0)
	97 aload (0, 0)
	99 aload_3 (0, 0)
	100 aload (0, 0)
	102 ldc2_w (0, 0)
	105 invokeinterface (0, 0)
	110 invokeinterface (0, 0)
	115 checkcast (0, 0)
	118 dconst_1 (0, 0)
	119 invokeinterface (0, 0)
	124 invokeinterface (0, 0)
	129 checkcast (0, 0)
	132 astore (0, 0)
	134 aload (0, 0)
	136 aload_3 (0, 0)
	137 aload_3 (0, 0)
	138 iconst_5 (0, 0)
	139 invokeinterface (0, 0)
	144 checkcast (0, 0)
	147 ldc2_w (0, 0)
	150 invokeinterface (0, 0)
	155 invokeinterface (0, 0)
	160 checkcast (0, 0)
	163 ldc2_w (0, 0)
	166 invokeinterface (0, 0)
	171 invokeinterface (0, 0)
	176 checkcast (0, 0)
	179 astore (0, 0)
	181 aload (0, 0)
	183 aload_3 (0, 0)
	184 aload_3 (0, 0)
	185 aload_3 (0, 0)
	186 bipush (0, 0)
	188 invokeinterface (0, 0)
	193 checkcast (0, 0)
	196 ldc2_w (0, 0)
	199 invokeinterface (0, 0)
	204 invokeinterface (0, 0)
	209 checkcast (0, 0)
	212 ldc2_w (0, 0)
	215 invokeinterface (0, 0)
	220 invokeinterface (0, 0)
	225 checkcast (0, 0)
	228 ldc2_w (0, 0)
	231 invokeinterface (0, 0)
	236 invokeinterface (0, 0)
	241 checkcast (0, 0)
	244 astore (0, 0)
	246 aload (0, 0)
	248 aload_3 (0, 0)
	249 aload_3 (0, 0)
	250 aload_3 (0, 0)
	251 aload_3 (0, 0)
	252 bipush (0, 0)
	254 invokeinterface (0, 0)
	259 checkcast (0, 0)
	262 ldc2_w (0, 0)
	265 invokeinterface (0, 0)
	270 invokeinterface (0, 0)
	275 checkcast (0, 0)
	278 ldc2_w (0, 0)
	281 invokeinterface (0, 0)
	286 invokeinterface (0, 0)
	291 checkcast (0, 0)
	294 ldc2_w (0, 0)
	297 invokeinterface (0, 0)
	302 invokeinterface (0, 0)
	307 invokeinterface (0, 0)
	312 checkcast (0, 0)
	315 astore (0, 0)
	317 aload_0 (1, 1)
	318 invokevirtual (1, 1)
	321 ifnull (1, 1)
	324 aload_3 (1, 1)
	325 invokeinterface (1, 1)
	330 ldc2_w (1, 1)
	333 dcmpg (1, 1)
	334 ifgt (1, 1)
	337 aload (1, 1)
	339 astore (1, 1)
	341 aload (1, 1)
	343 aload (1, 1)
	345 invokeinterface (1, 1)
	350 checkcast (1, 1)
	353 astore (1, 1)
	355 aload (1, 1)
	357 aload_3 (1, 1)
	358 invokeinterface (1, 1)
	363 checkcast (1, 1)
	366 astore (1, 1)
	368 aload (1, 1)
	370 aload (1, 1)
	372 invokeinterface (1, 1)
	377 checkcast (1, 1)
	380 astore (1, 1)
	382 aload (1, 1)
	384 aload_3 (1, 1)
	385 invokeinterface (1, 1)
	390 checkcast (1, 1)
	393 astore (1, 1)
	395 aload (1, 1)
	397 aload (1, 1)
	399 invokeinterface (1, 1)
	404 checkcast (1, 1)
	407 astore (1, 1)
	409 aload (1, 1)
	411 aload_3 (1, 1)
	412 invokeinterface (1, 1)
	417 checkcast (1, 1)
	420 astore (1, 1)
	422 aload_2 (1, 1)
	423 invokeinterface (1, 1)
	428 bipush (1, 1)
	430 invokestatic (1, 1)
	433 checkcast (1, 1)
	436 astore (1, 1)
	438 aload_2 (1, 1)
	439 invokeinterface (1, 1)
	444 bipush (1, 1)
	446 invokestatic (1, 1)
	449 checkcast (1, 1)
	452 astore (1, 1)
	454 iconst_0 (2, 4)
	455 istore (2, 4)
	457 iload (2, 4)
	459 aload (2, 4)
	461 arraylength (2, 4)
	462 if_icmpge (2, 4)
	465 aload (2, 4)
	467 iload (2, 4)
	469 aload (2, 4)
	471 aload_0 (2, 4)
	472 getfield (2, 4)
	475 iconst_0 (2, 4)
	476 aaload (2, 4)
	477 iload (2, 4)
	479 aaload (2, 4)
	480 invokeinterface (2, 4)
	485 checkcast (2, 4)
	488 aload (2, 4)
	490 aload_0 (2, 4)
	491 getfield (2, 4)
	494 iconst_1 (2, 4)
	495 aaload (2, 4)
	496 iload (2, 4)
	498 aaload (2, 4)
	499 invokeinterface (2, 4)
	504 invokeinterface (2, 4)
	509 checkcast (2, 4)
	512 aload (2, 4)
	514 aload_0 (2, 4)
	515 getfield (2, 4)
	518 iconst_2 (2, 4)
	519 aaload (2, 4)
	520 iload (2, 4)
	522 aaload (2, 4)
	523 invokeinterface (2, 4)
	528 invokeinterface (2, 4)
	533 checkcast (2, 4)
	536 aload (2, 4)
	538 aload_0 (2, 4)
	539 getfield (2, 4)
	542 iconst_3 (2, 4)
	543 aaload (2, 4)
	544 iload (2, 4)
	546 aaload (2, 4)
	547 invokeinterface (2, 4)
	552 invokeinterface (2, 4)
	557 checkcast (2, 4)
	560 aload (2, 4)
	562 aload_0 (2, 4)
	563 getfield (2, 4)
	566 iconst_4 (2, 4)
	567 aaload (2, 4)
	568 iload (2, 4)
	570 aaload (2, 4)
	571 invokeinterface (2, 4)
	576 invokeinterface (2, 4)
	581 checkcast (2, 4)
	584 aload (2, 4)
	586 aload_0 (2, 4)
	587 getfield (2, 4)
	590 iconst_5 (2, 4)
	591 aaload (2, 4)
	592 iload (2, 4)
	594 aaload (2, 4)
	595 invokeinterface (2, 4)
	600 invokeinterface (2, 4)
	605 checkcast (2, 4)
	608 aload (2, 4)
	610 aload_0 (2, 4)
	611 getfield (2, 4)
	614 bipush (2, 4)
	616 aaload (2, 4)
	617 iload (2, 4)
	619 aaload (2, 4)
	620 invokeinterface (2, 4)
	625 invokeinterface (2, 4)
	630 checkcast (2, 4)
	633 aastore (2, 4)
	634 aload (2, 4)
	636 iload (2, 4)
	638 aload_0 (2, 4)
	639 getfield (2, 4)
	642 iconst_0 (2, 4)
	643 aaload (2, 4)
	644 iload (2, 4)
	646 aaload (2, 4)
	647 aload (2, 4)
	649 aload_0 (2, 4)
	650 getfield (2, 4)
	653 iconst_1 (2, 4)
	654 aaload (2, 4)
	655 iload (2, 4)
	657 aaload (2, 4)
	658 invokeinterface (2, 4)
	663 invokeinterface (2, 4)
	668 checkcast (2, 4)
	671 aload (2, 4)
	673 aload_0 (2, 4)
	674 getfield (2, 4)
	677 iconst_2 (2, 4)
	678 aaload (2, 4)
	679 iload (2, 4)
	681 aaload (2, 4)
	682 invokeinterface (2, 4)
	687 invokeinterface (2, 4)
	692 checkcast (2, 4)
	695 aload (2, 4)
	697 aload_0 (2, 4)
	698 getfield (2, 4)
	701 iconst_3 (2, 4)
	702 aaload (2, 4)
	703 iload (2, 4)
	705 aaload (2, 4)
	706 invokeinterface (2, 4)
	711 invokeinterface (2, 4)
	716 checkcast (2, 4)
	719 aload (2, 4)
	721 aload_0 (2, 4)
	722 getfield (2, 4)
	725 iconst_4 (2, 4)
	726 aaload (2, 4)
	727 iload (2, 4)
	729 aaload (2, 4)
	730 invokeinterface (2, 4)
	735 invokeinterface (2, 4)
	740 checkcast (2, 4)
	743 aload (2, 4)
	745 aload_0 (2, 4)
	746 getfield (2, 4)
	749 iconst_5 (2, 4)
	750 aaload (2, 4)
	751 iload (2, 4)
	753 aaload (2, 4)
	754 invokeinterface (2, 4)
	759 invokeinterface (2, 4)
	764 checkcast (2, 4)
	767 aload (2, 4)
	769 aload_0 (2, 4)
	770 getfield (2, 4)
	773 bipush (2, 4)
	775 aaload (2, 4)
	776 iload (2, 4)
	778 aaload (2, 4)
	779 invokeinterface (2, 4)
	784 invokeinterface (2, 4)
	789 checkcast (2, 4)
	792 aastore (2, 4)
	793 iinc (2, 4)
	796 goto (2, 4)
	799 aload_0 (1, 1)
	800 bipush (1, 1)
	802 anewarray (1, 1)
	805 dup (1, 1)
	806 iconst_0 (1, 1)
	807 aload (1, 1)
	809 iconst_0 (1, 1)
	810 aaload (1, 1)
	811 aastore (1, 1)
	812 dup (1, 1)
	813 iconst_1 (1, 1)
	814 aload (1, 1)
	816 iconst_1 (1, 1)
	817 aaload (1, 1)
	818 aastore (1, 1)
	819 dup (1, 1)
	820 iconst_2 (1, 1)
	821 aload (1, 1)
	823 iconst_2 (1, 1)
	824 aaload (1, 1)
	825 aastore (1, 1)
	826 dup (1, 1)
	827 iconst_3 (1, 1)
	828 aload (1, 1)
	830 iconst_3 (1, 1)
	831 aaload (1, 1)
	832 aastore (1, 1)
	833 dup (1, 1)
	834 iconst_4 (1, 1)
	835 aload (1, 1)
	837 iconst_4 (1, 1)
	838 aaload (1, 1)
	839 aastore (1, 1)
	840 dup (1, 1)
	841 iconst_5 (1, 1)
	842 aload (1, 1)
	844 iconst_5 (1, 1)
	845 aaload (1, 1)
	846 aastore (1, 1)
	847 dup (1, 1)
	848 bipush (1, 1)
	850 aload (1, 1)
	852 bipush (1, 1)
	854 aaload (1, 1)
	855 aastore (1, 1)
	856 dup (1, 1)
	857 bipush (1, 1)
	859 aload (1, 1)
	861 bipush (1, 1)
	863 aaload (1, 1)
	864 aastore (1, 1)
	865 dup (1, 1)
	866 bipush (1, 1)
	868 aload (1, 1)
	870 bipush (1, 1)
	872 aaload (1, 1)
	873 aastore (1, 1)
	874 dup (1, 1)
	875 bipush (1, 1)
	877 aload (1, 1)
	879 bipush (1, 1)
	881 aaload (1, 1)
	882 aastore (1, 1)
	883 dup (1, 1)
	884 bipush (1, 1)
	886 aload (1, 1)
	888 bipush (1, 1)
	890 aaload (1, 1)
	891 aastore (1, 1)
	892 dup (1, 1)
	893 bipush (1, 1)
	895 aload (1, 1)
	897 bipush (1, 1)
	899 aaload (1, 1)
	900 aastore (1, 1)
	901 dup (1, 1)
	902 bipush (1, 1)
	904 aload (1, 1)
	906 bipush (1, 1)
	908 aaload (1, 1)
	909 aastore (1, 1)
	910 dup (1, 1)
	911 bipush (1, 1)
	913 aload (1, 1)
	915 bipush (1, 1)
	917 aaload (1, 1)
	918 aastore (1, 1)
	919 dup (1, 1)
	920 bipush (1, 1)
	922 aload (1, 1)
	924 bipush (1, 1)
	926 aaload (1, 1)
	927 aastore (1, 1)
	928 dup (1, 1)
	929 bipush (1, 1)
	931 aload (1, 1)
	933 bipush (1, 1)
	935 aaload (1, 1)
	936 aastore (1, 1)
	937 invokevirtual (1, 1)
	940 astore (1, 1)
	942 aload_0 (1, 1)
	943 bipush (1, 1)
	945 anewarray (1, 1)
	948 dup (1, 1)
	949 iconst_0 (1, 1)
	950 aload (1, 1)
	952 iconst_0 (1, 1)
	953 aaload (1, 1)
	954 aastore (1, 1)
	955 dup (1, 1)
	956 iconst_1 (1, 1)
	957 aload (1, 1)
	959 iconst_1 (1, 1)
	960 aaload (1, 1)
	961 aastore (1, 1)
	962 dup (1, 1)
	963 iconst_2 (1, 1)
	964 aload (1, 1)
	966 iconst_2 (1, 1)
	967 aaload (1, 1)
	968 aastore (1, 1)
	969 dup (1, 1)
	970 iconst_3 (1, 1)
	971 aload (1, 1)
	973 iconst_3 (1, 1)
	974 aaload (1, 1)
	975 aastore (1, 1)
	976 dup (1, 1)
	977 iconst_4 (1, 1)
	978 aload (1, 1)
	980 iconst_4 (1, 1)
	981 aaload (1, 1)
	982 aastore (1, 1)
	983 dup (1, 1)
	984 iconst_5 (1, 1)
	985 aload (1, 1)
	987 iconst_5 (1, 1)
	988 aaload (1, 1)
	989 aastore (1, 1)
	990 dup (1, 1)
	991 bipush (1, 1)
	993 aload (1, 1)
	995 bipush (1, 1)
	997 aaload (1, 1)
	998 aastore (1, 1)
	999 dup (1, 1)
	1000 bipush (1, 1)
	1002 aload (1, 1)
	1004 bipush (1, 1)
	1006 aaload (1, 1)
	1007 aastore (1, 1)
	1008 dup (1, 1)
	1009 bipush (1, 1)
	1011 aload (1, 1)
	1013 bipush (1, 1)
	1015 aaload (1, 1)
	1016 aastore (1, 1)
	1017 dup (1, 1)
	1018 bipush (1, 1)
	1020 aload (1, 1)
	1022 bipush (1, 1)
	1024 aaload (1, 1)
	1025 aastore (1, 1)
	1026 dup (1, 1)
	1027 bipush (1, 1)
	1029 aload (1, 1)
	1031 bipush (1, 1)
	1033 aaload (1, 1)
	1034 aastore (1, 1)
	1035 dup (1, 1)
	1036 bipush (1, 1)
	1038 aload (1, 1)
	1040 bipush (1, 1)
	1042 aaload (1, 1)
	1043 aastore (1, 1)
	1044 dup (1, 1)
	1045 bipush (1, 1)
	1047 aload (1, 1)
	1049 bipush (1, 1)
	1051 aaload (1, 1)
	1052 aastore (1, 1)
	1053 dup (1, 1)
	1054 bipush (1, 1)
	1056 aload (1, 1)
	1058 bipush (1, 1)
	1060 aaload (1, 1)
	1061 aastore (1, 1)
	1062 dup (1, 1)
	1063 bipush (1, 1)
	1065 aload (1, 1)
	1067 bipush (1, 1)
	1069 aaload (1, 1)
	1070 aastore (1, 1)
	1071 dup (1, 1)
	1072 bipush (1, 1)
	1074 aload (1, 1)
	1076 bipush (1, 1)
	1078 aaload (1, 1)
	1079 aastore (1, 1)
	1080 invokevirtual (1, 1)
	1083 astore (1, 1)
	1085 goto (1, 2)
	1088 aload (1, 2)
	1090 invokeinterface (1, 2)
	1095 checkcast (1, 2)
	1098 astore (1, 2)
	1100 aload (1, 2)
	1102 aload_3 (1, 2)
	1103 invokeinterface (1, 2)
	1108 checkcast (1, 2)
	1111 invokeinterface (1, 2)
	1116 checkcast (1, 2)
	1119 astore (1, 2)
	1121 aload (1, 2)
	1123 aload_3 (1, 2)
	1124 invokeinterface (1, 2)
	1129 checkcast (1, 2)
	1132 astore (1, 2)
	1134 aload (1, 2)
	1136 aload (1, 2)
	1138 invokeinterface (1, 2)
	1143 checkcast (1, 2)
	1146 astore (1, 2)
	1148 aload (1, 2)
	1150 aload_3 (1, 2)
	1151 invokeinterface (1, 2)
	1156 checkcast (1, 2)
	1159 astore (1, 2)
	1161 aload (1, 2)
	1163 aload (1, 2)
	1165 invokeinterface (1, 2)
	1170 checkcast (1, 2)
	1173 astore (1, 2)
	1175 aload (1, 2)
	1177 aload_3 (1, 2)
	1178 invokeinterface (1, 2)
	1183 checkcast (1, 2)
	1186 astore (1, 2)
	1188 aload_2 (1, 2)
	1189 invokeinterface (1, 2)
	1194 bipush (1, 2)
	1196 invokestatic (1, 2)
	1199 checkcast (1, 2)
	1202 astore (1, 2)
	1204 aload_2 (1, 2)
	1205 invokeinterface (1, 2)
	1210 bipush (1, 2)
	1212 invokestatic (1, 2)
	1215 checkcast (1, 2)
	1218 astore (1, 2)
	1220 iconst_0 (2, 4)
	1221 istore (2, 4)
	1223 iload (2, 4)
	1225 aload (2, 4)
	1227 arraylength (2, 4)
	1228 if_icmpge (2, 4)
	1231 aload (2, 4)
	1233 iload (2, 4)
	1235 aload (2, 4)
	1237 aload_0 (2, 4)
	1238 getfield (2, 4)
	1241 iconst_0 (2, 4)
	1242 aaload (2, 4)
	1243 iload (2, 4)
	1245 aaload (2, 4)
	1246 invokeinterface (2, 4)
	1251 checkcast (2, 4)
	1254 aload (2, 4)
	1256 aload_0 (2, 4)
	1257 getfield (2, 4)
	1260 iconst_1 (2, 4)
	1261 aaload (2, 4)
	1262 iload (2, 4)
	1264 aaload (2, 4)
	1265 invokeinterface (2, 4)
	1270 invokeinterface (2, 4)
	1275 checkcast (2, 4)
	1278 aload (2, 4)
	1280 aload_0 (2, 4)
	1281 getfield (2, 4)
	1284 iconst_2 (2, 4)
	1285 aaload (2, 4)
	1286 iload (2, 4)
	1288 aaload (2, 4)
	1289 invokeinterface (2, 4)
	1294 invokeinterface (2, 4)
	1299 checkcast (2, 4)
	1302 aload (2, 4)
	1304 aload_0 (2, 4)
	1305 getfield (2, 4)
	1308 iconst_3 (2, 4)
	1309 aaload (2, 4)
	1310 iload (2, 4)
	1312 aaload (2, 4)
	1313 invokeinterface (2, 4)
	1318 invokeinterface (2, 4)
	1323 checkcast (2, 4)
	1326 aload (2, 4)
	1328 aload_0 (2, 4)
	1329 getfield (2, 4)
	1332 iconst_4 (2, 4)
	1333 aaload (2, 4)
	1334 iload (2, 4)
	1336 aaload (2, 4)
	1337 invokeinterface (2, 4)
	1342 invokeinterface (2, 4)
	1347 checkcast (2, 4)
	1350 aload (2, 4)
	1352 aload_0 (2, 4)
	1353 getfield (2, 4)
	1356 iconst_5 (2, 4)
	1357 aaload (2, 4)
	1358 iload (2, 4)
	1360 aaload (2, 4)
	1361 invokeinterface (2, 4)
	1366 invokeinterface (2, 4)
	1371 checkcast (2, 4)
	1374 aload (2, 4)
	1376 aload_0 (2, 4)
	1377 getfield (2, 4)
	1380 bipush (2, 4)
	1382 aaload (2, 4)
	1383 iload (2, 4)
	1385 aaload (2, 4)
	1386 invokeinterface (2, 4)
	1391 invokeinterface (2, 4)
	1396 checkcast (2, 4)
	1399 aastore (2, 4)
	1400 aload (2, 4)
	1402 iload (2, 4)
	1404 aload_0 (2, 4)
	1405 getfield (2, 4)
	1408 iconst_0 (2, 4)
	1409 aaload (2, 4)
	1410 iload (2, 4)
	1412 aaload (2, 4)
	1413 aload (2, 4)
	1415 aload_0 (2, 4)
	1416 getfield (2, 4)
	1419 iconst_1 (2, 4)
	1420 aaload (2, 4)
	1421 iload (2, 4)
	1423 aaload (2, 4)
	1424 invokeinterface (2, 4)
	1429 invokeinterface (2, 4)
	1434 checkcast (2, 4)
	1437 aload (2, 4)
	1439 aload_0 (2, 4)
	1440 getfield (2, 4)
	1443 iconst_2 (2, 4)
	1444 aaload (2, 4)
	1445 iload (2, 4)
	1447 aaload (2, 4)
	1448 invokeinterface (2, 4)
	1453 invokeinterface (2, 4)
	1458 checkcast (2, 4)
	1461 aload (2, 4)
	1463 aload_0 (2, 4)
	1464 getfield (2, 4)
	1467 iconst_3 (2, 4)
	1468 aaload (2, 4)
	1469 iload (2, 4)
	1471 aaload (2, 4)
	1472 invokeinterface (2, 4)
	1477 invokeinterface (2, 4)
	1482 checkcast (2, 4)
	1485 aload (2, 4)
	1487 aload_0 (2, 4)
	1488 getfield (2, 4)
	1491 iconst_4 (2, 4)
	1492 aaload (2, 4)
	1493 iload (2, 4)
	1495 aaload (2, 4)
	1496 invokeinterface (2, 4)
	1501 invokeinterface (2, 4)
	1506 checkcast (2, 4)
	1509 aload (2, 4)
	1511 aload_0 (2, 4)
	1512 getfield (2, 4)
	1515 iconst_5 (2, 4)
	1516 aaload (2, 4)
	1517 iload (2, 4)
	1519 aaload (2, 4)
	1520 invokeinterface (2, 4)
	1525 invokeinterface (2, 4)
	1530 checkcast (2, 4)
	1533 aload (2, 4)
	1535 aload_0 (2, 4)
	1536 getfield (2, 4)
	1539 bipush (2, 4)
	1541 aaload (2, 4)
	1542 iload (2, 4)
	1544 aaload (2, 4)
	1545 invokeinterface (2, 4)
	1550 invokeinterface (2, 4)
	1555 checkcast (2, 4)
	1558 aastore (2, 4)
	1559 iinc (2, 4)
	1562 goto (2, 4)
	1565 aload_0 (1, 2)
	1566 bipush (1, 2)
	1568 anewarray (1, 2)
	1571 dup (1, 2)
	1572 iconst_0 (1, 2)
	1573 aload (1, 2)
	1575 iconst_0 (1, 2)
	1576 aaload (1, 2)
	1577 aastore (1, 2)
	1578 dup (1, 2)
	1579 iconst_1 (1, 2)
	1580 aload (1, 2)
	1582 iconst_1 (1, 2)
	1583 aaload (1, 2)
	1584 aastore (1, 2)
	1585 dup (1, 2)
	1586 iconst_2 (1, 2)
	1587 aload (1, 2)
	1589 iconst_2 (1, 2)
	1590 aaload (1, 2)
	1591 aastore (1, 2)
	1592 dup (1, 2)
	1593 iconst_3 (1, 2)
	1594 aload (1, 2)
	1596 iconst_3 (1, 2)
	1597 aaload (1, 2)
	1598 aastore (1, 2)
	1599 dup (1, 2)
	1600 iconst_4 (1, 2)
	1601 aload (1, 2)
	1603 iconst_4 (1, 2)
	1604 aaload (1, 2)
	1605 aastore (1, 2)
	1606 dup (1, 2)
	1607 iconst_5 (1, 2)
	1608 aload (1, 2)
	1610 iconst_5 (1, 2)
	1611 aaload (1, 2)
	1612 aastore (1, 2)
	1613 dup (1, 2)
	1614 bipush (1, 2)
	1616 aload (1, 2)
	1618 bipush (1, 2)
	1620 aaload (1, 2)
	1621 aastore (1, 2)
	1622 dup (1, 2)
	1623 bipush (1, 2)
	1625 aload (1, 2)
	1627 bipush (1, 2)
	1629 aaload (1, 2)
	1630 aastore (1, 2)
	1631 dup (1, 2)
	1632 bipush (1, 2)
	1634 aload (1, 2)
	1636 bipush (1, 2)
	1638 aaload (1, 2)
	1639 aastore (1, 2)
	1640 dup (1, 2)
	1641 bipush (1, 2)
	1643 aload (1, 2)
	1645 bipush (1, 2)
	1647 aaload (1, 2)
	1648 aastore (1, 2)
	1649 dup (1, 2)
	1650 bipush (1, 2)
	1652 aload (1, 2)
	1654 bipush (1, 2)
	1656 aaload (1, 2)
	1657 aastore (1, 2)
	1658 dup (1, 2)
	1659 bipush (1, 2)
	1661 aload (1, 2)
	1663 bipush (1, 2)
	1665 aaload (1, 2)
	1666 aastore (1, 2)
	1667 dup (1, 2)
	1668 bipush (1, 2)
	1670 aload (1, 2)
	1672 bipush (1, 2)
	1674 aaload (1, 2)
	1675 aastore (1, 2)
	1676 dup (1, 2)
	1677 bipush (1, 2)
	1679 aload (1, 2)
	1681 bipush (1, 2)
	1683 aaload (1, 2)
	1684 aastore (1, 2)
	1685 dup (1, 2)
	1686 bipush (1, 2)
	1688 aload (1, 2)
	1690 bipush (1, 2)
	1692 aaload (1, 2)
	1693 aastore (1, 2)
	1694 dup (1, 2)
	1695 bipush (1, 2)
	1697 aload (1, 2)
	1699 bipush (1, 2)
	1701 aaload (1, 2)
	1702 aastore (1, 2)
	1703 invokevirtual (1, 2)
	1706 astore (1, 2)
	1708 aload_0 (1, 2)
	1709 bipush (1, 2)
	1711 anewarray (1, 2)
	1714 dup (1, 2)
	1715 iconst_0 (1, 2)
	1716 aload (1, 2)
	1718 iconst_0 (1, 2)
	1719 aaload (1, 2)
	1720 aastore (1, 2)
	1721 dup (1, 2)
	1722 iconst_1 (1, 2)
	1723 aload (1, 2)
	1725 iconst_1 (1, 2)
	1726 aaload (1, 2)
	1727 aastore (1, 2)
	1728 dup (1, 2)
	1729 iconst_2 (1, 2)
	1730 aload (1, 2)
	1732 iconst_2 (1, 2)
	1733 aaload (1, 2)
	1734 aastore (1, 2)
	1735 dup (1, 2)
	1736 iconst_3 (1, 2)
	1737 aload (1, 2)
	1739 iconst_3 (1, 2)
	1740 aaload (1, 2)
	1741 aastore (1, 2)
	1742 dup (1, 2)
	1743 iconst_4 (1, 2)
	1744 aload (1, 2)
	1746 iconst_4 (1, 2)
	1747 aaload (1, 2)
	1748 aastore (1, 2)
	1749 dup (1, 2)
	1750 iconst_5 (1, 2)
	1751 aload (1, 2)
	1753 iconst_5 (1, 2)
	1754 aaload (1, 2)
	1755 aastore (1, 2)
	1756 dup (1, 2)
	1757 bipush (1, 2)
	1759 aload (1, 2)
	1761 bipush (1, 2)
	1763 aaload (1, 2)
	1764 aastore (1, 2)
	1765 dup (1, 2)
	1766 bipush (1, 2)
	1768 aload (1, 2)
	1770 bipush (1, 2)
	1772 aaload (1, 2)
	1773 aastore (1, 2)
	1774 dup (1, 2)
	1775 bipush (1, 2)
	1777 aload (1, 2)
	1779 bipush (1, 2)
	1781 aaload (1, 2)
	1782 aastore (1, 2)
	1783 dup (1, 2)
	1784 bipush (1, 2)
	1786 aload (1, 2)
	1788 bipush (1, 2)
	1790 aaload (1, 2)
	1791 aastore (1, 2)
	1792 dup (1, 2)
	1793 bipush (1, 2)
	1795 aload (1, 2)
	1797 bipush (1, 2)
	1799 aaload (1, 2)
	1800 aastore (1, 2)
	1801 dup (1, 2)
	1802 bipush (1, 2)
	1804 aload (1, 2)
	1806 bipush (1, 2)
	1808 aaload (1, 2)
	1809 aastore (1, 2)
	1810 dup (1, 2)
	1811 bipush (1, 2)
	1813 aload (1, 2)
	1815 bipush (1, 2)
	1817 aaload (1, 2)
	1818 aastore (1, 2)
	1819 dup (1, 2)
	1820 bipush (1, 2)
	1822 aload (1, 2)
	1824 bipush (1, 2)
	1826 aaload (1, 2)
	1827 aastore (1, 2)
	1828 dup (1, 2)
	1829 bipush (1, 2)
	1831 aload (1, 2)
	1833 bipush (1, 2)
	1835 aaload (1, 2)
	1836 aastore (1, 2)
	1837 dup (1, 2)
	1838 bipush (1, 2)
	1840 aload (1, 2)
	1842 bipush (1, 2)
	1844 aaload (1, 2)
	1845 aastore (1, 2)
	1846 invokevirtual (1, 2)
	1849 astore (1, 2)
	1851 new (0, 1)
	1854 dup (0, 1)
	1855 aload_2 (0, 1)
	1856 aload (0, 1)
	1858 aload (0, 1)
	1860 invokespecial (0, 1)
	1863 areturn (0, 1)

