Method: <init>
	0 aload_0 (1, 4)
	1 aload_1 (1, 4)
	2 iload_2 (1, 4)
	3 aload_3 (1, 4)
	4 aload (1, 4)
	5 #4 (1, 4)
	6 aload (1, 4)
	7 #5 (1, 4)
	8 aload (1, 4)
	9 #6 (1, 4)
	10 aload (1, 4)
	11 #7 (1, 4)
	12 aload (1, 4)
	13 #8 (1, 4)
	14 invokespecial (1, 4)
	15 org/apache/commons/math3/ode/nonstiff/RungeKuttaFieldStepInterpolator.<init>:(Lorg/apache/commons/math3/Field;Z[[Lorg/apache/commons/math3/RealFieldElement;Lorg/apache/commons/math3/ode/FieldODEStateAndDerivative;Lorg/apache/commons/math3/ode/FieldODEStateAndDerivative;Lorg/apache/commons/math3/ode/FieldODEStateAndDerivative;Lorg/apache/commons/math3/ode/FieldODEStateAndDerivative;Lorg/apache/commons/math3/ode/FieldEquationsMapper;)V (1, 4)
	17 aload_0 (1, 4)
	18 aload_1 (1, 4)
	19 bipush (1, 4)
	20 7 (1, 4)
	21 bipush (1, 4)
	22 16 (1, 4)
	23 invokestatic (1, 4)
	24 org/apache/commons/math3/util/MathArrays.buildArray:(Lorg/apache/commons/math3/Field;II)[[Ljava/lang/Object; (1, 4)
	26 checkcast (1, 4)
	27 [[Lorg/apache/commons/math3/RealFieldElement; (1, 4)
	29 putfield (1, 4)
	30 org/apache/commons/math3/ode/nonstiff/DormandPrince853FieldStepInterpolator.d:[[Lorg/apache/commons/math3/RealFieldElement; (1, 4)
	32 aload_0 (1, 4)
	33 getfield (1, 4)
	34 org/apache/commons/math3/ode/nonstiff/DormandPrince853FieldStepInterpolator.d:[[Lorg/apache/commons/math3/RealFieldElement; (1, 4)
	36 iconst_0 (1, 4)
	37 aaload (1, 4)
	38 iconst_0 (1, 4)
	39 aload_0 (1, 4)
	40 aload_1 (1, 4)
	41 ldc2_w (1, 4)
	42 104257.0 (1, 4)
	44 ldc2_w (1, 4)
	45 1920240.0 (1, 4)
	47 invokespecial (1, 4)
	48 org/apache/commons/math3/ode/nonstiff/DormandPrince853FieldStepInterpolator.fraction:(Lorg/apache/commons/math3/Field;DD)Lorg/apache/commons/math3/RealFieldElement; (1, 4)
	50 aastore (1, 4)
	51 aload_0 (1, 4)
	52 getfield (1, 4)
	53 org/apache/commons/math3/ode/nonstiff/DormandPrince853FieldStepInterpolator.d:[[Lorg/apache/commons/math3/RealFieldElement; (1, 4)
	55 iconst_0 (1, 4)
	56 aaload (1, 4)
	57 iconst_1 (1, 4)
	58 aload_1 (1, 4)
	59 invokeinterface (1, 4)
	60 org/apache/commons/math3/Field.org/apache/commons/math3/RealFieldElement (1, 4)
	62 0 (1, 4)
	64 checkcast (1, 4)
	65 org/apache/commons/math3/RealFieldElement (1, 4)
	67 aastore (1, 4)
	68 aload_0 (1, 4)
	69 getfield (1, 4)
	70 org/apache/commons/math3/ode/nonstiff/DormandPrince853FieldStepInterpolator.d:[[Lorg/apache/commons/math3/RealFieldElement; (1, 4)
	72 iconst_0 (1, 4)
	73 aaload (1, 4)
	74 iconst_2 (1, 4)
	75 aload_1 (1, 4)
	76 invokeinterface (1, 4)
	77 org/apache/commons/math3/Field.org/apache/commons/math3/RealFieldElement (1, 4)
	79 0 (1, 4)
	81 checkcast (1, 4)
	82 org/apache/commons/math3/RealFieldElement (1, 4)
	84 aastore (1, 4)
	85 aload_0 (1, 4)
	86 getfield (1, 4)
	87 org/apache/commons/math3/ode/nonstiff/DormandPrince853FieldStepInterpolator.d:[[Lorg/apache/commons/math3/RealFieldElement; (1, 4)
	89 iconst_0 (1, 4)
	90 aaload (1, 4)
	91 iconst_3 (1, 4)
	92 aload_1 (1, 4)
	93 invokeinterface (1, 4)
	94 org/apache/commons/math3/Field.org/apache/commons/math3/RealFieldElement (1, 4)
	96 0 (1, 4)
	98 checkcast (1, 4)
	99 org/apache/commons/math3/RealFieldElement (1, 4)
	101 aastore (1, 4)
	102 aload_0 (1, 4)
	103 getfield (1, 4)
	104 org/apache/commons/math3/ode/nonstiff/DormandPrince853FieldStepInterpolator.d:[[Lorg/apache/commons/math3/RealFieldElement; (1, 4)
	106 iconst_0 (1, 4)
	107 aaload (1, 4)
	108 iconst_4 (1, 4)
	109 aload_1 (1, 4)
	110 invokeinterface (1, 4)
	111 org/apache/commons/math3/Field.org/apache/commons/math3/RealFieldElement (1, 4)
	113 0 (1, 4)
	115 checkcast (1, 4)
	116 org/apache/commons/math3/RealFieldElement (1, 4)
	118 aastore (1, 4)
	119 aload_0 (1, 4)
	120 getfield (1, 4)
	121 org/apache/commons/math3/ode/nonstiff/DormandPrince853FieldStepInterpolator.d:[[Lorg/apache/commons/math3/RealFieldElement; (1, 4)
	123 iconst_0 (1, 4)
	124 aaload (1, 4)
	125 iconst_5 (1, 4)
	126 aload_0 (1, 4)
	127 aload_1 (1, 4)
	128 ldc2_w (1, 4)
	129 3399327.0 (1, 4)
	131 ldc2_w (1, 4)
	132 763840.0 (1, 4)
	134 invokespecial (1, 4)
	135 org/apache/commons/math3/ode/nonstiff/DormandPrince853FieldStepInterpolator.fraction:(Lorg/apache/commons/math3/Field;DD)Lorg/apache/commons/math3/RealFieldElement; (1, 4)
	137 aastore (1, 4)
	138 aload_0 (1, 4)
	139 getfield (1, 4)
	140 org/apache/commons/math3/ode/nonstiff/DormandPrince853FieldStepInterpolator.d:[[Lorg/apache/commons/math3/RealFieldElement; (1, 4)
	142 iconst_0 (1, 4)
	143 aaload (1, 4)
	144 bipush (1, 4)
	145 6 (1, 4)
	146 aload_0 (1, 4)
	147 aload_1 (1, 4)
	148 ldc2_w (1, 4)
	149 66578432.0 (1, 4)
	151 ldc2_w (1, 4)
	152 35198415.0 (1, 4)
	154 invokespecial (1, 4)
	155 org/apache/commons/math3/ode/nonstiff/DormandPrince853FieldStepInterpolator.fraction:(Lorg/apache/commons/math3/Field;DD)Lorg/apache/commons/math3/RealFieldElement; (1, 4)
	157 aastore (1, 4)
	158 aload_0 (1, 4)
	159 getfield (1, 4)
	160 org/apache/commons/math3/ode/nonstiff/DormandPrince853FieldStepInterpolator.d:[[Lorg/apache/commons/math3/RealFieldElement; (1, 4)
	162 iconst_0 (1, 4)
	163 aaload (1, 4)
	164 bipush (1, 4)
	165 7 (1, 4)
	166 aload_0 (1, 4)
	167 aload_1 (1, 4)
	168 ldc2_w (1, 4)
	169 -1674902723.0 (1, 4)
	171 ldc2_w (1, 4)
	172 288716400.0 (1, 4)
	174 invokespecial (1, 4)
	175 org/apache/commons/math3/ode/nonstiff/DormandPrince853FieldStepInterpolator.fraction:(Lorg/apache/commons/math3/Field;DD)Lorg/apache/commons/math3/RealFieldElement; (1, 4)
	177 aastore (1, 4)
	178 aload_0 (1, 4)
	179 getfield (1, 4)
	180 org/apache/commons/math3/ode/nonstiff/DormandPrince853FieldStepInterpolator.d:[[Lorg/apache/commons/math3/RealFieldElement; (1, 4)
	182 iconst_0 (1, 4)
	183 aaload (1, 4)
	184 bipush (1, 4)
	185 8 (1, 4)
	186 aload_0 (1, 4)
	187 aload_1 (1, 4)
	188 ldc2_w (1, 4)
	189 54980371265625.0 (1, 4)
	191 ldc2_w (1, 4)
	192 176692375811392.0 (1, 4)
	194 invokespecial (1, 4)
	195 org/apache/commons/math3/ode/nonstiff/DormandPrince853FieldStepInterpolator.fraction:(Lorg/apache/commons/math3/Field;DD)Lorg/apache/commons/math3/RealFieldElement; (1, 4)
	197 aastore (1, 4)
	198 aload_0 (1, 4)
	199 getfield (1, 4)
	200 org/apache/commons/math3/ode/nonstiff/DormandPrince853FieldStepInterpolator.d:[[Lorg/apache/commons/math3/RealFieldElement; (1, 4)
	202 iconst_0 (1, 4)
	203 aaload (1, 4)
	204 bipush (1, 4)
	205 9 (1, 4)
	206 aload_0 (1, 4)
	207 aload_1 (1, 4)
	208 ldc2_w (1, 4)
	209 -734375.0 (1, 4)
	211 ldc2_w (1, 4)
	212 4826304.0 (1, 4)
	214 invokespecial (1, 4)
	215 org/apache/commons/math3/ode/nonstiff/DormandPrince853FieldStepInterpolator.fraction:(Lorg/apache/commons/math3/Field;DD)Lorg/apache/commons/math3/RealFieldElement; (1, 4)
	217 aastore (1, 4)
	218 aload_0 (1, 4)
	219 getfield (1, 4)
	220 org/apache/commons/math3/ode/nonstiff/DormandPrince853FieldStepInterpolator.d:[[Lorg/apache/commons/math3/RealFieldElement; (1, 4)
	222 iconst_0 (1, 4)
	223 aaload (1, 4)
	224 bipush (1, 4)
	225 10 (1, 4)
	226 aload_0 (1, 4)
	227 aload_1 (1, 4)
	228 ldc2_w (1, 4)
	229 171414593.0 (1, 4)
	231 ldc2_w (1, 4)
	232 851261400.0 (1, 4)
	234 invokespecial (1, 4)
	235 org/apache/commons/math3/ode/nonstiff/DormandPrince853FieldStepInterpolator.fraction:(Lorg/apache/commons/math3/Field;DD)Lorg/apache/commons/math3/RealFieldElement; (1, 4)
	237 aastore (1, 4)
	238 aload_0 (1, 4)
	239 getfield (1, 4)
	240 org/apache/commons/math3/ode/nonstiff/DormandPrince853FieldStepInterpolator.d:[[Lorg/apache/commons/math3/RealFieldElement; (1, 4)
	242 iconst_0 (1, 4)
	243 aaload (1, 4)
	244 bipush (1, 4)
	245 11 (1, 4)
	246 aload_0 (1, 4)
	247 aload_1 (1, 4)
	248 ldc2_w (1, 4)
	249 137909.0 (1, 4)
	251 ldc2_w (1, 4)
	252 3084480.0 (1, 4)
	254 invokespecial (1, 4)
	255 org/apache/commons/math3/ode/nonstiff/DormandPrince853FieldStepInterpolator.fraction:(Lorg/apache/commons/math3/Field;DD)Lorg/apache/commons/math3/RealFieldElement; (1, 4)
	257 aastore (1, 4)
	258 aload_0 (1, 4)
	259 getfield (1, 4)
	260 org/apache/commons/math3/ode/nonstiff/DormandPrince853FieldStepInterpolator.d:[[Lorg/apache/commons/math3/RealFieldElement; (1, 4)
	262 iconst_0 (1, 4)
	263 aaload (1, 4)
	264 bipush (1, 4)
	265 12 (1, 4)
	266 aload_1 (1, 4)
	267 invokeinterface (1, 4)
	268 org/apache/commons/math3/Field.org/apache/commons/math3/RealFieldElement (1, 4)
	270 0 (1, 4)
	272 checkcast (1, 4)
	273 org/apache/commons/math3/RealFieldElement (1, 4)
	275 aastore (1, 4)
	276 aload_0 (1, 4)
	277 getfield (1, 4)
	278 org/apache/commons/math3/ode/nonstiff/DormandPrince853FieldStepInterpolator.d:[[Lorg/apache/commons/math3/RealFieldElement; (1, 4)
	280 iconst_0 (1, 4)
	281 aaload (1, 4)
	282 bipush (1, 4)
	283 13 (1, 4)
	284 aload_1 (1, 4)
	285 invokeinterface (1, 4)
	286 org/apache/commons/math3/Field.org/apache/commons/math3/RealFieldElement (1, 4)
	288 0 (1, 4)
	290 checkcast (1, 4)
	291 org/apache/commons/math3/RealFieldElement (1, 4)
	293 aastore (1, 4)
	294 aload_0 (1, 4)
	295 getfield (1, 4)
	296 org/apache/commons/math3/ode/nonstiff/DormandPrince853FieldStepInterpolator.d:[[Lorg/apache/commons/math3/RealFieldElement; (1, 4)
	298 iconst_0 (1, 4)
	299 aaload (1, 4)
	300 bipush (1, 4)
	301 14 (1, 4)
	302 aload_1 (1, 4)
	303 invokeinterface (1, 4)
	304 org/apache/commons/math3/Field.org/apache/commons/math3/RealFieldElement (1, 4)
	306 0 (1, 4)
	308 checkcast (1, 4)
	309 org/apache/commons/math3/RealFieldElement (1, 4)
	311 aastore (1, 4)
	312 aload_0 (1, 4)
	313 getfield (1, 4)
	314 org/apache/commons/math3/ode/nonstiff/DormandPrince853FieldStepInterpolator.d:[[Lorg/apache/commons/math3/RealFieldElement; (1, 4)
	316 iconst_0 (1, 4)
	317 aaload (1, 4)
	318 bipush (1, 4)
	319 15 (1, 4)
	320 aload_1 (1, 4)
	321 invokeinterface (1, 4)
	322 org/apache/commons/math3/Field.org/apache/commons/math3/RealFieldElement (1, 4)
	324 0 (1, 4)
	326 checkcast (1, 4)
	327 org/apache/commons/math3/RealFieldElement (1, 4)
	329 aastore (1, 4)
	330 aload_0 (1, 4)
	331 getfield (1, 4)
	332 org/apache/commons/math3/ode/nonstiff/DormandPrince853FieldStepInterpolator.d:[[Lorg/apache/commons/math3/RealFieldElement; (1, 4)
	334 iconst_1 (1, 4)
	335 aaload (1, 4)
	336 iconst_0 (1, 4)
	337 aload_0 (1, 4)
	338 getfield (1, 4)
	339 org/apache/commons/math3/ode/nonstiff/DormandPrince853FieldStepInterpolator.d:[[Lorg/apache/commons/math3/RealFieldElement; (1, 4)
	341 iconst_0 (1, 4)
	342 aaload (1, 4)
	343 iconst_0 (1, 4)
	344 aaload (1, 4)
	345 invokeinterface (1, 4)
	346 org/apache/commons/math3/RealFieldElement.add:(D)Ljava/lang/Object; (1, 4)
	348 0 (1, 4)
	350 checkcast (1, 4)
	351 org/apache/commons/math3/RealFieldElement (1, 4)
	353 dconst_1 (1, 4)
	354 invokeinterface (1, 4)
	355 org/apache/commons/math3/RealFieldElement.multiply:(I)Ljava/lang/Object; (1, 4)
	357 0 (1, 4)
	359 checkcast (1, 4)
	360 org/apache/commons/math3/RealFieldElement (1, 4)
	362 aastore (1, 4)
	363 aload_0 (1, 4)
	364 getfield (1, 4)
	365 org/apache/commons/math3/ode/nonstiff/DormandPrince853FieldStepInterpolator.d:[[Lorg/apache/commons/math3/RealFieldElement; (1, 4)
	367 iconst_1 (1, 4)
	368 aaload (1, 4)
	369 iconst_1 (1, 4)
	370 aload_0 (1, 4)
	371 getfield (1, 4)
	372 org/apache/commons/math3/ode/nonstiff/DormandPrince853FieldStepInterpolator.d:[[Lorg/apache/commons/math3/RealFieldElement; (1, 4)
	374 iconst_0 (1, 4)
	375 aaload (1, 4)
	376 iconst_1 (1, 4)
	377 aaload (1, 4)
	378 invokeinterface (1, 4)
	379 org/apache/commons/math3/RealFieldElement.add:(D)Ljava/lang/Object; (1, 4)
	381 0 (1, 4)
	383 checkcast (1, 4)
	384 org/apache/commons/math3/RealFieldElement (1, 4)
	386 aastore (1, 4)
	387 aload_0 (1, 4)
	388 getfield (1, 4)
	389 org/apache/commons/math3/ode/nonstiff/DormandPrince853FieldStepInterpolator.d:[[Lorg/apache/commons/math3/RealFieldElement; (1, 4)
	391 iconst_1 (1, 4)
	392 aaload (1, 4)
	393 iconst_2 (1, 4)
	394 aload_0 (1, 4)
	395 getfield (1, 4)
	396 org/apache/commons/math3/ode/nonstiff/DormandPrince853FieldStepInterpolator.d:[[Lorg/apache/commons/math3/RealFieldElement; (1, 4)
	398 iconst_0 (1, 4)
	399 aaload (1, 4)
	400 iconst_2 (1, 4)
	401 aaload (1, 4)
	402 invokeinterface (1, 4)
	403 org/apache/commons/math3/RealFieldElement.add:(D)Ljava/lang/Object; (1, 4)
	405 0 (1, 4)
	407 checkcast (1, 4)
	408 org/apache/commons/math3/RealFieldElement (1, 4)
	410 aastore (1, 4)
	411 aload_0 (1, 4)
	412 getfield (1, 4)
	413 org/apache/commons/math3/ode/nonstiff/DormandPrince853FieldStepInterpolator.d:[[Lorg/apache/commons/math3/RealFieldElement; (1, 4)
	415 iconst_1 (1, 4)
	416 aaload (1, 4)
	417 iconst_3 (1, 4)
	418 aload_0 (1, 4)
	419 getfield (1, 4)
	420 org/apache/commons/math3/ode/nonstiff/DormandPrince853FieldStepInterpolator.d:[[Lorg/apache/commons/math3/RealFieldElement; (1, 4)
	422 iconst_0 (1, 4)
	423 aaload (1, 4)
	424 iconst_3 (1, 4)
	425 aaload (1, 4)
	426 invokeinterface (1, 4)
	427 org/apache/commons/math3/RealFieldElement.add:(D)Ljava/lang/Object; (1, 4)
	429 0 (1, 4)
	431 checkcast (1, 4)
	432 org/apache/commons/math3/RealFieldElement (1, 4)
	434 aastore (1, 4)
	435 aload_0 (1, 4)
	436 getfield (1, 4)
	437 org/apache/commons/math3/ode/nonstiff/DormandPrince853FieldStepInterpolator.d:[[Lorg/apache/commons/math3/RealFieldElement; (1, 4)
	439 iconst_1 (1, 4)
	440 aaload (1, 4)
	441 iconst_4 (1, 4)
	442 aload_0 (1, 4)
	443 getfield (1, 4)
	444 org/apache/commons/math3/ode/nonstiff/DormandPrince853FieldStepInterpolator.d:[[Lorg/apache/commons/math3/RealFieldElement; (1, 4)
	446 iconst_0 (1, 4)
	447 aaload (1, 4)
	448 iconst_4 (1, 4)
	449 aaload (1, 4)
	450 invokeinterface (1, 4)
	451 org/apache/commons/math3/RealFieldElement.add:(D)Ljava/lang/Object; (1, 4)
	453 0 (1, 4)
	455 checkcast (1, 4)
	456 org/apache/commons/math3/RealFieldElement (1, 4)
	458 aastore (1, 4)
	459 aload_0 (1, 4)
	460 getfield (1, 4)
	461 org/apache/commons/math3/ode/nonstiff/DormandPrince853FieldStepInterpolator.d:[[Lorg/apache/commons/math3/RealFieldElement; (1, 4)
	463 iconst_1 (1, 4)
	464 aaload (1, 4)
	465 iconst_5 (1, 4)
	466 aload_0 (1, 4)
	467 getfield (1, 4)
	468 org/apache/commons/math3/ode/nonstiff/DormandPrince853FieldStepInterpolator.d:[[Lorg/apache/commons/math3/RealFieldElement; (1, 4)
	470 iconst_0 (1, 4)
	471 aaload (1, 4)
	472 iconst_5 (1, 4)
	473 aaload (1, 4)
	474 invokeinterface (1, 4)
	475 org/apache/commons/math3/RealFieldElement.add:(D)Ljava/lang/Object; (1, 4)
	477 0 (1, 4)
	479 checkcast (1, 4)
	480 org/apache/commons/math3/RealFieldElement (1, 4)
	482 aastore (1, 4)
	483 aload_0 (1, 4)
	484 getfield (1, 4)
	485 org/apache/commons/math3/ode/nonstiff/DormandPrince853FieldStepInterpolator.d:[[Lorg/apache/commons/math3/RealFieldElement; (1, 4)
	487 iconst_1 (1, 4)
	488 aaload (1, 4)
	489 bipush (1, 4)
	490 6 (1, 4)
	491 aload_0 (1, 4)
	492 getfield (1, 4)
	493 org/apache/commons/math3/ode/nonstiff/DormandPrince853FieldStepInterpolator.d:[[Lorg/apache/commons/math3/RealFieldElement; (1, 4)
	495 iconst_0 (1, 4)
	496 aaload (1, 4)
	497 bipush (1, 4)
	498 6 (1, 4)
	499 aaload (1, 4)
	500 invokeinterface (1, 4)
	501 org/apache/commons/math3/RealFieldElement.add:(D)Ljava/lang/Object; (1, 4)
	503 0 (1, 4)
	505 checkcast (1, 4)
	506 org/apache/commons/math3/RealFieldElement (1, 4)
	508 aastore (1, 4)
	509 aload_0 (1, 4)
	510 getfield (1, 4)
	511 org/apache/commons/math3/ode/nonstiff/DormandPrince853FieldStepInterpolator.d:[[Lorg/apache/commons/math3/RealFieldElement; (1, 4)
	513 iconst_1 (1, 4)
	514 aaload (1, 4)
	515 bipush (1, 4)
	516 7 (1, 4)
	517 aload_0 (1, 4)
	518 getfield (1, 4)
	519 org/apache/commons/math3/ode/nonstiff/DormandPrince853FieldStepInterpolator.d:[[Lorg/apache/commons/math3/RealFieldElement; (1, 4)
	521 iconst_0 (1, 4)
	522 aaload (1, 4)
	523 bipush (1, 4)
	524 7 (1, 4)
	525 aaload (1, 4)
	526 invokeinterface (1, 4)
	527 org/apache/commons/math3/RealFieldElement.add:(D)Ljava/lang/Object; (1, 4)
	529 0 (1, 4)
	531 checkcast (1, 4)
	532 org/apache/commons/math3/RealFieldElement (1, 4)
	534 aastore (1, 4)
	535 aload_0 (1, 4)
	536 getfield (1, 4)
	537 org/apache/commons/math3/ode/nonstiff/DormandPrince853FieldStepInterpolator.d:[[Lorg/apache/commons/math3/RealFieldElement; (1, 4)
	539 iconst_1 (1, 4)
	540 aaload (1, 4)
	541 bipush (1, 4)
	542 8 (1, 4)
	543 aload_0 (1, 4)
	544 getfield (1, 4)
	545 org/apache/commons/math3/ode/nonstiff/DormandPrince853FieldStepInterpolator.d:[[Lorg/apache/commons/math3/RealFieldElement; (1, 4)
	547 iconst_0 (1, 4)
	548 aaload (1, 4)
	549 bipush (1, 4)
	550 8 (1, 4)
	551 aaload (1, 4)
	552 invokeinterface (1, 4)
	553 org/apache/commons/math3/RealFieldElement.add:(D)Ljava/lang/Object; (1, 4)
	555 0 (1, 4)
	557 checkcast (1, 4)
	558 org/apache/commons/math3/RealFieldElement (1, 4)
	560 aastore (1, 4)
	561 aload_0 (1, 4)
	562 getfield (1, 4)
	563 org/apache/commons/math3/ode/nonstiff/DormandPrince853FieldStepInterpolator.d:[[Lorg/apache/commons/math3/RealFieldElement; (1, 4)
	565 iconst_1 (1, 4)
	566 aaload (1, 4)
	567 bipush (1, 4)
	568 9 (1, 4)
	569 aload_0 (1, 4)
	570 getfield (1, 4)
	571 org/apache/commons/math3/ode/nonstiff/DormandPrince853FieldStepInterpolator.d:[[Lorg/apache/commons/math3/RealFieldElement; (1, 4)
	573 iconst_0 (1, 4)
	574 aaload (1, 4)
	575 bipush (1, 4)
	576 9 (1, 4)
	577 aaload (1, 4)
	578 invokeinterface (1, 4)
	579 org/apache/commons/math3/RealFieldElement.add:(D)Ljava/lang/Object; (1, 4)
	581 0 (1, 4)
	583 checkcast (1, 4)
	584 org/apache/commons/math3/RealFieldElement (1, 4)
	586 aastore (1, 4)
	587 aload_0 (1, 4)
	588 getfield (1, 4)
	589 org/apache/commons/math3/ode/nonstiff/DormandPrince853FieldStepInterpolator.d:[[Lorg/apache/commons/math3/RealFieldElement; (1, 4)
	591 iconst_1 (1, 4)
	592 aaload (1, 4)
	593 bipush (1, 4)
	594 10 (1, 4)
	595 aload_0 (1, 4)
	596 getfield (1, 4)
	597 org/apache/commons/math3/ode/nonstiff/DormandPrince853FieldStepInterpolator.d:[[Lorg/apache/commons/math3/RealFieldElement; (1, 4)
	599 iconst_0 (1, 4)
	600 aaload (1, 4)
	601 bipush (1, 4)
	602 10 (1, 4)
	603 aaload (1, 4)
	604 invokeinterface (1, 4)
	605 org/apache/commons/math3/RealFieldElement.add:(D)Ljava/lang/Object; (1, 4)
	607 0 (1, 4)
	609 checkcast (1, 4)
	610 org/apache/commons/math3/RealFieldElement (1, 4)
	612 aastore (1, 4)
	613 aload_0 (1, 4)
	614 getfield (1, 4)
	615 org/apache/commons/math3/ode/nonstiff/DormandPrince853FieldStepInterpolator.d:[[Lorg/apache/commons/math3/RealFieldElement; (1, 4)
	617 iconst_1 (1, 4)
	618 aaload (1, 4)
	619 bipush (1, 4)
	620 11 (1, 4)
	621 aload_0 (1, 4)
	622 getfield (1, 4)
	623 org/apache/commons/math3/ode/nonstiff/DormandPrince853FieldStepInterpolator.d:[[Lorg/apache/commons/math3/RealFieldElement; (1, 4)
	625 iconst_0 (1, 4)
	626 aaload (1, 4)
	627 bipush (1, 4)
	628 11 (1, 4)
	629 aaload (1, 4)
	630 invokeinterface (1, 4)
	631 org/apache/commons/math3/RealFieldElement.add:(D)Ljava/lang/Object; (1, 4)
	633 0 (1, 4)
	635 checkcast (1, 4)
	636 org/apache/commons/math3/RealFieldElement (1, 4)
	638 aastore (1, 4)
	639 aload_0 (1, 4)
	640 getfield (1, 4)
	641 org/apache/commons/math3/ode/nonstiff/DormandPrince853FieldStepInterpolator.d:[[Lorg/apache/commons/math3/RealFieldElement; (1, 4)
	643 iconst_1 (1, 4)
	644 aaload (1, 4)
	645 bipush (1, 4)
	646 12 (1, 4)
	647 aload_0 (1, 4)
	648 getfield (1, 4)
	649 org/apache/commons/math3/ode/nonstiff/DormandPrince853FieldStepInterpolator.d:[[Lorg/apache/commons/math3/RealFieldElement; (1, 4)
	651 iconst_0 (1, 4)
	652 aaload (1, 4)
	653 bipush (1, 4)
	654 12 (1, 4)
	655 aaload (1, 4)
	656 invokeinterface (1, 4)
	657 org/apache/commons/math3/RealFieldElement.add:(D)Ljava/lang/Object; (1, 4)
	659 0 (1, 4)
	661 checkcast (1, 4)
	662 org/apache/commons/math3/RealFieldElement (1, 4)
	664 aastore (1, 4)
	665 aload_0 (1, 4)
	666 getfield (1, 4)
	667 org/apache/commons/math3/ode/nonstiff/DormandPrince853FieldStepInterpolator.d:[[Lorg/apache/commons/math3/RealFieldElement; (1, 4)
	669 iconst_1 (1, 4)
	670 aaload (1, 4)
	671 bipush (1, 4)
	672 13 (1, 4)
	673 aload_0 (1, 4)
	674 getfield (1, 4)
	675 org/apache/commons/math3/ode/nonstiff/DormandPrince853FieldStepInterpolator.d:[[Lorg/apache/commons/math3/RealFieldElement; (1, 4)
	677 iconst_0 (1, 4)
	678 aaload (1, 4)
	679 bipush (1, 4)
	680 13 (1, 4)
	681 aaload (1, 4)
	682 invokeinterface (1, 4)
	683 org/apache/commons/math3/RealFieldElement.add:(D)Ljava/lang/Object; (1, 4)
	685 0 (1, 4)
	687 checkcast (1, 4)
	688 org/apache/commons/math3/RealFieldElement (1, 4)
	690 aastore (1, 4)
	691 aload_0 (1, 4)
	692 getfield (1, 4)
	693 org/apache/commons/math3/ode/nonstiff/DormandPrince853FieldStepInterpolator.d:[[Lorg/apache/commons/math3/RealFieldElement; (1, 4)
	695 iconst_1 (1, 4)
	696 aaload (1, 4)
	697 bipush (1, 4)
	698 14 (1, 4)
	699 aload_0 (1, 4)
	700 getfield (1, 4)
	701 org/apache/commons/math3/ode/nonstiff/DormandPrince853FieldStepInterpolator.d:[[Lorg/apache/commons/math3/RealFieldElement; (1, 4)
	703 iconst_0 (1, 4)
	704 aaload (1, 4)
	705 bipush (1, 4)
	706 14 (1, 4)
	707 aaload (1, 4)
	708 invokeinterface (1, 4)
	709 org/apache/commons/math3/RealFieldElement.add:(D)Ljava/lang/Object; (1, 4)
	711 0 (1, 4)
	713 checkcast (1, 4)
	714 org/apache/commons/math3/RealFieldElement (1, 4)
	716 aastore (1, 4)
	717 aload_0 (1, 4)
	718 getfield (1, 4)
	719 org/apache/commons/math3/ode/nonstiff/DormandPrince853FieldStepInterpolator.d:[[Lorg/apache/commons/math3/RealFieldElement; (1, 4)
	721 iconst_1 (1, 4)
	722 aaload (1, 4)
	723 bipush (1, 4)
	724 15 (1, 4)
	725 aload_0 (1, 4)
	726 getfield (1, 4)
	727 org/apache/commons/math3/ode/nonstiff/DormandPrince853FieldStepInterpolator.d:[[Lorg/apache/commons/math3/RealFieldElement; (1, 4)
	729 iconst_0 (1, 4)
	730 aaload (1, 4)
	731 bipush (1, 4)
	732 15 (1, 4)
	733 aaload (1, 4)
	734 invokeinterface (1, 4)
	735 org/apache/commons/math3/RealFieldElement.add:(D)Ljava/lang/Object; (1, 4)
	737 0 (1, 4)
	739 checkcast (1, 4)
	740 org/apache/commons/math3/RealFieldElement (1, 4)
	742 aastore (1, 4)
	743 aload_0 (1, 4)
	744 getfield (1, 4)
	745 org/apache/commons/math3/ode/nonstiff/DormandPrince853FieldStepInterpolator.d:[[Lorg/apache/commons/math3/RealFieldElement; (1, 4)
	747 iconst_2 (1, 4)
	748 aaload (1, 4)
	749 iconst_0 (1, 4)
	750 aload_0 (1, 4)
	751 getfield (1, 4)
	752 org/apache/commons/math3/ode/nonstiff/DormandPrince853FieldStepInterpolator.d:[[Lorg/apache/commons/math3/RealFieldElement; (1, 4)
	754 iconst_0 (1, 4)
	755 aaload (1, 4)
	756 iconst_0 (1, 4)
	757 aaload (1, 4)
	758 iconst_2 (1, 4)
	759 invokeinterface (1, 4)
	760 org/apache/commons/math3/RealFieldElement.subtract:(D)Ljava/lang/Object; (1, 4)
	762 0 (1, 4)
	764 checkcast (1, 4)
	765 org/apache/commons/math3/RealFieldElement (1, 4)
	767 dconst_1 (1, 4)
	768 invokeinterface (1, 4)
	769 org/apache/commons/math3/RealFieldElement.org/apache/commons/math3/ode/nonstiff/DormandPrince853FieldStepInterpolator (1, 4)
	771 0 (1, 4)
	773 checkcast (1, 4)
	774 org/apache/commons/math3/RealFieldElement (1, 4)
	776 aastore (1, 4)
	777 aload_0 (1, 4)
	778 getfield (1, 4)
	779 org/apache/commons/math3/ode/nonstiff/DormandPrince853FieldStepInterpolator.d:[[Lorg/apache/commons/math3/RealFieldElement; (1, 4)
	781 iconst_2 (1, 4)
	782 aaload (1, 4)
	783 iconst_1 (1, 4)
	784 aload_0 (1, 4)
	785 getfield (1, 4)
	786 org/apache/commons/math3/ode/nonstiff/DormandPrince853FieldStepInterpolator.d:[[Lorg/apache/commons/math3/RealFieldElement; (1, 4)
	788 iconst_0 (1, 4)
	789 aaload (1, 4)
	790 iconst_1 (1, 4)
	791 aaload (1, 4)
	792 iconst_2 (1, 4)
	793 invokeinterface (1, 4)
	794 org/apache/commons/math3/RealFieldElement.subtract:(D)Ljava/lang/Object; (1, 4)
	796 0 (1, 4)
	798 checkcast (1, 4)
	799 org/apache/commons/math3/RealFieldElement (1, 4)
	801 aastore (1, 4)
	802 aload_0 (1, 4)
	803 getfield (1, 4)
	804 org/apache/commons/math3/ode/nonstiff/DormandPrince853FieldStepInterpolator.d:[[Lorg/apache/commons/math3/RealFieldElement; (1, 4)
	806 iconst_2 (1, 4)
	807 aaload (1, 4)
	808 iconst_2 (1, 4)
	809 aload_0 (1, 4)
	810 getfield (1, 4)
	811 org/apache/commons/math3/ode/nonstiff/DormandPrince853FieldStepInterpolator.d:[[Lorg/apache/commons/math3/RealFieldElement; (1, 4)
	813 iconst_0 (1, 4)
	814 aaload (1, 4)
	815 iconst_2 (1, 4)
	816 aaload (1, 4)
	817 iconst_2 (1, 4)
	818 invokeinterface (1, 4)
	819 org/apache/commons/math3/RealFieldElement.subtract:(D)Ljava/lang/Object; (1, 4)
	821 0 (1, 4)
	823 checkcast (1, 4)
	824 org/apache/commons/math3/RealFieldElement (1, 4)
	826 aastore (1, 4)
	827 aload_0 (1, 4)
	828 getfield (1, 4)
	829 org/apache/commons/math3/ode/nonstiff/DormandPrince853FieldStepInterpolator.d:[[Lorg/apache/commons/math3/RealFieldElement; (1, 4)
	831 iconst_2 (1, 4)
	832 aaload (1, 4)
	833 iconst_3 (1, 4)
	834 aload_0 (1, 4)
	835 getfield (1, 4)
	836 org/apache/commons/math3/ode/nonstiff/DormandPrince853FieldStepInterpolator.d:[[Lorg/apache/commons/math3/RealFieldElement; (1, 4)
	838 iconst_0 (1, 4)
	839 aaload (1, 4)
	840 iconst_3 (1, 4)
	841 aaload (1, 4)
	842 iconst_2 (1, 4)
	843 invokeinterface (1, 4)
	844 org/apache/commons/math3/RealFieldElement.subtract:(D)Ljava/lang/Object; (1, 4)
	846 0 (1, 4)
	848 checkcast (1, 4)
	849 org/apache/commons/math3/RealFieldElement (1, 4)
	851 aastore (1, 4)
	852 aload_0 (1, 4)
	853 getfield (1, 4)
	854 org/apache/commons/math3/ode/nonstiff/DormandPrince853FieldStepInterpolator.d:[[Lorg/apache/commons/math3/RealFieldElement; (1, 4)
	856 iconst_2 (1, 4)
	857 aaload (1, 4)
	858 iconst_4 (1, 4)
	859 aload_0 (1, 4)
	860 getfield (1, 4)
	861 org/apache/commons/math3/ode/nonstiff/DormandPrince853FieldStepInterpolator.d:[[Lorg/apache/commons/math3/RealFieldElement; (1, 4)
	863 iconst_0 (1, 4)
	864 aaload (1, 4)
	865 iconst_4 (1, 4)
	866 aaload (1, 4)
	867 iconst_2 (1, 4)
	868 invokeinterface (1, 4)
	869 org/apache/commons/math3/RealFieldElement.subtract:(D)Ljava/lang/Object; (1, 4)
	871 0 (1, 4)
	873 checkcast (1, 4)
	874 org/apache/commons/math3/RealFieldElement (1, 4)
	876 aastore (1, 4)
	877 aload_0 (1, 4)
	878 getfield (1, 4)
	879 org/apache/commons/math3/ode/nonstiff/DormandPrince853FieldStepInterpolator.d:[[Lorg/apache/commons/math3/RealFieldElement; (1, 4)
	881 iconst_2 (1, 4)
	882 aaload (1, 4)
	883 iconst_5 (1, 4)
	884 aload_0 (1, 4)
	885 getfield (1, 4)
	886 org/apache/commons/math3/ode/nonstiff/DormandPrince853FieldStepInterpolator.d:[[Lorg/apache/commons/math3/RealFieldElement; (1, 4)
	888 iconst_0 (1, 4)
	889 aaload (1, 4)
	890 iconst_5 (1, 4)
	891 aaload (1, 4)
	892 iconst_2 (1, 4)
	893 invokeinterface (1, 4)
	894 org/apache/commons/math3/RealFieldElement.subtract:(D)Ljava/lang/Object; (1, 4)
	896 0 (1, 4)
	898 checkcast (1, 4)
	899 org/apache/commons/math3/RealFieldElement (1, 4)
	901 aastore (1, 4)
	902 aload_0 (1, 4)
	903 getfield (1, 4)
	904 org/apache/commons/math3/ode/nonstiff/DormandPrince853FieldStepInterpolator.d:[[Lorg/apache/commons/math3/RealFieldElement; (1, 4)
	906 iconst_2 (1, 4)
	907 aaload (1, 4)
	908 bipush (1, 4)
	909 6 (1, 4)
	910 aload_0 (1, 4)
	911 getfield (1, 4)
	912 org/apache/commons/math3/ode/nonstiff/DormandPrince853FieldStepInterpolator.d:[[Lorg/apache/commons/math3/RealFieldElement; (1, 4)
	914 iconst_0 (1, 4)
	915 aaload (1, 4)
	916 bipush (1, 4)
	917 6 (1, 4)
	918 aaload (1, 4)
	919 iconst_2 (1, 4)
	920 invokeinterface (1, 4)
	921 org/apache/commons/math3/RealFieldElement.subtract:(D)Ljava/lang/Object; (1, 4)
	923 0 (1, 4)
	925 checkcast (1, 4)
	926 org/apache/commons/math3/RealFieldElement (1, 4)
	928 aastore (1, 4)
	929 aload_0 (1, 4)
	930 getfield (1, 4)
	931 org/apache/commons/math3/ode/nonstiff/DormandPrince853FieldStepInterpolator.d:[[Lorg/apache/commons/math3/RealFieldElement; (1, 4)
	933 iconst_2 (1, 4)
	934 aaload (1, 4)
	935 bipush (1, 4)
	936 7 (1, 4)
	937 aload_0 (1, 4)
	938 getfield (1, 4)
	939 org/apache/commons/math3/ode/nonstiff/DormandPrince853FieldStepInterpolator.d:[[Lorg/apache/commons/math3/RealFieldElement; (1, 4)
	941 iconst_0 (1, 4)
	942 aaload (1, 4)
	943 bipush (1, 4)
	944 7 (1, 4)
	945 aaload (1, 4)
	946 iconst_2 (1, 4)
	947 invokeinterface (1, 4)
	948 org/apache/commons/math3/RealFieldElement.subtract:(D)Ljava/lang/Object; (1, 4)
	950 0 (1, 4)
	952 checkcast (1, 4)
	953 org/apache/commons/math3/RealFieldElement (1, 4)
	955 aastore (1, 4)
	956 aload_0 (1, 4)
	957 getfield (1, 4)
	958 org/apache/commons/math3/ode/nonstiff/DormandPrince853FieldStepInterpolator.d:[[Lorg/apache/commons/math3/RealFieldElement; (1, 4)
	960 iconst_2 (1, 4)
	961 aaload (1, 4)
	962 bipush (1, 4)
	963 8 (1, 4)
	964 aload_0 (1, 4)
	965 getfield (1, 4)
	966 org/apache/commons/math3/ode/nonstiff/DormandPrince853FieldStepInterpolator.d:[[Lorg/apache/commons/math3/RealFieldElement; (1, 4)
	968 iconst_0 (1, 4)
	969 aaload (1, 4)
	970 bipush (1, 4)
	971 8 (1, 4)
	972 aaload (1, 4)
	973 iconst_2 (1, 4)
	974 invokeinterface (1, 4)
	975 org/apache/commons/math3/RealFieldElement.subtract:(D)Ljava/lang/Object; (1, 4)
	977 0 (1, 4)
	979 checkcast (1, 4)
	980 org/apache/commons/math3/RealFieldElement (1, 4)
	982 aastore (1, 4)
	983 aload_0 (1, 4)
	984 getfield (1, 4)
	985 org/apache/commons/math3/ode/nonstiff/DormandPrince853FieldStepInterpolator.d:[[Lorg/apache/commons/math3/RealFieldElement; (1, 4)
	987 iconst_2 (1, 4)
	988 aaload (1, 4)
	989 bipush (1, 4)
	990 9 (1, 4)
	991 aload_0 (1, 4)
	992 getfield (1, 4)
	993 org/apache/commons/math3/ode/nonstiff/DormandPrince853FieldStepInterpolator.d:[[Lorg/apache/commons/math3/RealFieldElement; (1, 4)
	995 iconst_0 (1, 4)
	996 aaload (1, 4)
	997 bipush (1, 4)
	998 9 (1, 4)
	999 aaload (1, 4)
	1000 iconst_2 (1, 4)
	1001 invokeinterface (1, 4)
	1002 org/apache/commons/math3/RealFieldElement.subtract:(D)Ljava/lang/Object; (1, 4)
	1004 0 (1, 4)
	1006 checkcast (1, 4)
	1007 org/apache/commons/math3/RealFieldElement (1, 4)
	1009 aastore (1, 4)
	1010 aload_0 (1, 4)
	1011 getfield (1, 4)
	1012 org/apache/commons/math3/ode/nonstiff/DormandPrince853FieldStepInterpolator.d:[[Lorg/apache/commons/math3/RealFieldElement; (1, 4)
	1014 iconst_2 (1, 4)
	1015 aaload (1, 4)
	1016 bipush (1, 4)
	1017 10 (1, 4)
	1018 aload_0 (1, 4)
	1019 getfield (1, 4)
	1020 org/apache/commons/math3/ode/nonstiff/DormandPrince853FieldStepInterpolator.d:[[Lorg/apache/commons/math3/RealFieldElement; (1, 4)
	1022 iconst_0 (1, 4)
	1023 aaload (1, 4)
	1024 bipush (1, 4)
	1025 10 (1, 4)
	1026 aaload (1, 4)
	1027 iconst_2 (1, 4)
	1028 invokeinterface (1, 4)
	1029 org/apache/commons/math3/RealFieldElement.subtract:(D)Ljava/lang/Object; (1, 4)
	1031 0 (1, 4)
	1033 checkcast (1, 4)
	1034 org/apache/commons/math3/RealFieldElement (1, 4)
	1036 aastore (1, 4)
	1037 aload_0 (1, 4)
	1038 getfield (1, 4)
	1039 org/apache/commons/math3/ode/nonstiff/DormandPrince853FieldStepInterpolator.d:[[Lorg/apache/commons/math3/RealFieldElement; (1, 4)
	1041 iconst_2 (1, 4)
	1042 aaload (1, 4)
	1043 bipush (1, 4)
	1044 11 (1, 4)
	1045 aload_0 (1, 4)
	1046 getfield (1, 4)
	1047 org/apache/commons/math3/ode/nonstiff/DormandPrince853FieldStepInterpolator.d:[[Lorg/apache/commons/math3/RealFieldElement; (1, 4)
	1049 iconst_0 (1, 4)
	1050 aaload (1, 4)
	1051 bipush (1, 4)
	1052 11 (1, 4)
	1053 aaload (1, 4)
	1054 iconst_2 (1, 4)
	1055 invokeinterface (1, 4)
	1056 org/apache/commons/math3/RealFieldElement.subtract:(D)Ljava/lang/Object; (1, 4)
	1058 0 (1, 4)
	1060 checkcast (1, 4)
	1061 org/apache/commons/math3/RealFieldElement (1, 4)
	1063 aastore (1, 4)
	1064 aload_0 (1, 4)
	1065 getfield (1, 4)
	1066 org/apache/commons/math3/ode/nonstiff/DormandPrince853FieldStepInterpolator.d:[[Lorg/apache/commons/math3/RealFieldElement; (1, 4)
	1068 iconst_2 (1, 4)
	1069 aaload (1, 4)
	1070 bipush (1, 4)
	1071 12 (1, 4)
	1072 aload_0 (1, 4)
	1073 getfield (1, 4)
	1074 org/apache/commons/math3/ode/nonstiff/DormandPrince853FieldStepInterpolator.d:[[Lorg/apache/commons/math3/RealFieldElement; (1, 4)
	1076 iconst_0 (1, 4)
	1077 aaload (1, 4)
	1078 bipush (1, 4)
	1079 12 (1, 4)
	1080 aaload (1, 4)
	1081 iconst_2 (1, 4)
	1082 invokeinterface (1, 4)
	1083 org/apache/commons/math3/RealFieldElement.subtract:(D)Ljava/lang/Object; (1, 4)
	1085 0 (1, 4)
	1087 checkcast (1, 4)
	1088 org/apache/commons/math3/RealFieldElement (1, 4)
	1090 dconst_1 (1, 4)
	1091 invokeinterface (1, 4)
	1092 org/apache/commons/math3/RealFieldElement.org/apache/commons/math3/ode/nonstiff/DormandPrince853FieldStepInterpolator (1, 4)
	1094 0 (1, 4)
	1096 checkcast (1, 4)
	1097 org/apache/commons/math3/RealFieldElement (1, 4)
	1099 aastore (1, 4)
	1100 aload_0 (1, 4)
	1101 getfield (1, 4)
	1102 org/apache/commons/math3/ode/nonstiff/DormandPrince853FieldStepInterpolator.d:[[Lorg/apache/commons/math3/RealFieldElement; (1, 4)
	1104 iconst_2 (1, 4)
	1105 aaload (1, 4)
	1106 bipush (1, 4)
	1107 13 (1, 4)
	1108 aload_0 (1, 4)
	1109 getfield (1, 4)
	1110 org/apache/commons/math3/ode/nonstiff/DormandPrince853FieldStepInterpolator.d:[[Lorg/apache/commons/math3/RealFieldElement; (1, 4)
	1112 iconst_0 (1, 4)
	1113 aaload (1, 4)
	1114 bipush (1, 4)
	1115 13 (1, 4)
	1116 aaload (1, 4)
	1117 iconst_2 (1, 4)
	1118 invokeinterface (1, 4)
	1119 org/apache/commons/math3/RealFieldElement.subtract:(D)Ljava/lang/Object; (1, 4)
	1121 0 (1, 4)
	1123 checkcast (1, 4)
	1124 org/apache/commons/math3/RealFieldElement (1, 4)
	1126 aastore (1, 4)
	1127 aload_0 (1, 4)
	1128 getfield (1, 4)
	1129 org/apache/commons/math3/ode/nonstiff/DormandPrince853FieldStepInterpolator.d:[[Lorg/apache/commons/math3/RealFieldElement; (1, 4)
	1131 iconst_2 (1, 4)
	1132 aaload (1, 4)
	1133 bipush (1, 4)
	1134 14 (1, 4)
	1135 aload_0 (1, 4)
	1136 getfield (1, 4)
	1137 org/apache/commons/math3/ode/nonstiff/DormandPrince853FieldStepInterpolator.d:[[Lorg/apache/commons/math3/RealFieldElement; (1, 4)
	1139 iconst_0 (1, 4)
	1140 aaload (1, 4)
	1141 bipush (1, 4)
	1142 14 (1, 4)
	1143 aaload (1, 4)
	1144 iconst_2 (1, 4)
	1145 invokeinterface (1, 4)
	1146 org/apache/commons/math3/RealFieldElement.subtract:(D)Ljava/lang/Object; (1, 4)
	1148 0 (1, 4)
	1150 checkcast (1, 4)
	1151 org/apache/commons/math3/RealFieldElement (1, 4)
	1153 aastore (1, 4)
	1154 aload_0 (1, 4)
	1155 getfield (1, 4)
	1156 org/apache/commons/math3/ode/nonstiff/DormandPrince853FieldStepInterpolator.d:[[Lorg/apache/commons/math3/RealFieldElement; (1, 4)
	1158 iconst_2 (1, 4)
	1159 aaload (1, 4)
	1160 bipush (1, 4)
	1161 15 (1, 4)
	1162 aload_0 (1, 4)
	1163 getfield (1, 4)
	1164 org/apache/commons/math3/ode/nonstiff/DormandPrince853FieldStepInterpolator.d:[[Lorg/apache/commons/math3/RealFieldElement; (1, 4)
	1166 iconst_0 (1, 4)
	1167 aaload (1, 4)
	1168 bipush (1, 4)
	1169 15 (1, 4)
	1170 aaload (1, 4)
	1171 iconst_2 (1, 4)
	1172 invokeinterface (1, 4)
	1173 org/apache/commons/math3/RealFieldElement.subtract:(D)Ljava/lang/Object; (1, 4)
	1175 0 (1, 4)
	1177 checkcast (1, 4)
	1178 org/apache/commons/math3/RealFieldElement (1, 4)
	1180 aastore (1, 4)
	1181 aload_0 (1, 4)
	1182 getfield (1, 4)
	1183 org/apache/commons/math3/ode/nonstiff/DormandPrince853FieldStepInterpolator.d:[[Lorg/apache/commons/math3/RealFieldElement; (1, 4)
	1185 iconst_3 (1, 4)
	1186 aaload (1, 4)
	1187 iconst_0 (1, 4)
	1188 aload_0 (1, 4)
	1189 aload_1 (1, 4)
	1190 ldc2_w (1, 4)
	1191 -17751989329.0 (1, 4)
	1193 ldc2_w (1, 4)
	1194 2106076560.0 (1, 4)
	1196 invokespecial (1, 4)
	1197 org/apache/commons/math3/ode/nonstiff/DormandPrince853FieldStepInterpolator.fraction:(Lorg/apache/commons/math3/Field;DD)Lorg/apache/commons/math3/RealFieldElement; (1, 4)
	1199 aastore (1, 4)
	1200 aload_0 (1, 4)
	1201 getfield (1, 4)
	1202 org/apache/commons/math3/ode/nonstiff/DormandPrince853FieldStepInterpolator.d:[[Lorg/apache/commons/math3/RealFieldElement; (1, 4)
	1204 iconst_3 (1, 4)
	1205 aaload (1, 4)
	1206 iconst_1 (1, 4)
	1207 aload_1 (1, 4)
	1208 invokeinterface (1, 4)
	1209 org/apache/commons/math3/Field.org/apache/commons/math3/RealFieldElement (1, 4)
	1211 0 (1, 4)
	1213 checkcast (1, 4)
	1214 org/apache/commons/math3/RealFieldElement (1, 4)
	1216 aastore (1, 4)
	1217 aload_0 (1, 4)
	1218 getfield (1, 4)
	1219 org/apache/commons/math3/ode/nonstiff/DormandPrince853FieldStepInterpolator.d:[[Lorg/apache/commons/math3/RealFieldElement; (1, 4)
	1221 iconst_3 (1, 4)
	1222 aaload (1, 4)
	1223 iconst_2 (1, 4)
	1224 aload_1 (1, 4)
	1225 invokeinterface (1, 4)
	1226 org/apache/commons/math3/Field.org/apache/commons/math3/RealFieldElement (1, 4)
	1228 0 (1, 4)
	1230 checkcast (1, 4)
	1231 org/apache/commons/math3/RealFieldElement (1, 4)
	1233 aastore (1, 4)
	1234 aload_0 (1, 4)
	1235 getfield (1, 4)
	1236 org/apache/commons/math3/ode/nonstiff/DormandPrince853FieldStepInterpolator.d:[[Lorg/apache/commons/math3/RealFieldElement; (1, 4)
	1238 iconst_3 (1, 4)
	1239 aaload (1, 4)
	1240 iconst_3 (1, 4)
	1241 aload_1 (1, 4)
	1242 invokeinterface (1, 4)
	1243 org/apache/commons/math3/Field.org/apache/commons/math3/RealFieldElement (1, 4)
	1245 0 (1, 4)
	1247 checkcast (1, 4)
	1248 org/apache/commons/math3/RealFieldElement (1, 4)
	1250 aastore (1, 4)
	1251 aload_0 (1, 4)
	1252 getfield (1, 4)
	1253 org/apache/commons/math3/ode/nonstiff/DormandPrince853FieldStepInterpolator.d:[[Lorg/apache/commons/math3/RealFieldElement; (1, 4)
	1255 iconst_3 (1, 4)
	1256 aaload (1, 4)
	1257 iconst_4 (1, 4)
	1258 aload_1 (1, 4)
	1259 invokeinterface (1, 4)
	1260 org/apache/commons/math3/Field.org/apache/commons/math3/RealFieldElement (1, 4)
	1262 0 (1, 4)
	1264 checkcast (1, 4)
	1265 org/apache/commons/math3/RealFieldElement (1, 4)
	1267 aastore (1, 4)
	1268 aload_0 (1, 4)
	1269 getfield (1, 4)
	1270 org/apache/commons/math3/ode/nonstiff/DormandPrince853FieldStepInterpolator.d:[[Lorg/apache/commons/math3/RealFieldElement; (1, 4)
	1272 iconst_3 (1, 4)
	1273 aaload (1, 4)
	1274 iconst_5 (1, 4)
	1275 aload_0 (1, 4)
	1276 aload_1 (1, 4)
	1277 ldc2_w (1, 4)
	1278 4272954039.0 (1, 4)
	1280 ldc2_w (1, 4)
	1281 7539864640.0 (1, 4)
	1283 invokespecial (1, 4)
	1284 org/apache/commons/math3/ode/nonstiff/DormandPrince853FieldStepInterpolator.fraction:(Lorg/apache/commons/math3/Field;DD)Lorg/apache/commons/math3/RealFieldElement; (1, 4)
	1286 aastore (1, 4)
	1287 aload_0 (1, 4)
	1288 getfield (1, 4)
	1289 org/apache/commons/math3/ode/nonstiff/DormandPrince853FieldStepInterpolator.d:[[Lorg/apache/commons/math3/RealFieldElement; (1, 4)
	1291 iconst_3 (1, 4)
	1292 aaload (1, 4)
	1293 bipush (1, 4)
	1294 6 (1, 4)
	1295 aload_0 (1, 4)
	1296 aload_1 (1, 4)
	1297 ldc2_w (1, 4)
	1298 -118476319744.0 (1, 4)
	1300 ldc2_w (1, 4)
	1301 38604839385.0 (1, 4)
	1303 invokespecial (1, 4)
	1304 org/apache/commons/math3/ode/nonstiff/DormandPrince853FieldStepInterpolator.fraction:(Lorg/apache/commons/math3/Field;DD)Lorg/apache/commons/math3/RealFieldElement; (1, 4)
	1306 aastore (1, 4)
	1307 aload_0 (1, 4)
	1308 getfield (1, 4)
	1309 org/apache/commons/math3/ode/nonstiff/DormandPrince853FieldStepInterpolator.d:[[Lorg/apache/commons/math3/RealFieldElement; (1, 4)
	1311 iconst_3 (1, 4)
	1312 aaload (1, 4)
	1313 bipush (1, 4)
	1314 7 (1, 4)
	1315 aload_0 (1, 4)
	1316 aload_1 (1, 4)
	1317 ldc2_w (1, 4)
	1318 755123450731.0 (1, 4)
	1320 ldc2_w (1, 4)
	1321 316657731600.0 (1, 4)
	1323 invokespecial (1, 4)
	1324 org/apache/commons/math3/ode/nonstiff/DormandPrince853FieldStepInterpolator.fraction:(Lorg/apache/commons/math3/Field;DD)Lorg/apache/commons/math3/RealFieldElement; (1, 4)
	1326 aastore (1, 4)
	1327 aload_0 (1, 4)
	1328 getfield (1, 4)
	1329 org/apache/commons/math3/ode/nonstiff/DormandPrince853FieldStepInterpolator.d:[[Lorg/apache/commons/math3/RealFieldElement; (1, 4)
	1331 iconst_3 (1, 4)
	1332 aaload (1, 4)
	1333 bipush (1, 4)
	1334 8 (1, 4)
	1335 aload_0 (1, 4)
	1336 aload_1 (1, 4)
	1337 ldc2_w (1, 4)
	1338 3.6923844612348283e+18 (1, 4)
	1340 ldc2_w (1, 4)
	1341 1.7441304416342505e+18 (1, 4)
	1343 invokespecial (1, 4)
	1344 org/apache/commons/math3/ode/nonstiff/DormandPrince853FieldStepInterpolator.fraction:(Lorg/apache/commons/math3/Field;DD)Lorg/apache/commons/math3/RealFieldElement; (1, 4)
	1346 aastore (1, 4)
	1347 aload_0 (1, 4)
	1348 getfield (1, 4)
	1349 org/apache/commons/math3/ode/nonstiff/DormandPrince853FieldStepInterpolator.d:[[Lorg/apache/commons/math3/RealFieldElement; (1, 4)
	1351 iconst_3 (1, 4)
	1352 aaload (1, 4)
	1353 bipush (1, 4)
	1354 9 (1, 4)
	1355 aload_0 (1, 4)
	1356 aload_1 (1, 4)
	1357 ldc2_w (1, 4)
	1358 -4612609375.0 (1, 4)
	1360 ldc2_w (1, 4)
	1361 5293382976.0 (1, 4)
	1363 invokespecial (1, 4)
	1364 org/apache/commons/math3/ode/nonstiff/DormandPrince853FieldStepInterpolator.fraction:(Lorg/apache/commons/math3/Field;DD)Lorg/apache/commons/math3/RealFieldElement; (1, 4)
	1366 aastore (1, 4)
	1367 aload_0 (1, 4)
	1368 getfield (1, 4)
	1369 org/apache/commons/math3/ode/nonstiff/DormandPrince853FieldStepInterpolator.d:[[Lorg/apache/commons/math3/RealFieldElement; (1, 4)
	1371 iconst_3 (1, 4)
	1372 aaload (1, 4)
	1373 bipush (1, 4)
	1374 10 (1, 4)
	1375 aload_0 (1, 4)
	1376 aload_1 (1, 4)
	1377 ldc2_w (1, 4)
	1378 2091772278379.0 (1, 4)
	1380 ldc2_w (1, 4)
	1381 933644586600.0 (1, 4)
	1383 invokespecial (1, 4)
	1384 org/apache/commons/math3/ode/nonstiff/DormandPrince853FieldStepInterpolator.fraction:(Lorg/apache/commons/math3/Field;DD)Lorg/apache/commons/math3/RealFieldElement; (1, 4)
	1386 aastore (1, 4)
	1387 aload_0 (1, 4)
	1388 getfield (1, 4)
	1389 org/apache/commons/math3/ode/nonstiff/DormandPrince853FieldStepInterpolator.d:[[Lorg/apache/commons/math3/RealFieldElement; (1, 4)
	1391 iconst_3 (1, 4)
	1392 aaload (1, 4)
	1393 bipush (1, 4)
	1394 11 (1, 4)
	1395 aload_0 (1, 4)
	1396 aload_1 (1, 4)
	1397 ldc2_w (1, 4)
	1398 2136624137.0 (1, 4)
	1400 ldc2_w (1, 4)
	1401 3382989120.0 (1, 4)
	1403 invokespecial (1, 4)
	1404 org/apache/commons/math3/ode/nonstiff/DormandPrince853FieldStepInterpolator.fraction:(Lorg/apache/commons/math3/Field;DD)Lorg/apache/commons/math3/RealFieldElement; (1, 4)
	1406 aastore (1, 4)
	1407 aload_0 (1, 4)
	1408 getfield (1, 4)
	1409 org/apache/commons/math3/ode/nonstiff/DormandPrince853FieldStepInterpolator.d:[[Lorg/apache/commons/math3/RealFieldElement; (1, 4)
	1411 iconst_3 (1, 4)
	1412 aaload (1, 4)
	1413 bipush (1, 4)
	1414 12 (1, 4)
	1415 aload_0 (1, 4)
	1416 aload_1 (1, 4)
	1417 ldc2_w (1, 4)
	1418 -126493.0 (1, 4)
	1420 ldc2_w (1, 4)
	1421 1421424.0 (1, 4)
	1423 invokespecial (1, 4)
	1424 org/apache/commons/math3/ode/nonstiff/DormandPrince853FieldStepInterpolator.fraction:(Lorg/apache/commons/math3/Field;DD)Lorg/apache/commons/math3/RealFieldElement; (1, 4)
	1426 aastore (1, 4)
	1427 aload_0 (1, 4)
	1428 getfield (1, 4)
	1429 org/apache/commons/math3/ode/nonstiff/DormandPrince853FieldStepInterpolator.d:[[Lorg/apache/commons/math3/RealFieldElement; (1, 4)
	1431 iconst_3 (1, 4)
	1432 aaload (1, 4)
	1433 bipush (1, 4)
	1434 13 (1, 4)
	1435 aload_0 (1, 4)
	1436 aload_1 (1, 4)
	1437 ldc2_w (1, 4)
	1438 98350000.0 (1, 4)
	1440 ldc2_w (1, 4)
	1441 5419179.0 (1, 4)
	1443 invokespecial (1, 4)
	1444 org/apache/commons/math3/ode/nonstiff/DormandPrince853FieldStepInterpolator.fraction:(Lorg/apache/commons/math3/Field;DD)Lorg/apache/commons/math3/RealFieldElement; (1, 4)
	1446 aastore (1, 4)
	1447 aload_0 (1, 4)
	1448 getfield (1, 4)
	1449 org/apache/commons/math3/ode/nonstiff/DormandPrince853FieldStepInterpolator.d:[[Lorg/apache/commons/math3/RealFieldElement; (1, 4)
	1451 iconst_3 (1, 4)
	1452 aaload (1, 4)
	1453 bipush (1, 4)
	1454 14 (1, 4)
	1455 aload_0 (1, 4)
	1456 aload_1 (1, 4)
	1457 ldc2_w (1, 4)
	1458 -18878125.0 (1, 4)
	1460 ldc2_w (1, 4)
	1461 2053168.0 (1, 4)
	1463 invokespecial (1, 4)
	1464 org/apache/commons/math3/ode/nonstiff/DormandPrince853FieldStepInterpolator.fraction:(Lorg/apache/commons/math3/Field;DD)Lorg/apache/commons/math3/RealFieldElement; (1, 4)
	1466 aastore (1, 4)
	1467 aload_0 (1, 4)
	1468 getfield (1, 4)
	1469 org/apache/commons/math3/ode/nonstiff/DormandPrince853FieldStepInterpolator.d:[[Lorg/apache/commons/math3/RealFieldElement; (1, 4)
	1471 iconst_3 (1, 4)
	1472 aaload (1, 4)
	1473 bipush (1, 4)
	1474 15 (1, 4)
	1475 aload_0 (1, 4)
	1476 aload_1 (1, 4)
	1477 ldc2_w (1, 4)
	1478 -1944542619.0 (1, 4)
	1480 ldc2_w (1, 4)
	1481 438351368.0 (1, 4)
	1483 invokespecial (1, 4)
	1484 org/apache/commons/math3/ode/nonstiff/DormandPrince853FieldStepInterpolator.fraction:(Lorg/apache/commons/math3/Field;DD)Lorg/apache/commons/math3/RealFieldElement; (1, 4)
	1486 aastore (1, 4)
	1487 aload_0 (1, 4)
	1488 getfield (1, 4)
	1489 org/apache/commons/math3/ode/nonstiff/DormandPrince853FieldStepInterpolator.d:[[Lorg/apache/commons/math3/RealFieldElement; (1, 4)
	1491 iconst_4 (1, 4)
	1492 aaload (1, 4)
	1493 iconst_0 (1, 4)
	1494 aload_0 (1, 4)
	1495 aload_1 (1, 4)
	1496 ldc2_w (1, 4)
	1497 32941697297.0 (1, 4)
	1499 ldc2_w (1, 4)
	1500 3159114840.0 (1, 4)
	1502 invokespecial (1, 4)
	1503 org/apache/commons/math3/ode/nonstiff/DormandPrince853FieldStepInterpolator.fraction:(Lorg/apache/commons/math3/Field;DD)Lorg/apache/commons/math3/RealFieldElement; (1, 4)
	1505 aastore (1, 4)
	1506 aload_0 (1, 4)
	1507 getfield (1, 4)
	1508 org/apache/commons/math3/ode/nonstiff/DormandPrince853FieldStepInterpolator.d:[[Lorg/apache/commons/math3/RealFieldElement; (1, 4)
	1510 iconst_4 (1, 4)
	1511 aaload (1, 4)
	1512 iconst_1 (1, 4)
	1513 aload_1 (1, 4)
	1514 invokeinterface (1, 4)
	1515 org/apache/commons/math3/Field.org/apache/commons/math3/RealFieldElement (1, 4)
	1517 0 (1, 4)
	1519 checkcast (1, 4)
	1520 org/apache/commons/math3/RealFieldElement (1, 4)
	1522 aastore (1, 4)
	1523 aload_0 (1, 4)
	1524 getfield (1, 4)
	1525 org/apache/commons/math3/ode/nonstiff/DormandPrince853FieldStepInterpolator.d:[[Lorg/apache/commons/math3/RealFieldElement; (1, 4)
	1527 iconst_4 (1, 4)
	1528 aaload (1, 4)
	1529 iconst_2 (1, 4)
	1530 aload_1 (1, 4)
	1531 invokeinterface (1, 4)
	1532 org/apache/commons/math3/Field.org/apache/commons/math3/RealFieldElement (1, 4)
	1534 0 (1, 4)
	1536 checkcast (1, 4)
	1537 org/apache/commons/math3/RealFieldElement (1, 4)
	1539 aastore (1, 4)
	1540 aload_0 (1, 4)
	1541 getfield (1, 4)
	1542 org/apache/commons/math3/ode/nonstiff/DormandPrince853FieldStepInterpolator.d:[[Lorg/apache/commons/math3/RealFieldElement; (1, 4)
	1544 iconst_4 (1, 4)
	1545 aaload (1, 4)
	1546 iconst_3 (1, 4)
	1547 aload_1 (1, 4)
	1548 invokeinterface (1, 4)
	1549 org/apache/commons/math3/Field.org/apache/commons/math3/RealFieldElement (1, 4)
	1551 0 (1, 4)
	1553 checkcast (1, 4)
	1554 org/apache/commons/math3/RealFieldElement (1, 4)
	1556 aastore (1, 4)
	1557 aload_0 (1, 4)
	1558 getfield (1, 4)
	1559 org/apache/commons/math3/ode/nonstiff/DormandPrince853FieldStepInterpolator.d:[[Lorg/apache/commons/math3/RealFieldElement; (1, 4)
	1561 iconst_4 (1, 4)
	1562 aaload (1, 4)
	1563 iconst_4 (1, 4)
	1564 aload_1 (1, 4)
	1565 invokeinterface (1, 4)
	1566 org/apache/commons/math3/Field.org/apache/commons/math3/RealFieldElement (1, 4)
	1568 0 (1, 4)
	1570 checkcast (1, 4)
	1571 org/apache/commons/math3/RealFieldElement (1, 4)
	1573 aastore (1, 4)
	1574 aload_0 (1, 4)
	1575 getfield (1, 4)
	1576 org/apache/commons/math3/ode/nonstiff/DormandPrince853FieldStepInterpolator.d:[[Lorg/apache/commons/math3/RealFieldElement; (1, 4)
	1578 iconst_4 (1, 4)
	1579 aaload (1, 4)
	1580 iconst_5 (1, 4)
	1581 aload_0 (1, 4)
	1582 aload_1 (1, 4)
	1583 ldc2_w (1, 4)
	1584 456696183123.0 (1, 4)
	1586 ldc2_w (1, 4)
	1587 1884966160.0 (1, 4)
	1589 invokespecial (1, 4)
	1590 org/apache/commons/math3/ode/nonstiff/DormandPrince853FieldStepInterpolator.fraction:(Lorg/apache/commons/math3/Field;DD)Lorg/apache/commons/math3/RealFieldElement; (1, 4)
	1592 aastore (1, 4)
	1593 aload_0 (1, 4)
	1594 getfield (1, 4)
	1595 org/apache/commons/math3/ode/nonstiff/DormandPrince853FieldStepInterpolator.d:[[Lorg/apache/commons/math3/RealFieldElement; (1, 4)
	1597 iconst_4 (1, 4)
	1598 aaload (1, 4)
	1599 bipush (1, 4)
	1600 6 (1, 4)
	1601 aload_0 (1, 4)
	1602 aload_1 (1, 4)
	1603 ldc2_w (1, 4)
	1604 19132610714624.0 (1, 4)
	1606 ldc2_w (1, 4)
	1607 115814518155.0 (1, 4)
	1609 invokespecial (1, 4)
	1610 org/apache/commons/math3/ode/nonstiff/DormandPrince853FieldStepInterpolator.fraction:(Lorg/apache/commons/math3/Field;DD)Lorg/apache/commons/math3/RealFieldElement; (1, 4)
	1612 aastore (1, 4)
	1613 aload_0 (1, 4)
	1614 getfield (1, 4)
	1615 org/apache/commons/math3/ode/nonstiff/DormandPrince853FieldStepInterpolator.d:[[Lorg/apache/commons/math3/RealFieldElement; (1, 4)
	1617 iconst_4 (1, 4)
	1618 aaload (1, 4)
	1619 bipush (1, 4)
	1620 7 (1, 4)
	1621 aload_0 (1, 4)
	1622 aload_1 (1, 4)
	1623 ldc2_w (1, 4)
	1624 -177904688592943.0 (1, 4)
	1626 ldc2_w (1, 4)
	1627 474986597400.0 (1, 4)
	1629 invokespecial (1, 4)
	1630 org/apache/commons/math3/ode/nonstiff/DormandPrince853FieldStepInterpolator.fraction:(Lorg/apache/commons/math3/Field;DD)Lorg/apache/commons/math3/RealFieldElement; (1, 4)
	1632 aastore (1, 4)
	1633 aload_0 (1, 4)
	1634 getfield (1, 4)
	1635 org/apache/commons/math3/ode/nonstiff/DormandPrince853FieldStepInterpolator.d:[[Lorg/apache/commons/math3/RealFieldElement; (1, 4)
	1637 iconst_4 (1, 4)
	1638 aaload (1, 4)
	1639 bipush (1, 4)
	1640 8 (1, 4)
	1641 aload_0 (1, 4)
	1642 aload_1 (1, 4)
	1643 ldc2_w (1, 4)
	1644 -4.821139941836765e+18 (1, 4)
	1646 ldc2_w (1, 4)
	1647 2.180163052042813e+17 (1, 4)
	1649 invokespecial (1, 4)
	1650 org/apache/commons/math3/ode/nonstiff/DormandPrince853FieldStepInterpolator.fraction:(Lorg/apache/commons/math3/Field;DD)Lorg/apache/commons/math3/RealFieldElement; (1, 4)
	1652 aastore (1, 4)
	1653 aload_0 (1, 4)
	1654 getfield (1, 4)
	1655 org/apache/commons/math3/ode/nonstiff/DormandPrince853FieldStepInterpolator.d:[[Lorg/apache/commons/math3/RealFieldElement; (1, 4)
	1657 iconst_4 (1, 4)
	1658 aaload (1, 4)
	1659 bipush (1, 4)
	1660 9 (1, 4)
	1661 aload_0 (1, 4)
	1662 aload_1 (1, 4)
	1663 ldc2_w (1, 4)
	1664 30702015625.0 (1, 4)
	1666 ldc2_w (1, 4)
	1667 3970037232.0 (1, 4)
	1669 invokespecial (1, 4)
	1670 org/apache/commons/math3/ode/nonstiff/DormandPrince853FieldStepInterpolator.fraction:(Lorg/apache/commons/math3/Field;DD)Lorg/apache/commons/math3/RealFieldElement; (1, 4)
	1672 aastore (1, 4)
	1673 aload_0 (1, 4)
	1674 getfield (1, 4)
	1675 org/apache/commons/math3/ode/nonstiff/DormandPrince853FieldStepInterpolator.d:[[Lorg/apache/commons/math3/RealFieldElement; (1, 4)
	1677 iconst_4 (1, 4)
	1678 aaload (1, 4)
	1679 bipush (1, 4)
	1680 10 (1, 4)
	1681 aload_0 (1, 4)
	1682 aload_1 (1, 4)
	1683 ldc2_w (1, 4)
	1684 -85916079474274.0 (1, 4)
	1686 ldc2_w (1, 4)
	1687 2800933759800.0 (1, 4)
	1689 invokespecial (1, 4)
	1690 org/apache/commons/math3/ode/nonstiff/DormandPrince853FieldStepInterpolator.fraction:(Lorg/apache/commons/math3/Field;DD)Lorg/apache/commons/math3/RealFieldElement; (1, 4)
	1692 aastore (1, 4)
	1693 aload_0 (1, 4)
	1694 getfield (1, 4)
	1695 org/apache/commons/math3/ode/nonstiff/DormandPrince853FieldStepInterpolator.d:[[Lorg/apache/commons/math3/RealFieldElement; (1, 4)
	1697 iconst_4 (1, 4)
	1698 aaload (1, 4)
	1699 bipush (1, 4)
	1700 11 (1, 4)
	1701 aload_0 (1, 4)
	1702 aload_1 (1, 4)
	1703 ldc2_w (1, 4)
	1704 -5919468007.0 (1, 4)
	1706 ldc2_w (1, 4)
	1707 634310460.0 (1, 4)
	1709 invokespecial (1, 4)
	1710 org/apache/commons/math3/ode/nonstiff/DormandPrince853FieldStepInterpolator.fraction:(Lorg/apache/commons/math3/Field;DD)Lorg/apache/commons/math3/RealFieldElement; (1, 4)
	1712 aastore (1, 4)
	1713 aload_0 (1, 4)
	1714 getfield (1, 4)
	1715 org/apache/commons/math3/ode/nonstiff/DormandPrince853FieldStepInterpolator.d:[[Lorg/apache/commons/math3/RealFieldElement; (1, 4)
	1717 iconst_4 (1, 4)
	1718 aaload (1, 4)
	1719 bipush (1, 4)
	1720 12 (1, 4)
	1721 aload_0 (1, 4)
	1722 aload_1 (1, 4)
	1723 ldc2_w (1, 4)
	1724 2479159.0 (1, 4)
	1726 ldc2_w (1, 4)
	1727 157936.0 (1, 4)
	1729 invokespecial (1, 4)
	1730 org/apache/commons/math3/ode/nonstiff/DormandPrince853FieldStepInterpolator.fraction:(Lorg/apache/commons/math3/Field;DD)Lorg/apache/commons/math3/RealFieldElement; (1, 4)
	1732 aastore (1, 4)
	1733 aload_0 (1, 4)
	1734 getfield (1, 4)
	1735 org/apache/commons/math3/ode/nonstiff/DormandPrince853FieldStepInterpolator.d:[[Lorg/apache/commons/math3/RealFieldElement; (1, 4)
	1737 iconst_4 (1, 4)
	1738 aaload (1, 4)
	1739 bipush (1, 4)
	1740 13 (1, 4)
	1741 aload_0 (1, 4)
	1742 aload_1 (1, 4)
	1743 ldc2_w (1, 4)
	1744 -18750000.0 (1, 4)
	1746 ldc2_w (1, 4)
	1747 602131.0 (1, 4)
	1749 invokespecial (1, 4)
	1750 org/apache/commons/math3/ode/nonstiff/DormandPrince853FieldStepInterpolator.fraction:(Lorg/apache/commons/math3/Field;DD)Lorg/apache/commons/math3/RealFieldElement; (1, 4)
	1752 aastore (1, 4)
	1753 aload_0 (1, 4)
	1754 getfield (1, 4)
	1755 org/apache/commons/math3/ode/nonstiff/DormandPrince853FieldStepInterpolator.d:[[Lorg/apache/commons/math3/RealFieldElement; (1, 4)
	1757 iconst_4 (1, 4)
	1758 aaload (1, 4)
	1759 bipush (1, 4)
	1760 14 (1, 4)
	1761 aload_0 (1, 4)
	1762 aload_1 (1, 4)
	1763 ldc2_w (1, 4)
	1764 -19203125.0 (1, 4)
	1766 ldc2_w (1, 4)
	1767 2053168.0 (1, 4)
	1769 invokespecial (1, 4)
	1770 org/apache/commons/math3/ode/nonstiff/DormandPrince853FieldStepInterpolator.fraction:(Lorg/apache/commons/math3/Field;DD)Lorg/apache/commons/math3/RealFieldElement; (1, 4)
	1772 aastore (1, 4)
	1773 aload_0 (1, 4)
	1774 getfield (1, 4)
	1775 org/apache/commons/math3/ode/nonstiff/DormandPrince853FieldStepInterpolator.d:[[Lorg/apache/commons/math3/RealFieldElement; (1, 4)
	1777 iconst_4 (1, 4)
	1778 aaload (1, 4)
	1779 bipush (1, 4)
	1780 15 (1, 4)
	1781 aload_0 (1, 4)
	1782 aload_1 (1, 4)
	1783 ldc2_w (1, 4)
	1784 15700361463.0 (1, 4)
	1786 ldc2_w (1, 4)
	1787 438351368.0 (1, 4)
	1789 invokespecial (1, 4)
	1790 org/apache/commons/math3/ode/nonstiff/DormandPrince853FieldStepInterpolator.fraction:(Lorg/apache/commons/math3/Field;DD)Lorg/apache/commons/math3/RealFieldElement; (1, 4)
	1792 aastore (1, 4)
	1793 aload_0 (1, 4)
	1794 getfield (1, 4)
	1795 org/apache/commons/math3/ode/nonstiff/DormandPrince853FieldStepInterpolator.d:[[Lorg/apache/commons/math3/RealFieldElement; (1, 4)
	1797 iconst_5 (1, 4)
	1798 aaload (1, 4)
	1799 iconst_0 (1, 4)
	1800 aload_0 (1, 4)
	1801 aload_1 (1, 4)
	1802 ldc2_w (1, 4)
	1803 12627015655.0 (1, 4)
	1805 ldc2_w (1, 4)
	1806 631822968.0 (1, 4)
	1808 invokespecial (1, 4)
	1809 org/apache/commons/math3/ode/nonstiff/DormandPrince853FieldStepInterpolator.fraction:(Lorg/apache/commons/math3/Field;DD)Lorg/apache/commons/math3/RealFieldElement; (1, 4)
	1811 aastore (1, 4)
	1812 aload_0 (1, 4)
	1813 getfield (1, 4)
	1814 org/apache/commons/math3/ode/nonstiff/DormandPrince853FieldStepInterpolator.d:[[Lorg/apache/commons/math3/RealFieldElement; (1, 4)
	1816 iconst_5 (1, 4)
	1817 aaload (1, 4)
	1818 iconst_1 (1, 4)
	1819 aload_1 (1, 4)
	1820 invokeinterface (1, 4)
	1821 org/apache/commons/math3/Field.org/apache/commons/math3/RealFieldElement (1, 4)
	1823 0 (1, 4)
	1825 checkcast (1, 4)
	1826 org/apache/commons/math3/RealFieldElement (1, 4)
	1828 aastore (1, 4)
	1829 aload_0 (1, 4)
	1830 getfield (1, 4)
	1831 org/apache/commons/math3/ode/nonstiff/DormandPrince853FieldStepInterpolator.d:[[Lorg/apache/commons/math3/RealFieldElement; (1, 4)
	1833 iconst_5 (1, 4)
	1834 aaload (1, 4)
	1835 iconst_2 (1, 4)
	1836 aload_1 (1, 4)
	1837 invokeinterface (1, 4)
	1838 org/apache/commons/math3/Field.org/apache/commons/math3/RealFieldElement (1, 4)
	1840 0 (1, 4)
	1842 checkcast (1, 4)
	1843 org/apache/commons/math3/RealFieldElement (1, 4)
	1845 aastore (1, 4)
	1846 aload_0 (1, 4)
	1847 getfield (1, 4)
	1848 org/apache/commons/math3/ode/nonstiff/DormandPrince853FieldStepInterpolator.d:[[Lorg/apache/commons/math3/RealFieldElement; (1, 4)
	1850 iconst_5 (1, 4)
	1851 aaload (1, 4)
	1852 iconst_3 (1, 4)
	1853 aload_1 (1, 4)
	1854 invokeinterface (1, 4)
	1855 org/apache/commons/math3/Field.org/apache/commons/math3/RealFieldElement (1, 4)
	1857 0 (1, 4)
	1859 checkcast (1, 4)
	1860 org/apache/commons/math3/RealFieldElement (1, 4)
	1862 aastore (1, 4)
	1863 aload_0 (1, 4)
	1864 getfield (1, 4)
	1865 org/apache/commons/math3/ode/nonstiff/DormandPrince853FieldStepInterpolator.d:[[Lorg/apache/commons/math3/RealFieldElement; (1, 4)
	1867 iconst_5 (1, 4)
	1868 aaload (1, 4)
	1869 iconst_4 (1, 4)
	1870 aload_1 (1, 4)
	1871 invokeinterface (1, 4)
	1872 org/apache/commons/math3/Field.org/apache/commons/math3/RealFieldElement (1, 4)
	1874 0 (1, 4)
	1876 checkcast (1, 4)
	1877 org/apache/commons/math3/RealFieldElement (1, 4)
	1879 aastore (1, 4)
	1880 aload_0 (1, 4)
	1881 getfield (1, 4)
	1882 org/apache/commons/math3/ode/nonstiff/DormandPrince853FieldStepInterpolator.d:[[Lorg/apache/commons/math3/RealFieldElement; (1, 4)
	1884 iconst_5 (1, 4)
	1885 aaload (1, 4)
	1886 iconst_5 (1, 4)
	1887 aload_0 (1, 4)
	1888 aload_1 (1, 4)
	1889 ldc2_w (1, 4)
	1890 -72955222965.0 (1, 4)
	1892 ldc2_w (1, 4)
	1893 188496616.0 (1, 4)
	1895 invokespecial (1, 4)
	1896 org/apache/commons/math3/ode/nonstiff/DormandPrince853FieldStepInterpolator.fraction:(Lorg/apache/commons/math3/Field;DD)Lorg/apache/commons/math3/RealFieldElement; (1, 4)
	1898 aastore (1, 4)
	1899 aload_0 (1, 4)
	1900 getfield (1, 4)
	1901 org/apache/commons/math3/ode/nonstiff/DormandPrince853FieldStepInterpolator.d:[[Lorg/apache/commons/math3/RealFieldElement; (1, 4)
	1903 iconst_5 (1, 4)
	1904 aaload (1, 4)
	1905 bipush (1, 4)
	1906 6 (1, 4)
	1907 aload_0 (1, 4)
	1908 aload_1 (1, 4)
	1909 ldc2_w (1, 4)
	1910 -13145744952320.0 (1, 4)
	1912 ldc2_w (1, 4)
	1913 69488710893.0 (1, 4)
	1915 invokespecial (1, 4)
	1916 org/apache/commons/math3/ode/nonstiff/DormandPrince853FieldStepInterpolator.fraction:(Lorg/apache/commons/math3/Field;DD)Lorg/apache/commons/math3/RealFieldElement; (1, 4)
	1918 aastore (1, 4)
	1919 aload_0 (1, 4)
	1920 getfield (1, 4)
	1921 org/apache/commons/math3/ode/nonstiff/DormandPrince853FieldStepInterpolator.d:[[Lorg/apache/commons/math3/RealFieldElement; (1, 4)
	1923 iconst_5 (1, 4)
	1924 aaload (1, 4)
	1925 bipush (1, 4)
	1926 7 (1, 4)
	1927 aload_0 (1, 4)
	1928 aload_1 (1, 4)
	1929 ldc2_w (1, 4)
	1930 30084216194513.0 (1, 4)
	1932 ldc2_w (1, 4)
	1933 56998391688.0 (1, 4)
	1935 invokespecial (1, 4)
	1936 org/apache/commons/math3/ode/nonstiff/DormandPrince853FieldStepInterpolator.fraction:(Lorg/apache/commons/math3/Field;DD)Lorg/apache/commons/math3/RealFieldElement; (1, 4)
	1938 aastore (1, 4)
	1939 aload_0 (1, 4)
	1940 getfield (1, 4)
	1941 org/apache/commons/math3/ode/nonstiff/DormandPrince853FieldStepInterpolator.d:[[Lorg/apache/commons/math3/RealFieldElement; (1, 4)
	1943 iconst_5 (1, 4)
	1944 aaload (1, 4)
	1945 bipush (1, 4)
	1946 8 (1, 4)
	1947 aload_0 (1, 4)
	1948 aload_1 (1, 4)
	1949 ldc2_w (1, 4)
	1950 -2.9685876100664064e+17 (1, 4)
	1952 ldc2_w (1, 4)
	1953 2.5648977082856624e+16 (1, 4)
	1955 invokespecial (1, 4)
	1956 org/apache/commons/math3/ode/nonstiff/DormandPrince853FieldStepInterpolator.fraction:(Lorg/apache/commons/math3/Field;DD)Lorg/apache/commons/math3/RealFieldElement; (1, 4)
	1958 aastore (1, 4)
	1959 aload_0 (1, 4)
	1960 getfield (1, 4)
	1961 org/apache/commons/math3/ode/nonstiff/DormandPrince853FieldStepInterpolator.d:[[Lorg/apache/commons/math3/RealFieldElement; (1, 4)
	1963 iconst_5 (1, 4)
	1964 aaload (1, 4)
	1965 bipush (1, 4)
	1966 9 (1, 4)
	1967 aload_0 (1, 4)
	1968 aload_1 (1, 4)
	1969 ldc2_w (1, 4)
	1970 569140625.0 (1, 4)
	1972 ldc2_w (1, 4)
	1973 82709109.0 (1, 4)
	1975 invokespecial (1, 4)
	1976 org/apache/commons/math3/ode/nonstiff/DormandPrince853FieldStepInterpolator.fraction:(Lorg/apache/commons/math3/Field;DD)Lorg/apache/commons/math3/RealFieldElement; (1, 4)
	1978 aastore (1, 4)
	1979 aload_0 (1, 4)
	1980 getfield (1, 4)
	1981 org/apache/commons/math3/ode/nonstiff/DormandPrince853FieldStepInterpolator.d:[[Lorg/apache/commons/math3/RealFieldElement; (1, 4)
	1983 iconst_5 (1, 4)
	1984 aaload (1, 4)
	1985 bipush (1, 4)
	1986 10 (1, 4)
	1987 aload_0 (1, 4)
	1988 aload_1 (1, 4)
	1989 ldc2_w (1, 4)
	1990 -18684190637.0 (1, 4)
	1992 ldc2_w (1, 4)
	1993 18672891732.0 (1, 4)
	1995 invokespecial (1, 4)
	1996 org/apache/commons/math3/ode/nonstiff/DormandPrince853FieldStepInterpolator.fraction:(Lorg/apache/commons/math3/Field;DD)Lorg/apache/commons/math3/RealFieldElement; (1, 4)
	1998 aastore (1, 4)
	1999 aload_0 (1, 4)
	2000 getfield (1, 4)
	2001 org/apache/commons/math3/ode/nonstiff/DormandPrince853FieldStepInterpolator.d:[[Lorg/apache/commons/math3/RealFieldElement; (1, 4)
	2003 iconst_5 (1, 4)
	2004 aaload (1, 4)
	2005 bipush (1, 4)
	2006 11 (1, 4)
	2007 aload_0 (1, 4)
	2008 aload_1 (1, 4)
	2009 ldc2_w (1, 4)
	2010 69644045.0 (1, 4)
	2012 ldc2_w (1, 4)
	2013 89549712.0 (1, 4)
	2015 invokespecial (1, 4)
	2016 org/apache/commons/math3/ode/nonstiff/DormandPrince853FieldStepInterpolator.fraction:(Lorg/apache/commons/math3/Field;DD)Lorg/apache/commons/math3/RealFieldElement; (1, 4)
	2018 aastore (1, 4)
	2019 aload_0 (1, 4)
	2020 getfield (1, 4)
	2021 org/apache/commons/math3/ode/nonstiff/DormandPrince853FieldStepInterpolator.d:[[Lorg/apache/commons/math3/RealFieldElement; (1, 4)
	2023 iconst_5 (1, 4)
	2024 aaload (1, 4)
	2025 bipush (1, 4)
	2026 12 (1, 4)
	2027 aload_0 (1, 4)
	2028 aload_1 (1, 4)
	2029 ldc2_w (1, 4)
	2030 -11847025.0 (1, 4)
	2032 ldc2_w (1, 4)
	2033 4264272.0 (1, 4)
	2035 invokespecial (1, 4)
	2036 org/apache/commons/math3/ode/nonstiff/DormandPrince853FieldStepInterpolator.fraction:(Lorg/apache/commons/math3/Field;DD)Lorg/apache/commons/math3/RealFieldElement; (1, 4)
	2038 aastore (1, 4)
	2039 aload_0 (1, 4)
	2040 getfield (1, 4)
	2041 org/apache/commons/math3/ode/nonstiff/DormandPrince853FieldStepInterpolator.d:[[Lorg/apache/commons/math3/RealFieldElement; (1, 4)
	2043 iconst_5 (1, 4)
	2044 aaload (1, 4)
	2045 bipush (1, 4)
	2046 13 (1, 4)
	2047 aload_0 (1, 4)
	2048 aload_1 (1, 4)
	2049 ldc2_w (1, 4)
	2050 -978650000.0 (1, 4)
	2052 ldc2_w (1, 4)
	2053 16257537.0 (1, 4)
	2055 invokespecial (1, 4)
	2056 org/apache/commons/math3/ode/nonstiff/DormandPrince853FieldStepInterpolator.fraction:(Lorg/apache/commons/math3/Field;DD)Lorg/apache/commons/math3/RealFieldElement; (1, 4)
	2058 aastore (1, 4)
	2059 aload_0 (1, 4)
	2060 getfield (1, 4)
	2061 org/apache/commons/math3/ode/nonstiff/DormandPrince853FieldStepInterpolator.d:[[Lorg/apache/commons/math3/RealFieldElement; (1, 4)
	2063 iconst_5 (1, 4)
	2064 aaload (1, 4)
	2065 bipush (1, 4)
	2066 14 (1, 4)
	2067 aload_0 (1, 4)
	2068 aload_1 (1, 4)
	2069 ldc2_w (1, 4)
	2070 519371875.0 (1, 4)
	2072 ldc2_w (1, 4)
	2073 6159504.0 (1, 4)
	2075 invokespecial (1, 4)
	2076 org/apache/commons/math3/ode/nonstiff/DormandPrince853FieldStepInterpolator.fraction:(Lorg/apache/commons/math3/Field;DD)Lorg/apache/commons/math3/RealFieldElement; (1, 4)
	2078 aastore (1, 4)
	2079 aload_0 (1, 4)
	2080 getfield (1, 4)
	2081 org/apache/commons/math3/ode/nonstiff/DormandPrince853FieldStepInterpolator.d:[[Lorg/apache/commons/math3/RealFieldElement; (1, 4)
	2083 iconst_5 (1, 4)
	2084 aaload (1, 4)
	2085 bipush (1, 4)
	2086 15 (1, 4)
	2087 aload_0 (1, 4)
	2088 aload_1 (1, 4)
	2089 ldc2_w (1, 4)
	2090 5256837225.0 (1, 4)
	2092 ldc2_w (1, 4)
	2093 438351368.0 (1, 4)
	2095 invokespecial (1, 4)
	2096 org/apache/commons/math3/ode/nonstiff/DormandPrince853FieldStepInterpolator.fraction:(Lorg/apache/commons/math3/Field;DD)Lorg/apache/commons/math3/RealFieldElement; (1, 4)
	2098 aastore (1, 4)
	2099 aload_0 (1, 4)
	2100 getfield (1, 4)
	2101 org/apache/commons/math3/ode/nonstiff/DormandPrince853FieldStepInterpolator.d:[[Lorg/apache/commons/math3/RealFieldElement; (1, 4)
	2103 bipush (1, 4)
	2104 6 (1, 4)
	2105 aaload (1, 4)
	2106 iconst_0 (1, 4)
	2107 aload_0 (1, 4)
	2108 aload_1 (1, 4)
	2109 ldc2_w (1, 4)
	2110 -450944925.0 (1, 4)
	2112 ldc2_w (1, 4)
	2113 17550638.0 (1, 4)
	2115 invokespecial (1, 4)
	2116 org/apache/commons/math3/ode/nonstiff/DormandPrince853FieldStepInterpolator.fraction:(Lorg/apache/commons/math3/Field;DD)Lorg/apache/commons/math3/RealFieldElement; (1, 4)
	2118 aastore (1, 4)
	2119 aload_0 (1, 4)
	2120 getfield (1, 4)
	2121 org/apache/commons/math3/ode/nonstiff/DormandPrince853FieldStepInterpolator.d:[[Lorg/apache/commons/math3/RealFieldElement; (1, 4)
	2123 bipush (1, 4)
	2124 6 (1, 4)
	2125 aaload (1, 4)
	2126 iconst_1 (1, 4)
	2127 aload_1 (1, 4)
	2128 invokeinterface (1, 4)
	2129 org/apache/commons/math3/Field.org/apache/commons/math3/RealFieldElement (1, 4)
	2131 0 (1, 4)
	2133 checkcast (1, 4)
	2134 org/apache/commons/math3/RealFieldElement (1, 4)
	2136 aastore (1, 4)
	2137 aload_0 (1, 4)
	2138 getfield (1, 4)
	2139 org/apache/commons/math3/ode/nonstiff/DormandPrince853FieldStepInterpolator.d:[[Lorg/apache/commons/math3/RealFieldElement; (1, 4)
	2141 bipush (1, 4)
	2142 6 (1, 4)
	2143 aaload (1, 4)
	2144 iconst_2 (1, 4)
	2145 aload_1 (1, 4)
	2146 invokeinterface (1, 4)
	2147 org/apache/commons/math3/Field.org/apache/commons/math3/RealFieldElement (1, 4)
	2149 0 (1, 4)
	2151 checkcast (1, 4)
	2152 org/apache/commons/math3/RealFieldElement (1, 4)
	2154 aastore (1, 4)
	2155 aload_0 (1, 4)
	2156 getfield (1, 4)
	2157 org/apache/commons/math3/ode/nonstiff/DormandPrince853FieldStepInterpolator.d:[[Lorg/apache/commons/math3/RealFieldElement; (1, 4)
	2159 bipush (1, 4)
	2160 6 (1, 4)
	2161 aaload (1, 4)
	2162 iconst_3 (1, 4)
	2163 aload_1 (1, 4)
	2164 invokeinterface (1, 4)
	2165 org/apache/commons/math3/Field.org/apache/commons/math3/RealFieldElement (1, 4)
	2167 0 (1, 4)
	2169 checkcast (1, 4)
	2170 org/apache/commons/math3/RealFieldElement (1, 4)
	2172 aastore (1, 4)
	2173 aload_0 (1, 4)
	2174 getfield (1, 4)
	2175 org/apache/commons/math3/ode/nonstiff/DormandPrince853FieldStepInterpolator.d:[[Lorg/apache/commons/math3/RealFieldElement; (1, 4)
	2177 bipush (1, 4)
	2178 6 (1, 4)
	2179 aaload (1, 4)
	2180 iconst_4 (1, 4)
	2181 aload_1 (1, 4)
	2182 invokeinterface (1, 4)
	2183 org/apache/commons/math3/Field.org/apache/commons/math3/RealFieldElement (1, 4)
	2185 0 (1, 4)
	2187 checkcast (1, 4)
	2188 org/apache/commons/math3/RealFieldElement (1, 4)
	2190 aastore (1, 4)
	2191 aload_0 (1, 4)
	2192 getfield (1, 4)
	2193 org/apache/commons/math3/ode/nonstiff/DormandPrince853FieldStepInterpolator.d:[[Lorg/apache/commons/math3/RealFieldElement; (1, 4)
	2195 bipush (1, 4)
	2196 6 (1, 4)
	2197 aaload (1, 4)
	2198 iconst_5 (1, 4)
	2199 aload_0 (1, 4)
	2200 aload_1 (1, 4)
	2201 ldc2_w (1, 4)
	2202 -14532122925.0 (1, 4)
	2204 ldc2_w (1, 4)
	2205 94248308.0 (1, 4)
	2207 invokespecial (1, 4)
	2208 org/apache/commons/math3/ode/nonstiff/DormandPrince853FieldStepInterpolator.fraction:(Lorg/apache/commons/math3/Field;DD)Lorg/apache/commons/math3/RealFieldElement; (1, 4)
	2210 aastore (1, 4)
	2211 aload_0 (1, 4)
	2212 getfield (1, 4)
	2213 org/apache/commons/math3/ode/nonstiff/DormandPrince853FieldStepInterpolator.d:[[Lorg/apache/commons/math3/RealFieldElement; (1, 4)
	2215 bipush (1, 4)
	2216 6 (1, 4)
	2217 aaload (1, 4)
	2218 bipush (1, 4)
	2219 6 (1, 4)
	2220 aload_0 (1, 4)
	2221 aload_1 (1, 4)
	2222 ldc2_w (1, 4)
	2223 -595876966400.0 (1, 4)
	2225 ldc2_w (1, 4)
	2226 2573655959.0 (1, 4)
	2228 invokespecial (1, 4)
	2229 org/apache/commons/math3/ode/nonstiff/DormandPrince853FieldStepInterpolator.fraction:(Lorg/apache/commons/math3/Field;DD)Lorg/apache/commons/math3/RealFieldElement; (1, 4)
	2231 aastore (1, 4)
	2232 aload_0 (1, 4)
	2233 getfield (1, 4)
	2234 org/apache/commons/math3/ode/nonstiff/DormandPrince853FieldStepInterpolator.d:[[Lorg/apache/commons/math3/RealFieldElement; (1, 4)
	2236 bipush (1, 4)
	2237 6 (1, 4)
	2238 aaload (1, 4)
	2239 bipush (1, 4)
	2240 7 (1, 4)
	2241 aload_0 (1, 4)
	2242 aload_1 (1, 4)
	2243 ldc2_w (1, 4)
	2244 188748653015.0 (1, 4)
	2246 ldc2_w (1, 4)
	2247 527762886.0 (1, 4)
	2249 invokespecial (1, 4)
	2250 org/apache/commons/math3/ode/nonstiff/DormandPrince853FieldStepInterpolator.fraction:(Lorg/apache/commons/math3/Field;DD)Lorg/apache/commons/math3/RealFieldElement; (1, 4)
	2252 aastore (1, 4)
	2253 aload_0 (1, 4)
	2254 getfield (1, 4)
	2255 org/apache/commons/math3/ode/nonstiff/DormandPrince853FieldStepInterpolator.d:[[Lorg/apache/commons/math3/RealFieldElement; (1, 4)
	2257 bipush (1, 4)
	2258 6 (1, 4)
	2259 aaload (1, 4)
	2260 bipush (1, 4)
	2261 8 (1, 4)
	2262 aload_0 (1, 4)
	2263 aload_1 (1, 4)
	2264 ldc2_w (1, 4)
	2265 2.5454854581152343e+18 (1, 4)
	2267 ldc2_w (1, 4)
	2268 2.7252038150535164e+16 (1, 4)
	2270 invokespecial (1, 4)
	2271 org/apache/commons/math3/ode/nonstiff/DormandPrince853FieldStepInterpolator.fraction:(Lorg/apache/commons/math3/Field;DD)Lorg/apache/commons/math3/RealFieldElement; (1, 4)
	2273 aastore (1, 4)
	2274 aload_0 (1, 4)
	2275 getfield (1, 4)
	2276 org/apache/commons/math3/ode/nonstiff/DormandPrince853FieldStepInterpolator.d:[[Lorg/apache/commons/math3/RealFieldElement; (1, 4)
	2278 bipush (1, 4)
	2279 6 (1, 4)
	2280 aaload (1, 4)
	2281 bipush (1, 4)
	2282 9 (1, 4)
	2283 aload_0 (1, 4)
	2284 aload_1 (1, 4)
	2285 ldc2_w (1, 4)
	2286 -1376953125.0 (1, 4)
	2288 ldc2_w (1, 4)
	2289 36759604.0 (1, 4)
	2291 invokespecial (1, 4)
	2292 org/apache/commons/math3/ode/nonstiff/DormandPrince853FieldStepInterpolator.fraction:(Lorg/apache/commons/math3/Field;DD)Lorg/apache/commons/math3/RealFieldElement; (1, 4)
	2294 aastore (1, 4)
	2295 aload_0 (1, 4)
	2296 getfield (1, 4)
	2297 org/apache/commons/math3/ode/nonstiff/DormandPrince853FieldStepInterpolator.d:[[Lorg/apache/commons/math3/RealFieldElement; (1, 4)
	2299 bipush (1, 4)
	2300 6 (1, 4)
	2301 aaload (1, 4)
	2302 bipush (1, 4)
	2303 10 (1, 4)
	2304 aload_0 (1, 4)
	2305 aload_1 (1, 4)
	2306 ldc2_w (1, 4)
	2307 53995596795.0 (1, 4)
	2309 ldc2_w (1, 4)
	2310 518691437.0 (1, 4)
	2312 invokespecial (1, 4)
	2313 org/apache/commons/math3/ode/nonstiff/DormandPrince853FieldStepInterpolator.fraction:(Lorg/apache/commons/math3/Field;DD)Lorg/apache/commons/math3/RealFieldElement; (1, 4)
	2315 aastore (1, 4)
	2316 aload_0 (1, 4)
	2317 getfield (1, 4)
	2318 org/apache/commons/math3/ode/nonstiff/DormandPrince853FieldStepInterpolator.d:[[Lorg/apache/commons/math3/RealFieldElement; (1, 4)
	2320 bipush (1, 4)
	2321 6 (1, 4)
	2322 aaload (1, 4)
	2323 bipush (1, 4)
	2324 11 (1, 4)
	2325 aload_0 (1, 4)
	2326 aload_1 (1, 4)
	2327 ldc2_w (1, 4)
	2328 210311225.0 (1, 4)
	2330 ldc2_w (1, 4)
	2331 7047894.0 (1, 4)
	2333 invokespecial (1, 4)
	2334 org/apache/commons/math3/ode/nonstiff/DormandPrince853FieldStepInterpolator.fraction:(Lorg/apache/commons/math3/Field;DD)Lorg/apache/commons/math3/RealFieldElement; (1, 4)
	2336 aastore (1, 4)
	2337 aload_0 (1, 4)
	2338 getfield (1, 4)
	2339 org/apache/commons/math3/ode/nonstiff/DormandPrince853FieldStepInterpolator.d:[[Lorg/apache/commons/math3/RealFieldElement; (1, 4)
	2341 bipush (1, 4)
	2342 6 (1, 4)
	2343 aaload (1, 4)
	2344 bipush (1, 4)
	2345 12 (1, 4)
	2346 aload_0 (1, 4)
	2347 aload_1 (1, 4)
	2348 ldc2_w (1, 4)
	2349 -1718875.0 (1, 4)
	2351 ldc2_w (1, 4)
	2352 39484.0 (1, 4)
	2354 invokespecial (1, 4)
	2355 org/apache/commons/math3/ode/nonstiff/DormandPrince853FieldStepInterpolator.fraction:(Lorg/apache/commons/math3/Field;DD)Lorg/apache/commons/math3/RealFieldElement; (1, 4)
	2357 aastore (1, 4)
	2358 aload_0 (1, 4)
	2359 getfield (1, 4)
	2360 org/apache/commons/math3/ode/nonstiff/DormandPrince853FieldStepInterpolator.d:[[Lorg/apache/commons/math3/RealFieldElement; (1, 4)
	2362 bipush (1, 4)
	2363 6 (1, 4)
	2364 aaload (1, 4)
	2365 bipush (1, 4)
	2366 13 (1, 4)
	2367 aload_0 (1, 4)
	2368 aload_1 (1, 4)
	2369 ldc2_w (1, 4)
	2370 58000000.0 (1, 4)
	2372 ldc2_w (1, 4)
	2373 602131.0 (1, 4)
	2375 invokespecial (1, 4)
	2376 org/apache/commons/math3/ode/nonstiff/DormandPrince853FieldStepInterpolator.fraction:(Lorg/apache/commons/math3/Field;DD)Lorg/apache/commons/math3/RealFieldElement; (1, 4)
	2378 aastore (1, 4)
	2379 aload_0 (1, 4)
	2380 getfield (1, 4)
	2381 org/apache/commons/math3/ode/nonstiff/DormandPrince853FieldStepInterpolator.d:[[Lorg/apache/commons/math3/RealFieldElement; (1, 4)
	2383 bipush (1, 4)
	2384 6 (1, 4)
	2385 aaload (1, 4)
	2386 bipush (1, 4)
	2387 14 (1, 4)
	2388 aload_0 (1, 4)
	2389 aload_1 (1, 4)
	2390 ldc2_w (1, 4)
	2391 -1546875.0 (1, 4)
	2393 ldc2_w (1, 4)
	2394 39484.0 (1, 4)
	2396 invokespecial (1, 4)
	2397 org/apache/commons/math3/ode/nonstiff/DormandPrince853FieldStepInterpolator.fraction:(Lorg/apache/commons/math3/Field;DD)Lorg/apache/commons/math3/RealFieldElement; (1, 4)
	2399 aastore (1, 4)
	2400 aload_0 (1, 4)
	2401 getfield (1, 4)
	2402 org/apache/commons/math3/ode/nonstiff/DormandPrince853FieldStepInterpolator.d:[[Lorg/apache/commons/math3/RealFieldElement; (1, 4)
	2404 bipush (1, 4)
	2405 6 (1, 4)
	2406 aaload (1, 4)
	2407 bipush (1, 4)
	2408 15 (1, 4)
	2409 aload_0 (1, 4)
	2410 aload_1 (1, 4)
	2411 ldc2_w (1, 4)
	2412 -1262172375.0 (1, 4)
	2414 ldc2_w (1, 4)
	2415 8429834.0 (1, 4)
	2417 invokespecial (1, 4)
	2418 org/apache/commons/math3/ode/nonstiff/DormandPrince853FieldStepInterpolator.fraction:(Lorg/apache/commons/math3/Field;DD)Lorg/apache/commons/math3/RealFieldElement; (1, 4)
	2420 aastore (1, 4)
	2421 return (0, 4)

Method: create
	0 aload_0 (0, 0)
	1 aload_1 (0, 0)
	2 iload_2 (0, 0)
	3 aload_3 (0, 0)
	4 aload (0, 0)
	5 #4 (0, 0)
	6 aload (0, 0)
	7 #5 (0, 0)
	8 aload (0, 0)
	9 #6 (0, 0)
	10 aload (0, 0)
	11 #7 (0, 0)
	12 aload (0, 0)
	13 #8 (0, 0)
	14 invokevirtual (0, 0)
	15 org/apache/commons/math3/ode/nonstiff/DormandPrince853FieldStepInterpolator.create:(Lorg/apache/commons/math3/Field;Z[[Lorg/apache/commons/math3/RealFieldElement;Lorg/apache/commons/math3/ode/FieldODEStateAndDerivative;Lorg/apache/commons/math3/ode/FieldODEStateAndDerivative;Lorg/apache/commons/math3/ode/FieldODEStateAndDerivative;Lorg/apache/commons/math3/ode/FieldODEStateAndDerivative;Lorg/apache/commons/math3/ode/FieldEquationsMapper;)Lorg/apache/commons/math3/ode/nonstiff/DormandPrince853FieldStepInterpolator; (0, 0)
	17 areturn (0, 0)

Method: fraction
	0 aload_1 (0, 0)
	1 invokeinterface (0, 0)
	2 org/apache/commons/math3/Field.org/apache/commons/math3/RealFieldElement (0, 0)
	4 0 (0, 0)
	6 checkcast (0, 0)
	7 org/apache/commons/math3/RealFieldElement (0, 0)
	9 dload_2 (0, 0)
	10 invokeinterface (0, 0)
	11 org/apache/commons/math3/RealFieldElement.multiply:(I)Ljava/lang/Object; (0, 0)
	13 0 (0, 0)
	15 checkcast (0, 0)
	16 org/apache/commons/math3/RealFieldElement (0, 0)
	18 dload (0, 0)
	19 #4 (0, 0)
	20 invokeinterface (0, 0)
	21 org/apache/commons/math3/RealFieldElement.getField:()Lorg/apache/commons/math3/Field; (0, 0)
	23 0 (0, 0)
	25 checkcast (0, 0)
	26 org/apache/commons/math3/RealFieldElement (0, 0)
	28 areturn (0, 0)

Method: computeInterpolatedStateAndDerivatives
	0 aload_2 (0, 0)
	1 invokeinterface (0, 0)
	2 org/apache/commons/math3/RealFieldElement.getOne:()Ljava/lang/Object; (0, 0)
	4 0 (0, 0)
	6 invokeinterface (0, 0)
	7 org/apache/commons/math3/Field.subtract:(Ljava/lang/Object;)Ljava/lang/Object; (0, 0)
	9 0 (0, 0)
	11 checkcast (0, 0)
	12 org/apache/commons/math3/RealFieldElement (0, 0)
	14 astore (0, 0)
	15 #6 (0, 0)
	16 aload (0, 0)
	17 #6 (0, 0)
	18 aload_3 (0, 0)
	19 invokeinterface (0, 0)
	20 org/apache/commons/math3/RealFieldElement.multiply:(Ljava/lang/Object;)Ljava/lang/Object; (0, 0)
	22 0 (0, 0)
	24 checkcast (0, 0)
	25 org/apache/commons/math3/RealFieldElement (0, 0)
	27 astore (0, 0)
	28 #7 (0, 0)
	29 aload_3 (0, 0)
	30 iconst_2 (0, 0)
	31 invokeinterface (0, 0)
	32 org/apache/commons/math3/RealFieldElement.subtract:(D)Ljava/lang/Object; (0, 0)
	34 0 (0, 0)
	36 checkcast (0, 0)
	37 org/apache/commons/math3/RealFieldElement (0, 0)
	39 astore (0, 0)
	40 #8 (0, 0)
	41 aload_3 (0, 0)
	42 aload_3 (0, 0)
	43 invokeinterface (0, 0)
	44 org/apache/commons/math3/RealFieldElement.getGlobalPreviousState:()Lorg/apache/commons/math3/ode/FieldODEStateAndDerivative; (0, 0)
	46 0 (0, 0)
	48 checkcast (0, 0)
	49 org/apache/commons/math3/RealFieldElement (0, 0)
	51 astore (0, 0)
	52 #9 (0, 0)
	53 aload (0, 0)
	54 #6 (0, 0)
	55 aload (0, 0)
	56 #8 (0, 0)
	57 invokeinterface (0, 0)
	58 org/apache/commons/math3/RealFieldElement.multiply:(Ljava/lang/Object;)Ljava/lang/Object; (0, 0)
	60 0 (0, 0)
	62 checkcast (0, 0)
	63 org/apache/commons/math3/RealFieldElement (0, 0)
	65 astore (0, 0)
	66 #10 (0, 0)
	67 aload_3 (0, 0)
	68 aload_3 (0, 0)
	69 bipush (0, 0)
	70 -3 (0, 0)
	71 invokeinterface (0, 0)
	72 org/apache/commons/math3/RealFieldElement.subtract:(D)Ljava/lang/Object; (0, 0)
	74 0 (0, 0)
	76 checkcast (0, 0)
	77 org/apache/commons/math3/RealFieldElement (0, 0)
	79 ldc2_w (0, 0)
	80 2.0 (0, 0)
	82 invokeinterface (0, 0)
	83 org/apache/commons/math3/RealFieldElement.multiply:(I)Ljava/lang/Object; (0, 0)
	85 0 (0, 0)
	87 invokeinterface (0, 0)
	88 org/apache/commons/math3/RealFieldElement.getGlobalPreviousState:()Lorg/apache/commons/math3/ode/FieldODEStateAndDerivative; (0, 0)
	90 0 (0, 0)
	92 checkcast (0, 0)
	93 org/apache/commons/math3/RealFieldElement (0, 0)
	95 astore (0, 0)
	96 #11 (0, 0)
	97 aload (0, 0)
	98 #8 (0, 0)
	99 aload_3 (0, 0)
	100 aload (0, 0)
	101 #8 (0, 0)
	102 ldc2_w (0, 0)
	103 3.0 (0, 0)
	105 invokeinterface (0, 0)
	106 org/apache/commons/math3/RealFieldElement.org/apache/commons/math3/ode/nonstiff/DormandPrince853FieldStepInterpolator (0, 0)
	108 0 (0, 0)
	110 invokeinterface (0, 0)
	111 org/apache/commons/math3/RealFieldElement.getGlobalPreviousState:()Lorg/apache/commons/math3/ode/FieldODEStateAndDerivative; (0, 0)
	113 0 (0, 0)
	115 checkcast (0, 0)
	116 org/apache/commons/math3/RealFieldElement (0, 0)
	118 dconst_1 (0, 0)
	119 invokeinterface (0, 0)
	120 org/apache/commons/math3/RealFieldElement.multiply:(I)Ljava/lang/Object; (0, 0)
	122 0 (0, 0)
	124 invokeinterface (0, 0)
	125 org/apache/commons/math3/RealFieldElement.getGlobalPreviousState:()Lorg/apache/commons/math3/ode/FieldODEStateAndDerivative; (0, 0)
	127 0 (0, 0)
	129 checkcast (0, 0)
	130 org/apache/commons/math3/RealFieldElement (0, 0)
	132 astore (0, 0)
	133 #12 (0, 0)
	134 aload (0, 0)
	135 #9 (0, 0)
	136 aload_3 (0, 0)
	137 aload_3 (0, 0)
	138 iconst_5 (0, 0)
	139 invokeinterface (0, 0)
	140 org/apache/commons/math3/RealFieldElement.subtract:(D)Ljava/lang/Object; (0, 0)
	142 0 (0, 0)
	144 checkcast (0, 0)
	145 org/apache/commons/math3/RealFieldElement (0, 0)
	147 ldc2_w (0, 0)
	148 8.0 (0, 0)
	150 invokeinterface (0, 0)
	151 org/apache/commons/math3/RealFieldElement.org/apache/commons/math3/ode/nonstiff/DormandPrince853FieldStepInterpolator (0, 0)
	153 0 (0, 0)
	155 invokeinterface (0, 0)
	156 org/apache/commons/math3/RealFieldElement.getGlobalPreviousState:()Lorg/apache/commons/math3/ode/FieldODEStateAndDerivative; (0, 0)
	158 0 (0, 0)
	160 checkcast (0, 0)
	161 org/apache/commons/math3/RealFieldElement (0, 0)
	163 ldc2_w (0, 0)
	164 3.0 (0, 0)
	166 invokeinterface (0, 0)
	167 org/apache/commons/math3/RealFieldElement.multiply:(I)Ljava/lang/Object; (0, 0)
	169 0 (0, 0)
	171 invokeinterface (0, 0)
	172 org/apache/commons/math3/RealFieldElement.getGlobalPreviousState:()Lorg/apache/commons/math3/ode/FieldODEStateAndDerivative; (0, 0)
	174 0 (0, 0)
	176 checkcast (0, 0)
	177 org/apache/commons/math3/RealFieldElement (0, 0)
	179 astore (0, 0)
	180 #13 (0, 0)
	181 aload (0, 0)
	182 #9 (0, 0)
	183 aload_3 (0, 0)
	184 aload_3 (0, 0)
	185 aload_3 (0, 0)
	186 bipush (0, 0)
	187 -6 (0, 0)
	188 invokeinterface (0, 0)
	189 org/apache/commons/math3/RealFieldElement.subtract:(D)Ljava/lang/Object; (0, 0)
	191 0 (0, 0)
	193 checkcast (0, 0)
	194 org/apache/commons/math3/RealFieldElement (0, 0)
	196 ldc2_w (0, 0)
	197 15.0 (0, 0)
	199 invokeinterface (0, 0)
	200 org/apache/commons/math3/RealFieldElement.multiply:(I)Ljava/lang/Object; (0, 0)
	202 0 (0, 0)
	204 invokeinterface (0, 0)
	205 org/apache/commons/math3/RealFieldElement.getGlobalPreviousState:()Lorg/apache/commons/math3/ode/FieldODEStateAndDerivative; (0, 0)
	207 0 (0, 0)
	209 checkcast (0, 0)
	210 org/apache/commons/math3/RealFieldElement (0, 0)
	212 ldc2_w (0, 0)
	213 12.0 (0, 0)
	215 invokeinterface (0, 0)
	216 org/apache/commons/math3/RealFieldElement.org/apache/commons/math3/ode/nonstiff/DormandPrince853FieldStepInterpolator (0, 0)
	218 0 (0, 0)
	220 invokeinterface (0, 0)
	221 org/apache/commons/math3/RealFieldElement.getGlobalPreviousState:()Lorg/apache/commons/math3/ode/FieldODEStateAndDerivative; (0, 0)
	223 0 (0, 0)
	225 checkcast (0, 0)
	226 org/apache/commons/math3/RealFieldElement (0, 0)
	228 ldc2_w (0, 0)
	229 3.0 (0, 0)
	231 invokeinterface (0, 0)
	232 org/apache/commons/math3/RealFieldElement.multiply:(I)Ljava/lang/Object; (0, 0)
	234 0 (0, 0)
	236 invokeinterface (0, 0)
	237 org/apache/commons/math3/RealFieldElement.getGlobalPreviousState:()Lorg/apache/commons/math3/ode/FieldODEStateAndDerivative; (0, 0)
	239 0 (0, 0)
	241 checkcast (0, 0)
	242 org/apache/commons/math3/RealFieldElement (0, 0)
	244 astore (0, 0)
	245 #14 (0, 0)
	246 aload (0, 0)
	247 #9 (0, 0)
	248 aload_3 (0, 0)
	249 aload_3 (0, 0)
	250 aload_3 (0, 0)
	251 aload_3 (0, 0)
	252 bipush (0, 0)
	253 -7 (0, 0)
	254 invokeinterface (0, 0)
	255 org/apache/commons/math3/RealFieldElement.subtract:(D)Ljava/lang/Object; (0, 0)
	257 0 (0, 0)
	259 checkcast (0, 0)
	260 org/apache/commons/math3/RealFieldElement (0, 0)
	262 ldc2_w (0, 0)
	263 18.0 (0, 0)
	265 invokeinterface (0, 0)
	266 org/apache/commons/math3/RealFieldElement.multiply:(I)Ljava/lang/Object; (0, 0)
	268 0 (0, 0)
	270 invokeinterface (0, 0)
	271 org/apache/commons/math3/RealFieldElement.getGlobalPreviousState:()Lorg/apache/commons/math3/ode/FieldODEStateAndDerivative; (0, 0)
	273 0 (0, 0)
	275 checkcast (0, 0)
	276 org/apache/commons/math3/RealFieldElement (0, 0)
	278 ldc2_w (0, 0)
	279 15.0 (0, 0)
	281 invokeinterface (0, 0)
	282 org/apache/commons/math3/RealFieldElement.org/apache/commons/math3/ode/nonstiff/DormandPrince853FieldStepInterpolator (0, 0)
	284 0 (0, 0)
	286 invokeinterface (0, 0)
	287 org/apache/commons/math3/RealFieldElement.getGlobalPreviousState:()Lorg/apache/commons/math3/ode/FieldODEStateAndDerivative; (0, 0)
	289 0 (0, 0)
	291 checkcast (0, 0)
	292 org/apache/commons/math3/RealFieldElement (0, 0)
	294 ldc2_w (0, 0)
	295 4.0 (0, 0)
	297 invokeinterface (0, 0)
	298 org/apache/commons/math3/RealFieldElement.multiply:(I)Ljava/lang/Object; (0, 0)
	300 0 (0, 0)
	302 invokeinterface (0, 0)
	303 org/apache/commons/math3/RealFieldElement.getGlobalPreviousState:()Lorg/apache/commons/math3/ode/FieldODEStateAndDerivative; (0, 0)
	305 0 (0, 0)
	307 invokeinterface (0, 0)
	308 org/apache/commons/math3/RealFieldElement.getGlobalPreviousState:()Lorg/apache/commons/math3/ode/FieldODEStateAndDerivative; (0, 0)
	310 0 (0, 0)
	312 checkcast (0, 0)
	313 org/apache/commons/math3/RealFieldElement (0, 0)
	315 astore (0, 0)
	316 #15 (0, 0)
	317 aload_0 (1, 1)
	318 invokevirtual (1, 1)
	319 org/apache/commons/math3/ode/nonstiff/DormandPrince853FieldStepInterpolator.getGlobalPreviousState:()Lorg/apache/commons/math3/ode/FieldODEStateAndDerivative; (1, 1)
	321 ifnull (1, 1)
	322 767 (1, 1)
	324 aload_3 (1, 1)
	325 invokeinterface (1, 1)
	326 org/apache/commons/math3/RealFieldElement.buildArray:(Lorg/apache/commons/math3/Field;I)[Ljava/lang/Object; (1, 1)
	328 0 (1, 1)
	330 ldc2_w (1, 1)
	331 0.5 (1, 1)
	333 dcmpg (1, 1)
	334 ifgt (1, 1)
	335 754 (1, 1)
	337 aload (1, 1)
	338 #4 (1, 1)
	339 astore (1, 1)
	340 #18 (1, 1)
	341 aload (1, 1)
	342 #18 (1, 1)
	343 aload (1, 1)
	344 #7 (1, 1)
	345 invokeinterface (1, 1)
	346 org/apache/commons/math3/RealFieldElement.getGlobalPreviousState:()Lorg/apache/commons/math3/ode/FieldODEStateAndDerivative; (1, 1)
	348 0 (1, 1)
	350 checkcast (1, 1)
	351 org/apache/commons/math3/RealFieldElement (1, 1)
	353 astore (1, 1)
	354 #19 (1, 1)
	355 aload (1, 1)
	356 #19 (1, 1)
	357 aload_3 (1, 1)
	358 invokeinterface (1, 1)
	359 org/apache/commons/math3/RealFieldElement.getGlobalPreviousState:()Lorg/apache/commons/math3/ode/FieldODEStateAndDerivative; (1, 1)
	361 0 (1, 1)
	363 checkcast (1, 1)
	364 org/apache/commons/math3/RealFieldElement (1, 1)
	366 astore (1, 1)
	367 #20 (1, 1)
	368 aload (1, 1)
	369 #20 (1, 1)
	370 aload (1, 1)
	371 #7 (1, 1)
	372 invokeinterface (1, 1)
	373 org/apache/commons/math3/RealFieldElement.getGlobalPreviousState:()Lorg/apache/commons/math3/ode/FieldODEStateAndDerivative; (1, 1)
	375 0 (1, 1)
	377 checkcast (1, 1)
	378 org/apache/commons/math3/RealFieldElement (1, 1)
	380 astore (1, 1)
	381 #21 (1, 1)
	382 aload (1, 1)
	383 #21 (1, 1)
	384 aload_3 (1, 1)
	385 invokeinterface (1, 1)
	386 org/apache/commons/math3/RealFieldElement.getGlobalPreviousState:()Lorg/apache/commons/math3/ode/FieldODEStateAndDerivative; (1, 1)
	388 0 (1, 1)
	390 checkcast (1, 1)
	391 org/apache/commons/math3/RealFieldElement (1, 1)
	393 astore (1, 1)
	394 #22 (1, 1)
	395 aload (1, 1)
	396 #22 (1, 1)
	397 aload (1, 1)
	398 #7 (1, 1)
	399 invokeinterface (1, 1)
	400 org/apache/commons/math3/RealFieldElement.getGlobalPreviousState:()Lorg/apache/commons/math3/ode/FieldODEStateAndDerivative; (1, 1)
	402 0 (1, 1)
	404 checkcast (1, 1)
	405 org/apache/commons/math3/RealFieldElement (1, 1)
	407 astore (1, 1)
	408 #23 (1, 1)
	409 aload (1, 1)
	410 #23 (1, 1)
	411 aload_3 (1, 1)
	412 invokeinterface (1, 1)
	413 org/apache/commons/math3/RealFieldElement.getGlobalPreviousState:()Lorg/apache/commons/math3/ode/FieldODEStateAndDerivative; (1, 1)
	415 0 (1, 1)
	417 checkcast (1, 1)
	418 org/apache/commons/math3/RealFieldElement (1, 1)
	420 astore (1, 1)
	421 #24 (1, 1)
	422 aload_2 (1, 1)
	423 invokeinterface (1, 1)
	424 org/apache/commons/math3/RealFieldElement.getOne:()Ljava/lang/Object; (1, 1)
	426 0 (1, 1)
	428 bipush (1, 1)
	429 16 (1, 1)
	430 invokestatic (1, 1)
	431 org/apache/commons/math3/util/MathArrays.buildArray:(Lorg/apache/commons/math3/Field;I)[Ljava/lang/Object; (1, 1)
	433 checkcast (1, 1)
	434 [Lorg/apache/commons/math3/RealFieldElement; (1, 1)
	436 astore (1, 1)
	437 #25 (1, 1)
	438 aload_2 (1, 1)
	439 invokeinterface (1, 1)
	440 org/apache/commons/math3/RealFieldElement.getOne:()Ljava/lang/Object; (1, 1)
	442 0 (1, 1)
	444 bipush (1, 1)
	445 16 (1, 1)
	446 invokestatic (1, 1)
	447 org/apache/commons/math3/util/MathArrays.buildArray:(Lorg/apache/commons/math3/Field;I)[Ljava/lang/Object; (1, 1)
	449 checkcast (1, 1)
	450 [Lorg/apache/commons/math3/RealFieldElement; (1, 1)
	452 astore (1, 1)
	453 #26 (1, 1)
	454 iconst_0 (2, 4)
	455 istore (2, 4)
	456 #27 (2, 4)
	457 iload (2, 4)
	458 #27 (2, 4)
	459 aload (2, 4)
	460 #25 (2, 4)
	461 arraylength (2, 4)
	462 if_icmpge (2, 4)
	463 337 (2, 4)
	465 aload (2, 4)
	466 #25 (2, 4)
	467 iload (2, 4)
	468 #27 (2, 4)
	469 aload (2, 4)
	470 #18 (2, 4)
	471 aload_0 (2, 4)
	472 getfield (2, 4)
	473 org/apache/commons/math3/ode/nonstiff/DormandPrince853FieldStepInterpolator.d:[[Lorg/apache/commons/math3/RealFieldElement; (2, 4)
	475 iconst_0 (2, 4)
	476 aaload (2, 4)
	477 iload (2, 4)
	478 #27 (2, 4)
	479 aaload (2, 4)
	480 invokeinterface (2, 4)
	481 org/apache/commons/math3/RealFieldElement.getGlobalPreviousState:()Lorg/apache/commons/math3/ode/FieldODEStateAndDerivative; (2, 4)
	483 0 (2, 4)
	485 checkcast (2, 4)
	486 org/apache/commons/math3/RealFieldElement (2, 4)
	488 aload (2, 4)
	489 #19 (2, 4)
	490 aload_0 (2, 4)
	491 getfield (2, 4)
	492 org/apache/commons/math3/ode/nonstiff/DormandPrince853FieldStepInterpolator.d:[[Lorg/apache/commons/math3/RealFieldElement; (2, 4)
	494 iconst_1 (2, 4)
	495 aaload (2, 4)
	496 iload (2, 4)
	497 #27 (2, 4)
	498 aaload (2, 4)
	499 invokeinterface (2, 4)
	500 org/apache/commons/math3/RealFieldElement.getGlobalPreviousState:()Lorg/apache/commons/math3/ode/FieldODEStateAndDerivative; (2, 4)
	502 0 (2, 4)
	504 invokeinterface (2, 4)
	505 org/apache/commons/math3/RealFieldElement.previousStateLinearCombination:([Lorg/apache/commons/math3/RealFieldElement;)[Lorg/apache/commons/math3/RealFieldElement; (2, 4)
	507 0 (2, 4)
	509 checkcast (2, 4)
	510 org/apache/commons/math3/RealFieldElement (2, 4)
	512 aload (2, 4)
	513 #20 (2, 4)
	514 aload_0 (2, 4)
	515 getfield (2, 4)
	516 org/apache/commons/math3/ode/nonstiff/DormandPrince853FieldStepInterpolator.d:[[Lorg/apache/commons/math3/RealFieldElement; (2, 4)
	518 iconst_2 (2, 4)
	519 aaload (2, 4)
	520 iload (2, 4)
	521 #27 (2, 4)
	522 aaload (2, 4)
	523 invokeinterface (2, 4)
	524 org/apache/commons/math3/RealFieldElement.getGlobalPreviousState:()Lorg/apache/commons/math3/ode/FieldODEStateAndDerivative; (2, 4)
	526 0 (2, 4)
	528 invokeinterface (2, 4)
	529 org/apache/commons/math3/RealFieldElement.previousStateLinearCombination:([Lorg/apache/commons/math3/RealFieldElement;)[Lorg/apache/commons/math3/RealFieldElement; (2, 4)
	531 0 (2, 4)
	533 checkcast (2, 4)
	534 org/apache/commons/math3/RealFieldElement (2, 4)
	536 aload (2, 4)
	537 #21 (2, 4)
	538 aload_0 (2, 4)
	539 getfield (2, 4)
	540 org/apache/commons/math3/ode/nonstiff/DormandPrince853FieldStepInterpolator.d:[[Lorg/apache/commons/math3/RealFieldElement; (2, 4)
	542 iconst_3 (2, 4)
	543 aaload (2, 4)
	544 iload (2, 4)
	545 #27 (2, 4)
	546 aaload (2, 4)
	547 invokeinterface (2, 4)
	548 org/apache/commons/math3/RealFieldElement.getGlobalPreviousState:()Lorg/apache/commons/math3/ode/FieldODEStateAndDerivative; (2, 4)
	550 0 (2, 4)
	552 invokeinterface (2, 4)
	553 org/apache/commons/math3/RealFieldElement.previousStateLinearCombination:([Lorg/apache/commons/math3/RealFieldElement;)[Lorg/apache/commons/math3/RealFieldElement; (2, 4)
	555 0 (2, 4)
	557 checkcast (2, 4)
	558 org/apache/commons/math3/RealFieldElement (2, 4)
	560 aload (2, 4)
	561 #22 (2, 4)
	562 aload_0 (2, 4)
	563 getfield (2, 4)
	564 org/apache/commons/math3/ode/nonstiff/DormandPrince853FieldStepInterpolator.d:[[Lorg/apache/commons/math3/RealFieldElement; (2, 4)
	566 iconst_4 (2, 4)
	567 aaload (2, 4)
	568 iload (2, 4)
	569 #27 (2, 4)
	570 aaload (2, 4)
	571 invokeinterface (2, 4)
	572 org/apache/commons/math3/RealFieldElement.getGlobalPreviousState:()Lorg/apache/commons/math3/ode/FieldODEStateAndDerivative; (2, 4)
	574 0 (2, 4)
	576 invokeinterface (2, 4)
	577 org/apache/commons/math3/RealFieldElement.previousStateLinearCombination:([Lorg/apache/commons/math3/RealFieldElement;)[Lorg/apache/commons/math3/RealFieldElement; (2, 4)
	579 0 (2, 4)
	581 checkcast (2, 4)
	582 org/apache/commons/math3/RealFieldElement (2, 4)
	584 aload (2, 4)
	585 #23 (2, 4)
	586 aload_0 (2, 4)
	587 getfield (2, 4)
	588 org/apache/commons/math3/ode/nonstiff/DormandPrince853FieldStepInterpolator.d:[[Lorg/apache/commons/math3/RealFieldElement; (2, 4)
	590 iconst_5 (2, 4)
	591 aaload (2, 4)
	592 iload (2, 4)
	593 #27 (2, 4)
	594 aaload (2, 4)
	595 invokeinterface (2, 4)
	596 org/apache/commons/math3/RealFieldElement.getGlobalPreviousState:()Lorg/apache/commons/math3/ode/FieldODEStateAndDerivative; (2, 4)
	598 0 (2, 4)
	600 invokeinterface (2, 4)
	601 org/apache/commons/math3/RealFieldElement.previousStateLinearCombination:([Lorg/apache/commons/math3/RealFieldElement;)[Lorg/apache/commons/math3/RealFieldElement; (2, 4)
	603 0 (2, 4)
	605 checkcast (2, 4)
	606 org/apache/commons/math3/RealFieldElement (2, 4)
	608 aload (2, 4)
	609 #24 (2, 4)
	610 aload_0 (2, 4)
	611 getfield (2, 4)
	612 org/apache/commons/math3/ode/nonstiff/DormandPrince853FieldStepInterpolator.d:[[Lorg/apache/commons/math3/RealFieldElement; (2, 4)
	614 bipush (2, 4)
	615 6 (2, 4)
	616 aaload (2, 4)
	617 iload (2, 4)
	618 #27 (2, 4)
	619 aaload (2, 4)
	620 invokeinterface (2, 4)
	621 org/apache/commons/math3/RealFieldElement.getGlobalPreviousState:()Lorg/apache/commons/math3/ode/FieldODEStateAndDerivative; (2, 4)
	623 0 (2, 4)
	625 invokeinterface (2, 4)
	626 org/apache/commons/math3/RealFieldElement.previousStateLinearCombination:([Lorg/apache/commons/math3/RealFieldElement;)[Lorg/apache/commons/math3/RealFieldElement; (2, 4)
	628 0 (2, 4)
	630 checkcast (2, 4)
	631 org/apache/commons/math3/RealFieldElement (2, 4)
	633 aastore (2, 4)
	634 aload (2, 4)
	635 #26 (2, 4)
	636 iload (2, 4)
	637 #27 (2, 4)
	638 aload_0 (2, 4)
	639 getfield (2, 4)
	640 org/apache/commons/math3/ode/nonstiff/DormandPrince853FieldStepInterpolator.d:[[Lorg/apache/commons/math3/RealFieldElement; (2, 4)
	642 iconst_0 (2, 4)
	643 aaload (2, 4)
	644 iload (2, 4)
	645 #27 (2, 4)
	646 aaload (2, 4)
	647 aload (2, 4)
	648 #10 (2, 4)
	649 aload_0 (2, 4)
	650 getfield (2, 4)
	651 org/apache/commons/math3/ode/nonstiff/DormandPrince853FieldStepInterpolator.d:[[Lorg/apache/commons/math3/RealFieldElement; (2, 4)
	653 iconst_1 (2, 4)
	654 aaload (2, 4)
	655 iload (2, 4)
	656 #27 (2, 4)
	657 aaload (2, 4)
	658 invokeinterface (2, 4)
	659 org/apache/commons/math3/RealFieldElement.getGlobalPreviousState:()Lorg/apache/commons/math3/ode/FieldODEStateAndDerivative; (2, 4)
	661 0 (2, 4)
	663 invokeinterface (2, 4)
	664 org/apache/commons/math3/RealFieldElement.previousStateLinearCombination:([Lorg/apache/commons/math3/RealFieldElement;)[Lorg/apache/commons/math3/RealFieldElement; (2, 4)
	666 0 (2, 4)
	668 checkcast (2, 4)
	669 org/apache/commons/math3/RealFieldElement (2, 4)
	671 aload (2, 4)
	672 #11 (2, 4)
	673 aload_0 (2, 4)
	674 getfield (2, 4)
	675 org/apache/commons/math3/ode/nonstiff/DormandPrince853FieldStepInterpolator.d:[[Lorg/apache/commons/math3/RealFieldElement; (2, 4)
	677 iconst_2 (2, 4)
	678 aaload (2, 4)
	679 iload (2, 4)
	680 #27 (2, 4)
	681 aaload (2, 4)
	682 invokeinterface (2, 4)
	683 org/apache/commons/math3/RealFieldElement.getGlobalPreviousState:()Lorg/apache/commons/math3/ode/FieldODEStateAndDerivative; (2, 4)
	685 0 (2, 4)
	687 invokeinterface (2, 4)
	688 org/apache/commons/math3/RealFieldElement.previousStateLinearCombination:([Lorg/apache/commons/math3/RealFieldElement;)[Lorg/apache/commons/math3/RealFieldElement; (2, 4)
	690 0 (2, 4)
	692 checkcast (2, 4)
	693 org/apache/commons/math3/RealFieldElement (2, 4)
	695 aload (2, 4)
	696 #12 (2, 4)
	697 aload_0 (2, 4)
	698 getfield (2, 4)
	699 org/apache/commons/math3/ode/nonstiff/DormandPrince853FieldStepInterpolator.d:[[Lorg/apache/commons/math3/RealFieldElement; (2, 4)
	701 iconst_3 (2, 4)
	702 aaload (2, 4)
	703 iload (2, 4)
	704 #27 (2, 4)
	705 aaload (2, 4)
	706 invokeinterface (2, 4)
	707 org/apache/commons/math3/RealFieldElement.getGlobalPreviousState:()Lorg/apache/commons/math3/ode/FieldODEStateAndDerivative; (2, 4)
	709 0 (2, 4)
	711 invokeinterface (2, 4)
	712 org/apache/commons/math3/RealFieldElement.previousStateLinearCombination:([Lorg/apache/commons/math3/RealFieldElement;)[Lorg/apache/commons/math3/RealFieldElement; (2, 4)
	714 0 (2, 4)
	716 checkcast (2, 4)
	717 org/apache/commons/math3/RealFieldElement (2, 4)
	719 aload (2, 4)
	720 #13 (2, 4)
	721 aload_0 (2, 4)
	722 getfield (2, 4)
	723 org/apache/commons/math3/ode/nonstiff/DormandPrince853FieldStepInterpolator.d:[[Lorg/apache/commons/math3/RealFieldElement; (2, 4)
	725 iconst_4 (2, 4)
	726 aaload (2, 4)
	727 iload (2, 4)
	728 #27 (2, 4)
	729 aaload (2, 4)
	730 invokeinterface (2, 4)
	731 org/apache/commons/math3/RealFieldElement.getGlobalPreviousState:()Lorg/apache/commons/math3/ode/FieldODEStateAndDerivative; (2, 4)
	733 0 (2, 4)
	735 invokeinterface (2, 4)
	736 org/apache/commons/math3/RealFieldElement.previousStateLinearCombination:([Lorg/apache/commons/math3/RealFieldElement;)[Lorg/apache/commons/math3/RealFieldElement; (2, 4)
	738 0 (2, 4)
	740 checkcast (2, 4)
	741 org/apache/commons/math3/RealFieldElement (2, 4)
	743 aload (2, 4)
	744 #14 (2, 4)
	745 aload_0 (2, 4)
	746 getfield (2, 4)
	747 org/apache/commons/math3/ode/nonstiff/DormandPrince853FieldStepInterpolator.d:[[Lorg/apache/commons/math3/RealFieldElement; (2, 4)
	749 iconst_5 (2, 4)
	750 aaload (2, 4)
	751 iload (2, 4)
	752 #27 (2, 4)
	753 aaload (2, 4)
	754 invokeinterface (2, 4)
	755 org/apache/commons/math3/RealFieldElement.getGlobalPreviousState:()Lorg/apache/commons/math3/ode/FieldODEStateAndDerivative; (2, 4)
	757 0 (2, 4)
	759 invokeinterface (2, 4)
	760 org/apache/commons/math3/RealFieldElement.previousStateLinearCombination:([Lorg/apache/commons/math3/RealFieldElement;)[Lorg/apache/commons/math3/RealFieldElement; (2, 4)
	762 0 (2, 4)
	764 checkcast (2, 4)
	765 org/apache/commons/math3/RealFieldElement (2, 4)
	767 aload (2, 4)
	768 #15 (2, 4)
	769 aload_0 (2, 4)
	770 getfield (2, 4)
	771 org/apache/commons/math3/ode/nonstiff/DormandPrince853FieldStepInterpolator.d:[[Lorg/apache/commons/math3/RealFieldElement; (2, 4)
	773 bipush (2, 4)
	774 6 (2, 4)
	775 aaload (2, 4)
	776 iload (2, 4)
	777 #27 (2, 4)
	778 aaload (2, 4)
	779 invokeinterface (2, 4)
	780 org/apache/commons/math3/RealFieldElement.getGlobalPreviousState:()Lorg/apache/commons/math3/ode/FieldODEStateAndDerivative; (2, 4)
	782 0 (2, 4)
	784 invokeinterface (2, 4)
	785 org/apache/commons/math3/RealFieldElement.previousStateLinearCombination:([Lorg/apache/commons/math3/RealFieldElement;)[Lorg/apache/commons/math3/RealFieldElement; (2, 4)
	787 0 (2, 4)
	789 checkcast (2, 4)
	790 org/apache/commons/math3/RealFieldElement (2, 4)
	792 aastore (2, 4)
	793 iinc (2, 4)
	794 #27 (2, 4)
	795 -89 (2, 4)
	796 goto (2, 4)
	797 -339 (2, 4)
	799 aload_0 (1, 1)
	800 bipush (1, 1)
	801 16 (1, 1)
	802 anewarray (1, 1)
	803 org/apache/commons/math3/RealFieldElement (1, 1)
	805 dup (1, 1)
	806 iconst_0 (1, 1)
	807 aload (1, 1)
	808 #25 (1, 1)
	809 iconst_0 (1, 1)
	810 aaload (1, 1)
	811 aastore (1, 1)
	812 dup (1, 1)
	813 iconst_1 (1, 1)
	814 aload (1, 1)
	815 #25 (1, 1)
	816 iconst_1 (1, 1)
	817 aaload (1, 1)
	818 aastore (1, 1)
	819 dup (1, 1)
	820 iconst_2 (1, 1)
	821 aload (1, 1)
	822 #25 (1, 1)
	823 iconst_2 (1, 1)
	824 aaload (1, 1)
	825 aastore (1, 1)
	826 dup (1, 1)
	827 iconst_3 (1, 1)
	828 aload (1, 1)
	829 #25 (1, 1)
	830 iconst_3 (1, 1)
	831 aaload (1, 1)
	832 aastore (1, 1)
	833 dup (1, 1)
	834 iconst_4 (1, 1)
	835 aload (1, 1)
	836 #25 (1, 1)
	837 iconst_4 (1, 1)
	838 aaload (1, 1)
	839 aastore (1, 1)
	840 dup (1, 1)
	841 iconst_5 (1, 1)
	842 aload (1, 1)
	843 #25 (1, 1)
	844 iconst_5 (1, 1)
	845 aaload (1, 1)
	846 aastore (1, 1)
	847 dup (1, 1)
	848 bipush (1, 1)
	849 6 (1, 1)
	850 aload (1, 1)
	851 #25 (1, 1)
	852 bipush (1, 1)
	853 6 (1, 1)
	854 aaload (1, 1)
	855 aastore (1, 1)
	856 dup (1, 1)
	857 bipush (1, 1)
	858 7 (1, 1)
	859 aload (1, 1)
	860 #25 (1, 1)
	861 bipush (1, 1)
	862 7 (1, 1)
	863 aaload (1, 1)
	864 aastore (1, 1)
	865 dup (1, 1)
	866 bipush (1, 1)
	867 8 (1, 1)
	868 aload (1, 1)
	869 #25 (1, 1)
	870 bipush (1, 1)
	871 8 (1, 1)
	872 aaload (1, 1)
	873 aastore (1, 1)
	874 dup (1, 1)
	875 bipush (1, 1)
	876 9 (1, 1)
	877 aload (1, 1)
	878 #25 (1, 1)
	879 bipush (1, 1)
	880 9 (1, 1)
	881 aaload (1, 1)
	882 aastore (1, 1)
	883 dup (1, 1)
	884 bipush (1, 1)
	885 10 (1, 1)
	886 aload (1, 1)
	887 #25 (1, 1)
	888 bipush (1, 1)
	889 10 (1, 1)
	890 aaload (1, 1)
	891 aastore (1, 1)
	892 dup (1, 1)
	893 bipush (1, 1)
	894 11 (1, 1)
	895 aload (1, 1)
	896 #25 (1, 1)
	897 bipush (1, 1)
	898 11 (1, 1)
	899 aaload (1, 1)
	900 aastore (1, 1)
	901 dup (1, 1)
	902 bipush (1, 1)
	903 12 (1, 1)
	904 aload (1, 1)
	905 #25 (1, 1)
	906 bipush (1, 1)
	907 12 (1, 1)
	908 aaload (1, 1)
	909 aastore (1, 1)
	910 dup (1, 1)
	911 bipush (1, 1)
	912 13 (1, 1)
	913 aload (1, 1)
	914 #25 (1, 1)
	915 bipush (1, 1)
	916 13 (1, 1)
	917 aaload (1, 1)
	918 aastore (1, 1)
	919 dup (1, 1)
	920 bipush (1, 1)
	921 14 (1, 1)
	922 aload (1, 1)
	923 #25 (1, 1)
	924 bipush (1, 1)
	925 14 (1, 1)
	926 aaload (1, 1)
	927 aastore (1, 1)
	928 dup (1, 1)
	929 bipush (1, 1)
	930 15 (1, 1)
	931 aload (1, 1)
	932 #25 (1, 1)
	933 bipush (1, 1)
	934 15 (1, 1)
	935 aaload (1, 1)
	936 aastore (1, 1)
	937 invokevirtual (1, 1)
	938 org/apache/commons/math3/ode/nonstiff/DormandPrince853FieldStepInterpolator.previousStateLinearCombination:([Lorg/apache/commons/math3/RealFieldElement;)[Lorg/apache/commons/math3/RealFieldElement; (1, 1)
	940 astore (1, 1)
	941 #16 (1, 1)
	942 aload_0 (1, 1)
	943 bipush (1, 1)
	944 16 (1, 1)
	945 anewarray (1, 1)
	946 org/apache/commons/math3/RealFieldElement (1, 1)
	948 dup (1, 1)
	949 iconst_0 (1, 1)
	950 aload (1, 1)
	951 #26 (1, 1)
	952 iconst_0 (1, 1)
	953 aaload (1, 1)
	954 aastore (1, 1)
	955 dup (1, 1)
	956 iconst_1 (1, 1)
	957 aload (1, 1)
	958 #26 (1, 1)
	959 iconst_1 (1, 1)
	960 aaload (1, 1)
	961 aastore (1, 1)
	962 dup (1, 1)
	963 iconst_2 (1, 1)
	964 aload (1, 1)
	965 #26 (1, 1)
	966 iconst_2 (1, 1)
	967 aaload (1, 1)
	968 aastore (1, 1)
	969 dup (1, 1)
	970 iconst_3 (1, 1)
	971 aload (1, 1)
	972 #26 (1, 1)
	973 iconst_3 (1, 1)
	974 aaload (1, 1)
	975 aastore (1, 1)
	976 dup (1, 1)
	977 iconst_4 (1, 1)
	978 aload (1, 1)
	979 #26 (1, 1)
	980 iconst_4 (1, 1)
	981 aaload (1, 1)
	982 aastore (1, 1)
	983 dup (1, 1)
	984 iconst_5 (1, 1)
	985 aload (1, 1)
	986 #26 (1, 1)
	987 iconst_5 (1, 1)
	988 aaload (1, 1)
	989 aastore (1, 1)
	990 dup (1, 1)
	991 bipush (1, 1)
	992 6 (1, 1)
	993 aload (1, 1)
	994 #26 (1, 1)
	995 bipush (1, 1)
	996 6 (1, 1)
	997 aaload (1, 1)
	998 aastore (1, 1)
	999 dup (1, 1)
	1000 bipush (1, 1)
	1001 7 (1, 1)
	1002 aload (1, 1)
	1003 #26 (1, 1)
	1004 bipush (1, 1)
	1005 7 (1, 1)
	1006 aaload (1, 1)
	1007 aastore (1, 1)
	1008 dup (1, 1)
	1009 bipush (1, 1)
	1010 8 (1, 1)
	1011 aload (1, 1)
	1012 #26 (1, 1)
	1013 bipush (1, 1)
	1014 8 (1, 1)
	1015 aaload (1, 1)
	1016 aastore (1, 1)
	1017 dup (1, 1)
	1018 bipush (1, 1)
	1019 9 (1, 1)
	1020 aload (1, 1)
	1021 #26 (1, 1)
	1022 bipush (1, 1)
	1023 9 (1, 1)
	1024 aaload (1, 1)
	1025 aastore (1, 1)
	1026 dup (1, 1)
	1027 bipush (1, 1)
	1028 10 (1, 1)
	1029 aload (1, 1)
	1030 #26 (1, 1)
	1031 bipush (1, 1)
	1032 10 (1, 1)
	1033 aaload (1, 1)
	1034 aastore (1, 1)
	1035 dup (1, 1)
	1036 bipush (1, 1)
	1037 11 (1, 1)
	1038 aload (1, 1)
	1039 #26 (1, 1)
	1040 bipush (1, 1)
	1041 11 (1, 1)
	1042 aaload (1, 1)
	1043 aastore (1, 1)
	1044 dup (1, 1)
	1045 bipush (1, 1)
	1046 12 (1, 1)
	1047 aload (1, 1)
	1048 #26 (1, 1)
	1049 bipush (1, 1)
	1050 12 (1, 1)
	1051 aaload (1, 1)
	1052 aastore (1, 1)
	1053 dup (1, 1)
	1054 bipush (1, 1)
	1055 13 (1, 1)
	1056 aload (1, 1)
	1057 #26 (1, 1)
	1058 bipush (1, 1)
	1059 13 (1, 1)
	1060 aaload (1, 1)
	1061 aastore (1, 1)
	1062 dup (1, 1)
	1063 bipush (1, 1)
	1064 14 (1, 1)
	1065 aload (1, 1)
	1066 #26 (1, 1)
	1067 bipush (1, 1)
	1068 14 (1, 1)
	1069 aaload (1, 1)
	1070 aastore (1, 1)
	1071 dup (1, 1)
	1072 bipush (1, 1)
	1073 15 (1, 1)
	1074 aload (1, 1)
	1075 #26 (1, 1)
	1076 bipush (1, 1)
	1077 15 (1, 1)
	1078 aaload (1, 1)
	1079 aastore (1, 1)
	1080 invokevirtual (1, 1)
	1081 org/apache/commons/math3/ode/nonstiff/DormandPrince853FieldStepInterpolator.derivativeLinearCombination:([Lorg/apache/commons/math3/RealFieldElement;)[Lorg/apache/commons/math3/RealFieldElement; (1, 1)
	1083 astore (1, 1)
	1084 #17 (1, 1)
	1085 goto (2, 2)
	1086 766 (2, 2)
	1088 aload (2, 2)
	1089 #5 (2, 2)
	1090 invokeinterface (2, 2)
	1091 org/apache/commons/math3/RealFieldElement.add:(D)Ljava/lang/Object; (2, 2)
	1093 0 (2, 2)
	1095 checkcast (2, 2)
	1096 org/apache/commons/math3/RealFieldElement (2, 2)
	1098 astore (2, 2)
	1099 #18 (2, 2)
	1100 aload (2, 2)
	1101 #18 (2, 2)
	1102 aload_3 (2, 2)
	1103 invokeinterface (2, 2)
	1104 org/apache/commons/math3/RealFieldElement.getGlobalPreviousState:()Lorg/apache/commons/math3/ode/FieldODEStateAndDerivative; (2, 2)
	1106 0 (2, 2)
	1108 checkcast (2, 2)
	1109 org/apache/commons/math3/RealFieldElement (2, 2)
	1111 invokeinterface (2, 2)
	1112 org/apache/commons/math3/RealFieldElement.add:(D)Ljava/lang/Object; (2, 2)
	1114 0 (2, 2)
	1116 checkcast (2, 2)
	1117 org/apache/commons/math3/RealFieldElement (2, 2)
	1119 astore (2, 2)
	1120 #19 (2, 2)
	1121 aload (2, 2)
	1122 #19 (2, 2)
	1123 aload_3 (2, 2)
	1124 invokeinterface (2, 2)
	1125 org/apache/commons/math3/RealFieldElement.getGlobalPreviousState:()Lorg/apache/commons/math3/ode/FieldODEStateAndDerivative; (2, 2)
	1127 0 (2, 2)
	1129 checkcast (2, 2)
	1130 org/apache/commons/math3/RealFieldElement (2, 2)
	1132 astore (2, 2)
	1133 #20 (2, 2)
	1134 aload (2, 2)
	1135 #20 (2, 2)
	1136 aload (2, 2)
	1137 #7 (2, 2)
	1138 invokeinterface (2, 2)
	1139 org/apache/commons/math3/RealFieldElement.getGlobalPreviousState:()Lorg/apache/commons/math3/ode/FieldODEStateAndDerivative; (2, 2)
	1141 0 (2, 2)
	1143 checkcast (2, 2)
	1144 org/apache/commons/math3/RealFieldElement (2, 2)
	1146 astore (2, 2)
	1147 #21 (2, 2)
	1148 aload (2, 2)
	1149 #21 (2, 2)
	1150 aload_3 (2, 2)
	1151 invokeinterface (2, 2)
	1152 org/apache/commons/math3/RealFieldElement.getGlobalPreviousState:()Lorg/apache/commons/math3/ode/FieldODEStateAndDerivative; (2, 2)
	1154 0 (2, 2)
	1156 checkcast (2, 2)
	1157 org/apache/commons/math3/RealFieldElement (2, 2)
	1159 astore (2, 2)
	1160 #22 (2, 2)
	1161 aload (2, 2)
	1162 #22 (2, 2)
	1163 aload (2, 2)
	1164 #7 (2, 2)
	1165 invokeinterface (2, 2)
	1166 org/apache/commons/math3/RealFieldElement.getGlobalPreviousState:()Lorg/apache/commons/math3/ode/FieldODEStateAndDerivative; (2, 2)
	1168 0 (2, 2)
	1170 checkcast (2, 2)
	1171 org/apache/commons/math3/RealFieldElement (2, 2)
	1173 astore (2, 2)
	1174 #23 (2, 2)
	1175 aload (2, 2)
	1176 #23 (2, 2)
	1177 aload_3 (2, 2)
	1178 invokeinterface (2, 2)
	1179 org/apache/commons/math3/RealFieldElement.getGlobalPreviousState:()Lorg/apache/commons/math3/ode/FieldODEStateAndDerivative; (2, 2)
	1181 0 (2, 2)
	1183 checkcast (2, 2)
	1184 org/apache/commons/math3/RealFieldElement (2, 2)
	1186 astore (2, 2)
	1187 #24 (2, 2)
	1188 aload_2 (2, 2)
	1189 invokeinterface (2, 2)
	1190 org/apache/commons/math3/RealFieldElement.getOne:()Ljava/lang/Object; (2, 2)
	1192 0 (2, 2)
	1194 bipush (2, 2)
	1195 16 (2, 2)
	1196 invokestatic (2, 2)
	1197 org/apache/commons/math3/util/MathArrays.buildArray:(Lorg/apache/commons/math3/Field;I)[Ljava/lang/Object; (2, 2)
	1199 checkcast (2, 2)
	1200 [Lorg/apache/commons/math3/RealFieldElement; (2, 2)
	1202 astore (2, 2)
	1203 #25 (2, 2)
	1204 aload_2 (2, 2)
	1205 invokeinterface (2, 2)
	1206 org/apache/commons/math3/RealFieldElement.getOne:()Ljava/lang/Object; (2, 2)
	1208 0 (2, 2)
	1210 bipush (2, 2)
	1211 16 (2, 2)
	1212 invokestatic (2, 2)
	1213 org/apache/commons/math3/util/MathArrays.buildArray:(Lorg/apache/commons/math3/Field;I)[Ljava/lang/Object; (2, 2)
	1215 checkcast (2, 2)
	1216 [Lorg/apache/commons/math3/RealFieldElement; (2, 2)
	1218 astore (2, 2)
	1219 #26 (2, 2)
	1220 iconst_0 (3, 4)
	1221 istore (3, 4)
	1222 #27 (3, 4)
	1223 iload (3, 4)
	1224 #27 (3, 4)
	1225 aload (3, 4)
	1226 #25 (3, 4)
	1227 arraylength (3, 4)
	1228 if_icmpge (3, 4)
	1229 337 (3, 4)
	1231 aload (3, 4)
	1232 #25 (3, 4)
	1233 iload (3, 4)
	1234 #27 (3, 4)
	1235 aload (3, 4)
	1236 #18 (3, 4)
	1237 aload_0 (3, 4)
	1238 getfield (3, 4)
	1239 org/apache/commons/math3/ode/nonstiff/DormandPrince853FieldStepInterpolator.d:[[Lorg/apache/commons/math3/RealFieldElement; (3, 4)
	1241 iconst_0 (3, 4)
	1242 aaload (3, 4)
	1243 iload (3, 4)
	1244 #27 (3, 4)
	1245 aaload (3, 4)
	1246 invokeinterface (3, 4)
	1247 org/apache/commons/math3/RealFieldElement.getGlobalPreviousState:()Lorg/apache/commons/math3/ode/FieldODEStateAndDerivative; (3, 4)
	1249 0 (3, 4)
	1251 checkcast (3, 4)
	1252 org/apache/commons/math3/RealFieldElement (3, 4)
	1254 aload (3, 4)
	1255 #19 (3, 4)
	1256 aload_0 (3, 4)
	1257 getfield (3, 4)
	1258 org/apache/commons/math3/ode/nonstiff/DormandPrince853FieldStepInterpolator.d:[[Lorg/apache/commons/math3/RealFieldElement; (3, 4)
	1260 iconst_1 (3, 4)
	1261 aaload (3, 4)
	1262 iload (3, 4)
	1263 #27 (3, 4)
	1264 aaload (3, 4)
	1265 invokeinterface (3, 4)
	1266 org/apache/commons/math3/RealFieldElement.getGlobalPreviousState:()Lorg/apache/commons/math3/ode/FieldODEStateAndDerivative; (3, 4)
	1268 0 (3, 4)
	1270 invokeinterface (3, 4)
	1271 org/apache/commons/math3/RealFieldElement.previousStateLinearCombination:([Lorg/apache/commons/math3/RealFieldElement;)[Lorg/apache/commons/math3/RealFieldElement; (3, 4)
	1273 0 (3, 4)
	1275 checkcast (3, 4)
	1276 org/apache/commons/math3/RealFieldElement (3, 4)
	1278 aload (3, 4)
	1279 #20 (3, 4)
	1280 aload_0 (3, 4)
	1281 getfield (3, 4)
	1282 org/apache/commons/math3/ode/nonstiff/DormandPrince853FieldStepInterpolator.d:[[Lorg/apache/commons/math3/RealFieldElement; (3, 4)
	1284 iconst_2 (3, 4)
	1285 aaload (3, 4)
	1286 iload (3, 4)
	1287 #27 (3, 4)
	1288 aaload (3, 4)
	1289 invokeinterface (3, 4)
	1290 org/apache/commons/math3/RealFieldElement.getGlobalPreviousState:()Lorg/apache/commons/math3/ode/FieldODEStateAndDerivative; (3, 4)
	1292 0 (3, 4)
	1294 invokeinterface (3, 4)
	1295 org/apache/commons/math3/RealFieldElement.previousStateLinearCombination:([Lorg/apache/commons/math3/RealFieldElement;)[Lorg/apache/commons/math3/RealFieldElement; (3, 4)
	1297 0 (3, 4)
	1299 checkcast (3, 4)
	1300 org/apache/commons/math3/RealFieldElement (3, 4)
	1302 aload (3, 4)
	1303 #21 (3, 4)
	1304 aload_0 (3, 4)
	1305 getfield (3, 4)
	1306 org/apache/commons/math3/ode/nonstiff/DormandPrince853FieldStepInterpolator.d:[[Lorg/apache/commons/math3/RealFieldElement; (3, 4)
	1308 iconst_3 (3, 4)
	1309 aaload (3, 4)
	1310 iload (3, 4)
	1311 #27 (3, 4)
	1312 aaload (3, 4)
	1313 invokeinterface (3, 4)
	1314 org/apache/commons/math3/RealFieldElement.getGlobalPreviousState:()Lorg/apache/commons/math3/ode/FieldODEStateAndDerivative; (3, 4)
	1316 0 (3, 4)
	1318 invokeinterface (3, 4)
	1319 org/apache/commons/math3/RealFieldElement.previousStateLinearCombination:([Lorg/apache/commons/math3/RealFieldElement;)[Lorg/apache/commons/math3/RealFieldElement; (3, 4)
	1321 0 (3, 4)
	1323 checkcast (3, 4)
	1324 org/apache/commons/math3/RealFieldElement (3, 4)
	1326 aload (3, 4)
	1327 #22 (3, 4)
	1328 aload_0 (3, 4)
	1329 getfield (3, 4)
	1330 org/apache/commons/math3/ode/nonstiff/DormandPrince853FieldStepInterpolator.d:[[Lorg/apache/commons/math3/RealFieldElement; (3, 4)
	1332 iconst_4 (3, 4)
	1333 aaload (3, 4)
	1334 iload (3, 4)
	1335 #27 (3, 4)
	1336 aaload (3, 4)
	1337 invokeinterface (3, 4)
	1338 org/apache/commons/math3/RealFieldElement.getGlobalPreviousState:()Lorg/apache/commons/math3/ode/FieldODEStateAndDerivative; (3, 4)
	1340 0 (3, 4)
	1342 invokeinterface (3, 4)
	1343 org/apache/commons/math3/RealFieldElement.previousStateLinearCombination:([Lorg/apache/commons/math3/RealFieldElement;)[Lorg/apache/commons/math3/RealFieldElement; (3, 4)
	1345 0 (3, 4)
	1347 checkcast (3, 4)
	1348 org/apache/commons/math3/RealFieldElement (3, 4)
	1350 aload (3, 4)
	1351 #23 (3, 4)
	1352 aload_0 (3, 4)
	1353 getfield (3, 4)
	1354 org/apache/commons/math3/ode/nonstiff/DormandPrince853FieldStepInterpolator.d:[[Lorg/apache/commons/math3/RealFieldElement; (3, 4)
	1356 iconst_5 (3, 4)
	1357 aaload (3, 4)
	1358 iload (3, 4)
	1359 #27 (3, 4)
	1360 aaload (3, 4)
	1361 invokeinterface (3, 4)
	1362 org/apache/commons/math3/RealFieldElement.getGlobalPreviousState:()Lorg/apache/commons/math3/ode/FieldODEStateAndDerivative; (3, 4)
	1364 0 (3, 4)
	1366 invokeinterface (3, 4)
	1367 org/apache/commons/math3/RealFieldElement.previousStateLinearCombination:([Lorg/apache/commons/math3/RealFieldElement;)[Lorg/apache/commons/math3/RealFieldElement; (3, 4)
	1369 0 (3, 4)
	1371 checkcast (3, 4)
	1372 org/apache/commons/math3/RealFieldElement (3, 4)
	1374 aload (3, 4)
	1375 #24 (3, 4)
	1376 aload_0 (3, 4)
	1377 getfield (3, 4)
	1378 org/apache/commons/math3/ode/nonstiff/DormandPrince853FieldStepInterpolator.d:[[Lorg/apache/commons/math3/RealFieldElement; (3, 4)
	1380 bipush (3, 4)
	1381 6 (3, 4)
	1382 aaload (3, 4)
	1383 iload (3, 4)
	1384 #27 (3, 4)
	1385 aaload (3, 4)
	1386 invokeinterface (3, 4)
	1387 org/apache/commons/math3/RealFieldElement.getGlobalPreviousState:()Lorg/apache/commons/math3/ode/FieldODEStateAndDerivative; (3, 4)
	1389 0 (3, 4)
	1391 invokeinterface (3, 4)
	1392 org/apache/commons/math3/RealFieldElement.previousStateLinearCombination:([Lorg/apache/commons/math3/RealFieldElement;)[Lorg/apache/commons/math3/RealFieldElement; (3, 4)
	1394 0 (3, 4)
	1396 checkcast (3, 4)
	1397 org/apache/commons/math3/RealFieldElement (3, 4)
	1399 aastore (3, 4)
	1400 aload (3, 4)
	1401 #26 (3, 4)
	1402 iload (3, 4)
	1403 #27 (3, 4)
	1404 aload_0 (3, 4)
	1405 getfield (3, 4)
	1406 org/apache/commons/math3/ode/nonstiff/DormandPrince853FieldStepInterpolator.d:[[Lorg/apache/commons/math3/RealFieldElement; (3, 4)
	1408 iconst_0 (3, 4)
	1409 aaload (3, 4)
	1410 iload (3, 4)
	1411 #27 (3, 4)
	1412 aaload (3, 4)
	1413 aload (3, 4)
	1414 #10 (3, 4)
	1415 aload_0 (3, 4)
	1416 getfield (3, 4)
	1417 org/apache/commons/math3/ode/nonstiff/DormandPrince853FieldStepInterpolator.d:[[Lorg/apache/commons/math3/RealFieldElement; (3, 4)
	1419 iconst_1 (3, 4)
	1420 aaload (3, 4)
	1421 iload (3, 4)
	1422 #27 (3, 4)
	1423 aaload (3, 4)
	1424 invokeinterface (3, 4)
	1425 org/apache/commons/math3/RealFieldElement.getGlobalPreviousState:()Lorg/apache/commons/math3/ode/FieldODEStateAndDerivative; (3, 4)
	1427 0 (3, 4)
	1429 invokeinterface (3, 4)
	1430 org/apache/commons/math3/RealFieldElement.previousStateLinearCombination:([Lorg/apache/commons/math3/RealFieldElement;)[Lorg/apache/commons/math3/RealFieldElement; (3, 4)
	1432 0 (3, 4)
	1434 checkcast (3, 4)
	1435 org/apache/commons/math3/RealFieldElement (3, 4)
	1437 aload (3, 4)
	1438 #11 (3, 4)
	1439 aload_0 (3, 4)
	1440 getfield (3, 4)
	1441 org/apache/commons/math3/ode/nonstiff/DormandPrince853FieldStepInterpolator.d:[[Lorg/apache/commons/math3/RealFieldElement; (3, 4)
	1443 iconst_2 (3, 4)
	1444 aaload (3, 4)
	1445 iload (3, 4)
	1446 #27 (3, 4)
	1447 aaload (3, 4)
	1448 invokeinterface (3, 4)
	1449 org/apache/commons/math3/RealFieldElement.getGlobalPreviousState:()Lorg/apache/commons/math3/ode/FieldODEStateAndDerivative; (3, 4)
	1451 0 (3, 4)
	1453 invokeinterface (3, 4)
	1454 org/apache/commons/math3/RealFieldElement.previousStateLinearCombination:([Lorg/apache/commons/math3/RealFieldElement;)[Lorg/apache/commons/math3/RealFieldElement; (3, 4)
	1456 0 (3, 4)
	1458 checkcast (3, 4)
	1459 org/apache/commons/math3/RealFieldElement (3, 4)
	1461 aload (3, 4)
	1462 #12 (3, 4)
	1463 aload_0 (3, 4)
	1464 getfield (3, 4)
	1465 org/apache/commons/math3/ode/nonstiff/DormandPrince853FieldStepInterpolator.d:[[Lorg/apache/commons/math3/RealFieldElement; (3, 4)
	1467 iconst_3 (3, 4)
	1468 aaload (3, 4)
	1469 iload (3, 4)
	1470 #27 (3, 4)
	1471 aaload (3, 4)
	1472 invokeinterface (3, 4)
	1473 org/apache/commons/math3/RealFieldElement.getGlobalPreviousState:()Lorg/apache/commons/math3/ode/FieldODEStateAndDerivative; (3, 4)
	1475 0 (3, 4)
	1477 invokeinterface (3, 4)
	1478 org/apache/commons/math3/RealFieldElement.previousStateLinearCombination:([Lorg/apache/commons/math3/RealFieldElement;)[Lorg/apache/commons/math3/RealFieldElement; (3, 4)
	1480 0 (3, 4)
	1482 checkcast (3, 4)
	1483 org/apache/commons/math3/RealFieldElement (3, 4)
	1485 aload (3, 4)
	1486 #13 (3, 4)
	1487 aload_0 (3, 4)
	1488 getfield (3, 4)
	1489 org/apache/commons/math3/ode/nonstiff/DormandPrince853FieldStepInterpolator.d:[[Lorg/apache/commons/math3/RealFieldElement; (3, 4)
	1491 iconst_4 (3, 4)
	1492 aaload (3, 4)
	1493 iload (3, 4)
	1494 #27 (3, 4)
	1495 aaload (3, 4)
	1496 invokeinterface (3, 4)
	1497 org/apache/commons/math3/RealFieldElement.getGlobalPreviousState:()Lorg/apache/commons/math3/ode/FieldODEStateAndDerivative; (3, 4)
	1499 0 (3, 4)
	1501 invokeinterface (3, 4)
	1502 org/apache/commons/math3/RealFieldElement.previousStateLinearCombination:([Lorg/apache/commons/math3/RealFieldElement;)[Lorg/apache/commons/math3/RealFieldElement; (3, 4)
	1504 0 (3, 4)
	1506 checkcast (3, 4)
	1507 org/apache/commons/math3/RealFieldElement (3, 4)
	1509 aload (3, 4)
	1510 #14 (3, 4)
	1511 aload_0 (3, 4)
	1512 getfield (3, 4)
	1513 org/apache/commons/math3/ode/nonstiff/DormandPrince853FieldStepInterpolator.d:[[Lorg/apache/commons/math3/RealFieldElement; (3, 4)
	1515 iconst_5 (3, 4)
	1516 aaload (3, 4)
	1517 iload (3, 4)
	1518 #27 (3, 4)
	1519 aaload (3, 4)
	1520 invokeinterface (3, 4)
	1521 org/apache/commons/math3/RealFieldElement.getGlobalPreviousState:()Lorg/apache/commons/math3/ode/FieldODEStateAndDerivative; (3, 4)
	1523 0 (3, 4)
	1525 invokeinterface (3, 4)
	1526 org/apache/commons/math3/RealFieldElement.previousStateLinearCombination:([Lorg/apache/commons/math3/RealFieldElement;)[Lorg/apache/commons/math3/RealFieldElement; (3, 4)
	1528 0 (3, 4)
	1530 checkcast (3, 4)
	1531 org/apache/commons/math3/RealFieldElement (3, 4)
	1533 aload (3, 4)
	1534 #15 (3, 4)
	1535 aload_0 (3, 4)
	1536 getfield (3, 4)
	1537 org/apache/commons/math3/ode/nonstiff/DormandPrince853FieldStepInterpolator.d:[[Lorg/apache/commons/math3/RealFieldElement; (3, 4)
	1539 bipush (3, 4)
	1540 6 (3, 4)
	1541 aaload (3, 4)
	1542 iload (3, 4)
	1543 #27 (3, 4)
	1544 aaload (3, 4)
	1545 invokeinterface (3, 4)
	1546 org/apache/commons/math3/RealFieldElement.getGlobalPreviousState:()Lorg/apache/commons/math3/ode/FieldODEStateAndDerivative; (3, 4)
	1548 0 (3, 4)
	1550 invokeinterface (3, 4)
	1551 org/apache/commons/math3/RealFieldElement.previousStateLinearCombination:([Lorg/apache/commons/math3/RealFieldElement;)[Lorg/apache/commons/math3/RealFieldElement; (3, 4)
	1553 0 (3, 4)
	1555 checkcast (3, 4)
	1556 org/apache/commons/math3/RealFieldElement (3, 4)
	1558 aastore (3, 4)
	1559 iinc (3, 4)
	1560 #27 (3, 4)
	1561 -89 (3, 4)
	1562 goto (3, 4)
	1563 -339 (3, 4)
	1565 aload_0 (2, 2)
	1566 bipush (2, 2)
	1567 16 (2, 2)
	1568 anewarray (2, 2)
	1569 org/apache/commons/math3/RealFieldElement (2, 2)
	1571 dup (2, 2)
	1572 iconst_0 (2, 2)
	1573 aload (2, 2)
	1574 #25 (2, 2)
	1575 iconst_0 (2, 2)
	1576 aaload (2, 2)
	1577 aastore (2, 2)
	1578 dup (2, 2)
	1579 iconst_1 (2, 2)
	1580 aload (2, 2)
	1581 #25 (2, 2)
	1582 iconst_1 (2, 2)
	1583 aaload (2, 2)
	1584 aastore (2, 2)
	1585 dup (2, 2)
	1586 iconst_2 (2, 2)
	1587 aload (2, 2)
	1588 #25 (2, 2)
	1589 iconst_2 (2, 2)
	1590 aaload (2, 2)
	1591 aastore (2, 2)
	1592 dup (2, 2)
	1593 iconst_3 (2, 2)
	1594 aload (2, 2)
	1595 #25 (2, 2)
	1596 iconst_3 (2, 2)
	1597 aaload (2, 2)
	1598 aastore (2, 2)
	1599 dup (2, 2)
	1600 iconst_4 (2, 2)
	1601 aload (2, 2)
	1602 #25 (2, 2)
	1603 iconst_4 (2, 2)
	1604 aaload (2, 2)
	1605 aastore (2, 2)
	1606 dup (2, 2)
	1607 iconst_5 (2, 2)
	1608 aload (2, 2)
	1609 #25 (2, 2)
	1610 iconst_5 (2, 2)
	1611 aaload (2, 2)
	1612 aastore (2, 2)
	1613 dup (2, 2)
	1614 bipush (2, 2)
	1615 6 (2, 2)
	1616 aload (2, 2)
	1617 #25 (2, 2)
	1618 bipush (2, 2)
	1619 6 (2, 2)
	1620 aaload (2, 2)
	1621 aastore (2, 2)
	1622 dup (2, 2)
	1623 bipush (2, 2)
	1624 7 (2, 2)
	1625 aload (2, 2)
	1626 #25 (2, 2)
	1627 bipush (2, 2)
	1628 7 (2, 2)
	1629 aaload (2, 2)
	1630 aastore (2, 2)
	1631 dup (2, 2)
	1632 bipush (2, 2)
	1633 8 (2, 2)
	1634 aload (2, 2)
	1635 #25 (2, 2)
	1636 bipush (2, 2)
	1637 8 (2, 2)
	1638 aaload (2, 2)
	1639 aastore (2, 2)
	1640 dup (2, 2)
	1641 bipush (2, 2)
	1642 9 (2, 2)
	1643 aload (2, 2)
	1644 #25 (2, 2)
	1645 bipush (2, 2)
	1646 9 (2, 2)
	1647 aaload (2, 2)
	1648 aastore (2, 2)
	1649 dup (2, 2)
	1650 bipush (2, 2)
	1651 10 (2, 2)
	1652 aload (2, 2)
	1653 #25 (2, 2)
	1654 bipush (2, 2)
	1655 10 (2, 2)
	1656 aaload (2, 2)
	1657 aastore (2, 2)
	1658 dup (2, 2)
	1659 bipush (2, 2)
	1660 11 (2, 2)
	1661 aload (2, 2)
	1662 #25 (2, 2)
	1663 bipush (2, 2)
	1664 11 (2, 2)
	1665 aaload (2, 2)
	1666 aastore (2, 2)
	1667 dup (2, 2)
	1668 bipush (2, 2)
	1669 12 (2, 2)
	1670 aload (2, 2)
	1671 #25 (2, 2)
	1672 bipush (2, 2)
	1673 12 (2, 2)
	1674 aaload (2, 2)
	1675 aastore (2, 2)
	1676 dup (2, 2)
	1677 bipush (2, 2)
	1678 13 (2, 2)
	1679 aload (2, 2)
	1680 #25 (2, 2)
	1681 bipush (2, 2)
	1682 13 (2, 2)
	1683 aaload (2, 2)
	1684 aastore (2, 2)
	1685 dup (2, 2)
	1686 bipush (2, 2)
	1687 14 (2, 2)
	1688 aload (2, 2)
	1689 #25 (2, 2)
	1690 bipush (2, 2)
	1691 14 (2, 2)
	1692 aaload (2, 2)
	1693 aastore (2, 2)
	1694 dup (2, 2)
	1695 bipush (2, 2)
	1696 15 (2, 2)
	1697 aload (2, 2)
	1698 #25 (2, 2)
	1699 bipush (2, 2)
	1700 15 (2, 2)
	1701 aaload (2, 2)
	1702 aastore (2, 2)
	1703 invokevirtual (2, 2)
	1704 org/apache/commons/math3/ode/nonstiff/DormandPrince853FieldStepInterpolator.currentStateLinearCombination:([Lorg/apache/commons/math3/RealFieldElement;)[Lorg/apache/commons/math3/RealFieldElement; (2, 2)
	1706 astore (2, 2)
	1707 #16 (2, 2)
	1708 aload_0 (2, 2)
	1709 bipush (2, 2)
	1710 16 (2, 2)
	1711 anewarray (2, 2)
	1712 org/apache/commons/math3/RealFieldElement (2, 2)
	1714 dup (2, 2)
	1715 iconst_0 (2, 2)
	1716 aload (2, 2)
	1717 #26 (2, 2)
	1718 iconst_0 (2, 2)
	1719 aaload (2, 2)
	1720 aastore (2, 2)
	1721 dup (2, 2)
	1722 iconst_1 (2, 2)
	1723 aload (2, 2)
	1724 #26 (2, 2)
	1725 iconst_1 (2, 2)
	1726 aaload (2, 2)
	1727 aastore (2, 2)
	1728 dup (2, 2)
	1729 iconst_2 (2, 2)
	1730 aload (2, 2)
	1731 #26 (2, 2)
	1732 iconst_2 (2, 2)
	1733 aaload (2, 2)
	1734 aastore (2, 2)
	1735 dup (2, 2)
	1736 iconst_3 (2, 2)
	1737 aload (2, 2)
	1738 #26 (2, 2)
	1739 iconst_3 (2, 2)
	1740 aaload (2, 2)
	1741 aastore (2, 2)
	1742 dup (2, 2)
	1743 iconst_4 (2, 2)
	1744 aload (2, 2)
	1745 #26 (2, 2)
	1746 iconst_4 (2, 2)
	1747 aaload (2, 2)
	1748 aastore (2, 2)
	1749 dup (2, 2)
	1750 iconst_5 (2, 2)
	1751 aload (2, 2)
	1752 #26 (2, 2)
	1753 iconst_5 (2, 2)
	1754 aaload (2, 2)
	1755 aastore (2, 2)
	1756 dup (2, 2)
	1757 bipush (2, 2)
	1758 6 (2, 2)
	1759 aload (2, 2)
	1760 #26 (2, 2)
	1761 bipush (2, 2)
	1762 6 (2, 2)
	1763 aaload (2, 2)
	1764 aastore (2, 2)
	1765 dup (2, 2)
	1766 bipush (2, 2)
	1767 7 (2, 2)
	1768 aload (2, 2)
	1769 #26 (2, 2)
	1770 bipush (2, 2)
	1771 7 (2, 2)
	1772 aaload (2, 2)
	1773 aastore (2, 2)
	1774 dup (2, 2)
	1775 bipush (2, 2)
	1776 8 (2, 2)
	1777 aload (2, 2)
	1778 #26 (2, 2)
	1779 bipush (2, 2)
	1780 8 (2, 2)
	1781 aaload (2, 2)
	1782 aastore (2, 2)
	1783 dup (2, 2)
	1784 bipush (2, 2)
	1785 9 (2, 2)
	1786 aload (2, 2)
	1787 #26 (2, 2)
	1788 bipush (2, 2)
	1789 9 (2, 2)
	1790 aaload (2, 2)
	1791 aastore (2, 2)
	1792 dup (2, 2)
	1793 bipush (2, 2)
	1794 10 (2, 2)
	1795 aload (2, 2)
	1796 #26 (2, 2)
	1797 bipush (2, 2)
	1798 10 (2, 2)
	1799 aaload (2, 2)
	1800 aastore (2, 2)
	1801 dup (2, 2)
	1802 bipush (2, 2)
	1803 11 (2, 2)
	1804 aload (2, 2)
	1805 #26 (2, 2)
	1806 bipush (2, 2)
	1807 11 (2, 2)
	1808 aaload (2, 2)
	1809 aastore (2, 2)
	1810 dup (2, 2)
	1811 bipush (2, 2)
	1812 12 (2, 2)
	1813 aload (2, 2)
	1814 #26 (2, 2)
	1815 bipush (2, 2)
	1816 12 (2, 2)
	1817 aaload (2, 2)
	1818 aastore (2, 2)
	1819 dup (2, 2)
	1820 bipush (2, 2)
	1821 13 (2, 2)
	1822 aload (2, 2)
	1823 #26 (2, 2)
	1824 bipush (2, 2)
	1825 13 (2, 2)
	1826 aaload (2, 2)
	1827 aastore (2, 2)
	1828 dup (2, 2)
	1829 bipush (2, 2)
	1830 14 (2, 2)
	1831 aload (2, 2)
	1832 #26 (2, 2)
	1833 bipush (2, 2)
	1834 14 (2, 2)
	1835 aaload (2, 2)
	1836 aastore (2, 2)
	1837 dup (2, 2)
	1838 bipush (2, 2)
	1839 15 (2, 2)
	1840 aload (2, 2)
	1841 #26 (2, 2)
	1842 bipush (2, 2)
	1843 15 (2, 2)
	1844 aaload (2, 2)
	1845 aastore (2, 2)
	1846 invokevirtual (2, 2)
	1847 org/apache/commons/math3/ode/nonstiff/DormandPrince853FieldStepInterpolator.derivativeLinearCombination:([Lorg/apache/commons/math3/RealFieldElement;)[Lorg/apache/commons/math3/RealFieldElement; (2, 2)
	1849 astore (2, 2)
	1850 #17 (2, 2)
	1851 new (0, 0)
	1852 org/apache/commons/math3/ode/FieldODEStateAndDerivative (0, 0)
	1854 dup (0, 0)
	1855 aload_2 (0, 0)
	1856 aload (0, 0)
	1857 #16 (0, 0)
	1858 aload (0, 0)
	1859 #17 (0, 0)
	1860 invokespecial (0, 0)
	1861 org/apache/commons/math3/ode/FieldODEStateAndDerivative.<init>:(Lorg/apache/commons/math3/RealFieldElement;[Lorg/apache/commons/math3/RealFieldElement;[Lorg/apache/commons/math3/RealFieldElement;)V (0, 0)
	1863 areturn (0, 0)

