Method: <init>
	0 aload_0 (0, 0)
	1 aload_1 (0, 0)
	2 ldc (0, 0)
	4 bipush (0, 0)
	6 dload_2 (0, 0)
	7 dload (0, 0)
	9 aload (0, 0)
	11 aload (0, 0)
	13 invokespecial (0, 0)
	16 aload_0 (0, 0)
	17 aload_0 (0, 0)
	18 ldc2_w (0, 0)
	21 ldc2_w (0, 0)
	24 invokevirtual (0, 0)
	27 putfield (0, 0)
	30 aload_0 (0, 0)
	31 aload_0 (0, 0)
	32 ldc2_w (0, 0)
	35 ldc2_w (0, 0)
	38 invokevirtual (0, 0)
	41 putfield (0, 0)
	44 aload_0 (0, 0)
	45 aload_0 (0, 0)
	46 ldc2_w (0, 0)
	49 ldc2_w (0, 0)
	52 invokevirtual (0, 0)
	55 putfield (0, 0)
	58 aload_0 (0, 0)
	59 aload_0 (0, 0)
	60 ldc2_w (0, 0)
	63 ldc2_w (0, 0)
	66 invokevirtual (0, 0)
	69 putfield (0, 0)
	72 aload_0 (0, 0)
	73 aload_0 (0, 0)
	74 ldc2_w (0, 0)
	77 ldc2_w (0, 0)
	80 invokevirtual (0, 0)
	83 putfield (0, 0)
	86 aload_0 (0, 0)
	87 aload_0 (0, 0)
	88 ldc2_w (0, 0)
	91 ldc2_w (0, 0)
	94 invokevirtual (0, 0)
	97 putfield (0, 0)
	100 aload_0 (0, 0)
	101 aload_0 (0, 0)
	102 ldc2_w (0, 0)
	105 ldc2_w (0, 0)
	108 invokevirtual (0, 0)
	111 putfield (0, 0)
	114 aload_0 (0, 0)
	115 aload_0 (0, 0)
	116 ldc2_w (0, 0)
	119 ldc2_w (0, 0)
	122 invokevirtual (0, 0)
	125 putfield (0, 0)
	128 aload_0 (0, 0)
	129 aload_0 (0, 0)
	130 ldc2_w (0, 0)
	133 ldc2_w (0, 0)
	136 invokevirtual (0, 0)
	139 putfield (0, 0)
	142 aload_0 (0, 0)
	143 aload_0 (0, 0)
	144 ldc2_w (0, 0)
	147 ldc2_w (0, 0)
	150 invokevirtual (0, 0)
	153 putfield (0, 0)
	156 aload_0 (0, 0)
	157 aload_0 (0, 0)
	158 ldc2_w (0, 0)
	161 ldc2_w (0, 0)
	164 invokevirtual (0, 0)
	167 putfield (0, 0)
	170 aload_0 (0, 0)
	171 aload_0 (0, 0)
	172 ldc2_w (0, 0)
	175 ldc2_w (0, 0)
	178 invokevirtual (0, 0)
	181 putfield (0, 0)
	184 aload_0 (0, 0)
	185 aload_0 (0, 0)
	186 ldc2_w (0, 0)
	189 ldc2_w (0, 0)
	192 invokevirtual (0, 0)
	195 putfield (0, 0)
	198 aload_0 (0, 0)
	199 aload_0 (0, 0)
	200 ldc2_w (0, 0)
	203 ldc2_w (0, 0)
	206 invokevirtual (0, 0)
	209 putfield (0, 0)
	212 aload_0 (0, 0)
	213 aload_0 (0, 0)
	214 ldc2_w (0, 0)
	217 ldc2_w (0, 0)
	220 invokevirtual (0, 0)
	223 putfield (0, 0)
	226 aload_0 (0, 0)
	227 aload_0 (0, 0)
	228 ldc2_w (0, 0)
	231 ldc2_w (0, 0)
	234 invokevirtual (0, 0)
	237 putfield (0, 0)
	240 return (0, 0)

Method: getC
	0 aload_0 (0, 0)
	1 invokevirtual (0, 0)
	4 invokeinterface (0, 0)
	9 checkcast (0, 0)
	12 bipush (0, 0)
	14 invokeinterface (0, 0)
	19 checkcast (0, 0)
	22 invokeinterface (0, 0)
	27 checkcast (0, 0)
	30 astore_1 (0, 0)
	31 aload_0 (0, 0)
	32 invokevirtual (0, 0)
	35 bipush (0, 0)
	37 invokestatic (0, 0)
	40 checkcast (0, 0)
	43 astore_2 (0, 0)
	44 aload_2 (0, 0)
	45 iconst_0 (0, 0)
	46 aload_1 (0, 0)
	47 ldc2_w (0, 0)
	50 invokeinterface (0, 0)
	55 checkcast (0, 0)
	58 ldc2_w (0, 0)
	61 invokeinterface (0, 0)
	66 checkcast (0, 0)
	69 aastore (0, 0)
	70 aload_2 (0, 0)
	71 iconst_1 (0, 0)
	72 aload_1 (0, 0)
	73 ldc2_w (0, 0)
	76 invokeinterface (0, 0)
	81 checkcast (0, 0)
	84 ldc2_w (0, 0)
	87 invokeinterface (0, 0)
	92 checkcast (0, 0)
	95 aastore (0, 0)
	96 aload_2 (0, 0)
	97 iconst_2 (0, 0)
	98 aload_1 (0, 0)
	99 ldc2_w (0, 0)
	102 invokeinterface (0, 0)
	107 checkcast (0, 0)
	110 ldc2_w (0, 0)
	113 invokeinterface (0, 0)
	118 checkcast (0, 0)
	121 aastore (0, 0)
	122 aload_2 (0, 0)
	123 iconst_3 (0, 0)
	124 aload_1 (0, 0)
	125 ldc2_w (0, 0)
	128 invokeinterface (0, 0)
	133 checkcast (0, 0)
	136 ldc2_w (0, 0)
	139 invokeinterface (0, 0)
	144 checkcast (0, 0)
	147 aastore (0, 0)
	148 aload_2 (0, 0)
	149 iconst_4 (0, 0)
	150 aload_0 (0, 0)
	151 iconst_1 (0, 0)
	152 iconst_3 (0, 0)
	153 invokevirtual (0, 0)
	156 aastore (0, 0)
	157 aload_2 (0, 0)
	158 iconst_5 (0, 0)
	159 aload_0 (0, 0)
	160 iconst_1 (0, 0)
	161 iconst_4 (0, 0)
	162 invokevirtual (0, 0)
	165 aastore (0, 0)
	166 aload_2 (0, 0)
	167 bipush (0, 0)
	169 aload_0 (0, 0)
	170 iconst_4 (0, 0)
	171 bipush (0, 0)
	173 invokevirtual (0, 0)
	176 aastore (0, 0)
	177 aload_2 (0, 0)
	178 bipush (0, 0)
	180 aload_0 (0, 0)
	181 bipush (0, 0)
	183 sipush (0, 0)
	186 invokevirtual (0, 0)
	189 aastore (0, 0)
	190 aload_2 (0, 0)
	191 bipush (0, 0)
	193 aload_0 (0, 0)
	194 iconst_3 (0, 0)
	195 iconst_5 (0, 0)
	196 invokevirtual (0, 0)
	199 aastore (0, 0)
	200 aload_2 (0, 0)
	201 bipush (0, 0)
	203 aload_0 (0, 0)
	204 bipush (0, 0)
	206 bipush (0, 0)
	208 invokevirtual (0, 0)
	211 aastore (0, 0)
	212 aload_2 (0, 0)
	213 bipush (0, 0)
	215 aload_0 (0, 0)
	216 invokevirtual (0, 0)
	219 invokeinterface (0, 0)
	224 checkcast (0, 0)
	227 aastore (0, 0)
	228 aload_2 (0, 0)
	229 bipush (0, 0)
	231 aload_0 (0, 0)
	232 invokevirtual (0, 0)
	235 invokeinterface (0, 0)
	240 checkcast (0, 0)
	243 aastore (0, 0)
	244 aload_2 (0, 0)
	245 bipush (0, 0)
	247 aload_0 (0, 0)
	248 dconst_1 (0, 0)
	249 ldc2_w (0, 0)
	252 invokevirtual (0, 0)
	255 aastore (0, 0)
	256 aload_2 (0, 0)
	257 bipush (0, 0)
	259 aload_0 (0, 0)
	260 dconst_1 (0, 0)
	261 ldc2_w (0, 0)
	264 invokevirtual (0, 0)
	267 aastore (0, 0)
	268 aload_2 (0, 0)
	269 bipush (0, 0)
	271 aload_0 (0, 0)
	272 ldc2_w (0, 0)
	275 ldc2_w (0, 0)
	278 invokevirtual (0, 0)
	281 aastore (0, 0)
	282 aload_2 (0, 0)
	283 areturn (0, 0)

Method: getA
	0 aload_0 (0, 0)
	1 invokevirtual (0, 0)
	4 invokeinterface (0, 0)
	9 checkcast (0, 0)
	12 bipush (0, 0)
	14 invokeinterface (0, 0)
	19 checkcast (0, 0)
	22 invokeinterface (0, 0)
	27 checkcast (0, 0)
	30 astore_1 (0, 0)
	31 aload_0 (0, 0)
	32 invokevirtual (0, 0)
	35 bipush (0, 0)
	37 iconst_m1 (0, 0)
	38 invokestatic (0, 0)
	41 checkcast (0, 0)
	44 astore_2 (0, 0)
	45 iconst_0 (1, 4)
	46 istore_3 (1, 4)
	47 iload_3 (1, 4)
	48 aload_2 (1, 4)
	49 arraylength (1, 4)
	50 if_icmpge (1, 4)
	53 aload_2 (1, 4)
	54 iload_3 (1, 4)
	55 aload_0 (1, 4)
	56 invokevirtual (1, 4)
	59 iload_3 (1, 4)
	60 iconst_1 (1, 4)
	61 iadd (1, 4)
	62 invokestatic (1, 4)
	65 checkcast (1, 4)
	68 aastore (1, 4)
	69 iinc (1, 4)
	72 goto (1, 4)
	75 aload_2 (0, 0)
	76 iconst_0 (0, 0)
	77 aaload (0, 0)
	78 iconst_0 (0, 0)
	79 aload_1 (0, 0)
	80 ldc2_w (0, 0)
	83 invokeinterface (0, 0)
	88 checkcast (0, 0)
	91 ldc2_w (0, 0)
	94 invokeinterface (0, 0)
	99 checkcast (0, 0)
	102 aastore (0, 0)
	103 aload_2 (0, 0)
	104 iconst_1 (0, 0)
	105 aaload (0, 0)
	106 iconst_0 (0, 0)
	107 aload_1 (0, 0)
	108 ldc2_w (0, 0)
	111 invokeinterface (0, 0)
	116 checkcast (0, 0)
	119 ldc2_w (0, 0)
	122 invokeinterface (0, 0)
	127 checkcast (0, 0)
	130 aastore (0, 0)
	131 aload_2 (0, 0)
	132 iconst_1 (0, 0)
	133 aaload (0, 0)
	134 iconst_1 (0, 0)
	135 aload_1 (0, 0)
	136 ldc2_w (0, 0)
	139 invokeinterface (0, 0)
	144 checkcast (0, 0)
	147 ldc2_w (0, 0)
	150 invokeinterface (0, 0)
	155 checkcast (0, 0)
	158 aastore (0, 0)
	159 aload_2 (0, 0)
	160 iconst_2 (0, 0)
	161 aaload (0, 0)
	162 iconst_0 (0, 0)
	163 aload_1 (0, 0)
	164 ldc2_w (0, 0)
	167 invokeinterface (0, 0)
	172 checkcast (0, 0)
	175 ldc2_w (0, 0)
	178 invokeinterface (0, 0)
	183 checkcast (0, 0)
	186 aastore (0, 0)
	187 aload_2 (0, 0)
	188 iconst_2 (0, 0)
	189 aaload (0, 0)
	190 iconst_1 (0, 0)
	191 aload_0 (0, 0)
	192 invokevirtual (0, 0)
	195 invokeinterface (0, 0)
	200 checkcast (0, 0)
	203 aastore (0, 0)
	204 aload_2 (0, 0)
	205 iconst_2 (0, 0)
	206 aaload (0, 0)
	207 iconst_2 (0, 0)
	208 aload_1 (0, 0)
	209 ldc2_w (0, 0)
	212 invokeinterface (0, 0)
	217 checkcast (0, 0)
	220 ldc2_w (0, 0)
	223 invokeinterface (0, 0)
	228 checkcast (0, 0)
	231 aastore (0, 0)
	232 aload_2 (0, 0)
	233 iconst_3 (0, 0)
	234 aaload (0, 0)
	235 iconst_0 (0, 0)
	236 aload_1 (0, 0)
	237 bipush (0, 0)
	239 invokeinterface (0, 0)
	244 checkcast (0, 0)
	247 ldc2_w (0, 0)
	250 invokeinterface (0, 0)
	255 checkcast (0, 0)
	258 ldc2_w (0, 0)
	261 invokeinterface (0, 0)
	266 checkcast (0, 0)
	269 aastore (0, 0)
	270 aload_2 (0, 0)
	271 iconst_3 (0, 0)
	272 aaload (0, 0)
	273 iconst_1 (0, 0)
	274 aload_0 (0, 0)
	275 invokevirtual (0, 0)
	278 invokeinterface (0, 0)
	283 checkcast (0, 0)
	286 aastore (0, 0)
	287 aload_2 (0, 0)
	288 iconst_3 (0, 0)
	289 aaload (0, 0)
	290 iconst_2 (0, 0)
	291 aload_1 (0, 0)
	292 sipush (0, 0)
	295 invokeinterface (0, 0)
	300 checkcast (0, 0)
	303 ldc2_w (0, 0)
	306 invokeinterface (0, 0)
	311 checkcast (0, 0)
	314 ldc2_w (0, 0)
	317 invokeinterface (0, 0)
	322 checkcast (0, 0)
	325 aastore (0, 0)
	326 aload_2 (0, 0)
	327 iconst_3 (0, 0)
	328 aaload (0, 0)
	329 iconst_3 (0, 0)
	330 aload_1 (0, 0)
	331 bipush (0, 0)
	333 invokeinterface (0, 0)
	338 checkcast (0, 0)
	341 ldc2_w (0, 0)
	344 invokeinterface (0, 0)
	349 checkcast (0, 0)
	352 ldc2_w (0, 0)
	355 invokeinterface (0, 0)
	360 checkcast (0, 0)
	363 aastore (0, 0)
	364 aload_2 (0, 0)
	365 iconst_4 (0, 0)
	366 aaload (0, 0)
	367 iconst_0 (0, 0)
	368 aload_0 (0, 0)
	369 iconst_1 (0, 0)
	370 bipush (0, 0)
	372 invokevirtual (0, 0)
	375 aastore (0, 0)
	376 aload_2 (0, 0)
	377 iconst_4 (0, 0)
	378 aaload (0, 0)
	379 iconst_1 (0, 0)
	380 aload_0 (0, 0)
	381 invokevirtual (0, 0)
	384 invokeinterface (0, 0)
	389 checkcast (0, 0)
	392 aastore (0, 0)
	393 aload_2 (0, 0)
	394 iconst_4 (0, 0)
	395 aaload (0, 0)
	396 iconst_2 (0, 0)
	397 aload_0 (0, 0)
	398 invokevirtual (0, 0)
	401 invokeinterface (0, 0)
	406 checkcast (0, 0)
	409 aastore (0, 0)
	410 aload_2 (0, 0)
	411 iconst_4 (0, 0)
	412 aaload (0, 0)
	413 iconst_3 (0, 0)
	414 aload_1 (0, 0)
	415 ldc2_w (0, 0)
	418 invokeinterface (0, 0)
	423 checkcast (0, 0)
	426 ldc2_w (0, 0)
	429 invokeinterface (0, 0)
	434 checkcast (0, 0)
	437 aastore (0, 0)
	438 aload_2 (0, 0)
	439 iconst_4 (0, 0)
	440 aaload (0, 0)
	441 iconst_4 (0, 0)
	442 aload_1 (0, 0)
	443 ldc2_w (0, 0)
	446 invokeinterface (0, 0)
	451 checkcast (0, 0)
	454 ldc2_w (0, 0)
	457 invokeinterface (0, 0)
	462 checkcast (0, 0)
	465 aastore (0, 0)
	466 aload_2 (0, 0)
	467 iconst_5 (0, 0)
	468 aaload (0, 0)
	469 iconst_0 (0, 0)
	470 aload_0 (0, 0)
	471 bipush (0, 0)
	473 sipush (0, 0)
	476 invokevirtual (0, 0)
	479 aastore (0, 0)
	480 aload_2 (0, 0)
	481 iconst_5 (0, 0)
	482 aaload (0, 0)
	483 iconst_1 (0, 0)
	484 aload_0 (0, 0)
	485 invokevirtual (0, 0)
	488 invokeinterface (0, 0)
	493 checkcast (0, 0)
	496 aastore (0, 0)
	497 aload_2 (0, 0)
	498 iconst_5 (0, 0)
	499 aaload (0, 0)
	500 iconst_2 (0, 0)
	501 aload_0 (0, 0)
	502 invokevirtual (0, 0)
	505 invokeinterface (0, 0)
	510 checkcast (0, 0)
	513 aastore (0, 0)
	514 aload_2 (0, 0)
	515 iconst_5 (0, 0)
	516 aaload (0, 0)
	517 iconst_3 (0, 0)
	518 aload_1 (0, 0)
	519 bipush (0, 0)
	521 invokeinterface (0, 0)
	526 checkcast (0, 0)
	529 ldc2_w (0, 0)
	532 invokeinterface (0, 0)
	537 checkcast (0, 0)
	540 ldc2_w (0, 0)
	543 invokeinterface (0, 0)
	548 checkcast (0, 0)
	551 aastore (0, 0)
	552 aload_2 (0, 0)
	553 iconst_5 (0, 0)
	554 aaload (0, 0)
	555 iconst_4 (0, 0)
	556 aload_1 (0, 0)
	557 bipush (0, 0)
	559 invokeinterface (0, 0)
	564 checkcast (0, 0)
	567 ldc2_w (0, 0)
	570 invokeinterface (0, 0)
	575 checkcast (0, 0)
	578 ldc2_w (0, 0)
	581 invokeinterface (0, 0)
	586 checkcast (0, 0)
	589 aastore (0, 0)
	590 aload_2 (0, 0)
	591 iconst_5 (0, 0)
	592 aaload (0, 0)
	593 iconst_5 (0, 0)
	594 aload_0 (0, 0)
	595 bipush (0, 0)
	597 sipush (0, 0)
	600 invokevirtual (0, 0)
	603 aastore (0, 0)
	604 aload_2 (0, 0)
	605 bipush (0, 0)
	607 aaload (0, 0)
	608 iconst_0 (0, 0)
	609 aload_0 (0, 0)
	610 sipush (0, 0)
	613 ldc (0, 0)
	615 invokevirtual (0, 0)
	618 aastore (0, 0)
	619 aload_2 (0, 0)
	620 bipush (0, 0)
	622 aaload (0, 0)
	623 iconst_1 (0, 0)
	624 aload_0 (0, 0)
	625 invokevirtual (0, 0)
	628 invokeinterface (0, 0)
	633 checkcast (0, 0)
	636 aastore (0, 0)
	637 aload_2 (0, 0)
	638 bipush (0, 0)
	640 aaload (0, 0)
	641 iconst_2 (0, 0)
	642 aload_0 (0, 0)
	643 invokevirtual (0, 0)
	646 invokeinterface (0, 0)
	651 checkcast (0, 0)
	654 aastore (0, 0)
	655 aload_2 (0, 0)
	656 bipush (0, 0)
	658 aaload (0, 0)
	659 iconst_3 (0, 0)
	660 aload_1 (0, 0)
	661 sipush (0, 0)
	664 invokeinterface (0, 0)
	669 checkcast (0, 0)
	672 ldc2_w (0, 0)
	675 invokeinterface (0, 0)
	680 checkcast (0, 0)
	683 ldc2_w (0, 0)
	686 invokeinterface (0, 0)
	691 checkcast (0, 0)
	694 aastore (0, 0)
	695 aload_2 (0, 0)
	696 bipush (0, 0)
	698 aaload (0, 0)
	699 iconst_4 (0, 0)
	700 aload_1 (0, 0)
	701 sipush (0, 0)
	704 invokeinterface (0, 0)
	709 checkcast (0, 0)
	712 ldc2_w (0, 0)
	715 invokeinterface (0, 0)
	720 checkcast (0, 0)
	723 ldc2_w (0, 0)
	726 invokeinterface (0, 0)
	731 checkcast (0, 0)
	734 aastore (0, 0)
	735 aload_2 (0, 0)
	736 bipush (0, 0)
	738 aaload (0, 0)
	739 iconst_5 (0, 0)
	740 aload_0 (0, 0)
	741 sipush (0, 0)
	744 ldc (0, 0)
	746 invokevirtual (0, 0)
	749 aastore (0, 0)
	750 aload_2 (0, 0)
	751 bipush (0, 0)
	753 aaload (0, 0)
	754 bipush (0, 0)
	756 aload_0 (0, 0)
	757 sipush (0, 0)
	760 ldc (0, 0)
	762 invokevirtual (0, 0)
	765 aastore (0, 0)
	766 aload_2 (0, 0)
	767 bipush (0, 0)
	769 aaload (0, 0)
	770 iconst_0 (0, 0)
	771 aload_0 (0, 0)
	772 ldc2_w (0, 0)
	775 ldc2_w (0, 0)
	778 invokevirtual (0, 0)
	781 aastore (0, 0)
	782 aload_2 (0, 0)
	783 bipush (0, 0)
	785 aaload (0, 0)
	786 iconst_1 (0, 0)
	787 aload_0 (0, 0)
	788 invokevirtual (0, 0)
	791 invokeinterface (0, 0)
	796 checkcast (0, 0)
	799 aastore (0, 0)
	800 aload_2 (0, 0)
	801 bipush (0, 0)
	803 aaload (0, 0)
	804 iconst_2 (0, 0)
	805 aload_0 (0, 0)
	806 invokevirtual (0, 0)
	809 invokeinterface (0, 0)
	814 checkcast (0, 0)
	817 aastore (0, 0)
	818 aload_2 (0, 0)
	819 bipush (0, 0)
	821 aaload (0, 0)
	822 iconst_3 (0, 0)
	823 aload_1 (0, 0)
	824 ldc2_w (0, 0)
	827 invokeinterface (0, 0)
	832 checkcast (0, 0)
	835 ldc2_w (0, 0)
	838 invokeinterface (0, 0)
	843 checkcast (0, 0)
	846 ldc2_w (0, 0)
	849 invokeinterface (0, 0)
	854 checkcast (0, 0)
	857 aastore (0, 0)
	858 aload_2 (0, 0)
	859 bipush (0, 0)
	861 aaload (0, 0)
	862 iconst_4 (0, 0)
	863 aload_1 (0, 0)
	864 ldc2_w (0, 0)
	867 invokeinterface (0, 0)
	872 checkcast (0, 0)
	875 ldc2_w (0, 0)
	878 invokeinterface (0, 0)
	883 checkcast (0, 0)
	886 ldc2_w (0, 0)
	889 invokeinterface (0, 0)
	894 checkcast (0, 0)
	897 aastore (0, 0)
	898 aload_2 (0, 0)
	899 bipush (0, 0)
	901 aaload (0, 0)
	902 iconst_5 (0, 0)
	903 aload_0 (0, 0)
	904 ldc2_w (0, 0)
	907 ldc2_w (0, 0)
	910 invokevirtual (0, 0)
	913 aastore (0, 0)
	914 aload_2 (0, 0)
	915 bipush (0, 0)
	917 aaload (0, 0)
	918 bipush (0, 0)
	920 aload_0 (0, 0)
	921 ldc2_w (0, 0)
	924 ldc2_w (0, 0)
	927 invokevirtual (0, 0)
	930 aastore (0, 0)
	931 aload_2 (0, 0)
	932 bipush (0, 0)
	934 aaload (0, 0)
	935 bipush (0, 0)
	937 aload_0 (0, 0)
	938 ldc2_w (0, 0)
	941 ldc2_w (0, 0)
	944 invokevirtual (0, 0)
	947 aastore (0, 0)
	948 aload_2 (0, 0)
	949 bipush (0, 0)
	951 aaload (0, 0)
	952 iconst_0 (0, 0)
	953 aload_0 (0, 0)
	954 ldc2_w (0, 0)
	957 ldc2_w (0, 0)
	960 invokevirtual (0, 0)
	963 aastore (0, 0)
	964 aload_2 (0, 0)
	965 bipush (0, 0)
	967 aaload (0, 0)
	968 iconst_1 (0, 0)
	969 aload_0 (0, 0)
	970 invokevirtual (0, 0)
	973 invokeinterface (0, 0)
	978 checkcast (0, 0)
	981 aastore (0, 0)
	982 aload_2 (0, 0)
	983 bipush (0, 0)
	985 aaload (0, 0)
	986 iconst_2 (0, 0)
	987 aload_0 (0, 0)
	988 invokevirtual (0, 0)
	991 invokeinterface (0, 0)
	996 checkcast (0, 0)
	999 aastore (0, 0)
	1000 aload_2 (0, 0)
	1001 bipush (0, 0)
	1003 aaload (0, 0)
	1004 iconst_3 (0, 0)
	1005 aload_1 (0, 0)
	1006 ldc2_w (0, 0)
	1009 invokeinterface (0, 0)
	1014 checkcast (0, 0)
	1017 ldc2_w (0, 0)
	1020 invokeinterface (0, 0)
	1025 checkcast (0, 0)
	1028 ldc2_w (0, 0)
	1031 invokeinterface (0, 0)
	1036 checkcast (0, 0)
	1039 aastore (0, 0)
	1040 aload_2 (0, 0)
	1041 bipush (0, 0)
	1043 aaload (0, 0)
	1044 iconst_4 (0, 0)
	1045 aload_1 (0, 0)
	1046 ldc2_w (0, 0)
	1049 invokeinterface (0, 0)
	1054 checkcast (0, 0)
	1057 ldc2_w (0, 0)
	1060 invokeinterface (0, 0)
	1065 checkcast (0, 0)
	1068 ldc2_w (0, 0)
	1071 invokeinterface (0, 0)
	1076 checkcast (0, 0)
	1079 aastore (0, 0)
	1080 aload_2 (0, 0)
	1081 bipush (0, 0)
	1083 aaload (0, 0)
	1084 iconst_5 (0, 0)
	1085 aload_0 (0, 0)
	1086 ldc2_w (0, 0)
	1089 ldc2_w (0, 0)
	1092 invokevirtual (0, 0)
	1095 aastore (0, 0)
	1096 aload_2 (0, 0)
	1097 bipush (0, 0)
	1099 aaload (0, 0)
	1100 bipush (0, 0)
	1102 aload_0 (0, 0)
	1103 ldc2_w (0, 0)
	1106 ldc2_w (0, 0)
	1109 invokevirtual (0, 0)
	1112 aastore (0, 0)
	1113 aload_2 (0, 0)
	1114 bipush (0, 0)
	1116 aaload (0, 0)
	1117 bipush (0, 0)
	1119 aload_0 (0, 0)
	1120 ldc2_w (0, 0)
	1123 ldc2_w (0, 0)
	1126 invokevirtual (0, 0)
	1129 aastore (0, 0)
	1130 aload_2 (0, 0)
	1131 bipush (0, 0)
	1133 aaload (0, 0)
	1134 bipush (0, 0)
	1136 aload_0 (0, 0)
	1137 ldc2_w (0, 0)
	1140 ldc2_w (0, 0)
	1143 invokevirtual (0, 0)
	1146 aastore (0, 0)
	1147 aload_2 (0, 0)
	1148 bipush (0, 0)
	1150 aaload (0, 0)
	1151 iconst_0 (0, 0)
	1152 aload_0 (0, 0)
	1153 ldc2_w (0, 0)
	1156 ldc2_w (0, 0)
	1159 invokevirtual (0, 0)
	1162 aastore (0, 0)
	1163 aload_2 (0, 0)
	1164 bipush (0, 0)
	1166 aaload (0, 0)
	1167 iconst_1 (0, 0)
	1168 aload_0 (0, 0)
	1169 invokevirtual (0, 0)
	1172 invokeinterface (0, 0)
	1177 checkcast (0, 0)
	1180 aastore (0, 0)
	1181 aload_2 (0, 0)
	1182 bipush (0, 0)
	1184 aaload (0, 0)
	1185 iconst_2 (0, 0)
	1186 aload_0 (0, 0)
	1187 invokevirtual (0, 0)
	1190 invokeinterface (0, 0)
	1195 checkcast (0, 0)
	1198 aastore (0, 0)
	1199 aload_2 (0, 0)
	1200 bipush (0, 0)
	1202 aaload (0, 0)
	1203 iconst_3 (0, 0)
	1204 aload_1 (0, 0)
	1205 ldc2_w (0, 0)
	1208 invokeinterface (0, 0)
	1213 checkcast (0, 0)
	1216 ldc2_w (0, 0)
	1219 invokeinterface (0, 0)
	1224 checkcast (0, 0)
	1227 ldc2_w (0, 0)
	1230 invokeinterface (0, 0)
	1235 checkcast (0, 0)
	1238 aastore (0, 0)
	1239 aload_2 (0, 0)
	1240 bipush (0, 0)
	1242 aaload (0, 0)
	1243 iconst_4 (0, 0)
	1244 aload_1 (0, 0)
	1245 ldc2_w (0, 0)
	1248 invokeinterface (0, 0)
	1253 checkcast (0, 0)
	1256 ldc2_w (0, 0)
	1259 invokeinterface (0, 0)
	1264 checkcast (0, 0)
	1267 ldc2_w (0, 0)
	1270 invokeinterface (0, 0)
	1275 checkcast (0, 0)
	1278 aastore (0, 0)
	1279 aload_2 (0, 0)
	1280 bipush (0, 0)
	1282 aaload (0, 0)
	1283 iconst_5 (0, 0)
	1284 aload_0 (0, 0)
	1285 ldc2_w (0, 0)
	1288 ldc2_w (0, 0)
	1291 invokevirtual (0, 0)
	1294 aastore (0, 0)
	1295 aload_2 (0, 0)
	1296 bipush (0, 0)
	1298 aaload (0, 0)
	1299 bipush (0, 0)
	1301 aload_0 (0, 0)
	1302 ldc2_w (0, 0)
	1305 ldc2_w (0, 0)
	1308 invokevirtual (0, 0)
	1311 aastore (0, 0)
	1312 aload_2 (0, 0)
	1313 bipush (0, 0)
	1315 aaload (0, 0)
	1316 bipush (0, 0)
	1318 aload_0 (0, 0)
	1319 ldc2_w (0, 0)
	1322 ldc2_w (0, 0)
	1325 invokevirtual (0, 0)
	1328 aastore (0, 0)
	1329 aload_2 (0, 0)
	1330 bipush (0, 0)
	1332 aaload (0, 0)
	1333 bipush (0, 0)
	1335 aload_0 (0, 0)
	1336 ldc2_w (0, 0)
	1339 ldc2_w (0, 0)
	1342 invokevirtual (0, 0)
	1345 aastore (0, 0)
	1346 aload_2 (0, 0)
	1347 bipush (0, 0)
	1349 aaload (0, 0)
	1350 bipush (0, 0)
	1352 aload_0 (0, 0)
	1353 ldc2_w (0, 0)
	1356 ldc2_w (0, 0)
	1359 invokevirtual (0, 0)
	1362 aastore (0, 0)
	1363 aload_2 (0, 0)
	1364 bipush (0, 0)
	1366 aaload (0, 0)
	1367 iconst_0 (0, 0)
	1368 aload_0 (0, 0)
	1369 ldc2_w (0, 0)
	1372 ldc2_w (0, 0)
	1375 invokevirtual (0, 0)
	1378 aastore (0, 0)
	1379 aload_2 (0, 0)
	1380 bipush (0, 0)
	1382 aaload (0, 0)
	1383 iconst_1 (0, 0)
	1384 aload_0 (0, 0)
	1385 invokevirtual (0, 0)
	1388 invokeinterface (0, 0)
	1393 checkcast (0, 0)
	1396 aastore (0, 0)
	1397 aload_2 (0, 0)
	1398 bipush (0, 0)
	1400 aaload (0, 0)
	1401 iconst_2 (0, 0)
	1402 aload_0 (0, 0)
	1403 invokevirtual (0, 0)
	1406 invokeinterface (0, 0)
	1411 checkcast (0, 0)
	1414 aastore (0, 0)
	1415 aload_2 (0, 0)
	1416 bipush (0, 0)
	1418 aaload (0, 0)
	1419 iconst_3 (0, 0)
	1420 aload_1 (0, 0)
	1421 ldc2_w (0, 0)
	1424 invokeinterface (0, 0)
	1429 checkcast (0, 0)
	1432 ldc2_w (0, 0)
	1435 invokeinterface (0, 0)
	1440 checkcast (0, 0)
	1443 ldc2_w (0, 0)
	1446 invokeinterface (0, 0)
	1451 checkcast (0, 0)
	1454 aastore (0, 0)
	1455 aload_2 (0, 0)
	1456 bipush (0, 0)
	1458 aaload (0, 0)
	1459 iconst_4 (0, 0)
	1460 aload_1 (0, 0)
	1461 ldc2_w (0, 0)
	1464 invokeinterface (0, 0)
	1469 checkcast (0, 0)
	1472 ldc2_w (0, 0)
	1475 invokeinterface (0, 0)
	1480 checkcast (0, 0)
	1483 ldc2_w (0, 0)
	1486 invokeinterface (0, 0)
	1491 checkcast (0, 0)
	1494 aastore (0, 0)
	1495 aload_2 (0, 0)
	1496 bipush (0, 0)
	1498 aaload (0, 0)
	1499 iconst_5 (0, 0)
	1500 aload_0 (0, 0)
	1501 ldc2_w (0, 0)
	1504 ldc2_w (0, 0)
	1507 invokevirtual (0, 0)
	1510 aastore (0, 0)
	1511 aload_2 (0, 0)
	1512 bipush (0, 0)
	1514 aaload (0, 0)
	1515 bipush (0, 0)
	1517 aload_0 (0, 0)
	1518 ldc2_w (0, 0)
	1521 ldc2_w (0, 0)
	1524 invokevirtual (0, 0)
	1527 aastore (0, 0)
	1528 aload_2 (0, 0)
	1529 bipush (0, 0)
	1531 aaload (0, 0)
	1532 bipush (0, 0)
	1534 aload_0 (0, 0)
	1535 ldc2_w (0, 0)
	1538 ldc2_w (0, 0)
	1541 invokevirtual (0, 0)
	1544 aastore (0, 0)
	1545 aload_2 (0, 0)
	1546 bipush (0, 0)
	1548 aaload (0, 0)
	1549 bipush (0, 0)
	1551 aload_0 (0, 0)
	1552 ldc2_w (0, 0)
	1555 ldc2_w (0, 0)
	1558 invokevirtual (0, 0)
	1561 aastore (0, 0)
	1562 aload_2 (0, 0)
	1563 bipush (0, 0)
	1565 aaload (0, 0)
	1566 bipush (0, 0)
	1568 aload_0 (0, 0)
	1569 ldc2_w (0, 0)
	1572 ldc2_w (0, 0)
	1575 invokevirtual (0, 0)
	1578 aastore (0, 0)
	1579 aload_2 (0, 0)
	1580 bipush (0, 0)
	1582 aaload (0, 0)
	1583 bipush (0, 0)
	1585 aload_0 (0, 0)
	1586 ldc2_w (0, 0)
	1589 ldc2_w (0, 0)
	1592 invokevirtual (0, 0)
	1595 aastore (0, 0)
	1596 aload_2 (0, 4)
	1597 bipush (0, 4)
	1599 aaload (0, 4)
	1600 iconst_0 (0, 4)
	1601 aload_0 (0, 4)
	1602 ldc2_w (0, 4)
	1605 ldc2_w (0, 4)
	1608 invokevirtual (0, 4)
	1611 aastore (0, 4)
	1612 aload_2 (0, 4)
	1613 bipush (0, 4)
	1615 aaload (0, 4)
	1616 iconst_1 (0, 4)
	1617 aload_0 (0, 4)
	1618 invokevirtual (0, 4)
	1621 invokeinterface (0, 4)
	1626 checkcast (0, 4)
	1629 aastore (0, 4)
	1630 aload_2 (0, 4)
	1631 bipush (0, 4)
	1633 aaload (0, 4)
	1634 iconst_2 (0, 4)
	1635 aload_0 (0, 4)
	1636 invokevirtual (0, 4)
	1639 invokeinterface (0, 4)
	1644 checkcast (0, 4)
	1647 aastore (0, 4)
	1648 aload_2 (0, 4)
	1649 bipush (0, 4)
	1651 aaload (0, 4)
	1652 iconst_3 (0, 4)
	1653 aload_0 (0, 4)
	1654 invokevirtual (0, 4)
	1657 invokeinterface (0, 4)
	1662 checkcast (0, 4)
	1665 aastore (0, 4)
	1666 aload_2 (0, 4)
	1667 bipush (0, 4)
	1669 aaload (0, 4)
	1670 iconst_4 (0, 4)
	1671 aload_0 (0, 4)
	1672 invokevirtual (0, 4)
	1675 invokeinterface (0, 4)
	1680 checkcast (0, 4)
	1683 aastore (0, 4)
	1684 aload_2 (0, 4)
	1685 bipush (0, 4)
	1687 aaload (0, 4)
	1688 iconst_5 (0, 4)
	1689 aload_0 (0, 4)
	1690 ldc2_w (0, 4)
	1693 ldc2_w (0, 4)
	1696 invokevirtual (0, 4)
	1699 aastore (0, 4)
	1700 aload_2 (0, 4)
	1701 bipush (0, 4)
	1703 aaload (0, 4)
	1704 bipush (0, 4)
	1706 aload_0 (0, 4)
	1707 ldc2_w (0, 4)
	1710 ldc2_w (0, 4)
	1713 invokevirtual (0, 4)
	1716 aastore (0, 4)
	1717 aload_2 (0, 4)
	1718 bipush (0, 4)
	1720 aaload (0, 4)
	1721 bipush (0, 4)
	1723 aload_0 (0, 4)
	1724 ldc2_w (0, 4)
	1727 ldc2_w (0, 4)
	1730 invokevirtual (0, 4)
	1733 aastore (0, 4)
	1734 aload_2 (0, 4)
	1735 bipush (0, 4)
	1737 aaload (0, 4)
	1738 bipush (0, 4)
	1740 aload_0 (0, 4)
	1741 ldc2_w (0, 4)
	1744 ldc2_w (0, 4)
	1747 invokevirtual (0, 4)
	1750 aastore (0, 4)
	1751 aload_2 (0, 4)
	1752 bipush (0, 4)
	1754 aaload (0, 4)
	1755 bipush (0, 4)
	1757 aload_0 (0, 4)
	1758 ldc2_w (0, 4)
	1761 ldc2_w (0, 4)
	1764 invokevirtual (0, 4)
	1767 aastore (0, 4)
	1768 aload_2 (0, 4)
	1769 bipush (0, 4)
	1771 aaload (0, 4)
	1772 bipush (0, 4)
	1774 aload_0 (0, 4)
	1775 ldc2_w (0, 4)
	1778 ldc2_w (0, 4)
	1781 invokevirtual (0, 4)
	1784 aastore (0, 4)
	1785 aload_2 (0, 4)
	1786 bipush (0, 4)
	1788 aaload (0, 4)
	1789 bipush (0, 4)
	1791 aload_0 (0, 4)
	1792 ldc2_w (0, 4)
	1795 ldc2_w (0, 4)
	1798 invokevirtual (0, 4)
	1801 aastore (0, 4)
	1802 aload_2 (0, 4)
	1803 bipush (0, 4)
	1805 aaload (0, 4)
	1806 iconst_0 (0, 4)
	1807 aload_0 (0, 4)
	1808 ldc2_w (0, 4)
	1811 ldc2_w (0, 4)
	1814 invokevirtual (0, 4)
	1817 aastore (0, 4)
	1818 aload_2 (0, 4)
	1819 bipush (0, 4)
	1821 aaload (0, 4)
	1822 iconst_1 (0, 4)
	1823 aload_0 (0, 4)
	1824 invokevirtual (0, 4)
	1827 invokeinterface (0, 4)
	1832 checkcast (0, 4)
	1835 aastore (0, 4)
	1836 aload_2 (0, 4)
	1837 bipush (0, 4)
	1839 aaload (0, 4)
	1840 iconst_2 (0, 4)
	1841 aload_0 (0, 4)
	1842 invokevirtual (0, 4)
	1845 invokeinterface (0, 4)
	1850 checkcast (0, 4)
	1853 aastore (0, 4)
	1854 aload_2 (0, 4)
	1855 bipush (0, 4)
	1857 aaload (0, 4)
	1858 iconst_3 (0, 4)
	1859 aload_0 (0, 4)
	1860 invokevirtual (0, 4)
	1863 invokeinterface (0, 4)
	1868 checkcast (0, 4)
	1871 aastore (0, 4)
	1872 aload_2 (0, 4)
	1873 bipush (0, 4)
	1875 aaload (0, 4)
	1876 iconst_4 (0, 4)
	1877 aload_0 (0, 4)
	1878 invokevirtual (0, 4)
	1881 invokeinterface (0, 4)
	1886 checkcast (0, 4)
	1889 aastore (0, 4)
	1890 aload_2 (0, 4)
	1891 bipush (0, 4)
	1893 aaload (0, 4)
	1894 iconst_5 (0, 4)
	1895 aload_0 (0, 4)
	1896 invokevirtual (0, 4)
	1899 invokeinterface (0, 4)
	1904 checkcast (0, 4)
	1907 aastore (0, 4)
	1908 aload_2 (0, 4)
	1909 bipush (0, 4)
	1911 aaload (0, 4)
	1912 bipush (0, 4)
	1914 aload_0 (0, 4)
	1915 ldc2_w (0, 4)
	1918 ldc2_w (0, 4)
	1921 invokevirtual (0, 4)
	1924 aastore (0, 4)
	1925 aload_2 (0, 4)
	1926 bipush (0, 4)
	1928 aaload (0, 4)
	1929 bipush (0, 4)
	1931 aload_0 (0, 4)
	1932 ldc2_w (0, 4)
	1935 ldc2_w (0, 4)
	1938 invokevirtual (0, 4)
	1941 aastore (0, 4)
	1942 aload_2 (0, 4)
	1943 bipush (0, 4)
	1945 aaload (0, 4)
	1946 bipush (0, 4)
	1948 aload_0 (0, 4)
	1949 ldc2_w (0, 4)
	1952 ldc2_w (0, 4)
	1955 invokevirtual (0, 4)
	1958 aastore (0, 4)
	1959 aload_2 (0, 4)
	1960 bipush (0, 4)
	1962 aaload (0, 4)
	1963 bipush (0, 4)
	1965 aload_0 (0, 4)
	1966 ldc2_w (0, 4)
	1969 ldc2_w (0, 4)
	1972 invokevirtual (0, 4)
	1975 aastore (0, 4)
	1976 aload_2 (0, 4)
	1977 bipush (0, 4)
	1979 aaload (0, 4)
	1980 bipush (0, 4)
	1982 aload_0 (0, 4)
	1983 ldc2_w (0, 4)
	1986 ldc2_w (0, 4)
	1989 invokevirtual (0, 4)
	1992 aastore (0, 4)
	1993 aload_2 (0, 4)
	1994 bipush (0, 4)
	1996 aaload (0, 4)
	1997 bipush (0, 4)
	1999 aload_0 (0, 4)
	2000 ldc2_w (0, 4)
	2003 ldc2_w (0, 4)
	2006 invokevirtual (0, 4)
	2009 aastore (0, 4)
	2010 aload_2 (0, 4)
	2011 bipush (0, 4)
	2013 aaload (0, 4)
	2014 bipush (0, 4)
	2016 aload_0 (0, 4)
	2017 ldc2_w (0, 4)
	2020 ldc2_w (0, 4)
	2023 invokevirtual (0, 4)
	2026 aastore (0, 4)
	2027 aload_2 (0, 4)
	2028 bipush (0, 4)
	2030 aaload (0, 4)
	2031 iconst_0 (0, 4)
	2032 aload_0 (0, 4)
	2033 ldc2_w (0, 4)
	2036 ldc2_w (0, 4)
	2039 invokevirtual (0, 4)
	2042 aastore (0, 4)
	2043 aload_2 (0, 4)
	2044 bipush (0, 4)
	2046 aaload (0, 4)
	2047 iconst_1 (0, 4)
	2048 aload_0 (0, 4)
	2049 invokevirtual (0, 4)
	2052 invokeinterface (0, 4)
	2057 checkcast (0, 4)
	2060 aastore (0, 4)
	2061 aload_2 (0, 4)
	2062 bipush (0, 4)
	2064 aaload (0, 4)
	2065 iconst_2 (0, 4)
	2066 aload_0 (0, 4)
	2067 invokevirtual (0, 4)
	2070 invokeinterface (0, 4)
	2075 checkcast (0, 4)
	2078 aastore (0, 4)
	2079 aload_2 (0, 4)
	2080 bipush (0, 4)
	2082 aaload (0, 4)
	2083 iconst_3 (0, 4)
	2084 aload_0 (0, 4)
	2085 invokevirtual (0, 4)
	2088 invokeinterface (0, 4)
	2093 checkcast (0, 4)
	2096 aastore (0, 4)
	2097 aload_2 (0, 4)
	2098 bipush (0, 4)
	2100 aaload (0, 4)
	2101 iconst_4 (0, 4)
	2102 aload_0 (0, 4)
	2103 invokevirtual (0, 4)
	2106 invokeinterface (0, 4)
	2111 checkcast (0, 4)
	2114 aastore (0, 4)
	2115 aload_2 (0, 4)
	2116 bipush (0, 4)
	2118 aaload (0, 4)
	2119 iconst_5 (0, 4)
	2120 aload_0 (0, 4)
	2121 ldc2_w (0, 4)
	2124 ldc2_w (0, 4)
	2127 invokevirtual (0, 4)
	2130 aastore (0, 4)
	2131 aload_2 (0, 4)
	2132 bipush (0, 4)
	2134 aaload (0, 4)
	2135 bipush (0, 4)
	2137 aload_0 (0, 4)
	2138 ldc2_w (0, 4)
	2141 ldc2_w (0, 4)
	2144 invokevirtual (0, 4)
	2147 aastore (0, 4)
	2148 aload_2 (0, 4)
	2149 bipush (0, 4)
	2151 aaload (0, 4)
	2152 bipush (0, 4)
	2154 aload_0 (0, 4)
	2155 ldc2_w (0, 4)
	2158 ldc2_w (0, 4)
	2161 invokevirtual (0, 4)
	2164 aastore (0, 4)
	2165 aload_2 (0, 4)
	2166 bipush (0, 4)
	2168 aaload (0, 4)
	2169 bipush (0, 4)
	2171 aload_0 (0, 4)
	2172 invokevirtual (0, 4)
	2175 invokeinterface (0, 4)
	2180 checkcast (0, 4)
	2183 aastore (0, 4)
	2184 aload_2 (0, 4)
	2185 bipush (0, 4)
	2187 aaload (0, 4)
	2188 bipush (0, 4)
	2190 aload_0 (0, 4)
	2191 invokevirtual (0, 4)
	2194 invokeinterface (0, 4)
	2199 checkcast (0, 4)
	2202 aastore (0, 4)
	2203 aload_2 (0, 4)
	2204 bipush (0, 4)
	2206 aaload (0, 4)
	2207 bipush (0, 4)
	2209 aload_0 (0, 4)
	2210 ldc2_w (0, 4)
	2213 ldc2_w (0, 4)
	2216 invokevirtual (0, 4)
	2219 aastore (0, 4)
	2220 aload_2 (0, 4)
	2221 bipush (0, 4)
	2223 aaload (0, 4)
	2224 bipush (0, 4)
	2226 aload_0 (0, 4)
	2227 ldc2_w (0, 4)
	2230 ldc2_w (0, 4)
	2233 invokevirtual (0, 4)
	2236 aastore (0, 4)
	2237 aload_2 (0, 4)
	2238 bipush (0, 4)
	2240 aaload (0, 4)
	2241 bipush (0, 4)
	2243 aload_0 (0, 4)
	2244 ldc2_w (0, 4)
	2247 ldc2_w (0, 4)
	2250 invokevirtual (0, 4)
	2253 aastore (0, 4)
	2254 aload_2 (0, 4)
	2255 bipush (0, 4)
	2257 aaload (0, 4)
	2258 bipush (0, 4)
	2260 aload_0 (0, 4)
	2261 ldc2_w (0, 4)
	2264 ldc2_w (0, 4)
	2267 invokevirtual (0, 4)
	2270 aastore (0, 4)
	2271 aload_2 (0, 4)
	2272 bipush (0, 4)
	2274 aaload (0, 4)
	2275 iconst_0 (0, 4)
	2276 aload_0 (0, 4)
	2277 ldc2_w (0, 4)
	2280 ldc2_w (0, 4)
	2283 invokevirtual (0, 4)
	2286 aastore (0, 4)
	2287 aload_2 (0, 4)
	2288 bipush (0, 4)
	2290 aaload (0, 4)
	2291 iconst_1 (0, 4)
	2292 aload_0 (0, 4)
	2293 invokevirtual (0, 4)
	2296 invokeinterface (0, 4)
	2301 checkcast (0, 4)
	2304 aastore (0, 4)
	2305 aload_2 (0, 4)
	2306 bipush (0, 4)
	2308 aaload (0, 4)
	2309 iconst_2 (0, 4)
	2310 aload_0 (0, 4)
	2311 invokevirtual (0, 4)
	2314 invokeinterface (0, 4)
	2319 checkcast (0, 4)
	2322 aastore (0, 4)
	2323 aload_2 (0, 4)
	2324 bipush (0, 4)
	2326 aaload (0, 4)
	2327 iconst_3 (0, 4)
	2328 aload_0 (0, 4)
	2329 invokevirtual (0, 4)
	2332 invokeinterface (0, 4)
	2337 checkcast (0, 4)
	2340 aastore (0, 4)
	2341 aload_2 (0, 4)
	2342 bipush (0, 4)
	2344 aaload (0, 4)
	2345 iconst_4 (0, 4)
	2346 aload_0 (0, 4)
	2347 invokevirtual (0, 4)
	2350 invokeinterface (0, 4)
	2355 checkcast (0, 4)
	2358 aastore (0, 4)
	2359 aload_2 (0, 4)
	2360 bipush (0, 4)
	2362 aaload (0, 4)
	2363 iconst_5 (0, 4)
	2364 aload_0 (0, 4)
	2365 ldc2_w (0, 4)
	2368 ldc2_w (0, 4)
	2371 invokevirtual (0, 4)
	2374 aastore (0, 4)
	2375 aload_2 (0, 4)
	2376 bipush (0, 4)
	2378 aaload (0, 4)
	2379 bipush (0, 4)
	2381 aload_0 (0, 4)
	2382 ldc2_w (0, 4)
	2385 ldc2_w (0, 4)
	2388 invokevirtual (0, 4)
	2391 aastore (0, 4)
	2392 aload_2 (0, 4)
	2393 bipush (0, 4)
	2395 aaload (0, 4)
	2396 bipush (0, 4)
	2398 aload_0 (0, 4)
	2399 ldc2_w (0, 4)
	2402 ldc2_w (0, 4)
	2405 invokevirtual (0, 4)
	2408 aastore (0, 4)
	2409 aload_2 (0, 4)
	2410 bipush (0, 4)
	2412 aaload (0, 4)
	2413 bipush (0, 4)
	2415 aload_0 (0, 4)
	2416 ldc2_w (0, 4)
	2419 ldc2_w (0, 4)
	2422 invokevirtual (0, 4)
	2425 aastore (0, 4)
	2426 aload_2 (0, 4)
	2427 bipush (0, 4)
	2429 aaload (0, 4)
	2430 bipush (0, 4)
	2432 aload_0 (0, 4)
	2433 invokevirtual (0, 4)
	2436 invokeinterface (0, 4)
	2441 checkcast (0, 4)
	2444 aastore (0, 4)
	2445 aload_2 (0, 4)
	2446 bipush (0, 4)
	2448 aaload (0, 4)
	2449 bipush (0, 4)
	2451 aload_0 (0, 4)
	2452 invokevirtual (0, 4)
	2455 invokeinterface (0, 4)
	2460 checkcast (0, 4)
	2463 aastore (0, 4)
	2464 aload_2 (0, 4)
	2465 bipush (0, 4)
	2467 aaload (0, 4)
	2468 bipush (0, 4)
	2470 aload_0 (0, 4)
	2471 invokevirtual (0, 4)
	2474 invokeinterface (0, 4)
	2479 checkcast (0, 4)
	2482 aastore (0, 4)
	2483 aload_2 (0, 4)
	2484 bipush (0, 4)
	2486 aaload (0, 4)
	2487 bipush (0, 4)
	2489 aload_0 (0, 4)
	2490 ldc2_w (0, 4)
	2493 ldc2_w (0, 4)
	2496 invokevirtual (0, 4)
	2499 aastore (0, 4)
	2500 aload_2 (0, 4)
	2501 bipush (0, 4)
	2503 aaload (0, 4)
	2504 bipush (0, 4)
	2506 aload_0 (0, 4)
	2507 ldc2_w (0, 4)
	2510 ldc2_w (0, 4)
	2513 invokevirtual (0, 4)
	2516 aastore (0, 4)
	2517 aload_2 (0, 4)
	2518 bipush (0, 4)
	2520 aaload (0, 4)
	2521 bipush (0, 4)
	2523 aload_0 (0, 4)
	2524 ldc2_w (0, 4)
	2527 ldc2_w (0, 4)
	2530 invokevirtual (0, 4)
	2533 aastore (0, 4)
	2534 aload_2 (0, 4)
	2535 areturn (0, 4)

Method: getB
	0 aload_0 (0, 0)
	1 invokevirtual (0, 0)
	4 bipush (0, 0)
	6 invokestatic (0, 0)
	9 checkcast (0, 0)
	12 astore_1 (0, 0)
	13 aload_1 (0, 0)
	14 iconst_0 (0, 0)
	15 aload_0 (0, 0)
	16 ldc_w (0, 0)
	19 ldc_w (0, 0)
	22 invokevirtual (0, 0)
	25 aastore (0, 0)
	26 aload_1 (0, 0)
	27 iconst_1 (0, 0)
	28 aload_0 (0, 0)
	29 invokevirtual (0, 0)
	32 invokeinterface (0, 0)
	37 checkcast (0, 0)
	40 aastore (0, 0)
	41 aload_1 (0, 0)
	42 iconst_2 (0, 0)
	43 aload_0 (0, 0)
	44 invokevirtual (0, 0)
	47 invokeinterface (0, 0)
	52 checkcast (0, 0)
	55 aastore (0, 0)
	56 aload_1 (0, 0)
	57 iconst_3 (0, 0)
	58 aload_0 (0, 0)
	59 invokevirtual (0, 0)
	62 invokeinterface (0, 0)
	67 checkcast (0, 0)
	70 aastore (0, 0)
	71 aload_1 (0, 0)
	72 iconst_4 (0, 0)
	73 aload_0 (0, 0)
	74 invokevirtual (0, 0)
	77 invokeinterface (0, 0)
	82 checkcast (0, 0)
	85 aastore (0, 0)
	86 aload_1 (0, 0)
	87 iconst_5 (0, 0)
	88 aload_0 (0, 0)
	89 ldc2_w (0, 0)
	92 ldc2_w (0, 0)
	95 invokevirtual (0, 0)
	98 aastore (0, 0)
	99 aload_1 (0, 0)
	100 bipush (0, 0)
	102 aload_0 (0, 0)
	103 ldc2_w (0, 0)
	106 ldc2_w (0, 0)
	109 invokevirtual (0, 0)
	112 aastore (0, 0)
	113 aload_1 (0, 0)
	114 bipush (0, 0)
	116 aload_0 (0, 0)
	117 ldc2_w (0, 0)
	120 ldc2_w (0, 0)
	123 invokevirtual (0, 0)
	126 aastore (0, 0)
	127 aload_1 (0, 0)
	128 bipush (0, 0)
	130 aload_0 (0, 0)
	131 ldc2_w (0, 0)
	134 ldc2_w (0, 0)
	137 invokevirtual (0, 0)
	140 aastore (0, 0)
	141 aload_1 (0, 0)
	142 bipush (0, 0)
	144 aload_0 (0, 0)
	145 ldc2_w (0, 0)
	148 ldc2_w (0, 0)
	151 invokevirtual (0, 0)
	154 aastore (0, 0)
	155 aload_1 (0, 0)
	156 bipush (0, 0)
	158 aload_0 (0, 0)
	159 ldc2_w (0, 0)
	162 ldc2_w (0, 0)
	165 invokevirtual (0, 0)
	168 aastore (0, 0)
	169 aload_1 (0, 0)
	170 bipush (0, 0)
	172 aload_0 (0, 0)
	173 ldc2_w (0, 0)
	176 ldc2_w (0, 0)
	179 invokevirtual (0, 0)
	182 aastore (0, 0)
	183 aload_1 (0, 0)
	184 bipush (0, 0)
	186 aload_0 (0, 0)
	187 invokevirtual (0, 0)
	190 invokeinterface (0, 0)
	195 checkcast (0, 0)
	198 aastore (0, 0)
	199 aload_1 (0, 0)
	200 bipush (0, 0)
	202 aload_0 (0, 0)
	203 invokevirtual (0, 0)
	206 invokeinterface (0, 0)
	211 checkcast (0, 0)
	214 aastore (0, 0)
	215 aload_1 (0, 0)
	216 bipush (0, 0)
	218 aload_0 (0, 0)
	219 invokevirtual (0, 0)
	222 invokeinterface (0, 0)
	227 checkcast (0, 0)
	230 aastore (0, 0)
	231 aload_1 (0, 0)
	232 bipush (0, 0)
	234 aload_0 (0, 0)
	235 invokevirtual (0, 0)
	238 invokeinterface (0, 0)
	243 checkcast (0, 0)
	246 aastore (0, 0)
	247 aload_1 (0, 0)
	248 areturn (0, 0)

Method: createInterpolator
	0 aload_0 (0, 0)
	1 iload_1 (0, 0)
	2 aload_2 (0, 0)
	3 aload_3 (0, 0)
	4 aload (0, 0)
	6 aload (0, 0)
	8 invokevirtual (0, 0)
	11 areturn (0, 0)

Method: getOrder
	0 bipush (0, 0)
	2 ireturn (0, 0)

Method: estimateError
	0 aload (0, 0)
	2 invokeinterface (0, 0)
	7 invokeinterface (0, 0)
	12 checkcast (0, 0)
	15 astore (0, 0)
	17 aload (0, 0)
	19 invokeinterface (0, 0)
	24 invokeinterface (0, 0)
	29 checkcast (0, 0)
	32 astore (0, 0)
	34 iconst_0 (1, 4)
	35 istore (1, 4)
	37 iload (1, 4)
	39 aload_0 (1, 4)
	40 getfield (1, 4)
	43 if_icmpge (1, 4)
	46 aload_1 (1, 4)
	47 iconst_0 (1, 4)
	48 aaload (1, 4)
	49 iload (1, 4)
	51 aaload (1, 4)
	52 aload_0 (1, 4)
	53 getfield (1, 4)
	56 invokeinterface (1, 4)
	61 checkcast (1, 4)
	64 aload_1 (1, 4)
	65 iconst_5 (1, 4)
	66 aaload (1, 4)
	67 iload (1, 4)
	69 aaload (1, 4)
	70 aload_0 (1, 4)
	71 getfield (1, 4)
	74 invokeinterface (1, 4)
	79 invokeinterface (1, 4)
	84 checkcast (1, 4)
	87 aload_1 (1, 4)
	88 bipush (1, 4)
	90 aaload (1, 4)
	91 iload (1, 4)
	93 aaload (1, 4)
	94 aload_0 (1, 4)
	95 getfield (1, 4)
	98 invokeinterface (1, 4)
	103 invokeinterface (1, 4)
	108 checkcast (1, 4)
	111 aload_1 (1, 4)
	112 bipush (1, 4)
	114 aaload (1, 4)
	115 iload (1, 4)
	117 aaload (1, 4)
	118 aload_0 (1, 4)
	119 getfield (1, 4)
	122 invokeinterface (1, 4)
	127 invokeinterface (1, 4)
	132 checkcast (1, 4)
	135 aload_1 (1, 4)
	136 bipush (1, 4)
	138 aaload (1, 4)
	139 iload (1, 4)
	141 aaload (1, 4)
	142 aload_0 (1, 4)
	143 getfield (1, 4)
	146 invokeinterface (1, 4)
	151 invokeinterface (1, 4)
	156 checkcast (1, 4)
	159 aload_1 (1, 4)
	160 bipush (1, 4)
	162 aaload (1, 4)
	163 iload (1, 4)
	165 aaload (1, 4)
	166 aload_0 (1, 4)
	167 getfield (1, 4)
	170 invokeinterface (1, 4)
	175 invokeinterface (1, 4)
	180 checkcast (1, 4)
	183 aload_1 (1, 4)
	184 bipush (1, 4)
	186 aaload (1, 4)
	187 iload (1, 4)
	189 aaload (1, 4)
	190 aload_0 (1, 4)
	191 getfield (1, 4)
	194 invokeinterface (1, 4)
	199 invokeinterface (1, 4)
	204 checkcast (1, 4)
	207 aload_1 (1, 4)
	208 bipush (1, 4)
	210 aaload (1, 4)
	211 iload (1, 4)
	213 aaload (1, 4)
	214 aload_0 (1, 4)
	215 getfield (1, 4)
	218 invokeinterface (1, 4)
	223 invokeinterface (1, 4)
	228 checkcast (1, 4)
	231 astore (1, 4)
	233 aload_1 (1, 4)
	234 iconst_0 (1, 4)
	235 aaload (1, 4)
	236 iload (1, 4)
	238 aaload (1, 4)
	239 aload_0 (1, 4)
	240 getfield (1, 4)
	243 invokeinterface (1, 4)
	248 checkcast (1, 4)
	251 aload_1 (1, 4)
	252 iconst_5 (1, 4)
	253 aaload (1, 4)
	254 iload (1, 4)
	256 aaload (1, 4)
	257 aload_0 (1, 4)
	258 getfield (1, 4)
	261 invokeinterface (1, 4)
	266 invokeinterface (1, 4)
	271 checkcast (1, 4)
	274 aload_1 (1, 4)
	275 bipush (1, 4)
	277 aaload (1, 4)
	278 iload (1, 4)
	280 aaload (1, 4)
	281 aload_0 (1, 4)
	282 getfield (1, 4)
	285 invokeinterface (1, 4)
	290 invokeinterface (1, 4)
	295 checkcast (1, 4)
	298 aload_1 (1, 4)
	299 bipush (1, 4)
	301 aaload (1, 4)
	302 iload (1, 4)
	304 aaload (1, 4)
	305 aload_0 (1, 4)
	306 getfield (1, 4)
	309 invokeinterface (1, 4)
	314 invokeinterface (1, 4)
	319 checkcast (1, 4)
	322 aload_1 (1, 4)
	323 bipush (1, 4)
	325 aaload (1, 4)
	326 iload (1, 4)
	328 aaload (1, 4)
	329 aload_0 (1, 4)
	330 getfield (1, 4)
	333 invokeinterface (1, 4)
	338 invokeinterface (1, 4)
	343 checkcast (1, 4)
	346 aload_1 (1, 4)
	347 bipush (1, 4)
	349 aaload (1, 4)
	350 iload (1, 4)
	352 aaload (1, 4)
	353 aload_0 (1, 4)
	354 getfield (1, 4)
	357 invokeinterface (1, 4)
	362 invokeinterface (1, 4)
	367 checkcast (1, 4)
	370 aload_1 (1, 4)
	371 bipush (1, 4)
	373 aaload (1, 4)
	374 iload (1, 4)
	376 aaload (1, 4)
	377 aload_0 (1, 4)
	378 getfield (1, 4)
	381 invokeinterface (1, 4)
	386 invokeinterface (1, 4)
	391 checkcast (1, 4)
	394 aload_1 (1, 4)
	395 bipush (1, 4)
	397 aaload (1, 4)
	398 iload (1, 4)
	400 aaload (1, 4)
	401 aload_0 (1, 4)
	402 getfield (1, 4)
	405 invokeinterface (1, 4)
	410 invokeinterface (1, 4)
	415 checkcast (1, 4)
	418 astore (1, 4)
	420 aload_2 (1, 4)
	421 iload (1, 4)
	423 aaload (1, 4)
	424 invokeinterface (1, 4)
	429 checkcast (1, 4)
	432 aload_3 (1, 4)
	433 iload (1, 4)
	435 aaload (1, 4)
	436 invokeinterface (1, 4)
	441 checkcast (1, 4)
	444 invokestatic (1, 4)
	447 astore (1, 4)
	449 aload_0 (1, 4)
	450 getfield (1, 4)
	453 ifnonnull (1, 4)
	456 aload (1, 4)
	458 aload_0 (1, 4)
	459 getfield (1, 4)
	462 invokeinterface (1, 4)
	467 checkcast (1, 4)
	470 aload_0 (1, 4)
	471 getfield (1, 4)
	474 invokeinterface (1, 4)
	479 checkcast (1, 4)
	482 goto (1, 4)
	485 aload (1, 4)
	487 aload_0 (1, 4)
	488 getfield (1, 4)
	491 iload (1, 4)
	493 daload (1, 4)
	494 invokeinterface (1, 4)
	499 checkcast (1, 4)
	502 aload_0 (1, 4)
	503 getfield (1, 4)
	506 iload (1, 4)
	508 daload (1, 4)
	509 invokeinterface (1, 4)
	514 checkcast (1, 4)
	517 astore (1, 4)
	519 aload (1, 4)
	521 aload (1, 4)
	523 invokeinterface (1, 4)
	528 checkcast (1, 4)
	531 astore (1, 4)
	533 aload (1, 4)
	535 aload (1, 4)
	537 aload (1, 4)
	539 invokeinterface (1, 4)
	544 invokeinterface (1, 4)
	549 checkcast (1, 4)
	552 astore (1, 4)
	554 aload (1, 4)
	556 aload (1, 4)
	558 invokeinterface (1, 4)
	563 checkcast (1, 4)
	566 astore (1, 4)
	568 aload (1, 4)
	570 aload (1, 4)
	572 aload (1, 4)
	574 invokeinterface (1, 4)
	579 invokeinterface (1, 4)
	584 checkcast (1, 4)
	587 astore (1, 4)
	589 iinc (1, 4)
	592 goto (1, 4)
	595 aload (0, 0)
	597 aload (0, 0)
	599 ldc2_w (0, 0)
	602 invokeinterface (0, 0)
	607 invokeinterface (0, 0)
	612 checkcast (0, 0)
	615 astore (0, 0)
	617 aload (1, 1)
	619 invokeinterface (1, 1)
	624 dconst_0 (1, 1)
	625 dcmpg (1, 1)
	626 ifgt (1, 1)
	629 aload (1, 1)
	631 invokeinterface (1, 1)
	636 invokeinterface (1, 1)
	641 checkcast (1, 1)
	644 astore (1, 1)
	646 aload (0, 0)
	648 invokeinterface (0, 0)
	653 checkcast (0, 0)
	656 aload (0, 0)
	658 invokeinterface (0, 0)
	663 checkcast (0, 0)
	666 aload (0, 0)
	668 aload_0 (0, 0)
	669 getfield (0, 0)
	672 invokeinterface (0, 0)
	677 checkcast (0, 0)
	680 invokeinterface (0, 0)
	685 invokeinterface (0, 0)
	690 checkcast (0, 0)
	693 areturn (0, 0)

