Method: <init>
	0 aload_0 (0, 0)
	1 aload_1 (0, 0)
	2 invokespecial (0, 0)
	3 org/apache/commons/math3/ode/nonstiff/RungeKuttaStepInterpolator.<init>:(Lorg/apache/commons/math3/ode/nonstiff/RungeKuttaStepInterpolator;)V (0, 0)
	5 aload_1 (1, 1)
	6 getfield (1, 1)
	7 org/apache/commons/math3/ode/nonstiff/DormandPrince853StepInterpolator.currentState:[D (1, 1)
	9 ifnonnull (1, 1)
	10 27 (1, 1)
	12 aload_0 (1, 1)
	13 aconst_null (1, 1)
	14 checkcast (1, 1)
	15 [[D (1, 1)
	17 putfield (1, 1)
	18 org/apache/commons/math3/ode/nonstiff/DormandPrince853StepInterpolator.yDotKLast:[[D (1, 1)
	20 aload_0 (1, 1)
	21 aconst_null (1, 1)
	22 checkcast (1, 1)
	23 [[D (1, 1)
	25 putfield (1, 1)
	26 org/apache/commons/math3/ode/nonstiff/DormandPrince853StepInterpolator.v:[[D (1, 1)
	28 aload_0 (1, 1)
	29 iconst_0 (1, 1)
	30 putfield (1, 1)
	31 org/apache/commons/math3/ode/nonstiff/DormandPrince853StepInterpolator.vectorsInitialized:Z (1, 1)
	33 goto (1, 1)
	34 122 (1, 1)
	36 aload_1 (1, 2)
	37 getfield (1, 2)
	38 org/apache/commons/math3/ode/nonstiff/DormandPrince853StepInterpolator.currentState:[D (1, 2)
	40 arraylength (1, 2)
	41 istore_2 (1, 2)
	42 aload_0 (1, 2)
	43 iconst_3 (1, 2)
	44 anewarray (1, 2)
	45 [D (1, 2)
	47 putfield (1, 2)
	48 org/apache/commons/math3/ode/nonstiff/DormandPrince853StepInterpolator.yDotKLast:[[D (1, 2)
	50 iconst_0 (2, 4)
	51 istore_3 (2, 4)
	52 iload_3 (2, 4)
	53 aload_0 (2, 4)
	54 getfield (2, 4)
	55 org/apache/commons/math3/ode/nonstiff/DormandPrince853StepInterpolator.yDotKLast:[[D (2, 4)
	57 arraylength (2, 4)
	58 if_icmpge (2, 4)
	59 36 (2, 4)
	61 aload_0 (2, 4)
	62 getfield (2, 4)
	63 org/apache/commons/math3/ode/nonstiff/DormandPrince853StepInterpolator.yDotKLast:[[D (2, 4)
	65 iload_3 (2, 4)
	66 iload_2 (2, 4)
	67 newarray (2, 4)
	68 7 (2, 4)
	69 aastore (2, 4)
	70 aload_1 (2, 4)
	71 getfield (2, 4)
	72 org/apache/commons/math3/ode/nonstiff/DormandPrince853StepInterpolator.yDotKLast:[[D (2, 4)
	74 iload_3 (2, 4)
	75 aaload (2, 4)
	76 iconst_0 (2, 4)
	77 aload_0 (2, 4)
	78 getfield (2, 4)
	79 org/apache/commons/math3/ode/nonstiff/DormandPrince853StepInterpolator.yDotKLast:[[D (2, 4)
	81 iload_3 (2, 4)
	82 aaload (2, 4)
	83 iconst_0 (2, 4)
	84 iload_2 (2, 4)
	85 invokestatic (2, 4)
	86 java/lang/System.arraycopy:(Ljava/lang/Object;ILjava/lang/Object;II)V (2, 4)
	88 iinc (2, 4)
	89 #3 (2, 4)
	90 -89 (2, 4)
	91 goto (2, 4)
	92 -39 (2, 4)
	94 aload_0 (1, 2)
	95 bipush (1, 2)
	96 7 (1, 2)
	97 anewarray (1, 2)
	98 [D (1, 2)
	100 putfield (1, 2)
	101 org/apache/commons/math3/ode/nonstiff/DormandPrince853StepInterpolator.v:[[D (1, 2)
	103 iconst_0 (2, 4)
	104 istore_3 (2, 4)
	105 iload_3 (2, 4)
	106 aload_0 (2, 4)
	107 getfield (2, 4)
	108 org/apache/commons/math3/ode/nonstiff/DormandPrince853StepInterpolator.v:[[D (2, 4)
	110 arraylength (2, 4)
	111 if_icmpge (2, 4)
	112 36 (2, 4)
	114 aload_0 (2, 4)
	115 getfield (2, 4)
	116 org/apache/commons/math3/ode/nonstiff/DormandPrince853StepInterpolator.v:[[D (2, 4)
	118 iload_3 (2, 4)
	119 iload_2 (2, 4)
	120 newarray (2, 4)
	121 7 (2, 4)
	122 aastore (2, 4)
	123 aload_1 (2, 4)
	124 getfield (2, 4)
	125 org/apache/commons/math3/ode/nonstiff/DormandPrince853StepInterpolator.v:[[D (2, 4)
	127 iload_3 (2, 4)
	128 aaload (2, 4)
	129 iconst_0 (2, 4)
	130 aload_0 (2, 4)
	131 getfield (2, 4)
	132 org/apache/commons/math3/ode/nonstiff/DormandPrince853StepInterpolator.v:[[D (2, 4)
	134 iload_3 (2, 4)
	135 aaload (2, 4)
	136 iconst_0 (2, 4)
	137 iload_2 (2, 4)
	138 invokestatic (2, 4)
	139 java/lang/System.arraycopy:(Ljava/lang/Object;ILjava/lang/Object;II)V (2, 4)
	141 iinc (2, 4)
	142 #3 (2, 4)
	143 -89 (2, 4)
	144 goto (2, 4)
	145 -39 (2, 4)
	147 aload_0 (1, 2)
	148 aload_1 (1, 2)
	149 getfield (1, 2)
	150 org/apache/commons/math3/ode/nonstiff/DormandPrince853StepInterpolator.vectorsInitialized:Z (1, 2)
	152 putfield (1, 2)
	153 org/apache/commons/math3/ode/nonstiff/DormandPrince853StepInterpolator.vectorsInitialized:Z (1, 2)
	155 return (0, 0)

Method: doCopy
	0 new (0, 0)
	1 org/apache/commons/math3/ode/nonstiff/DormandPrince853StepInterpolator (0, 0)
	3 dup (0, 0)
	4 aload_0 (0, 0)
	5 invokespecial (0, 0)
	6 org/apache/commons/math3/ode/nonstiff/DormandPrince853StepInterpolator.<init>:(Lorg/apache/commons/math3/ode/nonstiff/DormandPrince853StepInterpolator;)V (0, 0)
	8 areturn (0, 0)

Method: reinitialize
	0 aload_0 (0, 4)
	1 aload_1 (0, 4)
	2 aload_2 (0, 4)
	3 aload_3 (0, 4)
	4 iload (0, 4)
	5 #4 (0, 4)
	6 aload (0, 4)
	7 #5 (0, 4)
	8 aload (0, 4)
	9 #6 (0, 4)
	10 invokespecial (0, 4)
	11 org/apache/commons/math3/ode/nonstiff/RungeKuttaStepInterpolator.reinitialize:(Lorg/apache/commons/math3/ode/AbstractIntegrator;[D[[DZLorg/apache/commons/math3/ode/EquationsMapper;[Lorg/apache/commons/math3/ode/EquationsMapper;)V (0, 4)
	13 aload_0 (0, 4)
	14 getfield (0, 4)
	15 org/apache/commons/math3/ode/nonstiff/DormandPrince853StepInterpolator.currentState:[D (0, 4)
	17 arraylength (0, 4)
	18 istore (0, 4)
	19 #7 (0, 4)
	20 aload_0 (0, 4)
	21 iconst_3 (0, 4)
	22 anewarray (0, 4)
	23 [D (0, 4)
	25 putfield (0, 4)
	26 org/apache/commons/math3/ode/nonstiff/DormandPrince853StepInterpolator.yDotKLast:[[D (0, 4)
	28 iconst_0 (1, 4)
	29 istore (1, 4)
	30 #8 (1, 4)
	31 iload (1, 4)
	32 #8 (1, 4)
	33 aload_0 (1, 4)
	34 getfield (1, 4)
	35 org/apache/commons/math3/ode/nonstiff/DormandPrince853StepInterpolator.yDotKLast:[[D (1, 4)
	37 arraylength (1, 4)
	38 if_icmpge (1, 4)
	39 20 (1, 4)
	41 aload_0 (1, 4)
	42 getfield (1, 4)
	43 org/apache/commons/math3/ode/nonstiff/DormandPrince853StepInterpolator.yDotKLast:[[D (1, 4)
	45 iload (1, 4)
	46 #8 (1, 4)
	47 iload (1, 4)
	48 #7 (1, 4)
	49 newarray (1, 4)
	50 7 (1, 4)
	51 aastore (1, 4)
	52 iinc (1, 4)
	53 #8 (1, 4)
	54 -89 (1, 4)
	55 goto (1, 4)
	56 -24 (1, 4)
	58 aload_0 (0, 4)
	59 bipush (0, 4)
	60 7 (0, 4)
	61 anewarray (0, 4)
	62 [D (0, 4)
	64 putfield (0, 4)
	65 org/apache/commons/math3/ode/nonstiff/DormandPrince853StepInterpolator.v:[[D (0, 4)
	67 iconst_0 (1, 4)
	68 istore (1, 4)
	69 #8 (1, 4)
	70 iload (1, 4)
	71 #8 (1, 4)
	72 aload_0 (1, 4)
	73 getfield (1, 4)
	74 org/apache/commons/math3/ode/nonstiff/DormandPrince853StepInterpolator.v:[[D (1, 4)
	76 arraylength (1, 4)
	77 if_icmpge (1, 4)
	78 20 (1, 4)
	80 aload_0 (1, 4)
	81 getfield (1, 4)
	82 org/apache/commons/math3/ode/nonstiff/DormandPrince853StepInterpolator.v:[[D (1, 4)
	84 iload (1, 4)
	85 #8 (1, 4)
	86 iload (1, 4)
	87 #7 (1, 4)
	88 newarray (1, 4)
	89 7 (1, 4)
	90 aastore (1, 4)
	91 iinc (1, 4)
	92 #8 (1, 4)
	93 -89 (1, 4)
	94 goto (1, 4)
	95 -24 (1, 4)
	97 aload_0 (0, 4)
	98 iconst_0 (0, 4)
	99 putfield (0, 4)
	100 org/apache/commons/math3/ode/nonstiff/DormandPrince853StepInterpolator.vectorsInitialized:Z (0, 4)
	102 return (0, 4)

Method: storeTime
	0 aload_0 (0, 0)
	1 dload_1 (0, 0)
	2 invokespecial (0, 0)
	3 org/apache/commons/math3/ode/nonstiff/RungeKuttaStepInterpolator.storeTime:(D)V (0, 0)
	5 aload_0 (0, 0)
	6 iconst_0 (0, 0)
	7 putfield (0, 0)
	8 org/apache/commons/math3/ode/nonstiff/DormandPrince853StepInterpolator.vectorsInitialized:Z (0, 0)
	10 return (0, 0)

Method: computeInterpolatedStateAndDerivatives
	0 aload_0 (1, 1)
	1 getfield (1, 1)
	2 org/apache/commons/math3/ode/nonstiff/DormandPrince853StepInterpolator.vectorsInitialized:Z (1, 1)
	4 ifne (1, 1)
	5 519 (1, 1)
	7 aload_0 (2, 1)
	8 getfield (2, 1)
	9 org/apache/commons/math3/ode/nonstiff/DormandPrince853StepInterpolator.v:[[D (2, 1)
	11 ifnonnull (2, 1)
	12 42 (2, 1)
	14 aload_0 (2, 1)
	15 bipush (2, 1)
	16 7 (2, 1)
	17 anewarray (2, 1)
	18 [D (2, 1)
	20 putfield (2, 1)
	21 org/apache/commons/math3/ode/nonstiff/DormandPrince853StepInterpolator.v:[[D (2, 1)
	23 iconst_0 (3, 4)
	24 istore (3, 4)
	25 #5 (3, 4)
	26 iload (3, 4)
	27 #5 (3, 4)
	28 bipush (3, 4)
	29 7 (3, 4)
	30 if_icmpge (3, 4)
	31 23 (3, 4)
	33 aload_0 (3, 4)
	34 getfield (3, 4)
	35 org/apache/commons/math3/ode/nonstiff/DormandPrince853StepInterpolator.v:[[D (3, 4)
	37 iload (3, 4)
	38 #5 (3, 4)
	39 aload_0 (3, 4)
	40 getfield (3, 4)
	41 org/apache/commons/math3/ode/nonstiff/DormandPrince853StepInterpolator.interpolatedState:[D (3, 4)
	43 arraylength (3, 4)
	44 newarray (3, 4)
	45 7 (3, 4)
	46 aastore (3, 4)
	47 iinc (3, 4)
	48 #5 (3, 4)
	49 -89 (3, 4)
	50 goto (3, 4)
	51 -24 (3, 4)
	53 aload_0 (1, 1)
	54 invokevirtual (1, 1)
	55 org/apache/commons/math3/ode/nonstiff/DormandPrince853StepInterpolator.finalizeStep:()V (1, 1)
	57 iconst_0 (2, 4)
	58 istore (2, 4)
	59 #5 (2, 4)
	60 iload (2, 4)
	61 #5 (2, 4)
	62 aload_0 (2, 4)
	63 getfield (2, 4)
	64 org/apache/commons/math3/ode/nonstiff/DormandPrince853StepInterpolator.interpolatedState:[D (2, 4)
	66 arraylength (2, 4)
	67 if_icmpge (2, 4)
	68 451 (2, 4)
	70 aload_0 (2, 4)
	71 getfield (2, 4)
	72 org/apache/commons/math3/ode/nonstiff/DormandPrince853StepInterpolator.yDotK:[[D (2, 4)
	74 iconst_0 (2, 4)
	75 aaload (2, 4)
	76 iload (2, 4)
	77 #5 (2, 4)
	78 daload (2, 4)
	79 dstore (2, 4)
	80 #6 (2, 4)
	81 aload_0 (2, 4)
	82 getfield (2, 4)
	83 org/apache/commons/math3/ode/nonstiff/DormandPrince853StepInterpolator.yDotK:[[D (2, 4)
	85 iconst_5 (2, 4)
	86 aaload (2, 4)
	87 iload (2, 4)
	88 #5 (2, 4)
	89 daload (2, 4)
	90 dstore (2, 4)
	91 #8 (2, 4)
	92 aload_0 (2, 4)
	93 getfield (2, 4)
	94 org/apache/commons/math3/ode/nonstiff/DormandPrince853StepInterpolator.yDotK:[[D (2, 4)
	96 bipush (2, 4)
	97 6 (2, 4)
	98 aaload (2, 4)
	99 iload (2, 4)
	100 #5 (2, 4)
	101 daload (2, 4)
	102 dstore (2, 4)
	103 #10 (2, 4)
	104 aload_0 (2, 4)
	105 getfield (2, 4)
	106 org/apache/commons/math3/ode/nonstiff/DormandPrince853StepInterpolator.yDotK:[[D (2, 4)
	108 bipush (2, 4)
	109 7 (2, 4)
	110 aaload (2, 4)
	111 iload (2, 4)
	112 #5 (2, 4)
	113 daload (2, 4)
	114 dstore (2, 4)
	115 #12 (2, 4)
	116 aload_0 (2, 4)
	117 getfield (2, 4)
	118 org/apache/commons/math3/ode/nonstiff/DormandPrince853StepInterpolator.yDotK:[[D (2, 4)
	120 bipush (2, 4)
	121 8 (2, 4)
	122 aaload (2, 4)
	123 iload (2, 4)
	124 #5 (2, 4)
	125 daload (2, 4)
	126 dstore (2, 4)
	127 #14 (2, 4)
	128 aload_0 (2, 4)
	129 getfield (2, 4)
	130 org/apache/commons/math3/ode/nonstiff/DormandPrince853StepInterpolator.yDotK:[[D (2, 4)
	132 bipush (2, 4)
	133 9 (2, 4)
	134 aaload (2, 4)
	135 iload (2, 4)
	136 #5 (2, 4)
	137 daload (2, 4)
	138 dstore (2, 4)
	139 #16 (2, 4)
	140 aload_0 (2, 4)
	141 getfield (2, 4)
	142 org/apache/commons/math3/ode/nonstiff/DormandPrince853StepInterpolator.yDotK:[[D (2, 4)
	144 bipush (2, 4)
	145 10 (2, 4)
	146 aaload (2, 4)
	147 iload (2, 4)
	148 #5 (2, 4)
	149 daload (2, 4)
	150 dstore (2, 4)
	151 #18 (2, 4)
	152 aload_0 (2, 4)
	153 getfield (2, 4)
	154 org/apache/commons/math3/ode/nonstiff/DormandPrince853StepInterpolator.yDotK:[[D (2, 4)
	156 bipush (2, 4)
	157 11 (2, 4)
	158 aaload (2, 4)
	159 iload (2, 4)
	160 #5 (2, 4)
	161 daload (2, 4)
	162 dstore (2, 4)
	163 #20 (2, 4)
	164 aload_0 (2, 4)
	165 getfield (2, 4)
	166 org/apache/commons/math3/ode/nonstiff/DormandPrince853StepInterpolator.yDotK:[[D (2, 4)
	168 bipush (2, 4)
	169 12 (2, 4)
	170 aaload (2, 4)
	171 iload (2, 4)
	172 #5 (2, 4)
	173 daload (2, 4)
	174 dstore (2, 4)
	175 #22 (2, 4)
	176 aload_0 (2, 4)
	177 getfield (2, 4)
	178 org/apache/commons/math3/ode/nonstiff/DormandPrince853StepInterpolator.yDotKLast:[[D (2, 4)
	180 iconst_0 (2, 4)
	181 aaload (2, 4)
	182 iload (2, 4)
	183 #5 (2, 4)
	184 daload (2, 4)
	185 dstore (2, 4)
	186 #24 (2, 4)
	187 aload_0 (2, 4)
	188 getfield (2, 4)
	189 org/apache/commons/math3/ode/nonstiff/DormandPrince853StepInterpolator.yDotKLast:[[D (2, 4)
	191 iconst_1 (2, 4)
	192 aaload (2, 4)
	193 iload (2, 4)
	194 #5 (2, 4)
	195 daload (2, 4)
	196 dstore (2, 4)
	197 #26 (2, 4)
	198 aload_0 (2, 4)
	199 getfield (2, 4)
	200 org/apache/commons/math3/ode/nonstiff/DormandPrince853StepInterpolator.yDotKLast:[[D (2, 4)
	202 iconst_2 (2, 4)
	203 aaload (2, 4)
	204 iload (2, 4)
	205 #5 (2, 4)
	206 daload (2, 4)
	207 dstore (2, 4)
	208 #28 (2, 4)
	209 aload_0 (2, 4)
	210 getfield (2, 4)
	211 org/apache/commons/math3/ode/nonstiff/DormandPrince853StepInterpolator.v:[[D (2, 4)
	213 iconst_0 (2, 4)
	214 aaload (2, 4)
	215 iload (2, 4)
	216 #5 (2, 4)
	217 ldc2_w (2, 4)
	218 0.054293734116568765 (2, 4)
	220 dload (2, 4)
	221 #6 (2, 4)
	222 dmul (2, 4)
	223 ldc2_w (2, 4)
	224 4.450312892752409 (2, 4)
	226 dload (2, 4)
	227 #8 (2, 4)
	228 dmul (2, 4)
	229 dadd (2, 4)
	230 ldc2_w (2, 4)
	231 1.8915178993145003 (2, 4)
	233 dload (2, 4)
	234 #10 (2, 4)
	235 dmul (2, 4)
	236 dadd (2, 4)
	237 ldc2_w (2, 4)
	238 -5.801203960010585 (2, 4)
	240 dload (2, 4)
	241 #12 (2, 4)
	242 dmul (2, 4)
	243 dadd (2, 4)
	244 ldc2_w (2, 4)
	245 0.3111643669578199 (2, 4)
	247 dload (2, 4)
	248 #14 (2, 4)
	249 dmul (2, 4)
	250 dadd (2, 4)
	251 ldc2_w (2, 4)
	252 -0.1521609496625161 (2, 4)
	254 dload (2, 4)
	255 #16 (2, 4)
	256 dmul (2, 4)
	257 dadd (2, 4)
	258 ldc2_w (2, 4)
	259 0.20136540080403034 (2, 4)
	261 dload (2, 4)
	262 #18 (2, 4)
	263 dmul (2, 4)
	264 dadd (2, 4)
	265 ldc2_w (2, 4)
	266 0.04471061572777259 (2, 4)
	268 dload (2, 4)
	269 #20 (2, 4)
	270 dmul (2, 4)
	271 dadd (2, 4)
	272 dastore (2, 4)
	273 aload_0 (2, 4)
	274 getfield (2, 4)
	275 org/apache/commons/math3/ode/nonstiff/DormandPrince853StepInterpolator.v:[[D (2, 4)
	277 iconst_1 (2, 4)
	278 aaload (2, 4)
	279 iload (2, 4)
	280 #5 (2, 4)
	281 dload (2, 4)
	282 #6 (2, 4)
	283 aload_0 (2, 4)
	284 getfield (2, 4)
	285 org/apache/commons/math3/ode/nonstiff/DormandPrince853StepInterpolator.v:[[D (2, 4)
	287 iconst_0 (2, 4)
	288 aaload (2, 4)
	289 iload (2, 4)
	290 #5 (2, 4)
	291 daload (2, 4)
	292 dsub (2, 4)
	293 dastore (2, 4)
	294 aload_0 (2, 4)
	295 getfield (2, 4)
	296 org/apache/commons/math3/ode/nonstiff/DormandPrince853StepInterpolator.v:[[D (2, 4)
	298 iconst_2 (2, 4)
	299 aaload (2, 4)
	300 iload (2, 4)
	301 #5 (2, 4)
	302 aload_0 (2, 4)
	303 getfield (2, 4)
	304 org/apache/commons/math3/ode/nonstiff/DormandPrince853StepInterpolator.v:[[D (2, 4)
	306 iconst_0 (2, 4)
	307 aaload (2, 4)
	308 iload (2, 4)
	309 #5 (2, 4)
	310 daload (2, 4)
	311 aload_0 (2, 4)
	312 getfield (2, 4)
	313 org/apache/commons/math3/ode/nonstiff/DormandPrince853StepInterpolator.v:[[D (2, 4)
	315 iconst_1 (2, 4)
	316 aaload (2, 4)
	317 iload (2, 4)
	318 #5 (2, 4)
	319 daload (2, 4)
	320 dsub (2, 4)
	321 aload_0 (2, 4)
	322 getfield (2, 4)
	323 org/apache/commons/math3/ode/nonstiff/DormandPrince853StepInterpolator.yDotK:[[D (2, 4)
	325 bipush (2, 4)
	326 12 (2, 4)
	327 aaload (2, 4)
	328 iload (2, 4)
	329 #5 (2, 4)
	330 daload (2, 4)
	331 dsub (2, 4)
	332 dastore (2, 4)
	333 iconst_0 (3, 4)
	334 istore (3, 4)
	335 #30 (3, 4)
	336 iload (3, 4)
	337 #30 (3, 4)
	338 getstatic (3, 4)
	339 org/apache/commons/math3/ode/nonstiff/DormandPrince853StepInterpolator.D:[[D (3, 4)
	341 arraylength (3, 4)
	342 if_icmpge (3, 4)
	343 170 (3, 4)
	345 aload_0 (3, 4)
	346 getfield (3, 4)
	347 org/apache/commons/math3/ode/nonstiff/DormandPrince853StepInterpolator.v:[[D (3, 4)
	349 iload (3, 4)
	350 #30 (3, 4)
	351 iconst_3 (3, 4)
	352 iadd (3, 4)
	353 aaload (3, 4)
	354 iload (3, 4)
	355 #5 (3, 4)
	356 getstatic (3, 4)
	357 org/apache/commons/math3/ode/nonstiff/DormandPrince853StepInterpolator.D:[[D (3, 4)
	359 iload (3, 4)
	360 #30 (3, 4)
	361 aaload (3, 4)
	362 iconst_0 (3, 4)
	363 daload (3, 4)
	364 dload (3, 4)
	365 #6 (3, 4)
	366 dmul (3, 4)
	367 getstatic (3, 4)
	368 org/apache/commons/math3/ode/nonstiff/DormandPrince853StepInterpolator.D:[[D (3, 4)
	370 iload (3, 4)
	371 #30 (3, 4)
	372 aaload (3, 4)
	373 iconst_1 (3, 4)
	374 daload (3, 4)
	375 dload (3, 4)
	376 #8 (3, 4)
	377 dmul (3, 4)
	378 dadd (3, 4)
	379 getstatic (3, 4)
	380 org/apache/commons/math3/ode/nonstiff/DormandPrince853StepInterpolator.D:[[D (3, 4)
	382 iload (3, 4)
	383 #30 (3, 4)
	384 aaload (3, 4)
	385 iconst_2 (3, 4)
	386 daload (3, 4)
	387 dload (3, 4)
	388 #10 (3, 4)
	389 dmul (3, 4)
	390 dadd (3, 4)
	391 getstatic (3, 4)
	392 org/apache/commons/math3/ode/nonstiff/DormandPrince853StepInterpolator.D:[[D (3, 4)
	394 iload (3, 4)
	395 #30 (3, 4)
	396 aaload (3, 4)
	397 iconst_3 (3, 4)
	398 daload (3, 4)
	399 dload (3, 4)
	400 #12 (3, 4)
	401 dmul (3, 4)
	402 dadd (3, 4)
	403 getstatic (3, 4)
	404 org/apache/commons/math3/ode/nonstiff/DormandPrince853StepInterpolator.D:[[D (3, 4)
	406 iload (3, 4)
	407 #30 (3, 4)
	408 aaload (3, 4)
	409 iconst_4 (3, 4)
	410 daload (3, 4)
	411 dload (3, 4)
	412 #14 (3, 4)
	413 dmul (3, 4)
	414 dadd (3, 4)
	415 getstatic (3, 4)
	416 org/apache/commons/math3/ode/nonstiff/DormandPrince853StepInterpolator.D:[[D (3, 4)
	418 iload (3, 4)
	419 #30 (3, 4)
	420 aaload (3, 4)
	421 iconst_5 (3, 4)
	422 daload (3, 4)
	423 dload (3, 4)
	424 #16 (3, 4)
	425 dmul (3, 4)
	426 dadd (3, 4)
	427 getstatic (3, 4)
	428 org/apache/commons/math3/ode/nonstiff/DormandPrince853StepInterpolator.D:[[D (3, 4)
	430 iload (3, 4)
	431 #30 (3, 4)
	432 aaload (3, 4)
	433 bipush (3, 4)
	434 6 (3, 4)
	435 daload (3, 4)
	436 dload (3, 4)
	437 #18 (3, 4)
	438 dmul (3, 4)
	439 dadd (3, 4)
	440 getstatic (3, 4)
	441 org/apache/commons/math3/ode/nonstiff/DormandPrince853StepInterpolator.D:[[D (3, 4)
	443 iload (3, 4)
	444 #30 (3, 4)
	445 aaload (3, 4)
	446 bipush (3, 4)
	447 7 (3, 4)
	448 daload (3, 4)
	449 dload (3, 4)
	450 #20 (3, 4)
	451 dmul (3, 4)
	452 dadd (3, 4)
	453 getstatic (3, 4)
	454 org/apache/commons/math3/ode/nonstiff/DormandPrince853StepInterpolator.D:[[D (3, 4)
	456 iload (3, 4)
	457 #30 (3, 4)
	458 aaload (3, 4)
	459 bipush (3, 4)
	460 8 (3, 4)
	461 daload (3, 4)
	462 dload (3, 4)
	463 #22 (3, 4)
	464 dmul (3, 4)
	465 dadd (3, 4)
	466 getstatic (3, 4)
	467 org/apache/commons/math3/ode/nonstiff/DormandPrince853StepInterpolator.D:[[D (3, 4)
	469 iload (3, 4)
	470 #30 (3, 4)
	471 aaload (3, 4)
	472 bipush (3, 4)
	473 9 (3, 4)
	474 daload (3, 4)
	475 dload (3, 4)
	476 #24 (3, 4)
	477 dmul (3, 4)
	478 dadd (3, 4)
	479 getstatic (3, 4)
	480 org/apache/commons/math3/ode/nonstiff/DormandPrince853StepInterpolator.D:[[D (3, 4)
	482 iload (3, 4)
	483 #30 (3, 4)
	484 aaload (3, 4)
	485 bipush (3, 4)
	486 10 (3, 4)
	487 daload (3, 4)
	488 dload (3, 4)
	489 #26 (3, 4)
	490 dmul (3, 4)
	491 dadd (3, 4)
	492 getstatic (3, 4)
	493 org/apache/commons/math3/ode/nonstiff/DormandPrince853StepInterpolator.D:[[D (3, 4)
	495 iload (3, 4)
	496 #30 (3, 4)
	497 aaload (3, 4)
	498 bipush (3, 4)
	499 11 (3, 4)
	500 daload (3, 4)
	501 dload (3, 4)
	502 #28 (3, 4)
	503 dmul (3, 4)
	504 dadd (3, 4)
	505 dastore (3, 4)
	506 iinc (3, 4)
	507 #30 (3, 4)
	508 -89 (3, 4)
	509 goto (3, 4)
	510 -173 (3, 4)
	512 iinc (3, 4)
	513 #5 (3, 4)
	514 -89 (3, 4)
	515 goto (3, 4)
	516 -455 (3, 4)
	518 aload_0 (2, 4)
	519 iconst_1 (2, 4)
	520 putfield (2, 4)
	521 org/apache/commons/math3/ode/nonstiff/DormandPrince853StepInterpolator.vectorsInitialized:Z (2, 4)
	523 dconst_1 (1, 4)
	524 dload_1 (1, 4)
	525 dsub (1, 4)
	526 dstore (1, 4)
	527 #5 (1, 4)
	528 ldc2_w (1, 4)
	529 2.0 (1, 4)
	531 dload_1 (1, 4)
	532 dmul (1, 4)
	533 dstore (1, 4)
	534 #7 (1, 4)
	535 dload_1 (1, 4)
	536 dload_1 (1, 4)
	537 dmul (1, 4)
	538 dstore (1, 4)
	539 #9 (1, 4)
	540 dconst_1 (1, 4)
	541 dload (1, 4)
	542 #7 (1, 4)
	543 dsub (1, 4)
	544 dstore (1, 4)
	545 #11 (1, 4)
	546 dload_1 (1, 4)
	547 ldc2_w (1, 4)
	548 2.0 (1, 4)
	550 ldc2_w (1, 4)
	551 3.0 (1, 4)
	553 dload_1 (1, 4)
	554 dmul (1, 4)
	555 dsub (1, 4)
	556 dmul (1, 4)
	557 dstore (1, 4)
	558 #13 (1, 4)
	559 dload (1, 4)
	560 #7 (1, 4)
	561 dconst_1 (1, 4)
	562 dload_1 (1, 4)
	563 dload (1, 4)
	564 #7 (1, 4)
	565 ldc2_w (1, 4)
	566 3.0 (1, 4)
	568 dsub (1, 4)
	569 dmul (1, 4)
	570 dadd (1, 4)
	571 dmul (1, 4)
	572 dstore (1, 4)
	573 #15 (1, 4)
	574 dload (1, 4)
	575 #9 (1, 4)
	576 ldc2_w (1, 4)
	577 3.0 (1, 4)
	579 dload_1 (1, 4)
	580 ldc2_w (1, 4)
	581 5.0 (1, 4)
	583 dload_1 (1, 4)
	584 dmul (1, 4)
	585 ldc2_w (1, 4)
	586 8.0 (1, 4)
	588 dsub (1, 4)
	589 dmul (1, 4)
	590 dadd (1, 4)
	591 dmul (1, 4)
	592 dstore (1, 4)
	593 #17 (1, 4)
	594 dload (1, 4)
	595 #9 (1, 4)
	596 ldc2_w (1, 4)
	597 3.0 (1, 4)
	599 dload_1 (1, 4)
	600 ldc2_w (1, 4)
	601 -12.0 (1, 4)
	603 dload_1 (1, 4)
	604 ldc2_w (1, 4)
	605 15.0 (1, 4)
	607 ldc2_w (1, 4)
	608 6.0 (1, 4)
	610 dload_1 (1, 4)
	611 dmul (1, 4)
	612 dsub (1, 4)
	613 dmul (1, 4)
	614 dadd (1, 4)
	615 dmul (1, 4)
	616 dadd (1, 4)
	617 dmul (1, 4)
	618 dstore (1, 4)
	619 #19 (1, 4)
	620 dload (1, 4)
	621 #9 (1, 4)
	622 dload_1 (1, 4)
	623 dmul (1, 4)
	624 ldc2_w (1, 4)
	625 4.0 (1, 4)
	627 dload_1 (1, 4)
	628 ldc2_w (1, 4)
	629 -15.0 (1, 4)
	631 dload_1 (1, 4)
	632 ldc2_w (1, 4)
	633 18.0 (1, 4)
	635 ldc2_w (1, 4)
	636 7.0 (1, 4)
	638 dload_1 (1, 4)
	639 dmul (1, 4)
	640 dsub (1, 4)
	641 dmul (1, 4)
	642 dadd (1, 4)
	643 dmul (1, 4)
	644 dadd (1, 4)
	645 dmul (1, 4)
	646 dstore (1, 4)
	647 #21 (1, 4)
	648 aload_0 (2, 1)
	649 getfield (2, 1)
	650 org/apache/commons/math3/ode/nonstiff/DormandPrince853StepInterpolator.previousState:[D (2, 1)
	652 ifnull (2, 1)
	653 235 (2, 1)
	655 dload_1 (2, 1)
	656 ldc2_w (2, 1)
	657 0.5 (2, 1)
	659 dcmpg (2, 1)
	660 ifgt (2, 1)
	661 227 (2, 1)
	663 iconst_0 (3, 4)
	664 istore (3, 4)
	665 #23 (3, 4)
	666 iload (3, 4)
	667 #23 (3, 4)
	668 aload_0 (3, 4)
	669 getfield (3, 4)
	670 org/apache/commons/math3/ode/nonstiff/DormandPrince853StepInterpolator.interpolatedState:[D (3, 4)
	672 arraylength (3, 4)
	673 if_icmpge (3, 4)
	674 211 (3, 4)
	676 aload_0 (3, 4)
	677 getfield (3, 4)
	678 org/apache/commons/math3/ode/nonstiff/DormandPrince853StepInterpolator.interpolatedState:[D (3, 4)
	680 iload (3, 4)
	681 #23 (3, 4)
	682 aload_0 (3, 4)
	683 getfield (3, 4)
	684 org/apache/commons/math3/ode/nonstiff/DormandPrince853StepInterpolator.previousState:[D (3, 4)
	686 iload (3, 4)
	687 #23 (3, 4)
	688 daload (3, 4)
	689 dload_1 (3, 4)
	690 aload_0 (3, 4)
	691 getfield (3, 4)
	692 org/apache/commons/math3/ode/nonstiff/DormandPrince853StepInterpolator.h:D (3, 4)
	694 dmul (3, 4)
	695 aload_0 (3, 4)
	696 getfield (3, 4)
	697 org/apache/commons/math3/ode/nonstiff/DormandPrince853StepInterpolator.v:[[D (3, 4)
	699 iconst_0 (3, 4)
	700 aaload (3, 4)
	701 iload (3, 4)
	702 #23 (3, 4)
	703 daload (3, 4)
	704 dload (3, 4)
	705 #5 (3, 4)
	706 aload_0 (3, 4)
	707 getfield (3, 4)
	708 org/apache/commons/math3/ode/nonstiff/DormandPrince853StepInterpolator.v:[[D (3, 4)
	710 iconst_1 (3, 4)
	711 aaload (3, 4)
	712 iload (3, 4)
	713 #23 (3, 4)
	714 daload (3, 4)
	715 dload_1 (3, 4)
	716 aload_0 (3, 4)
	717 getfield (3, 4)
	718 org/apache/commons/math3/ode/nonstiff/DormandPrince853StepInterpolator.v:[[D (3, 4)
	720 iconst_2 (3, 4)
	721 aaload (3, 4)
	722 iload (3, 4)
	723 #23 (3, 4)
	724 daload (3, 4)
	725 dload (3, 4)
	726 #5 (3, 4)
	727 aload_0 (3, 4)
	728 getfield (3, 4)
	729 org/apache/commons/math3/ode/nonstiff/DormandPrince853StepInterpolator.v:[[D (3, 4)
	731 iconst_3 (3, 4)
	732 aaload (3, 4)
	733 iload (3, 4)
	734 #23 (3, 4)
	735 daload (3, 4)
	736 dload_1 (3, 4)
	737 aload_0 (3, 4)
	738 getfield (3, 4)
	739 org/apache/commons/math3/ode/nonstiff/DormandPrince853StepInterpolator.v:[[D (3, 4)
	741 iconst_4 (3, 4)
	742 aaload (3, 4)
	743 iload (3, 4)
	744 #23 (3, 4)
	745 daload (3, 4)
	746 dload (3, 4)
	747 #5 (3, 4)
	748 aload_0 (3, 4)
	749 getfield (3, 4)
	750 org/apache/commons/math3/ode/nonstiff/DormandPrince853StepInterpolator.v:[[D (3, 4)
	752 iconst_5 (3, 4)
	753 aaload (3, 4)
	754 iload (3, 4)
	755 #23 (3, 4)
	756 daload (3, 4)
	757 dload_1 (3, 4)
	758 aload_0 (3, 4)
	759 getfield (3, 4)
	760 org/apache/commons/math3/ode/nonstiff/DormandPrince853StepInterpolator.v:[[D (3, 4)
	762 bipush (3, 4)
	763 6 (3, 4)
	764 aaload (3, 4)
	765 iload (3, 4)
	766 #23 (3, 4)
	767 daload (3, 4)
	768 dmul (3, 4)
	769 dadd (3, 4)
	770 dmul (3, 4)
	771 dadd (3, 4)
	772 dmul (3, 4)
	773 dadd (3, 4)
	774 dmul (3, 4)
	775 dadd (3, 4)
	776 dmul (3, 4)
	777 dadd (3, 4)
	778 dmul (3, 4)
	779 dadd (3, 4)
	780 dmul (3, 4)
	781 dadd (3, 4)
	782 dastore (3, 4)
	783 aload_0 (3, 4)
	784 getfield (3, 4)
	785 org/apache/commons/math3/ode/nonstiff/DormandPrince853StepInterpolator.interpolatedDerivatives:[D (3, 4)
	787 iload (3, 4)
	788 #23 (3, 4)
	789 aload_0 (3, 4)
	790 getfield (3, 4)
	791 org/apache/commons/math3/ode/nonstiff/DormandPrince853StepInterpolator.v:[[D (3, 4)
	793 iconst_0 (3, 4)
	794 aaload (3, 4)
	795 iload (3, 4)
	796 #23 (3, 4)
	797 daload (3, 4)
	798 dload (3, 4)
	799 #11 (3, 4)
	800 aload_0 (3, 4)
	801 getfield (3, 4)
	802 org/apache/commons/math3/ode/nonstiff/DormandPrince853StepInterpolator.v:[[D (3, 4)
	804 iconst_1 (3, 4)
	805 aaload (3, 4)
	806 iload (3, 4)
	807 #23 (3, 4)
	808 daload (3, 4)
	809 dmul (3, 4)
	810 dadd (3, 4)
	811 dload (3, 4)
	812 #13 (3, 4)
	813 aload_0 (3, 4)
	814 getfield (3, 4)
	815 org/apache/commons/math3/ode/nonstiff/DormandPrince853StepInterpolator.v:[[D (3, 4)
	817 iconst_2 (3, 4)
	818 aaload (3, 4)
	819 iload (3, 4)
	820 #23 (3, 4)
	821 daload (3, 4)
	822 dmul (3, 4)
	823 dadd (3, 4)
	824 dload (3, 4)
	825 #15 (3, 4)
	826 aload_0 (3, 4)
	827 getfield (3, 4)
	828 org/apache/commons/math3/ode/nonstiff/DormandPrince853StepInterpolator.v:[[D (3, 4)
	830 iconst_3 (3, 4)
	831 aaload (3, 4)
	832 iload (3, 4)
	833 #23 (3, 4)
	834 daload (3, 4)
	835 dmul (3, 4)
	836 dadd (3, 4)
	837 dload (3, 4)
	838 #17 (3, 4)
	839 aload_0 (3, 4)
	840 getfield (3, 4)
	841 org/apache/commons/math3/ode/nonstiff/DormandPrince853StepInterpolator.v:[[D (3, 4)
	843 iconst_4 (3, 4)
	844 aaload (3, 4)
	845 iload (3, 4)
	846 #23 (3, 4)
	847 daload (3, 4)
	848 dmul (3, 4)
	849 dadd (3, 4)
	850 dload (3, 4)
	851 #19 (3, 4)
	852 aload_0 (3, 4)
	853 getfield (3, 4)
	854 org/apache/commons/math3/ode/nonstiff/DormandPrince853StepInterpolator.v:[[D (3, 4)
	856 iconst_5 (3, 4)
	857 aaload (3, 4)
	858 iload (3, 4)
	859 #23 (3, 4)
	860 daload (3, 4)
	861 dmul (3, 4)
	862 dadd (3, 4)
	863 dload (3, 4)
	864 #21 (3, 4)
	865 aload_0 (3, 4)
	866 getfield (3, 4)
	867 org/apache/commons/math3/ode/nonstiff/DormandPrince853StepInterpolator.v:[[D (3, 4)
	869 bipush (3, 4)
	870 6 (3, 4)
	871 aaload (3, 4)
	872 iload (3, 4)
	873 #23 (3, 4)
	874 daload (3, 4)
	875 dmul (3, 4)
	876 dadd (3, 4)
	877 dastore (3, 4)
	878 iinc (3, 4)
	879 #23 (3, 4)
	880 -89 (3, 4)
	881 goto (3, 4)
	882 -215 (3, 4)
	884 goto (3, 4)
	885 218 (3, 4)
	887 iconst_0 (3, 4)
	888 istore (3, 4)
	889 #23 (3, 4)
	890 iload (3, 4)
	891 #23 (3, 4)
	892 aload_0 (3, 4)
	893 getfield (3, 4)
	894 org/apache/commons/math3/ode/nonstiff/DormandPrince853StepInterpolator.interpolatedState:[D (3, 4)
	896 arraylength (3, 4)
	897 if_icmpge (3, 4)
	898 205 (3, 4)
	900 aload_0 (3, 4)
	901 getfield (3, 4)
	902 org/apache/commons/math3/ode/nonstiff/DormandPrince853StepInterpolator.interpolatedState:[D (3, 4)
	904 iload (3, 4)
	905 #23 (3, 4)
	906 aload_0 (3, 4)
	907 getfield (3, 4)
	908 org/apache/commons/math3/ode/nonstiff/DormandPrince853StepInterpolator.currentState:[D (3, 4)
	910 iload (3, 4)
	911 #23 (3, 4)
	912 daload (3, 4)
	913 dload_3 (3, 4)
	914 aload_0 (3, 4)
	915 getfield (3, 4)
	916 org/apache/commons/math3/ode/nonstiff/DormandPrince853StepInterpolator.v:[[D (3, 4)
	918 iconst_0 (3, 4)
	919 aaload (3, 4)
	920 iload (3, 4)
	921 #23 (3, 4)
	922 daload (3, 4)
	923 dload_1 (3, 4)
	924 aload_0 (3, 4)
	925 getfield (3, 4)
	926 org/apache/commons/math3/ode/nonstiff/DormandPrince853StepInterpolator.v:[[D (3, 4)
	928 iconst_1 (3, 4)
	929 aaload (3, 4)
	930 iload (3, 4)
	931 #23 (3, 4)
	932 daload (3, 4)
	933 dload_1 (3, 4)
	934 aload_0 (3, 4)
	935 getfield (3, 4)
	936 org/apache/commons/math3/ode/nonstiff/DormandPrince853StepInterpolator.v:[[D (3, 4)
	938 iconst_2 (3, 4)
	939 aaload (3, 4)
	940 iload (3, 4)
	941 #23 (3, 4)
	942 daload (3, 4)
	943 dload (3, 4)
	944 #5 (3, 4)
	945 aload_0 (3, 4)
	946 getfield (3, 4)
	947 org/apache/commons/math3/ode/nonstiff/DormandPrince853StepInterpolator.v:[[D (3, 4)
	949 iconst_3 (3, 4)
	950 aaload (3, 4)
	951 iload (3, 4)
	952 #23 (3, 4)
	953 daload (3, 4)
	954 dload_1 (3, 4)
	955 aload_0 (3, 4)
	956 getfield (3, 4)
	957 org/apache/commons/math3/ode/nonstiff/DormandPrince853StepInterpolator.v:[[D (3, 4)
	959 iconst_4 (3, 4)
	960 aaload (3, 4)
	961 iload (3, 4)
	962 #23 (3, 4)
	963 daload (3, 4)
	964 dload (3, 4)
	965 #5 (3, 4)
	966 aload_0 (3, 4)
	967 getfield (3, 4)
	968 org/apache/commons/math3/ode/nonstiff/DormandPrince853StepInterpolator.v:[[D (3, 4)
	970 iconst_5 (3, 4)
	971 aaload (3, 4)
	972 iload (3, 4)
	973 #23 (3, 4)
	974 daload (3, 4)
	975 dload_1 (3, 4)
	976 aload_0 (3, 4)
	977 getfield (3, 4)
	978 org/apache/commons/math3/ode/nonstiff/DormandPrince853StepInterpolator.v:[[D (3, 4)
	980 bipush (3, 4)
	981 6 (3, 4)
	982 aaload (3, 4)
	983 iload (3, 4)
	984 #23 (3, 4)
	985 daload (3, 4)
	986 dmul (3, 4)
	987 dadd (3, 4)
	988 dmul (3, 4)
	989 dadd (3, 4)
	990 dmul (3, 4)
	991 dadd (3, 4)
	992 dmul (3, 4)
	993 dadd (3, 4)
	994 dmul (3, 4)
	995 dadd (3, 4)
	996 dmul (3, 4)
	997 dsub (3, 4)
	998 dmul (3, 4)
	999 dsub (3, 4)
	1000 dastore (3, 4)
	1001 aload_0 (3, 4)
	1002 getfield (3, 4)
	1003 org/apache/commons/math3/ode/nonstiff/DormandPrince853StepInterpolator.interpolatedDerivatives:[D (3, 4)
	1005 iload (3, 4)
	1006 #23 (3, 4)
	1007 aload_0 (3, 4)
	1008 getfield (3, 4)
	1009 org/apache/commons/math3/ode/nonstiff/DormandPrince853StepInterpolator.v:[[D (3, 4)
	1011 iconst_0 (3, 4)
	1012 aaload (3, 4)
	1013 iload (3, 4)
	1014 #23 (3, 4)
	1015 daload (3, 4)
	1016 dload (3, 4)
	1017 #11 (3, 4)
	1018 aload_0 (3, 4)
	1019 getfield (3, 4)
	1020 org/apache/commons/math3/ode/nonstiff/DormandPrince853StepInterpolator.v:[[D (3, 4)
	1022 iconst_1 (3, 4)
	1023 aaload (3, 4)
	1024 iload (3, 4)
	1025 #23 (3, 4)
	1026 daload (3, 4)
	1027 dmul (3, 4)
	1028 dadd (3, 4)
	1029 dload (3, 4)
	1030 #13 (3, 4)
	1031 aload_0 (3, 4)
	1032 getfield (3, 4)
	1033 org/apache/commons/math3/ode/nonstiff/DormandPrince853StepInterpolator.v:[[D (3, 4)
	1035 iconst_2 (3, 4)
	1036 aaload (3, 4)
	1037 iload (3, 4)
	1038 #23 (3, 4)
	1039 daload (3, 4)
	1040 dmul (3, 4)
	1041 dadd (3, 4)
	1042 dload (3, 4)
	1043 #15 (3, 4)
	1044 aload_0 (3, 4)
	1045 getfield (3, 4)
	1046 org/apache/commons/math3/ode/nonstiff/DormandPrince853StepInterpolator.v:[[D (3, 4)
	1048 iconst_3 (3, 4)
	1049 aaload (3, 4)
	1050 iload (3, 4)
	1051 #23 (3, 4)
	1052 daload (3, 4)
	1053 dmul (3, 4)
	1054 dadd (3, 4)
	1055 dload (3, 4)
	1056 #17 (3, 4)
	1057 aload_0 (3, 4)
	1058 getfield (3, 4)
	1059 org/apache/commons/math3/ode/nonstiff/DormandPrince853StepInterpolator.v:[[D (3, 4)
	1061 iconst_4 (3, 4)
	1062 aaload (3, 4)
	1063 iload (3, 4)
	1064 #23 (3, 4)
	1065 daload (3, 4)
	1066 dmul (3, 4)
	1067 dadd (3, 4)
	1068 dload (3, 4)
	1069 #19 (3, 4)
	1070 aload_0 (3, 4)
	1071 getfield (3, 4)
	1072 org/apache/commons/math3/ode/nonstiff/DormandPrince853StepInterpolator.v:[[D (3, 4)
	1074 iconst_5 (3, 4)
	1075 aaload (3, 4)
	1076 iload (3, 4)
	1077 #23 (3, 4)
	1078 daload (3, 4)
	1079 dmul (3, 4)
	1080 dadd (3, 4)
	1081 dload (3, 4)
	1082 #21 (3, 4)
	1083 aload_0 (3, 4)
	1084 getfield (3, 4)
	1085 org/apache/commons/math3/ode/nonstiff/DormandPrince853StepInterpolator.v:[[D (3, 4)
	1087 bipush (3, 4)
	1088 6 (3, 4)
	1089 aaload (3, 4)
	1090 iload (3, 4)
	1091 #23 (3, 4)
	1092 daload (3, 4)
	1093 dmul (3, 4)
	1094 dadd (3, 4)
	1095 dastore (3, 4)
	1096 iinc (3, 4)
	1097 #23 (3, 4)
	1098 -89 (3, 4)
	1099 goto (3, 4)
	1100 -209 (3, 4)
	1102 return (0, 0)

Method: doFinalize
	0 aload_0 (1, 1)
	1 getfield (1, 1)
	2 org/apache/commons/math3/ode/nonstiff/DormandPrince853StepInterpolator.currentState:[D (1, 1)
	4 ifnonnull (1, 1)
	5 4 (1, 1)
	7 return (1, 1)
	8 aload_0 (0, 0)
	9 getfield (0, 0)
	10 org/apache/commons/math3/ode/nonstiff/DormandPrince853StepInterpolator.currentState:[D (0, 0)
	12 arraylength (0, 0)
	13 newarray (0, 0)
	14 7 (0, 0)
	15 astore_3 (0, 0)
	16 aload_0 (0, 0)
	17 invokevirtual (0, 0)
	18 org/apache/commons/math3/ode/nonstiff/DormandPrince853StepInterpolator.getGlobalPreviousTime:()D (0, 0)
	20 dstore (0, 0)
	21 #4 (0, 0)
	22 iconst_0 (1, 4)
	23 istore (1, 4)
	24 #6 (1, 4)
	25 iload (1, 4)
	26 #6 (1, 4)
	27 aload_0 (1, 4)
	28 getfield (1, 4)
	29 org/apache/commons/math3/ode/nonstiff/DormandPrince853StepInterpolator.currentState:[D (1, 4)
	31 arraylength (1, 4)
	32 if_icmpge (1, 4)
	33 160 (1, 4)
	35 ldc2_w (1, 4)
	36 0.0018737681664791894 (1, 4)
	38 aload_0 (1, 4)
	39 getfield (1, 4)
	40 org/apache/commons/math3/ode/nonstiff/DormandPrince853StepInterpolator.yDotK:[[D (1, 4)
	42 iconst_0 (1, 4)
	43 aaload (1, 4)
	44 iload (1, 4)
	45 #6 (1, 4)
	46 daload (1, 4)
	47 dmul (1, 4)
	48 ldc2_w (1, 4)
	49 -4.450312892752409 (1, 4)
	51 aload_0 (1, 4)
	52 getfield (1, 4)
	53 org/apache/commons/math3/ode/nonstiff/DormandPrince853StepInterpolator.yDotK:[[D (1, 4)
	55 iconst_5 (1, 4)
	56 aaload (1, 4)
	57 iload (1, 4)
	58 #6 (1, 4)
	59 daload (1, 4)
	60 dmul (1, 4)
	61 dadd (1, 4)
	62 ldc2_w (1, 4)
	63 -1.6380176890978755 (1, 4)
	65 aload_0 (1, 4)
	66 getfield (1, 4)
	67 org/apache/commons/math3/ode/nonstiff/DormandPrince853StepInterpolator.yDotK:[[D (1, 4)
	69 bipush (1, 4)
	70 6 (1, 4)
	71 aaload (1, 4)
	72 iload (1, 4)
	73 #6 (1, 4)
	74 daload (1, 4)
	75 dmul (1, 4)
	76 dadd (1, 4)
	77 ldc2_w (1, 4)
	78 5.554964922539782 (1, 4)
	80 aload_0 (1, 4)
	81 getfield (1, 4)
	82 org/apache/commons/math3/ode/nonstiff/DormandPrince853StepInterpolator.yDotK:[[D (1, 4)
	84 bipush (1, 4)
	85 7 (1, 4)
	86 aaload (1, 4)
	87 iload (1, 4)
	88 #6 (1, 4)
	89 daload (1, 4)
	90 dmul (1, 4)
	91 dadd (1, 4)
	92 ldc2_w (1, 4)
	93 -0.4353557902216363 (1, 4)
	95 aload_0 (1, 4)
	96 getfield (1, 4)
	97 org/apache/commons/math3/ode/nonstiff/DormandPrince853StepInterpolator.yDotK:[[D (1, 4)
	99 bipush (1, 4)
	100 8 (1, 4)
	101 aaload (1, 4)
	102 iload (1, 4)
	103 #6 (1, 4)
	104 daload (1, 4)
	105 dmul (1, 4)
	106 dadd (1, 4)
	107 ldc2_w (1, 4)
	108 0.30545274794128174 (1, 4)
	110 aload_0 (1, 4)
	111 getfield (1, 4)
	112 org/apache/commons/math3/ode/nonstiff/DormandPrince853StepInterpolator.yDotK:[[D (1, 4)
	114 bipush (1, 4)
	115 9 (1, 4)
	116 aaload (1, 4)
	117 iload (1, 4)
	118 #6 (1, 4)
	119 daload (1, 4)
	120 dmul (1, 4)
	121 dadd (1, 4)
	122 ldc2_w (1, 4)
	123 -0.19316434850839564 (1, 4)
	125 aload_0 (1, 4)
	126 getfield (1, 4)
	127 org/apache/commons/math3/ode/nonstiff/DormandPrince853StepInterpolator.yDotK:[[D (1, 4)
	129 bipush (1, 4)
	130 10 (1, 4)
	131 aaload (1, 4)
	132 iload (1, 4)
	133 #6 (1, 4)
	134 daload (1, 4)
	135 dmul (1, 4)
	136 dadd (1, 4)
	137 ldc2_w (1, 4)
	138 -0.03714271806722689 (1, 4)
	140 aload_0 (1, 4)
	141 getfield (1, 4)
	142 org/apache/commons/math3/ode/nonstiff/DormandPrince853StepInterpolator.yDotK:[[D (1, 4)
	144 bipush (1, 4)
	145 11 (1, 4)
	146 aaload (1, 4)
	147 iload (1, 4)
	148 #6 (1, 4)
	149 daload (1, 4)
	150 dmul (1, 4)
	151 dadd (1, 4)
	152 ldc2_w (1, 4)
	153 -0.008298 (1, 4)
	155 aload_0 (1, 4)
	156 getfield (1, 4)
	157 org/apache/commons/math3/ode/nonstiff/DormandPrince853StepInterpolator.yDotK:[[D (1, 4)
	159 bipush (1, 4)
	160 12 (1, 4)
	161 aaload (1, 4)
	162 iload (1, 4)
	163 #6 (1, 4)
	164 daload (1, 4)
	165 dmul (1, 4)
	166 dadd (1, 4)
	167 dstore_1 (1, 4)
	168 aload_3 (1, 4)
	169 iload (1, 4)
	170 #6 (1, 4)
	171 aload_0 (1, 4)
	172 getfield (1, 4)
	173 org/apache/commons/math3/ode/nonstiff/DormandPrince853StepInterpolator.currentState:[D (1, 4)
	175 iload (1, 4)
	176 #6 (1, 4)
	177 daload (1, 4)
	178 aload_0 (1, 4)
	179 getfield (1, 4)
	180 org/apache/commons/math3/ode/nonstiff/DormandPrince853StepInterpolator.h:D (1, 4)
	182 dload_1 (1, 4)
	183 dmul (1, 4)
	184 dadd (1, 4)
	185 dastore (1, 4)
	186 iinc (1, 4)
	187 #6 (1, 4)
	188 -89 (1, 4)
	189 goto (1, 4)
	190 -164 (1, 4)
	192 aload_0 (0, 0)
	193 getfield (0, 0)
	194 org/apache/commons/math3/ode/nonstiff/DormandPrince853StepInterpolator.integrator:Lorg/apache/commons/math3/ode/AbstractIntegrator; (0, 0)
	196 dload (0, 0)
	197 #4 (0, 0)
	198 ldc2_w (0, 0)
	199 0.1 (0, 0)
	201 aload_0 (0, 0)
	202 getfield (0, 0)
	203 org/apache/commons/math3/ode/nonstiff/DormandPrince853StepInterpolator.h:D (0, 0)
	205 dmul (0, 0)
	206 dadd (0, 0)
	207 aload_3 (0, 0)
	208 aload_0 (0, 0)
	209 getfield (0, 0)
	210 org/apache/commons/math3/ode/nonstiff/DormandPrince853StepInterpolator.yDotKLast:[[D (0, 0)
	212 iconst_0 (0, 0)
	213 aaload (0, 0)
	214 invokevirtual (0, 0)
	215 org/apache/commons/math3/ode/AbstractIntegrator.computeDerivatives:(D[D[D)V (0, 0)
	217 iconst_0 (1, 4)
	218 istore (1, 4)
	219 #6 (1, 4)
	220 iload (1, 4)
	221 #6 (1, 4)
	222 aload_0 (1, 4)
	223 getfield (1, 4)
	224 org/apache/commons/math3/ode/nonstiff/DormandPrince853StepInterpolator.currentState:[D (1, 4)
	226 arraylength (1, 4)
	227 if_icmpge (1, 4)
	228 174 (1, 4)
	230 ldc2_w (1, 4)
	231 -0.022459085953066622 (1, 4)
	233 aload_0 (1, 4)
	234 getfield (1, 4)
	235 org/apache/commons/math3/ode/nonstiff/DormandPrince853StepInterpolator.yDotK:[[D (1, 4)
	237 iconst_0 (1, 4)
	238 aaload (1, 4)
	239 iload (1, 4)
	240 #6 (1, 4)
	241 daload (1, 4)
	242 dmul (1, 4)
	243 ldc2_w (1, 4)
	244 -4.422011983080043 (1, 4)
	246 aload_0 (1, 4)
	247 getfield (1, 4)
	248 org/apache/commons/math3/ode/nonstiff/DormandPrince853StepInterpolator.yDotK:[[D (1, 4)
	250 iconst_5 (1, 4)
	251 aaload (1, 4)
	252 iload (1, 4)
	253 #6 (1, 4)
	254 daload (1, 4)
	255 dmul (1, 4)
	256 dadd (1, 4)
	257 ldc2_w (1, 4)
	258 -1.8379759110070617 (1, 4)
	260 aload_0 (1, 4)
	261 getfield (1, 4)
	262 org/apache/commons/math3/ode/nonstiff/DormandPrince853StepInterpolator.yDotK:[[D (1, 4)
	264 bipush (1, 4)
	265 6 (1, 4)
	266 aaload (1, 4)
	267 iload (1, 4)
	268 #6 (1, 4)
	269 daload (1, 4)
	270 dmul (1, 4)
	271 dadd (1, 4)
	272 ldc2_w (1, 4)
	273 5.746280211439194 (1, 4)
	275 aload_0 (1, 4)
	276 getfield (1, 4)
	277 org/apache/commons/math3/ode/nonstiff/DormandPrince853StepInterpolator.yDotK:[[D (1, 4)
	279 bipush (1, 4)
	280 7 (1, 4)
	281 aaload (1, 4)
	282 iload (1, 4)
	283 #6 (1, 4)
	284 daload (1, 4)
	285 dmul (1, 4)
	286 dadd (1, 4)
	287 ldc2_w (1, 4)
	288 -0.3111643669578199 (1, 4)
	290 aload_0 (1, 4)
	291 getfield (1, 4)
	292 org/apache/commons/math3/ode/nonstiff/DormandPrince853StepInterpolator.yDotK:[[D (1, 4)
	294 bipush (1, 4)
	295 8 (1, 4)
	296 aaload (1, 4)
	297 iload (1, 4)
	298 #6 (1, 4)
	299 daload (1, 4)
	300 dmul (1, 4)
	301 dadd (1, 4)
	302 ldc2_w (1, 4)
	303 0.1521609496625161 (1, 4)
	305 aload_0 (1, 4)
	306 getfield (1, 4)
	307 org/apache/commons/math3/ode/nonstiff/DormandPrince853StepInterpolator.yDotK:[[D (1, 4)
	309 bipush (1, 4)
	310 9 (1, 4)
	311 aaload (1, 4)
	312 iload (1, 4)
	313 #6 (1, 4)
	314 daload (1, 4)
	315 dmul (1, 4)
	316 dadd (1, 4)
	317 ldc2_w (1, 4)
	318 -0.2014737481327276 (1, 4)
	320 aload_0 (1, 4)
	321 getfield (1, 4)
	322 org/apache/commons/math3/ode/nonstiff/DormandPrince853StepInterpolator.yDotK:[[D (1, 4)
	324 bipush (1, 4)
	325 10 (1, 4)
	326 aaload (1, 4)
	327 iload (1, 4)
	328 #6 (1, 4)
	329 daload (1, 4)
	330 dmul (1, 4)
	331 dadd (1, 4)
	332 ldc2_w (1, 4)
	333 -0.04432804463693693 (1, 4)
	335 aload_0 (1, 4)
	336 getfield (1, 4)
	337 org/apache/commons/math3/ode/nonstiff/DormandPrince853StepInterpolator.yDotK:[[D (1, 4)
	339 bipush (1, 4)
	340 11 (1, 4)
	341 aaload (1, 4)
	342 iload (1, 4)
	343 #6 (1, 4)
	344 daload (1, 4)
	345 dmul (1, 4)
	346 dadd (1, 4)
	347 ldc2_w (1, 4)
	348 -0.00034046500868740456 (1, 4)
	350 aload_0 (1, 4)
	351 getfield (1, 4)
	352 org/apache/commons/math3/ode/nonstiff/DormandPrince853StepInterpolator.yDotK:[[D (1, 4)
	354 bipush (1, 4)
	355 12 (1, 4)
	356 aaload (1, 4)
	357 iload (1, 4)
	358 #6 (1, 4)
	359 daload (1, 4)
	360 dmul (1, 4)
	361 dadd (1, 4)
	362 ldc2_w (1, 4)
	363 0.1413124436746325 (1, 4)
	365 aload_0 (1, 4)
	366 getfield (1, 4)
	367 org/apache/commons/math3/ode/nonstiff/DormandPrince853StepInterpolator.yDotKLast:[[D (1, 4)
	369 iconst_0 (1, 4)
	370 aaload (1, 4)
	371 iload (1, 4)
	372 #6 (1, 4)
	373 daload (1, 4)
	374 dmul (1, 4)
	375 dadd (1, 4)
	376 dstore_1 (1, 4)
	377 aload_3 (1, 4)
	378 iload (1, 4)
	379 #6 (1, 4)
	380 aload_0 (1, 4)
	381 getfield (1, 4)
	382 org/apache/commons/math3/ode/nonstiff/DormandPrince853StepInterpolator.currentState:[D (1, 4)
	384 iload (1, 4)
	385 #6 (1, 4)
	386 daload (1, 4)
	387 aload_0 (1, 4)
	388 getfield (1, 4)
	389 org/apache/commons/math3/ode/nonstiff/DormandPrince853StepInterpolator.h:D (1, 4)
	391 dload_1 (1, 4)
	392 dmul (1, 4)
	393 dadd (1, 4)
	394 dastore (1, 4)
	395 iinc (1, 4)
	396 #6 (1, 4)
	397 -89 (1, 4)
	398 goto (1, 4)
	399 -178 (1, 4)
	401 aload_0 (0, 0)
	402 getfield (0, 0)
	403 org/apache/commons/math3/ode/nonstiff/DormandPrince853StepInterpolator.integrator:Lorg/apache/commons/math3/ode/AbstractIntegrator; (0, 0)
	405 dload (0, 0)
	406 #4 (0, 0)
	407 ldc2_w (0, 0)
	408 0.2 (0, 0)
	410 aload_0 (0, 0)
	411 getfield (0, 0)
	412 org/apache/commons/math3/ode/nonstiff/DormandPrince853StepInterpolator.h:D (0, 0)
	414 dmul (0, 0)
	415 dadd (0, 0)
	416 aload_3 (0, 0)
	417 aload_0 (0, 0)
	418 getfield (0, 0)
	419 org/apache/commons/math3/ode/nonstiff/DormandPrince853StepInterpolator.yDotKLast:[[D (0, 0)
	421 iconst_1 (0, 0)
	422 aaload (0, 0)
	423 invokevirtual (0, 0)
	424 org/apache/commons/math3/ode/AbstractIntegrator.computeDerivatives:(D[D[D)V (0, 0)
	426 iconst_0 (1, 4)
	427 istore (1, 4)
	428 #6 (1, 4)
	429 iload (1, 4)
	430 #6 (1, 4)
	431 aload_0 (1, 4)
	432 getfield (1, 4)
	433 org/apache/commons/math3/ode/nonstiff/DormandPrince853StepInterpolator.currentState:[D (1, 4)
	435 arraylength (1, 4)
	436 if_icmpge (1, 4)
	437 188 (1, 4)
	439 ldc2_w (1, 4)
	440 -0.4831900357003607 (1, 4)
	442 aload_0 (1, 4)
	443 getfield (1, 4)
	444 org/apache/commons/math3/ode/nonstiff/DormandPrince853StepInterpolator.yDotK:[[D (1, 4)
	446 iconst_0 (1, 4)
	447 aaload (1, 4)
	448 iload (1, 4)
	449 #6 (1, 4)
	450 daload (1, 4)
	451 dmul (1, 4)
	452 ldc2_w (1, 4)
	453 -9.147934308113573 (1, 4)
	455 aload_0 (1, 4)
	456 getfield (1, 4)
	457 org/apache/commons/math3/ode/nonstiff/DormandPrince853StepInterpolator.yDotK:[[D (1, 4)
	459 iconst_5 (1, 4)
	460 aaload (1, 4)
	461 iload (1, 4)
	462 #6 (1, 4)
	463 daload (1, 4)
	464 dmul (1, 4)
	465 dadd (1, 4)
	466 ldc2_w (1, 4)
	467 5.791903296748099 (1, 4)
	469 aload_0 (1, 4)
	470 getfield (1, 4)
	471 org/apache/commons/math3/ode/nonstiff/DormandPrince853StepInterpolator.yDotK:[[D (1, 4)
	473 bipush (1, 4)
	474 6 (1, 4)
	475 aaload (1, 4)
	476 iload (1, 4)
	477 #6 (1, 4)
	478 daload (1, 4)
	479 dmul (1, 4)
	480 dadd (1, 4)
	481 ldc2_w (1, 4)
	482 9.870193778407696 (1, 4)
	484 aload_0 (1, 4)
	485 getfield (1, 4)
	486 org/apache/commons/math3/ode/nonstiff/DormandPrince853StepInterpolator.yDotK:[[D (1, 4)
	488 bipush (1, 4)
	489 7 (1, 4)
	490 aaload (1, 4)
	491 iload (1, 4)
	492 #6 (1, 4)
	493 daload (1, 4)
	494 dmul (1, 4)
	495 dadd (1, 4)
	496 ldc2_w (1, 4)
	497 0.04556282049746119 (1, 4)
	499 aload_0 (1, 4)
	500 getfield (1, 4)
	501 org/apache/commons/math3/ode/nonstiff/DormandPrince853StepInterpolator.yDotK:[[D (1, 4)
	503 bipush (1, 4)
	504 8 (1, 4)
	505 aaload (1, 4)
	506 iload (1, 4)
	507 #6 (1, 4)
	508 daload (1, 4)
	509 dmul (1, 4)
	510 dadd (1, 4)
	511 ldc2_w (1, 4)
	512 0.1521609496625161 (1, 4)
	514 aload_0 (1, 4)
	515 getfield (1, 4)
	516 org/apache/commons/math3/ode/nonstiff/DormandPrince853StepInterpolator.yDotK:[[D (1, 4)
	518 bipush (1, 4)
	519 9 (1, 4)
	520 aaload (1, 4)
	521 iload (1, 4)
	522 #6 (1, 4)
	523 daload (1, 4)
	524 dmul (1, 4)
	525 dadd (1, 4)
	526 ldc2_w (1, 4)
	527 -0.20136540080403034 (1, 4)
	529 aload_0 (1, 4)
	530 getfield (1, 4)
	531 org/apache/commons/math3/ode/nonstiff/DormandPrince853StepInterpolator.yDotK:[[D (1, 4)
	533 bipush (1, 4)
	534 10 (1, 4)
	535 aaload (1, 4)
	536 iload (1, 4)
	537 #6 (1, 4)
	538 daload (1, 4)
	539 dmul (1, 4)
	540 dadd (1, 4)
	541 ldc2_w (1, 4)
	542 -0.04471061572777259 (1, 4)
	544 aload_0 (1, 4)
	545 getfield (1, 4)
	546 org/apache/commons/math3/ode/nonstiff/DormandPrince853StepInterpolator.yDotK:[[D (1, 4)
	548 bipush (1, 4)
	549 11 (1, 4)
	550 aaload (1, 4)
	551 iload (1, 4)
	552 #6 (1, 4)
	553 daload (1, 4)
	554 dmul (1, 4)
	555 dadd (1, 4)
	556 ldc2_w (1, 4)
	557 -0.0013990241651590145 (1, 4)
	559 aload_0 (1, 4)
	560 getfield (1, 4)
	561 org/apache/commons/math3/ode/nonstiff/DormandPrince853StepInterpolator.yDotK:[[D (1, 4)
	563 bipush (1, 4)
	564 12 (1, 4)
	565 aaload (1, 4)
	566 iload (1, 4)
	567 #6 (1, 4)
	568 daload (1, 4)
	569 dmul (1, 4)
	570 dadd (1, 4)
	571 ldc2_w (1, 4)
	572 2.9475147891527724 (1, 4)
	574 aload_0 (1, 4)
	575 getfield (1, 4)
	576 org/apache/commons/math3/ode/nonstiff/DormandPrince853StepInterpolator.yDotKLast:[[D (1, 4)
	578 iconst_0 (1, 4)
	579 aaload (1, 4)
	580 iload (1, 4)
	581 #6 (1, 4)
	582 daload (1, 4)
	583 dmul (1, 4)
	584 dadd (1, 4)
	585 ldc2_w (1, 4)
	586 -9.15095847217987 (1, 4)
	588 aload_0 (1, 4)
	589 getfield (1, 4)
	590 org/apache/commons/math3/ode/nonstiff/DormandPrince853StepInterpolator.yDotKLast:[[D (1, 4)
	592 iconst_1 (1, 4)
	593 aaload (1, 4)
	594 iload (1, 4)
	595 #6 (1, 4)
	596 daload (1, 4)
	597 dmul (1, 4)
	598 dadd (1, 4)
	599 dstore_1 (1, 4)
	600 aload_3 (1, 4)
	601 iload (1, 4)
	602 #6 (1, 4)
	603 aload_0 (1, 4)
	604 getfield (1, 4)
	605 org/apache/commons/math3/ode/nonstiff/DormandPrince853StepInterpolator.currentState:[D (1, 4)
	607 iload (1, 4)
	608 #6 (1, 4)
	609 daload (1, 4)
	610 aload_0 (1, 4)
	611 getfield (1, 4)
	612 org/apache/commons/math3/ode/nonstiff/DormandPrince853StepInterpolator.h:D (1, 4)
	614 dload_1 (1, 4)
	615 dmul (1, 4)
	616 dadd (1, 4)
	617 dastore (1, 4)
	618 iinc (1, 4)
	619 #6 (1, 4)
	620 -89 (1, 4)
	621 goto (1, 4)
	622 -192 (1, 4)
	624 aload_0 (0, 0)
	625 getfield (0, 0)
	626 org/apache/commons/math3/ode/nonstiff/DormandPrince853StepInterpolator.integrator:Lorg/apache/commons/math3/ode/AbstractIntegrator; (0, 0)
	628 dload (0, 0)
	629 #4 (0, 0)
	630 ldc2_w (0, 0)
	631 0.7777777777777778 (0, 0)
	633 aload_0 (0, 0)
	634 getfield (0, 0)
	635 org/apache/commons/math3/ode/nonstiff/DormandPrince853StepInterpolator.h:D (0, 0)
	637 dmul (0, 0)
	638 dadd (0, 0)
	639 aload_3 (0, 0)
	640 aload_0 (0, 0)
	641 getfield (0, 0)
	642 org/apache/commons/math3/ode/nonstiff/DormandPrince853StepInterpolator.yDotKLast:[[D (0, 0)
	644 iconst_2 (0, 0)
	645 aaload (0, 0)
	646 invokevirtual (0, 0)
	647 org/apache/commons/math3/ode/AbstractIntegrator.computeDerivatives:(D[D[D)V (0, 0)
	649 return (0, 0)

Method: writeExternal
	0 aload_0 (0, 0)
	1 invokevirtual (0, 0)
	2 org/apache/commons/math3/ode/nonstiff/DormandPrince853StepInterpolator.finalizeStep:()V (0, 0)
	4 goto (0, 0)
	5 24 (0, 0)
	7 astore_2 (0, 0)
	8 new (0, 0)
	9 java/io/IOException (0, 0)
	11 dup (0, 0)
	12 aload_2 (0, 0)
	13 invokevirtual (0, 0)
	14 org/apache/commons/math3/exception/MaxCountExceededException.getLocalizedMessage:()Ljava/lang/String; (0, 0)
	16 invokespecial (0, 0)
	17 java/io/IOException.<init>:(Ljava/lang/String;)V (0, 0)
	19 astore_3 (0, 0)
	20 aload_3 (0, 0)
	21 aload_2 (0, 0)
	22 invokevirtual (0, 0)
	23 java/io/IOException.initCause:(Ljava/lang/Throwable;)Ljava/lang/Throwable; (0, 0)
	25 pop (0, 0)
	26 aload_3 (0, 0)
	27 athrow (0, 0)
	28 aload_0 (0, 0)
	29 getfield (0, 0)
	30 org/apache/commons/math3/ode/nonstiff/DormandPrince853StepInterpolator.currentState:[D (0, 0)
	32 ifnonnull (0, 0)
	33 7 (0, 0)
	35 iconst_m1 (0, 0)
	36 goto (0, 0)
	37 8 (0, 0)
	39 aload_0 (0, 0)
	40 getfield (0, 0)
	41 org/apache/commons/math3/ode/nonstiff/DormandPrince853StepInterpolator.currentState:[D (0, 0)
	43 arraylength (0, 0)
	44 istore_2 (0, 0)
	45 aload_1 (0, 0)
	46 iload_2 (0, 0)
	47 invokeinterface (0, 0)
	48 java/io/ObjectOutput.writeDouble:(D)V (0, 0)
	50 0 (0, 0)
	52 iconst_0 (1, 4)
	53 istore_3 (1, 4)
	54 iload_3 (1, 4)
	55 iload_2 (1, 4)
	56 if_icmpge (1, 4)
	57 51 (1, 4)
	59 aload_1 (1, 4)
	60 aload_0 (1, 4)
	61 getfield (1, 4)
	62 org/apache/commons/math3/ode/nonstiff/DormandPrince853StepInterpolator.yDotKLast:[[D (1, 4)
	64 iconst_0 (1, 4)
	65 aaload (1, 4)
	66 iload_3 (1, 4)
	67 daload (1, 4)
	68 invokeinterface (1, 4)
	69 java/io/ObjectOutput.writeExternal:(Ljava/io/ObjectOutput;)V (1, 4)
	71 0 (1, 4)
	73 aload_1 (1, 4)
	74 aload_0 (1, 4)
	75 getfield (1, 4)
	76 org/apache/commons/math3/ode/nonstiff/DormandPrince853StepInterpolator.yDotKLast:[[D (1, 4)
	78 iconst_1 (1, 4)
	79 aaload (1, 4)
	80 iload_3 (1, 4)
	81 daload (1, 4)
	82 invokeinterface (1, 4)
	83 java/io/ObjectOutput.writeExternal:(Ljava/io/ObjectOutput;)V (1, 4)
	85 0 (1, 4)
	87 aload_1 (1, 4)
	88 aload_0 (1, 4)
	89 getfield (1, 4)
	90 org/apache/commons/math3/ode/nonstiff/DormandPrince853StepInterpolator.yDotKLast:[[D (1, 4)
	92 iconst_2 (1, 4)
	93 aaload (1, 4)
	94 iload_3 (1, 4)
	95 daload (1, 4)
	96 invokeinterface (1, 4)
	97 java/io/ObjectOutput.writeExternal:(Ljava/io/ObjectOutput;)V (1, 4)
	99 0 (1, 4)
	101 iinc (1, 4)
	102 #3 (1, 4)
	103 -89 (1, 4)
	104 goto (1, 4)
	105 -50 (1, 4)
	107 aload_0 (0, 0)
	108 aload_1 (0, 0)
	109 invokespecial (0, 0)
	110 org/apache/commons/math3/ode/nonstiff/RungeKuttaStepInterpolator.writeExternal:(Ljava/io/ObjectOutput;)V (0, 0)
	112 return (0, 0)

Method: readExternal
	0 aload_0 (0, 0)
	1 iconst_3 (0, 0)
	2 anewarray (0, 0)
	3 [D (0, 0)
	5 putfield (0, 0)
	6 org/apache/commons/math3/ode/nonstiff/DormandPrince853StepInterpolator.yDotKLast:[[D (0, 0)
	8 aload_1 (0, 0)
	9 invokeinterface (0, 0)
	10 java/io/ObjectInput.readDouble:()D (0, 0)
	12 0 (0, 0)
	14 istore_2 (0, 0)
	15 aload_0 (0, 0)
	16 getfield (0, 0)
	17 org/apache/commons/math3/ode/nonstiff/DormandPrince853StepInterpolator.yDotKLast:[[D (0, 0)
	19 iconst_0 (0, 0)
	20 iload_2 (0, 0)
	21 ifge (0, 0)
	22 7 (0, 0)
	24 aconst_null (0, 0)
	25 goto (0, 0)
	26 6 (0, 0)
	28 iload_2 (0, 0)
	29 newarray (0, 0)
	30 7 (0, 0)
	31 aastore (0, 0)
	32 aload_0 (0, 0)
	33 getfield (0, 0)
	34 org/apache/commons/math3/ode/nonstiff/DormandPrince853StepInterpolator.yDotKLast:[[D (0, 0)
	36 iconst_1 (0, 0)
	37 iload_2 (0, 0)
	38 ifge (0, 0)
	39 7 (0, 0)
	41 aconst_null (0, 0)
	42 goto (0, 0)
	43 6 (0, 0)
	45 iload_2 (0, 0)
	46 newarray (0, 0)
	47 7 (0, 0)
	48 aastore (0, 0)
	49 aload_0 (0, 0)
	50 getfield (0, 0)
	51 org/apache/commons/math3/ode/nonstiff/DormandPrince853StepInterpolator.yDotKLast:[[D (0, 0)
	53 iconst_2 (0, 0)
	54 iload_2 (0, 0)
	55 ifge (0, 0)
	56 7 (0, 0)
	58 aconst_null (0, 0)
	59 goto (0, 0)
	60 6 (0, 0)
	62 iload_2 (0, 0)
	63 newarray (0, 0)
	64 7 (0, 0)
	65 aastore (0, 0)
	66 iconst_0 (1, 4)
	67 istore_3 (1, 4)
	68 iload_3 (1, 4)
	69 iload_2 (1, 4)
	70 if_icmpge (1, 4)
	71 51 (1, 4)
	73 aload_0 (1, 4)
	74 getfield (1, 4)
	75 org/apache/commons/math3/ode/nonstiff/DormandPrince853StepInterpolator.yDotKLast:[[D (1, 4)
	77 iconst_0 (1, 4)
	78 aaload (1, 4)
	79 iload_3 (1, 4)
	80 aload_1 (1, 4)
	81 invokeinterface (1, 4)
	82 java/io/ObjectInput.readExternal:(Ljava/io/ObjectInput;)V (1, 4)
	84 0 (1, 4)
	86 dastore (1, 4)
	87 aload_0 (1, 4)
	88 getfield (1, 4)
	89 org/apache/commons/math3/ode/nonstiff/DormandPrince853StepInterpolator.yDotKLast:[[D (1, 4)
	91 iconst_1 (1, 4)
	92 aaload (1, 4)
	93 iload_3 (1, 4)
	94 aload_1 (1, 4)
	95 invokeinterface (1, 4)
	96 java/io/ObjectInput.readExternal:(Ljava/io/ObjectInput;)V (1, 4)
	98 0 (1, 4)
	100 dastore (1, 4)
	101 aload_0 (1, 4)
	102 getfield (1, 4)
	103 org/apache/commons/math3/ode/nonstiff/DormandPrince853StepInterpolator.yDotKLast:[[D (1, 4)
	105 iconst_2 (1, 4)
	106 aaload (1, 4)
	107 iload_3 (1, 4)
	108 aload_1 (1, 4)
	109 invokeinterface (1, 4)
	110 java/io/ObjectInput.readExternal:(Ljava/io/ObjectInput;)V (1, 4)
	112 0 (1, 4)
	114 dastore (1, 4)
	115 iinc (1, 4)
	116 #3 (1, 4)
	117 -89 (1, 4)
	118 goto (1, 4)
	119 -50 (1, 4)
	121 aload_0 (0, 0)
	122 aload_1 (0, 0)
	123 invokespecial (0, 0)
	124 org/apache/commons/math3/ode/nonstiff/RungeKuttaStepInterpolator.readExternal:(Ljava/io/ObjectInput;)V (0, 0)
	126 return (0, 0)

Method: <clinit>
	0 iconst_4 (0, 0)
	1 anewarray (0, 0)
	2 [D (0, 0)
	4 dup (0, 0)
	5 iconst_0 (0, 0)
	6 bipush (0, 0)
	7 12 (0, 0)
	8 newarray (0, 0)
	9 7 (0, 0)
	10 dup (0, 0)
	11 iconst_0 (0, 0)
	12 ldc2_w (0, 0)
	13 -8.428938276109013 (0, 0)
	15 dastore (0, 0)
	16 dup (0, 0)
	17 iconst_1 (0, 0)
	18 ldc2_w (0, 0)
	19 0.5667149535193777 (0, 0)
	21 dastore (0, 0)
	22 dup (0, 0)
	23 iconst_2 (0, 0)
	24 ldc2_w (0, 0)
	25 -3.0689499459498917 (0, 0)
	27 dastore (0, 0)
	28 dup (0, 0)
	29 iconst_3 (0, 0)
	30 ldc2_w (0, 0)
	31 2.38466765651207 (0, 0)
	33 dastore (0, 0)
	34 dup (0, 0)
	35 iconst_4 (0, 0)
	36 ldc2_w (0, 0)
	37 2.1170345824450285 (0, 0)
	39 dastore (0, 0)
	40 dup (0, 0)
	41 iconst_5 (0, 0)
	42 ldc2_w (0, 0)
	43 -0.871391583777973 (0, 0)
	45 dastore (0, 0)
	46 dup (0, 0)
	47 bipush (0, 0)
	48 6 (0, 0)
	49 ldc2_w (0, 0)
	50 2.2404374302607883 (0, 0)
	52 dastore (0, 0)
	53 dup (0, 0)
	54 bipush (0, 0)
	55 7 (0, 0)
	56 ldc2_w (0, 0)
	57 0.6315787787694688 (0, 0)
	59 dastore (0, 0)
	60 dup (0, 0)
	61 bipush (0, 0)
	62 8 (0, 0)
	63 ldc2_w (0, 0)
	64 -0.08899033645133331 (0, 0)
	66 dastore (0, 0)
	67 dup (0, 0)
	68 bipush (0, 0)
	69 9 (0, 0)
	70 ldc2_w (0, 0)
	71 18.148505520854727 (0, 0)
	73 dastore (0, 0)
	74 dup (0, 0)
	75 bipush (0, 0)
	76 10 (0, 0)
	77 ldc2_w (0, 0)
	78 -9.194632392478356 (0, 0)
	80 dastore (0, 0)
	81 dup (0, 0)
	82 bipush (0, 0)
	83 11 (0, 0)
	84 ldc2_w (0, 0)
	85 -4.436036387594894 (0, 0)
	87 dastore (0, 0)
	88 aastore (0, 0)
	89 dup (0, 0)
	90 iconst_1 (0, 0)
	91 bipush (0, 0)
	92 12 (0, 0)
	93 newarray (0, 0)
	94 7 (0, 0)
	95 dup (0, 0)
	96 iconst_0 (0, 0)
	97 ldc2_w (0, 0)
	98 10.427508642579134 (0, 0)
	100 dastore (0, 0)
	101 dup (0, 0)
	102 iconst_1 (0, 0)
	103 ldc2_w (0, 0)
	104 242.28349177525817 (0, 0)
	106 dastore (0, 0)
	107 dup (0, 0)
	108 iconst_2 (0, 0)
	109 ldc2_w (0, 0)
	110 165.20045171727028 (0, 0)
	112 dastore (0, 0)
	113 dup (0, 0)
	114 iconst_3 (0, 0)
	115 ldc2_w (0, 0)
	116 -374.5467547226902 (0, 0)
	118 dastore (0, 0)
	119 dup (0, 0)
	120 iconst_4 (0, 0)
	121 ldc2_w (0, 0)
	122 -22.113666853125302 (0, 0)
	124 dastore (0, 0)
	125 dup (0, 0)
	126 iconst_5 (0, 0)
	127 ldc2_w (0, 0)
	128 7.733432668472264 (0, 0)
	130 dastore (0, 0)
	131 dup (0, 0)
	132 bipush (0, 0)
	133 6 (0, 0)
	134 ldc2_w (0, 0)
	135 -30.674084731089398 (0, 0)
	137 dastore (0, 0)
	138 dup (0, 0)
	139 bipush (0, 0)
	140 7 (0, 0)
	141 ldc2_w (0, 0)
	142 -9.332130526430229 (0, 0)
	144 dastore (0, 0)
	145 dup (0, 0)
	146 bipush (0, 0)
	147 8 (0, 0)
	148 ldc2_w (0, 0)
	149 15.697238121770845 (0, 0)
	151 dastore (0, 0)
	152 dup (0, 0)
	153 bipush (0, 0)
	154 9 (0, 0)
	155 ldc2_w (0, 0)
	156 -31.139403219565178 (0, 0)
	158 dastore (0, 0)
	159 dup (0, 0)
	160 bipush (0, 0)
	161 10 (0, 0)
	162 ldc2_w (0, 0)
	163 -9.35292435884448 (0, 0)
	165 dastore (0, 0)
	166 dup (0, 0)
	167 bipush (0, 0)
	168 11 (0, 0)
	169 ldc2_w (0, 0)
	170 35.81684148639408 (0, 0)
	172 dastore (0, 0)
	173 aastore (0, 0)
	174 dup (0, 0)
	175 iconst_2 (0, 0)
	176 bipush (0, 0)
	177 12 (0, 0)
	178 newarray (0, 0)
	179 7 (0, 0)
	180 dup (0, 0)
	181 iconst_0 (0, 0)
	182 ldc2_w (0, 0)
	183 19.985053242002433 (0, 0)
	185 dastore (0, 0)
	186 dup (0, 0)
	187 iconst_1 (0, 0)
	188 ldc2_w (0, 0)
	189 -387.0373087493518 (0, 0)
	191 dastore (0, 0)
	192 dup (0, 0)
	193 iconst_2 (0, 0)
	194 ldc2_w (0, 0)
	195 -189.17813819516758 (0, 0)
	197 dastore (0, 0)
	198 dup (0, 0)
	199 iconst_3 (0, 0)
	200 ldc2_w (0, 0)
	201 527.8081592054236 (0, 0)
	203 dastore (0, 0)
	204 dup (0, 0)
	205 iconst_4 (0, 0)
	206 ldc2_w (0, 0)
	207 -11.573902539959631 (0, 0)
	209 dastore (0, 0)
	210 dup (0, 0)
	211 iconst_5 (0, 0)
	212 ldc2_w (0, 0)
	213 6.8812326946963 (0, 0)
	215 dastore (0, 0)
	216 dup (0, 0)
	217 bipush (0, 0)
	218 6 (0, 0)
	219 ldc2_w (0, 0)
	220 -1.0006050966910838 (0, 0)
	222 dastore (0, 0)
	223 dup (0, 0)
	224 bipush (0, 0)
	225 7 (0, 0)
	226 ldc2_w (0, 0)
	227 0.7777137798053443 (0, 0)
	229 dastore (0, 0)
	230 dup (0, 0)
	231 bipush (0, 0)
	232 8 (0, 0)
	233 ldc2_w (0, 0)
	234 -2.778205752353508 (0, 0)
	236 dastore (0, 0)
	237 dup (0, 0)
	238 bipush (0, 0)
	239 9 (0, 0)
	240 ldc2_w (0, 0)
	241 -60.19669523126412 (0, 0)
	243 dastore (0, 0)
	244 dup (0, 0)
	245 bipush (0, 0)
	246 10 (0, 0)
	247 ldc2_w (0, 0)
	248 84.32040550667716 (0, 0)
	250 dastore (0, 0)
	251 dup (0, 0)
	252 bipush (0, 0)
	253 11 (0, 0)
	254 ldc2_w (0, 0)
	255 11.99229113618279 (0, 0)
	257 dastore (0, 0)
	258 aastore (0, 0)
	259 dup (0, 0)
	260 iconst_3 (0, 0)
	261 bipush (0, 0)
	262 12 (0, 0)
	263 newarray (0, 0)
	264 7 (0, 0)
	265 dup (0, 0)
	266 iconst_0 (0, 0)
	267 ldc2_w (0, 0)
	268 -25.69393346270375 (0, 0)
	270 dastore (0, 0)
	271 dup (0, 0)
	272 iconst_1 (0, 0)
	273 ldc2_w (0, 0)
	274 -154.18974869023643 (0, 0)
	276 dastore (0, 0)
	277 dup (0, 0)
	278 iconst_2 (0, 0)
	279 ldc2_w (0, 0)
	280 -231.5293791760455 (0, 0)
	282 dastore (0, 0)
	283 dup (0, 0)
	284 iconst_3 (0, 0)
	285 ldc2_w (0, 0)
	286 357.6391179106141 (0, 0)
	288 dastore (0, 0)
	289 dup (0, 0)
	290 iconst_4 (0, 0)
	291 ldc2_w (0, 0)
	292 93.4053241836243 (0, 0)
	294 dastore (0, 0)
	295 dup (0, 0)
	296 iconst_5 (0, 0)
	297 ldc2_w (0, 0)
	298 -37.45832313645163 (0, 0)
	300 dastore (0, 0)
	301 dup (0, 0)
	302 bipush (0, 0)
	303 6 (0, 0)
	304 ldc2_w (0, 0)
	305 104.0996495089623 (0, 0)
	307 dastore (0, 0)
	308 dup (0, 0)
	309 bipush (0, 0)
	310 7 (0, 0)
	311 ldc2_w (0, 0)
	312 29.8402934266605 (0, 0)
	314 dastore (0, 0)
	315 dup (0, 0)
	316 bipush (0, 0)
	317 8 (0, 0)
	318 ldc2_w (0, 0)
	319 -43.53345659001114 (0, 0)
	321 dastore (0, 0)
	322 dup (0, 0)
	323 bipush (0, 0)
	324 9 (0, 0)
	325 ldc2_w (0, 0)
	326 96.32455395918828 (0, 0)
	328 dastore (0, 0)
	329 dup (0, 0)
	330 bipush (0, 0)
	331 10 (0, 0)
	332 ldc2_w (0, 0)
	333 -39.17726167561544 (0, 0)
	335 dastore (0, 0)
	336 dup (0, 0)
	337 bipush (0, 0)
	338 11 (0, 0)
	339 ldc2_w (0, 0)
	340 -149.72683625798564 (0, 0)
	342 dastore (0, 0)
	343 aastore (0, 0)
	344 putstatic (0, 0)
	345 org/apache/commons/math3/ode/nonstiff/DormandPrince853StepInterpolator.D:[[D (0, 0)
	347 return (0, 0)

