Method: <init>
	0 aload_0 (0, 0)
	1 ldc (0, 0)
	2 Dormand-Prince 8 (5, 3) (0, 0)
	3 iconst_1 (0, 0)
	4 getstatic (0, 0)
	5 org/apache/commons/math3/ode/nonstiff/DormandPrince853Integrator.STATIC_C:[D (0, 0)
	7 getstatic (0, 0)
	8 org/apache/commons/math3/ode/nonstiff/DormandPrince853Integrator.STATIC_A:[[D (0, 0)
	10 getstatic (0, 0)
	11 org/apache/commons/math3/ode/nonstiff/DormandPrince853Integrator.STATIC_B:[D (0, 0)
	13 new (0, 0)
	14 org/apache/commons/math3/ode/nonstiff/DormandPrince853StepInterpolator (0, 0)
	16 dup (0, 0)
	17 invokespecial (0, 0)
	18 org/apache/commons/math3/ode/nonstiff/DormandPrince853StepInterpolator.<init>:()V (0, 0)
	20 dload_1 (0, 0)
	21 dload_3 (0, 0)
	22 aload (0, 0)
	23 #5 (0, 0)
	24 aload (0, 0)
	25 #6 (0, 0)
	26 invokespecial (0, 0)
	27 org/apache/commons/math3/ode/nonstiff/EmbeddedRungeKuttaIntegrator.<init>:(Ljava/lang/String;Z[D[[D[DLorg/apache/commons/math3/ode/nonstiff/RungeKuttaStepInterpolator;DD[D[D)V (0, 0)
	29 return (0, 0)

Method: getOrder
	0 bipush (0, 0)
	1 8 (0, 0)
	2 ireturn (0, 0)

Method: estimateError
	0 dconst_0 (0, 0)
	1 dstore (0, 0)
	2 #6 (0, 0)
	3 dconst_0 (0, 0)
	4 dstore (0, 0)
	5 #8 (0, 0)
	6 iconst_0 (1, 4)
	7 istore (1, 4)
	8 #10 (1, 4)
	9 iload (1, 4)
	10 #10 (1, 4)
	11 aload_0 (1, 4)
	12 getfield (1, 4)
	13 org/apache/commons/math3/ode/nonstiff/DormandPrince853Integrator.mainSetDimension:I (1, 4)
	15 if_icmpge (1, 4)
	16 294 (1, 4)
	18 ldc2_w (1, 4)
	19 0.01312004499419488 (1, 4)
	21 aload_1 (1, 4)
	22 iconst_0 (1, 4)
	23 aaload (1, 4)
	24 iload (1, 4)
	25 #10 (1, 4)
	26 daload (1, 4)
	27 dmul (1, 4)
	28 ldc2_w (1, 4)
	29 -1.2251564463762044 (1, 4)
	31 aload_1 (1, 4)
	32 iconst_5 (1, 4)
	33 aaload (1, 4)
	34 iload (1, 4)
	35 #10 (1, 4)
	36 daload (1, 4)
	37 dmul (1, 4)
	38 dadd (1, 4)
	39 ldc2_w (1, 4)
	40 -0.4957589496572502 (1, 4)
	42 aload_1 (1, 4)
	43 bipush (1, 4)
	44 6 (1, 4)
	45 aaload (1, 4)
	46 iload (1, 4)
	47 #10 (1, 4)
	48 daload (1, 4)
	49 dmul (1, 4)
	50 dadd (1, 4)
	51 ldc2_w (1, 4)
	52 1.6643771824549864 (1, 4)
	54 aload_1 (1, 4)
	55 bipush (1, 4)
	56 7 (1, 4)
	57 aaload (1, 4)
	58 iload (1, 4)
	59 #10 (1, 4)
	60 daload (1, 4)
	61 dmul (1, 4)
	62 dadd (1, 4)
	63 ldc2_w (1, 4)
	64 -0.35032884874997366 (1, 4)
	66 aload_1 (1, 4)
	67 bipush (1, 4)
	68 8 (1, 4)
	69 aaload (1, 4)
	70 iload (1, 4)
	71 #10 (1, 4)
	72 daload (1, 4)
	73 dmul (1, 4)
	74 dadd (1, 4)
	75 ldc2_w (1, 4)
	76 0.3341791187130175 (1, 4)
	78 aload_1 (1, 4)
	79 bipush (1, 4)
	80 9 (1, 4)
	81 aaload (1, 4)
	82 iload (1, 4)
	83 #10 (1, 4)
	84 daload (1, 4)
	85 dmul (1, 4)
	86 dadd (1, 4)
	87 ldc2_w (1, 4)
	88 0.08192320648511571 (1, 4)
	90 aload_1 (1, 4)
	91 bipush (1, 4)
	92 10 (1, 4)
	93 aaload (1, 4)
	94 iload (1, 4)
	95 #10 (1, 4)
	96 daload (1, 4)
	97 dmul (1, 4)
	98 dadd (1, 4)
	99 ldc2_w (1, 4)
	100 -0.022355307863886294 (1, 4)
	102 aload_1 (1, 4)
	103 bipush (1, 4)
	104 11 (1, 4)
	105 aaload (1, 4)
	106 iload (1, 4)
	107 #10 (1, 4)
	108 daload (1, 4)
	109 dmul (1, 4)
	110 dadd (1, 4)
	111 dstore (1, 4)
	112 #11 (1, 4)
	113 ldc2_w (1, 4)
	114 -0.18980075407240762 (1, 4)
	116 aload_1 (1, 4)
	117 iconst_0 (1, 4)
	118 aaload (1, 4)
	119 iload (1, 4)
	120 #10 (1, 4)
	121 daload (1, 4)
	122 dmul (1, 4)
	123 ldc2_w (1, 4)
	124 4.450312892752409 (1, 4)
	126 aload_1 (1, 4)
	127 iconst_5 (1, 4)
	128 aaload (1, 4)
	129 iload (1, 4)
	130 #10 (1, 4)
	131 daload (1, 4)
	132 dmul (1, 4)
	133 dadd (1, 4)
	134 ldc2_w (1, 4)
	135 1.8915178993145003 (1, 4)
	137 aload_1 (1, 4)
	138 bipush (1, 4)
	139 6 (1, 4)
	140 aaload (1, 4)
	141 iload (1, 4)
	142 #10 (1, 4)
	143 daload (1, 4)
	144 dmul (1, 4)
	145 dadd (1, 4)
	146 ldc2_w (1, 4)
	147 -5.801203960010585 (1, 4)
	149 aload_1 (1, 4)
	150 bipush (1, 4)
	151 7 (1, 4)
	152 aaload (1, 4)
	153 iload (1, 4)
	154 #10 (1, 4)
	155 daload (1, 4)
	156 dmul (1, 4)
	157 dadd (1, 4)
	158 ldc2_w (1, 4)
	159 -0.42268232132379197 (1, 4)
	161 aload_1 (1, 4)
	162 bipush (1, 4)
	163 8 (1, 4)
	164 aaload (1, 4)
	165 iload (1, 4)
	166 #10 (1, 4)
	167 daload (1, 4)
	168 dmul (1, 4)
	169 dadd (1, 4)
	170 ldc2_w (1, 4)
	171 -0.1521609496625161 (1, 4)
	173 aload_1 (1, 4)
	174 bipush (1, 4)
	175 9 (1, 4)
	176 aaload (1, 4)
	177 iload (1, 4)
	178 #10 (1, 4)
	179 daload (1, 4)
	180 dmul (1, 4)
	181 dadd (1, 4)
	182 ldc2_w (1, 4)
	183 0.20136540080403034 (1, 4)
	185 aload_1 (1, 4)
	186 bipush (1, 4)
	187 10 (1, 4)
	188 aaload (1, 4)
	189 iload (1, 4)
	190 #10 (1, 4)
	191 daload (1, 4)
	192 dmul (1, 4)
	193 dadd (1, 4)
	194 ldc2_w (1, 4)
	195 0.022651792198360825 (1, 4)
	197 aload_1 (1, 4)
	198 bipush (1, 4)
	199 11 (1, 4)
	200 aaload (1, 4)
	201 iload (1, 4)
	202 #10 (1, 4)
	203 daload (1, 4)
	204 dmul (1, 4)
	205 dadd (1, 4)
	206 dstore (1, 4)
	207 #13 (1, 4)
	208 aload_2 (1, 4)
	209 iload (1, 4)
	210 #10 (1, 4)
	211 daload (1, 4)
	212 invokestatic (1, 4)
	213 org/apache/commons/math3/util/FastMath.abs:(D)D (1, 4)
	215 aload_3 (1, 4)
	216 iload (1, 4)
	217 #10 (1, 4)
	218 daload (1, 4)
	219 invokestatic (1, 4)
	220 org/apache/commons/math3/util/FastMath.abs:(D)D (1, 4)
	222 invokestatic (1, 4)
	223 org/apache/commons/math3/util/FastMath.max:(DD)D (1, 4)
	225 dstore (1, 4)
	226 #15 (1, 4)
	227 aload_0 (1, 4)
	228 getfield (1, 4)
	229 org/apache/commons/math3/ode/nonstiff/DormandPrince853Integrator.vecAbsoluteTolerance:[D (1, 4)
	231 ifnonnull (1, 4)
	232 18 (1, 4)
	234 aload_0 (1, 4)
	235 getfield (1, 4)
	236 org/apache/commons/math3/ode/nonstiff/DormandPrince853Integrator.scalAbsoluteTolerance:D (1, 4)
	238 aload_0 (1, 4)
	239 getfield (1, 4)
	240 org/apache/commons/math3/ode/nonstiff/DormandPrince853Integrator.scalRelativeTolerance:D (1, 4)
	242 dload (1, 4)
	243 #15 (1, 4)
	244 dmul (1, 4)
	245 dadd (1, 4)
	246 goto (1, 4)
	247 21 (1, 4)
	249 aload_0 (1, 4)
	250 getfield (1, 4)
	251 org/apache/commons/math3/ode/nonstiff/DormandPrince853Integrator.vecAbsoluteTolerance:[D (1, 4)
	253 iload (1, 4)
	254 #10 (1, 4)
	255 daload (1, 4)
	256 aload_0 (1, 4)
	257 getfield (1, 4)
	258 org/apache/commons/math3/ode/nonstiff/DormandPrince853Integrator.vecRelativeTolerance:[D (1, 4)
	260 iload (1, 4)
	261 #10 (1, 4)
	262 daload (1, 4)
	263 dload (1, 4)
	264 #15 (1, 4)
	265 dmul (1, 4)
	266 dadd (1, 4)
	267 dstore (1, 4)
	268 #17 (1, 4)
	269 dload (1, 4)
	270 #11 (1, 4)
	271 dload (1, 4)
	272 #17 (1, 4)
	273 ddiv (1, 4)
	274 dstore (1, 4)
	275 #19 (1, 4)
	276 dload (1, 4)
	277 #6 (1, 4)
	278 dload (1, 4)
	279 #19 (1, 4)
	280 dload (1, 4)
	281 #19 (1, 4)
	282 dmul (1, 4)
	283 dadd (1, 4)
	284 dstore (1, 4)
	285 #6 (1, 4)
	286 dload (1, 4)
	287 #13 (1, 4)
	288 dload (1, 4)
	289 #17 (1, 4)
	290 ddiv (1, 4)
	291 dstore (1, 4)
	292 #21 (1, 4)
	293 dload (1, 4)
	294 #8 (1, 4)
	295 dload (1, 4)
	296 #21 (1, 4)
	297 dload (1, 4)
	298 #21 (1, 4)
	299 dmul (1, 4)
	300 dadd (1, 4)
	301 dstore (1, 4)
	302 #8 (1, 4)
	303 iinc (1, 4)
	304 #10 (1, 4)
	305 -89 (1, 4)
	306 goto (1, 4)
	307 -297 (1, 4)
	309 dload (0, 0)
	310 #6 (0, 0)
	311 ldc2_w (0, 0)
	312 0.01 (0, 0)
	314 dload (0, 0)
	315 #8 (0, 0)
	316 dmul (0, 0)
	317 dadd (0, 0)
	318 dstore (0, 0)
	319 #10 (0, 0)
	320 dload (1, 1)
	321 #10 (1, 1)
	322 dconst_0 (1, 1)
	323 dcmpg (1, 1)
	324 ifgt (1, 1)
	325 6 (1, 1)
	327 dconst_1 (1, 1)
	328 dstore (1, 1)
	329 #10 (1, 1)
	330 dload (0, 0)
	331 #4 (0, 0)
	332 invokestatic (0, 0)
	333 org/apache/commons/math3/util/FastMath.abs:(D)D (0, 0)
	335 dload (0, 0)
	336 #6 (0, 0)
	337 dmul (0, 0)
	338 aload_0 (0, 0)
	339 getfield (0, 0)
	340 org/apache/commons/math3/ode/nonstiff/DormandPrince853Integrator.mainSetDimension:I (0, 0)
	342 i2d (0, 0)
	343 dload (0, 0)
	344 #10 (0, 0)
	345 dmul (0, 0)
	346 invokestatic (0, 0)
	347 org/apache/commons/math3/util/FastMath.sqrt:(D)D (0, 0)
	349 ddiv (0, 0)
	350 dreturn (0, 0)

Method: <clinit>
	0 bipush (0, 0)
	1 12 (0, 0)
	2 newarray (0, 0)
	3 7 (0, 0)
	4 dup (0, 0)
	5 iconst_0 (0, 0)
	6 ldc2_w (0, 0)
	7 12.0 (0, 0)
	9 ldc2_w (0, 0)
	10 2.0 (0, 0)
	12 ldc2_w (0, 0)
	13 6.0 (0, 0)
	15 invokestatic (0, 0)
	16 org/apache/commons/math3/util/FastMath.sqrt:(D)D (0, 0)
	18 dmul (0, 0)
	19 dsub (0, 0)
	20 ldc2_w (0, 0)
	21 135.0 (0, 0)
	23 ddiv (0, 0)
	24 dastore (0, 0)
	25 dup (0, 0)
	26 iconst_1 (0, 0)
	27 ldc2_w (0, 0)
	28 6.0 (0, 0)
	30 ldc2_w (0, 0)
	31 6.0 (0, 0)
	33 invokestatic (0, 0)
	34 org/apache/commons/math3/util/FastMath.sqrt:(D)D (0, 0)
	36 dsub (0, 0)
	37 ldc2_w (0, 0)
	38 45.0 (0, 0)
	40 ddiv (0, 0)
	41 dastore (0, 0)
	42 dup (0, 0)
	43 iconst_2 (0, 0)
	44 ldc2_w (0, 0)
	45 6.0 (0, 0)
	47 ldc2_w (0, 0)
	48 6.0 (0, 0)
	50 invokestatic (0, 0)
	51 org/apache/commons/math3/util/FastMath.sqrt:(D)D (0, 0)
	53 dsub (0, 0)
	54 ldc2_w (0, 0)
	55 30.0 (0, 0)
	57 ddiv (0, 0)
	58 dastore (0, 0)
	59 dup (0, 0)
	60 iconst_3 (0, 0)
	61 ldc2_w (0, 0)
	62 6.0 (0, 0)
	64 ldc2_w (0, 0)
	65 6.0 (0, 0)
	67 invokestatic (0, 0)
	68 org/apache/commons/math3/util/FastMath.sqrt:(D)D (0, 0)
	70 dadd (0, 0)
	71 ldc2_w (0, 0)
	72 30.0 (0, 0)
	74 ddiv (0, 0)
	75 dastore (0, 0)
	76 dup (0, 0)
	77 iconst_4 (0, 0)
	78 ldc2_w (0, 0)
	79 0.3333333333333333 (0, 0)
	81 dastore (0, 0)
	82 dup (0, 0)
	83 iconst_5 (0, 0)
	84 ldc2_w (0, 0)
	85 0.25 (0, 0)
	87 dastore (0, 0)
	88 dup (0, 0)
	89 bipush (0, 0)
	90 6 (0, 0)
	91 ldc2_w (0, 0)
	92 0.3076923076923077 (0, 0)
	94 dastore (0, 0)
	95 dup (0, 0)
	96 bipush (0, 0)
	97 7 (0, 0)
	98 ldc2_w (0, 0)
	99 0.6512820512820513 (0, 0)
	101 dastore (0, 0)
	102 dup (0, 0)
	103 bipush (0, 0)
	104 8 (0, 0)
	105 ldc2_w (0, 0)
	106 0.6 (0, 0)
	108 dastore (0, 0)
	109 dup (0, 0)
	110 bipush (0, 0)
	111 9 (0, 0)
	112 ldc2_w (0, 0)
	113 0.8571428571428571 (0, 0)
	115 dastore (0, 0)
	116 dup (0, 0)
	117 bipush (0, 0)
	118 10 (0, 0)
	119 dconst_1 (0, 0)
	120 dastore (0, 0)
	121 dup (0, 0)
	122 bipush (0, 0)
	123 11 (0, 0)
	124 dconst_1 (0, 0)
	125 dastore (0, 0)
	126 putstatic (0, 0)
	127 org/apache/commons/math3/ode/nonstiff/DormandPrince853Integrator.STATIC_C:[D (0, 0)
	129 bipush (0, 0)
	130 12 (0, 0)
	131 anewarray (0, 0)
	132 [D (0, 0)
	134 dup (0, 0)
	135 iconst_0 (0, 0)
	136 iconst_1 (0, 0)
	137 newarray (0, 0)
	138 7 (0, 0)
	139 dup (0, 0)
	140 iconst_0 (0, 0)
	141 ldc2_w (0, 0)
	142 12.0 (0, 0)
	144 ldc2_w (0, 0)
	145 2.0 (0, 0)
	147 ldc2_w (0, 0)
	148 6.0 (0, 0)
	150 invokestatic (0, 0)
	151 org/apache/commons/math3/util/FastMath.sqrt:(D)D (0, 0)
	153 dmul (0, 0)
	154 dsub (0, 0)
	155 ldc2_w (0, 0)
	156 135.0 (0, 0)
	158 ddiv (0, 0)
	159 dastore (0, 0)
	160 aastore (0, 0)
	161 dup (0, 0)
	162 iconst_1 (0, 0)
	163 iconst_2 (0, 0)
	164 newarray (0, 0)
	165 7 (0, 0)
	166 dup (0, 0)
	167 iconst_0 (0, 0)
	168 ldc2_w (0, 0)
	169 6.0 (0, 0)
	171 ldc2_w (0, 0)
	172 6.0 (0, 0)
	174 invokestatic (0, 0)
	175 org/apache/commons/math3/util/FastMath.sqrt:(D)D (0, 0)
	177 dsub (0, 0)
	178 ldc2_w (0, 0)
	179 180.0 (0, 0)
	181 ddiv (0, 0)
	182 dastore (0, 0)
	183 dup (0, 0)
	184 iconst_1 (0, 0)
	185 ldc2_w (0, 0)
	186 6.0 (0, 0)
	188 ldc2_w (0, 0)
	189 6.0 (0, 0)
	191 invokestatic (0, 0)
	192 org/apache/commons/math3/util/FastMath.sqrt:(D)D (0, 0)
	194 dsub (0, 0)
	195 ldc2_w (0, 0)
	196 60.0 (0, 0)
	198 ddiv (0, 0)
	199 dastore (0, 0)
	200 aastore (0, 0)
	201 dup (0, 0)
	202 iconst_2 (0, 0)
	203 iconst_3 (0, 0)
	204 newarray (0, 0)
	205 7 (0, 0)
	206 dup (0, 0)
	207 iconst_0 (0, 0)
	208 ldc2_w (0, 0)
	209 6.0 (0, 0)
	211 ldc2_w (0, 0)
	212 6.0 (0, 0)
	214 invokestatic (0, 0)
	215 org/apache/commons/math3/util/FastMath.sqrt:(D)D (0, 0)
	217 dsub (0, 0)
	218 ldc2_w (0, 0)
	219 120.0 (0, 0)
	221 ddiv (0, 0)
	222 dastore (0, 0)
	223 dup (0, 0)
	224 iconst_1 (0, 0)
	225 dconst_0 (0, 0)
	226 dastore (0, 0)
	227 dup (0, 0)
	228 iconst_2 (0, 0)
	229 ldc2_w (0, 0)
	230 6.0 (0, 0)
	232 ldc2_w (0, 0)
	233 6.0 (0, 0)
	235 invokestatic (0, 0)
	236 org/apache/commons/math3/util/FastMath.sqrt:(D)D (0, 0)
	238 dsub (0, 0)
	239 ldc2_w (0, 0)
	240 40.0 (0, 0)
	242 ddiv (0, 0)
	243 dastore (0, 0)
	244 aastore (0, 0)
	245 dup (0, 0)
	246 iconst_3 (0, 0)
	247 iconst_4 (0, 0)
	248 newarray (0, 0)
	249 7 (0, 0)
	250 dup (0, 0)
	251 iconst_0 (0, 0)
	252 ldc2_w (0, 0)
	253 462.0 (0, 0)
	255 ldc2_w (0, 0)
	256 107.0 (0, 0)
	258 ldc2_w (0, 0)
	259 6.0 (0, 0)
	261 invokestatic (0, 0)
	262 org/apache/commons/math3/util/FastMath.sqrt:(D)D (0, 0)
	264 dmul (0, 0)
	265 dadd (0, 0)
	266 ldc2_w (0, 0)
	267 3000.0 (0, 0)
	269 ddiv (0, 0)
	270 dastore (0, 0)
	271 dup (0, 0)
	272 iconst_1 (0, 0)
	273 dconst_0 (0, 0)
	274 dastore (0, 0)
	275 dup (0, 0)
	276 iconst_2 (0, 0)
	277 ldc2_w (0, 0)
	278 -402.0 (0, 0)
	280 ldc2_w (0, 0)
	281 197.0 (0, 0)
	283 ldc2_w (0, 0)
	284 6.0 (0, 0)
	286 invokestatic (0, 0)
	287 org/apache/commons/math3/util/FastMath.sqrt:(D)D (0, 0)
	289 dmul (0, 0)
	290 dsub (0, 0)
	291 ldc2_w (0, 0)
	292 1000.0 (0, 0)
	294 ddiv (0, 0)
	295 dastore (0, 0)
	296 dup (0, 0)
	297 iconst_3 (0, 0)
	298 ldc2_w (0, 0)
	299 168.0 (0, 0)
	301 ldc2_w (0, 0)
	302 73.0 (0, 0)
	304 ldc2_w (0, 0)
	305 6.0 (0, 0)
	307 invokestatic (0, 0)
	308 org/apache/commons/math3/util/FastMath.sqrt:(D)D (0, 0)
	310 dmul (0, 0)
	311 dadd (0, 0)
	312 ldc2_w (0, 0)
	313 375.0 (0, 0)
	315 ddiv (0, 0)
	316 dastore (0, 0)
	317 aastore (0, 0)
	318 dup (0, 0)
	319 iconst_4 (0, 0)
	320 iconst_5 (0, 0)
	321 newarray (0, 0)
	322 7 (0, 0)
	323 dup (0, 0)
	324 iconst_0 (0, 0)
	325 ldc2_w (0, 0)
	326 0.037037037037037035 (0, 0)
	328 dastore (0, 0)
	329 dup (0, 0)
	330 iconst_1 (0, 0)
	331 dconst_0 (0, 0)
	332 dastore (0, 0)
	333 dup (0, 0)
	334 iconst_2 (0, 0)
	335 dconst_0 (0, 0)
	336 dastore (0, 0)
	337 dup (0, 0)
	338 iconst_3 (0, 0)
	339 ldc2_w (0, 0)
	340 16.0 (0, 0)
	342 ldc2_w (0, 0)
	343 6.0 (0, 0)
	345 invokestatic (0, 0)
	346 org/apache/commons/math3/util/FastMath.sqrt:(D)D (0, 0)
	348 dadd (0, 0)
	349 ldc2_w (0, 0)
	350 108.0 (0, 0)
	352 ddiv (0, 0)
	353 dastore (0, 0)
	354 dup (0, 0)
	355 iconst_4 (0, 0)
	356 ldc2_w (0, 0)
	357 16.0 (0, 0)
	359 ldc2_w (0, 0)
	360 6.0 (0, 0)
	362 invokestatic (0, 0)
	363 org/apache/commons/math3/util/FastMath.sqrt:(D)D (0, 0)
	365 dsub (0, 0)
	366 ldc2_w (0, 0)
	367 108.0 (0, 0)
	369 ddiv (0, 0)
	370 dastore (0, 0)
	371 aastore (0, 0)
	372 dup (0, 0)
	373 iconst_5 (0, 0)
	374 bipush (0, 0)
	375 6 (0, 0)
	376 newarray (0, 0)
	377 7 (0, 0)
	378 dup (0, 0)
	379 iconst_0 (0, 0)
	380 ldc2_w (0, 0)
	381 0.037109375 (0, 0)
	383 dastore (0, 0)
	384 dup (0, 0)
	385 iconst_1 (0, 0)
	386 dconst_0 (0, 0)
	387 dastore (0, 0)
	388 dup (0, 0)
	389 iconst_2 (0, 0)
	390 dconst_0 (0, 0)
	391 dastore (0, 0)
	392 dup (0, 0)
	393 iconst_3 (0, 0)
	394 ldc2_w (0, 0)
	395 118.0 (0, 0)
	397 ldc2_w (0, 0)
	398 23.0 (0, 0)
	400 ldc2_w (0, 0)
	401 6.0 (0, 0)
	403 invokestatic (0, 0)
	404 org/apache/commons/math3/util/FastMath.sqrt:(D)D (0, 0)
	406 dmul (0, 0)
	407 dadd (0, 0)
	408 ldc2_w (0, 0)
	409 1024.0 (0, 0)
	411 ddiv (0, 0)
	412 dastore (0, 0)
	413 dup (0, 0)
	414 iconst_4 (0, 0)
	415 ldc2_w (0, 0)
	416 118.0 (0, 0)
	418 ldc2_w (0, 0)
	419 23.0 (0, 0)
	421 ldc2_w (0, 0)
	422 6.0 (0, 0)
	424 invokestatic (0, 0)
	425 org/apache/commons/math3/util/FastMath.sqrt:(D)D (0, 0)
	427 dmul (0, 0)
	428 dsub (0, 0)
	429 ldc2_w (0, 0)
	430 1024.0 (0, 0)
	432 ddiv (0, 0)
	433 dastore (0, 0)
	434 dup (0, 0)
	435 iconst_5 (0, 0)
	436 ldc2_w (0, 0)
	437 -0.017578125 (0, 0)
	439 dastore (0, 0)
	440 aastore (0, 0)
	441 dup (0, 0)
	442 bipush (0, 0)
	443 6 (0, 0)
	444 bipush (0, 0)
	445 7 (0, 0)
	446 newarray (0, 0)
	447 7 (0, 0)
	448 dup (0, 0)
	449 iconst_0 (0, 0)
	450 ldc2_w (0, 0)
	451 0.03709200011850479 (0, 0)
	453 dastore (0, 0)
	454 dup (0, 0)
	455 iconst_1 (0, 0)
	456 dconst_0 (0, 0)
	457 dastore (0, 0)
	458 dup (0, 0)
	459 iconst_2 (0, 0)
	460 dconst_0 (0, 0)
	461 dastore (0, 0)
	462 dup (0, 0)
	463 iconst_3 (0, 0)
	464 ldc2_w (0, 0)
	465 51544.0 (0, 0)
	467 ldc2_w (0, 0)
	468 4784.0 (0, 0)
	470 ldc2_w (0, 0)
	471 6.0 (0, 0)
	473 invokestatic (0, 0)
	474 org/apache/commons/math3/util/FastMath.sqrt:(D)D (0, 0)
	476 dmul (0, 0)
	477 dadd (0, 0)
	478 ldc2_w (0, 0)
	479 371293.0 (0, 0)
	481 ddiv (0, 0)
	482 dastore (0, 0)
	483 dup (0, 0)
	484 iconst_4 (0, 0)
	485 ldc2_w (0, 0)
	486 51544.0 (0, 0)
	488 ldc2_w (0, 0)
	489 4784.0 (0, 0)
	491 ldc2_w (0, 0)
	492 6.0 (0, 0)
	494 invokestatic (0, 0)
	495 org/apache/commons/math3/util/FastMath.sqrt:(D)D (0, 0)
	497 dmul (0, 0)
	498 dsub (0, 0)
	499 ldc2_w (0, 0)
	500 371293.0 (0, 0)
	502 ddiv (0, 0)
	503 dastore (0, 0)
	504 dup (0, 0)
	505 iconst_5 (0, 0)
	506 ldc2_w (0, 0)
	507 -0.015319437748624402 (0, 0)
	509 dastore (0, 0)
	510 dup (0, 0)
	511 bipush (0, 0)
	512 6 (0, 0)
	513 ldc2_w (0, 0)
	514 0.008273789163814023 (0, 0)
	516 dastore (0, 0)
	517 aastore (0, 0)
	518 dup (0, 0)
	519 bipush (0, 0)
	520 7 (0, 0)
	521 bipush (0, 0)
	522 8 (0, 0)
	523 newarray (0, 0)
	524 7 (0, 0)
	525 dup (0, 0)
	526 iconst_0 (0, 0)
	527 ldc2_w (0, 0)
	528 0.6241109587160757 (0, 0)
	530 dastore (0, 0)
	531 dup (0, 0)
	532 iconst_1 (0, 0)
	533 dconst_0 (0, 0)
	534 dastore (0, 0)
	535 dup (0, 0)
	536 iconst_2 (0, 0)
	537 dconst_0 (0, 0)
	538 dastore (0, 0)
	539 dup (0, 0)
	540 iconst_3 (0, 0)
	541 ldc2_w (0, 0)
	542 -1324889724104.0 (0, 0)
	544 ldc2_w (0, 0)
	545 318801444819.0 (0, 0)
	547 ldc2_w (0, 0)
	548 6.0 (0, 0)
	550 invokestatic (0, 0)
	551 org/apache/commons/math3/util/FastMath.sqrt:(D)D (0, 0)
	553 dmul (0, 0)
	554 dsub (0, 0)
	555 ldc2_w (0, 0)
	556 626556937500.0 (0, 0)
	558 ddiv (0, 0)
	559 dastore (0, 0)
	560 dup (0, 0)
	561 iconst_4 (0, 0)
	562 ldc2_w (0, 0)
	563 -1324889724104.0 (0, 0)
	565 ldc2_w (0, 0)
	566 318801444819.0 (0, 0)
	568 ldc2_w (0, 0)
	569 6.0 (0, 0)
	571 invokestatic (0, 0)
	572 org/apache/commons/math3/util/FastMath.sqrt:(D)D (0, 0)
	574 dmul (0, 0)
	575 dadd (0, 0)
	576 ldc2_w (0, 0)
	577 626556937500.0 (0, 0)
	579 ddiv (0, 0)
	580 dastore (0, 0)
	581 dup (0, 0)
	582 iconst_5 (0, 0)
	583 ldc2_w (0, 0)
	584 27.59209969944671 (0, 0)
	586 dastore (0, 0)
	587 dup (0, 0)
	588 bipush (0, 0)
	589 6 (0, 0)
	590 ldc2_w (0, 0)
	591 20.154067550477894 (0, 0)
	593 dastore (0, 0)
	594 dup (0, 0)
	595 bipush (0, 0)
	596 7 (0, 0)
	597 ldc2_w (0, 0)
	598 -43.48988418106996 (0, 0)
	600 dastore (0, 0)
	601 aastore (0, 0)
	602 dup (0, 0)
	603 bipush (0, 0)
	604 8 (0, 0)
	605 bipush (0, 0)
	606 9 (0, 0)
	607 newarray (0, 0)
	608 7 (0, 0)
	609 dup (0, 0)
	610 iconst_0 (0, 0)
	611 ldc2_w (0, 0)
	612 0.47766253643826434 (0, 0)
	614 dastore (0, 0)
	615 dup (0, 0)
	616 iconst_1 (0, 0)
	617 dconst_0 (0, 0)
	618 dastore (0, 0)
	619 dup (0, 0)
	620 iconst_2 (0, 0)
	621 dconst_0 (0, 0)
	622 dastore (0, 0)
	623 dup (0, 0)
	624 iconst_3 (0, 0)
	625 ldc2_w (0, 0)
	626 -4521408.0 (0, 0)
	628 ldc2_w (0, 0)
	629 1137963.0 (0, 0)
	631 ldc2_w (0, 0)
	632 6.0 (0, 0)
	634 invokestatic (0, 0)
	635 org/apache/commons/math3/util/FastMath.sqrt:(D)D (0, 0)
	637 dmul (0, 0)
	638 dsub (0, 0)
	639 ldc2_w (0, 0)
	640 2937500.0 (0, 0)
	642 ddiv (0, 0)
	643 dastore (0, 0)
	644 dup (0, 0)
	645 iconst_4 (0, 0)
	646 ldc2_w (0, 0)
	647 -4521408.0 (0, 0)
	649 ldc2_w (0, 0)
	650 1137963.0 (0, 0)
	652 ldc2_w (0, 0)
	653 6.0 (0, 0)
	655 invokestatic (0, 0)
	656 org/apache/commons/math3/util/FastMath.sqrt:(D)D (0, 0)
	658 dmul (0, 0)
	659 dadd (0, 0)
	660 ldc2_w (0, 0)
	661 2937500.0 (0, 0)
	663 ddiv (0, 0)
	664 dastore (0, 0)
	665 dup (0, 0)
	666 iconst_5 (0, 0)
	667 ldc2_w (0, 0)
	668 21.230051448181193 (0, 0)
	670 dastore (0, 0)
	671 dup (0, 0)
	672 bipush (0, 0)
	673 6 (0, 0)
	674 ldc2_w (0, 0)
	675 15.279233632882423 (0, 0)
	677 dastore (0, 0)
	678 dup (0, 0)
	679 bipush (0, 0)
	680 7 (0, 0)
	681 ldc2_w (0, 0)
	682 -33.28821096898486 (0, 0)
	684 dastore (0, 0)
	685 dup (0, 0)
	686 bipush (0, 0)
	687 8 (0, 0)
	688 ldc2_w (0, 0)
	689 -0.020331201708508627 (0, 0)
	691 dastore (0, 0)
	692 aastore (0, 0)
	693 dup (0, 0)
	694 bipush (0, 0)
	695 9 (0, 0)
	696 bipush (0, 0)
	697 10 (0, 0)
	698 newarray (0, 0)
	699 7 (0, 0)
	700 dup (0, 0)
	701 iconst_0 (0, 0)
	702 ldc2_w (0, 0)
	703 -0.9371424300859873 (0, 0)
	705 dastore (0, 0)
	706 dup (0, 0)
	707 iconst_1 (0, 0)
	708 dconst_0 (0, 0)
	709 dastore (0, 0)
	710 dup (0, 0)
	711 iconst_2 (0, 0)
	712 dconst_0 (0, 0)
	713 dastore (0, 0)
	714 dup (0, 0)
	715 iconst_3 (0, 0)
	716 ldc2_w (0, 0)
	717 354216.0 (0, 0)
	719 ldc2_w (0, 0)
	720 94326.0 (0, 0)
	722 ldc2_w (0, 0)
	723 6.0 (0, 0)
	725 invokestatic (0, 0)
	726 org/apache/commons/math3/util/FastMath.sqrt:(D)D (0, 0)
	728 dmul (0, 0)
	729 dadd (0, 0)
	730 ldc2_w (0, 0)
	731 112847.0 (0, 0)
	733 ddiv (0, 0)
	734 dastore (0, 0)
	735 dup (0, 0)
	736 iconst_4 (0, 0)
	737 ldc2_w (0, 0)
	738 354216.0 (0, 0)
	740 ldc2_w (0, 0)
	741 94326.0 (0, 0)
	743 ldc2_w (0, 0)
	744 6.0 (0, 0)
	746 invokestatic (0, 0)
	747 org/apache/commons/math3/util/FastMath.sqrt:(D)D (0, 0)
	749 dmul (0, 0)
	750 dsub (0, 0)
	751 ldc2_w (0, 0)
	752 112847.0 (0, 0)
	754 ddiv (0, 0)
	755 dastore (0, 0)
	756 dup (0, 0)
	757 iconst_5 (0, 0)
	758 ldc2_w (0, 0)
	759 -8.149787010746927 (0, 0)
	761 dastore (0, 0)
	762 dup (0, 0)
	763 bipush (0, 0)
	764 6 (0, 0)
	765 ldc2_w (0, 0)
	766 -18.52006565999696 (0, 0)
	768 dastore (0, 0)
	769 dup (0, 0)
	770 bipush (0, 0)
	771 7 (0, 0)
	772 ldc2_w (0, 0)
	773 22.739487099350505 (0, 0)
	775 dastore (0, 0)
	776 dup (0, 0)
	777 bipush (0, 0)
	778 8 (0, 0)
	779 ldc2_w (0, 0)
	780 2.4936055526796523 (0, 0)
	782 dastore (0, 0)
	783 dup (0, 0)
	784 bipush (0, 0)
	785 9 (0, 0)
	786 ldc2_w (0, 0)
	787 -3.0467644718982196 (0, 0)
	789 dastore (0, 0)
	790 aastore (0, 0)
	791 dup (0, 0)
	792 bipush (0, 0)
	793 10 (0, 0)
	794 bipush (0, 0)
	795 11 (0, 0)
	796 newarray (0, 0)
	797 7 (0, 0)
	798 dup (0, 0)
	799 iconst_0 (0, 0)
	800 ldc2_w (0, 0)
	801 2.273310147516538 (0, 0)
	803 dastore (0, 0)
	804 dup (0, 0)
	805 iconst_1 (0, 0)
	806 dconst_0 (0, 0)
	807 dastore (0, 0)
	808 dup (0, 0)
	809 iconst_2 (0, 0)
	810 dconst_0 (0, 0)
	811 dastore (0, 0)
	812 dup (0, 0)
	813 iconst_3 (0, 0)
	814 ldc2_w (0, 0)
	815 -3457480.0 (0, 0)
	817 ldc2_w (0, 0)
	818 960905.0 (0, 0)
	820 ldc2_w (0, 0)
	821 6.0 (0, 0)
	823 invokestatic (0, 0)
	824 org/apache/commons/math3/util/FastMath.sqrt:(D)D (0, 0)
	826 dmul (0, 0)
	827 dsub (0, 0)
	828 ldc2_w (0, 0)
	829 551636.0 (0, 0)
	831 ddiv (0, 0)
	832 dastore (0, 0)
	833 dup (0, 0)
	834 iconst_4 (0, 0)
	835 ldc2_w (0, 0)
	836 -3457480.0 (0, 0)
	838 ldc2_w (0, 0)
	839 960905.0 (0, 0)
	841 ldc2_w (0, 0)
	842 6.0 (0, 0)
	844 invokestatic (0, 0)
	845 org/apache/commons/math3/util/FastMath.sqrt:(D)D (0, 0)
	847 dmul (0, 0)
	848 dadd (0, 0)
	849 ldc2_w (0, 0)
	850 551636.0 (0, 0)
	852 ddiv (0, 0)
	853 dastore (0, 0)
	854 dup (0, 0)
	855 iconst_5 (0, 0)
	856 ldc2_w (0, 0)
	857 -17.9589318631188 (0, 0)
	859 dastore (0, 0)
	860 dup (0, 0)
	861 bipush (0, 0)
	862 6 (0, 0)
	863 ldc2_w (0, 0)
	864 27.94888452941996 (0, 0)
	866 dastore (0, 0)
	867 dup (0, 0)
	868 bipush (0, 0)
	869 7 (0, 0)
	870 ldc2_w (0, 0)
	871 -2.8589982771350235 (0, 0)
	873 dastore (0, 0)
	874 dup (0, 0)
	875 bipush (0, 0)
	876 8 (0, 0)
	877 ldc2_w (0, 0)
	878 -8.87285693353063 (0, 0)
	880 dastore (0, 0)
	881 dup (0, 0)
	882 bipush (0, 0)
	883 9 (0, 0)
	884 ldc2_w (0, 0)
	885 12.360567175794303 (0, 0)
	887 dastore (0, 0)
	888 dup (0, 0)
	889 bipush (0, 0)
	890 10 (0, 0)
	891 ldc2_w (0, 0)
	892 0.6433927460157636 (0, 0)
	894 dastore (0, 0)
	895 aastore (0, 0)
	896 dup (0, 0)
	897 bipush (0, 0)
	898 11 (0, 0)
	899 bipush (0, 0)
	900 12 (0, 0)
	901 newarray (0, 0)
	902 7 (0, 0)
	903 dup (0, 0)
	904 iconst_0 (0, 0)
	905 ldc2_w (0, 0)
	906 0.054293734116568765 (0, 0)
	908 dastore (0, 0)
	909 dup (0, 0)
	910 iconst_1 (0, 0)
	911 dconst_0 (0, 0)
	912 dastore (0, 0)
	913 dup (0, 0)
	914 iconst_2 (0, 0)
	915 dconst_0 (0, 0)
	916 dastore (0, 0)
	917 dup (0, 0)
	918 iconst_3 (0, 0)
	919 dconst_0 (0, 0)
	920 dastore (0, 0)
	921 dup (0, 0)
	922 iconst_4 (0, 0)
	923 dconst_0 (0, 0)
	924 dastore (0, 0)
	925 dup (0, 0)
	926 iconst_5 (0, 0)
	927 ldc2_w (0, 0)
	928 4.450312892752409 (0, 0)
	930 dastore (0, 0)
	931 dup (0, 0)
	932 bipush (0, 0)
	933 6 (0, 0)
	934 ldc2_w (0, 0)
	935 1.8915178993145003 (0, 0)
	937 dastore (0, 0)
	938 dup (0, 0)
	939 bipush (0, 0)
	940 7 (0, 0)
	941 ldc2_w (0, 0)
	942 -5.801203960010585 (0, 0)
	944 dastore (0, 0)
	945 dup (0, 0)
	946 bipush (0, 0)
	947 8 (0, 0)
	948 ldc2_w (0, 0)
	949 0.3111643669578199 (0, 0)
	951 dastore (0, 0)
	952 dup (0, 0)
	953 bipush (0, 0)
	954 9 (0, 0)
	955 ldc2_w (0, 0)
	956 -0.1521609496625161 (0, 0)
	958 dastore (0, 0)
	959 dup (0, 0)
	960 bipush (0, 0)
	961 10 (0, 0)
	962 ldc2_w (0, 0)
	963 0.20136540080403034 (0, 0)
	965 dastore (0, 0)
	966 dup (0, 0)
	967 bipush (0, 0)
	968 11 (0, 0)
	969 ldc2_w (0, 0)
	970 0.04471061572777259 (0, 0)
	972 dastore (0, 0)
	973 aastore (0, 0)
	974 putstatic (0, 0)
	975 org/apache/commons/math3/ode/nonstiff/DormandPrince853Integrator.STATIC_A:[[D (0, 0)
	977 bipush (0, 0)
	978 13 (0, 0)
	979 newarray (0, 0)
	980 7 (0, 0)
	981 dup (0, 0)
	982 iconst_0 (0, 0)
	983 ldc2_w (0, 0)
	984 0.054293734116568765 (0, 0)
	986 dastore (0, 0)
	987 dup (0, 0)
	988 iconst_1 (0, 0)
	989 dconst_0 (0, 0)
	990 dastore (0, 0)
	991 dup (0, 0)
	992 iconst_2 (0, 0)
	993 dconst_0 (0, 0)
	994 dastore (0, 0)
	995 dup (0, 0)
	996 iconst_3 (0, 0)
	997 dconst_0 (0, 0)
	998 dastore (0, 0)
	999 dup (0, 0)
	1000 iconst_4 (0, 0)
	1001 dconst_0 (0, 0)
	1002 dastore (0, 0)
	1003 dup (0, 0)
	1004 iconst_5 (0, 0)
	1005 ldc2_w (0, 0)
	1006 4.450312892752409 (0, 0)
	1008 dastore (0, 0)
	1009 dup (0, 0)
	1010 bipush (0, 0)
	1011 6 (0, 0)
	1012 ldc2_w (0, 0)
	1013 1.8915178993145003 (0, 0)
	1015 dastore (0, 0)
	1016 dup (0, 0)
	1017 bipush (0, 0)
	1018 7 (0, 0)
	1019 ldc2_w (0, 0)
	1020 -5.801203960010585 (0, 0)
	1022 dastore (0, 0)
	1023 dup (0, 0)
	1024 bipush (0, 0)
	1025 8 (0, 0)
	1026 ldc2_w (0, 0)
	1027 0.3111643669578199 (0, 0)
	1029 dastore (0, 0)
	1030 dup (0, 0)
	1031 bipush (0, 0)
	1032 9 (0, 0)
	1033 ldc2_w (0, 0)
	1034 -0.1521609496625161 (0, 0)
	1036 dastore (0, 0)
	1037 dup (0, 0)
	1038 bipush (0, 0)
	1039 10 (0, 0)
	1040 ldc2_w (0, 0)
	1041 0.20136540080403034 (0, 0)
	1043 dastore (0, 0)
	1044 dup (0, 0)
	1045 bipush (0, 0)
	1046 11 (0, 0)
	1047 ldc2_w (0, 0)
	1048 0.04471061572777259 (0, 0)
	1050 dastore (0, 0)
	1051 dup (0, 0)
	1052 bipush (0, 0)
	1053 12 (0, 0)
	1054 dconst_0 (0, 0)
	1055 dastore (0, 0)
	1056 putstatic (0, 0)
	1057 org/apache/commons/math3/ode/nonstiff/DormandPrince853Integrator.STATIC_B:[D (0, 0)
	1059 return (0, 0)

