Method: <init>
	0 aload_0 (0, 0)
	1 aload_1 (0, 0)
	2 invokespecial (0, 0)
	3 org/apache/commons/math3/ode/nonstiff/RungeKuttaStepInterpolator.<init>:(Lorg/apache/commons/math3/ode/nonstiff/RungeKuttaStepInterpolator;)V (0, 0)
	5 aload_1 (1, 1)
	6 getfield (1, 1)
	7 org/apache/commons/math3/ode/nonstiff/DormandPrince54StepInterpolator.v1:[D (1, 1)
	9 ifnonnull (1, 1)
	10 31 (1, 1)
	12 aload_0 (1, 1)
	13 aconst_null (1, 1)
	14 putfield (1, 1)
	15 org/apache/commons/math3/ode/nonstiff/DormandPrince54StepInterpolator.v1:[D (1, 1)
	17 aload_0 (1, 1)
	18 aconst_null (1, 1)
	19 putfield (1, 1)
	20 org/apache/commons/math3/ode/nonstiff/DormandPrince54StepInterpolator.v2:[D (1, 1)
	22 aload_0 (1, 1)
	23 aconst_null (1, 1)
	24 putfield (1, 1)
	25 org/apache/commons/math3/ode/nonstiff/DormandPrince54StepInterpolator.v3:[D (1, 1)
	27 aload_0 (1, 1)
	28 aconst_null (1, 1)
	29 putfield (1, 1)
	30 org/apache/commons/math3/ode/nonstiff/DormandPrince54StepInterpolator.v4:[D (1, 1)
	32 aload_0 (1, 1)
	33 iconst_0 (1, 1)
	34 putfield (1, 1)
	35 org/apache/commons/math3/ode/nonstiff/DormandPrince54StepInterpolator.vectorsInitialized:Z (1, 1)
	37 goto (1, 1)
	38 67 (1, 1)
	40 aload_0 (2, 2)
	41 aload_1 (2, 2)
	42 getfield (2, 2)
	43 org/apache/commons/math3/ode/nonstiff/DormandPrince54StepInterpolator.v1:[D (2, 2)
	45 invokevirtual (2, 2)
	46 [D.clone:()Ljava/lang/Object; (2, 2)
	48 checkcast (2, 2)
	49 [D (2, 2)
	51 putfield (2, 2)
	52 org/apache/commons/math3/ode/nonstiff/DormandPrince54StepInterpolator.v1:[D (2, 2)
	54 aload_0 (2, 2)
	55 aload_1 (2, 2)
	56 getfield (2, 2)
	57 org/apache/commons/math3/ode/nonstiff/DormandPrince54StepInterpolator.v2:[D (2, 2)
	59 invokevirtual (2, 2)
	60 [D.clone:()Ljava/lang/Object; (2, 2)
	62 checkcast (2, 2)
	63 [D (2, 2)
	65 putfield (2, 2)
	66 org/apache/commons/math3/ode/nonstiff/DormandPrince54StepInterpolator.v2:[D (2, 2)
	68 aload_0 (2, 2)
	69 aload_1 (2, 2)
	70 getfield (2, 2)
	71 org/apache/commons/math3/ode/nonstiff/DormandPrince54StepInterpolator.v3:[D (2, 2)
	73 invokevirtual (2, 2)
	74 [D.clone:()Ljava/lang/Object; (2, 2)
	76 checkcast (2, 2)
	77 [D (2, 2)
	79 putfield (2, 2)
	80 org/apache/commons/math3/ode/nonstiff/DormandPrince54StepInterpolator.v3:[D (2, 2)
	82 aload_0 (2, 2)
	83 aload_1 (2, 2)
	84 getfield (2, 2)
	85 org/apache/commons/math3/ode/nonstiff/DormandPrince54StepInterpolator.v4:[D (2, 2)
	87 invokevirtual (2, 2)
	88 [D.clone:()Ljava/lang/Object; (2, 2)
	90 checkcast (2, 2)
	91 [D (2, 2)
	93 putfield (2, 2)
	94 org/apache/commons/math3/ode/nonstiff/DormandPrince54StepInterpolator.v4:[D (2, 2)
	96 aload_0 (2, 2)
	97 aload_1 (2, 2)
	98 getfield (2, 2)
	99 org/apache/commons/math3/ode/nonstiff/DormandPrince54StepInterpolator.vectorsInitialized:Z (2, 2)
	101 putfield (2, 2)
	102 org/apache/commons/math3/ode/nonstiff/DormandPrince54StepInterpolator.vectorsInitialized:Z (2, 2)
	104 return (0, 0)

Method: doCopy
	0 new (0, 0)
	1 org/apache/commons/math3/ode/nonstiff/DormandPrince54StepInterpolator (0, 0)
	3 dup (0, 0)
	4 aload_0 (0, 0)
	5 invokespecial (0, 0)
	6 org/apache/commons/math3/ode/nonstiff/DormandPrince54StepInterpolator.<init>:(Lorg/apache/commons/math3/ode/nonstiff/DormandPrince54StepInterpolator;)V (0, 0)
	8 areturn (0, 0)

Method: reinitialize
	0 aload_0 (1, 4)
	1 aload_1 (1, 4)
	2 aload_2 (1, 4)
	3 aload_3 (1, 4)
	4 iload (1, 4)
	5 #4 (1, 4)
	6 aload (1, 4)
	7 #5 (1, 4)
	8 aload (1, 4)
	9 #6 (1, 4)
	10 invokespecial (1, 4)
	11 org/apache/commons/math3/ode/nonstiff/RungeKuttaStepInterpolator.reinitialize:(Lorg/apache/commons/math3/ode/AbstractIntegrator;[D[[DZLorg/apache/commons/math3/ode/EquationsMapper;[Lorg/apache/commons/math3/ode/EquationsMapper;)V (1, 4)
	13 aload_0 (1, 4)
	14 aconst_null (1, 4)
	15 putfield (1, 4)
	16 org/apache/commons/math3/ode/nonstiff/DormandPrince54StepInterpolator.v1:[D (1, 4)
	18 aload_0 (1, 4)
	19 aconst_null (1, 4)
	20 putfield (1, 4)
	21 org/apache/commons/math3/ode/nonstiff/DormandPrince54StepInterpolator.v2:[D (1, 4)
	23 aload_0 (1, 4)
	24 aconst_null (1, 4)
	25 putfield (1, 4)
	26 org/apache/commons/math3/ode/nonstiff/DormandPrince54StepInterpolator.v3:[D (1, 4)
	28 aload_0 (1, 4)
	29 aconst_null (1, 4)
	30 putfield (1, 4)
	31 org/apache/commons/math3/ode/nonstiff/DormandPrince54StepInterpolator.v4:[D (1, 4)
	33 aload_0 (1, 4)
	34 iconst_0 (1, 4)
	35 putfield (1, 4)
	36 org/apache/commons/math3/ode/nonstiff/DormandPrince54StepInterpolator.vectorsInitialized:Z (1, 4)
	38 return (0, 4)

Method: storeTime
	0 aload_0 (0, 0)
	1 dload_1 (0, 0)
	2 invokespecial (0, 0)
	3 org/apache/commons/math3/ode/nonstiff/RungeKuttaStepInterpolator.storeTime:(D)V (0, 0)
	5 aload_0 (0, 0)
	6 iconst_0 (0, 0)
	7 putfield (0, 0)
	8 org/apache/commons/math3/ode/nonstiff/DormandPrince54StepInterpolator.vectorsInitialized:Z (0, 0)
	10 return (0, 0)

Method: computeInterpolatedStateAndDerivatives
	0 aload_0 (1, 1)
	1 getfield (1, 1)
	2 org/apache/commons/math3/ode/nonstiff/DormandPrince54StepInterpolator.vectorsInitialized:Z (1, 1)
	4 ifne (1, 1)
	5 276 (1, 1)
	7 aload_0 (2, 1)
	8 getfield (2, 1)
	9 org/apache/commons/math3/ode/nonstiff/DormandPrince54StepInterpolator.v1:[D (2, 1)
	11 ifnonnull (2, 1)
	12 47 (2, 1)
	14 aload_0 (2, 1)
	15 aload_0 (2, 1)
	16 getfield (2, 1)
	17 org/apache/commons/math3/ode/nonstiff/DormandPrince54StepInterpolator.interpolatedState:[D (2, 1)
	19 arraylength (2, 1)
	20 newarray (2, 1)
	21 7 (2, 1)
	22 putfield (2, 1)
	23 org/apache/commons/math3/ode/nonstiff/DormandPrince54StepInterpolator.v1:[D (2, 1)
	25 aload_0 (2, 1)
	26 aload_0 (2, 1)
	27 getfield (2, 1)
	28 org/apache/commons/math3/ode/nonstiff/DormandPrince54StepInterpolator.interpolatedState:[D (2, 1)
	30 arraylength (2, 1)
	31 newarray (2, 1)
	32 7 (2, 1)
	33 putfield (2, 1)
	34 org/apache/commons/math3/ode/nonstiff/DormandPrince54StepInterpolator.v2:[D (2, 1)
	36 aload_0 (2, 1)
	37 aload_0 (2, 1)
	38 getfield (2, 1)
	39 org/apache/commons/math3/ode/nonstiff/DormandPrince54StepInterpolator.interpolatedState:[D (2, 1)
	41 arraylength (2, 1)
	42 newarray (2, 1)
	43 7 (2, 1)
	44 putfield (2, 1)
	45 org/apache/commons/math3/ode/nonstiff/DormandPrince54StepInterpolator.v3:[D (2, 1)
	47 aload_0 (2, 1)
	48 aload_0 (2, 1)
	49 getfield (2, 1)
	50 org/apache/commons/math3/ode/nonstiff/DormandPrince54StepInterpolator.interpolatedState:[D (2, 1)
	52 arraylength (2, 1)
	53 newarray (2, 1)
	54 7 (2, 1)
	55 putfield (2, 1)
	56 org/apache/commons/math3/ode/nonstiff/DormandPrince54StepInterpolator.v4:[D (2, 1)
	58 iconst_0 (4, 4)
	59 istore (4, 4)
	60 #5 (4, 4)
	61 iload (4, 4)
	62 #5 (4, 4)
	63 aload_0 (4, 4)
	64 getfield (4, 4)
	65 org/apache/commons/math3/ode/nonstiff/DormandPrince54StepInterpolator.interpolatedState:[D (4, 4)
	67 arraylength (4, 4)
	68 if_icmpge (4, 4)
	69 207 (4, 4)
	71 aload_0 (4, 4)
	72 getfield (4, 4)
	73 org/apache/commons/math3/ode/nonstiff/DormandPrince54StepInterpolator.yDotK:[[D (4, 4)
	75 iconst_0 (4, 4)
	76 aaload (4, 4)
	77 iload (4, 4)
	78 #5 (4, 4)
	79 daload (4, 4)
	80 dstore (4, 4)
	81 #6 (4, 4)
	82 aload_0 (4, 4)
	83 getfield (4, 4)
	84 org/apache/commons/math3/ode/nonstiff/DormandPrince54StepInterpolator.yDotK:[[D (4, 4)
	86 iconst_2 (4, 4)
	87 aaload (4, 4)
	88 iload (4, 4)
	89 #5 (4, 4)
	90 daload (4, 4)
	91 dstore (4, 4)
	92 #8 (4, 4)
	93 aload_0 (4, 4)
	94 getfield (4, 4)
	95 org/apache/commons/math3/ode/nonstiff/DormandPrince54StepInterpolator.yDotK:[[D (4, 4)
	97 iconst_3 (4, 4)
	98 aaload (4, 4)
	99 iload (4, 4)
	100 #5 (4, 4)
	101 daload (4, 4)
	102 dstore (4, 4)
	103 #10 (4, 4)
	104 aload_0 (4, 4)
	105 getfield (4, 4)
	106 org/apache/commons/math3/ode/nonstiff/DormandPrince54StepInterpolator.yDotK:[[D (4, 4)
	108 iconst_4 (4, 4)
	109 aaload (4, 4)
	110 iload (4, 4)
	111 #5 (4, 4)
	112 daload (4, 4)
	113 dstore (4, 4)
	114 #12 (4, 4)
	115 aload_0 (4, 4)
	116 getfield (4, 4)
	117 org/apache/commons/math3/ode/nonstiff/DormandPrince54StepInterpolator.yDotK:[[D (4, 4)
	119 iconst_5 (4, 4)
	120 aaload (4, 4)
	121 iload (4, 4)
	122 #5 (4, 4)
	123 daload (4, 4)
	124 dstore (4, 4)
	125 #14 (4, 4)
	126 aload_0 (4, 4)
	127 getfield (4, 4)
	128 org/apache/commons/math3/ode/nonstiff/DormandPrince54StepInterpolator.yDotK:[[D (4, 4)
	130 bipush (4, 4)
	131 6 (4, 4)
	132 aaload (4, 4)
	133 iload (4, 4)
	134 #5 (4, 4)
	135 daload (4, 4)
	136 dstore (4, 4)
	137 #16 (4, 4)
	138 aload_0 (4, 4)
	139 getfield (4, 4)
	140 org/apache/commons/math3/ode/nonstiff/DormandPrince54StepInterpolator.v1:[D (4, 4)
	142 iload (4, 4)
	143 #5 (4, 4)
	144 ldc2_w (4, 4)
	145 0.09114583333333333 (4, 4)
	147 dload (4, 4)
	148 #6 (4, 4)
	149 dmul (4, 4)
	150 ldc2_w (4, 4)
	151 0.44923629829290207 (4, 4)
	153 dload (4, 4)
	154 #8 (4, 4)
	155 dmul (4, 4)
	156 dadd (4, 4)
	157 ldc2_w (4, 4)
	158 0.6510416666666666 (4, 4)
	160 dload (4, 4)
	161 #10 (4, 4)
	162 dmul (4, 4)
	163 dadd (4, 4)
	164 ldc2_w (4, 4)
	165 -0.322376179245283 (4, 4)
	167 dload (4, 4)
	168 #12 (4, 4)
	169 dmul (4, 4)
	170 dadd (4, 4)
	171 ldc2_w (4, 4)
	172 0.13095238095238096 (4, 4)
	174 dload (4, 4)
	175 #14 (4, 4)
	176 dmul (4, 4)
	177 dadd (4, 4)
	178 dastore (4, 4)
	179 aload_0 (4, 4)
	180 getfield (4, 4)
	181 org/apache/commons/math3/ode/nonstiff/DormandPrince54StepInterpolator.v2:[D (4, 4)
	183 iload (4, 4)
	184 #5 (4, 4)
	185 dload (4, 4)
	186 #6 (4, 4)
	187 aload_0 (4, 4)
	188 getfield (4, 4)
	189 org/apache/commons/math3/ode/nonstiff/DormandPrince54StepInterpolator.v1:[D (4, 4)
	191 iload (4, 4)
	192 #5 (4, 4)
	193 daload (4, 4)
	194 dsub (4, 4)
	195 dastore (4, 4)
	196 aload_0 (4, 4)
	197 getfield (4, 4)
	198 org/apache/commons/math3/ode/nonstiff/DormandPrince54StepInterpolator.v3:[D (4, 4)
	200 iload (4, 4)
	201 #5 (4, 4)
	202 aload_0 (4, 4)
	203 getfield (4, 4)
	204 org/apache/commons/math3/ode/nonstiff/DormandPrince54StepInterpolator.v1:[D (4, 4)
	206 iload (4, 4)
	207 #5 (4, 4)
	208 daload (4, 4)
	209 aload_0 (4, 4)
	210 getfield (4, 4)
	211 org/apache/commons/math3/ode/nonstiff/DormandPrince54StepInterpolator.v2:[D (4, 4)
	213 iload (4, 4)
	214 #5 (4, 4)
	215 daload (4, 4)
	216 dsub (4, 4)
	217 dload (4, 4)
	218 #16 (4, 4)
	219 dsub (4, 4)
	220 dastore (4, 4)
	221 aload_0 (4, 4)
	222 getfield (4, 4)
	223 org/apache/commons/math3/ode/nonstiff/DormandPrince54StepInterpolator.v4:[D (4, 4)
	225 iload (4, 4)
	226 #5 (4, 4)
	227 ldc2_w (4, 4)
	228 -1.1270175653862835 (4, 4)
	230 dload (4, 4)
	231 #6 (4, 4)
	232 dmul (4, 4)
	233 ldc2_w (4, 4)
	234 2.675424484351598 (4, 4)
	236 dload (4, 4)
	237 #8 (4, 4)
	238 dmul (4, 4)
	239 dadd (4, 4)
	240 ldc2_w (4, 4)
	241 -5.685526961588504 (4, 4)
	243 dload (4, 4)
	244 #10 (4, 4)
	245 dmul (4, 4)
	246 dadd (4, 4)
	247 ldc2_w (4, 4)
	248 3.5219323679207912 (4, 4)
	250 dload (4, 4)
	251 #12 (4, 4)
	252 dmul (4, 4)
	253 dadd (4, 4)
	254 ldc2_w (4, 4)
	255 -1.7672812570757455 (4, 4)
	257 dload (4, 4)
	258 #14 (4, 4)
	259 dmul (4, 4)
	260 dadd (4, 4)
	261 ldc2_w (4, 4)
	262 2.382468931778144 (4, 4)
	264 dload (4, 4)
	265 #16 (4, 4)
	266 dmul (4, 4)
	267 dadd (4, 4)
	268 dastore (4, 4)
	269 iinc (4, 4)
	270 #5 (4, 4)
	271 -89 (4, 4)
	272 goto (4, 4)
	273 -211 (4, 4)
	275 aload_0 (3, 4)
	276 iconst_1 (3, 4)
	277 putfield (3, 4)
	278 org/apache/commons/math3/ode/nonstiff/DormandPrince54StepInterpolator.vectorsInitialized:Z (3, 4)
	280 dconst_1 (0, 0)
	281 dload_1 (0, 0)
	282 dsub (0, 0)
	283 dstore (0, 0)
	284 #5 (0, 0)
	285 ldc2_w (0, 0)
	286 2.0 (0, 0)
	288 dload_1 (0, 0)
	289 dmul (0, 0)
	290 dstore (0, 0)
	291 #7 (0, 0)
	292 dconst_1 (0, 0)
	293 dload (0, 0)
	294 #7 (0, 0)
	295 dsub (0, 0)
	296 dstore (0, 0)
	297 #9 (0, 0)
	298 dload_1 (0, 0)
	299 ldc2_w (0, 0)
	300 2.0 (0, 0)
	302 ldc2_w (0, 0)
	303 3.0 (0, 0)
	305 dload_1 (0, 0)
	306 dmul (0, 0)
	307 dsub (0, 0)
	308 dmul (0, 0)
	309 dstore (0, 0)
	310 #11 (0, 0)
	311 dload (0, 0)
	312 #7 (0, 0)
	313 dconst_1 (0, 0)
	314 dload_1 (0, 0)
	315 dload (0, 0)
	316 #7 (0, 0)
	317 ldc2_w (0, 0)
	318 3.0 (0, 0)
	320 dsub (0, 0)
	321 dmul (0, 0)
	322 dadd (0, 0)
	323 dmul (0, 0)
	324 dstore (0, 0)
	325 #13 (0, 0)
	326 aload_0 (1, 1)
	327 getfield (1, 1)
	328 org/apache/commons/math3/ode/nonstiff/DormandPrince54StepInterpolator.previousState:[D (1, 1)
	330 ifnull (1, 1)
	331 141 (1, 1)
	333 dload_1 (1, 1)
	334 ldc2_w (1, 1)
	335 0.5 (1, 1)
	337 dcmpg (1, 1)
	338 ifgt (1, 1)
	339 133 (1, 1)
	341 iconst_0 (2, 4)
	342 istore (2, 4)
	343 #15 (2, 4)
	344 iload (2, 4)
	345 #15 (2, 4)
	346 aload_0 (2, 4)
	347 getfield (2, 4)
	348 org/apache/commons/math3/ode/nonstiff/DormandPrince54StepInterpolator.interpolatedState:[D (2, 4)
	350 arraylength (2, 4)
	351 if_icmpge (2, 4)
	352 117 (2, 4)
	354 aload_0 (2, 4)
	355 getfield (2, 4)
	356 org/apache/commons/math3/ode/nonstiff/DormandPrince54StepInterpolator.interpolatedState:[D (2, 4)
	358 iload (2, 4)
	359 #15 (2, 4)
	360 aload_0 (2, 4)
	361 getfield (2, 4)
	362 org/apache/commons/math3/ode/nonstiff/DormandPrince54StepInterpolator.previousState:[D (2, 4)
	364 iload (2, 4)
	365 #15 (2, 4)
	366 daload (2, 4)
	367 dload_1 (2, 4)
	368 aload_0 (2, 4)
	369 getfield (2, 4)
	370 org/apache/commons/math3/ode/nonstiff/DormandPrince54StepInterpolator.h:D (2, 4)
	372 dmul (2, 4)
	373 aload_0 (2, 4)
	374 getfield (2, 4)
	375 org/apache/commons/math3/ode/nonstiff/DormandPrince54StepInterpolator.v1:[D (2, 4)
	377 iload (2, 4)
	378 #15 (2, 4)
	379 daload (2, 4)
	380 dload (2, 4)
	381 #5 (2, 4)
	382 aload_0 (2, 4)
	383 getfield (2, 4)
	384 org/apache/commons/math3/ode/nonstiff/DormandPrince54StepInterpolator.v2:[D (2, 4)
	386 iload (2, 4)
	387 #15 (2, 4)
	388 daload (2, 4)
	389 dload_1 (2, 4)
	390 aload_0 (2, 4)
	391 getfield (2, 4)
	392 org/apache/commons/math3/ode/nonstiff/DormandPrince54StepInterpolator.v3:[D (2, 4)
	394 iload (2, 4)
	395 #15 (2, 4)
	396 daload (2, 4)
	397 dload (2, 4)
	398 #5 (2, 4)
	399 aload_0 (2, 4)
	400 getfield (2, 4)
	401 org/apache/commons/math3/ode/nonstiff/DormandPrince54StepInterpolator.v4:[D (2, 4)
	403 iload (2, 4)
	404 #15 (2, 4)
	405 daload (2, 4)
	406 dmul (2, 4)
	407 dadd (2, 4)
	408 dmul (2, 4)
	409 dadd (2, 4)
	410 dmul (2, 4)
	411 dadd (2, 4)
	412 dmul (2, 4)
	413 dadd (2, 4)
	414 dastore (2, 4)
	415 aload_0 (2, 4)
	416 getfield (2, 4)
	417 org/apache/commons/math3/ode/nonstiff/DormandPrince54StepInterpolator.interpolatedDerivatives:[D (2, 4)
	419 iload (2, 4)
	420 #15 (2, 4)
	421 aload_0 (2, 4)
	422 getfield (2, 4)
	423 org/apache/commons/math3/ode/nonstiff/DormandPrince54StepInterpolator.v1:[D (2, 4)
	425 iload (2, 4)
	426 #15 (2, 4)
	427 daload (2, 4)
	428 dload (2, 4)
	429 #9 (2, 4)
	430 aload_0 (2, 4)
	431 getfield (2, 4)
	432 org/apache/commons/math3/ode/nonstiff/DormandPrince54StepInterpolator.v2:[D (2, 4)
	434 iload (2, 4)
	435 #15 (2, 4)
	436 daload (2, 4)
	437 dmul (2, 4)
	438 dadd (2, 4)
	439 dload (2, 4)
	440 #11 (2, 4)
	441 aload_0 (2, 4)
	442 getfield (2, 4)
	443 org/apache/commons/math3/ode/nonstiff/DormandPrince54StepInterpolator.v3:[D (2, 4)
	445 iload (2, 4)
	446 #15 (2, 4)
	447 daload (2, 4)
	448 dmul (2, 4)
	449 dadd (2, 4)
	450 dload (2, 4)
	451 #13 (2, 4)
	452 aload_0 (2, 4)
	453 getfield (2, 4)
	454 org/apache/commons/math3/ode/nonstiff/DormandPrince54StepInterpolator.v4:[D (2, 4)
	456 iload (2, 4)
	457 #15 (2, 4)
	458 daload (2, 4)
	459 dmul (2, 4)
	460 dadd (2, 4)
	461 dastore (2, 4)
	462 iinc (2, 4)
	463 #15 (2, 4)
	464 -89 (2, 4)
	465 goto (2, 4)
	466 -121 (2, 4)
	468 goto (2, 4)
	469 124 (2, 4)
	471 iconst_0 (3, 4)
	472 istore (3, 4)
	473 #15 (3, 4)
	474 iload (3, 4)
	475 #15 (3, 4)
	476 aload_0 (3, 4)
	477 getfield (3, 4)
	478 org/apache/commons/math3/ode/nonstiff/DormandPrince54StepInterpolator.interpolatedState:[D (3, 4)
	480 arraylength (3, 4)
	481 if_icmpge (3, 4)
	482 111 (3, 4)
	484 aload_0 (3, 4)
	485 getfield (3, 4)
	486 org/apache/commons/math3/ode/nonstiff/DormandPrince54StepInterpolator.interpolatedState:[D (3, 4)
	488 iload (3, 4)
	489 #15 (3, 4)
	490 aload_0 (3, 4)
	491 getfield (3, 4)
	492 org/apache/commons/math3/ode/nonstiff/DormandPrince54StepInterpolator.currentState:[D (3, 4)
	494 iload (3, 4)
	495 #15 (3, 4)
	496 daload (3, 4)
	497 dload_3 (3, 4)
	498 aload_0 (3, 4)
	499 getfield (3, 4)
	500 org/apache/commons/math3/ode/nonstiff/DormandPrince54StepInterpolator.v1:[D (3, 4)
	502 iload (3, 4)
	503 #15 (3, 4)
	504 daload (3, 4)
	505 dload_1 (3, 4)
	506 aload_0 (3, 4)
	507 getfield (3, 4)
	508 org/apache/commons/math3/ode/nonstiff/DormandPrince54StepInterpolator.v2:[D (3, 4)
	510 iload (3, 4)
	511 #15 (3, 4)
	512 daload (3, 4)
	513 dload_1 (3, 4)
	514 aload_0 (3, 4)
	515 getfield (3, 4)
	516 org/apache/commons/math3/ode/nonstiff/DormandPrince54StepInterpolator.v3:[D (3, 4)
	518 iload (3, 4)
	519 #15 (3, 4)
	520 daload (3, 4)
	521 dload (3, 4)
	522 #5 (3, 4)
	523 aload_0 (3, 4)
	524 getfield (3, 4)
	525 org/apache/commons/math3/ode/nonstiff/DormandPrince54StepInterpolator.v4:[D (3, 4)
	527 iload (3, 4)
	528 #15 (3, 4)
	529 daload (3, 4)
	530 dmul (3, 4)
	531 dadd (3, 4)
	532 dmul (3, 4)
	533 dadd (3, 4)
	534 dmul (3, 4)
	535 dsub (3, 4)
	536 dmul (3, 4)
	537 dsub (3, 4)
	538 dastore (3, 4)
	539 aload_0 (3, 4)
	540 getfield (3, 4)
	541 org/apache/commons/math3/ode/nonstiff/DormandPrince54StepInterpolator.interpolatedDerivatives:[D (3, 4)
	543 iload (3, 4)
	544 #15 (3, 4)
	545 aload_0 (3, 4)
	546 getfield (3, 4)
	547 org/apache/commons/math3/ode/nonstiff/DormandPrince54StepInterpolator.v1:[D (3, 4)
	549 iload (3, 4)
	550 #15 (3, 4)
	551 daload (3, 4)
	552 dload (3, 4)
	553 #9 (3, 4)
	554 aload_0 (3, 4)
	555 getfield (3, 4)
	556 org/apache/commons/math3/ode/nonstiff/DormandPrince54StepInterpolator.v2:[D (3, 4)
	558 iload (3, 4)
	559 #15 (3, 4)
	560 daload (3, 4)
	561 dmul (3, 4)
	562 dadd (3, 4)
	563 dload (3, 4)
	564 #11 (3, 4)
	565 aload_0 (3, 4)
	566 getfield (3, 4)
	567 org/apache/commons/math3/ode/nonstiff/DormandPrince54StepInterpolator.v3:[D (3, 4)
	569 iload (3, 4)
	570 #15 (3, 4)
	571 daload (3, 4)
	572 dmul (3, 4)
	573 dadd (3, 4)
	574 dload (3, 4)
	575 #13 (3, 4)
	576 aload_0 (3, 4)
	577 getfield (3, 4)
	578 org/apache/commons/math3/ode/nonstiff/DormandPrince54StepInterpolator.v4:[D (3, 4)
	580 iload (3, 4)
	581 #15 (3, 4)
	582 daload (3, 4)
	583 dmul (3, 4)
	584 dadd (3, 4)
	585 dastore (3, 4)
	586 iinc (3, 4)
	587 #15 (3, 4)
	588 -89 (3, 4)
	589 goto (3, 4)
	590 -115 (3, 4)
	592 return (0, 0)

