Method: <init>
	0 aload_0 (0, 0)
	1 aload_1 (0, 0)
	2 dload (0, 0)
	3 #7 (0, 0)
	4 dload (0, 0)
	5 #9 (0, 0)
	6 aload (0, 0)
	7 #11 (0, 0)
	8 aload (0, 0)
	9 #12 (0, 0)
	10 invokespecial (0, 0)
	11 org/apache/commons/math3/ode/nonstiff/AdaptiveStepsizeIntegrator.<init>:(Ljava/lang/String;DD[D[D)V (0, 0)
	13 aload_0 (0, 0)
	14 iload_2 (0, 0)
	15 putfield (0, 0)
	16 org/apache/commons/math3/ode/nonstiff/EmbeddedRungeKuttaIntegrator.fsal:Z (0, 0)
	18 aload_0 (0, 0)
	19 aload_3 (0, 0)
	20 putfield (0, 0)
	21 org/apache/commons/math3/ode/nonstiff/EmbeddedRungeKuttaIntegrator.c:[D (0, 0)
	23 aload_0 (0, 0)
	24 aload (0, 0)
	25 #4 (0, 0)
	26 putfield (0, 0)
	27 org/apache/commons/math3/ode/nonstiff/EmbeddedRungeKuttaIntegrator.a:[[D (0, 0)
	29 aload_0 (0, 0)
	30 aload (0, 0)
	31 #5 (0, 0)
	32 putfield (0, 0)
	33 org/apache/commons/math3/ode/nonstiff/EmbeddedRungeKuttaIntegrator.b:[D (0, 0)
	35 aload_0 (0, 0)
	36 aload (0, 0)
	37 #6 (0, 0)
	38 putfield (0, 0)
	39 org/apache/commons/math3/ode/nonstiff/EmbeddedRungeKuttaIntegrator.prototype:Lorg/apache/commons/math3/ode/nonstiff/RungeKuttaStepInterpolator; (0, 0)
	41 aload_0 (0, 0)
	42 ldc2_w (0, 0)
	43 -1.0 (0, 0)
	45 aload_0 (0, 0)
	46 invokevirtual (0, 0)
	47 org/apache/commons/math3/ode/nonstiff/EmbeddedRungeKuttaIntegrator.getOrder:()I (0, 0)
	49 i2d (0, 0)
	50 ddiv (0, 0)
	51 putfield (0, 0)
	52 org/apache/commons/math3/ode/nonstiff/EmbeddedRungeKuttaIntegrator.exp:D (0, 0)
	54 aload_0 (0, 0)
	55 ldc2_w (0, 0)
	56 0.9 (0, 0)
	58 invokevirtual (0, 0)
	59 org/apache/commons/math3/ode/nonstiff/EmbeddedRungeKuttaIntegrator.setSafety:(D)V (0, 0)
	61 aload_0 (0, 0)
	62 ldc2_w (0, 0)
	63 0.2 (0, 0)
	65 invokevirtual (0, 0)
	66 org/apache/commons/math3/ode/nonstiff/EmbeddedRungeKuttaIntegrator.setMinReduction:(D)V (0, 0)
	68 aload_0 (0, 0)
	69 ldc2_w (0, 0)
	70 10.0 (0, 0)
	72 invokevirtual (0, 0)
	73 org/apache/commons/math3/ode/nonstiff/EmbeddedRungeKuttaIntegrator.setMaxGrowth:(D)V (0, 0)
	75 return (0, 0)

Method: getSafety
	0 aload_0 (0, 0)
	1 getfield (0, 0)
	2 org/apache/commons/math3/ode/nonstiff/EmbeddedRungeKuttaIntegrator.safety:D (0, 0)
	4 dreturn (0, 0)

Method: setSafety
	0 aload_0 (0, 0)
	1 dload_1 (0, 0)
	2 putfield (0, 0)
	3 org/apache/commons/math3/ode/nonstiff/EmbeddedRungeKuttaIntegrator.safety:D (0, 0)
	5 return (0, 0)

Method: integrate
	0 aload_0 (0, 0)
	1 aload_1 (0, 0)
	2 dload_2 (0, 0)
	3 invokevirtual (0, 0)
	4 org/apache/commons/math3/ode/nonstiff/EmbeddedRungeKuttaIntegrator.sanityChecks:(Lorg/apache/commons/math3/ode/ExpandableStatefulODE;D)V (0, 0)
	6 aload_0 (0, 0)
	7 aload_1 (0, 0)
	8 invokevirtual (0, 0)
	9 org/apache/commons/math3/ode/nonstiff/EmbeddedRungeKuttaIntegrator.setEquations:(Lorg/apache/commons/math3/ode/ExpandableStatefulODE;)V (0, 0)
	11 dload_2 (1, 4)
	12 aload_1 (1, 4)
	13 invokevirtual (1, 4)
	14 org/apache/commons/math3/ode/ExpandableStatefulODE.getTime:()D (1, 4)
	16 dcmpl (1, 4)
	17 ifle (1, 4)
	18 7 (1, 4)
	20 iconst_1 (1, 4)
	21 goto (1, 4)
	22 4 (1, 4)
	24 iconst_0 (1, 4)
	25 istore (1, 4)
	26 #4 (1, 4)
	27 aload_1 (1, 4)
	28 invokevirtual (1, 4)
	29 org/apache/commons/math3/ode/ExpandableStatefulODE.getCompleteState:()[D (1, 4)
	31 astore (1, 4)
	32 #5 (1, 4)
	33 aload (1, 4)
	34 #5 (1, 4)
	35 invokevirtual (1, 4)
	36 [D.clone:()Ljava/lang/Object; (1, 4)
	38 checkcast (1, 4)
	39 [D (1, 4)
	41 astore (1, 4)
	42 #6 (1, 4)
	43 aload_0 (1, 4)
	44 getfield (1, 4)
	45 org/apache/commons/math3/ode/nonstiff/EmbeddedRungeKuttaIntegrator.c:[D (1, 4)
	47 arraylength (1, 4)
	48 iconst_1 (1, 4)
	49 iadd (1, 4)
	50 istore (1, 4)
	51 #7 (1, 4)
	52 iload (1, 4)
	53 #7 (1, 4)
	54 aload (1, 4)
	55 #6 (1, 4)
	56 arraylength (1, 4)
	57 multianewarray (1, 4)
	58 [[D (1, 4)
	60 58 (1, 4)
	61 astore (1, 4)
	62 #8 (1, 4)
	63 aload (1, 4)
	64 #5 (1, 4)
	65 invokevirtual (1, 4)
	66 [D.clone:()Ljava/lang/Object; (1, 4)
	68 checkcast (1, 4)
	69 [D (1, 4)
	71 astore (1, 4)
	72 #9 (1, 4)
	73 aload (1, 4)
	74 #6 (1, 4)
	75 arraylength (1, 4)
	76 newarray (1, 4)
	77 7 (1, 4)
	78 astore (1, 4)
	79 #10 (1, 4)
	80 aload_0 (1, 4)
	81 getfield (1, 4)
	82 org/apache/commons/math3/ode/nonstiff/EmbeddedRungeKuttaIntegrator.prototype:Lorg/apache/commons/math3/ode/nonstiff/RungeKuttaStepInterpolator; (1, 4)
	84 invokevirtual (1, 4)
	85 org/apache/commons/math3/ode/nonstiff/RungeKuttaStepInterpolator.copy:()Lorg/apache/commons/math3/ode/sampling/StepInterpolator; (1, 4)
	87 checkcast (1, 4)
	88 org/apache/commons/math3/ode/nonstiff/RungeKuttaStepInterpolator (1, 4)
	90 astore (1, 4)
	91 #11 (1, 4)
	92 aload (2, 4)
	93 #11 (2, 4)
	94 aload_0 (2, 4)
	95 aload (2, 4)
	96 #9 (2, 4)
	97 aload (2, 4)
	98 #8 (2, 4)
	99 iload (2, 4)
	100 #4 (2, 4)
	101 aload_1 (2, 4)
	102 invokevirtual (2, 4)
	103 org/apache/commons/math3/ode/ExpandableStatefulODE.getPrimaryMapper:()Lorg/apache/commons/math3/ode/EquationsMapper; (2, 4)
	105 aload_1 (2, 4)
	106 invokevirtual (2, 4)
	107 org/apache/commons/math3/ode/ExpandableStatefulODE.getSecondaryMappers:()[Lorg/apache/commons/math3/ode/EquationsMapper; (2, 4)
	109 invokevirtual (2, 4)
	110 org/apache/commons/math3/ode/nonstiff/RungeKuttaStepInterpolator.reinitialize:(Lorg/apache/commons/math3/ode/AbstractIntegrator;[D[[DZLorg/apache/commons/math3/ode/EquationsMapper;[Lorg/apache/commons/math3/ode/EquationsMapper;)V (2, 4)
	112 aload (2, 4)
	113 #11 (2, 4)
	114 aload_1 (2, 4)
	115 invokevirtual (2, 4)
	116 org/apache/commons/math3/ode/ExpandableStatefulODE.getTime:()D (2, 4)
	118 invokevirtual (2, 4)
	119 org/apache/commons/math3/ode/nonstiff/RungeKuttaStepInterpolator.storeTime:(D)V (2, 4)
	121 aload_0 (2, 4)
	122 aload_1 (2, 4)
	123 invokevirtual (2, 4)
	124 org/apache/commons/math3/ode/ExpandableStatefulODE.getTime:()D (2, 4)
	126 putfield (2, 4)
	127 org/apache/commons/math3/ode/nonstiff/EmbeddedRungeKuttaIntegrator.stepStart:D (2, 4)
	129 dconst_0 (2, 4)
	130 dstore (2, 4)
	131 #12 (2, 4)
	132 iconst_1 (2, 4)
	133 istore (2, 4)
	134 #14 (2, 4)
	135 aload_0 (2, 4)
	136 aload_1 (2, 4)
	137 invokevirtual (2, 4)
	138 org/apache/commons/math3/ode/ExpandableStatefulODE.getTime:()D (2, 4)
	140 aload (2, 4)
	141 #5 (2, 4)
	142 dload_2 (2, 4)
	143 invokevirtual (2, 4)
	144 org/apache/commons/math3/ode/nonstiff/EmbeddedRungeKuttaIntegrator.initIntegration:(D[DD)V (2, 4)
	146 aload_0 (2, 4)
	147 iconst_0 (2, 4)
	148 putfield (2, 4)
	149 org/apache/commons/math3/ode/nonstiff/EmbeddedRungeKuttaIntegrator.isLastStep:Z (2, 4)
	151 aload (3, 1)
	152 #11 (3, 1)
	153 invokevirtual (3, 1)
	154 org/apache/commons/math3/ode/nonstiff/RungeKuttaStepInterpolator.shift:()V (3, 1)
	156 ldc2_w (3, 1)
	157 10.0 (3, 1)
	159 dstore (3, 1)
	160 #15 (3, 1)
	161 dload (4, 3)
	162 #15 (4, 3)
	163 dconst_1 (4, 3)
	164 dcmpl (4, 3)
	165 iflt (4, 3)
	166 537 (4, 3)
	168 iload (5, 1)
	169 #14 (5, 1)
	170 ifne (5, 1)
	171 10 (5, 1)
	173 aload_0 (5, 1)
	174 getfield (5, 1)
	175 org/apache/commons/math3/ode/nonstiff/EmbeddedRungeKuttaIntegrator.fsal:Z (5, 1)
	177 ifne (5, 1)
	178 17 (5, 1)
	180 aload_0 (5, 1)
	181 aload_0 (5, 1)
	182 getfield (5, 1)
	183 org/apache/commons/math3/ode/nonstiff/EmbeddedRungeKuttaIntegrator.stepStart:D (5, 1)
	185 aload (5, 1)
	186 #6 (5, 1)
	187 aload (5, 1)
	188 #8 (5, 1)
	189 iconst_0 (5, 1)
	190 aaload (5, 1)
	191 invokevirtual (5, 1)
	192 org/apache/commons/math3/ode/nonstiff/EmbeddedRungeKuttaIntegrator.computeDerivatives:(D[D[D)V (5, 1)
	194 iload (5, 1)
	195 #14 (5, 1)
	196 ifeq (5, 1)
	197 140 (5, 1)
	199 aload_0 (5, 1)
	200 getfield (5, 1)
	201 org/apache/commons/math3/ode/nonstiff/EmbeddedRungeKuttaIntegrator.mainSetDimension:I (5, 1)
	203 newarray (5, 1)
	204 7 (5, 1)
	205 astore (5, 1)
	206 #17 (5, 1)
	207 aload_0 (6, 1)
	208 getfield (6, 1)
	209 org/apache/commons/math3/ode/nonstiff/EmbeddedRungeKuttaIntegrator.vecAbsoluteTolerance:[D (6, 1)
	211 ifnonnull (6, 1)
	212 46 (6, 1)
	214 iconst_0 (7, 4)
	215 istore (7, 4)
	216 #18 (7, 4)
	217 iload (7, 4)
	218 #18 (7, 4)
	219 aload (7, 4)
	220 #17 (7, 4)
	221 arraylength (7, 4)
	222 if_icmpge (7, 4)
	223 32 (7, 4)
	225 aload (7, 4)
	226 #17 (7, 4)
	227 iload (7, 4)
	228 #18 (7, 4)
	229 aload_0 (7, 4)
	230 getfield (7, 4)
	231 org/apache/commons/math3/ode/nonstiff/EmbeddedRungeKuttaIntegrator.scalAbsoluteTolerance:D (7, 4)
	233 aload_0 (7, 4)
	234 getfield (7, 4)
	235 org/apache/commons/math3/ode/nonstiff/EmbeddedRungeKuttaIntegrator.scalRelativeTolerance:D (7, 4)
	237 aload (7, 4)
	238 #6 (7, 4)
	239 iload (7, 4)
	240 #18 (7, 4)
	241 daload (7, 4)
	242 invokestatic (7, 4)
	243 org/apache/commons/math3/util/FastMath.abs:(D)D (7, 4)
	245 dmul (7, 4)
	246 dadd (7, 4)
	247 dastore (7, 4)
	248 iinc (7, 4)
	249 #18 (7, 4)
	250 -89 (7, 4)
	251 goto (7, 4)
	252 -34 (7, 4)
	254 goto (7, 4)
	255 49 (7, 4)
	257 iconst_0 (8, 4)
	258 istore (8, 4)
	259 #18 (8, 4)
	260 iload (8, 4)
	261 #18 (8, 4)
	262 aload (8, 4)
	263 #17 (8, 4)
	264 arraylength (8, 4)
	265 if_icmpge (8, 4)
	266 38 (8, 4)
	268 aload (8, 4)
	269 #17 (8, 4)
	270 iload (8, 4)
	271 #18 (8, 4)
	272 aload_0 (8, 4)
	273 getfield (8, 4)
	274 org/apache/commons/math3/ode/nonstiff/EmbeddedRungeKuttaIntegrator.vecAbsoluteTolerance:[D (8, 4)
	276 iload (8, 4)
	277 #18 (8, 4)
	278 daload (8, 4)
	279 aload_0 (8, 4)
	280 getfield (8, 4)
	281 org/apache/commons/math3/ode/nonstiff/EmbeddedRungeKuttaIntegrator.vecRelativeTolerance:[D (8, 4)
	283 iload (8, 4)
	284 #18 (8, 4)
	285 daload (8, 4)
	286 aload (8, 4)
	287 #6 (8, 4)
	288 iload (8, 4)
	289 #18 (8, 4)
	290 daload (8, 4)
	291 invokestatic (8, 4)
	292 org/apache/commons/math3/util/FastMath.abs:(D)D (8, 4)
	294 dmul (8, 4)
	295 dadd (8, 4)
	296 dastore (8, 4)
	297 iinc (8, 4)
	298 #18 (8, 4)
	299 -89 (8, 4)
	300 goto (8, 4)
	301 -40 (8, 4)
	303 aload_0 (6, 4)
	304 iload (6, 4)
	305 #4 (6, 4)
	306 aload_0 (6, 4)
	307 invokevirtual (6, 4)
	308 org/apache/commons/math3/ode/nonstiff/EmbeddedRungeKuttaIntegrator.getOrder:()I (6, 4)
	310 aload (6, 4)
	311 #17 (6, 4)
	312 aload_0 (6, 4)
	313 getfield (6, 4)
	314 org/apache/commons/math3/ode/nonstiff/EmbeddedRungeKuttaIntegrator.stepStart:D (6, 4)
	316 aload (6, 4)
	317 #6 (6, 4)
	318 aload (6, 4)
	319 #8 (6, 4)
	320 iconst_0 (6, 4)
	321 aaload (6, 4)
	322 aload (6, 4)
	323 #9 (6, 4)
	324 aload (6, 4)
	325 #8 (6, 4)
	326 iconst_1 (6, 4)
	327 aaload (6, 4)
	328 invokevirtual (6, 4)
	329 org/apache/commons/math3/ode/nonstiff/EmbeddedRungeKuttaIntegrator.initializeStep:(ZI[DD[D[D[D[D)D (6, 4)
	331 dstore (6, 4)
	332 #12 (6, 4)
	333 iconst_0 (6, 4)
	334 istore (6, 4)
	335 #14 (6, 4)
	336 aload_0 (4, 3)
	337 dload (4, 3)
	338 #12 (4, 3)
	339 putfield (4, 3)
	340 org/apache/commons/math3/ode/nonstiff/EmbeddedRungeKuttaIntegrator.stepSize:D (4, 3)
	342 iload (5, 1)
	343 #4 (5, 1)
	344 ifeq (5, 1)
	345 30 (5, 1)
	347 aload_0 (6, 1)
	348 getfield (6, 1)
	349 org/apache/commons/math3/ode/nonstiff/EmbeddedRungeKuttaIntegrator.stepStart:D (6, 1)
	351 aload_0 (6, 1)
	352 getfield (6, 1)
	353 org/apache/commons/math3/ode/nonstiff/EmbeddedRungeKuttaIntegrator.stepSize:D (6, 1)
	355 dadd (6, 1)
	356 dload_2 (6, 1)
	357 dcmpl (6, 1)
	358 iflt (6, 1)
	359 40 (6, 1)
	361 aload_0 (6, 1)
	362 dload_2 (6, 1)
	363 aload_0 (6, 1)
	364 getfield (6, 1)
	365 org/apache/commons/math3/ode/nonstiff/EmbeddedRungeKuttaIntegrator.stepStart:D (6, 1)
	367 dsub (6, 1)
	368 putfield (6, 1)
	369 org/apache/commons/math3/ode/nonstiff/EmbeddedRungeKuttaIntegrator.stepSize:D (6, 1)
	371 goto (6, 1)
	372 27 (6, 1)
	374 aload_0 (7, 1)
	375 getfield (7, 1)
	376 org/apache/commons/math3/ode/nonstiff/EmbeddedRungeKuttaIntegrator.stepStart:D (7, 1)
	378 aload_0 (7, 1)
	379 getfield (7, 1)
	380 org/apache/commons/math3/ode/nonstiff/EmbeddedRungeKuttaIntegrator.stepSize:D (7, 1)
	382 dadd (7, 1)
	383 dload_2 (7, 1)
	384 dcmpg (7, 1)
	385 ifgt (7, 1)
	386 13 (7, 1)
	388 aload_0 (7, 1)
	389 dload_2 (7, 1)
	390 aload_0 (7, 1)
	391 getfield (7, 1)
	392 org/apache/commons/math3/ode/nonstiff/EmbeddedRungeKuttaIntegrator.stepStart:D (7, 1)
	394 dsub (7, 1)
	395 putfield (7, 1)
	396 org/apache/commons/math3/ode/nonstiff/EmbeddedRungeKuttaIntegrator.stepSize:D (7, 1)
	398 iconst_1 (5, 4)
	399 istore (5, 4)
	400 #17 (5, 4)
	401 iload (5, 4)
	402 #17 (5, 4)
	403 iload (5, 4)
	404 #7 (5, 4)
	405 if_icmpge (5, 4)
	406 137 (5, 4)
	408 iconst_0 (6, 4)
	409 istore (6, 4)
	410 #18 (6, 4)
	411 iload (6, 4)
	412 #18 (6, 4)
	413 aload (6, 4)
	414 #5 (6, 4)
	415 arraylength (6, 4)
	416 if_icmpge (6, 4)
	417 90 (6, 4)
	419 aload_0 (6, 4)
	420 getfield (6, 4)
	421 org/apache/commons/math3/ode/nonstiff/EmbeddedRungeKuttaIntegrator.a:[[D (6, 4)
	423 iload (6, 4)
	424 #17 (6, 4)
	425 iconst_1 (6, 4)
	426 isub (6, 4)
	427 aaload (6, 4)
	428 iconst_0 (6, 4)
	429 daload (6, 4)
	430 aload (6, 4)
	431 #8 (6, 4)
	432 iconst_0 (6, 4)
	433 aaload (6, 4)
	434 iload (6, 4)
	435 #18 (6, 4)
	436 daload (6, 4)
	437 dmul (6, 4)
	438 dstore (6, 4)
	439 #19 (6, 4)
	440 iconst_1 (7, 4)
	441 istore (7, 4)
	442 #21 (7, 4)
	443 iload (7, 4)
	444 #21 (7, 4)
	445 iload (7, 4)
	446 #17 (7, 4)
	447 if_icmpge (7, 4)
	448 35 (7, 4)
	450 dload (7, 4)
	451 #19 (7, 4)
	452 aload_0 (7, 4)
	453 getfield (7, 4)
	454 org/apache/commons/math3/ode/nonstiff/EmbeddedRungeKuttaIntegrator.a:[[D (7, 4)
	456 iload (7, 4)
	457 #17 (7, 4)
	458 iconst_1 (7, 4)
	459 isub (7, 4)
	460 aaload (7, 4)
	461 iload (7, 4)
	462 #21 (7, 4)
	463 daload (7, 4)
	464 aload (7, 4)
	465 #8 (7, 4)
	466 iload (7, 4)
	467 #21 (7, 4)
	468 aaload (7, 4)
	469 iload (7, 4)
	470 #18 (7, 4)
	471 daload (7, 4)
	472 dmul (7, 4)
	473 dadd (7, 4)
	474 dstore (7, 4)
	475 #19 (7, 4)
	476 iinc (7, 4)
	477 #21 (7, 4)
	478 -89 (7, 4)
	479 goto (7, 4)
	480 -36 (7, 4)
	482 aload (6, 4)
	483 #9 (6, 4)
	484 iload (6, 4)
	485 #18 (6, 4)
	486 aload (6, 4)
	487 #6 (6, 4)
	488 iload (6, 4)
	489 #18 (6, 4)
	490 daload (6, 4)
	491 aload_0 (6, 4)
	492 getfield (6, 4)
	493 org/apache/commons/math3/ode/nonstiff/EmbeddedRungeKuttaIntegrator.stepSize:D (6, 4)
	495 dload (6, 4)
	496 #19 (6, 4)
	497 dmul (6, 4)
	498 dadd (6, 4)
	499 dastore (6, 4)
	500 iinc (6, 4)
	501 #18 (6, 4)
	502 -89 (6, 4)
	503 goto (6, 4)
	504 -92 (6, 4)
	506 aload_0 (5, 4)
	507 aload_0 (5, 4)
	508 getfield (5, 4)
	509 org/apache/commons/math3/ode/nonstiff/EmbeddedRungeKuttaIntegrator.stepStart:D (5, 4)
	511 aload_0 (5, 4)
	512 getfield (5, 4)
	513 org/apache/commons/math3/ode/nonstiff/EmbeddedRungeKuttaIntegrator.c:[D (5, 4)
	515 iload (5, 4)
	516 #17 (5, 4)
	517 iconst_1 (5, 4)
	518 isub (5, 4)
	519 daload (5, 4)
	520 aload_0 (5, 4)
	521 getfield (5, 4)
	522 org/apache/commons/math3/ode/nonstiff/EmbeddedRungeKuttaIntegrator.stepSize:D (5, 4)
	524 dmul (5, 4)
	525 dadd (5, 4)
	526 aload (5, 4)
	527 #9 (5, 4)
	528 aload (5, 4)
	529 #8 (5, 4)
	530 iload (5, 4)
	531 #17 (5, 4)
	532 aaload (5, 4)
	533 invokevirtual (5, 4)
	534 org/apache/commons/math3/ode/nonstiff/EmbeddedRungeKuttaIntegrator.computeDerivatives:(D[D[D)V (5, 4)
	536 iinc (5, 4)
	537 #17 (5, 4)
	538 -89 (5, 4)
	539 goto (5, 4)
	540 -138 (5, 4)
	542 iconst_0 (5, 4)
	543 istore (5, 4)
	544 #17 (5, 4)
	545 iload (5, 4)
	546 #17 (5, 4)
	547 aload (5, 4)
	548 #5 (5, 4)
	549 arraylength (5, 4)
	550 if_icmpge (5, 4)
	551 80 (5, 4)
	553 aload_0 (5, 4)
	554 getfield (5, 4)
	555 org/apache/commons/math3/ode/nonstiff/EmbeddedRungeKuttaIntegrator.b:[D (5, 4)
	557 iconst_0 (5, 4)
	558 daload (5, 4)
	559 aload (5, 4)
	560 #8 (5, 4)
	561 iconst_0 (5, 4)
	562 aaload (5, 4)
	563 iload (5, 4)
	564 #17 (5, 4)
	565 daload (5, 4)
	566 dmul (5, 4)
	567 dstore (5, 4)
	568 #18 (5, 4)
	569 iconst_1 (6, 4)
	570 istore (6, 4)
	571 #20 (6, 4)
	572 iload (6, 4)
	573 #20 (6, 4)
	574 iload (6, 4)
	575 #7 (6, 4)
	576 if_icmpge (6, 4)
	577 30 (6, 4)
	579 dload (6, 4)
	580 #18 (6, 4)
	581 aload_0 (6, 4)
	582 getfield (6, 4)
	583 org/apache/commons/math3/ode/nonstiff/EmbeddedRungeKuttaIntegrator.b:[D (6, 4)
	585 iload (6, 4)
	586 #20 (6, 4)
	587 daload (6, 4)
	588 aload (6, 4)
	589 #8 (6, 4)
	590 iload (6, 4)
	591 #20 (6, 4)
	592 aaload (6, 4)
	593 iload (6, 4)
	594 #17 (6, 4)
	595 daload (6, 4)
	596 dmul (6, 4)
	597 dadd (6, 4)
	598 dstore (6, 4)
	599 #18 (6, 4)
	600 iinc (6, 4)
	601 #20 (6, 4)
	602 -89 (6, 4)
	603 goto (6, 4)
	604 -31 (6, 4)
	606 aload (5, 4)
	607 #9 (5, 4)
	608 iload (5, 4)
	609 #17 (5, 4)
	610 aload (5, 4)
	611 #6 (5, 4)
	612 iload (5, 4)
	613 #17 (5, 4)
	614 daload (5, 4)
	615 aload_0 (5, 4)
	616 getfield (5, 4)
	617 org/apache/commons/math3/ode/nonstiff/EmbeddedRungeKuttaIntegrator.stepSize:D (5, 4)
	619 dload (5, 4)
	620 #18 (5, 4)
	621 dmul (5, 4)
	622 dadd (5, 4)
	623 dastore (5, 4)
	624 iinc (5, 4)
	625 #17 (5, 4)
	626 -89 (5, 4)
	627 goto (5, 4)
	628 -82 (5, 4)
	630 aload_0 (4, 3)
	631 aload (4, 3)
	632 #8 (4, 3)
	633 aload (4, 3)
	634 #6 (4, 3)
	635 aload (4, 3)
	636 #9 (4, 3)
	637 aload_0 (4, 3)
	638 getfield (4, 3)
	639 org/apache/commons/math3/ode/nonstiff/EmbeddedRungeKuttaIntegrator.stepSize:D (4, 3)
	641 invokevirtual (4, 3)
	642 org/apache/commons/math3/ode/nonstiff/EmbeddedRungeKuttaIntegrator.estimateError:([[D[D[DD)D (4, 3)
	644 dstore (4, 3)
	645 #15 (4, 3)
	646 dload (5, 1)
	647 #15 (5, 1)
	648 dconst_1 (5, 1)
	649 dcmpl (5, 1)
	650 iflt (5, 1)
	651 -489 (5, 1)
	653 aload_0 (5, 1)
	654 getfield (5, 1)
	655 org/apache/commons/math3/ode/nonstiff/EmbeddedRungeKuttaIntegrator.maxGrowth:D (5, 1)
	657 aload_0 (5, 1)
	658 getfield (5, 1)
	659 org/apache/commons/math3/ode/nonstiff/EmbeddedRungeKuttaIntegrator.minReduction:D (5, 1)
	661 aload_0 (5, 1)
	662 getfield (5, 1)
	663 org/apache/commons/math3/ode/nonstiff/EmbeddedRungeKuttaIntegrator.safety:D (5, 1)
	665 dload (5, 1)
	666 #15 (5, 1)
	667 aload_0 (5, 1)
	668 getfield (5, 1)
	669 org/apache/commons/math3/ode/nonstiff/EmbeddedRungeKuttaIntegrator.exp:D (5, 1)
	671 invokestatic (5, 1)
	672 org/apache/commons/math3/util/FastMath.pow:(DD)D (5, 1)
	674 dmul (5, 1)
	675 invokestatic (5, 1)
	676 org/apache/commons/math3/util/FastMath.max:(DD)D (5, 1)
	678 invokestatic (5, 1)
	679 org/apache/commons/math3/util/FastMath.min:(DD)D (5, 1)
	681 dstore (5, 1)
	682 #17 (5, 1)
	683 aload_0 (6, 4)
	684 aload_0 (6, 4)
	685 getfield (6, 4)
	686 org/apache/commons/math3/ode/nonstiff/EmbeddedRungeKuttaIntegrator.stepSize:D (6, 4)
	688 dload (6, 4)
	689 #17 (6, 4)
	690 dmul (6, 4)
	691 iload (6, 4)
	692 #4 (6, 4)
	693 iconst_0 (6, 4)
	694 invokevirtual (6, 4)
	695 org/apache/commons/math3/ode/nonstiff/EmbeddedRungeKuttaIntegrator.filterStep:(DZZ)D (6, 4)
	697 dstore (6, 4)
	698 #12 (6, 4)
	699 goto (4, 3)
	700 -538 (4, 3)
	702 aload (3, 1)
	703 #11 (3, 1)
	704 aload_0 (3, 1)
	705 getfield (3, 1)
	706 org/apache/commons/math3/ode/nonstiff/EmbeddedRungeKuttaIntegrator.stepStart:D (3, 1)
	708 aload_0 (3, 1)
	709 getfield (3, 1)
	710 org/apache/commons/math3/ode/nonstiff/EmbeddedRungeKuttaIntegrator.stepSize:D (3, 1)
	712 dadd (3, 1)
	713 invokevirtual (3, 1)
	714 org/apache/commons/math3/ode/nonstiff/RungeKuttaStepInterpolator.storeTime:(D)V (3, 1)
	716 aload (3, 1)
	717 #9 (3, 1)
	718 iconst_0 (3, 1)
	719 aload (3, 1)
	720 #6 (3, 1)
	721 iconst_0 (3, 1)
	722 aload (3, 1)
	723 #5 (3, 1)
	724 arraylength (3, 1)
	725 invokestatic (3, 1)
	726 java/lang/System.arraycopy:(Ljava/lang/Object;ILjava/lang/Object;II)V (3, 1)
	728 aload (3, 1)
	729 #8 (3, 1)
	730 iload (3, 1)
	731 #7 (3, 1)
	732 iconst_1 (3, 1)
	733 isub (3, 1)
	734 aaload (3, 1)
	735 iconst_0 (3, 1)
	736 aload (3, 1)
	737 #10 (3, 1)
	738 iconst_0 (3, 1)
	739 aload (3, 1)
	740 #5 (3, 1)
	741 arraylength (3, 1)
	742 invokestatic (3, 1)
	743 java/lang/System.arraycopy:(Ljava/lang/Object;ILjava/lang/Object;II)V (3, 1)
	745 aload_0 (3, 1)
	746 aload_0 (3, 1)
	747 aload (3, 1)
	748 #11 (3, 1)
	749 aload (3, 1)
	750 #6 (3, 1)
	751 aload (3, 1)
	752 #10 (3, 1)
	753 dload_2 (3, 1)
	754 invokevirtual (3, 1)
	755 org/apache/commons/math3/ode/nonstiff/EmbeddedRungeKuttaIntegrator.acceptStep:(Lorg/apache/commons/math3/ode/sampling/AbstractStepInterpolator;[D[DD)D (3, 1)
	757 putfield (3, 1)
	758 org/apache/commons/math3/ode/nonstiff/EmbeddedRungeKuttaIntegrator.stepStart:D (3, 1)
	760 aload (3, 1)
	761 #6 (3, 1)
	762 iconst_0 (3, 1)
	763 aload (3, 1)
	764 #9 (3, 1)
	765 iconst_0 (3, 1)
	766 aload (3, 1)
	767 #6 (3, 1)
	768 arraylength (3, 1)
	769 invokestatic (3, 1)
	770 java/lang/System.arraycopy:(Ljava/lang/Object;ILjava/lang/Object;II)V (3, 1)
	772 aload_0 (4, 1)
	773 getfield (4, 1)
	774 org/apache/commons/math3/ode/nonstiff/EmbeddedRungeKuttaIntegrator.isLastStep:Z (4, 1)
	776 ifne (4, 1)
	777 183 (4, 1)
	779 aload (4, 1)
	780 #11 (4, 1)
	781 aload_0 (4, 1)
	782 getfield (4, 1)
	783 org/apache/commons/math3/ode/nonstiff/EmbeddedRungeKuttaIntegrator.stepStart:D (4, 1)
	785 invokevirtual (4, 1)
	786 org/apache/commons/math3/ode/nonstiff/RungeKuttaStepInterpolator.storeTime:(D)V (4, 1)
	788 aload_0 (5, 1)
	789 getfield (5, 1)
	790 org/apache/commons/math3/ode/nonstiff/EmbeddedRungeKuttaIntegrator.fsal:Z (5, 1)
	792 ifeq (5, 1)
	793 17 (5, 1)
	795 aload (6, 4)
	796 #10 (6, 4)
	797 iconst_0 (6, 4)
	798 aload (6, 4)
	799 #8 (6, 4)
	800 iconst_0 (6, 4)
	801 aaload (6, 4)
	802 iconst_0 (6, 4)
	803 aload (6, 4)
	804 #5 (6, 4)
	805 arraylength (6, 4)
	806 invokestatic (6, 4)
	807 java/lang/System.arraycopy:(Ljava/lang/Object;ILjava/lang/Object;II)V (6, 4)
	809 aload_0 (5, 4)
	810 getfield (5, 4)
	811 org/apache/commons/math3/ode/nonstiff/EmbeddedRungeKuttaIntegrator.maxGrowth:D (5, 4)
	813 aload_0 (5, 4)
	814 getfield (5, 4)
	815 org/apache/commons/math3/ode/nonstiff/EmbeddedRungeKuttaIntegrator.minReduction:D (5, 4)
	817 aload_0 (5, 4)
	818 getfield (5, 4)
	819 org/apache/commons/math3/ode/nonstiff/EmbeddedRungeKuttaIntegrator.safety:D (5, 4)
	821 dload (5, 4)
	822 #15 (5, 4)
	823 aload_0 (5, 4)
	824 getfield (5, 4)
	825 org/apache/commons/math3/ode/nonstiff/EmbeddedRungeKuttaIntegrator.exp:D (5, 4)
	827 invokestatic (5, 4)
	828 org/apache/commons/math3/util/FastMath.pow:(DD)D (5, 4)
	830 dmul (5, 4)
	831 invokestatic (5, 4)
	832 org/apache/commons/math3/util/FastMath.max:(DD)D (5, 4)
	834 invokestatic (5, 4)
	835 org/apache/commons/math3/util/FastMath.min:(DD)D (5, 4)
	837 dstore (5, 4)
	838 #17 (5, 4)
	839 aload_0 (5, 4)
	840 getfield (5, 4)
	841 org/apache/commons/math3/ode/nonstiff/EmbeddedRungeKuttaIntegrator.stepSize:D (5, 4)
	843 dload (5, 4)
	844 #17 (5, 4)
	845 dmul (5, 4)
	846 dstore (5, 4)
	847 #19 (5, 4)
	848 aload_0 (5, 4)
	849 getfield (5, 4)
	850 org/apache/commons/math3/ode/nonstiff/EmbeddedRungeKuttaIntegrator.stepStart:D (5, 4)
	852 dload (5, 4)
	853 #19 (5, 4)
	854 dadd (5, 4)
	855 dstore (5, 4)
	856 #21 (5, 4)
	857 iload (6, 4)
	858 #4 (6, 4)
	859 ifeq (6, 4)
	860 18 (6, 4)
	862 dload (6, 4)
	863 #21 (6, 4)
	864 dload_2 (6, 4)
	865 dcmpl (6, 4)
	866 iflt (6, 4)
	867 7 (6, 4)
	869 iconst_1 (6, 4)
	870 goto (6, 4)
	871 19 (6, 4)
	873 iconst_0 (6, 4)
	874 goto (6, 4)
	875 15 (6, 4)
	877 dload (6, 4)
	878 #21 (6, 4)
	879 dload_2 (6, 4)
	880 dcmpg (6, 4)
	881 ifgt (6, 4)
	882 7 (6, 4)
	884 iconst_1 (6, 4)
	885 goto (6, 4)
	886 4 (6, 4)
	888 iconst_0 (6, 4)
	889 istore (6, 4)
	890 #23 (6, 4)
	891 aload_0 (7, 4)
	892 dload (7, 4)
	893 #19 (7, 4)
	894 iload (7, 4)
	895 #4 (7, 4)
	896 iload (7, 4)
	897 #23 (7, 4)
	898 invokevirtual (7, 4)
	899 org/apache/commons/math3/ode/nonstiff/EmbeddedRungeKuttaIntegrator.filterStep:(DZZ)D (7, 4)
	901 dstore (7, 4)
	902 #12 (7, 4)
	903 aload_0 (7, 4)
	904 getfield (7, 4)
	905 org/apache/commons/math3/ode/nonstiff/EmbeddedRungeKuttaIntegrator.stepStart:D (7, 4)
	907 dload (7, 4)
	908 #12 (7, 4)
	909 dadd (7, 4)
	910 dstore (7, 4)
	911 #24 (7, 4)
	912 iload (8, 4)
	913 #4 (8, 4)
	914 ifeq (8, 4)
	915 18 (8, 4)
	917 dload (8, 4)
	918 #24 (8, 4)
	919 dload_2 (8, 4)
	920 dcmpl (8, 4)
	921 iflt (8, 4)
	922 7 (8, 4)
	924 iconst_1 (8, 4)
	925 goto (8, 4)
	926 19 (8, 4)
	928 iconst_0 (8, 4)
	929 goto (8, 4)
	930 15 (8, 4)
	932 dload (8, 4)
	933 #24 (8, 4)
	934 dload_2 (8, 4)
	935 dcmpg (8, 4)
	936 ifgt (8, 4)
	937 7 (8, 4)
	939 iconst_1 (8, 4)
	940 goto (8, 4)
	941 4 (8, 4)
	943 iconst_0 (8, 4)
	944 istore (8, 4)
	945 #26 (8, 4)
	946 iload (9, 1)
	947 #26 (9, 1)
	948 ifeq (9, 1)
	949 11 (9, 1)
	951 dload_2 (9, 1)
	952 aload_0 (9, 1)
	953 getfield (9, 1)
	954 org/apache/commons/math3/ode/nonstiff/EmbeddedRungeKuttaIntegrator.stepStart:D (9, 1)
	956 dsub (9, 1)
	957 dstore (9, 1)
	958 #12 (9, 1)
	959 aload_0 (4, 3)
	960 getfield (4, 3)
	961 org/apache/commons/math3/ode/nonstiff/EmbeddedRungeKuttaIntegrator.isLastStep:Z (4, 3)
	963 ifeq (4, 3)
	964 -812 (4, 3)
	966 aload_1 (4, 3)
	967 aload_0 (4, 3)
	968 getfield (4, 3)
	969 org/apache/commons/math3/ode/nonstiff/EmbeddedRungeKuttaIntegrator.stepStart:D (4, 3)
	971 invokevirtual (4, 3)
	972 org/apache/commons/math3/ode/ExpandableStatefulODE.setTime:(D)V (4, 3)
	974 aload_1 (4, 3)
	975 aload (4, 3)
	976 #6 (4, 3)
	977 invokevirtual (4, 3)
	978 org/apache/commons/math3/ode/ExpandableStatefulODE.setCompleteState:([D)V (4, 3)
	980 aload_0 (4, 3)
	981 invokevirtual (4, 3)
	982 org/apache/commons/math3/ode/nonstiff/EmbeddedRungeKuttaIntegrator.resetInternalState:()V (4, 3)
	984 return (0, 3)

Method: getMinReduction
	0 aload_0 (0, 0)
	1 getfield (0, 0)
	2 org/apache/commons/math3/ode/nonstiff/EmbeddedRungeKuttaIntegrator.minReduction:D (0, 0)
	4 dreturn (0, 0)

Method: setMinReduction
	0 aload_0 (0, 0)
	1 dload_1 (0, 0)
	2 putfield (0, 0)
	3 org/apache/commons/math3/ode/nonstiff/EmbeddedRungeKuttaIntegrator.minReduction:D (0, 0)
	5 return (0, 0)

Method: getMaxGrowth
	0 aload_0 (0, 0)
	1 getfield (0, 0)
	2 org/apache/commons/math3/ode/nonstiff/EmbeddedRungeKuttaIntegrator.maxGrowth:D (0, 0)
	4 dreturn (0, 0)

Method: setMaxGrowth
	0 aload_0 (0, 0)
	1 dload_1 (0, 0)
	2 putfield (0, 0)
	3 org/apache/commons/math3/ode/nonstiff/EmbeddedRungeKuttaIntegrator.maxGrowth:D (0, 0)
	5 return (0, 0)

