Method: <init>
	0 aload_0 (0, 0)
	1 aload_1 (0, 0)
	2 aload_2 (0, 0)
	3 dload (0, 0)
	4 #4 (0, 0)
	5 dload (0, 0)
	6 #6 (0, 0)
	7 aload (0, 0)
	8 #8 (0, 0)
	9 aload (0, 0)
	10 #9 (0, 0)
	11 invokespecial (0, 0)
	12 org/apache/commons/math3/ode/nonstiff/AdaptiveStepsizeFieldIntegrator.<init>:(Lorg/apache/commons/math3/Field;Ljava/lang/String;DD[D[D)V (0, 0)
	14 aload_0 (0, 0)
	15 iload_3 (0, 0)
	16 putfield (0, 0)
	17 org/apache/commons/math3/ode/nonstiff/EmbeddedRungeKuttaFieldIntegrator.fsal:I (0, 0)
	19 aload_0 (0, 0)
	20 aload_0 (0, 0)
	21 invokevirtual (0, 0)
	22 org/apache/commons/math3/ode/nonstiff/EmbeddedRungeKuttaFieldIntegrator.getC:()[Lorg/apache/commons/math3/RealFieldElement; (0, 0)
	24 putfield (0, 0)
	25 org/apache/commons/math3/ode/nonstiff/EmbeddedRungeKuttaFieldIntegrator.c:[Lorg/apache/commons/math3/RealFieldElement; (0, 0)
	27 aload_0 (0, 0)
	28 aload_0 (0, 0)
	29 invokevirtual (0, 0)
	30 org/apache/commons/math3/ode/nonstiff/EmbeddedRungeKuttaFieldIntegrator.getA:()[[Lorg/apache/commons/math3/RealFieldElement; (0, 0)
	32 putfield (0, 0)
	33 org/apache/commons/math3/ode/nonstiff/EmbeddedRungeKuttaFieldIntegrator.a:[[Lorg/apache/commons/math3/RealFieldElement; (0, 0)
	35 aload_0 (0, 0)
	36 aload_0 (0, 0)
	37 invokevirtual (0, 0)
	38 org/apache/commons/math3/ode/nonstiff/EmbeddedRungeKuttaFieldIntegrator.getB:()[Lorg/apache/commons/math3/RealFieldElement; (0, 0)
	40 putfield (0, 0)
	41 org/apache/commons/math3/ode/nonstiff/EmbeddedRungeKuttaFieldIntegrator.b:[Lorg/apache/commons/math3/RealFieldElement; (0, 0)
	43 aload_0 (0, 0)
	44 aload_1 (0, 0)
	45 invokeinterface (0, 0)
	46 org/apache/commons/math3/Field.org/apache/commons/math3/RealFieldElement (0, 0)
	48 0 (0, 0)
	50 checkcast (0, 0)
	51 org/apache/commons/math3/RealFieldElement (0, 0)
	53 aload_0 (0, 0)
	54 invokevirtual (0, 0)
	55 org/apache/commons/math3/ode/nonstiff/EmbeddedRungeKuttaFieldIntegrator.getOrder:()I (0, 0)
	57 ineg (0, 0)
	58 i2d (0, 0)
	59 invokeinterface (0, 0)
	60 org/apache/commons/math3/RealFieldElement.exp:Lorg/apache/commons/math3/RealFieldElement; (0, 0)
	62 0 (0, 0)
	64 checkcast (0, 0)
	65 org/apache/commons/math3/RealFieldElement (0, 0)
	67 putfield (0, 0)
	68 org/apache/commons/math3/ode/nonstiff/EmbeddedRungeKuttaFieldIntegrator.exp:Lorg/apache/commons/math3/RealFieldElement; (0, 0)
	70 aload_0 (0, 0)
	71 aload_1 (0, 0)
	72 invokeinterface (0, 0)
	73 org/apache/commons/math3/Field.add:(D)Ljava/lang/Object; (0, 0)
	75 0 (0, 0)
	77 checkcast (0, 0)
	78 org/apache/commons/math3/RealFieldElement (0, 0)
	80 ldc2_w (0, 0)
	81 0.9 (0, 0)
	83 invokeinterface (0, 0)
	84 org/apache/commons/math3/RealFieldElement.setSafety:(Lorg/apache/commons/math3/RealFieldElement;)V (0, 0)
	86 0 (0, 0)
	88 checkcast (0, 0)
	89 org/apache/commons/math3/RealFieldElement (0, 0)
	91 invokevirtual (0, 0)
	92 org/apache/commons/math3/ode/nonstiff/EmbeddedRungeKuttaFieldIntegrator.setSafety:(Lorg/apache/commons/math3/RealFieldElement;)V (0, 0)
	94 aload_0 (0, 0)
	95 aload_1 (0, 0)
	96 invokeinterface (0, 0)
	97 org/apache/commons/math3/Field.add:(D)Ljava/lang/Object; (0, 0)
	99 0 (0, 0)
	101 checkcast (0, 0)
	102 org/apache/commons/math3/RealFieldElement (0, 0)
	104 ldc2_w (0, 0)
	105 0.2 (0, 0)
	107 invokeinterface (0, 0)
	108 org/apache/commons/math3/RealFieldElement.setSafety:(Lorg/apache/commons/math3/RealFieldElement;)V (0, 0)
	110 0 (0, 0)
	112 checkcast (0, 0)
	113 org/apache/commons/math3/RealFieldElement (0, 0)
	115 invokevirtual (0, 0)
	116 org/apache/commons/math3/ode/nonstiff/EmbeddedRungeKuttaFieldIntegrator.setMinReduction:(Lorg/apache/commons/math3/RealFieldElement;)V (0, 0)
	118 aload_0 (0, 0)
	119 aload_1 (0, 0)
	120 invokeinterface (0, 0)
	121 org/apache/commons/math3/Field.add:(D)Ljava/lang/Object; (0, 0)
	123 0 (0, 0)
	125 checkcast (0, 0)
	126 org/apache/commons/math3/RealFieldElement (0, 0)
	128 ldc2_w (0, 0)
	129 10.0 (0, 0)
	131 invokeinterface (0, 0)
	132 org/apache/commons/math3/RealFieldElement.setSafety:(Lorg/apache/commons/math3/RealFieldElement;)V (0, 0)
	134 0 (0, 0)
	136 checkcast (0, 0)
	137 org/apache/commons/math3/RealFieldElement (0, 0)
	139 invokevirtual (0, 0)
	140 org/apache/commons/math3/ode/nonstiff/EmbeddedRungeKuttaFieldIntegrator.setMaxGrowth:(Lorg/apache/commons/math3/RealFieldElement;)V (0, 0)
	142 return (0, 0)

Method: fraction
	0 aload_0 (0, 0)
	1 invokevirtual (0, 0)
	2 org/apache/commons/math3/ode/nonstiff/EmbeddedRungeKuttaFieldIntegrator.getField:()Lorg/apache/commons/math3/Field; (0, 0)
	4 invokeinterface (0, 0)
	5 org/apache/commons/math3/Field.org/apache/commons/math3/RealFieldElement (0, 0)
	7 0 (0, 0)
	9 checkcast (0, 0)
	10 org/apache/commons/math3/RealFieldElement (0, 0)
	12 dload_1 (0, 0)
	13 invokeinterface (0, 0)
	14 org/apache/commons/math3/RealFieldElement.safety:Lorg/apache/commons/math3/RealFieldElement; (0, 0)
	16 0 (0, 0)
	18 checkcast (0, 0)
	19 org/apache/commons/math3/RealFieldElement (0, 0)
	21 dload_3 (0, 0)
	22 invokeinterface (0, 0)
	23 org/apache/commons/math3/RealFieldElement.exp:Lorg/apache/commons/math3/RealFieldElement; (0, 0)
	25 0 (0, 0)
	27 checkcast (0, 0)
	28 org/apache/commons/math3/RealFieldElement (0, 0)
	30 areturn (0, 0)

Method: getSafety
	0 aload_0 (0, 0)
	1 getfield (0, 0)
	2 org/apache/commons/math3/ode/nonstiff/EmbeddedRungeKuttaFieldIntegrator.safety:Lorg/apache/commons/math3/RealFieldElement; (0, 0)
	4 areturn (0, 0)

Method: setSafety
	0 aload_0 (0, 0)
	1 aload_1 (0, 0)
	2 putfield (0, 0)
	3 org/apache/commons/math3/ode/nonstiff/EmbeddedRungeKuttaFieldIntegrator.safety:Lorg/apache/commons/math3/RealFieldElement; (0, 0)
	5 return (0, 0)

Method: integrate
	0 aload_0 (0, 0)
	1 aload_2 (0, 0)
	2 aload_3 (0, 0)
	3 invokevirtual (0, 0)
	4 org/apache/commons/math3/ode/nonstiff/EmbeddedRungeKuttaFieldIntegrator.sanityChecks:(Lorg/apache/commons/math3/ode/FieldODEState;Lorg/apache/commons/math3/RealFieldElement;)V (0, 0)
	6 aload_2 (0, 0)
	7 invokevirtual (0, 0)
	8 org/apache/commons/math3/ode/FieldODEState.getTime:()Lorg/apache/commons/math3/RealFieldElement; (0, 0)
	10 astore (0, 0)
	11 #4 (0, 0)
	12 aload_1 (0, 0)
	13 invokevirtual (0, 0)
	14 org/apache/commons/math3/ode/FieldExpandableODE.getMapper:()Lorg/apache/commons/math3/ode/FieldEquationsMapper; (0, 0)
	16 aload_2 (0, 0)
	17 invokevirtual (0, 0)
	18 org/apache/commons/math3/ode/FieldEquationsMapper.mapState:(Lorg/apache/commons/math3/ode/FieldODEState;)[Lorg/apache/commons/math3/RealFieldElement; (0, 0)
	20 astore (0, 0)
	21 #5 (0, 0)
	22 aload_0 (0, 0)
	23 aload_0 (0, 0)
	24 aload_1 (0, 0)
	25 aload (0, 0)
	26 #4 (0, 0)
	27 aload (0, 0)
	28 #5 (0, 0)
	29 aload_3 (0, 0)
	30 invokevirtual (0, 0)
	31 org/apache/commons/math3/ode/nonstiff/EmbeddedRungeKuttaFieldIntegrator.initIntegration:(Lorg/apache/commons/math3/ode/FieldExpandableODE;Lorg/apache/commons/math3/RealFieldElement;[Lorg/apache/commons/math3/RealFieldElement;Lorg/apache/commons/math3/RealFieldElement;)Lorg/apache/commons/math3/ode/FieldODEStateAndDerivative; (0, 0)
	33 invokevirtual (0, 0)
	34 org/apache/commons/math3/ode/nonstiff/EmbeddedRungeKuttaFieldIntegrator.setStepStart:(Lorg/apache/commons/math3/ode/FieldODEStateAndDerivative;)V (0, 0)
	36 aload_3 (0, 4)
	37 aload_2 (0, 4)
	38 invokevirtual (0, 4)
	39 org/apache/commons/math3/ode/FieldODEState.getTime:()Lorg/apache/commons/math3/RealFieldElement; (0, 4)
	41 invokeinterface (0, 4)
	42 org/apache/commons/math3/RealFieldElement.getReal:()D (0, 4)
	44 0 (0, 4)
	46 checkcast (0, 4)
	47 org/apache/commons/math3/RealFieldElement (0, 4)
	49 invokeinterface (0, 4)
	50 org/apache/commons/math3/RealFieldElement.org/apache/commons/math3/util/MathArrays (0, 4)
	52 0 (0, 4)
	54 dconst_0 (0, 4)
	55 dcmpl (0, 4)
	56 ifle (0, 4)
	57 7 (0, 4)
	59 iconst_1 (0, 4)
	60 goto (0, 4)
	61 4 (0, 4)
	63 iconst_0 (0, 4)
	64 istore (0, 4)
	65 #6 (0, 4)
	66 aload_0 (0, 4)
	67 getfield (0, 4)
	68 org/apache/commons/math3/ode/nonstiff/EmbeddedRungeKuttaFieldIntegrator.c:[Lorg/apache/commons/math3/RealFieldElement; (0, 4)
	70 arraylength (0, 4)
	71 iconst_1 (0, 4)
	72 iadd (0, 4)
	73 istore (0, 4)
	74 #7 (0, 4)
	75 aload (0, 4)
	76 #5 (0, 4)
	77 astore (0, 4)
	78 #8 (0, 4)
	79 aload_0 (0, 4)
	80 invokevirtual (0, 4)
	81 org/apache/commons/math3/ode/nonstiff/EmbeddedRungeKuttaFieldIntegrator.getField:()Lorg/apache/commons/math3/Field; (0, 4)
	83 iload (0, 4)
	84 #7 (0, 4)
	85 iconst_m1 (0, 4)
	86 invokestatic (0, 4)
	87 org/apache/commons/math3/util/MathArrays.buildArray:(Lorg/apache/commons/math3/Field;II)[[Ljava/lang/Object; (0, 4)
	89 checkcast (0, 4)
	90 [[Lorg/apache/commons/math3/RealFieldElement; (0, 4)
	92 astore (0, 4)
	93 #9 (0, 4)
	94 aload_0 (0, 4)
	95 invokevirtual (0, 4)
	96 org/apache/commons/math3/ode/nonstiff/EmbeddedRungeKuttaFieldIntegrator.getField:()Lorg/apache/commons/math3/Field; (0, 4)
	98 aload (0, 4)
	99 #5 (0, 4)
	100 arraylength (0, 4)
	101 invokestatic (0, 4)
	102 org/apache/commons/math3/util/MathArrays.buildArray:(Lorg/apache/commons/math3/Field;I)[Ljava/lang/Object; (0, 4)
	104 checkcast (0, 4)
	105 [Lorg/apache/commons/math3/RealFieldElement; (0, 4)
	107 astore (0, 4)
	108 #10 (0, 4)
	109 aload_0 (0, 4)
	110 invokevirtual (0, 4)
	111 org/apache/commons/math3/ode/nonstiff/EmbeddedRungeKuttaFieldIntegrator.getField:()Lorg/apache/commons/math3/Field; (0, 4)
	113 invokeinterface (0, 4)
	114 org/apache/commons/math3/Field.add:(D)Ljava/lang/Object; (0, 4)
	116 0 (0, 4)
	118 checkcast (0, 4)
	119 org/apache/commons/math3/RealFieldElement (0, 4)
	121 astore (0, 4)
	122 #11 (0, 4)
	123 iconst_1 (0, 4)
	124 istore (0, 4)
	125 #12 (0, 4)
	126 aload_0 (0, 4)
	127 iconst_0 (0, 4)
	128 invokevirtual (0, 4)
	129 org/apache/commons/math3/ode/nonstiff/EmbeddedRungeKuttaFieldIntegrator.setIsLastStep:(Z)V (0, 4)
	131 aload_0 (0, 4)
	132 invokevirtual (0, 4)
	133 org/apache/commons/math3/ode/nonstiff/EmbeddedRungeKuttaFieldIntegrator.getField:()Lorg/apache/commons/math3/Field; (0, 4)
	135 invokeinterface (0, 4)
	136 org/apache/commons/math3/Field.add:(D)Ljava/lang/Object; (0, 4)
	138 0 (0, 4)
	140 checkcast (0, 4)
	141 org/apache/commons/math3/RealFieldElement (0, 4)
	143 ldc2_w (0, 4)
	144 10.0 (0, 4)
	146 invokeinterface (0, 4)
	147 org/apache/commons/math3/RealFieldElement.setSafety:(Lorg/apache/commons/math3/RealFieldElement;)V (0, 4)
	149 0 (0, 4)
	151 checkcast (0, 4)
	152 org/apache/commons/math3/RealFieldElement (0, 4)
	154 astore (0, 4)
	155 #13 (0, 4)
	156 aload (2, 3)
	157 #13 (2, 3)
	158 dconst_1 (2, 3)
	159 invokeinterface (2, 3)
	160 org/apache/commons/math3/RealFieldElement.getStepStart:()Lorg/apache/commons/math3/ode/FieldODEStateAndDerivative; (2, 3)
	162 0 (2, 3)
	164 checkcast (2, 3)
	165 org/apache/commons/math3/RealFieldElement (2, 3)
	167 invokeinterface (2, 3)
	168 org/apache/commons/math3/RealFieldElement.org/apache/commons/math3/util/MathArrays (2, 3)
	170 0 (2, 3)
	172 dconst_0 (2, 3)
	173 dcmpl (2, 3)
	174 iflt (2, 3)
	175 747 (2, 3)
	177 aload_1 (2, 3)
	178 invokevirtual (2, 3)
	179 org/apache/commons/math3/ode/FieldExpandableODE.getMapper:()Lorg/apache/commons/math3/ode/FieldEquationsMapper; (2, 3)
	181 aload_0 (2, 3)
	182 invokevirtual (2, 3)
	183 org/apache/commons/math3/ode/nonstiff/EmbeddedRungeKuttaFieldIntegrator.getStepStart:()Lorg/apache/commons/math3/ode/FieldODEStateAndDerivative; (2, 3)
	185 invokevirtual (2, 3)
	186 org/apache/commons/math3/ode/FieldEquationsMapper.mapState:(Lorg/apache/commons/math3/ode/FieldODEState;)[Lorg/apache/commons/math3/RealFieldElement; (2, 3)
	188 astore (2, 3)
	189 #8 (2, 3)
	190 aload (2, 3)
	191 #9 (2, 3)
	192 iconst_0 (2, 3)
	193 aload_1 (2, 3)
	194 invokevirtual (2, 3)
	195 org/apache/commons/math3/ode/FieldExpandableODE.getMapper:()Lorg/apache/commons/math3/ode/FieldEquationsMapper; (2, 3)
	197 aload_0 (2, 3)
	198 invokevirtual (2, 3)
	199 org/apache/commons/math3/ode/nonstiff/EmbeddedRungeKuttaFieldIntegrator.getStepStart:()Lorg/apache/commons/math3/ode/FieldODEStateAndDerivative; (2, 3)
	201 invokevirtual (2, 3)
	202 org/apache/commons/math3/ode/FieldEquationsMapper.mapDerivative:(Lorg/apache/commons/math3/ode/FieldODEStateAndDerivative;)[Lorg/apache/commons/math3/RealFieldElement; (2, 3)
	204 aastore (2, 3)
	205 iload (3, 1)
	206 #12 (3, 1)
	207 ifeq (3, 1)
	208 178 (3, 1)
	210 aload_0 (3, 1)
	211 invokevirtual (3, 1)
	212 org/apache/commons/math3/ode/nonstiff/EmbeddedRungeKuttaFieldIntegrator.getField:()Lorg/apache/commons/math3/Field; (3, 1)
	214 aload_0 (3, 1)
	215 getfield (3, 1)
	216 org/apache/commons/math3/ode/nonstiff/EmbeddedRungeKuttaFieldIntegrator.mainSetDimension:I (3, 1)
	218 invokestatic (3, 1)
	219 org/apache/commons/math3/util/MathArrays.buildArray:(Lorg/apache/commons/math3/Field;I)[Ljava/lang/Object; (3, 1)
	221 checkcast (3, 1)
	222 [Lorg/apache/commons/math3/RealFieldElement; (3, 1)
	224 astore (3, 1)
	225 #14 (3, 1)
	226 aload_0 (4, 1)
	227 getfield (4, 1)
	228 org/apache/commons/math3/ode/nonstiff/EmbeddedRungeKuttaFieldIntegrator.vecAbsoluteTolerance:[D (4, 1)
	230 ifnonnull (4, 1)
	231 65 (4, 1)
	233 iconst_0 (5, 4)
	234 istore (5, 4)
	235 #15 (5, 4)
	236 iload (5, 4)
	237 #15 (5, 4)
	238 aload (5, 4)
	239 #14 (5, 4)
	240 arraylength (5, 4)
	241 if_icmpge (5, 4)
	242 51 (5, 4)
	244 aload (5, 4)
	245 #14 (5, 4)
	246 iload (5, 4)
	247 #15 (5, 4)
	248 aload (5, 4)
	249 #8 (5, 4)
	250 iload (5, 4)
	251 #15 (5, 4)
	252 aaload (5, 4)
	253 invokeinterface (5, 4)
	254 org/apache/commons/math3/RealFieldElement.scalRelativeTolerance:D (5, 4)
	256 0 (5, 4)
	258 checkcast (5, 4)
	259 org/apache/commons/math3/RealFieldElement (5, 4)
	261 aload_0 (5, 4)
	262 getfield (5, 4)
	263 org/apache/commons/math3/ode/nonstiff/EmbeddedRungeKuttaFieldIntegrator.scalRelativeTolerance:D (5, 4)
	265 invokeinterface (5, 4)
	266 org/apache/commons/math3/RealFieldElement.safety:Lorg/apache/commons/math3/RealFieldElement; (5, 4)
	268 0 (5, 4)
	270 checkcast (5, 4)
	271 org/apache/commons/math3/RealFieldElement (5, 4)
	273 aload_0 (5, 4)
	274 getfield (5, 4)
	275 org/apache/commons/math3/ode/nonstiff/EmbeddedRungeKuttaFieldIntegrator.scalAbsoluteTolerance:D (5, 4)
	277 invokeinterface (5, 4)
	278 org/apache/commons/math3/RealFieldElement.setSafety:(Lorg/apache/commons/math3/RealFieldElement;)V (5, 4)
	280 0 (5, 4)
	282 checkcast (5, 4)
	283 org/apache/commons/math3/RealFieldElement (5, 4)
	285 aastore (5, 4)
	286 iinc (5, 4)
	287 #15 (5, 4)
	288 -89 (5, 4)
	289 goto (5, 4)
	290 -53 (5, 4)
	292 goto (5, 4)
	293 68 (5, 4)
	295 iconst_0 (5, 4)
	296 istore (5, 4)
	297 #15 (5, 4)
	298 iload (5, 4)
	299 #15 (5, 4)
	300 aload (5, 4)
	301 #14 (5, 4)
	302 arraylength (5, 4)
	303 if_icmpge (5, 4)
	304 57 (5, 4)
	306 aload (5, 4)
	307 #14 (5, 4)
	308 iload (5, 4)
	309 #15 (5, 4)
	310 aload (5, 4)
	311 #8 (5, 4)
	312 iload (5, 4)
	313 #15 (5, 4)
	314 aaload (5, 4)
	315 invokeinterface (5, 4)
	316 org/apache/commons/math3/RealFieldElement.scalRelativeTolerance:D (5, 4)
	318 0 (5, 4)
	320 checkcast (5, 4)
	321 org/apache/commons/math3/RealFieldElement (5, 4)
	323 aload_0 (5, 4)
	324 getfield (5, 4)
	325 org/apache/commons/math3/ode/nonstiff/EmbeddedRungeKuttaFieldIntegrator.vecRelativeTolerance:[D (5, 4)
	327 iload (5, 4)
	328 #15 (5, 4)
	329 daload (5, 4)
	330 invokeinterface (5, 4)
	331 org/apache/commons/math3/RealFieldElement.safety:Lorg/apache/commons/math3/RealFieldElement; (5, 4)
	333 0 (5, 4)
	335 checkcast (5, 4)
	336 org/apache/commons/math3/RealFieldElement (5, 4)
	338 aload_0 (5, 4)
	339 getfield (5, 4)
	340 org/apache/commons/math3/ode/nonstiff/EmbeddedRungeKuttaFieldIntegrator.vecAbsoluteTolerance:[D (5, 4)
	342 iload (5, 4)
	343 #15 (5, 4)
	344 daload (5, 4)
	345 invokeinterface (5, 4)
	346 org/apache/commons/math3/RealFieldElement.setSafety:(Lorg/apache/commons/math3/RealFieldElement;)V (5, 4)
	348 0 (5, 4)
	350 checkcast (5, 4)
	351 org/apache/commons/math3/RealFieldElement (5, 4)
	353 aastore (5, 4)
	354 iinc (5, 4)
	355 #15 (5, 4)
	356 -89 (5, 4)
	357 goto (5, 4)
	358 -59 (5, 4)
	360 aload_0 (3, 4)
	361 iload (3, 4)
	362 #6 (3, 4)
	363 aload_0 (3, 4)
	364 invokevirtual (3, 4)
	365 org/apache/commons/math3/ode/nonstiff/EmbeddedRungeKuttaFieldIntegrator.getOrder:()I (3, 4)
	367 aload (3, 4)
	368 #14 (3, 4)
	369 aload_0 (3, 4)
	370 invokevirtual (3, 4)
	371 org/apache/commons/math3/ode/nonstiff/EmbeddedRungeKuttaFieldIntegrator.getStepStart:()Lorg/apache/commons/math3/ode/FieldODEStateAndDerivative; (3, 4)
	373 aload_1 (3, 4)
	374 invokevirtual (3, 4)
	375 org/apache/commons/math3/ode/FieldExpandableODE.getMapper:()Lorg/apache/commons/math3/ode/FieldEquationsMapper; (3, 4)
	377 invokevirtual (3, 4)
	378 org/apache/commons/math3/ode/nonstiff/EmbeddedRungeKuttaFieldIntegrator.initializeStep:(ZI[Lorg/apache/commons/math3/RealFieldElement;Lorg/apache/commons/math3/ode/FieldODEStateAndDerivative;Lorg/apache/commons/math3/ode/FieldEquationsMapper;)Lorg/apache/commons/math3/RealFieldElement; (3, 4)
	380 astore (3, 4)
	381 #11 (3, 4)
	382 iconst_0 (3, 4)
	383 istore (3, 4)
	384 #12 (3, 4)
	385 aload_0 (2, 3)
	386 aload (2, 3)
	387 #11 (2, 3)
	388 invokevirtual (2, 3)
	389 org/apache/commons/math3/ode/nonstiff/EmbeddedRungeKuttaFieldIntegrator.setStepSize:(Lorg/apache/commons/math3/RealFieldElement;)V (2, 3)
	391 iload (3, 1)
	392 #6 (3, 1)
	393 ifeq (3, 1)
	394 64 (3, 1)
	396 aload_0 (4, 1)
	397 invokevirtual (4, 1)
	398 org/apache/commons/math3/ode/nonstiff/EmbeddedRungeKuttaFieldIntegrator.getStepStart:()Lorg/apache/commons/math3/ode/FieldODEStateAndDerivative; (4, 1)
	400 invokevirtual (4, 1)
	401 org/apache/commons/math3/ode/FieldODEStateAndDerivative.getTime:()Lorg/apache/commons/math3/RealFieldElement; (4, 1)
	403 aload_0 (4, 1)
	404 invokevirtual (4, 1)
	405 org/apache/commons/math3/ode/nonstiff/EmbeddedRungeKuttaFieldIntegrator.getStepSize:()Lorg/apache/commons/math3/RealFieldElement; (4, 1)
	407 invokeinterface (4, 1)
	408 org/apache/commons/math3/RealFieldElement.multiply:(Ljava/lang/Object;)Ljava/lang/Object; (4, 1)
	410 0 (4, 1)
	412 checkcast (4, 1)
	413 org/apache/commons/math3/RealFieldElement (4, 1)
	415 aload_3 (4, 1)
	416 invokeinterface (4, 1)
	417 org/apache/commons/math3/RealFieldElement.getReal:()D (4, 1)
	419 0 (4, 1)
	421 checkcast (4, 1)
	422 org/apache/commons/math3/RealFieldElement (4, 1)
	424 invokeinterface (4, 1)
	425 org/apache/commons/math3/RealFieldElement.org/apache/commons/math3/util/MathArrays (4, 1)
	427 0 (4, 1)
	429 dconst_0 (4, 1)
	430 dcmpl (4, 1)
	431 iflt (4, 1)
	432 84 (4, 1)
	434 aload_0 (4, 1)
	435 aload_3 (4, 1)
	436 aload_0 (4, 1)
	437 invokevirtual (4, 1)
	438 org/apache/commons/math3/ode/nonstiff/EmbeddedRungeKuttaFieldIntegrator.getStepStart:()Lorg/apache/commons/math3/ode/FieldODEStateAndDerivative; (4, 1)
	440 invokevirtual (4, 1)
	441 org/apache/commons/math3/ode/FieldODEStateAndDerivative.getTime:()Lorg/apache/commons/math3/RealFieldElement; (4, 1)
	443 invokeinterface (4, 1)
	444 org/apache/commons/math3/RealFieldElement.getReal:()D (4, 1)
	446 0 (4, 1)
	448 checkcast (4, 1)
	449 org/apache/commons/math3/RealFieldElement (4, 1)
	451 invokevirtual (4, 1)
	452 org/apache/commons/math3/ode/nonstiff/EmbeddedRungeKuttaFieldIntegrator.setStepSize:(Lorg/apache/commons/math3/RealFieldElement;)V (4, 1)
	454 goto (4, 1)
	455 61 (4, 1)
	457 aload_0 (4, 1)
	458 invokevirtual (4, 1)
	459 org/apache/commons/math3/ode/nonstiff/EmbeddedRungeKuttaFieldIntegrator.getStepStart:()Lorg/apache/commons/math3/ode/FieldODEStateAndDerivative; (4, 1)
	461 invokevirtual (4, 1)
	462 org/apache/commons/math3/ode/FieldODEStateAndDerivative.getTime:()Lorg/apache/commons/math3/RealFieldElement; (4, 1)
	464 aload_0 (4, 1)
	465 invokevirtual (4, 1)
	466 org/apache/commons/math3/ode/nonstiff/EmbeddedRungeKuttaFieldIntegrator.getStepSize:()Lorg/apache/commons/math3/RealFieldElement; (4, 1)
	468 invokeinterface (4, 1)
	469 org/apache/commons/math3/RealFieldElement.multiply:(Ljava/lang/Object;)Ljava/lang/Object; (4, 1)
	471 0 (4, 1)
	473 checkcast (4, 1)
	474 org/apache/commons/math3/RealFieldElement (4, 1)
	476 aload_3 (4, 1)
	477 invokeinterface (4, 1)
	478 org/apache/commons/math3/RealFieldElement.getReal:()D (4, 1)
	480 0 (4, 1)
	482 checkcast (4, 1)
	483 org/apache/commons/math3/RealFieldElement (4, 1)
	485 invokeinterface (4, 1)
	486 org/apache/commons/math3/RealFieldElement.org/apache/commons/math3/util/MathArrays (4, 1)
	488 0 (4, 1)
	490 dconst_0 (4, 1)
	491 dcmpg (4, 1)
	492 ifgt (4, 1)
	493 23 (4, 1)
	495 aload_0 (4, 1)
	496 aload_3 (4, 1)
	497 aload_0 (4, 1)
	498 invokevirtual (4, 1)
	499 org/apache/commons/math3/ode/nonstiff/EmbeddedRungeKuttaFieldIntegrator.getStepStart:()Lorg/apache/commons/math3/ode/FieldODEStateAndDerivative; (4, 1)
	501 invokevirtual (4, 1)
	502 org/apache/commons/math3/ode/FieldODEStateAndDerivative.getTime:()Lorg/apache/commons/math3/RealFieldElement; (4, 1)
	504 invokeinterface (4, 1)
	505 org/apache/commons/math3/RealFieldElement.getReal:()D (4, 1)
	507 0 (4, 1)
	509 checkcast (4, 1)
	510 org/apache/commons/math3/RealFieldElement (4, 1)
	512 invokevirtual (4, 1)
	513 org/apache/commons/math3/ode/nonstiff/EmbeddedRungeKuttaFieldIntegrator.setStepSize:(Lorg/apache/commons/math3/RealFieldElement;)V (4, 1)
	515 iconst_1 (3, 4)
	516 istore (3, 4)
	517 #14 (3, 4)
	518 iload (3, 4)
	519 #14 (3, 4)
	520 iload (3, 4)
	521 #7 (3, 4)
	522 if_icmpge (3, 4)
	523 180 (3, 4)
	525 iconst_0 (4, 4)
	526 istore (4, 4)
	527 #15 (4, 4)
	528 iload (4, 4)
	529 #15 (4, 4)
	530 aload (4, 4)
	531 #5 (4, 4)
	532 arraylength (4, 4)
	533 if_icmpge (4, 4)
	534 119 (4, 4)
	536 aload (4, 4)
	537 #9 (4, 4)
	538 iconst_0 (4, 4)
	539 aaload (4, 4)
	540 iload (4, 4)
	541 #15 (4, 4)
	542 aaload (4, 4)
	543 aload_0 (4, 4)
	544 getfield (4, 4)
	545 org/apache/commons/math3/ode/nonstiff/EmbeddedRungeKuttaFieldIntegrator.a:[[Lorg/apache/commons/math3/RealFieldElement; (4, 4)
	547 iload (4, 4)
	548 #14 (4, 4)
	549 iconst_1 (4, 4)
	550 isub (4, 4)
	551 aaload (4, 4)
	552 iconst_0 (4, 4)
	553 aaload (4, 4)
	554 invokeinterface (4, 4)
	555 org/apache/commons/math3/RealFieldElement.computeDerivatives:(Lorg/apache/commons/math3/RealFieldElement;[Lorg/apache/commons/math3/RealFieldElement;)[Lorg/apache/commons/math3/RealFieldElement; (4, 4)
	557 0 (4, 4)
	559 checkcast (4, 4)
	560 org/apache/commons/math3/RealFieldElement (4, 4)
	562 astore (4, 4)
	563 #16 (4, 4)
	564 iconst_1 (5, 4)
	565 istore (5, 4)
	566 #17 (5, 4)
	567 iload (5, 4)
	568 #17 (5, 4)
	569 iload (5, 4)
	570 #14 (5, 4)
	571 if_icmpge (5, 4)
	572 46 (5, 4)
	574 aload (5, 4)
	575 #16 (5, 4)
	576 aload (5, 4)
	577 #9 (5, 4)
	578 iload (5, 4)
	579 #17 (5, 4)
	580 aaload (5, 4)
	581 iload (5, 4)
	582 #15 (5, 4)
	583 aaload (5, 4)
	584 aload_0 (5, 4)
	585 getfield (5, 4)
	586 org/apache/commons/math3/ode/nonstiff/EmbeddedRungeKuttaFieldIntegrator.a:[[Lorg/apache/commons/math3/RealFieldElement; (5, 4)
	588 iload (5, 4)
	589 #14 (5, 4)
	590 iconst_1 (5, 4)
	591 isub (5, 4)
	592 aaload (5, 4)
	593 iload (5, 4)
	594 #17 (5, 4)
	595 aaload (5, 4)
	596 invokeinterface (5, 4)
	597 org/apache/commons/math3/RealFieldElement.computeDerivatives:(Lorg/apache/commons/math3/RealFieldElement;[Lorg/apache/commons/math3/RealFieldElement;)[Lorg/apache/commons/math3/RealFieldElement; (5, 4)
	599 0 (5, 4)
	601 invokeinterface (5, 4)
	602 org/apache/commons/math3/RealFieldElement.multiply:(Ljava/lang/Object;)Ljava/lang/Object; (5, 4)
	604 0 (5, 4)
	606 checkcast (5, 4)
	607 org/apache/commons/math3/RealFieldElement (5, 4)
	609 astore (5, 4)
	610 #16 (5, 4)
	611 iinc (5, 4)
	612 #17 (5, 4)
	613 -89 (5, 4)
	614 goto (5, 4)
	615 -47 (5, 4)
	617 aload (4, 4)
	618 #10 (4, 4)
	619 iload (4, 4)
	620 #15 (4, 4)
	621 aload (4, 4)
	622 #8 (4, 4)
	623 iload (4, 4)
	624 #15 (4, 4)
	625 aaload (4, 4)
	626 aload_0 (4, 4)
	627 invokevirtual (4, 4)
	628 org/apache/commons/math3/ode/nonstiff/EmbeddedRungeKuttaFieldIntegrator.getStepSize:()Lorg/apache/commons/math3/RealFieldElement; (4, 4)
	630 aload (4, 4)
	631 #16 (4, 4)
	632 invokeinterface (4, 4)
	633 org/apache/commons/math3/RealFieldElement.computeDerivatives:(Lorg/apache/commons/math3/RealFieldElement;[Lorg/apache/commons/math3/RealFieldElement;)[Lorg/apache/commons/math3/RealFieldElement; (4, 4)
	635 0 (4, 4)
	637 invokeinterface (4, 4)
	638 org/apache/commons/math3/RealFieldElement.multiply:(Ljava/lang/Object;)Ljava/lang/Object; (4, 4)
	640 0 (4, 4)
	642 checkcast (4, 4)
	643 org/apache/commons/math3/RealFieldElement (4, 4)
	645 aastore (4, 4)
	646 iinc (4, 4)
	647 #15 (4, 4)
	648 -89 (4, 4)
	649 goto (4, 4)
	650 -121 (4, 4)
	652 aload (3, 4)
	653 #9 (3, 4)
	654 iload (3, 4)
	655 #14 (3, 4)
	656 aload_0 (3, 4)
	657 aload_0 (3, 4)
	658 invokevirtual (3, 4)
	659 org/apache/commons/math3/ode/nonstiff/EmbeddedRungeKuttaFieldIntegrator.getStepStart:()Lorg/apache/commons/math3/ode/FieldODEStateAndDerivative; (3, 4)
	661 invokevirtual (3, 4)
	662 org/apache/commons/math3/ode/FieldODEStateAndDerivative.getTime:()Lorg/apache/commons/math3/RealFieldElement; (3, 4)
	664 aload_0 (3, 4)
	665 invokevirtual (3, 4)
	666 org/apache/commons/math3/ode/nonstiff/EmbeddedRungeKuttaFieldIntegrator.getStepSize:()Lorg/apache/commons/math3/RealFieldElement; (3, 4)
	668 aload_0 (3, 4)
	669 getfield (3, 4)
	670 org/apache/commons/math3/ode/nonstiff/EmbeddedRungeKuttaFieldIntegrator.c:[Lorg/apache/commons/math3/RealFieldElement; (3, 4)
	672 iload (3, 4)
	673 #14 (3, 4)
	674 iconst_1 (3, 4)
	675 isub (3, 4)
	676 aaload (3, 4)
	677 invokeinterface (3, 4)
	678 org/apache/commons/math3/RealFieldElement.computeDerivatives:(Lorg/apache/commons/math3/RealFieldElement;[Lorg/apache/commons/math3/RealFieldElement;)[Lorg/apache/commons/math3/RealFieldElement; (3, 4)
	680 0 (3, 4)
	682 invokeinterface (3, 4)
	683 org/apache/commons/math3/RealFieldElement.multiply:(Ljava/lang/Object;)Ljava/lang/Object; (3, 4)
	685 0 (3, 4)
	687 checkcast (3, 4)
	688 org/apache/commons/math3/RealFieldElement (3, 4)
	690 aload (3, 4)
	691 #10 (3, 4)
	692 invokevirtual (3, 4)
	693 org/apache/commons/math3/ode/nonstiff/EmbeddedRungeKuttaFieldIntegrator.computeDerivatives:(Lorg/apache/commons/math3/RealFieldElement;[Lorg/apache/commons/math3/RealFieldElement;)[Lorg/apache/commons/math3/RealFieldElement; (3, 4)
	695 aastore (3, 4)
	696 iinc (3, 4)
	697 #14 (3, 4)
	698 -89 (3, 4)
	699 goto (3, 4)
	700 -181 (3, 4)
	702 iconst_0 (3, 4)
	703 istore (3, 4)
	704 #14 (3, 4)
	705 iload (3, 4)
	706 #14 (3, 4)
	707 aload (3, 4)
	708 #5 (3, 4)
	709 arraylength (3, 4)
	710 if_icmpge (3, 4)
	711 109 (3, 4)
	713 aload (3, 4)
	714 #9 (3, 4)
	715 iconst_0 (3, 4)
	716 aaload (3, 4)
	717 iload (3, 4)
	718 #14 (3, 4)
	719 aaload (3, 4)
	720 aload_0 (3, 4)
	721 getfield (3, 4)
	722 org/apache/commons/math3/ode/nonstiff/EmbeddedRungeKuttaFieldIntegrator.b:[Lorg/apache/commons/math3/RealFieldElement; (3, 4)
	724 iconst_0 (3, 4)
	725 aaload (3, 4)
	726 invokeinterface (3, 4)
	727 org/apache/commons/math3/RealFieldElement.computeDerivatives:(Lorg/apache/commons/math3/RealFieldElement;[Lorg/apache/commons/math3/RealFieldElement;)[Lorg/apache/commons/math3/RealFieldElement; (3, 4)
	729 0 (3, 4)
	731 checkcast (3, 4)
	732 org/apache/commons/math3/RealFieldElement (3, 4)
	734 astore (3, 4)
	735 #15 (3, 4)
	736 iconst_1 (4, 4)
	737 istore (4, 4)
	738 #16 (4, 4)
	739 iload (4, 4)
	740 #16 (4, 4)
	741 iload (4, 4)
	742 #7 (4, 4)
	743 if_icmpge (4, 4)
	744 41 (4, 4)
	746 aload (4, 4)
	747 #15 (4, 4)
	748 aload (4, 4)
	749 #9 (4, 4)
	750 iload (4, 4)
	751 #16 (4, 4)
	752 aaload (4, 4)
	753 iload (4, 4)
	754 #14 (4, 4)
	755 aaload (4, 4)
	756 aload_0 (4, 4)
	757 getfield (4, 4)
	758 org/apache/commons/math3/ode/nonstiff/EmbeddedRungeKuttaFieldIntegrator.b:[Lorg/apache/commons/math3/RealFieldElement; (4, 4)
	760 iload (4, 4)
	761 #16 (4, 4)
	762 aaload (4, 4)
	763 invokeinterface (4, 4)
	764 org/apache/commons/math3/RealFieldElement.computeDerivatives:(Lorg/apache/commons/math3/RealFieldElement;[Lorg/apache/commons/math3/RealFieldElement;)[Lorg/apache/commons/math3/RealFieldElement; (4, 4)
	766 0 (4, 4)
	768 invokeinterface (4, 4)
	769 org/apache/commons/math3/RealFieldElement.multiply:(Ljava/lang/Object;)Ljava/lang/Object; (4, 4)
	771 0 (4, 4)
	773 checkcast (4, 4)
	774 org/apache/commons/math3/RealFieldElement (4, 4)
	776 astore (4, 4)
	777 #15 (4, 4)
	778 iinc (4, 4)
	779 #16 (4, 4)
	780 -89 (4, 4)
	781 goto (4, 4)
	782 -42 (4, 4)
	784 aload (3, 4)
	785 #10 (3, 4)
	786 iload (3, 4)
	787 #14 (3, 4)
	788 aload (3, 4)
	789 #8 (3, 4)
	790 iload (3, 4)
	791 #14 (3, 4)
	792 aaload (3, 4)
	793 aload_0 (3, 4)
	794 invokevirtual (3, 4)
	795 org/apache/commons/math3/ode/nonstiff/EmbeddedRungeKuttaFieldIntegrator.getStepSize:()Lorg/apache/commons/math3/RealFieldElement; (3, 4)
	797 aload (3, 4)
	798 #15 (3, 4)
	799 invokeinterface (3, 4)
	800 org/apache/commons/math3/RealFieldElement.computeDerivatives:(Lorg/apache/commons/math3/RealFieldElement;[Lorg/apache/commons/math3/RealFieldElement;)[Lorg/apache/commons/math3/RealFieldElement; (3, 4)
	802 0 (3, 4)
	804 invokeinterface (3, 4)
	805 org/apache/commons/math3/RealFieldElement.multiply:(Ljava/lang/Object;)Ljava/lang/Object; (3, 4)
	807 0 (3, 4)
	809 checkcast (3, 4)
	810 org/apache/commons/math3/RealFieldElement (3, 4)
	812 aastore (3, 4)
	813 iinc (3, 4)
	814 #14 (3, 4)
	815 -89 (3, 4)
	816 goto (3, 4)
	817 -111 (3, 4)
	819 aload_0 (2, 3)
	820 aload (2, 3)
	821 #9 (2, 3)
	822 aload (2, 3)
	823 #8 (2, 3)
	824 aload (2, 3)
	825 #10 (2, 3)
	826 aload_0 (2, 3)
	827 invokevirtual (2, 3)
	828 org/apache/commons/math3/ode/nonstiff/EmbeddedRungeKuttaFieldIntegrator.getStepSize:()Lorg/apache/commons/math3/RealFieldElement; (2, 3)
	830 invokevirtual (2, 3)
	831 org/apache/commons/math3/ode/nonstiff/EmbeddedRungeKuttaFieldIntegrator.estimateError:([[Lorg/apache/commons/math3/RealFieldElement;[Lorg/apache/commons/math3/RealFieldElement;[Lorg/apache/commons/math3/RealFieldElement;Lorg/apache/commons/math3/RealFieldElement;)Lorg/apache/commons/math3/RealFieldElement; (2, 3)
	833 astore (2, 3)
	834 #13 (2, 3)
	835 aload (3, 1)
	836 #13 (3, 1)
	837 dconst_1 (3, 1)
	838 invokeinterface (3, 1)
	839 org/apache/commons/math3/RealFieldElement.getStepStart:()Lorg/apache/commons/math3/ode/FieldODEStateAndDerivative; (3, 1)
	841 0 (3, 1)
	843 checkcast (3, 1)
	844 org/apache/commons/math3/RealFieldElement (3, 1)
	846 invokeinterface (3, 1)
	847 org/apache/commons/math3/RealFieldElement.org/apache/commons/math3/util/MathArrays (3, 1)
	849 0 (3, 1)
	851 dconst_0 (3, 1)
	852 dcmpl (3, 1)
	853 iflt (3, 1)
	854 -697 (3, 1)
	856 aload_0 (3, 1)
	857 getfield (3, 1)
	858 org/apache/commons/math3/ode/nonstiff/EmbeddedRungeKuttaFieldIntegrator.maxGrowth:Lorg/apache/commons/math3/RealFieldElement; (3, 1)
	860 aload_0 (3, 1)
	861 getfield (3, 1)
	862 org/apache/commons/math3/ode/nonstiff/EmbeddedRungeKuttaFieldIntegrator.minReduction:Lorg/apache/commons/math3/RealFieldElement; (3, 1)
	864 aload_0 (3, 1)
	865 getfield (3, 1)
	866 org/apache/commons/math3/ode/nonstiff/EmbeddedRungeKuttaFieldIntegrator.safety:Lorg/apache/commons/math3/RealFieldElement; (3, 1)
	868 aload (3, 1)
	869 #13 (3, 1)
	870 aload_0 (3, 1)
	871 getfield (3, 1)
	872 org/apache/commons/math3/ode/nonstiff/EmbeddedRungeKuttaFieldIntegrator.exp:Lorg/apache/commons/math3/RealFieldElement; (3, 1)
	874 invokeinterface (3, 1)
	875 org/apache/commons/math3/RealFieldElement.org/apache/commons/math3/util/MathUtils (3, 1)
	877 0 (3, 1)
	879 invokeinterface (3, 1)
	880 org/apache/commons/math3/RealFieldElement.computeDerivatives:(Lorg/apache/commons/math3/RealFieldElement;[Lorg/apache/commons/math3/RealFieldElement;)[Lorg/apache/commons/math3/RealFieldElement; (3, 1)
	882 0 (3, 1)
	884 checkcast (3, 1)
	885 org/apache/commons/math3/RealFieldElement (3, 1)
	887 invokestatic (3, 1)
	888 org/apache/commons/math3/util/MathUtils.max:(Lorg/apache/commons/math3/RealFieldElement;Lorg/apache/commons/math3/RealFieldElement;)Lorg/apache/commons/math3/RealFieldElement; (3, 1)
	890 invokestatic (3, 1)
	891 org/apache/commons/math3/util/MathUtils.min:(Lorg/apache/commons/math3/RealFieldElement;Lorg/apache/commons/math3/RealFieldElement;)Lorg/apache/commons/math3/RealFieldElement; (3, 1)
	893 astore (3, 1)
	894 #14 (3, 1)
	895 aload_0 (3, 4)
	896 aload_0 (3, 4)
	897 invokevirtual (3, 4)
	898 org/apache/commons/math3/ode/nonstiff/EmbeddedRungeKuttaFieldIntegrator.getStepSize:()Lorg/apache/commons/math3/RealFieldElement; (3, 4)
	900 aload (3, 4)
	901 #14 (3, 4)
	902 invokeinterface (3, 4)
	903 org/apache/commons/math3/RealFieldElement.computeDerivatives:(Lorg/apache/commons/math3/RealFieldElement;[Lorg/apache/commons/math3/RealFieldElement;)[Lorg/apache/commons/math3/RealFieldElement; (3, 4)
	905 0 (3, 4)
	907 checkcast (3, 4)
	908 org/apache/commons/math3/RealFieldElement (3, 4)
	910 iload (3, 4)
	911 #6 (3, 4)
	912 iconst_0 (3, 4)
	913 invokevirtual (3, 4)
	914 org/apache/commons/math3/ode/nonstiff/EmbeddedRungeKuttaFieldIntegrator.filterStep:(Lorg/apache/commons/math3/RealFieldElement;ZZ)Lorg/apache/commons/math3/RealFieldElement; (3, 4)
	916 astore (3, 4)
	917 #11 (3, 4)
	918 goto (2, 3)
	919 -762 (2, 3)
	921 aload_0 (0, 4)
	922 invokevirtual (0, 4)
	923 org/apache/commons/math3/ode/nonstiff/EmbeddedRungeKuttaFieldIntegrator.getStepStart:()Lorg/apache/commons/math3/ode/FieldODEStateAndDerivative; (0, 4)
	925 invokevirtual (0, 4)
	926 org/apache/commons/math3/ode/FieldODEStateAndDerivative.getTime:()Lorg/apache/commons/math3/RealFieldElement; (0, 4)
	928 aload_0 (0, 4)
	929 invokevirtual (0, 4)
	930 org/apache/commons/math3/ode/nonstiff/EmbeddedRungeKuttaFieldIntegrator.getStepSize:()Lorg/apache/commons/math3/RealFieldElement; (0, 4)
	932 invokeinterface (0, 4)
	933 org/apache/commons/math3/RealFieldElement.multiply:(Ljava/lang/Object;)Ljava/lang/Object; (0, 4)
	935 0 (0, 4)
	937 checkcast (0, 4)
	938 org/apache/commons/math3/RealFieldElement (0, 4)
	940 astore (0, 4)
	941 #14 (0, 4)
	942 aload_0 (0, 4)
	943 getfield (0, 4)
	944 org/apache/commons/math3/ode/nonstiff/EmbeddedRungeKuttaFieldIntegrator.fsal:I (0, 4)
	946 iflt (0, 4)
	947 13 (0, 4)
	949 aload (0, 4)
	950 #9 (0, 4)
	951 aload_0 (0, 4)
	952 getfield (0, 4)
	953 org/apache/commons/math3/ode/nonstiff/EmbeddedRungeKuttaFieldIntegrator.fsal:I (0, 4)
	955 aaload (0, 4)
	956 goto (0, 4)
	957 11 (0, 4)
	959 aload_0 (0, 4)
	960 aload (0, 4)
	961 #14 (0, 4)
	962 aload (0, 4)
	963 #10 (0, 4)
	964 invokevirtual (0, 4)
	965 org/apache/commons/math3/ode/nonstiff/EmbeddedRungeKuttaFieldIntegrator.computeDerivatives:(Lorg/apache/commons/math3/RealFieldElement;[Lorg/apache/commons/math3/RealFieldElement;)[Lorg/apache/commons/math3/RealFieldElement; (0, 4)
	967 astore (0, 4)
	968 #15 (0, 4)
	969 new (0, 4)
	970 org/apache/commons/math3/ode/FieldODEStateAndDerivative (0, 4)
	972 dup (0, 4)
	973 aload (0, 4)
	974 #14 (0, 4)
	975 aload (0, 4)
	976 #10 (0, 4)
	977 aload (0, 4)
	978 #15 (0, 4)
	979 invokespecial (0, 4)
	980 org/apache/commons/math3/ode/FieldODEStateAndDerivative.<init>:(Lorg/apache/commons/math3/RealFieldElement;[Lorg/apache/commons/math3/RealFieldElement;[Lorg/apache/commons/math3/RealFieldElement;)V (0, 4)
	982 astore (0, 4)
	983 #16 (0, 4)
	984 aload (0, 4)
	985 #10 (0, 4)
	986 iconst_0 (0, 4)
	987 aload (0, 4)
	988 #8 (0, 4)
	989 iconst_0 (0, 4)
	990 aload (0, 4)
	991 #5 (0, 4)
	992 arraylength (0, 4)
	993 invokestatic (0, 4)
	994 java/lang/System.arraycopy:(Ljava/lang/Object;ILjava/lang/Object;II)V (0, 4)
	996 aload_0 (1, 4)
	997 aload_0 (1, 4)
	998 aload_0 (1, 4)
	999 iload (1, 4)
	1000 #6 (1, 4)
	1001 aload (1, 4)
	1002 #9 (1, 4)
	1003 aload_0 (1, 4)
	1004 invokevirtual (1, 4)
	1005 org/apache/commons/math3/ode/nonstiff/EmbeddedRungeKuttaFieldIntegrator.getStepStart:()Lorg/apache/commons/math3/ode/FieldODEStateAndDerivative; (1, 4)
	1007 aload (1, 4)
	1008 #16 (1, 4)
	1009 aload_1 (1, 4)
	1010 invokevirtual (1, 4)
	1011 org/apache/commons/math3/ode/FieldExpandableODE.getMapper:()Lorg/apache/commons/math3/ode/FieldEquationsMapper; (1, 4)
	1013 invokevirtual (1, 4)
	1014 org/apache/commons/math3/ode/nonstiff/EmbeddedRungeKuttaFieldIntegrator.createInterpolator:(Z[[Lorg/apache/commons/math3/RealFieldElement;Lorg/apache/commons/math3/ode/FieldODEStateAndDerivative;Lorg/apache/commons/math3/ode/FieldODEStateAndDerivative;Lorg/apache/commons/math3/ode/FieldEquationsMapper;)Lorg/apache/commons/math3/ode/nonstiff/RungeKuttaFieldStepInterpolator; (1, 4)
	1016 aload_3 (1, 4)
	1017 invokevirtual (1, 4)
	1018 org/apache/commons/math3/ode/nonstiff/EmbeddedRungeKuttaFieldIntegrator.acceptStep:(Lorg/apache/commons/math3/ode/sampling/AbstractFieldStepInterpolator;Lorg/apache/commons/math3/RealFieldElement;)Lorg/apache/commons/math3/ode/FieldODEStateAndDerivative; (1, 4)
	1020 invokevirtual (1, 4)
	1021 org/apache/commons/math3/ode/nonstiff/EmbeddedRungeKuttaFieldIntegrator.setStepStart:(Lorg/apache/commons/math3/ode/FieldODEStateAndDerivative;)V (1, 4)
	1023 aload_0 (2, 1)
	1024 invokevirtual (2, 1)
	1025 org/apache/commons/math3/ode/nonstiff/EmbeddedRungeKuttaFieldIntegrator.isLastStep:()Z (2, 1)
	1027 ifne (2, 1)
	1028 255 (2, 1)
	1030 aload_0 (2, 4)
	1031 getfield (2, 4)
	1032 org/apache/commons/math3/ode/nonstiff/EmbeddedRungeKuttaFieldIntegrator.maxGrowth:Lorg/apache/commons/math3/RealFieldElement; (2, 4)
	1034 aload_0 (2, 4)
	1035 getfield (2, 4)
	1036 org/apache/commons/math3/ode/nonstiff/EmbeddedRungeKuttaFieldIntegrator.minReduction:Lorg/apache/commons/math3/RealFieldElement; (2, 4)
	1038 aload_0 (2, 4)
	1039 getfield (2, 4)
	1040 org/apache/commons/math3/ode/nonstiff/EmbeddedRungeKuttaFieldIntegrator.safety:Lorg/apache/commons/math3/RealFieldElement; (2, 4)
	1042 aload (2, 4)
	1043 #13 (2, 4)
	1044 aload_0 (2, 4)
	1045 getfield (2, 4)
	1046 org/apache/commons/math3/ode/nonstiff/EmbeddedRungeKuttaFieldIntegrator.exp:Lorg/apache/commons/math3/RealFieldElement; (2, 4)
	1048 invokeinterface (2, 4)
	1049 org/apache/commons/math3/RealFieldElement.org/apache/commons/math3/util/MathUtils (2, 4)
	1051 0 (2, 4)
	1053 invokeinterface (2, 4)
	1054 org/apache/commons/math3/RealFieldElement.computeDerivatives:(Lorg/apache/commons/math3/RealFieldElement;[Lorg/apache/commons/math3/RealFieldElement;)[Lorg/apache/commons/math3/RealFieldElement; (2, 4)
	1056 0 (2, 4)
	1058 checkcast (2, 4)
	1059 org/apache/commons/math3/RealFieldElement (2, 4)
	1061 invokestatic (2, 4)
	1062 org/apache/commons/math3/util/MathUtils.max:(Lorg/apache/commons/math3/RealFieldElement;Lorg/apache/commons/math3/RealFieldElement;)Lorg/apache/commons/math3/RealFieldElement; (2, 4)
	1064 invokestatic (2, 4)
	1065 org/apache/commons/math3/util/MathUtils.min:(Lorg/apache/commons/math3/RealFieldElement;Lorg/apache/commons/math3/RealFieldElement;)Lorg/apache/commons/math3/RealFieldElement; (2, 4)
	1067 astore (2, 4)
	1068 #17 (2, 4)
	1069 aload_0 (2, 4)
	1070 invokevirtual (2, 4)
	1071 org/apache/commons/math3/ode/nonstiff/EmbeddedRungeKuttaFieldIntegrator.getStepSize:()Lorg/apache/commons/math3/RealFieldElement; (2, 4)
	1073 aload (2, 4)
	1074 #17 (2, 4)
	1075 invokeinterface (2, 4)
	1076 org/apache/commons/math3/RealFieldElement.computeDerivatives:(Lorg/apache/commons/math3/RealFieldElement;[Lorg/apache/commons/math3/RealFieldElement;)[Lorg/apache/commons/math3/RealFieldElement; (2, 4)
	1078 0 (2, 4)
	1080 checkcast (2, 4)
	1081 org/apache/commons/math3/RealFieldElement (2, 4)
	1083 astore (2, 4)
	1084 #18 (2, 4)
	1085 aload_0 (2, 4)
	1086 invokevirtual (2, 4)
	1087 org/apache/commons/math3/ode/nonstiff/EmbeddedRungeKuttaFieldIntegrator.getStepStart:()Lorg/apache/commons/math3/ode/FieldODEStateAndDerivative; (2, 4)
	1089 invokevirtual (2, 4)
	1090 org/apache/commons/math3/ode/FieldODEStateAndDerivative.getTime:()Lorg/apache/commons/math3/RealFieldElement; (2, 4)
	1092 aload (2, 4)
	1093 #18 (2, 4)
	1094 invokeinterface (2, 4)
	1095 org/apache/commons/math3/RealFieldElement.multiply:(Ljava/lang/Object;)Ljava/lang/Object; (2, 4)
	1097 0 (2, 4)
	1099 checkcast (2, 4)
	1100 org/apache/commons/math3/RealFieldElement (2, 4)
	1102 astore (2, 4)
	1103 #19 (2, 4)
	1104 iload (2, 4)
	1105 #6 (2, 4)
	1106 ifeq (2, 4)
	1107 32 (2, 4)
	1109 aload (2, 4)
	1110 #19 (2, 4)
	1111 aload_3 (2, 4)
	1112 invokeinterface (2, 4)
	1113 org/apache/commons/math3/RealFieldElement.getReal:()D (2, 4)
	1115 0 (2, 4)
	1117 checkcast (2, 4)
	1118 org/apache/commons/math3/RealFieldElement (2, 4)
	1120 invokeinterface (2, 4)
	1121 org/apache/commons/math3/RealFieldElement.org/apache/commons/math3/util/MathArrays (2, 4)
	1123 0 (2, 4)
	1125 dconst_0 (2, 4)
	1126 dcmpl (2, 4)
	1127 iflt (2, 4)
	1128 7 (2, 4)
	1130 iconst_1 (2, 4)
	1131 goto (2, 4)
	1132 33 (2, 4)
	1134 iconst_0 (2, 4)
	1135 goto (2, 4)
	1136 29 (2, 4)
	1138 aload (2, 4)
	1139 #19 (2, 4)
	1140 aload_3 (2, 4)
	1141 invokeinterface (2, 4)
	1142 org/apache/commons/math3/RealFieldElement.getReal:()D (2, 4)
	1144 0 (2, 4)
	1146 checkcast (2, 4)
	1147 org/apache/commons/math3/RealFieldElement (2, 4)
	1149 invokeinterface (2, 4)
	1150 org/apache/commons/math3/RealFieldElement.org/apache/commons/math3/util/MathArrays (2, 4)
	1152 0 (2, 4)
	1154 dconst_0 (2, 4)
	1155 dcmpg (2, 4)
	1156 ifgt (2, 4)
	1157 7 (2, 4)
	1159 iconst_1 (2, 4)
	1160 goto (2, 4)
	1161 4 (2, 4)
	1163 iconst_0 (2, 4)
	1164 istore (2, 4)
	1165 #20 (2, 4)
	1166 aload_0 (2, 4)
	1167 aload (2, 4)
	1168 #18 (2, 4)
	1169 iload (2, 4)
	1170 #6 (2, 4)
	1171 iload (2, 4)
	1172 #20 (2, 4)
	1173 invokevirtual (2, 4)
	1174 org/apache/commons/math3/ode/nonstiff/EmbeddedRungeKuttaFieldIntegrator.filterStep:(Lorg/apache/commons/math3/RealFieldElement;ZZ)Lorg/apache/commons/math3/RealFieldElement; (2, 4)
	1176 astore (2, 4)
	1177 #11 (2, 4)
	1178 aload_0 (2, 4)
	1179 invokevirtual (2, 4)
	1180 org/apache/commons/math3/ode/nonstiff/EmbeddedRungeKuttaFieldIntegrator.getStepStart:()Lorg/apache/commons/math3/ode/FieldODEStateAndDerivative; (2, 4)
	1182 invokevirtual (2, 4)
	1183 org/apache/commons/math3/ode/FieldODEStateAndDerivative.getTime:()Lorg/apache/commons/math3/RealFieldElement; (2, 4)
	1185 aload (2, 4)
	1186 #11 (2, 4)
	1187 invokeinterface (2, 4)
	1188 org/apache/commons/math3/RealFieldElement.multiply:(Ljava/lang/Object;)Ljava/lang/Object; (2, 4)
	1190 0 (2, 4)
	1192 checkcast (2, 4)
	1193 org/apache/commons/math3/RealFieldElement (2, 4)
	1195 astore (2, 4)
	1196 #21 (2, 4)
	1197 iload (2, 4)
	1198 #6 (2, 4)
	1199 ifeq (2, 4)
	1200 32 (2, 4)
	1202 aload (2, 4)
	1203 #21 (2, 4)
	1204 aload_3 (2, 4)
	1205 invokeinterface (2, 4)
	1206 org/apache/commons/math3/RealFieldElement.getReal:()D (2, 4)
	1208 0 (2, 4)
	1210 checkcast (2, 4)
	1211 org/apache/commons/math3/RealFieldElement (2, 4)
	1213 invokeinterface (2, 4)
	1214 org/apache/commons/math3/RealFieldElement.org/apache/commons/math3/util/MathArrays (2, 4)
	1216 0 (2, 4)
	1218 dconst_0 (2, 4)
	1219 dcmpl (2, 4)
	1220 iflt (2, 4)
	1221 7 (2, 4)
	1223 iconst_1 (2, 4)
	1224 goto (2, 4)
	1225 33 (2, 4)
	1227 iconst_0 (2, 4)
	1228 goto (2, 4)
	1229 29 (2, 4)
	1231 aload (2, 4)
	1232 #21 (2, 4)
	1233 aload_3 (2, 4)
	1234 invokeinterface (2, 4)
	1235 org/apache/commons/math3/RealFieldElement.getReal:()D (2, 4)
	1237 0 (2, 4)
	1239 checkcast (2, 4)
	1240 org/apache/commons/math3/RealFieldElement (2, 4)
	1242 invokeinterface (2, 4)
	1243 org/apache/commons/math3/RealFieldElement.org/apache/commons/math3/util/MathArrays (2, 4)
	1245 0 (2, 4)
	1247 dconst_0 (2, 4)
	1248 dcmpg (2, 4)
	1249 ifgt (2, 4)
	1250 7 (2, 4)
	1252 iconst_1 (2, 4)
	1253 goto (2, 4)
	1254 4 (2, 4)
	1256 iconst_0 (2, 4)
	1257 istore (2, 4)
	1258 #22 (2, 4)
	1259 iload (3, 1)
	1260 #22 (3, 1)
	1261 ifeq (3, 1)
	1262 21 (3, 1)
	1264 aload_3 (3, 1)
	1265 aload_0 (3, 1)
	1266 invokevirtual (3, 1)
	1267 org/apache/commons/math3/ode/nonstiff/EmbeddedRungeKuttaFieldIntegrator.getStepStart:()Lorg/apache/commons/math3/ode/FieldODEStateAndDerivative; (3, 1)
	1269 invokevirtual (3, 1)
	1270 org/apache/commons/math3/ode/FieldODEStateAndDerivative.getTime:()Lorg/apache/commons/math3/RealFieldElement; (3, 1)
	1272 invokeinterface (3, 1)
	1273 org/apache/commons/math3/RealFieldElement.getReal:()D (3, 1)
	1275 0 (3, 1)
	1277 checkcast (3, 1)
	1278 org/apache/commons/math3/RealFieldElement (3, 1)
	1280 astore (3, 1)
	1281 #11 (3, 1)
	1282 aload_0 (0, 3)
	1283 invokevirtual (0, 3)
	1284 org/apache/commons/math3/ode/nonstiff/EmbeddedRungeKuttaFieldIntegrator.isLastStep:()Z (0, 3)
	1286 ifeq (0, 3)
	1287 -1155 (0, 3)
	1289 aload_0 (0, 3)
	1290 invokevirtual (0, 3)
	1291 org/apache/commons/math3/ode/nonstiff/EmbeddedRungeKuttaFieldIntegrator.getStepStart:()Lorg/apache/commons/math3/ode/FieldODEStateAndDerivative; (0, 3)
	1293 astore (0, 3)
	1294 #13 (0, 3)
	1295 aload_0 (0, 3)
	1296 invokevirtual (0, 3)
	1297 org/apache/commons/math3/ode/nonstiff/EmbeddedRungeKuttaFieldIntegrator.resetInternalState:()V (0, 3)
	1299 aload (0, 3)
	1300 #13 (0, 3)
	1301 areturn (0, 3)

Method: getMinReduction
	0 aload_0 (0, 0)
	1 getfield (0, 0)
	2 org/apache/commons/math3/ode/nonstiff/EmbeddedRungeKuttaFieldIntegrator.minReduction:Lorg/apache/commons/math3/RealFieldElement; (0, 0)
	4 areturn (0, 0)

Method: setMinReduction
	0 aload_0 (0, 0)
	1 aload_1 (0, 0)
	2 putfield (0, 0)
	3 org/apache/commons/math3/ode/nonstiff/EmbeddedRungeKuttaFieldIntegrator.minReduction:Lorg/apache/commons/math3/RealFieldElement; (0, 0)
	5 return (0, 0)

Method: getMaxGrowth
	0 aload_0 (0, 0)
	1 getfield (0, 0)
	2 org/apache/commons/math3/ode/nonstiff/EmbeddedRungeKuttaFieldIntegrator.maxGrowth:Lorg/apache/commons/math3/RealFieldElement; (0, 0)
	4 areturn (0, 0)

Method: setMaxGrowth
	0 aload_0 (0, 0)
	1 aload_1 (0, 0)
	2 putfield (0, 0)
	3 org/apache/commons/math3/ode/nonstiff/EmbeddedRungeKuttaFieldIntegrator.maxGrowth:Lorg/apache/commons/math3/RealFieldElement; (0, 0)
	5 return (0, 0)

