Method: <init>
	0 aload_0 (0, 0)
	1 ldc (0, 0)
	2 Euler (0, 0)
	3 getstatic (0, 0)
	4 org/apache/commons/math3/ode/nonstiff/EulerIntegrator.STATIC_C:[D (0, 0)
	6 getstatic (0, 0)
	7 org/apache/commons/math3/ode/nonstiff/EulerIntegrator.STATIC_A:[[D (0, 0)
	9 getstatic (0, 0)
	10 org/apache/commons/math3/ode/nonstiff/EulerIntegrator.STATIC_B:[D (0, 0)
	12 new (0, 0)
	13 org/apache/commons/math3/ode/nonstiff/EulerStepInterpolator (0, 0)
	15 dup (0, 0)
	16 invokespecial (0, 0)
	17 org/apache/commons/math3/ode/nonstiff/EulerStepInterpolator.<init>:()V (0, 0)
	19 dload_1 (0, 0)
	20 invokespecial (0, 0)
	21 org/apache/commons/math3/ode/nonstiff/RungeKuttaIntegrator.<init>:(Ljava/lang/String;[D[[D[DLorg/apache/commons/math3/ode/nonstiff/RungeKuttaStepInterpolator;D)V (0, 0)
	23 return (0, 0)

Method: <clinit>
	0 iconst_0 (0, 0)
	1 newarray (0, 0)
	2 7 (0, 0)
	3 putstatic (0, 0)
	4 org/apache/commons/math3/ode/nonstiff/EulerIntegrator.STATIC_C:[D (0, 0)
	6 iconst_0 (0, 0)
	7 anewarray (0, 0)
	8 [D (0, 0)
	10 putstatic (0, 0)
	11 org/apache/commons/math3/ode/nonstiff/EulerIntegrator.STATIC_A:[[D (0, 0)
	13 iconst_1 (0, 0)
	14 newarray (0, 0)
	15 7 (0, 0)
	16 dup (0, 0)
	17 iconst_0 (0, 0)
	18 dconst_1 (0, 0)
	19 dastore (0, 0)
	20 putstatic (0, 0)
	21 org/apache/commons/math3/ode/nonstiff/EulerIntegrator.STATIC_B:[D (0, 0)
	23 return (0, 0)

