Method: <init>
	0 aload_0 (0, 0)
	1 ldc (0, 0)
	2 Gragg-Bulirsch-Stoer (0, 0)
	3 dload_1 (0, 0)
	4 dload_3 (0, 0)
	5 aload (0, 0)
	6 #5 (0, 0)
	7 aload (0, 0)
	8 #6 (0, 0)
	9 invokespecial (0, 0)
	10 org/apache/commons/math3/ode/nonstiff/AdaptiveStepsizeIntegrator.<init>:(Ljava/lang/String;DD[D[D)V (0, 0)
	12 aload_0 (0, 0)
	13 iconst_1 (0, 0)
	14 iconst_m1 (0, 0)
	15 iconst_m1 (0, 0)
	16 ldc2_w (0, 0)
	17 -1.0 (0, 0)
	19 invokevirtual (0, 0)
	20 org/apache/commons/math3/ode/nonstiff/GraggBulirschStoerIntegrator.setStabilityCheck:(ZIID)V (0, 0)
	22 aload_0 (0, 0)
	23 ldc2_w (0, 0)
	24 -1.0 (0, 0)
	26 ldc2_w (0, 0)
	27 -1.0 (0, 0)
	29 ldc2_w (0, 0)
	30 -1.0 (0, 0)
	32 ldc2_w (0, 0)
	33 -1.0 (0, 0)
	35 invokevirtual (0, 0)
	36 org/apache/commons/math3/ode/nonstiff/GraggBulirschStoerIntegrator.setControlFactors:(DDDD)V (0, 0)
	38 aload_0 (0, 0)
	39 iconst_m1 (0, 0)
	40 ldc2_w (0, 0)
	41 -1.0 (0, 0)
	43 ldc2_w (0, 0)
	44 -1.0 (0, 0)
	46 invokevirtual (0, 0)
	47 org/apache/commons/math3/ode/nonstiff/GraggBulirschStoerIntegrator.setOrderControl:(IDD)V (0, 0)
	49 aload_0 (0, 0)
	50 iconst_1 (0, 0)
	51 iconst_m1 (0, 0)
	52 invokevirtual (0, 0)
	53 org/apache/commons/math3/ode/nonstiff/GraggBulirschStoerIntegrator.setInterpolationControl:(ZI)V (0, 0)
	55 return (0, 0)

Method: setStabilityCheck
	0 aload_0 (1, 4)
	1 iload_1 (1, 4)
	2 putfield (1, 4)
	3 org/apache/commons/math3/ode/nonstiff/GraggBulirschStoerIntegrator.performTest:Z (1, 4)
	5 aload_0 (1, 4)
	6 iload_2 (1, 4)
	7 ifgt (1, 4)
	8 7 (1, 4)
	10 iconst_2 (1, 4)
	11 goto (1, 4)
	12 4 (1, 4)
	14 iload_2 (1, 4)
	15 putfield (1, 4)
	16 org/apache/commons/math3/ode/nonstiff/GraggBulirschStoerIntegrator.maxIter:I (1, 4)
	18 aload_0 (1, 4)
	19 iload_3 (1, 4)
	20 ifgt (1, 4)
	21 7 (1, 4)
	23 iconst_1 (1, 4)
	24 goto (1, 4)
	25 4 (1, 4)
	27 iload_3 (1, 4)
	28 putfield (1, 4)
	29 org/apache/commons/math3/ode/nonstiff/GraggBulirschStoerIntegrator.maxChecks:I (1, 4)
	31 dload (2, 1)
	32 #4 (2, 1)
	33 ldc2_w (2, 1)
	34 0.0001 (2, 1)
	36 dcmpg (2, 1)
	37 iflt (2, 1)
	38 12 (2, 1)
	40 dload (2, 1)
	41 #4 (2, 1)
	42 ldc2_w (2, 1)
	43 0.9999 (2, 1)
	45 dcmpl (2, 1)
	46 ifle (2, 1)
	47 13 (2, 1)
	49 aload_0 (2, 1)
	50 ldc2_w (2, 1)
	51 0.5 (2, 1)
	53 putfield (2, 1)
	54 org/apache/commons/math3/ode/nonstiff/GraggBulirschStoerIntegrator.stabilityReduction:D (2, 1)
	56 goto (2, 1)
	57 9 (2, 1)
	59 aload_0 (3, 2)
	60 dload (3, 2)
	61 #4 (3, 2)
	62 putfield (3, 2)
	63 org/apache/commons/math3/ode/nonstiff/GraggBulirschStoerIntegrator.stabilityReduction:D (3, 2)
	65 return (0, 4)

Method: setControlFactors
	0 dload_1 (1, 1)
	1 ldc2_w (1, 1)
	2 0.0001 (1, 1)
	4 dcmpg (1, 1)
	5 iflt (1, 1)
	6 11 (1, 1)
	8 dload_1 (1, 1)
	9 ldc2_w (1, 1)
	10 0.9999 (1, 1)
	12 dcmpl (1, 1)
	13 ifle (1, 1)
	14 13 (1, 1)
	16 aload_0 (1, 1)
	17 ldc2_w (1, 1)
	18 0.65 (1, 1)
	20 putfield (1, 1)
	21 org/apache/commons/math3/ode/nonstiff/GraggBulirschStoerIntegrator.stepControl1:D (1, 1)
	23 goto (1, 1)
	24 8 (1, 1)
	26 aload_0 (2, 2)
	27 dload_1 (2, 2)
	28 putfield (2, 2)
	29 org/apache/commons/math3/ode/nonstiff/GraggBulirschStoerIntegrator.stepControl1:D (2, 2)
	31 dload_3 (1, 1)
	32 ldc2_w (1, 1)
	33 0.0001 (1, 1)
	35 dcmpg (1, 1)
	36 iflt (1, 1)
	37 11 (1, 1)
	39 dload_3 (1, 1)
	40 ldc2_w (1, 1)
	41 0.9999 (1, 1)
	43 dcmpl (1, 1)
	44 ifle (1, 1)
	45 13 (1, 1)
	47 aload_0 (1, 1)
	48 ldc2_w (1, 1)
	49 0.94 (1, 1)
	51 putfield (1, 1)
	52 org/apache/commons/math3/ode/nonstiff/GraggBulirschStoerIntegrator.stepControl2:D (1, 1)
	54 goto (1, 1)
	55 8 (1, 1)
	57 aload_0 (2, 2)
	58 dload_3 (2, 2)
	59 putfield (2, 2)
	60 org/apache/commons/math3/ode/nonstiff/GraggBulirschStoerIntegrator.stepControl2:D (2, 2)
	62 dload (1, 1)
	63 #5 (1, 1)
	64 ldc2_w (1, 1)
	65 0.0001 (1, 1)
	67 dcmpg (1, 1)
	68 iflt (1, 1)
	69 12 (1, 1)
	71 dload (1, 1)
	72 #5 (1, 1)
	73 ldc2_w (1, 1)
	74 0.9999 (1, 1)
	76 dcmpl (1, 1)
	77 ifle (1, 1)
	78 13 (1, 1)
	80 aload_0 (1, 1)
	81 ldc2_w (1, 1)
	82 0.02 (1, 1)
	84 putfield (1, 1)
	85 org/apache/commons/math3/ode/nonstiff/GraggBulirschStoerIntegrator.stepControl3:D (1, 1)
	87 goto (1, 1)
	88 9 (1, 1)
	90 aload_0 (2, 2)
	91 dload (2, 2)
	92 #5 (2, 2)
	93 putfield (2, 2)
	94 org/apache/commons/math3/ode/nonstiff/GraggBulirschStoerIntegrator.stepControl3:D (2, 2)
	96 dload (1, 1)
	97 #7 (1, 1)
	98 ldc2_w (1, 1)
	99 1.0001 (1, 1)
	101 dcmpg (1, 1)
	102 iflt (1, 1)
	103 12 (1, 1)
	105 dload (1, 1)
	106 #7 (1, 1)
	107 ldc2_w (1, 1)
	108 999.9 (1, 1)
	110 dcmpl (1, 1)
	111 ifle (1, 1)
	112 13 (1, 1)
	114 aload_0 (1, 1)
	115 ldc2_w (1, 1)
	116 4.0 (1, 1)
	118 putfield (1, 1)
	119 org/apache/commons/math3/ode/nonstiff/GraggBulirschStoerIntegrator.stepControl4:D (1, 1)
	121 goto (1, 1)
	122 9 (1, 1)
	124 aload_0 (2, 2)
	125 dload (2, 2)
	126 #7 (2, 2)
	127 putfield (2, 2)
	128 org/apache/commons/math3/ode/nonstiff/GraggBulirschStoerIntegrator.stepControl4:D (2, 2)
	130 return (0, 0)

Method: setOrderControl
	0 iload_1 (1, 1)
	1 bipush (1, 1)
	2 6 (1, 1)
	3 if_icmple (1, 1)
	4 9 (1, 1)
	6 iload_1 (1, 1)
	7 iconst_2 (1, 1)
	8 irem (1, 1)
	9 ifeq (1, 1)
	10 9 (1, 1)
	12 aload_0 (1, 1)
	13 bipush (1, 1)
	14 18 (1, 1)
	15 putfield (1, 1)
	16 org/apache/commons/math3/ode/nonstiff/GraggBulirschStoerIntegrator.maxOrder:I (1, 1)
	18 dload_2 (1, 1)
	19 ldc2_w (1, 1)
	20 0.0001 (1, 1)
	22 dcmpg (1, 1)
	23 iflt (1, 1)
	24 11 (1, 1)
	26 dload_2 (1, 1)
	27 ldc2_w (1, 1)
	28 0.9999 (1, 1)
	30 dcmpl (1, 1)
	31 ifle (1, 1)
	32 13 (1, 1)
	34 aload_0 (1, 1)
	35 ldc2_w (1, 1)
	36 0.8 (1, 1)
	38 putfield (1, 1)
	39 org/apache/commons/math3/ode/nonstiff/GraggBulirschStoerIntegrator.orderControl1:D (1, 1)
	41 goto (1, 1)
	42 8 (1, 1)
	44 aload_0 (2, 2)
	45 dload_2 (2, 2)
	46 putfield (2, 2)
	47 org/apache/commons/math3/ode/nonstiff/GraggBulirschStoerIntegrator.orderControl1:D (2, 2)
	49 dload (1, 1)
	50 #4 (1, 1)
	51 ldc2_w (1, 1)
	52 0.0001 (1, 1)
	54 dcmpg (1, 1)
	55 iflt (1, 1)
	56 12 (1, 1)
	58 dload (1, 1)
	59 #4 (1, 1)
	60 ldc2_w (1, 1)
	61 0.9999 (1, 1)
	63 dcmpl (1, 1)
	64 ifle (1, 1)
	65 13 (1, 1)
	67 aload_0 (1, 1)
	68 ldc2_w (1, 1)
	69 0.9 (1, 1)
	71 putfield (1, 1)
	72 org/apache/commons/math3/ode/nonstiff/GraggBulirschStoerIntegrator.orderControl2:D (1, 1)
	74 goto (1, 1)
	75 9 (1, 1)
	77 aload_0 (2, 2)
	78 dload (2, 2)
	79 #4 (2, 2)
	80 putfield (2, 2)
	81 org/apache/commons/math3/ode/nonstiff/GraggBulirschStoerIntegrator.orderControl2:D (2, 2)
	83 aload_0 (0, 0)
	84 invokespecial (0, 0)
	85 org/apache/commons/math3/ode/nonstiff/GraggBulirschStoerIntegrator.initializeArrays:()V (0, 0)
	87 return (0, 0)

Method: addStepHandler
	0 aload_0 (0, 0)
	1 aload_1 (0, 0)
	2 invokespecial (0, 0)
	3 org/apache/commons/math3/ode/nonstiff/AdaptiveStepsizeIntegrator.addStepHandler:(Lorg/apache/commons/math3/ode/sampling/StepHandler;)V (0, 0)
	5 aload_0 (0, 0)
	6 invokespecial (0, 0)
	7 org/apache/commons/math3/ode/nonstiff/GraggBulirschStoerIntegrator.initializeArrays:()V (0, 0)
	9 return (0, 0)

Method: addEventHandler
	0 aload_0 (0, 0)
	1 aload_1 (0, 0)
	2 dload_2 (0, 0)
	3 dload (0, 0)
	4 #4 (0, 0)
	5 iload (0, 0)
	6 #6 (0, 0)
	7 aload (0, 0)
	8 #7 (0, 0)
	9 invokespecial (0, 0)
	10 org/apache/commons/math3/ode/nonstiff/AdaptiveStepsizeIntegrator.addEventHandler:(Lorg/apache/commons/math3/ode/events/EventHandler;DDILorg/apache/commons/math3/analysis/solvers/UnivariateSolver;)V (0, 0)
	12 aload_0 (0, 0)
	13 invokespecial (0, 0)
	14 org/apache/commons/math3/ode/nonstiff/GraggBulirschStoerIntegrator.initializeArrays:()V (0, 0)
	16 return (0, 0)

Method: initializeArrays
	0 aload_0 (0, 0)
	1 getfield (0, 0)
	2 org/apache/commons/math3/ode/nonstiff/GraggBulirschStoerIntegrator.maxOrder:I (0, 0)
	4 iconst_2 (0, 0)
	5 idiv (0, 0)
	6 istore_1 (0, 0)
	7 aload_0 (1, 1)
	8 getfield (1, 1)
	9 org/apache/commons/math3/ode/nonstiff/GraggBulirschStoerIntegrator.sequence:[I (1, 1)
	11 ifnull (1, 1)
	12 12 (1, 1)
	14 aload_0 (1, 1)
	15 getfield (1, 1)
	16 org/apache/commons/math3/ode/nonstiff/GraggBulirschStoerIntegrator.sequence:[I (1, 1)
	18 arraylength (1, 1)
	19 iload_1 (1, 1)
	20 if_icmpeq (1, 1)
	21 39 (1, 1)
	23 aload_0 (1, 1)
	24 iload_1 (1, 1)
	25 newarray (1, 1)
	26 10 (1, 1)
	27 putfield (1, 1)
	28 org/apache/commons/math3/ode/nonstiff/GraggBulirschStoerIntegrator.sequence:[I (1, 1)
	30 aload_0 (1, 1)
	31 iload_1 (1, 1)
	32 newarray (1, 1)
	33 10 (1, 1)
	34 putfield (1, 1)
	35 org/apache/commons/math3/ode/nonstiff/GraggBulirschStoerIntegrator.costPerStep:[I (1, 1)
	37 aload_0 (1, 1)
	38 iload_1 (1, 1)
	39 anewarray (1, 1)
	40 [D (1, 1)
	42 putfield (1, 1)
	43 org/apache/commons/math3/ode/nonstiff/GraggBulirschStoerIntegrator.coeff:[[D (1, 1)
	45 aload_0 (1, 1)
	46 iload_1 (1, 1)
	47 newarray (1, 1)
	48 7 (1, 1)
	49 putfield (1, 1)
	50 org/apache/commons/math3/ode/nonstiff/GraggBulirschStoerIntegrator.costPerTimeUnit:[D (1, 1)
	52 aload_0 (1, 1)
	53 iload_1 (1, 1)
	54 newarray (1, 1)
	55 7 (1, 1)
	56 putfield (1, 1)
	57 org/apache/commons/math3/ode/nonstiff/GraggBulirschStoerIntegrator.optimalStep:[D (1, 1)
	59 iconst_0 (1, 4)
	60 istore_2 (1, 4)
	61 iload_2 (1, 4)
	62 iload_1 (1, 4)
	63 if_icmpge (1, 4)
	64 20 (1, 4)
	66 aload_0 (1, 4)
	67 getfield (1, 4)
	68 org/apache/commons/math3/ode/nonstiff/GraggBulirschStoerIntegrator.sequence:[I (1, 4)
	70 iload_2 (1, 4)
	71 iconst_4 (1, 4)
	72 iload_2 (1, 4)
	73 imul (1, 4)
	74 iconst_2 (1, 4)
	75 iadd (1, 4)
	76 iastore (1, 4)
	77 iinc (1, 4)
	78 #2 (1, 4)
	79 -89 (1, 4)
	80 goto (1, 4)
	81 -19 (1, 4)
	83 aload_0 (1, 4)
	84 getfield (1, 4)
	85 org/apache/commons/math3/ode/nonstiff/GraggBulirschStoerIntegrator.costPerStep:[I (1, 4)
	87 iconst_0 (1, 4)
	88 aload_0 (1, 4)
	89 getfield (1, 4)
	90 org/apache/commons/math3/ode/nonstiff/GraggBulirschStoerIntegrator.sequence:[I (1, 4)
	92 iconst_0 (1, 4)
	93 iaload (1, 4)
	94 iconst_1 (1, 4)
	95 iadd (1, 4)
	96 iastore (1, 4)
	97 iconst_1 (2, 4)
	98 istore_2 (2, 4)
	99 iload_2 (2, 4)
	100 iload_1 (2, 4)
	101 if_icmpge (2, 4)
	102 30 (2, 4)
	104 aload_0 (2, 4)
	105 getfield (2, 4)
	106 org/apache/commons/math3/ode/nonstiff/GraggBulirschStoerIntegrator.costPerStep:[I (2, 4)
	108 iload_2 (2, 4)
	109 aload_0 (2, 4)
	110 getfield (2, 4)
	111 org/apache/commons/math3/ode/nonstiff/GraggBulirschStoerIntegrator.costPerStep:[I (2, 4)
	113 iload_2 (2, 4)
	114 iconst_1 (2, 4)
	115 isub (2, 4)
	116 iaload (2, 4)
	117 aload_0 (2, 4)
	118 getfield (2, 4)
	119 org/apache/commons/math3/ode/nonstiff/GraggBulirschStoerIntegrator.sequence:[I (2, 4)
	121 iload_2 (2, 4)
	122 iaload (2, 4)
	123 iadd (2, 4)
	124 iastore (2, 4)
	125 iinc (2, 4)
	126 #2 (2, 4)
	127 -89 (2, 4)
	128 goto (2, 4)
	129 -29 (2, 4)
	131 iconst_0 (2, 4)
	132 istore_2 (2, 4)
	133 iload_2 (2, 4)
	134 iload_1 (2, 4)
	135 if_icmpge (2, 4)
	136 77 (2, 4)
	138 aload_0 (2, 4)
	139 getfield (2, 4)
	140 org/apache/commons/math3/ode/nonstiff/GraggBulirschStoerIntegrator.coeff:[[D (2, 4)
	142 iload_2 (2, 4)
	143 iload_2 (2, 4)
	144 ifle (2, 4)
	145 9 (2, 4)
	147 iload_2 (2, 4)
	148 newarray (2, 4)
	149 7 (2, 4)
	150 goto (2, 4)
	151 4 (2, 4)
	153 aconst_null (2, 4)
	154 aastore (2, 4)
	155 iconst_0 (3, 4)
	156 istore_3 (3, 4)
	157 iload_3 (3, 4)
	158 iload_2 (3, 4)
	159 if_icmpge (3, 4)
	160 47 (3, 4)
	162 aload_0 (3, 4)
	163 getfield (3, 4)
	164 org/apache/commons/math3/ode/nonstiff/GraggBulirschStoerIntegrator.sequence:[I (3, 4)
	166 iload_2 (3, 4)
	167 iaload (3, 4)
	168 i2d (3, 4)
	169 aload_0 (3, 4)
	170 getfield (3, 4)
	171 org/apache/commons/math3/ode/nonstiff/GraggBulirschStoerIntegrator.sequence:[I (3, 4)
	173 iload_2 (3, 4)
	174 iload_3 (3, 4)
	175 isub (3, 4)
	176 iconst_1 (3, 4)
	177 isub (3, 4)
	178 iaload (3, 4)
	179 i2d (3, 4)
	180 ddiv (3, 4)
	181 dstore (3, 4)
	182 #4 (3, 4)
	183 aload_0 (3, 4)
	184 getfield (3, 4)
	185 org/apache/commons/math3/ode/nonstiff/GraggBulirschStoerIntegrator.coeff:[[D (3, 4)
	187 iload_2 (3, 4)
	188 aaload (3, 4)
	189 iload_3 (3, 4)
	190 dconst_1 (3, 4)
	191 dload (3, 4)
	192 #4 (3, 4)
	193 dload (3, 4)
	194 #4 (3, 4)
	195 dmul (3, 4)
	196 dconst_1 (3, 4)
	197 dsub (3, 4)
	198 ddiv (3, 4)
	199 dastore (3, 4)
	200 iinc (3, 4)
	201 #3 (3, 4)
	202 -89 (3, 4)
	203 goto (3, 4)
	204 -46 (3, 4)
	206 iinc (3, 4)
	207 #2 (3, 4)
	208 -89 (3, 4)
	209 goto (3, 4)
	210 -76 (3, 4)
	212 return (0, 4)

Method: setInterpolationControl
	0 aload_0 (0, 0)
	1 iload_1 (0, 0)
	2 putfield (0, 0)
	3 org/apache/commons/math3/ode/nonstiff/GraggBulirschStoerIntegrator.useInterpolationError:Z (0, 0)
	5 iload_2 (1, 1)
	6 ifle (1, 1)
	7 9 (1, 1)
	9 iload_2 (1, 1)
	10 bipush (1, 1)
	11 7 (1, 1)
	12 if_icmplt (1, 1)
	13 11 (1, 1)
	15 aload_0 (2, 1)
	16 iconst_4 (2, 1)
	17 putfield (2, 1)
	18 org/apache/commons/math3/ode/nonstiff/GraggBulirschStoerIntegrator.mudif:I (2, 1)
	20 goto (2, 1)
	21 8 (2, 1)
	23 aload_0 (4, 1)
	24 iload_2 (4, 1)
	25 putfield (4, 1)
	26 org/apache/commons/math3/ode/nonstiff/GraggBulirschStoerIntegrator.mudif:I (4, 1)
	28 return (0, 0)

Method: rescale
	0 aload_0 (1, 1)
	1 getfield (1, 1)
	2 org/apache/commons/math3/ode/nonstiff/GraggBulirschStoerIntegrator.vecAbsoluteTolerance:[D (1, 1)
	4 ifnonnull (1, 1)
	5 57 (1, 1)
	7 iconst_0 (2, 4)
	8 istore (2, 4)
	9 #4 (2, 4)
	10 iload (2, 4)
	11 #4 (2, 4)
	12 aload_3 (2, 4)
	13 arraylength (2, 4)
	14 if_icmpge (2, 4)
	15 44 (2, 4)
	17 aload_1 (2, 4)
	18 iload (2, 4)
	19 #4 (2, 4)
	20 daload (2, 4)
	21 invokestatic (2, 4)
	22 org/apache/commons/math3/util/FastMath.abs:(D)D (2, 4)
	24 aload_2 (2, 4)
	25 iload (2, 4)
	26 #4 (2, 4)
	27 daload (2, 4)
	28 invokestatic (2, 4)
	29 org/apache/commons/math3/util/FastMath.abs:(D)D (2, 4)
	31 invokestatic (2, 4)
	32 org/apache/commons/math3/util/FastMath.max:(DD)D (2, 4)
	34 dstore (2, 4)
	35 #5 (2, 4)
	36 aload_3 (2, 4)
	37 iload (2, 4)
	38 #4 (2, 4)
	39 aload_0 (2, 4)
	40 getfield (2, 4)
	41 org/apache/commons/math3/ode/nonstiff/GraggBulirschStoerIntegrator.scalAbsoluteTolerance:D (2, 4)
	43 aload_0 (2, 4)
	44 getfield (2, 4)
	45 org/apache/commons/math3/ode/nonstiff/GraggBulirschStoerIntegrator.scalRelativeTolerance:D (2, 4)
	47 dload (2, 4)
	48 #5 (2, 4)
	49 dmul (2, 4)
	50 dadd (2, 4)
	51 dastore (2, 4)
	52 iinc (2, 4)
	53 #4 (2, 4)
	54 -89 (2, 4)
	55 goto (2, 4)
	56 -45 (2, 4)
	58 goto (2, 4)
	59 60 (2, 4)
	61 iconst_0 (3, 4)
	62 istore (3, 4)
	63 #4 (3, 4)
	64 iload (3, 4)
	65 #4 (3, 4)
	66 aload_3 (3, 4)
	67 arraylength (3, 4)
	68 if_icmpge (3, 4)
	69 50 (3, 4)
	71 aload_1 (3, 4)
	72 iload (3, 4)
	73 #4 (3, 4)
	74 daload (3, 4)
	75 invokestatic (3, 4)
	76 org/apache/commons/math3/util/FastMath.abs:(D)D (3, 4)
	78 aload_2 (3, 4)
	79 iload (3, 4)
	80 #4 (3, 4)
	81 daload (3, 4)
	82 invokestatic (3, 4)
	83 org/apache/commons/math3/util/FastMath.abs:(D)D (3, 4)
	85 invokestatic (3, 4)
	86 org/apache/commons/math3/util/FastMath.max:(DD)D (3, 4)
	88 dstore (3, 4)
	89 #5 (3, 4)
	90 aload_3 (3, 4)
	91 iload (3, 4)
	92 #4 (3, 4)
	93 aload_0 (3, 4)
	94 getfield (3, 4)
	95 org/apache/commons/math3/ode/nonstiff/GraggBulirschStoerIntegrator.vecAbsoluteTolerance:[D (3, 4)
	97 iload (3, 4)
	98 #4 (3, 4)
	99 daload (3, 4)
	100 aload_0 (3, 4)
	101 getfield (3, 4)
	102 org/apache/commons/math3/ode/nonstiff/GraggBulirschStoerIntegrator.vecRelativeTolerance:[D (3, 4)
	104 iload (3, 4)
	105 #4 (3, 4)
	106 daload (3, 4)
	107 dload (3, 4)
	108 #5 (3, 4)
	109 dmul (3, 4)
	110 dadd (3, 4)
	111 dastore (3, 4)
	112 iinc (3, 4)
	113 #4 (3, 4)
	114 -89 (3, 4)
	115 goto (3, 4)
	116 -51 (3, 4)
	118 return (0, 0)

Method: tryStep
	0 aload_0 (0, 0)
	1 getfield (0, 0)
	2 org/apache/commons/math3/ode/nonstiff/GraggBulirschStoerIntegrator.sequence:[I (0, 0)
	4 iload (0, 0)
	5 #6 (0, 0)
	6 iaload (0, 0)
	7 istore (0, 0)
	8 #12 (0, 0)
	9 dload (0, 0)
	10 #4 (0, 0)
	11 iload (0, 0)
	12 #12 (0, 0)
	13 i2d (0, 0)
	14 ddiv (0, 0)
	15 dstore (0, 0)
	16 #13 (0, 0)
	17 ldc2_w (0, 0)
	18 2.0 (0, 0)
	20 dload (0, 0)
	21 #13 (0, 0)
	22 dmul (0, 0)
	23 dstore (0, 0)
	24 #15 (0, 0)
	25 dload_1 (0, 0)
	26 dload (0, 0)
	27 #13 (0, 0)
	28 dadd (0, 0)
	29 dstore (0, 0)
	30 #17 (0, 0)
	31 iconst_0 (1, 4)
	32 istore (1, 4)
	33 #19 (1, 4)
	34 iload (1, 4)
	35 #19 (1, 4)
	36 aload_3 (1, 4)
	37 arraylength (1, 4)
	38 if_icmpge (1, 4)
	39 38 (1, 4)
	41 aload (1, 4)
	42 #11 (1, 4)
	43 iload (1, 4)
	44 #19 (1, 4)
	45 aload_3 (1, 4)
	46 iload (1, 4)
	47 #19 (1, 4)
	48 daload (1, 4)
	49 dastore (1, 4)
	50 aload (1, 4)
	51 #10 (1, 4)
	52 iload (1, 4)
	53 #19 (1, 4)
	54 aload_3 (1, 4)
	55 iload (1, 4)
	56 #19 (1, 4)
	57 daload (1, 4)
	58 dload (1, 4)
	59 #13 (1, 4)
	60 aload (1, 4)
	61 #8 (1, 4)
	62 iconst_0 (1, 4)
	63 aaload (1, 4)
	64 iload (1, 4)
	65 #19 (1, 4)
	66 daload (1, 4)
	67 dmul (1, 4)
	68 dadd (1, 4)
	69 dastore (1, 4)
	70 iinc (1, 4)
	71 #19 (1, 4)
	72 -89 (1, 4)
	73 goto (1, 4)
	74 -39 (1, 4)
	76 aload_0 (0, 0)
	77 dload (0, 0)
	78 #17 (0, 0)
	79 aload (0, 0)
	80 #10 (0, 0)
	81 aload (0, 0)
	82 #8 (0, 0)
	83 iconst_1 (0, 0)
	84 aaload (0, 0)
	85 invokevirtual (0, 0)
	86 org/apache/commons/math3/ode/nonstiff/GraggBulirschStoerIntegrator.computeDerivatives:(D[D[D)V (0, 0)
	88 iconst_1 (1, 4)
	89 istore (1, 4)
	90 #19 (1, 4)
	91 iload (1, 4)
	92 #19 (1, 4)
	93 iload (1, 4)
	94 #12 (1, 4)
	95 if_icmpge (1, 4)
	96 249 (1, 4)
	98 iconst_2 (2, 1)
	99 iload (2, 1)
	100 #19 (2, 1)
	101 imul (2, 1)
	102 iload (2, 1)
	103 #12 (2, 1)
	104 if_icmpne (2, 1)
	105 14 (2, 1)
	107 aload (2, 1)
	108 #10 (2, 1)
	109 iconst_0 (2, 1)
	110 aload (2, 1)
	111 #9 (2, 1)
	112 iconst_0 (2, 1)
	113 aload_3 (2, 1)
	114 arraylength (2, 1)
	115 invokestatic (2, 1)
	116 java/lang/System.arraycopy:(Ljava/lang/Object;ILjava/lang/Object;II)V (2, 1)
	118 dload (1, 4)
	119 #17 (1, 4)
	120 dload (1, 4)
	121 #13 (1, 4)
	122 dadd (1, 4)
	123 dstore (1, 4)
	124 #17 (1, 4)
	125 iconst_0 (2, 4)
	126 istore (2, 4)
	127 #20 (2, 4)
	128 iload (2, 4)
	129 #20 (2, 4)
	130 aload_3 (2, 4)
	131 arraylength (2, 4)
	132 if_icmpge (2, 4)
	133 45 (2, 4)
	135 aload (2, 4)
	136 #10 (2, 4)
	137 iload (2, 4)
	138 #20 (2, 4)
	139 daload (2, 4)
	140 dstore (2, 4)
	141 #21 (2, 4)
	142 aload (2, 4)
	143 #10 (2, 4)
	144 iload (2, 4)
	145 #20 (2, 4)
	146 aload (2, 4)
	147 #11 (2, 4)
	148 iload (2, 4)
	149 #20 (2, 4)
	150 daload (2, 4)
	151 dload (2, 4)
	152 #15 (2, 4)
	153 aload (2, 4)
	154 #8 (2, 4)
	155 iload (2, 4)
	156 #19 (2, 4)
	157 aaload (2, 4)
	158 iload (2, 4)
	159 #20 (2, 4)
	160 daload (2, 4)
	161 dmul (2, 4)
	162 dadd (2, 4)
	163 dastore (2, 4)
	164 aload (2, 4)
	165 #11 (2, 4)
	166 iload (2, 4)
	167 #20 (2, 4)
	168 dload (2, 4)
	169 #21 (2, 4)
	170 dastore (2, 4)
	171 iinc (2, 4)
	172 #20 (2, 4)
	173 -89 (2, 4)
	174 goto (2, 4)
	175 -46 (2, 4)
	177 aload_0 (1, 4)
	178 dload (1, 4)
	179 #17 (1, 4)
	180 aload (1, 4)
	181 #10 (1, 4)
	182 aload (1, 4)
	183 #8 (1, 4)
	184 iload (1, 4)
	185 #19 (1, 4)
	186 iconst_1 (1, 4)
	187 iadd (1, 4)
	188 aaload (1, 4)
	189 invokevirtual (1, 4)
	190 org/apache/commons/math3/ode/nonstiff/GraggBulirschStoerIntegrator.computeDerivatives:(D[D[D)V (1, 4)
	192 aload_0 (2, 1)
	193 getfield (2, 1)
	194 org/apache/commons/math3/ode/nonstiff/GraggBulirschStoerIntegrator.performTest:Z (2, 1)
	196 ifeq (2, 1)
	197 142 (2, 1)
	199 iload (2, 1)
	200 #19 (2, 1)
	201 aload_0 (2, 1)
	202 getfield (2, 1)
	203 org/apache/commons/math3/ode/nonstiff/GraggBulirschStoerIntegrator.maxChecks:I (2, 1)
	205 if_icmpgt (2, 1)
	206 133 (2, 1)
	208 iload (2, 1)
	209 #6 (2, 1)
	210 aload_0 (2, 1)
	211 getfield (2, 1)
	212 org/apache/commons/math3/ode/nonstiff/GraggBulirschStoerIntegrator.maxIter:I (2, 1)
	214 if_icmpge (2, 1)
	215 124 (2, 1)
	217 dconst_0 (2, 1)
	218 dstore (2, 1)
	219 #20 (2, 1)
	220 iconst_0 (3, 4)
	221 istore (3, 4)
	222 #22 (3, 4)
	223 iload (3, 4)
	224 #22 (3, 4)
	225 aload (3, 4)
	226 #7 (3, 4)
	227 arraylength (3, 4)
	228 if_icmpge (3, 4)
	229 34 (3, 4)
	231 aload (3, 4)
	232 #8 (3, 4)
	233 iconst_0 (3, 4)
	234 aaload (3, 4)
	235 iload (3, 4)
	236 #22 (3, 4)
	237 daload (3, 4)
	238 aload (3, 4)
	239 #7 (3, 4)
	240 iload (3, 4)
	241 #22 (3, 4)
	242 daload (3, 4)
	243 ddiv (3, 4)
	244 dstore (3, 4)
	245 #23 (3, 4)
	246 dload (3, 4)
	247 #20 (3, 4)
	248 dload (3, 4)
	249 #23 (3, 4)
	250 dload (3, 4)
	251 #23 (3, 4)
	252 dmul (3, 4)
	253 dadd (3, 4)
	254 dstore (3, 4)
	255 #20 (3, 4)
	256 iinc (3, 4)
	257 #22 (3, 4)
	258 -89 (3, 4)
	259 goto (3, 4)
	260 -36 (3, 4)
	262 dconst_0 (2, 1)
	263 dstore (2, 1)
	264 #22 (2, 1)
	265 iconst_0 (3, 4)
	266 istore (3, 4)
	267 #24 (3, 4)
	268 iload (3, 4)
	269 #24 (3, 4)
	270 aload (3, 4)
	271 #7 (3, 4)
	272 arraylength (3, 4)
	273 if_icmpge (3, 4)
	274 45 (3, 4)
	276 aload (3, 4)
	277 #8 (3, 4)
	278 iload (3, 4)
	279 #19 (3, 4)
	280 iconst_1 (3, 4)
	281 iadd (3, 4)
	282 aaload (3, 4)
	283 iload (3, 4)
	284 #24 (3, 4)
	285 daload (3, 4)
	286 aload (3, 4)
	287 #8 (3, 4)
	288 iconst_0 (3, 4)
	289 aaload (3, 4)
	290 iload (3, 4)
	291 #24 (3, 4)
	292 daload (3, 4)
	293 dsub (3, 4)
	294 aload (3, 4)
	295 #7 (3, 4)
	296 iload (3, 4)
	297 #24 (3, 4)
	298 daload (3, 4)
	299 ddiv (3, 4)
	300 dstore (3, 4)
	301 #25 (3, 4)
	302 dload (3, 4)
	303 #22 (3, 4)
	304 dload (3, 4)
	305 #25 (3, 4)
	306 dload (3, 4)
	307 #25 (3, 4)
	308 dmul (3, 4)
	309 dadd (3, 4)
	310 dstore (3, 4)
	311 #22 (3, 4)
	312 iinc (3, 4)
	313 #24 (3, 4)
	314 -89 (3, 4)
	315 goto (3, 4)
	316 -47 (3, 4)
	318 dload (3, 1)
	319 #22 (3, 1)
	320 ldc2_w (3, 1)
	321 4.0 (3, 1)
	323 ldc2_w (3, 1)
	324 1e-15 (3, 1)
	326 dload (3, 1)
	327 #20 (3, 1)
	328 invokestatic (3, 1)
	329 org/apache/commons/math3/util/FastMath.max:(DD)D (3, 1)
	331 dmul (3, 1)
	332 dcmpl (3, 1)
	333 ifle (3, 1)
	334 5 (3, 1)
	336 iconst_0 (3, 1)
	337 ireturn (3, 1)
	338 iinc (3, 1)
	339 #19 (3, 1)
	340 -89 (3, 1)
	341 goto (3, 1)
	342 -250 (3, 1)
	344 iconst_0 (3, 4)
	345 istore (3, 4)
	346 #19 (3, 4)
	347 iload (3, 4)
	348 #19 (3, 4)
	349 aload_3 (3, 4)
	350 arraylength (3, 4)
	351 if_icmpge (3, 4)
	352 41 (3, 4)
	354 aload (3, 4)
	355 #10 (3, 4)
	356 iload (3, 4)
	357 #19 (3, 4)
	358 ldc2_w (3, 4)
	359 0.5 (3, 4)
	361 aload (3, 4)
	362 #11 (3, 4)
	363 iload (3, 4)
	364 #19 (3, 4)
	365 daload (3, 4)
	366 aload (3, 4)
	367 #10 (3, 4)
	368 iload (3, 4)
	369 #19 (3, 4)
	370 daload (3, 4)
	371 dadd (3, 4)
	372 dload (3, 4)
	373 #13 (3, 4)
	374 aload (3, 4)
	375 #8 (3, 4)
	376 iload (3, 4)
	377 #12 (3, 4)
	378 aaload (3, 4)
	379 iload (3, 4)
	380 #19 (3, 4)
	381 daload (3, 4)
	382 dmul (3, 4)
	383 dadd (3, 4)
	384 dmul (3, 4)
	385 dastore (3, 4)
	386 iinc (3, 4)
	387 #19 (3, 4)
	388 -89 (3, 4)
	389 goto (3, 4)
	390 -42 (3, 4)
	392 iconst_1 (2, 1)
	393 ireturn (2, 1)

Method: extrapolate
	0 iconst_1 (1, 4)
	1 istore (1, 4)
	2 #5 (1, 4)
	3 iload (1, 4)
	4 #5 (1, 4)
	5 iload_2 (1, 4)
	6 if_icmpge (1, 4)
	7 82 (1, 4)
	9 iconst_0 (2, 4)
	10 istore (2, 4)
	11 #6 (2, 4)
	12 iload (2, 4)
	13 #6 (2, 4)
	14 aload (2, 4)
	15 #4 (2, 4)
	16 arraylength (2, 4)
	17 if_icmpge (2, 4)
	18 65 (2, 4)
	20 aload_3 (3, 4)
	21 iload_2 (3, 4)
	22 iload (3, 4)
	23 #5 (3, 4)
	24 isub (3, 4)
	25 iconst_1 (3, 4)
	26 isub (3, 4)
	27 aaload (3, 4)
	28 iload (3, 4)
	29 #6 (3, 4)
	30 aload_3 (3, 4)
	31 iload_2 (3, 4)
	32 iload (3, 4)
	33 #5 (3, 4)
	34 isub (3, 4)
	35 aaload (3, 4)
	36 iload (3, 4)
	37 #6 (3, 4)
	38 daload (3, 4)
	39 aload_0 (3, 4)
	40 getfield (3, 4)
	41 org/apache/commons/math3/ode/nonstiff/GraggBulirschStoerIntegrator.coeff:[[D (3, 4)
	43 iload_2 (3, 4)
	44 iload_1 (3, 4)
	45 iadd (3, 4)
	46 aaload (3, 4)
	47 iload (3, 4)
	48 #5 (3, 4)
	49 iconst_1 (3, 4)
	50 isub (3, 4)
	51 daload (3, 4)
	52 aload_3 (3, 4)
	53 iload_2 (3, 4)
	54 iload (3, 4)
	55 #5 (3, 4)
	56 isub (3, 4)
	57 aaload (3, 4)
	58 iload (3, 4)
	59 #6 (3, 4)
	60 daload (3, 4)
	61 aload_3 (3, 4)
	62 iload_2 (3, 4)
	63 iload (3, 4)
	64 #5 (3, 4)
	65 isub (3, 4)
	66 iconst_1 (3, 4)
	67 isub (3, 4)
	68 aaload (3, 4)
	69 iload (3, 4)
	70 #6 (3, 4)
	71 daload (3, 4)
	72 dsub (3, 4)
	73 dmul (3, 4)
	74 dadd (3, 4)
	75 dastore (3, 4)
	76 iinc (3, 4)
	77 #6 (3, 4)
	78 -89 (3, 4)
	79 goto (3, 4)
	80 -67 (3, 4)
	82 iinc (3, 4)
	83 #5 (3, 4)
	84 -89 (3, 4)
	85 goto (3, 4)
	86 -82 (3, 4)
	88 iconst_0 (2, 4)
	89 istore (2, 4)
	90 #5 (2, 4)
	91 iload (2, 4)
	92 #5 (2, 4)
	93 aload (2, 4)
	94 #4 (2, 4)
	95 arraylength (2, 4)
	96 if_icmpge (2, 4)
	97 46 (2, 4)
	99 aload (3, 4)
	100 #4 (3, 4)
	101 iload (3, 4)
	102 #5 (3, 4)
	103 aload_3 (3, 4)
	104 iconst_0 (3, 4)
	105 aaload (3, 4)
	106 iload (3, 4)
	107 #5 (3, 4)
	108 daload (3, 4)
	109 aload_0 (3, 4)
	110 getfield (3, 4)
	111 org/apache/commons/math3/ode/nonstiff/GraggBulirschStoerIntegrator.coeff:[[D (3, 4)
	113 iload_2 (3, 4)
	114 iload_1 (3, 4)
	115 iadd (3, 4)
	116 aaload (3, 4)
	117 iload_2 (3, 4)
	118 iconst_1 (3, 4)
	119 isub (3, 4)
	120 daload (3, 4)
	121 aload_3 (3, 4)
	122 iconst_0 (3, 4)
	123 aaload (3, 4)
	124 iload (3, 4)
	125 #5 (3, 4)
	126 daload (3, 4)
	127 aload (3, 4)
	128 #4 (3, 4)
	129 iload (3, 4)
	130 #5 (3, 4)
	131 daload (3, 4)
	132 dsub (3, 4)
	133 dmul (3, 4)
	134 dadd (3, 4)
	135 dastore (3, 4)
	136 iinc (3, 4)
	137 #5 (3, 4)
	138 -89 (3, 4)
	139 goto (3, 4)
	140 -48 (3, 4)
	142 return (0, 0)

Method: integrate
	0 aload_0 (0, 0)
	1 aload_1 (0, 0)
	2 dload_2 (0, 0)
	3 invokevirtual (0, 0)
	4 org/apache/commons/math3/ode/nonstiff/GraggBulirschStoerIntegrator.sanityChecks:(Lorg/apache/commons/math3/ode/ExpandableStatefulODE;D)V (0, 0)
	6 aload_0 (0, 0)
	7 aload_1 (0, 0)
	8 invokevirtual (0, 0)
	9 org/apache/commons/math3/ode/nonstiff/GraggBulirschStoerIntegrator.setEquations:(Lorg/apache/commons/math3/ode/ExpandableStatefulODE;)V (0, 0)
	11 dload_2 (1, 4)
	12 aload_1 (1, 4)
	13 invokevirtual (1, 4)
	14 org/apache/commons/math3/ode/ExpandableStatefulODE.getTime:()D (1, 4)
	16 dcmpl (1, 4)
	17 ifle (1, 4)
	18 7 (1, 4)
	20 iconst_1 (1, 4)
	21 goto (1, 4)
	22 4 (1, 4)
	24 iconst_0 (1, 4)
	25 istore (1, 4)
	26 #4 (1, 4)
	27 aload_1 (1, 4)
	28 invokevirtual (1, 4)
	29 org/apache/commons/math3/ode/ExpandableStatefulODE.getCompleteState:()[D (1, 4)
	31 astore (1, 4)
	32 #5 (1, 4)
	33 aload (1, 4)
	34 #5 (1, 4)
	35 invokevirtual (1, 4)
	36 [D.clone:()Ljava/lang/Object; (1, 4)
	38 checkcast (1, 4)
	39 [D (1, 4)
	41 astore (1, 4)
	42 #6 (1, 4)
	43 aload (1, 4)
	44 #6 (1, 4)
	45 arraylength (1, 4)
	46 newarray (1, 4)
	47 7 (1, 4)
	48 astore (1, 4)
	49 #7 (1, 4)
	50 aload (1, 4)
	51 #6 (1, 4)
	52 arraylength (1, 4)
	53 newarray (1, 4)
	54 7 (1, 4)
	55 astore (1, 4)
	56 #8 (1, 4)
	57 aload (1, 4)
	58 #6 (1, 4)
	59 arraylength (1, 4)
	60 newarray (1, 4)
	61 7 (1, 4)
	62 astore (1, 4)
	63 #9 (1, 4)
	64 aload (1, 4)
	65 #6 (1, 4)
	66 arraylength (1, 4)
	67 newarray (1, 4)
	68 7 (1, 4)
	69 astore (1, 4)
	70 #10 (1, 4)
	71 aload_0 (1, 4)
	72 getfield (1, 4)
	73 org/apache/commons/math3/ode/nonstiff/GraggBulirschStoerIntegrator.sequence:[I (1, 4)
	75 arraylength (1, 4)
	76 iconst_1 (1, 4)
	77 isub (1, 4)
	78 anewarray (1, 4)
	79 [D (1, 4)
	81 astore (1, 4)
	82 #11 (1, 4)
	83 aload_0 (1, 4)
	84 getfield (1, 4)
	85 org/apache/commons/math3/ode/nonstiff/GraggBulirschStoerIntegrator.sequence:[I (1, 4)
	87 arraylength (1, 4)
	88 iconst_1 (1, 4)
	89 isub (1, 4)
	90 anewarray (1, 4)
	91 [D (1, 4)
	93 astore (1, 4)
	94 #12 (1, 4)
	95 iconst_0 (2, 4)
	96 istore (2, 4)
	97 #13 (2, 4)
	98 iload (2, 4)
	99 #13 (2, 4)
	100 aload_0 (2, 4)
	101 getfield (2, 4)
	102 org/apache/commons/math3/ode/nonstiff/GraggBulirschStoerIntegrator.sequence:[I (2, 4)
	104 arraylength (2, 4)
	105 iconst_1 (2, 4)
	106 isub (2, 4)
	107 if_icmpge (2, 4)
	108 29 (2, 4)
	110 aload (2, 4)
	111 #11 (2, 4)
	112 iload (2, 4)
	113 #13 (2, 4)
	114 aload (2, 4)
	115 #6 (2, 4)
	116 arraylength (2, 4)
	117 newarray (2, 4)
	118 7 (2, 4)
	119 aastore (2, 4)
	120 aload (2, 4)
	121 #12 (2, 4)
	122 iload (2, 4)
	123 #13 (2, 4)
	124 aload (2, 4)
	125 #6 (2, 4)
	126 arraylength (2, 4)
	127 newarray (2, 4)
	128 7 (2, 4)
	129 aastore (2, 4)
	130 iinc (2, 4)
	131 #13 (2, 4)
	132 -89 (2, 4)
	133 goto (2, 4)
	134 -35 (2, 4)
	136 aload_0 (1, 4)
	137 getfield (1, 4)
	138 org/apache/commons/math3/ode/nonstiff/GraggBulirschStoerIntegrator.sequence:[I (1, 4)
	140 arraylength (1, 4)
	141 anewarray (1, 4)
	142 [[D (1, 4)
	144 astore (1, 4)
	145 #13 (1, 4)
	146 iconst_0 (2, 4)
	147 istore (2, 4)
	148 #14 (2, 4)
	149 iload (2, 4)
	150 #14 (2, 4)
	151 aload_0 (2, 4)
	152 getfield (2, 4)
	153 org/apache/commons/math3/ode/nonstiff/GraggBulirschStoerIntegrator.sequence:[I (2, 4)
	155 arraylength (2, 4)
	156 if_icmpge (2, 4)
	157 71 (2, 4)
	159 aload (2, 4)
	160 #13 (2, 4)
	161 iload (2, 4)
	162 #14 (2, 4)
	163 aload_0 (2, 4)
	164 getfield (2, 4)
	165 org/apache/commons/math3/ode/nonstiff/GraggBulirschStoerIntegrator.sequence:[I (2, 4)
	167 iload (2, 4)
	168 #14 (2, 4)
	169 iaload (2, 4)
	170 iconst_1 (2, 4)
	171 iadd (2, 4)
	172 anewarray (2, 4)
	173 [D (2, 4)
	175 aastore (2, 4)
	176 aload (2, 4)
	177 #13 (2, 4)
	178 iload (2, 4)
	179 #14 (2, 4)
	180 aaload (2, 4)
	181 iconst_0 (2, 4)
	182 aload (2, 4)
	183 #7 (2, 4)
	184 aastore (2, 4)
	185 iconst_0 (3, 4)
	186 istore (3, 4)
	187 #15 (3, 4)
	188 iload (3, 4)
	189 #15 (3, 4)
	190 aload_0 (3, 4)
	191 getfield (3, 4)
	192 org/apache/commons/math3/ode/nonstiff/GraggBulirschStoerIntegrator.sequence:[I (3, 4)
	194 iload (3, 4)
	195 #14 (3, 4)
	196 iaload (3, 4)
	197 if_icmpge (3, 4)
	198 24 (3, 4)
	200 aload (3, 4)
	201 #13 (3, 4)
	202 iload (3, 4)
	203 #14 (3, 4)
	204 aaload (3, 4)
	205 iload (3, 4)
	206 #15 (3, 4)
	207 iconst_1 (3, 4)
	208 iadd (3, 4)
	209 aload (3, 4)
	210 #5 (3, 4)
	211 arraylength (3, 4)
	212 newarray (3, 4)
	213 7 (3, 4)
	214 aastore (3, 4)
	215 iinc (3, 4)
	216 #15 (3, 4)
	217 -89 (3, 4)
	218 goto (3, 4)
	219 -30 (3, 4)
	221 iinc (3, 4)
	222 #14 (3, 4)
	223 -89 (3, 4)
	224 goto (3, 4)
	225 -75 (3, 4)
	227 aload (3, 1)
	228 #6 (3, 1)
	229 aload (3, 1)
	230 #5 (3, 1)
	231 if_acmpeq (3, 1)
	232 15 (3, 1)
	234 aload (3, 1)
	235 #5 (3, 1)
	236 iconst_0 (3, 1)
	237 aload (3, 1)
	238 #6 (3, 1)
	239 iconst_0 (3, 1)
	240 aload (3, 1)
	241 #5 (3, 1)
	242 arraylength (3, 1)
	243 invokestatic (3, 1)
	244 java/lang/System.arraycopy:(Ljava/lang/Object;ILjava/lang/Object;II)V (3, 1)
	246 aload (2, 4)
	247 #5 (2, 4)
	248 arraylength (2, 4)
	249 newarray (2, 4)
	250 7 (2, 4)
	251 astore (2, 4)
	252 #14 (2, 4)
	253 iconst_1 (2, 4)
	254 iconst_2 (2, 4)
	255 aload_0 (2, 4)
	256 getfield (2, 4)
	257 org/apache/commons/math3/ode/nonstiff/GraggBulirschStoerIntegrator.sequence:[I (2, 4)
	259 arraylength (2, 4)
	260 imul (2, 4)
	261 iadd (2, 4)
	262 aload (2, 4)
	263 #5 (2, 4)
	264 arraylength (2, 4)
	265 multianewarray (2, 4)
	266 [[D (2, 4)
	268 58 (2, 4)
	269 astore (2, 4)
	270 #15 (2, 4)
	271 aload_0 (2, 4)
	272 getfield (2, 4)
	273 org/apache/commons/math3/ode/nonstiff/GraggBulirschStoerIntegrator.mainSetDimension:I (2, 4)
	275 newarray (2, 4)
	276 7 (2, 4)
	277 astore (2, 4)
	278 #16 (2, 4)
	279 aload_0 (2, 4)
	280 aload (2, 4)
	281 #6 (2, 4)
	282 aload (2, 4)
	283 #6 (2, 4)
	284 aload (2, 4)
	285 #16 (2, 4)
	286 invokespecial (2, 4)
	287 org/apache/commons/math3/ode/nonstiff/GraggBulirschStoerIntegrator.rescale:([D[D[D)V (2, 4)
	289 aload_0 (2, 4)
	290 getfield (2, 4)
	291 org/apache/commons/math3/ode/nonstiff/GraggBulirschStoerIntegrator.vecRelativeTolerance:[D (2, 4)
	293 ifnonnull (2, 4)
	294 10 (2, 4)
	296 aload_0 (2, 4)
	297 getfield (2, 4)
	298 org/apache/commons/math3/ode/nonstiff/GraggBulirschStoerIntegrator.scalRelativeTolerance:D (2, 4)
	300 goto (2, 4)
	301 9 (2, 4)
	303 aload_0 (2, 4)
	304 getfield (2, 4)
	305 org/apache/commons/math3/ode/nonstiff/GraggBulirschStoerIntegrator.vecRelativeTolerance:[D (2, 4)
	307 iconst_0 (2, 4)
	308 daload (2, 4)
	309 dstore (2, 4)
	310 #17 (2, 4)
	311 ldc2_w (2, 4)
	312 1e-10 (2, 4)
	314 dload (2, 4)
	315 #17 (2, 4)
	316 invokestatic (2, 4)
	317 org/apache/commons/math3/util/FastMath.max:(DD)D (2, 4)
	319 invokestatic (2, 4)
	320 org/apache/commons/math3/util/FastMath.log10:(D)D (2, 4)
	322 dstore (2, 4)
	323 #19 (2, 4)
	324 iconst_1 (2, 4)
	325 aload_0 (2, 4)
	326 getfield (2, 4)
	327 org/apache/commons/math3/ode/nonstiff/GraggBulirschStoerIntegrator.sequence:[I (2, 4)
	329 arraylength (2, 4)
	330 iconst_2 (2, 4)
	331 isub (2, 4)
	332 ldc2_w (2, 4)
	333 0.5 (2, 4)
	335 ldc2_w (2, 4)
	336 0.6 (2, 4)
	338 dload (2, 4)
	339 #19 (2, 4)
	340 dmul (2, 4)
	341 dsub (2, 4)
	342 invokestatic (2, 4)
	343 org/apache/commons/math3/util/FastMath.floor:(D)D (2, 4)
	345 d2i (2, 4)
	346 invokestatic (2, 4)
	347 org/apache/commons/math3/util/FastMath.min:(II)I (2, 4)
	349 invokestatic (2, 4)
	350 org/apache/commons/math3/util/FastMath.max:(II)I (2, 4)
	352 istore (2, 4)
	353 #21 (2, 4)
	354 new (2, 4)
	355 org/apache/commons/math3/ode/nonstiff/GraggBulirschStoerStepInterpolator (2, 4)
	357 dup (2, 4)
	358 aload (2, 4)
	359 #6 (2, 4)
	360 aload (2, 4)
	361 #7 (2, 4)
	362 aload (2, 4)
	363 #8 (2, 4)
	364 aload (2, 4)
	365 #14 (2, 4)
	366 aload (2, 4)
	367 #15 (2, 4)
	368 iload (2, 4)
	369 #4 (2, 4)
	370 aload_1 (2, 4)
	371 invokevirtual (3, 4)
	372 org/apache/commons/math3/ode/ExpandableStatefulODE.getPrimaryMapper:()Lorg/apache/commons/math3/ode/EquationsMapper; (3, 4)
	374 aload_1 (3, 4)
	375 invokevirtual (3, 4)
	376 org/apache/commons/math3/ode/ExpandableStatefulODE.getSecondaryMappers:()[Lorg/apache/commons/math3/ode/EquationsMapper; (3, 4)
	378 invokespecial (3, 4)
	379 org/apache/commons/math3/ode/nonstiff/GraggBulirschStoerStepInterpolator.<init>:([D[D[D[D[[DZLorg/apache/commons/math3/ode/EquationsMapper;[Lorg/apache/commons/math3/ode/EquationsMapper;)V (3, 4)
	381 astore (3, 4)
	382 #22 (3, 4)
	383 aload (3, 4)
	384 #22 (3, 4)
	385 aload_1 (3, 4)
	386 invokevirtual (3, 4)
	387 org/apache/commons/math3/ode/ExpandableStatefulODE.getTime:()D (3, 4)
	389 invokevirtual (3, 4)
	390 org/apache/commons/math3/ode/sampling/AbstractStepInterpolator.storeTime:(D)V (3, 4)
	392 aload_0 (3, 4)
	393 aload_1 (3, 4)
	394 invokevirtual (3, 4)
	395 org/apache/commons/math3/ode/ExpandableStatefulODE.getTime:()D (3, 4)
	397 putfield (3, 4)
	398 org/apache/commons/math3/ode/nonstiff/GraggBulirschStoerIntegrator.stepStart:D (3, 4)
	400 dconst_0 (3, 4)
	401 dstore (3, 4)
	402 #23 (3, 4)
	403 ldc2_w (3, 4)
	404 1.7976931348623157e+308 (3, 4)
	406 dstore (3, 4)
	407 #25 (3, 4)
	408 iconst_0 (3, 4)
	409 istore (3, 4)
	410 #27 (3, 4)
	411 iconst_1 (3, 4)
	412 istore (3, 4)
	413 #28 (3, 4)
	414 iconst_1 (3, 4)
	415 istore (3, 4)
	416 #29 (3, 4)
	417 iconst_0 (3, 4)
	418 istore (3, 4)
	419 #30 (3, 4)
	420 aload_0 (3, 4)
	421 aload_1 (3, 4)
	422 invokevirtual (3, 4)
	423 org/apache/commons/math3/ode/ExpandableStatefulODE.getTime:()D (3, 4)
	425 aload (3, 4)
	426 #5 (3, 4)
	427 dload_2 (3, 4)
	428 invokevirtual (3, 4)
	429 org/apache/commons/math3/ode/nonstiff/GraggBulirschStoerIntegrator.initIntegration:(D[DD)V (3, 4)
	431 aload_0 (3, 4)
	432 getfield (3, 4)
	433 org/apache/commons/math3/ode/nonstiff/GraggBulirschStoerIntegrator.costPerTimeUnit:[D (3, 4)
	435 iconst_0 (3, 4)
	436 dconst_0 (3, 4)
	437 dastore (3, 4)
	438 aload_0 (3, 4)
	439 iconst_0 (3, 4)
	440 putfield (3, 4)
	441 org/apache/commons/math3/ode/nonstiff/GraggBulirschStoerIntegrator.isLastStep:Z (3, 4)
	443 iconst_0 (3, 4)
	444 istore (3, 4)
	445 #33 (3, 4)
	446 iload (4, 1)
	447 #29 (4, 1)
	448 ifeq (4, 1)
	449 61 (4, 1)
	451 aload (5, 1)
	452 #22 (5, 1)
	453 invokevirtual (5, 1)
	454 org/apache/commons/math3/ode/sampling/AbstractStepInterpolator.shift:()V (5, 1)
	456 iload (6, 1)
	457 #30 (6, 1)
	458 ifne (6, 1)
	459 15 (6, 1)
	461 aload_0 (6, 1)
	462 aload_0 (6, 1)
	463 getfield (6, 1)
	464 org/apache/commons/math3/ode/nonstiff/GraggBulirschStoerIntegrator.stepStart:D (6, 1)
	466 aload (6, 1)
	467 #6 (6, 1)
	468 aload (6, 1)
	469 #7 (6, 1)
	470 invokevirtual (6, 1)
	471 org/apache/commons/math3/ode/nonstiff/GraggBulirschStoerIntegrator.computeDerivatives:(D[D[D)V (6, 1)
	473 iload (6, 1)
	474 #28 (6, 1)
	475 ifeq (6, 1)
	476 31 (6, 1)
	478 aload_0 (7, 4)
	479 iload (7, 4)
	480 #4 (7, 4)
	481 iconst_2 (7, 4)
	482 iload (7, 4)
	483 #21 (7, 4)
	484 imul (7, 4)
	485 iconst_1 (7, 4)
	486 iadd (7, 4)
	487 aload (7, 4)
	488 #16 (7, 4)
	489 aload_0 (7, 4)
	490 getfield (7, 4)
	491 org/apache/commons/math3/ode/nonstiff/GraggBulirschStoerIntegrator.stepStart:D (7, 4)
	493 aload (7, 4)
	494 #6 (7, 4)
	495 aload (7, 4)
	496 #7 (7, 4)
	497 aload (7, 4)
	498 #9 (7, 4)
	499 aload (7, 4)
	500 #10 (7, 4)
	501 invokevirtual (7, 4)
	502 org/apache/commons/math3/ode/nonstiff/GraggBulirschStoerIntegrator.initializeStep:(ZI[DD[D[D[D[D)D (7, 4)
	504 dstore (7, 4)
	505 #23 (7, 4)
	506 iconst_0 (5, 1)
	507 istore (5, 1)
	508 #29 (5, 1)
	509 aload_0 (3, 4)
	510 dload (3, 4)
	511 #23 (3, 4)
	512 putfield (3, 4)
	513 org/apache/commons/math3/ode/nonstiff/GraggBulirschStoerIntegrator.stepSize:D (3, 4)
	515 iload (4, 1)
	516 #4 (4, 1)
	517 ifeq (4, 1)
	518 17 (4, 1)
	520 aload_0 (4, 1)
	521 getfield (4, 1)
	522 org/apache/commons/math3/ode/nonstiff/GraggBulirschStoerIntegrator.stepStart:D (4, 1)
	524 aload_0 (4, 1)
	525 getfield (4, 1)
	526 org/apache/commons/math3/ode/nonstiff/GraggBulirschStoerIntegrator.stepSize:D (4, 1)
	528 dadd (4, 1)
	529 dload_2 (4, 1)
	530 dcmpl (4, 1)
	531 ifgt (4, 1)
	532 22 (4, 1)
	534 iload (4, 1)
	535 #4 (4, 1)
	536 ifne (4, 1)
	537 27 (4, 1)
	539 aload_0 (4, 1)
	540 getfield (4, 1)
	541 org/apache/commons/math3/ode/nonstiff/GraggBulirschStoerIntegrator.stepStart:D (4, 1)
	543 aload_0 (4, 1)
	544 getfield (4, 1)
	545 org/apache/commons/math3/ode/nonstiff/GraggBulirschStoerIntegrator.stepSize:D (4, 1)
	547 dadd (4, 1)
	548 dload_2 (4, 1)
	549 dcmpg (4, 1)
	550 ifge (4, 1)
	551 13 (4, 1)
	553 aload_0 (5, 4)
	554 dload_2 (5, 4)
	555 aload_0 (5, 4)
	556 getfield (5, 4)
	557 org/apache/commons/math3/ode/nonstiff/GraggBulirschStoerIntegrator.stepStart:D (5, 4)
	559 dsub (5, 4)
	560 putfield (5, 4)
	561 org/apache/commons/math3/ode/nonstiff/GraggBulirschStoerIntegrator.stepSize:D (5, 4)
	563 aload_0 (4, 1)
	564 getfield (4, 1)
	565 org/apache/commons/math3/ode/nonstiff/GraggBulirschStoerIntegrator.stepStart:D (4, 1)
	567 aload_0 (4, 1)
	568 getfield (4, 1)
	569 org/apache/commons/math3/ode/nonstiff/GraggBulirschStoerIntegrator.stepSize:D (4, 1)
	571 dadd (4, 1)
	572 dstore (4, 1)
	573 #34 (4, 1)
	574 aload_0 (5, 4)
	575 iload (5, 4)
	576 #4 (5, 4)
	577 ifeq (5, 4)
	578 18 (5, 4)
	580 dload (5, 4)
	581 #34 (5, 4)
	582 dload_2 (5, 4)
	583 dcmpl (5, 4)
	584 iflt (5, 4)
	585 7 (5, 4)
	587 iconst_1 (5, 4)
	588 goto (5, 4)
	589 19 (5, 4)
	591 iconst_0 (5, 4)
	592 goto (5, 4)
	593 15 (5, 4)
	595 dload (5, 4)
	596 #34 (5, 4)
	597 dload_2 (5, 4)
	598 dcmpg (5, 4)
	599 ifgt (5, 4)
	600 7 (5, 4)
	602 iconst_1 (5, 4)
	603 goto (5, 4)
	604 4 (5, 4)
	606 iconst_0 (5, 4)
	607 putfield (5, 4)
	608 org/apache/commons/math3/ode/nonstiff/GraggBulirschStoerIntegrator.isLastStep:Z (5, 4)
	610 iconst_m1 (5, 4)
	611 istore (5, 4)
	612 #36 (5, 4)
	613 iconst_1 (6, 4)
	614 istore (6, 4)
	615 #37 (6, 4)
	616 iload (6, 4)
	617 #37 (6, 4)
	618 ifeq (6, 4)
	619 705 (6, 4)
	621 iinc (6, 4)
	622 #36 (6, 4)
	623 42 (6, 4)
	624 aload_0 (8, 1)
	625 aload_0 (8, 1)
	626 getfield (8, 1)
	627 org/apache/commons/math3/ode/nonstiff/GraggBulirschStoerIntegrator.stepStart:D (8, 1)
	629 aload (8, 1)
	630 #6 (8, 1)
	631 aload_0 (8, 1)
	632 getfield (8, 1)
	633 org/apache/commons/math3/ode/nonstiff/GraggBulirschStoerIntegrator.stepSize:D (8, 1)
	635 iload (8, 1)
	636 #36 (8, 1)
	637 aload (8, 1)
	638 #16 (8, 1)
	639 aload (8, 1)
	640 #13 (8, 1)
	641 iload (8, 1)
	642 #36 (8, 1)
	643 aaload (8, 1)
	644 iload (8, 1)
	645 #36 (8, 1)
	646 ifne (8, 1)
	647 10 (8, 1)
	649 aload (8, 1)
	650 #15 (8, 1)
	651 iconst_0 (8, 1)
	652 aaload (8, 1)
	653 goto (8, 1)
	654 10 (8, 1)
	656 aload (8, 1)
	657 #11 (8, 1)
	658 iload (8, 1)
	659 #36 (8, 1)
	660 iconst_1 (8, 1)
	661 isub (8, 1)
	662 aaload (8, 1)
	663 iload (8, 1)
	664 #36 (8, 1)
	665 ifne (8, 1)
	666 8 (8, 1)
	668 aload (8, 1)
	669 #8 (8, 1)
	670 goto (8, 1)
	671 10 (8, 1)
	673 aload (8, 1)
	674 #12 (8, 1)
	675 iload (8, 1)
	676 #36 (8, 1)
	677 iconst_1 (8, 1)
	678 isub (8, 1)
	679 aaload (8, 1)
	680 aload (8, 1)
	681 #9 (8, 1)
	682 invokespecial (8, 1)
	683 org/apache/commons/math3/ode/nonstiff/GraggBulirschStoerIntegrator.tryStep:(D[DDI[D[[D[D[D[D)Z (8, 1)
	685 ifne (8, 1)
	686 33 (8, 1)
	688 aload_0 (9, 4)
	689 aload_0 (9, 4)
	690 getfield (9, 4)
	691 org/apache/commons/math3/ode/nonstiff/GraggBulirschStoerIntegrator.stepSize:D (9, 4)
	693 aload_0 (9, 4)
	694 getfield (9, 4)
	695 org/apache/commons/math3/ode/nonstiff/GraggBulirschStoerIntegrator.stabilityReduction:D (9, 4)
	697 dmul (9, 4)
	698 iload (9, 4)
	699 #4 (9, 4)
	700 iconst_0 (9, 4)
	701 invokevirtual (9, 4)
	702 org/apache/commons/math3/ode/nonstiff/GraggBulirschStoerIntegrator.filterStep:(DZZ)D (9, 4)
	704 invokestatic (9, 4)
	705 org/apache/commons/math3/util/FastMath.abs:(D)D (9, 4)
	707 dstore (9, 4)
	708 #23 (9, 4)
	709 iconst_1 (9, 4)
	710 istore (9, 4)
	711 #33 (9, 4)
	712 iconst_0 (9, 4)
	713 istore (9, 4)
	714 #37 (9, 4)
	715 goto (9, 4)
	716 -99 (9, 4)
	718 iload (11, 1)
	719 #36 (11, 1)
	720 ifle (11, 1)
	721 -104 (11, 1)
	723 aload_0 (11, 1)
	724 iconst_0 (11, 1)
	725 iload (11, 1)
	726 #36 (11, 1)
	727 aload (11, 1)
	728 #12 (11, 1)
	729 aload (11, 1)
	730 #8 (11, 1)
	731 invokespecial (11, 1)
	732 org/apache/commons/math3/ode/nonstiff/GraggBulirschStoerIntegrator.extrapolate:(II[[D[D)V (11, 1)
	734 aload_0 (11, 1)
	735 aload (11, 1)
	736 #6 (11, 1)
	737 aload (11, 1)
	738 #8 (11, 1)
	739 aload (11, 1)
	740 #16 (11, 1)
	741 invokespecial (11, 1)
	742 org/apache/commons/math3/ode/nonstiff/GraggBulirschStoerIntegrator.rescale:([D[D[D)V (11, 1)
	744 dconst_0 (11, 1)
	745 dstore (11, 1)
	746 #31 (11, 1)
	747 iconst_0 (12, 4)
	748 istore (12, 4)
	749 #38 (12, 4)
	750 iload (12, 4)
	751 #38 (12, 4)
	752 aload_0 (12, 4)
	753 getfield (12, 4)
	754 org/apache/commons/math3/ode/nonstiff/GraggBulirschStoerIntegrator.mainSetDimension:I (12, 4)
	756 if_icmpge (12, 4)
	757 43 (12, 4)
	759 aload (12, 4)
	760 #8 (12, 4)
	761 iload (12, 4)
	762 #38 (12, 4)
	763 daload (12, 4)
	764 aload (12, 4)
	765 #12 (12, 4)
	766 iconst_0 (12, 4)
	767 aaload (12, 4)
	768 iload (12, 4)
	769 #38 (12, 4)
	770 daload (12, 4)
	771 dsub (12, 4)
	772 invokestatic (12, 4)
	773 org/apache/commons/math3/util/FastMath.abs:(D)D (12, 4)
	775 aload (12, 4)
	776 #16 (12, 4)
	777 iload (12, 4)
	778 #38 (12, 4)
	779 daload (12, 4)
	780 ddiv (12, 4)
	781 dstore (12, 4)
	782 #39 (12, 4)
	783 dload (12, 4)
	784 #31 (12, 4)
	785 dload (12, 4)
	786 #39 (12, 4)
	787 dload (12, 4)
	788 #39 (12, 4)
	789 dmul (12, 4)
	790 dadd (12, 4)
	791 dstore (12, 4)
	792 #31 (12, 4)
	793 iinc (12, 4)
	794 #38 (12, 4)
	795 -89 (12, 4)
	796 goto (12, 4)
	797 -46 (12, 4)
	799 dload (11, 1)
	800 #31 (11, 1)
	801 aload_0 (11, 1)
	802 getfield (11, 1)
	803 org/apache/commons/math3/ode/nonstiff/GraggBulirschStoerIntegrator.mainSetDimension:I (11, 1)
	805 i2d (11, 1)
	806 ddiv (11, 1)
	807 invokestatic (11, 1)
	808 org/apache/commons/math3/util/FastMath.sqrt:(D)D (11, 1)
	810 dstore (11, 1)
	811 #31 (11, 1)
	812 dload (12, 1)
	813 #31 (12, 1)
	814 ldc2_w (12, 1)
	815 1000000000000000.0 (12, 1)
	817 dcmpl (12, 1)
	818 ifgt (12, 1)
	819 17 (12, 1)
	821 iload (12, 1)
	822 #36 (12, 1)
	823 iconst_1 (12, 1)
	824 if_icmple (12, 1)
	825 41 (12, 1)
	827 dload (12, 1)
	828 #31 (12, 1)
	829 dload (12, 1)
	830 #25 (12, 1)
	831 dcmpl (12, 1)
	832 ifle (12, 1)
	833 33 (12, 1)
	835 aload_0 (13, 4)
	836 aload_0 (13, 4)
	837 getfield (13, 4)
	838 org/apache/commons/math3/ode/nonstiff/GraggBulirschStoerIntegrator.stepSize:D (13, 4)
	840 aload_0 (13, 4)
	841 getfield (13, 4)
	842 org/apache/commons/math3/ode/nonstiff/GraggBulirschStoerIntegrator.stabilityReduction:D (13, 4)
	844 dmul (13, 4)
	845 iload (13, 4)
	846 #4 (13, 4)
	847 iconst_0 (13, 4)
	848 invokevirtual (13, 4)
	849 org/apache/commons/math3/ode/nonstiff/GraggBulirschStoerIntegrator.filterStep:(DZZ)D (13, 4)
	851 invokestatic (13, 4)
	852 org/apache/commons/math3/util/FastMath.abs:(D)D (13, 4)
	854 dstore (13, 4)
	855 #23 (13, 4)
	856 iconst_1 (13, 4)
	857 istore (13, 4)
	858 #33 (13, 4)
	859 iconst_0 (13, 4)
	860 istore (13, 4)
	861 #37 (13, 4)
	862 goto (13, 4)
	863 -246 (13, 4)
	865 ldc2_w (14, 2)
	866 4.0 (14, 2)
	868 dload (14, 2)
	869 #31 (14, 2)
	870 dmul (14, 2)
	871 dconst_1 (14, 2)
	872 invokestatic (14, 2)
	873 org/apache/commons/math3/util/FastMath.max:(DD)D (14, 2)
	875 dstore (14, 2)
	876 #25 (14, 2)
	877 dconst_1 (15, 4)
	878 iconst_2 (15, 4)
	879 iload (15, 4)
	880 #36 (15, 4)
	881 imul (15, 4)
	882 iconst_1 (15, 4)
	883 iadd (15, 4)
	884 i2d (15, 4)
	885 ddiv (15, 4)
	886 dstore (15, 4)
	887 #38 (15, 4)
	888 aload_0 (15, 4)
	889 getfield (15, 4)
	890 org/apache/commons/math3/ode/nonstiff/GraggBulirschStoerIntegrator.stepControl2:D (15, 4)
	892 dload (15, 4)
	893 #31 (15, 4)
	894 aload_0 (15, 4)
	895 getfield (15, 4)
	896 org/apache/commons/math3/ode/nonstiff/GraggBulirschStoerIntegrator.stepControl1:D (15, 4)
	898 ddiv (15, 4)
	899 dload (15, 4)
	900 #38 (15, 4)
	901 invokestatic (15, 4)
	902 org/apache/commons/math3/util/FastMath.pow:(DD)D (15, 4)
	904 ddiv (15, 4)
	905 dstore (15, 4)
	906 #40 (15, 4)
	907 aload_0 (15, 4)
	908 getfield (15, 4)
	909 org/apache/commons/math3/ode/nonstiff/GraggBulirschStoerIntegrator.stepControl3:D (15, 4)
	911 dload (15, 4)
	912 #38 (15, 4)
	913 invokestatic (15, 4)
	914 org/apache/commons/math3/util/FastMath.pow:(DD)D (15, 4)
	916 dstore (15, 4)
	917 #42 (15, 4)
	918 dload (15, 4)
	919 #42 (15, 4)
	920 aload_0 (15, 4)
	921 getfield (15, 4)
	922 org/apache/commons/math3/ode/nonstiff/GraggBulirschStoerIntegrator.stepControl4:D (15, 4)
	924 ddiv (15, 4)
	925 dconst_1 (15, 4)
	926 dload (15, 4)
	927 #42 (15, 4)
	928 ddiv (15, 4)
	929 dload (15, 4)
	930 #40 (15, 4)
	931 invokestatic (15, 4)
	932 org/apache/commons/math3/util/FastMath.min:(DD)D (15, 4)
	934 invokestatic (15, 4)
	935 org/apache/commons/math3/util/FastMath.max:(DD)D (15, 4)
	937 dstore (15, 4)
	938 #40 (15, 4)
	939 aload_0 (16, 4)
	940 getfield (16, 4)
	941 org/apache/commons/math3/ode/nonstiff/GraggBulirschStoerIntegrator.optimalStep:[D (16, 4)
	943 iload (16, 4)
	944 #36 (16, 4)
	945 aload_0 (16, 4)
	946 aload_0 (16, 4)
	947 getfield (16, 4)
	948 org/apache/commons/math3/ode/nonstiff/GraggBulirschStoerIntegrator.stepSize:D (16, 4)
	950 dload (16, 4)
	951 #40 (16, 4)
	952 dmul (16, 4)
	953 iload (16, 4)
	954 #4 (16, 4)
	955 iconst_1 (16, 4)
	956 invokevirtual (16, 4)
	957 org/apache/commons/math3/ode/nonstiff/GraggBulirschStoerIntegrator.filterStep:(DZZ)D (16, 4)
	959 invokestatic (16, 4)
	960 org/apache/commons/math3/util/FastMath.abs:(D)D (16, 4)
	962 dastore (16, 4)
	963 aload_0 (16, 4)
	964 getfield (16, 4)
	965 org/apache/commons/math3/ode/nonstiff/GraggBulirschStoerIntegrator.costPerTimeUnit:[D (16, 4)
	967 iload (16, 4)
	968 #36 (16, 4)
	969 aload_0 (16, 4)
	970 getfield (16, 4)
	971 org/apache/commons/math3/ode/nonstiff/GraggBulirschStoerIntegrator.costPerStep:[I (16, 4)
	973 iload (16, 4)
	974 #36 (16, 4)
	975 iaload (16, 4)
	976 i2d (16, 4)
	977 aload_0 (16, 4)
	978 getfield (16, 4)
	979 org/apache/commons/math3/ode/nonstiff/GraggBulirschStoerIntegrator.optimalStep:[D (16, 4)
	981 iload (16, 4)
	982 #36 (16, 4)
	983 daload (16, 4)
	984 ddiv (16, 4)
	985 dastore (16, 4)
	986 iload (17, 5)
	987 #36 (17, 5)
	988 iload (17, 5)
	989 #21 (17, 5)
	990 isub (17, 5)
	991 tableswitch (17, 5)
	992 -1 1016 (17, 5)
	996 0 1143 (17, 5)
	1000 1 1239 (17, 5)
	1016 iload (18, 1)
	1017 #21 (18, 1)
	1018 iconst_1 (18, 1)
	1019 if_icmple (18, 1)
	1020 301 (18, 1)
	1022 iload (18, 1)
	1023 #27 (18, 1)
	1024 ifne (18, 1)
	1025 296 (18, 1)
	1027 dload (20, 1)
	1028 #31 (20, 1)
	1029 dconst_1 (20, 1)
	1030 dcmpg (20, 1)
	1031 ifgt (20, 1)
	1032 9 (20, 1)
	1034 iconst_0 (21, 4)
	1035 istore (21, 4)
	1036 #37 (21, 4)
	1037 goto (21, 4)
	1038 283 (21, 4)
	1040 aload_0 (23, 1)
	1041 getfield (23, 1)
	1042 org/apache/commons/math3/ode/nonstiff/GraggBulirschStoerIntegrator.sequence:[I (23, 1)
	1044 iload (23, 1)
	1045 #21 (23, 1)
	1046 iaload (23, 1)
	1047 i2d (23, 1)
	1048 aload_0 (23, 1)
	1049 getfield (23, 1)
	1050 org/apache/commons/math3/ode/nonstiff/GraggBulirschStoerIntegrator.sequence:[I (23, 1)
	1052 iload (23, 1)
	1053 #21 (23, 1)
	1054 iconst_1 (23, 1)
	1055 iadd (23, 1)
	1056 iaload (23, 1)
	1057 i2d (23, 1)
	1058 dmul (23, 1)
	1059 aload_0 (23, 1)
	1060 getfield (23, 1)
	1061 org/apache/commons/math3/ode/nonstiff/GraggBulirschStoerIntegrator.sequence:[I (23, 1)
	1063 iconst_0 (23, 1)
	1064 iaload (23, 1)
	1065 aload_0 (23, 1)
	1066 getfield (23, 1)
	1067 org/apache/commons/math3/ode/nonstiff/GraggBulirschStoerIntegrator.sequence:[I (23, 1)
	1069 iconst_0 (23, 1)
	1070 iaload (23, 1)
	1071 imul (23, 1)
	1072 i2d (23, 1)
	1073 ddiv (23, 1)
	1074 dstore (23, 1)
	1075 #44 (23, 1)
	1076 dload (24, 1)
	1077 #31 (24, 1)
	1078 dload (24, 1)
	1079 #44 (24, 1)
	1080 dload (24, 1)
	1081 #44 (24, 1)
	1082 dmul (24, 1)
	1083 dcmpl (24, 1)
	1084 ifle (24, 1)
	1085 56 (24, 1)
	1087 iconst_1 (24, 1)
	1088 istore (24, 1)
	1089 #33 (24, 1)
	1090 iconst_0 (24, 1)
	1091 istore (24, 1)
	1092 #37 (24, 1)
	1093 iload (24, 1)
	1094 #36 (24, 1)
	1095 istore (24, 1)
	1096 #21 (24, 1)
	1097 iload (25, 1)
	1098 #21 (25, 1)
	1099 iconst_1 (25, 1)
	1100 if_icmple (25, 1)
	1101 31 (25, 1)
	1103 aload_0 (25, 1)
	1104 getfield (25, 1)
	1105 org/apache/commons/math3/ode/nonstiff/GraggBulirschStoerIntegrator.costPerTimeUnit:[D (25, 1)
	1107 iload (25, 1)
	1108 #21 (25, 1)
	1109 iconst_1 (25, 1)
	1110 isub (25, 1)
	1111 daload (25, 1)
	1112 aload_0 (25, 1)
	1113 getfield (25, 1)
	1114 org/apache/commons/math3/ode/nonstiff/GraggBulirschStoerIntegrator.orderControl1:D (25, 1)
	1116 aload_0 (25, 1)
	1117 getfield (25, 1)
	1118 org/apache/commons/math3/ode/nonstiff/GraggBulirschStoerIntegrator.costPerTimeUnit:[D (25, 1)
	1120 iload (25, 1)
	1121 #21 (25, 1)
	1122 daload (25, 1)
	1123 dmul (25, 1)
	1124 dcmpg (25, 1)
	1125 ifge (25, 1)
	1126 6 (25, 1)
	1128 iinc (25, 1)
	1129 #21 (25, 1)
	1130 42 (25, 1)
	1131 aload_0 (25, 1)
	1132 getfield (25, 1)
	1133 org/apache/commons/math3/ode/nonstiff/GraggBulirschStoerIntegrator.optimalStep:[D (25, 1)
	1135 iload (25, 1)
	1136 #21 (25, 1)
	1137 daload (25, 1)
	1138 dstore (25, 1)
	1139 #23 (25, 1)
	1140 goto (19, 1)
	1141 180 (19, 1)
	1143 dload (18, 1)
	1144 #31 (18, 1)
	1145 dconst_1 (18, 1)
	1146 dcmpg (18, 1)
	1147 ifgt (18, 1)
	1148 9 (18, 1)
	1150 iconst_0 (18, 1)
	1151 istore (18, 1)
	1152 #37 (18, 1)
	1153 goto (18, 1)
	1154 167 (18, 1)
	1156 aload_0 (20, 1)
	1157 getfield (20, 1)
	1158 org/apache/commons/math3/ode/nonstiff/GraggBulirschStoerIntegrator.sequence:[I (20, 1)
	1160 iload (20, 1)
	1161 #36 (20, 1)
	1162 iconst_1 (20, 1)
	1163 iadd (20, 1)
	1164 iaload (20, 1)
	1165 i2d (20, 1)
	1166 aload_0 (20, 1)
	1167 getfield (20, 1)
	1168 org/apache/commons/math3/ode/nonstiff/GraggBulirschStoerIntegrator.sequence:[I (20, 1)
	1170 iconst_0 (20, 1)
	1171 iaload (20, 1)
	1172 i2d (20, 1)
	1173 ddiv (20, 1)
	1174 dstore (20, 1)
	1175 #44 (20, 1)
	1176 dload (21, 1)
	1177 #31 (21, 1)
	1178 dload (21, 1)
	1179 #44 (21, 1)
	1180 dload (21, 1)
	1181 #44 (21, 1)
	1182 dmul (21, 1)
	1183 dcmpl (21, 1)
	1184 ifle (21, 1)
	1185 52 (21, 1)
	1187 iconst_1 (21, 1)
	1188 istore (21, 1)
	1189 #33 (21, 1)
	1190 iconst_0 (21, 1)
	1191 istore (21, 1)
	1192 #37 (21, 1)
	1193 iload (22, 1)
	1194 #21 (22, 1)
	1195 iconst_1 (22, 1)
	1196 if_icmple (22, 1)
	1197 31 (22, 1)
	1199 aload_0 (22, 1)
	1200 getfield (22, 1)
	1201 org/apache/commons/math3/ode/nonstiff/GraggBulirschStoerIntegrator.costPerTimeUnit:[D (22, 1)
	1203 iload (22, 1)
	1204 #21 (22, 1)
	1205 iconst_1 (22, 1)
	1206 isub (22, 1)
	1207 daload (22, 1)
	1208 aload_0 (22, 1)
	1209 getfield (22, 1)
	1210 org/apache/commons/math3/ode/nonstiff/GraggBulirschStoerIntegrator.orderControl1:D (22, 1)
	1212 aload_0 (22, 1)
	1213 getfield (22, 1)
	1214 org/apache/commons/math3/ode/nonstiff/GraggBulirschStoerIntegrator.costPerTimeUnit:[D (22, 1)
	1216 iload (22, 1)
	1217 #21 (22, 1)
	1218 daload (22, 1)
	1219 dmul (22, 1)
	1220 dcmpg (22, 1)
	1221 ifge (22, 1)
	1222 6 (22, 1)
	1224 iinc (22, 1)
	1225 #21 (22, 1)
	1226 42 (22, 1)
	1227 aload_0 (22, 1)
	1228 getfield (22, 1)
	1229 org/apache/commons/math3/ode/nonstiff/GraggBulirschStoerIntegrator.optimalStep:[D (22, 1)
	1231 iload (22, 1)
	1232 #21 (22, 1)
	1233 daload (22, 1)
	1234 dstore (22, 1)
	1235 #23 (22, 1)
	1236 goto (17, 5)
	1237 84 (17, 5)
	1239 dload (18, 1)
	1240 #31 (18, 1)
	1241 dconst_1 (18, 1)
	1242 dcmpl (18, 1)
	1243 ifle (18, 1)
	1244 49 (18, 1)
	1246 iconst_1 (18, 1)
	1247 istore (18, 1)
	1248 #33 (18, 1)
	1249 iload (19, 1)
	1250 #21 (19, 1)
	1251 iconst_1 (19, 1)
	1252 if_icmple (19, 1)
	1253 31 (19, 1)
	1255 aload_0 (19, 1)
	1256 getfield (19, 1)
	1257 org/apache/commons/math3/ode/nonstiff/GraggBulirschStoerIntegrator.costPerTimeUnit:[D (19, 1)
	1259 iload (19, 1)
	1260 #21 (19, 1)
	1261 iconst_1 (19, 1)
	1262 isub (19, 1)
	1263 daload (19, 1)
	1264 aload_0 (19, 1)
	1265 getfield (19, 1)
	1266 org/apache/commons/math3/ode/nonstiff/GraggBulirschStoerIntegrator.orderControl1:D (19, 1)
	1268 aload_0 (19, 1)
	1269 getfield (19, 1)
	1270 org/apache/commons/math3/ode/nonstiff/GraggBulirschStoerIntegrator.costPerTimeUnit:[D (19, 1)
	1272 iload (19, 1)
	1273 #21 (19, 1)
	1274 daload (19, 1)
	1275 dmul (19, 1)
	1276 dcmpg (19, 1)
	1277 ifge (19, 1)
	1278 6 (19, 1)
	1280 iinc (19, 1)
	1281 #21 (19, 1)
	1282 42 (19, 1)
	1283 aload_0 (19, 1)
	1284 getfield (19, 1)
	1285 org/apache/commons/math3/ode/nonstiff/GraggBulirschStoerIntegrator.optimalStep:[D (19, 1)
	1287 iload (19, 1)
	1288 #21 (19, 1)
	1289 daload (19, 1)
	1290 dstore (19, 1)
	1291 #23 (19, 1)
	1292 iconst_0 (17, 5)
	1293 istore (17, 5)
	1294 #37 (17, 5)
	1295 goto (17, 5)
	1296 25 (17, 5)
	1298 iload (18, 1)
	1299 #28 (18, 1)
	1300 ifne (18, 1)
	1301 10 (18, 1)
	1303 aload_0 (18, 1)
	1304 getfield (18, 1)
	1305 org/apache/commons/math3/ode/nonstiff/GraggBulirschStoerIntegrator.isLastStep:Z (18, 1)
	1307 ifeq (18, 1)
	1308 13 (18, 1)
	1310 dload (18, 1)
	1311 #31 (18, 1)
	1312 dconst_1 (18, 1)
	1313 dcmpg (18, 1)
	1314 ifgt (18, 1)
	1315 6 (18, 1)
	1317 iconst_0 (18, 1)
	1318 istore (18, 1)
	1319 #37 (18, 1)
	1320 goto (11, 1)
	1321 -704 (11, 1)
	1323 iload (6, 1)
	1324 #33 (6, 1)
	1325 ifne (6, 1)
	1326 20 (6, 1)
	1328 aload_0 (6, 1)
	1329 aload_0 (6, 1)
	1330 getfield (6, 1)
	1331 org/apache/commons/math3/ode/nonstiff/GraggBulirschStoerIntegrator.stepStart:D (6, 1)
	1333 aload_0 (6, 1)
	1334 getfield (6, 1)
	1335 org/apache/commons/math3/ode/nonstiff/GraggBulirschStoerIntegrator.stepSize:D (6, 1)
	1337 dadd (6, 1)
	1338 aload (6, 1)
	1339 #8 (6, 1)
	1340 aload (6, 1)
	1341 #14 (6, 1)
	1342 invokevirtual (6, 1)
	1343 org/apache/commons/math3/ode/nonstiff/GraggBulirschStoerIntegrator.computeDerivatives:(D[D[D)V (6, 1)
	1345 aload_0 (5, 4)
	1346 invokevirtual (5, 4)
	1347 org/apache/commons/math3/ode/nonstiff/GraggBulirschStoerIntegrator.getMaxStep:()D (5, 4)
	1349 dstore (5, 4)
	1350 #37 (5, 4)
	1351 iload (6, 1)
	1352 #33 (6, 1)
	1353 ifne (6, 1)
	1354 467 (6, 1)
	1356 iconst_1 (7, 4)
	1357 istore (7, 4)
	1358 #39 (7, 4)
	1359 iload (7, 4)
	1360 #39 (7, 4)
	1361 iload (7, 4)
	1362 #36 (7, 4)
	1363 if_icmpgt (7, 4)
	1364 22 (7, 4)
	1366 aload_0 (7, 4)
	1367 iconst_0 (7, 4)
	1368 iload (7, 4)
	1369 #39 (7, 4)
	1370 aload (7, 4)
	1371 #11 (7, 4)
	1372 aload (7, 4)
	1373 #15 (7, 4)
	1374 iconst_0 (7, 4)
	1375 aaload (7, 4)
	1376 invokespecial (7, 4)
	1377 org/apache/commons/math3/ode/nonstiff/GraggBulirschStoerIntegrator.extrapolate:(II[[D[D)V (7, 4)
	1379 iinc (7, 4)
	1380 #39 (7, 4)
	1381 -89 (7, 4)
	1382 goto (7, 4)
	1383 -23 (7, 4)
	1385 iconst_2 (7, 1)
	1386 iload (7, 1)
	1387 #36 (7, 1)
	1388 imul (7, 1)
	1389 aload_0 (7, 1)
	1390 getfield (7, 1)
	1391 org/apache/commons/math3/ode/nonstiff/GraggBulirschStoerIntegrator.mudif:I (7, 1)
	1393 isub (7, 1)
	1394 iconst_3 (7, 1)
	1395 iadd (7, 1)
	1396 istore (7, 1)
	1397 #39 (7, 1)
	1398 iconst_0 (8, 4)
	1399 istore (8, 4)
	1400 #40 (8, 4)
	1401 iload (8, 4)
	1402 #40 (8, 4)
	1403 iload (8, 4)
	1404 #39 (8, 4)
	1405 if_icmpge (8, 4)
	1406 332 (8, 4)
	1408 iload (8, 4)
	1409 #40 (8, 4)
	1410 iconst_2 (8, 4)
	1411 idiv (8, 4)
	1412 istore (8, 4)
	1413 #41 (8, 4)
	1414 ldc2_w (8, 4)
	1415 0.5 (8, 4)
	1417 aload_0 (8, 4)
	1418 getfield (8, 4)
	1419 org/apache/commons/math3/ode/nonstiff/GraggBulirschStoerIntegrator.sequence:[I (8, 4)
	1421 iload (8, 4)
	1422 #41 (8, 4)
	1423 iaload (8, 4)
	1424 i2d (8, 4)
	1425 dmul (8, 4)
	1426 iload (8, 4)
	1427 #40 (8, 4)
	1428 invokestatic (8, 4)
	1429 org/apache/commons/math3/util/FastMath.pow:(DI)D (8, 4)
	1431 dstore (8, 4)
	1432 #42 (8, 4)
	1433 aload (8, 4)
	1434 #13 (8, 4)
	1435 iload (8, 4)
	1436 #41 (8, 4)
	1437 aaload (8, 4)
	1438 arraylength (8, 4)
	1439 iconst_2 (8, 4)
	1440 idiv (8, 4)
	1441 istore (8, 4)
	1442 #44 (8, 4)
	1443 iconst_0 (9, 4)
	1444 istore (9, 4)
	1445 #45 (9, 4)
	1446 iload (9, 4)
	1447 #45 (9, 4)
	1448 aload (9, 4)
	1449 #5 (9, 4)
	1450 arraylength (9, 4)
	1451 if_icmpge (9, 4)
	1452 36 (9, 4)
	1454 aload (9, 4)
	1455 #15 (9, 4)
	1456 iload (9, 4)
	1457 #40 (9, 4)
	1458 iconst_1 (9, 4)
	1459 iadd (9, 4)
	1460 aaload (9, 4)
	1461 iload (9, 4)
	1462 #45 (9, 4)
	1463 dload (9, 4)
	1464 #42 (9, 4)
	1465 aload (9, 4)
	1466 #13 (9, 4)
	1467 iload (9, 4)
	1468 #41 (9, 4)
	1469 aaload (9, 4)
	1470 iload (9, 4)
	1471 #44 (9, 4)
	1472 iload (9, 4)
	1473 #40 (9, 4)
	1474 iadd (9, 4)
	1475 aaload (9, 4)
	1476 iload (9, 4)
	1477 #45 (9, 4)
	1478 daload (9, 4)
	1479 dmul (9, 4)
	1480 dastore (9, 4)
	1481 iinc (9, 4)
	1482 #45 (9, 4)
	1483 -89 (9, 4)
	1484 goto (9, 4)
	1485 -38 (9, 4)
	1487 iconst_1 (9, 4)
	1488 istore (9, 4)
	1489 #45 (9, 4)
	1490 iload (9, 4)
	1491 #45 (9, 4)
	1492 iload (9, 4)
	1493 #36 (9, 4)
	1494 iload (9, 4)
	1495 #41 (9, 4)
	1496 isub (9, 4)
	1497 if_icmpgt (9, 4)
	1498 108 (9, 4)
	1500 ldc2_w (9, 4)
	1501 0.5 (9, 4)
	1503 aload_0 (9, 4)
	1504 getfield (9, 4)
	1505 org/apache/commons/math3/ode/nonstiff/GraggBulirschStoerIntegrator.sequence:[I (9, 4)
	1507 iload (9, 4)
	1508 #45 (9, 4)
	1509 iload (9, 4)
	1510 #41 (9, 4)
	1511 iadd (9, 4)
	1512 iaload (9, 4)
	1513 i2d (9, 4)
	1514 dmul (9, 4)
	1515 iload (9, 4)
	1516 #40 (9, 4)
	1517 invokestatic (9, 4)
	1518 org/apache/commons/math3/util/FastMath.pow:(DI)D (9, 4)
	1520 dstore (9, 4)
	1521 #42 (9, 4)
	1522 aload (9, 4)
	1523 #13 (9, 4)
	1524 iload (9, 4)
	1525 #41 (9, 4)
	1526 iload (9, 4)
	1527 #45 (9, 4)
	1528 iadd (9, 4)
	1529 aaload (9, 4)
	1530 arraylength (9, 4)
	1531 iconst_2 (9, 4)
	1532 idiv (9, 4)
	1533 istore (9, 4)
	1534 #44 (9, 4)
	1535 iconst_0 (10, 4)
	1536 istore (10, 4)
	1537 #46 (10, 4)
	1538 iload (10, 4)
	1539 #46 (10, 4)
	1540 aload (10, 4)
	1541 #5 (10, 4)
	1542 arraylength (10, 4)
	1543 if_icmpge (10, 4)
	1544 39 (10, 4)
	1546 aload (10, 4)
	1547 #11 (10, 4)
	1548 iload (10, 4)
	1549 #45 (10, 4)
	1550 iconst_1 (10, 4)
	1551 isub (10, 4)
	1552 aaload (10, 4)
	1553 iload (10, 4)
	1554 #46 (10, 4)
	1555 dload (10, 4)
	1556 #42 (10, 4)
	1557 aload (10, 4)
	1558 #13 (10, 4)
	1559 iload (10, 4)
	1560 #41 (10, 4)
	1561 iload (10, 4)
	1562 #45 (10, 4)
	1563 iadd (10, 4)
	1564 aaload (10, 4)
	1565 iload (10, 4)
	1566 #44 (10, 4)
	1567 iload (10, 4)
	1568 #40 (10, 4)
	1569 iadd (10, 4)
	1570 aaload (10, 4)
	1571 iload (10, 4)
	1572 #46 (10, 4)
	1573 daload (10, 4)
	1574 dmul (10, 4)
	1575 dastore (10, 4)
	1576 iinc (10, 4)
	1577 #46 (10, 4)
	1578 -89 (10, 4)
	1579 goto (10, 4)
	1580 -41 (10, 4)
	1582 aload_0 (9, 4)
	1583 iload (9, 4)
	1584 #41 (9, 4)
	1585 iload (9, 4)
	1586 #45 (9, 4)
	1587 aload (9, 4)
	1588 #11 (9, 4)
	1589 aload (9, 4)
	1590 #15 (9, 4)
	1591 iload (9, 4)
	1592 #40 (9, 4)
	1593 iconst_1 (9, 4)
	1594 iadd (9, 4)
	1595 aaload (9, 4)
	1596 invokespecial (9, 4)
	1597 org/apache/commons/math3/ode/nonstiff/GraggBulirschStoerIntegrator.extrapolate:(II[[D[D)V (9, 4)
	1599 iinc (9, 4)
	1600 #45 (9, 4)
	1601 -89 (9, 4)
	1602 goto (9, 4)
	1603 -112 (9, 4)
	1605 iconst_0 (9, 4)
	1606 istore (9, 4)
	1607 #45 (9, 4)
	1608 iload (9, 4)
	1609 #45 (9, 4)
	1610 aload (9, 4)
	1611 #5 (9, 4)
	1612 arraylength (9, 4)
	1613 if_icmpge (9, 4)
	1614 26 (9, 4)
	1616 aload (9, 4)
	1617 #15 (9, 4)
	1618 iload (9, 4)
	1619 #40 (9, 4)
	1620 iconst_1 (9, 4)
	1621 iadd (9, 4)
	1622 aaload (9, 4)
	1623 iload (9, 4)
	1624 #45 (9, 4)
	1625 dup2 (9, 4)
	1626 daload (9, 4)
	1627 aload_0 (9, 4)
	1628 getfield (9, 4)
	1629 org/apache/commons/math3/ode/nonstiff/GraggBulirschStoerIntegrator.stepSize:D (9, 4)
	1631 dmul (9, 4)
	1632 dastore (9, 4)
	1633 iinc (9, 4)
	1634 #45 (9, 4)
	1635 -89 (9, 4)
	1636 goto (9, 4)
	1637 -28 (9, 4)
	1639 iload (10, 4)
	1640 #40 (10, 4)
	1641 iconst_1 (10, 4)
	1642 iadd (10, 4)
	1643 iconst_2 (10, 4)
	1644 idiv (10, 4)
	1645 istore (10, 4)
	1646 #45 (10, 4)
	1647 iload (10, 4)
	1648 #45 (10, 4)
	1649 iload (10, 4)
	1650 #36 (10, 4)
	1651 if_icmpgt (10, 4)
	1652 80 (10, 4)
	1654 aload (11, 4)
	1655 #13 (11, 4)
	1656 iload (11, 4)
	1657 #45 (11, 4)
	1658 aaload (11, 4)
	1659 arraylength (11, 4)
	1660 iconst_1 (11, 4)
	1661 isub (11, 4)
	1662 istore (11, 4)
	1663 #46 (11, 4)
	1664 iload (11, 4)
	1665 #46 (11, 4)
	1666 iconst_2 (11, 4)
	1667 iload (11, 4)
	1668 #40 (11, 4)
	1669 iconst_1 (11, 4)
	1670 iadd (11, 4)
	1671 imul (11, 4)
	1672 if_icmplt (11, 4)
	1673 53 (11, 4)
	1675 iconst_0 (12, 4)
	1676 istore (12, 4)
	1677 #47 (12, 4)
	1678 iload (12, 4)
	1679 #47 (12, 4)
	1680 aload (12, 4)
	1681 #5 (12, 4)
	1682 arraylength (12, 4)
	1683 if_icmpge (12, 4)
	1684 36 (12, 4)
	1686 aload (12, 4)
	1687 #13 (12, 4)
	1688 iload (12, 4)
	1689 #45 (12, 4)
	1690 aaload (12, 4)
	1691 iload (12, 4)
	1692 #46 (12, 4)
	1693 aaload (12, 4)
	1694 iload (12, 4)
	1695 #47 (12, 4)
	1696 dup2 (12, 4)
	1697 daload (12, 4)
	1698 aload (12, 4)
	1699 #13 (12, 4)
	1700 iload (12, 4)
	1701 #45 (12, 4)
	1702 aaload (12, 4)
	1703 iload (12, 4)
	1704 #46 (12, 4)
	1705 iconst_2 (12, 4)
	1706 isub (12, 4)
	1707 aaload (12, 4)
	1708 iload (12, 4)
	1709 #47 (12, 4)
	1710 daload (12, 4)
	1711 dsub (12, 4)
	1712 dastore (12, 4)
	1713 iinc (12, 4)
	1714 #47 (12, 4)
	1715 -89 (12, 4)
	1716 goto (12, 4)
	1717 -38 (12, 4)
	1719 iinc (12, 4)
	1720 #46 (12, 4)
	1721 -89 (12, 4)
	1722 goto (12, 4)
	1723 -58 (12, 4)
	1725 iinc (12, 4)
	1726 #45 (12, 4)
	1727 -89 (12, 4)
	1728 goto (12, 4)
	1729 -81 (12, 4)
	1731 iinc (12, 4)
	1732 #40 (12, 4)
	1733 -89 (12, 4)
	1734 goto (12, 4)
	1735 -333 (12, 4)
	1737 iload (12, 1)
	1738 #39 (12, 1)
	1739 iflt (12, 1)
	1740 81 (12, 1)
	1742 aload (12, 1)
	1743 #22 (12, 1)
	1744 checkcast (12, 1)
	1745 org/apache/commons/math3/ode/nonstiff/GraggBulirschStoerStepInterpolator (12, 1)
	1747 astore (12, 1)
	1748 #40 (12, 1)
	1749 aload (12, 1)
	1750 #40 (12, 1)
	1751 iload (12, 1)
	1752 #39 (12, 1)
	1753 aload_0 (12, 1)
	1754 getfield (12, 1)
	1755 org/apache/commons/math3/ode/nonstiff/GraggBulirschStoerIntegrator.stepSize:D (12, 1)
	1757 invokevirtual (12, 1)
	1758 org/apache/commons/math3/ode/nonstiff/GraggBulirschStoerStepInterpolator.computeCoefficients:(ID)V (12, 1)
	1760 aload_0 (13, 1)
	1761 getfield (13, 1)
	1762 org/apache/commons/math3/ode/nonstiff/GraggBulirschStoerIntegrator.useInterpolationError:Z (13, 1)
	1764 ifeq (13, 1)
	1765 56 (13, 1)
	1767 aload (13, 1)
	1768 #40 (13, 1)
	1769 aload (13, 1)
	1770 #16 (13, 1)
	1771 invokevirtual (13, 1)
	1772 org/apache/commons/math3/ode/nonstiff/GraggBulirschStoerStepInterpolator.estimateError:([D)D (13, 1)
	1774 dstore (13, 1)
	1775 #41 (13, 1)
	1776 aload_0 (13, 1)
	1777 getfield (13, 1)
	1778 org/apache/commons/math3/ode/nonstiff/GraggBulirschStoerIntegrator.stepSize:D (13, 1)
	1780 dload (13, 1)
	1781 #41 (13, 1)
	1782 dconst_1 (13, 1)
	1783 iload (13, 1)
	1784 #39 (13, 1)
	1785 iconst_4 (13, 1)
	1786 iadd (13, 1)
	1787 i2d (13, 1)
	1788 ddiv (13, 1)
	1789 invokestatic (13, 1)
	1790 org/apache/commons/math3/util/FastMath.pow:(DD)D (13, 1)
	1792 ldc2_w (13, 1)
	1793 0.01 (13, 1)
	1795 invokestatic (13, 1)
	1796 org/apache/commons/math3/util/FastMath.max:(DD)D (13, 1)
	1798 ddiv (13, 1)
	1799 invokestatic (13, 1)
	1800 org/apache/commons/math3/util/FastMath.abs:(D)D (13, 1)
	1802 dstore (13, 1)
	1803 #37 (13, 1)
	1804 dload (14, 1)
	1805 #41 (14, 1)
	1806 ldc2_w (14, 1)
	1807 10.0 (14, 1)
	1809 dcmpl (14, 1)
	1810 ifle (14, 1)
	1811 10 (14, 1)
	1813 dload (14, 1)
	1814 #37 (14, 1)
	1815 dstore (14, 1)
	1816 #23 (14, 1)
	1817 iconst_1 (14, 1)
	1818 istore (14, 1)
	1819 #33 (14, 1)
	1820 iload (11, 1)
	1821 #33 (11, 1)
	1822 ifne (11, 1)
	1823 426 (11, 1)
	1825 aload (11, 1)
	1826 #22 (11, 1)
	1827 aload_0 (11, 1)
	1828 getfield (11, 1)
	1829 org/apache/commons/math3/ode/nonstiff/GraggBulirschStoerIntegrator.stepStart:D (11, 1)
	1831 aload_0 (11, 1)
	1832 getfield (11, 1)
	1833 org/apache/commons/math3/ode/nonstiff/GraggBulirschStoerIntegrator.stepSize:D (11, 1)
	1835 dadd (11, 1)
	1836 invokevirtual (11, 1)
	1837 org/apache/commons/math3/ode/sampling/AbstractStepInterpolator.storeTime:(D)V (11, 1)
	1839 aload_0 (11, 1)
	1840 aload_0 (11, 1)
	1841 aload (11, 1)
	1842 #22 (11, 1)
	1843 aload (11, 1)
	1844 #8 (11, 1)
	1845 aload (11, 1)
	1846 #14 (11, 1)
	1847 dload_2 (11, 1)
	1848 invokevirtual (11, 1)
	1849 org/apache/commons/math3/ode/nonstiff/GraggBulirschStoerIntegrator.acceptStep:(Lorg/apache/commons/math3/ode/sampling/AbstractStepInterpolator;[D[DD)D (11, 1)
	1851 putfield (11, 1)
	1852 org/apache/commons/math3/ode/nonstiff/GraggBulirschStoerIntegrator.stepStart:D (11, 1)
	1854 aload (11, 1)
	1855 #22 (11, 1)
	1856 aload_0 (11, 1)
	1857 getfield (11, 1)
	1858 org/apache/commons/math3/ode/nonstiff/GraggBulirschStoerIntegrator.stepStart:D (11, 1)
	1860 invokevirtual (11, 1)
	1861 org/apache/commons/math3/ode/sampling/AbstractStepInterpolator.storeTime:(D)V (11, 1)
	1863 aload (11, 1)
	1864 #8 (11, 1)
	1865 iconst_0 (11, 1)
	1866 aload (11, 1)
	1867 #6 (11, 1)
	1868 iconst_0 (11, 1)
	1869 aload (11, 1)
	1870 #5 (11, 1)
	1871 arraylength (11, 1)
	1872 invokestatic (11, 1)
	1873 java/lang/System.arraycopy:(Ljava/lang/Object;ILjava/lang/Object;II)V (11, 1)
	1875 aload (11, 1)
	1876 #14 (11, 1)
	1877 iconst_0 (11, 1)
	1878 aload (11, 1)
	1879 #7 (11, 1)
	1880 iconst_0 (11, 1)
	1881 aload (11, 1)
	1882 #5 (11, 1)
	1883 arraylength (11, 1)
	1884 invokestatic (11, 1)
	1885 java/lang/System.arraycopy:(Ljava/lang/Object;ILjava/lang/Object;II)V (11, 1)
	1887 iconst_1 (11, 1)
	1888 istore (11, 1)
	1889 #30 (11, 1)
	1890 iload (12, 1)
	1891 #36 (12, 1)
	1892 iconst_1 (12, 1)
	1893 if_icmpne (12, 1)
	1894 17 (12, 1)
	1896 iconst_2 (12, 1)
	1897 istore (12, 1)
	1898 #39 (12, 1)
	1899 iload (13, 1)
	1900 #27 (13, 1)
	1901 ifeq (13, 1)
	1902 180 (13, 1)
	1904 iconst_1 (13, 1)
	1905 istore (13, 1)
	1906 #39 (13, 1)
	1907 goto (13, 1)
	1908 174 (13, 1)
	1910 iload (13, 1)
	1911 #36 (13, 1)
	1912 iload (13, 1)
	1913 #21 (13, 1)
	1914 if_icmpgt (13, 1)
	1915 85 (13, 1)
	1917 iload (13, 1)
	1918 #36 (13, 1)
	1919 istore (13, 1)
	1920 #39 (13, 1)
	1921 aload_0 (14, 1)
	1922 getfield (14, 1)
	1923 org/apache/commons/math3/ode/nonstiff/GraggBulirschStoerIntegrator.costPerTimeUnit:[D (14, 1)
	1925 iload (14, 1)
	1926 #36 (14, 1)
	1927 iconst_1 (14, 1)
	1928 isub (14, 1)
	1929 daload (14, 1)
	1930 aload_0 (14, 1)
	1931 getfield (14, 1)
	1932 org/apache/commons/math3/ode/nonstiff/GraggBulirschStoerIntegrator.orderControl1:D (14, 1)
	1934 aload_0 (14, 1)
	1935 getfield (14, 1)
	1936 org/apache/commons/math3/ode/nonstiff/GraggBulirschStoerIntegrator.costPerTimeUnit:[D (14, 1)
	1938 iload (14, 1)
	1939 #36 (14, 1)
	1940 daload (14, 1)
	1941 dmul (14, 1)
	1942 dcmpg (14, 1)
	1943 ifge (14, 1)
	1944 12 (14, 1)
	1946 iload (14, 1)
	1947 #36 (14, 1)
	1948 iconst_1 (14, 1)
	1949 isub (14, 1)
	1950 istore (14, 1)
	1951 #39 (14, 1)
	1952 goto (14, 1)
	1953 129 (14, 1)
	1955 aload_0 (15, 1)
	1956 getfield (15, 1)
	1957 org/apache/commons/math3/ode/nonstiff/GraggBulirschStoerIntegrator.costPerTimeUnit:[D (15, 1)
	1959 iload (15, 1)
	1960 #36 (15, 1)
	1961 daload (15, 1)
	1962 aload_0 (15, 1)
	1963 getfield (15, 1)
	1964 org/apache/commons/math3/ode/nonstiff/GraggBulirschStoerIntegrator.orderControl2:D (15, 1)
	1966 aload_0 (15, 1)
	1967 getfield (15, 1)
	1968 org/apache/commons/math3/ode/nonstiff/GraggBulirschStoerIntegrator.costPerTimeUnit:[D (15, 1)
	1970 iload (15, 1)
	1971 #36 (15, 1)
	1972 iconst_1 (15, 1)
	1973 isub (15, 1)
	1974 daload (15, 1)
	1975 dmul (15, 1)
	1976 dcmpg (15, 1)
	1977 ifge (15, 1)
	1978 104 (15, 1)
	1980 iload (15, 1)
	1981 #36 (15, 1)
	1982 iconst_1 (15, 1)
	1983 iadd (15, 1)
	1984 aload_0 (15, 1)
	1985 getfield (15, 1)
	1986 org/apache/commons/math3/ode/nonstiff/GraggBulirschStoerIntegrator.sequence:[I (15, 1)
	1988 arraylength (15, 1)
	1989 iconst_2 (15, 1)
	1990 isub (15, 1)
	1991 invokestatic (15, 1)
	1992 org/apache/commons/math3/util/FastMath.min:(II)I (15, 1)
	1994 istore (15, 1)
	1995 #39 (15, 1)
	1996 goto (15, 1)
	1997 85 (15, 1)
	1999 iload (14, 2)
	2000 #36 (14, 2)
	2001 iconst_1 (14, 2)
	2002 isub (14, 2)
	2003 istore (14, 2)
	2004 #39 (14, 2)
	2005 iload (15, 1)
	2006 #36 (15, 1)
	2007 iconst_2 (15, 1)
	2008 if_icmple (15, 1)
	2009 36 (15, 1)
	2011 aload_0 (15, 1)
	2012 getfield (15, 1)
	2013 org/apache/commons/math3/ode/nonstiff/GraggBulirschStoerIntegrator.costPerTimeUnit:[D (15, 1)
	2015 iload (15, 1)
	2016 #36 (15, 1)
	2017 iconst_2 (15, 1)
	2018 isub (15, 1)
	2019 daload (15, 1)
	2020 aload_0 (15, 1)
	2021 getfield (15, 1)
	2022 org/apache/commons/math3/ode/nonstiff/GraggBulirschStoerIntegrator.orderControl1:D (15, 1)
	2024 aload_0 (15, 1)
	2025 getfield (15, 1)
	2026 org/apache/commons/math3/ode/nonstiff/GraggBulirschStoerIntegrator.costPerTimeUnit:[D (15, 1)
	2028 iload (15, 1)
	2029 #36 (15, 1)
	2030 iconst_1 (15, 1)
	2031 isub (15, 1)
	2032 daload (15, 1)
	2033 dmul (15, 1)
	2034 dcmpg (15, 1)
	2035 ifge (15, 1)
	2036 9 (15, 1)
	2038 iload (15, 1)
	2039 #36 (15, 1)
	2040 iconst_2 (15, 1)
	2041 isub (15, 1)
	2042 istore (15, 1)
	2043 #39 (15, 1)
	2044 aload_0 (16, 1)
	2045 getfield (16, 1)
	2046 org/apache/commons/math3/ode/nonstiff/GraggBulirschStoerIntegrator.costPerTimeUnit:[D (16, 1)
	2048 iload (16, 1)
	2049 #36 (16, 1)
	2050 daload (16, 1)
	2051 aload_0 (16, 1)
	2052 getfield (16, 1)
	2053 org/apache/commons/math3/ode/nonstiff/GraggBulirschStoerIntegrator.orderControl2:D (16, 1)
	2055 aload_0 (16, 1)
	2056 getfield (16, 1)
	2057 org/apache/commons/math3/ode/nonstiff/GraggBulirschStoerIntegrator.costPerTimeUnit:[D (16, 1)
	2059 iload (16, 1)
	2060 #39 (16, 1)
	2061 daload (16, 1)
	2062 dmul (16, 1)
	2063 dcmpg (16, 1)
	2064 ifge (16, 1)
	2065 17 (16, 1)
	2067 iload (16, 1)
	2068 #36 (16, 1)
	2069 aload_0 (16, 1)
	2070 getfield (16, 1)
	2071 org/apache/commons/math3/ode/nonstiff/GraggBulirschStoerIntegrator.sequence:[I (16, 1)
	2073 arraylength (16, 1)
	2074 iconst_2 (16, 1)
	2075 isub (16, 1)
	2076 invokestatic (16, 1)
	2077 org/apache/commons/math3/util/FastMath.min:(II)I (16, 1)
	2079 istore (16, 1)
	2080 #39 (16, 1)
	2081 iload (12, 1)
	2082 #27 (12, 1)
	2083 ifeq (12, 1)
	2084 34 (12, 1)
	2086 iload (12, 1)
	2087 #39 (12, 1)
	2088 iload (12, 1)
	2089 #36 (12, 1)
	2090 invokestatic (12, 1)
	2091 org/apache/commons/math3/util/FastMath.min:(II)I (12, 1)
	2093 istore (12, 1)
	2094 #21 (12, 1)
	2095 aload_0 (12, 1)
	2096 getfield (12, 1)
	2097 org/apache/commons/math3/ode/nonstiff/GraggBulirschStoerIntegrator.stepSize:D (12, 1)
	2099 invokestatic (12, 1)
	2100 org/apache/commons/math3/util/FastMath.abs:(D)D (12, 1)
	2102 aload_0 (12, 1)
	2103 getfield (12, 1)
	2104 org/apache/commons/math3/ode/nonstiff/GraggBulirschStoerIntegrator.optimalStep:[D (12, 1)
	2106 iload (12, 1)
	2107 #21 (12, 1)
	2108 daload (12, 1)
	2109 invokestatic (12, 1)
	2110 org/apache/commons/math3/util/FastMath.min:(DD)D (12, 1)
	2112 dstore (12, 1)
	2113 #23 (12, 1)
	2114 goto (12, 1)
	2115 131 (12, 1)
	2117 iload (14, 1)
	2118 #39 (14, 1)
	2119 iload (14, 1)
	2120 #36 (14, 1)
	2121 if_icmpgt (14, 1)
	2122 15 (14, 1)
	2124 aload_0 (14, 1)
	2125 getfield (14, 1)
	2126 org/apache/commons/math3/ode/nonstiff/GraggBulirschStoerIntegrator.optimalStep:[D (14, 1)
	2128 iload (14, 1)
	2129 #39 (14, 1)
	2130 daload (14, 1)
	2131 dstore (14, 1)
	2132 #23 (14, 1)
	2133 goto (14, 1)
	2134 108 (14, 1)
	2136 iload (16, 1)
	2137 #36 (16, 1)
	2138 iload (16, 1)
	2139 #21 (16, 1)
	2140 if_icmpge (16, 1)
	2141 67 (16, 1)
	2143 aload_0 (16, 1)
	2144 getfield (16, 1)
	2145 org/apache/commons/math3/ode/nonstiff/GraggBulirschStoerIntegrator.costPerTimeUnit:[D (16, 1)
	2147 iload (16, 1)
	2148 #36 (16, 1)
	2149 daload (16, 1)
	2150 aload_0 (16, 1)
	2151 getfield (16, 1)
	2152 org/apache/commons/math3/ode/nonstiff/GraggBulirschStoerIntegrator.orderControl2:D (16, 1)
	2154 aload_0 (16, 1)
	2155 getfield (16, 1)
	2156 org/apache/commons/math3/ode/nonstiff/GraggBulirschStoerIntegrator.costPerTimeUnit:[D (16, 1)
	2158 iload (16, 1)
	2159 #36 (16, 1)
	2160 iconst_1 (16, 1)
	2161 isub (16, 1)
	2162 daload (16, 1)
	2163 dmul (16, 1)
	2164 dcmpg (16, 1)
	2165 ifge (16, 1)
	2166 42 (16, 1)
	2168 aload_0 (16, 1)
	2169 aload_0 (16, 1)
	2170 getfield (16, 1)
	2171 org/apache/commons/math3/ode/nonstiff/GraggBulirschStoerIntegrator.optimalStep:[D (16, 1)
	2173 iload (16, 1)
	2174 #36 (16, 1)
	2175 daload (16, 1)
	2176 aload_0 (16, 1)
	2177 getfield (16, 1)
	2178 org/apache/commons/math3/ode/nonstiff/GraggBulirschStoerIntegrator.costPerStep:[I (16, 1)
	2180 iload (16, 1)
	2181 #39 (16, 1)
	2182 iconst_1 (16, 1)
	2183 iadd (16, 1)
	2184 iaload (16, 1)
	2185 i2d (16, 1)
	2186 dmul (16, 1)
	2187 aload_0 (16, 1)
	2188 getfield (16, 1)
	2189 org/apache/commons/math3/ode/nonstiff/GraggBulirschStoerIntegrator.costPerStep:[I (16, 1)
	2191 iload (16, 1)
	2192 #36 (16, 1)
	2193 iaload (16, 1)
	2194 i2d (16, 1)
	2195 ddiv (16, 1)
	2196 iload (16, 1)
	2197 #4 (16, 1)
	2198 iconst_0 (16, 1)
	2199 invokevirtual (16, 1)
	2200 org/apache/commons/math3/ode/nonstiff/GraggBulirschStoerIntegrator.filterStep:(DZZ)D (16, 1)
	2202 dstore (16, 1)
	2203 #23 (16, 1)
	2204 goto (16, 1)
	2205 37 (16, 1)
	2207 aload_0 (18, 2)
	2208 aload_0 (18, 2)
	2209 getfield (18, 2)
	2210 org/apache/commons/math3/ode/nonstiff/GraggBulirschStoerIntegrator.optimalStep:[D (18, 2)
	2212 iload (18, 2)
	2213 #36 (18, 2)
	2214 daload (18, 2)
	2215 aload_0 (18, 2)
	2216 getfield (18, 2)
	2217 org/apache/commons/math3/ode/nonstiff/GraggBulirschStoerIntegrator.costPerStep:[I (18, 2)
	2219 iload (18, 2)
	2220 #39 (18, 2)
	2221 iaload (18, 2)
	2222 i2d (18, 2)
	2223 dmul (18, 2)
	2224 aload_0 (18, 2)
	2225 getfield (18, 2)
	2226 org/apache/commons/math3/ode/nonstiff/GraggBulirschStoerIntegrator.costPerStep:[I (18, 2)
	2228 iload (18, 2)
	2229 #36 (18, 2)
	2230 iaload (18, 2)
	2231 i2d (18, 2)
	2232 ddiv (18, 2)
	2233 iload (18, 2)
	2234 #4 (18, 2)
	2235 iconst_0 (18, 2)
	2236 invokevirtual (18, 2)
	2237 org/apache/commons/math3/ode/nonstiff/GraggBulirschStoerIntegrator.filterStep:(DZZ)D (18, 2)
	2239 dstore (18, 2)
	2240 #23 (18, 2)
	2241 iload (13, 2)
	2242 #39 (13, 2)
	2243 istore (13, 2)
	2244 #21 (13, 2)
	2245 iconst_1 (11, 1)
	2246 istore (11, 1)
	2247 #29 (11, 1)
	2248 dload (10, 4)
	2249 #23 (10, 4)
	2250 dload (10, 4)
	2251 #37 (10, 4)
	2252 invokestatic (10, 4)
	2253 org/apache/commons/math3/util/FastMath.min:(DD)D (10, 4)
	2255 dstore (10, 4)
	2256 #23 (10, 4)
	2257 iload (11, 1)
	2258 #4 (11, 1)
	2259 ifne (11, 1)
	2260 8 (11, 1)
	2262 dload (11, 1)
	2263 #23 (11, 1)
	2264 dneg (11, 1)
	2265 dstore (11, 1)
	2266 #23 (11, 1)
	2267 iconst_0 (10, 4)
	2268 istore (10, 4)
	2269 #28 (10, 4)
	2270 iload (11, 1)
	2271 #33 (11, 1)
	2272 ifeq (11, 1)
	2273 14 (11, 1)
	2275 aload_0 (11, 1)
	2276 iconst_0 (11, 1)
	2277 putfield (11, 1)
	2278 org/apache/commons/math3/ode/nonstiff/GraggBulirschStoerIntegrator.isLastStep:Z (11, 1)
	2280 iconst_1 (11, 1)
	2281 istore (11, 1)
	2282 #27 (11, 1)
	2283 goto (11, 1)
	2284 6 (11, 1)
	2286 iconst_0 (12, 2)
	2287 istore (12, 2)
	2288 #27 (12, 2)
	2289 aload_0 (11, 3)
	2290 getfield (11, 3)
	2291 org/apache/commons/math3/ode/nonstiff/GraggBulirschStoerIntegrator.isLastStep:Z (11, 3)
	2293 ifeq (11, 3)
	2294 -1850 (11, 3)
	2296 aload_1 (11, 3)
	2297 aload_0 (11, 3)
	2298 getfield (11, 3)
	2299 org/apache/commons/math3/ode/nonstiff/GraggBulirschStoerIntegrator.stepStart:D (11, 3)
	2301 invokevirtual (11, 3)
	2302 org/apache/commons/math3/ode/ExpandableStatefulODE.setTime:(D)V (11, 3)
	2304 aload_1 (11, 3)
	2305 aload (11, 3)
	2306 #6 (11, 3)
	2307 invokevirtual (11, 3)
	2308 org/apache/commons/math3/ode/ExpandableStatefulODE.setCompleteState:([D)V (11, 3)
	2310 aload_0 (11, 3)
	2311 invokevirtual (11, 3)
	2312 org/apache/commons/math3/ode/nonstiff/GraggBulirschStoerIntegrator.resetInternalState:()V (11, 3)
	2314 return (3, 1)

