Method: <init>
	0 aload_0 (0, 0)
	1 aload_1 (0, 0)
	2 invokespecial (0, 0)
	3 org/apache/commons/math3/ode/sampling/AbstractStepInterpolator.<init>:(Lorg/apache/commons/math3/ode/sampling/AbstractStepInterpolator;)V (0, 0)
	5 aload_0 (0, 0)
	6 getfield (0, 0)
	7 org/apache/commons/math3/ode/nonstiff/GraggBulirschStoerStepInterpolator.currentState:[D (0, 0)
	9 arraylength (0, 0)
	10 istore_2 (0, 0)
	11 aload_0 (0, 0)
	12 aconst_null (0, 0)
	13 putfield (0, 0)
	14 org/apache/commons/math3/ode/nonstiff/GraggBulirschStoerStepInterpolator.y0Dot:[D (0, 0)
	16 aload_0 (0, 0)
	17 aconst_null (0, 0)
	18 putfield (0, 0)
	19 org/apache/commons/math3/ode/nonstiff/GraggBulirschStoerStepInterpolator.y1:[D (0, 0)
	21 aload_0 (0, 0)
	22 aconst_null (0, 0)
	23 putfield (0, 0)
	24 org/apache/commons/math3/ode/nonstiff/GraggBulirschStoerStepInterpolator.y1Dot:[D (0, 0)
	26 aload_0 (0, 0)
	27 aconst_null (0, 0)
	28 checkcast (0, 0)
	29 [[D (0, 0)
	31 putfield (0, 0)
	32 org/apache/commons/math3/ode/nonstiff/GraggBulirschStoerStepInterpolator.yMidDots:[[D (0, 0)
	34 aload_1 (1, 1)
	35 getfield (1, 1)
	36 org/apache/commons/math3/ode/nonstiff/GraggBulirschStoerStepInterpolator.polynomials:[[D (1, 1)
	38 ifnonnull (1, 1)
	39 19 (1, 1)
	41 aload_0 (1, 1)
	42 aconst_null (1, 1)
	43 checkcast (1, 1)
	44 [[D (1, 1)
	46 putfield (1, 1)
	47 org/apache/commons/math3/ode/nonstiff/GraggBulirschStoerStepInterpolator.polynomials:[[D (1, 1)
	49 aload_0 (1, 1)
	50 iconst_m1 (1, 1)
	51 putfield (1, 1)
	52 org/apache/commons/math3/ode/nonstiff/GraggBulirschStoerStepInterpolator.currentDegree:I (1, 1)
	54 goto (1, 1)
	55 63 (1, 1)
	57 aload_0 (2, 2)
	58 aload_1 (2, 2)
	59 getfield (2, 2)
	60 org/apache/commons/math3/ode/nonstiff/GraggBulirschStoerStepInterpolator.currentDegree:I (2, 2)
	62 invokespecial (2, 2)
	63 org/apache/commons/math3/ode/nonstiff/GraggBulirschStoerStepInterpolator.resetTables:(I)V (2, 2)
	65 iconst_0 (3, 4)
	66 istore_3 (3, 4)
	67 iload_3 (3, 4)
	68 aload_0 (3, 4)
	69 getfield (3, 4)
	70 org/apache/commons/math3/ode/nonstiff/GraggBulirschStoerStepInterpolator.polynomials:[[D (3, 4)
	72 arraylength (3, 4)
	73 if_icmpge (3, 4)
	74 36 (3, 4)
	76 aload_0 (3, 4)
	77 getfield (3, 4)
	78 org/apache/commons/math3/ode/nonstiff/GraggBulirschStoerStepInterpolator.polynomials:[[D (3, 4)
	80 iload_3 (3, 4)
	81 iload_2 (3, 4)
	82 newarray (3, 4)
	83 7 (3, 4)
	84 aastore (3, 4)
	85 aload_1 (3, 4)
	86 getfield (3, 4)
	87 org/apache/commons/math3/ode/nonstiff/GraggBulirschStoerStepInterpolator.polynomials:[[D (3, 4)
	89 iload_3 (3, 4)
	90 aaload (3, 4)
	91 iconst_0 (3, 4)
	92 aload_0 (3, 4)
	93 getfield (3, 4)
	94 org/apache/commons/math3/ode/nonstiff/GraggBulirschStoerStepInterpolator.polynomials:[[D (3, 4)
	96 iload_3 (3, 4)
	97 aaload (3, 4)
	98 iconst_0 (3, 4)
	99 iload_2 (3, 4)
	100 invokestatic (3, 4)
	101 java/lang/System.arraycopy:(Ljava/lang/Object;ILjava/lang/Object;II)V (3, 4)
	103 iinc (3, 4)
	104 #3 (3, 4)
	105 -89 (3, 4)
	106 goto (3, 4)
	107 -39 (3, 4)
	109 aload_0 (2, 2)
	110 aload_1 (2, 2)
	111 getfield (2, 2)
	112 org/apache/commons/math3/ode/nonstiff/GraggBulirschStoerStepInterpolator.currentDegree:I (2, 2)
	114 putfield (2, 2)
	115 org/apache/commons/math3/ode/nonstiff/GraggBulirschStoerStepInterpolator.currentDegree:I (2, 2)
	117 return (0, 0)

Method: resetTables
	0 iload_1 (1, 1)
	1 ifge (1, 1)
	2 24 (1, 1)
	4 aload_0 (1, 1)
	5 aconst_null (1, 1)
	6 checkcast (1, 1)
	7 [[D (1, 1)
	9 putfield (1, 1)
	10 org/apache/commons/math3/ode/nonstiff/GraggBulirschStoerStepInterpolator.polynomials:[[D (1, 1)
	12 aload_0 (1, 1)
	13 aconst_null (1, 1)
	14 putfield (1, 1)
	15 org/apache/commons/math3/ode/nonstiff/GraggBulirschStoerStepInterpolator.errfac:[D (1, 1)
	17 aload_0 (1, 1)
	18 iconst_m1 (1, 1)
	19 putfield (1, 1)
	20 org/apache/commons/math3/ode/nonstiff/GraggBulirschStoerStepInterpolator.currentDegree:I (1, 1)
	22 goto (1, 1)
	23 204 (1, 1)
	25 iload_1 (2, 2)
	26 iconst_1 (2, 2)
	27 iadd (2, 2)
	28 anewarray (2, 2)
	29 [D (2, 2)
	31 astore_2 (2, 2)
	32 aload_0 (3, 1)
	33 getfield (3, 1)
	34 org/apache/commons/math3/ode/nonstiff/GraggBulirschStoerStepInterpolator.polynomials:[[D (3, 1)
	36 ifnull (3, 1)
	37 49 (3, 1)
	39 aload_0 (3, 1)
	40 getfield (3, 1)
	41 org/apache/commons/math3/ode/nonstiff/GraggBulirschStoerStepInterpolator.polynomials:[[D (3, 1)
	43 iconst_0 (3, 1)
	44 aload_2 (3, 1)
	45 iconst_0 (3, 1)
	46 aload_0 (3, 1)
	47 getfield (3, 1)
	48 org/apache/commons/math3/ode/nonstiff/GraggBulirschStoerStepInterpolator.polynomials:[[D (3, 1)
	50 arraylength (3, 1)
	51 invokestatic (3, 1)
	52 java/lang/System.arraycopy:(Ljava/lang/Object;ILjava/lang/Object;II)V (3, 1)
	54 aload_0 (4, 4)
	55 getfield (4, 4)
	56 org/apache/commons/math3/ode/nonstiff/GraggBulirschStoerStepInterpolator.polynomials:[[D (4, 4)
	58 arraylength (4, 4)
	59 istore_3 (4, 4)
	60 iload_3 (4, 4)
	61 aload_2 (4, 4)
	62 arraylength (4, 4)
	63 if_icmpge (4, 4)
	64 19 (4, 4)
	66 aload_2 (4, 4)
	67 iload_3 (4, 4)
	68 aload_0 (4, 4)
	69 getfield (4, 4)
	70 org/apache/commons/math3/ode/nonstiff/GraggBulirschStoerStepInterpolator.currentState:[D (4, 4)
	72 arraylength (4, 4)
	73 newarray (4, 4)
	74 7 (4, 4)
	75 aastore (4, 4)
	76 iinc (4, 4)
	77 #3 (4, 4)
	78 -89 (4, 4)
	79 goto (4, 4)
	80 -19 (4, 4)
	82 goto (4, 4)
	83 27 (4, 4)
	85 iconst_0 (5, 4)
	86 istore_3 (5, 4)
	87 iload_3 (5, 4)
	88 aload_2 (5, 4)
	89 arraylength (5, 4)
	90 if_icmpge (5, 4)
	91 19 (5, 4)
	93 aload_2 (5, 4)
	94 iload_3 (5, 4)
	95 aload_0 (5, 4)
	96 getfield (5, 4)
	97 org/apache/commons/math3/ode/nonstiff/GraggBulirschStoerStepInterpolator.currentState:[D (5, 4)
	99 arraylength (5, 4)
	100 newarray (5, 4)
	101 7 (5, 4)
	102 aastore (5, 4)
	103 iinc (5, 4)
	104 #3 (5, 4)
	105 -89 (5, 4)
	106 goto (5, 4)
	107 -19 (5, 4)
	109 aload_0 (2, 2)
	110 aload_2 (2, 2)
	111 putfield (2, 2)
	112 org/apache/commons/math3/ode/nonstiff/GraggBulirschStoerStepInterpolator.polynomials:[[D (2, 2)
	114 iload_1 (4, 1)
	115 iconst_4 (4, 1)
	116 if_icmpgt (4, 1)
	117 11 (4, 1)
	119 aload_0 (4, 1)
	120 aconst_null (4, 1)
	121 putfield (4, 1)
	122 org/apache/commons/math3/ode/nonstiff/GraggBulirschStoerStepInterpolator.errfac:[D (4, 1)
	124 goto (4, 1)
	125 97 (4, 1)
	127 aload_0 (5, 2)
	128 iload_1 (5, 2)
	129 iconst_4 (5, 2)
	130 isub (5, 2)
	131 newarray (5, 2)
	132 7 (5, 2)
	133 putfield (5, 2)
	134 org/apache/commons/math3/ode/nonstiff/GraggBulirschStoerStepInterpolator.errfac:[D (5, 2)
	136 iconst_0 (6, 4)
	137 istore_3 (6, 4)
	138 iload_3 (6, 4)
	139 aload_0 (6, 4)
	140 getfield (6, 4)
	141 org/apache/commons/math3/ode/nonstiff/GraggBulirschStoerStepInterpolator.errfac:[D (6, 4)
	143 arraylength (6, 4)
	144 if_icmpge (6, 4)
	145 77 (6, 4)
	147 iload_3 (6, 4)
	148 iconst_5 (6, 4)
	149 iadd (6, 4)
	150 istore (6, 4)
	151 #4 (6, 4)
	152 aload_0 (6, 4)
	153 getfield (6, 4)
	154 org/apache/commons/math3/ode/nonstiff/GraggBulirschStoerStepInterpolator.errfac:[D (6, 4)
	156 iload_3 (6, 4)
	157 dconst_1 (6, 4)
	158 iload (6, 4)
	159 #4 (6, 4)
	160 iload (6, 4)
	161 #4 (6, 4)
	162 imul (6, 4)
	163 i2d (6, 4)
	164 ddiv (6, 4)
	165 dastore (6, 4)
	166 ldc2_w (6, 4)
	167 0.5 (6, 4)
	169 iload_3 (6, 4)
	170 iconst_1 (6, 4)
	171 iadd (6, 4)
	172 i2d (6, 4)
	173 iload (6, 4)
	174 #4 (6, 4)
	175 i2d (6, 4)
	176 ddiv (6, 4)
	177 invokestatic (6, 4)
	178 org/apache/commons/math3/util/FastMath.sqrt:(D)D (6, 4)
	180 dmul (6, 4)
	181 dstore (6, 4)
	182 #5 (6, 4)
	183 iconst_0 (7, 4)
	184 istore (7, 4)
	185 #7 (7, 4)
	186 iload (7, 4)
	187 #7 (7, 4)
	188 iload_3 (7, 4)
	189 if_icmpgt (7, 4)
	190 26 (7, 4)
	192 aload_0 (7, 4)
	193 getfield (7, 4)
	194 org/apache/commons/math3/ode/nonstiff/GraggBulirschStoerStepInterpolator.errfac:[D (7, 4)
	196 iload_3 (7, 4)
	197 dup2 (7, 4)
	198 daload (7, 4)
	199 dload (7, 4)
	200 #5 (7, 4)
	201 iload (7, 4)
	202 #7 (7, 4)
	203 iconst_1 (7, 4)
	204 iadd (7, 4)
	205 i2d (7, 4)
	206 ddiv (7, 4)
	207 dmul (7, 4)
	208 dastore (7, 4)
	209 iinc (7, 4)
	210 #7 (7, 4)
	211 -89 (7, 4)
	212 goto (7, 4)
	213 -26 (7, 4)
	215 iinc (7, 4)
	216 #3 (7, 4)
	217 -89 (7, 4)
	218 goto (7, 4)
	219 -80 (7, 4)
	221 aload_0 (5, 2)
	222 iconst_0 (5, 2)
	223 putfield (5, 2)
	224 org/apache/commons/math3/ode/nonstiff/GraggBulirschStoerStepInterpolator.currentDegree:I (5, 2)
	226 return (0, 0)

Method: doCopy
	0 new (0, 0)
	1 org/apache/commons/math3/ode/nonstiff/GraggBulirschStoerStepInterpolator (0, 0)
	3 dup (0, 0)
	4 aload_0 (0, 0)
	5 invokespecial (0, 0)
	6 org/apache/commons/math3/ode/nonstiff/GraggBulirschStoerStepInterpolator.<init>:(Lorg/apache/commons/math3/ode/nonstiff/GraggBulirschStoerStepInterpolator;)V (0, 0)
	8 areturn (0, 0)

Method: computeCoefficients
	0 aload_0 (1, 1)
	1 getfield (1, 1)
	2 org/apache/commons/math3/ode/nonstiff/GraggBulirschStoerStepInterpolator.polynomials:[[D (1, 1)
	4 ifnull (1, 1)
	5 14 (1, 1)
	7 aload_0 (1, 1)
	8 getfield (1, 1)
	9 org/apache/commons/math3/ode/nonstiff/GraggBulirschStoerStepInterpolator.polynomials:[[D (1, 1)
	11 arraylength (1, 1)
	12 iload_1 (1, 1)
	13 iconst_4 (1, 1)
	14 iadd (1, 1)
	15 if_icmpgt (1, 1)
	16 10 (1, 1)
	18 aload_0 (1, 1)
	19 iload_1 (1, 1)
	20 iconst_4 (1, 1)
	21 iadd (1, 1)
	22 invokespecial (1, 1)
	23 org/apache/commons/math3/ode/nonstiff/GraggBulirschStoerStepInterpolator.resetTables:(I)V (1, 1)
	25 aload_0 (0, 0)
	26 iload_1 (0, 0)
	27 iconst_4 (0, 0)
	28 iadd (0, 0)
	29 putfield (0, 0)
	30 org/apache/commons/math3/ode/nonstiff/GraggBulirschStoerStepInterpolator.currentDegree:I (0, 0)
	32 iconst_0 (1, 4)
	33 istore (1, 4)
	34 #4 (1, 4)
	35 iload (1, 4)
	36 #4 (1, 4)
	37 aload_0 (1, 4)
	38 getfield (1, 4)
	39 org/apache/commons/math3/ode/nonstiff/GraggBulirschStoerStepInterpolator.currentState:[D (1, 4)
	41 arraylength (1, 4)
	42 if_icmpge (1, 4)
	43 425 (1, 4)
	45 dload_2 (1, 4)
	46 aload_0 (1, 4)
	47 getfield (1, 4)
	48 org/apache/commons/math3/ode/nonstiff/GraggBulirschStoerStepInterpolator.y0Dot:[D (1, 4)
	50 iload (1, 4)
	51 #4 (1, 4)
	52 daload (1, 4)
	53 dmul (1, 4)
	54 dstore (1, 4)
	55 #5 (1, 4)
	56 dload_2 (1, 4)
	57 aload_0 (1, 4)
	58 getfield (1, 4)
	59 org/apache/commons/math3/ode/nonstiff/GraggBulirschStoerStepInterpolator.y1Dot:[D (1, 4)
	61 iload (1, 4)
	62 #4 (1, 4)
	63 daload (1, 4)
	64 dmul (1, 4)
	65 dstore (1, 4)
	66 #7 (1, 4)
	67 aload_0 (2, 1)
	68 getfield (2, 1)
	69 org/apache/commons/math3/ode/nonstiff/GraggBulirschStoerStepInterpolator.y1:[D (2, 1)
	71 iload (2, 1)
	72 #4 (2, 1)
	73 daload (2, 1)
	74 aload_0 (2, 1)
	75 getfield (2, 1)
	76 org/apache/commons/math3/ode/nonstiff/GraggBulirschStoerStepInterpolator.currentState:[D (2, 1)
	78 iload (2, 1)
	79 #4 (2, 1)
	80 daload (2, 1)
	81 dsub (2, 1)
	82 dstore (2, 1)
	83 #9 (2, 1)
	84 dload (3, 1)
	85 #9 (3, 1)
	86 dload (3, 1)
	87 #7 (3, 1)
	88 dsub (3, 1)
	89 dstore (3, 1)
	90 #11 (3, 1)
	91 dload (4, 1)
	92 #5 (4, 1)
	93 dload (4, 1)
	94 #9 (4, 1)
	95 dsub (4, 1)
	96 dstore (4, 1)
	97 #13 (4, 1)
	98 aload_0 (4, 1)
	99 getfield (4, 1)
	100 org/apache/commons/math3/ode/nonstiff/GraggBulirschStoerStepInterpolator.polynomials:[[D (4, 1)
	102 iconst_0 (4, 1)
	103 aaload (4, 1)
	104 iload (4, 1)
	105 #4 (4, 1)
	106 aload_0 (4, 1)
	107 getfield (4, 1)
	108 org/apache/commons/math3/ode/nonstiff/GraggBulirschStoerStepInterpolator.currentState:[D (4, 1)
	110 iload (4, 1)
	111 #4 (4, 1)
	112 daload (4, 1)
	113 dastore (4, 1)
	114 aload_0 (5, 1)
	115 getfield (5, 1)
	116 org/apache/commons/math3/ode/nonstiff/GraggBulirschStoerStepInterpolator.polynomials:[[D (5, 1)
	118 iconst_1 (5, 1)
	119 aaload (5, 1)
	120 iload (5, 1)
	121 #4 (5, 1)
	122 dload (5, 1)
	123 #9 (5, 1)
	124 dastore (5, 1)
	125 aload_0 (5, 1)
	126 getfield (5, 1)
	127 org/apache/commons/math3/ode/nonstiff/GraggBulirschStoerStepInterpolator.polynomials:[[D (5, 1)
	129 iconst_2 (5, 1)
	130 aaload (5, 1)
	131 iload (5, 1)
	132 #4 (5, 1)
	133 dload (5, 1)
	134 #11 (5, 1)
	135 dastore (5, 1)
	136 aload_0 (5, 1)
	137 getfield (5, 1)
	138 org/apache/commons/math3/ode/nonstiff/GraggBulirschStoerStepInterpolator.polynomials:[[D (5, 1)
	140 iconst_3 (5, 1)
	141 aaload (5, 1)
	142 iload (5, 1)
	143 #4 (5, 1)
	144 dload (5, 1)
	145 #13 (5, 1)
	146 dastore (5, 1)
	147 iload_1 (6, 1)
	148 ifge (6, 1)
	149 4 (6, 1)
	151 return (6, 1)
	152 ldc2_w (5, 1)
	153 0.5 (5, 1)
	155 aload_0 (5, 1)
	156 getfield (5, 1)
	157 org/apache/commons/math3/ode/nonstiff/GraggBulirschStoerStepInterpolator.currentState:[D (5, 1)
	159 iload (5, 1)
	160 #4 (5, 1)
	161 daload (5, 1)
	162 aload_0 (5, 1)
	163 getfield (5, 1)
	164 org/apache/commons/math3/ode/nonstiff/GraggBulirschStoerStepInterpolator.y1:[D (5, 1)
	166 iload (5, 1)
	167 #4 (5, 1)
	168 daload (5, 1)
	169 dadd (5, 1)
	170 dmul (5, 1)
	171 ldc2_w (5, 1)
	172 0.125 (5, 1)
	174 dload (5, 1)
	175 #11 (5, 1)
	176 dload (5, 1)
	177 #13 (5, 1)
	178 dadd (5, 1)
	179 dmul (5, 1)
	180 dadd (5, 1)
	181 dstore (5, 1)
	182 #15 (5, 1)
	183 aload_0 (5, 1)
	184 getfield (5, 1)
	185 org/apache/commons/math3/ode/nonstiff/GraggBulirschStoerStepInterpolator.polynomials:[[D (5, 1)
	187 iconst_4 (5, 1)
	188 aaload (5, 1)
	189 iload (5, 1)
	190 #4 (5, 1)
	191 ldc2_w (5, 1)
	192 16.0 (5, 1)
	194 aload_0 (5, 1)
	195 getfield (5, 1)
	196 org/apache/commons/math3/ode/nonstiff/GraggBulirschStoerStepInterpolator.yMidDots:[[D (5, 1)
	198 iconst_0 (5, 1)
	199 aaload (5, 1)
	200 iload (5, 1)
	201 #4 (5, 1)
	202 daload (5, 1)
	203 dload (5, 1)
	204 #15 (5, 1)
	205 dsub (5, 1)
	206 dmul (5, 1)
	207 dastore (5, 1)
	208 iload_1 (6, 1)
	209 ifle (6, 1)
	210 252 (6, 1)
	212 dload (7, 1)
	213 #9 (7, 1)
	214 ldc2_w (7, 1)
	215 0.25 (7, 1)
	217 dload (7, 1)
	218 #11 (7, 1)
	219 dload (7, 1)
	220 #13 (7, 1)
	221 dsub (7, 1)
	222 dmul (7, 1)
	223 dadd (7, 1)
	224 dstore (7, 1)
	225 #17 (7, 1)
	226 aload_0 (7, 1)
	227 getfield (7, 1)
	228 org/apache/commons/math3/ode/nonstiff/GraggBulirschStoerStepInterpolator.polynomials:[[D (7, 1)
	230 iconst_5 (7, 1)
	231 aaload (7, 1)
	232 iload (7, 1)
	233 #4 (7, 1)
	234 ldc2_w (7, 1)
	235 16.0 (7, 1)
	237 aload_0 (7, 1)
	238 getfield (7, 1)
	239 org/apache/commons/math3/ode/nonstiff/GraggBulirschStoerStepInterpolator.yMidDots:[[D (7, 1)
	241 iconst_1 (7, 1)
	242 aaload (7, 1)
	243 iload (7, 1)
	244 #4 (7, 1)
	245 daload (7, 1)
	246 dload (7, 1)
	247 #17 (7, 1)
	248 dsub (7, 1)
	249 dmul (7, 1)
	250 dastore (7, 1)
	251 iload_1 (8, 1)
	252 iconst_1 (8, 1)
	253 if_icmple (8, 1)
	254 208 (8, 1)
	256 dload (8, 1)
	257 #7 (8, 1)
	258 dload (8, 1)
	259 #5 (8, 1)
	260 dsub (8, 1)
	261 dstore (8, 1)
	262 #19 (8, 1)
	263 aload_0 (8, 1)
	264 getfield (8, 1)
	265 org/apache/commons/math3/ode/nonstiff/GraggBulirschStoerStepInterpolator.polynomials:[[D (8, 1)
	267 bipush (8, 1)
	268 6 (8, 1)
	269 aaload (8, 1)
	270 iload (8, 1)
	271 #4 (8, 1)
	272 ldc2_w (8, 1)
	273 16.0 (8, 1)
	275 aload_0 (8, 1)
	276 getfield (8, 1)
	277 org/apache/commons/math3/ode/nonstiff/GraggBulirschStoerStepInterpolator.yMidDots:[[D (8, 1)
	279 iconst_2 (8, 1)
	280 aaload (8, 1)
	281 iload (8, 1)
	282 #4 (8, 1)
	283 daload (8, 1)
	284 dload (8, 1)
	285 #19 (8, 1)
	286 dsub (8, 1)
	287 aload_0 (8, 1)
	288 getfield (8, 1)
	289 org/apache/commons/math3/ode/nonstiff/GraggBulirschStoerStepInterpolator.polynomials:[[D (8, 1)
	291 iconst_4 (8, 1)
	292 aaload (8, 1)
	293 iload (8, 1)
	294 #4 (8, 1)
	295 daload (8, 1)
	296 dadd (8, 1)
	297 dmul (8, 1)
	298 dastore (8, 1)
	299 iload_1 (9, 1)
	300 iconst_2 (9, 1)
	301 if_icmple (9, 1)
	302 160 (9, 1)
	304 ldc2_w (9, 1)
	305 6.0 (9, 1)
	307 dload (9, 1)
	308 #13 (9, 1)
	309 dload (9, 1)
	310 #11 (9, 1)
	311 dsub (9, 1)
	312 dmul (9, 1)
	313 dstore (9, 1)
	314 #21 (9, 1)
	315 aload_0 (9, 1)
	316 getfield (9, 1)
	317 org/apache/commons/math3/ode/nonstiff/GraggBulirschStoerStepInterpolator.polynomials:[[D (9, 1)
	319 bipush (9, 1)
	320 7 (9, 1)
	321 aaload (9, 1)
	322 iload (9, 1)
	323 #4 (9, 1)
	324 ldc2_w (9, 1)
	325 16.0 (9, 1)
	327 aload_0 (9, 1)
	328 getfield (9, 1)
	329 org/apache/commons/math3/ode/nonstiff/GraggBulirschStoerStepInterpolator.yMidDots:[[D (9, 1)
	331 iconst_3 (9, 1)
	332 aaload (9, 1)
	333 iload (9, 1)
	334 #4 (9, 1)
	335 daload (9, 1)
	336 dload (9, 1)
	337 #21 (9, 1)
	338 dsub (9, 1)
	339 ldc2_w (9, 1)
	340 3.0 (9, 1)
	342 aload_0 (9, 1)
	343 getfield (9, 1)
	344 org/apache/commons/math3/ode/nonstiff/GraggBulirschStoerStepInterpolator.polynomials:[[D (9, 1)
	346 iconst_5 (9, 1)
	347 aaload (9, 1)
	348 iload (9, 1)
	349 #4 (9, 1)
	350 daload (9, 1)
	351 dmul (9, 1)
	352 dadd (9, 1)
	353 dmul (9, 1)
	354 dastore (9, 1)
	355 iconst_4 (10, 4)
	356 istore (10, 4)
	357 #23 (10, 4)
	358 iload (10, 4)
	359 #23 (10, 4)
	360 iload_1 (10, 4)
	361 if_icmpgt (10, 4)
	362 100 (10, 4)
	364 ldc2_w (10, 4)
	365 0.5 (10, 4)
	367 iload (10, 4)
	368 #23 (10, 4)
	369 i2d (10, 4)
	370 dmul (10, 4)
	371 iload (10, 4)
	372 #23 (10, 4)
	373 iconst_1 (10, 4)
	374 isub (10, 4)
	375 i2d (10, 4)
	376 dmul (10, 4)
	377 dstore (10, 4)
	378 #24 (10, 4)
	379 ldc2_w (10, 4)
	380 2.0 (10, 4)
	382 dload (10, 4)
	383 #24 (10, 4)
	384 dmul (10, 4)
	385 iload (10, 4)
	386 #23 (10, 4)
	387 iconst_2 (10, 4)
	388 isub (10, 4)
	389 i2d (10, 4)
	390 dmul (10, 4)
	391 iload (10, 4)
	392 #23 (10, 4)
	393 iconst_3 (10, 4)
	394 isub (10, 4)
	395 i2d (10, 4)
	396 dmul (10, 4)
	397 dstore (10, 4)
	398 #26 (10, 4)
	399 aload_0 (10, 4)
	400 getfield (10, 4)
	401 org/apache/commons/math3/ode/nonstiff/GraggBulirschStoerStepInterpolator.polynomials:[[D (10, 4)
	403 iload (10, 4)
	404 #23 (10, 4)
	405 iconst_4 (10, 4)
	406 iadd (10, 4)
	407 aaload (10, 4)
	408 iload (10, 4)
	409 #4 (10, 4)
	410 ldc2_w (10, 4)
	411 16.0 (10, 4)
	413 aload_0 (10, 4)
	414 getfield (10, 4)
	415 org/apache/commons/math3/ode/nonstiff/GraggBulirschStoerStepInterpolator.yMidDots:[[D (10, 4)
	417 iload (10, 4)
	418 #23 (10, 4)
	419 aaload (10, 4)
	420 iload (10, 4)
	421 #4 (10, 4)
	422 daload (10, 4)
	423 dload (10, 4)
	424 #24 (10, 4)
	425 aload_0 (10, 4)
	426 getfield (10, 4)
	427 org/apache/commons/math3/ode/nonstiff/GraggBulirschStoerStepInterpolator.polynomials:[[D (10, 4)
	429 iload (10, 4)
	430 #23 (10, 4)
	431 iconst_2 (10, 4)
	432 iadd (10, 4)
	433 aaload (10, 4)
	434 iload (10, 4)
	435 #4 (10, 4)
	436 daload (10, 4)
	437 dmul (10, 4)
	438 dadd (10, 4)
	439 dload (10, 4)
	440 #26 (10, 4)
	441 aload_0 (10, 4)
	442 getfield (10, 4)
	443 org/apache/commons/math3/ode/nonstiff/GraggBulirschStoerStepInterpolator.polynomials:[[D (10, 4)
	445 iload (10, 4)
	446 #23 (10, 4)
	447 aaload (10, 4)
	448 iload (10, 4)
	449 #4 (10, 4)
	450 daload (10, 4)
	451 dmul (10, 4)
	452 dsub (10, 4)
	453 dmul (10, 4)
	454 dastore (10, 4)
	455 iinc (10, 4)
	456 #23 (10, 4)
	457 -89 (10, 4)
	458 goto (10, 4)
	459 -100 (10, 4)
	461 iinc (10, 4)
	462 #4 (10, 4)
	463 -89 (10, 4)
	464 goto (10, 4)
	465 -429 (10, 4)
	467 return (3, 1)

Method: estimateError
	0 dconst_0 (0, 0)
	1 dstore_2 (0, 0)
	2 aload_0 (1, 1)
	3 getfield (1, 1)
	4 org/apache/commons/math3/ode/nonstiff/GraggBulirschStoerStepInterpolator.currentDegree:I (1, 1)
	6 iconst_5 (1, 1)
	7 if_icmplt (1, 1)
	8 67 (1, 1)
	10 iconst_0 (2, 4)
	11 istore (2, 4)
	12 #4 (2, 4)
	13 iload (2, 4)
	14 #4 (2, 4)
	15 aload_1 (2, 4)
	16 arraylength (2, 4)
	17 if_icmpge (2, 4)
	18 36 (2, 4)
	20 aload_0 (2, 4)
	21 getfield (2, 4)
	22 org/apache/commons/math3/ode/nonstiff/GraggBulirschStoerStepInterpolator.polynomials:[[D (2, 4)
	24 aload_0 (2, 4)
	25 getfield (2, 4)
	26 org/apache/commons/math3/ode/nonstiff/GraggBulirschStoerStepInterpolator.currentDegree:I (2, 4)
	28 aaload (2, 4)
	29 iload (2, 4)
	30 #4 (2, 4)
	31 daload (2, 4)
	32 aload_1 (2, 4)
	33 iload (2, 4)
	34 #4 (2, 4)
	35 daload (2, 4)
	36 ddiv (2, 4)
	37 dstore (2, 4)
	38 #5 (2, 4)
	39 dload_2 (2, 4)
	40 dload (2, 4)
	41 #5 (2, 4)
	42 dload (2, 4)
	43 #5 (2, 4)
	44 dmul (2, 4)
	45 dadd (2, 4)
	46 dstore_2 (2, 4)
	47 iinc (2, 4)
	48 #4 (2, 4)
	49 -89 (2, 4)
	50 goto (2, 4)
	51 -37 (2, 4)
	53 dload_2 (1, 1)
	54 aload_1 (1, 1)
	55 arraylength (1, 1)
	56 i2d (1, 1)
	57 ddiv (1, 1)
	58 invokestatic (1, 1)
	59 org/apache/commons/math3/util/FastMath.sqrt:(D)D (1, 1)
	61 aload_0 (1, 1)
	62 getfield (1, 1)
	63 org/apache/commons/math3/ode/nonstiff/GraggBulirschStoerStepInterpolator.errfac:[D (1, 1)
	65 aload_0 (1, 1)
	66 getfield (1, 1)
	67 org/apache/commons/math3/ode/nonstiff/GraggBulirschStoerStepInterpolator.currentDegree:I (1, 1)
	69 iconst_5 (1, 1)
	70 isub (1, 1)
	71 daload (1, 1)
	72 dmul (1, 1)
	73 dstore_2 (1, 1)
	74 dload_2 (0, 0)
	75 dreturn (0, 0)

Method: computeInterpolatedStateAndDerivatives
	0 aload_0 (0, 0)
	1 getfield (0, 0)
	2 org/apache/commons/math3/ode/nonstiff/GraggBulirschStoerStepInterpolator.currentState:[D (0, 0)
	4 arraylength (0, 0)
	5 istore (0, 0)
	6 #5 (0, 0)
	7 dconst_1 (0, 0)
	8 dload_1 (0, 0)
	9 dsub (0, 0)
	10 dstore (0, 0)
	11 #6 (0, 0)
	12 dload_1 (0, 0)
	13 ldc2_w (0, 0)
	14 0.5 (0, 0)
	16 dsub (0, 0)
	17 dstore (0, 0)
	18 #8 (0, 0)
	19 dload_1 (0, 0)
	20 dload (0, 0)
	21 #6 (0, 0)
	22 dmul (0, 0)
	23 dstore (0, 0)
	24 #10 (0, 0)
	25 dload (0, 0)
	26 #10 (0, 0)
	27 dload (0, 0)
	28 #10 (0, 0)
	29 dmul (0, 0)
	30 dstore (0, 0)
	31 #12 (0, 0)
	32 ldc2_w (0, 0)
	33 2.0 (0, 0)
	35 dload (0, 0)
	36 #10 (0, 0)
	37 dmul (0, 0)
	38 dconst_1 (0, 0)
	39 ldc2_w (0, 0)
	40 2.0 (0, 0)
	42 dload_1 (0, 0)
	43 dmul (0, 0)
	44 dsub (0, 0)
	45 dmul (0, 0)
	46 dstore (0, 0)
	47 #14 (0, 0)
	48 dconst_1 (0, 0)
	49 aload_0 (0, 0)
	50 getfield (0, 0)
	51 org/apache/commons/math3/ode/nonstiff/GraggBulirschStoerStepInterpolator.h:D (0, 0)
	53 ddiv (0, 0)
	54 dstore (0, 0)
	55 #16 (0, 0)
	56 dload_1 (0, 0)
	57 ldc2_w (0, 0)
	58 2.0 (0, 0)
	60 ldc2_w (0, 0)
	61 3.0 (0, 0)
	63 dload_1 (0, 0)
	64 dmul (0, 0)
	65 dsub (0, 0)
	66 dmul (0, 0)
	67 aload_0 (0, 0)
	68 getfield (0, 0)
	69 org/apache/commons/math3/ode/nonstiff/GraggBulirschStoerStepInterpolator.h:D (0, 0)
	71 ddiv (0, 0)
	72 dstore (0, 0)
	73 #18 (0, 0)
	74 ldc2_w (0, 0)
	75 3.0 (0, 0)
	77 dload_1 (0, 0)
	78 dmul (0, 0)
	79 ldc2_w (0, 0)
	80 4.0 (0, 0)
	82 dsub (0, 0)
	83 dload_1 (0, 0)
	84 dmul (0, 0)
	85 dconst_1 (0, 0)
	86 dadd (0, 0)
	87 aload_0 (0, 0)
	88 getfield (0, 0)
	89 org/apache/commons/math3/ode/nonstiff/GraggBulirschStoerStepInterpolator.h:D (0, 0)
	91 ddiv (0, 0)
	92 dstore (0, 0)
	93 #20 (0, 0)
	94 iconst_0 (1, 4)
	95 istore (1, 4)
	96 #22 (1, 4)
	97 iload (1, 4)
	98 #22 (1, 4)
	99 iload (1, 4)
	100 #5 (1, 4)
	101 if_icmpge (1, 4)
	102 234 (1, 4)
	104 aload_0 (1, 4)
	105 getfield (1, 4)
	106 org/apache/commons/math3/ode/nonstiff/GraggBulirschStoerStepInterpolator.polynomials:[[D (1, 4)
	108 iconst_0 (1, 4)
	109 aaload (1, 4)
	110 iload (1, 4)
	111 #22 (1, 4)
	112 daload (1, 4)
	113 dstore (1, 4)
	114 #23 (1, 4)
	115 aload_0 (1, 4)
	116 getfield (1, 4)
	117 org/apache/commons/math3/ode/nonstiff/GraggBulirschStoerStepInterpolator.polynomials:[[D (1, 4)
	119 iconst_1 (1, 4)
	120 aaload (1, 4)
	121 iload (1, 4)
	122 #22 (1, 4)
	123 daload (1, 4)
	124 dstore (1, 4)
	125 #25 (1, 4)
	126 aload_0 (1, 4)
	127 getfield (1, 4)
	128 org/apache/commons/math3/ode/nonstiff/GraggBulirschStoerStepInterpolator.polynomials:[[D (1, 4)
	130 iconst_2 (1, 4)
	131 aaload (1, 4)
	132 iload (1, 4)
	133 #22 (1, 4)
	134 daload (1, 4)
	135 dstore (1, 4)
	136 #27 (1, 4)
	137 aload_0 (1, 4)
	138 getfield (1, 4)
	139 org/apache/commons/math3/ode/nonstiff/GraggBulirschStoerStepInterpolator.polynomials:[[D (1, 4)
	141 iconst_3 (1, 4)
	142 aaload (1, 4)
	143 iload (1, 4)
	144 #22 (1, 4)
	145 daload (1, 4)
	146 dstore (1, 4)
	147 #29 (1, 4)
	148 aload_0 (1, 4)
	149 getfield (1, 4)
	150 org/apache/commons/math3/ode/nonstiff/GraggBulirschStoerStepInterpolator.interpolatedState:[D (1, 4)
	152 iload (1, 4)
	153 #22 (1, 4)
	154 dload (1, 4)
	155 #23 (1, 4)
	156 dload_1 (1, 4)
	157 dload (1, 4)
	158 #25 (1, 4)
	159 dload (1, 4)
	160 #6 (1, 4)
	161 dload (1, 4)
	162 #27 (1, 4)
	163 dload_1 (1, 4)
	164 dmul (1, 4)
	165 dload (1, 4)
	166 #29 (1, 4)
	167 dload (1, 4)
	168 #6 (1, 4)
	169 dmul (1, 4)
	170 dadd (1, 4)
	171 dmul (1, 4)
	172 dadd (1, 4)
	173 dmul (1, 4)
	174 dadd (1, 4)
	175 dastore (1, 4)
	176 aload_0 (1, 4)
	177 getfield (1, 4)
	178 org/apache/commons/math3/ode/nonstiff/GraggBulirschStoerStepInterpolator.interpolatedDerivatives:[D (1, 4)
	180 iload (1, 4)
	181 #22 (1, 4)
	182 dload (1, 4)
	183 #16 (1, 4)
	184 dload (1, 4)
	185 #25 (1, 4)
	186 dmul (1, 4)
	187 dload (1, 4)
	188 #18 (1, 4)
	189 dload (1, 4)
	190 #27 (1, 4)
	191 dmul (1, 4)
	192 dadd (1, 4)
	193 dload (1, 4)
	194 #20 (1, 4)
	195 dload (1, 4)
	196 #29 (1, 4)
	197 dmul (1, 4)
	198 dadd (1, 4)
	199 dastore (1, 4)
	200 aload_0 (2, 1)
	201 getfield (2, 1)
	202 org/apache/commons/math3/ode/nonstiff/GraggBulirschStoerStepInterpolator.currentDegree:I (2, 1)
	204 iconst_3 (2, 1)
	205 if_icmple (2, 1)
	206 124 (2, 1)
	208 dconst_0 (2, 1)
	209 dstore (2, 1)
	210 #31 (2, 1)
	211 aload_0 (2, 1)
	212 getfield (2, 1)
	213 org/apache/commons/math3/ode/nonstiff/GraggBulirschStoerStepInterpolator.polynomials:[[D (2, 1)
	215 aload_0 (2, 1)
	216 getfield (2, 1)
	217 org/apache/commons/math3/ode/nonstiff/GraggBulirschStoerStepInterpolator.currentDegree:I (2, 1)
	219 aaload (2, 1)
	220 iload (2, 1)
	221 #22 (2, 1)
	222 daload (2, 1)
	223 dstore (2, 1)
	224 #33 (2, 1)
	225 aload_0 (3, 4)
	226 getfield (3, 4)
	227 org/apache/commons/math3/ode/nonstiff/GraggBulirschStoerStepInterpolator.currentDegree:I (3, 4)
	229 iconst_1 (3, 4)
	230 isub (3, 4)
	231 istore (3, 4)
	232 #35 (3, 4)
	233 iload (3, 4)
	234 #35 (3, 4)
	235 iconst_3 (3, 4)
	236 if_icmple (3, 4)
	237 52 (3, 4)
	239 dconst_1 (3, 4)
	240 iload (3, 4)
	241 #35 (3, 4)
	242 iconst_3 (3, 4)
	243 isub (3, 4)
	244 i2d (3, 4)
	245 ddiv (3, 4)
	246 dstore (3, 4)
	247 #36 (3, 4)
	248 dload (3, 4)
	249 #36 (3, 4)
	250 dload (3, 4)
	251 #8 (3, 4)
	252 dload (3, 4)
	253 #31 (3, 4)
	254 dmul (3, 4)
	255 dload (3, 4)
	256 #33 (3, 4)
	257 dadd (3, 4)
	258 dmul (3, 4)
	259 dstore (3, 4)
	260 #31 (3, 4)
	261 aload_0 (3, 4)
	262 getfield (3, 4)
	263 org/apache/commons/math3/ode/nonstiff/GraggBulirschStoerStepInterpolator.polynomials:[[D (3, 4)
	265 iload (3, 4)
	266 #35 (3, 4)
	267 aaload (3, 4)
	268 iload (3, 4)
	269 #22 (3, 4)
	270 daload (3, 4)
	271 dload (3, 4)
	272 #33 (3, 4)
	273 dload (3, 4)
	274 #36 (3, 4)
	275 dmul (3, 4)
	276 dload (3, 4)
	277 #8 (3, 4)
	278 dmul (3, 4)
	279 dadd (3, 4)
	280 dstore (3, 4)
	281 #33 (3, 4)
	282 iinc (3, 4)
	283 #35 (3, 4)
	284 -89 (3, 4)
	285 goto (3, 4)
	286 -52 (3, 4)
	288 aload_0 (2, 1)
	289 getfield (2, 1)
	290 org/apache/commons/math3/ode/nonstiff/GraggBulirschStoerStepInterpolator.interpolatedState:[D (2, 1)
	292 iload (2, 1)
	293 #22 (2, 1)
	294 dup2 (2, 1)
	295 daload (2, 1)
	296 dload (2, 1)
	297 #12 (2, 1)
	298 dload (2, 1)
	299 #33 (2, 1)
	300 dmul (2, 1)
	301 dadd (2, 1)
	302 dastore (2, 1)
	303 aload_0 (2, 1)
	304 getfield (2, 1)
	305 org/apache/commons/math3/ode/nonstiff/GraggBulirschStoerStepInterpolator.interpolatedDerivatives:[D (2, 1)
	307 iload (2, 1)
	308 #22 (2, 1)
	309 dup2 (2, 1)
	310 daload (2, 1)
	311 dload (2, 1)
	312 #12 (2, 1)
	313 dload (2, 1)
	314 #31 (2, 1)
	315 dmul (2, 1)
	316 dload (2, 1)
	317 #14 (2, 1)
	318 dload (2, 1)
	319 #33 (2, 1)
	320 dmul (2, 1)
	321 dadd (2, 1)
	322 aload_0 (2, 1)
	323 getfield (2, 1)
	324 org/apache/commons/math3/ode/nonstiff/GraggBulirschStoerStepInterpolator.h:D (2, 1)
	326 ddiv (2, 1)
	327 dadd (2, 1)
	328 dastore (2, 1)
	329 iinc (2, 1)
	330 #22 (2, 1)
	331 -89 (2, 1)
	332 goto (2, 1)
	333 -235 (2, 1)
	335 aload_0 (2, 1)
	336 getfield (2, 1)
	337 org/apache/commons/math3/ode/nonstiff/GraggBulirschStoerStepInterpolator.h:D (2, 1)
	339 dconst_0 (2, 1)
	340 dcmpl (2, 1)
	341 ifne (2, 1)
	342 20 (2, 1)
	344 aload_0 (3, 4)
	345 getfield (3, 4)
	346 org/apache/commons/math3/ode/nonstiff/GraggBulirschStoerStepInterpolator.yMidDots:[[D (3, 4)
	348 iconst_1 (3, 4)
	349 aaload (3, 4)
	350 iconst_0 (3, 4)
	351 aload_0 (3, 4)
	352 getfield (3, 4)
	353 org/apache/commons/math3/ode/nonstiff/GraggBulirschStoerStepInterpolator.interpolatedDerivatives:[D (3, 4)
	355 iconst_0 (3, 4)
	356 iload (3, 4)
	357 #5 (3, 4)
	358 invokestatic (3, 4)
	359 java/lang/System.arraycopy:(Ljava/lang/Object;ILjava/lang/Object;II)V (3, 4)
	361 return (0, 0)

Method: writeExternal
	0 aload_0 (0, 0)
	1 getfield (0, 0)
	2 org/apache/commons/math3/ode/nonstiff/GraggBulirschStoerStepInterpolator.currentState:[D (0, 0)
	4 ifnonnull (0, 0)
	5 7 (0, 0)
	7 iconst_m1 (0, 0)
	8 goto (0, 0)
	9 8 (0, 0)
	11 aload_0 (0, 0)
	12 getfield (0, 0)
	13 org/apache/commons/math3/ode/nonstiff/GraggBulirschStoerStepInterpolator.currentState:[D (0, 0)
	15 arraylength (0, 0)
	16 istore_2 (0, 0)
	17 aload_0 (0, 0)
	18 aload_1 (0, 0)
	19 invokevirtual (0, 0)
	20 org/apache/commons/math3/ode/nonstiff/GraggBulirschStoerStepInterpolator.writeBaseExternal:(Ljava/io/ObjectOutput;)V (0, 0)
	22 aload_1 (0, 0)
	23 aload_0 (0, 0)
	24 getfield (0, 0)
	25 org/apache/commons/math3/ode/nonstiff/GraggBulirschStoerStepInterpolator.currentDegree:I (0, 0)
	27 invokeinterface (0, 0)
	28 java/io/ObjectOutput.writeDouble:(D)V (0, 0)
	30 0 (0, 0)
	32 iconst_0 (1, 4)
	33 istore_3 (1, 4)
	34 iload_3 (1, 4)
	35 aload_0 (1, 4)
	36 getfield (1, 4)
	37 org/apache/commons/math3/ode/nonstiff/GraggBulirschStoerStepInterpolator.currentDegree:I (1, 4)
	39 if_icmpgt (1, 4)
	40 39 (1, 4)
	42 iconst_0 (2, 4)
	43 istore (2, 4)
	44 #4 (2, 4)
	45 iload (2, 4)
	46 #4 (2, 4)
	47 iload_2 (2, 4)
	48 if_icmpge (2, 4)
	49 24 (2, 4)
	51 aload_1 (2, 4)
	52 aload_0 (2, 4)
	53 getfield (2, 4)
	54 org/apache/commons/math3/ode/nonstiff/GraggBulirschStoerStepInterpolator.polynomials:[[D (2, 4)
	56 iload_3 (2, 4)
	57 aaload (2, 4)
	58 iload (2, 4)
	59 #4 (2, 4)
	60 daload (2, 4)
	61 invokeinterface (2, 4)
	62 java/io/ObjectOutput.readBaseExternal:(Ljava/io/ObjectInput;)D (2, 4)
	64 0 (2, 4)
	66 iinc (2, 4)
	67 #4 (2, 4)
	68 -89 (2, 4)
	69 goto (2, 4)
	70 -24 (2, 4)
	72 iinc (2, 4)
	73 #3 (2, 4)
	74 -89 (2, 4)
	75 goto (2, 4)
	76 -41 (2, 4)
	78 return (0, 0)

Method: readExternal
	0 aload_0 (0, 0)
	1 aload_1 (0, 0)
	2 invokevirtual (0, 0)
	3 org/apache/commons/math3/ode/nonstiff/GraggBulirschStoerStepInterpolator.readBaseExternal:(Ljava/io/ObjectInput;)D (0, 0)
	5 dstore_2 (0, 0)
	6 aload_0 (0, 0)
	7 getfield (0, 0)
	8 org/apache/commons/math3/ode/nonstiff/GraggBulirschStoerStepInterpolator.currentState:[D (0, 0)
	10 ifnonnull (0, 0)
	11 7 (0, 0)
	13 iconst_m1 (0, 0)
	14 goto (0, 0)
	15 8 (0, 0)
	17 aload_0 (0, 0)
	18 getfield (0, 0)
	19 org/apache/commons/math3/ode/nonstiff/GraggBulirschStoerStepInterpolator.currentState:[D (0, 0)
	21 arraylength (0, 0)
	22 istore (0, 0)
	23 #4 (0, 0)
	24 aload_1 (0, 0)
	25 invokeinterface (0, 0)
	26 java/io/ObjectInput.readDouble:()D (0, 0)
	28 0 (0, 0)
	30 istore (0, 0)
	31 #5 (0, 0)
	32 aload_0 (0, 0)
	33 iload (0, 0)
	34 #5 (0, 0)
	35 invokespecial (0, 0)
	36 org/apache/commons/math3/ode/nonstiff/GraggBulirschStoerStepInterpolator.resetTables:(I)V (0, 0)
	38 aload_0 (0, 0)
	39 iload (0, 0)
	40 #5 (0, 0)
	41 putfield (0, 0)
	42 org/apache/commons/math3/ode/nonstiff/GraggBulirschStoerStepInterpolator.currentDegree:I (0, 0)
	44 iconst_0 (1, 4)
	45 istore (1, 4)
	46 #6 (1, 4)
	47 iload (1, 4)
	48 #6 (1, 4)
	49 aload_0 (1, 4)
	50 getfield (1, 4)
	51 org/apache/commons/math3/ode/nonstiff/GraggBulirschStoerStepInterpolator.currentDegree:I (1, 4)
	53 if_icmpgt (1, 4)
	54 41 (1, 4)
	56 iconst_0 (2, 4)
	57 istore (2, 4)
	58 #7 (2, 4)
	59 iload (2, 4)
	60 #7 (2, 4)
	61 iload (2, 4)
	62 #4 (2, 4)
	63 if_icmpge (2, 4)
	64 25 (2, 4)
	66 aload_0 (2, 4)
	67 getfield (2, 4)
	68 org/apache/commons/math3/ode/nonstiff/GraggBulirschStoerStepInterpolator.polynomials:[[D (2, 4)
	70 iload (2, 4)
	71 #6 (2, 4)
	72 aaload (2, 4)
	73 iload (2, 4)
	74 #7 (2, 4)
	75 aload_1 (2, 4)
	76 invokeinterface (2, 4)
	77 java/io/ObjectInput.setInterpolatedTime:(D)V (2, 4)
	79 0 (2, 4)
	81 dastore (2, 4)
	82 iinc (2, 4)
	83 #7 (2, 4)
	84 -89 (2, 4)
	85 goto (2, 4)
	86 -26 (2, 4)
	88 iinc (2, 4)
	89 #6 (2, 4)
	90 -89 (2, 4)
	91 goto (2, 4)
	92 -44 (2, 4)
	94 aload_0 (1, 4)
	95 dload_2 (1, 4)
	96 invokevirtual (1, 4)
	97 org/apache/commons/math3/ode/nonstiff/GraggBulirschStoerStepInterpolator.setInterpolatedTime:(D)V (1, 4)
	99 return (0, 0)

