Method: <init>
	0 aload_0 (0, 0)
	1 aload_1 (0, 0)
	2 invokespecial (0, 0)
	3 org/apache/commons/math3/ode/nonstiff/RungeKuttaStepInterpolator.<init>:(Lorg/apache/commons/math3/ode/nonstiff/RungeKuttaStepInterpolator;)V (0, 0)
	5 return (0, 0)

Method: doCopy
	0 new (0, 0)
	1 org/apache/commons/math3/ode/nonstiff/LutherStepInterpolator (0, 0)
	3 dup (0, 0)
	4 aload_0 (0, 0)
	5 invokespecial (0, 0)
	6 org/apache/commons/math3/ode/nonstiff/LutherStepInterpolator.<init>:(Lorg/apache/commons/math3/ode/nonstiff/LutherStepInterpolator;)V (0, 0)
	8 areturn (0, 0)

Method: computeInterpolatedStateAndDerivatives
	0 dconst_1 (0, 0)
	1 dload_1 (0, 0)
	2 ldc2_w (0, 0)
	3 -10.8 (0, 0)
	5 dload_1 (0, 0)
	6 ldc2_w (0, 0)
	7 36.0 (0, 0)
	9 dload_1 (0, 0)
	10 ldc2_w (0, 0)
	11 -47.0 (0, 0)
	13 dload_1 (0, 0)
	14 ldc2_w (0, 0)
	15 21.0 (0, 0)
	17 dmul (0, 0)
	18 dadd (0, 0)
	19 dmul (0, 0)
	20 dadd (0, 0)
	21 dmul (0, 0)
	22 dadd (0, 0)
	23 dmul (0, 0)
	24 dadd (0, 0)
	25 dstore (0, 0)
	26 #5 (0, 0)
	27 dconst_0 (0, 0)
	28 dstore (0, 0)
	29 #7 (0, 0)
	30 dload_1 (0, 0)
	31 ldc2_w (0, 0)
	32 -13.866666666666667 (0, 0)
	34 dload_1 (0, 0)
	35 ldc2_w (0, 0)
	36 106.66666666666667 (0, 0)
	38 dload_1 (0, 0)
	39 ldc2_w (0, 0)
	40 -202.66666666666666 (0, 0)
	42 dload_1 (0, 0)
	43 ldc2_w (0, 0)
	44 112.0 (0, 0)
	46 dmul (0, 0)
	47 dadd (0, 0)
	48 dmul (0, 0)
	49 dadd (0, 0)
	50 dmul (0, 0)
	51 dadd (0, 0)
	52 dmul (0, 0)
	53 dstore (0, 0)
	54 #9 (0, 0)
	55 dload_1 (0, 0)
	56 ldc2_w (0, 0)
	57 12.96 (0, 0)
	59 dload_1 (0, 0)
	60 ldc2_w (0, 0)
	61 -97.2 (0, 0)
	63 dload_1 (0, 0)
	64 ldc2_w (0, 0)
	65 194.4 (0, 0)
	67 dload_1 (0, 0)
	68 ldc2_w (0, 0)
	69 -567.0 (0, 0)
	71 dmul (0, 0)
	72 ldc2_w (0, 0)
	73 5.0 (0, 0)
	75 ddiv (0, 0)
	76 dadd (0, 0)
	77 dmul (0, 0)
	78 dadd (0, 0)
	79 dmul (0, 0)
	80 dadd (0, 0)
	81 dmul (0, 0)
	82 dstore (0, 0)
	83 #11 (0, 0)
	84 dload_1 (0, 0)
	85 ldc2_w (0, 0)
	86 833.0 (0, 0)
	88 ldc2_w (0, 0)
	89 343.0 (0, 0)
	91 getstatic (0, 0)
	92 org/apache/commons/math3/ode/nonstiff/LutherStepInterpolator.Q:D (0, 0)
	94 dmul (0, 0)
	95 dadd (0, 0)
	96 ldc2_w (0, 0)
	97 150.0 (0, 0)
	99 ddiv (0, 0)
	100 dload_1 (0, 0)
	101 ldc2_w (0, 0)
	102 -637.0 (0, 0)
	104 ldc2_w (0, 0)
	105 357.0 (0, 0)
	107 getstatic (0, 0)
	108 org/apache/commons/math3/ode/nonstiff/LutherStepInterpolator.Q:D (0, 0)
	110 dmul (0, 0)
	111 dsub (0, 0)
	112 ldc2_w (0, 0)
	113 30.0 (0, 0)
	115 ddiv (0, 0)
	116 dload_1 (0, 0)
	117 ldc2_w (0, 0)
	118 392.0 (0, 0)
	120 ldc2_w (0, 0)
	121 287.0 (0, 0)
	123 getstatic (0, 0)
	124 org/apache/commons/math3/ode/nonstiff/LutherStepInterpolator.Q:D (0, 0)
	126 dmul (0, 0)
	127 dadd (0, 0)
	128 ldc2_w (0, 0)
	129 15.0 (0, 0)
	131 ddiv (0, 0)
	132 dload_1 (0, 0)
	133 ldc2_w (0, 0)
	134 -49.0 (0, 0)
	136 ldc2_w (0, 0)
	137 49.0 (0, 0)
	139 getstatic (0, 0)
	140 org/apache/commons/math3/ode/nonstiff/LutherStepInterpolator.Q:D (0, 0)
	142 dmul (0, 0)
	143 dsub (0, 0)
	144 dmul (0, 0)
	145 ldc2_w (0, 0)
	146 5.0 (0, 0)
	148 ddiv (0, 0)
	149 dadd (0, 0)
	150 dmul (0, 0)
	151 dadd (0, 0)
	152 dmul (0, 0)
	153 dadd (0, 0)
	154 dmul (0, 0)
	155 dstore (0, 0)
	156 #13 (0, 0)
	157 dload_1 (0, 0)
	158 ldc2_w (0, 0)
	159 833.0 (0, 0)
	161 ldc2_w (0, 0)
	162 343.0 (0, 0)
	164 getstatic (0, 0)
	165 org/apache/commons/math3/ode/nonstiff/LutherStepInterpolator.Q:D (0, 0)
	167 dmul (0, 0)
	168 dsub (0, 0)
	169 ldc2_w (0, 0)
	170 150.0 (0, 0)
	172 ddiv (0, 0)
	173 dload_1 (0, 0)
	174 ldc2_w (0, 0)
	175 -637.0 (0, 0)
	177 ldc2_w (0, 0)
	178 357.0 (0, 0)
	180 getstatic (0, 0)
	181 org/apache/commons/math3/ode/nonstiff/LutherStepInterpolator.Q:D (0, 0)
	183 dmul (0, 0)
	184 dadd (0, 0)
	185 ldc2_w (0, 0)
	186 30.0 (0, 0)
	188 ddiv (0, 0)
	189 dload_1 (0, 0)
	190 ldc2_w (0, 0)
	191 392.0 (0, 0)
	193 ldc2_w (0, 0)
	194 287.0 (0, 0)
	196 getstatic (0, 0)
	197 org/apache/commons/math3/ode/nonstiff/LutherStepInterpolator.Q:D (0, 0)
	199 dmul (0, 0)
	200 dsub (0, 0)
	201 ldc2_w (0, 0)
	202 15.0 (0, 0)
	204 ddiv (0, 0)
	205 dload_1 (0, 0)
	206 ldc2_w (0, 0)
	207 -49.0 (0, 0)
	209 ldc2_w (0, 0)
	210 49.0 (0, 0)
	212 getstatic (0, 0)
	213 org/apache/commons/math3/ode/nonstiff/LutherStepInterpolator.Q:D (0, 0)
	215 dmul (0, 0)
	216 dadd (0, 0)
	217 dmul (0, 0)
	218 ldc2_w (0, 0)
	219 5.0 (0, 0)
	221 ddiv (0, 0)
	222 dadd (0, 0)
	223 dmul (0, 0)
	224 dadd (0, 0)
	225 dmul (0, 0)
	226 dadd (0, 0)
	227 dmul (0, 0)
	228 dstore (0, 0)
	229 #15 (0, 0)
	230 dload_1 (0, 0)
	231 ldc2_w (0, 0)
	232 0.6 (0, 0)
	234 dload_1 (0, 0)
	235 ldc2_w (0, 0)
	236 -3.0 (0, 0)
	238 dload_1 (0, 0)
	239 ldc2_w (0, 0)
	240 3.0 (0, 0)
	242 dmul (0, 0)
	243 dadd (0, 0)
	244 dmul (0, 0)
	245 dadd (0, 0)
	246 dmul (0, 0)
	247 dstore (0, 0)
	248 #17 (0, 0)
	249 aload_0 (1, 1)
	250 getfield (1, 1)
	251 org/apache/commons/math3/ode/nonstiff/LutherStepInterpolator.previousState:[D (1, 1)
	253 ifnull (1, 1)
	254 477 (1, 1)
	256 dload_1 (1, 1)
	257 ldc2_w (1, 1)
	258 0.5 (1, 1)
	260 dcmpg (1, 1)
	261 ifgt (1, 1)
	262 469 (1, 1)
	264 dconst_1 (1, 1)
	265 dload_1 (1, 1)
	266 ldc2_w (1, 1)
	267 -5.4 (1, 1)
	269 dload_1 (1, 1)
	270 ldc2_w (1, 1)
	271 12.0 (1, 1)
	273 dload_1 (1, 1)
	274 ldc2_w (1, 1)
	275 -11.75 (1, 1)
	277 dload_1 (1, 1)
	278 ldc2_w (1, 1)
	279 21.0 (1, 1)
	281 dmul (1, 1)
	282 ldc2_w (1, 1)
	283 5.0 (1, 1)
	285 ddiv (1, 1)
	286 dadd (1, 1)
	287 dmul (1, 1)
	288 dadd (1, 1)
	289 dmul (1, 1)
	290 dadd (1, 1)
	291 dmul (1, 1)
	292 dadd (1, 1)
	293 dstore (1, 1)
	294 #19 (1, 1)
	295 dconst_0 (1, 1)
	296 dstore (1, 1)
	297 #21 (1, 1)
	298 dload_1 (1, 1)
	299 ldc2_w (1, 1)
	300 -6.933333333333334 (1, 1)
	302 dload_1 (1, 1)
	303 ldc2_w (1, 1)
	304 35.55555555555556 (1, 1)
	306 dload_1 (1, 1)
	307 ldc2_w (1, 1)
	308 -50.666666666666664 (1, 1)
	310 dload_1 (1, 1)
	311 ldc2_w (1, 1)
	312 112.0 (1, 1)
	314 dmul (1, 1)
	315 ldc2_w (1, 1)
	316 5.0 (1, 1)
	318 ddiv (1, 1)
	319 dadd (1, 1)
	320 dmul (1, 1)
	321 dadd (1, 1)
	322 dmul (1, 1)
	323 dadd (1, 1)
	324 dmul (1, 1)
	325 dstore (1, 1)
	326 #23 (1, 1)
	327 dload_1 (1, 1)
	328 ldc2_w (1, 1)
	329 6.48 (1, 1)
	331 dload_1 (1, 1)
	332 ldc2_w (1, 1)
	333 -32.4 (1, 1)
	335 dload_1 (1, 1)
	336 ldc2_w (1, 1)
	337 48.6 (1, 1)
	339 dload_1 (1, 1)
	340 ldc2_w (1, 1)
	341 -567.0 (1, 1)
	343 dmul (1, 1)
	344 ldc2_w (1, 1)
	345 25.0 (1, 1)
	347 ddiv (1, 1)
	348 dadd (1, 1)
	349 dmul (1, 1)
	350 dadd (1, 1)
	351 dmul (1, 1)
	352 dadd (1, 1)
	353 dmul (1, 1)
	354 dstore (1, 1)
	355 #25 (1, 1)
	356 dload_1 (1, 1)
	357 ldc2_w (1, 1)
	358 833.0 (1, 1)
	360 ldc2_w (1, 1)
	361 343.0 (1, 1)
	363 getstatic (1, 1)
	364 org/apache/commons/math3/ode/nonstiff/LutherStepInterpolator.Q:D (1, 1)
	366 dmul (1, 1)
	367 dadd (1, 1)
	368 ldc2_w (1, 1)
	369 300.0 (1, 1)
	371 ddiv (1, 1)
	372 dload_1 (1, 1)
	373 ldc2_w (1, 1)
	374 -637.0 (1, 1)
	376 ldc2_w (1, 1)
	377 357.0 (1, 1)
	379 getstatic (1, 1)
	380 org/apache/commons/math3/ode/nonstiff/LutherStepInterpolator.Q:D (1, 1)
	382 dmul (1, 1)
	383 dsub (1, 1)
	384 ldc2_w (1, 1)
	385 90.0 (1, 1)
	387 ddiv (1, 1)
	388 dload_1 (1, 1)
	389 ldc2_w (1, 1)
	390 392.0 (1, 1)
	392 ldc2_w (1, 1)
	393 287.0 (1, 1)
	395 getstatic (1, 1)
	396 org/apache/commons/math3/ode/nonstiff/LutherStepInterpolator.Q:D (1, 1)
	398 dmul (1, 1)
	399 dadd (1, 1)
	400 ldc2_w (1, 1)
	401 60.0 (1, 1)
	403 ddiv (1, 1)
	404 dload_1 (1, 1)
	405 ldc2_w (1, 1)
	406 -49.0 (1, 1)
	408 ldc2_w (1, 1)
	409 49.0 (1, 1)
	411 getstatic (1, 1)
	412 org/apache/commons/math3/ode/nonstiff/LutherStepInterpolator.Q:D (1, 1)
	414 dmul (1, 1)
	415 dsub (1, 1)
	416 dmul (1, 1)
	417 ldc2_w (1, 1)
	418 25.0 (1, 1)
	420 ddiv (1, 1)
	421 dadd (1, 1)
	422 dmul (1, 1)
	423 dadd (1, 1)
	424 dmul (1, 1)
	425 dadd (1, 1)
	426 dmul (1, 1)
	427 dstore (1, 1)
	428 #27 (1, 1)
	429 dload_1 (1, 1)
	430 ldc2_w (1, 1)
	431 833.0 (1, 1)
	433 ldc2_w (1, 1)
	434 343.0 (1, 1)
	436 getstatic (1, 1)
	437 org/apache/commons/math3/ode/nonstiff/LutherStepInterpolator.Q:D (1, 1)
	439 dmul (1, 1)
	440 dsub (1, 1)
	441 ldc2_w (1, 1)
	442 300.0 (1, 1)
	444 ddiv (1, 1)
	445 dload_1 (1, 1)
	446 ldc2_w (1, 1)
	447 -637.0 (1, 1)
	449 ldc2_w (1, 1)
	450 357.0 (1, 1)
	452 getstatic (1, 1)
	453 org/apache/commons/math3/ode/nonstiff/LutherStepInterpolator.Q:D (1, 1)
	455 dmul (1, 1)
	456 dadd (1, 1)
	457 ldc2_w (1, 1)
	458 90.0 (1, 1)
	460 ddiv (1, 1)
	461 dload_1 (1, 1)
	462 ldc2_w (1, 1)
	463 392.0 (1, 1)
	465 ldc2_w (1, 1)
	466 287.0 (1, 1)
	468 getstatic (1, 1)
	469 org/apache/commons/math3/ode/nonstiff/LutherStepInterpolator.Q:D (1, 1)
	471 dmul (1, 1)
	472 dsub (1, 1)
	473 ldc2_w (1, 1)
	474 60.0 (1, 1)
	476 ddiv (1, 1)
	477 dload_1 (1, 1)
	478 ldc2_w (1, 1)
	479 -49.0 (1, 1)
	481 ldc2_w (1, 1)
	482 49.0 (1, 1)
	484 getstatic (1, 1)
	485 org/apache/commons/math3/ode/nonstiff/LutherStepInterpolator.Q:D (1, 1)
	487 dmul (1, 1)
	488 dadd (1, 1)
	489 dmul (1, 1)
	490 ldc2_w (1, 1)
	491 25.0 (1, 1)
	493 ddiv (1, 1)
	494 dadd (1, 1)
	495 dmul (1, 1)
	496 dadd (1, 1)
	497 dmul (1, 1)
	498 dadd (1, 1)
	499 dmul (1, 1)
	500 dstore (1, 1)
	501 #29 (1, 1)
	502 dload_1 (1, 1)
	503 ldc2_w (1, 1)
	504 0.3 (1, 1)
	506 dload_1 (1, 1)
	507 ldc2_w (1, 1)
	508 -1.0 (1, 1)
	510 dload_1 (1, 1)
	511 ldc2_w (1, 1)
	512 0.75 (1, 1)
	514 dmul (1, 1)
	515 dadd (1, 1)
	516 dmul (1, 1)
	517 dadd (1, 1)
	518 dmul (1, 1)
	519 dstore (1, 1)
	520 #31 (1, 1)
	521 iconst_0 (2, 4)
	522 istore (2, 4)
	523 #33 (2, 4)
	524 iload (2, 4)
	525 #33 (2, 4)
	526 aload_0 (2, 4)
	527 getfield (2, 4)
	528 org/apache/commons/math3/ode/nonstiff/LutherStepInterpolator.interpolatedState:[D (2, 4)
	530 arraylength (2, 4)
	531 if_icmpge (2, 4)
	532 196 (2, 4)
	534 aload_0 (2, 4)
	535 getfield (2, 4)
	536 org/apache/commons/math3/ode/nonstiff/LutherStepInterpolator.yDotK:[[D (2, 4)
	538 iconst_0 (2, 4)
	539 aaload (2, 4)
	540 iload (2, 4)
	541 #33 (2, 4)
	542 daload (2, 4)
	543 dstore (2, 4)
	544 #34 (2, 4)
	545 aload_0 (2, 4)
	546 getfield (2, 4)
	547 org/apache/commons/math3/ode/nonstiff/LutherStepInterpolator.yDotK:[[D (2, 4)
	549 iconst_1 (2, 4)
	550 aaload (2, 4)
	551 iload (2, 4)
	552 #33 (2, 4)
	553 daload (2, 4)
	554 dstore (2, 4)
	555 #36 (2, 4)
	556 aload_0 (2, 4)
	557 getfield (2, 4)
	558 org/apache/commons/math3/ode/nonstiff/LutherStepInterpolator.yDotK:[[D (2, 4)
	560 iconst_2 (2, 4)
	561 aaload (2, 4)
	562 iload (2, 4)
	563 #33 (2, 4)
	564 daload (2, 4)
	565 dstore (2, 4)
	566 #38 (2, 4)
	567 aload_0 (2, 4)
	568 getfield (2, 4)
	569 org/apache/commons/math3/ode/nonstiff/LutherStepInterpolator.yDotK:[[D (2, 4)
	571 iconst_3 (2, 4)
	572 aaload (2, 4)
	573 iload (2, 4)
	574 #33 (2, 4)
	575 daload (2, 4)
	576 dstore (2, 4)
	577 #40 (2, 4)
	578 aload_0 (2, 4)
	579 getfield (2, 4)
	580 org/apache/commons/math3/ode/nonstiff/LutherStepInterpolator.yDotK:[[D (2, 4)
	582 iconst_4 (2, 4)
	583 aaload (2, 4)
	584 iload (2, 4)
	585 #33 (2, 4)
	586 daload (2, 4)
	587 dstore (2, 4)
	588 #42 (2, 4)
	589 aload_0 (2, 4)
	590 getfield (2, 4)
	591 org/apache/commons/math3/ode/nonstiff/LutherStepInterpolator.yDotK:[[D (2, 4)
	593 iconst_5 (2, 4)
	594 aaload (2, 4)
	595 iload (2, 4)
	596 #33 (2, 4)
	597 daload (2, 4)
	598 dstore (2, 4)
	599 #44 (2, 4)
	600 aload_0 (2, 4)
	601 getfield (2, 4)
	602 org/apache/commons/math3/ode/nonstiff/LutherStepInterpolator.yDotK:[[D (2, 4)
	604 bipush (2, 4)
	605 6 (2, 4)
	606 aaload (2, 4)
	607 iload (2, 4)
	608 #33 (2, 4)
	609 daload (2, 4)
	610 dstore (2, 4)
	611 #46 (2, 4)
	612 aload_0 (2, 4)
	613 getfield (2, 4)
	614 org/apache/commons/math3/ode/nonstiff/LutherStepInterpolator.interpolatedState:[D (2, 4)
	616 iload (2, 4)
	617 #33 (2, 4)
	618 aload_0 (2, 4)
	619 getfield (2, 4)
	620 org/apache/commons/math3/ode/nonstiff/LutherStepInterpolator.previousState:[D (2, 4)
	622 iload (2, 4)
	623 #33 (2, 4)
	624 daload (2, 4)
	625 dload_1 (2, 4)
	626 aload_0 (2, 4)
	627 getfield (2, 4)
	628 org/apache/commons/math3/ode/nonstiff/LutherStepInterpolator.h:D (2, 4)
	630 dmul (2, 4)
	631 dload (2, 4)
	632 #19 (2, 4)
	633 dload (2, 4)
	634 #34 (2, 4)
	635 dmul (2, 4)
	636 dconst_0 (2, 4)
	637 dload (2, 4)
	638 #36 (2, 4)
	639 dmul (2, 4)
	640 dadd (2, 4)
	641 dload (2, 4)
	642 #23 (2, 4)
	643 dload (2, 4)
	644 #38 (2, 4)
	645 dmul (2, 4)
	646 dadd (2, 4)
	647 dload (2, 4)
	648 #25 (2, 4)
	649 dload (2, 4)
	650 #40 (2, 4)
	651 dmul (2, 4)
	652 dadd (2, 4)
	653 dload (2, 4)
	654 #27 (2, 4)
	655 dload (2, 4)
	656 #42 (2, 4)
	657 dmul (2, 4)
	658 dadd (2, 4)
	659 dload (2, 4)
	660 #29 (2, 4)
	661 dload (2, 4)
	662 #44 (2, 4)
	663 dmul (2, 4)
	664 dadd (2, 4)
	665 dload (2, 4)
	666 #31 (2, 4)
	667 dload (2, 4)
	668 #46 (2, 4)
	669 dmul (2, 4)
	670 dadd (2, 4)
	671 dmul (2, 4)
	672 dadd (2, 4)
	673 dastore (2, 4)
	674 aload_0 (2, 4)
	675 getfield (2, 4)
	676 org/apache/commons/math3/ode/nonstiff/LutherStepInterpolator.interpolatedDerivatives:[D (2, 4)
	678 iload (2, 4)
	679 #33 (2, 4)
	680 dload (2, 4)
	681 #5 (2, 4)
	682 dload (2, 4)
	683 #34 (2, 4)
	684 dmul (2, 4)
	685 dconst_0 (2, 4)
	686 dload (2, 4)
	687 #36 (2, 4)
	688 dmul (2, 4)
	689 dadd (2, 4)
	690 dload (2, 4)
	691 #9 (2, 4)
	692 dload (2, 4)
	693 #38 (2, 4)
	694 dmul (2, 4)
	695 dadd (2, 4)
	696 dload (2, 4)
	697 #11 (2, 4)
	698 dload (2, 4)
	699 #40 (2, 4)
	700 dmul (2, 4)
	701 dadd (2, 4)
	702 dload (2, 4)
	703 #13 (2, 4)
	704 dload (2, 4)
	705 #42 (2, 4)
	706 dmul (2, 4)
	707 dadd (2, 4)
	708 dload (2, 4)
	709 #15 (2, 4)
	710 dload (2, 4)
	711 #44 (2, 4)
	712 dmul (2, 4)
	713 dadd (2, 4)
	714 dload (2, 4)
	715 #17 (2, 4)
	716 dload (2, 4)
	717 #46 (2, 4)
	718 dmul (2, 4)
	719 dadd (2, 4)
	720 dastore (2, 4)
	721 iinc (2, 4)
	722 #33 (2, 4)
	723 -89 (2, 4)
	724 goto (2, 4)
	725 -200 (2, 4)
	727 goto (2, 2)
	728 451 (2, 2)
	730 ldc2_w (2, 2)
	731 -0.05 (2, 2)
	733 dload_1 (2, 2)
	734 ldc2_w (2, 2)
	735 0.95 (2, 2)
	737 dload_1 (2, 2)
	738 ldc2_w (2, 2)
	739 -4.45 (2, 2)
	741 dload_1 (2, 2)
	742 ldc2_w (2, 2)
	743 7.55 (2, 2)
	745 dload_1 (2, 2)
	746 ldc2_w (2, 2)
	747 -21.0 (2, 2)
	749 dmul (2, 2)
	750 ldc2_w (2, 2)
	751 5.0 (2, 2)
	753 ddiv (2, 2)
	754 dadd (2, 2)
	755 dmul (2, 2)
	756 dadd (2, 2)
	757 dmul (2, 2)
	758 dadd (2, 2)
	759 dmul (2, 2)
	760 dadd (2, 2)
	761 dstore (2, 2)
	762 #19 (2, 2)
	763 dconst_0 (2, 2)
	764 dstore (2, 2)
	765 #21 (2, 2)
	766 ldc2_w (2, 2)
	767 -0.35555555555555557 (2, 2)
	769 dload_1 (2, 2)
	770 ldc2_w (2, 2)
	771 -0.35555555555555557 (2, 2)
	773 dload_1 (2, 2)
	774 ldc2_w (2, 2)
	775 -7.288888888888889 (2, 2)
	777 dload_1 (2, 2)
	778 ldc2_w (2, 2)
	779 28.266666666666666 (2, 2)
	781 dload_1 (2, 2)
	782 ldc2_w (2, 2)
	783 -112.0 (2, 2)
	785 dmul (2, 2)
	786 ldc2_w (2, 2)
	787 5.0 (2, 2)
	789 ddiv (2, 2)
	790 dadd (2, 2)
	791 dmul (2, 2)
	792 dadd (2, 2)
	793 dmul (2, 2)
	794 dadd (2, 2)
	795 dmul (2, 2)
	796 dadd (2, 2)
	797 dstore (2, 2)
	798 #23 (2, 2)
	799 dload_1 (2, 2)
	800 dload_1 (2, 2)
	801 ldc2_w (2, 2)
	802 6.48 (2, 2)
	804 dload_1 (2, 2)
	805 ldc2_w (2, 2)
	806 -25.92 (2, 2)
	808 dload_1 (2, 2)
	809 ldc2_w (2, 2)
	810 567.0 (2, 2)
	812 dmul (2, 2)
	813 ldc2_w (2, 2)
	814 25.0 (2, 2)
	816 ddiv (2, 2)
	817 dadd (2, 2)
	818 dmul (2, 2)
	819 dadd (2, 2)
	820 dmul (2, 2)
	821 dmul (2, 2)
	822 dstore (2, 2)
	823 #25 (2, 2)
	824 ldc2_w (2, 2)
	825 -0.2722222222222222 (2, 2)
	827 dload_1 (2, 2)
	828 ldc2_w (2, 2)
	829 -0.2722222222222222 (2, 2)
	831 dload_1 (2, 2)
	832 ldc2_w (2, 2)
	833 2254.0 (2, 2)
	835 ldc2_w (2, 2)
	836 1029.0 (2, 2)
	838 getstatic (2, 2)
	839 org/apache/commons/math3/ode/nonstiff/LutherStepInterpolator.Q:D (2, 2)
	841 dmul (2, 2)
	842 dadd (2, 2)
	843 ldc2_w (2, 2)
	844 900.0 (2, 2)
	846 ddiv (2, 2)
	847 dload_1 (2, 2)
	848 ldc2_w (2, 2)
	849 -1372.0 (2, 2)
	851 ldc2_w (2, 2)
	852 847.0 (2, 2)
	854 getstatic (2, 2)
	855 org/apache/commons/math3/ode/nonstiff/LutherStepInterpolator.Q:D (2, 2)
	857 dmul (2, 2)
	858 dsub (2, 2)
	859 ldc2_w (2, 2)
	860 300.0 (2, 2)
	862 ddiv (2, 2)
	863 dload_1 (2, 2)
	864 ldc2_w (2, 2)
	865 49.0 (2, 2)
	867 ldc2_w (2, 2)
	868 49.0 (2, 2)
	870 getstatic (2, 2)
	871 org/apache/commons/math3/ode/nonstiff/LutherStepInterpolator.Q:D (2, 2)
	873 dmul (2, 2)
	874 dadd (2, 2)
	875 dmul (2, 2)
	876 ldc2_w (2, 2)
	877 25.0 (2, 2)
	879 ddiv (2, 2)
	880 dadd (2, 2)
	881 dmul (2, 2)
	882 dadd (2, 2)
	883 dmul (2, 2)
	884 dadd (2, 2)
	885 dmul (2, 2)
	886 dadd (2, 2)
	887 dstore (2, 2)
	888 #27 (2, 2)
	889 ldc2_w (2, 2)
	890 -0.2722222222222222 (2, 2)
	892 dload_1 (2, 2)
	893 ldc2_w (2, 2)
	894 -0.2722222222222222 (2, 2)
	896 dload_1 (2, 2)
	897 ldc2_w (2, 2)
	898 2254.0 (2, 2)
	900 ldc2_w (2, 2)
	901 1029.0 (2, 2)
	903 getstatic (2, 2)
	904 org/apache/commons/math3/ode/nonstiff/LutherStepInterpolator.Q:D (2, 2)
	906 dmul (2, 2)
	907 dsub (2, 2)
	908 ldc2_w (2, 2)
	909 900.0 (2, 2)
	911 ddiv (2, 2)
	912 dload_1 (2, 2)
	913 ldc2_w (2, 2)
	914 -1372.0 (2, 2)
	916 ldc2_w (2, 2)
	917 847.0 (2, 2)
	919 getstatic (2, 2)
	920 org/apache/commons/math3/ode/nonstiff/LutherStepInterpolator.Q:D (2, 2)
	922 dmul (2, 2)
	923 dadd (2, 2)
	924 ldc2_w (2, 2)
	925 300.0 (2, 2)
	927 ddiv (2, 2)
	928 dload_1 (2, 2)
	929 ldc2_w (2, 2)
	930 49.0 (2, 2)
	932 ldc2_w (2, 2)
	933 49.0 (2, 2)
	935 getstatic (2, 2)
	936 org/apache/commons/math3/ode/nonstiff/LutherStepInterpolator.Q:D (2, 2)
	938 dmul (2, 2)
	939 dsub (2, 2)
	940 dmul (2, 2)
	941 ldc2_w (2, 2)
	942 25.0 (2, 2)
	944 ddiv (2, 2)
	945 dadd (2, 2)
	946 dmul (2, 2)
	947 dadd (2, 2)
	948 dmul (2, 2)
	949 dadd (2, 2)
	950 dmul (2, 2)
	951 dadd (2, 2)
	952 dstore (2, 2)
	953 #29 (2, 2)
	954 ldc2_w (2, 2)
	955 -0.05 (2, 2)
	957 dload_1 (2, 2)
	958 ldc2_w (2, 2)
	959 -0.05 (2, 2)
	961 dload_1 (2, 2)
	962 ldc2_w (2, 2)
	963 0.25 (2, 2)
	965 dload_1 (2, 2)
	966 ldc2_w (2, 2)
	967 -0.75 (2, 2)
	969 dmul (2, 2)
	970 dadd (2, 2)
	971 dmul (2, 2)
	972 dadd (2, 2)
	973 dmul (2, 2)
	974 dadd (2, 2)
	975 dstore (2, 2)
	976 #31 (2, 2)
	977 iconst_0 (3, 4)
	978 istore (3, 4)
	979 #33 (3, 4)
	980 iload (3, 4)
	981 #33 (3, 4)
	982 aload_0 (3, 4)
	983 getfield (3, 4)
	984 org/apache/commons/math3/ode/nonstiff/LutherStepInterpolator.interpolatedState:[D (3, 4)
	986 arraylength (3, 4)
	987 if_icmpge (3, 4)
	988 191 (3, 4)
	990 aload_0 (3, 4)
	991 getfield (3, 4)
	992 org/apache/commons/math3/ode/nonstiff/LutherStepInterpolator.yDotK:[[D (3, 4)
	994 iconst_0 (3, 4)
	995 aaload (3, 4)
	996 iload (3, 4)
	997 #33 (3, 4)
	998 daload (3, 4)
	999 dstore (3, 4)
	1000 #34 (3, 4)
	1001 aload_0 (3, 4)
	1002 getfield (3, 4)
	1003 org/apache/commons/math3/ode/nonstiff/LutherStepInterpolator.yDotK:[[D (3, 4)
	1005 iconst_1 (3, 4)
	1006 aaload (3, 4)
	1007 iload (3, 4)
	1008 #33 (3, 4)
	1009 daload (3, 4)
	1010 dstore (3, 4)
	1011 #36 (3, 4)
	1012 aload_0 (3, 4)
	1013 getfield (3, 4)
	1014 org/apache/commons/math3/ode/nonstiff/LutherStepInterpolator.yDotK:[[D (3, 4)
	1016 iconst_2 (3, 4)
	1017 aaload (3, 4)
	1018 iload (3, 4)
	1019 #33 (3, 4)
	1020 daload (3, 4)
	1021 dstore (3, 4)
	1022 #38 (3, 4)
	1023 aload_0 (3, 4)
	1024 getfield (3, 4)
	1025 org/apache/commons/math3/ode/nonstiff/LutherStepInterpolator.yDotK:[[D (3, 4)
	1027 iconst_3 (3, 4)
	1028 aaload (3, 4)
	1029 iload (3, 4)
	1030 #33 (3, 4)
	1031 daload (3, 4)
	1032 dstore (3, 4)
	1033 #40 (3, 4)
	1034 aload_0 (3, 4)
	1035 getfield (3, 4)
	1036 org/apache/commons/math3/ode/nonstiff/LutherStepInterpolator.yDotK:[[D (3, 4)
	1038 iconst_4 (3, 4)
	1039 aaload (3, 4)
	1040 iload (3, 4)
	1041 #33 (3, 4)
	1042 daload (3, 4)
	1043 dstore (3, 4)
	1044 #42 (3, 4)
	1045 aload_0 (3, 4)
	1046 getfield (3, 4)
	1047 org/apache/commons/math3/ode/nonstiff/LutherStepInterpolator.yDotK:[[D (3, 4)
	1049 iconst_5 (3, 4)
	1050 aaload (3, 4)
	1051 iload (3, 4)
	1052 #33 (3, 4)
	1053 daload (3, 4)
	1054 dstore (3, 4)
	1055 #44 (3, 4)
	1056 aload_0 (3, 4)
	1057 getfield (3, 4)
	1058 org/apache/commons/math3/ode/nonstiff/LutherStepInterpolator.yDotK:[[D (3, 4)
	1060 bipush (3, 4)
	1061 6 (3, 4)
	1062 aaload (3, 4)
	1063 iload (3, 4)
	1064 #33 (3, 4)
	1065 daload (3, 4)
	1066 dstore (3, 4)
	1067 #46 (3, 4)
	1068 aload_0 (3, 4)
	1069 getfield (3, 4)
	1070 org/apache/commons/math3/ode/nonstiff/LutherStepInterpolator.interpolatedState:[D (3, 4)
	1072 iload (3, 4)
	1073 #33 (3, 4)
	1074 aload_0 (3, 4)
	1075 getfield (3, 4)
	1076 org/apache/commons/math3/ode/nonstiff/LutherStepInterpolator.currentState:[D (3, 4)
	1078 iload (3, 4)
	1079 #33 (3, 4)
	1080 daload (3, 4)
	1081 dload_3 (3, 4)
	1082 dload (3, 4)
	1083 #19 (3, 4)
	1084 dload (3, 4)
	1085 #34 (3, 4)
	1086 dmul (3, 4)
	1087 dconst_0 (3, 4)
	1088 dload (3, 4)
	1089 #36 (3, 4)
	1090 dmul (3, 4)
	1091 dadd (3, 4)
	1092 dload (3, 4)
	1093 #23 (3, 4)
	1094 dload (3, 4)
	1095 #38 (3, 4)
	1096 dmul (3, 4)
	1097 dadd (3, 4)
	1098 dload (3, 4)
	1099 #25 (3, 4)
	1100 dload (3, 4)
	1101 #40 (3, 4)
	1102 dmul (3, 4)
	1103 dadd (3, 4)
	1104 dload (3, 4)
	1105 #27 (3, 4)
	1106 dload (3, 4)
	1107 #42 (3, 4)
	1108 dmul (3, 4)
	1109 dadd (3, 4)
	1110 dload (3, 4)
	1111 #29 (3, 4)
	1112 dload (3, 4)
	1113 #44 (3, 4)
	1114 dmul (3, 4)
	1115 dadd (3, 4)
	1116 dload (3, 4)
	1117 #31 (3, 4)
	1118 dload (3, 4)
	1119 #46 (3, 4)
	1120 dmul (3, 4)
	1121 dadd (3, 4)
	1122 dmul (3, 4)
	1123 dadd (3, 4)
	1124 dastore (3, 4)
	1125 aload_0 (3, 4)
	1126 getfield (3, 4)
	1127 org/apache/commons/math3/ode/nonstiff/LutherStepInterpolator.interpolatedDerivatives:[D (3, 4)
	1129 iload (3, 4)
	1130 #33 (3, 4)
	1131 dload (3, 4)
	1132 #5 (3, 4)
	1133 dload (3, 4)
	1134 #34 (3, 4)
	1135 dmul (3, 4)
	1136 dconst_0 (3, 4)
	1137 dload (3, 4)
	1138 #36 (3, 4)
	1139 dmul (3, 4)
	1140 dadd (3, 4)
	1141 dload (3, 4)
	1142 #9 (3, 4)
	1143 dload (3, 4)
	1144 #38 (3, 4)
	1145 dmul (3, 4)
	1146 dadd (3, 4)
	1147 dload (3, 4)
	1148 #11 (3, 4)
	1149 dload (3, 4)
	1150 #40 (3, 4)
	1151 dmul (3, 4)
	1152 dadd (3, 4)
	1153 dload (3, 4)
	1154 #13 (3, 4)
	1155 dload (3, 4)
	1156 #42 (3, 4)
	1157 dmul (3, 4)
	1158 dadd (3, 4)
	1159 dload (3, 4)
	1160 #15 (3, 4)
	1161 dload (3, 4)
	1162 #44 (3, 4)
	1163 dmul (3, 4)
	1164 dadd (3, 4)
	1165 dload (3, 4)
	1166 #17 (3, 4)
	1167 dload (3, 4)
	1168 #46 (3, 4)
	1169 dmul (3, 4)
	1170 dadd (3, 4)
	1171 dastore (3, 4)
	1172 iinc (3, 4)
	1173 #33 (3, 4)
	1174 -89 (3, 4)
	1175 goto (3, 4)
	1176 -195 (3, 4)
	1178 return (0, 0)

Method: <clinit>
	0 ldc2_w (0, 0)
	1 21.0 (0, 0)
	3 invokestatic (0, 0)
	4 org/apache/commons/math3/util/FastMath.sqrt:(D)D (0, 0)
	6 putstatic (0, 0)
	7 org/apache/commons/math3/ode/nonstiff/LutherStepInterpolator.Q:D (0, 0)
	9 return (0, 0)

