Method: <init>
	0 aload_0 (0, 0)
	1 aload_1 (0, 0)
	2 ldc (0, 0)
	3 Luther (0, 0)
	4 aload_2 (0, 0)
	5 invokespecial (0, 0)
	6 org/apache/commons/math3/ode/nonstiff/RungeKuttaFieldIntegrator.<init>:(Lorg/apache/commons/math3/Field;Ljava/lang/String;Lorg/apache/commons/math3/RealFieldElement;)V (0, 0)
	8 return (0, 0)

Method: getC
	0 aload_0 (0, 0)
	1 invokevirtual (0, 0)
	2 org/apache/commons/math3/ode/nonstiff/LutherFieldIntegrator.getField:()Lorg/apache/commons/math3/Field; (0, 0)
	4 invokeinterface (0, 0)
	5 org/apache/commons/math3/Field.org/apache/commons/math3/RealFieldElement (0, 0)
	7 0 (0, 0)
	9 checkcast (0, 0)
	10 org/apache/commons/math3/RealFieldElement (0, 0)
	12 ldc2_w (0, 0)
	13 21.0 (0, 0)
	15 invokeinterface (0, 0)
	16 org/apache/commons/math3/RealFieldElement.sqrt:()Ljava/lang/Object; (0, 0)
	18 0 (0, 0)
	20 checkcast (0, 0)
	21 org/apache/commons/math3/RealFieldElement (0, 0)
	23 invokeinterface (0, 0)
	24 org/apache/commons/math3/RealFieldElement.org/apache/commons/math3/util/MathArrays (0, 0)
	26 0 (0, 0)
	28 checkcast (0, 0)
	29 org/apache/commons/math3/RealFieldElement (0, 0)
	31 astore_1 (0, 0)
	32 aload_0 (0, 0)
	33 invokevirtual (0, 0)
	34 org/apache/commons/math3/ode/nonstiff/LutherFieldIntegrator.getField:()Lorg/apache/commons/math3/Field; (0, 0)
	36 bipush (0, 0)
	37 6 (0, 0)
	38 invokestatic (0, 0)
	39 org/apache/commons/math3/util/MathArrays.buildArray:(Lorg/apache/commons/math3/Field;I)[Ljava/lang/Object; (0, 0)
	41 checkcast (0, 0)
	42 [Lorg/apache/commons/math3/RealFieldElement; (0, 0)
	44 astore_2 (0, 0)
	45 aload_2 (0, 0)
	46 iconst_0 (0, 0)
	47 aload_0 (0, 0)
	48 invokevirtual (0, 0)
	49 org/apache/commons/math3/ode/nonstiff/LutherFieldIntegrator.getField:()Lorg/apache/commons/math3/Field; (0, 0)
	51 invokeinterface (0, 0)
	52 org/apache/commons/math3/Field.fraction:(II)Lorg/apache/commons/math3/RealFieldElement; (0, 0)
	54 0 (0, 0)
	56 checkcast (0, 0)
	57 org/apache/commons/math3/RealFieldElement (0, 0)
	59 aastore (0, 0)
	60 aload_2 (0, 0)
	61 iconst_1 (0, 0)
	62 aload_0 (0, 0)
	63 iconst_1 (0, 0)
	64 iconst_2 (0, 0)
	65 invokevirtual (0, 0)
	66 org/apache/commons/math3/ode/nonstiff/LutherFieldIntegrator.fraction:(II)Lorg/apache/commons/math3/RealFieldElement; (0, 0)
	68 aastore (0, 0)
	69 aload_2 (0, 0)
	70 iconst_2 (0, 0)
	71 aload_0 (0, 0)
	72 iconst_2 (0, 0)
	73 iconst_3 (0, 0)
	74 invokevirtual (0, 0)
	75 org/apache/commons/math3/ode/nonstiff/LutherFieldIntegrator.fraction:(II)Lorg/apache/commons/math3/RealFieldElement; (0, 0)
	77 aastore (0, 0)
	78 aload_2 (0, 0)
	79 iconst_3 (0, 0)
	80 aload_1 (0, 0)
	81 ldc2_w (0, 0)
	82 7.0 (0, 0)
	84 invokeinterface (0, 0)
	85 org/apache/commons/math3/RealFieldElement.divide:(D)Ljava/lang/Object; (0, 0)
	87 0 (0, 0)
	89 checkcast (0, 0)
	90 org/apache/commons/math3/RealFieldElement (0, 0)
	92 ldc2_w (0, 0)
	93 -14.0 (0, 0)
	95 invokeinterface (0, 0)
	96 org/apache/commons/math3/RealFieldElement.buildArray:(Lorg/apache/commons/math3/Field;II)[[Ljava/lang/Object; (0, 0)
	98 0 (0, 0)
	100 checkcast (0, 0)
	101 org/apache/commons/math3/RealFieldElement (0, 0)
	103 aastore (0, 0)
	104 aload_2 (0, 0)
	105 iconst_4 (0, 0)
	106 aload_1 (0, 0)
	107 ldc2_w (0, 0)
	108 7.0 (0, 0)
	110 invokeinterface (0, 0)
	111 org/apache/commons/math3/RealFieldElement.sqrt:()Ljava/lang/Object; (0, 0)
	113 0 (0, 0)
	115 checkcast (0, 0)
	116 org/apache/commons/math3/RealFieldElement (0, 0)
	118 ldc2_w (0, 0)
	119 14.0 (0, 0)
	121 invokeinterface (0, 0)
	122 org/apache/commons/math3/RealFieldElement.buildArray:(Lorg/apache/commons/math3/Field;II)[[Ljava/lang/Object; (0, 0)
	124 0 (0, 0)
	126 checkcast (0, 0)
	127 org/apache/commons/math3/RealFieldElement (0, 0)
	129 aastore (0, 0)
	130 aload_2 (0, 0)
	131 iconst_5 (0, 0)
	132 aload_0 (0, 0)
	133 invokevirtual (0, 0)
	134 org/apache/commons/math3/ode/nonstiff/LutherFieldIntegrator.getField:()Lorg/apache/commons/math3/Field; (0, 0)
	136 invokeinterface (0, 0)
	137 org/apache/commons/math3/Field.fraction:(II)Lorg/apache/commons/math3/RealFieldElement; (0, 0)
	139 0 (0, 0)
	141 checkcast (0, 0)
	142 org/apache/commons/math3/RealFieldElement (0, 0)
	144 aastore (0, 0)
	145 aload_2 (0, 0)
	146 areturn (0, 0)

Method: getA
	0 aload_0 (0, 0)
	1 invokevirtual (0, 0)
	2 org/apache/commons/math3/ode/nonstiff/LutherFieldIntegrator.getField:()Lorg/apache/commons/math3/Field; (0, 0)
	4 invokeinterface (0, 0)
	5 org/apache/commons/math3/Field.org/apache/commons/math3/RealFieldElement (0, 0)
	7 0 (0, 0)
	9 checkcast (0, 0)
	10 org/apache/commons/math3/RealFieldElement (0, 0)
	12 ldc2_w (0, 0)
	13 21.0 (0, 0)
	15 invokeinterface (0, 0)
	16 org/apache/commons/math3/RealFieldElement.sqrt:()Ljava/lang/Object; (0, 0)
	18 0 (0, 0)
	20 checkcast (0, 0)
	21 org/apache/commons/math3/RealFieldElement (0, 0)
	23 invokeinterface (0, 0)
	24 org/apache/commons/math3/RealFieldElement.org/apache/commons/math3/util/MathArrays (0, 0)
	26 0 (0, 0)
	28 checkcast (0, 0)
	29 org/apache/commons/math3/RealFieldElement (0, 0)
	31 astore_1 (0, 0)
	32 aload_0 (0, 0)
	33 invokevirtual (0, 0)
	34 org/apache/commons/math3/ode/nonstiff/LutherFieldIntegrator.getField:()Lorg/apache/commons/math3/Field; (0, 0)
	36 bipush (0, 0)
	37 6 (0, 0)
	38 iconst_m1 (0, 0)
	39 invokestatic (0, 0)
	40 org/apache/commons/math3/util/MathArrays.buildArray:(Lorg/apache/commons/math3/Field;II)[[Ljava/lang/Object; (0, 0)
	42 checkcast (0, 0)
	43 [[Lorg/apache/commons/math3/RealFieldElement; (0, 0)
	45 astore_2 (0, 0)
	46 iconst_0 (1, 4)
	47 istore_3 (1, 4)
	48 iload_3 (1, 4)
	49 aload_2 (1, 4)
	50 arraylength (1, 4)
	51 if_icmpge (1, 4)
	52 25 (1, 4)
	54 aload_2 (1, 4)
	55 iload_3 (1, 4)
	56 aload_0 (1, 4)
	57 invokevirtual (1, 4)
	58 org/apache/commons/math3/ode/nonstiff/LutherFieldIntegrator.getField:()Lorg/apache/commons/math3/Field; (1, 4)
	60 iload_3 (1, 4)
	61 iconst_1 (1, 4)
	62 iadd (1, 4)
	63 invokestatic (1, 4)
	64 org/apache/commons/math3/util/MathArrays.buildArray:(Lorg/apache/commons/math3/Field;I)[Ljava/lang/Object; (1, 4)
	66 checkcast (1, 4)
	67 [Lorg/apache/commons/math3/RealFieldElement; (1, 4)
	69 aastore (1, 4)
	70 iinc (1, 4)
	71 #3 (1, 4)
	72 -89 (1, 4)
	73 goto (1, 4)
	74 -25 (1, 4)
	76 aload_2 (0, 0)
	77 iconst_0 (0, 0)
	78 aaload (0, 0)
	79 iconst_0 (0, 0)
	80 aload_0 (0, 0)
	81 invokevirtual (0, 0)
	82 org/apache/commons/math3/ode/nonstiff/LutherFieldIntegrator.getField:()Lorg/apache/commons/math3/Field; (0, 0)
	84 invokeinterface (0, 0)
	85 org/apache/commons/math3/Field.fraction:(II)Lorg/apache/commons/math3/RealFieldElement; (0, 0)
	87 0 (0, 0)
	89 checkcast (0, 0)
	90 org/apache/commons/math3/RealFieldElement (0, 0)
	92 aastore (0, 0)
	93 aload_2 (0, 0)
	94 iconst_1 (0, 0)
	95 aaload (0, 0)
	96 iconst_0 (0, 0)
	97 aload_0 (0, 0)
	98 iconst_3 (0, 0)
	99 bipush (0, 0)
	100 8 (0, 0)
	101 invokevirtual (0, 0)
	102 org/apache/commons/math3/ode/nonstiff/LutherFieldIntegrator.fraction:(II)Lorg/apache/commons/math3/RealFieldElement; (0, 0)
	104 aastore (0, 0)
	105 aload_2 (0, 0)
	106 iconst_1 (0, 0)
	107 aaload (0, 0)
	108 iconst_1 (0, 0)
	109 aload_0 (0, 0)
	110 iconst_1 (0, 0)
	111 bipush (0, 0)
	112 8 (0, 0)
	113 invokevirtual (0, 0)
	114 org/apache/commons/math3/ode/nonstiff/LutherFieldIntegrator.fraction:(II)Lorg/apache/commons/math3/RealFieldElement; (0, 0)
	116 aastore (0, 0)
	117 aload_2 (0, 0)
	118 iconst_2 (0, 0)
	119 aaload (0, 0)
	120 iconst_0 (0, 0)
	121 aload_0 (0, 0)
	122 bipush (0, 0)
	123 8 (0, 0)
	124 bipush (0, 0)
	125 27 (0, 0)
	126 invokevirtual (0, 0)
	127 org/apache/commons/math3/ode/nonstiff/LutherFieldIntegrator.fraction:(II)Lorg/apache/commons/math3/RealFieldElement; (0, 0)
	129 aastore (0, 0)
	130 aload_2 (0, 0)
	131 iconst_2 (0, 0)
	132 aaload (0, 0)
	133 iconst_1 (0, 0)
	134 aload_0 (0, 0)
	135 iconst_2 (0, 0)
	136 bipush (0, 0)
	137 27 (0, 0)
	138 invokevirtual (0, 0)
	139 org/apache/commons/math3/ode/nonstiff/LutherFieldIntegrator.fraction:(II)Lorg/apache/commons/math3/RealFieldElement; (0, 0)
	141 aastore (0, 0)
	142 aload_2 (0, 0)
	143 iconst_2 (0, 0)
	144 aaload (0, 0)
	145 iconst_2 (0, 0)
	146 aload_2 (0, 0)
	147 iconst_2 (0, 0)
	148 aaload (0, 0)
	149 iconst_0 (0, 0)
	150 aaload (0, 0)
	151 aastore (0, 0)
	152 aload_2 (0, 0)
	153 iconst_3 (0, 0)
	154 aaload (0, 0)
	155 iconst_0 (0, 0)
	156 aload_1 (0, 0)
	157 bipush (0, 0)
	158 9 (0, 0)
	159 invokeinterface (0, 0)
	160 org/apache/commons/math3/RealFieldElement.org/apache/commons/math3/ode/nonstiff/LutherFieldStepInterpolator (0, 0)
	162 0 (0, 0)
	164 checkcast (0, 0)
	165 org/apache/commons/math3/RealFieldElement (0, 0)
	167 ldc2_w (0, 0)
	168 -21.0 (0, 0)
	170 invokeinterface (0, 0)
	171 org/apache/commons/math3/RealFieldElement.sqrt:()Ljava/lang/Object; (0, 0)
	173 0 (0, 0)
	175 checkcast (0, 0)
	176 org/apache/commons/math3/RealFieldElement (0, 0)
	178 ldc2_w (0, 0)
	179 392.0 (0, 0)
	181 invokeinterface (0, 0)
	182 org/apache/commons/math3/RealFieldElement.buildArray:(Lorg/apache/commons/math3/Field;II)[[Ljava/lang/Object; (0, 0)
	184 0 (0, 0)
	186 checkcast (0, 0)
	187 org/apache/commons/math3/RealFieldElement (0, 0)
	189 aastore (0, 0)
	190 aload_2 (0, 0)
	191 iconst_3 (0, 0)
	192 aaload (0, 0)
	193 iconst_1 (0, 0)
	194 aload_1 (0, 0)
	195 bipush (0, 0)
	196 8 (0, 0)
	197 invokeinterface (0, 0)
	198 org/apache/commons/math3/RealFieldElement.org/apache/commons/math3/ode/nonstiff/LutherFieldStepInterpolator (0, 0)
	200 0 (0, 0)
	202 checkcast (0, 0)
	203 org/apache/commons/math3/RealFieldElement (0, 0)
	205 ldc2_w (0, 0)
	206 -56.0 (0, 0)
	208 invokeinterface (0, 0)
	209 org/apache/commons/math3/RealFieldElement.sqrt:()Ljava/lang/Object; (0, 0)
	211 0 (0, 0)
	213 checkcast (0, 0)
	214 org/apache/commons/math3/RealFieldElement (0, 0)
	216 ldc2_w (0, 0)
	217 392.0 (0, 0)
	219 invokeinterface (0, 0)
	220 org/apache/commons/math3/RealFieldElement.buildArray:(Lorg/apache/commons/math3/Field;II)[[Ljava/lang/Object; (0, 0)
	222 0 (0, 0)
	224 checkcast (0, 0)
	225 org/apache/commons/math3/RealFieldElement (0, 0)
	227 aastore (0, 0)
	228 aload_2 (0, 0)
	229 iconst_3 (0, 0)
	230 aaload (0, 0)
	231 iconst_2 (0, 0)
	232 aload_1 (0, 0)
	233 bipush (0, 0)
	234 -48 (0, 0)
	235 invokeinterface (0, 0)
	236 org/apache/commons/math3/RealFieldElement.org/apache/commons/math3/ode/nonstiff/LutherFieldStepInterpolator (0, 0)
	238 0 (0, 0)
	240 checkcast (0, 0)
	241 org/apache/commons/math3/RealFieldElement (0, 0)
	243 ldc2_w (0, 0)
	244 336.0 (0, 0)
	246 invokeinterface (0, 0)
	247 org/apache/commons/math3/RealFieldElement.sqrt:()Ljava/lang/Object; (0, 0)
	249 0 (0, 0)
	251 checkcast (0, 0)
	252 org/apache/commons/math3/RealFieldElement (0, 0)
	254 ldc2_w (0, 0)
	255 392.0 (0, 0)
	257 invokeinterface (0, 0)
	258 org/apache/commons/math3/RealFieldElement.buildArray:(Lorg/apache/commons/math3/Field;II)[[Ljava/lang/Object; (0, 0)
	260 0 (0, 0)
	262 checkcast (0, 0)
	263 org/apache/commons/math3/RealFieldElement (0, 0)
	265 aastore (0, 0)
	266 aload_2 (0, 0)
	267 iconst_3 (0, 0)
	268 aaload (0, 0)
	269 iconst_3 (0, 0)
	270 aload_1 (0, 0)
	271 iconst_3 (0, 0)
	272 invokeinterface (0, 0)
	273 org/apache/commons/math3/RealFieldElement.org/apache/commons/math3/ode/nonstiff/LutherFieldStepInterpolator (0, 0)
	275 0 (0, 0)
	277 checkcast (0, 0)
	278 org/apache/commons/math3/RealFieldElement (0, 0)
	280 ldc2_w (0, 0)
	281 -63.0 (0, 0)
	283 invokeinterface (0, 0)
	284 org/apache/commons/math3/RealFieldElement.sqrt:()Ljava/lang/Object; (0, 0)
	286 0 (0, 0)
	288 checkcast (0, 0)
	289 org/apache/commons/math3/RealFieldElement (0, 0)
	291 ldc2_w (0, 0)
	292 392.0 (0, 0)
	294 invokeinterface (0, 0)
	295 org/apache/commons/math3/RealFieldElement.buildArray:(Lorg/apache/commons/math3/Field;II)[[Ljava/lang/Object; (0, 0)
	297 0 (0, 0)
	299 checkcast (0, 0)
	300 org/apache/commons/math3/RealFieldElement (0, 0)
	302 aastore (0, 0)
	303 aload_2 (0, 0)
	304 iconst_4 (0, 0)
	305 aaload (0, 0)
	306 iconst_0 (0, 0)
	307 aload_1 (0, 0)
	308 sipush (0, 0)
	309 -255 (0, 0)
	311 invokeinterface (0, 0)
	312 org/apache/commons/math3/RealFieldElement.org/apache/commons/math3/ode/nonstiff/LutherFieldStepInterpolator (0, 0)
	314 0 (0, 0)
	316 checkcast (0, 0)
	317 org/apache/commons/math3/RealFieldElement (0, 0)
	319 ldc2_w (0, 0)
	320 -1155.0 (0, 0)
	322 invokeinterface (0, 0)
	323 org/apache/commons/math3/RealFieldElement.sqrt:()Ljava/lang/Object; (0, 0)
	325 0 (0, 0)
	327 checkcast (0, 0)
	328 org/apache/commons/math3/RealFieldElement (0, 0)
	330 ldc2_w (0, 0)
	331 1960.0 (0, 0)
	333 invokeinterface (0, 0)
	334 org/apache/commons/math3/RealFieldElement.buildArray:(Lorg/apache/commons/math3/Field;II)[[Ljava/lang/Object; (0, 0)
	336 0 (0, 0)
	338 checkcast (0, 0)
	339 org/apache/commons/math3/RealFieldElement (0, 0)
	341 aastore (0, 0)
	342 aload_2 (0, 0)
	343 iconst_4 (0, 0)
	344 aaload (0, 0)
	345 iconst_1 (0, 0)
	346 aload_1 (0, 0)
	347 bipush (0, 0)
	348 -40 (0, 0)
	349 invokeinterface (0, 0)
	350 org/apache/commons/math3/RealFieldElement.org/apache/commons/math3/ode/nonstiff/LutherFieldStepInterpolator (0, 0)
	352 0 (0, 0)
	354 checkcast (0, 0)
	355 org/apache/commons/math3/RealFieldElement (0, 0)
	357 ldc2_w (0, 0)
	358 -280.0 (0, 0)
	360 invokeinterface (0, 0)
	361 org/apache/commons/math3/RealFieldElement.sqrt:()Ljava/lang/Object; (0, 0)
	363 0 (0, 0)
	365 checkcast (0, 0)
	366 org/apache/commons/math3/RealFieldElement (0, 0)
	368 ldc2_w (0, 0)
	369 1960.0 (0, 0)
	371 invokeinterface (0, 0)
	372 org/apache/commons/math3/RealFieldElement.buildArray:(Lorg/apache/commons/math3/Field;II)[[Ljava/lang/Object; (0, 0)
	374 0 (0, 0)
	376 checkcast (0, 0)
	377 org/apache/commons/math3/RealFieldElement (0, 0)
	379 aastore (0, 0)
	380 aload_2 (0, 0)
	381 iconst_4 (0, 0)
	382 aaload (0, 0)
	383 iconst_2 (0, 0)
	384 aload_1 (0, 0)
	385 sipush (0, 0)
	386 -320 (0, 0)
	388 invokeinterface (0, 0)
	389 org/apache/commons/math3/RealFieldElement.org/apache/commons/math3/ode/nonstiff/LutherFieldStepInterpolator (0, 0)
	391 0 (0, 0)
	393 checkcast (0, 0)
	394 org/apache/commons/math3/RealFieldElement (0, 0)
	396 ldc2_w (0, 0)
	397 1960.0 (0, 0)
	399 invokeinterface (0, 0)
	400 org/apache/commons/math3/RealFieldElement.buildArray:(Lorg/apache/commons/math3/Field;II)[[Ljava/lang/Object; (0, 0)
	402 0 (0, 0)
	404 checkcast (0, 0)
	405 org/apache/commons/math3/RealFieldElement (0, 0)
	407 aastore (0, 0)
	408 aload_2 (0, 0)
	409 iconst_4 (0, 0)
	410 aaload (0, 0)
	411 iconst_3 (0, 0)
	412 aload_1 (0, 0)
	413 sipush (0, 0)
	414 363 (0, 0)
	416 invokeinterface (0, 0)
	417 org/apache/commons/math3/RealFieldElement.org/apache/commons/math3/ode/nonstiff/LutherFieldStepInterpolator (0, 0)
	419 0 (0, 0)
	421 checkcast (0, 0)
	422 org/apache/commons/math3/RealFieldElement (0, 0)
	424 ldc2_w (0, 0)
	425 63.0 (0, 0)
	427 invokeinterface (0, 0)
	428 org/apache/commons/math3/RealFieldElement.sqrt:()Ljava/lang/Object; (0, 0)
	430 0 (0, 0)
	432 checkcast (0, 0)
	433 org/apache/commons/math3/RealFieldElement (0, 0)
	435 ldc2_w (0, 0)
	436 1960.0 (0, 0)
	438 invokeinterface (0, 0)
	439 org/apache/commons/math3/RealFieldElement.buildArray:(Lorg/apache/commons/math3/Field;II)[[Ljava/lang/Object; (0, 0)
	441 0 (0, 0)
	443 checkcast (0, 0)
	444 org/apache/commons/math3/RealFieldElement (0, 0)
	446 aastore (0, 0)
	447 aload_2 (0, 0)
	448 iconst_4 (0, 0)
	449 aaload (0, 0)
	450 iconst_4 (0, 0)
	451 aload_1 (0, 0)
	452 sipush (0, 0)
	453 392 (0, 0)
	455 invokeinterface (0, 0)
	456 org/apache/commons/math3/RealFieldElement.org/apache/commons/math3/ode/nonstiff/LutherFieldStepInterpolator (0, 0)
	458 0 (0, 0)
	460 checkcast (0, 0)
	461 org/apache/commons/math3/RealFieldElement (0, 0)
	463 ldc2_w (0, 0)
	464 2352.0 (0, 0)
	466 invokeinterface (0, 0)
	467 org/apache/commons/math3/RealFieldElement.sqrt:()Ljava/lang/Object; (0, 0)
	469 0 (0, 0)
	471 checkcast (0, 0)
	472 org/apache/commons/math3/RealFieldElement (0, 0)
	474 ldc2_w (0, 0)
	475 1960.0 (0, 0)
	477 invokeinterface (0, 0)
	478 org/apache/commons/math3/RealFieldElement.buildArray:(Lorg/apache/commons/math3/Field;II)[[Ljava/lang/Object; (0, 0)
	480 0 (0, 0)
	482 checkcast (0, 0)
	483 org/apache/commons/math3/RealFieldElement (0, 0)
	485 aastore (0, 0)
	486 aload_2 (0, 0)
	487 iconst_5 (0, 0)
	488 aaload (0, 0)
	489 iconst_0 (0, 0)
	490 aload_1 (0, 0)
	491 bipush (0, 0)
	492 105 (0, 0)
	493 invokeinterface (0, 0)
	494 org/apache/commons/math3/RealFieldElement.org/apache/commons/math3/ode/nonstiff/LutherFieldStepInterpolator (0, 0)
	496 0 (0, 0)
	498 checkcast (0, 0)
	499 org/apache/commons/math3/RealFieldElement (0, 0)
	501 ldc2_w (0, 0)
	502 330.0 (0, 0)
	504 invokeinterface (0, 0)
	505 org/apache/commons/math3/RealFieldElement.sqrt:()Ljava/lang/Object; (0, 0)
	507 0 (0, 0)
	509 checkcast (0, 0)
	510 org/apache/commons/math3/RealFieldElement (0, 0)
	512 ldc2_w (0, 0)
	513 180.0 (0, 0)
	515 invokeinterface (0, 0)
	516 org/apache/commons/math3/RealFieldElement.buildArray:(Lorg/apache/commons/math3/Field;II)[[Ljava/lang/Object; (0, 0)
	518 0 (0, 0)
	520 checkcast (0, 0)
	521 org/apache/commons/math3/RealFieldElement (0, 0)
	523 aastore (0, 0)
	524 aload_2 (0, 0)
	525 iconst_5 (0, 0)
	526 aaload (0, 0)
	527 iconst_1 (0, 0)
	528 aload_0 (0, 0)
	529 iconst_2 (0, 0)
	530 iconst_3 (0, 0)
	531 invokevirtual (0, 0)
	532 org/apache/commons/math3/ode/nonstiff/LutherFieldIntegrator.fraction:(II)Lorg/apache/commons/math3/RealFieldElement; (0, 0)
	534 aastore (0, 0)
	535 aload_2 (0, 0)
	536 iconst_5 (0, 0)
	537 aaload (0, 0)
	538 iconst_2 (0, 0)
	539 aload_1 (0, 0)
	540 sipush (0, 0)
	541 280 (0, 0)
	543 invokeinterface (0, 0)
	544 org/apache/commons/math3/RealFieldElement.org/apache/commons/math3/ode/nonstiff/LutherFieldStepInterpolator (0, 0)
	546 0 (0, 0)
	548 checkcast (0, 0)
	549 org/apache/commons/math3/RealFieldElement (0, 0)
	551 ldc2_w (0, 0)
	552 -200.0 (0, 0)
	554 invokeinterface (0, 0)
	555 org/apache/commons/math3/RealFieldElement.sqrt:()Ljava/lang/Object; (0, 0)
	557 0 (0, 0)
	559 checkcast (0, 0)
	560 org/apache/commons/math3/RealFieldElement (0, 0)
	562 ldc2_w (0, 0)
	563 180.0 (0, 0)
	565 invokeinterface (0, 0)
	566 org/apache/commons/math3/RealFieldElement.buildArray:(Lorg/apache/commons/math3/Field;II)[[Ljava/lang/Object; (0, 0)
	568 0 (0, 0)
	570 checkcast (0, 0)
	571 org/apache/commons/math3/RealFieldElement (0, 0)
	573 aastore (0, 0)
	574 aload_2 (0, 0)
	575 iconst_5 (0, 0)
	576 aaload (0, 0)
	577 iconst_3 (0, 0)
	578 aload_1 (0, 0)
	579 sipush (0, 0)
	580 -189 (0, 0)
	582 invokeinterface (0, 0)
	583 org/apache/commons/math3/RealFieldElement.org/apache/commons/math3/ode/nonstiff/LutherFieldStepInterpolator (0, 0)
	585 0 (0, 0)
	587 checkcast (0, 0)
	588 org/apache/commons/math3/RealFieldElement (0, 0)
	590 ldc2_w (0, 0)
	591 126.0 (0, 0)
	593 invokeinterface (0, 0)
	594 org/apache/commons/math3/RealFieldElement.sqrt:()Ljava/lang/Object; (0, 0)
	596 0 (0, 0)
	598 checkcast (0, 0)
	599 org/apache/commons/math3/RealFieldElement (0, 0)
	601 ldc2_w (0, 0)
	602 180.0 (0, 0)
	604 invokeinterface (0, 0)
	605 org/apache/commons/math3/RealFieldElement.buildArray:(Lorg/apache/commons/math3/Field;II)[[Ljava/lang/Object; (0, 0)
	607 0 (0, 0)
	609 checkcast (0, 0)
	610 org/apache/commons/math3/RealFieldElement (0, 0)
	612 aastore (0, 0)
	613 aload_2 (0, 0)
	614 iconst_5 (0, 0)
	615 aaload (0, 0)
	616 iconst_4 (0, 0)
	617 aload_1 (0, 0)
	618 bipush (0, 0)
	619 -126 (0, 0)
	620 invokeinterface (0, 0)
	621 org/apache/commons/math3/RealFieldElement.org/apache/commons/math3/ode/nonstiff/LutherFieldStepInterpolator (0, 0)
	623 0 (0, 0)
	625 checkcast (0, 0)
	626 org/apache/commons/math3/RealFieldElement (0, 0)
	628 ldc2_w (0, 0)
	629 -686.0 (0, 0)
	631 invokeinterface (0, 0)
	632 org/apache/commons/math3/RealFieldElement.sqrt:()Ljava/lang/Object; (0, 0)
	634 0 (0, 0)
	636 checkcast (0, 0)
	637 org/apache/commons/math3/RealFieldElement (0, 0)
	639 ldc2_w (0, 0)
	640 180.0 (0, 0)
	642 invokeinterface (0, 0)
	643 org/apache/commons/math3/RealFieldElement.buildArray:(Lorg/apache/commons/math3/Field;II)[[Ljava/lang/Object; (0, 0)
	645 0 (0, 0)
	647 checkcast (0, 0)
	648 org/apache/commons/math3/RealFieldElement (0, 0)
	650 aastore (0, 0)
	651 aload_2 (0, 0)
	652 iconst_5 (0, 0)
	653 aaload (0, 0)
	654 iconst_5 (0, 0)
	655 aload_1 (0, 0)
	656 bipush (0, 0)
	657 -70 (0, 0)
	658 invokeinterface (0, 0)
	659 org/apache/commons/math3/RealFieldElement.org/apache/commons/math3/ode/nonstiff/LutherFieldStepInterpolator (0, 0)
	661 0 (0, 0)
	663 checkcast (0, 0)
	664 org/apache/commons/math3/RealFieldElement (0, 0)
	666 ldc2_w (0, 0)
	667 490.0 (0, 0)
	669 invokeinterface (0, 0)
	670 org/apache/commons/math3/RealFieldElement.sqrt:()Ljava/lang/Object; (0, 0)
	672 0 (0, 0)
	674 checkcast (0, 0)
	675 org/apache/commons/math3/RealFieldElement (0, 0)
	677 ldc2_w (0, 0)
	678 180.0 (0, 0)
	680 invokeinterface (0, 0)
	681 org/apache/commons/math3/RealFieldElement.buildArray:(Lorg/apache/commons/math3/Field;II)[[Ljava/lang/Object; (0, 0)
	683 0 (0, 0)
	685 checkcast (0, 0)
	686 org/apache/commons/math3/RealFieldElement (0, 0)
	688 aastore (0, 0)
	689 aload_2 (0, 0)
	690 areturn (0, 0)

Method: getB
	0 aload_0 (0, 0)
	1 invokevirtual (0, 0)
	2 org/apache/commons/math3/ode/nonstiff/LutherFieldIntegrator.getField:()Lorg/apache/commons/math3/Field; (0, 0)
	4 bipush (0, 0)
	5 7 (0, 0)
	6 invokestatic (0, 0)
	7 org/apache/commons/math3/util/MathArrays.buildArray:(Lorg/apache/commons/math3/Field;I)[Ljava/lang/Object; (0, 0)
	9 checkcast (0, 0)
	10 [Lorg/apache/commons/math3/RealFieldElement; (0, 0)
	12 astore_1 (0, 0)
	13 aload_1 (0, 0)
	14 iconst_0 (0, 0)
	15 aload_0 (0, 0)
	16 iconst_1 (0, 0)
	17 bipush (0, 0)
	18 20 (0, 0)
	19 invokevirtual (0, 0)
	20 org/apache/commons/math3/ode/nonstiff/LutherFieldIntegrator.fraction:(II)Lorg/apache/commons/math3/RealFieldElement; (0, 0)
	22 aastore (0, 0)
	23 aload_1 (0, 0)
	24 iconst_1 (0, 0)
	25 aload_0 (0, 0)
	26 invokevirtual (0, 0)
	27 org/apache/commons/math3/ode/nonstiff/LutherFieldIntegrator.getField:()Lorg/apache/commons/math3/Field; (0, 0)
	29 invokeinterface (0, 0)
	30 org/apache/commons/math3/Field.org/apache/commons/math3/RealFieldElement (0, 0)
	32 0 (0, 0)
	34 checkcast (0, 0)
	35 org/apache/commons/math3/RealFieldElement (0, 0)
	37 aastore (0, 0)
	38 aload_1 (0, 0)
	39 iconst_2 (0, 0)
	40 aload_0 (0, 0)
	41 bipush (0, 0)
	42 16 (0, 0)
	43 bipush (0, 0)
	44 45 (0, 0)
	45 invokevirtual (0, 0)
	46 org/apache/commons/math3/ode/nonstiff/LutherFieldIntegrator.fraction:(II)Lorg/apache/commons/math3/RealFieldElement; (0, 0)
	48 aastore (0, 0)
	49 aload_1 (0, 0)
	50 iconst_3 (0, 0)
	51 aload_0 (0, 0)
	52 invokevirtual (0, 0)
	53 org/apache/commons/math3/ode/nonstiff/LutherFieldIntegrator.getField:()Lorg/apache/commons/math3/Field; (0, 0)
	55 invokeinterface (0, 0)
	56 org/apache/commons/math3/Field.org/apache/commons/math3/RealFieldElement (0, 0)
	58 0 (0, 0)
	60 checkcast (0, 0)
	61 org/apache/commons/math3/RealFieldElement (0, 0)
	63 aastore (0, 0)
	64 aload_1 (0, 0)
	65 iconst_4 (0, 0)
	66 aload_0 (0, 0)
	67 bipush (0, 0)
	68 49 (0, 0)
	69 sipush (0, 0)
	70 180 (0, 0)
	72 invokevirtual (0, 0)
	73 org/apache/commons/math3/ode/nonstiff/LutherFieldIntegrator.fraction:(II)Lorg/apache/commons/math3/RealFieldElement; (0, 0)
	75 aastore (0, 0)
	76 aload_1 (0, 0)
	77 iconst_5 (0, 0)
	78 aload_1 (0, 0)
	79 iconst_4 (0, 0)
	80 aaload (0, 0)
	81 aastore (0, 0)
	82 aload_1 (0, 0)
	83 bipush (0, 0)
	84 6 (0, 0)
	85 aload_1 (0, 0)
	86 iconst_0 (0, 0)
	87 aaload (0, 0)
	88 aastore (0, 0)
	89 aload_1 (0, 0)
	90 areturn (0, 0)

Method: createInterpolator
	0 aload_0 (0, 0)
	1 iload_1 (0, 0)
	2 aload_2 (0, 0)
	3 aload_3 (0, 0)
	4 aload (0, 0)
	5 #4 (0, 0)
	6 aload (0, 0)
	7 #5 (0, 0)
	8 invokevirtual (0, 0)
	9 org/apache/commons/math3/ode/nonstiff/LutherFieldIntegrator.createInterpolator:(Z[[Lorg/apache/commons/math3/RealFieldElement;Lorg/apache/commons/math3/ode/FieldODEStateAndDerivative;Lorg/apache/commons/math3/ode/FieldODEStateAndDerivative;Lorg/apache/commons/math3/ode/FieldEquationsMapper;)Lorg/apache/commons/math3/ode/nonstiff/LutherFieldStepInterpolator; (0, 0)
	11 areturn (0, 0)

