Method: <init>
	0 aload_0 (0, 0)
	1 ldc (0, 0)
	2 Luther (0, 0)
	3 getstatic (0, 0)
	4 org/apache/commons/math3/ode/nonstiff/LutherIntegrator.STATIC_C:[D (0, 0)
	6 getstatic (0, 0)
	7 org/apache/commons/math3/ode/nonstiff/LutherIntegrator.STATIC_A:[[D (0, 0)
	9 getstatic (0, 0)
	10 org/apache/commons/math3/ode/nonstiff/LutherIntegrator.STATIC_B:[D (0, 0)
	12 new (0, 0)
	13 org/apache/commons/math3/ode/nonstiff/LutherStepInterpolator (0, 0)
	15 dup (0, 0)
	16 invokespecial (0, 0)
	17 org/apache/commons/math3/ode/nonstiff/LutherStepInterpolator.<init>:()V (0, 0)
	19 dload_1 (0, 0)
	20 invokespecial (0, 0)
	21 org/apache/commons/math3/ode/nonstiff/RungeKuttaIntegrator.<init>:(Ljava/lang/String;[D[[D[DLorg/apache/commons/math3/ode/nonstiff/RungeKuttaStepInterpolator;D)V (0, 0)
	23 return (0, 0)

Method: <clinit>
	0 ldc2_w (0, 0)
	1 21.0 (0, 0)
	3 invokestatic (0, 0)
	4 org/apache/commons/math3/util/FastMath.sqrt:(D)D (0, 0)
	6 putstatic (0, 0)
	7 org/apache/commons/math3/ode/nonstiff/LutherIntegrator.Q:D (0, 0)
	9 bipush (0, 0)
	10 6 (0, 0)
	11 newarray (0, 0)
	12 7 (0, 0)
	13 dup (0, 0)
	14 iconst_0 (0, 0)
	15 dconst_1 (0, 0)
	16 dastore (0, 0)
	17 dup (0, 0)
	18 iconst_1 (0, 0)
	19 ldc2_w (0, 0)
	20 0.5 (0, 0)
	22 dastore (0, 0)
	23 dup (0, 0)
	24 iconst_2 (0, 0)
	25 ldc2_w (0, 0)
	26 0.6666666666666666 (0, 0)
	28 dastore (0, 0)
	29 dup (0, 0)
	30 iconst_3 (0, 0)
	31 ldc2_w (0, 0)
	32 7.0 (0, 0)
	34 getstatic (0, 0)
	35 org/apache/commons/math3/ode/nonstiff/LutherIntegrator.Q:D (0, 0)
	37 dsub (0, 0)
	38 ldc2_w (0, 0)
	39 14.0 (0, 0)
	41 ddiv (0, 0)
	42 dastore (0, 0)
	43 dup (0, 0)
	44 iconst_4 (0, 0)
	45 ldc2_w (0, 0)
	46 7.0 (0, 0)
	48 getstatic (0, 0)
	49 org/apache/commons/math3/ode/nonstiff/LutherIntegrator.Q:D (0, 0)
	51 dadd (0, 0)
	52 ldc2_w (0, 0)
	53 14.0 (0, 0)
	55 ddiv (0, 0)
	56 dastore (0, 0)
	57 dup (0, 0)
	58 iconst_5 (0, 0)
	59 dconst_1 (0, 0)
	60 dastore (0, 0)
	61 putstatic (0, 0)
	62 org/apache/commons/math3/ode/nonstiff/LutherIntegrator.STATIC_C:[D (0, 0)
	64 bipush (0, 0)
	65 6 (0, 0)
	66 anewarray (0, 0)
	67 [D (0, 0)
	69 dup (0, 0)
	70 iconst_0 (0, 0)
	71 iconst_1 (0, 0)
	72 newarray (0, 0)
	73 7 (0, 0)
	74 dup (0, 0)
	75 iconst_0 (0, 0)
	76 dconst_1 (0, 0)
	77 dastore (0, 0)
	78 aastore (0, 0)
	79 dup (0, 0)
	80 iconst_1 (0, 0)
	81 iconst_2 (0, 0)
	82 newarray (0, 0)
	83 7 (0, 0)
	84 dup (0, 0)
	85 iconst_0 (0, 0)
	86 ldc2_w (0, 0)
	87 0.375 (0, 0)
	89 dastore (0, 0)
	90 dup (0, 0)
	91 iconst_1 (0, 0)
	92 ldc2_w (0, 0)
	93 0.125 (0, 0)
	95 dastore (0, 0)
	96 aastore (0, 0)
	97 dup (0, 0)
	98 iconst_2 (0, 0)
	99 iconst_3 (0, 0)
	100 newarray (0, 0)
	101 7 (0, 0)
	102 dup (0, 0)
	103 iconst_0 (0, 0)
	104 ldc2_w (0, 0)
	105 0.2962962962962963 (0, 0)
	107 dastore (0, 0)
	108 dup (0, 0)
	109 iconst_1 (0, 0)
	110 ldc2_w (0, 0)
	111 0.07407407407407407 (0, 0)
	113 dastore (0, 0)
	114 dup (0, 0)
	115 iconst_2 (0, 0)
	116 ldc2_w (0, 0)
	117 0.2962962962962963 (0, 0)
	119 dastore (0, 0)
	120 aastore (0, 0)
	121 dup (0, 0)
	122 iconst_3 (0, 0)
	123 iconst_4 (0, 0)
	124 newarray (0, 0)
	125 7 (0, 0)
	126 dup (0, 0)
	127 iconst_0 (0, 0)
	128 ldc2_w (0, 0)
	129 -21.0 (0, 0)
	131 ldc2_w (0, 0)
	132 9.0 (0, 0)
	134 getstatic (0, 0)
	135 org/apache/commons/math3/ode/nonstiff/LutherIntegrator.Q:D (0, 0)
	137 dmul (0, 0)
	138 dadd (0, 0)
	139 ldc2_w (0, 0)
	140 392.0 (0, 0)
	142 ddiv (0, 0)
	143 dastore (0, 0)
	144 dup (0, 0)
	145 iconst_1 (0, 0)
	146 ldc2_w (0, 0)
	147 -56.0 (0, 0)
	149 ldc2_w (0, 0)
	150 8.0 (0, 0)
	152 getstatic (0, 0)
	153 org/apache/commons/math3/ode/nonstiff/LutherIntegrator.Q:D (0, 0)
	155 dmul (0, 0)
	156 dadd (0, 0)
	157 ldc2_w (0, 0)
	158 392.0 (0, 0)
	160 ddiv (0, 0)
	161 dastore (0, 0)
	162 dup (0, 0)
	163 iconst_2 (0, 0)
	164 ldc2_w (0, 0)
	165 336.0 (0, 0)
	167 ldc2_w (0, 0)
	168 48.0 (0, 0)
	170 getstatic (0, 0)
	171 org/apache/commons/math3/ode/nonstiff/LutherIntegrator.Q:D (0, 0)
	173 dmul (0, 0)
	174 dsub (0, 0)
	175 ldc2_w (0, 0)
	176 392.0 (0, 0)
	178 ddiv (0, 0)
	179 dastore (0, 0)
	180 dup (0, 0)
	181 iconst_3 (0, 0)
	182 ldc2_w (0, 0)
	183 -63.0 (0, 0)
	185 ldc2_w (0, 0)
	186 3.0 (0, 0)
	188 getstatic (0, 0)
	189 org/apache/commons/math3/ode/nonstiff/LutherIntegrator.Q:D (0, 0)
	191 dmul (0, 0)
	192 dadd (0, 0)
	193 ldc2_w (0, 0)
	194 392.0 (0, 0)
	196 ddiv (0, 0)
	197 dastore (0, 0)
	198 aastore (0, 0)
	199 dup (0, 0)
	200 iconst_4 (0, 0)
	201 iconst_5 (0, 0)
	202 newarray (0, 0)
	203 7 (0, 0)
	204 dup (0, 0)
	205 iconst_0 (0, 0)
	206 ldc2_w (0, 0)
	207 -1155.0 (0, 0)
	209 ldc2_w (0, 0)
	210 255.0 (0, 0)
	212 getstatic (0, 0)
	213 org/apache/commons/math3/ode/nonstiff/LutherIntegrator.Q:D (0, 0)
	215 dmul (0, 0)
	216 dsub (0, 0)
	217 ldc2_w (0, 0)
	218 1960.0 (0, 0)
	220 ddiv (0, 0)
	221 dastore (0, 0)
	222 dup (0, 0)
	223 iconst_1 (0, 0)
	224 ldc2_w (0, 0)
	225 -280.0 (0, 0)
	227 ldc2_w (0, 0)
	228 40.0 (0, 0)
	230 getstatic (0, 0)
	231 org/apache/commons/math3/ode/nonstiff/LutherIntegrator.Q:D (0, 0)
	233 dmul (0, 0)
	234 dsub (0, 0)
	235 ldc2_w (0, 0)
	236 1960.0 (0, 0)
	238 ddiv (0, 0)
	239 dastore (0, 0)
	240 dup (0, 0)
	241 iconst_2 (0, 0)
	242 dconst_0 (0, 0)
	243 ldc2_w (0, 0)
	244 320.0 (0, 0)
	246 getstatic (0, 0)
	247 org/apache/commons/math3/ode/nonstiff/LutherIntegrator.Q:D (0, 0)
	249 dmul (0, 0)
	250 dsub (0, 0)
	251 ldc2_w (0, 0)
	252 1960.0 (0, 0)
	254 ddiv (0, 0)
	255 dastore (0, 0)
	256 dup (0, 0)
	257 iconst_3 (0, 0)
	258 ldc2_w (0, 0)
	259 63.0 (0, 0)
	261 ldc2_w (0, 0)
	262 363.0 (0, 0)
	264 getstatic (0, 0)
	265 org/apache/commons/math3/ode/nonstiff/LutherIntegrator.Q:D (0, 0)
	267 dmul (0, 0)
	268 dadd (0, 0)
	269 ldc2_w (0, 0)
	270 1960.0 (0, 0)
	272 ddiv (0, 0)
	273 dastore (0, 0)
	274 dup (0, 0)
	275 iconst_4 (0, 0)
	276 ldc2_w (0, 0)
	277 2352.0 (0, 0)
	279 ldc2_w (0, 0)
	280 392.0 (0, 0)
	282 getstatic (0, 0)
	283 org/apache/commons/math3/ode/nonstiff/LutherIntegrator.Q:D (0, 0)
	285 dmul (0, 0)
	286 dadd (0, 0)
	287 ldc2_w (0, 0)
	288 1960.0 (0, 0)
	290 ddiv (0, 0)
	291 dastore (0, 0)
	292 aastore (0, 0)
	293 dup (0, 0)
	294 iconst_5 (0, 0)
	295 bipush (0, 0)
	296 6 (0, 0)
	297 newarray (0, 0)
	298 7 (0, 0)
	299 dup (0, 0)
	300 iconst_0 (0, 0)
	301 ldc2_w (0, 0)
	302 330.0 (0, 0)
	304 ldc2_w (0, 0)
	305 105.0 (0, 0)
	307 getstatic (0, 0)
	308 org/apache/commons/math3/ode/nonstiff/LutherIntegrator.Q:D (0, 0)
	310 dmul (0, 0)
	311 dadd (0, 0)
	312 ldc2_w (0, 0)
	313 180.0 (0, 0)
	315 ddiv (0, 0)
	316 dastore (0, 0)
	317 dup (0, 0)
	318 iconst_1 (0, 0)
	319 ldc2_w (0, 0)
	320 120.0 (0, 0)
	322 dconst_0 (0, 0)
	323 getstatic (0, 0)
	324 org/apache/commons/math3/ode/nonstiff/LutherIntegrator.Q:D (0, 0)
	326 dmul (0, 0)
	327 dadd (0, 0)
	328 ldc2_w (0, 0)
	329 180.0 (0, 0)
	331 ddiv (0, 0)
	332 dastore (0, 0)
	333 dup (0, 0)
	334 iconst_2 (0, 0)
	335 ldc2_w (0, 0)
	336 -200.0 (0, 0)
	338 ldc2_w (0, 0)
	339 280.0 (0, 0)
	341 getstatic (0, 0)
	342 org/apache/commons/math3/ode/nonstiff/LutherIntegrator.Q:D (0, 0)
	344 dmul (0, 0)
	345 dadd (0, 0)
	346 ldc2_w (0, 0)
	347 180.0 (0, 0)
	349 ddiv (0, 0)
	350 dastore (0, 0)
	351 dup (0, 0)
	352 iconst_3 (0, 0)
	353 ldc2_w (0, 0)
	354 126.0 (0, 0)
	356 ldc2_w (0, 0)
	357 189.0 (0, 0)
	359 getstatic (0, 0)
	360 org/apache/commons/math3/ode/nonstiff/LutherIntegrator.Q:D (0, 0)
	362 dmul (0, 0)
	363 dsub (0, 0)
	364 ldc2_w (0, 0)
	365 180.0 (0, 0)
	367 ddiv (0, 0)
	368 dastore (0, 0)
	369 dup (0, 0)
	370 iconst_4 (0, 0)
	371 ldc2_w (0, 0)
	372 -686.0 (0, 0)
	374 ldc2_w (0, 0)
	375 126.0 (0, 0)
	377 getstatic (0, 0)
	378 org/apache/commons/math3/ode/nonstiff/LutherIntegrator.Q:D (0, 0)
	380 dmul (0, 0)
	381 dsub (0, 0)
	382 ldc2_w (0, 0)
	383 180.0 (0, 0)
	385 ddiv (0, 0)
	386 dastore (0, 0)
	387 dup (0, 0)
	388 iconst_5 (0, 0)
	389 ldc2_w (0, 0)
	390 490.0 (0, 0)
	392 ldc2_w (0, 0)
	393 70.0 (0, 0)
	395 getstatic (0, 0)
	396 org/apache/commons/math3/ode/nonstiff/LutherIntegrator.Q:D (0, 0)
	398 dmul (0, 0)
	399 dsub (0, 0)
	400 ldc2_w (0, 0)
	401 180.0 (0, 0)
	403 ddiv (0, 0)
	404 dastore (0, 0)
	405 aastore (0, 0)
	406 putstatic (0, 0)
	407 org/apache/commons/math3/ode/nonstiff/LutherIntegrator.STATIC_A:[[D (0, 0)
	409 bipush (0, 0)
	410 7 (0, 0)
	411 newarray (0, 0)
	412 7 (0, 0)
	413 dup (0, 0)
	414 iconst_0 (0, 0)
	415 ldc2_w (0, 0)
	416 0.05 (0, 0)
	418 dastore (0, 0)
	419 dup (0, 0)
	420 iconst_1 (0, 0)
	421 dconst_0 (0, 0)
	422 dastore (0, 0)
	423 dup (0, 0)
	424 iconst_2 (0, 0)
	425 ldc2_w (0, 0)
	426 0.35555555555555557 (0, 0)
	428 dastore (0, 0)
	429 dup (0, 0)
	430 iconst_3 (0, 0)
	431 dconst_0 (0, 0)
	432 dastore (0, 0)
	433 dup (0, 0)
	434 iconst_4 (0, 0)
	435 ldc2_w (0, 0)
	436 0.2722222222222222 (0, 0)
	438 dastore (0, 0)
	439 dup (0, 0)
	440 iconst_5 (0, 0)
	441 ldc2_w (0, 0)
	442 0.2722222222222222 (0, 0)
	444 dastore (0, 0)
	445 dup (0, 0)
	446 bipush (0, 0)
	447 6 (0, 0)
	448 ldc2_w (0, 0)
	449 0.05 (0, 0)
	451 dastore (0, 0)
	452 putstatic (0, 0)
	453 org/apache/commons/math3/ode/nonstiff/LutherIntegrator.STATIC_B:[D (0, 0)
	455 return (0, 0)

