Method: <init>
	0 aload_0 (0, 4)
	1 aload_1 (0, 4)
	2 iload_2 (0, 4)
	3 aload_3 (0, 4)
	4 aload (0, 4)
	5 #4 (0, 4)
	6 aload (0, 4)
	7 #5 (0, 4)
	8 aload (0, 4)
	9 #6 (0, 4)
	10 aload (0, 4)
	11 #7 (0, 4)
	12 aload (0, 4)
	13 #8 (0, 4)
	14 invokespecial (0, 4)
	15 org/apache/commons/math3/ode/nonstiff/RungeKuttaFieldStepInterpolator.<init>:(Lorg/apache/commons/math3/Field;Z[[Lorg/apache/commons/math3/RealFieldElement;Lorg/apache/commons/math3/ode/FieldODEStateAndDerivative;Lorg/apache/commons/math3/ode/FieldODEStateAndDerivative;Lorg/apache/commons/math3/ode/FieldODEStateAndDerivative;Lorg/apache/commons/math3/ode/FieldODEStateAndDerivative;Lorg/apache/commons/math3/ode/FieldEquationsMapper;)V (0, 4)
	17 aload_1 (0, 4)
	18 invokeinterface (0, 4)
	19 org/apache/commons/math3/Field.org/apache/commons/math3/RealFieldElement (0, 4)
	21 0 (0, 4)
	23 checkcast (0, 4)
	24 org/apache/commons/math3/RealFieldElement (0, 4)
	26 ldc2_w (0, 4)
	27 21.0 (0, 4)
	29 invokeinterface (0, 4)
	30 org/apache/commons/math3/RealFieldElement.sqrt:()Ljava/lang/Object; (0, 4)
	32 0 (0, 4)
	34 checkcast (0, 4)
	35 org/apache/commons/math3/RealFieldElement (0, 4)
	37 invokeinterface (0, 4)
	38 org/apache/commons/math3/RealFieldElement.multiply:(I)Ljava/lang/Object; (0, 4)
	40 0 (0, 4)
	42 checkcast (0, 4)
	43 org/apache/commons/math3/RealFieldElement (0, 4)
	45 astore (0, 4)
	46 #9 (0, 4)
	47 aload_0 (0, 4)
	48 aload (0, 4)
	49 #9 (0, 4)
	50 bipush (0, 4)
	51 -49 (0, 4)
	52 invokeinterface (0, 4)
	53 org/apache/commons/math3/RealFieldElement.c5a:Lorg/apache/commons/math3/RealFieldElement; (0, 4)
	55 0 (0, 4)
	57 checkcast (0, 4)
	58 org/apache/commons/math3/RealFieldElement (0, 4)
	60 ldc2_w (0, 4)
	61 -49.0 (0, 4)
	63 invokeinterface (0, 4)
	64 org/apache/commons/math3/RealFieldElement.sqrt:()Ljava/lang/Object; (0, 4)
	66 0 (0, 4)
	68 checkcast (0, 4)
	69 org/apache/commons/math3/RealFieldElement (0, 4)
	71 putfield (0, 4)
	72 org/apache/commons/math3/ode/nonstiff/LutherFieldStepInterpolator.c5a:Lorg/apache/commons/math3/RealFieldElement; (0, 4)
	74 aload_0 (0, 4)
	75 aload (0, 4)
	76 #9 (0, 4)
	77 sipush (0, 4)
	78 287 (0, 4)
	80 invokeinterface (0, 4)
	81 org/apache/commons/math3/RealFieldElement.c5a:Lorg/apache/commons/math3/RealFieldElement; (0, 4)
	83 0 (0, 4)
	85 checkcast (0, 4)
	86 org/apache/commons/math3/RealFieldElement (0, 4)
	88 ldc2_w (0, 4)
	89 392.0 (0, 4)
	91 invokeinterface (0, 4)
	92 org/apache/commons/math3/RealFieldElement.sqrt:()Ljava/lang/Object; (0, 4)
	94 0 (0, 4)
	96 checkcast (0, 4)
	97 org/apache/commons/math3/RealFieldElement (0, 4)
	99 putfield (0, 4)
	100 org/apache/commons/math3/ode/nonstiff/LutherFieldStepInterpolator.c5b:Lorg/apache/commons/math3/RealFieldElement; (0, 4)
	102 aload_0 (0, 4)
	103 aload (0, 4)
	104 #9 (0, 4)
	105 sipush (0, 4)
	106 -357 (0, 4)
	108 invokeinterface (0, 4)
	109 org/apache/commons/math3/RealFieldElement.c5a:Lorg/apache/commons/math3/RealFieldElement; (0, 4)
	111 0 (0, 4)
	113 checkcast (0, 4)
	114 org/apache/commons/math3/RealFieldElement (0, 4)
	116 ldc2_w (0, 4)
	117 -637.0 (0, 4)
	119 invokeinterface (0, 4)
	120 org/apache/commons/math3/RealFieldElement.sqrt:()Ljava/lang/Object; (0, 4)
	122 0 (0, 4)
	124 checkcast (0, 4)
	125 org/apache/commons/math3/RealFieldElement (0, 4)
	127 putfield (0, 4)
	128 org/apache/commons/math3/ode/nonstiff/LutherFieldStepInterpolator.c5c:Lorg/apache/commons/math3/RealFieldElement; (0, 4)
	130 aload_0 (0, 4)
	131 aload (0, 4)
	132 #9 (0, 4)
	133 sipush (0, 4)
	134 343 (0, 4)
	136 invokeinterface (0, 4)
	137 org/apache/commons/math3/RealFieldElement.c5a:Lorg/apache/commons/math3/RealFieldElement; (0, 4)
	139 0 (0, 4)
	141 checkcast (0, 4)
	142 org/apache/commons/math3/RealFieldElement (0, 4)
	144 ldc2_w (0, 4)
	145 833.0 (0, 4)
	147 invokeinterface (0, 4)
	148 org/apache/commons/math3/RealFieldElement.sqrt:()Ljava/lang/Object; (0, 4)
	150 0 (0, 4)
	152 checkcast (0, 4)
	153 org/apache/commons/math3/RealFieldElement (0, 4)
	155 putfield (0, 4)
	156 org/apache/commons/math3/ode/nonstiff/LutherFieldStepInterpolator.c5d:Lorg/apache/commons/math3/RealFieldElement; (0, 4)
	158 aload_0 (0, 4)
	159 aload (0, 4)
	160 #9 (0, 4)
	161 bipush (0, 4)
	162 49 (0, 4)
	163 invokeinterface (0, 4)
	164 org/apache/commons/math3/RealFieldElement.c5a:Lorg/apache/commons/math3/RealFieldElement; (0, 4)
	166 0 (0, 4)
	168 checkcast (0, 4)
	169 org/apache/commons/math3/RealFieldElement (0, 4)
	171 ldc2_w (0, 4)
	172 -49.0 (0, 4)
	174 invokeinterface (0, 4)
	175 org/apache/commons/math3/RealFieldElement.sqrt:()Ljava/lang/Object; (0, 4)
	177 0 (0, 4)
	179 checkcast (0, 4)
	180 org/apache/commons/math3/RealFieldElement (0, 4)
	182 putfield (0, 4)
	183 org/apache/commons/math3/ode/nonstiff/LutherFieldStepInterpolator.c6a:Lorg/apache/commons/math3/RealFieldElement; (0, 4)
	185 aload_0 (0, 4)
	186 aload (0, 4)
	187 #9 (0, 4)
	188 sipush (0, 4)
	189 -287 (0, 4)
	191 invokeinterface (0, 4)
	192 org/apache/commons/math3/RealFieldElement.c5a:Lorg/apache/commons/math3/RealFieldElement; (0, 4)
	194 0 (0, 4)
	196 checkcast (0, 4)
	197 org/apache/commons/math3/RealFieldElement (0, 4)
	199 ldc2_w (0, 4)
	200 392.0 (0, 4)
	202 invokeinterface (0, 4)
	203 org/apache/commons/math3/RealFieldElement.sqrt:()Ljava/lang/Object; (0, 4)
	205 0 (0, 4)
	207 checkcast (0, 4)
	208 org/apache/commons/math3/RealFieldElement (0, 4)
	210 putfield (0, 4)
	211 org/apache/commons/math3/ode/nonstiff/LutherFieldStepInterpolator.c6b:Lorg/apache/commons/math3/RealFieldElement; (0, 4)
	213 aload_0 (0, 4)
	214 aload (0, 4)
	215 #9 (0, 4)
	216 sipush (0, 4)
	217 357 (0, 4)
	219 invokeinterface (0, 4)
	220 org/apache/commons/math3/RealFieldElement.c5a:Lorg/apache/commons/math3/RealFieldElement; (0, 4)
	222 0 (0, 4)
	224 checkcast (0, 4)
	225 org/apache/commons/math3/RealFieldElement (0, 4)
	227 ldc2_w (0, 4)
	228 -637.0 (0, 4)
	230 invokeinterface (0, 4)
	231 org/apache/commons/math3/RealFieldElement.sqrt:()Ljava/lang/Object; (0, 4)
	233 0 (0, 4)
	235 checkcast (0, 4)
	236 org/apache/commons/math3/RealFieldElement (0, 4)
	238 putfield (0, 4)
	239 org/apache/commons/math3/ode/nonstiff/LutherFieldStepInterpolator.c6c:Lorg/apache/commons/math3/RealFieldElement; (0, 4)
	241 aload_0 (0, 4)
	242 aload (0, 4)
	243 #9 (0, 4)
	244 sipush (0, 4)
	245 -343 (0, 4)
	247 invokeinterface (0, 4)
	248 org/apache/commons/math3/RealFieldElement.c5a:Lorg/apache/commons/math3/RealFieldElement; (0, 4)
	250 0 (0, 4)
	252 checkcast (0, 4)
	253 org/apache/commons/math3/RealFieldElement (0, 4)
	255 ldc2_w (0, 4)
	256 833.0 (0, 4)
	258 invokeinterface (0, 4)
	259 org/apache/commons/math3/RealFieldElement.sqrt:()Ljava/lang/Object; (0, 4)
	261 0 (0, 4)
	263 checkcast (0, 4)
	264 org/apache/commons/math3/RealFieldElement (0, 4)
	266 putfield (0, 4)
	267 org/apache/commons/math3/ode/nonstiff/LutherFieldStepInterpolator.c6d:Lorg/apache/commons/math3/RealFieldElement; (0, 4)
	269 aload_0 (0, 4)
	270 aload (0, 4)
	271 #9 (0, 4)
	272 bipush (0, 4)
	273 49 (0, 4)
	274 invokeinterface (0, 4)
	275 org/apache/commons/math3/RealFieldElement.c5a:Lorg/apache/commons/math3/RealFieldElement; (0, 4)
	277 0 (0, 4)
	279 checkcast (0, 4)
	280 org/apache/commons/math3/RealFieldElement (0, 4)
	282 ldc2_w (0, 4)
	283 49.0 (0, 4)
	285 invokeinterface (0, 4)
	286 org/apache/commons/math3/RealFieldElement.sqrt:()Ljava/lang/Object; (0, 4)
	288 0 (0, 4)
	290 checkcast (0, 4)
	291 org/apache/commons/math3/RealFieldElement (0, 4)
	293 putfield (0, 4)
	294 org/apache/commons/math3/ode/nonstiff/LutherFieldStepInterpolator.d5a:Lorg/apache/commons/math3/RealFieldElement; (0, 4)
	296 aload_0 (0, 4)
	297 aload (0, 4)
	298 #9 (0, 4)
	299 sipush (0, 4)
	300 -847 (0, 4)
	302 invokeinterface (0, 4)
	303 org/apache/commons/math3/RealFieldElement.c5a:Lorg/apache/commons/math3/RealFieldElement; (0, 4)
	305 0 (0, 4)
	307 checkcast (0, 4)
	308 org/apache/commons/math3/RealFieldElement (0, 4)
	310 ldc2_w (0, 4)
	311 -1372.0 (0, 4)
	313 invokeinterface (0, 4)
	314 org/apache/commons/math3/RealFieldElement.sqrt:()Ljava/lang/Object; (0, 4)
	316 0 (0, 4)
	318 checkcast (0, 4)
	319 org/apache/commons/math3/RealFieldElement (0, 4)
	321 putfield (0, 4)
	322 org/apache/commons/math3/ode/nonstiff/LutherFieldStepInterpolator.d5b:Lorg/apache/commons/math3/RealFieldElement; (0, 4)
	324 aload_0 (0, 4)
	325 aload (0, 4)
	326 #9 (0, 4)
	327 sipush (0, 4)
	328 1029 (0, 4)
	330 invokeinterface (0, 4)
	331 org/apache/commons/math3/RealFieldElement.c5a:Lorg/apache/commons/math3/RealFieldElement; (0, 4)
	333 0 (0, 4)
	335 checkcast (0, 4)
	336 org/apache/commons/math3/RealFieldElement (0, 4)
	338 ldc2_w (0, 4)
	339 2254.0 (0, 4)
	341 invokeinterface (0, 4)
	342 org/apache/commons/math3/RealFieldElement.sqrt:()Ljava/lang/Object; (0, 4)
	344 0 (0, 4)
	346 checkcast (0, 4)
	347 org/apache/commons/math3/RealFieldElement (0, 4)
	349 putfield (0, 4)
	350 org/apache/commons/math3/ode/nonstiff/LutherFieldStepInterpolator.d5c:Lorg/apache/commons/math3/RealFieldElement; (0, 4)
	352 aload_0 (0, 4)
	353 aload (0, 4)
	354 #9 (0, 4)
	355 bipush (0, 4)
	356 -49 (0, 4)
	357 invokeinterface (0, 4)
	358 org/apache/commons/math3/RealFieldElement.c5a:Lorg/apache/commons/math3/RealFieldElement; (0, 4)
	360 0 (0, 4)
	362 checkcast (0, 4)
	363 org/apache/commons/math3/RealFieldElement (0, 4)
	365 ldc2_w (0, 4)
	366 49.0 (0, 4)
	368 invokeinterface (0, 4)
	369 org/apache/commons/math3/RealFieldElement.sqrt:()Ljava/lang/Object; (0, 4)
	371 0 (0, 4)
	373 checkcast (0, 4)
	374 org/apache/commons/math3/RealFieldElement (0, 4)
	376 putfield (0, 4)
	377 org/apache/commons/math3/ode/nonstiff/LutherFieldStepInterpolator.d6a:Lorg/apache/commons/math3/RealFieldElement; (0, 4)
	379 aload_0 (0, 4)
	380 aload (0, 4)
	381 #9 (0, 4)
	382 sipush (0, 4)
	383 847 (0, 4)
	385 invokeinterface (0, 4)
	386 org/apache/commons/math3/RealFieldElement.c5a:Lorg/apache/commons/math3/RealFieldElement; (0, 4)
	388 0 (0, 4)
	390 checkcast (0, 4)
	391 org/apache/commons/math3/RealFieldElement (0, 4)
	393 ldc2_w (0, 4)
	394 -1372.0 (0, 4)
	396 invokeinterface (0, 4)
	397 org/apache/commons/math3/RealFieldElement.sqrt:()Ljava/lang/Object; (0, 4)
	399 0 (0, 4)
	401 checkcast (0, 4)
	402 org/apache/commons/math3/RealFieldElement (0, 4)
	404 putfield (0, 4)
	405 org/apache/commons/math3/ode/nonstiff/LutherFieldStepInterpolator.d6b:Lorg/apache/commons/math3/RealFieldElement; (0, 4)
	407 aload_0 (0, 4)
	408 aload (0, 4)
	409 #9 (0, 4)
	410 sipush (0, 4)
	411 -1029 (0, 4)
	413 invokeinterface (0, 4)
	414 org/apache/commons/math3/RealFieldElement.c5a:Lorg/apache/commons/math3/RealFieldElement; (0, 4)
	416 0 (0, 4)
	418 checkcast (0, 4)
	419 org/apache/commons/math3/RealFieldElement (0, 4)
	421 ldc2_w (0, 4)
	422 2254.0 (0, 4)
	424 invokeinterface (0, 4)
	425 org/apache/commons/math3/RealFieldElement.sqrt:()Ljava/lang/Object; (0, 4)
	427 0 (0, 4)
	429 checkcast (0, 4)
	430 org/apache/commons/math3/RealFieldElement (0, 4)
	432 putfield (0, 4)
	433 org/apache/commons/math3/ode/nonstiff/LutherFieldStepInterpolator.d6c:Lorg/apache/commons/math3/RealFieldElement; (0, 4)
	435 return (0, 4)

Method: create
	0 aload_0 (0, 0)
	1 aload_1 (0, 0)
	2 iload_2 (0, 0)
	3 aload_3 (0, 0)
	4 aload (0, 0)
	5 #4 (0, 0)
	6 aload (0, 0)
	7 #5 (0, 0)
	8 aload (0, 0)
	9 #6 (0, 0)
	10 aload (0, 0)
	11 #7 (0, 0)
	12 aload (0, 0)
	13 #8 (0, 0)
	14 invokevirtual (0, 0)
	15 org/apache/commons/math3/ode/nonstiff/LutherFieldStepInterpolator.create:(Lorg/apache/commons/math3/Field;Z[[Lorg/apache/commons/math3/RealFieldElement;Lorg/apache/commons/math3/ode/FieldODEStateAndDerivative;Lorg/apache/commons/math3/ode/FieldODEStateAndDerivative;Lorg/apache/commons/math3/ode/FieldODEStateAndDerivative;Lorg/apache/commons/math3/ode/FieldODEStateAndDerivative;Lorg/apache/commons/math3/ode/FieldEquationsMapper;)Lorg/apache/commons/math3/ode/nonstiff/LutherFieldStepInterpolator; (0, 0)
	17 areturn (0, 0)

Method: computeInterpolatedStateAndDerivatives
	0 aload_3 (0, 0)
	1 aload_3 (0, 0)
	2 aload_3 (0, 0)
	3 aload_3 (0, 0)
	4 bipush (0, 0)
	5 21 (0, 0)
	6 invokeinterface (0, 0)
	7 org/apache/commons/math3/RealFieldElement.c5a:Lorg/apache/commons/math3/RealFieldElement; (0, 0)
	9 0 (0, 0)
	11 checkcast (0, 0)
	12 org/apache/commons/math3/RealFieldElement (0, 0)
	14 ldc2_w (0, 0)
	15 -47.0 (0, 0)
	17 invokeinterface (0, 0)
	18 org/apache/commons/math3/RealFieldElement.sqrt:()Ljava/lang/Object; (0, 0)
	20 0 (0, 0)
	22 invokeinterface (0, 0)
	23 org/apache/commons/math3/RealFieldElement.getField:()Lorg/apache/commons/math3/Field; (0, 0)
	25 0 (0, 0)
	27 checkcast (0, 0)
	28 org/apache/commons/math3/RealFieldElement (0, 0)
	30 ldc2_w (0, 0)
	31 36.0 (0, 0)
	33 invokeinterface (0, 0)
	34 org/apache/commons/math3/RealFieldElement.sqrt:()Ljava/lang/Object; (0, 0)
	36 0 (0, 0)
	38 invokeinterface (0, 0)
	39 org/apache/commons/math3/RealFieldElement.getField:()Lorg/apache/commons/math3/Field; (0, 0)
	41 0 (0, 0)
	43 checkcast (0, 0)
	44 org/apache/commons/math3/RealFieldElement (0, 0)
	46 ldc2_w (0, 0)
	47 -10.8 (0, 0)
	49 invokeinterface (0, 0)
	50 org/apache/commons/math3/RealFieldElement.sqrt:()Ljava/lang/Object; (0, 0)
	52 0 (0, 0)
	54 invokeinterface (0, 0)
	55 org/apache/commons/math3/RealFieldElement.getField:()Lorg/apache/commons/math3/Field; (0, 0)
	57 0 (0, 0)
	59 checkcast (0, 0)
	60 org/apache/commons/math3/RealFieldElement (0, 0)
	62 dconst_1 (0, 0)
	63 invokeinterface (0, 0)
	64 org/apache/commons/math3/RealFieldElement.sqrt:()Ljava/lang/Object; (0, 0)
	66 0 (0, 0)
	68 checkcast (0, 0)
	69 org/apache/commons/math3/RealFieldElement (0, 0)
	71 astore (0, 0)
	72 #6 (0, 0)
	73 aload_2 (0, 0)
	74 invokeinterface (0, 0)
	75 org/apache/commons/math3/RealFieldElement.multiply:(D)Ljava/lang/Object; (0, 0)
	77 0 (0, 0)
	79 invokeinterface (0, 0)
	80 org/apache/commons/math3/Field.org/apache/commons/math3/RealFieldElement (0, 0)
	82 0 (0, 0)
	84 checkcast (0, 0)
	85 org/apache/commons/math3/RealFieldElement (0, 0)
	87 astore (0, 0)
	88 #7 (0, 0)
	89 aload_3 (0, 0)
	90 aload_3 (0, 0)
	91 aload_3 (0, 0)
	92 aload_3 (0, 0)
	93 bipush (0, 0)
	94 112 (0, 0)
	95 invokeinterface (0, 0)
	96 org/apache/commons/math3/RealFieldElement.c5a:Lorg/apache/commons/math3/RealFieldElement; (0, 0)
	98 0 (0, 0)
	100 checkcast (0, 0)
	101 org/apache/commons/math3/RealFieldElement (0, 0)
	103 ldc2_w (0, 0)
	104 -202.66666666666666 (0, 0)
	106 invokeinterface (0, 0)
	107 org/apache/commons/math3/RealFieldElement.sqrt:()Ljava/lang/Object; (0, 0)
	109 0 (0, 0)
	111 invokeinterface (0, 0)
	112 org/apache/commons/math3/RealFieldElement.getField:()Lorg/apache/commons/math3/Field; (0, 0)
	114 0 (0, 0)
	116 checkcast (0, 0)
	117 org/apache/commons/math3/RealFieldElement (0, 0)
	119 ldc2_w (0, 0)
	120 106.66666666666667 (0, 0)
	122 invokeinterface (0, 0)
	123 org/apache/commons/math3/RealFieldElement.sqrt:()Ljava/lang/Object; (0, 0)
	125 0 (0, 0)
	127 invokeinterface (0, 0)
	128 org/apache/commons/math3/RealFieldElement.getField:()Lorg/apache/commons/math3/Field; (0, 0)
	130 0 (0, 0)
	132 checkcast (0, 0)
	133 org/apache/commons/math3/RealFieldElement (0, 0)
	135 ldc2_w (0, 0)
	136 -13.866666666666667 (0, 0)
	138 invokeinterface (0, 0)
	139 org/apache/commons/math3/RealFieldElement.sqrt:()Ljava/lang/Object; (0, 0)
	141 0 (0, 0)
	143 invokeinterface (0, 0)
	144 org/apache/commons/math3/RealFieldElement.getField:()Lorg/apache/commons/math3/Field; (0, 0)
	146 0 (0, 0)
	148 checkcast (0, 0)
	149 org/apache/commons/math3/RealFieldElement (0, 0)
	151 astore (0, 0)
	152 #8 (0, 0)
	153 aload_3 (0, 0)
	154 aload_3 (0, 0)
	155 aload_3 (0, 0)
	156 aload_3 (0, 0)
	157 ldc2_w (0, 0)
	158 -113.4 (0, 0)
	160 invokeinterface (0, 0)
	161 org/apache/commons/math3/RealFieldElement.divide:(D)Ljava/lang/Object; (0, 0)
	163 0 (0, 0)
	165 checkcast (0, 0)
	166 org/apache/commons/math3/RealFieldElement (0, 0)
	168 ldc2_w (0, 0)
	169 194.4 (0, 0)
	171 invokeinterface (0, 0)
	172 org/apache/commons/math3/RealFieldElement.sqrt:()Ljava/lang/Object; (0, 0)
	174 0 (0, 0)
	176 invokeinterface (0, 0)
	177 org/apache/commons/math3/RealFieldElement.getField:()Lorg/apache/commons/math3/Field; (0, 0)
	179 0 (0, 0)
	181 checkcast (0, 0)
	182 org/apache/commons/math3/RealFieldElement (0, 0)
	184 ldc2_w (0, 0)
	185 -97.2 (0, 0)
	187 invokeinterface (0, 0)
	188 org/apache/commons/math3/RealFieldElement.sqrt:()Ljava/lang/Object; (0, 0)
	190 0 (0, 0)
	192 invokeinterface (0, 0)
	193 org/apache/commons/math3/RealFieldElement.getField:()Lorg/apache/commons/math3/Field; (0, 0)
	195 0 (0, 0)
	197 checkcast (0, 0)
	198 org/apache/commons/math3/RealFieldElement (0, 0)
	200 ldc2_w (0, 0)
	201 12.96 (0, 0)
	203 invokeinterface (0, 0)
	204 org/apache/commons/math3/RealFieldElement.sqrt:()Ljava/lang/Object; (0, 0)
	206 0 (0, 0)
	208 invokeinterface (0, 0)
	209 org/apache/commons/math3/RealFieldElement.getField:()Lorg/apache/commons/math3/Field; (0, 0)
	211 0 (0, 0)
	213 checkcast (0, 0)
	214 org/apache/commons/math3/RealFieldElement (0, 0)
	216 astore (0, 0)
	217 #9 (0, 0)
	218 aload_3 (0, 0)
	219 aload_3 (0, 0)
	220 aload_3 (0, 0)
	221 aload_3 (0, 0)
	222 aload_0 (0, 0)
	223 getfield (0, 0)
	224 org/apache/commons/math3/ode/nonstiff/LutherFieldStepInterpolator.c5a:Lorg/apache/commons/math3/RealFieldElement; (0, 0)
	226 ldc2_w (0, 0)
	227 5.0 (0, 0)
	229 invokeinterface (0, 0)
	230 org/apache/commons/math3/RealFieldElement.add:(Ljava/lang/Object;)Ljava/lang/Object; (0, 0)
	232 0 (0, 0)
	234 invokeinterface (0, 0)
	235 org/apache/commons/math3/RealFieldElement.getField:()Lorg/apache/commons/math3/Field; (0, 0)
	237 0 (0, 0)
	239 checkcast (0, 0)
	240 org/apache/commons/math3/RealFieldElement (0, 0)
	242 aload_0 (0, 0)
	243 getfield (0, 0)
	244 org/apache/commons/math3/ode/nonstiff/LutherFieldStepInterpolator.c5b:Lorg/apache/commons/math3/RealFieldElement; (0, 0)
	246 ldc2_w (0, 0)
	247 15.0 (0, 0)
	249 invokeinterface (0, 0)
	250 org/apache/commons/math3/RealFieldElement.add:(Ljava/lang/Object;)Ljava/lang/Object; (0, 0)
	252 0 (0, 0)
	254 invokeinterface (0, 0)
	255 org/apache/commons/math3/RealFieldElement.getGlobalPreviousState:()Lorg/apache/commons/math3/ode/FieldODEStateAndDerivative; (0, 0)
	257 0 (0, 0)
	259 invokeinterface (0, 0)
	260 org/apache/commons/math3/RealFieldElement.getField:()Lorg/apache/commons/math3/Field; (0, 0)
	262 0 (0, 0)
	264 checkcast (0, 0)
	265 org/apache/commons/math3/RealFieldElement (0, 0)
	267 aload_0 (0, 0)
	268 getfield (0, 0)
	269 org/apache/commons/math3/ode/nonstiff/LutherFieldStepInterpolator.c5c:Lorg/apache/commons/math3/RealFieldElement; (0, 0)
	271 ldc2_w (0, 0)
	272 30.0 (0, 0)
	274 invokeinterface (0, 0)
	275 org/apache/commons/math3/RealFieldElement.add:(Ljava/lang/Object;)Ljava/lang/Object; (0, 0)
	277 0 (0, 0)
	279 invokeinterface (0, 0)
	280 org/apache/commons/math3/RealFieldElement.getGlobalPreviousState:()Lorg/apache/commons/math3/ode/FieldODEStateAndDerivative; (0, 0)
	282 0 (0, 0)
	284 invokeinterface (0, 0)
	285 org/apache/commons/math3/RealFieldElement.getField:()Lorg/apache/commons/math3/Field; (0, 0)
	287 0 (0, 0)
	289 checkcast (0, 0)
	290 org/apache/commons/math3/RealFieldElement (0, 0)
	292 aload_0 (0, 0)
	293 getfield (0, 0)
	294 org/apache/commons/math3/ode/nonstiff/LutherFieldStepInterpolator.c5d:Lorg/apache/commons/math3/RealFieldElement; (0, 0)
	296 ldc2_w (0, 0)
	297 150.0 (0, 0)
	299 invokeinterface (0, 0)
	300 org/apache/commons/math3/RealFieldElement.add:(Ljava/lang/Object;)Ljava/lang/Object; (0, 0)
	302 0 (0, 0)
	304 invokeinterface (0, 0)
	305 org/apache/commons/math3/RealFieldElement.getGlobalPreviousState:()Lorg/apache/commons/math3/ode/FieldODEStateAndDerivative; (0, 0)
	307 0 (0, 0)
	309 invokeinterface (0, 0)
	310 org/apache/commons/math3/RealFieldElement.getField:()Lorg/apache/commons/math3/Field; (0, 0)
	312 0 (0, 0)
	314 checkcast (0, 0)
	315 org/apache/commons/math3/RealFieldElement (0, 0)
	317 astore (0, 0)
	318 #10 (0, 0)
	319 aload_3 (0, 0)
	320 aload_3 (0, 0)
	321 aload_3 (0, 0)
	322 aload_3 (0, 0)
	323 aload_0 (0, 0)
	324 getfield (0, 0)
	325 org/apache/commons/math3/ode/nonstiff/LutherFieldStepInterpolator.c6a:Lorg/apache/commons/math3/RealFieldElement; (0, 0)
	327 ldc2_w (0, 0)
	328 5.0 (0, 0)
	330 invokeinterface (0, 0)
	331 org/apache/commons/math3/RealFieldElement.add:(Ljava/lang/Object;)Ljava/lang/Object; (0, 0)
	333 0 (0, 0)
	335 invokeinterface (0, 0)
	336 org/apache/commons/math3/RealFieldElement.getField:()Lorg/apache/commons/math3/Field; (0, 0)
	338 0 (0, 0)
	340 checkcast (0, 0)
	341 org/apache/commons/math3/RealFieldElement (0, 0)
	343 aload_0 (0, 0)
	344 getfield (0, 0)
	345 org/apache/commons/math3/ode/nonstiff/LutherFieldStepInterpolator.c6b:Lorg/apache/commons/math3/RealFieldElement; (0, 0)
	347 ldc2_w (0, 0)
	348 15.0 (0, 0)
	350 invokeinterface (0, 0)
	351 org/apache/commons/math3/RealFieldElement.add:(Ljava/lang/Object;)Ljava/lang/Object; (0, 0)
	353 0 (0, 0)
	355 invokeinterface (0, 0)
	356 org/apache/commons/math3/RealFieldElement.getGlobalPreviousState:()Lorg/apache/commons/math3/ode/FieldODEStateAndDerivative; (0, 0)
	358 0 (0, 0)
	360 invokeinterface (0, 0)
	361 org/apache/commons/math3/RealFieldElement.getField:()Lorg/apache/commons/math3/Field; (0, 0)
	363 0 (0, 0)
	365 checkcast (0, 0)
	366 org/apache/commons/math3/RealFieldElement (0, 0)
	368 aload_0 (0, 0)
	369 getfield (0, 0)
	370 org/apache/commons/math3/ode/nonstiff/LutherFieldStepInterpolator.c6c:Lorg/apache/commons/math3/RealFieldElement; (0, 0)
	372 ldc2_w (0, 0)
	373 30.0 (0, 0)
	375 invokeinterface (0, 0)
	376 org/apache/commons/math3/RealFieldElement.add:(Ljava/lang/Object;)Ljava/lang/Object; (0, 0)
	378 0 (0, 0)
	380 invokeinterface (0, 0)
	381 org/apache/commons/math3/RealFieldElement.getGlobalPreviousState:()Lorg/apache/commons/math3/ode/FieldODEStateAndDerivative; (0, 0)
	383 0 (0, 0)
	385 invokeinterface (0, 0)
	386 org/apache/commons/math3/RealFieldElement.getField:()Lorg/apache/commons/math3/Field; (0, 0)
	388 0 (0, 0)
	390 checkcast (0, 0)
	391 org/apache/commons/math3/RealFieldElement (0, 0)
	393 aload_0 (0, 0)
	394 getfield (0, 0)
	395 org/apache/commons/math3/ode/nonstiff/LutherFieldStepInterpolator.c6d:Lorg/apache/commons/math3/RealFieldElement; (0, 0)
	397 ldc2_w (0, 0)
	398 150.0 (0, 0)
	400 invokeinterface (0, 0)
	401 org/apache/commons/math3/RealFieldElement.add:(Ljava/lang/Object;)Ljava/lang/Object; (0, 0)
	403 0 (0, 0)
	405 invokeinterface (0, 0)
	406 org/apache/commons/math3/RealFieldElement.getGlobalPreviousState:()Lorg/apache/commons/math3/ode/FieldODEStateAndDerivative; (0, 0)
	408 0 (0, 0)
	410 invokeinterface (0, 0)
	411 org/apache/commons/math3/RealFieldElement.getField:()Lorg/apache/commons/math3/Field; (0, 0)
	413 0 (0, 0)
	415 checkcast (0, 0)
	416 org/apache/commons/math3/RealFieldElement (0, 0)
	418 astore (0, 0)
	419 #11 (0, 0)
	420 aload_3 (0, 0)
	421 aload_3 (0, 0)
	422 aload_3 (0, 0)
	423 ldc2_w (0, 0)
	424 3.0 (0, 0)
	426 invokeinterface (0, 0)
	427 org/apache/commons/math3/RealFieldElement.divide:(D)Ljava/lang/Object; (0, 0)
	429 0 (0, 0)
	431 checkcast (0, 0)
	432 org/apache/commons/math3/RealFieldElement (0, 0)
	434 ldc2_w (0, 0)
	435 -3.0 (0, 0)
	437 invokeinterface (0, 0)
	438 org/apache/commons/math3/RealFieldElement.sqrt:()Ljava/lang/Object; (0, 0)
	440 0 (0, 0)
	442 invokeinterface (0, 0)
	443 org/apache/commons/math3/RealFieldElement.getField:()Lorg/apache/commons/math3/Field; (0, 0)
	445 0 (0, 0)
	447 checkcast (0, 0)
	448 org/apache/commons/math3/RealFieldElement (0, 0)
	450 ldc2_w (0, 0)
	451 0.6 (0, 0)
	453 invokeinterface (0, 0)
	454 org/apache/commons/math3/RealFieldElement.sqrt:()Ljava/lang/Object; (0, 0)
	456 0 (0, 0)
	458 invokeinterface (0, 0)
	459 org/apache/commons/math3/RealFieldElement.getField:()Lorg/apache/commons/math3/Field; (0, 0)
	461 0 (0, 0)
	463 checkcast (0, 0)
	464 org/apache/commons/math3/RealFieldElement (0, 0)
	466 astore (0, 0)
	467 #12 (0, 0)
	468 aload_0 (1, 1)
	469 invokevirtual (1, 1)
	470 org/apache/commons/math3/ode/nonstiff/LutherFieldStepInterpolator.getGlobalPreviousState:()Lorg/apache/commons/math3/ode/FieldODEStateAndDerivative; (1, 1)
	472 ifnull (1, 1)
	473 629 (1, 1)
	475 aload_3 (1, 1)
	476 invokeinterface (1, 1)
	477 org/apache/commons/math3/RealFieldElement.previousStateLinearCombination:([Lorg/apache/commons/math3/RealFieldElement;)[Lorg/apache/commons/math3/RealFieldElement; (1, 1)
	479 0 (1, 1)
	481 ldc2_w (1, 1)
	482 0.5 (1, 1)
	484 dcmpg (1, 1)
	485 ifgt (1, 1)
	486 616 (1, 1)
	488 aload (1, 1)
	489 #4 (1, 1)
	490 astore (1, 1)
	491 #15 (1, 1)
	492 aload (1, 1)
	493 #15 (1, 1)
	494 aload_3 (1, 1)
	495 aload_3 (1, 1)
	496 aload_3 (1, 1)
	497 aload_3 (1, 1)
	498 ldc2_w (1, 1)
	499 4.2 (1, 1)
	501 invokeinterface (1, 1)
	502 org/apache/commons/math3/RealFieldElement.divide:(D)Ljava/lang/Object; (1, 1)
	504 0 (1, 1)
	506 checkcast (1, 1)
	507 org/apache/commons/math3/RealFieldElement (1, 1)
	509 ldc2_w (1, 1)
	510 -11.75 (1, 1)
	512 invokeinterface (1, 1)
	513 org/apache/commons/math3/RealFieldElement.sqrt:()Ljava/lang/Object; (1, 1)
	515 0 (1, 1)
	517 invokeinterface (1, 1)
	518 org/apache/commons/math3/RealFieldElement.getField:()Lorg/apache/commons/math3/Field; (1, 1)
	520 0 (1, 1)
	522 checkcast (1, 1)
	523 org/apache/commons/math3/RealFieldElement (1, 1)
	525 ldc2_w (1, 1)
	526 12.0 (1, 1)
	528 invokeinterface (1, 1)
	529 org/apache/commons/math3/RealFieldElement.sqrt:()Ljava/lang/Object; (1, 1)
	531 0 (1, 1)
	533 invokeinterface (1, 1)
	534 org/apache/commons/math3/RealFieldElement.getField:()Lorg/apache/commons/math3/Field; (1, 1)
	536 0 (1, 1)
	538 checkcast (1, 1)
	539 org/apache/commons/math3/RealFieldElement (1, 1)
	541 ldc2_w (1, 1)
	542 -5.4 (1, 1)
	544 invokeinterface (1, 1)
	545 org/apache/commons/math3/RealFieldElement.sqrt:()Ljava/lang/Object; (1, 1)
	547 0 (1, 1)
	549 invokeinterface (1, 1)
	550 org/apache/commons/math3/RealFieldElement.getField:()Lorg/apache/commons/math3/Field; (1, 1)
	552 0 (1, 1)
	554 checkcast (1, 1)
	555 org/apache/commons/math3/RealFieldElement (1, 1)
	557 dconst_1 (1, 1)
	558 invokeinterface (1, 1)
	559 org/apache/commons/math3/RealFieldElement.sqrt:()Ljava/lang/Object; (1, 1)
	561 0 (1, 1)
	563 invokeinterface (1, 1)
	564 org/apache/commons/math3/RealFieldElement.getField:()Lorg/apache/commons/math3/Field; (1, 1)
	566 0 (1, 1)
	568 checkcast (1, 1)
	569 org/apache/commons/math3/RealFieldElement (1, 1)
	571 astore (1, 1)
	572 #16 (1, 1)
	573 aload_2 (1, 1)
	574 invokeinterface (1, 1)
	575 org/apache/commons/math3/RealFieldElement.multiply:(D)Ljava/lang/Object; (1, 1)
	577 0 (1, 1)
	579 invokeinterface (1, 1)
	580 org/apache/commons/math3/Field.org/apache/commons/math3/RealFieldElement (1, 1)
	582 0 (1, 1)
	584 checkcast (1, 1)
	585 org/apache/commons/math3/RealFieldElement (1, 1)
	587 astore (1, 1)
	588 #17 (1, 1)
	589 aload (1, 1)
	590 #15 (1, 1)
	591 aload_3 (1, 1)
	592 aload_3 (1, 1)
	593 aload_3 (1, 1)
	594 aload_3 (1, 1)
	595 ldc2_w (1, 1)
	596 22.4 (1, 1)
	598 invokeinterface (1, 1)
	599 org/apache/commons/math3/RealFieldElement.divide:(D)Ljava/lang/Object; (1, 1)
	601 0 (1, 1)
	603 checkcast (1, 1)
	604 org/apache/commons/math3/RealFieldElement (1, 1)
	606 ldc2_w (1, 1)
	607 -50.666666666666664 (1, 1)
	609 invokeinterface (1, 1)
	610 org/apache/commons/math3/RealFieldElement.sqrt:()Ljava/lang/Object; (1, 1)
	612 0 (1, 1)
	614 invokeinterface (1, 1)
	615 org/apache/commons/math3/RealFieldElement.getField:()Lorg/apache/commons/math3/Field; (1, 1)
	617 0 (1, 1)
	619 checkcast (1, 1)
	620 org/apache/commons/math3/RealFieldElement (1, 1)
	622 ldc2_w (1, 1)
	623 35.55555555555556 (1, 1)
	625 invokeinterface (1, 1)
	626 org/apache/commons/math3/RealFieldElement.sqrt:()Ljava/lang/Object; (1, 1)
	628 0 (1, 1)
	630 invokeinterface (1, 1)
	631 org/apache/commons/math3/RealFieldElement.getField:()Lorg/apache/commons/math3/Field; (1, 1)
	633 0 (1, 1)
	635 checkcast (1, 1)
	636 org/apache/commons/math3/RealFieldElement (1, 1)
	638 ldc2_w (1, 1)
	639 -6.933333333333334 (1, 1)
	641 invokeinterface (1, 1)
	642 org/apache/commons/math3/RealFieldElement.sqrt:()Ljava/lang/Object; (1, 1)
	644 0 (1, 1)
	646 invokeinterface (1, 1)
	647 org/apache/commons/math3/RealFieldElement.getField:()Lorg/apache/commons/math3/Field; (1, 1)
	649 0 (1, 1)
	651 invokeinterface (1, 1)
	652 org/apache/commons/math3/RealFieldElement.getField:()Lorg/apache/commons/math3/Field; (1, 1)
	654 0 (1, 1)
	656 checkcast (1, 1)
	657 org/apache/commons/math3/RealFieldElement (1, 1)
	659 astore (1, 1)
	660 #18 (1, 1)
	661 aload (1, 1)
	662 #15 (1, 1)
	663 aload_3 (1, 1)
	664 aload_3 (1, 1)
	665 aload_3 (1, 1)
	666 aload_3 (1, 1)
	667 ldc2_w (1, 1)
	668 -22.68 (1, 1)
	670 invokeinterface (1, 1)
	671 org/apache/commons/math3/RealFieldElement.divide:(D)Ljava/lang/Object; (1, 1)
	673 0 (1, 1)
	675 checkcast (1, 1)
	676 org/apache/commons/math3/RealFieldElement (1, 1)
	678 ldc2_w (1, 1)
	679 48.6 (1, 1)
	681 invokeinterface (1, 1)
	682 org/apache/commons/math3/RealFieldElement.sqrt:()Ljava/lang/Object; (1, 1)
	684 0 (1, 1)
	686 invokeinterface (1, 1)
	687 org/apache/commons/math3/RealFieldElement.getField:()Lorg/apache/commons/math3/Field; (1, 1)
	689 0 (1, 1)
	691 checkcast (1, 1)
	692 org/apache/commons/math3/RealFieldElement (1, 1)
	694 ldc2_w (1, 1)
	695 -32.4 (1, 1)
	697 invokeinterface (1, 1)
	698 org/apache/commons/math3/RealFieldElement.sqrt:()Ljava/lang/Object; (1, 1)
	700 0 (1, 1)
	702 invokeinterface (1, 1)
	703 org/apache/commons/math3/RealFieldElement.getField:()Lorg/apache/commons/math3/Field; (1, 1)
	705 0 (1, 1)
	707 checkcast (1, 1)
	708 org/apache/commons/math3/RealFieldElement (1, 1)
	710 ldc2_w (1, 1)
	711 6.48 (1, 1)
	713 invokeinterface (1, 1)
	714 org/apache/commons/math3/RealFieldElement.sqrt:()Ljava/lang/Object; (1, 1)
	716 0 (1, 1)
	718 invokeinterface (1, 1)
	719 org/apache/commons/math3/RealFieldElement.getField:()Lorg/apache/commons/math3/Field; (1, 1)
	721 0 (1, 1)
	723 invokeinterface (1, 1)
	724 org/apache/commons/math3/RealFieldElement.getField:()Lorg/apache/commons/math3/Field; (1, 1)
	726 0 (1, 1)
	728 checkcast (1, 1)
	729 org/apache/commons/math3/RealFieldElement (1, 1)
	731 astore (1, 1)
	732 #19 (1, 1)
	733 aload (1, 1)
	734 #15 (1, 1)
	735 aload_3 (1, 1)
	736 aload_3 (1, 1)
	737 aload_3 (1, 1)
	738 aload_3 (1, 1)
	739 aload_0 (1, 1)
	740 getfield (1, 1)
	741 org/apache/commons/math3/ode/nonstiff/LutherFieldStepInterpolator.c5a:Lorg/apache/commons/math3/RealFieldElement; (1, 1)
	743 ldc2_w (1, 1)
	744 25.0 (1, 1)
	746 invokeinterface (1, 1)
	747 org/apache/commons/math3/RealFieldElement.add:(Ljava/lang/Object;)Ljava/lang/Object; (1, 1)
	749 0 (1, 1)
	751 invokeinterface (1, 1)
	752 org/apache/commons/math3/RealFieldElement.getField:()Lorg/apache/commons/math3/Field; (1, 1)
	754 0 (1, 1)
	756 checkcast (1, 1)
	757 org/apache/commons/math3/RealFieldElement (1, 1)
	759 aload_0 (1, 1)
	760 getfield (1, 1)
	761 org/apache/commons/math3/ode/nonstiff/LutherFieldStepInterpolator.c5b:Lorg/apache/commons/math3/RealFieldElement; (1, 1)
	763 ldc2_w (1, 1)
	764 60.0 (1, 1)
	766 invokeinterface (1, 1)
	767 org/apache/commons/math3/RealFieldElement.add:(Ljava/lang/Object;)Ljava/lang/Object; (1, 1)
	769 0 (1, 1)
	771 invokeinterface (1, 1)
	772 org/apache/commons/math3/RealFieldElement.getGlobalPreviousState:()Lorg/apache/commons/math3/ode/FieldODEStateAndDerivative; (1, 1)
	774 0 (1, 1)
	776 invokeinterface (1, 1)
	777 org/apache/commons/math3/RealFieldElement.getField:()Lorg/apache/commons/math3/Field; (1, 1)
	779 0 (1, 1)
	781 checkcast (1, 1)
	782 org/apache/commons/math3/RealFieldElement (1, 1)
	784 aload_0 (1, 1)
	785 getfield (1, 1)
	786 org/apache/commons/math3/ode/nonstiff/LutherFieldStepInterpolator.c5c:Lorg/apache/commons/math3/RealFieldElement; (1, 1)
	788 ldc2_w (1, 1)
	789 90.0 (1, 1)
	791 invokeinterface (1, 1)
	792 org/apache/commons/math3/RealFieldElement.add:(Ljava/lang/Object;)Ljava/lang/Object; (1, 1)
	794 0 (1, 1)
	796 invokeinterface (1, 1)
	797 org/apache/commons/math3/RealFieldElement.getGlobalPreviousState:()Lorg/apache/commons/math3/ode/FieldODEStateAndDerivative; (1, 1)
	799 0 (1, 1)
	801 invokeinterface (1, 1)
	802 org/apache/commons/math3/RealFieldElement.getField:()Lorg/apache/commons/math3/Field; (1, 1)
	804 0 (1, 1)
	806 checkcast (1, 1)
	807 org/apache/commons/math3/RealFieldElement (1, 1)
	809 aload_0 (1, 1)
	810 getfield (1, 1)
	811 org/apache/commons/math3/ode/nonstiff/LutherFieldStepInterpolator.c5d:Lorg/apache/commons/math3/RealFieldElement; (1, 1)
	813 ldc2_w (1, 1)
	814 300.0 (1, 1)
	816 invokeinterface (1, 1)
	817 org/apache/commons/math3/RealFieldElement.add:(Ljava/lang/Object;)Ljava/lang/Object; (1, 1)
	819 0 (1, 1)
	821 invokeinterface (1, 1)
	822 org/apache/commons/math3/RealFieldElement.getGlobalPreviousState:()Lorg/apache/commons/math3/ode/FieldODEStateAndDerivative; (1, 1)
	824 0 (1, 1)
	826 invokeinterface (1, 1)
	827 org/apache/commons/math3/RealFieldElement.getField:()Lorg/apache/commons/math3/Field; (1, 1)
	829 0 (1, 1)
	831 invokeinterface (1, 1)
	832 org/apache/commons/math3/RealFieldElement.getField:()Lorg/apache/commons/math3/Field; (1, 1)
	834 0 (1, 1)
	836 checkcast (1, 1)
	837 org/apache/commons/math3/RealFieldElement (1, 1)
	839 astore (1, 1)
	840 #20 (1, 1)
	841 aload (1, 1)
	842 #15 (1, 1)
	843 aload_3 (1, 1)
	844 aload_3 (1, 1)
	845 aload_3 (1, 1)
	846 aload_3 (1, 1)
	847 aload_0 (1, 1)
	848 getfield (1, 1)
	849 org/apache/commons/math3/ode/nonstiff/LutherFieldStepInterpolator.c6a:Lorg/apache/commons/math3/RealFieldElement; (1, 1)
	851 ldc2_w (1, 1)
	852 25.0 (1, 1)
	854 invokeinterface (1, 1)
	855 org/apache/commons/math3/RealFieldElement.add:(Ljava/lang/Object;)Ljava/lang/Object; (1, 1)
	857 0 (1, 1)
	859 invokeinterface (1, 1)
	860 org/apache/commons/math3/RealFieldElement.getField:()Lorg/apache/commons/math3/Field; (1, 1)
	862 0 (1, 1)
	864 checkcast (1, 1)
	865 org/apache/commons/math3/RealFieldElement (1, 1)
	867 aload_0 (1, 1)
	868 getfield (1, 1)
	869 org/apache/commons/math3/ode/nonstiff/LutherFieldStepInterpolator.c6b:Lorg/apache/commons/math3/RealFieldElement; (1, 1)
	871 ldc2_w (1, 1)
	872 60.0 (1, 1)
	874 invokeinterface (1, 1)
	875 org/apache/commons/math3/RealFieldElement.add:(Ljava/lang/Object;)Ljava/lang/Object; (1, 1)
	877 0 (1, 1)
	879 invokeinterface (1, 1)
	880 org/apache/commons/math3/RealFieldElement.getGlobalPreviousState:()Lorg/apache/commons/math3/ode/FieldODEStateAndDerivative; (1, 1)
	882 0 (1, 1)
	884 invokeinterface (1, 1)
	885 org/apache/commons/math3/RealFieldElement.getField:()Lorg/apache/commons/math3/Field; (1, 1)
	887 0 (1, 1)
	889 checkcast (1, 1)
	890 org/apache/commons/math3/RealFieldElement (1, 1)
	892 aload_0 (1, 1)
	893 getfield (1, 1)
	894 org/apache/commons/math3/ode/nonstiff/LutherFieldStepInterpolator.c6c:Lorg/apache/commons/math3/RealFieldElement; (1, 1)
	896 ldc2_w (1, 1)
	897 90.0 (1, 1)
	899 invokeinterface (1, 1)
	900 org/apache/commons/math3/RealFieldElement.add:(Ljava/lang/Object;)Ljava/lang/Object; (1, 1)
	902 0 (1, 1)
	904 invokeinterface (1, 1)
	905 org/apache/commons/math3/RealFieldElement.getGlobalPreviousState:()Lorg/apache/commons/math3/ode/FieldODEStateAndDerivative; (1, 1)
	907 0 (1, 1)
	909 invokeinterface (1, 1)
	910 org/apache/commons/math3/RealFieldElement.getField:()Lorg/apache/commons/math3/Field; (1, 1)
	912 0 (1, 1)
	914 checkcast (1, 1)
	915 org/apache/commons/math3/RealFieldElement (1, 1)
	917 aload_0 (1, 1)
	918 getfield (1, 1)
	919 org/apache/commons/math3/ode/nonstiff/LutherFieldStepInterpolator.c6d:Lorg/apache/commons/math3/RealFieldElement; (1, 1)
	921 ldc2_w (1, 1)
	922 300.0 (1, 1)
	924 invokeinterface (1, 1)
	925 org/apache/commons/math3/RealFieldElement.add:(Ljava/lang/Object;)Ljava/lang/Object; (1, 1)
	927 0 (1, 1)
	929 invokeinterface (1, 1)
	930 org/apache/commons/math3/RealFieldElement.getGlobalPreviousState:()Lorg/apache/commons/math3/ode/FieldODEStateAndDerivative; (1, 1)
	932 0 (1, 1)
	934 invokeinterface (1, 1)
	935 org/apache/commons/math3/RealFieldElement.getField:()Lorg/apache/commons/math3/Field; (1, 1)
	937 0 (1, 1)
	939 invokeinterface (1, 1)
	940 org/apache/commons/math3/RealFieldElement.getField:()Lorg/apache/commons/math3/Field; (1, 1)
	942 0 (1, 1)
	944 checkcast (1, 1)
	945 org/apache/commons/math3/RealFieldElement (1, 1)
	947 astore (1, 1)
	948 #21 (1, 1)
	949 aload (1, 1)
	950 #15 (1, 1)
	951 aload_3 (1, 1)
	952 aload_3 (1, 1)
	953 aload_3 (1, 1)
	954 ldc2_w (1, 1)
	955 0.75 (1, 1)
	957 invokeinterface (1, 1)
	958 org/apache/commons/math3/RealFieldElement.divide:(D)Ljava/lang/Object; (1, 1)
	960 0 (1, 1)
	962 checkcast (1, 1)
	963 org/apache/commons/math3/RealFieldElement (1, 1)
	965 ldc2_w (1, 1)
	966 -1.0 (1, 1)
	968 invokeinterface (1, 1)
	969 org/apache/commons/math3/RealFieldElement.sqrt:()Ljava/lang/Object; (1, 1)
	971 0 (1, 1)
	973 invokeinterface (1, 1)
	974 org/apache/commons/math3/RealFieldElement.getField:()Lorg/apache/commons/math3/Field; (1, 1)
	976 0 (1, 1)
	978 checkcast (1, 1)
	979 org/apache/commons/math3/RealFieldElement (1, 1)
	981 ldc2_w (1, 1)
	982 0.3 (1, 1)
	984 invokeinterface (1, 1)
	985 org/apache/commons/math3/RealFieldElement.sqrt:()Ljava/lang/Object; (1, 1)
	987 0 (1, 1)
	989 invokeinterface (1, 1)
	990 org/apache/commons/math3/RealFieldElement.getField:()Lorg/apache/commons/math3/Field; (1, 1)
	992 0 (1, 1)
	994 invokeinterface (1, 1)
	995 org/apache/commons/math3/RealFieldElement.getField:()Lorg/apache/commons/math3/Field; (1, 1)
	997 0 (1, 1)
	999 checkcast (1, 1)
	1000 org/apache/commons/math3/RealFieldElement (1, 1)
	1002 astore (1, 1)
	1003 #22 (1, 1)
	1004 aload_0 (1, 1)
	1005 bipush (1, 1)
	1006 7 (1, 1)
	1007 anewarray (1, 1)
	1008 org/apache/commons/math3/RealFieldElement (1, 1)
	1010 dup (1, 1)
	1011 iconst_0 (1, 1)
	1012 aload (1, 1)
	1013 #16 (1, 1)
	1014 aastore (1, 1)
	1015 dup (1, 1)
	1016 iconst_1 (1, 1)
	1017 aload (1, 1)
	1018 #17 (1, 1)
	1019 aastore (1, 1)
	1020 dup (1, 1)
	1021 iconst_2 (1, 1)
	1022 aload (1, 1)
	1023 #18 (1, 1)
	1024 aastore (1, 1)
	1025 dup (1, 1)
	1026 iconst_3 (1, 1)
	1027 aload (1, 1)
	1028 #19 (1, 1)
	1029 aastore (1, 1)
	1030 dup (1, 1)
	1031 iconst_4 (1, 1)
	1032 aload (1, 1)
	1033 #20 (1, 1)
	1034 aastore (1, 1)
	1035 dup (1, 1)
	1036 iconst_5 (1, 1)
	1037 aload (1, 1)
	1038 #21 (1, 1)
	1039 aastore (1, 1)
	1040 dup (1, 1)
	1041 bipush (1, 1)
	1042 6 (1, 1)
	1043 aload (1, 1)
	1044 #22 (1, 1)
	1045 aastore (1, 1)
	1046 invokevirtual (1, 1)
	1047 org/apache/commons/math3/ode/nonstiff/LutherFieldStepInterpolator.previousStateLinearCombination:([Lorg/apache/commons/math3/RealFieldElement;)[Lorg/apache/commons/math3/RealFieldElement; (1, 1)
	1049 astore (1, 1)
	1050 #13 (1, 1)
	1051 aload_0 (1, 1)
	1052 bipush (1, 1)
	1053 7 (1, 1)
	1054 anewarray (1, 1)
	1055 org/apache/commons/math3/RealFieldElement (1, 1)
	1057 dup (1, 1)
	1058 iconst_0 (1, 1)
	1059 aload (1, 1)
	1060 #6 (1, 1)
	1061 aastore (1, 1)
	1062 dup (1, 1)
	1063 iconst_1 (1, 1)
	1064 aload (1, 1)
	1065 #7 (1, 1)
	1066 aastore (1, 1)
	1067 dup (1, 1)
	1068 iconst_2 (1, 1)
	1069 aload (1, 1)
	1070 #8 (1, 1)
	1071 aastore (1, 1)
	1072 dup (1, 1)
	1073 iconst_3 (1, 1)
	1074 aload (1, 1)
	1075 #9 (1, 1)
	1076 aastore (1, 1)
	1077 dup (1, 1)
	1078 iconst_4 (1, 1)
	1079 aload (1, 1)
	1080 #10 (1, 1)
	1081 aastore (1, 1)
	1082 dup (1, 1)
	1083 iconst_5 (1, 1)
	1084 aload (1, 1)
	1085 #11 (1, 1)
	1086 aastore (1, 1)
	1087 dup (1, 1)
	1088 bipush (1, 1)
	1089 6 (1, 1)
	1090 aload (1, 1)
	1091 #12 (1, 1)
	1092 aastore (1, 1)
	1093 invokevirtual (1, 1)
	1094 org/apache/commons/math3/ode/nonstiff/LutherFieldStepInterpolator.derivativeLinearCombination:([Lorg/apache/commons/math3/RealFieldElement;)[Lorg/apache/commons/math3/RealFieldElement; (1, 1)
	1096 astore (1, 1)
	1097 #14 (1, 1)
	1098 goto (1, 2)
	1099 630 (1, 2)
	1101 aload (1, 2)
	1102 #5 (1, 2)
	1103 astore (1, 2)
	1104 #15 (1, 2)
	1105 aload (1, 2)
	1106 #15 (1, 2)
	1107 aload_3 (1, 2)
	1108 aload_3 (1, 2)
	1109 aload_3 (1, 2)
	1110 aload_3 (1, 2)
	1111 ldc2_w (1, 2)
	1112 -4.2 (1, 2)
	1114 invokeinterface (1, 2)
	1115 org/apache/commons/math3/RealFieldElement.divide:(D)Ljava/lang/Object; (1, 2)
	1117 0 (1, 2)
	1119 checkcast (1, 2)
	1120 org/apache/commons/math3/RealFieldElement (1, 2)
	1122 ldc2_w (1, 2)
	1123 7.55 (1, 2)
	1125 invokeinterface (1, 2)
	1126 org/apache/commons/math3/RealFieldElement.sqrt:()Ljava/lang/Object; (1, 2)
	1128 0 (1, 2)
	1130 invokeinterface (1, 2)
	1131 org/apache/commons/math3/RealFieldElement.getField:()Lorg/apache/commons/math3/Field; (1, 2)
	1133 0 (1, 2)
	1135 checkcast (1, 2)
	1136 org/apache/commons/math3/RealFieldElement (1, 2)
	1138 ldc2_w (1, 2)
	1139 -4.45 (1, 2)
	1141 invokeinterface (1, 2)
	1142 org/apache/commons/math3/RealFieldElement.sqrt:()Ljava/lang/Object; (1, 2)
	1144 0 (1, 2)
	1146 invokeinterface (1, 2)
	1147 org/apache/commons/math3/RealFieldElement.getField:()Lorg/apache/commons/math3/Field; (1, 2)
	1149 0 (1, 2)
	1151 checkcast (1, 2)
	1152 org/apache/commons/math3/RealFieldElement (1, 2)
	1154 ldc2_w (1, 2)
	1155 0.95 (1, 2)
	1157 invokeinterface (1, 2)
	1158 org/apache/commons/math3/RealFieldElement.sqrt:()Ljava/lang/Object; (1, 2)
	1160 0 (1, 2)
	1162 invokeinterface (1, 2)
	1163 org/apache/commons/math3/RealFieldElement.getField:()Lorg/apache/commons/math3/Field; (1, 2)
	1165 0 (1, 2)
	1167 checkcast (1, 2)
	1168 org/apache/commons/math3/RealFieldElement (1, 2)
	1170 ldc2_w (1, 2)
	1171 -0.05 (1, 2)
	1173 invokeinterface (1, 2)
	1174 org/apache/commons/math3/RealFieldElement.sqrt:()Ljava/lang/Object; (1, 2)
	1176 0 (1, 2)
	1178 invokeinterface (1, 2)
	1179 org/apache/commons/math3/RealFieldElement.getField:()Lorg/apache/commons/math3/Field; (1, 2)
	1181 0 (1, 2)
	1183 checkcast (1, 2)
	1184 org/apache/commons/math3/RealFieldElement (1, 2)
	1186 astore (1, 2)
	1187 #16 (1, 2)
	1188 aload_2 (1, 2)
	1189 invokeinterface (1, 2)
	1190 org/apache/commons/math3/RealFieldElement.multiply:(D)Ljava/lang/Object; (1, 2)
	1192 0 (1, 2)
	1194 invokeinterface (1, 2)
	1195 org/apache/commons/math3/Field.org/apache/commons/math3/RealFieldElement (1, 2)
	1197 0 (1, 2)
	1199 checkcast (1, 2)
	1200 org/apache/commons/math3/RealFieldElement (1, 2)
	1202 astore (1, 2)
	1203 #17 (1, 2)
	1204 aload (1, 2)
	1205 #15 (1, 2)
	1206 aload_3 (1, 2)
	1207 aload_3 (1, 2)
	1208 aload_3 (1, 2)
	1209 aload_3 (1, 2)
	1210 ldc2_w (1, 2)
	1211 -22.4 (1, 2)
	1213 invokeinterface (1, 2)
	1214 org/apache/commons/math3/RealFieldElement.divide:(D)Ljava/lang/Object; (1, 2)
	1216 0 (1, 2)
	1218 checkcast (1, 2)
	1219 org/apache/commons/math3/RealFieldElement (1, 2)
	1221 ldc2_w (1, 2)
	1222 28.266666666666666 (1, 2)
	1224 invokeinterface (1, 2)
	1225 org/apache/commons/math3/RealFieldElement.sqrt:()Ljava/lang/Object; (1, 2)
	1227 0 (1, 2)
	1229 invokeinterface (1, 2)
	1230 org/apache/commons/math3/RealFieldElement.getField:()Lorg/apache/commons/math3/Field; (1, 2)
	1232 0 (1, 2)
	1234 checkcast (1, 2)
	1235 org/apache/commons/math3/RealFieldElement (1, 2)
	1237 ldc2_w (1, 2)
	1238 -7.288888888888889 (1, 2)
	1240 invokeinterface (1, 2)
	1241 org/apache/commons/math3/RealFieldElement.sqrt:()Ljava/lang/Object; (1, 2)
	1243 0 (1, 2)
	1245 invokeinterface (1, 2)
	1246 org/apache/commons/math3/RealFieldElement.getField:()Lorg/apache/commons/math3/Field; (1, 2)
	1248 0 (1, 2)
	1250 checkcast (1, 2)
	1251 org/apache/commons/math3/RealFieldElement (1, 2)
	1253 ldc2_w (1, 2)
	1254 -0.35555555555555557 (1, 2)
	1256 invokeinterface (1, 2)
	1257 org/apache/commons/math3/RealFieldElement.sqrt:()Ljava/lang/Object; (1, 2)
	1259 0 (1, 2)
	1261 invokeinterface (1, 2)
	1262 org/apache/commons/math3/RealFieldElement.getField:()Lorg/apache/commons/math3/Field; (1, 2)
	1264 0 (1, 2)
	1266 checkcast (1, 2)
	1267 org/apache/commons/math3/RealFieldElement (1, 2)
	1269 ldc2_w (1, 2)
	1270 -0.35555555555555557 (1, 2)
	1272 invokeinterface (1, 2)
	1273 org/apache/commons/math3/RealFieldElement.sqrt:()Ljava/lang/Object; (1, 2)
	1275 0 (1, 2)
	1277 invokeinterface (1, 2)
	1278 org/apache/commons/math3/RealFieldElement.getField:()Lorg/apache/commons/math3/Field; (1, 2)
	1280 0 (1, 2)
	1282 checkcast (1, 2)
	1283 org/apache/commons/math3/RealFieldElement (1, 2)
	1285 astore (1, 2)
	1286 #18 (1, 2)
	1287 aload (1, 2)
	1288 #15 (1, 2)
	1289 aload_3 (1, 2)
	1290 aload_3 (1, 2)
	1291 aload_3 (1, 2)
	1292 aload_3 (1, 2)
	1293 ldc2_w (1, 2)
	1294 22.68 (1, 2)
	1296 invokeinterface (1, 2)
	1297 org/apache/commons/math3/RealFieldElement.divide:(D)Ljava/lang/Object; (1, 2)
	1299 0 (1, 2)
	1301 checkcast (1, 2)
	1302 org/apache/commons/math3/RealFieldElement (1, 2)
	1304 ldc2_w (1, 2)
	1305 -25.92 (1, 2)
	1307 invokeinterface (1, 2)
	1308 org/apache/commons/math3/RealFieldElement.sqrt:()Ljava/lang/Object; (1, 2)
	1310 0 (1, 2)
	1312 invokeinterface (1, 2)
	1313 org/apache/commons/math3/RealFieldElement.getField:()Lorg/apache/commons/math3/Field; (1, 2)
	1315 0 (1, 2)
	1317 checkcast (1, 2)
	1318 org/apache/commons/math3/RealFieldElement (1, 2)
	1320 ldc2_w (1, 2)
	1321 6.48 (1, 2)
	1323 invokeinterface (1, 2)
	1324 org/apache/commons/math3/RealFieldElement.sqrt:()Ljava/lang/Object; (1, 2)
	1326 0 (1, 2)
	1328 invokeinterface (1, 2)
	1329 org/apache/commons/math3/RealFieldElement.getField:()Lorg/apache/commons/math3/Field; (1, 2)
	1331 0 (1, 2)
	1333 invokeinterface (1, 2)
	1334 org/apache/commons/math3/RealFieldElement.getField:()Lorg/apache/commons/math3/Field; (1, 2)
	1336 0 (1, 2)
	1338 invokeinterface (1, 2)
	1339 org/apache/commons/math3/RealFieldElement.getField:()Lorg/apache/commons/math3/Field; (1, 2)
	1341 0 (1, 2)
	1343 checkcast (1, 2)
	1344 org/apache/commons/math3/RealFieldElement (1, 2)
	1346 astore (1, 2)
	1347 #19 (1, 2)
	1348 aload (1, 2)
	1349 #15 (1, 2)
	1350 aload_3 (1, 2)
	1351 aload_3 (1, 2)
	1352 aload_3 (1, 2)
	1353 aload_3 (1, 2)
	1354 aload_0 (1, 2)
	1355 getfield (1, 2)
	1356 org/apache/commons/math3/ode/nonstiff/LutherFieldStepInterpolator.d5a:Lorg/apache/commons/math3/RealFieldElement; (1, 2)
	1358 ldc2_w (1, 2)
	1359 25.0 (1, 2)
	1361 invokeinterface (1, 2)
	1362 org/apache/commons/math3/RealFieldElement.add:(Ljava/lang/Object;)Ljava/lang/Object; (1, 2)
	1364 0 (1, 2)
	1366 invokeinterface (1, 2)
	1367 org/apache/commons/math3/RealFieldElement.getField:()Lorg/apache/commons/math3/Field; (1, 2)
	1369 0 (1, 2)
	1371 checkcast (1, 2)
	1372 org/apache/commons/math3/RealFieldElement (1, 2)
	1374 aload_0 (1, 2)
	1375 getfield (1, 2)
	1376 org/apache/commons/math3/ode/nonstiff/LutherFieldStepInterpolator.d5b:Lorg/apache/commons/math3/RealFieldElement; (1, 2)
	1378 ldc2_w (1, 2)
	1379 300.0 (1, 2)
	1381 invokeinterface (1, 2)
	1382 org/apache/commons/math3/RealFieldElement.add:(Ljava/lang/Object;)Ljava/lang/Object; (1, 2)
	1384 0 (1, 2)
	1386 invokeinterface (1, 2)
	1387 org/apache/commons/math3/RealFieldElement.getGlobalPreviousState:()Lorg/apache/commons/math3/ode/FieldODEStateAndDerivative; (1, 2)
	1389 0 (1, 2)
	1391 invokeinterface (1, 2)
	1392 org/apache/commons/math3/RealFieldElement.getField:()Lorg/apache/commons/math3/Field; (1, 2)
	1394 0 (1, 2)
	1396 checkcast (1, 2)
	1397 org/apache/commons/math3/RealFieldElement (1, 2)
	1399 aload_0 (1, 2)
	1400 getfield (1, 2)
	1401 org/apache/commons/math3/ode/nonstiff/LutherFieldStepInterpolator.d5c:Lorg/apache/commons/math3/RealFieldElement; (1, 2)
	1403 ldc2_w (1, 2)
	1404 900.0 (1, 2)
	1406 invokeinterface (1, 2)
	1407 org/apache/commons/math3/RealFieldElement.add:(Ljava/lang/Object;)Ljava/lang/Object; (1, 2)
	1409 0 (1, 2)
	1411 invokeinterface (1, 2)
	1412 org/apache/commons/math3/RealFieldElement.getGlobalPreviousState:()Lorg/apache/commons/math3/ode/FieldODEStateAndDerivative; (1, 2)
	1414 0 (1, 2)
	1416 invokeinterface (1, 2)
	1417 org/apache/commons/math3/RealFieldElement.getField:()Lorg/apache/commons/math3/Field; (1, 2)
	1419 0 (1, 2)
	1421 checkcast (1, 2)
	1422 org/apache/commons/math3/RealFieldElement (1, 2)
	1424 ldc2_w (1, 2)
	1425 -0.2722222222222222 (1, 2)
	1427 invokeinterface (1, 2)
	1428 org/apache/commons/math3/RealFieldElement.sqrt:()Ljava/lang/Object; (1, 2)
	1430 0 (1, 2)
	1432 invokeinterface (1, 2)
	1433 org/apache/commons/math3/RealFieldElement.getField:()Lorg/apache/commons/math3/Field; (1, 2)
	1435 0 (1, 2)
	1437 checkcast (1, 2)
	1438 org/apache/commons/math3/RealFieldElement (1, 2)
	1440 ldc2_w (1, 2)
	1441 -0.2722222222222222 (1, 2)
	1443 invokeinterface (1, 2)
	1444 org/apache/commons/math3/RealFieldElement.sqrt:()Ljava/lang/Object; (1, 2)
	1446 0 (1, 2)
	1448 invokeinterface (1, 2)
	1449 org/apache/commons/math3/RealFieldElement.getField:()Lorg/apache/commons/math3/Field; (1, 2)
	1451 0 (1, 2)
	1453 checkcast (1, 2)
	1454 org/apache/commons/math3/RealFieldElement (1, 2)
	1456 astore (1, 2)
	1457 #20 (1, 2)
	1458 aload (1, 2)
	1459 #15 (1, 2)
	1460 aload_3 (1, 2)
	1461 aload_3 (1, 2)
	1462 aload_3 (1, 2)
	1463 aload_3 (1, 2)
	1464 aload_0 (1, 2)
	1465 getfield (1, 2)
	1466 org/apache/commons/math3/ode/nonstiff/LutherFieldStepInterpolator.d6a:Lorg/apache/commons/math3/RealFieldElement; (1, 2)
	1468 ldc2_w (1, 2)
	1469 25.0 (1, 2)
	1471 invokeinterface (1, 2)
	1472 org/apache/commons/math3/RealFieldElement.add:(Ljava/lang/Object;)Ljava/lang/Object; (1, 2)
	1474 0 (1, 2)
	1476 invokeinterface (1, 2)
	1477 org/apache/commons/math3/RealFieldElement.getField:()Lorg/apache/commons/math3/Field; (1, 2)
	1479 0 (1, 2)
	1481 checkcast (1, 2)
	1482 org/apache/commons/math3/RealFieldElement (1, 2)
	1484 aload_0 (1, 2)
	1485 getfield (1, 2)
	1486 org/apache/commons/math3/ode/nonstiff/LutherFieldStepInterpolator.d6b:Lorg/apache/commons/math3/RealFieldElement; (1, 2)
	1488 ldc2_w (1, 2)
	1489 300.0 (1, 2)
	1491 invokeinterface (1, 2)
	1492 org/apache/commons/math3/RealFieldElement.add:(Ljava/lang/Object;)Ljava/lang/Object; (1, 2)
	1494 0 (1, 2)
	1496 invokeinterface (1, 2)
	1497 org/apache/commons/math3/RealFieldElement.getGlobalPreviousState:()Lorg/apache/commons/math3/ode/FieldODEStateAndDerivative; (1, 2)
	1499 0 (1, 2)
	1501 invokeinterface (1, 2)
	1502 org/apache/commons/math3/RealFieldElement.getField:()Lorg/apache/commons/math3/Field; (1, 2)
	1504 0 (1, 2)
	1506 checkcast (1, 2)
	1507 org/apache/commons/math3/RealFieldElement (1, 2)
	1509 aload_0 (1, 2)
	1510 getfield (1, 2)
	1511 org/apache/commons/math3/ode/nonstiff/LutherFieldStepInterpolator.d6c:Lorg/apache/commons/math3/RealFieldElement; (1, 2)
	1513 ldc2_w (1, 2)
	1514 900.0 (1, 2)
	1516 invokeinterface (1, 2)
	1517 org/apache/commons/math3/RealFieldElement.add:(Ljava/lang/Object;)Ljava/lang/Object; (1, 2)
	1519 0 (1, 2)
	1521 invokeinterface (1, 2)
	1522 org/apache/commons/math3/RealFieldElement.getGlobalPreviousState:()Lorg/apache/commons/math3/ode/FieldODEStateAndDerivative; (1, 2)
	1524 0 (1, 2)
	1526 invokeinterface (1, 2)
	1527 org/apache/commons/math3/RealFieldElement.getField:()Lorg/apache/commons/math3/Field; (1, 2)
	1529 0 (1, 2)
	1531 checkcast (1, 2)
	1532 org/apache/commons/math3/RealFieldElement (1, 2)
	1534 ldc2_w (1, 2)
	1535 -0.2722222222222222 (1, 2)
	1537 invokeinterface (1, 2)
	1538 org/apache/commons/math3/RealFieldElement.sqrt:()Ljava/lang/Object; (1, 2)
	1540 0 (1, 2)
	1542 invokeinterface (1, 2)
	1543 org/apache/commons/math3/RealFieldElement.getField:()Lorg/apache/commons/math3/Field; (1, 2)
	1545 0 (1, 2)
	1547 checkcast (1, 2)
	1548 org/apache/commons/math3/RealFieldElement (1, 2)
	1550 ldc2_w (1, 2)
	1551 -0.2722222222222222 (1, 2)
	1553 invokeinterface (1, 2)
	1554 org/apache/commons/math3/RealFieldElement.sqrt:()Ljava/lang/Object; (1, 2)
	1556 0 (1, 2)
	1558 invokeinterface (1, 2)
	1559 org/apache/commons/math3/RealFieldElement.getField:()Lorg/apache/commons/math3/Field; (1, 2)
	1561 0 (1, 2)
	1563 checkcast (1, 2)
	1564 org/apache/commons/math3/RealFieldElement (1, 2)
	1566 astore (1, 2)
	1567 #21 (1, 2)
	1568 aload (1, 2)
	1569 #15 (1, 2)
	1570 aload_3 (1, 2)
	1571 aload_3 (1, 2)
	1572 aload_3 (1, 2)
	1573 ldc2_w (1, 2)
	1574 -0.75 (1, 2)
	1576 invokeinterface (1, 2)
	1577 org/apache/commons/math3/RealFieldElement.divide:(D)Ljava/lang/Object; (1, 2)
	1579 0 (1, 2)
	1581 checkcast (1, 2)
	1582 org/apache/commons/math3/RealFieldElement (1, 2)
	1584 ldc2_w (1, 2)
	1585 0.25 (1, 2)
	1587 invokeinterface (1, 2)
	1588 org/apache/commons/math3/RealFieldElement.sqrt:()Ljava/lang/Object; (1, 2)
	1590 0 (1, 2)
	1592 invokeinterface (1, 2)
	1593 org/apache/commons/math3/RealFieldElement.getField:()Lorg/apache/commons/math3/Field; (1, 2)
	1595 0 (1, 2)
	1597 checkcast (1, 2)
	1598 org/apache/commons/math3/RealFieldElement (1, 2)
	1600 ldc2_w (1, 2)
	1601 -0.05 (1, 2)
	1603 invokeinterface (1, 2)
	1604 org/apache/commons/math3/RealFieldElement.sqrt:()Ljava/lang/Object; (1, 2)
	1606 0 (1, 2)
	1608 invokeinterface (1, 2)
	1609 org/apache/commons/math3/RealFieldElement.getField:()Lorg/apache/commons/math3/Field; (1, 2)
	1611 0 (1, 2)
	1613 checkcast (1, 2)
	1614 org/apache/commons/math3/RealFieldElement (1, 2)
	1616 ldc2_w (1, 2)
	1617 -0.05 (1, 2)
	1619 invokeinterface (1, 2)
	1620 org/apache/commons/math3/RealFieldElement.sqrt:()Ljava/lang/Object; (1, 2)
	1622 0 (1, 2)
	1624 invokeinterface (1, 2)
	1625 org/apache/commons/math3/RealFieldElement.getField:()Lorg/apache/commons/math3/Field; (1, 2)
	1627 0 (1, 2)
	1629 checkcast (1, 2)
	1630 org/apache/commons/math3/RealFieldElement (1, 2)
	1632 astore (1, 2)
	1633 #22 (1, 2)
	1634 aload_0 (1, 2)
	1635 bipush (1, 2)
	1636 7 (1, 2)
	1637 anewarray (1, 2)
	1638 org/apache/commons/math3/RealFieldElement (1, 2)
	1640 dup (1, 2)
	1641 iconst_0 (1, 2)
	1642 aload (1, 2)
	1643 #16 (1, 2)
	1644 aastore (1, 2)
	1645 dup (1, 2)
	1646 iconst_1 (1, 2)
	1647 aload (1, 2)
	1648 #17 (1, 2)
	1649 aastore (1, 2)
	1650 dup (1, 2)
	1651 iconst_2 (1, 2)
	1652 aload (1, 2)
	1653 #18 (1, 2)
	1654 aastore (1, 2)
	1655 dup (1, 2)
	1656 iconst_3 (1, 2)
	1657 aload (1, 2)
	1658 #19 (1, 2)
	1659 aastore (1, 2)
	1660 dup (1, 2)
	1661 iconst_4 (1, 2)
	1662 aload (1, 2)
	1663 #20 (1, 2)
	1664 aastore (1, 2)
	1665 dup (1, 2)
	1666 iconst_5 (1, 2)
	1667 aload (1, 2)
	1668 #21 (1, 2)
	1669 aastore (1, 2)
	1670 dup (1, 2)
	1671 bipush (1, 2)
	1672 6 (1, 2)
	1673 aload (1, 2)
	1674 #22 (1, 2)
	1675 aastore (1, 2)
	1676 invokevirtual (1, 2)
	1677 org/apache/commons/math3/ode/nonstiff/LutherFieldStepInterpolator.currentStateLinearCombination:([Lorg/apache/commons/math3/RealFieldElement;)[Lorg/apache/commons/math3/RealFieldElement; (1, 2)
	1679 astore (1, 2)
	1680 #13 (1, 2)
	1681 aload_0 (1, 2)
	1682 bipush (1, 2)
	1683 7 (1, 2)
	1684 anewarray (1, 2)
	1685 org/apache/commons/math3/RealFieldElement (1, 2)
	1687 dup (1, 2)
	1688 iconst_0 (1, 2)
	1689 aload (1, 2)
	1690 #6 (1, 2)
	1691 aastore (1, 2)
	1692 dup (1, 2)
	1693 iconst_1 (1, 2)
	1694 aload (1, 2)
	1695 #7 (1, 2)
	1696 aastore (1, 2)
	1697 dup (1, 2)
	1698 iconst_2 (1, 2)
	1699 aload (1, 2)
	1700 #8 (1, 2)
	1701 aastore (1, 2)
	1702 dup (1, 2)
	1703 iconst_3 (1, 2)
	1704 aload (1, 2)
	1705 #9 (1, 2)
	1706 aastore (1, 2)
	1707 dup (1, 2)
	1708 iconst_4 (1, 2)
	1709 aload (1, 2)
	1710 #10 (1, 2)
	1711 aastore (1, 2)
	1712 dup (1, 2)
	1713 iconst_5 (1, 2)
	1714 aload (1, 2)
	1715 #11 (1, 2)
	1716 aastore (1, 2)
	1717 dup (1, 2)
	1718 bipush (1, 2)
	1719 6 (1, 2)
	1720 aload (1, 2)
	1721 #12 (1, 2)
	1722 aastore (1, 2)
	1723 invokevirtual (1, 2)
	1724 org/apache/commons/math3/ode/nonstiff/LutherFieldStepInterpolator.derivativeLinearCombination:([Lorg/apache/commons/math3/RealFieldElement;)[Lorg/apache/commons/math3/RealFieldElement; (1, 2)
	1726 astore (1, 2)
	1727 #14 (1, 2)
	1728 new (0, 0)
	1729 org/apache/commons/math3/ode/FieldODEStateAndDerivative (0, 0)
	1731 dup (0, 0)
	1732 aload_2 (0, 0)
	1733 aload (0, 0)
	1734 #13 (0, 0)
	1735 aload (0, 0)
	1736 #14 (0, 0)
	1737 invokespecial (0, 0)
	1738 org/apache/commons/math3/ode/FieldODEStateAndDerivative.<init>:(Lorg/apache/commons/math3/RealFieldElement;[Lorg/apache/commons/math3/RealFieldElement;[Lorg/apache/commons/math3/RealFieldElement;)V (0, 0)
	1740 areturn (0, 0)

