Method: <init>
	0 aload_0 (0, 0)
	1 aload_1 (0, 0)
	2 invokespecial (0, 0)
	3 org/apache/commons/math3/ode/AbstractIntegrator.<init>:(Ljava/lang/String;)V (0, 0)
	5 aload_0 (0, 0)
	6 aload_2 (0, 0)
	7 putfield (0, 0)
	8 org/apache/commons/math3/ode/nonstiff/RungeKuttaIntegrator.c:[D (0, 0)
	10 aload_0 (0, 0)
	11 aload_3 (0, 0)
	12 putfield (0, 0)
	13 org/apache/commons/math3/ode/nonstiff/RungeKuttaIntegrator.a:[[D (0, 0)
	15 aload_0 (0, 0)
	16 aload (0, 0)
	17 #4 (0, 0)
	18 putfield (0, 0)
	19 org/apache/commons/math3/ode/nonstiff/RungeKuttaIntegrator.b:[D (0, 0)
	21 aload_0 (0, 0)
	22 aload (0, 0)
	23 #5 (0, 0)
	24 putfield (0, 0)
	25 org/apache/commons/math3/ode/nonstiff/RungeKuttaIntegrator.prototype:Lorg/apache/commons/math3/ode/nonstiff/RungeKuttaStepInterpolator; (0, 0)
	27 aload_0 (0, 0)
	28 dload (0, 0)
	29 #6 (0, 0)
	30 invokestatic (0, 0)
	31 org/apache/commons/math3/util/FastMath.abs:(D)D (0, 0)
	33 putfield (0, 0)
	34 org/apache/commons/math3/ode/nonstiff/RungeKuttaIntegrator.step:D (0, 0)
	36 return (0, 0)

Method: integrate
	0 aload_0 (0, 0)
	1 aload_1 (0, 0)
	2 dload_2 (0, 0)
	3 invokevirtual (0, 0)
	4 org/apache/commons/math3/ode/nonstiff/RungeKuttaIntegrator.sanityChecks:(Lorg/apache/commons/math3/ode/ExpandableStatefulODE;D)V (0, 0)
	6 aload_0 (0, 0)
	7 aload_1 (0, 0)
	8 invokevirtual (0, 0)
	9 org/apache/commons/math3/ode/nonstiff/RungeKuttaIntegrator.setEquations:(Lorg/apache/commons/math3/ode/ExpandableStatefulODE;)V (0, 0)
	11 dload_2 (1, 4)
	12 aload_1 (1, 4)
	13 invokevirtual (1, 4)
	14 org/apache/commons/math3/ode/ExpandableStatefulODE.getTime:()D (1, 4)
	16 dcmpl (1, 4)
	17 ifle (1, 4)
	18 7 (1, 4)
	20 iconst_1 (1, 4)
	21 goto (1, 4)
	22 4 (1, 4)
	24 iconst_0 (1, 4)
	25 istore (1, 4)
	26 #4 (1, 4)
	27 aload_1 (1, 4)
	28 invokevirtual (1, 4)
	29 org/apache/commons/math3/ode/ExpandableStatefulODE.getCompleteState:()[D (1, 4)
	31 astore (1, 4)
	32 #5 (1, 4)
	33 aload (1, 4)
	34 #5 (1, 4)
	35 invokevirtual (1, 4)
	36 [D.clone:()Ljava/lang/Object; (1, 4)
	38 checkcast (1, 4)
	39 [D (1, 4)
	41 astore (1, 4)
	42 #6 (1, 4)
	43 aload_0 (1, 4)
	44 getfield (1, 4)
	45 org/apache/commons/math3/ode/nonstiff/RungeKuttaIntegrator.c:[D (1, 4)
	47 arraylength (1, 4)
	48 iconst_1 (1, 4)
	49 iadd (1, 4)
	50 istore (1, 4)
	51 #7 (1, 4)
	52 iload (1, 4)
	53 #7 (1, 4)
	54 anewarray (1, 4)
	55 [D (1, 4)
	57 astore (1, 4)
	58 #8 (1, 4)
	59 iconst_0 (2, 4)
	60 istore (2, 4)
	61 #9 (2, 4)
	62 iload (2, 4)
	63 #9 (2, 4)
	64 iload (2, 4)
	65 #7 (2, 4)
	66 if_icmpge (2, 4)
	67 19 (2, 4)
	69 aload (2, 4)
	70 #8 (2, 4)
	71 iload (2, 4)
	72 #9 (2, 4)
	73 aload (2, 4)
	74 #5 (2, 4)
	75 arraylength (2, 4)
	76 newarray (2, 4)
	77 7 (2, 4)
	78 aastore (2, 4)
	79 iinc (2, 4)
	80 #9 (2, 4)
	81 -89 (2, 4)
	82 goto (2, 4)
	83 -20 (2, 4)
	85 aload (1, 4)
	86 #5 (1, 4)
	87 invokevirtual (1, 4)
	88 [D.clone:()Ljava/lang/Object; (1, 4)
	90 checkcast (1, 4)
	91 [D (1, 4)
	93 astore (1, 4)
	94 #9 (1, 4)
	95 aload (1, 4)
	96 #5 (1, 4)
	97 arraylength (1, 4)
	98 newarray (1, 4)
	99 7 (1, 4)
	100 astore (1, 4)
	101 #10 (1, 4)
	102 aload_0 (1, 4)
	103 getfield (1, 4)
	104 org/apache/commons/math3/ode/nonstiff/RungeKuttaIntegrator.prototype:Lorg/apache/commons/math3/ode/nonstiff/RungeKuttaStepInterpolator; (1, 4)
	106 invokevirtual (1, 4)
	107 org/apache/commons/math3/ode/nonstiff/RungeKuttaStepInterpolator.copy:()Lorg/apache/commons/math3/ode/sampling/StepInterpolator; (1, 4)
	109 checkcast (1, 4)
	110 org/apache/commons/math3/ode/nonstiff/RungeKuttaStepInterpolator (1, 4)
	112 astore (1, 4)
	113 #11 (1, 4)
	114 aload (2, 4)
	115 #11 (2, 4)
	116 aload_0 (2, 4)
	117 aload (2, 4)
	118 #9 (2, 4)
	119 aload (2, 4)
	120 #8 (2, 4)
	121 iload (2, 4)
	122 #4 (2, 4)
	123 aload_1 (2, 4)
	124 invokevirtual (2, 4)
	125 org/apache/commons/math3/ode/ExpandableStatefulODE.getPrimaryMapper:()Lorg/apache/commons/math3/ode/EquationsMapper; (2, 4)
	127 aload_1 (2, 4)
	128 invokevirtual (2, 4)
	129 org/apache/commons/math3/ode/ExpandableStatefulODE.getSecondaryMappers:()[Lorg/apache/commons/math3/ode/EquationsMapper; (2, 4)
	131 invokevirtual (2, 4)
	132 org/apache/commons/math3/ode/nonstiff/RungeKuttaStepInterpolator.reinitialize:(Lorg/apache/commons/math3/ode/AbstractIntegrator;[D[[DZLorg/apache/commons/math3/ode/EquationsMapper;[Lorg/apache/commons/math3/ode/EquationsMapper;)V (2, 4)
	134 aload (2, 4)
	135 #11 (2, 4)
	136 aload_1 (2, 4)
	137 invokevirtual (2, 4)
	138 org/apache/commons/math3/ode/ExpandableStatefulODE.getTime:()D (2, 4)
	140 invokevirtual (2, 4)
	141 org/apache/commons/math3/ode/nonstiff/RungeKuttaStepInterpolator.storeTime:(D)V (2, 4)
	143 aload_0 (2, 4)
	144 aload_1 (2, 4)
	145 invokevirtual (2, 4)
	146 org/apache/commons/math3/ode/ExpandableStatefulODE.getTime:()D (2, 4)
	148 putfield (2, 4)
	149 org/apache/commons/math3/ode/nonstiff/RungeKuttaIntegrator.stepStart:D (2, 4)
	151 iload (3, 1)
	152 #4 (3, 1)
	153 ifeq (3, 1)
	154 41 (3, 1)
	156 aload_0 (4, 1)
	157 getfield (4, 1)
	158 org/apache/commons/math3/ode/nonstiff/RungeKuttaIntegrator.stepStart:D (4, 1)
	160 aload_0 (4, 1)
	161 getfield (4, 1)
	162 org/apache/commons/math3/ode/nonstiff/RungeKuttaIntegrator.step:D (4, 1)
	164 dadd (4, 1)
	165 dload_2 (4, 1)
	166 dcmpl (4, 1)
	167 iflt (4, 1)
	168 16 (4, 1)
	170 aload_0 (4, 1)
	171 dload_2 (4, 1)
	172 aload_0 (4, 1)
	173 getfield (4, 1)
	174 org/apache/commons/math3/ode/nonstiff/RungeKuttaIntegrator.stepStart:D (4, 1)
	176 dsub (4, 1)
	177 putfield (4, 1)
	178 org/apache/commons/math3/ode/nonstiff/RungeKuttaIntegrator.stepSize:D (4, 1)
	180 goto (4, 1)
	181 50 (4, 1)
	183 aload_0 (5, 2)
	184 aload_0 (5, 2)
	185 getfield (5, 2)
	186 org/apache/commons/math3/ode/nonstiff/RungeKuttaIntegrator.step:D (5, 2)
	188 putfield (5, 2)
	189 org/apache/commons/math3/ode/nonstiff/RungeKuttaIntegrator.stepSize:D (5, 2)
	191 goto (5, 2)
	192 39 (5, 2)
	194 aload_0 (5, 1)
	195 getfield (5, 1)
	196 org/apache/commons/math3/ode/nonstiff/RungeKuttaIntegrator.stepStart:D (5, 1)
	198 aload_0 (5, 1)
	199 getfield (5, 1)
	200 org/apache/commons/math3/ode/nonstiff/RungeKuttaIntegrator.step:D (5, 1)
	202 dsub (5, 1)
	203 dload_2 (5, 1)
	204 dcmpg (5, 1)
	205 ifgt (5, 1)
	206 16 (5, 1)
	208 aload_0 (5, 1)
	209 dload_2 (5, 1)
	210 aload_0 (5, 1)
	211 getfield (5, 1)
	212 org/apache/commons/math3/ode/nonstiff/RungeKuttaIntegrator.stepStart:D (5, 1)
	214 dsub (5, 1)
	215 putfield (5, 1)
	216 org/apache/commons/math3/ode/nonstiff/RungeKuttaIntegrator.stepSize:D (5, 1)
	218 goto (5, 1)
	219 12 (5, 1)
	221 aload_0 (6, 2)
	222 aload_0 (6, 2)
	223 getfield (6, 2)
	224 org/apache/commons/math3/ode/nonstiff/RungeKuttaIntegrator.step:D (6, 2)
	226 dneg (6, 2)
	227 putfield (6, 2)
	228 org/apache/commons/math3/ode/nonstiff/RungeKuttaIntegrator.stepSize:D (6, 2)
	230 aload_0 (2, 4)
	231 aload_1 (2, 4)
	232 invokevirtual (2, 4)
	233 org/apache/commons/math3/ode/ExpandableStatefulODE.getTime:()D (2, 4)
	235 aload (2, 4)
	236 #5 (2, 4)
	237 dload_2 (2, 4)
	238 invokevirtual (2, 4)
	239 org/apache/commons/math3/ode/nonstiff/RungeKuttaIntegrator.initIntegration:(D[DD)V (2, 4)
	241 aload_0 (2, 4)
	242 iconst_0 (2, 4)
	243 putfield (2, 4)
	244 org/apache/commons/math3/ode/nonstiff/RungeKuttaIntegrator.isLastStep:Z (2, 4)
	246 aload (3, 1)
	247 #11 (3, 1)
	248 invokevirtual (3, 1)
	249 org/apache/commons/math3/ode/nonstiff/RungeKuttaStepInterpolator.shift:()V (3, 1)
	251 aload_0 (3, 1)
	252 aload_0 (3, 1)
	253 getfield (3, 1)
	254 org/apache/commons/math3/ode/nonstiff/RungeKuttaIntegrator.stepStart:D (3, 1)
	256 aload (3, 1)
	257 #6 (3, 1)
	258 aload (3, 1)
	259 #8 (3, 1)
	260 iconst_0 (3, 1)
	261 aaload (3, 1)
	262 invokevirtual (3, 1)
	263 org/apache/commons/math3/ode/nonstiff/RungeKuttaIntegrator.computeDerivatives:(D[D[D)V (3, 1)
	265 iconst_1 (4, 4)
	266 istore (4, 4)
	267 #12 (4, 4)
	268 iload (4, 4)
	269 #12 (4, 4)
	270 iload (4, 4)
	271 #7 (4, 4)
	272 if_icmpge (4, 4)
	273 137 (4, 4)
	275 iconst_0 (5, 4)
	276 istore (5, 4)
	277 #13 (5, 4)
	278 iload (5, 4)
	279 #13 (5, 4)
	280 aload (5, 4)
	281 #5 (5, 4)
	282 arraylength (5, 4)
	283 if_icmpge (5, 4)
	284 90 (5, 4)
	286 aload_0 (5, 4)
	287 getfield (5, 4)
	288 org/apache/commons/math3/ode/nonstiff/RungeKuttaIntegrator.a:[[D (5, 4)
	290 iload (5, 4)
	291 #12 (5, 4)
	292 iconst_1 (5, 4)
	293 isub (5, 4)
	294 aaload (5, 4)
	295 iconst_0 (5, 4)
	296 daload (5, 4)
	297 aload (5, 4)
	298 #8 (5, 4)
	299 iconst_0 (5, 4)
	300 aaload (5, 4)
	301 iload (5, 4)
	302 #13 (5, 4)
	303 daload (5, 4)
	304 dmul (5, 4)
	305 dstore (5, 4)
	306 #14 (5, 4)
	307 iconst_1 (6, 4)
	308 istore (6, 4)
	309 #16 (6, 4)
	310 iload (6, 4)
	311 #16 (6, 4)
	312 iload (6, 4)
	313 #12 (6, 4)
	314 if_icmpge (6, 4)
	315 35 (6, 4)
	317 dload (6, 4)
	318 #14 (6, 4)
	319 aload_0 (6, 4)
	320 getfield (6, 4)
	321 org/apache/commons/math3/ode/nonstiff/RungeKuttaIntegrator.a:[[D (6, 4)
	323 iload (6, 4)
	324 #12 (6, 4)
	325 iconst_1 (6, 4)
	326 isub (6, 4)
	327 aaload (6, 4)
	328 iload (6, 4)
	329 #16 (6, 4)
	330 daload (6, 4)
	331 aload (6, 4)
	332 #8 (6, 4)
	333 iload (6, 4)
	334 #16 (6, 4)
	335 aaload (6, 4)
	336 iload (6, 4)
	337 #13 (6, 4)
	338 daload (6, 4)
	339 dmul (6, 4)
	340 dadd (6, 4)
	341 dstore (6, 4)
	342 #14 (6, 4)
	343 iinc (6, 4)
	344 #16 (6, 4)
	345 -89 (6, 4)
	346 goto (6, 4)
	347 -36 (6, 4)
	349 aload (5, 4)
	350 #9 (5, 4)
	351 iload (5, 4)
	352 #13 (5, 4)
	353 aload (5, 4)
	354 #6 (5, 4)
	355 iload (5, 4)
	356 #13 (5, 4)
	357 daload (5, 4)
	358 aload_0 (5, 4)
	359 getfield (5, 4)
	360 org/apache/commons/math3/ode/nonstiff/RungeKuttaIntegrator.stepSize:D (5, 4)
	362 dload (5, 4)
	363 #14 (5, 4)
	364 dmul (5, 4)
	365 dadd (5, 4)
	366 dastore (5, 4)
	367 iinc (5, 4)
	368 #13 (5, 4)
	369 -89 (5, 4)
	370 goto (5, 4)
	371 -92 (5, 4)
	373 aload_0 (4, 4)
	374 aload_0 (4, 4)
	375 getfield (4, 4)
	376 org/apache/commons/math3/ode/nonstiff/RungeKuttaIntegrator.stepStart:D (4, 4)
	378 aload_0 (4, 4)
	379 getfield (4, 4)
	380 org/apache/commons/math3/ode/nonstiff/RungeKuttaIntegrator.c:[D (4, 4)
	382 iload (4, 4)
	383 #12 (4, 4)
	384 iconst_1 (4, 4)
	385 isub (4, 4)
	386 daload (4, 4)
	387 aload_0 (4, 4)
	388 getfield (4, 4)
	389 org/apache/commons/math3/ode/nonstiff/RungeKuttaIntegrator.stepSize:D (4, 4)
	391 dmul (4, 4)
	392 dadd (4, 4)
	393 aload (4, 4)
	394 #9 (4, 4)
	395 aload (4, 4)
	396 #8 (4, 4)
	397 iload (4, 4)
	398 #12 (4, 4)
	399 aaload (4, 4)
	400 invokevirtual (4, 4)
	401 org/apache/commons/math3/ode/nonstiff/RungeKuttaIntegrator.computeDerivatives:(D[D[D)V (4, 4)
	403 iinc (4, 4)
	404 #12 (4, 4)
	405 -89 (4, 4)
	406 goto (4, 4)
	407 -138 (4, 4)
	409 iconst_0 (4, 4)
	410 istore (4, 4)
	411 #12 (4, 4)
	412 iload (4, 4)
	413 #12 (4, 4)
	414 aload (4, 4)
	415 #5 (4, 4)
	416 arraylength (4, 4)
	417 if_icmpge (4, 4)
	418 80 (4, 4)
	420 aload_0 (4, 4)
	421 getfield (4, 4)
	422 org/apache/commons/math3/ode/nonstiff/RungeKuttaIntegrator.b:[D (4, 4)
	424 iconst_0 (4, 4)
	425 daload (4, 4)
	426 aload (4, 4)
	427 #8 (4, 4)
	428 iconst_0 (4, 4)
	429 aaload (4, 4)
	430 iload (4, 4)
	431 #12 (4, 4)
	432 daload (4, 4)
	433 dmul (4, 4)
	434 dstore (4, 4)
	435 #13 (4, 4)
	436 iconst_1 (5, 4)
	437 istore (5, 4)
	438 #15 (5, 4)
	439 iload (5, 4)
	440 #15 (5, 4)
	441 iload (5, 4)
	442 #7 (5, 4)
	443 if_icmpge (5, 4)
	444 30 (5, 4)
	446 dload (5, 4)
	447 #13 (5, 4)
	448 aload_0 (5, 4)
	449 getfield (5, 4)
	450 org/apache/commons/math3/ode/nonstiff/RungeKuttaIntegrator.b:[D (5, 4)
	452 iload (5, 4)
	453 #15 (5, 4)
	454 daload (5, 4)
	455 aload (5, 4)
	456 #8 (5, 4)
	457 iload (5, 4)
	458 #15 (5, 4)
	459 aaload (5, 4)
	460 iload (5, 4)
	461 #12 (5, 4)
	462 daload (5, 4)
	463 dmul (5, 4)
	464 dadd (5, 4)
	465 dstore (5, 4)
	466 #13 (5, 4)
	467 iinc (5, 4)
	468 #15 (5, 4)
	469 -89 (5, 4)
	470 goto (5, 4)
	471 -31 (5, 4)
	473 aload (4, 4)
	474 #9 (4, 4)
	475 iload (4, 4)
	476 #12 (4, 4)
	477 aload (4, 4)
	478 #6 (4, 4)
	479 iload (4, 4)
	480 #12 (4, 4)
	481 daload (4, 4)
	482 aload_0 (4, 4)
	483 getfield (4, 4)
	484 org/apache/commons/math3/ode/nonstiff/RungeKuttaIntegrator.stepSize:D (4, 4)
	486 dload (4, 4)
	487 #13 (4, 4)
	488 dmul (4, 4)
	489 dadd (4, 4)
	490 dastore (4, 4)
	491 iinc (4, 4)
	492 #12 (4, 4)
	493 -89 (4, 4)
	494 goto (4, 4)
	495 -82 (4, 4)
	497 aload (3, 1)
	498 #11 (3, 1)
	499 aload_0 (3, 1)
	500 getfield (3, 1)
	501 org/apache/commons/math3/ode/nonstiff/RungeKuttaIntegrator.stepStart:D (3, 1)
	503 aload_0 (3, 1)
	504 getfield (3, 1)
	505 org/apache/commons/math3/ode/nonstiff/RungeKuttaIntegrator.stepSize:D (3, 1)
	507 dadd (3, 1)
	508 invokevirtual (3, 1)
	509 org/apache/commons/math3/ode/nonstiff/RungeKuttaStepInterpolator.storeTime:(D)V (3, 1)
	511 aload (3, 1)
	512 #9 (3, 1)
	513 iconst_0 (3, 1)
	514 aload (3, 1)
	515 #6 (3, 1)
	516 iconst_0 (3, 1)
	517 aload (3, 1)
	518 #5 (3, 1)
	519 arraylength (3, 1)
	520 invokestatic (3, 1)
	521 java/lang/System.arraycopy:(Ljava/lang/Object;ILjava/lang/Object;II)V (3, 1)
	523 aload (3, 1)
	524 #8 (3, 1)
	525 iload (3, 1)
	526 #7 (3, 1)
	527 iconst_1 (3, 1)
	528 isub (3, 1)
	529 aaload (3, 1)
	530 iconst_0 (3, 1)
	531 aload (3, 1)
	532 #10 (3, 1)
	533 iconst_0 (3, 1)
	534 aload (3, 1)
	535 #5 (3, 1)
	536 arraylength (3, 1)
	537 invokestatic (3, 1)
	538 java/lang/System.arraycopy:(Ljava/lang/Object;ILjava/lang/Object;II)V (3, 1)
	540 aload_0 (3, 1)
	541 aload_0 (3, 1)
	542 aload (3, 1)
	543 #11 (3, 1)
	544 aload (3, 1)
	545 #6 (3, 1)
	546 aload (3, 1)
	547 #10 (3, 1)
	548 dload_2 (3, 1)
	549 invokevirtual (3, 1)
	550 org/apache/commons/math3/ode/nonstiff/RungeKuttaIntegrator.acceptStep:(Lorg/apache/commons/math3/ode/sampling/AbstractStepInterpolator;[D[DD)D (3, 1)
	552 putfield (3, 1)
	553 org/apache/commons/math3/ode/nonstiff/RungeKuttaIntegrator.stepStart:D (3, 1)
	555 aload_0 (4, 1)
	556 getfield (4, 1)
	557 org/apache/commons/math3/ode/nonstiff/RungeKuttaIntegrator.isLastStep:Z (4, 1)
	559 ifne (4, 1)
	560 72 (4, 1)
	562 aload (4, 1)
	563 #11 (4, 1)
	564 aload_0 (4, 1)
	565 getfield (4, 1)
	566 org/apache/commons/math3/ode/nonstiff/RungeKuttaIntegrator.stepStart:D (4, 1)
	568 invokevirtual (4, 1)
	569 org/apache/commons/math3/ode/nonstiff/RungeKuttaStepInterpolator.storeTime:(D)V (4, 1)
	571 aload_0 (5, 4)
	572 getfield (5, 4)
	573 org/apache/commons/math3/ode/nonstiff/RungeKuttaIntegrator.stepStart:D (5, 4)
	575 aload_0 (5, 4)
	576 getfield (5, 4)
	577 org/apache/commons/math3/ode/nonstiff/RungeKuttaIntegrator.stepSize:D (5, 4)
	579 dadd (5, 4)
	580 dstore (5, 4)
	581 #12 (5, 4)
	582 iload (6, 4)
	583 #4 (6, 4)
	584 ifeq (6, 4)
	585 18 (6, 4)
	587 dload (6, 4)
	588 #12 (6, 4)
	589 dload_2 (6, 4)
	590 dcmpl (6, 4)
	591 iflt (6, 4)
	592 7 (6, 4)
	594 iconst_1 (6, 4)
	595 goto (6, 4)
	596 19 (6, 4)
	598 iconst_0 (6, 4)
	599 goto (6, 4)
	600 15 (6, 4)
	602 dload (6, 4)
	603 #12 (6, 4)
	604 dload_2 (6, 4)
	605 dcmpg (6, 4)
	606 ifgt (6, 4)
	607 7 (6, 4)
	609 iconst_1 (6, 4)
	610 goto (6, 4)
	611 4 (6, 4)
	613 iconst_0 (6, 4)
	614 istore (6, 4)
	615 #14 (6, 4)
	616 iload (7, 1)
	617 #14 (7, 1)
	618 ifeq (7, 1)
	619 13 (7, 1)
	621 aload_0 (7, 1)
	622 dload_2 (7, 1)
	623 aload_0 (7, 1)
	624 getfield (7, 1)
	625 org/apache/commons/math3/ode/nonstiff/RungeKuttaIntegrator.stepStart:D (7, 1)
	627 dsub (7, 1)
	628 putfield (7, 1)
	629 org/apache/commons/math3/ode/nonstiff/RungeKuttaIntegrator.stepSize:D (7, 1)
	631 aload_0 (4, 3)
	632 getfield (4, 3)
	633 org/apache/commons/math3/ode/nonstiff/RungeKuttaIntegrator.isLastStep:Z (4, 3)
	635 ifeq (4, 3)
	636 -389 (4, 3)
	638 aload_1 (4, 3)
	639 aload_0 (4, 3)
	640 getfield (4, 3)
	641 org/apache/commons/math3/ode/nonstiff/RungeKuttaIntegrator.stepStart:D (4, 3)
	643 invokevirtual (4, 3)
	644 org/apache/commons/math3/ode/ExpandableStatefulODE.setTime:(D)V (4, 3)
	646 aload_1 (4, 3)
	647 aload (4, 3)
	648 #6 (4, 3)
	649 invokevirtual (4, 3)
	650 org/apache/commons/math3/ode/ExpandableStatefulODE.setCompleteState:([D)V (4, 3)
	652 aload_0 (4, 3)
	653 ldc2_w (4, 3)
	654 nan (4, 3)
	656 putfield (4, 3)
	657 org/apache/commons/math3/ode/nonstiff/RungeKuttaIntegrator.stepStart:D (4, 3)
	659 aload_0 (4, 3)
	660 ldc2_w (4, 3)
	661 nan (4, 3)
	663 putfield (4, 3)
	664 org/apache/commons/math3/ode/nonstiff/RungeKuttaIntegrator.stepSize:D (4, 3)
	666 return (0, 3)

Method: singleStep
	0 aload (0, 0)
	1 #4 (0, 0)
	2 invokevirtual (0, 0)
	3 [D.clone:()Ljava/lang/Object; (0, 0)
	5 checkcast (0, 0)
	6 [D (0, 0)
	8 astore (0, 0)
	9 #7 (0, 0)
	10 aload_0 (0, 0)
	11 getfield (0, 0)
	12 org/apache/commons/math3/ode/nonstiff/RungeKuttaIntegrator.c:[D (0, 0)
	14 arraylength (0, 0)
	15 iconst_1 (0, 0)
	16 iadd (0, 0)
	17 istore (0, 0)
	18 #8 (0, 0)
	19 iload (0, 0)
	20 #8 (0, 0)
	21 anewarray (0, 0)
	22 [D (0, 0)
	24 astore (0, 0)
	25 #9 (0, 0)
	26 iconst_0 (1, 4)
	27 istore (1, 4)
	28 #10 (1, 4)
	29 iload (1, 4)
	30 #10 (1, 4)
	31 iload (1, 4)
	32 #8 (1, 4)
	33 if_icmpge (1, 4)
	34 19 (1, 4)
	36 aload (1, 4)
	37 #9 (1, 4)
	38 iload (1, 4)
	39 #10 (1, 4)
	40 aload (1, 4)
	41 #4 (1, 4)
	42 arraylength (1, 4)
	43 newarray (1, 4)
	44 7 (1, 4)
	45 aastore (1, 4)
	46 iinc (1, 4)
	47 #10 (1, 4)
	48 -89 (1, 4)
	49 goto (1, 4)
	50 -20 (1, 4)
	52 aload (0, 0)
	53 #4 (0, 0)
	54 invokevirtual (0, 0)
	55 [D.clone:()Ljava/lang/Object; (0, 0)
	57 checkcast (0, 0)
	58 [D (0, 0)
	60 astore (0, 0)
	61 #10 (0, 0)
	62 dload (0, 0)
	63 #5 (0, 0)
	64 dload_2 (0, 0)
	65 dsub (0, 0)
	66 dstore (0, 0)
	67 #11 (0, 0)
	68 aload_1 (0, 0)
	69 dload_2 (0, 0)
	70 aload (0, 0)
	71 #7 (0, 0)
	72 aload (0, 0)
	73 #9 (0, 0)
	74 iconst_0 (0, 0)
	75 aaload (0, 0)
	76 invokeinterface (0, 0)
	77 org/apache/commons/math3/ode/FirstOrderDifferentialEquations.java/lang/System (0, 0)
	79 0 (0, 0)
	81 iconst_1 (1, 4)
	82 istore (1, 4)
	83 #13 (1, 4)
	84 iload (1, 4)
	85 #13 (1, 4)
	86 iload (1, 4)
	87 #8 (1, 4)
	88 if_icmpge (1, 4)
	89 132 (1, 4)
	91 iconst_0 (2, 4)
	92 istore (2, 4)
	93 #14 (2, 4)
	94 iload (2, 4)
	95 #14 (2, 4)
	96 aload (2, 4)
	97 #4 (2, 4)
	98 arraylength (2, 4)
	99 if_icmpge (2, 4)
	100 88 (2, 4)
	102 aload_0 (2, 4)
	103 getfield (2, 4)
	104 org/apache/commons/math3/ode/nonstiff/RungeKuttaIntegrator.a:[[D (2, 4)
	106 iload (2, 4)
	107 #13 (2, 4)
	108 iconst_1 (2, 4)
	109 isub (2, 4)
	110 aaload (2, 4)
	111 iconst_0 (2, 4)
	112 daload (2, 4)
	113 aload (2, 4)
	114 #9 (2, 4)
	115 iconst_0 (2, 4)
	116 aaload (2, 4)
	117 iload (2, 4)
	118 #14 (2, 4)
	119 daload (2, 4)
	120 dmul (2, 4)
	121 dstore (2, 4)
	122 #15 (2, 4)
	123 iconst_1 (3, 4)
	124 istore (3, 4)
	125 #17 (3, 4)
	126 iload (3, 4)
	127 #17 (3, 4)
	128 iload (3, 4)
	129 #13 (3, 4)
	130 if_icmpge (3, 4)
	131 35 (3, 4)
	133 dload (3, 4)
	134 #15 (3, 4)
	135 aload_0 (3, 4)
	136 getfield (3, 4)
	137 org/apache/commons/math3/ode/nonstiff/RungeKuttaIntegrator.a:[[D (3, 4)
	139 iload (3, 4)
	140 #13 (3, 4)
	141 iconst_1 (3, 4)
	142 isub (3, 4)
	143 aaload (3, 4)
	144 iload (3, 4)
	145 #17 (3, 4)
	146 daload (3, 4)
	147 aload (3, 4)
	148 #9 (3, 4)
	149 iload (3, 4)
	150 #17 (3, 4)
	151 aaload (3, 4)
	152 iload (3, 4)
	153 #14 (3, 4)
	154 daload (3, 4)
	155 dmul (3, 4)
	156 dadd (3, 4)
	157 dstore (3, 4)
	158 #15 (3, 4)
	159 iinc (3, 4)
	160 #17 (3, 4)
	161 -89 (3, 4)
	162 goto (3, 4)
	163 -36 (3, 4)
	165 aload (2, 4)
	166 #10 (2, 4)
	167 iload (2, 4)
	168 #14 (2, 4)
	169 aload (2, 4)
	170 #7 (2, 4)
	171 iload (2, 4)
	172 #14 (2, 4)
	173 daload (2, 4)
	174 dload (2, 4)
	175 #11 (2, 4)
	176 dload (2, 4)
	177 #15 (2, 4)
	178 dmul (2, 4)
	179 dadd (2, 4)
	180 dastore (2, 4)
	181 iinc (2, 4)
	182 #14 (2, 4)
	183 -89 (2, 4)
	184 goto (2, 4)
	185 -90 (2, 4)
	187 aload_1 (1, 4)
	188 dload_2 (1, 4)
	189 aload_0 (1, 4)
	190 getfield (1, 4)
	191 org/apache/commons/math3/ode/nonstiff/RungeKuttaIntegrator.c:[D (1, 4)
	193 iload (1, 4)
	194 #13 (1, 4)
	195 iconst_1 (1, 4)
	196 isub (1, 4)
	197 daload (1, 4)
	198 dload (1, 4)
	199 #11 (1, 4)
	200 dmul (1, 4)
	201 dadd (1, 4)
	202 aload (1, 4)
	203 #10 (1, 4)
	204 aload (1, 4)
	205 #9 (1, 4)
	206 iload (1, 4)
	207 #13 (1, 4)
	208 aaload (1, 4)
	209 invokeinterface (1, 4)
	210 org/apache/commons/math3/ode/FirstOrderDifferentialEquations.java/lang/System (1, 4)
	212 0 (1, 4)
	214 iinc (1, 4)
	215 #13 (1, 4)
	216 -89 (1, 4)
	217 goto (1, 4)
	218 -133 (1, 4)
	220 iconst_0 (1, 4)
	221 istore (1, 4)
	222 #13 (1, 4)
	223 iload (1, 4)
	224 #13 (1, 4)
	225 aload (1, 4)
	226 #4 (1, 4)
	227 arraylength (1, 4)
	228 if_icmpge (1, 4)
	229 75 (1, 4)
	231 aload_0 (1, 4)
	232 getfield (1, 4)
	233 org/apache/commons/math3/ode/nonstiff/RungeKuttaIntegrator.b:[D (1, 4)
	235 iconst_0 (1, 4)
	236 daload (1, 4)
	237 aload (1, 4)
	238 #9 (1, 4)
	239 iconst_0 (1, 4)
	240 aaload (1, 4)
	241 iload (1, 4)
	242 #13 (1, 4)
	243 daload (1, 4)
	244 dmul (1, 4)
	245 dstore (1, 4)
	246 #14 (1, 4)
	247 iconst_1 (2, 4)
	248 istore (2, 4)
	249 #16 (2, 4)
	250 iload (2, 4)
	251 #16 (2, 4)
	252 iload (2, 4)
	253 #8 (2, 4)
	254 if_icmpge (2, 4)
	255 30 (2, 4)
	257 dload (2, 4)
	258 #14 (2, 4)
	259 aload_0 (2, 4)
	260 getfield (2, 4)
	261 org/apache/commons/math3/ode/nonstiff/RungeKuttaIntegrator.b:[D (2, 4)
	263 iload (2, 4)
	264 #16 (2, 4)
	265 daload (2, 4)
	266 aload (2, 4)
	267 #9 (2, 4)
	268 iload (2, 4)
	269 #16 (2, 4)
	270 aaload (2, 4)
	271 iload (2, 4)
	272 #13 (2, 4)
	273 daload (2, 4)
	274 dmul (2, 4)
	275 dadd (2, 4)
	276 dstore (2, 4)
	277 #14 (2, 4)
	278 iinc (2, 4)
	279 #16 (2, 4)
	280 -89 (2, 4)
	281 goto (2, 4)
	282 -31 (2, 4)
	284 aload (1, 4)
	285 #7 (1, 4)
	286 iload (1, 4)
	287 #13 (1, 4)
	288 dup2 (1, 4)
	289 daload (1, 4)
	290 dload (1, 4)
	291 #11 (1, 4)
	292 dload (1, 4)
	293 #14 (1, 4)
	294 dmul (1, 4)
	295 dadd (1, 4)
	296 dastore (1, 4)
	297 iinc (1, 4)
	298 #13 (1, 4)
	299 -89 (1, 4)
	300 goto (1, 4)
	301 -77 (1, 4)
	303 aload (0, 0)
	304 #7 (0, 0)
	305 areturn (0, 0)

