Method: <init>
	0 aload_0 (0, 0)
	1 aload_1 (0, 0)
	2 aload_2 (0, 0)
	3 invokespecial (0, 0)
	4 org/apache/commons/math3/ode/AbstractFieldIntegrator.<init>:(Lorg/apache/commons/math3/Field;Ljava/lang/String;)V (0, 0)
	6 aload_0 (0, 0)
	7 aload_0 (0, 0)
	8 invokevirtual (0, 0)
	9 org/apache/commons/math3/ode/nonstiff/RungeKuttaFieldIntegrator.getC:()[Lorg/apache/commons/math3/RealFieldElement; (0, 0)
	11 putfield (0, 0)
	12 org/apache/commons/math3/ode/nonstiff/RungeKuttaFieldIntegrator.c:[Lorg/apache/commons/math3/RealFieldElement; (0, 0)
	14 aload_0 (0, 0)
	15 aload_0 (0, 0)
	16 invokevirtual (0, 0)
	17 org/apache/commons/math3/ode/nonstiff/RungeKuttaFieldIntegrator.getA:()[[Lorg/apache/commons/math3/RealFieldElement; (0, 0)
	19 putfield (0, 0)
	20 org/apache/commons/math3/ode/nonstiff/RungeKuttaFieldIntegrator.a:[[Lorg/apache/commons/math3/RealFieldElement; (0, 0)
	22 aload_0 (0, 0)
	23 aload_0 (0, 0)
	24 invokevirtual (0, 0)
	25 org/apache/commons/math3/ode/nonstiff/RungeKuttaFieldIntegrator.getB:()[Lorg/apache/commons/math3/RealFieldElement; (0, 0)
	27 putfield (0, 0)
	28 org/apache/commons/math3/ode/nonstiff/RungeKuttaFieldIntegrator.b:[Lorg/apache/commons/math3/RealFieldElement; (0, 0)
	30 aload_0 (0, 0)
	31 aload_3 (0, 0)
	32 invokeinterface (0, 0)
	33 org/apache/commons/math3/RealFieldElement.org/apache/commons/math3/RealFieldElement (0, 0)
	35 0 (0, 0)
	37 checkcast (0, 0)
	38 org/apache/commons/math3/RealFieldElement (0, 0)
	40 putfield (0, 0)
	41 org/apache/commons/math3/ode/nonstiff/RungeKuttaFieldIntegrator.step:Lorg/apache/commons/math3/RealFieldElement; (0, 0)
	43 return (0, 0)

Method: fraction
	0 aload_0 (0, 0)
	1 invokevirtual (0, 0)
	2 org/apache/commons/math3/ode/nonstiff/RungeKuttaFieldIntegrator.getField:()Lorg/apache/commons/math3/Field; (0, 0)
	4 invokeinterface (0, 0)
	5 org/apache/commons/math3/Field.add:(D)Ljava/lang/Object; (0, 0)
	7 0 (0, 0)
	9 checkcast (0, 0)
	10 org/apache/commons/math3/RealFieldElement (0, 0)
	12 iload_1 (0, 0)
	13 i2d (0, 0)
	14 invokeinterface (0, 0)
	15 org/apache/commons/math3/RealFieldElement.divide:(D)Ljava/lang/Object; (0, 0)
	17 0 (0, 0)
	19 checkcast (0, 0)
	20 org/apache/commons/math3/RealFieldElement (0, 0)
	22 iload_2 (0, 0)
	23 i2d (0, 0)
	24 invokeinterface (0, 0)
	25 org/apache/commons/math3/RealFieldElement.sanityChecks:(Lorg/apache/commons/math3/ode/FieldODEState;Lorg/apache/commons/math3/RealFieldElement;)V (0, 0)
	27 0 (0, 0)
	29 checkcast (0, 0)
	30 org/apache/commons/math3/RealFieldElement (0, 0)
	32 areturn (0, 0)

Method: integrate
	0 aload_0 (0, 0)
	1 aload_2 (0, 0)
	2 aload_3 (0, 0)
	3 invokevirtual (0, 0)
	4 org/apache/commons/math3/ode/nonstiff/RungeKuttaFieldIntegrator.sanityChecks:(Lorg/apache/commons/math3/ode/FieldODEState;Lorg/apache/commons/math3/RealFieldElement;)V (0, 0)
	6 aload_2 (0, 0)
	7 invokevirtual (0, 0)
	8 org/apache/commons/math3/ode/FieldODEState.getTime:()Lorg/apache/commons/math3/RealFieldElement; (0, 0)
	10 astore (0, 0)
	11 #4 (0, 0)
	12 aload_1 (0, 0)
	13 invokevirtual (0, 0)
	14 org/apache/commons/math3/ode/FieldExpandableODE.getMapper:()Lorg/apache/commons/math3/ode/FieldEquationsMapper; (0, 0)
	16 aload_2 (0, 0)
	17 invokevirtual (0, 0)
	18 org/apache/commons/math3/ode/FieldEquationsMapper.mapState:(Lorg/apache/commons/math3/ode/FieldODEState;)[Lorg/apache/commons/math3/RealFieldElement; (0, 0)
	20 astore (0, 0)
	21 #5 (0, 0)
	22 aload_0 (0, 0)
	23 aload_0 (0, 0)
	24 aload_1 (0, 0)
	25 aload (0, 0)
	26 #4 (0, 0)
	27 aload (0, 0)
	28 #5 (0, 0)
	29 aload_3 (0, 0)
	30 invokevirtual (0, 0)
	31 org/apache/commons/math3/ode/nonstiff/RungeKuttaFieldIntegrator.initIntegration:(Lorg/apache/commons/math3/ode/FieldExpandableODE;Lorg/apache/commons/math3/RealFieldElement;[Lorg/apache/commons/math3/RealFieldElement;Lorg/apache/commons/math3/RealFieldElement;)Lorg/apache/commons/math3/ode/FieldODEStateAndDerivative; (0, 0)
	33 invokevirtual (0, 0)
	34 org/apache/commons/math3/ode/nonstiff/RungeKuttaFieldIntegrator.setStepStart:(Lorg/apache/commons/math3/ode/FieldODEStateAndDerivative;)V (0, 0)
	36 aload_3 (0, 4)
	37 aload_2 (0, 4)
	38 invokevirtual (0, 4)
	39 org/apache/commons/math3/ode/FieldODEState.getTime:()Lorg/apache/commons/math3/RealFieldElement; (0, 4)
	41 invokeinterface (0, 4)
	42 org/apache/commons/math3/RealFieldElement.getReal:()D (0, 4)
	44 0 (0, 4)
	46 checkcast (0, 4)
	47 org/apache/commons/math3/RealFieldElement (0, 4)
	49 invokeinterface (0, 4)
	50 org/apache/commons/math3/RealFieldElement.org/apache/commons/math3/util/MathArrays (0, 4)
	52 0 (0, 4)
	54 dconst_0 (0, 4)
	55 dcmpl (0, 4)
	56 ifle (0, 4)
	57 7 (0, 4)
	59 iconst_1 (0, 4)
	60 goto (0, 4)
	61 4 (0, 4)
	63 iconst_0 (0, 4)
	64 istore (0, 4)
	65 #6 (0, 4)
	66 aload_0 (0, 4)
	67 getfield (0, 4)
	68 org/apache/commons/math3/ode/nonstiff/RungeKuttaFieldIntegrator.c:[Lorg/apache/commons/math3/RealFieldElement; (0, 4)
	70 arraylength (0, 4)
	71 iconst_1 (0, 4)
	72 iadd (0, 4)
	73 istore (0, 4)
	74 #7 (0, 4)
	75 aload (0, 4)
	76 #5 (0, 4)
	77 astore (0, 4)
	78 #8 (0, 4)
	79 aload_0 (0, 4)
	80 invokevirtual (0, 4)
	81 org/apache/commons/math3/ode/nonstiff/RungeKuttaFieldIntegrator.getField:()Lorg/apache/commons/math3/Field; (0, 4)
	83 iload (0, 4)
	84 #7 (0, 4)
	85 iconst_m1 (0, 4)
	86 invokestatic (0, 4)
	87 org/apache/commons/math3/util/MathArrays.buildArray:(Lorg/apache/commons/math3/Field;II)[[Ljava/lang/Object; (0, 4)
	89 checkcast (0, 4)
	90 [[Lorg/apache/commons/math3/RealFieldElement; (0, 4)
	92 astore (0, 4)
	93 #9 (0, 4)
	94 aload_0 (0, 4)
	95 invokevirtual (0, 4)
	96 org/apache/commons/math3/ode/nonstiff/RungeKuttaFieldIntegrator.getField:()Lorg/apache/commons/math3/Field; (0, 4)
	98 aload (0, 4)
	99 #5 (0, 4)
	100 arraylength (0, 4)
	101 invokestatic (0, 4)
	102 org/apache/commons/math3/util/MathArrays.buildArray:(Lorg/apache/commons/math3/Field;I)[Ljava/lang/Object; (0, 4)
	104 checkcast (0, 4)
	105 [Lorg/apache/commons/math3/RealFieldElement; (0, 4)
	107 astore (0, 4)
	108 #10 (0, 4)
	109 iload (1, 1)
	110 #6 (1, 1)
	111 ifeq (1, 1)
	112 75 (1, 1)
	114 aload_0 (2, 1)
	115 invokevirtual (2, 1)
	116 org/apache/commons/math3/ode/nonstiff/RungeKuttaFieldIntegrator.getStepStart:()Lorg/apache/commons/math3/ode/FieldODEStateAndDerivative; (2, 1)
	118 invokevirtual (2, 1)
	119 org/apache/commons/math3/ode/FieldODEStateAndDerivative.getTime:()Lorg/apache/commons/math3/RealFieldElement; (2, 1)
	121 aload_0 (2, 1)
	122 getfield (2, 1)
	123 org/apache/commons/math3/ode/nonstiff/RungeKuttaFieldIntegrator.step:Lorg/apache/commons/math3/RealFieldElement; (2, 1)
	125 invokeinterface (2, 1)
	126 org/apache/commons/math3/RealFieldElement.setStepSize:(Lorg/apache/commons/math3/RealFieldElement;)V (2, 1)
	128 0 (2, 1)
	130 checkcast (2, 1)
	131 org/apache/commons/math3/RealFieldElement (2, 1)
	133 aload_3 (2, 1)
	134 invokeinterface (2, 1)
	135 org/apache/commons/math3/RealFieldElement.getReal:()D (2, 1)
	137 0 (2, 1)
	139 checkcast (2, 1)
	140 org/apache/commons/math3/RealFieldElement (2, 1)
	142 invokeinterface (2, 1)
	143 org/apache/commons/math3/RealFieldElement.org/apache/commons/math3/util/MathArrays (2, 1)
	145 0 (2, 1)
	147 dconst_0 (2, 1)
	148 dcmpl (2, 1)
	149 iflt (2, 1)
	150 26 (2, 1)
	152 aload_0 (2, 1)
	153 aload_3 (2, 1)
	154 aload_0 (2, 1)
	155 invokevirtual (2, 1)
	156 org/apache/commons/math3/ode/nonstiff/RungeKuttaFieldIntegrator.getStepStart:()Lorg/apache/commons/math3/ode/FieldODEStateAndDerivative; (2, 1)
	158 invokevirtual (2, 1)
	159 org/apache/commons/math3/ode/FieldODEStateAndDerivative.getTime:()Lorg/apache/commons/math3/RealFieldElement; (2, 1)
	161 invokeinterface (2, 1)
	162 org/apache/commons/math3/RealFieldElement.getReal:()D (2, 1)
	164 0 (2, 1)
	166 checkcast (2, 1)
	167 org/apache/commons/math3/RealFieldElement (2, 1)
	169 invokevirtual (2, 1)
	170 org/apache/commons/math3/ode/nonstiff/RungeKuttaFieldIntegrator.setStepSize:(Lorg/apache/commons/math3/RealFieldElement;)V (2, 1)
	172 goto (2, 1)
	173 91 (2, 1)
	175 aload_0 (2, 2)
	176 aload_0 (2, 2)
	177 getfield (2, 2)
	178 org/apache/commons/math3/ode/nonstiff/RungeKuttaFieldIntegrator.step:Lorg/apache/commons/math3/RealFieldElement; (2, 2)
	180 invokevirtual (2, 2)
	181 org/apache/commons/math3/ode/nonstiff/RungeKuttaFieldIntegrator.setStepSize:(Lorg/apache/commons/math3/RealFieldElement;)V (2, 2)
	183 goto (2, 2)
	184 80 (2, 2)
	186 aload_0 (2, 1)
	187 invokevirtual (2, 1)
	188 org/apache/commons/math3/ode/nonstiff/RungeKuttaFieldIntegrator.getStepStart:()Lorg/apache/commons/math3/ode/FieldODEStateAndDerivative; (2, 1)
	190 invokevirtual (2, 1)
	191 org/apache/commons/math3/ode/FieldODEStateAndDerivative.getTime:()Lorg/apache/commons/math3/RealFieldElement; (2, 1)
	193 aload_0 (2, 1)
	194 getfield (2, 1)
	195 org/apache/commons/math3/ode/nonstiff/RungeKuttaFieldIntegrator.step:Lorg/apache/commons/math3/RealFieldElement; (2, 1)
	197 invokeinterface (2, 1)
	198 org/apache/commons/math3/RealFieldElement.getReal:()D (2, 1)
	200 0 (2, 1)
	202 checkcast (2, 1)
	203 org/apache/commons/math3/RealFieldElement (2, 1)
	205 aload_3 (2, 1)
	206 invokeinterface (2, 1)
	207 org/apache/commons/math3/RealFieldElement.getReal:()D (2, 1)
	209 0 (2, 1)
	211 checkcast (2, 1)
	212 org/apache/commons/math3/RealFieldElement (2, 1)
	214 invokeinterface (2, 1)
	215 org/apache/commons/math3/RealFieldElement.org/apache/commons/math3/util/MathArrays (2, 1)
	217 0 (2, 1)
	219 dconst_0 (2, 1)
	220 dcmpg (2, 1)
	221 ifgt (2, 1)
	222 26 (2, 1)
	224 aload_0 (2, 1)
	225 aload_3 (2, 1)
	226 aload_0 (2, 1)
	227 invokevirtual (2, 1)
	228 org/apache/commons/math3/ode/nonstiff/RungeKuttaFieldIntegrator.getStepStart:()Lorg/apache/commons/math3/ode/FieldODEStateAndDerivative; (2, 1)
	230 invokevirtual (2, 1)
	231 org/apache/commons/math3/ode/FieldODEStateAndDerivative.getTime:()Lorg/apache/commons/math3/RealFieldElement; (2, 1)
	233 invokeinterface (2, 1)
	234 org/apache/commons/math3/RealFieldElement.getReal:()D (2, 1)
	236 0 (2, 1)
	238 checkcast (2, 1)
	239 org/apache/commons/math3/RealFieldElement (2, 1)
	241 invokevirtual (2, 1)
	242 org/apache/commons/math3/ode/nonstiff/RungeKuttaFieldIntegrator.setStepSize:(Lorg/apache/commons/math3/RealFieldElement;)V (2, 1)
	244 goto (2, 1)
	245 19 (2, 1)
	247 aload_0 (2, 2)
	248 aload_0 (2, 2)
	249 getfield (2, 2)
	250 org/apache/commons/math3/ode/nonstiff/RungeKuttaFieldIntegrator.step:Lorg/apache/commons/math3/RealFieldElement; (2, 2)
	252 invokeinterface (2, 2)
	253 org/apache/commons/math3/RealFieldElement.setIsLastStep:(Z)V (2, 2)
	255 0 (2, 2)
	257 checkcast (2, 2)
	258 org/apache/commons/math3/RealFieldElement (2, 2)
	260 invokevirtual (2, 2)
	261 org/apache/commons/math3/ode/nonstiff/RungeKuttaFieldIntegrator.setStepSize:(Lorg/apache/commons/math3/RealFieldElement;)V (2, 2)
	263 aload_0 (0, 4)
	264 iconst_0 (0, 4)
	265 invokevirtual (0, 4)
	266 org/apache/commons/math3/ode/nonstiff/RungeKuttaFieldIntegrator.setIsLastStep:(Z)V (0, 4)
	268 aload_1 (0, 4)
	269 invokevirtual (0, 4)
	270 org/apache/commons/math3/ode/FieldExpandableODE.getMapper:()Lorg/apache/commons/math3/ode/FieldEquationsMapper; (0, 4)
	272 aload_0 (0, 4)
	273 invokevirtual (0, 4)
	274 org/apache/commons/math3/ode/nonstiff/RungeKuttaFieldIntegrator.getStepStart:()Lorg/apache/commons/math3/ode/FieldODEStateAndDerivative; (0, 4)
	276 invokevirtual (0, 4)
	277 org/apache/commons/math3/ode/FieldEquationsMapper.mapState:(Lorg/apache/commons/math3/ode/FieldODEState;)[Lorg/apache/commons/math3/RealFieldElement; (0, 4)
	279 astore (0, 4)
	280 #8 (0, 4)
	281 aload (0, 4)
	282 #9 (0, 4)
	283 iconst_0 (0, 4)
	284 aload_1 (0, 4)
	285 invokevirtual (0, 4)
	286 org/apache/commons/math3/ode/FieldExpandableODE.getMapper:()Lorg/apache/commons/math3/ode/FieldEquationsMapper; (0, 4)
	288 aload_0 (0, 4)
	289 invokevirtual (0, 4)
	290 org/apache/commons/math3/ode/nonstiff/RungeKuttaFieldIntegrator.getStepStart:()Lorg/apache/commons/math3/ode/FieldODEStateAndDerivative; (0, 4)
	292 invokevirtual (0, 4)
	293 org/apache/commons/math3/ode/FieldEquationsMapper.mapDerivative:(Lorg/apache/commons/math3/ode/FieldODEStateAndDerivative;)[Lorg/apache/commons/math3/RealFieldElement; (0, 4)
	295 aastore (0, 4)
	296 iconst_1 (2, 4)
	297 istore (2, 4)
	298 #11 (2, 4)
	299 iload (2, 4)
	300 #11 (2, 4)
	301 iload (2, 4)
	302 #7 (2, 4)
	303 if_icmpge (2, 4)
	304 180 (2, 4)
	306 iconst_0 (3, 4)
	307 istore (3, 4)
	308 #12 (3, 4)
	309 iload (3, 4)
	310 #12 (3, 4)
	311 aload (3, 4)
	312 #5 (3, 4)
	313 arraylength (3, 4)
	314 if_icmpge (3, 4)
	315 119 (3, 4)
	317 aload (3, 4)
	318 #9 (3, 4)
	319 iconst_0 (3, 4)
	320 aaload (3, 4)
	321 iload (3, 4)
	322 #12 (3, 4)
	323 aaload (3, 4)
	324 aload_0 (3, 4)
	325 getfield (3, 4)
	326 org/apache/commons/math3/ode/nonstiff/RungeKuttaFieldIntegrator.a:[[Lorg/apache/commons/math3/RealFieldElement; (3, 4)
	328 iload (3, 4)
	329 #11 (3, 4)
	330 iconst_1 (3, 4)
	331 isub (3, 4)
	332 aaload (3, 4)
	333 iconst_0 (3, 4)
	334 aaload (3, 4)
	335 invokeinterface (3, 4)
	336 org/apache/commons/math3/RealFieldElement.getStepSize:()Lorg/apache/commons/math3/RealFieldElement; (3, 4)
	338 0 (3, 4)
	340 checkcast (3, 4)
	341 org/apache/commons/math3/RealFieldElement (3, 4)
	343 astore (3, 4)
	344 #13 (3, 4)
	345 iconst_1 (4, 4)
	346 istore (4, 4)
	347 #14 (4, 4)
	348 iload (4, 4)
	349 #14 (4, 4)
	350 iload (4, 4)
	351 #11 (4, 4)
	352 if_icmpge (4, 4)
	353 46 (4, 4)
	355 aload (4, 4)
	356 #13 (4, 4)
	357 aload (4, 4)
	358 #9 (4, 4)
	359 iload (4, 4)
	360 #14 (4, 4)
	361 aaload (4, 4)
	362 iload (4, 4)
	363 #12 (4, 4)
	364 aaload (4, 4)
	365 aload_0 (4, 4)
	366 getfield (4, 4)
	367 org/apache/commons/math3/ode/nonstiff/RungeKuttaFieldIntegrator.a:[[Lorg/apache/commons/math3/RealFieldElement; (4, 4)
	369 iload (4, 4)
	370 #11 (4, 4)
	371 iconst_1 (4, 4)
	372 isub (4, 4)
	373 aaload (4, 4)
	374 iload (4, 4)
	375 #14 (4, 4)
	376 aaload (4, 4)
	377 invokeinterface (4, 4)
	378 org/apache/commons/math3/RealFieldElement.getStepSize:()Lorg/apache/commons/math3/RealFieldElement; (4, 4)
	380 0 (4, 4)
	382 invokeinterface (4, 4)
	383 org/apache/commons/math3/RealFieldElement.setStepSize:(Lorg/apache/commons/math3/RealFieldElement;)V (4, 4)
	385 0 (4, 4)
	387 checkcast (4, 4)
	388 org/apache/commons/math3/RealFieldElement (4, 4)
	390 astore (4, 4)
	391 #13 (4, 4)
	392 iinc (4, 4)
	393 #14 (4, 4)
	394 -89 (4, 4)
	395 goto (4, 4)
	396 -47 (4, 4)
	398 aload (3, 4)
	399 #10 (3, 4)
	400 iload (3, 4)
	401 #12 (3, 4)
	402 aload (3, 4)
	403 #8 (3, 4)
	404 iload (3, 4)
	405 #12 (3, 4)
	406 aaload (3, 4)
	407 aload_0 (3, 4)
	408 invokevirtual (3, 4)
	409 org/apache/commons/math3/ode/nonstiff/RungeKuttaFieldIntegrator.getStepSize:()Lorg/apache/commons/math3/RealFieldElement; (3, 4)
	411 aload (3, 4)
	412 #13 (3, 4)
	413 invokeinterface (3, 4)
	414 org/apache/commons/math3/RealFieldElement.getStepSize:()Lorg/apache/commons/math3/RealFieldElement; (3, 4)
	416 0 (3, 4)
	418 invokeinterface (3, 4)
	419 org/apache/commons/math3/RealFieldElement.setStepSize:(Lorg/apache/commons/math3/RealFieldElement;)V (3, 4)
	421 0 (3, 4)
	423 checkcast (3, 4)
	424 org/apache/commons/math3/RealFieldElement (3, 4)
	426 aastore (3, 4)
	427 iinc (3, 4)
	428 #12 (3, 4)
	429 -89 (3, 4)
	430 goto (3, 4)
	431 -121 (3, 4)
	433 aload (2, 4)
	434 #9 (2, 4)
	435 iload (2, 4)
	436 #11 (2, 4)
	437 aload_0 (2, 4)
	438 aload_0 (2, 4)
	439 invokevirtual (2, 4)
	440 org/apache/commons/math3/ode/nonstiff/RungeKuttaFieldIntegrator.getStepStart:()Lorg/apache/commons/math3/ode/FieldODEStateAndDerivative; (2, 4)
	442 invokevirtual (2, 4)
	443 org/apache/commons/math3/ode/FieldODEStateAndDerivative.getTime:()Lorg/apache/commons/math3/RealFieldElement; (2, 4)
	445 aload_0 (2, 4)
	446 invokevirtual (2, 4)
	447 org/apache/commons/math3/ode/nonstiff/RungeKuttaFieldIntegrator.getStepSize:()Lorg/apache/commons/math3/RealFieldElement; (2, 4)
	449 aload_0 (2, 4)
	450 getfield (2, 4)
	451 org/apache/commons/math3/ode/nonstiff/RungeKuttaFieldIntegrator.c:[Lorg/apache/commons/math3/RealFieldElement; (2, 4)
	453 iload (2, 4)
	454 #11 (2, 4)
	455 iconst_1 (2, 4)
	456 isub (2, 4)
	457 aaload (2, 4)
	458 invokeinterface (2, 4)
	459 org/apache/commons/math3/RealFieldElement.getStepSize:()Lorg/apache/commons/math3/RealFieldElement; (2, 4)
	461 0 (2, 4)
	463 invokeinterface (2, 4)
	464 org/apache/commons/math3/RealFieldElement.setStepSize:(Lorg/apache/commons/math3/RealFieldElement;)V (2, 4)
	466 0 (2, 4)
	468 checkcast (2, 4)
	469 org/apache/commons/math3/RealFieldElement (2, 4)
	471 aload (2, 4)
	472 #10 (2, 4)
	473 invokevirtual (2, 4)
	474 org/apache/commons/math3/ode/nonstiff/RungeKuttaFieldIntegrator.computeDerivatives:(Lorg/apache/commons/math3/RealFieldElement;[Lorg/apache/commons/math3/RealFieldElement;)[Lorg/apache/commons/math3/RealFieldElement; (2, 4)
	476 aastore (2, 4)
	477 iinc (2, 4)
	478 #11 (2, 4)
	479 -89 (2, 4)
	480 goto (2, 4)
	481 -181 (2, 4)
	483 iconst_0 (2, 4)
	484 istore (2, 4)
	485 #11 (2, 4)
	486 iload (2, 4)
	487 #11 (2, 4)
	488 aload (2, 4)
	489 #5 (2, 4)
	490 arraylength (2, 4)
	491 if_icmpge (2, 4)
	492 109 (2, 4)
	494 aload (2, 4)
	495 #9 (2, 4)
	496 iconst_0 (2, 4)
	497 aaload (2, 4)
	498 iload (2, 4)
	499 #11 (2, 4)
	500 aaload (2, 4)
	501 aload_0 (2, 4)
	502 getfield (2, 4)
	503 org/apache/commons/math3/ode/nonstiff/RungeKuttaFieldIntegrator.b:[Lorg/apache/commons/math3/RealFieldElement; (2, 4)
	505 iconst_0 (2, 4)
	506 aaload (2, 4)
	507 invokeinterface (2, 4)
	508 org/apache/commons/math3/RealFieldElement.getStepSize:()Lorg/apache/commons/math3/RealFieldElement; (2, 4)
	510 0 (2, 4)
	512 checkcast (2, 4)
	513 org/apache/commons/math3/RealFieldElement (2, 4)
	515 astore (2, 4)
	516 #12 (2, 4)
	517 iconst_1 (3, 4)
	518 istore (3, 4)
	519 #13 (3, 4)
	520 iload (3, 4)
	521 #13 (3, 4)
	522 iload (3, 4)
	523 #7 (3, 4)
	524 if_icmpge (3, 4)
	525 41 (3, 4)
	527 aload (3, 4)
	528 #12 (3, 4)
	529 aload (3, 4)
	530 #9 (3, 4)
	531 iload (3, 4)
	532 #13 (3, 4)
	533 aaload (3, 4)
	534 iload (3, 4)
	535 #11 (3, 4)
	536 aaload (3, 4)
	537 aload_0 (3, 4)
	538 getfield (3, 4)
	539 org/apache/commons/math3/ode/nonstiff/RungeKuttaFieldIntegrator.b:[Lorg/apache/commons/math3/RealFieldElement; (3, 4)
	541 iload (3, 4)
	542 #13 (3, 4)
	543 aaload (3, 4)
	544 invokeinterface (3, 4)
	545 org/apache/commons/math3/RealFieldElement.getStepSize:()Lorg/apache/commons/math3/RealFieldElement; (3, 4)
	547 0 (3, 4)
	549 invokeinterface (3, 4)
	550 org/apache/commons/math3/RealFieldElement.setStepSize:(Lorg/apache/commons/math3/RealFieldElement;)V (3, 4)
	552 0 (3, 4)
	554 checkcast (3, 4)
	555 org/apache/commons/math3/RealFieldElement (3, 4)
	557 astore (3, 4)
	558 #12 (3, 4)
	559 iinc (3, 4)
	560 #13 (3, 4)
	561 -89 (3, 4)
	562 goto (3, 4)
	563 -42 (3, 4)
	565 aload (2, 4)
	566 #10 (2, 4)
	567 iload (2, 4)
	568 #11 (2, 4)
	569 aload (2, 4)
	570 #8 (2, 4)
	571 iload (2, 4)
	572 #11 (2, 4)
	573 aaload (2, 4)
	574 aload_0 (2, 4)
	575 invokevirtual (2, 4)
	576 org/apache/commons/math3/ode/nonstiff/RungeKuttaFieldIntegrator.getStepSize:()Lorg/apache/commons/math3/RealFieldElement; (2, 4)
	578 aload (2, 4)
	579 #12 (2, 4)
	580 invokeinterface (2, 4)
	581 org/apache/commons/math3/RealFieldElement.getStepSize:()Lorg/apache/commons/math3/RealFieldElement; (2, 4)
	583 0 (2, 4)
	585 invokeinterface (2, 4)
	586 org/apache/commons/math3/RealFieldElement.setStepSize:(Lorg/apache/commons/math3/RealFieldElement;)V (2, 4)
	588 0 (2, 4)
	590 checkcast (2, 4)
	591 org/apache/commons/math3/RealFieldElement (2, 4)
	593 aastore (2, 4)
	594 iinc (2, 4)
	595 #11 (2, 4)
	596 -89 (2, 4)
	597 goto (2, 4)
	598 -111 (2, 4)
	600 aload_0 (0, 4)
	601 invokevirtual (0, 4)
	602 org/apache/commons/math3/ode/nonstiff/RungeKuttaFieldIntegrator.getStepStart:()Lorg/apache/commons/math3/ode/FieldODEStateAndDerivative; (0, 4)
	604 invokevirtual (0, 4)
	605 org/apache/commons/math3/ode/FieldODEStateAndDerivative.getTime:()Lorg/apache/commons/math3/RealFieldElement; (0, 4)
	607 aload_0 (0, 4)
	608 invokevirtual (0, 4)
	609 org/apache/commons/math3/ode/nonstiff/RungeKuttaFieldIntegrator.getStepSize:()Lorg/apache/commons/math3/RealFieldElement; (0, 4)
	611 invokeinterface (0, 4)
	612 org/apache/commons/math3/RealFieldElement.setStepSize:(Lorg/apache/commons/math3/RealFieldElement;)V (0, 4)
	614 0 (0, 4)
	616 checkcast (0, 4)
	617 org/apache/commons/math3/RealFieldElement (0, 4)
	619 astore (0, 4)
	620 #11 (0, 4)
	621 aload_0 (0, 4)
	622 aload (0, 4)
	623 #11 (0, 4)
	624 aload (0, 4)
	625 #10 (0, 4)
	626 invokevirtual (0, 4)
	627 org/apache/commons/math3/ode/nonstiff/RungeKuttaFieldIntegrator.computeDerivatives:(Lorg/apache/commons/math3/RealFieldElement;[Lorg/apache/commons/math3/RealFieldElement;)[Lorg/apache/commons/math3/RealFieldElement; (0, 4)
	629 astore (0, 4)
	630 #12 (0, 4)
	631 new (0, 4)
	632 org/apache/commons/math3/ode/FieldODEStateAndDerivative (0, 4)
	634 dup (0, 4)
	635 aload (0, 4)
	636 #11 (0, 4)
	637 aload (0, 4)
	638 #10 (0, 4)
	639 aload (0, 4)
	640 #12 (0, 4)
	641 invokespecial (0, 4)
	642 org/apache/commons/math3/ode/FieldODEStateAndDerivative.<init>:(Lorg/apache/commons/math3/RealFieldElement;[Lorg/apache/commons/math3/RealFieldElement;[Lorg/apache/commons/math3/RealFieldElement;)V (0, 4)
	644 astore (0, 4)
	645 #13 (0, 4)
	646 aload (0, 4)
	647 #10 (0, 4)
	648 iconst_0 (0, 4)
	649 aload (0, 4)
	650 #8 (0, 4)
	651 iconst_0 (0, 4)
	652 aload (0, 4)
	653 #5 (0, 4)
	654 arraylength (0, 4)
	655 invokestatic (0, 4)
	656 java/lang/System.arraycopy:(Ljava/lang/Object;ILjava/lang/Object;II)V (0, 4)
	658 aload_0 (1, 4)
	659 aload_0 (1, 4)
	660 aload_0 (1, 4)
	661 iload (1, 4)
	662 #6 (1, 4)
	663 aload (1, 4)
	664 #9 (1, 4)
	665 aload_0 (1, 4)
	666 invokevirtual (1, 4)
	667 org/apache/commons/math3/ode/nonstiff/RungeKuttaFieldIntegrator.getStepStart:()Lorg/apache/commons/math3/ode/FieldODEStateAndDerivative; (1, 4)
	669 aload (1, 4)
	670 #13 (1, 4)
	671 aload_1 (1, 4)
	672 invokevirtual (1, 4)
	673 org/apache/commons/math3/ode/FieldExpandableODE.getMapper:()Lorg/apache/commons/math3/ode/FieldEquationsMapper; (1, 4)
	675 invokevirtual (1, 4)
	676 org/apache/commons/math3/ode/nonstiff/RungeKuttaFieldIntegrator.createInterpolator:(Z[[Lorg/apache/commons/math3/RealFieldElement;Lorg/apache/commons/math3/ode/FieldODEStateAndDerivative;Lorg/apache/commons/math3/ode/FieldODEStateAndDerivative;Lorg/apache/commons/math3/ode/FieldEquationsMapper;)Lorg/apache/commons/math3/ode/nonstiff/RungeKuttaFieldStepInterpolator; (1, 4)
	678 aload_3 (1, 4)
	679 invokevirtual (1, 4)
	680 org/apache/commons/math3/ode/nonstiff/RungeKuttaFieldIntegrator.acceptStep:(Lorg/apache/commons/math3/ode/sampling/AbstractFieldStepInterpolator;Lorg/apache/commons/math3/RealFieldElement;)Lorg/apache/commons/math3/ode/FieldODEStateAndDerivative; (1, 4)
	682 invokevirtual (1, 4)
	683 org/apache/commons/math3/ode/nonstiff/RungeKuttaFieldIntegrator.setStepStart:(Lorg/apache/commons/math3/ode/FieldODEStateAndDerivative;)V (1, 4)
	685 aload_0 (2, 1)
	686 invokevirtual (2, 1)
	687 org/apache/commons/math3/ode/nonstiff/RungeKuttaFieldIntegrator.isLastStep:()Z (2, 1)
	689 ifne (2, 1)
	690 111 (2, 1)
	692 aload_0 (2, 4)
	693 invokevirtual (2, 4)
	694 org/apache/commons/math3/ode/nonstiff/RungeKuttaFieldIntegrator.getStepStart:()Lorg/apache/commons/math3/ode/FieldODEStateAndDerivative; (2, 4)
	696 invokevirtual (2, 4)
	697 org/apache/commons/math3/ode/FieldODEStateAndDerivative.getTime:()Lorg/apache/commons/math3/RealFieldElement; (2, 4)
	699 aload_0 (2, 4)
	700 invokevirtual (2, 4)
	701 org/apache/commons/math3/ode/nonstiff/RungeKuttaFieldIntegrator.getStepSize:()Lorg/apache/commons/math3/RealFieldElement; (2, 4)
	703 invokeinterface (2, 4)
	704 org/apache/commons/math3/RealFieldElement.setStepSize:(Lorg/apache/commons/math3/RealFieldElement;)V (2, 4)
	706 0 (2, 4)
	708 checkcast (2, 4)
	709 org/apache/commons/math3/RealFieldElement (2, 4)
	711 astore (2, 4)
	712 #14 (2, 4)
	713 iload (2, 4)
	714 #6 (2, 4)
	715 ifeq (2, 4)
	716 32 (2, 4)
	718 aload (2, 4)
	719 #14 (2, 4)
	720 aload_3 (2, 4)
	721 invokeinterface (2, 4)
	722 org/apache/commons/math3/RealFieldElement.getReal:()D (2, 4)
	724 0 (2, 4)
	726 checkcast (2, 4)
	727 org/apache/commons/math3/RealFieldElement (2, 4)
	729 invokeinterface (2, 4)
	730 org/apache/commons/math3/RealFieldElement.org/apache/commons/math3/util/MathArrays (2, 4)
	732 0 (2, 4)
	734 dconst_0 (2, 4)
	735 dcmpl (2, 4)
	736 iflt (2, 4)
	737 7 (2, 4)
	739 iconst_1 (2, 4)
	740 goto (2, 4)
	741 33 (2, 4)
	743 iconst_0 (2, 4)
	744 goto (2, 4)
	745 29 (2, 4)
	747 aload (2, 4)
	748 #14 (2, 4)
	749 aload_3 (2, 4)
	750 invokeinterface (2, 4)
	751 org/apache/commons/math3/RealFieldElement.getReal:()D (2, 4)
	753 0 (2, 4)
	755 checkcast (2, 4)
	756 org/apache/commons/math3/RealFieldElement (2, 4)
	758 invokeinterface (2, 4)
	759 org/apache/commons/math3/RealFieldElement.org/apache/commons/math3/util/MathArrays (2, 4)
	761 0 (2, 4)
	763 dconst_0 (2, 4)
	764 dcmpg (2, 4)
	765 ifgt (2, 4)
	766 7 (2, 4)
	768 iconst_1 (2, 4)
	769 goto (2, 4)
	770 4 (2, 4)
	772 iconst_0 (2, 4)
	773 istore (2, 4)
	774 #15 (2, 4)
	775 iload (3, 1)
	776 #15 (3, 1)
	777 ifeq (3, 1)
	778 23 (3, 1)
	780 aload_0 (3, 1)
	781 aload_3 (3, 1)
	782 aload_0 (3, 1)
	783 invokevirtual (3, 1)
	784 org/apache/commons/math3/ode/nonstiff/RungeKuttaFieldIntegrator.getStepStart:()Lorg/apache/commons/math3/ode/FieldODEStateAndDerivative; (3, 1)
	786 invokevirtual (3, 1)
	787 org/apache/commons/math3/ode/FieldODEStateAndDerivative.getTime:()Lorg/apache/commons/math3/RealFieldElement; (3, 1)
	789 invokeinterface (3, 1)
	790 org/apache/commons/math3/RealFieldElement.getReal:()D (3, 1)
	792 0 (3, 1)
	794 checkcast (3, 1)
	795 org/apache/commons/math3/RealFieldElement (3, 1)
	797 invokevirtual (3, 1)
	798 org/apache/commons/math3/ode/nonstiff/RungeKuttaFieldIntegrator.setStepSize:(Lorg/apache/commons/math3/RealFieldElement;)V (3, 1)
	800 aload_0 (0, 3)
	801 invokevirtual (0, 3)
	802 org/apache/commons/math3/ode/nonstiff/RungeKuttaFieldIntegrator.isLastStep:()Z (0, 3)
	804 ifeq (0, 3)
	805 -536 (0, 3)
	807 aload_0 (0, 3)
	808 invokevirtual (0, 3)
	809 org/apache/commons/math3/ode/nonstiff/RungeKuttaFieldIntegrator.getStepStart:()Lorg/apache/commons/math3/ode/FieldODEStateAndDerivative; (0, 3)
	811 astore (0, 3)
	812 #11 (0, 3)
	813 aload_0 (0, 3)
	814 aconst_null (0, 3)
	815 invokevirtual (0, 3)
	816 org/apache/commons/math3/ode/nonstiff/RungeKuttaFieldIntegrator.setStepStart:(Lorg/apache/commons/math3/ode/FieldODEStateAndDerivative;)V (0, 3)
	818 aload_0 (0, 3)
	819 aconst_null (0, 3)
	820 invokevirtual (0, 3)
	821 org/apache/commons/math3/ode/nonstiff/RungeKuttaFieldIntegrator.setStepSize:(Lorg/apache/commons/math3/RealFieldElement;)V (0, 3)
	823 aload (0, 3)
	824 #11 (0, 3)
	825 areturn (0, 3)

Method: singleStep
	0 aload_3 (0, 0)
	1 invokevirtual (0, 0)
	2 [Lorg/apache/commons/math3/RealFieldElement;.clone:()Ljava/lang/Object; (0, 0)
	4 checkcast (0, 0)
	5 [Lorg/apache/commons/math3/RealFieldElement; (0, 0)
	7 astore (0, 0)
	8 #5 (0, 0)
	9 aload_0 (0, 0)
	10 getfield (0, 0)
	11 org/apache/commons/math3/ode/nonstiff/RungeKuttaFieldIntegrator.c:[Lorg/apache/commons/math3/RealFieldElement; (0, 0)
	13 arraylength (0, 0)
	14 iconst_1 (0, 0)
	15 iadd (0, 0)
	16 istore (0, 0)
	17 #6 (0, 0)
	18 aload_0 (0, 0)
	19 invokevirtual (0, 0)
	20 org/apache/commons/math3/ode/nonstiff/RungeKuttaFieldIntegrator.getField:()Lorg/apache/commons/math3/Field; (0, 0)
	22 iload (0, 0)
	23 #6 (0, 0)
	24 iconst_m1 (0, 0)
	25 invokestatic (0, 0)
	26 org/apache/commons/math3/util/MathArrays.buildArray:(Lorg/apache/commons/math3/Field;II)[[Ljava/lang/Object; (0, 0)
	28 checkcast (0, 0)
	29 [[Lorg/apache/commons/math3/RealFieldElement; (0, 0)
	31 astore (0, 0)
	32 #7 (0, 0)
	33 aload_3 (0, 0)
	34 invokevirtual (0, 0)
	35 [Lorg/apache/commons/math3/RealFieldElement;.clone:()Ljava/lang/Object; (0, 0)
	37 checkcast (0, 0)
	38 [Lorg/apache/commons/math3/RealFieldElement; (0, 0)
	40 astore (0, 0)
	41 #8 (0, 0)
	42 aload (0, 0)
	43 #4 (0, 0)
	44 aload_2 (0, 0)
	45 invokeinterface (0, 0)
	46 org/apache/commons/math3/RealFieldElement.getReal:()D (0, 0)
	48 0 (0, 0)
	50 checkcast (0, 0)
	51 org/apache/commons/math3/RealFieldElement (0, 0)
	53 astore (0, 0)
	54 #9 (0, 0)
	55 aload (0, 0)
	56 #7 (0, 0)
	57 iconst_0 (0, 0)
	58 aload_1 (0, 0)
	59 aload_2 (0, 0)
	60 aload (0, 0)
	61 #5 (0, 0)
	62 invokeinterface (0, 0)
	63 org/apache/commons/math3/ode/FirstOrderFieldDifferentialEquations.org/apache/commons/math3/ode/FieldODEStateAndDerivative (0, 0)
	65 0 (0, 0)
	67 aastore (0, 0)
	68 iconst_1 (1, 4)
	69 istore (1, 4)
	70 #10 (1, 4)
	71 iload (1, 4)
	72 #10 (1, 4)
	73 iload (1, 4)
	74 #6 (1, 4)
	75 if_icmpge (1, 4)
	76 171 (1, 4)
	78 iconst_0 (2, 4)
	79 istore (2, 4)
	80 #11 (2, 4)
	81 iload (2, 4)
	82 #11 (2, 4)
	83 aload_3 (2, 4)
	84 arraylength (2, 4)
	85 if_icmpge (2, 4)
	86 117 (2, 4)
	88 aload (2, 4)
	89 #7 (2, 4)
	90 iconst_0 (2, 4)
	91 aaload (2, 4)
	92 iload (2, 4)
	93 #11 (2, 4)
	94 aaload (2, 4)
	95 aload_0 (2, 4)
	96 getfield (2, 4)
	97 org/apache/commons/math3/ode/nonstiff/RungeKuttaFieldIntegrator.a:[[Lorg/apache/commons/math3/RealFieldElement; (2, 4)
	99 iload (2, 4)
	100 #10 (2, 4)
	101 iconst_1 (2, 4)
	102 isub (2, 4)
	103 aaload (2, 4)
	104 iconst_0 (2, 4)
	105 aaload (2, 4)
	106 invokeinterface (2, 4)
	107 org/apache/commons/math3/RealFieldElement.getStepSize:()Lorg/apache/commons/math3/RealFieldElement; (2, 4)
	109 0 (2, 4)
	111 checkcast (2, 4)
	112 org/apache/commons/math3/RealFieldElement (2, 4)
	114 astore (2, 4)
	115 #12 (2, 4)
	116 iconst_1 (3, 4)
	117 istore (3, 4)
	118 #13 (3, 4)
	119 iload (3, 4)
	120 #13 (3, 4)
	121 iload (3, 4)
	122 #10 (3, 4)
	123 if_icmpge (3, 4)
	124 46 (3, 4)
	126 aload (3, 4)
	127 #12 (3, 4)
	128 aload (3, 4)
	129 #7 (3, 4)
	130 iload (3, 4)
	131 #13 (3, 4)
	132 aaload (3, 4)
	133 iload (3, 4)
	134 #11 (3, 4)
	135 aaload (3, 4)
	136 aload_0 (3, 4)
	137 getfield (3, 4)
	138 org/apache/commons/math3/ode/nonstiff/RungeKuttaFieldIntegrator.a:[[Lorg/apache/commons/math3/RealFieldElement; (3, 4)
	140 iload (3, 4)
	141 #10 (3, 4)
	142 iconst_1 (3, 4)
	143 isub (3, 4)
	144 aaload (3, 4)
	145 iload (3, 4)
	146 #13 (3, 4)
	147 aaload (3, 4)
	148 invokeinterface (3, 4)
	149 org/apache/commons/math3/RealFieldElement.getStepSize:()Lorg/apache/commons/math3/RealFieldElement; (3, 4)
	151 0 (3, 4)
	153 invokeinterface (3, 4)
	154 org/apache/commons/math3/RealFieldElement.setStepSize:(Lorg/apache/commons/math3/RealFieldElement;)V (3, 4)
	156 0 (3, 4)
	158 checkcast (3, 4)
	159 org/apache/commons/math3/RealFieldElement (3, 4)
	161 astore (3, 4)
	162 #12 (3, 4)
	163 iinc (3, 4)
	164 #13 (3, 4)
	165 -89 (3, 4)
	166 goto (3, 4)
	167 -47 (3, 4)
	169 aload (2, 4)
	170 #8 (2, 4)
	171 iload (2, 4)
	172 #11 (2, 4)
	173 aload (2, 4)
	174 #5 (2, 4)
	175 iload (2, 4)
	176 #11 (2, 4)
	177 aaload (2, 4)
	178 aload (2, 4)
	179 #9 (2, 4)
	180 aload (2, 4)
	181 #12 (2, 4)
	182 invokeinterface (2, 4)
	183 org/apache/commons/math3/RealFieldElement.getStepSize:()Lorg/apache/commons/math3/RealFieldElement; (2, 4)
	185 0 (2, 4)
	187 invokeinterface (2, 4)
	188 org/apache/commons/math3/RealFieldElement.setStepSize:(Lorg/apache/commons/math3/RealFieldElement;)V (2, 4)
	190 0 (2, 4)
	192 checkcast (2, 4)
	193 org/apache/commons/math3/RealFieldElement (2, 4)
	195 aastore (2, 4)
	196 iinc (2, 4)
	197 #11 (2, 4)
	198 -89 (2, 4)
	199 goto (2, 4)
	200 -118 (2, 4)
	202 aload (1, 4)
	203 #7 (1, 4)
	204 iload (1, 4)
	205 #10 (1, 4)
	206 aload_1 (1, 4)
	207 aload_2 (1, 4)
	208 aload (1, 4)
	209 #9 (1, 4)
	210 aload_0 (1, 4)
	211 getfield (1, 4)
	212 org/apache/commons/math3/ode/nonstiff/RungeKuttaFieldIntegrator.c:[Lorg/apache/commons/math3/RealFieldElement; (1, 4)
	214 iload (1, 4)
	215 #10 (1, 4)
	216 iconst_1 (1, 4)
	217 isub (1, 4)
	218 aaload (1, 4)
	219 invokeinterface (1, 4)
	220 org/apache/commons/math3/RealFieldElement.getStepSize:()Lorg/apache/commons/math3/RealFieldElement; (1, 4)
	222 0 (1, 4)
	224 invokeinterface (1, 4)
	225 org/apache/commons/math3/RealFieldElement.setStepSize:(Lorg/apache/commons/math3/RealFieldElement;)V (1, 4)
	227 0 (1, 4)
	229 checkcast (1, 4)
	230 org/apache/commons/math3/RealFieldElement (1, 4)
	232 aload (1, 4)
	233 #8 (1, 4)
	234 invokeinterface (1, 4)
	235 org/apache/commons/math3/ode/FirstOrderFieldDifferentialEquations.org/apache/commons/math3/ode/FieldODEStateAndDerivative (1, 4)
	237 0 (1, 4)
	239 aastore (1, 4)
	240 iinc (1, 4)
	241 #10 (1, 4)
	242 -89 (1, 4)
	243 goto (1, 4)
	244 -172 (1, 4)
	246 iconst_0 (1, 4)
	247 istore (1, 4)
	248 #10 (1, 4)
	249 iload (1, 4)
	250 #10 (1, 4)
	251 aload_3 (1, 4)
	252 arraylength (1, 4)
	253 if_icmpge (1, 4)
	254 107 (1, 4)
	256 aload (1, 4)
	257 #7 (1, 4)
	258 iconst_0 (1, 4)
	259 aaload (1, 4)
	260 iload (1, 4)
	261 #10 (1, 4)
	262 aaload (1, 4)
	263 aload_0 (1, 4)
	264 getfield (1, 4)
	265 org/apache/commons/math3/ode/nonstiff/RungeKuttaFieldIntegrator.b:[Lorg/apache/commons/math3/RealFieldElement; (1, 4)
	267 iconst_0 (1, 4)
	268 aaload (1, 4)
	269 invokeinterface (1, 4)
	270 org/apache/commons/math3/RealFieldElement.getStepSize:()Lorg/apache/commons/math3/RealFieldElement; (1, 4)
	272 0 (1, 4)
	274 checkcast (1, 4)
	275 org/apache/commons/math3/RealFieldElement (1, 4)
	277 astore (1, 4)
	278 #11 (1, 4)
	279 iconst_1 (2, 4)
	280 istore (2, 4)
	281 #12 (2, 4)
	282 iload (2, 4)
	283 #12 (2, 4)
	284 iload (2, 4)
	285 #6 (2, 4)
	286 if_icmpge (2, 4)
	287 41 (2, 4)
	289 aload (2, 4)
	290 #11 (2, 4)
	291 aload (2, 4)
	292 #7 (2, 4)
	293 iload (2, 4)
	294 #12 (2, 4)
	295 aaload (2, 4)
	296 iload (2, 4)
	297 #10 (2, 4)
	298 aaload (2, 4)
	299 aload_0 (2, 4)
	300 getfield (2, 4)
	301 org/apache/commons/math3/ode/nonstiff/RungeKuttaFieldIntegrator.b:[Lorg/apache/commons/math3/RealFieldElement; (2, 4)
	303 iload (2, 4)
	304 #12 (2, 4)
	305 aaload (2, 4)
	306 invokeinterface (2, 4)
	307 org/apache/commons/math3/RealFieldElement.getStepSize:()Lorg/apache/commons/math3/RealFieldElement; (2, 4)
	309 0 (2, 4)
	311 invokeinterface (2, 4)
	312 org/apache/commons/math3/RealFieldElement.setStepSize:(Lorg/apache/commons/math3/RealFieldElement;)V (2, 4)
	314 0 (2, 4)
	316 checkcast (2, 4)
	317 org/apache/commons/math3/RealFieldElement (2, 4)
	319 astore (2, 4)
	320 #11 (2, 4)
	321 iinc (2, 4)
	322 #12 (2, 4)
	323 -89 (2, 4)
	324 goto (2, 4)
	325 -42 (2, 4)
	327 aload (1, 4)
	328 #5 (1, 4)
	329 iload (1, 4)
	330 #10 (1, 4)
	331 aload (1, 4)
	332 #5 (1, 4)
	333 iload (1, 4)
	334 #10 (1, 4)
	335 aaload (1, 4)
	336 aload (1, 4)
	337 #9 (1, 4)
	338 aload (1, 4)
	339 #11 (1, 4)
	340 invokeinterface (1, 4)
	341 org/apache/commons/math3/RealFieldElement.getStepSize:()Lorg/apache/commons/math3/RealFieldElement; (1, 4)
	343 0 (1, 4)
	345 invokeinterface (1, 4)
	346 org/apache/commons/math3/RealFieldElement.setStepSize:(Lorg/apache/commons/math3/RealFieldElement;)V (1, 4)
	348 0 (1, 4)
	350 checkcast (1, 4)
	351 org/apache/commons/math3/RealFieldElement (1, 4)
	353 aastore (1, 4)
	354 iinc (1, 4)
	355 #10 (1, 4)
	356 -89 (1, 4)
	357 goto (1, 4)
	358 -108 (1, 4)
	360 aload (0, 0)
	361 #5 (0, 0)
	362 areturn (0, 0)

