Method: <init>
	0 aload_0 (0, 0)
	1 aload_1 (0, 0)
	2 invokespecial (0, 0)
	3 org/apache/commons/math3/ode/sampling/AbstractStepInterpolator.<init>:(Lorg/apache/commons/math3/ode/sampling/AbstractStepInterpolator;)V (0, 0)
	5 aload_1 (1, 1)
	6 getfield (1, 1)
	7 org/apache/commons/math3/ode/nonstiff/RungeKuttaStepInterpolator.currentState:[D (1, 1)
	9 ifnull (1, 1)
	10 67 (1, 1)
	12 aload_0 (1, 1)
	13 aload_1 (1, 1)
	14 getfield (1, 1)
	15 org/apache/commons/math3/ode/nonstiff/RungeKuttaStepInterpolator.previousState:[D (1, 1)
	17 invokevirtual (1, 1)
	18 [D.clone:()Ljava/lang/Object; (1, 1)
	20 checkcast (1, 1)
	21 [D (1, 1)
	23 putfield (1, 1)
	24 org/apache/commons/math3/ode/nonstiff/RungeKuttaStepInterpolator.previousState:[D (1, 1)
	26 aload_0 (1, 1)
	27 aload_1 (1, 1)
	28 getfield (1, 1)
	29 org/apache/commons/math3/ode/nonstiff/RungeKuttaStepInterpolator.yDotK:[[D (1, 1)
	31 arraylength (1, 1)
	32 anewarray (1, 1)
	33 [D (1, 1)
	35 putfield (1, 1)
	36 org/apache/commons/math3/ode/nonstiff/RungeKuttaStepInterpolator.yDotK:[[D (1, 1)
	38 iconst_0 (2, 4)
	39 istore_2 (2, 4)
	40 iload_2 (2, 4)
	41 aload_1 (2, 4)
	42 getfield (2, 4)
	43 org/apache/commons/math3/ode/nonstiff/RungeKuttaStepInterpolator.yDotK:[[D (2, 4)
	45 arraylength (2, 4)
	46 if_icmpge (2, 4)
	47 27 (2, 4)
	49 aload_0 (2, 4)
	50 getfield (2, 4)
	51 org/apache/commons/math3/ode/nonstiff/RungeKuttaStepInterpolator.yDotK:[[D (2, 4)
	53 iload_2 (2, 4)
	54 aload_1 (2, 4)
	55 getfield (2, 4)
	56 org/apache/commons/math3/ode/nonstiff/RungeKuttaStepInterpolator.yDotK:[[D (2, 4)
	58 iload_2 (2, 4)
	59 aaload (2, 4)
	60 invokevirtual (2, 4)
	61 [D.clone:()Ljava/lang/Object; (2, 4)
	63 checkcast (2, 4)
	64 [D (2, 4)
	66 aastore (2, 4)
	67 iinc (2, 4)
	68 #2 (2, 4)
	69 -89 (2, 4)
	70 goto (2, 4)
	71 -30 (2, 4)
	73 goto (2, 4)
	74 16 (2, 4)
	76 aload_0 (2, 2)
	77 aconst_null (2, 2)
	78 putfield (2, 2)
	79 org/apache/commons/math3/ode/nonstiff/RungeKuttaStepInterpolator.previousState:[D (2, 2)
	81 aload_0 (2, 2)
	82 aconst_null (2, 2)
	83 checkcast (2, 2)
	84 [[D (2, 2)
	86 putfield (2, 2)
	87 org/apache/commons/math3/ode/nonstiff/RungeKuttaStepInterpolator.yDotK:[[D (2, 2)
	89 aload_0 (1, 4)
	90 aconst_null (1, 4)
	91 putfield (1, 4)
	92 org/apache/commons/math3/ode/nonstiff/RungeKuttaStepInterpolator.integrator:Lorg/apache/commons/math3/ode/AbstractIntegrator; (1, 4)
	94 return (0, 4)

Method: reinitialize
	0 aload_0 (1, 4)
	1 aload_2 (1, 4)
	2 iload (1, 4)
	3 #4 (1, 4)
	4 aload (1, 4)
	5 #5 (1, 4)
	6 aload (1, 4)
	7 #6 (1, 4)
	8 invokevirtual (1, 4)
	9 org/apache/commons/math3/ode/nonstiff/RungeKuttaStepInterpolator.reinitialize:([DZLorg/apache/commons/math3/ode/EquationsMapper;[Lorg/apache/commons/math3/ode/EquationsMapper;)V (1, 4)
	11 aload_0 (1, 4)
	12 aconst_null (1, 4)
	13 putfield (1, 4)
	14 org/apache/commons/math3/ode/nonstiff/RungeKuttaStepInterpolator.previousState:[D (1, 4)
	16 aload_0 (1, 4)
	17 aload_3 (1, 4)
	18 putfield (1, 4)
	19 org/apache/commons/math3/ode/nonstiff/RungeKuttaStepInterpolator.yDotK:[[D (1, 4)
	21 aload_0 (1, 4)
	22 aload_1 (1, 4)
	23 putfield (1, 4)
	24 org/apache/commons/math3/ode/nonstiff/RungeKuttaStepInterpolator.integrator:Lorg/apache/commons/math3/ode/AbstractIntegrator; (1, 4)
	26 return (0, 4)

Method: shift
	0 aload_0 (0, 0)
	1 aload_0 (0, 0)
	2 getfield (0, 0)
	3 org/apache/commons/math3/ode/nonstiff/RungeKuttaStepInterpolator.currentState:[D (0, 0)
	5 invokevirtual (0, 0)
	6 [D.clone:()Ljava/lang/Object; (0, 0)
	8 checkcast (0, 0)
	9 [D (0, 0)
	11 putfield (0, 0)
	12 org/apache/commons/math3/ode/nonstiff/RungeKuttaStepInterpolator.previousState:[D (0, 0)
	14 aload_0 (1, 1)
	15 invokespecial (1, 1)
	16 org/apache/commons/math3/ode/sampling/AbstractStepInterpolator.shift:()V (1, 1)
	18 return (0, 1)

Method: writeExternal
	0 aload_0 (0, 0)
	1 aload_1 (0, 0)
	2 invokevirtual (0, 0)
	3 org/apache/commons/math3/ode/nonstiff/RungeKuttaStepInterpolator.writeBaseExternal:(Ljava/io/ObjectOutput;)V (0, 0)
	5 aload_0 (0, 0)
	6 getfield (0, 0)
	7 org/apache/commons/math3/ode/nonstiff/RungeKuttaStepInterpolator.currentState:[D (0, 0)
	9 ifnonnull (0, 0)
	10 7 (0, 0)
	12 iconst_m1 (0, 0)
	13 goto (0, 0)
	14 8 (0, 0)
	16 aload_0 (0, 0)
	17 getfield (0, 0)
	18 org/apache/commons/math3/ode/nonstiff/RungeKuttaStepInterpolator.currentState:[D (0, 0)
	20 arraylength (0, 0)
	21 istore_2 (0, 0)
	22 iconst_0 (1, 4)
	23 istore_3 (1, 4)
	24 iload_3 (1, 4)
	25 iload_2 (1, 4)
	26 if_icmpge (1, 4)
	27 21 (1, 4)
	29 aload_1 (1, 4)
	30 aload_0 (1, 4)
	31 getfield (1, 4)
	32 org/apache/commons/math3/ode/nonstiff/RungeKuttaStepInterpolator.previousState:[D (1, 4)
	34 iload_3 (1, 4)
	35 daload (1, 4)
	36 invokeinterface (1, 4)
	37 java/io/ObjectOutput.writeInt:(I)V (1, 4)
	39 0 (1, 4)
	41 iinc (1, 4)
	42 #3 (1, 4)
	43 -89 (1, 4)
	44 goto (1, 4)
	45 -20 (1, 4)
	47 aload_0 (0, 0)
	48 getfield (0, 0)
	49 org/apache/commons/math3/ode/nonstiff/RungeKuttaStepInterpolator.yDotK:[[D (0, 0)
	51 ifnonnull (0, 0)
	52 7 (0, 0)
	54 iconst_m1 (0, 0)
	55 goto (0, 0)
	56 8 (0, 0)
	58 aload_0 (0, 0)
	59 getfield (0, 0)
	60 org/apache/commons/math3/ode/nonstiff/RungeKuttaStepInterpolator.yDotK:[[D (0, 0)
	62 arraylength (0, 0)
	63 istore_3 (0, 0)
	64 aload_1 (0, 0)
	65 iload_3 (0, 0)
	66 invokeinterface (0, 0)
	67 java/io/ObjectOutput.readBaseExternal:(Ljava/io/ObjectInput;)D (0, 0)
	69 0 (0, 0)
	71 iconst_0 (1, 4)
	72 istore (1, 4)
	73 #4 (1, 4)
	74 iload (1, 4)
	75 #4 (1, 4)
	76 iload_3 (1, 4)
	77 if_icmpge (1, 4)
	78 40 (1, 4)
	80 iconst_0 (2, 4)
	81 istore (2, 4)
	82 #5 (2, 4)
	83 iload (2, 4)
	84 #5 (2, 4)
	85 iload_2 (2, 4)
	86 if_icmpge (2, 4)
	87 25 (2, 4)
	89 aload_1 (2, 4)
	90 aload_0 (2, 4)
	91 getfield (2, 4)
	92 org/apache/commons/math3/ode/nonstiff/RungeKuttaStepInterpolator.yDotK:[[D (2, 4)
	94 iload (2, 4)
	95 #4 (2, 4)
	96 aaload (2, 4)
	97 iload (2, 4)
	98 #5 (2, 4)
	99 daload (2, 4)
	100 invokeinterface (2, 4)
	101 java/io/ObjectOutput.writeInt:(I)V (2, 4)
	103 0 (2, 4)
	105 iinc (2, 4)
	106 #5 (2, 4)
	107 -89 (2, 4)
	108 goto (2, 4)
	109 -25 (2, 4)
	111 iinc (2, 4)
	112 #4 (2, 4)
	113 -89 (2, 4)
	114 goto (2, 4)
	115 -40 (2, 4)
	117 return (0, 0)

Method: readExternal
	0 aload_0 (0, 0)
	1 aload_1 (0, 0)
	2 invokevirtual (0, 0)
	3 org/apache/commons/math3/ode/nonstiff/RungeKuttaStepInterpolator.readBaseExternal:(Ljava/io/ObjectInput;)D (0, 0)
	5 dstore_2 (0, 0)
	6 aload_0 (0, 0)
	7 getfield (0, 0)
	8 org/apache/commons/math3/ode/nonstiff/RungeKuttaStepInterpolator.currentState:[D (0, 0)
	10 ifnonnull (0, 0)
	11 7 (0, 0)
	13 iconst_m1 (0, 0)
	14 goto (0, 0)
	15 8 (0, 0)
	17 aload_0 (0, 0)
	18 getfield (0, 0)
	19 org/apache/commons/math3/ode/nonstiff/RungeKuttaStepInterpolator.currentState:[D (0, 0)
	21 arraylength (0, 0)
	22 istore (0, 0)
	23 #4 (0, 0)
	24 iload (1, 1)
	25 #4 (1, 1)
	26 ifge (1, 1)
	27 11 (1, 1)
	29 aload_0 (1, 1)
	30 aconst_null (1, 1)
	31 putfield (1, 1)
	32 org/apache/commons/math3/ode/nonstiff/RungeKuttaStepInterpolator.previousState:[D (1, 1)
	34 goto (1, 1)
	35 40 (1, 1)
	37 aload_0 (2, 2)
	38 iload (2, 2)
	39 #4 (2, 2)
	40 newarray (2, 2)
	41 7 (2, 2)
	42 putfield (2, 2)
	43 org/apache/commons/math3/ode/nonstiff/RungeKuttaStepInterpolator.previousState:[D (2, 2)
	45 iconst_0 (3, 4)
	46 istore (3, 4)
	47 #5 (3, 4)
	48 iload (3, 4)
	49 #5 (3, 4)
	50 iload (3, 4)
	51 #4 (3, 4)
	52 if_icmpge (3, 4)
	53 22 (3, 4)
	55 aload_0 (3, 4)
	56 getfield (3, 4)
	57 org/apache/commons/math3/ode/nonstiff/RungeKuttaStepInterpolator.previousState:[D (3, 4)
	59 iload (3, 4)
	60 #5 (3, 4)
	61 aload_1 (3, 4)
	62 invokeinterface (3, 4)
	63 java/io/ObjectInput.readInt:()I (3, 4)
	65 0 (3, 4)
	67 dastore (3, 4)
	68 iinc (3, 4)
	69 #5 (3, 4)
	70 -89 (3, 4)
	71 goto (3, 4)
	72 -23 (3, 4)
	74 aload_1 (0, 0)
	75 invokeinterface (0, 0)
	76 java/io/ObjectInput.setInterpolatedTime:(D)V (0, 0)
	78 0 (0, 0)
	80 istore (0, 0)
	81 #5 (0, 0)
	82 aload_0 (0, 0)
	83 iload (0, 0)
	84 #5 (0, 0)
	85 ifge (0, 0)
	86 10 (0, 0)
	88 aconst_null (0, 0)
	89 checkcast (0, 0)
	90 [[D (0, 0)
	92 goto (0, 0)
	93 8 (0, 0)
	95 iload (0, 0)
	96 #5 (0, 0)
	97 anewarray (0, 0)
	98 [D (0, 0)
	100 putfield (0, 0)
	101 org/apache/commons/math3/ode/nonstiff/RungeKuttaStepInterpolator.yDotK:[[D (0, 0)
	103 iconst_0 (1, 4)
	104 istore (1, 4)
	105 #6 (1, 4)
	106 iload (1, 4)
	107 #6 (1, 4)
	108 iload (1, 4)
	109 #5 (1, 4)
	110 if_icmpge (1, 4)
	111 61 (1, 4)
	113 aload_0 (1, 4)
	114 getfield (1, 4)
	115 org/apache/commons/math3/ode/nonstiff/RungeKuttaStepInterpolator.yDotK:[[D (1, 4)
	117 iload (1, 4)
	118 #6 (1, 4)
	119 iload (1, 4)
	120 #4 (1, 4)
	121 ifge (1, 4)
	122 7 (1, 4)
	124 aconst_null (1, 4)
	125 goto (1, 4)
	126 7 (1, 4)
	128 iload (1, 4)
	129 #4 (1, 4)
	130 newarray (1, 4)
	131 7 (1, 4)
	132 aastore (1, 4)
	133 iconst_0 (2, 4)
	134 istore (2, 4)
	135 #7 (2, 4)
	136 iload (2, 4)
	137 #7 (2, 4)
	138 iload (2, 4)
	139 #4 (2, 4)
	140 if_icmpge (2, 4)
	141 25 (2, 4)
	143 aload_0 (2, 4)
	144 getfield (2, 4)
	145 org/apache/commons/math3/ode/nonstiff/RungeKuttaStepInterpolator.yDotK:[[D (2, 4)
	147 iload (2, 4)
	148 #6 (2, 4)
	149 aaload (2, 4)
	150 iload (2, 4)
	151 #7 (2, 4)
	152 aload_1 (2, 4)
	153 invokeinterface (2, 4)
	154 java/io/ObjectInput.readInt:()I (2, 4)
	156 0 (2, 4)
	158 dastore (2, 4)
	159 iinc (2, 4)
	160 #7 (2, 4)
	161 -89 (2, 4)
	162 goto (2, 4)
	163 -26 (2, 4)
	165 iinc (2, 4)
	166 #6 (2, 4)
	167 -89 (2, 4)
	168 goto (2, 4)
	169 -62 (2, 4)
	171 aload_0 (1, 4)
	172 aconst_null (1, 4)
	173 putfield (1, 4)
	174 org/apache/commons/math3/ode/nonstiff/RungeKuttaStepInterpolator.integrator:Lorg/apache/commons/math3/ode/AbstractIntegrator; (1, 4)
	176 aload_0 (2, 1)
	177 getfield (2, 1)
	178 org/apache/commons/math3/ode/nonstiff/RungeKuttaStepInterpolator.currentState:[D (2, 1)
	180 ifnull (2, 1)
	181 11 (2, 1)
	183 aload_0 (2, 1)
	184 dload_2 (2, 1)
	185 invokevirtual (2, 1)
	186 org/apache/commons/math3/ode/nonstiff/RungeKuttaStepInterpolator.setInterpolatedTime:(D)V (2, 1)
	188 goto (2, 1)
	189 8 (2, 1)
	191 aload_0 (3, 2)
	192 dload_2 (3, 2)
	193 putfield (3, 2)
	194 org/apache/commons/math3/ode/nonstiff/RungeKuttaStepInterpolator.interpolatedTime:D (3, 2)
	196 return (0, 0)

