Method: <init>
	0 aload_0 (1, 4)
	1 iload_2 (1, 4)
	2 aload (1, 4)
	3 #4 (1, 4)
	4 aload (1, 4)
	5 #5 (1, 4)
	6 aload (1, 4)
	7 #6 (1, 4)
	8 aload (1, 4)
	9 #7 (1, 4)
	10 aload (1, 4)
	11 #8 (1, 4)
	12 invokespecial (1, 4)
	13 org/apache/commons/math3/ode/sampling/AbstractFieldStepInterpolator.<init>:(ZLorg/apache/commons/math3/ode/FieldODEStateAndDerivative;Lorg/apache/commons/math3/ode/FieldODEStateAndDerivative;Lorg/apache/commons/math3/ode/FieldODEStateAndDerivative;Lorg/apache/commons/math3/ode/FieldODEStateAndDerivative;Lorg/apache/commons/math3/ode/FieldEquationsMapper;)V (1, 4)
	15 aload_0 (1, 4)
	16 aload_1 (1, 4)
	17 putfield (1, 4)
	18 org/apache/commons/math3/ode/nonstiff/RungeKuttaFieldStepInterpolator.field:Lorg/apache/commons/math3/Field; (1, 4)
	20 aload_0 (1, 4)
	21 aload_1 (1, 4)
	22 aload_3 (1, 4)
	23 arraylength (1, 4)
	24 iconst_m1 (1, 4)
	25 invokestatic (1, 4)
	26 org/apache/commons/math3/util/MathArrays.buildArray:(Lorg/apache/commons/math3/Field;II)[[Ljava/lang/Object; (1, 4)
	28 checkcast (1, 4)
	29 [[Lorg/apache/commons/math3/RealFieldElement; (1, 4)
	31 putfield (1, 4)
	32 org/apache/commons/math3/ode/nonstiff/RungeKuttaFieldStepInterpolator.yDotK:[[Lorg/apache/commons/math3/RealFieldElement; (1, 4)
	34 iconst_0 (2, 4)
	35 istore (2, 4)
	36 #9 (2, 4)
	37 iload (2, 4)
	38 #9 (2, 4)
	39 aload_3 (2, 4)
	40 arraylength (2, 4)
	41 if_icmpge (2, 4)
	42 26 (2, 4)
	44 aload_0 (2, 4)
	45 getfield (2, 4)
	46 org/apache/commons/math3/ode/nonstiff/RungeKuttaFieldStepInterpolator.yDotK:[[Lorg/apache/commons/math3/RealFieldElement; (2, 4)
	48 iload (2, 4)
	49 #9 (2, 4)
	50 aload_3 (2, 4)
	51 iload (2, 4)
	52 #9 (2, 4)
	53 aaload (2, 4)
	54 invokevirtual (2, 4)
	55 [Lorg/apache/commons/math3/RealFieldElement;.clone:()Ljava/lang/Object; (2, 4)
	57 checkcast (2, 4)
	58 [Lorg/apache/commons/math3/RealFieldElement; (2, 4)
	60 aastore (2, 4)
	61 iinc (2, 4)
	62 #9 (2, 4)
	63 -89 (2, 4)
	64 goto (2, 4)
	65 -27 (2, 4)
	67 return (0, 4)

Method: create
	0 aload_0 (0, 0)
	1 iload_1 (0, 0)
	2 aload_2 (0, 0)
	3 aload_3 (0, 0)
	4 aload (0, 0)
	5 #4 (0, 0)
	6 aload (0, 0)
	7 #5 (0, 0)
	8 aload (0, 0)
	9 #6 (0, 0)
	10 invokevirtual (0, 0)
	11 org/apache/commons/math3/ode/nonstiff/RungeKuttaFieldStepInterpolator.create:(ZLorg/apache/commons/math3/ode/FieldODEStateAndDerivative;Lorg/apache/commons/math3/ode/FieldODEStateAndDerivative;Lorg/apache/commons/math3/ode/FieldODEStateAndDerivative;Lorg/apache/commons/math3/ode/FieldODEStateAndDerivative;Lorg/apache/commons/math3/ode/FieldEquationsMapper;)Lorg/apache/commons/math3/ode/nonstiff/RungeKuttaFieldStepInterpolator; (0, 0)
	13 areturn (0, 0)

Method: previousStateLinearCombination
	0 aload_0 (0, 0)
	1 aload_0 (0, 0)
	2 invokevirtual (0, 0)
	3 org/apache/commons/math3/ode/nonstiff/RungeKuttaFieldStepInterpolator.getPreviousState:()Lorg/apache/commons/math3/ode/FieldODEStateAndDerivative; (0, 0)
	5 invokevirtual (0, 0)
	6 org/apache/commons/math3/ode/FieldODEStateAndDerivative.getState:()[Lorg/apache/commons/math3/RealFieldElement; (0, 0)
	8 aload_1 (0, 0)
	9 invokespecial (0, 0)
	10 org/apache/commons/math3/ode/nonstiff/RungeKuttaFieldStepInterpolator.combine:([Lorg/apache/commons/math3/RealFieldElement;[Lorg/apache/commons/math3/RealFieldElement;)[Lorg/apache/commons/math3/RealFieldElement; (0, 0)
	12 areturn (0, 0)

Method: currentStateLinearCombination
	0 aload_0 (0, 0)
	1 aload_0 (0, 0)
	2 invokevirtual (0, 0)
	3 org/apache/commons/math3/ode/nonstiff/RungeKuttaFieldStepInterpolator.getCurrentState:()Lorg/apache/commons/math3/ode/FieldODEStateAndDerivative; (0, 0)
	5 invokevirtual (0, 0)
	6 org/apache/commons/math3/ode/FieldODEStateAndDerivative.getState:()[Lorg/apache/commons/math3/RealFieldElement; (0, 0)
	8 aload_1 (0, 0)
	9 invokespecial (0, 0)
	10 org/apache/commons/math3/ode/nonstiff/RungeKuttaFieldStepInterpolator.combine:([Lorg/apache/commons/math3/RealFieldElement;[Lorg/apache/commons/math3/RealFieldElement;)[Lorg/apache/commons/math3/RealFieldElement; (0, 0)
	12 areturn (0, 0)

Method: derivativeLinearCombination
	0 aload_0 (0, 0)
	1 aload_0 (0, 0)
	2 getfield (0, 0)
	3 org/apache/commons/math3/ode/nonstiff/RungeKuttaFieldStepInterpolator.field:Lorg/apache/commons/math3/Field; (0, 0)
	5 aload_0 (0, 0)
	6 getfield (0, 0)
	7 org/apache/commons/math3/ode/nonstiff/RungeKuttaFieldStepInterpolator.yDotK:[[Lorg/apache/commons/math3/RealFieldElement; (0, 0)
	9 iconst_0 (0, 0)
	10 aaload (0, 0)
	11 arraylength (0, 0)
	12 invokestatic (0, 0)
	13 org/apache/commons/math3/util/MathArrays.buildArray:(Lorg/apache/commons/math3/Field;I)[Ljava/lang/Object; (0, 0)
	15 checkcast (0, 0)
	16 [Lorg/apache/commons/math3/RealFieldElement; (0, 0)
	18 aload_1 (0, 0)
	19 invokespecial (0, 0)
	20 org/apache/commons/math3/ode/nonstiff/RungeKuttaFieldStepInterpolator.combine:([Lorg/apache/commons/math3/RealFieldElement;[Lorg/apache/commons/math3/RealFieldElement;)[Lorg/apache/commons/math3/RealFieldElement; (0, 0)
	22 areturn (0, 0)

Method: combine
	0 iconst_0 (1, 4)
	1 istore_3 (1, 4)
	2 iload_3 (1, 4)
	3 aload_1 (1, 4)
	4 arraylength (1, 4)
	5 if_icmpge (1, 4)
	6 57 (1, 4)
	8 iconst_0 (2, 4)
	9 istore (2, 4)
	10 #4 (2, 4)
	11 iload (2, 4)
	12 #4 (2, 4)
	13 aload_2 (2, 4)
	14 arraylength (2, 4)
	15 if_icmpge (2, 4)
	16 41 (2, 4)
	18 aload_1 (2, 4)
	19 iload_3 (2, 4)
	20 aload_1 (2, 4)
	21 iload_3 (2, 4)
	22 aaload (2, 4)
	23 aload_2 (2, 4)
	24 iload (2, 4)
	25 #4 (2, 4)
	26 aaload (2, 4)
	27 aload_0 (2, 4)
	28 getfield (2, 4)
	29 org/apache/commons/math3/ode/nonstiff/RungeKuttaFieldStepInterpolator.yDotK:[[Lorg/apache/commons/math3/RealFieldElement; (2, 4)
	31 iload (2, 4)
	32 #4 (2, 4)
	33 aaload (2, 4)
	34 iload_3 (2, 4)
	35 aaload (2, 4)
	36 invokeinterface (2, 4)
	37 org/apache/commons/math3/RealFieldElement.add:(Ljava/lang/Object;)Ljava/lang/Object; (2, 4)
	39 0 (2, 4)
	41 invokeinterface (2, 4)
	42 org/apache/commons/math3/RealFieldElement.org/apache/commons/math3/RealFieldElement (2, 4)
	44 0 (2, 4)
	46 checkcast (2, 4)
	47 org/apache/commons/math3/RealFieldElement (2, 4)
	49 aastore (2, 4)
	50 iinc (2, 4)
	51 #4 (2, 4)
	52 -89 (2, 4)
	53 goto (2, 4)
	54 -42 (2, 4)
	56 iinc (2, 4)
	57 #3 (2, 4)
	58 -89 (2, 4)
	59 goto (2, 4)
	60 -57 (2, 4)
	62 aload_1 (1, 4)
	63 areturn (1, 4)

