Method: <init>
	0 aload_0 (0, 0)
	1 iload_1 (0, 0)
	2 ifeq (0, 0)
	3 9 (0, 0)
	5 getstatic (0, 0)
	6 org/apache/commons/math3/exception/util/LocalizedFormats.CARDAN_ANGLES_SINGULARITY:Lorg/apache/commons/math3/exception/util/LocalizedFormats; (0, 0)
	8 goto (0, 0)
	9 6 (0, 0)
	11 getstatic (0, 0)
	12 org/apache/commons/math3/exception/util/LocalizedFormats.EULER_ANGLES_SINGULARITY:Lorg/apache/commons/math3/exception/util/LocalizedFormats; (0, 0)
	14 iconst_0 (0, 0)
	15 anewarray (0, 0)
	16 java/lang/Object (0, 0)
	18 invokespecial (0, 0)
	19 org/apache/commons/math3/exception/MathIllegalStateException.<init>:(Lorg/apache/commons/math3/exception/util/Localizable;[Ljava/lang/Object;)V (0, 0)
	21 return (0, 0)

