Method: <init>
	0 aload_0 (0, 0)
	1 invokespecial (0, 0)
	4 aload_3 (0, 0)
	5 invokeinterface (0, 0)
	10 invokeinterface (0, 0)
	15 checkcast (0, 0)
	18 astore (0, 0)
	20 new (0, 0)
	23 dup (0, 0)
	24 new (0, 0)
	27 dup (0, 0)
	28 aload (0, 0)
	30 aload_1 (0, 0)
	31 invokevirtual (0, 0)
	34 invokespecial (0, 0)
	37 aload_3 (0, 0)
	38 aload_2 (0, 0)
	39 invokespecial (0, 0)
	42 astore (0, 0)
	44 new (0, 0)
	47 dup (0, 0)
	48 new (0, 0)
	51 dup (0, 0)
	52 aload (0, 0)
	54 aload_1 (0, 0)
	55 invokevirtual (0, 0)
	58 invokespecial (0, 0)
	61 aload (0, 0)
	63 aload_2 (0, 0)
	64 invokespecial (0, 0)
	67 astore (0, 0)
	69 new (0, 0)
	72 dup (0, 0)
	73 new (0, 0)
	76 dup (0, 0)
	77 aload (0, 0)
	79 aload_1 (0, 0)
	80 invokevirtual (0, 0)
	83 invokespecial (0, 0)
	86 aload (0, 0)
	88 aload_2 (0, 0)
	89 invokespecial (0, 0)
	92 astore (0, 0)
	94 aload (0, 0)
	96 aload (0, 0)
	98 aload (0, 0)
	100 aload_2 (0, 0)
	101 invokevirtual (0, 0)
	104 aload_2 (0, 0)
	105 invokevirtual (0, 0)
	108 astore (0, 0)
	110 aload_0 (0, 0)
	111 aload (0, 0)
	113 getfield (0, 0)
	116 putfield (0, 0)
	119 aload_0 (0, 0)
	120 aload (0, 0)
	122 getfield (0, 0)
	125 putfield (0, 0)
	128 aload_0 (0, 0)
	129 aload (0, 0)
	131 getfield (0, 0)
	134 putfield (0, 0)
	137 aload_0 (0, 0)
	138 aload (0, 0)
	140 getfield (0, 0)
	143 putfield (0, 0)
	146 return (0, 0)

Method: mat2quat
	0 aload_1 (0, 0)
	1 iconst_0 (0, 0)
	2 aaload (0, 0)
	3 iconst_0 (0, 0)
	4 aaload (0, 0)
	5 invokeinterface (0, 0)
	10 iconst_4 (0, 0)
	11 invokestatic (0, 0)
	14 checkcast (0, 0)
	17 astore_2 (0, 0)
	18 aload_1 (0, 4)
	19 iconst_0 (0, 4)
	20 aaload (0, 4)
	21 iconst_0 (0, 4)
	22 aaload (0, 4)
	23 aload_1 (0, 4)
	24 iconst_1 (0, 4)
	25 aaload (0, 4)
	26 iconst_1 (0, 4)
	27 aaload (0, 4)
	28 invokeinterface (0, 4)
	33 checkcast (0, 4)
	36 aload_1 (0, 4)
	37 iconst_2 (0, 4)
	38 aaload (0, 4)
	39 iconst_2 (0, 4)
	40 aaload (0, 4)
	41 invokeinterface (0, 4)
	46 checkcast (0, 4)
	49 astore_3 (0, 4)
	50 aload_3 (1, 1)
	51 invokeinterface (1, 1)
	56 ldc2_w (1, 1)
	59 dcmpl (1, 1)
	60 ifle (1, 1)
	63 aload_2 (1, 1)
	64 iconst_0 (1, 1)
	65 aload_3 (1, 1)
	66 dconst_1 (1, 1)
	67 invokeinterface (1, 1)
	72 checkcast (1, 1)
	75 invokeinterface (1, 1)
	80 checkcast (1, 1)
	83 ldc2_w (1, 1)
	86 invokeinterface (1, 1)
	91 checkcast (1, 1)
	94 aastore (1, 1)
	95 aload_2 (1, 1)
	96 iconst_0 (1, 1)
	97 aaload (1, 1)
	98 invokeinterface (1, 1)
	103 checkcast (1, 1)
	106 ldc2_w (1, 1)
	109 invokeinterface (1, 1)
	114 checkcast (1, 1)
	117 astore (1, 1)
	119 aload_2 (1, 1)
	120 iconst_1 (1, 1)
	121 aload (1, 1)
	123 aload_1 (1, 1)
	124 iconst_1 (1, 1)
	125 aaload (1, 1)
	126 iconst_2 (1, 1)
	127 aaload (1, 1)
	128 aload_1 (1, 1)
	129 iconst_2 (1, 1)
	130 aaload (1, 1)
	131 iconst_1 (1, 1)
	132 aaload (1, 1)
	133 invokeinterface (1, 1)
	138 invokeinterface (1, 1)
	143 checkcast (1, 1)
	146 aastore (1, 1)
	147 aload_2 (1, 1)
	148 iconst_2 (1, 1)
	149 aload (1, 1)
	151 aload_1 (1, 1)
	152 iconst_2 (1, 1)
	153 aaload (1, 1)
	154 iconst_0 (1, 1)
	155 aaload (1, 1)
	156 aload_1 (1, 1)
	157 iconst_0 (1, 1)
	158 aaload (1, 1)
	159 iconst_2 (1, 1)
	160 aaload (1, 1)
	161 invokeinterface (1, 1)
	166 invokeinterface (1, 1)
	171 checkcast (1, 1)
	174 aastore (1, 1)
	175 aload_2 (1, 1)
	176 iconst_3 (1, 1)
	177 aload (1, 1)
	179 aload_1 (1, 1)
	180 iconst_0 (1, 1)
	181 aaload (1, 1)
	182 iconst_1 (1, 1)
	183 aaload (1, 1)
	184 aload_1 (1, 1)
	185 iconst_1 (1, 1)
	186 aaload (1, 1)
	187 iconst_0 (1, 1)
	188 aaload (1, 1)
	189 invokeinterface (1, 1)
	194 invokeinterface (1, 1)
	199 checkcast (1, 1)
	202 aastore (1, 1)
	203 goto (1, 2)
	206 aload_1 (1, 2)
	207 iconst_0 (1, 2)
	208 aaload (1, 2)
	209 iconst_0 (1, 2)
	210 aaload (1, 2)
	211 aload_1 (1, 2)
	212 iconst_1 (1, 2)
	213 aaload (1, 2)
	214 iconst_1 (1, 2)
	215 aaload (1, 2)
	216 invokeinterface (1, 2)
	221 checkcast (1, 2)
	224 aload_1 (1, 2)
	225 iconst_2 (1, 2)
	226 aaload (1, 2)
	227 iconst_2 (1, 2)
	228 aaload (1, 2)
	229 invokeinterface (1, 2)
	234 checkcast (1, 2)
	237 astore_3 (1, 2)
	238 aload_3 (2, 1)
	239 invokeinterface (2, 1)
	244 ldc2_w (2, 1)
	247 dcmpl (2, 1)
	248 ifle (2, 1)
	251 aload_2 (2, 1)
	252 iconst_1 (2, 1)
	253 aload_3 (2, 1)
	254 dconst_1 (2, 1)
	255 invokeinterface (2, 1)
	260 checkcast (2, 1)
	263 invokeinterface (2, 1)
	268 checkcast (2, 1)
	271 ldc2_w (2, 1)
	274 invokeinterface (2, 1)
	279 checkcast (2, 1)
	282 aastore (2, 1)
	283 aload_2 (2, 1)
	284 iconst_1 (2, 1)
	285 aaload (2, 1)
	286 invokeinterface (2, 1)
	291 checkcast (2, 1)
	294 ldc2_w (2, 1)
	297 invokeinterface (2, 1)
	302 checkcast (2, 1)
	305 astore (2, 1)
	307 aload_2 (2, 1)
	308 iconst_0 (2, 1)
	309 aload (2, 1)
	311 aload_1 (2, 1)
	312 iconst_1 (2, 1)
	313 aaload (2, 1)
	314 iconst_2 (2, 1)
	315 aaload (2, 1)
	316 aload_1 (2, 1)
	317 iconst_2 (2, 1)
	318 aaload (2, 1)
	319 iconst_1 (2, 1)
	320 aaload (2, 1)
	321 invokeinterface (2, 1)
	326 invokeinterface (2, 1)
	331 checkcast (2, 1)
	334 aastore (2, 1)
	335 aload_2 (2, 1)
	336 iconst_2 (2, 1)
	337 aload (2, 1)
	339 aload_1 (2, 1)
	340 iconst_0 (2, 1)
	341 aaload (2, 1)
	342 iconst_1 (2, 1)
	343 aaload (2, 1)
	344 aload_1 (2, 1)
	345 iconst_1 (2, 1)
	346 aaload (2, 1)
	347 iconst_0 (2, 1)
	348 aaload (2, 1)
	349 invokeinterface (2, 1)
	354 invokeinterface (2, 1)
	359 checkcast (2, 1)
	362 aastore (2, 1)
	363 aload_2 (2, 1)
	364 iconst_3 (2, 1)
	365 aload (2, 1)
	367 aload_1 (2, 1)
	368 iconst_0 (2, 1)
	369 aaload (2, 1)
	370 iconst_2 (2, 1)
	371 aaload (2, 1)
	372 aload_1 (2, 1)
	373 iconst_2 (2, 1)
	374 aaload (2, 1)
	375 iconst_0 (2, 1)
	376 aaload (2, 1)
	377 invokeinterface (2, 1)
	382 invokeinterface (2, 1)
	387 checkcast (2, 1)
	390 aastore (2, 1)
	391 goto (2, 2)
	394 aload_1 (2, 2)
	395 iconst_1 (2, 2)
	396 aaload (2, 2)
	397 iconst_1 (2, 2)
	398 aaload (2, 2)
	399 aload_1 (2, 2)
	400 iconst_0 (2, 2)
	401 aaload (2, 2)
	402 iconst_0 (2, 2)
	403 aaload (2, 2)
	404 invokeinterface (2, 2)
	409 checkcast (2, 2)
	412 aload_1 (2, 2)
	413 iconst_2 (2, 2)
	414 aaload (2, 2)
	415 iconst_2 (2, 2)
	416 aaload (2, 2)
	417 invokeinterface (2, 2)
	422 checkcast (2, 2)
	425 astore_3 (2, 2)
	426 aload_3 (3, 1)
	427 invokeinterface (3, 1)
	432 ldc2_w (3, 1)
	435 dcmpl (3, 1)
	436 ifle (3, 1)
	439 aload_2 (3, 1)
	440 iconst_2 (3, 1)
	441 aload_3 (3, 1)
	442 dconst_1 (3, 1)
	443 invokeinterface (3, 1)
	448 checkcast (3, 1)
	451 invokeinterface (3, 1)
	456 checkcast (3, 1)
	459 ldc2_w (3, 1)
	462 invokeinterface (3, 1)
	467 checkcast (3, 1)
	470 aastore (3, 1)
	471 aload_2 (3, 1)
	472 iconst_2 (3, 1)
	473 aaload (3, 1)
	474 invokeinterface (3, 1)
	479 checkcast (3, 1)
	482 ldc2_w (3, 1)
	485 invokeinterface (3, 1)
	490 checkcast (3, 1)
	493 astore (3, 1)
	495 aload_2 (3, 1)
	496 iconst_0 (3, 1)
	497 aload (3, 1)
	499 aload_1 (3, 1)
	500 iconst_2 (3, 1)
	501 aaload (3, 1)
	502 iconst_0 (3, 1)
	503 aaload (3, 1)
	504 aload_1 (3, 1)
	505 iconst_0 (3, 1)
	506 aaload (3, 1)
	507 iconst_2 (3, 1)
	508 aaload (3, 1)
	509 invokeinterface (3, 1)
	514 invokeinterface (3, 1)
	519 checkcast (3, 1)
	522 aastore (3, 1)
	523 aload_2 (3, 1)
	524 iconst_1 (3, 1)
	525 aload (3, 1)
	527 aload_1 (3, 1)
	528 iconst_0 (3, 1)
	529 aaload (3, 1)
	530 iconst_1 (3, 1)
	531 aaload (3, 1)
	532 aload_1 (3, 1)
	533 iconst_1 (3, 1)
	534 aaload (3, 1)
	535 iconst_0 (3, 1)
	536 aaload (3, 1)
	537 invokeinterface (3, 1)
	542 invokeinterface (3, 1)
	547 checkcast (3, 1)
	550 aastore (3, 1)
	551 aload_2 (3, 1)
	552 iconst_3 (3, 1)
	553 aload (3, 1)
	555 aload_1 (3, 1)
	556 iconst_2 (3, 1)
	557 aaload (3, 1)
	558 iconst_1 (3, 1)
	559 aaload (3, 1)
	560 aload_1 (3, 1)
	561 iconst_1 (3, 1)
	562 aaload (3, 1)
	563 iconst_2 (3, 1)
	564 aaload (3, 1)
	565 invokeinterface (3, 1)
	570 invokeinterface (3, 1)
	575 checkcast (3, 1)
	578 aastore (3, 1)
	579 goto (3, 2)
	582 aload_1 (3, 2)
	583 iconst_2 (3, 2)
	584 aaload (3, 2)
	585 iconst_2 (3, 2)
	586 aaload (3, 2)
	587 aload_1 (3, 2)
	588 iconst_0 (3, 2)
	589 aaload (3, 2)
	590 iconst_0 (3, 2)
	591 aaload (3, 2)
	592 invokeinterface (3, 2)
	597 checkcast (3, 2)
	600 aload_1 (3, 2)
	601 iconst_1 (3, 2)
	602 aaload (3, 2)
	603 iconst_1 (3, 2)
	604 aaload (3, 2)
	605 invokeinterface (3, 2)
	610 checkcast (3, 2)
	613 astore_3 (3, 2)
	614 aload_2 (3, 2)
	615 iconst_3 (3, 2)
	616 aload_3 (3, 2)
	617 dconst_1 (3, 2)
	618 invokeinterface (3, 2)
	623 checkcast (3, 2)
	626 invokeinterface (3, 2)
	631 checkcast (3, 2)
	634 ldc2_w (3, 2)
	637 invokeinterface (3, 2)
	642 checkcast (3, 2)
	645 aastore (3, 2)
	646 aload_2 (3, 2)
	647 iconst_3 (3, 2)
	648 aaload (3, 2)
	649 invokeinterface (3, 2)
	654 checkcast (3, 2)
	657 ldc2_w (3, 2)
	660 invokeinterface (3, 2)
	665 checkcast (3, 2)
	668 astore (3, 2)
	670 aload_2 (3, 2)
	671 iconst_0 (3, 2)
	672 aload (3, 2)
	674 aload_1 (3, 2)
	675 iconst_0 (3, 2)
	676 aaload (3, 2)
	677 iconst_1 (3, 2)
	678 aaload (3, 2)
	679 aload_1 (3, 2)
	680 iconst_1 (3, 2)
	681 aaload (3, 2)
	682 iconst_0 (3, 2)
	683 aaload (3, 2)
	684 invokeinterface (3, 2)
	689 invokeinterface (3, 2)
	694 checkcast (3, 2)
	697 aastore (3, 2)
	698 aload_2 (3, 2)
	699 iconst_1 (3, 2)
	700 aload (3, 2)
	702 aload_1 (3, 2)
	703 iconst_0 (3, 2)
	704 aaload (3, 2)
	705 iconst_2 (3, 2)
	706 aaload (3, 2)
	707 aload_1 (3, 2)
	708 iconst_2 (3, 2)
	709 aaload (3, 2)
	710 iconst_0 (3, 2)
	711 aaload (3, 2)
	712 invokeinterface (3, 2)
	717 invokeinterface (3, 2)
	722 checkcast (3, 2)
	725 aastore (3, 2)
	726 aload_2 (3, 2)
	727 iconst_2 (3, 2)
	728 aload (3, 2)
	730 aload_1 (3, 2)
	731 iconst_2 (3, 2)
	732 aaload (3, 2)
	733 iconst_1 (3, 2)
	734 aaload (3, 2)
	735 aload_1 (3, 2)
	736 iconst_1 (3, 2)
	737 aaload (3, 2)
	738 iconst_2 (3, 2)
	739 aaload (3, 2)
	740 invokeinterface (3, 2)
	745 invokeinterface (3, 2)
	750 checkcast (3, 2)
	753 aastore (3, 2)
	754 aload_2 (0, 1)
	755 areturn (0, 1)

Method: revert
	0 new (0, 0)
	3 dup (0, 0)
	4 aload_0 (0, 0)
	5 getfield (0, 0)
	8 invokeinterface (0, 0)
	13 checkcast (0, 0)
	16 aload_0 (0, 0)
	17 getfield (0, 0)
	20 aload_0 (0, 0)
	21 getfield (0, 0)
	24 aload_0 (0, 0)
	25 getfield (0, 0)
	28 iconst_0 (0, 0)
	29 invokespecial (0, 0)
	32 areturn (0, 0)

Method: getQ0
	0 aload_0 (0, 0)
	1 getfield (0, 0)
	4 areturn (0, 0)

Method: getQ1
	0 aload_0 (0, 0)
	1 getfield (0, 0)
	4 areturn (0, 0)

Method: getQ2
	0 aload_0 (0, 0)
	1 getfield (0, 0)
	4 areturn (0, 0)

Method: getQ3
	0 aload_0 (0, 0)
	1 getfield (0, 0)
	4 areturn (0, 0)

Method: getAxis
	0 aload_0 (0, 0)
	1 getfield (0, 0)
	4 aload_0 (0, 0)
	5 getfield (0, 0)
	8 invokeinterface (0, 0)
	13 checkcast (0, 0)
	16 aload_0 (0, 0)
	17 getfield (0, 0)
	20 aload_0 (0, 0)
	21 getfield (0, 0)
	24 invokeinterface (0, 0)
	29 invokeinterface (0, 0)
	34 checkcast (0, 0)
	37 aload_0 (0, 0)
	38 getfield (0, 0)
	41 aload_0 (0, 0)
	42 getfield (0, 0)
	45 invokeinterface (0, 0)
	50 invokeinterface (0, 0)
	55 checkcast (0, 0)
	58 astore_2 (0, 0)
	59 aload_2 (1, 1)
	60 invokeinterface (1, 1)
	65 dconst_0 (1, 1)
	66 dcmpl (1, 1)
	67 ifne (1, 1)
	70 aload_2 (1, 1)
	71 invokeinterface (1, 1)
	76 astore_3 (1, 1)
	77 new (1, 1)
	80 dup (1, 1)
	81 aload_1 (1, 1)
	82 getstatic (1, 1)
	85 if_acmpne (1, 1)
	88 aload_3 (1, 1)
	89 invokeinterface (1, 1)
	94 checkcast (1, 1)
	97 goto (1, 1)
	100 aload_3 (1, 1)
	101 invokeinterface (1, 1)
	106 checkcast (1, 1)
	109 invokeinterface (1, 1)
	114 checkcast (1, 1)
	117 aload_3 (1, 1)
	118 invokeinterface (1, 1)
	123 checkcast (1, 1)
	126 aload_3 (1, 1)
	127 invokeinterface (1, 1)
	132 checkcast (1, 1)
	135 invokespecial (1, 1)
	138 areturn (1, 1)
	139 aload_1 (1, 2)
	140 getstatic (1, 2)
	143 if_acmpne (1, 2)
	146 dconst_1 (1, 2)
	147 goto (1, 2)
	150 ldc2_w (1, 2)
	153 dstore_3 (1, 2)
	154 aload_0 (2, 1)
	155 getfield (2, 1)
	158 invokeinterface (2, 1)
	163 dconst_0 (2, 1)
	164 dcmpg (2, 1)
	165 ifge (2, 1)
	168 aload_2 (2, 1)
	169 invokeinterface (2, 1)
	174 checkcast (2, 1)
	177 invokeinterface (2, 1)
	182 checkcast (2, 1)
	185 dload_3 (2, 1)
	186 invokeinterface (2, 1)
	191 checkcast (2, 1)
	194 astore (2, 1)
	196 new (2, 1)
	199 dup (2, 1)
	200 aload_0 (2, 1)
	201 getfield (2, 1)
	204 aload (2, 1)
	206 invokeinterface (2, 1)
	211 checkcast (2, 1)
	214 aload_0 (2, 1)
	215 getfield (2, 1)
	218 aload (2, 1)
	220 invokeinterface (2, 1)
	225 checkcast (2, 1)
	228 aload_0 (2, 1)
	229 getfield (2, 1)
	232 aload (2, 1)
	234 invokeinterface (2, 1)
	239 checkcast (2, 1)
	242 invokespecial (2, 1)
	245 areturn (2, 1)
	246 aload_2 (1, 2)
	247 invokeinterface (1, 2)
	252 checkcast (1, 2)
	255 invokeinterface (1, 2)
	260 checkcast (1, 2)
	263 invokeinterface (1, 2)
	268 checkcast (1, 2)
	271 dload_3 (1, 2)
	272 invokeinterface (1, 2)
	277 checkcast (1, 2)
	280 astore (1, 2)
	282 new (1, 2)
	285 dup (1, 2)
	286 aload_0 (1, 2)
	287 getfield (1, 2)
	290 aload (1, 2)
	292 invokeinterface (1, 2)
	297 checkcast (1, 2)
	300 aload_0 (1, 2)
	301 getfield (1, 2)
	304 aload (1, 2)
	306 invokeinterface (1, 2)
	311 checkcast (1, 2)
	314 aload_0 (1, 2)
	315 getfield (1, 2)
	318 aload (1, 2)
	320 invokeinterface (1, 2)
	325 checkcast (1, 2)
	328 invokespecial (1, 2)
	331 areturn (1, 2)

Method: getAngle
	0 aload_0 (1, 1)
	1 getfield (1, 1)
	4 invokeinterface (1, 1)
	9 ldc2_w (1, 1)
	12 dcmpg (1, 1)
	13 iflt (1, 1)
	16 aload_0 (1, 1)
	17 getfield (1, 1)
	20 invokeinterface (1, 1)
	25 ldc2_w (1, 1)
	28 dcmpl (1, 1)
	29 ifle (1, 1)
	32 aload_0 (1, 1)
	33 getfield (1, 1)
	36 aload_0 (1, 1)
	37 getfield (1, 1)
	40 invokeinterface (1, 1)
	45 checkcast (1, 1)
	48 aload_0 (1, 1)
	49 getfield (1, 1)
	52 aload_0 (1, 1)
	53 getfield (1, 1)
	56 invokeinterface (1, 1)
	61 invokeinterface (1, 1)
	66 checkcast (1, 1)
	69 aload_0 (1, 1)
	70 getfield (1, 1)
	73 aload_0 (1, 1)
	74 getfield (1, 1)
	77 invokeinterface (1, 1)
	82 invokeinterface (1, 1)
	87 checkcast (1, 1)
	90 invokeinterface (1, 1)
	95 checkcast (1, 1)
	98 invokeinterface (1, 1)
	103 checkcast (1, 1)
	106 iconst_2 (1, 1)
	107 invokeinterface (1, 1)
	112 checkcast (1, 1)
	115 areturn (1, 1)
	116 aload_0 (1, 1)
	117 getfield (1, 1)
	120 invokeinterface (1, 1)
	125 dconst_0 (1, 1)
	126 dcmpg (1, 1)
	127 ifge (1, 1)
	130 aload_0 (1, 1)
	131 getfield (1, 1)
	134 invokeinterface (1, 1)
	139 checkcast (1, 1)
	142 invokeinterface (1, 1)
	147 checkcast (1, 1)
	150 iconst_2 (1, 1)
	151 invokeinterface (1, 1)
	156 checkcast (1, 1)
	159 areturn (1, 1)
	160 aload_0 (0, 1)
	161 getfield (0, 1)
	164 invokeinterface (0, 1)
	169 checkcast (0, 1)
	172 iconst_2 (0, 1)
	173 invokeinterface (0, 1)
	178 checkcast (0, 1)
	181 areturn (0, 1)

Method: getAngles
	0 aload_2 (1, 1)
	1 getstatic (1, 1)
	4 if_acmpne (1, 1)
	7 aload_1 (2, 1)
	8 getstatic (2, 1)
	11 if_acmpne (2, 1)
	14 aload_0 (2, 1)
	15 aload_0 (2, 1)
	16 dconst_0 (2, 1)
	17 dconst_0 (2, 1)
	18 dconst_1 (2, 1)
	19 invokespecial (2, 1)
	22 invokevirtual (2, 1)
	25 astore_3 (2, 1)
	26 aload_0 (2, 1)
	27 aload_0 (2, 1)
	28 dconst_1 (2, 1)
	29 dconst_0 (2, 1)
	30 dconst_0 (2, 1)
	31 invokespecial (2, 1)
	34 invokevirtual (2, 1)
	37 astore (2, 1)
	39 aload (3, 1)
	41 invokevirtual (3, 1)
	44 invokeinterface (3, 1)
	49 ldc2_w (3, 1)
	52 dcmpg (3, 1)
	53 iflt (3, 1)
	56 aload (3, 1)
	58 invokevirtual (3, 1)
	61 invokeinterface (3, 1)
	66 ldc2_w (3, 1)
	69 dcmpl (3, 1)
	70 ifle (3, 1)
	73 new (3, 1)
	76 dup (3, 1)
	77 iconst_1 (3, 1)
	78 invokespecial (3, 1)
	81 athrow (3, 1)
	82 aload_0 (2, 1)
	83 aload_3 (2, 1)
	84 invokevirtual (2, 1)
	87 invokeinterface (2, 1)
	92 checkcast (2, 1)
	95 aload_3 (2, 1)
	96 invokevirtual (2, 1)
	99 invokeinterface (2, 1)
	104 checkcast (2, 1)
	107 aload (2, 1)
	109 invokevirtual (2, 1)
	112 invokeinterface (2, 1)
	117 checkcast (2, 1)
	120 aload (2, 1)
	122 invokevirtual (2, 1)
	125 invokeinterface (2, 1)
	130 checkcast (2, 1)
	133 aload (2, 1)
	135 invokevirtual (2, 1)
	138 invokeinterface (2, 1)
	143 checkcast (2, 1)
	146 invokespecial (2, 1)
	149 areturn (2, 1)
	150 aload_1 (2, 1)
	151 getstatic (2, 1)
	154 if_acmpne (2, 1)
	157 aload_0 (2, 1)
	158 aload_0 (2, 1)
	159 dconst_0 (2, 1)
	160 dconst_1 (2, 1)
	161 dconst_0 (2, 1)
	162 invokespecial (2, 1)
	165 invokevirtual (2, 1)
	168 astore_3 (2, 1)
	169 aload_0 (2, 1)
	170 aload_0 (2, 1)
	171 dconst_1 (2, 1)
	172 dconst_0 (2, 1)
	173 dconst_0 (2, 1)
	174 invokespecial (2, 1)
	177 invokevirtual (2, 1)
	180 astore (2, 1)
	182 aload (3, 1)
	184 invokevirtual (3, 1)
	187 invokeinterface (3, 1)
	192 ldc2_w (3, 1)
	195 dcmpg (3, 1)
	196 iflt (3, 1)
	199 aload (3, 1)
	201 invokevirtual (3, 1)
	204 invokeinterface (3, 1)
	209 ldc2_w (3, 1)
	212 dcmpl (3, 1)
	213 ifle (3, 1)
	216 new (3, 1)
	219 dup (3, 1)
	220 iconst_1 (3, 1)
	221 invokespecial (3, 1)
	224 athrow (3, 1)
	225 aload_0 (2, 1)
	226 aload_3 (2, 1)
	227 invokevirtual (2, 1)
	230 aload_3 (2, 1)
	231 invokevirtual (2, 1)
	234 invokeinterface (2, 1)
	239 checkcast (2, 1)
	242 aload (2, 1)
	244 invokevirtual (2, 1)
	247 invokeinterface (2, 1)
	252 checkcast (2, 1)
	255 invokeinterface (2, 1)
	260 checkcast (2, 1)
	263 aload (2, 1)
	265 invokevirtual (2, 1)
	268 aload (2, 1)
	270 invokevirtual (2, 1)
	273 invokeinterface (2, 1)
	278 checkcast (2, 1)
	281 invokespecial (2, 1)
	284 areturn (2, 1)
	285 aload_1 (2, 1)
	286 getstatic (2, 1)
	289 if_acmpne (2, 1)
	292 aload_0 (2, 1)
	293 aload_0 (2, 1)
	294 dconst_0 (2, 1)
	295 dconst_0 (2, 1)
	296 dconst_1 (2, 1)
	297 invokespecial (2, 1)
	300 invokevirtual (2, 1)
	303 astore_3 (2, 1)
	304 aload_0 (2, 1)
	305 aload_0 (2, 1)
	306 dconst_0 (2, 1)
	307 dconst_1 (2, 1)
	308 dconst_0 (2, 1)
	309 invokespecial (2, 1)
	312 invokevirtual (2, 1)
	315 astore (2, 1)
	317 aload (3, 1)
	319 invokevirtual (3, 1)
	322 invokeinterface (3, 1)
	327 ldc2_w (3, 1)
	330 dcmpg (3, 1)
	331 iflt (3, 1)
	334 aload (3, 1)
	336 invokevirtual (3, 1)
	339 invokeinterface (3, 1)
	344 ldc2_w (3, 1)
	347 dcmpl (3, 1)
	348 ifle (3, 1)
	351 new (3, 1)
	354 dup (3, 1)
	355 iconst_1 (3, 1)
	356 invokespecial (3, 1)
	359 athrow (3, 1)
	360 aload_0 (2, 1)
	361 aload_3 (2, 1)
	362 invokevirtual (2, 1)
	365 aload_3 (2, 1)
	366 invokevirtual (2, 1)
	369 invokeinterface (2, 1)
	374 checkcast (2, 1)
	377 aload (2, 1)
	379 invokevirtual (2, 1)
	382 invokeinterface (2, 1)
	387 checkcast (2, 1)
	390 invokeinterface (2, 1)
	395 checkcast (2, 1)
	398 aload (2, 1)
	400 invokevirtual (2, 1)
	403 aload (2, 1)
	405 invokevirtual (2, 1)
	408 invokeinterface (2, 1)
	413 checkcast (2, 1)
	416 invokespecial (2, 1)
	419 areturn (2, 1)
	420 aload_1 (2, 1)
	421 getstatic (2, 1)
	424 if_acmpne (2, 1)
	427 aload_0 (2, 1)
	428 aload_0 (2, 1)
	429 dconst_1 (2, 1)
	430 dconst_0 (2, 1)
	431 dconst_0 (2, 1)
	432 invokespecial (2, 1)
	435 invokevirtual (2, 1)
	438 astore_3 (2, 1)
	439 aload_0 (2, 1)
	440 aload_0 (2, 1)
	441 dconst_0 (2, 1)
	442 dconst_1 (2, 1)
	443 dconst_0 (2, 1)
	444 invokespecial (2, 1)
	447 invokevirtual (2, 1)
	450 astore (2, 1)
	452 aload (3, 1)
	454 invokevirtual (3, 1)
	457 invokeinterface (3, 1)
	462 ldc2_w (3, 1)
	465 dcmpg (3, 1)
	466 iflt (3, 1)
	469 aload (3, 1)
	471 invokevirtual (3, 1)
	474 invokeinterface (3, 1)
	479 ldc2_w (3, 1)
	482 dcmpl (3, 1)
	483 ifle (3, 1)
	486 new (3, 1)
	489 dup (3, 1)
	490 iconst_1 (3, 1)
	491 invokespecial (3, 1)
	494 athrow (3, 1)
	495 aload_0 (2, 1)
	496 aload_3 (2, 1)
	497 invokevirtual (2, 1)
	500 invokeinterface (2, 1)
	505 checkcast (2, 1)
	508 aload_3 (2, 1)
	509 invokevirtual (2, 1)
	512 invokeinterface (2, 1)
	517 checkcast (2, 1)
	520 aload (2, 1)
	522 invokevirtual (2, 1)
	525 invokeinterface (2, 1)
	530 checkcast (2, 1)
	533 aload (2, 1)
	535 invokevirtual (2, 1)
	538 invokeinterface (2, 1)
	543 checkcast (2, 1)
	546 aload (2, 1)
	548 invokevirtual (2, 1)
	551 invokeinterface (2, 1)
	556 checkcast (2, 1)
	559 invokespecial (2, 1)
	562 areturn (2, 1)
	563 aload_1 (2, 1)
	564 getstatic (2, 1)
	567 if_acmpne (2, 1)
	570 aload_0 (2, 1)
	571 aload_0 (2, 1)
	572 dconst_0 (2, 1)
	573 dconst_1 (2, 1)
	574 dconst_0 (2, 1)
	575 invokespecial (2, 1)
	578 invokevirtual (2, 1)
	581 astore_3 (2, 1)
	582 aload_0 (2, 1)
	583 aload_0 (2, 1)
	584 dconst_0 (2, 1)
	585 dconst_0 (2, 1)
	586 dconst_1 (2, 1)
	587 invokespecial (2, 1)
	590 invokevirtual (2, 1)
	593 astore (2, 1)
	595 aload (3, 1)
	597 invokevirtual (3, 1)
	600 invokeinterface (3, 1)
	605 ldc2_w (3, 1)
	608 dcmpg (3, 1)
	609 iflt (3, 1)
	612 aload (3, 1)
	614 invokevirtual (3, 1)
	617 invokeinterface (3, 1)
	622 ldc2_w (3, 1)
	625 dcmpl (3, 1)
	626 ifle (3, 1)
	629 new (3, 1)
	632 dup (3, 1)
	633 iconst_1 (3, 1)
	634 invokespecial (3, 1)
	637 athrow (3, 1)
	638 aload_0 (2, 1)
	639 aload_3 (2, 1)
	640 invokevirtual (2, 1)
	643 invokeinterface (2, 1)
	648 checkcast (2, 1)
	651 aload_3 (2, 1)
	652 invokevirtual (2, 1)
	655 invokeinterface (2, 1)
	660 checkcast (2, 1)
	663 aload (2, 1)
	665 invokevirtual (2, 1)
	668 invokeinterface (2, 1)
	673 checkcast (2, 1)
	676 aload (2, 1)
	678 invokevirtual (2, 1)
	681 invokeinterface (2, 1)
	686 checkcast (2, 1)
	689 aload (2, 1)
	691 invokevirtual (2, 1)
	694 invokeinterface (2, 1)
	699 checkcast (2, 1)
	702 invokespecial (2, 1)
	705 areturn (2, 1)
	706 aload_1 (2, 1)
	707 getstatic (2, 1)
	710 if_acmpne (2, 1)
	713 aload_0 (2, 1)
	714 aload_0 (2, 1)
	715 dconst_1 (2, 1)
	716 dconst_0 (2, 1)
	717 dconst_0 (2, 1)
	718 invokespecial (2, 1)
	721 invokevirtual (2, 1)
	724 astore_3 (2, 1)
	725 aload_0 (2, 1)
	726 aload_0 (2, 1)
	727 dconst_0 (2, 1)
	728 dconst_0 (2, 1)
	729 dconst_1 (2, 1)
	730 invokespecial (2, 1)
	733 invokevirtual (2, 1)
	736 astore (2, 1)
	738 aload (3, 1)
	740 invokevirtual (3, 1)
	743 invokeinterface (3, 1)
	748 ldc2_w (3, 1)
	751 dcmpg (3, 1)
	752 iflt (3, 1)
	755 aload (3, 1)
	757 invokevirtual (3, 1)
	760 invokeinterface (3, 1)
	765 ldc2_w (3, 1)
	768 dcmpl (3, 1)
	769 ifle (3, 1)
	772 new (3, 1)
	775 dup (3, 1)
	776 iconst_1 (3, 1)
	777 invokespecial (3, 1)
	780 athrow (3, 1)
	781 aload_0 (2, 1)
	782 aload_3 (2, 1)
	783 invokevirtual (2, 1)
	786 aload_3 (2, 1)
	787 invokevirtual (2, 1)
	790 invokeinterface (2, 1)
	795 checkcast (2, 1)
	798 aload (2, 1)
	800 invokevirtual (2, 1)
	803 invokeinterface (2, 1)
	808 checkcast (2, 1)
	811 invokeinterface (2, 1)
	816 checkcast (2, 1)
	819 aload (2, 1)
	821 invokevirtual (2, 1)
	824 aload (2, 1)
	826 invokevirtual (2, 1)
	829 invokeinterface (2, 1)
	834 checkcast (2, 1)
	837 invokespecial (2, 1)
	840 areturn (2, 1)
	841 aload_1 (2, 1)
	842 getstatic (2, 1)
	845 if_acmpne (2, 1)
	848 aload_0 (2, 1)
	849 aload_0 (2, 1)
	850 dconst_1 (2, 1)
	851 dconst_0 (2, 1)
	852 dconst_0 (2, 1)
	853 invokespecial (2, 1)
	856 invokevirtual (2, 1)
	859 astore_3 (2, 1)
	860 aload_0 (2, 1)
	861 aload_0 (2, 1)
	862 dconst_1 (2, 1)
	863 dconst_0 (2, 1)
	864 dconst_0 (2, 1)
	865 invokespecial (2, 1)
	868 invokevirtual (2, 1)
	871 astore (2, 1)
	873 aload (3, 1)
	875 invokevirtual (3, 1)
	878 invokeinterface (3, 1)
	883 ldc2_w (3, 1)
	886 dcmpg (3, 1)
	887 iflt (3, 1)
	890 aload (3, 1)
	892 invokevirtual (3, 1)
	895 invokeinterface (3, 1)
	900 ldc2_w (3, 1)
	903 dcmpl (3, 1)
	904 ifle (3, 1)
	907 new (3, 1)
	910 dup (3, 1)
	911 iconst_0 (3, 1)
	912 invokespecial (3, 1)
	915 athrow (3, 1)
	916 aload_0 (2, 1)
	917 aload_3 (2, 1)
	918 invokevirtual (2, 1)
	921 aload_3 (2, 1)
	922 invokevirtual (2, 1)
	925 invokeinterface (2, 1)
	930 invokeinterface (2, 1)
	935 checkcast (2, 1)
	938 aload (2, 1)
	940 invokevirtual (2, 1)
	943 invokeinterface (2, 1)
	948 checkcast (2, 1)
	951 aload (2, 1)
	953 invokevirtual (2, 1)
	956 aload (2, 1)
	958 invokevirtual (2, 1)
	961 invokeinterface (2, 1)
	966 checkcast (2, 1)
	969 invokespecial (2, 1)
	972 areturn (2, 1)
	973 aload_1 (2, 1)
	974 getstatic (2, 1)
	977 if_acmpne (2, 1)
	980 aload_0 (2, 1)
	981 aload_0 (2, 1)
	982 dconst_1 (2, 1)
	983 dconst_0 (2, 1)
	984 dconst_0 (2, 1)
	985 invokespecial (2, 1)
	988 invokevirtual (2, 1)
	991 astore_3 (2, 1)
	992 aload_0 (2, 1)
	993 aload_0 (2, 1)
	994 dconst_1 (2, 1)
	995 dconst_0 (2, 1)
	996 dconst_0 (2, 1)
	997 invokespecial (2, 1)
	1000 invokevirtual (2, 1)
	1003 astore (2, 1)
	1005 aload (3, 1)
	1007 invokevirtual (3, 1)
	1010 invokeinterface (3, 1)
	1015 ldc2_w (3, 1)
	1018 dcmpg (3, 1)
	1019 iflt (3, 1)
	1022 aload (3, 1)
	1024 invokevirtual (3, 1)
	1027 invokeinterface (3, 1)
	1032 ldc2_w (3, 1)
	1035 dcmpl (3, 1)
	1036 ifle (3, 1)
	1039 new (3, 1)
	1042 dup (3, 1)
	1043 iconst_0 (3, 1)
	1044 invokespecial (3, 1)
	1047 athrow (3, 1)
	1048 aload_0 (2, 1)
	1049 aload_3 (2, 1)
	1050 invokevirtual (2, 1)
	1053 aload_3 (2, 1)
	1054 invokevirtual (2, 1)
	1057 invokeinterface (2, 1)
	1062 checkcast (2, 1)
	1065 aload (2, 1)
	1067 invokevirtual (2, 1)
	1070 invokeinterface (2, 1)
	1075 checkcast (2, 1)
	1078 aload (2, 1)
	1080 invokevirtual (2, 1)
	1083 aload (2, 1)
	1085 invokevirtual (2, 1)
	1088 invokeinterface (2, 1)
	1093 invokeinterface (2, 1)
	1098 checkcast (2, 1)
	1101 invokespecial (2, 1)
	1104 areturn (2, 1)
	1105 aload_1 (2, 1)
	1106 getstatic (2, 1)
	1109 if_acmpne (2, 1)
	1112 aload_0 (2, 1)
	1113 aload_0 (2, 1)
	1114 dconst_0 (2, 1)
	1115 dconst_1 (2, 1)
	1116 dconst_0 (2, 1)
	1117 invokespecial (2, 1)
	1120 invokevirtual (2, 1)
	1123 astore_3 (2, 1)
	1124 aload_0 (2, 1)
	1125 aload_0 (2, 1)
	1126 dconst_0 (2, 1)
	1127 dconst_1 (2, 1)
	1128 dconst_0 (2, 1)
	1129 invokespecial (2, 1)
	1132 invokevirtual (2, 1)
	1135 astore (2, 1)
	1137 aload (3, 1)
	1139 invokevirtual (3, 1)
	1142 invokeinterface (3, 1)
	1147 ldc2_w (3, 1)
	1150 dcmpg (3, 1)
	1151 iflt (3, 1)
	1154 aload (3, 1)
	1156 invokevirtual (3, 1)
	1159 invokeinterface (3, 1)
	1164 ldc2_w (3, 1)
	1167 dcmpl (3, 1)
	1168 ifle (3, 1)
	1171 new (3, 1)
	1174 dup (3, 1)
	1175 iconst_0 (3, 1)
	1176 invokespecial (3, 1)
	1179 athrow (3, 1)
	1180 aload_0 (2, 1)
	1181 aload_3 (2, 1)
	1182 invokevirtual (2, 1)
	1185 aload_3 (2, 1)
	1186 invokevirtual (2, 1)
	1189 invokeinterface (2, 1)
	1194 checkcast (2, 1)
	1197 aload (2, 1)
	1199 invokevirtual (2, 1)
	1202 invokeinterface (2, 1)
	1207 checkcast (2, 1)
	1210 aload (2, 1)
	1212 invokevirtual (2, 1)
	1215 aload (2, 1)
	1217 invokevirtual (2, 1)
	1220 invokeinterface (2, 1)
	1225 invokeinterface (2, 1)
	1230 checkcast (2, 1)
	1233 invokespecial (2, 1)
	1236 areturn (2, 1)
	1237 aload_1 (2, 1)
	1238 getstatic (2, 1)
	1241 if_acmpne (2, 1)
	1244 aload_0 (2, 1)
	1245 aload_0 (2, 1)
	1246 dconst_0 (2, 1)
	1247 dconst_1 (2, 1)
	1248 dconst_0 (2, 1)
	1249 invokespecial (2, 1)
	1252 invokevirtual (2, 1)
	1255 astore_3 (2, 1)
	1256 aload_0 (2, 1)
	1257 aload_0 (2, 1)
	1258 dconst_0 (2, 1)
	1259 dconst_1 (2, 1)
	1260 dconst_0 (2, 1)
	1261 invokespecial (2, 1)
	1264 invokevirtual (2, 1)
	1267 astore (2, 1)
	1269 aload (3, 1)
	1271 invokevirtual (3, 1)
	1274 invokeinterface (3, 1)
	1279 ldc2_w (3, 1)
	1282 dcmpg (3, 1)
	1283 iflt (3, 1)
	1286 aload (3, 1)
	1288 invokevirtual (3, 1)
	1291 invokeinterface (3, 1)
	1296 ldc2_w (3, 1)
	1299 dcmpl (3, 1)
	1300 ifle (3, 1)
	1303 new (3, 1)
	1306 dup (3, 1)
	1307 iconst_0 (3, 1)
	1308 invokespecial (3, 1)
	1311 athrow (3, 1)
	1312 aload_0 (2, 1)
	1313 aload_3 (2, 1)
	1314 invokevirtual (2, 1)
	1317 aload_3 (2, 1)
	1318 invokevirtual (2, 1)
	1321 invokeinterface (2, 1)
	1326 invokeinterface (2, 1)
	1331 checkcast (2, 1)
	1334 aload (2, 1)
	1336 invokevirtual (2, 1)
	1339 invokeinterface (2, 1)
	1344 checkcast (2, 1)
	1347 aload (2, 1)
	1349 invokevirtual (2, 1)
	1352 aload (2, 1)
	1354 invokevirtual (2, 1)
	1357 invokeinterface (2, 1)
	1362 checkcast (2, 1)
	1365 invokespecial (2, 1)
	1368 areturn (2, 1)
	1369 aload_1 (2, 1)
	1370 getstatic (2, 1)
	1373 if_acmpne (2, 1)
	1376 aload_0 (2, 1)
	1377 aload_0 (2, 1)
	1378 dconst_0 (2, 1)
	1379 dconst_0 (2, 1)
	1380 dconst_1 (2, 1)
	1381 invokespecial (2, 1)
	1384 invokevirtual (2, 1)
	1387 astore_3 (2, 1)
	1388 aload_0 (2, 1)
	1389 aload_0 (2, 1)
	1390 dconst_0 (2, 1)
	1391 dconst_0 (2, 1)
	1392 dconst_1 (2, 1)
	1393 invokespecial (2, 1)
	1396 invokevirtual (2, 1)
	1399 astore (2, 1)
	1401 aload (3, 1)
	1403 invokevirtual (3, 1)
	1406 invokeinterface (3, 1)
	1411 ldc2_w (3, 1)
	1414 dcmpg (3, 1)
	1415 iflt (3, 1)
	1418 aload (3, 1)
	1420 invokevirtual (3, 1)
	1423 invokeinterface (3, 1)
	1428 ldc2_w (3, 1)
	1431 dcmpl (3, 1)
	1432 ifle (3, 1)
	1435 new (3, 1)
	1438 dup (3, 1)
	1439 iconst_0 (3, 1)
	1440 invokespecial (3, 1)
	1443 athrow (3, 1)
	1444 aload_0 (2, 1)
	1445 aload_3 (2, 1)
	1446 invokevirtual (2, 1)
	1449 aload_3 (2, 1)
	1450 invokevirtual (2, 1)
	1453 invokeinterface (2, 1)
	1458 invokeinterface (2, 1)
	1463 checkcast (2, 1)
	1466 aload (2, 1)
	1468 invokevirtual (2, 1)
	1471 invokeinterface (2, 1)
	1476 checkcast (2, 1)
	1479 aload (2, 1)
	1481 invokevirtual (2, 1)
	1484 aload (2, 1)
	1486 invokevirtual (2, 1)
	1489 invokeinterface (2, 1)
	1494 checkcast (2, 1)
	1497 invokespecial (2, 1)
	1500 areturn (2, 1)
	1501 aload_0 (2, 2)
	1502 aload_0 (2, 2)
	1503 dconst_0 (2, 2)
	1504 dconst_0 (2, 2)
	1505 dconst_1 (2, 2)
	1506 invokespecial (2, 2)
	1509 invokevirtual (2, 2)
	1512 astore_3 (2, 2)
	1513 aload_0 (2, 2)
	1514 aload_0 (2, 2)
	1515 dconst_0 (2, 2)
	1516 dconst_0 (2, 2)
	1517 dconst_1 (2, 2)
	1518 invokespecial (2, 2)
	1521 invokevirtual (2, 2)
	1524 astore (2, 2)
	1526 aload (3, 1)
	1528 invokevirtual (3, 1)
	1531 invokeinterface (3, 1)
	1536 ldc2_w (3, 1)
	1539 dcmpg (3, 1)
	1540 iflt (3, 1)
	1543 aload (3, 1)
	1545 invokevirtual (3, 1)
	1548 invokeinterface (3, 1)
	1553 ldc2_w (3, 1)
	1556 dcmpl (3, 1)
	1557 ifle (3, 1)
	1560 new (3, 1)
	1563 dup (3, 1)
	1564 iconst_0 (3, 1)
	1565 invokespecial (3, 1)
	1568 athrow (3, 1)
	1569 aload_0 (2, 2)
	1570 aload_3 (2, 2)
	1571 invokevirtual (2, 2)
	1574 aload_3 (2, 2)
	1575 invokevirtual (2, 2)
	1578 invokeinterface (2, 2)
	1583 checkcast (2, 2)
	1586 aload (2, 2)
	1588 invokevirtual (2, 2)
	1591 invokeinterface (2, 2)
	1596 checkcast (2, 2)
	1599 aload (2, 2)
	1601 invokevirtual (2, 2)
	1604 aload (2, 2)
	1606 invokevirtual (2, 2)
	1609 invokeinterface (2, 2)
	1614 invokeinterface (2, 2)
	1619 checkcast (2, 2)
	1622 invokespecial (2, 2)
	1625 areturn (2, 2)
	1626 aload_1 (2, 1)
	1627 getstatic (2, 1)
	1630 if_acmpne (2, 1)
	1633 aload_0 (2, 1)
	1634 getstatic (2, 1)
	1637 invokevirtual (2, 1)
	1640 astore_3 (2, 1)
	1641 aload_0 (2, 1)
	1642 getstatic (2, 1)
	1645 invokevirtual (2, 1)
	1648 astore (2, 1)
	1650 aload (3, 1)
	1652 invokevirtual (3, 1)
	1655 invokeinterface (3, 1)
	1660 ldc2_w (3, 1)
	1663 dcmpg (3, 1)
	1664 iflt (3, 1)
	1667 aload (3, 1)
	1669 invokevirtual (3, 1)
	1672 invokeinterface (3, 1)
	1677 ldc2_w (3, 1)
	1680 dcmpl (3, 1)
	1681 ifle (3, 1)
	1684 new (3, 1)
	1687 dup (3, 1)
	1688 iconst_1 (3, 1)
	1689 invokespecial (3, 1)
	1692 athrow (3, 1)
	1693 aload_0 (2, 1)
	1694 aload (2, 1)
	1696 invokevirtual (2, 1)
	1699 invokeinterface (2, 1)
	1704 checkcast (2, 1)
	1707 aload (2, 1)
	1709 invokevirtual (2, 1)
	1712 invokeinterface (2, 1)
	1717 checkcast (2, 1)
	1720 aload (2, 1)
	1722 invokevirtual (2, 1)
	1725 invokeinterface (2, 1)
	1730 checkcast (2, 1)
	1733 aload_3 (2, 1)
	1734 invokevirtual (2, 1)
	1737 invokeinterface (2, 1)
	1742 checkcast (2, 1)
	1745 aload_3 (2, 1)
	1746 invokevirtual (2, 1)
	1749 invokeinterface (2, 1)
	1754 checkcast (2, 1)
	1757 invokespecial (2, 1)
	1760 areturn (2, 1)
	1761 aload_1 (2, 1)
	1762 getstatic (2, 1)
	1765 if_acmpne (2, 1)
	1768 aload_0 (2, 1)
	1769 getstatic (2, 1)
	1772 invokevirtual (2, 1)
	1775 astore_3 (2, 1)
	1776 aload_0 (2, 1)
	1777 getstatic (2, 1)
	1780 invokevirtual (2, 1)
	1783 astore (2, 1)
	1785 aload (3, 1)
	1787 invokevirtual (3, 1)
	1790 invokeinterface (3, 1)
	1795 ldc2_w (3, 1)
	1798 dcmpg (3, 1)
	1799 iflt (3, 1)
	1802 aload (3, 1)
	1804 invokevirtual (3, 1)
	1807 invokeinterface (3, 1)
	1812 ldc2_w (3, 1)
	1815 dcmpl (3, 1)
	1816 ifle (3, 1)
	1819 new (3, 1)
	1822 dup (3, 1)
	1823 iconst_1 (3, 1)
	1824 invokespecial (3, 1)
	1827 athrow (3, 1)
	1828 aload_0 (2, 1)
	1829 aload (2, 1)
	1831 invokevirtual (2, 1)
	1834 aload (2, 1)
	1836 invokevirtual (2, 1)
	1839 invokeinterface (2, 1)
	1844 checkcast (2, 1)
	1847 aload (2, 1)
	1849 invokevirtual (2, 1)
	1852 invokeinterface (2, 1)
	1857 checkcast (2, 1)
	1860 invokeinterface (2, 1)
	1865 checkcast (2, 1)
	1868 aload_3 (2, 1)
	1869 invokevirtual (2, 1)
	1872 aload_3 (2, 1)
	1873 invokevirtual (2, 1)
	1876 invokeinterface (2, 1)
	1881 checkcast (2, 1)
	1884 invokespecial (2, 1)
	1887 areturn (2, 1)
	1888 aload_1 (2, 1)
	1889 getstatic (2, 1)
	1892 if_acmpne (2, 1)
	1895 aload_0 (2, 1)
	1896 getstatic (2, 1)
	1899 invokevirtual (2, 1)
	1902 astore_3 (2, 1)
	1903 aload_0 (2, 1)
	1904 getstatic (2, 1)
	1907 invokevirtual (2, 1)
	1910 astore (2, 1)
	1912 aload (3, 1)
	1914 invokevirtual (3, 1)
	1917 invokeinterface (3, 1)
	1922 ldc2_w (3, 1)
	1925 dcmpg (3, 1)
	1926 iflt (3, 1)
	1929 aload (3, 1)
	1931 invokevirtual (3, 1)
	1934 invokeinterface (3, 1)
	1939 ldc2_w (3, 1)
	1942 dcmpl (3, 1)
	1943 ifle (3, 1)
	1946 new (3, 1)
	1949 dup (3, 1)
	1950 iconst_1 (3, 1)
	1951 invokespecial (3, 1)
	1954 athrow (3, 1)
	1955 aload_0 (2, 1)
	1956 aload (2, 1)
	1958 invokevirtual (2, 1)
	1961 aload (2, 1)
	1963 invokevirtual (2, 1)
	1966 invokeinterface (2, 1)
	1971 checkcast (2, 1)
	1974 aload (2, 1)
	1976 invokevirtual (2, 1)
	1979 invokeinterface (2, 1)
	1984 checkcast (2, 1)
	1987 invokeinterface (2, 1)
	1992 checkcast (2, 1)
	1995 aload_3 (2, 1)
	1996 invokevirtual (2, 1)
	1999 aload_3 (2, 1)
	2000 invokevirtual (2, 1)
	2003 invokeinterface (2, 1)
	2008 checkcast (2, 1)
	2011 invokespecial (2, 1)
	2014 areturn (2, 1)
	2015 aload_1 (2, 1)
	2016 getstatic (2, 1)
	2019 if_acmpne (2, 1)
	2022 aload_0 (2, 1)
	2023 getstatic (2, 1)
	2026 invokevirtual (2, 1)
	2029 astore_3 (2, 1)
	2030 aload_0 (2, 1)
	2031 getstatic (2, 1)
	2034 invokevirtual (2, 1)
	2037 astore (2, 1)
	2039 aload (3, 1)
	2041 invokevirtual (3, 1)
	2044 invokeinterface (3, 1)
	2049 ldc2_w (3, 1)
	2052 dcmpg (3, 1)
	2053 iflt (3, 1)
	2056 aload (3, 1)
	2058 invokevirtual (3, 1)
	2061 invokeinterface (3, 1)
	2066 ldc2_w (3, 1)
	2069 dcmpl (3, 1)
	2070 ifle (3, 1)
	2073 new (3, 1)
	2076 dup (3, 1)
	2077 iconst_1 (3, 1)
	2078 invokespecial (3, 1)
	2081 athrow (3, 1)
	2082 aload_0 (2, 1)
	2083 aload (2, 1)
	2085 invokevirtual (2, 1)
	2088 invokeinterface (2, 1)
	2093 checkcast (2, 1)
	2096 aload (2, 1)
	2098 invokevirtual (2, 1)
	2101 invokeinterface (2, 1)
	2106 checkcast (2, 1)
	2109 aload (2, 1)
	2111 invokevirtual (2, 1)
	2114 invokeinterface (2, 1)
	2119 checkcast (2, 1)
	2122 aload_3 (2, 1)
	2123 invokevirtual (2, 1)
	2126 invokeinterface (2, 1)
	2131 checkcast (2, 1)
	2134 aload_3 (2, 1)
	2135 invokevirtual (2, 1)
	2138 invokeinterface (2, 1)
	2143 checkcast (2, 1)
	2146 invokespecial (2, 1)
	2149 areturn (2, 1)
	2150 aload_1 (2, 1)
	2151 getstatic (2, 1)
	2154 if_acmpne (2, 1)
	2157 aload_0 (2, 1)
	2158 getstatic (2, 1)
	2161 invokevirtual (2, 1)
	2164 astore_3 (2, 1)
	2165 aload_0 (2, 1)
	2166 getstatic (2, 1)
	2169 invokevirtual (2, 1)
	2172 astore (2, 1)
	2174 aload (3, 1)
	2176 invokevirtual (3, 1)
	2179 invokeinterface (3, 1)
	2184 ldc2_w (3, 1)
	2187 dcmpg (3, 1)
	2188 iflt (3, 1)
	2191 aload (3, 1)
	2193 invokevirtual (3, 1)
	2196 invokeinterface (3, 1)
	2201 ldc2_w (3, 1)
	2204 dcmpl (3, 1)
	2205 ifle (3, 1)
	2208 new (3, 1)
	2211 dup (3, 1)
	2212 iconst_1 (3, 1)
	2213 invokespecial (3, 1)
	2216 athrow (3, 1)
	2217 aload_0 (2, 1)
	2218 aload (2, 1)
	2220 invokevirtual (2, 1)
	2223 invokeinterface (2, 1)
	2228 checkcast (2, 1)
	2231 aload (2, 1)
	2233 invokevirtual (2, 1)
	2236 invokeinterface (2, 1)
	2241 checkcast (2, 1)
	2244 aload (2, 1)
	2246 invokevirtual (2, 1)
	2249 invokeinterface (2, 1)
	2254 checkcast (2, 1)
	2257 aload_3 (2, 1)
	2258 invokevirtual (2, 1)
	2261 invokeinterface (2, 1)
	2266 checkcast (2, 1)
	2269 aload_3 (2, 1)
	2270 invokevirtual (2, 1)
	2273 invokeinterface (2, 1)
	2278 checkcast (2, 1)
	2281 invokespecial (2, 1)
	2284 areturn (2, 1)
	2285 aload_1 (2, 1)
	2286 getstatic (2, 1)
	2289 if_acmpne (2, 1)
	2292 aload_0 (2, 1)
	2293 getstatic (2, 1)
	2296 invokevirtual (2, 1)
	2299 astore_3 (2, 1)
	2300 aload_0 (2, 1)
	2301 getstatic (2, 1)
	2304 invokevirtual (2, 1)
	2307 astore (2, 1)
	2309 aload (3, 1)
	2311 invokevirtual (3, 1)
	2314 invokeinterface (3, 1)
	2319 ldc2_w (3, 1)
	2322 dcmpg (3, 1)
	2323 iflt (3, 1)
	2326 aload (3, 1)
	2328 invokevirtual (3, 1)
	2331 invokeinterface (3, 1)
	2336 ldc2_w (3, 1)
	2339 dcmpl (3, 1)
	2340 ifle (3, 1)
	2343 new (3, 1)
	2346 dup (3, 1)
	2347 iconst_1 (3, 1)
	2348 invokespecial (3, 1)
	2351 athrow (3, 1)
	2352 aload_0 (2, 1)
	2353 aload (2, 1)
	2355 invokevirtual (2, 1)
	2358 aload (2, 1)
	2360 invokevirtual (2, 1)
	2363 invokeinterface (2, 1)
	2368 checkcast (2, 1)
	2371 aload (2, 1)
	2373 invokevirtual (2, 1)
	2376 invokeinterface (2, 1)
	2381 checkcast (2, 1)
	2384 invokeinterface (2, 1)
	2389 checkcast (2, 1)
	2392 aload_3 (2, 1)
	2393 invokevirtual (2, 1)
	2396 aload_3 (2, 1)
	2397 invokevirtual (2, 1)
	2400 invokeinterface (2, 1)
	2405 checkcast (2, 1)
	2408 invokespecial (2, 1)
	2411 areturn (2, 1)
	2412 aload_1 (2, 1)
	2413 getstatic (2, 1)
	2416 if_acmpne (2, 1)
	2419 aload_0 (2, 1)
	2420 getstatic (2, 1)
	2423 invokevirtual (2, 1)
	2426 astore_3 (2, 1)
	2427 aload_0 (2, 1)
	2428 getstatic (2, 1)
	2431 invokevirtual (2, 1)
	2434 astore (2, 1)
	2436 aload (3, 1)
	2438 invokevirtual (3, 1)
	2441 invokeinterface (3, 1)
	2446 ldc2_w (3, 1)
	2449 dcmpg (3, 1)
	2450 iflt (3, 1)
	2453 aload (3, 1)
	2455 invokevirtual (3, 1)
	2458 invokeinterface (3, 1)
	2463 ldc2_w (3, 1)
	2466 dcmpl (3, 1)
	2467 ifle (3, 1)
	2470 new (3, 1)
	2473 dup (3, 1)
	2474 iconst_0 (3, 1)
	2475 invokespecial (3, 1)
	2478 athrow (3, 1)
	2479 aload_0 (2, 1)
	2480 aload (2, 1)
	2482 invokevirtual (2, 1)
	2485 aload (2, 1)
	2487 invokevirtual (2, 1)
	2490 invokeinterface (2, 1)
	2495 invokeinterface (2, 1)
	2500 checkcast (2, 1)
	2503 aload (2, 1)
	2505 invokevirtual (2, 1)
	2508 invokeinterface (2, 1)
	2513 checkcast (2, 1)
	2516 aload_3 (2, 1)
	2517 invokevirtual (2, 1)
	2520 aload_3 (2, 1)
	2521 invokevirtual (2, 1)
	2524 invokeinterface (2, 1)
	2529 checkcast (2, 1)
	2532 invokespecial (2, 1)
	2535 areturn (2, 1)
	2536 aload_1 (2, 1)
	2537 getstatic (2, 1)
	2540 if_acmpne (2, 1)
	2543 aload_0 (2, 1)
	2544 getstatic (2, 1)
	2547 invokevirtual (2, 1)
	2550 astore_3 (2, 1)
	2551 aload_0 (2, 1)
	2552 getstatic (2, 1)
	2555 invokevirtual (2, 1)
	2558 astore (2, 1)
	2560 aload (3, 1)
	2562 invokevirtual (3, 1)
	2565 invokeinterface (3, 1)
	2570 ldc2_w (3, 1)
	2573 dcmpg (3, 1)
	2574 iflt (3, 1)
	2577 aload (3, 1)
	2579 invokevirtual (3, 1)
	2582 invokeinterface (3, 1)
	2587 ldc2_w (3, 1)
	2590 dcmpl (3, 1)
	2591 ifle (3, 1)
	2594 new (3, 1)
	2597 dup (3, 1)
	2598 iconst_0 (3, 1)
	2599 invokespecial (3, 1)
	2602 athrow (3, 1)
	2603 aload_0 (2, 1)
	2604 aload (2, 1)
	2606 invokevirtual (2, 1)
	2609 aload (2, 1)
	2611 invokevirtual (2, 1)
	2614 invokeinterface (2, 1)
	2619 checkcast (2, 1)
	2622 aload (2, 1)
	2624 invokevirtual (2, 1)
	2627 invokeinterface (2, 1)
	2632 checkcast (2, 1)
	2635 aload_3 (2, 1)
	2636 invokevirtual (2, 1)
	2639 aload_3 (2, 1)
	2640 invokevirtual (2, 1)
	2643 invokeinterface (2, 1)
	2648 invokeinterface (2, 1)
	2653 checkcast (2, 1)
	2656 invokespecial (2, 1)
	2659 areturn (2, 1)
	2660 aload_1 (2, 1)
	2661 getstatic (2, 1)
	2664 if_acmpne (2, 1)
	2667 aload_0 (2, 1)
	2668 getstatic (2, 1)
	2671 invokevirtual (2, 1)
	2674 astore_3 (2, 1)
	2675 aload_0 (2, 1)
	2676 getstatic (2, 1)
	2679 invokevirtual (2, 1)
	2682 astore (2, 1)
	2684 aload (3, 1)
	2686 invokevirtual (3, 1)
	2689 invokeinterface (3, 1)
	2694 ldc2_w (3, 1)
	2697 dcmpg (3, 1)
	2698 iflt (3, 1)
	2701 aload (3, 1)
	2703 invokevirtual (3, 1)
	2706 invokeinterface (3, 1)
	2711 ldc2_w (3, 1)
	2714 dcmpl (3, 1)
	2715 ifle (3, 1)
	2718 new (3, 1)
	2721 dup (3, 1)
	2722 iconst_0 (3, 1)
	2723 invokespecial (3, 1)
	2726 athrow (3, 1)
	2727 aload_0 (2, 1)
	2728 aload (2, 1)
	2730 invokevirtual (2, 1)
	2733 aload (2, 1)
	2735 invokevirtual (2, 1)
	2738 invokeinterface (2, 1)
	2743 checkcast (2, 1)
	2746 aload (2, 1)
	2748 invokevirtual (2, 1)
	2751 invokeinterface (2, 1)
	2756 checkcast (2, 1)
	2759 aload_3 (2, 1)
	2760 invokevirtual (2, 1)
	2763 aload_3 (2, 1)
	2764 invokevirtual (2, 1)
	2767 invokeinterface (2, 1)
	2772 invokeinterface (2, 1)
	2777 checkcast (2, 1)
	2780 invokespecial (2, 1)
	2783 areturn (2, 1)
	2784 aload_1 (2, 1)
	2785 getstatic (2, 1)
	2788 if_acmpne (2, 1)
	2791 aload_0 (2, 1)
	2792 getstatic (2, 1)
	2795 invokevirtual (2, 1)
	2798 astore_3 (2, 1)
	2799 aload_0 (2, 1)
	2800 getstatic (2, 1)
	2803 invokevirtual (2, 1)
	2806 astore (2, 1)
	2808 aload (3, 1)
	2810 invokevirtual (3, 1)
	2813 invokeinterface (3, 1)
	2818 ldc2_w (3, 1)
	2821 dcmpg (3, 1)
	2822 iflt (3, 1)
	2825 aload (3, 1)
	2827 invokevirtual (3, 1)
	2830 invokeinterface (3, 1)
	2835 ldc2_w (3, 1)
	2838 dcmpl (3, 1)
	2839 ifle (3, 1)
	2842 new (3, 1)
	2845 dup (3, 1)
	2846 iconst_0 (3, 1)
	2847 invokespecial (3, 1)
	2850 athrow (3, 1)
	2851 aload_0 (2, 1)
	2852 aload (2, 1)
	2854 invokevirtual (2, 1)
	2857 aload (2, 1)
	2859 invokevirtual (2, 1)
	2862 invokeinterface (2, 1)
	2867 invokeinterface (2, 1)
	2872 checkcast (2, 1)
	2875 aload (2, 1)
	2877 invokevirtual (2, 1)
	2880 invokeinterface (2, 1)
	2885 checkcast (2, 1)
	2888 aload_3 (2, 1)
	2889 invokevirtual (2, 1)
	2892 aload_3 (2, 1)
	2893 invokevirtual (2, 1)
	2896 invokeinterface (2, 1)
	2901 checkcast (2, 1)
	2904 invokespecial (2, 1)
	2907 areturn (2, 1)
	2908 aload_1 (2, 1)
	2909 getstatic (2, 1)
	2912 if_acmpne (2, 1)
	2915 aload_0 (2, 1)
	2916 getstatic (2, 1)
	2919 invokevirtual (2, 1)
	2922 astore_3 (2, 1)
	2923 aload_0 (2, 1)
	2924 getstatic (2, 1)
	2927 invokevirtual (2, 1)
	2930 astore (2, 1)
	2932 aload (3, 1)
	2934 invokevirtual (3, 1)
	2937 invokeinterface (3, 1)
	2942 ldc2_w (3, 1)
	2945 dcmpg (3, 1)
	2946 iflt (3, 1)
	2949 aload (3, 1)
	2951 invokevirtual (3, 1)
	2954 invokeinterface (3, 1)
	2959 ldc2_w (3, 1)
	2962 dcmpl (3, 1)
	2963 ifle (3, 1)
	2966 new (3, 1)
	2969 dup (3, 1)
	2970 iconst_0 (3, 1)
	2971 invokespecial (3, 1)
	2974 athrow (3, 1)
	2975 aload_0 (2, 1)
	2976 aload (2, 1)
	2978 invokevirtual (2, 1)
	2981 aload (2, 1)
	2983 invokevirtual (2, 1)
	2986 invokeinterface (2, 1)
	2991 invokeinterface (2, 1)
	2996 checkcast (2, 1)
	2999 aload (2, 1)
	3001 invokevirtual (2, 1)
	3004 invokeinterface (2, 1)
	3009 checkcast (2, 1)
	3012 aload_3 (2, 1)
	3013 invokevirtual (2, 1)
	3016 aload_3 (2, 1)
	3017 invokevirtual (2, 1)
	3020 invokeinterface (2, 1)
	3025 checkcast (2, 1)
	3028 invokespecial (2, 1)
	3031 areturn (2, 1)
	3032 aload_0 (2, 2)
	3033 getstatic (2, 2)
	3036 invokevirtual (2, 2)
	3039 astore_3 (2, 2)
	3040 aload_0 (2, 2)
	3041 getstatic (2, 2)
	3044 invokevirtual (2, 2)
	3047 astore (2, 2)
	3049 aload (3, 1)
	3051 invokevirtual (3, 1)
	3054 invokeinterface (3, 1)
	3059 ldc2_w (3, 1)
	3062 dcmpg (3, 1)
	3063 iflt (3, 1)
	3066 aload (3, 1)
	3068 invokevirtual (3, 1)
	3071 invokeinterface (3, 1)
	3076 ldc2_w (3, 1)
	3079 dcmpl (3, 1)
	3080 ifle (3, 1)
	3083 new (3, 1)
	3086 dup (3, 1)
	3087 iconst_0 (3, 1)
	3088 invokespecial (3, 1)
	3091 athrow (3, 1)
	3092 aload_0 (2, 2)
	3093 aload (2, 2)
	3095 invokevirtual (2, 2)
	3098 aload (2, 2)
	3100 invokevirtual (2, 2)
	3103 invokeinterface (2, 2)
	3108 checkcast (2, 2)
	3111 aload (2, 2)
	3113 invokevirtual (2, 2)
	3116 invokeinterface (2, 2)
	3121 checkcast (2, 2)
	3124 aload_3 (2, 2)
	3125 invokevirtual (2, 2)
	3128 aload_3 (2, 2)
	3129 invokevirtual (2, 2)
	3132 invokeinterface (2, 2)
	3137 invokeinterface (2, 2)
	3142 checkcast (2, 2)
	3145 invokespecial (2, 2)
	3148 areturn (2, 2)

Method: buildArray
	0 aload_1 (0, 0)
	1 invokeinterface (0, 0)
	6 iconst_3 (0, 0)
	7 invokestatic (0, 0)
	10 checkcast (0, 0)
	13 astore (0, 0)
	15 aload (0, 0)
	17 iconst_0 (0, 0)
	18 aload_1 (0, 0)
	19 aastore (0, 0)
	20 aload (0, 0)
	22 iconst_1 (0, 0)
	23 aload_2 (0, 0)
	24 aastore (0, 0)
	25 aload (0, 0)
	27 iconst_2 (0, 0)
	28 aload_3 (0, 0)
	29 aastore (0, 0)
	30 aload (0, 0)
	32 areturn (0, 0)

Method: vector
	0 aload_0 (0, 0)
	1 getfield (0, 0)
	4 invokeinterface (0, 0)
	9 invokeinterface (0, 0)
	14 checkcast (0, 0)
	17 astore (0, 0)
	19 new (0, 0)
	22 dup (0, 0)
	23 aload (0, 0)
	25 dload_1 (0, 0)
	26 invokeinterface (0, 0)
	31 checkcast (0, 0)
	34 aload (0, 0)
	36 dload_3 (0, 0)
	37 invokeinterface (0, 0)
	42 checkcast (0, 0)
	45 aload (0, 0)
	47 dload (0, 0)
	49 invokeinterface (0, 0)
	54 checkcast (0, 0)
	57 invokespecial (0, 0)
	60 areturn (0, 0)

Method: getMatrix
	0 aload_0 (0, 0)
	1 getfield (0, 0)
	4 aload_0 (0, 0)
	5 getfield (0, 0)
	8 invokeinterface (0, 0)
	13 checkcast (0, 0)
	16 astore_1 (0, 0)
	17 aload_0 (0, 0)
	18 getfield (0, 0)
	21 aload_0 (0, 0)
	22 getfield (0, 0)
	25 invokeinterface (0, 0)
	30 checkcast (0, 0)
	33 astore_2 (0, 0)
	34 aload_0 (0, 0)
	35 getfield (0, 0)
	38 aload_0 (0, 0)
	39 getfield (0, 0)
	42 invokeinterface (0, 0)
	47 checkcast (0, 0)
	50 astore_3 (0, 0)
	51 aload_0 (0, 0)
	52 getfield (0, 0)
	55 aload_0 (0, 0)
	56 getfield (0, 0)
	59 invokeinterface (0, 0)
	64 checkcast (0, 0)
	67 astore (0, 0)
	69 aload_0 (0, 0)
	70 getfield (0, 0)
	73 aload_0 (0, 0)
	74 getfield (0, 0)
	77 invokeinterface (0, 0)
	82 checkcast (0, 0)
	85 astore (0, 0)
	87 aload_0 (0, 0)
	88 getfield (0, 0)
	91 aload_0 (0, 0)
	92 getfield (0, 0)
	95 invokeinterface (0, 0)
	100 checkcast (0, 0)
	103 astore (0, 0)
	105 aload_0 (0, 0)
	106 getfield (0, 0)
	109 aload_0 (0, 0)
	110 getfield (0, 0)
	113 invokeinterface (0, 0)
	118 checkcast (0, 0)
	121 astore (0, 0)
	123 aload_0 (0, 0)
	124 getfield (0, 0)
	127 aload_0 (0, 0)
	128 getfield (0, 0)
	131 invokeinterface (0, 0)
	136 checkcast (0, 0)
	139 astore (0, 0)
	141 aload_0 (0, 0)
	142 getfield (0, 0)
	145 aload_0 (0, 0)
	146 getfield (0, 0)
	149 invokeinterface (0, 0)
	154 checkcast (0, 0)
	157 astore (0, 0)
	159 aload_0 (0, 0)
	160 getfield (0, 0)
	163 aload_0 (0, 0)
	164 getfield (0, 0)
	167 invokeinterface (0, 0)
	172 checkcast (0, 0)
	175 astore (0, 0)
	177 aload_0 (0, 0)
	178 getfield (0, 0)
	181 invokeinterface (0, 0)
	186 iconst_3 (0, 0)
	187 iconst_3 (0, 0)
	188 invokestatic (0, 0)
	191 checkcast (0, 0)
	194 astore (0, 0)
	196 aload (0, 0)
	198 iconst_0 (0, 0)
	199 aaload (0, 0)
	200 iconst_0 (0, 0)
	201 aload_1 (0, 0)
	202 aload (0, 0)
	204 invokeinterface (0, 0)
	209 checkcast (0, 0)
	212 iconst_2 (0, 0)
	213 invokeinterface (0, 0)
	218 checkcast (0, 0)
	221 dconst_1 (0, 0)
	222 invokeinterface (0, 0)
	227 checkcast (0, 0)
	230 aastore (0, 0)
	231 aload (0, 0)
	233 iconst_1 (0, 0)
	234 aaload (0, 0)
	235 iconst_0 (0, 0)
	236 aload (0, 0)
	238 aload (0, 0)
	240 invokeinterface (0, 0)
	245 checkcast (0, 0)
	248 iconst_2 (0, 0)
	249 invokeinterface (0, 0)
	254 checkcast (0, 0)
	257 aastore (0, 0)
	258 aload (0, 0)
	260 iconst_2 (0, 0)
	261 aaload (0, 0)
	262 iconst_0 (0, 0)
	263 aload (0, 0)
	265 aload_3 (0, 0)
	266 invokeinterface (0, 0)
	271 checkcast (0, 0)
	274 iconst_2 (0, 0)
	275 invokeinterface (0, 0)
	280 checkcast (0, 0)
	283 aastore (0, 0)
	284 aload (0, 0)
	286 iconst_0 (0, 0)
	287 aaload (0, 0)
	288 iconst_1 (0, 0)
	289 aload (0, 0)
	291 aload (0, 0)
	293 invokeinterface (0, 0)
	298 checkcast (0, 0)
	301 iconst_2 (0, 0)
	302 invokeinterface (0, 0)
	307 checkcast (0, 0)
	310 aastore (0, 0)
	311 aload (0, 0)
	313 iconst_1 (0, 0)
	314 aaload (0, 0)
	315 iconst_1 (0, 0)
	316 aload_1 (0, 0)
	317 aload (0, 0)
	319 invokeinterface (0, 0)
	324 checkcast (0, 0)
	327 iconst_2 (0, 0)
	328 invokeinterface (0, 0)
	333 checkcast (0, 0)
	336 dconst_1 (0, 0)
	337 invokeinterface (0, 0)
	342 checkcast (0, 0)
	345 aastore (0, 0)
	346 aload (0, 0)
	348 iconst_2 (0, 0)
	349 aaload (0, 0)
	350 iconst_1 (0, 0)
	351 aload (0, 0)
	353 aload_2 (0, 0)
	354 invokeinterface (0, 0)
	359 checkcast (0, 0)
	362 iconst_2 (0, 0)
	363 invokeinterface (0, 0)
	368 checkcast (0, 0)
	371 aastore (0, 0)
	372 aload (0, 0)
	374 iconst_0 (0, 0)
	375 aaload (0, 0)
	376 iconst_2 (0, 0)
	377 aload (0, 0)
	379 aload_3 (0, 0)
	380 invokeinterface (0, 0)
	385 checkcast (0, 0)
	388 iconst_2 (0, 0)
	389 invokeinterface (0, 0)
	394 checkcast (0, 0)
	397 aastore (0, 0)
	398 aload (0, 0)
	400 iconst_1 (0, 0)
	401 aaload (0, 0)
	402 iconst_2 (0, 0)
	403 aload (0, 0)
	405 aload_2 (0, 0)
	406 invokeinterface (0, 0)
	411 checkcast (0, 0)
	414 iconst_2 (0, 0)
	415 invokeinterface (0, 0)
	420 checkcast (0, 0)
	423 aastore (0, 0)
	424 aload (0, 0)
	426 iconst_2 (0, 0)
	427 aaload (0, 0)
	428 iconst_2 (0, 0)
	429 aload_1 (0, 0)
	430 aload (0, 0)
	432 invokeinterface (0, 0)
	437 checkcast (0, 0)
	440 iconst_2 (0, 0)
	441 invokeinterface (0, 0)
	446 checkcast (0, 0)
	449 dconst_1 (0, 0)
	450 invokeinterface (0, 0)
	455 checkcast (0, 0)
	458 aastore (0, 0)
	459 aload (0, 0)
	461 areturn (0, 0)

Method: toRotation
	0 new (0, 0)
	3 dup (0, 0)
	4 aload_0 (0, 0)
	5 getfield (0, 0)
	8 invokeinterface (0, 0)
	13 aload_0 (0, 0)
	14 getfield (0, 0)
	17 invokeinterface (0, 0)
	22 aload_0 (0, 0)
	23 getfield (0, 0)
	26 invokeinterface (0, 0)
	31 aload_0 (0, 0)
	32 getfield (0, 0)
	35 invokeinterface (0, 0)
	40 iconst_0 (0, 0)
	41 invokespecial (0, 0)
	44 areturn (0, 0)

Method: applyTo
	0 new (0, 0)
	3 dup (0, 0)
	4 aload_1 (0, 0)
	5 getfield (0, 0)
	8 aload_0 (0, 0)
	9 invokevirtual (0, 0)
	12 invokeinterface (0, 0)
	17 checkcast (0, 0)
	20 aload_1 (0, 0)
	21 getfield (0, 0)
	24 aload_0 (0, 0)
	25 invokevirtual (0, 0)
	28 invokeinterface (0, 0)
	33 checkcast (0, 0)
	36 aload_1 (0, 0)
	37 getfield (0, 0)
	40 aload_0 (0, 0)
	41 invokevirtual (0, 0)
	44 invokeinterface (0, 0)
	49 invokeinterface (0, 0)
	54 checkcast (0, 0)
	57 aload_1 (0, 0)
	58 getfield (0, 0)
	61 aload_0 (0, 0)
	62 invokevirtual (0, 0)
	65 invokeinterface (0, 0)
	70 invokeinterface (0, 0)
	75 invokeinterface (0, 0)
	80 checkcast (0, 0)
	83 aload_1 (0, 0)
	84 getfield (0, 0)
	87 aload_0 (0, 0)
	88 invokevirtual (0, 0)
	91 invokeinterface (0, 0)
	96 checkcast (0, 0)
	99 aload_1 (0, 0)
	100 getfield (0, 0)
	103 aload_0 (0, 0)
	104 invokevirtual (0, 0)
	107 invokeinterface (0, 0)
	112 invokeinterface (0, 0)
	117 checkcast (0, 0)
	120 aload_1 (0, 0)
	121 getfield (0, 0)
	124 aload_0 (0, 0)
	125 invokevirtual (0, 0)
	128 invokeinterface (0, 0)
	133 checkcast (0, 0)
	136 aload_1 (0, 0)
	137 getfield (0, 0)
	140 aload_0 (0, 0)
	141 invokevirtual (0, 0)
	144 invokeinterface (0, 0)
	149 invokeinterface (0, 0)
	154 invokeinterface (0, 0)
	159 checkcast (0, 0)
	162 aload_1 (0, 0)
	163 getfield (0, 0)
	166 aload_0 (0, 0)
	167 invokevirtual (0, 0)
	170 invokeinterface (0, 0)
	175 checkcast (0, 0)
	178 aload_1 (0, 0)
	179 getfield (0, 0)
	182 aload_0 (0, 0)
	183 invokevirtual (0, 0)
	186 invokeinterface (0, 0)
	191 invokeinterface (0, 0)
	196 checkcast (0, 0)
	199 aload_1 (0, 0)
	200 getfield (0, 0)
	203 aload_0 (0, 0)
	204 invokevirtual (0, 0)
	207 invokeinterface (0, 0)
	212 checkcast (0, 0)
	215 aload_1 (0, 0)
	216 getfield (0, 0)
	219 aload_0 (0, 0)
	220 invokevirtual (0, 0)
	223 invokeinterface (0, 0)
	228 invokeinterface (0, 0)
	233 invokeinterface (0, 0)
	238 checkcast (0, 0)
	241 aload_1 (0, 0)
	242 getfield (0, 0)
	245 aload_0 (0, 0)
	246 invokevirtual (0, 0)
	249 invokeinterface (0, 0)
	254 checkcast (0, 0)
	257 aload_1 (0, 0)
	258 getfield (0, 0)
	261 aload_0 (0, 0)
	262 invokevirtual (0, 0)
	265 invokeinterface (0, 0)
	270 invokeinterface (0, 0)
	275 checkcast (0, 0)
	278 aload_1 (0, 0)
	279 getfield (0, 0)
	282 aload_0 (0, 0)
	283 invokevirtual (0, 0)
	286 invokeinterface (0, 0)
	291 checkcast (0, 0)
	294 aload_1 (0, 0)
	295 getfield (0, 0)
	298 aload_0 (0, 0)
	299 invokevirtual (0, 0)
	302 invokeinterface (0, 0)
	307 invokeinterface (0, 0)
	312 invokeinterface (0, 0)
	317 checkcast (0, 0)
	320 iconst_0 (0, 0)
	321 invokespecial (0, 0)
	324 areturn (0, 0)

Method: applyInverseTo
	0 new (0, 0)
	3 dup (0, 0)
	4 aload_1 (0, 0)
	5 getfield (0, 0)
	8 aload_0 (0, 0)
	9 invokevirtual (0, 0)
	12 invokeinterface (0, 0)
	17 checkcast (0, 0)
	20 aload_1 (0, 0)
	21 getfield (0, 0)
	24 aload_0 (0, 0)
	25 invokevirtual (0, 0)
	28 invokeinterface (0, 0)
	33 checkcast (0, 0)
	36 aload_1 (0, 0)
	37 getfield (0, 0)
	40 aload_0 (0, 0)
	41 invokevirtual (0, 0)
	44 invokeinterface (0, 0)
	49 invokeinterface (0, 0)
	54 checkcast (0, 0)
	57 aload_1 (0, 0)
	58 getfield (0, 0)
	61 aload_0 (0, 0)
	62 invokevirtual (0, 0)
	65 invokeinterface (0, 0)
	70 invokeinterface (0, 0)
	75 invokeinterface (0, 0)
	80 checkcast (0, 0)
	83 invokeinterface (0, 0)
	88 checkcast (0, 0)
	91 aload_1 (0, 0)
	92 getfield (0, 0)
	95 aload_0 (0, 0)
	96 invokevirtual (0, 0)
	99 invokeinterface (0, 0)
	104 checkcast (0, 0)
	107 aload_1 (0, 0)
	108 getfield (0, 0)
	111 aload_0 (0, 0)
	112 invokevirtual (0, 0)
	115 invokeinterface (0, 0)
	120 checkcast (0, 0)
	123 aload_1 (0, 0)
	124 getfield (0, 0)
	127 aload_0 (0, 0)
	128 invokevirtual (0, 0)
	131 invokeinterface (0, 0)
	136 invokeinterface (0, 0)
	141 invokeinterface (0, 0)
	146 checkcast (0, 0)
	149 aload_1 (0, 0)
	150 getfield (0, 0)
	153 aload_0 (0, 0)
	154 invokevirtual (0, 0)
	157 invokeinterface (0, 0)
	162 invokeinterface (0, 0)
	167 checkcast (0, 0)
	170 aload_1 (0, 0)
	171 getfield (0, 0)
	174 aload_0 (0, 0)
	175 invokevirtual (0, 0)
	178 invokeinterface (0, 0)
	183 checkcast (0, 0)
	186 aload_1 (0, 0)
	187 getfield (0, 0)
	190 aload_0 (0, 0)
	191 invokevirtual (0, 0)
	194 invokeinterface (0, 0)
	199 checkcast (0, 0)
	202 aload_1 (0, 0)
	203 getfield (0, 0)
	206 aload_0 (0, 0)
	207 invokevirtual (0, 0)
	210 invokeinterface (0, 0)
	215 invokeinterface (0, 0)
	220 invokeinterface (0, 0)
	225 checkcast (0, 0)
	228 aload_1 (0, 0)
	229 getfield (0, 0)
	232 aload_0 (0, 0)
	233 invokevirtual (0, 0)
	236 invokeinterface (0, 0)
	241 invokeinterface (0, 0)
	246 checkcast (0, 0)
	249 aload_1 (0, 0)
	250 getfield (0, 0)
	253 aload_0 (0, 0)
	254 invokevirtual (0, 0)
	257 invokeinterface (0, 0)
	262 checkcast (0, 0)
	265 aload_1 (0, 0)
	266 getfield (0, 0)
	269 aload_0 (0, 0)
	270 invokevirtual (0, 0)
	273 invokeinterface (0, 0)
	278 checkcast (0, 0)
	281 aload_1 (0, 0)
	282 getfield (0, 0)
	285 aload_0 (0, 0)
	286 invokevirtual (0, 0)
	289 invokeinterface (0, 0)
	294 invokeinterface (0, 0)
	299 invokeinterface (0, 0)
	304 checkcast (0, 0)
	307 aload_1 (0, 0)
	308 getfield (0, 0)
	311 aload_0 (0, 0)
	312 invokevirtual (0, 0)
	315 invokeinterface (0, 0)
	320 invokeinterface (0, 0)
	325 checkcast (0, 0)
	328 iconst_0 (0, 0)
	329 invokespecial (0, 0)
	332 areturn (0, 0)

Method: compose
	0 aload_2 (0, 0)
	1 getstatic (0, 0)
	4 if_acmpne (0, 0)
	7 aload_0 (0, 0)
	8 aload_1 (0, 0)
	9 invokespecial (0, 0)
	12 goto (0, 0)
	15 aload_1 (0, 0)
	16 aload_0 (0, 0)
	17 invokestatic (0, 0)
	20 areturn (0, 0)

Method: composeInternal
	0 new (0, 0)
	3 dup (0, 0)
	4 aload_0 (0, 0)
	5 getfield (0, 0)
	8 aload_1 (0, 0)
	9 invokevirtual (0, 0)
	12 invokeinterface (0, 0)
	17 checkcast (0, 0)
	20 aload_0 (0, 0)
	21 getfield (0, 0)
	24 aload_1 (0, 0)
	25 invokevirtual (0, 0)
	28 invokeinterface (0, 0)
	33 checkcast (0, 0)
	36 aload_0 (0, 0)
	37 getfield (0, 0)
	40 aload_1 (0, 0)
	41 invokevirtual (0, 0)
	44 invokeinterface (0, 0)
	49 invokeinterface (0, 0)
	54 checkcast (0, 0)
	57 aload_0 (0, 0)
	58 getfield (0, 0)
	61 aload_1 (0, 0)
	62 invokevirtual (0, 0)
	65 invokeinterface (0, 0)
	70 invokeinterface (0, 0)
	75 invokeinterface (0, 0)
	80 checkcast (0, 0)
	83 aload_0 (0, 0)
	84 getfield (0, 0)
	87 aload_1 (0, 0)
	88 invokevirtual (0, 0)
	91 invokeinterface (0, 0)
	96 checkcast (0, 0)
	99 aload_0 (0, 0)
	100 getfield (0, 0)
	103 aload_1 (0, 0)
	104 invokevirtual (0, 0)
	107 invokeinterface (0, 0)
	112 invokeinterface (0, 0)
	117 checkcast (0, 0)
	120 aload_0 (0, 0)
	121 getfield (0, 0)
	124 aload_1 (0, 0)
	125 invokevirtual (0, 0)
	128 invokeinterface (0, 0)
	133 checkcast (0, 0)
	136 aload_0 (0, 0)
	137 getfield (0, 0)
	140 aload_1 (0, 0)
	141 invokevirtual (0, 0)
	144 invokeinterface (0, 0)
	149 invokeinterface (0, 0)
	154 invokeinterface (0, 0)
	159 checkcast (0, 0)
	162 aload_0 (0, 0)
	163 getfield (0, 0)
	166 aload_1 (0, 0)
	167 invokevirtual (0, 0)
	170 invokeinterface (0, 0)
	175 checkcast (0, 0)
	178 aload_0 (0, 0)
	179 getfield (0, 0)
	182 aload_1 (0, 0)
	183 invokevirtual (0, 0)
	186 invokeinterface (0, 0)
	191 invokeinterface (0, 0)
	196 checkcast (0, 0)
	199 aload_0 (0, 0)
	200 getfield (0, 0)
	203 aload_1 (0, 0)
	204 invokevirtual (0, 0)
	207 invokeinterface (0, 0)
	212 checkcast (0, 0)
	215 aload_0 (0, 0)
	216 getfield (0, 0)
	219 aload_1 (0, 0)
	220 invokevirtual (0, 0)
	223 invokeinterface (0, 0)
	228 invokeinterface (0, 0)
	233 invokeinterface (0, 0)
	238 checkcast (0, 0)
	241 aload_0 (0, 0)
	242 getfield (0, 0)
	245 aload_1 (0, 0)
	246 invokevirtual (0, 0)
	249 invokeinterface (0, 0)
	254 checkcast (0, 0)
	257 aload_0 (0, 0)
	258 getfield (0, 0)
	261 aload_1 (0, 0)
	262 invokevirtual (0, 0)
	265 invokeinterface (0, 0)
	270 invokeinterface (0, 0)
	275 checkcast (0, 0)
	278 aload_0 (0, 0)
	279 getfield (0, 0)
	282 aload_1 (0, 0)
	283 invokevirtual (0, 0)
	286 invokeinterface (0, 0)
	291 checkcast (0, 0)
	294 aload_0 (0, 0)
	295 getfield (0, 0)
	298 aload_1 (0, 0)
	299 invokevirtual (0, 0)
	302 invokeinterface (0, 0)
	307 invokeinterface (0, 0)
	312 invokeinterface (0, 0)
	317 checkcast (0, 0)
	320 iconst_0 (0, 0)
	321 invokespecial (0, 0)
	324 areturn (0, 0)

Method: composeInverse
	0 aload_2 (0, 0)
	1 getstatic (0, 0)
	4 if_acmpne (0, 0)
	7 aload_0 (0, 0)
	8 aload_1 (0, 0)
	9 invokespecial (0, 0)
	12 goto (0, 0)
	15 aload_1 (0, 0)
	16 aload_0 (0, 0)
	17 invokevirtual (0, 0)
	20 invokestatic (0, 0)
	23 areturn (0, 0)

Method: composeInverseInternal
	0 new (0, 0)
	3 dup (0, 0)
	4 aload_0 (0, 0)
	5 getfield (0, 0)
	8 aload_1 (0, 0)
	9 invokevirtual (0, 0)
	12 invokeinterface (0, 0)
	17 checkcast (0, 0)
	20 aload_0 (0, 0)
	21 getfield (0, 0)
	24 aload_1 (0, 0)
	25 invokevirtual (0, 0)
	28 invokeinterface (0, 0)
	33 checkcast (0, 0)
	36 aload_0 (0, 0)
	37 getfield (0, 0)
	40 aload_1 (0, 0)
	41 invokevirtual (0, 0)
	44 invokeinterface (0, 0)
	49 invokeinterface (0, 0)
	54 checkcast (0, 0)
	57 aload_0 (0, 0)
	58 getfield (0, 0)
	61 aload_1 (0, 0)
	62 invokevirtual (0, 0)
	65 invokeinterface (0, 0)
	70 invokeinterface (0, 0)
	75 invokeinterface (0, 0)
	80 checkcast (0, 0)
	83 invokeinterface (0, 0)
	88 checkcast (0, 0)
	91 aload_0 (0, 0)
	92 getfield (0, 0)
	95 aload_1 (0, 0)
	96 invokevirtual (0, 0)
	99 invokeinterface (0, 0)
	104 checkcast (0, 0)
	107 aload_0 (0, 0)
	108 getfield (0, 0)
	111 aload_1 (0, 0)
	112 invokevirtual (0, 0)
	115 invokeinterface (0, 0)
	120 checkcast (0, 0)
	123 aload_0 (0, 0)
	124 getfield (0, 0)
	127 aload_1 (0, 0)
	128 invokevirtual (0, 0)
	131 invokeinterface (0, 0)
	136 invokeinterface (0, 0)
	141 invokeinterface (0, 0)
	146 checkcast (0, 0)
	149 aload_0 (0, 0)
	150 getfield (0, 0)
	153 aload_1 (0, 0)
	154 invokevirtual (0, 0)
	157 invokeinterface (0, 0)
	162 invokeinterface (0, 0)
	167 checkcast (0, 0)
	170 aload_0 (0, 0)
	171 getfield (0, 0)
	174 aload_1 (0, 0)
	175 invokevirtual (0, 0)
	178 invokeinterface (0, 0)
	183 checkcast (0, 0)
	186 aload_0 (0, 0)
	187 getfield (0, 0)
	190 aload_1 (0, 0)
	191 invokevirtual (0, 0)
	194 invokeinterface (0, 0)
	199 checkcast (0, 0)
	202 aload_0 (0, 0)
	203 getfield (0, 0)
	206 aload_1 (0, 0)
	207 invokevirtual (0, 0)
	210 invokeinterface (0, 0)
	215 invokeinterface (0, 0)
	220 invokeinterface (0, 0)
	225 checkcast (0, 0)
	228 aload_0 (0, 0)
	229 getfield (0, 0)
	232 aload_1 (0, 0)
	233 invokevirtual (0, 0)
	236 invokeinterface (0, 0)
	241 invokeinterface (0, 0)
	246 checkcast (0, 0)
	249 aload_0 (0, 0)
	250 getfield (0, 0)
	253 aload_1 (0, 0)
	254 invokevirtual (0, 0)
	257 invokeinterface (0, 0)
	262 checkcast (0, 0)
	265 aload_0 (0, 0)
	266 getfield (0, 0)
	269 aload_1 (0, 0)
	270 invokevirtual (0, 0)
	273 invokeinterface (0, 0)
	278 checkcast (0, 0)
	281 aload_0 (0, 0)
	282 getfield (0, 0)
	285 aload_1 (0, 0)
	286 invokevirtual (0, 0)
	289 invokeinterface (0, 0)
	294 invokeinterface (0, 0)
	299 invokeinterface (0, 0)
	304 checkcast (0, 0)
	307 aload_0 (0, 0)
	308 getfield (0, 0)
	311 aload_1 (0, 0)
	312 invokevirtual (0, 0)
	315 invokeinterface (0, 0)
	320 invokeinterface (0, 0)
	325 checkcast (0, 0)
	328 iconst_0 (0, 0)
	329 invokespecial (0, 0)
	332 areturn (0, 0)

Method: orthogonalizeMatrix
	0 aload_1 (0, 0)
	1 iconst_0 (0, 0)
	2 aaload (0, 0)
	3 iconst_0 (0, 0)
	4 aaload (0, 0)
	5 astore (0, 0)
	7 aload_1 (0, 0)
	8 iconst_0 (0, 0)
	9 aaload (0, 0)
	10 iconst_1 (0, 0)
	11 aaload (0, 0)
	12 astore (0, 0)
	14 aload_1 (0, 0)
	15 iconst_0 (0, 0)
	16 aaload (0, 0)
	17 iconst_2 (0, 0)
	18 aaload (0, 0)
	19 astore (0, 0)
	21 aload_1 (0, 0)
	22 iconst_1 (0, 0)
	23 aaload (0, 0)
	24 iconst_0 (0, 0)
	25 aaload (0, 0)
	26 astore (0, 0)
	28 aload_1 (0, 0)
	29 iconst_1 (0, 0)
	30 aaload (0, 0)
	31 iconst_1 (0, 0)
	32 aaload (0, 0)
	33 astore (0, 0)
	35 aload_1 (0, 0)
	36 iconst_1 (0, 0)
	37 aaload (0, 0)
	38 iconst_2 (0, 0)
	39 aaload (0, 0)
	40 astore (0, 0)
	42 aload_1 (0, 0)
	43 iconst_2 (0, 0)
	44 aaload (0, 0)
	45 iconst_0 (0, 0)
	46 aaload (0, 0)
	47 astore (0, 0)
	49 aload_1 (0, 0)
	50 iconst_2 (0, 0)
	51 aaload (0, 0)
	52 iconst_1 (0, 0)
	53 aaload (0, 0)
	54 astore (0, 0)
	56 aload_1 (0, 0)
	57 iconst_2 (0, 0)
	58 aaload (0, 0)
	59 iconst_2 (0, 0)
	60 aaload (0, 0)
	61 astore (0, 0)
	63 dconst_0 (0, 0)
	64 dstore (0, 0)
	66 aload_1 (0, 0)
	67 iconst_0 (0, 0)
	68 aaload (0, 0)
	69 iconst_0 (0, 0)
	70 aaload (0, 0)
	71 invokeinterface (0, 0)
	76 iconst_3 (0, 0)
	77 iconst_3 (0, 0)
	78 invokestatic (0, 0)
	81 checkcast (0, 0)
	84 astore (0, 0)
	86 iconst_0 (0, 0)
	87 istore (0, 0)
	89 iinc (1, 3)
	92 iload (1, 3)
	94 bipush (1, 3)
	96 if_icmpge (1, 3)
	99 aload_1 (1, 3)
	100 iconst_0 (1, 3)
	101 aaload (1, 3)
	102 iconst_0 (1, 3)
	103 aaload (1, 3)
	104 aload (1, 3)
	106 invokeinterface (1, 3)
	111 checkcast (1, 3)
	114 aload_1 (1, 3)
	115 iconst_1 (1, 3)
	116 aaload (1, 3)
	117 iconst_0 (1, 3)
	118 aaload (1, 3)
	119 aload (1, 3)
	121 invokeinterface (1, 3)
	126 invokeinterface (1, 3)
	131 checkcast (1, 3)
	134 aload_1 (1, 3)
	135 iconst_2 (1, 3)
	136 aaload (1, 3)
	137 iconst_0 (1, 3)
	138 aaload (1, 3)
	139 aload (1, 3)
	141 invokeinterface (1, 3)
	146 invokeinterface (1, 3)
	151 checkcast (1, 3)
	154 astore (1, 3)
	156 aload_1 (1, 3)
	157 iconst_0 (1, 3)
	158 aaload (1, 3)
	159 iconst_1 (1, 3)
	160 aaload (1, 3)
	161 aload (1, 3)
	163 invokeinterface (1, 3)
	168 checkcast (1, 3)
	171 aload_1 (1, 3)
	172 iconst_1 (1, 3)
	173 aaload (1, 3)
	174 iconst_1 (1, 3)
	175 aaload (1, 3)
	176 aload (1, 3)
	178 invokeinterface (1, 3)
	183 invokeinterface (1, 3)
	188 checkcast (1, 3)
	191 aload_1 (1, 3)
	192 iconst_2 (1, 3)
	193 aaload (1, 3)
	194 iconst_1 (1, 3)
	195 aaload (1, 3)
	196 aload (1, 3)
	198 invokeinterface (1, 3)
	203 invokeinterface (1, 3)
	208 checkcast (1, 3)
	211 astore (1, 3)
	213 aload_1 (1, 3)
	214 iconst_0 (1, 3)
	215 aaload (1, 3)
	216 iconst_2 (1, 3)
	217 aaload (1, 3)
	218 aload (1, 3)
	220 invokeinterface (1, 3)
	225 checkcast (1, 3)
	228 aload_1 (1, 3)
	229 iconst_1 (1, 3)
	230 aaload (1, 3)
	231 iconst_2 (1, 3)
	232 aaload (1, 3)
	233 aload (1, 3)
	235 invokeinterface (1, 3)
	240 invokeinterface (1, 3)
	245 checkcast (1, 3)
	248 aload_1 (1, 3)
	249 iconst_2 (1, 3)
	250 aaload (1, 3)
	251 iconst_2 (1, 3)
	252 aaload (1, 3)
	253 aload (1, 3)
	255 invokeinterface (1, 3)
	260 invokeinterface (1, 3)
	265 checkcast (1, 3)
	268 astore (1, 3)
	270 aload_1 (1, 3)
	271 iconst_0 (1, 3)
	272 aaload (1, 3)
	273 iconst_0 (1, 3)
	274 aaload (1, 3)
	275 aload (1, 3)
	277 invokeinterface (1, 3)
	282 checkcast (1, 3)
	285 aload_1 (1, 3)
	286 iconst_1 (1, 3)
	287 aaload (1, 3)
	288 iconst_0 (1, 3)
	289 aaload (1, 3)
	290 aload (1, 3)
	292 invokeinterface (1, 3)
	297 invokeinterface (1, 3)
	302 checkcast (1, 3)
	305 aload_1 (1, 3)
	306 iconst_2 (1, 3)
	307 aaload (1, 3)
	308 iconst_0 (1, 3)
	309 aaload (1, 3)
	310 aload (1, 3)
	312 invokeinterface (1, 3)
	317 invokeinterface (1, 3)
	322 checkcast (1, 3)
	325 astore (1, 3)
	327 aload_1 (1, 3)
	328 iconst_0 (1, 3)
	329 aaload (1, 3)
	330 iconst_1 (1, 3)
	331 aaload (1, 3)
	332 aload (1, 3)
	334 invokeinterface (1, 3)
	339 checkcast (1, 3)
	342 aload_1 (1, 3)
	343 iconst_1 (1, 3)
	344 aaload (1, 3)
	345 iconst_1 (1, 3)
	346 aaload (1, 3)
	347 aload (1, 3)
	349 invokeinterface (1, 3)
	354 invokeinterface (1, 3)
	359 checkcast (1, 3)
	362 aload_1 (1, 3)
	363 iconst_2 (1, 3)
	364 aaload (1, 3)
	365 iconst_1 (1, 3)
	366 aaload (1, 3)
	367 aload (1, 3)
	369 invokeinterface (1, 3)
	374 invokeinterface (1, 3)
	379 checkcast (1, 3)
	382 astore (1, 3)
	384 aload_1 (1, 3)
	385 iconst_0 (1, 3)
	386 aaload (1, 3)
	387 iconst_2 (1, 3)
	388 aaload (1, 3)
	389 aload (1, 3)
	391 invokeinterface (1, 3)
	396 checkcast (1, 3)
	399 aload_1 (1, 3)
	400 iconst_1 (1, 3)
	401 aaload (1, 3)
	402 iconst_2 (1, 3)
	403 aaload (1, 3)
	404 aload (1, 3)
	406 invokeinterface (1, 3)
	411 invokeinterface (1, 3)
	416 checkcast (1, 3)
	419 aload_1 (1, 3)
	420 iconst_2 (1, 3)
	421 aaload (1, 3)
	422 iconst_2 (1, 3)
	423 aaload (1, 3)
	424 aload (1, 3)
	426 invokeinterface (1, 3)
	431 invokeinterface (1, 3)
	436 checkcast (1, 3)
	439 astore (1, 3)
	441 aload_1 (1, 3)
	442 iconst_0 (1, 3)
	443 aaload (1, 3)
	444 iconst_0 (1, 3)
	445 aaload (1, 3)
	446 aload (1, 3)
	448 invokeinterface (1, 3)
	453 checkcast (1, 3)
	456 aload_1 (1, 3)
	457 iconst_1 (1, 3)
	458 aaload (1, 3)
	459 iconst_0 (1, 3)
	460 aaload (1, 3)
	461 aload (1, 3)
	463 invokeinterface (1, 3)
	468 invokeinterface (1, 3)
	473 checkcast (1, 3)
	476 aload_1 (1, 3)
	477 iconst_2 (1, 3)
	478 aaload (1, 3)
	479 iconst_0 (1, 3)
	480 aaload (1, 3)
	481 aload (1, 3)
	483 invokeinterface (1, 3)
	488 invokeinterface (1, 3)
	493 checkcast (1, 3)
	496 astore (1, 3)
	498 aload_1 (1, 3)
	499 iconst_0 (1, 3)
	500 aaload (1, 3)
	501 iconst_1 (1, 3)
	502 aaload (1, 3)
	503 aload (1, 3)
	505 invokeinterface (1, 3)
	510 checkcast (1, 3)
	513 aload_1 (1, 3)
	514 iconst_1 (1, 3)
	515 aaload (1, 3)
	516 iconst_1 (1, 3)
	517 aaload (1, 3)
	518 aload (1, 3)
	520 invokeinterface (1, 3)
	525 invokeinterface (1, 3)
	530 checkcast (1, 3)
	533 aload_1 (1, 3)
	534 iconst_2 (1, 3)
	535 aaload (1, 3)
	536 iconst_1 (1, 3)
	537 aaload (1, 3)
	538 aload (1, 3)
	540 invokeinterface (1, 3)
	545 invokeinterface (1, 3)
	550 checkcast (1, 3)
	553 astore (1, 3)
	555 aload_1 (1, 3)
	556 iconst_0 (1, 3)
	557 aaload (1, 3)
	558 iconst_2 (1, 3)
	559 aaload (1, 3)
	560 aload (1, 3)
	562 invokeinterface (1, 3)
	567 checkcast (1, 3)
	570 aload_1 (1, 3)
	571 iconst_1 (1, 3)
	572 aaload (1, 3)
	573 iconst_2 (1, 3)
	574 aaload (1, 3)
	575 aload (1, 3)
	577 invokeinterface (1, 3)
	582 invokeinterface (1, 3)
	587 checkcast (1, 3)
	590 aload_1 (1, 3)
	591 iconst_2 (1, 3)
	592 aaload (1, 3)
	593 iconst_2 (1, 3)
	594 aaload (1, 3)
	595 aload (1, 3)
	597 invokeinterface (1, 3)
	602 invokeinterface (1, 3)
	607 checkcast (1, 3)
	610 astore (1, 3)
	612 aload (1, 3)
	614 iconst_0 (1, 3)
	615 aaload (1, 3)
	616 iconst_0 (1, 3)
	617 aload (1, 3)
	619 aload (1, 3)
	621 aload (1, 3)
	623 invokeinterface (1, 3)
	628 checkcast (1, 3)
	631 aload (1, 3)
	633 aload (1, 3)
	635 invokeinterface (1, 3)
	640 invokeinterface (1, 3)
	645 checkcast (1, 3)
	648 aload (1, 3)
	650 aload (1, 3)
	652 invokeinterface (1, 3)
	657 invokeinterface (1, 3)
	662 checkcast (1, 3)
	665 aload_1 (1, 3)
	666 iconst_0 (1, 3)
	667 aaload (1, 3)
	668 iconst_0 (1, 3)
	669 aaload (1, 3)
	670 invokeinterface (1, 3)
	675 checkcast (1, 3)
	678 ldc2_w (1, 3)
	681 invokeinterface (1, 3)
	686 invokeinterface (1, 3)
	691 checkcast (1, 3)
	694 aastore (1, 3)
	695 aload (1, 3)
	697 iconst_0 (1, 3)
	698 aaload (1, 3)
	699 iconst_1 (1, 3)
	700 aload (1, 3)
	702 aload (1, 3)
	704 aload (1, 3)
	706 invokeinterface (1, 3)
	711 checkcast (1, 3)
	714 aload (1, 3)
	716 aload (1, 3)
	718 invokeinterface (1, 3)
	723 invokeinterface (1, 3)
	728 checkcast (1, 3)
	731 aload (1, 3)
	733 aload (1, 3)
	735 invokeinterface (1, 3)
	740 invokeinterface (1, 3)
	745 checkcast (1, 3)
	748 aload_1 (1, 3)
	749 iconst_0 (1, 3)
	750 aaload (1, 3)
	751 iconst_1 (1, 3)
	752 aaload (1, 3)
	753 invokeinterface (1, 3)
	758 checkcast (1, 3)
	761 ldc2_w (1, 3)
	764 invokeinterface (1, 3)
	769 invokeinterface (1, 3)
	774 checkcast (1, 3)
	777 aastore (1, 3)
	778 aload (1, 3)
	780 iconst_0 (1, 3)
	781 aaload (1, 3)
	782 iconst_2 (1, 3)
	783 aload (1, 3)
	785 aload (1, 3)
	787 aload (1, 3)
	789 invokeinterface (1, 3)
	794 checkcast (1, 3)
	797 aload (1, 3)
	799 aload (1, 3)
	801 invokeinterface (1, 3)
	806 invokeinterface (1, 3)
	811 checkcast (1, 3)
	814 aload (1, 3)
	816 aload (1, 3)
	818 invokeinterface (1, 3)
	823 invokeinterface (1, 3)
	828 checkcast (1, 3)
	831 aload_1 (1, 3)
	832 iconst_0 (1, 3)
	833 aaload (1, 3)
	834 iconst_2 (1, 3)
	835 aaload (1, 3)
	836 invokeinterface (1, 3)
	841 checkcast (1, 3)
	844 ldc2_w (1, 3)
	847 invokeinterface (1, 3)
	852 invokeinterface (1, 3)
	857 checkcast (1, 3)
	860 aastore (1, 3)
	861 aload (1, 3)
	863 iconst_1 (1, 3)
	864 aaload (1, 3)
	865 iconst_0 (1, 3)
	866 aload (1, 3)
	868 aload (1, 3)
	870 aload (1, 3)
	872 invokeinterface (1, 3)
	877 checkcast (1, 3)
	880 aload (1, 3)
	882 aload (1, 3)
	884 invokeinterface (1, 3)
	889 invokeinterface (1, 3)
	894 checkcast (1, 3)
	897 aload (1, 3)
	899 aload (1, 3)
	901 invokeinterface (1, 3)
	906 invokeinterface (1, 3)
	911 checkcast (1, 3)
	914 aload_1 (1, 3)
	915 iconst_1 (1, 3)
	916 aaload (1, 3)
	917 iconst_0 (1, 3)
	918 aaload (1, 3)
	919 invokeinterface (1, 3)
	924 checkcast (1, 3)
	927 ldc2_w (1, 3)
	930 invokeinterface (1, 3)
	935 invokeinterface (1, 3)
	940 checkcast (1, 3)
	943 aastore (1, 3)
	944 aload (1, 3)
	946 iconst_1 (1, 3)
	947 aaload (1, 3)
	948 iconst_1 (1, 3)
	949 aload (1, 3)
	951 aload (1, 3)
	953 aload (1, 3)
	955 invokeinterface (1, 3)
	960 checkcast (1, 3)
	963 aload (1, 3)
	965 aload (1, 3)
	967 invokeinterface (1, 3)
	972 invokeinterface (1, 3)
	977 checkcast (1, 3)
	980 aload (1, 3)
	982 aload (1, 3)
	984 invokeinterface (1, 3)
	989 invokeinterface (1, 3)
	994 checkcast (1, 3)
	997 aload_1 (1, 3)
	998 iconst_1 (1, 3)
	999 aaload (1, 3)
	1000 iconst_1 (1, 3)
	1001 aaload (1, 3)
	1002 invokeinterface (1, 3)
	1007 checkcast (1, 3)
	1010 ldc2_w (1, 3)
	1013 invokeinterface (1, 3)
	1018 invokeinterface (1, 3)
	1023 checkcast (1, 3)
	1026 aastore (1, 3)
	1027 aload (1, 3)
	1029 iconst_1 (1, 3)
	1030 aaload (1, 3)
	1031 iconst_2 (1, 3)
	1032 aload (1, 3)
	1034 aload (1, 3)
	1036 aload (1, 3)
	1038 invokeinterface (1, 3)
	1043 checkcast (1, 3)
	1046 aload (1, 3)
	1048 aload (1, 3)
	1050 invokeinterface (1, 3)
	1055 invokeinterface (1, 3)
	1060 checkcast (1, 3)
	1063 aload (1, 3)
	1065 aload (1, 3)
	1067 invokeinterface (1, 3)
	1072 invokeinterface (1, 3)
	1077 checkcast (1, 3)
	1080 aload_1 (1, 3)
	1081 iconst_1 (1, 3)
	1082 aaload (1, 3)
	1083 iconst_2 (1, 3)
	1084 aaload (1, 3)
	1085 invokeinterface (1, 3)
	1090 checkcast (1, 3)
	1093 ldc2_w (1, 3)
	1096 invokeinterface (1, 3)
	1101 invokeinterface (1, 3)
	1106 checkcast (1, 3)
	1109 aastore (1, 3)
	1110 aload (1, 3)
	1112 iconst_2 (1, 3)
	1113 aaload (1, 3)
	1114 iconst_0 (1, 3)
	1115 aload (1, 3)
	1117 aload (1, 3)
	1119 aload (1, 3)
	1121 invokeinterface (1, 3)
	1126 checkcast (1, 3)
	1129 aload (1, 3)
	1131 aload (1, 3)
	1133 invokeinterface (1, 3)
	1138 invokeinterface (1, 3)
	1143 checkcast (1, 3)
	1146 aload (1, 3)
	1148 aload (1, 3)
	1150 invokeinterface (1, 3)
	1155 invokeinterface (1, 3)
	1160 checkcast (1, 3)
	1163 aload_1 (1, 3)
	1164 iconst_2 (1, 3)
	1165 aaload (1, 3)
	1166 iconst_0 (1, 3)
	1167 aaload (1, 3)
	1168 invokeinterface (1, 3)
	1173 checkcast (1, 3)
	1176 ldc2_w (1, 3)
	1179 invokeinterface (1, 3)
	1184 invokeinterface (1, 3)
	1189 checkcast (1, 3)
	1192 aastore (1, 3)
	1193 aload (1, 3)
	1195 iconst_2 (1, 3)
	1196 aaload (1, 3)
	1197 iconst_1 (1, 3)
	1198 aload (1, 3)
	1200 aload (1, 3)
	1202 aload (1, 3)
	1204 invokeinterface (1, 3)
	1209 checkcast (1, 3)
	1212 aload (1, 3)
	1214 aload (1, 3)
	1216 invokeinterface (1, 3)
	1221 invokeinterface (1, 3)
	1226 checkcast (1, 3)
	1229 aload (1, 3)
	1231 aload (1, 3)
	1233 invokeinterface (1, 3)
	1238 invokeinterface (1, 3)
	1243 checkcast (1, 3)
	1246 aload_1 (1, 3)
	1247 iconst_2 (1, 3)
	1248 aaload (1, 3)
	1249 iconst_1 (1, 3)
	1250 aaload (1, 3)
	1251 invokeinterface (1, 3)
	1256 checkcast (1, 3)
	1259 ldc2_w (1, 3)
	1262 invokeinterface (1, 3)
	1267 invokeinterface (1, 3)
	1272 checkcast (1, 3)
	1275 aastore (1, 3)
	1276 aload (1, 3)
	1278 iconst_2 (1, 3)
	1279 aaload (1, 3)
	1280 iconst_2 (1, 3)
	1281 aload (1, 3)
	1283 aload (1, 3)
	1285 aload (1, 3)
	1287 invokeinterface (1, 3)
	1292 checkcast (1, 3)
	1295 aload (1, 3)
	1297 aload (1, 3)
	1299 invokeinterface (1, 3)
	1304 invokeinterface (1, 3)
	1309 checkcast (1, 3)
	1312 aload (1, 3)
	1314 aload (1, 3)
	1316 invokeinterface (1, 3)
	1321 invokeinterface (1, 3)
	1326 checkcast (1, 3)
	1329 aload_1 (1, 3)
	1330 iconst_2 (1, 3)
	1331 aaload (1, 3)
	1332 iconst_2 (1, 3)
	1333 aaload (1, 3)
	1334 invokeinterface (1, 3)
	1339 checkcast (1, 3)
	1342 ldc2_w (1, 3)
	1345 invokeinterface (1, 3)
	1350 invokeinterface (1, 3)
	1355 checkcast (1, 3)
	1358 aastore (1, 3)
	1359 aload (1, 3)
	1361 iconst_0 (1, 3)
	1362 aaload (1, 3)
	1363 iconst_0 (1, 3)
	1364 aaload (1, 3)
	1365 invokeinterface (1, 3)
	1370 aload_1 (1, 3)
	1371 iconst_0 (1, 3)
	1372 aaload (1, 3)
	1373 iconst_0 (1, 3)
	1374 aaload (1, 3)
	1375 invokeinterface (1, 3)
	1380 dsub (1, 3)
	1381 dstore (1, 3)
	1383 aload (1, 3)
	1385 iconst_0 (1, 3)
	1386 aaload (1, 3)
	1387 iconst_1 (1, 3)
	1388 aaload (1, 3)
	1389 invokeinterface (1, 3)
	1394 aload_1 (1, 3)
	1395 iconst_0 (1, 3)
	1396 aaload (1, 3)
	1397 iconst_1 (1, 3)
	1398 aaload (1, 3)
	1399 invokeinterface (1, 3)
	1404 dsub (1, 3)
	1405 dstore (1, 3)
	1407 aload (1, 3)
	1409 iconst_0 (1, 3)
	1410 aaload (1, 3)
	1411 iconst_2 (1, 3)
	1412 aaload (1, 3)
	1413 invokeinterface (1, 3)
	1418 aload_1 (1, 3)
	1419 iconst_0 (1, 3)
	1420 aaload (1, 3)
	1421 iconst_2 (1, 3)
	1422 aaload (1, 3)
	1423 invokeinterface (1, 3)
	1428 dsub (1, 3)
	1429 dstore (1, 3)
	1431 aload (1, 3)
	1433 iconst_1 (1, 3)
	1434 aaload (1, 3)
	1435 iconst_0 (1, 3)
	1436 aaload (1, 3)
	1437 invokeinterface (1, 3)
	1442 aload_1 (1, 3)
	1443 iconst_1 (1, 3)
	1444 aaload (1, 3)
	1445 iconst_0 (1, 3)
	1446 aaload (1, 3)
	1447 invokeinterface (1, 3)
	1452 dsub (1, 3)
	1453 dstore (1, 3)
	1455 aload (1, 3)
	1457 iconst_1 (1, 3)
	1458 aaload (1, 3)
	1459 iconst_1 (1, 3)
	1460 aaload (1, 3)
	1461 invokeinterface (1, 3)
	1466 aload_1 (1, 3)
	1467 iconst_1 (1, 3)
	1468 aaload (1, 3)
	1469 iconst_1 (1, 3)
	1470 aaload (1, 3)
	1471 invokeinterface (1, 3)
	1476 dsub (1, 3)
	1477 dstore (1, 3)
	1479 aload (1, 3)
	1481 iconst_1 (1, 3)
	1482 aaload (1, 3)
	1483 iconst_2 (1, 3)
	1484 aaload (1, 3)
	1485 invokeinterface (1, 3)
	1490 aload_1 (1, 3)
	1491 iconst_1 (1, 3)
	1492 aaload (1, 3)
	1493 iconst_2 (1, 3)
	1494 aaload (1, 3)
	1495 invokeinterface (1, 3)
	1500 dsub (1, 3)
	1501 dstore (1, 3)
	1503 aload (1, 3)
	1505 iconst_2 (1, 3)
	1506 aaload (1, 3)
	1507 iconst_0 (1, 3)
	1508 aaload (1, 3)
	1509 invokeinterface (1, 3)
	1514 aload_1 (1, 3)
	1515 iconst_2 (1, 3)
	1516 aaload (1, 3)
	1517 iconst_0 (1, 3)
	1518 aaload (1, 3)
	1519 invokeinterface (1, 3)
	1524 dsub (1, 3)
	1525 dstore (1, 3)
	1527 aload (1, 3)
	1529 iconst_2 (1, 3)
	1530 aaload (1, 3)
	1531 iconst_1 (1, 3)
	1532 aaload (1, 3)
	1533 invokeinterface (1, 3)
	1538 aload_1 (1, 3)
	1539 iconst_2 (1, 3)
	1540 aaload (1, 3)
	1541 iconst_1 (1, 3)
	1542 aaload (1, 3)
	1543 invokeinterface (1, 3)
	1548 dsub (1, 3)
	1549 dstore (1, 3)
	1551 aload (1, 3)
	1553 iconst_2 (1, 3)
	1554 aaload (1, 3)
	1555 iconst_2 (1, 3)
	1556 aaload (1, 3)
	1557 invokeinterface (1, 3)
	1562 aload_1 (1, 3)
	1563 iconst_2 (1, 3)
	1564 aaload (1, 3)
	1565 iconst_2 (1, 3)
	1566 aaload (1, 3)
	1567 invokeinterface (1, 3)
	1572 dsub (1, 3)
	1573 dstore (1, 3)
	1575 dload (1, 3)
	1577 dload (1, 3)
	1579 dmul (1, 3)
	1580 dload (1, 3)
	1582 dload (1, 3)
	1584 dmul (1, 3)
	1585 dadd (1, 3)
	1586 dload (1, 3)
	1588 dload (1, 3)
	1590 dmul (1, 3)
	1591 dadd (1, 3)
	1592 dload (1, 3)
	1594 dload (1, 3)
	1596 dmul (1, 3)
	1597 dadd (1, 3)
	1598 dload (1, 3)
	1600 dload (1, 3)
	1602 dmul (1, 3)
	1603 dadd (1, 3)
	1604 dload (1, 3)
	1606 dload (1, 3)
	1608 dmul (1, 3)
	1609 dadd (1, 3)
	1610 dload (1, 3)
	1612 dload (1, 3)
	1614 dmul (1, 3)
	1615 dadd (1, 3)
	1616 dload (1, 3)
	1618 dload (1, 3)
	1620 dmul (1, 3)
	1621 dadd (1, 3)
	1622 dload (1, 3)
	1624 dload (1, 3)
	1626 dmul (1, 3)
	1627 dadd (1, 3)
	1628 dstore (1, 3)
	1630 dload (2, 1)
	1632 dload (2, 1)
	1634 dsub (2, 1)
	1635 invokestatic (2, 1)
	1638 dload_2 (2, 1)
	1639 dcmpg (2, 1)
	1640 ifgt (2, 1)
	1643 aload (2, 1)
	1645 areturn (2, 1)
	1646 aload (1, 3)
	1648 iconst_0 (1, 3)
	1649 aaload (1, 3)
	1650 iconst_0 (1, 3)
	1651 aaload (1, 3)
	1652 astore (1, 3)
	1654 aload (1, 3)
	1656 iconst_0 (1, 3)
	1657 aaload (1, 3)
	1658 iconst_1 (1, 3)
	1659 aaload (1, 3)
	1660 astore (1, 3)
	1662 aload (1, 3)
	1664 iconst_0 (1, 3)
	1665 aaload (1, 3)
	1666 iconst_2 (1, 3)
	1667 aaload (1, 3)
	1668 astore (1, 3)
	1670 aload (1, 3)
	1672 iconst_1 (1, 3)
	1673 aaload (1, 3)
	1674 iconst_0 (1, 3)
	1675 aaload (1, 3)
	1676 astore (1, 3)
	1678 aload (1, 3)
	1680 iconst_1 (1, 3)
	1681 aaload (1, 3)
	1682 iconst_1 (1, 3)
	1683 aaload (1, 3)
	1684 astore (1, 3)
	1686 aload (1, 3)
	1688 iconst_1 (1, 3)
	1689 aaload (1, 3)
	1690 iconst_2 (1, 3)
	1691 aaload (1, 3)
	1692 astore (1, 3)
	1694 aload (1, 3)
	1696 iconst_2 (1, 3)
	1697 aaload (1, 3)
	1698 iconst_0 (1, 3)
	1699 aaload (1, 3)
	1700 astore (1, 3)
	1702 aload (1, 3)
	1704 iconst_2 (1, 3)
	1705 aaload (1, 3)
	1706 iconst_1 (1, 3)
	1707 aaload (1, 3)
	1708 astore (1, 3)
	1710 aload (1, 3)
	1712 iconst_2 (1, 3)
	1713 aaload (1, 3)
	1714 iconst_2 (1, 3)
	1715 aaload (1, 3)
	1716 astore (1, 3)
	1718 dload (1, 3)
	1720 dstore (1, 3)
	1722 goto (0, 0)
	1725 new (0, 0)
	1728 dup (0, 0)
	1729 getstatic (0, 0)
	1732 iconst_1 (0, 0)
	1733 anewarray (0, 0)
	1736 dup (0, 0)
	1737 iconst_0 (0, 0)
	1738 iload (0, 0)
	1740 iconst_1 (0, 0)
	1741 isub (0, 0)
	1742 invokestatic (0, 0)
	1745 aastore (0, 0)
	1746 invokespecial (0, 0)
	1749 athrow (0, 0)

Method: distance
	0 aload_0 (0, 0)
	1 aload_1 (0, 0)
	2 invokespecial (0, 0)
	5 invokevirtual (0, 0)
	8 areturn (0, 0)

