Method: <init>
	0 aload_0 (0, 0)
	1 invokespecial (0, 0)
	2 java/lang/Object.<init>:()V (0, 0)
	4 aload_3 (0, 0)
	5 invokevirtual (0, 0)
	6 org/apache/commons/math3/geometry/euclidean/threed/FieldVector3D.getX:()Lorg/apache/commons/math3/RealFieldElement; (0, 0)
	8 astore (0, 0)
	9 #13 (0, 0)
	10 aload_0 (0, 0)
	11 aload (0, 0)
	12 #13 (0, 0)
	13 dload_1 (0, 0)
	14 aload_3 (0, 0)
	15 invokevirtual (0, 0)
	16 org/apache/commons/math3/geometry/euclidean/threed/FieldVector3D.getX:()Lorg/apache/commons/math3/RealFieldElement; (0, 0)
	18 dload (0, 0)
	19 #4 (0, 0)
	20 aload (0, 0)
	21 #6 (0, 0)
	22 invokevirtual (0, 0)
	23 org/apache/commons/math3/geometry/euclidean/threed/FieldVector3D.getX:()Lorg/apache/commons/math3/RealFieldElement; (0, 0)
	25 dload (0, 0)
	26 #7 (0, 0)
	27 aload (0, 0)
	28 #9 (0, 0)
	29 invokevirtual (0, 0)
	30 org/apache/commons/math3/geometry/euclidean/threed/FieldVector3D.getX:()Lorg/apache/commons/math3/RealFieldElement; (0, 0)
	32 dload (0, 0)
	33 #10 (0, 0)
	34 aload (0, 0)
	35 #12 (0, 0)
	36 invokevirtual (0, 0)
	37 org/apache/commons/math3/geometry/euclidean/threed/FieldVector3D.getX:()Lorg/apache/commons/math3/RealFieldElement; (0, 0)
	39 invokeinterface (0, 0)
	40 org/apache/commons/math3/RealFieldElement.getField:()Lorg/apache/commons/math3/Field; (0, 0)
	42 0 (0, 0)
	44 checkcast (0, 0)
	45 org/apache/commons/math3/RealFieldElement (0, 0)
	47 putfield (0, 0)
	48 org/apache/commons/math3/geometry/euclidean/threed/FieldVector3D.x:Lorg/apache/commons/math3/RealFieldElement; (0, 0)
	50 aload_0 (0, 0)
	51 aload (0, 0)
	52 #13 (0, 0)
	53 dload_1 (0, 0)
	54 aload_3 (0, 0)
	55 invokevirtual (0, 0)
	56 org/apache/commons/math3/geometry/euclidean/threed/FieldVector3D.getY:()Lorg/apache/commons/math3/RealFieldElement; (0, 0)
	58 dload (0, 0)
	59 #4 (0, 0)
	60 aload (0, 0)
	61 #6 (0, 0)
	62 invokevirtual (0, 0)
	63 org/apache/commons/math3/geometry/euclidean/threed/FieldVector3D.getY:()Lorg/apache/commons/math3/RealFieldElement; (0, 0)
	65 dload (0, 0)
	66 #7 (0, 0)
	67 aload (0, 0)
	68 #9 (0, 0)
	69 invokevirtual (0, 0)
	70 org/apache/commons/math3/geometry/euclidean/threed/FieldVector3D.getY:()Lorg/apache/commons/math3/RealFieldElement; (0, 0)
	72 dload (0, 0)
	73 #10 (0, 0)
	74 aload (0, 0)
	75 #12 (0, 0)
	76 invokevirtual (0, 0)
	77 org/apache/commons/math3/geometry/euclidean/threed/FieldVector3D.getY:()Lorg/apache/commons/math3/RealFieldElement; (0, 0)
	79 invokeinterface (0, 0)
	80 org/apache/commons/math3/RealFieldElement.getField:()Lorg/apache/commons/math3/Field; (0, 0)
	82 0 (0, 0)
	84 checkcast (0, 0)
	85 org/apache/commons/math3/RealFieldElement (0, 0)
	87 putfield (0, 0)
	88 org/apache/commons/math3/geometry/euclidean/threed/FieldVector3D.y:Lorg/apache/commons/math3/RealFieldElement; (0, 0)
	90 aload_0 (0, 0)
	91 aload (0, 0)
	92 #13 (0, 0)
	93 dload_1 (0, 0)
	94 aload_3 (0, 0)
	95 invokevirtual (0, 0)
	96 org/apache/commons/math3/geometry/euclidean/threed/FieldVector3D.getZ:()Lorg/apache/commons/math3/RealFieldElement; (0, 0)
	98 dload (0, 0)
	99 #4 (0, 0)
	100 aload (0, 0)
	101 #6 (0, 0)
	102 invokevirtual (0, 0)
	103 org/apache/commons/math3/geometry/euclidean/threed/FieldVector3D.getZ:()Lorg/apache/commons/math3/RealFieldElement; (0, 0)
	105 dload (0, 0)
	106 #7 (0, 0)
	107 aload (0, 0)
	108 #9 (0, 0)
	109 invokevirtual (0, 0)
	110 org/apache/commons/math3/geometry/euclidean/threed/FieldVector3D.getZ:()Lorg/apache/commons/math3/RealFieldElement; (0, 0)
	112 dload (0, 0)
	113 #10 (0, 0)
	114 aload (0, 0)
	115 #12 (0, 0)
	116 invokevirtual (0, 0)
	117 org/apache/commons/math3/geometry/euclidean/threed/FieldVector3D.getZ:()Lorg/apache/commons/math3/RealFieldElement; (0, 0)
	119 invokeinterface (0, 0)
	120 org/apache/commons/math3/RealFieldElement.getField:()Lorg/apache/commons/math3/Field; (0, 0)
	122 0 (0, 0)
	124 checkcast (0, 0)
	125 org/apache/commons/math3/RealFieldElement (0, 0)
	127 putfield (0, 0)
	128 org/apache/commons/math3/geometry/euclidean/threed/FieldVector3D.z:Lorg/apache/commons/math3/RealFieldElement; (0, 0)
	130 return (0, 0)

Method: getX
	0 aload_0 (0, 0)
	1 getfield (0, 0)
	2 org/apache/commons/math3/geometry/euclidean/threed/FieldVector3D.x:Lorg/apache/commons/math3/RealFieldElement; (0, 0)
	4 areturn (0, 0)

Method: getY
	0 aload_0 (0, 0)
	1 getfield (0, 0)
	2 org/apache/commons/math3/geometry/euclidean/threed/FieldVector3D.y:Lorg/apache/commons/math3/RealFieldElement; (0, 0)
	4 areturn (0, 0)

Method: getZ
	0 aload_0 (0, 0)
	1 getfield (0, 0)
	2 org/apache/commons/math3/geometry/euclidean/threed/FieldVector3D.z:Lorg/apache/commons/math3/RealFieldElement; (0, 0)
	4 areturn (0, 0)

Method: toArray
	0 aload_0 (0, 0)
	1 getfield (0, 0)
	2 org/apache/commons/math3/geometry/euclidean/threed/FieldVector3D.x:Lorg/apache/commons/math3/RealFieldElement; (0, 0)
	4 invokeinterface (0, 0)
	5 org/apache/commons/math3/RealFieldElement.org/apache/commons/math3/util/MathArrays (0, 0)
	7 0 (0, 0)
	9 iconst_3 (0, 0)
	10 invokestatic (0, 0)
	11 org/apache/commons/math3/util/MathArrays.buildArray:(Lorg/apache/commons/math3/Field;I)[Ljava/lang/Object; (0, 0)
	13 checkcast (0, 0)
	14 [Lorg/apache/commons/math3/RealFieldElement; (0, 0)
	16 astore_1 (0, 0)
	17 aload_1 (0, 0)
	18 iconst_0 (0, 0)
	19 aload_0 (0, 0)
	20 getfield (0, 0)
	21 org/apache/commons/math3/geometry/euclidean/threed/FieldVector3D.x:Lorg/apache/commons/math3/RealFieldElement; (0, 0)
	23 aastore (0, 0)
	24 aload_1 (0, 0)
	25 iconst_1 (0, 0)
	26 aload_0 (0, 0)
	27 getfield (0, 0)
	28 org/apache/commons/math3/geometry/euclidean/threed/FieldVector3D.y:Lorg/apache/commons/math3/RealFieldElement; (0, 0)
	30 aastore (0, 0)
	31 aload_1 (0, 0)
	32 iconst_2 (0, 0)
	33 aload_0 (0, 0)
	34 getfield (0, 0)
	35 org/apache/commons/math3/geometry/euclidean/threed/FieldVector3D.z:Lorg/apache/commons/math3/RealFieldElement; (0, 0)
	37 aastore (0, 0)
	38 aload_1 (0, 0)
	39 areturn (0, 0)

Method: toVector3D
	0 new (0, 0)
	1 org/apache/commons/math3/geometry/euclidean/threed/Vector3D (0, 0)
	3 dup (0, 0)
	4 aload_0 (0, 0)
	5 getfield (0, 0)
	6 org/apache/commons/math3/geometry/euclidean/threed/FieldVector3D.x:Lorg/apache/commons/math3/RealFieldElement; (0, 0)
	8 invokeinterface (0, 0)
	9 org/apache/commons/math3/RealFieldElement.<init>:(DDD)V (0, 0)
	11 0 (0, 0)
	13 aload_0 (0, 0)
	14 getfield (0, 0)
	15 org/apache/commons/math3/geometry/euclidean/threed/FieldVector3D.y:Lorg/apache/commons/math3/RealFieldElement; (0, 0)
	17 invokeinterface (0, 0)
	18 org/apache/commons/math3/RealFieldElement.<init>:(DDD)V (0, 0)
	20 0 (0, 0)
	22 aload_0 (0, 0)
	23 getfield (0, 0)
	24 org/apache/commons/math3/geometry/euclidean/threed/FieldVector3D.z:Lorg/apache/commons/math3/RealFieldElement; (0, 0)
	26 invokeinterface (0, 0)
	27 org/apache/commons/math3/RealFieldElement.<init>:(DDD)V (0, 0)
	29 0 (0, 0)
	31 invokespecial (0, 0)
	32 org/apache/commons/math3/geometry/euclidean/threed/Vector3D.<init>:(DDD)V (0, 0)
	34 areturn (0, 0)

Method: getNorm1
	0 aload_0 (0, 0)
	1 getfield (0, 0)
	2 org/apache/commons/math3/geometry/euclidean/threed/FieldVector3D.x:Lorg/apache/commons/math3/RealFieldElement; (0, 0)
	4 invokeinterface (0, 0)
	5 org/apache/commons/math3/RealFieldElement.add:(Ljava/lang/Object;)Ljava/lang/Object; (0, 0)
	7 0 (0, 0)
	9 checkcast (0, 0)
	10 org/apache/commons/math3/RealFieldElement (0, 0)
	12 aload_0 (0, 0)
	13 getfield (0, 0)
	14 org/apache/commons/math3/geometry/euclidean/threed/FieldVector3D.y:Lorg/apache/commons/math3/RealFieldElement; (0, 0)
	16 invokeinterface (0, 0)
	17 org/apache/commons/math3/RealFieldElement.add:(Ljava/lang/Object;)Ljava/lang/Object; (0, 0)
	19 0 (0, 0)
	21 invokeinterface (0, 0)
	22 org/apache/commons/math3/RealFieldElement.sqrt:()Ljava/lang/Object; (0, 0)
	24 0 (0, 0)
	26 checkcast (0, 0)
	27 org/apache/commons/math3/RealFieldElement (0, 0)
	29 aload_0 (0, 0)
	30 getfield (0, 0)
	31 org/apache/commons/math3/geometry/euclidean/threed/FieldVector3D.z:Lorg/apache/commons/math3/RealFieldElement; (0, 0)
	33 invokeinterface (0, 0)
	34 org/apache/commons/math3/RealFieldElement.add:(Ljava/lang/Object;)Ljava/lang/Object; (0, 0)
	36 0 (0, 0)
	38 invokeinterface (0, 0)
	39 org/apache/commons/math3/RealFieldElement.sqrt:()Ljava/lang/Object; (0, 0)
	41 0 (0, 0)
	43 checkcast (0, 0)
	44 org/apache/commons/math3/RealFieldElement (0, 0)
	46 areturn (0, 0)

Method: getNorm
	0 aload_0 (0, 0)
	1 getfield (0, 0)
	2 org/apache/commons/math3/geometry/euclidean/threed/FieldVector3D.x:Lorg/apache/commons/math3/RealFieldElement; (0, 0)
	4 aload_0 (0, 0)
	5 getfield (0, 0)
	6 org/apache/commons/math3/geometry/euclidean/threed/FieldVector3D.x:Lorg/apache/commons/math3/RealFieldElement; (0, 0)
	8 invokeinterface (0, 0)
	9 org/apache/commons/math3/RealFieldElement.sin:()Ljava/lang/Object; (0, 0)
	11 0 (0, 0)
	13 checkcast (0, 0)
	14 org/apache/commons/math3/RealFieldElement (0, 0)
	16 aload_0 (0, 0)
	17 getfield (0, 0)
	18 org/apache/commons/math3/geometry/euclidean/threed/FieldVector3D.y:Lorg/apache/commons/math3/RealFieldElement; (0, 0)
	20 aload_0 (0, 0)
	21 getfield (0, 0)
	22 org/apache/commons/math3/geometry/euclidean/threed/FieldVector3D.y:Lorg/apache/commons/math3/RealFieldElement; (0, 0)
	24 invokeinterface (0, 0)
	25 org/apache/commons/math3/RealFieldElement.sin:()Ljava/lang/Object; (0, 0)
	27 0 (0, 0)
	29 invokeinterface (0, 0)
	30 org/apache/commons/math3/RealFieldElement.sqrt:()Ljava/lang/Object; (0, 0)
	32 0 (0, 0)
	34 checkcast (0, 0)
	35 org/apache/commons/math3/RealFieldElement (0, 0)
	37 aload_0 (0, 0)
	38 getfield (0, 0)
	39 org/apache/commons/math3/geometry/euclidean/threed/FieldVector3D.z:Lorg/apache/commons/math3/RealFieldElement; (0, 0)
	41 aload_0 (0, 0)
	42 getfield (0, 0)
	43 org/apache/commons/math3/geometry/euclidean/threed/FieldVector3D.z:Lorg/apache/commons/math3/RealFieldElement; (0, 0)
	45 invokeinterface (0, 0)
	46 org/apache/commons/math3/RealFieldElement.sin:()Ljava/lang/Object; (0, 0)
	48 0 (0, 0)
	50 invokeinterface (0, 0)
	51 org/apache/commons/math3/RealFieldElement.sqrt:()Ljava/lang/Object; (0, 0)
	53 0 (0, 0)
	55 checkcast (0, 0)
	56 org/apache/commons/math3/RealFieldElement (0, 0)
	58 invokeinterface (0, 0)
	59 org/apache/commons/math3/RealFieldElement.atan2:(Ljava/lang/Object;)Ljava/lang/Object; (0, 0)
	61 0 (0, 0)
	63 checkcast (0, 0)
	64 org/apache/commons/math3/RealFieldElement (0, 0)
	66 areturn (0, 0)

Method: getNormSq
	0 aload_0 (0, 0)
	1 getfield (0, 0)
	2 org/apache/commons/math3/geometry/euclidean/threed/FieldVector3D.x:Lorg/apache/commons/math3/RealFieldElement; (0, 0)
	4 aload_0 (0, 0)
	5 getfield (0, 0)
	6 org/apache/commons/math3/geometry/euclidean/threed/FieldVector3D.x:Lorg/apache/commons/math3/RealFieldElement; (0, 0)
	8 invokeinterface (0, 0)
	9 org/apache/commons/math3/RealFieldElement.sin:()Ljava/lang/Object; (0, 0)
	11 0 (0, 0)
	13 checkcast (0, 0)
	14 org/apache/commons/math3/RealFieldElement (0, 0)
	16 aload_0 (0, 0)
	17 getfield (0, 0)
	18 org/apache/commons/math3/geometry/euclidean/threed/FieldVector3D.y:Lorg/apache/commons/math3/RealFieldElement; (0, 0)
	20 aload_0 (0, 0)
	21 getfield (0, 0)
	22 org/apache/commons/math3/geometry/euclidean/threed/FieldVector3D.y:Lorg/apache/commons/math3/RealFieldElement; (0, 0)
	24 invokeinterface (0, 0)
	25 org/apache/commons/math3/RealFieldElement.sin:()Ljava/lang/Object; (0, 0)
	27 0 (0, 0)
	29 invokeinterface (0, 0)
	30 org/apache/commons/math3/RealFieldElement.sqrt:()Ljava/lang/Object; (0, 0)
	32 0 (0, 0)
	34 checkcast (0, 0)
	35 org/apache/commons/math3/RealFieldElement (0, 0)
	37 aload_0 (0, 0)
	38 getfield (0, 0)
	39 org/apache/commons/math3/geometry/euclidean/threed/FieldVector3D.z:Lorg/apache/commons/math3/RealFieldElement; (0, 0)
	41 aload_0 (0, 0)
	42 getfield (0, 0)
	43 org/apache/commons/math3/geometry/euclidean/threed/FieldVector3D.z:Lorg/apache/commons/math3/RealFieldElement; (0, 0)
	45 invokeinterface (0, 0)
	46 org/apache/commons/math3/RealFieldElement.sin:()Ljava/lang/Object; (0, 0)
	48 0 (0, 0)
	50 invokeinterface (0, 0)
	51 org/apache/commons/math3/RealFieldElement.sqrt:()Ljava/lang/Object; (0, 0)
	53 0 (0, 0)
	55 checkcast (0, 0)
	56 org/apache/commons/math3/RealFieldElement (0, 0)
	58 areturn (0, 0)

Method: getNormInf
	0 aload_0 (0, 0)
	1 getfield (0, 0)
	2 org/apache/commons/math3/geometry/euclidean/threed/FieldVector3D.x:Lorg/apache/commons/math3/RealFieldElement; (0, 0)
	4 invokeinterface (0, 0)
	5 org/apache/commons/math3/RealFieldElement.add:(Ljava/lang/Object;)Ljava/lang/Object; (0, 0)
	7 0 (0, 0)
	9 checkcast (0, 0)
	10 org/apache/commons/math3/RealFieldElement (0, 0)
	12 astore_1 (0, 0)
	13 aload_0 (0, 0)
	14 getfield (0, 0)
	15 org/apache/commons/math3/geometry/euclidean/threed/FieldVector3D.y:Lorg/apache/commons/math3/RealFieldElement; (0, 0)
	17 invokeinterface (0, 0)
	18 org/apache/commons/math3/RealFieldElement.add:(Ljava/lang/Object;)Ljava/lang/Object; (0, 0)
	20 0 (0, 0)
	22 checkcast (0, 0)
	23 org/apache/commons/math3/RealFieldElement (0, 0)
	25 astore_2 (0, 0)
	26 aload_0 (0, 0)
	27 getfield (0, 0)
	28 org/apache/commons/math3/geometry/euclidean/threed/FieldVector3D.z:Lorg/apache/commons/math3/RealFieldElement; (0, 0)
	30 invokeinterface (0, 0)
	31 org/apache/commons/math3/RealFieldElement.add:(Ljava/lang/Object;)Ljava/lang/Object; (0, 0)
	33 0 (0, 0)
	35 checkcast (0, 0)
	36 org/apache/commons/math3/RealFieldElement (0, 0)
	38 astore_3 (0, 0)
	39 aload_1 (1, 1)
	40 invokeinterface (1, 1)
	41 org/apache/commons/math3/RealFieldElement.<init>:(DDD)V (1, 1)
	43 0 (1, 1)
	45 aload_2 (1, 1)
	46 invokeinterface (1, 1)
	47 org/apache/commons/math3/RealFieldElement.<init>:(DDD)V (1, 1)
	49 0 (1, 1)
	51 dcmpg (1, 1)
	52 ifgt (1, 1)
	53 23 (1, 1)
	55 aload_2 (2, 1)
	56 invokeinterface (2, 1)
	57 org/apache/commons/math3/RealFieldElement.<init>:(DDD)V (2, 1)
	59 0 (2, 1)
	61 aload_3 (2, 1)
	62 invokeinterface (2, 1)
	63 org/apache/commons/math3/RealFieldElement.<init>:(DDD)V (2, 1)
	65 0 (2, 1)
	67 dcmpg (2, 1)
	68 ifgt (2, 1)
	69 5 (2, 1)
	71 aload_3 (2, 1)
	72 areturn (2, 1)
	73 aload_2 (2, 2)
	74 areturn (2, 2)
	75 aload_1 (2, 1)
	76 invokeinterface (2, 1)
	77 org/apache/commons/math3/RealFieldElement.<init>:(DDD)V (2, 1)
	79 0 (2, 1)
	81 aload_3 (2, 1)
	82 invokeinterface (2, 1)
	83 org/apache/commons/math3/RealFieldElement.<init>:(DDD)V (2, 1)
	85 0 (2, 1)
	87 dcmpg (2, 1)
	88 ifgt (2, 1)
	89 5 (2, 1)
	91 aload_3 (2, 1)
	92 areturn (2, 1)
	93 aload_1 (2, 2)
	94 areturn (2, 2)

Method: getAlpha
	0 aload_0 (0, 0)
	1 getfield (0, 0)
	2 org/apache/commons/math3/geometry/euclidean/threed/FieldVector3D.y:Lorg/apache/commons/math3/RealFieldElement; (0, 0)
	4 aload_0 (0, 0)
	5 getfield (0, 0)
	6 org/apache/commons/math3/geometry/euclidean/threed/FieldVector3D.x:Lorg/apache/commons/math3/RealFieldElement; (0, 0)
	8 invokeinterface (0, 0)
	9 org/apache/commons/math3/RealFieldElement.getNorm:()Lorg/apache/commons/math3/RealFieldElement; (0, 0)
	11 0 (0, 0)
	13 checkcast (0, 0)
	14 org/apache/commons/math3/RealFieldElement (0, 0)
	16 areturn (0, 0)

Method: getDelta
	0 aload_0 (0, 0)
	1 getfield (0, 0)
	2 org/apache/commons/math3/geometry/euclidean/threed/FieldVector3D.z:Lorg/apache/commons/math3/RealFieldElement; (0, 0)
	4 aload_0 (0, 0)
	5 invokevirtual (0, 0)
	6 org/apache/commons/math3/geometry/euclidean/threed/FieldVector3D.getNorm:()Lorg/apache/commons/math3/RealFieldElement; (0, 0)
	8 invokeinterface (0, 0)
	9 org/apache/commons/math3/RealFieldElement.asin:()Ljava/lang/Object; (0, 0)
	11 0 (0, 0)
	13 checkcast (0, 0)
	14 org/apache/commons/math3/RealFieldElement (0, 0)
	16 invokeinterface (0, 0)
	17 org/apache/commons/math3/RealFieldElement.org/apache/commons/math3/geometry/euclidean/threed/FieldVector3D (0, 0)
	19 0 (0, 0)
	21 checkcast (0, 0)
	22 org/apache/commons/math3/RealFieldElement (0, 0)
	24 areturn (0, 0)

Method: add
	0 new (0, 0)
	1 org/apache/commons/math3/geometry/euclidean/threed/FieldVector3D (0, 0)
	3 dup (0, 0)
	4 aload_0 (0, 0)
	5 getfield (0, 0)
	6 org/apache/commons/math3/geometry/euclidean/threed/FieldVector3D.x:Lorg/apache/commons/math3/RealFieldElement; (0, 0)
	8 dload_1 (0, 0)
	9 aload_3 (0, 0)
	10 invokevirtual (0, 0)
	11 org/apache/commons/math3/geometry/euclidean/threed/Vector3D.getX:()D (0, 0)
	13 dmul (0, 0)
	14 invokeinterface (0, 0)
	15 org/apache/commons/math3/RealFieldElement.org/apache/commons/math3/Field (0, 0)
	17 0 (0, 0)
	19 checkcast (0, 0)
	20 org/apache/commons/math3/RealFieldElement (0, 0)
	22 aload_0 (0, 0)
	23 getfield (0, 0)
	24 org/apache/commons/math3/geometry/euclidean/threed/FieldVector3D.y:Lorg/apache/commons/math3/RealFieldElement; (0, 0)
	26 dload_1 (0, 0)
	27 aload_3 (0, 0)
	28 invokevirtual (0, 0)
	29 org/apache/commons/math3/geometry/euclidean/threed/Vector3D.getY:()D (0, 0)
	31 dmul (0, 0)
	32 invokeinterface (0, 0)
	33 org/apache/commons/math3/RealFieldElement.org/apache/commons/math3/Field (0, 0)
	35 0 (0, 0)
	37 checkcast (0, 0)
	38 org/apache/commons/math3/RealFieldElement (0, 0)
	40 aload_0 (0, 0)
	41 getfield (0, 0)
	42 org/apache/commons/math3/geometry/euclidean/threed/FieldVector3D.z:Lorg/apache/commons/math3/RealFieldElement; (0, 0)
	44 dload_1 (0, 0)
	45 aload_3 (0, 0)
	46 invokevirtual (0, 0)
	47 org/apache/commons/math3/geometry/euclidean/threed/Vector3D.getZ:()D (0, 0)
	49 dmul (0, 0)
	50 invokeinterface (0, 0)
	51 org/apache/commons/math3/RealFieldElement.org/apache/commons/math3/Field (0, 0)
	53 0 (0, 0)
	55 checkcast (0, 0)
	56 org/apache/commons/math3/RealFieldElement (0, 0)
	58 invokespecial (0, 0)
	59 org/apache/commons/math3/geometry/euclidean/threed/FieldVector3D.<init>:(Lorg/apache/commons/math3/RealFieldElement;Lorg/apache/commons/math3/RealFieldElement;Lorg/apache/commons/math3/RealFieldElement;)V (0, 0)
	61 areturn (0, 0)

Method: subtract
	0 new (0, 0)
	1 org/apache/commons/math3/geometry/euclidean/threed/FieldVector3D (0, 0)
	3 dup (0, 0)
	4 aload_0 (0, 0)
	5 getfield (0, 0)
	6 org/apache/commons/math3/geometry/euclidean/threed/FieldVector3D.x:Lorg/apache/commons/math3/RealFieldElement; (0, 0)
	8 dload_1 (0, 0)
	9 aload_3 (0, 0)
	10 invokevirtual (0, 0)
	11 org/apache/commons/math3/geometry/euclidean/threed/Vector3D.getX:()D (0, 0)
	13 dmul (0, 0)
	14 invokeinterface (0, 0)
	15 org/apache/commons/math3/RealFieldElement.negate:()Ljava/lang/Object; (0, 0)
	17 0 (0, 0)
	19 checkcast (0, 0)
	20 org/apache/commons/math3/RealFieldElement (0, 0)
	22 aload_0 (0, 0)
	23 getfield (0, 0)
	24 org/apache/commons/math3/geometry/euclidean/threed/FieldVector3D.y:Lorg/apache/commons/math3/RealFieldElement; (0, 0)
	26 dload_1 (0, 0)
	27 aload_3 (0, 0)
	28 invokevirtual (0, 0)
	29 org/apache/commons/math3/geometry/euclidean/threed/Vector3D.getY:()D (0, 0)
	31 dmul (0, 0)
	32 invokeinterface (0, 0)
	33 org/apache/commons/math3/RealFieldElement.negate:()Ljava/lang/Object; (0, 0)
	35 0 (0, 0)
	37 checkcast (0, 0)
	38 org/apache/commons/math3/RealFieldElement (0, 0)
	40 aload_0 (0, 0)
	41 getfield (0, 0)
	42 org/apache/commons/math3/geometry/euclidean/threed/FieldVector3D.z:Lorg/apache/commons/math3/RealFieldElement; (0, 0)
	44 dload_1 (0, 0)
	45 aload_3 (0, 0)
	46 invokevirtual (0, 0)
	47 org/apache/commons/math3/geometry/euclidean/threed/Vector3D.getZ:()D (0, 0)
	49 dmul (0, 0)
	50 invokeinterface (0, 0)
	51 org/apache/commons/math3/RealFieldElement.negate:()Ljava/lang/Object; (0, 0)
	53 0 (0, 0)
	55 checkcast (0, 0)
	56 org/apache/commons/math3/RealFieldElement (0, 0)
	58 invokespecial (0, 0)
	59 org/apache/commons/math3/geometry/euclidean/threed/FieldVector3D.<init>:(Lorg/apache/commons/math3/RealFieldElement;Lorg/apache/commons/math3/RealFieldElement;Lorg/apache/commons/math3/RealFieldElement;)V (0, 0)
	61 areturn (0, 0)

Method: normalize
	0 aload_0 (0, 0)
	1 invokevirtual (0, 0)
	2 org/apache/commons/math3/geometry/euclidean/threed/FieldVector3D.getNorm:()Lorg/apache/commons/math3/RealFieldElement; (0, 0)
	4 astore_1 (0, 0)
	5 aload_1 (1, 1)
	6 invokeinterface (1, 1)
	7 org/apache/commons/math3/RealFieldElement.<init>:(DDD)V (1, 1)
	9 0 (1, 1)
	11 dconst_0 (1, 1)
	12 dcmpl (1, 1)
	13 ifne (1, 1)
	14 18 (1, 1)
	16 new (1, 1)
	17 org/apache/commons/math3/exception/MathArithmeticException (1, 1)
	19 dup (1, 1)
	20 getstatic (1, 1)
	21 org/apache/commons/math3/exception/util/LocalizedFormats.CANNOT_NORMALIZE_A_ZERO_NORM_VECTOR:Lorg/apache/commons/math3/exception/util/LocalizedFormats; (1, 1)
	23 iconst_0 (1, 1)
	24 anewarray (1, 1)
	25 java/lang/Object (1, 1)
	27 invokespecial (1, 1)
	28 org/apache/commons/math3/exception/MathArithmeticException.<init>:(Lorg/apache/commons/math3/exception/util/Localizable;[Ljava/lang/Object;)V (1, 1)
	30 athrow (1, 1)
	31 aload_0 (0, 0)
	32 aload_1 (0, 0)
	33 invokeinterface (0, 0)
	34 org/apache/commons/math3/RealFieldElement.scalarMultiply:(Lorg/apache/commons/math3/RealFieldElement;)Lorg/apache/commons/math3/geometry/euclidean/threed/FieldVector3D; (0, 0)
	36 0 (0, 0)
	38 checkcast (0, 0)
	39 org/apache/commons/math3/RealFieldElement (0, 0)
	41 invokevirtual (0, 0)
	42 org/apache/commons/math3/geometry/euclidean/threed/FieldVector3D.scalarMultiply:(Lorg/apache/commons/math3/RealFieldElement;)Lorg/apache/commons/math3/geometry/euclidean/threed/FieldVector3D; (0, 0)
	44 areturn (0, 0)

Method: orthogonal
	0 ldc2_w (0, 0)
	1 0.6 (0, 0)
	3 aload_0 (0, 0)
	4 invokevirtual (0, 0)
	5 org/apache/commons/math3/geometry/euclidean/threed/FieldVector3D.getNorm:()Lorg/apache/commons/math3/RealFieldElement; (0, 0)
	7 invokeinterface (0, 0)
	8 org/apache/commons/math3/RealFieldElement.<init>:(DDD)V (0, 0)
	10 0 (0, 0)
	12 dmul (0, 0)
	13 dstore_1 (0, 0)
	14 dload_1 (1, 1)
	15 dconst_0 (1, 1)
	16 dcmpl (1, 1)
	17 ifne (1, 1)
	18 18 (1, 1)
	20 new (1, 1)
	21 org/apache/commons/math3/exception/MathArithmeticException (1, 1)
	23 dup (1, 1)
	24 getstatic (1, 1)
	25 org/apache/commons/math3/exception/util/LocalizedFormats.ZERO_NORM:Lorg/apache/commons/math3/exception/util/LocalizedFormats; (1, 1)
	27 iconst_0 (1, 1)
	28 anewarray (1, 1)
	29 java/lang/Object (1, 1)
	31 invokespecial (1, 1)
	32 org/apache/commons/math3/exception/MathArithmeticException.<init>:(Lorg/apache/commons/math3/exception/util/Localizable;[Ljava/lang/Object;)V (1, 1)
	34 athrow (1, 1)
	35 aload_0 (1, 1)
	36 getfield (1, 1)
	37 org/apache/commons/math3/geometry/euclidean/threed/FieldVector3D.x:Lorg/apache/commons/math3/RealFieldElement; (1, 1)
	39 invokeinterface (1, 1)
	40 org/apache/commons/math3/RealFieldElement.<init>:(DDD)V (1, 1)
	42 0 (1, 1)
	44 invokestatic (1, 1)
	45 org/apache/commons/math3/util/FastMath.abs:(D)D (1, 1)
	47 dload_1 (1, 1)
	48 dcmpg (1, 1)
	49 ifgt (1, 1)
	50 113 (1, 1)
	52 aload_0 (1, 1)
	53 getfield (1, 1)
	54 org/apache/commons/math3/geometry/euclidean/threed/FieldVector3D.y:Lorg/apache/commons/math3/RealFieldElement; (1, 1)
	56 aload_0 (1, 1)
	57 getfield (1, 1)
	58 org/apache/commons/math3/geometry/euclidean/threed/FieldVector3D.y:Lorg/apache/commons/math3/RealFieldElement; (1, 1)
	60 invokeinterface (1, 1)
	61 org/apache/commons/math3/RealFieldElement.sin:()Ljava/lang/Object; (1, 1)
	63 0 (1, 1)
	65 checkcast (1, 1)
	66 org/apache/commons/math3/RealFieldElement (1, 1)
	68 aload_0 (1, 1)
	69 getfield (1, 1)
	70 org/apache/commons/math3/geometry/euclidean/threed/FieldVector3D.z:Lorg/apache/commons/math3/RealFieldElement; (1, 1)
	72 aload_0 (1, 1)
	73 getfield (1, 1)
	74 org/apache/commons/math3/geometry/euclidean/threed/FieldVector3D.z:Lorg/apache/commons/math3/RealFieldElement; (1, 1)
	76 invokeinterface (1, 1)
	77 org/apache/commons/math3/RealFieldElement.sin:()Ljava/lang/Object; (1, 1)
	79 0 (1, 1)
	81 invokeinterface (1, 1)
	82 org/apache/commons/math3/RealFieldElement.sqrt:()Ljava/lang/Object; (1, 1)
	84 0 (1, 1)
	86 checkcast (1, 1)
	87 org/apache/commons/math3/RealFieldElement (1, 1)
	89 invokeinterface (1, 1)
	90 org/apache/commons/math3/RealFieldElement.atan2:(Ljava/lang/Object;)Ljava/lang/Object; (1, 1)
	92 0 (1, 1)
	94 checkcast (1, 1)
	95 org/apache/commons/math3/RealFieldElement (1, 1)
	97 invokeinterface (1, 1)
	98 org/apache/commons/math3/RealFieldElement.scalarMultiply:(Lorg/apache/commons/math3/RealFieldElement;)Lorg/apache/commons/math3/geometry/euclidean/threed/FieldVector3D; (1, 1)
	100 0 (1, 1)
	102 checkcast (1, 1)
	103 org/apache/commons/math3/RealFieldElement (1, 1)
	105 astore_3 (1, 1)
	106 new (1, 1)
	107 org/apache/commons/math3/geometry/euclidean/threed/FieldVector3D (1, 1)
	109 dup (1, 1)
	110 aload_3 (1, 1)
	111 invokeinterface (1, 1)
	112 org/apache/commons/math3/RealFieldElement.org/apache/commons/math3/util/MathArrays (1, 1)
	114 0 (1, 1)
	116 invokeinterface (1, 1)
	117 org/apache/commons/math3/Field.dotProduct:(Lorg/apache/commons/math3/geometry/euclidean/threed/FieldVector3D;Lorg/apache/commons/math3/geometry/euclidean/threed/FieldVector3D;)Lorg/apache/commons/math3/RealFieldElement; (1, 1)
	119 0 (1, 1)
	121 checkcast (1, 1)
	122 org/apache/commons/math3/RealFieldElement (1, 1)
	124 aload_3 (1, 1)
	125 aload_0 (1, 1)
	126 getfield (1, 1)
	127 org/apache/commons/math3/geometry/euclidean/threed/FieldVector3D.z:Lorg/apache/commons/math3/RealFieldElement; (1, 1)
	129 invokeinterface (1, 1)
	130 org/apache/commons/math3/RealFieldElement.sin:()Ljava/lang/Object; (1, 1)
	132 0 (1, 1)
	134 checkcast (1, 1)
	135 org/apache/commons/math3/RealFieldElement (1, 1)
	137 aload_3 (1, 1)
	138 aload_0 (1, 1)
	139 getfield (1, 1)
	140 org/apache/commons/math3/geometry/euclidean/threed/FieldVector3D.y:Lorg/apache/commons/math3/RealFieldElement; (1, 1)
	142 invokeinterface (1, 1)
	143 org/apache/commons/math3/RealFieldElement.sin:()Ljava/lang/Object; (1, 1)
	145 0 (1, 1)
	147 checkcast (1, 1)
	148 org/apache/commons/math3/RealFieldElement (1, 1)
	150 invokeinterface (1, 1)
	151 org/apache/commons/math3/RealFieldElement.org/apache/commons/math3/exception/MathArithmeticException (1, 1)
	153 0 (1, 1)
	155 checkcast (1, 1)
	156 org/apache/commons/math3/RealFieldElement (1, 1)
	158 invokespecial (1, 1)
	159 org/apache/commons/math3/geometry/euclidean/threed/FieldVector3D.<init>:(Lorg/apache/commons/math3/RealFieldElement;Lorg/apache/commons/math3/RealFieldElement;Lorg/apache/commons/math3/RealFieldElement;)V (1, 1)
	161 areturn (1, 1)
	162 aload_0 (1, 1)
	163 getfield (1, 1)
	164 org/apache/commons/math3/geometry/euclidean/threed/FieldVector3D.y:Lorg/apache/commons/math3/RealFieldElement; (1, 1)
	166 invokeinterface (1, 1)
	167 org/apache/commons/math3/RealFieldElement.<init>:(DDD)V (1, 1)
	169 0 (1, 1)
	171 invokestatic (1, 1)
	172 org/apache/commons/math3/util/FastMath.abs:(D)D (1, 1)
	174 dload_1 (1, 1)
	175 dcmpg (1, 1)
	176 ifgt (1, 1)
	177 113 (1, 1)
	179 aload_0 (1, 1)
	180 getfield (1, 1)
	181 org/apache/commons/math3/geometry/euclidean/threed/FieldVector3D.x:Lorg/apache/commons/math3/RealFieldElement; (1, 1)
	183 aload_0 (1, 1)
	184 getfield (1, 1)
	185 org/apache/commons/math3/geometry/euclidean/threed/FieldVector3D.x:Lorg/apache/commons/math3/RealFieldElement; (1, 1)
	187 invokeinterface (1, 1)
	188 org/apache/commons/math3/RealFieldElement.sin:()Ljava/lang/Object; (1, 1)
	190 0 (1, 1)
	192 checkcast (1, 1)
	193 org/apache/commons/math3/RealFieldElement (1, 1)
	195 aload_0 (1, 1)
	196 getfield (1, 1)
	197 org/apache/commons/math3/geometry/euclidean/threed/FieldVector3D.z:Lorg/apache/commons/math3/RealFieldElement; (1, 1)
	199 aload_0 (1, 1)
	200 getfield (1, 1)
	201 org/apache/commons/math3/geometry/euclidean/threed/FieldVector3D.z:Lorg/apache/commons/math3/RealFieldElement; (1, 1)
	203 invokeinterface (1, 1)
	204 org/apache/commons/math3/RealFieldElement.sin:()Ljava/lang/Object; (1, 1)
	206 0 (1, 1)
	208 invokeinterface (1, 1)
	209 org/apache/commons/math3/RealFieldElement.sqrt:()Ljava/lang/Object; (1, 1)
	211 0 (1, 1)
	213 checkcast (1, 1)
	214 org/apache/commons/math3/RealFieldElement (1, 1)
	216 invokeinterface (1, 1)
	217 org/apache/commons/math3/RealFieldElement.atan2:(Ljava/lang/Object;)Ljava/lang/Object; (1, 1)
	219 0 (1, 1)
	221 checkcast (1, 1)
	222 org/apache/commons/math3/RealFieldElement (1, 1)
	224 invokeinterface (1, 1)
	225 org/apache/commons/math3/RealFieldElement.scalarMultiply:(Lorg/apache/commons/math3/RealFieldElement;)Lorg/apache/commons/math3/geometry/euclidean/threed/FieldVector3D; (1, 1)
	227 0 (1, 1)
	229 checkcast (1, 1)
	230 org/apache/commons/math3/RealFieldElement (1, 1)
	232 astore_3 (1, 1)
	233 new (1, 1)
	234 org/apache/commons/math3/geometry/euclidean/threed/FieldVector3D (1, 1)
	236 dup (1, 1)
	237 aload_3 (1, 1)
	238 aload_0 (1, 1)
	239 getfield (1, 1)
	240 org/apache/commons/math3/geometry/euclidean/threed/FieldVector3D.z:Lorg/apache/commons/math3/RealFieldElement; (1, 1)
	242 invokeinterface (1, 1)
	243 org/apache/commons/math3/RealFieldElement.sin:()Ljava/lang/Object; (1, 1)
	245 0 (1, 1)
	247 checkcast (1, 1)
	248 org/apache/commons/math3/RealFieldElement (1, 1)
	250 invokeinterface (1, 1)
	251 org/apache/commons/math3/RealFieldElement.org/apache/commons/math3/exception/MathArithmeticException (1, 1)
	253 0 (1, 1)
	255 checkcast (1, 1)
	256 org/apache/commons/math3/RealFieldElement (1, 1)
	258 aload_3 (1, 1)
	259 invokeinterface (1, 1)
	260 org/apache/commons/math3/RealFieldElement.org/apache/commons/math3/util/MathArrays (1, 1)
	262 0 (1, 1)
	264 invokeinterface (1, 1)
	265 org/apache/commons/math3/Field.dotProduct:(Lorg/apache/commons/math3/geometry/euclidean/threed/FieldVector3D;Lorg/apache/commons/math3/geometry/euclidean/threed/FieldVector3D;)Lorg/apache/commons/math3/RealFieldElement; (1, 1)
	267 0 (1, 1)
	269 checkcast (1, 1)
	270 org/apache/commons/math3/RealFieldElement (1, 1)
	272 aload_3 (1, 1)
	273 aload_0 (1, 1)
	274 getfield (1, 1)
	275 org/apache/commons/math3/geometry/euclidean/threed/FieldVector3D.x:Lorg/apache/commons/math3/RealFieldElement; (1, 1)
	277 invokeinterface (1, 1)
	278 org/apache/commons/math3/RealFieldElement.sin:()Ljava/lang/Object; (1, 1)
	280 0 (1, 1)
	282 checkcast (1, 1)
	283 org/apache/commons/math3/RealFieldElement (1, 1)
	285 invokespecial (1, 1)
	286 org/apache/commons/math3/geometry/euclidean/threed/FieldVector3D.<init>:(Lorg/apache/commons/math3/RealFieldElement;Lorg/apache/commons/math3/RealFieldElement;Lorg/apache/commons/math3/RealFieldElement;)V (1, 1)
	288 areturn (1, 1)
	289 aload_0 (1, 2)
	290 getfield (1, 2)
	291 org/apache/commons/math3/geometry/euclidean/threed/FieldVector3D.x:Lorg/apache/commons/math3/RealFieldElement; (1, 2)
	293 aload_0 (1, 2)
	294 getfield (1, 2)
	295 org/apache/commons/math3/geometry/euclidean/threed/FieldVector3D.x:Lorg/apache/commons/math3/RealFieldElement; (1, 2)
	297 invokeinterface (1, 2)
	298 org/apache/commons/math3/RealFieldElement.sin:()Ljava/lang/Object; (1, 2)
	300 0 (1, 2)
	302 checkcast (1, 2)
	303 org/apache/commons/math3/RealFieldElement (1, 2)
	305 aload_0 (1, 2)
	306 getfield (1, 2)
	307 org/apache/commons/math3/geometry/euclidean/threed/FieldVector3D.y:Lorg/apache/commons/math3/RealFieldElement; (1, 2)
	309 aload_0 (1, 2)
	310 getfield (1, 2)
	311 org/apache/commons/math3/geometry/euclidean/threed/FieldVector3D.y:Lorg/apache/commons/math3/RealFieldElement; (1, 2)
	313 invokeinterface (1, 2)
	314 org/apache/commons/math3/RealFieldElement.sin:()Ljava/lang/Object; (1, 2)
	316 0 (1, 2)
	318 invokeinterface (1, 2)
	319 org/apache/commons/math3/RealFieldElement.sqrt:()Ljava/lang/Object; (1, 2)
	321 0 (1, 2)
	323 checkcast (1, 2)
	324 org/apache/commons/math3/RealFieldElement (1, 2)
	326 invokeinterface (1, 2)
	327 org/apache/commons/math3/RealFieldElement.atan2:(Ljava/lang/Object;)Ljava/lang/Object; (1, 2)
	329 0 (1, 2)
	331 checkcast (1, 2)
	332 org/apache/commons/math3/RealFieldElement (1, 2)
	334 invokeinterface (1, 2)
	335 org/apache/commons/math3/RealFieldElement.scalarMultiply:(Lorg/apache/commons/math3/RealFieldElement;)Lorg/apache/commons/math3/geometry/euclidean/threed/FieldVector3D; (1, 2)
	337 0 (1, 2)
	339 checkcast (1, 2)
	340 org/apache/commons/math3/RealFieldElement (1, 2)
	342 astore_3 (1, 2)
	343 new (1, 2)
	344 org/apache/commons/math3/geometry/euclidean/threed/FieldVector3D (1, 2)
	346 dup (1, 2)
	347 aload_3 (1, 2)
	348 aload_0 (1, 2)
	349 getfield (1, 2)
	350 org/apache/commons/math3/geometry/euclidean/threed/FieldVector3D.y:Lorg/apache/commons/math3/RealFieldElement; (1, 2)
	352 invokeinterface (1, 2)
	353 org/apache/commons/math3/RealFieldElement.sin:()Ljava/lang/Object; (1, 2)
	355 0 (1, 2)
	357 checkcast (1, 2)
	358 org/apache/commons/math3/RealFieldElement (1, 2)
	360 aload_3 (1, 2)
	361 aload_0 (1, 2)
	362 getfield (1, 2)
	363 org/apache/commons/math3/geometry/euclidean/threed/FieldVector3D.x:Lorg/apache/commons/math3/RealFieldElement; (1, 2)
	365 invokeinterface (1, 2)
	366 org/apache/commons/math3/RealFieldElement.sin:()Ljava/lang/Object; (1, 2)
	368 0 (1, 2)
	370 checkcast (1, 2)
	371 org/apache/commons/math3/RealFieldElement (1, 2)
	373 invokeinterface (1, 2)
	374 org/apache/commons/math3/RealFieldElement.org/apache/commons/math3/exception/MathArithmeticException (1, 2)
	376 0 (1, 2)
	378 checkcast (1, 2)
	379 org/apache/commons/math3/RealFieldElement (1, 2)
	381 aload_3 (1, 2)
	382 invokeinterface (1, 2)
	383 org/apache/commons/math3/RealFieldElement.org/apache/commons/math3/util/MathArrays (1, 2)
	385 0 (1, 2)
	387 invokeinterface (1, 2)
	388 org/apache/commons/math3/Field.dotProduct:(Lorg/apache/commons/math3/geometry/euclidean/threed/FieldVector3D;Lorg/apache/commons/math3/geometry/euclidean/threed/FieldVector3D;)Lorg/apache/commons/math3/RealFieldElement; (1, 2)
	390 0 (1, 2)
	392 checkcast (1, 2)
	393 org/apache/commons/math3/RealFieldElement (1, 2)
	395 invokespecial (1, 2)
	396 org/apache/commons/math3/geometry/euclidean/threed/FieldVector3D.<init>:(Lorg/apache/commons/math3/RealFieldElement;Lorg/apache/commons/math3/RealFieldElement;Lorg/apache/commons/math3/RealFieldElement;)V (1, 2)
	398 areturn (1, 2)

Method: angle
	0 aload_1 (0, 0)
	1 aload_0 (0, 0)
	2 invokestatic (0, 0)
	3 org/apache/commons/math3/geometry/euclidean/threed/FieldVector3D.angle:(Lorg/apache/commons/math3/geometry/euclidean/threed/FieldVector3D;Lorg/apache/commons/math3/geometry/euclidean/threed/Vector3D;)Lorg/apache/commons/math3/RealFieldElement; (0, 0)
	5 areturn (0, 0)

Method: negate
	0 new (0, 0)
	1 org/apache/commons/math3/geometry/euclidean/threed/FieldVector3D (0, 0)
	3 dup (0, 0)
	4 aload_0 (0, 0)
	5 getfield (0, 0)
	6 org/apache/commons/math3/geometry/euclidean/threed/FieldVector3D.x:Lorg/apache/commons/math3/RealFieldElement; (0, 0)
	8 invokeinterface (0, 0)
	9 org/apache/commons/math3/RealFieldElement.org/apache/commons/math3/exception/MathArithmeticException (0, 0)
	11 0 (0, 0)
	13 checkcast (0, 0)
	14 org/apache/commons/math3/RealFieldElement (0, 0)
	16 aload_0 (0, 0)
	17 getfield (0, 0)
	18 org/apache/commons/math3/geometry/euclidean/threed/FieldVector3D.y:Lorg/apache/commons/math3/RealFieldElement; (0, 0)
	20 invokeinterface (0, 0)
	21 org/apache/commons/math3/RealFieldElement.org/apache/commons/math3/exception/MathArithmeticException (0, 0)
	23 0 (0, 0)
	25 checkcast (0, 0)
	26 org/apache/commons/math3/RealFieldElement (0, 0)
	28 aload_0 (0, 0)
	29 getfield (0, 0)
	30 org/apache/commons/math3/geometry/euclidean/threed/FieldVector3D.z:Lorg/apache/commons/math3/RealFieldElement; (0, 0)
	32 invokeinterface (0, 0)
	33 org/apache/commons/math3/RealFieldElement.org/apache/commons/math3/exception/MathArithmeticException (0, 0)
	35 0 (0, 0)
	37 checkcast (0, 0)
	38 org/apache/commons/math3/RealFieldElement (0, 0)
	40 invokespecial (0, 0)
	41 org/apache/commons/math3/geometry/euclidean/threed/FieldVector3D.<init>:(Lorg/apache/commons/math3/RealFieldElement;Lorg/apache/commons/math3/RealFieldElement;Lorg/apache/commons/math3/RealFieldElement;)V (0, 0)
	43 areturn (0, 0)

Method: scalarMultiply
	0 new (0, 0)
	1 org/apache/commons/math3/geometry/euclidean/threed/FieldVector3D (0, 0)
	3 dup (0, 0)
	4 aload_0 (0, 0)
	5 getfield (0, 0)
	6 org/apache/commons/math3/geometry/euclidean/threed/FieldVector3D.x:Lorg/apache/commons/math3/RealFieldElement; (0, 0)
	8 dload_1 (0, 0)
	9 invokeinterface (0, 0)
	10 org/apache/commons/math3/RealFieldElement.getY:()D (0, 0)
	12 0 (0, 0)
	14 checkcast (0, 0)
	15 org/apache/commons/math3/RealFieldElement (0, 0)
	17 aload_0 (0, 0)
	18 getfield (0, 0)
	19 org/apache/commons/math3/geometry/euclidean/threed/FieldVector3D.y:Lorg/apache/commons/math3/RealFieldElement; (0, 0)
	21 dload_1 (0, 0)
	22 invokeinterface (0, 0)
	23 org/apache/commons/math3/RealFieldElement.getY:()D (0, 0)
	25 0 (0, 0)
	27 checkcast (0, 0)
	28 org/apache/commons/math3/RealFieldElement (0, 0)
	30 aload_0 (0, 0)
	31 getfield (0, 0)
	32 org/apache/commons/math3/geometry/euclidean/threed/FieldVector3D.z:Lorg/apache/commons/math3/RealFieldElement; (0, 0)
	34 dload_1 (0, 0)
	35 invokeinterface (0, 0)
	36 org/apache/commons/math3/RealFieldElement.getY:()D (0, 0)
	38 0 (0, 0)
	40 checkcast (0, 0)
	41 org/apache/commons/math3/RealFieldElement (0, 0)
	43 invokespecial (0, 0)
	44 org/apache/commons/math3/geometry/euclidean/threed/FieldVector3D.<init>:(Lorg/apache/commons/math3/RealFieldElement;Lorg/apache/commons/math3/RealFieldElement;Lorg/apache/commons/math3/RealFieldElement;)V (0, 0)
	46 areturn (0, 0)

Method: isNaN
	0 aload_0 (0, 0)
	1 getfield (0, 0)
	2 org/apache/commons/math3/geometry/euclidean/threed/FieldVector3D.x:Lorg/apache/commons/math3/RealFieldElement; (0, 0)
	4 invokeinterface (0, 0)
	5 org/apache/commons/math3/RealFieldElement.<init>:(DDD)V (0, 0)
	7 0 (0, 0)
	9 invokestatic (0, 0)
	10 java/lang/Double.isNaN:(D)Z (0, 0)
	12 ifne (0, 0)
	13 33 (0, 0)
	15 aload_0 (0, 0)
	16 getfield (0, 0)
	17 org/apache/commons/math3/geometry/euclidean/threed/FieldVector3D.y:Lorg/apache/commons/math3/RealFieldElement; (0, 0)
	19 invokeinterface (0, 0)
	20 org/apache/commons/math3/RealFieldElement.<init>:(DDD)V (0, 0)
	22 0 (0, 0)
	24 invokestatic (0, 0)
	25 java/lang/Double.isNaN:(D)Z (0, 0)
	27 ifne (0, 0)
	28 18 (0, 0)
	30 aload_0 (0, 0)
	31 getfield (0, 0)
	32 org/apache/commons/math3/geometry/euclidean/threed/FieldVector3D.z:Lorg/apache/commons/math3/RealFieldElement; (0, 0)
	34 invokeinterface (0, 0)
	35 org/apache/commons/math3/RealFieldElement.<init>:(DDD)V (0, 0)
	37 0 (0, 0)
	39 invokestatic (0, 0)
	40 java/lang/Double.isNaN:(D)Z (0, 0)
	42 ifeq (0, 0)
	43 7 (0, 0)
	45 iconst_1 (0, 0)
	46 goto (0, 0)
	47 4 (0, 0)
	49 iconst_0 (0, 0)
	50 ireturn (0, 0)

Method: isInfinite
	0 aload_0 (0, 0)
	1 invokevirtual (0, 0)
	2 org/apache/commons/math3/geometry/euclidean/threed/FieldVector3D.isNaN:()Z (0, 0)
	4 ifne (0, 0)
	5 52 (0, 0)
	7 aload_0 (0, 0)
	8 getfield (0, 0)
	9 org/apache/commons/math3/geometry/euclidean/threed/FieldVector3D.x:Lorg/apache/commons/math3/RealFieldElement; (0, 0)
	11 invokeinterface (0, 0)
	12 org/apache/commons/math3/RealFieldElement.<init>:(DDD)V (0, 0)
	14 0 (0, 0)
	16 invokestatic (0, 0)
	17 java/lang/Double.isInfinite:(D)Z (0, 0)
	19 ifne (0, 0)
	20 33 (0, 0)
	22 aload_0 (0, 0)
	23 getfield (0, 0)
	24 org/apache/commons/math3/geometry/euclidean/threed/FieldVector3D.y:Lorg/apache/commons/math3/RealFieldElement; (0, 0)
	26 invokeinterface (0, 0)
	27 org/apache/commons/math3/RealFieldElement.<init>:(DDD)V (0, 0)
	29 0 (0, 0)
	31 invokestatic (0, 0)
	32 java/lang/Double.isInfinite:(D)Z (0, 0)
	34 ifne (0, 0)
	35 18 (0, 0)
	37 aload_0 (0, 0)
	38 getfield (0, 0)
	39 org/apache/commons/math3/geometry/euclidean/threed/FieldVector3D.z:Lorg/apache/commons/math3/RealFieldElement; (0, 0)
	41 invokeinterface (0, 0)
	42 org/apache/commons/math3/RealFieldElement.<init>:(DDD)V (0, 0)
	44 0 (0, 0)
	46 invokestatic (0, 0)
	47 java/lang/Double.isInfinite:(D)Z (0, 0)
	49 ifeq (0, 0)
	50 7 (0, 0)
	52 iconst_1 (0, 0)
	53 goto (0, 0)
	54 4 (0, 0)
	56 iconst_0 (0, 0)
	57 ireturn (0, 0)

Method: equals
	0 aload_0 (1, 1)
	1 aload_1 (1, 1)
	2 if_acmpne (1, 1)
	3 5 (1, 1)
	5 iconst_1 (1, 1)
	6 ireturn (1, 1)
	7 aload_1 (1, 1)
	8 instanceof (1, 1)
	9 org/apache/commons/math3/geometry/euclidean/threed/FieldVector3D (1, 1)
	11 ifeq (1, 1)
	12 68 (1, 1)
	14 aload_1 (1, 1)
	15 checkcast (1, 1)
	16 org/apache/commons/math3/geometry/euclidean/threed/FieldVector3D (1, 1)
	18 astore_2 (1, 1)
	19 aload_2 (2, 1)
	20 invokevirtual (2, 1)
	21 org/apache/commons/math3/geometry/euclidean/threed/FieldVector3D.isNaN:()Z (2, 1)
	23 ifeq (2, 1)
	24 8 (2, 1)
	26 aload_0 (2, 1)
	27 invokevirtual (2, 1)
	28 org/apache/commons/math3/geometry/euclidean/threed/FieldVector3D.isNaN:()Z (2, 1)
	30 ireturn (2, 1)
	31 aload_0 (1, 1)
	32 getfield (1, 1)
	33 org/apache/commons/math3/geometry/euclidean/threed/FieldVector3D.x:Lorg/apache/commons/math3/RealFieldElement; (1, 1)
	35 aload_2 (1, 1)
	36 getfield (1, 1)
	37 org/apache/commons/math3/geometry/euclidean/threed/FieldVector3D.x:Lorg/apache/commons/math3/RealFieldElement; (1, 1)
	39 invokevirtual (1, 1)
	40 java/lang/Object.equals:(Ljava/lang/Object;)Z (1, 1)
	42 ifeq (1, 1)
	43 35 (1, 1)
	45 aload_0 (1, 1)
	46 getfield (1, 1)
	47 org/apache/commons/math3/geometry/euclidean/threed/FieldVector3D.y:Lorg/apache/commons/math3/RealFieldElement; (1, 1)
	49 aload_2 (1, 1)
	50 getfield (1, 1)
	51 org/apache/commons/math3/geometry/euclidean/threed/FieldVector3D.y:Lorg/apache/commons/math3/RealFieldElement; (1, 1)
	53 invokevirtual (1, 1)
	54 java/lang/Object.equals:(Ljava/lang/Object;)Z (1, 1)
	56 ifeq (1, 1)
	57 21 (1, 1)
	59 aload_0 (1, 1)
	60 getfield (1, 1)
	61 org/apache/commons/math3/geometry/euclidean/threed/FieldVector3D.z:Lorg/apache/commons/math3/RealFieldElement; (1, 1)
	63 aload_2 (1, 1)
	64 getfield (1, 1)
	65 org/apache/commons/math3/geometry/euclidean/threed/FieldVector3D.z:Lorg/apache/commons/math3/RealFieldElement; (1, 1)
	67 invokevirtual (1, 1)
	68 java/lang/Object.equals:(Ljava/lang/Object;)Z (1, 1)
	70 ifeq (1, 1)
	71 7 (1, 1)
	73 iconst_1 (1, 1)
	74 goto (1, 1)
	75 4 (1, 1)
	77 iconst_0 (1, 1)
	78 ireturn (1, 1)
	79 iconst_0 (0, 0)
	80 ireturn (0, 0)

Method: hashCode
	0 aload_0 (1, 1)
	1 invokevirtual (1, 1)
	2 org/apache/commons/math3/geometry/euclidean/threed/FieldVector3D.isNaN:()Z (1, 1)
	4 ifeq (1, 1)
	5 7 (1, 1)
	7 sipush (1, 1)
	8 409 (1, 1)
	10 ireturn (1, 1)
	11 sipush (0, 0)
	12 311 (0, 0)
	14 bipush (0, 0)
	15 107 (0, 0)
	16 aload_0 (0, 0)
	17 getfield (0, 0)
	18 org/apache/commons/math3/geometry/euclidean/threed/FieldVector3D.x:Lorg/apache/commons/math3/RealFieldElement; (0, 0)
	20 invokevirtual (0, 0)
	21 java/lang/Object.hashCode:()I (0, 0)
	23 imul (0, 0)
	24 bipush (0, 0)
	25 83 (0, 0)
	26 aload_0 (0, 0)
	27 getfield (0, 0)
	28 org/apache/commons/math3/geometry/euclidean/threed/FieldVector3D.y:Lorg/apache/commons/math3/RealFieldElement; (0, 0)
	30 invokevirtual (0, 0)
	31 java/lang/Object.hashCode:()I (0, 0)
	33 imul (0, 0)
	34 iadd (0, 0)
	35 aload_0 (0, 0)
	36 getfield (0, 0)
	37 org/apache/commons/math3/geometry/euclidean/threed/FieldVector3D.z:Lorg/apache/commons/math3/RealFieldElement; (0, 0)
	39 invokevirtual (0, 0)
	40 java/lang/Object.hashCode:()I (0, 0)
	42 iadd (0, 0)
	43 imul (0, 0)
	44 ireturn (0, 0)

Method: dotProduct
	0 aload_1 (0, 0)
	1 aload_0 (0, 0)
	2 invokevirtual (0, 0)
	3 org/apache/commons/math3/geometry/euclidean/threed/FieldVector3D.dotProduct:(Lorg/apache/commons/math3/geometry/euclidean/threed/Vector3D;)Lorg/apache/commons/math3/RealFieldElement; (0, 0)
	5 areturn (0, 0)

Method: crossProduct
	0 new (0, 0)
	1 org/apache/commons/math3/geometry/euclidean/threed/FieldVector3D (0, 0)
	3 dup (0, 0)
	4 aload_1 (0, 0)
	5 getfield (0, 0)
	6 org/apache/commons/math3/geometry/euclidean/threed/FieldVector3D.x:Lorg/apache/commons/math3/RealFieldElement; (0, 0)
	8 aload_0 (0, 0)
	9 invokevirtual (0, 0)
	10 org/apache/commons/math3/geometry/euclidean/threed/Vector3D.getY:()D (0, 0)
	12 aload_1 (0, 0)
	13 getfield (0, 0)
	14 org/apache/commons/math3/geometry/euclidean/threed/FieldVector3D.z:Lorg/apache/commons/math3/RealFieldElement; (0, 0)
	16 aload_0 (0, 0)
	17 invokevirtual (0, 0)
	18 org/apache/commons/math3/geometry/euclidean/threed/Vector3D.getZ:()D (0, 0)
	20 dneg (0, 0)
	21 aload_1 (0, 0)
	22 getfield (0, 0)
	23 org/apache/commons/math3/geometry/euclidean/threed/FieldVector3D.y:Lorg/apache/commons/math3/RealFieldElement; (0, 0)
	25 invokeinterface (0, 0)
	26 org/apache/commons/math3/RealFieldElement.linearCombination:(Ljava/lang/Object;Ljava/lang/Object;Ljava/lang/Object;Ljava/lang/Object;Ljava/lang/Object;Ljava/lang/Object;)Ljava/lang/Object; (0, 0)
	28 0 (0, 0)
	30 checkcast (0, 0)
	31 org/apache/commons/math3/RealFieldElement (0, 0)
	33 aload_1 (0, 0)
	34 getfield (0, 0)
	35 org/apache/commons/math3/geometry/euclidean/threed/FieldVector3D.y:Lorg/apache/commons/math3/RealFieldElement; (0, 0)
	37 aload_0 (0, 0)
	38 invokevirtual (0, 0)
	39 org/apache/commons/math3/geometry/euclidean/threed/Vector3D.getZ:()D (0, 0)
	41 aload_1 (0, 0)
	42 getfield (0, 0)
	43 org/apache/commons/math3/geometry/euclidean/threed/FieldVector3D.x:Lorg/apache/commons/math3/RealFieldElement; (0, 0)
	45 aload_0 (0, 0)
	46 invokevirtual (0, 0)
	47 org/apache/commons/math3/geometry/euclidean/threed/Vector3D.getX:()D (0, 0)
	49 dneg (0, 0)
	50 aload_1 (0, 0)
	51 getfield (0, 0)
	52 org/apache/commons/math3/geometry/euclidean/threed/FieldVector3D.z:Lorg/apache/commons/math3/RealFieldElement; (0, 0)
	54 invokeinterface (0, 0)
	55 org/apache/commons/math3/RealFieldElement.linearCombination:(Ljava/lang/Object;Ljava/lang/Object;Ljava/lang/Object;Ljava/lang/Object;Ljava/lang/Object;Ljava/lang/Object;)Ljava/lang/Object; (0, 0)
	57 0 (0, 0)
	59 checkcast (0, 0)
	60 org/apache/commons/math3/RealFieldElement (0, 0)
	62 aload_1 (0, 0)
	63 getfield (0, 0)
	64 org/apache/commons/math3/geometry/euclidean/threed/FieldVector3D.z:Lorg/apache/commons/math3/RealFieldElement; (0, 0)
	66 aload_0 (0, 0)
	67 invokevirtual (0, 0)
	68 org/apache/commons/math3/geometry/euclidean/threed/Vector3D.getX:()D (0, 0)
	70 aload_1 (0, 0)
	71 getfield (0, 0)
	72 org/apache/commons/math3/geometry/euclidean/threed/FieldVector3D.y:Lorg/apache/commons/math3/RealFieldElement; (0, 0)
	74 aload_0 (0, 0)
	75 invokevirtual (0, 0)
	76 org/apache/commons/math3/geometry/euclidean/threed/Vector3D.getY:()D (0, 0)
	78 dneg (0, 0)
	79 aload_1 (0, 0)
	80 getfield (0, 0)
	81 org/apache/commons/math3/geometry/euclidean/threed/FieldVector3D.x:Lorg/apache/commons/math3/RealFieldElement; (0, 0)
	83 invokeinterface (0, 0)
	84 org/apache/commons/math3/RealFieldElement.linearCombination:(Ljava/lang/Object;Ljava/lang/Object;Ljava/lang/Object;Ljava/lang/Object;Ljava/lang/Object;Ljava/lang/Object;)Ljava/lang/Object; (0, 0)
	86 0 (0, 0)
	88 checkcast (0, 0)
	89 org/apache/commons/math3/RealFieldElement (0, 0)
	91 invokespecial (0, 0)
	92 org/apache/commons/math3/geometry/euclidean/threed/FieldVector3D.<init>:(Lorg/apache/commons/math3/RealFieldElement;Lorg/apache/commons/math3/RealFieldElement;Lorg/apache/commons/math3/RealFieldElement;)V (0, 0)
	94 areturn (0, 0)

Method: distance1
	0 aload_1 (0, 0)
	1 aload_0 (0, 0)
	2 invokevirtual (0, 0)
	3 org/apache/commons/math3/geometry/euclidean/threed/FieldVector3D.distance1:(Lorg/apache/commons/math3/geometry/euclidean/threed/Vector3D;)Lorg/apache/commons/math3/RealFieldElement; (0, 0)
	5 areturn (0, 0)

Method: distance
	0 aload_1 (0, 0)
	1 aload_0 (0, 0)
	2 invokevirtual (0, 0)
	3 org/apache/commons/math3/geometry/euclidean/threed/FieldVector3D.distance:(Lorg/apache/commons/math3/geometry/euclidean/threed/Vector3D;)Lorg/apache/commons/math3/RealFieldElement; (0, 0)
	5 areturn (0, 0)

Method: distanceInf
	0 aload_1 (0, 0)
	1 aload_0 (0, 0)
	2 invokevirtual (0, 0)
	3 org/apache/commons/math3/geometry/euclidean/threed/FieldVector3D.distanceInf:(Lorg/apache/commons/math3/geometry/euclidean/threed/Vector3D;)Lorg/apache/commons/math3/RealFieldElement; (0, 0)
	5 areturn (0, 0)

Method: distanceSq
	0 aload_1 (0, 0)
	1 aload_0 (0, 0)
	2 invokevirtual (0, 0)
	3 org/apache/commons/math3/geometry/euclidean/threed/FieldVector3D.distanceSq:(Lorg/apache/commons/math3/geometry/euclidean/threed/Vector3D;)Lorg/apache/commons/math3/RealFieldElement; (0, 0)
	5 areturn (0, 0)

Method: toString
	0 new (0, 4)
	1 org/apache/commons/math3/geometry/euclidean/threed/Vector3DFormat (0, 4)
	3 dup (0, 4)
	4 aload_1 (0, 4)
	5 invokespecial (0, 4)
	6 org/apache/commons/math3/geometry/euclidean/threed/Vector3DFormat.<init>:(Ljava/text/NumberFormat;)V (0, 4)
	8 aload_0 (0, 4)
	9 invokevirtual (0, 4)
	10 org/apache/commons/math3/geometry/euclidean/threed/FieldVector3D.toVector3D:()Lorg/apache/commons/math3/geometry/euclidean/threed/Vector3D; (0, 4)
	12 invokevirtual (0, 4)
	13 org/apache/commons/math3/geometry/euclidean/threed/Vector3DFormat.format:(Lorg/apache/commons/math3/geometry/Vector;)Ljava/lang/String; (0, 4)
	15 areturn (0, 4)

