Method: <init>
	0 aload_0 (0, 0)
	1 invokespecial (0, 0)
	2 java/lang/Object.<init>:()V (0, 0)
	4 aload_0 (0, 0)
	5 aload_1 (0, 0)
	6 putfield (0, 0)
	7 org/apache/commons/math3/geometry/euclidean/threed/OutlineExtractor.u:Lorg/apache/commons/math3/geometry/euclidean/threed/Vector3D; (0, 0)
	9 aload_0 (0, 0)
	10 aload_2 (0, 0)
	11 putfield (0, 0)
	12 org/apache/commons/math3/geometry/euclidean/threed/OutlineExtractor.v:Lorg/apache/commons/math3/geometry/euclidean/threed/Vector3D; (0, 0)
	14 aload_0 (0, 0)
	15 aload_1 (0, 0)
	16 aload_2 (0, 0)
	17 invokestatic (0, 0)
	18 org/apache/commons/math3/geometry/euclidean/threed/Vector3D.crossProduct:(Lorg/apache/commons/math3/geometry/euclidean/threed/Vector3D;Lorg/apache/commons/math3/geometry/euclidean/threed/Vector3D;)Lorg/apache/commons/math3/geometry/euclidean/threed/Vector3D; (0, 0)
	20 putfield (0, 0)
	21 org/apache/commons/math3/geometry/euclidean/threed/OutlineExtractor.w:Lorg/apache/commons/math3/geometry/euclidean/threed/Vector3D; (0, 0)
	23 return (0, 0)

Method: getOutline
	0 new (0, 0)
	1 org/apache/commons/math3/geometry/euclidean/threed/OutlineExtractor$BoundaryProjector (0, 0)
	3 dup (0, 0)
	4 aload_0 (0, 0)
	5 aload_1 (0, 0)
	6 invokevirtual (0, 0)
	7 org/apache/commons/math3/geometry/euclidean/threed/PolyhedronsSet.getTolerance:()D (0, 0)
	9 invokespecial (0, 0)
	10 org/apache/commons/math3/geometry/euclidean/threed/OutlineExtractor$BoundaryProjector.<init>:(Lorg/apache/commons/math3/geometry/euclidean/threed/OutlineExtractor;D)V (0, 0)
	12 astore_2 (0, 0)
	13 aload_1 (0, 0)
	14 iconst_1 (0, 0)
	15 invokevirtual (0, 0)
	16 org/apache/commons/math3/geometry/euclidean/threed/PolyhedronsSet.getTree:(Z)Lorg/apache/commons/math3/geometry/partitioning/BSPTree; (0, 0)
	18 aload_2 (0, 0)
	19 invokevirtual (0, 0)
	20 org/apache/commons/math3/geometry/partitioning/BSPTree.visit:(Lorg/apache/commons/math3/geometry/partitioning/BSPTreeVisitor;)V (0, 0)
	22 aload_2 (0, 0)
	23 invokevirtual (0, 0)
	24 org/apache/commons/math3/geometry/euclidean/threed/OutlineExtractor$BoundaryProjector.getProjected:()Lorg/apache/commons/math3/geometry/euclidean/twod/PolygonsSet; (0, 0)
	26 astore_3 (0, 0)
	27 aload_3 (0, 0)
	28 invokevirtual (0, 0)
	29 org/apache/commons/math3/geometry/euclidean/twod/PolygonsSet.getVertices:()[[Lorg/apache/commons/math3/geometry/euclidean/twod/Vector2D; (0, 0)
	31 astore (0, 0)
	32 #4 (0, 0)
	33 iconst_0 (1, 4)
	34 istore (1, 4)
	35 #5 (1, 4)
	36 iload (1, 4)
	37 #5 (1, 4)
	38 aload (1, 4)
	39 #4 (1, 4)
	40 arraylength (1, 4)
	41 if_icmpge (1, 4)
	42 119 (1, 4)
	44 aload (1, 4)
	45 #4 (1, 4)
	46 iload (1, 4)
	47 #5 (1, 4)
	48 aaload (1, 4)
	49 astore (1, 4)
	50 #6 (1, 4)
	51 aload (1, 4)
	52 #6 (1, 4)
	53 arraylength (1, 4)
	54 istore (1, 4)
	55 #7 (1, 4)
	56 iconst_0 (1, 4)
	57 istore (1, 4)
	58 #8 (1, 4)
	59 iload (2, 3)
	60 #8 (2, 3)
	61 iload (2, 3)
	62 #7 (2, 3)
	63 if_icmpge (2, 3)
	64 59 (2, 3)
	66 aload_0 (3, 1)
	67 aload (3, 1)
	68 #6 (3, 1)
	69 iload (3, 1)
	70 #7 (3, 1)
	71 iload (3, 1)
	72 #8 (3, 1)
	73 invokespecial (3, 1)
	74 org/apache/commons/math3/geometry/euclidean/threed/OutlineExtractor.pointIsBetween:([Lorg/apache/commons/math3/geometry/euclidean/twod/Vector2D;II)Z (3, 1)
	76 ifeq (3, 1)
	77 40 (3, 1)
	79 iload (4, 4)
	80 #8 (4, 4)
	81 istore (4, 4)
	82 #9 (4, 4)
	83 iload (4, 4)
	84 #9 (4, 4)
	85 iload (4, 4)
	86 #7 (4, 4)
	87 iconst_1 (4, 4)
	88 isub (4, 4)
	89 if_icmpge (4, 4)
	90 21 (4, 4)
	92 aload (4, 4)
	93 #6 (4, 4)
	94 iload (4, 4)
	95 #9 (4, 4)
	96 aload (4, 4)
	97 #6 (4, 4)
	98 iload (4, 4)
	99 #9 (4, 4)
	100 iconst_1 (4, 4)
	101 iadd (4, 4)
	102 aaload (4, 4)
	103 aastore (4, 4)
	104 iinc (4, 4)
	105 #9 (4, 4)
	106 -89 (4, 4)
	107 goto (4, 4)
	108 -24 (4, 4)
	110 iinc (3, 1)
	111 #7 (3, 1)
	112 -89 (3, 1)
	113 goto (3, 1)
	114 -54 (3, 1)
	116 iinc (4, 2)
	117 #8 (4, 2)
	118 -89 (4, 2)
	119 goto (4, 2)
	120 -60 (4, 2)
	122 iload (2, 1)
	123 #7 (2, 1)
	124 aload (2, 1)
	125 #6 (2, 1)
	126 arraylength (2, 1)
	127 if_icmpeq (2, 1)
	128 27 (2, 1)
	130 aload (2, 1)
	131 #4 (2, 1)
	132 iload (2, 1)
	133 #5 (2, 1)
	134 iload (2, 1)
	135 #7 (2, 1)
	136 anewarray (2, 1)
	137 org/apache/commons/math3/geometry/euclidean/twod/Vector2D (2, 1)
	139 aastore (2, 1)
	140 aload (2, 1)
	141 #6 (2, 1)
	142 iconst_0 (2, 1)
	143 aload (2, 1)
	144 #4 (2, 1)
	145 iload (2, 1)
	146 #5 (2, 1)
	147 aaload (2, 1)
	148 iconst_0 (2, 1)
	149 iload (2, 1)
	150 #7 (2, 1)
	151 invokestatic (2, 1)
	152 java/lang/System.arraycopy:(Ljava/lang/Object;ILjava/lang/Object;II)V (2, 1)
	154 iinc (2, 1)
	155 #5 (2, 1)
	156 -89 (2, 1)
	157 goto (2, 1)
	158 -121 (2, 1)
	160 aload (1, 4)
	161 #4 (1, 4)
	162 areturn (1, 4)

Method: pointIsBetween
	0 aload_1 (0, 0)
	1 iload_3 (0, 0)
	2 iload_2 (0, 0)
	3 iadd (0, 0)
	4 iconst_1 (0, 0)
	5 isub (0, 0)
	6 iload_2 (0, 0)
	7 irem (0, 0)
	8 aaload (0, 0)
	9 astore (0, 0)
	10 #4 (0, 0)
	11 aload_1 (0, 0)
	12 iload_3 (0, 0)
	13 aaload (0, 0)
	14 astore (0, 0)
	15 #5 (0, 0)
	16 aload_1 (0, 0)
	17 iload_3 (0, 0)
	18 iconst_1 (0, 0)
	19 iadd (0, 0)
	20 iload_2 (0, 0)
	21 irem (0, 0)
	22 aaload (0, 0)
	23 astore (0, 0)
	24 #6 (0, 0)
	25 aload (0, 0)
	26 #5 (0, 0)
	27 invokevirtual (0, 0)
	28 org/apache/commons/math3/geometry/euclidean/twod/Vector2D.getX:()D (0, 0)
	30 aload (0, 0)
	31 #4 (0, 0)
	32 invokevirtual (0, 0)
	33 org/apache/commons/math3/geometry/euclidean/twod/Vector2D.getX:()D (0, 0)
	35 dsub (0, 0)
	36 dstore (0, 0)
	37 #7 (0, 0)
	38 aload (0, 0)
	39 #5 (0, 0)
	40 invokevirtual (0, 0)
	41 org/apache/commons/math3/geometry/euclidean/twod/Vector2D.getY:()D (0, 0)
	43 aload (0, 0)
	44 #4 (0, 0)
	45 invokevirtual (0, 0)
	46 org/apache/commons/math3/geometry/euclidean/twod/Vector2D.getY:()D (0, 0)
	48 dsub (0, 0)
	49 dstore (0, 0)
	50 #9 (0, 0)
	51 aload (0, 0)
	52 #6 (0, 0)
	53 invokevirtual (0, 0)
	54 org/apache/commons/math3/geometry/euclidean/twod/Vector2D.getX:()D (0, 0)
	56 aload (0, 0)
	57 #5 (0, 0)
	58 invokevirtual (0, 0)
	59 org/apache/commons/math3/geometry/euclidean/twod/Vector2D.getX:()D (0, 0)
	61 dsub (0, 0)
	62 dstore (0, 0)
	63 #11 (0, 0)
	64 aload (0, 0)
	65 #6 (0, 0)
	66 invokevirtual (0, 0)
	67 org/apache/commons/math3/geometry/euclidean/twod/Vector2D.getY:()D (0, 0)
	69 aload (0, 0)
	70 #5 (0, 0)
	71 invokevirtual (0, 0)
	72 org/apache/commons/math3/geometry/euclidean/twod/Vector2D.getY:()D (0, 0)
	74 dsub (0, 0)
	75 dstore (0, 0)
	76 #13 (0, 0)
	77 dload (0, 0)
	78 #7 (0, 0)
	79 dload (0, 0)
	80 #13 (0, 0)
	81 dmul (0, 0)
	82 dload (0, 0)
	83 #11 (0, 0)
	84 dload (0, 0)
	85 #9 (0, 0)
	86 dmul (0, 0)
	87 dsub (0, 0)
	88 dstore (0, 0)
	89 #15 (0, 0)
	90 dload (0, 0)
	91 #7 (0, 0)
	92 dload (0, 0)
	93 #11 (0, 0)
	94 dmul (0, 0)
	95 dload (0, 0)
	96 #9 (0, 0)
	97 dload (0, 0)
	98 #13 (0, 0)
	99 dmul (0, 0)
	100 dadd (0, 0)
	101 dstore (0, 0)
	102 #17 (0, 0)
	103 dload (0, 0)
	104 #7 (0, 0)
	105 dload (0, 0)
	106 #7 (0, 0)
	107 dmul (0, 0)
	108 dload (0, 0)
	109 #9 (0, 0)
	110 dload (0, 0)
	111 #9 (0, 0)
	112 dmul (0, 0)
	113 dadd (0, 0)
	114 dload (0, 0)
	115 #11 (0, 0)
	116 dload (0, 0)
	117 #11 (0, 0)
	118 dmul (0, 0)
	119 dload (0, 0)
	120 #13 (0, 0)
	121 dload (0, 0)
	122 #13 (0, 0)
	123 dmul (0, 0)
	124 dadd (0, 0)
	125 dmul (0, 0)
	126 invokestatic (0, 0)
	127 org/apache/commons/math3/util/FastMath.sqrt:(D)D (0, 0)
	129 dstore (0, 0)
	130 #19 (0, 0)
	131 dload (0, 0)
	132 #15 (0, 0)
	133 invokestatic (0, 0)
	134 org/apache/commons/math3/util/FastMath.abs:(D)D (0, 0)
	136 ldc2_w (0, 0)
	137 1e-06 (0, 0)
	139 dload (0, 0)
	140 #19 (0, 0)
	141 dmul (0, 0)
	142 dcmpg (0, 0)
	143 ifgt (0, 0)
	144 14 (0, 0)
	146 dload (0, 0)
	147 #17 (0, 0)
	148 dconst_0 (0, 0)
	149 dcmpl (0, 0)
	150 iflt (0, 0)
	151 7 (0, 0)
	153 iconst_1 (0, 0)
	154 goto (0, 0)
	155 4 (0, 0)
	157 iconst_0 (0, 0)
	158 ireturn (0, 0)

Method: access$000
	0 aload_0 (0, 0)
	1 getfield (0, 0)
	2 org/apache/commons/math3/geometry/euclidean/threed/OutlineExtractor.w:Lorg/apache/commons/math3/geometry/euclidean/threed/Vector3D; (0, 0)
	4 areturn (0, 0)

Method: access$100
	0 aload_0 (0, 0)
	1 getfield (0, 0)
	2 org/apache/commons/math3/geometry/euclidean/threed/OutlineExtractor.u:Lorg/apache/commons/math3/geometry/euclidean/threed/Vector3D; (0, 0)
	4 areturn (0, 0)

Method: access$200
	0 aload_0 (0, 0)
	1 getfield (0, 0)
	2 org/apache/commons/math3/geometry/euclidean/threed/OutlineExtractor.v:Lorg/apache/commons/math3/geometry/euclidean/threed/Vector3D; (0, 0)
	4 areturn (0, 0)

