Method: <init>
	0 aload_0 (0, 0)
	1 aload_1 (0, 0)
	2 putfield (0, 0)
	3 org/apache/commons/math3/geometry/euclidean/threed/OutlineExtractor$BoundaryProjector.this$0:Lorg/apache/commons/math3/geometry/euclidean/threed/OutlineExtractor; (0, 0)
	5 aload_0 (0, 0)
	6 invokespecial (0, 0)
	7 java/lang/Object.<init>:()V (0, 0)
	9 aload_0 (0, 0)
	10 new (0, 0)
	11 org/apache/commons/math3/geometry/euclidean/twod/PolygonsSet (0, 0)
	13 dup (0, 0)
	14 new (0, 0)
	15 org/apache/commons/math3/geometry/partitioning/BSPTree (0, 0)
	17 dup (0, 0)
	18 getstatic (0, 0)
	19 java/lang/Boolean.FALSE:Ljava/lang/Boolean; (0, 0)
	21 invokespecial (0, 0)
	22 org/apache/commons/math3/geometry/partitioning/BSPTree.<init>:(Ljava/lang/Object;)V (0, 0)
	24 dload_2 (0, 0)
	25 invokespecial (0, 0)
	26 org/apache/commons/math3/geometry/euclidean/twod/PolygonsSet.<init>:(Lorg/apache/commons/math3/geometry/partitioning/BSPTree;D)V (0, 0)
	28 putfield (0, 0)
	29 org/apache/commons/math3/geometry/euclidean/threed/OutlineExtractor$BoundaryProjector.projected:Lorg/apache/commons/math3/geometry/euclidean/twod/PolygonsSet; (0, 0)
	31 aload_0 (0, 0)
	32 dload_2 (0, 0)
	33 putfield (0, 0)
	34 org/apache/commons/math3/geometry/euclidean/threed/OutlineExtractor$BoundaryProjector.tolerance:D (0, 0)
	36 return (0, 0)

Method: visitOrder
	0 getstatic (0, 0)
	1 org/apache/commons/math3/geometry/partitioning/BSPTreeVisitor$Order.MINUS_SUB_PLUS:Lorg/apache/commons/math3/geometry/partitioning/BSPTreeVisitor$Order; (0, 0)
	3 areturn (0, 0)

Method: visitInternalNode
	0 aload_1 (0, 0)
	1 invokevirtual (0, 0)
	2 org/apache/commons/math3/geometry/partitioning/BSPTree.getAttribute:()Ljava/lang/Object; (0, 0)
	4 checkcast (0, 0)
	5 org/apache/commons/math3/geometry/partitioning/BoundaryAttribute (0, 0)
	7 astore_2 (0, 0)
	8 aload_2 (1, 1)
	9 invokevirtual (1, 1)
	10 org/apache/commons/math3/geometry/partitioning/BoundaryAttribute.getPlusOutside:()Lorg/apache/commons/math3/geometry/partitioning/SubHyperplane; (1, 1)
	12 ifnull (1, 1)
	13 12 (1, 1)
	15 aload_0 (1, 1)
	16 aload_2 (1, 1)
	17 invokevirtual (1, 1)
	18 org/apache/commons/math3/geometry/partitioning/BoundaryAttribute.getPlusOutside:()Lorg/apache/commons/math3/geometry/partitioning/SubHyperplane; (1, 1)
	20 iconst_0 (1, 1)
	21 invokespecial (1, 1)
	22 org/apache/commons/math3/geometry/euclidean/threed/OutlineExtractor$BoundaryProjector.addContribution:(Lorg/apache/commons/math3/geometry/partitioning/SubHyperplane;Z)V (1, 1)
	24 aload_2 (1, 1)
	25 invokevirtual (1, 1)
	26 org/apache/commons/math3/geometry/partitioning/BoundaryAttribute.getPlusInside:()Lorg/apache/commons/math3/geometry/partitioning/SubHyperplane; (1, 1)
	28 ifnull (1, 1)
	29 12 (1, 1)
	31 aload_0 (1, 1)
	32 aload_2 (1, 1)
	33 invokevirtual (1, 1)
	34 org/apache/commons/math3/geometry/partitioning/BoundaryAttribute.getPlusInside:()Lorg/apache/commons/math3/geometry/partitioning/SubHyperplane; (1, 1)
	36 iconst_1 (1, 1)
	37 invokespecial (1, 1)
	38 org/apache/commons/math3/geometry/euclidean/threed/OutlineExtractor$BoundaryProjector.addContribution:(Lorg/apache/commons/math3/geometry/partitioning/SubHyperplane;Z)V (1, 1)
	40 return (0, 0)

Method: visitLeafNode
	0 return (0, 0)

Method: addContribution
	0 aload_1 (0, 0)
	1 checkcast (0, 0)
	2 org/apache/commons/math3/geometry/partitioning/AbstractSubHyperplane (0, 0)
	4 astore_3 (0, 0)
	5 aload_1 (0, 0)
	6 invokeinterface (0, 0)
	7 org/apache/commons/math3/geometry/partitioning/SubHyperplane.org/apache/commons/math3/geometry/euclidean/threed/Plane (0, 0)
	9 0 (0, 0)
	11 checkcast (0, 0)
	12 org/apache/commons/math3/geometry/euclidean/threed/Plane (0, 0)
	14 astore (0, 0)
	15 #4 (0, 0)
	16 aload (0, 0)
	17 #4 (0, 0)
	18 invokevirtual (0, 0)
	19 org/apache/commons/math3/geometry/euclidean/threed/Plane.getNormal:()Lorg/apache/commons/math3/geometry/euclidean/threed/Vector3D; (0, 0)
	21 aload_0 (0, 0)
	22 getfield (0, 0)
	23 org/apache/commons/math3/geometry/euclidean/threed/OutlineExtractor$BoundaryProjector.this$0:Lorg/apache/commons/math3/geometry/euclidean/threed/OutlineExtractor; (0, 0)
	25 invokestatic (0, 0)
	26 org/apache/commons/math3/geometry/euclidean/threed/OutlineExtractor.access$000:(Lorg/apache/commons/math3/geometry/euclidean/threed/OutlineExtractor;)Lorg/apache/commons/math3/geometry/euclidean/threed/Vector3D; (0, 0)
	28 invokevirtual (0, 0)
	29 org/apache/commons/math3/geometry/euclidean/threed/Vector3D.dotProduct:(Lorg/apache/commons/math3/geometry/Vector;)D (0, 0)
	31 dstore (0, 0)
	32 #5 (0, 0)
	33 dload (1, 1)
	34 #5 (1, 1)
	35 invokestatic (1, 1)
	36 org/apache/commons/math3/util/FastMath.abs:(D)D (1, 1)
	38 ldc2_w (1, 1)
	39 0.001 (1, 1)
	41 dcmpl (1, 1)
	42 ifle (1, 1)
	43 539 (1, 1)
	45 aload_3 (1, 1)
	46 invokevirtual (1, 1)
	47 org/apache/commons/math3/geometry/partitioning/AbstractSubHyperplane.getRemainingRegion:()Lorg/apache/commons/math3/geometry/partitioning/Region; (1, 1)
	49 checkcast (1, 1)
	50 org/apache/commons/math3/geometry/euclidean/twod/PolygonsSet (1, 1)
	52 invokevirtual (1, 1)
	53 org/apache/commons/math3/geometry/euclidean/twod/PolygonsSet.getVertices:()[[Lorg/apache/commons/math3/geometry/euclidean/twod/Vector2D; (1, 1)
	55 astore (1, 1)
	56 #7 (1, 1)
	57 dload (2, 1)
	58 #5 (2, 1)
	59 dconst_0 (2, 1)
	60 dcmpg (2, 1)
	61 ifge (2, 1)
	62 7 (2, 1)
	64 iconst_1 (2, 1)
	65 goto (2, 1)
	66 4 (2, 1)
	68 iconst_0 (2, 1)
	69 iload_2 (2, 1)
	70 ixor (2, 1)
	71 ifeq (2, 1)
	72 133 (2, 1)
	74 aload (2, 1)
	75 #7 (2, 1)
	76 arraylength (2, 1)
	77 anewarray (2, 1)
	78 [Lorg/apache/commons/math3/geometry/euclidean/twod/Vector2D; (2, 1)
	80 astore (2, 1)
	81 #8 (2, 1)
	82 iconst_0 (3, 4)
	83 istore (3, 4)
	84 #9 (3, 4)
	85 iload (3, 4)
	86 #9 (3, 4)
	87 aload (3, 4)
	88 #7 (3, 4)
	89 arraylength (3, 4)
	90 if_icmpge (3, 4)
	91 110 (3, 4)
	93 aload (3, 4)
	94 #7 (3, 4)
	95 iload (3, 4)
	96 #9 (3, 4)
	97 aaload (3, 4)
	98 astore (3, 4)
	99 #10 (3, 4)
	100 aload (3, 4)
	101 #10 (3, 4)
	102 arraylength (3, 4)
	103 anewarray (3, 4)
	104 org/apache/commons/math3/geometry/euclidean/twod/Vector2D (3, 4)
	106 astore (3, 4)
	107 #11 (3, 4)
	108 aload (4, 1)
	109 #10 (4, 1)
	110 iconst_0 (4, 1)
	111 aaload (4, 1)
	112 ifnonnull (4, 1)
	113 42 (4, 1)
	115 aload (4, 1)
	116 #11 (4, 1)
	117 iconst_0 (4, 1)
	118 aconst_null (4, 1)
	119 aastore (4, 1)
	120 iconst_1 (5, 4)
	121 istore (5, 4)
	122 #12 (5, 4)
	123 iload (5, 4)
	124 #12 (5, 4)
	125 aload (5, 4)
	126 #10 (5, 4)
	127 arraylength (5, 4)
	128 if_icmpge (5, 4)
	129 23 (5, 4)
	131 aload (5, 4)
	132 #11 (5, 4)
	133 iload (5, 4)
	134 #12 (5, 4)
	135 aload (5, 4)
	136 #10 (5, 4)
	137 aload (5, 4)
	138 #10 (5, 4)
	139 arraylength (5, 4)
	140 iload (5, 4)
	141 #12 (5, 4)
	142 isub (5, 4)
	143 aaload (5, 4)
	144 aastore (5, 4)
	145 iinc (5, 4)
	146 #12 (5, 4)
	147 -89 (5, 4)
	148 goto (5, 4)
	149 -25 (5, 4)
	151 goto (5, 4)
	152 36 (5, 4)
	154 iconst_0 (6, 4)
	155 istore (6, 4)
	156 #12 (6, 4)
	157 iload (6, 4)
	158 #12 (6, 4)
	159 aload (6, 4)
	160 #10 (6, 4)
	161 arraylength (6, 4)
	162 if_icmpge (6, 4)
	163 25 (6, 4)
	165 aload (6, 4)
	166 #11 (6, 4)
	167 iload (6, 4)
	168 #12 (6, 4)
	169 aload (6, 4)
	170 #10 (6, 4)
	171 aload (6, 4)
	172 #10 (6, 4)
	173 arraylength (6, 4)
	174 iload (6, 4)
	175 #12 (6, 4)
	176 iconst_1 (6, 4)
	177 iadd (6, 4)
	178 isub (6, 4)
	179 aaload (6, 4)
	180 aastore (6, 4)
	181 iinc (6, 4)
	182 #12 (6, 4)
	183 -89 (6, 4)
	184 goto (6, 4)
	185 -27 (6, 4)
	187 aload (3, 4)
	188 #8 (3, 4)
	189 iload (3, 4)
	190 #9 (3, 4)
	191 aload (3, 4)
	192 #11 (3, 4)
	193 aastore (3, 4)
	194 iinc (3, 4)
	195 #9 (3, 4)
	196 -89 (3, 4)
	197 goto (3, 4)
	198 -112 (3, 4)
	200 aload (2, 1)
	201 #8 (2, 1)
	202 astore (2, 1)
	203 #7 (2, 1)
	204 new (1, 1)
	205 java/util/ArrayList (1, 1)
	207 dup (1, 1)
	208 invokespecial (1, 1)
	209 java/util/ArrayList.<init>:()V (1, 1)
	211 astore (1, 1)
	212 #8 (1, 1)
	213 aload (2, 4)
	214 #7 (2, 4)
	215 astore (2, 4)
	216 #9 (2, 4)
	217 aload (2, 4)
	218 #9 (2, 4)
	219 arraylength (2, 4)
	220 istore (2, 4)
	221 #10 (2, 4)
	222 iconst_0 (2, 4)
	223 istore (2, 4)
	224 #11 (2, 4)
	225 iload (2, 4)
	226 #11 (2, 4)
	227 iload (2, 4)
	228 #10 (2, 4)
	229 if_icmpge (2, 4)
	230 314 (2, 4)
	232 aload (2, 4)
	233 #9 (2, 4)
	234 iload (2, 4)
	235 #11 (2, 4)
	236 aaload (2, 4)
	237 astore (2, 4)
	238 #12 (2, 4)
	239 aload (2, 4)
	240 #12 (2, 4)
	241 iconst_0 (2, 4)
	242 aaload (2, 4)
	243 ifnull (2, 4)
	244 7 (2, 4)
	246 iconst_1 (2, 4)
	247 goto (2, 4)
	248 4 (2, 4)
	250 iconst_0 (2, 4)
	251 istore (2, 4)
	252 #13 (2, 4)
	253 iload (2, 4)
	254 #13 (2, 4)
	255 ifeq (2, 4)
	256 11 (2, 4)
	258 aload (2, 4)
	259 #12 (2, 4)
	260 arraylength (2, 4)
	261 iconst_1 (2, 4)
	262 isub (2, 4)
	263 goto (2, 4)
	264 4 (2, 4)
	266 iconst_1 (2, 4)
	267 istore (2, 4)
	268 #14 (2, 4)
	269 aload (2, 4)
	270 #4 (2, 4)
	271 aload (2, 4)
	272 #12 (2, 4)
	273 iload (2, 4)
	274 #14 (2, 4)
	275 aaload (2, 4)
	276 invokevirtual (2, 4)
	277 org/apache/commons/math3/geometry/euclidean/threed/Plane.toSpace:(Lorg/apache/commons/math3/geometry/Point;)Lorg/apache/commons/math3/geometry/euclidean/threed/Vector3D; (2, 4)
	279 astore (2, 4)
	280 #15 (2, 4)
	281 iload (2, 4)
	282 #14 (2, 4)
	283 iconst_1 (2, 4)
	284 iadd (2, 4)
	285 aload (2, 4)
	286 #12 (2, 4)
	287 arraylength (2, 4)
	288 irem (2, 4)
	289 istore (2, 4)
	290 #16 (2, 4)
	291 new (2, 4)
	292 org/apache/commons/math3/geometry/euclidean/twod/Vector2D (2, 4)
	294 dup (2, 4)
	295 aload (2, 4)
	296 #15 (2, 4)
	297 aload_0 (2, 4)
	298 getfield (2, 4)
	299 org/apache/commons/math3/geometry/euclidean/threed/OutlineExtractor$BoundaryProjector.this$0:Lorg/apache/commons/math3/geometry/euclidean/threed/OutlineExtractor; (2, 4)
	301 invokestatic (2, 4)
	302 org/apache/commons/math3/geometry/euclidean/threed/OutlineExtractor.access$100:(Lorg/apache/commons/math3/geometry/euclidean/threed/OutlineExtractor;)Lorg/apache/commons/math3/geometry/euclidean/threed/Vector3D; (2, 4)
	304 invokevirtual (2, 4)
	305 org/apache/commons/math3/geometry/euclidean/threed/Vector3D.dotProduct:(Lorg/apache/commons/math3/geometry/Vector;)D (2, 4)
	307 aload (2, 4)
	308 #15 (2, 4)
	309 aload_0 (2, 4)
	310 getfield (2, 4)
	311 org/apache/commons/math3/geometry/euclidean/threed/OutlineExtractor$BoundaryProjector.this$0:Lorg/apache/commons/math3/geometry/euclidean/threed/OutlineExtractor; (2, 4)
	313 invokestatic (2, 4)
	314 org/apache/commons/math3/geometry/euclidean/threed/OutlineExtractor.access$200:(Lorg/apache/commons/math3/geometry/euclidean/threed/OutlineExtractor;)Lorg/apache/commons/math3/geometry/euclidean/threed/Vector3D; (2, 4)
	316 invokevirtual (2, 4)
	317 org/apache/commons/math3/geometry/euclidean/threed/Vector3D.dotProduct:(Lorg/apache/commons/math3/geometry/Vector;)D (2, 4)
	319 invokespecial (2, 4)
	320 org/apache/commons/math3/geometry/euclidean/twod/Vector2D.<init>:(DD)V (2, 4)
	322 astore (2, 4)
	323 #17 (2, 4)
	324 iload (3, 3)
	325 #16 (3, 3)
	326 aload (3, 3)
	327 #12 (3, 3)
	328 arraylength (3, 3)
	329 if_icmpge (3, 3)
	330 208 (3, 3)
	332 aload (3, 3)
	333 #4 (3, 3)
	334 aload (3, 3)
	335 #12 (3, 3)
	336 iload (3, 3)
	337 #16 (3, 3)
	338 aaload (3, 3)
	339 invokevirtual (3, 3)
	340 org/apache/commons/math3/geometry/euclidean/threed/Plane.toSpace:(Lorg/apache/commons/math3/geometry/Point;)Lorg/apache/commons/math3/geometry/euclidean/threed/Vector3D; (3, 3)
	342 astore (3, 3)
	343 #18 (3, 3)
	344 new (3, 3)
	345 org/apache/commons/math3/geometry/euclidean/twod/Vector2D (3, 3)
	347 dup (3, 3)
	348 aload (3, 3)
	349 #18 (3, 3)
	350 aload_0 (3, 3)
	351 getfield (3, 3)
	352 org/apache/commons/math3/geometry/euclidean/threed/OutlineExtractor$BoundaryProjector.this$0:Lorg/apache/commons/math3/geometry/euclidean/threed/OutlineExtractor; (3, 3)
	354 invokestatic (3, 3)
	355 org/apache/commons/math3/geometry/euclidean/threed/OutlineExtractor.access$100:(Lorg/apache/commons/math3/geometry/euclidean/threed/OutlineExtractor;)Lorg/apache/commons/math3/geometry/euclidean/threed/Vector3D; (3, 3)
	357 invokevirtual (3, 3)
	358 org/apache/commons/math3/geometry/euclidean/threed/Vector3D.dotProduct:(Lorg/apache/commons/math3/geometry/Vector;)D (3, 3)
	360 aload (3, 3)
	361 #18 (3, 3)
	362 aload_0 (3, 3)
	363 getfield (3, 3)
	364 org/apache/commons/math3/geometry/euclidean/threed/OutlineExtractor$BoundaryProjector.this$0:Lorg/apache/commons/math3/geometry/euclidean/threed/OutlineExtractor; (3, 3)
	366 invokestatic (3, 3)
	367 org/apache/commons/math3/geometry/euclidean/threed/OutlineExtractor.access$200:(Lorg/apache/commons/math3/geometry/euclidean/threed/OutlineExtractor;)Lorg/apache/commons/math3/geometry/euclidean/threed/Vector3D; (3, 3)
	369 invokevirtual (3, 3)
	370 org/apache/commons/math3/geometry/euclidean/threed/Vector3D.dotProduct:(Lorg/apache/commons/math3/geometry/Vector;)D (3, 3)
	372 invokespecial (3, 3)
	373 org/apache/commons/math3/geometry/euclidean/twod/Vector2D.<init>:(DD)V (3, 3)
	375 astore (3, 3)
	376 #19 (3, 3)
	377 new (3, 3)
	378 org/apache/commons/math3/geometry/euclidean/twod/Line (3, 3)
	380 dup (3, 3)
	381 aload (3, 3)
	382 #17 (3, 3)
	383 aload (3, 3)
	384 #19 (3, 3)
	385 aload_0 (3, 3)
	386 getfield (3, 3)
	387 org/apache/commons/math3/geometry/euclidean/threed/OutlineExtractor$BoundaryProjector.tolerance:D (3, 3)
	389 invokespecial (3, 3)
	390 org/apache/commons/math3/geometry/euclidean/twod/Line.<init>:(Lorg/apache/commons/math3/geometry/euclidean/twod/Vector2D;Lorg/apache/commons/math3/geometry/euclidean/twod/Vector2D;D)V (3, 3)
	392 astore (3, 3)
	393 #20 (3, 3)
	394 aload (3, 3)
	395 #20 (3, 3)
	396 invokevirtual (3, 3)
	397 org/apache/commons/math3/geometry/euclidean/twod/Line.wholeHyperplane:()Lorg/apache/commons/math3/geometry/euclidean/twod/SubLine; (3, 3)
	399 astore (3, 3)
	400 #21 (3, 3)
	401 iload (4, 1)
	402 #13 (4, 1)
	403 ifne (4, 1)
	404 9 (4, 1)
	406 iload (4, 1)
	407 #14 (4, 1)
	408 iconst_1 (4, 1)
	409 if_icmpeq (4, 1)
	410 45 (4, 1)
	412 aload (4, 1)
	413 #20 (4, 1)
	414 invokevirtual (4, 1)
	415 org/apache/commons/math3/geometry/euclidean/twod/Line.getAngle:()D (4, 1)
	417 ldc2_w (4, 1)
	418 1.5707963267948966 (4, 1)
	420 dadd (4, 1)
	421 dstore (4, 1)
	422 #22 (4, 1)
	423 new (4, 1)
	424 org/apache/commons/math3/geometry/euclidean/twod/Line (4, 1)
	426 dup (4, 1)
	427 aload (4, 1)
	428 #17 (4, 1)
	429 dload (4, 1)
	430 #22 (4, 1)
	431 aload_0 (4, 1)
	432 getfield (4, 1)
	433 org/apache/commons/math3/geometry/euclidean/threed/OutlineExtractor$BoundaryProjector.tolerance:D (4, 1)
	435 invokespecial (4, 1)
	436 org/apache/commons/math3/geometry/euclidean/twod/Line.<init>:(Lorg/apache/commons/math3/geometry/euclidean/twod/Vector2D;DD)V (4, 1)
	438 astore (4, 1)
	439 #24 (4, 1)
	440 aload (4, 1)
	441 #21 (4, 1)
	442 aload (4, 1)
	443 #24 (4, 1)
	444 invokeinterface (4, 1)
	445 org/apache/commons/math3/geometry/partitioning/SubHyperplane.org/apache/commons/math3/geometry/partitioning/SubHyperplane$SplitSubHyperplane (4, 1)
	447 0 (4, 1)
	449 invokevirtual (4, 1)
	450 org/apache/commons/math3/geometry/partitioning/SubHyperplane$SplitSubHyperplane.getPlus:()Lorg/apache/commons/math3/geometry/partitioning/SubHyperplane; (4, 1)
	452 astore (4, 1)
	453 #21 (4, 1)
	454 iload (4, 1)
	455 #13 (4, 1)
	456 ifne (4, 1)
	457 13 (4, 1)
	459 iload (4, 1)
	460 #16 (4, 1)
	461 aload (4, 1)
	462 #12 (4, 1)
	463 arraylength (4, 1)
	464 iconst_1 (4, 1)
	465 isub (4, 1)
	466 if_icmpeq (4, 1)
	467 45 (4, 1)
	469 aload (4, 1)
	470 #20 (4, 1)
	471 invokevirtual (4, 1)
	472 org/apache/commons/math3/geometry/euclidean/twod/Line.getAngle:()D (4, 1)
	474 ldc2_w (4, 1)
	475 1.5707963267948966 (4, 1)
	477 dadd (4, 1)
	478 dstore (4, 1)
	479 #22 (4, 1)
	480 new (4, 1)
	481 org/apache/commons/math3/geometry/euclidean/twod/Line (4, 1)
	483 dup (4, 1)
	484 aload (4, 1)
	485 #19 (4, 1)
	486 dload (4, 1)
	487 #22 (4, 1)
	488 aload_0 (4, 1)
	489 getfield (4, 1)
	490 org/apache/commons/math3/geometry/euclidean/threed/OutlineExtractor$BoundaryProjector.tolerance:D (4, 1)
	492 invokespecial (4, 1)
	493 org/apache/commons/math3/geometry/euclidean/twod/Line.<init>:(Lorg/apache/commons/math3/geometry/euclidean/twod/Vector2D;DD)V (4, 1)
	495 astore (4, 1)
	496 #24 (4, 1)
	497 aload (4, 1)
	498 #21 (4, 1)
	499 aload (4, 1)
	500 #24 (4, 1)
	501 invokeinterface (4, 1)
	502 org/apache/commons/math3/geometry/partitioning/SubHyperplane.org/apache/commons/math3/geometry/partitioning/SubHyperplane$SplitSubHyperplane (4, 1)
	504 0 (4, 1)
	506 invokevirtual (4, 1)
	507 org/apache/commons/math3/geometry/partitioning/SubHyperplane$SplitSubHyperplane.getMinus:()Lorg/apache/commons/math3/geometry/partitioning/SubHyperplane; (4, 1)
	509 astore (4, 1)
	510 #21 (4, 1)
	511 aload (3, 3)
	512 #8 (3, 3)
	513 aload (3, 3)
	514 #21 (3, 3)
	515 invokevirtual (3, 3)
	516 java/util/ArrayList.add:(Ljava/lang/Object;)Z (3, 3)
	518 pop (3, 3)
	519 iload (3, 3)
	520 #16 (3, 3)
	521 iinc (3, 3)
	522 #16 (3, 3)
	523 54 (3, 3)
	524 istore (3, 3)
	525 #14 (3, 3)
	526 aload (3, 3)
	527 #18 (3, 3)
	528 astore (3, 3)
	529 #15 (3, 3)
	530 aload (3, 3)
	531 #19 (3, 3)
	532 astore (3, 3)
	533 #17 (3, 3)
	534 goto (2, 4)
	535 -210 (2, 4)
	537 iinc (2, 4)
	538 #11 (2, 4)
	539 -89 (2, 4)
	540 goto (2, 4)
	541 -315 (2, 4)
	543 new (1, 1)
	544 org/apache/commons/math3/geometry/euclidean/twod/PolygonsSet (1, 1)
	546 dup (1, 1)
	547 aload (1, 1)
	548 #8 (1, 1)
	549 aload_0 (1, 1)
	550 getfield (1, 1)
	551 org/apache/commons/math3/geometry/euclidean/threed/OutlineExtractor$BoundaryProjector.tolerance:D (1, 1)
	553 invokespecial (1, 1)
	554 org/apache/commons/math3/geometry/euclidean/twod/PolygonsSet.<init>:(Ljava/util/Collection;D)V (1, 1)
	556 astore (1, 1)
	557 #9 (1, 1)
	558 aload_0 (1, 1)
	559 new (1, 1)
	560 org/apache/commons/math3/geometry/partitioning/RegionFactory (1, 1)
	562 dup (1, 1)
	563 invokespecial (1, 1)
	564 org/apache/commons/math3/geometry/partitioning/RegionFactory.<init>:()V (1, 1)
	566 aload_0 (1, 1)
	567 getfield (1, 1)
	568 org/apache/commons/math3/geometry/euclidean/threed/OutlineExtractor$BoundaryProjector.projected:Lorg/apache/commons/math3/geometry/euclidean/twod/PolygonsSet; (1, 1)
	570 aload (1, 1)
	571 #9 (1, 1)
	572 invokevirtual (1, 1)
	573 org/apache/commons/math3/geometry/partitioning/RegionFactory.union:(Lorg/apache/commons/math3/geometry/partitioning/Region;Lorg/apache/commons/math3/geometry/partitioning/Region;)Lorg/apache/commons/math3/geometry/partitioning/Region; (1, 1)
	575 checkcast (1, 1)
	576 org/apache/commons/math3/geometry/euclidean/twod/PolygonsSet (1, 1)
	578 putfield (1, 1)
	579 org/apache/commons/math3/geometry/euclidean/threed/OutlineExtractor$BoundaryProjector.projected:Lorg/apache/commons/math3/geometry/euclidean/twod/PolygonsSet; (1, 1)
	581 return (0, 0)

Method: getProjected
	0 aload_0 (0, 0)
	1 getfield (0, 0)
	2 org/apache/commons/math3/geometry/euclidean/threed/OutlineExtractor$BoundaryProjector.projected:Lorg/apache/commons/math3/geometry/euclidean/twod/PolygonsSet; (0, 0)
	4 areturn (0, 0)

