Method: <init>
	0 aload_0 (0, 0)
	1 invokespecial (0, 0)
	2 java/lang/Object.<init>:()V (0, 0)
	4 aload_0 (0, 0)
	5 aload_1 (0, 0)
	6 getfield (0, 0)
	7 org/apache/commons/math3/geometry/euclidean/threed/Plane.originOffset:D (0, 0)
	9 putfield (0, 0)
	10 org/apache/commons/math3/geometry/euclidean/threed/Plane.originOffset:D (0, 0)
	12 aload_0 (0, 0)
	13 aload_1 (0, 0)
	14 getfield (0, 0)
	15 org/apache/commons/math3/geometry/euclidean/threed/Plane.origin:Lorg/apache/commons/math3/geometry/euclidean/threed/Vector3D; (0, 0)
	17 putfield (0, 0)
	18 org/apache/commons/math3/geometry/euclidean/threed/Plane.origin:Lorg/apache/commons/math3/geometry/euclidean/threed/Vector3D; (0, 0)
	20 aload_0 (0, 0)
	21 aload_1 (0, 0)
	22 getfield (0, 0)
	23 org/apache/commons/math3/geometry/euclidean/threed/Plane.u:Lorg/apache/commons/math3/geometry/euclidean/threed/Vector3D; (0, 0)
	25 putfield (0, 0)
	26 org/apache/commons/math3/geometry/euclidean/threed/Plane.u:Lorg/apache/commons/math3/geometry/euclidean/threed/Vector3D; (0, 0)
	28 aload_0 (0, 0)
	29 aload_1 (0, 0)
	30 getfield (0, 0)
	31 org/apache/commons/math3/geometry/euclidean/threed/Plane.v:Lorg/apache/commons/math3/geometry/euclidean/threed/Vector3D; (0, 0)
	33 putfield (0, 0)
	34 org/apache/commons/math3/geometry/euclidean/threed/Plane.v:Lorg/apache/commons/math3/geometry/euclidean/threed/Vector3D; (0, 0)
	36 aload_0 (0, 0)
	37 aload_1 (0, 0)
	38 getfield (0, 0)
	39 org/apache/commons/math3/geometry/euclidean/threed/Plane.w:Lorg/apache/commons/math3/geometry/euclidean/threed/Vector3D; (0, 0)
	41 putfield (0, 0)
	42 org/apache/commons/math3/geometry/euclidean/threed/Plane.w:Lorg/apache/commons/math3/geometry/euclidean/threed/Vector3D; (0, 0)
	44 aload_0 (0, 0)
	45 aload_1 (0, 0)
	46 getfield (0, 0)
	47 org/apache/commons/math3/geometry/euclidean/threed/Plane.tolerance:D (0, 0)
	49 putfield (0, 0)
	50 org/apache/commons/math3/geometry/euclidean/threed/Plane.tolerance:D (0, 0)
	52 return (0, 0)

Method: copySelf
	0 aload_0 (0, 0)
	1 invokevirtual (0, 0)
	2 org/apache/commons/math3/geometry/euclidean/threed/Plane.copySelf:()Lorg/apache/commons/math3/geometry/euclidean/threed/Plane; (0, 0)
	4 areturn (0, 0)

Method: reset
	0 aload_0 (0, 0)
	1 aload_1 (0, 0)
	2 getfield (0, 0)
	3 org/apache/commons/math3/geometry/euclidean/threed/Plane.originOffset:D (0, 0)
	5 putfield (0, 0)
	6 org/apache/commons/math3/geometry/euclidean/threed/Plane.originOffset:D (0, 0)
	8 aload_0 (0, 0)
	9 aload_1 (0, 0)
	10 getfield (0, 0)
	11 org/apache/commons/math3/geometry/euclidean/threed/Plane.origin:Lorg/apache/commons/math3/geometry/euclidean/threed/Vector3D; (0, 0)
	13 putfield (0, 0)
	14 org/apache/commons/math3/geometry/euclidean/threed/Plane.origin:Lorg/apache/commons/math3/geometry/euclidean/threed/Vector3D; (0, 0)
	16 aload_0 (0, 0)
	17 aload_1 (0, 0)
	18 getfield (0, 0)
	19 org/apache/commons/math3/geometry/euclidean/threed/Plane.u:Lorg/apache/commons/math3/geometry/euclidean/threed/Vector3D; (0, 0)
	21 putfield (0, 0)
	22 org/apache/commons/math3/geometry/euclidean/threed/Plane.u:Lorg/apache/commons/math3/geometry/euclidean/threed/Vector3D; (0, 0)
	24 aload_0 (0, 0)
	25 aload_1 (0, 0)
	26 getfield (0, 0)
	27 org/apache/commons/math3/geometry/euclidean/threed/Plane.v:Lorg/apache/commons/math3/geometry/euclidean/threed/Vector3D; (0, 0)
	29 putfield (0, 0)
	30 org/apache/commons/math3/geometry/euclidean/threed/Plane.v:Lorg/apache/commons/math3/geometry/euclidean/threed/Vector3D; (0, 0)
	32 aload_0 (0, 0)
	33 aload_1 (0, 0)
	34 getfield (0, 0)
	35 org/apache/commons/math3/geometry/euclidean/threed/Plane.w:Lorg/apache/commons/math3/geometry/euclidean/threed/Vector3D; (0, 0)
	37 putfield (0, 0)
	38 org/apache/commons/math3/geometry/euclidean/threed/Plane.w:Lorg/apache/commons/math3/geometry/euclidean/threed/Vector3D; (0, 0)
	40 return (0, 0)

Method: setNormal
	0 aload_1 (0, 0)
	1 invokevirtual (0, 0)
	2 org/apache/commons/math3/geometry/euclidean/threed/Vector3D.getNorm:()D (0, 0)
	4 dstore_2 (0, 0)
	5 dload_2 (1, 1)
	6 ldc2_w (1, 1)
	7 1e-10 (1, 1)
	9 dcmpg (1, 1)
	10 ifge (1, 1)
	11 18 (1, 1)
	13 new (1, 1)
	14 org/apache/commons/math3/exception/MathArithmeticException (1, 1)
	16 dup (1, 1)
	17 getstatic (1, 1)
	18 org/apache/commons/math3/exception/util/LocalizedFormats.ZERO_NORM:Lorg/apache/commons/math3/exception/util/LocalizedFormats; (1, 1)
	20 iconst_0 (1, 1)
	21 anewarray (1, 1)
	22 java/lang/Object (1, 1)
	24 invokespecial (1, 1)
	25 org/apache/commons/math3/exception/MathArithmeticException.<init>:(Lorg/apache/commons/math3/exception/util/Localizable;[Ljava/lang/Object;)V (1, 1)
	27 athrow (1, 1)
	28 aload_0 (0, 0)
	29 new (0, 0)
	30 org/apache/commons/math3/geometry/euclidean/threed/Vector3D (0, 0)
	32 dup (0, 0)
	33 dconst_1 (0, 0)
	34 dload_2 (0, 0)
	35 ddiv (0, 0)
	36 aload_1 (0, 0)
	37 invokespecial (0, 0)
	38 org/apache/commons/math3/geometry/euclidean/threed/Vector3D.<init>:(DLorg/apache/commons/math3/geometry/euclidean/threed/Vector3D;)V (0, 0)
	40 putfield (0, 0)
	41 org/apache/commons/math3/geometry/euclidean/threed/Plane.w:Lorg/apache/commons/math3/geometry/euclidean/threed/Vector3D; (0, 0)
	43 return (0, 0)

Method: setFrame
	0 aload_0 (0, 0)
	1 new (0, 0)
	2 org/apache/commons/math3/geometry/euclidean/threed/Vector3D (0, 0)
	4 dup (0, 0)
	5 aload_0 (0, 0)
	6 getfield (0, 0)
	7 org/apache/commons/math3/geometry/euclidean/threed/Plane.originOffset:D (0, 0)
	9 dneg (0, 0)
	10 aload_0 (0, 0)
	11 getfield (0, 0)
	12 org/apache/commons/math3/geometry/euclidean/threed/Plane.w:Lorg/apache/commons/math3/geometry/euclidean/threed/Vector3D; (0, 0)
	14 invokespecial (0, 0)
	15 org/apache/commons/math3/geometry/euclidean/threed/Vector3D.<init>:(DLorg/apache/commons/math3/geometry/euclidean/threed/Vector3D;)V (0, 0)
	17 putfield (0, 0)
	18 org/apache/commons/math3/geometry/euclidean/threed/Plane.origin:Lorg/apache/commons/math3/geometry/euclidean/threed/Vector3D; (0, 0)
	20 aload_0 (0, 0)
	21 aload_0 (0, 0)
	22 getfield (0, 0)
	23 org/apache/commons/math3/geometry/euclidean/threed/Plane.w:Lorg/apache/commons/math3/geometry/euclidean/threed/Vector3D; (0, 0)
	25 invokevirtual (0, 0)
	26 org/apache/commons/math3/geometry/euclidean/threed/Vector3D.orthogonal:()Lorg/apache/commons/math3/geometry/euclidean/threed/Vector3D; (0, 0)
	28 putfield (0, 0)
	29 org/apache/commons/math3/geometry/euclidean/threed/Plane.u:Lorg/apache/commons/math3/geometry/euclidean/threed/Vector3D; (0, 0)
	31 aload_0 (0, 0)
	32 aload_0 (0, 0)
	33 getfield (0, 0)
	34 org/apache/commons/math3/geometry/euclidean/threed/Plane.w:Lorg/apache/commons/math3/geometry/euclidean/threed/Vector3D; (0, 0)
	36 aload_0 (0, 0)
	37 getfield (0, 0)
	38 org/apache/commons/math3/geometry/euclidean/threed/Plane.u:Lorg/apache/commons/math3/geometry/euclidean/threed/Vector3D; (0, 0)
	40 invokestatic (0, 0)
	41 org/apache/commons/math3/geometry/euclidean/threed/Vector3D.crossProduct:(Lorg/apache/commons/math3/geometry/euclidean/threed/Vector3D;Lorg/apache/commons/math3/geometry/euclidean/threed/Vector3D;)Lorg/apache/commons/math3/geometry/euclidean/threed/Vector3D; (0, 0)
	43 putfield (0, 0)
	44 org/apache/commons/math3/geometry/euclidean/threed/Plane.v:Lorg/apache/commons/math3/geometry/euclidean/threed/Vector3D; (0, 0)
	46 return (0, 0)

Method: getOrigin
	0 aload_0 (0, 0)
	1 getfield (0, 0)
	2 org/apache/commons/math3/geometry/euclidean/threed/Plane.origin:Lorg/apache/commons/math3/geometry/euclidean/threed/Vector3D; (0, 0)
	4 areturn (0, 0)

Method: getNormal
	0 aload_0 (0, 0)
	1 getfield (0, 0)
	2 org/apache/commons/math3/geometry/euclidean/threed/Plane.w:Lorg/apache/commons/math3/geometry/euclidean/threed/Vector3D; (0, 0)
	4 areturn (0, 0)

Method: getU
	0 aload_0 (0, 0)
	1 getfield (0, 0)
	2 org/apache/commons/math3/geometry/euclidean/threed/Plane.u:Lorg/apache/commons/math3/geometry/euclidean/threed/Vector3D; (0, 0)
	4 areturn (0, 0)

Method: getV
	0 aload_0 (0, 0)
	1 getfield (0, 0)
	2 org/apache/commons/math3/geometry/euclidean/threed/Plane.v:Lorg/apache/commons/math3/geometry/euclidean/threed/Vector3D; (0, 0)
	4 areturn (0, 0)

Method: project
	0 aload_0 (0, 0)
	1 aload_0 (0, 0)
	2 aload_1 (0, 0)
	3 invokevirtual (0, 0)
	4 org/apache/commons/math3/geometry/euclidean/threed/Plane.toSubSpace:(Lorg/apache/commons/math3/geometry/Point;)Lorg/apache/commons/math3/geometry/euclidean/twod/Vector2D; (0, 0)
	6 invokevirtual (0, 0)
	7 org/apache/commons/math3/geometry/euclidean/threed/Plane.toSpace:(Lorg/apache/commons/math3/geometry/Vector;)Lorg/apache/commons/math3/geometry/euclidean/threed/Vector3D; (0, 0)
	9 areturn (0, 0)

Method: getTolerance
	0 aload_0 (0, 0)
	1 getfield (0, 0)
	2 org/apache/commons/math3/geometry/euclidean/threed/Plane.tolerance:D (0, 0)
	4 dreturn (0, 0)

Method: revertSelf
	0 aload_0 (0, 0)
	1 getfield (0, 0)
	2 org/apache/commons/math3/geometry/euclidean/threed/Plane.u:Lorg/apache/commons/math3/geometry/euclidean/threed/Vector3D; (0, 0)
	4 astore_1 (0, 0)
	5 aload_0 (0, 0)
	6 aload_0 (0, 0)
	7 getfield (0, 0)
	8 org/apache/commons/math3/geometry/euclidean/threed/Plane.v:Lorg/apache/commons/math3/geometry/euclidean/threed/Vector3D; (0, 0)
	10 putfield (0, 0)
	11 org/apache/commons/math3/geometry/euclidean/threed/Plane.u:Lorg/apache/commons/math3/geometry/euclidean/threed/Vector3D; (0, 0)
	13 aload_0 (0, 0)
	14 aload_1 (0, 0)
	15 putfield (0, 0)
	16 org/apache/commons/math3/geometry/euclidean/threed/Plane.v:Lorg/apache/commons/math3/geometry/euclidean/threed/Vector3D; (0, 0)
	18 aload_0 (0, 0)
	19 aload_0 (0, 0)
	20 getfield (0, 0)
	21 org/apache/commons/math3/geometry/euclidean/threed/Plane.w:Lorg/apache/commons/math3/geometry/euclidean/threed/Vector3D; (0, 0)
	23 invokevirtual (0, 0)
	24 org/apache/commons/math3/geometry/euclidean/threed/Vector3D.negate:()Lorg/apache/commons/math3/geometry/euclidean/threed/Vector3D; (0, 0)
	26 putfield (0, 0)
	27 org/apache/commons/math3/geometry/euclidean/threed/Plane.w:Lorg/apache/commons/math3/geometry/euclidean/threed/Vector3D; (0, 0)
	29 aload_0 (0, 0)
	30 aload_0 (0, 0)
	31 getfield (0, 0)
	32 org/apache/commons/math3/geometry/euclidean/threed/Plane.originOffset:D (0, 0)
	34 dneg (0, 0)
	35 putfield (0, 0)
	36 org/apache/commons/math3/geometry/euclidean/threed/Plane.originOffset:D (0, 0)
	38 return (0, 0)

Method: toSubSpace
	0 aload_0 (0, 0)
	1 aload_1 (0, 0)
	2 invokevirtual (0, 0)
	3 org/apache/commons/math3/geometry/euclidean/threed/Plane.toSubSpace:(Lorg/apache/commons/math3/geometry/Point;)Lorg/apache/commons/math3/geometry/euclidean/twod/Vector2D; (0, 0)
	5 areturn (0, 0)

Method: toSpace
	0 aload_0 (0, 0)
	1 aload_1 (0, 0)
	2 invokevirtual (0, 0)
	3 org/apache/commons/math3/geometry/euclidean/threed/Plane.toSpace:(Lorg/apache/commons/math3/geometry/Point;)Lorg/apache/commons/math3/geometry/euclidean/threed/Vector3D; (0, 0)
	5 areturn (0, 0)

Method: getPointAt
	0 new (0, 0)
	1 org/apache/commons/math3/geometry/euclidean/threed/Vector3D (0, 0)
	3 dup (0, 0)
	4 aload_1 (0, 0)
	5 invokevirtual (0, 0)
	6 org/apache/commons/math3/geometry/euclidean/twod/Vector2D.getX:()D (0, 0)
	8 aload_0 (0, 0)
	9 getfield (0, 0)
	10 org/apache/commons/math3/geometry/euclidean/threed/Plane.u:Lorg/apache/commons/math3/geometry/euclidean/threed/Vector3D; (0, 0)
	12 aload_1 (0, 0)
	13 invokevirtual (0, 0)
	14 org/apache/commons/math3/geometry/euclidean/twod/Vector2D.getY:()D (0, 0)
	16 aload_0 (0, 0)
	17 getfield (0, 0)
	18 org/apache/commons/math3/geometry/euclidean/threed/Plane.v:Lorg/apache/commons/math3/geometry/euclidean/threed/Vector3D; (0, 0)
	20 dload_2 (0, 0)
	21 aload_0 (0, 0)
	22 getfield (0, 0)
	23 org/apache/commons/math3/geometry/euclidean/threed/Plane.originOffset:D (0, 0)
	25 dsub (0, 0)
	26 aload_0 (0, 0)
	27 getfield (0, 0)
	28 org/apache/commons/math3/geometry/euclidean/threed/Plane.w:Lorg/apache/commons/math3/geometry/euclidean/threed/Vector3D; (0, 0)
	30 invokespecial (0, 0)
	31 org/apache/commons/math3/geometry/euclidean/threed/Vector3D.<init>:(DLorg/apache/commons/math3/geometry/euclidean/threed/Vector3D;DLorg/apache/commons/math3/geometry/euclidean/threed/Vector3D;DLorg/apache/commons/math3/geometry/euclidean/threed/Vector3D;)V (0, 0)
	33 areturn (0, 0)

Method: isSimilarTo
	0 aload_0 (0, 0)
	1 getfield (0, 0)
	2 org/apache/commons/math3/geometry/euclidean/threed/Plane.w:Lorg/apache/commons/math3/geometry/euclidean/threed/Vector3D; (0, 0)
	4 aload_1 (0, 0)
	5 getfield (0, 0)
	6 org/apache/commons/math3/geometry/euclidean/threed/Plane.w:Lorg/apache/commons/math3/geometry/euclidean/threed/Vector3D; (0, 0)
	8 invokestatic (0, 0)
	9 org/apache/commons/math3/geometry/euclidean/threed/Vector3D.angle:(Lorg/apache/commons/math3/geometry/euclidean/threed/Vector3D;Lorg/apache/commons/math3/geometry/euclidean/threed/Vector3D;)D (0, 0)
	11 dstore_2 (0, 0)
	12 dload_2 (0, 0)
	13 ldc2_w (0, 0)
	14 1e-10 (0, 0)
	16 dcmpg (0, 0)
	17 ifge (0, 0)
	18 23 (0, 0)
	20 aload_0 (0, 0)
	21 getfield (0, 0)
	22 org/apache/commons/math3/geometry/euclidean/threed/Plane.originOffset:D (0, 0)
	24 aload_1 (0, 0)
	25 getfield (0, 0)
	26 org/apache/commons/math3/geometry/euclidean/threed/Plane.originOffset:D (0, 0)
	28 dsub (0, 0)
	29 invokestatic (0, 0)
	30 org/apache/commons/math3/util/FastMath.abs:(D)D (0, 0)
	32 aload_0 (0, 0)
	33 getfield (0, 0)
	34 org/apache/commons/math3/geometry/euclidean/threed/Plane.tolerance:D (0, 0)
	36 dcmpg (0, 0)
	37 iflt (0, 0)
	38 31 (0, 0)
	40 dload_2 (0, 0)
	41 ldc2_w (0, 0)
	42 3.141592653489793 (0, 0)
	44 dcmpl (0, 0)
	45 ifle (0, 0)
	46 27 (0, 0)
	48 aload_0 (0, 0)
	49 getfield (0, 0)
	50 org/apache/commons/math3/geometry/euclidean/threed/Plane.originOffset:D (0, 0)
	52 aload_1 (0, 0)
	53 getfield (0, 0)
	54 org/apache/commons/math3/geometry/euclidean/threed/Plane.originOffset:D (0, 0)
	56 dadd (0, 0)
	57 invokestatic (0, 0)
	58 org/apache/commons/math3/util/FastMath.abs:(D)D (0, 0)
	60 aload_0 (0, 0)
	61 getfield (0, 0)
	62 org/apache/commons/math3/geometry/euclidean/threed/Plane.tolerance:D (0, 0)
	64 dcmpg (0, 0)
	65 ifge (0, 0)
	66 7 (0, 0)
	68 iconst_1 (0, 0)
	69 goto (0, 0)
	70 4 (0, 0)
	72 iconst_0 (0, 0)
	73 ireturn (0, 0)

Method: rotate
	0 aload_0 (0, 0)
	1 getfield (0, 0)
	2 org/apache/commons/math3/geometry/euclidean/threed/Plane.origin:Lorg/apache/commons/math3/geometry/euclidean/threed/Vector3D; (0, 0)
	4 aload_1 (0, 0)
	5 invokevirtual (0, 0)
	6 org/apache/commons/math3/geometry/euclidean/threed/Vector3D.subtract:(Lorg/apache/commons/math3/geometry/Vector;)Lorg/apache/commons/math3/geometry/euclidean/threed/Vector3D; (0, 0)
	8 astore_3 (0, 0)
	9 new (0, 0)
	10 org/apache/commons/math3/geometry/euclidean/threed/Plane (0, 0)
	12 dup (0, 0)
	13 aload_1 (0, 0)
	14 aload_2 (0, 0)
	15 aload_3 (0, 0)
	16 invokevirtual (0, 0)
	17 org/apache/commons/math3/geometry/euclidean/threed/Rotation.applyTo:(Lorg/apache/commons/math3/geometry/euclidean/threed/Vector3D;)Lorg/apache/commons/math3/geometry/euclidean/threed/Vector3D; (0, 0)
	19 invokevirtual (0, 0)
	20 org/apache/commons/math3/geometry/euclidean/threed/Vector3D.add:(Lorg/apache/commons/math3/geometry/Vector;)Lorg/apache/commons/math3/geometry/euclidean/threed/Vector3D; (0, 0)
	22 aload_2 (0, 0)
	23 aload_0 (0, 0)
	24 getfield (0, 0)
	25 org/apache/commons/math3/geometry/euclidean/threed/Plane.w:Lorg/apache/commons/math3/geometry/euclidean/threed/Vector3D; (0, 0)
	27 invokevirtual (0, 0)
	28 org/apache/commons/math3/geometry/euclidean/threed/Rotation.applyTo:(Lorg/apache/commons/math3/geometry/euclidean/threed/Vector3D;)Lorg/apache/commons/math3/geometry/euclidean/threed/Vector3D; (0, 0)
	30 aload_0 (0, 0)
	31 getfield (0, 0)
	32 org/apache/commons/math3/geometry/euclidean/threed/Plane.tolerance:D (0, 0)
	34 invokespecial (0, 0)
	35 org/apache/commons/math3/geometry/euclidean/threed/Plane.<init>:(Lorg/apache/commons/math3/geometry/euclidean/threed/Vector3D;Lorg/apache/commons/math3/geometry/euclidean/threed/Vector3D;D)V (0, 0)
	37 astore (0, 0)
	38 #4 (0, 0)
	39 aload (0, 4)
	40 #4 (0, 4)
	41 aload_2 (0, 4)
	42 aload_0 (0, 4)
	43 getfield (0, 4)
	44 org/apache/commons/math3/geometry/euclidean/threed/Plane.u:Lorg/apache/commons/math3/geometry/euclidean/threed/Vector3D; (0, 4)
	46 invokevirtual (0, 4)
	47 org/apache/commons/math3/geometry/euclidean/threed/Rotation.applyTo:(Lorg/apache/commons/math3/geometry/euclidean/threed/Vector3D;)Lorg/apache/commons/math3/geometry/euclidean/threed/Vector3D; (0, 4)
	49 putfield (0, 4)
	50 org/apache/commons/math3/geometry/euclidean/threed/Plane.u:Lorg/apache/commons/math3/geometry/euclidean/threed/Vector3D; (0, 4)
	52 aload (0, 4)
	53 #4 (0, 4)
	54 aload_2 (0, 4)
	55 aload_0 (0, 4)
	56 getfield (0, 4)
	57 org/apache/commons/math3/geometry/euclidean/threed/Plane.v:Lorg/apache/commons/math3/geometry/euclidean/threed/Vector3D; (0, 4)
	59 invokevirtual (0, 4)
	60 org/apache/commons/math3/geometry/euclidean/threed/Rotation.applyTo:(Lorg/apache/commons/math3/geometry/euclidean/threed/Vector3D;)Lorg/apache/commons/math3/geometry/euclidean/threed/Vector3D; (0, 4)
	62 putfield (0, 4)
	63 org/apache/commons/math3/geometry/euclidean/threed/Plane.v:Lorg/apache/commons/math3/geometry/euclidean/threed/Vector3D; (0, 4)
	65 aload (0, 4)
	66 #4 (0, 4)
	67 areturn (0, 4)

Method: translate
	0 new (0, 0)
	1 org/apache/commons/math3/geometry/euclidean/threed/Plane (0, 0)
	3 dup (0, 0)
	4 aload_0 (0, 0)
	5 getfield (0, 0)
	6 org/apache/commons/math3/geometry/euclidean/threed/Plane.origin:Lorg/apache/commons/math3/geometry/euclidean/threed/Vector3D; (0, 0)
	8 aload_1 (0, 0)
	9 invokevirtual (0, 0)
	10 org/apache/commons/math3/geometry/euclidean/threed/Vector3D.add:(Lorg/apache/commons/math3/geometry/Vector;)Lorg/apache/commons/math3/geometry/euclidean/threed/Vector3D; (0, 0)
	12 aload_0 (0, 0)
	13 getfield (0, 0)
	14 org/apache/commons/math3/geometry/euclidean/threed/Plane.w:Lorg/apache/commons/math3/geometry/euclidean/threed/Vector3D; (0, 0)
	16 aload_0 (0, 0)
	17 getfield (0, 0)
	18 org/apache/commons/math3/geometry/euclidean/threed/Plane.tolerance:D (0, 0)
	20 invokespecial (0, 0)
	21 org/apache/commons/math3/geometry/euclidean/threed/Plane.<init>:(Lorg/apache/commons/math3/geometry/euclidean/threed/Vector3D;Lorg/apache/commons/math3/geometry/euclidean/threed/Vector3D;D)V (0, 0)
	23 astore_2 (0, 0)
	24 aload_2 (0, 4)
	25 aload_0 (0, 4)
	26 getfield (0, 4)
	27 org/apache/commons/math3/geometry/euclidean/threed/Plane.u:Lorg/apache/commons/math3/geometry/euclidean/threed/Vector3D; (0, 4)
	29 putfield (0, 4)
	30 org/apache/commons/math3/geometry/euclidean/threed/Plane.u:Lorg/apache/commons/math3/geometry/euclidean/threed/Vector3D; (0, 4)
	32 aload_2 (0, 4)
	33 aload_0 (0, 4)
	34 getfield (0, 4)
	35 org/apache/commons/math3/geometry/euclidean/threed/Plane.v:Lorg/apache/commons/math3/geometry/euclidean/threed/Vector3D; (0, 4)
	37 putfield (0, 4)
	38 org/apache/commons/math3/geometry/euclidean/threed/Plane.v:Lorg/apache/commons/math3/geometry/euclidean/threed/Vector3D; (0, 4)
	40 aload_2 (0, 4)
	41 areturn (0, 4)

Method: intersection
	0 aload_0 (0, 0)
	1 getfield (0, 0)
	2 org/apache/commons/math3/geometry/euclidean/threed/Plane.w:Lorg/apache/commons/math3/geometry/euclidean/threed/Vector3D; (0, 0)
	4 invokevirtual (0, 0)
	5 org/apache/commons/math3/geometry/euclidean/threed/Vector3D.getX:()D (0, 0)
	7 dstore_3 (0, 0)
	8 aload_0 (0, 0)
	9 getfield (0, 0)
	10 org/apache/commons/math3/geometry/euclidean/threed/Plane.w:Lorg/apache/commons/math3/geometry/euclidean/threed/Vector3D; (0, 0)
	12 invokevirtual (0, 0)
	13 org/apache/commons/math3/geometry/euclidean/threed/Vector3D.getY:()D (0, 0)
	15 dstore (0, 0)
	16 #5 (0, 0)
	17 aload_0 (0, 0)
	18 getfield (0, 0)
	19 org/apache/commons/math3/geometry/euclidean/threed/Plane.w:Lorg/apache/commons/math3/geometry/euclidean/threed/Vector3D; (0, 0)
	21 invokevirtual (0, 0)
	22 org/apache/commons/math3/geometry/euclidean/threed/Vector3D.getZ:()D (0, 0)
	24 dstore (0, 0)
	25 #7 (0, 0)
	26 aload_0 (0, 0)
	27 getfield (0, 0)
	28 org/apache/commons/math3/geometry/euclidean/threed/Plane.originOffset:D (0, 0)
	30 dstore (0, 0)
	31 #9 (0, 0)
	32 aload_1 (0, 0)
	33 getfield (0, 0)
	34 org/apache/commons/math3/geometry/euclidean/threed/Plane.w:Lorg/apache/commons/math3/geometry/euclidean/threed/Vector3D; (0, 0)
	36 invokevirtual (0, 0)
	37 org/apache/commons/math3/geometry/euclidean/threed/Vector3D.getX:()D (0, 0)
	39 dstore (0, 0)
	40 #11 (0, 0)
	41 aload_1 (0, 0)
	42 getfield (0, 0)
	43 org/apache/commons/math3/geometry/euclidean/threed/Plane.w:Lorg/apache/commons/math3/geometry/euclidean/threed/Vector3D; (0, 0)
	45 invokevirtual (0, 0)
	46 org/apache/commons/math3/geometry/euclidean/threed/Vector3D.getY:()D (0, 0)
	48 dstore (0, 0)
	49 #13 (0, 0)
	50 aload_1 (0, 0)
	51 getfield (0, 0)
	52 org/apache/commons/math3/geometry/euclidean/threed/Plane.w:Lorg/apache/commons/math3/geometry/euclidean/threed/Vector3D; (0, 0)
	54 invokevirtual (0, 0)
	55 org/apache/commons/math3/geometry/euclidean/threed/Vector3D.getZ:()D (0, 0)
	57 dstore (0, 0)
	58 #15 (0, 0)
	59 aload_1 (0, 0)
	60 getfield (0, 0)
	61 org/apache/commons/math3/geometry/euclidean/threed/Plane.originOffset:D (0, 0)
	63 dstore (0, 0)
	64 #17 (0, 0)
	65 aload_2 (0, 0)
	66 getfield (0, 0)
	67 org/apache/commons/math3/geometry/euclidean/threed/Plane.w:Lorg/apache/commons/math3/geometry/euclidean/threed/Vector3D; (0, 0)
	69 invokevirtual (0, 0)
	70 org/apache/commons/math3/geometry/euclidean/threed/Vector3D.getX:()D (0, 0)
	72 dstore (0, 0)
	73 #19 (0, 0)
	74 aload_2 (0, 0)
	75 getfield (0, 0)
	76 org/apache/commons/math3/geometry/euclidean/threed/Plane.w:Lorg/apache/commons/math3/geometry/euclidean/threed/Vector3D; (0, 0)
	78 invokevirtual (0, 0)
	79 org/apache/commons/math3/geometry/euclidean/threed/Vector3D.getY:()D (0, 0)
	81 dstore (0, 0)
	82 #21 (0, 0)
	83 aload_2 (0, 0)
	84 getfield (0, 0)
	85 org/apache/commons/math3/geometry/euclidean/threed/Plane.w:Lorg/apache/commons/math3/geometry/euclidean/threed/Vector3D; (0, 0)
	87 invokevirtual (0, 0)
	88 org/apache/commons/math3/geometry/euclidean/threed/Vector3D.getZ:()D (0, 0)
	90 dstore (0, 0)
	91 #23 (0, 0)
	92 aload_2 (0, 0)
	93 getfield (0, 0)
	94 org/apache/commons/math3/geometry/euclidean/threed/Plane.originOffset:D (0, 0)
	96 dstore (0, 0)
	97 #25 (0, 0)
	98 dload (0, 4)
	99 #13 (0, 4)
	100 dload (0, 4)
	101 #23 (0, 4)
	102 dmul (0, 4)
	103 dload (0, 4)
	104 #21 (0, 4)
	105 dload (0, 4)
	106 #15 (0, 4)
	107 dmul (0, 4)
	108 dsub (0, 4)
	109 dstore (0, 4)
	110 #27 (0, 4)
	111 dload (0, 4)
	112 #15 (0, 4)
	113 dload (0, 4)
	114 #19 (0, 4)
	115 dmul (0, 4)
	116 dload (0, 4)
	117 #23 (0, 4)
	118 dload (0, 4)
	119 #11 (0, 4)
	120 dmul (0, 4)
	121 dsub (0, 4)
	122 dstore (0, 4)
	123 #29 (0, 4)
	124 dload (0, 4)
	125 #11 (0, 4)
	126 dload (0, 4)
	127 #21 (0, 4)
	128 dmul (0, 4)
	129 dload (0, 4)
	130 #19 (0, 4)
	131 dload (0, 4)
	132 #13 (0, 4)
	133 dmul (0, 4)
	134 dsub (0, 4)
	135 dstore (0, 4)
	136 #31 (0, 4)
	137 dload_3 (0, 4)
	138 dload (0, 4)
	139 #27 (0, 4)
	140 dmul (0, 4)
	141 dload (0, 4)
	142 #5 (0, 4)
	143 dload (0, 4)
	144 #29 (0, 4)
	145 dmul (0, 4)
	146 dadd (0, 4)
	147 dload (0, 4)
	148 #7 (0, 4)
	149 dload (0, 4)
	150 #31 (0, 4)
	151 dmul (0, 4)
	152 dadd (0, 4)
	153 dstore (0, 4)
	154 #33 (0, 4)
	155 dload (1, 1)
	156 #33 (1, 1)
	157 invokestatic (1, 1)
	158 org/apache/commons/math3/util/FastMath.abs:(D)D (1, 1)
	160 ldc2_w (1, 1)
	161 1e-10 (1, 1)
	163 dcmpg (1, 1)
	164 ifge (1, 1)
	165 5 (1, 1)
	167 aconst_null (1, 1)
	168 areturn (1, 1)
	169 dconst_1 (0, 4)
	170 dload (0, 4)
	171 #33 (0, 4)
	172 ddiv (0, 4)
	173 dstore (0, 4)
	174 #35 (0, 4)
	175 new (0, 4)
	176 org/apache/commons/math3/geometry/euclidean/threed/Vector3D (0, 4)
	178 dup (0, 4)
	179 dload (0, 4)
	180 #27 (0, 4)
	181 dneg (0, 4)
	182 dload (0, 4)
	183 #9 (0, 4)
	184 dmul (0, 4)
	185 dload (0, 4)
	186 #7 (0, 4)
	187 dload (0, 4)
	188 #21 (0, 4)
	189 dmul (0, 4)
	190 dload (0, 4)
	191 #23 (0, 4)
	192 dload (0, 4)
	193 #5 (0, 4)
	194 dmul (0, 4)
	195 dsub (0, 4)
	196 dload (0, 4)
	197 #17 (0, 4)
	198 dmul (0, 4)
	199 dsub (0, 4)
	200 dload (0, 4)
	201 #15 (0, 4)
	202 dload (0, 4)
	203 #5 (0, 4)
	204 dmul (0, 4)
	205 dload (0, 4)
	206 #7 (0, 4)
	207 dload (0, 4)
	208 #13 (0, 4)
	209 dmul (0, 4)
	210 dsub (0, 4)
	211 dload (0, 4)
	212 #25 (0, 4)
	213 dmul (0, 4)
	214 dsub (0, 4)
	215 dload (0, 4)
	216 #35 (0, 4)
	217 dmul (0, 4)
	218 dload (0, 4)
	219 #29 (0, 4)
	220 dneg (0, 4)
	221 dload (0, 4)
	222 #9 (0, 4)
	223 dmul (0, 4)
	224 dload (0, 4)
	225 #23 (0, 4)
	226 dload_3 (0, 4)
	227 dmul (0, 4)
	228 dload (0, 4)
	229 #7 (0, 4)
	230 dload (0, 4)
	231 #19 (0, 4)
	232 dmul (0, 4)
	233 dsub (0, 4)
	234 dload (0, 4)
	235 #17 (0, 4)
	236 dmul (0, 4)
	237 dsub (0, 4)
	238 dload (0, 4)
	239 #7 (0, 4)
	240 dload (0, 4)
	241 #11 (0, 4)
	242 dmul (0, 4)
	243 dload (0, 4)
	244 #15 (0, 4)
	245 dload_3 (0, 4)
	246 dmul (0, 4)
	247 dsub (0, 4)
	248 dload (0, 4)
	249 #25 (0, 4)
	250 dmul (0, 4)
	251 dsub (0, 4)
	252 dload (0, 4)
	253 #35 (0, 4)
	254 dmul (0, 4)
	255 dload (0, 4)
	256 #31 (0, 4)
	257 dneg (0, 4)
	258 dload (0, 4)
	259 #9 (0, 4)
	260 dmul (0, 4)
	261 dload (0, 4)
	262 #5 (0, 4)
	263 dload (0, 4)
	264 #19 (0, 4)
	265 dmul (0, 4)
	266 dload (0, 4)
	267 #21 (0, 4)
	268 dload_3 (0, 4)
	269 dmul (0, 4)
	270 dsub (0, 4)
	271 dload (0, 4)
	272 #17 (0, 4)
	273 dmul (0, 4)
	274 dsub (0, 4)
	275 dload (0, 4)
	276 #13 (0, 4)
	277 dload_3 (0, 4)
	278 dmul (0, 4)
	279 dload (0, 4)
	280 #5 (0, 4)
	281 dload (0, 4)
	282 #11 (0, 4)
	283 dmul (0, 4)
	284 dsub (0, 4)
	285 dload (0, 4)
	286 #25 (0, 4)
	287 dmul (0, 4)
	288 dsub (0, 4)
	289 dload (0, 4)
	290 #35 (0, 4)
	291 dmul (0, 4)
	292 invokespecial (0, 4)
	293 org/apache/commons/math3/geometry/euclidean/threed/Vector3D.<init>:(DDD)V (0, 4)
	295 areturn (0, 4)

Method: wholeHyperplane
	0 aload_0 (0, 0)
	1 invokevirtual (0, 0)
	2 org/apache/commons/math3/geometry/euclidean/threed/Plane.wholeHyperplane:()Lorg/apache/commons/math3/geometry/euclidean/threed/SubPlane; (0, 0)
	4 areturn (0, 0)

Method: wholeSpace
	0 aload_0 (0, 0)
	1 invokevirtual (0, 0)
	2 org/apache/commons/math3/geometry/euclidean/threed/Plane.wholeSpace:()Lorg/apache/commons/math3/geometry/euclidean/threed/PolyhedronsSet; (0, 0)
	4 areturn (0, 0)

Method: contains
	0 aload_0 (0, 0)
	1 aload_1 (0, 0)
	2 invokevirtual (0, 0)
	3 org/apache/commons/math3/geometry/euclidean/threed/Plane.getOffset:(Lorg/apache/commons/math3/geometry/Vector;)D (0, 0)
	5 invokestatic (0, 0)
	6 org/apache/commons/math3/util/FastMath.abs:(D)D (0, 0)
	8 aload_0 (0, 0)
	9 getfield (0, 0)
	10 org/apache/commons/math3/geometry/euclidean/threed/Plane.tolerance:D (0, 0)
	12 dcmpg (0, 0)
	13 ifge (0, 0)
	14 7 (0, 0)
	16 iconst_1 (0, 0)
	17 goto (0, 0)
	18 4 (0, 0)
	20 iconst_0 (0, 0)
	21 ireturn (0, 0)

Method: getOffset
	0 aload_1 (0, 0)
	1 checkcast (0, 0)
	2 org/apache/commons/math3/geometry/euclidean/threed/Vector3D (0, 0)
	4 aload_0 (0, 0)
	5 getfield (0, 0)
	6 org/apache/commons/math3/geometry/euclidean/threed/Plane.w:Lorg/apache/commons/math3/geometry/euclidean/threed/Vector3D; (0, 0)
	8 invokevirtual (0, 0)
	9 org/apache/commons/math3/geometry/euclidean/threed/Vector3D.dotProduct:(Lorg/apache/commons/math3/geometry/Vector;)D (0, 0)
	11 aload_0 (0, 0)
	12 getfield (0, 0)
	13 org/apache/commons/math3/geometry/euclidean/threed/Plane.originOffset:D (0, 0)
	15 dadd (0, 0)
	16 dreturn (0, 0)

Method: sameOrientationAs
	0 aload_1 (0, 0)
	1 checkcast (0, 0)
	2 org/apache/commons/math3/geometry/euclidean/threed/Plane (0, 0)
	4 getfield (0, 0)
	5 org/apache/commons/math3/geometry/euclidean/threed/Plane.w:Lorg/apache/commons/math3/geometry/euclidean/threed/Vector3D; (0, 0)
	7 aload_0 (0, 0)
	8 getfield (0, 0)
	9 org/apache/commons/math3/geometry/euclidean/threed/Plane.w:Lorg/apache/commons/math3/geometry/euclidean/threed/Vector3D; (0, 0)
	11 invokevirtual (0, 0)
	12 org/apache/commons/math3/geometry/euclidean/threed/Vector3D.dotProduct:(Lorg/apache/commons/math3/geometry/Vector;)D (0, 0)
	14 dconst_0 (0, 0)
	15 dcmpl (0, 0)
	16 ifle (0, 0)
	17 7 (0, 0)
	19 iconst_1 (0, 0)
	20 goto (0, 0)
	21 4 (0, 0)
	23 iconst_0 (0, 0)
	24 ireturn (0, 0)

