Method: <init>
	0 aload_0 (0, 0)
	1 dload_1 (0, 0)
	2 dload_3 (0, 0)
	3 dload (0, 0)
	4 #5 (0, 0)
	5 dload (0, 0)
	6 #7 (0, 0)
	7 dload (0, 0)
	8 #9 (0, 0)
	9 dload (0, 0)
	10 #11 (0, 0)
	11 ldc2_w (0, 0)
	12 1e-10 (0, 0)
	14 invokespecial (0, 0)
	15 org/apache/commons/math3/geometry/euclidean/threed/PolyhedronsSet.<init>:(DDDDDDD)V (0, 0)
	17 return (0, 0)

Method: buildBoundary
	0 iconst_0 (1, 4)
	1 istore (1, 4)
	2 #4 (1, 4)
	3 iload (1, 4)
	4 #4 (1, 4)
	5 aload_0 (1, 4)
	6 invokeinterface (1, 4)
	7 java/util/List.get:(I)Ljava/lang/Object; (1, 4)
	9 0 (1, 4)
	11 iconst_1 (1, 4)
	12 isub (1, 4)
	13 if_icmpge (1, 4)
	14 114 (1, 4)
	16 aload_0 (1, 4)
	17 iload (1, 4)
	18 #4 (1, 4)
	19 invokeinterface (1, 4)
	20 java/util/List.distance:(Lorg/apache/commons/math3/geometry/euclidean/threed/Vector3D;Lorg/apache/commons/math3/geometry/euclidean/threed/Vector3D;)D (1, 4)
	22 0 (1, 4)
	24 checkcast (1, 4)
	25 org/apache/commons/math3/geometry/euclidean/threed/Vector3D (1, 4)
	27 astore (1, 4)
	28 #5 (1, 4)
	29 iload (2, 4)
	30 #4 (2, 4)
	31 iconst_1 (2, 4)
	32 iadd (2, 4)
	33 istore (2, 4)
	34 #6 (2, 4)
	35 iload (2, 4)
	36 #6 (2, 4)
	37 aload_0 (2, 4)
	38 invokeinterface (2, 4)
	39 java/util/List.get:(I)Ljava/lang/Object; (2, 4)
	41 0 (2, 4)
	43 if_icmpge (2, 4)
	44 78 (2, 4)
	46 aload (3, 1)
	47 #5 (3, 1)
	48 aload_0 (3, 1)
	49 iload (3, 1)
	50 #6 (3, 1)
	51 invokeinterface (3, 1)
	52 java/util/List.distance:(Lorg/apache/commons/math3/geometry/euclidean/threed/Vector3D;Lorg/apache/commons/math3/geometry/euclidean/threed/Vector3D;)D (3, 1)
	54 0 (3, 1)
	56 checkcast (3, 1)
	57 org/apache/commons/math3/geometry/euclidean/threed/Vector3D (3, 1)
	59 invokestatic (3, 1)
	60 org/apache/commons/math3/geometry/euclidean/threed/Vector3D.distance:(Lorg/apache/commons/math3/geometry/euclidean/threed/Vector3D;Lorg/apache/commons/math3/geometry/euclidean/threed/Vector3D;)D (3, 1)
	62 dload_2 (3, 1)
	63 dcmpg (3, 1)
	64 ifgt (3, 1)
	65 51 (3, 1)
	67 new (3, 1)
	68 org/apache/commons/math3/exception/MathIllegalArgumentException (3, 1)
	70 dup (3, 1)
	71 getstatic (3, 1)
	72 org/apache/commons/math3/exception/util/LocalizedFormats.CLOSE_VERTICES:Lorg/apache/commons/math3/exception/util/LocalizedFormats; (3, 1)
	74 iconst_3 (3, 1)
	75 anewarray (3, 1)
	76 java/lang/Object (3, 1)
	78 dup (3, 1)
	79 iconst_0 (3, 1)
	80 aload (3, 1)
	81 #5 (3, 1)
	82 invokevirtual (3, 1)
	83 org/apache/commons/math3/geometry/euclidean/threed/Vector3D.getX:()D (3, 1)
	85 invokestatic (3, 1)
	86 java/lang/Double.valueOf:(D)Ljava/lang/Double; (3, 1)
	88 aastore (3, 1)
	89 dup (3, 1)
	90 iconst_1 (3, 1)
	91 aload (3, 1)
	92 #5 (3, 1)
	93 invokevirtual (3, 1)
	94 org/apache/commons/math3/geometry/euclidean/threed/Vector3D.getY:()D (3, 1)
	96 invokestatic (3, 1)
	97 java/lang/Double.valueOf:(D)Ljava/lang/Double; (3, 1)
	99 aastore (3, 1)
	100 dup (3, 1)
	101 iconst_2 (3, 1)
	102 aload (3, 1)
	103 #5 (3, 1)
	104 invokevirtual (3, 1)
	105 org/apache/commons/math3/geometry/euclidean/threed/Vector3D.getZ:()D (3, 1)
	107 invokestatic (3, 1)
	108 java/lang/Double.valueOf:(D)Ljava/lang/Double; (3, 1)
	110 aastore (3, 1)
	111 invokespecial (3, 1)
	112 org/apache/commons/math3/exception/MathIllegalArgumentException.<init>:(Lorg/apache/commons/math3/exception/util/Localizable;[Ljava/lang/Object;)V (3, 1)
	114 athrow (3, 1)
	115 iinc (3, 1)
	116 #6 (3, 1)
	117 -89 (3, 1)
	118 goto (3, 1)
	119 -83 (3, 1)
	121 iinc (3, 1)
	122 #4 (3, 1)
	123 -89 (3, 1)
	124 goto (3, 1)
	125 -121 (3, 1)
	127 aload_0 (2, 4)
	128 aload_1 (2, 4)
	129 invokestatic (2, 4)
	130 org/apache/commons/math3/geometry/euclidean/threed/PolyhedronsSet.findReferences:(Ljava/util/List;Ljava/util/List;)[[I (2, 4)
	132 astore (2, 4)
	133 #4 (2, 4)
	134 aload_0 (2, 4)
	135 aload_1 (2, 4)
	136 aload (2, 4)
	137 #4 (2, 4)
	138 invokestatic (2, 4)
	139 org/apache/commons/math3/geometry/euclidean/threed/PolyhedronsSet.successors:(Ljava/util/List;Ljava/util/List;[[I)[[I (2, 4)
	141 astore (2, 4)
	142 #5 (2, 4)
	143 iconst_0 (3, 4)
	144 istore (3, 4)
	145 #6 (3, 4)
	146 iload (3, 4)
	147 #6 (3, 4)
	148 aload_0 (3, 4)
	149 invokeinterface (3, 4)
	150 java/util/List.get:(I)Ljava/lang/Object; (3, 4)
	152 0 (3, 4)
	154 if_icmpge (3, 4)
	155 219 (3, 4)
	157 aload (4, 4)
	158 #5 (4, 4)
	159 iload (4, 4)
	160 #6 (4, 4)
	161 aaload (4, 4)
	162 astore (4, 4)
	163 #7 (4, 4)
	164 aload (4, 4)
	165 #7 (4, 4)
	166 arraylength (4, 4)
	167 istore (4, 4)
	168 #8 (4, 4)
	169 iconst_0 (4, 4)
	170 istore (4, 4)
	171 #9 (4, 4)
	172 iload (4, 4)
	173 #9 (4, 4)
	174 iload (4, 4)
	175 #8 (4, 4)
	176 if_icmpge (4, 4)
	177 191 (4, 4)
	179 aload (4, 4)
	180 #7 (4, 4)
	181 iload (4, 4)
	182 #9 (4, 4)
	183 iaload (4, 4)
	184 istore (4, 4)
	185 #10 (4, 4)
	186 iload (5, 1)
	187 #10 (5, 1)
	188 iflt (5, 1)
	189 173 (5, 1)
	191 iconst_0 (6, 1)
	192 istore (6, 1)
	193 #11 (6, 1)
	194 aload (7, 4)
	195 #5 (7, 4)
	196 iload (7, 4)
	197 #10 (7, 4)
	198 aaload (7, 4)
	199 astore (7, 4)
	200 #12 (7, 4)
	201 aload (7, 4)
	202 #12 (7, 4)
	203 arraylength (7, 4)
	204 istore (7, 4)
	205 #13 (7, 4)
	206 iconst_0 (7, 4)
	207 istore (7, 4)
	208 #14 (7, 4)
	209 iload (7, 4)
	210 #14 (7, 4)
	211 iload (7, 4)
	212 #13 (7, 4)
	213 if_icmpge (7, 4)
	214 35 (7, 4)
	216 aload (7, 4)
	217 #12 (7, 4)
	218 iload (7, 4)
	219 #14 (7, 4)
	220 iaload (7, 4)
	221 istore (7, 4)
	222 #15 (7, 4)
	223 iload (7, 4)
	224 #11 (7, 4)
	225 ifne (7, 4)
	226 10 (7, 4)
	228 iload (7, 4)
	229 #15 (7, 4)
	230 iload (7, 4)
	231 #6 (7, 4)
	232 if_icmpne (7, 4)
	233 7 (7, 4)
	235 iconst_1 (7, 4)
	236 goto (7, 4)
	237 4 (7, 4)
	239 iconst_0 (7, 4)
	240 istore (7, 4)
	241 #11 (7, 4)
	242 iinc (7, 4)
	243 #14 (7, 4)
	244 -89 (7, 4)
	245 goto (7, 4)
	246 -36 (7, 4)
	248 iload (7, 1)
	249 #11 (7, 1)
	250 ifne (7, 1)
	251 111 (7, 1)
	253 aload_0 (7, 1)
	254 iload (7, 1)
	255 #6 (7, 1)
	256 invokeinterface (7, 1)
	257 java/util/List.distance:(Lorg/apache/commons/math3/geometry/euclidean/threed/Vector3D;Lorg/apache/commons/math3/geometry/euclidean/threed/Vector3D;)D (7, 1)
	259 0 (7, 1)
	261 checkcast (7, 1)
	262 org/apache/commons/math3/geometry/euclidean/threed/Vector3D (7, 1)
	264 astore (7, 1)
	265 #12 (7, 1)
	266 aload_0 (7, 1)
	267 iload (7, 1)
	268 #10 (7, 1)
	269 invokeinterface (7, 1)
	270 java/util/List.distance:(Lorg/apache/commons/math3/geometry/euclidean/threed/Vector3D;Lorg/apache/commons/math3/geometry/euclidean/threed/Vector3D;)D (7, 1)
	272 0 (7, 1)
	274 checkcast (7, 1)
	275 org/apache/commons/math3/geometry/euclidean/threed/Vector3D (7, 1)
	277 astore (7, 1)
	278 #13 (7, 1)
	279 new (7, 1)
	280 org/apache/commons/math3/exception/MathIllegalArgumentException (7, 1)
	282 dup (7, 1)
	283 getstatic (7, 1)
	284 org/apache/commons/math3/exception/util/LocalizedFormats.EDGE_CONNECTED_TO_ONE_FACET:Lorg/apache/commons/math3/exception/util/LocalizedFormats; (7, 1)
	286 bipush (7, 1)
	287 6 (7, 1)
	288 anewarray (7, 1)
	289 java/lang/Object (7, 1)
	291 dup (7, 1)
	292 iconst_0 (7, 1)
	293 aload (7, 1)
	294 #12 (7, 1)
	295 invokevirtual (7, 1)
	296 org/apache/commons/math3/geometry/euclidean/threed/Vector3D.getX:()D (7, 1)
	298 invokestatic (7, 1)
	299 java/lang/Double.valueOf:(D)Ljava/lang/Double; (7, 1)
	301 aastore (7, 1)
	302 dup (7, 1)
	303 iconst_1 (7, 1)
	304 aload (7, 1)
	305 #12 (7, 1)
	306 invokevirtual (7, 1)
	307 org/apache/commons/math3/geometry/euclidean/threed/Vector3D.getY:()D (7, 1)
	309 invokestatic (7, 1)
	310 java/lang/Double.valueOf:(D)Ljava/lang/Double; (7, 1)
	312 aastore (7, 1)
	313 dup (7, 1)
	314 iconst_2 (7, 1)
	315 aload (7, 1)
	316 #12 (7, 1)
	317 invokevirtual (7, 1)
	318 org/apache/commons/math3/geometry/euclidean/threed/Vector3D.getZ:()D (7, 1)
	320 invokestatic (7, 1)
	321 java/lang/Double.valueOf:(D)Ljava/lang/Double; (7, 1)
	323 aastore (7, 1)
	324 dup (7, 1)
	325 iconst_3 (7, 1)
	326 aload (7, 1)
	327 #13 (7, 1)
	328 invokevirtual (7, 1)
	329 org/apache/commons/math3/geometry/euclidean/threed/Vector3D.getX:()D (7, 1)
	331 invokestatic (7, 1)
	332 java/lang/Double.valueOf:(D)Ljava/lang/Double; (7, 1)
	334 aastore (7, 1)
	335 dup (7, 1)
	336 iconst_4 (7, 1)
	337 aload (7, 1)
	338 #13 (7, 1)
	339 invokevirtual (7, 1)
	340 org/apache/commons/math3/geometry/euclidean/threed/Vector3D.getY:()D (7, 1)
	342 invokestatic (7, 1)
	343 java/lang/Double.valueOf:(D)Ljava/lang/Double; (7, 1)
	345 aastore (7, 1)
	346 dup (7, 1)
	347 iconst_5 (7, 1)
	348 aload (7, 1)
	349 #13 (7, 1)
	350 invokevirtual (7, 1)
	351 org/apache/commons/math3/geometry/euclidean/threed/Vector3D.getZ:()D (7, 1)
	353 invokestatic (7, 1)
	354 java/lang/Double.valueOf:(D)Ljava/lang/Double; (7, 1)
	356 aastore (7, 1)
	357 invokespecial (7, 1)
	358 org/apache/commons/math3/exception/MathIllegalArgumentException.<init>:(Lorg/apache/commons/math3/exception/util/Localizable;[Ljava/lang/Object;)V (7, 1)
	360 athrow (7, 1)
	361 iinc (7, 1)
	362 #9 (7, 1)
	363 -89 (7, 1)
	364 goto (7, 1)
	365 -192 (7, 1)
	367 iinc (7, 1)
	368 #6 (7, 1)
	369 -89 (7, 1)
	370 goto (7, 1)
	371 -224 (7, 1)
	373 new (6, 1)
	374 java/util/ArrayList (6, 1)
	376 dup (6, 1)
	377 invokespecial (6, 1)
	378 java/util/ArrayList.<init>:()V (6, 1)
	380 astore (6, 1)
	381 #6 (6, 1)
	382 aload_1 (7, 4)
	383 invokeinterface (7, 4)
	384 java/util/List.java/util/Iterator (7, 4)
	386 0 (7, 4)
	388 astore (7, 4)
	389 #7 (7, 4)
	390 aload (7, 4)
	391 #7 (7, 4)
	392 invokeinterface (7, 4)
	393 java/util/Iterator.next:()Ljava/lang/Object; (7, 4)
	395 0 (7, 4)
	397 ifeq (7, 4)
	398 205 (7, 4)
	400 aload (7, 4)
	401 #7 (7, 4)
	402 invokeinterface (7, 4)
	403 java/util/Iterator.<init>:(Lorg/apache/commons/math3/geometry/euclidean/threed/Vector3D;Lorg/apache/commons/math3/geometry/euclidean/threed/Vector3D;Lorg/apache/commons/math3/geometry/euclidean/threed/Vector3D;D)V (7, 4)
	405 0 (7, 4)
	407 checkcast (7, 4)
	408 [I (7, 4)
	410 astore (7, 4)
	411 #8 (7, 4)
	412 new (7, 4)
	413 org/apache/commons/math3/geometry/euclidean/threed/Plane (7, 4)
	415 dup (7, 4)
	416 aload_0 (7, 4)
	417 aload (7, 4)
	418 #8 (7, 4)
	419 iconst_0 (7, 4)
	420 iaload (7, 4)
	421 invokeinterface (7, 4)
	422 java/util/List.distance:(Lorg/apache/commons/math3/geometry/euclidean/threed/Vector3D;Lorg/apache/commons/math3/geometry/euclidean/threed/Vector3D;)D (7, 4)
	424 0 (7, 4)
	426 checkcast (7, 4)
	427 org/apache/commons/math3/geometry/euclidean/threed/Vector3D (7, 4)
	429 aload_0 (7, 4)
	430 aload (7, 4)
	431 #8 (7, 4)
	432 iconst_1 (7, 4)
	433 iaload (7, 4)
	434 invokeinterface (7, 4)
	435 java/util/List.distance:(Lorg/apache/commons/math3/geometry/euclidean/threed/Vector3D;Lorg/apache/commons/math3/geometry/euclidean/threed/Vector3D;)D (7, 4)
	437 0 (7, 4)
	439 checkcast (7, 4)
	440 org/apache/commons/math3/geometry/euclidean/threed/Vector3D (7, 4)
	442 aload_0 (7, 4)
	443 aload (7, 4)
	444 #8 (7, 4)
	445 iconst_2 (7, 4)
	446 iaload (7, 4)
	447 invokeinterface (7, 4)
	448 java/util/List.distance:(Lorg/apache/commons/math3/geometry/euclidean/threed/Vector3D;Lorg/apache/commons/math3/geometry/euclidean/threed/Vector3D;)D (7, 4)
	450 0 (7, 4)
	452 checkcast (7, 4)
	453 org/apache/commons/math3/geometry/euclidean/threed/Vector3D (7, 4)
	455 dload_2 (7, 4)
	456 invokespecial (7, 4)
	457 org/apache/commons/math3/geometry/euclidean/threed/Plane.<init>:(Lorg/apache/commons/math3/geometry/euclidean/threed/Vector3D;Lorg/apache/commons/math3/geometry/euclidean/threed/Vector3D;Lorg/apache/commons/math3/geometry/euclidean/threed/Vector3D;D)V (7, 4)
	459 astore (7, 4)
	460 #9 (7, 4)
	461 aload (7, 4)
	462 #8 (7, 4)
	463 arraylength (7, 4)
	464 anewarray (7, 4)
	465 org/apache/commons/math3/geometry/euclidean/twod/Vector2D (7, 4)
	467 astore (7, 4)
	468 #10 (7, 4)
	469 iconst_0 (8, 4)
	470 istore (8, 4)
	471 #11 (8, 4)
	472 iload (8, 4)
	473 #11 (8, 4)
	474 aload (8, 4)
	475 #8 (8, 4)
	476 arraylength (8, 4)
	477 if_icmpge (8, 4)
	478 95 (8, 4)
	480 aload_0 (8, 4)
	481 aload (8, 4)
	482 #8 (8, 4)
	483 iload (8, 4)
	484 #11 (8, 4)
	485 iaload (8, 4)
	486 invokeinterface (8, 4)
	487 java/util/List.distance:(Lorg/apache/commons/math3/geometry/euclidean/threed/Vector3D;Lorg/apache/commons/math3/geometry/euclidean/threed/Vector3D;)D (8, 4)
	489 0 (8, 4)
	491 checkcast (8, 4)
	492 org/apache/commons/math3/geometry/euclidean/threed/Vector3D (8, 4)
	494 astore (8, 4)
	495 #12 (8, 4)
	496 aload (9, 1)
	497 #9 (9, 1)
	498 aload (9, 1)
	499 #12 (9, 1)
	500 invokevirtual (9, 1)
	501 org/apache/commons/math3/geometry/euclidean/threed/Plane.contains:(Lorg/apache/commons/math3/geometry/euclidean/threed/Vector3D;)Z (9, 1)
	503 ifne (9, 1)
	504 51 (9, 1)
	506 new (9, 1)
	507 org/apache/commons/math3/exception/MathIllegalArgumentException (9, 1)
	509 dup (9, 1)
	510 getstatic (9, 1)
	511 org/apache/commons/math3/exception/util/LocalizedFormats.OUT_OF_PLANE:Lorg/apache/commons/math3/exception/util/LocalizedFormats; (9, 1)
	513 iconst_3 (9, 1)
	514 anewarray (9, 1)
	515 java/lang/Object (9, 1)
	517 dup (9, 1)
	518 iconst_0 (9, 1)
	519 aload (9, 1)
	520 #12 (9, 1)
	521 invokevirtual (9, 1)
	522 org/apache/commons/math3/geometry/euclidean/threed/Vector3D.getX:()D (9, 1)
	524 invokestatic (9, 1)
	525 java/lang/Double.valueOf:(D)Ljava/lang/Double; (9, 1)
	527 aastore (9, 1)
	528 dup (9, 1)
	529 iconst_1 (9, 1)
	530 aload (9, 1)
	531 #12 (9, 1)
	532 invokevirtual (9, 1)
	533 org/apache/commons/math3/geometry/euclidean/threed/Vector3D.getY:()D (9, 1)
	535 invokestatic (9, 1)
	536 java/lang/Double.valueOf:(D)Ljava/lang/Double; (9, 1)
	538 aastore (9, 1)
	539 dup (9, 1)
	540 iconst_2 (9, 1)
	541 aload (9, 1)
	542 #12 (9, 1)
	543 invokevirtual (9, 1)
	544 org/apache/commons/math3/geometry/euclidean/threed/Vector3D.getZ:()D (9, 1)
	546 invokestatic (9, 1)
	547 java/lang/Double.valueOf:(D)Ljava/lang/Double; (9, 1)
	549 aastore (9, 1)
	550 invokespecial (9, 1)
	551 org/apache/commons/math3/exception/MathIllegalArgumentException.<init>:(Lorg/apache/commons/math3/exception/util/Localizable;[Ljava/lang/Object;)V (9, 1)
	553 athrow (9, 1)
	554 aload (8, 4)
	555 #10 (8, 4)
	556 iload (8, 4)
	557 #11 (8, 4)
	558 aload (8, 4)
	559 #9 (8, 4)
	560 aload (8, 4)
	561 #12 (8, 4)
	562 invokevirtual (8, 4)
	563 org/apache/commons/math3/geometry/euclidean/threed/Plane.toSubSpace:(Lorg/apache/commons/math3/geometry/Vector;)Lorg/apache/commons/math3/geometry/euclidean/twod/Vector2D; (8, 4)
	565 aastore (8, 4)
	566 iinc (8, 4)
	567 #11 (8, 4)
	568 -89 (8, 4)
	569 goto (8, 4)
	570 -97 (8, 4)
	572 aload (7, 4)
	573 #6 (7, 4)
	574 new (7, 4)
	575 org/apache/commons/math3/geometry/euclidean/threed/SubPlane (7, 4)
	577 dup (7, 4)
	578 aload (7, 4)
	579 #9 (7, 4)
	580 new (7, 4)
	581 org/apache/commons/math3/geometry/euclidean/twod/PolygonsSet (7, 4)
	583 dup (7, 4)
	584 dload_2 (7, 4)
	585 aload (7, 4)
	586 #10 (7, 4)
	587 invokespecial (7, 4)
	588 org/apache/commons/math3/geometry/euclidean/twod/PolygonsSet.<init>:(D[Lorg/apache/commons/math3/geometry/euclidean/twod/Vector2D;)V (7, 4)
	590 invokespecial (7, 4)
	591 org/apache/commons/math3/geometry/euclidean/threed/SubPlane.<init>:(Lorg/apache/commons/math3/geometry/partitioning/Hyperplane;Lorg/apache/commons/math3/geometry/partitioning/Region;)V (7, 4)
	593 invokeinterface (7, 4)
	594 java/util/List.org/apache/commons/math3/exception/NumberIsTooSmallException (7, 4)
	596 0 (7, 4)
	598 pop (7, 4)
	599 goto (6, 1)
	600 -209 (6, 1)
	602 aload (6, 1)
	603 #6 (6, 1)
	604 areturn (5, 1)

Method: findReferences
	0 aload_0 (0, 0)
	1 invokeinterface (0, 0)
	2 java/util/List.get:(I)Ljava/lang/Object; (0, 0)
	4 0 (0, 0)
	6 newarray (0, 0)
	7 10 (0, 0)
	8 astore_2 (0, 0)
	9 iconst_0 (0, 0)
	10 istore_3 (0, 0)
	11 aload_1 (1, 4)
	12 invokeinterface (1, 4)
	13 java/util/List.java/util/Iterator (1, 4)
	15 0 (1, 4)
	17 astore (1, 4)
	18 #4 (1, 4)
	19 aload (1, 4)
	20 #4 (1, 4)
	21 invokeinterface (1, 4)
	22 java/util/Iterator.next:()Ljava/lang/Object; (1, 4)
	24 0 (1, 4)
	26 ifeq (1, 4)
	27 93 (1, 4)
	29 aload (1, 4)
	30 #4 (1, 4)
	31 invokeinterface (1, 4)
	32 java/util/Iterator.<init>:(Lorg/apache/commons/math3/geometry/euclidean/threed/Vector3D;Lorg/apache/commons/math3/geometry/euclidean/threed/Vector3D;Lorg/apache/commons/math3/geometry/euclidean/threed/Vector3D;D)V (1, 4)
	34 0 (1, 4)
	36 checkcast (1, 4)
	37 [I (1, 4)
	39 astore (1, 4)
	40 #5 (1, 4)
	41 aload (2, 1)
	42 #5 (2, 1)
	43 arraylength (2, 1)
	44 iconst_3 (2, 1)
	45 if_icmpge (2, 1)
	46 25 (2, 1)
	48 new (2, 1)
	49 org/apache/commons/math3/exception/NumberIsTooSmallException (2, 1)
	51 dup (2, 1)
	52 getstatic (2, 1)
	53 org/apache/commons/math3/exception/util/LocalizedFormats.WRONG_NUMBER_OF_POINTS:Lorg/apache/commons/math3/exception/util/LocalizedFormats; (2, 1)
	55 iconst_3 (2, 1)
	56 invokestatic (2, 1)
	57 java/lang/Integer.valueOf:(I)Ljava/lang/Integer; (2, 1)
	59 aload (2, 1)
	60 #5 (2, 1)
	61 arraylength (2, 1)
	62 invokestatic (2, 1)
	63 java/lang/Integer.valueOf:(I)Ljava/lang/Integer; (2, 1)
	65 iconst_1 (2, 1)
	66 invokespecial (2, 1)
	67 org/apache/commons/math3/exception/NumberIsTooSmallException.<init>:(Lorg/apache/commons/math3/exception/util/Localizable;Ljava/lang/Number;Ljava/lang/Number;Z)V (2, 1)
	69 athrow (2, 1)
	70 aload (2, 4)
	71 #5 (2, 4)
	72 astore (2, 4)
	73 #6 (2, 4)
	74 aload (2, 4)
	75 #6 (2, 4)
	76 arraylength (2, 4)
	77 istore (2, 4)
	78 #7 (2, 4)
	79 iconst_0 (2, 4)
	80 istore (2, 4)
	81 #8 (2, 4)
	82 iload (2, 4)
	83 #8 (2, 4)
	84 iload (2, 4)
	85 #7 (2, 4)
	86 if_icmpge (2, 4)
	87 30 (2, 4)
	89 aload (2, 4)
	90 #6 (2, 4)
	91 iload (2, 4)
	92 #8 (2, 4)
	93 iaload (2, 4)
	94 istore (2, 4)
	95 #9 (2, 4)
	96 iload_3 (2, 4)
	97 aload_2 (2, 4)
	98 iload (2, 4)
	99 #9 (2, 4)
	100 dup2 (2, 4)
	101 iaload (2, 4)
	102 iconst_1 (2, 4)
	103 iadd (2, 4)
	104 dup_x2 (2, 4)
	105 iastore (2, 4)
	106 invokestatic (2, 4)
	107 org/apache/commons/math3/util/FastMath.max:(II)I (2, 4)
	109 istore_3 (2, 4)
	110 iinc (2, 4)
	111 #8 (2, 4)
	112 -89 (2, 4)
	113 goto (2, 4)
	114 -31 (2, 4)
	116 goto (0, 0)
	117 -97 (0, 0)
	119 aload_0 (0, 0)
	120 invokeinterface (0, 0)
	121 java/util/List.get:(I)Ljava/lang/Object; (0, 0)
	123 0 (0, 0)
	125 iload_3 (0, 0)
	126 multianewarray (0, 0)
	127 [[I (0, 0)
	129 58 (0, 0)
	130 astore (0, 0)
	131 #4 (0, 0)
	132 aload (1, 4)
	133 #4 (1, 4)
	134 astore (1, 4)
	135 #5 (1, 4)
	136 aload (1, 4)
	137 #5 (1, 4)
	138 arraylength (1, 4)
	139 istore (1, 4)
	140 #6 (1, 4)
	141 iconst_0 (1, 4)
	142 istore (1, 4)
	143 #7 (1, 4)
	144 iload (1, 4)
	145 #7 (1, 4)
	146 iload (1, 4)
	147 #6 (1, 4)
	148 if_icmpge (1, 4)
	149 22 (1, 4)
	151 aload (1, 4)
	152 #5 (1, 4)
	153 iload (1, 4)
	154 #7 (1, 4)
	155 aaload (1, 4)
	156 astore (1, 4)
	157 #8 (1, 4)
	158 aload (1, 4)
	159 #8 (1, 4)
	160 iconst_m1 (1, 4)
	161 invokestatic (1, 4)
	162 java/util/Arrays.fill:([II)V (1, 4)
	164 iinc (1, 4)
	165 #7 (1, 4)
	166 -89 (1, 4)
	167 goto (1, 4)
	168 -23 (1, 4)
	170 iconst_0 (1, 4)
	171 istore (1, 4)
	172 #5 (1, 4)
	173 iload (1, 4)
	174 #5 (1, 4)
	175 aload_1 (1, 4)
	176 invokeinterface (1, 4)
	177 java/util/List.get:(I)Ljava/lang/Object; (1, 4)
	179 0 (1, 4)
	181 if_icmpge (1, 4)
	182 86 (1, 4)
	184 aload_1 (2, 4)
	185 iload (2, 4)
	186 #5 (2, 4)
	187 invokeinterface (2, 4)
	188 java/util/List.distance:(Lorg/apache/commons/math3/geometry/euclidean/threed/Vector3D;Lorg/apache/commons/math3/geometry/euclidean/threed/Vector3D;)D (2, 4)
	190 0 (2, 4)
	192 checkcast (2, 4)
	193 [I (2, 4)
	195 astore (2, 4)
	196 #6 (2, 4)
	197 aload (2, 4)
	198 #6 (2, 4)
	199 arraylength (2, 4)
	200 istore (2, 4)
	201 #7 (2, 4)
	202 iconst_0 (2, 4)
	203 istore (2, 4)
	204 #8 (2, 4)
	205 iload (2, 4)
	206 #8 (2, 4)
	207 iload (2, 4)
	208 #7 (2, 4)
	209 if_icmpge (2, 4)
	210 52 (2, 4)
	212 aload (2, 4)
	213 #6 (2, 4)
	214 iload (2, 4)
	215 #8 (2, 4)
	216 iaload (2, 4)
	217 istore (2, 4)
	218 #9 (2, 4)
	219 iconst_0 (2, 4)
	220 istore (2, 4)
	221 #10 (2, 4)
	222 iload (3, 3)
	223 #10 (3, 3)
	224 iload_3 (3, 3)
	225 if_icmpge (3, 3)
	226 20 (3, 3)
	228 aload (3, 3)
	229 #4 (3, 3)
	230 iload (3, 3)
	231 #9 (3, 3)
	232 aaload (3, 3)
	233 iload (3, 3)
	234 #10 (3, 3)
	235 iaload (3, 3)
	236 iflt (3, 3)
	237 9 (3, 3)
	239 iinc (3, 3)
	240 #10 (3, 3)
	241 -89 (3, 3)
	242 goto (3, 3)
	243 -20 (3, 3)
	245 aload (2, 4)
	246 #4 (2, 4)
	247 iload (2, 4)
	248 #9 (2, 4)
	249 aaload (2, 4)
	250 iload (2, 4)
	251 #10 (2, 4)
	252 iload (2, 4)
	253 #5 (2, 4)
	254 iastore (2, 4)
	255 iinc (2, 4)
	256 #8 (2, 4)
	257 -89 (2, 4)
	258 goto (2, 4)
	259 -53 (2, 4)
	261 iinc (2, 4)
	262 #5 (2, 4)
	263 -89 (2, 4)
	264 goto (2, 4)
	265 -91 (2, 4)
	267 aload (1, 4)
	268 #4 (1, 4)
	269 areturn (1, 4)

Method: successors
	0 aload_0 (0, 0)
	1 invokeinterface (0, 0)
	2 java/util/List.get:(I)Ljava/lang/Object; (0, 0)
	4 0 (0, 0)
	6 aload_2 (0, 0)
	7 iconst_0 (0, 0)
	8 aaload (0, 0)
	9 arraylength (0, 0)
	10 multianewarray (0, 0)
	11 [[I (0, 0)
	13 78 (0, 0)
	14 astore_3 (0, 0)
	15 aload_3 (1, 4)
	16 astore (1, 4)
	17 #4 (1, 4)
	18 aload (1, 4)
	19 #4 (1, 4)
	20 arraylength (1, 4)
	21 istore (1, 4)
	22 #5 (1, 4)
	23 iconst_0 (1, 4)
	24 istore (1, 4)
	25 #6 (1, 4)
	26 iload (1, 4)
	27 #6 (1, 4)
	28 iload (1, 4)
	29 #5 (1, 4)
	30 if_icmpge (1, 4)
	31 22 (1, 4)
	33 aload (1, 4)
	34 #4 (1, 4)
	35 iload (1, 4)
	36 #6 (1, 4)
	37 aaload (1, 4)
	38 astore (1, 4)
	39 #7 (1, 4)
	40 aload (1, 4)
	41 #7 (1, 4)
	42 iconst_m1 (1, 4)
	43 invokestatic (1, 4)
	44 java/util/Arrays.fill:([II)V (1, 4)
	46 iinc (1, 4)
	47 #6 (1, 4)
	48 -89 (1, 4)
	49 goto (1, 4)
	50 -23 (1, 4)
	52 iconst_0 (1, 4)
	53 istore (1, 4)
	54 #4 (1, 4)
	55 iload (1, 4)
	56 #4 (1, 4)
	57 aload_0 (1, 4)
	58 invokeinterface (1, 4)
	59 java/util/List.get:(I)Ljava/lang/Object; (1, 4)
	61 0 (1, 4)
	63 if_icmpge (1, 4)
	64 247 (1, 4)
	66 iconst_0 (2, 4)
	67 istore (2, 4)
	68 #5 (2, 4)
	69 iload (2, 4)
	70 #5 (2, 4)
	71 aload_3 (2, 4)
	72 iload (2, 4)
	73 #4 (2, 4)
	74 aaload (2, 4)
	75 arraylength (2, 4)
	76 if_icmpge (2, 4)
	77 228 (2, 4)
	79 aload_2 (2, 4)
	80 iload (2, 4)
	81 #4 (2, 4)
	82 aaload (2, 4)
	83 iload (2, 4)
	84 #5 (2, 4)
	85 iaload (2, 4)
	86 iflt (2, 4)
	87 218 (2, 4)
	89 aload_1 (3, 4)
	90 aload_2 (3, 4)
	91 iload (3, 4)
	92 #4 (3, 4)
	93 aaload (3, 4)
	94 iload (3, 4)
	95 #5 (3, 4)
	96 iaload (3, 4)
	97 invokeinterface (3, 4)
	98 java/util/List.distance:(Lorg/apache/commons/math3/geometry/euclidean/threed/Vector3D;Lorg/apache/commons/math3/geometry/euclidean/threed/Vector3D;)D (3, 4)
	100 0 (3, 4)
	102 checkcast (3, 4)
	103 [I (3, 4)
	105 astore (3, 4)
	106 #6 (3, 4)
	107 iconst_0 (3, 4)
	108 istore (3, 4)
	109 #7 (3, 4)
	110 iload (4, 3)
	111 #7 (4, 3)
	112 aload (4, 3)
	113 #6 (4, 3)
	114 arraylength (4, 3)
	115 if_icmpge (4, 3)
	116 19 (4, 3)
	118 aload (4, 3)
	119 #6 (4, 3)
	120 iload (4, 3)
	121 #7 (4, 3)
	122 iaload (4, 3)
	123 iload (4, 3)
	124 #4 (4, 3)
	125 if_icmpeq (4, 3)
	126 9 (4, 3)
	128 iinc (4, 3)
	129 #7 (4, 3)
	130 -89 (4, 3)
	131 goto (4, 3)
	132 -21 (4, 3)
	134 aload_3 (3, 4)
	135 iload (3, 4)
	136 #4 (3, 4)
	137 aaload (3, 4)
	138 iload (3, 4)
	139 #5 (3, 4)
	140 aload (3, 4)
	141 #6 (3, 4)
	142 iload (3, 4)
	143 #7 (3, 4)
	144 iconst_1 (3, 4)
	145 iadd (3, 4)
	146 aload (3, 4)
	147 #6 (3, 4)
	148 arraylength (3, 4)
	149 irem (3, 4)
	150 iaload (3, 4)
	151 iastore (3, 4)
	152 iconst_0 (4, 4)
	153 istore (4, 4)
	154 #8 (4, 4)
	155 iload (4, 4)
	156 #8 (4, 4)
	157 iload (4, 4)
	158 #5 (4, 4)
	159 if_icmpge (4, 4)
	160 139 (4, 4)
	162 aload_3 (5, 1)
	163 iload (5, 1)
	164 #4 (5, 1)
	165 aaload (5, 1)
	166 iload (5, 1)
	167 #8 (5, 1)
	168 iaload (5, 1)
	169 aload_3 (5, 1)
	170 iload (5, 1)
	171 #4 (5, 1)
	172 aaload (5, 1)
	173 iload (5, 1)
	174 #5 (5, 1)
	175 iaload (5, 1)
	176 if_icmpne (5, 1)
	177 116 (5, 1)
	179 aload_0 (5, 1)
	180 iload (5, 1)
	181 #4 (5, 1)
	182 invokeinterface (5, 1)
	183 java/util/List.distance:(Lorg/apache/commons/math3/geometry/euclidean/threed/Vector3D;Lorg/apache/commons/math3/geometry/euclidean/threed/Vector3D;)D (5, 1)
	185 0 (5, 1)
	187 checkcast (5, 1)
	188 org/apache/commons/math3/geometry/euclidean/threed/Vector3D (5, 1)
	190 astore (5, 1)
	191 #9 (5, 1)
	192 aload_0 (5, 1)
	193 aload_3 (5, 1)
	194 iload (5, 1)
	195 #4 (5, 1)
	196 aaload (5, 1)
	197 iload (5, 1)
	198 #5 (5, 1)
	199 iaload (5, 1)
	200 invokeinterface (5, 1)
	201 java/util/List.distance:(Lorg/apache/commons/math3/geometry/euclidean/threed/Vector3D;Lorg/apache/commons/math3/geometry/euclidean/threed/Vector3D;)D (5, 1)
	203 0 (5, 1)
	205 checkcast (5, 1)
	206 org/apache/commons/math3/geometry/euclidean/threed/Vector3D (5, 1)
	208 astore (5, 1)
	209 #10 (5, 1)
	210 new (5, 1)
	211 org/apache/commons/math3/exception/MathIllegalArgumentException (5, 1)
	213 dup (5, 1)
	214 getstatic (5, 1)
	215 org/apache/commons/math3/exception/util/LocalizedFormats.FACET_ORIENTATION_MISMATCH:Lorg/apache/commons/math3/exception/util/LocalizedFormats; (5, 1)
	217 bipush (5, 1)
	218 6 (5, 1)
	219 anewarray (5, 1)
	220 java/lang/Object (5, 1)
	222 dup (5, 1)
	223 iconst_0 (5, 1)
	224 aload (5, 1)
	225 #9 (5, 1)
	226 invokevirtual (5, 1)
	227 org/apache/commons/math3/geometry/euclidean/threed/Vector3D.getX:()D (5, 1)
	229 invokestatic (5, 1)
	230 java/lang/Double.valueOf:(D)Ljava/lang/Double; (5, 1)
	232 aastore (5, 1)
	233 dup (5, 1)
	234 iconst_1 (5, 1)
	235 aload (5, 1)
	236 #9 (5, 1)
	237 invokevirtual (5, 1)
	238 org/apache/commons/math3/geometry/euclidean/threed/Vector3D.getY:()D (5, 1)
	240 invokestatic (5, 1)
	241 java/lang/Double.valueOf:(D)Ljava/lang/Double; (5, 1)
	243 aastore (5, 1)
	244 dup (5, 1)
	245 iconst_2 (5, 1)
	246 aload (5, 1)
	247 #9 (5, 1)
	248 invokevirtual (5, 1)
	249 org/apache/commons/math3/geometry/euclidean/threed/Vector3D.getZ:()D (5, 1)
	251 invokestatic (5, 1)
	252 java/lang/Double.valueOf:(D)Ljava/lang/Double; (5, 1)
	254 aastore (5, 1)
	255 dup (5, 1)
	256 iconst_3 (5, 1)
	257 aload (5, 1)
	258 #10 (5, 1)
	259 invokevirtual (5, 1)
	260 org/apache/commons/math3/geometry/euclidean/threed/Vector3D.getX:()D (5, 1)
	262 invokestatic (5, 1)
	263 java/lang/Double.valueOf:(D)Ljava/lang/Double; (5, 1)
	265 aastore (5, 1)
	266 dup (5, 1)
	267 iconst_4 (5, 1)
	268 aload (5, 1)
	269 #10 (5, 1)
	270 invokevirtual (5, 1)
	271 org/apache/commons/math3/geometry/euclidean/threed/Vector3D.getY:()D (5, 1)
	273 invokestatic (5, 1)
	274 java/lang/Double.valueOf:(D)Ljava/lang/Double; (5, 1)
	276 aastore (5, 1)
	277 dup (5, 1)
	278 iconst_5 (5, 1)
	279 aload (5, 1)
	280 #10 (5, 1)
	281 invokevirtual (5, 1)
	282 org/apache/commons/math3/geometry/euclidean/threed/Vector3D.getZ:()D (5, 1)
	284 invokestatic (5, 1)
	285 java/lang/Double.valueOf:(D)Ljava/lang/Double; (5, 1)
	287 aastore (5, 1)
	288 invokespecial (5, 1)
	289 org/apache/commons/math3/exception/MathIllegalArgumentException.<init>:(Lorg/apache/commons/math3/exception/util/Localizable;[Ljava/lang/Object;)V (5, 1)
	291 athrow (5, 1)
	292 iinc (5, 1)
	293 #8 (5, 1)
	294 -89 (5, 1)
	295 goto (5, 1)
	296 -140 (5, 1)
	298 iinc (5, 1)
	299 #5 (5, 1)
	300 -89 (5, 1)
	301 goto (5, 1)
	302 -232 (5, 1)
	304 iinc (5, 1)
	305 #4 (5, 1)
	306 -89 (5, 1)
	307 goto (5, 1)
	308 -252 (5, 1)
	310 aload_3 (4, 4)
	311 areturn (3, 4)

Method: buildNew
	0 aload_0 (0, 0)
	1 aload_1 (0, 0)
	2 invokevirtual (0, 0)
	3 org/apache/commons/math3/geometry/euclidean/threed/PolyhedronsSet.buildNew:(Lorg/apache/commons/math3/geometry/partitioning/BSPTree;)Lorg/apache/commons/math3/geometry/euclidean/threed/PolyhedronsSet; (0, 0)
	5 areturn (0, 0)

Method: computeGeometricalProperties
	0 aload_0 (0, 0)
	1 iconst_1 (0, 0)
	2 invokevirtual (0, 0)
	3 org/apache/commons/math3/geometry/euclidean/threed/PolyhedronsSet.getTree:(Z)Lorg/apache/commons/math3/geometry/partitioning/BSPTree; (0, 0)
	5 new (0, 0)
	6 org/apache/commons/math3/geometry/euclidean/threed/PolyhedronsSet$FacetsContributionVisitor (0, 0)
	8 dup (0, 0)
	9 aload_0 (0, 0)
	10 invokespecial (0, 0)
	11 org/apache/commons/math3/geometry/euclidean/threed/PolyhedronsSet$FacetsContributionVisitor.<init>:(Lorg/apache/commons/math3/geometry/euclidean/threed/PolyhedronsSet;)V (0, 0)
	13 invokevirtual (0, 0)
	14 org/apache/commons/math3/geometry/partitioning/BSPTree.visit:(Lorg/apache/commons/math3/geometry/partitioning/BSPTreeVisitor;)V (0, 0)
	16 aload_0 (1, 1)
	17 invokevirtual (1, 1)
	18 org/apache/commons/math3/geometry/euclidean/threed/PolyhedronsSet.getSize:()D (1, 1)
	20 dconst_0 (1, 1)
	21 dcmpg (1, 1)
	22 ifge (1, 1)
	23 20 (1, 1)
	25 aload_0 (1, 1)
	26 ldc2_w (1, 1)
	27 inf (1, 1)
	29 invokevirtual (1, 1)
	30 org/apache/commons/math3/geometry/euclidean/threed/PolyhedronsSet.setSize:(D)V (1, 1)
	32 aload_0 (1, 1)
	33 getstatic (1, 1)
	34 org/apache/commons/math3/geometry/euclidean/threed/Vector3D.NaN:Lorg/apache/commons/math3/geometry/euclidean/threed/Vector3D; (1, 1)
	36 invokevirtual (1, 1)
	37 org/apache/commons/math3/geometry/euclidean/threed/PolyhedronsSet.setBarycenter:(Lorg/apache/commons/math3/geometry/Point;)V (1, 1)
	39 goto (1, 1)
	40 43 (1, 1)
	42 aload_0 (2, 2)
	43 aload_0 (2, 2)
	44 invokevirtual (2, 2)
	45 org/apache/commons/math3/geometry/euclidean/threed/PolyhedronsSet.getSize:()D (2, 2)
	47 ldc2_w (2, 2)
	48 3.0 (2, 2)
	50 ddiv (2, 2)
	51 invokevirtual (2, 2)
	52 org/apache/commons/math3/geometry/euclidean/threed/PolyhedronsSet.setSize:(D)V (2, 2)
	54 aload_0 (2, 2)
	55 new (2, 2)
	56 org/apache/commons/math3/geometry/euclidean/threed/Vector3D (2, 2)
	58 dup (2, 2)
	59 dconst_1 (2, 2)
	60 ldc2_w (2, 2)
	61 4.0 (2, 2)
	63 aload_0 (2, 2)
	64 invokevirtual (2, 2)
	65 org/apache/commons/math3/geometry/euclidean/threed/PolyhedronsSet.getSize:()D (2, 2)
	67 dmul (2, 2)
	68 ddiv (2, 2)
	69 aload_0 (2, 2)
	70 invokevirtual (2, 2)
	71 org/apache/commons/math3/geometry/euclidean/threed/PolyhedronsSet.getBarycenter:()Lorg/apache/commons/math3/geometry/Point; (2, 2)
	73 checkcast (2, 2)
	74 org/apache/commons/math3/geometry/euclidean/threed/Vector3D (2, 2)
	76 invokespecial (2, 2)
	77 org/apache/commons/math3/geometry/euclidean/threed/Vector3D.<init>:(DLorg/apache/commons/math3/geometry/euclidean/threed/Vector3D;)V (2, 2)
	79 invokevirtual (2, 2)
	80 org/apache/commons/math3/geometry/euclidean/threed/PolyhedronsSet.setBarycenter:(Lorg/apache/commons/math3/geometry/Point;)V (2, 2)
	82 return (0, 0)

Method: firstIntersection
	0 aload_0 (0, 0)
	1 aload_0 (0, 0)
	2 iconst_1 (0, 0)
	3 invokevirtual (0, 0)
	4 org/apache/commons/math3/geometry/euclidean/threed/PolyhedronsSet.getTree:(Z)Lorg/apache/commons/math3/geometry/partitioning/BSPTree; (0, 0)
	6 aload_1 (0, 0)
	7 aload_2 (0, 0)
	8 invokespecial (0, 0)
	9 org/apache/commons/math3/geometry/euclidean/threed/PolyhedronsSet.recurseFirstIntersection:(Lorg/apache/commons/math3/geometry/partitioning/BSPTree;Lorg/apache/commons/math3/geometry/euclidean/threed/Vector3D;Lorg/apache/commons/math3/geometry/euclidean/threed/Line;)Lorg/apache/commons/math3/geometry/partitioning/SubHyperplane; (0, 0)
	11 areturn (0, 0)

Method: recurseFirstIntersection
	0 aload_1 (0, 0)
	1 invokevirtual (0, 0)
	2 org/apache/commons/math3/geometry/partitioning/BSPTree.getCut:()Lorg/apache/commons/math3/geometry/partitioning/SubHyperplane; (0, 0)
	4 astore (0, 0)
	5 #4 (0, 0)
	6 aload (1, 1)
	7 #4 (1, 1)
	8 ifnonnull (1, 1)
	9 5 (1, 1)
	11 aconst_null (1, 1)
	12 areturn (1, 1)
	13 aload_1 (0, 0)
	14 invokevirtual (0, 0)
	15 org/apache/commons/math3/geometry/partitioning/BSPTree.getMinus:()Lorg/apache/commons/math3/geometry/partitioning/BSPTree; (0, 0)
	17 astore (0, 0)
	18 #5 (0, 0)
	19 aload_1 (0, 0)
	20 invokevirtual (0, 0)
	21 org/apache/commons/math3/geometry/partitioning/BSPTree.getPlus:()Lorg/apache/commons/math3/geometry/partitioning/BSPTree; (0, 0)
	23 astore (0, 0)
	24 #6 (0, 0)
	25 aload (0, 0)
	26 #4 (0, 0)
	27 invokeinterface (0, 0)
	28 org/apache/commons/math3/geometry/partitioning/SubHyperplane.getOffset:(Lorg/apache/commons/math3/geometry/Point;)D (0, 0)
	30 0 (0, 0)
	32 checkcast (0, 0)
	33 org/apache/commons/math3/geometry/euclidean/threed/Plane (0, 0)
	35 astore (0, 0)
	36 #7 (0, 0)
	37 aload (0, 0)
	38 #7 (0, 0)
	39 aload_2 (0, 0)
	40 invokevirtual (0, 0)
	41 org/apache/commons/math3/geometry/euclidean/threed/Plane.getOffset:(Lorg/apache/commons/math3/geometry/Point;)D (0, 0)
	43 dstore (0, 0)
	44 #8 (0, 0)
	45 dload (0, 0)
	46 #8 (0, 0)
	47 invokestatic (0, 0)
	48 org/apache/commons/math3/util/FastMath.abs:(D)D (0, 0)
	50 aload_0 (0, 0)
	51 invokevirtual (0, 0)
	52 org/apache/commons/math3/geometry/euclidean/threed/PolyhedronsSet.getTolerance:()D (0, 0)
	54 dcmpg (0, 0)
	55 ifge (0, 0)
	56 7 (0, 0)
	58 iconst_1 (0, 0)
	59 goto (0, 0)
	60 4 (0, 0)
	62 iconst_0 (0, 0)
	63 istore (0, 0)
	64 #10 (0, 0)
	65 dload (1, 1)
	66 #8 (1, 1)
	67 dconst_0 (1, 1)
	68 dcmpg (1, 1)
	69 ifge (1, 1)
	70 14 (1, 1)
	72 aload (1, 1)
	73 #5 (1, 1)
	74 astore (1, 1)
	75 #11 (1, 1)
	76 aload (1, 1)
	77 #6 (1, 1)
	78 astore (1, 1)
	79 #12 (1, 1)
	80 goto (1, 1)
	81 11 (1, 1)
	83 aload (2, 2)
	84 #6 (2, 2)
	85 astore (2, 2)
	86 #11 (2, 2)
	87 aload (2, 2)
	88 #5 (2, 2)
	89 astore (2, 2)
	90 #12 (2, 2)
	91 iload (1, 1)
	92 #10 (1, 1)
	93 ifeq (1, 1)
	94 19 (1, 1)
	96 aload_0 (1, 1)
	97 aload_2 (1, 1)
	98 aload_1 (1, 1)
	99 invokespecial (1, 1)
	100 org/apache/commons/math3/geometry/euclidean/threed/PolyhedronsSet.boundaryFacet:(Lorg/apache/commons/math3/geometry/euclidean/threed/Vector3D;Lorg/apache/commons/math3/geometry/partitioning/BSPTree;)Lorg/apache/commons/math3/geometry/partitioning/SubHyperplane; (1, 1)
	102 astore (1, 1)
	103 #13 (1, 1)
	104 aload (2, 1)
	105 #13 (2, 1)
	106 ifnull (2, 1)
	107 6 (2, 1)
	109 aload (2, 1)
	110 #13 (2, 1)
	111 areturn (2, 1)
	112 aload_0 (0, 0)
	113 aload (0, 0)
	114 #11 (0, 0)
	115 aload_2 (0, 0)
	116 aload_3 (0, 0)
	117 invokespecial (0, 0)
	118 org/apache/commons/math3/geometry/euclidean/threed/PolyhedronsSet.recurseFirstIntersection:(Lorg/apache/commons/math3/geometry/partitioning/BSPTree;Lorg/apache/commons/math3/geometry/euclidean/threed/Vector3D;Lorg/apache/commons/math3/geometry/euclidean/threed/Line;)Lorg/apache/commons/math3/geometry/partitioning/SubHyperplane; (0, 0)
	120 astore (0, 0)
	121 #13 (0, 0)
	122 aload (1, 1)
	123 #13 (1, 1)
	124 ifnull (1, 1)
	125 6 (1, 1)
	127 aload (1, 1)
	128 #13 (1, 1)
	129 areturn (1, 1)
	130 iload (1, 1)
	131 #10 (1, 1)
	132 ifne (1, 1)
	133 48 (1, 1)
	135 aload (1, 1)
	136 #7 (1, 1)
	137 aload_3 (1, 1)
	138 invokevirtual (1, 1)
	139 org/apache/commons/math3/geometry/euclidean/threed/Plane.intersection:(Lorg/apache/commons/math3/geometry/euclidean/threed/Line;)Lorg/apache/commons/math3/geometry/euclidean/threed/Vector3D; (1, 1)
	141 astore (1, 1)
	142 #14 (1, 1)
	143 aload (2, 1)
	144 #14 (2, 1)
	145 ifnull (2, 1)
	146 35 (2, 1)
	148 aload_3 (2, 1)
	149 aload (2, 1)
	150 #14 (2, 1)
	151 invokevirtual (2, 1)
	152 org/apache/commons/math3/geometry/euclidean/threed/Line.getAbscissa:(Lorg/apache/commons/math3/geometry/euclidean/threed/Vector3D;)D (2, 1)
	154 aload_3 (2, 1)
	155 aload_2 (2, 1)
	156 invokevirtual (2, 1)
	157 org/apache/commons/math3/geometry/euclidean/threed/Line.getAbscissa:(Lorg/apache/commons/math3/geometry/euclidean/threed/Vector3D;)D (2, 1)
	159 dcmpl (2, 1)
	160 ifle (2, 1)
	161 20 (2, 1)
	163 aload_0 (2, 1)
	164 aload (2, 1)
	165 #14 (2, 1)
	166 aload_1 (2, 1)
	167 invokespecial (2, 1)
	168 org/apache/commons/math3/geometry/euclidean/threed/PolyhedronsSet.boundaryFacet:(Lorg/apache/commons/math3/geometry/euclidean/threed/Vector3D;Lorg/apache/commons/math3/geometry/partitioning/BSPTree;)Lorg/apache/commons/math3/geometry/partitioning/SubHyperplane; (2, 1)
	170 astore (2, 1)
	171 #15 (2, 1)
	172 aload (3, 1)
	173 #15 (3, 1)
	174 ifnull (3, 1)
	175 6 (3, 1)
	177 aload (3, 1)
	178 #15 (3, 1)
	179 areturn (3, 1)
	180 aload_0 (0, 0)
	181 aload (0, 0)
	182 #12 (0, 0)
	183 aload_2 (0, 0)
	184 aload_3 (0, 0)
	185 invokespecial (0, 0)
	186 org/apache/commons/math3/geometry/euclidean/threed/PolyhedronsSet.recurseFirstIntersection:(Lorg/apache/commons/math3/geometry/partitioning/BSPTree;Lorg/apache/commons/math3/geometry/euclidean/threed/Vector3D;Lorg/apache/commons/math3/geometry/euclidean/threed/Line;)Lorg/apache/commons/math3/geometry/partitioning/SubHyperplane; (0, 0)
	188 areturn (0, 0)

Method: boundaryFacet
	0 aload_2 (0, 0)
	1 invokevirtual (0, 0)
	2 org/apache/commons/math3/geometry/partitioning/BSPTree.getCut:()Lorg/apache/commons/math3/geometry/partitioning/SubHyperplane; (0, 0)
	4 invokeinterface (0, 0)
	5 org/apache/commons/math3/geometry/partitioning/SubHyperplane.getOffset:(Lorg/apache/commons/math3/geometry/Point;)D (0, 0)
	7 0 (0, 0)
	9 checkcast (0, 0)
	10 org/apache/commons/math3/geometry/euclidean/threed/Plane (0, 0)
	12 aload_1 (0, 0)
	13 invokevirtual (0, 0)
	14 org/apache/commons/math3/geometry/euclidean/threed/Plane.toSubSpace:(Lorg/apache/commons/math3/geometry/Point;)Lorg/apache/commons/math3/geometry/euclidean/twod/Vector2D; (0, 0)
	16 astore_3 (0, 0)
	17 aload_2 (0, 0)
	18 invokevirtual (0, 0)
	19 org/apache/commons/math3/geometry/partitioning/BSPTree.getAttribute:()Ljava/lang/Object; (0, 0)
	21 checkcast (0, 0)
	22 org/apache/commons/math3/geometry/partitioning/BoundaryAttribute (0, 0)
	24 astore (0, 0)
	25 #4 (0, 0)
	26 aload (1, 1)
	27 #4 (1, 1)
	28 invokevirtual (1, 1)
	29 org/apache/commons/math3/geometry/partitioning/BoundaryAttribute.getPlusOutside:()Lorg/apache/commons/math3/geometry/partitioning/SubHyperplane; (1, 1)
	31 ifnull (1, 1)
	32 32 (1, 1)
	34 aload (1, 1)
	35 #4 (1, 1)
	36 invokevirtual (1, 1)
	37 org/apache/commons/math3/geometry/partitioning/BoundaryAttribute.getPlusOutside:()Lorg/apache/commons/math3/geometry/partitioning/SubHyperplane; (1, 1)
	39 checkcast (1, 1)
	40 org/apache/commons/math3/geometry/euclidean/threed/SubPlane (1, 1)
	42 invokevirtual (1, 1)
	43 org/apache/commons/math3/geometry/euclidean/threed/SubPlane.getRemainingRegion:()Lorg/apache/commons/math3/geometry/partitioning/Region; (1, 1)
	45 aload_3 (1, 1)
	46 invokeinterface (1, 1)
	47 org/apache/commons/math3/geometry/partitioning/Region.org/apache/commons/math3/geometry/partitioning/Region$Location (1, 1)
	49 0 (1, 1)
	51 getstatic (1, 1)
	52 org/apache/commons/math3/geometry/partitioning/Region$Location.INSIDE:Lorg/apache/commons/math3/geometry/partitioning/Region$Location; (1, 1)
	54 if_acmpne (1, 1)
	55 9 (1, 1)
	57 aload (1, 1)
	58 #4 (1, 1)
	59 invokevirtual (1, 1)
	60 org/apache/commons/math3/geometry/partitioning/BoundaryAttribute.getPlusOutside:()Lorg/apache/commons/math3/geometry/partitioning/SubHyperplane; (1, 1)
	62 areturn (1, 1)
	63 aload (2, 1)
	64 #4 (2, 1)
	65 invokevirtual (2, 1)
	66 org/apache/commons/math3/geometry/partitioning/BoundaryAttribute.getPlusInside:()Lorg/apache/commons/math3/geometry/partitioning/SubHyperplane; (2, 1)
	68 ifnull (2, 1)
	69 32 (2, 1)
	71 aload (2, 1)
	72 #4 (2, 1)
	73 invokevirtual (2, 1)
	74 org/apache/commons/math3/geometry/partitioning/BoundaryAttribute.getPlusInside:()Lorg/apache/commons/math3/geometry/partitioning/SubHyperplane; (2, 1)
	76 checkcast (2, 1)
	77 org/apache/commons/math3/geometry/euclidean/threed/SubPlane (2, 1)
	79 invokevirtual (2, 1)
	80 org/apache/commons/math3/geometry/euclidean/threed/SubPlane.getRemainingRegion:()Lorg/apache/commons/math3/geometry/partitioning/Region; (2, 1)
	82 aload_3 (2, 1)
	83 invokeinterface (2, 1)
	84 org/apache/commons/math3/geometry/partitioning/Region.org/apache/commons/math3/geometry/partitioning/Region$Location (2, 1)
	86 0 (2, 1)
	88 getstatic (2, 1)
	89 org/apache/commons/math3/geometry/partitioning/Region$Location.INSIDE:Lorg/apache/commons/math3/geometry/partitioning/Region$Location; (2, 1)
	91 if_acmpne (2, 1)
	92 9 (2, 1)
	94 aload (2, 1)
	95 #4 (2, 1)
	96 invokevirtual (2, 1)
	97 org/apache/commons/math3/geometry/partitioning/BoundaryAttribute.getPlusInside:()Lorg/apache/commons/math3/geometry/partitioning/SubHyperplane; (2, 1)
	99 areturn (2, 1)
	100 aconst_null (2, 1)
	101 areturn (0, 1)

Method: rotate
	0 aload_0 (1, 4)
	1 new (1, 4)
	2 org/apache/commons/math3/geometry/euclidean/threed/PolyhedronsSet$RotationTransform (1, 4)
	4 dup (1, 4)
	5 aload_1 (1, 4)
	6 aload_2 (1, 4)
	7 invokespecial (1, 4)
	8 org/apache/commons/math3/geometry/euclidean/threed/PolyhedronsSet$RotationTransform.<init>:(Lorg/apache/commons/math3/geometry/euclidean/threed/Vector3D;Lorg/apache/commons/math3/geometry/euclidean/threed/Rotation;)V (1, 4)
	10 invokevirtual (1, 4)
	11 org/apache/commons/math3/geometry/euclidean/threed/PolyhedronsSet.applyTransform:(Lorg/apache/commons/math3/geometry/partitioning/Transform;)Lorg/apache/commons/math3/geometry/partitioning/AbstractRegion; (1, 4)
	13 checkcast (1, 4)
	14 org/apache/commons/math3/geometry/euclidean/threed/PolyhedronsSet (1, 4)
	16 areturn (0, 4)

Method: translate
	0 aload_0 (1, 4)
	1 new (1, 4)
	2 org/apache/commons/math3/geometry/euclidean/threed/PolyhedronsSet$TranslationTransform (1, 4)
	4 dup (1, 4)
	5 aload_1 (1, 4)
	6 invokespecial (1, 4)
	7 org/apache/commons/math3/geometry/euclidean/threed/PolyhedronsSet$TranslationTransform.<init>:(Lorg/apache/commons/math3/geometry/euclidean/threed/Vector3D;)V (1, 4)
	9 invokevirtual (1, 4)
	10 org/apache/commons/math3/geometry/euclidean/threed/PolyhedronsSet.applyTransform:(Lorg/apache/commons/math3/geometry/partitioning/Transform;)Lorg/apache/commons/math3/geometry/partitioning/AbstractRegion; (1, 4)
	12 checkcast (1, 4)
	13 org/apache/commons/math3/geometry/euclidean/threed/PolyhedronsSet (1, 4)
	15 areturn (0, 4)

Method: access$000
	0 aload_0 (0, 0)
	1 dload_1 (0, 0)
	2 invokevirtual (0, 0)
	3 org/apache/commons/math3/geometry/euclidean/threed/PolyhedronsSet.setSize:(D)V (0, 0)
	5 return (0, 0)

Method: access$100
	0 aload_0 (0, 0)
	1 aload_1 (0, 0)
	2 invokevirtual (0, 0)
	3 org/apache/commons/math3/geometry/euclidean/threed/PolyhedronsSet.setBarycenter:(Lorg/apache/commons/math3/geometry/Point;)V (0, 0)
	5 return (0, 0)

Method: access$200
	0 aload_0 (0, 0)
	1 dload_1 (0, 0)
	2 invokevirtual (0, 0)
	3 org/apache/commons/math3/geometry/euclidean/threed/PolyhedronsSet.setSize:(D)V (0, 0)
	5 return (0, 0)

Method: access$300
	0 aload_0 (0, 0)
	1 aload_1 (0, 0)
	2 invokevirtual (0, 0)
	3 org/apache/commons/math3/geometry/euclidean/threed/PolyhedronsSet.setBarycenter:(Lorg/apache/commons/math3/geometry/Point;)V (0, 0)
	5 return (0, 0)

Method: access$400
	0 aload_0 (0, 0)
	1 dload_1 (0, 0)
	2 invokevirtual (0, 0)
	3 org/apache/commons/math3/geometry/euclidean/threed/PolyhedronsSet.setSize:(D)V (0, 0)
	5 return (0, 0)

Method: access$500
	0 aload_0 (0, 0)
	1 aload_1 (0, 0)
	2 invokevirtual (0, 0)
	3 org/apache/commons/math3/geometry/euclidean/threed/PolyhedronsSet.setBarycenter:(Lorg/apache/commons/math3/geometry/Point;)V (0, 0)
	5 return (0, 0)

