Method: <init>
	0 aload_0 (1, 4)
	1 invokespecial (1, 4)
	2 java/lang/Object.<init>:()V (1, 4)
	4 aload_0 (1, 4)
	5 aload_1 (1, 4)
	6 putfield (1, 4)
	7 org/apache/commons/math3/geometry/euclidean/threed/PolyhedronsSet$RotationTransform.center:Lorg/apache/commons/math3/geometry/euclidean/threed/Vector3D; (1, 4)
	9 aload_0 (1, 4)
	10 aload_2 (1, 4)
	11 putfield (1, 4)
	12 org/apache/commons/math3/geometry/euclidean/threed/PolyhedronsSet$RotationTransform.rotation:Lorg/apache/commons/math3/geometry/euclidean/threed/Rotation; (1, 4)
	14 return (0, 0)

Method: apply
	0 aload_0 (1, 4)
	1 aload_1 (1, 4)
	2 invokevirtual (1, 4)
	3 org/apache/commons/math3/geometry/euclidean/threed/PolyhedronsSet$RotationTransform.apply:(Lorg/apache/commons/math3/geometry/Point;)Lorg/apache/commons/math3/geometry/euclidean/threed/Vector3D; (1, 4)
	5 areturn (1, 4)

