Method: <init>
	0 aload_0 (0, 0)
	1 invokespecial (0, 0)
	2 java/lang/Object.<init>:()V (0, 0)
	4 aload_0 (0, 0)
	5 aload_1 (0, 0)
	6 putfield (0, 0)
	7 org/apache/commons/math3/geometry/euclidean/threed/RotationOrder.name:Ljava/lang/String; (0, 0)
	9 aload_0 (0, 0)
	10 aload_2 (0, 0)
	11 putfield (0, 0)
	12 org/apache/commons/math3/geometry/euclidean/threed/RotationOrder.a1:Lorg/apache/commons/math3/geometry/euclidean/threed/Vector3D; (0, 0)
	14 aload_0 (0, 0)
	15 aload_3 (0, 0)
	16 putfield (0, 0)
	17 org/apache/commons/math3/geometry/euclidean/threed/RotationOrder.a2:Lorg/apache/commons/math3/geometry/euclidean/threed/Vector3D; (0, 0)
	19 aload_0 (0, 0)
	20 aload (0, 0)
	21 #4 (0, 0)
	22 putfield (0, 0)
	23 org/apache/commons/math3/geometry/euclidean/threed/RotationOrder.a3:Lorg/apache/commons/math3/geometry/euclidean/threed/Vector3D; (0, 0)
	25 return (0, 0)

Method: toString
	0 aload_0 (0, 0)
	1 getfield (0, 0)
	2 org/apache/commons/math3/geometry/euclidean/threed/RotationOrder.name:Ljava/lang/String; (0, 0)
	4 areturn (0, 0)

Method: getA1
	0 aload_0 (0, 0)
	1 getfield (0, 0)
	2 org/apache/commons/math3/geometry/euclidean/threed/RotationOrder.a1:Lorg/apache/commons/math3/geometry/euclidean/threed/Vector3D; (0, 0)
	4 areturn (0, 0)

Method: getA2
	0 aload_0 (0, 0)
	1 getfield (0, 0)
	2 org/apache/commons/math3/geometry/euclidean/threed/RotationOrder.a2:Lorg/apache/commons/math3/geometry/euclidean/threed/Vector3D; (0, 0)
	4 areturn (0, 0)

Method: getA3
	0 aload_0 (0, 0)
	1 getfield (0, 0)
	2 org/apache/commons/math3/geometry/euclidean/threed/RotationOrder.a3:Lorg/apache/commons/math3/geometry/euclidean/threed/Vector3D; (0, 0)
	4 areturn (0, 0)

Method: <clinit>
	0 new (0, 0)
	1 org/apache/commons/math3/geometry/euclidean/threed/RotationOrder (0, 0)
	3 dup (0, 0)
	4 ldc (0, 0)
	5 XYZ (0, 0)
	6 getstatic (0, 0)
	7 org/apache/commons/math3/geometry/euclidean/threed/Vector3D.PLUS_I:Lorg/apache/commons/math3/geometry/euclidean/threed/Vector3D; (0, 0)
	9 getstatic (0, 0)
	10 org/apache/commons/math3/geometry/euclidean/threed/Vector3D.PLUS_J:Lorg/apache/commons/math3/geometry/euclidean/threed/Vector3D; (0, 0)
	12 getstatic (0, 0)
	13 org/apache/commons/math3/geometry/euclidean/threed/Vector3D.PLUS_K:Lorg/apache/commons/math3/geometry/euclidean/threed/Vector3D; (0, 0)
	15 invokespecial (0, 0)
	16 org/apache/commons/math3/geometry/euclidean/threed/RotationOrder.<init>:(Ljava/lang/String;Lorg/apache/commons/math3/geometry/euclidean/threed/Vector3D;Lorg/apache/commons/math3/geometry/euclidean/threed/Vector3D;Lorg/apache/commons/math3/geometry/euclidean/threed/Vector3D;)V (0, 0)
	18 putstatic (0, 0)
	19 org/apache/commons/math3/geometry/euclidean/threed/RotationOrder.XYZ:Lorg/apache/commons/math3/geometry/euclidean/threed/RotationOrder; (0, 0)
	21 new (0, 0)
	22 org/apache/commons/math3/geometry/euclidean/threed/RotationOrder (0, 0)
	24 dup (0, 0)
	25 ldc (0, 0)
	26 XZY (0, 0)
	27 getstatic (0, 0)
	28 org/apache/commons/math3/geometry/euclidean/threed/Vector3D.PLUS_I:Lorg/apache/commons/math3/geometry/euclidean/threed/Vector3D; (0, 0)
	30 getstatic (0, 0)
	31 org/apache/commons/math3/geometry/euclidean/threed/Vector3D.PLUS_K:Lorg/apache/commons/math3/geometry/euclidean/threed/Vector3D; (0, 0)
	33 getstatic (0, 0)
	34 org/apache/commons/math3/geometry/euclidean/threed/Vector3D.PLUS_J:Lorg/apache/commons/math3/geometry/euclidean/threed/Vector3D; (0, 0)
	36 invokespecial (0, 0)
	37 org/apache/commons/math3/geometry/euclidean/threed/RotationOrder.<init>:(Ljava/lang/String;Lorg/apache/commons/math3/geometry/euclidean/threed/Vector3D;Lorg/apache/commons/math3/geometry/euclidean/threed/Vector3D;Lorg/apache/commons/math3/geometry/euclidean/threed/Vector3D;)V (0, 0)
	39 putstatic (0, 0)
	40 org/apache/commons/math3/geometry/euclidean/threed/RotationOrder.XZY:Lorg/apache/commons/math3/geometry/euclidean/threed/RotationOrder; (0, 0)
	42 new (0, 0)
	43 org/apache/commons/math3/geometry/euclidean/threed/RotationOrder (0, 0)
	45 dup (0, 0)
	46 ldc (0, 0)
	47 YXZ (0, 0)
	48 getstatic (0, 0)
	49 org/apache/commons/math3/geometry/euclidean/threed/Vector3D.PLUS_J:Lorg/apache/commons/math3/geometry/euclidean/threed/Vector3D; (0, 0)
	51 getstatic (0, 0)
	52 org/apache/commons/math3/geometry/euclidean/threed/Vector3D.PLUS_I:Lorg/apache/commons/math3/geometry/euclidean/threed/Vector3D; (0, 0)
	54 getstatic (0, 0)
	55 org/apache/commons/math3/geometry/euclidean/threed/Vector3D.PLUS_K:Lorg/apache/commons/math3/geometry/euclidean/threed/Vector3D; (0, 0)
	57 invokespecial (0, 0)
	58 org/apache/commons/math3/geometry/euclidean/threed/RotationOrder.<init>:(Ljava/lang/String;Lorg/apache/commons/math3/geometry/euclidean/threed/Vector3D;Lorg/apache/commons/math3/geometry/euclidean/threed/Vector3D;Lorg/apache/commons/math3/geometry/euclidean/threed/Vector3D;)V (0, 0)
	60 putstatic (0, 0)
	61 org/apache/commons/math3/geometry/euclidean/threed/RotationOrder.YXZ:Lorg/apache/commons/math3/geometry/euclidean/threed/RotationOrder; (0, 0)
	63 new (0, 0)
	64 org/apache/commons/math3/geometry/euclidean/threed/RotationOrder (0, 0)
	66 dup (0, 0)
	67 ldc (0, 0)
	68 YZX (0, 0)
	69 getstatic (0, 0)
	70 org/apache/commons/math3/geometry/euclidean/threed/Vector3D.PLUS_J:Lorg/apache/commons/math3/geometry/euclidean/threed/Vector3D; (0, 0)
	72 getstatic (0, 0)
	73 org/apache/commons/math3/geometry/euclidean/threed/Vector3D.PLUS_K:Lorg/apache/commons/math3/geometry/euclidean/threed/Vector3D; (0, 0)
	75 getstatic (0, 0)
	76 org/apache/commons/math3/geometry/euclidean/threed/Vector3D.PLUS_I:Lorg/apache/commons/math3/geometry/euclidean/threed/Vector3D; (0, 0)
	78 invokespecial (0, 0)
	79 org/apache/commons/math3/geometry/euclidean/threed/RotationOrder.<init>:(Ljava/lang/String;Lorg/apache/commons/math3/geometry/euclidean/threed/Vector3D;Lorg/apache/commons/math3/geometry/euclidean/threed/Vector3D;Lorg/apache/commons/math3/geometry/euclidean/threed/Vector3D;)V (0, 0)
	81 putstatic (0, 0)
	82 org/apache/commons/math3/geometry/euclidean/threed/RotationOrder.YZX:Lorg/apache/commons/math3/geometry/euclidean/threed/RotationOrder; (0, 0)
	84 new (0, 0)
	85 org/apache/commons/math3/geometry/euclidean/threed/RotationOrder (0, 0)
	87 dup (0, 0)
	88 ldc (0, 0)
	89 ZXY (0, 0)
	90 getstatic (0, 0)
	91 org/apache/commons/math3/geometry/euclidean/threed/Vector3D.PLUS_K:Lorg/apache/commons/math3/geometry/euclidean/threed/Vector3D; (0, 0)
	93 getstatic (0, 0)
	94 org/apache/commons/math3/geometry/euclidean/threed/Vector3D.PLUS_I:Lorg/apache/commons/math3/geometry/euclidean/threed/Vector3D; (0, 0)
	96 getstatic (0, 0)
	97 org/apache/commons/math3/geometry/euclidean/threed/Vector3D.PLUS_J:Lorg/apache/commons/math3/geometry/euclidean/threed/Vector3D; (0, 0)
	99 invokespecial (0, 0)
	100 org/apache/commons/math3/geometry/euclidean/threed/RotationOrder.<init>:(Ljava/lang/String;Lorg/apache/commons/math3/geometry/euclidean/threed/Vector3D;Lorg/apache/commons/math3/geometry/euclidean/threed/Vector3D;Lorg/apache/commons/math3/geometry/euclidean/threed/Vector3D;)V (0, 0)
	102 putstatic (0, 0)
	103 org/apache/commons/math3/geometry/euclidean/threed/RotationOrder.ZXY:Lorg/apache/commons/math3/geometry/euclidean/threed/RotationOrder; (0, 0)
	105 new (0, 0)
	106 org/apache/commons/math3/geometry/euclidean/threed/RotationOrder (0, 0)
	108 dup (0, 0)
	109 ldc (0, 0)
	110 ZYX (0, 0)
	111 getstatic (0, 0)
	112 org/apache/commons/math3/geometry/euclidean/threed/Vector3D.PLUS_K:Lorg/apache/commons/math3/geometry/euclidean/threed/Vector3D; (0, 0)
	114 getstatic (0, 0)
	115 org/apache/commons/math3/geometry/euclidean/threed/Vector3D.PLUS_J:Lorg/apache/commons/math3/geometry/euclidean/threed/Vector3D; (0, 0)
	117 getstatic (0, 0)
	118 org/apache/commons/math3/geometry/euclidean/threed/Vector3D.PLUS_I:Lorg/apache/commons/math3/geometry/euclidean/threed/Vector3D; (0, 0)
	120 invokespecial (0, 0)
	121 org/apache/commons/math3/geometry/euclidean/threed/RotationOrder.<init>:(Ljava/lang/String;Lorg/apache/commons/math3/geometry/euclidean/threed/Vector3D;Lorg/apache/commons/math3/geometry/euclidean/threed/Vector3D;Lorg/apache/commons/math3/geometry/euclidean/threed/Vector3D;)V (0, 0)
	123 putstatic (0, 0)
	124 org/apache/commons/math3/geometry/euclidean/threed/RotationOrder.ZYX:Lorg/apache/commons/math3/geometry/euclidean/threed/RotationOrder; (0, 0)
	126 new (0, 0)
	127 org/apache/commons/math3/geometry/euclidean/threed/RotationOrder (0, 0)
	129 dup (0, 0)
	130 ldc (0, 0)
	131 XYX (0, 0)
	132 getstatic (0, 0)
	133 org/apache/commons/math3/geometry/euclidean/threed/Vector3D.PLUS_I:Lorg/apache/commons/math3/geometry/euclidean/threed/Vector3D; (0, 0)
	135 getstatic (0, 0)
	136 org/apache/commons/math3/geometry/euclidean/threed/Vector3D.PLUS_J:Lorg/apache/commons/math3/geometry/euclidean/threed/Vector3D; (0, 0)
	138 getstatic (0, 0)
	139 org/apache/commons/math3/geometry/euclidean/threed/Vector3D.PLUS_I:Lorg/apache/commons/math3/geometry/euclidean/threed/Vector3D; (0, 0)
	141 invokespecial (0, 0)
	142 org/apache/commons/math3/geometry/euclidean/threed/RotationOrder.<init>:(Ljava/lang/String;Lorg/apache/commons/math3/geometry/euclidean/threed/Vector3D;Lorg/apache/commons/math3/geometry/euclidean/threed/Vector3D;Lorg/apache/commons/math3/geometry/euclidean/threed/Vector3D;)V (0, 0)
	144 putstatic (0, 0)
	145 org/apache/commons/math3/geometry/euclidean/threed/RotationOrder.XYX:Lorg/apache/commons/math3/geometry/euclidean/threed/RotationOrder; (0, 0)
	147 new (0, 0)
	148 org/apache/commons/math3/geometry/euclidean/threed/RotationOrder (0, 0)
	150 dup (0, 0)
	151 ldc (0, 0)
	152 XZX (0, 0)
	153 getstatic (0, 0)
	154 org/apache/commons/math3/geometry/euclidean/threed/Vector3D.PLUS_I:Lorg/apache/commons/math3/geometry/euclidean/threed/Vector3D; (0, 0)
	156 getstatic (0, 0)
	157 org/apache/commons/math3/geometry/euclidean/threed/Vector3D.PLUS_K:Lorg/apache/commons/math3/geometry/euclidean/threed/Vector3D; (0, 0)
	159 getstatic (0, 0)
	160 org/apache/commons/math3/geometry/euclidean/threed/Vector3D.PLUS_I:Lorg/apache/commons/math3/geometry/euclidean/threed/Vector3D; (0, 0)
	162 invokespecial (0, 0)
	163 org/apache/commons/math3/geometry/euclidean/threed/RotationOrder.<init>:(Ljava/lang/String;Lorg/apache/commons/math3/geometry/euclidean/threed/Vector3D;Lorg/apache/commons/math3/geometry/euclidean/threed/Vector3D;Lorg/apache/commons/math3/geometry/euclidean/threed/Vector3D;)V (0, 0)
	165 putstatic (0, 0)
	166 org/apache/commons/math3/geometry/euclidean/threed/RotationOrder.XZX:Lorg/apache/commons/math3/geometry/euclidean/threed/RotationOrder; (0, 0)
	168 new (0, 0)
	169 org/apache/commons/math3/geometry/euclidean/threed/RotationOrder (0, 0)
	171 dup (0, 0)
	172 ldc (0, 0)
	173 YXY (0, 0)
	174 getstatic (0, 0)
	175 org/apache/commons/math3/geometry/euclidean/threed/Vector3D.PLUS_J:Lorg/apache/commons/math3/geometry/euclidean/threed/Vector3D; (0, 0)
	177 getstatic (0, 0)
	178 org/apache/commons/math3/geometry/euclidean/threed/Vector3D.PLUS_I:Lorg/apache/commons/math3/geometry/euclidean/threed/Vector3D; (0, 0)
	180 getstatic (0, 0)
	181 org/apache/commons/math3/geometry/euclidean/threed/Vector3D.PLUS_J:Lorg/apache/commons/math3/geometry/euclidean/threed/Vector3D; (0, 0)
	183 invokespecial (0, 0)
	184 org/apache/commons/math3/geometry/euclidean/threed/RotationOrder.<init>:(Ljava/lang/String;Lorg/apache/commons/math3/geometry/euclidean/threed/Vector3D;Lorg/apache/commons/math3/geometry/euclidean/threed/Vector3D;Lorg/apache/commons/math3/geometry/euclidean/threed/Vector3D;)V (0, 0)
	186 putstatic (0, 0)
	187 org/apache/commons/math3/geometry/euclidean/threed/RotationOrder.YXY:Lorg/apache/commons/math3/geometry/euclidean/threed/RotationOrder; (0, 0)
	189 new (0, 0)
	190 org/apache/commons/math3/geometry/euclidean/threed/RotationOrder (0, 0)
	192 dup (0, 0)
	193 ldc (0, 0)
	194 YZY (0, 0)
	195 getstatic (0, 0)
	196 org/apache/commons/math3/geometry/euclidean/threed/Vector3D.PLUS_J:Lorg/apache/commons/math3/geometry/euclidean/threed/Vector3D; (0, 0)
	198 getstatic (0, 0)
	199 org/apache/commons/math3/geometry/euclidean/threed/Vector3D.PLUS_K:Lorg/apache/commons/math3/geometry/euclidean/threed/Vector3D; (0, 0)
	201 getstatic (0, 0)
	202 org/apache/commons/math3/geometry/euclidean/threed/Vector3D.PLUS_J:Lorg/apache/commons/math3/geometry/euclidean/threed/Vector3D; (0, 0)
	204 invokespecial (0, 0)
	205 org/apache/commons/math3/geometry/euclidean/threed/RotationOrder.<init>:(Ljava/lang/String;Lorg/apache/commons/math3/geometry/euclidean/threed/Vector3D;Lorg/apache/commons/math3/geometry/euclidean/threed/Vector3D;Lorg/apache/commons/math3/geometry/euclidean/threed/Vector3D;)V (0, 0)
	207 putstatic (0, 0)
	208 org/apache/commons/math3/geometry/euclidean/threed/RotationOrder.YZY:Lorg/apache/commons/math3/geometry/euclidean/threed/RotationOrder; (0, 0)
	210 new (0, 0)
	211 org/apache/commons/math3/geometry/euclidean/threed/RotationOrder (0, 0)
	213 dup (0, 0)
	214 ldc (0, 0)
	215 ZXZ (0, 0)
	216 getstatic (0, 0)
	217 org/apache/commons/math3/geometry/euclidean/threed/Vector3D.PLUS_K:Lorg/apache/commons/math3/geometry/euclidean/threed/Vector3D; (0, 0)
	219 getstatic (0, 0)
	220 org/apache/commons/math3/geometry/euclidean/threed/Vector3D.PLUS_I:Lorg/apache/commons/math3/geometry/euclidean/threed/Vector3D; (0, 0)
	222 getstatic (0, 0)
	223 org/apache/commons/math3/geometry/euclidean/threed/Vector3D.PLUS_K:Lorg/apache/commons/math3/geometry/euclidean/threed/Vector3D; (0, 0)
	225 invokespecial (0, 0)
	226 org/apache/commons/math3/geometry/euclidean/threed/RotationOrder.<init>:(Ljava/lang/String;Lorg/apache/commons/math3/geometry/euclidean/threed/Vector3D;Lorg/apache/commons/math3/geometry/euclidean/threed/Vector3D;Lorg/apache/commons/math3/geometry/euclidean/threed/Vector3D;)V (0, 0)
	228 putstatic (0, 0)
	229 org/apache/commons/math3/geometry/euclidean/threed/RotationOrder.ZXZ:Lorg/apache/commons/math3/geometry/euclidean/threed/RotationOrder; (0, 0)
	231 new (0, 0)
	232 org/apache/commons/math3/geometry/euclidean/threed/RotationOrder (0, 0)
	234 dup (0, 0)
	235 ldc (0, 0)
	236 ZYZ (0, 0)
	237 getstatic (0, 0)
	238 org/apache/commons/math3/geometry/euclidean/threed/Vector3D.PLUS_K:Lorg/apache/commons/math3/geometry/euclidean/threed/Vector3D; (0, 0)
	240 getstatic (0, 0)
	241 org/apache/commons/math3/geometry/euclidean/threed/Vector3D.PLUS_J:Lorg/apache/commons/math3/geometry/euclidean/threed/Vector3D; (0, 0)
	243 getstatic (0, 0)
	244 org/apache/commons/math3/geometry/euclidean/threed/Vector3D.PLUS_K:Lorg/apache/commons/math3/geometry/euclidean/threed/Vector3D; (0, 0)
	246 invokespecial (0, 0)
	247 org/apache/commons/math3/geometry/euclidean/threed/RotationOrder.<init>:(Ljava/lang/String;Lorg/apache/commons/math3/geometry/euclidean/threed/Vector3D;Lorg/apache/commons/math3/geometry/euclidean/threed/Vector3D;Lorg/apache/commons/math3/geometry/euclidean/threed/Vector3D;)V (0, 0)
	249 putstatic (0, 0)
	250 org/apache/commons/math3/geometry/euclidean/threed/RotationOrder.ZYZ:Lorg/apache/commons/math3/geometry/euclidean/threed/RotationOrder; (0, 0)
	252 return (0, 0)

