Method: <init>
	0 aload_0 (0, 0)
	1 invokespecial (0, 0)
	4 aload_0 (0, 0)
	5 aload_1 (0, 0)
	6 putfield (0, 0)
	9 aload_0 (0, 0)
	10 aload_2 (0, 0)
	11 putfield (0, 0)
	14 aload_0 (0, 0)
	15 aload_3 (0, 0)
	16 putfield (0, 0)
	19 aload_0 (0, 0)
	20 aload (0, 0)
	22 putfield (0, 0)
	25 return (0, 0)

Method: toString
	0 aload_0 (0, 0)
	1 getfield (0, 0)
	4 areturn (0, 0)

Method: getA1
	0 aload_0 (0, 0)
	1 getfield (0, 0)
	4 areturn (0, 0)

Method: getA2
	0 aload_0 (0, 0)
	1 getfield (0, 0)
	4 areturn (0, 0)

Method: getA3
	0 aload_0 (0, 0)
	1 getfield (0, 0)
	4 areturn (0, 0)

Method: <clinit>
	0 new (0, 0)
	3 dup (0, 0)
	4 ldc (0, 0)
	6 getstatic (0, 0)
	9 getstatic (0, 0)
	12 getstatic (0, 0)
	15 invokespecial (0, 0)
	18 putstatic (0, 0)
	21 new (0, 0)
	24 dup (0, 0)
	25 ldc (0, 0)
	27 getstatic (0, 0)
	30 getstatic (0, 0)
	33 getstatic (0, 0)
	36 invokespecial (0, 0)
	39 putstatic (0, 0)
	42 new (0, 0)
	45 dup (0, 0)
	46 ldc (0, 0)
	48 getstatic (0, 0)
	51 getstatic (0, 0)
	54 getstatic (0, 0)
	57 invokespecial (0, 0)
	60 putstatic (0, 0)
	63 new (0, 0)
	66 dup (0, 0)
	67 ldc (0, 0)
	69 getstatic (0, 0)
	72 getstatic (0, 0)
	75 getstatic (0, 0)
	78 invokespecial (0, 0)
	81 putstatic (0, 0)
	84 new (0, 0)
	87 dup (0, 0)
	88 ldc (0, 0)
	90 getstatic (0, 0)
	93 getstatic (0, 0)
	96 getstatic (0, 0)
	99 invokespecial (0, 0)
	102 putstatic (0, 0)
	105 new (0, 0)
	108 dup (0, 0)
	109 ldc (0, 0)
	111 getstatic (0, 0)
	114 getstatic (0, 0)
	117 getstatic (0, 0)
	120 invokespecial (0, 0)
	123 putstatic (0, 0)
	126 new (0, 0)
	129 dup (0, 0)
	130 ldc (0, 0)
	132 getstatic (0, 0)
	135 getstatic (0, 0)
	138 getstatic (0, 0)
	141 invokespecial (0, 0)
	144 putstatic (0, 0)
	147 new (0, 0)
	150 dup (0, 0)
	151 ldc (0, 0)
	153 getstatic (0, 0)
	156 getstatic (0, 0)
	159 getstatic (0, 0)
	162 invokespecial (0, 0)
	165 putstatic (0, 0)
	168 new (0, 0)
	171 dup (0, 0)
	172 ldc (0, 0)
	174 getstatic (0, 0)
	177 getstatic (0, 0)
	180 getstatic (0, 0)
	183 invokespecial (0, 0)
	186 putstatic (0, 0)
	189 new (0, 0)
	192 dup (0, 0)
	193 ldc (0, 0)
	195 getstatic (0, 0)
	198 getstatic (0, 0)
	201 getstatic (0, 0)
	204 invokespecial (0, 0)
	207 putstatic (0, 0)
	210 new (0, 0)
	213 dup (0, 0)
	214 ldc (0, 0)
	216 getstatic (0, 0)
	219 getstatic (0, 0)
	222 getstatic (0, 0)
	225 invokespecial (0, 0)
	228 putstatic (0, 0)
	231 new (0, 0)
	234 dup (0, 0)
	235 ldc (0, 0)
	237 getstatic (0, 0)
	240 getstatic (0, 0)
	243 getstatic (0, 0)
	246 invokespecial (0, 0)
	249 putstatic (0, 0)
	252 return (0, 0)

