Method: <init>
	0 aload_0 (0, 0)
	1 invokespecial (0, 0)
	2 java/lang/Object.<init>:()V (0, 0)
	4 aload_0 (0, 0)
	5 aload_1 (0, 0)
	6 putfield (0, 0)
	7 org/apache/commons/math3/geometry/euclidean/threed/Segment.start:Lorg/apache/commons/math3/geometry/euclidean/threed/Vector3D; (0, 0)
	9 aload_0 (0, 0)
	10 aload_2 (0, 0)
	11 putfield (0, 0)
	12 org/apache/commons/math3/geometry/euclidean/threed/Segment.end:Lorg/apache/commons/math3/geometry/euclidean/threed/Vector3D; (0, 0)
	14 aload_0 (0, 0)
	15 aload_3 (0, 0)
	16 putfield (0, 0)
	17 org/apache/commons/math3/geometry/euclidean/threed/Segment.line:Lorg/apache/commons/math3/geometry/euclidean/threed/Line; (0, 0)
	19 return (0, 0)

Method: getStart
	0 aload_0 (0, 0)
	1 getfield (0, 0)
	2 org/apache/commons/math3/geometry/euclidean/threed/Segment.start:Lorg/apache/commons/math3/geometry/euclidean/threed/Vector3D; (0, 0)
	4 areturn (0, 0)

Method: getEnd
	0 aload_0 (0, 0)
	1 getfield (0, 0)
	2 org/apache/commons/math3/geometry/euclidean/threed/Segment.end:Lorg/apache/commons/math3/geometry/euclidean/threed/Vector3D; (0, 0)
	4 areturn (0, 0)

Method: getLine
	0 aload_0 (0, 0)
	1 getfield (0, 0)
	2 org/apache/commons/math3/geometry/euclidean/threed/Segment.line:Lorg/apache/commons/math3/geometry/euclidean/threed/Line; (0, 0)
	4 areturn (0, 0)

