Method: <init>
	0 aload_0 (0, 0)
	1 invokespecial (0, 0)
	2 java/lang/Object.<init>:()V (0, 0)
	4 dload_3 (0, 0)
	5 invokestatic (0, 0)
	6 org/apache/commons/math3/util/FastMath.cos:(D)D (0, 0)
	8 dstore (0, 0)
	9 #7 (0, 0)
	10 dload_3 (0, 0)
	11 invokestatic (0, 0)
	12 org/apache/commons/math3/util/FastMath.sin:(D)D (0, 0)
	14 dstore (0, 0)
	15 #9 (0, 0)
	16 dload (0, 0)
	17 #5 (0, 0)
	18 invokestatic (0, 0)
	19 org/apache/commons/math3/util/FastMath.cos:(D)D (0, 0)
	21 dstore (0, 0)
	22 #11 (0, 0)
	23 dload (0, 0)
	24 #5 (0, 0)
	25 invokestatic (0, 0)
	26 org/apache/commons/math3/util/FastMath.sin:(D)D (0, 0)
	28 dstore (0, 0)
	29 #13 (0, 0)
	30 aload_0 (0, 0)
	31 dload_1 (0, 0)
	32 putfield (0, 0)
	33 org/apache/commons/math3/geometry/euclidean/threed/SphericalCoordinates.r:D (0, 0)
	35 aload_0 (0, 0)
	36 dload_3 (0, 0)
	37 putfield (0, 0)
	38 org/apache/commons/math3/geometry/euclidean/threed/SphericalCoordinates.theta:D (0, 0)
	40 aload_0 (0, 0)
	41 dload (0, 0)
	42 #5 (0, 0)
	43 putfield (0, 0)
	44 org/apache/commons/math3/geometry/euclidean/threed/SphericalCoordinates.phi:D (0, 0)
	46 aload_0 (0, 0)
	47 new (0, 0)
	48 org/apache/commons/math3/geometry/euclidean/threed/Vector3D (0, 0)
	50 dup (0, 0)
	51 dload_1 (0, 0)
	52 dload (0, 0)
	53 #7 (0, 0)
	54 dmul (0, 0)
	55 dload (0, 0)
	56 #13 (0, 0)
	57 dmul (0, 0)
	58 dload_1 (0, 0)
	59 dload (0, 0)
	60 #9 (0, 0)
	61 dmul (0, 0)
	62 dload (0, 0)
	63 #13 (0, 0)
	64 dmul (0, 0)
	65 dload_1 (0, 0)
	66 dload (0, 0)
	67 #11 (0, 0)
	68 dmul (0, 0)
	69 invokespecial (0, 0)
	70 org/apache/commons/math3/geometry/euclidean/threed/Vector3D.<init>:(DDD)V (0, 0)
	72 putfield (0, 0)
	73 org/apache/commons/math3/geometry/euclidean/threed/SphericalCoordinates.v:Lorg/apache/commons/math3/geometry/euclidean/threed/Vector3D; (0, 0)
	75 return (0, 0)

Method: getCartesian
	0 aload_0 (0, 0)
	1 getfield (0, 0)
	2 org/apache/commons/math3/geometry/euclidean/threed/SphericalCoordinates.v:Lorg/apache/commons/math3/geometry/euclidean/threed/Vector3D; (0, 0)
	4 areturn (0, 0)

Method: getR
	0 aload_0 (0, 0)
	1 getfield (0, 0)
	2 org/apache/commons/math3/geometry/euclidean/threed/SphericalCoordinates.r:D (0, 0)
	4 dreturn (0, 0)

Method: getTheta
	0 aload_0 (0, 0)
	1 getfield (0, 0)
	2 org/apache/commons/math3/geometry/euclidean/threed/SphericalCoordinates.theta:D (0, 0)
	4 dreturn (0, 0)

Method: getPhi
	0 aload_0 (0, 0)
	1 getfield (0, 0)
	2 org/apache/commons/math3/geometry/euclidean/threed/SphericalCoordinates.phi:D (0, 0)
	4 dreturn (0, 0)

Method: toCartesianGradient
	0 aload_0 (0, 0)
	1 invokespecial (0, 0)
	2 org/apache/commons/math3/geometry/euclidean/threed/SphericalCoordinates.computeJacobian:()V (0, 0)
	4 iconst_3 (0, 1)
	5 newarray (0, 1)
	6 7 (0, 1)
	7 dup (0, 1)
	8 iconst_0 (0, 1)
	9 aload_1 (0, 1)
	10 iconst_0 (0, 1)
	11 daload (0, 1)
	12 aload_0 (0, 1)
	13 getfield (0, 1)
	14 org/apache/commons/math3/geometry/euclidean/threed/SphericalCoordinates.jacobian:[[D (0, 1)
	16 iconst_0 (0, 1)
	17 aaload (0, 1)
	18 iconst_0 (0, 1)
	19 daload (0, 1)
	20 dmul (0, 1)
	21 aload_1 (0, 1)
	22 iconst_1 (0, 1)
	23 daload (0, 1)
	24 aload_0 (0, 1)
	25 getfield (0, 1)
	26 org/apache/commons/math3/geometry/euclidean/threed/SphericalCoordinates.jacobian:[[D (0, 1)
	28 iconst_1 (0, 1)
	29 aaload (0, 1)
	30 iconst_0 (0, 1)
	31 daload (0, 1)
	32 dmul (0, 1)
	33 dadd (0, 1)
	34 aload_1 (0, 1)
	35 iconst_2 (0, 1)
	36 daload (0, 1)
	37 aload_0 (0, 1)
	38 getfield (0, 1)
	39 org/apache/commons/math3/geometry/euclidean/threed/SphericalCoordinates.jacobian:[[D (0, 1)
	41 iconst_2 (0, 1)
	42 aaload (0, 1)
	43 iconst_0 (0, 1)
	44 daload (0, 1)
	45 dmul (0, 1)
	46 dadd (0, 1)
	47 dastore (0, 1)
	48 dup (0, 1)
	49 iconst_1 (0, 1)
	50 aload_1 (0, 1)
	51 iconst_0 (0, 1)
	52 daload (0, 1)
	53 aload_0 (0, 1)
	54 getfield (0, 1)
	55 org/apache/commons/math3/geometry/euclidean/threed/SphericalCoordinates.jacobian:[[D (0, 1)
	57 iconst_0 (0, 1)
	58 aaload (0, 1)
	59 iconst_1 (0, 1)
	60 daload (0, 1)
	61 dmul (0, 1)
	62 aload_1 (0, 1)
	63 iconst_1 (0, 1)
	64 daload (0, 1)
	65 aload_0 (0, 1)
	66 getfield (0, 1)
	67 org/apache/commons/math3/geometry/euclidean/threed/SphericalCoordinates.jacobian:[[D (0, 1)
	69 iconst_1 (0, 1)
	70 aaload (0, 1)
	71 iconst_1 (0, 1)
	72 daload (0, 1)
	73 dmul (0, 1)
	74 dadd (0, 1)
	75 aload_1 (0, 1)
	76 iconst_2 (0, 1)
	77 daload (0, 1)
	78 aload_0 (0, 1)
	79 getfield (0, 1)
	80 org/apache/commons/math3/geometry/euclidean/threed/SphericalCoordinates.jacobian:[[D (0, 1)
	82 iconst_2 (0, 1)
	83 aaload (0, 1)
	84 iconst_1 (0, 1)
	85 daload (0, 1)
	86 dmul (0, 1)
	87 dadd (0, 1)
	88 dastore (0, 1)
	89 dup (0, 1)
	90 iconst_2 (0, 1)
	91 aload_1 (0, 1)
	92 iconst_0 (0, 1)
	93 daload (0, 1)
	94 aload_0 (0, 1)
	95 getfield (0, 1)
	96 org/apache/commons/math3/geometry/euclidean/threed/SphericalCoordinates.jacobian:[[D (0, 1)
	98 iconst_0 (0, 1)
	99 aaload (0, 1)
	100 iconst_2 (0, 1)
	101 daload (0, 1)
	102 dmul (0, 1)
	103 aload_1 (0, 1)
	104 iconst_2 (0, 1)
	105 daload (0, 1)
	106 aload_0 (0, 1)
	107 getfield (0, 1)
	108 org/apache/commons/math3/geometry/euclidean/threed/SphericalCoordinates.jacobian:[[D (0, 1)
	110 iconst_2 (0, 1)
	111 aaload (0, 1)
	112 iconst_2 (0, 1)
	113 daload (0, 1)
	114 dmul (0, 1)
	115 dadd (0, 1)
	116 dastore (0, 1)
	117 areturn (0, 1)

Method: toCartesianHessian
	0 aload_0 (0, 0)
	1 invokespecial (0, 0)
	2 org/apache/commons/math3/geometry/euclidean/threed/SphericalCoordinates.computeJacobian:()V (0, 0)
	4 aload_0 (0, 0)
	5 invokespecial (0, 0)
	6 org/apache/commons/math3/geometry/euclidean/threed/SphericalCoordinates.computeHessians:()V (0, 0)
	8 iconst_3 (0, 1)
	9 iconst_3 (0, 1)
	10 multianewarray (0, 1)
	11 [[D (0, 1)
	13 78 (0, 1)
	14 astore_3 (0, 1)
	15 iconst_3 (0, 1)
	16 iconst_3 (0, 1)
	17 multianewarray (0, 1)
	18 [[D (0, 1)
	20 58 (0, 1)
	21 astore (0, 1)
	22 #4 (0, 1)
	23 aload_3 (0, 1)
	24 iconst_0 (0, 1)
	25 aaload (0, 1)
	26 iconst_0 (0, 1)
	27 aload_1 (0, 1)
	28 iconst_0 (0, 1)
	29 aaload (0, 1)
	30 iconst_0 (0, 1)
	31 daload (0, 1)
	32 aload_0 (0, 1)
	33 getfield (0, 1)
	34 org/apache/commons/math3/geometry/euclidean/threed/SphericalCoordinates.jacobian:[[D (0, 1)
	36 iconst_0 (0, 1)
	37 aaload (0, 1)
	38 iconst_0 (0, 1)
	39 daload (0, 1)
	40 dmul (0, 1)
	41 aload_1 (0, 1)
	42 iconst_1 (0, 1)
	43 aaload (0, 1)
	44 iconst_0 (0, 1)
	45 daload (0, 1)
	46 aload_0 (0, 1)
	47 getfield (0, 1)
	48 org/apache/commons/math3/geometry/euclidean/threed/SphericalCoordinates.jacobian:[[D (0, 1)
	50 iconst_1 (0, 1)
	51 aaload (0, 1)
	52 iconst_0 (0, 1)
	53 daload (0, 1)
	54 dmul (0, 1)
	55 dadd (0, 1)
	56 aload_1 (0, 1)
	57 iconst_2 (0, 1)
	58 aaload (0, 1)
	59 iconst_0 (0, 1)
	60 daload (0, 1)
	61 aload_0 (0, 1)
	62 getfield (0, 1)
	63 org/apache/commons/math3/geometry/euclidean/threed/SphericalCoordinates.jacobian:[[D (0, 1)
	65 iconst_2 (0, 1)
	66 aaload (0, 1)
	67 iconst_0 (0, 1)
	68 daload (0, 1)
	69 dmul (0, 1)
	70 dadd (0, 1)
	71 dastore (0, 1)
	72 aload_3 (0, 1)
	73 iconst_0 (0, 1)
	74 aaload (0, 1)
	75 iconst_1 (0, 1)
	76 aload_1 (0, 1)
	77 iconst_0 (0, 1)
	78 aaload (0, 1)
	79 iconst_0 (0, 1)
	80 daload (0, 1)
	81 aload_0 (0, 1)
	82 getfield (0, 1)
	83 org/apache/commons/math3/geometry/euclidean/threed/SphericalCoordinates.jacobian:[[D (0, 1)
	85 iconst_0 (0, 1)
	86 aaload (0, 1)
	87 iconst_1 (0, 1)
	88 daload (0, 1)
	89 dmul (0, 1)
	90 aload_1 (0, 1)
	91 iconst_1 (0, 1)
	92 aaload (0, 1)
	93 iconst_0 (0, 1)
	94 daload (0, 1)
	95 aload_0 (0, 1)
	96 getfield (0, 1)
	97 org/apache/commons/math3/geometry/euclidean/threed/SphericalCoordinates.jacobian:[[D (0, 1)
	99 iconst_1 (0, 1)
	100 aaload (0, 1)
	101 iconst_1 (0, 1)
	102 daload (0, 1)
	103 dmul (0, 1)
	104 dadd (0, 1)
	105 aload_1 (0, 1)
	106 iconst_2 (0, 1)
	107 aaload (0, 1)
	108 iconst_0 (0, 1)
	109 daload (0, 1)
	110 aload_0 (0, 1)
	111 getfield (0, 1)
	112 org/apache/commons/math3/geometry/euclidean/threed/SphericalCoordinates.jacobian:[[D (0, 1)
	114 iconst_2 (0, 1)
	115 aaload (0, 1)
	116 iconst_1 (0, 1)
	117 daload (0, 1)
	118 dmul (0, 1)
	119 dadd (0, 1)
	120 dastore (0, 1)
	121 aload_3 (0, 1)
	122 iconst_0 (0, 1)
	123 aaload (0, 1)
	124 iconst_2 (0, 1)
	125 aload_1 (0, 1)
	126 iconst_0 (0, 1)
	127 aaload (0, 1)
	128 iconst_0 (0, 1)
	129 daload (0, 1)
	130 aload_0 (0, 1)
	131 getfield (0, 1)
	132 org/apache/commons/math3/geometry/euclidean/threed/SphericalCoordinates.jacobian:[[D (0, 1)
	134 iconst_0 (0, 1)
	135 aaload (0, 1)
	136 iconst_2 (0, 1)
	137 daload (0, 1)
	138 dmul (0, 1)
	139 aload_1 (0, 1)
	140 iconst_2 (0, 1)
	141 aaload (0, 1)
	142 iconst_0 (0, 1)
	143 daload (0, 1)
	144 aload_0 (0, 1)
	145 getfield (0, 1)
	146 org/apache/commons/math3/geometry/euclidean/threed/SphericalCoordinates.jacobian:[[D (0, 1)
	148 iconst_2 (0, 1)
	149 aaload (0, 1)
	150 iconst_2 (0, 1)
	151 daload (0, 1)
	152 dmul (0, 1)
	153 dadd (0, 1)
	154 dastore (0, 1)
	155 aload_3 (0, 1)
	156 iconst_1 (0, 1)
	157 aaload (0, 1)
	158 iconst_0 (0, 1)
	159 aload_1 (0, 1)
	160 iconst_1 (0, 1)
	161 aaload (0, 1)
	162 iconst_0 (0, 1)
	163 daload (0, 1)
	164 aload_0 (0, 1)
	165 getfield (0, 1)
	166 org/apache/commons/math3/geometry/euclidean/threed/SphericalCoordinates.jacobian:[[D (0, 1)
	168 iconst_0 (0, 1)
	169 aaload (0, 1)
	170 iconst_0 (0, 1)
	171 daload (0, 1)
	172 dmul (0, 1)
	173 aload_1 (0, 1)
	174 iconst_1 (0, 1)
	175 aaload (0, 1)
	176 iconst_1 (0, 1)
	177 daload (0, 1)
	178 aload_0 (0, 1)
	179 getfield (0, 1)
	180 org/apache/commons/math3/geometry/euclidean/threed/SphericalCoordinates.jacobian:[[D (0, 1)
	182 iconst_1 (0, 1)
	183 aaload (0, 1)
	184 iconst_0 (0, 1)
	185 daload (0, 1)
	186 dmul (0, 1)
	187 dadd (0, 1)
	188 aload_1 (0, 1)
	189 iconst_2 (0, 1)
	190 aaload (0, 1)
	191 iconst_1 (0, 1)
	192 daload (0, 1)
	193 aload_0 (0, 1)
	194 getfield (0, 1)
	195 org/apache/commons/math3/geometry/euclidean/threed/SphericalCoordinates.jacobian:[[D (0, 1)
	197 iconst_2 (0, 1)
	198 aaload (0, 1)
	199 iconst_0 (0, 1)
	200 daload (0, 1)
	201 dmul (0, 1)
	202 dadd (0, 1)
	203 dastore (0, 1)
	204 aload_3 (0, 1)
	205 iconst_1 (0, 1)
	206 aaload (0, 1)
	207 iconst_1 (0, 1)
	208 aload_1 (0, 1)
	209 iconst_1 (0, 1)
	210 aaload (0, 1)
	211 iconst_0 (0, 1)
	212 daload (0, 1)
	213 aload_0 (0, 1)
	214 getfield (0, 1)
	215 org/apache/commons/math3/geometry/euclidean/threed/SphericalCoordinates.jacobian:[[D (0, 1)
	217 iconst_0 (0, 1)
	218 aaload (0, 1)
	219 iconst_1 (0, 1)
	220 daload (0, 1)
	221 dmul (0, 1)
	222 aload_1 (0, 1)
	223 iconst_1 (0, 1)
	224 aaload (0, 1)
	225 iconst_1 (0, 1)
	226 daload (0, 1)
	227 aload_0 (0, 1)
	228 getfield (0, 1)
	229 org/apache/commons/math3/geometry/euclidean/threed/SphericalCoordinates.jacobian:[[D (0, 1)
	231 iconst_1 (0, 1)
	232 aaload (0, 1)
	233 iconst_1 (0, 1)
	234 daload (0, 1)
	235 dmul (0, 1)
	236 dadd (0, 1)
	237 aload_1 (0, 1)
	238 iconst_2 (0, 1)
	239 aaload (0, 1)
	240 iconst_1 (0, 1)
	241 daload (0, 1)
	242 aload_0 (0, 1)
	243 getfield (0, 1)
	244 org/apache/commons/math3/geometry/euclidean/threed/SphericalCoordinates.jacobian:[[D (0, 1)
	246 iconst_2 (0, 1)
	247 aaload (0, 1)
	248 iconst_1 (0, 1)
	249 daload (0, 1)
	250 dmul (0, 1)
	251 dadd (0, 1)
	252 dastore (0, 1)
	253 aload_3 (0, 1)
	254 iconst_2 (0, 1)
	255 aaload (0, 1)
	256 iconst_0 (0, 1)
	257 aload_1 (0, 1)
	258 iconst_2 (0, 1)
	259 aaload (0, 1)
	260 iconst_0 (0, 1)
	261 daload (0, 1)
	262 aload_0 (0, 1)
	263 getfield (0, 1)
	264 org/apache/commons/math3/geometry/euclidean/threed/SphericalCoordinates.jacobian:[[D (0, 1)
	266 iconst_0 (0, 1)
	267 aaload (0, 1)
	268 iconst_0 (0, 1)
	269 daload (0, 1)
	270 dmul (0, 1)
	271 aload_1 (0, 1)
	272 iconst_2 (0, 1)
	273 aaload (0, 1)
	274 iconst_1 (0, 1)
	275 daload (0, 1)
	276 aload_0 (0, 1)
	277 getfield (0, 1)
	278 org/apache/commons/math3/geometry/euclidean/threed/SphericalCoordinates.jacobian:[[D (0, 1)
	280 iconst_1 (0, 1)
	281 aaload (0, 1)
	282 iconst_0 (0, 1)
	283 daload (0, 1)
	284 dmul (0, 1)
	285 dadd (0, 1)
	286 aload_1 (0, 1)
	287 iconst_2 (0, 1)
	288 aaload (0, 1)
	289 iconst_2 (0, 1)
	290 daload (0, 1)
	291 aload_0 (0, 1)
	292 getfield (0, 1)
	293 org/apache/commons/math3/geometry/euclidean/threed/SphericalCoordinates.jacobian:[[D (0, 1)
	295 iconst_2 (0, 1)
	296 aaload (0, 1)
	297 iconst_0 (0, 1)
	298 daload (0, 1)
	299 dmul (0, 1)
	300 dadd (0, 1)
	301 dastore (0, 1)
	302 aload_3 (0, 1)
	303 iconst_2 (0, 1)
	304 aaload (0, 1)
	305 iconst_1 (0, 1)
	306 aload_1 (0, 1)
	307 iconst_2 (0, 1)
	308 aaload (0, 1)
	309 iconst_0 (0, 1)
	310 daload (0, 1)
	311 aload_0 (0, 1)
	312 getfield (0, 1)
	313 org/apache/commons/math3/geometry/euclidean/threed/SphericalCoordinates.jacobian:[[D (0, 1)
	315 iconst_0 (0, 1)
	316 aaload (0, 1)
	317 iconst_1 (0, 1)
	318 daload (0, 1)
	319 dmul (0, 1)
	320 aload_1 (0, 1)
	321 iconst_2 (0, 1)
	322 aaload (0, 1)
	323 iconst_1 (0, 1)
	324 daload (0, 1)
	325 aload_0 (0, 1)
	326 getfield (0, 1)
	327 org/apache/commons/math3/geometry/euclidean/threed/SphericalCoordinates.jacobian:[[D (0, 1)
	329 iconst_1 (0, 1)
	330 aaload (0, 1)
	331 iconst_1 (0, 1)
	332 daload (0, 1)
	333 dmul (0, 1)
	334 dadd (0, 1)
	335 aload_1 (0, 1)
	336 iconst_2 (0, 1)
	337 aaload (0, 1)
	338 iconst_2 (0, 1)
	339 daload (0, 1)
	340 aload_0 (0, 1)
	341 getfield (0, 1)
	342 org/apache/commons/math3/geometry/euclidean/threed/SphericalCoordinates.jacobian:[[D (0, 1)
	344 iconst_2 (0, 1)
	345 aaload (0, 1)
	346 iconst_1 (0, 1)
	347 daload (0, 1)
	348 dmul (0, 1)
	349 dadd (0, 1)
	350 dastore (0, 1)
	351 aload_3 (0, 1)
	352 iconst_2 (0, 1)
	353 aaload (0, 1)
	354 iconst_2 (0, 1)
	355 aload_1 (0, 1)
	356 iconst_2 (0, 1)
	357 aaload (0, 1)
	358 iconst_0 (0, 1)
	359 daload (0, 1)
	360 aload_0 (0, 1)
	361 getfield (0, 1)
	362 org/apache/commons/math3/geometry/euclidean/threed/SphericalCoordinates.jacobian:[[D (0, 1)
	364 iconst_0 (0, 1)
	365 aaload (0, 1)
	366 iconst_2 (0, 1)
	367 daload (0, 1)
	368 dmul (0, 1)
	369 aload_1 (0, 1)
	370 iconst_2 (0, 1)
	371 aaload (0, 1)
	372 iconst_2 (0, 1)
	373 daload (0, 1)
	374 aload_0 (0, 1)
	375 getfield (0, 1)
	376 org/apache/commons/math3/geometry/euclidean/threed/SphericalCoordinates.jacobian:[[D (0, 1)
	378 iconst_2 (0, 1)
	379 aaload (0, 1)
	380 iconst_2 (0, 1)
	381 daload (0, 1)
	382 dmul (0, 1)
	383 dadd (0, 1)
	384 dastore (0, 1)
	385 aload (0, 1)
	386 #4 (0, 1)
	387 iconst_0 (0, 1)
	388 aaload (0, 1)
	389 iconst_0 (0, 1)
	390 aload_0 (0, 1)
	391 getfield (0, 1)
	392 org/apache/commons/math3/geometry/euclidean/threed/SphericalCoordinates.jacobian:[[D (0, 1)
	394 iconst_0 (0, 1)
	395 aaload (0, 1)
	396 iconst_0 (0, 1)
	397 daload (0, 1)
	398 aload_3 (0, 1)
	399 iconst_0 (0, 1)
	400 aaload (0, 1)
	401 iconst_0 (0, 1)
	402 daload (0, 1)
	403 dmul (0, 1)
	404 aload_0 (0, 1)
	405 getfield (0, 1)
	406 org/apache/commons/math3/geometry/euclidean/threed/SphericalCoordinates.jacobian:[[D (0, 1)
	408 iconst_1 (0, 1)
	409 aaload (0, 1)
	410 iconst_0 (0, 1)
	411 daload (0, 1)
	412 aload_3 (0, 1)
	413 iconst_1 (0, 1)
	414 aaload (0, 1)
	415 iconst_0 (0, 1)
	416 daload (0, 1)
	417 dmul (0, 1)
	418 dadd (0, 1)
	419 aload_0 (0, 1)
	420 getfield (0, 1)
	421 org/apache/commons/math3/geometry/euclidean/threed/SphericalCoordinates.jacobian:[[D (0, 1)
	423 iconst_2 (0, 1)
	424 aaload (0, 1)
	425 iconst_0 (0, 1)
	426 daload (0, 1)
	427 aload_3 (0, 1)
	428 iconst_2 (0, 1)
	429 aaload (0, 1)
	430 iconst_0 (0, 1)
	431 daload (0, 1)
	432 dmul (0, 1)
	433 dadd (0, 1)
	434 dastore (0, 1)
	435 aload (0, 1)
	436 #4 (0, 1)
	437 iconst_1 (0, 1)
	438 aaload (0, 1)
	439 iconst_0 (0, 1)
	440 aload_0 (0, 1)
	441 getfield (0, 1)
	442 org/apache/commons/math3/geometry/euclidean/threed/SphericalCoordinates.jacobian:[[D (0, 1)
	444 iconst_0 (0, 1)
	445 aaload (0, 1)
	446 iconst_1 (0, 1)
	447 daload (0, 1)
	448 aload_3 (0, 1)
	449 iconst_0 (0, 1)
	450 aaload (0, 1)
	451 iconst_0 (0, 1)
	452 daload (0, 1)
	453 dmul (0, 1)
	454 aload_0 (0, 1)
	455 getfield (0, 1)
	456 org/apache/commons/math3/geometry/euclidean/threed/SphericalCoordinates.jacobian:[[D (0, 1)
	458 iconst_1 (0, 1)
	459 aaload (0, 1)
	460 iconst_1 (0, 1)
	461 daload (0, 1)
	462 aload_3 (0, 1)
	463 iconst_1 (0, 1)
	464 aaload (0, 1)
	465 iconst_0 (0, 1)
	466 daload (0, 1)
	467 dmul (0, 1)
	468 dadd (0, 1)
	469 aload_0 (0, 1)
	470 getfield (0, 1)
	471 org/apache/commons/math3/geometry/euclidean/threed/SphericalCoordinates.jacobian:[[D (0, 1)
	473 iconst_2 (0, 1)
	474 aaload (0, 1)
	475 iconst_1 (0, 1)
	476 daload (0, 1)
	477 aload_3 (0, 1)
	478 iconst_2 (0, 1)
	479 aaload (0, 1)
	480 iconst_0 (0, 1)
	481 daload (0, 1)
	482 dmul (0, 1)
	483 dadd (0, 1)
	484 dastore (0, 1)
	485 aload (0, 1)
	486 #4 (0, 1)
	487 iconst_2 (0, 1)
	488 aaload (0, 1)
	489 iconst_0 (0, 1)
	490 aload_0 (0, 1)
	491 getfield (0, 1)
	492 org/apache/commons/math3/geometry/euclidean/threed/SphericalCoordinates.jacobian:[[D (0, 1)
	494 iconst_0 (0, 1)
	495 aaload (0, 1)
	496 iconst_2 (0, 1)
	497 daload (0, 1)
	498 aload_3 (0, 1)
	499 iconst_0 (0, 1)
	500 aaload (0, 1)
	501 iconst_0 (0, 1)
	502 daload (0, 1)
	503 dmul (0, 1)
	504 aload_0 (0, 1)
	505 getfield (0, 1)
	506 org/apache/commons/math3/geometry/euclidean/threed/SphericalCoordinates.jacobian:[[D (0, 1)
	508 iconst_2 (0, 1)
	509 aaload (0, 1)
	510 iconst_2 (0, 1)
	511 daload (0, 1)
	512 aload_3 (0, 1)
	513 iconst_2 (0, 1)
	514 aaload (0, 1)
	515 iconst_0 (0, 1)
	516 daload (0, 1)
	517 dmul (0, 1)
	518 dadd (0, 1)
	519 dastore (0, 1)
	520 aload (0, 1)
	521 #4 (0, 1)
	522 iconst_1 (0, 1)
	523 aaload (0, 1)
	524 iconst_1 (0, 1)
	525 aload_0 (0, 1)
	526 getfield (0, 1)
	527 org/apache/commons/math3/geometry/euclidean/threed/SphericalCoordinates.jacobian:[[D (0, 1)
	529 iconst_0 (0, 1)
	530 aaload (0, 1)
	531 iconst_1 (0, 1)
	532 daload (0, 1)
	533 aload_3 (0, 1)
	534 iconst_0 (0, 1)
	535 aaload (0, 1)
	536 iconst_1 (0, 1)
	537 daload (0, 1)
	538 dmul (0, 1)
	539 aload_0 (0, 1)
	540 getfield (0, 1)
	541 org/apache/commons/math3/geometry/euclidean/threed/SphericalCoordinates.jacobian:[[D (0, 1)
	543 iconst_1 (0, 1)
	544 aaload (0, 1)
	545 iconst_1 (0, 1)
	546 daload (0, 1)
	547 aload_3 (0, 1)
	548 iconst_1 (0, 1)
	549 aaload (0, 1)
	550 iconst_1 (0, 1)
	551 daload (0, 1)
	552 dmul (0, 1)
	553 dadd (0, 1)
	554 aload_0 (0, 1)
	555 getfield (0, 1)
	556 org/apache/commons/math3/geometry/euclidean/threed/SphericalCoordinates.jacobian:[[D (0, 1)
	558 iconst_2 (0, 1)
	559 aaload (0, 1)
	560 iconst_1 (0, 1)
	561 daload (0, 1)
	562 aload_3 (0, 1)
	563 iconst_2 (0, 1)
	564 aaload (0, 1)
	565 iconst_1 (0, 1)
	566 daload (0, 1)
	567 dmul (0, 1)
	568 dadd (0, 1)
	569 dastore (0, 1)
	570 aload (0, 1)
	571 #4 (0, 1)
	572 iconst_2 (0, 1)
	573 aaload (0, 1)
	574 iconst_1 (0, 1)
	575 aload_0 (0, 1)
	576 getfield (0, 1)
	577 org/apache/commons/math3/geometry/euclidean/threed/SphericalCoordinates.jacobian:[[D (0, 1)
	579 iconst_0 (0, 1)
	580 aaload (0, 1)
	581 iconst_2 (0, 1)
	582 daload (0, 1)
	583 aload_3 (0, 1)
	584 iconst_0 (0, 1)
	585 aaload (0, 1)
	586 iconst_1 (0, 1)
	587 daload (0, 1)
	588 dmul (0, 1)
	589 aload_0 (0, 1)
	590 getfield (0, 1)
	591 org/apache/commons/math3/geometry/euclidean/threed/SphericalCoordinates.jacobian:[[D (0, 1)
	593 iconst_2 (0, 1)
	594 aaload (0, 1)
	595 iconst_2 (0, 1)
	596 daload (0, 1)
	597 aload_3 (0, 1)
	598 iconst_2 (0, 1)
	599 aaload (0, 1)
	600 iconst_1 (0, 1)
	601 daload (0, 1)
	602 dmul (0, 1)
	603 dadd (0, 1)
	604 dastore (0, 1)
	605 aload (0, 1)
	606 #4 (0, 1)
	607 iconst_2 (0, 1)
	608 aaload (0, 1)
	609 iconst_2 (0, 1)
	610 aload_0 (0, 1)
	611 getfield (0, 1)
	612 org/apache/commons/math3/geometry/euclidean/threed/SphericalCoordinates.jacobian:[[D (0, 1)
	614 iconst_0 (0, 1)
	615 aaload (0, 1)
	616 iconst_2 (0, 1)
	617 daload (0, 1)
	618 aload_3 (0, 1)
	619 iconst_0 (0, 1)
	620 aaload (0, 1)
	621 iconst_2 (0, 1)
	622 daload (0, 1)
	623 dmul (0, 1)
	624 aload_0 (0, 1)
	625 getfield (0, 1)
	626 org/apache/commons/math3/geometry/euclidean/threed/SphericalCoordinates.jacobian:[[D (0, 1)
	628 iconst_2 (0, 1)
	629 aaload (0, 1)
	630 iconst_2 (0, 1)
	631 daload (0, 1)
	632 aload_3 (0, 1)
	633 iconst_2 (0, 1)
	634 aaload (0, 1)
	635 iconst_2 (0, 1)
	636 daload (0, 1)
	637 dmul (0, 1)
	638 dadd (0, 1)
	639 dastore (0, 1)
	640 aload (0, 1)
	641 #4 (0, 1)
	642 iconst_0 (0, 1)
	643 aaload (0, 1)
	644 iconst_0 (0, 1)
	645 dup2 (0, 1)
	646 daload (0, 1)
	647 aload_2 (0, 1)
	648 iconst_0 (0, 1)
	649 daload (0, 1)
	650 aload_0 (0, 1)
	651 getfield (0, 1)
	652 org/apache/commons/math3/geometry/euclidean/threed/SphericalCoordinates.rHessian:[[D (0, 1)
	654 iconst_0 (0, 1)
	655 aaload (0, 1)
	656 iconst_0 (0, 1)
	657 daload (0, 1)
	658 dmul (0, 1)
	659 aload_2 (0, 1)
	660 iconst_1 (0, 1)
	661 daload (0, 1)
	662 aload_0 (0, 1)
	663 getfield (0, 1)
	664 org/apache/commons/math3/geometry/euclidean/threed/SphericalCoordinates.thetaHessian:[[D (0, 1)
	666 iconst_0 (0, 1)
	667 aaload (0, 1)
	668 iconst_0 (0, 1)
	669 daload (0, 1)
	670 dmul (0, 1)
	671 dadd (0, 1)
	672 aload_2 (0, 1)
	673 iconst_2 (0, 1)
	674 daload (0, 1)
	675 aload_0 (0, 1)
	676 getfield (0, 1)
	677 org/apache/commons/math3/geometry/euclidean/threed/SphericalCoordinates.phiHessian:[[D (0, 1)
	679 iconst_0 (0, 1)
	680 aaload (0, 1)
	681 iconst_0 (0, 1)
	682 daload (0, 1)
	683 dmul (0, 1)
	684 dadd (0, 1)
	685 dadd (0, 1)
	686 dastore (0, 1)
	687 aload (0, 1)
	688 #4 (0, 1)
	689 iconst_1 (0, 1)
	690 aaload (0, 1)
	691 iconst_0 (0, 1)
	692 dup2 (0, 1)
	693 daload (0, 1)
	694 aload_2 (0, 1)
	695 iconst_0 (0, 1)
	696 daload (0, 1)
	697 aload_0 (0, 1)
	698 getfield (0, 1)
	699 org/apache/commons/math3/geometry/euclidean/threed/SphericalCoordinates.rHessian:[[D (0, 1)
	701 iconst_1 (0, 1)
	702 aaload (0, 1)
	703 iconst_0 (0, 1)
	704 daload (0, 1)
	705 dmul (0, 1)
	706 aload_2 (0, 1)
	707 iconst_1 (0, 1)
	708 daload (0, 1)
	709 aload_0 (0, 1)
	710 getfield (0, 1)
	711 org/apache/commons/math3/geometry/euclidean/threed/SphericalCoordinates.thetaHessian:[[D (0, 1)
	713 iconst_1 (0, 1)
	714 aaload (0, 1)
	715 iconst_0 (0, 1)
	716 daload (0, 1)
	717 dmul (0, 1)
	718 dadd (0, 1)
	719 aload_2 (0, 1)
	720 iconst_2 (0, 1)
	721 daload (0, 1)
	722 aload_0 (0, 1)
	723 getfield (0, 1)
	724 org/apache/commons/math3/geometry/euclidean/threed/SphericalCoordinates.phiHessian:[[D (0, 1)
	726 iconst_1 (0, 1)
	727 aaload (0, 1)
	728 iconst_0 (0, 1)
	729 daload (0, 1)
	730 dmul (0, 1)
	731 dadd (0, 1)
	732 dadd (0, 1)
	733 dastore (0, 1)
	734 aload (0, 1)
	735 #4 (0, 1)
	736 iconst_2 (0, 1)
	737 aaload (0, 1)
	738 iconst_0 (0, 1)
	739 dup2 (0, 1)
	740 daload (0, 1)
	741 aload_2 (0, 1)
	742 iconst_0 (0, 1)
	743 daload (0, 1)
	744 aload_0 (0, 1)
	745 getfield (0, 1)
	746 org/apache/commons/math3/geometry/euclidean/threed/SphericalCoordinates.rHessian:[[D (0, 1)
	748 iconst_2 (0, 1)
	749 aaload (0, 1)
	750 iconst_0 (0, 1)
	751 daload (0, 1)
	752 dmul (0, 1)
	753 aload_2 (0, 1)
	754 iconst_2 (0, 1)
	755 daload (0, 1)
	756 aload_0 (0, 1)
	757 getfield (0, 1)
	758 org/apache/commons/math3/geometry/euclidean/threed/SphericalCoordinates.phiHessian:[[D (0, 1)
	760 iconst_2 (0, 1)
	761 aaload (0, 1)
	762 iconst_0 (0, 1)
	763 daload (0, 1)
	764 dmul (0, 1)
	765 dadd (0, 1)
	766 dadd (0, 1)
	767 dastore (0, 1)
	768 aload (0, 1)
	769 #4 (0, 1)
	770 iconst_1 (0, 1)
	771 aaload (0, 1)
	772 iconst_1 (0, 1)
	773 dup2 (0, 1)
	774 daload (0, 1)
	775 aload_2 (0, 1)
	776 iconst_0 (0, 1)
	777 daload (0, 1)
	778 aload_0 (0, 1)
	779 getfield (0, 1)
	780 org/apache/commons/math3/geometry/euclidean/threed/SphericalCoordinates.rHessian:[[D (0, 1)
	782 iconst_1 (0, 1)
	783 aaload (0, 1)
	784 iconst_1 (0, 1)
	785 daload (0, 1)
	786 dmul (0, 1)
	787 aload_2 (0, 1)
	788 iconst_1 (0, 1)
	789 daload (0, 1)
	790 aload_0 (0, 1)
	791 getfield (0, 1)
	792 org/apache/commons/math3/geometry/euclidean/threed/SphericalCoordinates.thetaHessian:[[D (0, 1)
	794 iconst_1 (0, 1)
	795 aaload (0, 1)
	796 iconst_1 (0, 1)
	797 daload (0, 1)
	798 dmul (0, 1)
	799 dadd (0, 1)
	800 aload_2 (0, 1)
	801 iconst_2 (0, 1)
	802 daload (0, 1)
	803 aload_0 (0, 1)
	804 getfield (0, 1)
	805 org/apache/commons/math3/geometry/euclidean/threed/SphericalCoordinates.phiHessian:[[D (0, 1)
	807 iconst_1 (0, 1)
	808 aaload (0, 1)
	809 iconst_1 (0, 1)
	810 daload (0, 1)
	811 dmul (0, 1)
	812 dadd (0, 1)
	813 dadd (0, 1)
	814 dastore (0, 1)
	815 aload (0, 1)
	816 #4 (0, 1)
	817 iconst_2 (0, 1)
	818 aaload (0, 1)
	819 iconst_1 (0, 1)
	820 dup2 (0, 1)
	821 daload (0, 1)
	822 aload_2 (0, 1)
	823 iconst_0 (0, 1)
	824 daload (0, 1)
	825 aload_0 (0, 1)
	826 getfield (0, 1)
	827 org/apache/commons/math3/geometry/euclidean/threed/SphericalCoordinates.rHessian:[[D (0, 1)
	829 iconst_2 (0, 1)
	830 aaload (0, 1)
	831 iconst_1 (0, 1)
	832 daload (0, 1)
	833 dmul (0, 1)
	834 aload_2 (0, 1)
	835 iconst_2 (0, 1)
	836 daload (0, 1)
	837 aload_0 (0, 1)
	838 getfield (0, 1)
	839 org/apache/commons/math3/geometry/euclidean/threed/SphericalCoordinates.phiHessian:[[D (0, 1)
	841 iconst_2 (0, 1)
	842 aaload (0, 1)
	843 iconst_1 (0, 1)
	844 daload (0, 1)
	845 dmul (0, 1)
	846 dadd (0, 1)
	847 dadd (0, 1)
	848 dastore (0, 1)
	849 aload (0, 1)
	850 #4 (0, 1)
	851 iconst_2 (0, 1)
	852 aaload (0, 1)
	853 iconst_2 (0, 1)
	854 dup2 (0, 1)
	855 daload (0, 1)
	856 aload_2 (0, 1)
	857 iconst_0 (0, 1)
	858 daload (0, 1)
	859 aload_0 (0, 1)
	860 getfield (0, 1)
	861 org/apache/commons/math3/geometry/euclidean/threed/SphericalCoordinates.rHessian:[[D (0, 1)
	863 iconst_2 (0, 1)
	864 aaload (0, 1)
	865 iconst_2 (0, 1)
	866 daload (0, 1)
	867 dmul (0, 1)
	868 aload_2 (0, 1)
	869 iconst_2 (0, 1)
	870 daload (0, 1)
	871 aload_0 (0, 1)
	872 getfield (0, 1)
	873 org/apache/commons/math3/geometry/euclidean/threed/SphericalCoordinates.phiHessian:[[D (0, 1)
	875 iconst_2 (0, 1)
	876 aaload (0, 1)
	877 iconst_2 (0, 1)
	878 daload (0, 1)
	879 dmul (0, 1)
	880 dadd (0, 1)
	881 dadd (0, 1)
	882 dastore (0, 1)
	883 aload (0, 1)
	884 #4 (0, 1)
	885 iconst_0 (0, 1)
	886 aaload (0, 1)
	887 iconst_1 (0, 1)
	888 aload (0, 1)
	889 #4 (0, 1)
	890 iconst_1 (0, 1)
	891 aaload (0, 1)
	892 iconst_0 (0, 1)
	893 daload (0, 1)
	894 dastore (0, 1)
	895 aload (0, 1)
	896 #4 (0, 1)
	897 iconst_0 (0, 1)
	898 aaload (0, 1)
	899 iconst_2 (0, 1)
	900 aload (0, 1)
	901 #4 (0, 1)
	902 iconst_2 (0, 1)
	903 aaload (0, 1)
	904 iconst_0 (0, 1)
	905 daload (0, 1)
	906 dastore (0, 1)
	907 aload (0, 1)
	908 #4 (0, 1)
	909 iconst_1 (0, 1)
	910 aaload (0, 1)
	911 iconst_2 (0, 1)
	912 aload (0, 1)
	913 #4 (0, 1)
	914 iconst_2 (0, 1)
	915 aaload (0, 1)
	916 iconst_1 (0, 1)
	917 daload (0, 1)
	918 dastore (0, 1)
	919 aload (0, 1)
	920 #4 (0, 1)
	921 areturn (0, 1)

Method: computeJacobian
	0 aload_0 (1, 1)
	1 getfield (1, 1)
	2 org/apache/commons/math3/geometry/euclidean/threed/SphericalCoordinates.jacobian:[[D (1, 1)
	4 ifnonnull (1, 1)
	5 182 (1, 1)
	7 aload_0 (1, 1)
	8 getfield (1, 1)
	9 org/apache/commons/math3/geometry/euclidean/threed/SphericalCoordinates.v:Lorg/apache/commons/math3/geometry/euclidean/threed/Vector3D; (1, 1)
	11 invokevirtual (1, 1)
	12 org/apache/commons/math3/geometry/euclidean/threed/Vector3D.getX:()D (1, 1)
	14 dstore_1 (1, 1)
	15 aload_0 (1, 1)
	16 getfield (1, 1)
	17 org/apache/commons/math3/geometry/euclidean/threed/SphericalCoordinates.v:Lorg/apache/commons/math3/geometry/euclidean/threed/Vector3D; (1, 1)
	19 invokevirtual (1, 1)
	20 org/apache/commons/math3/geometry/euclidean/threed/Vector3D.getY:()D (1, 1)
	22 dstore_3 (1, 1)
	23 aload_0 (1, 1)
	24 getfield (1, 1)
	25 org/apache/commons/math3/geometry/euclidean/threed/SphericalCoordinates.v:Lorg/apache/commons/math3/geometry/euclidean/threed/Vector3D; (1, 1)
	27 invokevirtual (1, 1)
	28 org/apache/commons/math3/geometry/euclidean/threed/Vector3D.getZ:()D (1, 1)
	30 dstore (1, 1)
	31 #5 (1, 1)
	32 dload_1 (1, 1)
	33 dload_1 (1, 1)
	34 dmul (1, 1)
	35 dload_3 (1, 1)
	36 dload_3 (1, 1)
	37 dmul (1, 1)
	38 dadd (1, 1)
	39 dstore (1, 1)
	40 #7 (1, 1)
	41 dload (1, 1)
	42 #7 (1, 1)
	43 invokestatic (1, 1)
	44 org/apache/commons/math3/util/FastMath.sqrt:(D)D (1, 1)
	46 dstore (1, 1)
	47 #9 (1, 1)
	48 dload (1, 1)
	49 #7 (1, 1)
	50 dload (1, 1)
	51 #5 (1, 1)
	52 dload (1, 1)
	53 #5 (1, 1)
	54 dmul (1, 1)
	55 dadd (1, 1)
	56 dstore (1, 1)
	57 #11 (1, 1)
	58 aload_0 (1, 1)
	59 iconst_3 (1, 1)
	60 iconst_3 (1, 1)
	61 multianewarray (1, 1)
	62 [[D (1, 1)
	64 -75 (1, 1)
	65 putfield (1, 1)
	66 org/apache/commons/math3/geometry/euclidean/threed/SphericalCoordinates.jacobian:[[D (1, 1)
	68 aload_0 (1, 1)
	69 getfield (1, 1)
	70 org/apache/commons/math3/geometry/euclidean/threed/SphericalCoordinates.jacobian:[[D (1, 1)
	72 iconst_0 (1, 1)
	73 aaload (1, 1)
	74 iconst_0 (1, 1)
	75 dload_1 (1, 1)
	76 aload_0 (1, 1)
	77 getfield (1, 1)
	78 org/apache/commons/math3/geometry/euclidean/threed/SphericalCoordinates.r:D (1, 1)
	80 ddiv (1, 1)
	81 dastore (1, 1)
	82 aload_0 (1, 1)
	83 getfield (1, 1)
	84 org/apache/commons/math3/geometry/euclidean/threed/SphericalCoordinates.jacobian:[[D (1, 1)
	86 iconst_0 (1, 1)
	87 aaload (1, 1)
	88 iconst_1 (1, 1)
	89 dload_3 (1, 1)
	90 aload_0 (1, 1)
	91 getfield (1, 1)
	92 org/apache/commons/math3/geometry/euclidean/threed/SphericalCoordinates.r:D (1, 1)
	94 ddiv (1, 1)
	95 dastore (1, 1)
	96 aload_0 (1, 1)
	97 getfield (1, 1)
	98 org/apache/commons/math3/geometry/euclidean/threed/SphericalCoordinates.jacobian:[[D (1, 1)
	100 iconst_0 (1, 1)
	101 aaload (1, 1)
	102 iconst_2 (1, 1)
	103 dload (1, 1)
	104 #5 (1, 1)
	105 aload_0 (1, 1)
	106 getfield (1, 1)
	107 org/apache/commons/math3/geometry/euclidean/threed/SphericalCoordinates.r:D (1, 1)
	109 ddiv (1, 1)
	110 dastore (1, 1)
	111 aload_0 (1, 1)
	112 getfield (1, 1)
	113 org/apache/commons/math3/geometry/euclidean/threed/SphericalCoordinates.jacobian:[[D (1, 1)
	115 iconst_1 (1, 1)
	116 aaload (1, 1)
	117 iconst_0 (1, 1)
	118 dload_3 (1, 1)
	119 dneg (1, 1)
	120 dload (1, 1)
	121 #7 (1, 1)
	122 ddiv (1, 1)
	123 dastore (1, 1)
	124 aload_0 (1, 1)
	125 getfield (1, 1)
	126 org/apache/commons/math3/geometry/euclidean/threed/SphericalCoordinates.jacobian:[[D (1, 1)
	128 iconst_1 (1, 1)
	129 aaload (1, 1)
	130 iconst_1 (1, 1)
	131 dload_1 (1, 1)
	132 dload (1, 1)
	133 #7 (1, 1)
	134 ddiv (1, 1)
	135 dastore (1, 1)
	136 aload_0 (1, 1)
	137 getfield (1, 1)
	138 org/apache/commons/math3/geometry/euclidean/threed/SphericalCoordinates.jacobian:[[D (1, 1)
	140 iconst_2 (1, 1)
	141 aaload (1, 1)
	142 iconst_0 (1, 1)
	143 dload_1 (1, 1)
	144 dload (1, 1)
	145 #5 (1, 1)
	146 dmul (1, 1)
	147 dload (1, 1)
	148 #9 (1, 1)
	149 dload (1, 1)
	150 #11 (1, 1)
	151 dmul (1, 1)
	152 ddiv (1, 1)
	153 dastore (1, 1)
	154 aload_0 (1, 1)
	155 getfield (1, 1)
	156 org/apache/commons/math3/geometry/euclidean/threed/SphericalCoordinates.jacobian:[[D (1, 1)
	158 iconst_2 (1, 1)
	159 aaload (1, 1)
	160 iconst_1 (1, 1)
	161 dload_3 (1, 1)
	162 dload (1, 1)
	163 #5 (1, 1)
	164 dmul (1, 1)
	165 dload (1, 1)
	166 #9 (1, 1)
	167 dload (1, 1)
	168 #11 (1, 1)
	169 dmul (1, 1)
	170 ddiv (1, 1)
	171 dastore (1, 1)
	172 aload_0 (1, 1)
	173 getfield (1, 1)
	174 org/apache/commons/math3/geometry/euclidean/threed/SphericalCoordinates.jacobian:[[D (1, 1)
	176 iconst_2 (1, 1)
	177 aaload (1, 1)
	178 iconst_2 (1, 1)
	179 dload (1, 1)
	180 #9 (1, 1)
	181 dneg (1, 1)
	182 dload (1, 1)
	183 #11 (1, 1)
	184 ddiv (1, 1)
	185 dastore (1, 1)
	186 return (0, 0)

Method: computeHessians
	0 aload_0 (1, 1)
	1 getfield (1, 1)
	2 org/apache/commons/math3/geometry/euclidean/threed/SphericalCoordinates.rHessian:[[D (1, 1)
	4 ifnonnull (1, 1)
	5 574 (1, 1)
	7 aload_0 (1, 1)
	8 getfield (1, 1)
	9 org/apache/commons/math3/geometry/euclidean/threed/SphericalCoordinates.v:Lorg/apache/commons/math3/geometry/euclidean/threed/Vector3D; (1, 1)
	11 invokevirtual (1, 1)
	12 org/apache/commons/math3/geometry/euclidean/threed/Vector3D.getX:()D (1, 1)
	14 dstore_1 (1, 1)
	15 aload_0 (1, 1)
	16 getfield (1, 1)
	17 org/apache/commons/math3/geometry/euclidean/threed/SphericalCoordinates.v:Lorg/apache/commons/math3/geometry/euclidean/threed/Vector3D; (1, 1)
	19 invokevirtual (1, 1)
	20 org/apache/commons/math3/geometry/euclidean/threed/Vector3D.getY:()D (1, 1)
	22 dstore_3 (1, 1)
	23 aload_0 (1, 1)
	24 getfield (1, 1)
	25 org/apache/commons/math3/geometry/euclidean/threed/SphericalCoordinates.v:Lorg/apache/commons/math3/geometry/euclidean/threed/Vector3D; (1, 1)
	27 invokevirtual (1, 1)
	28 org/apache/commons/math3/geometry/euclidean/threed/Vector3D.getZ:()D (1, 1)
	30 dstore (1, 1)
	31 #5 (1, 1)
	32 dload_1 (1, 1)
	33 dload_1 (1, 1)
	34 dmul (1, 1)
	35 dstore (1, 1)
	36 #7 (1, 1)
	37 dload_3 (1, 1)
	38 dload_3 (1, 1)
	39 dmul (1, 1)
	40 dstore (1, 1)
	41 #9 (1, 1)
	42 dload (1, 1)
	43 #5 (1, 1)
	44 dload (1, 1)
	45 #5 (1, 1)
	46 dmul (1, 1)
	47 dstore (1, 1)
	48 #11 (1, 1)
	49 dload (1, 1)
	50 #7 (1, 1)
	51 dload (1, 1)
	52 #9 (1, 1)
	53 dadd (1, 1)
	54 dstore (1, 1)
	55 #13 (1, 1)
	56 dload (1, 1)
	57 #13 (1, 1)
	58 invokestatic (1, 1)
	59 org/apache/commons/math3/util/FastMath.sqrt:(D)D (1, 1)
	61 dstore (1, 1)
	62 #15 (1, 1)
	63 dload (1, 1)
	64 #13 (1, 1)
	65 dload (1, 1)
	66 #11 (1, 1)
	67 dadd (1, 1)
	68 dstore (1, 1)
	69 #17 (1, 1)
	70 dload_1 (1, 1)
	71 aload_0 (1, 1)
	72 getfield (1, 1)
	73 org/apache/commons/math3/geometry/euclidean/threed/SphericalCoordinates.r:D (1, 1)
	75 ddiv (1, 1)
	76 dstore (1, 1)
	77 #19 (1, 1)
	78 dload_3 (1, 1)
	79 aload_0 (1, 1)
	80 getfield (1, 1)
	81 org/apache/commons/math3/geometry/euclidean/threed/SphericalCoordinates.r:D (1, 1)
	83 ddiv (1, 1)
	84 dstore (1, 1)
	85 #21 (1, 1)
	86 dload (1, 1)
	87 #5 (1, 1)
	88 aload_0 (1, 1)
	89 getfield (1, 1)
	90 org/apache/commons/math3/geometry/euclidean/threed/SphericalCoordinates.r:D (1, 1)
	92 ddiv (1, 1)
	93 dstore (1, 1)
	94 #23 (1, 1)
	95 dload_1 (1, 1)
	96 dload (1, 1)
	97 #13 (1, 1)
	98 ddiv (1, 1)
	99 dstore (1, 1)
	100 #25 (1, 1)
	101 dload_3 (1, 1)
	102 dload (1, 1)
	103 #13 (1, 1)
	104 ddiv (1, 1)
	105 dstore (1, 1)
	106 #27 (1, 1)
	107 dload (1, 1)
	108 #19 (1, 1)
	109 dload (1, 1)
	110 #17 (1, 1)
	111 ddiv (1, 1)
	112 dstore (1, 1)
	113 #29 (1, 1)
	114 dload (1, 1)
	115 #21 (1, 1)
	116 dload (1, 1)
	117 #17 (1, 1)
	118 ddiv (1, 1)
	119 dstore (1, 1)
	120 #31 (1, 1)
	121 dload (1, 1)
	122 #23 (1, 1)
	123 dload (1, 1)
	124 #17 (1, 1)
	125 ddiv (1, 1)
	126 dstore (1, 1)
	127 #33 (1, 1)
	128 aload_0 (1, 1)
	129 iconst_3 (1, 1)
	130 iconst_3 (1, 1)
	131 multianewarray (1, 1)
	132 [[D (1, 1)
	134 -75 (1, 1)
	135 putfield (1, 1)
	136 org/apache/commons/math3/geometry/euclidean/threed/SphericalCoordinates.rHessian:[[D (1, 1)
	138 aload_0 (1, 1)
	139 getfield (1, 1)
	140 org/apache/commons/math3/geometry/euclidean/threed/SphericalCoordinates.rHessian:[[D (1, 1)
	142 iconst_0 (1, 1)
	143 aaload (1, 1)
	144 iconst_0 (1, 1)
	145 dload_3 (1, 1)
	146 dload (1, 1)
	147 #31 (1, 1)
	148 dmul (1, 1)
	149 dload (1, 1)
	150 #5 (1, 1)
	151 dload (1, 1)
	152 #33 (1, 1)
	153 dmul (1, 1)
	154 dadd (1, 1)
	155 dastore (1, 1)
	156 aload_0 (1, 1)
	157 getfield (1, 1)
	158 org/apache/commons/math3/geometry/euclidean/threed/SphericalCoordinates.rHessian:[[D (1, 1)
	160 iconst_1 (1, 1)
	161 aaload (1, 1)
	162 iconst_0 (1, 1)
	163 dload_1 (1, 1)
	164 dneg (1, 1)
	165 dload (1, 1)
	166 #31 (1, 1)
	167 dmul (1, 1)
	168 dastore (1, 1)
	169 aload_0 (1, 1)
	170 getfield (1, 1)
	171 org/apache/commons/math3/geometry/euclidean/threed/SphericalCoordinates.rHessian:[[D (1, 1)
	173 iconst_2 (1, 1)
	174 aaload (1, 1)
	175 iconst_0 (1, 1)
	176 dload (1, 1)
	177 #5 (1, 1)
	178 dneg (1, 1)
	179 dload (1, 1)
	180 #29 (1, 1)
	181 dmul (1, 1)
	182 dastore (1, 1)
	183 aload_0 (1, 1)
	184 getfield (1, 1)
	185 org/apache/commons/math3/geometry/euclidean/threed/SphericalCoordinates.rHessian:[[D (1, 1)
	187 iconst_1 (1, 1)
	188 aaload (1, 1)
	189 iconst_1 (1, 1)
	190 dload_1 (1, 1)
	191 dload (1, 1)
	192 #29 (1, 1)
	193 dmul (1, 1)
	194 dload (1, 1)
	195 #5 (1, 1)
	196 dload (1, 1)
	197 #33 (1, 1)
	198 dmul (1, 1)
	199 dadd (1, 1)
	200 dastore (1, 1)
	201 aload_0 (1, 1)
	202 getfield (1, 1)
	203 org/apache/commons/math3/geometry/euclidean/threed/SphericalCoordinates.rHessian:[[D (1, 1)
	205 iconst_2 (1, 1)
	206 aaload (1, 1)
	207 iconst_1 (1, 1)
	208 dload_3 (1, 1)
	209 dneg (1, 1)
	210 dload (1, 1)
	211 #33 (1, 1)
	212 dmul (1, 1)
	213 dastore (1, 1)
	214 aload_0 (1, 1)
	215 getfield (1, 1)
	216 org/apache/commons/math3/geometry/euclidean/threed/SphericalCoordinates.rHessian:[[D (1, 1)
	218 iconst_2 (1, 1)
	219 aaload (1, 1)
	220 iconst_2 (1, 1)
	221 dload_1 (1, 1)
	222 dload (1, 1)
	223 #29 (1, 1)
	224 dmul (1, 1)
	225 dload_3 (1, 1)
	226 dload (1, 1)
	227 #31 (1, 1)
	228 dmul (1, 1)
	229 dadd (1, 1)
	230 dastore (1, 1)
	231 aload_0 (1, 1)
	232 getfield (1, 1)
	233 org/apache/commons/math3/geometry/euclidean/threed/SphericalCoordinates.rHessian:[[D (1, 1)
	235 iconst_0 (1, 1)
	236 aaload (1, 1)
	237 iconst_1 (1, 1)
	238 aload_0 (1, 1)
	239 getfield (1, 1)
	240 org/apache/commons/math3/geometry/euclidean/threed/SphericalCoordinates.rHessian:[[D (1, 1)
	242 iconst_1 (1, 1)
	243 aaload (1, 1)
	244 iconst_0 (1, 1)
	245 daload (1, 1)
	246 dastore (1, 1)
	247 aload_0 (1, 1)
	248 getfield (1, 1)
	249 org/apache/commons/math3/geometry/euclidean/threed/SphericalCoordinates.rHessian:[[D (1, 1)
	251 iconst_0 (1, 1)
	252 aaload (1, 1)
	253 iconst_2 (1, 1)
	254 aload_0 (1, 1)
	255 getfield (1, 1)
	256 org/apache/commons/math3/geometry/euclidean/threed/SphericalCoordinates.rHessian:[[D (1, 1)
	258 iconst_2 (1, 1)
	259 aaload (1, 1)
	260 iconst_0 (1, 1)
	261 daload (1, 1)
	262 dastore (1, 1)
	263 aload_0 (1, 1)
	264 getfield (1, 1)
	265 org/apache/commons/math3/geometry/euclidean/threed/SphericalCoordinates.rHessian:[[D (1, 1)
	267 iconst_1 (1, 1)
	268 aaload (1, 1)
	269 iconst_2 (1, 1)
	270 aload_0 (1, 1)
	271 getfield (1, 1)
	272 org/apache/commons/math3/geometry/euclidean/threed/SphericalCoordinates.rHessian:[[D (1, 1)
	274 iconst_2 (1, 1)
	275 aaload (1, 1)
	276 iconst_1 (1, 1)
	277 daload (1, 1)
	278 dastore (1, 1)
	279 aload_0 (1, 1)
	280 iconst_2 (1, 1)
	281 iconst_2 (1, 1)
	282 multianewarray (1, 1)
	283 [[D (1, 1)
	285 -75 (1, 1)
	286 putfield (1, 1)
	287 org/apache/commons/math3/geometry/euclidean/threed/SphericalCoordinates.thetaHessian:[[D (1, 1)
	289 aload_0 (1, 1)
	290 getfield (1, 1)
	291 org/apache/commons/math3/geometry/euclidean/threed/SphericalCoordinates.thetaHessian:[[D (1, 1)
	293 iconst_0 (1, 1)
	294 aaload (1, 1)
	295 iconst_0 (1, 1)
	296 ldc2_w (1, 1)
	297 2.0 (1, 1)
	299 dload (1, 1)
	300 #25 (1, 1)
	301 dmul (1, 1)
	302 dload (1, 1)
	303 #27 (1, 1)
	304 dmul (1, 1)
	305 dastore (1, 1)
	306 aload_0 (1, 1)
	307 getfield (1, 1)
	308 org/apache/commons/math3/geometry/euclidean/threed/SphericalCoordinates.thetaHessian:[[D (1, 1)
	310 iconst_1 (1, 1)
	311 aaload (1, 1)
	312 iconst_0 (1, 1)
	313 dload (1, 1)
	314 #27 (1, 1)
	315 dload (1, 1)
	316 #27 (1, 1)
	317 dmul (1, 1)
	318 dload (1, 1)
	319 #25 (1, 1)
	320 dload (1, 1)
	321 #25 (1, 1)
	322 dmul (1, 1)
	323 dsub (1, 1)
	324 dastore (1, 1)
	325 aload_0 (1, 1)
	326 getfield (1, 1)
	327 org/apache/commons/math3/geometry/euclidean/threed/SphericalCoordinates.thetaHessian:[[D (1, 1)
	329 iconst_1 (1, 1)
	330 aaload (1, 1)
	331 iconst_1 (1, 1)
	332 ldc2_w (1, 1)
	333 -2.0 (1, 1)
	335 dload (1, 1)
	336 #25 (1, 1)
	337 dmul (1, 1)
	338 dload (1, 1)
	339 #27 (1, 1)
	340 dmul (1, 1)
	341 dastore (1, 1)
	342 aload_0 (1, 1)
	343 getfield (1, 1)
	344 org/apache/commons/math3/geometry/euclidean/threed/SphericalCoordinates.thetaHessian:[[D (1, 1)
	346 iconst_0 (1, 1)
	347 aaload (1, 1)
	348 iconst_1 (1, 1)
	349 aload_0 (1, 1)
	350 getfield (1, 1)
	351 org/apache/commons/math3/geometry/euclidean/threed/SphericalCoordinates.thetaHessian:[[D (1, 1)
	353 iconst_1 (1, 1)
	354 aaload (1, 1)
	355 iconst_0 (1, 1)
	356 daload (1, 1)
	357 dastore (1, 1)
	358 dload (1, 1)
	359 #15 (1, 1)
	360 dload (1, 1)
	361 #17 (1, 1)
	362 dmul (1, 1)
	363 dstore (1, 1)
	364 #35 (1, 1)
	365 dload (1, 1)
	366 #15 (1, 1)
	367 dload (1, 1)
	368 #35 (1, 1)
	369 dmul (1, 1)
	370 dstore (1, 1)
	371 #37 (1, 1)
	372 dload (1, 1)
	373 #35 (1, 1)
	374 dload (1, 1)
	375 #17 (1, 1)
	376 dmul (1, 1)
	377 dstore (1, 1)
	378 #39 (1, 1)
	379 dload (1, 1)
	380 #39 (1, 1)
	381 dload (1, 1)
	382 #13 (1, 1)
	383 dmul (1, 1)
	384 dstore (1, 1)
	385 #41 (1, 1)
	386 ldc2_w (1, 1)
	387 3.0 (1, 1)
	389 dload (1, 1)
	390 #13 (1, 1)
	391 dmul (1, 1)
	392 dload (1, 1)
	393 #11 (1, 1)
	394 dadd (1, 1)
	395 dstore (1, 1)
	396 #43 (1, 1)
	397 aload_0 (1, 1)
	398 iconst_3 (1, 1)
	399 iconst_3 (1, 1)
	400 multianewarray (1, 1)
	401 [[D (1, 1)
	403 -75 (1, 1)
	404 putfield (1, 1)
	405 org/apache/commons/math3/geometry/euclidean/threed/SphericalCoordinates.phiHessian:[[D (1, 1)
	407 aload_0 (1, 1)
	408 getfield (1, 1)
	409 org/apache/commons/math3/geometry/euclidean/threed/SphericalCoordinates.phiHessian:[[D (1, 1)
	411 iconst_0 (1, 1)
	412 aaload (1, 1)
	413 iconst_0 (1, 1)
	414 dload (1, 1)
	415 #5 (1, 1)
	416 dload (1, 1)
	417 #37 (1, 1)
	418 dload (1, 1)
	419 #7 (1, 1)
	420 dload (1, 1)
	421 #43 (1, 1)
	422 dmul (1, 1)
	423 dsub (1, 1)
	424 dmul (1, 1)
	425 dload (1, 1)
	426 #41 (1, 1)
	427 ddiv (1, 1)
	428 dastore (1, 1)
	429 aload_0 (1, 1)
	430 getfield (1, 1)
	431 org/apache/commons/math3/geometry/euclidean/threed/SphericalCoordinates.phiHessian:[[D (1, 1)
	433 iconst_1 (1, 1)
	434 aaload (1, 1)
	435 iconst_0 (1, 1)
	436 dload_1 (1, 1)
	437 dneg (1, 1)
	438 dload_3 (1, 1)
	439 dmul (1, 1)
	440 dload (1, 1)
	441 #5 (1, 1)
	442 dmul (1, 1)
	443 dload (1, 1)
	444 #43 (1, 1)
	445 dmul (1, 1)
	446 dload (1, 1)
	447 #41 (1, 1)
	448 ddiv (1, 1)
	449 dastore (1, 1)
	450 aload_0 (1, 1)
	451 getfield (1, 1)
	452 org/apache/commons/math3/geometry/euclidean/threed/SphericalCoordinates.phiHessian:[[D (1, 1)
	454 iconst_2 (1, 1)
	455 aaload (1, 1)
	456 iconst_0 (1, 1)
	457 dload_1 (1, 1)
	458 dload (1, 1)
	459 #13 (1, 1)
	460 dload (1, 1)
	461 #11 (1, 1)
	462 dsub (1, 1)
	463 dmul (1, 1)
	464 dload (1, 1)
	465 #39 (1, 1)
	466 ddiv (1, 1)
	467 dastore (1, 1)
	468 aload_0 (1, 1)
	469 getfield (1, 1)
	470 org/apache/commons/math3/geometry/euclidean/threed/SphericalCoordinates.phiHessian:[[D (1, 1)
	472 iconst_1 (1, 1)
	473 aaload (1, 1)
	474 iconst_1 (1, 1)
	475 dload (1, 1)
	476 #5 (1, 1)
	477 dload (1, 1)
	478 #37 (1, 1)
	479 dload (1, 1)
	480 #9 (1, 1)
	481 dload (1, 1)
	482 #43 (1, 1)
	483 dmul (1, 1)
	484 dsub (1, 1)
	485 dmul (1, 1)
	486 dload (1, 1)
	487 #41 (1, 1)
	488 ddiv (1, 1)
	489 dastore (1, 1)
	490 aload_0 (1, 1)
	491 getfield (1, 1)
	492 org/apache/commons/math3/geometry/euclidean/threed/SphericalCoordinates.phiHessian:[[D (1, 1)
	494 iconst_2 (1, 1)
	495 aaload (1, 1)
	496 iconst_1 (1, 1)
	497 dload_3 (1, 1)
	498 dload (1, 1)
	499 #13 (1, 1)
	500 dload (1, 1)
	501 #11 (1, 1)
	502 dsub (1, 1)
	503 dmul (1, 1)
	504 dload (1, 1)
	505 #39 (1, 1)
	506 ddiv (1, 1)
	507 dastore (1, 1)
	508 aload_0 (1, 1)
	509 getfield (1, 1)
	510 org/apache/commons/math3/geometry/euclidean/threed/SphericalCoordinates.phiHessian:[[D (1, 1)
	512 iconst_2 (1, 1)
	513 aaload (1, 1)
	514 iconst_2 (1, 1)
	515 ldc2_w (1, 1)
	516 2.0 (1, 1)
	518 dload (1, 1)
	519 #15 (1, 1)
	520 dmul (1, 1)
	521 dload (1, 1)
	522 #33 (1, 1)
	523 dmul (1, 1)
	524 aload_0 (1, 1)
	525 getfield (1, 1)
	526 org/apache/commons/math3/geometry/euclidean/threed/SphericalCoordinates.r:D (1, 1)
	528 ddiv (1, 1)
	529 dastore (1, 1)
	530 aload_0 (1, 1)
	531 getfield (1, 1)
	532 org/apache/commons/math3/geometry/euclidean/threed/SphericalCoordinates.phiHessian:[[D (1, 1)
	534 iconst_0 (1, 1)
	535 aaload (1, 1)
	536 iconst_1 (1, 1)
	537 aload_0 (1, 1)
	538 getfield (1, 1)
	539 org/apache/commons/math3/geometry/euclidean/threed/SphericalCoordinates.phiHessian:[[D (1, 1)
	541 iconst_1 (1, 1)
	542 aaload (1, 1)
	543 iconst_0 (1, 1)
	544 daload (1, 1)
	545 dastore (1, 1)
	546 aload_0 (1, 1)
	547 getfield (1, 1)
	548 org/apache/commons/math3/geometry/euclidean/threed/SphericalCoordinates.phiHessian:[[D (1, 1)
	550 iconst_0 (1, 1)
	551 aaload (1, 1)
	552 iconst_2 (1, 1)
	553 aload_0 (1, 1)
	554 getfield (1, 1)
	555 org/apache/commons/math3/geometry/euclidean/threed/SphericalCoordinates.phiHessian:[[D (1, 1)
	557 iconst_2 (1, 1)
	558 aaload (1, 1)
	559 iconst_0 (1, 1)
	560 daload (1, 1)
	561 dastore (1, 1)
	562 aload_0 (1, 1)
	563 getfield (1, 1)
	564 org/apache/commons/math3/geometry/euclidean/threed/SphericalCoordinates.phiHessian:[[D (1, 1)
	566 iconst_1 (1, 1)
	567 aaload (1, 1)
	568 iconst_2 (1, 1)
	569 aload_0 (1, 1)
	570 getfield (1, 1)
	571 org/apache/commons/math3/geometry/euclidean/threed/SphericalCoordinates.phiHessian:[[D (1, 1)
	573 iconst_2 (1, 1)
	574 aaload (1, 1)
	575 iconst_1 (1, 1)
	576 daload (1, 1)
	577 dastore (1, 1)
	578 return (0, 0)

Method: writeReplace
	0 new (0, 0)
	1 org/apache/commons/math3/geometry/euclidean/threed/SphericalCoordinates$DataTransferObject (0, 0)
	3 dup (0, 0)
	4 aload_0 (0, 0)
	5 getfield (0, 0)
	6 org/apache/commons/math3/geometry/euclidean/threed/SphericalCoordinates.v:Lorg/apache/commons/math3/geometry/euclidean/threed/Vector3D; (0, 0)
	8 invokevirtual (0, 0)
	9 org/apache/commons/math3/geometry/euclidean/threed/Vector3D.getX:()D (0, 0)
	11 aload_0 (0, 0)
	12 getfield (0, 0)
	13 org/apache/commons/math3/geometry/euclidean/threed/SphericalCoordinates.v:Lorg/apache/commons/math3/geometry/euclidean/threed/Vector3D; (0, 0)
	15 invokevirtual (0, 0)
	16 org/apache/commons/math3/geometry/euclidean/threed/Vector3D.getY:()D (0, 0)
	18 aload_0 (0, 0)
	19 getfield (0, 0)
	20 org/apache/commons/math3/geometry/euclidean/threed/SphericalCoordinates.v:Lorg/apache/commons/math3/geometry/euclidean/threed/Vector3D; (0, 0)
	22 invokevirtual (0, 0)
	23 org/apache/commons/math3/geometry/euclidean/threed/Vector3D.getZ:()D (0, 0)
	25 invokespecial (0, 0)
	26 org/apache/commons/math3/geometry/euclidean/threed/SphericalCoordinates$DataTransferObject.<init>:(DDD)V (0, 0)
	28 areturn (0, 0)

