Method: ballOnSupport
	0 aload_1 (1, 1)
	1 invokeinterface (1, 1)
	6 iconst_1 (1, 1)
	7 if_icmpge (1, 1)
	10 new (1, 1)
	13 dup (1, 1)
	14 getstatic (1, 1)
	17 ldc2_w (1, 1)
	20 iconst_0 (1, 1)
	21 anewarray (1, 1)
	24 invokespecial (1, 1)
	27 areturn (1, 1)
	28 aload_1 (1, 2)
	29 iconst_0 (1, 2)
	30 invokeinterface (1, 2)
	35 checkcast (1, 2)
	38 astore_2 (1, 2)
	39 aload_1 (2, 1)
	40 invokeinterface (2, 1)
	45 iconst_2 (2, 1)
	46 if_icmpge (2, 1)
	49 new (2, 1)
	52 dup (2, 1)
	53 aload_2 (2, 1)
	54 dconst_0 (2, 1)
	55 iconst_1 (2, 1)
	56 anewarray (2, 1)
	59 dup (2, 1)
	60 iconst_0 (2, 1)
	61 aload_2 (2, 1)
	62 aastore (2, 1)
	63 invokespecial (2, 1)
	66 areturn (2, 1)
	67 aload_1 (2, 2)
	68 iconst_1 (2, 2)
	69 invokeinterface (2, 2)
	74 checkcast (2, 2)
	77 astore_3 (2, 2)
	78 aload_1 (3, 1)
	79 invokeinterface (3, 1)
	84 iconst_3 (3, 1)
	85 if_icmpge (3, 1)
	88 new (3, 1)
	91 dup (3, 1)
	92 new (3, 1)
	95 dup (3, 1)
	96 ldc2_w (3, 1)
	99 aload_2 (3, 1)
	100 ldc2_w (3, 1)
	103 aload_3 (3, 1)
	104 invokespecial (3, 1)
	107 ldc2_w (3, 1)
	110 aload_2 (3, 1)
	111 aload_3 (3, 1)
	112 invokevirtual (3, 1)
	115 dmul (3, 1)
	116 iconst_2 (3, 1)
	117 anewarray (3, 1)
	120 dup (3, 1)
	121 iconst_0 (3, 1)
	122 aload_2 (3, 1)
	123 aastore (3, 1)
	124 dup (3, 1)
	125 iconst_1 (3, 1)
	126 aload_3 (3, 1)
	127 aastore (3, 1)
	128 invokespecial (3, 1)
	131 areturn (3, 1)
	132 aload_1 (3, 2)
	133 iconst_2 (3, 2)
	134 invokeinterface (3, 2)
	139 checkcast (3, 2)
	142 astore (3, 2)
	144 aload_1 (4, 1)
	145 invokeinterface (4, 1)
	150 iconst_4 (4, 1)
	151 if_icmpge (4, 1)
	154 new (4, 1)
	157 dup (4, 1)
	158 aload_2 (4, 1)
	159 aload_3 (4, 1)
	160 aload (4, 1)
	162 ldc2_w (4, 1)
	165 aload_2 (4, 1)
	166 invokevirtual (4, 1)
	169 aload_3 (4, 1)
	170 invokevirtual (4, 1)
	173 dadd (4, 1)
	174 aload (4, 1)
	176 invokevirtual (4, 1)
	179 dadd (4, 1)
	180 dmul (4, 1)
	181 invokespecial (4, 1)
	184 astore (4, 1)
	186 new (4, 1)
	189 dup (4, 1)
	190 invokespecial (4, 1)
	193 iconst_3 (4, 1)
	194 anewarray (4, 1)
	197 dup (4, 1)
	198 iconst_0 (4, 1)
	199 aload (4, 1)
	201 aload_2 (4, 1)
	202 invokevirtual (4, 1)
	205 aastore (4, 1)
	206 dup (4, 1)
	207 iconst_1 (4, 1)
	208 aload (4, 1)
	210 aload_3 (4, 1)
	211 invokevirtual (4, 1)
	214 aastore (4, 1)
	215 dup (4, 1)
	216 iconst_2 (4, 1)
	217 aload (4, 1)
	219 aload (4, 1)
	221 invokevirtual (4, 1)
	224 aastore (4, 1)
	225 invokestatic (4, 1)
	228 invokevirtual (4, 1)
	231 astore (4, 1)
	233 new (4, 1)
	236 dup (4, 1)
	237 aload (4, 1)
	239 aload (4, 1)
	241 invokevirtual (4, 1)
	244 checkcast (4, 1)
	247 invokevirtual (4, 1)
	250 aload (4, 1)
	252 invokevirtual (4, 1)
	255 iconst_3 (4, 1)
	256 anewarray (4, 1)
	259 dup (4, 1)
	260 iconst_0 (4, 1)
	261 aload_2 (4, 1)
	262 aastore (4, 1)
	263 dup (4, 1)
	264 iconst_1 (4, 1)
	265 aload_3 (4, 1)
	266 aastore (4, 1)
	267 dup (4, 1)
	268 iconst_2 (4, 1)
	269 aload (4, 1)
	271 aastore (4, 1)
	272 invokespecial (4, 1)
	275 areturn (4, 1)
	276 aload_1 (4, 2)
	277 iconst_3 (4, 2)
	278 invokeinterface (4, 2)
	283 checkcast (4, 2)
	286 astore (4, 2)
	288 iconst_4 (5, 1)
	289 anewarray (5, 1)
	292 dup (5, 1)
	293 iconst_0 (5, 1)
	294 new (5, 1)
	297 dup (5, 1)
	298 aload_2 (5, 1)
	299 invokevirtual (5, 1)
	302 invokespecial (5, 1)
	305 aastore (5, 1)
	306 dup (5, 1)
	307 iconst_1 (5, 1)
	308 new (5, 1)
	311 dup (5, 1)
	312 aload_3 (5, 1)
	313 invokevirtual (5, 1)
	316 invokespecial (5, 1)
	319 aastore (5, 1)
	320 dup (5, 1)
	321 iconst_2 (5, 1)
	322 new (5, 1)
	325 dup (5, 1)
	326 aload (5, 1)
	328 invokevirtual (5, 1)
	331 invokespecial (5, 1)
	334 aastore (5, 1)
	335 dup (5, 1)
	336 iconst_3 (5, 1)
	337 new (5, 1)
	340 dup (5, 1)
	341 aload (5, 1)
	343 invokevirtual (5, 1)
	346 invokespecial (5, 1)
	349 aastore (5, 1)
	350 astore (5, 1)
	352 iconst_4 (5, 1)
	353 anewarray (5, 1)
	356 dup (5, 1)
	357 iconst_0 (5, 1)
	358 new (5, 1)
	361 dup (5, 1)
	362 aload_2 (5, 1)
	363 invokevirtual (5, 1)
	366 invokespecial (5, 1)
	369 aastore (5, 1)
	370 dup (5, 1)
	371 iconst_1 (5, 1)
	372 new (5, 1)
	375 dup (5, 1)
	376 aload_3 (5, 1)
	377 invokevirtual (5, 1)
	380 invokespecial (5, 1)
	383 aastore (5, 1)
	384 dup (5, 1)
	385 iconst_2 (5, 1)
	386 new (5, 1)
	389 dup (5, 1)
	390 aload (5, 1)
	392 invokevirtual (5, 1)
	395 invokespecial (5, 1)
	398 aastore (5, 1)
	399 dup (5, 1)
	400 iconst_3 (5, 1)
	401 new (5, 1)
	404 dup (5, 1)
	405 aload (5, 1)
	407 invokevirtual (5, 1)
	410 invokespecial (5, 1)
	413 aastore (5, 1)
	414 astore (5, 1)
	416 iconst_4 (5, 2)
	417 anewarray (5, 2)
	420 dup (5, 2)
	421 iconst_0 (5, 2)
	422 new (5, 2)
	425 dup (5, 2)
	426 aload_2 (5, 2)
	427 invokevirtual (5, 2)
	430 invokespecial (5, 2)
	433 aastore (5, 2)
	434 dup (5, 2)
	435 iconst_1 (5, 2)
	436 new (5, 2)
	439 dup (5, 2)
	440 aload_3 (5, 2)
	441 invokevirtual (5, 2)
	444 invokespecial (5, 2)
	447 aastore (5, 2)
	448 dup (5, 2)
	449 iconst_2 (5, 2)
	450 new (5, 2)
	453 dup (5, 2)
	454 aload (5, 2)
	456 invokevirtual (5, 2)
	459 invokespecial (5, 2)
	462 aastore (5, 2)
	463 dup (5, 2)
	464 iconst_3 (5, 2)
	465 new (5, 2)
	468 dup (5, 2)
	469 aload (5, 2)
	471 invokevirtual (5, 2)
	474 invokespecial (5, 2)
	477 aastore (5, 2)
	478 astore (5, 2)
	480 iconst_4 (5, 1)
	481 anewarray (5, 1)
	484 dup (5, 1)
	485 iconst_0 (5, 1)
	486 aload (5, 1)
	488 iconst_0 (5, 1)
	489 aaload (5, 1)
	490 aload (5, 1)
	492 iconst_0 (5, 1)
	493 aaload (5, 1)
	494 invokevirtual (5, 1)
	497 aload (5, 1)
	499 iconst_0 (5, 1)
	500 aaload (5, 1)
	501 aload (5, 1)
	503 iconst_0 (5, 1)
	504 aaload (5, 1)
	505 invokevirtual (5, 1)
	508 invokevirtual (5, 1)
	511 aload (5, 1)
	513 iconst_0 (5, 1)
	514 aaload (5, 1)
	515 aload (5, 1)
	517 iconst_0 (5, 1)
	518 aaload (5, 1)
	519 invokevirtual (5, 1)
	522 invokevirtual (5, 1)
	525 aastore (5, 1)
	526 dup (5, 1)
	527 iconst_1 (5, 1)
	528 aload (5, 1)
	530 iconst_1 (5, 1)
	531 aaload (5, 1)
	532 aload (5, 1)
	534 iconst_1 (5, 1)
	535 aaload (5, 1)
	536 invokevirtual (5, 1)
	539 aload (5, 1)
	541 iconst_1 (5, 1)
	542 aaload (5, 1)
	543 aload (5, 1)
	545 iconst_1 (5, 1)
	546 aaload (5, 1)
	547 invokevirtual (5, 1)
	550 invokevirtual (5, 1)
	553 aload (5, 1)
	555 iconst_1 (5, 1)
	556 aaload (5, 1)
	557 aload (5, 1)
	559 iconst_1 (5, 1)
	560 aaload (5, 1)
	561 invokevirtual (5, 1)
	564 invokevirtual (5, 1)
	567 aastore (5, 1)
	568 dup (5, 1)
	569 iconst_2 (5, 1)
	570 aload (5, 1)
	572 iconst_2 (5, 1)
	573 aaload (5, 1)
	574 aload (5, 1)
	576 iconst_2 (5, 1)
	577 aaload (5, 1)
	578 invokevirtual (5, 1)
	581 aload (5, 1)
	583 iconst_2 (5, 1)
	584 aaload (5, 1)
	585 aload (5, 1)
	587 iconst_2 (5, 1)
	588 aaload (5, 1)
	589 invokevirtual (5, 1)
	592 invokevirtual (5, 1)
	595 aload (5, 1)
	597 iconst_2 (5, 1)
	598 aaload (5, 1)
	599 aload (5, 1)
	601 iconst_2 (5, 1)
	602 aaload (5, 1)
	603 invokevirtual (5, 1)
	606 invokevirtual (5, 1)
	609 aastore (5, 1)
	610 dup (5, 1)
	611 iconst_3 (5, 1)
	612 aload (5, 1)
	614 iconst_3 (5, 1)
	615 aaload (5, 1)
	616 aload (5, 1)
	618 iconst_3 (5, 1)
	619 aaload (5, 1)
	620 invokevirtual (5, 1)
	623 aload (5, 1)
	625 iconst_3 (5, 1)
	626 aaload (5, 1)
	627 aload (5, 1)
	629 iconst_3 (5, 1)
	630 aaload (5, 1)
	631 invokevirtual (5, 1)
	634 invokevirtual (5, 1)
	637 aload (5, 1)
	639 iconst_3 (5, 1)
	640 aaload (5, 1)
	641 aload (5, 1)
	643 iconst_3 (5, 1)
	644 aaload (5, 1)
	645 invokevirtual (5, 1)
	648 invokevirtual (5, 1)
	651 aastore (5, 1)
	652 astore (5, 1)
	654 aload_0 (4, 2)
	655 aload (4, 2)
	657 aload (4, 2)
	659 aload (4, 2)
	661 invokespecial (4, 2)
	664 iconst_2 (4, 2)
	665 invokevirtual (4, 2)
	668 astore (4, 2)
	670 aload_0 (4, 2)
	671 aload (4, 2)
	673 aload (4, 2)
	675 aload (4, 2)
	677 invokespecial (4, 2)
	680 astore (4, 2)
	682 aload_0 (4, 2)
	683 aload (4, 2)
	685 aload (4, 2)
	687 aload (4, 2)
	689 invokespecial (4, 2)
	692 astore (4, 2)
	694 aload_0 (4, 2)
	695 aload (4, 2)
	697 aload (4, 2)
	699 aload (4, 2)
	701 invokespecial (4, 2)
	704 astore (4, 2)
	706 aload (4, 2)
	708 aload (4, 2)
	710 invokevirtual (4, 2)
	713 astore (4, 2)
	715 aload (4, 2)
	717 aload (4, 2)
	719 invokevirtual (4, 2)
	722 invokevirtual (4, 2)
	725 astore (4, 2)
	727 aload (4, 2)
	729 aload (4, 2)
	731 invokevirtual (4, 2)
	734 astore (4, 2)
	736 aload (4, 2)
	738 iconst_0 (4, 2)
	739 aaload (4, 2)
	740 aload (4, 2)
	742 invokevirtual (4, 2)
	745 astore (4, 2)
	747 aload (4, 2)
	749 iconst_0 (4, 2)
	750 aaload (4, 2)
	751 aload (4, 2)
	753 invokevirtual (4, 2)
	756 astore (4, 2)
	758 aload (4, 2)
	760 iconst_0 (4, 2)
	761 aaload (4, 2)
	762 aload (4, 2)
	764 invokevirtual (4, 2)
	767 astore (4, 2)
	769 aload (4, 2)
	771 aload (4, 2)
	773 invokevirtual (4, 2)
	776 aload (4, 2)
	778 aload (4, 2)
	780 invokevirtual (4, 2)
	783 invokevirtual (4, 2)
	786 aload (4, 2)
	788 aload (4, 2)
	790 invokevirtual (4, 2)
	793 invokevirtual (4, 2)
	796 astore (4, 2)
	798 new (4, 2)
	801 dup (4, 2)
	802 new (4, 2)
	805 dup (4, 2)
	806 aload (4, 2)
	808 invokevirtual (4, 2)
	811 aload (4, 2)
	813 invokevirtual (4, 2)
	816 aload (4, 2)
	818 invokevirtual (4, 2)
	821 invokespecial (4, 2)
	824 aload (4, 2)
	826 invokevirtual (4, 2)
	829 invokestatic (4, 2)
	832 iconst_4 (4, 2)
	833 anewarray (4, 2)
	836 dup (4, 2)
	837 iconst_0 (4, 2)
	838 aload_2 (4, 2)
	839 aastore (4, 2)
	840 dup (4, 2)
	841 iconst_1 (4, 2)
	842 aload_3 (4, 2)
	843 aastore (4, 2)
	844 dup (4, 2)
	845 iconst_2 (4, 2)
	846 aload (4, 2)
	848 aastore (4, 2)
	849 dup (4, 2)
	850 iconst_3 (4, 2)
	851 aload (4, 2)
	853 aastore (4, 2)
	854 invokespecial (4, 2)
	857 areturn (4, 2)

Method: minor
	0 aload_2 (0, 0)
	1 iconst_0 (0, 0)
	2 aaload (0, 0)
	3 aload_3 (0, 0)
	4 iconst_1 (0, 0)
	5 aaload (0, 0)
	6 invokevirtual (0, 0)
	9 aload_1 (0, 0)
	10 iconst_2 (0, 0)
	11 aaload (0, 0)
	12 aload_1 (0, 0)
	13 iconst_3 (0, 0)
	14 aaload (0, 0)
	15 invokevirtual (0, 0)
	18 invokevirtual (0, 0)
	21 aload_2 (0, 0)
	22 iconst_0 (0, 0)
	23 aaload (0, 0)
	24 aload_3 (0, 0)
	25 iconst_2 (0, 0)
	26 aaload (0, 0)
	27 invokevirtual (0, 0)
	30 aload_1 (0, 0)
	31 iconst_3 (0, 0)
	32 aaload (0, 0)
	33 aload_1 (0, 0)
	34 iconst_1 (0, 0)
	35 aaload (0, 0)
	36 invokevirtual (0, 0)
	39 invokevirtual (0, 0)
	42 invokevirtual (0, 0)
	45 aload_2 (0, 0)
	46 iconst_0 (0, 0)
	47 aaload (0, 0)
	48 aload_3 (0, 0)
	49 iconst_3 (0, 0)
	50 aaload (0, 0)
	51 invokevirtual (0, 0)
	54 aload_1 (0, 0)
	55 iconst_1 (0, 0)
	56 aaload (0, 0)
	57 aload_1 (0, 0)
	58 iconst_2 (0, 0)
	59 aaload (0, 0)
	60 invokevirtual (0, 0)
	63 invokevirtual (0, 0)
	66 invokevirtual (0, 0)
	69 aload_2 (0, 0)
	70 iconst_1 (0, 0)
	71 aaload (0, 0)
	72 aload_3 (0, 0)
	73 iconst_0 (0, 0)
	74 aaload (0, 0)
	75 invokevirtual (0, 0)
	78 aload_1 (0, 0)
	79 iconst_3 (0, 0)
	80 aaload (0, 0)
	81 aload_1 (0, 0)
	82 iconst_2 (0, 0)
	83 aaload (0, 0)
	84 invokevirtual (0, 0)
	87 invokevirtual (0, 0)
	90 invokevirtual (0, 0)
	93 aload_2 (0, 0)
	94 iconst_1 (0, 0)
	95 aaload (0, 0)
	96 aload_3 (0, 0)
	97 iconst_2 (0, 0)
	98 aaload (0, 0)
	99 invokevirtual (0, 0)
	102 aload_1 (0, 0)
	103 iconst_0 (0, 0)
	104 aaload (0, 0)
	105 aload_1 (0, 0)
	106 iconst_3 (0, 0)
	107 aaload (0, 0)
	108 invokevirtual (0, 0)
	111 invokevirtual (0, 0)
	114 invokevirtual (0, 0)
	117 aload_2 (0, 0)
	118 iconst_1 (0, 0)
	119 aaload (0, 0)
	120 aload_3 (0, 0)
	121 iconst_3 (0, 0)
	122 aaload (0, 0)
	123 invokevirtual (0, 0)
	126 aload_1 (0, 0)
	127 iconst_2 (0, 0)
	128 aaload (0, 0)
	129 aload_1 (0, 0)
	130 iconst_0 (0, 0)
	131 aaload (0, 0)
	132 invokevirtual (0, 0)
	135 invokevirtual (0, 0)
	138 invokevirtual (0, 0)
	141 aload_2 (0, 0)
	142 iconst_2 (0, 0)
	143 aaload (0, 0)
	144 aload_3 (0, 0)
	145 iconst_0 (0, 0)
	146 aaload (0, 0)
	147 invokevirtual (0, 0)
	150 aload_1 (0, 0)
	151 iconst_1 (0, 0)
	152 aaload (0, 0)
	153 aload_1 (0, 0)
	154 iconst_3 (0, 0)
	155 aaload (0, 0)
	156 invokevirtual (0, 0)
	159 invokevirtual (0, 0)
	162 invokevirtual (0, 0)
	165 aload_2 (0, 0)
	166 iconst_2 (0, 0)
	167 aaload (0, 0)
	168 aload_3 (0, 0)
	169 iconst_1 (0, 0)
	170 aaload (0, 0)
	171 invokevirtual (0, 0)
	174 aload_1 (0, 0)
	175 iconst_3 (0, 0)
	176 aaload (0, 0)
	177 aload_1 (0, 0)
	178 iconst_0 (0, 0)
	179 aaload (0, 0)
	180 invokevirtual (0, 0)
	183 invokevirtual (0, 0)
	186 invokevirtual (0, 0)
	189 aload_2 (0, 0)
	190 iconst_2 (0, 0)
	191 aaload (0, 0)
	192 aload_3 (0, 0)
	193 iconst_3 (0, 0)
	194 aaload (0, 0)
	195 invokevirtual (0, 0)
	198 aload_1 (0, 0)
	199 iconst_0 (0, 0)
	200 aaload (0, 0)
	201 aload_1 (0, 0)
	202 iconst_1 (0, 0)
	203 aaload (0, 0)
	204 invokevirtual (0, 0)
	207 invokevirtual (0, 0)
	210 invokevirtual (0, 0)
	213 aload_2 (0, 0)
	214 iconst_3 (0, 0)
	215 aaload (0, 0)
	216 aload_3 (0, 0)
	217 iconst_0 (0, 0)
	218 aaload (0, 0)
	219 invokevirtual (0, 0)
	222 aload_1 (0, 0)
	223 iconst_2 (0, 0)
	224 aaload (0, 0)
	225 aload_1 (0, 0)
	226 iconst_1 (0, 0)
	227 aaload (0, 0)
	228 invokevirtual (0, 0)
	231 invokevirtual (0, 0)
	234 invokevirtual (0, 0)
	237 aload_2 (0, 0)
	238 iconst_3 (0, 0)
	239 aaload (0, 0)
	240 aload_3 (0, 0)
	241 iconst_1 (0, 0)
	242 aaload (0, 0)
	243 invokevirtual (0, 0)
	246 aload_1 (0, 0)
	247 iconst_0 (0, 0)
	248 aaload (0, 0)
	249 aload_1 (0, 0)
	250 iconst_2 (0, 0)
	251 aaload (0, 0)
	252 invokevirtual (0, 0)
	255 invokevirtual (0, 0)
	258 invokevirtual (0, 0)
	261 aload_2 (0, 0)
	262 iconst_3 (0, 0)
	263 aaload (0, 0)
	264 aload_3 (0, 0)
	265 iconst_2 (0, 0)
	266 aaload (0, 0)
	267 invokevirtual (0, 0)
	270 aload_1 (0, 0)
	271 iconst_1 (0, 0)
	272 aaload (0, 0)
	273 aload_1 (0, 0)
	274 iconst_0 (0, 0)
	275 aaload (0, 0)
	276 invokevirtual (0, 0)
	279 invokevirtual (0, 0)
	282 invokevirtual (0, 0)
	285 areturn (0, 0)

