Method: <init>
	0 aload_0 (0, 4)
	1 aload_1 (0, 4)
	2 aload_2 (0, 4)
	3 aload_3 (0, 4)
	4 aload (0, 4)
	5 #4 (0, 4)
	6 invokespecial (0, 4)
	7 org/apache/commons/math3/geometry/VectorFormat.<init>:(Ljava/lang/String;Ljava/lang/String;Ljava/lang/String;Ljava/text/NumberFormat;)V (0, 4)
	9 return (0, 4)

Method: getInstance
	0 new (0, 0)
	1 org/apache/commons/math3/geometry/euclidean/threed/Vector3DFormat (0, 0)
	3 dup (0, 0)
	4 aload_0 (0, 0)
	5 invokestatic (0, 0)
	6 org/apache/commons/math3/util/CompositeFormat.getDefaultNumberFormat:(Ljava/util/Locale;)Ljava/text/NumberFormat; (0, 0)
	8 invokespecial (0, 0)
	9 org/apache/commons/math3/geometry/euclidean/threed/Vector3DFormat.<init>:(Ljava/text/NumberFormat;)V (0, 0)
	11 areturn (0, 0)

Method: format
	0 aload_1 (0, 0)
	1 checkcast (0, 0)
	2 org/apache/commons/math3/geometry/euclidean/threed/Vector3D (0, 0)
	4 astore (0, 0)
	5 #4 (0, 0)
	6 aload_0 (0, 4)
	7 aload_2 (0, 4)
	8 aload_3 (0, 4)
	9 iconst_3 (0, 4)
	10 newarray (0, 4)
	11 7 (0, 4)
	12 dup (0, 4)
	13 iconst_0 (0, 4)
	14 aload (0, 4)
	15 #4 (0, 4)
	16 invokevirtual (0, 4)
	17 org/apache/commons/math3/geometry/euclidean/threed/Vector3D.getX:()D (0, 4)
	19 dastore (0, 4)
	20 dup (0, 4)
	21 iconst_1 (0, 4)
	22 aload (0, 4)
	23 #4 (0, 4)
	24 invokevirtual (0, 4)
	25 org/apache/commons/math3/geometry/euclidean/threed/Vector3D.getY:()D (0, 4)
	27 dastore (0, 4)
	28 dup (0, 4)
	29 iconst_2 (0, 4)
	30 aload (0, 4)
	31 #4 (0, 4)
	32 invokevirtual (0, 4)
	33 org/apache/commons/math3/geometry/euclidean/threed/Vector3D.getZ:()D (0, 4)
	35 dastore (0, 4)
	36 invokevirtual (0, 4)
	37 org/apache/commons/math3/geometry/euclidean/threed/Vector3DFormat.format:(Ljava/lang/StringBuffer;Ljava/text/FieldPosition;[D)Ljava/lang/StringBuffer; (0, 4)
	39 areturn (0, 4)

Method: parse
	0 aload_0 (0, 0)
	1 aload_1 (0, 0)
	2 invokevirtual (0, 0)
	3 org/apache/commons/math3/geometry/euclidean/threed/Vector3DFormat.parse:(Ljava/lang/String;)Lorg/apache/commons/math3/geometry/euclidean/threed/Vector3D; (0, 0)
	5 areturn (0, 0)

