Method: <init>
	0 aload_0 (0, 0)
	1 invokespecial (0, 0)
	2 java/lang/Object.<init>:()V (0, 0)
	4 return (0, 0)

Method: getInstance
	0 invokestatic (0, 0)
	1 org/apache/commons/math3/geometry/euclidean/oned/Euclidean1D$LazyHolder.access$000:()Lorg/apache/commons/math3/geometry/euclidean/oned/Euclidean1D; (0, 0)
	3 areturn (0, 0)

Method: getDimension
	0 iconst_1 (0, 0)
	1 ireturn (0, 0)

Method: getSubSpace
	0 new (0, 0)
	1 org/apache/commons/math3/geometry/euclidean/oned/Euclidean1D$NoSubSpaceException (0, 0)
	3 dup (0, 0)
	4 invokespecial (0, 0)
	5 org/apache/commons/math3/geometry/euclidean/oned/Euclidean1D$NoSubSpaceException.<init>:()V (0, 0)
	7 athrow (0, 0)

Method: readResolve
	0 invokestatic (0, 0)
	1 org/apache/commons/math3/geometry/euclidean/oned/Euclidean1D$LazyHolder.access$000:()Lorg/apache/commons/math3/geometry/euclidean/oned/Euclidean1D; (0, 0)
	3 areturn (0, 0)

