Method: <init>
	0 aload_0 (0, 0)
	1 aload_1 (0, 0)
	2 ldc2_w (0, 0)
	3 1e-10 (0, 0)
	5 invokespecial (0, 0)
	6 org/apache/commons/math3/geometry/euclidean/oned/IntervalsSet.<init>:(Ljava/util/Collection;D)V (0, 0)
	8 return (0, 0)

Method: buildTree
	0 dload_0 (1, 1)
	1 invokestatic (1, 1)
	2 java/lang/Double.isInfinite:(D)Z (1, 1)
	4 ifeq (1, 1)
	5 87 (1, 1)
	7 dload_0 (1, 1)
	8 dconst_0 (1, 1)
	9 dcmpg (1, 1)
	10 ifge (1, 1)
	11 81 (1, 1)
	13 dload_2 (2, 1)
	14 invokestatic (2, 1)
	15 java/lang/Double.isInfinite:(D)Z (2, 1)
	17 ifeq (2, 1)
	18 20 (2, 1)
	20 dload_2 (2, 1)
	21 dconst_0 (2, 1)
	22 dcmpl (2, 1)
	23 ifle (2, 1)
	24 14 (2, 1)
	26 new (2, 1)
	27 org/apache/commons/math3/geometry/partitioning/BSPTree (2, 1)
	29 dup (2, 1)
	30 getstatic (2, 1)
	31 java/lang/Boolean.TRUE:Ljava/lang/Boolean; (2, 1)
	33 invokespecial (2, 1)
	34 org/apache/commons/math3/geometry/partitioning/BSPTree.<init>:(Ljava/lang/Object;)V (2, 1)
	36 areturn (2, 1)
	37 new (1, 1)
	38 org/apache/commons/math3/geometry/euclidean/oned/OrientedPoint (1, 1)
	40 dup (1, 1)
	41 new (1, 1)
	42 org/apache/commons/math3/geometry/euclidean/oned/Vector1D (1, 1)
	44 dup (1, 1)
	45 dload_2 (1, 1)
	46 invokespecial (1, 1)
	47 org/apache/commons/math3/geometry/euclidean/oned/Vector1D.<init>:(D)V (1, 1)
	49 iconst_1 (1, 1)
	50 dload (1, 1)
	51 #4 (1, 1)
	52 invokespecial (1, 1)
	53 org/apache/commons/math3/geometry/euclidean/oned/OrientedPoint.<init>:(Lorg/apache/commons/math3/geometry/euclidean/oned/Vector1D;ZD)V (1, 1)
	55 invokevirtual (1, 1)
	56 org/apache/commons/math3/geometry/euclidean/oned/OrientedPoint.wholeHyperplane:()Lorg/apache/commons/math3/geometry/euclidean/oned/SubOrientedPoint; (1, 1)
	58 astore (1, 1)
	59 #6 (1, 1)
	60 new (1, 1)
	61 org/apache/commons/math3/geometry/partitioning/BSPTree (1, 1)
	63 dup (1, 1)
	64 aload (1, 1)
	65 #6 (1, 1)
	66 new (1, 1)
	67 org/apache/commons/math3/geometry/partitioning/BSPTree (1, 1)
	69 dup (1, 1)
	70 getstatic (1, 1)
	71 java/lang/Boolean.FALSE:Ljava/lang/Boolean; (1, 1)
	73 invokespecial (1, 1)
	74 org/apache/commons/math3/geometry/partitioning/BSPTree.<init>:(Ljava/lang/Object;)V (1, 1)
	76 new (1, 1)
	77 org/apache/commons/math3/geometry/partitioning/BSPTree (1, 1)
	79 dup (1, 1)
	80 getstatic (1, 1)
	81 java/lang/Boolean.TRUE:Ljava/lang/Boolean; (1, 1)
	83 invokespecial (1, 1)
	84 org/apache/commons/math3/geometry/partitioning/BSPTree.<init>:(Ljava/lang/Object;)V (1, 1)
	86 aconst_null (1, 1)
	87 invokespecial (1, 1)
	88 org/apache/commons/math3/geometry/partitioning/BSPTree.<init>:(Lorg/apache/commons/math3/geometry/partitioning/SubHyperplane;Lorg/apache/commons/math3/geometry/partitioning/BSPTree;Lorg/apache/commons/math3/geometry/partitioning/BSPTree;Ljava/lang/Object;)V (1, 1)
	90 areturn (1, 1)
	91 new (0, 0)
	92 org/apache/commons/math3/geometry/euclidean/oned/OrientedPoint (0, 0)
	94 dup (0, 0)
	95 new (0, 0)
	96 org/apache/commons/math3/geometry/euclidean/oned/Vector1D (0, 0)
	98 dup (0, 0)
	99 dload_0 (0, 0)
	100 invokespecial (0, 0)
	101 org/apache/commons/math3/geometry/euclidean/oned/Vector1D.<init>:(D)V (0, 0)
	103 iconst_0 (0, 0)
	104 dload (0, 0)
	105 #4 (0, 0)
	106 invokespecial (0, 0)
	107 org/apache/commons/math3/geometry/euclidean/oned/OrientedPoint.<init>:(Lorg/apache/commons/math3/geometry/euclidean/oned/Vector1D;ZD)V (0, 0)
	109 invokevirtual (0, 0)
	110 org/apache/commons/math3/geometry/euclidean/oned/OrientedPoint.wholeHyperplane:()Lorg/apache/commons/math3/geometry/euclidean/oned/SubOrientedPoint; (0, 0)
	112 astore (0, 0)
	113 #6 (0, 0)
	114 dload_2 (1, 1)
	115 invokestatic (1, 1)
	116 java/lang/Double.isInfinite:(D)Z (1, 1)
	118 ifeq (1, 1)
	119 40 (1, 1)
	121 dload_2 (1, 1)
	122 dconst_0 (1, 1)
	123 dcmpl (1, 1)
	124 ifle (1, 1)
	125 34 (1, 1)
	127 new (1, 1)
	128 org/apache/commons/math3/geometry/partitioning/BSPTree (1, 1)
	130 dup (1, 1)
	131 aload (1, 1)
	132 #6 (1, 1)
	133 new (1, 1)
	134 org/apache/commons/math3/geometry/partitioning/BSPTree (1, 1)
	136 dup (1, 1)
	137 getstatic (1, 1)
	138 java/lang/Boolean.FALSE:Ljava/lang/Boolean; (1, 1)
	140 invokespecial (1, 1)
	141 org/apache/commons/math3/geometry/partitioning/BSPTree.<init>:(Ljava/lang/Object;)V (1, 1)
	143 new (1, 1)
	144 org/apache/commons/math3/geometry/partitioning/BSPTree (1, 1)
	146 dup (1, 1)
	147 getstatic (1, 1)
	148 java/lang/Boolean.TRUE:Ljava/lang/Boolean; (1, 1)
	150 invokespecial (1, 1)
	151 org/apache/commons/math3/geometry/partitioning/BSPTree.<init>:(Ljava/lang/Object;)V (1, 1)
	153 aconst_null (1, 1)
	154 invokespecial (1, 1)
	155 org/apache/commons/math3/geometry/partitioning/BSPTree.<init>:(Lorg/apache/commons/math3/geometry/partitioning/SubHyperplane;Lorg/apache/commons/math3/geometry/partitioning/BSPTree;Lorg/apache/commons/math3/geometry/partitioning/BSPTree;Ljava/lang/Object;)V (1, 1)
	157 areturn (1, 1)
	158 new (0, 0)
	159 org/apache/commons/math3/geometry/euclidean/oned/OrientedPoint (0, 0)
	161 dup (0, 0)
	162 new (0, 0)
	163 org/apache/commons/math3/geometry/euclidean/oned/Vector1D (0, 0)
	165 dup (0, 0)
	166 dload_2 (0, 0)
	167 invokespecial (0, 0)
	168 org/apache/commons/math3/geometry/euclidean/oned/Vector1D.<init>:(D)V (0, 0)
	170 iconst_1 (0, 0)
	171 dload (0, 0)
	172 #4 (0, 0)
	173 invokespecial (0, 0)
	174 org/apache/commons/math3/geometry/euclidean/oned/OrientedPoint.<init>:(Lorg/apache/commons/math3/geometry/euclidean/oned/Vector1D;ZD)V (0, 0)
	176 invokevirtual (0, 0)
	177 org/apache/commons/math3/geometry/euclidean/oned/OrientedPoint.wholeHyperplane:()Lorg/apache/commons/math3/geometry/euclidean/oned/SubOrientedPoint; (0, 0)
	179 astore (0, 0)
	180 #7 (0, 0)
	181 new (0, 0)
	182 org/apache/commons/math3/geometry/partitioning/BSPTree (0, 0)
	184 dup (0, 0)
	185 aload (0, 0)
	186 #6 (0, 0)
	187 new (0, 0)
	188 org/apache/commons/math3/geometry/partitioning/BSPTree (0, 0)
	190 dup (0, 0)
	191 getstatic (0, 0)
	192 java/lang/Boolean.FALSE:Ljava/lang/Boolean; (0, 0)
	194 invokespecial (0, 0)
	195 org/apache/commons/math3/geometry/partitioning/BSPTree.<init>:(Ljava/lang/Object;)V (0, 0)
	197 new (0, 0)
	198 org/apache/commons/math3/geometry/partitioning/BSPTree (0, 0)
	200 dup (0, 0)
	201 aload (0, 0)
	202 #7 (0, 0)
	203 new (0, 0)
	204 org/apache/commons/math3/geometry/partitioning/BSPTree (0, 0)
	206 dup (0, 0)
	207 getstatic (0, 0)
	208 java/lang/Boolean.FALSE:Ljava/lang/Boolean; (0, 0)
	210 invokespecial (0, 0)
	211 org/apache/commons/math3/geometry/partitioning/BSPTree.<init>:(Ljava/lang/Object;)V (0, 0)
	213 new (0, 0)
	214 org/apache/commons/math3/geometry/partitioning/BSPTree (0, 0)
	216 dup (0, 0)
	217 getstatic (0, 0)
	218 java/lang/Boolean.TRUE:Ljava/lang/Boolean; (0, 0)
	220 invokespecial (0, 0)
	221 org/apache/commons/math3/geometry/partitioning/BSPTree.<init>:(Ljava/lang/Object;)V (0, 0)
	223 aconst_null (0, 0)
	224 invokespecial (0, 0)
	225 org/apache/commons/math3/geometry/partitioning/BSPTree.<init>:(Lorg/apache/commons/math3/geometry/partitioning/SubHyperplane;Lorg/apache/commons/math3/geometry/partitioning/BSPTree;Lorg/apache/commons/math3/geometry/partitioning/BSPTree;Ljava/lang/Object;)V (0, 0)
	227 aconst_null (0, 0)
	228 invokespecial (0, 0)
	229 org/apache/commons/math3/geometry/partitioning/BSPTree.<init>:(Lorg/apache/commons/math3/geometry/partitioning/SubHyperplane;Lorg/apache/commons/math3/geometry/partitioning/BSPTree;Lorg/apache/commons/math3/geometry/partitioning/BSPTree;Ljava/lang/Object;)V (0, 0)
	231 areturn (0, 0)

Method: buildNew
	0 aload_0 (0, 0)
	1 aload_1 (0, 0)
	2 invokevirtual (0, 0)
	3 org/apache/commons/math3/geometry/euclidean/oned/IntervalsSet.buildNew:(Lorg/apache/commons/math3/geometry/partitioning/BSPTree;)Lorg/apache/commons/math3/geometry/euclidean/oned/IntervalsSet; (0, 0)
	5 areturn (0, 0)

Method: computeGeometricalProperties
	0 aload_0 (1, 1)
	1 iconst_0 (1, 1)
	2 invokevirtual (1, 1)
	3 org/apache/commons/math3/geometry/euclidean/oned/IntervalsSet.getTree:(Z)Lorg/apache/commons/math3/geometry/partitioning/BSPTree; (1, 1)
	5 invokevirtual (1, 1)
	6 org/apache/commons/math3/geometry/partitioning/BSPTree.getCut:()Lorg/apache/commons/math3/geometry/partitioning/SubHyperplane; (1, 1)
	8 ifnonnull (1, 1)
	9 41 (1, 1)
	11 aload_0 (1, 1)
	12 getstatic (1, 1)
	13 org/apache/commons/math3/geometry/euclidean/oned/Vector1D.NaN:Lorg/apache/commons/math3/geometry/euclidean/oned/Vector1D; (1, 1)
	15 invokevirtual (1, 1)
	16 org/apache/commons/math3/geometry/euclidean/oned/IntervalsSet.setBarycenter:(Lorg/apache/commons/math3/geometry/Point;)V (1, 1)
	18 aload_0 (1, 1)
	19 aload_0 (1, 1)
	20 iconst_0 (1, 1)
	21 invokevirtual (1, 1)
	22 org/apache/commons/math3/geometry/euclidean/oned/IntervalsSet.getTree:(Z)Lorg/apache/commons/math3/geometry/partitioning/BSPTree; (1, 1)
	24 invokevirtual (1, 1)
	25 org/apache/commons/math3/geometry/partitioning/BSPTree.getAttribute:()Ljava/lang/Object; (1, 1)
	27 checkcast (1, 1)
	28 java/lang/Boolean (1, 1)
	30 invokevirtual (1, 1)
	31 java/lang/Boolean.booleanValue:()Z (1, 1)
	33 ifeq (1, 1)
	34 9 (1, 1)
	36 ldc2_w (1, 1)
	37 inf (1, 1)
	39 goto (1, 1)
	40 4 (1, 1)
	42 dconst_0 (1, 1)
	43 invokevirtual (1, 1)
	44 org/apache/commons/math3/geometry/euclidean/oned/IntervalsSet.setSize:(D)V (1, 1)
	46 goto (1, 1)
	47 135 (1, 1)
	49 dconst_0 (2, 2)
	50 dstore_1 (2, 2)
	51 dconst_0 (2, 2)
	52 dstore_3 (2, 2)
	53 aload_0 (3, 4)
	54 invokevirtual (3, 4)
	55 org/apache/commons/math3/geometry/euclidean/oned/IntervalsSet.asList:()Ljava/util/List; (3, 4)
	57 invokeinterface (3, 4)
	58 java/util/List.java/util/Iterator (3, 4)
	60 0 (3, 4)
	62 astore (3, 4)
	63 #5 (3, 4)
	64 aload (3, 4)
	65 #5 (3, 4)
	66 invokeinterface (3, 4)
	67 java/util/Iterator.next:()Ljava/lang/Object; (3, 4)
	69 0 (3, 4)
	71 ifeq (3, 4)
	72 40 (3, 4)
	74 aload (3, 4)
	75 #5 (3, 4)
	76 invokeinterface (3, 4)
	77 java/util/Iterator.org/apache/commons/math3/geometry/euclidean/oned/Interval (3, 4)
	79 0 (3, 4)
	81 checkcast (3, 4)
	82 org/apache/commons/math3/geometry/euclidean/oned/Interval (3, 4)
	84 astore (3, 4)
	85 #6 (3, 4)
	86 dload_1 (3, 4)
	87 aload (3, 4)
	88 #6 (3, 4)
	89 invokevirtual (3, 4)
	90 org/apache/commons/math3/geometry/euclidean/oned/Interval.getSize:()D (3, 4)
	92 dadd (3, 4)
	93 dstore_1 (3, 4)
	94 dload_3 (3, 4)
	95 aload (3, 4)
	96 #6 (3, 4)
	97 invokevirtual (3, 4)
	98 org/apache/commons/math3/geometry/euclidean/oned/Interval.getSize:()D (3, 4)
	100 aload (3, 4)
	101 #6 (3, 4)
	102 invokevirtual (3, 4)
	103 org/apache/commons/math3/geometry/euclidean/oned/Interval.getBarycenter:()D (3, 4)
	105 dmul (3, 4)
	106 dadd (3, 4)
	107 dstore_3 (3, 4)
	108 goto (2, 2)
	109 -44 (2, 2)
	111 aload_0 (2, 2)
	112 dload_1 (2, 2)
	113 invokevirtual (2, 2)
	114 org/apache/commons/math3/geometry/euclidean/oned/IntervalsSet.setSize:(D)V (2, 2)
	116 dload_1 (3, 1)
	117 invokestatic (3, 1)
	118 java/lang/Double.isInfinite:(D)Z (3, 1)
	120 ifeq (3, 1)
	121 13 (3, 1)
	123 aload_0 (3, 1)
	124 getstatic (3, 1)
	125 org/apache/commons/math3/geometry/euclidean/oned/Vector1D.NaN:Lorg/apache/commons/math3/geometry/euclidean/oned/Vector1D; (3, 1)
	127 invokevirtual (3, 1)
	128 org/apache/commons/math3/geometry/euclidean/oned/IntervalsSet.setBarycenter:(Lorg/apache/commons/math3/geometry/Point;)V (3, 1)
	130 goto (3, 1)
	131 51 (3, 1)
	133 dload_1 (4, 1)
	134 getstatic (4, 1)
	135 org/apache/commons/math3/util/Precision.SAFE_MIN:D (4, 1)
	137 dcmpl (4, 1)
	138 iflt (4, 1)
	139 20 (4, 1)
	141 aload_0 (4, 1)
	142 new (4, 1)
	143 org/apache/commons/math3/geometry/euclidean/oned/Vector1D (4, 1)
	145 dup (4, 1)
	146 dload_3 (4, 1)
	147 dload_1 (4, 1)
	148 ddiv (4, 1)
	149 invokespecial (4, 1)
	150 org/apache/commons/math3/geometry/euclidean/oned/Vector1D.<init>:(D)V (4, 1)
	152 invokevirtual (4, 1)
	153 org/apache/commons/math3/geometry/euclidean/oned/IntervalsSet.setBarycenter:(Lorg/apache/commons/math3/geometry/Point;)V (4, 1)
	155 goto (4, 1)
	156 26 (4, 1)
	158 aload_0 (5, 2)
	159 aload_0 (5, 2)
	160 iconst_0 (5, 2)
	161 invokevirtual (5, 2)
	162 org/apache/commons/math3/geometry/euclidean/oned/IntervalsSet.getTree:(Z)Lorg/apache/commons/math3/geometry/partitioning/BSPTree; (5, 2)
	164 invokevirtual (5, 2)
	165 org/apache/commons/math3/geometry/partitioning/BSPTree.getCut:()Lorg/apache/commons/math3/geometry/partitioning/SubHyperplane; (5, 2)
	167 invokeinterface (5, 2)
	168 org/apache/commons/math3/geometry/partitioning/SubHyperplane.getLocation:()Lorg/apache/commons/math3/geometry/euclidean/oned/Vector1D; (5, 2)
	170 0 (5, 2)
	172 checkcast (5, 2)
	173 org/apache/commons/math3/geometry/euclidean/oned/OrientedPoint (5, 2)
	175 invokevirtual (5, 2)
	176 org/apache/commons/math3/geometry/euclidean/oned/OrientedPoint.getLocation:()Lorg/apache/commons/math3/geometry/euclidean/oned/Vector1D; (5, 2)
	178 invokevirtual (5, 2)
	179 org/apache/commons/math3/geometry/euclidean/oned/IntervalsSet.setBarycenter:(Lorg/apache/commons/math3/geometry/Point;)V (5, 2)
	181 return (0, 0)

Method: getInf
	0 aload_0 (0, 0)
	1 iconst_0 (0, 0)
	2 invokevirtual (0, 0)
	3 org/apache/commons/math3/geometry/euclidean/oned/IntervalsSet.getTree:(Z)Lorg/apache/commons/math3/geometry/partitioning/BSPTree; (0, 0)
	5 astore_1 (0, 0)
	6 ldc2_w (0, 0)
	7 inf (0, 0)
	9 dstore_2 (0, 0)
	10 aload_1 (1, 3)
	11 invokevirtual (1, 3)
	12 org/apache/commons/math3/geometry/partitioning/BSPTree.getCut:()Lorg/apache/commons/math3/geometry/partitioning/SubHyperplane; (1, 3)
	14 ifnull (1, 3)
	15 49 (1, 3)
	17 aload_1 (1, 3)
	18 invokevirtual (1, 3)
	19 org/apache/commons/math3/geometry/partitioning/BSPTree.getCut:()Lorg/apache/commons/math3/geometry/partitioning/SubHyperplane; (1, 3)
	21 invokeinterface (1, 3)
	22 org/apache/commons/math3/geometry/partitioning/SubHyperplane.getLocation:()Lorg/apache/commons/math3/geometry/euclidean/oned/Vector1D; (1, 3)
	24 0 (1, 3)
	26 checkcast (1, 3)
	27 org/apache/commons/math3/geometry/euclidean/oned/OrientedPoint (1, 3)
	29 astore (1, 3)
	30 #4 (1, 3)
	31 aload (1, 3)
	32 #4 (1, 3)
	33 invokevirtual (1, 3)
	34 org/apache/commons/math3/geometry/euclidean/oned/OrientedPoint.getLocation:()Lorg/apache/commons/math3/geometry/euclidean/oned/Vector1D; (1, 3)
	36 invokevirtual (1, 3)
	37 org/apache/commons/math3/geometry/euclidean/oned/Vector1D.getX:()D (1, 3)
	39 dstore_2 (1, 3)
	40 aload (1, 3)
	41 #4 (1, 3)
	42 invokevirtual (1, 3)
	43 org/apache/commons/math3/geometry/euclidean/oned/OrientedPoint.isDirect:()Z (1, 3)
	45 ifeq (1, 3)
	46 10 (1, 3)
	48 aload_1 (1, 3)
	49 invokevirtual (1, 3)
	50 org/apache/commons/math3/geometry/partitioning/BSPTree.getMinus:()Lorg/apache/commons/math3/geometry/partitioning/BSPTree; (1, 3)
	52 goto (1, 3)
	53 7 (1, 3)
	55 aload_1 (1, 3)
	56 invokevirtual (1, 3)
	57 org/apache/commons/math3/geometry/partitioning/BSPTree.getPlus:()Lorg/apache/commons/math3/geometry/partitioning/BSPTree; (1, 3)
	59 astore_1 (1, 3)
	60 goto (0, 0)
	61 -50 (0, 0)
	63 aload_1 (0, 0)
	64 invokevirtual (0, 0)
	65 org/apache/commons/math3/geometry/partitioning/BSPTree.getAttribute:()Ljava/lang/Object; (0, 0)
	67 checkcast (0, 0)
	68 java/lang/Boolean (0, 0)
	70 invokevirtual (0, 0)
	71 java/lang/Boolean.booleanValue:()Z (0, 0)
	73 ifeq (0, 0)
	74 9 (0, 0)
	76 ldc2_w (0, 0)
	77 -inf (0, 0)
	79 goto (0, 0)
	80 4 (0, 0)
	82 dload_2 (0, 0)
	83 dreturn (0, 0)

Method: getSup
	0 aload_0 (0, 0)
	1 iconst_0 (0, 0)
	2 invokevirtual (0, 0)
	3 org/apache/commons/math3/geometry/euclidean/oned/IntervalsSet.getTree:(Z)Lorg/apache/commons/math3/geometry/partitioning/BSPTree; (0, 0)
	5 astore_1 (0, 0)
	6 ldc2_w (0, 0)
	7 -inf (0, 0)
	9 dstore_2 (0, 0)
	10 aload_1 (1, 3)
	11 invokevirtual (1, 3)
	12 org/apache/commons/math3/geometry/partitioning/BSPTree.getCut:()Lorg/apache/commons/math3/geometry/partitioning/SubHyperplane; (1, 3)
	14 ifnull (1, 3)
	15 49 (1, 3)
	17 aload_1 (1, 3)
	18 invokevirtual (1, 3)
	19 org/apache/commons/math3/geometry/partitioning/BSPTree.getCut:()Lorg/apache/commons/math3/geometry/partitioning/SubHyperplane; (1, 3)
	21 invokeinterface (1, 3)
	22 org/apache/commons/math3/geometry/partitioning/SubHyperplane.getLocation:()Lorg/apache/commons/math3/geometry/euclidean/oned/Vector1D; (1, 3)
	24 0 (1, 3)
	26 checkcast (1, 3)
	27 org/apache/commons/math3/geometry/euclidean/oned/OrientedPoint (1, 3)
	29 astore (1, 3)
	30 #4 (1, 3)
	31 aload (1, 3)
	32 #4 (1, 3)
	33 invokevirtual (1, 3)
	34 org/apache/commons/math3/geometry/euclidean/oned/OrientedPoint.getLocation:()Lorg/apache/commons/math3/geometry/euclidean/oned/Vector1D; (1, 3)
	36 invokevirtual (1, 3)
	37 org/apache/commons/math3/geometry/euclidean/oned/Vector1D.getX:()D (1, 3)
	39 dstore_2 (1, 3)
	40 aload (1, 3)
	41 #4 (1, 3)
	42 invokevirtual (1, 3)
	43 org/apache/commons/math3/geometry/euclidean/oned/OrientedPoint.isDirect:()Z (1, 3)
	45 ifeq (1, 3)
	46 10 (1, 3)
	48 aload_1 (1, 3)
	49 invokevirtual (1, 3)
	50 org/apache/commons/math3/geometry/partitioning/BSPTree.getPlus:()Lorg/apache/commons/math3/geometry/partitioning/BSPTree; (1, 3)
	52 goto (1, 3)
	53 7 (1, 3)
	55 aload_1 (1, 3)
	56 invokevirtual (1, 3)
	57 org/apache/commons/math3/geometry/partitioning/BSPTree.getMinus:()Lorg/apache/commons/math3/geometry/partitioning/BSPTree; (1, 3)
	59 astore_1 (1, 3)
	60 goto (0, 0)
	61 -50 (0, 0)
	63 aload_1 (0, 0)
	64 invokevirtual (0, 0)
	65 org/apache/commons/math3/geometry/partitioning/BSPTree.getAttribute:()Ljava/lang/Object; (0, 0)
	67 checkcast (0, 0)
	68 java/lang/Boolean (0, 0)
	70 invokevirtual (0, 0)
	71 java/lang/Boolean.booleanValue:()Z (0, 0)
	73 ifeq (0, 0)
	74 9 (0, 0)
	76 ldc2_w (0, 0)
	77 inf (0, 0)
	79 goto (0, 0)
	80 4 (0, 0)
	82 dload_2 (0, 0)
	83 dreturn (0, 0)

Method: projectToBoundary
	0 aload_1 (0, 0)
	1 checkcast (0, 0)
	2 org/apache/commons/math3/geometry/euclidean/oned/Vector1D (0, 0)
	4 invokevirtual (0, 0)
	5 org/apache/commons/math3/geometry/euclidean/oned/Vector1D.getX:()D (0, 0)
	7 dstore_2 (0, 0)
	8 ldc2_w (0, 0)
	9 -inf (0, 0)
	11 dstore (0, 0)
	12 #4 (0, 0)
	13 aload_0 (1, 4)
	14 invokevirtual (1, 4)
	15 org/apache/commons/math3/geometry/euclidean/oned/IntervalsSet.iterator:()Ljava/util/Iterator; (1, 4)
	17 astore (1, 4)
	18 #6 (1, 4)
	19 aload (1, 4)
	20 #6 (1, 4)
	21 invokeinterface (1, 4)
	22 java/util/Iterator.next:()Ljava/lang/Object; (1, 4)
	24 0 (1, 4)
	26 ifeq (1, 4)
	27 162 (1, 4)
	29 aload (1, 4)
	30 #6 (1, 4)
	31 invokeinterface (1, 4)
	32 java/util/Iterator.org/apache/commons/math3/geometry/euclidean/oned/Interval (1, 4)
	34 0 (1, 4)
	36 checkcast (1, 4)
	37 [D (1, 4)
	39 astore (1, 4)
	40 #7 (1, 4)
	41 dload_2 (2, 1)
	42 aload (2, 1)
	43 #7 (2, 1)
	44 iconst_0 (2, 1)
	45 daload (2, 1)
	46 dcmpg (2, 1)
	47 ifge (2, 1)
	48 61 (2, 1)
	50 dload_2 (2, 1)
	51 dload (2, 1)
	52 #4 (2, 1)
	53 dsub (2, 1)
	54 dstore (2, 1)
	55 #8 (2, 1)
	56 aload (2, 1)
	57 #7 (2, 1)
	58 iconst_0 (2, 1)
	59 daload (2, 1)
	60 dload_2 (2, 1)
	61 dsub (2, 1)
	62 dstore (2, 1)
	63 #10 (2, 1)
	64 dload (3, 1)
	65 #8 (3, 1)
	66 dload (3, 1)
	67 #10 (3, 1)
	68 dcmpg (3, 1)
	69 ifge (3, 1)
	70 20 (3, 1)
	72 new (3, 1)
	73 org/apache/commons/math3/geometry/partitioning/BoundaryProjection (3, 1)
	75 dup (3, 1)
	76 aload_1 (3, 1)
	77 aload_0 (3, 1)
	78 dload (3, 1)
	79 #4 (3, 1)
	80 invokespecial (3, 1)
	81 org/apache/commons/math3/geometry/euclidean/oned/IntervalsSet.finiteOrNullPoint:(D)Lorg/apache/commons/math3/geometry/euclidean/oned/Vector1D; (3, 1)
	83 dload (3, 1)
	84 #8 (3, 1)
	85 invokespecial (3, 1)
	86 org/apache/commons/math3/geometry/partitioning/BoundaryProjection.<init>:(Lorg/apache/commons/math3/geometry/Point;Lorg/apache/commons/math3/geometry/Point;D)V (3, 1)
	88 areturn (3, 1)
	89 new (4, 2)
	90 org/apache/commons/math3/geometry/partitioning/BoundaryProjection (4, 2)
	92 dup (4, 2)
	93 aload_1 (4, 2)
	94 aload_0 (4, 2)
	95 aload (4, 2)
	96 #7 (4, 2)
	97 iconst_0 (4, 2)
	98 daload (4, 2)
	99 invokespecial (4, 2)
	100 org/apache/commons/math3/geometry/euclidean/oned/IntervalsSet.finiteOrNullPoint:(D)Lorg/apache/commons/math3/geometry/euclidean/oned/Vector1D; (4, 2)
	102 dload (4, 2)
	103 #10 (4, 2)
	104 invokespecial (4, 2)
	105 org/apache/commons/math3/geometry/partitioning/BoundaryProjection.<init>:(Lorg/apache/commons/math3/geometry/Point;Lorg/apache/commons/math3/geometry/Point;D)V (4, 2)
	107 areturn (4, 2)
	108 dload_2 (3, 1)
	109 aload (3, 1)
	110 #7 (3, 1)
	111 iconst_1 (3, 1)
	112 daload (3, 1)
	113 dcmpg (3, 1)
	114 ifgt (3, 1)
	115 65 (3, 1)
	117 aload (3, 1)
	118 #7 (3, 1)
	119 iconst_0 (3, 1)
	120 daload (3, 1)
	121 dload_2 (3, 1)
	122 dsub (3, 1)
	123 dstore (3, 1)
	124 #8 (3, 1)
	125 dload_2 (3, 1)
	126 aload (3, 1)
	127 #7 (3, 1)
	128 iconst_1 (3, 1)
	129 daload (3, 1)
	130 dsub (3, 1)
	131 dstore (3, 1)
	132 #10 (3, 1)
	133 dload (4, 1)
	134 #8 (4, 1)
	135 dload (4, 1)
	136 #10 (4, 1)
	137 dcmpg (4, 1)
	138 ifge (4, 1)
	139 22 (4, 1)
	141 new (4, 1)
	142 org/apache/commons/math3/geometry/partitioning/BoundaryProjection (4, 1)
	144 dup (4, 1)
	145 aload_1 (4, 1)
	146 aload_0 (4, 1)
	147 aload (4, 1)
	148 #7 (4, 1)
	149 iconst_1 (4, 1)
	150 daload (4, 1)
	151 invokespecial (4, 1)
	152 org/apache/commons/math3/geometry/euclidean/oned/IntervalsSet.finiteOrNullPoint:(D)Lorg/apache/commons/math3/geometry/euclidean/oned/Vector1D; (4, 1)
	154 dload (4, 1)
	155 #10 (4, 1)
	156 invokespecial (4, 1)
	157 org/apache/commons/math3/geometry/partitioning/BoundaryProjection.<init>:(Lorg/apache/commons/math3/geometry/Point;Lorg/apache/commons/math3/geometry/Point;D)V (4, 1)
	159 areturn (4, 1)
	160 new (5, 2)
	161 org/apache/commons/math3/geometry/partitioning/BoundaryProjection (5, 2)
	163 dup (5, 2)
	164 aload_1 (5, 2)
	165 aload_0 (5, 2)
	166 aload (5, 2)
	167 #7 (5, 2)
	168 iconst_0 (5, 2)
	169 daload (5, 2)
	170 invokespecial (5, 2)
	171 org/apache/commons/math3/geometry/euclidean/oned/IntervalsSet.finiteOrNullPoint:(D)Lorg/apache/commons/math3/geometry/euclidean/oned/Vector1D; (5, 2)
	173 dload (5, 2)
	174 #8 (5, 2)
	175 invokespecial (5, 2)
	176 org/apache/commons/math3/geometry/partitioning/BoundaryProjection.<init>:(Lorg/apache/commons/math3/geometry/Point;Lorg/apache/commons/math3/geometry/Point;D)V (5, 2)
	178 areturn (5, 2)
	179 aload (1, 4)
	180 #7 (1, 4)
	181 iconst_1 (1, 4)
	182 daload (1, 4)
	183 dstore (1, 4)
	184 #4 (1, 4)
	185 goto (0, 0)
	186 -166 (0, 0)
	188 new (1, 1)
	189 org/apache/commons/math3/geometry/partitioning/BoundaryProjection (1, 1)
	191 dup (1, 1)
	192 aload_1 (1, 1)
	193 aload_0 (1, 1)
	194 dload (1, 1)
	195 #4 (1, 1)
	196 invokespecial (1, 1)
	197 org/apache/commons/math3/geometry/euclidean/oned/IntervalsSet.finiteOrNullPoint:(D)Lorg/apache/commons/math3/geometry/euclidean/oned/Vector1D; (1, 1)
	199 dload_2 (1, 1)
	200 dload (1, 1)
	201 #4 (1, 1)
	202 dsub (1, 1)
	203 invokespecial (1, 1)
	204 org/apache/commons/math3/geometry/partitioning/BoundaryProjection.<init>:(Lorg/apache/commons/math3/geometry/Point;Lorg/apache/commons/math3/geometry/Point;D)V (1, 1)
	206 areturn (0, 1)

Method: finiteOrNullPoint
	0 dload_1 (0, 0)
	1 invokestatic (0, 0)
	2 java/lang/Double.isInfinite:(D)Z (0, 0)
	4 ifeq (0, 0)
	5 7 (0, 0)
	7 aconst_null (0, 0)
	8 goto (0, 0)
	9 11 (0, 0)
	11 new (0, 0)
	12 org/apache/commons/math3/geometry/euclidean/oned/Vector1D (0, 0)
	14 dup (0, 0)
	15 dload_1 (0, 0)
	16 invokespecial (0, 0)
	17 org/apache/commons/math3/geometry/euclidean/oned/Vector1D.<init>:(D)V (0, 0)
	19 areturn (0, 0)

Method: asList
	0 new (0, 0)
	1 java/util/ArrayList (0, 0)
	3 dup (0, 0)
	4 invokespecial (0, 0)
	5 java/util/ArrayList.<init>:()V (0, 0)
	7 astore_1 (0, 0)
	8 aload_0 (1, 4)
	9 invokevirtual (1, 4)
	10 org/apache/commons/math3/geometry/euclidean/oned/IntervalsSet.iterator:()Ljava/util/Iterator; (1, 4)
	12 astore_2 (1, 4)
	13 aload_2 (1, 4)
	14 invokeinterface (1, 4)
	15 java/util/Iterator.next:()Ljava/lang/Object; (1, 4)
	17 0 (1, 4)
	19 ifeq (1, 4)
	20 36 (1, 4)
	22 aload_2 (1, 4)
	23 invokeinterface (1, 4)
	24 java/util/Iterator.org/apache/commons/math3/geometry/euclidean/oned/Interval (1, 4)
	26 0 (1, 4)
	28 checkcast (1, 4)
	29 [D (1, 4)
	31 astore_3 (1, 4)
	32 aload_1 (1, 4)
	33 new (1, 4)
	34 org/apache/commons/math3/geometry/euclidean/oned/Interval (1, 4)
	36 dup (1, 4)
	37 aload_3 (1, 4)
	38 iconst_0 (1, 4)
	39 daload (1, 4)
	40 aload_3 (1, 4)
	41 iconst_1 (1, 4)
	42 daload (1, 4)
	43 invokespecial (1, 4)
	44 org/apache/commons/math3/geometry/euclidean/oned/Interval.<init>:(DD)V (1, 4)
	46 invokeinterface (1, 4)
	47 java/util/List.previousInternalNode:(Lorg/apache/commons/math3/geometry/partitioning/BSPTree;)Lorg/apache/commons/math3/geometry/partitioning/BSPTree; (1, 4)
	49 0 (1, 4)
	51 pop (1, 4)
	52 goto (0, 0)
	53 -39 (0, 0)
	55 aload_1 (0, 0)
	56 areturn (0, 0)

Method: getFirstLeaf
	0 aload_1 (1, 1)
	1 invokevirtual (1, 1)
	2 org/apache/commons/math3/geometry/partitioning/BSPTree.getCut:()Lorg/apache/commons/math3/geometry/partitioning/SubHyperplane; (1, 1)
	4 ifnonnull (1, 1)
	5 5 (1, 1)
	7 aload_1 (1, 1)
	8 areturn (1, 1)
	9 aconst_null (0, 0)
	10 astore_2 (0, 0)
	11 aload_1 (1, 4)
	12 astore_3 (1, 4)
	13 aload_3 (1, 4)
	14 ifnull (1, 4)
	15 14 (1, 4)
	17 aload_3 (1, 4)
	18 astore_2 (1, 4)
	19 aload_0 (1, 4)
	20 aload_3 (1, 4)
	21 invokespecial (1, 4)
	22 org/apache/commons/math3/geometry/euclidean/oned/IntervalsSet.previousInternalNode:(Lorg/apache/commons/math3/geometry/partitioning/BSPTree;)Lorg/apache/commons/math3/geometry/partitioning/BSPTree; (1, 4)
	24 astore_3 (1, 4)
	25 goto (1, 4)
	26 -12 (1, 4)
	28 aload_0 (1, 4)
	29 aload_2 (1, 4)
	30 invokespecial (1, 4)
	31 org/apache/commons/math3/geometry/euclidean/oned/IntervalsSet.leafBefore:(Lorg/apache/commons/math3/geometry/partitioning/BSPTree;)Lorg/apache/commons/math3/geometry/partitioning/BSPTree; (1, 4)
	33 areturn (0, 4)

Method: getFirstIntervalBoundary
	0 aload_0 (0, 0)
	1 iconst_0 (0, 0)
	2 invokevirtual (0, 0)
	3 org/apache/commons/math3/geometry/euclidean/oned/IntervalsSet.getTree:(Z)Lorg/apache/commons/math3/geometry/partitioning/BSPTree; (0, 0)
	5 astore_1 (0, 0)
	6 aload_1 (1, 1)
	7 invokevirtual (1, 1)
	8 org/apache/commons/math3/geometry/partitioning/BSPTree.getCut:()Lorg/apache/commons/math3/geometry/partitioning/SubHyperplane; (1, 1)
	10 ifnonnull (1, 1)
	11 5 (1, 1)
	13 aconst_null (1, 1)
	14 areturn (1, 1)
	15 aload_0 (0, 0)
	16 aload_1 (0, 0)
	17 invokespecial (0, 0)
	18 org/apache/commons/math3/geometry/euclidean/oned/IntervalsSet.getFirstLeaf:(Lorg/apache/commons/math3/geometry/partitioning/BSPTree;)Lorg/apache/commons/math3/geometry/partitioning/BSPTree; (0, 0)
	20 invokevirtual (0, 0)
	21 org/apache/commons/math3/geometry/partitioning/BSPTree.getParent:()Lorg/apache/commons/math3/geometry/partitioning/BSPTree; (0, 0)
	23 astore_1 (0, 0)
	24 aload_1 (1, 3)
	25 ifnull (1, 3)
	26 28 (1, 3)
	28 aload_0 (1, 3)
	29 aload_1 (1, 3)
	30 invokespecial (1, 3)
	31 org/apache/commons/math3/geometry/euclidean/oned/IntervalsSet.isIntervalStart:(Lorg/apache/commons/math3/geometry/partitioning/BSPTree;)Z (1, 3)
	33 ifne (1, 3)
	34 20 (1, 3)
	36 aload_0 (1, 3)
	37 aload_1 (1, 3)
	38 invokespecial (1, 3)
	39 org/apache/commons/math3/geometry/euclidean/oned/IntervalsSet.isIntervalEnd:(Lorg/apache/commons/math3/geometry/partitioning/BSPTree;)Z (1, 3)
	41 ifne (1, 3)
	42 12 (1, 3)
	44 aload_0 (1, 3)
	45 aload_1 (1, 3)
	46 invokespecial (1, 3)
	47 org/apache/commons/math3/geometry/euclidean/oned/IntervalsSet.nextInternalNode:(Lorg/apache/commons/math3/geometry/partitioning/BSPTree;)Lorg/apache/commons/math3/geometry/partitioning/BSPTree; (1, 3)
	49 astore_1 (1, 3)
	50 goto (1, 3)
	51 -26 (1, 3)
	53 aload_1 (0, 0)
	54 areturn (0, 0)

Method: isIntervalStart
	0 aload_0 (1, 1)
	1 aload_1 (1, 1)
	2 invokespecial (1, 1)
	3 org/apache/commons/math3/geometry/euclidean/oned/IntervalsSet.leafBefore:(Lorg/apache/commons/math3/geometry/partitioning/BSPTree;)Lorg/apache/commons/math3/geometry/partitioning/BSPTree; (1, 1)
	5 invokevirtual (1, 1)
	6 org/apache/commons/math3/geometry/partitioning/BSPTree.getAttribute:()Ljava/lang/Object; (1, 1)
	8 checkcast (1, 1)
	9 java/lang/Boolean (1, 1)
	11 invokevirtual (1, 1)
	12 java/lang/Boolean.booleanValue:()Z (1, 1)
	14 ifeq (1, 1)
	15 5 (1, 1)
	17 iconst_0 (2, 4)
	18 ireturn (2, 4)
	19 aload_0 (1, 1)
	20 aload_1 (1, 1)
	21 invokespecial (1, 1)
	22 org/apache/commons/math3/geometry/euclidean/oned/IntervalsSet.leafAfter:(Lorg/apache/commons/math3/geometry/partitioning/BSPTree;)Lorg/apache/commons/math3/geometry/partitioning/BSPTree; (1, 1)
	24 invokevirtual (1, 1)
	25 org/apache/commons/math3/geometry/partitioning/BSPTree.getAttribute:()Ljava/lang/Object; (1, 1)
	27 checkcast (1, 1)
	28 java/lang/Boolean (1, 1)
	30 invokevirtual (1, 1)
	31 java/lang/Boolean.booleanValue:()Z (1, 1)
	33 ifne (1, 1)
	34 5 (1, 1)
	36 iconst_0 (1, 1)
	37 ireturn (1, 1)
	38 iconst_1 (1, 4)
	39 ireturn (0, 4)

Method: isIntervalEnd
	0 aload_0 (1, 1)
	1 aload_1 (1, 1)
	2 invokespecial (1, 1)
	3 org/apache/commons/math3/geometry/euclidean/oned/IntervalsSet.leafBefore:(Lorg/apache/commons/math3/geometry/partitioning/BSPTree;)Lorg/apache/commons/math3/geometry/partitioning/BSPTree; (1, 1)
	5 invokevirtual (1, 1)
	6 org/apache/commons/math3/geometry/partitioning/BSPTree.getAttribute:()Ljava/lang/Object; (1, 1)
	8 checkcast (1, 1)
	9 java/lang/Boolean (1, 1)
	11 invokevirtual (1, 1)
	12 java/lang/Boolean.booleanValue:()Z (1, 1)
	14 ifne (1, 1)
	15 5 (1, 1)
	17 iconst_0 (2, 4)
	18 ireturn (2, 4)
	19 aload_0 (1, 1)
	20 aload_1 (1, 1)
	21 invokespecial (1, 1)
	22 org/apache/commons/math3/geometry/euclidean/oned/IntervalsSet.leafAfter:(Lorg/apache/commons/math3/geometry/partitioning/BSPTree;)Lorg/apache/commons/math3/geometry/partitioning/BSPTree; (1, 1)
	24 invokevirtual (1, 1)
	25 org/apache/commons/math3/geometry/partitioning/BSPTree.getAttribute:()Ljava/lang/Object; (1, 1)
	27 checkcast (1, 1)
	28 java/lang/Boolean (1, 1)
	30 invokevirtual (1, 1)
	31 java/lang/Boolean.booleanValue:()Z (1, 1)
	33 ifeq (1, 1)
	34 5 (1, 1)
	36 iconst_0 (1, 1)
	37 ireturn (1, 1)
	38 iconst_1 (1, 4)
	39 ireturn (0, 4)

Method: nextInternalNode
	0 aload_0 (1, 1)
	1 aload_1 (1, 1)
	2 invokespecial (1, 1)
	3 org/apache/commons/math3/geometry/euclidean/oned/IntervalsSet.childAfter:(Lorg/apache/commons/math3/geometry/partitioning/BSPTree;)Lorg/apache/commons/math3/geometry/partitioning/BSPTree; (1, 1)
	5 invokevirtual (1, 1)
	6 org/apache/commons/math3/geometry/partitioning/BSPTree.getCut:()Lorg/apache/commons/math3/geometry/partitioning/SubHyperplane; (1, 1)
	8 ifnull (1, 1)
	9 12 (1, 1)
	11 aload_0 (1, 1)
	12 aload_1 (1, 1)
	13 invokespecial (1, 1)
	14 org/apache/commons/math3/geometry/euclidean/oned/IntervalsSet.leafAfter:(Lorg/apache/commons/math3/geometry/partitioning/BSPTree;)Lorg/apache/commons/math3/geometry/partitioning/BSPTree; (1, 1)
	16 invokevirtual (1, 1)
	17 org/apache/commons/math3/geometry/partitioning/BSPTree.getParent:()Lorg/apache/commons/math3/geometry/partitioning/BSPTree; (1, 1)
	19 areturn (1, 1)
	20 aload_0 (1, 3)
	21 aload_1 (1, 3)
	22 invokespecial (1, 3)
	23 org/apache/commons/math3/geometry/euclidean/oned/IntervalsSet.isAfterParent:(Lorg/apache/commons/math3/geometry/partitioning/BSPTree;)Z (1, 3)
	25 ifeq (1, 3)
	26 11 (1, 3)
	28 aload_1 (1, 3)
	29 invokevirtual (1, 3)
	30 org/apache/commons/math3/geometry/partitioning/BSPTree.getParent:()Lorg/apache/commons/math3/geometry/partitioning/BSPTree; (1, 3)
	32 astore_1 (1, 3)
	33 goto (1, 3)
	34 -13 (1, 3)
	36 aload_1 (0, 0)
	37 invokevirtual (0, 0)
	38 org/apache/commons/math3/geometry/partitioning/BSPTree.getParent:()Lorg/apache/commons/math3/geometry/partitioning/BSPTree; (0, 0)
	40 areturn (0, 0)

Method: previousInternalNode
	0 aload_0 (1, 1)
	1 aload_1 (1, 1)
	2 invokespecial (1, 1)
	3 org/apache/commons/math3/geometry/euclidean/oned/IntervalsSet.childBefore:(Lorg/apache/commons/math3/geometry/partitioning/BSPTree;)Lorg/apache/commons/math3/geometry/partitioning/BSPTree; (1, 1)
	5 invokevirtual (1, 1)
	6 org/apache/commons/math3/geometry/partitioning/BSPTree.getCut:()Lorg/apache/commons/math3/geometry/partitioning/SubHyperplane; (1, 1)
	8 ifnull (1, 1)
	9 12 (1, 1)
	11 aload_0 (2, 4)
	12 aload_1 (2, 4)
	13 invokespecial (2, 4)
	14 org/apache/commons/math3/geometry/euclidean/oned/IntervalsSet.leafBefore:(Lorg/apache/commons/math3/geometry/partitioning/BSPTree;)Lorg/apache/commons/math3/geometry/partitioning/BSPTree; (2, 4)
	16 invokevirtual (2, 4)
	17 org/apache/commons/math3/geometry/partitioning/BSPTree.getParent:()Lorg/apache/commons/math3/geometry/partitioning/BSPTree; (2, 4)
	19 areturn (2, 4)
	20 aload_0 (1, 3)
	21 aload_1 (1, 3)
	22 invokespecial (1, 3)
	23 org/apache/commons/math3/geometry/euclidean/oned/IntervalsSet.isBeforeParent:(Lorg/apache/commons/math3/geometry/partitioning/BSPTree;)Z (1, 3)
	25 ifeq (1, 3)
	26 11 (1, 3)
	28 aload_1 (1, 3)
	29 invokevirtual (1, 3)
	30 org/apache/commons/math3/geometry/partitioning/BSPTree.getParent:()Lorg/apache/commons/math3/geometry/partitioning/BSPTree; (1, 3)
	32 astore_1 (1, 3)
	33 goto (1, 3)
	34 -13 (1, 3)
	36 aload_1 (0, 0)
	37 invokevirtual (0, 0)
	38 org/apache/commons/math3/geometry/partitioning/BSPTree.getParent:()Lorg/apache/commons/math3/geometry/partitioning/BSPTree; (0, 0)
	40 areturn (0, 0)

Method: leafBefore
	0 aload_0 (1, 4)
	1 aload_1 (1, 4)
	2 invokespecial (1, 4)
	3 org/apache/commons/math3/geometry/euclidean/oned/IntervalsSet.childBefore:(Lorg/apache/commons/math3/geometry/partitioning/BSPTree;)Lorg/apache/commons/math3/geometry/partitioning/BSPTree; (1, 4)
	5 astore_1 (1, 4)
	6 aload_1 (2, 3)
	7 invokevirtual (2, 3)
	8 org/apache/commons/math3/geometry/partitioning/BSPTree.getCut:()Lorg/apache/commons/math3/geometry/partitioning/SubHyperplane; (2, 3)
	10 ifnull (2, 3)
	11 12 (2, 3)
	13 aload_0 (2, 3)
	14 aload_1 (2, 3)
	15 invokespecial (2, 3)
	16 org/apache/commons/math3/geometry/euclidean/oned/IntervalsSet.childAfter:(Lorg/apache/commons/math3/geometry/partitioning/BSPTree;)Lorg/apache/commons/math3/geometry/partitioning/BSPTree; (2, 3)
	18 astore_1 (2, 3)
	19 goto (2, 3)
	20 -13 (2, 3)
	22 aload_1 (1, 4)
	23 areturn (0, 4)

Method: leafAfter
	0 aload_0 (0, 0)
	1 aload_1 (0, 0)
	2 invokespecial (0, 0)
	3 org/apache/commons/math3/geometry/euclidean/oned/IntervalsSet.childAfter:(Lorg/apache/commons/math3/geometry/partitioning/BSPTree;)Lorg/apache/commons/math3/geometry/partitioning/BSPTree; (0, 0)
	5 astore_1 (0, 0)
	6 aload_1 (1, 3)
	7 invokevirtual (1, 3)
	8 org/apache/commons/math3/geometry/partitioning/BSPTree.getCut:()Lorg/apache/commons/math3/geometry/partitioning/SubHyperplane; (1, 3)
	10 ifnull (1, 3)
	11 12 (1, 3)
	13 aload_0 (2, 4)
	14 aload_1 (2, 4)
	15 invokespecial (2, 4)
	16 org/apache/commons/math3/geometry/euclidean/oned/IntervalsSet.childBefore:(Lorg/apache/commons/math3/geometry/partitioning/BSPTree;)Lorg/apache/commons/math3/geometry/partitioning/BSPTree; (2, 4)
	18 astore_1 (2, 4)
	19 goto (2, 4)
	20 -13 (2, 4)
	22 aload_1 (0, 0)
	23 areturn (0, 0)

Method: isBeforeParent
	0 aload_1 (0, 0)
	1 invokevirtual (0, 0)
	2 org/apache/commons/math3/geometry/partitioning/BSPTree.getParent:()Lorg/apache/commons/math3/geometry/partitioning/BSPTree; (0, 0)
	4 astore_2 (0, 0)
	5 aload_2 (1, 1)
	6 ifnonnull (1, 1)
	7 5 (1, 1)
	9 iconst_0 (1, 1)
	10 ireturn (1, 1)
	11 aload_1 (3, 4)
	12 aload_0 (3, 4)
	13 aload_2 (3, 4)
	14 invokespecial (3, 4)
	15 org/apache/commons/math3/geometry/euclidean/oned/IntervalsSet.childBefore:(Lorg/apache/commons/math3/geometry/partitioning/BSPTree;)Lorg/apache/commons/math3/geometry/partitioning/BSPTree; (3, 4)
	17 if_acmpne (3, 4)
	18 7 (3, 4)
	20 iconst_1 (3, 4)
	21 goto (3, 4)
	22 4 (3, 4)
	24 iconst_0 (3, 4)
	25 ireturn (1, 4)

Method: isAfterParent
	0 aload_1 (0, 0)
	1 invokevirtual (0, 0)
	2 org/apache/commons/math3/geometry/partitioning/BSPTree.getParent:()Lorg/apache/commons/math3/geometry/partitioning/BSPTree; (0, 0)
	4 astore_2 (0, 0)
	5 aload_2 (1, 1)
	6 ifnonnull (1, 1)
	7 5 (1, 1)
	9 iconst_0 (1, 1)
	10 ireturn (1, 1)
	11 aload_1 (2, 2)
	12 aload_0 (2, 2)
	13 aload_2 (2, 2)
	14 invokespecial (2, 2)
	15 org/apache/commons/math3/geometry/euclidean/oned/IntervalsSet.childAfter:(Lorg/apache/commons/math3/geometry/partitioning/BSPTree;)Lorg/apache/commons/math3/geometry/partitioning/BSPTree; (2, 2)
	17 if_acmpne (2, 2)
	18 7 (2, 2)
	20 iconst_1 (2, 2)
	21 goto (2, 2)
	22 4 (2, 2)
	24 iconst_0 (2, 2)
	25 ireturn (1, 2)

Method: childBefore
	0 aload_0 (1, 1)
	1 aload_1 (1, 1)
	2 invokespecial (1, 1)
	3 org/apache/commons/math3/geometry/euclidean/oned/IntervalsSet.isDirect:(Lorg/apache/commons/math3/geometry/partitioning/BSPTree;)Z (1, 1)
	5 ifeq (1, 1)
	6 8 (1, 1)
	8 aload_1 (1, 1)
	9 invokevirtual (1, 1)
	10 org/apache/commons/math3/geometry/partitioning/BSPTree.getMinus:()Lorg/apache/commons/math3/geometry/partitioning/BSPTree; (1, 1)
	12 areturn (1, 1)
	13 aload_1 (2, 2)
	14 invokevirtual (2, 2)
	15 org/apache/commons/math3/geometry/partitioning/BSPTree.getPlus:()Lorg/apache/commons/math3/geometry/partitioning/BSPTree; (2, 2)
	17 areturn (1, 2)

Method: childAfter
	0 aload_0 (1, 1)
	1 aload_1 (1, 1)
	2 invokespecial (1, 1)
	3 org/apache/commons/math3/geometry/euclidean/oned/IntervalsSet.isDirect:(Lorg/apache/commons/math3/geometry/partitioning/BSPTree;)Z (1, 1)
	5 ifeq (1, 1)
	6 8 (1, 1)
	8 aload_1 (1, 1)
	9 invokevirtual (1, 1)
	10 org/apache/commons/math3/geometry/partitioning/BSPTree.getPlus:()Lorg/apache/commons/math3/geometry/partitioning/BSPTree; (1, 1)
	12 areturn (1, 1)
	13 aload_1 (2, 2)
	14 invokevirtual (2, 2)
	15 org/apache/commons/math3/geometry/partitioning/BSPTree.getMinus:()Lorg/apache/commons/math3/geometry/partitioning/BSPTree; (2, 2)
	17 areturn (1, 2)

Method: isDirect
	0 aload_1 (0, 0)
	1 invokevirtual (0, 0)
	2 org/apache/commons/math3/geometry/partitioning/BSPTree.getCut:()Lorg/apache/commons/math3/geometry/partitioning/SubHyperplane; (0, 0)
	4 invokeinterface (0, 0)
	5 org/apache/commons/math3/geometry/partitioning/SubHyperplane.getLocation:()Lorg/apache/commons/math3/geometry/euclidean/oned/Vector1D; (0, 0)
	7 0 (0, 0)
	9 checkcast (0, 0)
	10 org/apache/commons/math3/geometry/euclidean/oned/OrientedPoint (0, 0)
	12 invokevirtual (0, 0)
	13 org/apache/commons/math3/geometry/euclidean/oned/OrientedPoint.isDirect:()Z (0, 0)
	15 ireturn (0, 0)

Method: getAngle
	0 aload_1 (0, 0)
	1 invokevirtual (0, 0)
	2 org/apache/commons/math3/geometry/partitioning/BSPTree.getCut:()Lorg/apache/commons/math3/geometry/partitioning/SubHyperplane; (0, 0)
	4 invokeinterface (0, 0)
	5 org/apache/commons/math3/geometry/partitioning/SubHyperplane.getLocation:()Lorg/apache/commons/math3/geometry/euclidean/oned/Vector1D; (0, 0)
	7 0 (0, 0)
	9 checkcast (0, 0)
	10 org/apache/commons/math3/geometry/euclidean/oned/OrientedPoint (0, 0)
	12 invokevirtual (0, 0)
	13 org/apache/commons/math3/geometry/euclidean/oned/OrientedPoint.getLocation:()Lorg/apache/commons/math3/geometry/euclidean/oned/Vector1D; (0, 0)
	15 invokevirtual (0, 0)
	16 org/apache/commons/math3/geometry/euclidean/oned/Vector1D.getX:()D (0, 0)
	18 dreturn (0, 0)

Method: iterator
	0 new (0, 0)
	1 org/apache/commons/math3/geometry/euclidean/oned/IntervalsSet$SubIntervalsIterator (0, 0)
	3 dup (0, 0)
	4 aload_0 (0, 0)
	5 invokespecial (0, 0)
	6 org/apache/commons/math3/geometry/euclidean/oned/IntervalsSet$SubIntervalsIterator.<init>:(Lorg/apache/commons/math3/geometry/euclidean/oned/IntervalsSet;)V (0, 0)
	8 areturn (0, 0)

Method: access$000
	0 aload_0 (0, 0)
	1 invokespecial (0, 0)
	2 org/apache/commons/math3/geometry/euclidean/oned/IntervalsSet.getFirstIntervalBoundary:()Lorg/apache/commons/math3/geometry/partitioning/BSPTree; (0, 0)
	4 areturn (0, 0)

Method: access$100
	0 aload_0 (0, 0)
	1 aload_1 (0, 0)
	2 invokespecial (0, 0)
	3 org/apache/commons/math3/geometry/euclidean/oned/IntervalsSet.getFirstLeaf:(Lorg/apache/commons/math3/geometry/partitioning/BSPTree;)Lorg/apache/commons/math3/geometry/partitioning/BSPTree; (0, 0)
	5 areturn (0, 0)

Method: access$200
	0 aload_0 (0, 0)
	1 aload_1 (0, 0)
	2 invokespecial (0, 0)
	3 org/apache/commons/math3/geometry/euclidean/oned/IntervalsSet.isIntervalEnd:(Lorg/apache/commons/math3/geometry/partitioning/BSPTree;)Z (0, 0)
	5 ireturn (0, 0)

Method: access$300
	0 aload_0 (0, 0)
	1 aload_1 (0, 0)
	2 invokespecial (0, 0)
	3 org/apache/commons/math3/geometry/euclidean/oned/IntervalsSet.getAngle:(Lorg/apache/commons/math3/geometry/partitioning/BSPTree;)D (0, 0)
	5 dreturn (0, 0)

Method: access$400
	0 aload_0 (0, 0)
	1 aload_1 (0, 0)
	2 invokespecial (0, 0)
	3 org/apache/commons/math3/geometry/euclidean/oned/IntervalsSet.isIntervalStart:(Lorg/apache/commons/math3/geometry/partitioning/BSPTree;)Z (0, 0)
	5 ireturn (0, 0)

Method: access$500
	0 aload_0 (0, 0)
	1 aload_1 (0, 0)
	2 invokespecial (0, 0)
	3 org/apache/commons/math3/geometry/euclidean/oned/IntervalsSet.nextInternalNode:(Lorg/apache/commons/math3/geometry/partitioning/BSPTree;)Lorg/apache/commons/math3/geometry/partitioning/BSPTree; (0, 0)
	5 areturn (0, 0)

