Method: <init>
	0 aload_0 (0, 0)
	1 invokespecial (0, 0)
	2 java/lang/Object.<init>:()V (0, 0)
	4 dload_3 (0, 0)
	5 dload_1 (0, 0)
	6 dcmpg (0, 0)
	7 ifge (0, 0)
	8 23 (0, 0)
	10 new (0, 0)
	11 org/apache/commons/math3/exception/NumberIsTooSmallException (0, 0)
	13 dup (0, 0)
	14 getstatic (0, 0)
	15 org/apache/commons/math3/exception/util/LocalizedFormats.ENDPOINTS_NOT_AN_INTERVAL:Lorg/apache/commons/math3/exception/util/LocalizedFormats; (0, 0)
	17 dload_3 (0, 0)
	18 invokestatic (0, 0)
	19 java/lang/Double.valueOf:(D)Ljava/lang/Double; (0, 0)
	21 dload_1 (0, 0)
	22 invokestatic (0, 0)
	23 java/lang/Double.valueOf:(D)Ljava/lang/Double; (0, 0)
	25 iconst_1 (0, 0)
	26 invokespecial (0, 0)
	27 org/apache/commons/math3/exception/NumberIsTooSmallException.<init>:(Lorg/apache/commons/math3/exception/util/Localizable;Ljava/lang/Number;Ljava/lang/Number;Z)V (0, 0)
	29 athrow (0, 0)
	30 aload_0 (0, 0)
	31 dload_1 (0, 0)
	32 putfield (0, 0)
	33 org/apache/commons/math3/geometry/euclidean/oned/Interval.lower:D (0, 0)
	35 aload_0 (0, 0)
	36 dload_3 (0, 0)
	37 putfield (0, 0)
	38 org/apache/commons/math3/geometry/euclidean/oned/Interval.upper:D (0, 0)
	40 return (0, 0)

Method: getInf
	0 aload_0 (0, 0)
	1 getfield (0, 0)
	2 org/apache/commons/math3/geometry/euclidean/oned/Interval.lower:D (0, 0)
	4 dreturn (0, 0)

Method: getLower
	0 aload_0 (1, 4)
	1 invokevirtual (1, 4)
	2 org/apache/commons/math3/geometry/euclidean/oned/Interval.getInf:()D (1, 4)
	4 dreturn (0, 4)

Method: getSup
	0 aload_0 (0, 0)
	1 getfield (0, 0)
	2 org/apache/commons/math3/geometry/euclidean/oned/Interval.upper:D (0, 0)
	4 dreturn (0, 0)

Method: getUpper
	0 aload_0 (1, 4)
	1 invokevirtual (1, 4)
	2 org/apache/commons/math3/geometry/euclidean/oned/Interval.getSup:()D (1, 4)
	4 dreturn (0, 4)

Method: getSize
	0 aload_0 (0, 0)
	1 getfield (0, 0)
	2 org/apache/commons/math3/geometry/euclidean/oned/Interval.upper:D (0, 0)
	4 aload_0 (0, 0)
	5 getfield (0, 0)
	6 org/apache/commons/math3/geometry/euclidean/oned/Interval.lower:D (0, 0)
	8 dsub (0, 0)
	9 dreturn (0, 0)

Method: getLength
	0 aload_0 (0, 0)
	1 invokevirtual (0, 0)
	2 org/apache/commons/math3/geometry/euclidean/oned/Interval.getSize:()D (0, 0)
	4 dreturn (0, 0)

Method: getBarycenter
	0 ldc2_w (0, 0)
	1 0.5 (0, 0)
	3 aload_0 (0, 0)
	4 getfield (0, 0)
	5 org/apache/commons/math3/geometry/euclidean/oned/Interval.lower:D (0, 0)
	7 aload_0 (0, 0)
	8 getfield (0, 0)
	9 org/apache/commons/math3/geometry/euclidean/oned/Interval.upper:D (0, 0)
	11 dadd (0, 0)
	12 dmul (0, 0)
	13 dreturn (0, 0)

Method: getMidPoint
	0 aload_0 (0, 0)
	1 invokevirtual (0, 0)
	2 org/apache/commons/math3/geometry/euclidean/oned/Interval.getBarycenter:()D (0, 0)
	4 dreturn (0, 0)

Method: checkPoint
	0 dload_1 (0, 0)
	1 aload_0 (0, 0)
	2 getfield (0, 0)
	3 org/apache/commons/math3/geometry/euclidean/oned/Interval.lower:D (0, 0)
	5 dload_3 (0, 0)
	6 dsub (0, 0)
	7 dcmpg (0, 0)
	8 iflt (0, 0)
	9 14 (0, 0)
	11 dload_1 (0, 0)
	12 aload_0 (0, 0)
	13 getfield (0, 0)
	14 org/apache/commons/math3/geometry/euclidean/oned/Interval.upper:D (0, 0)
	16 dload_3 (0, 0)
	17 dadd (0, 0)
	18 dcmpl (0, 0)
	19 ifle (0, 0)
	20 7 (0, 0)
	22 getstatic (0, 0)
	23 org/apache/commons/math3/geometry/partitioning/Region$Location.OUTSIDE:Lorg/apache/commons/math3/geometry/partitioning/Region$Location; (0, 0)
	25 areturn (0, 0)
	26 dload_1 (0, 0)
	27 aload_0 (0, 0)
	28 getfield (0, 0)
	29 org/apache/commons/math3/geometry/euclidean/oned/Interval.lower:D (0, 0)
	31 dload_3 (0, 0)
	32 dadd (0, 0)
	33 dcmpl (0, 0)
	34 ifle (0, 0)
	35 18 (0, 0)
	37 dload_1 (0, 0)
	38 aload_0 (0, 0)
	39 getfield (0, 0)
	40 org/apache/commons/math3/geometry/euclidean/oned/Interval.upper:D (0, 0)
	42 dload_3 (0, 0)
	43 dsub (0, 0)
	44 dcmpg (0, 0)
	45 ifge (0, 0)
	46 7 (0, 0)
	48 getstatic (0, 0)
	49 org/apache/commons/math3/geometry/partitioning/Region$Location.INSIDE:Lorg/apache/commons/math3/geometry/partitioning/Region$Location; (0, 0)
	51 areturn (0, 0)
	52 getstatic (0, 0)
	53 org/apache/commons/math3/geometry/partitioning/Region$Location.BOUNDARY:Lorg/apache/commons/math3/geometry/partitioning/Region$Location; (0, 0)
	55 areturn (0, 0)

