Method: <init>
	0 aload_0 (0, 0)
	1 aload_1 (0, 0)
	2 aload_2 (0, 0)
	3 invokespecial (0, 0)
	4 org/apache/commons/math3/geometry/partitioning/AbstractSubHyperplane.<init>:(Lorg/apache/commons/math3/geometry/partitioning/Hyperplane;Lorg/apache/commons/math3/geometry/partitioning/Region;)V (0, 0)
	6 return (0, 0)

Method: getSize
	0 dconst_0 (0, 0)
	1 dreturn (0, 0)

Method: isEmpty
	0 iconst_0 (0, 0)
	1 ireturn (0, 0)

Method: buildNew
	0 new (0, 0)
	1 org/apache/commons/math3/geometry/euclidean/oned/SubOrientedPoint (0, 0)
	3 dup (0, 0)
	4 aload_1 (0, 0)
	5 aload_2 (0, 0)
	6 invokespecial (0, 0)
	7 org/apache/commons/math3/geometry/euclidean/oned/SubOrientedPoint.<init>:(Lorg/apache/commons/math3/geometry/partitioning/Hyperplane;Lorg/apache/commons/math3/geometry/partitioning/Region;)V (0, 0)
	9 areturn (0, 0)

Method: split
	0 aload_1 (0, 0)
	1 aload_0 (0, 0)
	2 invokevirtual (0, 0)
	3 org/apache/commons/math3/geometry/euclidean/oned/SubOrientedPoint.getHyperplane:()Lorg/apache/commons/math3/geometry/partitioning/Hyperplane; (0, 0)
	5 checkcast (0, 0)
	6 org/apache/commons/math3/geometry/euclidean/oned/OrientedPoint (0, 0)
	8 invokevirtual (0, 0)
	9 org/apache/commons/math3/geometry/euclidean/oned/OrientedPoint.getLocation:()Lorg/apache/commons/math3/geometry/euclidean/oned/Vector1D; (0, 0)
	11 invokeinterface (0, 0)
	12 org/apache/commons/math3/geometry/partitioning/Hyperplane.org/apache/commons/math3/geometry/partitioning/SubHyperplane (0, 0)
	14 0 (0, 0)
	16 dstore_2 (0, 0)
	17 dload_2 (1, 1)
	18 ldc2_w (1, 1)
	19 -1e-10 (1, 1)
	21 dcmpg (1, 1)
	22 ifge (1, 1)
	23 13 (1, 1)
	25 new (1, 1)
	26 org/apache/commons/math3/geometry/partitioning/SubHyperplane$SplitSubHyperplane (1, 1)
	28 dup (1, 1)
	29 aconst_null (1, 1)
	30 aload_0 (1, 1)
	31 invokespecial (1, 1)
	32 org/apache/commons/math3/geometry/partitioning/SubHyperplane$SplitSubHyperplane.<init>:(Lorg/apache/commons/math3/geometry/partitioning/SubHyperplane;Lorg/apache/commons/math3/geometry/partitioning/SubHyperplane;)V (1, 1)
	34 areturn (1, 1)
	35 dload_2 (2, 1)
	36 ldc2_w (2, 1)
	37 1e-10 (2, 1)
	39 dcmpl (2, 1)
	40 ifle (2, 1)
	41 13 (2, 1)
	43 new (2, 1)
	44 org/apache/commons/math3/geometry/partitioning/SubHyperplane$SplitSubHyperplane (2, 1)
	46 dup (2, 1)
	47 aload_0 (2, 1)
	48 aconst_null (2, 1)
	49 invokespecial (2, 1)
	50 org/apache/commons/math3/geometry/partitioning/SubHyperplane$SplitSubHyperplane.<init>:(Lorg/apache/commons/math3/geometry/partitioning/SubHyperplane;Lorg/apache/commons/math3/geometry/partitioning/SubHyperplane;)V (2, 1)
	52 areturn (2, 1)
	53 new (3, 2)
	54 org/apache/commons/math3/geometry/partitioning/SubHyperplane$SplitSubHyperplane (3, 2)
	56 dup (3, 2)
	57 aconst_null (3, 2)
	58 aconst_null (3, 2)
	59 invokespecial (3, 2)
	60 org/apache/commons/math3/geometry/partitioning/SubHyperplane$SplitSubHyperplane.<init>:(Lorg/apache/commons/math3/geometry/partitioning/SubHyperplane;Lorg/apache/commons/math3/geometry/partitioning/SubHyperplane;)V (3, 2)
	62 areturn (1, 2)

