Method: <init>
	0 aload_0 (0, 0)
	1 aload_1 (0, 0)
	2 aload_2 (0, 0)
	3 invokespecial (0, 0)
	6 return (0, 0)

Method: getSize
	0 dconst_0 (0, 0)
	1 dreturn (0, 0)

Method: isEmpty
	0 iconst_0 (0, 0)
	1 ireturn (0, 0)

Method: buildNew
	0 new (0, 0)
	3 dup (0, 0)
	4 aload_1 (0, 0)
	5 aload_2 (0, 0)
	6 invokespecial (0, 0)
	9 areturn (0, 0)

Method: split
	0 aload_1 (0, 0)
	1 aload_0 (0, 0)
	2 invokevirtual (0, 0)
	5 checkcast (0, 0)
	8 invokevirtual (0, 0)
	11 invokeinterface (0, 0)
	16 dstore_2 (0, 0)
	17 dload_2 (1, 1)
	18 ldc2_w (1, 1)
	21 dcmpg (1, 1)
	22 ifge (1, 1)
	25 new (1, 1)
	28 dup (1, 1)
	29 aconst_null (1, 1)
	30 aload_0 (1, 1)
	31 invokespecial (1, 1)
	34 areturn (1, 1)
	35 dload_2 (1, 1)
	36 ldc2_w (1, 1)
	39 dcmpl (1, 1)
	40 ifle (1, 1)
	43 new (1, 1)
	46 dup (1, 1)
	47 aload_0 (1, 1)
	48 aconst_null (1, 1)
	49 invokespecial (1, 1)
	52 areturn (1, 1)
	53 new (1, 2)
	56 dup (1, 2)
	57 aconst_null (1, 2)
	58 aconst_null (1, 2)
	59 invokespecial (1, 2)
	62 areturn (1, 2)

