Method: <init>
	0 aload_0 (0, 0)
	1 invokespecial (0, 0)
	2 java/lang/Object.<init>:()V (0, 0)
	4 aload_0 (0, 0)
	5 dload_1 (0, 0)
	6 aload_3 (0, 0)
	7 getfield (0, 0)
	8 org/apache/commons/math3/geometry/euclidean/oned/Vector1D.x:D (0, 0)
	10 dmul (0, 0)
	11 dload (0, 0)
	12 #4 (0, 0)
	13 aload (0, 0)
	14 #6 (0, 0)
	15 getfield (0, 0)
	16 org/apache/commons/math3/geometry/euclidean/oned/Vector1D.x:D (0, 0)
	18 dmul (0, 0)
	19 dadd (0, 0)
	20 dload (0, 0)
	21 #7 (0, 0)
	22 aload (0, 0)
	23 #9 (0, 0)
	24 getfield (0, 0)
	25 org/apache/commons/math3/geometry/euclidean/oned/Vector1D.x:D (0, 0)
	27 dmul (0, 0)
	28 dadd (0, 0)
	29 dload (0, 0)
	30 #10 (0, 0)
	31 aload (0, 0)
	32 #12 (0, 0)
	33 getfield (0, 0)
	34 org/apache/commons/math3/geometry/euclidean/oned/Vector1D.x:D (0, 0)
	36 dmul (0, 0)
	37 dadd (0, 0)
	38 putfield (0, 0)
	39 org/apache/commons/math3/geometry/euclidean/oned/Vector1D.x:D (0, 0)
	41 return (0, 0)

Method: getX
	0 aload_0 (0, 0)
	1 getfield (0, 0)
	2 org/apache/commons/math3/geometry/euclidean/oned/Vector1D.x:D (0, 0)
	4 dreturn (0, 0)

Method: getSpace
	0 invokestatic (0, 0)
	1 org/apache/commons/math3/geometry/euclidean/oned/Euclidean1D.getInstance:()Lorg/apache/commons/math3/geometry/euclidean/oned/Euclidean1D; (0, 0)
	3 areturn (0, 0)

