Method: <init>
	0 aload_0 (0, 0)
	1 invokespecial (0, 0)
	4 return (0, 0)

Method: smallTrialDivision
	0 getstatic (1, 4)
	3 astore_2 (1, 4)
	4 aload_2 (1, 4)
	5 arraylength (1, 4)
	6 istore_3 (1, 4)
	7 iconst_0 (1, 4)
	8 istore (1, 4)
	10 iload (1, 4)
	12 iload_3 (1, 4)
	13 if_icmpge (1, 4)
	16 aload_2 (1, 4)
	17 iload (1, 4)
	19 iaload (1, 4)
	20 istore (1, 4)
	22 iconst_0 (2, 3)
	23 iload_0 (2, 3)
	24 iload (2, 3)
	26 irem (2, 3)
	27 if_icmpne (2, 3)
	30 iload_0 (2, 3)
	31 iload (2, 3)
	33 idiv (2, 3)
	34 istore_0 (2, 3)
	35 aload_1 (2, 3)
	36 iload (2, 3)
	38 invokestatic (2, 3)
	41 invokeinterface (2, 3)
	46 pop (2, 3)
	47 goto (2, 3)
	50 iinc (2, 3)
	53 goto (2, 3)
	56 iload_0 (1, 4)
	57 ireturn (1, 4)

Method: boundedTrialDivision
	0 getstatic (0, 0)
	3 iconst_2 (0, 0)
	4 iadd (0, 0)
	5 istore_3 (0, 0)
	6 iload_3 (1, 3)
	7 iload_1 (1, 3)
	8 if_icmpgt (1, 3)
	11 iconst_0 (2, 1)
	12 iload_0 (2, 1)
	13 iload_3 (2, 1)
	14 irem (2, 1)
	15 if_icmpne (2, 1)
	18 iload_0 (2, 1)
	19 iload_3 (2, 1)
	20 idiv (2, 1)
	21 istore_0 (2, 1)
	22 aload_2 (2, 1)
	23 iload_3 (2, 1)
	24 invokestatic (2, 1)
	27 invokeinterface (2, 1)
	32 pop (2, 1)
	33 goto (2, 1)
	36 iinc (1, 3)
	39 iconst_0 (2, 1)
	40 iload_0 (2, 1)
	41 iload_3 (2, 1)
	42 irem (2, 1)
	43 if_icmpne (2, 1)
	46 iload_0 (2, 1)
	47 iload_3 (2, 1)
	48 idiv (2, 1)
	49 istore_0 (2, 1)
	50 aload_2 (2, 1)
	51 iload_3 (2, 1)
	52 invokestatic (2, 1)
	55 invokeinterface (2, 1)
	60 pop (2, 1)
	61 goto (2, 1)
	64 iinc (1, 3)
	67 goto (1, 3)
	70 iload_0 (1, 1)
	71 iconst_1 (1, 1)
	72 if_icmpeq (1, 1)
	75 aload_2 (1, 1)
	76 iload_0 (1, 1)
	77 invokestatic (1, 1)
	80 invokeinterface (1, 1)
	85 pop (1, 1)
	86 iload_0 (0, 0)
	87 ireturn (0, 0)

Method: trialDivision
	0 new (0, 0)
	3 dup (0, 0)
	4 bipush (0, 0)
	6 invokespecial (0, 0)
	9 astore_1 (0, 0)
	10 iload_0 (0, 0)
	11 aload_1 (0, 0)
	12 invokestatic (0, 0)
	15 istore_0 (0, 0)
	16 iconst_1 (1, 1)
	17 iload_0 (1, 1)
	18 if_icmpne (1, 1)
	21 aload_1 (1, 1)
	22 areturn (1, 1)
	23 iload_0 (0, 0)
	24 i2d (0, 0)
	25 invokestatic (0, 0)
	28 d2i (0, 0)
	29 istore_2 (0, 0)
	30 iload_0 (0, 0)
	31 iload_2 (0, 0)
	32 aload_1 (0, 0)
	33 invokestatic (0, 0)
	36 pop (0, 0)
	37 aload_1 (0, 0)
	38 areturn (0, 0)

Method: millerRabinPrimeTest
	0 iload_0 (0, 0)
	1 iconst_1 (0, 0)
	2 isub (0, 0)
	3 istore_1 (0, 0)
	4 iload_1 (0, 0)
	5 invokestatic (0, 0)
	8 istore_2 (0, 0)
	9 iload_1 (0, 0)
	10 iload_2 (0, 0)
	11 ishr (0, 0)
	12 istore_3 (0, 0)
	13 iconst_1 (0, 0)
	14 istore (0, 0)
	16 iload_0 (1, 1)
	17 sipush (1, 1)
	20 if_icmplt (1, 1)
	23 iconst_2 (1, 1)
	24 istore (1, 1)
	26 iload_0 (1, 1)
	27 ldc (1, 1)
	29 if_icmplt (1, 1)
	32 iconst_3 (1, 1)
	33 istore (1, 1)
	35 iload_0 (1, 1)
	36 ldc (1, 1)
	38 if_icmplt (1, 1)
	41 iconst_4 (1, 1)
	42 istore (1, 1)
	44 iload_3 (0, 0)
	45 i2l (0, 0)
	46 invokestatic (0, 0)
	49 astore (0, 0)
	51 iload_0 (0, 0)
	52 i2l (0, 0)
	53 invokestatic (0, 0)
	56 astore (0, 0)
	58 iconst_0 (1, 4)
	59 istore (1, 4)
	61 iload (1, 4)
	63 iload (1, 4)
	65 if_icmpge (1, 4)
	68 getstatic (1, 4)
	71 iload (1, 4)
	73 iaload (1, 4)
	74 i2l (1, 4)
	75 invokestatic (1, 4)
	78 astore (1, 4)
	80 aload (1, 4)
	82 aload (1, 4)
	84 aload (1, 4)
	86 invokevirtual (1, 4)
	89 astore (1, 4)
	91 aload (1, 4)
	93 invokevirtual (1, 4)
	96 istore (1, 4)
	98 iconst_1 (2, 1)
	99 iload (2, 1)
	101 if_icmpeq (2, 1)
	104 iload (2, 1)
	106 iload_1 (2, 1)
	107 if_icmpeq (2, 1)
	110 iconst_1 (2, 1)
	111 istore (2, 1)
	113 iload (3, 3)
	115 iload_2 (3, 3)
	116 iconst_1 (3, 3)
	117 isub (3, 3)
	118 if_icmpgt (3, 3)
	121 iload_1 (3, 3)
	122 iload (3, 3)
	124 if_icmpeq (3, 3)
	127 iload (3, 3)
	129 i2l (3, 3)
	130 iload (3, 3)
	132 i2l (3, 3)
	133 lmul (3, 3)
	134 lstore (3, 3)
	136 lload (3, 3)
	138 iload_0 (3, 3)
	139 i2l (3, 3)
	140 lrem (3, 3)
	141 l2i (3, 3)
	142 istore (3, 3)
	144 iconst_1 (4, 1)
	145 iload (4, 1)
	147 if_icmpne (4, 1)
	150 iconst_0 (4, 1)
	151 ireturn (4, 1)
	152 iinc (3, 3)
	155 goto (2, 1)
	158 iload_1 (3, 1)
	159 iload (3, 1)
	161 if_icmpeq (3, 1)
	164 iconst_0 (3, 1)
	165 ireturn (3, 1)
	166 iinc (3, 1)
	169 goto (3, 1)
	172 iconst_1 (2, 1)
	173 ireturn (2, 1)

Method: <clinit>
	0 sipush (0, 0)
	3 newarray (0, 0)
	5 dup (0, 0)
	6 iconst_0 (0, 0)
	7 iconst_2 (0, 0)
	8 iastore (0, 0)
	9 dup (0, 0)
	10 iconst_1 (0, 0)
	11 iconst_3 (0, 0)
	12 iastore (0, 0)
	13 dup (0, 0)
	14 iconst_2 (0, 0)
	15 iconst_5 (0, 0)
	16 iastore (0, 0)
	17 dup (0, 0)
	18 iconst_3 (0, 0)
	19 bipush (0, 0)
	21 iastore (0, 0)
	22 dup (0, 0)
	23 iconst_4 (0, 0)
	24 bipush (0, 0)
	26 iastore (0, 0)
	27 dup (0, 0)
	28 iconst_5 (0, 0)
	29 bipush (0, 0)
	31 iastore (0, 0)
	32 dup (0, 0)
	33 bipush (0, 0)
	35 bipush (0, 0)
	37 iastore (0, 0)
	38 dup (0, 0)
	39 bipush (0, 0)
	41 bipush (0, 0)
	43 iastore (0, 0)
	44 dup (0, 0)
	45 bipush (0, 0)
	47 bipush (0, 0)
	49 iastore (0, 0)
	50 dup (0, 0)
	51 bipush (0, 0)
	53 bipush (0, 0)
	55 iastore (0, 0)
	56 dup (0, 0)
	57 bipush (0, 0)
	59 bipush (0, 0)
	61 iastore (0, 0)
	62 dup (0, 0)
	63 bipush (0, 0)
	65 bipush (0, 0)
	67 iastore (0, 0)
	68 dup (0, 0)
	69 bipush (0, 0)
	71 bipush (0, 0)
	73 iastore (0, 0)
	74 dup (0, 0)
	75 bipush (0, 0)
	77 bipush (0, 0)
	79 iastore (0, 0)
	80 dup (0, 0)
	81 bipush (0, 0)
	83 bipush (0, 0)
	85 iastore (0, 0)
	86 dup (0, 0)
	87 bipush (0, 0)
	89 bipush (0, 0)
	91 iastore (0, 0)
	92 dup (0, 0)
	93 bipush (0, 0)
	95 bipush (0, 0)
	97 iastore (0, 0)
	98 dup (0, 0)
	99 bipush (0, 0)
	101 bipush (0, 0)
	103 iastore (0, 0)
	104 dup (0, 0)
	105 bipush (0, 0)
	107 bipush (0, 0)
	109 iastore (0, 0)
	110 dup (0, 0)
	111 bipush (0, 0)
	113 bipush (0, 0)
	115 iastore (0, 0)
	116 dup (0, 0)
	117 bipush (0, 0)
	119 bipush (0, 0)
	121 iastore (0, 0)
	122 dup (0, 0)
	123 bipush (0, 0)
	125 bipush (0, 0)
	127 iastore (0, 0)
	128 dup (0, 0)
	129 bipush (0, 0)
	131 bipush (0, 0)
	133 iastore (0, 0)
	134 dup (0, 0)
	135 bipush (0, 0)
	137 bipush (0, 0)
	139 iastore (0, 0)
	140 dup (0, 0)
	141 bipush (0, 0)
	143 bipush (0, 0)
	145 iastore (0, 0)
	146 dup (0, 0)
	147 bipush (0, 0)
	149 bipush (0, 0)
	151 iastore (0, 0)
	152 dup (0, 0)
	153 bipush (0, 0)
	155 bipush (0, 0)
	157 iastore (0, 0)
	158 dup (0, 0)
	159 bipush (0, 0)
	161 bipush (0, 0)
	163 iastore (0, 0)
	164 dup (0, 0)
	165 bipush (0, 0)
	167 bipush (0, 0)
	169 iastore (0, 0)
	170 dup (0, 0)
	171 bipush (0, 0)
	173 bipush (0, 0)
	175 iastore (0, 0)
	176 dup (0, 0)
	177 bipush (0, 0)
	179 bipush (0, 0)
	181 iastore (0, 0)
	182 dup (0, 0)
	183 bipush (0, 0)
	185 sipush (0, 0)
	188 iastore (0, 0)
	189 dup (0, 0)
	190 bipush (0, 0)
	192 sipush (0, 0)
	195 iastore (0, 0)
	196 dup (0, 0)
	197 bipush (0, 0)
	199 sipush (0, 0)
	202 iastore (0, 0)
	203 dup (0, 0)
	204 bipush (0, 0)
	206 sipush (0, 0)
	209 iastore (0, 0)
	210 dup (0, 0)
	211 bipush (0, 0)
	213 sipush (0, 0)
	216 iastore (0, 0)
	217 dup (0, 0)
	218 bipush (0, 0)
	220 sipush (0, 0)
	223 iastore (0, 0)
	224 dup (0, 0)
	225 bipush (0, 0)
	227 sipush (0, 0)
	230 iastore (0, 0)
	231 dup (0, 0)
	232 bipush (0, 0)
	234 sipush (0, 0)
	237 iastore (0, 0)
	238 dup (0, 0)
	239 bipush (0, 0)
	241 sipush (0, 0)
	244 iastore (0, 0)
	245 dup (0, 0)
	246 bipush (0, 0)
	248 sipush (0, 0)
	251 iastore (0, 0)
	252 dup (0, 0)
	253 bipush (0, 0)
	255 sipush (0, 0)
	258 iastore (0, 0)
	259 dup (0, 0)
	260 bipush (0, 0)
	262 sipush (0, 0)
	265 iastore (0, 0)
	266 dup (0, 0)
	267 bipush (0, 0)
	269 sipush (0, 0)
	272 iastore (0, 0)
	273 dup (0, 0)
	274 bipush (0, 0)
	276 sipush (0, 0)
	279 iastore (0, 0)
	280 dup (0, 0)
	281 bipush (0, 0)
	283 sipush (0, 0)
	286 iastore (0, 0)
	287 dup (0, 0)
	288 bipush (0, 0)
	290 sipush (0, 0)
	293 iastore (0, 0)
	294 dup (0, 0)
	295 bipush (0, 0)
	297 sipush (0, 0)
	300 iastore (0, 0)
	301 dup (0, 0)
	302 bipush (0, 0)
	304 sipush (0, 0)
	307 iastore (0, 0)
	308 dup (0, 0)
	309 bipush (0, 0)
	311 sipush (0, 0)
	314 iastore (0, 0)
	315 dup (0, 0)
	316 bipush (0, 0)
	318 sipush (0, 0)
	321 iastore (0, 0)
	322 dup (0, 0)
	323 bipush (0, 0)
	325 sipush (0, 0)
	328 iastore (0, 0)
	329 dup (0, 0)
	330 bipush (0, 0)
	332 sipush (0, 0)
	335 iastore (0, 0)
	336 dup (0, 0)
	337 bipush (0, 0)
	339 sipush (0, 0)
	342 iastore (0, 0)
	343 dup (0, 0)
	344 bipush (0, 0)
	346 sipush (0, 0)
	349 iastore (0, 0)
	350 dup (0, 0)
	351 bipush (0, 0)
	353 sipush (0, 0)
	356 iastore (0, 0)
	357 dup (0, 0)
	358 bipush (0, 0)
	360 sipush (0, 0)
	363 iastore (0, 0)
	364 dup (0, 0)
	365 bipush (0, 0)
	367 sipush (0, 0)
	370 iastore (0, 0)
	371 dup (0, 0)
	372 bipush (0, 0)
	374 sipush (0, 0)
	377 iastore (0, 0)
	378 dup (0, 0)
	379 bipush (0, 0)
	381 sipush (0, 0)
	384 iastore (0, 0)
	385 dup (0, 0)
	386 bipush (0, 0)
	388 sipush (0, 0)
	391 iastore (0, 0)
	392 dup (0, 0)
	393 bipush (0, 0)
	395 sipush (0, 0)
	398 iastore (0, 0)
	399 dup (0, 0)
	400 bipush (0, 0)
	402 sipush (0, 0)
	405 iastore (0, 0)
	406 dup (0, 0)
	407 bipush (0, 0)
	409 sipush (0, 0)
	412 iastore (0, 0)
	413 dup (0, 0)
	414 bipush (0, 0)
	416 sipush (0, 0)
	419 iastore (0, 0)
	420 dup (0, 0)
	421 bipush (0, 0)
	423 sipush (0, 0)
	426 iastore (0, 0)
	427 dup (0, 0)
	428 bipush (0, 0)
	430 sipush (0, 0)
	433 iastore (0, 0)
	434 dup (0, 0)
	435 bipush (0, 0)
	437 sipush (0, 0)
	440 iastore (0, 0)
	441 dup (0, 0)
	442 bipush (0, 0)
	444 sipush (0, 0)
	447 iastore (0, 0)
	448 dup (0, 0)
	449 bipush (0, 0)
	451 sipush (0, 0)
	454 iastore (0, 0)
	455 dup (0, 0)
	456 bipush (0, 0)
	458 sipush (0, 0)
	461 iastore (0, 0)
	462 dup (0, 0)
	463 bipush (0, 0)
	465 sipush (0, 0)
	468 iastore (0, 0)
	469 dup (0, 0)
	470 bipush (0, 0)
	472 sipush (0, 0)
	475 iastore (0, 0)
	476 dup (0, 0)
	477 bipush (0, 0)
	479 sipush (0, 0)
	482 iastore (0, 0)
	483 dup (0, 0)
	484 bipush (0, 0)
	486 sipush (0, 0)
	489 iastore (0, 0)
	490 dup (0, 0)
	491 bipush (0, 0)
	493 sipush (0, 0)
	496 iastore (0, 0)
	497 dup (0, 0)
	498 bipush (0, 0)
	500 sipush (0, 0)
	503 iastore (0, 0)
	504 dup (0, 0)
	505 bipush (0, 0)
	507 sipush (0, 0)
	510 iastore (0, 0)
	511 dup (0, 0)
	512 bipush (0, 0)
	514 sipush (0, 0)
	517 iastore (0, 0)
	518 dup (0, 0)
	519 bipush (0, 0)
	521 sipush (0, 0)
	524 iastore (0, 0)
	525 dup (0, 0)
	526 bipush (0, 0)
	528 sipush (0, 0)
	531 iastore (0, 0)
	532 dup (0, 0)
	533 bipush (0, 0)
	535 sipush (0, 0)
	538 iastore (0, 0)
	539 dup (0, 0)
	540 bipush (0, 0)
	542 sipush (0, 0)
	545 iastore (0, 0)
	546 dup (0, 0)
	547 bipush (0, 0)
	549 sipush (0, 0)
	552 iastore (0, 0)
	553 dup (0, 0)
	554 bipush (0, 0)
	556 sipush (0, 0)
	559 iastore (0, 0)
	560 dup (0, 0)
	561 bipush (0, 0)
	563 sipush (0, 0)
	566 iastore (0, 0)
	567 dup (0, 0)
	568 bipush (0, 0)
	570 sipush (0, 0)
	573 iastore (0, 0)
	574 dup (0, 0)
	575 bipush (0, 0)
	577 sipush (0, 0)
	580 iastore (0, 0)
	581 dup (0, 0)
	582 bipush (0, 0)
	584 sipush (0, 0)
	587 iastore (0, 0)
	588 dup (0, 0)
	589 bipush (0, 0)
	591 sipush (0, 0)
	594 iastore (0, 0)
	595 dup (0, 0)
	596 bipush (0, 0)
	598 sipush (0, 0)
	601 iastore (0, 0)
	602 dup (0, 0)
	603 bipush (0, 0)
	605 sipush (0, 0)
	608 iastore (0, 0)
	609 dup (0, 0)
	610 bipush (0, 0)
	612 sipush (0, 0)
	615 iastore (0, 0)
	616 dup (0, 0)
	617 bipush (0, 0)
	619 sipush (0, 0)
	622 iastore (0, 0)
	623 dup (0, 0)
	624 bipush (0, 0)
	626 sipush (0, 0)
	629 iastore (0, 0)
	630 dup (0, 0)
	631 bipush (0, 0)
	633 sipush (0, 0)
	636 iastore (0, 0)
	637 dup (0, 0)
	638 bipush (0, 0)
	640 sipush (0, 0)
	643 iastore (0, 0)
	644 dup (0, 0)
	645 bipush (0, 0)
	647 sipush (0, 0)
	650 iastore (0, 0)
	651 dup (0, 0)
	652 bipush (0, 0)
	654 sipush (0, 0)
	657 iastore (0, 0)
	658 dup (0, 0)
	659 bipush (0, 0)
	661 sipush (0, 0)
	664 iastore (0, 0)
	665 dup (0, 0)
	666 bipush (0, 0)
	668 sipush (0, 0)
	671 iastore (0, 0)
	672 dup (0, 0)
	673 bipush (0, 0)
	675 sipush (0, 0)
	678 iastore (0, 0)
	679 dup (0, 0)
	680 bipush (0, 0)
	682 sipush (0, 0)
	685 iastore (0, 0)
	686 dup (0, 0)
	687 bipush (0, 0)
	689 sipush (0, 0)
	692 iastore (0, 0)
	693 dup (0, 0)
	694 bipush (0, 0)
	696 sipush (0, 0)
	699 iastore (0, 0)
	700 dup (0, 0)
	701 bipush (0, 0)
	703 sipush (0, 0)
	706 iastore (0, 0)
	707 dup (0, 0)
	708 bipush (0, 0)
	710 sipush (0, 0)
	713 iastore (0, 0)
	714 dup (0, 0)
	715 bipush (0, 0)
	717 sipush (0, 0)
	720 iastore (0, 0)
	721 dup (0, 0)
	722 bipush (0, 0)
	724 sipush (0, 0)
	727 iastore (0, 0)
	728 dup (0, 0)
	729 bipush (0, 0)
	731 sipush (0, 0)
	734 iastore (0, 0)
	735 dup (0, 0)
	736 bipush (0, 0)
	738 sipush (0, 0)
	741 iastore (0, 0)
	742 dup (0, 0)
	743 bipush (0, 0)
	745 sipush (0, 0)
	748 iastore (0, 0)
	749 dup (0, 0)
	750 bipush (0, 0)
	752 sipush (0, 0)
	755 iastore (0, 0)
	756 dup (0, 0)
	757 bipush (0, 0)
	759 sipush (0, 0)
	762 iastore (0, 0)
	763 dup (0, 0)
	764 bipush (0, 0)
	766 sipush (0, 0)
	769 iastore (0, 0)
	770 dup (0, 0)
	771 bipush (0, 0)
	773 sipush (0, 0)
	776 iastore (0, 0)
	777 dup (0, 0)
	778 bipush (0, 0)
	780 sipush (0, 0)
	783 iastore (0, 0)
	784 dup (0, 0)
	785 bipush (0, 0)
	787 sipush (0, 0)
	790 iastore (0, 0)
	791 dup (0, 0)
	792 bipush (0, 0)
	794 sipush (0, 0)
	797 iastore (0, 0)
	798 dup (0, 0)
	799 bipush (0, 0)
	801 sipush (0, 0)
	804 iastore (0, 0)
	805 dup (0, 0)
	806 bipush (0, 0)
	808 sipush (0, 0)
	811 iastore (0, 0)
	812 dup (0, 0)
	813 bipush (0, 0)
	815 sipush (0, 0)
	818 iastore (0, 0)
	819 dup (0, 0)
	820 bipush (0, 0)
	822 sipush (0, 0)
	825 iastore (0, 0)
	826 dup (0, 0)
	827 bipush (0, 0)
	829 sipush (0, 0)
	832 iastore (0, 0)
	833 dup (0, 0)
	834 bipush (0, 0)
	836 sipush (0, 0)
	839 iastore (0, 0)
	840 dup (0, 0)
	841 bipush (0, 0)
	843 sipush (0, 0)
	846 iastore (0, 0)
	847 dup (0, 0)
	848 bipush (0, 0)
	850 sipush (0, 0)
	853 iastore (0, 0)
	854 dup (0, 0)
	855 bipush (0, 0)
	857 sipush (0, 0)
	860 iastore (0, 0)
	861 dup (0, 0)
	862 sipush (0, 0)
	865 sipush (0, 0)
	868 iastore (0, 0)
	869 dup (0, 0)
	870 sipush (0, 0)
	873 sipush (0, 0)
	876 iastore (0, 0)
	877 dup (0, 0)
	878 sipush (0, 0)
	881 sipush (0, 0)
	884 iastore (0, 0)
	885 dup (0, 0)
	886 sipush (0, 0)
	889 sipush (0, 0)
	892 iastore (0, 0)
	893 dup (0, 0)
	894 sipush (0, 0)
	897 sipush (0, 0)
	900 iastore (0, 0)
	901 dup (0, 0)
	902 sipush (0, 0)
	905 sipush (0, 0)
	908 iastore (0, 0)
	909 dup (0, 0)
	910 sipush (0, 0)
	913 sipush (0, 0)
	916 iastore (0, 0)
	917 dup (0, 0)
	918 sipush (0, 0)
	921 sipush (0, 0)
	924 iastore (0, 0)
	925 dup (0, 0)
	926 sipush (0, 0)
	929 sipush (0, 0)
	932 iastore (0, 0)
	933 dup (0, 0)
	934 sipush (0, 0)
	937 sipush (0, 0)
	940 iastore (0, 0)
	941 dup (0, 0)
	942 sipush (0, 0)
	945 sipush (0, 0)
	948 iastore (0, 0)
	949 dup (0, 0)
	950 sipush (0, 0)
	953 sipush (0, 0)
	956 iastore (0, 0)
	957 dup (0, 0)
	958 sipush (0, 0)
	961 sipush (0, 0)
	964 iastore (0, 0)
	965 dup (0, 0)
	966 sipush (0, 0)
	969 sipush (0, 0)
	972 iastore (0, 0)
	973 dup (0, 0)
	974 sipush (0, 0)
	977 sipush (0, 0)
	980 iastore (0, 0)
	981 dup (0, 0)
	982 sipush (0, 0)
	985 sipush (0, 0)
	988 iastore (0, 0)
	989 dup (0, 0)
	990 sipush (0, 0)
	993 sipush (0, 0)
	996 iastore (0, 0)
	997 dup (0, 0)
	998 sipush (0, 0)
	1001 sipush (0, 0)
	1004 iastore (0, 0)
	1005 dup (0, 0)
	1006 sipush (0, 0)
	1009 sipush (0, 0)
	1012 iastore (0, 0)
	1013 dup (0, 0)
	1014 sipush (0, 0)
	1017 sipush (0, 0)
	1020 iastore (0, 0)
	1021 dup (0, 0)
	1022 sipush (0, 0)
	1025 sipush (0, 0)
	1028 iastore (0, 0)
	1029 dup (0, 0)
	1030 sipush (0, 0)
	1033 sipush (0, 0)
	1036 iastore (0, 0)
	1037 dup (0, 0)
	1038 sipush (0, 0)
	1041 sipush (0, 0)
	1044 iastore (0, 0)
	1045 dup (0, 0)
	1046 sipush (0, 0)
	1049 sipush (0, 0)
	1052 iastore (0, 0)
	1053 dup (0, 0)
	1054 sipush (0, 0)
	1057 sipush (0, 0)
	1060 iastore (0, 0)
	1061 dup (0, 0)
	1062 sipush (0, 0)
	1065 sipush (0, 0)
	1068 iastore (0, 0)
	1069 dup (0, 0)
	1070 sipush (0, 0)
	1073 sipush (0, 0)
	1076 iastore (0, 0)
	1077 dup (0, 0)
	1078 sipush (0, 0)
	1081 sipush (0, 0)
	1084 iastore (0, 0)
	1085 dup (0, 0)
	1086 sipush (0, 0)
	1089 sipush (0, 0)
	1092 iastore (0, 0)
	1093 dup (0, 0)
	1094 sipush (0, 0)
	1097 sipush (0, 0)
	1100 iastore (0, 0)
	1101 dup (0, 0)
	1102 sipush (0, 0)
	1105 sipush (0, 0)
	1108 iastore (0, 0)
	1109 dup (0, 0)
	1110 sipush (0, 0)
	1113 sipush (0, 0)
	1116 iastore (0, 0)
	1117 dup (0, 0)
	1118 sipush (0, 0)
	1121 sipush (0, 0)
	1124 iastore (0, 0)
	1125 dup (0, 0)
	1126 sipush (0, 0)
	1129 sipush (0, 0)
	1132 iastore (0, 0)
	1133 dup (0, 0)
	1134 sipush (0, 0)
	1137 sipush (0, 0)
	1140 iastore (0, 0)
	1141 dup (0, 0)
	1142 sipush (0, 0)
	1145 sipush (0, 0)
	1148 iastore (0, 0)
	1149 dup (0, 0)
	1150 sipush (0, 0)
	1153 sipush (0, 0)
	1156 iastore (0, 0)
	1157 dup (0, 0)
	1158 sipush (0, 0)
	1161 sipush (0, 0)
	1164 iastore (0, 0)
	1165 dup (0, 0)
	1166 sipush (0, 0)
	1169 sipush (0, 0)
	1172 iastore (0, 0)
	1173 dup (0, 0)
	1174 sipush (0, 0)
	1177 sipush (0, 0)
	1180 iastore (0, 0)
	1181 dup (0, 0)
	1182 sipush (0, 0)
	1185 sipush (0, 0)
	1188 iastore (0, 0)
	1189 dup (0, 0)
	1190 sipush (0, 0)
	1193 sipush (0, 0)
	1196 iastore (0, 0)
	1197 dup (0, 0)
	1198 sipush (0, 0)
	1201 sipush (0, 0)
	1204 iastore (0, 0)
	1205 dup (0, 0)
	1206 sipush (0, 0)
	1209 sipush (0, 0)
	1212 iastore (0, 0)
	1213 dup (0, 0)
	1214 sipush (0, 0)
	1217 sipush (0, 0)
	1220 iastore (0, 0)
	1221 dup (0, 0)
	1222 sipush (0, 0)
	1225 sipush (0, 0)
	1228 iastore (0, 0)
	1229 dup (0, 0)
	1230 sipush (0, 0)
	1233 sipush (0, 0)
	1236 iastore (0, 0)
	1237 dup (0, 0)
	1238 sipush (0, 0)
	1241 sipush (0, 0)
	1244 iastore (0, 0)
	1245 dup (0, 0)
	1246 sipush (0, 0)
	1249 sipush (0, 0)
	1252 iastore (0, 0)
	1253 dup (0, 0)
	1254 sipush (0, 0)
	1257 sipush (0, 0)
	1260 iastore (0, 0)
	1261 dup (0, 0)
	1262 sipush (0, 0)
	1265 sipush (0, 0)
	1268 iastore (0, 0)
	1269 dup (0, 0)
	1270 sipush (0, 0)
	1273 sipush (0, 0)
	1276 iastore (0, 0)
	1277 dup (0, 0)
	1278 sipush (0, 0)
	1281 sipush (0, 0)
	1284 iastore (0, 0)
	1285 dup (0, 0)
	1286 sipush (0, 0)
	1289 sipush (0, 0)
	1292 iastore (0, 0)
	1293 dup (0, 0)
	1294 sipush (0, 0)
	1297 sipush (0, 0)
	1300 iastore (0, 0)
	1301 dup (0, 0)
	1302 sipush (0, 0)
	1305 sipush (0, 0)
	1308 iastore (0, 0)
	1309 dup (0, 0)
	1310 sipush (0, 0)
	1313 sipush (0, 0)
	1316 iastore (0, 0)
	1317 dup (0, 0)
	1318 sipush (0, 0)
	1321 sipush (0, 0)
	1324 iastore (0, 0)
	1325 dup (0, 0)
	1326 sipush (0, 0)
	1329 sipush (0, 0)
	1332 iastore (0, 0)
	1333 dup (0, 0)
	1334 sipush (0, 0)
	1337 sipush (0, 0)
	1340 iastore (0, 0)
	1341 dup (0, 0)
	1342 sipush (0, 0)
	1345 sipush (0, 0)
	1348 iastore (0, 0)
	1349 dup (0, 0)
	1350 sipush (0, 0)
	1353 sipush (0, 0)
	1356 iastore (0, 0)
	1357 dup (0, 0)
	1358 sipush (0, 0)
	1361 sipush (0, 0)
	1364 iastore (0, 0)
	1365 dup (0, 0)
	1366 sipush (0, 0)
	1369 sipush (0, 0)
	1372 iastore (0, 0)
	1373 dup (0, 0)
	1374 sipush (0, 0)
	1377 sipush (0, 0)
	1380 iastore (0, 0)
	1381 dup (0, 0)
	1382 sipush (0, 0)
	1385 sipush (0, 0)
	1388 iastore (0, 0)
	1389 dup (0, 0)
	1390 sipush (0, 0)
	1393 sipush (0, 0)
	1396 iastore (0, 0)
	1397 dup (0, 0)
	1398 sipush (0, 0)
	1401 sipush (0, 0)
	1404 iastore (0, 0)
	1405 dup (0, 0)
	1406 sipush (0, 0)
	1409 sipush (0, 0)
	1412 iastore (0, 0)
	1413 dup (0, 0)
	1414 sipush (0, 0)
	1417 sipush (0, 0)
	1420 iastore (0, 0)
	1421 dup (0, 0)
	1422 sipush (0, 0)
	1425 sipush (0, 0)
	1428 iastore (0, 0)
	1429 dup (0, 0)
	1430 sipush (0, 0)
	1433 sipush (0, 0)
	1436 iastore (0, 0)
	1437 dup (0, 0)
	1438 sipush (0, 0)
	1441 sipush (0, 0)
	1444 iastore (0, 0)
	1445 dup (0, 0)
	1446 sipush (0, 0)
	1449 sipush (0, 0)
	1452 iastore (0, 0)
	1453 dup (0, 0)
	1454 sipush (0, 0)
	1457 sipush (0, 0)
	1460 iastore (0, 0)
	1461 dup (0, 0)
	1462 sipush (0, 0)
	1465 sipush (0, 0)
	1468 iastore (0, 0)
	1469 dup (0, 0)
	1470 sipush (0, 0)
	1473 sipush (0, 0)
	1476 iastore (0, 0)
	1477 dup (0, 0)
	1478 sipush (0, 0)
	1481 sipush (0, 0)
	1484 iastore (0, 0)
	1485 dup (0, 0)
	1486 sipush (0, 0)
	1489 sipush (0, 0)
	1492 iastore (0, 0)
	1493 dup (0, 0)
	1494 sipush (0, 0)
	1497 sipush (0, 0)
	1500 iastore (0, 0)
	1501 dup (0, 0)
	1502 sipush (0, 0)
	1505 sipush (0, 0)
	1508 iastore (0, 0)
	1509 dup (0, 0)
	1510 sipush (0, 0)
	1513 sipush (0, 0)
	1516 iastore (0, 0)
	1517 dup (0, 0)
	1518 sipush (0, 0)
	1521 sipush (0, 0)
	1524 iastore (0, 0)
	1525 dup (0, 0)
	1526 sipush (0, 0)
	1529 sipush (0, 0)
	1532 iastore (0, 0)
	1533 dup (0, 0)
	1534 sipush (0, 0)
	1537 sipush (0, 0)
	1540 iastore (0, 0)
	1541 dup (0, 0)
	1542 sipush (0, 0)
	1545 sipush (0, 0)
	1548 iastore (0, 0)
	1549 dup (0, 0)
	1550 sipush (0, 0)
	1553 sipush (0, 0)
	1556 iastore (0, 0)
	1557 dup (0, 0)
	1558 sipush (0, 0)
	1561 sipush (0, 0)
	1564 iastore (0, 0)
	1565 dup (0, 0)
	1566 sipush (0, 0)
	1569 sipush (0, 0)
	1572 iastore (0, 0)
	1573 dup (0, 0)
	1574 sipush (0, 0)
	1577 sipush (0, 0)
	1580 iastore (0, 0)
	1581 dup (0, 0)
	1582 sipush (0, 0)
	1585 sipush (0, 0)
	1588 iastore (0, 0)
	1589 dup (0, 0)
	1590 sipush (0, 0)
	1593 sipush (0, 0)
	1596 iastore (0, 0)
	1597 dup (0, 0)
	1598 sipush (0, 0)
	1601 sipush (0, 0)
	1604 iastore (0, 0)
	1605 dup (0, 0)
	1606 sipush (0, 0)
	1609 sipush (0, 0)
	1612 iastore (0, 0)
	1613 dup (0, 0)
	1614 sipush (0, 0)
	1617 sipush (0, 0)
	1620 iastore (0, 0)
	1621 dup (0, 0)
	1622 sipush (0, 0)
	1625 sipush (0, 0)
	1628 iastore (0, 0)
	1629 dup (0, 0)
	1630 sipush (0, 0)
	1633 sipush (0, 0)
	1636 iastore (0, 0)
	1637 dup (0, 0)
	1638 sipush (0, 0)
	1641 sipush (0, 0)
	1644 iastore (0, 0)
	1645 dup (0, 0)
	1646 sipush (0, 0)
	1649 sipush (0, 0)
	1652 iastore (0, 0)
	1653 dup (0, 0)
	1654 sipush (0, 0)
	1657 sipush (0, 0)
	1660 iastore (0, 0)
	1661 dup (0, 0)
	1662 sipush (0, 0)
	1665 sipush (0, 0)
	1668 iastore (0, 0)
	1669 dup (0, 0)
	1670 sipush (0, 0)
	1673 sipush (0, 0)
	1676 iastore (0, 0)
	1677 dup (0, 0)
	1678 sipush (0, 0)
	1681 sipush (0, 0)
	1684 iastore (0, 0)
	1685 dup (0, 0)
	1686 sipush (0, 0)
	1689 sipush (0, 0)
	1692 iastore (0, 0)
	1693 dup (0, 0)
	1694 sipush (0, 0)
	1697 sipush (0, 0)
	1700 iastore (0, 0)
	1701 dup (0, 0)
	1702 sipush (0, 0)
	1705 sipush (0, 0)
	1708 iastore (0, 0)
	1709 dup (0, 0)
	1710 sipush (0, 0)
	1713 sipush (0, 0)
	1716 iastore (0, 0)
	1717 dup (0, 0)
	1718 sipush (0, 0)
	1721 sipush (0, 0)
	1724 iastore (0, 0)
	1725 dup (0, 0)
	1726 sipush (0, 0)
	1729 sipush (0, 0)
	1732 iastore (0, 0)
	1733 dup (0, 0)
	1734 sipush (0, 0)
	1737 sipush (0, 0)
	1740 iastore (0, 0)
	1741 dup (0, 0)
	1742 sipush (0, 0)
	1745 sipush (0, 0)
	1748 iastore (0, 0)
	1749 dup (0, 0)
	1750 sipush (0, 0)
	1753 sipush (0, 0)
	1756 iastore (0, 0)
	1757 dup (0, 0)
	1758 sipush (0, 0)
	1761 sipush (0, 0)
	1764 iastore (0, 0)
	1765 dup (0, 0)
	1766 sipush (0, 0)
	1769 sipush (0, 0)
	1772 iastore (0, 0)
	1773 dup (0, 0)
	1774 sipush (0, 0)
	1777 sipush (0, 0)
	1780 iastore (0, 0)
	1781 dup (0, 0)
	1782 sipush (0, 0)
	1785 sipush (0, 0)
	1788 iastore (0, 0)
	1789 dup (0, 0)
	1790 sipush (0, 0)
	1793 sipush (0, 0)
	1796 iastore (0, 0)
	1797 dup (0, 0)
	1798 sipush (0, 0)
	1801 sipush (0, 0)
	1804 iastore (0, 0)
	1805 dup (0, 0)
	1806 sipush (0, 0)
	1809 sipush (0, 0)
	1812 iastore (0, 0)
	1813 dup (0, 0)
	1814 sipush (0, 0)
	1817 sipush (0, 0)
	1820 iastore (0, 0)
	1821 dup (0, 0)
	1822 sipush (0, 0)
	1825 sipush (0, 0)
	1828 iastore (0, 0)
	1829 dup (0, 0)
	1830 sipush (0, 0)
	1833 sipush (0, 0)
	1836 iastore (0, 0)
	1837 dup (0, 0)
	1838 sipush (0, 0)
	1841 sipush (0, 0)
	1844 iastore (0, 0)
	1845 dup (0, 0)
	1846 sipush (0, 0)
	1849 sipush (0, 0)
	1852 iastore (0, 0)
	1853 dup (0, 0)
	1854 sipush (0, 0)
	1857 sipush (0, 0)
	1860 iastore (0, 0)
	1861 dup (0, 0)
	1862 sipush (0, 0)
	1865 sipush (0, 0)
	1868 iastore (0, 0)
	1869 dup (0, 0)
	1870 sipush (0, 0)
	1873 sipush (0, 0)
	1876 iastore (0, 0)
	1877 dup (0, 0)
	1878 sipush (0, 0)
	1881 sipush (0, 0)
	1884 iastore (0, 0)
	1885 dup (0, 0)
	1886 sipush (0, 0)
	1889 sipush (0, 0)
	1892 iastore (0, 0)
	1893 dup (0, 0)
	1894 sipush (0, 0)
	1897 sipush (0, 0)
	1900 iastore (0, 0)
	1901 dup (0, 0)
	1902 sipush (0, 0)
	1905 sipush (0, 0)
	1908 iastore (0, 0)
	1909 dup (0, 0)
	1910 sipush (0, 0)
	1913 sipush (0, 0)
	1916 iastore (0, 0)
	1917 dup (0, 0)
	1918 sipush (0, 0)
	1921 sipush (0, 0)
	1924 iastore (0, 0)
	1925 dup (0, 0)
	1926 sipush (0, 0)
	1929 sipush (0, 0)
	1932 iastore (0, 0)
	1933 dup (0, 0)
	1934 sipush (0, 0)
	1937 sipush (0, 0)
	1940 iastore (0, 0)
	1941 dup (0, 0)
	1942 sipush (0, 0)
	1945 sipush (0, 0)
	1948 iastore (0, 0)
	1949 dup (0, 0)
	1950 sipush (0, 0)
	1953 sipush (0, 0)
	1956 iastore (0, 0)
	1957 dup (0, 0)
	1958 sipush (0, 0)
	1961 sipush (0, 0)
	1964 iastore (0, 0)
	1965 dup (0, 0)
	1966 sipush (0, 0)
	1969 sipush (0, 0)
	1972 iastore (0, 0)
	1973 dup (0, 0)
	1974 sipush (0, 0)
	1977 sipush (0, 0)
	1980 iastore (0, 0)
	1981 dup (0, 0)
	1982 sipush (0, 0)
	1985 sipush (0, 0)
	1988 iastore (0, 0)
	1989 dup (0, 0)
	1990 sipush (0, 0)
	1993 sipush (0, 0)
	1996 iastore (0, 0)
	1997 dup (0, 0)
	1998 sipush (0, 0)
	2001 sipush (0, 0)
	2004 iastore (0, 0)
	2005 dup (0, 0)
	2006 sipush (0, 0)
	2009 sipush (0, 0)
	2012 iastore (0, 0)
	2013 dup (0, 0)
	2014 sipush (0, 0)
	2017 sipush (0, 0)
	2020 iastore (0, 0)
	2021 dup (0, 0)
	2022 sipush (0, 0)
	2025 sipush (0, 0)
	2028 iastore (0, 0)
	2029 dup (0, 0)
	2030 sipush (0, 0)
	2033 sipush (0, 0)
	2036 iastore (0, 0)
	2037 dup (0, 0)
	2038 sipush (0, 0)
	2041 sipush (0, 0)
	2044 iastore (0, 0)
	2045 dup (0, 0)
	2046 sipush (0, 0)
	2049 sipush (0, 0)
	2052 iastore (0, 0)
	2053 dup (0, 0)
	2054 sipush (0, 0)
	2057 sipush (0, 0)
	2060 iastore (0, 0)
	2061 dup (0, 0)
	2062 sipush (0, 0)
	2065 sipush (0, 0)
	2068 iastore (0, 0)
	2069 dup (0, 0)
	2070 sipush (0, 0)
	2073 sipush (0, 0)
	2076 iastore (0, 0)
	2077 dup (0, 0)
	2078 sipush (0, 0)
	2081 sipush (0, 0)
	2084 iastore (0, 0)
	2085 dup (0, 0)
	2086 sipush (0, 0)
	2089 sipush (0, 0)
	2092 iastore (0, 0)
	2093 dup (0, 0)
	2094 sipush (0, 0)
	2097 sipush (0, 0)
	2100 iastore (0, 0)
	2101 dup (0, 0)
	2102 sipush (0, 0)
	2105 sipush (0, 0)
	2108 iastore (0, 0)
	2109 dup (0, 0)
	2110 sipush (0, 0)
	2113 sipush (0, 0)
	2116 iastore (0, 0)
	2117 dup (0, 0)
	2118 sipush (0, 0)
	2121 sipush (0, 0)
	2124 iastore (0, 0)
	2125 dup (0, 0)
	2126 sipush (0, 0)
	2129 sipush (0, 0)
	2132 iastore (0, 0)
	2133 dup (0, 0)
	2134 sipush (0, 0)
	2137 sipush (0, 0)
	2140 iastore (0, 0)
	2141 dup (0, 0)
	2142 sipush (0, 0)
	2145 sipush (0, 0)
	2148 iastore (0, 0)
	2149 dup (0, 0)
	2150 sipush (0, 0)
	2153 sipush (0, 0)
	2156 iastore (0, 0)
	2157 dup (0, 0)
	2158 sipush (0, 0)
	2161 sipush (0, 0)
	2164 iastore (0, 0)
	2165 dup (0, 0)
	2166 sipush (0, 0)
	2169 sipush (0, 0)
	2172 iastore (0, 0)
	2173 dup (0, 0)
	2174 sipush (0, 0)
	2177 sipush (0, 0)
	2180 iastore (0, 0)
	2181 dup (0, 0)
	2182 sipush (0, 0)
	2185 sipush (0, 0)
	2188 iastore (0, 0)
	2189 dup (0, 0)
	2190 sipush (0, 0)
	2193 sipush (0, 0)
	2196 iastore (0, 0)
	2197 dup (0, 0)
	2198 sipush (0, 0)
	2201 sipush (0, 0)
	2204 iastore (0, 0)
	2205 dup (0, 0)
	2206 sipush (0, 0)
	2209 sipush (0, 0)
	2212 iastore (0, 0)
	2213 dup (0, 0)
	2214 sipush (0, 0)
	2217 sipush (0, 0)
	2220 iastore (0, 0)
	2221 dup (0, 0)
	2222 sipush (0, 0)
	2225 sipush (0, 0)
	2228 iastore (0, 0)
	2229 dup (0, 0)
	2230 sipush (0, 0)
	2233 sipush (0, 0)
	2236 iastore (0, 0)
	2237 dup (0, 0)
	2238 sipush (0, 0)
	2241 sipush (0, 0)
	2244 iastore (0, 0)
	2245 dup (0, 0)
	2246 sipush (0, 0)
	2249 sipush (0, 0)
	2252 iastore (0, 0)
	2253 dup (0, 0)
	2254 sipush (0, 0)
	2257 sipush (0, 0)
	2260 iastore (0, 0)
	2261 dup (0, 0)
	2262 sipush (0, 0)
	2265 sipush (0, 0)
	2268 iastore (0, 0)
	2269 dup (0, 0)
	2270 sipush (0, 0)
	2273 sipush (0, 0)
	2276 iastore (0, 0)
	2277 dup (0, 0)
	2278 sipush (0, 0)
	2281 sipush (0, 0)
	2284 iastore (0, 0)
	2285 dup (0, 0)
	2286 sipush (0, 0)
	2289 sipush (0, 0)
	2292 iastore (0, 0)
	2293 dup (0, 0)
	2294 sipush (0, 0)
	2297 sipush (0, 0)
	2300 iastore (0, 0)
	2301 dup (0, 0)
	2302 sipush (0, 0)
	2305 sipush (0, 0)
	2308 iastore (0, 0)
	2309 dup (0, 0)
	2310 sipush (0, 0)
	2313 sipush (0, 0)
	2316 iastore (0, 0)
	2317 dup (0, 0)
	2318 sipush (0, 0)
	2321 sipush (0, 0)
	2324 iastore (0, 0)
	2325 dup (0, 0)
	2326 sipush (0, 0)
	2329 sipush (0, 0)
	2332 iastore (0, 0)
	2333 dup (0, 0)
	2334 sipush (0, 0)
	2337 sipush (0, 0)
	2340 iastore (0, 0)
	2341 dup (0, 0)
	2342 sipush (0, 0)
	2345 sipush (0, 0)
	2348 iastore (0, 0)
	2349 dup (0, 0)
	2350 sipush (0, 0)
	2353 sipush (0, 0)
	2356 iastore (0, 0)
	2357 dup (0, 0)
	2358 sipush (0, 0)
	2361 sipush (0, 0)
	2364 iastore (0, 0)
	2365 dup (0, 0)
	2366 sipush (0, 0)
	2369 sipush (0, 0)
	2372 iastore (0, 0)
	2373 dup (0, 0)
	2374 sipush (0, 0)
	2377 sipush (0, 0)
	2380 iastore (0, 0)
	2381 dup (0, 0)
	2382 sipush (0, 0)
	2385 sipush (0, 0)
	2388 iastore (0, 0)
	2389 dup (0, 0)
	2390 sipush (0, 0)
	2393 sipush (0, 0)
	2396 iastore (0, 0)
	2397 dup (0, 0)
	2398 sipush (0, 0)
	2401 sipush (0, 0)
	2404 iastore (0, 0)
	2405 dup (0, 0)
	2406 sipush (0, 0)
	2409 sipush (0, 0)
	2412 iastore (0, 0)
	2413 dup (0, 0)
	2414 sipush (0, 0)
	2417 sipush (0, 0)
	2420 iastore (0, 0)
	2421 dup (0, 0)
	2422 sipush (0, 0)
	2425 sipush (0, 0)
	2428 iastore (0, 0)
	2429 dup (0, 0)
	2430 sipush (0, 0)
	2433 sipush (0, 0)
	2436 iastore (0, 0)
	2437 dup (0, 0)
	2438 sipush (0, 0)
	2441 sipush (0, 0)
	2444 iastore (0, 0)
	2445 dup (0, 0)
	2446 sipush (0, 0)
	2449 sipush (0, 0)
	2452 iastore (0, 0)
	2453 dup (0, 0)
	2454 sipush (0, 0)
	2457 sipush (0, 0)
	2460 iastore (0, 0)
	2461 dup (0, 0)
	2462 sipush (0, 0)
	2465 sipush (0, 0)
	2468 iastore (0, 0)
	2469 dup (0, 0)
	2470 sipush (0, 0)
	2473 sipush (0, 0)
	2476 iastore (0, 0)
	2477 dup (0, 0)
	2478 sipush (0, 0)
	2481 sipush (0, 0)
	2484 iastore (0, 0)
	2485 dup (0, 0)
	2486 sipush (0, 0)
	2489 sipush (0, 0)
	2492 iastore (0, 0)
	2493 dup (0, 0)
	2494 sipush (0, 0)
	2497 sipush (0, 0)
	2500 iastore (0, 0)
	2501 dup (0, 0)
	2502 sipush (0, 0)
	2505 sipush (0, 0)
	2508 iastore (0, 0)
	2509 dup (0, 0)
	2510 sipush (0, 0)
	2513 sipush (0, 0)
	2516 iastore (0, 0)
	2517 dup (0, 0)
	2518 sipush (0, 0)
	2521 sipush (0, 0)
	2524 iastore (0, 0)
	2525 dup (0, 0)
	2526 sipush (0, 0)
	2529 sipush (0, 0)
	2532 iastore (0, 0)
	2533 dup (0, 0)
	2534 sipush (0, 0)
	2537 sipush (0, 0)
	2540 iastore (0, 0)
	2541 dup (0, 0)
	2542 sipush (0, 0)
	2545 sipush (0, 0)
	2548 iastore (0, 0)
	2549 dup (0, 0)
	2550 sipush (0, 0)
	2553 sipush (0, 0)
	2556 iastore (0, 0)
	2557 dup (0, 0)
	2558 sipush (0, 0)
	2561 sipush (0, 0)
	2564 iastore (0, 0)
	2565 dup (0, 0)
	2566 sipush (0, 0)
	2569 sipush (0, 0)
	2572 iastore (0, 0)
	2573 dup (0, 0)
	2574 sipush (0, 0)
	2577 sipush (0, 0)
	2580 iastore (0, 0)
	2581 dup (0, 0)
	2582 sipush (0, 0)
	2585 sipush (0, 0)
	2588 iastore (0, 0)
	2589 dup (0, 0)
	2590 sipush (0, 0)
	2593 sipush (0, 0)
	2596 iastore (0, 0)
	2597 dup (0, 0)
	2598 sipush (0, 0)
	2601 sipush (0, 0)
	2604 iastore (0, 0)
	2605 dup (0, 0)
	2606 sipush (0, 0)
	2609 sipush (0, 0)
	2612 iastore (0, 0)
	2613 dup (0, 0)
	2614 sipush (0, 0)
	2617 sipush (0, 0)
	2620 iastore (0, 0)
	2621 dup (0, 0)
	2622 sipush (0, 0)
	2625 sipush (0, 0)
	2628 iastore (0, 0)
	2629 dup (0, 0)
	2630 sipush (0, 0)
	2633 sipush (0, 0)
	2636 iastore (0, 0)
	2637 dup (0, 0)
	2638 sipush (0, 0)
	2641 sipush (0, 0)
	2644 iastore (0, 0)
	2645 dup (0, 0)
	2646 sipush (0, 0)
	2649 sipush (0, 0)
	2652 iastore (0, 0)
	2653 dup (0, 0)
	2654 sipush (0, 0)
	2657 sipush (0, 0)
	2660 iastore (0, 0)
	2661 dup (0, 0)
	2662 sipush (0, 0)
	2665 sipush (0, 0)
	2668 iastore (0, 0)
	2669 dup (0, 0)
	2670 sipush (0, 0)
	2673 sipush (0, 0)
	2676 iastore (0, 0)
	2677 dup (0, 0)
	2678 sipush (0, 0)
	2681 sipush (0, 0)
	2684 iastore (0, 0)
	2685 dup (0, 0)
	2686 sipush (0, 0)
	2689 sipush (0, 0)
	2692 iastore (0, 0)
	2693 dup (0, 0)
	2694 sipush (0, 0)
	2697 sipush (0, 0)
	2700 iastore (0, 0)
	2701 dup (0, 0)
	2702 sipush (0, 0)
	2705 sipush (0, 0)
	2708 iastore (0, 0)
	2709 dup (0, 0)
	2710 sipush (0, 0)
	2713 sipush (0, 0)
	2716 iastore (0, 0)
	2717 dup (0, 0)
	2718 sipush (0, 0)
	2721 sipush (0, 0)
	2724 iastore (0, 0)
	2725 dup (0, 0)
	2726 sipush (0, 0)
	2729 sipush (0, 0)
	2732 iastore (0, 0)
	2733 dup (0, 0)
	2734 sipush (0, 0)
	2737 sipush (0, 0)
	2740 iastore (0, 0)
	2741 dup (0, 0)
	2742 sipush (0, 0)
	2745 sipush (0, 0)
	2748 iastore (0, 0)
	2749 dup (0, 0)
	2750 sipush (0, 0)
	2753 sipush (0, 0)
	2756 iastore (0, 0)
	2757 dup (0, 0)
	2758 sipush (0, 0)
	2761 sipush (0, 0)
	2764 iastore (0, 0)
	2765 dup (0, 0)
	2766 sipush (0, 0)
	2769 sipush (0, 0)
	2772 iastore (0, 0)
	2773 dup (0, 0)
	2774 sipush (0, 0)
	2777 sipush (0, 0)
	2780 iastore (0, 0)
	2781 dup (0, 0)
	2782 sipush (0, 0)
	2785 sipush (0, 0)
	2788 iastore (0, 0)
	2789 dup (0, 0)
	2790 sipush (0, 0)
	2793 sipush (0, 0)
	2796 iastore (0, 0)
	2797 dup (0, 0)
	2798 sipush (0, 0)
	2801 sipush (0, 0)
	2804 iastore (0, 0)
	2805 dup (0, 0)
	2806 sipush (0, 0)
	2809 sipush (0, 0)
	2812 iastore (0, 0)
	2813 dup (0, 0)
	2814 sipush (0, 0)
	2817 sipush (0, 0)
	2820 iastore (0, 0)
	2821 dup (0, 0)
	2822 sipush (0, 0)
	2825 sipush (0, 0)
	2828 iastore (0, 0)
	2829 dup (0, 0)
	2830 sipush (0, 0)
	2833 sipush (0, 0)
	2836 iastore (0, 0)
	2837 dup (0, 0)
	2838 sipush (0, 0)
	2841 sipush (0, 0)
	2844 iastore (0, 0)
	2845 dup (0, 0)
	2846 sipush (0, 0)
	2849 sipush (0, 0)
	2852 iastore (0, 0)
	2853 dup (0, 0)
	2854 sipush (0, 0)
	2857 sipush (0, 0)
	2860 iastore (0, 0)
	2861 dup (0, 0)
	2862 sipush (0, 0)
	2865 sipush (0, 0)
	2868 iastore (0, 0)
	2869 dup (0, 0)
	2870 sipush (0, 0)
	2873 sipush (0, 0)
	2876 iastore (0, 0)
	2877 dup (0, 0)
	2878 sipush (0, 0)
	2881 sipush (0, 0)
	2884 iastore (0, 0)
	2885 dup (0, 0)
	2886 sipush (0, 0)
	2889 sipush (0, 0)
	2892 iastore (0, 0)
	2893 dup (0, 0)
	2894 sipush (0, 0)
	2897 sipush (0, 0)
	2900 iastore (0, 0)
	2901 dup (0, 0)
	2902 sipush (0, 0)
	2905 sipush (0, 0)
	2908 iastore (0, 0)
	2909 dup (0, 0)
	2910 sipush (0, 0)
	2913 sipush (0, 0)
	2916 iastore (0, 0)
	2917 dup (0, 0)
	2918 sipush (0, 0)
	2921 sipush (0, 0)
	2924 iastore (0, 0)
	2925 dup (0, 0)
	2926 sipush (0, 0)
	2929 sipush (0, 0)
	2932 iastore (0, 0)
	2933 dup (0, 0)
	2934 sipush (0, 0)
	2937 sipush (0, 0)
	2940 iastore (0, 0)
	2941 dup (0, 0)
	2942 sipush (0, 0)
	2945 sipush (0, 0)
	2948 iastore (0, 0)
	2949 dup (0, 0)
	2950 sipush (0, 0)
	2953 sipush (0, 0)
	2956 iastore (0, 0)
	2957 dup (0, 0)
	2958 sipush (0, 0)
	2961 sipush (0, 0)
	2964 iastore (0, 0)
	2965 dup (0, 0)
	2966 sipush (0, 0)
	2969 sipush (0, 0)
	2972 iastore (0, 0)
	2973 dup (0, 0)
	2974 sipush (0, 0)
	2977 sipush (0, 0)
	2980 iastore (0, 0)
	2981 dup (0, 0)
	2982 sipush (0, 0)
	2985 sipush (0, 0)
	2988 iastore (0, 0)
	2989 dup (0, 0)
	2990 sipush (0, 0)
	2993 sipush (0, 0)
	2996 iastore (0, 0)
	2997 dup (0, 0)
	2998 sipush (0, 0)
	3001 sipush (0, 0)
	3004 iastore (0, 0)
	3005 dup (0, 0)
	3006 sipush (0, 0)
	3009 sipush (0, 0)
	3012 iastore (0, 0)
	3013 dup (0, 0)
	3014 sipush (0, 0)
	3017 sipush (0, 0)
	3020 iastore (0, 0)
	3021 dup (0, 0)
	3022 sipush (0, 0)
	3025 sipush (0, 0)
	3028 iastore (0, 0)
	3029 dup (0, 0)
	3030 sipush (0, 0)
	3033 sipush (0, 0)
	3036 iastore (0, 0)
	3037 dup (0, 0)
	3038 sipush (0, 0)
	3041 sipush (0, 0)
	3044 iastore (0, 0)
	3045 dup (0, 0)
	3046 sipush (0, 0)
	3049 sipush (0, 0)
	3052 iastore (0, 0)
	3053 dup (0, 0)
	3054 sipush (0, 0)
	3057 sipush (0, 0)
	3060 iastore (0, 0)
	3061 dup (0, 0)
	3062 sipush (0, 0)
	3065 sipush (0, 0)
	3068 iastore (0, 0)
	3069 dup (0, 0)
	3070 sipush (0, 0)
	3073 sipush (0, 0)
	3076 iastore (0, 0)
	3077 dup (0, 0)
	3078 sipush (0, 0)
	3081 sipush (0, 0)
	3084 iastore (0, 0)
	3085 dup (0, 0)
	3086 sipush (0, 0)
	3089 sipush (0, 0)
	3092 iastore (0, 0)
	3093 dup (0, 0)
	3094 sipush (0, 0)
	3097 sipush (0, 0)
	3100 iastore (0, 0)
	3101 dup (0, 0)
	3102 sipush (0, 0)
	3105 sipush (0, 0)
	3108 iastore (0, 0)
	3109 dup (0, 0)
	3110 sipush (0, 0)
	3113 sipush (0, 0)
	3116 iastore (0, 0)
	3117 dup (0, 0)
	3118 sipush (0, 0)
	3121 sipush (0, 0)
	3124 iastore (0, 0)
	3125 dup (0, 0)
	3126 sipush (0, 0)
	3129 sipush (0, 0)
	3132 iastore (0, 0)
	3133 dup (0, 0)
	3134 sipush (0, 0)
	3137 sipush (0, 0)
	3140 iastore (0, 0)
	3141 dup (0, 0)
	3142 sipush (0, 0)
	3145 sipush (0, 0)
	3148 iastore (0, 0)
	3149 dup (0, 0)
	3150 sipush (0, 0)
	3153 sipush (0, 0)
	3156 iastore (0, 0)
	3157 dup (0, 0)
	3158 sipush (0, 0)
	3161 sipush (0, 0)
	3164 iastore (0, 0)
	3165 dup (0, 0)
	3166 sipush (0, 0)
	3169 sipush (0, 0)
	3172 iastore (0, 0)
	3173 dup (0, 0)
	3174 sipush (0, 0)
	3177 sipush (0, 0)
	3180 iastore (0, 0)
	3181 dup (0, 0)
	3182 sipush (0, 0)
	3185 sipush (0, 0)
	3188 iastore (0, 0)
	3189 dup (0, 0)
	3190 sipush (0, 0)
	3193 sipush (0, 0)
	3196 iastore (0, 0)
	3197 dup (0, 0)
	3198 sipush (0, 0)
	3201 sipush (0, 0)
	3204 iastore (0, 0)
	3205 dup (0, 0)
	3206 sipush (0, 0)
	3209 sipush (0, 0)
	3212 iastore (0, 0)
	3213 dup (0, 0)
	3214 sipush (0, 0)
	3217 sipush (0, 0)
	3220 iastore (0, 0)
	3221 dup (0, 0)
	3222 sipush (0, 0)
	3225 sipush (0, 0)
	3228 iastore (0, 0)
	3229 dup (0, 0)
	3230 sipush (0, 0)
	3233 sipush (0, 0)
	3236 iastore (0, 0)
	3237 dup (0, 0)
	3238 sipush (0, 0)
	3241 sipush (0, 0)
	3244 iastore (0, 0)
	3245 dup (0, 0)
	3246 sipush (0, 0)
	3249 sipush (0, 0)
	3252 iastore (0, 0)
	3253 dup (0, 0)
	3254 sipush (0, 0)
	3257 sipush (0, 0)
	3260 iastore (0, 0)
	3261 dup (0, 0)
	3262 sipush (0, 0)
	3265 sipush (0, 0)
	3268 iastore (0, 0)
	3269 dup (0, 0)
	3270 sipush (0, 0)
	3273 sipush (0, 0)
	3276 iastore (0, 0)
	3277 dup (0, 0)
	3278 sipush (0, 0)
	3281 sipush (0, 0)
	3284 iastore (0, 0)
	3285 dup (0, 0)
	3286 sipush (0, 0)
	3289 sipush (0, 0)
	3292 iastore (0, 0)
	3293 dup (0, 0)
	3294 sipush (0, 0)
	3297 sipush (0, 0)
	3300 iastore (0, 0)
	3301 dup (0, 0)
	3302 sipush (0, 0)
	3305 sipush (0, 0)
	3308 iastore (0, 0)
	3309 dup (0, 0)
	3310 sipush (0, 0)
	3313 sipush (0, 0)
	3316 iastore (0, 0)
	3317 dup (0, 0)
	3318 sipush (0, 0)
	3321 sipush (0, 0)
	3324 iastore (0, 0)
	3325 dup (0, 0)
	3326 sipush (0, 0)
	3329 sipush (0, 0)
	3332 iastore (0, 0)
	3333 dup (0, 0)
	3334 sipush (0, 0)
	3337 sipush (0, 0)
	3340 iastore (0, 0)
	3341 dup (0, 0)
	3342 sipush (0, 0)
	3345 sipush (0, 0)
	3348 iastore (0, 0)
	3349 dup (0, 0)
	3350 sipush (0, 0)
	3353 sipush (0, 0)
	3356 iastore (0, 0)
	3357 dup (0, 0)
	3358 sipush (0, 0)
	3361 sipush (0, 0)
	3364 iastore (0, 0)
	3365 dup (0, 0)
	3366 sipush (0, 0)
	3369 sipush (0, 0)
	3372 iastore (0, 0)
	3373 dup (0, 0)
	3374 sipush (0, 0)
	3377 sipush (0, 0)
	3380 iastore (0, 0)
	3381 dup (0, 0)
	3382 sipush (0, 0)
	3385 sipush (0, 0)
	3388 iastore (0, 0)
	3389 dup (0, 0)
	3390 sipush (0, 0)
	3393 sipush (0, 0)
	3396 iastore (0, 0)
	3397 dup (0, 0)
	3398 sipush (0, 0)
	3401 sipush (0, 0)
	3404 iastore (0, 0)
	3405 dup (0, 0)
	3406 sipush (0, 0)
	3409 sipush (0, 0)
	3412 iastore (0, 0)
	3413 dup (0, 0)
	3414 sipush (0, 0)
	3417 sipush (0, 0)
	3420 iastore (0, 0)
	3421 dup (0, 0)
	3422 sipush (0, 0)
	3425 sipush (0, 0)
	3428 iastore (0, 0)
	3429 dup (0, 0)
	3430 sipush (0, 0)
	3433 sipush (0, 0)
	3436 iastore (0, 0)
	3437 dup (0, 0)
	3438 sipush (0, 0)
	3441 sipush (0, 0)
	3444 iastore (0, 0)
	3445 dup (0, 0)
	3446 sipush (0, 0)
	3449 sipush (0, 0)
	3452 iastore (0, 0)
	3453 dup (0, 0)
	3454 sipush (0, 0)
	3457 sipush (0, 0)
	3460 iastore (0, 0)
	3461 dup (0, 0)
	3462 sipush (0, 0)
	3465 sipush (0, 0)
	3468 iastore (0, 0)
	3469 dup (0, 0)
	3470 sipush (0, 0)
	3473 sipush (0, 0)
	3476 iastore (0, 0)
	3477 dup (0, 0)
	3478 sipush (0, 0)
	3481 sipush (0, 0)
	3484 iastore (0, 0)
	3485 dup (0, 0)
	3486 sipush (0, 0)
	3489 sipush (0, 0)
	3492 iastore (0, 0)
	3493 dup (0, 0)
	3494 sipush (0, 0)
	3497 sipush (0, 0)
	3500 iastore (0, 0)
	3501 dup (0, 0)
	3502 sipush (0, 0)
	3505 sipush (0, 0)
	3508 iastore (0, 0)
	3509 dup (0, 0)
	3510 sipush (0, 0)
	3513 sipush (0, 0)
	3516 iastore (0, 0)
	3517 dup (0, 0)
	3518 sipush (0, 0)
	3521 sipush (0, 0)
	3524 iastore (0, 0)
	3525 dup (0, 0)
	3526 sipush (0, 0)
	3529 sipush (0, 0)
	3532 iastore (0, 0)
	3533 dup (0, 0)
	3534 sipush (0, 0)
	3537 sipush (0, 0)
	3540 iastore (0, 0)
	3541 dup (0, 0)
	3542 sipush (0, 0)
	3545 sipush (0, 0)
	3548 iastore (0, 0)
	3549 dup (0, 0)
	3550 sipush (0, 0)
	3553 sipush (0, 0)
	3556 iastore (0, 0)
	3557 dup (0, 0)
	3558 sipush (0, 0)
	3561 sipush (0, 0)
	3564 iastore (0, 0)
	3565 dup (0, 0)
	3566 sipush (0, 0)
	3569 sipush (0, 0)
	3572 iastore (0, 0)
	3573 dup (0, 0)
	3574 sipush (0, 0)
	3577 sipush (0, 0)
	3580 iastore (0, 0)
	3581 dup (0, 0)
	3582 sipush (0, 0)
	3585 sipush (0, 0)
	3588 iastore (0, 0)
	3589 dup (0, 0)
	3590 sipush (0, 0)
	3593 sipush (0, 0)
	3596 iastore (0, 0)
	3597 dup (0, 0)
	3598 sipush (0, 0)
	3601 sipush (0, 0)
	3604 iastore (0, 0)
	3605 dup (0, 0)
	3606 sipush (0, 0)
	3609 sipush (0, 0)
	3612 iastore (0, 0)
	3613 dup (0, 0)
	3614 sipush (0, 0)
	3617 sipush (0, 0)
	3620 iastore (0, 0)
	3621 dup (0, 0)
	3622 sipush (0, 0)
	3625 sipush (0, 0)
	3628 iastore (0, 0)
	3629 dup (0, 0)
	3630 sipush (0, 0)
	3633 sipush (0, 0)
	3636 iastore (0, 0)
	3637 dup (0, 0)
	3638 sipush (0, 0)
	3641 sipush (0, 0)
	3644 iastore (0, 0)
	3645 dup (0, 0)
	3646 sipush (0, 0)
	3649 sipush (0, 0)
	3652 iastore (0, 0)
	3653 dup (0, 0)
	3654 sipush (0, 0)
	3657 sipush (0, 0)
	3660 iastore (0, 0)
	3661 dup (0, 0)
	3662 sipush (0, 0)
	3665 sipush (0, 0)
	3668 iastore (0, 0)
	3669 dup (0, 0)
	3670 sipush (0, 0)
	3673 sipush (0, 0)
	3676 iastore (0, 0)
	3677 dup (0, 0)
	3678 sipush (0, 0)
	3681 sipush (0, 0)
	3684 iastore (0, 0)
	3685 dup (0, 0)
	3686 sipush (0, 0)
	3689 sipush (0, 0)
	3692 iastore (0, 0)
	3693 dup (0, 0)
	3694 sipush (0, 0)
	3697 sipush (0, 0)
	3700 iastore (0, 0)
	3701 dup (0, 0)
	3702 sipush (0, 0)
	3705 sipush (0, 0)
	3708 iastore (0, 0)
	3709 dup (0, 0)
	3710 sipush (0, 0)
	3713 sipush (0, 0)
	3716 iastore (0, 0)
	3717 dup (0, 0)
	3718 sipush (0, 0)
	3721 sipush (0, 0)
	3724 iastore (0, 0)
	3725 dup (0, 0)
	3726 sipush (0, 0)
	3729 sipush (0, 0)
	3732 iastore (0, 0)
	3733 dup (0, 0)
	3734 sipush (0, 0)
	3737 sipush (0, 0)
	3740 iastore (0, 0)
	3741 dup (0, 0)
	3742 sipush (0, 0)
	3745 sipush (0, 0)
	3748 iastore (0, 0)
	3749 dup (0, 0)
	3750 sipush (0, 0)
	3753 sipush (0, 0)
	3756 iastore (0, 0)
	3757 dup (0, 0)
	3758 sipush (0, 0)
	3761 sipush (0, 0)
	3764 iastore (0, 0)
	3765 dup (0, 0)
	3766 sipush (0, 0)
	3769 sipush (0, 0)
	3772 iastore (0, 0)
	3773 dup (0, 0)
	3774 sipush (0, 0)
	3777 sipush (0, 0)
	3780 iastore (0, 0)
	3781 dup (0, 0)
	3782 sipush (0, 0)
	3785 sipush (0, 0)
	3788 iastore (0, 0)
	3789 dup (0, 0)
	3790 sipush (0, 0)
	3793 sipush (0, 0)
	3796 iastore (0, 0)
	3797 dup (0, 0)
	3798 sipush (0, 0)
	3801 sipush (0, 0)
	3804 iastore (0, 0)
	3805 dup (0, 0)
	3806 sipush (0, 0)
	3809 sipush (0, 0)
	3812 iastore (0, 0)
	3813 dup (0, 0)
	3814 sipush (0, 0)
	3817 sipush (0, 0)
	3820 iastore (0, 0)
	3821 dup (0, 0)
	3822 sipush (0, 0)
	3825 sipush (0, 0)
	3828 iastore (0, 0)
	3829 dup (0, 0)
	3830 sipush (0, 0)
	3833 sipush (0, 0)
	3836 iastore (0, 0)
	3837 dup (0, 0)
	3838 sipush (0, 0)
	3841 sipush (0, 0)
	3844 iastore (0, 0)
	3845 dup (0, 0)
	3846 sipush (0, 0)
	3849 sipush (0, 0)
	3852 iastore (0, 0)
	3853 dup (0, 0)
	3854 sipush (0, 0)
	3857 sipush (0, 0)
	3860 iastore (0, 0)
	3861 dup (0, 0)
	3862 sipush (0, 0)
	3865 sipush (0, 0)
	3868 iastore (0, 0)
	3869 dup (0, 0)
	3870 sipush (0, 0)
	3873 sipush (0, 0)
	3876 iastore (0, 0)
	3877 dup (0, 0)
	3878 sipush (0, 0)
	3881 sipush (0, 0)
	3884 iastore (0, 0)
	3885 dup (0, 0)
	3886 sipush (0, 0)
	3889 sipush (0, 0)
	3892 iastore (0, 0)
	3893 dup (0, 0)
	3894 sipush (0, 0)
	3897 sipush (0, 0)
	3900 iastore (0, 0)
	3901 dup (0, 0)
	3902 sipush (0, 0)
	3905 sipush (0, 0)
	3908 iastore (0, 0)
	3909 dup (0, 0)
	3910 sipush (0, 0)
	3913 sipush (0, 0)
	3916 iastore (0, 0)
	3917 dup (0, 0)
	3918 sipush (0, 0)
	3921 sipush (0, 0)
	3924 iastore (0, 0)
	3925 dup (0, 0)
	3926 sipush (0, 0)
	3929 sipush (0, 0)
	3932 iastore (0, 0)
	3933 putstatic (0, 0)
	3936 getstatic (0, 0)
	3939 getstatic (0, 0)
	3942 arraylength (0, 0)
	3943 iconst_1 (0, 0)
	3944 isub (0, 0)
	3945 iaload (0, 0)
	3946 putstatic (0, 0)
	3949 return (0, 0)

