Method: <init>
	0 aload_0 (0, 0)
	1 invokespecial (0, 0)
	4 aload_0 (0, 0)
	5 aload_1 (0, 0)
	6 putfield (0, 0)
	9 aload_0 (0, 0)
	10 dload_2 (0, 0)
	11 putfield (0, 0)
	14 aload_0 (0, 0)
	15 aload (0, 0)
	17 invokevirtual (0, 0)
	20 checkcast (0, 0)
	23 putfield (0, 0)
	26 return (0, 0)

Method: getCenter
	0 aload_0 (0, 0)
	1 getfield (0, 0)
	4 areturn (0, 0)

Method: getRadius
	0 aload_0 (0, 0)
	1 getfield (0, 0)
	4 dreturn (0, 0)

Method: getSupport
	0 aload_0 (0, 0)
	1 getfield (0, 0)
	4 invokevirtual (0, 0)
	7 checkcast (0, 0)
	10 areturn (0, 0)

Method: getSupportSize
	0 aload_0 (0, 0)
	1 getfield (0, 0)
	4 arraylength (0, 0)
	5 ireturn (0, 0)

Method: contains
	0 aload_1 (0, 0)
	1 aload_0 (0, 0)
	2 getfield (0, 0)
	5 invokeinterface (0, 0)
	10 aload_0 (0, 0)
	11 getfield (0, 0)
	14 dload_2 (0, 0)
	15 dadd (0, 0)
	16 dcmpg (0, 0)
	17 ifgt (0, 0)
	20 iconst_1 (0, 0)
	21 goto (0, 0)
	24 iconst_0 (0, 0)
	25 ireturn (0, 0)

