Method: <init>
	0 aload_0 (0, 0)
	1 invokespecial (0, 0)
	2 java/lang/Object.<init>:()V (0, 0)
	4 aload_0 (0, 0)
	5 dload_1 (0, 0)
	6 putfield (0, 0)
	7 org/apache/commons/math3/geometry/enclosing/WelzlEncloser.tolerance:D (0, 0)
	9 aload_0 (0, 0)
	10 aload_3 (0, 0)
	11 putfield (0, 0)
	12 org/apache/commons/math3/geometry/enclosing/WelzlEncloser.generator:Lorg/apache/commons/math3/geometry/enclosing/SupportBallGenerator; (0, 0)
	14 return (0, 0)

Method: enclose
	0 aload_1 (1, 1)
	1 ifnull (1, 1)
	2 17 (1, 1)
	4 aload_1 (1, 1)
	5 invokeinterface (1, 1)
	6 java/lang/Iterable.java/util/Iterator (1, 1)
	8 0 (1, 1)
	10 invokeinterface (1, 1)
	11 java/util/Iterator.java/util/ArrayList (1, 1)
	13 0 (1, 1)
	15 ifne (1, 1)
	16 20 (1, 1)
	18 aload_0 (1, 1)
	19 getfield (1, 1)
	20 org/apache/commons/math3/geometry/enclosing/WelzlEncloser.generator:Lorg/apache/commons/math3/geometry/enclosing/SupportBallGenerator; (1, 1)
	22 new (1, 1)
	23 java/util/ArrayList (1, 1)
	25 dup (1, 1)
	26 invokespecial (1, 1)
	27 java/util/ArrayList.<init>:()V (1, 1)
	29 invokeinterface (1, 1)
	30 org/apache/commons/math3/geometry/enclosing/SupportBallGenerator.pivotingBall:(Ljava/lang/Iterable;)Lorg/apache/commons/math3/geometry/enclosing/EnclosingBall; (1, 1)
	32 0 (1, 1)
	34 areturn (1, 1)
	35 aload_0 (0, 0)
	36 aload_1 (0, 0)
	37 invokespecial (0, 0)
	38 org/apache/commons/math3/geometry/enclosing/WelzlEncloser.pivotingBall:(Ljava/lang/Iterable;)Lorg/apache/commons/math3/geometry/enclosing/EnclosingBall; (0, 0)
	40 areturn (0, 0)

Method: pivotingBall
	0 aload_1 (0, 0)
	1 invokeinterface (0, 0)
	2 java/lang/Iterable.java/util/Iterator (0, 0)
	4 0 (0, 0)
	6 invokeinterface (0, 0)
	7 java/util/Iterator.org/apache/commons/math3/geometry/Point (0, 0)
	9 0 (0, 0)
	11 checkcast (0, 0)
	12 org/apache/commons/math3/geometry/Point (0, 0)
	14 astore_2 (0, 0)
	15 new (0, 0)
	16 java/util/ArrayList (0, 0)
	18 dup (0, 0)
	19 aload_2 (0, 0)
	20 invokeinterface (0, 0)
	21 org/apache/commons/math3/geometry/Point.org/apache/commons/math3/geometry/Space (0, 0)
	23 0 (0, 0)
	25 invokeinterface (0, 0)
	26 org/apache/commons/math3/geometry/Space.<init>:(I)V (0, 0)
	28 0 (0, 0)
	30 iconst_1 (0, 0)
	31 iadd (0, 0)
	32 invokespecial (0, 0)
	33 java/util/ArrayList.<init>:(I)V (0, 0)
	35 astore_3 (0, 0)
	36 new (0, 0)
	37 java/util/ArrayList (0, 0)
	39 dup (0, 0)
	40 aload_2 (0, 0)
	41 invokeinterface (0, 0)
	42 org/apache/commons/math3/geometry/Point.org/apache/commons/math3/geometry/Space (0, 0)
	44 0 (0, 0)
	46 invokeinterface (0, 0)
	47 org/apache/commons/math3/geometry/Space.<init>:(I)V (0, 0)
	49 0 (0, 0)
	51 iconst_1 (0, 0)
	52 iadd (0, 0)
	53 invokespecial (0, 0)
	54 java/util/ArrayList.<init>:(I)V (0, 0)
	56 astore (0, 0)
	57 #4 (0, 0)
	58 aload_3 (0, 0)
	59 aload_2 (0, 0)
	60 invokeinterface (0, 0)
	61 java/util/List.size:()I (0, 0)
	63 0 (0, 0)
	65 pop (0, 0)
	66 aload_0 (0, 0)
	67 aload_3 (0, 0)
	68 aload_3 (0, 0)
	69 invokeinterface (0, 0)
	70 java/util/List.moveToFrontBall:(Ljava/util/List;ILjava/util/List;)Lorg/apache/commons/math3/geometry/enclosing/EnclosingBall; (0, 0)
	72 0 (0, 0)
	74 aload (0, 0)
	75 #4 (0, 0)
	76 invokespecial (0, 0)
	77 org/apache/commons/math3/geometry/enclosing/WelzlEncloser.moveToFrontBall:(Ljava/util/List;ILjava/util/List;)Lorg/apache/commons/math3/geometry/enclosing/EnclosingBall; (0, 0)
	79 astore (0, 0)
	80 #5 (0, 0)
	81 aload_0 (1, 3)
	82 aload_1 (1, 3)
	83 aload (1, 3)
	84 #5 (1, 3)
	85 invokevirtual (1, 3)
	86 org/apache/commons/math3/geometry/enclosing/WelzlEncloser.selectFarthest:(Ljava/lang/Iterable;Lorg/apache/commons/math3/geometry/enclosing/EnclosingBall;)Lorg/apache/commons/math3/geometry/Point; (1, 3)
	88 astore (1, 3)
	89 #6 (1, 3)
	90 aload (2, 1)
	91 #5 (2, 1)
	92 aload (2, 1)
	93 #6 (2, 1)
	94 aload_0 (2, 1)
	95 getfield (2, 1)
	96 org/apache/commons/math3/geometry/enclosing/WelzlEncloser.tolerance:D (2, 1)
	98 invokevirtual (2, 1)
	99 org/apache/commons/math3/geometry/enclosing/EnclosingBall.contains:(Lorg/apache/commons/math3/geometry/Point;D)Z (2, 1)
	101 ifeq (2, 1)
	102 6 (2, 1)
	104 aload (2, 1)
	105 #5 (2, 1)
	106 areturn (2, 1)
	107 aload (1, 3)
	108 #4 (1, 3)
	109 invokeinterface (1, 3)
	110 java/util/List.getRadius:()D (1, 3)
	112 0 (1, 3)
	114 aload (1, 3)
	115 #4 (1, 3)
	116 aload (1, 3)
	117 #6 (1, 3)
	118 invokeinterface (1, 3)
	119 java/util/List.size:()I (1, 3)
	121 0 (1, 3)
	123 pop (1, 3)
	124 aload (1, 3)
	125 #5 (1, 3)
	126 astore (1, 3)
	127 #7 (1, 3)
	128 aload_0 (1, 3)
	129 aload_3 (1, 3)
	130 aload_3 (1, 3)
	131 invokeinterface (1, 3)
	132 java/util/List.moveToFrontBall:(Ljava/util/List;ILjava/util/List;)Lorg/apache/commons/math3/geometry/enclosing/EnclosingBall; (1, 3)
	134 0 (1, 3)
	136 aload (1, 3)
	137 #4 (1, 3)
	138 invokespecial (1, 3)
	139 org/apache/commons/math3/geometry/enclosing/WelzlEncloser.moveToFrontBall:(Ljava/util/List;ILjava/util/List;)Lorg/apache/commons/math3/geometry/enclosing/EnclosingBall; (1, 3)
	141 astore (1, 3)
	142 #5 (1, 3)
	143 aload (2, 1)
	144 #5 (2, 1)
	145 invokevirtual (2, 1)
	146 org/apache/commons/math3/geometry/enclosing/EnclosingBall.getRadius:()D (2, 1)
	148 aload (2, 1)
	149 #7 (2, 1)
	150 invokevirtual (2, 1)
	151 org/apache/commons/math3/geometry/enclosing/EnclosingBall.getRadius:()D (2, 1)
	153 dcmpg (2, 1)
	154 ifge (2, 1)
	155 11 (2, 1)
	157 new (2, 1)
	158 org/apache/commons/math3/exception/MathInternalError (2, 1)
	160 dup (2, 1)
	161 invokespecial (2, 1)
	162 org/apache/commons/math3/exception/MathInternalError.<init>:()V (2, 1)
	164 athrow (2, 1)
	165 aload_3 (1, 3)
	166 iconst_0 (1, 3)
	167 aload (1, 3)
	168 #6 (1, 3)
	169 invokeinterface (1, 3)
	170 java/util/List.getSupportSize:()I (1, 3)
	172 0 (1, 3)
	174 aload_3 (1, 3)
	175 aload (1, 3)
	176 #5 (1, 3)
	177 invokevirtual (1, 3)
	178 org/apache/commons/math3/geometry/enclosing/EnclosingBall.getSupportSize:()I (1, 3)
	180 aload_3 (1, 3)
	181 invokeinterface (1, 3)
	182 java/util/List.moveToFrontBall:(Ljava/util/List;ILjava/util/List;)Lorg/apache/commons/math3/geometry/enclosing/EnclosingBall; (1, 3)
	184 0 (1, 3)
	186 invokeinterface (1, 3)
	187 java/util/List.getCenter:()Lorg/apache/commons/math3/geometry/Point; (1, 3)
	189 0 (1, 3)
	191 invokeinterface (1, 3)
	192 java/util/List.getRadius:()D (1, 3)
	194 0 (1, 3)
	196 goto (0, 0)
	197 -115 (0, 0)

Method: moveToFrontBall
	0 aload_0 (0, 0)
	1 getfield (0, 0)
	2 org/apache/commons/math3/geometry/enclosing/WelzlEncloser.generator:Lorg/apache/commons/math3/geometry/enclosing/SupportBallGenerator; (0, 0)
	4 aload_3 (0, 0)
	5 invokeinterface (0, 0)
	6 org/apache/commons/math3/geometry/enclosing/SupportBallGenerator.pivotingBall:(Ljava/lang/Iterable;)Lorg/apache/commons/math3/geometry/enclosing/EnclosingBall; (0, 0)
	8 0 (0, 0)
	10 astore (0, 0)
	11 #4 (0, 0)
	12 aload (1, 1)
	13 #4 (1, 1)
	14 invokevirtual (1, 1)
	15 org/apache/commons/math3/geometry/enclosing/EnclosingBall.getSupportSize:()I (1, 1)
	17 aload (1, 1)
	18 #4 (1, 1)
	19 invokevirtual (1, 1)
	20 org/apache/commons/math3/geometry/enclosing/EnclosingBall.getCenter:()Lorg/apache/commons/math3/geometry/Point; (1, 1)
	22 invokeinterface (1, 1)
	23 org/apache/commons/math3/geometry/Point.org/apache/commons/math3/geometry/Space (1, 1)
	25 0 (1, 1)
	27 invokeinterface (1, 1)
	28 org/apache/commons/math3/geometry/Space.<init>:(I)V (1, 1)
	30 0 (1, 1)
	32 if_icmpgt (1, 1)
	33 123 (1, 1)
	35 iconst_0 (2, 4)
	36 istore (2, 4)
	37 #5 (2, 4)
	38 iload (2, 4)
	39 #5 (2, 4)
	40 iload_2 (2, 4)
	41 if_icmpge (2, 4)
	42 114 (2, 4)
	44 aload_1 (2, 4)
	45 iload (2, 4)
	46 #5 (2, 4)
	47 invokeinterface (2, 4)
	48 java/util/List.remove:(I)Ljava/lang/Object; (2, 4)
	50 0 (2, 4)
	52 checkcast (2, 4)
	53 org/apache/commons/math3/geometry/Point (2, 4)
	55 astore (2, 4)
	56 #6 (2, 4)
	57 aload (3, 1)
	58 #4 (3, 1)
	59 aload (3, 1)
	60 #6 (3, 1)
	61 aload_0 (3, 1)
	62 getfield (3, 1)
	63 org/apache/commons/math3/geometry/enclosing/WelzlEncloser.tolerance:D (3, 1)
	65 invokevirtual (3, 1)
	66 org/apache/commons/math3/geometry/enclosing/EnclosingBall.contains:(Lorg/apache/commons/math3/geometry/Point;D)Z (3, 1)
	68 ifne (3, 1)
	69 81 (3, 1)
	71 aload_3 (3, 1)
	72 aload (3, 1)
	73 #6 (3, 1)
	74 invokeinterface (3, 1)
	75 java/util/List.size:()I (3, 1)
	77 0 (3, 1)
	79 pop (3, 1)
	80 aload_0 (3, 1)
	81 aload_1 (3, 1)
	82 iload (3, 1)
	83 #5 (3, 1)
	84 aload_3 (3, 1)
	85 invokespecial (3, 1)
	86 org/apache/commons/math3/geometry/enclosing/WelzlEncloser.moveToFrontBall:(Ljava/util/List;ILjava/util/List;)Lorg/apache/commons/math3/geometry/enclosing/EnclosingBall; (3, 1)
	88 astore (3, 1)
	89 #4 (3, 1)
	90 aload_3 (3, 1)
	91 aload_3 (3, 1)
	92 invokeinterface (3, 1)
	93 java/util/List.moveToFrontBall:(Ljava/util/List;ILjava/util/List;)Lorg/apache/commons/math3/geometry/enclosing/EnclosingBall; (3, 1)
	95 0 (3, 1)
	97 iconst_1 (3, 1)
	98 isub (3, 1)
	99 invokeinterface (3, 1)
	100 java/util/List.set:(ILjava/lang/Object;)Ljava/lang/Object; (3, 1)
	102 0 (3, 1)
	104 pop (3, 1)
	105 iload (4, 4)
	106 #5 (4, 4)
	107 istore (4, 4)
	108 #7 (4, 4)
	109 iload (4, 4)
	110 #7 (4, 4)
	111 ifle (4, 4)
	112 28 (4, 4)
	114 aload_1 (4, 4)
	115 iload (4, 4)
	116 #7 (4, 4)
	117 aload_1 (4, 4)
	118 iload (4, 4)
	119 #7 (4, 4)
	120 iconst_1 (4, 4)
	121 isub (4, 4)
	122 invokeinterface (4, 4)
	123 java/util/List.remove:(I)Ljava/lang/Object; (4, 4)
	125 0 (4, 4)
	127 invokeinterface (4, 4)
	128 java/util/List.distance:(Lorg/apache/commons/math3/geometry/Point;)D (4, 4)
	130 0 (4, 4)
	132 pop (4, 4)
	133 iinc (4, 4)
	134 #7 (4, 4)
	135 -89 (4, 4)
	136 goto (4, 4)
	137 -27 (4, 4)
	139 aload_1 (3, 1)
	140 iconst_0 (3, 1)
	141 aload (3, 1)
	142 #6 (3, 1)
	143 invokeinterface (3, 1)
	144 java/util/List.distance:(Lorg/apache/commons/math3/geometry/Point;)D (3, 1)
	146 0 (3, 1)
	148 pop (3, 1)
	149 iinc (3, 1)
	150 #5 (3, 1)
	151 -89 (3, 1)
	152 goto (3, 1)
	153 -114 (3, 1)
	155 aload (1, 1)
	156 #4 (1, 1)
	157 areturn (1, 1)

Method: selectFarthest
	0 aload_2 (0, 0)
	1 invokevirtual (0, 0)
	2 org/apache/commons/math3/geometry/enclosing/EnclosingBall.getCenter:()Lorg/apache/commons/math3/geometry/Point; (0, 0)
	4 astore_3 (0, 0)
	5 aconst_null (0, 0)
	6 astore (0, 0)
	7 #4 (0, 0)
	8 ldc2_w (0, 0)
	9 -1.0 (0, 0)
	11 dstore (0, 0)
	12 #5 (0, 0)
	13 aload_1 (1, 4)
	14 invokeinterface (1, 4)
	15 java/lang/Iterable.java/util/Iterator (1, 4)
	17 0 (1, 4)
	19 astore (1, 4)
	20 #7 (1, 4)
	21 aload (1, 4)
	22 #7 (1, 4)
	23 invokeinterface (1, 4)
	24 java/util/Iterator.java/util/ArrayList (1, 4)
	26 0 (1, 4)
	28 ifeq (1, 4)
	29 44 (1, 4)
	31 aload (1, 4)
	32 #7 (1, 4)
	33 invokeinterface (1, 4)
	34 java/util/Iterator.org/apache/commons/math3/geometry/Point (1, 4)
	36 0 (1, 4)
	38 checkcast (1, 4)
	39 org/apache/commons/math3/geometry/Point (1, 4)
	41 astore (1, 4)
	42 #8 (1, 4)
	43 aload (1, 4)
	44 #8 (1, 4)
	45 aload_3 (1, 4)
	46 invokeinterface (1, 4)
	47 org/apache/commons/math3/geometry/Point.org/apache/commons/math3/geometry/enclosing/WelzlEncloser (1, 4)
	49 0 (1, 4)
	51 dstore (1, 4)
	52 #9 (1, 4)
	53 dload (2, 1)
	54 #9 (2, 1)
	55 dload (2, 1)
	56 #5 (2, 1)
	57 dcmpl (2, 1)
	58 ifle (2, 1)
	59 11 (2, 1)
	61 aload (2, 1)
	62 #8 (2, 1)
	63 astore (2, 1)
	64 #4 (2, 1)
	65 dload (2, 1)
	66 #9 (2, 1)
	67 dstore (2, 1)
	68 #5 (2, 1)
	69 goto (0, 0)
	70 -48 (0, 0)
	72 aload (0, 0)
	73 #4 (0, 0)
	74 areturn (0, 0)

