Method: <init>
	0 aload_0 (0, 0)
	1 invokespecial (0, 0)
	2 java/lang/Object.<init>:()V (0, 0)
	4 aload_0 (0, 0)
	5 iload_1 (0, 0)
	6 putfield (0, 0)
	7 org/apache/commons/math3/analysis/polynomials/PolynomialsUtils$JacobiKey.v:I (0, 0)
	9 aload_0 (0, 0)
	10 iload_2 (0, 0)
	11 putfield (0, 0)
	12 org/apache/commons/math3/analysis/polynomials/PolynomialsUtils$JacobiKey.w:I (0, 0)
	14 return (0, 0)

Method: hashCode
	0 aload_0 (0, 0)
	1 getfield (0, 0)
	2 org/apache/commons/math3/analysis/polynomials/PolynomialsUtils$JacobiKey.v:I (0, 0)
	4 bipush (0, 0)
	5 16 (0, 0)
	6 ishl (0, 0)
	7 aload_0 (0, 0)
	8 getfield (0, 0)
	9 org/apache/commons/math3/analysis/polynomials/PolynomialsUtils$JacobiKey.w:I (0, 0)
	11 ixor (0, 0)
	12 ireturn (0, 0)

Method: equals
	0 aload_1 (1, 1)
	1 ifnull (1, 1)
	2 10 (1, 1)
	4 aload_1 (1, 1)
	5 instanceof (1, 1)
	6 org/apache/commons/math3/analysis/polynomials/PolynomialsUtils$JacobiKey (1, 1)
	8 ifne (1, 1)
	9 5 (1, 1)
	11 iconst_0 (1, 1)
	12 ireturn (1, 1)
	13 aload_1 (0, 0)
	14 checkcast (0, 0)
	15 org/apache/commons/math3/analysis/polynomials/PolynomialsUtils$JacobiKey (0, 0)
	17 astore_2 (0, 0)
	18 aload_0 (0, 0)
	19 getfield (0, 0)
	20 org/apache/commons/math3/analysis/polynomials/PolynomialsUtils$JacobiKey.v:I (0, 0)
	22 aload_2 (0, 0)
	23 getfield (0, 0)
	24 org/apache/commons/math3/analysis/polynomials/PolynomialsUtils$JacobiKey.v:I (0, 0)
	26 if_icmpne (0, 0)
	27 18 (0, 0)
	29 aload_0 (0, 0)
	30 getfield (0, 0)
	31 org/apache/commons/math3/analysis/polynomials/PolynomialsUtils$JacobiKey.w:I (0, 0)
	33 aload_2 (0, 0)
	34 getfield (0, 0)
	35 org/apache/commons/math3/analysis/polynomials/PolynomialsUtils$JacobiKey.w:I (0, 0)
	37 if_icmpne (0, 0)
	38 7 (0, 0)
	40 iconst_1 (0, 0)
	41 goto (0, 0)
	42 4 (0, 0)
	44 iconst_0 (0, 0)
	45 ireturn (0, 0)

