Method: generate
	0 iconst_3 (0, 0)
	1 anewarray (0, 0)
	2 org/apache/commons/math3/fraction/BigFraction (0, 0)
	4 dup (0, 0)
	5 iconst_0 (0, 0)
	6 getstatic (0, 0)
	7 org/apache/commons/math3/fraction/BigFraction.ZERO:Lorg/apache/commons/math3/fraction/BigFraction; (0, 0)
	9 aastore (0, 0)
	10 dup (0, 0)
	11 iconst_1 (0, 0)
	12 getstatic (0, 0)
	13 org/apache/commons/math3/fraction/BigFraction.TWO:Lorg/apache/commons/math3/fraction/BigFraction; (0, 0)
	15 aastore (0, 0)
	16 dup (0, 0)
	17 iconst_2 (0, 0)
	18 new (0, 0)
	19 org/apache/commons/math3/fraction/BigFraction (0, 0)
	21 dup (0, 0)
	22 iconst_2 (0, 0)
	23 iload_1 (0, 0)
	24 imul (0, 0)
	25 invokespecial (0, 0)
	26 org/apache/commons/math3/fraction/BigFraction.<init>:(I)V (0, 0)
	28 aastore (0, 0)
	29 areturn (0, 0)

