Method: <init>
	0 aload_0 (0, 0)
	1 invokespecial (0, 0)
	2 java/lang/Object.<init>:()V (0, 0)
	4 return (0, 0)

Method: createChebyshevPolynomial
	0 iload_0 (0, 0)
	1 getstatic (0, 0)
	2 org/apache/commons/math3/analysis/polynomials/PolynomialsUtils.CHEBYSHEV_COEFFICIENTS:Ljava/util/List; (0, 0)
	4 new (0, 0)
	5 org/apache/commons/math3/analysis/polynomials/PolynomialsUtils$1 (0, 0)
	7 dup (0, 0)
	8 invokespecial (0, 0)
	9 org/apache/commons/math3/analysis/polynomials/PolynomialsUtils$1.<init>:()V (0, 0)
	11 invokestatic (0, 0)
	12 org/apache/commons/math3/analysis/polynomials/PolynomialsUtils.buildPolynomial:(ILjava/util/List;Lorg/apache/commons/math3/analysis/polynomials/PolynomialsUtils$RecurrenceCoefficientsGenerator;)Lorg/apache/commons/math3/analysis/polynomials/PolynomialFunction; (0, 0)
	14 areturn (0, 0)

Method: createHermitePolynomial
	0 iload_0 (0, 0)
	1 getstatic (0, 0)
	2 org/apache/commons/math3/analysis/polynomials/PolynomialsUtils.HERMITE_COEFFICIENTS:Ljava/util/List; (0, 0)
	4 new (0, 0)
	5 org/apache/commons/math3/analysis/polynomials/PolynomialsUtils$2 (0, 0)
	7 dup (0, 0)
	8 invokespecial (0, 0)
	9 org/apache/commons/math3/analysis/polynomials/PolynomialsUtils$2.<init>:()V (0, 0)
	11 invokestatic (0, 0)
	12 org/apache/commons/math3/analysis/polynomials/PolynomialsUtils.buildPolynomial:(ILjava/util/List;Lorg/apache/commons/math3/analysis/polynomials/PolynomialsUtils$RecurrenceCoefficientsGenerator;)Lorg/apache/commons/math3/analysis/polynomials/PolynomialFunction; (0, 0)
	14 areturn (0, 0)

Method: createLaguerrePolynomial
	0 iload_0 (0, 0)
	1 getstatic (0, 0)
	2 org/apache/commons/math3/analysis/polynomials/PolynomialsUtils.LAGUERRE_COEFFICIENTS:Ljava/util/List; (0, 0)
	4 new (0, 0)
	5 org/apache/commons/math3/analysis/polynomials/PolynomialsUtils$3 (0, 0)
	7 dup (0, 0)
	8 invokespecial (0, 0)
	9 org/apache/commons/math3/analysis/polynomials/PolynomialsUtils$3.<init>:()V (0, 0)
	11 invokestatic (0, 0)
	12 org/apache/commons/math3/analysis/polynomials/PolynomialsUtils.buildPolynomial:(ILjava/util/List;Lorg/apache/commons/math3/analysis/polynomials/PolynomialsUtils$RecurrenceCoefficientsGenerator;)Lorg/apache/commons/math3/analysis/polynomials/PolynomialFunction; (0, 0)
	14 areturn (0, 0)

Method: createLegendrePolynomial
	0 iload_0 (0, 0)
	1 getstatic (0, 0)
	2 org/apache/commons/math3/analysis/polynomials/PolynomialsUtils.LEGENDRE_COEFFICIENTS:Ljava/util/List; (0, 0)
	4 new (0, 0)
	5 org/apache/commons/math3/analysis/polynomials/PolynomialsUtils$4 (0, 0)
	7 dup (0, 0)
	8 invokespecial (0, 0)
	9 org/apache/commons/math3/analysis/polynomials/PolynomialsUtils$4.<init>:()V (0, 0)
	11 invokestatic (0, 0)
	12 org/apache/commons/math3/analysis/polynomials/PolynomialsUtils.buildPolynomial:(ILjava/util/List;Lorg/apache/commons/math3/analysis/polynomials/PolynomialsUtils$RecurrenceCoefficientsGenerator;)Lorg/apache/commons/math3/analysis/polynomials/PolynomialFunction; (0, 0)
	14 areturn (0, 0)

Method: createJacobiPolynomial
	0 new (0, 0)
	1 org/apache/commons/math3/analysis/polynomials/PolynomialsUtils$JacobiKey (0, 0)
	3 dup (0, 0)
	4 iload_1 (0, 0)
	5 iload_2 (0, 0)
	6 invokespecial (0, 0)
	7 org/apache/commons/math3/analysis/polynomials/PolynomialsUtils$JacobiKey.<init>:(II)V (0, 0)
	9 astore_3 (0, 0)
	10 getstatic (1, 1)
	11 org/apache/commons/math3/analysis/polynomials/PolynomialsUtils.JACOBI_COEFFICIENTS:Ljava/util/Map; (1, 1)
	13 aload_3 (1, 1)
	14 invokeinterface (1, 1)
	15 java/util/Map.java/util/ArrayList (1, 1)
	17 0 (1, 1)
	19 ifne (1, 1)
	20 75 (1, 1)
	22 new (2, 4)
	23 java/util/ArrayList (2, 4)
	25 dup (2, 4)
	26 invokespecial (2, 4)
	27 java/util/ArrayList.<init>:()V (2, 4)
	29 astore (2, 4)
	30 #4 (2, 4)
	31 getstatic (2, 4)
	32 org/apache/commons/math3/analysis/polynomials/PolynomialsUtils.JACOBI_COEFFICIENTS:Ljava/util/Map; (2, 4)
	34 aload_3 (2, 4)
	35 aload (2, 4)
	36 #4 (2, 4)
	37 invokeinterface (2, 4)
	38 java/util/Map.ONE:Lorg/apache/commons/math3/fraction/BigFraction; (2, 4)
	40 0 (2, 4)
	42 pop (2, 4)
	43 aload (2, 4)
	44 #4 (2, 4)
	45 getstatic (2, 4)
	46 org/apache/commons/math3/fraction/BigFraction.ONE:Lorg/apache/commons/math3/fraction/BigFraction; (2, 4)
	48 invokeinterface (2, 4)
	49 java/util/List.org/apache/commons/math3/fraction/BigFraction (2, 4)
	51 0 (2, 4)
	53 pop (2, 4)
	54 aload (2, 4)
	55 #4 (2, 4)
	56 new (2, 4)
	57 org/apache/commons/math3/fraction/BigFraction (2, 4)
	59 dup (2, 4)
	60 iload_1 (2, 4)
	61 iload_2 (2, 4)
	62 isub (2, 4)
	63 iconst_2 (2, 4)
	64 invokespecial (2, 4)
	65 org/apache/commons/math3/fraction/BigFraction.<init>:(II)V (2, 4)
	67 invokeinterface (2, 4)
	68 java/util/List.org/apache/commons/math3/fraction/BigFraction (2, 4)
	70 0 (2, 4)
	72 pop (2, 4)
	73 aload (2, 4)
	74 #4 (2, 4)
	75 new (2, 4)
	76 org/apache/commons/math3/fraction/BigFraction (2, 4)
	78 dup (2, 4)
	79 iconst_2 (2, 4)
	80 iload_1 (2, 4)
	81 iadd (2, 4)
	82 iload_2 (2, 4)
	83 iadd (2, 4)
	84 iconst_2 (2, 4)
	85 invokespecial (2, 4)
	86 org/apache/commons/math3/fraction/BigFraction.<init>:(II)V (2, 4)
	88 invokeinterface (2, 4)
	89 java/util/List.org/apache/commons/math3/fraction/BigFraction (2, 4)
	91 0 (2, 4)
	93 pop (2, 4)
	94 iload_0 (0, 0)
	95 getstatic (0, 0)
	96 org/apache/commons/math3/analysis/polynomials/PolynomialsUtils.JACOBI_COEFFICIENTS:Ljava/util/Map; (0, 0)
	98 aload_3 (0, 0)
	99 invokeinterface (0, 0)
	100 java/util/Map.java/util/List (0, 0)
	102 0 (0, 0)
	104 checkcast (0, 0)
	105 java/util/List (0, 0)
	107 new (0, 0)
	108 org/apache/commons/math3/analysis/polynomials/PolynomialsUtils$5 (0, 0)
	110 dup (0, 0)
	111 iload_1 (0, 0)
	112 iload_2 (0, 0)
	113 invokespecial (0, 0)
	114 org/apache/commons/math3/analysis/polynomials/PolynomialsUtils$5.<init>:(II)V (0, 0)
	116 invokestatic (0, 0)
	117 org/apache/commons/math3/analysis/polynomials/PolynomialsUtils.buildPolynomial:(ILjava/util/List;Lorg/apache/commons/math3/analysis/polynomials/PolynomialsUtils$RecurrenceCoefficientsGenerator;)Lorg/apache/commons/math3/analysis/polynomials/PolynomialFunction; (0, 0)
	119 areturn (0, 0)

Method: shift
	0 aload_0 (0, 0)
	1 arraylength (0, 0)
	2 istore_3 (0, 0)
	3 iload_3 (0, 0)
	4 newarray (0, 0)
	5 7 (0, 0)
	6 astore (0, 0)
	7 #4 (0, 0)
	8 iload_3 (0, 0)
	9 iload_3 (0, 0)
	10 multianewarray (0, 0)
	11 [[I (0, 0)
	13 58 (0, 0)
	14 astore (0, 0)
	15 #5 (0, 0)
	16 iconst_0 (1, 4)
	17 istore (1, 4)
	18 #6 (1, 4)
	19 iload (1, 4)
	20 #6 (1, 4)
	21 iload_3 (1, 4)
	22 if_icmpge (1, 4)
	23 41 (1, 4)
	25 iconst_0 (2, 4)
	26 istore (2, 4)
	27 #7 (2, 4)
	28 iload (2, 4)
	29 #7 (2, 4)
	30 iload (2, 4)
	31 #6 (2, 4)
	32 if_icmpgt (2, 4)
	33 25 (2, 4)
	35 aload (2, 4)
	36 #5 (2, 4)
	37 iload (2, 4)
	38 #6 (2, 4)
	39 aaload (2, 4)
	40 iload (2, 4)
	41 #7 (2, 4)
	42 iload (2, 4)
	43 #6 (2, 4)
	44 iload (2, 4)
	45 #7 (2, 4)
	46 invokestatic (2, 4)
	47 org/apache/commons/math3/util/CombinatoricsUtils.binomialCoefficient:(II)J (2, 4)
	49 l2i (2, 4)
	50 iastore (2, 4)
	51 iinc (2, 4)
	52 #7 (2, 4)
	53 -89 (2, 4)
	54 goto (2, 4)
	55 -26 (2, 4)
	57 iinc (2, 4)
	58 #6 (2, 4)
	59 -89 (2, 4)
	60 goto (2, 4)
	61 -41 (2, 4)
	63 iconst_0 (2, 4)
	64 istore (2, 4)
	65 #6 (2, 4)
	66 iload (2, 4)
	67 #6 (2, 4)
	68 iload_3 (2, 4)
	69 if_icmpge (2, 4)
	70 27 (2, 4)
	72 aload (3, 1)
	73 #4 (3, 1)
	74 iconst_0 (3, 1)
	75 dup2 (3, 1)
	76 daload (3, 1)
	77 aload_0 (3, 1)
	78 iload (3, 1)
	79 #6 (3, 1)
	80 daload (3, 1)
	81 dload_1 (3, 1)
	82 iload (3, 1)
	83 #6 (3, 1)
	84 invokestatic (3, 1)
	85 org/apache/commons/math3/util/FastMath.pow:(DI)D (3, 1)
	87 dmul (3, 1)
	88 dadd (3, 1)
	89 dastore (3, 1)
	90 iinc (3, 1)
	91 #6 (3, 1)
	92 -89 (3, 1)
	93 goto (3, 1)
	94 -27 (3, 1)
	96 iload_3 (1, 4)
	97 iconst_1 (1, 4)
	98 isub (1, 4)
	99 istore (1, 4)
	100 #6 (1, 4)
	101 iconst_0 (2, 4)
	102 istore (2, 4)
	103 #7 (2, 4)
	104 iload (2, 4)
	105 #7 (2, 4)
	106 iload (2, 4)
	107 #6 (2, 4)
	108 if_icmpge (2, 4)
	109 67 (2, 4)
	111 iload (3, 4)
	112 #7 (3, 4)
	113 istore (3, 4)
	114 #8 (3, 4)
	115 iload (3, 4)
	116 #8 (3, 4)
	117 iload (3, 4)
	118 #6 (3, 4)
	119 if_icmpge (3, 4)
	120 50 (3, 4)
	122 aload (3, 4)
	123 #4 (3, 4)
	124 iload (3, 4)
	125 #7 (3, 4)
	126 iconst_1 (3, 4)
	127 iadd (3, 4)
	128 dup2 (3, 4)
	129 daload (3, 4)
	130 aload (3, 4)
	131 #5 (3, 4)
	132 iload (3, 4)
	133 #8 (3, 4)
	134 iconst_1 (3, 4)
	135 iadd (3, 4)
	136 aaload (3, 4)
	137 iload (3, 4)
	138 #8 (3, 4)
	139 iload (3, 4)
	140 #7 (3, 4)
	141 isub (3, 4)
	142 iaload (3, 4)
	143 i2d (3, 4)
	144 aload_0 (3, 4)
	145 iload (3, 4)
	146 #8 (3, 4)
	147 iconst_1 (3, 4)
	148 iadd (3, 4)
	149 daload (3, 4)
	150 dmul (3, 4)
	151 dload_1 (3, 4)
	152 iload (3, 4)
	153 #8 (3, 4)
	154 iload (3, 4)
	155 #7 (3, 4)
	156 isub (3, 4)
	157 invokestatic (4, 1)
	158 org/apache/commons/math3/util/FastMath.pow:(DI)D (4, 1)
	160 dmul (4, 1)
	161 dadd (4, 1)
	162 dastore (4, 1)
	163 iinc (4, 1)
	164 #8 (4, 1)
	165 -89 (4, 1)
	166 goto (4, 1)
	167 -51 (4, 1)
	169 iinc (4, 1)
	170 #7 (4, 1)
	171 -89 (4, 1)
	172 goto (4, 1)
	173 -68 (4, 1)
	175 aload (2, 4)
	176 #4 (2, 4)
	177 areturn (2, 4)

Method: buildPolynomial
	0 aload_1 (0, 0)
	1 dup (0, 0)
	2 astore_3 (0, 0)
	3 monitorenter (0, 0)
	4 iconst_2 (0, 0)
	5 aload_1 (0, 0)
	6 invokeinterface (0, 0)
	7 java/util/List.sqrt:(D)D (0, 0)
	9 0 (0, 0)
	11 imul (0, 0)
	12 i2d (0, 0)
	13 invokestatic (0, 0)
	14 org/apache/commons/math3/util/FastMath.sqrt:(D)D (0, 0)
	16 invokestatic (0, 0)
	17 org/apache/commons/math3/util/FastMath.floor:(D)D (0, 0)
	19 d2i (0, 0)
	20 iconst_1 (0, 0)
	21 isub (0, 0)
	22 istore (0, 0)
	23 #4 (0, 0)
	24 iload_0 (1, 1)
	25 iload (1, 1)
	26 #4 (1, 1)
	27 if_icmple (1, 1)
	28 11 (1, 1)
	30 iload_0 (1, 1)
	31 iload (1, 1)
	32 #4 (1, 1)
	33 aload_2 (1, 1)
	34 aload_1 (1, 1)
	35 invokestatic (1, 1)
	36 org/apache/commons/math3/analysis/polynomials/PolynomialsUtils.computeUpToDegree:(IILorg/apache/commons/math3/analysis/polynomials/PolynomialsUtils$RecurrenceCoefficientsGenerator;Ljava/util/List;)V (1, 1)
	38 aload_3 (0, 0)
	39 monitorexit (0, 0)
	40 goto (0, 0)
	41 10 (0, 0)
	43 astore (0, 0)
	44 #5 (0, 0)
	45 aload_3 (0, 0)
	46 monitorexit (0, 0)
	47 aload (0, 0)
	48 #5 (0, 0)
	49 athrow (0, 0)
	50 iload_0 (7, 4)
	51 iload_0 (7, 4)
	52 iconst_1 (7, 4)
	53 iadd (7, 4)
	54 imul (7, 4)
	55 iconst_2 (7, 4)
	56 idiv (7, 4)
	57 istore_3 (7, 4)
	58 iload_0 (7, 4)
	59 iconst_1 (7, 4)
	60 iadd (7, 4)
	61 newarray (7, 4)
	62 7 (7, 4)
	63 astore (7, 4)
	64 #4 (7, 4)
	65 iconst_0 (8, 4)
	66 istore (8, 4)
	67 #5 (8, 4)
	68 iload (8, 4)
	69 #5 (8, 4)
	70 iload_0 (8, 4)
	71 if_icmpgt (8, 4)
	72 30 (8, 4)
	74 aload (8, 4)
	75 #4 (8, 4)
	76 iload (8, 4)
	77 #5 (8, 4)
	78 aload_1 (8, 4)
	79 iload_3 (8, 4)
	80 iload (8, 4)
	81 #5 (8, 4)
	82 iadd (8, 4)
	83 invokeinterface (8, 4)
	84 java/util/List.doubleValue:()D (8, 4)
	86 0 (8, 4)
	88 checkcast (8, 4)
	89 org/apache/commons/math3/fraction/BigFraction (8, 4)
	91 invokevirtual (8, 4)
	92 org/apache/commons/math3/fraction/BigFraction.doubleValue:()D (8, 4)
	94 dastore (8, 4)
	95 iinc (8, 4)
	96 #5 (8, 4)
	97 -89 (8, 4)
	98 goto (8, 4)
	99 -30 (8, 4)
	101 new (7, 4)
	102 org/apache/commons/math3/analysis/polynomials/PolynomialFunction (7, 4)
	104 dup (7, 4)
	105 aload (7, 4)
	106 #4 (7, 4)
	107 invokespecial (7, 4)
	108 org/apache/commons/math3/analysis/polynomials/PolynomialFunction.<init>:([D)V (7, 4)
	110 areturn (0, 4)

Method: computeUpToDegree
	0 iload_1 (0, 0)
	1 iconst_1 (0, 0)
	2 isub (0, 0)
	3 iload_1 (0, 0)
	4 imul (0, 0)
	5 iconst_2 (0, 0)
	6 idiv (0, 0)
	7 istore (0, 0)
	8 #4 (0, 0)
	9 iload_1 (1, 4)
	10 istore (1, 4)
	11 #5 (1, 4)
	12 iload (1, 4)
	13 #5 (1, 4)
	14 iload_0 (1, 4)
	15 if_icmpge (1, 4)
	16 240 (1, 4)
	18 iload (1, 4)
	19 #4 (1, 4)
	20 istore (1, 4)
	21 #6 (1, 4)
	22 iload (1, 4)
	23 #4 (1, 4)
	24 iload (1, 4)
	25 #5 (1, 4)
	26 iadd (1, 4)
	27 istore (1, 4)
	28 #4 (1, 4)
	29 aload_2 (1, 4)
	30 iload (1, 4)
	31 #5 (1, 4)
	32 invokeinterface (1, 4)
	33 org/apache/commons/math3/analysis/polynomials/PolynomialsUtils$RecurrenceCoefficientsGenerator.multiply:(Lorg/apache/commons/math3/fraction/BigFraction;)Lorg/apache/commons/math3/fraction/BigFraction; (1, 4)
	35 0 (1, 4)
	37 astore (1, 4)
	38 #7 (1, 4)
	39 aload_3 (1, 4)
	40 iload (1, 4)
	41 #4 (1, 4)
	42 invokeinterface (1, 4)
	43 java/util/List.doubleValue:()D (1, 4)
	45 0 (1, 4)
	47 checkcast (1, 4)
	48 org/apache/commons/math3/fraction/BigFraction (1, 4)
	50 astore (1, 4)
	51 #8 (1, 4)
	52 aload_3 (1, 4)
	53 iload (1, 4)
	54 #6 (1, 4)
	55 invokeinterface (1, 4)
	56 java/util/List.doubleValue:()D (1, 4)
	58 0 (1, 4)
	60 checkcast (1, 4)
	61 org/apache/commons/math3/fraction/BigFraction (1, 4)
	63 astore (1, 4)
	64 #9 (1, 4)
	65 aload_3 (1, 4)
	66 aload (1, 4)
	67 #8 (1, 4)
	68 aload (1, 4)
	69 #7 (1, 4)
	70 iconst_0 (1, 4)
	71 aaload (1, 4)
	72 invokevirtual (1, 4)
	73 org/apache/commons/math3/fraction/BigFraction.multiply:(Lorg/apache/commons/math3/fraction/BigFraction;)Lorg/apache/commons/math3/fraction/BigFraction; (1, 4)
	75 aload (1, 4)
	76 #9 (1, 4)
	77 aload (1, 4)
	78 #7 (1, 4)
	79 iconst_2 (1, 4)
	80 aaload (1, 4)
	81 invokevirtual (1, 4)
	82 org/apache/commons/math3/fraction/BigFraction.multiply:(Lorg/apache/commons/math3/fraction/BigFraction;)Lorg/apache/commons/math3/fraction/BigFraction; (1, 4)
	84 invokevirtual (1, 4)
	85 org/apache/commons/math3/fraction/BigFraction.subtract:(Lorg/apache/commons/math3/fraction/BigFraction;)Lorg/apache/commons/math3/fraction/BigFraction; (1, 4)
	87 invokeinterface (1, 4)
	88 java/util/List.org/apache/commons/math3/fraction/BigFraction (1, 4)
	90 0 (1, 4)
	92 pop (1, 4)
	93 iconst_1 (2, 4)
	94 istore (2, 4)
	95 #10 (2, 4)
	96 iload (2, 4)
	97 #10 (2, 4)
	98 iload (2, 4)
	99 #5 (2, 4)
	100 if_icmpge (2, 4)
	101 85 (2, 4)
	103 aload (2, 4)
	104 #8 (2, 4)
	105 astore (2, 4)
	106 #11 (2, 4)
	107 aload_3 (2, 4)
	108 iload (2, 4)
	109 #4 (2, 4)
	110 iload (2, 4)
	111 #10 (2, 4)
	112 iadd (2, 4)
	113 invokeinterface (2, 4)
	114 java/util/List.doubleValue:()D (2, 4)
	116 0 (2, 4)
	118 checkcast (2, 4)
	119 org/apache/commons/math3/fraction/BigFraction (2, 4)
	121 astore (2, 4)
	122 #8 (2, 4)
	123 aload_3 (2, 4)
	124 iload (2, 4)
	125 #6 (2, 4)
	126 iload (2, 4)
	127 #10 (2, 4)
	128 iadd (2, 4)
	129 invokeinterface (2, 4)
	130 java/util/List.doubleValue:()D (2, 4)
	132 0 (2, 4)
	134 checkcast (2, 4)
	135 org/apache/commons/math3/fraction/BigFraction (2, 4)
	137 astore (2, 4)
	138 #9 (2, 4)
	139 aload_3 (2, 4)
	140 aload (2, 4)
	141 #8 (2, 4)
	142 aload (2, 4)
	143 #7 (2, 4)
	144 iconst_0 (2, 4)
	145 aaload (2, 4)
	146 invokevirtual (2, 4)
	147 org/apache/commons/math3/fraction/BigFraction.multiply:(Lorg/apache/commons/math3/fraction/BigFraction;)Lorg/apache/commons/math3/fraction/BigFraction; (2, 4)
	149 aload (2, 4)
	150 #11 (2, 4)
	151 aload (2, 4)
	152 #7 (2, 4)
	153 iconst_1 (2, 4)
	154 aaload (2, 4)
	155 invokevirtual (2, 4)
	156 org/apache/commons/math3/fraction/BigFraction.multiply:(Lorg/apache/commons/math3/fraction/BigFraction;)Lorg/apache/commons/math3/fraction/BigFraction; (2, 4)
	158 invokevirtual (2, 4)
	159 org/apache/commons/math3/fraction/BigFraction.add:(Lorg/apache/commons/math3/fraction/BigFraction;)Lorg/apache/commons/math3/fraction/BigFraction; (2, 4)
	161 aload (2, 4)
	162 #9 (2, 4)
	163 aload (2, 4)
	164 #7 (2, 4)
	165 iconst_2 (2, 4)
	166 aaload (2, 4)
	167 invokevirtual (2, 4)
	168 org/apache/commons/math3/fraction/BigFraction.multiply:(Lorg/apache/commons/math3/fraction/BigFraction;)Lorg/apache/commons/math3/fraction/BigFraction; (2, 4)
	170 invokevirtual (2, 4)
	171 org/apache/commons/math3/fraction/BigFraction.subtract:(Lorg/apache/commons/math3/fraction/BigFraction;)Lorg/apache/commons/math3/fraction/BigFraction; (2, 4)
	173 invokeinterface (2, 4)
	174 java/util/List.org/apache/commons/math3/fraction/BigFraction (2, 4)
	176 0 (2, 4)
	178 pop (2, 4)
	179 iinc (2, 4)
	180 #10 (2, 4)
	181 -89 (2, 4)
	182 goto (2, 4)
	183 -86 (2, 4)
	185 aload (1, 4)
	186 #8 (1, 4)
	187 astore (1, 4)
	188 #10 (1, 4)
	189 aload_3 (1, 4)
	190 iload (1, 4)
	191 #4 (1, 4)
	192 iload (1, 4)
	193 #5 (1, 4)
	194 iadd (1, 4)
	195 invokeinterface (1, 4)
	196 java/util/List.doubleValue:()D (1, 4)
	198 0 (1, 4)
	200 checkcast (1, 4)
	201 org/apache/commons/math3/fraction/BigFraction (1, 4)
	203 astore (1, 4)
	204 #8 (1, 4)
	205 aload_3 (1, 4)
	206 aload (1, 4)
	207 #8 (1, 4)
	208 aload (1, 4)
	209 #7 (1, 4)
	210 iconst_0 (1, 4)
	211 aaload (1, 4)
	212 invokevirtual (1, 4)
	213 org/apache/commons/math3/fraction/BigFraction.multiply:(Lorg/apache/commons/math3/fraction/BigFraction;)Lorg/apache/commons/math3/fraction/BigFraction; (1, 4)
	215 aload (1, 4)
	216 #10 (1, 4)
	217 aload (1, 4)
	218 #7 (1, 4)
	219 iconst_1 (1, 4)
	220 aaload (1, 4)
	221 invokevirtual (1, 4)
	222 org/apache/commons/math3/fraction/BigFraction.multiply:(Lorg/apache/commons/math3/fraction/BigFraction;)Lorg/apache/commons/math3/fraction/BigFraction; (1, 4)
	224 invokevirtual (1, 4)
	225 org/apache/commons/math3/fraction/BigFraction.add:(Lorg/apache/commons/math3/fraction/BigFraction;)Lorg/apache/commons/math3/fraction/BigFraction; (1, 4)
	227 invokeinterface (1, 4)
	228 java/util/List.org/apache/commons/math3/fraction/BigFraction (1, 4)
	230 0 (1, 4)
	232 pop (1, 4)
	233 aload_3 (1, 4)
	234 aload (1, 4)
	235 #8 (1, 4)
	236 aload (1, 4)
	237 #7 (1, 4)
	238 iconst_1 (1, 4)
	239 aaload (1, 4)
	240 invokevirtual (1, 4)
	241 org/apache/commons/math3/fraction/BigFraction.multiply:(Lorg/apache/commons/math3/fraction/BigFraction;)Lorg/apache/commons/math3/fraction/BigFraction; (1, 4)
	243 invokeinterface (1, 4)
	244 java/util/List.org/apache/commons/math3/fraction/BigFraction (1, 4)
	246 0 (1, 4)
	248 pop (1, 4)
	249 iinc (1, 4)
	250 #5 (1, 4)
	251 -89 (1, 4)
	252 goto (1, 4)
	253 -240 (1, 4)
	255 return (0, 0)

Method: <clinit>
	0 new (0, 0)
	1 java/util/ArrayList (0, 0)
	3 dup (0, 0)
	4 invokespecial (0, 0)
	5 java/util/ArrayList.<init>:()V (0, 0)
	7 putstatic (0, 0)
	8 org/apache/commons/math3/analysis/polynomials/PolynomialsUtils.CHEBYSHEV_COEFFICIENTS:Ljava/util/List; (0, 0)
	10 getstatic (0, 0)
	11 org/apache/commons/math3/analysis/polynomials/PolynomialsUtils.CHEBYSHEV_COEFFICIENTS:Ljava/util/List; (0, 0)
	13 getstatic (0, 0)
	14 org/apache/commons/math3/fraction/BigFraction.ONE:Lorg/apache/commons/math3/fraction/BigFraction; (0, 0)
	16 invokeinterface (0, 0)
	17 java/util/List.org/apache/commons/math3/fraction/BigFraction (0, 0)
	19 0 (0, 0)
	21 pop (0, 0)
	22 getstatic (0, 0)
	23 org/apache/commons/math3/analysis/polynomials/PolynomialsUtils.CHEBYSHEV_COEFFICIENTS:Ljava/util/List; (0, 0)
	25 getstatic (0, 0)
	26 org/apache/commons/math3/fraction/BigFraction.ZERO:Lorg/apache/commons/math3/fraction/BigFraction; (0, 0)
	28 invokeinterface (0, 0)
	29 java/util/List.org/apache/commons/math3/fraction/BigFraction (0, 0)
	31 0 (0, 0)
	33 pop (0, 0)
	34 getstatic (0, 0)
	35 org/apache/commons/math3/analysis/polynomials/PolynomialsUtils.CHEBYSHEV_COEFFICIENTS:Ljava/util/List; (0, 0)
	37 getstatic (0, 0)
	38 org/apache/commons/math3/fraction/BigFraction.ONE:Lorg/apache/commons/math3/fraction/BigFraction; (0, 0)
	40 invokeinterface (0, 0)
	41 java/util/List.org/apache/commons/math3/fraction/BigFraction (0, 0)
	43 0 (0, 0)
	45 pop (0, 0)
	46 new (1, 4)
	47 java/util/ArrayList (1, 4)
	49 dup (1, 4)
	50 invokespecial (1, 4)
	51 java/util/ArrayList.<init>:()V (1, 4)
	53 putstatic (1, 4)
	54 org/apache/commons/math3/analysis/polynomials/PolynomialsUtils.HERMITE_COEFFICIENTS:Ljava/util/List; (1, 4)
	56 getstatic (1, 4)
	57 org/apache/commons/math3/analysis/polynomials/PolynomialsUtils.HERMITE_COEFFICIENTS:Ljava/util/List; (1, 4)
	59 getstatic (1, 4)
	60 org/apache/commons/math3/fraction/BigFraction.ONE:Lorg/apache/commons/math3/fraction/BigFraction; (1, 4)
	62 invokeinterface (1, 4)
	63 java/util/List.org/apache/commons/math3/fraction/BigFraction (1, 4)
	65 0 (1, 4)
	67 pop (1, 4)
	68 getstatic (1, 4)
	69 org/apache/commons/math3/analysis/polynomials/PolynomialsUtils.HERMITE_COEFFICIENTS:Ljava/util/List; (1, 4)
	71 getstatic (1, 4)
	72 org/apache/commons/math3/fraction/BigFraction.ZERO:Lorg/apache/commons/math3/fraction/BigFraction; (1, 4)
	74 invokeinterface (1, 4)
	75 java/util/List.org/apache/commons/math3/fraction/BigFraction (1, 4)
	77 0 (1, 4)
	79 pop (1, 4)
	80 getstatic (1, 4)
	81 org/apache/commons/math3/analysis/polynomials/PolynomialsUtils.HERMITE_COEFFICIENTS:Ljava/util/List; (1, 4)
	83 getstatic (1, 4)
	84 org/apache/commons/math3/fraction/BigFraction.TWO:Lorg/apache/commons/math3/fraction/BigFraction; (1, 4)
	86 invokeinterface (1, 4)
	87 java/util/List.org/apache/commons/math3/fraction/BigFraction (1, 4)
	89 0 (1, 4)
	91 pop (1, 4)
	92 new (2, 4)
	93 java/util/ArrayList (2, 4)
	95 dup (2, 4)
	96 invokespecial (2, 4)
	97 java/util/ArrayList.<init>:()V (2, 4)
	99 putstatic (2, 4)
	100 org/apache/commons/math3/analysis/polynomials/PolynomialsUtils.LAGUERRE_COEFFICIENTS:Ljava/util/List; (2, 4)
	102 getstatic (2, 4)
	103 org/apache/commons/math3/analysis/polynomials/PolynomialsUtils.LAGUERRE_COEFFICIENTS:Ljava/util/List; (2, 4)
	105 getstatic (2, 4)
	106 org/apache/commons/math3/fraction/BigFraction.ONE:Lorg/apache/commons/math3/fraction/BigFraction; (2, 4)
	108 invokeinterface (2, 4)
	109 java/util/List.org/apache/commons/math3/fraction/BigFraction (2, 4)
	111 0 (2, 4)
	113 pop (2, 4)
	114 getstatic (2, 4)
	115 org/apache/commons/math3/analysis/polynomials/PolynomialsUtils.LAGUERRE_COEFFICIENTS:Ljava/util/List; (2, 4)
	117 getstatic (2, 4)
	118 org/apache/commons/math3/fraction/BigFraction.ONE:Lorg/apache/commons/math3/fraction/BigFraction; (2, 4)
	120 invokeinterface (2, 4)
	121 java/util/List.org/apache/commons/math3/fraction/BigFraction (2, 4)
	123 0 (2, 4)
	125 pop (2, 4)
	126 getstatic (2, 4)
	127 org/apache/commons/math3/analysis/polynomials/PolynomialsUtils.LAGUERRE_COEFFICIENTS:Ljava/util/List; (2, 4)
	129 getstatic (2, 4)
	130 org/apache/commons/math3/fraction/BigFraction.MINUS_ONE:Lorg/apache/commons/math3/fraction/BigFraction; (2, 4)
	132 invokeinterface (2, 4)
	133 java/util/List.org/apache/commons/math3/fraction/BigFraction (2, 4)
	135 0 (2, 4)
	137 pop (2, 4)
	138 new (3, 4)
	139 java/util/ArrayList (3, 4)
	141 dup (3, 4)
	142 invokespecial (3, 4)
	143 java/util/ArrayList.<init>:()V (3, 4)
	145 putstatic (3, 4)
	146 org/apache/commons/math3/analysis/polynomials/PolynomialsUtils.LEGENDRE_COEFFICIENTS:Ljava/util/List; (3, 4)
	148 getstatic (3, 4)
	149 org/apache/commons/math3/analysis/polynomials/PolynomialsUtils.LEGENDRE_COEFFICIENTS:Ljava/util/List; (3, 4)
	151 getstatic (3, 4)
	152 org/apache/commons/math3/fraction/BigFraction.ONE:Lorg/apache/commons/math3/fraction/BigFraction; (3, 4)
	154 invokeinterface (3, 4)
	155 java/util/List.org/apache/commons/math3/fraction/BigFraction (3, 4)
	157 0 (3, 4)
	159 pop (3, 4)
	160 getstatic (3, 4)
	161 org/apache/commons/math3/analysis/polynomials/PolynomialsUtils.LEGENDRE_COEFFICIENTS:Ljava/util/List; (3, 4)
	163 getstatic (3, 4)
	164 org/apache/commons/math3/fraction/BigFraction.ZERO:Lorg/apache/commons/math3/fraction/BigFraction; (3, 4)
	166 invokeinterface (3, 4)
	167 java/util/List.org/apache/commons/math3/fraction/BigFraction (3, 4)
	169 0 (3, 4)
	171 pop (3, 4)
	172 getstatic (3, 4)
	173 org/apache/commons/math3/analysis/polynomials/PolynomialsUtils.LEGENDRE_COEFFICIENTS:Ljava/util/List; (3, 4)
	175 getstatic (3, 4)
	176 org/apache/commons/math3/fraction/BigFraction.ONE:Lorg/apache/commons/math3/fraction/BigFraction; (3, 4)
	178 invokeinterface (3, 4)
	179 java/util/List.org/apache/commons/math3/fraction/BigFraction (3, 4)
	181 0 (3, 4)
	183 pop (3, 4)
	184 new (4, 4)
	185 java/util/HashMap (4, 4)
	187 dup (4, 4)
	188 invokespecial (4, 4)
	189 java/util/HashMap.<init>:()V (4, 4)
	191 putstatic (4, 4)
	192 org/apache/commons/math3/analysis/polynomials/PolynomialsUtils.JACOBI_COEFFICIENTS:Ljava/util/Map; (4, 4)
	194 return (0, 4)

