Method: <init>
	0 aload_0 (0, 0)
	1 invokespecial (0, 0)
	2 java/lang/Object.<init>:()V (0, 0)
	4 aload_1 (1, 1)
	5 ifnull (1, 1)
	6 7 (1, 1)
	8 aload_2 (1, 1)
	9 ifnonnull (1, 1)
	10 11 (1, 1)
	12 new (1, 1)
	13 org/apache/commons/math3/exception/NullArgumentException (1, 1)
	15 dup (1, 1)
	16 invokespecial (1, 1)
	17 org/apache/commons/math3/exception/NullArgumentException.<init>:()V (1, 1)
	19 athrow (1, 1)
	20 aload_1 (2, 1)
	21 arraylength (2, 1)
	22 iconst_2 (2, 1)
	23 if_icmpge (2, 1)
	24 24 (2, 1)
	26 new (2, 1)
	27 org/apache/commons/math3/exception/NumberIsTooSmallException (2, 1)
	29 dup (2, 1)
	30 getstatic (2, 1)
	31 org/apache/commons/math3/exception/util/LocalizedFormats.NOT_ENOUGH_POINTS_IN_SPLINE_PARTITION:Lorg/apache/commons/math3/exception/util/LocalizedFormats; (2, 1)
	33 iconst_2 (2, 1)
	34 invokestatic (2, 1)
	35 java/lang/Integer.valueOf:(I)Ljava/lang/Integer; (2, 1)
	37 aload_1 (2, 1)
	38 arraylength (2, 1)
	39 invokestatic (2, 1)
	40 java/lang/Integer.valueOf:(I)Ljava/lang/Integer; (2, 1)
	42 iconst_0 (2, 1)
	43 invokespecial (2, 1)
	44 org/apache/commons/math3/exception/NumberIsTooSmallException.<init>:(Lorg/apache/commons/math3/exception/util/Localizable;Ljava/lang/Number;Ljava/lang/Number;Z)V (2, 1)
	46 athrow (2, 1)
	47 aload_1 (2, 1)
	48 arraylength (2, 1)
	49 iconst_1 (2, 1)
	50 isub (2, 1)
	51 aload_2 (2, 1)
	52 arraylength (2, 1)
	53 if_icmpeq (2, 1)
	54 15 (2, 1)
	56 new (2, 1)
	57 org/apache/commons/math3/exception/DimensionMismatchException (2, 1)
	59 dup (2, 1)
	60 aload_2 (2, 1)
	61 arraylength (2, 1)
	62 aload_1 (2, 1)
	63 arraylength (2, 1)
	64 invokespecial (2, 1)
	65 org/apache/commons/math3/exception/DimensionMismatchException.<init>:(II)V (2, 1)
	67 athrow (2, 1)
	68 aload_1 (1, 1)
	69 invokestatic (1, 1)
	70 org/apache/commons/math3/util/MathArrays.checkOrder:([D)V (1, 1)
	72 aload_0 (1, 1)
	73 aload_1 (1, 1)
	74 arraylength (1, 1)
	75 iconst_1 (1, 1)
	76 isub (1, 1)
	77 putfield (1, 1)
	78 org/apache/commons/math3/analysis/polynomials/PolynomialSplineFunction.n:I (1, 1)
	80 aload_0 (1, 1)
	81 aload_0 (1, 1)
	82 getfield (1, 1)
	83 org/apache/commons/math3/analysis/polynomials/PolynomialSplineFunction.n:I (1, 1)
	85 iconst_1 (1, 1)
	86 iadd (1, 1)
	87 newarray (1, 1)
	88 7 (1, 1)
	89 putfield (1, 1)
	90 org/apache/commons/math3/analysis/polynomials/PolynomialSplineFunction.knots:[D (1, 1)
	92 aload_1 (1, 1)
	93 iconst_0 (1, 1)
	94 aload_0 (1, 1)
	95 getfield (1, 1)
	96 org/apache/commons/math3/analysis/polynomials/PolynomialSplineFunction.knots:[D (1, 1)
	98 iconst_0 (1, 1)
	99 aload_0 (1, 1)
	100 getfield (1, 1)
	101 org/apache/commons/math3/analysis/polynomials/PolynomialSplineFunction.n:I (1, 1)
	103 iconst_1 (1, 1)
	104 iadd (1, 1)
	105 invokestatic (1, 1)
	106 java/lang/System.arraycopy:(Ljava/lang/Object;ILjava/lang/Object;II)V (1, 1)
	108 aload_0 (1, 1)
	109 aload_0 (1, 1)
	110 getfield (1, 1)
	111 org/apache/commons/math3/analysis/polynomials/PolynomialSplineFunction.n:I (1, 1)
	113 anewarray (1, 1)
	114 org/apache/commons/math3/analysis/polynomials/PolynomialFunction (1, 1)
	116 putfield (1, 1)
	117 org/apache/commons/math3/analysis/polynomials/PolynomialSplineFunction.polynomials:[Lorg/apache/commons/math3/analysis/polynomials/PolynomialFunction; (1, 1)
	119 aload_2 (1, 1)
	120 iconst_0 (1, 1)
	121 aload_0 (1, 1)
	122 getfield (1, 1)
	123 org/apache/commons/math3/analysis/polynomials/PolynomialSplineFunction.polynomials:[Lorg/apache/commons/math3/analysis/polynomials/PolynomialFunction; (1, 1)
	125 iconst_0 (1, 1)
	126 aload_0 (1, 1)
	127 getfield (1, 1)
	128 org/apache/commons/math3/analysis/polynomials/PolynomialSplineFunction.n:I (1, 1)
	130 invokestatic (1, 1)
	131 java/lang/System.arraycopy:(Ljava/lang/Object;ILjava/lang/Object;II)V (1, 1)
	133 return (0, 0)

Method: value
	0 aload_1 (0, 0)
	1 invokevirtual (0, 0)
	2 org/apache/commons/math3/analysis/differentiation/DerivativeStructure.getValue:()D (0, 0)
	4 dstore_2 (0, 0)
	5 dload_2 (1, 1)
	6 aload_0 (1, 1)
	7 getfield (1, 1)
	8 org/apache/commons/math3/analysis/polynomials/PolynomialSplineFunction.knots:[D (1, 1)
	10 iconst_0 (1, 1)
	11 daload (1, 1)
	12 dcmpg (1, 1)
	13 iflt (1, 1)
	14 17 (1, 1)
	16 dload_2 (1, 1)
	17 aload_0 (1, 1)
	18 getfield (1, 1)
	19 org/apache/commons/math3/analysis/polynomials/PolynomialSplineFunction.knots:[D (1, 1)
	21 aload_0 (1, 1)
	22 getfield (1, 1)
	23 org/apache/commons/math3/analysis/polynomials/PolynomialSplineFunction.n:I (1, 1)
	25 daload (1, 1)
	26 dcmpl (1, 1)
	27 ifle (1, 1)
	28 36 (1, 1)
	30 new (1, 1)
	31 org/apache/commons/math3/exception/OutOfRangeException (1, 1)
	33 dup (1, 1)
	34 dload_2 (1, 1)
	35 invokestatic (1, 1)
	36 java/lang/Double.valueOf:(D)Ljava/lang/Double; (1, 1)
	38 aload_0 (1, 1)
	39 getfield (1, 1)
	40 org/apache/commons/math3/analysis/polynomials/PolynomialSplineFunction.knots:[D (1, 1)
	42 iconst_0 (1, 1)
	43 daload (1, 1)
	44 invokestatic (1, 1)
	45 java/lang/Double.valueOf:(D)Ljava/lang/Double; (1, 1)
	47 aload_0 (1, 1)
	48 getfield (1, 1)
	49 org/apache/commons/math3/analysis/polynomials/PolynomialSplineFunction.knots:[D (1, 1)
	51 aload_0 (1, 1)
	52 getfield (1, 1)
	53 org/apache/commons/math3/analysis/polynomials/PolynomialSplineFunction.n:I (1, 1)
	55 daload (1, 1)
	56 invokestatic (1, 1)
	57 java/lang/Double.valueOf:(D)Ljava/lang/Double; (1, 1)
	59 invokespecial (1, 1)
	60 org/apache/commons/math3/exception/OutOfRangeException.<init>:(Ljava/lang/Number;Ljava/lang/Number;Ljava/lang/Number;)V (1, 1)
	62 athrow (1, 1)
	63 aload_0 (0, 0)
	64 getfield (0, 0)
	65 org/apache/commons/math3/analysis/polynomials/PolynomialSplineFunction.knots:[D (0, 0)
	67 dload_2 (0, 0)
	68 invokestatic (0, 0)
	69 java/util/Arrays.binarySearch:([DD)I (0, 0)
	71 istore (0, 0)
	72 #4 (0, 0)
	73 iload (1, 1)
	74 #4 (1, 1)
	75 ifge (1, 1)
	76 10 (1, 1)
	78 iload (1, 1)
	79 #4 (1, 1)
	80 ineg (1, 1)
	81 iconst_2 (1, 1)
	82 isub (1, 1)
	83 istore (1, 1)
	84 #4 (1, 1)
	85 iload (2, 1)
	86 #4 (2, 1)
	87 aload_0 (2, 1)
	88 getfield (2, 1)
	89 org/apache/commons/math3/analysis/polynomials/PolynomialSplineFunction.polynomials:[Lorg/apache/commons/math3/analysis/polynomials/PolynomialFunction; (2, 1)
	91 arraylength (2, 1)
	92 if_icmplt (2, 1)
	93 6 (2, 1)
	95 iinc (2, 1)
	96 #4 (2, 1)
	97 42 (2, 1)
	98 aload_0 (1, 1)
	99 getfield (1, 1)
	100 org/apache/commons/math3/analysis/polynomials/PolynomialSplineFunction.polynomials:[Lorg/apache/commons/math3/analysis/polynomials/PolynomialFunction; (1, 1)
	102 iload (1, 1)
	103 #4 (1, 1)
	104 aaload (1, 1)
	105 aload_1 (1, 1)
	106 aload_0 (1, 1)
	107 getfield (1, 1)
	108 org/apache/commons/math3/analysis/polynomials/PolynomialSplineFunction.knots:[D (1, 1)
	110 iload (1, 1)
	111 #4 (1, 1)
	112 daload (1, 1)
	113 invokevirtual (1, 1)
	114 org/apache/commons/math3/analysis/differentiation/DerivativeStructure.subtract:(D)Lorg/apache/commons/math3/analysis/differentiation/DerivativeStructure; (1, 1)
	116 invokevirtual (1, 1)
	117 org/apache/commons/math3/analysis/polynomials/PolynomialFunction.value:(Lorg/apache/commons/math3/analysis/differentiation/DerivativeStructure;)Lorg/apache/commons/math3/analysis/differentiation/DerivativeStructure; (1, 1)
	119 areturn (0, 1)

Method: derivative
	0 aload_0 (0, 0)
	1 invokevirtual (0, 0)
	2 org/apache/commons/math3/analysis/polynomials/PolynomialSplineFunction.polynomialSplineDerivative:()Lorg/apache/commons/math3/analysis/polynomials/PolynomialSplineFunction; (0, 0)
	4 areturn (0, 0)

Method: polynomialSplineDerivative
	0 aload_0 (0, 0)
	1 getfield (0, 0)
	2 org/apache/commons/math3/analysis/polynomials/PolynomialSplineFunction.n:I (0, 0)
	4 anewarray (0, 0)
	5 org/apache/commons/math3/analysis/polynomials/PolynomialFunction (0, 0)
	7 astore_1 (0, 0)
	8 iconst_0 (1, 4)
	9 istore_2 (1, 4)
	10 iload_2 (1, 4)
	11 aload_0 (1, 4)
	12 getfield (1, 4)
	13 org/apache/commons/math3/analysis/polynomials/PolynomialSplineFunction.n:I (1, 4)
	15 if_icmpge (1, 4)
	16 21 (1, 4)
	18 aload_1 (1, 4)
	19 iload_2 (1, 4)
	20 aload_0 (1, 4)
	21 getfield (1, 4)
	22 org/apache/commons/math3/analysis/polynomials/PolynomialSplineFunction.polynomials:[Lorg/apache/commons/math3/analysis/polynomials/PolynomialFunction; (1, 4)
	24 iload_2 (1, 4)
	25 aaload (1, 4)
	26 invokevirtual (1, 4)
	27 org/apache/commons/math3/analysis/polynomials/PolynomialFunction.polynomialDerivative:()Lorg/apache/commons/math3/analysis/polynomials/PolynomialFunction; (1, 4)
	29 aastore (1, 4)
	30 iinc (1, 4)
	31 #2 (1, 4)
	32 -89 (1, 4)
	33 goto (1, 4)
	34 -23 (1, 4)
	36 new (0, 0)
	37 org/apache/commons/math3/analysis/polynomials/PolynomialSplineFunction (0, 0)
	39 dup (0, 0)
	40 aload_0 (0, 0)
	41 getfield (0, 0)
	42 org/apache/commons/math3/analysis/polynomials/PolynomialSplineFunction.knots:[D (0, 0)
	44 aload_1 (0, 0)
	45 invokespecial (0, 0)
	46 org/apache/commons/math3/analysis/polynomials/PolynomialSplineFunction.<init>:([D[Lorg/apache/commons/math3/analysis/polynomials/PolynomialFunction;)V (0, 0)
	48 areturn (0, 0)

Method: getN
	0 aload_0 (0, 0)
	1 getfield (0, 0)
	2 org/apache/commons/math3/analysis/polynomials/PolynomialSplineFunction.n:I (0, 0)
	4 ireturn (0, 0)

Method: getPolynomials
	0 aload_0 (0, 0)
	1 getfield (0, 0)
	2 org/apache/commons/math3/analysis/polynomials/PolynomialSplineFunction.n:I (0, 0)
	4 anewarray (0, 0)
	5 org/apache/commons/math3/analysis/polynomials/PolynomialFunction (0, 0)
	7 astore_1 (0, 0)
	8 aload_0 (0, 0)
	9 getfield (0, 0)
	10 org/apache/commons/math3/analysis/polynomials/PolynomialSplineFunction.polynomials:[Lorg/apache/commons/math3/analysis/polynomials/PolynomialFunction; (0, 0)
	12 iconst_0 (0, 0)
	13 aload_1 (0, 0)
	14 iconst_0 (0, 0)
	15 aload_0 (0, 0)
	16 getfield (0, 0)
	17 org/apache/commons/math3/analysis/polynomials/PolynomialSplineFunction.n:I (0, 0)
	19 invokestatic (0, 0)
	20 java/lang/System.arraycopy:(Ljava/lang/Object;ILjava/lang/Object;II)V (0, 0)
	22 aload_1 (0, 0)
	23 areturn (0, 0)

Method: getKnots
	0 aload_0 (0, 0)
	1 getfield (0, 0)
	2 org/apache/commons/math3/analysis/polynomials/PolynomialSplineFunction.n:I (0, 0)
	4 iconst_1 (0, 0)
	5 iadd (0, 0)
	6 newarray (0, 0)
	7 7 (0, 0)
	8 astore_1 (0, 0)
	9 aload_0 (0, 0)
	10 getfield (0, 0)
	11 org/apache/commons/math3/analysis/polynomials/PolynomialSplineFunction.knots:[D (0, 0)
	13 iconst_0 (0, 0)
	14 aload_1 (0, 0)
	15 iconst_0 (0, 0)
	16 aload_0 (0, 0)
	17 getfield (0, 0)
	18 org/apache/commons/math3/analysis/polynomials/PolynomialSplineFunction.n:I (0, 0)
	20 iconst_1 (0, 0)
	21 iadd (0, 0)
	22 invokestatic (0, 0)
	23 java/lang/System.arraycopy:(Ljava/lang/Object;ILjava/lang/Object;II)V (0, 0)
	25 aload_1 (0, 0)
	26 areturn (0, 0)

Method: isValidPoint
	0 dload_1 (1, 1)
	1 aload_0 (1, 1)
	2 getfield (1, 1)
	3 org/apache/commons/math3/analysis/polynomials/PolynomialSplineFunction.knots:[D (1, 1)
	5 iconst_0 (1, 1)
	6 daload (1, 1)
	7 dcmpg (1, 1)
	8 iflt (1, 1)
	9 17 (1, 1)
	11 dload_1 (1, 1)
	12 aload_0 (1, 1)
	13 getfield (1, 1)
	14 org/apache/commons/math3/analysis/polynomials/PolynomialSplineFunction.knots:[D (1, 1)
	16 aload_0 (1, 1)
	17 getfield (1, 1)
	18 org/apache/commons/math3/analysis/polynomials/PolynomialSplineFunction.n:I (1, 1)
	20 daload (1, 1)
	21 dcmpl (1, 1)
	22 ifle (1, 1)
	23 5 (1, 1)
	25 iconst_0 (1, 1)
	26 ireturn (1, 1)
	27 iconst_1 (2, 2)
	28 ireturn (1, 2)

