Method: <init>
	0 aload_0 (0, 0)
	1 invokespecial (0, 0)
	2 java/lang/Object.<init>:()V (0, 0)
	4 aload_1 (1, 1)
	5 aload_2 (1, 1)
	6 invokestatic (1, 1)
	7 org/apache/commons/math3/analysis/polynomials/PolynomialFunctionNewtonForm.verifyInputArray:([D[D)V (1, 1)
	9 aload_0 (1, 1)
	10 aload_1 (1, 1)
	11 arraylength (1, 1)
	12 newarray (1, 1)
	13 7 (1, 1)
	14 putfield (1, 1)
	15 org/apache/commons/math3/analysis/polynomials/PolynomialFunctionNewtonForm.a:[D (1, 1)
	17 aload_0 (1, 1)
	18 aload_2 (1, 1)
	19 arraylength (1, 1)
	20 newarray (1, 1)
	21 7 (1, 1)
	22 putfield (1, 1)
	23 org/apache/commons/math3/analysis/polynomials/PolynomialFunctionNewtonForm.c:[D (1, 1)
	25 aload_1 (1, 1)
	26 iconst_0 (1, 1)
	27 aload_0 (1, 1)
	28 getfield (1, 1)
	29 org/apache/commons/math3/analysis/polynomials/PolynomialFunctionNewtonForm.a:[D (1, 1)
	31 iconst_0 (1, 1)
	32 aload_1 (1, 1)
	33 arraylength (1, 1)
	34 invokestatic (1, 1)
	35 java/lang/System.arraycopy:(Ljava/lang/Object;ILjava/lang/Object;II)V (1, 1)
	37 aload_2 (1, 1)
	38 iconst_0 (1, 1)
	39 aload_0 (1, 1)
	40 getfield (1, 1)
	41 org/apache/commons/math3/analysis/polynomials/PolynomialFunctionNewtonForm.c:[D (1, 1)
	43 iconst_0 (1, 1)
	44 aload_2 (1, 1)
	45 arraylength (1, 1)
	46 invokestatic (1, 1)
	47 java/lang/System.arraycopy:(Ljava/lang/Object;ILjava/lang/Object;II)V (1, 1)
	49 aload_0 (1, 1)
	50 iconst_0 (1, 1)
	51 putfield (1, 1)
	52 org/apache/commons/math3/analysis/polynomials/PolynomialFunctionNewtonForm.coefficientsComputed:Z (1, 1)
	54 return (0, 0)

Method: value
	0 aload_0 (1, 1)
	1 getfield (1, 1)
	2 org/apache/commons/math3/analysis/polynomials/PolynomialFunctionNewtonForm.a:[D (1, 1)
	4 aload_0 (1, 1)
	5 getfield (1, 1)
	6 org/apache/commons/math3/analysis/polynomials/PolynomialFunctionNewtonForm.c:[D (1, 1)
	8 invokestatic (1, 1)
	9 org/apache/commons/math3/analysis/polynomials/PolynomialFunctionNewtonForm.verifyInputArray:([D[D)V (1, 1)
	11 aload_0 (1, 1)
	12 getfield (1, 1)
	13 org/apache/commons/math3/analysis/polynomials/PolynomialFunctionNewtonForm.c:[D (1, 1)
	15 arraylength (1, 1)
	16 istore_2 (1, 1)
	17 new (1, 1)
	18 org/apache/commons/math3/analysis/differentiation/DerivativeStructure (1, 1)
	20 dup (1, 1)
	21 aload_1 (1, 1)
	22 invokevirtual (1, 1)
	23 org/apache/commons/math3/analysis/differentiation/DerivativeStructure.getFreeParameters:()I (1, 1)
	25 aload_1 (1, 1)
	26 invokevirtual (1, 1)
	27 org/apache/commons/math3/analysis/differentiation/DerivativeStructure.getOrder:()I (1, 1)
	29 aload_0 (1, 1)
	30 getfield (1, 1)
	31 org/apache/commons/math3/analysis/polynomials/PolynomialFunctionNewtonForm.a:[D (1, 1)
	33 iload_2 (1, 1)
	34 daload (1, 1)
	35 invokespecial (1, 1)
	36 org/apache/commons/math3/analysis/differentiation/DerivativeStructure.<init>:(IID)V (1, 1)
	38 astore_3 (1, 1)
	39 iload_2 (2, 4)
	40 iconst_1 (2, 4)
	41 isub (2, 4)
	42 istore (2, 4)
	43 #4 (2, 4)
	44 iload (2, 4)
	45 #4 (2, 4)
	46 iflt (2, 4)
	47 35 (2, 4)
	49 aload_1 (2, 4)
	50 aload_0 (2, 4)
	51 getfield (2, 4)
	52 org/apache/commons/math3/analysis/polynomials/PolynomialFunctionNewtonForm.c:[D (2, 4)
	54 iload (2, 4)
	55 #4 (2, 4)
	56 daload (2, 4)
	57 invokevirtual (2, 4)
	58 org/apache/commons/math3/analysis/differentiation/DerivativeStructure.subtract:(D)Lorg/apache/commons/math3/analysis/differentiation/DerivativeStructure; (2, 4)
	60 aload_3 (2, 4)
	61 invokevirtual (2, 4)
	62 org/apache/commons/math3/analysis/differentiation/DerivativeStructure.multiply:(Lorg/apache/commons/math3/analysis/differentiation/DerivativeStructure;)Lorg/apache/commons/math3/analysis/differentiation/DerivativeStructure; (2, 4)
	64 aload_0 (2, 4)
	65 getfield (2, 4)
	66 org/apache/commons/math3/analysis/polynomials/PolynomialFunctionNewtonForm.a:[D (2, 4)
	68 iload (2, 4)
	69 #4 (2, 4)
	70 daload (2, 4)
	71 invokevirtual (2, 4)
	72 org/apache/commons/math3/analysis/differentiation/DerivativeStructure.add:(D)Lorg/apache/commons/math3/analysis/differentiation/DerivativeStructure; (2, 4)
	74 astore_3 (2, 4)
	75 iinc (2, 4)
	76 #4 (2, 4)
	77 -89 (2, 4)
	78 goto (2, 4)
	79 -34 (2, 4)
	81 aload_3 (1, 1)
	82 areturn (0, 1)

Method: degree
	0 aload_0 (0, 0)
	1 getfield (0, 0)
	2 org/apache/commons/math3/analysis/polynomials/PolynomialFunctionNewtonForm.c:[D (0, 0)
	4 arraylength (0, 0)
	5 ireturn (0, 0)

Method: getNewtonCoefficients
	0 aload_0 (0, 0)
	1 getfield (0, 0)
	2 org/apache/commons/math3/analysis/polynomials/PolynomialFunctionNewtonForm.a:[D (0, 0)
	4 arraylength (0, 0)
	5 newarray (0, 0)
	6 7 (0, 0)
	7 astore_1 (0, 0)
	8 aload_0 (0, 0)
	9 getfield (0, 0)
	10 org/apache/commons/math3/analysis/polynomials/PolynomialFunctionNewtonForm.a:[D (0, 0)
	12 iconst_0 (0, 0)
	13 aload_1 (0, 0)
	14 iconst_0 (0, 0)
	15 aload_0 (0, 0)
	16 getfield (0, 0)
	17 org/apache/commons/math3/analysis/polynomials/PolynomialFunctionNewtonForm.a:[D (0, 0)
	19 arraylength (0, 0)
	20 invokestatic (0, 0)
	21 java/lang/System.arraycopy:(Ljava/lang/Object;ILjava/lang/Object;II)V (0, 0)
	23 aload_1 (0, 0)
	24 areturn (0, 0)

Method: getCenters
	0 aload_0 (0, 0)
	1 getfield (0, 0)
	2 org/apache/commons/math3/analysis/polynomials/PolynomialFunctionNewtonForm.c:[D (0, 0)
	4 arraylength (0, 0)
	5 newarray (0, 0)
	6 7 (0, 0)
	7 astore_1 (0, 0)
	8 aload_0 (0, 0)
	9 getfield (0, 0)
	10 org/apache/commons/math3/analysis/polynomials/PolynomialFunctionNewtonForm.c:[D (0, 0)
	12 iconst_0 (0, 0)
	13 aload_1 (0, 0)
	14 iconst_0 (0, 0)
	15 aload_0 (0, 0)
	16 getfield (0, 0)
	17 org/apache/commons/math3/analysis/polynomials/PolynomialFunctionNewtonForm.c:[D (0, 0)
	19 arraylength (0, 0)
	20 invokestatic (0, 0)
	21 java/lang/System.arraycopy:(Ljava/lang/Object;ILjava/lang/Object;II)V (0, 0)
	23 aload_1 (0, 0)
	24 areturn (0, 0)

Method: getCoefficients
	0 aload_0 (1, 1)
	1 getfield (1, 1)
	2 org/apache/commons/math3/analysis/polynomials/PolynomialFunctionNewtonForm.coefficientsComputed:Z (1, 1)
	4 ifne (1, 1)
	5 7 (1, 1)
	7 aload_0 (1, 1)
	8 invokevirtual (1, 1)
	9 org/apache/commons/math3/analysis/polynomials/PolynomialFunctionNewtonForm.computeCoefficients:()V (1, 1)
	11 aload_0 (0, 0)
	12 getfield (0, 0)
	13 org/apache/commons/math3/analysis/polynomials/PolynomialFunctionNewtonForm.coefficients:[D (0, 0)
	15 arraylength (0, 0)
	16 newarray (0, 0)
	17 7 (0, 0)
	18 astore_1 (0, 0)
	19 aload_0 (0, 0)
	20 getfield (0, 0)
	21 org/apache/commons/math3/analysis/polynomials/PolynomialFunctionNewtonForm.coefficients:[D (0, 0)
	23 iconst_0 (0, 0)
	24 aload_1 (0, 0)
	25 iconst_0 (0, 0)
	26 aload_0 (0, 0)
	27 getfield (0, 0)
	28 org/apache/commons/math3/analysis/polynomials/PolynomialFunctionNewtonForm.coefficients:[D (0, 0)
	30 arraylength (0, 0)
	31 invokestatic (0, 0)
	32 java/lang/System.arraycopy:(Ljava/lang/Object;ILjava/lang/Object;II)V (0, 0)
	34 aload_1 (0, 0)
	35 areturn (0, 0)

Method: evaluate
	0 aload_0 (1, 1)
	1 aload_1 (1, 1)
	2 invokestatic (1, 1)
	3 org/apache/commons/math3/analysis/polynomials/PolynomialFunctionNewtonForm.verifyInputArray:([D[D)V (1, 1)
	5 aload_1 (1, 1)
	6 arraylength (1, 1)
	7 istore (1, 1)
	8 #4 (1, 1)
	9 aload_0 (1, 1)
	10 iload (1, 1)
	11 #4 (1, 1)
	12 daload (1, 1)
	13 dstore (1, 1)
	14 #5 (1, 1)
	15 iload (2, 4)
	16 #4 (2, 4)
	17 iconst_1 (2, 4)
	18 isub (2, 4)
	19 istore (2, 4)
	20 #7 (2, 4)
	21 iload (2, 4)
	22 #7 (2, 4)
	23 iflt (2, 4)
	24 25 (2, 4)
	26 aload_0 (2, 4)
	27 iload (2, 4)
	28 #7 (2, 4)
	29 daload (2, 4)
	30 dload_2 (2, 4)
	31 aload_1 (2, 4)
	32 iload (2, 4)
	33 #7 (2, 4)
	34 daload (2, 4)
	35 dsub (2, 4)
	36 dload (2, 4)
	37 #5 (2, 4)
	38 dmul (2, 4)
	39 dadd (2, 4)
	40 dstore (2, 4)
	41 #5 (2, 4)
	42 iinc (2, 4)
	43 #7 (2, 4)
	44 -89 (2, 4)
	45 goto (2, 4)
	46 -24 (2, 4)
	48 dload (1, 1)
	49 #5 (1, 1)
	50 dreturn (0, 1)

Method: computeCoefficients
	0 aload_0 (0, 0)
	1 invokevirtual (0, 0)
	2 org/apache/commons/math3/analysis/polynomials/PolynomialFunctionNewtonForm.degree:()I (0, 0)
	4 istore_1 (0, 0)
	5 aload_0 (0, 0)
	6 iload_1 (0, 0)
	7 iconst_1 (0, 0)
	8 iadd (0, 0)
	9 newarray (0, 0)
	10 7 (0, 0)
	11 putfield (0, 0)
	12 org/apache/commons/math3/analysis/polynomials/PolynomialFunctionNewtonForm.coefficients:[D (0, 0)
	14 iconst_0 (1, 4)
	15 istore_2 (1, 4)
	16 iload_2 (1, 4)
	17 iload_1 (1, 4)
	18 if_icmpgt (1, 4)
	19 16 (1, 4)
	21 aload_0 (1, 4)
	22 getfield (1, 4)
	23 org/apache/commons/math3/analysis/polynomials/PolynomialFunctionNewtonForm.coefficients:[D (1, 4)
	25 iload_2 (1, 4)
	26 dconst_0 (1, 4)
	27 dastore (1, 4)
	28 iinc (1, 4)
	29 #2 (1, 4)
	30 -89 (1, 4)
	31 goto (1, 4)
	32 -15 (1, 4)
	34 aload_0 (0, 0)
	35 getfield (0, 0)
	36 org/apache/commons/math3/analysis/polynomials/PolynomialFunctionNewtonForm.coefficients:[D (0, 0)
	38 iconst_0 (0, 0)
	39 aload_0 (0, 0)
	40 getfield (0, 0)
	41 org/apache/commons/math3/analysis/polynomials/PolynomialFunctionNewtonForm.a:[D (0, 0)
	43 iload_1 (0, 0)
	44 daload (0, 0)
	45 dastore (0, 0)
	46 iload_1 (1, 4)
	47 iconst_1 (1, 4)
	48 isub (1, 4)
	49 istore_2 (1, 4)
	50 iload_2 (1, 4)
	51 iflt (1, 4)
	52 77 (1, 4)
	54 iload_1 (2, 4)
	55 iload_2 (2, 4)
	56 isub (2, 4)
	57 istore_3 (2, 4)
	58 iload_3 (2, 4)
	59 ifle (2, 4)
	60 37 (2, 4)
	62 aload_0 (2, 4)
	63 getfield (2, 4)
	64 org/apache/commons/math3/analysis/polynomials/PolynomialFunctionNewtonForm.coefficients:[D (2, 4)
	66 iload_3 (2, 4)
	67 aload_0 (2, 4)
	68 getfield (2, 4)
	69 org/apache/commons/math3/analysis/polynomials/PolynomialFunctionNewtonForm.coefficients:[D (2, 4)
	71 iload_3 (2, 4)
	72 iconst_1 (2, 4)
	73 isub (2, 4)
	74 daload (2, 4)
	75 aload_0 (2, 4)
	76 getfield (2, 4)
	77 org/apache/commons/math3/analysis/polynomials/PolynomialFunctionNewtonForm.c:[D (2, 4)
	79 iload_2 (2, 4)
	80 daload (2, 4)
	81 aload_0 (2, 4)
	82 getfield (2, 4)
	83 org/apache/commons/math3/analysis/polynomials/PolynomialFunctionNewtonForm.coefficients:[D (2, 4)
	85 iload_3 (2, 4)
	86 daload (2, 4)
	87 dmul (2, 4)
	88 dsub (2, 4)
	89 dastore (2, 4)
	90 iinc (2, 4)
	91 #3 (2, 4)
	92 -89 (2, 4)
	93 goto (2, 4)
	94 -35 (2, 4)
	96 aload_0 (1, 4)
	97 getfield (1, 4)
	98 org/apache/commons/math3/analysis/polynomials/PolynomialFunctionNewtonForm.coefficients:[D (1, 4)
	100 iconst_0 (1, 4)
	101 aload_0 (1, 4)
	102 getfield (1, 4)
	103 org/apache/commons/math3/analysis/polynomials/PolynomialFunctionNewtonForm.a:[D (1, 4)
	105 iload_2 (1, 4)
	106 daload (1, 4)
	107 aload_0 (1, 4)
	108 getfield (1, 4)
	109 org/apache/commons/math3/analysis/polynomials/PolynomialFunctionNewtonForm.c:[D (1, 4)
	111 iload_2 (1, 4)
	112 daload (1, 4)
	113 aload_0 (1, 4)
	114 getfield (1, 4)
	115 org/apache/commons/math3/analysis/polynomials/PolynomialFunctionNewtonForm.coefficients:[D (1, 4)
	117 iconst_0 (1, 4)
	118 daload (1, 4)
	119 dmul (1, 4)
	120 dsub (1, 4)
	121 dastore (1, 4)
	122 iinc (1, 4)
	123 #2 (1, 4)
	124 -89 (1, 4)
	125 goto (1, 4)
	126 -75 (1, 4)
	128 aload_0 (0, 0)
	129 iconst_1 (0, 0)
	130 putfield (0, 0)
	131 org/apache/commons/math3/analysis/polynomials/PolynomialFunctionNewtonForm.coefficientsComputed:Z (0, 0)
	133 return (0, 0)

Method: verifyInputArray
	0 aload_0 (0, 0)
	1 invokestatic (0, 0)
	2 org/apache/commons/math3/util/MathUtils.checkNotNull:(Ljava/lang/Object;)V (0, 0)
	4 aload_1 (0, 0)
	5 invokestatic (0, 0)
	6 org/apache/commons/math3/util/MathUtils.checkNotNull:(Ljava/lang/Object;)V (0, 0)
	8 aload_0 (1, 1)
	9 arraylength (1, 1)
	10 ifeq (1, 1)
	11 8 (1, 1)
	13 aload_1 (1, 1)
	14 arraylength (1, 1)
	15 ifne (1, 1)
	16 14 (1, 1)
	18 new (1, 1)
	19 org/apache/commons/math3/exception/NoDataException (1, 1)
	21 dup (1, 1)
	22 getstatic (1, 1)
	23 org/apache/commons/math3/exception/util/LocalizedFormats.EMPTY_POLYNOMIALS_COEFFICIENTS_ARRAY:Lorg/apache/commons/math3/exception/util/LocalizedFormats; (1, 1)
	25 invokespecial (1, 1)
	26 org/apache/commons/math3/exception/NoDataException.<init>:(Lorg/apache/commons/math3/exception/util/Localizable;)V (1, 1)
	28 athrow (1, 1)
	29 aload_0 (1, 1)
	30 arraylength (1, 1)
	31 aload_1 (1, 1)
	32 arraylength (1, 1)
	33 iconst_1 (1, 1)
	34 iadd (1, 1)
	35 if_icmpeq (1, 1)
	36 18 (1, 1)
	38 new (1, 1)
	39 org/apache/commons/math3/exception/DimensionMismatchException (1, 1)
	41 dup (1, 1)
	42 getstatic (1, 1)
	43 org/apache/commons/math3/exception/util/LocalizedFormats.ARRAY_SIZES_SHOULD_HAVE_DIFFERENCE_1:Lorg/apache/commons/math3/exception/util/LocalizedFormats; (1, 1)
	45 aload_0 (1, 1)
	46 arraylength (1, 1)
	47 aload_1 (1, 1)
	48 arraylength (1, 1)
	49 invokespecial (1, 1)
	50 org/apache/commons/math3/exception/DimensionMismatchException.<init>:(Lorg/apache/commons/math3/exception/util/Localizable;II)V (1, 1)
	52 athrow (1, 1)
	53 return (0, 0)

