Method: <init>
	0 aload_0 (0, 0)
	1 invokespecial (0, 0)
	2 org/apache/commons/math3/stat/descriptive/AbstractStorelessUnivariateStatistic.<init>:()V (0, 0)
	4 aload_1 (0, 0)
	5 aload_0 (0, 0)
	6 invokestatic (0, 0)
	7 org/apache/commons/math3/stat/descriptive/summary/Sum.copy:(Lorg/apache/commons/math3/stat/descriptive/summary/Sum;Lorg/apache/commons/math3/stat/descriptive/summary/Sum;)V (0, 0)
	9 return (0, 0)

Method: increment
	0 aload_0 (0, 0)
	1 dup (0, 0)
	2 getfield (0, 0)
	3 org/apache/commons/math3/stat/descriptive/summary/Sum.value:D (0, 0)
	5 dload_1 (0, 0)
	6 dadd (0, 0)
	7 putfield (0, 0)
	8 org/apache/commons/math3/stat/descriptive/summary/Sum.value:D (0, 0)
	10 aload_0 (0, 0)
	11 dup (0, 0)
	12 getfield (0, 0)
	13 org/apache/commons/math3/stat/descriptive/summary/Sum.n:J (0, 0)
	15 lconst_1 (0, 0)
	16 ladd (0, 0)
	17 putfield (0, 0)
	18 org/apache/commons/math3/stat/descriptive/summary/Sum.n:J (0, 0)
	20 return (0, 0)

Method: getResult
	0 aload_0 (0, 0)
	1 getfield (0, 0)
	2 org/apache/commons/math3/stat/descriptive/summary/Sum.value:D (0, 0)
	4 dreturn (0, 0)

Method: getN
	0 aload_0 (0, 0)
	1 getfield (0, 0)
	2 org/apache/commons/math3/stat/descriptive/summary/Sum.n:J (0, 0)
	4 lreturn (0, 0)

Method: clear
	0 aload_0 (0, 0)
	1 dconst_0 (0, 0)
	2 putfield (0, 0)
	3 org/apache/commons/math3/stat/descriptive/summary/Sum.value:D (0, 0)
	5 aload_0 (0, 0)
	6 lconst_0 (0, 0)
	7 putfield (0, 0)
	8 org/apache/commons/math3/stat/descriptive/summary/Sum.n:J (0, 0)
	10 return (0, 0)

Method: evaluate
	0 aload_0 (0, 0)
	1 aload_1 (0, 0)
	2 aload_2 (0, 0)
	3 iconst_0 (0, 0)
	4 aload_1 (0, 0)
	5 arraylength (0, 0)
	6 invokevirtual (0, 0)
	7 org/apache/commons/math3/stat/descriptive/summary/Sum.evaluate:([D[DII)D (0, 0)
	9 dreturn (0, 0)

Method: copy
	0 aload_0 (0, 0)
	1 invokevirtual (0, 0)
	2 org/apache/commons/math3/stat/descriptive/summary/Sum.copy:()Lorg/apache/commons/math3/stat/descriptive/summary/Sum; (0, 0)
	4 areturn (0, 0)

