Method: <init>
	0 aload_0 (0, 0)
	1 invokespecial (0, 0)
	2 org/apache/commons/math3/stat/descriptive/AbstractStorelessUnivariateStatistic.<init>:()V (0, 0)
	4 aload_1 (0, 0)
	5 aload_0 (0, 0)
	6 invokestatic (0, 0)
	7 org/apache/commons/math3/stat/descriptive/rank/Max.copy:(Lorg/apache/commons/math3/stat/descriptive/rank/Max;Lorg/apache/commons/math3/stat/descriptive/rank/Max;)V (0, 0)
	9 return (0, 0)

Method: increment
	0 dload_1 (1, 1)
	1 aload_0 (1, 1)
	2 getfield (1, 1)
	3 org/apache/commons/math3/stat/descriptive/rank/Max.value:D (1, 1)
	5 dcmpl (1, 1)
	6 ifgt (1, 1)
	7 13 (1, 1)
	9 aload_0 (1, 1)
	10 getfield (1, 1)
	11 org/apache/commons/math3/stat/descriptive/rank/Max.value:D (1, 1)
	13 invokestatic (1, 1)
	14 java/lang/Double.isNaN:(D)Z (1, 1)
	16 ifeq (1, 1)
	17 8 (1, 1)
	19 aload_0 (1, 1)
	20 dload_1 (1, 1)
	21 putfield (1, 1)
	22 org/apache/commons/math3/stat/descriptive/rank/Max.value:D (1, 1)
	24 aload_0 (0, 0)
	25 dup (0, 0)
	26 getfield (0, 0)
	27 org/apache/commons/math3/stat/descriptive/rank/Max.n:J (0, 0)
	29 lconst_1 (0, 0)
	30 ladd (0, 0)
	31 putfield (0, 0)
	32 org/apache/commons/math3/stat/descriptive/rank/Max.n:J (0, 0)
	34 return (0, 0)

Method: clear
	0 aload_0 (0, 0)
	1 ldc2_w (0, 0)
	2 nan (0, 0)
	4 putfield (0, 0)
	5 org/apache/commons/math3/stat/descriptive/rank/Max.value:D (0, 0)
	7 aload_0 (0, 0)
	8 lconst_0 (0, 0)
	9 putfield (0, 0)
	10 org/apache/commons/math3/stat/descriptive/rank/Max.n:J (0, 0)
	12 return (0, 0)

Method: getResult
	0 aload_0 (0, 0)
	1 getfield (0, 0)
	2 org/apache/commons/math3/stat/descriptive/rank/Max.value:D (0, 0)
	4 dreturn (0, 0)

Method: getN
	0 aload_0 (0, 0)
	1 getfield (0, 0)
	2 org/apache/commons/math3/stat/descriptive/rank/Max.n:J (0, 0)
	4 lreturn (0, 0)

Method: evaluate
	0 ldc2_w (0, 0)
	1 nan (0, 0)
	3 dstore (0, 0)
	4 #4 (0, 0)
	5 aload_0 (1, 1)
	6 aload_1 (1, 1)
	7 iload_2 (1, 1)
	8 iload_3 (1, 1)
	9 invokevirtual (1, 1)
	10 org/apache/commons/math3/stat/descriptive/rank/Max.test:([DII)Z (1, 1)
	12 ifeq (1, 1)
	13 56 (1, 1)
	15 aload_1 (1, 1)
	16 iload_2 (1, 1)
	17 daload (1, 1)
	18 dstore (1, 1)
	19 #4 (1, 1)
	20 iload_2 (2, 4)
	21 istore (2, 4)
	22 #6 (2, 4)
	23 iload (2, 4)
	24 #6 (2, 4)
	25 iload_2 (2, 4)
	26 iload_3 (2, 4)
	27 iadd (2, 4)
	28 if_icmpge (2, 4)
	29 40 (2, 4)
	31 aload_1 (3, 1)
	32 iload (3, 1)
	33 #6 (3, 1)
	34 daload (3, 1)
	35 invokestatic (3, 1)
	36 java/lang/Double.isNaN:(D)Z (3, 1)
	38 ifne (3, 1)
	39 24 (3, 1)
	41 dload (3, 1)
	42 #4 (3, 1)
	43 aload_1 (3, 1)
	44 iload (3, 1)
	45 #6 (3, 1)
	46 daload (3, 1)
	47 dcmpl (3, 1)
	48 ifle (3, 1)
	49 8 (3, 1)
	51 dload (3, 1)
	52 #4 (3, 1)
	53 goto (3, 1)
	54 7 (3, 1)
	56 aload_1 (3, 1)
	57 iload (3, 1)
	58 #6 (3, 1)
	59 daload (3, 1)
	60 dstore (3, 1)
	61 #4 (3, 1)
	62 iinc (3, 1)
	63 #6 (3, 1)
	64 -89 (3, 1)
	65 goto (3, 1)
	66 -42 (3, 1)
	68 dload (1, 1)
	69 #4 (1, 1)
	70 dreturn (1, 1)

Method: copy
	0 aload_0 (0, 0)
	1 invokevirtual (0, 0)
	2 org/apache/commons/math3/stat/descriptive/rank/Max.copy:()Lorg/apache/commons/math3/stat/descriptive/rank/Max; (0, 0)
	4 areturn (0, 0)

