Method: values
	0 getstatic (0, 0)
	1 org/apache/commons/math3/stat/descriptive/rank/Percentile$EstimationType.$VALUES:[Lorg/apache/commons/math3/stat/descriptive/rank/Percentile$EstimationType; (0, 0)
	3 invokevirtual (0, 0)
	4 [Lorg/apache/commons/math3/stat/descriptive/rank/Percentile$EstimationType;.clone:()Ljava/lang/Object; (0, 0)
	6 checkcast (0, 0)
	7 [Lorg/apache/commons/math3/stat/descriptive/rank/Percentile$EstimationType; (0, 0)
	9 areturn (0, 0)

Method: valueOf
	0 ldc (0, 0)
	1 org/apache/commons/math3/stat/descriptive/rank/Percentile$EstimationType (0, 0)
	2 aload_0 (0, 0)
	3 invokestatic (0, 0)
	4 java/lang/Enum.valueOf:(Ljava/lang/Class;Ljava/lang/String;)Ljava/lang/Enum; (0, 0)
	6 checkcast (0, 0)
	7 org/apache/commons/math3/stat/descriptive/rank/Percentile$EstimationType (0, 0)
	9 areturn (0, 0)

Method: <init>
	0 aload_0 (0, 0)
	1 aload_1 (0, 0)
	2 iload_2 (0, 0)
	3 invokespecial (0, 0)
	4 java/lang/Enum.<init>:(Ljava/lang/String;I)V (0, 0)
	6 aload_0 (0, 0)
	7 aload_3 (0, 0)
	8 putfield (0, 0)
	9 org/apache/commons/math3/stat/descriptive/rank/Percentile$EstimationType.name:Ljava/lang/String; (0, 0)
	11 return (0, 0)

Method: estimate
	0 dload_3 (0, 0)
	1 invokestatic (0, 0)
	2 org/apache/commons/math3/util/FastMath.floor:(D)D (0, 0)
	4 dstore (0, 0)
	5 #7 (0, 0)
	6 dload (0, 0)
	7 #7 (0, 0)
	8 d2i (0, 0)
	9 istore (0, 0)
	10 #9 (0, 0)
	11 dload_3 (1, 1)
	12 dload (1, 1)
	13 #7 (1, 1)
	14 dsub (1, 1)
	15 dstore (1, 1)
	16 #10 (1, 1)
	17 dload_3 (2, 1)
	18 dconst_1 (2, 1)
	19 dcmpg (2, 1)
	20 ifge (2, 1)
	21 12 (2, 1)
	23 aload (2, 1)
	24 #6 (2, 1)
	25 aload_1 (2, 1)
	26 aload_2 (2, 1)
	27 iconst_0 (2, 1)
	28 invokevirtual (2, 1)
	29 org/apache/commons/math3/util/KthSelector.select:([D[II)D (2, 1)
	31 dreturn (2, 1)
	32 dload_3 (2, 1)
	33 iload (2, 1)
	34 #5 (2, 1)
	35 i2d (2, 1)
	36 dcmpl (2, 1)
	37 iflt (2, 1)
	38 15 (2, 1)
	40 aload (2, 1)
	41 #6 (2, 1)
	42 aload_1 (2, 1)
	43 aload_2 (2, 1)
	44 iload (2, 1)
	45 #5 (2, 1)
	46 iconst_1 (2, 1)
	47 isub (2, 1)
	48 invokevirtual (2, 1)
	49 org/apache/commons/math3/util/KthSelector.select:([D[II)D (2, 1)
	51 dreturn (2, 1)
	52 aload (1, 1)
	53 #6 (1, 1)
	54 aload_1 (1, 1)
	55 aload_2 (1, 1)
	56 iload (1, 1)
	57 #9 (1, 1)
	58 iconst_1 (1, 1)
	59 isub (1, 1)
	60 invokevirtual (1, 1)
	61 org/apache/commons/math3/util/KthSelector.select:([D[II)D (1, 1)
	63 dstore (1, 1)
	64 #12 (1, 1)
	65 aload (1, 1)
	66 #6 (1, 1)
	67 aload_1 (1, 1)
	68 aload_2 (1, 1)
	69 iload (1, 1)
	70 #9 (1, 1)
	71 invokevirtual (1, 1)
	72 org/apache/commons/math3/util/KthSelector.select:([D[II)D (1, 1)
	74 dstore (1, 1)
	75 #14 (1, 1)
	76 dload (2, 1)
	77 #12 (2, 1)
	78 dload (2, 1)
	79 #10 (2, 1)
	80 dload (2, 1)
	81 #14 (2, 1)
	82 dload (2, 1)
	83 #12 (2, 1)
	84 dsub (2, 1)
	85 dmul (2, 1)
	86 dadd (2, 1)
	87 dreturn (0, 1)

Method: evaluate
	0 aload_0 (0, 0)
	1 aload_1 (0, 0)
	2 aconst_null (0, 0)
	3 dload_2 (0, 0)
	4 aload (0, 0)
	5 #4 (0, 0)
	6 invokevirtual (0, 0)
	7 org/apache/commons/math3/stat/descriptive/rank/Percentile$EstimationType.evaluate:([D[IDLorg/apache/commons/math3/util/KthSelector;)D (0, 0)
	9 dreturn (0, 0)

Method: getName
	0 aload_0 (0, 0)
	1 getfield (0, 0)
	2 org/apache/commons/math3/stat/descriptive/rank/Percentile$EstimationType.name:Ljava/lang/String; (0, 0)
	4 areturn (0, 0)

Method: <clinit>
	0 new (0, 0)
	1 org/apache/commons/math3/stat/descriptive/rank/Percentile$EstimationType$1 (0, 0)
	3 dup (0, 0)
	4 ldc (0, 0)
	5 LEGACY (0, 0)
	6 iconst_0 (0, 0)
	7 ldc (0, 0)
	8 Legacy Apache Commons Math (0, 0)
	9 invokespecial (0, 0)
	10 org/apache/commons/math3/stat/descriptive/rank/Percentile$EstimationType$1.<init>:(Ljava/lang/String;ILjava/lang/String;)V (0, 0)
	12 putstatic (0, 0)
	13 org/apache/commons/math3/stat/descriptive/rank/Percentile$EstimationType.LEGACY:Lorg/apache/commons/math3/stat/descriptive/rank/Percentile$EstimationType; (0, 0)
	15 new (1, 4)
	16 org/apache/commons/math3/stat/descriptive/rank/Percentile$EstimationType$2 (1, 4)
	18 dup (1, 4)
	19 ldc (1, 4)
	20 R_1 (1, 4)
	21 iconst_1 (1, 4)
	22 ldc (1, 4)
	23 R-1 (1, 4)
	24 invokespecial (1, 4)
	25 org/apache/commons/math3/stat/descriptive/rank/Percentile$EstimationType$2.<init>:(Ljava/lang/String;ILjava/lang/String;)V (1, 4)
	27 putstatic (1, 4)
	28 org/apache/commons/math3/stat/descriptive/rank/Percentile$EstimationType.R_1:Lorg/apache/commons/math3/stat/descriptive/rank/Percentile$EstimationType; (1, 4)
	30 new (2, 4)
	31 org/apache/commons/math3/stat/descriptive/rank/Percentile$EstimationType$3 (2, 4)
	33 dup (2, 4)
	34 ldc (2, 4)
	35 R_2 (2, 4)
	36 iconst_2 (2, 4)
	37 ldc (2, 4)
	38 R-2 (2, 4)
	39 invokespecial (2, 4)
	40 org/apache/commons/math3/stat/descriptive/rank/Percentile$EstimationType$3.<init>:(Ljava/lang/String;ILjava/lang/String;)V (2, 4)
	42 putstatic (2, 4)
	43 org/apache/commons/math3/stat/descriptive/rank/Percentile$EstimationType.R_2:Lorg/apache/commons/math3/stat/descriptive/rank/Percentile$EstimationType; (2, 4)
	45 new (3, 4)
	46 org/apache/commons/math3/stat/descriptive/rank/Percentile$EstimationType$4 (3, 4)
	48 dup (3, 4)
	49 ldc (3, 4)
	50 R_3 (3, 4)
	51 iconst_3 (3, 4)
	52 ldc (3, 4)
	53 R-3 (3, 4)
	54 invokespecial (3, 4)
	55 org/apache/commons/math3/stat/descriptive/rank/Percentile$EstimationType$4.<init>:(Ljava/lang/String;ILjava/lang/String;)V (3, 4)
	57 putstatic (3, 4)
	58 org/apache/commons/math3/stat/descriptive/rank/Percentile$EstimationType.R_3:Lorg/apache/commons/math3/stat/descriptive/rank/Percentile$EstimationType; (3, 4)
	60 new (4, 4)
	61 org/apache/commons/math3/stat/descriptive/rank/Percentile$EstimationType$5 (4, 4)
	63 dup (4, 4)
	64 ldc (4, 4)
	65 R_4 (4, 4)
	66 iconst_4 (4, 4)
	67 ldc (4, 4)
	68 R-4 (4, 4)
	69 invokespecial (4, 4)
	70 org/apache/commons/math3/stat/descriptive/rank/Percentile$EstimationType$5.<init>:(Ljava/lang/String;ILjava/lang/String;)V (4, 4)
	72 putstatic (4, 4)
	73 org/apache/commons/math3/stat/descriptive/rank/Percentile$EstimationType.R_4:Lorg/apache/commons/math3/stat/descriptive/rank/Percentile$EstimationType; (4, 4)
	75 new (5, 4)
	76 org/apache/commons/math3/stat/descriptive/rank/Percentile$EstimationType$6 (5, 4)
	78 dup (5, 4)
	79 ldc (5, 4)
	80 R_5 (5, 4)
	81 iconst_5 (5, 4)
	82 ldc (5, 4)
	83 R-5 (5, 4)
	84 invokespecial (5, 4)
	85 org/apache/commons/math3/stat/descriptive/rank/Percentile$EstimationType$6.<init>:(Ljava/lang/String;ILjava/lang/String;)V (5, 4)
	87 putstatic (5, 4)
	88 org/apache/commons/math3/stat/descriptive/rank/Percentile$EstimationType.R_5:Lorg/apache/commons/math3/stat/descriptive/rank/Percentile$EstimationType; (5, 4)
	90 new (7, 1)
	91 org/apache/commons/math3/stat/descriptive/rank/Percentile$EstimationType$7 (7, 1)
	93 dup (7, 1)
	94 ldc (7, 1)
	95 R_6 (7, 1)
	96 bipush (7, 1)
	97 6 (7, 1)
	98 ldc (7, 1)
	99 R-6 (7, 1)
	100 invokespecial (7, 1)
	101 org/apache/commons/math3/stat/descriptive/rank/Percentile$EstimationType$7.<init>:(Ljava/lang/String;ILjava/lang/String;)V (7, 1)
	103 putstatic (7, 1)
	104 org/apache/commons/math3/stat/descriptive/rank/Percentile$EstimationType.R_6:Lorg/apache/commons/math3/stat/descriptive/rank/Percentile$EstimationType; (7, 1)
	106 new (8, 4)
	107 org/apache/commons/math3/stat/descriptive/rank/Percentile$EstimationType$8 (8, 4)
	109 dup (8, 4)
	110 ldc (8, 4)
	111 R_7 (8, 4)
	112 bipush (8, 4)
	113 7 (8, 4)
	114 ldc (8, 4)
	115 R-7 (8, 4)
	116 invokespecial (8, 4)
	117 org/apache/commons/math3/stat/descriptive/rank/Percentile$EstimationType$8.<init>:(Ljava/lang/String;ILjava/lang/String;)V (8, 4)
	119 putstatic (8, 4)
	120 org/apache/commons/math3/stat/descriptive/rank/Percentile$EstimationType.R_7:Lorg/apache/commons/math3/stat/descriptive/rank/Percentile$EstimationType; (8, 4)
	122 new (9, 4)
	123 org/apache/commons/math3/stat/descriptive/rank/Percentile$EstimationType$9 (9, 4)
	125 dup (9, 4)
	126 ldc (9, 4)
	127 R_8 (9, 4)
	128 bipush (9, 4)
	129 8 (9, 4)
	130 ldc (9, 4)
	131 R-8 (9, 4)
	132 invokespecial (9, 4)
	133 org/apache/commons/math3/stat/descriptive/rank/Percentile$EstimationType$9.<init>:(Ljava/lang/String;ILjava/lang/String;)V (9, 4)
	135 putstatic (9, 4)
	136 org/apache/commons/math3/stat/descriptive/rank/Percentile$EstimationType.R_8:Lorg/apache/commons/math3/stat/descriptive/rank/Percentile$EstimationType; (9, 4)
	138 new (10, 4)
	139 org/apache/commons/math3/stat/descriptive/rank/Percentile$EstimationType$10 (10, 4)
	141 dup (10, 4)
	142 ldc (10, 4)
	143 R_9 (10, 4)
	144 bipush (10, 4)
	145 9 (10, 4)
	146 ldc (10, 4)
	147 R-9 (10, 4)
	148 invokespecial (10, 4)
	149 org/apache/commons/math3/stat/descriptive/rank/Percentile$EstimationType$10.<init>:(Ljava/lang/String;ILjava/lang/String;)V (10, 4)
	151 putstatic (10, 4)
	152 org/apache/commons/math3/stat/descriptive/rank/Percentile$EstimationType.R_9:Lorg/apache/commons/math3/stat/descriptive/rank/Percentile$EstimationType; (10, 4)
	154 bipush (10, 4)
	155 10 (10, 4)
	156 anewarray (10, 4)
	157 org/apache/commons/math3/stat/descriptive/rank/Percentile$EstimationType (10, 4)
	159 dup (10, 4)
	160 iconst_0 (10, 4)
	161 getstatic (10, 4)
	162 org/apache/commons/math3/stat/descriptive/rank/Percentile$EstimationType.LEGACY:Lorg/apache/commons/math3/stat/descriptive/rank/Percentile$EstimationType; (10, 4)
	164 aastore (10, 4)
	165 dup (10, 4)
	166 iconst_1 (10, 4)
	167 getstatic (10, 4)
	168 org/apache/commons/math3/stat/descriptive/rank/Percentile$EstimationType.R_1:Lorg/apache/commons/math3/stat/descriptive/rank/Percentile$EstimationType; (10, 4)
	170 aastore (10, 4)
	171 dup (10, 4)
	172 iconst_2 (10, 4)
	173 getstatic (10, 4)
	174 org/apache/commons/math3/stat/descriptive/rank/Percentile$EstimationType.R_2:Lorg/apache/commons/math3/stat/descriptive/rank/Percentile$EstimationType; (10, 4)
	176 aastore (10, 4)
	177 dup (10, 4)
	178 iconst_3 (10, 4)
	179 getstatic (10, 4)
	180 org/apache/commons/math3/stat/descriptive/rank/Percentile$EstimationType.R_3:Lorg/apache/commons/math3/stat/descriptive/rank/Percentile$EstimationType; (10, 4)
	182 aastore (10, 4)
	183 dup (10, 4)
	184 iconst_4 (10, 4)
	185 getstatic (10, 4)
	186 org/apache/commons/math3/stat/descriptive/rank/Percentile$EstimationType.R_4:Lorg/apache/commons/math3/stat/descriptive/rank/Percentile$EstimationType; (10, 4)
	188 aastore (10, 4)
	189 dup (10, 4)
	190 iconst_5 (10, 4)
	191 getstatic (10, 4)
	192 org/apache/commons/math3/stat/descriptive/rank/Percentile$EstimationType.R_5:Lorg/apache/commons/math3/stat/descriptive/rank/Percentile$EstimationType; (10, 4)
	194 aastore (10, 4)
	195 dup (10, 4)
	196 bipush (10, 4)
	197 6 (10, 4)
	198 getstatic (10, 4)
	199 org/apache/commons/math3/stat/descriptive/rank/Percentile$EstimationType.R_6:Lorg/apache/commons/math3/stat/descriptive/rank/Percentile$EstimationType; (10, 4)
	201 aastore (10, 4)
	202 dup (10, 4)
	203 bipush (10, 4)
	204 7 (10, 4)
	205 getstatic (10, 4)
	206 org/apache/commons/math3/stat/descriptive/rank/Percentile$EstimationType.R_7:Lorg/apache/commons/math3/stat/descriptive/rank/Percentile$EstimationType; (10, 4)
	208 aastore (10, 4)
	209 dup (10, 4)
	210 bipush (10, 4)
	211 8 (10, 4)
	212 getstatic (10, 4)
	213 org/apache/commons/math3/stat/descriptive/rank/Percentile$EstimationType.R_8:Lorg/apache/commons/math3/stat/descriptive/rank/Percentile$EstimationType; (10, 4)
	215 aastore (10, 4)
	216 dup (10, 4)
	217 bipush (10, 4)
	218 9 (10, 4)
	219 getstatic (10, 4)
	220 org/apache/commons/math3/stat/descriptive/rank/Percentile$EstimationType.R_9:Lorg/apache/commons/math3/stat/descriptive/rank/Percentile$EstimationType; (10, 4)
	222 aastore (10, 4)
	223 putstatic (10, 4)
	224 org/apache/commons/math3/stat/descriptive/rank/Percentile$EstimationType.$VALUES:[Lorg/apache/commons/math3/stat/descriptive/rank/Percentile$EstimationType; (10, 4)
	226 return (0, 4)

