Method: <init>
	0 aload_0 (0, 0)
	1 invokespecial (0, 0)
	2 org/apache/commons/math3/stat/descriptive/AbstractUnivariateStatistic.<init>:()V (0, 0)
	4 aload_0 (0, 0)
	5 dload_1 (0, 0)
	6 invokevirtual (0, 0)
	7 org/apache/commons/math3/stat/descriptive/rank/Percentile.setQuantile:(D)V (0, 0)
	9 aload_0 (0, 0)
	10 aconst_null (0, 0)
	11 putfield (0, 0)
	12 org/apache/commons/math3/stat/descriptive/rank/Percentile.cachedPivots:[I (0, 0)
	14 aload_3 (0, 0)
	15 invokestatic (0, 0)
	16 org/apache/commons/math3/util/MathUtils.checkNotNull:(Ljava/lang/Object;)V (0, 0)
	18 aload (0, 0)
	19 #4 (0, 0)
	20 invokestatic (0, 0)
	21 org/apache/commons/math3/util/MathUtils.checkNotNull:(Ljava/lang/Object;)V (0, 0)
	23 aload (0, 0)
	24 #5 (0, 0)
	25 invokestatic (0, 0)
	26 org/apache/commons/math3/util/MathUtils.checkNotNull:(Ljava/lang/Object;)V (0, 0)
	28 aload_0 (0, 0)
	29 aload_3 (0, 0)
	30 putfield (0, 0)
	31 org/apache/commons/math3/stat/descriptive/rank/Percentile.estimationType:Lorg/apache/commons/math3/stat/descriptive/rank/Percentile$EstimationType; (0, 0)
	33 aload_0 (0, 0)
	34 aload (0, 0)
	35 #4 (0, 0)
	36 putfield (0, 0)
	37 org/apache/commons/math3/stat/descriptive/rank/Percentile.nanStrategy:Lorg/apache/commons/math3/stat/ranking/NaNStrategy; (0, 0)
	39 aload_0 (0, 0)
	40 aload (0, 0)
	41 #5 (0, 0)
	42 putfield (0, 0)
	43 org/apache/commons/math3/stat/descriptive/rank/Percentile.kthSelector:Lorg/apache/commons/math3/util/KthSelector; (0, 0)
	45 return (0, 0)

Method: setData
	0 aload_1 (1, 1)
	1 ifnonnull (1, 1)
	2 11 (1, 1)
	4 aload_0 (1, 1)
	5 aconst_null (1, 1)
	6 putfield (1, 1)
	7 org/apache/commons/math3/stat/descriptive/rank/Percentile.cachedPivots:[I (1, 1)
	9 goto (1, 1)
	10 20 (1, 1)
	12 aload_0 (2, 2)
	13 sipush (2, 2)
	14 512 (2, 2)
	16 newarray (2, 2)
	17 10 (2, 2)
	18 putfield (2, 2)
	19 org/apache/commons/math3/stat/descriptive/rank/Percentile.cachedPivots:[I (2, 2)
	21 aload_0 (2, 2)
	22 getfield (2, 2)
	23 org/apache/commons/math3/stat/descriptive/rank/Percentile.cachedPivots:[I (2, 2)
	25 iconst_m1 (2, 2)
	26 invokestatic (2, 2)
	27 java/util/Arrays.fill:([II)V (2, 2)
	29 aload_0 (0, 0)
	30 aload_1 (0, 0)
	31 iload_2 (0, 0)
	32 iload_3 (0, 0)
	33 invokespecial (0, 0)
	34 org/apache/commons/math3/stat/descriptive/AbstractUnivariateStatistic.setData:([DII)V (0, 0)
	36 return (0, 0)

Method: evaluate
	0 aload_0 (0, 0)
	1 aload_1 (0, 0)
	2 iload_2 (0, 0)
	3 iload_3 (0, 0)
	4 invokevirtual (0, 0)
	5 org/apache/commons/math3/stat/descriptive/rank/Percentile.test:([DII)Z (0, 0)
	7 pop (0, 0)
	8 dload (1, 1)
	9 #4 (1, 1)
	10 ldc2_w (1, 1)
	11 100.0 (1, 1)
	13 dcmpl (1, 1)
	14 ifgt (1, 1)
	15 10 (1, 1)
	17 dload (1, 1)
	18 #4 (1, 1)
	19 dconst_0 (1, 1)
	20 dcmpg (1, 1)
	21 ifgt (1, 1)
	22 28 (1, 1)
	24 new (1, 1)
	25 org/apache/commons/math3/exception/OutOfRangeException (1, 1)
	27 dup (1, 1)
	28 getstatic (1, 1)
	29 org/apache/commons/math3/exception/util/LocalizedFormats.OUT_OF_BOUNDS_QUANTILE_VALUE:Lorg/apache/commons/math3/exception/util/LocalizedFormats; (1, 1)
	31 dload (1, 1)
	32 #4 (1, 1)
	33 invokestatic (1, 1)
	34 java/lang/Double.valueOf:(D)Ljava/lang/Double; (1, 1)
	36 iconst_0 (1, 1)
	37 invokestatic (1, 1)
	38 java/lang/Integer.valueOf:(I)Ljava/lang/Integer; (1, 1)
	40 bipush (1, 1)
	41 100 (1, 1)
	42 invokestatic (1, 1)
	43 java/lang/Integer.valueOf:(I)Ljava/lang/Integer; (1, 1)
	45 invokespecial (1, 1)
	46 org/apache/commons/math3/exception/OutOfRangeException.<init>:(Lorg/apache/commons/math3/exception/util/Localizable;Ljava/lang/Number;Ljava/lang/Number;Ljava/lang/Number;)V (1, 1)
	48 athrow (1, 1)
	49 iload_3 (1, 1)
	50 ifne (1, 1)
	51 7 (1, 1)
	53 ldc2_w (1, 1)
	54 nan (1, 1)
	56 dreturn (1, 1)
	57 iload_3 (1, 1)
	58 iconst_1 (1, 1)
	59 if_icmpne (1, 1)
	60 7 (1, 1)
	62 aload_1 (2, 4)
	63 iload_2 (2, 4)
	64 daload (2, 4)
	65 dreturn (2, 4)
	66 aload_0 (0, 0)
	67 aload_1 (0, 0)
	68 iload_2 (0, 0)
	69 iload_3 (0, 0)
	70 invokevirtual (0, 0)
	71 org/apache/commons/math3/stat/descriptive/rank/Percentile.getWorkArray:([DII)[D (0, 0)
	73 astore (0, 0)
	74 #6 (0, 0)
	75 aload_0 (0, 0)
	76 aload_1 (0, 0)
	77 invokespecial (0, 0)
	78 org/apache/commons/math3/stat/descriptive/rank/Percentile.getPivots:([D)[I (0, 0)
	80 astore (0, 0)
	81 #7 (0, 0)
	82 aload (0, 0)
	83 #6 (0, 0)
	84 arraylength (0, 0)
	85 ifne (0, 0)
	86 9 (0, 0)
	88 ldc2_w (0, 0)
	89 nan (0, 0)
	91 goto (0, 0)
	92 20 (0, 0)
	94 aload_0 (0, 0)
	95 getfield (0, 0)
	96 org/apache/commons/math3/stat/descriptive/rank/Percentile.estimationType:Lorg/apache/commons/math3/stat/descriptive/rank/Percentile$EstimationType; (0, 0)
	98 aload (0, 0)
	99 #6 (0, 0)
	100 aload (0, 0)
	101 #7 (0, 0)
	102 dload (0, 0)
	103 #4 (0, 0)
	104 aload_0 (0, 0)
	105 getfield (0, 0)
	106 org/apache/commons/math3/stat/descriptive/rank/Percentile.kthSelector:Lorg/apache/commons/math3/util/KthSelector; (0, 0)
	108 invokevirtual (0, 0)
	109 org/apache/commons/math3/stat/descriptive/rank/Percentile$EstimationType.evaluate:([D[IDLorg/apache/commons/math3/util/KthSelector;)D (0, 0)
	111 dreturn (0, 0)

Method: medianOf3
	0 new (0, 0)
	1 org/apache/commons/math3/util/MedianOf3PivotingStrategy (0, 0)
	3 dup (0, 0)
	4 invokespecial (0, 0)
	5 org/apache/commons/math3/util/MedianOf3PivotingStrategy.<init>:()V (0, 0)
	7 aload_1 (0, 0)
	8 iload_2 (0, 0)
	9 iload_3 (0, 0)
	10 invokevirtual (0, 0)
	11 org/apache/commons/math3/util/MedianOf3PivotingStrategy.pivotIndex:([DII)I (0, 0)
	13 ireturn (0, 0)

Method: getQuantile
	0 aload_0 (0, 0)
	1 getfield (0, 0)
	2 org/apache/commons/math3/stat/descriptive/rank/Percentile.quantile:D (0, 0)
	4 dreturn (0, 0)

Method: setQuantile
	0 dload_1 (1, 1)
	1 dconst_0 (1, 1)
	2 dcmpg (1, 1)
	3 ifle (1, 1)
	4 11 (1, 1)
	6 dload_1 (1, 1)
	7 ldc2_w (1, 1)
	8 100.0 (1, 1)
	10 dcmpl (1, 1)
	11 ifle (1, 1)
	12 27 (1, 1)
	14 new (1, 1)
	15 org/apache/commons/math3/exception/OutOfRangeException (1, 1)
	17 dup (1, 1)
	18 getstatic (1, 1)
	19 org/apache/commons/math3/exception/util/LocalizedFormats.OUT_OF_BOUNDS_QUANTILE_VALUE:Lorg/apache/commons/math3/exception/util/LocalizedFormats; (1, 1)
	21 dload_1 (1, 1)
	22 invokestatic (1, 1)
	23 java/lang/Double.valueOf:(D)Ljava/lang/Double; (1, 1)
	25 iconst_0 (1, 1)
	26 invokestatic (1, 1)
	27 java/lang/Integer.valueOf:(I)Ljava/lang/Integer; (1, 1)
	29 bipush (1, 1)
	30 100 (1, 1)
	31 invokestatic (1, 1)
	32 java/lang/Integer.valueOf:(I)Ljava/lang/Integer; (1, 1)
	34 invokespecial (1, 1)
	35 org/apache/commons/math3/exception/OutOfRangeException.<init>:(Lorg/apache/commons/math3/exception/util/Localizable;Ljava/lang/Number;Ljava/lang/Number;Ljava/lang/Number;)V (1, 1)
	37 athrow (1, 1)
	38 aload_0 (0, 0)
	39 dload_1 (0, 0)
	40 putfield (0, 0)
	41 org/apache/commons/math3/stat/descriptive/rank/Percentile.quantile:D (0, 0)
	43 return (0, 0)

Method: copy
	0 aload_0 (0, 0)
	1 invokevirtual (0, 0)
	2 org/apache/commons/math3/stat/descriptive/rank/Percentile.copy:()Lorg/apache/commons/math3/stat/descriptive/rank/Percentile; (0, 0)
	4 areturn (0, 0)

Method: getWorkArray
	0 aload_1 (1, 1)
	1 aload_0 (1, 1)
	2 invokevirtual (1, 1)
	3 org/apache/commons/math3/stat/descriptive/rank/Percentile.getDataRef:()[D (1, 1)
	5 if_acmpne (1, 1)
	6 12 (1, 1)
	8 aload_0 (1, 1)
	9 invokevirtual (1, 1)
	10 org/apache/commons/math3/stat/descriptive/rank/Percentile.getDataRef:()[D (1, 1)
	12 astore (1, 1)
	13 #4 (1, 1)
	14 goto (1, 1)
	15 118 (1, 1)
	17 getstatic (3, 5)
	18 org/apache/commons/math3/stat/descriptive/rank/Percentile$1.$SwitchMap$org$apache$commons$math3$stat$ranking$NaNStrategy:[I (3, 5)
	20 aload_0 (3, 5)
	21 getfield (3, 5)
	22 org/apache/commons/math3/stat/descriptive/rank/Percentile.nanStrategy:Lorg/apache/commons/math3/stat/ranking/NaNStrategy; (3, 5)
	24 invokevirtual (3, 5)
	25 org/apache/commons/math3/stat/ranking/NaNStrategy.ordinal:()I (3, 5)
	27 iaload (3, 5)
	28 tableswitch (3, 5)
	29 1 60 (3, 5)
	33 2 77 (3, 5)
	37 3 94 (3, 5)
	41 4 108 (3, 5)
	60 aload_1 (3, 5)
	61 iload_2 (3, 5)
	62 iload_3 (3, 5)
	63 ldc2_w (3, 5)
	64 nan (3, 5)
	66 ldc2_w (3, 5)
	67 inf (3, 5)
	69 invokestatic (3, 5)
	70 org/apache/commons/math3/stat/descriptive/rank/Percentile.replaceAndSlice:([DIIDD)[D (3, 5)
	72 astore (3, 5)
	73 #4 (3, 5)
	74 goto (3, 5)
	75 58 (3, 5)
	77 aload_1 (3, 5)
	78 iload_2 (3, 5)
	79 iload_3 (3, 5)
	80 ldc2_w (3, 5)
	81 nan (3, 5)
	83 ldc2_w (3, 5)
	84 -inf (3, 5)
	86 invokestatic (3, 5)
	87 org/apache/commons/math3/stat/descriptive/rank/Percentile.replaceAndSlice:([DIIDD)[D (3, 5)
	89 astore (3, 5)
	90 #4 (3, 5)
	91 goto (3, 5)
	92 41 (3, 5)
	94 aload_1 (3, 5)
	95 iload_2 (3, 5)
	96 iload_3 (3, 5)
	97 ldc2_w (3, 5)
	98 nan (3, 5)
	100 invokestatic (3, 5)
	101 org/apache/commons/math3/stat/descriptive/rank/Percentile.removeAndSlice:([DIID)[D (3, 5)
	103 astore (3, 5)
	104 #4 (3, 5)
	105 goto (3, 5)
	106 27 (3, 5)
	108 aload_1 (3, 5)
	109 iload_2 (3, 5)
	110 iload_3 (3, 5)
	111 invokestatic (3, 5)
	112 org/apache/commons/math3/stat/descriptive/rank/Percentile.copyOf:([DII)[D (3, 5)
	114 astore (3, 5)
	115 #4 (3, 5)
	116 aload (3, 5)
	117 #4 (3, 5)
	118 invokestatic (3, 5)
	119 org/apache/commons/math3/util/MathArrays.checkNotNaN:([D)V (3, 5)
	121 goto (3, 5)
	122 11 (3, 5)
	124 aload_1 (3, 5)
	125 iload_2 (3, 5)
	126 iload_3 (3, 5)
	127 invokestatic (3, 5)
	128 org/apache/commons/math3/stat/descriptive/rank/Percentile.copyOf:([DII)[D (3, 5)
	130 astore (3, 5)
	131 #4 (3, 5)
	132 aload (0, 0)
	133 #4 (0, 0)
	134 areturn (0, 0)

Method: copyOf
	0 aload_0 (1, 1)
	1 iload_1 (1, 1)
	2 iload_2 (1, 1)
	3 invokestatic (1, 1)
	4 org/apache/commons/math3/util/MathArrays.verifyValues:([DII)Z (1, 1)
	6 pop (1, 1)
	7 aload_0 (1, 1)
	8 iload_1 (1, 1)
	9 iload_1 (1, 1)
	10 iload_2 (1, 1)
	11 iadd (1, 1)
	12 invokestatic (1, 1)
	13 org/apache/commons/math3/util/MathArrays.copyOfRange:([DII)[D (1, 1)
	15 areturn (0, 1)

Method: replaceAndSlice
	0 aload_0 (0, 0)
	1 iload_1 (0, 0)
	2 iload_2 (0, 0)
	3 invokestatic (0, 0)
	4 org/apache/commons/math3/stat/descriptive/rank/Percentile.copyOf:([DII)[D (0, 0)
	6 astore (0, 0)
	7 #7 (0, 0)
	8 iconst_0 (1, 4)
	9 istore (1, 4)
	10 #8 (1, 4)
	11 iload (1, 4)
	12 #8 (1, 4)
	13 iload_2 (1, 4)
	14 if_icmpge (1, 4)
	15 36 (1, 4)
	17 aload (1, 4)
	18 #7 (1, 4)
	19 iload (1, 4)
	20 #8 (1, 4)
	21 dload_3 (1, 4)
	22 aload (1, 4)
	23 #7 (1, 4)
	24 iload (1, 4)
	25 #8 (1, 4)
	26 daload (1, 4)
	27 invokestatic (1, 4)
	28 org/apache/commons/math3/util/Precision.equalsIncludingNaN:(DD)Z (1, 4)
	30 ifeq (1, 4)
	31 8 (1, 4)
	33 dload (1, 4)
	34 #5 (1, 4)
	35 goto (1, 4)
	36 8 (1, 4)
	38 aload (1, 4)
	39 #7 (1, 4)
	40 iload (1, 4)
	41 #8 (1, 4)
	42 daload (1, 4)
	43 dastore (1, 4)
	44 iinc (1, 4)
	45 #8 (1, 4)
	46 -89 (1, 4)
	47 goto (1, 4)
	48 -36 (1, 4)
	50 aload (0, 0)
	51 #7 (0, 0)
	52 areturn (0, 0)

Method: removeAndSlice
	0 aload_0 (1, 1)
	1 iload_1 (1, 1)
	2 iload_2 (1, 1)
	3 invokestatic (1, 1)
	4 org/apache/commons/math3/util/MathArrays.verifyValues:([DII)Z (1, 1)
	6 pop (1, 1)
	7 new (1, 1)
	8 java/util/BitSet (1, 1)
	10 dup (1, 1)
	11 iload_2 (1, 1)
	12 invokespecial (1, 1)
	13 java/util/BitSet.<init>:(I)V (1, 1)
	15 astore (1, 1)
	16 #6 (1, 1)
	17 iload_1 (2, 4)
	18 istore (2, 4)
	19 #7 (2, 4)
	20 iload (2, 4)
	21 #7 (2, 4)
	22 iload_1 (2, 4)
	23 iload_2 (2, 4)
	24 iadd (2, 4)
	25 if_icmpge (2, 4)
	26 29 (2, 4)
	28 dload_3 (3, 1)
	29 aload_0 (3, 1)
	30 iload (3, 1)
	31 #7 (3, 1)
	32 daload (3, 1)
	33 invokestatic (3, 1)
	34 org/apache/commons/math3/util/Precision.equalsIncludingNaN:(DD)Z (3, 1)
	36 ifeq (3, 1)
	37 12 (3, 1)
	39 aload (3, 1)
	40 #6 (3, 1)
	41 iload (3, 1)
	42 #7 (3, 1)
	43 iload_1 (3, 1)
	44 isub (3, 1)
	45 invokevirtual (3, 1)
	46 java/util/BitSet.set:(I)V (3, 1)
	48 iinc (3, 1)
	49 #7 (3, 1)
	50 -89 (3, 1)
	51 goto (3, 1)
	52 -31 (3, 1)
	54 aload (4, 1)
	55 #6 (4, 1)
	56 invokevirtual (4, 1)
	57 java/util/BitSet.isEmpty:()Z (4, 1)
	59 ifeq (4, 1)
	60 14 (4, 1)
	62 aload_0 (4, 1)
	63 iload_1 (4, 1)
	64 iload_2 (4, 1)
	65 invokestatic (4, 1)
	66 org/apache/commons/math3/stat/descriptive/rank/Percentile.copyOf:([DII)[D (4, 1)
	68 astore (4, 1)
	69 #5 (4, 1)
	70 goto (4, 1)
	71 124 (4, 1)
	73 aload (5, 1)
	74 #6 (5, 1)
	75 invokevirtual (5, 1)
	76 java/util/BitSet.cardinality:()I (5, 1)
	78 iload_2 (5, 1)
	79 if_icmpne (5, 1)
	80 11 (5, 1)
	82 iconst_0 (5, 1)
	83 newarray (5, 1)
	84 7 (5, 1)
	85 astore (5, 1)
	86 #5 (5, 1)
	87 goto (5, 1)
	88 107 (5, 1)
	90 iload_2 (6, 2)
	91 aload (6, 2)
	92 #6 (6, 2)
	93 invokevirtual (6, 2)
	94 java/util/BitSet.cardinality:()I (6, 2)
	96 isub (6, 2)
	97 newarray (6, 2)
	98 7 (6, 2)
	99 astore (6, 2)
	100 #5 (6, 2)
	101 iload_1 (6, 2)
	102 istore (6, 2)
	103 #7 (6, 2)
	104 iconst_0 (6, 2)
	105 istore (6, 2)
	106 #8 (6, 2)
	107 iconst_m1 (6, 2)
	108 istore (6, 2)
	109 #9 (6, 2)
	110 iconst_0 (6, 2)
	111 istore (6, 2)
	112 #10 (6, 2)
	113 aload (7, 3)
	114 #6 (7, 3)
	115 iload (7, 3)
	116 #10 (7, 3)
	117 invokevirtual (7, 3)
	118 java/util/BitSet.nextSetBit:(I)I (7, 3)
	120 dup (7, 3)
	121 istore (7, 3)
	122 #9 (7, 3)
	123 iconst_m1 (7, 3)
	124 if_icmpeq (7, 3)
	125 46 (7, 3)
	127 iload (7, 3)
	128 #9 (7, 3)
	129 iload (7, 3)
	130 #10 (7, 3)
	131 isub (7, 3)
	132 istore (7, 3)
	133 #11 (7, 3)
	134 aload_0 (7, 3)
	135 iload (7, 3)
	136 #7 (7, 3)
	137 aload (7, 3)
	138 #5 (7, 3)
	139 iload (7, 3)
	140 #8 (7, 3)
	141 iload (7, 3)
	142 #11 (7, 3)
	143 invokestatic (7, 3)
	144 java/lang/System.arraycopy:(Ljava/lang/Object;ILjava/lang/Object;II)V (7, 3)
	146 iload (7, 3)
	147 #8 (7, 3)
	148 iload (7, 3)
	149 #11 (7, 3)
	150 iadd (7, 3)
	151 istore (7, 3)
	152 #8 (7, 3)
	153 iload_1 (7, 3)
	154 aload (7, 3)
	155 #6 (7, 3)
	156 iload (7, 3)
	157 #9 (7, 3)
	158 invokevirtual (7, 3)
	159 java/util/BitSet.nextClearBit:(I)I (7, 3)
	161 dup (7, 3)
	162 istore (7, 3)
	163 #10 (7, 3)
	164 iadd (7, 3)
	165 istore (7, 3)
	166 #7 (7, 3)
	167 goto (6, 2)
	168 -54 (6, 2)
	170 iload (7, 1)
	171 #7 (7, 1)
	172 iload_1 (7, 1)
	173 iload_2 (7, 1)
	174 iadd (7, 1)
	175 if_icmpge (7, 1)
	176 19 (7, 1)
	178 aload_0 (7, 1)
	179 iload (7, 1)
	180 #7 (7, 1)
	181 aload (7, 1)
	182 #5 (7, 1)
	183 iload (7, 1)
	184 #8 (7, 1)
	185 iload_1 (7, 1)
	186 iload_2 (7, 1)
	187 iadd (7, 1)
	188 iload (7, 1)
	189 #7 (7, 1)
	190 isub (7, 1)
	191 invokestatic (7, 1)
	192 java/lang/System.arraycopy:(Ljava/lang/Object;ILjava/lang/Object;II)V (7, 1)
	194 aload (3, 1)
	195 #5 (3, 1)
	196 areturn (1, 1)

Method: getPivots
	0 aload_1 (1, 1)
	1 aload_0 (1, 1)
	2 invokevirtual (1, 1)
	3 org/apache/commons/math3/stat/descriptive/rank/Percentile.getDataRef:()[D (1, 1)
	5 if_acmpne (1, 1)
	6 11 (1, 1)
	8 aload_0 (1, 1)
	9 getfield (1, 1)
	10 org/apache/commons/math3/stat/descriptive/rank/Percentile.cachedPivots:[I (1, 1)
	12 astore_2 (1, 1)
	13 goto (1, 1)
	14 14 (1, 1)
	16 sipush (2, 2)
	17 512 (2, 2)
	19 newarray (2, 2)
	20 10 (2, 2)
	21 astore_2 (2, 2)
	22 aload_2 (2, 2)
	23 iconst_m1 (2, 2)
	24 invokestatic (2, 2)
	25 java/util/Arrays.fill:([II)V (2, 2)
	27 aload_2 (0, 0)
	28 areturn (0, 0)

Method: getEstimationType
	0 aload_0 (0, 0)
	1 getfield (0, 0)
	2 org/apache/commons/math3/stat/descriptive/rank/Percentile.estimationType:Lorg/apache/commons/math3/stat/descriptive/rank/Percentile$EstimationType; (0, 0)
	4 areturn (0, 0)

Method: withEstimationType
	0 new (0, 0)
	1 org/apache/commons/math3/stat/descriptive/rank/Percentile (0, 0)
	3 dup (0, 0)
	4 aload_0 (0, 0)
	5 getfield (0, 0)
	6 org/apache/commons/math3/stat/descriptive/rank/Percentile.quantile:D (0, 0)
	8 aload_1 (0, 0)
	9 aload_0 (0, 0)
	10 getfield (0, 0)
	11 org/apache/commons/math3/stat/descriptive/rank/Percentile.nanStrategy:Lorg/apache/commons/math3/stat/ranking/NaNStrategy; (0, 0)
	13 aload_0 (0, 0)
	14 getfield (0, 0)
	15 org/apache/commons/math3/stat/descriptive/rank/Percentile.kthSelector:Lorg/apache/commons/math3/util/KthSelector; (0, 0)
	17 invokespecial (0, 0)
	18 org/apache/commons/math3/stat/descriptive/rank/Percentile.<init>:(DLorg/apache/commons/math3/stat/descriptive/rank/Percentile$EstimationType;Lorg/apache/commons/math3/stat/ranking/NaNStrategy;Lorg/apache/commons/math3/util/KthSelector;)V (0, 0)
	20 areturn (0, 0)

Method: getNaNStrategy
	0 aload_0 (0, 0)
	1 getfield (0, 0)
	2 org/apache/commons/math3/stat/descriptive/rank/Percentile.nanStrategy:Lorg/apache/commons/math3/stat/ranking/NaNStrategy; (0, 0)
	4 areturn (0, 0)

Method: withNaNStrategy
	0 new (0, 0)
	1 org/apache/commons/math3/stat/descriptive/rank/Percentile (0, 0)
	3 dup (0, 0)
	4 aload_0 (0, 0)
	5 getfield (0, 0)
	6 org/apache/commons/math3/stat/descriptive/rank/Percentile.quantile:D (0, 0)
	8 aload_0 (0, 0)
	9 getfield (0, 0)
	10 org/apache/commons/math3/stat/descriptive/rank/Percentile.estimationType:Lorg/apache/commons/math3/stat/descriptive/rank/Percentile$EstimationType; (0, 0)
	12 aload_1 (0, 0)
	13 aload_0 (0, 0)
	14 getfield (0, 0)
	15 org/apache/commons/math3/stat/descriptive/rank/Percentile.kthSelector:Lorg/apache/commons/math3/util/KthSelector; (0, 0)
	17 invokespecial (0, 0)
	18 org/apache/commons/math3/stat/descriptive/rank/Percentile.<init>:(DLorg/apache/commons/math3/stat/descriptive/rank/Percentile$EstimationType;Lorg/apache/commons/math3/stat/ranking/NaNStrategy;Lorg/apache/commons/math3/util/KthSelector;)V (0, 0)
	20 areturn (0, 0)

Method: getKthSelector
	0 aload_0 (0, 0)
	1 getfield (0, 0)
	2 org/apache/commons/math3/stat/descriptive/rank/Percentile.kthSelector:Lorg/apache/commons/math3/util/KthSelector; (0, 0)
	4 areturn (0, 0)

Method: getPivotingStrategy
	0 aload_0 (0, 0)
	1 getfield (0, 0)
	2 org/apache/commons/math3/stat/descriptive/rank/Percentile.kthSelector:Lorg/apache/commons/math3/util/KthSelector; (0, 0)
	4 invokevirtual (0, 0)
	5 org/apache/commons/math3/util/KthSelector.getPivotingStrategy:()Lorg/apache/commons/math3/util/PivotingStrategyInterface; (0, 0)
	7 areturn (0, 0)

Method: withKthSelector
	0 new (0, 0)
	1 org/apache/commons/math3/stat/descriptive/rank/Percentile (0, 0)
	3 dup (0, 0)
	4 aload_0 (0, 0)
	5 getfield (0, 0)
	6 org/apache/commons/math3/stat/descriptive/rank/Percentile.quantile:D (0, 0)
	8 aload_0 (0, 0)
	9 getfield (0, 0)
	10 org/apache/commons/math3/stat/descriptive/rank/Percentile.estimationType:Lorg/apache/commons/math3/stat/descriptive/rank/Percentile$EstimationType; (0, 0)
	12 aload_0 (0, 0)
	13 getfield (0, 0)
	14 org/apache/commons/math3/stat/descriptive/rank/Percentile.nanStrategy:Lorg/apache/commons/math3/stat/ranking/NaNStrategy; (0, 0)
	16 aload_1 (0, 0)
	17 invokespecial (0, 0)
	18 org/apache/commons/math3/stat/descriptive/rank/Percentile.<init>:(DLorg/apache/commons/math3/stat/descriptive/rank/Percentile$EstimationType;Lorg/apache/commons/math3/stat/ranking/NaNStrategy;Lorg/apache/commons/math3/util/KthSelector;)V (0, 0)
	20 areturn (0, 0)

