Method: index
	0 dconst_0 (0, 0)
	1 dstore (0, 0)
	2 #4 (0, 0)
	3 dconst_1 (0, 0)
	4 dstore (0, 0)
	5 #6 (0, 0)
	6 dload_1 (0, 0)
	7 dconst_1 (0, 0)
	8 invokestatic (0, 0)
	9 java/lang/Double.compare:(DD)I (0, 0)
	11 ifne (0, 0)
	12 8 (0, 0)
	14 iload_3 (0, 0)
	15 i2d (0, 0)
	16 goto (0, 0)
	17 23 (0, 0)
	19 dload_1 (0, 0)
	20 dconst_0 (0, 0)
	21 invokestatic (0, 0)
	22 java/lang/Double.compare:(DD)I (0, 0)
	24 ifne (0, 0)
	25 7 (0, 0)
	27 dconst_0 (0, 0)
	28 goto (0, 0)
	29 11 (0, 0)
	31 iload_3 (0, 0)
	32 i2d (0, 0)
	33 dload_1 (0, 0)
	34 dmul (0, 0)
	35 ldc2_w (0, 0)
	36 0.5 (0, 0)
	38 dadd (0, 0)
	39 dreturn (0, 0)

Method: estimate
	0 aload_0 (0, 0)
	1 aload_1 (0, 0)
	2 aload_2 (0, 0)
	3 dload_3 (0, 0)
	4 ldc2_w (0, 0)
	5 0.5 (0, 0)
	7 dsub (0, 0)
	8 invokestatic (0, 0)
	9 org/apache/commons/math3/util/FastMath.ceil:(D)D (0, 0)
	11 iload (0, 0)
	12 #5 (0, 0)
	13 aload (0, 0)
	14 #6 (0, 0)
	15 invokespecial (0, 0)
	16 org/apache/commons/math3/stat/descriptive/rank/Percentile$EstimationType.estimate:([D[IDILorg/apache/commons/math3/util/KthSelector;)D (0, 0)
	18 dstore (0, 0)
	19 #7 (0, 0)
	20 aload_0 (0, 0)
	21 aload_1 (0, 0)
	22 aload_2 (0, 0)
	23 dload_3 (0, 0)
	24 ldc2_w (0, 0)
	25 0.5 (0, 0)
	27 dadd (0, 0)
	28 invokestatic (0, 0)
	29 org/apache/commons/math3/util/FastMath.floor:(D)D (0, 0)
	31 iload (0, 0)
	32 #5 (0, 0)
	33 aload (0, 0)
	34 #6 (0, 0)
	35 invokespecial (0, 0)
	36 org/apache/commons/math3/stat/descriptive/rank/Percentile$EstimationType.estimate:([D[IDILorg/apache/commons/math3/util/KthSelector;)D (0, 0)
	38 dstore (0, 0)
	39 #9 (0, 0)
	40 dload (0, 0)
	41 #7 (0, 0)
	42 dload (0, 0)
	43 #9 (0, 0)
	44 dadd (0, 0)
	45 ldc2_w (0, 0)
	46 2.0 (0, 0)
	48 ddiv (0, 0)
	49 dreturn (0, 0)

