Method: <init>
	0 aload_0 (0, 0)
	1 invokespecial (0, 0)
	4 aload_0 (0, 0)
	5 dload_1 (0, 0)
	6 invokevirtual (0, 0)
	9 aload_0 (0, 0)
	10 aconst_null (0, 0)
	11 putfield (0, 0)
	14 aload_3 (0, 0)
	15 invokestatic (0, 0)
	18 aload (0, 0)
	20 invokestatic (0, 0)
	23 aload (0, 0)
	25 invokestatic (0, 0)
	28 aload_0 (0, 0)
	29 aload_3 (0, 0)
	30 putfield (0, 0)
	33 aload_0 (0, 0)
	34 aload (0, 0)
	36 putfield (0, 0)
	39 aload_0 (0, 0)
	40 aload (0, 0)
	42 putfield (0, 0)
	45 return (0, 0)

Method: setData
	0 aload_1 (1, 1)
	1 ifnonnull (1, 1)
	4 aload_0 (1, 1)
	5 aconst_null (1, 1)
	6 putfield (1, 1)
	9 goto (1, 1)
	12 aload_0 (1, 2)
	13 sipush (1, 2)
	16 newarray (1, 2)
	18 putfield (1, 2)
	21 aload_0 (1, 2)
	22 getfield (1, 2)
	25 iconst_m1 (1, 2)
	26 invokestatic (1, 2)
	29 aload_0 (0, 1)
	30 aload_1 (0, 1)
	31 iload_2 (0, 1)
	32 iload_3 (0, 1)
	33 invokespecial (0, 1)
	36 return (0, 0)

Method: evaluate
	0 aload_0 (0, 0)
	1 aload_1 (0, 0)
	2 iload_2 (0, 0)
	3 iload_3 (0, 0)
	4 invokevirtual (0, 0)
	7 pop (0, 0)
	8 dload (1, 1)
	10 ldc2_w (1, 1)
	13 dcmpl (1, 1)
	14 ifgt (1, 1)
	17 dload (1, 1)
	19 dconst_0 (1, 1)
	20 dcmpg (1, 1)
	21 ifgt (1, 1)
	24 new (1, 1)
	27 dup (1, 1)
	28 getstatic (1, 1)
	31 dload (1, 1)
	33 invokestatic (1, 1)
	36 iconst_0 (1, 1)
	37 invokestatic (1, 1)
	40 bipush (1, 1)
	42 invokestatic (1, 1)
	45 invokespecial (1, 1)
	48 athrow (1, 1)
	49 iload_3 (1, 1)
	50 ifne (1, 1)
	53 ldc2_w (1, 1)
	56 dreturn (1, 1)
	57 iload_3 (1, 1)
	58 iconst_1 (1, 1)
	59 if_icmpne (1, 1)
	62 aload_1 (1, 4)
	63 iload_2 (1, 4)
	64 daload (1, 4)
	65 dreturn (1, 4)
	66 aload_0 (0, 1)
	67 aload_1 (0, 1)
	68 iload_2 (0, 1)
	69 iload_3 (0, 1)
	70 invokevirtual (0, 1)
	73 astore (0, 1)
	75 aload_0 (0, 1)
	76 aload_1 (0, 1)
	77 invokespecial (0, 1)
	80 astore (0, 1)
	82 aload (0, 1)
	84 arraylength (0, 1)
	85 ifne (0, 1)
	88 ldc2_w (0, 1)
	91 goto (0, 1)
	94 aload_0 (0, 1)
	95 getfield (0, 1)
	98 aload (0, 1)
	100 aload (0, 1)
	102 dload (0, 1)
	104 aload_0 (0, 1)
	105 getfield (0, 1)
	108 invokevirtual (0, 1)
	111 dreturn (0, 1)

Method: medianOf3
	0 new (0, 0)
	3 dup (0, 0)
	4 invokespecial (0, 0)
	7 aload_1 (0, 0)
	8 iload_2 (0, 0)
	9 iload_3 (0, 0)
	10 invokevirtual (0, 0)
	13 ireturn (0, 0)

Method: getQuantile
	0 aload_0 (0, 0)
	1 getfield (0, 0)
	4 dreturn (0, 0)

Method: setQuantile
	0 dload_1 (1, 1)
	1 dconst_0 (1, 1)
	2 dcmpg (1, 1)
	3 ifle (1, 1)
	6 dload_1 (1, 1)
	7 ldc2_w (1, 1)
	10 dcmpl (1, 1)
	11 ifle (1, 1)
	14 new (1, 1)
	17 dup (1, 1)
	18 getstatic (1, 1)
	21 dload_1 (1, 1)
	22 invokestatic (1, 1)
	25 iconst_0 (1, 1)
	26 invokestatic (1, 1)
	29 bipush (1, 1)
	31 invokestatic (1, 1)
	34 invokespecial (1, 1)
	37 athrow (1, 1)
	38 aload_0 (0, 0)
	39 dload_1 (0, 0)
	40 putfield (0, 0)
	43 return (0, 0)

Method: copy
	0 aload_0 (0, 0)
	1 invokevirtual (0, 0)
	4 areturn (0, 0)

Method: getWorkArray
	0 aload_1 (1, 1)
	1 aload_0 (1, 1)
	2 invokevirtual (1, 1)
	5 if_acmpne (1, 1)
	8 aload_0 (1, 1)
	9 invokevirtual (1, 1)
	12 astore (1, 1)
	14 goto (1, 1)
	17 getstatic (2, 5)
	20 aload_0 (2, 5)
	21 getfield (2, 5)
	24 invokevirtual (2, 5)
	27 iaload (2, 5)
	28 tableswitch (2, 5)
	60 aload_1 (2, 5)
	61 iload_2 (2, 5)
	62 iload_3 (2, 5)
	63 ldc2_w (2, 5)
	66 ldc2_w (2, 5)
	69 invokestatic (2, 5)
	72 astore (2, 5)
	74 goto (2, 5)
	77 aload_1 (2, 5)
	78 iload_2 (2, 5)
	79 iload_3 (2, 5)
	80 ldc2_w (2, 5)
	83 ldc2_w (2, 5)
	86 invokestatic (2, 5)
	89 astore (2, 5)
	91 goto (2, 5)
	94 aload_1 (2, 5)
	95 iload_2 (2, 5)
	96 iload_3 (2, 5)
	97 ldc2_w (2, 5)
	100 invokestatic (2, 5)
	103 astore (2, 5)
	105 goto (2, 5)
	108 aload_1 (2, 5)
	109 iload_2 (2, 5)
	110 iload_3 (2, 5)
	111 invokestatic (2, 5)
	114 astore (2, 5)
	116 aload (2, 5)
	118 invokestatic (2, 5)
	121 goto (2, 5)
	124 aload_1 (2, 5)
	125 iload_2 (2, 5)
	126 iload_3 (2, 5)
	127 invokestatic (2, 5)
	130 astore (2, 5)
	132 aload (0, 1)
	134 areturn (0, 1)

Method: copyOf
	0 aload_0 (0, 1)
	1 iload_1 (0, 1)
	2 iload_2 (0, 1)
	3 invokestatic (0, 1)
	6 pop (0, 1)
	7 aload_0 (0, 1)
	8 iload_1 (0, 1)
	9 iload_1 (0, 1)
	10 iload_2 (0, 1)
	11 iadd (0, 1)
	12 invokestatic (0, 1)
	15 areturn (0, 1)

Method: replaceAndSlice
	0 aload_0 (0, 0)
	1 iload_1 (0, 0)
	2 iload_2 (0, 0)
	3 invokestatic (0, 0)
	6 astore (0, 0)
	8 iconst_0 (1, 4)
	9 istore (1, 4)
	11 iload (1, 4)
	13 iload_2 (1, 4)
	14 if_icmpge (1, 4)
	17 aload (1, 4)
	19 iload (1, 4)
	21 dload_3 (1, 4)
	22 aload (1, 4)
	24 iload (1, 4)
	26 daload (1, 4)
	27 invokestatic (1, 4)
	30 ifeq (1, 4)
	33 dload (1, 4)
	35 goto (1, 4)
	38 aload (1, 4)
	40 iload (1, 4)
	42 daload (1, 4)
	43 dastore (1, 4)
	44 iinc (1, 4)
	47 goto (1, 4)
	50 aload (0, 0)
	52 areturn (0, 0)

Method: removeAndSlice
	0 aload_0 (0, 1)
	1 iload_1 (0, 1)
	2 iload_2 (0, 1)
	3 invokestatic (0, 1)
	6 pop (0, 1)
	7 new (0, 1)
	10 dup (0, 1)
	11 iload_2 (0, 1)
	12 invokespecial (0, 1)
	15 astore (0, 1)
	17 iload_1 (1, 4)
	18 istore (1, 4)
	20 iload (1, 4)
	22 iload_1 (1, 4)
	23 iload_2 (1, 4)
	24 iadd (1, 4)
	25 if_icmpge (1, 4)
	28 dload_3 (2, 1)
	29 aload_0 (2, 1)
	30 iload (2, 1)
	32 daload (2, 1)
	33 invokestatic (2, 1)
	36 ifeq (2, 1)
	39 aload (2, 1)
	41 iload (2, 1)
	43 iload_1 (2, 1)
	44 isub (2, 1)
	45 invokevirtual (2, 1)
	48 iinc (2, 1)
	51 goto (2, 1)
	54 aload (2, 1)
	56 invokevirtual (2, 1)
	59 ifeq (2, 1)
	62 aload_0 (2, 1)
	63 iload_1 (2, 1)
	64 iload_2 (2, 1)
	65 invokestatic (2, 1)
	68 astore (2, 1)
	70 goto (2, 1)
	73 aload (2, 1)
	75 invokevirtual (2, 1)
	78 iload_2 (2, 1)
	79 if_icmpne (2, 1)
	82 iconst_0 (2, 1)
	83 newarray (2, 1)
	85 astore (2, 1)
	87 goto (2, 1)
	90 iload_2 (2, 2)
	91 aload (2, 2)
	93 invokevirtual (2, 2)
	96 isub (2, 2)
	97 newarray (2, 2)
	99 astore (2, 2)
	101 iload_1 (2, 2)
	102 istore (2, 2)
	104 iconst_0 (2, 2)
	105 istore (2, 2)
	107 iconst_m1 (2, 2)
	108 istore (2, 2)
	110 iconst_0 (2, 2)
	111 istore (2, 2)
	113 aload (3, 3)
	115 iload (3, 3)
	117 invokevirtual (3, 3)
	120 dup (3, 3)
	121 istore (3, 3)
	123 iconst_m1 (3, 3)
	124 if_icmpeq (3, 3)
	127 iload (3, 3)
	129 iload (3, 3)
	131 isub (3, 3)
	132 istore (3, 3)
	134 aload_0 (3, 3)
	135 iload (3, 3)
	137 aload (3, 3)
	139 iload (3, 3)
	141 iload (3, 3)
	143 invokestatic (3, 3)
	146 iload (3, 3)
	148 iload (3, 3)
	150 iadd (3, 3)
	151 istore (3, 3)
	153 iload_1 (3, 3)
	154 aload (3, 3)
	156 iload (3, 3)
	158 invokevirtual (3, 3)
	161 dup (3, 3)
	162 istore (3, 3)
	164 iadd (3, 3)
	165 istore (3, 3)
	167 goto (2, 2)
	170 iload (3, 1)
	172 iload_1 (3, 1)
	173 iload_2 (3, 1)
	174 iadd (3, 1)
	175 if_icmpge (3, 1)
	178 aload_0 (3, 1)
	179 iload (3, 1)
	181 aload (3, 1)
	183 iload (3, 1)
	185 iload_1 (3, 1)
	186 iload_2 (3, 1)
	187 iadd (3, 1)
	188 iload (3, 1)
	190 isub (3, 1)
	191 invokestatic (3, 1)
	194 aload (1, 1)
	196 areturn (1, 1)

Method: getPivots
	0 aload_1 (1, 1)
	1 aload_0 (1, 1)
	2 invokevirtual (1, 1)
	5 if_acmpne (1, 1)
	8 aload_0 (1, 1)
	9 getfield (1, 1)
	12 astore_2 (1, 1)
	13 goto (1, 1)
	16 sipush (1, 2)
	19 newarray (1, 2)
	21 astore_2 (1, 2)
	22 aload_2 (1, 2)
	23 iconst_m1 (1, 2)
	24 invokestatic (1, 2)
	27 aload_2 (0, 1)
	28 areturn (0, 1)

Method: getEstimationType
	0 aload_0 (0, 0)
	1 getfield (0, 0)
	4 areturn (0, 0)

Method: withEstimationType
	0 new (0, 0)
	3 dup (0, 0)
	4 aload_0 (0, 0)
	5 getfield (0, 0)
	8 aload_1 (0, 0)
	9 aload_0 (0, 0)
	10 getfield (0, 0)
	13 aload_0 (0, 0)
	14 getfield (0, 0)
	17 invokespecial (0, 0)
	20 areturn (0, 0)

Method: getNaNStrategy
	0 aload_0 (0, 0)
	1 getfield (0, 0)
	4 areturn (0, 0)

Method: withNaNStrategy
	0 new (0, 0)
	3 dup (0, 0)
	4 aload_0 (0, 0)
	5 getfield (0, 0)
	8 aload_0 (0, 0)
	9 getfield (0, 0)
	12 aload_1 (0, 0)
	13 aload_0 (0, 0)
	14 getfield (0, 0)
	17 invokespecial (0, 0)
	20 areturn (0, 0)

Method: getKthSelector
	0 aload_0 (0, 0)
	1 getfield (0, 0)
	4 areturn (0, 0)

Method: getPivotingStrategy
	0 aload_0 (0, 0)
	1 getfield (0, 0)
	4 invokevirtual (0, 0)
	7 areturn (0, 0)

Method: withKthSelector
	0 new (0, 0)
	3 dup (0, 0)
	4 aload_0 (0, 0)
	5 getfield (0, 0)
	8 aload_0 (0, 0)
	9 getfield (0, 0)
	12 aload_0 (0, 0)
	13 getfield (0, 0)
	16 aload_1 (0, 0)
	17 invokespecial (0, 0)
	20 areturn (0, 0)

