Method: values
	0 getstatic (0, 0)
	3 invokevirtual (0, 0)
	6 checkcast (0, 0)
	9 areturn (0, 0)

Method: valueOf
	0 ldc (0, 0)
	2 aload_0 (0, 0)
	3 invokestatic (0, 0)
	6 checkcast (0, 0)
	9 areturn (0, 0)

Method: <init>
	0 aload_0 (0, 0)
	1 aload_1 (0, 0)
	2 iload_2 (0, 0)
	3 invokespecial (0, 0)
	6 aload_0 (0, 0)
	7 aload_3 (0, 0)
	8 putfield (0, 0)
	11 return (0, 0)

Method: estimate
	0 dload_3 (0, 0)
	1 invokestatic (0, 0)
	4 dstore (0, 0)
	6 dload (0, 0)
	8 d2i (0, 0)
	9 istore (0, 0)
	11 dload_3 (0, 1)
	12 dload (0, 1)
	14 dsub (0, 1)
	15 dstore (0, 1)
	17 dload_3 (1, 1)
	18 dconst_1 (1, 1)
	19 dcmpg (1, 1)
	20 ifge (1, 1)
	23 aload (1, 1)
	25 aload_1 (1, 1)
	26 aload_2 (1, 1)
	27 iconst_0 (1, 1)
	28 invokevirtual (1, 1)
	31 dreturn (1, 1)
	32 dload_3 (1, 1)
	33 iload (1, 1)
	35 i2d (1, 1)
	36 dcmpl (1, 1)
	37 iflt (1, 1)
	40 aload (1, 1)
	42 aload_1 (1, 1)
	43 aload_2 (1, 1)
	44 iload (1, 1)
	46 iconst_1 (1, 1)
	47 isub (1, 1)
	48 invokevirtual (1, 1)
	51 dreturn (1, 1)
	52 aload (0, 1)
	54 aload_1 (0, 1)
	55 aload_2 (0, 1)
	56 iload (0, 1)
	58 iconst_1 (0, 1)
	59 isub (0, 1)
	60 invokevirtual (0, 1)
	63 dstore (0, 1)
	65 aload (0, 1)
	67 aload_1 (0, 1)
	68 aload_2 (0, 1)
	69 iload (0, 1)
	71 invokevirtual (0, 1)
	74 dstore (0, 1)
	76 dload (0, 1)
	78 dload (0, 1)
	80 dload (0, 1)
	82 dload (0, 1)
	84 dsub (0, 1)
	85 dmul (0, 1)
	86 dadd (0, 1)
	87 dreturn (0, 1)

Method: evaluate
	0 aload_0 (0, 0)
	1 aload_1 (0, 0)
	2 aconst_null (0, 0)
	3 dload_2 (0, 0)
	4 aload (0, 0)
	6 invokevirtual (0, 0)
	9 dreturn (0, 0)

Method: getName
	0 aload_0 (0, 0)
	1 getfield (0, 0)
	4 areturn (0, 0)

Method: <clinit>
	0 new (0, 0)
	3 dup (0, 0)
	4 ldc (0, 0)
	6 iconst_0 (0, 0)
	7 ldc (0, 0)
	9 invokespecial (0, 0)
	12 putstatic (0, 0)
	15 new (1, 4)
	18 dup (1, 4)
	19 ldc (1, 4)
	21 iconst_1 (1, 4)
	22 ldc (1, 4)
	24 invokespecial (1, 4)
	27 putstatic (1, 4)
	30 new (1, 0)
	33 dup (1, 0)
	34 ldc (1, 0)
	36 iconst_2 (1, 0)
	37 ldc (1, 0)
	39 invokespecial (1, 0)
	42 putstatic (1, 0)
	45 new (2, 4)
	48 dup (2, 4)
	49 ldc (2, 4)
	51 iconst_3 (2, 4)
	52 ldc (2, 4)
	54 invokespecial (2, 4)
	57 putstatic (2, 4)
	60 new (2, 0)
	63 dup (2, 0)
	64 ldc (2, 0)
	66 iconst_4 (2, 0)
	67 ldc (2, 0)
	69 invokespecial (2, 0)
	72 putstatic (2, 0)
	75 new (2, 0)
	78 dup (2, 0)
	79 ldc (2, 0)
	81 iconst_5 (2, 0)
	82 ldc (2, 0)
	84 invokespecial (2, 0)
	87 putstatic (2, 0)
	90 new (3, 1)
	93 dup (3, 1)
	94 ldc (3, 1)
	96 bipush (3, 1)
	98 ldc (3, 1)
	100 invokespecial (3, 1)
	103 putstatic (3, 1)
	106 new (3, 0)
	109 dup (3, 0)
	110 ldc (3, 0)
	112 bipush (3, 0)
	114 ldc (3, 0)
	116 invokespecial (3, 0)
	119 putstatic (3, 0)
	122 new (3, 0)
	125 dup (3, 0)
	126 ldc (3, 0)
	128 bipush (3, 0)
	130 ldc (3, 0)
	132 invokespecial (3, 0)
	135 putstatic (3, 0)
	138 new (3, 0)
	141 dup (3, 0)
	142 ldc (3, 0)
	144 bipush (3, 0)
	146 ldc (3, 0)
	148 invokespecial (3, 0)
	151 putstatic (3, 0)
	154 bipush (3, 0)
	156 anewarray (3, 0)
	159 dup (3, 0)
	160 iconst_0 (3, 0)
	161 getstatic (3, 0)
	164 aastore (3, 0)
	165 dup (3, 0)
	166 iconst_1 (3, 0)
	167 getstatic (3, 0)
	170 aastore (3, 0)
	171 dup (3, 0)
	172 iconst_2 (3, 0)
	173 getstatic (3, 0)
	176 aastore (3, 0)
	177 dup (3, 0)
	178 iconst_3 (3, 0)
	179 getstatic (3, 0)
	182 aastore (3, 0)
	183 dup (3, 0)
	184 iconst_4 (3, 0)
	185 getstatic (3, 0)
	188 aastore (3, 0)
	189 dup (3, 0)
	190 iconst_5 (3, 0)
	191 getstatic (3, 0)
	194 aastore (3, 0)
	195 dup (3, 0)
	196 bipush (3, 0)
	198 getstatic (3, 0)
	201 aastore (3, 0)
	202 dup (3, 0)
	203 bipush (3, 0)
	205 getstatic (3, 0)
	208 aastore (3, 0)
	209 dup (3, 0)
	210 bipush (3, 0)
	212 getstatic (3, 0)
	215 aastore (3, 0)
	216 dup (3, 0)
	217 bipush (3, 0)
	219 getstatic (3, 0)
	222 aastore (3, 0)
	223 putstatic (3, 0)
	226 return (3, 0)

