Method: <init>
	0 aload_0 (0, 0)
	1 iload_1 (0, 0)
	2 invokespecial (0, 0)
	3 java/util/ArrayList.<init>:(I)V (0, 0)
	5 aload_0 (0, 0)
	6 iload_1 (0, 0)
	7 putfield (0, 0)
	8 org/apache/commons/math3/stat/descriptive/rank/PSquarePercentile$FixedCapacityList.capacity:I (0, 0)
	10 return (0, 0)

Method: add
	0 aload_0 (0, 0)
	1 invokevirtual (0, 0)
	2 org/apache/commons/math3/stat/descriptive/rank/PSquarePercentile$FixedCapacityList.size:()I (0, 0)
	4 aload_0 (0, 0)
	5 getfield (0, 0)
	6 org/apache/commons/math3/stat/descriptive/rank/PSquarePercentile$FixedCapacityList.capacity:I (0, 0)
	8 if_icmpge (0, 0)
	9 11 (0, 0)
	11 aload_0 (0, 0)
	12 aload_1 (0, 0)
	13 invokespecial (0, 0)
	14 java/util/ArrayList.add:(Ljava/lang/Object;)Z (0, 0)
	16 goto (0, 0)
	17 4 (0, 0)
	19 iconst_0 (0, 0)
	20 ireturn (0, 0)

Method: addAll
	0 aload_1 (0, 0)
	1 ifnull (0, 0)
	2 25 (0, 0)
	4 aload_1 (0, 0)
	5 invokeinterface (0, 0)
	6 java/util/Collection.add:(Ljava/lang/Object;)Z (0, 0)
	8 0 (0, 0)
	10 aload_0 (0, 0)
	11 invokevirtual (0, 0)
	12 org/apache/commons/math3/stat/descriptive/rank/PSquarePercentile$FixedCapacityList.size:()I (0, 0)
	14 iadd (0, 0)
	15 aload_0 (0, 0)
	16 getfield (0, 0)
	17 org/apache/commons/math3/stat/descriptive/rank/PSquarePercentile$FixedCapacityList.capacity:I (0, 0)
	19 if_icmpgt (0, 0)
	20 7 (0, 0)
	22 iconst_1 (0, 0)
	23 goto (0, 0)
	24 4 (0, 0)
	26 iconst_0 (0, 0)
	27 istore_2 (0, 0)
	28 iload_2 (0, 0)
	29 ifeq (0, 0)
	30 11 (0, 0)
	32 aload_0 (0, 0)
	33 aload_1 (0, 0)
	34 invokespecial (0, 0)
	35 java/util/ArrayList.addAll:(Ljava/util/Collection;)Z (0, 0)
	37 goto (0, 0)
	38 4 (0, 0)
	40 iconst_0 (0, 0)
	41 ireturn (0, 0)

