Method: <init>
	0 aload_0 (0, 0)
	1 ldc2_w (0, 0)
	2 50.0 (0, 0)
	4 invokespecial (0, 0)
	5 org/apache/commons/math3/stat/descriptive/rank/PSquarePercentile.<init>:(D)V (0, 0)
	7 return (0, 0)

Method: hashCode
	0 aload_0 (0, 0)
	1 invokevirtual (0, 0)
	2 org/apache/commons/math3/stat/descriptive/rank/PSquarePercentile.getResult:()D (0, 0)
	4 dstore_1 (0, 0)
	5 dload_1 (0, 0)
	6 invokestatic (0, 0)
	7 java/lang/Double.isNaN:(D)Z (0, 0)
	9 ifeq (0, 0)
	10 9 (0, 0)
	12 ldc2_w (0, 0)
	13 37.0 (0, 0)
	15 goto (0, 0)
	16 4 (0, 0)
	18 dload_1 (0, 0)
	19 dstore_1 (0, 0)
	20 aload_0 (0, 0)
	21 getfield (0, 0)
	22 org/apache/commons/math3/stat/descriptive/rank/PSquarePercentile.markers:Lorg/apache/commons/math3/stat/descriptive/rank/PSquarePercentile$PSquareMarkers; (0, 0)
	24 ifnonnull (0, 0)
	25 7 (0, 0)
	27 dconst_0 (0, 0)
	28 goto (0, 0)
	29 11 (0, 0)
	31 aload_0 (0, 0)
	32 getfield (0, 0)
	33 org/apache/commons/math3/stat/descriptive/rank/PSquarePercentile.markers:Lorg/apache/commons/math3/stat/descriptive/rank/PSquarePercentile$PSquareMarkers; (0, 0)
	35 invokevirtual (0, 0)
	36 java/lang/Object.hashCode:()I (0, 0)
	38 i2d (0, 0)
	39 dstore_3 (0, 0)
	40 iconst_4 (0, 0)
	41 newarray (0, 0)
	42 7 (0, 0)
	43 dup (0, 0)
	44 iconst_0 (0, 0)
	45 dload_1 (0, 0)
	46 dastore (0, 0)
	47 dup (0, 0)
	48 iconst_1 (0, 0)
	49 aload_0 (0, 0)
	50 getfield (0, 0)
	51 org/apache/commons/math3/stat/descriptive/rank/PSquarePercentile.quantile:D (0, 0)
	53 dastore (0, 0)
	54 dup (0, 0)
	55 iconst_2 (0, 0)
	56 dload_3 (0, 0)
	57 dastore (0, 0)
	58 dup (0, 0)
	59 iconst_3 (0, 0)
	60 aload_0 (0, 0)
	61 getfield (0, 0)
	62 org/apache/commons/math3/stat/descriptive/rank/PSquarePercentile.countOfObservations:J (0, 0)
	64 l2d (0, 0)
	65 dastore (0, 0)
	66 astore (0, 0)
	67 #5 (0, 0)
	68 aload (0, 0)
	69 #5 (0, 0)
	70 invokestatic (0, 0)
	71 java/util/Arrays.hashCode:([D)I (0, 0)
	73 ireturn (0, 0)

Method: equals
	0 iconst_0 (0, 0)
	1 istore_2 (0, 0)
	2 aload_0 (1, 1)
	3 aload_1 (1, 1)
	4 if_acmpne (1, 1)
	5 8 (1, 1)
	7 iconst_1 (1, 1)
	8 istore_2 (1, 1)
	9 goto (1, 1)
	10 105 (1, 1)
	12 aload_1 (1, 1)
	13 ifnull (1, 1)
	14 101 (1, 1)
	16 aload_1 (1, 1)
	17 instanceof (1, 1)
	18 org/apache/commons/math3/stat/descriptive/rank/PSquarePercentile (1, 1)
	20 ifeq (1, 1)
	21 94 (1, 1)
	23 aload_1 (1, 1)
	24 checkcast (1, 1)
	25 org/apache/commons/math3/stat/descriptive/rank/PSquarePercentile (1, 1)
	27 astore_3 (1, 1)
	28 aload_0 (1, 1)
	29 getfield (1, 1)
	30 org/apache/commons/math3/stat/descriptive/rank/PSquarePercentile.markers:Lorg/apache/commons/math3/stat/descriptive/rank/PSquarePercentile$PSquareMarkers; (1, 1)
	32 ifnull (1, 1)
	33 14 (1, 1)
	35 aload_3 (1, 1)
	36 getfield (1, 1)
	37 org/apache/commons/math3/stat/descriptive/rank/PSquarePercentile.markers:Lorg/apache/commons/math3/stat/descriptive/rank/PSquarePercentile$PSquareMarkers; (1, 1)
	39 ifnull (1, 1)
	40 7 (1, 1)
	42 iconst_1 (1, 1)
	43 goto (1, 1)
	44 4 (1, 1)
	46 iconst_0 (1, 1)
	47 istore (1, 1)
	48 #4 (1, 1)
	49 aload_0 (1, 1)
	50 getfield (1, 1)
	51 org/apache/commons/math3/stat/descriptive/rank/PSquarePercentile.markers:Lorg/apache/commons/math3/stat/descriptive/rank/PSquarePercentile$PSquareMarkers; (1, 1)
	53 ifnonnull (1, 1)
	54 14 (1, 1)
	56 aload_3 (1, 1)
	57 getfield (1, 1)
	58 org/apache/commons/math3/stat/descriptive/rank/PSquarePercentile.markers:Lorg/apache/commons/math3/stat/descriptive/rank/PSquarePercentile$PSquareMarkers; (1, 1)
	60 ifnonnull (1, 1)
	61 7 (1, 1)
	63 iconst_1 (1, 1)
	64 goto (1, 1)
	65 4 (1, 1)
	67 iconst_0 (1, 1)
	68 istore (1, 1)
	69 #5 (1, 1)
	70 iload (1, 1)
	71 #4 (1, 1)
	72 ifeq (1, 1)
	73 17 (1, 1)
	75 aload_0 (1, 1)
	76 getfield (1, 1)
	77 org/apache/commons/math3/stat/descriptive/rank/PSquarePercentile.markers:Lorg/apache/commons/math3/stat/descriptive/rank/PSquarePercentile$PSquareMarkers; (1, 1)
	79 aload_3 (1, 1)
	80 getfield (1, 1)
	81 org/apache/commons/math3/stat/descriptive/rank/PSquarePercentile.markers:Lorg/apache/commons/math3/stat/descriptive/rank/PSquarePercentile$PSquareMarkers; (1, 1)
	83 invokevirtual (1, 1)
	84 java/lang/Object.equals:(Ljava/lang/Object;)Z (1, 1)
	86 goto (1, 1)
	87 5 (1, 1)
	89 iload (1, 1)
	90 #5 (1, 1)
	91 istore_2 (1, 1)
	92 iload_2 (1, 1)
	93 ifeq (1, 1)
	94 19 (1, 1)
	96 aload_0 (1, 1)
	97 invokevirtual (1, 1)
	98 org/apache/commons/math3/stat/descriptive/rank/PSquarePercentile.getN:()J (1, 1)
	100 aload_3 (1, 1)
	101 invokevirtual (1, 1)
	102 org/apache/commons/math3/stat/descriptive/rank/PSquarePercentile.getN:()J (1, 1)
	104 lcmp (1, 1)
	105 ifne (1, 1)
	106 7 (1, 1)
	108 iconst_1 (1, 1)
	109 goto (1, 1)
	110 4 (1, 1)
	112 iconst_0 (1, 1)
	113 istore_2 (1, 1)
	114 iload_2 (0, 0)
	115 ireturn (0, 0)

Method: increment
	0 aload_0 (0, 0)
	1 dup (0, 0)
	2 getfield (0, 0)
	3 org/apache/commons/math3/stat/descriptive/rank/PSquarePercentile.countOfObservations:J (0, 0)
	5 lconst_1 (0, 0)
	6 ladd (0, 0)
	7 putfield (0, 0)
	8 org/apache/commons/math3/stat/descriptive/rank/PSquarePercentile.countOfObservations:J (0, 0)
	10 aload_0 (0, 0)
	11 dload_1 (0, 0)
	12 putfield (0, 0)
	13 org/apache/commons/math3/stat/descriptive/rank/PSquarePercentile.lastObservation:D (0, 0)
	15 aload_0 (1, 1)
	16 getfield (1, 1)
	17 org/apache/commons/math3/stat/descriptive/rank/PSquarePercentile.markers:Lorg/apache/commons/math3/stat/descriptive/rank/PSquarePercentile$PSquareMarkers; (1, 1)
	19 ifnonnull (1, 1)
	20 79 (1, 1)
	22 aload_0 (2, 1)
	23 getfield (2, 1)
	24 org/apache/commons/math3/stat/descriptive/rank/PSquarePercentile.initialFive:Ljava/util/List; (2, 1)
	26 dload_1 (2, 1)
	27 invokestatic (2, 1)
	28 java/lang/Double.valueOf:(D)Ljava/lang/Double; (2, 1)
	30 invokeinterface (2, 1)
	31 java/util/List.java/util/Collections (2, 1)
	33 0 (2, 1)
	35 ifeq (2, 1)
	36 48 (2, 1)
	38 aload_0 (2, 1)
	39 getfield (2, 1)
	40 org/apache/commons/math3/stat/descriptive/rank/PSquarePercentile.initialFive:Ljava/util/List; (2, 1)
	42 invokestatic (2, 1)
	43 java/util/Collections.sort:(Ljava/util/List;)V (2, 1)
	45 aload_0 (2, 1)
	46 aload_0 (2, 1)
	47 getfield (2, 1)
	48 org/apache/commons/math3/stat/descriptive/rank/PSquarePercentile.initialFive:Ljava/util/List; (2, 1)
	50 aload_0 (2, 1)
	51 getfield (2, 1)
	52 org/apache/commons/math3/stat/descriptive/rank/PSquarePercentile.quantile:D (2, 1)
	54 aload_0 (2, 1)
	55 getfield (2, 1)
	56 org/apache/commons/math3/stat/descriptive/rank/PSquarePercentile.initialFive:Ljava/util/List; (2, 1)
	58 invokeinterface (2, 1)
	59 java/util/List.get:(I)Ljava/lang/Object; (2, 1)
	61 0 (2, 1)
	63 iconst_1 (2, 1)
	64 isub (2, 1)
	65 i2d (2, 1)
	66 dmul (2, 1)
	67 d2i (2, 1)
	68 invokeinterface (2, 1)
	69 java/util/List.doubleValue:()D (2, 1)
	71 0 (2, 1)
	73 checkcast (2, 1)
	74 java/lang/Double (2, 1)
	76 invokevirtual (2, 1)
	77 java/lang/Double.doubleValue:()D (2, 1)
	79 putfield (2, 1)
	80 org/apache/commons/math3/stat/descriptive/rank/PSquarePercentile.pValue:D (2, 1)
	82 return (2, 1)
	83 aload_0 (1, 1)
	84 aload_0 (1, 1)
	85 getfield (1, 1)
	86 org/apache/commons/math3/stat/descriptive/rank/PSquarePercentile.initialFive:Ljava/util/List; (1, 1)
	88 aload_0 (1, 1)
	89 getfield (1, 1)
	90 org/apache/commons/math3/stat/descriptive/rank/PSquarePercentile.quantile:D (1, 1)
	92 invokestatic (1, 1)
	93 org/apache/commons/math3/stat/descriptive/rank/PSquarePercentile.newMarkers:(Ljava/util/List;D)Lorg/apache/commons/math3/stat/descriptive/rank/PSquarePercentile$PSquareMarkers; (1, 1)
	95 putfield (1, 1)
	96 org/apache/commons/math3/stat/descriptive/rank/PSquarePercentile.markers:Lorg/apache/commons/math3/stat/descriptive/rank/PSquarePercentile$PSquareMarkers; (1, 1)
	98 aload_0 (0, 4)
	99 aload_0 (0, 4)
	100 getfield (0, 4)
	101 org/apache/commons/math3/stat/descriptive/rank/PSquarePercentile.markers:Lorg/apache/commons/math3/stat/descriptive/rank/PSquarePercentile$PSquareMarkers; (0, 4)
	103 dload_1 (0, 4)
	104 invokeinterface (0, 4)
	105 org/apache/commons/math3/stat/descriptive/rank/PSquarePercentile$PSquareMarkers.obs=%s pValue=%s (0, 4)
	107 0 (0, 4)
	109 putfield (0, 4)
	110 org/apache/commons/math3/stat/descriptive/rank/PSquarePercentile.pValue:D (0, 4)
	112 return (0, 4)

Method: toString
	0 aload_0 (1, 1)
	1 getfield (1, 1)
	2 org/apache/commons/math3/stat/descriptive/rank/PSquarePercentile.markers:Lorg/apache/commons/math3/stat/descriptive/rank/PSquarePercentile$PSquareMarkers; (1, 1)
	4 ifnonnull (1, 1)
	5 39 (1, 1)
	7 ldc (1, 4)
	8 obs=%s pValue=%s (1, 4)
	9 iconst_2 (1, 4)
	10 anewarray (1, 4)
	11 java/lang/Object (1, 4)
	13 dup (1, 4)
	14 iconst_0 (1, 4)
	15 getstatic (1, 4)
	16 org/apache/commons/math3/stat/descriptive/rank/PSquarePercentile.DECIMAL_FORMAT:Ljava/text/DecimalFormat; (1, 4)
	18 aload_0 (1, 4)
	19 getfield (1, 4)
	20 org/apache/commons/math3/stat/descriptive/rank/PSquarePercentile.lastObservation:D (1, 4)
	22 invokevirtual (1, 4)
	23 java/text/DecimalFormat.format:(D)Ljava/lang/String; (1, 4)
	25 aastore (1, 4)
	26 dup (1, 4)
	27 iconst_1 (1, 4)
	28 getstatic (1, 4)
	29 org/apache/commons/math3/stat/descriptive/rank/PSquarePercentile.DECIMAL_FORMAT:Ljava/text/DecimalFormat; (1, 4)
	31 aload_0 (1, 4)
	32 getfield (1, 4)
	33 org/apache/commons/math3/stat/descriptive/rank/PSquarePercentile.pValue:D (1, 4)
	35 invokevirtual (1, 4)
	36 java/text/DecimalFormat.format:(D)Ljava/lang/String; (1, 4)
	38 aastore (1, 4)
	39 invokestatic (1, 4)
	40 java/lang/String.format:(Ljava/lang/String;[Ljava/lang/Object;)Ljava/lang/String; (1, 4)
	42 areturn (1, 4)
	43 ldc (1, 4)
	44 obs=%s markers=%s (1, 4)
	45 iconst_2 (1, 4)
	46 anewarray (1, 4)
	47 java/lang/Object (1, 4)
	49 dup (1, 4)
	50 iconst_0 (1, 4)
	51 getstatic (1, 4)
	52 org/apache/commons/math3/stat/descriptive/rank/PSquarePercentile.DECIMAL_FORMAT:Ljava/text/DecimalFormat; (1, 4)
	54 aload_0 (1, 4)
	55 getfield (1, 4)
	56 org/apache/commons/math3/stat/descriptive/rank/PSquarePercentile.lastObservation:D (1, 4)
	58 invokevirtual (1, 4)
	59 java/text/DecimalFormat.format:(D)Ljava/lang/String; (1, 4)
	61 aastore (1, 4)
	62 dup (1, 4)
	63 iconst_1 (1, 4)
	64 aload_0 (1, 4)
	65 getfield (1, 4)
	66 org/apache/commons/math3/stat/descriptive/rank/PSquarePercentile.markers:Lorg/apache/commons/math3/stat/descriptive/rank/PSquarePercentile$PSquareMarkers; (1, 4)
	68 invokevirtual (1, 4)
	69 java/lang/Object.toString:()Ljava/lang/String; (1, 4)
	71 aastore (1, 4)
	72 invokestatic (1, 4)
	73 java/lang/String.format:(Ljava/lang/String;[Ljava/lang/Object;)Ljava/lang/String; (1, 4)
	75 areturn (1, 4)

Method: getN
	0 aload_0 (0, 0)
	1 getfield (0, 0)
	2 org/apache/commons/math3/stat/descriptive/rank/PSquarePercentile.countOfObservations:J (0, 0)
	4 lreturn (0, 0)

Method: copy
	0 aload_0 (0, 0)
	1 invokevirtual (0, 0)
	2 org/apache/commons/math3/stat/descriptive/rank/PSquarePercentile.copy:()Lorg/apache/commons/math3/stat/descriptive/StorelessUnivariateStatistic; (0, 0)
	4 areturn (0, 0)

Method: quantile
	0 aload_0 (0, 0)
	1 getfield (0, 0)
	2 org/apache/commons/math3/stat/descriptive/rank/PSquarePercentile.quantile:D (0, 0)
	4 dreturn (0, 0)

Method: clear
	0 aload_0 (0, 0)
	1 aconst_null (0, 0)
	2 putfield (0, 0)
	3 org/apache/commons/math3/stat/descriptive/rank/PSquarePercentile.markers:Lorg/apache/commons/math3/stat/descriptive/rank/PSquarePercentile$PSquareMarkers; (0, 0)
	5 aload_0 (0, 0)
	6 getfield (0, 0)
	7 org/apache/commons/math3/stat/descriptive/rank/PSquarePercentile.initialFive:Ljava/util/List; (0, 0)
	9 invokeinterface (0, 0)
	10 java/util/List.addAll:(Ljava/util/Collection;)Z (0, 0)
	12 0 (0, 0)
	14 aload_0 (0, 0)
	15 lconst_0 (0, 0)
	16 putfield (0, 0)
	17 org/apache/commons/math3/stat/descriptive/rank/PSquarePercentile.countOfObservations:J (0, 0)
	19 aload_0 (0, 0)
	20 ldc2_w (0, 0)
	21 nan (0, 0)
	23 putfield (0, 0)
	24 org/apache/commons/math3/stat/descriptive/rank/PSquarePercentile.pValue:D (0, 0)
	26 return (0, 0)

Method: getResult
	0 aload_0 (1, 1)
	1 getfield (1, 1)
	2 org/apache/commons/math3/stat/descriptive/rank/PSquarePercentile.quantile:D (1, 1)
	4 dconst_1 (1, 1)
	5 invokestatic (1, 1)
	6 java/lang/Double.compare:(DD)I (1, 1)
	8 ifne (1, 1)
	9 14 (1, 1)
	11 aload_0 (1, 1)
	12 aload_0 (1, 1)
	13 invokespecial (1, 1)
	14 org/apache/commons/math3/stat/descriptive/rank/PSquarePercentile.maximum:()D (1, 1)
	16 putfield (1, 1)
	17 org/apache/commons/math3/stat/descriptive/rank/PSquarePercentile.pValue:D (1, 1)
	19 goto (1, 1)
	20 22 (1, 1)
	22 aload_0 (1, 1)
	23 getfield (1, 1)
	24 org/apache/commons/math3/stat/descriptive/rank/PSquarePercentile.quantile:D (1, 1)
	26 dconst_0 (1, 1)
	27 invokestatic (1, 1)
	28 java/lang/Double.compare:(DD)I (1, 1)
	30 ifne (1, 1)
	31 11 (1, 1)
	33 aload_0 (1, 1)
	34 aload_0 (1, 1)
	35 invokespecial (1, 1)
	36 org/apache/commons/math3/stat/descriptive/rank/PSquarePercentile.minimum:()D (1, 1)
	38 putfield (1, 1)
	39 org/apache/commons/math3/stat/descriptive/rank/PSquarePercentile.pValue:D (1, 1)
	41 aload_0 (0, 0)
	42 getfield (0, 0)
	43 org/apache/commons/math3/stat/descriptive/rank/PSquarePercentile.pValue:D (0, 0)
	45 dreturn (0, 0)

Method: maximum
	0 ldc2_w (0, 0)
	1 nan (0, 0)
	3 dstore_1 (0, 0)
	4 aload_0 (1, 1)
	5 getfield (1, 1)
	6 org/apache/commons/math3/stat/descriptive/rank/PSquarePercentile.markers:Lorg/apache/commons/math3/stat/descriptive/rank/PSquarePercentile$PSquareMarkers; (1, 1)
	8 ifnull (1, 1)
	9 17 (1, 1)
	11 aload_0 (1, 1)
	12 getfield (1, 1)
	13 org/apache/commons/math3/stat/descriptive/rank/PSquarePercentile.markers:Lorg/apache/commons/math3/stat/descriptive/rank/PSquarePercentile$PSquareMarkers; (1, 1)
	15 iconst_5 (1, 1)
	16 invokeinterface (1, 1)
	17 org/apache/commons/math3/stat/descriptive/rank/PSquarePercentile$PSquareMarkers.isEmpty:()Z (1, 1)
	19 0 (1, 1)
	21 dstore_1 (1, 1)
	22 goto (1, 1)
	23 42 (1, 1)
	25 aload_0 (1, 1)
	26 getfield (1, 1)
	27 org/apache/commons/math3/stat/descriptive/rank/PSquarePercentile.initialFive:Ljava/util/List; (1, 1)
	29 invokeinterface (1, 1)
	30 java/util/List.org/apache/commons/math3/stat/descriptive/rank/PSquarePercentile$Markers (1, 1)
	32 0 (1, 1)
	34 ifne (1, 1)
	35 30 (1, 1)
	37 aload_0 (1, 1)
	38 getfield (1, 1)
	39 org/apache/commons/math3/stat/descriptive/rank/PSquarePercentile.initialFive:Ljava/util/List; (1, 1)
	41 aload_0 (1, 1)
	42 getfield (1, 1)
	43 org/apache/commons/math3/stat/descriptive/rank/PSquarePercentile.initialFive:Ljava/util/List; (1, 1)
	45 invokeinterface (1, 1)
	46 java/util/List.get:(I)Ljava/lang/Object; (1, 1)
	48 0 (1, 1)
	50 iconst_1 (1, 1)
	51 isub (1, 1)
	52 invokeinterface (1, 1)
	53 java/util/List.doubleValue:()D (1, 1)
	55 0 (1, 1)
	57 checkcast (1, 1)
	58 java/lang/Double (1, 1)
	60 invokevirtual (1, 1)
	61 java/lang/Double.doubleValue:()D (1, 1)
	63 dstore_1 (1, 1)
	64 dload_1 (0, 0)
	65 dreturn (0, 0)

Method: minimum
	0 ldc2_w (0, 0)
	1 nan (0, 0)
	3 dstore_1 (0, 0)
	4 aload_0 (1, 1)
	5 getfield (1, 1)
	6 org/apache/commons/math3/stat/descriptive/rank/PSquarePercentile.markers:Lorg/apache/commons/math3/stat/descriptive/rank/PSquarePercentile$PSquareMarkers; (1, 1)
	8 ifnull (1, 1)
	9 17 (1, 1)
	11 aload_0 (1, 1)
	12 getfield (1, 1)
	13 org/apache/commons/math3/stat/descriptive/rank/PSquarePercentile.markers:Lorg/apache/commons/math3/stat/descriptive/rank/PSquarePercentile$PSquareMarkers; (1, 1)
	15 iconst_1 (1, 1)
	16 invokeinterface (1, 1)
	17 org/apache/commons/math3/stat/descriptive/rank/PSquarePercentile$PSquareMarkers.isEmpty:()Z (1, 1)
	19 0 (1, 1)
	21 dstore_1 (1, 1)
	22 goto (1, 1)
	23 32 (1, 1)
	25 aload_0 (1, 1)
	26 getfield (1, 1)
	27 org/apache/commons/math3/stat/descriptive/rank/PSquarePercentile.initialFive:Ljava/util/List; (1, 1)
	29 invokeinterface (1, 1)
	30 java/util/List.org/apache/commons/math3/stat/descriptive/rank/PSquarePercentile$Markers (1, 1)
	32 0 (1, 1)
	34 ifne (1, 1)
	35 20 (1, 1)
	37 aload_0 (1, 1)
	38 getfield (1, 1)
	39 org/apache/commons/math3/stat/descriptive/rank/PSquarePercentile.initialFive:Ljava/util/List; (1, 1)
	41 iconst_0 (1, 1)
	42 invokeinterface (1, 1)
	43 java/util/List.doubleValue:()D (1, 1)
	45 0 (1, 1)
	47 checkcast (1, 1)
	48 java/lang/Double (1, 1)
	50 invokevirtual (1, 1)
	51 java/lang/Double.doubleValue:()D (1, 1)
	53 dstore_1 (1, 1)
	54 dload_1 (0, 0)
	55 dreturn (0, 0)

Method: newMarkers
	0 new (0, 0)
	1 org/apache/commons/math3/stat/descriptive/rank/PSquarePercentile$Markers (0, 0)
	3 dup (0, 0)
	4 aload_0 (0, 0)
	5 dload_1 (0, 0)
	6 aconst_null (0, 0)
	7 invokespecial (0, 0)
	8 org/apache/commons/math3/stat/descriptive/rank/PSquarePercentile$Markers.<init>:(Ljava/util/List;DLorg/apache/commons/math3/stat/descriptive/rank/PSquarePercentile$1;)V (0, 0)
	10 areturn (0, 0)

Method: <clinit>
	0 new (0, 0)
	1 java/text/DecimalFormat (0, 0)
	3 dup (0, 0)
	4 ldc (0, 0)
	5 00.00 (0, 0)
	6 invokespecial (0, 0)
	7 java/text/DecimalFormat.<init>:(Ljava/lang/String;)V (0, 0)
	9 putstatic (0, 0)
	10 org/apache/commons/math3/stat/descriptive/rank/PSquarePercentile.DECIMAL_FORMAT:Ljava/text/DecimalFormat; (0, 0)
	12 return (0, 0)

