Method: <init>
	0 aload_0 (0, 0)
	1 invokespecial (0, 0)
	2 org/apache/commons/math3/stat/descriptive/rank/PSquarePercentile$Marker.<init>:()V (0, 0)
	4 aload_0 (0, 0)
	5 dload_1 (0, 0)
	6 putfield (0, 0)
	7 org/apache/commons/math3/stat/descriptive/rank/PSquarePercentile$Marker.markerHeight:D (0, 0)
	9 aload_0 (0, 0)
	10 dload_3 (0, 0)
	11 putfield (0, 0)
	12 org/apache/commons/math3/stat/descriptive/rank/PSquarePercentile$Marker.desiredMarkerPosition:D (0, 0)
	14 aload_0 (0, 0)
	15 dload (0, 0)
	16 #5 (0, 0)
	17 putfield (0, 0)
	18 org/apache/commons/math3/stat/descriptive/rank/PSquarePercentile$Marker.desiredMarkerIncrement:D (0, 0)
	20 aload_0 (0, 0)
	21 dload (0, 0)
	22 #7 (0, 0)
	23 putfield (0, 0)
	24 org/apache/commons/math3/stat/descriptive/rank/PSquarePercentile$Marker.intMarkerPosition:D (0, 0)
	26 return (0, 0)

Method: previous
	0 aload_1 (0, 0)
	1 invokestatic (0, 0)
	2 org/apache/commons/math3/util/MathUtils.checkNotNull:(Ljava/lang/Object;)V (0, 0)
	4 aload_0 (0, 0)
	5 aload_1 (0, 0)
	6 putfield (0, 0)
	7 org/apache/commons/math3/stat/descriptive/rank/PSquarePercentile$Marker.previous:Lorg/apache/commons/math3/stat/descriptive/rank/PSquarePercentile$Marker; (0, 0)
	9 aload_0 (0, 0)
	10 areturn (0, 0)

Method: next
	0 aload_1 (0, 0)
	1 invokestatic (0, 0)
	2 org/apache/commons/math3/util/MathUtils.checkNotNull:(Ljava/lang/Object;)V (0, 0)
	4 aload_0 (0, 0)
	5 aload_1 (0, 0)
	6 putfield (0, 0)
	7 org/apache/commons/math3/stat/descriptive/rank/PSquarePercentile$Marker.next:Lorg/apache/commons/math3/stat/descriptive/rank/PSquarePercentile$Marker; (0, 0)
	9 aload_0 (0, 0)
	10 areturn (0, 0)

Method: index
	0 aload_0 (0, 0)
	1 iload_1 (0, 0)
	2 putfield (0, 0)
	3 org/apache/commons/math3/stat/descriptive/rank/PSquarePercentile$Marker.index:I (0, 0)
	5 aload_0 (0, 0)
	6 areturn (0, 0)

Method: updateDesiredPosition
	0 aload_0 (0, 0)
	1 dup (0, 0)
	2 getfield (0, 0)
	3 org/apache/commons/math3/stat/descriptive/rank/PSquarePercentile$Marker.desiredMarkerPosition:D (0, 0)
	5 aload_0 (0, 0)
	6 getfield (0, 0)
	7 org/apache/commons/math3/stat/descriptive/rank/PSquarePercentile$Marker.desiredMarkerIncrement:D (0, 0)
	9 dadd (0, 0)
	10 putfield (0, 0)
	11 org/apache/commons/math3/stat/descriptive/rank/PSquarePercentile$Marker.desiredMarkerPosition:D (0, 0)
	13 return (0, 0)

Method: incrementPosition
	0 aload_0 (0, 0)
	1 dup (0, 0)
	2 getfield (0, 0)
	3 org/apache/commons/math3/stat/descriptive/rank/PSquarePercentile$Marker.intMarkerPosition:D (0, 0)
	5 iload_1 (0, 0)
	6 i2d (0, 0)
	7 dadd (0, 0)
	8 putfield (0, 0)
	9 org/apache/commons/math3/stat/descriptive/rank/PSquarePercentile$Marker.intMarkerPosition:D (0, 0)
	11 return (0, 0)

Method: difference
	0 aload_0 (0, 0)
	1 getfield (0, 0)
	2 org/apache/commons/math3/stat/descriptive/rank/PSquarePercentile$Marker.desiredMarkerPosition:D (0, 0)
	4 aload_0 (0, 0)
	5 getfield (0, 0)
	6 org/apache/commons/math3/stat/descriptive/rank/PSquarePercentile$Marker.intMarkerPosition:D (0, 0)
	8 dsub (0, 0)
	9 dreturn (0, 0)

Method: estimate
	0 aload_0 (0, 1)
	1 invokespecial (0, 1)
	2 org/apache/commons/math3/stat/descriptive/rank/PSquarePercentile$Marker.difference:()D (0, 1)
	4 dstore_1 (0, 1)
	5 aload_0 (0, 1)
	6 getfield (0, 1)
	7 org/apache/commons/math3/stat/descriptive/rank/PSquarePercentile$Marker.next:Lorg/apache/commons/math3/stat/descriptive/rank/PSquarePercentile$Marker; (0, 1)
	9 getfield (0, 1)
	10 org/apache/commons/math3/stat/descriptive/rank/PSquarePercentile$Marker.intMarkerPosition:D (0, 1)
	12 aload_0 (0, 1)
	13 getfield (0, 1)
	14 org/apache/commons/math3/stat/descriptive/rank/PSquarePercentile$Marker.intMarkerPosition:D (0, 1)
	16 dsub (0, 1)
	17 dconst_1 (0, 1)
	18 dcmpl (0, 1)
	19 ifle (0, 1)
	20 7 (0, 1)
	22 iconst_1 (0, 1)
	23 goto (0, 1)
	24 4 (0, 1)
	26 iconst_0 (0, 1)
	27 istore_3 (0, 1)
	28 aload_0 (0, 1)
	29 getfield (0, 1)
	30 org/apache/commons/math3/stat/descriptive/rank/PSquarePercentile$Marker.previous:Lorg/apache/commons/math3/stat/descriptive/rank/PSquarePercentile$Marker; (0, 1)
	32 getfield (0, 1)
	33 org/apache/commons/math3/stat/descriptive/rank/PSquarePercentile$Marker.intMarkerPosition:D (0, 1)
	35 aload_0 (0, 1)
	36 getfield (0, 1)
	37 org/apache/commons/math3/stat/descriptive/rank/PSquarePercentile$Marker.intMarkerPosition:D (0, 1)
	39 dsub (0, 1)
	40 ldc2_w (0, 1)
	41 -1.0 (0, 1)
	43 dcmpg (0, 1)
	44 ifge (0, 1)
	45 7 (0, 1)
	47 iconst_1 (0, 1)
	48 goto (0, 1)
	49 4 (0, 1)
	51 iconst_0 (0, 1)
	52 istore (0, 1)
	53 #4 (0, 1)
	54 dload_1 (1, 1)
	55 dconst_1 (1, 1)
	56 dcmpl (1, 1)
	57 iflt (1, 1)
	58 7 (1, 1)
	60 iload_3 (1, 1)
	61 ifne (1, 1)
	62 16 (1, 1)
	64 dload_1 (1, 1)
	65 ldc2_w (1, 1)
	66 -1.0 (1, 1)
	68 dcmpg (1, 1)
	69 ifgt (1, 1)
	70 247 (1, 1)
	72 iload (1, 1)
	73 #4 (1, 1)
	74 ifeq (1, 1)
	75 242 (1, 1)
	77 dload_1 (1, 1)
	78 dconst_0 (1, 1)
	79 dcmpl (1, 1)
	80 iflt (1, 1)
	81 7 (1, 1)
	83 iconst_1 (1, 1)
	84 goto (1, 1)
	85 4 (1, 1)
	87 iconst_m1 (1, 1)
	88 istore (1, 1)
	89 #5 (1, 1)
	90 iconst_3 (1, 1)
	91 newarray (1, 1)
	92 7 (1, 1)
	93 dup (1, 1)
	94 iconst_0 (1, 1)
	95 aload_0 (1, 1)
	96 getfield (1, 1)
	97 org/apache/commons/math3/stat/descriptive/rank/PSquarePercentile$Marker.previous:Lorg/apache/commons/math3/stat/descriptive/rank/PSquarePercentile$Marker; (1, 1)
	99 getfield (1, 1)
	100 org/apache/commons/math3/stat/descriptive/rank/PSquarePercentile$Marker.intMarkerPosition:D (1, 1)
	102 dastore (1, 1)
	103 dup (1, 1)
	104 iconst_1 (1, 1)
	105 aload_0 (1, 1)
	106 getfield (1, 1)
	107 org/apache/commons/math3/stat/descriptive/rank/PSquarePercentile$Marker.intMarkerPosition:D (1, 1)
	109 dastore (1, 1)
	110 dup (1, 1)
	111 iconst_2 (1, 1)
	112 aload_0 (1, 1)
	113 getfield (1, 1)
	114 org/apache/commons/math3/stat/descriptive/rank/PSquarePercentile$Marker.next:Lorg/apache/commons/math3/stat/descriptive/rank/PSquarePercentile$Marker; (1, 1)
	116 getfield (1, 1)
	117 org/apache/commons/math3/stat/descriptive/rank/PSquarePercentile$Marker.intMarkerPosition:D (1, 1)
	119 dastore (1, 1)
	120 astore (1, 1)
	121 #6 (1, 1)
	122 iconst_3 (1, 1)
	123 newarray (1, 1)
	124 7 (1, 1)
	125 dup (1, 1)
	126 iconst_0 (1, 1)
	127 aload_0 (1, 1)
	128 getfield (1, 1)
	129 org/apache/commons/math3/stat/descriptive/rank/PSquarePercentile$Marker.previous:Lorg/apache/commons/math3/stat/descriptive/rank/PSquarePercentile$Marker; (1, 1)
	131 getfield (1, 1)
	132 org/apache/commons/math3/stat/descriptive/rank/PSquarePercentile$Marker.markerHeight:D (1, 1)
	134 dastore (1, 1)
	135 dup (1, 1)
	136 iconst_1 (1, 1)
	137 aload_0 (1, 1)
	138 getfield (1, 1)
	139 org/apache/commons/math3/stat/descriptive/rank/PSquarePercentile$Marker.markerHeight:D (1, 1)
	141 dastore (1, 1)
	142 dup (1, 1)
	143 iconst_2 (1, 1)
	144 aload_0 (1, 1)
	145 getfield (1, 1)
	146 org/apache/commons/math3/stat/descriptive/rank/PSquarePercentile$Marker.next:Lorg/apache/commons/math3/stat/descriptive/rank/PSquarePercentile$Marker; (1, 1)
	148 getfield (1, 1)
	149 org/apache/commons/math3/stat/descriptive/rank/PSquarePercentile$Marker.markerHeight:D (1, 1)
	151 dastore (1, 1)
	152 astore (1, 1)
	153 #7 (1, 1)
	154 aload_0 (1, 1)
	155 getfield (1, 1)
	156 org/apache/commons/math3/stat/descriptive/rank/PSquarePercentile$Marker.intMarkerPosition:D (1, 1)
	158 iload (1, 1)
	159 #5 (1, 1)
	160 i2d (1, 1)
	161 dadd (1, 1)
	162 dstore (1, 1)
	163 #8 (1, 1)
	164 aload_0 (1, 1)
	165 getfield (1, 1)
	166 org/apache/commons/math3/stat/descriptive/rank/PSquarePercentile$Marker.nonLinear:Lorg/apache/commons/math3/analysis/interpolation/UnivariateInterpolator; (1, 1)
	168 aload (1, 1)
	169 #6 (1, 1)
	170 aload (1, 1)
	171 #7 (1, 1)
	172 invokeinterface (1, 1)
	173 org/apache/commons/math3/analysis/interpolation/UnivariateInterpolator.org/apache/commons/math3/analysis/UnivariateFunction (1, 1)
	175 0 (1, 1)
	177 astore (1, 1)
	178 #10 (1, 1)
	179 aload_0 (1, 1)
	180 aload (1, 1)
	181 #10 (1, 1)
	182 dload (1, 1)
	183 #8 (1, 1)
	184 invokeinterface (1, 1)
	185 org/apache/commons/math3/analysis/UnivariateFunction.isEstimateBad:([DD)Z (1, 1)
	187 0 (1, 1)
	189 putfield (1, 1)
	190 org/apache/commons/math3/stat/descriptive/rank/PSquarePercentile$Marker.markerHeight:D (1, 1)
	192 aload_0 (2, 1)
	193 aload (2, 1)
	194 #7 (2, 1)
	195 aload_0 (2, 1)
	196 getfield (2, 1)
	197 org/apache/commons/math3/stat/descriptive/rank/PSquarePercentile$Marker.markerHeight:D (2, 1)
	199 invokespecial (2, 1)
	200 org/apache/commons/math3/stat/descriptive/rank/PSquarePercentile$Marker.isEstimateBad:([DD)Z (2, 1)
	202 ifeq (2, 1)
	203 108 (2, 1)
	205 dload (2, 1)
	206 #8 (2, 1)
	207 aload (2, 1)
	208 #6 (2, 1)
	209 iconst_1 (2, 1)
	210 daload (2, 1)
	211 dsub (2, 1)
	212 dconst_0 (2, 1)
	213 dcmpl (2, 1)
	214 ifle (2, 1)
	215 7 (2, 1)
	217 iconst_1 (2, 1)
	218 goto (2, 1)
	219 4 (2, 1)
	221 iconst_m1 (2, 1)
	222 istore (2, 1)
	223 #11 (2, 1)
	224 iconst_2 (2, 1)
	225 newarray (2, 1)
	226 7 (2, 1)
	227 dup (2, 1)
	228 iconst_0 (2, 1)
	229 aload (2, 1)
	230 #6 (2, 1)
	231 iconst_1 (2, 1)
	232 daload (2, 1)
	233 dastore (2, 1)
	234 dup (2, 1)
	235 iconst_1 (2, 1)
	236 aload (2, 1)
	237 #6 (2, 1)
	238 iconst_1 (2, 1)
	239 iload (2, 1)
	240 #11 (2, 1)
	241 iadd (2, 1)
	242 daload (2, 1)
	243 dastore (2, 1)
	244 astore (2, 1)
	245 #12 (2, 1)
	246 iconst_2 (2, 1)
	247 newarray (2, 1)
	248 7 (2, 1)
	249 dup (2, 1)
	250 iconst_0 (2, 1)
	251 aload (2, 1)
	252 #7 (2, 1)
	253 iconst_1 (2, 1)
	254 daload (2, 1)
	255 dastore (2, 1)
	256 dup (2, 1)
	257 iconst_1 (2, 1)
	258 aload (2, 1)
	259 #7 (2, 1)
	260 iconst_1 (2, 1)
	261 iload (2, 1)
	262 #11 (2, 1)
	263 iadd (2, 1)
	264 daload (2, 1)
	265 dastore (2, 1)
	266 astore (2, 1)
	267 #13 (2, 1)
	268 aload (2, 1)
	269 #12 (2, 1)
	270 iconst_1 (2, 1)
	271 anewarray (2, 1)
	272 [D (2, 1)
	274 dup (2, 1)
	275 iconst_0 (2, 1)
	276 aload (2, 1)
	277 #13 (2, 1)
	278 aastore (2, 1)
	279 invokestatic (2, 1)
	280 org/apache/commons/math3/util/MathArrays.sortInPlace:([D[[D)V (2, 1)
	282 aload_0 (2, 1)
	283 getfield (2, 1)
	284 org/apache/commons/math3/stat/descriptive/rank/PSquarePercentile$Marker.linear:Lorg/apache/commons/math3/analysis/interpolation/UnivariateInterpolator; (2, 1)
	286 aload (2, 1)
	287 #12 (2, 1)
	288 aload (2, 1)
	289 #13 (2, 1)
	290 invokeinterface (2, 1)
	291 org/apache/commons/math3/analysis/interpolation/UnivariateInterpolator.org/apache/commons/math3/analysis/UnivariateFunction (2, 1)
	293 0 (2, 1)
	295 astore (2, 1)
	296 #10 (2, 1)
	297 aload_0 (2, 1)
	298 aload (2, 1)
	299 #10 (2, 1)
	300 dload (2, 1)
	301 #8 (2, 1)
	302 invokeinterface (2, 1)
	303 org/apache/commons/math3/analysis/UnivariateFunction.isEstimateBad:([DD)Z (2, 1)
	305 0 (2, 1)
	307 putfield (2, 1)
	308 org/apache/commons/math3/stat/descriptive/rank/PSquarePercentile$Marker.markerHeight:D (2, 1)
	310 aload_0 (1, 1)
	311 iload (1, 1)
	312 #5 (1, 1)
	313 invokespecial (1, 1)
	314 org/apache/commons/math3/stat/descriptive/rank/PSquarePercentile$Marker.incrementPosition:(I)V (1, 1)
	316 aload_0 (0, 1)
	317 getfield (0, 1)
	318 org/apache/commons/math3/stat/descriptive/rank/PSquarePercentile$Marker.markerHeight:D (0, 1)
	320 dreturn (0, 1)

Method: isEstimateBad
	0 dload_2 (0, 0)
	1 aload_1 (0, 0)
	2 iconst_0 (0, 0)
	3 daload (0, 0)
	4 dcmpg (0, 0)
	5 ifle (0, 0)
	6 11 (0, 0)
	8 dload_2 (0, 0)
	9 aload_1 (0, 0)
	10 iconst_2 (0, 0)
	11 daload (0, 0)
	12 dcmpl (0, 0)
	13 iflt (0, 0)
	14 7 (0, 0)
	16 iconst_1 (0, 0)
	17 goto (0, 0)
	18 4 (0, 0)
	20 iconst_0 (0, 0)
	21 ireturn (0, 0)

Method: equals
	0 iconst_0 (0, 0)
	1 istore_2 (0, 0)
	2 aload_0 (1, 1)
	3 aload_1 (1, 1)
	4 if_acmpne (1, 1)
	5 8 (1, 1)
	7 iconst_1 (1, 1)
	8 istore_2 (1, 1)
	9 goto (1, 1)
	10 165 (1, 1)
	12 aload_1 (1, 1)
	13 ifnull (1, 1)
	14 161 (1, 1)
	16 aload_1 (1, 1)
	17 instanceof (1, 1)
	18 org/apache/commons/math3/stat/descriptive/rank/PSquarePercentile$Marker (1, 1)
	20 ifeq (1, 1)
	21 154 (1, 1)
	23 aload_1 (1, 1)
	24 checkcast (1, 1)
	25 org/apache/commons/math3/stat/descriptive/rank/PSquarePercentile$Marker (1, 1)
	27 astore_3 (1, 1)
	28 aload_0 (1, 1)
	29 getfield (1, 1)
	30 org/apache/commons/math3/stat/descriptive/rank/PSquarePercentile$Marker.markerHeight:D (1, 1)
	32 aload_3 (1, 1)
	33 getfield (1, 1)
	34 org/apache/commons/math3/stat/descriptive/rank/PSquarePercentile$Marker.markerHeight:D (1, 1)
	36 invokestatic (1, 1)
	37 java/lang/Double.compare:(DD)I (1, 1)
	39 ifne (1, 1)
	40 7 (1, 1)
	42 iconst_1 (1, 1)
	43 goto (1, 1)
	44 4 (1, 1)
	46 iconst_0 (1, 1)
	47 istore_2 (1, 1)
	48 iload_2 (1, 1)
	49 ifeq (1, 1)
	50 21 (1, 1)
	52 aload_0 (1, 1)
	53 getfield (1, 1)
	54 org/apache/commons/math3/stat/descriptive/rank/PSquarePercentile$Marker.intMarkerPosition:D (1, 1)
	56 aload_3 (1, 1)
	57 getfield (1, 1)
	58 org/apache/commons/math3/stat/descriptive/rank/PSquarePercentile$Marker.intMarkerPosition:D (1, 1)
	60 invokestatic (1, 1)
	61 java/lang/Double.compare:(DD)I (1, 1)
	63 ifne (1, 1)
	64 7 (1, 1)
	66 iconst_1 (1, 1)
	67 goto (1, 1)
	68 4 (1, 1)
	70 iconst_0 (1, 1)
	71 istore_2 (1, 1)
	72 iload_2 (1, 1)
	73 ifeq (1, 1)
	74 21 (1, 1)
	76 aload_0 (1, 1)
	77 getfield (1, 1)
	78 org/apache/commons/math3/stat/descriptive/rank/PSquarePercentile$Marker.desiredMarkerPosition:D (1, 1)
	80 aload_3 (1, 1)
	81 getfield (1, 1)
	82 org/apache/commons/math3/stat/descriptive/rank/PSquarePercentile$Marker.desiredMarkerPosition:D (1, 1)
	84 invokestatic (1, 1)
	85 java/lang/Double.compare:(DD)I (1, 1)
	87 ifne (1, 1)
	88 7 (1, 1)
	90 iconst_1 (1, 1)
	91 goto (1, 1)
	92 4 (1, 1)
	94 iconst_0 (1, 1)
	95 istore_2 (1, 1)
	96 iload_2 (1, 1)
	97 ifeq (1, 1)
	98 21 (1, 1)
	100 aload_0 (1, 1)
	101 getfield (1, 1)
	102 org/apache/commons/math3/stat/descriptive/rank/PSquarePercentile$Marker.desiredMarkerIncrement:D (1, 1)
	104 aload_3 (1, 1)
	105 getfield (1, 1)
	106 org/apache/commons/math3/stat/descriptive/rank/PSquarePercentile$Marker.desiredMarkerIncrement:D (1, 1)
	108 invokestatic (1, 1)
	109 java/lang/Double.compare:(DD)I (1, 1)
	111 ifne (1, 1)
	112 7 (1, 1)
	114 iconst_1 (1, 1)
	115 goto (1, 1)
	116 4 (1, 1)
	118 iconst_0 (1, 1)
	119 istore_2 (1, 1)
	120 iload_2 (1, 1)
	121 ifeq (1, 1)
	122 24 (1, 1)
	124 aload_0 (1, 1)
	125 getfield (1, 1)
	126 org/apache/commons/math3/stat/descriptive/rank/PSquarePercentile$Marker.next:Lorg/apache/commons/math3/stat/descriptive/rank/PSquarePercentile$Marker; (1, 1)
	128 getfield (1, 1)
	129 org/apache/commons/math3/stat/descriptive/rank/PSquarePercentile$Marker.index:I (1, 1)
	131 aload_3 (1, 1)
	132 getfield (1, 1)
	133 org/apache/commons/math3/stat/descriptive/rank/PSquarePercentile$Marker.next:Lorg/apache/commons/math3/stat/descriptive/rank/PSquarePercentile$Marker; (1, 1)
	135 getfield (1, 1)
	136 org/apache/commons/math3/stat/descriptive/rank/PSquarePercentile$Marker.index:I (1, 1)
	138 if_icmpne (1, 1)
	139 7 (1, 1)
	141 iconst_1 (1, 1)
	142 goto (1, 1)
	143 4 (1, 1)
	145 iconst_0 (1, 1)
	146 istore_2 (1, 1)
	147 iload_2 (1, 1)
	148 ifeq (1, 1)
	149 24 (1, 1)
	151 aload_0 (1, 1)
	152 getfield (1, 1)
	153 org/apache/commons/math3/stat/descriptive/rank/PSquarePercentile$Marker.previous:Lorg/apache/commons/math3/stat/descriptive/rank/PSquarePercentile$Marker; (1, 1)
	155 getfield (1, 1)
	156 org/apache/commons/math3/stat/descriptive/rank/PSquarePercentile$Marker.index:I (1, 1)
	158 aload_3 (1, 1)
	159 getfield (1, 1)
	160 org/apache/commons/math3/stat/descriptive/rank/PSquarePercentile$Marker.previous:Lorg/apache/commons/math3/stat/descriptive/rank/PSquarePercentile$Marker; (1, 1)
	162 getfield (1, 1)
	163 org/apache/commons/math3/stat/descriptive/rank/PSquarePercentile$Marker.index:I (1, 1)
	165 if_icmpne (1, 1)
	166 7 (1, 1)
	168 iconst_1 (1, 1)
	169 goto (1, 1)
	170 4 (1, 1)
	172 iconst_0 (1, 1)
	173 istore_2 (1, 1)
	174 iload_2 (0, 0)
	175 ireturn (0, 0)

Method: hashCode
	0 bipush (0, 0)
	1 6 (0, 0)
	2 newarray (0, 0)
	3 7 (0, 0)
	4 dup (0, 0)
	5 iconst_0 (0, 0)
	6 aload_0 (0, 0)
	7 getfield (0, 0)
	8 org/apache/commons/math3/stat/descriptive/rank/PSquarePercentile$Marker.markerHeight:D (0, 0)
	10 dastore (0, 0)
	11 dup (0, 0)
	12 iconst_1 (0, 0)
	13 aload_0 (0, 0)
	14 getfield (0, 0)
	15 org/apache/commons/math3/stat/descriptive/rank/PSquarePercentile$Marker.intMarkerPosition:D (0, 0)
	17 dastore (0, 0)
	18 dup (0, 0)
	19 iconst_2 (0, 0)
	20 aload_0 (0, 0)
	21 getfield (0, 0)
	22 org/apache/commons/math3/stat/descriptive/rank/PSquarePercentile$Marker.desiredMarkerIncrement:D (0, 0)
	24 dastore (0, 0)
	25 dup (0, 0)
	26 iconst_3 (0, 0)
	27 aload_0 (0, 0)
	28 getfield (0, 0)
	29 org/apache/commons/math3/stat/descriptive/rank/PSquarePercentile$Marker.desiredMarkerPosition:D (0, 0)
	31 dastore (0, 0)
	32 dup (0, 0)
	33 iconst_4 (0, 0)
	34 aload_0 (0, 0)
	35 getfield (0, 0)
	36 org/apache/commons/math3/stat/descriptive/rank/PSquarePercentile$Marker.previous:Lorg/apache/commons/math3/stat/descriptive/rank/PSquarePercentile$Marker; (0, 0)
	38 getfield (0, 0)
	39 org/apache/commons/math3/stat/descriptive/rank/PSquarePercentile$Marker.index:I (0, 0)
	41 i2d (0, 0)
	42 dastore (0, 0)
	43 dup (0, 0)
	44 iconst_5 (0, 0)
	45 aload_0 (0, 0)
	46 getfield (0, 0)
	47 org/apache/commons/math3/stat/descriptive/rank/PSquarePercentile$Marker.next:Lorg/apache/commons/math3/stat/descriptive/rank/PSquarePercentile$Marker; (0, 0)
	49 getfield (0, 0)
	50 org/apache/commons/math3/stat/descriptive/rank/PSquarePercentile$Marker.index:I (0, 0)
	52 i2d (0, 0)
	53 dastore (0, 0)
	54 invokestatic (0, 0)
	55 java/util/Arrays.hashCode:([D)I (0, 0)
	57 ireturn (0, 0)

Method: readObject
	0 aload_1 (0, 0)
	1 invokevirtual (0, 0)
	2 java/io/ObjectInputStream.defaultReadObject:()V (0, 0)
	4 aload_0 (0, 0)
	5 aload_0 (0, 0)
	6 aload_0 (0, 0)
	7 dup_x1 (0, 0)
	8 putfield (0, 0)
	9 org/apache/commons/math3/stat/descriptive/rank/PSquarePercentile$Marker.next:Lorg/apache/commons/math3/stat/descriptive/rank/PSquarePercentile$Marker; (0, 0)
	11 putfield (0, 0)
	12 org/apache/commons/math3/stat/descriptive/rank/PSquarePercentile$Marker.previous:Lorg/apache/commons/math3/stat/descriptive/rank/PSquarePercentile$Marker; (0, 0)
	14 aload_0 (0, 0)
	15 new (0, 0)
	16 org/apache/commons/math3/analysis/interpolation/LinearInterpolator (0, 0)
	18 dup (0, 0)
	19 invokespecial (0, 0)
	20 org/apache/commons/math3/analysis/interpolation/LinearInterpolator.<init>:()V (0, 0)
	22 putfield (0, 0)
	23 org/apache/commons/math3/stat/descriptive/rank/PSquarePercentile$Marker.linear:Lorg/apache/commons/math3/analysis/interpolation/UnivariateInterpolator; (0, 0)
	25 return (0, 0)

Method: clone
	0 new (0, 0)
	1 org/apache/commons/math3/stat/descriptive/rank/PSquarePercentile$Marker (0, 0)
	3 dup (0, 0)
	4 aload_0 (0, 0)
	5 getfield (0, 0)
	6 org/apache/commons/math3/stat/descriptive/rank/PSquarePercentile$Marker.markerHeight:D (0, 0)
	8 aload_0 (0, 0)
	9 getfield (0, 0)
	10 org/apache/commons/math3/stat/descriptive/rank/PSquarePercentile$Marker.desiredMarkerPosition:D (0, 0)
	12 aload_0 (0, 0)
	13 getfield (0, 0)
	14 org/apache/commons/math3/stat/descriptive/rank/PSquarePercentile$Marker.desiredMarkerIncrement:D (0, 0)
	16 aload_0 (0, 0)
	17 getfield (0, 0)
	18 org/apache/commons/math3/stat/descriptive/rank/PSquarePercentile$Marker.intMarkerPosition:D (0, 0)
	20 invokespecial (0, 0)
	21 org/apache/commons/math3/stat/descriptive/rank/PSquarePercentile$Marker.<init>:(DDDD)V (0, 0)
	23 areturn (0, 0)

Method: toString
	0 ldc (0, 4)
	1 index=%.0f,n=%.0f,np=%.2f,q=%.2f,dn=%.2f,prev=%d,next=%d (0, 4)
	2 bipush (0, 4)
	3 7 (0, 4)
	4 anewarray (0, 4)
	5 java/lang/Object (0, 4)
	7 dup (0, 4)
	8 iconst_0 (0, 4)
	9 aload_0 (0, 4)
	10 getfield (0, 4)
	11 org/apache/commons/math3/stat/descriptive/rank/PSquarePercentile$Marker.index:I (0, 4)
	13 i2d (0, 4)
	14 invokestatic (0, 4)
	15 java/lang/Double.valueOf:(D)Ljava/lang/Double; (0, 4)
	17 aastore (0, 4)
	18 dup (0, 4)
	19 iconst_1 (0, 4)
	20 aload_0 (0, 4)
	21 getfield (0, 4)
	22 org/apache/commons/math3/stat/descriptive/rank/PSquarePercentile$Marker.intMarkerPosition:D (0, 4)
	24 iconst_0 (0, 4)
	25 invokestatic (0, 4)
	26 org/apache/commons/math3/util/Precision.round:(DI)D (0, 4)
	28 invokestatic (0, 4)
	29 java/lang/Double.valueOf:(D)Ljava/lang/Double; (0, 4)
	31 aastore (0, 4)
	32 dup (0, 4)
	33 iconst_2 (0, 4)
	34 aload_0 (0, 4)
	35 getfield (0, 4)
	36 org/apache/commons/math3/stat/descriptive/rank/PSquarePercentile$Marker.desiredMarkerPosition:D (0, 4)
	38 iconst_2 (0, 4)
	39 invokestatic (0, 4)
	40 org/apache/commons/math3/util/Precision.round:(DI)D (0, 4)
	42 invokestatic (0, 4)
	43 java/lang/Double.valueOf:(D)Ljava/lang/Double; (0, 4)
	45 aastore (0, 4)
	46 dup (0, 4)
	47 iconst_3 (0, 4)
	48 aload_0 (0, 4)
	49 getfield (0, 4)
	50 org/apache/commons/math3/stat/descriptive/rank/PSquarePercentile$Marker.markerHeight:D (0, 4)
	52 iconst_2 (0, 4)
	53 invokestatic (0, 4)
	54 org/apache/commons/math3/util/Precision.round:(DI)D (0, 4)
	56 invokestatic (0, 4)
	57 java/lang/Double.valueOf:(D)Ljava/lang/Double; (0, 4)
	59 aastore (0, 4)
	60 dup (0, 4)
	61 iconst_4 (0, 4)
	62 aload_0 (0, 4)
	63 getfield (0, 4)
	64 org/apache/commons/math3/stat/descriptive/rank/PSquarePercentile$Marker.desiredMarkerIncrement:D (0, 4)
	66 iconst_2 (0, 4)
	67 invokestatic (0, 4)
	68 org/apache/commons/math3/util/Precision.round:(DI)D (0, 4)
	70 invokestatic (0, 4)
	71 java/lang/Double.valueOf:(D)Ljava/lang/Double; (0, 4)
	73 aastore (0, 4)
	74 dup (0, 4)
	75 iconst_5 (0, 4)
	76 aload_0 (0, 4)
	77 getfield (0, 4)
	78 org/apache/commons/math3/stat/descriptive/rank/PSquarePercentile$Marker.previous:Lorg/apache/commons/math3/stat/descriptive/rank/PSquarePercentile$Marker; (0, 4)
	80 getfield (0, 4)
	81 org/apache/commons/math3/stat/descriptive/rank/PSquarePercentile$Marker.index:I (0, 4)
	83 invokestatic (0, 4)
	84 java/lang/Integer.valueOf:(I)Ljava/lang/Integer; (0, 4)
	86 aastore (0, 4)
	87 dup (0, 4)
	88 bipush (0, 4)
	89 6 (0, 4)
	90 aload_0 (0, 4)
	91 getfield (0, 4)
	92 org/apache/commons/math3/stat/descriptive/rank/PSquarePercentile$Marker.next:Lorg/apache/commons/math3/stat/descriptive/rank/PSquarePercentile$Marker; (0, 4)
	94 getfield (0, 4)
	95 org/apache/commons/math3/stat/descriptive/rank/PSquarePercentile$Marker.index:I (0, 4)
	97 invokestatic (0, 4)
	98 java/lang/Integer.valueOf:(I)Ljava/lang/Integer; (0, 4)
	100 aastore (0, 4)
	101 invokestatic (0, 4)
	102 java/lang/String.format:(Ljava/lang/String;[Ljava/lang/Object;)Ljava/lang/String; (0, 4)
	104 areturn (0, 4)

Method: access$000
	0 aload_0 (0, 0)
	1 aload_1 (0, 0)
	2 invokespecial (0, 0)
	3 org/apache/commons/math3/stat/descriptive/rank/PSquarePercentile$Marker.previous:(Lorg/apache/commons/math3/stat/descriptive/rank/PSquarePercentile$Marker;)Lorg/apache/commons/math3/stat/descriptive/rank/PSquarePercentile$Marker; (0, 0)
	5 areturn (0, 0)

Method: access$100
	0 aload_0 (0, 0)
	1 aload_1 (0, 0)
	2 invokespecial (0, 0)
	3 org/apache/commons/math3/stat/descriptive/rank/PSquarePercentile$Marker.next:(Lorg/apache/commons/math3/stat/descriptive/rank/PSquarePercentile$Marker;)Lorg/apache/commons/math3/stat/descriptive/rank/PSquarePercentile$Marker; (0, 0)
	5 areturn (0, 0)

Method: access$200
	0 aload_0 (0, 0)
	1 iload_1 (0, 0)
	2 invokespecial (0, 0)
	3 org/apache/commons/math3/stat/descriptive/rank/PSquarePercentile$Marker.index:(I)Lorg/apache/commons/math3/stat/descriptive/rank/PSquarePercentile$Marker; (0, 0)
	5 areturn (0, 0)

Method: access$502
	0 aload_0 (0, 0)
	1 dload_1 (0, 0)
	2 dup2_x1 (0, 0)
	3 putfield (0, 0)
	4 org/apache/commons/math3/stat/descriptive/rank/PSquarePercentile$Marker.markerHeight:D (0, 0)
	6 dreturn (0, 0)

Method: access$600
	0 aload_0 (0, 0)
	1 invokespecial (0, 0)
	2 org/apache/commons/math3/stat/descriptive/rank/PSquarePercentile$Marker.estimate:()D (0, 0)
	4 dreturn (0, 0)

Method: access$700
	0 aload_0 (0, 0)
	1 iload_1 (0, 0)
	2 invokespecial (0, 0)
	3 org/apache/commons/math3/stat/descriptive/rank/PSquarePercentile$Marker.incrementPosition:(I)V (0, 0)
	5 return (0, 0)

Method: access$800
	0 aload_0 (0, 0)
	1 invokespecial (0, 0)
	2 org/apache/commons/math3/stat/descriptive/rank/PSquarePercentile$Marker.updateDesiredPosition:()V (0, 0)
	4 return (0, 0)

Method: access$500
	0 aload_0 (0, 0)
	1 getfield (0, 0)
	2 org/apache/commons/math3/stat/descriptive/rank/PSquarePercentile$Marker.markerHeight:D (0, 0)
	4 dreturn (0, 0)

