Method: <init>
	0 aload_0 (0, 0)
	1 aload_1 (0, 0)
	2 dload_2 (0, 0)
	3 invokestatic (0, 0)
	4 org/apache/commons/math3/stat/descriptive/rank/PSquarePercentile$Markers.createMarkerArray:(Ljava/util/List;D)[Lorg/apache/commons/math3/stat/descriptive/rank/PSquarePercentile$Marker; (0, 0)
	6 invokespecial (0, 0)
	7 org/apache/commons/math3/stat/descriptive/rank/PSquarePercentile$Markers.<init>:([Lorg/apache/commons/math3/stat/descriptive/rank/PSquarePercentile$Marker;)V (0, 0)
	9 return (0, 0)

Method: createMarkerArray
	0 aload_0 (0, 0)
	1 ifnonnull (0, 0)
	2 7 (0, 0)
	4 iconst_m1 (0, 0)
	5 goto (0, 0)
	6 9 (0, 0)
	8 aload_0 (0, 0)
	9 invokeinterface (0, 0)
	10 java/util/List.org/apache/commons/math3/exception/InsufficientDataException (0, 0)
	12 0 (0, 0)
	14 istore_3 (0, 0)
	15 iload_3 (1, 1)
	16 iconst_5 (1, 1)
	17 if_icmpge (1, 1)
	18 32 (1, 1)
	20 new (1, 1)
	21 org/apache/commons/math3/exception/InsufficientDataException (1, 1)
	23 dup (1, 1)
	24 getstatic (1, 1)
	25 org/apache/commons/math3/exception/util/LocalizedFormats.INSUFFICIENT_OBSERVED_POINTS_IN_SAMPLE:Lorg/apache/commons/math3/exception/util/LocalizedFormats; (1, 1)
	27 iconst_2 (1, 1)
	28 anewarray (1, 1)
	29 java/lang/Object (1, 1)
	31 dup (1, 1)
	32 iconst_0 (1, 1)
	33 iload_3 (1, 1)
	34 invokestatic (1, 1)
	35 java/lang/Integer.valueOf:(I)Ljava/lang/Integer; (1, 1)
	37 aastore (1, 1)
	38 dup (1, 1)
	39 iconst_1 (1, 1)
	40 iconst_5 (1, 1)
	41 invokestatic (1, 1)
	42 java/lang/Integer.valueOf:(I)Ljava/lang/Integer; (1, 1)
	44 aastore (1, 1)
	45 invokespecial (1, 1)
	46 org/apache/commons/math3/exception/InsufficientDataException.<init>:(Lorg/apache/commons/math3/exception/util/Localizable;[Ljava/lang/Object;)V (1, 1)
	48 athrow (1, 1)
	49 aload_0 (0, 0)
	50 invokestatic (0, 0)
	51 java/util/Collections.sort:(Ljava/util/List;)V (0, 0)
	53 bipush (0, 0)
	54 6 (0, 0)
	55 anewarray (0, 0)
	56 org/apache/commons/math3/stat/descriptive/rank/PSquarePercentile$Marker (0, 0)
	58 dup (0, 0)
	59 iconst_0 (0, 0)
	60 new (0, 0)
	61 org/apache/commons/math3/stat/descriptive/rank/PSquarePercentile$Marker (0, 0)
	63 dup (0, 0)
	64 aconst_null (0, 0)
	65 invokespecial (0, 0)
	66 org/apache/commons/math3/stat/descriptive/rank/PSquarePercentile$Marker.<init>:(Lorg/apache/commons/math3/stat/descriptive/rank/PSquarePercentile$1;)V (0, 0)
	68 aastore (0, 0)
	69 dup (0, 0)
	70 iconst_1 (0, 0)
	71 new (0, 0)
	72 org/apache/commons/math3/stat/descriptive/rank/PSquarePercentile$Marker (0, 0)
	74 dup (0, 0)
	75 aload_0 (0, 0)
	76 iconst_0 (0, 0)
	77 invokeinterface (0, 0)
	78 java/util/List.java/lang/Double (0, 0)
	80 0 (0, 0)
	82 checkcast (0, 0)
	83 java/lang/Double (0, 0)
	85 invokevirtual (0, 0)
	86 java/lang/Double.doubleValue:()D (0, 0)
	88 dconst_1 (0, 0)
	89 dconst_0 (0, 0)
	90 dconst_1 (0, 0)
	91 aconst_null (0, 0)
	92 invokespecial (0, 0)
	93 org/apache/commons/math3/stat/descriptive/rank/PSquarePercentile$Marker.<init>:(DDDDLorg/apache/commons/math3/stat/descriptive/rank/PSquarePercentile$1;)V (0, 0)
	95 aastore (0, 0)
	96 dup (0, 0)
	97 iconst_2 (0, 0)
	98 new (0, 0)
	99 org/apache/commons/math3/stat/descriptive/rank/PSquarePercentile$Marker (0, 0)
	101 dup (0, 0)
	102 aload_0 (0, 0)
	103 iconst_1 (0, 0)
	104 invokeinterface (0, 0)
	105 java/util/List.java/lang/Double (0, 0)
	107 0 (0, 0)
	109 checkcast (0, 0)
	110 java/lang/Double (0, 0)
	112 invokevirtual (0, 0)
	113 java/lang/Double.doubleValue:()D (0, 0)
	115 dconst_1 (0, 0)
	116 ldc2_w (0, 0)
	117 2.0 (0, 0)
	119 dload_1 (0, 0)
	120 dmul (0, 0)
	121 dadd (0, 0)
	122 dload_1 (0, 0)
	123 ldc2_w (0, 0)
	124 2.0 (0, 0)
	126 ddiv (0, 0)
	127 ldc2_w (0, 0)
	128 2.0 (0, 0)
	130 aconst_null (0, 0)
	131 invokespecial (0, 0)
	132 org/apache/commons/math3/stat/descriptive/rank/PSquarePercentile$Marker.<init>:(DDDDLorg/apache/commons/math3/stat/descriptive/rank/PSquarePercentile$1;)V (0, 0)
	134 aastore (0, 0)
	135 dup (0, 0)
	136 iconst_3 (0, 0)
	137 new (0, 0)
	138 org/apache/commons/math3/stat/descriptive/rank/PSquarePercentile$Marker (0, 0)
	140 dup (0, 0)
	141 aload_0 (0, 0)
	142 iconst_2 (0, 0)
	143 invokeinterface (0, 0)
	144 java/util/List.java/lang/Double (0, 0)
	146 0 (0, 0)
	148 checkcast (0, 0)
	149 java/lang/Double (0, 0)
	151 invokevirtual (0, 0)
	152 java/lang/Double.doubleValue:()D (0, 0)
	154 dconst_1 (0, 0)
	155 ldc2_w (0, 0)
	156 4.0 (0, 0)
	158 dload_1 (0, 0)
	159 dmul (0, 0)
	160 dadd (0, 0)
	161 dload_1 (0, 0)
	162 ldc2_w (0, 0)
	163 3.0 (0, 0)
	165 aconst_null (0, 0)
	166 invokespecial (0, 0)
	167 org/apache/commons/math3/stat/descriptive/rank/PSquarePercentile$Marker.<init>:(DDDDLorg/apache/commons/math3/stat/descriptive/rank/PSquarePercentile$1;)V (0, 0)
	169 aastore (0, 0)
	170 dup (0, 0)
	171 iconst_4 (0, 0)
	172 new (0, 0)
	173 org/apache/commons/math3/stat/descriptive/rank/PSquarePercentile$Marker (0, 0)
	175 dup (0, 0)
	176 aload_0 (0, 0)
	177 iconst_3 (0, 0)
	178 invokeinterface (0, 0)
	179 java/util/List.java/lang/Double (0, 0)
	181 0 (0, 0)
	183 checkcast (0, 0)
	184 java/lang/Double (0, 0)
	186 invokevirtual (0, 0)
	187 java/lang/Double.doubleValue:()D (0, 0)
	189 ldc2_w (0, 0)
	190 3.0 (0, 0)
	192 ldc2_w (0, 0)
	193 2.0 (0, 0)
	195 dload_1 (0, 0)
	196 dmul (0, 0)
	197 dadd (0, 0)
	198 dconst_1 (0, 0)
	199 dload_1 (0, 0)
	200 dadd (0, 0)
	201 ldc2_w (0, 0)
	202 2.0 (0, 0)
	204 ddiv (0, 0)
	205 ldc2_w (0, 0)
	206 4.0 (0, 0)
	208 aconst_null (0, 0)
	209 invokespecial (0, 0)
	210 org/apache/commons/math3/stat/descriptive/rank/PSquarePercentile$Marker.<init>:(DDDDLorg/apache/commons/math3/stat/descriptive/rank/PSquarePercentile$1;)V (0, 0)
	212 aastore (0, 0)
	213 dup (0, 0)
	214 iconst_5 (0, 0)
	215 new (0, 0)
	216 org/apache/commons/math3/stat/descriptive/rank/PSquarePercentile$Marker (0, 0)
	218 dup (0, 0)
	219 aload_0 (0, 0)
	220 iconst_4 (0, 0)
	221 invokeinterface (0, 0)
	222 java/util/List.java/lang/Double (0, 0)
	224 0 (0, 0)
	226 checkcast (0, 0)
	227 java/lang/Double (0, 0)
	229 invokevirtual (0, 0)
	230 java/lang/Double.doubleValue:()D (0, 0)
	232 ldc2_w (0, 0)
	233 5.0 (0, 0)
	235 dconst_1 (0, 0)
	236 ldc2_w (0, 0)
	237 5.0 (0, 0)
	239 aconst_null (0, 0)
	240 invokespecial (0, 0)
	241 org/apache/commons/math3/stat/descriptive/rank/PSquarePercentile$Marker.<init>:(DDDDLorg/apache/commons/math3/stat/descriptive/rank/PSquarePercentile$1;)V (0, 0)
	243 aastore (0, 0)
	244 areturn (0, 0)

Method: hashCode
	0 aload_0 (0, 0)
	1 getfield (0, 0)
	2 org/apache/commons/math3/stat/descriptive/rank/PSquarePercentile$Markers.markerArray:[Lorg/apache/commons/math3/stat/descriptive/rank/PSquarePercentile$Marker; (0, 0)
	4 invokestatic (0, 0)
	5 java/util/Arrays.deepHashCode:([Ljava/lang/Object;)I (0, 0)
	7 ireturn (0, 0)

Method: equals
	0 iconst_0 (0, 0)
	1 istore_2 (0, 0)
	2 aload_0 (1, 1)
	3 aload_1 (1, 1)
	4 if_acmpne (1, 1)
	5 8 (1, 1)
	7 iconst_1 (1, 1)
	8 istore_2 (1, 1)
	9 goto (1, 1)
	10 31 (1, 1)
	12 aload_1 (2, 1)
	13 ifnull (2, 1)
	14 27 (2, 1)
	16 aload_1 (2, 1)
	17 instanceof (2, 1)
	18 org/apache/commons/math3/stat/descriptive/rank/PSquarePercentile$Markers (2, 1)
	20 ifeq (2, 1)
	21 20 (2, 1)
	23 aload_1 (2, 1)
	24 checkcast (2, 1)
	25 org/apache/commons/math3/stat/descriptive/rank/PSquarePercentile$Markers (2, 1)
	27 astore_3 (2, 1)
	28 aload_0 (2, 1)
	29 getfield (2, 1)
	30 org/apache/commons/math3/stat/descriptive/rank/PSquarePercentile$Markers.markerArray:[Lorg/apache/commons/math3/stat/descriptive/rank/PSquarePercentile$Marker; (2, 1)
	32 aload_3 (2, 1)
	33 getfield (2, 1)
	34 org/apache/commons/math3/stat/descriptive/rank/PSquarePercentile$Markers.markerArray:[Lorg/apache/commons/math3/stat/descriptive/rank/PSquarePercentile$Marker; (2, 1)
	36 invokestatic (2, 1)
	37 java/util/Arrays.deepEquals:([Ljava/lang/Object;[Ljava/lang/Object;)Z (2, 1)
	39 istore_2 (2, 1)
	40 iload_2 (0, 0)
	41 ireturn (0, 0)

Method: processDataPoint
	0 aload_0 (0, 0)
	1 dload_1 (0, 0)
	2 invokespecial (0, 0)
	3 org/apache/commons/math3/stat/descriptive/rank/PSquarePercentile$Markers.findCellAndUpdateMinMax:(D)I (0, 0)
	5 istore_3 (0, 0)
	6 aload_0 (0, 0)
	7 iconst_1 (0, 0)
	8 iload_3 (0, 0)
	9 iconst_1 (0, 0)
	10 iadd (0, 0)
	11 iconst_5 (0, 0)
	12 invokespecial (0, 0)
	13 org/apache/commons/math3/stat/descriptive/rank/PSquarePercentile$Markers.incrementPositions:(III)V (0, 0)
	15 aload_0 (0, 0)
	16 invokespecial (0, 0)
	17 org/apache/commons/math3/stat/descriptive/rank/PSquarePercentile$Markers.updateDesiredPositions:()V (0, 0)
	19 aload_0 (1, 1)
	20 invokespecial (1, 1)
	21 org/apache/commons/math3/stat/descriptive/rank/PSquarePercentile$Markers.adjustHeightsOfMarkers:()V (1, 1)
	23 aload_0 (1, 1)
	24 invokevirtual (1, 1)
	25 org/apache/commons/math3/stat/descriptive/rank/PSquarePercentile$Markers.getPercentileValue:()D (1, 1)
	27 dreturn (0, 1)

Method: getPercentileValue
	0 aload_0 (0, 0)
	1 iconst_3 (0, 0)
	2 invokevirtual (0, 0)
	3 org/apache/commons/math3/stat/descriptive/rank/PSquarePercentile$Markers.height:(I)D (0, 0)
	5 dreturn (0, 0)

Method: findCellAndUpdateMinMax
	0 aload_0 (0, 0)
	1 iconst_m1 (0, 0)
	2 putfield (0, 0)
	3 org/apache/commons/math3/stat/descriptive/rank/PSquarePercentile$Markers.k:I (0, 0)
	5 dload_1 (1, 1)
	6 aload_0 (1, 1)
	7 iconst_1 (1, 1)
	8 invokevirtual (1, 1)
	9 org/apache/commons/math3/stat/descriptive/rank/PSquarePercentile$Markers.height:(I)D (1, 1)
	11 dcmpg (1, 1)
	12 ifge (1, 1)
	13 22 (1, 1)
	15 aload_0 (1, 1)
	16 getfield (1, 1)
	17 org/apache/commons/math3/stat/descriptive/rank/PSquarePercentile$Markers.markerArray:[Lorg/apache/commons/math3/stat/descriptive/rank/PSquarePercentile$Marker; (1, 1)
	19 iconst_1 (1, 1)
	20 aaload (1, 1)
	21 dload_1 (1, 1)
	22 invokestatic (1, 1)
	23 org/apache/commons/math3/stat/descriptive/rank/PSquarePercentile$Marker.access$502:(Lorg/apache/commons/math3/stat/descriptive/rank/PSquarePercentile$Marker;D)D (1, 1)
	25 pop2 (1, 1)
	26 aload_0 (1, 1)
	27 iconst_1 (1, 1)
	28 putfield (1, 1)
	29 org/apache/commons/math3/stat/descriptive/rank/PSquarePercentile$Markers.k:I (1, 1)
	31 goto (1, 1)
	32 91 (1, 1)
	34 dload_1 (2, 1)
	35 aload_0 (2, 1)
	36 iconst_2 (2, 1)
	37 invokevirtual (2, 1)
	38 org/apache/commons/math3/stat/descriptive/rank/PSquarePercentile$Markers.height:(I)D (2, 1)
	40 dcmpg (2, 1)
	41 ifge (2, 1)
	42 11 (2, 1)
	44 aload_0 (2, 1)
	45 iconst_1 (2, 1)
	46 putfield (2, 1)
	47 org/apache/commons/math3/stat/descriptive/rank/PSquarePercentile$Markers.k:I (2, 1)
	49 goto (2, 1)
	50 73 (2, 1)
	52 dload_1 (3, 1)
	53 aload_0 (3, 1)
	54 iconst_3 (3, 1)
	55 invokevirtual (3, 1)
	56 org/apache/commons/math3/stat/descriptive/rank/PSquarePercentile$Markers.height:(I)D (3, 1)
	58 dcmpg (3, 1)
	59 ifge (3, 1)
	60 11 (3, 1)
	62 aload_0 (3, 1)
	63 iconst_2 (3, 1)
	64 putfield (3, 1)
	65 org/apache/commons/math3/stat/descriptive/rank/PSquarePercentile$Markers.k:I (3, 1)
	67 goto (3, 1)
	68 55 (3, 1)
	70 dload_1 (4, 1)
	71 aload_0 (4, 1)
	72 iconst_4 (4, 1)
	73 invokevirtual (4, 1)
	74 org/apache/commons/math3/stat/descriptive/rank/PSquarePercentile$Markers.height:(I)D (4, 1)
	76 dcmpg (4, 1)
	77 ifge (4, 1)
	78 11 (4, 1)
	80 aload_0 (4, 1)
	81 iconst_3 (4, 1)
	82 putfield (4, 1)
	83 org/apache/commons/math3/stat/descriptive/rank/PSquarePercentile$Markers.k:I (4, 1)
	85 goto (4, 1)
	86 37 (4, 1)
	88 dload_1 (5, 1)
	89 aload_0 (5, 1)
	90 iconst_5 (5, 1)
	91 invokevirtual (5, 1)
	92 org/apache/commons/math3/stat/descriptive/rank/PSquarePercentile$Markers.height:(I)D (5, 1)
	94 dcmpg (5, 1)
	95 ifgt (5, 1)
	96 11 (5, 1)
	98 aload_0 (5, 1)
	99 iconst_4 (5, 1)
	100 putfield (5, 1)
	101 org/apache/commons/math3/stat/descriptive/rank/PSquarePercentile$Markers.k:I (5, 1)
	103 goto (5, 1)
	104 19 (5, 1)
	106 aload_0 (6, 2)
	107 getfield (6, 2)
	108 org/apache/commons/math3/stat/descriptive/rank/PSquarePercentile$Markers.markerArray:[Lorg/apache/commons/math3/stat/descriptive/rank/PSquarePercentile$Marker; (6, 2)
	110 iconst_5 (6, 2)
	111 aaload (6, 2)
	112 dload_1 (6, 2)
	113 invokestatic (6, 2)
	114 org/apache/commons/math3/stat/descriptive/rank/PSquarePercentile$Marker.access$502:(Lorg/apache/commons/math3/stat/descriptive/rank/PSquarePercentile$Marker;D)D (6, 2)
	116 pop2 (6, 2)
	117 aload_0 (6, 2)
	118 iconst_4 (6, 2)
	119 putfield (6, 2)
	120 org/apache/commons/math3/stat/descriptive/rank/PSquarePercentile$Markers.k:I (6, 2)
	122 aload_0 (0, 0)
	123 getfield (0, 0)
	124 org/apache/commons/math3/stat/descriptive/rank/PSquarePercentile$Markers.k:I (0, 0)
	126 ireturn (0, 0)

Method: adjustHeightsOfMarkers
	0 iconst_2 (1, 4)
	1 istore_1 (1, 4)
	2 iload_1 (1, 4)
	3 iconst_4 (1, 4)
	4 if_icmpgt (1, 4)
	5 15 (1, 4)
	7 aload_0 (1, 4)
	8 iload_1 (1, 4)
	9 invokevirtual (1, 4)
	10 org/apache/commons/math3/stat/descriptive/rank/PSquarePercentile$Markers.estimate:(I)D (1, 4)
	12 pop2 (1, 4)
	13 iinc (1, 4)
	14 #1 (1, 4)
	15 -89 (1, 4)
	16 goto (1, 4)
	17 -14 (1, 4)
	19 return (0, 0)

Method: estimate
	0 iload_1 (1, 1)
	1 iconst_2 (1, 1)
	2 if_icmplt (1, 1)
	3 8 (1, 1)
	5 iload_1 (1, 1)
	6 iconst_4 (1, 1)
	7 if_icmple (1, 1)
	8 23 (1, 1)
	10 new (1, 1)
	11 org/apache/commons/math3/exception/OutOfRangeException (1, 1)
	13 dup (1, 1)
	14 iload_1 (1, 1)
	15 invokestatic (1, 1)
	16 java/lang/Integer.valueOf:(I)Ljava/lang/Integer; (1, 1)
	18 iconst_2 (1, 1)
	19 invokestatic (1, 1)
	20 java/lang/Integer.valueOf:(I)Ljava/lang/Integer; (1, 1)
	22 iconst_4 (1, 1)
	23 invokestatic (1, 1)
	24 java/lang/Integer.valueOf:(I)Ljava/lang/Integer; (1, 1)
	26 invokespecial (1, 1)
	27 org/apache/commons/math3/exception/OutOfRangeException.<init>:(Ljava/lang/Number;Ljava/lang/Number;Ljava/lang/Number;)V (1, 1)
	29 athrow (1, 1)
	30 aload_0 (0, 0)
	31 getfield (0, 0)
	32 org/apache/commons/math3/stat/descriptive/rank/PSquarePercentile$Markers.markerArray:[Lorg/apache/commons/math3/stat/descriptive/rank/PSquarePercentile$Marker; (0, 0)
	34 iload_1 (0, 0)
	35 aaload (0, 0)
	36 invokestatic (0, 0)
	37 org/apache/commons/math3/stat/descriptive/rank/PSquarePercentile$Marker.access$600:(Lorg/apache/commons/math3/stat/descriptive/rank/PSquarePercentile$Marker;)D (0, 0)
	39 dreturn (0, 0)

Method: incrementPositions
	0 iload_2 (1, 4)
	1 istore (1, 4)
	2 #4 (1, 4)
	3 iload (1, 4)
	4 #4 (1, 4)
	5 iload_3 (1, 4)
	6 if_icmpgt (1, 4)
	7 20 (1, 4)
	9 aload_0 (1, 4)
	10 getfield (1, 4)
	11 org/apache/commons/math3/stat/descriptive/rank/PSquarePercentile$Markers.markerArray:[Lorg/apache/commons/math3/stat/descriptive/rank/PSquarePercentile$Marker; (1, 4)
	13 iload (1, 4)
	14 #4 (1, 4)
	15 aaload (1, 4)
	16 iload_1 (1, 4)
	17 invokestatic (1, 4)
	18 org/apache/commons/math3/stat/descriptive/rank/PSquarePercentile$Marker.access$700:(Lorg/apache/commons/math3/stat/descriptive/rank/PSquarePercentile$Marker;I)V (1, 4)
	20 iinc (1, 4)
	21 #4 (1, 4)
	22 -89 (1, 4)
	23 goto (1, 4)
	24 -20 (1, 4)
	26 return (0, 0)

Method: updateDesiredPositions
	0 iconst_1 (1, 4)
	1 istore_1 (1, 4)
	2 iload_1 (1, 4)
	3 aload_0 (1, 4)
	4 getfield (1, 4)
	5 org/apache/commons/math3/stat/descriptive/rank/PSquarePercentile$Markers.markerArray:[Lorg/apache/commons/math3/stat/descriptive/rank/PSquarePercentile$Marker; (1, 4)
	7 arraylength (1, 4)
	8 if_icmpge (1, 4)
	9 18 (1, 4)
	11 aload_0 (1, 4)
	12 getfield (1, 4)
	13 org/apache/commons/math3/stat/descriptive/rank/PSquarePercentile$Markers.markerArray:[Lorg/apache/commons/math3/stat/descriptive/rank/PSquarePercentile$Marker; (1, 4)
	15 iload_1 (1, 4)
	16 aaload (1, 4)
	17 invokestatic (1, 4)
	18 org/apache/commons/math3/stat/descriptive/rank/PSquarePercentile$Marker.access$800:(Lorg/apache/commons/math3/stat/descriptive/rank/PSquarePercentile$Marker;)V (1, 4)
	20 iinc (1, 4)
	21 #1 (1, 4)
	22 -89 (1, 4)
	23 goto (1, 4)
	24 -21 (1, 4)
	26 return (0, 0)

Method: readObject
	0 aload_1 (0, 0)
	1 invokevirtual (0, 0)
	2 java/io/ObjectInputStream.defaultReadObject:()V (0, 0)
	4 iconst_1 (1, 4)
	5 istore_2 (1, 4)
	6 iload_2 (1, 4)
	7 iconst_5 (1, 4)
	8 if_icmpge (1, 4)
	9 42 (1, 4)
	11 aload_0 (1, 4)
	12 getfield (1, 4)
	13 org/apache/commons/math3/stat/descriptive/rank/PSquarePercentile$Markers.markerArray:[Lorg/apache/commons/math3/stat/descriptive/rank/PSquarePercentile$Marker; (1, 4)
	15 iload_2 (1, 4)
	16 aaload (1, 4)
	17 aload_0 (1, 4)
	18 getfield (1, 4)
	19 org/apache/commons/math3/stat/descriptive/rank/PSquarePercentile$Markers.markerArray:[Lorg/apache/commons/math3/stat/descriptive/rank/PSquarePercentile$Marker; (1, 4)
	21 iload_2 (1, 4)
	22 iconst_1 (1, 4)
	23 isub (1, 4)
	24 aaload (1, 4)
	25 invokestatic (1, 4)
	26 org/apache/commons/math3/stat/descriptive/rank/PSquarePercentile$Marker.access$000:(Lorg/apache/commons/math3/stat/descriptive/rank/PSquarePercentile$Marker;Lorg/apache/commons/math3/stat/descriptive/rank/PSquarePercentile$Marker;)Lorg/apache/commons/math3/stat/descriptive/rank/PSquarePercentile$Marker; (1, 4)
	28 aload_0 (1, 4)
	29 getfield (1, 4)
	30 org/apache/commons/math3/stat/descriptive/rank/PSquarePercentile$Markers.markerArray:[Lorg/apache/commons/math3/stat/descriptive/rank/PSquarePercentile$Marker; (1, 4)
	32 iload_2 (1, 4)
	33 iconst_1 (1, 4)
	34 iadd (1, 4)
	35 aaload (1, 4)
	36 invokestatic (1, 4)
	37 org/apache/commons/math3/stat/descriptive/rank/PSquarePercentile$Marker.access$100:(Lorg/apache/commons/math3/stat/descriptive/rank/PSquarePercentile$Marker;Lorg/apache/commons/math3/stat/descriptive/rank/PSquarePercentile$Marker;)Lorg/apache/commons/math3/stat/descriptive/rank/PSquarePercentile$Marker; (1, 4)
	39 iload_2 (1, 4)
	40 invokestatic (1, 4)
	41 org/apache/commons/math3/stat/descriptive/rank/PSquarePercentile$Marker.access$200:(Lorg/apache/commons/math3/stat/descriptive/rank/PSquarePercentile$Marker;I)Lorg/apache/commons/math3/stat/descriptive/rank/PSquarePercentile$Marker; (1, 4)
	43 pop (1, 4)
	44 iinc (1, 4)
	45 #2 (1, 4)
	46 -89 (1, 4)
	47 goto (1, 4)
	48 -41 (1, 4)
	50 aload_0 (0, 0)
	51 getfield (0, 0)
	52 org/apache/commons/math3/stat/descriptive/rank/PSquarePercentile$Markers.markerArray:[Lorg/apache/commons/math3/stat/descriptive/rank/PSquarePercentile$Marker; (0, 0)
	54 iconst_0 (0, 0)
	55 aaload (0, 0)
	56 aload_0 (0, 0)
	57 getfield (0, 0)
	58 org/apache/commons/math3/stat/descriptive/rank/PSquarePercentile$Markers.markerArray:[Lorg/apache/commons/math3/stat/descriptive/rank/PSquarePercentile$Marker; (0, 0)
	60 iconst_0 (0, 0)
	61 aaload (0, 0)
	62 invokestatic (0, 0)
	63 org/apache/commons/math3/stat/descriptive/rank/PSquarePercentile$Marker.access$000:(Lorg/apache/commons/math3/stat/descriptive/rank/PSquarePercentile$Marker;Lorg/apache/commons/math3/stat/descriptive/rank/PSquarePercentile$Marker;)Lorg/apache/commons/math3/stat/descriptive/rank/PSquarePercentile$Marker; (0, 0)
	65 aload_0 (0, 0)
	66 getfield (0, 0)
	67 org/apache/commons/math3/stat/descriptive/rank/PSquarePercentile$Markers.markerArray:[Lorg/apache/commons/math3/stat/descriptive/rank/PSquarePercentile$Marker; (0, 0)
	69 iconst_1 (0, 0)
	70 aaload (0, 0)
	71 invokestatic (0, 0)
	72 org/apache/commons/math3/stat/descriptive/rank/PSquarePercentile$Marker.access$100:(Lorg/apache/commons/math3/stat/descriptive/rank/PSquarePercentile$Marker;Lorg/apache/commons/math3/stat/descriptive/rank/PSquarePercentile$Marker;)Lorg/apache/commons/math3/stat/descriptive/rank/PSquarePercentile$Marker; (0, 0)
	74 iconst_0 (0, 0)
	75 invokestatic (0, 0)
	76 org/apache/commons/math3/stat/descriptive/rank/PSquarePercentile$Marker.access$200:(Lorg/apache/commons/math3/stat/descriptive/rank/PSquarePercentile$Marker;I)Lorg/apache/commons/math3/stat/descriptive/rank/PSquarePercentile$Marker; (0, 0)
	78 pop (0, 0)
	79 aload_0 (0, 0)
	80 getfield (0, 0)
	81 org/apache/commons/math3/stat/descriptive/rank/PSquarePercentile$Markers.markerArray:[Lorg/apache/commons/math3/stat/descriptive/rank/PSquarePercentile$Marker; (0, 0)
	83 iconst_5 (0, 0)
	84 aaload (0, 0)
	85 aload_0 (0, 0)
	86 getfield (0, 0)
	87 org/apache/commons/math3/stat/descriptive/rank/PSquarePercentile$Markers.markerArray:[Lorg/apache/commons/math3/stat/descriptive/rank/PSquarePercentile$Marker; (0, 0)
	89 iconst_4 (0, 0)
	90 aaload (0, 0)
	91 invokestatic (0, 0)
	92 org/apache/commons/math3/stat/descriptive/rank/PSquarePercentile$Marker.access$000:(Lorg/apache/commons/math3/stat/descriptive/rank/PSquarePercentile$Marker;Lorg/apache/commons/math3/stat/descriptive/rank/PSquarePercentile$Marker;)Lorg/apache/commons/math3/stat/descriptive/rank/PSquarePercentile$Marker; (0, 0)
	94 aload_0 (0, 0)
	95 getfield (0, 0)
	96 org/apache/commons/math3/stat/descriptive/rank/PSquarePercentile$Markers.markerArray:[Lorg/apache/commons/math3/stat/descriptive/rank/PSquarePercentile$Marker; (0, 0)
	98 iconst_5 (0, 0)
	99 aaload (0, 0)
	100 invokestatic (0, 0)
	101 org/apache/commons/math3/stat/descriptive/rank/PSquarePercentile$Marker.access$100:(Lorg/apache/commons/math3/stat/descriptive/rank/PSquarePercentile$Marker;Lorg/apache/commons/math3/stat/descriptive/rank/PSquarePercentile$Marker;)Lorg/apache/commons/math3/stat/descriptive/rank/PSquarePercentile$Marker; (0, 0)
	103 iconst_5 (0, 0)
	104 invokestatic (0, 0)
	105 org/apache/commons/math3/stat/descriptive/rank/PSquarePercentile$Marker.access$200:(Lorg/apache/commons/math3/stat/descriptive/rank/PSquarePercentile$Marker;I)Lorg/apache/commons/math3/stat/descriptive/rank/PSquarePercentile$Marker; (0, 0)
	107 pop (0, 0)
	108 return (0, 0)

Method: height
	0 iload_1 (1, 1)
	1 aload_0 (1, 1)
	2 getfield (1, 1)
	3 org/apache/commons/math3/stat/descriptive/rank/PSquarePercentile$Markers.markerArray:[Lorg/apache/commons/math3/stat/descriptive/rank/PSquarePercentile$Marker; (1, 1)
	5 arraylength (1, 1)
	6 if_icmpge (1, 1)
	7 7 (1, 1)
	9 iload_1 (1, 1)
	10 ifgt (1, 1)
	11 27 (1, 1)
	13 new (1, 1)
	14 org/apache/commons/math3/exception/OutOfRangeException (1, 1)
	16 dup (1, 1)
	17 iload_1 (1, 1)
	18 invokestatic (1, 1)
	19 java/lang/Integer.valueOf:(I)Ljava/lang/Integer; (1, 1)
	21 iconst_1 (1, 1)
	22 invokestatic (1, 1)
	23 java/lang/Integer.valueOf:(I)Ljava/lang/Integer; (1, 1)
	25 aload_0 (1, 1)
	26 getfield (1, 1)
	27 org/apache/commons/math3/stat/descriptive/rank/PSquarePercentile$Markers.markerArray:[Lorg/apache/commons/math3/stat/descriptive/rank/PSquarePercentile$Marker; (1, 1)
	29 arraylength (1, 1)
	30 invokestatic (1, 1)
	31 java/lang/Integer.valueOf:(I)Ljava/lang/Integer; (1, 1)
	33 invokespecial (1, 1)
	34 org/apache/commons/math3/exception/OutOfRangeException.<init>:(Ljava/lang/Number;Ljava/lang/Number;Ljava/lang/Number;)V (1, 1)
	36 athrow (1, 1)
	37 aload_0 (0, 0)
	38 getfield (0, 0)
	39 org/apache/commons/math3/stat/descriptive/rank/PSquarePercentile$Markers.markerArray:[Lorg/apache/commons/math3/stat/descriptive/rank/PSquarePercentile$Marker; (0, 0)
	41 iload_1 (0, 0)
	42 aaload (0, 0)
	43 invokestatic (0, 0)
	44 org/apache/commons/math3/stat/descriptive/rank/PSquarePercentile$Marker.access$500:(Lorg/apache/commons/math3/stat/descriptive/rank/PSquarePercentile$Marker;)D (0, 0)
	46 dreturn (0, 0)

Method: clone
	0 new (0, 0)
	1 org/apache/commons/math3/stat/descriptive/rank/PSquarePercentile$Markers (0, 0)
	3 dup (0, 0)
	4 bipush (0, 0)
	5 6 (0, 0)
	6 anewarray (0, 0)
	7 org/apache/commons/math3/stat/descriptive/rank/PSquarePercentile$Marker (0, 0)
	9 dup (0, 0)
	10 iconst_0 (0, 0)
	11 new (0, 0)
	12 org/apache/commons/math3/stat/descriptive/rank/PSquarePercentile$Marker (0, 0)
	14 dup (0, 0)
	15 aconst_null (0, 0)
	16 invokespecial (0, 0)
	17 org/apache/commons/math3/stat/descriptive/rank/PSquarePercentile$Marker.<init>:(Lorg/apache/commons/math3/stat/descriptive/rank/PSquarePercentile$1;)V (0, 0)
	19 aastore (0, 0)
	20 dup (0, 0)
	21 iconst_1 (0, 0)
	22 aload_0 (0, 0)
	23 getfield (0, 0)
	24 org/apache/commons/math3/stat/descriptive/rank/PSquarePercentile$Markers.markerArray:[Lorg/apache/commons/math3/stat/descriptive/rank/PSquarePercentile$Marker; (0, 0)
	26 iconst_1 (0, 0)
	27 aaload (0, 0)
	28 invokevirtual (0, 0)
	29 org/apache/commons/math3/stat/descriptive/rank/PSquarePercentile$Marker.clone:()Ljava/lang/Object; (0, 0)
	31 checkcast (0, 0)
	32 org/apache/commons/math3/stat/descriptive/rank/PSquarePercentile$Marker (0, 0)
	34 aastore (0, 0)
	35 dup (0, 0)
	36 iconst_2 (0, 0)
	37 aload_0 (0, 0)
	38 getfield (0, 0)
	39 org/apache/commons/math3/stat/descriptive/rank/PSquarePercentile$Markers.markerArray:[Lorg/apache/commons/math3/stat/descriptive/rank/PSquarePercentile$Marker; (0, 0)
	41 iconst_2 (0, 0)
	42 aaload (0, 0)
	43 invokevirtual (0, 0)
	44 org/apache/commons/math3/stat/descriptive/rank/PSquarePercentile$Marker.clone:()Ljava/lang/Object; (0, 0)
	46 checkcast (0, 0)
	47 org/apache/commons/math3/stat/descriptive/rank/PSquarePercentile$Marker (0, 0)
	49 aastore (0, 0)
	50 dup (0, 0)
	51 iconst_3 (0, 0)
	52 aload_0 (0, 0)
	53 getfield (0, 0)
	54 org/apache/commons/math3/stat/descriptive/rank/PSquarePercentile$Markers.markerArray:[Lorg/apache/commons/math3/stat/descriptive/rank/PSquarePercentile$Marker; (0, 0)
	56 iconst_3 (0, 0)
	57 aaload (0, 0)
	58 invokevirtual (0, 0)
	59 org/apache/commons/math3/stat/descriptive/rank/PSquarePercentile$Marker.clone:()Ljava/lang/Object; (0, 0)
	61 checkcast (0, 0)
	62 org/apache/commons/math3/stat/descriptive/rank/PSquarePercentile$Marker (0, 0)
	64 aastore (0, 0)
	65 dup (0, 0)
	66 iconst_4 (0, 0)
	67 aload_0 (0, 0)
	68 getfield (0, 0)
	69 org/apache/commons/math3/stat/descriptive/rank/PSquarePercentile$Markers.markerArray:[Lorg/apache/commons/math3/stat/descriptive/rank/PSquarePercentile$Marker; (0, 0)
	71 iconst_4 (0, 0)
	72 aaload (0, 0)
	73 invokevirtual (0, 0)
	74 org/apache/commons/math3/stat/descriptive/rank/PSquarePercentile$Marker.clone:()Ljava/lang/Object; (0, 0)
	76 checkcast (0, 0)
	77 org/apache/commons/math3/stat/descriptive/rank/PSquarePercentile$Marker (0, 0)
	79 aastore (0, 0)
	80 dup (0, 0)
	81 iconst_5 (0, 0)
	82 aload_0 (0, 0)
	83 getfield (0, 0)
	84 org/apache/commons/math3/stat/descriptive/rank/PSquarePercentile$Markers.markerArray:[Lorg/apache/commons/math3/stat/descriptive/rank/PSquarePercentile$Marker; (0, 0)
	86 iconst_5 (0, 0)
	87 aaload (0, 0)
	88 invokevirtual (0, 0)
	89 org/apache/commons/math3/stat/descriptive/rank/PSquarePercentile$Marker.clone:()Ljava/lang/Object; (0, 0)
	91 checkcast (0, 0)
	92 org/apache/commons/math3/stat/descriptive/rank/PSquarePercentile$Marker (0, 0)
	94 aastore (0, 0)
	95 invokespecial (0, 0)
	96 org/apache/commons/math3/stat/descriptive/rank/PSquarePercentile$Markers.<init>:([Lorg/apache/commons/math3/stat/descriptive/rank/PSquarePercentile$Marker;)V (0, 0)
	98 areturn (0, 0)

Method: toString
	0 ldc (1, 4)
	1 m1=[%s],m2=[%s],m3=[%s],m4=[%s],m5=[%s] (1, 4)
	2 iconst_5 (1, 4)
	3 anewarray (1, 4)
	4 java/lang/Object (1, 4)
	6 dup (1, 4)
	7 iconst_0 (1, 4)
	8 aload_0 (1, 4)
	9 getfield (1, 4)
	10 org/apache/commons/math3/stat/descriptive/rank/PSquarePercentile$Markers.markerArray:[Lorg/apache/commons/math3/stat/descriptive/rank/PSquarePercentile$Marker; (1, 4)
	12 iconst_1 (1, 4)
	13 aaload (1, 4)
	14 invokevirtual (1, 4)
	15 org/apache/commons/math3/stat/descriptive/rank/PSquarePercentile$Marker.toString:()Ljava/lang/String; (1, 4)
	17 aastore (1, 4)
	18 dup (1, 4)
	19 iconst_1 (1, 4)
	20 aload_0 (1, 4)
	21 getfield (1, 4)
	22 org/apache/commons/math3/stat/descriptive/rank/PSquarePercentile$Markers.markerArray:[Lorg/apache/commons/math3/stat/descriptive/rank/PSquarePercentile$Marker; (1, 4)
	24 iconst_2 (1, 4)
	25 aaload (1, 4)
	26 invokevirtual (1, 4)
	27 org/apache/commons/math3/stat/descriptive/rank/PSquarePercentile$Marker.toString:()Ljava/lang/String; (1, 4)
	29 aastore (1, 4)
	30 dup (1, 4)
	31 iconst_2 (1, 4)
	32 aload_0 (1, 4)
	33 getfield (1, 4)
	34 org/apache/commons/math3/stat/descriptive/rank/PSquarePercentile$Markers.markerArray:[Lorg/apache/commons/math3/stat/descriptive/rank/PSquarePercentile$Marker; (1, 4)
	36 iconst_3 (1, 4)
	37 aaload (1, 4)
	38 invokevirtual (1, 4)
	39 org/apache/commons/math3/stat/descriptive/rank/PSquarePercentile$Marker.toString:()Ljava/lang/String; (1, 4)
	41 aastore (1, 4)
	42 dup (1, 4)
	43 iconst_3 (1, 4)
	44 aload_0 (1, 4)
	45 getfield (1, 4)
	46 org/apache/commons/math3/stat/descriptive/rank/PSquarePercentile$Markers.markerArray:[Lorg/apache/commons/math3/stat/descriptive/rank/PSquarePercentile$Marker; (1, 4)
	48 iconst_4 (1, 4)
	49 aaload (1, 4)
	50 invokevirtual (1, 4)
	51 org/apache/commons/math3/stat/descriptive/rank/PSquarePercentile$Marker.toString:()Ljava/lang/String; (1, 4)
	53 aastore (1, 4)
	54 dup (1, 4)
	55 iconst_4 (1, 4)
	56 aload_0 (1, 4)
	57 getfield (1, 4)
	58 org/apache/commons/math3/stat/descriptive/rank/PSquarePercentile$Markers.markerArray:[Lorg/apache/commons/math3/stat/descriptive/rank/PSquarePercentile$Marker; (1, 4)
	60 iconst_5 (1, 4)
	61 aaload (1, 4)
	62 invokevirtual (1, 4)
	63 org/apache/commons/math3/stat/descriptive/rank/PSquarePercentile$Marker.toString:()Ljava/lang/String; (1, 4)
	65 aastore (1, 4)
	66 invokestatic (1, 4)
	67 java/lang/String.format:(Ljava/lang/String;[Ljava/lang/Object;)Ljava/lang/String; (1, 4)
	69 areturn (0, 4)

