Method: <init>
	0 aload_0 (0, 0)
	1 ldc2_w (0, 0)
	4 invokespecial (0, 0)
	7 return (0, 0)

Method: hashCode
	0 aload_0 (0, 0)
	1 invokevirtual (0, 0)
	4 dstore_1 (0, 0)
	5 dload_1 (0, 0)
	6 invokestatic (0, 0)
	9 ifeq (0, 0)
	12 ldc2_w (0, 0)
	15 goto (0, 0)
	18 dload_1 (0, 0)
	19 dstore_1 (0, 0)
	20 aload_0 (0, 0)
	21 getfield (0, 0)
	24 ifnonnull (0, 0)
	27 dconst_0 (0, 0)
	28 goto (0, 0)
	31 aload_0 (0, 0)
	32 getfield (0, 0)
	35 invokevirtual (0, 0)
	38 i2d (0, 0)
	39 dstore_3 (0, 0)
	40 iconst_4 (0, 0)
	41 newarray (0, 0)
	43 dup (0, 0)
	44 iconst_0 (0, 0)
	45 dload_1 (0, 0)
	46 dastore (0, 0)
	47 dup (0, 0)
	48 iconst_1 (0, 0)
	49 aload_0 (0, 0)
	50 getfield (0, 0)
	53 dastore (0, 0)
	54 dup (0, 0)
	55 iconst_2 (0, 0)
	56 dload_3 (0, 0)
	57 dastore (0, 0)
	58 dup (0, 0)
	59 iconst_3 (0, 0)
	60 aload_0 (0, 0)
	61 getfield (0, 0)
	64 l2d (0, 0)
	65 dastore (0, 0)
	66 astore (0, 0)
	68 aload (0, 0)
	70 invokestatic (0, 0)
	73 ireturn (0, 0)

Method: equals
	0 iconst_0 (0, 0)
	1 istore_2 (0, 0)
	2 aload_0 (1, 1)
	3 aload_1 (1, 1)
	4 if_acmpne (1, 1)
	7 iconst_1 (1, 1)
	8 istore_2 (1, 1)
	9 goto (1, 1)
	12 aload_1 (1, 1)
	13 ifnull (1, 1)
	16 aload_1 (1, 1)
	17 instanceof (1, 1)
	20 ifeq (1, 1)
	23 aload_1 (1, 1)
	24 checkcast (1, 1)
	27 astore_3 (1, 1)
	28 aload_0 (1, 1)
	29 getfield (1, 1)
	32 ifnull (1, 1)
	35 aload_3 (1, 1)
	36 getfield (1, 1)
	39 ifnull (1, 1)
	42 iconst_1 (1, 1)
	43 goto (1, 1)
	46 iconst_0 (1, 1)
	47 istore (1, 1)
	49 aload_0 (1, 1)
	50 getfield (1, 1)
	53 ifnonnull (1, 1)
	56 aload_3 (1, 1)
	57 getfield (1, 1)
	60 ifnonnull (1, 1)
	63 iconst_1 (1, 1)
	64 goto (1, 1)
	67 iconst_0 (1, 1)
	68 istore (1, 1)
	70 iload (1, 1)
	72 ifeq (1, 1)
	75 aload_0 (1, 1)
	76 getfield (1, 1)
	79 aload_3 (1, 1)
	80 getfield (1, 1)
	83 invokevirtual (1, 1)
	86 goto (1, 1)
	89 iload (1, 1)
	91 istore_2 (1, 1)
	92 iload_2 (1, 1)
	93 ifeq (1, 1)
	96 aload_0 (1, 1)
	97 invokevirtual (1, 1)
	100 aload_3 (1, 1)
	101 invokevirtual (1, 1)
	104 lcmp (1, 1)
	105 ifne (1, 1)
	108 iconst_1 (1, 1)
	109 goto (1, 1)
	112 iconst_0 (1, 1)
	113 istore_2 (1, 1)
	114 iload_2 (0, 1)
	115 ireturn (0, 1)

Method: increment
	0 aload_0 (0, 0)
	1 dup (0, 0)
	2 getfield (0, 0)
	5 lconst_1 (0, 0)
	6 ladd (0, 0)
	7 putfield (0, 0)
	10 aload_0 (0, 0)
	11 dload_1 (0, 0)
	12 putfield (0, 0)
	15 aload_0 (1, 1)
	16 getfield (1, 1)
	19 ifnonnull (1, 1)
	22 aload_0 (2, 1)
	23 getfield (2, 1)
	26 dload_1 (2, 1)
	27 invokestatic (2, 1)
	30 invokeinterface (2, 1)
	35 ifeq (2, 1)
	38 aload_0 (2, 1)
	39 getfield (2, 1)
	42 invokestatic (2, 1)
	45 aload_0 (2, 1)
	46 aload_0 (2, 1)
	47 getfield (2, 1)
	50 aload_0 (2, 1)
	51 getfield (2, 1)
	54 aload_0 (2, 1)
	55 getfield (2, 1)
	58 invokeinterface (2, 1)
	63 iconst_1 (2, 1)
	64 isub (2, 1)
	65 i2d (2, 1)
	66 dmul (2, 1)
	67 d2i (2, 1)
	68 invokeinterface (2, 1)
	73 checkcast (2, 1)
	76 invokevirtual (2, 1)
	79 putfield (2, 1)
	82 return (2, 1)
	83 aload_0 (1, 1)
	84 aload_0 (1, 1)
	85 getfield (1, 1)
	88 aload_0 (1, 1)
	89 getfield (1, 1)
	92 invokestatic (1, 1)
	95 putfield (1, 1)
	98 aload_0 (0, 4)
	99 aload_0 (0, 4)
	100 getfield (0, 4)
	103 dload_1 (0, 4)
	104 invokeinterface (0, 4)
	109 putfield (0, 4)
	112 return (0, 0)

Method: toString
	0 aload_0 (1, 1)
	1 getfield (1, 1)
	4 ifnonnull (1, 1)
	7 ldc (1, 4)
	9 iconst_2 (1, 4)
	10 anewarray (1, 4)
	13 dup (1, 4)
	14 iconst_0 (1, 4)
	15 getstatic (1, 4)
	18 aload_0 (1, 4)
	19 getfield (1, 4)
	22 invokevirtual (1, 4)
	25 aastore (1, 4)
	26 dup (1, 4)
	27 iconst_1 (1, 4)
	28 getstatic (1, 4)
	31 aload_0 (1, 4)
	32 getfield (1, 4)
	35 invokevirtual (1, 4)
	38 aastore (1, 4)
	39 invokestatic (1, 4)
	42 areturn (1, 4)
	43 ldc (1, 4)
	45 iconst_2 (1, 4)
	46 anewarray (1, 4)
	49 dup (1, 4)
	50 iconst_0 (1, 4)
	51 getstatic (1, 4)
	54 aload_0 (1, 4)
	55 getfield (1, 4)
	58 invokevirtual (1, 4)
	61 aastore (1, 4)
	62 dup (1, 4)
	63 iconst_1 (1, 4)
	64 aload_0 (1, 4)
	65 getfield (1, 4)
	68 invokevirtual (1, 4)
	71 aastore (1, 4)
	72 invokestatic (1, 4)
	75 areturn (1, 4)

Method: getN
	0 aload_0 (0, 0)
	1 getfield (0, 0)
	4 lreturn (0, 0)

Method: copy
	0 aload_0 (0, 0)
	1 invokevirtual (0, 0)
	4 areturn (0, 0)

Method: quantile
	0 aload_0 (0, 0)
	1 getfield (0, 0)
	4 dreturn (0, 0)

Method: clear
	0 aload_0 (0, 0)
	1 aconst_null (0, 0)
	2 putfield (0, 0)
	5 aload_0 (0, 0)
	6 getfield (0, 0)
	9 invokeinterface (0, 0)
	14 aload_0 (0, 0)
	15 lconst_0 (0, 0)
	16 putfield (0, 0)
	19 aload_0 (0, 0)
	20 ldc2_w (0, 0)
	23 putfield (0, 0)
	26 return (0, 0)

Method: getResult
	0 aload_0 (1, 1)
	1 getfield (1, 1)
	4 dconst_1 (1, 1)
	5 invokestatic (1, 1)
	8 ifne (1, 1)
	11 aload_0 (1, 1)
	12 aload_0 (1, 1)
	13 invokespecial (1, 1)
	16 putfield (1, 1)
	19 goto (1, 1)
	22 aload_0 (1, 1)
	23 getfield (1, 1)
	26 dconst_0 (1, 1)
	27 invokestatic (1, 1)
	30 ifne (1, 1)
	33 aload_0 (1, 1)
	34 aload_0 (1, 1)
	35 invokespecial (1, 1)
	38 putfield (1, 1)
	41 aload_0 (0, 1)
	42 getfield (0, 1)
	45 dreturn (0, 1)

Method: maximum
	0 ldc2_w (0, 0)
	3 dstore_1 (0, 0)
	4 aload_0 (1, 1)
	5 getfield (1, 1)
	8 ifnull (1, 1)
	11 aload_0 (1, 1)
	12 getfield (1, 1)
	15 iconst_5 (1, 1)
	16 invokeinterface (1, 1)
	21 dstore_1 (1, 1)
	22 goto (1, 1)
	25 aload_0 (1, 1)
	26 getfield (1, 1)
	29 invokeinterface (1, 1)
	34 ifne (1, 1)
	37 aload_0 (1, 1)
	38 getfield (1, 1)
	41 aload_0 (1, 1)
	42 getfield (1, 1)
	45 invokeinterface (1, 1)
	50 iconst_1 (1, 1)
	51 isub (1, 1)
	52 invokeinterface (1, 1)
	57 checkcast (1, 1)
	60 invokevirtual (1, 1)
	63 dstore_1 (1, 1)
	64 dload_1 (0, 1)
	65 dreturn (0, 1)

Method: minimum
	0 ldc2_w (0, 0)
	3 dstore_1 (0, 0)
	4 aload_0 (1, 1)
	5 getfield (1, 1)
	8 ifnull (1, 1)
	11 aload_0 (1, 1)
	12 getfield (1, 1)
	15 iconst_1 (1, 1)
	16 invokeinterface (1, 1)
	21 dstore_1 (1, 1)
	22 goto (1, 1)
	25 aload_0 (1, 1)
	26 getfield (1, 1)
	29 invokeinterface (1, 1)
	34 ifne (1, 1)
	37 aload_0 (1, 1)
	38 getfield (1, 1)
	41 iconst_0 (1, 1)
	42 invokeinterface (1, 1)
	47 checkcast (1, 1)
	50 invokevirtual (1, 1)
	53 dstore_1 (1, 1)
	54 dload_1 (0, 1)
	55 dreturn (0, 1)

Method: newMarkers
	0 new (0, 0)
	3 dup (0, 0)
	4 aload_0 (0, 0)
	5 dload_1 (0, 0)
	6 aconst_null (0, 0)
	7 invokespecial (0, 0)
	10 areturn (0, 0)

Method: <clinit>
	0 new (0, 0)
	3 dup (0, 0)
	4 ldc (0, 0)
	6 invokespecial (0, 0)
	9 putstatic (0, 0)
	12 return (0, 0)

