Method: value
	0 aload_0 (0, 0)
	1 aload_3 (0, 0)
	2 invokespecial (0, 0)
	3 org/apache/commons/math3/analysis/function/Gaussian$Parametric.validateParameters:([D)V (0, 0)
	5 dload_1 (0, 1)
	6 aload_3 (0, 1)
	7 iconst_1 (0, 1)
	8 daload (0, 1)
	9 dsub (0, 1)
	10 dstore (0, 1)
	11 #4 (0, 1)
	12 dconst_1 (0, 1)
	13 ldc2_w (0, 1)
	14 2.0 (0, 1)
	16 aload_3 (0, 1)
	17 iconst_2 (0, 1)
	18 daload (0, 1)
	19 dmul (0, 1)
	20 aload_3 (0, 1)
	21 iconst_2 (0, 1)
	22 daload (0, 1)
	23 dmul (0, 1)
	24 ddiv (0, 1)
	25 dstore (0, 1)
	26 #6 (0, 1)
	27 dload (0, 1)
	28 #4 (0, 1)
	29 aload_3 (0, 1)
	30 iconst_0 (0, 1)
	31 daload (0, 1)
	32 dload (0, 1)
	33 #6 (0, 1)
	34 invokestatic (0, 1)
	35 org/apache/commons/math3/analysis/function/Gaussian.access$000:(DDD)D (0, 1)
	37 dreturn (0, 1)

Method: gradient
	0 aload_0 (0, 0)
	1 aload_3 (0, 0)
	2 invokespecial (0, 0)
	3 org/apache/commons/math3/analysis/function/Gaussian$Parametric.validateParameters:([D)V (0, 0)
	5 aload_3 (0, 0)
	6 iconst_0 (0, 0)
	7 daload (0, 0)
	8 dstore (0, 0)
	9 #4 (0, 0)
	10 dload_1 (0, 1)
	11 aload_3 (0, 1)
	12 iconst_1 (0, 1)
	13 daload (0, 1)
	14 dsub (0, 1)
	15 dstore (0, 1)
	16 #6 (0, 1)
	17 aload_3 (0, 1)
	18 iconst_2 (0, 1)
	19 daload (0, 1)
	20 dstore (0, 1)
	21 #8 (0, 1)
	22 dconst_1 (0, 1)
	23 ldc2_w (0, 1)
	24 2.0 (0, 1)
	26 dload (0, 1)
	27 #8 (0, 1)
	28 dmul (0, 1)
	29 dload (0, 1)
	30 #8 (0, 1)
	31 dmul (0, 1)
	32 ddiv (0, 1)
	33 dstore (0, 1)
	34 #10 (0, 1)
	35 dload (0, 1)
	36 #6 (0, 1)
	37 dconst_1 (0, 1)
	38 dload (0, 1)
	39 #10 (0, 1)
	40 invokestatic (0, 1)
	41 org/apache/commons/math3/analysis/function/Gaussian.access$000:(DDD)D (0, 1)
	43 dstore (0, 1)
	44 #12 (0, 1)
	45 dload (0, 1)
	46 #4 (0, 1)
	47 dload (0, 1)
	48 #12 (0, 1)
	49 dmul (0, 1)
	50 ldc2_w (0, 1)
	51 2.0 (0, 1)
	53 dmul (0, 1)
	54 dload (0, 1)
	55 #10 (0, 1)
	56 dmul (0, 1)
	57 dload (0, 1)
	58 #6 (0, 1)
	59 dmul (0, 1)
	60 dstore (0, 1)
	61 #14 (0, 1)
	62 dload (0, 1)
	63 #14 (0, 1)
	64 dload (0, 1)
	65 #6 (0, 1)
	66 dmul (0, 1)
	67 dload (0, 1)
	68 #8 (0, 1)
	69 ddiv (0, 1)
	70 dstore (0, 1)
	71 #16 (0, 1)
	72 iconst_3 (0, 1)
	73 newarray (0, 1)
	74 7 (0, 1)
	75 dup (0, 1)
	76 iconst_0 (0, 1)
	77 dload (0, 1)
	78 #12 (0, 1)
	79 dastore (0, 1)
	80 dup (0, 1)
	81 iconst_1 (0, 1)
	82 dload (0, 1)
	83 #14 (0, 1)
	84 dastore (0, 1)
	85 dup (0, 1)
	86 iconst_2 (0, 1)
	87 dload (0, 1)
	88 #16 (0, 1)
	89 dastore (0, 1)
	90 areturn (0, 1)

Method: validateParameters
	0 aload_1 (1, 1)
	1 ifnonnull (1, 1)
	2 11 (1, 1)
	4 new (1, 1)
	5 org/apache/commons/math3/exception/NullArgumentException (1, 1)
	7 dup (1, 1)
	8 invokespecial (1, 1)
	9 org/apache/commons/math3/exception/NullArgumentException.<init>:()V (1, 1)
	11 athrow (1, 1)
	12 aload_1 (1, 1)
	13 arraylength (1, 1)
	14 iconst_3 (1, 1)
	15 if_icmpeq (1, 1)
	16 14 (1, 1)
	18 new (1, 1)
	19 org/apache/commons/math3/exception/DimensionMismatchException (1, 1)
	21 dup (1, 1)
	22 aload_1 (1, 1)
	23 arraylength (1, 1)
	24 iconst_3 (1, 1)
	25 invokespecial (1, 1)
	26 org/apache/commons/math3/exception/DimensionMismatchException.<init>:(II)V (1, 1)
	28 athrow (1, 1)
	29 aload_1 (1, 1)
	30 iconst_2 (1, 1)
	31 daload (1, 1)
	32 dconst_0 (1, 1)
	33 dcmpg (1, 1)
	34 ifgt (1, 1)
	35 17 (1, 1)
	37 new (1, 1)
	38 org/apache/commons/math3/exception/NotStrictlyPositiveException (1, 1)
	40 dup (1, 1)
	41 aload_1 (1, 1)
	42 iconst_2 (1, 1)
	43 daload (1, 1)
	44 invokestatic (1, 1)
	45 java/lang/Double.valueOf:(D)Ljava/lang/Double; (1, 1)
	47 invokespecial (1, 1)
	48 org/apache/commons/math3/exception/NotStrictlyPositiveException.<init>:(Ljava/lang/Number;)V (1, 1)
	50 athrow (1, 1)
	51 return (0, 0)

