Method: value
	0 aload_0 (0, 0)
	1 aload_3 (0, 0)
	2 invokespecial (0, 0)
	5 aload_3 (0, 0)
	6 iconst_1 (0, 0)
	7 daload (0, 0)
	8 dload_1 (0, 0)
	9 dsub (0, 0)
	10 aload_3 (0, 0)
	11 iconst_0 (0, 0)
	12 daload (0, 0)
	13 aload_3 (0, 0)
	14 iconst_2 (0, 0)
	15 daload (0, 0)
	16 aload_3 (0, 0)
	17 iconst_3 (0, 0)
	18 daload (0, 0)
	19 aload_3 (0, 0)
	20 iconst_4 (0, 0)
	21 daload (0, 0)
	22 dconst_1 (0, 0)
	23 aload_3 (0, 0)
	24 iconst_5 (0, 0)
	25 daload (0, 0)
	26 ddiv (0, 0)
	27 invokestatic (0, 0)
	30 dreturn (0, 0)

Method: gradient
	0 aload_0 (0, 0)
	1 aload_3 (0, 0)
	2 invokespecial (0, 0)
	5 aload_3 (0, 0)
	6 iconst_2 (0, 0)
	7 daload (0, 0)
	8 dstore (0, 0)
	10 aload_3 (0, 0)
	11 iconst_3 (0, 0)
	12 daload (0, 0)
	13 dstore (0, 0)
	15 aload_3 (0, 0)
	16 iconst_1 (0, 0)
	17 daload (0, 0)
	18 dload_1 (0, 0)
	19 dsub (0, 0)
	20 dstore (0, 0)
	22 dconst_1 (0, 0)
	23 aload_3 (0, 0)
	24 iconst_5 (0, 0)
	25 daload (0, 0)
	26 ddiv (0, 0)
	27 dstore (0, 0)
	29 dload (0, 0)
	31 dload (0, 0)
	33 dmul (0, 0)
	34 invokestatic (0, 0)
	37 dstore (0, 0)
	39 dload (0, 0)
	41 dload (0, 0)
	43 dmul (0, 0)
	44 dstore (0, 0)
	46 dload (0, 0)
	48 dconst_1 (0, 0)
	49 dadd (0, 0)
	50 dstore (0, 0)
	52 aload_3 (0, 0)
	53 iconst_0 (0, 0)
	54 daload (0, 0)
	55 aload_3 (0, 0)
	56 iconst_4 (0, 0)
	57 daload (0, 0)
	58 dsub (0, 0)
	59 dload (0, 0)
	61 dmul (0, 0)
	62 dload (0, 0)
	64 dload (0, 0)
	66 invokestatic (0, 0)
	69 ddiv (0, 0)
	70 dstore (0, 0)
	72 dload (0, 0)
	74 dneg (0, 0)
	75 dload (0, 0)
	77 ddiv (0, 0)
	78 dstore (0, 0)
	80 dload (0, 0)
	82 dconst_1 (0, 0)
	83 dload (0, 0)
	85 dload (0, 0)
	87 dconst_0 (0, 0)
	88 dload (0, 0)
	90 invokestatic (0, 0)
	93 dstore (0, 0)
	95 dload (0, 0)
	97 dload (0, 0)
	99 dmul (0, 0)
	100 dload (0, 0)
	102 dmul (0, 0)
	103 dstore (0, 0)
	105 dload (0, 0)
	107 dload (0, 0)
	109 dmul (0, 0)
	110 dload (0, 0)
	112 dmul (0, 0)
	113 dstore (0, 0)
	115 dload (0, 0)
	117 dload (0, 0)
	119 dmul (0, 0)
	120 dstore (0, 0)
	122 dload (0, 0)
	124 dconst_0 (0, 0)
	125 dload (0, 0)
	127 dload (0, 0)
	129 dconst_1 (0, 0)
	130 dload (0, 0)
	132 invokestatic (0, 0)
	135 dstore (0, 0)
	137 dload (0, 0)
	139 dload (0, 0)
	141 invokestatic (0, 0)
	144 dmul (0, 0)
	145 dload (0, 0)
	147 dmul (0, 0)
	148 dstore (0, 0)
	150 bipush (0, 0)
	152 newarray (0, 0)
	154 dup (0, 0)
	155 iconst_0 (0, 0)
	156 dload (0, 0)
	158 dastore (0, 0)
	159 dup (0, 0)
	160 iconst_1 (0, 0)
	161 dload (0, 0)
	163 dastore (0, 0)
	164 dup (0, 0)
	165 iconst_2 (0, 0)
	166 dload (0, 0)
	168 dastore (0, 0)
	169 dup (0, 0)
	170 iconst_3 (0, 0)
	171 dload (0, 0)
	173 dastore (0, 0)
	174 dup (0, 0)
	175 iconst_4 (0, 0)
	176 dload (0, 0)
	178 dastore (0, 0)
	179 dup (0, 0)
	180 iconst_5 (0, 0)
	181 dload (0, 0)
	183 dastore (0, 0)
	184 areturn (0, 0)

Method: validateParameters
	0 aload_1 (1, 1)
	1 ifnonnull (1, 1)
	4 new (1, 1)
	7 dup (1, 1)
	8 invokespecial (1, 1)
	11 athrow (1, 1)
	12 aload_1 (1, 1)
	13 arraylength (1, 1)
	14 bipush (1, 1)
	16 if_icmpeq (1, 1)
	19 new (1, 1)
	22 dup (1, 1)
	23 aload_1 (1, 1)
	24 arraylength (1, 1)
	25 bipush (1, 1)
	27 invokespecial (1, 1)
	30 athrow (1, 1)
	31 aload_1 (1, 1)
	32 iconst_5 (1, 1)
	33 daload (1, 1)
	34 dconst_0 (1, 1)
	35 dcmpg (1, 1)
	36 ifgt (1, 1)
	39 new (1, 1)
	42 dup (1, 1)
	43 aload_1 (1, 1)
	44 iconst_5 (1, 1)
	45 daload (1, 1)
	46 invokestatic (1, 1)
	49 invokespecial (1, 1)
	52 athrow (1, 1)
	53 return (0, 0)

