Method: <init>
	0 aload_0 (0, 0)
	1 invokespecial (0, 0)
	4 dload (1, 1)
	6 dconst_0 (1, 1)
	7 dcmpg (1, 1)
	8 ifgt (1, 1)
	11 new (1, 1)
	14 dup (1, 1)
	15 dload (1, 1)
	17 invokestatic (1, 1)
	20 invokespecial (1, 1)
	23 athrow (1, 1)
	24 aload_0 (0, 0)
	25 dload_1 (0, 0)
	26 putfield (0, 0)
	29 aload_0 (0, 0)
	30 dload_3 (0, 0)
	31 putfield (0, 0)
	34 aload_0 (0, 0)
	35 dload (0, 0)
	37 putfield (0, 0)
	40 aload_0 (0, 0)
	41 dload (0, 0)
	43 putfield (0, 0)
	46 aload_0 (0, 0)
	47 dload (0, 0)
	49 putfield (0, 0)
	52 aload_0 (0, 0)
	53 dconst_1 (0, 0)
	54 dload (0, 0)
	56 ddiv (0, 0)
	57 putfield (0, 0)
	60 return (0, 0)

Method: value
	0 aload_1 (0, 0)
	1 invokevirtual (0, 0)
	4 aload_0 (0, 0)
	5 getfield (0, 0)
	8 invokevirtual (0, 0)
	11 aload_0 (0, 0)
	12 getfield (0, 0)
	15 invokevirtual (0, 0)
	18 invokevirtual (0, 0)
	21 aload_0 (0, 0)
	22 getfield (0, 0)
	25 invokevirtual (0, 0)
	28 dconst_1 (0, 0)
	29 invokevirtual (0, 0)
	32 aload_0 (0, 0)
	33 getfield (0, 0)
	36 invokevirtual (0, 0)
	39 invokevirtual (0, 0)
	42 aload_0 (0, 0)
	43 getfield (0, 0)
	46 aload_0 (0, 0)
	47 getfield (0, 0)
	50 dsub (0, 0)
	51 invokevirtual (0, 0)
	54 aload_0 (0, 0)
	55 getfield (0, 0)
	58 invokevirtual (0, 0)
	61 areturn (0, 0)

Method: derivative
	0 aload_0 (0, 1)
	1 invokestatic (0, 1)
	4 invokeinterface (0, 1)
	9 areturn (0, 1)

Method: access$000
	0 dload_0 (1, 1)
	1 dload_2 (1, 1)
	2 dload (1, 1)
	4 dload (1, 1)
	6 dload (1, 1)
	8 dload (1, 1)
	10 invokestatic (1, 1)
	13 dreturn (1, 1)

