Method: <init>
	0 aload_0 (0, 0)
	1 invokespecial (0, 0)
	2 java/lang/Object.<init>:()V (0, 0)
	4 aload_0 (0, 0)
	5 dload_1 (0, 0)
	6 putfield (0, 0)
	7 org/apache/commons/math3/analysis/function/Power.p:D (0, 0)
	9 return (0, 0)

Method: value
	0 aload_1 (0, 0)
	1 aload_0 (0, 0)
	2 getfield (0, 0)
	3 org/apache/commons/math3/analysis/function/Power.p:D (0, 0)
	5 invokevirtual (0, 0)
	6 org/apache/commons/math3/analysis/differentiation/DerivativeStructure.pow:(D)Lorg/apache/commons/math3/analysis/differentiation/DerivativeStructure; (0, 0)
	8 areturn (0, 0)

Method: derivative
	0 aload_0 (1, 1)
	1 invokestatic (1, 1)
	2 org/apache/commons/math3/analysis/FunctionUtils.toDifferentiableUnivariateFunction:(Lorg/apache/commons/math3/analysis/differentiation/UnivariateDifferentiableFunction;)Lorg/apache/commons/math3/analysis/DifferentiableUnivariateFunction; (1, 1)
	4 invokeinterface (1, 1)
	5 org/apache/commons/math3/analysis/DifferentiableUnivariateFunction.org/apache/commons/math3/analysis/differentiation/DerivativeStructure (1, 1)
	7 0 (1, 1)
	9 areturn (0, 1)

