Method: <init>
	0 aload_0 (0, 0)
	1 invokespecial (0, 0)
	2 java/lang/Object.<init>:()V (0, 0)
	4 aload_0 (0, 0)
	5 iload_1 (0, 0)
	6 putfield (0, 0)
	7 org/apache/commons/math3/analysis/function/Sinc.normalized:Z (0, 0)
	9 return (0, 0)

Method: value
	0 aload_0 (0, 0)
	1 getfield (0, 0)
	2 org/apache/commons/math3/analysis/function/Sinc.normalized:Z (0, 0)
	4 ifeq (0, 0)
	5 9 (0, 0)
	7 ldc2_w (0, 0)
	8 3.141592653589793 (0, 0)
	10 goto (0, 0)
	11 4 (0, 0)
	13 dconst_1 (0, 0)
	14 aload_1 (0, 0)
	15 invokevirtual (0, 0)
	16 org/apache/commons/math3/analysis/differentiation/DerivativeStructure.getValue:()D (0, 0)
	18 dmul (0, 0)
	19 dstore_2 (0, 0)
	20 dload_2 (0, 0)
	21 dload_2 (0, 0)
	22 dmul (0, 0)
	23 dstore (0, 0)
	24 #4 (0, 0)
	25 aload_1 (0, 0)
	26 invokevirtual (0, 0)
	27 org/apache/commons/math3/analysis/differentiation/DerivativeStructure.getOrder:()I (0, 0)
	29 iconst_1 (0, 0)
	30 iadd (0, 0)
	31 newarray (0, 0)
	32 7 (0, 0)
	33 astore (0, 0)
	34 #6 (0, 0)
	35 dload_2 (1, 1)
	36 invokestatic (1, 1)
	37 org/apache/commons/math3/util/FastMath.abs:(D)D (1, 1)
	39 ldc2_w (1, 1)
	40 0.006 (1, 1)
	42 dcmpg (1, 1)
	43 ifgt (1, 1)
	44 147 (1, 1)
	46 iconst_0 (2, 4)
	47 istore (2, 4)
	48 #7 (2, 4)
	49 iload (2, 4)
	50 #7 (2, 4)
	51 aload (2, 4)
	52 #6 (2, 4)
	53 arraylength (2, 4)
	54 if_icmpge (2, 4)
	55 133 (2, 4)
	57 iload (2, 4)
	58 #7 (2, 4)
	59 iconst_2 (2, 4)
	60 idiv (2, 4)
	61 istore (2, 4)
	62 #8 (2, 4)
	63 iload (3, 1)
	64 #7 (3, 1)
	65 iconst_1 (3, 1)
	66 iand (3, 1)
	67 ifne (3, 1)
	68 59 (3, 1)
	70 aload (3, 1)
	71 #6 (3, 1)
	72 iload (3, 1)
	73 #7 (3, 1)
	74 iload (3, 1)
	75 #8 (3, 1)
	76 iconst_1 (3, 1)
	77 iand (3, 1)
	78 ifne (3, 1)
	79 7 (3, 1)
	81 iconst_1 (3, 1)
	82 goto (3, 1)
	83 4 (3, 1)
	85 iconst_m1 (3, 1)
	86 i2d (3, 1)
	87 dconst_1 (3, 1)
	88 iload (3, 1)
	89 #7 (3, 1)
	90 iconst_1 (3, 1)
	91 iadd (3, 1)
	92 i2d (3, 1)
	93 ddiv (3, 1)
	94 dload (3, 1)
	95 #4 (3, 1)
	96 dconst_1 (3, 1)
	97 iconst_2 (3, 1)
	98 iload (3, 1)
	99 #7 (3, 1)
	100 imul (3, 1)
	101 bipush (3, 1)
	102 6 (3, 1)
	103 iadd (3, 1)
	104 i2d (3, 1)
	105 ddiv (3, 1)
	106 dload (3, 1)
	107 #4 (3, 1)
	108 bipush (3, 1)
	109 24 (3, 1)
	110 iload (3, 1)
	111 #7 (3, 1)
	112 imul (3, 1)
	113 bipush (3, 1)
	114 120 (3, 1)
	115 iadd (3, 1)
	116 i2d (3, 1)
	117 ddiv (3, 1)
	118 dsub (3, 1)
	119 dmul (3, 1)
	120 dsub (3, 1)
	121 dmul (3, 1)
	122 dastore (3, 1)
	123 goto (3, 1)
	124 58 (3, 1)
	126 aload (4, 2)
	127 #6 (4, 2)
	128 iload (4, 2)
	129 #7 (4, 2)
	130 iload (4, 2)
	131 #8 (4, 2)
	132 iconst_1 (4, 2)
	133 iand (4, 2)
	134 ifne (4, 2)
	135 8 (4, 2)
	137 dload_2 (4, 2)
	138 dneg (4, 2)
	139 goto (4, 2)
	140 4 (4, 2)
	142 dload_2 (4, 2)
	143 dconst_1 (4, 2)
	144 iload (4, 2)
	145 #7 (4, 2)
	146 iconst_2 (4, 2)
	147 iadd (4, 2)
	148 i2d (4, 2)
	149 ddiv (4, 2)
	150 dload (4, 2)
	151 #4 (4, 2)
	152 dconst_1 (4, 2)
	153 bipush (4, 2)
	154 6 (4, 2)
	155 iload (4, 2)
	156 #7 (4, 2)
	157 imul (4, 2)
	158 bipush (4, 2)
	159 24 (4, 2)
	160 iadd (4, 2)
	161 i2d (4, 2)
	162 ddiv (4, 2)
	163 dload (4, 2)
	164 #4 (4, 2)
	165 bipush (4, 2)
	166 120 (4, 2)
	167 iload (4, 2)
	168 #7 (4, 2)
	169 imul (4, 2)
	170 sipush (4, 2)
	171 720 (4, 2)
	173 iadd (4, 2)
	174 i2d (4, 2)
	175 ddiv (4, 2)
	176 dsub (4, 2)
	177 dmul (4, 2)
	178 dsub (4, 2)
	179 dmul (4, 2)
	180 dastore (4, 2)
	181 iinc (4, 2)
	182 #7 (4, 2)
	183 -89 (4, 2)
	184 goto (4, 2)
	185 -135 (4, 2)
	187 goto (4, 2)
	188 264 (4, 2)
	190 dconst_1 (3, 2)
	191 dload_2 (3, 2)
	192 ddiv (3, 2)
	193 dstore (3, 2)
	194 #7 (3, 2)
	195 dload_2 (3, 2)
	196 invokestatic (3, 2)
	197 org/apache/commons/math3/util/FastMath.cos:(D)D (3, 2)
	199 dstore (3, 2)
	200 #9 (3, 2)
	201 dload_2 (3, 2)
	202 invokestatic (3, 2)
	203 org/apache/commons/math3/util/FastMath.sin:(D)D (3, 2)
	205 dstore (3, 2)
	206 #11 (3, 2)
	207 aload (3, 2)
	208 #6 (3, 2)
	209 iconst_0 (3, 2)
	210 dload (3, 2)
	211 #7 (3, 2)
	212 dload (3, 2)
	213 #11 (3, 2)
	214 dmul (3, 2)
	215 dastore (3, 2)
	216 aload (5, 4)
	217 #6 (5, 4)
	218 arraylength (5, 4)
	219 newarray (5, 4)
	220 7 (5, 4)
	221 astore (5, 4)
	222 #13 (5, 4)
	223 aload (5, 4)
	224 #13 (5, 4)
	225 iconst_0 (5, 4)
	226 dconst_1 (5, 4)
	227 dastore (5, 4)
	228 dload (5, 4)
	229 #7 (5, 4)
	230 dstore (5, 4)
	231 #14 (5, 4)
	232 iconst_1 (6, 4)
	233 istore (6, 4)
	234 #16 (6, 4)
	235 iload (6, 4)
	236 #16 (6, 4)
	237 aload (6, 4)
	238 #6 (6, 4)
	239 arraylength (6, 4)
	240 if_icmpge (6, 4)
	241 211 (6, 4)
	243 dconst_0 (6, 4)
	244 dstore (6, 4)
	245 #17 (6, 4)
	246 dconst_0 (6, 4)
	247 dstore (6, 4)
	248 #19 (6, 4)
	249 iload (7, 1)
	250 #16 (7, 1)
	251 iconst_1 (7, 1)
	252 iand (7, 1)
	253 ifne (7, 1)
	254 16 (7, 1)
	256 aload (7, 1)
	257 #13 (7, 1)
	258 iload (7, 1)
	259 #16 (7, 1)
	260 dconst_0 (7, 1)
	261 dastore (7, 1)
	262 iload (7, 1)
	263 #16 (7, 1)
	264 istore (7, 1)
	265 #21 (7, 1)
	266 goto (7, 1)
	267 28 (7, 1)
	269 aload (8, 2)
	270 #13 (8, 2)
	271 iload (8, 2)
	272 #16 (8, 2)
	273 aload (8, 2)
	274 #13 (8, 2)
	275 iload (8, 2)
	276 #16 (8, 2)
	277 iconst_1 (8, 2)
	278 isub (8, 2)
	279 daload (8, 2)
	280 dastore (8, 2)
	281 aload (8, 2)
	282 #13 (8, 2)
	283 iload (8, 2)
	284 #16 (8, 2)
	285 daload (8, 2)
	286 dstore (8, 2)
	287 #19 (8, 2)
	288 iload (8, 2)
	289 #16 (8, 2)
	290 iconst_1 (8, 2)
	291 isub (8, 2)
	292 istore (8, 2)
	293 #21 (8, 2)
	294 iload (7, 4)
	295 #21 (7, 4)
	296 istore (7, 4)
	297 #22 (7, 4)
	298 iload (7, 4)
	299 #22 (7, 4)
	300 iconst_1 (7, 4)
	301 if_icmple (7, 4)
	302 93 (7, 4)
	304 aload (7, 4)
	305 #13 (7, 4)
	306 iload (7, 4)
	307 #22 (7, 4)
	308 iload (7, 4)
	309 #22 (7, 4)
	310 iload (7, 4)
	311 #16 (7, 4)
	312 isub (7, 4)
	313 i2d (7, 4)
	314 aload (7, 4)
	315 #13 (7, 4)
	316 iload (7, 4)
	317 #22 (7, 4)
	318 daload (7, 4)
	319 dmul (7, 4)
	320 aload (7, 4)
	321 #13 (7, 4)
	322 iload (7, 4)
	323 #22 (7, 4)
	324 iconst_1 (7, 4)
	325 isub (7, 4)
	326 daload (7, 4)
	327 dsub (7, 4)
	328 dastore (7, 4)
	329 dload (7, 4)
	330 #17 (7, 4)
	331 dload (7, 4)
	332 #4 (7, 4)
	333 dmul (7, 4)
	334 aload (7, 4)
	335 #13 (7, 4)
	336 iload (7, 4)
	337 #22 (7, 4)
	338 daload (7, 4)
	339 dadd (7, 4)
	340 dstore (7, 4)
	341 #17 (7, 4)
	342 aload (7, 4)
	343 #13 (7, 4)
	344 iload (7, 4)
	345 #22 (7, 4)
	346 iconst_1 (7, 4)
	347 isub (7, 4)
	348 iload (7, 4)
	349 #22 (7, 4)
	350 iconst_1 (7, 4)
	351 isub (7, 4)
	352 iload (7, 4)
	353 #16 (7, 4)
	354 isub (7, 4)
	355 i2d (7, 4)
	356 aload (7, 4)
	357 #13 (7, 4)
	358 iload (7, 4)
	359 #22 (7, 4)
	360 iconst_1 (7, 4)
	361 isub (7, 4)
	362 daload (7, 4)
	363 dmul (7, 4)
	364 aload (7, 4)
	365 #13 (7, 4)
	366 iload (7, 4)
	367 #22 (7, 4)
	368 iconst_2 (7, 4)
	369 isub (7, 4)
	370 daload (7, 4)
	371 dadd (7, 4)
	372 dastore (7, 4)
	373 dload (7, 4)
	374 #19 (7, 4)
	375 dload (7, 4)
	376 #4 (7, 4)
	377 dmul (7, 4)
	378 aload (7, 4)
	379 #13 (7, 4)
	380 iload (7, 4)
	381 #22 (7, 4)
	382 iconst_1 (7, 4)
	383 isub (7, 4)
	384 daload (7, 4)
	385 dadd (7, 4)
	386 dstore (7, 4)
	387 #19 (7, 4)
	388 iinc (7, 4)
	389 #22 (7, 4)
	390 -89 (7, 4)
	391 goto (7, 4)
	392 -93 (7, 4)
	394 aload (6, 4)
	395 #13 (6, 4)
	396 iconst_0 (6, 4)
	397 dup2 (6, 4)
	398 daload (6, 4)
	399 iload (6, 4)
	400 #16 (6, 4)
	401 ineg (6, 4)
	402 i2d (6, 4)
	403 dmul (6, 4)
	404 dastore (6, 4)
	405 dload (6, 4)
	406 #17 (6, 4)
	407 dload (6, 4)
	408 #4 (6, 4)
	409 dmul (6, 4)
	410 aload (6, 4)
	411 #13 (6, 4)
	412 iconst_0 (6, 4)
	413 daload (6, 4)
	414 dadd (6, 4)
	415 dstore (6, 4)
	416 #17 (6, 4)
	417 dload (6, 4)
	418 #14 (6, 4)
	419 dload (6, 4)
	420 #7 (6, 4)
	421 dmul (6, 4)
	422 dstore (6, 4)
	423 #14 (6, 4)
	424 aload (6, 4)
	425 #6 (6, 4)
	426 iload (6, 4)
	427 #16 (6, 4)
	428 dload (6, 4)
	429 #14 (6, 4)
	430 dload (6, 4)
	431 #17 (6, 4)
	432 dload (6, 4)
	433 #11 (6, 4)
	434 dmul (6, 4)
	435 dload (6, 4)
	436 #19 (6, 4)
	437 dload_2 (6, 4)
	438 dmul (6, 4)
	439 dload (6, 4)
	440 #9 (6, 4)
	441 dmul (6, 4)
	442 dadd (6, 4)
	443 dmul (6, 4)
	444 dastore (6, 4)
	445 iinc (6, 4)
	446 #16 (6, 4)
	447 -89 (6, 4)
	448 goto (6, 4)
	449 -213 (6, 4)
	451 aload_0 (2, 1)
	452 getfield (2, 1)
	453 org/apache/commons/math3/analysis/function/Sinc.normalized:Z (2, 1)
	455 ifeq (2, 1)
	456 43 (2, 1)
	458 ldc2_w (2, 1)
	459 3.141592653589793 (2, 1)
	461 dstore (2, 1)
	462 #7 (2, 1)
	463 iconst_1 (3, 4)
	464 istore (3, 4)
	465 #9 (3, 4)
	466 iload (3, 4)
	467 #9 (3, 4)
	468 aload (3, 4)
	469 #6 (3, 4)
	470 arraylength (3, 4)
	471 if_icmpge (3, 4)
	472 27 (3, 4)
	474 aload (3, 4)
	475 #6 (3, 4)
	476 iload (3, 4)
	477 #9 (3, 4)
	478 dup2 (3, 4)
	479 daload (3, 4)
	480 dload (3, 4)
	481 #7 (3, 4)
	482 dmul (3, 4)
	483 dastore (3, 4)
	484 dload (3, 4)
	485 #7 (3, 4)
	486 ldc2_w (3, 4)
	487 3.141592653589793 (3, 4)
	489 dmul (3, 4)
	490 dstore (3, 4)
	491 #7 (3, 4)
	492 iinc (3, 4)
	493 #9 (3, 4)
	494 -89 (3, 4)
	495 goto (3, 4)
	496 -29 (3, 4)
	498 aload_1 (1, 1)
	499 aload (1, 1)
	500 #6 (1, 1)
	501 invokevirtual (1, 1)
	502 org/apache/commons/math3/analysis/differentiation/DerivativeStructure.compose:([D)Lorg/apache/commons/math3/analysis/differentiation/DerivativeStructure; (1, 1)
	504 areturn (1, 1)

Method: derivative
	0 aload_0 (1, 1)
	1 invokestatic (1, 1)
	2 org/apache/commons/math3/analysis/FunctionUtils.toDifferentiableUnivariateFunction:(Lorg/apache/commons/math3/analysis/differentiation/UnivariateDifferentiableFunction;)Lorg/apache/commons/math3/analysis/DifferentiableUnivariateFunction; (1, 1)
	4 invokeinterface (1, 1)
	5 org/apache/commons/math3/analysis/DifferentiableUnivariateFunction.org/apache/commons/math3/analysis/differentiation/DerivativeStructure (1, 1)
	7 0 (1, 1)
	9 areturn (0, 1)

