Method: <init>
	0 aload_0 (0, 0)
	1 invokespecial (0, 0)
	2 java/lang/Object.<init>:()V (0, 0)
	4 aload_0 (0, 0)
	5 new (0, 0)
	6 java/util/TreeMap (0, 0)
	8 dup (0, 0)
	9 aload_1 (0, 0)
	10 invokespecial (0, 0)
	11 java/util/TreeMap.<init>:(Ljava/util/Comparator;)V (0, 0)
	13 putfield (0, 0)
	14 org/apache/commons/math3/stat/Frequency.freqTable:Ljava/util/SortedMap; (0, 0)
	16 return (0, 0)

Method: toString
	0 invokestatic (0, 0)
	1 java/text/NumberFormat.getPercentInstance:()Ljava/text/NumberFormat; (0, 0)
	3 astore_1 (0, 0)
	4 new (0, 0)
	5 java/lang/StringBuilder (0, 0)
	7 dup (0, 0)
	8 invokespecial (0, 0)
	9 java/lang/StringBuilder.<init>:()V (0, 0)
	11 astore_2 (0, 0)
	12 aload_2 (0, 0)
	13 ldc (0, 0)
	14 Value 	 Freq. 	 Pct. 	 Cum Pct. 
 (0, 0)
	15 invokevirtual (0, 0)
	16 java/lang/StringBuilder.append:(Ljava/lang/String;)Ljava/lang/StringBuilder; (0, 0)
	18 pop (0, 0)
	19 aload_0 (0, 0)
	20 getfield (0, 0)
	21 org/apache/commons/math3/stat/Frequency.freqTable:Ljava/util/SortedMap; (0, 0)
	23 invokeinterface (0, 0)
	24 java/util/SortedMap.java/util/Set (0, 0)
	26 0 (0, 0)
	28 invokeinterface (0, 0)
	29 java/util/Set.java/util/Iterator (0, 0)
	31 0 (0, 0)
	33 astore_3 (0, 0)
	34 aload_3 (1, 3)
	35 invokeinterface (1, 3)
	36 java/util/Iterator.next:()Ljava/lang/Object; (1, 3)
	38 0 (1, 3)
	40 ifeq (1, 3)
	41 93 (1, 3)
	43 aload_3 (1, 3)
	44 invokeinterface (1, 3)
	45 java/util/Iterator.java/lang/Comparable (1, 3)
	47 0 (1, 3)
	49 checkcast (1, 3)
	50 java/lang/Comparable (1, 3)
	52 astore (1, 3)
	53 #4 (1, 3)
	54 aload_2 (1, 3)
	55 aload (1, 3)
	56 #4 (1, 3)
	57 invokevirtual (1, 3)
	58 java/lang/StringBuilder.append:(Ljava/lang/Object;)Ljava/lang/StringBuilder; (1, 3)
	60 pop (1, 3)
	61 aload_2 (1, 3)
	62 bipush (1, 3)
	63 9 (1, 3)
	64 invokevirtual (1, 3)
	65 java/lang/StringBuilder.append:(C)Ljava/lang/StringBuilder; (1, 3)
	67 pop (1, 3)
	68 aload_2 (1, 3)
	69 aload_0 (1, 3)
	70 aload (1, 3)
	71 #4 (1, 3)
	72 invokevirtual (1, 3)
	73 org/apache/commons/math3/stat/Frequency.getCount:(Ljava/lang/Comparable;)J (1, 3)
	75 invokevirtual (1, 3)
	76 java/lang/StringBuilder.append:(J)Ljava/lang/StringBuilder; (1, 3)
	78 pop (1, 3)
	79 aload_2 (1, 3)
	80 bipush (1, 3)
	81 9 (1, 3)
	82 invokevirtual (1, 3)
	83 java/lang/StringBuilder.append:(C)Ljava/lang/StringBuilder; (1, 3)
	85 pop (1, 3)
	86 aload_2 (2, 4)
	87 aload_1 (2, 4)
	88 aload_0 (2, 4)
	89 aload (2, 4)
	90 #4 (2, 4)
	91 invokevirtual (2, 4)
	92 org/apache/commons/math3/stat/Frequency.getPct:(Ljava/lang/Comparable;)D (2, 4)
	94 invokevirtual (2, 4)
	95 java/text/NumberFormat.format:(D)Ljava/lang/String; (2, 4)
	97 invokevirtual (2, 4)
	98 java/lang/StringBuilder.append:(Ljava/lang/String;)Ljava/lang/StringBuilder; (2, 4)
	100 pop (2, 4)
	101 aload_2 (2, 4)
	102 bipush (2, 4)
	103 9 (2, 4)
	104 invokevirtual (2, 4)
	105 java/lang/StringBuilder.append:(C)Ljava/lang/StringBuilder; (2, 4)
	107 pop (2, 4)
	108 aload_2 (3, 4)
	109 aload_1 (3, 4)
	110 aload_0 (3, 4)
	111 aload (3, 4)
	112 #4 (3, 4)
	113 invokevirtual (3, 4)
	114 org/apache/commons/math3/stat/Frequency.getCumPct:(Ljava/lang/Comparable;)D (3, 4)
	116 invokevirtual (3, 4)
	117 java/text/NumberFormat.format:(D)Ljava/lang/String; (3, 4)
	119 invokevirtual (3, 4)
	120 java/lang/StringBuilder.append:(Ljava/lang/String;)Ljava/lang/StringBuilder; (3, 4)
	122 pop (3, 4)
	123 aload_2 (3, 4)
	124 bipush (3, 4)
	125 10 (3, 4)
	126 invokevirtual (3, 4)
	127 java/lang/StringBuilder.append:(C)Ljava/lang/StringBuilder; (3, 4)
	129 pop (3, 4)
	130 goto (0, 0)
	131 -96 (0, 0)
	133 aload_2 (0, 0)
	134 invokevirtual (0, 0)
	135 java/lang/StringBuilder.toString:()Ljava/lang/String; (0, 0)
	137 areturn (0, 0)

Method: addValue
	0 aload_0 (0, 0)
	1 iload_1 (0, 0)
	2 invokestatic (0, 0)
	3 java/lang/Character.valueOf:(C)Ljava/lang/Character; (0, 0)
	5 invokevirtual (0, 0)
	6 org/apache/commons/math3/stat/Frequency.addValue:(Ljava/lang/Comparable;)V (0, 0)
	8 return (0, 0)

Method: incrementValue
	0 aload_0 (0, 0)
	1 iload_1 (0, 0)
	2 invokestatic (0, 0)
	3 java/lang/Character.valueOf:(C)Ljava/lang/Character; (0, 0)
	5 lload_2 (0, 0)
	6 invokevirtual (0, 0)
	7 org/apache/commons/math3/stat/Frequency.incrementValue:(Ljava/lang/Comparable;J)V (0, 0)
	9 return (0, 0)

Method: clear
	0 aload_0 (0, 0)
	1 getfield (0, 0)
	2 org/apache/commons/math3/stat/Frequency.freqTable:Ljava/util/SortedMap; (0, 0)
	4 invokeinterface (0, 0)
	5 java/util/SortedMap.entrySet:()Ljava/util/Set; (0, 0)
	7 0 (0, 0)
	9 return (0, 0)

Method: valuesIterator
	0 aload_0 (0, 0)
	1 getfield (0, 0)
	2 org/apache/commons/math3/stat/Frequency.freqTable:Ljava/util/SortedMap; (0, 0)
	4 invokeinterface (0, 0)
	5 java/util/SortedMap.java/util/Set (0, 0)
	7 0 (0, 0)
	9 invokeinterface (0, 0)
	10 java/util/Set.java/util/Iterator (0, 0)
	12 0 (0, 0)
	14 areturn (0, 0)

Method: entrySetIterator
	0 aload_0 (0, 0)
	1 getfield (0, 0)
	2 org/apache/commons/math3/stat/Frequency.freqTable:Ljava/util/SortedMap; (0, 0)
	4 invokeinterface (0, 0)
	5 java/util/SortedMap.values:()Ljava/util/Collection; (0, 0)
	7 0 (0, 0)
	9 invokeinterface (0, 0)
	10 java/util/Set.java/util/Iterator (0, 0)
	12 0 (0, 0)
	14 areturn (0, 0)

Method: getSumFreq
	0 lconst_0 (0, 0)
	1 lstore_1 (0, 0)
	2 aload_0 (0, 0)
	3 getfield (0, 0)
	4 org/apache/commons/math3/stat/Frequency.freqTable:Ljava/util/SortedMap; (0, 0)
	6 invokeinterface (0, 0)
	7 java/util/SortedMap.java/util/Collection (0, 0)
	9 0 (0, 0)
	11 invokeinterface (0, 0)
	12 java/util/Collection.java/util/Iterator (0, 0)
	14 0 (0, 0)
	16 astore_3 (0, 0)
	17 aload_3 (1, 3)
	18 invokeinterface (1, 3)
	19 java/util/Iterator.next:()Ljava/lang/Object; (1, 3)
	21 0 (1, 3)
	23 ifeq (1, 3)
	24 21 (1, 3)
	26 lload_1 (1, 3)
	27 aload_3 (1, 3)
	28 invokeinterface (1, 3)
	29 java/util/Iterator.java/lang/Comparable (1, 3)
	31 0 (1, 3)
	33 checkcast (1, 3)
	34 java/lang/Long (1, 3)
	36 invokevirtual (1, 3)
	37 java/lang/Long.longValue:()J (1, 3)
	39 ladd (1, 3)
	40 lstore_1 (1, 3)
	41 goto (1, 3)
	42 -24 (1, 3)
	44 lload_1 (0, 0)
	45 lreturn (0, 0)

Method: getCount
	0 aload_0 (0, 0)
	1 iload_1 (0, 0)
	2 invokestatic (0, 0)
	3 java/lang/Character.valueOf:(C)Ljava/lang/Character; (0, 0)
	5 invokevirtual (0, 0)
	6 org/apache/commons/math3/stat/Frequency.getCount:(Ljava/lang/Comparable;)J (0, 0)
	8 lreturn (0, 0)

Method: getUniqueCount
	0 aload_0 (0, 0)
	1 getfield (0, 0)
	2 org/apache/commons/math3/stat/Frequency.freqTable:Ljava/util/SortedMap; (0, 0)
	4 invokeinterface (0, 0)
	5 java/util/SortedMap.java/util/Set (0, 0)
	7 0 (0, 0)
	9 invokeinterface (0, 0)
	10 java/util/Set.getSumFreq:()J (0, 0)
	12 0 (0, 0)
	14 ireturn (0, 0)

Method: getPct
	0 aload_0 (0, 0)
	1 iload_1 (0, 0)
	2 invokestatic (0, 0)
	3 java/lang/Character.valueOf:(C)Ljava/lang/Character; (0, 0)
	5 invokevirtual (0, 0)
	6 org/apache/commons/math3/stat/Frequency.getPct:(Ljava/lang/Comparable;)D (0, 0)
	8 dreturn (0, 0)

Method: getCumFreq
	0 aload_0 (0, 0)
	1 iload_1 (0, 0)
	2 invokestatic (0, 0)
	3 java/lang/Character.valueOf:(C)Ljava/lang/Character; (0, 0)
	5 invokevirtual (0, 0)
	6 org/apache/commons/math3/stat/Frequency.getCumFreq:(Ljava/lang/Comparable;)J (0, 0)
	8 lreturn (0, 0)

Method: getCumPct
	0 aload_0 (0, 0)
	1 iload_1 (0, 0)
	2 invokestatic (0, 0)
	3 java/lang/Character.valueOf:(C)Ljava/lang/Character; (0, 0)
	5 invokevirtual (0, 0)
	6 org/apache/commons/math3/stat/Frequency.getCumPct:(Ljava/lang/Comparable;)D (0, 0)
	8 dreturn (0, 0)

Method: getMode
	0 lconst_0 (0, 0)
	1 lstore_1 (0, 0)
	2 aload_0 (1, 4)
	3 getfield (1, 4)
	4 org/apache/commons/math3/stat/Frequency.freqTable:Ljava/util/SortedMap; (1, 4)
	6 invokeinterface (1, 4)
	7 java/util/SortedMap.java/util/Collection (1, 4)
	9 0 (1, 4)
	11 invokeinterface (1, 4)
	12 java/util/Collection.java/util/Iterator (1, 4)
	14 0 (1, 4)
	16 astore_3 (1, 4)
	17 aload_3 (1, 4)
	18 invokeinterface (1, 4)
	19 java/util/Iterator.next:()Ljava/lang/Object; (1, 4)
	21 0 (1, 4)
	23 ifeq (1, 4)
	24 34 (1, 4)
	26 aload_3 (1, 4)
	27 invokeinterface (1, 4)
	28 java/util/Iterator.java/lang/Comparable (1, 4)
	30 0 (1, 4)
	32 checkcast (1, 4)
	33 java/lang/Long (1, 4)
	35 astore (1, 4)
	36 #4 (1, 4)
	37 aload (1, 4)
	38 #4 (1, 4)
	39 invokevirtual (1, 4)
	40 java/lang/Long.longValue:()J (1, 4)
	42 lstore (1, 4)
	43 #5 (1, 4)
	44 lload (2, 1)
	45 #5 (2, 1)
	46 lload_1 (2, 1)
	47 lcmp (2, 1)
	48 ifle (2, 1)
	49 6 (2, 1)
	51 lload (2, 1)
	52 #5 (2, 1)
	53 lstore_1 (2, 1)
	54 goto (0, 0)
	55 -37 (0, 0)
	57 new (0, 0)
	58 java/util/ArrayList (0, 0)
	60 dup (0, 0)
	61 invokespecial (0, 0)
	62 java/util/ArrayList.<init>:()V (0, 0)
	64 astore_3 (0, 0)
	65 aload_0 (1, 4)
	66 getfield (1, 4)
	67 org/apache/commons/math3/stat/Frequency.freqTable:Ljava/util/SortedMap; (1, 4)
	69 invokeinterface (1, 4)
	70 java/util/SortedMap.values:()Ljava/util/Collection; (1, 4)
	72 0 (1, 4)
	74 invokeinterface (1, 4)
	75 java/util/Set.java/util/Iterator (1, 4)
	77 0 (1, 4)
	79 astore (1, 4)
	80 #4 (1, 4)
	81 aload (1, 4)
	82 #4 (1, 4)
	83 invokeinterface (1, 4)
	84 java/util/Iterator.next:()Ljava/lang/Object; (1, 4)
	86 0 (1, 4)
	88 ifeq (1, 4)
	89 54 (1, 4)
	91 aload (1, 4)
	92 #4 (1, 4)
	93 invokeinterface (1, 4)
	94 java/util/Iterator.java/lang/Comparable (1, 4)
	96 0 (1, 4)
	98 checkcast (1, 4)
	99 java/util/Map$Entry (1, 4)
	101 astore (1, 4)
	102 #5 (1, 4)
	103 aload (1, 4)
	104 #5 (1, 4)
	105 invokeinterface (1, 4)
	106 java/util/Map$Entry.getKey:()Ljava/lang/Object; (1, 4)
	108 0 (1, 4)
	110 checkcast (1, 4)
	111 java/lang/Long (1, 4)
	113 invokevirtual (1, 4)
	114 java/lang/Long.longValue:()J (1, 4)
	116 lstore (1, 4)
	117 #6 (1, 4)
	118 lload (2, 1)
	119 #6 (2, 1)
	120 lload_1 (2, 1)
	121 lcmp (2, 1)
	122 ifne (2, 1)
	123 17 (2, 1)
	125 aload_3 (2, 1)
	126 aload (2, 1)
	127 #5 (2, 1)
	128 invokeinterface (2, 1)
	129 java/util/Map$Entry.java/util/List (2, 1)
	131 0 (2, 1)
	133 invokeinterface (2, 1)
	134 java/util/List.NULL_NOT_ALLOWED:Lorg/apache/commons/math3/exception/util/LocalizedFormats; (2, 1)
	136 0 (2, 1)
	138 pop (2, 1)
	139 goto (0, 0)
	140 -58 (0, 0)
	142 aload_3 (0, 0)
	143 areturn (0, 0)

Method: merge
	0 aload_1 (0, 0)
	1 getstatic (0, 0)
	2 org/apache/commons/math3/exception/util/LocalizedFormats.NULL_NOT_ALLOWED:Lorg/apache/commons/math3/exception/util/LocalizedFormats; (0, 0)
	4 iconst_0 (0, 0)
	5 anewarray (0, 0)
	6 java/lang/Object (0, 0)
	8 invokestatic (0, 0)
	9 org/apache/commons/math3/util/MathUtils.checkNotNull:(Ljava/lang/Object;Lorg/apache/commons/math3/exception/util/Localizable;[Ljava/lang/Object;)V (0, 0)
	11 aload_1 (1, 4)
	12 invokeinterface (1, 4)
	13 java/util/Collection.java/util/Iterator (1, 4)
	15 0 (1, 4)
	17 astore_2 (1, 4)
	18 aload_2 (1, 4)
	19 invokeinterface (1, 4)
	20 java/util/Iterator.next:()Ljava/lang/Object; (1, 4)
	22 0 (1, 4)
	24 ifeq (1, 4)
	25 21 (1, 4)
	27 aload_2 (1, 4)
	28 invokeinterface (1, 4)
	29 java/util/Iterator.java/lang/Comparable (1, 4)
	31 0 (1, 4)
	33 checkcast (1, 4)
	34 org/apache/commons/math3/stat/Frequency (1, 4)
	36 astore_3 (1, 4)
	37 aload_0 (1, 4)
	38 aload_3 (1, 4)
	39 invokevirtual (1, 4)
	40 org/apache/commons/math3/stat/Frequency.merge:(Lorg/apache/commons/math3/stat/Frequency;)V (1, 4)
	42 goto (0, 0)
	43 -24 (0, 0)
	45 return (0, 0)

Method: hashCode
	0 bipush (0, 0)
	1 31 (0, 0)
	2 istore_1 (0, 0)
	3 iconst_1 (0, 0)
	4 istore_2 (0, 0)
	5 bipush (0, 0)
	6 31 (0, 0)
	7 iload_2 (0, 0)
	8 imul (0, 0)
	9 aload_0 (0, 0)
	10 getfield (0, 0)
	11 org/apache/commons/math3/stat/Frequency.freqTable:Ljava/util/SortedMap; (0, 0)
	13 ifnonnull (0, 0)
	14 7 (0, 0)
	16 iconst_0 (0, 0)
	17 goto (0, 0)
	18 10 (0, 0)
	20 aload_0 (0, 0)
	21 getfield (0, 0)
	22 org/apache/commons/math3/stat/Frequency.freqTable:Ljava/util/SortedMap; (0, 0)
	24 invokevirtual (0, 0)
	25 java/lang/Object.hashCode:()I (0, 0)
	27 iadd (0, 0)
	28 istore_2 (0, 0)
	29 iload_2 (0, 0)
	30 ireturn (0, 0)

Method: equals
	0 aload_0 (1, 1)
	1 aload_1 (1, 1)
	2 if_acmpne (1, 1)
	3 5 (1, 1)
	5 iconst_1 (1, 1)
	6 ireturn (1, 1)
	7 aload_1 (1, 1)
	8 instanceof (1, 1)
	9 org/apache/commons/math3/stat/Frequency (1, 1)
	11 ifne (1, 1)
	12 5 (1, 1)
	14 iconst_0 (1, 1)
	15 ireturn (1, 1)
	16 aload_1 (0, 0)
	17 checkcast (0, 0)
	18 org/apache/commons/math3/stat/Frequency (0, 0)
	20 astore_2 (0, 0)
	21 aload_0 (1, 1)
	22 getfield (1, 1)
	23 org/apache/commons/math3/stat/Frequency.freqTable:Ljava/util/SortedMap; (1, 1)
	25 ifnonnull (1, 1)
	26 12 (1, 1)
	28 aload_2 (2, 1)
	29 getfield (2, 1)
	30 org/apache/commons/math3/stat/Frequency.freqTable:Ljava/util/SortedMap; (2, 1)
	32 ifnull (2, 1)
	33 21 (2, 1)
	35 iconst_0 (2, 1)
	36 ireturn (2, 1)
	37 aload_0 (2, 1)
	38 getfield (2, 1)
	39 org/apache/commons/math3/stat/Frequency.freqTable:Ljava/util/SortedMap; (2, 1)
	41 aload_2 (2, 1)
	42 getfield (2, 1)
	43 org/apache/commons/math3/stat/Frequency.freqTable:Ljava/util/SortedMap; (2, 1)
	45 invokevirtual (2, 1)
	46 java/lang/Object.equals:(Ljava/lang/Object;)Z (2, 1)
	48 ifne (2, 1)
	49 5 (2, 1)
	51 iconst_0 (2, 1)
	52 ireturn (2, 1)
	53 iconst_1 (0, 0)
	54 ireturn (0, 0)

