Method: <init>
	0 aload_0 (0, 0)
	1 invokespecial (0, 0)
	4 aload_0 (0, 0)
	5 new (0, 0)
	8 dup (0, 0)
	9 aload_1 (0, 0)
	10 invokespecial (0, 0)
	13 putfield (0, 0)
	16 return (0, 0)

Method: toString
	0 invokestatic (0, 0)
	3 astore_1 (0, 0)
	4 new (0, 0)
	7 dup (0, 0)
	8 invokespecial (0, 0)
	11 astore_2 (0, 0)
	12 aload_2 (0, 0)
	13 ldc (0, 0)
	15 invokevirtual (0, 0)
	18 pop (0, 0)
	19 aload_0 (0, 0)
	20 getfield (0, 0)
	23 invokeinterface (0, 0)
	28 invokeinterface (0, 0)
	33 astore_3 (0, 0)
	34 aload_3 (1, 3)
	35 invokeinterface (1, 3)
	40 ifeq (1, 3)
	43 aload_3 (1, 3)
	44 invokeinterface (1, 3)
	49 checkcast (1, 3)
	52 astore (1, 3)
	54 aload_2 (1, 3)
	55 aload (1, 3)
	57 invokevirtual (1, 3)
	60 pop (1, 3)
	61 aload_2 (1, 3)
	62 bipush (1, 3)
	64 invokevirtual (1, 3)
	67 pop (1, 3)
	68 aload_2 (1, 3)
	69 aload_0 (1, 3)
	70 aload (1, 3)
	72 invokevirtual (1, 3)
	75 invokevirtual (1, 3)
	78 pop (1, 3)
	79 aload_2 (1, 3)
	80 bipush (1, 3)
	82 invokevirtual (1, 3)
	85 pop (1, 3)
	86 aload_2 (1, 4)
	87 aload_1 (1, 4)
	88 aload_0 (1, 4)
	89 aload (1, 4)
	91 invokevirtual (1, 4)
	94 invokevirtual (1, 4)
	97 invokevirtual (1, 4)
	100 pop (1, 4)
	101 aload_2 (1, 4)
	102 bipush (1, 4)
	104 invokevirtual (1, 4)
	107 pop (1, 4)
	108 aload_2 (1, 4)
	109 aload_1 (1, 4)
	110 aload_0 (1, 4)
	111 aload (1, 4)
	113 invokevirtual (1, 4)
	116 invokevirtual (1, 4)
	119 invokevirtual (1, 4)
	122 pop (1, 4)
	123 aload_2 (1, 4)
	124 bipush (1, 4)
	126 invokevirtual (1, 4)
	129 pop (1, 4)
	130 goto (0, 4)
	133 aload_2 (0, 4)
	134 invokevirtual (0, 4)
	137 areturn (0, 4)

Method: addValue
	0 aload_0 (0, 0)
	1 iload_1 (0, 0)
	2 invokestatic (0, 0)
	5 invokevirtual (0, 0)
	8 return (0, 0)

Method: incrementValue
	0 aload_0 (0, 0)
	1 iload_1 (0, 0)
	2 invokestatic (0, 0)
	5 lload_2 (0, 0)
	6 invokevirtual (0, 0)
	9 return (0, 0)

Method: clear
	0 aload_0 (0, 0)
	1 getfield (0, 0)
	4 invokeinterface (0, 0)
	9 return (0, 0)

Method: valuesIterator
	0 aload_0 (0, 0)
	1 getfield (0, 0)
	4 invokeinterface (0, 0)
	9 invokeinterface (0, 0)
	14 areturn (0, 0)

Method: entrySetIterator
	0 aload_0 (0, 0)
	1 getfield (0, 0)
	4 invokeinterface (0, 0)
	9 invokeinterface (0, 0)
	14 areturn (0, 0)

Method: getSumFreq
	0 lconst_0 (0, 0)
	1 lstore_1 (0, 0)
	2 aload_0 (0, 0)
	3 getfield (0, 0)
	6 invokeinterface (0, 0)
	11 invokeinterface (0, 0)
	16 astore_3 (0, 0)
	17 aload_3 (1, 3)
	18 invokeinterface (1, 3)
	23 ifeq (1, 3)
	26 lload_1 (1, 3)
	27 aload_3 (1, 3)
	28 invokeinterface (1, 3)
	33 checkcast (1, 3)
	36 invokevirtual (1, 3)
	39 ladd (1, 3)
	40 lstore_1 (1, 3)
	41 goto (1, 3)
	44 lload_1 (0, 0)
	45 lreturn (0, 0)

Method: getCount
	0 aload_0 (0, 0)
	1 iload_1 (0, 0)
	2 invokestatic (0, 0)
	5 invokevirtual (0, 0)
	8 lreturn (0, 0)

Method: getUniqueCount
	0 aload_0 (0, 0)
	1 getfield (0, 0)
	4 invokeinterface (0, 0)
	9 invokeinterface (0, 0)
	14 ireturn (0, 0)

Method: getPct
	0 aload_0 (0, 0)
	1 iload_1 (0, 0)
	2 invokestatic (0, 0)
	5 invokevirtual (0, 0)
	8 dreturn (0, 0)

Method: getCumFreq
	0 aload_0 (0, 0)
	1 iload_1 (0, 0)
	2 invokestatic (0, 0)
	5 invokevirtual (0, 0)
	8 lreturn (0, 0)

Method: getCumPct
	0 aload_0 (0, 0)
	1 iload_1 (0, 0)
	2 invokestatic (0, 0)
	5 invokevirtual (0, 0)
	8 dreturn (0, 0)

Method: getMode
	0 lconst_0 (0, 0)
	1 lstore_1 (0, 0)
	2 aload_0 (1, 4)
	3 getfield (1, 4)
	6 invokeinterface (1, 4)
	11 invokeinterface (1, 4)
	16 astore_3 (1, 4)
	17 aload_3 (1, 4)
	18 invokeinterface (1, 4)
	23 ifeq (1, 4)
	26 aload_3 (1, 4)
	27 invokeinterface (1, 4)
	32 checkcast (1, 4)
	35 astore (1, 4)
	37 aload (1, 4)
	39 invokevirtual (1, 4)
	42 lstore (1, 4)
	44 lload (2, 1)
	46 lload_1 (2, 1)
	47 lcmp (2, 1)
	48 ifle (2, 1)
	51 lload (2, 1)
	53 lstore_1 (2, 1)
	54 goto (0, 0)
	57 new (0, 0)
	60 dup (0, 0)
	61 invokespecial (0, 0)
	64 astore_3 (0, 0)
	65 aload_0 (1, 4)
	66 getfield (1, 4)
	69 invokeinterface (1, 4)
	74 invokeinterface (1, 4)
	79 astore (1, 4)
	81 aload (1, 4)
	83 invokeinterface (1, 4)
	88 ifeq (1, 4)
	91 aload (1, 4)
	93 invokeinterface (1, 4)
	98 checkcast (1, 4)
	101 astore (1, 4)
	103 aload (1, 4)
	105 invokeinterface (1, 4)
	110 checkcast (1, 4)
	113 invokevirtual (1, 4)
	116 lstore (1, 4)
	118 lload (2, 1)
	120 lload_1 (2, 1)
	121 lcmp (2, 1)
	122 ifne (2, 1)
	125 aload_3 (2, 1)
	126 aload (2, 1)
	128 invokeinterface (2, 1)
	133 invokeinterface (2, 1)
	138 pop (2, 1)
	139 goto (0, 0)
	142 aload_3 (0, 0)
	143 areturn (0, 0)

Method: merge
	0 aload_1 (0, 0)
	1 getstatic (0, 0)
	4 iconst_0 (0, 0)
	5 anewarray (0, 0)
	8 invokestatic (0, 0)
	11 aload_1 (1, 4)
	12 invokeinterface (1, 4)
	17 astore_2 (1, 4)
	18 aload_2 (1, 4)
	19 invokeinterface (1, 4)
	24 ifeq (1, 4)
	27 aload_2 (1, 4)
	28 invokeinterface (1, 4)
	33 checkcast (1, 4)
	36 astore_3 (1, 4)
	37 aload_0 (1, 4)
	38 aload_3 (1, 4)
	39 invokevirtual (1, 4)
	42 goto (0, 0)
	45 return (0, 0)

Method: hashCode
	0 bipush (0, 0)
	2 istore_1 (0, 0)
	3 iconst_1 (0, 0)
	4 istore_2 (0, 0)
	5 bipush (0, 0)
	7 iload_2 (0, 0)
	8 imul (0, 0)
	9 aload_0 (0, 0)
	10 getfield (0, 0)
	13 ifnonnull (0, 0)
	16 iconst_0 (0, 0)
	17 goto (0, 0)
	20 aload_0 (0, 0)
	21 getfield (0, 0)
	24 invokevirtual (0, 0)
	27 iadd (0, 0)
	28 istore_2 (0, 0)
	29 iload_2 (0, 0)
	30 ireturn (0, 0)

Method: equals
	0 aload_0 (1, 1)
	1 aload_1 (1, 1)
	2 if_acmpne (1, 1)
	5 iconst_1 (1, 1)
	6 ireturn (1, 1)
	7 aload_1 (1, 1)
	8 instanceof (1, 1)
	11 ifne (1, 1)
	14 iconst_0 (1, 1)
	15 ireturn (1, 1)
	16 aload_1 (0, 0)
	17 checkcast (0, 0)
	20 astore_2 (0, 0)
	21 aload_0 (1, 1)
	22 getfield (1, 1)
	25 ifnonnull (1, 1)
	28 aload_2 (2, 1)
	29 getfield (2, 1)
	32 ifnull (2, 1)
	35 iconst_0 (2, 1)
	36 ireturn (2, 1)
	37 aload_0 (1, 1)
	38 getfield (1, 1)
	41 aload_2 (1, 1)
	42 getfield (1, 1)
	45 invokevirtual (1, 1)
	48 ifne (1, 1)
	51 iconst_0 (1, 1)
	52 ireturn (1, 1)
	53 iconst_1 (0, 1)
	54 ireturn (0, 1)

