Method: <init>
	0 aload_0 (0, 0)
	1 invokespecial (0, 0)
	4 return (0, 0)

Method: sum
	0 getstatic (0, 0)
	3 aload_0 (0, 0)
	4 iload_1 (0, 0)
	5 iload_2 (0, 0)
	6 invokeinterface (0, 0)
	11 dreturn (0, 0)

Method: sumSq
	0 getstatic (0, 0)
	3 aload_0 (0, 0)
	4 iload_1 (0, 0)
	5 iload_2 (0, 0)
	6 invokeinterface (0, 0)
	11 dreturn (0, 0)

Method: product
	0 getstatic (0, 0)
	3 aload_0 (0, 0)
	4 iload_1 (0, 0)
	5 iload_2 (0, 0)
	6 invokeinterface (0, 0)
	11 dreturn (0, 0)

Method: sumLog
	0 getstatic (0, 0)
	3 aload_0 (0, 0)
	4 iload_1 (0, 0)
	5 iload_2 (0, 0)
	6 invokeinterface (0, 0)
	11 dreturn (0, 0)

Method: mean
	0 getstatic (0, 0)
	3 aload_0 (0, 0)
	4 iload_1 (0, 0)
	5 iload_2 (0, 0)
	6 invokeinterface (0, 0)
	11 dreturn (0, 0)

Method: geometricMean
	0 getstatic (0, 0)
	3 aload_0 (0, 0)
	4 iload_1 (0, 0)
	5 iload_2 (0, 0)
	6 invokevirtual (0, 0)
	9 dreturn (0, 0)

Method: variance
	0 getstatic (0, 0)
	3 aload_0 (0, 0)
	4 dload_1 (0, 0)
	5 invokevirtual (0, 0)
	8 dreturn (0, 0)

Method: populationVariance
	0 new (0, 0)
	3 dup (0, 0)
	4 iconst_0 (0, 0)
	5 invokespecial (0, 0)
	8 aload_0 (0, 0)
	9 dload_1 (0, 0)
	10 invokevirtual (0, 0)
	13 dreturn (0, 0)

Method: max
	0 getstatic (0, 0)
	3 aload_0 (0, 0)
	4 iload_1 (0, 0)
	5 iload_2 (0, 0)
	6 invokeinterface (0, 0)
	11 dreturn (0, 0)

Method: min
	0 getstatic (0, 0)
	3 aload_0 (0, 0)
	4 iload_1 (0, 0)
	5 iload_2 (0, 0)
	6 invokeinterface (0, 0)
	11 dreturn (0, 0)

Method: percentile
	0 getstatic (0, 0)
	3 aload_0 (0, 0)
	4 iload_1 (0, 0)
	5 iload_2 (0, 0)
	6 dload_3 (0, 0)
	7 invokevirtual (0, 0)
	10 dreturn (0, 0)

Method: sumDifference
	0 aload_0 (0, 0)
	1 arraylength (0, 0)
	2 istore_2 (0, 0)
	3 iload_2 (1, 1)
	4 aload_1 (1, 1)
	5 arraylength (1, 1)
	6 if_icmpeq (1, 1)
	9 new (1, 1)
	12 dup (1, 1)
	13 iload_2 (1, 1)
	14 aload_1 (1, 1)
	15 arraylength (1, 1)
	16 invokespecial (1, 1)
	19 athrow (1, 1)
	20 iload_2 (1, 1)
	21 ifgt (1, 1)
	24 new (1, 1)
	27 dup (1, 1)
	28 getstatic (1, 1)
	31 invokespecial (1, 1)
	34 athrow (1, 1)
	35 dconst_0 (0, 0)
	36 dstore_3 (0, 0)
	37 iconst_0 (1, 4)
	38 istore (1, 4)
	40 iload (1, 4)
	42 iload_2 (1, 4)
	43 if_icmpge (1, 4)
	46 dload_3 (1, 4)
	47 aload_0 (1, 4)
	48 iload (1, 4)
	50 daload (1, 4)
	51 aload_1 (1, 4)
	52 iload (1, 4)
	54 daload (1, 4)
	55 dsub (1, 4)
	56 dadd (1, 4)
	57 dstore_3 (1, 4)
	58 iinc (1, 4)
	61 goto (1, 4)
	64 dload_3 (0, 0)
	65 dreturn (0, 0)

Method: meanDifference
	0 aload_0 (0, 1)
	1 aload_1 (0, 1)
	2 invokestatic (0, 1)
	5 aload_0 (0, 1)
	6 arraylength (0, 1)
	7 i2d (0, 1)
	8 ddiv (0, 1)
	9 dreturn (0, 1)

Method: varianceDifference
	0 dconst_0 (0, 0)
	1 dstore (0, 0)
	3 dconst_0 (0, 0)
	4 dstore (0, 0)
	6 dconst_0 (0, 1)
	7 dstore (0, 1)
	9 aload_0 (0, 1)
	10 arraylength (0, 1)
	11 istore (0, 1)
	13 iload (1, 1)
	15 aload_1 (1, 1)
	16 arraylength (1, 1)
	17 if_icmpeq (1, 1)
	20 new (1, 1)
	23 dup (1, 1)
	24 iload (1, 1)
	26 aload_1 (1, 1)
	27 arraylength (1, 1)
	28 invokespecial (1, 1)
	31 athrow (1, 1)
	32 iload (1, 1)
	34 iconst_2 (1, 1)
	35 if_icmpge (1, 1)
	38 new (1, 1)
	41 dup (1, 1)
	42 iload (1, 1)
	44 invokestatic (1, 1)
	47 iconst_2 (1, 1)
	48 invokestatic (1, 1)
	51 iconst_1 (1, 1)
	52 invokespecial (1, 1)
	55 athrow (1, 1)
	56 iconst_0 (1, 4)
	57 istore (1, 4)
	59 iload (1, 4)
	61 iload (1, 4)
	63 if_icmpge (1, 4)
	66 aload_0 (1, 1)
	67 iload (1, 1)
	69 daload (1, 1)
	70 aload_1 (1, 1)
	71 iload (1, 1)
	73 daload (1, 1)
	74 dsub (1, 1)
	75 dstore (1, 1)
	77 dload (1, 1)
	79 dload (1, 1)
	81 dload_2 (1, 1)
	82 dsub (1, 1)
	83 dload (1, 1)
	85 dload_2 (1, 1)
	86 dsub (1, 1)
	87 dmul (1, 1)
	88 dadd (1, 1)
	89 dstore (1, 1)
	91 dload (1, 1)
	93 dload (1, 1)
	95 dload_2 (1, 1)
	96 dsub (1, 1)
	97 dadd (1, 1)
	98 dstore (1, 1)
	100 iinc (1, 1)
	103 goto (1, 1)
	106 dload (0, 1)
	108 dload (0, 1)
	110 dload (0, 1)
	112 dmul (0, 1)
	113 iload (0, 1)
	115 i2d (0, 1)
	116 ddiv (0, 1)
	117 dsub (0, 1)
	118 iload (0, 1)
	120 iconst_1 (0, 1)
	121 isub (0, 1)
	122 i2d (0, 1)
	123 ddiv (0, 1)
	124 dreturn (0, 1)

Method: normalize
	0 new (0, 0)
	3 dup (0, 0)
	4 invokespecial (0, 0)
	7 astore_1 (0, 0)
	8 iconst_0 (1, 4)
	9 istore_2 (1, 4)
	10 iload_2 (1, 4)
	11 aload_0 (1, 4)
	12 arraylength (1, 4)
	13 if_icmpge (1, 4)
	16 aload_1 (1, 4)
	17 aload_0 (1, 4)
	18 iload_2 (1, 4)
	19 daload (1, 4)
	20 invokevirtual (1, 4)
	23 iinc (1, 4)
	26 goto (1, 4)
	29 aload_1 (0, 0)
	30 invokevirtual (0, 0)
	33 dstore_2 (0, 0)
	34 aload_1 (0, 0)
	35 invokevirtual (0, 0)
	38 dstore (0, 0)
	40 aload_0 (0, 0)
	41 arraylength (0, 0)
	42 newarray (0, 0)
	44 astore (0, 0)
	46 iconst_0 (1, 4)
	47 istore (1, 4)
	49 iload (1, 4)
	51 aload_0 (1, 4)
	52 arraylength (1, 4)
	53 if_icmpge (1, 4)
	56 aload (1, 4)
	58 iload (1, 4)
	60 aload_0 (1, 4)
	61 iload (1, 4)
	63 daload (1, 4)
	64 dload_2 (1, 4)
	65 dsub (1, 4)
	66 dload (1, 4)
	68 ddiv (1, 4)
	69 dastore (1, 4)
	70 iinc (1, 4)
	73 goto (1, 4)
	76 aload (0, 0)
	78 areturn (0, 0)

Method: mode
	0 aload_0 (1, 1)
	1 ifnonnull (1, 1)
	4 new (1, 1)
	7 dup (1, 1)
	8 getstatic (1, 1)
	11 iconst_0 (1, 1)
	12 anewarray (1, 1)
	15 invokespecial (1, 1)
	18 athrow (1, 1)
	19 iload_1 (1, 1)
	20 ifge (1, 1)
	23 new (1, 1)
	26 dup (1, 1)
	27 getstatic (1, 1)
	30 iload_1 (1, 1)
	31 invokestatic (1, 1)
	34 invokespecial (1, 1)
	37 athrow (1, 1)
	38 iload_2 (1, 1)
	39 ifge (1, 1)
	42 new (1, 1)
	45 dup (1, 1)
	46 getstatic (1, 1)
	49 iload_2 (1, 1)
	50 invokestatic (1, 1)
	53 invokespecial (1, 1)
	56 athrow (1, 1)
	57 aload_0 (0, 0)
	58 iload_1 (0, 0)
	59 iload_2 (0, 0)
	60 invokestatic (0, 0)
	63 areturn (0, 0)

Method: getMode
	0 new (0, 0)
	3 dup (0, 0)
	4 invokespecial (0, 0)
	7 astore_3 (0, 0)
	8 iload_1 (1, 4)
	9 istore (1, 4)
	11 iload (1, 4)
	13 iload_1 (1, 4)
	14 iload_2 (1, 4)
	15 iadd (1, 4)
	16 if_icmpge (1, 4)
	19 aload_0 (1, 4)
	20 iload (1, 4)
	22 daload (1, 4)
	23 dstore (1, 4)
	25 dload (2, 1)
	27 invokestatic (2, 1)
	30 ifne (2, 1)
	33 aload_3 (2, 1)
	34 dload (2, 1)
	36 invokestatic (2, 1)
	39 invokevirtual (2, 1)
	42 iinc (2, 1)
	45 goto (2, 1)
	48 aload_3 (1, 4)
	49 invokevirtual (1, 4)
	52 astore (1, 4)
	54 aload (1, 4)
	56 invokeinterface (1, 4)
	61 newarray (1, 4)
	63 astore (1, 4)
	65 iconst_0 (1, 4)
	66 istore (1, 4)
	68 aload (2, 4)
	70 invokeinterface (2, 4)
	75 astore (2, 4)
	77 aload (2, 4)
	79 invokeinterface (2, 4)
	84 ifeq (2, 4)
	87 aload (2, 4)
	89 invokeinterface (2, 4)
	94 checkcast (2, 4)
	97 astore (2, 4)
	99 aload (2, 4)
	101 iload (2, 4)
	103 iinc (2, 4)
	106 aload (2, 4)
	108 checkcast (2, 4)
	111 invokevirtual (2, 4)
	114 dastore (2, 4)
	115 goto (1, 4)
	118 aload (1, 4)
	120 areturn (1, 4)

Method: <clinit>
	0 new (0, 0)
	3 dup (0, 0)
	4 invokespecial (0, 0)
	7 putstatic (0, 0)
	10 new (0, 0)
	13 dup (0, 0)
	14 invokespecial (0, 0)
	17 putstatic (0, 0)
	20 new (0, 0)
	23 dup (0, 0)
	24 invokespecial (0, 0)
	27 putstatic (0, 0)
	30 new (0, 0)
	33 dup (0, 0)
	34 invokespecial (0, 0)
	37 putstatic (0, 0)
	40 new (0, 0)
	43 dup (0, 0)
	44 invokespecial (0, 0)
	47 putstatic (0, 0)
	50 new (0, 0)
	53 dup (0, 0)
	54 invokespecial (0, 0)
	57 putstatic (0, 0)
	60 new (0, 0)
	63 dup (0, 0)
	64 invokespecial (0, 0)
	67 putstatic (0, 0)
	70 new (0, 0)
	73 dup (0, 0)
	74 invokespecial (0, 0)
	77 putstatic (0, 0)
	80 new (0, 0)
	83 dup (0, 0)
	84 invokespecial (0, 0)
	87 putstatic (0, 0)
	90 new (0, 0)
	93 dup (0, 0)
	94 invokespecial (0, 0)
	97 putstatic (0, 0)
	100 return (0, 0)

