Method: <init>
	0 aload_0 (0, 0)
	1 iload_1 (0, 0)
	2 iload_2 (0, 0)
	3 iload_3 (0, 0)
	4 iload (0, 0)
	6 iconst_2 (0, 0)
	7 newarray (0, 0)
	9 dup (0, 0)
	10 iconst_0 (0, 0)
	11 lload (0, 0)
	13 bipush (0, 0)
	15 lushr (0, 0)
	16 l2i (0, 0)
	17 iastore (0, 0)
	18 dup (0, 0)
	19 iconst_1 (0, 0)
	20 lload (0, 0)
	22 ldc2_w (0, 0)
	25 land (0, 0)
	26 l2i (0, 0)
	27 iastore (0, 0)
	28 invokespecial (0, 0)
	31 return (0, 0)

Method: setSeed
	0 aload_0 (0, 0)
	1 iconst_2 (0, 0)
	2 newarray (0, 0)
	4 dup (0, 0)
	5 iconst_0 (0, 0)
	6 lload_1 (0, 0)
	7 bipush (0, 0)
	9 lushr (0, 0)
	10 l2i (0, 0)
	11 iastore (0, 0)
	12 dup (0, 0)
	13 iconst_1 (0, 0)
	14 lload_1 (0, 0)
	15 ldc2_w (0, 0)
	18 land (0, 0)
	19 l2i (0, 0)
	20 iastore (0, 0)
	21 invokevirtual (0, 0)
	24 return (0, 0)

