Method: <init>
	0 aload_0 (0, 0)
	1 invokespecial (0, 0)
	2 java/lang/Object.<init>:()V (0, 0)
	4 aload_0 (0, 0)
	5 ldc2_w (0, 0)
	6 nan (0, 0)
	8 putfield (0, 0)
	9 org/apache/commons/math3/random/BitsStreamGenerator.nextGaussian:D (0, 0)
	11 return (0, 0)

Method: nextBoolean
	0 aload_0 (0, 0)
	1 iconst_1 (0, 0)
	2 invokevirtual (0, 0)
	3 org/apache/commons/math3/random/BitsStreamGenerator.next:(I)I (0, 0)
	5 ifeq (0, 0)
	6 7 (0, 0)
	8 iconst_1 (0, 0)
	9 goto (0, 0)
	10 4 (0, 0)
	12 iconst_0 (0, 0)
	13 ireturn (0, 0)

Method: nextDouble
	0 aload_0 (0, 0)
	1 bipush (0, 0)
	2 26 (0, 0)
	3 invokevirtual (0, 0)
	4 org/apache/commons/math3/random/BitsStreamGenerator.next:(I)I (0, 0)
	6 i2l (0, 0)
	7 bipush (0, 0)
	8 26 (0, 0)
	9 lshl (0, 0)
	10 lstore_1 (0, 0)
	11 aload_0 (0, 0)
	12 bipush (0, 0)
	13 26 (0, 0)
	14 invokevirtual (0, 0)
	15 org/apache/commons/math3/random/BitsStreamGenerator.next:(I)I (0, 0)
	17 istore_3 (0, 0)
	18 lload_1 (0, 0)
	19 iload_3 (0, 0)
	20 i2l (0, 0)
	21 lor (0, 0)
	22 l2d (0, 0)
	23 ldc2_w (0, 0)
	24 2.220446049250313e-16 (0, 0)
	26 dmul (0, 0)
	27 dreturn (0, 0)

Method: nextFloat
	0 aload_0 (0, 0)
	1 bipush (0, 0)
	2 23 (0, 0)
	3 invokevirtual (0, 0)
	4 org/apache/commons/math3/random/BitsStreamGenerator.next:(I)I (0, 0)
	6 i2f (0, 0)
	7 ldc (0, 0)
	8 1.1920928955078125e-07 (0, 0)
	9 fmul (0, 0)
	10 freturn (0, 0)

Method: nextGaussian
	0 aload_0 (1, 1)
	1 getfield (1, 1)
	2 org/apache/commons/math3/random/BitsStreamGenerator.nextGaussian:D (1, 1)
	4 invokestatic (1, 1)
	5 java/lang/Double.isNaN:(D)Z (1, 1)
	7 ifeq (1, 1)
	8 59 (1, 1)
	10 aload_0 (1, 1)
	11 invokevirtual (1, 1)
	12 org/apache/commons/math3/random/BitsStreamGenerator.nextDouble:()D (1, 1)
	14 dstore_3 (1, 1)
	15 aload_0 (1, 1)
	16 invokevirtual (1, 1)
	17 org/apache/commons/math3/random/BitsStreamGenerator.nextDouble:()D (1, 1)
	19 dstore (1, 1)
	20 #5 (1, 1)
	21 ldc2_w (1, 1)
	22 6.283185307179586 (1, 1)
	24 dload_3 (1, 1)
	25 dmul (1, 1)
	26 dstore (1, 1)
	27 #7 (1, 1)
	28 ldc2_w (1, 1)
	29 -2.0 (1, 1)
	31 dload (1, 1)
	32 #5 (1, 1)
	33 invokestatic (1, 1)
	34 org/apache/commons/math3/util/FastMath.log:(D)D (1, 1)
	36 dmul (1, 1)
	37 invokestatic (1, 1)
	38 org/apache/commons/math3/util/FastMath.sqrt:(D)D (1, 1)
	40 dstore (1, 1)
	41 #9 (1, 1)
	42 dload (1, 1)
	43 #9 (1, 1)
	44 dload (1, 1)
	45 #7 (1, 1)
	46 invokestatic (1, 1)
	47 org/apache/commons/math3/util/FastMath.cos:(D)D (1, 1)
	49 dmul (1, 1)
	50 dstore_1 (1, 1)
	51 aload_0 (1, 1)
	52 dload (1, 1)
	53 #9 (1, 1)
	54 dload (1, 1)
	55 #7 (1, 1)
	56 invokestatic (1, 1)
	57 org/apache/commons/math3/util/FastMath.sin:(D)D (1, 1)
	59 dmul (1, 1)
	60 putfield (1, 1)
	61 org/apache/commons/math3/random/BitsStreamGenerator.nextGaussian:D (1, 1)
	63 goto (2, 2)
	64 15 (2, 2)
	66 aload_0 (2, 2)
	67 getfield (2, 2)
	68 org/apache/commons/math3/random/BitsStreamGenerator.nextGaussian:D (2, 2)
	70 dstore_1 (2, 2)
	71 aload_0 (2, 2)
	72 ldc2_w (2, 2)
	73 nan (2, 2)
	75 putfield (2, 2)
	76 org/apache/commons/math3/random/BitsStreamGenerator.nextGaussian:D (2, 2)
	78 dload_1 (0, 0)
	79 dreturn (0, 0)

Method: nextInt
	0 iload_1 (1, 1)
	1 ifle (1, 1)
	2 49 (1, 1)
	4 iload_1 (2, 1)
	5 iload_1 (2, 1)
	6 ineg (2, 1)
	7 iand (2, 1)
	8 iload_1 (2, 1)
	9 if_icmpne (2, 1)
	10 18 (2, 1)
	12 iload_1 (2, 1)
	13 i2l (2, 1)
	14 aload_0 (2, 1)
	15 bipush (2, 1)
	16 31 (2, 1)
	17 invokevirtual (2, 1)
	18 org/apache/commons/math3/random/BitsStreamGenerator.next:(I)I (2, 1)
	20 i2l (2, 1)
	21 lmul (2, 1)
	22 bipush (2, 1)
	23 31 (2, 1)
	24 lshr (2, 1)
	25 l2i (2, 1)
	26 ireturn (2, 1)
	27 aload_0 (1, 1)
	28 bipush (1, 1)
	29 31 (1, 1)
	30 invokevirtual (1, 1)
	31 org/apache/commons/math3/random/BitsStreamGenerator.next:(I)I (1, 1)
	33 istore_2 (1, 1)
	34 iload_2 (1, 1)
	35 iload_1 (1, 1)
	36 irem (1, 1)
	37 istore_3 (1, 1)
	38 iload_2 (2, 3)
	39 iload_3 (2, 3)
	40 isub (2, 3)
	41 iload_1 (2, 3)
	42 iconst_1 (2, 3)
	43 isub (2, 3)
	44 iadd (2, 3)
	45 iflt (2, 3)
	46 -18 (2, 3)
	48 iload_3 (2, 3)
	49 ireturn (2, 3)
	50 new (0, 0)
	51 org/apache/commons/math3/exception/NotStrictlyPositiveException (0, 0)
	53 dup (0, 0)
	54 iload_1 (0, 0)
	55 invokestatic (0, 0)
	56 java/lang/Integer.valueOf:(I)Ljava/lang/Integer; (0, 0)
	58 invokespecial (0, 0)
	59 org/apache/commons/math3/exception/NotStrictlyPositiveException.<init>:(Ljava/lang/Number;)V (0, 0)
	61 athrow (0, 0)

Method: nextLong
	0 lload_1 (1, 1)
	1 lconst_0 (1, 1)
	2 lcmp (1, 1)
	3 ifle (1, 1)
	4 49 (1, 1)
	6 aload_0 (1, 1)
	7 bipush (1, 1)
	8 31 (1, 1)
	9 invokevirtual (1, 1)
	10 org/apache/commons/math3/random/BitsStreamGenerator.next:(I)I (1, 1)
	12 i2l (1, 1)
	13 bipush (1, 1)
	14 32 (1, 1)
	15 lshl (1, 1)
	16 lstore_3 (1, 1)
	17 lload_3 (1, 1)
	18 aload_0 (1, 1)
	19 bipush (1, 1)
	20 32 (1, 1)
	21 invokevirtual (1, 1)
	22 org/apache/commons/math3/random/BitsStreamGenerator.next:(I)I (1, 1)
	24 i2l (1, 1)
	25 ldc2_w (1, 1)
	26 4294967295 (1, 1)
	28 land (1, 1)
	29 lor (1, 1)
	30 lstore_3 (1, 1)
	31 lload_3 (1, 1)
	32 lload_1 (1, 1)
	33 lrem (1, 1)
	34 lstore (1, 1)
	35 #5 (1, 1)
	36 lload_3 (2, 3)
	37 lload (2, 3)
	38 #5 (2, 3)
	39 lsub (2, 3)
	40 lload_1 (2, 3)
	41 lconst_1 (2, 3)
	42 lsub (2, 3)
	43 ladd (2, 3)
	44 lconst_0 (2, 3)
	45 lcmp (2, 3)
	46 iflt (2, 3)
	47 -40 (2, 3)
	49 lload (2, 3)
	50 #5 (2, 3)
	51 lreturn (2, 3)
	52 new (0, 0)
	53 org/apache/commons/math3/exception/NotStrictlyPositiveException (0, 0)
	55 dup (0, 0)
	56 lload_1 (0, 0)
	57 invokestatic (0, 0)
	58 java/lang/Long.valueOf:(J)Ljava/lang/Long; (0, 0)
	60 invokespecial (0, 0)
	61 org/apache/commons/math3/exception/NotStrictlyPositiveException.<init>:(Ljava/lang/Number;)V (0, 0)
	63 athrow (0, 0)

Method: clear
	0 aload_0 (0, 0)
	1 ldc2_w (0, 0)
	2 nan (0, 0)
	4 putfield (0, 0)
	5 org/apache/commons/math3/random/BitsStreamGenerator.nextGaussian:D (0, 0)
	7 return (0, 0)

Method: nextBytes
	0 iload_2 (1, 1)
	1 iflt (1, 1)
	2 9 (1, 1)
	4 iload_2 (1, 1)
	5 aload_1 (1, 1)
	6 arraylength (1, 1)
	7 if_icmplt (1, 1)
	8 24 (1, 1)
	10 new (1, 1)
	11 org/apache/commons/math3/exception/OutOfRangeException (1, 1)
	13 dup (1, 1)
	14 iload_2 (1, 1)
	15 invokestatic (1, 1)
	16 java/lang/Integer.valueOf:(I)Ljava/lang/Integer; (1, 1)
	18 iconst_0 (1, 1)
	19 invokestatic (1, 1)
	20 java/lang/Integer.valueOf:(I)Ljava/lang/Integer; (1, 1)
	22 aload_1 (1, 1)
	23 arraylength (1, 1)
	24 invokestatic (1, 1)
	25 java/lang/Integer.valueOf:(I)Ljava/lang/Integer; (1, 1)
	27 invokespecial (1, 1)
	28 org/apache/commons/math3/exception/OutOfRangeException.<init>:(Ljava/lang/Number;Ljava/lang/Number;Ljava/lang/Number;)V (1, 1)
	30 athrow (1, 1)
	31 iload_3 (2, 1)
	32 iflt (2, 1)
	33 11 (2, 1)
	35 iload_3 (2, 1)
	36 aload_1 (2, 1)
	37 arraylength (2, 1)
	38 iload_2 (2, 1)
	39 isub (2, 1)
	40 if_icmple (2, 1)
	41 26 (2, 1)
	43 new (2, 1)
	44 org/apache/commons/math3/exception/OutOfRangeException (2, 1)
	46 dup (2, 1)
	47 iload_3 (2, 1)
	48 invokestatic (2, 1)
	49 java/lang/Integer.valueOf:(I)Ljava/lang/Integer; (2, 1)
	51 iconst_0 (2, 1)
	52 invokestatic (2, 1)
	53 java/lang/Integer.valueOf:(I)Ljava/lang/Integer; (2, 1)
	55 aload_1 (2, 1)
	56 arraylength (2, 1)
	57 iload_2 (2, 1)
	58 isub (2, 1)
	59 invokestatic (2, 1)
	60 java/lang/Integer.valueOf:(I)Ljava/lang/Integer; (2, 1)
	62 invokespecial (2, 1)
	63 org/apache/commons/math3/exception/OutOfRangeException.<init>:(Ljava/lang/Number;Ljava/lang/Number;Ljava/lang/Number;)V (2, 1)
	65 athrow (2, 1)
	66 aload_0 (2, 1)
	67 aload_1 (2, 1)
	68 iload_2 (2, 1)
	69 iload_3 (2, 1)
	70 invokespecial (2, 1)
	71 org/apache/commons/math3/random/BitsStreamGenerator.nextBytesFill:([BII)V (2, 1)
	73 return (0, 1)

Method: nextBytesFill
	0 iload_2 (0, 0)
	1 istore (0, 0)
	2 #4 (0, 0)
	3 iload (1, 1)
	4 #4 (1, 1)
	5 iload_3 (1, 1)
	6 ldc (1, 1)
	7 2147483644 (1, 1)
	8 iand (1, 1)
	9 iadd (1, 1)
	10 istore (1, 1)
	11 #5 (1, 1)
	12 iload (2, 3)
	13 #4 (2, 3)
	14 iload (2, 3)
	15 #5 (2, 3)
	16 if_icmpge (2, 3)
	17 63 (2, 3)
	19 aload_0 (2, 3)
	20 bipush (2, 3)
	21 32 (2, 3)
	22 invokevirtual (2, 3)
	23 org/apache/commons/math3/random/BitsStreamGenerator.next:(I)I (2, 3)
	25 istore (2, 3)
	26 #6 (2, 3)
	27 aload_1 (2, 3)
	28 iload (2, 3)
	29 #4 (2, 3)
	30 iinc (2, 3)
	31 #4 (2, 3)
	32 21 (2, 3)
	33 iload (2, 3)
	34 #6 (2, 3)
	35 i2b (2, 3)
	36 bastore (2, 3)
	37 aload_1 (2, 3)
	38 iload (2, 3)
	39 #4 (2, 3)
	40 iinc (2, 3)
	41 #4 (2, 3)
	42 21 (2, 3)
	43 iload (2, 3)
	44 #6 (2, 3)
	45 bipush (2, 3)
	46 8 (2, 3)
	47 iushr (2, 3)
	48 i2b (2, 3)
	49 bastore (2, 3)
	50 aload_1 (2, 3)
	51 iload (2, 3)
	52 #4 (2, 3)
	53 iinc (2, 3)
	54 #4 (2, 3)
	55 21 (2, 3)
	56 iload (2, 3)
	57 #6 (2, 3)
	58 bipush (2, 3)
	59 16 (2, 3)
	60 iushr (2, 3)
	61 i2b (2, 3)
	62 bastore (2, 3)
	63 aload_1 (2, 3)
	64 iload (2, 3)
	65 #4 (2, 3)
	66 iinc (2, 3)
	67 #4 (2, 3)
	68 21 (2, 3)
	69 iload (2, 3)
	70 #6 (2, 3)
	71 bipush (2, 3)
	72 24 (2, 3)
	73 iushr (2, 3)
	74 i2b (2, 3)
	75 bastore (2, 3)
	76 goto (1, 1)
	77 -64 (1, 1)
	79 iload_2 (1, 1)
	80 iload_3 (1, 1)
	81 iadd (1, 1)
	82 istore (1, 1)
	83 #6 (1, 1)
	84 iload (2, 1)
	85 #4 (2, 1)
	86 iload (2, 1)
	87 #6 (2, 1)
	88 if_icmpge (2, 1)
	89 38 (2, 1)
	91 aload_0 (2, 1)
	92 bipush (2, 1)
	93 32 (2, 1)
	94 invokevirtual (2, 1)
	95 org/apache/commons/math3/random/BitsStreamGenerator.next:(I)I (2, 1)
	97 istore (2, 1)
	98 #7 (2, 1)
	99 aload_1 (3, 3)
	100 iload (3, 3)
	101 #4 (3, 3)
	102 iinc (3, 3)
	103 #4 (3, 3)
	104 21 (3, 3)
	105 iload (3, 3)
	106 #7 (3, 3)
	107 i2b (3, 3)
	108 bastore (3, 3)
	109 iload (4, 1)
	110 #4 (4, 1)
	111 iload (4, 1)
	112 #6 (4, 1)
	113 if_icmpge (4, 1)
	114 13 (4, 1)
	116 iload (4, 1)
	117 #7 (4, 1)
	118 bipush (4, 1)
	119 8 (4, 1)
	120 iushr (4, 1)
	121 istore (4, 1)
	122 #7 (4, 1)
	123 goto (4, 1)
	124 -24 (4, 1)
	126 return (0, 1)

