Method: <init>
	0 aload_0 (0, 0)
	1 invokespecial (0, 0)
	2 java/lang/Object.<init>:()V (0, 0)
	4 aload_1 (0, 0)
	5 invokeinterface (0, 0)
	6 org/apache/commons/math3/linear/RealMatrix.org/apache/commons/math3/exception/DimensionMismatchException (0, 0)
	8 0 (0, 0)
	10 istore (0, 0)
	11 #5 (0, 0)
	12 aload_0 (0, 0)
	13 iload (0, 0)
	14 #5 (0, 0)
	15 newarray (0, 0)
	16 7 (0, 0)
	17 putfield (0, 0)
	18 org/apache/commons/math3/random/CorrelatedRandomVectorGenerator.mean:[D (0, 0)
	20 iconst_0 (2, 4)
	21 istore (2, 4)
	22 #6 (2, 4)
	23 iload (2, 4)
	24 #6 (2, 4)
	25 iload (2, 4)
	26 #5 (2, 4)
	27 if_icmpge (2, 4)
	28 17 (2, 4)
	30 aload_0 (2, 4)
	31 getfield (2, 4)
	32 org/apache/commons/math3/random/CorrelatedRandomVectorGenerator.mean:[D (2, 4)
	34 iload (2, 4)
	35 #6 (2, 4)
	36 dconst_0 (2, 4)
	37 dastore (2, 4)
	38 iinc (2, 4)
	39 #6 (2, 4)
	40 -89 (2, 4)
	41 goto (2, 4)
	42 -18 (2, 4)
	44 new (0, 0)
	45 org/apache/commons/math3/linear/RectangularCholeskyDecomposition (0, 0)
	47 dup (0, 0)
	48 aload_1 (0, 0)
	49 dload_2 (0, 0)
	50 invokespecial (0, 0)
	51 org/apache/commons/math3/linear/RectangularCholeskyDecomposition.<init>:(Lorg/apache/commons/math3/linear/RealMatrix;D)V (0, 0)
	53 astore (0, 0)
	54 #6 (0, 0)
	55 aload_0 (0, 0)
	56 aload (0, 0)
	57 #6 (0, 0)
	58 invokevirtual (0, 0)
	59 org/apache/commons/math3/linear/RectangularCholeskyDecomposition.getRootMatrix:()Lorg/apache/commons/math3/linear/RealMatrix; (0, 0)
	61 putfield (0, 0)
	62 org/apache/commons/math3/random/CorrelatedRandomVectorGenerator.root:Lorg/apache/commons/math3/linear/RealMatrix; (0, 0)
	64 aload_0 (0, 0)
	65 aload (0, 0)
	66 #4 (0, 0)
	67 putfield (0, 0)
	68 org/apache/commons/math3/random/CorrelatedRandomVectorGenerator.generator:Lorg/apache/commons/math3/random/NormalizedRandomGenerator; (0, 0)
	70 aload_0 (0, 0)
	71 aload (0, 0)
	72 #6 (0, 0)
	73 invokevirtual (0, 0)
	74 org/apache/commons/math3/linear/RectangularCholeskyDecomposition.getRank:()I (0, 0)
	76 newarray (0, 0)
	77 7 (0, 0)
	78 putfield (0, 0)
	79 org/apache/commons/math3/random/CorrelatedRandomVectorGenerator.normalized:[D (0, 0)
	81 return (0, 0)

Method: getGenerator
	0 aload_0 (0, 0)
	1 getfield (0, 0)
	2 org/apache/commons/math3/random/CorrelatedRandomVectorGenerator.generator:Lorg/apache/commons/math3/random/NormalizedRandomGenerator; (0, 0)
	4 areturn (0, 0)

Method: getRank
	0 aload_0 (0, 0)
	1 getfield (0, 0)
	2 org/apache/commons/math3/random/CorrelatedRandomVectorGenerator.normalized:[D (0, 0)
	4 arraylength (0, 0)
	5 ireturn (0, 0)

Method: getRootMatrix
	0 aload_0 (0, 0)
	1 getfield (0, 0)
	2 org/apache/commons/math3/random/CorrelatedRandomVectorGenerator.root:Lorg/apache/commons/math3/linear/RealMatrix; (0, 0)
	4 areturn (0, 0)

Method: nextVector
	0 iconst_0 (1, 4)
	1 istore_1 (1, 4)
	2 iload_1 (1, 4)
	3 aload_0 (1, 4)
	4 getfield (1, 4)
	5 org/apache/commons/math3/random/CorrelatedRandomVectorGenerator.normalized:[D (1, 4)
	7 arraylength (1, 4)
	8 if_icmpge (1, 4)
	9 24 (1, 4)
	11 aload_0 (1, 4)
	12 getfield (1, 4)
	13 org/apache/commons/math3/random/CorrelatedRandomVectorGenerator.normalized:[D (1, 4)
	15 iload_1 (1, 4)
	16 aload_0 (1, 4)
	17 getfield (1, 4)
	18 org/apache/commons/math3/random/CorrelatedRandomVectorGenerator.generator:Lorg/apache/commons/math3/random/NormalizedRandomGenerator; (1, 4)
	20 invokeinterface (1, 4)
	21 org/apache/commons/math3/random/NormalizedRandomGenerator.getColumnDimension:()I (1, 4)
	23 0 (1, 4)
	25 dastore (1, 4)
	26 iinc (1, 4)
	27 #1 (1, 4)
	28 -89 (1, 4)
	29 goto (1, 4)
	30 -27 (1, 4)
	32 aload_0 (0, 0)
	33 getfield (0, 0)
	34 org/apache/commons/math3/random/CorrelatedRandomVectorGenerator.mean:[D (0, 0)
	36 arraylength (0, 0)
	37 newarray (0, 0)
	38 7 (0, 0)
	39 astore_1 (0, 0)
	40 iconst_0 (1, 4)
	41 istore_2 (1, 4)
	42 iload_2 (1, 4)
	43 aload_1 (1, 4)
	44 arraylength (1, 4)
	45 if_icmpge (1, 4)
	46 63 (1, 4)
	48 aload_1 (1, 4)
	49 iload_2 (1, 4)
	50 aload_0 (1, 4)
	51 getfield (1, 4)
	52 org/apache/commons/math3/random/CorrelatedRandomVectorGenerator.mean:[D (1, 4)
	54 iload_2 (1, 4)
	55 daload (1, 4)
	56 dastore (1, 4)
	57 iconst_0 (2, 4)
	58 istore_3 (2, 4)
	59 iload_3 (2, 4)
	60 aload_0 (2, 4)
	61 getfield (2, 4)
	62 org/apache/commons/math3/random/CorrelatedRandomVectorGenerator.root:Lorg/apache/commons/math3/linear/RealMatrix; (2, 4)
	64 invokeinterface (2, 4)
	65 org/apache/commons/math3/linear/RealMatrix.getEntry:(II)D (2, 4)
	67 0 (2, 4)
	69 if_icmpge (2, 4)
	70 33 (2, 4)
	72 aload_1 (2, 4)
	73 iload_2 (2, 4)
	74 dup2 (2, 4)
	75 daload (2, 4)
	76 aload_0 (2, 4)
	77 getfield (2, 4)
	78 org/apache/commons/math3/random/CorrelatedRandomVectorGenerator.root:Lorg/apache/commons/math3/linear/RealMatrix; (2, 4)
	80 iload_2 (2, 4)
	81 iload_3 (2, 4)
	82 invokeinterface (2, 4)
	83 org/apache/commons/math3/linear/RealMatrix.org/apache/commons/math3/random/CorrelatedRandomVectorGenerator (2, 4)
	85 0 (2, 4)
	87 aload_0 (2, 4)
	88 getfield (2, 4)
	89 org/apache/commons/math3/random/CorrelatedRandomVectorGenerator.normalized:[D (2, 4)
	91 iload_3 (2, 4)
	92 daload (2, 4)
	93 dmul (2, 4)
	94 dadd (2, 4)
	95 dastore (2, 4)
	96 iinc (2, 4)
	97 #3 (2, 4)
	98 -89 (2, 4)
	99 goto (2, 4)
	100 -40 (2, 4)
	102 iinc (2, 4)
	103 #2 (2, 4)
	104 -89 (2, 4)
	105 goto (2, 4)
	106 -63 (2, 4)
	108 aload_1 (1, 4)
	109 areturn (1, 4)

