Method: <init>
	0 aload_0 (0, 0)
	1 aload_1 (0, 0)
	2 putfield (0, 0)
	3 org/apache/commons/math3/random/EmpiricalDistribution$StreamDataAdapter.this$0:Lorg/apache/commons/math3/random/EmpiricalDistribution; (0, 0)
	5 aload_0 (0, 0)
	6 aload_1 (0, 0)
	7 aconst_null (0, 0)
	8 invokespecial (0, 0)
	9 org/apache/commons/math3/random/EmpiricalDistribution$DataAdapter.<init>:(Lorg/apache/commons/math3/random/EmpiricalDistribution;Lorg/apache/commons/math3/random/EmpiricalDistribution$1;)V (0, 0)
	11 aload_0 (0, 0)
	12 aload_2 (0, 0)
	13 putfield (0, 0)
	14 org/apache/commons/math3/random/EmpiricalDistribution$StreamDataAdapter.inputStream:Ljava/io/BufferedReader; (0, 0)
	16 return (0, 0)

Method: computeBinStats
	0 aconst_null (0, 0)
	1 astore_1 (0, 0)
	2 dconst_0 (0, 0)
	3 dstore_2 (0, 0)
	4 aload_0 (1, 3)
	5 getfield (1, 3)
	6 org/apache/commons/math3/random/EmpiricalDistribution$StreamDataAdapter.inputStream:Ljava/io/BufferedReader; (1, 3)
	8 invokevirtual (1, 3)
	9 java/io/BufferedReader.readLine:()Ljava/lang/String; (1, 3)
	11 dup (1, 3)
	12 astore_1 (1, 3)
	13 ifnull (1, 3)
	14 42 (1, 3)
	16 aload_1 (1, 3)
	17 invokestatic (1, 3)
	18 java/lang/Double.parseDouble:(Ljava/lang/String;)D (1, 3)
	20 dstore_2 (1, 3)
	21 aload_0 (1, 3)
	22 getfield (1, 3)
	23 org/apache/commons/math3/random/EmpiricalDistribution$StreamDataAdapter.this$0:Lorg/apache/commons/math3/random/EmpiricalDistribution; (1, 3)
	25 invokestatic (1, 3)
	26 org/apache/commons/math3/random/EmpiricalDistribution.access$200:(Lorg/apache/commons/math3/random/EmpiricalDistribution;)Ljava/util/List; (1, 3)
	28 aload_0 (1, 3)
	29 getfield (1, 3)
	30 org/apache/commons/math3/random/EmpiricalDistribution$StreamDataAdapter.this$0:Lorg/apache/commons/math3/random/EmpiricalDistribution; (1, 3)
	32 dload_2 (1, 3)
	33 invokestatic (1, 3)
	34 org/apache/commons/math3/random/EmpiricalDistribution.access$100:(Lorg/apache/commons/math3/random/EmpiricalDistribution;D)I (1, 3)
	36 invokeinterface (1, 3)
	37 java/util/List.org/apache/commons/math3/stat/descriptive/SummaryStatistics (1, 3)
	39 0 (1, 3)
	41 checkcast (1, 3)
	42 org/apache/commons/math3/stat/descriptive/SummaryStatistics (1, 3)
	44 astore (1, 3)
	45 #4 (1, 3)
	46 aload (1, 3)
	47 #4 (1, 3)
	48 dload_2 (1, 3)
	49 invokevirtual (1, 3)
	50 org/apache/commons/math3/stat/descriptive/SummaryStatistics.addValue:(D)V (1, 3)
	52 goto (0, 0)
	53 -48 (0, 0)
	55 aload_0 (0, 0)
	56 getfield (0, 0)
	57 org/apache/commons/math3/random/EmpiricalDistribution$StreamDataAdapter.inputStream:Ljava/io/BufferedReader; (0, 0)
	59 invokevirtual (0, 0)
	60 java/io/BufferedReader.close:()V (0, 0)
	62 aload_0 (0, 0)
	63 aconst_null (0, 0)
	64 putfield (0, 0)
	65 org/apache/commons/math3/random/EmpiricalDistribution$StreamDataAdapter.inputStream:Ljava/io/BufferedReader; (0, 0)
	67 return (0, 0)

Method: computeStats
	0 aconst_null (0, 0)
	1 astore_1 (0, 0)
	2 dconst_0 (0, 0)
	3 dstore_2 (0, 0)
	4 aload_0 (0, 0)
	5 getfield (0, 0)
	6 org/apache/commons/math3/random/EmpiricalDistribution$StreamDataAdapter.this$0:Lorg/apache/commons/math3/random/EmpiricalDistribution; (0, 0)
	8 new (0, 0)
	9 org/apache/commons/math3/stat/descriptive/SummaryStatistics (0, 0)
	11 dup (0, 0)
	12 invokespecial (0, 0)
	13 org/apache/commons/math3/stat/descriptive/SummaryStatistics.<init>:()V (0, 0)
	15 invokestatic (0, 0)
	16 org/apache/commons/math3/random/EmpiricalDistribution.access$302:(Lorg/apache/commons/math3/random/EmpiricalDistribution;Lorg/apache/commons/math3/stat/descriptive/SummaryStatistics;)Lorg/apache/commons/math3/stat/descriptive/SummaryStatistics; (0, 0)
	18 pop (0, 0)
	19 aload_0 (1, 3)
	20 getfield (1, 3)
	21 org/apache/commons/math3/random/EmpiricalDistribution$StreamDataAdapter.inputStream:Ljava/io/BufferedReader; (1, 3)
	23 invokevirtual (1, 3)
	24 java/io/BufferedReader.readLine:()Ljava/lang/String; (1, 3)
	26 dup (1, 3)
	27 astore_1 (1, 3)
	28 ifnull (1, 3)
	29 22 (1, 3)
	31 aload_1 (1, 3)
	32 invokestatic (1, 3)
	33 java/lang/Double.parseDouble:(Ljava/lang/String;)D (1, 3)
	35 dstore_2 (1, 3)
	36 aload_0 (1, 3)
	37 getfield (1, 3)
	38 org/apache/commons/math3/random/EmpiricalDistribution$StreamDataAdapter.this$0:Lorg/apache/commons/math3/random/EmpiricalDistribution; (1, 3)
	40 invokestatic (1, 3)
	41 org/apache/commons/math3/random/EmpiricalDistribution.access$300:(Lorg/apache/commons/math3/random/EmpiricalDistribution;)Lorg/apache/commons/math3/stat/descriptive/SummaryStatistics; (1, 3)
	43 dload_2 (1, 3)
	44 invokevirtual (1, 3)
	45 org/apache/commons/math3/stat/descriptive/SummaryStatistics.addValue:(D)V (1, 3)
	47 goto (1, 3)
	48 -28 (1, 3)
	50 aload_0 (0, 0)
	51 getfield (0, 0)
	52 org/apache/commons/math3/random/EmpiricalDistribution$StreamDataAdapter.inputStream:Ljava/io/BufferedReader; (0, 0)
	54 invokevirtual (0, 0)
	55 java/io/BufferedReader.close:()V (0, 0)
	57 aload_0 (0, 0)
	58 aconst_null (0, 0)
	59 putfield (0, 0)
	60 org/apache/commons/math3/random/EmpiricalDistribution$StreamDataAdapter.inputStream:Ljava/io/BufferedReader; (0, 0)
	62 return (0, 0)

