Method: <init>
	0 aload_0 (0, 0)
	1 aload_2 (0, 0)
	2 invokevirtual (0, 0)
	5 invokespecial (0, 0)
	8 aload_0 (0, 0)
	9 aconst_null (0, 0)
	10 putfield (0, 0)
	13 aload_0 (0, 0)
	14 ldc2_w (0, 0)
	17 putfield (0, 0)
	20 aload_0 (0, 0)
	21 ldc2_w (0, 0)
	24 putfield (0, 0)
	27 aload_0 (0, 0)
	28 dconst_0 (0, 0)
	29 putfield (0, 0)
	32 aload_0 (0, 0)
	33 iconst_0 (0, 0)
	34 putfield (0, 0)
	37 aload_0 (0, 0)
	38 aconst_null (0, 0)
	39 putfield (0, 0)
	42 iload_1 (2, 1)
	43 ifgt (2, 1)
	46 new (2, 1)
	49 dup (2, 1)
	50 iload_1 (2, 1)
	51 invokestatic (2, 1)
	54 invokespecial (2, 1)
	57 athrow (2, 1)
	58 aload_0 (1, 1)
	59 iload_1 (1, 1)
	60 putfield (1, 1)
	63 aload_0 (1, 1)
	64 aload_2 (1, 1)
	65 putfield (1, 1)
	68 aload_0 (1, 1)
	69 new (1, 1)
	72 dup (1, 1)
	73 invokespecial (1, 1)
	76 putfield (1, 1)
	79 return (0, 0)

Method: load
	0 aload_1 (0, 0)
	1 invokestatic (0, 0)
	4 ldc (0, 4)
	6 invokestatic (0, 4)
	9 astore_2 (0, 4)
	10 new (0, 4)
	13 dup (0, 4)
	14 aload_1 (0, 4)
	15 invokespecial (0, 4)
	18 astore_3 (0, 4)
	19 new (0, 4)
	22 dup (0, 4)
	23 new (0, 4)
	26 dup (0, 4)
	27 aload_3 (0, 4)
	28 aload_2 (0, 4)
	29 invokespecial (0, 4)
	32 invokespecial (0, 4)
	35 astore (0, 4)
	37 new (1, 4)
	40 dup (1, 4)
	41 aload_0 (1, 4)
	42 aload (1, 4)
	44 invokespecial (1, 4)
	47 astore (1, 4)
	49 aload (1, 4)
	51 invokevirtual (1, 4)
	54 new (1, 4)
	57 dup (1, 4)
	58 aload_1 (1, 4)
	59 invokespecial (1, 4)
	62 astore_3 (1, 4)
	63 new (1, 4)
	66 dup (1, 4)
	67 new (1, 4)
	70 dup (1, 4)
	71 aload_3 (1, 4)
	72 aload_2 (1, 4)
	73 invokespecial (1, 4)
	76 invokespecial (1, 4)
	79 astore (1, 4)
	81 aload_0 (1, 4)
	82 new (1, 4)
	85 dup (1, 4)
	86 aload_0 (1, 4)
	87 aload (1, 4)
	89 invokespecial (1, 4)
	92 invokespecial (1, 4)
	95 aload_0 (1, 4)
	96 iconst_1 (1, 4)
	97 putfield (1, 4)
	100 aload (2, 4)
	102 invokevirtual (2, 4)
	105 goto (1, 4)
	108 astore (1, 4)
	110 goto (0, 0)
	113 astore (0, 0)
	115 aload (0, 0)
	117 invokevirtual (0, 0)
	120 goto (0, 0)
	123 astore (0, 0)
	125 aload (0, 0)
	127 athrow (0, 0)
	128 return (0, 0)

Method: fillBinStats
	0 aload_0 (0, 0)
	1 aload_0 (0, 0)
	2 getfield (0, 0)
	5 invokevirtual (0, 0)
	8 putfield (0, 0)
	11 aload_0 (0, 0)
	12 aload_0 (0, 0)
	13 getfield (0, 0)
	16 invokevirtual (0, 0)
	19 putfield (0, 0)
	22 aload_0 (0, 0)
	23 aload_0 (0, 0)
	24 getfield (0, 0)
	27 aload_0 (0, 0)
	28 getfield (0, 0)
	31 dsub (0, 0)
	32 aload_0 (0, 0)
	33 getfield (0, 0)
	36 i2d (0, 0)
	37 ddiv (0, 0)
	38 putfield (0, 0)
	41 aload_0 (1, 1)
	42 getfield (1, 1)
	45 invokeinterface (1, 1)
	50 ifne (1, 1)
	53 aload_0 (1, 1)
	54 getfield (1, 1)
	57 invokeinterface (1, 1)
	62 iconst_0 (1, 4)
	63 istore_2 (1, 4)
	64 iload_2 (1, 4)
	65 aload_0 (1, 4)
	66 getfield (1, 4)
	69 if_icmpge (1, 4)
	72 new (1, 4)
	75 dup (1, 4)
	76 invokespecial (1, 4)
	79 astore_3 (1, 4)
	80 aload_0 (1, 4)
	81 getfield (1, 4)
	84 iload_2 (1, 4)
	85 aload_3 (1, 4)
	86 invokeinterface (1, 4)
	91 iinc (1, 4)
	94 goto (1, 4)
	97 aload_1 (0, 0)
	98 invokevirtual (0, 0)
	101 aload_0 (0, 0)
	102 aload_0 (0, 0)
	103 getfield (0, 0)
	106 newarray (0, 0)
	108 putfield (0, 0)
	111 aload_0 (0, 0)
	112 getfield (0, 0)
	115 iconst_0 (0, 0)
	116 aload_0 (0, 0)
	117 getfield (0, 0)
	120 iconst_0 (0, 0)
	121 invokeinterface (0, 0)
	126 checkcast (0, 0)
	129 invokevirtual (0, 0)
	132 l2d (0, 0)
	133 aload_0 (0, 0)
	134 getfield (0, 0)
	137 invokevirtual (0, 0)
	140 l2d (0, 0)
	141 ddiv (0, 0)
	142 dastore (0, 0)
	143 iconst_1 (1, 4)
	144 istore_2 (1, 4)
	145 iload_2 (1, 4)
	146 aload_0 (1, 4)
	147 getfield (1, 4)
	150 iconst_1 (1, 4)
	151 isub (1, 4)
	152 if_icmpge (1, 4)
	155 aload_0 (1, 4)
	156 getfield (1, 4)
	159 iload_2 (1, 4)
	160 aload_0 (1, 4)
	161 getfield (1, 4)
	164 iload_2 (1, 4)
	165 iconst_1 (1, 4)
	166 isub (1, 4)
	167 daload (1, 4)
	168 aload_0 (1, 4)
	169 getfield (1, 4)
	172 iload_2 (1, 4)
	173 invokeinterface (1, 4)
	178 checkcast (1, 4)
	181 invokevirtual (1, 4)
	184 l2d (1, 4)
	185 aload_0 (1, 4)
	186 getfield (1, 4)
	189 invokevirtual (1, 4)
	192 l2d (1, 4)
	193 ddiv (1, 4)
	194 dadd (1, 4)
	195 dastore (1, 4)
	196 iinc (1, 4)
	199 goto (1, 4)
	202 aload_0 (0, 0)
	203 getfield (0, 0)
	206 aload_0 (0, 0)
	207 getfield (0, 0)
	210 iconst_1 (0, 0)
	211 isub (0, 0)
	212 dconst_1 (0, 0)
	213 dastore (0, 0)
	214 return (0, 0)

Method: findBin
	0 dload_1 (0, 0)
	1 aload_0 (0, 0)
	2 getfield (0, 0)
	5 dsub (0, 0)
	6 aload_0 (0, 0)
	7 getfield (0, 0)
	10 ddiv (0, 0)
	11 invokestatic (0, 0)
	14 d2i (0, 0)
	15 iconst_1 (0, 0)
	16 isub (0, 0)
	17 iconst_0 (0, 0)
	18 invokestatic (0, 0)
	21 aload_0 (0, 0)
	22 getfield (0, 0)
	25 iconst_1 (0, 0)
	26 isub (0, 0)
	27 invokestatic (0, 0)
	30 ireturn (0, 0)

Method: getNextValue
	0 aload_0 (1, 1)
	1 getfield (1, 1)
	4 ifne (1, 1)
	7 new (1, 1)
	10 dup (1, 1)
	11 getstatic (1, 1)
	14 iconst_0 (1, 1)
	15 anewarray (1, 1)
	18 invokespecial (1, 1)
	21 athrow (1, 1)
	22 aload_0 (0, 0)
	23 invokevirtual (0, 0)
	26 dreturn (0, 0)

Method: getSampleStats
	0 aload_0 (0, 0)
	1 getfield (0, 0)
	4 areturn (0, 0)

Method: getBinCount
	0 aload_0 (0, 0)
	1 getfield (0, 0)
	4 ireturn (0, 0)

Method: getBinStats
	0 aload_0 (0, 0)
	1 getfield (0, 0)
	4 areturn (0, 0)

Method: getUpperBounds
	0 aload_0 (0, 0)
	1 getfield (0, 0)
	4 newarray (0, 0)
	6 astore_1 (0, 0)
	7 iconst_0 (1, 4)
	8 istore_2 (1, 4)
	9 iload_2 (1, 4)
	10 aload_0 (1, 4)
	11 getfield (1, 4)
	14 iconst_1 (1, 4)
	15 isub (1, 4)
	16 if_icmpge (1, 4)
	19 aload_1 (1, 4)
	20 iload_2 (1, 4)
	21 aload_0 (1, 4)
	22 getfield (1, 4)
	25 aload_0 (1, 4)
	26 getfield (1, 4)
	29 iload_2 (1, 4)
	30 iconst_1 (1, 4)
	31 iadd (1, 4)
	32 i2d (1, 4)
	33 dmul (1, 4)
	34 dadd (1, 4)
	35 dastore (1, 4)
	36 iinc (1, 4)
	39 goto (1, 4)
	42 aload_1 (0, 0)
	43 aload_0 (0, 0)
	44 getfield (0, 0)
	47 iconst_1 (0, 0)
	48 isub (0, 0)
	49 aload_0 (0, 0)
	50 getfield (0, 0)
	53 dastore (0, 0)
	54 aload_1 (0, 0)
	55 areturn (0, 0)

Method: getGeneratorUpperBounds
	0 aload_0 (0, 0)
	1 getfield (0, 0)
	4 arraylength (0, 0)
	5 istore_1 (0, 0)
	6 iload_1 (0, 0)
	7 newarray (0, 0)
	9 astore_2 (0, 0)
	10 aload_0 (0, 0)
	11 getfield (0, 0)
	14 iconst_0 (0, 0)
	15 aload_2 (0, 0)
	16 iconst_0 (0, 0)
	17 iload_1 (0, 0)
	18 invokestatic (0, 0)
	21 aload_2 (0, 0)
	22 areturn (0, 0)

Method: isLoaded
	0 aload_0 (0, 0)
	1 getfield (0, 0)
	4 ireturn (0, 0)

Method: reSeed
	0 aload_0 (0, 0)
	1 getfield (0, 0)
	4 lload_1 (0, 0)
	5 invokevirtual (0, 0)
	8 return (0, 0)

Method: probability
	0 dconst_0 (0, 0)
	1 dreturn (0, 0)

Method: density
	0 dload_1 (1, 1)
	1 aload_0 (1, 1)
	2 getfield (1, 1)
	5 dcmpg (1, 1)
	6 iflt (1, 1)
	9 dload_1 (1, 1)
	10 aload_0 (1, 1)
	11 getfield (1, 1)
	14 dcmpl (1, 1)
	15 ifle (1, 1)
	18 dconst_0 (1, 1)
	19 dreturn (1, 1)
	20 aload_0 (0, 0)
	21 dload_1 (0, 0)
	22 invokespecial (0, 0)
	25 istore_3 (0, 0)
	26 aload_0 (0, 0)
	27 aload_0 (0, 0)
	28 getfield (0, 0)
	31 iload_3 (0, 0)
	32 invokeinterface (0, 0)
	37 checkcast (0, 0)
	40 invokevirtual (0, 0)
	43 astore (0, 0)
	45 aload (0, 0)
	47 dload_1 (0, 0)
	48 invokeinterface (0, 0)
	53 aload_0 (0, 0)
	54 iload_3 (0, 0)
	55 invokespecial (0, 0)
	58 dmul (0, 0)
	59 aload_0 (0, 0)
	60 iload_3 (0, 0)
	61 invokespecial (0, 0)
	64 ddiv (0, 0)
	65 dreturn (0, 0)

Method: cumulativeProbability
	0 dload_1 (1, 1)
	1 aload_0 (1, 1)
	2 getfield (1, 1)
	5 dcmpg (1, 1)
	6 ifge (1, 1)
	9 dconst_0 (1, 1)
	10 dreturn (1, 1)
	11 dload_1 (1, 1)
	12 aload_0 (1, 1)
	13 getfield (1, 1)
	16 dcmpl (1, 1)
	17 iflt (1, 1)
	20 dconst_1 (1, 1)
	21 dreturn (1, 1)
	22 aload_0 (0, 1)
	23 dload_1 (0, 1)
	24 invokespecial (0, 1)
	27 istore_3 (0, 1)
	28 aload_0 (0, 1)
	29 iload_3 (0, 1)
	30 invokespecial (0, 1)
	33 dstore (0, 1)
	35 aload_0 (0, 1)
	36 iload_3 (0, 1)
	37 invokespecial (0, 1)
	40 dstore (0, 1)
	42 aload_0 (0, 1)
	43 dload_1 (0, 1)
	44 invokespecial (0, 1)
	47 astore (0, 1)
	49 aload (1, 1)
	51 instanceof (1, 1)
	54 ifeq (1, 1)
	57 dload_1 (2, 1)
	58 aload (2, 1)
	60 invokeinterface (2, 1)
	65 dcmpg (2, 1)
	66 ifge (2, 1)
	69 dload (2, 1)
	71 dreturn (2, 1)
	72 dload (2, 2)
	74 dload (2, 2)
	76 dadd (2, 2)
	77 dreturn (2, 2)
	78 aload_0 (0, 1)
	79 invokevirtual (0, 1)
	82 astore (0, 1)
	84 aload_0 (0, 1)
	85 iload_3 (0, 1)
	86 invokespecial (0, 1)
	89 dstore (0, 1)
	91 iload_3 (0, 1)
	92 ifne (0, 1)
	95 aload_0 (0, 1)
	96 getfield (0, 1)
	99 goto (0, 1)
	102 aload (0, 1)
	104 iload_3 (0, 1)
	105 iconst_1 (0, 1)
	106 isub (0, 1)
	107 daload (0, 1)
	108 dstore (0, 1)
	110 aload (0, 1)
	112 dload_1 (0, 1)
	113 invokeinterface (0, 1)
	118 aload (0, 1)
	120 dload (0, 1)
	122 invokeinterface (0, 1)
	127 dsub (0, 1)
	128 dload (0, 1)
	130 ddiv (0, 1)
	131 dstore (0, 1)
	133 dload (0, 1)
	135 dload (0, 1)
	137 dload (0, 1)
	139 dmul (0, 1)
	140 dadd (0, 1)
	141 dreturn (0, 1)

Method: inverseCumulativeProbability
	0 dload_1 (1, 1)
	1 dconst_0 (1, 1)
	2 dcmpg (1, 1)
	3 iflt (1, 1)
	6 dload_1 (1, 1)
	7 dconst_1 (1, 1)
	8 dcmpl (1, 1)
	9 ifle (1, 1)
	12 new (1, 1)
	15 dup (1, 1)
	16 dload_1 (1, 1)
	17 invokestatic (1, 1)
	20 iconst_0 (1, 1)
	21 invokestatic (1, 1)
	24 iconst_1 (1, 1)
	25 invokestatic (1, 1)
	28 invokespecial (1, 1)
	31 athrow (1, 1)
	32 dload_1 (1, 1)
	33 dconst_0 (1, 1)
	34 dcmpl (1, 1)
	35 ifne (1, 1)
	38 aload_0 (1, 1)
	39 invokevirtual (1, 1)
	42 dreturn (1, 1)
	43 dload_1 (1, 1)
	44 dconst_1 (1, 1)
	45 dcmpl (1, 1)
	46 ifne (1, 1)
	49 aload_0 (1, 1)
	50 invokevirtual (1, 1)
	53 dreturn (1, 1)
	54 iconst_0 (0, 0)
	55 istore_3 (0, 0)
	56 aload_0 (1, 3)
	57 iload_3 (1, 3)
	58 invokespecial (1, 3)
	61 dload_1 (1, 3)
	62 dcmpg (1, 3)
	63 ifge (1, 3)
	66 iinc (1, 3)
	69 goto (1, 3)
	72 aload_0 (0, 0)
	73 aload_0 (0, 0)
	74 getfield (0, 0)
	77 iload_3 (0, 0)
	78 invokeinterface (0, 0)
	83 checkcast (0, 0)
	86 invokevirtual (0, 0)
	89 astore (0, 0)
	91 aload_0 (0, 0)
	92 iload_3 (0, 0)
	93 invokespecial (0, 0)
	96 dstore (0, 0)
	98 aload_0 (0, 0)
	99 invokevirtual (0, 0)
	102 astore (0, 0)
	104 iload_3 (0, 0)
	105 ifne (0, 0)
	108 aload_0 (0, 0)
	109 getfield (0, 0)
	112 goto (0, 0)
	115 aload (0, 0)
	117 iload_3 (0, 0)
	118 iconst_1 (0, 0)
	119 isub (0, 0)
	120 daload (0, 0)
	121 dstore (0, 0)
	123 aload (0, 0)
	125 dload (0, 0)
	127 invokeinterface (0, 0)
	132 dstore (0, 0)
	134 aload_0 (0, 0)
	135 iload_3 (0, 0)
	136 invokespecial (0, 0)
	139 dstore (0, 0)
	141 aload_0 (0, 0)
	142 iload_3 (0, 0)
	143 invokespecial (0, 0)
	146 dstore (0, 0)
	148 dload_1 (0, 0)
	149 dload (0, 0)
	151 dsub (0, 0)
	152 dstore (0, 0)
	154 dload (1, 1)
	156 dconst_0 (1, 1)
	157 dcmpg (1, 1)
	158 ifgt (1, 1)
	161 dload (1, 1)
	163 dreturn (1, 1)
	164 aload (0, 0)
	166 dload (0, 0)
	168 dload (0, 0)
	170 dload (0, 0)
	172 dmul (0, 0)
	173 dload (0, 0)
	175 ddiv (0, 0)
	176 dadd (0, 0)
	177 invokeinterface (0, 0)
	182 dreturn (0, 0)

Method: getNumericalMean
	0 aload_0 (0, 0)
	1 getfield (0, 0)
	4 invokevirtual (0, 0)
	7 dreturn (0, 0)

Method: getNumericalVariance
	0 aload_0 (0, 0)
	1 getfield (0, 0)
	4 invokevirtual (0, 0)
	7 dreturn (0, 0)

Method: getSupportLowerBound
	0 aload_0 (0, 0)
	1 getfield (0, 0)
	4 dreturn (0, 0)

Method: getSupportUpperBound
	0 aload_0 (0, 0)
	1 getfield (0, 0)
	4 dreturn (0, 0)

Method: isSupportLowerBoundInclusive
	0 iconst_1 (0, 0)
	1 ireturn (0, 0)

Method: isSupportUpperBoundInclusive
	0 iconst_1 (0, 0)
	1 ireturn (0, 0)

Method: isSupportConnected
	0 iconst_1 (0, 0)
	1 ireturn (0, 0)

Method: reseedRandomGenerator
	0 aload_0 (0, 0)
	1 getfield (0, 0)
	4 lload_1 (0, 0)
	5 invokevirtual (0, 0)
	8 return (0, 0)

Method: pB
	0 iload_1 (0, 0)
	1 ifne (0, 0)
	4 aload_0 (0, 0)
	5 getfield (0, 0)
	8 iconst_0 (0, 0)
	9 daload (0, 0)
	10 goto (0, 0)
	13 aload_0 (0, 0)
	14 getfield (0, 0)
	17 iload_1 (0, 0)
	18 daload (0, 0)
	19 aload_0 (0, 0)
	20 getfield (0, 0)
	23 iload_1 (0, 0)
	24 iconst_1 (0, 0)
	25 isub (0, 0)
	26 daload (0, 0)
	27 dsub (0, 0)
	28 dreturn (0, 0)

Method: pBminus
	0 iload_1 (0, 0)
	1 ifne (0, 0)
	4 dconst_0 (0, 0)
	5 goto (0, 0)
	8 aload_0 (0, 0)
	9 getfield (0, 0)
	12 iload_1 (0, 0)
	13 iconst_1 (0, 0)
	14 isub (0, 0)
	15 daload (0, 0)
	16 dreturn (0, 0)

Method: kB
	0 aload_0 (0, 0)
	1 invokevirtual (0, 0)
	4 astore_2 (0, 0)
	5 aload_0 (0, 0)
	6 aload_0 (0, 0)
	7 getfield (0, 0)
	10 iload_1 (0, 0)
	11 invokeinterface (0, 0)
	16 checkcast (0, 0)
	19 invokevirtual (0, 0)
	22 astore_3 (0, 0)
	23 iload_1 (0, 0)
	24 ifne (0, 0)
	27 aload_3 (0, 0)
	28 aload_0 (0, 0)
	29 getfield (0, 0)
	32 aload_2 (0, 0)
	33 iconst_0 (0, 0)
	34 daload (0, 0)
	35 invokeinterface (0, 0)
	40 goto (0, 0)
	43 aload_3 (0, 0)
	44 aload_2 (0, 0)
	45 iload_1 (0, 0)
	46 iconst_1 (0, 0)
	47 isub (0, 0)
	48 daload (0, 0)
	49 aload_2 (0, 0)
	50 iload_1 (0, 0)
	51 daload (0, 0)
	52 invokeinterface (0, 0)
	57 dreturn (0, 0)

Method: k
	0 aload_0 (0, 0)
	1 dload_1 (0, 0)
	2 invokespecial (0, 0)
	5 istore_3 (0, 0)
	6 aload_0 (0, 0)
	7 aload_0 (0, 0)
	8 getfield (0, 0)
	11 iload_3 (0, 0)
	12 invokeinterface (0, 0)
	17 checkcast (0, 0)
	20 invokevirtual (0, 0)
	23 areturn (0, 0)

Method: cumBinP
	0 aload_0 (0, 0)
	1 getfield (0, 0)
	4 iload_1 (0, 0)
	5 daload (0, 0)
	6 dreturn (0, 0)

Method: getKernel
	0 aload_1 (1, 1)
	1 invokevirtual (1, 1)
	4 lconst_1 (1, 1)
	5 lcmp (1, 1)
	6 ifeq (1, 1)
	9 aload_1 (1, 1)
	10 invokevirtual (1, 1)
	13 dconst_0 (1, 1)
	14 dcmpl (1, 1)
	15 ifne (1, 1)
	18 new (1, 1)
	21 dup (1, 1)
	22 aload_1 (1, 1)
	23 invokevirtual (1, 1)
	26 invokespecial (1, 1)
	29 areturn (1, 1)
	30 new (1, 2)
	33 dup (1, 2)
	34 aload_0 (1, 2)
	35 getfield (1, 2)
	38 invokevirtual (1, 2)
	41 aload_1 (1, 2)
	42 invokevirtual (1, 2)
	45 aload_1 (1, 2)
	46 invokevirtual (1, 2)
	49 ldc2_w (1, 2)
	52 invokespecial (1, 2)
	55 areturn (1, 2)

Method: access$100
	0 aload_0 (0, 0)
	1 dload_1 (0, 0)
	2 invokespecial (0, 0)
	5 ireturn (0, 0)

Method: access$200
	0 aload_0 (0, 0)
	1 getfield (0, 0)
	4 areturn (0, 0)

Method: access$302
	0 aload_0 (0, 0)
	1 aload_1 (0, 0)
	2 dup_x1 (0, 0)
	3 putfield (0, 0)
	6 areturn (0, 0)

Method: access$300
	0 aload_0 (0, 0)
	1 getfield (0, 0)
	4 areturn (0, 0)

