Method: <init>
	0 aload_0 (0, 0)
	1 aload_2 (0, 0)
	2 invokevirtual (0, 0)
	3 org/apache/commons/math3/random/RandomDataGenerator.getRandomGenerator:()Lorg/apache/commons/math3/random/RandomGenerator; (0, 0)
	5 invokespecial (0, 0)
	6 org/apache/commons/math3/distribution/AbstractRealDistribution.<init>:(Lorg/apache/commons/math3/random/RandomGenerator;)V (0, 0)
	8 aload_0 (0, 0)
	9 aconst_null (0, 0)
	10 putfield (0, 0)
	11 org/apache/commons/math3/random/EmpiricalDistribution.sampleStats:Lorg/apache/commons/math3/stat/descriptive/SummaryStatistics; (0, 0)
	13 aload_0 (0, 0)
	14 ldc2_w (0, 0)
	15 -inf (0, 0)
	17 putfield (0, 0)
	18 org/apache/commons/math3/random/EmpiricalDistribution.max:D (0, 0)
	20 aload_0 (0, 0)
	21 ldc2_w (0, 0)
	22 inf (0, 0)
	24 putfield (0, 0)
	25 org/apache/commons/math3/random/EmpiricalDistribution.min:D (0, 0)
	27 aload_0 (0, 0)
	28 dconst_0 (0, 0)
	29 putfield (0, 0)
	30 org/apache/commons/math3/random/EmpiricalDistribution.delta:D (0, 0)
	32 aload_0 (0, 0)
	33 iconst_0 (0, 0)
	34 putfield (0, 0)
	35 org/apache/commons/math3/random/EmpiricalDistribution.loaded:Z (0, 0)
	37 aload_0 (0, 0)
	38 aconst_null (0, 0)
	39 putfield (0, 0)
	40 org/apache/commons/math3/random/EmpiricalDistribution.upperBounds:[D (0, 0)
	42 iload_1 (2, 1)
	43 ifgt (2, 1)
	44 15 (2, 1)
	46 new (2, 1)
	47 org/apache/commons/math3/exception/NotStrictlyPositiveException (2, 1)
	49 dup (2, 1)
	50 iload_1 (2, 1)
	51 invokestatic (2, 1)
	52 java/lang/Integer.valueOf:(I)Ljava/lang/Integer; (2, 1)
	54 invokespecial (2, 1)
	55 org/apache/commons/math3/exception/NotStrictlyPositiveException.<init>:(Ljava/lang/Number;)V (2, 1)
	57 athrow (2, 1)
	58 aload_0 (0, 1)
	59 iload_1 (0, 1)
	60 putfield (0, 1)
	61 org/apache/commons/math3/random/EmpiricalDistribution.binCount:I (0, 1)
	63 aload_0 (0, 1)
	64 aload_2 (0, 1)
	65 putfield (0, 1)
	66 org/apache/commons/math3/random/EmpiricalDistribution.randomData:Lorg/apache/commons/math3/random/RandomDataGenerator; (0, 1)
	68 aload_0 (0, 1)
	69 new (0, 1)
	70 java/util/ArrayList (0, 1)
	72 dup (0, 1)
	73 invokespecial (0, 1)
	74 java/util/ArrayList.<init>:()V (0, 1)
	76 putfield (0, 1)
	77 org/apache/commons/math3/random/EmpiricalDistribution.binStats:Ljava/util/List; (0, 1)
	79 return (0, 1)

Method: load
	0 aload_1 (0, 0)
	1 invokestatic (0, 0)
	2 org/apache/commons/math3/util/MathUtils.checkNotNull:(Ljava/lang/Object;)V (0, 0)
	4 ldc (0, 4)
	5 US-ASCII (0, 4)
	6 invokestatic (0, 4)
	7 java/nio/charset/Charset.forName:(Ljava/lang/String;)Ljava/nio/charset/Charset; (0, 4)
	9 astore_2 (0, 4)
	10 new (0, 4)
	11 java/io/FileInputStream (0, 4)
	13 dup (0, 4)
	14 aload_1 (0, 4)
	15 invokespecial (0, 4)
	16 java/io/FileInputStream.<init>:(Ljava/io/File;)V (0, 4)
	18 astore_3 (0, 4)
	19 new (0, 4)
	20 java/io/BufferedReader (0, 4)
	22 dup (0, 4)
	23 new (0, 4)
	24 java/io/InputStreamReader (0, 4)
	26 dup (0, 4)
	27 aload_3 (0, 4)
	28 aload_2 (0, 4)
	29 invokespecial (0, 4)
	30 java/io/InputStreamReader.<init>:(Ljava/io/InputStream;Ljava/nio/charset/Charset;)V (0, 4)
	32 invokespecial (0, 4)
	33 java/io/BufferedReader.<init>:(Ljava/io/Reader;)V (0, 4)
	35 astore (0, 4)
	36 #4 (0, 4)
	37 new (0, 4)
	38 org/apache/commons/math3/random/EmpiricalDistribution$StreamDataAdapter (0, 4)
	40 dup (0, 4)
	41 aload_0 (0, 4)
	42 aload (0, 4)
	43 #4 (0, 4)
	44 invokespecial (0, 4)
	45 org/apache/commons/math3/random/EmpiricalDistribution$StreamDataAdapter.<init>:(Lorg/apache/commons/math3/random/EmpiricalDistribution;Ljava/io/BufferedReader;)V (0, 4)
	47 astore (0, 4)
	48 #5 (0, 4)
	49 aload (0, 4)
	50 #5 (0, 4)
	51 invokevirtual (0, 4)
	52 org/apache/commons/math3/random/EmpiricalDistribution$DataAdapter.computeStats:()V (0, 4)
	54 new (1, 4)
	55 java/io/FileInputStream (1, 4)
	57 dup (1, 4)
	58 aload_1 (1, 4)
	59 invokespecial (1, 4)
	60 java/io/FileInputStream.<init>:(Ljava/io/File;)V (1, 4)
	62 astore_3 (1, 4)
	63 new (1, 4)
	64 java/io/BufferedReader (1, 4)
	66 dup (1, 4)
	67 new (1, 4)
	68 java/io/InputStreamReader (1, 4)
	70 dup (1, 4)
	71 aload_3 (1, 4)
	72 aload_2 (1, 4)
	73 invokespecial (1, 4)
	74 java/io/InputStreamReader.<init>:(Ljava/io/InputStream;Ljava/nio/charset/Charset;)V (1, 4)
	76 invokespecial (1, 4)
	77 java/io/BufferedReader.<init>:(Ljava/io/Reader;)V (1, 4)
	79 astore (1, 4)
	80 #4 (1, 4)
	81 aload_0 (1, 4)
	82 new (1, 4)
	83 org/apache/commons/math3/random/EmpiricalDistribution$StreamDataAdapter (1, 4)
	85 dup (1, 4)
	86 aload_0 (1, 4)
	87 aload (1, 4)
	88 #4 (1, 4)
	89 invokespecial (1, 4)
	90 org/apache/commons/math3/random/EmpiricalDistribution$StreamDataAdapter.<init>:(Lorg/apache/commons/math3/random/EmpiricalDistribution;Ljava/io/BufferedReader;)V (1, 4)
	92 invokespecial (1, 4)
	93 org/apache/commons/math3/random/EmpiricalDistribution.fillBinStats:(Lorg/apache/commons/math3/random/EmpiricalDistribution$DataAdapter;)V (1, 4)
	95 aload_0 (1, 4)
	96 iconst_1 (1, 4)
	97 putfield (1, 4)
	98 org/apache/commons/math3/random/EmpiricalDistribution.loaded:Z (1, 4)
	100 aload (1, 4)
	101 #4 (1, 4)
	102 invokevirtual (1, 4)
	103 java/io/BufferedReader.close:()V (1, 4)
	105 goto (1, 4)
	106 23 (1, 4)
	108 astore (1, 4)
	109 #5 (1, 4)
	110 goto (0, 4)
	111 18 (0, 4)
	113 astore (0, 4)
	114 #6 (0, 4)
	115 aload (0, 4)
	116 #4 (0, 4)
	117 invokevirtual (0, 4)
	118 java/io/BufferedReader.close:()V (0, 4)
	120 goto (0, 4)
	121 5 (0, 4)
	123 astore (0, 4)
	124 #7 (0, 4)
	125 aload (0, 4)
	126 #6 (0, 4)
	127 athrow (0, 4)
	128 return (0, 4)

Method: fillBinStats
	0 aload_0 (0, 0)
	1 aload_0 (0, 0)
	2 getfield (0, 0)
	3 org/apache/commons/math3/random/EmpiricalDistribution.sampleStats:Lorg/apache/commons/math3/stat/descriptive/SummaryStatistics; (0, 0)
	5 invokevirtual (0, 0)
	6 org/apache/commons/math3/stat/descriptive/SummaryStatistics.getMin:()D (0, 0)
	8 putfield (0, 0)
	9 org/apache/commons/math3/random/EmpiricalDistribution.min:D (0, 0)
	11 aload_0 (0, 0)
	12 aload_0 (0, 0)
	13 getfield (0, 0)
	14 org/apache/commons/math3/random/EmpiricalDistribution.sampleStats:Lorg/apache/commons/math3/stat/descriptive/SummaryStatistics; (0, 0)
	16 invokevirtual (0, 0)
	17 org/apache/commons/math3/stat/descriptive/SummaryStatistics.getMax:()D (0, 0)
	19 putfield (0, 0)
	20 org/apache/commons/math3/random/EmpiricalDistribution.max:D (0, 0)
	22 aload_0 (0, 0)
	23 aload_0 (0, 0)
	24 getfield (0, 0)
	25 org/apache/commons/math3/random/EmpiricalDistribution.max:D (0, 0)
	27 aload_0 (0, 0)
	28 getfield (0, 0)
	29 org/apache/commons/math3/random/EmpiricalDistribution.min:D (0, 0)
	31 dsub (0, 0)
	32 aload_0 (0, 0)
	33 getfield (0, 0)
	34 org/apache/commons/math3/random/EmpiricalDistribution.binCount:I (0, 0)
	36 i2d (0, 0)
	37 ddiv (0, 0)
	38 putfield (0, 0)
	39 org/apache/commons/math3/random/EmpiricalDistribution.delta:D (0, 0)
	41 aload_0 (1, 1)
	42 getfield (1, 1)
	43 org/apache/commons/math3/random/EmpiricalDistribution.binStats:Ljava/util/List; (1, 1)
	45 invokeinterface (1, 1)
	46 java/util/List.clear:()V (1, 1)
	48 0 (1, 1)
	50 ifne (1, 1)
	51 12 (1, 1)
	53 aload_0 (1, 1)
	54 getfield (1, 1)
	55 org/apache/commons/math3/random/EmpiricalDistribution.binStats:Ljava/util/List; (1, 1)
	57 invokeinterface (1, 1)
	58 java/util/List.org/apache/commons/math3/stat/descriptive/SummaryStatistics (1, 1)
	60 0 (1, 1)
	62 iconst_0 (1, 4)
	63 istore_2 (1, 4)
	64 iload_2 (1, 4)
	65 aload_0 (1, 4)
	66 getfield (1, 4)
	67 org/apache/commons/math3/random/EmpiricalDistribution.binCount:I (1, 4)
	69 if_icmpge (1, 4)
	70 28 (1, 4)
	72 new (1, 4)
	73 org/apache/commons/math3/stat/descriptive/SummaryStatistics (1, 4)
	75 dup (1, 4)
	76 invokespecial (1, 4)
	77 org/apache/commons/math3/stat/descriptive/SummaryStatistics.<init>:()V (1, 4)
	79 astore_3 (1, 4)
	80 aload_0 (1, 4)
	81 getfield (1, 4)
	82 org/apache/commons/math3/random/EmpiricalDistribution.binStats:Ljava/util/List; (1, 4)
	84 iload_2 (1, 4)
	85 aload_3 (1, 4)
	86 invokeinterface (1, 4)
	87 java/util/List.computeBinStats:()V (1, 4)
	89 0 (1, 4)
	91 iinc (1, 4)
	92 #2 (1, 4)
	93 -89 (1, 4)
	94 goto (1, 4)
	95 -30 (1, 4)
	97 aload_1 (0, 0)
	98 invokevirtual (0, 0)
	99 org/apache/commons/math3/random/EmpiricalDistribution$DataAdapter.computeBinStats:()V (0, 0)
	101 aload_0 (0, 0)
	102 aload_0 (0, 0)
	103 getfield (0, 0)
	104 org/apache/commons/math3/random/EmpiricalDistribution.binCount:I (0, 0)
	106 newarray (0, 0)
	107 7 (0, 0)
	108 putfield (0, 0)
	109 org/apache/commons/math3/random/EmpiricalDistribution.upperBounds:[D (0, 0)
	111 aload_0 (0, 0)
	112 getfield (0, 0)
	113 org/apache/commons/math3/random/EmpiricalDistribution.upperBounds:[D (0, 0)
	115 iconst_0 (0, 0)
	116 aload_0 (0, 0)
	117 getfield (0, 0)
	118 org/apache/commons/math3/random/EmpiricalDistribution.binStats:Ljava/util/List; (0, 0)
	120 iconst_0 (0, 0)
	121 invokeinterface (0, 0)
	122 java/util/List.org/apache/commons/math3/util/FastMath (0, 0)
	124 0 (0, 0)
	126 checkcast (0, 0)
	127 org/apache/commons/math3/stat/descriptive/SummaryStatistics (0, 0)
	129 invokevirtual (0, 0)
	130 org/apache/commons/math3/stat/descriptive/SummaryStatistics.getN:()J (0, 0)
	132 l2d (0, 0)
	133 aload_0 (0, 0)
	134 getfield (0, 0)
	135 org/apache/commons/math3/random/EmpiricalDistribution.sampleStats:Lorg/apache/commons/math3/stat/descriptive/SummaryStatistics; (0, 0)
	137 invokevirtual (0, 0)
	138 org/apache/commons/math3/stat/descriptive/SummaryStatistics.getN:()J (0, 0)
	140 l2d (0, 0)
	141 ddiv (0, 0)
	142 dastore (0, 0)
	143 iconst_1 (1, 4)
	144 istore_2 (1, 4)
	145 iload_2 (1, 4)
	146 aload_0 (1, 4)
	147 getfield (1, 4)
	148 org/apache/commons/math3/random/EmpiricalDistribution.binCount:I (1, 4)
	150 iconst_1 (1, 4)
	151 isub (1, 4)
	152 if_icmpge (1, 4)
	153 50 (1, 4)
	155 aload_0 (1, 4)
	156 getfield (1, 4)
	157 org/apache/commons/math3/random/EmpiricalDistribution.upperBounds:[D (1, 4)
	159 iload_2 (1, 4)
	160 aload_0 (1, 4)
	161 getfield (1, 4)
	162 org/apache/commons/math3/random/EmpiricalDistribution.upperBounds:[D (1, 4)
	164 iload_2 (1, 4)
	165 iconst_1 (1, 4)
	166 isub (1, 4)
	167 daload (1, 4)
	168 aload_0 (1, 4)
	169 getfield (1, 4)
	170 org/apache/commons/math3/random/EmpiricalDistribution.binStats:Ljava/util/List; (1, 4)
	172 iload_2 (1, 4)
	173 invokeinterface (1, 4)
	174 java/util/List.org/apache/commons/math3/util/FastMath (1, 4)
	176 0 (1, 4)
	178 checkcast (1, 4)
	179 org/apache/commons/math3/stat/descriptive/SummaryStatistics (1, 4)
	181 invokevirtual (1, 4)
	182 org/apache/commons/math3/stat/descriptive/SummaryStatistics.getN:()J (1, 4)
	184 l2d (1, 4)
	185 aload_0 (1, 4)
	186 getfield (1, 4)
	187 org/apache/commons/math3/random/EmpiricalDistribution.sampleStats:Lorg/apache/commons/math3/stat/descriptive/SummaryStatistics; (1, 4)
	189 invokevirtual (1, 4)
	190 org/apache/commons/math3/stat/descriptive/SummaryStatistics.getN:()J (1, 4)
	192 l2d (1, 4)
	193 ddiv (1, 4)
	194 dadd (1, 4)
	195 dastore (1, 4)
	196 iinc (1, 4)
	197 #2 (1, 4)
	198 -89 (1, 4)
	199 goto (1, 4)
	200 -54 (1, 4)
	202 aload_0 (0, 0)
	203 getfield (0, 0)
	204 org/apache/commons/math3/random/EmpiricalDistribution.upperBounds:[D (0, 0)
	206 aload_0 (0, 0)
	207 getfield (0, 0)
	208 org/apache/commons/math3/random/EmpiricalDistribution.binCount:I (0, 0)
	210 iconst_1 (0, 0)
	211 isub (0, 0)
	212 dconst_1 (0, 0)
	213 dastore (0, 0)
	214 return (0, 0)

Method: findBin
	0 dload_1 (0, 0)
	1 aload_0 (0, 0)
	2 getfield (0, 0)
	3 org/apache/commons/math3/random/EmpiricalDistribution.min:D (0, 0)
	5 dsub (0, 0)
	6 aload_0 (0, 0)
	7 getfield (0, 0)
	8 org/apache/commons/math3/random/EmpiricalDistribution.delta:D (0, 0)
	10 ddiv (0, 0)
	11 invokestatic (0, 0)
	12 org/apache/commons/math3/util/FastMath.ceil:(D)D (0, 0)
	14 d2i (0, 0)
	15 iconst_1 (0, 0)
	16 isub (0, 0)
	17 iconst_0 (0, 0)
	18 invokestatic (0, 0)
	19 org/apache/commons/math3/util/FastMath.max:(II)I (0, 0)
	21 aload_0 (0, 0)
	22 getfield (0, 0)
	23 org/apache/commons/math3/random/EmpiricalDistribution.binCount:I (0, 0)
	25 iconst_1 (0, 0)
	26 isub (0, 0)
	27 invokestatic (0, 0)
	28 org/apache/commons/math3/util/FastMath.min:(II)I (0, 0)
	30 ireturn (0, 0)

Method: getNextValue
	0 aload_0 (1, 1)
	1 getfield (1, 1)
	2 org/apache/commons/math3/random/EmpiricalDistribution.loaded:Z (1, 1)
	4 ifne (1, 1)
	5 18 (1, 1)
	7 new (1, 1)
	8 org/apache/commons/math3/exception/MathIllegalStateException (1, 1)
	10 dup (1, 1)
	11 getstatic (1, 1)
	12 org/apache/commons/math3/exception/util/LocalizedFormats.DISTRIBUTION_NOT_LOADED:Lorg/apache/commons/math3/exception/util/LocalizedFormats; (1, 1)
	14 iconst_0 (1, 1)
	15 anewarray (1, 1)
	16 java/lang/Object (1, 1)
	18 invokespecial (1, 1)
	19 org/apache/commons/math3/exception/MathIllegalStateException.<init>:(Lorg/apache/commons/math3/exception/util/Localizable;[Ljava/lang/Object;)V (1, 1)
	21 athrow (1, 1)
	22 aload_0 (0, 0)
	23 invokevirtual (0, 0)
	24 org/apache/commons/math3/random/EmpiricalDistribution.sample:()D (0, 0)
	26 dreturn (0, 0)

Method: getSampleStats
	0 aload_0 (0, 0)
	1 getfield (0, 0)
	2 org/apache/commons/math3/random/EmpiricalDistribution.sampleStats:Lorg/apache/commons/math3/stat/descriptive/SummaryStatistics; (0, 0)
	4 areturn (0, 0)

Method: getBinCount
	0 aload_0 (0, 0)
	1 getfield (0, 0)
	2 org/apache/commons/math3/random/EmpiricalDistribution.binCount:I (0, 0)
	4 ireturn (0, 0)

Method: getBinStats
	0 aload_0 (0, 0)
	1 getfield (0, 0)
	2 org/apache/commons/math3/random/EmpiricalDistribution.binStats:Ljava/util/List; (0, 0)
	4 areturn (0, 0)

Method: getUpperBounds
	0 aload_0 (0, 0)
	1 getfield (0, 0)
	2 org/apache/commons/math3/random/EmpiricalDistribution.binCount:I (0, 0)
	4 newarray (0, 0)
	5 7 (0, 0)
	6 astore_1 (0, 0)
	7 iconst_0 (1, 4)
	8 istore_2 (1, 4)
	9 iload_2 (1, 4)
	10 aload_0 (1, 4)
	11 getfield (1, 4)
	12 org/apache/commons/math3/random/EmpiricalDistribution.binCount:I (1, 4)
	14 iconst_1 (1, 4)
	15 isub (1, 4)
	16 if_icmpge (1, 4)
	17 26 (1, 4)
	19 aload_1 (1, 4)
	20 iload_2 (1, 4)
	21 aload_0 (1, 4)
	22 getfield (1, 4)
	23 org/apache/commons/math3/random/EmpiricalDistribution.min:D (1, 4)
	25 aload_0 (1, 4)
	26 getfield (1, 4)
	27 org/apache/commons/math3/random/EmpiricalDistribution.delta:D (1, 4)
	29 iload_2 (1, 4)
	30 iconst_1 (1, 4)
	31 iadd (1, 4)
	32 i2d (1, 4)
	33 dmul (1, 4)
	34 dadd (1, 4)
	35 dastore (1, 4)
	36 iinc (1, 4)
	37 #2 (1, 4)
	38 -89 (1, 4)
	39 goto (1, 4)
	40 -30 (1, 4)
	42 aload_1 (0, 0)
	43 aload_0 (0, 0)
	44 getfield (0, 0)
	45 org/apache/commons/math3/random/EmpiricalDistribution.binCount:I (0, 0)
	47 iconst_1 (0, 0)
	48 isub (0, 0)
	49 aload_0 (0, 0)
	50 getfield (0, 0)
	51 org/apache/commons/math3/random/EmpiricalDistribution.max:D (0, 0)
	53 dastore (0, 0)
	54 aload_1 (0, 0)
	55 areturn (0, 0)

Method: getGeneratorUpperBounds
	0 aload_0 (0, 0)
	1 getfield (0, 0)
	2 org/apache/commons/math3/random/EmpiricalDistribution.upperBounds:[D (0, 0)
	4 arraylength (0, 0)
	5 istore_1 (0, 0)
	6 iload_1 (0, 0)
	7 newarray (0, 0)
	8 7 (0, 0)
	9 astore_2 (0, 0)
	10 aload_0 (0, 0)
	11 getfield (0, 0)
	12 org/apache/commons/math3/random/EmpiricalDistribution.upperBounds:[D (0, 0)
	14 iconst_0 (0, 0)
	15 aload_2 (0, 0)
	16 iconst_0 (0, 0)
	17 iload_1 (0, 0)
	18 invokestatic (0, 0)
	19 java/lang/System.arraycopy:(Ljava/lang/Object;ILjava/lang/Object;II)V (0, 0)
	21 aload_2 (0, 0)
	22 areturn (0, 0)

Method: isLoaded
	0 aload_0 (0, 0)
	1 getfield (0, 0)
	2 org/apache/commons/math3/random/EmpiricalDistribution.loaded:Z (0, 0)
	4 ireturn (0, 0)

Method: reSeed
	0 aload_0 (0, 0)
	1 getfield (0, 0)
	2 org/apache/commons/math3/random/EmpiricalDistribution.randomData:Lorg/apache/commons/math3/random/RandomDataGenerator; (0, 0)
	4 lload_1 (0, 0)
	5 invokevirtual (0, 0)
	6 org/apache/commons/math3/random/RandomDataGenerator.reSeed:(J)V (0, 0)
	8 return (0, 0)

Method: probability
	0 dconst_0 (0, 0)
	1 dreturn (0, 0)

Method: density
	0 dload_1 (1, 1)
	1 aload_0 (1, 1)
	2 getfield (1, 1)
	3 org/apache/commons/math3/random/EmpiricalDistribution.min:D (1, 1)
	5 dcmpg (1, 1)
	6 iflt (1, 1)
	7 12 (1, 1)
	9 dload_1 (1, 1)
	10 aload_0 (1, 1)
	11 getfield (1, 1)
	12 org/apache/commons/math3/random/EmpiricalDistribution.max:D (1, 1)
	14 dcmpl (1, 1)
	15 ifle (1, 1)
	16 5 (1, 1)
	18 dconst_0 (1, 1)
	19 dreturn (1, 1)
	20 aload_0 (0, 0)
	21 dload_1 (0, 0)
	22 invokespecial (0, 0)
	23 org/apache/commons/math3/random/EmpiricalDistribution.findBin:(D)I (0, 0)
	25 istore_3 (0, 0)
	26 aload_0 (0, 0)
	27 aload_0 (0, 0)
	28 getfield (0, 0)
	29 org/apache/commons/math3/random/EmpiricalDistribution.binStats:Ljava/util/List; (0, 0)
	31 iload_3 (0, 0)
	32 invokeinterface (0, 0)
	33 java/util/List.org/apache/commons/math3/util/FastMath (0, 0)
	35 0 (0, 0)
	37 checkcast (0, 0)
	38 org/apache/commons/math3/stat/descriptive/SummaryStatistics (0, 0)
	40 invokevirtual (0, 0)
	41 org/apache/commons/math3/random/EmpiricalDistribution.getKernel:(Lorg/apache/commons/math3/stat/descriptive/SummaryStatistics;)Lorg/apache/commons/math3/distribution/RealDistribution; (0, 0)
	43 astore (0, 0)
	44 #4 (0, 0)
	45 aload (0, 0)
	46 #4 (0, 0)
	47 dload_1 (0, 0)
	48 invokeinterface (0, 0)
	49 org/apache/commons/math3/distribution/RealDistribution.pB:(I)D (0, 0)
	51 0 (0, 0)
	53 aload_0 (0, 0)
	54 iload_3 (0, 0)
	55 invokespecial (0, 0)
	56 org/apache/commons/math3/random/EmpiricalDistribution.pB:(I)D (0, 0)
	58 dmul (0, 0)
	59 aload_0 (0, 0)
	60 iload_3 (0, 0)
	61 invokespecial (0, 0)
	62 org/apache/commons/math3/random/EmpiricalDistribution.kB:(I)D (0, 0)
	64 ddiv (0, 0)
	65 dreturn (0, 0)

Method: cumulativeProbability
	0 dload_1 (1, 1)
	1 aload_0 (1, 1)
	2 getfield (1, 1)
	3 org/apache/commons/math3/random/EmpiricalDistribution.min:D (1, 1)
	5 dcmpg (1, 1)
	6 ifge (1, 1)
	7 5 (1, 1)
	9 dconst_0 (1, 1)
	10 dreturn (1, 1)
	11 dload_1 (1, 1)
	12 aload_0 (1, 1)
	13 getfield (1, 1)
	14 org/apache/commons/math3/random/EmpiricalDistribution.max:D (1, 1)
	16 dcmpl (1, 1)
	17 iflt (1, 1)
	18 5 (1, 1)
	20 dconst_1 (1, 1)
	21 dreturn (1, 1)
	22 aload_0 (0, 0)
	23 dload_1 (0, 0)
	24 invokespecial (0, 0)
	25 org/apache/commons/math3/random/EmpiricalDistribution.findBin:(D)I (0, 0)
	27 istore_3 (0, 0)
	28 aload_0 (0, 0)
	29 iload_3 (0, 0)
	30 invokespecial (0, 0)
	31 org/apache/commons/math3/random/EmpiricalDistribution.pBminus:(I)D (0, 0)
	33 dstore (0, 0)
	34 #4 (0, 0)
	35 aload_0 (0, 0)
	36 iload_3 (0, 0)
	37 invokespecial (0, 0)
	38 org/apache/commons/math3/random/EmpiricalDistribution.pB:(I)D (0, 0)
	40 dstore (0, 0)
	41 #6 (0, 0)
	42 aload_0 (0, 0)
	43 dload_1 (0, 0)
	44 invokespecial (0, 0)
	45 org/apache/commons/math3/random/EmpiricalDistribution.k:(D)Lorg/apache/commons/math3/distribution/RealDistribution; (0, 0)
	47 astore (0, 0)
	48 #8 (0, 0)
	49 aload (1, 1)
	50 #8 (1, 1)
	51 instanceof (1, 1)
	52 org/apache/commons/math3/distribution/ConstantRealDistribution (1, 1)
	54 ifeq (1, 1)
	55 24 (1, 1)
	57 dload_1 (2, 1)
	58 aload (2, 1)
	59 #8 (2, 1)
	60 invokeinterface (2, 1)
	61 org/apache/commons/math3/distribution/RealDistribution.getUpperBounds:()[D (2, 1)
	63 0 (2, 1)
	65 dcmpg (2, 1)
	66 ifge (2, 1)
	67 6 (2, 1)
	69 dload (2, 1)
	70 #4 (2, 1)
	71 dreturn (2, 1)
	72 dload (2, 2)
	73 #4 (2, 2)
	74 dload (2, 2)
	75 #6 (2, 2)
	76 dadd (2, 2)
	77 dreturn (2, 2)
	78 aload_0 (0, 0)
	79 invokevirtual (0, 0)
	80 org/apache/commons/math3/random/EmpiricalDistribution.getUpperBounds:()[D (0, 0)
	82 astore (0, 0)
	83 #9 (0, 0)
	84 aload_0 (0, 0)
	85 iload_3 (0, 0)
	86 invokespecial (0, 0)
	87 org/apache/commons/math3/random/EmpiricalDistribution.kB:(I)D (0, 0)
	89 dstore (0, 0)
	90 #10 (0, 0)
	91 iload_3 (0, 0)
	92 ifne (0, 0)
	93 10 (0, 0)
	95 aload_0 (0, 0)
	96 getfield (0, 0)
	97 org/apache/commons/math3/random/EmpiricalDistribution.min:D (0, 0)
	99 goto (0, 0)
	100 9 (0, 0)
	102 aload (0, 0)
	103 #9 (0, 0)
	104 iload_3 (0, 0)
	105 iconst_1 (0, 0)
	106 isub (0, 0)
	107 daload (0, 0)
	108 dstore (0, 0)
	109 #12 (0, 0)
	110 aload (0, 0)
	111 #8 (0, 0)
	112 dload_1 (0, 0)
	113 invokeinterface (0, 0)
	114 org/apache/commons/math3/distribution/RealDistribution.org/apache/commons/math3/exception/OutOfRangeException (0, 0)
	116 0 (0, 0)
	118 aload (0, 0)
	119 #8 (0, 0)
	120 dload (0, 0)
	121 #12 (0, 0)
	122 invokeinterface (0, 0)
	123 org/apache/commons/math3/distribution/RealDistribution.org/apache/commons/math3/exception/OutOfRangeException (0, 0)
	125 0 (0, 0)
	127 dsub (0, 0)
	128 dload (0, 0)
	129 #10 (0, 0)
	130 ddiv (0, 0)
	131 dstore (0, 0)
	132 #14 (0, 0)
	133 dload (0, 0)
	134 #4 (0, 0)
	135 dload (0, 0)
	136 #6 (0, 0)
	137 dload (0, 0)
	138 #14 (0, 0)
	139 dmul (0, 0)
	140 dadd (0, 0)
	141 dreturn (0, 0)

Method: inverseCumulativeProbability
	0 dload_1 (1, 1)
	1 dconst_0 (1, 1)
	2 dcmpg (1, 1)
	3 iflt (1, 1)
	4 9 (1, 1)
	6 dload_1 (1, 1)
	7 dconst_1 (1, 1)
	8 dcmpl (1, 1)
	9 ifle (1, 1)
	10 23 (1, 1)
	12 new (1, 1)
	13 org/apache/commons/math3/exception/OutOfRangeException (1, 1)
	15 dup (1, 1)
	16 dload_1 (1, 1)
	17 invokestatic (1, 1)
	18 java/lang/Double.valueOf:(D)Ljava/lang/Double; (1, 1)
	20 iconst_0 (1, 1)
	21 invokestatic (1, 1)
	22 java/lang/Integer.valueOf:(I)Ljava/lang/Integer; (1, 1)
	24 iconst_1 (1, 1)
	25 invokestatic (1, 1)
	26 java/lang/Integer.valueOf:(I)Ljava/lang/Integer; (1, 1)
	28 invokespecial (1, 1)
	29 org/apache/commons/math3/exception/OutOfRangeException.<init>:(Ljava/lang/Number;Ljava/lang/Number;Ljava/lang/Number;)V (1, 1)
	31 athrow (1, 1)
	32 dload_1 (1, 1)
	33 dconst_0 (1, 1)
	34 dcmpl (1, 1)
	35 ifne (1, 1)
	36 8 (1, 1)
	38 aload_0 (1, 1)
	39 invokevirtual (1, 1)
	40 org/apache/commons/math3/random/EmpiricalDistribution.getSupportLowerBound:()D (1, 1)
	42 dreturn (1, 1)
	43 dload_1 (1, 1)
	44 dconst_1 (1, 1)
	45 dcmpl (1, 1)
	46 ifne (1, 1)
	47 8 (1, 1)
	49 aload_0 (1, 1)
	50 invokevirtual (1, 1)
	51 org/apache/commons/math3/random/EmpiricalDistribution.getSupportUpperBound:()D (1, 1)
	53 dreturn (1, 1)
	54 iconst_0 (0, 0)
	55 istore_3 (0, 0)
	56 aload_0 (1, 3)
	57 iload_3 (1, 3)
	58 invokespecial (1, 3)
	59 org/apache/commons/math3/random/EmpiricalDistribution.cumBinP:(I)D (1, 3)
	61 dload_1 (1, 3)
	62 dcmpg (1, 3)
	63 ifge (1, 3)
	64 9 (1, 3)
	66 iinc (1, 3)
	67 #3 (1, 3)
	68 -89 (1, 3)
	69 goto (1, 3)
	70 -13 (1, 3)
	72 aload_0 (0, 0)
	73 aload_0 (0, 0)
	74 getfield (0, 0)
	75 org/apache/commons/math3/random/EmpiricalDistribution.binStats:Ljava/util/List; (0, 0)
	77 iload_3 (0, 0)
	78 invokeinterface (0, 0)
	79 java/util/List.org/apache/commons/math3/util/FastMath (0, 0)
	81 0 (0, 0)
	83 checkcast (0, 0)
	84 org/apache/commons/math3/stat/descriptive/SummaryStatistics (0, 0)
	86 invokevirtual (0, 0)
	87 org/apache/commons/math3/random/EmpiricalDistribution.getKernel:(Lorg/apache/commons/math3/stat/descriptive/SummaryStatistics;)Lorg/apache/commons/math3/distribution/RealDistribution; (0, 0)
	89 astore (0, 0)
	90 #4 (0, 0)
	91 aload_0 (0, 0)
	92 iload_3 (0, 0)
	93 invokespecial (0, 0)
	94 org/apache/commons/math3/random/EmpiricalDistribution.kB:(I)D (0, 0)
	96 dstore (0, 0)
	97 #5 (0, 0)
	98 aload_0 (0, 0)
	99 invokevirtual (0, 0)
	100 org/apache/commons/math3/random/EmpiricalDistribution.getUpperBounds:()[D (0, 0)
	102 astore (0, 0)
	103 #7 (0, 0)
	104 iload_3 (0, 0)
	105 ifne (0, 0)
	106 10 (0, 0)
	108 aload_0 (0, 0)
	109 getfield (0, 0)
	110 org/apache/commons/math3/random/EmpiricalDistribution.min:D (0, 0)
	112 goto (0, 0)
	113 9 (0, 0)
	115 aload (0, 0)
	116 #7 (0, 0)
	117 iload_3 (0, 0)
	118 iconst_1 (0, 0)
	119 isub (0, 0)
	120 daload (0, 0)
	121 dstore (0, 0)
	122 #8 (0, 0)
	123 aload (0, 0)
	124 #4 (0, 0)
	125 dload (0, 0)
	126 #8 (0, 0)
	127 invokeinterface (0, 0)
	128 org/apache/commons/math3/distribution/RealDistribution.org/apache/commons/math3/exception/OutOfRangeException (0, 0)
	130 0 (0, 0)
	132 dstore (0, 0)
	133 #10 (0, 0)
	134 aload_0 (0, 0)
	135 iload_3 (0, 0)
	136 invokespecial (0, 0)
	137 org/apache/commons/math3/random/EmpiricalDistribution.pB:(I)D (0, 0)
	139 dstore (0, 0)
	140 #12 (0, 0)
	141 aload_0 (0, 0)
	142 iload_3 (0, 0)
	143 invokespecial (0, 0)
	144 org/apache/commons/math3/random/EmpiricalDistribution.pBminus:(I)D (0, 0)
	146 dstore (0, 0)
	147 #14 (0, 0)
	148 dload_1 (0, 0)
	149 dload (0, 0)
	150 #14 (0, 0)
	151 dsub (0, 0)
	152 dstore (0, 0)
	153 #16 (0, 0)
	154 dload (1, 1)
	155 #16 (1, 1)
	156 dconst_0 (1, 1)
	157 dcmpg (1, 1)
	158 ifgt (1, 1)
	159 6 (1, 1)
	161 dload (1, 1)
	162 #8 (1, 1)
	163 dreturn (1, 1)
	164 aload (0, 0)
	165 #4 (0, 0)
	166 dload (0, 0)
	167 #10 (0, 0)
	168 dload (0, 0)
	169 #16 (0, 0)
	170 dload (0, 0)
	171 #5 (0, 0)
	172 dmul (0, 0)
	173 dload (0, 0)
	174 #12 (0, 0)
	175 ddiv (0, 0)
	176 dadd (0, 0)
	177 invokeinterface (0, 0)
	178 org/apache/commons/math3/distribution/RealDistribution.getMean:()D (0, 0)
	180 0 (0, 0)
	182 dreturn (0, 0)

Method: getNumericalMean
	0 aload_0 (0, 0)
	1 getfield (0, 0)
	2 org/apache/commons/math3/random/EmpiricalDistribution.sampleStats:Lorg/apache/commons/math3/stat/descriptive/SummaryStatistics; (0, 0)
	4 invokevirtual (0, 0)
	5 org/apache/commons/math3/stat/descriptive/SummaryStatistics.getMean:()D (0, 0)
	7 dreturn (0, 0)

Method: getNumericalVariance
	0 aload_0 (0, 0)
	1 getfield (0, 0)
	2 org/apache/commons/math3/random/EmpiricalDistribution.sampleStats:Lorg/apache/commons/math3/stat/descriptive/SummaryStatistics; (0, 0)
	4 invokevirtual (0, 0)
	5 org/apache/commons/math3/stat/descriptive/SummaryStatistics.getVariance:()D (0, 0)
	7 dreturn (0, 0)

Method: getSupportLowerBound
	0 aload_0 (0, 0)
	1 getfield (0, 0)
	2 org/apache/commons/math3/random/EmpiricalDistribution.min:D (0, 0)
	4 dreturn (0, 0)

Method: getSupportUpperBound
	0 aload_0 (0, 0)
	1 getfield (0, 0)
	2 org/apache/commons/math3/random/EmpiricalDistribution.max:D (0, 0)
	4 dreturn (0, 0)

Method: isSupportLowerBoundInclusive
	0 iconst_1 (0, 0)
	1 ireturn (0, 0)

Method: isSupportUpperBoundInclusive
	0 iconst_1 (0, 0)
	1 ireturn (0, 0)

Method: isSupportConnected
	0 iconst_1 (0, 0)
	1 ireturn (0, 0)

Method: reseedRandomGenerator
	0 aload_0 (0, 0)
	1 getfield (0, 0)
	2 org/apache/commons/math3/random/EmpiricalDistribution.randomData:Lorg/apache/commons/math3/random/RandomDataGenerator; (0, 0)
	4 lload_1 (0, 0)
	5 invokevirtual (0, 0)
	6 org/apache/commons/math3/random/RandomDataGenerator.reSeed:(J)V (0, 0)
	8 return (0, 0)

Method: pB
	0 iload_1 (0, 0)
	1 ifne (0, 0)
	2 12 (0, 0)
	4 aload_0 (0, 0)
	5 getfield (0, 0)
	6 org/apache/commons/math3/random/EmpiricalDistribution.upperBounds:[D (0, 0)
	8 iconst_0 (0, 0)
	9 daload (0, 0)
	10 goto (0, 0)
	11 18 (0, 0)
	13 aload_0 (0, 0)
	14 getfield (0, 0)
	15 org/apache/commons/math3/random/EmpiricalDistribution.upperBounds:[D (0, 0)
	17 iload_1 (0, 0)
	18 daload (0, 0)
	19 aload_0 (0, 0)
	20 getfield (0, 0)
	21 org/apache/commons/math3/random/EmpiricalDistribution.upperBounds:[D (0, 0)
	23 iload_1 (0, 0)
	24 iconst_1 (0, 0)
	25 isub (0, 0)
	26 daload (0, 0)
	27 dsub (0, 0)
	28 dreturn (0, 0)

Method: pBminus
	0 iload_1 (0, 0)
	1 ifne (0, 0)
	2 7 (0, 0)
	4 dconst_0 (0, 0)
	5 goto (0, 0)
	6 11 (0, 0)
	8 aload_0 (0, 0)
	9 getfield (0, 0)
	10 org/apache/commons/math3/random/EmpiricalDistribution.upperBounds:[D (0, 0)
	12 iload_1 (0, 0)
	13 iconst_1 (0, 0)
	14 isub (0, 0)
	15 daload (0, 0)
	16 dreturn (0, 0)

Method: kB
	0 aload_0 (0, 0)
	1 invokevirtual (0, 0)
	2 org/apache/commons/math3/random/EmpiricalDistribution.getUpperBounds:()[D (0, 0)
	4 astore_2 (0, 0)
	5 aload_0 (0, 0)
	6 aload_0 (0, 0)
	7 getfield (0, 0)
	8 org/apache/commons/math3/random/EmpiricalDistribution.binStats:Ljava/util/List; (0, 0)
	10 iload_1 (0, 0)
	11 invokeinterface (0, 0)
	12 java/util/List.org/apache/commons/math3/util/FastMath (0, 0)
	14 0 (0, 0)
	16 checkcast (0, 0)
	17 org/apache/commons/math3/stat/descriptive/SummaryStatistics (0, 0)
	19 invokevirtual (0, 0)
	20 org/apache/commons/math3/random/EmpiricalDistribution.getKernel:(Lorg/apache/commons/math3/stat/descriptive/SummaryStatistics;)Lorg/apache/commons/math3/distribution/RealDistribution; (0, 0)
	22 astore_3 (0, 0)
	23 iload_1 (0, 0)
	24 ifne (0, 0)
	25 19 (0, 0)
	27 aload_3 (0, 0)
	28 aload_0 (0, 0)
	29 getfield (0, 0)
	30 org/apache/commons/math3/random/EmpiricalDistribution.min:D (0, 0)
	32 aload_2 (0, 0)
	33 iconst_0 (0, 0)
	34 daload (0, 0)
	35 invokeinterface (0, 0)
	36 org/apache/commons/math3/distribution/RealDistribution.<init>:(D)V (0, 0)
	38 0 (0, 0)
	40 goto (0, 0)
	41 17 (0, 0)
	43 aload_3 (0, 0)
	44 aload_2 (0, 0)
	45 iload_1 (0, 0)
	46 iconst_1 (0, 0)
	47 isub (0, 0)
	48 daload (0, 0)
	49 aload_2 (0, 0)
	50 iload_1 (0, 0)
	51 daload (0, 0)
	52 invokeinterface (0, 0)
	53 org/apache/commons/math3/distribution/RealDistribution.<init>:(D)V (0, 0)
	55 0 (0, 0)
	57 dreturn (0, 0)

Method: k
	0 aload_0 (0, 0)
	1 dload_1 (0, 0)
	2 invokespecial (0, 0)
	3 org/apache/commons/math3/random/EmpiricalDistribution.findBin:(D)I (0, 0)
	5 istore_3 (0, 0)
	6 aload_0 (0, 0)
	7 aload_0 (0, 0)
	8 getfield (0, 0)
	9 org/apache/commons/math3/random/EmpiricalDistribution.binStats:Ljava/util/List; (0, 0)
	11 iload_3 (0, 0)
	12 invokeinterface (0, 0)
	13 java/util/List.org/apache/commons/math3/util/FastMath (0, 0)
	15 0 (0, 0)
	17 checkcast (0, 0)
	18 org/apache/commons/math3/stat/descriptive/SummaryStatistics (0, 0)
	20 invokevirtual (0, 0)
	21 org/apache/commons/math3/random/EmpiricalDistribution.getKernel:(Lorg/apache/commons/math3/stat/descriptive/SummaryStatistics;)Lorg/apache/commons/math3/distribution/RealDistribution; (0, 0)
	23 areturn (0, 0)

Method: cumBinP
	0 aload_0 (0, 0)
	1 getfield (0, 0)
	2 org/apache/commons/math3/random/EmpiricalDistribution.upperBounds:[D (0, 0)
	4 iload_1 (0, 0)
	5 daload (0, 0)
	6 dreturn (0, 0)

Method: getKernel
	0 aload_1 (1, 1)
	1 invokevirtual (1, 1)
	2 org/apache/commons/math3/stat/descriptive/SummaryStatistics.getN:()J (1, 1)
	4 lconst_1 (1, 1)
	5 lcmp (1, 1)
	6 ifeq (1, 1)
	7 12 (1, 1)
	9 aload_1 (1, 1)
	10 invokevirtual (1, 1)
	11 org/apache/commons/math3/stat/descriptive/SummaryStatistics.getVariance:()D (1, 1)
	13 dconst_0 (1, 1)
	14 dcmpl (1, 1)
	15 ifne (1, 1)
	16 15 (1, 1)
	18 new (1, 1)
	19 org/apache/commons/math3/distribution/ConstantRealDistribution (1, 1)
	21 dup (1, 1)
	22 aload_1 (1, 1)
	23 invokevirtual (1, 1)
	24 org/apache/commons/math3/stat/descriptive/SummaryStatistics.getMean:()D (1, 1)
	26 invokespecial (1, 1)
	27 org/apache/commons/math3/distribution/ConstantRealDistribution.<init>:(D)V (1, 1)
	29 areturn (1, 1)
	30 new (1, 2)
	31 org/apache/commons/math3/distribution/NormalDistribution (1, 2)
	33 dup (1, 2)
	34 aload_0 (1, 2)
	35 getfield (1, 2)
	36 org/apache/commons/math3/random/EmpiricalDistribution.randomData:Lorg/apache/commons/math3/random/RandomDataGenerator; (1, 2)
	38 invokevirtual (1, 2)
	39 org/apache/commons/math3/random/RandomDataGenerator.getRandomGenerator:()Lorg/apache/commons/math3/random/RandomGenerator; (1, 2)
	41 aload_1 (1, 2)
	42 invokevirtual (1, 2)
	43 org/apache/commons/math3/stat/descriptive/SummaryStatistics.getMean:()D (1, 2)
	45 aload_1 (1, 2)
	46 invokevirtual (1, 2)
	47 org/apache/commons/math3/stat/descriptive/SummaryStatistics.getStandardDeviation:()D (1, 2)
	49 ldc2_w (1, 2)
	50 1e-09 (1, 2)
	52 invokespecial (1, 2)
	53 org/apache/commons/math3/distribution/NormalDistribution.<init>:(Lorg/apache/commons/math3/random/RandomGenerator;DDD)V (1, 2)
	55 areturn (1, 2)

Method: access$100
	0 aload_0 (0, 0)
	1 dload_1 (0, 0)
	2 invokespecial (0, 0)
	3 org/apache/commons/math3/random/EmpiricalDistribution.findBin:(D)I (0, 0)
	5 ireturn (0, 0)

Method: access$200
	0 aload_0 (0, 0)
	1 getfield (0, 0)
	2 org/apache/commons/math3/random/EmpiricalDistribution.binStats:Ljava/util/List; (0, 0)
	4 areturn (0, 0)

Method: access$302
	0 aload_0 (0, 0)
	1 aload_1 (0, 0)
	2 dup_x1 (0, 0)
	3 putfield (0, 0)
	4 org/apache/commons/math3/random/EmpiricalDistribution.sampleStats:Lorg/apache/commons/math3/stat/descriptive/SummaryStatistics; (0, 0)
	6 areturn (0, 0)

Method: access$300
	0 aload_0 (0, 0)
	1 getfield (0, 0)
	2 org/apache/commons/math3/random/EmpiricalDistribution.sampleStats:Lorg/apache/commons/math3/stat/descriptive/SummaryStatistics; (0, 0)
	4 areturn (0, 0)

