Method: <init>
	0 aload_0 (0, 0)
	1 invokespecial (0, 0)
	2 java/lang/Object.<init>:()V (0, 0)
	4 aload_0 (0, 0)
	5 iconst_0 (0, 0)
	6 putfield (0, 0)
	7 org/apache/commons/math3/random/HaltonSequenceGenerator.count:I (0, 0)
	9 aload_2 (10, 1)
	10 invokestatic (10, 1)
	11 org/apache/commons/math3/util/MathUtils.checkNotNull:(Ljava/lang/Object;)V (10, 1)
	13 iload_1 (11, 1)
	14 iconst_1 (11, 1)
	15 if_icmplt (11, 1)
	16 9 (11, 1)
	18 iload_1 (11, 1)
	19 aload_2 (11, 1)
	20 arraylength (11, 1)
	21 if_icmple (11, 1)
	22 26 (11, 1)
	24 new (11, 1)
	25 org/apache/commons/math3/exception/OutOfRangeException (11, 1)
	27 dup (11, 1)
	28 iload_1 (11, 1)
	29 invokestatic (11, 1)
	30 java/lang/Integer.valueOf:(I)Ljava/lang/Integer; (11, 1)
	32 iconst_1 (11, 1)
	33 invokestatic (11, 1)
	34 java/lang/Integer.valueOf:(I)Ljava/lang/Integer; (11, 1)
	36 getstatic (11, 1)
	37 org/apache/commons/math3/random/HaltonSequenceGenerator.PRIMES:[I (11, 1)
	39 arraylength (11, 1)
	40 invokestatic (11, 1)
	41 java/lang/Integer.valueOf:(I)Ljava/lang/Integer; (11, 1)
	43 invokespecial (11, 1)
	44 org/apache/commons/math3/exception/OutOfRangeException.<init>:(Ljava/lang/Number;Ljava/lang/Number;Ljava/lang/Number;)V (11, 1)
	46 athrow (11, 1)
	47 aload_3 (11, 1)
	48 ifnull (11, 1)
	49 22 (11, 1)
	51 aload_3 (11, 1)
	52 arraylength (11, 1)
	53 aload_2 (11, 1)
	54 arraylength (11, 1)
	55 if_icmpeq (11, 1)
	56 15 (11, 1)
	58 new (11, 1)
	59 org/apache/commons/math3/exception/DimensionMismatchException (11, 1)
	61 dup (11, 1)
	62 aload_3 (11, 1)
	63 arraylength (11, 1)
	64 aload_2 (11, 1)
	65 arraylength (11, 1)
	66 invokespecial (11, 1)
	67 org/apache/commons/math3/exception/DimensionMismatchException.<init>:(II)V (11, 1)
	69 athrow (11, 1)
	70 aload_0 (10, 1)
	71 iload_1 (10, 1)
	72 putfield (10, 1)
	73 org/apache/commons/math3/random/HaltonSequenceGenerator.dimension:I (10, 1)
	75 aload_0 (10, 1)
	76 aload_2 (10, 1)
	77 invokevirtual (10, 1)
	78 [I.clone:()Ljava/lang/Object; (10, 1)
	80 checkcast (10, 1)
	81 [I (10, 1)
	83 putfield (10, 1)
	84 org/apache/commons/math3/random/HaltonSequenceGenerator.base:[I (10, 1)
	86 aload_0 (10, 1)
	87 aload_3 (10, 1)
	88 ifnonnull (10, 1)
	89 7 (10, 1)
	91 aconst_null (10, 1)
	92 goto (10, 1)
	93 10 (10, 1)
	95 aload_3 (10, 1)
	96 invokevirtual (10, 1)
	97 [I.clone:()Ljava/lang/Object; (10, 1)
	99 checkcast (10, 1)
	100 [I (10, 1)
	102 putfield (10, 1)
	103 org/apache/commons/math3/random/HaltonSequenceGenerator.weight:[I (10, 1)
	105 aload_0 (10, 1)
	106 iconst_0 (10, 1)
	107 putfield (10, 1)
	108 org/apache/commons/math3/random/HaltonSequenceGenerator.count:I (10, 1)
	110 return (1, 1)

Method: nextVector
	0 aload_0 (0, 0)
	1 getfield (0, 0)
	2 org/apache/commons/math3/random/HaltonSequenceGenerator.dimension:I (0, 0)
	4 newarray (0, 0)
	5 7 (0, 0)
	6 astore_1 (0, 0)
	7 iconst_0 (1, 4)
	8 istore_2 (1, 4)
	9 iload_2 (1, 4)
	10 aload_0 (1, 4)
	11 getfield (1, 4)
	12 org/apache/commons/math3/random/HaltonSequenceGenerator.dimension:I (1, 4)
	14 if_icmpge (1, 4)
	15 91 (1, 4)
	17 aload_0 (1, 4)
	18 getfield (1, 4)
	19 org/apache/commons/math3/random/HaltonSequenceGenerator.count:I (1, 4)
	21 istore_3 (1, 4)
	22 dconst_1 (1, 4)
	23 aload_0 (1, 4)
	24 getfield (1, 4)
	25 org/apache/commons/math3/random/HaltonSequenceGenerator.base:[I (1, 4)
	27 iload_2 (1, 4)
	28 iaload (1, 4)
	29 i2d (1, 4)
	30 ddiv (1, 4)
	31 dstore (1, 4)
	32 #4 (1, 4)
	33 iconst_0 (1, 4)
	34 istore (1, 4)
	35 #6 (1, 4)
	36 iload_3 (2, 3)
	37 ifle (2, 3)
	38 62 (2, 3)
	40 aload_0 (2, 3)
	41 iload_2 (2, 3)
	42 iload (2, 3)
	43 #6 (2, 3)
	44 aload_0 (2, 3)
	45 getfield (2, 3)
	46 org/apache/commons/math3/random/HaltonSequenceGenerator.base:[I (2, 3)
	48 iload_2 (2, 3)
	49 iaload (2, 3)
	50 iload_3 (2, 3)
	51 aload_0 (2, 3)
	52 getfield (2, 3)
	53 org/apache/commons/math3/random/HaltonSequenceGenerator.base:[I (2, 3)
	55 iload_2 (2, 3)
	56 iaload (2, 3)
	57 irem (2, 3)
	58 invokevirtual (2, 3)
	59 org/apache/commons/math3/random/HaltonSequenceGenerator.scramble:(IIII)I (2, 3)
	61 istore (2, 3)
	62 #7 (2, 3)
	63 aload_1 (2, 3)
	64 iload_2 (2, 3)
	65 dup2 (2, 3)
	66 daload (2, 3)
	67 dload (2, 3)
	68 #4 (2, 3)
	69 iload (2, 3)
	70 #7 (2, 3)
	71 i2d (2, 3)
	72 dmul (2, 3)
	73 dadd (2, 3)
	74 dastore (2, 3)
	75 iload_3 (2, 3)
	76 aload_0 (2, 3)
	77 getfield (2, 3)
	78 org/apache/commons/math3/random/HaltonSequenceGenerator.base:[I (2, 3)
	80 iload_2 (2, 3)
	81 iaload (2, 3)
	82 idiv (2, 3)
	83 istore_3 (2, 3)
	84 dload (2, 3)
	85 #4 (2, 3)
	86 aload_0 (2, 3)
	87 getfield (2, 3)
	88 org/apache/commons/math3/random/HaltonSequenceGenerator.base:[I (2, 3)
	90 iload_2 (2, 3)
	91 iaload (2, 3)
	92 i2d (2, 3)
	93 ddiv (2, 3)
	94 dstore (2, 3)
	95 #4 (2, 3)
	96 goto (1, 4)
	97 -60 (1, 4)
	99 iinc (1, 4)
	100 #2 (1, 4)
	101 -89 (1, 4)
	102 goto (1, 4)
	103 -93 (1, 4)
	105 aload_0 (0, 0)
	106 dup (0, 0)
	107 getfield (0, 0)
	108 org/apache/commons/math3/random/HaltonSequenceGenerator.count:I (0, 0)
	110 iconst_1 (0, 0)
	111 iadd (0, 0)
	112 putfield (0, 0)
	113 org/apache/commons/math3/random/HaltonSequenceGenerator.count:I (0, 0)
	115 aload_1 (0, 0)
	116 areturn (0, 0)

Method: scramble
	0 aload_0 (0, 0)
	1 getfield (0, 0)
	2 org/apache/commons/math3/random/HaltonSequenceGenerator.weight:[I (0, 0)
	4 ifnull (0, 0)
	5 17 (0, 0)
	7 aload_0 (0, 0)
	8 getfield (0, 0)
	9 org/apache/commons/math3/random/HaltonSequenceGenerator.weight:[I (0, 0)
	11 iload_1 (0, 0)
	12 iaload (0, 0)
	13 iload (0, 0)
	14 #4 (0, 0)
	15 imul (0, 0)
	16 iload_3 (0, 0)
	17 irem (0, 0)
	18 goto (0, 0)
	19 5 (0, 0)
	21 iload (0, 0)
	22 #4 (0, 0)
	23 ireturn (0, 0)

Method: skipTo
	0 aload_0 (0, 0)
	1 iload_1 (0, 0)
	2 putfield (0, 0)
	3 org/apache/commons/math3/random/HaltonSequenceGenerator.count:I (0, 0)
	5 aload_0 (0, 0)
	6 invokevirtual (0, 0)
	7 org/apache/commons/math3/random/HaltonSequenceGenerator.nextVector:()[D (0, 0)
	9 areturn (0, 0)

Method: getNextIndex
	0 aload_0 (0, 0)
	1 getfield (0, 0)
	2 org/apache/commons/math3/random/HaltonSequenceGenerator.count:I (0, 0)
	4 ireturn (0, 0)

Method: <clinit>
	0 bipush (0, 0)
	1 40 (0, 0)
	2 newarray (0, 0)
	3 10 (0, 0)
	4 dup (0, 0)
	5 iconst_0 (0, 0)
	6 iconst_2 (0, 0)
	7 iastore (0, 0)
	8 dup (0, 0)
	9 iconst_1 (0, 0)
	10 iconst_3 (0, 0)
	11 iastore (0, 0)
	12 dup (0, 0)
	13 iconst_2 (0, 0)
	14 iconst_5 (0, 0)
	15 iastore (0, 0)
	16 dup (0, 0)
	17 iconst_3 (0, 0)
	18 bipush (0, 0)
	19 7 (0, 0)
	20 iastore (0, 0)
	21 dup (0, 0)
	22 iconst_4 (0, 0)
	23 bipush (0, 0)
	24 11 (0, 0)
	25 iastore (0, 0)
	26 dup (0, 0)
	27 iconst_5 (0, 0)
	28 bipush (0, 0)
	29 13 (0, 0)
	30 iastore (0, 0)
	31 dup (0, 0)
	32 bipush (0, 0)
	33 6 (0, 0)
	34 bipush (0, 0)
	35 17 (0, 0)
	36 iastore (0, 0)
	37 dup (0, 0)
	38 bipush (0, 0)
	39 7 (0, 0)
	40 bipush (0, 0)
	41 19 (0, 0)
	42 iastore (0, 0)
	43 dup (0, 0)
	44 bipush (0, 0)
	45 8 (0, 0)
	46 bipush (0, 0)
	47 23 (0, 0)
	48 iastore (0, 0)
	49 dup (0, 0)
	50 bipush (0, 0)
	51 9 (0, 0)
	52 bipush (0, 0)
	53 29 (0, 0)
	54 iastore (0, 0)
	55 dup (0, 0)
	56 bipush (0, 0)
	57 10 (0, 0)
	58 bipush (0, 0)
	59 31 (0, 0)
	60 iastore (0, 0)
	61 dup (0, 0)
	62 bipush (0, 0)
	63 11 (0, 0)
	64 bipush (0, 0)
	65 37 (0, 0)
	66 iastore (0, 0)
	67 dup (0, 0)
	68 bipush (0, 0)
	69 12 (0, 0)
	70 bipush (0, 0)
	71 41 (0, 0)
	72 iastore (0, 0)
	73 dup (0, 0)
	74 bipush (0, 0)
	75 13 (0, 0)
	76 bipush (0, 0)
	77 43 (0, 0)
	78 iastore (0, 0)
	79 dup (0, 0)
	80 bipush (0, 0)
	81 14 (0, 0)
	82 bipush (0, 0)
	83 47 (0, 0)
	84 iastore (0, 0)
	85 dup (0, 0)
	86 bipush (0, 0)
	87 15 (0, 0)
	88 bipush (0, 0)
	89 53 (0, 0)
	90 iastore (0, 0)
	91 dup (0, 0)
	92 bipush (0, 0)
	93 16 (0, 0)
	94 bipush (0, 0)
	95 59 (0, 0)
	96 iastore (0, 0)
	97 dup (0, 0)
	98 bipush (0, 0)
	99 17 (0, 0)
	100 bipush (0, 0)
	101 61 (0, 0)
	102 iastore (0, 0)
	103 dup (0, 0)
	104 bipush (0, 0)
	105 18 (0, 0)
	106 bipush (0, 0)
	107 67 (0, 0)
	108 iastore (0, 0)
	109 dup (0, 0)
	110 bipush (0, 0)
	111 19 (0, 0)
	112 bipush (0, 0)
	113 71 (0, 0)
	114 iastore (0, 0)
	115 dup (0, 0)
	116 bipush (0, 0)
	117 20 (0, 0)
	118 bipush (0, 0)
	119 73 (0, 0)
	120 iastore (0, 0)
	121 dup (0, 0)
	122 bipush (0, 0)
	123 21 (0, 0)
	124 bipush (0, 0)
	125 79 (0, 0)
	126 iastore (0, 0)
	127 dup (0, 0)
	128 bipush (0, 0)
	129 22 (0, 0)
	130 bipush (0, 0)
	131 83 (0, 0)
	132 iastore (0, 0)
	133 dup (0, 0)
	134 bipush (0, 0)
	135 23 (0, 0)
	136 bipush (0, 0)
	137 89 (0, 0)
	138 iastore (0, 0)
	139 dup (0, 0)
	140 bipush (0, 0)
	141 24 (0, 0)
	142 bipush (0, 0)
	143 97 (0, 0)
	144 iastore (0, 0)
	145 dup (0, 0)
	146 bipush (0, 0)
	147 25 (0, 0)
	148 bipush (0, 0)
	149 101 (0, 0)
	150 iastore (0, 0)
	151 dup (0, 0)
	152 bipush (0, 0)
	153 26 (0, 0)
	154 bipush (0, 0)
	155 103 (0, 0)
	156 iastore (0, 0)
	157 dup (0, 0)
	158 bipush (0, 0)
	159 27 (0, 0)
	160 bipush (0, 0)
	161 107 (0, 0)
	162 iastore (0, 0)
	163 dup (0, 0)
	164 bipush (0, 0)
	165 28 (0, 0)
	166 bipush (0, 0)
	167 109 (0, 0)
	168 iastore (0, 0)
	169 dup (0, 0)
	170 bipush (0, 0)
	171 29 (0, 0)
	172 bipush (0, 0)
	173 113 (0, 0)
	174 iastore (0, 0)
	175 dup (0, 0)
	176 bipush (0, 0)
	177 30 (0, 0)
	178 bipush (0, 0)
	179 127 (0, 0)
	180 iastore (0, 0)
	181 dup (0, 0)
	182 bipush (0, 0)
	183 31 (0, 0)
	184 sipush (0, 0)
	185 131 (0, 0)
	187 iastore (0, 0)
	188 dup (0, 0)
	189 bipush (0, 0)
	190 32 (0, 0)
	191 sipush (0, 0)
	192 137 (0, 0)
	194 iastore (0, 0)
	195 dup (0, 0)
	196 bipush (0, 0)
	197 33 (0, 0)
	198 sipush (0, 0)
	199 139 (0, 0)
	201 iastore (0, 0)
	202 dup (0, 0)
	203 bipush (0, 0)
	204 34 (0, 0)
	205 sipush (0, 0)
	206 149 (0, 0)
	208 iastore (0, 0)
	209 dup (0, 0)
	210 bipush (0, 0)
	211 35 (0, 0)
	212 sipush (0, 0)
	213 151 (0, 0)
	215 iastore (0, 0)
	216 dup (0, 0)
	217 bipush (0, 0)
	218 36 (0, 0)
	219 sipush (0, 0)
	220 157 (0, 0)
	222 iastore (0, 0)
	223 dup (0, 0)
	224 bipush (0, 0)
	225 37 (0, 0)
	226 sipush (0, 0)
	227 163 (0, 0)
	229 iastore (0, 0)
	230 dup (0, 0)
	231 bipush (0, 0)
	232 38 (0, 0)
	233 sipush (0, 0)
	234 167 (0, 0)
	236 iastore (0, 0)
	237 dup (0, 0)
	238 bipush (0, 0)
	239 39 (0, 0)
	240 sipush (0, 0)
	241 173 (0, 0)
	243 iastore (0, 0)
	244 putstatic (0, 0)
	245 org/apache/commons/math3/random/HaltonSequenceGenerator.PRIMES:[I (0, 0)
	247 bipush (1, 4)
	248 40 (1, 4)
	249 newarray (1, 4)
	250 10 (1, 4)
	251 dup (1, 4)
	252 iconst_0 (1, 4)
	253 iconst_1 (1, 4)
	254 iastore (1, 4)
	255 dup (1, 4)
	256 iconst_1 (1, 4)
	257 iconst_2 (1, 4)
	258 iastore (1, 4)
	259 dup (1, 4)
	260 iconst_2 (1, 4)
	261 iconst_3 (1, 4)
	262 iastore (1, 4)
	263 dup (1, 4)
	264 iconst_3 (1, 4)
	265 iconst_3 (1, 4)
	266 iastore (1, 4)
	267 dup (1, 4)
	268 iconst_4 (1, 4)
	269 bipush (1, 4)
	270 8 (1, 4)
	271 iastore (1, 4)
	272 dup (1, 4)
	273 iconst_5 (1, 4)
	274 bipush (1, 4)
	275 11 (1, 4)
	276 iastore (1, 4)
	277 dup (1, 4)
	278 bipush (1, 4)
	279 6 (1, 4)
	280 bipush (1, 4)
	281 12 (1, 4)
	282 iastore (1, 4)
	283 dup (1, 4)
	284 bipush (1, 4)
	285 7 (1, 4)
	286 bipush (1, 4)
	287 14 (1, 4)
	288 iastore (1, 4)
	289 dup (1, 4)
	290 bipush (1, 4)
	291 8 (1, 4)
	292 bipush (1, 4)
	293 7 (1, 4)
	294 iastore (1, 4)
	295 dup (1, 4)
	296 bipush (1, 4)
	297 9 (1, 4)
	298 bipush (1, 4)
	299 18 (1, 4)
	300 iastore (1, 4)
	301 dup (1, 4)
	302 bipush (1, 4)
	303 10 (1, 4)
	304 bipush (1, 4)
	305 12 (1, 4)
	306 iastore (1, 4)
	307 dup (1, 4)
	308 bipush (1, 4)
	309 11 (1, 4)
	310 bipush (1, 4)
	311 13 (1, 4)
	312 iastore (1, 4)
	313 dup (1, 4)
	314 bipush (1, 4)
	315 12 (1, 4)
	316 bipush (1, 4)
	317 17 (1, 4)
	318 iastore (1, 4)
	319 dup (1, 4)
	320 bipush (1, 4)
	321 13 (1, 4)
	322 bipush (1, 4)
	323 18 (1, 4)
	324 iastore (1, 4)
	325 dup (1, 4)
	326 bipush (1, 4)
	327 14 (1, 4)
	328 bipush (1, 4)
	329 29 (1, 4)
	330 iastore (1, 4)
	331 dup (1, 4)
	332 bipush (1, 4)
	333 15 (1, 4)
	334 bipush (1, 4)
	335 14 (1, 4)
	336 iastore (1, 4)
	337 dup (1, 4)
	338 bipush (1, 4)
	339 16 (1, 4)
	340 bipush (1, 4)
	341 18 (1, 4)
	342 iastore (1, 4)
	343 dup (1, 4)
	344 bipush (1, 4)
	345 17 (1, 4)
	346 bipush (1, 4)
	347 43 (1, 4)
	348 iastore (1, 4)
	349 dup (1, 4)
	350 bipush (1, 4)
	351 18 (1, 4)
	352 bipush (1, 4)
	353 41 (1, 4)
	354 iastore (1, 4)
	355 dup (1, 4)
	356 bipush (1, 4)
	357 19 (1, 4)
	358 bipush (1, 4)
	359 44 (1, 4)
	360 iastore (1, 4)
	361 dup (1, 4)
	362 bipush (1, 4)
	363 20 (1, 4)
	364 bipush (1, 4)
	365 40 (1, 4)
	366 iastore (1, 4)
	367 dup (1, 4)
	368 bipush (1, 4)
	369 21 (1, 4)
	370 bipush (1, 4)
	371 30 (1, 4)
	372 iastore (1, 4)
	373 dup (1, 4)
	374 bipush (1, 4)
	375 22 (1, 4)
	376 bipush (1, 4)
	377 47 (1, 4)
	378 iastore (1, 4)
	379 dup (1, 4)
	380 bipush (1, 4)
	381 23 (1, 4)
	382 bipush (1, 4)
	383 65 (1, 4)
	384 iastore (1, 4)
	385 dup (1, 4)
	386 bipush (1, 4)
	387 24 (1, 4)
	388 bipush (1, 4)
	389 71 (1, 4)
	390 iastore (1, 4)
	391 dup (1, 4)
	392 bipush (1, 4)
	393 25 (1, 4)
	394 bipush (1, 4)
	395 28 (1, 4)
	396 iastore (1, 4)
	397 dup (1, 4)
	398 bipush (1, 4)
	399 26 (1, 4)
	400 bipush (1, 4)
	401 40 (1, 4)
	402 iastore (1, 4)
	403 dup (1, 4)
	404 bipush (1, 4)
	405 27 (1, 4)
	406 bipush (1, 4)
	407 60 (1, 4)
	408 iastore (1, 4)
	409 dup (1, 4)
	410 bipush (1, 4)
	411 28 (1, 4)
	412 bipush (1, 4)
	413 79 (1, 4)
	414 iastore (1, 4)
	415 dup (1, 4)
	416 bipush (1, 4)
	417 29 (1, 4)
	418 bipush (1, 4)
	419 89 (1, 4)
	420 iastore (1, 4)
	421 dup (1, 4)
	422 bipush (1, 4)
	423 30 (1, 4)
	424 bipush (1, 4)
	425 56 (1, 4)
	426 iastore (1, 4)
	427 dup (1, 4)
	428 bipush (1, 4)
	429 31 (1, 4)
	430 bipush (1, 4)
	431 50 (1, 4)
	432 iastore (1, 4)
	433 dup (1, 4)
	434 bipush (1, 4)
	435 32 (1, 4)
	436 bipush (1, 4)
	437 52 (1, 4)
	438 iastore (1, 4)
	439 dup (1, 4)
	440 bipush (1, 4)
	441 33 (1, 4)
	442 bipush (1, 4)
	443 61 (1, 4)
	444 iastore (1, 4)
	445 dup (1, 4)
	446 bipush (1, 4)
	447 34 (1, 4)
	448 bipush (1, 4)
	449 108 (1, 4)
	450 iastore (1, 4)
	451 dup (1, 4)
	452 bipush (1, 4)
	453 35 (1, 4)
	454 bipush (1, 4)
	455 56 (1, 4)
	456 iastore (1, 4)
	457 dup (1, 4)
	458 bipush (1, 4)
	459 36 (1, 4)
	460 bipush (1, 4)
	461 66 (1, 4)
	462 iastore (1, 4)
	463 dup (1, 4)
	464 bipush (1, 4)
	465 37 (1, 4)
	466 bipush (1, 4)
	467 63 (1, 4)
	468 iastore (1, 4)
	469 dup (1, 4)
	470 bipush (1, 4)
	471 38 (1, 4)
	472 bipush (1, 4)
	473 60 (1, 4)
	474 iastore (1, 4)
	475 dup (1, 4)
	476 bipush (1, 4)
	477 39 (1, 4)
	478 bipush (1, 4)
	479 66 (1, 4)
	480 iastore (1, 4)
	481 putstatic (1, 4)
	482 org/apache/commons/math3/random/HaltonSequenceGenerator.WEIGHTS:[I (1, 4)
	484 return (0, 4)

