Method: <init>
	0 aload_0 (0, 0)
	1 invokespecial (0, 0)
	4 aload_0 (0, 0)
	5 sipush (0, 0)
	8 newarray (0, 0)
	10 putfield (0, 0)
	13 aload_0 (0, 0)
	14 sipush (0, 0)
	17 newarray (0, 0)
	19 putfield (0, 0)
	22 aload_0 (0, 0)
	23 bipush (0, 0)
	25 newarray (0, 0)
	27 putfield (0, 0)
	30 aload_0 (0, 0)
	31 aload_1 (0, 0)
	32 invokevirtual (0, 0)
	35 return (0, 0)

Method: setSeed
	0 aload_1 (1, 1)
	1 ifnonnull (1, 1)
	4 aload_0 (1, 1)
	5 invokestatic (1, 1)
	8 aload_0 (1, 1)
	9 invokestatic (1, 1)
	12 i2l (1, 1)
	13 ladd (1, 1)
	14 invokevirtual (1, 1)
	17 return (1, 1)
	18 aload_1 (0, 0)
	19 arraylength (0, 0)
	20 istore_2 (0, 0)
	21 aload_0 (0, 0)
	22 getfield (0, 0)
	25 arraylength (0, 0)
	26 istore_3 (0, 0)
	27 aload_1 (0, 0)
	28 iconst_0 (0, 0)
	29 aload_0 (0, 0)
	30 getfield (0, 0)
	33 iconst_0 (0, 0)
	34 iload_2 (0, 0)
	35 iload_3 (0, 0)
	36 invokestatic (0, 0)
	39 invokestatic (0, 0)
	42 iload_2 (1, 1)
	43 iload_3 (1, 1)
	44 if_icmpge (1, 1)
	47 iload_2 (2, 4)
	48 istore (2, 4)
	50 iload (2, 4)
	52 iload_3 (2, 4)
	53 if_icmpge (2, 4)
	56 aload_0 (2, 4)
	57 getfield (2, 4)
	60 iload (2, 4)
	62 iload_2 (2, 4)
	63 isub (2, 4)
	64 iaload (2, 4)
	65 i2l (2, 4)
	66 lstore (2, 4)
	68 aload_0 (2, 4)
	69 getfield (2, 4)
	72 iload (2, 4)
	74 ldc2_w (2, 4)
	77 lload (2, 4)
	79 lload (2, 4)
	81 bipush (2, 4)
	83 lshr (2, 4)
	84 lxor (2, 4)
	85 lmul (2, 4)
	86 iload (2, 4)
	88 i2l (2, 4)
	89 ladd (2, 4)
	90 ldc2_w (2, 4)
	93 land (2, 4)
	94 l2i (2, 4)
	95 iastore (2, 4)
	96 iinc (2, 4)
	99 goto (2, 4)
	102 aload_0 (0, 0)
	103 invokespecial (0, 0)
	106 return (0, 0)

Method: next
	0 aload_0 (1, 1)
	1 getfield (1, 1)
	4 ifge (1, 1)
	7 aload_0 (1, 1)
	8 invokespecial (1, 1)
	11 aload_0 (1, 1)
	12 sipush (1, 1)
	15 putfield (1, 1)
	18 aload_0 (0, 0)
	19 getfield (0, 0)
	22 aload_0 (0, 0)
	23 dup (0, 0)
	24 getfield (0, 0)
	27 dup_x1 (0, 0)
	28 iconst_1 (0, 0)
	29 isub (0, 0)
	30 putfield (0, 0)
	33 iaload (0, 0)
	34 bipush (0, 0)
	36 iload_1 (0, 0)
	37 isub (0, 0)
	38 iushr (0, 0)
	39 ireturn (0, 0)

Method: isaac
	0 aload_0 (0, 0)
	1 iconst_0 (0, 0)
	2 putfield (0, 0)
	5 aload_0 (0, 0)
	6 sipush (0, 0)
	9 putfield (0, 0)
	12 aload_0 (0, 0)
	13 dup (0, 0)
	14 getfield (0, 0)
	17 aload_0 (0, 0)
	18 dup (0, 0)
	19 getfield (0, 0)
	22 iconst_1 (0, 0)
	23 iadd (0, 0)
	24 dup_x1 (0, 0)
	25 putfield (0, 0)
	28 iadd (0, 0)
	29 putfield (0, 0)
	32 aload_0 (1, 3)
	33 getfield (1, 3)
	36 sipush (1, 3)
	39 if_icmpge (1, 3)
	42 aload_0 (1, 3)
	43 invokespecial (1, 3)
	46 goto (1, 3)
	49 aload_0 (0, 0)
	50 iconst_0 (0, 0)
	51 putfield (0, 0)
	54 aload_0 (1, 3)
	55 getfield (1, 3)
	58 sipush (1, 3)
	61 if_icmpge (1, 3)
	64 aload_0 (1, 3)
	65 invokespecial (1, 3)
	68 goto (1, 3)
	71 return (0, 0)

Method: isaac2
	0 aload_0 (0, 0)
	1 aload_0 (0, 0)
	2 getfield (0, 0)
	5 aload_0 (0, 0)
	6 getfield (0, 0)
	9 iaload (0, 0)
	10 putfield (0, 0)
	13 aload_0 (0, 0)
	14 dup (0, 0)
	15 getfield (0, 0)
	18 aload_0 (0, 0)
	19 getfield (0, 0)
	22 bipush (0, 0)
	24 ishl (0, 0)
	25 ixor (0, 0)
	26 putfield (0, 0)
	29 aload_0 (0, 0)
	30 dup (0, 0)
	31 getfield (0, 0)
	34 aload_0 (0, 0)
	35 getfield (0, 0)
	38 aload_0 (0, 0)
	39 dup (0, 0)
	40 getfield (0, 0)
	43 dup_x1 (0, 0)
	44 iconst_1 (0, 0)
	45 iadd (0, 0)
	46 putfield (0, 0)
	49 iaload (0, 0)
	50 iadd (0, 0)
	51 putfield (0, 0)
	54 aload_0 (0, 0)
	55 invokespecial (0, 0)
	58 aload_0 (0, 0)
	59 aload_0 (0, 0)
	60 getfield (0, 0)
	63 aload_0 (0, 0)
	64 getfield (0, 0)
	67 iaload (0, 0)
	68 putfield (0, 0)
	71 aload_0 (0, 0)
	72 dup (0, 0)
	73 getfield (0, 0)
	76 aload_0 (0, 0)
	77 getfield (0, 0)
	80 bipush (0, 0)
	82 iushr (0, 0)
	83 ixor (0, 0)
	84 putfield (0, 0)
	87 aload_0 (0, 0)
	88 dup (0, 0)
	89 getfield (0, 0)
	92 aload_0 (0, 0)
	93 getfield (0, 0)
	96 aload_0 (0, 0)
	97 dup (0, 0)
	98 getfield (0, 0)
	101 dup_x1 (0, 0)
	102 iconst_1 (0, 0)
	103 iadd (0, 0)
	104 putfield (0, 0)
	107 iaload (0, 0)
	108 iadd (0, 0)
	109 putfield (0, 0)
	112 aload_0 (0, 0)
	113 invokespecial (0, 0)
	116 aload_0 (0, 0)
	117 aload_0 (0, 0)
	118 getfield (0, 0)
	121 aload_0 (0, 0)
	122 getfield (0, 0)
	125 iaload (0, 0)
	126 putfield (0, 0)
	129 aload_0 (0, 0)
	130 dup (0, 0)
	131 getfield (0, 0)
	134 aload_0 (0, 0)
	135 getfield (0, 0)
	138 iconst_2 (0, 0)
	139 ishl (0, 0)
	140 ixor (0, 0)
	141 putfield (0, 0)
	144 aload_0 (0, 0)
	145 dup (0, 0)
	146 getfield (0, 0)
	149 aload_0 (0, 0)
	150 getfield (0, 0)
	153 aload_0 (0, 0)
	154 dup (0, 0)
	155 getfield (0, 0)
	158 dup_x1 (0, 0)
	159 iconst_1 (0, 0)
	160 iadd (0, 0)
	161 putfield (0, 0)
	164 iaload (0, 0)
	165 iadd (0, 0)
	166 putfield (0, 0)
	169 aload_0 (0, 0)
	170 invokespecial (0, 0)
	173 aload_0 (0, 0)
	174 aload_0 (0, 0)
	175 getfield (0, 0)
	178 aload_0 (0, 0)
	179 getfield (0, 0)
	182 iaload (0, 0)
	183 putfield (0, 0)
	186 aload_0 (0, 0)
	187 dup (0, 0)
	188 getfield (0, 0)
	191 aload_0 (0, 0)
	192 getfield (0, 0)
	195 bipush (0, 0)
	197 iushr (0, 0)
	198 ixor (0, 0)
	199 putfield (0, 0)
	202 aload_0 (0, 0)
	203 dup (0, 0)
	204 getfield (0, 0)
	207 aload_0 (0, 0)
	208 getfield (0, 0)
	211 aload_0 (0, 0)
	212 dup (0, 0)
	213 getfield (0, 0)
	216 dup_x1 (0, 0)
	217 iconst_1 (0, 0)
	218 iadd (0, 0)
	219 putfield (0, 0)
	222 iaload (0, 0)
	223 iadd (0, 0)
	224 putfield (0, 0)
	227 aload_0 (0, 0)
	228 invokespecial (0, 0)
	231 return (0, 0)

Method: isaac3
	0 aload_0 (0, 0)
	1 getfield (0, 0)
	4 aload_0 (0, 0)
	5 getfield (0, 0)
	8 aload_0 (0, 0)
	9 getfield (0, 0)
	12 aload_0 (0, 0)
	13 getfield (0, 0)
	16 sipush (0, 0)
	19 iand (0, 0)
	20 iconst_2 (0, 0)
	21 ishr (0, 0)
	22 iaload (0, 0)
	23 aload_0 (0, 0)
	24 getfield (0, 0)
	27 iadd (0, 0)
	28 aload_0 (0, 0)
	29 getfield (0, 0)
	32 iadd (0, 0)
	33 iastore (0, 0)
	34 aload_0 (0, 0)
	35 aload_0 (0, 0)
	36 getfield (0, 0)
	39 aload_0 (0, 0)
	40 getfield (0, 0)
	43 aload_0 (0, 0)
	44 getfield (0, 0)
	47 iaload (0, 0)
	48 bipush (0, 0)
	50 ishr (0, 0)
	51 sipush (0, 0)
	54 iand (0, 0)
	55 iconst_2 (0, 0)
	56 ishr (0, 0)
	57 iaload (0, 0)
	58 aload_0 (0, 0)
	59 getfield (0, 0)
	62 iadd (0, 0)
	63 putfield (0, 0)
	66 aload_0 (0, 0)
	67 getfield (0, 0)
	70 aload_0 (0, 0)
	71 dup (0, 0)
	72 getfield (0, 0)
	75 dup_x1 (0, 0)
	76 iconst_1 (0, 0)
	77 iadd (0, 0)
	78 putfield (0, 0)
	81 aload_0 (0, 0)
	82 getfield (0, 0)
	85 iastore (0, 0)
	86 return (0, 0)

Method: initState
	0 aload_0 (0, 0)
	1 iconst_0 (0, 0)
	2 putfield (0, 0)
	5 aload_0 (0, 0)
	6 iconst_0 (0, 0)
	7 putfield (0, 0)
	10 aload_0 (0, 0)
	11 iconst_0 (0, 0)
	12 putfield (0, 0)
	15 iconst_0 (1, 4)
	16 istore_1 (1, 4)
	17 iload_1 (1, 4)
	18 aload_0 (1, 4)
	19 getfield (1, 4)
	22 arraylength (1, 4)
	23 if_icmpge (1, 4)
	26 aload_0 (1, 4)
	27 getfield (1, 4)
	30 iload_1 (1, 4)
	31 ldc (1, 4)
	33 iastore (1, 4)
	34 iinc (1, 4)
	37 goto (1, 4)
	40 iconst_0 (1, 4)
	41 istore_1 (1, 4)
	42 iload_1 (1, 4)
	43 iconst_4 (1, 4)
	44 if_icmpge (1, 4)
	47 aload_0 (1, 4)
	48 invokespecial (1, 4)
	51 iinc (1, 4)
	54 goto (1, 4)
	57 iconst_0 (1, 4)
	58 istore_1 (1, 4)
	59 iload_1 (1, 4)
	60 sipush (1, 4)
	63 if_icmpge (1, 4)
	66 aload_0 (1, 4)
	67 getfield (1, 4)
	70 iconst_0 (1, 4)
	71 dup2 (1, 4)
	72 iaload (1, 4)
	73 aload_0 (1, 4)
	74 getfield (1, 4)
	77 iload_1 (1, 4)
	78 iaload (1, 4)
	79 iadd (1, 4)
	80 iastore (1, 4)
	81 aload_0 (1, 4)
	82 getfield (1, 4)
	85 iconst_1 (1, 4)
	86 dup2 (1, 4)
	87 iaload (1, 4)
	88 aload_0 (1, 4)
	89 getfield (1, 4)
	92 iload_1 (1, 4)
	93 iconst_1 (1, 4)
	94 iadd (1, 4)
	95 iaload (1, 4)
	96 iadd (1, 4)
	97 iastore (1, 4)
	98 aload_0 (1, 4)
	99 getfield (1, 4)
	102 iconst_2 (1, 4)
	103 dup2 (1, 4)
	104 iaload (1, 4)
	105 aload_0 (1, 4)
	106 getfield (1, 4)
	109 iload_1 (1, 4)
	110 iconst_2 (1, 4)
	111 iadd (1, 4)
	112 iaload (1, 4)
	113 iadd (1, 4)
	114 iastore (1, 4)
	115 aload_0 (1, 4)
	116 getfield (1, 4)
	119 iconst_3 (1, 4)
	120 dup2 (1, 4)
	121 iaload (1, 4)
	122 aload_0 (1, 4)
	123 getfield (1, 4)
	126 iload_1 (1, 4)
	127 iconst_3 (1, 4)
	128 iadd (1, 4)
	129 iaload (1, 4)
	130 iadd (1, 4)
	131 iastore (1, 4)
	132 aload_0 (1, 4)
	133 getfield (1, 4)
	136 iconst_4 (1, 4)
	137 dup2 (1, 4)
	138 iaload (1, 4)
	139 aload_0 (1, 4)
	140 getfield (1, 4)
	143 iload_1 (1, 4)
	144 iconst_4 (1, 4)
	145 iadd (1, 4)
	146 iaload (1, 4)
	147 iadd (1, 4)
	148 iastore (1, 4)
	149 aload_0 (1, 4)
	150 getfield (1, 4)
	153 iconst_5 (1, 4)
	154 dup2 (1, 4)
	155 iaload (1, 4)
	156 aload_0 (1, 4)
	157 getfield (1, 4)
	160 iload_1 (1, 4)
	161 iconst_5 (1, 4)
	162 iadd (1, 4)
	163 iaload (1, 4)
	164 iadd (1, 4)
	165 iastore (1, 4)
	166 aload_0 (1, 4)
	167 getfield (1, 4)
	170 bipush (1, 4)
	172 dup2 (1, 4)
	173 iaload (1, 4)
	174 aload_0 (1, 4)
	175 getfield (1, 4)
	178 iload_1 (1, 4)
	179 bipush (1, 4)
	181 iadd (1, 4)
	182 iaload (1, 4)
	183 iadd (1, 4)
	184 iastore (1, 4)
	185 aload_0 (1, 4)
	186 getfield (1, 4)
	189 bipush (1, 4)
	191 dup2 (1, 4)
	192 iaload (1, 4)
	193 aload_0 (1, 4)
	194 getfield (1, 4)
	197 iload_1 (1, 4)
	198 bipush (1, 4)
	200 iadd (1, 4)
	201 iaload (1, 4)
	202 iadd (1, 4)
	203 iastore (1, 4)
	204 aload_0 (1, 4)
	205 invokespecial (1, 4)
	208 aload_0 (1, 4)
	209 iload_1 (1, 4)
	210 invokespecial (1, 4)
	213 iinc (1, 4)
	216 goto (1, 4)
	219 iconst_0 (1, 4)
	220 istore_1 (1, 4)
	221 iload_1 (1, 4)
	222 sipush (1, 4)
	225 if_icmpge (1, 4)
	228 aload_0 (1, 4)
	229 getfield (1, 4)
	232 iconst_0 (1, 4)
	233 dup2 (1, 4)
	234 iaload (1, 4)
	235 aload_0 (1, 4)
	236 getfield (1, 4)
	239 iload_1 (1, 4)
	240 iaload (1, 4)
	241 iadd (1, 4)
	242 iastore (1, 4)
	243 aload_0 (1, 4)
	244 getfield (1, 4)
	247 iconst_1 (1, 4)
	248 dup2 (1, 4)
	249 iaload (1, 4)
	250 aload_0 (1, 4)
	251 getfield (1, 4)
	254 iload_1 (1, 4)
	255 iconst_1 (1, 4)
	256 iadd (1, 4)
	257 iaload (1, 4)
	258 iadd (1, 4)
	259 iastore (1, 4)
	260 aload_0 (1, 4)
	261 getfield (1, 4)
	264 iconst_2 (1, 4)
	265 dup2 (1, 4)
	266 iaload (1, 4)
	267 aload_0 (1, 4)
	268 getfield (1, 4)
	271 iload_1 (1, 4)
	272 iconst_2 (1, 4)
	273 iadd (1, 4)
	274 iaload (1, 4)
	275 iadd (1, 4)
	276 iastore (1, 4)
	277 aload_0 (1, 4)
	278 getfield (1, 4)
	281 iconst_3 (1, 4)
	282 dup2 (1, 4)
	283 iaload (1, 4)
	284 aload_0 (1, 4)
	285 getfield (1, 4)
	288 iload_1 (1, 4)
	289 iconst_3 (1, 4)
	290 iadd (1, 4)
	291 iaload (1, 4)
	292 iadd (1, 4)
	293 iastore (1, 4)
	294 aload_0 (1, 4)
	295 getfield (1, 4)
	298 iconst_4 (1, 4)
	299 dup2 (1, 4)
	300 iaload (1, 4)
	301 aload_0 (1, 4)
	302 getfield (1, 4)
	305 iload_1 (1, 4)
	306 iconst_4 (1, 4)
	307 iadd (1, 4)
	308 iaload (1, 4)
	309 iadd (1, 4)
	310 iastore (1, 4)
	311 aload_0 (1, 4)
	312 getfield (1, 4)
	315 iconst_5 (1, 4)
	316 dup2 (1, 4)
	317 iaload (1, 4)
	318 aload_0 (1, 4)
	319 getfield (1, 4)
	322 iload_1 (1, 4)
	323 iconst_5 (1, 4)
	324 iadd (1, 4)
	325 iaload (1, 4)
	326 iadd (1, 4)
	327 iastore (1, 4)
	328 aload_0 (1, 4)
	329 getfield (1, 4)
	332 bipush (1, 4)
	334 dup2 (1, 4)
	335 iaload (1, 4)
	336 aload_0 (1, 4)
	337 getfield (1, 4)
	340 iload_1 (1, 4)
	341 bipush (1, 4)
	343 iadd (1, 4)
	344 iaload (1, 4)
	345 iadd (1, 4)
	346 iastore (1, 4)
	347 aload_0 (1, 4)
	348 getfield (1, 4)
	351 bipush (1, 4)
	353 dup2 (1, 4)
	354 iaload (1, 4)
	355 aload_0 (1, 4)
	356 getfield (1, 4)
	359 iload_1 (1, 4)
	360 bipush (1, 4)
	362 iadd (1, 4)
	363 iaload (1, 4)
	364 iadd (1, 4)
	365 iastore (1, 4)
	366 aload_0 (1, 4)
	367 invokespecial (1, 4)
	370 aload_0 (1, 4)
	371 iload_1 (1, 4)
	372 invokespecial (1, 4)
	375 iinc (1, 4)
	378 goto (1, 4)
	381 aload_0 (0, 0)
	382 invokespecial (0, 0)
	385 aload_0 (0, 0)
	386 sipush (0, 0)
	389 putfield (0, 0)
	392 aload_0 (0, 0)
	393 invokevirtual (0, 0)
	396 return (0, 0)

Method: shuffle
	0 aload_0 (0, 0)
	1 getfield (0, 0)
	4 iconst_0 (0, 0)
	5 dup2 (0, 0)
	6 iaload (0, 0)
	7 aload_0 (0, 0)
	8 getfield (0, 0)
	11 iconst_1 (0, 0)
	12 iaload (0, 0)
	13 bipush (0, 0)
	15 ishl (0, 0)
	16 ixor (0, 0)
	17 iastore (0, 0)
	18 aload_0 (0, 0)
	19 getfield (0, 0)
	22 iconst_3 (0, 0)
	23 dup2 (0, 0)
	24 iaload (0, 0)
	25 aload_0 (0, 0)
	26 getfield (0, 0)
	29 iconst_0 (0, 0)
	30 iaload (0, 0)
	31 iadd (0, 0)
	32 iastore (0, 0)
	33 aload_0 (0, 0)
	34 getfield (0, 0)
	37 iconst_1 (0, 0)
	38 dup2 (0, 0)
	39 iaload (0, 0)
	40 aload_0 (0, 0)
	41 getfield (0, 0)
	44 iconst_2 (0, 0)
	45 iaload (0, 0)
	46 iadd (0, 0)
	47 iastore (0, 0)
	48 aload_0 (0, 0)
	49 getfield (0, 0)
	52 iconst_1 (0, 0)
	53 dup2 (0, 0)
	54 iaload (0, 0)
	55 aload_0 (0, 0)
	56 getfield (0, 0)
	59 iconst_2 (0, 0)
	60 iaload (0, 0)
	61 iconst_2 (0, 0)
	62 iushr (0, 0)
	63 ixor (0, 0)
	64 iastore (0, 0)
	65 aload_0 (0, 0)
	66 getfield (0, 0)
	69 iconst_4 (0, 0)
	70 dup2 (0, 0)
	71 iaload (0, 0)
	72 aload_0 (0, 0)
	73 getfield (0, 0)
	76 iconst_1 (0, 0)
	77 iaload (0, 0)
	78 iadd (0, 0)
	79 iastore (0, 0)
	80 aload_0 (0, 0)
	81 getfield (0, 0)
	84 iconst_2 (0, 0)
	85 dup2 (0, 0)
	86 iaload (0, 0)
	87 aload_0 (0, 0)
	88 getfield (0, 0)
	91 iconst_3 (0, 0)
	92 iaload (0, 0)
	93 iadd (0, 0)
	94 iastore (0, 0)
	95 aload_0 (0, 0)
	96 getfield (0, 0)
	99 iconst_2 (0, 0)
	100 dup2 (0, 0)
	101 iaload (0, 0)
	102 aload_0 (0, 0)
	103 getfield (0, 0)
	106 iconst_3 (0, 0)
	107 iaload (0, 0)
	108 bipush (0, 0)
	110 ishl (0, 0)
	111 ixor (0, 0)
	112 iastore (0, 0)
	113 aload_0 (0, 0)
	114 getfield (0, 0)
	117 iconst_5 (0, 0)
	118 dup2 (0, 0)
	119 iaload (0, 0)
	120 aload_0 (0, 0)
	121 getfield (0, 0)
	124 iconst_2 (0, 0)
	125 iaload (0, 0)
	126 iadd (0, 0)
	127 iastore (0, 0)
	128 aload_0 (0, 0)
	129 getfield (0, 0)
	132 iconst_3 (0, 0)
	133 dup2 (0, 0)
	134 iaload (0, 0)
	135 aload_0 (0, 0)
	136 getfield (0, 0)
	139 iconst_4 (0, 0)
	140 iaload (0, 0)
	141 iadd (0, 0)
	142 iastore (0, 0)
	143 aload_0 (0, 0)
	144 getfield (0, 0)
	147 iconst_3 (0, 0)
	148 dup2 (0, 0)
	149 iaload (0, 0)
	150 aload_0 (0, 0)
	151 getfield (0, 0)
	154 iconst_4 (0, 0)
	155 iaload (0, 0)
	156 bipush (0, 0)
	158 iushr (0, 0)
	159 ixor (0, 0)
	160 iastore (0, 0)
	161 aload_0 (0, 0)
	162 getfield (0, 0)
	165 bipush (0, 0)
	167 dup2 (0, 0)
	168 iaload (0, 0)
	169 aload_0 (0, 0)
	170 getfield (0, 0)
	173 iconst_3 (0, 0)
	174 iaload (0, 0)
	175 iadd (0, 0)
	176 iastore (0, 0)
	177 aload_0 (0, 0)
	178 getfield (0, 0)
	181 iconst_4 (0, 0)
	182 dup2 (0, 0)
	183 iaload (0, 0)
	184 aload_0 (0, 0)
	185 getfield (0, 0)
	188 iconst_5 (0, 0)
	189 iaload (0, 0)
	190 iadd (0, 0)
	191 iastore (0, 0)
	192 aload_0 (0, 0)
	193 getfield (0, 0)
	196 iconst_4 (0, 0)
	197 dup2 (0, 0)
	198 iaload (0, 0)
	199 aload_0 (0, 0)
	200 getfield (0, 0)
	203 iconst_5 (0, 0)
	204 iaload (0, 0)
	205 bipush (0, 0)
	207 ishl (0, 0)
	208 ixor (0, 0)
	209 iastore (0, 0)
	210 aload_0 (0, 0)
	211 getfield (0, 0)
	214 bipush (0, 0)
	216 dup2 (0, 0)
	217 iaload (0, 0)
	218 aload_0 (0, 0)
	219 getfield (0, 0)
	222 iconst_4 (0, 0)
	223 iaload (0, 0)
	224 iadd (0, 0)
	225 iastore (0, 0)
	226 aload_0 (0, 0)
	227 getfield (0, 0)
	230 iconst_5 (0, 0)
	231 dup2 (0, 0)
	232 iaload (0, 0)
	233 aload_0 (0, 0)
	234 getfield (0, 0)
	237 bipush (0, 0)
	239 iaload (0, 0)
	240 iadd (0, 0)
	241 iastore (0, 0)
	242 aload_0 (0, 0)
	243 getfield (0, 0)
	246 iconst_5 (0, 0)
	247 dup2 (0, 0)
	248 iaload (0, 0)
	249 aload_0 (0, 0)
	250 getfield (0, 0)
	253 bipush (0, 0)
	255 iaload (0, 0)
	256 iconst_4 (0, 0)
	257 iushr (0, 0)
	258 ixor (0, 0)
	259 iastore (0, 0)
	260 aload_0 (0, 0)
	261 getfield (0, 0)
	264 iconst_0 (0, 0)
	265 dup2 (0, 0)
	266 iaload (0, 0)
	267 aload_0 (0, 0)
	268 getfield (0, 0)
	271 iconst_5 (0, 0)
	272 iaload (0, 0)
	273 iadd (0, 0)
	274 iastore (0, 0)
	275 aload_0 (0, 0)
	276 getfield (0, 0)
	279 bipush (0, 0)
	281 dup2 (0, 0)
	282 iaload (0, 0)
	283 aload_0 (0, 0)
	284 getfield (0, 0)
	287 bipush (0, 0)
	289 iaload (0, 0)
	290 iadd (0, 0)
	291 iastore (0, 0)
	292 aload_0 (0, 0)
	293 getfield (0, 0)
	296 bipush (0, 0)
	298 dup2 (0, 0)
	299 iaload (0, 0)
	300 aload_0 (0, 0)
	301 getfield (0, 0)
	304 bipush (0, 0)
	306 iaload (0, 0)
	307 bipush (0, 0)
	309 ishl (0, 0)
	310 ixor (0, 0)
	311 iastore (0, 0)
	312 aload_0 (0, 0)
	313 getfield (0, 0)
	316 iconst_1 (0, 0)
	317 dup2 (0, 0)
	318 iaload (0, 0)
	319 aload_0 (0, 0)
	320 getfield (0, 0)
	323 bipush (0, 0)
	325 iaload (0, 0)
	326 iadd (0, 0)
	327 iastore (0, 0)
	328 aload_0 (0, 0)
	329 getfield (0, 0)
	332 bipush (0, 0)
	334 dup2 (0, 0)
	335 iaload (0, 0)
	336 aload_0 (0, 0)
	337 getfield (0, 0)
	340 iconst_0 (0, 0)
	341 iaload (0, 0)
	342 iadd (0, 0)
	343 iastore (0, 0)
	344 aload_0 (0, 0)
	345 getfield (0, 0)
	348 bipush (0, 0)
	350 dup2 (0, 0)
	351 iaload (0, 0)
	352 aload_0 (0, 0)
	353 getfield (0, 0)
	356 iconst_0 (0, 0)
	357 iaload (0, 0)
	358 bipush (0, 0)
	360 iushr (0, 0)
	361 ixor (0, 0)
	362 iastore (0, 0)
	363 aload_0 (0, 0)
	364 getfield (0, 0)
	367 iconst_2 (0, 0)
	368 dup2 (0, 0)
	369 iaload (0, 0)
	370 aload_0 (0, 0)
	371 getfield (0, 0)
	374 bipush (0, 0)
	376 iaload (0, 0)
	377 iadd (0, 0)
	378 iastore (0, 0)
	379 aload_0 (0, 0)
	380 getfield (0, 0)
	383 iconst_0 (0, 0)
	384 dup2 (0, 0)
	385 iaload (0, 0)
	386 aload_0 (0, 0)
	387 getfield (0, 0)
	390 iconst_1 (0, 0)
	391 iaload (0, 0)
	392 iadd (0, 0)
	393 iastore (0, 0)
	394 return (0, 0)

Method: setState
	0 aload_0 (0, 0)
	1 getfield (0, 0)
	4 iload_1 (0, 0)
	5 aload_0 (0, 0)
	6 getfield (0, 0)
	9 iconst_0 (0, 0)
	10 iaload (0, 0)
	11 iastore (0, 0)
	12 aload_0 (0, 0)
	13 getfield (0, 0)
	16 iload_1 (0, 0)
	17 iconst_1 (0, 0)
	18 iadd (0, 0)
	19 aload_0 (0, 0)
	20 getfield (0, 0)
	23 iconst_1 (0, 0)
	24 iaload (0, 0)
	25 iastore (0, 0)
	26 aload_0 (0, 0)
	27 getfield (0, 0)
	30 iload_1 (0, 0)
	31 iconst_2 (0, 0)
	32 iadd (0, 0)
	33 aload_0 (0, 0)
	34 getfield (0, 0)
	37 iconst_2 (0, 0)
	38 iaload (0, 0)
	39 iastore (0, 0)
	40 aload_0 (0, 0)
	41 getfield (0, 0)
	44 iload_1 (0, 0)
	45 iconst_3 (0, 0)
	46 iadd (0, 0)
	47 aload_0 (0, 0)
	48 getfield (0, 0)
	51 iconst_3 (0, 0)
	52 iaload (0, 0)
	53 iastore (0, 0)
	54 aload_0 (0, 0)
	55 getfield (0, 0)
	58 iload_1 (0, 0)
	59 iconst_4 (0, 0)
	60 iadd (0, 0)
	61 aload_0 (0, 0)
	62 getfield (0, 0)
	65 iconst_4 (0, 0)
	66 iaload (0, 0)
	67 iastore (0, 0)
	68 aload_0 (0, 0)
	69 getfield (0, 0)
	72 iload_1 (0, 0)
	73 iconst_5 (0, 0)
	74 iadd (0, 0)
	75 aload_0 (0, 0)
	76 getfield (0, 0)
	79 iconst_5 (0, 0)
	80 iaload (0, 0)
	81 iastore (0, 0)
	82 aload_0 (0, 0)
	83 getfield (0, 0)
	86 iload_1 (0, 0)
	87 bipush (0, 0)
	89 iadd (0, 0)
	90 aload_0 (0, 0)
	91 getfield (0, 0)
	94 bipush (0, 0)
	96 iaload (0, 0)
	97 iastore (0, 0)
	98 aload_0 (0, 0)
	99 getfield (0, 0)
	102 iload_1 (0, 0)
	103 bipush (0, 0)
	105 iadd (0, 0)
	106 aload_0 (0, 0)
	107 getfield (0, 0)
	110 bipush (0, 0)
	112 iaload (0, 0)
	113 iastore (0, 0)
	114 return (0, 0)

