Method: <init>
	0 aload_0 (0, 0)
	1 invokespecial (0, 0)
	2 org/apache/commons/math3/random/BitsStreamGenerator.<init>:()V (0, 0)
	4 aload_0 (0, 0)
	5 sipush (0, 0)
	6 624 (0, 0)
	8 newarray (0, 0)
	9 10 (0, 0)
	10 putfield (0, 0)
	11 org/apache/commons/math3/random/MersenneTwister.mt:[I (0, 0)
	13 aload_0 (0, 0)
	14 lload_1 (0, 0)
	15 invokevirtual (0, 0)
	16 org/apache/commons/math3/random/MersenneTwister.setSeed:(J)V (0, 0)
	18 return (0, 0)

Method: setSeed
	0 aload_0 (0, 0)
	1 iconst_2 (0, 0)
	2 newarray (0, 0)
	3 10 (0, 0)
	4 dup (0, 0)
	5 iconst_0 (0, 0)
	6 lload_1 (0, 0)
	7 bipush (0, 0)
	8 32 (0, 0)
	9 lushr (0, 0)
	10 l2i (0, 0)
	11 iastore (0, 0)
	12 dup (0, 0)
	13 iconst_1 (0, 0)
	14 lload_1 (0, 0)
	15 ldc2_w (0, 0)
	16 4294967295 (0, 0)
	18 land (0, 0)
	19 l2i (0, 0)
	20 iastore (0, 0)
	21 invokevirtual (0, 0)
	22 org/apache/commons/math3/random/MersenneTwister.setSeed:([I)V (0, 0)
	24 return (0, 0)

Method: next
	0 aload_0 (1, 1)
	1 getfield (1, 1)
	2 org/apache/commons/math3/random/MersenneTwister.mti:I (1, 1)
	4 sipush (1, 1)
	5 624 (1, 1)
	7 if_icmplt (1, 1)
	8 202 (1, 1)
	10 aload_0 (1, 1)
	11 getfield (1, 1)
	12 org/apache/commons/math3/random/MersenneTwister.mt:[I (1, 1)
	14 iconst_0 (1, 1)
	15 iaload (1, 1)
	16 istore_3 (1, 1)
	17 iconst_0 (2, 4)
	18 istore (2, 4)
	19 #4 (2, 4)
	20 iload (2, 4)
	21 #4 (2, 4)
	22 sipush (2, 4)
	23 227 (2, 4)
	25 if_icmpge (2, 4)
	26 63 (2, 4)
	28 iload_3 (2, 4)
	29 istore (2, 4)
	30 #5 (2, 4)
	31 aload_0 (2, 4)
	32 getfield (2, 4)
	33 org/apache/commons/math3/random/MersenneTwister.mt:[I (2, 4)
	35 iload (2, 4)
	36 #4 (2, 4)
	37 iconst_1 (2, 4)
	38 iadd (2, 4)
	39 iaload (2, 4)
	40 istore_3 (2, 4)
	41 iload (2, 4)
	42 #5 (2, 4)
	43 ldc (2, 4)
	44 2147483648 (2, 4)
	45 iand (2, 4)
	46 iload_3 (2, 4)
	47 ldc (2, 4)
	48 2147483647 (2, 4)
	49 iand (2, 4)
	50 ior (2, 4)
	51 istore_2 (2, 4)
	52 aload_0 (2, 4)
	53 getfield (2, 4)
	54 org/apache/commons/math3/random/MersenneTwister.mt:[I (2, 4)
	56 iload (2, 4)
	57 #4 (2, 4)
	58 aload_0 (2, 4)
	59 getfield (2, 4)
	60 org/apache/commons/math3/random/MersenneTwister.mt:[I (2, 4)
	62 iload (2, 4)
	63 #4 (2, 4)
	64 sipush (2, 4)
	65 397 (2, 4)
	67 iadd (2, 4)
	68 iaload (2, 4)
	69 iload_2 (2, 4)
	70 iconst_1 (2, 4)
	71 iushr (2, 4)
	72 ixor (2, 4)
	73 getstatic (2, 4)
	74 org/apache/commons/math3/random/MersenneTwister.MAG01:[I (2, 4)
	76 iload_2 (2, 4)
	77 iconst_1 (2, 4)
	78 iand (2, 4)
	79 iaload (2, 4)
	80 ixor (2, 4)
	81 iastore (2, 4)
	82 iinc (2, 4)
	83 #4 (2, 4)
	84 -89 (2, 4)
	85 goto (2, 4)
	86 -65 (2, 4)
	88 sipush (2, 4)
	89 227 (2, 4)
	91 istore (2, 4)
	92 #4 (2, 4)
	93 iload (2, 4)
	94 #4 (2, 4)
	95 sipush (2, 4)
	96 623 (2, 4)
	98 if_icmpge (2, 4)
	99 63 (2, 4)
	101 iload_3 (2, 4)
	102 istore (2, 4)
	103 #5 (2, 4)
	104 aload_0 (2, 4)
	105 getfield (2, 4)
	106 org/apache/commons/math3/random/MersenneTwister.mt:[I (2, 4)
	108 iload (2, 4)
	109 #4 (2, 4)
	110 iconst_1 (2, 4)
	111 iadd (2, 4)
	112 iaload (2, 4)
	113 istore_3 (2, 4)
	114 iload (2, 4)
	115 #5 (2, 4)
	116 ldc (2, 4)
	117 2147483648 (2, 4)
	118 iand (2, 4)
	119 iload_3 (2, 4)
	120 ldc (2, 4)
	121 2147483647 (2, 4)
	122 iand (2, 4)
	123 ior (2, 4)
	124 istore_2 (2, 4)
	125 aload_0 (2, 4)
	126 getfield (2, 4)
	127 org/apache/commons/math3/random/MersenneTwister.mt:[I (2, 4)
	129 iload (2, 4)
	130 #4 (2, 4)
	131 aload_0 (2, 4)
	132 getfield (2, 4)
	133 org/apache/commons/math3/random/MersenneTwister.mt:[I (2, 4)
	135 iload (2, 4)
	136 #4 (2, 4)
	137 sipush (2, 4)
	138 -227 (2, 4)
	140 iadd (2, 4)
	141 iaload (2, 4)
	142 iload_2 (2, 4)
	143 iconst_1 (2, 4)
	144 iushr (2, 4)
	145 ixor (2, 4)
	146 getstatic (2, 4)
	147 org/apache/commons/math3/random/MersenneTwister.MAG01:[I (2, 4)
	149 iload_2 (2, 4)
	150 iconst_1 (2, 4)
	151 iand (2, 4)
	152 iaload (2, 4)
	153 ixor (2, 4)
	154 iastore (2, 4)
	155 iinc (2, 4)
	156 #4 (2, 4)
	157 -89 (2, 4)
	158 goto (2, 4)
	159 -65 (2, 4)
	161 iload_3 (1, 1)
	162 ldc (1, 1)
	163 2147483648 (1, 1)
	164 iand (1, 1)
	165 aload_0 (1, 1)
	166 getfield (1, 1)
	167 org/apache/commons/math3/random/MersenneTwister.mt:[I (1, 1)
	169 iconst_0 (1, 1)
	170 iaload (1, 1)
	171 ldc (1, 1)
	172 2147483647 (1, 1)
	173 iand (1, 1)
	174 ior (1, 1)
	175 istore_2 (1, 1)
	176 aload_0 (1, 1)
	177 getfield (1, 1)
	178 org/apache/commons/math3/random/MersenneTwister.mt:[I (1, 1)
	180 sipush (1, 1)
	181 623 (1, 1)
	183 aload_0 (1, 1)
	184 getfield (1, 1)
	185 org/apache/commons/math3/random/MersenneTwister.mt:[I (1, 1)
	187 sipush (1, 1)
	188 396 (1, 1)
	190 iaload (1, 1)
	191 iload_2 (1, 1)
	192 iconst_1 (1, 1)
	193 iushr (1, 1)
	194 ixor (1, 1)
	195 getstatic (1, 1)
	196 org/apache/commons/math3/random/MersenneTwister.MAG01:[I (1, 1)
	198 iload_2 (1, 1)
	199 iconst_1 (1, 1)
	200 iand (1, 1)
	201 iaload (1, 1)
	202 ixor (1, 1)
	203 iastore (1, 1)
	204 aload_0 (1, 1)
	205 iconst_0 (1, 1)
	206 putfield (1, 1)
	207 org/apache/commons/math3/random/MersenneTwister.mti:I (1, 1)
	209 aload_0 (0, 0)
	210 getfield (0, 0)
	211 org/apache/commons/math3/random/MersenneTwister.mt:[I (0, 0)
	213 aload_0 (0, 0)
	214 dup (0, 0)
	215 getfield (0, 0)
	216 org/apache/commons/math3/random/MersenneTwister.mti:I (0, 0)
	218 dup_x1 (0, 0)
	219 iconst_1 (0, 0)
	220 iadd (0, 0)
	221 putfield (0, 0)
	222 org/apache/commons/math3/random/MersenneTwister.mti:I (0, 0)
	224 iaload (0, 0)
	225 istore_2 (0, 0)
	226 iload_2 (0, 0)
	227 iload_2 (0, 0)
	228 bipush (0, 0)
	229 11 (0, 0)
	230 iushr (0, 0)
	231 ixor (0, 0)
	232 istore_2 (0, 0)
	233 iload_2 (0, 0)
	234 iload_2 (0, 0)
	235 bipush (0, 0)
	236 7 (0, 0)
	237 ishl (0, 0)
	238 ldc (0, 0)
	239 2636928640 (0, 0)
	240 iand (0, 0)
	241 ixor (0, 0)
	242 istore_2 (0, 0)
	243 iload_2 (0, 0)
	244 iload_2 (0, 0)
	245 bipush (0, 0)
	246 15 (0, 0)
	247 ishl (0, 0)
	248 ldc (0, 0)
	249 4022730752 (0, 0)
	250 iand (0, 0)
	251 ixor (0, 0)
	252 istore_2 (0, 0)
	253 iload_2 (0, 0)
	254 iload_2 (0, 0)
	255 bipush (0, 0)
	256 18 (0, 0)
	257 iushr (0, 0)
	258 ixor (0, 0)
	259 istore_2 (0, 0)
	260 iload_2 (0, 0)
	261 bipush (0, 0)
	262 32 (0, 0)
	263 iload_1 (0, 0)
	264 isub (0, 0)
	265 iushr (0, 0)
	266 ireturn (0, 0)

Method: <clinit>
	0 iconst_2 (0, 0)
	1 newarray (0, 0)
	2 10 (0, 0)
	3 dup (0, 0)
	4 iconst_0 (0, 0)
	5 iconst_0 (0, 0)
	6 iastore (0, 0)
	7 dup (0, 0)
	8 iconst_1 (0, 0)
	9 ldc (0, 0)
	10 2567483615 (0, 0)
	11 iastore (0, 0)
	12 putstatic (0, 0)
	13 org/apache/commons/math3/random/MersenneTwister.MAG01:[I (0, 0)
	15 return (0, 0)

