Method: <init>
	0 aload_0 (0, 0)
	1 invokespecial (0, 0)
	2 java/lang/Object.<init>:()V (0, 0)
	4 aload_0 (0, 0)
	5 aconst_null (0, 0)
	6 putfield (0, 0)
	7 org/apache/commons/math3/random/RandomDataGenerator.rand:Lorg/apache/commons/math3/random/RandomGenerator; (0, 0)
	9 aload_0 (0, 0)
	10 aconst_null (0, 0)
	11 putfield (0, 0)
	12 org/apache/commons/math3/random/RandomDataGenerator.secRand:Lorg/apache/commons/math3/random/RandomGenerator; (0, 0)
	14 aload_0 (0, 0)
	15 aload_1 (0, 0)
	16 putfield (0, 0)
	17 org/apache/commons/math3/random/RandomDataGenerator.rand:Lorg/apache/commons/math3/random/RandomGenerator; (0, 0)
	19 return (0, 0)

Method: nextHexString
	0 iload_1 (1, 1)
	1 ifgt (1, 1)
	2 18 (1, 1)
	4 new (1, 1)
	5 org/apache/commons/math3/exception/NotStrictlyPositiveException (1, 1)
	7 dup (1, 1)
	8 getstatic (1, 1)
	9 org/apache/commons/math3/exception/util/LocalizedFormats.LENGTH:Lorg/apache/commons/math3/exception/util/LocalizedFormats; (1, 1)
	11 iload_1 (1, 1)
	12 invokestatic (1, 1)
	13 java/lang/Integer.valueOf:(I)Ljava/lang/Integer; (1, 1)
	15 invokespecial (1, 1)
	16 org/apache/commons/math3/exception/NotStrictlyPositiveException.<init>:(Lorg/apache/commons/math3/exception/util/Localizable;Ljava/lang/Number;)V (1, 1)
	18 athrow (1, 1)
	19 aload_0 (0, 0)
	20 invokevirtual (0, 0)
	21 org/apache/commons/math3/random/RandomDataGenerator.getRandomGenerator:()Lorg/apache/commons/math3/random/RandomGenerator; (0, 0)
	23 astore_2 (0, 0)
	24 new (0, 0)
	25 java/lang/StringBuilder (0, 0)
	27 dup (0, 0)
	28 invokespecial (0, 0)
	29 java/lang/StringBuilder.<init>:()V (0, 0)
	31 astore_3 (0, 0)
	32 iload_1 (0, 0)
	33 iconst_2 (0, 0)
	34 idiv (0, 0)
	35 iconst_1 (0, 0)
	36 iadd (0, 0)
	37 newarray (0, 0)
	38 8 (0, 0)
	39 astore (0, 0)
	40 #4 (0, 0)
	41 aload_2 (0, 0)
	42 aload (0, 0)
	43 #4 (0, 0)
	44 invokeinterface (0, 0)
	45 org/apache/commons/math3/random/RandomGenerator.intValue:()I (0, 0)
	47 0 (0, 0)
	49 iconst_0 (1, 4)
	50 istore (1, 4)
	51 #5 (1, 4)
	52 iload (1, 4)
	53 #5 (1, 4)
	54 aload (1, 4)
	55 #4 (1, 4)
	56 arraylength (1, 4)
	57 if_icmpge (1, 4)
	58 71 (1, 4)
	60 aload (1, 4)
	61 #4 (1, 4)
	62 iload (1, 4)
	63 #5 (1, 4)
	64 baload (1, 4)
	65 invokestatic (1, 4)
	66 java/lang/Integer.valueOf:(I)Ljava/lang/Integer; (1, 4)
	68 astore (1, 4)
	69 #6 (1, 4)
	70 aload (1, 4)
	71 #6 (1, 4)
	72 invokevirtual (1, 4)
	73 java/lang/Integer.intValue:()I (1, 4)
	75 sipush (1, 4)
	76 128 (1, 4)
	78 iadd (1, 4)
	79 invokestatic (1, 4)
	80 java/lang/Integer.toHexString:(I)Ljava/lang/String; (1, 4)
	82 astore (1, 4)
	83 #7 (1, 4)
	84 aload (2, 1)
	85 #7 (2, 1)
	86 invokevirtual (2, 1)
	87 java/lang/String.length:()I (2, 1)
	89 iconst_1 (2, 1)
	90 if_icmpne (2, 1)
	91 25 (2, 1)
	93 new (2, 1)
	94 java/lang/StringBuilder (2, 1)
	96 dup (2, 1)
	97 invokespecial (2, 1)
	98 java/lang/StringBuilder.<init>:()V (2, 1)
	100 ldc (2, 1)
	101 0 (2, 1)
	102 invokevirtual (2, 1)
	103 java/lang/StringBuilder.append:(Ljava/lang/String;)Ljava/lang/StringBuilder; (2, 1)
	105 aload (2, 1)
	106 #7 (2, 1)
	107 invokevirtual (2, 1)
	108 java/lang/StringBuilder.append:(Ljava/lang/String;)Ljava/lang/StringBuilder; (2, 1)
	110 invokevirtual (2, 1)
	111 java/lang/StringBuilder.toString:()Ljava/lang/String; (2, 1)
	113 astore (2, 1)
	114 #7 (2, 1)
	115 aload_3 (1, 4)
	116 aload (1, 4)
	117 #7 (1, 4)
	118 invokevirtual (1, 4)
	119 java/lang/StringBuilder.append:(Ljava/lang/String;)Ljava/lang/StringBuilder; (1, 4)
	121 pop (1, 4)
	122 iinc (1, 4)
	123 #5 (1, 4)
	124 -89 (1, 4)
	125 goto (1, 4)
	126 -73 (1, 4)
	128 aload_3 (0, 0)
	129 invokevirtual (0, 0)
	130 java/lang/StringBuilder.toString:()Ljava/lang/String; (0, 0)
	132 iconst_0 (0, 0)
	133 iload_1 (0, 0)
	134 invokevirtual (0, 0)
	135 java/lang/String.substring:(II)Ljava/lang/String; (0, 0)
	137 areturn (0, 0)

Method: nextInt
	0 new (0, 1)
	1 org/apache/commons/math3/distribution/UniformIntegerDistribution (0, 1)
	3 dup (0, 1)
	4 aload_0 (0, 1)
	5 invokevirtual (0, 1)
	6 org/apache/commons/math3/random/RandomDataGenerator.getRandomGenerator:()Lorg/apache/commons/math3/random/RandomGenerator; (0, 1)
	8 iload_1 (0, 1)
	9 iload_2 (0, 1)
	10 invokespecial (0, 1)
	11 org/apache/commons/math3/distribution/UniformIntegerDistribution.<init>:(Lorg/apache/commons/math3/random/RandomGenerator;II)V (0, 1)
	13 invokevirtual (0, 1)
	14 org/apache/commons/math3/distribution/UniformIntegerDistribution.sample:()I (0, 1)
	16 ireturn (0, 1)

Method: nextLong
	0 lload_1 (1, 1)
	1 lconst_0 (1, 1)
	2 lcmp (1, 1)
	3 ifle (1, 1)
	4 95 (1, 1)
	6 bipush (1, 1)
	7 8 (1, 1)
	8 newarray (1, 1)
	9 8 (1, 1)
	10 astore_3 (1, 1)
	11 aload_0 (1, 1)
	12 aload_3 (1, 1)
	13 invokeinterface (1, 1)
	14 org/apache/commons/math3/random/RandomGenerator.intValue:()I (1, 1)
	16 0 (1, 1)
	18 lconst_0 (1, 1)
	19 lstore (1, 1)
	20 #4 (1, 1)
	21 aload_3 (3, 4)
	22 astore (3, 4)
	23 #8 (3, 4)
	24 aload (3, 4)
	25 #8 (3, 4)
	26 arraylength (3, 4)
	27 istore (3, 4)
	28 #9 (3, 4)
	29 iconst_0 (3, 4)
	30 istore (3, 4)
	31 #10 (3, 4)
	32 iload (3, 4)
	33 #10 (3, 4)
	34 iload (3, 4)
	35 #9 (3, 4)
	36 if_icmpge (3, 4)
	37 31 (3, 4)
	39 aload (3, 4)
	40 #8 (3, 4)
	41 iload (3, 4)
	42 #10 (3, 4)
	43 baload (3, 4)
	44 istore (3, 4)
	45 #11 (3, 4)
	46 lload (3, 4)
	47 #4 (3, 4)
	48 bipush (3, 4)
	49 8 (3, 4)
	50 lshl (3, 4)
	51 iload (3, 4)
	52 #11 (3, 4)
	53 i2l (3, 4)
	54 ldc2_w (3, 4)
	55 255 (3, 4)
	57 land (3, 4)
	58 lor (3, 4)
	59 lstore (3, 4)
	60 #4 (3, 4)
	61 iinc (3, 4)
	62 #10 (3, 4)
	63 -89 (3, 4)
	64 goto (3, 4)
	65 -32 (3, 4)
	67 lload (1, 1)
	68 #4 (1, 1)
	69 ldc2_w (1, 1)
	70 9223372036854775807 (1, 1)
	72 land (1, 1)
	73 lstore (1, 1)
	74 #4 (1, 1)
	75 lload (1, 1)
	76 #4 (1, 1)
	77 lload_1 (1, 1)
	78 lrem (1, 1)
	79 lstore (1, 1)
	80 #6 (1, 1)
	81 lload (1, 3)
	82 #4 (1, 3)
	83 lload (1, 3)
	84 #6 (1, 3)
	85 lsub (1, 3)
	86 lload_1 (1, 3)
	87 lconst_1 (1, 3)
	88 lsub (1, 3)
	89 ladd (1, 3)
	90 lconst_0 (1, 3)
	91 lcmp (1, 3)
	92 iflt (1, 3)
	93 -81 (1, 3)
	95 lload (1, 3)
	96 #6 (1, 3)
	97 lreturn (1, 3)
	98 new (0, 0)
	99 org/apache/commons/math3/exception/NotStrictlyPositiveException (0, 0)
	101 dup (0, 0)
	102 lload_1 (0, 0)
	103 invokestatic (0, 0)
	104 java/lang/Long.valueOf:(J)Ljava/lang/Long; (0, 0)
	106 invokespecial (0, 0)
	107 org/apache/commons/math3/exception/NotStrictlyPositiveException.<init>:(Ljava/lang/Number;)V (0, 0)
	109 athrow (0, 0)

Method: nextSecureHexString
	0 iload_1 (1, 1)
	1 ifgt (1, 1)
	2 18 (1, 1)
	4 new (1, 1)
	5 org/apache/commons/math3/exception/NotStrictlyPositiveException (1, 1)
	7 dup (1, 1)
	8 getstatic (1, 1)
	9 org/apache/commons/math3/exception/util/LocalizedFormats.LENGTH:Lorg/apache/commons/math3/exception/util/LocalizedFormats; (1, 1)
	11 iload_1 (1, 1)
	12 invokestatic (1, 1)
	13 java/lang/Integer.valueOf:(I)Ljava/lang/Integer; (1, 1)
	15 invokespecial (1, 1)
	16 org/apache/commons/math3/exception/NotStrictlyPositiveException.<init>:(Lorg/apache/commons/math3/exception/util/Localizable;Ljava/lang/Number;)V (1, 1)
	18 athrow (1, 1)
	19 aload_0 (0, 0)
	20 invokespecial (0, 0)
	21 org/apache/commons/math3/random/RandomDataGenerator.getSecRan:()Lorg/apache/commons/math3/random/RandomGenerator; (0, 0)
	23 astore_2 (0, 0)
	24 aconst_null (0, 0)
	25 astore_3 (0, 0)
	26 ldc (0, 0)
	27 SHA-1 (0, 0)
	28 invokestatic (0, 0)
	29 java/security/MessageDigest.getInstance:(Ljava/lang/String;)Ljava/security/MessageDigest; (0, 0)
	31 astore_3 (0, 0)
	32 goto (0, 0)
	33 15 (0, 0)
	35 astore (0, 0)
	36 #4 (0, 0)
	37 new (0, 0)
	38 org/apache/commons/math3/exception/MathInternalError (0, 0)
	40 dup (0, 0)
	41 aload (0, 0)
	42 #4 (0, 0)
	43 invokespecial (0, 0)
	44 org/apache/commons/math3/exception/MathInternalError.<init>:(Ljava/lang/Throwable;)V (0, 0)
	46 athrow (0, 0)
	47 aload_3 (0, 0)
	48 invokevirtual (0, 0)
	49 java/security/MessageDigest.reset:()V (0, 0)
	51 iload_1 (0, 0)
	52 bipush (0, 0)
	53 40 (0, 0)
	54 idiv (0, 0)
	55 iconst_1 (0, 0)
	56 iadd (0, 0)
	57 istore (0, 0)
	58 #4 (0, 0)
	59 new (0, 0)
	60 java/lang/StringBuilder (0, 0)
	62 dup (0, 0)
	63 invokespecial (0, 0)
	64 java/lang/StringBuilder.<init>:()V (0, 0)
	66 astore (0, 0)
	67 #5 (0, 0)
	68 iconst_1 (1, 4)
	69 istore (1, 4)
	70 #6 (1, 4)
	71 iload (1, 4)
	72 #6 (1, 4)
	73 iload (1, 4)
	74 #4 (1, 4)
	75 iconst_1 (1, 4)
	76 iadd (1, 4)
	77 if_icmpge (1, 4)
	78 115 (1, 4)
	80 bipush (1, 4)
	81 40 (1, 4)
	82 newarray (1, 4)
	83 8 (1, 4)
	84 astore (1, 4)
	85 #7 (1, 4)
	86 aload_2 (1, 4)
	87 aload (1, 4)
	88 #7 (1, 4)
	89 invokeinterface (1, 4)
	90 org/apache/commons/math3/random/RandomGenerator.intValue:()I (1, 4)
	92 0 (1, 4)
	94 aload_3 (1, 4)
	95 aload (1, 4)
	96 #7 (1, 4)
	97 invokevirtual (1, 4)
	98 java/security/MessageDigest.update:([B)V (1, 4)
	100 aload_3 (1, 4)
	101 invokevirtual (1, 4)
	102 java/security/MessageDigest.digest:()[B (1, 4)
	104 astore (1, 4)
	105 #8 (1, 4)
	106 iconst_0 (2, 4)
	107 istore (2, 4)
	108 #9 (2, 4)
	109 iload (2, 4)
	110 #9 (2, 4)
	111 aload (2, 4)
	112 #8 (2, 4)
	113 arraylength (2, 4)
	114 if_icmpge (2, 4)
	115 72 (2, 4)
	117 aload (2, 4)
	118 #8 (2, 4)
	119 iload (2, 4)
	120 #9 (2, 4)
	121 baload (2, 4)
	122 invokestatic (2, 4)
	123 java/lang/Integer.valueOf:(I)Ljava/lang/Integer; (2, 4)
	125 astore (2, 4)
	126 #10 (2, 4)
	127 aload (2, 4)
	128 #10 (2, 4)
	129 invokevirtual (2, 4)
	130 java/lang/Integer.intValue:()I (2, 4)
	132 sipush (2, 4)
	133 128 (2, 4)
	135 iadd (2, 4)
	136 invokestatic (2, 4)
	137 java/lang/Integer.toHexString:(I)Ljava/lang/String; (2, 4)
	139 astore (2, 4)
	140 #11 (2, 4)
	141 aload (3, 1)
	142 #11 (3, 1)
	143 invokevirtual (3, 1)
	144 java/lang/String.length:()I (3, 1)
	146 iconst_1 (3, 1)
	147 if_icmpne (3, 1)
	148 25 (3, 1)
	150 new (3, 1)
	151 java/lang/StringBuilder (3, 1)
	153 dup (3, 1)
	154 invokespecial (3, 1)
	155 java/lang/StringBuilder.<init>:()V (3, 1)
	157 ldc (3, 1)
	158 0 (3, 1)
	159 invokevirtual (3, 1)
	160 java/lang/StringBuilder.append:(Ljava/lang/String;)Ljava/lang/StringBuilder; (3, 1)
	162 aload (3, 1)
	163 #11 (3, 1)
	164 invokevirtual (3, 1)
	165 java/lang/StringBuilder.append:(Ljava/lang/String;)Ljava/lang/StringBuilder; (3, 1)
	167 invokevirtual (3, 1)
	168 java/lang/StringBuilder.toString:()Ljava/lang/String; (3, 1)
	170 astore (3, 1)
	171 #11 (3, 1)
	172 aload (2, 1)
	173 #5 (2, 1)
	174 aload (2, 1)
	175 #11 (2, 1)
	176 invokevirtual (2, 1)
	177 java/lang/StringBuilder.append:(Ljava/lang/String;)Ljava/lang/StringBuilder; (2, 1)
	179 pop (2, 1)
	180 iinc (2, 1)
	181 #9 (2, 1)
	182 -89 (2, 1)
	183 goto (2, 1)
	184 -74 (2, 1)
	186 iinc (2, 1)
	187 #6 (2, 1)
	188 -89 (2, 1)
	189 goto (2, 1)
	190 -118 (2, 1)
	192 aload (1, 4)
	193 #5 (1, 4)
	194 invokevirtual (1, 4)
	195 java/lang/StringBuilder.toString:()Ljava/lang/String; (1, 4)
	197 iconst_0 (1, 4)
	198 iload_1 (1, 4)
	199 invokevirtual (1, 4)
	200 java/lang/String.substring:(II)Ljava/lang/String; (1, 4)
	202 areturn (1, 4)

Method: nextSecureInt
	0 new (0, 1)
	1 org/apache/commons/math3/distribution/UniformIntegerDistribution (0, 1)
	3 dup (0, 1)
	4 aload_0 (0, 1)
	5 invokespecial (0, 1)
	6 org/apache/commons/math3/random/RandomDataGenerator.getSecRan:()Lorg/apache/commons/math3/random/RandomGenerator; (0, 1)
	8 iload_1 (0, 1)
	9 iload_2 (0, 1)
	10 invokespecial (0, 1)
	11 org/apache/commons/math3/distribution/UniformIntegerDistribution.<init>:(Lorg/apache/commons/math3/random/RandomGenerator;II)V (0, 1)
	13 invokevirtual (0, 1)
	14 org/apache/commons/math3/distribution/UniformIntegerDistribution.sample:()I (0, 1)
	16 ireturn (0, 1)

Method: nextSecureLong
	0 lload_1 (1, 1)
	1 lload_3 (1, 1)
	2 lcmp (1, 1)
	3 iflt (1, 1)
	4 23 (1, 1)
	6 new (1, 1)
	7 org/apache/commons/math3/exception/NumberIsTooLargeException (1, 1)
	9 dup (1, 1)
	10 getstatic (1, 1)
	11 org/apache/commons/math3/exception/util/LocalizedFormats.LOWER_BOUND_NOT_BELOW_UPPER_BOUND:Lorg/apache/commons/math3/exception/util/LocalizedFormats; (1, 1)
	13 lload_1 (1, 1)
	14 invokestatic (1, 1)
	15 java/lang/Long.valueOf:(J)Ljava/lang/Long; (1, 1)
	17 lload_3 (1, 1)
	18 invokestatic (1, 1)
	19 java/lang/Long.valueOf:(J)Ljava/lang/Long; (1, 1)
	21 iconst_0 (1, 1)
	22 invokespecial (1, 1)
	23 org/apache/commons/math3/exception/NumberIsTooLargeException.<init>:(Lorg/apache/commons/math3/exception/util/Localizable;Ljava/lang/Number;Ljava/lang/Number;Z)V (1, 1)
	25 athrow (1, 1)
	26 aload_0 (0, 0)
	27 invokespecial (0, 0)
	28 org/apache/commons/math3/random/RandomDataGenerator.getSecRan:()Lorg/apache/commons/math3/random/RandomGenerator; (0, 0)
	30 astore (0, 0)
	31 #5 (0, 0)
	32 lload_3 (0, 0)
	33 lload_1 (0, 0)
	34 lsub (0, 0)
	35 lconst_1 (0, 0)
	36 ladd (0, 0)
	37 lstore (0, 0)
	38 #6 (0, 0)
	39 lload (1, 1)
	40 #6 (1, 1)
	41 lconst_0 (1, 1)
	42 lcmp (1, 1)
	43 ifgt (1, 1)
	44 32 (1, 1)
	46 aload (2, 3)
	47 #5 (2, 3)
	48 invokeinterface (2, 3)
	49 org/apache/commons/math3/random/RandomGenerator.java/lang/Integer (2, 3)
	51 0 (2, 3)
	53 lstore (2, 3)
	54 #8 (2, 3)
	55 lload (3, 1)
	56 #8 (3, 1)
	57 lload_1 (3, 1)
	58 lcmp (3, 1)
	59 iflt (3, 1)
	60 13 (3, 1)
	62 lload (3, 1)
	63 #8 (3, 1)
	64 lload_3 (3, 1)
	65 lcmp (3, 1)
	66 ifgt (3, 1)
	67 6 (3, 1)
	69 lload (3, 1)
	70 #8 (3, 1)
	71 lreturn (3, 1)
	72 goto (1, 1)
	73 -26 (1, 1)
	75 lload (1, 1)
	76 #6 (1, 1)
	77 ldc2_w (1, 1)
	78 2147483647 (1, 1)
	80 lcmp (1, 1)
	81 ifge (1, 1)
	82 17 (1, 1)
	84 lload_1 (1, 1)
	85 aload (1, 1)
	86 #5 (1, 1)
	87 lload (1, 1)
	88 #6 (1, 1)
	89 l2i (1, 1)
	90 invokeinterface (1, 1)
	91 org/apache/commons/math3/random/RandomGenerator.nextLong:(Lorg/apache/commons/math3/random/RandomGenerator;J)J (1, 1)
	93 0 (1, 1)
	95 i2l (1, 1)
	96 ladd (1, 1)
	97 lreturn (1, 1)
	98 lload_1 (1, 1)
	99 aload (1, 1)
	100 #5 (1, 1)
	101 lload (1, 1)
	102 #6 (1, 1)
	103 invokestatic (1, 1)
	104 org/apache/commons/math3/random/RandomDataGenerator.nextLong:(Lorg/apache/commons/math3/random/RandomGenerator;J)J (1, 1)
	106 ladd (1, 1)
	107 lreturn (1, 1)

Method: nextPoisson
	0 new (0, 0)
	1 org/apache/commons/math3/distribution/PoissonDistribution (0, 0)
	3 dup (0, 0)
	4 aload_0 (0, 0)
	5 invokevirtual (0, 0)
	6 org/apache/commons/math3/random/RandomDataGenerator.getRandomGenerator:()Lorg/apache/commons/math3/random/RandomGenerator; (0, 0)
	8 dload_1 (0, 0)
	9 ldc2_w (0, 0)
	10 1e-12 (0, 0)
	12 ldc (0, 0)
	13 10000000 (0, 0)
	14 invokespecial (0, 0)
	15 org/apache/commons/math3/distribution/PoissonDistribution.<init>:(Lorg/apache/commons/math3/random/RandomGenerator;DDI)V (0, 0)
	17 invokevirtual (0, 0)
	18 org/apache/commons/math3/distribution/PoissonDistribution.sample:()I (0, 0)
	20 i2l (0, 0)
	21 lreturn (0, 0)

Method: nextGaussian
	0 dload_3 (1, 1)
	1 dconst_0 (1, 1)
	2 dcmpg (1, 1)
	3 ifgt (1, 1)
	4 18 (1, 1)
	6 new (1, 1)
	7 org/apache/commons/math3/exception/NotStrictlyPositiveException (1, 1)
	9 dup (1, 1)
	10 getstatic (1, 1)
	11 org/apache/commons/math3/exception/util/LocalizedFormats.STANDARD_DEVIATION:Lorg/apache/commons/math3/exception/util/LocalizedFormats; (1, 1)
	13 dload_3 (1, 1)
	14 invokestatic (1, 1)
	15 java/lang/Double.valueOf:(D)Ljava/lang/Double; (1, 1)
	17 invokespecial (1, 1)
	18 org/apache/commons/math3/exception/NotStrictlyPositiveException.<init>:(Lorg/apache/commons/math3/exception/util/Localizable;Ljava/lang/Number;)V (1, 1)
	20 athrow (1, 1)
	21 dload_3 (0, 0)
	22 aload_0 (0, 0)
	23 invokevirtual (0, 0)
	24 org/apache/commons/math3/random/RandomDataGenerator.getRandomGenerator:()Lorg/apache/commons/math3/random/RandomGenerator; (0, 0)
	26 invokeinterface (0, 0)
	27 org/apache/commons/math3/random/RandomGenerator.org/apache/commons/math3/distribution/ExponentialDistribution (0, 0)
	29 0 (0, 0)
	31 dmul (0, 0)
	32 dload_1 (0, 0)
	33 dadd (0, 0)
	34 dreturn (0, 0)

Method: nextExponential
	0 new (0, 0)
	1 org/apache/commons/math3/distribution/ExponentialDistribution (0, 0)
	3 dup (0, 0)
	4 aload_0 (0, 0)
	5 invokevirtual (0, 0)
	6 org/apache/commons/math3/random/RandomDataGenerator.getRandomGenerator:()Lorg/apache/commons/math3/random/RandomGenerator; (0, 0)
	8 dload_1 (0, 0)
	9 ldc2_w (0, 0)
	10 1e-09 (0, 0)
	12 invokespecial (0, 0)
	13 org/apache/commons/math3/distribution/ExponentialDistribution.<init>:(Lorg/apache/commons/math3/random/RandomGenerator;DD)V (0, 0)
	15 invokevirtual (0, 0)
	16 org/apache/commons/math3/distribution/ExponentialDistribution.sample:()D (0, 0)
	18 dreturn (0, 0)

Method: nextGamma
	0 new (0, 0)
	1 org/apache/commons/math3/distribution/GammaDistribution (0, 0)
	3 dup (0, 0)
	4 aload_0 (0, 0)
	5 invokevirtual (0, 0)
	6 org/apache/commons/math3/random/RandomDataGenerator.getRandomGenerator:()Lorg/apache/commons/math3/random/RandomGenerator; (0, 0)
	8 dload_1 (0, 0)
	9 dload_3 (0, 0)
	10 ldc2_w (0, 0)
	11 1e-09 (0, 0)
	13 invokespecial (0, 0)
	14 org/apache/commons/math3/distribution/GammaDistribution.<init>:(Lorg/apache/commons/math3/random/RandomGenerator;DDD)V (0, 0)
	16 invokevirtual (0, 0)
	17 org/apache/commons/math3/distribution/GammaDistribution.sample:()D (0, 0)
	19 dreturn (0, 0)

Method: nextHypergeometric
	0 new (0, 0)
	1 org/apache/commons/math3/distribution/HypergeometricDistribution (0, 0)
	3 dup (0, 0)
	4 aload_0 (0, 0)
	5 invokevirtual (0, 0)
	6 org/apache/commons/math3/random/RandomDataGenerator.getRandomGenerator:()Lorg/apache/commons/math3/random/RandomGenerator; (0, 0)
	8 iload_1 (0, 0)
	9 iload_2 (0, 0)
	10 iload_3 (0, 0)
	11 invokespecial (0, 0)
	12 org/apache/commons/math3/distribution/HypergeometricDistribution.<init>:(Lorg/apache/commons/math3/random/RandomGenerator;III)V (0, 0)
	14 invokevirtual (0, 0)
	15 org/apache/commons/math3/distribution/HypergeometricDistribution.sample:()I (0, 0)
	17 ireturn (0, 0)

Method: nextPascal
	0 new (0, 0)
	1 org/apache/commons/math3/distribution/PascalDistribution (0, 0)
	3 dup (0, 0)
	4 aload_0 (0, 0)
	5 invokevirtual (0, 0)
	6 org/apache/commons/math3/random/RandomDataGenerator.getRandomGenerator:()Lorg/apache/commons/math3/random/RandomGenerator; (0, 0)
	8 iload_1 (0, 0)
	9 dload_2 (0, 0)
	10 invokespecial (0, 0)
	11 org/apache/commons/math3/distribution/PascalDistribution.<init>:(Lorg/apache/commons/math3/random/RandomGenerator;ID)V (0, 0)
	13 invokevirtual (0, 0)
	14 org/apache/commons/math3/distribution/PascalDistribution.sample:()I (0, 0)
	16 ireturn (0, 0)

Method: nextT
	0 new (0, 0)
	1 org/apache/commons/math3/distribution/TDistribution (0, 0)
	3 dup (0, 0)
	4 aload_0 (0, 0)
	5 invokevirtual (0, 0)
	6 org/apache/commons/math3/random/RandomDataGenerator.getRandomGenerator:()Lorg/apache/commons/math3/random/RandomGenerator; (0, 0)
	8 dload_1 (0, 0)
	9 ldc2_w (0, 0)
	10 1e-09 (0, 0)
	12 invokespecial (0, 0)
	13 org/apache/commons/math3/distribution/TDistribution.<init>:(Lorg/apache/commons/math3/random/RandomGenerator;DD)V (0, 0)
	15 invokevirtual (0, 0)
	16 org/apache/commons/math3/distribution/TDistribution.sample:()D (0, 0)
	18 dreturn (0, 0)

Method: nextWeibull
	0 new (0, 0)
	1 org/apache/commons/math3/distribution/WeibullDistribution (0, 0)
	3 dup (0, 0)
	4 aload_0 (0, 0)
	5 invokevirtual (0, 0)
	6 org/apache/commons/math3/random/RandomDataGenerator.getRandomGenerator:()Lorg/apache/commons/math3/random/RandomGenerator; (0, 0)
	8 dload_1 (0, 0)
	9 dload_3 (0, 0)
	10 ldc2_w (0, 0)
	11 1e-09 (0, 0)
	13 invokespecial (0, 0)
	14 org/apache/commons/math3/distribution/WeibullDistribution.<init>:(Lorg/apache/commons/math3/random/RandomGenerator;DDD)V (0, 0)
	16 invokevirtual (0, 0)
	17 org/apache/commons/math3/distribution/WeibullDistribution.sample:()D (0, 0)
	19 dreturn (0, 0)

Method: nextZipf
	0 new (0, 0)
	1 org/apache/commons/math3/distribution/ZipfDistribution (0, 0)
	3 dup (0, 0)
	4 aload_0 (0, 0)
	5 invokevirtual (0, 0)
	6 org/apache/commons/math3/random/RandomDataGenerator.getRandomGenerator:()Lorg/apache/commons/math3/random/RandomGenerator; (0, 0)
	8 iload_1 (0, 0)
	9 dload_2 (0, 0)
	10 invokespecial (0, 0)
	11 org/apache/commons/math3/distribution/ZipfDistribution.<init>:(Lorg/apache/commons/math3/random/RandomGenerator;ID)V (0, 0)
	13 invokevirtual (0, 0)
	14 org/apache/commons/math3/distribution/ZipfDistribution.sample:()I (0, 0)
	16 ireturn (0, 0)

Method: nextBeta
	0 new (0, 0)
	1 org/apache/commons/math3/distribution/BetaDistribution (0, 0)
	3 dup (0, 0)
	4 aload_0 (0, 0)
	5 invokevirtual (0, 0)
	6 org/apache/commons/math3/random/RandomDataGenerator.getRandomGenerator:()Lorg/apache/commons/math3/random/RandomGenerator; (0, 0)
	8 dload_1 (0, 0)
	9 dload_3 (0, 0)
	10 ldc2_w (0, 0)
	11 1e-09 (0, 0)
	13 invokespecial (0, 0)
	14 org/apache/commons/math3/distribution/BetaDistribution.<init>:(Lorg/apache/commons/math3/random/RandomGenerator;DDD)V (0, 0)
	16 invokevirtual (0, 0)
	17 org/apache/commons/math3/distribution/BetaDistribution.sample:()D (0, 0)
	19 dreturn (0, 0)

Method: nextBinomial
	0 new (0, 0)
	1 org/apache/commons/math3/distribution/BinomialDistribution (0, 0)
	3 dup (0, 0)
	4 aload_0 (0, 0)
	5 invokevirtual (0, 0)
	6 org/apache/commons/math3/random/RandomDataGenerator.getRandomGenerator:()Lorg/apache/commons/math3/random/RandomGenerator; (0, 0)
	8 iload_1 (0, 0)
	9 dload_2 (0, 0)
	10 invokespecial (0, 0)
	11 org/apache/commons/math3/distribution/BinomialDistribution.<init>:(Lorg/apache/commons/math3/random/RandomGenerator;ID)V (0, 0)
	13 invokevirtual (0, 0)
	14 org/apache/commons/math3/distribution/BinomialDistribution.sample:()I (0, 0)
	16 ireturn (0, 0)

Method: nextCauchy
	0 new (0, 0)
	1 org/apache/commons/math3/distribution/CauchyDistribution (0, 0)
	3 dup (0, 0)
	4 aload_0 (0, 0)
	5 invokevirtual (0, 0)
	6 org/apache/commons/math3/random/RandomDataGenerator.getRandomGenerator:()Lorg/apache/commons/math3/random/RandomGenerator; (0, 0)
	8 dload_1 (0, 0)
	9 dload_3 (0, 0)
	10 ldc2_w (0, 0)
	11 1e-09 (0, 0)
	13 invokespecial (0, 0)
	14 org/apache/commons/math3/distribution/CauchyDistribution.<init>:(Lorg/apache/commons/math3/random/RandomGenerator;DDD)V (0, 0)
	16 invokevirtual (0, 0)
	17 org/apache/commons/math3/distribution/CauchyDistribution.sample:()D (0, 0)
	19 dreturn (0, 0)

Method: nextChiSquare
	0 new (0, 0)
	1 org/apache/commons/math3/distribution/ChiSquaredDistribution (0, 0)
	3 dup (0, 0)
	4 aload_0 (0, 0)
	5 invokevirtual (0, 0)
	6 org/apache/commons/math3/random/RandomDataGenerator.getRandomGenerator:()Lorg/apache/commons/math3/random/RandomGenerator; (0, 0)
	8 dload_1 (0, 0)
	9 ldc2_w (0, 0)
	10 1e-09 (0, 0)
	12 invokespecial (0, 0)
	13 org/apache/commons/math3/distribution/ChiSquaredDistribution.<init>:(Lorg/apache/commons/math3/random/RandomGenerator;DD)V (0, 0)
	15 invokevirtual (0, 0)
	16 org/apache/commons/math3/distribution/ChiSquaredDistribution.sample:()D (0, 0)
	18 dreturn (0, 0)

Method: nextF
	0 new (0, 0)
	1 org/apache/commons/math3/distribution/FDistribution (0, 0)
	3 dup (0, 0)
	4 aload_0 (0, 0)
	5 invokevirtual (0, 0)
	6 org/apache/commons/math3/random/RandomDataGenerator.getRandomGenerator:()Lorg/apache/commons/math3/random/RandomGenerator; (0, 0)
	8 dload_1 (0, 0)
	9 dload_3 (0, 0)
	10 ldc2_w (0, 0)
	11 1e-09 (0, 0)
	13 invokespecial (0, 0)
	14 org/apache/commons/math3/distribution/FDistribution.<init>:(Lorg/apache/commons/math3/random/RandomGenerator;DDD)V (0, 0)
	16 invokevirtual (0, 0)
	17 org/apache/commons/math3/distribution/FDistribution.sample:()D (0, 0)
	19 dreturn (0, 0)

Method: nextUniform
	0 dload_1 (1, 1)
	1 dload_3 (1, 1)
	2 dcmpl (1, 1)
	3 iflt (1, 1)
	4 23 (1, 1)
	6 new (1, 1)
	7 org/apache/commons/math3/exception/NumberIsTooLargeException (1, 1)
	9 dup (1, 1)
	10 getstatic (1, 1)
	11 org/apache/commons/math3/exception/util/LocalizedFormats.LOWER_BOUND_NOT_BELOW_UPPER_BOUND:Lorg/apache/commons/math3/exception/util/LocalizedFormats; (1, 1)
	13 dload_1 (1, 1)
	14 invokestatic (1, 1)
	15 java/lang/Double.valueOf:(D)Ljava/lang/Double; (1, 1)
	17 dload_3 (1, 1)
	18 invokestatic (1, 1)
	19 java/lang/Double.valueOf:(D)Ljava/lang/Double; (1, 1)
	21 iconst_0 (1, 1)
	22 invokespecial (1, 1)
	23 org/apache/commons/math3/exception/NumberIsTooLargeException.<init>:(Lorg/apache/commons/math3/exception/util/Localizable;Ljava/lang/Number;Ljava/lang/Number;Z)V (1, 1)
	25 athrow (1, 1)
	26 dload_1 (1, 1)
	27 invokestatic (1, 1)
	28 java/lang/Double.isInfinite:(D)Z (1, 1)
	30 ifeq (1, 1)
	31 22 (1, 1)
	33 new (1, 1)
	34 org/apache/commons/math3/exception/NotFiniteNumberException (1, 1)
	36 dup (1, 1)
	37 getstatic (1, 1)
	38 org/apache/commons/math3/exception/util/LocalizedFormats.INFINITE_BOUND:Lorg/apache/commons/math3/exception/util/LocalizedFormats; (1, 1)
	40 dload_1 (1, 1)
	41 invokestatic (1, 1)
	42 java/lang/Double.valueOf:(D)Ljava/lang/Double; (1, 1)
	44 iconst_0 (1, 1)
	45 anewarray (1, 1)
	46 java/lang/Object (1, 1)
	48 invokespecial (1, 1)
	49 org/apache/commons/math3/exception/NotFiniteNumberException.<init>:(Lorg/apache/commons/math3/exception/util/Localizable;Ljava/lang/Number;[Ljava/lang/Object;)V (1, 1)
	51 athrow (1, 1)
	52 dload_3 (1, 1)
	53 invokestatic (1, 1)
	54 java/lang/Double.isInfinite:(D)Z (1, 1)
	56 ifeq (1, 1)
	57 22 (1, 1)
	59 new (1, 1)
	60 org/apache/commons/math3/exception/NotFiniteNumberException (1, 1)
	62 dup (1, 1)
	63 getstatic (1, 1)
	64 org/apache/commons/math3/exception/util/LocalizedFormats.INFINITE_BOUND:Lorg/apache/commons/math3/exception/util/LocalizedFormats; (1, 1)
	66 dload_3 (1, 1)
	67 invokestatic (1, 1)
	68 java/lang/Double.valueOf:(D)Ljava/lang/Double; (1, 1)
	70 iconst_0 (1, 1)
	71 anewarray (1, 1)
	72 java/lang/Object (1, 1)
	74 invokespecial (1, 1)
	75 org/apache/commons/math3/exception/NotFiniteNumberException.<init>:(Lorg/apache/commons/math3/exception/util/Localizable;Ljava/lang/Number;[Ljava/lang/Object;)V (1, 1)
	77 athrow (1, 1)
	78 dload_1 (1, 1)
	79 invokestatic (1, 1)
	80 java/lang/Double.isNaN:(D)Z (1, 1)
	82 ifne (1, 1)
	83 10 (1, 1)
	85 dload_3 (1, 1)
	86 invokestatic (1, 1)
	87 java/lang/Double.isNaN:(D)Z (1, 1)
	89 ifeq (1, 1)
	90 11 (1, 1)
	92 new (1, 1)
	93 org/apache/commons/math3/exception/NotANumberException (1, 1)
	95 dup (1, 1)
	96 invokespecial (1, 1)
	97 org/apache/commons/math3/exception/NotANumberException.<init>:()V (1, 1)
	99 athrow (1, 1)
	100 aload_0 (0, 0)
	101 invokevirtual (0, 0)
	102 org/apache/commons/math3/random/RandomDataGenerator.getRandomGenerator:()Lorg/apache/commons/math3/random/RandomGenerator; (0, 0)
	104 astore (0, 0)
	105 #6 (0, 0)
	106 aload (0, 0)
	107 #6 (0, 0)
	108 invokeinterface (0, 0)
	109 org/apache/commons/math3/random/RandomGenerator.PERMUTATION_EXCEEDS_N:Lorg/apache/commons/math3/exception/util/LocalizedFormats; (0, 0)
	111 0 (0, 0)
	113 dstore (0, 0)
	114 #7 (0, 0)
	115 iload (1, 3)
	116 #5 (1, 3)
	117 ifne (1, 3)
	118 22 (1, 3)
	120 dload (1, 3)
	121 #7 (1, 3)
	122 dconst_0 (1, 3)
	123 dcmpg (1, 3)
	124 ifgt (1, 3)
	125 15 (1, 3)
	127 aload (1, 3)
	128 #6 (1, 3)
	129 invokeinterface (1, 3)
	130 org/apache/commons/math3/random/RandomGenerator.PERMUTATION_EXCEEDS_N:Lorg/apache/commons/math3/exception/util/LocalizedFormats; (1, 3)
	132 0 (1, 3)
	134 dstore (1, 3)
	135 #7 (1, 3)
	136 goto (1, 3)
	137 -21 (1, 3)
	139 dload (0, 0)
	140 #7 (0, 0)
	141 dload_3 (0, 0)
	142 dmul (0, 0)
	143 dconst_1 (0, 0)
	144 dload (0, 0)
	145 #7 (0, 0)
	146 dsub (0, 0)
	147 dload_1 (0, 0)
	148 dmul (0, 0)
	149 dadd (0, 0)
	150 dreturn (0, 0)

Method: nextPermutation
	0 iload_2 (1, 1)
	1 iload_1 (1, 1)
	2 if_icmple (1, 1)
	3 23 (1, 1)
	5 new (1, 1)
	6 org/apache/commons/math3/exception/NumberIsTooLargeException (1, 1)
	8 dup (1, 1)
	9 getstatic (1, 1)
	10 org/apache/commons/math3/exception/util/LocalizedFormats.PERMUTATION_EXCEEDS_N:Lorg/apache/commons/math3/exception/util/LocalizedFormats; (1, 1)
	12 iload_2 (1, 1)
	13 invokestatic (1, 1)
	14 java/lang/Integer.valueOf:(I)Ljava/lang/Integer; (1, 1)
	16 iload_1 (1, 1)
	17 invokestatic (1, 1)
	18 java/lang/Integer.valueOf:(I)Ljava/lang/Integer; (1, 1)
	20 iconst_1 (1, 1)
	21 invokespecial (1, 1)
	22 org/apache/commons/math3/exception/NumberIsTooLargeException.<init>:(Lorg/apache/commons/math3/exception/util/Localizable;Ljava/lang/Number;Ljava/lang/Number;Z)V (1, 1)
	24 athrow (1, 1)
	25 iload_2 (1, 1)
	26 ifgt (1, 1)
	27 18 (1, 1)
	29 new (1, 1)
	30 org/apache/commons/math3/exception/NotStrictlyPositiveException (1, 1)
	32 dup (1, 1)
	33 getstatic (1, 1)
	34 org/apache/commons/math3/exception/util/LocalizedFormats.PERMUTATION_SIZE:Lorg/apache/commons/math3/exception/util/LocalizedFormats; (1, 1)
	36 iload_2 (1, 1)
	37 invokestatic (1, 1)
	38 java/lang/Integer.valueOf:(I)Ljava/lang/Integer; (1, 1)
	40 invokespecial (1, 1)
	41 org/apache/commons/math3/exception/NotStrictlyPositiveException.<init>:(Lorg/apache/commons/math3/exception/util/Localizable;Ljava/lang/Number;)V (1, 1)
	43 athrow (1, 1)
	44 iload_1 (0, 0)
	45 invokestatic (0, 0)
	46 org/apache/commons/math3/util/MathArrays.natural:(I)[I (0, 0)
	48 astore_3 (0, 0)
	49 aload_3 (0, 0)
	50 aload_0 (0, 0)
	51 invokevirtual (0, 0)
	52 org/apache/commons/math3/random/RandomDataGenerator.getRandomGenerator:()Lorg/apache/commons/math3/random/RandomGenerator; (0, 0)
	54 invokestatic (0, 0)
	55 org/apache/commons/math3/util/MathArrays.shuffle:([ILorg/apache/commons/math3/random/RandomGenerator;)V (0, 0)
	57 aload_3 (0, 0)
	58 iload_2 (0, 0)
	59 invokestatic (0, 0)
	60 org/apache/commons/math3/util/MathArrays.copyOf:([II)[I (0, 0)
	62 areturn (0, 0)

Method: nextSample
	0 aload_1 (0, 0)
	1 invokeinterface (0, 0)
	2 java/util/Collection.SAMPLE_SIZE_EXCEEDS_COLLECTION_SIZE:Lorg/apache/commons/math3/exception/util/LocalizedFormats; (0, 0)
	4 0 (0, 0)
	6 istore_3 (0, 0)
	7 iload_2 (1, 1)
	8 iload_3 (1, 1)
	9 if_icmple (1, 1)
	10 23 (1, 1)
	12 new (1, 1)
	13 org/apache/commons/math3/exception/NumberIsTooLargeException (1, 1)
	15 dup (1, 1)
	16 getstatic (1, 1)
	17 org/apache/commons/math3/exception/util/LocalizedFormats.SAMPLE_SIZE_EXCEEDS_COLLECTION_SIZE:Lorg/apache/commons/math3/exception/util/LocalizedFormats; (1, 1)
	19 iload_2 (1, 1)
	20 invokestatic (1, 1)
	21 java/lang/Integer.valueOf:(I)Ljava/lang/Integer; (1, 1)
	23 iload_3 (1, 1)
	24 invokestatic (1, 1)
	25 java/lang/Integer.valueOf:(I)Ljava/lang/Integer; (1, 1)
	27 iconst_1 (1, 1)
	28 invokespecial (1, 1)
	29 org/apache/commons/math3/exception/NumberIsTooLargeException.<init>:(Lorg/apache/commons/math3/exception/util/Localizable;Ljava/lang/Number;Ljava/lang/Number;Z)V (1, 1)
	31 athrow (1, 1)
	32 iload_2 (1, 1)
	33 ifgt (1, 1)
	34 18 (1, 1)
	36 new (1, 1)
	37 org/apache/commons/math3/exception/NotStrictlyPositiveException (1, 1)
	39 dup (1, 1)
	40 getstatic (1, 1)
	41 org/apache/commons/math3/exception/util/LocalizedFormats.NUMBER_OF_SAMPLES:Lorg/apache/commons/math3/exception/util/LocalizedFormats; (1, 1)
	43 iload_2 (1, 1)
	44 invokestatic (1, 1)
	45 java/lang/Integer.valueOf:(I)Ljava/lang/Integer; (1, 1)
	47 invokespecial (1, 1)
	48 org/apache/commons/math3/exception/NotStrictlyPositiveException.<init>:(Lorg/apache/commons/math3/exception/util/Localizable;Ljava/lang/Number;)V (1, 1)
	50 athrow (1, 1)
	51 aload_1 (0, 0)
	52 invokeinterface (0, 0)
	53 java/util/Collection.nextPermutation:(II)[I (0, 0)
	55 0 (0, 0)
	57 astore (0, 0)
	58 #4 (0, 0)
	59 aload_0 (0, 0)
	60 iload_3 (0, 0)
	61 iload_2 (0, 0)
	62 invokevirtual (0, 0)
	63 org/apache/commons/math3/random/RandomDataGenerator.nextPermutation:(II)[I (0, 0)
	65 astore (0, 0)
	66 #5 (0, 0)
	67 iload_2 (0, 0)
	68 anewarray (0, 0)
	69 java/lang/Object (0, 0)
	71 astore (0, 0)
	72 #6 (0, 0)
	73 iconst_0 (1, 4)
	74 istore (1, 4)
	75 #7 (1, 4)
	76 iload (1, 4)
	77 #7 (1, 4)
	78 iload_2 (1, 4)
	79 if_icmpge (1, 4)
	80 22 (1, 4)
	82 aload (1, 4)
	83 #6 (1, 4)
	84 iload (1, 4)
	85 #7 (1, 4)
	86 aload (1, 4)
	87 #4 (1, 4)
	88 aload (1, 4)
	89 #5 (1, 4)
	90 iload (1, 4)
	91 #7 (1, 4)
	92 iaload (1, 4)
	93 aaload (1, 4)
	94 aastore (1, 4)
	95 iinc (1, 4)
	96 #7 (1, 4)
	97 -89 (1, 4)
	98 goto (1, 4)
	99 -22 (1, 4)
	101 aload (0, 0)
	102 #6 (0, 0)
	103 areturn (0, 0)

Method: reSeed
	0 aload_0 (0, 0)
	1 invokevirtual (0, 0)
	2 org/apache/commons/math3/random/RandomDataGenerator.getRandomGenerator:()Lorg/apache/commons/math3/random/RandomGenerator; (0, 0)
	4 invokestatic (0, 0)
	5 java/lang/System.currentTimeMillis:()J (0, 0)
	7 aload_0 (0, 0)
	8 invokestatic (0, 0)
	9 java/lang/System.identityHashCode:(Ljava/lang/Object;)I (0, 0)
	11 i2l (0, 0)
	12 ladd (0, 0)
	13 invokeinterface (0, 0)
	14 org/apache/commons/math3/random/RandomGenerator.java/lang/System (0, 0)
	16 0 (0, 0)
	18 return (0, 0)

Method: reSeedSecure
	0 aload_0 (0, 0)
	1 invokespecial (0, 0)
	2 org/apache/commons/math3/random/RandomDataGenerator.getSecRan:()Lorg/apache/commons/math3/random/RandomGenerator; (0, 0)
	4 lload_1 (0, 0)
	5 invokeinterface (0, 0)
	6 org/apache/commons/math3/random/RandomGenerator.java/lang/System (0, 0)
	8 0 (0, 0)
	10 return (0, 0)

Method: setSecureAlgorithm
	0 aload_0 (0, 0)
	1 aload_1 (0, 0)
	2 aload_2 (0, 0)
	3 invokestatic (0, 0)
	4 java/security/SecureRandom.getInstance:(Ljava/lang/String;Ljava/lang/String;)Ljava/security/SecureRandom; (0, 0)
	6 invokestatic (0, 0)
	7 org/apache/commons/math3/random/RandomGeneratorFactory.createRandomGenerator:(Ljava/util/Random;)Lorg/apache/commons/math3/random/RandomGenerator; (0, 0)
	9 putfield (0, 0)
	10 org/apache/commons/math3/random/RandomDataGenerator.secRand:Lorg/apache/commons/math3/random/RandomGenerator; (0, 0)
	12 return (0, 0)

Method: getRandomGenerator
	0 aload_0 (1, 1)
	1 getfield (1, 1)
	2 org/apache/commons/math3/random/RandomDataGenerator.rand:Lorg/apache/commons/math3/random/RandomGenerator; (1, 1)
	4 ifnonnull (1, 1)
	5 7 (1, 1)
	7 aload_0 (1, 1)
	8 invokespecial (1, 1)
	9 org/apache/commons/math3/random/RandomDataGenerator.initRan:()V (1, 1)
	11 aload_0 (0, 0)
	12 getfield (0, 0)
	13 org/apache/commons/math3/random/RandomDataGenerator.rand:Lorg/apache/commons/math3/random/RandomGenerator; (0, 0)
	15 areturn (0, 0)

Method: initRan
	0 aload_0 (0, 0)
	1 new (0, 0)
	2 org/apache/commons/math3/random/Well19937c (0, 0)
	4 dup (0, 0)
	5 invokestatic (0, 0)
	6 java/lang/System.currentTimeMillis:()J (0, 0)
	8 aload_0 (0, 0)
	9 invokestatic (0, 0)
	10 java/lang/System.identityHashCode:(Ljava/lang/Object;)I (0, 0)
	12 i2l (0, 0)
	13 ladd (0, 0)
	14 invokespecial (0, 0)
	15 org/apache/commons/math3/random/Well19937c.<init>:(J)V (0, 0)
	17 putfield (0, 0)
	18 org/apache/commons/math3/random/RandomDataGenerator.rand:Lorg/apache/commons/math3/random/RandomGenerator; (0, 0)
	20 return (0, 0)

Method: getSecRan
	0 aload_0 (1, 1)
	1 getfield (1, 1)
	2 org/apache/commons/math3/random/RandomDataGenerator.secRand:Lorg/apache/commons/math3/random/RandomGenerator; (1, 1)
	4 ifnonnull (1, 1)
	5 35 (1, 1)
	7 aload_0 (1, 1)
	8 new (1, 1)
	9 java/security/SecureRandom (1, 1)
	11 dup (1, 1)
	12 invokespecial (1, 1)
	13 java/security/SecureRandom.<init>:()V (1, 1)
	15 invokestatic (1, 1)
	16 org/apache/commons/math3/random/RandomGeneratorFactory.createRandomGenerator:(Ljava/util/Random;)Lorg/apache/commons/math3/random/RandomGenerator; (1, 1)
	18 putfield (1, 1)
	19 org/apache/commons/math3/random/RandomDataGenerator.secRand:Lorg/apache/commons/math3/random/RandomGenerator; (1, 1)
	21 aload_0 (1, 1)
	22 getfield (1, 1)
	23 org/apache/commons/math3/random/RandomDataGenerator.secRand:Lorg/apache/commons/math3/random/RandomGenerator; (1, 1)
	25 invokestatic (1, 1)
	26 java/lang/System.currentTimeMillis:()J (1, 1)
	28 aload_0 (1, 1)
	29 invokestatic (1, 1)
	30 java/lang/System.identityHashCode:(Ljava/lang/Object;)I (1, 1)
	32 i2l (1, 1)
	33 ladd (1, 1)
	34 invokeinterface (1, 1)
	35 org/apache/commons/math3/random/RandomGenerator.java/lang/System (1, 1)
	37 0 (1, 1)
	39 aload_0 (0, 0)
	40 getfield (0, 0)
	41 org/apache/commons/math3/random/RandomDataGenerator.secRand:Lorg/apache/commons/math3/random/RandomGenerator; (0, 0)
	43 areturn (0, 0)

