Method: createRandomGenerator
	0 new (0, 0)
	1 org/apache/commons/math3/random/RandomGeneratorFactory$1 (0, 0)
	3 dup (0, 0)
	4 aload_0 (0, 0)
	5 invokespecial (0, 0)
	6 org/apache/commons/math3/random/RandomGeneratorFactory$1.<init>:(Ljava/util/Random;)V (0, 0)
	8 areturn (0, 0)

Method: convertToLong
	0 ldc2_w (0, 0)
	1 4294967291 (0, 0)
	3 lstore_1 (0, 0)
	4 lconst_0 (0, 0)
	5 lstore_3 (0, 0)
	6 aload_0 (1, 4)
	7 astore (1, 4)
	8 #5 (1, 4)
	9 aload (1, 4)
	10 #5 (1, 4)
	11 arraylength (1, 4)
	12 istore (1, 4)
	13 #6 (1, 4)
	14 iconst_0 (1, 4)
	15 istore (1, 4)
	16 #7 (1, 4)
	17 iload (1, 4)
	18 #7 (1, 4)
	19 iload (1, 4)
	20 #6 (1, 4)
	21 if_icmpge (1, 4)
	22 26 (1, 4)
	24 aload (1, 4)
	25 #5 (1, 4)
	26 iload (1, 4)
	27 #7 (1, 4)
	28 iaload (1, 4)
	29 istore (1, 4)
	30 #8 (1, 4)
	31 lload_3 (1, 4)
	32 ldc2_w (1, 4)
	33 4294967291 (1, 4)
	35 lmul (1, 4)
	36 iload (1, 4)
	37 #8 (1, 4)
	38 i2l (1, 4)
	39 ladd (1, 4)
	40 lstore_3 (1, 4)
	41 iinc (1, 4)
	42 #7 (1, 4)
	43 -89 (1, 4)
	44 goto (1, 4)
	45 -27 (1, 4)
	47 lload_3 (0, 0)
	48 lreturn (0, 0)

