Method: <init>
	0 aload_0 (0, 0)
	1 invokespecial (0, 0)
	2 java/lang/Object.<init>:()V (0, 0)
	4 aload_0 (0, 0)
	5 new (0, 0)
	6 org/apache/commons/math3/random/RandomDataGenerator (0, 0)
	8 dup (0, 0)
	9 aload_1 (0, 0)
	10 invokespecial (0, 0)
	11 org/apache/commons/math3/random/RandomDataGenerator.<init>:(Lorg/apache/commons/math3/random/RandomGenerator;)V (0, 0)
	13 putfield (0, 0)
	14 org/apache/commons/math3/random/RandomDataImpl.delegate:Lorg/apache/commons/math3/random/RandomDataGenerator; (0, 0)
	16 return (0, 0)

Method: getDelegate
	0 aload_0 (0, 0)
	1 getfield (0, 0)
	2 org/apache/commons/math3/random/RandomDataImpl.delegate:Lorg/apache/commons/math3/random/RandomDataGenerator; (0, 0)
	4 areturn (0, 0)

Method: nextHexString
	0 aload_0 (0, 0)
	1 getfield (0, 0)
	2 org/apache/commons/math3/random/RandomDataImpl.delegate:Lorg/apache/commons/math3/random/RandomDataGenerator; (0, 0)
	4 iload_1 (0, 0)
	5 invokevirtual (0, 0)
	6 org/apache/commons/math3/random/RandomDataGenerator.nextHexString:(I)Ljava/lang/String; (0, 0)
	8 areturn (0, 0)

Method: nextInt
	0 aload_0 (0, 0)
	1 getfield (0, 0)
	2 org/apache/commons/math3/random/RandomDataImpl.delegate:Lorg/apache/commons/math3/random/RandomDataGenerator; (0, 0)
	4 iload_1 (0, 0)
	5 iload_2 (0, 0)
	6 invokevirtual (0, 0)
	7 org/apache/commons/math3/random/RandomDataGenerator.nextInt:(II)I (0, 0)
	9 ireturn (0, 0)

Method: nextLong
	0 aload_0 (0, 0)
	1 getfield (0, 0)
	2 org/apache/commons/math3/random/RandomDataImpl.delegate:Lorg/apache/commons/math3/random/RandomDataGenerator; (0, 0)
	4 lload_1 (0, 0)
	5 lload_3 (0, 0)
	6 invokevirtual (0, 0)
	7 org/apache/commons/math3/random/RandomDataGenerator.nextLong:(JJ)J (0, 0)
	9 lreturn (0, 0)

Method: nextSecureHexString
	0 aload_0 (0, 0)
	1 getfield (0, 0)
	2 org/apache/commons/math3/random/RandomDataImpl.delegate:Lorg/apache/commons/math3/random/RandomDataGenerator; (0, 0)
	4 iload_1 (0, 0)
	5 invokevirtual (0, 0)
	6 org/apache/commons/math3/random/RandomDataGenerator.nextSecureHexString:(I)Ljava/lang/String; (0, 0)
	8 areturn (0, 0)

Method: nextSecureInt
	0 aload_0 (0, 0)
	1 getfield (0, 0)
	2 org/apache/commons/math3/random/RandomDataImpl.delegate:Lorg/apache/commons/math3/random/RandomDataGenerator; (0, 0)
	4 iload_1 (0, 0)
	5 iload_2 (0, 0)
	6 invokevirtual (0, 0)
	7 org/apache/commons/math3/random/RandomDataGenerator.nextSecureInt:(II)I (0, 0)
	9 ireturn (0, 0)

Method: nextSecureLong
	0 aload_0 (0, 0)
	1 getfield (0, 0)
	2 org/apache/commons/math3/random/RandomDataImpl.delegate:Lorg/apache/commons/math3/random/RandomDataGenerator; (0, 0)
	4 lload_1 (0, 0)
	5 lload_3 (0, 0)
	6 invokevirtual (0, 0)
	7 org/apache/commons/math3/random/RandomDataGenerator.nextSecureLong:(JJ)J (0, 0)
	9 lreturn (0, 0)

Method: nextPoisson
	0 aload_0 (0, 0)
	1 getfield (0, 0)
	2 org/apache/commons/math3/random/RandomDataImpl.delegate:Lorg/apache/commons/math3/random/RandomDataGenerator; (0, 0)
	4 dload_1 (0, 0)
	5 invokevirtual (0, 0)
	6 org/apache/commons/math3/random/RandomDataGenerator.nextPoisson:(D)J (0, 0)
	8 lreturn (0, 0)

Method: nextGaussian
	0 aload_0 (0, 0)
	1 getfield (0, 0)
	2 org/apache/commons/math3/random/RandomDataImpl.delegate:Lorg/apache/commons/math3/random/RandomDataGenerator; (0, 0)
	4 dload_1 (0, 0)
	5 dload_3 (0, 0)
	6 invokevirtual (0, 0)
	7 org/apache/commons/math3/random/RandomDataGenerator.nextGaussian:(DD)D (0, 0)
	9 dreturn (0, 0)

Method: nextExponential
	0 aload_0 (0, 0)
	1 getfield (0, 0)
	2 org/apache/commons/math3/random/RandomDataImpl.delegate:Lorg/apache/commons/math3/random/RandomDataGenerator; (0, 0)
	4 dload_1 (0, 0)
	5 invokevirtual (0, 0)
	6 org/apache/commons/math3/random/RandomDataGenerator.nextExponential:(D)D (0, 0)
	8 dreturn (0, 0)

Method: nextUniform
	0 aload_0 (1, 1)
	1 getfield (1, 1)
	2 org/apache/commons/math3/random/RandomDataImpl.delegate:Lorg/apache/commons/math3/random/RandomDataGenerator; (1, 1)
	4 dload_1 (1, 1)
	5 dload_3 (1, 1)
	6 iload (1, 1)
	7 #5 (1, 1)
	8 invokevirtual (1, 1)
	9 org/apache/commons/math3/random/RandomDataGenerator.nextUniform:(DDZ)D (1, 1)
	11 dreturn (0, 1)

Method: nextBeta
	0 aload_0 (0, 0)
	1 getfield (0, 0)
	2 org/apache/commons/math3/random/RandomDataImpl.delegate:Lorg/apache/commons/math3/random/RandomDataGenerator; (0, 0)
	4 dload_1 (0, 0)
	5 dload_3 (0, 0)
	6 invokevirtual (0, 0)
	7 org/apache/commons/math3/random/RandomDataGenerator.nextBeta:(DD)D (0, 0)
	9 dreturn (0, 0)

Method: nextBinomial
	0 aload_0 (0, 0)
	1 getfield (0, 0)
	2 org/apache/commons/math3/random/RandomDataImpl.delegate:Lorg/apache/commons/math3/random/RandomDataGenerator; (0, 0)
	4 iload_1 (0, 0)
	5 dload_2 (0, 0)
	6 invokevirtual (0, 0)
	7 org/apache/commons/math3/random/RandomDataGenerator.nextBinomial:(ID)I (0, 0)
	9 ireturn (0, 0)

Method: nextCauchy
	0 aload_0 (0, 0)
	1 getfield (0, 0)
	2 org/apache/commons/math3/random/RandomDataImpl.delegate:Lorg/apache/commons/math3/random/RandomDataGenerator; (0, 0)
	4 dload_1 (0, 0)
	5 dload_3 (0, 0)
	6 invokevirtual (0, 0)
	7 org/apache/commons/math3/random/RandomDataGenerator.nextCauchy:(DD)D (0, 0)
	9 dreturn (0, 0)

Method: nextChiSquare
	0 aload_0 (0, 0)
	1 getfield (0, 0)
	2 org/apache/commons/math3/random/RandomDataImpl.delegate:Lorg/apache/commons/math3/random/RandomDataGenerator; (0, 0)
	4 dload_1 (0, 0)
	5 invokevirtual (0, 0)
	6 org/apache/commons/math3/random/RandomDataGenerator.nextChiSquare:(D)D (0, 0)
	8 dreturn (0, 0)

Method: nextF
	0 aload_0 (0, 0)
	1 getfield (0, 0)
	2 org/apache/commons/math3/random/RandomDataImpl.delegate:Lorg/apache/commons/math3/random/RandomDataGenerator; (0, 0)
	4 dload_1 (0, 0)
	5 dload_3 (0, 0)
	6 invokevirtual (0, 0)
	7 org/apache/commons/math3/random/RandomDataGenerator.nextF:(DD)D (0, 0)
	9 dreturn (0, 0)

Method: nextGamma
	0 aload_0 (0, 0)
	1 getfield (0, 0)
	2 org/apache/commons/math3/random/RandomDataImpl.delegate:Lorg/apache/commons/math3/random/RandomDataGenerator; (0, 0)
	4 dload_1 (0, 0)
	5 dload_3 (0, 0)
	6 invokevirtual (0, 0)
	7 org/apache/commons/math3/random/RandomDataGenerator.nextGamma:(DD)D (0, 0)
	9 dreturn (0, 0)

Method: nextHypergeometric
	0 aload_0 (0, 0)
	1 getfield (0, 0)
	2 org/apache/commons/math3/random/RandomDataImpl.delegate:Lorg/apache/commons/math3/random/RandomDataGenerator; (0, 0)
	4 iload_1 (0, 0)
	5 iload_2 (0, 0)
	6 iload_3 (0, 0)
	7 invokevirtual (0, 0)
	8 org/apache/commons/math3/random/RandomDataGenerator.nextHypergeometric:(III)I (0, 0)
	10 ireturn (0, 0)

Method: nextPascal
	0 aload_0 (0, 0)
	1 getfield (0, 0)
	2 org/apache/commons/math3/random/RandomDataImpl.delegate:Lorg/apache/commons/math3/random/RandomDataGenerator; (0, 0)
	4 iload_1 (0, 0)
	5 dload_2 (0, 0)
	6 invokevirtual (0, 0)
	7 org/apache/commons/math3/random/RandomDataGenerator.nextPascal:(ID)I (0, 0)
	9 ireturn (0, 0)

Method: nextT
	0 aload_0 (0, 0)
	1 getfield (0, 0)
	2 org/apache/commons/math3/random/RandomDataImpl.delegate:Lorg/apache/commons/math3/random/RandomDataGenerator; (0, 0)
	4 dload_1 (0, 0)
	5 invokevirtual (0, 0)
	6 org/apache/commons/math3/random/RandomDataGenerator.nextT:(D)D (0, 0)
	8 dreturn (0, 0)

Method: nextWeibull
	0 aload_0 (0, 0)
	1 getfield (0, 0)
	2 org/apache/commons/math3/random/RandomDataImpl.delegate:Lorg/apache/commons/math3/random/RandomDataGenerator; (0, 0)
	4 dload_1 (0, 0)
	5 dload_3 (0, 0)
	6 invokevirtual (0, 0)
	7 org/apache/commons/math3/random/RandomDataGenerator.nextWeibull:(DD)D (0, 0)
	9 dreturn (0, 0)

Method: nextZipf
	0 aload_0 (0, 0)
	1 getfield (0, 0)
	2 org/apache/commons/math3/random/RandomDataImpl.delegate:Lorg/apache/commons/math3/random/RandomDataGenerator; (0, 0)
	4 iload_1 (0, 0)
	5 dload_2 (0, 0)
	6 invokevirtual (0, 0)
	7 org/apache/commons/math3/random/RandomDataGenerator.nextZipf:(ID)I (0, 0)
	9 ireturn (0, 0)

Method: reSeed
	0 aload_0 (0, 0)
	1 getfield (0, 0)
	2 org/apache/commons/math3/random/RandomDataImpl.delegate:Lorg/apache/commons/math3/random/RandomDataGenerator; (0, 0)
	4 invokevirtual (0, 0)
	5 org/apache/commons/math3/random/RandomDataGenerator.reSeed:()V (0, 0)
	7 return (0, 0)

Method: reSeedSecure
	0 aload_0 (0, 0)
	1 getfield (0, 0)
	2 org/apache/commons/math3/random/RandomDataImpl.delegate:Lorg/apache/commons/math3/random/RandomDataGenerator; (0, 0)
	4 lload_1 (0, 0)
	5 invokevirtual (0, 0)
	6 org/apache/commons/math3/random/RandomDataGenerator.reSeedSecure:(J)V (0, 0)
	8 return (0, 0)

Method: setSecureAlgorithm
	0 aload_0 (0, 0)
	1 getfield (0, 0)
	2 org/apache/commons/math3/random/RandomDataImpl.delegate:Lorg/apache/commons/math3/random/RandomDataGenerator; (0, 0)
	4 aload_1 (0, 0)
	5 aload_2 (0, 0)
	6 invokevirtual (0, 0)
	7 org/apache/commons/math3/random/RandomDataGenerator.setSecureAlgorithm:(Ljava/lang/String;Ljava/lang/String;)V (0, 0)
	9 return (0, 0)

Method: nextPermutation
	0 aload_0 (0, 0)
	1 getfield (0, 0)
	2 org/apache/commons/math3/random/RandomDataImpl.delegate:Lorg/apache/commons/math3/random/RandomDataGenerator; (0, 0)
	4 iload_1 (0, 0)
	5 iload_2 (0, 0)
	6 invokevirtual (0, 0)
	7 org/apache/commons/math3/random/RandomDataGenerator.nextPermutation:(II)[I (0, 0)
	9 areturn (0, 0)

Method: nextSample
	0 aload_0 (0, 0)
	1 getfield (0, 0)
	2 org/apache/commons/math3/random/RandomDataImpl.delegate:Lorg/apache/commons/math3/random/RandomDataGenerator; (0, 0)
	4 aload_1 (0, 0)
	5 iload_2 (0, 0)
	6 invokevirtual (0, 0)
	7 org/apache/commons/math3/random/RandomDataGenerator.nextSample:(Ljava/util/Collection;I)[Ljava/lang/Object; (0, 0)
	9 areturn (0, 0)

Method: nextInversionDeviate
	0 aload_1 (1, 1)
	1 aload_0 (1, 1)
	2 dconst_0 (1, 1)
	3 dconst_1 (1, 1)
	4 invokevirtual (1, 1)
	5 org/apache/commons/math3/random/RandomDataImpl.nextUniform:(DD)D (1, 1)
	7 invokeinterface (1, 1)
	8 org/apache/commons/math3/distribution/IntegerDistribution.org/apache/commons/math3/random/RandomDataImpl (1, 1)
	10 0 (1, 1)
	12 ireturn (0, 1)

