Method: <init>
	0 aload_0 (0, 0)
	1 invokespecial (0, 0)
	2 java/lang/Object.<init>:()V (0, 0)
	4 aload_0 (0, 0)
	5 iconst_0 (0, 0)
	6 putfield (0, 0)
	7 org/apache/commons/math3/random/SobolSequenceGenerator.count:I (0, 0)
	9 iload_1 (10, 1)
	10 iconst_1 (10, 1)
	11 if_icmpge (10, 1)
	12 15 (10, 1)
	14 new (10, 1)
	15 org/apache/commons/math3/exception/NotStrictlyPositiveException (10, 1)
	17 dup (10, 1)
	18 iload_1 (10, 1)
	19 invokestatic (10, 1)
	20 java/lang/Integer.valueOf:(I)Ljava/lang/Integer; (10, 1)
	22 invokespecial (10, 1)
	23 org/apache/commons/math3/exception/NotStrictlyPositiveException.<init>:(Ljava/lang/Number;)V (10, 1)
	25 athrow (10, 1)
	26 aload_0 (9, 1)
	27 iload_1 (9, 1)
	28 putfield (9, 1)
	29 org/apache/commons/math3/random/SobolSequenceGenerator.dimension:I (9, 1)
	31 aload_0 (9, 1)
	32 iload_1 (9, 1)
	33 bipush (9, 1)
	34 53 (9, 1)
	35 multianewarray (9, 1)
	36 [[J (9, 1)
	38 -75 (9, 1)
	39 putfield (9, 1)
	40 org/apache/commons/math3/random/SobolSequenceGenerator.direction:[[J (9, 1)
	42 aload_0 (9, 1)
	43 iload_1 (9, 1)
	44 newarray (9, 1)
	45 11 (9, 1)
	46 putfield (9, 1)
	47 org/apache/commons/math3/random/SobolSequenceGenerator.x:[J (9, 1)
	49 aload_0 (9, 1)
	50 aload_2 (9, 1)
	51 invokespecial (9, 1)
	52 org/apache/commons/math3/random/SobolSequenceGenerator.initFromStream:(Ljava/io/InputStream;)I (9, 1)
	54 istore_3 (9, 1)
	55 iload_3 (10, 1)
	56 iload_1 (10, 1)
	57 if_icmpge (10, 1)
	58 23 (10, 1)
	60 new (10, 1)
	61 org/apache/commons/math3/exception/OutOfRangeException (10, 1)
	63 dup (10, 1)
	64 iload_1 (10, 1)
	65 invokestatic (10, 1)
	66 java/lang/Integer.valueOf:(I)Ljava/lang/Integer; (10, 1)
	68 iconst_1 (10, 1)
	69 invokestatic (10, 1)
	70 java/lang/Integer.valueOf:(I)Ljava/lang/Integer; (10, 1)
	72 iload_3 (10, 1)
	73 invokestatic (10, 1)
	74 java/lang/Integer.valueOf:(I)Ljava/lang/Integer; (10, 1)
	76 invokespecial (10, 1)
	77 org/apache/commons/math3/exception/OutOfRangeException.<init>:(Ljava/lang/Number;Ljava/lang/Number;Ljava/lang/Number;)V (10, 1)
	79 athrow (10, 1)
	80 return (1, 1)

Method: initFromStream
	0 iconst_1 (1, 4)
	1 istore_2 (1, 4)
	2 iload_2 (1, 4)
	3 bipush (1, 4)
	4 52 (1, 4)
	5 if_icmpgt (1, 4)
	6 23 (1, 4)
	8 aload_0 (1, 4)
	9 getfield (1, 4)
	10 org/apache/commons/math3/random/SobolSequenceGenerator.direction:[[J (1, 4)
	12 iconst_0 (1, 4)
	13 aaload (1, 4)
	14 iload_2 (1, 4)
	15 lconst_1 (1, 4)
	16 bipush (1, 4)
	17 52 (1, 4)
	18 iload_2 (1, 4)
	19 isub (1, 4)
	20 lshl (1, 4)
	21 lastore (1, 4)
	22 iinc (1, 4)
	23 #2 (1, 4)
	24 -89 (1, 4)
	25 goto (1, 4)
	26 -23 (1, 4)
	28 ldc (1, 4)
	29 US-ASCII (1, 4)
	30 invokestatic (1, 4)
	31 java/nio/charset/Charset.forName:(Ljava/lang/String;)Ljava/nio/charset/Charset; (1, 4)
	33 astore_2 (1, 4)
	34 new (1, 4)
	35 java/io/BufferedReader (1, 4)
	37 dup (1, 4)
	38 new (1, 4)
	39 java/io/InputStreamReader (1, 4)
	41 dup (1, 4)
	42 aload_1 (1, 4)
	43 aload_2 (1, 4)
	44 invokespecial (1, 4)
	45 java/io/InputStreamReader.<init>:(Ljava/io/InputStream;Ljava/nio/charset/Charset;)V (1, 4)
	47 invokespecial (1, 4)
	48 java/io/BufferedReader.<init>:(Ljava/io/Reader;)V (1, 4)
	50 astore_3 (1, 4)
	51 iconst_m1 (1, 4)
	52 istore (1, 4)
	53 #4 (1, 4)
	54 aload_3 (1, 4)
	55 invokevirtual (1, 4)
	56 java/io/BufferedReader.readLine:()Ljava/lang/String; (1, 4)
	58 pop (1, 4)
	59 iconst_2 (1, 4)
	60 istore (1, 4)
	61 #5 (1, 4)
	62 iconst_1 (1, 4)
	63 istore (1, 4)
	64 #6 (1, 4)
	65 aconst_null (1, 4)
	66 astore (1, 4)
	67 #7 (1, 4)
	68 aload_3 (2, 3)
	69 invokevirtual (2, 3)
	70 java/io/BufferedReader.readLine:()Ljava/lang/String; (2, 3)
	72 dup (2, 3)
	73 astore (2, 3)
	74 #7 (2, 3)
	75 ifnull (2, 3)
	76 168 (2, 3)
	78 new (2, 3)
	79 java/util/StringTokenizer (2, 3)
	81 dup (2, 3)
	82 aload (2, 3)
	83 #7 (2, 3)
	84 ldc (2, 3)
	85   (2, 3)
	86 invokespecial (2, 3)
	87 java/util/StringTokenizer.<init>:(Ljava/lang/String;Ljava/lang/String;)V (2, 3)
	89 astore (2, 3)
	90 #8 (2, 3)
	91 aload (2, 3)
	92 #8 (2, 3)
	93 invokevirtual (2, 3)
	94 java/util/StringTokenizer.nextToken:()Ljava/lang/String; (2, 3)
	96 invokestatic (2, 3)
	97 java/lang/Integer.parseInt:(Ljava/lang/String;)I (2, 3)
	99 istore (2, 3)
	100 #4 (2, 3)
	101 iload (3, 1)
	102 #4 (3, 1)
	103 iconst_2 (3, 1)
	104 if_icmplt (3, 1)
	105 82 (3, 1)
	107 iload (3, 1)
	108 #4 (3, 1)
	109 aload_0 (3, 1)
	110 getfield (3, 1)
	111 org/apache/commons/math3/random/SobolSequenceGenerator.dimension:I (3, 1)
	113 if_icmpgt (3, 1)
	114 73 (3, 1)
	116 aload (3, 1)
	117 #8 (3, 1)
	118 invokevirtual (3, 1)
	119 java/util/StringTokenizer.nextToken:()Ljava/lang/String; (3, 1)
	121 invokestatic (3, 1)
	122 java/lang/Integer.parseInt:(Ljava/lang/String;)I (3, 1)
	124 istore (3, 1)
	125 #9 (3, 1)
	126 aload (3, 1)
	127 #8 (3, 1)
	128 invokevirtual (3, 1)
	129 java/util/StringTokenizer.nextToken:()Ljava/lang/String; (3, 1)
	131 invokestatic (3, 1)
	132 java/lang/Integer.parseInt:(Ljava/lang/String;)I (3, 1)
	134 istore (3, 1)
	135 #10 (3, 1)
	136 iload (3, 1)
	137 #9 (3, 1)
	138 iconst_1 (3, 1)
	139 iadd (3, 1)
	140 newarray (3, 1)
	141 10 (3, 1)
	142 astore (3, 1)
	143 #11 (3, 1)
	144 iconst_1 (4, 4)
	145 istore (4, 4)
	146 #12 (4, 4)
	147 iload (4, 4)
	148 #12 (4, 4)
	149 iload (4, 4)
	150 #9 (4, 4)
	151 if_icmpgt (4, 4)
	152 22 (4, 4)
	154 aload (4, 4)
	155 #11 (4, 4)
	156 iload (4, 4)
	157 #12 (4, 4)
	158 aload (4, 4)
	159 #8 (4, 4)
	160 invokevirtual (4, 4)
	161 java/util/StringTokenizer.nextToken:()Ljava/lang/String; (4, 4)
	163 invokestatic (4, 4)
	164 java/lang/Integer.parseInt:(Ljava/lang/String;)I (4, 4)
	166 iastore (4, 4)
	167 iinc (4, 4)
	168 #12 (4, 4)
	169 -89 (4, 4)
	170 goto (4, 4)
	171 -23 (4, 4)
	173 aload_0 (3, 1)
	174 iload (3, 1)
	175 #6 (3, 1)
	176 iinc (3, 1)
	177 #6 (3, 1)
	178 21 (3, 1)
	179 iload (3, 1)
	180 #10 (3, 1)
	181 aload (3, 1)
	182 #11 (3, 1)
	183 invokespecial (3, 1)
	184 org/apache/commons/math3/random/SobolSequenceGenerator.initDirectionVector:(II[I)V (3, 1)
	186 iload (3, 1)
	187 #4 (3, 1)
	188 aload_0 (3, 1)
	189 getfield (3, 1)
	190 org/apache/commons/math3/random/SobolSequenceGenerator.dimension:I (3, 1)
	192 if_icmple (3, 1)
	193 14 (3, 1)
	195 iload (3, 1)
	196 #4 (3, 1)
	197 istore (3, 1)
	198 #9 (3, 1)
	199 aload_3 (1, 4)
	200 invokevirtual (1, 4)
	201 java/io/BufferedReader.close:()V (1, 4)
	203 iload (1, 4)
	204 #9 (1, 4)
	205 ireturn (1, 4)
	206 goto (1, 4)
	207 31 (1, 4)
	209 astore (1, 4)
	210 #9 (1, 4)
	211 new (1, 4)
	212 org/apache/commons/math3/exception/MathParseException (1, 4)
	214 dup (1, 4)
	215 aload (1, 4)
	216 #7 (1, 4)
	217 iload (1, 4)
	218 #5 (1, 4)
	219 invokespecial (1, 4)
	220 org/apache/commons/math3/exception/MathParseException.<init>:(Ljava/lang/String;I)V (1, 4)
	222 athrow (1, 4)
	223 astore (1, 4)
	224 #9 (1, 4)
	225 new (1, 4)
	226 org/apache/commons/math3/exception/MathParseException (1, 4)
	228 dup (1, 4)
	229 aload (1, 4)
	230 #7 (1, 4)
	231 iload (1, 4)
	232 #5 (1, 4)
	233 invokespecial (1, 4)
	234 org/apache/commons/math3/exception/MathParseException.<init>:(Ljava/lang/String;I)V (1, 4)
	236 athrow (1, 4)
	237 iinc (1, 4)
	238 #5 (1, 4)
	239 -89 (1, 4)
	240 goto (1, 4)
	241 -172 (1, 4)
	243 aload_3 (1, 4)
	244 invokevirtual (1, 4)
	245 java/io/BufferedReader.close:()V (1, 4)
	247 goto (1, 4)
	248 12 (1, 4)
	250 astore (1, 4)
	251 #13 (1, 4)
	252 aload_3 (1, 4)
	253 invokevirtual (1, 4)
	254 java/io/BufferedReader.close:()V (1, 4)
	256 aload (1, 4)
	257 #13 (1, 4)
	258 athrow (1, 4)
	259 iload (1, 4)
	260 #4 (1, 4)
	261 ireturn (0, 4)

Method: initDirectionVector
	0 aload_3 (0, 0)
	1 arraylength (0, 0)
	2 iconst_1 (0, 0)
	3 isub (0, 0)
	4 istore (0, 0)
	5 #4 (0, 0)
	6 iconst_1 (1, 4)
	7 istore (1, 4)
	8 #5 (1, 4)
	9 iload (1, 4)
	10 #5 (1, 4)
	11 iload (1, 4)
	12 #4 (1, 4)
	13 if_icmpgt (1, 4)
	14 29 (1, 4)
	16 aload_0 (1, 4)
	17 getfield (1, 4)
	18 org/apache/commons/math3/random/SobolSequenceGenerator.direction:[[J (1, 4)
	20 iload_1 (1, 4)
	21 aaload (1, 4)
	22 iload (1, 4)
	23 #5 (1, 4)
	24 aload_3 (1, 4)
	25 iload (1, 4)
	26 #5 (1, 4)
	27 iaload (1, 4)
	28 i2l (1, 4)
	29 bipush (1, 4)
	30 52 (1, 4)
	31 iload (1, 4)
	32 #5 (1, 4)
	33 isub (1, 4)
	34 lshl (1, 4)
	35 lastore (1, 4)
	36 iinc (1, 4)
	37 #5 (1, 4)
	38 -89 (1, 4)
	39 goto (1, 4)
	40 -30 (1, 4)
	42 iload (1, 4)
	43 #4 (1, 4)
	44 iconst_1 (1, 4)
	45 iadd (1, 4)
	46 istore (1, 4)
	47 #5 (1, 4)
	48 iload (1, 4)
	49 #5 (1, 4)
	50 bipush (1, 4)
	51 52 (1, 4)
	52 if_icmpgt (1, 4)
	53 101 (1, 4)
	55 aload_0 (1, 4)
	56 getfield (1, 4)
	57 org/apache/commons/math3/random/SobolSequenceGenerator.direction:[[J (1, 4)
	59 iload_1 (1, 4)
	60 aaload (1, 4)
	61 iload (1, 4)
	62 #5 (1, 4)
	63 aload_0 (1, 4)
	64 getfield (1, 4)
	65 org/apache/commons/math3/random/SobolSequenceGenerator.direction:[[J (1, 4)
	67 iload_1 (1, 4)
	68 aaload (1, 4)
	69 iload (1, 4)
	70 #5 (1, 4)
	71 iload (1, 4)
	72 #4 (1, 4)
	73 isub (1, 4)
	74 laload (1, 4)
	75 aload_0 (1, 4)
	76 getfield (1, 4)
	77 org/apache/commons/math3/random/SobolSequenceGenerator.direction:[[J (1, 4)
	79 iload_1 (1, 4)
	80 aaload (1, 4)
	81 iload (1, 4)
	82 #5 (1, 4)
	83 iload (1, 4)
	84 #4 (1, 4)
	85 isub (1, 4)
	86 laload (1, 4)
	87 iload (1, 4)
	88 #4 (1, 4)
	89 lshr (1, 4)
	90 lxor (1, 4)
	91 lastore (1, 4)
	92 iconst_1 (2, 4)
	93 istore (2, 4)
	94 #6 (2, 4)
	95 iload (2, 4)
	96 #6 (2, 4)
	97 iload (2, 4)
	98 #4 (2, 4)
	99 iconst_1 (2, 4)
	100 isub (2, 4)
	101 if_icmpgt (2, 4)
	102 46 (2, 4)
	104 aload_0 (2, 4)
	105 getfield (2, 4)
	106 org/apache/commons/math3/random/SobolSequenceGenerator.direction:[[J (2, 4)
	108 iload_1 (2, 4)
	109 aaload (2, 4)
	110 iload (2, 4)
	111 #5 (2, 4)
	112 dup2 (2, 4)
	113 laload (2, 4)
	114 iload_2 (2, 4)
	115 iload (2, 4)
	116 #4 (2, 4)
	117 iconst_1 (2, 4)
	118 isub (2, 4)
	119 iload (2, 4)
	120 #6 (2, 4)
	121 isub (2, 4)
	122 ishr (2, 4)
	123 iconst_1 (2, 4)
	124 iand (2, 4)
	125 i2l (2, 4)
	126 aload_0 (2, 4)
	127 getfield (2, 4)
	128 org/apache/commons/math3/random/SobolSequenceGenerator.direction:[[J (2, 4)
	130 iload_1 (2, 4)
	131 aaload (2, 4)
	132 iload (2, 4)
	133 #5 (2, 4)
	134 iload (2, 4)
	135 #6 (2, 4)
	136 isub (2, 4)
	137 laload (2, 4)
	138 lmul (2, 4)
	139 lxor (2, 4)
	140 lastore (2, 4)
	141 iinc (2, 4)
	142 #6 (2, 4)
	143 -89 (2, 4)
	144 goto (2, 4)
	145 -49 (2, 4)
	147 iinc (2, 4)
	148 #5 (2, 4)
	149 -89 (2, 4)
	150 goto (2, 4)
	151 -102 (2, 4)
	153 return (0, 0)

Method: nextVector
	0 aload_0 (0, 0)
	1 getfield (0, 0)
	2 org/apache/commons/math3/random/SobolSequenceGenerator.dimension:I (0, 0)
	4 newarray (0, 0)
	5 7 (0, 0)
	6 astore_1 (0, 0)
	7 aload_0 (1, 1)
	8 getfield (1, 1)
	9 org/apache/commons/math3/random/SobolSequenceGenerator.count:I (1, 1)
	11 ifne (1, 1)
	12 15 (1, 1)
	14 aload_0 (1, 1)
	15 dup (1, 1)
	16 getfield (1, 1)
	17 org/apache/commons/math3/random/SobolSequenceGenerator.count:I (1, 1)
	19 iconst_1 (1, 1)
	20 iadd (1, 1)
	21 putfield (1, 1)
	22 org/apache/commons/math3/random/SobolSequenceGenerator.count:I (1, 1)
	24 aload_1 (1, 1)
	25 areturn (1, 1)
	26 iconst_1 (0, 0)
	27 istore_2 (0, 0)
	28 aload_0 (0, 0)
	29 getfield (0, 0)
	30 org/apache/commons/math3/random/SobolSequenceGenerator.count:I (0, 0)
	32 iconst_1 (0, 0)
	33 isub (0, 0)
	34 istore_3 (0, 0)
	35 iload_3 (1, 3)
	36 iconst_1 (1, 3)
	37 iand (1, 3)
	38 iconst_1 (1, 3)
	39 if_icmpne (1, 3)
	40 13 (1, 3)
	42 iload_3 (1, 3)
	43 iconst_1 (1, 3)
	44 ishr (1, 3)
	45 istore_3 (1, 3)
	46 iinc (1, 3)
	47 #2 (1, 3)
	48 -89 (1, 3)
	49 goto (1, 3)
	50 -14 (1, 3)
	52 iconst_0 (1, 4)
	53 istore (1, 4)
	54 #4 (1, 4)
	55 iload (1, 4)
	56 #4 (1, 4)
	57 aload_0 (1, 4)
	58 getfield (1, 4)
	59 org/apache/commons/math3/random/SobolSequenceGenerator.dimension:I (1, 4)
	61 if_icmpge (1, 4)
	62 44 (1, 4)
	64 aload_0 (1, 4)
	65 getfield (1, 4)
	66 org/apache/commons/math3/random/SobolSequenceGenerator.x:[J (1, 4)
	68 iload (1, 4)
	69 #4 (1, 4)
	70 dup2 (1, 4)
	71 laload (1, 4)
	72 aload_0 (1, 4)
	73 getfield (1, 4)
	74 org/apache/commons/math3/random/SobolSequenceGenerator.direction:[[J (1, 4)
	76 iload (1, 4)
	77 #4 (1, 4)
	78 aaload (1, 4)
	79 iload_2 (1, 4)
	80 laload (1, 4)
	81 lxor (1, 4)
	82 lastore (1, 4)
	83 aload_1 (1, 4)
	84 iload (1, 4)
	85 #4 (1, 4)
	86 aload_0 (1, 4)
	87 getfield (1, 4)
	88 org/apache/commons/math3/random/SobolSequenceGenerator.x:[J (1, 4)
	90 iload (1, 4)
	91 #4 (1, 4)
	92 laload (1, 4)
	93 l2d (1, 4)
	94 getstatic (1, 4)
	95 org/apache/commons/math3/random/SobolSequenceGenerator.SCALE:D (1, 4)
	97 ddiv (1, 4)
	98 dastore (1, 4)
	99 iinc (1, 4)
	100 #4 (1, 4)
	101 -89 (1, 4)
	102 goto (1, 4)
	103 -47 (1, 4)
	105 aload_0 (0, 0)
	106 dup (0, 0)
	107 getfield (0, 0)
	108 org/apache/commons/math3/random/SobolSequenceGenerator.count:I (0, 0)
	110 iconst_1 (0, 0)
	111 iadd (0, 0)
	112 putfield (0, 0)
	113 org/apache/commons/math3/random/SobolSequenceGenerator.count:I (0, 0)
	115 aload_1 (0, 0)
	116 areturn (0, 0)

Method: skipTo
	0 iload_1 (1, 1)
	1 ifne (1, 1)
	2 14 (1, 1)
	4 aload_0 (1, 1)
	5 getfield (1, 1)
	6 org/apache/commons/math3/random/SobolSequenceGenerator.x:[J (1, 1)
	8 lconst_0 (1, 1)
	9 invokestatic (1, 1)
	10 java/util/Arrays.fill:([JJ)V (1, 1)
	12 goto (1, 1)
	13 102 (1, 1)
	15 iload_1 (2, 2)
	16 iconst_1 (2, 2)
	17 isub (2, 2)
	18 istore_2 (2, 2)
	19 iload_2 (2, 2)
	20 iload_2 (2, 2)
	21 iconst_1 (2, 2)
	22 ishr (2, 2)
	23 ixor (2, 2)
	24 i2l (2, 2)
	25 lstore_3 (2, 2)
	26 iconst_0 (3, 4)
	27 istore (3, 4)
	28 #5 (3, 4)
	29 iload (3, 4)
	30 #5 (3, 4)
	31 aload_0 (3, 4)
	32 getfield (3, 4)
	33 org/apache/commons/math3/random/SobolSequenceGenerator.dimension:I (3, 4)
	35 if_icmpge (3, 4)
	36 79 (3, 4)
	38 lconst_0 (3, 4)
	39 lstore (3, 4)
	40 #6 (3, 4)
	41 iconst_1 (4, 4)
	42 istore (4, 4)
	43 #8 (4, 4)
	44 iload (4, 4)
	45 #8 (4, 4)
	46 bipush (4, 4)
	47 52 (4, 4)
	48 if_icmpgt (4, 4)
	49 51 (4, 4)
	51 lload_3 (5, 1)
	52 iload (5, 1)
	53 #8 (5, 1)
	54 iconst_1 (5, 1)
	55 isub (5, 1)
	56 lshr (5, 1)
	57 lstore (5, 1)
	58 #9 (5, 1)
	59 lload (6, 1)
	60 #9 (6, 1)
	61 lconst_0 (6, 1)
	62 lcmp (6, 1)
	63 ifne (6, 1)
	64 6 (6, 1)
	66 goto (6, 1)
	67 33 (6, 1)
	69 lload (6, 1)
	70 #9 (6, 1)
	71 lconst_1 (6, 1)
	72 land (6, 1)
	73 lstore (6, 1)
	74 #11 (6, 1)
	75 lload (6, 1)
	76 #6 (6, 1)
	77 lload (6, 1)
	78 #11 (6, 1)
	79 aload_0 (6, 1)
	80 getfield (6, 1)
	81 org/apache/commons/math3/random/SobolSequenceGenerator.direction:[[J (6, 1)
	83 iload (6, 1)
	84 #5 (6, 1)
	85 aaload (6, 1)
	86 iload (6, 1)
	87 #8 (6, 1)
	88 laload (6, 1)
	89 lmul (6, 1)
	90 lxor (6, 1)
	91 lstore (6, 1)
	92 #6 (6, 1)
	93 iinc (6, 1)
	94 #8 (6, 1)
	95 -89 (6, 1)
	96 goto (6, 1)
	97 -52 (6, 1)
	99 aload_0 (3, 4)
	100 getfield (3, 4)
	101 org/apache/commons/math3/random/SobolSequenceGenerator.x:[J (3, 4)
	103 iload (3, 4)
	104 #5 (3, 4)
	105 lload (3, 4)
	106 #6 (3, 4)
	107 lastore (3, 4)
	108 iinc (3, 4)
	109 #5 (3, 4)
	110 -89 (3, 4)
	111 goto (3, 4)
	112 -82 (3, 4)
	114 aload_0 (0, 0)
	115 iload_1 (0, 0)
	116 putfield (0, 0)
	117 org/apache/commons/math3/random/SobolSequenceGenerator.count:I (0, 0)
	119 aload_0 (0, 0)
	120 invokevirtual (0, 0)
	121 org/apache/commons/math3/random/SobolSequenceGenerator.nextVector:()[D (0, 0)
	123 areturn (0, 0)

Method: getNextIndex
	0 aload_0 (0, 0)
	1 getfield (0, 0)
	2 org/apache/commons/math3/random/SobolSequenceGenerator.count:I (0, 0)
	4 ireturn (0, 0)

Method: <clinit>
	0 ldc2_w (0, 0)
	1 2.0 (0, 0)
	3 bipush (0, 0)
	4 52 (0, 0)
	5 invokestatic (0, 0)
	6 org/apache/commons/math3/util/FastMath.pow:(DI)D (0, 0)
	8 putstatic (0, 0)
	9 org/apache/commons/math3/random/SobolSequenceGenerator.SCALE:D (0, 0)
	11 return (0, 0)

