Method: <init>
	0 aload_0 (0, 0)
	1 invokespecial (0, 0)
	2 java/lang/Object.<init>:()V (0, 0)
	4 aload_1 (1, 1)
	5 ifnonnull (1, 1)
	6 11 (1, 1)
	8 new (1, 1)
	9 org/apache/commons/math3/exception/NullArgumentException (1, 1)
	11 dup (1, 1)
	12 invokespecial (1, 1)
	13 org/apache/commons/math3/exception/NullArgumentException.<init>:()V (1, 1)
	15 athrow (1, 1)
	16 dload_2 (1, 1)
	17 dconst_0 (1, 1)
	18 dcmpl (1, 1)
	19 ifle (1, 1)
	20 11 (1, 1)
	22 dload_2 (1, 1)
	23 ldc2_w (1, 1)
	24 2.0 (1, 1)
	26 dcmpg (1, 1)
	27 ifle (1, 1)
	28 26 (1, 1)
	30 new (1, 1)
	31 org/apache/commons/math3/exception/OutOfRangeException (1, 1)
	33 dup (1, 1)
	34 getstatic (1, 1)
	35 org/apache/commons/math3/exception/util/LocalizedFormats.OUT_OF_RANGE_LEFT:Lorg/apache/commons/math3/exception/util/LocalizedFormats; (1, 1)
	37 dload_2 (1, 1)
	38 invokestatic (1, 1)
	39 java/lang/Double.valueOf:(D)Ljava/lang/Double; (1, 1)
	41 iconst_0 (1, 1)
	42 invokestatic (1, 1)
	43 java/lang/Integer.valueOf:(I)Ljava/lang/Integer; (1, 1)
	45 iconst_2 (1, 1)
	46 invokestatic (1, 1)
	47 java/lang/Integer.valueOf:(I)Ljava/lang/Integer; (1, 1)
	49 invokespecial (1, 1)
	50 org/apache/commons/math3/exception/OutOfRangeException.<init>:(Lorg/apache/commons/math3/exception/util/Localizable;Ljava/lang/Number;Ljava/lang/Number;Ljava/lang/Number;)V (1, 1)
	52 athrow (1, 1)
	53 dload (1, 1)
	54 #4 (1, 1)
	55 ldc2_w (1, 1)
	56 -1.0 (1, 1)
	58 dcmpl (1, 1)
	59 iflt (1, 1)
	60 10 (1, 1)
	62 dload (1, 1)
	63 #4 (1, 1)
	64 dconst_1 (1, 1)
	65 dcmpg (1, 1)
	66 ifle (1, 1)
	67 27 (1, 1)
	69 new (1, 1)
	70 org/apache/commons/math3/exception/OutOfRangeException (1, 1)
	72 dup (1, 1)
	73 getstatic (1, 1)
	74 org/apache/commons/math3/exception/util/LocalizedFormats.OUT_OF_RANGE_SIMPLE:Lorg/apache/commons/math3/exception/util/LocalizedFormats; (1, 1)
	76 dload (1, 1)
	77 #4 (1, 1)
	78 invokestatic (1, 1)
	79 java/lang/Double.valueOf:(D)Ljava/lang/Double; (1, 1)
	81 iconst_m1 (1, 1)
	82 invokestatic (1, 1)
	83 java/lang/Integer.valueOf:(I)Ljava/lang/Integer; (1, 1)
	85 iconst_1 (1, 1)
	86 invokestatic (1, 1)
	87 java/lang/Integer.valueOf:(I)Ljava/lang/Integer; (1, 1)
	89 invokespecial (1, 1)
	90 org/apache/commons/math3/exception/OutOfRangeException.<init>:(Lorg/apache/commons/math3/exception/util/Localizable;Ljava/lang/Number;Ljava/lang/Number;Ljava/lang/Number;)V (1, 1)
	92 athrow (1, 1)
	93 aload_0 (0, 0)
	94 aload_1 (0, 0)
	95 putfield (0, 0)
	96 org/apache/commons/math3/random/StableRandomGenerator.generator:Lorg/apache/commons/math3/random/RandomGenerator; (0, 0)
	98 aload_0 (0, 0)
	99 dload_2 (0, 0)
	100 putfield (0, 0)
	101 org/apache/commons/math3/random/StableRandomGenerator.alpha:D (0, 0)
	103 aload_0 (0, 0)
	104 dload (0, 0)
	105 #4 (0, 0)
	106 putfield (0, 0)
	107 org/apache/commons/math3/random/StableRandomGenerator.beta:D (0, 0)
	109 dload_2 (1, 1)
	110 ldc2_w (1, 1)
	111 2.0 (1, 1)
	113 dcmpg (1, 1)
	114 ifge (1, 1)
	115 32 (1, 1)
	117 dload (1, 1)
	118 #4 (1, 1)
	119 dconst_0 (1, 1)
	120 dcmpl (1, 1)
	121 ifeq (1, 1)
	122 25 (1, 1)
	124 aload_0 (1, 1)
	125 dload (1, 1)
	126 #4 (1, 1)
	127 ldc2_w (1, 1)
	128 3.141592653589793 (1, 1)
	130 dload_2 (1, 1)
	131 dmul (1, 1)
	132 ldc2_w (1, 1)
	133 2.0 (1, 1)
	135 ddiv (1, 1)
	136 invokestatic (1, 1)
	137 org/apache/commons/math3/util/FastMath.tan:(D)D (1, 1)
	139 dmul (1, 1)
	140 putfield (1, 1)
	141 org/apache/commons/math3/random/StableRandomGenerator.zeta:D (1, 1)
	143 goto (1, 1)
	144 8 (1, 1)
	146 aload_0 (2, 2)
	147 dconst_0 (2, 2)
	148 putfield (2, 2)
	149 org/apache/commons/math3/random/StableRandomGenerator.zeta:D (2, 2)
	151 return (0, 0)

Method: nextNormalizedDouble
	0 aload_0 (0, 0)
	1 getfield (0, 0)
	2 org/apache/commons/math3/random/StableRandomGenerator.generator:Lorg/apache/commons/math3/random/RandomGenerator; (0, 0)
	4 invokeinterface (0, 0)
	5 org/apache/commons/math3/random/RandomGenerator.log:(D)D (0, 0)
	7 0 (0, 0)
	9 invokestatic (0, 0)
	10 org/apache/commons/math3/util/FastMath.log:(D)D (0, 0)
	12 dneg (0, 0)
	13 dstore_1 (0, 0)
	14 ldc2_w (0, 0)
	15 3.141592653589793 (0, 0)
	17 aload_0 (0, 0)
	18 getfield (0, 0)
	19 org/apache/commons/math3/random/StableRandomGenerator.generator:Lorg/apache/commons/math3/random/RandomGenerator; (0, 0)
	21 invokeinterface (0, 0)
	22 org/apache/commons/math3/random/RandomGenerator.log:(D)D (0, 0)
	24 0 (0, 0)
	26 ldc2_w (0, 0)
	27 0.5 (0, 0)
	29 dsub (0, 0)
	30 dmul (0, 0)
	31 dstore_3 (0, 0)
	32 aload_0 (1, 1)
	33 getfield (1, 1)
	34 org/apache/commons/math3/random/StableRandomGenerator.alpha:D (1, 1)
	36 ldc2_w (1, 1)
	37 2.0 (1, 1)
	39 dcmpl (1, 1)
	40 ifne (1, 1)
	41 17 (1, 1)
	43 ldc2_w (1, 1)
	44 2.0 (1, 1)
	46 dload_1 (1, 1)
	47 dmul (1, 1)
	48 invokestatic (1, 1)
	49 org/apache/commons/math3/util/FastMath.sqrt:(D)D (1, 1)
	51 dload_3 (1, 1)
	52 invokestatic (1, 1)
	53 org/apache/commons/math3/util/FastMath.sin:(D)D (1, 1)
	55 dmul (1, 1)
	56 dreturn (1, 1)
	57 aload_0 (2, 1)
	58 getfield (2, 1)
	59 org/apache/commons/math3/random/StableRandomGenerator.beta:D (2, 1)
	61 dconst_0 (2, 1)
	62 dcmpl (2, 1)
	63 ifne (2, 1)
	64 74 (2, 1)
	66 aload_0 (3, 1)
	67 getfield (3, 1)
	68 org/apache/commons/math3/random/StableRandomGenerator.alpha:D (3, 1)
	70 dconst_1 (3, 1)
	71 dcmpl (3, 1)
	72 ifne (3, 1)
	73 12 (3, 1)
	75 dload_3 (3, 1)
	76 invokestatic (3, 1)
	77 org/apache/commons/math3/util/FastMath.tan:(D)D (3, 1)
	79 dstore (3, 1)
	80 #5 (3, 1)
	81 goto (3, 1)
	82 231 (3, 1)
	84 dload_1 (4, 2)
	85 dconst_1 (4, 2)
	86 aload_0 (4, 2)
	87 getfield (4, 2)
	88 org/apache/commons/math3/random/StableRandomGenerator.alpha:D (4, 2)
	90 dsub (4, 2)
	91 dload_3 (4, 2)
	92 dmul (4, 2)
	93 invokestatic (4, 2)
	94 org/apache/commons/math3/util/FastMath.cos:(D)D (4, 2)
	96 dmul (4, 2)
	97 dconst_1 (4, 2)
	98 aload_0 (4, 2)
	99 getfield (4, 2)
	100 org/apache/commons/math3/random/StableRandomGenerator.alpha:D (4, 2)
	102 ddiv (4, 2)
	103 dconst_1 (4, 2)
	104 dsub (4, 2)
	105 invokestatic (4, 2)
	106 org/apache/commons/math3/util/FastMath.pow:(DD)D (4, 2)
	108 aload_0 (4, 2)
	109 getfield (4, 2)
	110 org/apache/commons/math3/random/StableRandomGenerator.alpha:D (4, 2)
	112 dload_3 (4, 2)
	113 dmul (4, 2)
	114 invokestatic (4, 2)
	115 org/apache/commons/math3/util/FastMath.sin:(D)D (4, 2)
	117 dmul (4, 2)
	118 dload_3 (4, 2)
	119 invokestatic (4, 2)
	120 org/apache/commons/math3/util/FastMath.cos:(D)D (4, 2)
	122 dconst_1 (4, 2)
	123 aload_0 (4, 2)
	124 getfield (4, 2)
	125 org/apache/commons/math3/random/StableRandomGenerator.alpha:D (4, 2)
	127 ddiv (4, 2)
	128 invokestatic (4, 2)
	129 org/apache/commons/math3/util/FastMath.pow:(DD)D (4, 2)
	131 ddiv (4, 2)
	132 dstore (4, 2)
	133 #5 (4, 2)
	134 goto (4, 2)
	135 178 (4, 2)
	137 dload_3 (3, 2)
	138 invokestatic (3, 2)
	139 org/apache/commons/math3/util/FastMath.cos:(D)D (3, 2)
	141 dstore (3, 2)
	142 #7 (3, 2)
	143 aload_0 (4, 1)
	144 getfield (4, 1)
	145 org/apache/commons/math3/random/StableRandomGenerator.alpha:D (4, 1)
	147 dconst_1 (4, 1)
	148 dsub (4, 1)
	149 invokestatic (4, 1)
	150 org/apache/commons/math3/util/FastMath.abs:(D)D (4, 1)
	152 ldc2_w (4, 1)
	153 1e-08 (4, 1)
	155 dcmpl (4, 1)
	156 ifle (4, 1)
	157 77 (4, 1)
	159 aload_0 (4, 1)
	160 getfield (4, 1)
	161 org/apache/commons/math3/random/StableRandomGenerator.alpha:D (4, 1)
	163 dload_3 (4, 1)
	164 dmul (4, 1)
	165 dstore (4, 1)
	166 #9 (4, 1)
	167 dload_3 (4, 1)
	168 dload (4, 1)
	169 #9 (4, 1)
	170 dsub (4, 1)
	171 dstore (4, 1)
	172 #11 (4, 1)
	173 dload (4, 1)
	174 #9 (4, 1)
	175 invokestatic (4, 1)
	176 org/apache/commons/math3/util/FastMath.sin:(D)D (4, 1)
	178 aload_0 (4, 1)
	179 getfield (4, 1)
	180 org/apache/commons/math3/random/StableRandomGenerator.zeta:D (4, 1)
	182 dload (4, 1)
	183 #9 (4, 1)
	184 invokestatic (4, 1)
	185 org/apache/commons/math3/util/FastMath.cos:(D)D (4, 1)
	187 dmul (4, 1)
	188 dadd (4, 1)
	189 dload (4, 1)
	190 #7 (4, 1)
	191 ddiv (4, 1)
	192 dload (4, 1)
	193 #11 (4, 1)
	194 invokestatic (4, 1)
	195 org/apache/commons/math3/util/FastMath.cos:(D)D (4, 1)
	197 aload_0 (4, 1)
	198 getfield (4, 1)
	199 org/apache/commons/math3/random/StableRandomGenerator.zeta:D (4, 1)
	201 dload (4, 1)
	202 #11 (4, 1)
	203 invokestatic (4, 1)
	204 org/apache/commons/math3/util/FastMath.sin:(D)D (4, 1)
	206 dmul (4, 1)
	207 dadd (4, 1)
	208 dmul (4, 1)
	209 dload_1 (4, 1)
	210 dload (4, 1)
	211 #7 (4, 1)
	212 dmul (4, 1)
	213 dconst_1 (4, 1)
	214 aload_0 (4, 1)
	215 getfield (4, 1)
	216 org/apache/commons/math3/random/StableRandomGenerator.alpha:D (4, 1)
	218 dsub (4, 1)
	219 aload_0 (4, 1)
	220 getfield (4, 1)
	221 org/apache/commons/math3/random/StableRandomGenerator.alpha:D (4, 1)
	223 ddiv (4, 1)
	224 invokestatic (4, 1)
	225 org/apache/commons/math3/util/FastMath.pow:(DD)D (4, 1)
	227 ddiv (4, 1)
	228 dstore (4, 1)
	229 #5 (4, 1)
	230 goto (5, 2)
	231 82 (5, 2)
	233 ldc2_w (5, 2)
	234 1.5707963267948966 (5, 2)
	236 aload_0 (5, 2)
	237 getfield (5, 2)
	238 org/apache/commons/math3/random/StableRandomGenerator.beta:D (5, 2)
	240 dload_3 (5, 2)
	241 dmul (5, 2)
	242 dadd (5, 2)
	243 dstore (5, 2)
	244 #9 (5, 2)
	245 ldc2_w (5, 2)
	246 0.6366197723675814 (5, 2)
	248 dload (5, 2)
	249 #9 (5, 2)
	250 dload_3 (5, 2)
	251 invokestatic (5, 2)
	252 org/apache/commons/math3/util/FastMath.tan:(D)D (5, 2)
	254 dmul (5, 2)
	255 aload_0 (5, 2)
	256 getfield (5, 2)
	257 org/apache/commons/math3/random/StableRandomGenerator.beta:D (5, 2)
	259 ldc2_w (5, 2)
	260 1.5707963267948966 (5, 2)
	262 dload_1 (5, 2)
	263 dmul (5, 2)
	264 dload (5, 2)
	265 #7 (5, 2)
	266 dmul (5, 2)
	267 dload (5, 2)
	268 #9 (5, 2)
	269 ddiv (5, 2)
	270 invokestatic (5, 2)
	271 org/apache/commons/math3/util/FastMath.log:(D)D (5, 2)
	273 dmul (5, 2)
	274 dsub (5, 2)
	275 dmul (5, 2)
	276 dstore (5, 2)
	277 #5 (5, 2)
	278 aload_0 (6, 1)
	279 getfield (6, 1)
	280 org/apache/commons/math3/random/StableRandomGenerator.alpha:D (6, 1)
	282 dconst_1 (6, 1)
	283 dcmpl (6, 1)
	284 ifeq (6, 1)
	285 28 (6, 1)
	287 dload (6, 1)
	288 #5 (6, 1)
	289 aload_0 (6, 1)
	290 getfield (6, 1)
	291 org/apache/commons/math3/random/StableRandomGenerator.beta:D (6, 1)
	293 ldc2_w (6, 1)
	294 3.141592653589793 (6, 1)
	296 aload_0 (6, 1)
	297 getfield (6, 1)
	298 org/apache/commons/math3/random/StableRandomGenerator.alpha:D (6, 1)
	300 dmul (6, 1)
	301 ldc2_w (6, 1)
	302 2.0 (6, 1)
	304 ddiv (6, 1)
	305 invokestatic (6, 1)
	306 org/apache/commons/math3/util/FastMath.tan:(D)D (6, 1)
	308 dmul (6, 1)
	309 dadd (6, 1)
	310 dstore (6, 1)
	311 #5 (6, 1)
	312 dload (1, 4)
	313 #5 (1, 4)
	314 dreturn (0, 4)

