Method: <init>
	0 aload_0 (0, 0)
	1 invokespecial (0, 0)
	2 java/lang/Object.<init>:()V (0, 0)
	4 aload_0 (0, 0)
	5 iload_1 (0, 0)
	6 newarray (0, 0)
	7 7 (0, 0)
	8 putfield (0, 0)
	9 org/apache/commons/math3/random/UncorrelatedRandomVectorGenerator.mean:[D (0, 0)
	11 aload_0 (0, 0)
	12 iload_1 (0, 0)
	13 newarray (0, 0)
	14 7 (0, 0)
	15 putfield (0, 0)
	16 org/apache/commons/math3/random/UncorrelatedRandomVectorGenerator.standardDeviation:[D (0, 0)
	18 aload_0 (0, 0)
	19 getfield (0, 0)
	20 org/apache/commons/math3/random/UncorrelatedRandomVectorGenerator.standardDeviation:[D (0, 0)
	22 dconst_1 (0, 0)
	23 invokestatic (0, 0)
	24 java/util/Arrays.fill:([DD)V (0, 0)
	26 aload_0 (0, 0)
	27 aload_2 (0, 0)
	28 putfield (0, 0)
	29 org/apache/commons/math3/random/UncorrelatedRandomVectorGenerator.generator:Lorg/apache/commons/math3/random/NormalizedRandomGenerator; (0, 0)
	31 return (0, 0)

Method: nextVector
	0 aload_0 (0, 0)
	1 getfield (0, 0)
	2 org/apache/commons/math3/random/UncorrelatedRandomVectorGenerator.mean:[D (0, 0)
	4 arraylength (0, 0)
	5 newarray (0, 0)
	6 7 (0, 0)
	7 astore_1 (0, 0)
	8 iconst_0 (1, 4)
	9 istore_2 (1, 4)
	10 iload_2 (1, 4)
	11 aload_1 (1, 4)
	12 arraylength (1, 4)
	13 if_icmpge (1, 4)
	14 35 (1, 4)
	16 aload_1 (1, 4)
	17 iload_2 (1, 4)
	18 aload_0 (1, 4)
	19 getfield (1, 4)
	20 org/apache/commons/math3/random/UncorrelatedRandomVectorGenerator.mean:[D (1, 4)
	22 iload_2 (1, 4)
	23 daload (1, 4)
	24 aload_0 (1, 4)
	25 getfield (1, 4)
	26 org/apache/commons/math3/random/UncorrelatedRandomVectorGenerator.standardDeviation:[D (1, 4)
	28 iload_2 (1, 4)
	29 daload (1, 4)
	30 aload_0 (1, 4)
	31 getfield (1, 4)
	32 org/apache/commons/math3/random/UncorrelatedRandomVectorGenerator.generator:Lorg/apache/commons/math3/random/NormalizedRandomGenerator; (1, 4)
	34 invokeinterface (1, 4)
	35 org/apache/commons/math3/random/NormalizedRandomGenerator.org/apache/commons/math3/random/UncorrelatedRandomVectorGenerator (1, 4)
	37 0 (1, 4)
	39 dmul (1, 4)
	40 dadd (1, 4)
	41 dastore (1, 4)
	42 iinc (1, 4)
	43 #2 (1, 4)
	44 -89 (1, 4)
	45 goto (1, 4)
	46 -35 (1, 4)
	48 aload_1 (0, 0)
	49 areturn (0, 0)

