Method: <init>
	0 aload_0 (0, 0)
	1 iload_1 (0, 0)
	2 new (0, 0)
	3 org/apache/commons/math3/random/MersenneTwister (0, 0)
	5 dup (0, 0)
	6 invokespecial (0, 0)
	7 org/apache/commons/math3/random/MersenneTwister.<init>:()V (0, 0)
	9 invokespecial (0, 0)
	10 org/apache/commons/math3/random/UnitSphereRandomVectorGenerator.<init>:(ILorg/apache/commons/math3/random/RandomGenerator;)V (0, 0)
	12 return (0, 0)

Method: nextVector
	0 aload_0 (0, 0)
	1 getfield (0, 0)
	2 org/apache/commons/math3/random/UnitSphereRandomVectorGenerator.dimension:I (0, 0)
	4 newarray (0, 0)
	5 7 (0, 0)
	6 astore_1 (0, 0)
	7 dconst_0 (0, 4)
	8 dstore_2 (0, 4)
	9 iconst_0 (1, 4)
	10 istore (1, 4)
	11 #4 (1, 4)
	12 iload (1, 4)
	13 #4 (1, 4)
	14 aload_0 (1, 4)
	15 getfield (1, 4)
	16 org/apache/commons/math3/random/UnitSphereRandomVectorGenerator.dimension:I (1, 4)
	18 if_icmpge (1, 4)
	19 34 (1, 4)
	21 aload_0 (1, 4)
	22 getfield (1, 4)
	23 org/apache/commons/math3/random/UnitSphereRandomVectorGenerator.rand:Lorg/apache/commons/math3/random/RandomGenerator; (1, 4)
	25 invokeinterface (1, 4)
	26 org/apache/commons/math3/random/RandomGenerator.org/apache/commons/math3/util/FastMath (1, 4)
	28 0 (1, 4)
	30 dstore (1, 4)
	31 #5 (1, 4)
	32 aload_1 (1, 4)
	33 iload (1, 4)
	34 #4 (1, 4)
	35 dload (1, 4)
	36 #5 (1, 4)
	37 dastore (1, 4)
	38 dload_2 (1, 4)
	39 dload (1, 4)
	40 #5 (1, 4)
	41 dload (1, 4)
	42 #5 (1, 4)
	43 dmul (1, 4)
	44 dadd (1, 4)
	45 dstore_2 (1, 4)
	46 iinc (1, 4)
	47 #4 (1, 4)
	48 -89 (1, 4)
	49 goto (1, 4)
	50 -37 (1, 4)
	52 dconst_1 (0, 4)
	53 dload_2 (0, 4)
	54 invokestatic (0, 4)
	55 org/apache/commons/math3/util/FastMath.sqrt:(D)D (0, 4)
	57 ddiv (0, 4)
	58 dstore (0, 4)
	59 #4 (0, 4)
	60 iconst_0 (1, 4)
	61 istore (1, 4)
	62 #6 (1, 4)
	63 iload (1, 4)
	64 #6 (1, 4)
	65 aload_0 (1, 4)
	66 getfield (1, 4)
	67 org/apache/commons/math3/random/UnitSphereRandomVectorGenerator.dimension:I (1, 4)
	69 if_icmpge (1, 4)
	70 18 (1, 4)
	72 aload_1 (1, 4)
	73 iload (1, 4)
	74 #6 (1, 4)
	75 dup2 (1, 4)
	76 daload (1, 4)
	77 dload (1, 4)
	78 #4 (1, 4)
	79 dmul (1, 4)
	80 dastore (1, 4)
	81 iinc (1, 4)
	82 #6 (1, 4)
	83 -89 (1, 4)
	84 goto (1, 4)
	85 -21 (1, 4)
	87 aload_1 (0, 4)
	88 areturn (0, 4)

