Method: <init>
	0 aload_0 (0, 0)
	1 invokespecial (0, 0)
	4 aload_0 (0, 0)
	5 iconst_5 (0, 0)
	6 putfield (0, 0)
	9 aload_0 (0, 0)
	10 aconst_null (0, 0)
	11 putfield (0, 0)
	14 aload_0 (0, 4)
	15 dconst_0 (0, 4)
	16 putfield (0, 4)
	19 aload_0 (0, 4)
	20 dconst_0 (0, 4)
	21 putfield (0, 4)
	24 aload_0 (0, 4)
	25 aconst_null (0, 4)
	26 putfield (0, 4)
	29 aload_0 (0, 4)
	30 aconst_null (0, 4)
	31 putfield (0, 4)
	34 aload_0 (1, 4)
	35 new (1, 4)
	38 dup (1, 4)
	39 aload_1 (1, 4)
	40 invokespecial (1, 4)
	43 putfield (1, 4)
	46 return (0, 4)

Method: getNext
	0 aload_0 (1, 5)
	1 getfield (1, 5)
	4 tableswitch (1, 5)
	44 aload_0 (1, 5)
	45 invokespecial (1, 5)
	48 dreturn (1, 5)
	49 aload_0 (1, 5)
	50 invokespecial (1, 5)
	53 dreturn (1, 5)
	54 aload_0 (1, 1)
	55 invokespecial (1, 1)
	58 dreturn (1, 1)
	59 aload_0 (1, 1)
	60 invokespecial (1, 1)
	63 dreturn (1, 1)
	64 aload_0 (1, 1)
	65 invokespecial (1, 1)
	68 dreturn (1, 1)
	69 aload_0 (1, 1)
	70 getfield (1, 1)
	73 dreturn (1, 1)
	74 new (1, 1)
	77 dup (1, 1)
	78 getstatic (1, 1)
	81 bipush (1, 1)
	83 anewarray (1, 1)
	86 dup (1, 1)
	87 iconst_0 (1, 1)
	88 aload_0 (1, 1)
	89 getfield (1, 1)
	92 invokestatic (1, 1)
	95 aastore (1, 1)
	96 dup (1, 1)
	97 iconst_1 (1, 1)
	98 ldc (1, 1)
	100 aastore (1, 1)
	101 dup (1, 1)
	102 iconst_2 (1, 1)
	103 iconst_0 (1, 1)
	104 invokestatic (1, 1)
	107 aastore (1, 1)
	108 dup (1, 1)
	109 iconst_3 (1, 1)
	110 ldc (1, 1)
	112 aastore (1, 1)
	113 dup (1, 1)
	114 iconst_4 (1, 1)
	115 iconst_1 (1, 1)
	116 invokestatic (1, 1)
	119 aastore (1, 1)
	120 dup (1, 1)
	121 iconst_5 (1, 1)
	122 ldc (1, 1)
	124 aastore (1, 1)
	125 dup (1, 1)
	126 bipush (1, 1)
	128 iconst_2 (1, 1)
	129 invokestatic (1, 1)
	132 aastore (1, 1)
	133 dup (1, 1)
	134 bipush (1, 1)
	136 ldc (1, 1)
	138 aastore (1, 1)
	139 dup (1, 1)
	140 bipush (1, 1)
	142 iconst_3 (1, 1)
	143 invokestatic (1, 1)
	146 aastore (1, 1)
	147 dup (1, 1)
	148 bipush (1, 1)
	150 ldc (1, 1)
	152 aastore (1, 1)
	153 dup (1, 1)
	154 bipush (1, 1)
	156 iconst_4 (1, 1)
	157 invokestatic (1, 1)
	160 aastore (1, 1)
	161 dup (1, 1)
	162 bipush (1, 1)
	164 ldc (1, 1)
	166 aastore (1, 1)
	167 dup (1, 1)
	168 bipush (1, 1)
	170 iconst_5 (1, 1)
	171 invokestatic (1, 1)
	174 aastore (1, 1)
	175 invokespecial (1, 1)
	178 athrow (1, 1)

Method: fill
	0 iload_1 (0, 0)
	1 newarray (0, 0)
	3 astore_2 (0, 0)
	4 iconst_0 (1, 4)
	5 istore_3 (1, 4)
	6 iload_3 (1, 4)
	7 iload_1 (1, 4)
	8 if_icmpge (1, 4)
	11 aload_2 (1, 4)
	12 iload_3 (1, 4)
	13 aload_0 (1, 4)
	14 invokevirtual (1, 4)
	17 dastore (1, 4)
	18 iinc (1, 4)
	21 goto (1, 4)
	24 aload_2 (0, 0)
	25 areturn (0, 0)

Method: computeDistribution
	0 aload_0 (0, 0)
	1 new (0, 0)
	4 dup (0, 0)
	5 iload_1 (0, 0)
	6 aload_0 (0, 0)
	7 getfield (0, 0)
	10 invokevirtual (0, 0)
	13 invokespecial (0, 0)
	16 putfield (0, 0)
	19 aload_0 (0, 0)
	20 getfield (0, 0)
	23 aload_0 (0, 0)
	24 getfield (0, 0)
	27 invokevirtual (0, 0)
	30 aload_0 (0, 0)
	31 aload_0 (0, 0)
	32 getfield (0, 0)
	35 invokevirtual (0, 0)
	38 invokeinterface (0, 0)
	43 putfield (0, 0)
	46 aload_0 (0, 0)
	47 aload_0 (0, 0)
	48 getfield (0, 0)
	51 invokevirtual (0, 0)
	54 invokeinterface (0, 0)
	59 putfield (0, 0)
	62 return (0, 0)

Method: getMode
	0 aload_0 (0, 0)
	1 getfield (0, 0)
	4 ireturn (0, 0)

Method: setMode
	0 aload_0 (0, 0)
	1 iload_1 (0, 0)
	2 putfield (0, 0)
	5 return (0, 0)

Method: getValuesFileURL
	0 aload_0 (0, 0)
	1 getfield (0, 0)
	4 areturn (0, 0)

Method: setValuesFileURL
	0 aload_0 (0, 0)
	1 aload_1 (0, 0)
	2 putfield (0, 0)
	5 return (0, 0)

Method: getEmpiricalDistribution
	0 aload_0 (0, 0)
	1 getfield (0, 0)
	4 areturn (0, 0)

Method: resetReplayFile
	0 aload_0 (1, 1)
	1 getfield (1, 1)
	4 ifnull (1, 1)
	7 aload_0 (2, 1)
	8 getfield (2, 1)
	11 invokevirtual (2, 1)
	14 aload_0 (2, 1)
	15 aconst_null (2, 1)
	16 putfield (2, 1)
	19 goto (1, 0)
	22 astore_1 (1, 0)
	23 aload_0 (1, 0)
	24 new (1, 0)
	27 dup (1, 0)
	28 new (1, 0)
	31 dup (1, 0)
	32 aload_0 (1, 0)
	33 getfield (1, 0)
	36 invokevirtual (1, 0)
	39 ldc (1, 0)
	41 invokespecial (1, 0)
	44 invokespecial (1, 0)
	47 putfield (1, 0)
	50 return (1, 0)

Method: closeReplayFile
	0 aload_0 (1, 1)
	1 getfield (1, 1)
	4 ifnull (1, 1)
	7 aload_0 (1, 1)
	8 getfield (1, 1)
	11 invokevirtual (1, 1)
	14 aload_0 (1, 1)
	15 aconst_null (1, 1)
	16 putfield (1, 1)
	19 return (0, 0)

Method: getMu
	0 aload_0 (0, 0)
	1 getfield (0, 0)
	4 dreturn (0, 0)

Method: setMu
	0 aload_0 (0, 0)
	1 dload_1 (0, 0)
	2 putfield (0, 0)
	5 return (0, 0)

Method: getSigma
	0 aload_0 (0, 0)
	1 getfield (0, 0)
	4 dreturn (0, 0)

Method: setSigma
	0 aload_0 (0, 0)
	1 dload_1 (0, 0)
	2 putfield (0, 0)
	5 return (0, 0)

Method: reSeed
	0 aload_0 (0, 0)
	1 getfield (0, 0)
	4 lload_1 (0, 0)
	5 invokevirtual (0, 0)
	8 return (0, 0)

Method: getNextDigest
	0 aload_0 (0, 1)
	1 getfield (0, 1)
	4 ifnull (0, 1)
	7 aload_0 (0, 1)
	8 getfield (0, 1)
	11 invokevirtual (1, 1)
	14 invokeinterface (1, 1)
	19 ifne (1, 1)
	22 new (1, 1)
	25 dup (1, 1)
	26 getstatic (1, 1)
	29 iconst_0 (1, 1)
	30 anewarray (1, 1)
	33 invokespecial (1, 1)
	36 athrow (1, 1)
	37 aload_0 (0, 0)
	38 getfield (0, 0)
	41 invokevirtual (0, 0)
	44 dreturn (0, 0)

Method: getNextReplay
	0 aconst_null (0, 0)
	1 astore_1 (0, 0)
	2 aload_0 (1, 1)
	3 getfield (1, 1)
	6 ifnonnull (1, 1)
	9 aload_0 (1, 1)
	10 invokevirtual (1, 1)
	13 aload_0 (1, 1)
	14 getfield (1, 1)
	17 invokevirtual (1, 1)
	20 dup (1, 1)
	21 astore_1 (1, 1)
	22 ifnonnull (1, 1)
	25 aload_0 (1, 1)
	26 invokevirtual (1, 1)
	29 aload_0 (1, 1)
	30 invokevirtual (1, 1)
	33 aload_0 (2, 1)
	34 getfield (2, 1)
	37 invokevirtual (2, 1)
	40 dup (2, 1)
	41 astore_1 (2, 1)
	42 ifnonnull (2, 1)
	45 new (2, 1)
	48 dup (2, 1)
	49 getstatic (2, 1)
	52 iconst_1 (2, 1)
	53 anewarray (2, 1)
	56 dup (2, 1)
	57 iconst_0 (2, 1)
	58 aload_0 (2, 1)
	59 getfield (2, 1)
	62 aastore (2, 1)
	63 invokespecial (2, 1)
	66 athrow (2, 1)
	67 aload_1 (0, 0)
	68 invokestatic (0, 0)
	71 dreturn (0, 0)

Method: getNextUniform
	0 aload_0 (0, 1)
	1 getfield (0, 1)
	4 dconst_0 (0, 1)
	5 ldc2_w (0, 1)
	8 aload_0 (0, 1)
	9 getfield (0, 1)
	12 dmul (0, 1)
	13 invokevirtual (0, 1)
	16 dreturn (0, 1)

Method: getNextExponential
	0 aload_0 (0, 0)
	1 getfield (0, 0)
	4 aload_0 (0, 0)
	5 getfield (0, 0)
	8 invokevirtual (0, 0)
	11 dreturn (0, 0)

Method: getNextGaussian
	0 aload_0 (0, 0)
	1 getfield (0, 0)
	4 aload_0 (0, 0)
	5 getfield (0, 0)
	8 aload_0 (0, 0)
	9 getfield (0, 0)
	12 invokevirtual (0, 0)
	15 dreturn (0, 0)

