Method: <init>
	0 aload_0 (0, 0)
	1 invokespecial (0, 0)
	2 java/lang/Object.<init>:()V (0, 0)
	4 aload_0 (0, 0)
	5 iconst_5 (0, 0)
	6 putfield (0, 0)
	7 org/apache/commons/math3/random/ValueServer.mode:I (0, 0)
	9 aload_0 (0, 0)
	10 aconst_null (0, 0)
	11 putfield (0, 0)
	12 org/apache/commons/math3/random/ValueServer.valuesFileURL:Ljava/net/URL; (0, 0)
	14 aload_0 (1, 4)
	15 dconst_0 (1, 4)
	16 putfield (1, 4)
	17 org/apache/commons/math3/random/ValueServer.mu:D (1, 4)
	19 aload_0 (2, 4)
	20 dconst_0 (2, 4)
	21 putfield (2, 4)
	22 org/apache/commons/math3/random/ValueServer.sigma:D (2, 4)
	24 aload_0 (3, 4)
	25 aconst_null (3, 4)
	26 putfield (3, 4)
	27 org/apache/commons/math3/random/ValueServer.empiricalDistribution:Lorg/apache/commons/math3/random/EmpiricalDistribution; (3, 4)
	29 aload_0 (4, 4)
	30 aconst_null (4, 4)
	31 putfield (4, 4)
	32 org/apache/commons/math3/random/ValueServer.filePointer:Ljava/io/BufferedReader; (4, 4)
	34 aload_0 (5, 4)
	35 new (5, 4)
	36 org/apache/commons/math3/random/RandomDataGenerator (5, 4)
	38 dup (5, 4)
	39 aload_1 (5, 4)
	40 invokespecial (5, 4)
	41 org/apache/commons/math3/random/RandomDataGenerator.<init>:(Lorg/apache/commons/math3/random/RandomGenerator;)V (5, 4)
	43 putfield (5, 4)
	44 org/apache/commons/math3/random/ValueServer.randomData:Lorg/apache/commons/math3/random/RandomDataGenerator; (5, 4)
	46 return (1, 4)

Method: getNext
	0 aload_0 (1, 5)
	1 getfield (1, 5)
	2 org/apache/commons/math3/random/ValueServer.mode:I (1, 5)
	4 tableswitch (1, 5)
	5 0 44 (1, 5)
	9 1 49 (1, 5)
	13 2 54 (1, 5)
	17 3 59 (1, 5)
	21 4 64 (1, 5)
	25 5 69 (1, 5)
	44 aload_0 (1, 5)
	45 invokespecial (1, 5)
	46 org/apache/commons/math3/random/ValueServer.getNextDigest:()D (1, 5)
	48 dreturn (1, 5)
	49 aload_0 (1, 5)
	50 invokespecial (1, 5)
	51 org/apache/commons/math3/random/ValueServer.getNextReplay:()D (1, 5)
	53 dreturn (1, 5)
	54 aload_0 (2, 1)
	55 invokespecial (2, 1)
	56 org/apache/commons/math3/random/ValueServer.getNextUniform:()D (2, 1)
	58 dreturn (2, 1)
	59 aload_0 (2, 1)
	60 invokespecial (2, 1)
	61 org/apache/commons/math3/random/ValueServer.getNextExponential:()D (2, 1)
	63 dreturn (2, 1)
	64 aload_0 (2, 1)
	65 invokespecial (2, 1)
	66 org/apache/commons/math3/random/ValueServer.getNextGaussian:()D (2, 1)
	68 dreturn (2, 1)
	69 aload_0 (2, 1)
	70 getfield (2, 1)
	71 org/apache/commons/math3/random/ValueServer.mu:D (2, 1)
	73 dreturn (2, 1)
	74 new (2, 1)
	75 org/apache/commons/math3/exception/MathIllegalStateException (2, 1)
	77 dup (2, 1)
	78 getstatic (2, 1)
	79 org/apache/commons/math3/exception/util/LocalizedFormats.UNKNOWN_MODE:Lorg/apache/commons/math3/exception/util/LocalizedFormats; (2, 1)
	81 bipush (2, 1)
	82 13 (2, 1)
	83 anewarray (2, 1)
	84 java/lang/Object (2, 1)
	86 dup (2, 1)
	87 iconst_0 (2, 1)
	88 aload_0 (2, 1)
	89 getfield (2, 1)
	90 org/apache/commons/math3/random/ValueServer.mode:I (2, 1)
	92 invokestatic (2, 1)
	93 java/lang/Integer.valueOf:(I)Ljava/lang/Integer; (2, 1)
	95 aastore (2, 1)
	96 dup (2, 1)
	97 iconst_1 (2, 1)
	98 ldc (2, 1)
	99 DIGEST_MODE (2, 1)
	100 aastore (2, 1)
	101 dup (2, 1)
	102 iconst_2 (2, 1)
	103 iconst_0 (2, 1)
	104 invokestatic (2, 1)
	105 java/lang/Integer.valueOf:(I)Ljava/lang/Integer; (2, 1)
	107 aastore (2, 1)
	108 dup (2, 1)
	109 iconst_3 (2, 1)
	110 ldc (2, 1)
	111 REPLAY_MODE (2, 1)
	112 aastore (2, 1)
	113 dup (2, 1)
	114 iconst_4 (2, 1)
	115 iconst_1 (2, 1)
	116 invokestatic (2, 1)
	117 java/lang/Integer.valueOf:(I)Ljava/lang/Integer; (2, 1)
	119 aastore (2, 1)
	120 dup (2, 1)
	121 iconst_5 (2, 1)
	122 ldc (2, 1)
	123 UNIFORM_MODE (2, 1)
	124 aastore (2, 1)
	125 dup (2, 1)
	126 bipush (2, 1)
	127 6 (2, 1)
	128 iconst_2 (2, 1)
	129 invokestatic (2, 1)
	130 java/lang/Integer.valueOf:(I)Ljava/lang/Integer; (2, 1)
	132 aastore (2, 1)
	133 dup (2, 1)
	134 bipush (2, 1)
	135 7 (2, 1)
	136 ldc (2, 1)
	137 EXPONENTIAL_MODE (2, 1)
	138 aastore (2, 1)
	139 dup (2, 1)
	140 bipush (2, 1)
	141 8 (2, 1)
	142 iconst_3 (2, 1)
	143 invokestatic (2, 1)
	144 java/lang/Integer.valueOf:(I)Ljava/lang/Integer; (2, 1)
	146 aastore (2, 1)
	147 dup (2, 1)
	148 bipush (2, 1)
	149 9 (2, 1)
	150 ldc (2, 1)
	151 GAUSSIAN_MODE (2, 1)
	152 aastore (2, 1)
	153 dup (2, 1)
	154 bipush (2, 1)
	155 10 (2, 1)
	156 iconst_4 (2, 1)
	157 invokestatic (2, 1)
	158 java/lang/Integer.valueOf:(I)Ljava/lang/Integer; (2, 1)
	160 aastore (2, 1)
	161 dup (2, 1)
	162 bipush (2, 1)
	163 11 (2, 1)
	164 ldc (2, 1)
	165 CONSTANT_MODE (2, 1)
	166 aastore (2, 1)
	167 dup (2, 1)
	168 bipush (2, 1)
	169 12 (2, 1)
	170 iconst_5 (2, 1)
	171 invokestatic (2, 1)
	172 java/lang/Integer.valueOf:(I)Ljava/lang/Integer; (2, 1)
	174 aastore (2, 1)
	175 invokespecial (2, 1)
	176 org/apache/commons/math3/exception/MathIllegalStateException.<init>:(Lorg/apache/commons/math3/exception/util/Localizable;[Ljava/lang/Object;)V (2, 1)
	178 athrow (1, 1)

Method: fill
	0 iload_1 (0, 0)
	1 newarray (0, 0)
	2 7 (0, 0)
	3 astore_2 (0, 0)
	4 iconst_0 (1, 4)
	5 istore_3 (1, 4)
	6 iload_3 (1, 4)
	7 iload_1 (1, 4)
	8 if_icmpge (1, 4)
	9 16 (1, 4)
	11 aload_2 (1, 4)
	12 iload_3 (1, 4)
	13 aload_0 (1, 4)
	14 invokevirtual (1, 4)
	15 org/apache/commons/math3/random/ValueServer.getNext:()D (1, 4)
	17 dastore (1, 4)
	18 iinc (1, 4)
	19 #3 (1, 4)
	20 -89 (1, 4)
	21 goto (1, 4)
	22 -15 (1, 4)
	24 aload_2 (0, 0)
	25 areturn (0, 0)

Method: computeDistribution
	0 aload_0 (0, 0)
	1 new (0, 0)
	2 org/apache/commons/math3/random/EmpiricalDistribution (0, 0)
	4 dup (0, 0)
	5 iload_1 (0, 0)
	6 aload_0 (0, 0)
	7 getfield (0, 0)
	8 org/apache/commons/math3/random/ValueServer.randomData:Lorg/apache/commons/math3/random/RandomDataGenerator; (0, 0)
	10 invokevirtual (0, 0)
	11 org/apache/commons/math3/random/RandomDataGenerator.getRandomGenerator:()Lorg/apache/commons/math3/random/RandomGenerator; (0, 0)
	13 invokespecial (0, 0)
	14 org/apache/commons/math3/random/EmpiricalDistribution.<init>:(ILorg/apache/commons/math3/random/RandomGenerator;)V (0, 0)
	16 putfield (0, 0)
	17 org/apache/commons/math3/random/ValueServer.empiricalDistribution:Lorg/apache/commons/math3/random/EmpiricalDistribution; (0, 0)
	19 aload_0 (0, 0)
	20 getfield (0, 0)
	21 org/apache/commons/math3/random/ValueServer.empiricalDistribution:Lorg/apache/commons/math3/random/EmpiricalDistribution; (0, 0)
	23 aload_0 (0, 0)
	24 getfield (0, 0)
	25 org/apache/commons/math3/random/ValueServer.valuesFileURL:Ljava/net/URL; (0, 0)
	27 invokevirtual (0, 0)
	28 org/apache/commons/math3/random/EmpiricalDistribution.load:(Ljava/net/URL;)V (0, 0)
	30 aload_0 (0, 0)
	31 aload_0 (0, 0)
	32 getfield (0, 0)
	33 org/apache/commons/math3/random/ValueServer.empiricalDistribution:Lorg/apache/commons/math3/random/EmpiricalDistribution; (0, 0)
	35 invokevirtual (0, 0)
	36 org/apache/commons/math3/random/EmpiricalDistribution.getSampleStats:()Lorg/apache/commons/math3/stat/descriptive/StatisticalSummary; (0, 0)
	38 invokeinterface (0, 0)
	39 org/apache/commons/math3/stat/descriptive/StatisticalSummary.getStandardDeviation:()D (0, 0)
	41 0 (0, 0)
	43 putfield (0, 0)
	44 org/apache/commons/math3/random/ValueServer.mu:D (0, 0)
	46 aload_0 (0, 0)
	47 aload_0 (0, 0)
	48 getfield (0, 0)
	49 org/apache/commons/math3/random/ValueServer.empiricalDistribution:Lorg/apache/commons/math3/random/EmpiricalDistribution; (0, 0)
	51 invokevirtual (0, 0)
	52 org/apache/commons/math3/random/EmpiricalDistribution.getSampleStats:()Lorg/apache/commons/math3/stat/descriptive/StatisticalSummary; (0, 0)
	54 invokeinterface (0, 0)
	55 org/apache/commons/math3/stat/descriptive/StatisticalSummary.java/net/URL (0, 0)
	57 0 (0, 0)
	59 putfield (0, 0)
	60 org/apache/commons/math3/random/ValueServer.sigma:D (0, 0)
	62 return (0, 0)

Method: getMode
	0 aload_0 (0, 0)
	1 getfield (0, 0)
	2 org/apache/commons/math3/random/ValueServer.mode:I (0, 0)
	4 ireturn (0, 0)

Method: setMode
	0 aload_0 (0, 0)
	1 iload_1 (0, 0)
	2 putfield (0, 0)
	3 org/apache/commons/math3/random/ValueServer.mode:I (0, 0)
	5 return (0, 0)

Method: getValuesFileURL
	0 aload_0 (0, 0)
	1 getfield (0, 0)
	2 org/apache/commons/math3/random/ValueServer.valuesFileURL:Ljava/net/URL; (0, 0)
	4 areturn (0, 0)

Method: setValuesFileURL
	0 aload_0 (0, 0)
	1 aload_1 (0, 0)
	2 putfield (0, 0)
	3 org/apache/commons/math3/random/ValueServer.valuesFileURL:Ljava/net/URL; (0, 0)
	5 return (0, 0)

Method: getEmpiricalDistribution
	0 aload_0 (0, 0)
	1 getfield (0, 0)
	2 org/apache/commons/math3/random/ValueServer.empiricalDistribution:Lorg/apache/commons/math3/random/EmpiricalDistribution; (0, 0)
	4 areturn (0, 0)

Method: resetReplayFile
	0 aload_0 (1, 1)
	1 getfield (1, 1)
	2 org/apache/commons/math3/random/ValueServer.filePointer:Ljava/io/BufferedReader; (1, 1)
	4 ifnull (1, 1)
	5 19 (1, 1)
	7 aload_0 (1, 1)
	8 getfield (1, 1)
	9 org/apache/commons/math3/random/ValueServer.filePointer:Ljava/io/BufferedReader; (1, 1)
	11 invokevirtual (1, 1)
	12 java/io/BufferedReader.close:()V (1, 1)
	14 aload_0 (1, 1)
	15 aconst_null (1, 1)
	16 putfield (1, 1)
	17 org/apache/commons/math3/random/ValueServer.filePointer:Ljava/io/BufferedReader; (1, 1)
	19 goto (1, 1)
	20 4 (1, 1)
	22 astore_1 (1, 1)
	23 aload_0 (0, 0)
	24 new (0, 0)
	25 java/io/BufferedReader (0, 0)
	27 dup (0, 0)
	28 new (0, 0)
	29 java/io/InputStreamReader (0, 0)
	31 dup (0, 0)
	32 aload_0 (0, 0)
	33 getfield (0, 0)
	34 org/apache/commons/math3/random/ValueServer.valuesFileURL:Ljava/net/URL; (0, 0)
	36 invokevirtual (0, 0)
	37 java/net/URL.openStream:()Ljava/io/InputStream; (0, 0)
	39 ldc (0, 0)
	40 UTF-8 (0, 0)
	41 invokespecial (0, 0)
	42 java/io/InputStreamReader.<init>:(Ljava/io/InputStream;Ljava/lang/String;)V (0, 0)
	44 invokespecial (0, 0)
	45 java/io/BufferedReader.<init>:(Ljava/io/Reader;)V (0, 0)
	47 putfield (0, 0)
	48 org/apache/commons/math3/random/ValueServer.filePointer:Ljava/io/BufferedReader; (0, 0)
	50 return (0, 0)

Method: closeReplayFile
	0 aload_0 (1, 1)
	1 getfield (1, 1)
	2 org/apache/commons/math3/random/ValueServer.filePointer:Ljava/io/BufferedReader; (1, 1)
	4 ifnull (1, 1)
	5 15 (1, 1)
	7 aload_0 (1, 1)
	8 getfield (1, 1)
	9 org/apache/commons/math3/random/ValueServer.filePointer:Ljava/io/BufferedReader; (1, 1)
	11 invokevirtual (1, 1)
	12 java/io/BufferedReader.close:()V (1, 1)
	14 aload_0 (1, 1)
	15 aconst_null (1, 1)
	16 putfield (1, 1)
	17 org/apache/commons/math3/random/ValueServer.filePointer:Ljava/io/BufferedReader; (1, 1)
	19 return (0, 0)

Method: getMu
	0 aload_0 (0, 0)
	1 getfield (0, 0)
	2 org/apache/commons/math3/random/ValueServer.mu:D (0, 0)
	4 dreturn (0, 0)

Method: setMu
	0 aload_0 (0, 0)
	1 dload_1 (0, 0)
	2 putfield (0, 0)
	3 org/apache/commons/math3/random/ValueServer.mu:D (0, 0)
	5 return (0, 0)

Method: getSigma
	0 aload_0 (0, 0)
	1 getfield (0, 0)
	2 org/apache/commons/math3/random/ValueServer.sigma:D (0, 0)
	4 dreturn (0, 0)

Method: setSigma
	0 aload_0 (0, 0)
	1 dload_1 (0, 0)
	2 putfield (0, 0)
	3 org/apache/commons/math3/random/ValueServer.sigma:D (0, 0)
	5 return (0, 0)

Method: reSeed
	0 aload_0 (0, 0)
	1 getfield (0, 0)
	2 org/apache/commons/math3/random/ValueServer.randomData:Lorg/apache/commons/math3/random/RandomDataGenerator; (0, 0)
	4 lload_1 (0, 0)
	5 invokevirtual (0, 0)
	6 org/apache/commons/math3/random/RandomDataGenerator.reSeed:(J)V (0, 0)
	8 return (0, 0)

Method: getNextDigest
	0 aload_0 (1, 1)
	1 getfield (1, 1)
	2 org/apache/commons/math3/random/ValueServer.empiricalDistribution:Lorg/apache/commons/math3/random/EmpiricalDistribution; (1, 1)
	4 ifnull (1, 1)
	5 18 (1, 1)
	7 aload_0 (1, 1)
	8 getfield (1, 1)
	9 org/apache/commons/math3/random/ValueServer.empiricalDistribution:Lorg/apache/commons/math3/random/EmpiricalDistribution; (1, 1)
	11 invokevirtual (1, 1)
	12 org/apache/commons/math3/random/EmpiricalDistribution.getBinStats:()Ljava/util/List; (1, 1)
	14 invokeinterface (1, 1)
	15 java/util/List.DIGEST_NOT_INITIALIZED:Lorg/apache/commons/math3/exception/util/LocalizedFormats; (1, 1)
	17 0 (1, 1)
	19 ifne (1, 1)
	20 18 (1, 1)
	22 new (1, 1)
	23 org/apache/commons/math3/exception/MathIllegalStateException (1, 1)
	25 dup (1, 1)
	26 getstatic (1, 1)
	27 org/apache/commons/math3/exception/util/LocalizedFormats.DIGEST_NOT_INITIALIZED:Lorg/apache/commons/math3/exception/util/LocalizedFormats; (1, 1)
	29 iconst_0 (1, 1)
	30 anewarray (1, 1)
	31 java/lang/Object (1, 1)
	33 invokespecial (1, 1)
	34 org/apache/commons/math3/exception/MathIllegalStateException.<init>:(Lorg/apache/commons/math3/exception/util/Localizable;[Ljava/lang/Object;)V (1, 1)
	36 athrow (1, 1)
	37 aload_0 (1, 1)
	38 getfield (1, 1)
	39 org/apache/commons/math3/random/ValueServer.empiricalDistribution:Lorg/apache/commons/math3/random/EmpiricalDistribution; (1, 1)
	41 invokevirtual (1, 1)
	42 org/apache/commons/math3/random/EmpiricalDistribution.getNextValue:()D (1, 1)
	44 dreturn (0, 1)

Method: getNextReplay
	0 aconst_null (0, 0)
	1 astore_1 (0, 0)
	2 aload_0 (1, 1)
	3 getfield (1, 1)
	4 org/apache/commons/math3/random/ValueServer.filePointer:Ljava/io/BufferedReader; (1, 1)
	6 ifnonnull (1, 1)
	7 7 (1, 1)
	9 aload_0 (1, 1)
	10 invokevirtual (1, 1)
	11 org/apache/commons/math3/random/ValueServer.resetReplayFile:()V (1, 1)
	13 aload_0 (1, 1)
	14 getfield (1, 1)
	15 org/apache/commons/math3/random/ValueServer.filePointer:Ljava/io/BufferedReader; (1, 1)
	17 invokevirtual (1, 1)
	18 java/io/BufferedReader.readLine:()Ljava/lang/String; (1, 1)
	20 dup (1, 1)
	21 astore_1 (1, 1)
	22 ifnonnull (1, 1)
	23 45 (1, 1)
	25 aload_0 (1, 1)
	26 invokevirtual (1, 1)
	27 org/apache/commons/math3/random/ValueServer.closeReplayFile:()V (1, 1)
	29 aload_0 (1, 1)
	30 invokevirtual (1, 1)
	31 org/apache/commons/math3/random/ValueServer.resetReplayFile:()V (1, 1)
	33 aload_0 (2, 1)
	34 getfield (2, 1)
	35 org/apache/commons/math3/random/ValueServer.filePointer:Ljava/io/BufferedReader; (2, 1)
	37 invokevirtual (2, 1)
	38 java/io/BufferedReader.readLine:()Ljava/lang/String; (2, 1)
	40 dup (2, 1)
	41 astore_1 (2, 1)
	42 ifnonnull (2, 1)
	43 25 (2, 1)
	45 new (2, 1)
	46 org/apache/commons/math3/exception/MathIllegalStateException (2, 1)
	48 dup (2, 1)
	49 getstatic (2, 1)
	50 org/apache/commons/math3/exception/util/LocalizedFormats.URL_CONTAINS_NO_DATA:Lorg/apache/commons/math3/exception/util/LocalizedFormats; (2, 1)
	52 iconst_1 (2, 1)
	53 anewarray (2, 1)
	54 java/lang/Object (2, 1)
	56 dup (2, 1)
	57 iconst_0 (2, 1)
	58 aload_0 (2, 1)
	59 getfield (2, 1)
	60 org/apache/commons/math3/random/ValueServer.valuesFileURL:Ljava/net/URL; (2, 1)
	62 aastore (2, 1)
	63 invokespecial (2, 1)
	64 org/apache/commons/math3/exception/MathIllegalStateException.<init>:(Lorg/apache/commons/math3/exception/util/Localizable;[Ljava/lang/Object;)V (2, 1)
	66 athrow (2, 1)
	67 aload_1 (0, 0)
	68 invokestatic (0, 0)
	69 java/lang/Double.parseDouble:(Ljava/lang/String;)D (0, 0)
	71 dreturn (0, 0)

Method: getNextUniform
	0 aload_0 (1, 1)
	1 getfield (1, 1)
	2 org/apache/commons/math3/random/ValueServer.randomData:Lorg/apache/commons/math3/random/RandomDataGenerator; (1, 1)
	4 dconst_0 (1, 1)
	5 ldc2_w (1, 1)
	6 2.0 (1, 1)
	8 aload_0 (1, 1)
	9 getfield (1, 1)
	10 org/apache/commons/math3/random/ValueServer.mu:D (1, 1)
	12 dmul (1, 1)
	13 invokevirtual (1, 1)
	14 org/apache/commons/math3/random/RandomDataGenerator.nextUniform:(DD)D (1, 1)
	16 dreturn (0, 1)

Method: getNextExponential
	0 aload_0 (0, 0)
	1 getfield (0, 0)
	2 org/apache/commons/math3/random/ValueServer.randomData:Lorg/apache/commons/math3/random/RandomDataGenerator; (0, 0)
	4 aload_0 (0, 0)
	5 getfield (0, 0)
	6 org/apache/commons/math3/random/ValueServer.mu:D (0, 0)
	8 invokevirtual (0, 0)
	9 org/apache/commons/math3/random/RandomDataGenerator.nextExponential:(D)D (0, 0)
	11 dreturn (0, 0)

Method: getNextGaussian
	0 aload_0 (0, 0)
	1 getfield (0, 0)
	2 org/apache/commons/math3/random/ValueServer.randomData:Lorg/apache/commons/math3/random/RandomDataGenerator; (0, 0)
	4 aload_0 (0, 0)
	5 getfield (0, 0)
	6 org/apache/commons/math3/random/ValueServer.mu:D (0, 0)
	8 aload_0 (0, 0)
	9 getfield (0, 0)
	10 org/apache/commons/math3/random/ValueServer.sigma:D (0, 0)
	12 invokevirtual (0, 0)
	13 org/apache/commons/math3/random/RandomDataGenerator.nextGaussian:(DD)D (0, 0)
	15 dreturn (0, 0)

