Method: <init>
	0 aload_0 (0, 0)
	1 ldc (0, 0)
	2 44497 (0, 0)
	3 bipush (0, 0)
	4 23 (0, 0)
	5 sipush (0, 0)
	6 481 (0, 0)
	8 sipush (0, 0)
	9 229 (0, 0)
	11 lload_1 (0, 0)
	12 invokespecial (0, 0)
	13 org/apache/commons/math3/random/AbstractWell.<init>:(IIIIJ)V (0, 0)
	15 return (0, 0)

Method: next
	0 aload_0 (0, 0)
	1 getfield (0, 0)
	2 org/apache/commons/math3/random/Well44497b.iRm1:[I (0, 0)
	4 aload_0 (0, 0)
	5 getfield (0, 0)
	6 org/apache/commons/math3/random/Well44497b.index:I (0, 0)
	8 iaload (0, 0)
	9 istore_2 (0, 0)
	10 aload_0 (0, 0)
	11 getfield (0, 0)
	12 org/apache/commons/math3/random/Well44497b.iRm2:[I (0, 0)
	14 aload_0 (0, 0)
	15 getfield (0, 0)
	16 org/apache/commons/math3/random/Well44497b.index:I (0, 0)
	18 iaload (0, 0)
	19 istore_3 (0, 0)
	20 aload_0 (0, 0)
	21 getfield (0, 0)
	22 org/apache/commons/math3/random/Well44497b.v:[I (0, 0)
	24 aload_0 (0, 0)
	25 getfield (0, 0)
	26 org/apache/commons/math3/random/Well44497b.index:I (0, 0)
	28 iaload (0, 0)
	29 istore (0, 0)
	30 #4 (0, 0)
	31 aload_0 (0, 0)
	32 getfield (0, 0)
	33 org/apache/commons/math3/random/Well44497b.v:[I (0, 0)
	35 aload_0 (0, 0)
	36 getfield (0, 0)
	37 org/apache/commons/math3/random/Well44497b.i1:[I (0, 0)
	39 aload_0 (0, 0)
	40 getfield (0, 0)
	41 org/apache/commons/math3/random/Well44497b.index:I (0, 0)
	43 iaload (0, 0)
	44 iaload (0, 0)
	45 istore (0, 0)
	46 #5 (0, 0)
	47 aload_0 (0, 0)
	48 getfield (0, 0)
	49 org/apache/commons/math3/random/Well44497b.v:[I (0, 0)
	51 aload_0 (0, 0)
	52 getfield (0, 0)
	53 org/apache/commons/math3/random/Well44497b.i2:[I (0, 0)
	55 aload_0 (0, 0)
	56 getfield (0, 0)
	57 org/apache/commons/math3/random/Well44497b.index:I (0, 0)
	59 iaload (0, 0)
	60 iaload (0, 0)
	61 istore (0, 0)
	62 #6 (0, 0)
	63 aload_0 (0, 0)
	64 getfield (0, 0)
	65 org/apache/commons/math3/random/Well44497b.v:[I (0, 0)
	67 aload_0 (0, 0)
	68 getfield (0, 0)
	69 org/apache/commons/math3/random/Well44497b.i3:[I (0, 0)
	71 aload_0 (0, 0)
	72 getfield (0, 0)
	73 org/apache/commons/math3/random/Well44497b.index:I (0, 0)
	75 iaload (0, 0)
	76 iaload (0, 0)
	77 istore (0, 0)
	78 #7 (0, 0)
	79 sipush (0, 0)
	80 -32768 (0, 0)
	82 aload_0 (0, 0)
	83 getfield (0, 0)
	84 org/apache/commons/math3/random/Well44497b.v:[I (0, 0)
	86 iload_2 (0, 0)
	87 iaload (0, 0)
	88 iand (0, 0)
	89 sipush (0, 0)
	90 32767 (0, 0)
	92 aload_0 (0, 0)
	93 getfield (0, 0)
	94 org/apache/commons/math3/random/Well44497b.v:[I (0, 0)
	96 iload_3 (0, 0)
	97 iaload (0, 0)
	98 iand (0, 0)
	99 ixor (0, 0)
	100 istore (0, 0)
	101 #8 (0, 0)
	102 iload (0, 0)
	103 #4 (0, 0)
	104 iload (0, 0)
	105 #4 (0, 0)
	106 bipush (0, 0)
	107 24 (0, 0)
	108 ishl (0, 0)
	109 ixor (0, 0)
	110 iload (0, 0)
	111 #5 (0, 0)
	112 iload (0, 0)
	113 #5 (0, 0)
	114 bipush (0, 0)
	115 30 (0, 0)
	116 iushr (0, 0)
	117 ixor (0, 0)
	118 ixor (0, 0)
	119 istore (0, 0)
	120 #9 (0, 0)
	121 iload (0, 0)
	122 #6 (0, 0)
	123 iload (0, 0)
	124 #6 (0, 0)
	125 bipush (0, 0)
	126 10 (0, 0)
	127 ishl (0, 0)
	128 ixor (0, 0)
	129 iload (0, 0)
	130 #7 (0, 0)
	131 bipush (0, 0)
	132 26 (0, 0)
	133 ishl (0, 0)
	134 ixor (0, 0)
	135 istore (0, 0)
	136 #10 (0, 0)
	137 iload (0, 0)
	138 #9 (0, 0)
	139 iload (0, 0)
	140 #10 (0, 0)
	141 ixor (0, 0)
	142 istore (0, 0)
	143 #11 (0, 0)
	144 iload (0, 0)
	145 #10 (0, 0)
	146 bipush (0, 0)
	147 9 (0, 0)
	148 ishl (0, 0)
	149 iload (0, 0)
	150 #10 (0, 0)
	151 bipush (0, 0)
	152 23 (0, 0)
	153 iushr (0, 0)
	154 ixor (0, 0)
	155 ldc (0, 0)
	156 4227858431 (0, 0)
	157 iand (0, 0)
	158 istore (0, 0)
	159 #12 (0, 0)
	160 iload (0, 0)
	161 #10 (0, 0)
	162 ldc (0, 0)
	163 131072 (0, 0)
	164 iand (0, 0)
	165 ifeq (0, 0)
	166 11 (0, 0)
	168 iload (0, 0)
	169 #12 (0, 0)
	170 ldc (0, 0)
	171 3072982252 (0, 0)
	172 ixor (0, 0)
	173 goto (0, 0)
	174 5 (0, 0)
	176 iload (0, 0)
	177 #12 (0, 0)
	178 istore (0, 0)
	179 #13 (0, 0)
	180 iload (0, 0)
	181 #8 (0, 0)
	182 iload (0, 0)
	183 #9 (0, 0)
	184 iload (0, 0)
	185 #9 (0, 0)
	186 bipush (0, 0)
	187 20 (0, 0)
	188 iushr (0, 0)
	189 ixor (0, 0)
	190 ixor (0, 0)
	191 iload (0, 0)
	192 #13 (0, 0)
	193 ixor (0, 0)
	194 iload (0, 0)
	195 #11 (0, 0)
	196 ixor (0, 0)
	197 istore (0, 0)
	198 #14 (0, 0)
	199 aload_0 (0, 0)
	200 getfield (0, 0)
	201 org/apache/commons/math3/random/Well44497b.v:[I (0, 0)
	203 aload_0 (0, 0)
	204 getfield (0, 0)
	205 org/apache/commons/math3/random/Well44497b.index:I (0, 0)
	207 iload (0, 0)
	208 #11 (0, 0)
	209 iastore (0, 0)
	210 aload_0 (0, 0)
	211 getfield (0, 0)
	212 org/apache/commons/math3/random/Well44497b.v:[I (0, 0)
	214 iload_2 (0, 0)
	215 iload (0, 0)
	216 #14 (0, 0)
	217 iastore (0, 0)
	218 aload_0 (0, 0)
	219 getfield (0, 0)
	220 org/apache/commons/math3/random/Well44497b.v:[I (0, 0)
	222 iload_3 (0, 0)
	223 dup2 (0, 0)
	224 iaload (0, 0)
	225 sipush (0, 0)
	226 -32768 (0, 0)
	228 iand (0, 0)
	229 iastore (0, 0)
	230 aload_0 (0, 0)
	231 iload_2 (0, 0)
	232 putfield (0, 0)
	233 org/apache/commons/math3/random/Well44497b.index:I (0, 0)
	235 iload (0, 0)
	236 #14 (0, 0)
	237 iload (0, 0)
	238 #14 (0, 0)
	239 bipush (0, 0)
	240 7 (0, 0)
	241 ishl (0, 0)
	242 ldc (0, 0)
	243 2480739328 (0, 0)
	244 iand (0, 0)
	245 ixor (0, 0)
	246 istore (0, 0)
	247 #14 (0, 0)
	248 iload (0, 0)
	249 #14 (0, 0)
	250 iload (0, 0)
	251 #14 (0, 0)
	252 bipush (0, 0)
	253 15 (0, 0)
	254 ishl (0, 0)
	255 ldc (0, 0)
	256 4195450880 (0, 0)
	257 iand (0, 0)
	258 ixor (0, 0)
	259 istore (0, 0)
	260 #14 (0, 0)
	261 iload (0, 0)
	262 #14 (0, 0)
	263 bipush (0, 0)
	264 32 (0, 0)
	265 iload_1 (0, 0)
	266 isub (0, 0)
	267 iushr (0, 0)
	268 ireturn (0, 0)

