Method: <init>
	0 aload_0 (0, 0)
	1 invokespecial (0, 0)
	2 java/lang/Object.<init>:()V (0, 0)
	4 aload_0 (0, 0)
	5 dload_1 (0, 0)
	6 putfield (0, 0)
	7 org/apache/commons/math3/special/BesselJ.order:D (0, 0)
	9 return (0, 0)

Method: value
	0 dload_0 (0, 0)
	1 d2i (0, 0)
	2 istore (0, 0)
	3 #4 (0, 0)
	4 dload_0 (0, 0)
	5 iload (0, 0)
	6 #4 (0, 0)
	7 i2d (0, 0)
	8 dsub (0, 0)
	9 dstore (0, 0)
	10 #5 (0, 0)
	11 iload (0, 0)
	12 #4 (0, 0)
	13 iconst_1 (0, 0)
	14 iadd (0, 0)
	15 istore (0, 0)
	16 #7 (0, 0)
	17 dload_2 (0, 0)
	18 dload (0, 0)
	19 #5 (0, 0)
	20 iload (0, 0)
	21 #7 (0, 0)
	22 invokestatic (0, 0)
	23 org/apache/commons/math3/special/BesselJ.rjBesl:(DDI)Lorg/apache/commons/math3/special/BesselJ$BesselJResult; (0, 0)
	25 astore (0, 0)
	26 #8 (0, 0)
	27 aload (1, 1)
	28 #8 (1, 1)
	29 invokestatic (1, 1)
	30 org/apache/commons/math3/special/BesselJ$BesselJResult.access$000:(Lorg/apache/commons/math3/special/BesselJ$BesselJResult;)I (1, 1)
	32 iload (1, 1)
	33 #7 (1, 1)
	34 if_icmplt (1, 1)
	35 12 (1, 1)
	37 aload (1, 1)
	38 #8 (1, 1)
	39 invokestatic (1, 1)
	40 org/apache/commons/math3/special/BesselJ$BesselJResult.access$100:(Lorg/apache/commons/math3/special/BesselJ$BesselJResult;)[D (1, 1)
	42 iload (1, 1)
	43 #4 (1, 1)
	44 daload (1, 1)
	45 dreturn (1, 1)
	46 aload (2, 1)
	47 #8 (2, 1)
	48 invokestatic (2, 1)
	49 org/apache/commons/math3/special/BesselJ$BesselJResult.access$000:(Lorg/apache/commons/math3/special/BesselJ$BesselJResult;)I (2, 1)
	51 ifge (2, 1)
	52 32 (2, 1)
	54 new (2, 1)
	55 org/apache/commons/math3/exception/MathIllegalArgumentException (2, 1)
	57 dup (2, 1)
	58 getstatic (2, 1)
	59 org/apache/commons/math3/exception/util/LocalizedFormats.BESSEL_FUNCTION_BAD_ARGUMENT:Lorg/apache/commons/math3/exception/util/LocalizedFormats; (2, 1)
	61 iconst_2 (2, 1)
	62 anewarray (2, 1)
	63 java/lang/Object (2, 1)
	65 dup (2, 1)
	66 iconst_0 (2, 1)
	67 dload_0 (2, 1)
	68 invokestatic (2, 1)
	69 java/lang/Double.valueOf:(D)Ljava/lang/Double; (2, 1)
	71 aastore (2, 1)
	72 dup (2, 1)
	73 iconst_1 (2, 1)
	74 dload_2 (2, 1)
	75 invokestatic (2, 1)
	76 java/lang/Double.valueOf:(D)Ljava/lang/Double; (2, 1)
	78 aastore (2, 1)
	79 invokespecial (2, 1)
	80 org/apache/commons/math3/exception/MathIllegalArgumentException.<init>:(Lorg/apache/commons/math3/exception/util/Localizable;[Ljava/lang/Object;)V (2, 1)
	82 athrow (2, 1)
	83 aload (3, 1)
	84 #8 (3, 1)
	85 invokestatic (3, 1)
	86 org/apache/commons/math3/special/BesselJ$BesselJResult.access$100:(Lorg/apache/commons/math3/special/BesselJ$BesselJResult;)[D (3, 1)
	88 aload (3, 1)
	89 #8 (3, 1)
	90 invokestatic (3, 1)
	91 org/apache/commons/math3/special/BesselJ$BesselJResult.access$000:(Lorg/apache/commons/math3/special/BesselJ$BesselJResult;)I (3, 1)
	93 iconst_1 (3, 1)
	94 isub (3, 1)
	95 daload (3, 1)
	96 invokestatic (3, 1)
	97 org/apache/commons/math3/util/FastMath.abs:(D)D (3, 1)
	99 ldc2_w (3, 1)
	100 1e-100 (3, 1)
	102 dcmpg (3, 1)
	103 ifge (3, 1)
	104 12 (3, 1)
	106 aload (3, 1)
	107 #8 (3, 1)
	108 invokestatic (3, 1)
	109 org/apache/commons/math3/special/BesselJ$BesselJResult.access$100:(Lorg/apache/commons/math3/special/BesselJ$BesselJResult;)[D (3, 1)
	111 iload (3, 1)
	112 #4 (3, 1)
	113 daload (3, 1)
	114 dreturn (3, 1)
	115 new (0, 0)
	116 org/apache/commons/math3/exception/ConvergenceException (0, 0)
	118 dup (0, 0)
	119 getstatic (0, 0)
	120 org/apache/commons/math3/exception/util/LocalizedFormats.BESSEL_FUNCTION_FAILED_CONVERGENCE:Lorg/apache/commons/math3/exception/util/LocalizedFormats; (0, 0)
	122 iconst_2 (0, 0)
	123 anewarray (0, 0)
	124 java/lang/Object (0, 0)
	126 dup (0, 0)
	127 iconst_0 (0, 0)
	128 dload_0 (0, 0)
	129 invokestatic (0, 0)
	130 java/lang/Double.valueOf:(D)Ljava/lang/Double; (0, 0)
	132 aastore (0, 0)
	133 dup (0, 0)
	134 iconst_1 (0, 0)
	135 dload_2 (0, 0)
	136 invokestatic (0, 0)
	137 java/lang/Double.valueOf:(D)Ljava/lang/Double; (0, 0)
	139 aastore (0, 0)
	140 invokespecial (0, 0)
	141 org/apache/commons/math3/exception/ConvergenceException.<init>:(Lorg/apache/commons/math3/exception/util/Localizable;[Ljava/lang/Object;)V (0, 0)
	143 athrow (0, 0)

Method: rjBesl
	0 iload (0, 0)
	1 #4 (0, 0)
	2 newarray (0, 0)
	3 7 (0, 0)
	4 astore (0, 0)
	5 #5 (0, 0)
	6 iconst_0 (0, 0)
	7 istore (0, 0)
	8 #6 (0, 0)
	9 dconst_0 (0, 0)
	10 dstore (0, 0)
	11 #7 (0, 0)
	12 dconst_0 (0, 0)
	13 dstore (0, 0)
	14 #9 (0, 0)
	15 dload_0 (1, 4)
	16 d2i (1, 4)
	17 istore (1, 4)
	18 #11 (1, 4)
	19 iload (2, 1)
	20 #4 (2, 1)
	21 ifle (2, 1)
	22 1975 (2, 1)
	24 dload_0 (2, 1)
	25 dconst_0 (2, 1)
	26 dcmpl (2, 1)
	27 iflt (2, 1)
	28 1969 (2, 1)
	30 dload_0 (2, 1)
	31 ldc2_w (2, 1)
	32 10000.0 (2, 1)
	34 dcmpg (2, 1)
	35 ifgt (2, 1)
	36 1961 (2, 1)
	38 dload_2 (2, 1)
	39 dconst_0 (2, 1)
	40 dcmpl (2, 1)
	41 iflt (2, 1)
	42 1955 (2, 1)
	44 dload_2 (2, 1)
	45 dconst_1 (2, 1)
	46 dcmpg (2, 1)
	47 ifge (2, 1)
	48 1949 (2, 1)
	50 iload (2, 1)
	51 #4 (2, 1)
	52 istore (2, 1)
	53 #6 (2, 1)
	54 iconst_0 (3, 4)
	55 istore (3, 4)
	56 #12 (3, 4)
	57 iload (3, 4)
	58 #12 (3, 4)
	59 iload (3, 4)
	60 #4 (3, 4)
	61 if_icmpge (3, 4)
	62 15 (3, 4)
	64 aload (3, 4)
	65 #5 (3, 4)
	66 iload (3, 4)
	67 #12 (3, 4)
	68 dconst_0 (3, 4)
	69 dastore (3, 4)
	70 iinc (3, 4)
	71 #12 (3, 4)
	72 -89 (3, 4)
	73 goto (3, 4)
	74 -16 (3, 4)
	76 dload_0 (5, 1)
	77 ldc2_w (5, 1)
	78 0.0001 (5, 1)
	80 dcmpg (5, 1)
	81 ifge (5, 1)
	82 256 (5, 1)
	84 dconst_1 (6, 4)
	85 dstore (6, 4)
	86 #12 (6, 4)
	87 dconst_1 (6, 4)
	88 dload_2 (6, 4)
	89 dadd (6, 4)
	90 dstore (6, 4)
	91 #7 (6, 4)
	92 dconst_0 (6, 4)
	93 dstore (6, 4)
	94 #20 (6, 4)
	95 dload_0 (7, 1)
	96 ldc2_w (7, 1)
	97 8.9e-308 (7, 1)
	99 dcmpl (7, 1)
	100 ifle (7, 1)
	101 10 (7, 1)
	103 ldc2_w (7, 1)
	104 0.5 (7, 1)
	106 dload_0 (7, 1)
	107 dmul (7, 1)
	108 dstore (7, 1)
	109 #20 (7, 1)
	110 dload_2 (7, 1)
	111 dconst_0 (7, 1)
	112 dcmpl (7, 1)
	113 ifeq (7, 1)
	114 18 (7, 1)
	116 dload (7, 1)
	117 #20 (7, 1)
	118 dload_2 (7, 1)
	119 invokestatic (7, 1)
	120 org/apache/commons/math3/util/FastMath.pow:(DD)D (7, 1)
	122 dload_2 (7, 1)
	123 dload_2 (7, 1)
	124 invokestatic (7, 1)
	125 org/apache/commons/math3/special/Gamma.gamma:(D)D (7, 1)
	127 dmul (7, 1)
	128 ddiv (7, 1)
	129 dstore (7, 1)
	130 #12 (7, 1)
	131 dconst_0 (6, 4)
	132 dstore (6, 4)
	133 #14 (6, 4)
	134 dload_0 (7, 1)
	135 dconst_1 (7, 1)
	136 dadd (7, 1)
	137 dconst_1 (7, 1)
	138 dcmpl (7, 1)
	139 ifle (7, 1)
	140 11 (7, 1)
	142 dload (7, 1)
	143 #20 (7, 1)
	144 dneg (7, 1)
	145 dload (7, 1)
	146 #20 (7, 1)
	147 dmul (7, 1)
	148 dstore (7, 1)
	149 #14 (7, 1)
	150 aload (6, 4)
	151 #5 (6, 4)
	152 iconst_0 (6, 4)
	153 dload (6, 4)
	154 #12 (6, 4)
	155 dload (6, 4)
	156 #12 (6, 4)
	157 dload (6, 4)
	158 #14 (6, 4)
	159 dmul (6, 4)
	160 dload (6, 4)
	161 #7 (6, 4)
	162 ddiv (6, 4)
	163 dadd (6, 4)
	164 dastore (6, 4)
	165 dload_0 (7, 1)
	166 dconst_0 (7, 1)
	167 dcmpl (7, 1)
	168 ifeq (7, 1)
	169 15 (7, 1)
	171 aload (7, 1)
	172 #5 (7, 1)
	173 iconst_0 (7, 1)
	174 daload (7, 1)
	175 dconst_0 (7, 1)
	176 dcmpl (7, 1)
	177 ifne (7, 1)
	178 6 (7, 1)
	180 iconst_0 (7, 1)
	181 istore (7, 1)
	182 #6 (7, 1)
	183 iload (7, 1)
	184 #4 (7, 1)
	185 iconst_1 (7, 1)
	186 if_icmpeq (7, 1)
	187 148 (7, 1)
	189 dload_0 (8, 1)
	190 dconst_0 (8, 1)
	191 dcmpg (8, 1)
	192 ifgt (8, 1)
	193 28 (8, 1)
	195 iconst_1 (9, 4)
	196 istore (9, 4)
	197 #22 (9, 4)
	198 iload (9, 4)
	199 #22 (9, 4)
	200 iload (9, 4)
	201 #4 (9, 4)
	202 if_icmpge (9, 4)
	203 15 (9, 4)
	205 aload (9, 4)
	206 #5 (9, 4)
	207 iload (9, 4)
	208 #22 (9, 4)
	209 dconst_0 (9, 4)
	210 dastore (9, 4)
	211 iinc (9, 4)
	212 #22 (9, 4)
	213 -89 (9, 4)
	214 goto (9, 4)
	215 -16 (9, 4)
	217 goto (9, 4)
	218 117 (9, 4)
	220 dload (9, 2)
	221 #20 (9, 2)
	222 dstore (9, 2)
	223 #16 (9, 2)
	224 dload (9, 2)
	225 #14 (9, 2)
	226 dconst_0 (9, 2)
	227 dcmpl (9, 2)
	228 ifeq (9, 2)
	229 12 (9, 2)
	231 ldc2_w (9, 2)
	232 8.9e-308 (9, 2)
	234 dload (9, 2)
	235 #14 (9, 2)
	236 ddiv (9, 2)
	237 goto (9, 2)
	238 8 (9, 2)
	240 ldc2_w (9, 2)
	241 1.78e-307 (9, 2)
	243 dload_0 (9, 2)
	244 ddiv (9, 2)
	245 dstore (9, 2)
	246 #18 (9, 2)
	247 iconst_1 (10, 4)
	248 istore (10, 4)
	249 #22 (10, 4)
	250 iload (10, 4)
	251 #22 (10, 4)
	252 iload (10, 4)
	253 #4 (10, 4)
	254 if_icmpge (10, 4)
	255 80 (10, 4)
	257 dload (10, 4)
	258 #12 (10, 4)
	259 dload (10, 4)
	260 #7 (10, 4)
	261 ddiv (10, 4)
	262 dstore (10, 4)
	263 #12 (10, 4)
	264 dload (10, 4)
	265 #7 (10, 4)
	266 dconst_1 (10, 4)
	267 dadd (10, 4)
	268 dstore (10, 4)
	269 #7 (10, 4)
	270 dload (10, 4)
	271 #12 (10, 4)
	272 dload (10, 4)
	273 #16 (10, 4)
	274 dmul (10, 4)
	275 dstore (10, 4)
	276 #12 (10, 4)
	277 dload (11, 1)
	278 #12 (11, 1)
	279 dload (11, 1)
	280 #18 (11, 1)
	281 dload (11, 1)
	282 #7 (11, 1)
	283 dmul (11, 1)
	284 dcmpg (11, 1)
	285 ifgt (11, 1)
	286 6 (11, 1)
	288 dconst_0 (11, 1)
	289 dstore (11, 1)
	290 #12 (11, 1)
	291 aload (10, 4)
	292 #5 (10, 4)
	293 iload (10, 4)
	294 #22 (10, 4)
	295 dload (10, 4)
	296 #12 (10, 4)
	297 dload (10, 4)
	298 #12 (10, 4)
	299 dload (10, 4)
	300 #14 (10, 4)
	301 dmul (10, 4)
	302 dload (10, 4)
	303 #7 (10, 4)
	304 ddiv (10, 4)
	305 dadd (10, 4)
	306 dastore (10, 4)
	307 aload (11, 1)
	308 #5 (11, 1)
	309 iload (11, 1)
	310 #22 (11, 1)
	311 daload (11, 1)
	312 dconst_0 (11, 1)
	313 dcmpl (11, 1)
	314 ifne (11, 1)
	315 14 (11, 1)
	317 iload (11, 1)
	318 #6 (11, 1)
	319 iload (11, 1)
	320 #22 (11, 1)
	321 if_icmple (11, 1)
	322 7 (11, 1)
	324 iload (11, 1)
	325 #22 (11, 1)
	326 istore (11, 1)
	327 #6 (11, 1)
	328 iinc (11, 1)
	329 #22 (11, 1)
	330 -89 (11, 1)
	331 goto (11, 1)
	332 -81 (11, 1)
	334 goto (8, 1)
	335 1659 (8, 1)
	337 dload_0 (8, 1)
	338 ldc2_w (8, 1)
	339 25.0 (8, 1)
	341 dcmpl (8, 1)
	342 ifle (8, 1)
	343 545 (8, 1)
	345 iload (8, 1)
	346 #4 (8, 1)
	347 iload (8, 1)
	348 #11 (8, 1)
	349 iconst_1 (8, 1)
	350 iadd (8, 1)
	351 if_icmpgt (8, 1)
	352 536 (8, 1)
	354 ldc2_w (9, 4)
	355 0.6366197723675814 (9, 4)
	357 dload_0 (9, 4)
	358 ddiv (9, 4)
	359 invokestatic (9, 4)
	360 org/apache/commons/math3/util/FastMath.sqrt:(D)D (9, 4)
	362 dstore (9, 4)
	363 #20 (9, 4)
	364 ldc2_w (9, 4)
	365 0.125 (9, 4)
	367 dload_0 (9, 4)
	368 ddiv (9, 4)
	369 dstore (9, 4)
	370 #22 (9, 4)
	371 dload (9, 4)
	372 #22 (9, 4)
	373 dload (9, 4)
	374 #22 (9, 4)
	375 dmul (9, 4)
	376 dstore (9, 4)
	377 #24 (9, 4)
	378 iconst_0 (9, 4)
	379 istore (9, 4)
	380 #26 (9, 4)
	381 dload_0 (10, 1)
	382 ldc2_w (10, 1)
	383 130.0 (10, 1)
	385 dcmpl (10, 1)
	386 iflt (10, 1)
	387 9 (10, 1)
	389 iconst_4 (10, 1)
	390 istore (10, 1)
	391 #26 (10, 1)
	392 goto (10, 1)
	393 22 (10, 1)
	395 dload_0 (11, 1)
	396 ldc2_w (11, 1)
	397 35.0 (11, 1)
	399 dcmpl (11, 1)
	400 iflt (11, 1)
	401 10 (11, 1)
	403 bipush (11, 1)
	404 8 (11, 1)
	405 istore (11, 1)
	406 #26 (11, 1)
	407 goto (11, 1)
	408 7 (11, 1)
	410 bipush (12, 2)
	411 11 (12, 2)
	412 istore (12, 2)
	413 #26 (12, 2)
	414 ldc2_w (9, 4)
	415 4.0 (9, 4)
	417 iload (9, 4)
	418 #26 (9, 4)
	419 i2d (9, 4)
	420 dmul (9, 4)
	421 dstore (9, 4)
	422 #27 (9, 4)
	423 dload_0 (10, 4)
	424 ldc2_w (10, 4)
	425 6.283185307179586 (10, 4)
	427 ddiv (10, 4)
	428 ldc2_w (10, 4)
	429 0.5 (10, 4)
	431 dadd (10, 4)
	432 d2i (10, 4)
	433 i2d (10, 4)
	434 dstore (10, 4)
	435 #29 (10, 4)
	436 dload_0 (10, 4)
	437 dload (10, 4)
	438 #29 (10, 4)
	439 ldc2_w (10, 4)
	440 6.28125 (10, 4)
	442 dmul (10, 4)
	443 dsub (10, 4)
	444 dload (10, 4)
	445 #29 (10, 4)
	446 ldc2_w (10, 4)
	447 0.001935307179586477 (10, 4)
	449 dmul (10, 4)
	450 dsub (10, 4)
	451 dload_2 (10, 4)
	452 ldc2_w (10, 4)
	453 0.5 (10, 4)
	455 dadd (10, 4)
	456 ldc2_w (10, 4)
	457 0.6366197723675814 (10, 4)
	459 ddiv (10, 4)
	460 dsub (10, 4)
	461 dstore (10, 4)
	462 #31 (10, 4)
	463 dload (10, 4)
	464 #31 (10, 4)
	465 invokestatic (10, 4)
	466 org/apache/commons/math3/util/FastMath.sin:(D)D (10, 4)
	468 dstore (10, 4)
	469 #33 (10, 4)
	470 dload (10, 4)
	471 #31 (10, 4)
	472 invokestatic (10, 4)
	473 org/apache/commons/math3/util/FastMath.cos:(D)D (10, 4)
	475 dstore (10, 4)
	476 #35 (10, 4)
	477 ldc2_w (10, 4)
	478 2.0 (10, 4)
	480 dload_2 (10, 4)
	481 dmul (10, 4)
	482 dstore (10, 4)
	483 #37 (10, 4)
	484 iconst_1 (11, 4)
	485 istore (11, 4)
	486 #49 (11, 4)
	487 iload (11, 4)
	488 #49 (11, 4)
	489 iconst_2 (11, 4)
	490 if_icmpgt (11, 4)
	491 328 (11, 4)
	493 dload (11, 4)
	494 #27 (11, 4)
	495 dconst_1 (11, 4)
	496 dsub (11, 4)
	497 dload (11, 4)
	498 #37 (11, 4)
	499 dsub (11, 4)
	500 dload (11, 4)
	501 #27 (11, 4)
	502 dconst_1 (11, 4)
	503 dsub (11, 4)
	504 dload (11, 4)
	505 #37 (11, 4)
	506 dadd (11, 4)
	507 dmul (11, 4)
	508 dload (11, 4)
	509 #24 (11, 4)
	510 dmul (11, 4)
	511 ldc2_w (11, 4)
	512 0.5 (11, 4)
	514 dmul (11, 4)
	515 dstore (11, 4)
	516 #43 (11, 4)
	517 dload (11, 4)
	518 #37 (11, 4)
	519 dload (11, 4)
	520 #27 (11, 4)
	521 ldc2_w (11, 4)
	522 3.0 (11, 4)
	524 dsub (11, 4)
	525 dsub (11, 4)
	526 dload (11, 4)
	527 #37 (11, 4)
	528 dload (11, 4)
	529 #27 (11, 4)
	530 ldc2_w (11, 4)
	531 3.0 (11, 4)
	533 dsub (11, 4)
	534 dadd (11, 4)
	535 dmul (11, 4)
	536 dstore (11, 4)
	537 #29 (11, 4)
	538 dload (11, 4)
	539 #43 (11, 4)
	540 dload (11, 4)
	541 #29 (11, 4)
	542 dmul (11, 4)
	543 getstatic (11, 4)
	544 org/apache/commons/math3/special/BesselJ.FACT:[D (11, 4)
	546 iconst_2 (11, 4)
	547 iload (11, 4)
	548 #26 (11, 4)
	549 imul (11, 4)
	550 daload (11, 4)
	551 ddiv (11, 4)
	552 dstore (11, 4)
	553 #41 (11, 4)
	554 dload (11, 4)
	555 #37 (11, 4)
	556 dload (11, 4)
	557 #27 (11, 4)
	558 dconst_1 (11, 4)
	559 dadd (11, 4)
	560 dsub (11, 4)
	561 dload (11, 4)
	562 #37 (11, 4)
	563 dload (11, 4)
	564 #27 (11, 4)
	565 dconst_1 (11, 4)
	566 dadd (11, 4)
	567 dadd (11, 4)
	568 dmul (11, 4)
	569 dstore (11, 4)
	570 #45 (11, 4)
	571 dload (11, 4)
	572 #43 (11, 4)
	573 dload (11, 4)
	574 #45 (11, 4)
	575 dmul (11, 4)
	576 getstatic (11, 4)
	577 org/apache/commons/math3/special/BesselJ.FACT:[D (11, 4)
	579 iconst_2 (11, 4)
	580 iload (11, 4)
	581 #26 (11, 4)
	582 imul (11, 4)
	583 iconst_1 (11, 4)
	584 iadd (11, 4)
	585 daload (11, 4)
	586 ddiv (11, 4)
	587 dstore (11, 4)
	588 #39 (11, 4)
	589 dload (11, 4)
	590 #27 (11, 4)
	591 dstore (11, 4)
	592 #47 (11, 4)
	593 iconst_2 (11, 4)
	594 iload (11, 4)
	595 #26 (11, 4)
	596 imul (11, 4)
	597 istore (11, 4)
	598 #50 (11, 4)
	599 dload (11, 4)
	600 #29 (11, 4)
	601 dstore (11, 4)
	602 #45 (11, 4)
	603 iconst_2 (12, 4)
	604 istore (12, 4)
	605 #51 (12, 4)
	606 iload (12, 4)
	607 #51 (12, 4)
	608 iload (12, 4)
	609 #26 (12, 4)
	610 if_icmpgt (12, 4)
	611 110 (12, 4)
	613 dload (12, 4)
	614 #47 (12, 4)
	615 ldc2_w (12, 4)
	616 4.0 (12, 4)
	618 dsub (12, 4)
	619 dstore (12, 4)
	620 #47 (12, 4)
	621 dload (12, 4)
	622 #47 (12, 4)
	623 dconst_1 (12, 4)
	624 dsub (12, 4)
	625 dload (12, 4)
	626 #37 (12, 4)
	627 dsub (12, 4)
	628 dload (12, 4)
	629 #47 (12, 4)
	630 dconst_1 (12, 4)
	631 dsub (12, 4)
	632 dload (12, 4)
	633 #37 (12, 4)
	634 dadd (12, 4)
	635 dmul (12, 4)
	636 dstore (12, 4)
	637 #43 (12, 4)
	638 dload (12, 4)
	639 #37 (12, 4)
	640 dload (12, 4)
	641 #47 (12, 4)
	642 ldc2_w (12, 4)
	643 3.0 (12, 4)
	645 dsub (12, 4)
	646 dsub (12, 4)
	647 dload (12, 4)
	648 #37 (12, 4)
	649 dload (12, 4)
	650 #47 (12, 4)
	651 ldc2_w (12, 4)
	652 3.0 (12, 4)
	654 dsub (12, 4)
	655 dadd (12, 4)
	656 dmul (12, 4)
	657 dstore (12, 4)
	658 #29 (12, 4)
	659 dload (12, 4)
	660 #41 (12, 4)
	661 dconst_1 (12, 4)
	662 getstatic (12, 4)
	663 org/apache/commons/math3/special/BesselJ.FACT:[D (12, 4)
	665 iload (12, 4)
	666 #50 (12, 4)
	667 iconst_2 (12, 4)
	668 isub (12, 4)
	669 daload (12, 4)
	670 ddiv (12, 4)
	671 dadd (12, 4)
	672 dload (12, 4)
	673 #43 (12, 4)
	674 dmul (12, 4)
	675 dload (12, 4)
	676 #29 (12, 4)
	677 dmul (12, 4)
	678 dload (12, 4)
	679 #24 (12, 4)
	680 dmul (12, 4)
	681 dstore (12, 4)
	682 #41 (12, 4)
	683 dload (12, 4)
	684 #39 (12, 4)
	685 dconst_1 (12, 4)
	686 getstatic (12, 4)
	687 org/apache/commons/math3/special/BesselJ.FACT:[D (12, 4)
	689 iload (12, 4)
	690 #50 (12, 4)
	691 iconst_1 (12, 4)
	692 isub (12, 4)
	693 daload (12, 4)
	694 ddiv (12, 4)
	695 dadd (12, 4)
	696 dload (12, 4)
	697 #43 (12, 4)
	698 dmul (12, 4)
	699 dload (12, 4)
	700 #45 (12, 4)
	701 dmul (12, 4)
	702 dload (12, 4)
	703 #24 (12, 4)
	704 dmul (12, 4)
	705 dstore (12, 4)
	706 #39 (12, 4)
	707 iinc (12, 4)
	708 #50 (12, 4)
	709 24 (12, 4)
	710 dload (12, 4)
	711 #29 (12, 4)
	712 dstore (12, 4)
	713 #45 (12, 4)
	714 iinc (12, 4)
	715 #51 (12, 4)
	716 -89 (12, 4)
	717 goto (12, 4)
	718 -111 (12, 4)
	720 dload (11, 4)
	721 #41 (11, 4)
	722 dconst_1 (11, 4)
	723 dadd (11, 4)
	724 dstore (11, 4)
	725 #41 (11, 4)
	726 dload (11, 4)
	727 #39 (11, 4)
	728 dconst_1 (11, 4)
	729 dadd (11, 4)
	730 dload (11, 4)
	731 #37 (11, 4)
	732 dload (11, 4)
	733 #37 (11, 4)
	734 dmul (11, 4)
	735 dconst_1 (11, 4)
	736 dsub (11, 4)
	737 dmul (11, 4)
	738 ldc2_w (11, 4)
	739 0.125 (11, 4)
	741 dload_0 (11, 4)
	742 ddiv (11, 4)
	743 dmul (11, 4)
	744 dstore (11, 4)
	745 #39 (11, 4)
	746 aload (11, 4)
	747 #5 (11, 4)
	748 iload (11, 4)
	749 #49 (11, 4)
	750 iconst_1 (11, 4)
	751 isub (11, 4)
	752 dload (11, 4)
	753 #20 (11, 4)
	754 dload (11, 4)
	755 #41 (11, 4)
	756 dload (11, 4)
	757 #35 (11, 4)
	758 dmul (11, 4)
	759 dload (11, 4)
	760 #39 (11, 4)
	761 dload (11, 4)
	762 #33 (11, 4)
	763 dmul (11, 4)
	764 dsub (11, 4)
	765 dmul (11, 4)
	766 dastore (11, 4)
	767 iload (12, 1)
	768 #4 (12, 1)
	769 iconst_1 (12, 1)
	770 if_icmpne (12, 1)
	771 21 (12, 1)
	773 new (12, 1)
	774 org/apache/commons/math3/special/BesselJ$BesselJResult (12, 1)
	776 dup (12, 1)
	777 aload (12, 1)
	778 #5 (12, 1)
	779 aload (12, 1)
	780 #5 (12, 1)
	781 arraylength (12, 1)
	782 invokestatic (12, 1)
	783 org/apache/commons/math3/util/MathArrays.copyOf:([DI)[D (12, 1)
	785 iload (12, 1)
	786 #6 (12, 1)
	787 invokespecial (12, 1)
	788 org/apache/commons/math3/special/BesselJ$BesselJResult.<init>:([DI)V (12, 1)
	790 areturn (12, 1)
	791 dload (11, 4)
	792 #33 (11, 4)
	793 dstore (11, 4)
	794 #29 (11, 4)
	795 dload (11, 4)
	796 #35 (11, 4)
	797 dneg (11, 4)
	798 dstore (11, 4)
	799 #33 (11, 4)
	800 dload (11, 4)
	801 #29 (11, 4)
	802 dstore (11, 4)
	803 #35 (11, 4)
	804 dload (11, 4)
	805 #37 (11, 4)
	806 ldc2_w (11, 4)
	807 2.0 (11, 4)
	809 dadd (11, 4)
	810 dstore (11, 4)
	811 #37 (11, 4)
	812 iinc (11, 4)
	813 #49 (11, 4)
	814 -89 (11, 4)
	815 goto (11, 4)
	816 -328 (11, 4)
	818 iload (11, 1)
	819 #4 (11, 1)
	820 iconst_2 (11, 1)
	821 if_icmple (11, 1)
	822 63 (11, 1)
	824 ldc2_w (11, 1)
	825 2.0 (11, 1)
	827 dload_2 (11, 1)
	828 dmul (11, 1)
	829 ldc2_w (11, 1)
	830 2.0 (11, 1)
	832 dadd (11, 1)
	833 dstore (11, 1)
	834 #37 (11, 1)
	835 iconst_2 (12, 4)
	836 istore (12, 4)
	837 #49 (12, 4)
	838 iload (12, 4)
	839 #49 (12, 4)
	840 iload (12, 4)
	841 #4 (12, 4)
	842 if_icmpge (12, 4)
	843 42 (12, 4)
	845 aload (12, 4)
	846 #5 (12, 4)
	847 iload (12, 4)
	848 #49 (12, 4)
	849 dload (12, 4)
	850 #37 (12, 4)
	851 aload (12, 4)
	852 #5 (12, 4)
	853 iload (12, 4)
	854 #49 (12, 4)
	855 iconst_1 (12, 4)
	856 isub (12, 4)
	857 daload (12, 4)
	858 dmul (12, 4)
	859 dload_0 (12, 4)
	860 ddiv (12, 4)
	861 aload (12, 4)
	862 #5 (12, 4)
	863 iload (12, 4)
	864 #49 (12, 4)
	865 iconst_2 (12, 4)
	866 isub (12, 4)
	867 daload (12, 4)
	868 dsub (12, 4)
	869 dastore (12, 4)
	870 dload (12, 4)
	871 #37 (12, 4)
	872 ldc2_w (12, 4)
	873 2.0 (12, 4)
	875 dadd (12, 4)
	876 dstore (12, 4)
	877 #37 (12, 4)
	878 iinc (12, 4)
	879 #49 (12, 4)
	880 -89 (12, 4)
	881 goto (12, 4)
	882 -43 (12, 4)
	884 goto (11, 2)
	885 1109 (11, 2)
	887 iload (11, 2)
	888 #4 (11, 2)
	889 iload (11, 2)
	890 #11 (11, 2)
	891 isub (11, 2)
	892 istore (11, 2)
	893 #20 (11, 2)
	894 iload (11, 2)
	895 #11 (11, 2)
	896 iconst_1 (11, 2)
	897 iadd (11, 2)
	898 istore (11, 2)
	899 #21 (11, 2)
	900 iconst_0 (11, 2)
	901 istore (11, 2)
	902 #22 (11, 2)
	903 iconst_0 (11, 2)
	904 istore (11, 2)
	905 #23 (11, 2)
	906 ldc2_w (11, 2)
	907 2.0 (11, 2)
	909 iload (11, 2)
	910 #21 (11, 2)
	911 i2d (11, 2)
	912 dload_2 (11, 2)
	913 dadd (11, 2)
	914 dmul (11, 2)
	915 dstore (11, 2)
	916 #24 (11, 2)
	917 dconst_1 (11, 2)
	918 dstore (11, 2)
	919 #26 (11, 2)
	920 dload (11, 2)
	921 #24 (11, 2)
	922 dload_0 (11, 2)
	923 ddiv (11, 2)
	924 dstore (11, 2)
	925 #28 (11, 2)
	926 ldc2_w (12, 1)
	927 2e+16 (12, 1)
	929 dstore (12, 1)
	930 #32 (12, 1)
	931 iconst_0 (12, 1)
	932 istore (12, 1)
	933 #34 (12, 1)
	934 iload (13, 1)
	935 #20 (13, 1)
	936 iconst_3 (13, 1)
	937 if_icmplt (13, 1)
	938 339 (13, 1)
	940 ldc2_w (14, 4)
	941 1e+292 (14, 4)
	943 dstore (14, 4)
	944 #18 (14, 4)
	945 iload (14, 4)
	946 #11 (14, 4)
	947 iconst_2 (14, 4)
	948 iadd (14, 4)
	949 istore (14, 4)
	950 #22 (14, 4)
	951 iload (14, 4)
	952 #4 (14, 4)
	953 iconst_1 (14, 4)
	954 isub (14, 4)
	955 istore (14, 4)
	956 #23 (14, 4)
	957 ldc2_w (14, 4)
	958 2.0 (14, 4)
	960 iload (14, 4)
	961 #22 (14, 4)
	962 iconst_1 (14, 4)
	963 isub (14, 4)
	964 i2d (14, 4)
	965 dload_2 (14, 4)
	966 dadd (14, 4)
	967 dmul (14, 4)
	968 dstore (14, 4)
	969 #24 (14, 4)
	970 iload (15, 4)
	971 #22 (15, 4)
	972 istore (15, 4)
	973 #39 (15, 4)
	974 iload (15, 4)
	975 #39 (15, 4)
	976 iload (15, 4)
	977 #23 (15, 4)
	978 if_icmpgt (15, 4)
	979 252 (15, 4)
	981 iload (15, 4)
	982 #39 (15, 4)
	983 istore (15, 4)
	984 #21 (15, 4)
	985 dload (15, 4)
	986 #24 (15, 4)
	987 ldc2_w (15, 4)
	988 2.0 (15, 4)
	990 dadd (15, 4)
	991 dstore (15, 4)
	992 #24 (15, 4)
	993 dload (15, 4)
	994 #26 (15, 4)
	995 dstore (15, 4)
	996 #30 (15, 4)
	997 dload (15, 4)
	998 #28 (15, 4)
	999 dstore (15, 4)
	1000 #26 (15, 4)
	1001 dload (15, 4)
	1002 #24 (15, 4)
	1003 dload (15, 4)
	1004 #26 (15, 4)
	1005 dmul (15, 4)
	1006 dload_0 (15, 4)
	1007 ddiv (15, 4)
	1008 dload (15, 4)
	1009 #30 (15, 4)
	1010 dsub (15, 4)
	1011 dstore (15, 4)
	1012 #28 (15, 4)
	1013 dload (16, 1)
	1014 #28 (16, 1)
	1015 dload (16, 1)
	1016 #18 (16, 1)
	1017 dcmpl (16, 1)
	1018 ifle (16, 1)
	1019 206 (16, 1)
	1021 ldc2_w (16, 1)
	1022 1e+308 (16, 1)
	1024 dstore (16, 1)
	1025 #18 (16, 1)
	1026 dload (16, 1)
	1027 #28 (16, 1)
	1028 dload (16, 1)
	1029 #18 (16, 1)
	1030 ddiv (16, 1)
	1031 dstore (16, 1)
	1032 #28 (16, 1)
	1033 dload (16, 1)
	1034 #26 (16, 1)
	1035 dload (16, 1)
	1036 #18 (16, 1)
	1037 ddiv (16, 1)
	1038 dstore (16, 1)
	1039 #26 (16, 1)
	1040 dload (16, 1)
	1041 #28 (16, 1)
	1042 dstore (16, 1)
	1043 #35 (16, 1)
	1044 dload (16, 1)
	1045 #26 (16, 1)
	1046 dstore (16, 1)
	1047 #37 (16, 1)
	1048 iload (16, 1)
	1049 #21 (16, 1)
	1050 iconst_1 (16, 1)
	1051 iadd (16, 1)
	1052 istore (16, 1)
	1053 #22 (16, 1)
	1054 iinc (16, 1)
	1055 #21 (16, 1)
	1056 24 (16, 1)
	1057 dload (16, 1)
	1058 #24 (16, 1)
	1059 ldc2_w (16, 1)
	1060 2.0 (16, 1)
	1062 dadd (16, 1)
	1063 dstore (16, 1)
	1064 #24 (16, 1)
	1065 dload (16, 1)
	1066 #26 (16, 1)
	1067 dstore (16, 1)
	1068 #30 (16, 1)
	1069 dload (16, 1)
	1070 #28 (16, 1)
	1071 dstore (16, 1)
	1072 #26 (16, 1)
	1073 dload (16, 1)
	1074 #24 (16, 1)
	1075 dload (16, 1)
	1076 #26 (16, 1)
	1077 dmul (16, 1)
	1078 dload_0 (16, 1)
	1079 ddiv (16, 1)
	1080 dload (16, 1)
	1081 #30 (16, 1)
	1082 dsub (16, 1)
	1083 dstore (16, 1)
	1084 #28 (16, 1)
	1085 dload (17, 3)
	1086 #28 (17, 3)
	1087 dconst_1 (17, 3)
	1088 dcmpg (17, 3)
	1089 ifle (17, 3)
	1090 -35 (17, 3)
	1092 dload (17, 3)
	1093 #24 (17, 3)
	1094 dload_0 (17, 3)
	1095 ddiv (17, 3)
	1096 dstore (17, 3)
	1097 #14 (17, 3)
	1098 dload (17, 3)
	1099 #30 (17, 3)
	1100 dload (17, 3)
	1101 #26 (17, 3)
	1102 dmul (17, 3)
	1103 ldc2_w (17, 3)
	1104 0.5 (17, 3)
	1106 ldc2_w (17, 3)
	1107 0.5 (17, 3)
	1109 dload (17, 3)
	1110 #14 (17, 3)
	1111 dload (17, 3)
	1112 #14 (17, 3)
	1113 dmul (17, 3)
	1114 ddiv (17, 3)
	1115 dsub (17, 3)
	1116 dmul (17, 3)
	1117 dstore (17, 3)
	1118 #32 (17, 3)
	1119 dload (17, 3)
	1120 #32 (17, 3)
	1121 ldc2_w (17, 3)
	1122 1e+16 (17, 3)
	1124 ddiv (17, 3)
	1125 dstore (17, 3)
	1126 #32 (17, 3)
	1127 dload (17, 3)
	1128 #26 (17, 3)
	1129 dload (17, 3)
	1130 #18 (17, 3)
	1131 dmul (17, 3)
	1132 dstore (17, 3)
	1133 #28 (17, 3)
	1134 iinc (17, 3)
	1135 #21 (17, 3)
	1136 24 (17, 3)
	1137 dload (17, 3)
	1138 #24 (17, 3)
	1139 ldc2_w (17, 3)
	1140 2.0 (17, 3)
	1142 dsub (17, 3)
	1143 dstore (17, 3)
	1144 #24 (17, 3)
	1145 iload (17, 3)
	1146 #4 (17, 3)
	1147 iload (17, 3)
	1148 #21 (17, 3)
	1149 invokestatic (17, 3)
	1150 org/apache/commons/math3/util/FastMath.min:(II)I (17, 3)
	1152 istore (17, 3)
	1153 #23 (17, 3)
	1154 iload (18, 4)
	1155 #22 (18, 4)
	1156 istore (18, 4)
	1157 #40 (18, 4)
	1158 iload (18, 4)
	1159 #40 (18, 4)
	1160 iload (18, 4)
	1161 #23 (18, 4)
	1162 if_icmpgt (18, 4)
	1163 52 (18, 4)
	1165 dload (18, 4)
	1166 #37 (18, 4)
	1167 dstore (18, 4)
	1168 #30 (18, 4)
	1169 dload (18, 4)
	1170 #35 (18, 4)
	1171 dstore (18, 4)
	1172 #37 (18, 4)
	1173 dload (18, 4)
	1174 #24 (18, 4)
	1175 dload (18, 4)
	1176 #37 (18, 4)
	1177 dmul (18, 4)
	1178 dload_0 (18, 4)
	1179 ddiv (18, 4)
	1180 dload (18, 4)
	1181 #30 (18, 4)
	1182 dsub (18, 4)
	1183 dstore (18, 4)
	1184 #35 (18, 4)
	1185 dload (19, 1)
	1186 #35 (19, 1)
	1187 dload (19, 1)
	1188 #37 (19, 1)
	1189 dmul (19, 1)
	1190 dload (19, 1)
	1191 #32 (19, 1)
	1192 dcmpl (19, 1)
	1193 ifle (19, 1)
	1194 15 (19, 1)
	1196 iload (19, 1)
	1197 #40 (19, 1)
	1198 iconst_1 (19, 1)
	1199 isub (19, 1)
	1200 istore (19, 1)
	1201 #6 (19, 1)
	1202 iconst_1 (19, 1)
	1203 istore (19, 1)
	1204 #34 (19, 1)
	1205 goto (19, 1)
	1206 9 (19, 1)
	1208 iinc (19, 1)
	1209 #40 (19, 1)
	1210 -89 (19, 1)
	1211 goto (19, 1)
	1212 -53 (19, 1)
	1214 iload (18, 4)
	1215 #23 (18, 4)
	1216 istore (18, 4)
	1217 #6 (18, 4)
	1218 iconst_1 (18, 4)
	1219 istore (18, 4)
	1220 #34 (18, 4)
	1221 goto (18, 4)
	1222 9 (18, 4)
	1224 iinc (18, 4)
	1225 #39 (18, 4)
	1226 -89 (18, 4)
	1227 goto (18, 4)
	1228 -253 (18, 4)
	1230 iload (18, 1)
	1231 #34 (18, 1)
	1232 ifne (18, 1)
	1233 44 (18, 1)
	1235 iload (18, 1)
	1236 #23 (18, 1)
	1237 istore (18, 1)
	1238 #21 (18, 1)
	1239 ldc2_w (18, 1)
	1240 2.0 (18, 1)
	1242 iload (18, 1)
	1243 #21 (18, 1)
	1244 i2d (18, 1)
	1245 dload_2 (18, 1)
	1246 dadd (18, 1)
	1247 dmul (18, 1)
	1248 dstore (18, 1)
	1249 #24 (18, 1)
	1250 dload (19, 1)
	1251 #32 (19, 1)
	1252 dload (19, 1)
	1253 #26 (19, 1)
	1254 ldc2_w (19, 1)
	1255 1e+16 (19, 1)
	1257 dmul (19, 1)
	1258 invokestatic (19, 1)
	1259 org/apache/commons/math3/util/FastMath.sqrt:(D)D (19, 1)
	1261 ldc2_w (19, 1)
	1262 2.0 (19, 1)
	1264 dload (19, 1)
	1265 #28 (19, 1)
	1266 dmul (19, 1)
	1267 invokestatic (19, 1)
	1268 org/apache/commons/math3/util/FastMath.sqrt:(D)D (19, 1)
	1270 dmul (19, 1)
	1271 invokestatic (19, 1)
	1272 org/apache/commons/math3/util/FastMath.max:(DD)D (19, 1)
	1274 dstore (19, 1)
	1275 #32 (19, 1)
	1276 iload (17, 1)
	1277 #34 (17, 1)
	1278 ifne (17, 1)
	1279 42 (17, 1)
	1281 iinc (17, 1)
	1282 #21 (17, 1)
	1283 24 (17, 1)
	1284 dload (17, 1)
	1285 #24 (17, 1)
	1286 ldc2_w (17, 1)
	1287 2.0 (17, 1)
	1289 dadd (17, 1)
	1290 dstore (17, 1)
	1291 #24 (17, 1)
	1292 dload (17, 1)
	1293 #26 (17, 1)
	1294 dstore (17, 1)
	1295 #30 (17, 1)
	1296 dload (17, 1)
	1297 #28 (17, 1)
	1298 dstore (17, 1)
	1299 #26 (17, 1)
	1300 dload (17, 1)
	1301 #24 (17, 1)
	1302 dload (17, 1)
	1303 #26 (17, 1)
	1304 dmul (17, 1)
	1305 dload_0 (17, 1)
	1306 ddiv (17, 1)
	1307 dload (17, 1)
	1308 #30 (17, 1)
	1309 dsub (17, 1)
	1310 dstore (17, 1)
	1311 #28 (17, 1)
	1312 dload (18, 3)
	1313 #28 (18, 3)
	1314 dload (18, 3)
	1315 #32 (18, 3)
	1316 dcmpg (18, 3)
	1317 iflt (18, 3)
	1318 -36 (18, 3)
	1320 iinc (16, 1)
	1321 #21 (16, 1)
	1322 24 (16, 1)
	1323 dload (16, 1)
	1324 #24 (16, 1)
	1325 ldc2_w (16, 1)
	1326 2.0 (16, 1)
	1328 dadd (16, 1)
	1329 dstore (16, 1)
	1330 #24 (16, 1)
	1331 dconst_0 (16, 1)
	1332 dstore (16, 1)
	1333 #14 (16, 1)
	1334 dconst_1 (16, 1)
	1335 dload (16, 1)
	1336 #28 (16, 1)
	1337 ddiv (16, 1)
	1338 dstore (16, 1)
	1339 #12 (16, 1)
	1340 iconst_2 (16, 1)
	1341 iload (16, 1)
	1342 #21 (16, 1)
	1343 imul (16, 1)
	1344 iconst_4 (16, 1)
	1345 iload (16, 1)
	1346 #21 (16, 1)
	1347 iconst_2 (16, 1)
	1348 idiv (16, 1)
	1349 imul (16, 1)
	1350 isub (16, 1)
	1351 istore (16, 1)
	1352 #35 (16, 1)
	1353 dconst_0 (16, 1)
	1354 dstore (16, 1)
	1355 #36 (16, 1)
	1356 iload (16, 1)
	1357 #21 (16, 1)
	1358 iconst_2 (16, 1)
	1359 idiv (16, 1)
	1360 i2d (16, 1)
	1361 dstore (16, 1)
	1362 #38 (16, 1)
	1363 dload (16, 1)
	1364 #38 (16, 1)
	1365 dconst_1 (16, 1)
	1366 dsub (16, 1)
	1367 dload_2 (16, 1)
	1368 dadd (16, 1)
	1369 dstore (16, 1)
	1370 #7 (16, 1)
	1371 ldc2_w (16, 1)
	1372 2.0 (16, 1)
	1374 dload (16, 1)
	1375 #38 (16, 1)
	1376 dmul (16, 1)
	1377 dload_2 (16, 1)
	1378 dadd (16, 1)
	1379 dstore (16, 1)
	1380 #9 (16, 1)
	1381 iload (17, 1)
	1382 #35 (17, 1)
	1383 ifeq (17, 1)
	1384 16 (17, 1)
	1386 dload (17, 1)
	1387 #12 (17, 1)
	1388 dload (17, 1)
	1389 #7 (17, 1)
	1390 dmul (17, 1)
	1391 dload (17, 1)
	1392 #9 (17, 1)
	1393 dmul (17, 1)
	1394 dload (17, 1)
	1395 #38 (17, 1)
	1396 ddiv (17, 1)
	1397 dstore (17, 1)
	1398 #36 (17, 1)
	1399 iload (16, 1)
	1400 #21 (16, 1)
	1401 iload (16, 1)
	1402 #4 (16, 1)
	1403 isub (16, 1)
	1404 istore (16, 1)
	1405 #23 (16, 1)
	1406 iconst_0 (16, 1)
	1407 istore (16, 1)
	1408 #40 (16, 1)
	1409 iconst_0 (16, 1)
	1410 istore (16, 1)
	1411 #41 (16, 1)
	1412 iconst_1 (18, 4)
	1413 istore (18, 4)
	1414 #42 (18, 4)
	1415 iload (18, 4)
	1416 #42 (18, 4)
	1417 iload (18, 4)
	1418 #23 (18, 4)
	1419 if_icmpgt (18, 4)
	1420 110 (18, 4)
	1422 iinc (18, 4)
	1423 #21 (18, 4)
	1424 24 (18, 4)
	1425 dload (18, 4)
	1426 #24 (18, 4)
	1427 ldc2_w (18, 4)
	1428 2.0 (18, 4)
	1430 dsub (18, 4)
	1431 dstore (18, 4)
	1432 #24 (18, 4)
	1433 dload (18, 4)
	1434 #14 (18, 4)
	1435 dstore (18, 4)
	1436 #16 (18, 4)
	1437 dload (18, 4)
	1438 #12 (18, 4)
	1439 dstore (18, 4)
	1440 #14 (18, 4)
	1441 dload (18, 4)
	1442 #24 (18, 4)
	1443 dload (18, 4)
	1444 #14 (18, 4)
	1445 dmul (18, 4)
	1446 dload_0 (18, 4)
	1447 ddiv (18, 4)
	1448 dload (18, 4)
	1449 #16 (18, 4)
	1450 dsub (18, 4)
	1451 dstore (18, 4)
	1452 #12 (18, 4)
	1453 iconst_2 (18, 4)
	1454 iload (18, 4)
	1455 #35 (18, 4)
	1456 isub (18, 4)
	1457 istore (18, 4)
	1458 #35 (18, 4)
	1459 iload (19, 1)
	1460 #35 (19, 1)
	1461 ifeq (19, 1)
	1462 62 (19, 1)
	1464 dload (19, 1)
	1465 #38 (19, 1)
	1466 dconst_1 (19, 1)
	1467 dsub (19, 1)
	1468 dstore (19, 1)
	1469 #38 (19, 1)
	1470 ldc2_w (19, 1)
	1471 2.0 (19, 1)
	1473 dload (19, 1)
	1474 #38 (19, 1)
	1475 dmul (19, 1)
	1476 dload_2 (19, 1)
	1477 dadd (19, 1)
	1478 dstore (19, 1)
	1479 #9 (19, 1)
	1480 iload (20, 1)
	1481 #21 (20, 1)
	1482 iconst_1 (20, 1)
	1483 if_icmpne (20, 1)
	1484 6 (20, 1)
	1486 goto (20, 1)
	1487 43 (20, 1)
	1489 dload (19, 1)
	1490 #38 (19, 1)
	1491 dconst_1 (19, 1)
	1492 dsub (19, 1)
	1493 dload_2 (19, 1)
	1494 dadd (19, 1)
	1495 dstore (19, 1)
	1496 #7 (19, 1)
	1497 dload (20, 1)
	1498 #7 (20, 1)
	1499 dconst_0 (20, 1)
	1500 dcmpl (20, 1)
	1501 ifne (20, 1)
	1502 6 (20, 1)
	1504 dconst_1 (20, 1)
	1505 dstore (20, 1)
	1506 #7 (20, 1)
	1507 dload (19, 1)
	1508 #36 (19, 1)
	1509 dload (19, 1)
	1510 #12 (19, 1)
	1511 dload (19, 1)
	1512 #9 (19, 1)
	1513 dmul (19, 1)
	1514 dadd (19, 1)
	1515 dload (19, 1)
	1516 #7 (19, 1)
	1517 dmul (19, 1)
	1518 dload (19, 1)
	1519 #38 (19, 1)
	1520 ddiv (19, 1)
	1521 dstore (19, 1)
	1522 #36 (19, 1)
	1523 iinc (19, 1)
	1524 #42 (19, 1)
	1525 -89 (19, 1)
	1526 goto (19, 1)
	1527 -111 (19, 1)
	1529 aload (18, 4)
	1530 #5 (18, 4)
	1531 iload (18, 4)
	1532 #21 (18, 4)
	1533 iconst_1 (18, 4)
	1534 isub (18, 4)
	1535 dload (18, 4)
	1536 #12 (18, 4)
	1537 dastore (18, 4)
	1538 iload (19, 1)
	1539 #23 (19, 1)
	1540 iflt (19, 1)
	1541 147 (19, 1)
	1543 iload (20, 1)
	1544 #4 (20, 1)
	1545 iconst_1 (20, 1)
	1546 if_icmpgt (20, 1)
	1547 35 (20, 1)
	1549 dload_2 (20, 1)
	1550 dstore (20, 1)
	1551 #9 (20, 1)
	1552 dload_2 (21, 1)
	1553 dconst_1 (21, 1)
	1554 dadd (21, 1)
	1555 dconst_1 (21, 1)
	1556 dcmpl (21, 1)
	1557 ifne (21, 1)
	1558 6 (21, 1)
	1560 dconst_1 (21, 1)
	1561 dstore (21, 1)
	1562 #9 (21, 1)
	1563 dload (20, 1)
	1564 #36 (20, 1)
	1565 aload (20, 1)
	1566 #5 (20, 1)
	1567 iconst_0 (20, 1)
	1568 daload (20, 1)
	1569 dload (20, 1)
	1570 #9 (20, 1)
	1571 dmul (20, 1)
	1572 dadd (20, 1)
	1573 dstore (20, 1)
	1574 #36 (20, 1)
	1575 iconst_1 (20, 1)
	1576 istore (20, 1)
	1577 #40 (20, 1)
	1578 goto (20, 1)
	1579 109 (20, 1)
	1581 iinc (21, 2)
	1582 #21 (21, 2)
	1583 24 (21, 2)
	1584 dload (21, 2)
	1585 #24 (21, 2)
	1586 ldc2_w (21, 2)
	1587 2.0 (21, 2)
	1589 dsub (21, 2)
	1590 dstore (21, 2)
	1591 #24 (21, 2)
	1592 aload (21, 2)
	1593 #5 (21, 2)
	1594 iload (21, 2)
	1595 #21 (21, 2)
	1596 iconst_1 (21, 2)
	1597 isub (21, 2)
	1598 dload (21, 2)
	1599 #24 (21, 2)
	1600 dload (21, 2)
	1601 #12 (21, 2)
	1602 dmul (21, 2)
	1603 dload_0 (21, 2)
	1604 ddiv (21, 2)
	1605 dload (21, 2)
	1606 #14 (21, 2)
	1607 dsub (21, 2)
	1608 dastore (21, 2)
	1609 iload (22, 1)
	1610 #21 (22, 1)
	1611 iconst_1 (22, 1)
	1612 if_icmpne (22, 1)
	1613 9 (22, 1)
	1615 iconst_1 (22, 1)
	1616 istore (22, 1)
	1617 #41 (22, 1)
	1618 goto (22, 1)
	1619 69 (22, 1)
	1621 iconst_2 (23, 2)
	1622 iload (23, 2)
	1623 #35 (23, 2)
	1624 isub (23, 2)
	1625 istore (23, 2)
	1626 #35 (23, 2)
	1627 iload (24, 1)
	1628 #35 (24, 1)
	1629 ifeq (24, 1)
	1630 58 (24, 1)
	1632 dload (24, 1)
	1633 #38 (24, 1)
	1634 dconst_1 (24, 1)
	1635 dsub (24, 1)
	1636 dstore (24, 1)
	1637 #38 (24, 1)
	1638 ldc2_w (24, 1)
	1639 2.0 (24, 1)
	1641 dload (24, 1)
	1642 #38 (24, 1)
	1643 dmul (24, 1)
	1644 dload_2 (24, 1)
	1645 dadd (24, 1)
	1646 dstore (24, 1)
	1647 #9 (24, 1)
	1648 dload (24, 1)
	1649 #38 (24, 1)
	1650 dconst_1 (24, 1)
	1651 dsub (24, 1)
	1652 dload_2 (24, 1)
	1653 dadd (24, 1)
	1654 dstore (24, 1)
	1655 #7 (24, 1)
	1656 dload (25, 1)
	1657 #7 (25, 1)
	1658 dconst_0 (25, 1)
	1659 dcmpl (25, 1)
	1660 ifne (25, 1)
	1661 6 (25, 1)
	1663 dconst_1 (25, 1)
	1664 dstore (25, 1)
	1665 #7 (25, 1)
	1666 dload (24, 1)
	1667 #36 (24, 1)
	1668 aload (24, 1)
	1669 #5 (24, 1)
	1670 iload (24, 1)
	1671 #21 (24, 1)
	1672 iconst_1 (24, 1)
	1673 isub (24, 1)
	1674 daload (24, 1)
	1675 dload (24, 1)
	1676 #9 (24, 1)
	1677 dmul (24, 1)
	1678 dadd (24, 1)
	1679 dload (24, 1)
	1680 #7 (24, 1)
	1681 dmul (24, 1)
	1682 dload (24, 1)
	1683 #38 (24, 1)
	1684 ddiv (24, 1)
	1685 dstore (24, 1)
	1686 #36 (24, 1)
	1687 iload (19, 1)
	1688 #40 (19, 1)
	1689 ifne (19, 1)
	1690 137 (19, 1)
	1692 iload (19, 1)
	1693 #41 (19, 1)
	1694 ifne (19, 1)
	1695 132 (19, 1)
	1697 iload (19, 1)
	1698 #21 (19, 1)
	1699 iconst_2 (19, 1)
	1700 isub (19, 1)
	1701 istore (19, 1)
	1702 #23 (19, 1)
	1703 iload (20, 1)
	1704 #23 (20, 1)
	1705 ifeq (20, 1)
	1706 121 (20, 1)
	1708 iconst_1 (22, 4)
	1709 istore (22, 4)
	1710 #42 (22, 4)
	1711 iload (22, 4)
	1712 #42 (22, 4)
	1713 iload (22, 4)
	1714 #23 (22, 4)
	1715 if_icmpgt (22, 4)
	1716 111 (22, 4)
	1718 iinc (22, 4)
	1719 #21 (22, 4)
	1720 24 (22, 4)
	1721 dload (22, 4)
	1722 #24 (22, 4)
	1723 ldc2_w (22, 4)
	1724 2.0 (22, 4)
	1726 dsub (22, 4)
	1727 dstore (22, 4)
	1728 #24 (22, 4)
	1729 aload (22, 4)
	1730 #5 (22, 4)
	1731 iload (22, 4)
	1732 #21 (22, 4)
	1733 iconst_1 (22, 4)
	1734 isub (22, 4)
	1735 dload (22, 4)
	1736 #24 (22, 4)
	1737 aload (22, 4)
	1738 #5 (22, 4)
	1739 iload (22, 4)
	1740 #21 (22, 4)
	1741 daload (22, 4)
	1742 dmul (22, 4)
	1743 dload_0 (22, 4)
	1744 ddiv (22, 4)
	1745 aload (22, 4)
	1746 #5 (22, 4)
	1747 iload (22, 4)
	1748 #21 (22, 4)
	1749 iconst_1 (22, 4)
	1750 iadd (22, 4)
	1751 daload (22, 4)
	1752 dsub (22, 4)
	1753 dastore (22, 4)
	1754 iconst_2 (22, 4)
	1755 iload (22, 4)
	1756 #35 (22, 4)
	1757 isub (22, 4)
	1758 istore (22, 4)
	1759 #35 (22, 4)
	1760 iload (23, 1)
	1761 #35 (23, 1)
	1762 ifeq (23, 1)
	1763 58 (23, 1)
	1765 dload (23, 1)
	1766 #38 (23, 1)
	1767 dconst_1 (23, 1)
	1768 dsub (23, 1)
	1769 dstore (23, 1)
	1770 #38 (23, 1)
	1771 ldc2_w (23, 1)
	1772 2.0 (23, 1)
	1774 dload (23, 1)
	1775 #38 (23, 1)
	1776 dmul (23, 1)
	1777 dload_2 (23, 1)
	1778 dadd (23, 1)
	1779 dstore (23, 1)
	1780 #9 (23, 1)
	1781 dload (23, 1)
	1782 #38 (23, 1)
	1783 dconst_1 (23, 1)
	1784 dsub (23, 1)
	1785 dload_2 (23, 1)
	1786 dadd (23, 1)
	1787 dstore (23, 1)
	1788 #7 (23, 1)
	1789 dload (24, 1)
	1790 #7 (24, 1)
	1791 dconst_0 (24, 1)
	1792 dcmpl (24, 1)
	1793 ifne (24, 1)
	1794 6 (24, 1)
	1796 dconst_1 (24, 1)
	1797 dstore (24, 1)
	1798 #7 (24, 1)
	1799 dload (23, 1)
	1800 #36 (23, 1)
	1801 aload (23, 1)
	1802 #5 (23, 1)
	1803 iload (23, 1)
	1804 #21 (23, 1)
	1805 iconst_1 (23, 1)
	1806 isub (23, 1)
	1807 daload (23, 1)
	1808 dload (23, 1)
	1809 #9 (23, 1)
	1810 dmul (23, 1)
	1811 dadd (23, 1)
	1812 dload (23, 1)
	1813 #7 (23, 1)
	1814 dmul (23, 1)
	1815 dload (23, 1)
	1816 #38 (23, 1)
	1817 ddiv (23, 1)
	1818 dstore (23, 1)
	1819 #36 (23, 1)
	1820 iinc (23, 1)
	1821 #42 (23, 1)
	1822 -89 (23, 1)
	1823 goto (23, 1)
	1824 -112 (23, 1)
	1826 iload (20, 1)
	1827 #40 (20, 1)
	1828 ifne (20, 1)
	1829 69 (20, 1)
	1831 iload (21, 1)
	1832 #41 (21, 1)
	1833 ifne (21, 1)
	1834 26 (21, 1)
	1836 aload (21, 1)
	1837 #5 (21, 1)
	1838 iconst_0 (21, 1)
	1839 ldc2_w (21, 1)
	1840 2.0 (21, 1)
	1842 dload_2 (21, 1)
	1843 dconst_1 (21, 1)
	1844 dadd (21, 1)
	1845 dmul (21, 1)
	1846 aload (21, 1)
	1847 #5 (21, 1)
	1848 iconst_1 (21, 1)
	1849 daload (21, 1)
	1850 dmul (21, 1)
	1851 dload_0 (21, 1)
	1852 ddiv (21, 1)
	1853 aload (21, 1)
	1854 #5 (21, 1)
	1855 iconst_2 (21, 1)
	1856 daload (21, 1)
	1857 dsub (21, 1)
	1858 dastore (21, 1)
	1859 dload (20, 1)
	1860 #38 (20, 1)
	1861 dconst_1 (20, 1)
	1862 dsub (20, 1)
	1863 dstore (20, 1)
	1864 #38 (20, 1)
	1865 ldc2_w (20, 1)
	1866 2.0 (20, 1)
	1868 dload (20, 1)
	1869 #38 (20, 1)
	1870 dmul (20, 1)
	1871 dload_2 (20, 1)
	1872 dadd (20, 1)
	1873 dstore (20, 1)
	1874 #9 (20, 1)
	1875 dload (21, 1)
	1876 #9 (21, 1)
	1877 dconst_0 (21, 1)
	1878 dcmpl (21, 1)
	1879 ifne (21, 1)
	1880 6 (21, 1)
	1882 dconst_1 (21, 1)
	1883 dstore (21, 1)
	1884 #9 (21, 1)
	1885 dload (20, 1)
	1886 #36 (20, 1)
	1887 aload (20, 1)
	1888 #5 (20, 1)
	1889 iconst_0 (20, 1)
	1890 daload (20, 1)
	1891 dload (20, 1)
	1892 #9 (20, 1)
	1893 dmul (20, 1)
	1894 dadd (20, 1)
	1895 dstore (20, 1)
	1896 #36 (20, 1)
	1897 dload_2 (20, 1)
	1898 invokestatic (20, 1)
	1899 org/apache/commons/math3/util/FastMath.abs:(D)D (20, 1)
	1901 ldc2_w (20, 1)
	1902 1e-16 (20, 1)
	1904 dcmpl (20, 1)
	1905 ifle (20, 1)
	1906 23 (20, 1)
	1908 dload (20, 1)
	1909 #36 (20, 1)
	1910 dload_2 (20, 1)
	1911 invokestatic (20, 1)
	1912 org/apache/commons/math3/special/Gamma.gamma:(D)D (20, 1)
	1914 dload_0 (20, 1)
	1915 ldc2_w (20, 1)
	1916 0.5 (20, 1)
	1918 dmul (20, 1)
	1919 dload_2 (20, 1)
	1920 dneg (20, 1)
	1921 invokestatic (20, 1)
	1922 org/apache/commons/math3/util/FastMath.pow:(DD)D (20, 1)
	1924 dmul (20, 1)
	1925 dmul (20, 1)
	1926 dstore (20, 1)
	1927 #36 (20, 1)
	1928 ldc2_w (19, 1)
	1929 8.9e-308 (19, 1)
	1931 dstore (19, 1)
	1932 #12 (19, 1)
	1933 dload (20, 1)
	1934 #36 (20, 1)
	1935 dconst_1 (20, 1)
	1936 dcmpl (20, 1)
	1937 ifle (20, 1)
	1938 10 (20, 1)
	1940 dload (20, 1)
	1941 #12 (20, 1)
	1942 dload (20, 1)
	1943 #36 (20, 1)
	1944 dmul (20, 1)
	1945 dstore (20, 1)
	1946 #12 (20, 1)
	1947 iconst_0 (20, 4)
	1948 istore (20, 4)
	1949 #21 (20, 4)
	1950 iload (20, 4)
	1951 #21 (20, 4)
	1952 iload (20, 4)
	1953 #4 (20, 4)
	1954 if_icmpge (20, 4)
	1955 39 (20, 4)
	1957 aload (21, 1)
	1958 #5 (21, 1)
	1959 iload (21, 1)
	1960 #21 (21, 1)
	1961 daload (21, 1)
	1962 invokestatic (21, 1)
	1963 org/apache/commons/math3/util/FastMath.abs:(D)D (21, 1)
	1965 dload (21, 1)
	1966 #12 (21, 1)
	1967 dcmpg (21, 1)
	1968 ifge (21, 1)
	1969 9 (21, 1)
	1971 aload (21, 1)
	1972 #5 (21, 1)
	1973 iload (21, 1)
	1974 #21 (21, 1)
	1975 dconst_0 (21, 1)
	1976 dastore (21, 1)
	1977 aload (20, 4)
	1978 #5 (20, 4)
	1979 iload (20, 4)
	1980 #21 (20, 4)
	1981 dup2 (20, 4)
	1982 daload (20, 4)
	1983 dload (20, 4)
	1984 #36 (20, 4)
	1985 ddiv (20, 4)
	1986 dastore (20, 4)
	1987 iinc (20, 4)
	1988 #21 (20, 4)
	1989 -89 (20, 4)
	1990 goto (20, 4)
	1991 -40 (20, 4)
	1993 goto (19, 2)
	1994 24 (19, 2)
	1996 aload (20, 1)
	1997 #5 (20, 1)
	1998 arraylength (20, 1)
	1999 ifle (20, 1)
	2000 8 (20, 1)
	2002 aload (20, 1)
	2003 #5 (20, 1)
	2004 iconst_0 (20, 1)
	2005 dconst_0 (20, 1)
	2006 dastore (20, 1)
	2007 iload (19, 2)
	2008 #4 (19, 2)
	2009 iconst_0 (19, 2)
	2010 invokestatic (19, 2)
	2011 org/apache/commons/math3/util/FastMath.min:(II)I (19, 2)
	2013 iconst_1 (19, 2)
	2014 isub (19, 2)
	2015 istore (19, 2)
	2016 #6 (19, 2)
	2017 new (17, 1)
	2018 org/apache/commons/math3/special/BesselJ$BesselJResult (17, 1)
	2020 dup (17, 1)
	2021 aload (17, 1)
	2022 #5 (17, 1)
	2023 aload (17, 1)
	2024 #5 (17, 1)
	2025 arraylength (17, 1)
	2026 invokestatic (17, 1)
	2027 org/apache/commons/math3/util/MathArrays.copyOf:([DI)[D (17, 1)
	2029 iload (17, 1)
	2030 #6 (17, 1)
	2031 invokespecial (17, 1)
	2032 org/apache/commons/math3/special/BesselJ$BesselJResult.<init>:([DI)V (17, 1)
	2034 areturn (5, 1)

Method: <clinit>
	0 bipush (0, 0)
	1 25 (0, 0)
	2 newarray (0, 0)
	3 7 (0, 0)
	4 dup (0, 0)
	5 iconst_0 (0, 0)
	6 dconst_1 (0, 0)
	7 dastore (0, 0)
	8 dup (0, 0)
	9 iconst_1 (0, 0)
	10 dconst_1 (0, 0)
	11 dastore (0, 0)
	12 dup (0, 0)
	13 iconst_2 (0, 0)
	14 ldc2_w (0, 0)
	15 2.0 (0, 0)
	17 dastore (0, 0)
	18 dup (0, 0)
	19 iconst_3 (0, 0)
	20 ldc2_w (0, 0)
	21 6.0 (0, 0)
	23 dastore (0, 0)
	24 dup (0, 0)
	25 iconst_4 (0, 0)
	26 ldc2_w (0, 0)
	27 24.0 (0, 0)
	29 dastore (0, 0)
	30 dup (0, 0)
	31 iconst_5 (0, 0)
	32 ldc2_w (0, 0)
	33 120.0 (0, 0)
	35 dastore (0, 0)
	36 dup (0, 0)
	37 bipush (0, 0)
	38 6 (0, 0)
	39 ldc2_w (0, 0)
	40 720.0 (0, 0)
	42 dastore (0, 0)
	43 dup (0, 0)
	44 bipush (0, 0)
	45 7 (0, 0)
	46 ldc2_w (0, 0)
	47 5040.0 (0, 0)
	49 dastore (0, 0)
	50 dup (0, 0)
	51 bipush (0, 0)
	52 8 (0, 0)
	53 ldc2_w (0, 0)
	54 40320.0 (0, 0)
	56 dastore (0, 0)
	57 dup (0, 0)
	58 bipush (0, 0)
	59 9 (0, 0)
	60 ldc2_w (0, 0)
	61 362880.0 (0, 0)
	63 dastore (0, 0)
	64 dup (0, 0)
	65 bipush (0, 0)
	66 10 (0, 0)
	67 ldc2_w (0, 0)
	68 3628800.0 (0, 0)
	70 dastore (0, 0)
	71 dup (0, 0)
	72 bipush (0, 0)
	73 11 (0, 0)
	74 ldc2_w (0, 0)
	75 39916800.0 (0, 0)
	77 dastore (0, 0)
	78 dup (0, 0)
	79 bipush (0, 0)
	80 12 (0, 0)
	81 ldc2_w (0, 0)
	82 479001600.0 (0, 0)
	84 dastore (0, 0)
	85 dup (0, 0)
	86 bipush (0, 0)
	87 13 (0, 0)
	88 ldc2_w (0, 0)
	89 6227020800.0 (0, 0)
	91 dastore (0, 0)
	92 dup (0, 0)
	93 bipush (0, 0)
	94 14 (0, 0)
	95 ldc2_w (0, 0)
	96 87178291200.0 (0, 0)
	98 dastore (0, 0)
	99 dup (0, 0)
	100 bipush (0, 0)
	101 15 (0, 0)
	102 ldc2_w (0, 0)
	103 1307674368000.0 (0, 0)
	105 dastore (0, 0)
	106 dup (0, 0)
	107 bipush (0, 0)
	108 16 (0, 0)
	109 ldc2_w (0, 0)
	110 20922789888000.0 (0, 0)
	112 dastore (0, 0)
	113 dup (0, 0)
	114 bipush (0, 0)
	115 17 (0, 0)
	116 ldc2_w (0, 0)
	117 355687428096000.0 (0, 0)
	119 dastore (0, 0)
	120 dup (0, 0)
	121 bipush (0, 0)
	122 18 (0, 0)
	123 ldc2_w (0, 0)
	124 6402373705728000.0 (0, 0)
	126 dastore (0, 0)
	127 dup (0, 0)
	128 bipush (0, 0)
	129 19 (0, 0)
	130 ldc2_w (0, 0)
	131 1.21645100408832e+17 (0, 0)
	133 dastore (0, 0)
	134 dup (0, 0)
	135 bipush (0, 0)
	136 20 (0, 0)
	137 ldc2_w (0, 0)
	138 2.43290200817664e+18 (0, 0)
	140 dastore (0, 0)
	141 dup (0, 0)
	142 bipush (0, 0)
	143 21 (0, 0)
	144 ldc2_w (0, 0)
	145 5.109094217170944e+19 (0, 0)
	147 dastore (0, 0)
	148 dup (0, 0)
	149 bipush (0, 0)
	150 22 (0, 0)
	151 ldc2_w (0, 0)
	152 1.1240007277776077e+21 (0, 0)
	154 dastore (0, 0)
	155 dup (0, 0)
	156 bipush (0, 0)
	157 23 (0, 0)
	158 ldc2_w (0, 0)
	159 2.585201673888498e+22 (0, 0)
	161 dastore (0, 0)
	162 dup (0, 0)
	163 bipush (0, 0)
	164 24 (0, 0)
	165 ldc2_w (0, 0)
	166 6.204484017332394e+23 (0, 0)
	168 dastore (0, 0)
	169 putstatic (0, 0)
	170 org/apache/commons/math3/special/BesselJ.FACT:[D (0, 0)
	172 return (0, 0)

