Method: getB
	0 iload_1 (1, 1)
	1 iconst_2 (1, 1)
	2 irem (1, 1)
	3 ifne (1, 1)
	4 54 (1, 1)
	6 iload_1 (1, 1)
	7 i2d (1, 1)
	8 ldc2_w (1, 1)
	9 2.0 (1, 1)
	11 ddiv (1, 1)
	12 dstore (1, 1)
	13 #6 (1, 1)
	14 dload (1, 1)
	15 #6 (1, 1)
	16 aload_0 (1, 1)
	17 getfield (1, 1)
	18 org/apache/commons/math3/special/Beta$1.val$b:D (1, 1)
	20 dload (1, 1)
	21 #6 (1, 1)
	22 dsub (1, 1)
	23 dmul (1, 1)
	24 dload_2 (1, 1)
	25 dmul (1, 1)
	26 aload_0 (1, 1)
	27 getfield (1, 1)
	28 org/apache/commons/math3/special/Beta$1.val$a:D (1, 1)
	30 ldc2_w (1, 1)
	31 2.0 (1, 1)
	33 dload (1, 1)
	34 #6 (1, 1)
	35 dmul (1, 1)
	36 dadd (1, 1)
	37 dconst_1 (1, 1)
	38 dsub (1, 1)
	39 aload_0 (1, 1)
	40 getfield (1, 1)
	41 org/apache/commons/math3/special/Beta$1.val$a:D (1, 1)
	43 ldc2_w (1, 1)
	44 2.0 (1, 1)
	46 dload (1, 1)
	47 #6 (1, 1)
	48 dmul (1, 1)
	49 dadd (1, 1)
	50 dmul (1, 1)
	51 ddiv (1, 1)
	52 dstore (1, 1)
	53 #4 (1, 1)
	54 goto (1, 1)
	55 64 (1, 1)
	57 iload_1 (1, 2)
	58 i2d (1, 2)
	59 dconst_1 (1, 2)
	60 dsub (1, 2)
	61 ldc2_w (1, 2)
	62 2.0 (1, 2)
	64 ddiv (1, 2)
	65 dstore (1, 2)
	66 #6 (1, 2)
	67 aload_0 (1, 2)
	68 getfield (1, 2)
	69 org/apache/commons/math3/special/Beta$1.val$a:D (1, 2)
	71 dload (1, 2)
	72 #6 (1, 2)
	73 dadd (1, 2)
	74 aload_0 (1, 2)
	75 getfield (1, 2)
	76 org/apache/commons/math3/special/Beta$1.val$a:D (1, 2)
	78 aload_0 (1, 2)
	79 getfield (1, 2)
	80 org/apache/commons/math3/special/Beta$1.val$b:D (1, 2)
	82 dadd (1, 2)
	83 dload (1, 2)
	84 #6 (1, 2)
	85 dadd (1, 2)
	86 dmul (1, 2)
	87 dload_2 (1, 2)
	88 dmul (1, 2)
	89 dneg (1, 2)
	90 aload_0 (1, 2)
	91 getfield (1, 2)
	92 org/apache/commons/math3/special/Beta$1.val$a:D (1, 2)
	94 ldc2_w (1, 2)
	95 2.0 (1, 2)
	97 dload (1, 2)
	98 #6 (1, 2)
	99 dmul (1, 2)
	100 dadd (1, 2)
	101 aload_0 (1, 2)
	102 getfield (1, 2)
	103 org/apache/commons/math3/special/Beta$1.val$a:D (1, 2)
	105 ldc2_w (1, 2)
	106 2.0 (1, 2)
	108 dload (1, 2)
	109 #6 (1, 2)
	110 dmul (1, 2)
	111 dadd (1, 2)
	112 dconst_1 (1, 2)
	113 dadd (1, 2)
	114 dmul (1, 2)
	115 ddiv (1, 2)
	116 dstore (1, 2)
	117 #4 (1, 2)
	118 dload (0, 0)
	119 #4 (0, 0)
	120 dreturn (0, 0)

Method: getA
	0 dconst_1 (0, 0)
	1 dreturn (0, 0)

