Method: logGamma
	0 dload_0 (1, 1)
	1 invokestatic (1, 1)
	2 java/lang/Double.isNaN:(D)Z (1, 1)
	4 ifne (1, 1)
	5 9 (1, 1)
	7 dload_0 (1, 1)
	8 dconst_0 (1, 1)
	9 dcmpg (1, 1)
	10 ifgt (1, 1)
	11 10 (1, 1)
	13 ldc2_w (1, 1)
	14 nan (1, 1)
	16 dstore_2 (1, 1)
	17 goto (1, 1)
	18 151 (1, 1)
	20 dload_0 (2, 1)
	21 ldc2_w (2, 1)
	22 0.5 (2, 1)
	24 dcmpg (2, 1)
	25 ifge (2, 1)
	26 13 (2, 1)
	28 dload_0 (2, 1)
	29 invokestatic (2, 1)
	30 org/apache/commons/math3/special/Gamma.logGamma1p:(D)D (2, 1)
	32 dload_0 (2, 1)
	33 invokestatic (2, 1)
	34 org/apache/commons/math3/util/FastMath.log:(D)D (2, 1)
	36 dsub (2, 1)
	37 dreturn (2, 1)
	38 dload_0 (3, 1)
	39 ldc2_w (3, 1)
	40 2.5 (3, 1)
	42 dcmpg (3, 1)
	43 ifgt (3, 1)
	44 16 (3, 1)
	46 dload_0 (3, 1)
	47 ldc2_w (3, 1)
	48 0.5 (3, 1)
	50 dsub (3, 1)
	51 ldc2_w (3, 1)
	52 0.5 (3, 1)
	54 dsub (3, 1)
	55 invokestatic (3, 1)
	56 org/apache/commons/math3/special/Gamma.logGamma1p:(D)D (3, 1)
	58 dreturn (3, 1)
	59 dload_0 (4, 1)
	60 ldc2_w (4, 1)
	61 8.0 (4, 1)
	63 dcmpg (4, 1)
	64 ifgt (4, 1)
	65 60 (4, 1)
	67 dload_0 (4, 1)
	68 ldc2_w (4, 1)
	69 1.5 (4, 1)
	71 dsub (4, 1)
	72 invokestatic (4, 1)
	73 org/apache/commons/math3/util/FastMath.floor:(D)D (4, 1)
	75 d2i (4, 1)
	76 istore (4, 1)
	77 #4 (4, 1)
	78 dconst_1 (4, 1)
	79 dstore (4, 1)
	80 #5 (4, 1)
	81 iconst_1 (5, 4)
	82 istore (5, 4)
	83 #7 (5, 4)
	84 iload (5, 4)
	85 #7 (5, 4)
	86 iload (5, 4)
	87 #4 (5, 4)
	88 if_icmpgt (5, 4)
	89 19 (5, 4)
	91 dload (5, 4)
	92 #5 (5, 4)
	93 dload_0 (5, 4)
	94 iload (5, 4)
	95 #7 (5, 4)
	96 i2d (5, 4)
	97 dsub (5, 4)
	98 dmul (5, 4)
	99 dstore (5, 4)
	100 #5 (5, 4)
	101 iinc (5, 4)
	102 #7 (5, 4)
	103 -89 (5, 4)
	104 goto (5, 4)
	105 -20 (5, 4)
	107 dload_0 (4, 1)
	108 iload (4, 1)
	109 #4 (4, 1)
	110 iconst_1 (4, 1)
	111 iadd (4, 1)
	112 i2d (4, 1)
	113 dsub (4, 1)
	114 invokestatic (4, 1)
	115 org/apache/commons/math3/special/Gamma.logGamma1p:(D)D (4, 1)
	117 dload (4, 1)
	118 #5 (4, 1)
	119 invokestatic (4, 1)
	120 org/apache/commons/math3/util/FastMath.log:(D)D (4, 1)
	122 dadd (4, 1)
	123 dreturn (4, 1)
	124 dload_0 (5, 2)
	125 invokestatic (5, 2)
	126 org/apache/commons/math3/special/Gamma.lanczos:(D)D (5, 2)
	128 dstore (5, 2)
	129 #4 (5, 2)
	130 dload_0 (5, 2)
	131 ldc2_w (5, 2)
	132 4.7421875 (5, 2)
	134 dadd (5, 2)
	135 ldc2_w (5, 2)
	136 0.5 (5, 2)
	138 dadd (5, 2)
	139 dstore (5, 2)
	140 #6 (5, 2)
	141 dload_0 (5, 2)
	142 ldc2_w (5, 2)
	143 0.5 (5, 2)
	145 dadd (5, 2)
	146 dload (5, 2)
	147 #6 (5, 2)
	148 invokestatic (5, 2)
	149 org/apache/commons/math3/util/FastMath.log:(D)D (5, 2)
	151 dmul (5, 2)
	152 dload (5, 2)
	153 #6 (5, 2)
	154 dsub (5, 2)
	155 getstatic (5, 2)
	156 org/apache/commons/math3/special/Gamma.HALF_LOG_2_PI:D (5, 2)
	158 dadd (5, 2)
	159 dload (5, 2)
	160 #4 (5, 2)
	161 dload_0 (5, 2)
	162 ddiv (5, 2)
	163 invokestatic (5, 2)
	164 org/apache/commons/math3/util/FastMath.log:(D)D (5, 2)
	166 dadd (5, 2)
	167 dstore_2 (5, 2)
	168 dload_2 (0, 0)
	169 dreturn (0, 0)

Method: regularizedGammaP
	0 dload_0 (1, 1)
	1 invokestatic (1, 1)
	2 java/lang/Double.isNaN:(D)Z (1, 1)
	4 ifne (1, 1)
	5 22 (1, 1)
	7 dload_2 (1, 1)
	8 invokestatic (1, 1)
	9 java/lang/Double.isNaN:(D)Z (1, 1)
	11 ifne (1, 1)
	12 15 (1, 1)
	14 dload_0 (1, 1)
	15 dconst_0 (1, 1)
	16 dcmpg (1, 1)
	17 ifle (1, 1)
	18 9 (1, 1)
	20 dload_2 (1, 1)
	21 dconst_0 (1, 1)
	22 dcmpg (1, 1)
	23 ifge (1, 1)
	24 11 (1, 1)
	26 ldc2_w (1, 1)
	27 nan (1, 1)
	29 dstore (1, 1)
	30 #7 (1, 1)
	31 goto (1, 1)
	32 168 (1, 1)
	34 dload_2 (2, 1)
	35 dconst_0 (2, 1)
	36 dcmpl (2, 1)
	37 ifne (2, 1)
	38 9 (2, 1)
	40 dconst_0 (2, 1)
	41 dstore (2, 1)
	42 #7 (2, 1)
	43 goto (2, 1)
	44 156 (2, 1)
	46 dload_2 (3, 1)
	47 dload_0 (3, 1)
	48 dconst_1 (3, 1)
	49 dadd (3, 1)
	50 dcmpl (3, 1)
	51 iflt (3, 1)
	52 19 (3, 1)
	54 dconst_1 (3, 1)
	55 dload_0 (3, 1)
	56 dload_2 (3, 1)
	57 dload (3, 1)
	58 #4 (3, 1)
	59 iload (3, 1)
	60 #6 (3, 1)
	61 invokestatic (3, 1)
	62 org/apache/commons/math3/special/Gamma.regularizedGammaQ:(DDDI)D (3, 1)
	64 dsub (3, 1)
	65 dstore (3, 1)
	66 #7 (3, 1)
	67 goto (3, 1)
	68 132 (3, 1)
	70 dconst_0 (4, 2)
	71 dstore (4, 2)
	72 #9 (4, 2)
	73 dconst_1 (4, 2)
	74 dload_0 (4, 2)
	75 ddiv (4, 2)
	76 dstore (4, 2)
	77 #11 (4, 2)
	78 dload (4, 2)
	79 #11 (4, 2)
	80 dstore (4, 2)
	81 #13 (4, 2)
	82 dload (5, 3)
	83 #11 (5, 3)
	84 dload (5, 3)
	85 #13 (5, 3)
	86 ddiv (5, 3)
	87 invokestatic (5, 3)
	88 org/apache/commons/math3/util/FastMath.abs:(D)D (5, 3)
	90 dload (5, 3)
	91 #4 (5, 3)
	92 dcmpl (5, 3)
	93 ifle (5, 3)
	94 48 (5, 3)
	96 dload (5, 3)
	97 #9 (5, 3)
	98 iload (5, 3)
	99 #6 (5, 3)
	100 i2d (5, 3)
	101 dcmpg (5, 3)
	102 ifge (5, 3)
	103 39 (5, 3)
	105 dload (5, 3)
	106 #13 (5, 3)
	107 ldc2_w (5, 3)
	108 inf (5, 3)
	110 dcmpg (5, 3)
	111 ifge (5, 3)
	112 30 (5, 3)
	114 dload (5, 3)
	115 #9 (5, 3)
	116 dconst_1 (5, 3)
	117 dadd (5, 3)
	118 dstore (5, 3)
	119 #9 (5, 3)
	120 dload (5, 3)
	121 #11 (5, 3)
	122 dload_2 (5, 3)
	123 dload_0 (5, 3)
	124 dload (5, 3)
	125 #9 (5, 3)
	126 dadd (5, 3)
	127 ddiv (5, 3)
	128 dmul (5, 3)
	129 dstore (5, 3)
	130 #11 (5, 3)
	131 dload (5, 3)
	132 #13 (5, 3)
	133 dload (5, 3)
	134 #11 (5, 3)
	135 dadd (5, 3)
	136 dstore (5, 3)
	137 #13 (5, 3)
	138 goto (5, 3)
	139 -56 (5, 3)
	141 dload (6, 1)
	142 #9 (6, 1)
	143 iload (6, 1)
	144 #6 (6, 1)
	145 i2d (6, 1)
	146 dcmpl (6, 1)
	147 iflt (6, 1)
	148 16 (6, 1)
	150 new (6, 1)
	151 org/apache/commons/math3/exception/MaxCountExceededException (6, 1)
	153 dup (6, 1)
	154 iload (6, 1)
	155 #6 (6, 1)
	156 invokestatic (6, 1)
	157 java/lang/Integer.valueOf:(I)Ljava/lang/Integer; (6, 1)
	159 invokespecial (6, 1)
	160 org/apache/commons/math3/exception/MaxCountExceededException.<init>:(Ljava/lang/Number;)V (6, 1)
	162 athrow (6, 1)
	163 dload (7, 1)
	164 #13 (7, 1)
	165 invokestatic (7, 1)
	166 java/lang/Double.isInfinite:(D)Z (7, 1)
	168 ifeq (7, 1)
	169 9 (7, 1)
	171 dconst_1 (7, 1)
	172 dstore (7, 1)
	173 #7 (7, 1)
	174 goto (7, 1)
	175 25 (7, 1)
	177 dload_2 (8, 2)
	178 dneg (8, 2)
	179 dload_0 (8, 2)
	180 dload_2 (8, 2)
	181 invokestatic (8, 2)
	182 org/apache/commons/math3/util/FastMath.log:(D)D (8, 2)
	184 dmul (8, 2)
	185 dadd (8, 2)
	186 dload_0 (8, 2)
	187 invokestatic (8, 2)
	188 org/apache/commons/math3/special/Gamma.logGamma:(D)D (8, 2)
	190 dsub (8, 2)
	191 invokestatic (8, 2)
	192 org/apache/commons/math3/util/FastMath.exp:(D)D (8, 2)
	194 dload (8, 2)
	195 #13 (8, 2)
	196 dmul (8, 2)
	197 dstore (8, 2)
	198 #7 (8, 2)
	199 dload (0, 0)
	200 #7 (0, 0)
	201 dreturn (0, 0)

Method: regularizedGammaQ
	0 dload_0 (1, 1)
	1 invokestatic (1, 1)
	2 java/lang/Double.isNaN:(D)Z (1, 1)
	4 ifne (1, 1)
	5 22 (1, 1)
	7 dload_2 (1, 1)
	8 invokestatic (1, 1)
	9 java/lang/Double.isNaN:(D)Z (1, 1)
	11 ifne (1, 1)
	12 15 (1, 1)
	14 dload_0 (1, 1)
	15 dconst_0 (1, 1)
	16 dcmpg (1, 1)
	17 ifle (1, 1)
	18 9 (1, 1)
	20 dload_2 (1, 1)
	21 dconst_0 (1, 1)
	22 dcmpg (1, 1)
	23 ifge (1, 1)
	24 11 (1, 1)
	26 ldc2_w (1, 1)
	27 nan (1, 1)
	29 dstore (1, 1)
	30 #7 (1, 1)
	31 goto (1, 1)
	32 85 (1, 1)
	34 dload_2 (2, 1)
	35 dconst_0 (2, 1)
	36 dcmpl (2, 1)
	37 ifne (2, 1)
	38 9 (2, 1)
	40 dconst_1 (2, 1)
	41 dstore (2, 1)
	42 #7 (2, 1)
	43 goto (2, 1)
	44 73 (2, 1)
	46 dload_2 (3, 1)
	47 dload_0 (3, 1)
	48 dconst_1 (3, 1)
	49 dadd (3, 1)
	50 dcmpg (3, 1)
	51 ifge (3, 1)
	52 19 (3, 1)
	54 dconst_1 (3, 1)
	55 dload_0 (3, 1)
	56 dload_2 (3, 1)
	57 dload (3, 1)
	58 #4 (3, 1)
	59 iload (3, 1)
	60 #6 (3, 1)
	61 invokestatic (3, 1)
	62 org/apache/commons/math3/special/Gamma.regularizedGammaP:(DDDI)D (3, 1)
	64 dsub (3, 1)
	65 dstore (3, 1)
	66 #7 (3, 1)
	67 goto (3, 1)
	68 49 (3, 1)
	70 new (4, 2)
	71 org/apache/commons/math3/special/Gamma$1 (4, 2)
	73 dup (4, 2)
	74 dload_0 (4, 2)
	75 invokespecial (4, 2)
	76 org/apache/commons/math3/special/Gamma$1.<init>:(D)V (4, 2)
	78 astore (4, 2)
	79 #9 (4, 2)
	80 dconst_1 (4, 2)
	81 aload (4, 2)
	82 #9 (4, 2)
	83 dload_2 (4, 2)
	84 dload (4, 2)
	85 #4 (4, 2)
	86 iload (4, 2)
	87 #6 (4, 2)
	88 invokevirtual (4, 2)
	89 org/apache/commons/math3/util/ContinuedFraction.evaluate:(DDI)D (4, 2)
	91 ddiv (4, 2)
	92 dstore (4, 2)
	93 #7 (4, 2)
	94 dload_2 (4, 2)
	95 dneg (4, 2)
	96 dload_0 (4, 2)
	97 dload_2 (4, 2)
	98 invokestatic (4, 2)
	99 org/apache/commons/math3/util/FastMath.log:(D)D (4, 2)
	101 dmul (4, 2)
	102 dadd (4, 2)
	103 dload_0 (4, 2)
	104 invokestatic (4, 2)
	105 org/apache/commons/math3/special/Gamma.logGamma:(D)D (4, 2)
	107 dsub (4, 2)
	108 invokestatic (4, 2)
	109 org/apache/commons/math3/util/FastMath.exp:(D)D (4, 2)
	111 dload (4, 2)
	112 #7 (4, 2)
	113 dmul (4, 2)
	114 dstore (4, 2)
	115 #7 (4, 2)
	116 dload (0, 0)
	117 #7 (0, 0)
	118 dreturn (0, 0)

Method: digamma
	0 dload_0 (1, 1)
	1 invokestatic (1, 1)
	2 java/lang/Double.isNaN:(D)Z (1, 1)
	4 ifne (1, 1)
	5 10 (1, 1)
	7 dload_0 (1, 1)
	8 invokestatic (1, 1)
	9 java/lang/Double.isInfinite:(D)Z (1, 1)
	11 ifeq (1, 1)
	12 5 (1, 1)
	14 dload_0 (1, 1)
	15 dreturn (1, 1)
	16 dload_0 (1, 1)
	17 dconst_0 (1, 1)
	18 dcmpl (1, 1)
	19 ifle (1, 1)
	20 19 (1, 1)
	22 dload_0 (1, 1)
	23 ldc2_w (1, 1)
	24 1e-05 (1, 1)
	26 dcmpg (1, 1)
	27 ifgt (1, 1)
	28 11 (1, 1)
	30 ldc2_w (1, 1)
	31 -0.5772156649015329 (1, 1)
	33 dconst_1 (1, 1)
	34 dload_0 (1, 1)
	35 ddiv (1, 1)
	36 dsub (1, 1)
	37 dreturn (1, 1)
	38 dload_0 (1, 1)
	39 ldc2_w (1, 1)
	40 49.0 (1, 1)
	42 dcmpl (1, 1)
	43 iflt (1, 1)
	44 38 (1, 1)
	46 dconst_1 (1, 1)
	47 dload_0 (1, 1)
	48 dload_0 (1, 1)
	49 dmul (1, 1)
	50 ddiv (1, 1)
	51 dstore_2 (1, 1)
	52 dload_0 (1, 1)
	53 invokestatic (1, 1)
	54 org/apache/commons/math3/util/FastMath.log:(D)D (1, 1)
	56 ldc2_w (1, 1)
	57 0.5 (1, 1)
	59 dload_0 (1, 1)
	60 ddiv (1, 1)
	61 dsub (1, 1)
	62 dload_2 (1, 1)
	63 ldc2_w (1, 1)
	64 0.08333333333333333 (1, 1)
	66 dload_2 (1, 1)
	67 ldc2_w (1, 1)
	68 0.008333333333333333 (1, 1)
	70 dload_2 (1, 1)
	71 ldc2_w (1, 1)
	72 252.0 (1, 1)
	74 ddiv (1, 1)
	75 dsub (1, 1)
	76 dmul (1, 1)
	77 dadd (1, 1)
	78 dmul (1, 1)
	79 dsub (1, 1)
	80 dreturn (1, 1)
	81 dload_0 (0, 0)
	82 dconst_1 (0, 0)
	83 dadd (0, 0)
	84 invokestatic (0, 0)
	85 org/apache/commons/math3/special/Gamma.digamma:(D)D (0, 0)
	87 dconst_1 (0, 0)
	88 dload_0 (0, 0)
	89 ddiv (0, 0)
	90 dsub (0, 0)
	91 dreturn (0, 0)

Method: trigamma
	0 dload_0 (1, 1)
	1 invokestatic (1, 1)
	2 java/lang/Double.isNaN:(D)Z (1, 1)
	4 ifne (1, 1)
	5 10 (1, 1)
	7 dload_0 (1, 1)
	8 invokestatic (1, 1)
	9 java/lang/Double.isInfinite:(D)Z (1, 1)
	11 ifeq (1, 1)
	12 5 (1, 1)
	14 dload_0 (1, 1)
	15 dreturn (1, 1)
	16 dload_0 (1, 1)
	17 dconst_0 (1, 1)
	18 dcmpl (1, 1)
	19 ifle (1, 1)
	20 17 (1, 1)
	22 dload_0 (1, 1)
	23 ldc2_w (1, 1)
	24 1e-05 (1, 1)
	26 dcmpg (1, 1)
	27 ifgt (1, 1)
	28 9 (1, 1)
	30 dconst_1 (1, 1)
	31 dload_0 (1, 1)
	32 dload_0 (1, 1)
	33 dmul (1, 1)
	34 ddiv (1, 1)
	35 dreturn (1, 1)
	36 dload_0 (1, 1)
	37 ldc2_w (1, 1)
	38 49.0 (1, 1)
	40 dcmpl (1, 1)
	41 iflt (1, 1)
	42 39 (1, 1)
	44 dconst_1 (1, 1)
	45 dload_0 (1, 1)
	46 dload_0 (1, 1)
	47 dmul (1, 1)
	48 ddiv (1, 1)
	49 dstore_2 (1, 1)
	50 dconst_1 (1, 1)
	51 dload_0 (1, 1)
	52 ddiv (1, 1)
	53 dload_2 (1, 1)
	54 ldc2_w (1, 1)
	55 2.0 (1, 1)
	57 ddiv (1, 1)
	58 dadd (1, 1)
	59 dload_2 (1, 1)
	60 dload_0 (1, 1)
	61 ddiv (1, 1)
	62 ldc2_w (1, 1)
	63 0.16666666666666666 (1, 1)
	65 dload_2 (1, 1)
	66 ldc2_w (1, 1)
	67 0.03333333333333333 (1, 1)
	69 dload_2 (1, 1)
	70 ldc2_w (1, 1)
	71 42.0 (1, 1)
	73 ddiv (1, 1)
	74 dadd (1, 1)
	75 dmul (1, 1)
	76 dsub (1, 1)
	77 dmul (1, 1)
	78 dadd (1, 1)
	79 dreturn (1, 1)
	80 dload_0 (0, 0)
	81 dconst_1 (0, 0)
	82 dadd (0, 0)
	83 invokestatic (0, 0)
	84 org/apache/commons/math3/special/Gamma.trigamma:(D)D (0, 0)
	86 dconst_1 (0, 0)
	87 dload_0 (0, 0)
	88 dload_0 (0, 0)
	89 dmul (0, 0)
	90 ddiv (0, 0)
	91 dadd (0, 0)
	92 dreturn (0, 0)

Method: lanczos
	0 dconst_0 (0, 0)
	1 dstore_2 (0, 0)
	2 getstatic (1, 4)
	3 org/apache/commons/math3/special/Gamma.LANCZOS:[D (1, 4)
	5 arraylength (1, 4)
	6 iconst_1 (1, 4)
	7 isub (1, 4)
	8 istore (1, 4)
	9 #4 (1, 4)
	10 iload (1, 4)
	11 #4 (1, 4)
	12 ifle (1, 4)
	13 24 (1, 4)
	15 dload_2 (1, 4)
	16 getstatic (1, 4)
	17 org/apache/commons/math3/special/Gamma.LANCZOS:[D (1, 4)
	19 iload (1, 4)
	20 #4 (1, 4)
	21 daload (1, 4)
	22 dload_0 (1, 4)
	23 iload (1, 4)
	24 #4 (1, 4)
	25 i2d (1, 4)
	26 dadd (1, 4)
	27 ddiv (1, 4)
	28 dadd (1, 4)
	29 dstore_2 (1, 4)
	30 iinc (1, 4)
	31 #4 (1, 4)
	32 -89 (1, 4)
	33 goto (1, 4)
	34 -23 (1, 4)
	36 dload_2 (0, 0)
	37 getstatic (0, 0)
	38 org/apache/commons/math3/special/Gamma.LANCZOS:[D (0, 0)
	40 iconst_0 (0, 0)
	41 daload (0, 0)
	42 dadd (0, 0)
	43 dreturn (0, 0)

Method: invGamma1pm1
	0 dload_0 (1, 1)
	1 ldc2_w (1, 1)
	2 -0.5 (1, 1)
	4 dcmpg (1, 1)
	5 ifge (1, 1)
	6 22 (1, 1)
	8 new (1, 1)
	9 org/apache/commons/math3/exception/NumberIsTooSmallException (1, 1)
	11 dup (1, 1)
	12 dload_0 (1, 1)
	13 invokestatic (1, 1)
	14 java/lang/Double.valueOf:(D)Ljava/lang/Double; (1, 1)
	16 ldc2_w (1, 1)
	17 -0.5 (1, 1)
	19 invokestatic (1, 1)
	20 java/lang/Double.valueOf:(D)Ljava/lang/Double; (1, 1)
	22 iconst_1 (1, 1)
	23 invokespecial (1, 1)
	24 org/apache/commons/math3/exception/NumberIsTooSmallException.<init>:(Ljava/lang/Number;Ljava/lang/Number;Z)V (1, 1)
	26 athrow (1, 1)
	27 dload_0 (1, 1)
	28 ldc2_w (1, 1)
	29 1.5 (1, 1)
	31 dcmpl (1, 1)
	32 ifle (1, 1)
	33 22 (1, 1)
	35 new (1, 1)
	36 org/apache/commons/math3/exception/NumberIsTooLargeException (1, 1)
	38 dup (1, 1)
	39 dload_0 (1, 1)
	40 invokestatic (1, 1)
	41 java/lang/Double.valueOf:(D)Ljava/lang/Double; (1, 1)
	43 ldc2_w (1, 1)
	44 1.5 (1, 1)
	46 invokestatic (1, 1)
	47 java/lang/Double.valueOf:(D)Ljava/lang/Double; (1, 1)
	49 iconst_1 (1, 1)
	50 invokespecial (1, 1)
	51 org/apache/commons/math3/exception/NumberIsTooLargeException.<init>:(Ljava/lang/Number;Ljava/lang/Number;Z)V (1, 1)
	53 athrow (1, 1)
	54 dload_0 (0, 0)
	55 ldc2_w (0, 0)
	56 0.5 (0, 0)
	58 dcmpg (0, 0)
	59 ifgt (0, 0)
	60 7 (0, 0)
	62 dload_0 (0, 0)
	63 goto (0, 0)
	64 12 (0, 0)
	66 dload_0 (0, 0)
	67 ldc2_w (0, 0)
	68 0.5 (0, 0)
	70 dsub (0, 0)
	71 ldc2_w (0, 0)
	72 0.5 (0, 0)
	74 dsub (0, 0)
	75 dstore (0, 0)
	76 #4 (0, 0)
	77 dload (1, 1)
	78 #4 (1, 1)
	79 dconst_0 (1, 1)
	80 dcmpg (1, 1)
	81 ifge (1, 1)
	82 298 (1, 1)
	84 ldc2_w (1, 1)
	85 6.116095104481416e-09 (1, 1)
	87 dload (1, 1)
	88 #4 (1, 1)
	89 ldc2_w (1, 1)
	90 6.247308301164655e-09 (1, 1)
	92 dmul (1, 1)
	93 dadd (1, 1)
	94 dstore (1, 1)
	95 #6 (1, 1)
	96 ldc2_w (1, 1)
	97 1.9575583661463974e-10 (1, 1)
	99 dstore (1, 1)
	100 #8 (1, 1)
	101 ldc2_w (1, 1)
	102 -6.077618957228252e-08 (1, 1)
	104 dload (1, 1)
	105 #4 (1, 1)
	106 dload (1, 1)
	107 #8 (1, 1)
	108 dmul (1, 1)
	109 dadd (1, 1)
	110 dstore (1, 1)
	111 #8 (1, 1)
	112 ldc2_w (1, 1)
	113 9.926418406727737e-07 (1, 1)
	115 dload (1, 1)
	116 #4 (1, 1)
	117 dload (1, 1)
	118 #8 (1, 1)
	119 dmul (1, 1)
	120 dadd (1, 1)
	121 dstore (1, 1)
	122 #8 (1, 1)
	123 ldc2_w (1, 1)
	124 -6.4304548177935305e-06 (1, 1)
	126 dload (1, 1)
	127 #4 (1, 1)
	128 dload (1, 1)
	129 #8 (1, 1)
	130 dmul (1, 1)
	131 dadd (1, 1)
	132 dstore (1, 1)
	133 #8 (1, 1)
	134 ldc2_w (1, 1)
	135 -8.514194324403149e-06 (1, 1)
	137 dload (1, 1)
	138 #4 (1, 1)
	139 dload (1, 1)
	140 #8 (1, 1)
	141 dmul (1, 1)
	142 dadd (1, 1)
	143 dstore (1, 1)
	144 #8 (1, 1)
	145 ldc2_w (1, 1)
	146 0.0004939449793824468 (1, 1)
	148 dload (1, 1)
	149 #4 (1, 1)
	150 dload (1, 1)
	151 #8 (1, 1)
	152 dmul (1, 1)
	153 dadd (1, 1)
	154 dstore (1, 1)
	155 #8 (1, 1)
	156 ldc2_w (1, 1)
	157 0.026620534842894922 (1, 1)
	159 dload (1, 1)
	160 #4 (1, 1)
	161 dload (1, 1)
	162 #8 (1, 1)
	163 dmul (1, 1)
	164 dadd (1, 1)
	165 dstore (1, 1)
	166 #8 (1, 1)
	167 ldc2_w (1, 1)
	168 0.203610414066807 (1, 1)
	170 dload (1, 1)
	171 #4 (1, 1)
	172 dload (1, 1)
	173 #8 (1, 1)
	174 dmul (1, 1)
	175 dadd (1, 1)
	176 dstore (1, 1)
	177 #8 (1, 1)
	178 dconst_1 (1, 1)
	179 dload (1, 1)
	180 #4 (1, 1)
	181 dload (1, 1)
	182 #8 (1, 1)
	183 dmul (1, 1)
	184 dadd (1, 1)
	185 dstore (1, 1)
	186 #8 (1, 1)
	187 ldc2_w (1, 1)
	188 -2.056338416977607e-07 (1, 1)
	190 dload (1, 1)
	191 #4 (1, 1)
	192 dload (1, 1)
	193 #6 (1, 1)
	194 dload (1, 1)
	195 #8 (1, 1)
	196 ddiv (1, 1)
	197 dmul (1, 1)
	198 dadd (1, 1)
	199 dstore (1, 1)
	200 #10 (1, 1)
	201 ldc2_w (1, 1)
	202 1.133027231981696e-06 (1, 1)
	204 dload (1, 1)
	205 #4 (1, 1)
	206 dload (1, 1)
	207 #10 (1, 1)
	208 dmul (1, 1)
	209 dadd (1, 1)
	210 dstore (1, 1)
	211 #10 (1, 1)
	212 ldc2_w (1, 1)
	213 -1.2504934821426706e-06 (1, 1)
	215 dload (1, 1)
	216 #4 (1, 1)
	217 dload (1, 1)
	218 #10 (1, 1)
	219 dmul (1, 1)
	220 dadd (1, 1)
	221 dstore (1, 1)
	222 #10 (1, 1)
	223 ldc2_w (1, 1)
	224 -2.013485478078824e-05 (1, 1)
	226 dload (1, 1)
	227 #4 (1, 1)
	228 dload (1, 1)
	229 #10 (1, 1)
	230 dmul (1, 1)
	231 dadd (1, 1)
	232 dstore (1, 1)
	233 #10 (1, 1)
	234 ldc2_w (1, 1)
	235 0.0001280502823881162 (1, 1)
	237 dload (1, 1)
	238 #4 (1, 1)
	239 dload (1, 1)
	240 #10 (1, 1)
	241 dmul (1, 1)
	242 dadd (1, 1)
	243 dstore (1, 1)
	244 #10 (1, 1)
	245 ldc2_w (1, 1)
	246 -0.00021524167411495098 (1, 1)
	248 dload (1, 1)
	249 #4 (1, 1)
	250 dload (1, 1)
	251 #10 (1, 1)
	252 dmul (1, 1)
	253 dadd (1, 1)
	254 dstore (1, 1)
	255 #10 (1, 1)
	256 ldc2_w (1, 1)
	257 -0.0011651675918590652 (1, 1)
	259 dload (1, 1)
	260 #4 (1, 1)
	261 dload (1, 1)
	262 #10 (1, 1)
	263 dmul (1, 1)
	264 dadd (1, 1)
	265 dstore (1, 1)
	266 #10 (1, 1)
	267 ldc2_w (1, 1)
	268 0.0072189432466631 (1, 1)
	270 dload (1, 1)
	271 #4 (1, 1)
	272 dload (1, 1)
	273 #10 (1, 1)
	274 dmul (1, 1)
	275 dadd (1, 1)
	276 dstore (1, 1)
	277 #10 (1, 1)
	278 ldc2_w (1, 1)
	279 -0.009621971527876973 (1, 1)
	281 dload (1, 1)
	282 #4 (1, 1)
	283 dload (1, 1)
	284 #10 (1, 1)
	285 dmul (1, 1)
	286 dadd (1, 1)
	287 dstore (1, 1)
	288 #10 (1, 1)
	289 ldc2_w (1, 1)
	290 -0.04219773455554433 (1, 1)
	292 dload (1, 1)
	293 #4 (1, 1)
	294 dload (1, 1)
	295 #10 (1, 1)
	296 dmul (1, 1)
	297 dadd (1, 1)
	298 dstore (1, 1)
	299 #10 (1, 1)
	300 ldc2_w (1, 1)
	301 0.16653861138229148 (1, 1)
	303 dload (1, 1)
	304 #4 (1, 1)
	305 dload (1, 1)
	306 #10 (1, 1)
	307 dmul (1, 1)
	308 dadd (1, 1)
	309 dstore (1, 1)
	310 #10 (1, 1)
	311 ldc2_w (1, 1)
	312 -0.04200263503409524 (1, 1)
	314 dload (1, 1)
	315 #4 (1, 1)
	316 dload (1, 1)
	317 #10 (1, 1)
	318 dmul (1, 1)
	319 dadd (1, 1)
	320 dstore (1, 1)
	321 #10 (1, 1)
	322 ldc2_w (1, 1)
	323 -0.6558780715202539 (1, 1)
	325 dload (1, 1)
	326 #4 (1, 1)
	327 dload (1, 1)
	328 #10 (1, 1)
	329 dmul (1, 1)
	330 dadd (1, 1)
	331 dstore (1, 1)
	332 #10 (1, 1)
	333 ldc2_w (1, 1)
	334 -0.42278433509846713 (1, 1)
	336 dload (1, 1)
	337 #4 (1, 1)
	338 dload (1, 1)
	339 #10 (1, 1)
	340 dmul (1, 1)
	341 dadd (1, 1)
	342 dstore (1, 1)
	343 #10 (1, 1)
	344 dload_0 (2, 1)
	345 ldc2_w (2, 1)
	346 0.5 (2, 1)
	348 dcmpl (2, 1)
	349 ifle (2, 1)
	350 14 (2, 1)
	352 dload (2, 1)
	353 #4 (2, 1)
	354 dload (2, 1)
	355 #10 (2, 1)
	356 dmul (2, 1)
	357 dload_0 (2, 1)
	358 ddiv (2, 1)
	359 dstore_2 (2, 1)
	360 goto (2, 1)
	361 16 (2, 1)
	363 dload_0 (3, 2)
	364 dload (3, 2)
	365 #10 (3, 2)
	366 ldc2_w (3, 2)
	367 0.5 (3, 2)
	369 dadd (3, 2)
	370 ldc2_w (3, 2)
	371 0.5 (3, 2)
	373 dadd (3, 2)
	374 dmul (3, 2)
	375 dstore_2 (3, 2)
	376 goto (2, 2)
	377 310 (2, 2)
	379 ldc2_w (2, 2)
	380 4.343529937408594e-15 (2, 2)
	382 dstore (2, 2)
	383 #6 (2, 2)
	384 ldc2_w (2, 2)
	385 -1.2494415722763663e-13 (2, 2)
	387 dload (2, 2)
	388 #4 (2, 2)
	389 dload (2, 2)
	390 #6 (2, 2)
	391 dmul (2, 2)
	392 dadd (2, 2)
	393 dstore (2, 2)
	394 #6 (2, 2)
	395 ldc2_w (2, 2)
	396 1.5728330277104463e-12 (2, 2)
	398 dload (2, 2)
	399 #4 (2, 2)
	400 dload (2, 2)
	401 #6 (2, 2)
	402 dmul (2, 2)
	403 dadd (2, 2)
	404 dstore (2, 2)
	405 #6 (2, 2)
	406 ldc2_w (2, 2)
	407 4.686843322948848e-11 (2, 2)
	409 dload (2, 2)
	410 #4 (2, 2)
	411 dload (2, 2)
	412 #6 (2, 2)
	413 dmul (2, 2)
	414 dadd (2, 2)
	415 dstore (2, 2)
	416 #6 (2, 2)
	417 ldc2_w (2, 2)
	418 6.820161668496171e-10 (2, 2)
	420 dload (2, 2)
	421 #4 (2, 2)
	422 dload (2, 2)
	423 #6 (2, 2)
	424 dmul (2, 2)
	425 dadd (2, 2)
	426 dstore (2, 2)
	427 #6 (2, 2)
	428 ldc2_w (2, 2)
	429 6.8716741130671986e-09 (2, 2)
	431 dload (2, 2)
	432 #4 (2, 2)
	433 dload (2, 2)
	434 #6 (2, 2)
	435 dmul (2, 2)
	436 dadd (2, 2)
	437 dstore (2, 2)
	438 #6 (2, 2)
	439 ldc2_w (2, 2)
	440 6.116095104481416e-09 (2, 2)
	442 dload (2, 2)
	443 #4 (2, 2)
	444 dload (2, 2)
	445 #6 (2, 2)
	446 dmul (2, 2)
	447 dadd (2, 2)
	448 dstore (2, 2)
	449 #6 (2, 2)
	450 ldc2_w (2, 2)
	451 0.00026923694661863613 (2, 2)
	453 dstore (2, 2)
	454 #8 (2, 2)
	455 ldc2_w (2, 2)
	456 0.004956830093825887 (2, 2)
	458 dload (2, 2)
	459 #4 (2, 2)
	460 dload (2, 2)
	461 #8 (2, 2)
	462 dmul (2, 2)
	463 dadd (2, 2)
	464 dstore (2, 2)
	465 #8 (2, 2)
	466 ldc2_w (2, 2)
	467 0.054642130860422966 (2, 2)
	469 dload (2, 2)
	470 #4 (2, 2)
	471 dload (2, 2)
	472 #8 (2, 2)
	473 dmul (2, 2)
	474 dadd (2, 2)
	475 dstore (2, 2)
	476 #8 (2, 2)
	477 ldc2_w (2, 2)
	478 0.3056961078365221 (2, 2)
	480 dload (2, 2)
	481 #4 (2, 2)
	482 dload (2, 2)
	483 #8 (2, 2)
	484 dmul (2, 2)
	485 dadd (2, 2)
	486 dstore (2, 2)
	487 #8 (2, 2)
	488 dconst_1 (2, 2)
	489 dload (2, 2)
	490 #4 (2, 2)
	491 dload (2, 2)
	492 #8 (2, 2)
	493 dmul (2, 2)
	494 dadd (2, 2)
	495 dstore (2, 2)
	496 #8 (2, 2)
	497 ldc2_w (2, 2)
	498 -2.056338416977607e-07 (2, 2)
	500 dload (2, 2)
	501 #6 (2, 2)
	502 dload (2, 2)
	503 #8 (2, 2)
	504 ddiv (2, 2)
	505 dload (2, 2)
	506 #4 (2, 2)
	507 dmul (2, 2)
	508 dadd (2, 2)
	509 dstore (2, 2)
	510 #10 (2, 2)
	511 ldc2_w (2, 2)
	512 1.133027231981696e-06 (2, 2)
	514 dload (2, 2)
	515 #4 (2, 2)
	516 dload (2, 2)
	517 #10 (2, 2)
	518 dmul (2, 2)
	519 dadd (2, 2)
	520 dstore (2, 2)
	521 #10 (2, 2)
	522 ldc2_w (2, 2)
	523 -1.2504934821426706e-06 (2, 2)
	525 dload (2, 2)
	526 #4 (2, 2)
	527 dload (2, 2)
	528 #10 (2, 2)
	529 dmul (2, 2)
	530 dadd (2, 2)
	531 dstore (2, 2)
	532 #10 (2, 2)
	533 ldc2_w (2, 2)
	534 -2.013485478078824e-05 (2, 2)
	536 dload (2, 2)
	537 #4 (2, 2)
	538 dload (2, 2)
	539 #10 (2, 2)
	540 dmul (2, 2)
	541 dadd (2, 2)
	542 dstore (2, 2)
	543 #10 (2, 2)
	544 ldc2_w (2, 2)
	545 0.0001280502823881162 (2, 2)
	547 dload (2, 2)
	548 #4 (2, 2)
	549 dload (2, 2)
	550 #10 (2, 2)
	551 dmul (2, 2)
	552 dadd (2, 2)
	553 dstore (2, 2)
	554 #10 (2, 2)
	555 ldc2_w (2, 2)
	556 -0.00021524167411495098 (2, 2)
	558 dload (2, 2)
	559 #4 (2, 2)
	560 dload (2, 2)
	561 #10 (2, 2)
	562 dmul (2, 2)
	563 dadd (2, 2)
	564 dstore (2, 2)
	565 #10 (2, 2)
	566 ldc2_w (2, 2)
	567 -0.0011651675918590652 (2, 2)
	569 dload (2, 2)
	570 #4 (2, 2)
	571 dload (2, 2)
	572 #10 (2, 2)
	573 dmul (2, 2)
	574 dadd (2, 2)
	575 dstore (2, 2)
	576 #10 (2, 2)
	577 ldc2_w (2, 2)
	578 0.0072189432466631 (2, 2)
	580 dload (2, 2)
	581 #4 (2, 2)
	582 dload (2, 2)
	583 #10 (2, 2)
	584 dmul (2, 2)
	585 dadd (2, 2)
	586 dstore (2, 2)
	587 #10 (2, 2)
	588 ldc2_w (2, 2)
	589 -0.009621971527876973 (2, 2)
	591 dload (2, 2)
	592 #4 (2, 2)
	593 dload (2, 2)
	594 #10 (2, 2)
	595 dmul (2, 2)
	596 dadd (2, 2)
	597 dstore (2, 2)
	598 #10 (2, 2)
	599 ldc2_w (2, 2)
	600 -0.04219773455554433 (2, 2)
	602 dload (2, 2)
	603 #4 (2, 2)
	604 dload (2, 2)
	605 #10 (2, 2)
	606 dmul (2, 2)
	607 dadd (2, 2)
	608 dstore (2, 2)
	609 #10 (2, 2)
	610 ldc2_w (2, 2)
	611 0.16653861138229148 (2, 2)
	613 dload (2, 2)
	614 #4 (2, 2)
	615 dload (2, 2)
	616 #10 (2, 2)
	617 dmul (2, 2)
	618 dadd (2, 2)
	619 dstore (2, 2)
	620 #10 (2, 2)
	621 ldc2_w (2, 2)
	622 -0.04200263503409524 (2, 2)
	624 dload (2, 2)
	625 #4 (2, 2)
	626 dload (2, 2)
	627 #10 (2, 2)
	628 dmul (2, 2)
	629 dadd (2, 2)
	630 dstore (2, 2)
	631 #10 (2, 2)
	632 ldc2_w (2, 2)
	633 -0.6558780715202539 (2, 2)
	635 dload (2, 2)
	636 #4 (2, 2)
	637 dload (2, 2)
	638 #10 (2, 2)
	639 dmul (2, 2)
	640 dadd (2, 2)
	641 dstore (2, 2)
	642 #10 (2, 2)
	643 ldc2_w (2, 2)
	644 0.5772156649015329 (2, 2)
	646 dload (2, 2)
	647 #4 (2, 2)
	648 dload (2, 2)
	649 #10 (2, 2)
	650 dmul (2, 2)
	651 dadd (2, 2)
	652 dstore (2, 2)
	653 #10 (2, 2)
	654 dload_0 (3, 1)
	655 ldc2_w (3, 1)
	656 0.5 (3, 1)
	658 dcmpl (3, 1)
	659 ifle (3, 1)
	660 22 (3, 1)
	662 dload (3, 1)
	663 #4 (3, 1)
	664 dload_0 (3, 1)
	665 ddiv (3, 1)
	666 dload (3, 1)
	667 #10 (3, 1)
	668 ldc2_w (3, 1)
	669 0.5 (3, 1)
	671 dsub (3, 1)
	672 ldc2_w (3, 1)
	673 0.5 (3, 1)
	675 dsub (3, 1)
	676 dmul (3, 1)
	677 dstore_2 (3, 1)
	678 goto (3, 1)
	679 8 (3, 1)
	681 dload_0 (4, 2)
	682 dload (4, 2)
	683 #10 (4, 2)
	684 dmul (4, 2)
	685 dstore_2 (4, 2)
	686 dload_2 (0, 0)
	687 dreturn (0, 0)

Method: logGamma1p
	0 dload_0 (1, 1)
	1 ldc2_w (1, 1)
	2 -0.5 (1, 1)
	4 dcmpg (1, 1)
	5 ifge (1, 1)
	6 22 (1, 1)
	8 new (1, 1)
	9 org/apache/commons/math3/exception/NumberIsTooSmallException (1, 1)
	11 dup (1, 1)
	12 dload_0 (1, 1)
	13 invokestatic (1, 1)
	14 java/lang/Double.valueOf:(D)Ljava/lang/Double; (1, 1)
	16 ldc2_w (1, 1)
	17 -0.5 (1, 1)
	19 invokestatic (1, 1)
	20 java/lang/Double.valueOf:(D)Ljava/lang/Double; (1, 1)
	22 iconst_1 (1, 1)
	23 invokespecial (1, 1)
	24 org/apache/commons/math3/exception/NumberIsTooSmallException.<init>:(Ljava/lang/Number;Ljava/lang/Number;Z)V (1, 1)
	26 athrow (1, 1)
	27 dload_0 (1, 1)
	28 ldc2_w (1, 1)
	29 1.5 (1, 1)
	31 dcmpl (1, 1)
	32 ifle (1, 1)
	33 22 (1, 1)
	35 new (1, 1)
	36 org/apache/commons/math3/exception/NumberIsTooLargeException (1, 1)
	38 dup (1, 1)
	39 dload_0 (1, 1)
	40 invokestatic (1, 1)
	41 java/lang/Double.valueOf:(D)Ljava/lang/Double; (1, 1)
	43 ldc2_w (1, 1)
	44 1.5 (1, 1)
	46 invokestatic (1, 1)
	47 java/lang/Double.valueOf:(D)Ljava/lang/Double; (1, 1)
	49 iconst_1 (1, 1)
	50 invokespecial (1, 1)
	51 org/apache/commons/math3/exception/NumberIsTooLargeException.<init>:(Ljava/lang/Number;Ljava/lang/Number;Z)V (1, 1)
	53 athrow (1, 1)
	54 dload_0 (0, 0)
	55 invokestatic (0, 0)
	56 org/apache/commons/math3/special/Gamma.invGamma1pm1:(D)D (0, 0)
	58 invokestatic (0, 0)
	59 org/apache/commons/math3/util/FastMath.log1p:(D)D (0, 0)
	61 dneg (0, 0)
	62 dreturn (0, 0)

Method: gamma
	0 dload_0 (1, 1)
	1 dload_0 (1, 1)
	2 invokestatic (1, 1)
	3 org/apache/commons/math3/util/FastMath.rint:(D)D (1, 1)
	5 dcmpl (1, 1)
	6 ifne (1, 1)
	7 13 (1, 1)
	9 dload_0 (1, 1)
	10 dconst_0 (1, 1)
	11 dcmpg (1, 1)
	12 ifgt (1, 1)
	13 7 (1, 1)
	15 ldc2_w (1, 1)
	16 nan (1, 1)
	18 dreturn (1, 1)
	19 dload_0 (0, 0)
	20 invokestatic (0, 0)
	21 org/apache/commons/math3/util/FastMath.abs:(D)D (0, 0)
	23 dstore (0, 0)
	24 #4 (0, 0)
	25 dload (1, 1)
	26 #4 (1, 1)
	27 ldc2_w (1, 1)
	28 20.0 (1, 1)
	30 dcmpg (1, 1)
	31 ifgt (1, 1)
	32 103 (1, 1)
	34 dload_0 (2, 1)
	35 dconst_1 (2, 1)
	36 dcmpl (2, 1)
	37 iflt (2, 1)
	38 50 (2, 1)
	40 dconst_1 (2, 1)
	41 dstore (2, 1)
	42 #6 (2, 1)
	43 dload_0 (2, 1)
	44 dstore (2, 1)
	45 #8 (2, 1)
	46 dload (3, 3)
	47 #8 (3, 3)
	48 ldc2_w (3, 3)
	49 2.5 (3, 3)
	51 dcmpl (3, 3)
	52 ifle (3, 3)
	53 19 (3, 3)
	55 dload (3, 3)
	56 #8 (3, 3)
	57 dconst_1 (3, 3)
	58 dsub (3, 3)
	59 dstore (3, 3)
	60 #8 (3, 3)
	61 dload (3, 3)
	62 #6 (3, 3)
	63 dload (3, 3)
	64 #8 (3, 3)
	65 dmul (3, 3)
	66 dstore (3, 3)
	67 #6 (3, 3)
	68 goto (3, 3)
	69 -22 (3, 3)
	71 dload (2, 1)
	72 #6 (2, 1)
	73 dconst_1 (2, 1)
	74 dload (2, 1)
	75 #8 (2, 1)
	76 dconst_1 (2, 1)
	77 dsub (2, 1)
	78 invokestatic (2, 1)
	79 org/apache/commons/math3/special/Gamma.invGamma1pm1:(D)D (2, 1)
	81 dadd (2, 1)
	82 ddiv (2, 1)
	83 dstore_2 (2, 1)
	84 goto (3, 2)
	85 125 (3, 2)
	87 dload_0 (3, 2)
	88 dstore (3, 2)
	89 #6 (3, 2)
	90 dload_0 (3, 2)
	91 dstore (3, 2)
	92 #8 (3, 2)
	93 dload (4, 3)
	94 #8 (4, 3)
	95 ldc2_w (4, 3)
	96 -0.5 (4, 3)
	98 dcmpg (4, 3)
	99 ifge (4, 3)
	100 19 (4, 3)
	102 dload (4, 3)
	103 #8 (4, 3)
	104 dconst_1 (4, 3)
	105 dadd (4, 3)
	106 dstore (4, 3)
	107 #8 (4, 3)
	108 dload (4, 3)
	109 #6 (4, 3)
	110 dload (4, 3)
	111 #8 (4, 3)
	112 dmul (4, 3)
	113 dstore (4, 3)
	114 #6 (4, 3)
	115 goto (4, 3)
	116 -22 (4, 3)
	118 dconst_1 (3, 2)
	119 dload (3, 2)
	120 #6 (3, 2)
	121 dconst_1 (3, 2)
	122 dload (3, 2)
	123 #8 (3, 2)
	124 invokestatic (3, 2)
	125 org/apache/commons/math3/special/Gamma.invGamma1pm1:(D)D (3, 2)
	127 dadd (3, 2)
	128 dmul (3, 2)
	129 ddiv (3, 2)
	130 dstore_2 (3, 2)
	131 goto (1, 1)
	132 78 (1, 1)
	134 dload (2, 2)
	135 #4 (2, 2)
	136 ldc2_w (2, 2)
	137 4.7421875 (2, 2)
	139 dadd (2, 2)
	140 ldc2_w (2, 2)
	141 0.5 (2, 2)
	143 dadd (2, 2)
	144 dstore (2, 2)
	145 #6 (2, 2)
	146 ldc2_w (2, 2)
	147 2.5066282746310007 (2, 2)
	149 dload (2, 2)
	150 #4 (2, 2)
	151 ddiv (2, 2)
	152 dload (2, 2)
	153 #6 (2, 2)
	154 dload (2, 2)
	155 #4 (2, 2)
	156 ldc2_w (2, 2)
	157 0.5 (2, 2)
	159 dadd (2, 2)
	160 invokestatic (2, 2)
	161 org/apache/commons/math3/util/FastMath.pow:(DD)D (2, 2)
	163 dmul (2, 2)
	164 dload (2, 2)
	165 #6 (2, 2)
	166 dneg (2, 2)
	167 invokestatic (2, 2)
	168 org/apache/commons/math3/util/FastMath.exp:(D)D (2, 2)
	170 dmul (2, 2)
	171 dload (2, 2)
	172 #4 (2, 2)
	173 invokestatic (2, 2)
	174 org/apache/commons/math3/special/Gamma.lanczos:(D)D (2, 2)
	176 dmul (2, 2)
	177 dstore (2, 2)
	178 #8 (2, 2)
	179 dload_0 (3, 1)
	180 dconst_0 (3, 1)
	181 dcmpl (3, 1)
	182 ifle (3, 1)
	183 9 (3, 1)
	185 dload (3, 1)
	186 #8 (3, 1)
	187 dstore_2 (3, 1)
	188 goto (3, 1)
	189 21 (3, 1)
	191 ldc2_w (5, 4)
	192 -3.141592653589793 (5, 4)
	194 dload_0 (5, 4)
	195 ldc2_w (5, 4)
	196 3.141592653589793 (5, 4)
	198 dload_0 (5, 4)
	199 dmul (5, 4)
	200 invokestatic (5, 4)
	201 org/apache/commons/math3/util/FastMath.sin:(D)D (5, 4)
	203 dmul (5, 4)
	204 dload (5, 4)
	205 #8 (5, 4)
	206 dmul (5, 4)
	207 ddiv (5, 4)
	208 dstore_2 (5, 4)
	209 dload_2 (0, 0)
	210 dreturn (0, 0)

Method: <clinit>
	0 bipush (0, 0)
	1 15 (0, 0)
	2 newarray (0, 0)
	3 7 (0, 0)
	4 dup (0, 0)
	5 iconst_0 (0, 0)
	6 ldc2_w (0, 0)
	7 0.9999999999999971 (0, 0)
	9 dastore (0, 0)
	10 dup (0, 0)
	11 iconst_1 (0, 0)
	12 ldc2_w (0, 0)
	13 57.15623566586292 (0, 0)
	15 dastore (0, 0)
	16 dup (0, 0)
	17 iconst_2 (0, 0)
	18 ldc2_w (0, 0)
	19 -59.59796035547549 (0, 0)
	21 dastore (0, 0)
	22 dup (0, 0)
	23 iconst_3 (0, 0)
	24 ldc2_w (0, 0)
	25 14.136097974741746 (0, 0)
	27 dastore (0, 0)
	28 dup (0, 0)
	29 iconst_4 (0, 0)
	30 ldc2_w (0, 0)
	31 -0.4919138160976202 (0, 0)
	33 dastore (0, 0)
	34 dup (0, 0)
	35 iconst_5 (0, 0)
	36 ldc2_w (0, 0)
	37 3.399464998481189e-05 (0, 0)
	39 dastore (0, 0)
	40 dup (0, 0)
	41 bipush (0, 0)
	42 6 (0, 0)
	43 ldc2_w (0, 0)
	44 4.652362892704858e-05 (0, 0)
	46 dastore (0, 0)
	47 dup (0, 0)
	48 bipush (0, 0)
	49 7 (0, 0)
	50 ldc2_w (0, 0)
	51 -9.837447530487956e-05 (0, 0)
	53 dastore (0, 0)
	54 dup (0, 0)
	55 bipush (0, 0)
	56 8 (0, 0)
	57 ldc2_w (0, 0)
	58 0.0001580887032249125 (0, 0)
	60 dastore (0, 0)
	61 dup (0, 0)
	62 bipush (0, 0)
	63 9 (0, 0)
	64 ldc2_w (0, 0)
	65 -0.00021026444172410488 (0, 0)
	67 dastore (0, 0)
	68 dup (0, 0)
	69 bipush (0, 0)
	70 10 (0, 0)
	71 ldc2_w (0, 0)
	72 0.00021743961811521265 (0, 0)
	74 dastore (0, 0)
	75 dup (0, 0)
	76 bipush (0, 0)
	77 11 (0, 0)
	78 ldc2_w (0, 0)
	79 -0.0001643181065367639 (0, 0)
	81 dastore (0, 0)
	82 dup (0, 0)
	83 bipush (0, 0)
	84 12 (0, 0)
	85 ldc2_w (0, 0)
	86 8.441822398385275e-05 (0, 0)
	88 dastore (0, 0)
	89 dup (0, 0)
	90 bipush (0, 0)
	91 13 (0, 0)
	92 ldc2_w (0, 0)
	93 -2.6190838401581408e-05 (0, 0)
	95 dastore (0, 0)
	96 dup (0, 0)
	97 bipush (0, 0)
	98 14 (0, 0)
	99 ldc2_w (0, 0)
	100 3.6899182659531625e-06 (0, 0)
	102 dastore (0, 0)
	103 putstatic (0, 0)
	104 org/apache/commons/math3/special/Gamma.LANCZOS:[D (0, 0)
	106 ldc2_w (0, 0)
	107 0.5 (0, 0)
	109 ldc2_w (0, 0)
	110 6.283185307179586 (0, 0)
	112 invokestatic (0, 0)
	113 org/apache/commons/math3/util/FastMath.log:(D)D (0, 0)
	115 dmul (0, 0)
	116 putstatic (0, 0)
	117 org/apache/commons/math3/special/Gamma.HALF_LOG_2_PI:D (0, 0)
	119 return (0, 0)

