Method: getZero
	0 aload_0 (0, 0)
	1 invokevirtual (0, 0)
	2 org/apache/commons/math3/analysis/differentiation/DerivativeStructure$1.getZero:()Lorg/apache/commons/math3/analysis/differentiation/DerivativeStructure; (0, 0)
	4 areturn (0, 0)

Method: getOne
	0 aload_0 (0, 0)
	1 invokevirtual (0, 0)
	2 org/apache/commons/math3/analysis/differentiation/DerivativeStructure$1.getOne:()Lorg/apache/commons/math3/analysis/differentiation/DerivativeStructure; (0, 0)
	4 areturn (0, 0)

Method: getRuntimeClass
	0 ldc (0, 0)
	1 org/apache/commons/math3/analysis/differentiation/DerivativeStructure (0, 0)
	2 areturn (0, 0)

