Method: <init>
	0 aload_0 (0, 0)
	1 invokespecial (0, 0)
	2 java/lang/Object.<init>:()V (0, 0)
	4 aload_0 (0, 0)
	5 iload_1 (0, 0)
	6 putfield (0, 0)
	7 org/apache/commons/math3/analysis/differentiation/DerivativeStructure$DataTransferObject.variables:I (0, 0)
	9 aload_0 (0, 0)
	10 iload_2 (0, 0)
	11 putfield (0, 0)
	12 org/apache/commons/math3/analysis/differentiation/DerivativeStructure$DataTransferObject.order:I (0, 0)
	14 aload_0 (0, 0)
	15 aload_3 (0, 0)
	16 putfield (0, 0)
	17 org/apache/commons/math3/analysis/differentiation/DerivativeStructure$DataTransferObject.data:[D (0, 0)
	19 return (0, 0)

Method: readResolve
	0 new (0, 0)
	1 org/apache/commons/math3/analysis/differentiation/DerivativeStructure (0, 0)
	3 dup (0, 0)
	4 aload_0 (0, 0)
	5 getfield (0, 0)
	6 org/apache/commons/math3/analysis/differentiation/DerivativeStructure$DataTransferObject.variables:I (0, 0)
	8 aload_0 (0, 0)
	9 getfield (0, 0)
	10 org/apache/commons/math3/analysis/differentiation/DerivativeStructure$DataTransferObject.order:I (0, 0)
	12 aload_0 (0, 0)
	13 getfield (0, 0)
	14 org/apache/commons/math3/analysis/differentiation/DerivativeStructure$DataTransferObject.data:[D (0, 0)
	16 invokespecial (0, 0)
	17 org/apache/commons/math3/analysis/differentiation/DerivativeStructure.<init>:(II[D)V (0, 0)
	19 areturn (0, 0)

