Method: <init>
	0 aload_0 (0, 0)
	1 invokespecial (0, 0)
	4 aload_0 (0, 0)
	5 iload_1 (0, 0)
	6 putfield (0, 0)
	9 aload_0 (0, 0)
	10 iload_2 (0, 0)
	11 putfield (0, 0)
	14 aload_0 (0, 0)
	15 iload_1 (0, 0)
	16 iload_2 (0, 0)
	17 aload_3 (0, 0)
	18 invokestatic (0, 0)
	21 putfield (0, 0)
	24 aload_0 (0, 0)
	25 iload_1 (0, 0)
	26 iload_2 (0, 0)
	27 aload_3 (0, 0)
	28 aload (0, 0)
	30 invokestatic (0, 0)
	33 putfield (0, 0)
	36 aload_0 (0, 0)
	37 iload_1 (0, 0)
	38 iload_2 (0, 0)
	39 aload_3 (0, 0)
	40 aload (0, 0)
	42 invokestatic (0, 0)
	45 putfield (0, 0)
	48 aload_0 (0, 0)
	49 iload_1 (0, 0)
	50 iload_2 (0, 0)
	51 aload_3 (0, 0)
	52 aload (0, 0)
	54 aload_0 (0, 0)
	55 getfield (0, 0)
	58 invokestatic (0, 0)
	61 putfield (0, 0)
	64 aload_0 (0, 0)
	65 iload_1 (0, 0)
	66 iload_2 (0, 0)
	67 aload_3 (0, 0)
	68 aload (0, 0)
	70 aload_0 (0, 0)
	71 getfield (0, 0)
	74 aload_0 (0, 0)
	75 getfield (0, 0)
	78 invokestatic (0, 0)
	81 putfield (0, 0)
	84 return (0, 0)

Method: getCompiler
	0 getstatic (0, 0)
	3 invokevirtual (0, 0)
	6 checkcast (0, 0)
	9 astore_2 (0, 0)
	10 aload_2 (0, 1)
	11 ifnull (0, 1)
	14 aload_2 (0, 1)
	15 arraylength (0, 1)
	16 iload_0 (0, 1)
	17 if_icmple (0, 1)
	20 aload_2 (0, 1)
	21 iload_0 (0, 1)
	22 aaload (0, 1)
	23 arraylength (0, 1)
	24 iload_1 (0, 1)
	25 if_icmple (0, 1)
	28 aload_2 (0, 1)
	29 iload_0 (0, 1)
	30 aaload (0, 1)
	31 iload_1 (0, 1)
	32 aaload (0, 1)
	33 ifnull (0, 1)
	36 aload_2 (1, 1)
	37 iload_0 (1, 1)
	38 aaload (1, 1)
	39 iload_1 (1, 1)
	40 aaload (1, 1)
	41 areturn (1, 1)
	42 iload_0 (0, 0)
	43 aload_2 (0, 0)
	44 ifnonnull (0, 0)
	47 iconst_0 (0, 0)
	48 goto (0, 0)
	51 aload_2 (0, 0)
	52 arraylength (0, 0)
	53 invokestatic (0, 0)
	56 istore_3 (0, 0)
	57 iload_1 (0, 0)
	58 aload_2 (0, 0)
	59 ifnonnull (0, 0)
	62 iconst_0 (0, 0)
	63 goto (0, 0)
	66 aload_2 (0, 0)
	67 iconst_0 (0, 0)
	68 aaload (0, 0)
	69 arraylength (0, 0)
	70 invokestatic (0, 0)
	73 istore (0, 0)
	75 iload_3 (0, 0)
	76 iconst_1 (0, 0)
	77 iadd (0, 0)
	78 iload (0, 0)
	80 iconst_1 (0, 0)
	81 iadd (0, 0)
	82 multianewarray (0, 0)
	86 astore (0, 0)
	88 aload_2 (1, 1)
	89 ifnull (1, 1)
	92 iconst_0 (2, 4)
	93 istore (2, 4)
	95 iload (2, 4)
	97 aload_2 (2, 4)
	98 arraylength (2, 4)
	99 if_icmpge (2, 4)
	102 aload_2 (2, 4)
	103 iload (2, 4)
	105 aaload (2, 4)
	106 iconst_0 (2, 4)
	107 aload (2, 4)
	109 iload (2, 4)
	111 aaload (2, 4)
	112 iconst_0 (2, 4)
	113 aload_2 (2, 4)
	114 iload (2, 4)
	116 aaload (2, 4)
	117 arraylength (2, 4)
	118 invokestatic (2, 4)
	121 iinc (2, 4)
	124 goto (2, 4)
	127 iconst_0 (1, 4)
	128 istore (1, 4)
	130 iload (1, 4)
	132 iload_0 (1, 4)
	133 iload_1 (1, 4)
	134 iadd (1, 4)
	135 if_icmpgt (1, 4)
	138 iconst_0 (2, 4)
	139 iload (2, 4)
	141 iload_0 (2, 4)
	142 isub (2, 4)
	143 invokestatic (2, 4)
	146 istore (2, 4)
	148 iload (2, 4)
	150 iload_1 (2, 4)
	151 iload (2, 4)
	153 invokestatic (2, 4)
	156 if_icmpgt (2, 4)
	159 iload (2, 4)
	161 iload (2, 4)
	163 isub (2, 4)
	164 istore (2, 4)
	166 aload (3, 1)
	168 iload (3, 1)
	170 aaload (3, 1)
	171 iload (3, 1)
	173 aaload (3, 1)
	174 ifnonnull (3, 1)
	177 iload (3, 1)
	179 ifne (3, 1)
	182 aconst_null (3, 1)
	183 goto (3, 1)
	186 aload (3, 1)
	188 iload (3, 1)
	190 iconst_1 (3, 1)
	191 isub (3, 1)
	192 aaload (3, 1)
	193 iload (3, 1)
	195 aaload (3, 1)
	196 astore (3, 1)
	198 iload (3, 1)
	200 ifne (3, 1)
	203 aconst_null (3, 1)
	204 goto (3, 1)
	207 aload (3, 1)
	209 iload (3, 1)
	211 aaload (3, 1)
	212 iload (3, 1)
	214 iconst_1 (3, 1)
	215 isub (3, 1)
	216 aaload (3, 1)
	217 astore (3, 1)
	219 aload (3, 1)
	221 iload (3, 1)
	223 aaload (3, 1)
	224 iload (3, 1)
	226 new (3, 1)
	229 dup (3, 1)
	230 iload (3, 1)
	232 iload (3, 1)
	234 aload (3, 1)
	236 aload (3, 1)
	238 invokespecial (3, 1)
	241 aastore (3, 1)
	242 iinc (3, 1)
	245 goto (3, 1)
	248 iinc (3, 1)
	251 goto (3, 1)
	254 getstatic (2, 4)
	257 aload_2 (2, 4)
	258 aload (2, 4)
	260 invokevirtual (2, 4)
	263 pop (2, 4)
	264 aload (2, 4)
	266 iload_0 (2, 4)
	267 aaload (2, 4)
	268 iload_1 (2, 4)
	269 aaload (2, 4)
	270 areturn (2, 4)

Method: compileSizes
	0 iload_0 (0, 0)
	1 iconst_1 (0, 0)
	2 iadd (0, 0)
	3 iload_1 (0, 0)
	4 iconst_1 (0, 0)
	5 iadd (0, 0)
	6 multianewarray (0, 0)
	10 astore_3 (0, 0)
	11 iload_0 (1, 1)
	12 ifne (1, 1)
	15 aload_3 (1, 1)
	16 iconst_0 (1, 1)
	17 aaload (1, 1)
	18 iconst_1 (1, 1)
	19 invokestatic (1, 1)
	22 goto (1, 1)
	25 aload_2 (1, 2)
	26 getfield (1, 2)
	29 iconst_0 (1, 2)
	30 aload_3 (1, 2)
	31 iconst_0 (1, 2)
	32 iload_0 (1, 2)
	33 invokestatic (1, 2)
	36 aload_3 (1, 2)
	37 iload_0 (1, 2)
	38 aaload (1, 2)
	39 iconst_0 (1, 2)
	40 iconst_1 (1, 2)
	41 iastore (1, 2)
	42 iconst_0 (2, 4)
	43 istore (2, 4)
	45 iload (2, 4)
	47 iload_1 (2, 4)
	48 if_icmpge (2, 4)
	51 aload_3 (2, 4)
	52 iload_0 (2, 4)
	53 aaload (2, 4)
	54 iload (2, 4)
	56 iconst_1 (2, 4)
	57 iadd (2, 4)
	58 aload_3 (2, 4)
	59 iload_0 (2, 4)
	60 aaload (2, 4)
	61 iload (2, 4)
	63 iaload (2, 4)
	64 aload_3 (2, 4)
	65 iload_0 (2, 4)
	66 iconst_1 (2, 4)
	67 isub (2, 4)
	68 aaload (2, 4)
	69 iload (2, 4)
	71 iconst_1 (2, 4)
	72 iadd (2, 4)
	73 iaload (2, 4)
	74 iadd (2, 4)
	75 iastore (2, 4)
	76 iinc (2, 4)
	79 goto (2, 4)
	82 aload_3 (0, 1)
	83 areturn (0, 1)

Method: compileDerivativesIndirection
	0 iload_0 (1, 1)
	1 ifeq (1, 1)
	4 iload_1 (1, 1)
	5 ifne (1, 1)
	8 iconst_1 (1, 1)
	9 iload_0 (1, 1)
	10 multianewarray (1, 1)
	14 areturn (1, 1)
	15 aload_2 (0, 0)
	16 getfield (0, 0)
	19 arraylength (0, 0)
	20 istore (0, 0)
	22 aload_3 (0, 0)
	23 getfield (0, 0)
	26 arraylength (0, 0)
	27 istore (0, 0)
	29 iload (0, 0)
	31 iload (0, 0)
	33 iadd (0, 0)
	34 iload_0 (0, 0)
	35 multianewarray (0, 0)
	39 astore (0, 0)
	41 iconst_0 (1, 4)
	42 istore (1, 4)
	44 iload (1, 4)
	46 iload (1, 4)
	48 if_icmpge (1, 4)
	51 aload_2 (1, 4)
	52 getfield (1, 4)
	55 iload (1, 4)
	57 aaload (1, 4)
	58 iconst_0 (1, 4)
	59 aload (1, 4)
	61 iload (1, 4)
	63 aaload (1, 4)
	64 iconst_0 (1, 4)
	65 iload_0 (1, 4)
	66 iconst_1 (1, 4)
	67 isub (1, 4)
	68 invokestatic (1, 4)
	71 iinc (1, 4)
	74 goto (1, 4)
	77 iconst_0 (1, 4)
	78 istore (1, 4)
	80 iload (1, 4)
	82 iload (1, 4)
	84 if_icmpge (1, 4)
	87 aload_3 (1, 4)
	88 getfield (1, 4)
	91 iload (1, 4)
	93 aaload (1, 4)
	94 iconst_0 (1, 4)
	95 aload (1, 4)
	97 iload (1, 4)
	99 iload (1, 4)
	101 iadd (1, 4)
	102 aaload (1, 4)
	103 iconst_0 (1, 4)
	104 iload_0 (1, 4)
	105 invokestatic (1, 4)
	108 aload (1, 4)
	110 iload (1, 4)
	112 iload (1, 4)
	114 iadd (1, 4)
	115 aaload (1, 4)
	116 iload_0 (1, 4)
	117 iconst_1 (1, 4)
	118 isub (1, 4)
	119 dup2 (1, 4)
	120 iaload (1, 4)
	121 iconst_1 (1, 4)
	122 iadd (1, 4)
	123 iastore (1, 4)
	124 iinc (1, 4)
	127 goto (1, 4)
	130 aload (0, 4)
	132 areturn (0, 4)

Method: compileLowerIndirection
	0 iload_0 (1, 1)
	1 ifeq (1, 1)
	4 iload_1 (1, 1)
	5 iconst_1 (1, 1)
	6 if_icmpgt (1, 1)
	9 iconst_1 (1, 1)
	10 newarray (1, 1)
	12 dup (1, 1)
	13 iconst_0 (1, 1)
	14 iconst_0 (1, 1)
	15 iastore (1, 1)
	16 areturn (1, 1)
	17 aload_2 (0, 0)
	18 getfield (0, 0)
	21 arraylength (0, 0)
	22 istore (0, 0)
	24 aload_3 (0, 0)
	25 getfield (0, 0)
	28 arraylength (0, 0)
	29 istore (0, 0)
	31 iload (0, 0)
	33 iload (0, 0)
	35 iadd (0, 0)
	36 newarray (0, 0)
	38 astore (0, 0)
	40 aload_2 (0, 0)
	41 getfield (0, 0)
	44 iconst_0 (0, 0)
	45 aload (0, 0)
	47 iconst_0 (0, 0)
	48 iload (0, 0)
	50 invokestatic (0, 0)
	53 iconst_0 (1, 4)
	54 istore (1, 4)
	56 iload (1, 4)
	58 iload (1, 4)
	60 if_icmpge (1, 4)
	63 aload (1, 4)
	65 iload (1, 4)
	67 iload (1, 4)
	69 iadd (1, 4)
	70 aload_2 (1, 4)
	71 invokevirtual (1, 4)
	74 aload_3 (1, 4)
	75 getfield (1, 4)
	78 iload (1, 4)
	80 iaload (1, 4)
	81 iadd (1, 4)
	82 iastore (1, 4)
	83 iinc (1, 4)
	86 goto (1, 4)
	89 aload (0, 0)
	91 areturn (0, 0)

Method: compileMultiplicationIndirection
	0 iload_0 (1, 1)
	1 ifeq (1, 1)
	4 iload_1 (1, 1)
	5 ifne (1, 1)
	8 iconst_1 (1, 1)
	9 anewarray (1, 1)
	12 dup (1, 1)
	13 iconst_0 (1, 1)
	14 iconst_1 (1, 1)
	15 anewarray (1, 1)
	18 dup (1, 1)
	19 iconst_0 (1, 1)
	20 iconst_3 (1, 1)
	21 newarray (1, 1)
	23 dup (1, 1)
	24 iconst_0 (1, 1)
	25 iconst_1 (1, 1)
	26 iastore (1, 1)
	27 dup (1, 1)
	28 iconst_1 (1, 1)
	29 iconst_0 (1, 1)
	30 iastore (1, 1)
	31 dup (1, 1)
	32 iconst_2 (1, 1)
	33 iconst_0 (1, 1)
	34 iastore (1, 1)
	35 aastore (1, 1)
	36 aastore (1, 1)
	37 areturn (1, 1)
	38 aload_2 (0, 0)
	39 getfield (0, 0)
	42 arraylength (0, 0)
	43 istore (0, 0)
	45 aload_3 (0, 0)
	46 getfield (0, 0)
	49 arraylength (0, 0)
	50 istore (0, 0)
	52 iload (0, 0)
	54 iload (0, 0)
	56 iadd (0, 0)
	57 anewarray (0, 0)
	60 astore (0, 0)
	62 aload_2 (0, 0)
	63 getfield (0, 0)
	66 iconst_0 (0, 0)
	67 aload (0, 0)
	69 iconst_0 (0, 0)
	70 iload (0, 0)
	72 invokestatic (0, 0)
	75 iconst_0 (1, 4)
	76 istore (1, 4)
	78 iload (1, 4)
	80 iload (1, 4)
	82 if_icmpge (1, 4)
	85 aload_3 (1, 4)
	86 getfield (1, 4)
	89 iload (1, 4)
	91 aaload (1, 4)
	92 astore (1, 4)
	94 new (1, 4)
	97 dup (1, 4)
	98 aload (1, 4)
	100 arraylength (1, 4)
	101 iconst_2 (1, 4)
	102 imul (1, 4)
	103 invokespecial (1, 4)
	106 astore (1, 4)
	108 iconst_0 (2, 4)
	109 istore (2, 4)
	111 iload (2, 4)
	113 aload (2, 4)
	115 arraylength (2, 4)
	116 if_icmpge (2, 4)
	119 aload (2, 4)
	121 iconst_3 (2, 4)
	122 newarray (2, 4)
	124 dup (2, 4)
	125 iconst_0 (2, 4)
	126 aload (2, 4)
	128 iload (2, 4)
	130 aaload (2, 4)
	131 iconst_0 (2, 4)
	132 iaload (2, 4)
	133 iastore (2, 4)
	134 dup (2, 4)
	135 iconst_1 (2, 4)
	136 aload (2, 4)
	138 aload (2, 4)
	140 iload (2, 4)
	142 aaload (2, 4)
	143 iconst_1 (2, 4)
	144 iaload (2, 4)
	145 iaload (2, 4)
	146 iastore (2, 4)
	147 dup (2, 4)
	148 iconst_2 (2, 4)
	149 iload (2, 4)
	151 aload (2, 4)
	153 iload (2, 4)
	155 aaload (2, 4)
	156 iconst_2 (2, 4)
	157 iaload (2, 4)
	158 iadd (2, 4)
	159 iastore (2, 4)
	160 invokeinterface (2, 4)
	165 pop (2, 4)
	166 aload (2, 4)
	168 iconst_3 (2, 4)
	169 newarray (2, 4)
	171 dup (2, 4)
	172 iconst_0 (2, 4)
	173 aload (2, 4)
	175 iload (2, 4)
	177 aaload (2, 4)
	178 iconst_0 (2, 4)
	179 iaload (2, 4)
	180 iastore (2, 4)
	181 dup (2, 4)
	182 iconst_1 (2, 4)
	183 iload (2, 4)
	185 aload (2, 4)
	187 iload (2, 4)
	189 aaload (2, 4)
	190 iconst_1 (2, 4)
	191 iaload (2, 4)
	192 iadd (2, 4)
	193 iastore (2, 4)
	194 dup (2, 4)
	195 iconst_2 (2, 4)
	196 aload (2, 4)
	198 aload (2, 4)
	200 iload (2, 4)
	202 aaload (2, 4)
	203 iconst_2 (2, 4)
	204 iaload (2, 4)
	205 iaload (2, 4)
	206 iastore (2, 4)
	207 invokeinterface (2, 4)
	212 pop (2, 4)
	213 iinc (2, 4)
	216 goto (2, 4)
	219 new (1, 4)
	222 dup (1, 4)
	223 aload (1, 4)
	225 invokeinterface (1, 4)
	230 invokespecial (1, 4)
	233 astore (1, 4)
	235 iconst_0 (2, 4)
	236 istore (2, 4)
	238 iload (2, 4)
	240 aload (2, 4)
	242 invokeinterface (2, 4)
	247 if_icmpge (2, 4)
	250 aload (2, 4)
	252 iload (2, 4)
	254 invokeinterface (2, 4)
	259 checkcast (2, 4)
	262 astore (2, 4)
	264 aload (3, 1)
	266 iconst_0 (3, 1)
	267 iaload (3, 1)
	268 ifle (3, 1)
	271 iload (4, 4)
	273 iconst_1 (4, 4)
	274 iadd (4, 4)
	275 istore (4, 4)
	277 iload (4, 4)
	279 aload (4, 4)
	281 invokeinterface (4, 4)
	286 if_icmpge (4, 4)
	289 aload (4, 4)
	291 iload (4, 4)
	293 invokeinterface (4, 4)
	298 checkcast (4, 4)
	301 astore (4, 4)
	303 aload (5, 1)
	305 iconst_1 (5, 1)
	306 iaload (5, 1)
	307 aload (5, 1)
	309 iconst_1 (5, 1)
	310 iaload (5, 1)
	311 if_icmpne (5, 1)
	314 aload (5, 1)
	316 iconst_2 (5, 1)
	317 iaload (5, 1)
	318 aload (5, 1)
	320 iconst_2 (5, 1)
	321 iaload (5, 1)
	322 if_icmpne (5, 1)
	325 aload (5, 1)
	327 iconst_0 (5, 1)
	328 dup2 (5, 1)
	329 iaload (5, 1)
	330 aload (5, 1)
	332 iconst_0 (5, 1)
	333 iaload (5, 1)
	334 iadd (5, 1)
	335 iastore (5, 1)
	336 aload (5, 1)
	338 iconst_0 (5, 1)
	339 iconst_0 (5, 1)
	340 iastore (5, 1)
	341 iinc (5, 1)
	344 goto (5, 1)
	347 aload (4, 4)
	349 aload (4, 4)
	351 invokeinterface (4, 4)
	356 pop (4, 4)
	357 iinc (4, 4)
	360 goto (4, 4)
	363 aload (3, 1)
	365 iload (3, 1)
	367 iload (3, 1)
	369 iadd (3, 1)
	370 aload (3, 1)
	372 aload (3, 1)
	374 invokeinterface (3, 1)
	379 anewarray (3, 1)
	382 invokeinterface (3, 1)
	387 checkcast (3, 1)
	390 aastore (3, 1)
	391 iinc (3, 1)
	394 goto (3, 1)
	397 aload (2, 4)
	399 areturn (2, 4)

Method: compileCompositionIndirection
	0 iload_0 (1, 1)
	1 ifeq (1, 1)
	4 iload_1 (1, 1)
	5 ifne (1, 1)
	8 iconst_1 (1, 1)
	9 anewarray (1, 1)
	12 dup (1, 1)
	13 iconst_0 (1, 1)
	14 iconst_1 (1, 1)
	15 anewarray (1, 1)
	18 dup (1, 1)
	19 iconst_0 (1, 1)
	20 iconst_2 (1, 1)
	21 newarray (1, 1)
	23 dup (1, 1)
	24 iconst_0 (1, 1)
	25 iconst_1 (1, 1)
	26 iastore (1, 1)
	27 dup (1, 1)
	28 iconst_1 (1, 1)
	29 iconst_0 (1, 1)
	30 iastore (1, 1)
	31 aastore (1, 1)
	32 aastore (1, 1)
	33 areturn (1, 1)
	34 aload_2 (0, 0)
	35 getfield (0, 0)
	38 arraylength (0, 0)
	39 istore (0, 0)
	41 aload_3 (0, 0)
	42 getfield (0, 0)
	45 arraylength (0, 0)
	46 istore (0, 0)
	48 iload (0, 0)
	50 iload (0, 0)
	52 iadd (0, 0)
	53 anewarray (0, 0)
	56 astore (0, 0)
	58 aload_2 (0, 0)
	59 getfield (0, 0)
	62 iconst_0 (0, 0)
	63 aload (0, 0)
	65 iconst_0 (0, 0)
	66 iload (0, 0)
	68 invokestatic (0, 0)
	71 iconst_0 (1, 4)
	72 istore (1, 4)
	74 iload (1, 4)
	76 iload (1, 4)
	78 if_icmpge (1, 4)
	81 new (1, 4)
	84 dup (1, 4)
	85 invokespecial (1, 4)
	88 astore (1, 4)
	90 aload_3 (2, 4)
	91 getfield (2, 4)
	94 iload (2, 4)
	96 aaload (2, 4)
	97 astore (2, 4)
	99 aload (2, 4)
	101 arraylength (2, 4)
	102 istore (2, 4)
	104 iconst_0 (2, 4)
	105 istore (2, 4)
	107 iload (2, 4)
	109 iload (2, 4)
	111 if_icmpge (2, 4)
	114 aload (2, 4)
	116 iload (2, 4)
	118 aaload (2, 4)
	119 astore (2, 4)
	121 aload (2, 4)
	123 arraylength (2, 4)
	124 iconst_1 (2, 4)
	125 iadd (2, 4)
	126 newarray (2, 4)
	128 astore (2, 4)
	130 aload (2, 4)
	132 iconst_0 (2, 4)
	133 aload (2, 4)
	135 iconst_0 (2, 4)
	136 iaload (2, 4)
	137 iastore (2, 4)
	138 aload (2, 4)
	140 iconst_1 (2, 4)
	141 aload (2, 4)
	143 iconst_1 (2, 4)
	144 iaload (2, 4)
	145 iconst_1 (2, 4)
	146 iadd (2, 4)
	147 iastore (2, 4)
	148 iload_0 (2, 4)
	149 newarray (2, 4)
	151 astore (2, 4)
	153 aload (2, 4)
	155 iload_0 (2, 4)
	156 iconst_1 (2, 4)
	157 isub (2, 4)
	158 iconst_1 (2, 4)
	159 iastore (2, 4)
	160 aload (2, 4)
	162 aload (2, 4)
	164 arraylength (2, 4)
	165 iload_0 (2, 4)
	166 iload_1 (2, 4)
	167 aload (2, 4)
	169 aload (2, 4)
	171 invokestatic (2, 4)
	174 iastore (2, 4)
	175 iconst_2 (3, 4)
	176 istore (3, 4)
	178 iload (3, 4)
	180 aload (3, 4)
	182 arraylength (3, 4)
	183 if_icmpge (3, 4)
	186 aload (3, 1)
	188 iload (3, 1)
	190 aload (3, 1)
	192 iload (3, 1)
	194 iaload (3, 1)
	195 iload_0 (3, 1)
	196 aload_3 (3, 1)
	197 getfield (3, 1)
	200 iload_0 (3, 1)
	201 iload_1 (3, 1)
	202 aload (3, 1)
	204 invokestatic (3, 1)
	207 iastore (3, 1)
	208 iinc (3, 1)
	211 goto (3, 1)
	214 aload (2, 4)
	216 iconst_2 (2, 4)
	217 aload (2, 4)
	219 arraylength (2, 4)
	220 invokestatic (2, 4)
	223 aload (2, 4)
	225 aload (2, 4)
	227 invokeinterface (2, 4)
	232 pop (2, 4)
	233 iconst_2 (3, 4)
	234 istore (3, 4)
	236 iload (3, 4)
	238 aload (3, 4)
	240 arraylength (3, 4)
	241 if_icmpge (3, 4)
	244 aload (3, 4)
	246 arraylength (3, 4)
	247 newarray (3, 4)
	249 astore (3, 4)
	251 aload (3, 4)
	253 iconst_0 (3, 4)
	254 aload (3, 4)
	256 iconst_0 (3, 4)
	257 iaload (3, 4)
	258 iastore (3, 4)
	259 aload (3, 4)
	261 iconst_1 (3, 4)
	262 aload (3, 4)
	264 iconst_1 (3, 4)
	265 iaload (3, 4)
	266 iastore (3, 4)
	267 iconst_2 (4, 4)
	268 istore (4, 4)
	270 iload (4, 4)
	272 aload (4, 4)
	274 arraylength (4, 4)
	275 if_icmpge (4, 4)
	278 aload (4, 1)
	280 iload (4, 1)
	282 aload (4, 1)
	284 iload (4, 1)
	286 iaload (4, 1)
	287 iload_0 (4, 1)
	288 aload_3 (4, 1)
	289 getfield (4, 1)
	292 iload_0 (4, 1)
	293 iload_1 (4, 1)
	294 aload (4, 1)
	296 invokestatic (4, 1)
	299 iastore (4, 1)
	300 iload (5, 1)
	302 iload (5, 1)
	304 if_icmpne (5, 1)
	307 aload (5, 1)
	309 aload (5, 1)
	311 iload (5, 1)
	313 iaload (5, 1)
	314 aaload (5, 1)
	315 iconst_0 (5, 1)
	316 aload (5, 1)
	318 iconst_0 (5, 1)
	319 iload_0 (5, 1)
	320 invokestatic (5, 1)
	323 aload (5, 1)
	325 iload_0 (5, 1)
	326 iconst_1 (5, 1)
	327 isub (5, 1)
	328 dup2 (5, 1)
	329 iaload (5, 1)
	330 iconst_1 (5, 1)
	331 iadd (5, 1)
	332 iastore (5, 1)
	333 aload (5, 1)
	335 iload (5, 1)
	337 iload_0 (5, 1)
	338 iload_1 (5, 1)
	339 aload (5, 1)
	341 aload (5, 1)
	343 invokestatic (5, 1)
	346 iastore (5, 1)
	347 iinc (5, 1)
	350 goto (5, 1)
	353 aload (4, 4)
	355 iconst_2 (4, 4)
	356 aload (4, 4)
	358 arraylength (4, 4)
	359 invokestatic (4, 4)
	362 aload (4, 4)
	364 aload (4, 4)
	366 invokeinterface (4, 4)
	371 pop (4, 4)
	372 iinc (4, 4)
	375 goto (4, 4)
	378 iinc (4, 4)
	381 goto (4, 4)
	384 new (3, 4)
	387 dup (3, 4)
	388 aload (3, 4)
	390 invokeinterface (3, 4)
	395 invokespecial (3, 4)
	398 astore (3, 4)
	400 iconst_0 (4, 4)
	401 istore (4, 4)
	403 iload (4, 4)
	405 aload (4, 4)
	407 invokeinterface (4, 4)
	412 if_icmpge (4, 4)
	415 aload (4, 4)
	417 iload (4, 4)
	419 invokeinterface (4, 4)
	424 checkcast (4, 4)
	427 astore (4, 4)
	429 aload (5, 1)
	431 iconst_0 (5, 1)
	432 iaload (5, 1)
	433 ifle (5, 1)
	436 iload (6, 4)
	438 iconst_1 (6, 4)
	439 iadd (6, 4)
	440 istore (6, 4)
	442 iload (6, 4)
	444 aload (6, 4)
	446 invokeinterface (6, 4)
	451 if_icmpge (6, 4)
	454 aload (6, 4)
	456 iload (6, 4)
	458 invokeinterface (6, 4)
	463 checkcast (6, 4)
	466 astore (6, 4)
	468 aload (6, 4)
	470 arraylength (6, 4)
	471 aload (6, 4)
	473 arraylength (6, 4)
	474 if_icmpne (6, 4)
	477 iconst_1 (6, 4)
	478 goto (6, 4)
	481 iconst_0 (6, 4)
	482 istore (6, 4)
	484 iconst_1 (7, 4)
	485 istore (7, 4)
	487 iload (7, 4)
	489 ifeq (7, 4)
	492 iload (7, 4)
	494 aload (7, 4)
	496 arraylength (7, 4)
	497 if_icmpge (7, 4)
	500 iload (7, 4)
	502 aload (7, 4)
	504 iload (7, 4)
	506 iaload (7, 4)
	507 aload (7, 4)
	509 iload (7, 4)
	511 iaload (7, 4)
	512 if_icmpne (7, 4)
	515 iconst_1 (7, 4)
	516 goto (7, 4)
	519 iconst_0 (7, 4)
	520 iand (7, 4)
	521 istore (7, 4)
	523 iinc (7, 4)
	526 goto (7, 4)
	529 iload (7, 1)
	531 ifeq (7, 1)
	534 aload (7, 1)
	536 iconst_0 (7, 1)
	537 dup2 (7, 1)
	538 iaload (7, 1)
	539 aload (7, 1)
	541 iconst_0 (7, 1)
	542 iaload (7, 1)
	543 iadd (7, 1)
	544 iastore (7, 1)
	545 aload (7, 1)
	547 iconst_0 (7, 1)
	548 iconst_0 (7, 1)
	549 iastore (7, 1)
	550 iinc (7, 1)
	553 goto (7, 1)
	556 aload (6, 4)
	558 aload (6, 4)
	560 invokeinterface (6, 4)
	565 pop (6, 4)
	566 iinc (6, 4)
	569 goto (6, 4)
	572 aload (5, 1)
	574 iload (5, 1)
	576 iload (5, 1)
	578 iadd (5, 1)
	579 aload (5, 1)
	581 aload (5, 1)
	583 invokeinterface (5, 1)
	588 anewarray (5, 1)
	591 invokeinterface (5, 1)
	596 checkcast (5, 1)
	599 aastore (5, 1)
	600 iinc (5, 1)
	603 goto (5, 1)
	606 aload (4, 4)
	608 areturn (4, 4)

Method: getPartialDerivativeIndex
	0 iconst_0 (0, 0)
	1 istore (0, 0)
	3 iload_1 (0, 0)
	4 istore (0, 0)
	6 iconst_0 (0, 0)
	7 istore (0, 0)
	9 iload_0 (1, 4)
	10 iconst_1 (1, 4)
	11 isub (1, 4)
	12 istore (1, 4)
	14 iload (1, 4)
	16 iflt (1, 4)
	19 aload_3 (1, 4)
	20 iload (1, 4)
	22 iaload (1, 4)
	23 istore (1, 4)
	25 iload (1, 4)
	27 iload (1, 4)
	29 iadd (1, 4)
	30 istore (1, 4)
	32 iload (2, 1)
	34 iload_1 (2, 1)
	35 if_icmple (2, 1)
	38 new (2, 1)
	41 dup (2, 1)
	42 iload (2, 1)
	44 invokestatic (2, 1)
	47 iload_1 (2, 1)
	48 invokestatic (2, 1)
	51 iconst_1 (2, 1)
	52 invokespecial (2, 1)
	55 athrow (2, 1)
	56 iload (2, 3)
	58 iinc (2, 3)
	61 ifle (2, 3)
	64 iload (2, 1)
	66 aload_2 (2, 1)
	67 iload (2, 1)
	69 aaload (2, 1)
	70 iload (2, 1)
	72 iinc (2, 1)
	75 iaload (2, 1)
	76 iadd (2, 1)
	77 istore (2, 1)
	79 goto (2, 1)
	82 iinc (2, 1)
	85 goto (2, 1)
	88 iload (1, 4)
	90 ireturn (1, 4)

Method: convertIndex
	0 iload_3 (0, 0)
	1 newarray (0, 0)
	3 astore (0, 0)
	5 aload_2 (0, 0)
	6 iload_0 (0, 0)
	7 aaload (0, 0)
	8 iconst_0 (0, 0)
	9 aload (0, 0)
	11 iconst_0 (0, 0)
	12 iload_1 (0, 0)
	13 iload_3 (0, 0)
	14 invokestatic (0, 0)
	17 invokestatic (0, 0)
	20 iload_3 (0, 0)
	21 iload (0, 0)
	23 aload (0, 0)
	25 aload (0, 0)
	27 invokestatic (0, 0)
	30 ireturn (0, 0)

Method: getPartialDerivativeOrders
	0 aload_0 (0, 0)
	1 getfield (0, 0)
	4 iload_1 (0, 0)
	5 aaload (0, 0)
	6 areturn (0, 0)

Method: getFreeParameters
	0 aload_0 (0, 0)
	1 getfield (0, 0)
	4 ireturn (0, 0)

Method: getOrder
	0 aload_0 (0, 0)
	1 getfield (0, 0)
	4 ireturn (0, 0)

Method: getSize
	0 aload_0 (0, 0)
	1 getfield (0, 0)
	4 aload_0 (0, 0)
	5 getfield (0, 0)
	8 aaload (0, 0)
	9 aload_0 (0, 0)
	10 getfield (0, 0)
	13 iaload (0, 0)
	14 ireturn (0, 0)

Method: linearCombination
	0 iconst_0 (1, 4)
	1 istore (1, 4)
	3 iload (1, 4)
	5 aload_0 (1, 4)
	6 invokevirtual (1, 4)
	9 if_icmpge (1, 4)
	12 aload (1, 4)
	14 iload (1, 4)
	16 iload (1, 4)
	18 iadd (1, 4)
	19 dload_1 (1, 4)
	20 aload_3 (1, 4)
	21 iload (1, 4)
	23 iload (1, 4)
	25 iadd (1, 4)
	26 daload (1, 4)
	27 dload (1, 4)
	29 aload (1, 4)
	31 iload (1, 4)
	33 iload (1, 4)
	35 iadd (1, 4)
	36 daload (1, 4)
	37 dload (1, 4)
	39 aload (1, 4)
	41 iload (1, 4)
	43 iload (1, 4)
	45 iadd (1, 4)
	46 daload (1, 4)
	47 dload (1, 4)
	49 aload (1, 4)
	51 iload (1, 4)
	53 iload (1, 4)
	55 iadd (1, 4)
	56 daload (1, 4)
	57 invokestatic (1, 4)
	60 dastore (1, 4)
	61 iinc (1, 4)
	64 goto (1, 4)
	67 return (0, 0)

Method: add
	0 iconst_0 (1, 4)
	1 istore (1, 4)
	3 iload (1, 4)
	5 aload_0 (1, 4)
	6 invokevirtual (1, 4)
	9 if_icmpge (1, 4)
	12 aload (1, 4)
	14 iload (1, 4)
	16 iload (1, 4)
	18 iadd (1, 4)
	19 aload_1 (1, 4)
	20 iload_2 (1, 4)
	21 iload (1, 4)
	23 iadd (1, 4)
	24 daload (1, 4)
	25 aload_3 (1, 4)
	26 iload (1, 4)
	28 iload (1, 4)
	30 iadd (1, 4)
	31 daload (1, 4)
	32 dadd (1, 4)
	33 dastore (1, 4)
	34 iinc (1, 4)
	37 goto (1, 4)
	40 return (0, 0)

Method: subtract
	0 iconst_0 (1, 4)
	1 istore (1, 4)
	3 iload (1, 4)
	5 aload_0 (1, 4)
	6 invokevirtual (1, 4)
	9 if_icmpge (1, 4)
	12 aload (1, 4)
	14 iload (1, 4)
	16 iload (1, 4)
	18 iadd (1, 4)
	19 aload_1 (1, 4)
	20 iload_2 (1, 4)
	21 iload (1, 4)
	23 iadd (1, 4)
	24 daload (1, 4)
	25 aload_3 (1, 4)
	26 iload (1, 4)
	28 iload (1, 4)
	30 iadd (1, 4)
	31 daload (1, 4)
	32 dsub (1, 4)
	33 dastore (1, 4)
	34 iinc (1, 4)
	37 goto (1, 4)
	40 return (0, 0)

Method: multiply
	0 iconst_0 (1, 4)
	1 istore (1, 4)
	3 iload (1, 4)
	5 aload_0 (1, 4)
	6 getfield (1, 4)
	9 arraylength (1, 4)
	10 if_icmpge (1, 4)
	13 aload_0 (1, 4)
	14 getfield (1, 4)
	17 iload (1, 4)
	19 aaload (1, 4)
	20 astore (1, 4)
	22 dconst_0 (1, 4)
	23 dstore (1, 4)
	25 iconst_0 (2, 4)
	26 istore (2, 4)
	28 iload (2, 4)
	30 aload (2, 4)
	32 arraylength (2, 4)
	33 if_icmpge (2, 4)
	36 dload (2, 4)
	38 aload (2, 4)
	40 iload (2, 4)
	42 aaload (2, 4)
	43 iconst_0 (2, 4)
	44 iaload (2, 4)
	45 i2d (2, 4)
	46 aload_1 (2, 4)
	47 iload_2 (2, 4)
	48 aload (2, 4)
	50 iload (2, 4)
	52 aaload (2, 4)
	53 iconst_1 (2, 4)
	54 iaload (2, 4)
	55 iadd (2, 4)
	56 daload (2, 4)
	57 dmul (2, 4)
	58 aload_3 (2, 4)
	59 iload (2, 4)
	61 aload (2, 4)
	63 iload (2, 4)
	65 aaload (2, 4)
	66 iconst_2 (2, 4)
	67 iaload (2, 4)
	68 iadd (2, 4)
	69 daload (2, 4)
	70 dmul (2, 4)
	71 dadd (2, 4)
	72 dstore (2, 4)
	74 iinc (2, 4)
	77 goto (2, 4)
	80 aload (1, 4)
	82 iload (1, 4)
	84 iload (1, 4)
	86 iadd (1, 4)
	87 dload (1, 4)
	89 dastore (1, 4)
	90 iinc (1, 4)
	93 goto (1, 4)
	96 return (0, 0)

Method: divide
	0 aload_0 (0, 0)
	1 invokevirtual (0, 0)
	4 newarray (0, 0)
	6 astore (0, 0)
	8 aload_0 (0, 0)
	9 aload_3 (0, 0)
	10 iload_2 (0, 0)
	11 iconst_m1 (0, 0)
	12 aload (0, 0)
	14 iconst_0 (0, 0)
	15 invokevirtual (0, 0)
	18 aload_0 (0, 0)
	19 aload_1 (0, 0)
	20 iload_2 (0, 0)
	21 aload (0, 0)
	23 iconst_0 (0, 0)
	24 aload (0, 0)
	26 iload (0, 0)
	28 invokevirtual (0, 0)
	31 return (0, 0)

Method: remainder
	0 aload_1 (0, 0)
	1 iload_2 (0, 0)
	2 daload (0, 0)
	3 aload_3 (0, 0)
	4 iload (0, 0)
	6 daload (0, 0)
	7 invokestatic (0, 0)
	10 dstore (0, 0)
	12 aload_1 (0, 0)
	13 iload_2 (0, 0)
	14 daload (0, 0)
	15 dload (0, 0)
	17 dsub (0, 0)
	18 aload_3 (0, 0)
	19 iload (0, 0)
	21 daload (0, 0)
	22 ddiv (0, 0)
	23 invokestatic (0, 0)
	26 dstore (0, 0)
	28 aload (0, 0)
	30 iload (0, 0)
	32 dload (0, 0)
	34 dastore (0, 0)
	35 iconst_1 (1, 4)
	36 istore (1, 4)
	38 iload (1, 4)
	40 aload_0 (1, 4)
	41 invokevirtual (1, 4)
	44 if_icmpge (1, 4)
	47 aload (1, 4)
	49 iload (1, 4)
	51 iload (1, 4)
	53 iadd (1, 4)
	54 aload_1 (1, 4)
	55 iload_2 (1, 4)
	56 iload (1, 4)
	58 iadd (1, 4)
	59 daload (1, 4)
	60 dload (1, 4)
	62 aload_3 (1, 4)
	63 iload (1, 4)
	65 iload (1, 4)
	67 iadd (1, 4)
	68 daload (1, 4)
	69 dmul (1, 4)
	70 dsub (1, 4)
	71 dastore (1, 4)
	72 iinc (1, 4)
	75 goto (1, 4)
	78 return (0, 0)

Method: pow
	0 aload_0 (0, 0)
	1 invokevirtual (0, 0)
	4 newarray (0, 0)
	6 astore (0, 0)
	8 aload_0 (0, 0)
	9 aload_1 (0, 0)
	10 iload_2 (0, 0)
	11 aload (0, 0)
	13 iconst_0 (0, 0)
	14 invokevirtual (0, 0)
	17 aload_0 (0, 0)
	18 invokevirtual (0, 0)
	21 newarray (0, 0)
	23 astore (0, 0)
	25 aload_0 (0, 0)
	26 aload (0, 0)
	28 iconst_0 (0, 0)
	29 aload_3 (0, 0)
	30 iload (0, 0)
	32 aload (0, 0)
	34 iconst_0 (0, 0)
	35 invokevirtual (0, 0)
	38 aload_0 (0, 0)
	39 aload (0, 0)
	41 iconst_0 (0, 0)
	42 aload (0, 0)
	44 iload (0, 0)
	46 invokevirtual (0, 0)
	49 return (0, 0)

Method: rootN
	0 iconst_1 (0, 0)
	1 aload_0 (0, 0)
	2 getfield (0, 0)
	5 iadd (0, 0)
	6 newarray (0, 0)
	8 astore (0, 0)
	10 iload_3 (1, 1)
	11 iconst_2 (1, 1)
	12 if_icmpne (1, 1)
	15 aload (1, 1)
	17 iconst_0 (1, 1)
	18 aload_1 (1, 1)
	19 iload_2 (1, 1)
	20 daload (1, 1)
	21 invokestatic (1, 1)
	24 dastore (1, 1)
	25 ldc2_w (1, 1)
	28 aload (1, 1)
	30 iconst_0 (1, 1)
	31 daload (1, 1)
	32 ddiv (1, 1)
	33 dstore (1, 1)
	35 goto (1, 1)
	38 iload_3 (1, 1)
	39 iconst_3 (1, 1)
	40 if_icmpne (1, 1)
	43 aload (1, 1)
	45 iconst_0 (1, 1)
	46 aload_1 (1, 1)
	47 iload_2 (1, 1)
	48 daload (1, 1)
	49 invokestatic (1, 1)
	52 dastore (1, 1)
	53 dconst_1 (1, 1)
	54 ldc2_w (1, 1)
	57 aload (1, 1)
	59 iconst_0 (1, 1)
	60 daload (1, 1)
	61 dmul (1, 1)
	62 aload (1, 1)
	64 iconst_0 (1, 1)
	65 daload (1, 1)
	66 dmul (1, 1)
	67 ddiv (1, 1)
	68 dstore (1, 1)
	70 goto (1, 1)
	73 aload (1, 2)
	75 iconst_0 (1, 2)
	76 aload_1 (1, 2)
	77 iload_2 (1, 2)
	78 daload (1, 2)
	79 dconst_1 (1, 2)
	80 iload_3 (1, 2)
	81 i2d (1, 2)
	82 ddiv (1, 2)
	83 invokestatic (1, 2)
	86 dastore (1, 2)
	87 dconst_1 (1, 2)
	88 iload_3 (1, 2)
	89 i2d (1, 2)
	90 aload (1, 2)
	92 iconst_0 (1, 2)
	93 daload (1, 2)
	94 iload_3 (1, 2)
	95 iconst_1 (1, 2)
	96 isub (1, 2)
	97 invokestatic (1, 2)
	100 dmul (1, 2)
	101 ddiv (1, 2)
	102 dstore (1, 2)
	104 dconst_1 (0, 1)
	105 iload_3 (0, 1)
	106 i2d (0, 1)
	107 ddiv (0, 1)
	108 dstore (0, 1)
	110 dconst_1 (0, 1)
	111 aload_1 (0, 1)
	112 iload_2 (0, 1)
	113 daload (0, 1)
	114 ddiv (0, 1)
	115 dstore (0, 1)
	117 iconst_1 (1, 4)
	118 istore (1, 4)
	120 iload (1, 4)
	122 aload_0 (1, 4)
	123 getfield (1, 4)
	126 if_icmpgt (1, 4)
	129 aload (1, 4)
	131 iload (1, 4)
	133 dload (1, 4)
	135 dastore (1, 4)
	136 dload (1, 4)
	138 dload (1, 4)
	140 dload (1, 4)
	142 iload (1, 4)
	144 i2d (1, 4)
	145 dsub (1, 4)
	146 dmul (1, 4)
	147 dmul (1, 4)
	148 dstore (1, 4)
	150 iinc (1, 4)
	153 goto (1, 4)
	156 aload_0 (0, 1)
	157 aload_1 (0, 1)
	158 iload_2 (0, 1)
	159 aload (0, 1)
	161 aload (0, 1)
	163 iload (0, 1)
	165 invokevirtual (0, 1)
	168 return (0, 1)

Method: exp
	0 iconst_1 (0, 0)
	1 aload_0 (0, 0)
	2 getfield (0, 0)
	5 iadd (0, 0)
	6 newarray (0, 0)
	8 astore (0, 0)
	10 aload (0, 0)
	12 aload_1 (0, 0)
	13 iload_2 (0, 0)
	14 daload (0, 0)
	15 invokestatic (0, 0)
	18 invokestatic (0, 0)
	21 aload_0 (0, 0)
	22 aload_1 (0, 0)
	23 iload_2 (0, 0)
	24 aload (0, 0)
	26 aload_3 (0, 0)
	27 iload (0, 0)
	29 invokevirtual (0, 0)
	32 return (0, 0)

Method: expm1
	0 iconst_1 (0, 0)
	1 aload_0 (0, 0)
	2 getfield (0, 0)
	5 iadd (0, 0)
	6 newarray (0, 0)
	8 astore (0, 0)
	10 aload (0, 0)
	12 iconst_0 (0, 0)
	13 aload_1 (0, 0)
	14 iload_2 (0, 0)
	15 daload (0, 0)
	16 invokestatic (0, 0)
	19 dastore (0, 0)
	20 aload (0, 0)
	22 iconst_1 (0, 0)
	23 iconst_1 (0, 0)
	24 aload_0 (0, 0)
	25 getfield (0, 0)
	28 iadd (0, 0)
	29 aload_1 (0, 0)
	30 iload_2 (0, 0)
	31 daload (0, 0)
	32 invokestatic (0, 0)
	35 invokestatic (0, 0)
	38 aload_0 (0, 0)
	39 aload_1 (0, 0)
	40 iload_2 (0, 0)
	41 aload (0, 0)
	43 aload_3 (0, 0)
	44 iload (0, 0)
	46 invokevirtual (0, 0)
	49 return (0, 0)

Method: log
	0 iconst_1 (0, 0)
	1 aload_0 (0, 0)
	2 getfield (0, 0)
	5 iadd (0, 0)
	6 newarray (0, 0)
	8 astore (0, 0)
	10 aload (0, 0)
	12 iconst_0 (0, 0)
	13 aload_1 (0, 0)
	14 iload_2 (0, 0)
	15 daload (0, 0)
	16 invokestatic (0, 0)
	19 dastore (0, 0)
	20 aload_0 (1, 1)
	21 getfield (1, 1)
	24 ifle (1, 1)
	27 dconst_1 (1, 1)
	28 aload_1 (1, 1)
	29 iload_2 (1, 1)
	30 daload (1, 1)
	31 ddiv (1, 1)
	32 dstore (1, 1)
	34 dload (1, 1)
	36 dstore (1, 1)
	38 iconst_1 (2, 4)
	39 istore (2, 4)
	41 iload (2, 4)
	43 aload_0 (2, 4)
	44 getfield (2, 4)
	47 if_icmpgt (2, 4)
	50 aload (2, 4)
	52 iload (2, 4)
	54 dload (2, 4)
	56 dastore (2, 4)
	57 dload (2, 4)
	59 iload (2, 4)
	61 ineg (2, 4)
	62 i2d (2, 4)
	63 dload (2, 4)
	65 dmul (2, 4)
	66 dmul (2, 4)
	67 dstore (2, 4)
	69 iinc (2, 4)
	72 goto (2, 4)
	75 aload_0 (0, 0)
	76 aload_1 (0, 0)
	77 iload_2 (0, 0)
	78 aload (0, 0)
	80 aload_3 (0, 0)
	81 iload (0, 0)
	83 invokevirtual (0, 0)
	86 return (0, 0)

Method: log1p
	0 iconst_1 (0, 0)
	1 aload_0 (0, 0)
	2 getfield (0, 0)
	5 iadd (0, 0)
	6 newarray (0, 0)
	8 astore (0, 0)
	10 aload (0, 0)
	12 iconst_0 (0, 0)
	13 aload_1 (0, 0)
	14 iload_2 (0, 0)
	15 daload (0, 0)
	16 invokestatic (0, 0)
	19 dastore (0, 0)
	20 aload_0 (1, 1)
	21 getfield (1, 1)
	24 ifle (1, 1)
	27 dconst_1 (1, 1)
	28 dconst_1 (1, 1)
	29 aload_1 (1, 1)
	30 iload_2 (1, 1)
	31 daload (1, 1)
	32 dadd (1, 1)
	33 ddiv (1, 1)
	34 dstore (1, 1)
	36 dload (1, 1)
	38 dstore (1, 1)
	40 iconst_1 (2, 4)
	41 istore (2, 4)
	43 iload (2, 4)
	45 aload_0 (2, 4)
	46 getfield (2, 4)
	49 if_icmpgt (2, 4)
	52 aload (2, 4)
	54 iload (2, 4)
	56 dload (2, 4)
	58 dastore (2, 4)
	59 dload (2, 4)
	61 iload (2, 4)
	63 ineg (2, 4)
	64 i2d (2, 4)
	65 dload (2, 4)
	67 dmul (2, 4)
	68 dmul (2, 4)
	69 dstore (2, 4)
	71 iinc (2, 4)
	74 goto (2, 4)
	77 aload_0 (0, 0)
	78 aload_1 (0, 0)
	79 iload_2 (0, 0)
	80 aload (0, 0)
	82 aload_3 (0, 0)
	83 iload (0, 0)
	85 invokevirtual (0, 0)
	88 return (0, 0)

Method: log10
	0 iconst_1 (0, 0)
	1 aload_0 (0, 0)
	2 getfield (0, 0)
	5 iadd (0, 0)
	6 newarray (0, 0)
	8 astore (0, 0)
	10 aload (0, 0)
	12 iconst_0 (0, 0)
	13 aload_1 (0, 0)
	14 iload_2 (0, 0)
	15 daload (0, 0)
	16 invokestatic (0, 0)
	19 dastore (0, 0)
	20 aload_0 (1, 1)
	21 getfield (1, 1)
	24 ifle (1, 1)
	27 dconst_1 (1, 1)
	28 aload_1 (1, 1)
	29 iload_2 (1, 1)
	30 daload (1, 1)
	31 ddiv (1, 1)
	32 dstore (1, 1)
	34 dload (1, 1)
	36 ldc2_w (1, 1)
	39 invokestatic (1, 1)
	42 ddiv (1, 1)
	43 dstore (1, 1)
	45 iconst_1 (2, 4)
	46 istore (2, 4)
	48 iload (2, 4)
	50 aload_0 (2, 4)
	51 getfield (2, 4)
	54 if_icmpgt (2, 4)
	57 aload (2, 4)
	59 iload (2, 4)
	61 dload (2, 4)
	63 dastore (2, 4)
	64 dload (2, 4)
	66 iload (2, 4)
	68 ineg (2, 4)
	69 i2d (2, 4)
	70 dload (2, 4)
	72 dmul (2, 4)
	73 dmul (2, 4)
	74 dstore (2, 4)
	76 iinc (2, 4)
	79 goto (2, 4)
	82 aload_0 (0, 0)
	83 aload_1 (0, 0)
	84 iload_2 (0, 0)
	85 aload (0, 0)
	87 aload_3 (0, 0)
	88 iload (0, 0)
	90 invokevirtual (0, 0)
	93 return (0, 0)

Method: cos
	0 iconst_1 (0, 0)
	1 aload_0 (0, 0)
	2 getfield (0, 0)
	5 iadd (0, 0)
	6 newarray (0, 0)
	8 astore (0, 0)
	10 aload (0, 0)
	12 iconst_0 (0, 0)
	13 aload_1 (0, 0)
	14 iload_2 (0, 0)
	15 daload (0, 0)
	16 invokestatic (0, 0)
	19 dastore (0, 0)
	20 aload_0 (1, 1)
	21 getfield (1, 1)
	24 ifle (1, 1)
	27 aload (1, 1)
	29 iconst_1 (1, 1)
	30 aload_1 (1, 1)
	31 iload_2 (1, 1)
	32 daload (1, 1)
	33 invokestatic (1, 1)
	36 dneg (1, 1)
	37 dastore (1, 1)
	38 iconst_2 (2, 4)
	39 istore (2, 4)
	41 iload (2, 4)
	43 aload_0 (2, 4)
	44 getfield (2, 4)
	47 if_icmpgt (2, 4)
	50 aload (2, 4)
	52 iload (2, 4)
	54 aload (2, 4)
	56 iload (2, 4)
	58 iconst_2 (2, 4)
	59 isub (2, 4)
	60 daload (2, 4)
	61 dneg (2, 4)
	62 dastore (2, 4)
	63 iinc (2, 4)
	66 goto (2, 4)
	69 aload_0 (0, 0)
	70 aload_1 (0, 0)
	71 iload_2 (0, 0)
	72 aload (0, 0)
	74 aload_3 (0, 0)
	75 iload (0, 0)
	77 invokevirtual (0, 0)
	80 return (0, 0)

Method: sin
	0 iconst_1 (0, 0)
	1 aload_0 (0, 0)
	2 getfield (0, 0)
	5 iadd (0, 0)
	6 newarray (0, 0)
	8 astore (0, 0)
	10 aload (0, 0)
	12 iconst_0 (0, 0)
	13 aload_1 (0, 0)
	14 iload_2 (0, 0)
	15 daload (0, 0)
	16 invokestatic (0, 0)
	19 dastore (0, 0)
	20 aload_0 (1, 1)
	21 getfield (1, 1)
	24 ifle (1, 1)
	27 aload (1, 1)
	29 iconst_1 (1, 1)
	30 aload_1 (1, 1)
	31 iload_2 (1, 1)
	32 daload (1, 1)
	33 invokestatic (1, 1)
	36 dastore (1, 1)
	37 iconst_2 (2, 4)
	38 istore (2, 4)
	40 iload (2, 4)
	42 aload_0 (2, 4)
	43 getfield (2, 4)
	46 if_icmpgt (2, 4)
	49 aload (2, 4)
	51 iload (2, 4)
	53 aload (2, 4)
	55 iload (2, 4)
	57 iconst_2 (2, 4)
	58 isub (2, 4)
	59 daload (2, 4)
	60 dneg (2, 4)
	61 dastore (2, 4)
	62 iinc (2, 4)
	65 goto (2, 4)
	68 aload_0 (0, 0)
	69 aload_1 (0, 0)
	70 iload_2 (0, 0)
	71 aload (0, 0)
	73 aload_3 (0, 0)
	74 iload (0, 0)
	76 invokevirtual (0, 0)
	79 return (0, 0)

Method: tan
	0 iconst_1 (0, 0)
	1 aload_0 (0, 0)
	2 getfield (0, 0)
	5 iadd (0, 0)
	6 newarray (0, 0)
	8 astore (0, 0)
	10 aload_1 (0, 0)
	11 iload_2 (0, 0)
	12 daload (0, 0)
	13 invokestatic (0, 0)
	16 dstore (0, 0)
	18 aload (0, 0)
	20 iconst_0 (0, 0)
	21 dload (0, 0)
	23 dastore (0, 0)
	24 aload_0 (1, 1)
	25 getfield (1, 1)
	28 ifle (1, 1)
	31 aload_0 (1, 4)
	32 getfield (1, 4)
	35 iconst_2 (1, 4)
	36 iadd (1, 4)
	37 newarray (1, 4)
	39 astore (1, 4)
	41 aload (1, 4)
	43 iconst_1 (1, 4)
	44 dconst_1 (1, 4)
	45 dastore (1, 4)
	46 dload (1, 4)
	48 dload (1, 4)
	50 dmul (1, 4)
	51 dstore (1, 4)
	53 iconst_1 (2, 4)
	54 istore (2, 4)
	56 iload (2, 4)
	58 aload_0 (2, 4)
	59 getfield (2, 4)
	62 if_icmpgt (2, 4)
	65 dconst_0 (2, 4)
	66 dstore (2, 4)
	68 aload (2, 4)
	70 iload (2, 4)
	72 iconst_1 (2, 4)
	73 iadd (2, 4)
	74 iload (2, 4)
	76 i2d (2, 4)
	77 aload (2, 4)
	79 iload (2, 4)
	81 daload (2, 4)
	82 dmul (2, 4)
	83 dastore (2, 4)
	84 iload (3, 4)
	86 iconst_1 (3, 4)
	87 iadd (3, 4)
	88 istore (3, 4)
	90 iload (3, 4)
	92 iflt (3, 4)
	95 dload (3, 4)
	97 dload (3, 4)
	99 dmul (3, 4)
	100 aload (3, 4)
	102 iload (3, 4)
	104 daload (3, 4)
	105 dadd (3, 4)
	106 dstore (3, 4)
	108 iload (4, 1)
	110 iconst_2 (4, 1)
	111 if_icmple (4, 1)
	114 aload (4, 1)
	116 iload (4, 1)
	118 iconst_2 (4, 1)
	119 isub (4, 1)
	120 iload (4, 1)
	122 iconst_1 (4, 1)
	123 isub (4, 1)
	124 i2d (4, 1)
	125 aload (4, 1)
	127 iload (4, 1)
	129 iconst_1 (4, 1)
	130 isub (4, 1)
	131 daload (4, 1)
	132 dmul (4, 1)
	133 iload (4, 1)
	135 iconst_3 (4, 1)
	136 isub (4, 1)
	137 i2d (4, 1)
	138 aload (4, 1)
	140 iload (4, 1)
	142 iconst_3 (4, 1)
	143 isub (4, 1)
	144 daload (4, 1)
	145 dmul (4, 1)
	146 dadd (4, 1)
	147 dastore (4, 1)
	148 goto (4, 1)
	151 iload (4, 1)
	153 iconst_2 (4, 1)
	154 if_icmpne (4, 1)
	157 aload (4, 1)
	159 iconst_0 (4, 1)
	160 aload (4, 1)
	162 iconst_1 (4, 1)
	163 daload (4, 1)
	164 dastore (4, 1)
	165 iinc (4, 1)
	168 goto (4, 1)
	171 iload (4, 1)
	173 iconst_1 (4, 1)
	174 iand (4, 1)
	175 ifne (4, 1)
	178 dload (4, 1)
	180 dload (4, 1)
	182 dmul (4, 1)
	183 dstore (4, 1)
	185 aload (3, 1)
	187 iload (3, 1)
	189 dload (3, 1)
	191 dastore (3, 1)
	192 iinc (3, 1)
	195 goto (3, 1)
	198 aload_0 (1, 1)
	199 aload_1 (1, 1)
	200 iload_2 (1, 1)
	201 aload (1, 1)
	203 aload_3 (1, 1)
	204 iload (1, 1)
	206 invokevirtual (1, 1)
	209 return (0, 4)

Method: acos
	0 iconst_1 (0, 0)
	1 aload_0 (0, 0)
	2 getfield (0, 0)
	5 iadd (0, 0)
	6 newarray (0, 0)
	8 astore (0, 0)
	10 aload_1 (0, 0)
	11 iload_2 (0, 0)
	12 daload (0, 0)
	13 dstore (0, 0)
	15 aload (0, 0)
	17 iconst_0 (0, 0)
	18 dload (0, 0)
	20 invokestatic (0, 0)
	23 dastore (0, 0)
	24 aload_0 (1, 1)
	25 getfield (1, 1)
	28 ifle (1, 1)
	31 aload_0 (1, 4)
	32 getfield (1, 4)
	35 newarray (1, 4)
	37 astore (1, 4)
	39 aload (1, 4)
	41 iconst_0 (1, 4)
	42 ldc2_w (1, 4)
	45 dastore (1, 4)
	46 dload (1, 4)
	48 dload (1, 4)
	50 dmul (1, 4)
	51 dstore (1, 4)
	53 dconst_1 (1, 4)
	54 dconst_1 (1, 4)
	55 dload (1, 4)
	57 dsub (1, 4)
	58 ddiv (1, 4)
	59 dstore (1, 4)
	61 dload (1, 4)
	63 invokestatic (1, 4)
	66 dstore (1, 4)
	68 aload (1, 4)
	70 iconst_1 (1, 4)
	71 dload (1, 4)
	73 aload (1, 4)
	75 iconst_0 (1, 4)
	76 daload (1, 4)
	77 dmul (1, 4)
	78 dastore (1, 4)
	79 iconst_2 (2, 4)
	80 istore (2, 4)
	82 iload (2, 4)
	84 aload_0 (2, 4)
	85 getfield (2, 4)
	88 if_icmpgt (2, 4)
	91 dconst_0 (2, 4)
	92 dstore (2, 4)
	94 aload (2, 4)
	96 iload (2, 4)
	98 iconst_1 (2, 4)
	99 isub (2, 4)
	100 iload (2, 4)
	102 iconst_1 (2, 4)
	103 isub (2, 4)
	104 i2d (2, 4)
	105 aload (2, 4)
	107 iload (2, 4)
	109 iconst_2 (2, 4)
	110 isub (2, 4)
	111 daload (2, 4)
	112 dmul (2, 4)
	113 dastore (2, 4)
	114 iload (3, 4)
	116 iconst_1 (3, 4)
	117 isub (3, 4)
	118 istore (3, 4)
	120 iload (3, 4)
	122 iflt (3, 4)
	125 dload (3, 4)
	127 dload (3, 4)
	129 dmul (3, 4)
	130 aload (3, 4)
	132 iload (3, 4)
	134 daload (3, 4)
	135 dadd (3, 4)
	136 dstore (3, 4)
	138 iload (4, 1)
	140 iconst_2 (4, 1)
	141 if_icmple (4, 1)
	144 aload (4, 1)
	146 iload (4, 1)
	148 iconst_2 (4, 1)
	149 isub (4, 1)
	150 iload (4, 1)
	152 iconst_1 (4, 1)
	153 isub (4, 1)
	154 i2d (4, 1)
	155 aload (4, 1)
	157 iload (4, 1)
	159 iconst_1 (4, 1)
	160 isub (4, 1)
	161 daload (4, 1)
	162 dmul (4, 1)
	163 iconst_2 (4, 1)
	164 iload (4, 1)
	166 imul (4, 1)
	167 iload (4, 1)
	169 isub (4, 1)
	170 i2d (4, 1)
	171 aload (4, 1)
	173 iload (4, 1)
	175 iconst_3 (4, 1)
	176 isub (4, 1)
	177 daload (4, 1)
	178 dmul (4, 1)
	179 dadd (4, 1)
	180 dastore (4, 1)
	181 goto (4, 1)
	184 iload (4, 1)
	186 iconst_2 (4, 1)
	187 if_icmpne (4, 1)
	190 aload (4, 1)
	192 iconst_0 (4, 1)
	193 aload (4, 1)
	195 iconst_1 (4, 1)
	196 daload (4, 1)
	197 dastore (4, 1)
	198 iinc (4, 1)
	201 goto (4, 1)
	204 iload (4, 1)
	206 iconst_1 (4, 1)
	207 iand (4, 1)
	208 ifne (4, 1)
	211 dload (4, 1)
	213 dload (4, 1)
	215 dmul (4, 1)
	216 dstore (4, 1)
	218 dload (3, 1)
	220 dload (3, 1)
	222 dmul (3, 1)
	223 dstore (3, 1)
	225 aload (3, 1)
	227 iload (3, 1)
	229 dload (3, 1)
	231 dload (3, 1)
	233 dmul (3, 1)
	234 dastore (3, 1)
	235 iinc (3, 1)
	238 goto (3, 1)
	241 aload_0 (1, 1)
	242 aload_1 (1, 1)
	243 iload_2 (1, 1)
	244 aload (1, 1)
	246 aload_3 (1, 1)
	247 iload (1, 1)
	249 invokevirtual (1, 1)
	252 return (0, 4)

Method: asin
	0 iconst_1 (0, 0)
	1 aload_0 (0, 0)
	2 getfield (0, 0)
	5 iadd (0, 0)
	6 newarray (0, 0)
	8 astore (0, 0)
	10 aload_1 (0, 0)
	11 iload_2 (0, 0)
	12 daload (0, 0)
	13 dstore (0, 0)
	15 aload (0, 0)
	17 iconst_0 (0, 0)
	18 dload (0, 0)
	20 invokestatic (0, 0)
	23 dastore (0, 0)
	24 aload_0 (1, 1)
	25 getfield (1, 1)
	28 ifle (1, 1)
	31 aload_0 (1, 4)
	32 getfield (1, 4)
	35 newarray (1, 4)
	37 astore (1, 4)
	39 aload (1, 4)
	41 iconst_0 (1, 4)
	42 dconst_1 (1, 4)
	43 dastore (1, 4)
	44 dload (1, 4)
	46 dload (1, 4)
	48 dmul (1, 4)
	49 dstore (1, 4)
	51 dconst_1 (1, 4)
	52 dconst_1 (1, 4)
	53 dload (1, 4)
	55 dsub (1, 4)
	56 ddiv (1, 4)
	57 dstore (1, 4)
	59 dload (1, 4)
	61 invokestatic (1, 4)
	64 dstore (1, 4)
	66 aload (1, 4)
	68 iconst_1 (1, 4)
	69 dload (1, 4)
	71 aload (1, 4)
	73 iconst_0 (1, 4)
	74 daload (1, 4)
	75 dmul (1, 4)
	76 dastore (1, 4)
	77 iconst_2 (2, 4)
	78 istore (2, 4)
	80 iload (2, 4)
	82 aload_0 (2, 4)
	83 getfield (2, 4)
	86 if_icmpgt (2, 4)
	89 dconst_0 (2, 4)
	90 dstore (2, 4)
	92 aload (2, 4)
	94 iload (2, 4)
	96 iconst_1 (2, 4)
	97 isub (2, 4)
	98 iload (2, 4)
	100 iconst_1 (2, 4)
	101 isub (2, 4)
	102 i2d (2, 4)
	103 aload (2, 4)
	105 iload (2, 4)
	107 iconst_2 (2, 4)
	108 isub (2, 4)
	109 daload (2, 4)
	110 dmul (2, 4)
	111 dastore (2, 4)
	112 iload (3, 4)
	114 iconst_1 (3, 4)
	115 isub (3, 4)
	116 istore (3, 4)
	118 iload (3, 4)
	120 iflt (3, 4)
	123 dload (3, 4)
	125 dload (3, 4)
	127 dmul (3, 4)
	128 aload (3, 4)
	130 iload (3, 4)
	132 daload (3, 4)
	133 dadd (3, 4)
	134 dstore (3, 4)
	136 iload (4, 1)
	138 iconst_2 (4, 1)
	139 if_icmple (4, 1)
	142 aload (4, 1)
	144 iload (4, 1)
	146 iconst_2 (4, 1)
	147 isub (4, 1)
	148 iload (4, 1)
	150 iconst_1 (4, 1)
	151 isub (4, 1)
	152 i2d (4, 1)
	153 aload (4, 1)
	155 iload (4, 1)
	157 iconst_1 (4, 1)
	158 isub (4, 1)
	159 daload (4, 1)
	160 dmul (4, 1)
	161 iconst_2 (4, 1)
	162 iload (4, 1)
	164 imul (4, 1)
	165 iload (4, 1)
	167 isub (4, 1)
	168 i2d (4, 1)
	169 aload (4, 1)
	171 iload (4, 1)
	173 iconst_3 (4, 1)
	174 isub (4, 1)
	175 daload (4, 1)
	176 dmul (4, 1)
	177 dadd (4, 1)
	178 dastore (4, 1)
	179 goto (4, 1)
	182 iload (4, 1)
	184 iconst_2 (4, 1)
	185 if_icmpne (4, 1)
	188 aload (4, 1)
	190 iconst_0 (4, 1)
	191 aload (4, 1)
	193 iconst_1 (4, 1)
	194 daload (4, 1)
	195 dastore (4, 1)
	196 iinc (4, 1)
	199 goto (4, 1)
	202 iload (4, 1)
	204 iconst_1 (4, 1)
	205 iand (4, 1)
	206 ifne (4, 1)
	209 dload (4, 1)
	211 dload (4, 1)
	213 dmul (4, 1)
	214 dstore (4, 1)
	216 dload (3, 1)
	218 dload (3, 1)
	220 dmul (3, 1)
	221 dstore (3, 1)
	223 aload (3, 1)
	225 iload (3, 1)
	227 dload (3, 1)
	229 dload (3, 1)
	231 dmul (3, 1)
	232 dastore (3, 1)
	233 iinc (3, 1)
	236 goto (3, 1)
	239 aload_0 (1, 1)
	240 aload_1 (1, 1)
	241 iload_2 (1, 1)
	242 aload (1, 1)
	244 aload_3 (1, 1)
	245 iload (1, 1)
	247 invokevirtual (1, 1)
	250 return (0, 4)

Method: atan
	0 iconst_1 (0, 0)
	1 aload_0 (0, 0)
	2 getfield (0, 0)
	5 iadd (0, 0)
	6 newarray (0, 0)
	8 astore (0, 0)
	10 aload_1 (0, 0)
	11 iload_2 (0, 0)
	12 daload (0, 0)
	13 dstore (0, 0)
	15 aload (0, 0)
	17 iconst_0 (0, 0)
	18 dload (0, 0)
	20 invokestatic (0, 0)
	23 dastore (0, 0)
	24 aload_0 (1, 1)
	25 getfield (1, 1)
	28 ifle (1, 1)
	31 aload_0 (1, 4)
	32 getfield (1, 4)
	35 newarray (1, 4)
	37 astore (1, 4)
	39 aload (1, 4)
	41 iconst_0 (1, 4)
	42 dconst_1 (1, 4)
	43 dastore (1, 4)
	44 dload (1, 4)
	46 dload (1, 4)
	48 dmul (1, 4)
	49 dstore (1, 4)
	51 dconst_1 (1, 4)
	52 dconst_1 (1, 4)
	53 dload (1, 4)
	55 dadd (1, 4)
	56 ddiv (1, 4)
	57 dstore (1, 4)
	59 dload (1, 4)
	61 dstore (1, 4)
	63 aload (1, 4)
	65 iconst_1 (1, 4)
	66 dload (1, 4)
	68 aload (1, 4)
	70 iconst_0 (1, 4)
	71 daload (1, 4)
	72 dmul (1, 4)
	73 dastore (1, 4)
	74 iconst_2 (2, 4)
	75 istore (2, 4)
	77 iload (2, 4)
	79 aload_0 (2, 4)
	80 getfield (2, 4)
	83 if_icmpgt (2, 4)
	86 dconst_0 (2, 4)
	87 dstore (2, 4)
	89 aload (2, 4)
	91 iload (2, 4)
	93 iconst_1 (2, 4)
	94 isub (2, 4)
	95 iload (2, 4)
	97 ineg (2, 4)
	98 i2d (2, 4)
	99 aload (2, 4)
	101 iload (2, 4)
	103 iconst_2 (2, 4)
	104 isub (2, 4)
	105 daload (2, 4)
	106 dmul (2, 4)
	107 dastore (2, 4)
	108 iload (3, 4)
	110 iconst_1 (3, 4)
	111 isub (3, 4)
	112 istore (3, 4)
	114 iload (3, 4)
	116 iflt (3, 4)
	119 dload (3, 4)
	121 dload (3, 4)
	123 dmul (3, 4)
	124 aload (3, 4)
	126 iload (3, 4)
	128 daload (3, 4)
	129 dadd (3, 4)
	130 dstore (3, 4)
	132 iload (4, 1)
	134 iconst_2 (4, 1)
	135 if_icmple (4, 1)
	138 aload (4, 1)
	140 iload (4, 1)
	142 iconst_2 (4, 1)
	143 isub (4, 1)
	144 iload (4, 1)
	146 iconst_1 (4, 1)
	147 isub (4, 1)
	148 i2d (4, 1)
	149 aload (4, 1)
	151 iload (4, 1)
	153 iconst_1 (4, 1)
	154 isub (4, 1)
	155 daload (4, 1)
	156 dmul (4, 1)
	157 iload (4, 1)
	159 iconst_1 (4, 1)
	160 isub (4, 1)
	161 iconst_2 (4, 1)
	162 iload (4, 1)
	164 imul (4, 1)
	165 isub (4, 1)
	166 i2d (4, 1)
	167 aload (4, 1)
	169 iload (4, 1)
	171 iconst_3 (4, 1)
	172 isub (4, 1)
	173 daload (4, 1)
	174 dmul (4, 1)
	175 dadd (4, 1)
	176 dastore (4, 1)
	177 goto (4, 1)
	180 iload (4, 1)
	182 iconst_2 (4, 1)
	183 if_icmpne (4, 1)
	186 aload (4, 1)
	188 iconst_0 (4, 1)
	189 aload (4, 1)
	191 iconst_1 (4, 1)
	192 daload (4, 1)
	193 dastore (4, 1)
	194 iinc (4, 1)
	197 goto (4, 1)
	200 iload (4, 1)
	202 iconst_1 (4, 1)
	203 iand (4, 1)
	204 ifne (4, 1)
	207 dload (4, 1)
	209 dload (4, 1)
	211 dmul (4, 1)
	212 dstore (4, 1)
	214 dload (3, 1)
	216 dload (3, 1)
	218 dmul (3, 1)
	219 dstore (3, 1)
	221 aload (3, 1)
	223 iload (3, 1)
	225 dload (3, 1)
	227 dload (3, 1)
	229 dmul (3, 1)
	230 dastore (3, 1)
	231 iinc (3, 1)
	234 goto (3, 1)
	237 aload_0 (1, 1)
	238 aload_1 (1, 1)
	239 iload_2 (1, 1)
	240 aload (1, 1)
	242 aload_3 (1, 1)
	243 iload (1, 1)
	245 invokevirtual (1, 1)
	248 return (0, 4)

Method: atan2
	0 aload_0 (0, 0)
	1 invokevirtual (0, 0)
	4 newarray (0, 0)
	6 astore (0, 0)
	8 aload_0 (0, 0)
	9 aload_3 (0, 0)
	10 iload (0, 0)
	12 aload_3 (0, 0)
	13 iload (0, 0)
	15 aload (0, 0)
	17 iconst_0 (0, 0)
	18 invokevirtual (0, 0)
	21 aload_0 (0, 0)
	22 invokevirtual (0, 0)
	25 newarray (0, 0)
	27 astore (0, 0)
	29 aload_0 (0, 0)
	30 aload_1 (0, 0)
	31 iload_2 (0, 0)
	32 aload_1 (0, 0)
	33 iload_2 (0, 0)
	34 aload (0, 0)
	36 iconst_0 (0, 0)
	37 invokevirtual (0, 0)
	40 aload_0 (0, 0)
	41 aload (0, 0)
	43 iconst_0 (0, 0)
	44 aload (0, 0)
	46 iconst_0 (0, 0)
	47 aload (0, 0)
	49 iconst_0 (0, 0)
	50 invokevirtual (0, 0)
	53 aload_0 (0, 0)
	54 aload (0, 0)
	56 iconst_0 (0, 0)
	57 iconst_2 (0, 0)
	58 aload (0, 0)
	60 iconst_0 (0, 0)
	61 invokevirtual (0, 0)
	64 aload_3 (1, 1)
	65 iload (1, 1)
	67 daload (1, 1)
	68 dconst_0 (1, 1)
	69 dcmpl (1, 1)
	70 iflt (1, 1)
	73 aload_0 (1, 1)
	74 aload (1, 1)
	76 iconst_0 (1, 1)
	77 aload_3 (1, 1)
	78 iload (1, 1)
	80 aload (1, 1)
	82 iconst_0 (1, 1)
	83 invokevirtual (1, 1)
	86 aload_0 (1, 1)
	87 aload_1 (1, 1)
	88 iload_2 (1, 1)
	89 aload (1, 1)
	91 iconst_0 (1, 1)
	92 aload (1, 1)
	94 iconst_0 (1, 1)
	95 invokevirtual (1, 1)
	98 aload_0 (1, 1)
	99 aload (1, 1)
	101 iconst_0 (1, 1)
	102 aload (1, 1)
	104 iconst_0 (1, 1)
	105 invokevirtual (1, 1)
	108 iconst_0 (2, 4)
	109 istore (2, 4)
	111 iload (2, 4)
	113 aload (2, 4)
	115 arraylength (2, 4)
	116 if_icmpge (2, 4)
	119 aload (2, 4)
	121 iload (2, 4)
	123 iload (2, 4)
	125 iadd (2, 4)
	126 ldc2_w (2, 4)
	129 aload (2, 4)
	131 iload (2, 4)
	133 daload (2, 4)
	134 dmul (2, 4)
	135 dastore (2, 4)
	136 iinc (2, 4)
	139 goto (2, 4)
	142 goto (2, 4)
	145 aload_0 (1, 2)
	146 aload (1, 2)
	148 iconst_0 (1, 2)
	149 aload_3 (1, 2)
	150 iload (1, 2)
	152 aload (1, 2)
	154 iconst_0 (1, 2)
	155 invokevirtual (1, 2)
	158 aload_0 (1, 2)
	159 aload_1 (1, 2)
	160 iload_2 (1, 2)
	161 aload (1, 2)
	163 iconst_0 (1, 2)
	164 aload (1, 2)
	166 iconst_0 (1, 2)
	167 invokevirtual (1, 2)
	170 aload_0 (1, 2)
	171 aload (1, 2)
	173 iconst_0 (1, 2)
	174 aload (1, 2)
	176 iconst_0 (1, 2)
	177 invokevirtual (1, 2)
	180 aload (1, 2)
	182 iload (1, 2)
	184 aload (1, 2)
	186 iconst_0 (1, 2)
	187 daload (1, 2)
	188 dconst_0 (1, 2)
	189 dcmpg (1, 2)
	190 ifgt (1, 2)
	193 ldc2_w (1, 2)
	196 goto (1, 2)
	199 ldc2_w (1, 2)
	202 ldc2_w (1, 2)
	205 aload (1, 2)
	207 iconst_0 (1, 2)
	208 daload (1, 2)
	209 dmul (1, 2)
	210 dsub (1, 2)
	211 dastore (1, 2)
	212 iconst_1 (2, 4)
	213 istore (2, 4)
	215 iload (2, 4)
	217 aload (2, 4)
	219 arraylength (2, 4)
	220 if_icmpge (2, 4)
	223 aload (2, 4)
	225 iload (2, 4)
	227 iload (2, 4)
	229 iadd (2, 4)
	230 ldc2_w (2, 4)
	233 aload (2, 4)
	235 iload (2, 4)
	237 daload (2, 4)
	238 dmul (2, 4)
	239 dastore (2, 4)
	240 iinc (2, 4)
	243 goto (2, 4)
	246 aload (0, 1)
	248 iload (0, 1)
	250 aload_1 (0, 1)
	251 iload_2 (0, 1)
	252 daload (0, 1)
	253 aload_3 (0, 1)
	254 iload (0, 1)
	256 daload (0, 1)
	257 invokestatic (0, 1)
	260 dastore (0, 1)
	261 return (0, 0)

Method: cosh
	0 iconst_1 (0, 0)
	1 aload_0 (0, 0)
	2 getfield (0, 0)
	5 iadd (0, 0)
	6 newarray (0, 0)
	8 astore (0, 0)
	10 aload (0, 0)
	12 iconst_0 (0, 0)
	13 aload_1 (0, 0)
	14 iload_2 (0, 0)
	15 daload (0, 0)
	16 invokestatic (0, 0)
	19 dastore (0, 0)
	20 aload_0 (1, 1)
	21 getfield (1, 1)
	24 ifle (1, 1)
	27 aload (1, 1)
	29 iconst_1 (1, 1)
	30 aload_1 (1, 1)
	31 iload_2 (1, 1)
	32 daload (1, 1)
	33 invokestatic (1, 1)
	36 dastore (1, 1)
	37 iconst_2 (2, 4)
	38 istore (2, 4)
	40 iload (2, 4)
	42 aload_0 (2, 4)
	43 getfield (2, 4)
	46 if_icmpgt (2, 4)
	49 aload (2, 4)
	51 iload (2, 4)
	53 aload (2, 4)
	55 iload (2, 4)
	57 iconst_2 (2, 4)
	58 isub (2, 4)
	59 daload (2, 4)
	60 dastore (2, 4)
	61 iinc (2, 4)
	64 goto (2, 4)
	67 aload_0 (0, 0)
	68 aload_1 (0, 0)
	69 iload_2 (0, 0)
	70 aload (0, 0)
	72 aload_3 (0, 0)
	73 iload (0, 0)
	75 invokevirtual (0, 0)
	78 return (0, 0)

Method: sinh
	0 iconst_1 (0, 0)
	1 aload_0 (0, 0)
	2 getfield (0, 0)
	5 iadd (0, 0)
	6 newarray (0, 0)
	8 astore (0, 0)
	10 aload (0, 0)
	12 iconst_0 (0, 0)
	13 aload_1 (0, 0)
	14 iload_2 (0, 0)
	15 daload (0, 0)
	16 invokestatic (0, 0)
	19 dastore (0, 0)
	20 aload_0 (1, 1)
	21 getfield (1, 1)
	24 ifle (1, 1)
	27 aload (1, 1)
	29 iconst_1 (1, 1)
	30 aload_1 (1, 1)
	31 iload_2 (1, 1)
	32 daload (1, 1)
	33 invokestatic (1, 1)
	36 dastore (1, 1)
	37 iconst_2 (2, 4)
	38 istore (2, 4)
	40 iload (2, 4)
	42 aload_0 (2, 4)
	43 getfield (2, 4)
	46 if_icmpgt (2, 4)
	49 aload (2, 4)
	51 iload (2, 4)
	53 aload (2, 4)
	55 iload (2, 4)
	57 iconst_2 (2, 4)
	58 isub (2, 4)
	59 daload (2, 4)
	60 dastore (2, 4)
	61 iinc (2, 4)
	64 goto (2, 4)
	67 aload_0 (0, 0)
	68 aload_1 (0, 0)
	69 iload_2 (0, 0)
	70 aload (0, 0)
	72 aload_3 (0, 0)
	73 iload (0, 0)
	75 invokevirtual (0, 0)
	78 return (0, 0)

Method: tanh
	0 iconst_1 (0, 0)
	1 aload_0 (0, 0)
	2 getfield (0, 0)
	5 iadd (0, 0)
	6 newarray (0, 0)
	8 astore (0, 0)
	10 aload_1 (0, 0)
	11 iload_2 (0, 0)
	12 daload (0, 0)
	13 invokestatic (0, 0)
	16 dstore (0, 0)
	18 aload (0, 0)
	20 iconst_0 (0, 0)
	21 dload (0, 0)
	23 dastore (0, 0)
	24 aload_0 (1, 1)
	25 getfield (1, 1)
	28 ifle (1, 1)
	31 aload_0 (1, 4)
	32 getfield (1, 4)
	35 iconst_2 (1, 4)
	36 iadd (1, 4)
	37 newarray (1, 4)
	39 astore (1, 4)
	41 aload (1, 4)
	43 iconst_1 (1, 4)
	44 dconst_1 (1, 4)
	45 dastore (1, 4)
	46 dload (1, 4)
	48 dload (1, 4)
	50 dmul (1, 4)
	51 dstore (1, 4)
	53 iconst_1 (2, 4)
	54 istore (2, 4)
	56 iload (2, 4)
	58 aload_0 (2, 4)
	59 getfield (2, 4)
	62 if_icmpgt (2, 4)
	65 dconst_0 (2, 4)
	66 dstore (2, 4)
	68 aload (2, 4)
	70 iload (2, 4)
	72 iconst_1 (2, 4)
	73 iadd (2, 4)
	74 iload (2, 4)
	76 ineg (2, 4)
	77 i2d (2, 4)
	78 aload (2, 4)
	80 iload (2, 4)
	82 daload (2, 4)
	83 dmul (2, 4)
	84 dastore (2, 4)
	85 iload (3, 4)
	87 iconst_1 (3, 4)
	88 iadd (3, 4)
	89 istore (3, 4)
	91 iload (3, 4)
	93 iflt (3, 4)
	96 dload (3, 4)
	98 dload (3, 4)
	100 dmul (3, 4)
	101 aload (3, 4)
	103 iload (3, 4)
	105 daload (3, 4)
	106 dadd (3, 4)
	107 dstore (3, 4)
	109 iload (4, 1)
	111 iconst_2 (4, 1)
	112 if_icmple (4, 1)
	115 aload (4, 1)
	117 iload (4, 1)
	119 iconst_2 (4, 1)
	120 isub (4, 1)
	121 iload (4, 1)
	123 iconst_1 (4, 1)
	124 isub (4, 1)
	125 i2d (4, 1)
	126 aload (4, 1)
	128 iload (4, 1)
	130 iconst_1 (4, 1)
	131 isub (4, 1)
	132 daload (4, 1)
	133 dmul (4, 1)
	134 iload (4, 1)
	136 iconst_3 (4, 1)
	137 isub (4, 1)
	138 i2d (4, 1)
	139 aload (4, 1)
	141 iload (4, 1)
	143 iconst_3 (4, 1)
	144 isub (4, 1)
	145 daload (4, 1)
	146 dmul (4, 1)
	147 dsub (4, 1)
	148 dastore (4, 1)
	149 goto (4, 1)
	152 iload (4, 1)
	154 iconst_2 (4, 1)
	155 if_icmpne (4, 1)
	158 aload (4, 1)
	160 iconst_0 (4, 1)
	161 aload (4, 1)
	163 iconst_1 (4, 1)
	164 daload (4, 1)
	165 dastore (4, 1)
	166 iinc (4, 1)
	169 goto (4, 1)
	172 iload (4, 1)
	174 iconst_1 (4, 1)
	175 iand (4, 1)
	176 ifne (4, 1)
	179 dload (4, 1)
	181 dload (4, 1)
	183 dmul (4, 1)
	184 dstore (4, 1)
	186 aload (3, 1)
	188 iload (3, 1)
	190 dload (3, 1)
	192 dastore (3, 1)
	193 iinc (3, 1)
	196 goto (3, 1)
	199 aload_0 (1, 1)
	200 aload_1 (1, 1)
	201 iload_2 (1, 1)
	202 aload (1, 1)
	204 aload_3 (1, 1)
	205 iload (1, 1)
	207 invokevirtual (1, 1)
	210 return (0, 4)

Method: acosh
	0 iconst_1 (0, 0)
	1 aload_0 (0, 0)
	2 getfield (0, 0)
	5 iadd (0, 0)
	6 newarray (0, 0)
	8 astore (0, 0)
	10 aload_1 (0, 0)
	11 iload_2 (0, 0)
	12 daload (0, 0)
	13 dstore (0, 0)
	15 aload (0, 0)
	17 iconst_0 (0, 0)
	18 dload (0, 0)
	20 invokestatic (0, 0)
	23 dastore (0, 0)
	24 aload_0 (1, 1)
	25 getfield (1, 1)
	28 ifle (1, 1)
	31 aload_0 (1, 4)
	32 getfield (1, 4)
	35 newarray (1, 4)
	37 astore (1, 4)
	39 aload (1, 4)
	41 iconst_0 (1, 4)
	42 dconst_1 (1, 4)
	43 dastore (1, 4)
	44 dload (1, 4)
	46 dload (1, 4)
	48 dmul (1, 4)
	49 dstore (1, 4)
	51 dconst_1 (1, 4)
	52 dload (1, 4)
	54 dconst_1 (1, 4)
	55 dsub (1, 4)
	56 ddiv (1, 4)
	57 dstore (1, 4)
	59 dload (1, 4)
	61 invokestatic (1, 4)
	64 dstore (1, 4)
	66 aload (1, 4)
	68 iconst_1 (1, 4)
	69 dload (1, 4)
	71 aload (1, 4)
	73 iconst_0 (1, 4)
	74 daload (1, 4)
	75 dmul (1, 4)
	76 dastore (1, 4)
	77 iconst_2 (2, 4)
	78 istore (2, 4)
	80 iload (2, 4)
	82 aload_0 (2, 4)
	83 getfield (2, 4)
	86 if_icmpgt (2, 4)
	89 dconst_0 (2, 4)
	90 dstore (2, 4)
	92 aload (2, 4)
	94 iload (2, 4)
	96 iconst_1 (2, 4)
	97 isub (2, 4)
	98 iconst_1 (2, 4)
	99 iload (2, 4)
	101 isub (2, 4)
	102 i2d (2, 4)
	103 aload (2, 4)
	105 iload (2, 4)
	107 iconst_2 (2, 4)
	108 isub (2, 4)
	109 daload (2, 4)
	110 dmul (2, 4)
	111 dastore (2, 4)
	112 iload (3, 4)
	114 iconst_1 (3, 4)
	115 isub (3, 4)
	116 istore (3, 4)
	118 iload (3, 4)
	120 iflt (3, 4)
	123 dload (3, 4)
	125 dload (3, 4)
	127 dmul (3, 4)
	128 aload (3, 4)
	130 iload (3, 4)
	132 daload (3, 4)
	133 dadd (3, 4)
	134 dstore (3, 4)
	136 iload (4, 1)
	138 iconst_2 (4, 1)
	139 if_icmple (4, 1)
	142 aload (4, 1)
	144 iload (4, 1)
	146 iconst_2 (4, 1)
	147 isub (4, 1)
	148 iconst_1 (4, 1)
	149 iload (4, 1)
	151 isub (4, 1)
	152 i2d (4, 1)
	153 aload (4, 1)
	155 iload (4, 1)
	157 iconst_1 (4, 1)
	158 isub (4, 1)
	159 daload (4, 1)
	160 dmul (4, 1)
	161 iload (4, 1)
	163 iconst_2 (4, 1)
	164 iload (4, 1)
	166 imul (4, 1)
	167 isub (4, 1)
	168 i2d (4, 1)
	169 aload (4, 1)
	171 iload (4, 1)
	173 iconst_3 (4, 1)
	174 isub (4, 1)
	175 daload (4, 1)
	176 dmul (4, 1)
	177 dadd (4, 1)
	178 dastore (4, 1)
	179 goto (4, 1)
	182 iload (4, 1)
	184 iconst_2 (4, 1)
	185 if_icmpne (4, 1)
	188 aload (4, 1)
	190 iconst_0 (4, 1)
	191 aload (4, 1)
	193 iconst_1 (4, 1)
	194 daload (4, 1)
	195 dneg (4, 1)
	196 dastore (4, 1)
	197 iinc (4, 1)
	200 goto (4, 1)
	203 iload (4, 1)
	205 iconst_1 (4, 1)
	206 iand (4, 1)
	207 ifne (4, 1)
	210 dload (4, 1)
	212 dload (4, 1)
	214 dmul (4, 1)
	215 dstore (4, 1)
	217 dload (3, 1)
	219 dload (3, 1)
	221 dmul (3, 1)
	222 dstore (3, 1)
	224 aload (3, 1)
	226 iload (3, 1)
	228 dload (3, 1)
	230 dload (3, 1)
	232 dmul (3, 1)
	233 dastore (3, 1)
	234 iinc (3, 1)
	237 goto (3, 1)
	240 aload_0 (1, 1)
	241 aload_1 (1, 1)
	242 iload_2 (1, 1)
	243 aload (1, 1)
	245 aload_3 (1, 1)
	246 iload (1, 1)
	248 invokevirtual (1, 1)
	251 return (0, 4)

Method: asinh
	0 iconst_1 (0, 0)
	1 aload_0 (0, 0)
	2 getfield (0, 0)
	5 iadd (0, 0)
	6 newarray (0, 0)
	8 astore (0, 0)
	10 aload_1 (0, 0)
	11 iload_2 (0, 0)
	12 daload (0, 0)
	13 dstore (0, 0)
	15 aload (0, 0)
	17 iconst_0 (0, 0)
	18 dload (0, 0)
	20 invokestatic (0, 0)
	23 dastore (0, 0)
	24 aload_0 (1, 1)
	25 getfield (1, 1)
	28 ifle (1, 1)
	31 aload_0 (1, 4)
	32 getfield (1, 4)
	35 newarray (1, 4)
	37 astore (1, 4)
	39 aload (1, 4)
	41 iconst_0 (1, 4)
	42 dconst_1 (1, 4)
	43 dastore (1, 4)
	44 dload (1, 4)
	46 dload (1, 4)
	48 dmul (1, 4)
	49 dstore (1, 4)
	51 dconst_1 (1, 4)
	52 dconst_1 (1, 4)
	53 dload (1, 4)
	55 dadd (1, 4)
	56 ddiv (1, 4)
	57 dstore (1, 4)
	59 dload (1, 4)
	61 invokestatic (1, 4)
	64 dstore (1, 4)
	66 aload (1, 4)
	68 iconst_1 (1, 4)
	69 dload (1, 4)
	71 aload (1, 4)
	73 iconst_0 (1, 4)
	74 daload (1, 4)
	75 dmul (1, 4)
	76 dastore (1, 4)
	77 iconst_2 (2, 4)
	78 istore (2, 4)
	80 iload (2, 4)
	82 aload_0 (2, 4)
	83 getfield (2, 4)
	86 if_icmpgt (2, 4)
	89 dconst_0 (2, 4)
	90 dstore (2, 4)
	92 aload (2, 4)
	94 iload (2, 4)
	96 iconst_1 (2, 4)
	97 isub (2, 4)
	98 iconst_1 (2, 4)
	99 iload (2, 4)
	101 isub (2, 4)
	102 i2d (2, 4)
	103 aload (2, 4)
	105 iload (2, 4)
	107 iconst_2 (2, 4)
	108 isub (2, 4)
	109 daload (2, 4)
	110 dmul (2, 4)
	111 dastore (2, 4)
	112 iload (3, 4)
	114 iconst_1 (3, 4)
	115 isub (3, 4)
	116 istore (3, 4)
	118 iload (3, 4)
	120 iflt (3, 4)
	123 dload (3, 4)
	125 dload (3, 4)
	127 dmul (3, 4)
	128 aload (3, 4)
	130 iload (3, 4)
	132 daload (3, 4)
	133 dadd (3, 4)
	134 dstore (3, 4)
	136 iload (4, 1)
	138 iconst_2 (4, 1)
	139 if_icmple (4, 1)
	142 aload (4, 1)
	144 iload (4, 1)
	146 iconst_2 (4, 1)
	147 isub (4, 1)
	148 iload (4, 1)
	150 iconst_1 (4, 1)
	151 isub (4, 1)
	152 i2d (4, 1)
	153 aload (4, 1)
	155 iload (4, 1)
	157 iconst_1 (4, 1)
	158 isub (4, 1)
	159 daload (4, 1)
	160 dmul (4, 1)
	161 iload (4, 1)
	163 iconst_2 (4, 1)
	164 iload (4, 1)
	166 imul (4, 1)
	167 isub (4, 1)
	168 i2d (4, 1)
	169 aload (4, 1)
	171 iload (4, 1)
	173 iconst_3 (4, 1)
	174 isub (4, 1)
	175 daload (4, 1)
	176 dmul (4, 1)
	177 dadd (4, 1)
	178 dastore (4, 1)
	179 goto (4, 1)
	182 iload (4, 1)
	184 iconst_2 (4, 1)
	185 if_icmpne (4, 1)
	188 aload (4, 1)
	190 iconst_0 (4, 1)
	191 aload (4, 1)
	193 iconst_1 (4, 1)
	194 daload (4, 1)
	195 dastore (4, 1)
	196 iinc (4, 1)
	199 goto (4, 1)
	202 iload (4, 1)
	204 iconst_1 (4, 1)
	205 iand (4, 1)
	206 ifne (4, 1)
	209 dload (4, 1)
	211 dload (4, 1)
	213 dmul (4, 1)
	214 dstore (4, 1)
	216 dload (3, 1)
	218 dload (3, 1)
	220 dmul (3, 1)
	221 dstore (3, 1)
	223 aload (3, 1)
	225 iload (3, 1)
	227 dload (3, 1)
	229 dload (3, 1)
	231 dmul (3, 1)
	232 dastore (3, 1)
	233 iinc (3, 1)
	236 goto (3, 1)
	239 aload_0 (1, 1)
	240 aload_1 (1, 1)
	241 iload_2 (1, 1)
	242 aload (1, 1)
	244 aload_3 (1, 1)
	245 iload (1, 1)
	247 invokevirtual (1, 1)
	250 return (0, 4)

Method: atanh
	0 iconst_1 (0, 0)
	1 aload_0 (0, 0)
	2 getfield (0, 0)
	5 iadd (0, 0)
	6 newarray (0, 0)
	8 astore (0, 0)
	10 aload_1 (0, 0)
	11 iload_2 (0, 0)
	12 daload (0, 0)
	13 dstore (0, 0)
	15 aload (0, 0)
	17 iconst_0 (0, 0)
	18 dload (0, 0)
	20 invokestatic (0, 0)
	23 dastore (0, 0)
	24 aload_0 (1, 1)
	25 getfield (1, 1)
	28 ifle (1, 1)
	31 aload_0 (1, 4)
	32 getfield (1, 4)
	35 newarray (1, 4)
	37 astore (1, 4)
	39 aload (1, 4)
	41 iconst_0 (1, 4)
	42 dconst_1 (1, 4)
	43 dastore (1, 4)
	44 dload (1, 4)
	46 dload (1, 4)
	48 dmul (1, 4)
	49 dstore (1, 4)
	51 dconst_1 (1, 4)
	52 dconst_1 (1, 4)
	53 dload (1, 4)
	55 dsub (1, 4)
	56 ddiv (1, 4)
	57 dstore (1, 4)
	59 dload (1, 4)
	61 dstore (1, 4)
	63 aload (1, 4)
	65 iconst_1 (1, 4)
	66 dload (1, 4)
	68 aload (1, 4)
	70 iconst_0 (1, 4)
	71 daload (1, 4)
	72 dmul (1, 4)
	73 dastore (1, 4)
	74 iconst_2 (2, 4)
	75 istore (2, 4)
	77 iload (2, 4)
	79 aload_0 (2, 4)
	80 getfield (2, 4)
	83 if_icmpgt (2, 4)
	86 dconst_0 (2, 4)
	87 dstore (2, 4)
	89 aload (2, 4)
	91 iload (2, 4)
	93 iconst_1 (2, 4)
	94 isub (2, 4)
	95 iload (2, 4)
	97 i2d (2, 4)
	98 aload (2, 4)
	100 iload (2, 4)
	102 iconst_2 (2, 4)
	103 isub (2, 4)
	104 daload (2, 4)
	105 dmul (2, 4)
	106 dastore (2, 4)
	107 iload (3, 4)
	109 iconst_1 (3, 4)
	110 isub (3, 4)
	111 istore (3, 4)
	113 iload (3, 4)
	115 iflt (3, 4)
	118 dload (3, 4)
	120 dload (3, 4)
	122 dmul (3, 4)
	123 aload (3, 4)
	125 iload (3, 4)
	127 daload (3, 4)
	128 dadd (3, 4)
	129 dstore (3, 4)
	131 iload (4, 1)
	133 iconst_2 (4, 1)
	134 if_icmple (4, 1)
	137 aload (4, 1)
	139 iload (4, 1)
	141 iconst_2 (4, 1)
	142 isub (4, 1)
	143 iload (4, 1)
	145 iconst_1 (4, 1)
	146 isub (4, 1)
	147 i2d (4, 1)
	148 aload (4, 1)
	150 iload (4, 1)
	152 iconst_1 (4, 1)
	153 isub (4, 1)
	154 daload (4, 1)
	155 dmul (4, 1)
	156 iconst_2 (4, 1)
	157 iload (4, 1)
	159 imul (4, 1)
	160 iload (4, 1)
	162 isub (4, 1)
	163 iconst_1 (4, 1)
	164 iadd (4, 1)
	165 i2d (4, 1)
	166 aload (4, 1)
	168 iload (4, 1)
	170 iconst_3 (4, 1)
	171 isub (4, 1)
	172 daload (4, 1)
	173 dmul (4, 1)
	174 dadd (4, 1)
	175 dastore (4, 1)
	176 goto (4, 1)
	179 iload (4, 1)
	181 iconst_2 (4, 1)
	182 if_icmpne (4, 1)
	185 aload (4, 1)
	187 iconst_0 (4, 1)
	188 aload (4, 1)
	190 iconst_1 (4, 1)
	191 daload (4, 1)
	192 dastore (4, 1)
	193 iinc (4, 1)
	196 goto (4, 1)
	199 iload (4, 1)
	201 iconst_1 (4, 1)
	202 iand (4, 1)
	203 ifne (4, 1)
	206 dload (4, 1)
	208 dload (4, 1)
	210 dmul (4, 1)
	211 dstore (4, 1)
	213 dload (3, 1)
	215 dload (3, 1)
	217 dmul (3, 1)
	218 dstore (3, 1)
	220 aload (3, 1)
	222 iload (3, 1)
	224 dload (3, 1)
	226 dload (3, 1)
	228 dmul (3, 1)
	229 dastore (3, 1)
	230 iinc (3, 1)
	233 goto (3, 1)
	236 aload_0 (1, 1)
	237 aload_1 (1, 1)
	238 iload_2 (1, 1)
	239 aload (1, 1)
	241 aload_3 (1, 1)
	242 iload (1, 1)
	244 invokevirtual (1, 1)
	247 return (0, 4)

Method: compose
	0 iconst_0 (1, 4)
	1 istore (1, 4)
	3 iload (1, 4)
	5 aload_0 (1, 4)
	6 getfield (1, 4)
	9 arraylength (1, 4)
	10 if_icmpge (1, 4)
	13 aload_0 (1, 4)
	14 getfield (1, 4)
	17 iload (1, 4)
	19 aaload (1, 4)
	20 astore (1, 4)
	22 dconst_0 (1, 4)
	23 dstore (1, 4)
	25 iconst_0 (2, 4)
	26 istore (2, 4)
	28 iload (2, 4)
	30 aload (2, 4)
	32 arraylength (2, 4)
	33 if_icmpge (2, 4)
	36 aload (2, 4)
	38 iload (2, 4)
	40 aaload (2, 4)
	41 astore (2, 4)
	43 aload (2, 4)
	45 iconst_0 (2, 4)
	46 iaload (2, 4)
	47 i2d (2, 4)
	48 aload_3 (2, 4)
	49 aload (2, 4)
	51 iconst_1 (2, 4)
	52 iaload (2, 4)
	53 daload (2, 4)
	54 dmul (2, 4)
	55 dstore (2, 4)
	57 iconst_2 (3, 4)
	58 istore (3, 4)
	60 iload (3, 4)
	62 aload (3, 4)
	64 arraylength (3, 4)
	65 if_icmpge (3, 4)
	68 dload (3, 4)
	70 aload_1 (3, 4)
	71 iload_2 (3, 4)
	72 aload (3, 4)
	74 iload (3, 4)
	76 iaload (3, 4)
	77 iadd (3, 4)
	78 daload (3, 4)
	79 dmul (3, 4)
	80 dstore (3, 4)
	82 iinc (3, 4)
	85 goto (3, 4)
	88 dload (2, 4)
	90 dload (2, 4)
	92 dadd (2, 4)
	93 dstore (2, 4)
	95 iinc (2, 4)
	98 goto (2, 4)
	101 aload (1, 4)
	103 iload (1, 4)
	105 iload (1, 4)
	107 iadd (1, 4)
	108 dload (1, 4)
	110 dastore (1, 4)
	111 iinc (1, 4)
	114 goto (1, 4)
	117 return (0, 0)

Method: taylor
	0 dconst_0 (0, 0)
	1 dstore (0, 0)
	3 aload_0 (1, 4)
	4 invokevirtual (1, 4)
	7 iconst_1 (1, 4)
	8 isub (1, 4)
	9 istore (1, 4)
	11 iload (1, 4)
	13 iflt (1, 4)
	16 aload_0 (1, 4)
	17 iload (1, 4)
	19 invokevirtual (1, 4)
	22 astore (1, 4)
	24 aload_1 (1, 4)
	25 iload_2 (1, 4)
	26 iload (1, 4)
	28 iadd (1, 4)
	29 daload (1, 4)
	30 dstore (1, 4)
	32 iconst_0 (2, 4)
	33 istore (2, 4)
	35 iload (2, 4)
	37 aload (2, 4)
	39 arraylength (2, 4)
	40 if_icmpge (2, 4)
	43 aload (3, 1)
	45 iload (3, 1)
	47 iaload (3, 1)
	48 ifle (3, 1)
	51 dload (4, 1)
	53 aload_3 (4, 1)
	54 iload (4, 1)
	56 daload (4, 1)
	57 aload (4, 1)
	59 iload (4, 1)
	61 iaload (4, 1)
	62 invokestatic (4, 1)
	65 aload (4, 1)
	67 iload (4, 1)
	69 iaload (4, 1)
	70 invokestatic (4, 1)
	73 l2d (4, 1)
	74 ddiv (4, 1)
	75 dmul (4, 1)
	76 dstore (4, 1)
	78 goto (3, 4)
	81 astore (3, 4)
	83 new (3, 4)
	86 dup (3, 4)
	87 aload (3, 4)
	89 invokespecial (3, 4)
	92 athrow (3, 4)
	93 iinc (3, 4)
	96 goto (3, 4)
	99 dload (2, 0)
	101 dload (2, 0)
	103 dadd (2, 0)
	104 dstore (2, 0)
	106 iinc (2, 0)
	109 goto (2, 0)
	112 dload (3, 0)
	114 dreturn (3, 0)

Method: checkCompatibility
	0 aload_0 (1, 1)
	1 getfield (1, 1)
	4 aload_1 (1, 1)
	5 getfield (1, 1)
	8 if_icmpeq (1, 1)
	11 new (1, 1)
	14 dup (1, 1)
	15 aload_0 (1, 1)
	16 getfield (1, 1)
	19 aload_1 (1, 1)
	20 getfield (1, 1)
	23 invokespecial (1, 1)
	26 athrow (1, 1)
	27 aload_0 (1, 1)
	28 getfield (1, 1)
	31 aload_1 (1, 1)
	32 getfield (1, 1)
	35 if_icmpeq (1, 1)
	38 new (1, 1)
	41 dup (1, 1)
	42 aload_0 (1, 1)
	43 getfield (1, 1)
	46 aload_1 (1, 1)
	47 getfield (1, 1)
	50 invokespecial (1, 1)
	53 athrow (1, 1)
	54 return (0, 0)

Method: <clinit>
	0 new (0, 0)
	3 dup (0, 0)
	4 aconst_null (0, 0)
	5 invokespecial (0, 0)
	8 putstatic (0, 0)
	11 return (0, 0)

