Method: value
	0 aload_1 (1, 1)
	1 invokevirtual (1, 1)
	2 org/apache/commons/math3/analysis/differentiation/DerivativeStructure.getOrder:()I (1, 1)
	4 aload_0 (1, 1)
	5 getfield (1, 1)
	6 org/apache/commons/math3/analysis/differentiation/FiniteDifferencesDifferentiator$3.this$0:Lorg/apache/commons/math3/analysis/differentiation/FiniteDifferencesDifferentiator; (1, 1)
	8 invokestatic (1, 1)
	9 org/apache/commons/math3/analysis/differentiation/FiniteDifferencesDifferentiator.access$000:(Lorg/apache/commons/math3/analysis/differentiation/FiniteDifferencesDifferentiator;)I (1, 1)
	11 if_icmplt (1, 1)
	12 29 (1, 1)
	14 new (1, 1)
	15 org/apache/commons/math3/exception/NumberIsTooLargeException (1, 1)
	17 dup (1, 1)
	18 aload_1 (1, 1)
	19 invokevirtual (1, 1)
	20 org/apache/commons/math3/analysis/differentiation/DerivativeStructure.getOrder:()I (1, 1)
	22 invokestatic (1, 1)
	23 java/lang/Integer.valueOf:(I)Ljava/lang/Integer; (1, 1)
	25 aload_0 (1, 1)
	26 getfield (1, 1)
	27 org/apache/commons/math3/analysis/differentiation/FiniteDifferencesDifferentiator$3.this$0:Lorg/apache/commons/math3/analysis/differentiation/FiniteDifferencesDifferentiator; (1, 1)
	29 invokestatic (1, 1)
	30 org/apache/commons/math3/analysis/differentiation/FiniteDifferencesDifferentiator.access$000:(Lorg/apache/commons/math3/analysis/differentiation/FiniteDifferencesDifferentiator;)I (1, 1)
	32 invokestatic (1, 1)
	33 java/lang/Integer.valueOf:(I)Ljava/lang/Integer; (1, 1)
	35 iconst_0 (1, 1)
	36 invokespecial (1, 1)
	37 org/apache/commons/math3/exception/NumberIsTooLargeException.<init>:(Ljava/lang/Number;Ljava/lang/Number;Z)V (1, 1)
	39 athrow (1, 1)
	40 aload_1 (1, 1)
	41 invokevirtual (1, 1)
	42 org/apache/commons/math3/analysis/differentiation/DerivativeStructure.getValue:()D (1, 1)
	44 aload_0 (1, 1)
	45 getfield (1, 1)
	46 org/apache/commons/math3/analysis/differentiation/FiniteDifferencesDifferentiator$3.this$0:Lorg/apache/commons/math3/analysis/differentiation/FiniteDifferencesDifferentiator; (1, 1)
	48 invokestatic (1, 1)
	49 org/apache/commons/math3/analysis/differentiation/FiniteDifferencesDifferentiator.access$100:(Lorg/apache/commons/math3/analysis/differentiation/FiniteDifferencesDifferentiator;)D (1, 1)
	51 invokestatic (1, 1)
	52 org/apache/commons/math3/util/FastMath.min:(DD)D (1, 1)
	54 aload_0 (1, 1)
	55 getfield (1, 1)
	56 org/apache/commons/math3/analysis/differentiation/FiniteDifferencesDifferentiator$3.this$0:Lorg/apache/commons/math3/analysis/differentiation/FiniteDifferencesDifferentiator; (1, 1)
	58 invokestatic (1, 1)
	59 org/apache/commons/math3/analysis/differentiation/FiniteDifferencesDifferentiator.access$200:(Lorg/apache/commons/math3/analysis/differentiation/FiniteDifferencesDifferentiator;)D (1, 1)
	61 invokestatic (1, 1)
	62 org/apache/commons/math3/util/FastMath.max:(DD)D (1, 1)
	64 aload_0 (1, 1)
	65 getfield (1, 1)
	66 org/apache/commons/math3/analysis/differentiation/FiniteDifferencesDifferentiator$3.this$0:Lorg/apache/commons/math3/analysis/differentiation/FiniteDifferencesDifferentiator; (1, 1)
	68 invokestatic (1, 1)
	69 org/apache/commons/math3/analysis/differentiation/FiniteDifferencesDifferentiator.access$300:(Lorg/apache/commons/math3/analysis/differentiation/FiniteDifferencesDifferentiator;)D (1, 1)
	71 dsub (1, 1)
	72 dstore_2 (1, 1)
	73 aconst_null (1, 1)
	74 checkcast (1, 1)
	75 [[[D (1, 1)
	77 astore (1, 1)
	78 #4 (1, 1)
	79 iconst_0 (2, 4)
	80 istore (2, 4)
	81 #5 (2, 4)
	82 iload (2, 4)
	83 #5 (2, 4)
	84 aload_0 (2, 4)
	85 getfield (2, 4)
	86 org/apache/commons/math3/analysis/differentiation/FiniteDifferencesDifferentiator$3.this$0:Lorg/apache/commons/math3/analysis/differentiation/FiniteDifferencesDifferentiator; (2, 4)
	88 invokestatic (2, 4)
	89 org/apache/commons/math3/analysis/differentiation/FiniteDifferencesDifferentiator.access$000:(Lorg/apache/commons/math3/analysis/differentiation/FiniteDifferencesDifferentiator;)I (2, 4)
	91 if_icmpge (2, 4)
	92 115 (2, 4)
	94 aload_0 (2, 4)
	95 getfield (2, 4)
	96 org/apache/commons/math3/analysis/differentiation/FiniteDifferencesDifferentiator$3.val$function:Lorg/apache/commons/math3/analysis/UnivariateMatrixFunction; (2, 4)
	98 dload_2 (2, 4)
	99 iload (2, 4)
	100 #5 (2, 4)
	101 i2d (2, 4)
	102 aload_0 (2, 4)
	103 getfield (2, 4)
	104 org/apache/commons/math3/analysis/differentiation/FiniteDifferencesDifferentiator$3.this$0:Lorg/apache/commons/math3/analysis/differentiation/FiniteDifferencesDifferentiator; (2, 4)
	106 invokestatic (2, 4)
	107 org/apache/commons/math3/analysis/differentiation/FiniteDifferencesDifferentiator.access$400:(Lorg/apache/commons/math3/analysis/differentiation/FiniteDifferencesDifferentiator;)D (2, 4)
	109 dmul (2, 4)
	110 dadd (2, 4)
	111 invokeinterface (2, 4)
	112 org/apache/commons/math3/analysis/UnivariateMatrixFunction.org/apache/commons/math3/analysis/differentiation/DerivativeStructure (2, 4)
	114 0 (2, 4)
	116 astore (2, 4)
	117 #6 (2, 4)
	118 iload (3, 1)
	119 #5 (3, 1)
	120 ifne (3, 1)
	121 24 (3, 1)
	123 aload (3, 1)
	124 #6 (3, 1)
	125 arraylength (3, 1)
	126 aload (3, 1)
	127 #6 (3, 1)
	128 iconst_0 (3, 1)
	129 aaload (3, 1)
	130 arraylength (3, 1)
	131 aload_0 (3, 1)
	132 getfield (3, 1)
	133 org/apache/commons/math3/analysis/differentiation/FiniteDifferencesDifferentiator$3.this$0:Lorg/apache/commons/math3/analysis/differentiation/FiniteDifferencesDifferentiator; (3, 1)
	135 invokestatic (3, 1)
	136 org/apache/commons/math3/analysis/differentiation/FiniteDifferencesDifferentiator.access$000:(Lorg/apache/commons/math3/analysis/differentiation/FiniteDifferencesDifferentiator;)I (3, 1)
	138 multianewarray (3, 1)
	139 [[[D (3, 1)
	141 58 (3, 1)
	142 astore (3, 1)
	143 #4 (3, 1)
	144 iconst_0 (3, 4)
	145 istore (3, 4)
	146 #7 (3, 4)
	147 iload (3, 4)
	148 #7 (3, 4)
	149 aload (3, 4)
	150 #6 (3, 4)
	151 arraylength (3, 4)
	152 if_icmpge (3, 4)
	153 48 (3, 4)
	155 iconst_0 (4, 4)
	156 istore (4, 4)
	157 #8 (4, 4)
	158 iload (4, 4)
	159 #8 (4, 4)
	160 aload (4, 4)
	161 #6 (4, 4)
	162 iload (4, 4)
	163 #7 (4, 4)
	164 aaload (4, 4)
	165 arraylength (4, 4)
	166 if_icmpge (4, 4)
	167 28 (4, 4)
	169 aload (4, 4)
	170 #4 (4, 4)
	171 iload (4, 4)
	172 #7 (4, 4)
	173 aaload (4, 4)
	174 iload (4, 4)
	175 #8 (4, 4)
	176 aaload (4, 4)
	177 iload (4, 4)
	178 #5 (4, 4)
	179 aload (4, 4)
	180 #6 (4, 4)
	181 iload (4, 4)
	182 #7 (4, 4)
	183 aaload (4, 4)
	184 iload (4, 4)
	185 #8 (4, 4)
	186 daload (4, 4)
	187 dastore (4, 4)
	188 iinc (4, 4)
	189 #8 (4, 4)
	190 -89 (4, 4)
	191 goto (4, 4)
	192 -33 (4, 4)
	194 iinc (4, 4)
	195 #7 (4, 4)
	196 -89 (4, 4)
	197 goto (4, 4)
	198 -50 (4, 4)
	200 iinc (4, 4)
	201 #5 (4, 4)
	202 -89 (4, 4)
	203 goto (4, 4)
	204 -121 (4, 4)
	206 aload (3, 4)
	207 #4 (3, 4)
	208 arraylength (3, 4)
	209 aload (3, 4)
	210 #4 (3, 4)
	211 iconst_0 (3, 4)
	212 aaload (3, 4)
	213 arraylength (3, 4)
	214 multianewarray (3, 4)
	215 [[Lorg/apache/commons/math3/analysis/differentiation/DerivativeStructure; (3, 4)
	217 58 (3, 4)
	218 astore (3, 4)
	219 #5 (3, 4)
	220 iconst_0 (4, 4)
	221 istore (4, 4)
	222 #6 (4, 4)
	223 iload (4, 4)
	224 #6 (4, 4)
	225 aload (4, 4)
	226 #5 (4, 4)
	227 arraylength (4, 4)
	228 if_icmpge (4, 4)
	229 54 (4, 4)
	231 iconst_0 (5, 4)
	232 istore (5, 4)
	233 #7 (5, 4)
	234 iload (5, 4)
	235 #7 (5, 4)
	236 aload (5, 4)
	237 #4 (5, 4)
	238 iload (5, 4)
	239 #6 (5, 4)
	240 aaload (5, 4)
	241 arraylength (5, 4)
	242 if_icmpge (5, 4)
	243 34 (5, 4)
	245 aload (5, 4)
	246 #5 (5, 4)
	247 iload (5, 4)
	248 #6 (5, 4)
	249 aaload (5, 4)
	250 iload (5, 4)
	251 #7 (5, 4)
	252 aload_0 (5, 4)
	253 getfield (5, 4)
	254 org/apache/commons/math3/analysis/differentiation/FiniteDifferencesDifferentiator$3.this$0:Lorg/apache/commons/math3/analysis/differentiation/FiniteDifferencesDifferentiator; (5, 4)
	256 aload_1 (5, 4)
	257 dload_2 (5, 4)
	258 aload (5, 4)
	259 #4 (5, 4)
	260 iload (5, 4)
	261 #6 (5, 4)
	262 aaload (5, 4)
	263 iload (5, 4)
	264 #7 (5, 4)
	265 aaload (5, 4)
	266 invokestatic (5, 4)
	267 org/apache/commons/math3/analysis/differentiation/FiniteDifferencesDifferentiator.access$500:(Lorg/apache/commons/math3/analysis/differentiation/FiniteDifferencesDifferentiator;Lorg/apache/commons/math3/analysis/differentiation/DerivativeStructure;D[D)Lorg/apache/commons/math3/analysis/differentiation/DerivativeStructure; (5, 4)
	269 aastore (5, 4)
	270 iinc (5, 4)
	271 #7 (5, 4)
	272 -89 (5, 4)
	273 goto (5, 4)
	274 -39 (5, 4)
	276 iinc (5, 4)
	277 #6 (5, 4)
	278 -89 (5, 4)
	279 goto (5, 4)
	280 -56 (5, 4)
	282 aload (4, 4)
	283 #5 (4, 4)
	284 areturn (3, 4)

