Method: <init>
	0 aload_0 (0, 0)
	1 invokespecial (0, 0)
	2 java/lang/Object.<init>:()V (0, 0)
	4 iload_1 (2, 1)
	5 iconst_1 (2, 1)
	6 if_icmpgt (2, 1)
	7 20 (2, 1)
	9 new (2, 1)
	10 org/apache/commons/math3/exception/NumberIsTooSmallException (2, 1)
	12 dup (2, 1)
	13 dload_2 (2, 1)
	14 invokestatic (2, 1)
	15 java/lang/Double.valueOf:(D)Ljava/lang/Double; (2, 1)
	17 iconst_1 (2, 1)
	18 invokestatic (2, 1)
	19 java/lang/Integer.valueOf:(I)Ljava/lang/Integer; (2, 1)
	21 iconst_0 (2, 1)
	22 invokespecial (2, 1)
	23 org/apache/commons/math3/exception/NumberIsTooSmallException.<init>:(Ljava/lang/Number;Ljava/lang/Number;Z)V (2, 1)
	25 athrow (2, 1)
	26 aload_0 (0, 0)
	27 iload_1 (0, 0)
	28 putfield (0, 0)
	29 org/apache/commons/math3/analysis/differentiation/FiniteDifferencesDifferentiator.nbPoints:I (0, 0)
	31 dload_2 (2, 1)
	32 dconst_0 (2, 1)
	33 dcmpg (2, 1)
	34 ifgt (2, 1)
	35 15 (2, 1)
	37 new (2, 1)
	38 org/apache/commons/math3/exception/NotPositiveException (2, 1)
	40 dup (2, 1)
	41 dload_2 (2, 1)
	42 invokestatic (2, 1)
	43 java/lang/Double.valueOf:(D)Ljava/lang/Double; (2, 1)
	45 invokespecial (2, 1)
	46 org/apache/commons/math3/exception/NotPositiveException.<init>:(Ljava/lang/Number;)V (2, 1)
	48 athrow (2, 1)
	49 aload_0 (0, 0)
	50 dload_2 (0, 0)
	51 putfield (0, 0)
	52 org/apache/commons/math3/analysis/differentiation/FiniteDifferencesDifferentiator.stepSize:D (0, 0)
	54 aload_0 (0, 0)
	55 ldc2_w (0, 0)
	56 0.5 (0, 0)
	58 dload_2 (0, 0)
	59 dmul (0, 0)
	60 iload_1 (0, 0)
	61 iconst_1 (0, 0)
	62 isub (0, 0)
	63 i2d (0, 0)
	64 dmul (0, 0)
	65 putfield (0, 0)
	66 org/apache/commons/math3/analysis/differentiation/FiniteDifferencesDifferentiator.halfSampleSpan:D (0, 0)
	68 ldc2_w (2, 1)
	69 2.0 (2, 1)
	71 aload_0 (2, 1)
	72 getfield (2, 1)
	73 org/apache/commons/math3/analysis/differentiation/FiniteDifferencesDifferentiator.halfSampleSpan:D (2, 1)
	75 dmul (2, 1)
	76 dload (2, 1)
	77 #6 (2, 1)
	78 dload (2, 1)
	79 #4 (2, 1)
	80 dsub (2, 1)
	81 dcmpl (2, 1)
	82 iflt (2, 1)
	83 31 (2, 1)
	85 new (2, 1)
	86 org/apache/commons/math3/exception/NumberIsTooLargeException (2, 1)
	88 dup (2, 1)
	89 ldc2_w (2, 1)
	90 2.0 (2, 1)
	92 aload_0 (2, 1)
	93 getfield (2, 1)
	94 org/apache/commons/math3/analysis/differentiation/FiniteDifferencesDifferentiator.halfSampleSpan:D (2, 1)
	96 dmul (2, 1)
	97 invokestatic (2, 1)
	98 java/lang/Double.valueOf:(D)Ljava/lang/Double; (2, 1)
	100 dload (2, 1)
	101 #6 (2, 1)
	102 dload (2, 1)
	103 #4 (2, 1)
	104 dsub (2, 1)
	105 invokestatic (2, 1)
	106 java/lang/Double.valueOf:(D)Ljava/lang/Double; (2, 1)
	108 iconst_0 (2, 1)
	109 invokespecial (2, 1)
	110 org/apache/commons/math3/exception/NumberIsTooLargeException.<init>:(Ljava/lang/Number;Ljava/lang/Number;Z)V (2, 1)
	112 athrow (2, 1)
	113 aload_0 (0, 0)
	114 getfield (0, 0)
	115 org/apache/commons/math3/analysis/differentiation/FiniteDifferencesDifferentiator.halfSampleSpan:D (0, 0)
	117 invokestatic (0, 0)
	118 org/apache/commons/math3/util/FastMath.ulp:(D)D (0, 0)
	120 dstore (0, 0)
	121 #8 (0, 0)
	122 aload_0 (0, 0)
	123 dload (0, 0)
	124 #4 (0, 0)
	125 aload_0 (0, 0)
	126 getfield (0, 0)
	127 org/apache/commons/math3/analysis/differentiation/FiniteDifferencesDifferentiator.halfSampleSpan:D (0, 0)
	129 dadd (0, 0)
	130 dload (0, 0)
	131 #8 (0, 0)
	132 dadd (0, 0)
	133 putfield (0, 0)
	134 org/apache/commons/math3/analysis/differentiation/FiniteDifferencesDifferentiator.tMin:D (0, 0)
	136 aload_0 (0, 0)
	137 dload (0, 0)
	138 #6 (0, 0)
	139 aload_0 (0, 0)
	140 getfield (0, 0)
	141 org/apache/commons/math3/analysis/differentiation/FiniteDifferencesDifferentiator.halfSampleSpan:D (0, 0)
	143 dsub (0, 0)
	144 dload (0, 0)
	145 #8 (0, 0)
	146 dsub (0, 0)
	147 putfield (0, 0)
	148 org/apache/commons/math3/analysis/differentiation/FiniteDifferencesDifferentiator.tMax:D (0, 0)
	150 return (0, 0)

Method: getNbPoints
	0 aload_0 (0, 0)
	1 getfield (0, 0)
	2 org/apache/commons/math3/analysis/differentiation/FiniteDifferencesDifferentiator.nbPoints:I (0, 0)
	4 ireturn (0, 0)

Method: getStepSize
	0 aload_0 (0, 0)
	1 getfield (0, 0)
	2 org/apache/commons/math3/analysis/differentiation/FiniteDifferencesDifferentiator.stepSize:D (0, 0)
	4 dreturn (0, 0)

Method: evaluate
	0 aload_0 (0, 0)
	1 getfield (0, 0)
	2 org/apache/commons/math3/analysis/differentiation/FiniteDifferencesDifferentiator.nbPoints:I (0, 0)
	4 newarray (0, 0)
	5 7 (0, 0)
	6 astore (0, 0)
	7 #5 (0, 0)
	8 aload_0 (0, 0)
	9 getfield (0, 0)
	10 org/apache/commons/math3/analysis/differentiation/FiniteDifferencesDifferentiator.nbPoints:I (0, 0)
	12 newarray (0, 0)
	13 7 (0, 0)
	14 astore (0, 0)
	15 #6 (0, 0)
	16 iconst_0 (1, 4)
	17 istore (1, 4)
	18 #7 (1, 4)
	19 iload (1, 4)
	20 #7 (1, 4)
	21 aload_0 (1, 4)
	22 getfield (1, 4)
	23 org/apache/commons/math3/analysis/differentiation/FiniteDifferencesDifferentiator.nbPoints:I (1, 4)
	25 if_icmpge (1, 4)
	26 80 (1, 4)
	28 aload (1, 1)
	29 #6 (1, 1)
	30 iload (1, 1)
	31 #7 (1, 1)
	32 aload (1, 1)
	33 #4 (1, 1)
	34 iload (1, 1)
	35 #7 (1, 1)
	36 daload (1, 1)
	37 dastore (1, 1)
	38 iconst_1 (2, 4)
	39 istore (2, 4)
	40 #8 (2, 4)
	41 iload (2, 4)
	42 #8 (2, 4)
	43 iload (2, 4)
	44 #7 (2, 4)
	45 if_icmpgt (2, 4)
	46 45 (2, 4)
	48 aload (2, 4)
	49 #6 (2, 4)
	50 iload (2, 4)
	51 #7 (2, 4)
	52 iload (2, 4)
	53 #8 (2, 4)
	54 isub (2, 4)
	55 aload (2, 4)
	56 #6 (2, 4)
	57 iload (2, 4)
	58 #7 (2, 4)
	59 iload (2, 4)
	60 #8 (2, 4)
	61 isub (2, 4)
	62 iconst_1 (2, 4)
	63 iadd (2, 4)
	64 daload (2, 4)
	65 aload (2, 4)
	66 #6 (2, 4)
	67 iload (2, 4)
	68 #7 (2, 4)
	69 iload (2, 4)
	70 #8 (2, 4)
	71 isub (2, 4)
	72 daload (2, 4)
	73 dsub (2, 4)
	74 iload (2, 4)
	75 #8 (2, 4)
	76 i2d (2, 4)
	77 aload_0 (2, 4)
	78 getfield (2, 4)
	79 org/apache/commons/math3/analysis/differentiation/FiniteDifferencesDifferentiator.stepSize:D (2, 4)
	81 dmul (2, 4)
	82 ddiv (2, 4)
	83 dastore (2, 4)
	84 iinc (2, 4)
	85 #8 (2, 4)
	86 -89 (2, 4)
	87 goto (2, 4)
	88 -46 (2, 4)
	90 aload (1, 1)
	91 #5 (1, 1)
	92 iload (1, 1)
	93 #7 (1, 1)
	94 aload (1, 1)
	95 #6 (1, 1)
	96 iconst_0 (1, 1)
	97 daload (1, 1)
	98 dastore (1, 1)
	99 iinc (1, 1)
	100 #7 (1, 1)
	101 -89 (1, 1)
	102 goto (1, 1)
	103 -83 (1, 1)
	105 aload_1 (0, 0)
	106 invokevirtual (0, 0)
	107 org/apache/commons/math3/analysis/differentiation/DerivativeStructure.getOrder:()I (0, 0)
	109 istore (0, 0)
	110 #7 (0, 0)
	111 aload_1 (0, 0)
	112 invokevirtual (0, 0)
	113 org/apache/commons/math3/analysis/differentiation/DerivativeStructure.getFreeParameters:()I (0, 0)
	115 istore (0, 0)
	116 #8 (0, 0)
	117 aload_1 (0, 0)
	118 invokevirtual (0, 0)
	119 org/apache/commons/math3/analysis/differentiation/DerivativeStructure.getAllDerivatives:()[D (0, 0)
	121 astore (0, 0)
	122 #9 (0, 0)
	123 aload_1 (0, 0)
	124 invokevirtual (0, 0)
	125 org/apache/commons/math3/analysis/differentiation/DerivativeStructure.getValue:()D (0, 0)
	127 dload_2 (0, 0)
	128 dsub (0, 0)
	129 dstore (0, 0)
	130 #10 (0, 0)
	131 new (0, 0)
	132 org/apache/commons/math3/analysis/differentiation/DerivativeStructure (0, 0)
	134 dup (0, 0)
	135 iload (0, 0)
	136 #8 (0, 0)
	137 iload (0, 0)
	138 #7 (0, 0)
	139 dconst_0 (0, 0)
	140 invokespecial (0, 0)
	141 org/apache/commons/math3/analysis/differentiation/DerivativeStructure.<init>:(IID)V (0, 0)
	143 astore (0, 0)
	144 #12 (0, 0)
	145 aconst_null (0, 0)
	146 astore (0, 0)
	147 #13 (0, 0)
	148 iconst_0 (1, 4)
	149 istore (1, 4)
	150 #14 (1, 4)
	151 iload (1, 4)
	152 #14 (1, 4)
	153 aload_0 (1, 4)
	154 getfield (1, 4)
	155 org/apache/commons/math3/analysis/differentiation/FiniteDifferencesDifferentiator.nbPoints:I (1, 4)
	157 if_icmpge (1, 4)
	158 89 (1, 4)
	160 iload (2, 1)
	161 #14 (2, 1)
	162 ifne (2, 1)
	163 20 (2, 1)
	165 new (2, 1)
	166 org/apache/commons/math3/analysis/differentiation/DerivativeStructure (2, 1)
	168 dup (2, 1)
	169 iload (2, 1)
	170 #8 (2, 1)
	171 iload (2, 1)
	172 #7 (2, 1)
	173 dconst_1 (2, 1)
	174 invokespecial (2, 1)
	175 org/apache/commons/math3/analysis/differentiation/DerivativeStructure.<init>:(IID)V (2, 1)
	177 astore (2, 1)
	178 #13 (2, 1)
	179 goto (2, 1)
	180 44 (2, 1)
	182 aload (2, 2)
	183 #9 (2, 2)
	184 iconst_0 (2, 2)
	185 dload (2, 2)
	186 #10 (2, 2)
	187 iload (2, 2)
	188 #14 (2, 2)
	189 iconst_1 (2, 2)
	190 isub (2, 2)
	191 i2d (2, 2)
	192 aload_0 (2, 2)
	193 getfield (2, 2)
	194 org/apache/commons/math3/analysis/differentiation/FiniteDifferencesDifferentiator.stepSize:D (2, 2)
	196 dmul (2, 2)
	197 dsub (2, 2)
	198 dastore (2, 2)
	199 new (2, 2)
	200 org/apache/commons/math3/analysis/differentiation/DerivativeStructure (2, 2)
	202 dup (2, 2)
	203 iload (2, 2)
	204 #8 (2, 2)
	205 iload (2, 2)
	206 #7 (2, 2)
	207 aload (2, 2)
	208 #9 (2, 2)
	209 invokespecial (2, 2)
	210 org/apache/commons/math3/analysis/differentiation/DerivativeStructure.<init>:(II[D)V (2, 2)
	212 astore (2, 2)
	213 #15 (2, 2)
	214 aload (2, 2)
	215 #13 (2, 2)
	216 aload (2, 2)
	217 #15 (2, 2)
	218 invokevirtual (2, 2)
	219 org/apache/commons/math3/analysis/differentiation/DerivativeStructure.multiply:(Lorg/apache/commons/math3/analysis/differentiation/DerivativeStructure;)Lorg/apache/commons/math3/analysis/differentiation/DerivativeStructure; (2, 2)
	221 astore (2, 2)
	222 #13 (2, 2)
	223 aload (1, 4)
	224 #12 (1, 4)
	225 aload (1, 4)
	226 #13 (1, 4)
	227 aload (1, 4)
	228 #5 (1, 4)
	229 iload (1, 4)
	230 #14 (1, 4)
	231 daload (1, 4)
	232 invokevirtual (1, 4)
	233 org/apache/commons/math3/analysis/differentiation/DerivativeStructure.multiply:(D)Lorg/apache/commons/math3/analysis/differentiation/DerivativeStructure; (1, 4)
	235 invokevirtual (1, 4)
	236 org/apache/commons/math3/analysis/differentiation/DerivativeStructure.add:(Lorg/apache/commons/math3/analysis/differentiation/DerivativeStructure;)Lorg/apache/commons/math3/analysis/differentiation/DerivativeStructure; (1, 4)
	238 astore (1, 4)
	239 #12 (1, 4)
	240 iinc (1, 4)
	241 #14 (1, 4)
	242 -89 (1, 4)
	243 goto (1, 4)
	244 -92 (1, 4)
	246 aload (0, 0)
	247 #12 (0, 0)
	248 areturn (0, 0)

Method: differentiate
	0 new (1, 1)
	1 org/apache/commons/math3/analysis/differentiation/FiniteDifferencesDifferentiator$3 (1, 1)
	3 dup (1, 1)
	4 aload_0 (1, 1)
	5 aload_1 (1, 1)
	6 invokespecial (1, 1)
	7 org/apache/commons/math3/analysis/differentiation/FiniteDifferencesDifferentiator$3.<init>:(Lorg/apache/commons/math3/analysis/differentiation/FiniteDifferencesDifferentiator;Lorg/apache/commons/math3/analysis/UnivariateMatrixFunction;)V (1, 1)
	9 areturn (1, 1)

Method: access$000
	0 aload_0 (0, 1)
	1 getfield (0, 1)
	2 org/apache/commons/math3/analysis/differentiation/FiniteDifferencesDifferentiator.nbPoints:I (0, 1)
	4 ireturn (0, 1)

Method: access$100
	0 aload_0 (0, 1)
	1 getfield (0, 1)
	2 org/apache/commons/math3/analysis/differentiation/FiniteDifferencesDifferentiator.tMax:D (0, 1)
	4 dreturn (0, 1)

Method: access$200
	0 aload_0 (0, 1)
	1 getfield (0, 1)
	2 org/apache/commons/math3/analysis/differentiation/FiniteDifferencesDifferentiator.tMin:D (0, 1)
	4 dreturn (0, 1)

Method: access$300
	0 aload_0 (0, 1)
	1 getfield (0, 1)
	2 org/apache/commons/math3/analysis/differentiation/FiniteDifferencesDifferentiator.halfSampleSpan:D (0, 1)
	4 dreturn (0, 1)

Method: access$400
	0 aload_0 (0, 1)
	1 getfield (0, 1)
	2 org/apache/commons/math3/analysis/differentiation/FiniteDifferencesDifferentiator.stepSize:D (0, 1)
	4 dreturn (0, 1)

Method: access$500
	0 aload_0 (0, 1)
	1 aload_1 (0, 1)
	2 dload_2 (0, 1)
	3 aload (0, 1)
	4 #4 (0, 1)
	5 invokespecial (0, 1)
	6 org/apache/commons/math3/analysis/differentiation/FiniteDifferencesDifferentiator.evaluate:(Lorg/apache/commons/math3/analysis/differentiation/DerivativeStructure;D[D)Lorg/apache/commons/math3/analysis/differentiation/DerivativeStructure; (0, 1)
	8 areturn (0, 1)

