Method: <init>
	0 aload_0 (1, 1)
	1 invokespecial (1, 1)
	2 java/lang/Object.<init>:()V (1, 1)
	4 aload_0 (1, 1)
	5 aload_1 (1, 1)
	6 putfield (1, 1)
	7 org/apache/commons/math3/analysis/differentiation/JacobianFunction.f:Lorg/apache/commons/math3/analysis/differentiation/MultivariateDifferentiableVectorFunction; (1, 1)
	9 return (0, 0)

Method: value
	0 aload_1 (0, 0)
	1 arraylength (0, 0)
	2 anewarray (0, 0)
	3 org/apache/commons/math3/analysis/differentiation/DerivativeStructure (0, 0)
	5 astore_2 (0, 0)
	6 iconst_0 (1, 4)
	7 istore_3 (1, 4)
	8 iload_3 (1, 4)
	9 aload_1 (1, 4)
	10 arraylength (1, 4)
	11 if_icmpge (1, 4)
	12 26 (1, 4)
	14 aload_2 (1, 4)
	15 iload_3 (1, 4)
	16 new (1, 4)
	17 org/apache/commons/math3/analysis/differentiation/DerivativeStructure (1, 4)
	19 dup (1, 4)
	20 aload_1 (1, 4)
	21 arraylength (1, 4)
	22 iconst_1 (1, 4)
	23 iload_3 (1, 4)
	24 aload_1 (1, 4)
	25 iload_3 (1, 4)
	26 daload (1, 4)
	27 invokespecial (1, 4)
	28 org/apache/commons/math3/analysis/differentiation/DerivativeStructure.<init>:(IIID)V (1, 4)
	30 aastore (1, 4)
	31 iinc (1, 4)
	32 #3 (1, 4)
	33 -89 (1, 4)
	34 goto (1, 4)
	35 -26 (1, 4)
	37 aload_0 (0, 0)
	38 getfield (0, 0)
	39 org/apache/commons/math3/analysis/differentiation/JacobianFunction.f:Lorg/apache/commons/math3/analysis/differentiation/MultivariateDifferentiableVectorFunction; (0, 0)
	41 aload_2 (0, 0)
	42 invokeinterface (0, 0)
	43 org/apache/commons/math3/analysis/differentiation/MultivariateDifferentiableVectorFunction.getPartialDerivative:([I)D (0, 0)
	45 0 (0, 0)
	47 astore_3 (0, 0)
	48 aload_3 (0, 0)
	49 arraylength (0, 0)
	50 aload_1 (0, 0)
	51 arraylength (0, 0)
	52 multianewarray (0, 0)
	53 [[D (0, 0)
	55 58 (0, 0)
	56 astore (0, 0)
	57 #4 (0, 0)
	58 aload_1 (0, 0)
	59 arraylength (0, 0)
	60 newarray (0, 0)
	61 10 (0, 0)
	62 astore (0, 0)
	63 #5 (0, 0)
	64 iconst_0 (1, 4)
	65 istore (1, 4)
	66 #6 (1, 4)
	67 iload (1, 4)
	68 #6 (1, 4)
	69 aload_3 (1, 4)
	70 arraylength (1, 4)
	71 if_icmpge (1, 4)
	72 54 (1, 4)
	74 iconst_0 (2, 4)
	75 istore (2, 4)
	76 #7 (2, 4)
	77 iload (2, 4)
	78 #7 (2, 4)
	79 aload_1 (2, 4)
	80 arraylength (2, 4)
	81 if_icmpge (2, 4)
	82 38 (2, 4)
	84 aload (2, 4)
	85 #5 (2, 4)
	86 iload (2, 4)
	87 #7 (2, 4)
	88 iconst_1 (2, 4)
	89 iastore (2, 4)
	90 aload (2, 4)
	91 #4 (2, 4)
	92 iload (2, 4)
	93 #6 (2, 4)
	94 aaload (2, 4)
	95 iload (2, 4)
	96 #7 (2, 4)
	97 aload_3 (2, 4)
	98 iload (2, 4)
	99 #6 (2, 4)
	100 aaload (2, 4)
	101 aload (2, 4)
	102 #5 (2, 4)
	103 invokevirtual (2, 4)
	104 org/apache/commons/math3/analysis/differentiation/DerivativeStructure.getPartialDerivative:([I)D (2, 4)
	106 dastore (2, 4)
	107 aload (2, 4)
	108 #5 (2, 4)
	109 iload (2, 4)
	110 #7 (2, 4)
	111 iconst_0 (2, 4)
	112 iastore (2, 4)
	113 iinc (2, 4)
	114 #7 (2, 4)
	115 -89 (2, 4)
	116 goto (2, 4)
	117 -39 (2, 4)
	119 iinc (2, 4)
	120 #6 (2, 4)
	121 -89 (2, 4)
	122 goto (2, 4)
	123 -55 (2, 4)
	125 aload (1, 4)
	126 #4 (1, 4)
	127 areturn (1, 4)

