Method: <init>
	0 aload_0 (0, 0)
	1 invokespecial (0, 0)
	2 java/lang/Object.<init>:()V (0, 0)
	4 aload_0 (0, 0)
	5 dload_1 (0, 0)
	6 putfield (0, 0)
	7 org/apache/commons/math3/analysis/differentiation/SparseGradient.value:D (0, 0)
	9 aload_0 (0, 0)
	10 new (0, 0)
	11 java/util/HashMap (0, 0)
	13 dup (0, 0)
	14 invokespecial (0, 0)
	15 java/util/HashMap.<init>:()V (0, 0)
	17 putfield (0, 0)
	18 org/apache/commons/math3/analysis/differentiation/SparseGradient.derivatives:Ljava/util/Map; (0, 0)
	20 aload (2, 1)
	21 #5 (2, 1)
	22 ifnull (2, 1)
	23 77 (2, 1)
	25 aload (3, 4)
	26 #5 (3, 4)
	27 invokeinterface (3, 4)
	28 java/util/Map.java/util/Set (3, 4)
	30 0 (3, 4)
	32 invokeinterface (3, 4)
	33 java/util/Set.java/util/Iterator (3, 4)
	35 0 (3, 4)
	37 astore (3, 4)
	38 #6 (3, 4)
	39 aload (3, 4)
	40 #6 (3, 4)
	41 invokeinterface (3, 4)
	42 java/util/Iterator.next:()Ljava/lang/Object; (3, 4)
	44 0 (3, 4)
	46 ifeq (3, 4)
	47 53 (3, 4)
	49 aload (3, 4)
	50 #6 (3, 4)
	51 invokeinterface (3, 4)
	52 java/util/Iterator.java/util/Map$Entry (3, 4)
	54 0 (3, 4)
	56 checkcast (3, 4)
	57 java/util/Map$Entry (3, 4)
	59 astore (3, 4)
	60 #7 (3, 4)
	61 aload_0 (3, 4)
	62 getfield (3, 4)
	63 org/apache/commons/math3/analysis/differentiation/SparseGradient.derivatives:Ljava/util/Map; (3, 4)
	65 aload (3, 4)
	66 #7 (3, 4)
	67 invokeinterface (3, 4)
	68 java/util/Map$Entry.getValue:()Ljava/lang/Object; (3, 4)
	70 0 (3, 4)
	72 dload_3 (3, 4)
	73 aload (3, 4)
	74 #7 (3, 4)
	75 invokeinterface (3, 4)
	76 java/util/Map$Entry.java/lang/Double (3, 4)
	78 0 (3, 4)
	80 checkcast (3, 4)
	81 java/lang/Double (3, 4)
	83 invokevirtual (3, 4)
	84 java/lang/Double.doubleValue:()D (3, 4)
	86 dmul (3, 4)
	87 invokestatic (3, 4)
	88 java/lang/Double.valueOf:(D)Ljava/lang/Double; (3, 4)
	90 invokeinterface (3, 4)
	91 java/util/Map.org/apache/commons/math3/analysis/differentiation/SparseGradient (3, 4)
	93 0 (3, 4)
	95 pop (3, 4)
	96 goto (2, 1)
	97 -57 (2, 1)
	99 return (0, 0)

Method: createConstant
	0 new (0, 0)
	1 org/apache/commons/math3/analysis/differentiation/SparseGradient (0, 0)
	3 dup (0, 0)
	4 dload_0 (0, 0)
	5 invokestatic (0, 0)
	6 java/util/Collections.emptyMap:()Ljava/util/Map; (0, 0)
	8 invokespecial (0, 0)
	9 org/apache/commons/math3/analysis/differentiation/SparseGradient.<init>:(DLjava/util/Map;)V (0, 0)
	11 areturn (0, 0)

Method: createVariable
	0 new (0, 0)
	1 org/apache/commons/math3/analysis/differentiation/SparseGradient (0, 0)
	3 dup (0, 0)
	4 dload_1 (0, 0)
	5 iload_0 (0, 0)
	6 invokestatic (0, 0)
	7 java/lang/Integer.valueOf:(I)Ljava/lang/Integer; (0, 0)
	9 dconst_1 (0, 0)
	10 invokestatic (0, 0)
	11 java/lang/Double.valueOf:(D)Ljava/lang/Double; (0, 0)
	13 invokestatic (0, 0)
	14 java/util/Collections.singletonMap:(Ljava/lang/Object;Ljava/lang/Object;)Ljava/util/Map; (0, 0)
	16 invokespecial (0, 0)
	17 org/apache/commons/math3/analysis/differentiation/SparseGradient.<init>:(DLjava/util/Map;)V (0, 0)
	19 areturn (0, 0)

Method: numVars
	0 aload_0 (0, 0)
	1 getfield (0, 0)
	2 org/apache/commons/math3/analysis/differentiation/SparseGradient.derivatives:Ljava/util/Map; (0, 0)
	4 invokeinterface (0, 0)
	5 java/util/Map.get:(Ljava/lang/Object;)Ljava/lang/Object; (0, 0)
	7 0 (0, 0)
	9 ireturn (0, 0)

Method: getDerivative
	0 aload_0 (0, 0)
	1 getfield (0, 0)
	2 org/apache/commons/math3/analysis/differentiation/SparseGradient.derivatives:Ljava/util/Map; (0, 0)
	4 iload_1 (0, 0)
	5 invokestatic (0, 0)
	6 java/lang/Integer.valueOf:(I)Ljava/lang/Integer; (0, 0)
	8 invokeinterface (0, 0)
	9 java/util/Map.java/lang/Integer (0, 0)
	11 0 (0, 0)
	13 checkcast (0, 0)
	14 java/lang/Double (0, 0)
	16 astore_2 (0, 0)
	17 aload_2 (0, 0)
	18 ifnonnull (0, 0)
	19 7 (0, 0)
	21 dconst_0 (0, 0)
	22 goto (0, 0)
	23 7 (0, 0)
	25 aload_2 (0, 0)
	26 invokevirtual (0, 0)
	27 java/lang/Double.doubleValue:()D (0, 0)
	29 dreturn (0, 0)

Method: getValue
	0 aload_0 (0, 0)
	1 getfield (0, 0)
	2 org/apache/commons/math3/analysis/differentiation/SparseGradient.value:D (0, 0)
	4 dreturn (0, 0)

Method: getReal
	0 aload_0 (0, 0)
	1 getfield (0, 0)
	2 org/apache/commons/math3/analysis/differentiation/SparseGradient.value:D (0, 0)
	4 dreturn (0, 0)

Method: add
	0 aload_0 (0, 0)
	1 aload_1 (0, 0)
	2 checkcast (0, 0)
	3 org/apache/commons/math3/analysis/differentiation/SparseGradient (0, 0)
	5 invokevirtual (0, 0)
	6 org/apache/commons/math3/analysis/differentiation/SparseGradient.add:(Lorg/apache/commons/math3/analysis/differentiation/SparseGradient;)Lorg/apache/commons/math3/analysis/differentiation/SparseGradient; (0, 0)
	8 areturn (0, 0)

Method: addInPlace
	0 aload_0 (0, 0)
	1 dup (0, 0)
	2 getfield (0, 0)
	3 org/apache/commons/math3/analysis/differentiation/SparseGradient.value:D (0, 0)
	5 aload_1 (0, 0)
	6 getfield (0, 0)
	7 org/apache/commons/math3/analysis/differentiation/SparseGradient.value:D (0, 0)
	9 dadd (0, 0)
	10 putfield (0, 0)
	11 org/apache/commons/math3/analysis/differentiation/SparseGradient.value:D (0, 0)
	13 aload_1 (1, 4)
	14 getfield (1, 4)
	15 org/apache/commons/math3/analysis/differentiation/SparseGradient.derivatives:Ljava/util/Map; (1, 4)
	17 invokeinterface (1, 4)
	18 java/util/Map.java/util/Set (1, 4)
	20 0 (1, 4)
	22 invokeinterface (1, 4)
	23 java/util/Set.java/util/Iterator (1, 4)
	25 0 (1, 4)
	27 astore_2 (1, 4)
	28 aload_2 (1, 4)
	29 invokeinterface (1, 4)
	30 java/util/Iterator.next:()Ljava/lang/Object; (1, 4)
	32 0 (1, 4)
	34 ifeq (1, 4)
	35 114 (1, 4)
	37 aload_2 (1, 4)
	38 invokeinterface (1, 4)
	39 java/util/Iterator.java/util/Map$Entry (1, 4)
	41 0 (1, 4)
	43 checkcast (1, 4)
	44 java/util/Map$Entry (1, 4)
	46 astore_3 (1, 4)
	47 aload_3 (1, 4)
	48 invokeinterface (1, 4)
	49 java/util/Map$Entry.getValue:()Ljava/lang/Object; (1, 4)
	51 0 (1, 4)
	53 checkcast (1, 4)
	54 java/lang/Integer (1, 4)
	56 invokevirtual (1, 4)
	57 java/lang/Integer.intValue:()I (1, 4)
	59 istore (1, 4)
	60 #4 (1, 4)
	61 aload_0 (1, 4)
	62 getfield (1, 4)
	63 org/apache/commons/math3/analysis/differentiation/SparseGradient.derivatives:Ljava/util/Map; (1, 4)
	65 iload (1, 4)
	66 #4 (1, 4)
	67 invokestatic (1, 4)
	68 java/lang/Integer.valueOf:(I)Ljava/lang/Integer; (1, 4)
	70 invokeinterface (1, 4)
	71 java/util/Map.java/lang/Integer (1, 4)
	73 0 (1, 4)
	75 checkcast (1, 4)
	76 java/lang/Double (1, 4)
	78 astore (1, 4)
	79 #5 (1, 4)
	80 aload (2, 1)
	81 #5 (2, 1)
	82 ifnonnull (2, 1)
	83 27 (2, 1)
	85 aload_0 (2, 1)
	86 getfield (2, 1)
	87 org/apache/commons/math3/analysis/differentiation/SparseGradient.derivatives:Ljava/util/Map; (2, 1)
	89 iload (2, 1)
	90 #4 (2, 1)
	91 invokestatic (2, 1)
	92 java/lang/Integer.valueOf:(I)Ljava/lang/Integer; (2, 1)
	94 aload_3 (2, 1)
	95 invokeinterface (2, 1)
	96 java/util/Map$Entry.java/lang/Double (2, 1)
	98 0 (2, 1)
	100 invokeinterface (2, 1)
	101 java/util/Map.org/apache/commons/math3/analysis/differentiation/SparseGradient (2, 1)
	103 0 (2, 1)
	105 pop (2, 1)
	106 goto (2, 1)
	107 39 (2, 1)
	109 aload_0 (2, 2)
	110 getfield (2, 2)
	111 org/apache/commons/math3/analysis/differentiation/SparseGradient.derivatives:Ljava/util/Map; (2, 2)
	113 iload (2, 2)
	114 #4 (2, 2)
	115 invokestatic (2, 2)
	116 java/lang/Integer.valueOf:(I)Ljava/lang/Integer; (2, 2)
	118 aload (2, 2)
	119 #5 (2, 2)
	120 invokevirtual (2, 2)
	121 java/lang/Double.doubleValue:()D (2, 2)
	123 aload_3 (2, 2)
	124 invokeinterface (2, 2)
	125 java/util/Map$Entry.java/lang/Double (2, 2)
	127 0 (2, 2)
	129 checkcast (2, 2)
	130 java/lang/Double (2, 2)
	132 invokevirtual (2, 2)
	133 java/lang/Double.doubleValue:()D (2, 2)
	135 dadd (2, 2)
	136 invokestatic (2, 2)
	137 java/lang/Double.valueOf:(D)Ljava/lang/Double; (2, 2)
	139 invokeinterface (2, 2)
	140 java/util/Map.org/apache/commons/math3/analysis/differentiation/SparseGradient (2, 2)
	142 0 (2, 2)
	144 pop (2, 2)
	145 goto (0, 0)
	146 -117 (0, 0)
	148 return (0, 0)

Method: subtract
	0 aload_0 (0, 0)
	1 aload_1 (0, 0)
	2 checkcast (0, 0)
	3 org/apache/commons/math3/analysis/differentiation/SparseGradient (0, 0)
	5 invokevirtual (0, 0)
	6 org/apache/commons/math3/analysis/differentiation/SparseGradient.subtract:(Lorg/apache/commons/math3/analysis/differentiation/SparseGradient;)Lorg/apache/commons/math3/analysis/differentiation/SparseGradient; (0, 0)
	8 areturn (0, 0)

Method: multiply
	0 aload_0 (0, 0)
	1 iload_1 (0, 0)
	2 invokevirtual (0, 0)
	3 org/apache/commons/math3/analysis/differentiation/SparseGradient.multiply:(I)Lorg/apache/commons/math3/analysis/differentiation/SparseGradient; (0, 0)
	5 areturn (0, 0)

Method: multiplyInPlace
	0 aload_0 (1, 4)
	1 getfield (1, 4)
	2 org/apache/commons/math3/analysis/differentiation/SparseGradient.derivatives:Ljava/util/Map; (1, 4)
	4 invokeinterface (1, 4)
	5 java/util/Map.java/util/Set (1, 4)
	7 0 (1, 4)
	9 invokeinterface (1, 4)
	10 java/util/Set.java/util/Iterator (1, 4)
	12 0 (1, 4)
	14 astore_2 (1, 4)
	15 aload_2 (1, 4)
	16 invokeinterface (1, 4)
	17 java/util/Iterator.next:()Ljava/lang/Object; (1, 4)
	19 0 (1, 4)
	21 ifeq (1, 4)
	22 52 (1, 4)
	24 aload_2 (1, 4)
	25 invokeinterface (1, 4)
	26 java/util/Iterator.java/util/Map$Entry (1, 4)
	28 0 (1, 4)
	30 checkcast (1, 4)
	31 java/util/Map$Entry (1, 4)
	33 astore_3 (1, 4)
	34 aload_0 (1, 4)
	35 getfield (1, 4)
	36 org/apache/commons/math3/analysis/differentiation/SparseGradient.derivatives:Ljava/util/Map; (1, 4)
	38 aload_3 (1, 4)
	39 invokeinterface (1, 4)
	40 java/util/Map$Entry.getValue:()Ljava/lang/Object; (1, 4)
	42 0 (1, 4)
	44 aload_1 (1, 4)
	45 getfield (1, 4)
	46 org/apache/commons/math3/analysis/differentiation/SparseGradient.value:D (1, 4)
	48 aload_3 (1, 4)
	49 invokeinterface (1, 4)
	50 java/util/Map$Entry.java/lang/Double (1, 4)
	52 0 (1, 4)
	54 checkcast (1, 4)
	55 java/lang/Double (1, 4)
	57 invokevirtual (1, 4)
	58 java/lang/Double.doubleValue:()D (1, 4)
	60 dmul (1, 4)
	61 invokestatic (1, 4)
	62 java/lang/Double.valueOf:(D)Ljava/lang/Double; (1, 4)
	64 invokeinterface (1, 4)
	65 java/util/Map.org/apache/commons/math3/analysis/differentiation/SparseGradient (1, 4)
	67 0 (1, 4)
	69 pop (1, 4)
	70 goto (0, 0)
	71 -55 (0, 0)
	73 aload_1 (1, 4)
	74 getfield (1, 4)
	75 org/apache/commons/math3/analysis/differentiation/SparseGradient.derivatives:Ljava/util/Map; (1, 4)
	77 invokeinterface (1, 4)
	78 java/util/Map.java/util/Set (1, 4)
	80 0 (1, 4)
	82 invokeinterface (1, 4)
	83 java/util/Set.java/util/Iterator (1, 4)
	85 0 (1, 4)
	87 astore_2 (1, 4)
	88 aload_2 (1, 4)
	89 invokeinterface (1, 4)
	90 java/util/Iterator.next:()Ljava/lang/Object; (1, 4)
	92 0 (1, 4)
	94 ifeq (1, 4)
	95 133 (1, 4)
	97 aload_2 (1, 4)
	98 invokeinterface (1, 4)
	99 java/util/Iterator.java/util/Map$Entry (1, 4)
	101 0 (1, 4)
	103 checkcast (1, 4)
	104 java/util/Map$Entry (1, 4)
	106 astore_3 (1, 4)
	107 aload_3 (1, 4)
	108 invokeinterface (1, 4)
	109 java/util/Map$Entry.getValue:()Ljava/lang/Object; (1, 4)
	111 0 (1, 4)
	113 checkcast (1, 4)
	114 java/lang/Integer (1, 4)
	116 invokevirtual (1, 4)
	117 java/lang/Integer.intValue:()I (1, 4)
	119 istore (1, 4)
	120 #4 (1, 4)
	121 aload_0 (1, 4)
	122 getfield (1, 4)
	123 org/apache/commons/math3/analysis/differentiation/SparseGradient.derivatives:Ljava/util/Map; (1, 4)
	125 iload (1, 4)
	126 #4 (1, 4)
	127 invokestatic (1, 4)
	128 java/lang/Integer.valueOf:(I)Ljava/lang/Integer; (1, 4)
	130 invokeinterface (1, 4)
	131 java/util/Map.java/lang/Integer (1, 4)
	133 0 (1, 4)
	135 checkcast (1, 4)
	136 java/lang/Double (1, 4)
	138 astore (1, 4)
	139 #5 (1, 4)
	140 aload (2, 1)
	141 #5 (2, 1)
	142 ifnonnull (2, 1)
	143 41 (2, 1)
	145 aload_0 (2, 1)
	146 getfield (2, 1)
	147 org/apache/commons/math3/analysis/differentiation/SparseGradient.derivatives:Ljava/util/Map; (2, 1)
	149 iload (2, 1)
	150 #4 (2, 1)
	151 invokestatic (2, 1)
	152 java/lang/Integer.valueOf:(I)Ljava/lang/Integer; (2, 1)
	154 aload_0 (2, 1)
	155 getfield (2, 1)
	156 org/apache/commons/math3/analysis/differentiation/SparseGradient.value:D (2, 1)
	158 aload_3 (2, 1)
	159 invokeinterface (2, 1)
	160 java/util/Map$Entry.java/lang/Double (2, 1)
	162 0 (2, 1)
	164 checkcast (2, 1)
	165 java/lang/Double (2, 1)
	167 invokevirtual (2, 1)
	168 java/lang/Double.doubleValue:()D (2, 1)
	170 dmul (2, 1)
	171 invokestatic (2, 1)
	172 java/lang/Double.valueOf:(D)Ljava/lang/Double; (2, 1)
	174 invokeinterface (2, 1)
	175 java/util/Map.org/apache/commons/math3/analysis/differentiation/SparseGradient (2, 1)
	177 0 (2, 1)
	179 pop (2, 1)
	180 goto (2, 1)
	181 44 (2, 1)
	183 aload_0 (2, 2)
	184 getfield (2, 2)
	185 org/apache/commons/math3/analysis/differentiation/SparseGradient.derivatives:Ljava/util/Map; (2, 2)
	187 iload (2, 2)
	188 #4 (2, 2)
	189 invokestatic (2, 2)
	190 java/lang/Integer.valueOf:(I)Ljava/lang/Integer; (2, 2)
	192 aload (2, 2)
	193 #5 (2, 2)
	194 invokevirtual (2, 2)
	195 java/lang/Double.doubleValue:()D (2, 2)
	197 aload_0 (2, 2)
	198 getfield (2, 2)
	199 org/apache/commons/math3/analysis/differentiation/SparseGradient.value:D (2, 2)
	201 aload_3 (2, 2)
	202 invokeinterface (2, 2)
	203 java/util/Map$Entry.java/lang/Double (2, 2)
	205 0 (2, 2)
	207 checkcast (2, 2)
	208 java/lang/Double (2, 2)
	210 invokevirtual (2, 2)
	211 java/lang/Double.doubleValue:()D (2, 2)
	213 dmul (2, 2)
	214 dadd (2, 2)
	215 invokestatic (2, 2)
	216 java/lang/Double.valueOf:(D)Ljava/lang/Double; (2, 2)
	218 invokeinterface (2, 2)
	219 java/util/Map.org/apache/commons/math3/analysis/differentiation/SparseGradient (2, 2)
	221 0 (2, 2)
	223 pop (2, 2)
	224 goto (0, 0)
	225 -136 (0, 0)
	227 aload_0 (0, 0)
	228 dup (0, 0)
	229 getfield (0, 0)
	230 org/apache/commons/math3/analysis/differentiation/SparseGradient.value:D (0, 0)
	232 aload_1 (0, 0)
	233 getfield (0, 0)
	234 org/apache/commons/math3/analysis/differentiation/SparseGradient.value:D (0, 0)
	236 dmul (0, 0)
	237 putfield (0, 0)
	238 org/apache/commons/math3/analysis/differentiation/SparseGradient.value:D (0, 0)
	240 return (0, 0)

Method: divide
	0 aload_0 (0, 0)
	1 aload_1 (0, 0)
	2 checkcast (0, 0)
	3 org/apache/commons/math3/analysis/differentiation/SparseGradient (0, 0)
	5 invokevirtual (0, 0)
	6 org/apache/commons/math3/analysis/differentiation/SparseGradient.divide:(Lorg/apache/commons/math3/analysis/differentiation/SparseGradient;)Lorg/apache/commons/math3/analysis/differentiation/SparseGradient; (0, 0)
	8 areturn (0, 0)

Method: negate
	0 aload_0 (0, 0)
	1 invokevirtual (0, 0)
	2 org/apache/commons/math3/analysis/differentiation/SparseGradient.negate:()Lorg/apache/commons/math3/analysis/differentiation/SparseGradient; (0, 0)
	4 areturn (0, 0)

Method: getField
	0 new (0, 0)
	1 org/apache/commons/math3/analysis/differentiation/SparseGradient$1 (0, 0)
	3 dup (0, 0)
	4 aload_0 (0, 0)
	5 invokespecial (0, 0)
	6 org/apache/commons/math3/analysis/differentiation/SparseGradient$1.<init>:(Lorg/apache/commons/math3/analysis/differentiation/SparseGradient;)V (0, 0)
	8 areturn (0, 0)

Method: remainder
	0 aload_0 (0, 0)
	1 dload_1 (0, 0)
	2 invokevirtual (0, 0)
	3 org/apache/commons/math3/analysis/differentiation/SparseGradient.remainder:(D)Lorg/apache/commons/math3/analysis/differentiation/SparseGradient; (0, 0)
	5 areturn (0, 0)

Method: abs
	0 aload_0 (0, 0)
	1 invokevirtual (0, 0)
	2 org/apache/commons/math3/analysis/differentiation/SparseGradient.abs:()Lorg/apache/commons/math3/analysis/differentiation/SparseGradient; (0, 0)
	4 areturn (0, 0)

Method: ceil
	0 aload_0 (0, 0)
	1 invokevirtual (0, 0)
	2 org/apache/commons/math3/analysis/differentiation/SparseGradient.ceil:()Lorg/apache/commons/math3/analysis/differentiation/SparseGradient; (0, 0)
	4 areturn (0, 0)

Method: floor
	0 aload_0 (0, 0)
	1 invokevirtual (0, 0)
	2 org/apache/commons/math3/analysis/differentiation/SparseGradient.floor:()Lorg/apache/commons/math3/analysis/differentiation/SparseGradient; (0, 0)
	4 areturn (0, 0)

Method: rint
	0 aload_0 (0, 0)
	1 invokevirtual (0, 0)
	2 org/apache/commons/math3/analysis/differentiation/SparseGradient.rint:()Lorg/apache/commons/math3/analysis/differentiation/SparseGradient; (0, 0)
	4 areturn (0, 0)

Method: round
	0 aload_0 (0, 0)
	1 getfield (0, 0)
	2 org/apache/commons/math3/analysis/differentiation/SparseGradient.value:D (0, 0)
	4 invokestatic (0, 0)
	5 org/apache/commons/math3/util/FastMath.round:(D)J (0, 0)
	7 lreturn (0, 0)

Method: signum
	0 aload_0 (0, 0)
	1 invokevirtual (0, 0)
	2 org/apache/commons/math3/analysis/differentiation/SparseGradient.signum:()Lorg/apache/commons/math3/analysis/differentiation/SparseGradient; (0, 0)
	4 areturn (0, 0)

Method: copySign
	0 aload_0 (0, 0)
	1 aload_1 (0, 0)
	2 checkcast (0, 0)
	3 org/apache/commons/math3/analysis/differentiation/SparseGradient (0, 0)
	5 invokevirtual (0, 0)
	6 org/apache/commons/math3/analysis/differentiation/SparseGradient.copySign:(Lorg/apache/commons/math3/analysis/differentiation/SparseGradient;)Lorg/apache/commons/math3/analysis/differentiation/SparseGradient; (0, 0)
	8 areturn (0, 0)

Method: scalb
	0 aload_0 (0, 0)
	1 iload_1 (0, 0)
	2 invokevirtual (0, 0)
	3 org/apache/commons/math3/analysis/differentiation/SparseGradient.scalb:(I)Lorg/apache/commons/math3/analysis/differentiation/SparseGradient; (0, 0)
	5 areturn (0, 0)

Method: hypot
	0 aload_0 (0, 0)
	1 aload_1 (0, 0)
	2 checkcast (0, 0)
	3 org/apache/commons/math3/analysis/differentiation/SparseGradient (0, 0)
	5 invokevirtual (0, 0)
	6 org/apache/commons/math3/analysis/differentiation/SparseGradient.hypot:(Lorg/apache/commons/math3/analysis/differentiation/SparseGradient;)Lorg/apache/commons/math3/analysis/differentiation/SparseGradient; (0, 0)
	8 areturn (0, 0)

Method: reciprocal
	0 aload_0 (0, 0)
	1 invokevirtual (0, 0)
	2 org/apache/commons/math3/analysis/differentiation/SparseGradient.reciprocal:()Lorg/apache/commons/math3/analysis/differentiation/SparseGradient; (0, 0)
	4 areturn (0, 0)

Method: sqrt
	0 aload_0 (0, 0)
	1 invokevirtual (0, 0)
	2 org/apache/commons/math3/analysis/differentiation/SparseGradient.sqrt:()Lorg/apache/commons/math3/analysis/differentiation/SparseGradient; (0, 0)
	4 areturn (0, 0)

Method: cbrt
	0 aload_0 (0, 0)
	1 invokevirtual (0, 0)
	2 org/apache/commons/math3/analysis/differentiation/SparseGradient.cbrt:()Lorg/apache/commons/math3/analysis/differentiation/SparseGradient; (0, 0)
	4 areturn (0, 0)

Method: rootN
	0 aload_0 (0, 0)
	1 iload_1 (0, 0)
	2 invokevirtual (0, 0)
	3 org/apache/commons/math3/analysis/differentiation/SparseGradient.rootN:(I)Lorg/apache/commons/math3/analysis/differentiation/SparseGradient; (0, 0)
	5 areturn (0, 0)

Method: pow
	0 aload_0 (0, 0)
	1 dload_1 (0, 0)
	2 invokevirtual (0, 0)
	3 org/apache/commons/math3/analysis/differentiation/SparseGradient.pow:(D)Lorg/apache/commons/math3/analysis/differentiation/SparseGradient; (0, 0)
	5 areturn (0, 0)

Method: exp
	0 aload_0 (0, 0)
	1 invokevirtual (0, 0)
	2 org/apache/commons/math3/analysis/differentiation/SparseGradient.exp:()Lorg/apache/commons/math3/analysis/differentiation/SparseGradient; (0, 0)
	4 areturn (0, 0)

Method: expm1
	0 aload_0 (0, 0)
	1 invokevirtual (0, 0)
	2 org/apache/commons/math3/analysis/differentiation/SparseGradient.expm1:()Lorg/apache/commons/math3/analysis/differentiation/SparseGradient; (0, 0)
	4 areturn (0, 0)

Method: log
	0 aload_0 (0, 0)
	1 invokevirtual (0, 0)
	2 org/apache/commons/math3/analysis/differentiation/SparseGradient.log:()Lorg/apache/commons/math3/analysis/differentiation/SparseGradient; (0, 0)
	4 areturn (0, 0)

Method: log10
	0 new (0, 0)
	1 org/apache/commons/math3/analysis/differentiation/SparseGradient (0, 0)
	3 dup (0, 0)
	4 aload_0 (0, 0)
	5 getfield (0, 0)
	6 org/apache/commons/math3/analysis/differentiation/SparseGradient.value:D (0, 0)
	8 invokestatic (0, 0)
	9 org/apache/commons/math3/util/FastMath.log10:(D)D (0, 0)
	11 dconst_1 (0, 0)
	12 ldc2_w (0, 0)
	13 10.0 (0, 0)
	15 invokestatic (0, 0)
	16 org/apache/commons/math3/util/FastMath.log:(D)D (0, 0)
	18 aload_0 (0, 0)
	19 getfield (0, 0)
	20 org/apache/commons/math3/analysis/differentiation/SparseGradient.value:D (0, 0)
	22 dmul (0, 0)
	23 ddiv (0, 0)
	24 aload_0 (0, 0)
	25 getfield (0, 0)
	26 org/apache/commons/math3/analysis/differentiation/SparseGradient.derivatives:Ljava/util/Map; (0, 0)
	28 invokespecial (0, 0)
	29 org/apache/commons/math3/analysis/differentiation/SparseGradient.<init>:(DDLjava/util/Map;)V (0, 0)
	31 areturn (0, 0)

Method: log1p
	0 aload_0 (0, 0)
	1 invokevirtual (0, 0)
	2 org/apache/commons/math3/analysis/differentiation/SparseGradient.log1p:()Lorg/apache/commons/math3/analysis/differentiation/SparseGradient; (0, 0)
	4 areturn (0, 0)

Method: cos
	0 aload_0 (0, 0)
	1 invokevirtual (0, 0)
	2 org/apache/commons/math3/analysis/differentiation/SparseGradient.cos:()Lorg/apache/commons/math3/analysis/differentiation/SparseGradient; (0, 0)
	4 areturn (0, 0)

Method: sin
	0 aload_0 (0, 0)
	1 invokevirtual (0, 0)
	2 org/apache/commons/math3/analysis/differentiation/SparseGradient.sin:()Lorg/apache/commons/math3/analysis/differentiation/SparseGradient; (0, 0)
	4 areturn (0, 0)

Method: tan
	0 aload_0 (0, 0)
	1 invokevirtual (0, 0)
	2 org/apache/commons/math3/analysis/differentiation/SparseGradient.tan:()Lorg/apache/commons/math3/analysis/differentiation/SparseGradient; (0, 0)
	4 areturn (0, 0)

Method: acos
	0 aload_0 (0, 0)
	1 invokevirtual (0, 0)
	2 org/apache/commons/math3/analysis/differentiation/SparseGradient.acos:()Lorg/apache/commons/math3/analysis/differentiation/SparseGradient; (0, 0)
	4 areturn (0, 0)

Method: asin
	0 aload_0 (0, 0)
	1 invokevirtual (0, 0)
	2 org/apache/commons/math3/analysis/differentiation/SparseGradient.asin:()Lorg/apache/commons/math3/analysis/differentiation/SparseGradient; (0, 0)
	4 areturn (0, 0)

Method: atan
	0 aload_0 (0, 0)
	1 invokevirtual (0, 0)
	2 org/apache/commons/math3/analysis/differentiation/SparseGradient.atan:()Lorg/apache/commons/math3/analysis/differentiation/SparseGradient; (0, 0)
	4 areturn (0, 0)

Method: atan2
	0 aload_0 (0, 0)
	1 aload_1 (0, 0)
	2 checkcast (0, 0)
	3 org/apache/commons/math3/analysis/differentiation/SparseGradient (0, 0)
	5 invokevirtual (0, 0)
	6 org/apache/commons/math3/analysis/differentiation/SparseGradient.atan2:(Lorg/apache/commons/math3/analysis/differentiation/SparseGradient;)Lorg/apache/commons/math3/analysis/differentiation/SparseGradient; (0, 0)
	8 areturn (0, 0)

Method: cosh
	0 aload_0 (0, 0)
	1 invokevirtual (0, 0)
	2 org/apache/commons/math3/analysis/differentiation/SparseGradient.cosh:()Lorg/apache/commons/math3/analysis/differentiation/SparseGradient; (0, 0)
	4 areturn (0, 0)

Method: sinh
	0 aload_0 (0, 0)
	1 invokevirtual (0, 0)
	2 org/apache/commons/math3/analysis/differentiation/SparseGradient.sinh:()Lorg/apache/commons/math3/analysis/differentiation/SparseGradient; (0, 0)
	4 areturn (0, 0)

Method: tanh
	0 aload_0 (0, 0)
	1 invokevirtual (0, 0)
	2 org/apache/commons/math3/analysis/differentiation/SparseGradient.tanh:()Lorg/apache/commons/math3/analysis/differentiation/SparseGradient; (0, 0)
	4 areturn (0, 0)

Method: acosh
	0 aload_0 (0, 0)
	1 invokevirtual (0, 0)
	2 org/apache/commons/math3/analysis/differentiation/SparseGradient.acosh:()Lorg/apache/commons/math3/analysis/differentiation/SparseGradient; (0, 0)
	4 areturn (0, 0)

Method: asinh
	0 aload_0 (0, 0)
	1 invokevirtual (0, 0)
	2 org/apache/commons/math3/analysis/differentiation/SparseGradient.asinh:()Lorg/apache/commons/math3/analysis/differentiation/SparseGradient; (0, 0)
	4 areturn (0, 0)

Method: atanh
	0 aload_0 (0, 0)
	1 invokevirtual (0, 0)
	2 org/apache/commons/math3/analysis/differentiation/SparseGradient.atanh:()Lorg/apache/commons/math3/analysis/differentiation/SparseGradient; (0, 0)
	4 areturn (0, 0)

Method: toDegrees
	0 new (0, 0)
	1 org/apache/commons/math3/analysis/differentiation/SparseGradient (0, 0)
	3 dup (0, 0)
	4 aload_0 (0, 0)
	5 getfield (0, 0)
	6 org/apache/commons/math3/analysis/differentiation/SparseGradient.value:D (0, 0)
	8 invokestatic (0, 0)
	9 org/apache/commons/math3/util/FastMath.toDegrees:(D)D (0, 0)
	11 dconst_1 (0, 0)
	12 invokestatic (0, 0)
	13 org/apache/commons/math3/util/FastMath.toDegrees:(D)D (0, 0)
	15 aload_0 (0, 0)
	16 getfield (0, 0)
	17 org/apache/commons/math3/analysis/differentiation/SparseGradient.derivatives:Ljava/util/Map; (0, 0)
	19 invokespecial (0, 0)
	20 org/apache/commons/math3/analysis/differentiation/SparseGradient.<init>:(DDLjava/util/Map;)V (0, 0)
	22 areturn (0, 0)

Method: toRadians
	0 new (0, 0)
	1 org/apache/commons/math3/analysis/differentiation/SparseGradient (0, 0)
	3 dup (0, 0)
	4 aload_0 (0, 0)
	5 getfield (0, 0)
	6 org/apache/commons/math3/analysis/differentiation/SparseGradient.value:D (0, 0)
	8 invokestatic (0, 0)
	9 org/apache/commons/math3/util/FastMath.toRadians:(D)D (0, 0)
	11 dconst_1 (0, 0)
	12 invokestatic (0, 0)
	13 org/apache/commons/math3/util/FastMath.toRadians:(D)D (0, 0)
	15 aload_0 (0, 0)
	16 getfield (0, 0)
	17 org/apache/commons/math3/analysis/differentiation/SparseGradient.derivatives:Ljava/util/Map; (0, 0)
	19 invokespecial (0, 0)
	20 org/apache/commons/math3/analysis/differentiation/SparseGradient.<init>:(DDLjava/util/Map;)V (0, 0)
	22 areturn (0, 0)

Method: taylor
	0 aload_0 (0, 0)
	1 getfield (0, 0)
	2 org/apache/commons/math3/analysis/differentiation/SparseGradient.value:D (0, 0)
	4 dstore_2 (0, 0)
	5 iconst_0 (1, 4)
	6 istore (1, 4)
	7 #4 (1, 4)
	8 iload (1, 4)
	9 #4 (1, 4)
	10 aload_1 (1, 4)
	11 arraylength (1, 4)
	12 if_icmpge (1, 4)
	13 23 (1, 4)
	15 dload_2 (1, 4)
	16 aload_1 (1, 4)
	17 iload (1, 4)
	18 #4 (1, 4)
	19 daload (1, 4)
	20 aload_0 (1, 4)
	21 iload (1, 4)
	22 #4 (1, 4)
	23 invokevirtual (1, 4)
	24 org/apache/commons/math3/analysis/differentiation/SparseGradient.getDerivative:(I)D (1, 4)
	26 dmul (1, 4)
	27 dadd (1, 4)
	28 dstore_2 (1, 4)
	29 iinc (1, 4)
	30 #4 (1, 4)
	31 -89 (1, 4)
	32 goto (1, 4)
	33 -24 (1, 4)
	35 dload_2 (0, 0)
	36 dreturn (0, 0)

Method: compose
	0 new (0, 0)
	1 org/apache/commons/math3/analysis/differentiation/SparseGradient (0, 0)
	3 dup (0, 0)
	4 dload_1 (0, 0)
	5 dload_3 (0, 0)
	6 aload_0 (0, 0)
	7 getfield (0, 0)
	8 org/apache/commons/math3/analysis/differentiation/SparseGradient.derivatives:Ljava/util/Map; (0, 0)
	10 invokespecial (0, 0)
	11 org/apache/commons/math3/analysis/differentiation/SparseGradient.<init>:(DDLjava/util/Map;)V (0, 0)
	13 areturn (0, 0)

Method: linearCombination
	0 aload_0 (0, 0)
	1 aload_1 (0, 0)
	2 checkcast (0, 0)
	3 [Lorg/apache/commons/math3/analysis/differentiation/SparseGradient; (0, 0)
	5 aload_2 (0, 0)
	6 checkcast (0, 0)
	7 [Lorg/apache/commons/math3/analysis/differentiation/SparseGradient; (0, 0)
	9 invokevirtual (0, 0)
	10 org/apache/commons/math3/analysis/differentiation/SparseGradient.linearCombination:([Lorg/apache/commons/math3/analysis/differentiation/SparseGradient;[Lorg/apache/commons/math3/analysis/differentiation/SparseGradient;)Lorg/apache/commons/math3/analysis/differentiation/SparseGradient; (0, 0)
	12 areturn (0, 0)

Method: equals
	0 aload_0 (1, 1)
	1 aload_1 (1, 1)
	2 if_acmpne (1, 1)
	3 5 (1, 1)
	5 iconst_1 (1, 1)
	6 ireturn (1, 1)
	7 aload_1 (1, 1)
	8 instanceof (1, 1)
	9 org/apache/commons/math3/analysis/differentiation/SparseGradient (1, 1)
	11 ifeq (1, 1)
	12 153 (1, 1)
	14 aload_1 (1, 1)
	15 checkcast (1, 1)
	16 org/apache/commons/math3/analysis/differentiation/SparseGradient (1, 1)
	18 astore_2 (1, 1)
	19 aload_0 (2, 1)
	20 getfield (2, 1)
	21 org/apache/commons/math3/analysis/differentiation/SparseGradient.value:D (2, 1)
	23 aload_2 (2, 1)
	24 getfield (2, 1)
	25 org/apache/commons/math3/analysis/differentiation/SparseGradient.value:D (2, 1)
	27 iconst_1 (2, 1)
	28 invokestatic (2, 1)
	29 org/apache/commons/math3/util/Precision.equals:(DDI)Z (2, 1)
	31 ifne (2, 1)
	32 5 (2, 1)
	34 iconst_0 (2, 1)
	35 ireturn (2, 1)
	36 aload_0 (2, 1)
	37 getfield (2, 1)
	38 org/apache/commons/math3/analysis/differentiation/SparseGradient.derivatives:Ljava/util/Map; (2, 1)
	40 invokeinterface (2, 1)
	41 java/util/Map.get:(Ljava/lang/Object;)Ljava/lang/Object; (2, 1)
	43 0 (2, 1)
	45 aload_2 (2, 1)
	46 getfield (2, 1)
	47 org/apache/commons/math3/analysis/differentiation/SparseGradient.derivatives:Ljava/util/Map; (2, 1)
	49 invokeinterface (2, 1)
	50 java/util/Map.get:(Ljava/lang/Object;)Ljava/lang/Object; (2, 1)
	52 0 (2, 1)
	54 if_icmpeq (2, 1)
	55 5 (2, 1)
	57 iconst_0 (2, 1)
	58 ireturn (2, 1)
	59 aload_0 (2, 4)
	60 getfield (2, 4)
	61 org/apache/commons/math3/analysis/differentiation/SparseGradient.derivatives:Ljava/util/Map; (2, 4)
	63 invokeinterface (2, 4)
	64 java/util/Map.java/util/Set (2, 4)
	66 0 (2, 4)
	68 invokeinterface (2, 4)
	69 java/util/Set.java/util/Iterator (2, 4)
	71 0 (2, 4)
	73 astore_3 (2, 4)
	74 aload_3 (2, 4)
	75 invokeinterface (2, 4)
	76 java/util/Iterator.next:()Ljava/lang/Object; (2, 4)
	78 0 (2, 4)
	80 ifeq (2, 4)
	81 82 (2, 4)
	83 aload_3 (2, 4)
	84 invokeinterface (2, 4)
	85 java/util/Iterator.java/util/Map$Entry (2, 4)
	87 0 (2, 4)
	89 checkcast (2, 4)
	90 java/util/Map$Entry (2, 4)
	92 astore (2, 4)
	93 #4 (2, 4)
	94 aload_2 (3, 1)
	95 getfield (3, 1)
	96 org/apache/commons/math3/analysis/differentiation/SparseGradient.derivatives:Ljava/util/Map; (3, 1)
	98 aload (3, 1)
	99 #4 (3, 1)
	100 invokeinterface (3, 1)
	101 java/util/Map$Entry.getValue:()Ljava/lang/Object; (3, 1)
	103 0 (3, 1)
	105 invokeinterface (3, 1)
	106 java/util/Map.org/apache/commons/math3/util/MathUtils (3, 1)
	108 0 (3, 1)
	110 ifne (3, 1)
	111 5 (3, 1)
	113 iconst_0 (3, 1)
	114 ireturn (3, 1)
	115 aload (3, 1)
	116 #4 (3, 1)
	117 invokeinterface (3, 1)
	118 java/util/Map$Entry.java/lang/Double (3, 1)
	120 0 (3, 1)
	122 checkcast (3, 1)
	123 java/lang/Double (3, 1)
	125 invokevirtual (3, 1)
	126 java/lang/Double.doubleValue:()D (3, 1)
	128 aload_2 (3, 1)
	129 getfield (3, 1)
	130 org/apache/commons/math3/analysis/differentiation/SparseGradient.derivatives:Ljava/util/Map; (3, 1)
	132 aload (3, 1)
	133 #4 (3, 1)
	134 invokeinterface (3, 1)
	135 java/util/Map$Entry.getValue:()Ljava/lang/Object; (3, 1)
	137 0 (3, 1)
	139 invokeinterface (3, 1)
	140 java/util/Map.java/lang/Integer (3, 1)
	142 0 (3, 1)
	144 checkcast (3, 1)
	145 java/lang/Double (3, 1)
	147 invokevirtual (3, 1)
	148 java/lang/Double.doubleValue:()D (3, 1)
	150 iconst_1 (3, 1)
	151 invokestatic (3, 1)
	152 org/apache/commons/math3/util/Precision.equals:(DDI)Z (3, 1)
	154 ifne (3, 1)
	155 5 (3, 1)
	157 iconst_0 (3, 1)
	158 ireturn (3, 1)
	159 goto (1, 1)
	160 -85 (1, 1)
	162 iconst_1 (1, 1)
	163 ireturn (1, 1)
	164 iconst_0 (0, 0)
	165 ireturn (0, 0)

Method: hashCode
	0 sipush (0, 0)
	1 743 (0, 0)
	3 sipush (0, 0)
	4 809 (0, 0)
	6 aload_0 (0, 0)
	7 getfield (0, 0)
	8 org/apache/commons/math3/analysis/differentiation/SparseGradient.value:D (0, 0)
	10 invokestatic (0, 0)
	11 org/apache/commons/math3/util/MathUtils.hash:(D)I (0, 0)
	13 imul (0, 0)
	14 iadd (0, 0)
	15 sipush (0, 0)
	16 167 (0, 0)
	18 aload_0 (0, 0)
	19 getfield (0, 0)
	20 org/apache/commons/math3/analysis/differentiation/SparseGradient.derivatives:Ljava/util/Map; (0, 0)
	22 invokeinterface (0, 0)
	23 java/util/Map.linearCombination:(DLorg/apache/commons/math3/analysis/differentiation/SparseGradient;DLorg/apache/commons/math3/analysis/differentiation/SparseGradient;DLorg/apache/commons/math3/analysis/differentiation/SparseGradient;DLorg/apache/commons/math3/analysis/differentiation/SparseGradient;)Lorg/apache/commons/math3/analysis/differentiation/SparseGradient; (0, 0)
	25 0 (0, 0)
	27 imul (0, 0)
	28 iadd (0, 0)
	29 ireturn (0, 0)

