Method: <init>
	0 aload_0 (0, 0)
	1 invokespecial (0, 0)
	4 aload_0 (0, 0)
	5 dload_1 (0, 0)
	6 putfield (0, 0)
	9 aload_0 (0, 0)
	10 new (0, 0)
	13 dup (0, 0)
	14 invokespecial (0, 0)
	17 putfield (0, 0)
	20 aload (1, 1)
	22 ifnull (1, 1)
	25 aload (2, 4)
	27 invokeinterface (2, 4)
	32 invokeinterface (2, 4)
	37 astore (2, 4)
	39 aload (2, 4)
	41 invokeinterface (2, 4)
	46 ifeq (2, 4)
	49 aload (2, 4)
	51 invokeinterface (2, 4)
	56 checkcast (2, 4)
	59 astore (2, 4)
	61 aload_0 (2, 4)
	62 getfield (2, 4)
	65 aload (2, 4)
	67 invokeinterface (2, 4)
	72 dload_3 (2, 4)
	73 aload (2, 4)
	75 invokeinterface (2, 4)
	80 checkcast (2, 4)
	83 invokevirtual (2, 4)
	86 dmul (2, 4)
	87 invokestatic (2, 4)
	90 invokeinterface (2, 4)
	95 pop (2, 4)
	96 goto (1, 1)
	99 return (0, 0)

Method: createConstant
	0 new (0, 0)
	3 dup (0, 0)
	4 dload_0 (0, 0)
	5 invokestatic (0, 0)
	8 invokespecial (0, 0)
	11 areturn (0, 0)

Method: createVariable
	0 new (0, 0)
	3 dup (0, 0)
	4 dload_1 (0, 0)
	5 iload_0 (0, 0)
	6 invokestatic (0, 0)
	9 dconst_1 (0, 0)
	10 invokestatic (0, 0)
	13 invokestatic (0, 0)
	16 invokespecial (0, 0)
	19 areturn (0, 0)

Method: numVars
	0 aload_0 (0, 0)
	1 getfield (0, 0)
	4 invokeinterface (0, 0)
	9 ireturn (0, 0)

Method: getDerivative
	0 aload_0 (0, 0)
	1 getfield (0, 0)
	4 iload_1 (0, 0)
	5 invokestatic (0, 0)
	8 invokeinterface (0, 0)
	13 checkcast (0, 0)
	16 astore_2 (0, 0)
	17 aload_2 (0, 0)
	18 ifnonnull (0, 0)
	21 dconst_0 (0, 0)
	22 goto (0, 0)
	25 aload_2 (0, 0)
	26 invokevirtual (0, 0)
	29 dreturn (0, 0)

Method: getValue
	0 aload_0 (0, 0)
	1 getfield (0, 0)
	4 dreturn (0, 0)

Method: getReal
	0 aload_0 (0, 0)
	1 getfield (0, 0)
	4 dreturn (0, 0)

Method: add
	0 aload_0 (0, 0)
	1 aload_1 (0, 0)
	2 checkcast (0, 0)
	5 invokevirtual (0, 0)
	8 areturn (0, 0)

Method: addInPlace
	0 aload_0 (0, 0)
	1 dup (0, 0)
	2 getfield (0, 0)
	5 aload_1 (0, 0)
	6 getfield (0, 0)
	9 dadd (0, 0)
	10 putfield (0, 0)
	13 aload_1 (1, 4)
	14 getfield (1, 4)
	17 invokeinterface (1, 4)
	22 invokeinterface (1, 4)
	27 astore_2 (1, 4)
	28 aload_2 (1, 4)
	29 invokeinterface (1, 4)
	34 ifeq (1, 4)
	37 aload_2 (1, 4)
	38 invokeinterface (1, 4)
	43 checkcast (1, 4)
	46 astore_3 (1, 4)
	47 aload_3 (1, 4)
	48 invokeinterface (1, 4)
	53 checkcast (1, 4)
	56 invokevirtual (1, 4)
	59 istore (1, 4)
	61 aload_0 (1, 4)
	62 getfield (1, 4)
	65 iload (1, 4)
	67 invokestatic (1, 4)
	70 invokeinterface (1, 4)
	75 checkcast (1, 4)
	78 astore (1, 4)
	80 aload (2, 1)
	82 ifnonnull (2, 1)
	85 aload_0 (2, 1)
	86 getfield (2, 1)
	89 iload (2, 1)
	91 invokestatic (2, 1)
	94 aload_3 (2, 1)
	95 invokeinterface (2, 1)
	100 invokeinterface (2, 1)
	105 pop (2, 1)
	106 goto (2, 1)
	109 aload_0 (2, 2)
	110 getfield (2, 2)
	113 iload (2, 2)
	115 invokestatic (2, 2)
	118 aload (2, 2)
	120 invokevirtual (2, 2)
	123 aload_3 (2, 2)
	124 invokeinterface (2, 2)
	129 checkcast (2, 2)
	132 invokevirtual (2, 2)
	135 dadd (2, 2)
	136 invokestatic (2, 2)
	139 invokeinterface (2, 2)
	144 pop (2, 2)
	145 goto (0, 4)
	148 return (0, 0)

Method: subtract
	0 aload_0 (0, 0)
	1 aload_1 (0, 0)
	2 checkcast (0, 0)
	5 invokevirtual (0, 0)
	8 areturn (0, 0)

Method: multiply
	0 aload_0 (0, 0)
	1 iload_1 (0, 0)
	2 invokevirtual (0, 0)
	5 areturn (0, 0)

Method: multiplyInPlace
	0 aload_0 (1, 4)
	1 getfield (1, 4)
	4 invokeinterface (1, 4)
	9 invokeinterface (1, 4)
	14 astore_2 (1, 4)
	15 aload_2 (1, 4)
	16 invokeinterface (1, 4)
	21 ifeq (1, 4)
	24 aload_2 (1, 4)
	25 invokeinterface (1, 4)
	30 checkcast (1, 4)
	33 astore_3 (1, 4)
	34 aload_0 (1, 4)
	35 getfield (1, 4)
	38 aload_3 (1, 4)
	39 invokeinterface (1, 4)
	44 aload_1 (1, 4)
	45 getfield (1, 4)
	48 aload_3 (1, 4)
	49 invokeinterface (1, 4)
	54 checkcast (1, 4)
	57 invokevirtual (1, 4)
	60 dmul (1, 4)
	61 invokestatic (1, 4)
	64 invokeinterface (1, 4)
	69 pop (1, 4)
	70 goto (0, 0)
	73 aload_1 (1, 4)
	74 getfield (1, 4)
	77 invokeinterface (1, 4)
	82 invokeinterface (1, 4)
	87 astore_2 (1, 4)
	88 aload_2 (1, 4)
	89 invokeinterface (1, 4)
	94 ifeq (1, 4)
	97 aload_2 (1, 4)
	98 invokeinterface (1, 4)
	103 checkcast (1, 4)
	106 astore_3 (1, 4)
	107 aload_3 (1, 4)
	108 invokeinterface (1, 4)
	113 checkcast (1, 4)
	116 invokevirtual (1, 4)
	119 istore (1, 4)
	121 aload_0 (1, 4)
	122 getfield (1, 4)
	125 iload (1, 4)
	127 invokestatic (1, 4)
	130 invokeinterface (1, 4)
	135 checkcast (1, 4)
	138 astore (1, 4)
	140 aload (2, 1)
	142 ifnonnull (2, 1)
	145 aload_0 (2, 1)
	146 getfield (2, 1)
	149 iload (2, 1)
	151 invokestatic (2, 1)
	154 aload_0 (2, 1)
	155 getfield (2, 1)
	158 aload_3 (2, 1)
	159 invokeinterface (2, 1)
	164 checkcast (2, 1)
	167 invokevirtual (2, 1)
	170 dmul (2, 1)
	171 invokestatic (2, 1)
	174 invokeinterface (2, 1)
	179 pop (2, 1)
	180 goto (2, 1)
	183 aload_0 (2, 2)
	184 getfield (2, 2)
	187 iload (2, 2)
	189 invokestatic (2, 2)
	192 aload (2, 2)
	194 invokevirtual (2, 2)
	197 aload_0 (2, 2)
	198 getfield (2, 2)
	201 aload_3 (2, 2)
	202 invokeinterface (2, 2)
	207 checkcast (2, 2)
	210 invokevirtual (2, 2)
	213 dmul (2, 2)
	214 dadd (2, 2)
	215 invokestatic (2, 2)
	218 invokeinterface (2, 2)
	223 pop (2, 2)
	224 goto (0, 4)
	227 aload_0 (0, 4)
	228 dup (0, 4)
	229 getfield (0, 4)
	232 aload_1 (0, 4)
	233 getfield (0, 4)
	236 dmul (0, 4)
	237 putfield (0, 4)
	240 return (0, 0)

Method: divide
	0 aload_0 (0, 0)
	1 aload_1 (0, 0)
	2 checkcast (0, 0)
	5 invokevirtual (0, 0)
	8 areturn (0, 0)

Method: negate
	0 aload_0 (0, 0)
	1 invokevirtual (0, 0)
	4 areturn (0, 0)

Method: getField
	0 new (0, 0)
	3 dup (0, 0)
	4 aload_0 (0, 0)
	5 invokespecial (0, 0)
	8 areturn (0, 0)

Method: remainder
	0 aload_0 (0, 0)
	1 dload_1 (0, 0)
	2 invokevirtual (0, 0)
	5 areturn (0, 0)

Method: abs
	0 aload_0 (0, 0)
	1 invokevirtual (0, 0)
	4 areturn (0, 0)

Method: ceil
	0 aload_0 (0, 0)
	1 invokevirtual (0, 0)
	4 areturn (0, 0)

Method: floor
	0 aload_0 (0, 0)
	1 invokevirtual (0, 0)
	4 areturn (0, 0)

Method: rint
	0 aload_0 (0, 0)
	1 invokevirtual (0, 0)
	4 areturn (0, 0)

Method: round
	0 aload_0 (0, 0)
	1 getfield (0, 0)
	4 invokestatic (0, 0)
	7 lreturn (0, 0)

Method: signum
	0 aload_0 (0, 0)
	1 invokevirtual (0, 0)
	4 areturn (0, 0)

Method: copySign
	0 aload_0 (0, 0)
	1 aload_1 (0, 0)
	2 checkcast (0, 0)
	5 invokevirtual (0, 0)
	8 areturn (0, 0)

Method: scalb
	0 aload_0 (0, 0)
	1 iload_1 (0, 0)
	2 invokevirtual (0, 0)
	5 areturn (0, 0)

Method: hypot
	0 aload_0 (0, 0)
	1 aload_1 (0, 0)
	2 checkcast (0, 0)
	5 invokevirtual (0, 0)
	8 areturn (0, 0)

Method: reciprocal
	0 aload_0 (0, 0)
	1 invokevirtual (0, 0)
	4 areturn (0, 0)

Method: sqrt
	0 aload_0 (0, 0)
	1 invokevirtual (0, 0)
	4 areturn (0, 0)

Method: cbrt
	0 aload_0 (0, 0)
	1 invokevirtual (0, 0)
	4 areturn (0, 0)

Method: rootN
	0 aload_0 (0, 0)
	1 iload_1 (0, 0)
	2 invokevirtual (0, 0)
	5 areturn (0, 0)

Method: pow
	0 aload_0 (0, 0)
	1 dload_1 (0, 0)
	2 invokevirtual (0, 0)
	5 areturn (0, 0)

Method: exp
	0 aload_0 (0, 0)
	1 invokevirtual (0, 0)
	4 areturn (0, 0)

Method: expm1
	0 aload_0 (0, 0)
	1 invokevirtual (0, 0)
	4 areturn (0, 0)

Method: log
	0 aload_0 (0, 0)
	1 invokevirtual (0, 0)
	4 areturn (0, 0)

Method: log10
	0 new (0, 0)
	3 dup (0, 0)
	4 aload_0 (0, 0)
	5 getfield (0, 0)
	8 invokestatic (0, 0)
	11 dconst_1 (0, 0)
	12 ldc2_w (0, 0)
	15 invokestatic (0, 0)
	18 aload_0 (0, 0)
	19 getfield (0, 0)
	22 dmul (0, 0)
	23 ddiv (0, 0)
	24 aload_0 (0, 0)
	25 getfield (0, 0)
	28 invokespecial (0, 0)
	31 areturn (0, 0)

Method: log1p
	0 aload_0 (0, 0)
	1 invokevirtual (0, 0)
	4 areturn (0, 0)

Method: cos
	0 aload_0 (0, 0)
	1 invokevirtual (0, 0)
	4 areturn (0, 0)

Method: sin
	0 aload_0 (0, 0)
	1 invokevirtual (0, 0)
	4 areturn (0, 0)

Method: tan
	0 aload_0 (0, 0)
	1 invokevirtual (0, 0)
	4 areturn (0, 0)

Method: acos
	0 aload_0 (0, 0)
	1 invokevirtual (0, 0)
	4 areturn (0, 0)

Method: asin
	0 aload_0 (0, 0)
	1 invokevirtual (0, 0)
	4 areturn (0, 0)

Method: atan
	0 aload_0 (0, 0)
	1 invokevirtual (0, 0)
	4 areturn (0, 0)

Method: atan2
	0 aload_0 (0, 0)
	1 aload_1 (0, 0)
	2 checkcast (0, 0)
	5 invokevirtual (0, 0)
	8 areturn (0, 0)

Method: cosh
	0 aload_0 (0, 0)
	1 invokevirtual (0, 0)
	4 areturn (0, 0)

Method: sinh
	0 aload_0 (0, 0)
	1 invokevirtual (0, 0)
	4 areturn (0, 0)

Method: tanh
	0 aload_0 (0, 0)
	1 invokevirtual (0, 0)
	4 areturn (0, 0)

Method: acosh
	0 aload_0 (0, 0)
	1 invokevirtual (0, 0)
	4 areturn (0, 0)

Method: asinh
	0 aload_0 (0, 0)
	1 invokevirtual (0, 0)
	4 areturn (0, 0)

Method: atanh
	0 aload_0 (0, 0)
	1 invokevirtual (0, 0)
	4 areturn (0, 0)

Method: toDegrees
	0 new (0, 0)
	3 dup (0, 0)
	4 aload_0 (0, 0)
	5 getfield (0, 0)
	8 invokestatic (0, 0)
	11 dconst_1 (0, 0)
	12 invokestatic (0, 0)
	15 aload_0 (0, 0)
	16 getfield (0, 0)
	19 invokespecial (0, 0)
	22 areturn (0, 0)

Method: toRadians
	0 new (0, 0)
	3 dup (0, 0)
	4 aload_0 (0, 0)
	5 getfield (0, 0)
	8 invokestatic (0, 0)
	11 dconst_1 (0, 0)
	12 invokestatic (0, 0)
	15 aload_0 (0, 0)
	16 getfield (0, 0)
	19 invokespecial (0, 0)
	22 areturn (0, 0)

Method: taylor
	0 aload_0 (0, 0)
	1 getfield (0, 0)
	4 dstore_2 (0, 0)
	5 iconst_0 (1, 4)
	6 istore (1, 4)
	8 iload (1, 4)
	10 aload_1 (1, 4)
	11 arraylength (1, 4)
	12 if_icmpge (1, 4)
	15 dload_2 (1, 4)
	16 aload_1 (1, 4)
	17 iload (1, 4)
	19 daload (1, 4)
	20 aload_0 (1, 4)
	21 iload (1, 4)
	23 invokevirtual (1, 4)
	26 dmul (1, 4)
	27 dadd (1, 4)
	28 dstore_2 (1, 4)
	29 iinc (1, 4)
	32 goto (1, 4)
	35 dload_2 (0, 0)
	36 dreturn (0, 0)

Method: compose
	0 new (0, 0)
	3 dup (0, 0)
	4 dload_1 (0, 0)
	5 dload_3 (0, 0)
	6 aload_0 (0, 0)
	7 getfield (0, 0)
	10 invokespecial (0, 0)
	13 areturn (0, 0)

Method: linearCombination
	0 aload_0 (0, 0)
	1 aload_1 (0, 0)
	2 checkcast (0, 0)
	5 aload_2 (0, 0)
	6 checkcast (0, 0)
	9 invokevirtual (0, 0)
	12 areturn (0, 0)

Method: equals
	0 aload_0 (1, 1)
	1 aload_1 (1, 1)
	2 if_acmpne (1, 1)
	5 iconst_1 (1, 1)
	6 ireturn (1, 1)
	7 aload_1 (1, 1)
	8 instanceof (1, 1)
	11 ifeq (1, 1)
	14 aload_1 (1, 1)
	15 checkcast (1, 1)
	18 astore_2 (1, 1)
	19 aload_0 (2, 1)
	20 getfield (2, 1)
	23 aload_2 (2, 1)
	24 getfield (2, 1)
	27 iconst_1 (2, 1)
	28 invokestatic (2, 1)
	31 ifne (2, 1)
	34 iconst_0 (2, 1)
	35 ireturn (2, 1)
	36 aload_0 (2, 1)
	37 getfield (2, 1)
	40 invokeinterface (2, 1)
	45 aload_2 (2, 1)
	46 getfield (2, 1)
	49 invokeinterface (2, 1)
	54 if_icmpeq (2, 1)
	57 iconst_0 (2, 1)
	58 ireturn (2, 1)
	59 aload_0 (2, 4)
	60 getfield (2, 4)
	63 invokeinterface (2, 4)
	68 invokeinterface (2, 4)
	73 astore_3 (2, 4)
	74 aload_3 (2, 4)
	75 invokeinterface (2, 4)
	80 ifeq (2, 4)
	83 aload_3 (2, 4)
	84 invokeinterface (2, 4)
	89 checkcast (2, 4)
	92 astore (2, 4)
	94 aload_2 (3, 1)
	95 getfield (3, 1)
	98 aload (3, 1)
	100 invokeinterface (3, 1)
	105 invokeinterface (3, 1)
	110 ifne (3, 1)
	113 iconst_0 (3, 1)
	114 ireturn (3, 1)
	115 aload (3, 1)
	117 invokeinterface (3, 1)
	122 checkcast (3, 1)
	125 invokevirtual (3, 1)
	128 aload_2 (3, 1)
	129 getfield (3, 1)
	132 aload (3, 1)
	134 invokeinterface (3, 1)
	139 invokeinterface (3, 1)
	144 checkcast (3, 1)
	147 invokevirtual (3, 1)
	150 iconst_1 (3, 1)
	151 invokestatic (3, 1)
	154 ifne (3, 1)
	157 iconst_0 (3, 1)
	158 ireturn (3, 1)
	159 goto (1, 1)
	162 iconst_1 (1, 1)
	163 ireturn (1, 1)
	164 iconst_0 (0, 0)
	165 ireturn (0, 0)

Method: hashCode
	0 sipush (0, 0)
	3 sipush (0, 0)
	6 aload_0 (0, 0)
	7 getfield (0, 0)
	10 invokestatic (0, 0)
	13 imul (0, 0)
	14 iadd (0, 0)
	15 sipush (0, 0)
	18 aload_0 (0, 0)
	19 getfield (0, 0)
	22 invokeinterface (0, 0)
	27 imul (0, 0)
	28 iadd (0, 0)
	29 ireturn (0, 0)

