Method: <init>
	0 aload_0 (1, 4)
	1 invokespecial (1, 4)
	2 java/lang/Object.<init>:()V (1, 4)
	4 aload_0 (1, 4)
	5 aload_1 (1, 4)
	6 putfield (1, 4)
	7 org/apache/commons/math3/transform/FastCosineTransformer.normalization:Lorg/apache/commons/math3/transform/DctNormalization; (1, 4)
	9 return (0, 0)

Method: transform
	0 aload_1 (0, 0)
	1 dload_2 (0, 0)
	2 dload (0, 0)
	3 #4 (0, 0)
	4 iload (0, 0)
	5 #6 (0, 0)
	6 invokestatic (0, 0)
	7 org/apache/commons/math3/analysis/FunctionUtils.sample:(Lorg/apache/commons/math3/analysis/UnivariateFunction;DDI)[D (0, 0)
	9 astore (0, 0)
	10 #8 (0, 0)
	11 aload_0 (1, 4)
	12 aload (1, 4)
	13 #8 (1, 4)
	14 aload (1, 4)
	15 #7 (1, 4)
	16 invokevirtual (1, 4)
	17 org/apache/commons/math3/transform/FastCosineTransformer.transform:([DLorg/apache/commons/math3/transform/TransformType;)[D (1, 4)
	19 areturn (0, 4)

Method: fct
	0 aload_1 (1, 4)
	1 arraylength (1, 4)
	2 newarray (1, 4)
	3 7 (1, 4)
	4 astore_2 (1, 4)
	5 aload_1 (1, 4)
	6 arraylength (1, 4)
	7 iconst_1 (1, 4)
	8 isub (1, 4)
	9 istore_3 (1, 4)
	10 iload_3 (2, 1)
	11 i2l (2, 1)
	12 invokestatic (2, 1)
	13 org/apache/commons/math3/util/ArithmeticUtils.isPowerOfTwo:(J)Z (2, 1)
	15 ifne (2, 1)
	16 26 (2, 1)
	18 new (2, 1)
	19 org/apache/commons/math3/exception/MathIllegalArgumentException (2, 1)
	21 dup (2, 1)
	22 getstatic (2, 1)
	23 org/apache/commons/math3/exception/util/LocalizedFormats.NOT_POWER_OF_TWO_PLUS_ONE:Lorg/apache/commons/math3/exception/util/LocalizedFormats; (2, 1)
	25 iconst_1 (2, 1)
	26 anewarray (2, 1)
	27 java/lang/Object (2, 1)
	29 dup (2, 1)
	30 iconst_0 (2, 1)
	31 aload_1 (2, 1)
	32 arraylength (2, 1)
	33 invokestatic (2, 1)
	34 java/lang/Integer.valueOf:(I)Ljava/lang/Integer; (2, 1)
	36 aastore (2, 1)
	37 invokespecial (2, 1)
	38 org/apache/commons/math3/exception/MathIllegalArgumentException.<init>:(Lorg/apache/commons/math3/exception/util/Localizable;[Ljava/lang/Object;)V (2, 1)
	40 athrow (2, 1)
	41 iload_3 (2, 1)
	42 iconst_1 (2, 1)
	43 if_icmpne (2, 1)
	44 33 (2, 1)
	46 aload_2 (3, 4)
	47 iconst_0 (3, 4)
	48 ldc2_w (3, 4)
	49 0.5 (3, 4)
	51 aload_1 (3, 4)
	52 iconst_0 (3, 4)
	53 daload (3, 4)
	54 aload_1 (3, 4)
	55 iconst_1 (3, 4)
	56 daload (3, 4)
	57 dadd (3, 4)
	58 dmul (3, 4)
	59 dastore (3, 4)
	60 aload_2 (4, 4)
	61 iconst_1 (4, 4)
	62 ldc2_w (4, 4)
	63 0.5 (4, 4)
	65 aload_1 (4, 4)
	66 iconst_0 (4, 4)
	67 daload (4, 4)
	68 aload_1 (4, 4)
	69 iconst_1 (4, 4)
	70 daload (4, 4)
	71 dsub (4, 4)
	72 dmul (4, 4)
	73 dastore (4, 4)
	74 aload_2 (5, 4)
	75 areturn (5, 4)
	76 iload_3 (2, 4)
	77 newarray (2, 4)
	78 7 (2, 4)
	79 astore (2, 4)
	80 #4 (2, 4)
	81 aload (2, 4)
	82 #4 (2, 4)
	83 iconst_0 (2, 4)
	84 ldc2_w (2, 4)
	85 0.5 (2, 4)
	87 aload_1 (2, 4)
	88 iconst_0 (2, 4)
	89 daload (2, 4)
	90 aload_1 (2, 4)
	91 iload_3 (2, 4)
	92 daload (2, 4)
	93 dadd (2, 4)
	94 dmul (2, 4)
	95 dastore (2, 4)
	96 aload (2, 4)
	97 #4 (2, 4)
	98 iload_3 (2, 4)
	99 iconst_1 (2, 4)
	100 ishr (2, 4)
	101 aload_1 (2, 4)
	102 iload_3 (2, 4)
	103 iconst_1 (2, 4)
	104 ishr (2, 4)
	105 daload (2, 4)
	106 dastore (2, 4)
	107 ldc2_w (3, 4)
	108 0.5 (3, 4)
	110 aload_1 (3, 4)
	111 iconst_0 (3, 4)
	112 daload (3, 4)
	113 aload_1 (3, 4)
	114 iload_3 (3, 4)
	115 daload (3, 4)
	116 dsub (3, 4)
	117 dmul (3, 4)
	118 dstore (3, 4)
	119 #5 (3, 4)
	120 iconst_1 (4, 4)
	121 istore (4, 4)
	122 #7 (4, 4)
	123 iload (4, 4)
	124 #7 (4, 4)
	125 iload_3 (4, 4)
	126 iconst_1 (4, 4)
	127 ishr (4, 4)
	128 if_icmpge (4, 4)
	129 109 (4, 4)
	131 ldc2_w (4, 4)
	132 0.5 (4, 4)
	134 aload_1 (4, 4)
	135 iload (4, 4)
	136 #7 (4, 4)
	137 daload (4, 4)
	138 aload_1 (4, 4)
	139 iload_3 (4, 4)
	140 iload (4, 4)
	141 #7 (4, 4)
	142 isub (4, 4)
	143 daload (4, 4)
	144 dadd (4, 4)
	145 dmul (4, 4)
	146 dstore (4, 4)
	147 #8 (4, 4)
	148 iload (4, 4)
	149 #7 (4, 4)
	150 i2d (4, 4)
	151 ldc2_w (4, 4)
	152 3.141592653589793 (4, 4)
	154 dmul (4, 4)
	155 iload_3 (4, 4)
	156 i2d (4, 4)
	157 ddiv (4, 4)
	158 invokestatic (4, 4)
	159 org/apache/commons/math3/util/FastMath.sin:(D)D (4, 4)
	161 aload_1 (4, 4)
	162 iload (4, 4)
	163 #7 (4, 4)
	164 daload (4, 4)
	165 aload_1 (4, 4)
	166 iload_3 (4, 4)
	167 iload (4, 4)
	168 #7 (4, 4)
	169 isub (4, 4)
	170 daload (4, 4)
	171 dsub (4, 4)
	172 dmul (4, 4)
	173 dstore (4, 4)
	174 #10 (4, 4)
	175 iload (4, 4)
	176 #7 (4, 4)
	177 i2d (4, 4)
	178 ldc2_w (4, 4)
	179 3.141592653589793 (4, 4)
	181 dmul (4, 4)
	182 iload_3 (4, 4)
	183 i2d (4, 4)
	184 ddiv (4, 4)
	185 invokestatic (4, 4)
	186 org/apache/commons/math3/util/FastMath.cos:(D)D (4, 4)
	188 aload_1 (4, 4)
	189 iload (4, 4)
	190 #7 (4, 4)
	191 daload (4, 4)
	192 aload_1 (4, 4)
	193 iload_3 (4, 4)
	194 iload (4, 4)
	195 #7 (4, 4)
	196 isub (4, 4)
	197 daload (4, 4)
	198 dsub (4, 4)
	199 dmul (4, 4)
	200 dstore (4, 4)
	201 #12 (4, 4)
	202 aload (4, 4)
	203 #4 (4, 4)
	204 iload (4, 4)
	205 #7 (4, 4)
	206 dload (4, 4)
	207 #8 (4, 4)
	208 dload (4, 4)
	209 #10 (4, 4)
	210 dsub (4, 4)
	211 dastore (4, 4)
	212 aload (4, 4)
	213 #4 (4, 4)
	214 iload_3 (4, 4)
	215 iload (4, 4)
	216 #7 (4, 4)
	217 isub (4, 4)
	218 dload (4, 4)
	219 #8 (4, 4)
	220 dload (4, 4)
	221 #10 (4, 4)
	222 dadd (4, 4)
	223 dastore (4, 4)
	224 dload (4, 4)
	225 #5 (4, 4)
	226 dload (4, 4)
	227 #12 (4, 4)
	228 dadd (4, 4)
	229 dstore (4, 4)
	230 #5 (4, 4)
	231 iinc (4, 4)
	232 #7 (4, 4)
	233 -89 (4, 4)
	234 goto (4, 4)
	235 -111 (4, 4)
	237 new (5, 4)
	238 org/apache/commons/math3/transform/FastFourierTransformer (5, 4)
	240 dup (5, 4)
	241 getstatic (5, 4)
	242 org/apache/commons/math3/transform/DftNormalization.STANDARD:Lorg/apache/commons/math3/transform/DftNormalization; (5, 4)
	244 invokespecial (5, 4)
	245 org/apache/commons/math3/transform/FastFourierTransformer.<init>:(Lorg/apache/commons/math3/transform/DftNormalization;)V (5, 4)
	247 astore (5, 4)
	248 #7 (5, 4)
	249 aload (6, 4)
	250 #7 (6, 4)
	251 aload (6, 4)
	252 #4 (6, 4)
	253 getstatic (6, 4)
	254 org/apache/commons/math3/transform/TransformType.FORWARD:Lorg/apache/commons/math3/transform/TransformType; (6, 4)
	256 invokevirtual (6, 4)
	257 org/apache/commons/math3/transform/FastFourierTransformer.transform:([DLorg/apache/commons/math3/transform/TransformType;)[Lorg/apache/commons/math3/complex/Complex; (6, 4)
	259 astore (6, 4)
	260 #8 (6, 4)
	261 aload_2 (8, 4)
	262 iconst_0 (8, 4)
	263 aload (8, 4)
	264 #8 (8, 4)
	265 iconst_0 (8, 4)
	266 aaload (8, 4)
	267 invokevirtual (8, 4)
	268 org/apache/commons/math3/complex/Complex.getReal:()D (8, 4)
	270 dastore (8, 4)
	271 aload_2 (9, 4)
	272 iconst_1 (9, 4)
	273 dload (9, 4)
	274 #5 (9, 4)
	275 dastore (9, 4)
	276 iconst_1 (10, 4)
	277 istore (10, 4)
	278 #9 (10, 4)
	279 iload (10, 4)
	280 #9 (10, 4)
	281 iload_3 (10, 4)
	282 iconst_1 (10, 4)
	283 ishr (10, 4)
	284 if_icmpge (10, 4)
	285 48 (10, 4)
	287 aload_2 (11, 4)
	288 iconst_2 (11, 4)
	289 iload (11, 4)
	290 #9 (11, 4)
	291 imul (11, 4)
	292 aload (11, 4)
	293 #8 (11, 4)
	294 iload (11, 4)
	295 #9 (11, 4)
	296 aaload (11, 4)
	297 invokevirtual (11, 4)
	298 org/apache/commons/math3/complex/Complex.getReal:()D (11, 4)
	300 dastore (11, 4)
	301 aload_2 (12, 4)
	302 iconst_2 (12, 4)
	303 iload (12, 4)
	304 #9 (12, 4)
	305 imul (12, 4)
	306 iconst_1 (12, 4)
	307 iadd (12, 4)
	308 aload_2 (12, 4)
	309 iconst_2 (12, 4)
	310 iload (12, 4)
	311 #9 (12, 4)
	312 imul (12, 4)
	313 iconst_1 (12, 4)
	314 isub (12, 4)
	315 daload (12, 4)
	316 aload (12, 4)
	317 #8 (12, 4)
	318 iload (12, 4)
	319 #9 (12, 4)
	320 aaload (12, 4)
	321 invokevirtual (12, 4)
	322 org/apache/commons/math3/complex/Complex.getImaginary:()D (12, 4)
	324 dsub (12, 4)
	325 dastore (12, 4)
	326 iinc (12, 4)
	327 #9 (12, 4)
	328 -89 (12, 4)
	329 goto (12, 4)
	330 -50 (12, 4)
	332 aload_2 (10, 4)
	333 iload_3 (10, 4)
	334 aload (10, 4)
	335 #8 (10, 4)
	336 iload_3 (10, 4)
	337 iconst_1 (10, 4)
	338 ishr (10, 4)
	339 aaload (10, 4)
	340 invokevirtual (10, 4)
	341 org/apache/commons/math3/complex/Complex.getReal:()D (10, 4)
	343 dastore (10, 4)
	344 aload_2 (11, 4)
	345 areturn (0, 4)

