Method: <init>
	0 aload_0 (1, 4)
	1 invokespecial (1, 4)
	2 java/lang/Object.<init>:()V (1, 4)
	4 aload_0 (1, 4)
	5 aload_1 (1, 4)
	6 putfield (1, 4)
	7 org/apache/commons/math3/transform/FastFourierTransformer.normalization:Lorg/apache/commons/math3/transform/DftNormalization; (1, 4)
	9 return (0, 0)

Method: bitReversalShuffle2
	0 aload_0 (0, 0)
	1 arraylength (0, 0)
	2 istore_2 (0, 0)
	3 getstatic (0, 0)
	4 org/apache/commons/math3/transform/FastFourierTransformer.$assertionsDisabled:Z (0, 0)
	6 ifne (0, 0)
	7 17 (0, 0)
	9 aload_1 (0, 0)
	10 arraylength (0, 0)
	11 iload_2 (0, 0)
	12 if_icmpeq (0, 0)
	13 11 (0, 0)
	15 new (0, 0)
	16 java/lang/AssertionError (0, 0)
	18 dup (0, 0)
	19 invokespecial (0, 0)
	20 java/lang/AssertionError.<init>:()V (0, 0)
	22 athrow (0, 0)
	23 iload_2 (0, 0)
	24 iconst_1 (0, 0)
	25 ishr (0, 0)
	26 istore_3 (0, 0)
	27 iconst_0 (0, 0)
	28 istore (0, 0)
	29 #4 (0, 0)
	30 iconst_0 (1, 4)
	31 istore (1, 4)
	32 #5 (1, 4)
	33 iload (1, 4)
	34 #5 (1, 4)
	35 iload_2 (1, 4)
	36 if_icmpge (1, 4)
	37 94 (1, 4)
	39 iload (2, 1)
	40 #5 (2, 1)
	41 iload (2, 1)
	42 #4 (2, 1)
	43 if_icmpge (2, 1)
	44 43 (2, 1)
	46 aload_0 (2, 1)
	47 iload (2, 1)
	48 #5 (2, 1)
	49 daload (2, 1)
	50 dstore (2, 1)
	51 #6 (2, 1)
	52 aload_0 (2, 1)
	53 iload (2, 1)
	54 #5 (2, 1)
	55 aload_0 (2, 1)
	56 iload (2, 1)
	57 #4 (2, 1)
	58 daload (2, 1)
	59 dastore (2, 1)
	60 aload_0 (2, 1)
	61 iload (2, 1)
	62 #4 (2, 1)
	63 dload (2, 1)
	64 #6 (2, 1)
	65 dastore (2, 1)
	66 aload_1 (2, 1)
	67 iload (2, 1)
	68 #5 (2, 1)
	69 daload (2, 1)
	70 dstore (2, 1)
	71 #6 (2, 1)
	72 aload_1 (2, 1)
	73 iload (2, 1)
	74 #5 (2, 1)
	75 aload_1 (2, 1)
	76 iload (2, 1)
	77 #4 (2, 1)
	78 daload (2, 1)
	79 dastore (2, 1)
	80 aload_1 (2, 1)
	81 iload (2, 1)
	82 #4 (2, 1)
	83 dload (2, 1)
	84 #6 (2, 1)
	85 dastore (2, 1)
	86 iload_3 (1, 4)
	87 istore (1, 4)
	88 #6 (1, 4)
	89 iload (2, 3)
	90 #6 (2, 3)
	91 iload (2, 3)
	92 #4 (2, 3)
	93 if_icmpgt (2, 3)
	94 24 (2, 3)
	96 iload (2, 3)
	97 #6 (2, 3)
	98 ifle (2, 3)
	99 19 (2, 3)
	101 iload (2, 3)
	102 #4 (2, 3)
	103 iload (2, 3)
	104 #6 (2, 3)
	105 isub (2, 3)
	106 istore (2, 3)
	107 #4 (2, 3)
	108 iload (2, 3)
	109 #6 (2, 3)
	110 iconst_1 (2, 3)
	111 ishr (2, 3)
	112 istore (2, 3)
	113 #6 (2, 3)
	114 goto (2, 3)
	115 -25 (2, 3)
	117 iload (1, 4)
	118 #4 (1, 4)
	119 iload (1, 4)
	120 #6 (1, 4)
	121 iadd (1, 4)
	122 istore (1, 4)
	123 #4 (1, 4)
	124 iinc (1, 4)
	125 #5 (1, 4)
	126 -89 (1, 4)
	127 goto (1, 4)
	128 -94 (1, 4)
	130 return (0, 0)

Method: normalizeTransformedData
	0 aload_0 (0, 0)
	1 iconst_0 (0, 0)
	2 aaload (0, 0)
	3 astore_3 (0, 0)
	4 aload_0 (0, 0)
	5 iconst_1 (0, 0)
	6 aaload (0, 0)
	7 astore (0, 0)
	8 #4 (0, 0)
	9 aload_3 (0, 0)
	10 arraylength (0, 0)
	11 istore (0, 0)
	12 #5 (0, 0)
	13 getstatic (0, 0)
	14 org/apache/commons/math3/transform/FastFourierTransformer.$assertionsDisabled:Z (0, 0)
	16 ifne (0, 0)
	17 19 (0, 0)
	19 aload (0, 0)
	20 #4 (0, 0)
	21 arraylength (0, 0)
	22 iload (0, 0)
	23 #5 (0, 0)
	24 if_icmpeq (0, 0)
	25 11 (0, 0)
	27 new (0, 0)
	28 java/lang/AssertionError (0, 0)
	30 dup (0, 0)
	31 invokespecial (0, 0)
	32 java/lang/AssertionError.<init>:()V (0, 0)
	34 athrow (0, 0)
	35 getstatic (1, 5)
	36 org/apache/commons/math3/transform/FastFourierTransformer$1.$SwitchMap$org$apache$commons$math3$transform$DftNormalization:[I (1, 5)
	38 aload_1 (1, 5)
	39 invokevirtual (1, 5)
	40 org/apache/commons/math3/transform/DftNormalization.ordinal:()I (1, 5)
	42 iaload (1, 5)
	43 lookupswitch (1, 5)
	44 1: 68 (1, 5)
	48 2: 120 (1, 5)
	68 aload_2 (2, 1)
	69 getstatic (2, 1)
	70 org/apache/commons/math3/transform/TransformType.INVERSE:Lorg/apache/commons/math3/transform/TransformType; (2, 1)
	72 if_acmpne (2, 1)
	73 104 (2, 1)
	75 dconst_1 (2, 1)
	76 iload (2, 1)
	77 #5 (2, 1)
	78 i2d (2, 1)
	79 ddiv (2, 1)
	80 dstore (2, 1)
	81 #6 (2, 1)
	82 iconst_0 (3, 4)
	83 istore (3, 4)
	84 #8 (3, 4)
	85 iload (3, 4)
	86 #8 (3, 4)
	87 iload (3, 4)
	88 #5 (3, 4)
	89 if_icmpge (3, 4)
	90 28 (3, 4)
	92 aload_3 (3, 4)
	93 iload (3, 4)
	94 #8 (3, 4)
	95 dup2 (3, 4)
	96 daload (3, 4)
	97 dload (3, 4)
	98 #6 (3, 4)
	99 dmul (3, 4)
	100 dastore (3, 4)
	101 aload (3, 4)
	102 #4 (3, 4)
	103 iload (3, 4)
	104 #8 (3, 4)
	105 dup2 (3, 4)
	106 daload (3, 4)
	107 dload (3, 4)
	108 #6 (3, 4)
	109 dmul (3, 4)
	110 dastore (3, 4)
	111 iinc (3, 4)
	112 #8 (3, 4)
	113 -89 (3, 4)
	114 goto (3, 4)
	115 -29 (3, 4)
	117 goto (1, 5)
	118 59 (1, 5)
	120 dconst_1 (1, 5)
	121 iload (1, 5)
	122 #5 (1, 5)
	123 i2d (1, 5)
	124 invokestatic (1, 5)
	125 org/apache/commons/math3/util/FastMath.sqrt:(D)D (1, 5)
	127 ddiv (1, 5)
	128 dstore (1, 5)
	129 #6 (1, 5)
	130 iconst_0 (2, 4)
	131 istore (2, 4)
	132 #8 (2, 4)
	133 iload (2, 4)
	134 #8 (2, 4)
	135 iload (2, 4)
	136 #5 (2, 4)
	137 if_icmpge (2, 4)
	138 28 (2, 4)
	140 aload_3 (2, 4)
	141 iload (2, 4)
	142 #8 (2, 4)
	143 dup2 (2, 4)
	144 daload (2, 4)
	145 dload (2, 4)
	146 #6 (2, 4)
	147 dmul (2, 4)
	148 dastore (2, 4)
	149 aload (2, 4)
	150 #4 (2, 4)
	151 iload (2, 4)
	152 #8 (2, 4)
	153 dup2 (2, 4)
	154 daload (2, 4)
	155 dload (2, 4)
	156 #6 (2, 4)
	157 dmul (2, 4)
	158 dastore (2, 4)
	159 iinc (2, 4)
	160 #8 (2, 4)
	161 -89 (2, 4)
	162 goto (2, 4)
	163 -29 (2, 4)
	165 goto (1, 5)
	166 11 (1, 5)
	168 new (1, 4)
	169 org/apache/commons/math3/exception/MathIllegalStateException (1, 4)
	171 dup (1, 4)
	172 invokespecial (1, 4)
	173 org/apache/commons/math3/exception/MathIllegalStateException.<init>:()V (1, 4)
	175 athrow (1, 4)
	176 return (0, 0)

Method: transformInPlace
	0 aload_0 (1, 1)
	1 arraylength (1, 1)
	2 iconst_2 (1, 1)
	3 if_icmpeq (1, 1)
	4 14 (1, 1)
	6 new (1, 1)
	7 org/apache/commons/math3/exception/DimensionMismatchException (1, 1)
	9 dup (1, 1)
	10 aload_0 (1, 1)
	11 arraylength (1, 1)
	12 iconst_2 (1, 1)
	13 invokespecial (1, 1)
	14 org/apache/commons/math3/exception/DimensionMismatchException.<init>:(II)V (1, 1)
	16 athrow (1, 1)
	17 aload_0 (0, 0)
	18 iconst_0 (0, 0)
	19 aaload (0, 0)
	20 astore_3 (0, 0)
	21 aload_0 (0, 0)
	22 iconst_1 (0, 0)
	23 aaload (0, 0)
	24 astore (0, 0)
	25 #4 (0, 0)
	26 aload_3 (1, 1)
	27 arraylength (1, 1)
	28 aload (1, 1)
	29 #4 (1, 1)
	30 arraylength (1, 1)
	31 if_icmpeq (1, 1)
	32 16 (1, 1)
	34 new (1, 1)
	35 org/apache/commons/math3/exception/DimensionMismatchException (1, 1)
	37 dup (1, 1)
	38 aload (1, 1)
	39 #4 (1, 1)
	40 arraylength (1, 1)
	41 aload_3 (1, 1)
	42 arraylength (1, 1)
	43 invokespecial (1, 1)
	44 org/apache/commons/math3/exception/DimensionMismatchException.<init>:(II)V (1, 1)
	46 athrow (1, 1)
	47 aload_3 (0, 0)
	48 arraylength (0, 0)
	49 istore (0, 0)
	50 #5 (0, 0)
	51 iload (1, 1)
	52 #5 (1, 1)
	53 i2l (1, 1)
	54 invokestatic (1, 1)
	55 org/apache/commons/math3/util/ArithmeticUtils.isPowerOfTwo:(J)Z (1, 1)
	57 ifne (1, 1)
	58 26 (1, 1)
	60 new (1, 1)
	61 org/apache/commons/math3/exception/MathIllegalArgumentException (1, 1)
	63 dup (1, 1)
	64 getstatic (1, 1)
	65 org/apache/commons/math3/exception/util/LocalizedFormats.NOT_POWER_OF_TWO_CONSIDER_PADDING:Lorg/apache/commons/math3/exception/util/LocalizedFormats; (1, 1)
	67 iconst_1 (1, 1)
	68 anewarray (1, 1)
	69 java/lang/Object (1, 1)
	71 dup (1, 1)
	72 iconst_0 (1, 1)
	73 iload (1, 1)
	74 #5 (1, 1)
	75 invokestatic (1, 1)
	76 java/lang/Integer.valueOf:(I)Ljava/lang/Integer; (1, 1)
	78 aastore (1, 1)
	79 invokespecial (1, 1)
	80 org/apache/commons/math3/exception/MathIllegalArgumentException.<init>:(Lorg/apache/commons/math3/exception/util/Localizable;[Ljava/lang/Object;)V (1, 1)
	82 athrow (1, 1)
	83 iload (1, 1)
	84 #5 (1, 1)
	85 iconst_1 (1, 1)
	86 if_icmpne (1, 1)
	87 4 (1, 1)
	89 return (1, 1)
	90 iload (1, 1)
	91 #5 (1, 1)
	92 iconst_2 (1, 1)
	93 if_icmpne (1, 1)
	94 66 (1, 1)
	96 aload_3 (1, 1)
	97 iconst_0 (1, 1)
	98 daload (1, 1)
	99 dstore (1, 1)
	100 #6 (1, 1)
	101 aload (1, 1)
	102 #4 (1, 1)
	103 iconst_0 (1, 1)
	104 daload (1, 1)
	105 dstore (1, 1)
	106 #8 (1, 1)
	107 aload_3 (1, 1)
	108 iconst_1 (1, 1)
	109 daload (1, 1)
	110 dstore (1, 1)
	111 #10 (1, 1)
	112 aload (1, 1)
	113 #4 (1, 1)
	114 iconst_1 (1, 1)
	115 daload (1, 1)
	116 dstore (1, 1)
	117 #12 (1, 1)
	118 aload_3 (1, 1)
	119 iconst_0 (1, 1)
	120 dload (1, 1)
	121 #6 (1, 1)
	122 dload (1, 1)
	123 #10 (1, 1)
	124 dadd (1, 1)
	125 dastore (1, 1)
	126 aload (1, 1)
	127 #4 (1, 1)
	128 iconst_0 (1, 1)
	129 dload (1, 1)
	130 #8 (1, 1)
	131 dload (1, 1)
	132 #12 (1, 1)
	133 dadd (1, 1)
	134 dastore (1, 1)
	135 aload_3 (1, 1)
	136 iconst_1 (1, 1)
	137 dload (1, 1)
	138 #6 (1, 1)
	139 dload (1, 1)
	140 #10 (1, 1)
	141 dsub (1, 1)
	142 dastore (1, 1)
	143 aload (1, 1)
	144 #4 (1, 1)
	145 iconst_1 (1, 1)
	146 dload (1, 1)
	147 #8 (1, 1)
	148 dload (1, 1)
	149 #12 (1, 1)
	150 dsub (1, 1)
	151 dastore (1, 1)
	152 aload_0 (1, 4)
	153 aload_1 (1, 4)
	154 aload_2 (1, 4)
	155 invokestatic (1, 4)
	156 org/apache/commons/math3/transform/FastFourierTransformer.normalizeTransformedData:([[DLorg/apache/commons/math3/transform/DftNormalization;Lorg/apache/commons/math3/transform/TransformType;)V (1, 4)
	158 return (1, 4)
	159 aload_3 (0, 0)
	160 aload (0, 0)
	161 #4 (0, 0)
	162 invokestatic (0, 0)
	163 org/apache/commons/math3/transform/FastFourierTransformer.bitReversalShuffle2:([D[D)V (0, 0)
	165 aload_2 (1, 1)
	166 getstatic (1, 1)
	167 org/apache/commons/math3/transform/TransformType.INVERSE:Lorg/apache/commons/math3/transform/TransformType; (1, 1)
	169 if_acmpne (1, 1)
	170 216 (1, 1)
	172 iconst_0 (2, 4)
	173 istore (2, 4)
	174 #6 (2, 4)
	175 iload (2, 4)
	176 #6 (2, 4)
	177 iload (2, 4)
	178 #5 (2, 4)
	179 if_icmpge (2, 4)
	180 203 (2, 4)
	182 iload (2, 4)
	183 #6 (2, 4)
	184 iconst_1 (2, 4)
	185 iadd (2, 4)
	186 istore (2, 4)
	187 #7 (2, 4)
	188 iload (2, 4)
	189 #6 (2, 4)
	190 iconst_2 (2, 4)
	191 iadd (2, 4)
	192 istore (2, 4)
	193 #8 (2, 4)
	194 iload (2, 4)
	195 #6 (2, 4)
	196 iconst_3 (2, 4)
	197 iadd (2, 4)
	198 istore (2, 4)
	199 #9 (2, 4)
	200 aload_3 (2, 4)
	201 iload (2, 4)
	202 #6 (2, 4)
	203 daload (2, 4)
	204 dstore (2, 4)
	205 #10 (2, 4)
	206 aload (2, 4)
	207 #4 (2, 4)
	208 iload (2, 4)
	209 #6 (2, 4)
	210 daload (2, 4)
	211 dstore (2, 4)
	212 #12 (2, 4)
	213 aload_3 (2, 4)
	214 iload (2, 4)
	215 #8 (2, 4)
	216 daload (2, 4)
	217 dstore (2, 4)
	218 #14 (2, 4)
	219 aload (2, 4)
	220 #4 (2, 4)
	221 iload (2, 4)
	222 #8 (2, 4)
	223 daload (2, 4)
	224 dstore (2, 4)
	225 #16 (2, 4)
	226 aload_3 (2, 4)
	227 iload (2, 4)
	228 #7 (2, 4)
	229 daload (2, 4)
	230 dstore (2, 4)
	231 #18 (2, 4)
	232 aload (2, 4)
	233 #4 (2, 4)
	234 iload (2, 4)
	235 #7 (2, 4)
	236 daload (2, 4)
	237 dstore (2, 4)
	238 #20 (2, 4)
	239 aload_3 (2, 4)
	240 iload (2, 4)
	241 #9 (2, 4)
	242 daload (2, 4)
	243 dstore (2, 4)
	244 #22 (2, 4)
	245 aload (2, 4)
	246 #4 (2, 4)
	247 iload (2, 4)
	248 #9 (2, 4)
	249 daload (2, 4)
	250 dstore (2, 4)
	251 #24 (2, 4)
	252 aload_3 (2, 4)
	253 iload (2, 4)
	254 #6 (2, 4)
	255 dload (2, 4)
	256 #10 (2, 4)
	257 dload (2, 4)
	258 #14 (2, 4)
	259 dadd (2, 4)
	260 dload (2, 4)
	261 #18 (2, 4)
	262 dadd (2, 4)
	263 dload (2, 4)
	264 #22 (2, 4)
	265 dadd (2, 4)
	266 dastore (2, 4)
	267 aload (2, 4)
	268 #4 (2, 4)
	269 iload (2, 4)
	270 #6 (2, 4)
	271 dload (2, 4)
	272 #12 (2, 4)
	273 dload (2, 4)
	274 #16 (2, 4)
	275 dadd (2, 4)
	276 dload (2, 4)
	277 #20 (2, 4)
	278 dadd (2, 4)
	279 dload (2, 4)
	280 #24 (2, 4)
	281 dadd (2, 4)
	282 dastore (2, 4)
	283 aload_3 (2, 4)
	284 iload (2, 4)
	285 #7 (2, 4)
	286 dload (2, 4)
	287 #10 (2, 4)
	288 dload (2, 4)
	289 #18 (2, 4)
	290 dsub (2, 4)
	291 dload (2, 4)
	292 #24 (2, 4)
	293 dload (2, 4)
	294 #16 (2, 4)
	295 dsub (2, 4)
	296 dadd (2, 4)
	297 dastore (2, 4)
	298 aload (2, 4)
	299 #4 (2, 4)
	300 iload (2, 4)
	301 #7 (2, 4)
	302 dload (2, 4)
	303 #12 (2, 4)
	304 dload (2, 4)
	305 #20 (2, 4)
	306 dsub (2, 4)
	307 dload (2, 4)
	308 #14 (2, 4)
	309 dload (2, 4)
	310 #22 (2, 4)
	311 dsub (2, 4)
	312 dadd (2, 4)
	313 dastore (2, 4)
	314 aload_3 (2, 4)
	315 iload (2, 4)
	316 #8 (2, 4)
	317 dload (2, 4)
	318 #10 (2, 4)
	319 dload (2, 4)
	320 #14 (2, 4)
	321 dsub (2, 4)
	322 dload (2, 4)
	323 #18 (2, 4)
	324 dadd (2, 4)
	325 dload (2, 4)
	326 #22 (2, 4)
	327 dsub (2, 4)
	328 dastore (2, 4)
	329 aload (2, 4)
	330 #4 (2, 4)
	331 iload (2, 4)
	332 #8 (2, 4)
	333 dload (2, 4)
	334 #12 (2, 4)
	335 dload (2, 4)
	336 #16 (2, 4)
	337 dsub (2, 4)
	338 dload (2, 4)
	339 #20 (2, 4)
	340 dadd (2, 4)
	341 dload (2, 4)
	342 #24 (2, 4)
	343 dsub (2, 4)
	344 dastore (2, 4)
	345 aload_3 (2, 4)
	346 iload (2, 4)
	347 #9 (2, 4)
	348 dload (2, 4)
	349 #10 (2, 4)
	350 dload (2, 4)
	351 #18 (2, 4)
	352 dsub (2, 4)
	353 dload (2, 4)
	354 #16 (2, 4)
	355 dload (2, 4)
	356 #24 (2, 4)
	357 dsub (2, 4)
	358 dadd (2, 4)
	359 dastore (2, 4)
	360 aload (2, 4)
	361 #4 (2, 4)
	362 iload (2, 4)
	363 #9 (2, 4)
	364 dload (2, 4)
	365 #12 (2, 4)
	366 dload (2, 4)
	367 #20 (2, 4)
	368 dsub (2, 4)
	369 dload (2, 4)
	370 #22 (2, 4)
	371 dload (2, 4)
	372 #14 (2, 4)
	373 dsub (2, 4)
	374 dadd (2, 4)
	375 dastore (2, 4)
	376 iinc (2, 4)
	377 #6 (2, 4)
	378 -89 (2, 4)
	379 goto (2, 4)
	380 -204 (2, 4)
	382 goto (2, 4)
	383 213 (2, 4)
	385 iconst_0 (2, 4)
	386 istore (2, 4)
	387 #6 (2, 4)
	388 iload (2, 4)
	389 #6 (2, 4)
	390 iload (2, 4)
	391 #5 (2, 4)
	392 if_icmpge (2, 4)
	393 203 (2, 4)
	395 iload (2, 4)
	396 #6 (2, 4)
	397 iconst_1 (2, 4)
	398 iadd (2, 4)
	399 istore (2, 4)
	400 #7 (2, 4)
	401 iload (2, 4)
	402 #6 (2, 4)
	403 iconst_2 (2, 4)
	404 iadd (2, 4)
	405 istore (2, 4)
	406 #8 (2, 4)
	407 iload (2, 4)
	408 #6 (2, 4)
	409 iconst_3 (2, 4)
	410 iadd (2, 4)
	411 istore (2, 4)
	412 #9 (2, 4)
	413 aload_3 (2, 4)
	414 iload (2, 4)
	415 #6 (2, 4)
	416 daload (2, 4)
	417 dstore (2, 4)
	418 #10 (2, 4)
	419 aload (2, 4)
	420 #4 (2, 4)
	421 iload (2, 4)
	422 #6 (2, 4)
	423 daload (2, 4)
	424 dstore (2, 4)
	425 #12 (2, 4)
	426 aload_3 (2, 4)
	427 iload (2, 4)
	428 #8 (2, 4)
	429 daload (2, 4)
	430 dstore (2, 4)
	431 #14 (2, 4)
	432 aload (2, 4)
	433 #4 (2, 4)
	434 iload (2, 4)
	435 #8 (2, 4)
	436 daload (2, 4)
	437 dstore (2, 4)
	438 #16 (2, 4)
	439 aload_3 (2, 4)
	440 iload (2, 4)
	441 #7 (2, 4)
	442 daload (2, 4)
	443 dstore (2, 4)
	444 #18 (2, 4)
	445 aload (2, 4)
	446 #4 (2, 4)
	447 iload (2, 4)
	448 #7 (2, 4)
	449 daload (2, 4)
	450 dstore (2, 4)
	451 #20 (2, 4)
	452 aload_3 (2, 4)
	453 iload (2, 4)
	454 #9 (2, 4)
	455 daload (2, 4)
	456 dstore (2, 4)
	457 #22 (2, 4)
	458 aload (2, 4)
	459 #4 (2, 4)
	460 iload (2, 4)
	461 #9 (2, 4)
	462 daload (2, 4)
	463 dstore (2, 4)
	464 #24 (2, 4)
	465 aload_3 (2, 4)
	466 iload (2, 4)
	467 #6 (2, 4)
	468 dload (2, 4)
	469 #10 (2, 4)
	470 dload (2, 4)
	471 #14 (2, 4)
	472 dadd (2, 4)
	473 dload (2, 4)
	474 #18 (2, 4)
	475 dadd (2, 4)
	476 dload (2, 4)
	477 #22 (2, 4)
	478 dadd (2, 4)
	479 dastore (2, 4)
	480 aload (2, 4)
	481 #4 (2, 4)
	482 iload (2, 4)
	483 #6 (2, 4)
	484 dload (2, 4)
	485 #12 (2, 4)
	486 dload (2, 4)
	487 #16 (2, 4)
	488 dadd (2, 4)
	489 dload (2, 4)
	490 #20 (2, 4)
	491 dadd (2, 4)
	492 dload (2, 4)
	493 #24 (2, 4)
	494 dadd (2, 4)
	495 dastore (2, 4)
	496 aload_3 (2, 4)
	497 iload (2, 4)
	498 #7 (2, 4)
	499 dload (2, 4)
	500 #10 (2, 4)
	501 dload (2, 4)
	502 #18 (2, 4)
	503 dsub (2, 4)
	504 dload (2, 4)
	505 #16 (2, 4)
	506 dload (2, 4)
	507 #24 (2, 4)
	508 dsub (2, 4)
	509 dadd (2, 4)
	510 dastore (2, 4)
	511 aload (2, 4)
	512 #4 (2, 4)
	513 iload (2, 4)
	514 #7 (2, 4)
	515 dload (2, 4)
	516 #12 (2, 4)
	517 dload (2, 4)
	518 #20 (2, 4)
	519 dsub (2, 4)
	520 dload (2, 4)
	521 #22 (2, 4)
	522 dload (2, 4)
	523 #14 (2, 4)
	524 dsub (2, 4)
	525 dadd (2, 4)
	526 dastore (2, 4)
	527 aload_3 (2, 4)
	528 iload (2, 4)
	529 #8 (2, 4)
	530 dload (2, 4)
	531 #10 (2, 4)
	532 dload (2, 4)
	533 #14 (2, 4)
	534 dsub (2, 4)
	535 dload (2, 4)
	536 #18 (2, 4)
	537 dadd (2, 4)
	538 dload (2, 4)
	539 #22 (2, 4)
	540 dsub (2, 4)
	541 dastore (2, 4)
	542 aload (2, 4)
	543 #4 (2, 4)
	544 iload (2, 4)
	545 #8 (2, 4)
	546 dload (2, 4)
	547 #12 (2, 4)
	548 dload (2, 4)
	549 #16 (2, 4)
	550 dsub (2, 4)
	551 dload (2, 4)
	552 #20 (2, 4)
	553 dadd (2, 4)
	554 dload (2, 4)
	555 #24 (2, 4)
	556 dsub (2, 4)
	557 dastore (2, 4)
	558 aload_3 (2, 4)
	559 iload (2, 4)
	560 #9 (2, 4)
	561 dload (2, 4)
	562 #10 (2, 4)
	563 dload (2, 4)
	564 #18 (2, 4)
	565 dsub (2, 4)
	566 dload (2, 4)
	567 #24 (2, 4)
	568 dload (2, 4)
	569 #16 (2, 4)
	570 dsub (2, 4)
	571 dadd (2, 4)
	572 dastore (2, 4)
	573 aload (2, 4)
	574 #4 (2, 4)
	575 iload (2, 4)
	576 #9 (2, 4)
	577 dload (2, 4)
	578 #12 (2, 4)
	579 dload (2, 4)
	580 #20 (2, 4)
	581 dsub (2, 4)
	582 dload (2, 4)
	583 #14 (2, 4)
	584 dload (2, 4)
	585 #22 (2, 4)
	586 dsub (2, 4)
	587 dadd (2, 4)
	588 dastore (2, 4)
	589 iinc (2, 4)
	590 #6 (2, 4)
	591 -89 (2, 4)
	592 goto (2, 4)
	593 -204 (2, 4)
	595 iconst_4 (0, 0)
	596 istore (0, 0)
	597 #6 (0, 0)
	598 iconst_2 (0, 0)
	599 istore (0, 0)
	600 #7 (0, 0)
	601 iload (1, 3)
	602 #6 (1, 3)
	603 iload (1, 3)
	604 #5 (1, 3)
	605 if_icmpge (1, 3)
	606 261 (1, 3)
	608 iload (1, 3)
	609 #6 (1, 3)
	610 iconst_1 (1, 3)
	611 ishl (1, 3)
	612 istore (1, 3)
	613 #8 (1, 3)
	614 iload (1, 3)
	615 #7 (1, 3)
	616 iconst_1 (1, 3)
	617 iadd (1, 3)
	618 istore (1, 3)
	619 #9 (1, 3)
	620 getstatic (1, 3)
	621 org/apache/commons/math3/transform/FastFourierTransformer.W_SUB_N_R:[D (1, 3)
	623 iload (1, 3)
	624 #9 (1, 3)
	625 daload (1, 3)
	626 dstore (1, 3)
	627 #10 (1, 3)
	628 getstatic (1, 3)
	629 org/apache/commons/math3/transform/FastFourierTransformer.W_SUB_N_I:[D (1, 3)
	631 iload (1, 3)
	632 #9 (1, 3)
	633 daload (1, 3)
	634 dstore (1, 3)
	635 #12 (1, 3)
	636 aload_2 (2, 1)
	637 getstatic (2, 1)
	638 org/apache/commons/math3/transform/TransformType.INVERSE:Lorg/apache/commons/math3/transform/TransformType; (2, 1)
	640 if_acmpne (2, 1)
	641 8 (2, 1)
	643 dload (2, 1)
	644 #12 (2, 1)
	645 dneg (2, 1)
	646 dstore (2, 1)
	647 #12 (2, 1)
	648 iconst_0 (2, 4)
	649 istore (2, 4)
	650 #14 (2, 4)
	651 iload (2, 4)
	652 #14 (2, 4)
	653 iload (2, 4)
	654 #5 (2, 4)
	655 if_icmpge (2, 4)
	656 200 (2, 4)
	658 iload (2, 4)
	659 #14 (2, 4)
	660 iload (2, 4)
	661 #6 (2, 4)
	662 iadd (2, 4)
	663 istore (2, 4)
	664 #15 (2, 4)
	665 dconst_1 (2, 4)
	666 dstore (2, 4)
	667 #16 (2, 4)
	668 dconst_0 (2, 4)
	669 dstore (2, 4)
	670 #18 (2, 4)
	671 iconst_0 (3, 4)
	672 istore (3, 4)
	673 #20 (3, 4)
	674 iload (3, 4)
	675 #20 (3, 4)
	676 iload (3, 4)
	677 #6 (3, 4)
	678 if_icmpge (3, 4)
	679 167 (3, 4)
	681 aload_3 (3, 4)
	682 iload (3, 4)
	683 #14 (3, 4)
	684 iload (3, 4)
	685 #20 (3, 4)
	686 iadd (3, 4)
	687 daload (3, 4)
	688 dstore (3, 4)
	689 #21 (3, 4)
	690 aload (3, 4)
	691 #4 (3, 4)
	692 iload (3, 4)
	693 #14 (3, 4)
	694 iload (3, 4)
	695 #20 (3, 4)
	696 iadd (3, 4)
	697 daload (3, 4)
	698 dstore (3, 4)
	699 #23 (3, 4)
	700 aload_3 (3, 4)
	701 iload (3, 4)
	702 #15 (3, 4)
	703 iload (3, 4)
	704 #20 (3, 4)
	705 iadd (3, 4)
	706 daload (3, 4)
	707 dstore (3, 4)
	708 #25 (3, 4)
	709 aload (3, 4)
	710 #4 (3, 4)
	711 iload (3, 4)
	712 #15 (3, 4)
	713 iload (3, 4)
	714 #20 (3, 4)
	715 iadd (3, 4)
	716 daload (3, 4)
	717 dstore (3, 4)
	718 #27 (3, 4)
	719 aload_3 (3, 4)
	720 iload (3, 4)
	721 #14 (3, 4)
	722 iload (3, 4)
	723 #20 (3, 4)
	724 iadd (3, 4)
	725 dload (3, 4)
	726 #21 (3, 4)
	727 dload (3, 4)
	728 #16 (3, 4)
	729 dload (3, 4)
	730 #25 (3, 4)
	731 dmul (3, 4)
	732 dadd (3, 4)
	733 dload (3, 4)
	734 #18 (3, 4)
	735 dload (3, 4)
	736 #27 (3, 4)
	737 dmul (3, 4)
	738 dsub (3, 4)
	739 dastore (3, 4)
	740 aload (3, 4)
	741 #4 (3, 4)
	742 iload (3, 4)
	743 #14 (3, 4)
	744 iload (3, 4)
	745 #20 (3, 4)
	746 iadd (3, 4)
	747 dload (3, 4)
	748 #23 (3, 4)
	749 dload (3, 4)
	750 #16 (3, 4)
	751 dload (3, 4)
	752 #27 (3, 4)
	753 dmul (3, 4)
	754 dadd (3, 4)
	755 dload (3, 4)
	756 #18 (3, 4)
	757 dload (3, 4)
	758 #25 (3, 4)
	759 dmul (3, 4)
	760 dadd (3, 4)
	761 dastore (3, 4)
	762 aload_3 (3, 4)
	763 iload (3, 4)
	764 #15 (3, 4)
	765 iload (3, 4)
	766 #20 (3, 4)
	767 iadd (3, 4)
	768 dload (3, 4)
	769 #21 (3, 4)
	770 dload (3, 4)
	771 #16 (3, 4)
	772 dload (3, 4)
	773 #25 (3, 4)
	774 dmul (3, 4)
	775 dload (3, 4)
	776 #18 (3, 4)
	777 dload (3, 4)
	778 #27 (3, 4)
	779 dmul (3, 4)
	780 dsub (3, 4)
	781 dsub (3, 4)
	782 dastore (3, 4)
	783 aload (3, 4)
	784 #4 (3, 4)
	785 iload (3, 4)
	786 #15 (3, 4)
	787 iload (3, 4)
	788 #20 (3, 4)
	789 iadd (3, 4)
	790 dload (3, 4)
	791 #23 (3, 4)
	792 dload (3, 4)
	793 #16 (3, 4)
	794 dload (3, 4)
	795 #27 (3, 4)
	796 dmul (3, 4)
	797 dload (3, 4)
	798 #18 (3, 4)
	799 dload (3, 4)
	800 #25 (3, 4)
	801 dmul (3, 4)
	802 dadd (3, 4)
	803 dsub (3, 4)
	804 dastore (3, 4)
	805 dload (3, 4)
	806 #16 (3, 4)
	807 dload (3, 4)
	808 #10 (3, 4)
	809 dmul (3, 4)
	810 dload (3, 4)
	811 #18 (3, 4)
	812 dload (3, 4)
	813 #12 (3, 4)
	814 dmul (3, 4)
	815 dsub (3, 4)
	816 dstore (3, 4)
	817 #29 (3, 4)
	818 dload (3, 4)
	819 #16 (3, 4)
	820 dload (3, 4)
	821 #12 (3, 4)
	822 dmul (3, 4)
	823 dload (3, 4)
	824 #18 (3, 4)
	825 dload (3, 4)
	826 #10 (3, 4)
	827 dmul (3, 4)
	828 dadd (3, 4)
	829 dstore (3, 4)
	830 #31 (3, 4)
	831 dload (3, 4)
	832 #29 (3, 4)
	833 dstore (3, 4)
	834 #16 (3, 4)
	835 dload (3, 4)
	836 #31 (3, 4)
	837 dstore (3, 4)
	838 #18 (3, 4)
	839 iinc (3, 4)
	840 #20 (3, 4)
	841 -89 (3, 4)
	842 goto (3, 4)
	843 -168 (3, 4)
	845 iload (3, 4)
	846 #14 (3, 4)
	847 iload (3, 4)
	848 #8 (3, 4)
	849 iadd (3, 4)
	850 istore (3, 4)
	851 #14 (3, 4)
	852 goto (3, 4)
	853 -201 (3, 4)
	855 iload (2, 4)
	856 #8 (2, 4)
	857 istore (2, 4)
	858 #6 (2, 4)
	859 iload (2, 4)
	860 #9 (2, 4)
	861 istore (2, 4)
	862 #7 (2, 4)
	863 goto (1, 4)
	864 -262 (1, 4)
	866 aload_0 (1, 4)
	867 aload_1 (1, 4)
	868 aload_2 (1, 4)
	869 invokestatic (1, 4)
	870 org/apache/commons/math3/transform/FastFourierTransformer.normalizeTransformedData:([[DLorg/apache/commons/math3/transform/DftNormalization;Lorg/apache/commons/math3/transform/TransformType;)V (1, 4)
	872 return (0, 0)

Method: transform
	0 aload_1 (0, 4)
	1 invokestatic (0, 4)
	2 org/apache/commons/math3/transform/TransformUtils.createRealImaginaryArray:([Lorg/apache/commons/math3/complex/Complex;)[[D (0, 4)
	4 astore_3 (0, 4)
	5 aload_3 (0, 4)
	6 aload_0 (0, 4)
	7 getfield (0, 4)
	8 org/apache/commons/math3/transform/FastFourierTransformer.normalization:Lorg/apache/commons/math3/transform/DftNormalization; (0, 4)
	10 aload_2 (0, 4)
	11 invokestatic (0, 4)
	12 org/apache/commons/math3/transform/FastFourierTransformer.transformInPlace:([[DLorg/apache/commons/math3/transform/DftNormalization;Lorg/apache/commons/math3/transform/TransformType;)V (0, 4)
	14 aload_3 (0, 4)
	15 invokestatic (0, 4)
	16 org/apache/commons/math3/transform/TransformUtils.createComplexArray:([[D)[Lorg/apache/commons/math3/complex/Complex; (0, 4)
	18 areturn (0, 4)

Method: mdfft
	0 aload_1 (0, 0)
	1 invokevirtual (0, 0)
	2 org/apache/commons/math3/transform/FastFourierTransformer$MultiDimensionalComplexMatrix.getDimensionSizes:()[I (0, 0)
	4 astore (0, 0)
	5 #5 (0, 0)
	6 aload (1, 1)
	7 #4 (1, 1)
	8 arraylength (1, 1)
	9 aload (1, 1)
	10 #5 (1, 1)
	11 arraylength (1, 1)
	12 if_icmpne (1, 1)
	13 95 (1, 1)
	15 aload (1, 1)
	16 #5 (1, 1)
	17 iload_3 (1, 1)
	18 iaload (1, 1)
	19 anewarray (1, 1)
	20 org/apache/commons/math3/complex/Complex (1, 1)
	22 astore (1, 1)
	23 #6 (1, 1)
	24 iconst_0 (2, 4)
	25 istore (2, 4)
	26 #7 (2, 4)
	27 iload (2, 4)
	28 #7 (2, 4)
	29 aload (2, 4)
	30 #5 (2, 4)
	31 iload_3 (2, 4)
	32 iaload (2, 4)
	33 if_icmpge (2, 4)
	34 26 (2, 4)
	36 aload (2, 4)
	37 #4 (2, 4)
	38 iload_3 (2, 4)
	39 iload (2, 4)
	40 #7 (2, 4)
	41 iastore (2, 4)
	42 aload (2, 4)
	43 #6 (2, 4)
	44 iload (2, 4)
	45 #7 (2, 4)
	46 aload_1 (2, 4)
	47 aload (2, 4)
	48 #4 (2, 4)
	49 invokevirtual (2, 4)
	50 org/apache/commons/math3/transform/FastFourierTransformer$MultiDimensionalComplexMatrix.get:([I)Lorg/apache/commons/math3/complex/Complex; (2, 4)
	52 aastore (2, 4)
	53 iinc (2, 4)
	54 #7 (2, 4)
	55 -89 (2, 4)
	56 goto (2, 4)
	57 -29 (2, 4)
	59 aload_0 (1, 4)
	60 aload (1, 4)
	61 #6 (1, 4)
	62 aload_2 (1, 4)
	63 invokevirtual (1, 4)
	64 org/apache/commons/math3/transform/FastFourierTransformer.transform:([Lorg/apache/commons/math3/complex/Complex;Lorg/apache/commons/math3/transform/TransformType;)[Lorg/apache/commons/math3/complex/Complex; (1, 4)
	66 astore (1, 4)
	67 #6 (1, 4)
	68 iconst_0 (2, 4)
	69 istore (2, 4)
	70 #7 (2, 4)
	71 iload (2, 4)
	72 #7 (2, 4)
	73 aload (2, 4)
	74 #5 (2, 4)
	75 iload_3 (2, 4)
	76 iaload (2, 4)
	77 if_icmpge (2, 4)
	78 27 (2, 4)
	80 aload (2, 4)
	81 #4 (2, 4)
	82 iload_3 (2, 4)
	83 iload (2, 4)
	84 #7 (2, 4)
	85 iastore (2, 4)
	86 aload_1 (2, 4)
	87 aload (2, 4)
	88 #6 (2, 4)
	89 iload (2, 4)
	90 #7 (2, 4)
	91 aaload (2, 4)
	92 aload (2, 4)
	93 #4 (2, 4)
	94 invokevirtual (2, 4)
	95 org/apache/commons/math3/transform/FastFourierTransformer$MultiDimensionalComplexMatrix.set:(Lorg/apache/commons/math3/complex/Complex;[I)Lorg/apache/commons/math3/complex/Complex; (2, 4)
	97 pop (2, 4)
	98 iinc (2, 4)
	99 #7 (2, 4)
	100 -89 (2, 4)
	101 goto (2, 4)
	102 -30 (2, 4)
	104 goto (1, 2)
	105 85 (1, 2)
	107 aload (1, 2)
	108 #4 (1, 2)
	109 arraylength (1, 2)
	110 iconst_1 (1, 2)
	111 iadd (1, 2)
	112 newarray (1, 2)
	113 10 (1, 2)
	114 astore (1, 2)
	115 #6 (1, 2)
	116 aload (1, 2)
	117 #4 (1, 2)
	118 iconst_0 (1, 2)
	119 aload (1, 2)
	120 #6 (1, 2)
	121 iconst_0 (1, 2)
	122 aload (1, 2)
	123 #4 (1, 2)
	124 arraylength (1, 2)
	125 invokestatic (1, 2)
	126 java/lang/System.arraycopy:(Ljava/lang/Object;ILjava/lang/Object;II)V (1, 2)
	128 aload (2, 1)
	129 #4 (2, 1)
	130 arraylength (2, 1)
	131 iload_3 (2, 1)
	132 if_icmpne (2, 1)
	133 20 (2, 1)
	135 aload (2, 1)
	136 #6 (2, 1)
	137 iload_3 (2, 1)
	138 iconst_0 (2, 1)
	139 iastore (2, 1)
	140 aload_0 (2, 1)
	141 aload_1 (2, 1)
	142 aload_2 (2, 1)
	143 iload_3 (2, 1)
	144 aload (2, 1)
	145 #6 (2, 1)
	146 invokespecial (2, 1)
	147 org/apache/commons/math3/transform/FastFourierTransformer.mdfft:(Lorg/apache/commons/math3/transform/FastFourierTransformer$MultiDimensionalComplexMatrix;Lorg/apache/commons/math3/transform/TransformType;I[I)V (2, 1)
	149 goto (2, 1)
	150 40 (2, 1)
	152 iconst_0 (3, 4)
	153 istore (3, 4)
	154 #7 (3, 4)
	155 iload (3, 4)
	156 #7 (3, 4)
	157 aload (3, 4)
	158 #5 (3, 4)
	159 aload (3, 4)
	160 #4 (3, 4)
	161 arraylength (3, 4)
	162 iaload (3, 4)
	163 if_icmpge (3, 4)
	164 26 (3, 4)
	166 aload (3, 4)
	167 #6 (3, 4)
	168 aload (3, 4)
	169 #4 (3, 4)
	170 arraylength (3, 4)
	171 iload (3, 4)
	172 #7 (3, 4)
	173 iastore (3, 4)
	174 aload_0 (3, 4)
	175 aload_1 (3, 4)
	176 aload_2 (3, 4)
	177 iload_3 (3, 4)
	178 aload (3, 4)
	179 #6 (3, 4)
	180 invokespecial (3, 4)
	181 org/apache/commons/math3/transform/FastFourierTransformer.mdfft:(Lorg/apache/commons/math3/transform/FastFourierTransformer$MultiDimensionalComplexMatrix;Lorg/apache/commons/math3/transform/TransformType;I[I)V (3, 4)
	183 iinc (3, 4)
	184 #7 (3, 4)
	185 -89 (3, 4)
	186 goto (3, 4)
	187 -31 (3, 4)
	189 return (0, 1)

Method: <clinit>
	0 ldc (1, 4)
	1 org/apache/commons/math3/transform/FastFourierTransformer (1, 4)
	2 invokevirtual (1, 4)
	3 java/lang/Class.desiredAssertionStatus:()Z (1, 4)
	5 ifne (1, 4)
	6 7 (1, 4)
	8 iconst_1 (1, 4)
	9 goto (1, 4)
	10 4 (1, 4)
	12 iconst_0 (1, 4)
	13 putstatic (1, 4)
	14 org/apache/commons/math3/transform/FastFourierTransformer.$assertionsDisabled:Z (1, 4)
	16 bipush (1, 1)
	17 63 (1, 1)
	18 newarray (1, 1)
	19 7 (1, 1)
	20 dup (1, 1)
	21 iconst_0 (1, 1)
	22 dconst_1 (1, 1)
	23 dastore (1, 1)
	24 dup (1, 1)
	25 iconst_1 (1, 1)
	26 ldc2_w (1, 1)
	27 -1.0 (1, 1)
	29 dastore (1, 1)
	30 dup (1, 1)
	31 iconst_2 (1, 1)
	32 ldc2_w (1, 1)
	33 6.123233995736766e-17 (1, 1)
	35 dastore (1, 1)
	36 dup (1, 1)
	37 iconst_3 (1, 1)
	38 ldc2_w (1, 1)
	39 0.7071067811865476 (1, 1)
	41 dastore (1, 1)
	42 dup (1, 1)
	43 iconst_4 (1, 1)
	44 ldc2_w (1, 1)
	45 0.9238795325112867 (1, 1)
	47 dastore (1, 1)
	48 dup (1, 1)
	49 iconst_5 (1, 1)
	50 ldc2_w (1, 1)
	51 0.9807852804032304 (1, 1)
	53 dastore (1, 1)
	54 dup (1, 1)
	55 bipush (1, 1)
	56 6 (1, 1)
	57 ldc2_w (1, 1)
	58 0.9951847266721969 (1, 1)
	60 dastore (1, 1)
	61 dup (1, 1)
	62 bipush (1, 1)
	63 7 (1, 1)
	64 ldc2_w (1, 1)
	65 0.9987954562051724 (1, 1)
	67 dastore (1, 1)
	68 dup (1, 1)
	69 bipush (1, 1)
	70 8 (1, 1)
	71 ldc2_w (1, 1)
	72 0.9996988186962042 (1, 1)
	74 dastore (1, 1)
	75 dup (1, 1)
	76 bipush (1, 1)
	77 9 (1, 1)
	78 ldc2_w (1, 1)
	79 0.9999247018391445 (1, 1)
	81 dastore (1, 1)
	82 dup (1, 1)
	83 bipush (1, 1)
	84 10 (1, 1)
	85 ldc2_w (1, 1)
	86 0.9999811752826011 (1, 1)
	88 dastore (1, 1)
	89 dup (1, 1)
	90 bipush (1, 1)
	91 11 (1, 1)
	92 ldc2_w (1, 1)
	93 0.9999952938095762 (1, 1)
	95 dastore (1, 1)
	96 dup (1, 1)
	97 bipush (1, 1)
	98 12 (1, 1)
	99 ldc2_w (1, 1)
	100 0.9999988234517019 (1, 1)
	102 dastore (1, 1)
	103 dup (1, 1)
	104 bipush (1, 1)
	105 13 (1, 1)
	106 ldc2_w (1, 1)
	107 0.9999997058628822 (1, 1)
	109 dastore (1, 1)
	110 dup (1, 1)
	111 bipush (1, 1)
	112 14 (1, 1)
	113 ldc2_w (1, 1)
	114 0.9999999264657179 (1, 1)
	116 dastore (1, 1)
	117 dup (1, 1)
	118 bipush (1, 1)
	119 15 (1, 1)
	120 ldc2_w (1, 1)
	121 0.9999999816164293 (1, 1)
	123 dastore (1, 1)
	124 dup (1, 1)
	125 bipush (1, 1)
	126 16 (1, 1)
	127 ldc2_w (1, 1)
	128 0.9999999954041073 (1, 1)
	130 dastore (1, 1)
	131 dup (1, 1)
	132 bipush (1, 1)
	133 17 (1, 1)
	134 ldc2_w (1, 1)
	135 0.9999999988510269 (1, 1)
	137 dastore (1, 1)
	138 dup (1, 1)
	139 bipush (1, 1)
	140 18 (1, 1)
	141 ldc2_w (1, 1)
	142 0.9999999997127567 (1, 1)
	144 dastore (1, 1)
	145 dup (1, 1)
	146 bipush (1, 1)
	147 19 (1, 1)
	148 ldc2_w (1, 1)
	149 0.9999999999281892 (1, 1)
	151 dastore (1, 1)
	152 dup (1, 1)
	153 bipush (1, 1)
	154 20 (1, 1)
	155 ldc2_w (1, 1)
	156 0.9999999999820472 (1, 1)
	158 dastore (1, 1)
	159 dup (1, 1)
	160 bipush (1, 1)
	161 21 (1, 1)
	162 ldc2_w (1, 1)
	163 0.9999999999955118 (1, 1)
	165 dastore (1, 1)
	166 dup (1, 1)
	167 bipush (1, 1)
	168 22 (1, 1)
	169 ldc2_w (1, 1)
	170 0.999999999998878 (1, 1)
	172 dastore (1, 1)
	173 dup (1, 1)
	174 bipush (1, 1)
	175 23 (1, 1)
	176 ldc2_w (1, 1)
	177 0.9999999999997194 (1, 1)
	179 dastore (1, 1)
	180 dup (1, 1)
	181 bipush (1, 1)
	182 24 (1, 1)
	183 ldc2_w (1, 1)
	184 0.9999999999999298 (1, 1)
	186 dastore (1, 1)
	187 dup (1, 1)
	188 bipush (1, 1)
	189 25 (1, 1)
	190 ldc2_w (1, 1)
	191 0.9999999999999825 (1, 1)
	193 dastore (1, 1)
	194 dup (1, 1)
	195 bipush (1, 1)
	196 26 (1, 1)
	197 ldc2_w (1, 1)
	198 0.9999999999999957 (1, 1)
	200 dastore (1, 1)
	201 dup (1, 1)
	202 bipush (1, 1)
	203 27 (1, 1)
	204 ldc2_w (1, 1)
	205 0.9999999999999989 (1, 1)
	207 dastore (1, 1)
	208 dup (1, 1)
	209 bipush (1, 1)
	210 28 (1, 1)
	211 ldc2_w (1, 1)
	212 0.9999999999999998 (1, 1)
	214 dastore (1, 1)
	215 dup (1, 1)
	216 bipush (1, 1)
	217 29 (1, 1)
	218 ldc2_w (1, 1)
	219 0.9999999999999999 (1, 1)
	221 dastore (1, 1)
	222 dup (1, 1)
	223 bipush (1, 1)
	224 30 (1, 1)
	225 dconst_1 (1, 1)
	226 dastore (1, 1)
	227 dup (1, 1)
	228 bipush (1, 1)
	229 31 (1, 1)
	230 dconst_1 (1, 1)
	231 dastore (1, 1)
	232 dup (1, 1)
	233 bipush (1, 1)
	234 32 (1, 1)
	235 dconst_1 (1, 1)
	236 dastore (1, 1)
	237 dup (1, 1)
	238 bipush (1, 1)
	239 33 (1, 1)
	240 dconst_1 (1, 1)
	241 dastore (1, 1)
	242 dup (1, 1)
	243 bipush (1, 1)
	244 34 (1, 1)
	245 dconst_1 (1, 1)
	246 dastore (1, 1)
	247 dup (1, 1)
	248 bipush (1, 1)
	249 35 (1, 1)
	250 dconst_1 (1, 1)
	251 dastore (1, 1)
	252 dup (1, 1)
	253 bipush (1, 1)
	254 36 (1, 1)
	255 dconst_1 (1, 1)
	256 dastore (1, 1)
	257 dup (1, 1)
	258 bipush (1, 1)
	259 37 (1, 1)
	260 dconst_1 (1, 1)
	261 dastore (1, 1)
	262 dup (1, 1)
	263 bipush (1, 1)
	264 38 (1, 1)
	265 dconst_1 (1, 1)
	266 dastore (1, 1)
	267 dup (1, 1)
	268 bipush (1, 1)
	269 39 (1, 1)
	270 dconst_1 (1, 1)
	271 dastore (1, 1)
	272 dup (1, 1)
	273 bipush (1, 1)
	274 40 (1, 1)
	275 dconst_1 (1, 1)
	276 dastore (1, 1)
	277 dup (1, 1)
	278 bipush (1, 1)
	279 41 (1, 1)
	280 dconst_1 (1, 1)
	281 dastore (1, 1)
	282 dup (1, 1)
	283 bipush (1, 1)
	284 42 (1, 1)
	285 dconst_1 (1, 1)
	286 dastore (1, 1)
	287 dup (1, 1)
	288 bipush (1, 1)
	289 43 (1, 1)
	290 dconst_1 (1, 1)
	291 dastore (1, 1)
	292 dup (1, 1)
	293 bipush (1, 1)
	294 44 (1, 1)
	295 dconst_1 (1, 1)
	296 dastore (1, 1)
	297 dup (1, 1)
	298 bipush (1, 1)
	299 45 (1, 1)
	300 dconst_1 (1, 1)
	301 dastore (1, 1)
	302 dup (1, 1)
	303 bipush (1, 1)
	304 46 (1, 1)
	305 dconst_1 (1, 1)
	306 dastore (1, 1)
	307 dup (1, 1)
	308 bipush (1, 1)
	309 47 (1, 1)
	310 dconst_1 (1, 1)
	311 dastore (1, 1)
	312 dup (1, 1)
	313 bipush (1, 1)
	314 48 (1, 1)
	315 dconst_1 (1, 1)
	316 dastore (1, 1)
	317 dup (1, 1)
	318 bipush (1, 1)
	319 49 (1, 1)
	320 dconst_1 (1, 1)
	321 dastore (1, 1)
	322 dup (1, 1)
	323 bipush (1, 1)
	324 50 (1, 1)
	325 dconst_1 (1, 1)
	326 dastore (1, 1)
	327 dup (1, 1)
	328 bipush (1, 1)
	329 51 (1, 1)
	330 dconst_1 (1, 1)
	331 dastore (1, 1)
	332 dup (1, 1)
	333 bipush (1, 1)
	334 52 (1, 1)
	335 dconst_1 (1, 1)
	336 dastore (1, 1)
	337 dup (1, 1)
	338 bipush (1, 1)
	339 53 (1, 1)
	340 dconst_1 (1, 1)
	341 dastore (1, 1)
	342 dup (1, 1)
	343 bipush (1, 1)
	344 54 (1, 1)
	345 dconst_1 (1, 1)
	346 dastore (1, 1)
	347 dup (1, 1)
	348 bipush (1, 1)
	349 55 (1, 1)
	350 dconst_1 (1, 1)
	351 dastore (1, 1)
	352 dup (1, 1)
	353 bipush (1, 1)
	354 56 (1, 1)
	355 dconst_1 (1, 1)
	356 dastore (1, 1)
	357 dup (1, 1)
	358 bipush (1, 1)
	359 57 (1, 1)
	360 dconst_1 (1, 1)
	361 dastore (1, 1)
	362 dup (1, 1)
	363 bipush (1, 1)
	364 58 (1, 1)
	365 dconst_1 (1, 1)
	366 dastore (1, 1)
	367 dup (1, 1)
	368 bipush (1, 1)
	369 59 (1, 1)
	370 dconst_1 (1, 1)
	371 dastore (1, 1)
	372 dup (1, 1)
	373 bipush (1, 1)
	374 60 (1, 1)
	375 dconst_1 (1, 1)
	376 dastore (1, 1)
	377 dup (1, 1)
	378 bipush (1, 1)
	379 61 (1, 1)
	380 dconst_1 (1, 1)
	381 dastore (1, 1)
	382 dup (1, 1)
	383 bipush (1, 1)
	384 62 (1, 1)
	385 dconst_1 (1, 1)
	386 dastore (1, 1)
	387 putstatic (1, 1)
	388 org/apache/commons/math3/transform/FastFourierTransformer.W_SUB_N_R:[D (1, 1)
	390 bipush (1, 1)
	391 63 (1, 1)
	392 newarray (1, 1)
	393 7 (1, 1)
	394 dup (1, 1)
	395 iconst_0 (1, 1)
	396 ldc2_w (1, 1)
	397 2.4492935982947064e-16 (1, 1)
	399 dastore (1, 1)
	400 dup (1, 1)
	401 iconst_1 (1, 1)
	402 ldc2_w (1, 1)
	403 -1.2246467991473532e-16 (1, 1)
	405 dastore (1, 1)
	406 dup (1, 1)
	407 iconst_2 (1, 1)
	408 ldc2_w (1, 1)
	409 -1.0 (1, 1)
	411 dastore (1, 1)
	412 dup (1, 1)
	413 iconst_3 (1, 1)
	414 ldc2_w (1, 1)
	415 -0.7071067811865475 (1, 1)
	417 dastore (1, 1)
	418 dup (1, 1)
	419 iconst_4 (1, 1)
	420 ldc2_w (1, 1)
	421 -0.3826834323650898 (1, 1)
	423 dastore (1, 1)
	424 dup (1, 1)
	425 iconst_5 (1, 1)
	426 ldc2_w (1, 1)
	427 -0.19509032201612825 (1, 1)
	429 dastore (1, 1)
	430 dup (1, 1)
	431 bipush (1, 1)
	432 6 (1, 1)
	433 ldc2_w (1, 1)
	434 -0.0980171403295606 (1, 1)
	436 dastore (1, 1)
	437 dup (1, 1)
	438 bipush (1, 1)
	439 7 (1, 1)
	440 ldc2_w (1, 1)
	441 -0.049067674327418015 (1, 1)
	443 dastore (1, 1)
	444 dup (1, 1)
	445 bipush (1, 1)
	446 8 (1, 1)
	447 ldc2_w (1, 1)
	448 -0.024541228522912288 (1, 1)
	450 dastore (1, 1)
	451 dup (1, 1)
	452 bipush (1, 1)
	453 9 (1, 1)
	454 ldc2_w (1, 1)
	455 -0.012271538285719925 (1, 1)
	457 dastore (1, 1)
	458 dup (1, 1)
	459 bipush (1, 1)
	460 10 (1, 1)
	461 ldc2_w (1, 1)
	462 -0.006135884649154475 (1, 1)
	464 dastore (1, 1)
	465 dup (1, 1)
	466 bipush (1, 1)
	467 11 (1, 1)
	468 ldc2_w (1, 1)
	469 -0.003067956762965976 (1, 1)
	471 dastore (1, 1)
	472 dup (1, 1)
	473 bipush (1, 1)
	474 12 (1, 1)
	475 ldc2_w (1, 1)
	476 -0.0015339801862847655 (1, 1)
	478 dastore (1, 1)
	479 dup (1, 1)
	480 bipush (1, 1)
	481 13 (1, 1)
	482 ldc2_w (1, 1)
	483 -0.0007669903187427045 (1, 1)
	485 dastore (1, 1)
	486 dup (1, 1)
	487 bipush (1, 1)
	488 14 (1, 1)
	489 ldc2_w (1, 1)
	490 -0.00038349518757139556 (1, 1)
	492 dastore (1, 1)
	493 dup (1, 1)
	494 bipush (1, 1)
	495 15 (1, 1)
	496 ldc2_w (1, 1)
	497 -0.0001917475973107033 (1, 1)
	499 dastore (1, 1)
	500 dup (1, 1)
	501 bipush (1, 1)
	502 16 (1, 1)
	503 ldc2_w (1, 1)
	504 -9.587379909597734e-05 (1, 1)
	506 dastore (1, 1)
	507 dup (1, 1)
	508 bipush (1, 1)
	509 17 (1, 1)
	510 ldc2_w (1, 1)
	511 -4.793689960306688e-05 (1, 1)
	513 dastore (1, 1)
	514 dup (1, 1)
	515 bipush (1, 1)
	516 18 (1, 1)
	517 ldc2_w (1, 1)
	518 -2.396844980841822e-05 (1, 1)
	520 dastore (1, 1)
	521 dup (1, 1)
	522 bipush (1, 1)
	523 19 (1, 1)
	524 ldc2_w (1, 1)
	525 -1.1984224905069705e-05 (1, 1)
	527 dastore (1, 1)
	528 dup (1, 1)
	529 bipush (1, 1)
	530 20 (1, 1)
	531 ldc2_w (1, 1)
	532 -5.9921124526424275e-06 (1, 1)
	534 dastore (1, 1)
	535 dup (1, 1)
	536 bipush (1, 1)
	537 21 (1, 1)
	538 ldc2_w (1, 1)
	539 -2.996056226334661e-06 (1, 1)
	541 dastore (1, 1)
	542 dup (1, 1)
	543 bipush (1, 1)
	544 22 (1, 1)
	545 ldc2_w (1, 1)
	546 -1.4980281131690111e-06 (1, 1)
	548 dastore (1, 1)
	549 dup (1, 1)
	550 bipush (1, 1)
	551 23 (1, 1)
	552 ldc2_w (1, 1)
	553 -7.490140565847157e-07 (1, 1)
	555 dastore (1, 1)
	556 dup (1, 1)
	557 bipush (1, 1)
	558 24 (1, 1)
	559 ldc2_w (1, 1)
	560 -3.7450702829238413e-07 (1, 1)
	562 dastore (1, 1)
	563 dup (1, 1)
	564 bipush (1, 1)
	565 25 (1, 1)
	566 ldc2_w (1, 1)
	567 -1.8725351414619535e-07 (1, 1)
	569 dastore (1, 1)
	570 dup (1, 1)
	571 bipush (1, 1)
	572 26 (1, 1)
	573 ldc2_w (1, 1)
	574 -9.362675707309808e-08 (1, 1)
	576 dastore (1, 1)
	577 dup (1, 1)
	578 bipush (1, 1)
	579 27 (1, 1)
	580 ldc2_w (1, 1)
	581 -4.681337853654909e-08 (1, 1)
	583 dastore (1, 1)
	584 dup (1, 1)
	585 bipush (1, 1)
	586 28 (1, 1)
	587 ldc2_w (1, 1)
	588 -2.340668926827455e-08 (1, 1)
	590 dastore (1, 1)
	591 dup (1, 1)
	592 bipush (1, 1)
	593 29 (1, 1)
	594 ldc2_w (1, 1)
	595 -1.1703344634137277e-08 (1, 1)
	597 dastore (1, 1)
	598 dup (1, 1)
	599 bipush (1, 1)
	600 30 (1, 1)
	601 ldc2_w (1, 1)
	602 -5.8516723170686385e-09 (1, 1)
	604 dastore (1, 1)
	605 dup (1, 1)
	606 bipush (1, 1)
	607 31 (1, 1)
	608 ldc2_w (1, 1)
	609 -2.9258361585343192e-09 (1, 1)
	611 dastore (1, 1)
	612 dup (1, 1)
	613 bipush (1, 1)
	614 32 (1, 1)
	615 ldc2_w (1, 1)
	616 -1.4629180792671596e-09 (1, 1)
	618 dastore (1, 1)
	619 dup (1, 1)
	620 bipush (1, 1)
	621 33 (1, 1)
	622 ldc2_w (1, 1)
	623 -7.314590396335798e-10 (1, 1)
	625 dastore (1, 1)
	626 dup (1, 1)
	627 bipush (1, 1)
	628 34 (1, 1)
	629 ldc2_w (1, 1)
	630 -3.657295198167899e-10 (1, 1)
	632 dastore (1, 1)
	633 dup (1, 1)
	634 bipush (1, 1)
	635 35 (1, 1)
	636 ldc2_w (1, 1)
	637 -1.8286475990839495e-10 (1, 1)
	639 dastore (1, 1)
	640 dup (1, 1)
	641 bipush (1, 1)
	642 36 (1, 1)
	643 ldc2_w (1, 1)
	644 -9.143237995419748e-11 (1, 1)
	646 dastore (1, 1)
	647 dup (1, 1)
	648 bipush (1, 1)
	649 37 (1, 1)
	650 ldc2_w (1, 1)
	651 -4.571618997709874e-11 (1, 1)
	653 dastore (1, 1)
	654 dup (1, 1)
	655 bipush (1, 1)
	656 38 (1, 1)
	657 ldc2_w (1, 1)
	658 -2.285809498854937e-11 (1, 1)
	660 dastore (1, 1)
	661 dup (1, 1)
	662 bipush (1, 1)
	663 39 (1, 1)
	664 ldc2_w (1, 1)
	665 -1.1429047494274685e-11 (1, 1)
	667 dastore (1, 1)
	668 dup (1, 1)
	669 bipush (1, 1)
	670 40 (1, 1)
	671 ldc2_w (1, 1)
	672 -5.714523747137342e-12 (1, 1)
	674 dastore (1, 1)
	675 dup (1, 1)
	676 bipush (1, 1)
	677 41 (1, 1)
	678 ldc2_w (1, 1)
	679 -2.857261873568671e-12 (1, 1)
	681 dastore (1, 1)
	682 dup (1, 1)
	683 bipush (1, 1)
	684 42 (1, 1)
	685 ldc2_w (1, 1)
	686 -1.4286309367843356e-12 (1, 1)
	688 dastore (1, 1)
	689 dup (1, 1)
	690 bipush (1, 1)
	691 43 (1, 1)
	692 ldc2_w (1, 1)
	693 -7.143154683921678e-13 (1, 1)
	695 dastore (1, 1)
	696 dup (1, 1)
	697 bipush (1, 1)
	698 44 (1, 1)
	699 ldc2_w (1, 1)
	700 -3.571577341960839e-13 (1, 1)
	702 dastore (1, 1)
	703 dup (1, 1)
	704 bipush (1, 1)
	705 45 (1, 1)
	706 ldc2_w (1, 1)
	707 -1.7857886709804195e-13 (1, 1)
	709 dastore (1, 1)
	710 dup (1, 1)
	711 bipush (1, 1)
	712 46 (1, 1)
	713 ldc2_w (1, 1)
	714 -8.928943354902097e-14 (1, 1)
	716 dastore (1, 1)
	717 dup (1, 1)
	718 bipush (1, 1)
	719 47 (1, 1)
	720 ldc2_w (1, 1)
	721 -4.4644716774510487e-14 (1, 1)
	723 dastore (1, 1)
	724 dup (1, 1)
	725 bipush (1, 1)
	726 48 (1, 1)
	727 ldc2_w (1, 1)
	728 -2.2322358387255243e-14 (1, 1)
	730 dastore (1, 1)
	731 dup (1, 1)
	732 bipush (1, 1)
	733 49 (1, 1)
	734 ldc2_w (1, 1)
	735 -1.1161179193627622e-14 (1, 1)
	737 dastore (1, 1)
	738 dup (1, 1)
	739 bipush (1, 1)
	740 50 (1, 1)
	741 ldc2_w (1, 1)
	742 -5.580589596813811e-15 (1, 1)
	744 dastore (1, 1)
	745 dup (1, 1)
	746 bipush (1, 1)
	747 51 (1, 1)
	748 ldc2_w (1, 1)
	749 -2.7902947984069054e-15 (1, 1)
	751 dastore (1, 1)
	752 dup (1, 1)
	753 bipush (1, 1)
	754 52 (1, 1)
	755 ldc2_w (1, 1)
	756 -1.3951473992034527e-15 (1, 1)
	758 dastore (1, 1)
	759 dup (1, 1)
	760 bipush (1, 1)
	761 53 (1, 1)
	762 ldc2_w (1, 1)
	763 -6.975736996017264e-16 (1, 1)
	765 dastore (1, 1)
	766 dup (1, 1)
	767 bipush (1, 1)
	768 54 (1, 1)
	769 ldc2_w (1, 1)
	770 -3.487868498008632e-16 (1, 1)
	772 dastore (1, 1)
	773 dup (1, 1)
	774 bipush (1, 1)
	775 55 (1, 1)
	776 ldc2_w (1, 1)
	777 -1.743934249004316e-16 (1, 1)
	779 dastore (1, 1)
	780 dup (1, 1)
	781 bipush (1, 1)
	782 56 (1, 1)
	783 ldc2_w (1, 1)
	784 -8.71967124502158e-17 (1, 1)
	786 dastore (1, 1)
	787 dup (1, 1)
	788 bipush (1, 1)
	789 57 (1, 1)
	790 ldc2_w (1, 1)
	791 -4.35983562251079e-17 (1, 1)
	793 dastore (1, 1)
	794 dup (1, 1)
	795 bipush (1, 1)
	796 58 (1, 1)
	797 ldc2_w (1, 1)
	798 -2.179917811255395e-17 (1, 1)
	800 dastore (1, 1)
	801 dup (1, 1)
	802 bipush (1, 1)
	803 59 (1, 1)
	804 ldc2_w (1, 1)
	805 -1.0899589056276974e-17 (1, 1)
	807 dastore (1, 1)
	808 dup (1, 1)
	809 bipush (1, 1)
	810 60 (1, 1)
	811 ldc2_w (1, 1)
	812 -5.449794528138487e-18 (1, 1)
	814 dastore (1, 1)
	815 dup (1, 1)
	816 bipush (1, 1)
	817 61 (1, 1)
	818 ldc2_w (1, 1)
	819 -2.7248972640692436e-18 (1, 1)
	821 dastore (1, 1)
	822 dup (1, 1)
	823 bipush (1, 1)
	824 62 (1, 1)
	825 ldc2_w (1, 1)
	826 -1.3624486320346218e-18 (1, 1)
	828 dastore (1, 1)
	829 putstatic (1, 1)
	830 org/apache/commons/math3/transform/FastFourierTransformer.W_SUB_N_I:[D (1, 1)
	832 return (1, 1)

