Method: transform
	0 aload_0 (0, 0)
	1 aload_1 (0, 0)
	2 invokevirtual (0, 0)
	3 org/apache/commons/math3/transform/FastHadamardTransformer.fht:([I)[I (0, 0)
	5 areturn (0, 0)

Method: fht
	0 aload_1 (0, 0)
	1 arraylength (0, 0)
	2 istore_2 (0, 0)
	3 iload_2 (0, 0)
	4 iconst_2 (0, 0)
	5 idiv (0, 0)
	6 istore_3 (0, 0)
	7 iload_2 (1, 1)
	8 i2l (1, 1)
	9 invokestatic (1, 1)
	10 org/apache/commons/math3/util/ArithmeticUtils.isPowerOfTwo:(J)Z (1, 1)
	12 ifne (1, 1)
	13 25 (1, 1)
	15 new (1, 1)
	16 org/apache/commons/math3/exception/MathIllegalArgumentException (1, 1)
	18 dup (1, 1)
	19 getstatic (1, 1)
	20 org/apache/commons/math3/exception/util/LocalizedFormats.NOT_POWER_OF_TWO:Lorg/apache/commons/math3/exception/util/LocalizedFormats; (1, 1)
	22 iconst_1 (1, 1)
	23 anewarray (1, 1)
	24 java/lang/Object (1, 1)
	26 dup (1, 1)
	27 iconst_0 (1, 1)
	28 iload_2 (1, 1)
	29 invokestatic (1, 1)
	30 java/lang/Integer.valueOf:(I)Ljava/lang/Integer; (1, 1)
	32 aastore (1, 1)
	33 invokespecial (1, 1)
	34 org/apache/commons/math3/exception/MathIllegalArgumentException.<init>:(Lorg/apache/commons/math3/exception/util/Localizable;[Ljava/lang/Object;)V (1, 1)
	36 athrow (1, 1)
	37 iload_2 (0, 0)
	38 newarray (0, 0)
	39 10 (0, 0)
	40 astore (0, 0)
	41 #4 (0, 0)
	42 aload_1 (0, 0)
	43 invokevirtual (0, 0)
	44 [I.clone:()Ljava/lang/Object; (0, 0)
	46 checkcast (0, 0)
	47 [I (0, 0)
	49 astore (0, 0)
	50 #5 (0, 0)
	51 iconst_1 (1, 4)
	52 istore (1, 4)
	53 #6 (1, 4)
	54 iload (1, 4)
	55 #6 (1, 4)
	56 iload_2 (1, 4)
	57 if_icmpge (1, 4)
	58 106 (1, 4)
	60 aload (2, 5)
	61 #5 (2, 5)
	62 astore (2, 5)
	63 #7 (2, 5)
	64 aload (2, 5)
	65 #4 (2, 5)
	66 astore (2, 5)
	67 #5 (2, 5)
	68 aload (2, 5)
	69 #7 (2, 5)
	70 astore (2, 5)
	71 #4 (2, 5)
	72 iconst_0 (3, 4)
	73 istore (3, 4)
	74 #8 (3, 4)
	75 iload (3, 4)
	76 #8 (3, 4)
	77 iload_3 (3, 4)
	78 if_icmpge (3, 4)
	79 33 (3, 4)
	81 iconst_2 (3, 4)
	82 iload (3, 4)
	83 #8 (3, 4)
	84 imul (3, 4)
	85 istore (3, 4)
	86 #9 (3, 4)
	87 aload (3, 4)
	88 #5 (3, 4)
	89 iload (3, 4)
	90 #8 (3, 4)
	91 aload (3, 4)
	92 #4 (3, 4)
	93 iload (3, 4)
	94 #9 (3, 4)
	95 iaload (3, 4)
	96 aload (3, 4)
	97 #4 (3, 4)
	98 iload (3, 4)
	99 #9 (3, 4)
	100 iconst_1 (3, 4)
	101 iadd (3, 4)
	102 iaload (3, 4)
	103 iadd (3, 4)
	104 iastore (3, 4)
	105 iinc (3, 4)
	106 #8 (3, 4)
	107 -89 (3, 4)
	108 goto (3, 4)
	109 -33 (3, 4)
	111 iload_3 (3, 4)
	112 istore (3, 4)
	113 #8 (3, 4)
	114 iload (3, 4)
	115 #8 (3, 4)
	116 iload_2 (3, 4)
	117 if_icmpge (3, 4)
	118 37 (3, 4)
	120 iconst_2 (3, 4)
	121 iload (3, 4)
	122 #8 (3, 4)
	123 imul (3, 4)
	124 istore (3, 4)
	125 #9 (3, 4)
	126 aload (3, 4)
	127 #5 (3, 4)
	128 iload (3, 4)
	129 #8 (3, 4)
	130 aload (3, 4)
	131 #4 (3, 4)
	132 iload (3, 4)
	133 #9 (3, 4)
	134 iload_2 (3, 4)
	135 isub (3, 4)
	136 iaload (3, 4)
	137 aload (3, 4)
	138 #4 (3, 4)
	139 iload (3, 4)
	140 #9 (3, 4)
	141 iload_2 (3, 4)
	142 isub (3, 4)
	143 iconst_1 (3, 4)
	144 iadd (3, 4)
	145 iaload (3, 4)
	146 isub (3, 4)
	147 iastore (3, 4)
	148 iinc (3, 4)
	149 #8 (3, 4)
	150 -89 (3, 4)
	151 goto (3, 4)
	152 -37 (3, 4)
	154 iload (3, 4)
	155 #6 (3, 4)
	156 iconst_1 (3, 4)
	157 ishl (3, 4)
	158 istore (3, 4)
	159 #6 (3, 4)
	160 goto (3, 4)
	161 -106 (3, 4)
	163 aload (2, 5)
	164 #5 (2, 5)
	165 areturn (1, 5)

