Method: <init>
	0 aload_0 (0, 0)
	1 dload_1 (0, 0)
	2 putfield (0, 0)
	3 org/apache/commons/math3/ml/neuralnet/FeatureInitializerFactory$1.val$init:D (0, 0)
	5 aload_0 (0, 0)
	6 aload_3 (0, 0)
	7 putfield (0, 0)
	8 org/apache/commons/math3/ml/neuralnet/FeatureInitializerFactory$1.val$f:Lorg/apache/commons/math3/analysis/UnivariateFunction; (0, 0)
	10 aload_0 (0, 0)
	11 dload (0, 0)
	12 #4 (0, 0)
	13 putfield (0, 0)
	14 org/apache/commons/math3/ml/neuralnet/FeatureInitializerFactory$1.val$inc:D (0, 0)
	16 aload_0 (0, 0)
	17 invokespecial (0, 0)
	18 java/lang/Object.<init>:()V (0, 0)
	20 aload_0 (0, 0)
	21 aload_0 (0, 0)
	22 getfield (0, 0)
	23 org/apache/commons/math3/ml/neuralnet/FeatureInitializerFactory$1.val$init:D (0, 0)
	25 putfield (0, 0)
	26 org/apache/commons/math3/ml/neuralnet/FeatureInitializerFactory$1.arg:D (0, 0)
	28 return (0, 0)

Method: value
	0 aload_0 (0, 0)
	1 getfield (0, 0)
	2 org/apache/commons/math3/ml/neuralnet/FeatureInitializerFactory$1.val$f:Lorg/apache/commons/math3/analysis/UnivariateFunction; (0, 0)
	4 aload_0 (0, 0)
	5 getfield (0, 0)
	6 org/apache/commons/math3/ml/neuralnet/FeatureInitializerFactory$1.arg:D (0, 0)
	8 invokeinterface (0, 0)
	9 org/apache/commons/math3/analysis/UnivariateFunction.org/apache/commons/math3/ml/neuralnet/FeatureInitializerFactory$1 (0, 0)
	11 0 (0, 0)
	13 dstore_1 (0, 0)
	14 aload_0 (0, 0)
	15 dup (0, 0)
	16 getfield (0, 0)
	17 org/apache/commons/math3/ml/neuralnet/FeatureInitializerFactory$1.arg:D (0, 0)
	19 aload_0 (0, 0)
	20 getfield (0, 0)
	21 org/apache/commons/math3/ml/neuralnet/FeatureInitializerFactory$1.val$inc:D (0, 0)
	23 dadd (0, 0)
	24 putfield (0, 0)
	25 org/apache/commons/math3/ml/neuralnet/FeatureInitializerFactory$1.arg:D (0, 0)
	27 dload_1 (0, 0)
	28 dreturn (0, 0)

