Method: uniform
	0 new (0, 1)
	3 dup (0, 1)
	4 dload_0 (0, 1)
	5 dload_2 (0, 1)
	6 invokespecial (0, 1)
	9 new (0, 1)
	12 dup (0, 1)
	13 dconst_0 (0, 1)
	14 invokespecial (0, 1)
	17 dconst_0 (0, 1)
	18 dconst_0 (0, 1)
	19 invokestatic (0, 1)
	22 invokestatic (0, 1)
	25 areturn (0, 1)

Method: function
	0 new (0, 0)
	3 dup (0, 0)
	4 dload_1 (0, 0)
	5 aload_0 (0, 0)
	6 dload_3 (0, 0)
	7 invokespecial (0, 0)
	10 areturn (0, 0)

Method: randomize
	0 new (0, 0)
	3 dup (0, 0)
	4 aload_1 (0, 0)
	5 aload_0 (0, 0)
	6 invokespecial (0, 0)
	9 areturn (0, 0)

