Method: value
	0 aload_0 (0, 0)
	1 getfield (0, 0)
	2 org/apache/commons/math3/ml/neuralnet/FeatureInitializerFactory$2.val$orig:Lorg/apache/commons/math3/ml/neuralnet/FeatureInitializer; (0, 0)
	4 invokeinterface (0, 0)
	5 org/apache/commons/math3/ml/neuralnet/FeatureInitializer.org/apache/commons/math3/distribution/RealDistribution (0, 0)
	7 0 (0, 0)
	9 aload_0 (0, 0)
	10 getfield (0, 0)
	11 org/apache/commons/math3/ml/neuralnet/FeatureInitializerFactory$2.val$random:Lorg/apache/commons/math3/distribution/RealDistribution; (0, 0)
	13 invokeinterface (0, 0)
	14 org/apache/commons/math3/distribution/RealDistribution.org/apache/commons/math3/ml/neuralnet/FeatureInitializerFactory$2 (0, 0)
	16 0 (0, 0)
	18 dadd (0, 0)
	19 dreturn (0, 0)

