Method: <init>
	0 aload_0 (0, 0)
	1 invokespecial (0, 0)
	2 java/lang/Object.<init>:()V (0, 0)
	4 aload_0 (0, 0)
	5 aload_1 (0, 0)
	6 putfield (0, 0)
	7 org/apache/commons/math3/ml/neuralnet/MapUtils$PairNeuronDouble.neuron:Lorg/apache/commons/math3/ml/neuralnet/Neuron; (0, 0)
	9 aload_0 (0, 0)
	10 dload_2 (0, 0)
	11 putfield (0, 0)
	12 org/apache/commons/math3/ml/neuralnet/MapUtils$PairNeuronDouble.value:D (0, 0)
	14 return (0, 0)

Method: getNeuron
	0 aload_0 (0, 0)
	1 getfield (0, 0)
	2 org/apache/commons/math3/ml/neuralnet/MapUtils$PairNeuronDouble.neuron:Lorg/apache/commons/math3/ml/neuralnet/Neuron; (0, 0)
	4 areturn (0, 0)

Method: access$000
	0 aload_0 (0, 0)
	1 getfield (0, 0)
	2 org/apache/commons/math3/ml/neuralnet/MapUtils$PairNeuronDouble.value:D (0, 0)
	4 dreturn (0, 0)

Method: <clinit>
	0 new (0, 0)
	1 org/apache/commons/math3/ml/neuralnet/MapUtils$PairNeuronDouble$1 (0, 0)
	3 dup (0, 0)
	4 invokespecial (0, 0)
	5 org/apache/commons/math3/ml/neuralnet/MapUtils$PairNeuronDouble$1.<init>:()V (0, 0)
	7 putstatic (0, 0)
	8 org/apache/commons/math3/ml/neuralnet/MapUtils$PairNeuronDouble.COMPARATOR:Ljava/util/Comparator; (0, 0)
	10 return (0, 0)

