Method: <init>
	0 aload_0 (0, 0)
	1 invokespecial (0, 0)
	2 java/lang/Object.<init>:()V (0, 0)
	4 aload_0 (0, 0)
	5 new (0, 0)
	6 java/util/concurrent/ConcurrentHashMap (0, 0)
	8 dup (0, 0)
	9 invokespecial (0, 0)
	10 java/util/concurrent/ConcurrentHashMap.<init>:()V (0, 0)
	12 putfield (0, 0)
	13 org/apache/commons/math3/ml/neuralnet/Network.neuronMap:Ljava/util/concurrent/ConcurrentHashMap; (0, 0)
	15 aload_0 (1, 1)
	16 new (1, 1)
	17 java/util/concurrent/ConcurrentHashMap (1, 1)
	19 dup (1, 1)
	20 invokespecial (1, 1)
	21 java/util/concurrent/ConcurrentHashMap.<init>:()V (1, 1)
	23 putfield (1, 1)
	24 org/apache/commons/math3/ml/neuralnet/Network.linkMap:Ljava/util/concurrent/ConcurrentHashMap; (1, 1)
	26 aload_0 (10, 1)
	27 new (10, 1)
	28 java/util/concurrent/atomic/AtomicLong (10, 1)
	30 dup (10, 1)
	31 lload_1 (10, 1)
	32 invokespecial (10, 1)
	33 java/util/concurrent/atomic/AtomicLong.<init>:(J)V (10, 1)
	35 putfield (10, 1)
	36 org/apache/commons/math3/ml/neuralnet/Network.nextId:Ljava/util/concurrent/atomic/AtomicLong; (10, 1)
	38 aload_0 (10, 1)
	39 iload_3 (10, 1)
	40 putfield (10, 1)
	41 org/apache/commons/math3/ml/neuralnet/Network.featureSize:I (10, 1)
	43 return (1, 1)

Method: copy
	0 new (0, 0)
	1 org/apache/commons/math3/ml/neuralnet/Network (0, 0)
	3 dup (0, 0)
	4 aload_0 (0, 0)
	5 getfield (0, 0)
	6 org/apache/commons/math3/ml/neuralnet/Network.nextId:Ljava/util/concurrent/atomic/AtomicLong; (0, 0)
	8 invokevirtual (0, 0)
	9 java/util/concurrent/atomic/AtomicLong.get:()J (0, 0)
	11 aload_0 (0, 0)
	12 getfield (0, 0)
	13 org/apache/commons/math3/ml/neuralnet/Network.featureSize:I (0, 0)
	15 invokespecial (0, 0)
	16 org/apache/commons/math3/ml/neuralnet/Network.<init>:(JI)V (0, 0)
	18 astore_1 (0, 0)
	19 aload_0 (1, 4)
	20 getfield (1, 4)
	21 org/apache/commons/math3/ml/neuralnet/Network.neuronMap:Ljava/util/concurrent/ConcurrentHashMap; (1, 4)
	23 invokevirtual (1, 4)
	24 java/util/concurrent/ConcurrentHashMap.entrySet:()Ljava/util/Set; (1, 4)
	26 invokeinterface (1, 4)
	27 java/util/Set.java/util/Iterator (1, 4)
	29 0 (1, 4)
	31 astore_2 (1, 4)
	32 aload_2 (1, 4)
	33 invokeinterface (1, 4)
	34 java/util/Iterator.next:()Ljava/lang/Object; (1, 4)
	36 0 (1, 4)
	38 ifeq (1, 4)
	39 42 (1, 4)
	41 aload_2 (1, 4)
	42 invokeinterface (1, 4)
	43 java/util/Iterator.java/util/Map (1, 4)
	45 0 (1, 4)
	47 checkcast (1, 4)
	48 java/util/Map$Entry (1, 4)
	50 astore_3 (1, 4)
	51 aload_1 (1, 4)
	52 getfield (1, 4)
	53 org/apache/commons/math3/ml/neuralnet/Network.neuronMap:Ljava/util/concurrent/ConcurrentHashMap; (1, 4)
	55 aload_3 (1, 4)
	56 invokeinterface (1, 4)
	57 java/util/Map$Entry.getValue:()Ljava/lang/Object; (1, 4)
	59 0 (1, 4)
	61 aload_3 (1, 4)
	62 invokeinterface (1, 4)
	63 java/util/Map$Entry.org/apache/commons/math3/ml/neuralnet/Neuron (1, 4)
	65 0 (1, 4)
	67 checkcast (1, 4)
	68 org/apache/commons/math3/ml/neuralnet/Neuron (1, 4)
	70 invokevirtual (1, 4)
	71 org/apache/commons/math3/ml/neuralnet/Neuron.copy:()Lorg/apache/commons/math3/ml/neuralnet/Neuron; (1, 4)
	73 invokevirtual (1, 4)
	74 java/util/concurrent/ConcurrentHashMap.put:(Ljava/lang/Object;Ljava/lang/Object;)Ljava/lang/Object; (1, 4)
	76 pop (1, 4)
	77 goto (0, 0)
	78 -45 (0, 0)
	80 aload_0 (1, 4)
	81 getfield (1, 4)
	82 org/apache/commons/math3/ml/neuralnet/Network.linkMap:Ljava/util/concurrent/ConcurrentHashMap; (1, 4)
	84 invokevirtual (1, 4)
	85 java/util/concurrent/ConcurrentHashMap.entrySet:()Ljava/util/Set; (1, 4)
	87 invokeinterface (1, 4)
	88 java/util/Set.java/util/Iterator (1, 4)
	90 0 (1, 4)
	92 astore_2 (1, 4)
	93 aload_2 (1, 4)
	94 invokeinterface (1, 4)
	95 java/util/Iterator.next:()Ljava/lang/Object; (1, 4)
	97 0 (1, 4)
	99 ifeq (1, 4)
	100 46 (1, 4)
	102 aload_2 (1, 4)
	103 invokeinterface (1, 4)
	104 java/util/Iterator.java/util/Map (1, 4)
	106 0 (1, 4)
	108 checkcast (1, 4)
	109 java/util/Map$Entry (1, 4)
	111 astore_3 (1, 4)
	112 aload_1 (1, 4)
	113 getfield (1, 4)
	114 org/apache/commons/math3/ml/neuralnet/Network.linkMap:Ljava/util/concurrent/ConcurrentHashMap; (1, 4)
	116 aload_3 (1, 4)
	117 invokeinterface (1, 4)
	118 java/util/Map$Entry.getValue:()Ljava/lang/Object; (1, 4)
	120 0 (1, 4)
	122 new (1, 4)
	123 java/util/HashSet (1, 4)
	125 dup (1, 4)
	126 aload_3 (1, 4)
	127 invokeinterface (1, 4)
	128 java/util/Map$Entry.org/apache/commons/math3/ml/neuralnet/Neuron (1, 4)
	130 0 (1, 4)
	132 checkcast (1, 4)
	133 java/util/Collection (1, 4)
	135 invokespecial (1, 4)
	136 java/util/HashSet.<init>:(Ljava/util/Collection;)V (1, 4)
	138 invokevirtual (1, 4)
	139 java/util/concurrent/ConcurrentHashMap.put:(Ljava/lang/Object;Ljava/lang/Object;)Ljava/lang/Object; (1, 4)
	141 pop (1, 4)
	142 goto (0, 0)
	143 -49 (0, 0)
	145 aload_1 (0, 0)
	146 areturn (0, 0)

Method: iterator
	0 aload_0 (0, 0)
	1 getfield (0, 0)
	2 org/apache/commons/math3/ml/neuralnet/Network.neuronMap:Ljava/util/concurrent/ConcurrentHashMap; (0, 0)
	4 invokevirtual (0, 0)
	5 java/util/concurrent/ConcurrentHashMap.values:()Ljava/util/Collection; (0, 0)
	7 invokeinterface (0, 0)
	8 java/util/Collection.java/util/Iterator (0, 0)
	10 0 (0, 0)
	12 areturn (0, 0)

Method: getNeurons
	0 new (0, 0)
	1 java/util/ArrayList (0, 0)
	3 dup (0, 0)
	4 invokespecial (0, 0)
	5 java/util/ArrayList.<init>:()V (0, 0)
	7 astore_2 (0, 0)
	8 aload_2 (0, 0)
	9 aload_0 (0, 0)
	10 getfield (0, 0)
	11 org/apache/commons/math3/ml/neuralnet/Network.neuronMap:Ljava/util/concurrent/ConcurrentHashMap; (0, 0)
	13 invokevirtual (0, 0)
	14 java/util/concurrent/ConcurrentHashMap.values:()Ljava/util/Collection; (0, 0)
	16 invokeinterface (0, 0)
	17 java/util/List.java/util/Collections (0, 0)
	19 0 (0, 0)
	21 pop (0, 0)
	22 aload_2 (0, 0)
	23 aload_1 (0, 0)
	24 invokestatic (0, 0)
	25 java/util/Collections.sort:(Ljava/util/List;Ljava/util/Comparator;)V (0, 0)
	27 aload_2 (0, 0)
	28 areturn (0, 0)

Method: createNeuron
	0 aload_1 (1, 1)
	1 arraylength (1, 1)
	2 aload_0 (1, 1)
	3 getfield (1, 1)
	4 org/apache/commons/math3/ml/neuralnet/Network.featureSize:I (1, 1)
	6 if_icmpeq (1, 1)
	7 17 (1, 1)
	9 new (1, 1)
	10 org/apache/commons/math3/exception/DimensionMismatchException (1, 1)
	12 dup (1, 1)
	13 aload_1 (1, 1)
	14 arraylength (1, 1)
	15 aload_0 (1, 1)
	16 getfield (1, 1)
	17 org/apache/commons/math3/ml/neuralnet/Network.featureSize:I (1, 1)
	19 invokespecial (1, 1)
	20 org/apache/commons/math3/exception/DimensionMismatchException.<init>:(II)V (1, 1)
	22 athrow (1, 1)
	23 aload_0 (0, 0)
	24 invokespecial (0, 0)
	25 org/apache/commons/math3/ml/neuralnet/Network.createNextId:()Ljava/lang/Long; (0, 0)
	27 invokevirtual (0, 0)
	28 java/lang/Long.longValue:()J (0, 0)
	30 lstore_2 (0, 0)
	31 aload_0 (0, 0)
	32 getfield (0, 0)
	33 org/apache/commons/math3/ml/neuralnet/Network.neuronMap:Ljava/util/concurrent/ConcurrentHashMap; (0, 0)
	35 lload_2 (0, 0)
	36 invokestatic (0, 0)
	37 java/lang/Long.valueOf:(J)Ljava/lang/Long; (0, 0)
	39 new (0, 0)
	40 org/apache/commons/math3/ml/neuralnet/Neuron (0, 0)
	42 dup (0, 0)
	43 lload_2 (0, 0)
	44 aload_1 (0, 0)
	45 invokespecial (0, 0)
	46 org/apache/commons/math3/ml/neuralnet/Neuron.<init>:(J[D)V (0, 0)
	48 invokevirtual (0, 0)
	49 java/util/concurrent/ConcurrentHashMap.put:(Ljava/lang/Object;Ljava/lang/Object;)Ljava/lang/Object; (0, 0)
	51 pop (0, 0)
	52 aload_0 (0, 0)
	53 getfield (0, 0)
	54 org/apache/commons/math3/ml/neuralnet/Network.linkMap:Ljava/util/concurrent/ConcurrentHashMap; (0, 0)
	56 lload_2 (0, 0)
	57 invokestatic (0, 0)
	58 java/lang/Long.valueOf:(J)Ljava/lang/Long; (0, 0)
	60 new (0, 0)
	61 java/util/HashSet (0, 0)
	63 dup (0, 0)
	64 invokespecial (0, 0)
	65 java/util/HashSet.<init>:()V (0, 0)
	67 invokevirtual (0, 0)
	68 java/util/concurrent/ConcurrentHashMap.put:(Ljava/lang/Object;Ljava/lang/Object;)Ljava/lang/Object; (0, 0)
	70 pop (0, 0)
	71 lload_2 (0, 0)
	72 lreturn (0, 0)

Method: deleteNeuron
	0 aload_0 (0, 0)
	1 aload_1 (0, 0)
	2 invokevirtual (0, 0)
	3 org/apache/commons/math3/ml/neuralnet/Network.getNeighbours:(Lorg/apache/commons/math3/ml/neuralnet/Neuron;)Ljava/util/Collection; (0, 0)
	5 astore_2 (0, 0)
	6 aload_2 (1, 4)
	7 invokeinterface (1, 4)
	8 java/util/Collection.java/util/Iterator (1, 4)
	10 0 (1, 4)
	12 astore_3 (1, 4)
	13 aload_3 (1, 4)
	14 invokeinterface (1, 4)
	15 java/util/Iterator.next:()Ljava/lang/Object; (1, 4)
	17 0 (1, 4)
	19 ifeq (1, 4)
	20 24 (1, 4)
	22 aload_3 (1, 4)
	23 invokeinterface (1, 4)
	24 java/util/Iterator.java/util/Map (1, 4)
	26 0 (1, 4)
	28 checkcast (1, 4)
	29 org/apache/commons/math3/ml/neuralnet/Neuron (1, 4)
	31 astore (1, 4)
	32 #4 (1, 4)
	33 aload_0 (1, 4)
	34 aload (1, 4)
	35 #4 (1, 4)
	36 aload_1 (1, 4)
	37 invokevirtual (1, 4)
	38 org/apache/commons/math3/ml/neuralnet/Network.deleteLink:(Lorg/apache/commons/math3/ml/neuralnet/Neuron;Lorg/apache/commons/math3/ml/neuralnet/Neuron;)V (1, 4)
	40 goto (0, 0)
	41 -27 (0, 0)
	43 aload_0 (1, 1)
	44 getfield (1, 1)
	45 org/apache/commons/math3/ml/neuralnet/Network.neuronMap:Ljava/util/concurrent/ConcurrentHashMap; (1, 1)
	47 aload_1 (1, 1)
	48 invokevirtual (1, 1)
	49 org/apache/commons/math3/ml/neuralnet/Neuron.getIdentifier:()J (1, 1)
	51 invokestatic (1, 1)
	52 java/lang/Long.valueOf:(J)Ljava/lang/Long; (1, 1)
	54 invokevirtual (1, 1)
	55 java/util/concurrent/ConcurrentHashMap.remove:(Ljava/lang/Object;)Ljava/lang/Object; (1, 1)
	57 pop (1, 1)
	58 return (0, 1)

Method: getFeaturesSize
	0 aload_0 (0, 0)
	1 getfield (0, 0)
	2 org/apache/commons/math3/ml/neuralnet/Network.featureSize:I (0, 0)
	4 ireturn (0, 0)

Method: addLink
	0 aload_1 (1, 1)
	1 invokevirtual (1, 1)
	2 org/apache/commons/math3/ml/neuralnet/Neuron.getIdentifier:()J (1, 1)
	4 lstore_3 (1, 1)
	5 aload_2 (2, 1)
	6 invokevirtual (2, 1)
	7 org/apache/commons/math3/ml/neuralnet/Neuron.getIdentifier:()J (2, 1)
	9 lstore (2, 1)
	10 #5 (2, 1)
	11 aload_1 (3, 1)
	12 aload_0 (3, 1)
	13 lload_3 (3, 1)
	14 invokevirtual (3, 1)
	15 org/apache/commons/math3/ml/neuralnet/Network.getNeuron:(J)Lorg/apache/commons/math3/ml/neuralnet/Neuron; (3, 1)
	17 if_acmpeq (3, 1)
	18 15 (3, 1)
	20 new (3, 1)
	21 java/util/NoSuchElementException (3, 1)
	23 dup (3, 1)
	24 lload_3 (3, 1)
	25 invokestatic (3, 1)
	26 java/lang/Long.toString:(J)Ljava/lang/String; (3, 1)
	28 invokespecial (3, 1)
	29 java/util/NoSuchElementException.<init>:(Ljava/lang/String;)V (3, 1)
	31 athrow (3, 1)
	32 aload_2 (3, 1)
	33 aload_0 (3, 1)
	34 lload (3, 1)
	35 #5 (3, 1)
	36 invokevirtual (3, 1)
	37 org/apache/commons/math3/ml/neuralnet/Network.getNeuron:(J)Lorg/apache/commons/math3/ml/neuralnet/Neuron; (3, 1)
	39 if_acmpeq (3, 1)
	40 16 (3, 1)
	42 new (3, 1)
	43 java/util/NoSuchElementException (3, 1)
	45 dup (3, 1)
	46 lload (3, 1)
	47 #5 (3, 1)
	48 invokestatic (3, 1)
	49 java/lang/Long.toString:(J)Ljava/lang/String; (3, 1)
	51 invokespecial (3, 1)
	52 java/util/NoSuchElementException.<init>:(Ljava/lang/String;)V (3, 1)
	54 athrow (3, 1)
	55 aload_0 (2, 1)
	56 aload_0 (2, 1)
	57 getfield (2, 1)
	58 org/apache/commons/math3/ml/neuralnet/Network.linkMap:Ljava/util/concurrent/ConcurrentHashMap; (2, 1)
	60 lload_3 (2, 1)
	61 invokestatic (2, 1)
	62 java/lang/Long.valueOf:(J)Ljava/lang/Long; (2, 1)
	64 invokevirtual (2, 1)
	65 java/util/concurrent/ConcurrentHashMap.get:(Ljava/lang/Object;)Ljava/lang/Object; (2, 1)
	67 checkcast (2, 1)
	68 java/util/Set (2, 1)
	70 lload (2, 1)
	71 #5 (2, 1)
	72 invokespecial (2, 1)
	73 org/apache/commons/math3/ml/neuralnet/Network.addLinkToLinkSet:(Ljava/util/Set;J)V (2, 1)
	75 return (0, 1)

Method: addLinkToLinkSet
	0 aload_1 (0, 0)
	1 lload_2 (0, 0)
	2 invokestatic (0, 0)
	3 java/lang/Long.valueOf:(J)Ljava/lang/Long; (0, 0)
	5 invokeinterface (0, 0)
	6 java/util/Set.deleteLinkFromLinkSet:(Ljava/util/Set;J)V (0, 0)
	8 0 (0, 0)
	10 pop (0, 0)
	11 return (0, 0)

Method: deleteLink
	0 aload_1 (1, 1)
	1 invokevirtual (1, 1)
	2 org/apache/commons/math3/ml/neuralnet/Neuron.getIdentifier:()J (1, 1)
	4 lstore_3 (1, 1)
	5 aload_2 (2, 1)
	6 invokevirtual (2, 1)
	7 org/apache/commons/math3/ml/neuralnet/Neuron.getIdentifier:()J (2, 1)
	9 lstore (2, 1)
	10 #5 (2, 1)
	11 aload_1 (3, 1)
	12 aload_0 (3, 1)
	13 lload_3 (3, 1)
	14 invokevirtual (3, 1)
	15 org/apache/commons/math3/ml/neuralnet/Network.getNeuron:(J)Lorg/apache/commons/math3/ml/neuralnet/Neuron; (3, 1)
	17 if_acmpeq (3, 1)
	18 15 (3, 1)
	20 new (3, 1)
	21 java/util/NoSuchElementException (3, 1)
	23 dup (3, 1)
	24 lload_3 (3, 1)
	25 invokestatic (3, 1)
	26 java/lang/Long.toString:(J)Ljava/lang/String; (3, 1)
	28 invokespecial (3, 1)
	29 java/util/NoSuchElementException.<init>:(Ljava/lang/String;)V (3, 1)
	31 athrow (3, 1)
	32 aload_2 (3, 1)
	33 aload_0 (3, 1)
	34 lload (3, 1)
	35 #5 (3, 1)
	36 invokevirtual (3, 1)
	37 org/apache/commons/math3/ml/neuralnet/Network.getNeuron:(J)Lorg/apache/commons/math3/ml/neuralnet/Neuron; (3, 1)
	39 if_acmpeq (3, 1)
	40 16 (3, 1)
	42 new (3, 1)
	43 java/util/NoSuchElementException (3, 1)
	45 dup (3, 1)
	46 lload (3, 1)
	47 #5 (3, 1)
	48 invokestatic (3, 1)
	49 java/lang/Long.toString:(J)Ljava/lang/String; (3, 1)
	51 invokespecial (3, 1)
	52 java/util/NoSuchElementException.<init>:(Ljava/lang/String;)V (3, 1)
	54 athrow (3, 1)
	55 aload_0 (2, 1)
	56 aload_0 (2, 1)
	57 getfield (2, 1)
	58 org/apache/commons/math3/ml/neuralnet/Network.linkMap:Ljava/util/concurrent/ConcurrentHashMap; (2, 1)
	60 lload_3 (2, 1)
	61 invokestatic (2, 1)
	62 java/lang/Long.valueOf:(J)Ljava/lang/Long; (2, 1)
	64 invokevirtual (2, 1)
	65 java/util/concurrent/ConcurrentHashMap.get:(Ljava/lang/Object;)Ljava/lang/Object; (2, 1)
	67 checkcast (2, 1)
	68 java/util/Set (2, 1)
	70 lload (2, 1)
	71 #5 (2, 1)
	72 invokespecial (2, 1)
	73 org/apache/commons/math3/ml/neuralnet/Network.deleteLinkFromLinkSet:(Ljava/util/Set;J)V (2, 1)
	75 return (0, 1)

Method: deleteLinkFromLinkSet
	0 aload_1 (0, 0)
	1 lload_2 (0, 0)
	2 invokestatic (0, 0)
	3 java/lang/Long.valueOf:(J)Ljava/lang/Long; (0, 0)
	5 invokeinterface (0, 0)
	6 java/util/Set.getNeighbours:(Ljava/lang/Iterable;Ljava/lang/Iterable;)Ljava/util/Collection; (0, 0)
	8 0 (0, 0)
	10 pop (0, 0)
	11 return (0, 0)

Method: getNeuron
	0 aload_0 (0, 0)
	1 getfield (0, 0)
	2 org/apache/commons/math3/ml/neuralnet/Network.neuronMap:Ljava/util/concurrent/ConcurrentHashMap; (0, 0)
	4 lload_1 (0, 0)
	5 invokestatic (0, 0)
	6 java/lang/Long.valueOf:(J)Ljava/lang/Long; (0, 0)
	8 invokevirtual (0, 0)
	9 java/util/concurrent/ConcurrentHashMap.get:(Ljava/lang/Object;)Ljava/lang/Object; (0, 0)
	11 checkcast (0, 0)
	12 org/apache/commons/math3/ml/neuralnet/Neuron (0, 0)
	14 astore_3 (0, 0)
	15 aload_3 (1, 1)
	16 ifnonnull (1, 1)
	17 15 (1, 1)
	19 new (1, 1)
	20 java/util/NoSuchElementException (1, 1)
	22 dup (1, 1)
	23 lload_1 (1, 1)
	24 invokestatic (1, 1)
	25 java/lang/Long.toString:(J)Ljava/lang/String; (1, 1)
	27 invokespecial (1, 1)
	28 java/util/NoSuchElementException.<init>:(Ljava/lang/String;)V (1, 1)
	30 athrow (1, 1)
	31 aload_3 (0, 0)
	32 areturn (0, 0)

Method: getNeighbours
	0 aload_0 (1, 1)
	1 getfield (1, 1)
	2 org/apache/commons/math3/ml/neuralnet/Network.linkMap:Ljava/util/concurrent/ConcurrentHashMap; (1, 1)
	4 aload_1 (1, 1)
	5 invokevirtual (1, 1)
	6 org/apache/commons/math3/ml/neuralnet/Neuron.getIdentifier:()J (1, 1)
	8 invokestatic (1, 1)
	9 java/lang/Long.valueOf:(J)Ljava/lang/Long; (1, 1)
	11 invokevirtual (1, 1)
	12 java/util/concurrent/ConcurrentHashMap.get:(Ljava/lang/Object;)Ljava/lang/Object; (1, 1)
	14 checkcast (1, 1)
	15 java/util/Set (1, 1)
	17 astore_3 (1, 1)
	18 aload_2 (2, 1)
	19 ifnull (2, 1)
	20 51 (2, 1)
	22 aload_2 (3, 4)
	23 invokeinterface (3, 4)
	24 java/lang/Iterable.java/util/Iterator (3, 4)
	26 0 (3, 4)
	28 astore (3, 4)
	29 #4 (3, 4)
	30 aload (3, 4)
	31 #4 (3, 4)
	32 invokeinterface (3, 4)
	33 java/util/Iterator.next:()Ljava/lang/Object; (3, 4)
	35 0 (3, 4)
	37 ifeq (3, 4)
	38 33 (3, 4)
	40 aload (3, 4)
	41 #4 (3, 4)
	42 invokeinterface (3, 4)
	43 java/util/Iterator.java/util/Map (3, 4)
	45 0 (3, 4)
	47 checkcast (3, 4)
	48 org/apache/commons/math3/ml/neuralnet/Neuron (3, 4)
	50 astore (3, 4)
	51 #5 (3, 4)
	52 aload_3 (4, 1)
	53 aload (4, 1)
	54 #5 (4, 1)
	55 invokevirtual (4, 1)
	56 org/apache/commons/math3/ml/neuralnet/Neuron.getIdentifier:()J (4, 1)
	58 invokestatic (4, 1)
	59 java/lang/Long.valueOf:(J)Ljava/lang/Long; (4, 1)
	61 invokeinterface (4, 1)
	62 java/util/Set.getNeighbours:(Ljava/lang/Iterable;Ljava/lang/Iterable;)Ljava/util/Collection; (4, 1)
	64 0 (4, 1)
	66 pop (4, 1)
	67 goto (2, 1)
	68 -37 (2, 1)
	70 new (1, 1)
	71 java/util/ArrayList (1, 1)
	73 dup (1, 1)
	74 invokespecial (1, 1)
	75 java/util/ArrayList.<init>:()V (1, 1)
	77 astore (1, 1)
	78 #4 (1, 1)
	79 aload_3 (2, 4)
	80 invokeinterface (2, 4)
	81 java/util/Set.java/util/Iterator (2, 4)
	83 0 (2, 4)
	85 astore (2, 4)
	86 #5 (2, 4)
	87 aload (2, 4)
	88 #5 (2, 4)
	89 invokeinterface (2, 4)
	90 java/util/Iterator.next:()Ljava/lang/Object; (2, 4)
	92 0 (2, 4)
	94 ifeq (2, 4)
	95 35 (2, 4)
	97 aload (2, 4)
	98 #5 (2, 4)
	99 invokeinterface (2, 4)
	100 java/util/Iterator.java/util/Map (2, 4)
	102 0 (2, 4)
	104 checkcast (2, 4)
	105 java/lang/Long (2, 4)
	107 astore (2, 4)
	108 #6 (2, 4)
	109 aload (2, 4)
	110 #4 (2, 4)
	111 aload_0 (2, 4)
	112 aload (2, 4)
	113 #6 (2, 4)
	114 invokevirtual (2, 4)
	115 java/lang/Long.longValue:()J (2, 4)
	117 invokevirtual (2, 4)
	118 org/apache/commons/math3/ml/neuralnet/Network.getNeuron:(J)Lorg/apache/commons/math3/ml/neuralnet/Neuron; (2, 4)
	120 invokeinterface (2, 4)
	121 java/util/List.deleteLinkFromLinkSet:(Ljava/util/Set;J)V (2, 4)
	123 0 (2, 4)
	125 pop (2, 4)
	126 goto (1, 1)
	127 -39 (1, 1)
	129 aload (1, 1)
	130 #4 (1, 1)
	131 areturn (0, 1)

Method: createNextId
	0 aload_0 (0, 0)
	1 getfield (0, 0)
	2 org/apache/commons/math3/ml/neuralnet/Network.nextId:Ljava/util/concurrent/atomic/AtomicLong; (0, 0)
	4 invokevirtual (0, 0)
	5 java/util/concurrent/atomic/AtomicLong.getAndIncrement:()J (0, 0)
	7 invokestatic (0, 0)
	8 java/lang/Long.valueOf:(J)Ljava/lang/Long; (0, 0)
	10 areturn (0, 0)

Method: readObject
	0 new (0, 0)
	1 java/lang/IllegalStateException (0, 0)
	3 dup (0, 0)
	4 invokespecial (0, 0)
	5 java/lang/IllegalStateException.<init>:()V (0, 0)
	7 athrow (0, 0)

Method: writeReplace
	0 aload_0 (0, 0)
	1 getfield (0, 0)
	2 org/apache/commons/math3/ml/neuralnet/Network.neuronMap:Ljava/util/concurrent/ConcurrentHashMap; (0, 0)
	4 invokevirtual (0, 0)
	5 java/util/concurrent/ConcurrentHashMap.values:()Ljava/util/Collection; (0, 0)
	7 iconst_0 (0, 0)
	8 anewarray (0, 0)
	9 org/apache/commons/math3/ml/neuralnet/Neuron (0, 0)
	11 invokeinterface (0, 0)
	12 java/util/Collection.size:()I (0, 0)
	14 0 (0, 0)
	16 checkcast (0, 0)
	17 [Lorg/apache/commons/math3/ml/neuralnet/Neuron; (0, 0)
	19 astore_1 (0, 0)
	20 aload_1 (0, 0)
	21 arraylength (0, 0)
	22 anewarray (0, 0)
	23 [J (0, 0)
	25 astore_2 (0, 0)
	26 iconst_0 (1, 4)
	27 istore_3 (1, 4)
	28 iload_3 (1, 4)
	29 aload_1 (1, 4)
	30 arraylength (1, 4)
	31 if_icmpge (1, 4)
	32 84 (1, 4)
	34 aload_0 (1, 4)
	35 aload_1 (1, 4)
	36 iload_3 (1, 4)
	37 aaload (1, 4)
	38 invokevirtual (1, 4)
	39 org/apache/commons/math3/ml/neuralnet/Network.getNeighbours:(Lorg/apache/commons/math3/ml/neuralnet/Neuron;)Ljava/util/Collection; (1, 4)
	41 astore (1, 4)
	42 #4 (1, 4)
	43 aload (1, 4)
	44 #4 (1, 4)
	45 invokeinterface (1, 4)
	46 java/util/Collection.org/apache/commons/math3/ml/neuralnet/Network$SerializationProxy (1, 4)
	48 0 (1, 4)
	50 newarray (1, 4)
	51 11 (1, 4)
	52 astore (1, 4)
	53 #5 (1, 4)
	54 iconst_0 (1, 4)
	55 istore (1, 4)
	56 #6 (1, 4)
	57 aload (2, 4)
	58 #4 (2, 4)
	59 invokeinterface (2, 4)
	60 java/util/Collection.java/util/Iterator (2, 4)
	62 0 (2, 4)
	64 astore (2, 4)
	65 #7 (2, 4)
	66 aload (2, 4)
	67 #7 (2, 4)
	68 invokeinterface (2, 4)
	69 java/util/Iterator.next:()Ljava/lang/Object; (2, 4)
	71 0 (2, 4)
	73 ifeq (2, 4)
	74 31 (2, 4)
	76 aload (2, 4)
	77 #7 (2, 4)
	78 invokeinterface (2, 4)
	79 java/util/Iterator.java/util/Map (2, 4)
	81 0 (2, 4)
	83 checkcast (2, 4)
	84 org/apache/commons/math3/ml/neuralnet/Neuron (2, 4)
	86 astore (2, 4)
	87 #8 (2, 4)
	88 aload (3, 1)
	89 #5 (3, 1)
	90 iload (3, 1)
	91 #6 (3, 1)
	92 aload (3, 1)
	93 #8 (3, 1)
	94 invokevirtual (3, 1)
	95 org/apache/commons/math3/ml/neuralnet/Neuron.getIdentifier:()J (3, 1)
	97 lastore (3, 1)
	98 iinc (3, 1)
	99 #6 (3, 1)
	100 -89 (3, 1)
	101 goto (1, 4)
	102 -35 (1, 4)
	104 aload_2 (1, 4)
	105 iload_3 (1, 4)
	106 aload (1, 4)
	107 #5 (1, 4)
	108 aastore (1, 4)
	109 iinc (1, 4)
	110 #3 (1, 4)
	111 -89 (1, 4)
	112 goto (1, 4)
	113 -84 (1, 4)
	115 new (0, 0)
	116 org/apache/commons/math3/ml/neuralnet/Network$SerializationProxy (0, 0)
	118 dup (0, 0)
	119 aload_0 (0, 0)
	120 getfield (0, 0)
	121 org/apache/commons/math3/ml/neuralnet/Network.nextId:Ljava/util/concurrent/atomic/AtomicLong; (0, 0)
	123 invokevirtual (0, 0)
	124 java/util/concurrent/atomic/AtomicLong.get:()J (0, 0)
	126 aload_0 (0, 0)
	127 getfield (0, 0)
	128 org/apache/commons/math3/ml/neuralnet/Network.featureSize:I (0, 0)
	130 aload_1 (0, 0)
	131 aload_2 (0, 0)
	132 invokespecial (0, 0)
	133 org/apache/commons/math3/ml/neuralnet/Network$SerializationProxy.<init>:(JI[Lorg/apache/commons/math3/ml/neuralnet/Neuron;[[J)V (0, 0)
	135 areturn (0, 0)

