Method: <init>
	0 aload_0 (0, 0)
	1 invokespecial (0, 0)
	2 java/lang/Object.<init>:()V (0, 0)
	4 aload_0 (0, 0)
	5 lload_1 (0, 0)
	6 putfield (0, 0)
	7 org/apache/commons/math3/ml/neuralnet/Network$SerializationProxy.nextId:J (0, 0)
	9 aload_0 (0, 0)
	10 iload_3 (0, 0)
	11 putfield (0, 0)
	12 org/apache/commons/math3/ml/neuralnet/Network$SerializationProxy.featureSize:I (0, 0)
	14 aload_0 (0, 0)
	15 aload (0, 0)
	16 #4 (0, 0)
	17 putfield (0, 0)
	18 org/apache/commons/math3/ml/neuralnet/Network$SerializationProxy.neuronList:[Lorg/apache/commons/math3/ml/neuralnet/Neuron; (0, 0)
	20 aload_0 (0, 0)
	21 aload (0, 0)
	22 #5 (0, 0)
	23 putfield (0, 0)
	24 org/apache/commons/math3/ml/neuralnet/Network$SerializationProxy.neighbourIdList:[[J (0, 0)
	26 return (0, 0)

Method: readResolve
	0 new (0, 0)
	1 org/apache/commons/math3/ml/neuralnet/Network (0, 0)
	3 dup (0, 0)
	4 aload_0 (0, 0)
	5 getfield (0, 0)
	6 org/apache/commons/math3/ml/neuralnet/Network$SerializationProxy.nextId:J (0, 0)
	8 aload_0 (0, 0)
	9 getfield (0, 0)
	10 org/apache/commons/math3/ml/neuralnet/Network$SerializationProxy.featureSize:I (0, 0)
	12 aload_0 (0, 0)
	13 getfield (0, 0)
	14 org/apache/commons/math3/ml/neuralnet/Network$SerializationProxy.neuronList:[Lorg/apache/commons/math3/ml/neuralnet/Neuron; (0, 0)
	16 aload_0 (0, 0)
	17 getfield (0, 0)
	18 org/apache/commons/math3/ml/neuralnet/Network$SerializationProxy.neighbourIdList:[[J (0, 0)
	20 invokespecial (0, 0)
	21 org/apache/commons/math3/ml/neuralnet/Network.<init>:(JI[Lorg/apache/commons/math3/ml/neuralnet/Neuron;[[J)V (0, 0)
	23 areturn (0, 0)

