Method: <init>
	0 aload_0 (0, 0)
	1 invokespecial (0, 0)
	2 java/lang/Object.<init>:()V (0, 0)
	4 aload_0 (0, 0)
	5 new (0, 0)
	6 java/util/concurrent/atomic/AtomicLong (0, 0)
	8 dup (0, 0)
	9 lconst_0 (0, 0)
	10 invokespecial (0, 0)
	11 java/util/concurrent/atomic/AtomicLong.<init>:(J)V (0, 0)
	13 putfield (0, 0)
	14 org/apache/commons/math3/ml/neuralnet/Neuron.numberOfAttemptedUpdates:Ljava/util/concurrent/atomic/AtomicLong; (0, 0)
	16 aload_0 (0, 0)
	17 new (0, 0)
	18 java/util/concurrent/atomic/AtomicLong (0, 0)
	20 dup (0, 0)
	21 lconst_0 (0, 0)
	22 invokespecial (0, 0)
	23 java/util/concurrent/atomic/AtomicLong.<init>:(J)V (0, 0)
	25 putfield (0, 0)
	26 org/apache/commons/math3/ml/neuralnet/Neuron.numberOfSuccessfulUpdates:Ljava/util/concurrent/atomic/AtomicLong; (0, 0)
	28 aload_0 (2, 1)
	29 lload_1 (2, 1)
	30 putfield (2, 1)
	31 org/apache/commons/math3/ml/neuralnet/Neuron.identifier:J (2, 1)
	33 aload_0 (2, 1)
	34 aload_3 (2, 1)
	35 arraylength (2, 1)
	36 putfield (2, 1)
	37 org/apache/commons/math3/ml/neuralnet/Neuron.size:I (2, 1)
	39 aload_0 (2, 1)
	40 new (2, 1)
	41 java/util/concurrent/atomic/AtomicReference (2, 1)
	43 dup (2, 1)
	44 aload_3 (2, 1)
	45 invokevirtual (2, 1)
	46 [D.clone:()Ljava/lang/Object; (2, 1)
	48 invokespecial (2, 1)
	49 java/util/concurrent/atomic/AtomicReference.<init>:(Ljava/lang/Object;)V (2, 1)
	51 putfield (2, 1)
	52 org/apache/commons/math3/ml/neuralnet/Neuron.features:Ljava/util/concurrent/atomic/AtomicReference; (2, 1)
	54 return (1, 1)

Method: copy
	0 new (0, 1)
	1 org/apache/commons/math3/ml/neuralnet/Neuron (0, 1)
	3 dup (0, 1)
	4 aload_0 (0, 1)
	5 invokevirtual (0, 1)
	6 org/apache/commons/math3/ml/neuralnet/Neuron.getIdentifier:()J (0, 1)
	8 aload_0 (0, 1)
	9 invokevirtual (0, 1)
	10 org/apache/commons/math3/ml/neuralnet/Neuron.getFeatures:()[D (0, 1)
	12 invokespecial (0, 1)
	13 org/apache/commons/math3/ml/neuralnet/Neuron.<init>:(J[D)V (0, 1)
	15 astore_1 (0, 1)
	16 aload_1 (0, 1)
	17 getfield (0, 1)
	18 org/apache/commons/math3/ml/neuralnet/Neuron.numberOfAttemptedUpdates:Ljava/util/concurrent/atomic/AtomicLong; (0, 1)
	20 aload_0 (0, 1)
	21 getfield (0, 1)
	22 org/apache/commons/math3/ml/neuralnet/Neuron.numberOfAttemptedUpdates:Ljava/util/concurrent/atomic/AtomicLong; (0, 1)
	24 invokevirtual (0, 1)
	25 java/util/concurrent/atomic/AtomicLong.get:()J (0, 1)
	27 invokevirtual (0, 1)
	28 java/util/concurrent/atomic/AtomicLong.set:(J)V (0, 1)
	30 aload_1 (0, 1)
	31 getfield (0, 1)
	32 org/apache/commons/math3/ml/neuralnet/Neuron.numberOfSuccessfulUpdates:Ljava/util/concurrent/atomic/AtomicLong; (0, 1)
	34 aload_0 (0, 1)
	35 getfield (0, 1)
	36 org/apache/commons/math3/ml/neuralnet/Neuron.numberOfSuccessfulUpdates:Ljava/util/concurrent/atomic/AtomicLong; (0, 1)
	38 invokevirtual (0, 1)
	39 java/util/concurrent/atomic/AtomicLong.get:()J (0, 1)
	41 invokevirtual (0, 1)
	42 java/util/concurrent/atomic/AtomicLong.set:(J)V (0, 1)
	44 aload_1 (0, 1)
	45 areturn (0, 1)

Method: getIdentifier
	0 aload_0 (0, 1)
	1 getfield (0, 1)
	2 org/apache/commons/math3/ml/neuralnet/Neuron.identifier:J (0, 1)
	4 lreturn (0, 1)

Method: getSize
	0 aload_0 (0, 0)
	1 getfield (0, 0)
	2 org/apache/commons/math3/ml/neuralnet/Neuron.size:I (0, 0)
	4 ireturn (0, 0)

Method: getFeatures
	0 aload_0 (0, 0)
	1 getfield (0, 0)
	2 org/apache/commons/math3/ml/neuralnet/Neuron.features:Ljava/util/concurrent/atomic/AtomicReference; (0, 0)
	4 invokevirtual (0, 0)
	5 java/util/concurrent/atomic/AtomicReference.get:()Ljava/lang/Object; (0, 0)
	7 checkcast (0, 0)
	8 [D (0, 0)
	10 invokevirtual (0, 0)
	11 [D.clone:()Ljava/lang/Object; (0, 0)
	13 checkcast (0, 0)
	14 [D (0, 0)
	16 areturn (0, 0)

Method: compareAndSetFeatures
	0 aload_2 (1, 1)
	1 arraylength (1, 1)
	2 aload_0 (1, 1)
	3 getfield (1, 1)
	4 org/apache/commons/math3/ml/neuralnet/Neuron.size:I (1, 1)
	6 if_icmpeq (1, 1)
	7 17 (1, 1)
	9 new (1, 1)
	10 org/apache/commons/math3/exception/DimensionMismatchException (1, 1)
	12 dup (1, 1)
	13 aload_2 (1, 1)
	14 arraylength (1, 1)
	15 aload_0 (1, 1)
	16 getfield (1, 1)
	17 org/apache/commons/math3/ml/neuralnet/Neuron.size:I (1, 1)
	19 invokespecial (1, 1)
	20 org/apache/commons/math3/exception/DimensionMismatchException.<init>:(II)V (1, 1)
	22 athrow (1, 1)
	23 aload_0 (0, 0)
	24 getfield (0, 0)
	25 org/apache/commons/math3/ml/neuralnet/Neuron.features:Ljava/util/concurrent/atomic/AtomicReference; (0, 0)
	27 invokevirtual (0, 0)
	28 java/util/concurrent/atomic/AtomicReference.get:()Ljava/lang/Object; (0, 0)
	30 checkcast (0, 0)
	31 [D (0, 0)
	33 astore_3 (0, 0)
	34 aload_0 (1, 1)
	35 aload_3 (1, 1)
	36 aload_1 (1, 1)
	37 invokespecial (1, 1)
	38 org/apache/commons/math3/ml/neuralnet/Neuron.containSameValues:([D[D)Z (1, 1)
	40 ifne (1, 1)
	41 5 (1, 1)
	43 iconst_0 (1, 1)
	44 ireturn (1, 1)
	45 aload_0 (0, 0)
	46 getfield (0, 0)
	47 org/apache/commons/math3/ml/neuralnet/Neuron.numberOfAttemptedUpdates:Ljava/util/concurrent/atomic/AtomicLong; (0, 0)
	49 invokevirtual (0, 0)
	50 java/util/concurrent/atomic/AtomicLong.incrementAndGet:()J (0, 0)
	52 pop2 (0, 0)
	53 aload_0 (1, 1)
	54 getfield (1, 1)
	55 org/apache/commons/math3/ml/neuralnet/Neuron.features:Ljava/util/concurrent/atomic/AtomicReference; (1, 1)
	57 aload_3 (1, 1)
	58 aload_2 (1, 1)
	59 invokevirtual (1, 1)
	60 [D.clone:()Ljava/lang/Object; (1, 1)
	62 invokevirtual (1, 1)
	63 java/util/concurrent/atomic/AtomicReference.compareAndSet:(Ljava/lang/Object;Ljava/lang/Object;)Z (1, 1)
	65 ifeq (1, 1)
	66 13 (1, 1)
	68 aload_0 (1, 1)
	69 getfield (1, 1)
	70 org/apache/commons/math3/ml/neuralnet/Neuron.numberOfSuccessfulUpdates:Ljava/util/concurrent/atomic/AtomicLong; (1, 1)
	72 invokevirtual (1, 1)
	73 java/util/concurrent/atomic/AtomicLong.incrementAndGet:()J (1, 1)
	75 pop2 (1, 1)
	76 iconst_1 (1, 1)
	77 ireturn (1, 1)
	78 iconst_0 (1, 2)
	79 ireturn (1, 2)

Method: getNumberOfAttemptedUpdates
	0 aload_0 (0, 0)
	1 getfield (0, 0)
	2 org/apache/commons/math3/ml/neuralnet/Neuron.numberOfAttemptedUpdates:Ljava/util/concurrent/atomic/AtomicLong; (0, 0)
	4 invokevirtual (0, 0)
	5 java/util/concurrent/atomic/AtomicLong.get:()J (0, 0)
	7 lreturn (0, 0)

Method: getNumberOfSuccessfulUpdates
	0 aload_0 (0, 0)
	1 getfield (0, 0)
	2 org/apache/commons/math3/ml/neuralnet/Neuron.numberOfSuccessfulUpdates:Ljava/util/concurrent/atomic/AtomicLong; (0, 0)
	4 invokevirtual (0, 0)
	5 java/util/concurrent/atomic/AtomicLong.get:()J (0, 0)
	7 lreturn (0, 0)

Method: containSameValues
	0 aload_2 (1, 1)
	1 arraylength (1, 1)
	2 aload_0 (1, 1)
	3 getfield (1, 1)
	4 org/apache/commons/math3/ml/neuralnet/Neuron.size:I (1, 1)
	6 if_icmpeq (1, 1)
	7 17 (1, 1)
	9 new (1, 1)
	10 org/apache/commons/math3/exception/DimensionMismatchException (1, 1)
	12 dup (1, 1)
	13 aload_2 (1, 1)
	14 arraylength (1, 1)
	15 aload_0 (1, 1)
	16 getfield (1, 1)
	17 org/apache/commons/math3/ml/neuralnet/Neuron.size:I (1, 1)
	19 invokespecial (1, 1)
	20 org/apache/commons/math3/exception/DimensionMismatchException.<init>:(II)V (1, 1)
	22 athrow (1, 1)
	23 iconst_0 (1, 4)
	24 istore_3 (1, 4)
	25 iload_3 (1, 4)
	26 aload_0 (1, 4)
	27 getfield (1, 4)
	28 org/apache/commons/math3/ml/neuralnet/Neuron.size:I (1, 4)
	30 if_icmpge (1, 4)
	31 23 (1, 4)
	33 aload_1 (2, 1)
	34 iload_3 (2, 1)
	35 daload (2, 1)
	36 aload_2 (2, 1)
	37 iload_3 (2, 1)
	38 daload (2, 1)
	39 invokestatic (2, 1)
	40 org/apache/commons/math3/util/Precision.equals:(DD)Z (2, 1)
	42 ifne (2, 1)
	43 5 (2, 1)
	45 iconst_0 (2, 1)
	46 ireturn (2, 1)
	47 iinc (2, 1)
	48 #3 (2, 1)
	49 -89 (2, 1)
	50 goto (2, 1)
	51 -25 (2, 1)
	53 iconst_1 (1, 4)
	54 ireturn (1, 4)

Method: readObject
	0 new (0, 0)
	1 java/lang/IllegalStateException (0, 0)
	3 dup (0, 0)
	4 invokespecial (0, 0)
	5 java/lang/IllegalStateException.<init>:()V (0, 0)
	7 athrow (0, 0)

Method: writeReplace
	0 new (0, 1)
	1 org/apache/commons/math3/ml/neuralnet/Neuron$SerializationProxy (0, 1)
	3 dup (0, 1)
	4 aload_0 (0, 1)
	5 getfield (0, 1)
	6 org/apache/commons/math3/ml/neuralnet/Neuron.identifier:J (0, 1)
	8 aload_0 (0, 1)
	9 getfield (0, 1)
	10 org/apache/commons/math3/ml/neuralnet/Neuron.features:Ljava/util/concurrent/atomic/AtomicReference; (0, 1)
	12 invokevirtual (0, 1)
	13 java/util/concurrent/atomic/AtomicReference.get:()Ljava/lang/Object; (0, 1)
	15 checkcast (0, 1)
	16 [D (0, 1)
	18 invokespecial (0, 1)
	19 org/apache/commons/math3/ml/neuralnet/Neuron$SerializationProxy.<init>:(J[D)V (0, 1)
	21 areturn (0, 1)

