Method: <init>
	0 aload_0 (0, 0)
	1 invokespecial (0, 0)
	2 java/lang/Object.<init>:()V (0, 0)
	4 aload_0 (1, 1)
	5 lload_1 (1, 1)
	6 putfield (1, 1)
	7 org/apache/commons/math3/ml/neuralnet/Neuron$SerializationProxy.identifier:J (1, 1)
	9 aload_0 (1, 1)
	10 aload_3 (1, 1)
	11 putfield (1, 1)
	12 org/apache/commons/math3/ml/neuralnet/Neuron$SerializationProxy.features:[D (1, 1)
	14 return (0, 0)

Method: readResolve
	0 new (1, 1)
	1 org/apache/commons/math3/ml/neuralnet/Neuron (1, 1)
	3 dup (1, 1)
	4 aload_0 (1, 1)
	5 getfield (1, 1)
	6 org/apache/commons/math3/ml/neuralnet/Neuron$SerializationProxy.identifier:J (1, 1)
	8 aload_0 (1, 1)
	9 getfield (1, 1)
	10 org/apache/commons/math3/ml/neuralnet/Neuron$SerializationProxy.features:[D (1, 1)
	12 invokespecial (1, 1)
	13 org/apache/commons/math3/ml/neuralnet/Neuron.<init>:(J[D)V (1, 1)
	15 areturn (0, 1)

