Method: interpolate
	0 aload_0 (0, 0)
	1 aload_1 (0, 0)
	2 aload_2 (0, 0)
	3 invokevirtual (0, 0)
	4 org/apache/commons/math3/analysis/interpolation/AkimaSplineInterpolator.interpolate:([D[D)Lorg/apache/commons/math3/analysis/polynomials/PolynomialSplineFunction; (0, 0)
	6 areturn (0, 0)

Method: differentiateThreePoint
	0 aload_2 (0, 0)
	1 iload (0, 0)
	2 #4 (0, 0)
	3 daload (0, 0)
	4 dstore (0, 0)
	5 #7 (0, 0)
	6 aload_2 (0, 0)
	7 iload (0, 0)
	8 #5 (0, 0)
	9 daload (0, 0)
	10 dstore (0, 0)
	11 #9 (0, 0)
	12 aload_2 (0, 0)
	13 iload (0, 0)
	14 #6 (0, 0)
	15 daload (0, 0)
	16 dstore (0, 0)
	17 #11 (0, 0)
	18 aload_1 (0, 1)
	19 iload_3 (0, 1)
	20 daload (0, 1)
	21 aload_1 (0, 1)
	22 iload (0, 1)
	23 #4 (0, 1)
	24 daload (0, 1)
	25 dsub (0, 1)
	26 dstore (0, 1)
	27 #13 (0, 1)
	28 aload_1 (0, 1)
	29 iload (0, 1)
	30 #5 (0, 1)
	31 daload (0, 1)
	32 aload_1 (0, 1)
	33 iload (0, 1)
	34 #4 (0, 1)
	35 daload (0, 1)
	36 dsub (0, 1)
	37 dstore (0, 1)
	38 #15 (0, 1)
	39 aload_1 (0, 1)
	40 iload (0, 1)
	41 #6 (0, 1)
	42 daload (0, 1)
	43 aload_1 (0, 1)
	44 iload (0, 1)
	45 #4 (0, 1)
	46 daload (0, 1)
	47 dsub (0, 1)
	48 dstore (0, 1)
	49 #17 (0, 1)
	50 dload (0, 1)
	51 #11 (0, 1)
	52 dload (0, 1)
	53 #7 (0, 1)
	54 dsub (0, 1)
	55 dload (0, 1)
	56 #17 (0, 1)
	57 dload (0, 1)
	58 #15 (0, 1)
	59 ddiv (0, 1)
	60 dload (0, 1)
	61 #9 (0, 1)
	62 dload (0, 1)
	63 #7 (0, 1)
	64 dsub (0, 1)
	65 dmul (0, 1)
	66 dsub (0, 1)
	67 dload (0, 1)
	68 #17 (0, 1)
	69 dload (0, 1)
	70 #17 (0, 1)
	71 dmul (0, 1)
	72 dload (0, 1)
	73 #15 (0, 1)
	74 dload (0, 1)
	75 #17 (0, 1)
	76 dmul (0, 1)
	77 dsub (0, 1)
	78 ddiv (0, 1)
	79 dstore (0, 1)
	80 #19 (0, 1)
	81 dload (0, 1)
	82 #9 (0, 1)
	83 dload (0, 1)
	84 #7 (0, 1)
	85 dsub (0, 1)
	86 dload (0, 1)
	87 #19 (0, 1)
	88 dload (0, 1)
	89 #15 (0, 1)
	90 dmul (0, 1)
	91 dload (0, 1)
	92 #15 (0, 1)
	93 dmul (0, 1)
	94 dsub (0, 1)
	95 dload (0, 1)
	96 #15 (0, 1)
	97 ddiv (0, 1)
	98 dstore (0, 1)
	99 #21 (0, 1)
	100 ldc2_w (0, 1)
	101 2.0 (0, 1)
	103 dload (0, 1)
	104 #19 (0, 1)
	105 dmul (0, 1)
	106 dload (0, 1)
	107 #13 (0, 1)
	108 dmul (0, 1)
	109 dload (0, 1)
	110 #21 (0, 1)
	111 dadd (0, 1)
	112 dreturn (0, 1)

Method: interpolateHermiteSorted
	0 aload_1 (1, 1)
	1 arraylength (1, 1)
	2 aload_2 (1, 1)
	3 arraylength (1, 1)
	4 if_icmpeq (1, 1)
	5 15 (1, 1)
	7 new (1, 1)
	8 org/apache/commons/math3/exception/DimensionMismatchException (1, 1)
	10 dup (1, 1)
	11 aload_1 (1, 1)
	12 arraylength (1, 1)
	13 aload_2 (1, 1)
	14 arraylength (1, 1)
	15 invokespecial (1, 1)
	16 org/apache/commons/math3/exception/DimensionMismatchException.<init>:(II)V (1, 1)
	18 athrow (1, 1)
	19 aload_1 (1, 1)
	20 arraylength (1, 1)
	21 aload_3 (1, 1)
	22 arraylength (1, 1)
	23 if_icmpeq (1, 1)
	24 15 (1, 1)
	26 new (1, 1)
	27 org/apache/commons/math3/exception/DimensionMismatchException (1, 1)
	29 dup (1, 1)
	30 aload_1 (1, 1)
	31 arraylength (1, 1)
	32 aload_3 (1, 1)
	33 arraylength (1, 1)
	34 invokespecial (1, 1)
	35 org/apache/commons/math3/exception/DimensionMismatchException.<init>:(II)V (1, 1)
	37 athrow (1, 1)
	38 iconst_2 (0, 0)
	39 istore (0, 0)
	40 #4 (0, 0)
	41 aload_1 (1, 1)
	42 arraylength (1, 1)
	43 iconst_2 (1, 1)
	44 if_icmpge (1, 1)
	45 24 (1, 1)
	47 new (1, 1)
	48 org/apache/commons/math3/exception/NumberIsTooSmallException (1, 1)
	50 dup (1, 1)
	51 getstatic (1, 1)
	52 org/apache/commons/math3/exception/util/LocalizedFormats.NUMBER_OF_POINTS:Lorg/apache/commons/math3/exception/util/LocalizedFormats; (1, 1)
	54 aload_1 (1, 1)
	55 arraylength (1, 1)
	56 invokestatic (1, 1)
	57 java/lang/Integer.valueOf:(I)Ljava/lang/Integer; (1, 1)
	59 iconst_2 (1, 1)
	60 invokestatic (1, 1)
	61 java/lang/Integer.valueOf:(I)Ljava/lang/Integer; (1, 1)
	63 iconst_1 (1, 1)
	64 invokespecial (1, 1)
	65 org/apache/commons/math3/exception/NumberIsTooSmallException.<init>:(Lorg/apache/commons/math3/exception/util/Localizable;Ljava/lang/Number;Ljava/lang/Number;Z)V (1, 1)
	67 athrow (1, 1)
	68 aload_1 (0, 0)
	69 arraylength (0, 0)
	70 iconst_1 (0, 0)
	71 isub (0, 0)
	72 istore (0, 0)
	73 #5 (0, 0)
	74 iload (0, 0)
	75 #5 (0, 0)
	76 anewarray (0, 0)
	77 org/apache/commons/math3/analysis/polynomials/PolynomialFunction (0, 0)
	79 astore (0, 0)
	80 #6 (0, 0)
	81 iconst_4 (0, 0)
	82 newarray (0, 0)
	83 7 (0, 0)
	84 astore (0, 0)
	85 #7 (0, 0)
	86 iconst_0 (1, 4)
	87 istore (1, 4)
	88 #8 (1, 4)
	89 iload (1, 4)
	90 #8 (1, 4)
	91 aload (1, 4)
	92 #6 (1, 4)
	93 arraylength (1, 4)
	94 if_icmpge (1, 4)
	95 139 (1, 4)
	97 aload_1 (1, 4)
	98 iload (1, 4)
	99 #8 (1, 4)
	100 iconst_1 (1, 4)
	101 iadd (1, 4)
	102 daload (1, 4)
	103 aload_1 (1, 4)
	104 iload (1, 4)
	105 #8 (1, 4)
	106 daload (1, 4)
	107 dsub (1, 4)
	108 dstore (1, 4)
	109 #9 (1, 4)
	110 dload (1, 4)
	111 #9 (1, 4)
	112 dload (1, 4)
	113 #9 (1, 4)
	114 dmul (1, 4)
	115 dstore (1, 4)
	116 #11 (1, 4)
	117 aload_2 (1, 4)
	118 iload (1, 4)
	119 #8 (1, 4)
	120 daload (1, 4)
	121 dstore (1, 4)
	122 #13 (1, 4)
	123 aload_2 (1, 4)
	124 iload (1, 4)
	125 #8 (1, 4)
	126 iconst_1 (1, 4)
	127 iadd (1, 4)
	128 daload (1, 4)
	129 dstore (1, 4)
	130 #15 (1, 4)
	131 aload_3 (1, 4)
	132 iload (1, 4)
	133 #8 (1, 4)
	134 daload (1, 4)
	135 dstore (1, 4)
	136 #17 (1, 4)
	137 aload_3 (1, 4)
	138 iload (1, 4)
	139 #8 (1, 4)
	140 iconst_1 (1, 4)
	141 iadd (1, 4)
	142 daload (1, 4)
	143 dstore (1, 4)
	144 #19 (1, 4)
	145 aload (1, 4)
	146 #7 (1, 4)
	147 iconst_0 (1, 4)
	148 dload (1, 4)
	149 #13 (1, 4)
	150 dastore (1, 4)
	151 aload (1, 4)
	152 #7 (1, 4)
	153 iconst_1 (1, 4)
	154 aload_3 (1, 4)
	155 iload (1, 4)
	156 #8 (1, 4)
	157 daload (1, 4)
	158 dastore (1, 4)
	159 aload (1, 4)
	160 #7 (1, 4)
	161 iconst_2 (1, 4)
	162 ldc2_w (1, 4)
	163 3.0 (1, 4)
	165 dload (1, 4)
	166 #15 (1, 4)
	167 dload (1, 4)
	168 #13 (1, 4)
	169 dsub (1, 4)
	170 dmul (1, 4)
	171 dload (1, 4)
	172 #9 (1, 4)
	173 ddiv (1, 4)
	174 ldc2_w (1, 4)
	175 2.0 (1, 4)
	177 dload (1, 4)
	178 #17 (1, 4)
	179 dmul (1, 4)
	180 dsub (1, 4)
	181 dload (1, 4)
	182 #19 (1, 4)
	183 dsub (1, 4)
	184 dload (1, 4)
	185 #9 (1, 4)
	186 ddiv (1, 4)
	187 dastore (1, 4)
	188 aload (1, 4)
	189 #7 (1, 4)
	190 iconst_3 (1, 4)
	191 ldc2_w (1, 4)
	192 2.0 (1, 4)
	194 dload (1, 4)
	195 #13 (1, 4)
	196 dload (1, 4)
	197 #15 (1, 4)
	198 dsub (1, 4)
	199 dmul (1, 4)
	200 dload (1, 4)
	201 #9 (1, 4)
	202 ddiv (1, 4)
	203 dload (1, 4)
	204 #17 (1, 4)
	205 dadd (1, 4)
	206 dload (1, 4)
	207 #19 (1, 4)
	208 dadd (1, 4)
	209 dload (1, 4)
	210 #11 (1, 4)
	211 ddiv (1, 4)
	212 dastore (1, 4)
	213 aload (1, 4)
	214 #6 (1, 4)
	215 iload (1, 4)
	216 #8 (1, 4)
	217 new (1, 4)
	218 org/apache/commons/math3/analysis/polynomials/PolynomialFunction (1, 4)
	220 dup (1, 4)
	221 aload (1, 4)
	222 #7 (1, 4)
	223 invokespecial (1, 4)
	224 org/apache/commons/math3/analysis/polynomials/PolynomialFunction.<init>:([D)V (1, 4)
	226 aastore (1, 4)
	227 iinc (1, 4)
	228 #8 (1, 4)
	229 -89 (1, 4)
	230 goto (1, 4)
	231 -141 (1, 4)
	233 new (0, 0)
	234 org/apache/commons/math3/analysis/polynomials/PolynomialSplineFunction (0, 0)
	236 dup (0, 0)
	237 aload_1 (0, 0)
	238 aload (0, 0)
	239 #6 (0, 0)
	240 invokespecial (0, 0)
	241 org/apache/commons/math3/analysis/polynomials/PolynomialSplineFunction.<init>:([D[Lorg/apache/commons/math3/analysis/polynomials/PolynomialFunction;)V (0, 0)
	243 areturn (0, 0)

