Method: interpolate
	0 aload_0 (0, 1)
	1 aload_1 (0, 1)
	2 aload_2 (0, 1)
	3 invokevirtual (0, 1)
	4 org/apache/commons/math3/analysis/interpolation/DividedDifferenceInterpolator.interpolate:([D[D)Lorg/apache/commons/math3/analysis/polynomials/PolynomialFunctionNewtonForm; (0, 1)
	6 areturn (0, 1)

Method: computeDividedDifference
	0 aload_0 (0, 1)
	1 aload_1 (0, 1)
	2 iconst_1 (0, 1)
	3 invokestatic (0, 1)
	4 org/apache/commons/math3/analysis/polynomials/PolynomialFunctionLagrangeForm.verifyInterpolationArray:([D[DZ)Z (0, 1)
	6 pop (0, 1)
	7 aload_1 (0, 1)
	8 invokevirtual (0, 1)
	9 [D.clone:()Ljava/lang/Object; (0, 1)
	11 checkcast (0, 1)
	12 [D (0, 1)
	14 astore_2 (0, 1)
	15 aload_0 (0, 1)
	16 arraylength (0, 1)
	17 istore_3 (0, 1)
	18 iload_3 (0, 1)
	19 newarray (0, 1)
	20 7 (0, 1)
	21 astore (0, 1)
	22 #4 (0, 1)
	23 aload (0, 1)
	24 #4 (0, 1)
	25 iconst_0 (0, 1)
	26 aload_2 (0, 1)
	27 iconst_0 (0, 1)
	28 daload (0, 1)
	29 dastore (0, 1)
	30 iconst_1 (1, 4)
	31 istore (1, 4)
	32 #5 (1, 4)
	33 iload (1, 4)
	34 #5 (1, 4)
	35 iload_3 (1, 4)
	36 if_icmpge (1, 4)
	37 67 (1, 4)
	39 iconst_0 (2, 4)
	40 istore (2, 4)
	41 #6 (2, 4)
	42 iload (2, 4)
	43 #6 (2, 4)
	44 iload_3 (2, 4)
	45 iload (2, 4)
	46 #5 (2, 4)
	47 isub (2, 4)
	48 if_icmpge (2, 4)
	49 41 (2, 4)
	51 aload_0 (2, 4)
	52 iload (2, 4)
	53 #6 (2, 4)
	54 iload (2, 4)
	55 #5 (2, 4)
	56 iadd (2, 4)
	57 daload (2, 4)
	58 aload_0 (2, 4)
	59 iload (2, 4)
	60 #6 (2, 4)
	61 daload (2, 4)
	62 dsub (2, 4)
	63 dstore (2, 4)
	64 #7 (2, 4)
	65 aload_2 (2, 1)
	66 iload (2, 1)
	67 #6 (2, 1)
	68 aload_2 (2, 1)
	69 iload (2, 1)
	70 #6 (2, 1)
	71 iconst_1 (2, 1)
	72 iadd (2, 1)
	73 daload (2, 1)
	74 aload_2 (2, 1)
	75 iload (2, 1)
	76 #6 (2, 1)
	77 daload (2, 1)
	78 dsub (2, 1)
	79 dload (2, 1)
	80 #7 (2, 1)
	81 ddiv (2, 1)
	82 dastore (2, 1)
	83 iinc (2, 1)
	84 #6 (2, 1)
	85 -89 (2, 1)
	86 goto (2, 1)
	87 -44 (2, 1)
	89 aload (1, 1)
	90 #4 (1, 1)
	91 iload (1, 1)
	92 #5 (1, 1)
	93 aload_2 (1, 1)
	94 iconst_0 (1, 1)
	95 daload (1, 1)
	96 dastore (1, 1)
	97 iinc (1, 1)
	98 #5 (1, 1)
	99 -89 (1, 1)
	100 goto (1, 1)
	101 -67 (1, 1)
	103 aload (0, 1)
	104 #4 (0, 1)
	105 areturn (0, 1)

