Method: <init>
	0 aload_0 (0, 0)
	1 invokespecial (0, 0)
	2 java/lang/Object.<init>:()V (0, 0)
	4 aload_0 (0, 0)
	5 new (0, 0)
	6 java/util/ArrayList (0, 0)
	8 dup (0, 0)
	9 invokespecial (0, 0)
	10 java/util/ArrayList.<init>:()V (0, 0)
	12 putfield (0, 0)
	13 org/apache/commons/math3/analysis/interpolation/FieldHermiteInterpolator.abscissae:Ljava/util/List; (0, 0)
	15 aload_0 (0, 0)
	16 new (0, 0)
	17 java/util/ArrayList (0, 0)
	19 dup (0, 0)
	20 invokespecial (0, 0)
	21 java/util/ArrayList.<init>:()V (0, 0)
	23 putfield (0, 0)
	24 org/apache/commons/math3/analysis/interpolation/FieldHermiteInterpolator.topDiagonal:Ljava/util/List; (0, 0)
	26 aload_0 (0, 0)
	27 new (0, 0)
	28 java/util/ArrayList (0, 0)
	30 dup (0, 0)
	31 invokespecial (0, 0)
	32 java/util/ArrayList.<init>:()V (0, 0)
	34 putfield (0, 0)
	35 org/apache/commons/math3/analysis/interpolation/FieldHermiteInterpolator.bottomDiagonal:Ljava/util/List; (0, 0)
	37 return (0, 0)

Method: addSamplePoint
	0 aload_1 (0, 0)
	1 invokestatic (0, 0)
	2 org/apache/commons/math3/util/MathUtils.checkNotNull:(Ljava/lang/Object;)V (0, 0)
	4 aload_1 (0, 0)
	5 invokeinterface (0, 0)
	6 org/apache/commons/math3/FieldElement.org/apache/commons/math3/Field (0, 0)
	8 0 (0, 0)
	10 invokeinterface (0, 0)
	11 org/apache/commons/math3/Field.org/apache/commons/math3/FieldElement (0, 0)
	13 0 (0, 0)
	15 checkcast (0, 0)
	16 org/apache/commons/math3/FieldElement (0, 0)
	18 astore_3 (0, 0)
	19 iconst_0 (1, 4)
	20 istore (1, 4)
	21 #4 (1, 4)
	22 iload (1, 4)
	23 #4 (1, 4)
	24 aload_2 (1, 4)
	25 arraylength (1, 4)
	26 if_icmpge (1, 4)
	27 310 (1, 4)
	29 aload_2 (1, 4)
	30 iload (1, 4)
	31 #4 (1, 4)
	32 aaload (1, 4)
	33 invokevirtual (1, 4)
	34 [Lorg/apache/commons/math3/FieldElement;.clone:()Ljava/lang/Object; (1, 4)
	36 checkcast (1, 4)
	37 [Lorg/apache/commons/math3/FieldElement; (1, 4)
	39 astore (1, 4)
	40 #5 (1, 4)
	41 iload (2, 1)
	42 #4 (2, 1)
	43 iconst_1 (2, 1)
	44 if_icmple (2, 1)
	45 63 (2, 1)
	47 aload_3 (2, 1)
	48 iload (2, 1)
	49 #4 (2, 1)
	50 invokeinterface (2, 1)
	51 org/apache/commons/math3/FieldElement.reciprocal:()Ljava/lang/Object; (2, 1)
	53 0 (2, 1)
	55 checkcast (2, 1)
	56 org/apache/commons/math3/FieldElement (2, 1)
	58 astore_3 (2, 1)
	59 aload_3 (2, 1)
	60 invokeinterface (2, 1)
	61 org/apache/commons/math3/FieldElement.multiply:(Ljava/lang/Object;)Ljava/lang/Object; (2, 1)
	63 0 (2, 1)
	65 checkcast (2, 1)
	66 org/apache/commons/math3/FieldElement (2, 1)
	68 astore (2, 1)
	69 #6 (2, 1)
	70 iconst_0 (3, 4)
	71 istore (3, 4)
	72 #7 (3, 4)
	73 iload (3, 4)
	74 #7 (3, 4)
	75 aload (3, 4)
	76 #5 (3, 4)
	77 arraylength (3, 4)
	78 if_icmpge (3, 4)
	79 29 (3, 4)
	81 aload (3, 4)
	82 #5 (3, 4)
	83 iload (3, 4)
	84 #7 (3, 4)
	85 aload (3, 4)
	86 #5 (3, 4)
	87 iload (3, 4)
	88 #7 (3, 4)
	89 aaload (3, 4)
	90 aload (3, 4)
	91 #6 (3, 4)
	92 invokeinterface (3, 4)
	93 org/apache/commons/math3/FieldElement.java/util/List (3, 4)
	95 0 (3, 4)
	97 checkcast (3, 4)
	98 org/apache/commons/math3/FieldElement (3, 4)
	100 aastore (3, 4)
	101 iinc (3, 4)
	102 #7 (3, 4)
	103 -89 (3, 4)
	104 goto (3, 4)
	105 -31 (3, 4)
	107 aload_0 (1, 1)
	108 getfield (1, 1)
	109 org/apache/commons/math3/analysis/interpolation/FieldHermiteInterpolator.abscissae:Ljava/util/List; (1, 1)
	111 invokeinterface (1, 1)
	112 java/util/List.add:(ILjava/lang/Object;)V (1, 1)
	114 0 (1, 1)
	116 istore (1, 1)
	117 #6 (1, 1)
	118 aload_0 (1, 1)
	119 getfield (1, 1)
	120 org/apache/commons/math3/analysis/interpolation/FieldHermiteInterpolator.bottomDiagonal:Ljava/util/List; (1, 1)
	122 iload (1, 1)
	123 #6 (1, 1)
	124 iload (1, 1)
	125 #4 (1, 1)
	126 isub (1, 1)
	127 aload (1, 1)
	128 #5 (1, 1)
	129 invokeinterface (1, 1)
	130 java/util/List.get:(I)Ljava/lang/Object; (1, 1)
	132 0 (1, 1)
	134 aload (1, 1)
	135 #5 (1, 1)
	136 astore (1, 1)
	137 #7 (1, 1)
	138 iload (2, 4)
	139 #4 (2, 4)
	140 istore (2, 4)
	141 #8 (2, 4)
	142 iload (2, 4)
	143 #8 (2, 4)
	144 iload (2, 4)
	145 #6 (2, 4)
	146 if_icmpge (2, 4)
	147 158 (2, 4)
	149 aload_0 (2, 4)
	150 getfield (2, 4)
	151 org/apache/commons/math3/analysis/interpolation/FieldHermiteInterpolator.bottomDiagonal:Ljava/util/List; (2, 4)
	153 iload (2, 4)
	154 #6 (2, 4)
	155 iload (2, 4)
	156 #8 (2, 4)
	157 iconst_1 (2, 4)
	158 iadd (2, 4)
	159 isub (2, 4)
	160 invokeinterface (2, 4)
	161 java/util/List.equals:(Ljava/lang/Object;)Z (2, 4)
	163 0 (2, 4)
	165 checkcast (2, 4)
	166 [Lorg/apache/commons/math3/FieldElement; (2, 4)
	168 astore (2, 4)
	169 #9 (2, 4)
	170 aload_1 (3, 1)
	171 aload_0 (3, 1)
	172 getfield (3, 1)
	173 org/apache/commons/math3/analysis/interpolation/FieldHermiteInterpolator.abscissae:Ljava/util/List; (3, 1)
	175 iload (3, 1)
	176 #6 (3, 1)
	177 iload (3, 1)
	178 #8 (3, 1)
	179 iconst_1 (3, 1)
	180 iadd (3, 1)
	181 isub (3, 1)
	182 invokeinterface (3, 1)
	183 java/util/List.equals:(Ljava/lang/Object;)Z (3, 1)
	185 0 (3, 1)
	187 invokevirtual (3, 1)
	188 java/lang/Object.equals:(Ljava/lang/Object;)Z (3, 1)
	190 ifeq (3, 1)
	191 22 (3, 1)
	193 new (3, 1)
	194 org/apache/commons/math3/exception/ZeroException (3, 1)
	196 dup (3, 1)
	197 getstatic (3, 1)
	198 org/apache/commons/math3/exception/util/LocalizedFormats.DUPLICATED_ABSCISSA_DIVISION_BY_ZERO:Lorg/apache/commons/math3/exception/util/LocalizedFormats; (3, 1)
	200 iconst_1 (3, 1)
	201 anewarray (3, 1)
	202 java/lang/Object (3, 1)
	204 dup (3, 1)
	205 iconst_0 (3, 1)
	206 aload_1 (3, 1)
	207 aastore (3, 1)
	208 invokespecial (3, 1)
	209 org/apache/commons/math3/exception/ZeroException.<init>:(Lorg/apache/commons/math3/exception/util/Localizable;[Ljava/lang/Object;)V (3, 1)
	211 athrow (3, 1)
	212 aload_1 (2, 4)
	213 aload_0 (2, 4)
	214 getfield (2, 4)
	215 org/apache/commons/math3/analysis/interpolation/FieldHermiteInterpolator.abscissae:Ljava/util/List; (2, 4)
	217 iload (2, 4)
	218 #6 (2, 4)
	219 iload (2, 4)
	220 #8 (2, 4)
	221 iconst_1 (2, 4)
	222 iadd (2, 4)
	223 isub (2, 4)
	224 invokeinterface (2, 4)
	225 java/util/List.equals:(Ljava/lang/Object;)Z (2, 4)
	227 0 (2, 4)
	229 invokeinterface (2, 4)
	230 org/apache/commons/math3/FieldElement.[Lorg/apache/commons/math3/FieldElement; (2, 4)
	232 0 (2, 4)
	234 checkcast (2, 4)
	235 org/apache/commons/math3/FieldElement (2, 4)
	237 invokeinterface (2, 4)
	238 org/apache/commons/math3/FieldElement.multiply:(Ljava/lang/Object;)Ljava/lang/Object; (2, 4)
	240 0 (2, 4)
	242 checkcast (2, 4)
	243 org/apache/commons/math3/FieldElement (2, 4)
	245 astore (2, 4)
	246 #10 (2, 4)
	247 iconst_0 (3, 4)
	248 istore (3, 4)
	249 #11 (3, 4)
	250 iload (3, 4)
	251 #11 (3, 4)
	252 aload (3, 4)
	253 #5 (3, 4)
	254 arraylength (3, 4)
	255 if_icmpge (3, 4)
	256 39 (3, 4)
	258 aload (3, 4)
	259 #9 (3, 4)
	260 iload (3, 4)
	261 #11 (3, 4)
	262 aload (3, 4)
	263 #10 (3, 4)
	264 aload (3, 4)
	265 #7 (3, 4)
	266 iload (3, 4)
	267 #11 (3, 4)
	268 aaload (3, 4)
	269 aload (3, 4)
	270 #9 (3, 4)
	271 iload (3, 4)
	272 #11 (3, 4)
	273 aaload (3, 4)
	274 invokeinterface (3, 4)
	275 org/apache/commons/math3/FieldElement.[Lorg/apache/commons/math3/FieldElement; (3, 4)
	277 0 (3, 4)
	279 invokeinterface (3, 4)
	280 org/apache/commons/math3/FieldElement.java/util/List (3, 4)
	282 0 (3, 4)
	284 checkcast (3, 4)
	285 org/apache/commons/math3/FieldElement (3, 4)
	287 aastore (3, 4)
	288 iinc (3, 4)
	289 #11 (3, 4)
	290 -89 (3, 4)
	291 goto (3, 4)
	292 -41 (3, 4)
	294 aload (2, 4)
	295 #9 (2, 4)
	296 astore (2, 4)
	297 #7 (2, 4)
	298 iinc (2, 4)
	299 #8 (2, 4)
	300 -89 (2, 4)
	301 goto (2, 4)
	302 -159 (2, 4)
	304 aload_0 (1, 1)
	305 getfield (1, 1)
	306 org/apache/commons/math3/analysis/interpolation/FieldHermiteInterpolator.topDiagonal:Ljava/util/List; (1, 1)
	308 aload (1, 1)
	309 #7 (1, 1)
	310 invokevirtual (1, 1)
	311 [Lorg/apache/commons/math3/FieldElement;.clone:()Ljava/lang/Object; (1, 1)
	313 invokeinterface (1, 1)
	314 java/util/List.isEmpty:()Z (1, 1)
	316 0 (1, 1)
	318 pop (1, 1)
	319 aload_0 (1, 1)
	320 getfield (1, 1)
	321 org/apache/commons/math3/analysis/interpolation/FieldHermiteInterpolator.abscissae:Ljava/util/List; (1, 1)
	323 aload_1 (1, 1)
	324 invokeinterface (1, 1)
	325 java/util/List.isEmpty:()Z (1, 1)
	327 0 (1, 1)
	329 pop (1, 1)
	330 iinc (1, 1)
	331 #4 (1, 1)
	332 -89 (1, 1)
	333 goto (1, 1)
	334 -311 (1, 1)
	336 return (0, 0)

Method: value
	0 aload_1 (0, 0)
	1 invokestatic (0, 0)
	2 org/apache/commons/math3/util/MathUtils.checkNotNull:(Ljava/lang/Object;)V (0, 0)
	4 aload_0 (1, 1)
	5 getfield (1, 1)
	6 org/apache/commons/math3/analysis/interpolation/FieldHermiteInterpolator.abscissae:Ljava/util/List; (1, 1)
	8 invokeinterface (1, 1)
	9 java/util/List.org/apache/commons/math3/exception/NoDataException (1, 1)
	11 0 (1, 1)
	13 ifeq (1, 1)
	14 14 (1, 1)
	16 new (1, 1)
	17 org/apache/commons/math3/exception/NoDataException (1, 1)
	19 dup (1, 1)
	20 getstatic (1, 1)
	21 org/apache/commons/math3/exception/util/LocalizedFormats.EMPTY_INTERPOLATION_SAMPLE:Lorg/apache/commons/math3/exception/util/LocalizedFormats; (1, 1)
	23 invokespecial (1, 1)
	24 org/apache/commons/math3/exception/NoDataException.<init>:(Lorg/apache/commons/math3/exception/util/Localizable;)V (1, 1)
	26 athrow (1, 1)
	27 aload_1 (0, 0)
	28 invokeinterface (0, 0)
	29 org/apache/commons/math3/FieldElement.org/apache/commons/math3/Field (0, 0)
	31 0 (0, 0)
	33 aload_0 (0, 0)
	34 getfield (0, 0)
	35 org/apache/commons/math3/analysis/interpolation/FieldHermiteInterpolator.topDiagonal:Ljava/util/List; (0, 0)
	37 iconst_0 (0, 0)
	38 invokeinterface (0, 0)
	39 java/util/List.equals:(Ljava/lang/Object;)Z (0, 0)
	41 0 (0, 0)
	43 checkcast (0, 0)
	44 [Lorg/apache/commons/math3/FieldElement; (0, 0)
	46 arraylength (0, 0)
	47 invokestatic (0, 0)
	48 org/apache/commons/math3/util/MathArrays.buildArray:(Lorg/apache/commons/math3/Field;I)[Ljava/lang/Object; (0, 0)
	50 checkcast (0, 0)
	51 [Lorg/apache/commons/math3/FieldElement; (0, 0)
	53 astore_2 (0, 0)
	54 aload_1 (0, 0)
	55 invokeinterface (0, 0)
	56 org/apache/commons/math3/FieldElement.org/apache/commons/math3/Field (0, 0)
	58 0 (0, 0)
	60 invokeinterface (0, 0)
	61 org/apache/commons/math3/Field.org/apache/commons/math3/FieldElement (0, 0)
	63 0 (0, 0)
	65 checkcast (0, 0)
	66 org/apache/commons/math3/FieldElement (0, 0)
	68 astore_3 (0, 0)
	69 iconst_0 (1, 4)
	70 istore (1, 4)
	71 #4 (1, 4)
	72 iload (1, 4)
	73 #4 (1, 4)
	74 aload_0 (1, 4)
	75 getfield (1, 4)
	76 org/apache/commons/math3/analysis/interpolation/FieldHermiteInterpolator.topDiagonal:Ljava/util/List; (1, 4)
	78 invokeinterface (1, 4)
	79 java/util/List.add:(ILjava/lang/Object;)V (1, 4)
	81 0 (1, 4)
	83 if_icmpge (1, 4)
	84 102 (1, 4)
	86 aload_0 (1, 1)
	87 getfield (1, 1)
	88 org/apache/commons/math3/analysis/interpolation/FieldHermiteInterpolator.topDiagonal:Ljava/util/List; (1, 1)
	90 iload (1, 1)
	91 #4 (1, 1)
	92 invokeinterface (1, 1)
	93 java/util/List.equals:(Ljava/lang/Object;)Z (1, 1)
	95 0 (1, 1)
	97 checkcast (1, 1)
	98 [Lorg/apache/commons/math3/FieldElement; (1, 1)
	100 astore (1, 1)
	101 #5 (1, 1)
	102 iconst_0 (2, 4)
	103 istore (2, 4)
	104 #6 (2, 4)
	105 iload (2, 4)
	106 #6 (2, 4)
	107 aload_2 (2, 4)
	108 arraylength (2, 4)
	109 if_icmpge (2, 4)
	110 36 (2, 4)
	112 aload_2 (2, 1)
	113 iload (2, 1)
	114 #6 (2, 1)
	115 aload_2 (2, 1)
	116 iload (2, 1)
	117 #6 (2, 1)
	118 aaload (2, 1)
	119 aload (2, 1)
	120 #5 (2, 1)
	121 iload (2, 1)
	122 #6 (2, 1)
	123 aaload (2, 1)
	124 aload_3 (2, 1)
	125 invokeinterface (2, 1)
	126 org/apache/commons/math3/FieldElement.java/util/List (2, 1)
	128 0 (2, 1)
	130 invokeinterface (2, 1)
	131 org/apache/commons/math3/FieldElement.getZero:()Ljava/lang/Object; (2, 1)
	133 0 (2, 1)
	135 checkcast (2, 1)
	136 org/apache/commons/math3/FieldElement (2, 1)
	138 aastore (2, 1)
	139 iinc (2, 1)
	140 #6 (2, 1)
	141 -89 (2, 1)
	142 goto (2, 1)
	143 -37 (2, 1)
	145 aload_1 (1, 1)
	146 aload_0 (1, 1)
	147 getfield (1, 1)
	148 org/apache/commons/math3/analysis/interpolation/FieldHermiteInterpolator.abscissae:Ljava/util/List; (1, 1)
	150 iload (1, 1)
	151 #4 (1, 1)
	152 invokeinterface (1, 1)
	153 java/util/List.equals:(Ljava/lang/Object;)Z (1, 1)
	155 0 (1, 1)
	157 invokeinterface (1, 1)
	158 org/apache/commons/math3/FieldElement.[Lorg/apache/commons/math3/FieldElement; (1, 1)
	160 0 (1, 1)
	162 checkcast (1, 1)
	163 org/apache/commons/math3/FieldElement (1, 1)
	165 astore (1, 1)
	166 #6 (1, 1)
	167 aload_3 (1, 1)
	168 aload (1, 1)
	169 #6 (1, 1)
	170 invokeinterface (1, 1)
	171 org/apache/commons/math3/FieldElement.java/util/List (1, 1)
	173 0 (1, 1)
	175 checkcast (1, 1)
	176 org/apache/commons/math3/FieldElement (1, 1)
	178 astore_3 (1, 1)
	179 iinc (1, 1)
	180 #4 (1, 1)
	181 -89 (1, 1)
	182 goto (1, 1)
	183 -110 (1, 1)
	185 aload_2 (0, 0)
	186 areturn (0, 0)

Method: derivatives
	0 aload_1 (0, 0)
	1 invokestatic (0, 0)
	2 org/apache/commons/math3/util/MathUtils.checkNotNull:(Ljava/lang/Object;)V (0, 0)
	4 aload_0 (1, 1)
	5 getfield (1, 1)
	6 org/apache/commons/math3/analysis/interpolation/FieldHermiteInterpolator.abscissae:Ljava/util/List; (1, 1)
	8 invokeinterface (1, 1)
	9 java/util/List.org/apache/commons/math3/exception/NoDataException (1, 1)
	11 0 (1, 1)
	13 ifeq (1, 1)
	14 14 (1, 1)
	16 new (1, 1)
	17 org/apache/commons/math3/exception/NoDataException (1, 1)
	19 dup (1, 1)
	20 getstatic (1, 1)
	21 org/apache/commons/math3/exception/util/LocalizedFormats.EMPTY_INTERPOLATION_SAMPLE:Lorg/apache/commons/math3/exception/util/LocalizedFormats; (1, 1)
	23 invokespecial (1, 1)
	24 org/apache/commons/math3/exception/NoDataException.<init>:(Lorg/apache/commons/math3/exception/util/Localizable;)V (1, 1)
	26 athrow (1, 1)
	27 aload_1 (0, 0)
	28 invokeinterface (0, 0)
	29 org/apache/commons/math3/FieldElement.org/apache/commons/math3/Field (0, 0)
	31 0 (0, 0)
	33 invokeinterface (0, 0)
	34 org/apache/commons/math3/Field.buildArray:(Lorg/apache/commons/math3/Field;II)[[Ljava/lang/Object; (0, 0)
	36 0 (0, 0)
	38 checkcast (0, 0)
	39 org/apache/commons/math3/FieldElement (0, 0)
	41 astore_3 (0, 0)
	42 aload_1 (0, 0)
	43 invokeinterface (0, 0)
	44 org/apache/commons/math3/FieldElement.org/apache/commons/math3/Field (0, 0)
	46 0 (0, 0)
	48 invokeinterface (0, 0)
	49 org/apache/commons/math3/Field.org/apache/commons/math3/FieldElement (0, 0)
	51 0 (0, 0)
	53 checkcast (0, 0)
	54 org/apache/commons/math3/FieldElement (0, 0)
	56 astore (0, 0)
	57 #4 (0, 0)
	58 aload_1 (0, 0)
	59 invokeinterface (0, 0)
	60 org/apache/commons/math3/FieldElement.org/apache/commons/math3/Field (0, 0)
	62 0 (0, 0)
	64 iload_2 (0, 0)
	65 iconst_1 (0, 0)
	66 iadd (0, 0)
	67 invokestatic (0, 0)
	68 org/apache/commons/math3/util/MathArrays.buildArray:(Lorg/apache/commons/math3/Field;I)[Ljava/lang/Object; (0, 0)
	70 checkcast (0, 0)
	71 [Lorg/apache/commons/math3/FieldElement; (0, 0)
	73 astore (0, 0)
	74 #5 (0, 0)
	75 aload (0, 0)
	76 #5 (0, 0)
	77 iconst_0 (0, 0)
	78 aload_3 (0, 0)
	79 aastore (0, 0)
	80 iconst_0 (1, 4)
	81 istore (1, 4)
	82 #6 (1, 4)
	83 iload (1, 4)
	84 #6 (1, 4)
	85 iload_2 (1, 4)
	86 if_icmpge (1, 4)
	87 31 (1, 4)
	89 aload (1, 4)
	90 #5 (1, 4)
	91 iload (1, 4)
	92 #6 (1, 4)
	93 iconst_1 (1, 4)
	94 iadd (1, 4)
	95 aload (1, 4)
	96 #5 (1, 4)
	97 iload (1, 4)
	98 #6 (1, 4)
	99 aaload (1, 4)
	100 aload (1, 4)
	101 #4 (1, 4)
	102 invokeinterface (1, 4)
	103 org/apache/commons/math3/FieldElement.getZero:()Ljava/lang/Object; (1, 4)
	105 0 (1, 4)
	107 checkcast (1, 4)
	108 org/apache/commons/math3/FieldElement (1, 4)
	110 aastore (1, 4)
	111 iinc (1, 4)
	112 #6 (1, 4)
	113 -89 (1, 4)
	114 goto (1, 4)
	115 -31 (1, 4)
	117 aload_1 (0, 0)
	118 invokeinterface (0, 0)
	119 org/apache/commons/math3/FieldElement.org/apache/commons/math3/Field (0, 0)
	121 0 (0, 0)
	123 iload_2 (0, 0)
	124 iconst_1 (0, 0)
	125 iadd (0, 0)
	126 aload_0 (0, 0)
	127 getfield (0, 0)
	128 org/apache/commons/math3/analysis/interpolation/FieldHermiteInterpolator.topDiagonal:Ljava/util/List; (0, 0)
	130 iconst_0 (0, 0)
	131 invokeinterface (0, 0)
	132 java/util/List.equals:(Ljava/lang/Object;)Z (0, 0)
	134 0 (0, 0)
	136 checkcast (0, 0)
	137 [Lorg/apache/commons/math3/FieldElement; (0, 0)
	139 arraylength (0, 0)
	140 invokestatic (0, 0)
	141 org/apache/commons/math3/util/MathArrays.buildArray:(Lorg/apache/commons/math3/Field;II)[[Ljava/lang/Object; (0, 0)
	143 checkcast (0, 0)
	144 [[Lorg/apache/commons/math3/FieldElement; (0, 0)
	146 astore (0, 0)
	147 #6 (0, 0)
	148 aload_1 (0, 0)
	149 invokeinterface (0, 0)
	150 org/apache/commons/math3/FieldElement.org/apache/commons/math3/Field (0, 0)
	152 0 (0, 0)
	154 iload_2 (0, 0)
	155 iconst_1 (0, 0)
	156 iadd (0, 0)
	157 invokestatic (0, 0)
	158 org/apache/commons/math3/util/MathArrays.buildArray:(Lorg/apache/commons/math3/Field;I)[Ljava/lang/Object; (0, 0)
	160 checkcast (0, 0)
	161 [Lorg/apache/commons/math3/FieldElement; (0, 0)
	163 astore (0, 0)
	164 #7 (0, 0)
	165 aload (0, 0)
	166 #7 (0, 0)
	167 iconst_0 (0, 0)
	168 aload_1 (0, 0)
	169 invokeinterface (0, 0)
	170 org/apache/commons/math3/FieldElement.org/apache/commons/math3/Field (0, 0)
	172 0 (0, 0)
	174 invokeinterface (0, 0)
	175 org/apache/commons/math3/Field.org/apache/commons/math3/FieldElement (0, 0)
	177 0 (0, 0)
	179 checkcast (0, 0)
	180 org/apache/commons/math3/FieldElement (0, 0)
	182 aastore (0, 0)
	183 iconst_0 (1, 4)
	184 istore (1, 4)
	185 #8 (1, 4)
	186 iload (1, 4)
	187 #8 (1, 4)
	188 aload_0 (1, 4)
	189 getfield (1, 4)
	190 org/apache/commons/math3/analysis/interpolation/FieldHermiteInterpolator.topDiagonal:Ljava/util/List; (1, 4)
	192 invokeinterface (1, 4)
	193 java/util/List.add:(ILjava/lang/Object;)V (1, 4)
	195 0 (1, 4)
	197 if_icmpge (1, 4)
	198 180 (1, 4)
	200 aload_0 (1, 1)
	201 getfield (1, 1)
	202 org/apache/commons/math3/analysis/interpolation/FieldHermiteInterpolator.topDiagonal:Ljava/util/List; (1, 1)
	204 iload (1, 1)
	205 #8 (1, 1)
	206 invokeinterface (1, 1)
	207 java/util/List.equals:(Ljava/lang/Object;)Z (1, 1)
	209 0 (1, 1)
	211 checkcast (1, 1)
	212 [Lorg/apache/commons/math3/FieldElement; (1, 1)
	214 astore (1, 1)
	215 #9 (1, 1)
	216 aload_1 (1, 1)
	217 aload_0 (1, 1)
	218 getfield (1, 1)
	219 org/apache/commons/math3/analysis/interpolation/FieldHermiteInterpolator.abscissae:Ljava/util/List; (1, 1)
	221 iload (1, 1)
	222 #8 (1, 1)
	223 invokeinterface (1, 1)
	224 java/util/List.equals:(Ljava/lang/Object;)Z (1, 1)
	226 0 (1, 1)
	228 invokeinterface (1, 1)
	229 org/apache/commons/math3/FieldElement.[Lorg/apache/commons/math3/FieldElement; (1, 1)
	231 0 (1, 1)
	233 checkcast (1, 1)
	234 org/apache/commons/math3/FieldElement (1, 1)
	236 astore (1, 1)
	237 #10 (1, 1)
	238 iload_2 (2, 4)
	239 istore (2, 4)
	240 #11 (2, 4)
	241 iload (2, 4)
	242 #11 (2, 4)
	243 iflt (2, 4)
	244 128 (2, 4)
	246 iconst_0 (3, 4)
	247 istore (3, 4)
	248 #12 (3, 4)
	249 iload (3, 4)
	250 #12 (3, 4)
	251 aload (3, 4)
	252 #6 (3, 4)
	253 iload (3, 4)
	254 #11 (3, 4)
	255 aaload (3, 4)
	256 arraylength (3, 4)
	257 if_icmpge (3, 4)
	258 48 (3, 4)
	260 aload (3, 4)
	261 #6 (3, 4)
	262 iload (3, 4)
	263 #11 (3, 4)
	264 aaload (3, 4)
	265 iload (3, 4)
	266 #12 (3, 4)
	267 aload (3, 4)
	268 #6 (3, 4)
	269 iload (3, 4)
	270 #11 (3, 4)
	271 aaload (3, 4)
	272 iload (3, 4)
	273 #12 (3, 4)
	274 aaload (3, 4)
	275 aload (3, 4)
	276 #9 (3, 4)
	277 iload (3, 4)
	278 #12 (3, 4)
	279 aaload (3, 4)
	280 aload (3, 4)
	281 #7 (3, 4)
	282 iload (3, 4)
	283 #11 (3, 4)
	284 aaload (3, 4)
	285 invokeinterface (3, 1)
	286 org/apache/commons/math3/FieldElement.java/util/List (3, 1)
	288 0 (3, 1)
	290 invokeinterface (3, 1)
	291 org/apache/commons/math3/FieldElement.getZero:()Ljava/lang/Object; (3, 1)
	293 0 (3, 1)
	295 checkcast (3, 1)
	296 org/apache/commons/math3/FieldElement (3, 1)
	298 aastore (3, 1)
	299 iinc (3, 1)
	300 #12 (3, 1)
	301 -89 (3, 1)
	302 goto (3, 1)
	303 -53 (3, 1)
	305 aload (2, 4)
	306 #7 (2, 4)
	307 iload (2, 4)
	308 #11 (2, 4)
	309 aload (2, 4)
	310 #7 (2, 4)
	311 iload (2, 4)
	312 #11 (2, 4)
	313 aaload (2, 4)
	314 aload (2, 4)
	315 #10 (2, 4)
	316 invokeinterface (2, 4)
	317 org/apache/commons/math3/FieldElement.java/util/List (2, 4)
	319 0 (2, 4)
	321 checkcast (2, 4)
	322 org/apache/commons/math3/FieldElement (2, 4)
	324 aastore (2, 4)
	325 iload (3, 1)
	326 #11 (3, 1)
	327 ifle (3, 1)
	328 38 (3, 1)
	330 aload (3, 1)
	331 #7 (3, 1)
	332 iload (3, 1)
	333 #11 (3, 1)
	334 aload (3, 1)
	335 #7 (3, 1)
	336 iload (3, 1)
	337 #11 (3, 1)
	338 aaload (3, 1)
	339 aload (3, 1)
	340 #5 (3, 1)
	341 iload (3, 1)
	342 #11 (3, 1)
	343 aaload (3, 1)
	344 aload (3, 1)
	345 #7 (3, 1)
	346 iload (3, 1)
	347 #11 (3, 1)
	348 iconst_1 (3, 1)
	349 isub (3, 1)
	350 aaload (3, 1)
	351 invokeinterface (3, 1)
	352 org/apache/commons/math3/FieldElement.java/util/List (3, 1)
	354 0 (3, 1)
	356 invokeinterface (3, 1)
	357 org/apache/commons/math3/FieldElement.getZero:()Ljava/lang/Object; (3, 1)
	359 0 (3, 1)
	361 checkcast (3, 1)
	362 org/apache/commons/math3/FieldElement (3, 1)
	364 aastore (3, 1)
	365 iinc (3, 1)
	366 #11 (3, 1)
	367 -89 (3, 1)
	368 goto (3, 1)
	369 -127 (3, 1)
	371 iinc (3, 1)
	372 #8 (3, 1)
	373 -89 (3, 1)
	374 goto (3, 1)
	375 -188 (3, 1)
	377 aload (2, 4)
	378 #6 (2, 4)
	379 areturn (2, 4)

