Method: <init>
	0 aload_0 (0, 0)
	1 invokespecial (0, 0)
	2 java/lang/Object.<init>:()V (0, 0)
	4 aload_0 (0, 0)
	5 new (0, 0)
	6 java/util/ArrayList (0, 0)
	8 dup (0, 0)
	9 invokespecial (0, 0)
	10 java/util/ArrayList.<init>:()V (0, 0)
	12 putfield (0, 0)
	13 org/apache/commons/math3/analysis/interpolation/HermiteInterpolator.abscissae:Ljava/util/List; (0, 0)
	15 aload_0 (0, 0)
	16 new (0, 0)
	17 java/util/ArrayList (0, 0)
	19 dup (0, 0)
	20 invokespecial (0, 0)
	21 java/util/ArrayList.<init>:()V (0, 0)
	23 putfield (0, 0)
	24 org/apache/commons/math3/analysis/interpolation/HermiteInterpolator.topDiagonal:Ljava/util/List; (0, 0)
	26 aload_0 (0, 0)
	27 new (0, 0)
	28 java/util/ArrayList (0, 0)
	30 dup (0, 0)
	31 invokespecial (0, 0)
	32 java/util/ArrayList.<init>:()V (0, 0)
	34 putfield (0, 0)
	35 org/apache/commons/math3/analysis/interpolation/HermiteInterpolator.bottomDiagonal:Ljava/util/List; (0, 0)
	37 return (0, 0)

Method: addSamplePoint
	0 iconst_0 (1, 4)
	1 istore (1, 4)
	2 #4 (1, 4)
	3 iload (1, 4)
	4 #4 (1, 4)
	5 aload_3 (1, 4)
	6 arraylength (1, 4)
	7 if_icmpge (1, 4)
	8 260 (1, 4)
	10 aload_3 (1, 4)
	11 iload (1, 4)
	12 #4 (1, 4)
	13 aaload (1, 4)
	14 invokevirtual (1, 4)
	15 [D.clone:()Ljava/lang/Object; (1, 4)
	17 checkcast (1, 4)
	18 [D (1, 4)
	20 astore (1, 4)
	21 #5 (1, 4)
	22 iload (2, 1)
	23 #4 (2, 1)
	24 iconst_1 (2, 1)
	25 if_icmple (2, 1)
	26 40 (2, 1)
	28 dconst_1 (2, 1)
	29 iload (2, 1)
	30 #4 (2, 1)
	31 invokestatic (2, 1)
	32 org/apache/commons/math3/util/CombinatoricsUtils.factorial:(I)J (2, 1)
	34 l2d (2, 1)
	35 ddiv (2, 1)
	36 dstore (2, 1)
	37 #6 (2, 1)
	38 iconst_0 (3, 4)
	39 istore (3, 4)
	40 #8 (3, 4)
	41 iload (3, 4)
	42 #8 (3, 4)
	43 aload (3, 4)
	44 #5 (3, 4)
	45 arraylength (3, 4)
	46 if_icmpge (3, 4)
	47 19 (3, 4)
	49 aload (3, 4)
	50 #5 (3, 4)
	51 iload (3, 4)
	52 #8 (3, 4)
	53 dup2 (3, 4)
	54 daload (3, 4)
	55 dload (3, 4)
	56 #6 (3, 4)
	57 dmul (3, 4)
	58 dastore (3, 4)
	59 iinc (3, 4)
	60 #8 (3, 4)
	61 -89 (3, 4)
	62 goto (3, 4)
	63 -21 (3, 4)
	65 aload_0 (1, 1)
	66 getfield (1, 1)
	67 org/apache/commons/math3/analysis/interpolation/HermiteInterpolator.abscissae:Ljava/util/List; (1, 1)
	69 invokeinterface (1, 1)
	70 java/util/List.add:(ILjava/lang/Object;)V (1, 1)
	72 0 (1, 1)
	74 istore (1, 1)
	75 #6 (1, 1)
	76 aload_0 (1, 1)
	77 getfield (1, 1)
	78 org/apache/commons/math3/analysis/interpolation/HermiteInterpolator.bottomDiagonal:Ljava/util/List; (1, 1)
	80 iload (1, 1)
	81 #6 (1, 1)
	82 iload (1, 1)
	83 #4 (1, 1)
	84 isub (1, 1)
	85 aload (1, 1)
	86 #5 (1, 1)
	87 invokeinterface (1, 1)
	88 java/util/List.get:(I)Ljava/lang/Object; (1, 1)
	90 0 (1, 1)
	92 aload (1, 1)
	93 #5 (1, 1)
	94 astore (1, 1)
	95 #7 (1, 1)
	96 iload (2, 4)
	97 #4 (2, 4)
	98 istore (2, 4)
	99 #8 (2, 4)
	100 iload (2, 4)
	101 #8 (2, 4)
	102 iload (2, 4)
	103 #6 (2, 4)
	104 if_icmpge (2, 4)
	105 128 (2, 4)
	107 aload_0 (2, 4)
	108 getfield (2, 4)
	109 org/apache/commons/math3/analysis/interpolation/HermiteInterpolator.bottomDiagonal:Ljava/util/List; (2, 4)
	111 iload (2, 4)
	112 #6 (2, 4)
	113 iload (2, 4)
	114 #8 (2, 4)
	115 iconst_1 (2, 4)
	116 iadd (2, 4)
	117 isub (2, 4)
	118 invokeinterface (2, 4)
	119 java/util/List.java/lang/Double (2, 4)
	121 0 (2, 4)
	123 checkcast (2, 4)
	124 [D (2, 4)
	126 astore (2, 4)
	127 #9 (2, 4)
	128 dconst_1 (2, 4)
	129 dload_1 (2, 4)
	130 aload_0 (2, 4)
	131 getfield (2, 4)
	132 org/apache/commons/math3/analysis/interpolation/HermiteInterpolator.abscissae:Ljava/util/List; (2, 4)
	134 iload (2, 4)
	135 #6 (2, 4)
	136 iload (2, 4)
	137 #8 (2, 4)
	138 iconst_1 (2, 4)
	139 iadd (2, 4)
	140 isub (2, 4)
	141 invokeinterface (2, 4)
	142 java/util/List.java/lang/Double (2, 4)
	144 0 (2, 4)
	146 checkcast (2, 4)
	147 java/lang/Double (2, 4)
	149 invokevirtual (2, 4)
	150 java/lang/Double.doubleValue:()D (2, 4)
	152 dsub (2, 4)
	153 ddiv (2, 4)
	154 dstore (2, 4)
	155 #10 (2, 4)
	156 dload (3, 1)
	157 #10 (3, 1)
	158 invokestatic (3, 1)
	159 java/lang/Double.isInfinite:(D)Z (3, 1)
	161 ifeq (3, 1)
	162 25 (3, 1)
	164 new (3, 1)
	165 org/apache/commons/math3/exception/ZeroException (3, 1)
	167 dup (3, 1)
	168 getstatic (3, 1)
	169 org/apache/commons/math3/exception/util/LocalizedFormats.DUPLICATED_ABSCISSA_DIVISION_BY_ZERO:Lorg/apache/commons/math3/exception/util/LocalizedFormats; (3, 1)
	171 iconst_1 (3, 1)
	172 anewarray (3, 1)
	173 java/lang/Object (3, 1)
	175 dup (3, 1)
	176 iconst_0 (3, 1)
	177 dload_1 (3, 1)
	178 invokestatic (3, 1)
	179 java/lang/Double.valueOf:(D)Ljava/lang/Double; (3, 1)
	181 aastore (3, 1)
	182 invokespecial (3, 1)
	183 org/apache/commons/math3/exception/ZeroException.<init>:(Lorg/apache/commons/math3/exception/util/Localizable;[Ljava/lang/Object;)V (3, 1)
	185 athrow (3, 1)
	186 iconst_0 (3, 4)
	187 istore (3, 4)
	188 #12 (3, 4)
	189 iload (3, 4)
	190 #12 (3, 4)
	191 aload (3, 4)
	192 #5 (3, 4)
	193 arraylength (3, 4)
	194 if_icmpge (3, 4)
	195 28 (3, 4)
	197 aload (3, 4)
	198 #9 (3, 4)
	199 iload (3, 4)
	200 #12 (3, 4)
	201 dload (3, 4)
	202 #10 (3, 4)
	203 aload (3, 4)
	204 #7 (3, 4)
	205 iload (3, 4)
	206 #12 (3, 4)
	207 daload (3, 4)
	208 aload (3, 4)
	209 #9 (3, 4)
	210 iload (3, 4)
	211 #12 (3, 4)
	212 daload (3, 4)
	213 dsub (3, 4)
	214 dmul (3, 4)
	215 dastore (3, 4)
	216 iinc (3, 4)
	217 #12 (3, 4)
	218 -89 (3, 4)
	219 goto (3, 4)
	220 -30 (3, 4)
	222 aload (2, 4)
	223 #9 (2, 4)
	224 astore (2, 4)
	225 #7 (2, 4)
	226 iinc (2, 4)
	227 #8 (2, 4)
	228 -89 (2, 4)
	229 goto (2, 4)
	230 -129 (2, 4)
	232 aload_0 (1, 1)
	233 getfield (1, 1)
	234 org/apache/commons/math3/analysis/interpolation/HermiteInterpolator.topDiagonal:Ljava/util/List; (1, 1)
	236 aload (1, 1)
	237 #7 (1, 1)
	238 invokevirtual (1, 1)
	239 [D.clone:()Ljava/lang/Object; (1, 1)
	241 invokeinterface (1, 1)
	242 java/util/List.checkInterpolation:()V (1, 1)
	244 0 (1, 1)
	246 pop (1, 1)
	247 aload_0 (1, 1)
	248 getfield (1, 1)
	249 org/apache/commons/math3/analysis/interpolation/HermiteInterpolator.abscissae:Ljava/util/List; (1, 1)
	251 dload_1 (1, 1)
	252 invokestatic (1, 1)
	253 java/lang/Double.valueOf:(D)Ljava/lang/Double; (1, 1)
	255 invokeinterface (1, 1)
	256 java/util/List.checkInterpolation:()V (1, 1)
	258 0 (1, 1)
	260 pop (1, 1)
	261 iinc (1, 1)
	262 #4 (1, 1)
	263 -89 (1, 1)
	264 goto (1, 1)
	265 -261 (1, 1)
	267 return (0, 0)

Method: getPolynomials
	0 aload_0 (0, 0)
	1 invokespecial (0, 0)
	2 org/apache/commons/math3/analysis/interpolation/HermiteInterpolator.checkInterpolation:()V (0, 0)
	4 aload_0 (0, 0)
	5 iconst_1 (0, 0)
	6 newarray (0, 0)
	7 7 (0, 0)
	8 dup (0, 0)
	9 iconst_0 (0, 0)
	10 dconst_0 (0, 0)
	11 dastore (0, 0)
	12 invokespecial (0, 0)
	13 org/apache/commons/math3/analysis/interpolation/HermiteInterpolator.polynomial:([D)Lorg/apache/commons/math3/analysis/polynomials/PolynomialFunction; (0, 0)
	15 astore_1 (0, 0)
	16 aload_0 (0, 0)
	17 getfield (0, 0)
	18 org/apache/commons/math3/analysis/interpolation/HermiteInterpolator.topDiagonal:Ljava/util/List; (0, 0)
	20 iconst_0 (0, 0)
	21 invokeinterface (0, 0)
	22 java/util/List.java/lang/Double (0, 0)
	24 0 (0, 0)
	26 checkcast (0, 0)
	27 [D (0, 0)
	29 arraylength (0, 0)
	30 anewarray (0, 0)
	31 org/apache/commons/math3/analysis/polynomials/PolynomialFunction (0, 0)
	33 astore_2 (0, 0)
	34 iconst_0 (1, 4)
	35 istore_3 (1, 4)
	36 iload_3 (1, 4)
	37 aload_2 (1, 4)
	38 arraylength (1, 4)
	39 if_icmpge (1, 4)
	40 13 (1, 4)
	42 aload_2 (1, 4)
	43 iload_3 (1, 4)
	44 aload_1 (1, 4)
	45 aastore (1, 4)
	46 iinc (1, 4)
	47 #3 (1, 4)
	48 -89 (1, 4)
	49 goto (1, 4)
	50 -13 (1, 4)
	52 aload_0 (0, 0)
	53 iconst_1 (0, 0)
	54 newarray (0, 0)
	55 7 (0, 0)
	56 dup (0, 0)
	57 iconst_0 (0, 0)
	58 dconst_1 (0, 0)
	59 dastore (0, 0)
	60 invokespecial (0, 0)
	61 org/apache/commons/math3/analysis/interpolation/HermiteInterpolator.polynomial:([D)Lorg/apache/commons/math3/analysis/polynomials/PolynomialFunction; (0, 0)
	63 astore_3 (0, 0)
	64 iconst_0 (1, 4)
	65 istore (1, 4)
	66 #4 (1, 4)
	67 iload (1, 4)
	68 #4 (1, 4)
	69 aload_0 (1, 4)
	70 getfield (1, 4)
	71 org/apache/commons/math3/analysis/interpolation/HermiteInterpolator.topDiagonal:Ljava/util/List; (1, 4)
	73 invokeinterface (1, 4)
	74 java/util/List.add:(ILjava/lang/Object;)V (1, 4)
	76 0 (1, 4)
	78 if_icmpge (1, 4)
	79 108 (1, 4)
	81 aload_0 (1, 4)
	82 getfield (1, 4)
	83 org/apache/commons/math3/analysis/interpolation/HermiteInterpolator.topDiagonal:Ljava/util/List; (1, 4)
	85 iload (1, 4)
	86 #4 (1, 4)
	87 invokeinterface (1, 4)
	88 java/util/List.java/lang/Double (1, 4)
	90 0 (1, 4)
	92 checkcast (1, 4)
	93 [D (1, 4)
	95 astore (1, 4)
	96 #5 (1, 4)
	97 iconst_0 (2, 4)
	98 istore (2, 4)
	99 #6 (2, 4)
	100 iload (2, 4)
	101 #6 (2, 4)
	102 aload_2 (2, 4)
	103 arraylength (2, 4)
	104 if_icmpge (2, 4)
	105 39 (2, 4)
	107 aload_2 (2, 4)
	108 iload (2, 4)
	109 #6 (2, 4)
	110 aload_2 (2, 4)
	111 iload (2, 4)
	112 #6 (2, 4)
	113 aaload (2, 4)
	114 aload_3 (2, 4)
	115 aload_0 (2, 4)
	116 iconst_1 (2, 4)
	117 newarray (2, 4)
	118 7 (2, 4)
	119 dup (2, 4)
	120 iconst_0 (2, 4)
	121 aload (2, 4)
	122 #5 (2, 4)
	123 iload (2, 4)
	124 #6 (2, 4)
	125 daload (2, 4)
	126 dastore (2, 4)
	127 invokespecial (2, 4)
	128 org/apache/commons/math3/analysis/interpolation/HermiteInterpolator.polynomial:([D)Lorg/apache/commons/math3/analysis/polynomials/PolynomialFunction; (2, 4)
	130 invokevirtual (2, 4)
	131 org/apache/commons/math3/analysis/polynomials/PolynomialFunction.multiply:(Lorg/apache/commons/math3/analysis/polynomials/PolynomialFunction;)Lorg/apache/commons/math3/analysis/polynomials/PolynomialFunction; (2, 4)
	133 invokevirtual (2, 4)
	134 org/apache/commons/math3/analysis/polynomials/PolynomialFunction.add:(Lorg/apache/commons/math3/analysis/polynomials/PolynomialFunction;)Lorg/apache/commons/math3/analysis/polynomials/PolynomialFunction; (2, 4)
	136 aastore (2, 4)
	137 iinc (2, 4)
	138 #6 (2, 4)
	139 -89 (2, 4)
	140 goto (2, 4)
	141 -40 (2, 4)
	143 aload_3 (1, 4)
	144 aload_0 (1, 4)
	145 iconst_2 (1, 4)
	146 newarray (1, 4)
	147 7 (1, 4)
	148 dup (1, 4)
	149 iconst_0 (1, 4)
	150 aload_0 (1, 4)
	151 getfield (1, 4)
	152 org/apache/commons/math3/analysis/interpolation/HermiteInterpolator.abscissae:Ljava/util/List; (1, 4)
	154 iload (1, 4)
	155 #4 (1, 4)
	156 invokeinterface (1, 4)
	157 java/util/List.java/lang/Double (1, 4)
	159 0 (1, 4)
	161 checkcast (1, 4)
	162 java/lang/Double (1, 4)
	164 invokevirtual (1, 4)
	165 java/lang/Double.doubleValue:()D (1, 4)
	167 dneg (1, 4)
	168 dastore (1, 4)
	169 dup (1, 4)
	170 iconst_1 (1, 4)
	171 dconst_1 (1, 4)
	172 dastore (1, 4)
	173 invokespecial (1, 4)
	174 org/apache/commons/math3/analysis/interpolation/HermiteInterpolator.polynomial:([D)Lorg/apache/commons/math3/analysis/polynomials/PolynomialFunction; (1, 4)
	176 invokevirtual (1, 4)
	177 org/apache/commons/math3/analysis/polynomials/PolynomialFunction.multiply:(Lorg/apache/commons/math3/analysis/polynomials/PolynomialFunction;)Lorg/apache/commons/math3/analysis/polynomials/PolynomialFunction; (1, 4)
	179 astore_3 (1, 4)
	180 iinc (1, 4)
	181 #4 (1, 4)
	182 -89 (1, 4)
	183 goto (1, 4)
	184 -116 (1, 4)
	186 aload_2 (0, 1)
	187 areturn (0, 1)

Method: value
	0 aload_0 (0, 0)
	1 invokespecial (0, 0)
	2 org/apache/commons/math3/analysis/interpolation/HermiteInterpolator.checkInterpolation:()V (0, 0)
	4 aload_0 (0, 0)
	5 getfield (0, 0)
	6 org/apache/commons/math3/analysis/interpolation/HermiteInterpolator.topDiagonal:Ljava/util/List; (0, 0)
	8 iconst_0 (0, 0)
	9 invokeinterface (0, 0)
	10 java/util/List.java/lang/Double (0, 0)
	12 0 (0, 0)
	14 checkcast (0, 0)
	15 [D (0, 0)
	17 arraylength (0, 0)
	18 anewarray (0, 0)
	19 org/apache/commons/math3/analysis/differentiation/DerivativeStructure (0, 0)
	21 astore_2 (0, 0)
	22 aload_2 (0, 0)
	23 aload_1 (0, 0)
	24 invokevirtual (0, 0)
	25 org/apache/commons/math3/analysis/differentiation/DerivativeStructure.getField:()Lorg/apache/commons/math3/Field; (0, 0)
	27 invokeinterface (0, 0)
	28 org/apache/commons/math3/Field.java/util/Arrays (0, 0)
	30 0 (0, 0)
	32 invokestatic (0, 0)
	33 java/util/Arrays.fill:([Ljava/lang/Object;Ljava/lang/Object;)V (0, 0)
	35 aload_1 (0, 0)
	36 invokevirtual (0, 0)
	37 org/apache/commons/math3/analysis/differentiation/DerivativeStructure.getField:()Lorg/apache/commons/math3/Field; (0, 0)
	39 invokeinterface (0, 0)
	40 org/apache/commons/math3/Field.multiply:(D)Lorg/apache/commons/math3/analysis/differentiation/DerivativeStructure; (0, 0)
	42 0 (0, 0)
	44 checkcast (0, 0)
	45 org/apache/commons/math3/analysis/differentiation/DerivativeStructure (0, 0)
	47 astore_3 (0, 0)
	48 iconst_0 (1, 4)
	49 istore (1, 4)
	50 #4 (1, 4)
	51 iload (1, 4)
	52 #4 (1, 4)
	53 aload_0 (1, 4)
	54 getfield (1, 4)
	55 org/apache/commons/math3/analysis/interpolation/HermiteInterpolator.topDiagonal:Ljava/util/List; (1, 4)
	57 invokeinterface (1, 4)
	58 java/util/List.add:(ILjava/lang/Object;)V (1, 4)
	60 0 (1, 4)
	62 if_icmpge (1, 4)
	63 91 (1, 4)
	65 aload_0 (1, 1)
	66 getfield (1, 1)
	67 org/apache/commons/math3/analysis/interpolation/HermiteInterpolator.topDiagonal:Ljava/util/List; (1, 1)
	69 iload (1, 1)
	70 #4 (1, 1)
	71 invokeinterface (1, 1)
	72 java/util/List.java/lang/Double (1, 1)
	74 0 (1, 1)
	76 checkcast (1, 1)
	77 [D (1, 1)
	79 astore (1, 1)
	80 #5 (1, 1)
	81 iconst_0 (2, 4)
	82 istore (2, 4)
	83 #6 (2, 4)
	84 iload (2, 4)
	85 #6 (2, 4)
	86 aload_2 (2, 4)
	87 arraylength (2, 4)
	88 if_icmpge (2, 4)
	89 29 (2, 4)
	91 aload_2 (2, 1)
	92 iload (2, 1)
	93 #6 (2, 1)
	94 aload_2 (2, 1)
	95 iload (2, 1)
	96 #6 (2, 1)
	97 aaload (2, 1)
	98 aload_3 (2, 1)
	99 aload (2, 1)
	100 #5 (2, 1)
	101 iload (2, 1)
	102 #6 (2, 1)
	103 daload (2, 1)
	104 invokevirtual (2, 1)
	105 org/apache/commons/math3/analysis/differentiation/DerivativeStructure.multiply:(D)Lorg/apache/commons/math3/analysis/differentiation/DerivativeStructure; (2, 1)
	107 invokevirtual (2, 1)
	108 org/apache/commons/math3/analysis/differentiation/DerivativeStructure.add:(Lorg/apache/commons/math3/analysis/differentiation/DerivativeStructure;)Lorg/apache/commons/math3/analysis/differentiation/DerivativeStructure; (2, 1)
	110 aastore (2, 1)
	111 iinc (2, 1)
	112 #6 (2, 1)
	113 -89 (2, 1)
	114 goto (2, 1)
	115 -30 (2, 1)
	117 aload_1 (1, 1)
	118 aload_0 (1, 1)
	119 getfield (1, 1)
	120 org/apache/commons/math3/analysis/interpolation/HermiteInterpolator.abscissae:Ljava/util/List; (1, 1)
	122 iload (1, 1)
	123 #4 (1, 1)
	124 invokeinterface (1, 1)
	125 java/util/List.java/lang/Double (1, 1)
	127 0 (1, 1)
	129 checkcast (1, 1)
	130 java/lang/Double (1, 1)
	132 invokevirtual (1, 1)
	133 java/lang/Double.doubleValue:()D (1, 1)
	135 invokevirtual (1, 1)
	136 org/apache/commons/math3/analysis/differentiation/DerivativeStructure.subtract:(D)Lorg/apache/commons/math3/analysis/differentiation/DerivativeStructure; (1, 1)
	138 astore (1, 1)
	139 #6 (1, 1)
	140 aload_3 (1, 1)
	141 aload (1, 1)
	142 #6 (1, 1)
	143 invokevirtual (1, 1)
	144 org/apache/commons/math3/analysis/differentiation/DerivativeStructure.multiply:(Lorg/apache/commons/math3/analysis/differentiation/DerivativeStructure;)Lorg/apache/commons/math3/analysis/differentiation/DerivativeStructure; (1, 1)
	146 astore_3 (1, 1)
	147 iinc (1, 1)
	148 #4 (1, 1)
	149 -89 (1, 1)
	150 goto (1, 1)
	151 -99 (1, 1)
	153 aload_2 (0, 0)
	154 areturn (0, 0)

Method: checkInterpolation
	0 aload_0 (1, 1)
	1 getfield (1, 1)
	2 org/apache/commons/math3/analysis/interpolation/HermiteInterpolator.abscissae:Ljava/util/List; (1, 1)
	4 invokeinterface (1, 1)
	5 java/util/List.org/apache/commons/math3/exception/NoDataException (1, 1)
	7 0 (1, 1)
	9 ifeq (1, 1)
	10 14 (1, 1)
	12 new (1, 1)
	13 org/apache/commons/math3/exception/NoDataException (1, 1)
	15 dup (1, 1)
	16 getstatic (1, 1)
	17 org/apache/commons/math3/exception/util/LocalizedFormats.EMPTY_INTERPOLATION_SAMPLE:Lorg/apache/commons/math3/exception/util/LocalizedFormats; (1, 1)
	19 invokespecial (1, 1)
	20 org/apache/commons/math3/exception/NoDataException.<init>:(Lorg/apache/commons/math3/exception/util/Localizable;)V (1, 1)
	22 athrow (1, 1)
	23 return (0, 0)

Method: polynomial
	0 new (0, 0)
	1 org/apache/commons/math3/analysis/polynomials/PolynomialFunction (0, 0)
	3 dup (0, 0)
	4 aload_1 (0, 0)
	5 invokespecial (0, 0)
	6 org/apache/commons/math3/analysis/polynomials/PolynomialFunction.<init>:([D)V (0, 0)
	8 areturn (0, 0)

