Method: <init>
	0 aload_0 (0, 0)
	1 invokespecial (0, 0)
	2 java/lang/Object.<init>:()V (0, 0)
	4 aload_0 (0, 0)
	5 aload_1 (0, 0)
	6 getfield (0, 0)
	7 org/apache/commons/math3/analysis/interpolation/InterpolatingMicrosphere.dimension:I (0, 0)
	9 putfield (0, 0)
	10 org/apache/commons/math3/analysis/interpolation/InterpolatingMicrosphere.dimension:I (0, 0)
	12 aload_0 (0, 0)
	13 aload_1 (0, 0)
	14 getfield (0, 0)
	15 org/apache/commons/math3/analysis/interpolation/InterpolatingMicrosphere.size:I (0, 0)
	17 putfield (0, 0)
	18 org/apache/commons/math3/analysis/interpolation/InterpolatingMicrosphere.size:I (0, 0)
	20 aload_0 (0, 0)
	21 aload_1 (0, 0)
	22 getfield (0, 0)
	23 org/apache/commons/math3/analysis/interpolation/InterpolatingMicrosphere.maxDarkFraction:D (0, 0)
	25 putfield (0, 0)
	26 org/apache/commons/math3/analysis/interpolation/InterpolatingMicrosphere.maxDarkFraction:D (0, 0)
	28 aload_0 (0, 0)
	29 aload_1 (0, 0)
	30 getfield (0, 0)
	31 org/apache/commons/math3/analysis/interpolation/InterpolatingMicrosphere.darkThreshold:D (0, 0)
	33 putfield (0, 0)
	34 org/apache/commons/math3/analysis/interpolation/InterpolatingMicrosphere.darkThreshold:D (0, 0)
	36 aload_0 (0, 0)
	37 aload_1 (0, 0)
	38 getfield (0, 0)
	39 org/apache/commons/math3/analysis/interpolation/InterpolatingMicrosphere.background:D (0, 0)
	41 putfield (0, 0)
	42 org/apache/commons/math3/analysis/interpolation/InterpolatingMicrosphere.background:D (0, 0)
	44 aload_0 (0, 0)
	45 aload_1 (0, 0)
	46 getfield (0, 0)
	47 org/apache/commons/math3/analysis/interpolation/InterpolatingMicrosphere.microsphere:Ljava/util/List; (0, 0)
	49 putfield (0, 0)
	50 org/apache/commons/math3/analysis/interpolation/InterpolatingMicrosphere.microsphere:Ljava/util/List; (0, 0)
	52 aload_0 (0, 0)
	53 new (0, 0)
	54 java/util/ArrayList (0, 0)
	56 dup (0, 0)
	57 aload_0 (0, 0)
	58 getfield (0, 0)
	59 org/apache/commons/math3/analysis/interpolation/InterpolatingMicrosphere.size:I (0, 0)
	61 invokespecial (0, 0)
	62 java/util/ArrayList.<init>:(I)V (0, 0)
	64 putfield (0, 0)
	65 org/apache/commons/math3/analysis/interpolation/InterpolatingMicrosphere.microsphereData:Ljava/util/List; (0, 0)
	67 aload_1 (2, 4)
	68 getfield (2, 4)
	69 org/apache/commons/math3/analysis/interpolation/InterpolatingMicrosphere.microsphereData:Ljava/util/List; (2, 4)
	71 invokeinterface (2, 4)
	72 java/util/List.java/util/Iterator (2, 4)
	74 0 (2, 4)
	76 astore_2 (2, 4)
	77 aload_2 (2, 4)
	78 invokeinterface (2, 4)
	79 java/util/Iterator.next:()Ljava/lang/Object; (2, 4)
	81 0 (2, 4)
	83 ifeq (2, 4)
	84 41 (2, 4)
	86 aload_2 (2, 4)
	87 invokeinterface (2, 4)
	88 java/util/Iterator.org/apache/commons/math3/analysis/interpolation/InterpolatingMicrosphere$FacetData (2, 4)
	90 0 (2, 4)
	92 checkcast (2, 4)
	93 org/apache/commons/math3/analysis/interpolation/InterpolatingMicrosphere$FacetData (2, 4)
	95 astore_3 (2, 4)
	96 aload_0 (2, 4)
	97 getfield (2, 4)
	98 org/apache/commons/math3/analysis/interpolation/InterpolatingMicrosphere.microsphereData:Ljava/util/List; (2, 4)
	100 new (2, 4)
	101 org/apache/commons/math3/analysis/interpolation/InterpolatingMicrosphere$FacetData (2, 4)
	103 dup (2, 4)
	104 aload_3 (2, 4)
	105 invokevirtual (2, 4)
	106 org/apache/commons/math3/analysis/interpolation/InterpolatingMicrosphere$FacetData.illumination:()D (2, 4)
	108 aload_3 (2, 4)
	109 invokevirtual (2, 4)
	110 org/apache/commons/math3/analysis/interpolation/InterpolatingMicrosphere$FacetData.sample:()D (2, 4)
	112 invokespecial (2, 4)
	113 org/apache/commons/math3/analysis/interpolation/InterpolatingMicrosphere$FacetData.<init>:(DD)V (2, 4)
	115 invokeinterface (2, 4)
	116 java/util/List.org/apache/commons/math3/analysis/interpolation/InterpolatingMicrosphere (2, 4)
	118 0 (2, 4)
	120 pop (2, 4)
	121 goto (0, 0)
	122 -44 (0, 0)
	124 return (0, 0)

Method: copy
	0 new (0, 0)
	1 org/apache/commons/math3/analysis/interpolation/InterpolatingMicrosphere (0, 0)
	3 dup (0, 0)
	4 aload_0 (0, 0)
	5 invokespecial (0, 0)
	6 org/apache/commons/math3/analysis/interpolation/InterpolatingMicrosphere.<init>:(Lorg/apache/commons/math3/analysis/interpolation/InterpolatingMicrosphere;)V (0, 0)
	8 areturn (0, 0)

Method: getDimension
	0 aload_0 (0, 0)
	1 getfield (0, 0)
	2 org/apache/commons/math3/analysis/interpolation/InterpolatingMicrosphere.dimension:I (0, 0)
	4 ireturn (0, 0)

Method: getSize
	0 aload_0 (0, 0)
	1 getfield (0, 0)
	2 org/apache/commons/math3/analysis/interpolation/InterpolatingMicrosphere.size:I (0, 0)
	4 ireturn (0, 0)

Method: value
	0 dload (1, 1)
	1 #4 (1, 1)
	2 dconst_0 (1, 1)
	3 dcmpg (1, 1)
	4 ifge (1, 1)
	5 16 (1, 1)
	7 new (1, 1)
	8 org/apache/commons/math3/exception/NotPositiveException (1, 1)
	10 dup (1, 1)
	11 dload (1, 1)
	12 #4 (1, 1)
	13 invokestatic (1, 1)
	14 java/lang/Double.valueOf:(D)Ljava/lang/Double; (1, 1)
	16 invokespecial (1, 1)
	17 org/apache/commons/math3/exception/NotPositiveException.<init>:(Ljava/lang/Number;)V (1, 1)
	19 athrow (1, 1)
	20 aload_0 (0, 0)
	21 invokespecial (0, 0)
	22 org/apache/commons/math3/analysis/interpolation/InterpolatingMicrosphere.clear:()V (0, 0)
	24 aload_2 (0, 0)
	25 arraylength (0, 0)
	26 istore (0, 0)
	27 #8 (0, 0)
	28 iconst_0 (1, 4)
	29 istore (1, 4)
	30 #9 (1, 4)
	31 iload (1, 4)
	32 #9 (1, 4)
	33 iload (1, 4)
	34 #8 (1, 4)
	35 if_icmpge (1, 4)
	36 64 (1, 4)
	38 aload_2 (1, 1)
	39 iload (1, 1)
	40 #9 (1, 1)
	41 aaload (1, 1)
	42 aload_1 (1, 1)
	43 invokestatic (1, 1)
	44 org/apache/commons/math3/util/MathArrays.ebeSubtract:([D[D)[D (1, 1)
	46 astore (1, 1)
	47 #10 (1, 1)
	48 aload (1, 1)
	49 #10 (1, 1)
	50 invokestatic (1, 1)
	51 org/apache/commons/math3/util/MathArrays.safeNorm:([D)D (1, 1)
	53 dstore (1, 1)
	54 #11 (1, 1)
	55 dload (2, 1)
	56 #11 (2, 1)
	57 invokestatic (2, 1)
	58 org/apache/commons/math3/util/FastMath.abs:(D)D (2, 1)
	60 dload (2, 1)
	61 #6 (2, 1)
	62 dcmpg (2, 1)
	63 ifge (2, 1)
	64 8 (2, 1)
	66 aload_3 (2, 1)
	67 iload (2, 1)
	68 #9 (2, 1)
	69 daload (2, 1)
	70 dreturn (2, 1)
	71 dload (1, 1)
	72 #11 (1, 1)
	73 dload (1, 1)
	74 #4 (1, 1)
	75 dneg (1, 1)
	76 invokestatic (1, 1)
	77 org/apache/commons/math3/util/FastMath.pow:(DD)D (1, 1)
	79 dstore (1, 1)
	80 #13 (1, 1)
	81 aload_0 (1, 1)
	82 aload (1, 1)
	83 #10 (1, 1)
	84 aload_3 (1, 1)
	85 iload (1, 1)
	86 #9 (1, 1)
	87 daload (1, 1)
	88 dload (1, 1)
	89 #13 (1, 1)
	90 invokespecial (1, 1)
	91 org/apache/commons/math3/analysis/interpolation/InterpolatingMicrosphere.illuminate:([DDD)V (1, 1)
	93 iinc (1, 1)
	94 #9 (1, 1)
	95 -89 (1, 1)
	96 goto (1, 1)
	97 -65 (1, 1)
	99 aload_0 (0, 0)
	100 invokespecial (0, 0)
	101 org/apache/commons/math3/analysis/interpolation/InterpolatingMicrosphere.interpolate:()D (0, 0)
	103 dreturn (0, 0)

Method: add
	0 aload_0 (1, 1)
	1 getfield (1, 1)
	2 org/apache/commons/math3/analysis/interpolation/InterpolatingMicrosphere.microsphere:Ljava/util/List; (1, 1)
	4 invokeinterface (1, 1)
	5 java/util/List.org/apache/commons/math3/exception/MaxCountExceededException (1, 1)
	7 0 (1, 1)
	9 aload_0 (1, 1)
	10 getfield (1, 1)
	11 org/apache/commons/math3/analysis/interpolation/InterpolatingMicrosphere.size:I (1, 1)
	13 if_icmplt (1, 1)
	14 18 (1, 1)
	16 new (1, 1)
	17 org/apache/commons/math3/exception/MaxCountExceededException (1, 1)
	19 dup (1, 1)
	20 aload_0 (1, 1)
	21 getfield (1, 1)
	22 org/apache/commons/math3/analysis/interpolation/InterpolatingMicrosphere.size:I (1, 1)
	24 invokestatic (1, 1)
	25 java/lang/Integer.valueOf:(I)Ljava/lang/Integer; (1, 1)
	27 invokespecial (1, 1)
	28 org/apache/commons/math3/exception/MaxCountExceededException.<init>:(Ljava/lang/Number;)V (1, 1)
	30 athrow (1, 1)
	31 aload_1 (1, 1)
	32 arraylength (1, 1)
	33 aload_0 (1, 1)
	34 getfield (1, 1)
	35 org/apache/commons/math3/analysis/interpolation/InterpolatingMicrosphere.dimension:I (1, 1)
	37 if_icmple (1, 1)
	38 17 (1, 1)
	40 new (1, 1)
	41 org/apache/commons/math3/exception/DimensionMismatchException (1, 1)
	43 dup (1, 1)
	44 aload_1 (1, 1)
	45 arraylength (1, 1)
	46 aload_0 (1, 1)
	47 getfield (1, 1)
	48 org/apache/commons/math3/analysis/interpolation/InterpolatingMicrosphere.dimension:I (1, 1)
	50 invokespecial (1, 1)
	51 org/apache/commons/math3/exception/DimensionMismatchException.<init>:(II)V (1, 1)
	53 athrow (1, 1)
	54 aload_0 (0, 0)
	55 getfield (0, 0)
	56 org/apache/commons/math3/analysis/interpolation/InterpolatingMicrosphere.microsphere:Ljava/util/List; (0, 0)
	58 new (0, 0)
	59 org/apache/commons/math3/analysis/interpolation/InterpolatingMicrosphere$Facet (0, 0)
	61 dup (0, 0)
	62 iload_2 (0, 0)
	63 ifeq (0, 0)
	64 13 (0, 0)
	66 aload_1 (0, 0)
	67 invokevirtual (0, 0)
	68 [D.clone:()Ljava/lang/Object; (0, 0)
	70 checkcast (0, 0)
	71 [D (0, 0)
	73 goto (0, 0)
	74 4 (0, 0)
	76 aload_1 (0, 0)
	77 invokespecial (0, 0)
	78 org/apache/commons/math3/analysis/interpolation/InterpolatingMicrosphere$Facet.<init>:([D)V (0, 0)
	80 invokeinterface (0, 0)
	81 java/util/List.org/apache/commons/math3/analysis/interpolation/InterpolatingMicrosphere (0, 0)
	83 0 (0, 0)
	85 pop (0, 0)
	86 aload_0 (0, 0)
	87 getfield (0, 0)
	88 org/apache/commons/math3/analysis/interpolation/InterpolatingMicrosphere.microsphereData:Ljava/util/List; (0, 0)
	90 new (0, 0)
	91 org/apache/commons/math3/analysis/interpolation/InterpolatingMicrosphere$FacetData (0, 0)
	93 dup (0, 0)
	94 dconst_0 (0, 0)
	95 dconst_0 (0, 0)
	96 invokespecial (0, 0)
	97 org/apache/commons/math3/analysis/interpolation/InterpolatingMicrosphere$FacetData.<init>:(DD)V (0, 0)
	99 invokeinterface (0, 0)
	100 java/util/List.org/apache/commons/math3/analysis/interpolation/InterpolatingMicrosphere (0, 0)
	102 0 (0, 0)
	104 pop (0, 0)
	105 return (0, 0)

Method: interpolate
	0 iconst_0 (0, 0)
	1 istore_1 (0, 0)
	2 dconst_0 (0, 0)
	3 dstore_2 (0, 0)
	4 dconst_0 (0, 0)
	5 dstore (0, 0)
	6 #4 (0, 0)
	7 aload_0 (1, 4)
	8 getfield (1, 4)
	9 org/apache/commons/math3/analysis/interpolation/InterpolatingMicrosphere.microsphereData:Ljava/util/List; (1, 4)
	11 invokeinterface (1, 4)
	12 java/util/List.java/util/Iterator (1, 4)
	14 0 (1, 4)
	16 astore (1, 4)
	17 #6 (1, 4)
	18 aload (1, 4)
	19 #6 (1, 4)
	20 invokeinterface (1, 4)
	21 java/util/Iterator.next:()Ljava/lang/Object; (1, 4)
	23 0 (1, 4)
	25 ifeq (1, 4)
	26 56 (1, 4)
	28 aload (1, 4)
	29 #6 (1, 4)
	30 invokeinterface (1, 4)
	31 java/util/Iterator.org/apache/commons/math3/analysis/interpolation/InterpolatingMicrosphere$FacetData (1, 4)
	33 0 (1, 4)
	35 checkcast (1, 4)
	36 org/apache/commons/math3/analysis/interpolation/InterpolatingMicrosphere$FacetData (1, 4)
	38 astore (1, 4)
	39 #7 (1, 4)
	40 aload (1, 4)
	41 #7 (1, 4)
	42 invokevirtual (1, 4)
	43 org/apache/commons/math3/analysis/interpolation/InterpolatingMicrosphere$FacetData.illumination:()D (1, 4)
	45 dstore (1, 4)
	46 #8 (1, 4)
	47 dload (2, 1)
	48 #8 (2, 1)
	49 dconst_0 (2, 1)
	50 dcmpl (2, 1)
	51 ifeq (2, 1)
	52 24 (2, 1)
	54 dload_2 (2, 1)
	55 dload (2, 1)
	56 #8 (2, 1)
	57 aload (2, 1)
	58 #7 (2, 1)
	59 invokevirtual (2, 1)
	60 org/apache/commons/math3/analysis/interpolation/InterpolatingMicrosphere$FacetData.sample:()D (2, 1)
	62 dmul (2, 1)
	63 dadd (2, 1)
	64 dstore_2 (2, 1)
	65 dload (2, 1)
	66 #4 (2, 1)
	67 dload (2, 1)
	68 #8 (2, 1)
	69 dadd (2, 1)
	70 dstore (2, 1)
	71 #4 (2, 1)
	72 goto (2, 1)
	73 6 (2, 1)
	75 iinc (2, 2)
	76 #1 (2, 2)
	77 -89 (2, 2)
	78 goto (0, 0)
	79 -60 (0, 0)
	81 iload_1 (0, 0)
	82 i2d (0, 0)
	83 aload_0 (0, 0)
	84 getfield (0, 0)
	85 org/apache/commons/math3/analysis/interpolation/InterpolatingMicrosphere.size:I (0, 0)
	87 i2d (0, 0)
	88 ddiv (0, 0)
	89 dstore (0, 0)
	90 #6 (0, 0)
	91 dload (0, 0)
	92 #6 (0, 0)
	93 aload_0 (0, 0)
	94 getfield (0, 0)
	95 org/apache/commons/math3/analysis/interpolation/InterpolatingMicrosphere.maxDarkFraction:D (0, 0)
	97 dcmpg (0, 0)
	98 ifgt (0, 0)
	99 10 (0, 0)
	101 dload_2 (0, 0)
	102 dload (0, 0)
	103 #4 (0, 0)
	104 ddiv (0, 0)
	105 goto (0, 0)
	106 7 (0, 0)
	108 aload_0 (0, 0)
	109 getfield (0, 0)
	110 org/apache/commons/math3/analysis/interpolation/InterpolatingMicrosphere.background:D (0, 0)
	112 dreturn (0, 0)

Method: illuminate
	0 iconst_0 (1, 4)
	1 istore (1, 4)
	2 #6 (1, 4)
	3 iload (1, 4)
	4 #6 (1, 4)
	5 aload_0 (1, 4)
	6 getfield (1, 4)
	7 org/apache/commons/math3/analysis/interpolation/InterpolatingMicrosphere.size:I (1, 4)
	9 if_icmpge (1, 4)
	10 105 (1, 4)
	12 aload_0 (1, 4)
	13 getfield (1, 4)
	14 org/apache/commons/math3/analysis/interpolation/InterpolatingMicrosphere.microsphere:Ljava/util/List; (1, 4)
	16 iload (1, 4)
	17 #6 (1, 4)
	18 invokeinterface (1, 4)
	19 java/util/List.getNormal:()[D (1, 4)
	21 0 (1, 4)
	23 checkcast (1, 4)
	24 org/apache/commons/math3/analysis/interpolation/InterpolatingMicrosphere$Facet (1, 4)
	26 invokevirtual (1, 4)
	27 org/apache/commons/math3/analysis/interpolation/InterpolatingMicrosphere$Facet.getNormal:()[D (1, 4)
	29 astore (1, 4)
	30 #7 (1, 4)
	31 aload (1, 4)
	32 #7 (1, 4)
	33 aload_1 (1, 4)
	34 invokestatic (1, 4)
	35 org/apache/commons/math3/util/MathArrays.cosAngle:([D[D)D (1, 4)
	37 dstore (1, 4)
	38 #8 (1, 4)
	39 dload (2, 1)
	40 #8 (2, 1)
	41 dconst_0 (2, 1)
	42 dcmpl (2, 1)
	43 ifle (2, 1)
	44 65 (2, 1)
	46 dload (2, 1)
	47 #8 (2, 1)
	48 dload (2, 1)
	49 #4 (2, 1)
	50 dmul (2, 1)
	51 dstore (2, 1)
	52 #10 (2, 1)
	53 dload (2, 1)
	54 #10 (2, 1)
	55 aload_0 (2, 1)
	56 getfield (2, 1)
	57 org/apache/commons/math3/analysis/interpolation/InterpolatingMicrosphere.darkThreshold:D (2, 1)
	59 dcmpl (2, 1)
	60 ifle (2, 1)
	61 48 (2, 1)
	63 dload (2, 1)
	64 #10 (2, 1)
	65 aload_0 (2, 1)
	66 getfield (2, 1)
	67 org/apache/commons/math3/analysis/interpolation/InterpolatingMicrosphere.microsphereData:Ljava/util/List; (2, 1)
	69 iload (2, 1)
	70 #6 (2, 1)
	71 invokeinterface (2, 1)
	72 java/util/List.getNormal:()[D (2, 1)
	74 0 (2, 1)
	76 checkcast (2, 1)
	77 org/apache/commons/math3/analysis/interpolation/InterpolatingMicrosphere$FacetData (2, 1)
	79 invokevirtual (2, 1)
	80 org/apache/commons/math3/analysis/interpolation/InterpolatingMicrosphere$FacetData.illumination:()D (2, 1)
	82 dcmpl (2, 1)
	83 ifle (2, 1)
	84 25 (2, 1)
	86 aload_0 (2, 1)
	87 getfield (2, 1)
	88 org/apache/commons/math3/analysis/interpolation/InterpolatingMicrosphere.microsphereData:Ljava/util/List; (2, 1)
	90 iload (2, 1)
	91 #6 (2, 1)
	92 new (2, 1)
	93 org/apache/commons/math3/analysis/interpolation/InterpolatingMicrosphere$FacetData (2, 1)
	95 dup (2, 1)
	96 dload (2, 1)
	97 #10 (2, 1)
	98 dload_2 (2, 1)
	99 invokespecial (2, 1)
	100 org/apache/commons/math3/analysis/interpolation/InterpolatingMicrosphere$FacetData.<init>:(DD)V (2, 1)
	102 invokeinterface (2, 1)
	103 java/util/List.java/lang/Object (2, 1)
	105 0 (2, 1)
	107 pop (2, 1)
	108 iinc (2, 1)
	109 #6 (2, 1)
	110 -89 (2, 1)
	111 goto (2, 1)
	112 -108 (2, 1)
	114 return (1, 4)

Method: clear
	0 iconst_0 (1, 4)
	1 istore_1 (1, 4)
	2 iload_1 (1, 4)
	3 aload_0 (1, 4)
	4 getfield (1, 4)
	5 org/apache/commons/math3/analysis/interpolation/InterpolatingMicrosphere.size:I (1, 4)
	7 if_icmpge (1, 4)
	8 29 (1, 4)
	10 aload_0 (1, 4)
	11 getfield (1, 4)
	12 org/apache/commons/math3/analysis/interpolation/InterpolatingMicrosphere.microsphereData:Ljava/util/List; (1, 4)
	14 iload_1 (1, 4)
	15 new (1, 4)
	16 org/apache/commons/math3/analysis/interpolation/InterpolatingMicrosphere$FacetData (1, 4)
	18 dup (1, 4)
	19 dconst_0 (1, 4)
	20 dconst_0 (1, 4)
	21 invokespecial (1, 4)
	22 org/apache/commons/math3/analysis/interpolation/InterpolatingMicrosphere$FacetData.<init>:(DD)V (1, 4)
	24 invokeinterface (1, 4)
	25 java/util/List.java/lang/Object (1, 4)
	27 0 (1, 4)
	29 pop (1, 4)
	30 iinc (1, 4)
	31 #1 (1, 4)
	32 -89 (1, 4)
	33 goto (1, 4)
	34 -31 (1, 4)
	36 return (0, 0)

