Method: <init>
	0 aload_0 (0, 0)
	1 invokespecial (0, 0)
	2 java/lang/Object.<init>:()V (0, 0)
	4 dload_1 (1, 1)
	5 dconst_0 (1, 1)
	6 dcmpg (1, 1)
	7 iflt (1, 1)
	8 9 (1, 1)
	10 dload_1 (1, 1)
	11 dconst_1 (1, 1)
	12 dcmpl (1, 1)
	13 ifle (1, 1)
	14 26 (1, 1)
	16 new (1, 1)
	17 org/apache/commons/math3/exception/OutOfRangeException (1, 1)
	19 dup (1, 1)
	20 getstatic (1, 1)
	21 org/apache/commons/math3/exception/util/LocalizedFormats.BANDWIDTH:Lorg/apache/commons/math3/exception/util/LocalizedFormats; (1, 1)
	23 dload_1 (1, 1)
	24 invokestatic (1, 1)
	25 java/lang/Double.valueOf:(D)Ljava/lang/Double; (1, 1)
	27 iconst_0 (1, 1)
	28 invokestatic (1, 1)
	29 java/lang/Integer.valueOf:(I)Ljava/lang/Integer; (1, 1)
	31 iconst_1 (1, 1)
	32 invokestatic (1, 1)
	33 java/lang/Integer.valueOf:(I)Ljava/lang/Integer; (1, 1)
	35 invokespecial (1, 1)
	36 org/apache/commons/math3/exception/OutOfRangeException.<init>:(Lorg/apache/commons/math3/exception/util/Localizable;Ljava/lang/Number;Ljava/lang/Number;Ljava/lang/Number;)V (1, 1)
	38 athrow (1, 1)
	39 aload_0 (1, 1)
	40 dload_1 (1, 1)
	41 putfield (1, 1)
	42 org/apache/commons/math3/analysis/interpolation/LoessInterpolator.bandwidth:D (1, 1)
	44 iload_3 (2, 1)
	45 ifge (2, 1)
	46 18 (2, 1)
	48 new (2, 1)
	49 org/apache/commons/math3/exception/NotPositiveException (2, 1)
	51 dup (2, 1)
	52 getstatic (2, 1)
	53 org/apache/commons/math3/exception/util/LocalizedFormats.ROBUSTNESS_ITERATIONS:Lorg/apache/commons/math3/exception/util/LocalizedFormats; (2, 1)
	55 iload_3 (2, 1)
	56 invokestatic (2, 1)
	57 java/lang/Integer.valueOf:(I)Ljava/lang/Integer; (2, 1)
	59 invokespecial (2, 1)
	60 org/apache/commons/math3/exception/NotPositiveException.<init>:(Lorg/apache/commons/math3/exception/util/Localizable;Ljava/lang/Number;)V (2, 1)
	62 athrow (2, 1)
	63 aload_0 (1, 1)
	64 iload_3 (1, 1)
	65 putfield (1, 1)
	66 org/apache/commons/math3/analysis/interpolation/LoessInterpolator.robustnessIters:I (1, 1)
	68 aload_0 (1, 1)
	69 dload (1, 1)
	70 #4 (1, 1)
	71 putfield (1, 1)
	72 org/apache/commons/math3/analysis/interpolation/LoessInterpolator.accuracy:D (1, 1)
	74 return (0, 0)

Method: interpolate
	0 aload_0 (0, 0)
	1 aload_1 (0, 0)
	2 aload_2 (0, 0)
	3 invokevirtual (0, 0)
	4 org/apache/commons/math3/analysis/interpolation/LoessInterpolator.interpolate:([D[D)Lorg/apache/commons/math3/analysis/polynomials/PolynomialSplineFunction; (0, 0)
	6 areturn (0, 0)

Method: smooth
	0 aload_1 (1, 1)
	1 arraylength (1, 1)
	2 aload_2 (1, 1)
	3 arraylength (1, 1)
	4 if_icmpeq (1, 1)
	5 15 (1, 1)
	7 new (1, 1)
	8 org/apache/commons/math3/exception/DimensionMismatchException (1, 1)
	10 dup (1, 1)
	11 aload_1 (1, 1)
	12 arraylength (1, 1)
	13 aload_2 (1, 1)
	14 arraylength (1, 1)
	15 invokespecial (1, 1)
	16 org/apache/commons/math3/exception/DimensionMismatchException.<init>:(II)V (1, 1)
	18 athrow (1, 1)
	19 aload_1 (0, 0)
	20 arraylength (0, 0)
	21 newarray (0, 0)
	22 7 (0, 0)
	23 astore_3 (0, 0)
	24 aload_3 (0, 0)
	25 dconst_1 (0, 0)
	26 invokestatic (0, 0)
	27 java/util/Arrays.fill:([DD)V (0, 0)
	29 aload_0 (0, 0)
	30 aload_1 (0, 0)
	31 aload_2 (0, 0)
	32 aload_3 (0, 0)
	33 invokevirtual (0, 0)
	34 org/apache/commons/math3/analysis/interpolation/LoessInterpolator.smooth:([D[D[D)[D (0, 0)
	36 areturn (0, 0)

Method: updateBandwidthInterval
	0 aload_3 (0, 0)
	1 iconst_0 (0, 0)
	2 iaload (0, 0)
	3 istore (0, 0)
	4 #4 (0, 0)
	5 aload_3 (0, 0)
	6 iconst_1 (0, 0)
	7 iaload (0, 0)
	8 istore (0, 0)
	9 #5 (0, 0)
	10 aload_1 (1, 1)
	11 iload (1, 1)
	12 #5 (1, 1)
	13 invokestatic (1, 1)
	14 org/apache/commons/math3/analysis/interpolation/LoessInterpolator.nextNonzero:([DI)I (1, 1)
	16 istore (1, 1)
	17 #6 (1, 1)
	18 iload (2, 1)
	19 #6 (2, 1)
	20 aload_0 (2, 1)
	21 arraylength (2, 1)
	22 if_icmpge (2, 1)
	23 42 (2, 1)
	25 aload_0 (2, 1)
	26 iload (2, 1)
	27 #6 (2, 1)
	28 daload (2, 1)
	29 aload_0 (2, 1)
	30 iload_2 (2, 1)
	31 daload (2, 1)
	32 dsub (2, 1)
	33 aload_0 (2, 1)
	34 iload_2 (2, 1)
	35 daload (2, 1)
	36 aload_0 (2, 1)
	37 iload (2, 1)
	38 #4 (2, 1)
	39 daload (2, 1)
	40 dsub (2, 1)
	41 dcmpg (2, 1)
	42 ifge (2, 1)
	43 22 (2, 1)
	45 aload_1 (2, 1)
	46 aload_3 (2, 1)
	47 iconst_0 (2, 1)
	48 iaload (2, 1)
	49 invokestatic (2, 1)
	50 org/apache/commons/math3/analysis/interpolation/LoessInterpolator.nextNonzero:([DI)I (2, 1)
	52 istore (2, 1)
	53 #7 (2, 1)
	54 aload_3 (2, 1)
	55 iconst_0 (2, 1)
	56 iload (2, 1)
	57 #7 (2, 1)
	58 iastore (2, 1)
	59 aload_3 (2, 1)
	60 iconst_1 (2, 1)
	61 iload (2, 1)
	62 #6 (2, 1)
	63 iastore (2, 1)
	64 return (0, 1)

Method: nextNonzero
	0 iload_1 (0, 0)
	1 iconst_1 (0, 0)
	2 iadd (0, 0)
	3 istore_2 (0, 0)
	4 iload_2 (1, 3)
	5 aload_0 (1, 3)
	6 arraylength (1, 3)
	7 if_icmpge (1, 3)
	8 17 (1, 3)
	10 aload_0 (1, 3)
	11 iload_2 (1, 3)
	12 daload (1, 3)
	13 dconst_0 (1, 3)
	14 dcmpl (1, 3)
	15 ifne (1, 3)
	16 9 (1, 3)
	18 iinc (1, 3)
	19 #2 (1, 3)
	20 -89 (1, 3)
	21 goto (1, 3)
	22 -17 (1, 3)
	24 iload_2 (0, 0)
	25 ireturn (0, 0)

Method: tricube
	0 dload_0 (0, 0)
	1 invokestatic (0, 0)
	2 org/apache/commons/math3/util/FastMath.abs:(D)D (0, 0)
	4 dstore_2 (0, 0)
	5 dload_2 (1, 1)
	6 dconst_1 (1, 1)
	7 dcmpl (1, 1)
	8 iflt (1, 1)
	9 5 (1, 1)
	11 dconst_0 (1, 1)
	12 dreturn (1, 1)
	13 dconst_1 (0, 0)
	14 dload_2 (0, 0)
	15 dload_2 (0, 0)
	16 dmul (0, 0)
	17 dload_2 (0, 0)
	18 dmul (0, 0)
	19 dsub (0, 0)
	20 dstore (0, 0)
	21 #4 (0, 0)
	22 dload (0, 0)
	23 #4 (0, 0)
	24 dload (0, 0)
	25 #4 (0, 0)
	26 dmul (0, 0)
	27 dload (0, 0)
	28 #4 (0, 0)
	29 dmul (0, 0)
	30 dreturn (0, 0)

Method: checkAllFiniteReal
	0 iconst_0 (1, 4)
	1 istore_1 (1, 4)
	2 iload_1 (1, 4)
	3 aload_0 (1, 4)
	4 arraylength (1, 4)
	5 if_icmpge (1, 4)
	6 15 (1, 4)
	8 aload_0 (1, 4)
	9 iload_1 (1, 4)
	10 daload (1, 4)
	11 invokestatic (1, 4)
	12 org/apache/commons/math3/util/MathUtils.checkFinite:(D)V (1, 4)
	14 iinc (1, 4)
	15 #1 (1, 4)
	16 -89 (1, 4)
	17 goto (1, 4)
	18 -15 (1, 4)
	20 return (0, 0)

