Method: <init>
	0 aload_0 (0, 0)
	1 invokespecial (0, 0)
	4 iload_2 (1, 1)
	5 ifge (1, 1)
	8 new (1, 1)
	11 dup (1, 1)
	12 iload_2 (1, 1)
	13 invokestatic (1, 1)
	16 invokespecial (1, 1)
	19 athrow (1, 1)
	20 iload_1 (1, 1)
	21 ifgt (1, 1)
	24 new (1, 1)
	27 dup (1, 1)
	28 iload_1 (1, 1)
	29 invokestatic (1, 1)
	32 invokespecial (1, 1)
	35 athrow (1, 1)
	36 aload_0 (0, 0)
	37 iload_1 (0, 0)
	38 putfield (0, 0)
	41 aload_0 (0, 0)
	42 iload_2 (0, 0)
	43 putfield (0, 0)
	46 return (0, 0)

Method: interpolate
	0 new (0, 0)
	3 dup (0, 0)
	4 aload_1 (0, 0)
	5 iconst_0 (0, 0)
	6 aaload (0, 0)
	7 arraylength (0, 0)
	8 invokespecial (0, 0)
	11 astore_3 (0, 0)
	12 new (0, 0)
	15 dup (0, 0)
	16 aload_1 (0, 0)
	17 aload_2 (0, 0)
	18 aload_0 (0, 0)
	19 getfield (0, 0)
	22 aload_0 (0, 0)
	23 getfield (0, 0)
	26 aload_3 (0, 0)
	27 invokespecial (0, 0)
	30 areturn (0, 0)

