Method: <init>
	0 aload_0 (0, 0)
	1 invokespecial (0, 0)
	2 java/lang/Object.<init>:()V (0, 0)
	4 dload_2 (2, 1)
	5 dconst_0 (2, 1)
	6 dcmpg (2, 1)
	7 ifge (2, 1)
	8 15 (2, 1)
	10 new (2, 1)
	11 org/apache/commons/math3/exception/NotPositiveException (2, 1)
	13 dup (2, 1)
	14 dload_2 (2, 1)
	15 invokestatic (2, 1)
	16 java/lang/Double.valueOf:(D)Ljava/lang/Double; (2, 1)
	18 invokespecial (2, 1)
	19 org/apache/commons/math3/exception/NotPositiveException.<init>:(Ljava/lang/Number;)V (2, 1)
	21 athrow (2, 1)
	22 aload_0 (0, 0)
	23 aload_1 (0, 0)
	24 putfield (0, 0)
	25 org/apache/commons/math3/analysis/interpolation/MicrosphereProjectionInterpolator.microsphere:Lorg/apache/commons/math3/analysis/interpolation/InterpolatingMicrosphere; (0, 0)
	27 aload_0 (0, 0)
	28 dload_2 (0, 0)
	29 putfield (0, 0)
	30 org/apache/commons/math3/analysis/interpolation/MicrosphereProjectionInterpolator.exponent:D (0, 0)
	32 aload_0 (0, 0)
	33 iload (0, 0)
	34 #4 (0, 0)
	35 putfield (0, 0)
	36 org/apache/commons/math3/analysis/interpolation/MicrosphereProjectionInterpolator.sharedSphere:Z (0, 0)
	38 aload_0 (0, 0)
	39 dload (0, 0)
	40 #5 (0, 0)
	41 putfield (0, 0)
	42 org/apache/commons/math3/analysis/interpolation/MicrosphereProjectionInterpolator.noInterpolationTolerance:D (0, 0)
	44 return (0, 0)

Method: interpolate
	0 aload_1 (0, 1)
	1 ifnull (0, 1)
	2 7 (0, 1)
	4 aload_2 (0, 1)
	5 ifnonnull (0, 1)
	6 11 (0, 1)
	8 new (0, 1)
	9 org/apache/commons/math3/exception/NullArgumentException (0, 1)
	11 dup (0, 1)
	12 invokespecial (0, 1)
	13 org/apache/commons/math3/exception/NullArgumentException.<init>:()V (0, 1)
	15 athrow (0, 1)
	16 aload_1 (1, 1)
	17 arraylength (1, 1)
	18 ifne (1, 1)
	19 11 (1, 1)
	21 new (1, 1)
	22 org/apache/commons/math3/exception/NoDataException (1, 1)
	24 dup (1, 1)
	25 invokespecial (1, 1)
	26 org/apache/commons/math3/exception/NoDataException.<init>:()V (1, 1)
	28 athrow (1, 1)
	29 aload_1 (1, 1)
	30 arraylength (1, 1)
	31 aload_2 (1, 1)
	32 arraylength (1, 1)
	33 if_icmpeq (1, 1)
	34 15 (1, 1)
	36 new (1, 1)
	37 org/apache/commons/math3/exception/DimensionMismatchException (1, 1)
	39 dup (1, 1)
	40 aload_1 (1, 1)
	41 arraylength (1, 1)
	42 aload_2 (1, 1)
	43 arraylength (1, 1)
	44 invokespecial (1, 1)
	45 org/apache/commons/math3/exception/DimensionMismatchException.<init>:(II)V (1, 1)
	47 athrow (1, 1)
	48 aload_1 (1, 1)
	49 iconst_0 (1, 1)
	50 aaload (1, 1)
	51 ifnonnull (1, 1)
	52 11 (1, 1)
	54 new (1, 1)
	55 org/apache/commons/math3/exception/NullArgumentException (1, 1)
	57 dup (1, 1)
	58 invokespecial (1, 1)
	59 org/apache/commons/math3/exception/NullArgumentException.<init>:()V (1, 1)
	61 athrow (1, 1)
	62 aload_0 (0, 1)
	63 getfield (0, 1)
	64 org/apache/commons/math3/analysis/interpolation/MicrosphereProjectionInterpolator.microsphere:Lorg/apache/commons/math3/analysis/interpolation/InterpolatingMicrosphere; (0, 1)
	66 invokevirtual (0, 1)
	67 org/apache/commons/math3/analysis/interpolation/InterpolatingMicrosphere.getDimension:()I (0, 1)
	69 istore_3 (0, 1)
	70 iload_3 (1, 1)
	71 aload_1 (1, 1)
	72 iconst_0 (1, 1)
	73 aaload (1, 1)
	74 arraylength (1, 1)
	75 if_icmpeq (1, 1)
	76 16 (1, 1)
	78 new (1, 1)
	79 org/apache/commons/math3/exception/DimensionMismatchException (1, 1)
	81 dup (1, 1)
	82 aload_1 (1, 1)
	83 iconst_0 (1, 1)
	84 aaload (1, 1)
	85 arraylength (1, 1)
	86 iload_3 (1, 1)
	87 invokespecial (1, 1)
	88 org/apache/commons/math3/exception/DimensionMismatchException.<init>:(II)V (1, 1)
	90 athrow (1, 1)
	91 aload_0 (0, 1)
	92 getfield (0, 1)
	93 org/apache/commons/math3/analysis/interpolation/MicrosphereProjectionInterpolator.sharedSphere:Z (0, 1)
	95 ifeq (0, 1)
	96 10 (0, 1)
	98 aload_0 (0, 1)
	99 getfield (0, 1)
	100 org/apache/commons/math3/analysis/interpolation/MicrosphereProjectionInterpolator.microsphere:Lorg/apache/commons/math3/analysis/interpolation/InterpolatingMicrosphere; (0, 1)
	102 goto (0, 1)
	103 10 (0, 1)
	105 aload_0 (0, 1)
	106 getfield (0, 1)
	107 org/apache/commons/math3/analysis/interpolation/MicrosphereProjectionInterpolator.microsphere:Lorg/apache/commons/math3/analysis/interpolation/InterpolatingMicrosphere; (0, 1)
	109 invokevirtual (0, 1)
	110 org/apache/commons/math3/analysis/interpolation/InterpolatingMicrosphere.copy:()Lorg/apache/commons/math3/analysis/interpolation/InterpolatingMicrosphere; (0, 1)
	112 astore (0, 1)
	113 #4 (0, 1)
	114 new (0, 1)
	115 org/apache/commons/math3/analysis/interpolation/MicrosphereProjectionInterpolator$1 (0, 1)
	117 dup (0, 1)
	118 aload_0 (0, 1)
	119 aload (0, 1)
	120 #4 (0, 1)
	121 aload_1 (0, 1)
	122 aload_2 (0, 1)
	123 invokespecial (0, 1)
	124 org/apache/commons/math3/analysis/interpolation/MicrosphereProjectionInterpolator$1.<init>:(Lorg/apache/commons/math3/analysis/interpolation/MicrosphereProjectionInterpolator;Lorg/apache/commons/math3/analysis/interpolation/InterpolatingMicrosphere;[[D[D)V (0, 1)
	126 areturn (0, 1)

Method: access$000
	0 aload_0 (0, 0)
	1 getfield (0, 0)
	2 org/apache/commons/math3/analysis/interpolation/MicrosphereProjectionInterpolator.exponent:D (0, 0)
	4 dreturn (0, 0)

Method: access$100
	0 aload_0 (0, 0)
	1 getfield (0, 0)
	2 org/apache/commons/math3/analysis/interpolation/MicrosphereProjectionInterpolator.noInterpolationTolerance:D (0, 0)
	4 dreturn (0, 0)

