Method: value
	0 aload_0 (0, 0)
	1 getfield (0, 0)
	2 org/apache/commons/math3/analysis/interpolation/MicrosphereProjectionInterpolator$1.val$m:Lorg/apache/commons/math3/analysis/interpolation/InterpolatingMicrosphere; (0, 0)
	4 aload_1 (0, 0)
	5 aload_0 (0, 0)
	6 getfield (0, 0)
	7 org/apache/commons/math3/analysis/interpolation/MicrosphereProjectionInterpolator$1.val$xval:[[D (0, 0)
	9 aload_0 (0, 0)
	10 getfield (0, 0)
	11 org/apache/commons/math3/analysis/interpolation/MicrosphereProjectionInterpolator$1.val$yval:[D (0, 0)
	13 aload_0 (0, 0)
	14 getfield (0, 0)
	15 org/apache/commons/math3/analysis/interpolation/MicrosphereProjectionInterpolator$1.this$0:Lorg/apache/commons/math3/analysis/interpolation/MicrosphereProjectionInterpolator; (0, 0)
	17 invokestatic (0, 0)
	18 org/apache/commons/math3/analysis/interpolation/MicrosphereProjectionInterpolator.access$000:(Lorg/apache/commons/math3/analysis/interpolation/MicrosphereProjectionInterpolator;)D (0, 0)
	20 aload_0 (0, 0)
	21 getfield (0, 0)
	22 org/apache/commons/math3/analysis/interpolation/MicrosphereProjectionInterpolator$1.this$0:Lorg/apache/commons/math3/analysis/interpolation/MicrosphereProjectionInterpolator; (0, 0)
	24 invokestatic (0, 0)
	25 org/apache/commons/math3/analysis/interpolation/MicrosphereProjectionInterpolator.access$100:(Lorg/apache/commons/math3/analysis/interpolation/MicrosphereProjectionInterpolator;)D (0, 0)
	27 invokevirtual (0, 0)
	28 org/apache/commons/math3/analysis/interpolation/InterpolatingMicrosphere.value:([D[[D[DDD)D (0, 0)
	30 dreturn (0, 0)

