Method: <init>
	0 aload_0 (0, 0)
	1 invokespecial (0, 0)
	2 java/lang/Object.<init>:()V (0, 0)
	4 aload_1 (1, 1)
	5 ifnull (1, 1)
	6 7 (1, 1)
	8 aload_2 (1, 1)
	9 ifnonnull (1, 1)
	10 11 (1, 1)
	12 new (1, 1)
	13 org/apache/commons/math3/exception/NullArgumentException (1, 1)
	15 dup (1, 1)
	16 invokespecial (1, 1)
	17 org/apache/commons/math3/exception/NullArgumentException.<init>:()V (1, 1)
	19 athrow (1, 1)
	20 aload_1 (2, 1)
	21 arraylength (2, 1)
	22 ifne (2, 1)
	23 11 (2, 1)
	25 new (2, 1)
	26 org/apache/commons/math3/exception/NoDataException (2, 1)
	28 dup (2, 1)
	29 invokespecial (2, 1)
	30 org/apache/commons/math3/exception/NoDataException.<init>:()V (2, 1)
	32 athrow (2, 1)
	33 aload_1 (2, 1)
	34 arraylength (2, 1)
	35 aload_2 (2, 1)
	36 arraylength (2, 1)
	37 if_icmpeq (2, 1)
	38 15 (2, 1)
	40 new (2, 1)
	41 org/apache/commons/math3/exception/DimensionMismatchException (2, 1)
	43 dup (2, 1)
	44 aload_1 (2, 1)
	45 arraylength (2, 1)
	46 aload_2 (2, 1)
	47 arraylength (2, 1)
	48 invokespecial (2, 1)
	49 org/apache/commons/math3/exception/DimensionMismatchException.<init>:(II)V (2, 1)
	51 athrow (2, 1)
	52 aload_1 (2, 1)
	53 iconst_0 (2, 1)
	54 aaload (2, 1)
	55 ifnonnull (2, 1)
	56 11 (2, 1)
	58 new (2, 1)
	59 org/apache/commons/math3/exception/NullArgumentException (2, 1)
	61 dup (2, 1)
	62 invokespecial (2, 1)
	63 org/apache/commons/math3/exception/NullArgumentException.<init>:()V (2, 1)
	65 athrow (2, 1)
	66 aload_0 (1, 1)
	67 aload_1 (1, 1)
	68 iconst_0 (1, 1)
	69 aaload (1, 1)
	70 arraylength (1, 1)
	71 putfield (1, 1)
	72 org/apache/commons/math3/analysis/interpolation/MicrosphereInterpolatingFunction.dimension:I (1, 1)
	74 aload_0 (1, 1)
	75 iload_3 (1, 1)
	76 i2d (1, 1)
	77 putfield (1, 1)
	78 org/apache/commons/math3/analysis/interpolation/MicrosphereInterpolatingFunction.brightnessExponent:D (1, 1)
	80 aload_0 (1, 1)
	81 new (1, 1)
	82 java/util/HashMap (1, 1)
	84 dup (1, 1)
	85 aload_2 (1, 1)
	86 arraylength (1, 1)
	87 invokespecial (1, 1)
	88 java/util/HashMap.<init>:(I)V (1, 1)
	90 putfield (1, 1)
	91 org/apache/commons/math3/analysis/interpolation/MicrosphereInterpolatingFunction.samples:Ljava/util/Map; (1, 1)
	93 iconst_0 (2, 4)
	94 istore (2, 4)
	95 #6 (2, 4)
	96 iload (2, 4)
	97 #6 (2, 4)
	98 aload_1 (2, 4)
	99 arraylength (2, 4)
	100 if_icmpge (2, 4)
	101 79 (2, 4)
	103 aload_1 (2, 4)
	104 iload (2, 4)
	105 #6 (2, 4)
	106 aaload (2, 4)
	107 astore (2, 4)
	108 #7 (2, 4)
	109 aload (3, 1)
	110 #7 (3, 1)
	111 ifnonnull (3, 1)
	112 11 (3, 1)
	114 new (3, 1)
	115 org/apache/commons/math3/exception/NullArgumentException (3, 1)
	117 dup (3, 1)
	118 invokespecial (3, 1)
	119 org/apache/commons/math3/exception/NullArgumentException.<init>:()V (3, 1)
	121 athrow (3, 1)
	122 aload (3, 1)
	123 #7 (3, 1)
	124 arraylength (3, 1)
	125 aload_0 (3, 1)
	126 getfield (3, 1)
	127 org/apache/commons/math3/analysis/interpolation/MicrosphereInterpolatingFunction.dimension:I (3, 1)
	129 if_icmpeq (3, 1)
	130 18 (3, 1)
	132 new (3, 1)
	133 org/apache/commons/math3/exception/DimensionMismatchException (3, 1)
	135 dup (3, 1)
	136 aload (3, 1)
	137 #7 (3, 1)
	138 arraylength (3, 1)
	139 aload_0 (3, 1)
	140 getfield (3, 1)
	141 org/apache/commons/math3/analysis/interpolation/MicrosphereInterpolatingFunction.dimension:I (3, 1)
	143 invokespecial (3, 1)
	144 org/apache/commons/math3/exception/DimensionMismatchException.<init>:(II)V (3, 1)
	146 athrow (3, 1)
	147 aload_0 (2, 4)
	148 getfield (2, 4)
	149 org/apache/commons/math3/analysis/interpolation/MicrosphereInterpolatingFunction.samples:Ljava/util/Map; (2, 4)
	151 new (2, 4)
	152 org/apache/commons/math3/linear/ArrayRealVector (2, 4)
	154 dup (2, 4)
	155 aload (2, 4)
	156 #7 (2, 4)
	157 invokespecial (2, 4)
	158 org/apache/commons/math3/linear/ArrayRealVector.<init>:([D)V (2, 4)
	160 aload_2 (2, 4)
	161 iload (2, 4)
	162 #6 (2, 4)
	163 daload (2, 4)
	164 invokestatic (2, 4)
	165 java/lang/Double.valueOf:(D)Ljava/lang/Double; (2, 4)
	167 invokeinterface (2, 4)
	168 java/util/Map.java/util/ArrayList (2, 4)
	170 0 (2, 4)
	172 pop (2, 4)
	173 iinc (2, 4)
	174 #6 (2, 4)
	175 -89 (2, 4)
	176 goto (2, 4)
	177 -80 (2, 4)
	179 aload_0 (1, 1)
	180 new (1, 1)
	181 java/util/ArrayList (1, 1)
	183 dup (1, 1)
	184 iload (1, 1)
	185 #4 (1, 1)
	186 invokespecial (1, 1)
	187 java/util/ArrayList.<init>:(I)V (1, 1)
	189 putfield (1, 1)
	190 org/apache/commons/math3/analysis/interpolation/MicrosphereInterpolatingFunction.microsphere:Ljava/util/List; (1, 1)
	192 iconst_0 (2, 4)
	193 istore (2, 4)
	194 #6 (2, 4)
	195 iload (2, 4)
	196 #6 (2, 4)
	197 iload (2, 4)
	198 #4 (2, 4)
	199 if_icmpge (2, 4)
	200 31 (2, 4)
	202 aload_0 (2, 4)
	203 getfield (2, 4)
	204 org/apache/commons/math3/analysis/interpolation/MicrosphereInterpolatingFunction.microsphere:Ljava/util/List; (2, 4)
	206 new (2, 4)
	207 org/apache/commons/math3/analysis/interpolation/MicrosphereInterpolatingFunction$MicrosphereSurfaceElement (2, 4)
	209 dup (2, 4)
	210 aload (2, 4)
	211 #5 (2, 4)
	212 invokevirtual (2, 4)
	213 org/apache/commons/math3/random/UnitSphereRandomVectorGenerator.nextVector:()[D (2, 4)
	215 invokespecial (2, 4)
	216 org/apache/commons/math3/analysis/interpolation/MicrosphereInterpolatingFunction$MicrosphereSurfaceElement.<init>:([D)V (2, 4)
	218 invokeinterface (2, 4)
	219 java/util/List.iterator:()Ljava/util/Iterator; (2, 4)
	221 0 (2, 4)
	223 pop (2, 4)
	224 iinc (2, 4)
	225 #6 (2, 4)
	226 -89 (2, 4)
	227 goto (2, 4)
	228 -32 (2, 4)
	230 return (0, 0)

Method: value
	0 new (0, 0)
	1 org/apache/commons/math3/linear/ArrayRealVector (0, 0)
	3 dup (0, 0)
	4 aload_1 (0, 0)
	5 invokespecial (0, 0)
	6 org/apache/commons/math3/linear/ArrayRealVector.<init>:([D)V (0, 0)
	8 astore_2 (0, 0)
	9 aload_0 (1, 4)
	10 getfield (1, 4)
	11 org/apache/commons/math3/analysis/interpolation/MicrosphereInterpolatingFunction.microsphere:Ljava/util/List; (1, 4)
	13 invokeinterface (1, 4)
	14 java/util/List.java/util/Iterator (1, 4)
	16 0 (1, 4)
	18 astore_3 (1, 4)
	19 aload_3 (1, 4)
	20 invokeinterface (1, 4)
	21 java/util/Iterator.next:()Ljava/lang/Object; (1, 4)
	23 0 (1, 4)
	25 ifeq (1, 4)
	26 22 (1, 4)
	28 aload_3 (1, 4)
	29 invokeinterface (1, 4)
	30 java/util/Iterator.reset:()V (1, 4)
	32 0 (1, 4)
	34 checkcast (1, 4)
	35 org/apache/commons/math3/analysis/interpolation/MicrosphereInterpolatingFunction$MicrosphereSurfaceElement (1, 4)
	37 astore (1, 4)
	38 #4 (1, 4)
	39 aload (1, 4)
	40 #4 (1, 4)
	41 invokevirtual (1, 4)
	42 org/apache/commons/math3/analysis/interpolation/MicrosphereInterpolatingFunction$MicrosphereSurfaceElement.reset:()V (1, 4)
	44 goto (0, 0)
	45 -25 (0, 0)
	47 aload_0 (1, 4)
	48 getfield (1, 4)
	49 org/apache/commons/math3/analysis/interpolation/MicrosphereInterpolatingFunction.samples:Ljava/util/Map; (1, 4)
	51 invokeinterface (1, 4)
	52 java/util/Map.java/util/Set (1, 4)
	54 0 (1, 4)
	56 invokeinterface (1, 4)
	57 java/util/Set.java/util/Iterator (1, 4)
	59 0 (1, 4)
	61 astore_3 (1, 4)
	62 aload_3 (1, 4)
	63 invokeinterface (1, 4)
	64 java/util/Iterator.next:()Ljava/lang/Object; (1, 4)
	66 0 (1, 4)
	68 ifeq (1, 4)
	69 136 (1, 4)
	71 aload_3 (1, 4)
	72 invokeinterface (1, 4)
	73 java/util/Iterator.reset:()V (1, 4)
	75 0 (1, 4)
	77 checkcast (1, 4)
	78 java/util/Map$Entry (1, 4)
	80 astore (1, 4)
	81 #4 (1, 4)
	82 aload (2, 1)
	83 #4 (2, 1)
	84 invokeinterface (2, 1)
	85 java/util/Map$Entry.org/apache/commons/math3/linear/RealVector (2, 1)
	87 0 (2, 1)
	89 checkcast (2, 1)
	90 org/apache/commons/math3/linear/RealVector (2, 1)
	92 aload_2 (2, 1)
	93 invokevirtual (2, 1)
	94 org/apache/commons/math3/linear/RealVector.subtract:(Lorg/apache/commons/math3/linear/RealVector;)Lorg/apache/commons/math3/linear/RealVector; (2, 1)
	96 astore (2, 1)
	97 #5 (2, 1)
	98 aload (3, 1)
	99 #5 (3, 1)
	100 invokevirtual (3, 1)
	101 org/apache/commons/math3/linear/RealVector.getNorm:()D (3, 1)
	103 dstore (3, 1)
	104 #6 (3, 1)
	105 dload (4, 1)
	106 #6 (4, 1)
	107 invokestatic (4, 1)
	108 org/apache/commons/math3/util/FastMath.abs:(D)D (4, 1)
	110 dconst_1 (4, 1)
	111 invokestatic (4, 1)
	112 org/apache/commons/math3/util/FastMath.ulp:(D)D (4, 1)
	114 dcmpg (4, 1)
	115 ifge (4, 1)
	116 17 (4, 1)
	118 aload (4, 1)
	119 #4 (4, 1)
	120 invokeinterface (4, 1)
	121 java/util/Map$Entry.java/lang/Double (4, 1)
	123 0 (4, 1)
	125 checkcast (4, 1)
	126 java/lang/Double (4, 1)
	128 invokevirtual (4, 1)
	129 java/lang/Double.doubleValue:()D (4, 1)
	131 dreturn (4, 1)
	132 aload_0 (4, 4)
	133 getfield (4, 4)
	134 org/apache/commons/math3/analysis/interpolation/MicrosphereInterpolatingFunction.microsphere:Ljava/util/List; (4, 4)
	136 invokeinterface (4, 4)
	137 java/util/List.java/util/Iterator (4, 4)
	139 0 (4, 4)
	141 astore (4, 4)
	142 #8 (4, 4)
	143 aload (4, 4)
	144 #8 (4, 4)
	145 invokeinterface (4, 4)
	146 java/util/Iterator.next:()Ljava/lang/Object; (4, 4)
	148 0 (4, 4)
	150 ifeq (4, 4)
	151 51 (4, 4)
	153 aload (4, 4)
	154 #8 (4, 4)
	155 invokeinterface (4, 4)
	156 java/util/Iterator.reset:()V (4, 4)
	158 0 (4, 4)
	160 checkcast (4, 4)
	161 org/apache/commons/math3/analysis/interpolation/MicrosphereInterpolatingFunction$MicrosphereSurfaceElement (4, 4)
	163 astore (4, 4)
	164 #9 (4, 4)
	165 dload (5, 1)
	166 #6 (5, 1)
	167 aload_0 (5, 1)
	168 getfield (5, 1)
	169 org/apache/commons/math3/analysis/interpolation/MicrosphereInterpolatingFunction.brightnessExponent:D (5, 1)
	171 dneg (5, 1)
	172 invokestatic (5, 1)
	173 org/apache/commons/math3/util/FastMath.pow:(DD)D (5, 1)
	175 dstore (5, 1)
	176 #10 (5, 1)
	177 aload (6, 1)
	178 #9 (6, 1)
	179 aload_0 (6, 1)
	180 aload (6, 1)
	181 #5 (6, 1)
	182 aload (6, 1)
	183 #9 (6, 1)
	184 invokevirtual (6, 1)
	185 org/apache/commons/math3/analysis/interpolation/MicrosphereInterpolatingFunction$MicrosphereSurfaceElement.normal:()Lorg/apache/commons/math3/linear/RealVector; (6, 1)
	187 invokespecial (6, 1)
	188 org/apache/commons/math3/analysis/interpolation/MicrosphereInterpolatingFunction.cosAngle:(Lorg/apache/commons/math3/linear/RealVector;Lorg/apache/commons/math3/linear/RealVector;)D (6, 1)
	190 dload (6, 1)
	191 #10 (6, 1)
	192 dmul (6, 1)
	193 aload (6, 1)
	194 #4 (6, 1)
	195 invokevirtual (6, 1)
	196 org/apache/commons/math3/analysis/interpolation/MicrosphereInterpolatingFunction$MicrosphereSurfaceElement.store:(DLjava/util/Map$Entry;)V (6, 1)
	198 goto (3, 1)
	199 -55 (3, 1)
	201 goto (0, 0)
	202 -139 (0, 0)
	204 dconst_0 (0, 0)
	205 dstore_3 (0, 0)
	206 dconst_0 (0, 0)
	207 dstore (0, 0)
	208 #5 (0, 0)
	209 aload_0 (1, 4)
	210 getfield (1, 4)
	211 org/apache/commons/math3/analysis/interpolation/MicrosphereInterpolatingFunction.microsphere:Ljava/util/List; (1, 4)
	213 invokeinterface (1, 4)
	214 java/util/List.java/util/Iterator (1, 4)
	216 0 (1, 4)
	218 astore (1, 4)
	219 #7 (1, 4)
	220 aload (1, 4)
	221 #7 (1, 4)
	222 invokeinterface (1, 4)
	223 java/util/Iterator.next:()Ljava/lang/Object; (1, 4)
	225 0 (1, 4)
	227 ifeq (1, 4)
	228 63 (1, 4)
	230 aload (1, 4)
	231 #7 (1, 4)
	232 invokeinterface (1, 4)
	233 java/util/Iterator.reset:()V (1, 4)
	235 0 (1, 4)
	237 checkcast (1, 4)
	238 org/apache/commons/math3/analysis/interpolation/MicrosphereInterpolatingFunction$MicrosphereSurfaceElement (1, 4)
	240 astore (1, 4)
	241 #8 (1, 4)
	242 aload (1, 4)
	243 #8 (1, 4)
	244 invokevirtual (1, 4)
	245 org/apache/commons/math3/analysis/interpolation/MicrosphereInterpolatingFunction$MicrosphereSurfaceElement.illumination:()D (1, 4)
	247 dstore (1, 4)
	248 #9 (1, 4)
	249 aload (1, 4)
	250 #8 (1, 4)
	251 invokevirtual (1, 4)
	252 org/apache/commons/math3/analysis/interpolation/MicrosphereInterpolatingFunction$MicrosphereSurfaceElement.sample:()Ljava/util/Map$Entry; (1, 4)
	254 astore (1, 4)
	255 #11 (1, 4)
	256 aload (2, 1)
	257 #11 (2, 1)
	258 ifnull (2, 1)
	259 29 (2, 1)
	261 dload_3 (2, 1)
	262 dload (2, 1)
	263 #9 (2, 1)
	264 aload (2, 1)
	265 #11 (2, 1)
	266 invokeinterface (2, 1)
	267 java/util/Map$Entry.java/lang/Double (2, 1)
	269 0 (2, 1)
	271 checkcast (2, 1)
	272 java/lang/Double (2, 1)
	274 invokevirtual (2, 1)
	275 java/lang/Double.doubleValue:()D (2, 1)
	277 dmul (2, 1)
	278 dadd (2, 1)
	279 dstore_3 (2, 1)
	280 dload (2, 1)
	281 #5 (2, 1)
	282 dload (2, 1)
	283 #9 (2, 1)
	284 dadd (2, 1)
	285 dstore (2, 1)
	286 #5 (2, 1)
	287 goto (0, 0)
	288 -67 (0, 0)
	290 dload_3 (0, 0)
	291 dload (0, 0)
	292 #5 (0, 0)
	293 ddiv (0, 0)
	294 dreturn (0, 0)

Method: cosAngle
	0 aload_1 (0, 0)
	1 aload_2 (0, 0)
	2 invokevirtual (0, 0)
	3 org/apache/commons/math3/linear/RealVector.dotProduct:(Lorg/apache/commons/math3/linear/RealVector;)D (0, 0)
	5 aload_1 (0, 0)
	6 invokevirtual (0, 0)
	7 org/apache/commons/math3/linear/RealVector.getNorm:()D (0, 0)
	9 aload_2 (0, 0)
	10 invokevirtual (0, 0)
	11 org/apache/commons/math3/linear/RealVector.getNorm:()D (0, 0)
	13 dmul (0, 0)
	14 ddiv (0, 0)
	15 dreturn (0, 0)

