Method: <init>
	0 aload_0 (0, 0)
	1 invokespecial (0, 0)
	2 java/lang/Object.<init>:()V (0, 0)
	4 aload_1 (1, 1)
	5 ifnull (1, 1)
	6 17 (1, 1)
	8 aload_2 (1, 1)
	9 ifnull (1, 1)
	10 13 (1, 1)
	12 aload_3 (1, 1)
	13 ifnull (1, 1)
	14 9 (1, 1)
	16 aload_3 (1, 1)
	17 iconst_0 (1, 1)
	18 aaload (1, 1)
	19 ifnonnull (1, 1)
	20 11 (1, 1)
	22 new (1, 1)
	23 org/apache/commons/math3/exception/NullArgumentException (1, 1)
	25 dup (1, 1)
	26 invokespecial (1, 1)
	27 org/apache/commons/math3/exception/NullArgumentException.<init>:()V (1, 1)
	29 athrow (1, 1)
	30 aload_1 (1, 1)
	31 arraylength (1, 1)
	32 istore (1, 1)
	33 #4 (1, 1)
	34 aload_2 (1, 1)
	35 arraylength (1, 1)
	36 istore (1, 1)
	37 #5 (1, 1)
	38 iload (1, 1)
	39 #4 (1, 1)
	40 ifeq (1, 1)
	41 20 (1, 1)
	43 iload (1, 1)
	44 #5 (1, 1)
	45 ifeq (1, 1)
	46 15 (1, 1)
	48 aload_3 (1, 1)
	49 arraylength (1, 1)
	50 ifeq (1, 1)
	51 10 (1, 1)
	53 aload_3 (1, 1)
	54 iconst_0 (1, 1)
	55 aaload (1, 1)
	56 arraylength (1, 1)
	57 ifne (1, 1)
	58 11 (1, 1)
	60 new (1, 1)
	61 org/apache/commons/math3/exception/NoDataException (1, 1)
	63 dup (1, 1)
	64 invokespecial (1, 1)
	65 org/apache/commons/math3/exception/NoDataException.<init>:()V (1, 1)
	67 athrow (1, 1)
	68 iload (1, 1)
	69 #4 (1, 1)
	70 iconst_5 (1, 1)
	71 if_icmplt (1, 1)
	72 23 (1, 1)
	74 iload (1, 1)
	75 #5 (1, 1)
	76 iconst_5 (1, 1)
	77 if_icmplt (1, 1)
	78 17 (1, 1)
	80 aload_3 (1, 1)
	81 arraylength (1, 1)
	82 iconst_5 (1, 1)
	83 if_icmplt (1, 1)
	84 11 (1, 1)
	86 aload_3 (1, 1)
	87 iconst_0 (1, 1)
	88 aaload (1, 1)
	89 arraylength (1, 1)
	90 iconst_5 (1, 1)
	91 if_icmpge (1, 1)
	92 11 (1, 1)
	94 new (1, 1)
	95 org/apache/commons/math3/exception/InsufficientDataException (1, 1)
	97 dup (1, 1)
	98 invokespecial (1, 1)
	99 org/apache/commons/math3/exception/InsufficientDataException.<init>:()V (1, 1)
	101 athrow (1, 1)
	102 iload (2, 1)
	103 #4 (2, 1)
	104 aload_3 (2, 1)
	105 arraylength (2, 1)
	106 if_icmpeq (2, 1)
	107 15 (2, 1)
	109 new (2, 1)
	110 org/apache/commons/math3/exception/DimensionMismatchException (2, 1)
	112 dup (2, 1)
	113 iload (2, 1)
	114 #4 (2, 1)
	115 aload_3 (2, 1)
	116 arraylength (2, 1)
	117 invokespecial (2, 1)
	118 org/apache/commons/math3/exception/DimensionMismatchException.<init>:(II)V (2, 1)
	120 athrow (2, 1)
	121 iload (2, 1)
	122 #5 (2, 1)
	123 aload_3 (2, 1)
	124 iconst_0 (2, 1)
	125 aaload (2, 1)
	126 arraylength (2, 1)
	127 if_icmpeq (2, 1)
	128 17 (2, 1)
	130 new (2, 1)
	131 org/apache/commons/math3/exception/DimensionMismatchException (2, 1)
	133 dup (2, 1)
	134 iload (2, 1)
	135 #5 (2, 1)
	136 aload_3 (2, 1)
	137 iconst_0 (2, 1)
	138 aaload (2, 1)
	139 arraylength (2, 1)
	140 invokespecial (2, 1)
	141 org/apache/commons/math3/exception/DimensionMismatchException.<init>:(II)V (2, 1)
	143 athrow (2, 1)
	144 aload_1 (1, 1)
	145 invokestatic (1, 1)
	146 org/apache/commons/math3/util/MathArrays.checkOrder:([D)V (1, 1)
	148 aload_2 (1, 1)
	149 invokestatic (1, 1)
	150 org/apache/commons/math3/util/MathArrays.checkOrder:([D)V (1, 1)
	152 aload_0 (1, 1)
	153 aload_1 (1, 1)
	154 invokevirtual (1, 1)
	155 [D.clone:()Ljava/lang/Object; (1, 1)
	157 checkcast (1, 1)
	158 [D (1, 1)
	160 putfield (1, 1)
	161 org/apache/commons/math3/analysis/interpolation/PiecewiseBicubicSplineInterpolatingFunction.xval:[D (1, 1)
	163 aload_0 (1, 1)
	164 aload_2 (1, 1)
	165 invokevirtual (1, 1)
	166 [D.clone:()Ljava/lang/Object; (1, 1)
	168 checkcast (1, 1)
	169 [D (1, 1)
	171 putfield (1, 1)
	172 org/apache/commons/math3/analysis/interpolation/PiecewiseBicubicSplineInterpolatingFunction.yval:[D (1, 1)
	174 aload_0 (1, 1)
	175 aload_3 (1, 1)
	176 invokevirtual (1, 1)
	177 [[D.clone:()Ljava/lang/Object; (1, 1)
	179 checkcast (1, 1)
	180 [[D (1, 1)
	182 putfield (1, 1)
	183 org/apache/commons/math3/analysis/interpolation/PiecewiseBicubicSplineInterpolatingFunction.fval:[[D (1, 1)
	185 return (0, 0)

Method: value
	0 new (0, 0)
	1 org/apache/commons/math3/analysis/interpolation/AkimaSplineInterpolator (0, 0)
	3 dup (0, 0)
	4 invokespecial (0, 0)
	5 org/apache/commons/math3/analysis/interpolation/AkimaSplineInterpolator.<init>:()V (0, 0)
	7 astore (0, 0)
	8 #5 (0, 0)
	9 iconst_2 (0, 0)
	10 istore (0, 0)
	11 #6 (0, 0)
	12 iconst_5 (0, 0)
	13 istore (0, 0)
	14 #7 (0, 0)
	15 aload_0 (0, 0)
	16 dload_1 (0, 0)
	17 aload_0 (0, 0)
	18 getfield (0, 0)
	19 org/apache/commons/math3/analysis/interpolation/PiecewiseBicubicSplineInterpolatingFunction.xval:[D (0, 0)
	21 iconst_2 (0, 0)
	22 iconst_5 (0, 0)
	23 invokespecial (0, 0)
	24 org/apache/commons/math3/analysis/interpolation/PiecewiseBicubicSplineInterpolatingFunction.searchIndex:(D[DII)I (0, 0)
	26 istore (0, 0)
	27 #8 (0, 0)
	28 aload_0 (0, 0)
	29 dload_3 (0, 0)
	30 aload_0 (0, 0)
	31 getfield (0, 0)
	32 org/apache/commons/math3/analysis/interpolation/PiecewiseBicubicSplineInterpolatingFunction.yval:[D (0, 0)
	34 iconst_2 (0, 0)
	35 iconst_5 (0, 0)
	36 invokespecial (0, 0)
	37 org/apache/commons/math3/analysis/interpolation/PiecewiseBicubicSplineInterpolatingFunction.searchIndex:(D[DII)I (0, 0)
	39 istore (0, 0)
	40 #9 (0, 0)
	41 iconst_5 (0, 0)
	42 newarray (0, 0)
	43 7 (0, 0)
	44 astore (0, 0)
	45 #10 (0, 0)
	46 iconst_5 (0, 0)
	47 newarray (0, 0)
	48 7 (0, 0)
	49 astore (0, 0)
	50 #11 (0, 0)
	51 iconst_5 (0, 0)
	52 newarray (0, 0)
	53 7 (0, 0)
	54 astore (0, 0)
	55 #12 (0, 0)
	56 iconst_5 (0, 0)
	57 newarray (0, 0)
	58 7 (0, 0)
	59 astore (0, 0)
	60 #13 (0, 0)
	61 iconst_0 (1, 4)
	62 istore (1, 4)
	63 #14 (1, 4)
	64 iload (1, 4)
	65 #14 (1, 4)
	66 iconst_5 (1, 4)
	67 if_icmpge (1, 4)
	68 39 (1, 4)
	70 aload (1, 4)
	71 #10 (1, 4)
	72 iload (1, 4)
	73 #14 (1, 4)
	74 aload_0 (1, 4)
	75 getfield (1, 4)
	76 org/apache/commons/math3/analysis/interpolation/PiecewiseBicubicSplineInterpolatingFunction.xval:[D (1, 4)
	78 iload (1, 4)
	79 #8 (1, 4)
	80 iload (1, 4)
	81 #14 (1, 4)
	82 iadd (1, 4)
	83 daload (1, 4)
	84 dastore (1, 4)
	85 aload (1, 4)
	86 #11 (1, 4)
	87 iload (1, 4)
	88 #14 (1, 4)
	89 aload_0 (1, 4)
	90 getfield (1, 4)
	91 org/apache/commons/math3/analysis/interpolation/PiecewiseBicubicSplineInterpolatingFunction.yval:[D (1, 4)
	93 iload (1, 4)
	94 #9 (1, 4)
	95 iload (1, 4)
	96 #14 (1, 4)
	97 iadd (1, 4)
	98 daload (1, 4)
	99 dastore (1, 4)
	100 iinc (1, 4)
	101 #14 (1, 4)
	102 -89 (1, 4)
	103 goto (1, 4)
	104 -39 (1, 4)
	106 iconst_0 (1, 4)
	107 istore (1, 4)
	108 #14 (1, 4)
	109 iload (1, 4)
	110 #14 (1, 4)
	111 iconst_5 (1, 4)
	112 if_icmpge (1, 4)
	113 67 (1, 4)
	115 iconst_0 (2, 4)
	116 istore (2, 4)
	117 #15 (2, 4)
	118 iload (2, 4)
	119 #15 (2, 4)
	120 iconst_5 (2, 4)
	121 if_icmpge (2, 4)
	122 30 (2, 4)
	124 aload (2, 4)
	125 #12 (2, 4)
	126 iload (2, 4)
	127 #15 (2, 4)
	128 aload_0 (2, 4)
	129 getfield (2, 4)
	130 org/apache/commons/math3/analysis/interpolation/PiecewiseBicubicSplineInterpolatingFunction.fval:[[D (2, 4)
	132 iload (2, 4)
	133 #8 (2, 4)
	134 iload (2, 4)
	135 #15 (2, 4)
	136 iadd (2, 4)
	137 aaload (2, 4)
	138 iload (2, 4)
	139 #9 (2, 4)
	140 iload (2, 4)
	141 #14 (2, 4)
	142 iadd (2, 4)
	143 daload (2, 4)
	144 dastore (2, 4)
	145 iinc (2, 4)
	146 #15 (2, 4)
	147 -89 (2, 4)
	148 goto (2, 4)
	149 -30 (2, 4)
	151 aload (1, 4)
	152 #5 (1, 4)
	153 aload (1, 4)
	154 #10 (1, 4)
	155 aload (1, 4)
	156 #12 (1, 4)
	157 invokevirtual (1, 4)
	158 org/apache/commons/math3/analysis/interpolation/AkimaSplineInterpolator.interpolate:([D[D)Lorg/apache/commons/math3/analysis/polynomials/PolynomialSplineFunction; (1, 4)
	160 astore (1, 4)
	161 #15 (1, 4)
	162 aload (1, 4)
	163 #13 (1, 4)
	164 iload (1, 4)
	165 #14 (1, 4)
	166 aload (1, 4)
	167 #15 (1, 4)
	168 dload_1 (1, 4)
	169 invokevirtual (1, 4)
	170 org/apache/commons/math3/analysis/polynomials/PolynomialSplineFunction.value:(D)D (1, 4)
	172 dastore (1, 4)
	173 iinc (1, 4)
	174 #14 (1, 4)
	175 -89 (1, 4)
	176 goto (1, 4)
	177 -67 (1, 4)
	179 aload (0, 0)
	180 #5 (0, 0)
	181 aload (0, 0)
	182 #11 (0, 0)
	183 aload (0, 0)
	184 #13 (0, 0)
	185 invokevirtual (0, 0)
	186 org/apache/commons/math3/analysis/interpolation/AkimaSplineInterpolator.interpolate:([D[D)Lorg/apache/commons/math3/analysis/polynomials/PolynomialSplineFunction; (0, 0)
	188 astore (0, 0)
	189 #14 (0, 0)
	190 aload (0, 0)
	191 #14 (0, 0)
	192 dload_3 (0, 0)
	193 invokevirtual (0, 0)
	194 org/apache/commons/math3/analysis/polynomials/PolynomialSplineFunction.value:(D)D (0, 0)
	196 dstore (0, 0)
	197 #15 (0, 0)
	198 dload (0, 0)
	199 #15 (0, 0)
	200 dreturn (0, 0)

Method: isValidPoint
	0 dload_1 (0, 1)
	1 aload_0 (0, 1)
	2 getfield (0, 1)
	3 org/apache/commons/math3/analysis/interpolation/PiecewiseBicubicSplineInterpolatingFunction.xval:[D (0, 1)
	5 iconst_0 (0, 1)
	6 daload (0, 1)
	7 dcmpg (0, 1)
	8 iflt (0, 1)
	9 48 (0, 1)
	11 dload_1 (0, 1)
	12 aload_0 (0, 1)
	13 getfield (0, 1)
	14 org/apache/commons/math3/analysis/interpolation/PiecewiseBicubicSplineInterpolatingFunction.xval:[D (0, 1)
	16 aload_0 (0, 1)
	17 getfield (0, 1)
	18 org/apache/commons/math3/analysis/interpolation/PiecewiseBicubicSplineInterpolatingFunction.xval:[D (0, 1)
	20 arraylength (0, 1)
	21 iconst_1 (0, 1)
	22 isub (0, 1)
	23 daload (0, 1)
	24 dcmpl (0, 1)
	25 ifgt (0, 1)
	26 31 (0, 1)
	28 dload_3 (0, 1)
	29 aload_0 (0, 1)
	30 getfield (0, 1)
	31 org/apache/commons/math3/analysis/interpolation/PiecewiseBicubicSplineInterpolatingFunction.yval:[D (0, 1)
	33 iconst_0 (0, 1)
	34 daload (0, 1)
	35 dcmpg (0, 1)
	36 iflt (0, 1)
	37 20 (0, 1)
	39 dload_3 (0, 1)
	40 aload_0 (0, 1)
	41 getfield (0, 1)
	42 org/apache/commons/math3/analysis/interpolation/PiecewiseBicubicSplineInterpolatingFunction.yval:[D (0, 1)
	44 aload_0 (0, 1)
	45 getfield (0, 1)
	46 org/apache/commons/math3/analysis/interpolation/PiecewiseBicubicSplineInterpolatingFunction.yval:[D (0, 1)
	48 arraylength (0, 1)
	49 iconst_1 (0, 1)
	50 isub (0, 1)
	51 daload (0, 1)
	52 dcmpl (0, 1)
	53 ifle (0, 1)
	54 5 (0, 1)
	56 iconst_0 (0, 1)
	57 ireturn (0, 1)
	58 iconst_1 (1, 2)
	59 ireturn (1, 2)

Method: searchIndex
	0 aload_3 (0, 0)
	1 dload_1 (0, 0)
	2 invokestatic (0, 0)
	3 java/util/Arrays.binarySearch:([DD)I (0, 0)
	5 istore (0, 0)
	6 #6 (0, 0)
	7 iload (1, 1)
	8 #6 (1, 1)
	9 iconst_m1 (1, 1)
	10 if_icmpeq (1, 1)
	11 13 (1, 1)
	13 iload (1, 1)
	14 #6 (1, 1)
	15 aload_3 (1, 1)
	16 arraylength (1, 1)
	17 ineg (1, 1)
	18 iconst_1 (1, 1)
	19 isub (1, 1)
	20 if_icmpne (1, 1)
	21 30 (1, 1)
	23 new (1, 1)
	24 org/apache/commons/math3/exception/OutOfRangeException (1, 1)
	26 dup (1, 1)
	27 dload_1 (1, 1)
	28 invokestatic (1, 1)
	29 java/lang/Double.valueOf:(D)Ljava/lang/Double; (1, 1)
	31 aload_3 (1, 1)
	32 iconst_0 (1, 1)
	33 daload (1, 1)
	34 invokestatic (1, 1)
	35 java/lang/Double.valueOf:(D)Ljava/lang/Double; (1, 1)
	37 aload_3 (1, 1)
	38 aload_3 (1, 1)
	39 arraylength (1, 1)
	40 iconst_1 (1, 1)
	41 isub (1, 1)
	42 daload (1, 1)
	43 invokestatic (1, 1)
	44 java/lang/Double.valueOf:(D)Ljava/lang/Double; (1, 1)
	46 invokespecial (1, 1)
	47 org/apache/commons/math3/exception/OutOfRangeException.<init>:(Ljava/lang/Number;Ljava/lang/Number;Ljava/lang/Number;)V (1, 1)
	49 athrow (1, 1)
	50 iload (1, 1)
	51 #6 (1, 1)
	52 ifge (1, 1)
	53 16 (1, 1)
	55 iload (1, 4)
	56 #6 (1, 4)
	57 ineg (1, 4)
	58 iload (1, 4)
	59 #4 (1, 4)
	60 isub (1, 4)
	61 iconst_1 (1, 4)
	62 isub (1, 4)
	63 istore (1, 4)
	64 #6 (1, 4)
	65 goto (1, 4)
	66 10 (1, 4)
	68 iload (1, 2)
	69 #6 (1, 2)
	70 iload (1, 2)
	71 #4 (1, 2)
	72 isub (1, 2)
	73 istore (1, 2)
	74 #6 (1, 2)
	75 iload (1, 1)
	76 #6 (1, 1)
	77 ifge (1, 1)
	78 6 (1, 1)
	80 iconst_0 (1, 1)
	81 istore (1, 1)
	82 #6 (1, 1)
	83 iload (1, 1)
	84 #6 (1, 1)
	85 iload (1, 1)
	86 #5 (1, 1)
	87 iadd (1, 1)
	88 aload_3 (1, 1)
	89 arraylength (1, 1)
	90 if_icmplt (1, 1)
	91 10 (1, 1)
	93 aload_3 (1, 1)
	94 arraylength (1, 1)
	95 iload (1, 1)
	96 #5 (1, 1)
	97 isub (1, 1)
	98 istore (1, 1)
	99 #6 (1, 1)
	100 iload (0, 0)
	101 #6 (0, 0)
	102 ireturn (0, 0)

