Method: <init>
	0 aload_0 (0, 0)
	1 invokespecial (0, 0)
	4 iload_1 (1, 1)
	5 ifge (1, 1)
	8 new (1, 1)
	11 dup (1, 1)
	12 iload_1 (1, 1)
	13 invokestatic (1, 1)
	16 invokespecial (1, 1)
	19 athrow (1, 1)
	20 iload_2 (1, 1)
	21 ifge (1, 1)
	24 new (1, 1)
	27 dup (1, 1)
	28 iload_2 (1, 1)
	29 invokestatic (1, 1)
	32 invokespecial (1, 1)
	35 athrow (1, 1)
	36 aload_0 (0, 0)
	37 iload_1 (0, 0)
	38 putfield (0, 0)
	41 aload_0 (0, 0)
	42 iload_2 (0, 0)
	43 putfield (0, 0)
	46 ldc2_w (0, 0)
	49 dstore_3 (0, 0)
	50 new (0, 0)
	53 dup (0, 0)
	54 ldc2_w (0, 0)
	57 getstatic (0, 0)
	60 dmul (0, 0)
	61 ldc2_w (0, 0)
	64 getstatic (0, 0)
	67 dmul (0, 0)
	68 invokespecial (0, 0)
	71 astore (0, 0)
	73 aload_0 (0, 0)
	74 new (0, 0)
	77 dup (0, 0)
	78 new (0, 0)
	81 dup (0, 0)
	82 iconst_0 (0, 0)
	83 aload (0, 0)
	85 invokespecial (0, 0)
	88 invokespecial (0, 0)
	91 putfield (0, 0)
	94 aload_0 (0, 0)
	95 new (0, 0)
	98 dup (0, 0)
	99 new (0, 0)
	102 dup (0, 0)
	103 iconst_0 (0, 0)
	104 aload (0, 0)
	106 invokespecial (0, 0)
	109 invokespecial (0, 0)
	112 putfield (0, 0)
	115 return (0, 0)

Method: interpolate
	0 aload_0 (0, 0)
	1 aload_1 (0, 0)
	2 aload_2 (0, 0)
	3 aload_3 (0, 0)
	4 invokevirtual (0, 0)
	7 areturn (0, 0)

