Method: <init>
	0 aload_0 (0, 0)
	1 invokespecial (0, 0)
	2 org/apache/commons/math3/analysis/interpolation/BicubicSplineInterpolator.<init>:()V (0, 0)
	4 iload_1 (1, 1)
	5 ifge (1, 1)
	6 15 (1, 1)
	8 new (1, 1)
	9 org/apache/commons/math3/exception/NotPositiveException (1, 1)
	11 dup (1, 1)
	12 iload_1 (1, 1)
	13 invokestatic (1, 1)
	14 java/lang/Integer.valueOf:(I)Ljava/lang/Integer; (1, 1)
	16 invokespecial (1, 1)
	17 org/apache/commons/math3/exception/NotPositiveException.<init>:(Ljava/lang/Number;)V (1, 1)
	19 athrow (1, 1)
	20 iload_2 (1, 1)
	21 ifge (1, 1)
	22 15 (1, 1)
	24 new (1, 1)
	25 org/apache/commons/math3/exception/NotPositiveException (1, 1)
	27 dup (1, 1)
	28 iload_2 (1, 1)
	29 invokestatic (1, 1)
	30 java/lang/Integer.valueOf:(I)Ljava/lang/Integer; (1, 1)
	32 invokespecial (1, 1)
	33 org/apache/commons/math3/exception/NotPositiveException.<init>:(Ljava/lang/Number;)V (1, 1)
	35 athrow (1, 1)
	36 aload_0 (0, 0)
	37 iload_1 (0, 0)
	38 putfield (0, 0)
	39 org/apache/commons/math3/analysis/interpolation/SmoothingPolynomialBicubicSplineInterpolator.xDegree:I (0, 0)
	41 aload_0 (0, 0)
	42 iload_2 (0, 0)
	43 putfield (0, 0)
	44 org/apache/commons/math3/analysis/interpolation/SmoothingPolynomialBicubicSplineInterpolator.yDegree:I (0, 0)
	46 ldc2_w (0, 0)
	47 100.0 (0, 0)
	49 dstore_3 (0, 0)
	50 new (0, 0)
	51 org/apache/commons/math3/optim/SimpleVectorValueChecker (0, 0)
	53 dup (0, 0)
	54 ldc2_w (0, 0)
	55 100.0 (0, 0)
	57 getstatic (0, 0)
	58 org/apache/commons/math3/util/Precision.EPSILON:D (0, 0)
	60 dmul (0, 0)
	61 ldc2_w (0, 0)
	62 100.0 (0, 0)
	64 getstatic (0, 0)
	65 org/apache/commons/math3/util/Precision.SAFE_MIN:D (0, 0)
	67 dmul (0, 0)
	68 invokespecial (0, 0)
	69 org/apache/commons/math3/optim/SimpleVectorValueChecker.<init>:(DD)V (0, 0)
	71 astore (0, 0)
	72 #5 (0, 0)
	73 aload_0 (0, 0)
	74 new (0, 0)
	75 org/apache/commons/math3/fitting/PolynomialFitter (0, 0)
	77 dup (0, 0)
	78 new (0, 0)
	79 org/apache/commons/math3/optim/nonlinear/vector/jacobian/GaussNewtonOptimizer (0, 0)
	81 dup (0, 0)
	82 iconst_0 (0, 0)
	83 aload (0, 0)
	84 #5 (0, 0)
	85 invokespecial (0, 0)
	86 org/apache/commons/math3/optim/nonlinear/vector/jacobian/GaussNewtonOptimizer.<init>:(ZLorg/apache/commons/math3/optim/ConvergenceChecker;)V (0, 0)
	88 invokespecial (0, 0)
	89 org/apache/commons/math3/fitting/PolynomialFitter.<init>:(Lorg/apache/commons/math3/optim/nonlinear/vector/MultivariateVectorOptimizer;)V (0, 0)
	91 putfield (0, 0)
	92 org/apache/commons/math3/analysis/interpolation/SmoothingPolynomialBicubicSplineInterpolator.xFitter:Lorg/apache/commons/math3/fitting/PolynomialFitter; (0, 0)
	94 aload_0 (0, 0)
	95 new (0, 0)
	96 org/apache/commons/math3/fitting/PolynomialFitter (0, 0)
	98 dup (0, 0)
	99 new (0, 0)
	100 org/apache/commons/math3/optim/nonlinear/vector/jacobian/GaussNewtonOptimizer (0, 0)
	102 dup (0, 0)
	103 iconst_0 (0, 0)
	104 aload (0, 0)
	105 #5 (0, 0)
	106 invokespecial (0, 0)
	107 org/apache/commons/math3/optim/nonlinear/vector/jacobian/GaussNewtonOptimizer.<init>:(ZLorg/apache/commons/math3/optim/ConvergenceChecker;)V (0, 0)
	109 invokespecial (0, 0)
	110 org/apache/commons/math3/fitting/PolynomialFitter.<init>:(Lorg/apache/commons/math3/optim/nonlinear/vector/MultivariateVectorOptimizer;)V (0, 0)
	112 putfield (0, 0)
	113 org/apache/commons/math3/analysis/interpolation/SmoothingPolynomialBicubicSplineInterpolator.yFitter:Lorg/apache/commons/math3/fitting/PolynomialFitter; (0, 0)
	115 return (0, 0)

Method: interpolate
	0 aload_0 (0, 0)
	1 aload_1 (0, 0)
	2 aload_2 (0, 0)
	3 aload_3 (0, 0)
	4 invokevirtual (0, 0)
	5 org/apache/commons/math3/analysis/interpolation/SmoothingPolynomialBicubicSplineInterpolator.interpolate:([D[D[[D)Lorg/apache/commons/math3/analysis/interpolation/BicubicSplineInterpolatingFunction; (0, 0)
	7 areturn (0, 0)

