Method: isValidPoint
	0 dload_1 (0, 1)
	1 aload_0 (0, 1)
	2 getfield (0, 1)
	3 org/apache/commons/math3/analysis/interpolation/TricubicInterpolator$1.val$xval:[D (0, 1)
	5 iconst_1 (0, 1)
	6 daload (0, 1)
	7 dcmpg (0, 1)
	8 iflt (0, 1)
	9 78 (0, 1)
	11 dload_1 (0, 1)
	12 aload_0 (0, 1)
	13 getfield (0, 1)
	14 org/apache/commons/math3/analysis/interpolation/TricubicInterpolator$1.val$xval:[D (0, 1)
	16 aload_0 (0, 1)
	17 getfield (0, 1)
	18 org/apache/commons/math3/analysis/interpolation/TricubicInterpolator$1.val$xval:[D (0, 1)
	20 arraylength (0, 1)
	21 iconst_2 (0, 1)
	22 isub (0, 1)
	23 daload (0, 1)
	24 dcmpl (0, 1)
	25 ifgt (0, 1)
	26 61 (0, 1)
	28 dload_3 (0, 1)
	29 aload_0 (0, 1)
	30 getfield (0, 1)
	31 org/apache/commons/math3/analysis/interpolation/TricubicInterpolator$1.val$yval:[D (0, 1)
	33 iconst_1 (0, 1)
	34 daload (0, 1)
	35 dcmpg (0, 1)
	36 iflt (0, 1)
	37 50 (0, 1)
	39 dload_3 (0, 1)
	40 aload_0 (0, 1)
	41 getfield (0, 1)
	42 org/apache/commons/math3/analysis/interpolation/TricubicInterpolator$1.val$yval:[D (0, 1)
	44 aload_0 (0, 1)
	45 getfield (0, 1)
	46 org/apache/commons/math3/analysis/interpolation/TricubicInterpolator$1.val$yval:[D (0, 1)
	48 arraylength (0, 1)
	49 iconst_2 (0, 1)
	50 isub (0, 1)
	51 daload (0, 1)
	52 dcmpl (0, 1)
	53 ifgt (0, 1)
	54 33 (0, 1)
	56 dload (0, 1)
	57 #5 (0, 1)
	58 aload_0 (0, 1)
	59 getfield (0, 1)
	60 org/apache/commons/math3/analysis/interpolation/TricubicInterpolator$1.val$zval:[D (0, 1)
	62 iconst_1 (0, 1)
	63 daload (0, 1)
	64 dcmpg (0, 1)
	65 iflt (0, 1)
	66 21 (0, 1)
	68 dload (0, 1)
	69 #5 (0, 1)
	70 aload_0 (0, 1)
	71 getfield (0, 1)
	72 org/apache/commons/math3/analysis/interpolation/TricubicInterpolator$1.val$zval:[D (0, 1)
	74 aload_0 (0, 1)
	75 getfield (0, 1)
	76 org/apache/commons/math3/analysis/interpolation/TricubicInterpolator$1.val$zval:[D (0, 1)
	78 arraylength (0, 1)
	79 iconst_2 (0, 1)
	80 isub (0, 1)
	81 daload (0, 1)
	82 dcmpl (0, 1)
	83 ifle (0, 1)
	84 5 (0, 1)
	86 iconst_0 (0, 1)
	87 ireturn (0, 1)
	88 iconst_1 (1, 2)
	89 ireturn (1, 2)

