Method: interpolate
	0 aload_0 (0, 0)
	1 aload_1 (0, 0)
	2 aload_2 (0, 0)
	3 aload_3 (0, 0)
	4 aload (0, 0)
	6 invokevirtual (0, 0)
	9 areturn (0, 0)

Method: nextIndex
	0 iload_1 (0, 0)
	1 iconst_1 (0, 0)
	2 iadd (0, 0)
	3 istore_3 (0, 0)
	4 iload_3 (0, 0)
	5 iload_2 (0, 0)
	6 if_icmpge (0, 0)
	9 iload_3 (0, 0)
	10 goto (0, 0)
	13 iload_3 (0, 0)
	14 iconst_1 (0, 0)
	15 isub (0, 0)
	16 ireturn (0, 0)

Method: previousIndex
	0 iload_1 (0, 0)
	1 iconst_1 (0, 0)
	2 isub (0, 0)
	3 istore_2 (0, 0)
	4 iload_2 (0, 0)
	5 iflt (0, 0)
	8 iload_2 (0, 0)
	9 goto (0, 0)
	12 iconst_0 (0, 0)
	13 ireturn (0, 0)

