Method: value
	0 aload_0 (0, 0)
	1 getfield (0, 0)
	2 org/apache/commons/math3/analysis/interpolation/UnivariatePeriodicInterpolator$1.val$f:Lorg/apache/commons/math3/analysis/UnivariateFunction; (0, 0)
	4 dload_1 (0, 0)
	5 aload_0 (0, 0)
	6 getfield (0, 0)
	7 org/apache/commons/math3/analysis/interpolation/UnivariatePeriodicInterpolator$1.this$0:Lorg/apache/commons/math3/analysis/interpolation/UnivariatePeriodicInterpolator; (0, 0)
	9 invokestatic (0, 0)
	10 org/apache/commons/math3/analysis/interpolation/UnivariatePeriodicInterpolator.access$000:(Lorg/apache/commons/math3/analysis/interpolation/UnivariatePeriodicInterpolator;)D (0, 0)
	12 aload_0 (0, 0)
	13 getfield (0, 0)
	14 org/apache/commons/math3/analysis/interpolation/UnivariatePeriodicInterpolator$1.val$offset:D (0, 0)
	16 invokestatic (0, 0)
	17 org/apache/commons/math3/util/MathUtils.reduce:(DDD)D (0, 0)
	19 invokeinterface (0, 0)
	20 org/apache/commons/math3/analysis/UnivariateFunction.org/apache/commons/math3/analysis/interpolation/UnivariatePeriodicInterpolator$1 (0, 0)
	22 0 (0, 0)
	24 dreturn (0, 0)

