Method: <init>
	0 aload_0 (0, 0)
	1 aload_1 (0, 0)
	2 dload_2 (0, 0)
	3 iconst_5 (0, 0)
	4 invokespecial (0, 0)
	5 org/apache/commons/math3/analysis/interpolation/UnivariatePeriodicInterpolator.<init>:(Lorg/apache/commons/math3/analysis/interpolation/UnivariateInterpolator;DI)V (0, 0)
	7 return (0, 0)

Method: interpolate
	0 aload_1 (1, 1)
	1 arraylength (1, 1)
	2 aload_0 (1, 1)
	3 getfield (1, 1)
	4 org/apache/commons/math3/analysis/interpolation/UnivariatePeriodicInterpolator.extend:I (1, 1)
	6 if_icmpge (1, 1)
	7 24 (1, 1)
	9 new (1, 1)
	10 org/apache/commons/math3/exception/NumberIsTooSmallException (1, 1)
	12 dup (1, 1)
	13 aload_1 (1, 1)
	14 arraylength (1, 1)
	15 invokestatic (1, 1)
	16 java/lang/Integer.valueOf:(I)Ljava/lang/Integer; (1, 1)
	18 aload_0 (1, 1)
	19 getfield (1, 1)
	20 org/apache/commons/math3/analysis/interpolation/UnivariatePeriodicInterpolator.extend:I (1, 1)
	22 invokestatic (1, 1)
	23 java/lang/Integer.valueOf:(I)Ljava/lang/Integer; (1, 1)
	25 iconst_1 (1, 1)
	26 invokespecial (1, 1)
	27 org/apache/commons/math3/exception/NumberIsTooSmallException.<init>:(Ljava/lang/Number;Ljava/lang/Number;Z)V (1, 1)
	29 athrow (1, 1)
	30 aload_1 (0, 0)
	31 invokestatic (0, 0)
	32 org/apache/commons/math3/util/MathArrays.checkOrder:([D)V (0, 0)
	34 aload_1 (0, 0)
	35 iconst_0 (0, 0)
	36 daload (0, 0)
	37 dstore_3 (0, 0)
	38 aload_1 (0, 0)
	39 arraylength (0, 0)
	40 aload_0 (0, 0)
	41 getfield (0, 0)
	42 org/apache/commons/math3/analysis/interpolation/UnivariatePeriodicInterpolator.extend:I (0, 0)
	44 iconst_2 (0, 0)
	45 imul (0, 0)
	46 iadd (0, 0)
	47 istore (0, 0)
	48 #5 (0, 0)
	49 iload (0, 0)
	50 #5 (0, 0)
	51 newarray (0, 0)
	52 7 (0, 0)
	53 astore (0, 0)
	54 #6 (0, 0)
	55 iload (0, 0)
	56 #5 (0, 0)
	57 newarray (0, 0)
	58 7 (0, 0)
	59 astore (0, 0)
	60 #7 (0, 0)
	61 iconst_0 (1, 4)
	62 istore (1, 4)
	63 #8 (1, 4)
	64 iload (1, 4)
	65 #8 (1, 4)
	66 aload_1 (1, 4)
	67 arraylength (1, 4)
	68 if_icmpge (1, 4)
	69 44 (1, 4)
	71 iload (1, 4)
	72 #8 (1, 4)
	73 aload_0 (1, 4)
	74 getfield (1, 4)
	75 org/apache/commons/math3/analysis/interpolation/UnivariatePeriodicInterpolator.extend:I (1, 4)
	77 iadd (1, 4)
	78 istore (1, 4)
	79 #9 (1, 4)
	80 aload (1, 4)
	81 #6 (1, 4)
	82 iload (1, 4)
	83 #9 (1, 4)
	84 aload_1 (1, 4)
	85 iload (1, 4)
	86 #8 (1, 4)
	87 daload (1, 4)
	88 aload_0 (1, 4)
	89 getfield (1, 4)
	90 org/apache/commons/math3/analysis/interpolation/UnivariatePeriodicInterpolator.period:D (1, 4)
	92 dload_3 (1, 4)
	93 invokestatic (1, 4)
	94 org/apache/commons/math3/util/MathUtils.reduce:(DDD)D (1, 4)
	96 dastore (1, 4)
	97 aload (1, 4)
	98 #7 (1, 4)
	99 iload (1, 4)
	100 #9 (1, 4)
	101 aload_2 (1, 4)
	102 iload (1, 4)
	103 #8 (1, 4)
	104 daload (1, 4)
	105 dastore (1, 4)
	106 iinc (1, 4)
	107 #8 (1, 4)
	108 -89 (1, 4)
	109 goto (1, 4)
	110 -45 (1, 4)
	112 iconst_0 (1, 4)
	113 istore (1, 4)
	114 #8 (1, 4)
	115 iload (1, 4)
	116 #8 (1, 4)
	117 aload_0 (1, 4)
	118 getfield (1, 4)
	119 org/apache/commons/math3/analysis/interpolation/UnivariatePeriodicInterpolator.extend:I (1, 4)
	121 if_icmpge (1, 4)
	122 95 (1, 4)
	124 aload_1 (1, 4)
	125 arraylength (1, 4)
	126 aload_0 (1, 4)
	127 getfield (1, 4)
	128 org/apache/commons/math3/analysis/interpolation/UnivariatePeriodicInterpolator.extend:I (1, 4)
	130 isub (1, 4)
	131 iload (1, 4)
	132 #8 (1, 4)
	133 iadd (1, 4)
	134 istore (1, 4)
	135 #9 (1, 4)
	136 aload (1, 4)
	137 #6 (1, 4)
	138 iload (1, 4)
	139 #8 (1, 4)
	140 aload_1 (1, 4)
	141 iload (1, 4)
	142 #9 (1, 4)
	143 daload (1, 4)
	144 aload_0 (1, 4)
	145 getfield (1, 4)
	146 org/apache/commons/math3/analysis/interpolation/UnivariatePeriodicInterpolator.period:D (1, 4)
	148 dload_3 (1, 4)
	149 invokestatic (1, 4)
	150 org/apache/commons/math3/util/MathUtils.reduce:(DDD)D (1, 4)
	152 aload_0 (1, 4)
	153 getfield (1, 4)
	154 org/apache/commons/math3/analysis/interpolation/UnivariatePeriodicInterpolator.period:D (1, 4)
	156 dsub (1, 4)
	157 dastore (1, 4)
	158 aload (1, 4)
	159 #7 (1, 4)
	160 iload (1, 4)
	161 #8 (1, 4)
	162 aload_2 (1, 4)
	163 iload (1, 4)
	164 #9 (1, 4)
	165 daload (1, 4)
	166 dastore (1, 4)
	167 iload (1, 4)
	168 #5 (1, 4)
	169 aload_0 (1, 4)
	170 getfield (1, 4)
	171 org/apache/commons/math3/analysis/interpolation/UnivariatePeriodicInterpolator.extend:I (1, 4)
	173 isub (1, 4)
	174 iload (1, 4)
	175 #8 (1, 4)
	176 iadd (1, 4)
	177 istore (1, 4)
	178 #9 (1, 4)
	179 aload (1, 4)
	180 #6 (1, 4)
	181 iload (1, 4)
	182 #9 (1, 4)
	183 aload_1 (1, 4)
	184 iload (1, 4)
	185 #8 (1, 4)
	186 daload (1, 4)
	187 aload_0 (1, 4)
	188 getfield (1, 4)
	189 org/apache/commons/math3/analysis/interpolation/UnivariatePeriodicInterpolator.period:D (1, 4)
	191 dload_3 (1, 4)
	192 invokestatic (1, 4)
	193 org/apache/commons/math3/util/MathUtils.reduce:(DDD)D (1, 4)
	195 aload_0 (1, 4)
	196 getfield (1, 4)
	197 org/apache/commons/math3/analysis/interpolation/UnivariatePeriodicInterpolator.period:D (1, 4)
	199 dadd (1, 4)
	200 dastore (1, 4)
	201 aload (1, 4)
	202 #7 (1, 4)
	203 iload (1, 4)
	204 #9 (1, 4)
	205 aload_2 (1, 4)
	206 iload (1, 4)
	207 #8 (1, 4)
	208 daload (1, 4)
	209 dastore (1, 4)
	210 iinc (1, 4)
	211 #8 (1, 4)
	212 -89 (1, 4)
	213 goto (1, 4)
	214 -98 (1, 4)
	216 aload (0, 0)
	217 #6 (0, 0)
	218 iconst_1 (0, 0)
	219 anewarray (0, 0)
	220 [D (0, 0)
	222 dup (0, 0)
	223 iconst_0 (0, 0)
	224 aload (0, 0)
	225 #7 (0, 0)
	226 aastore (0, 0)
	227 invokestatic (0, 0)
	228 org/apache/commons/math3/util/MathArrays.sortInPlace:([D[[D)V (0, 0)
	230 aload_0 (0, 0)
	231 getfield (0, 0)
	232 org/apache/commons/math3/analysis/interpolation/UnivariatePeriodicInterpolator.interpolator:Lorg/apache/commons/math3/analysis/interpolation/UnivariateInterpolator; (0, 0)
	234 aload (0, 0)
	235 #6 (0, 0)
	236 aload (0, 0)
	237 #7 (0, 0)
	238 invokeinterface (0, 0)
	239 org/apache/commons/math3/analysis/interpolation/UnivariateInterpolator.org/apache/commons/math3/analysis/interpolation/UnivariatePeriodicInterpolator$1 (0, 0)
	241 0 (0, 0)
	243 astore (0, 0)
	244 #8 (0, 0)
	245 new (0, 0)
	246 org/apache/commons/math3/analysis/interpolation/UnivariatePeriodicInterpolator$1 (0, 0)
	248 dup (0, 0)
	249 aload_0 (0, 0)
	250 aload (0, 0)
	251 #8 (0, 0)
	252 dload_3 (0, 0)
	253 invokespecial (0, 0)
	254 org/apache/commons/math3/analysis/interpolation/UnivariatePeriodicInterpolator$1.<init>:(Lorg/apache/commons/math3/analysis/interpolation/UnivariatePeriodicInterpolator;Lorg/apache/commons/math3/analysis/UnivariateFunction;D)V (0, 0)
	256 areturn (0, 0)

Method: access$000
	0 aload_0 (0, 0)
	1 getfield (0, 0)
	2 org/apache/commons/math3/analysis/interpolation/UnivariatePeriodicInterpolator.period:D (0, 0)
	4 dreturn (0, 0)

