Method: <init>
	0 aload_0 (0, 0)
	1 dload_1 (0, 0)
	2 dload_3 (0, 0)
	3 aconst_null (0, 0)
	4 invokespecial (0, 0)
	5 org/apache/commons/math3/optimization/univariate/BrentOptimizer.<init>:(DDLorg/apache/commons/math3/optimization/ConvergenceChecker;)V (0, 0)
	7 return (0, 0)

Method: doOptimize
	0 aload_0 (0, 0)
	1 invokevirtual (0, 0)
	2 org/apache/commons/math3/optimization/univariate/BrentOptimizer.getGoalType:()Lorg/apache/commons/math3/optimization/GoalType; (0, 0)
	4 getstatic (0, 0)
	5 org/apache/commons/math3/optimization/GoalType.MINIMIZE:Lorg/apache/commons/math3/optimization/GoalType; (0, 0)
	7 if_acmpne (0, 0)
	8 7 (0, 0)
	10 iconst_1 (0, 0)
	11 goto (0, 0)
	12 4 (0, 0)
	14 iconst_0 (0, 0)
	15 istore_1 (0, 0)
	16 aload_0 (0, 0)
	17 invokevirtual (0, 0)
	18 org/apache/commons/math3/optimization/univariate/BrentOptimizer.getMin:()D (0, 0)
	20 dstore_2 (0, 0)
	21 aload_0 (0, 0)
	22 invokevirtual (0, 0)
	23 org/apache/commons/math3/optimization/univariate/BrentOptimizer.getStartValue:()D (0, 0)
	25 dstore (0, 0)
	26 #4 (0, 0)
	27 aload_0 (0, 0)
	28 invokevirtual (0, 0)
	29 org/apache/commons/math3/optimization/univariate/BrentOptimizer.getMax:()D (0, 0)
	31 dstore (0, 0)
	32 #6 (0, 0)
	33 aload_0 (0, 0)
	34 invokevirtual (0, 0)
	35 org/apache/commons/math3/optimization/univariate/BrentOptimizer.getConvergenceChecker:()Lorg/apache/commons/math3/optimization/ConvergenceChecker; (0, 0)
	37 astore (0, 0)
	38 #8 (0, 0)
	39 dload_2 (1, 1)
	40 dload (1, 1)
	41 #6 (1, 1)
	42 dcmpg (1, 1)
	43 ifge (1, 1)
	44 13 (1, 1)
	46 dload_2 (1, 1)
	47 dstore (1, 1)
	48 #9 (1, 1)
	49 dload (1, 1)
	50 #6 (1, 1)
	51 dstore (1, 1)
	52 #11 (1, 1)
	53 goto (1, 1)
	54 10 (1, 1)
	56 dload (1, 2)
	57 #6 (1, 2)
	58 dstore (1, 2)
	59 #9 (1, 2)
	60 dload_2 (1, 2)
	61 dstore (1, 2)
	62 #11 (1, 2)
	63 dload (0, 0)
	64 #4 (0, 0)
	65 dstore (0, 0)
	66 #13 (0, 0)
	67 dload (0, 0)
	68 #13 (0, 0)
	69 dstore (0, 0)
	70 #15 (0, 0)
	71 dload (0, 0)
	72 #13 (0, 0)
	73 dstore (0, 0)
	74 #17 (0, 0)
	75 dconst_0 (0, 0)
	76 dstore (0, 0)
	77 #19 (0, 0)
	78 dconst_0 (0, 0)
	79 dstore (0, 0)
	80 #21 (0, 0)
	81 aload_0 (0, 0)
	82 dload (0, 0)
	83 #13 (0, 0)
	84 invokevirtual (0, 0)
	85 org/apache/commons/math3/optimization/univariate/BrentOptimizer.computeObjectiveValue:(D)D (0, 0)
	87 dstore (0, 0)
	88 #23 (0, 0)
	89 iload_1 (1, 1)
	90 ifne (1, 1)
	91 8 (1, 1)
	93 dload (1, 1)
	94 #23 (1, 1)
	95 dneg (1, 1)
	96 dstore (1, 1)
	97 #23 (1, 1)
	98 dload (0, 0)
	99 #23 (0, 0)
	100 dstore (0, 0)
	101 #25 (0, 0)
	102 dload (0, 0)
	103 #23 (0, 0)
	104 dstore (0, 0)
	105 #27 (0, 0)
	106 aconst_null (0, 0)
	107 astore (0, 0)
	108 #29 (0, 0)
	109 new (0, 0)
	110 org/apache/commons/math3/optimization/univariate/UnivariatePointValuePair (0, 0)
	112 dup (0, 0)
	113 dload (0, 0)
	114 #13 (0, 0)
	115 iload_1 (0, 0)
	116 ifeq (0, 0)
	117 8 (0, 0)
	119 dload (0, 0)
	120 #23 (0, 0)
	121 goto (0, 0)
	122 6 (0, 0)
	124 dload (0, 0)
	125 #23 (0, 0)
	126 dneg (0, 0)
	127 invokespecial (0, 0)
	128 org/apache/commons/math3/optimization/univariate/UnivariatePointValuePair.<init>:(DD)V (0, 0)
	130 astore (0, 0)
	131 #30 (0, 0)
	132 aload (0, 0)
	133 #30 (0, 0)
	134 astore (0, 0)
	135 #31 (0, 0)
	136 iconst_0 (0, 0)
	137 istore (0, 0)
	138 #32 (0, 0)
	139 ldc2_w (1, 3)
	140 0.5 (1, 3)
	142 dload (1, 3)
	143 #9 (1, 3)
	144 dload (1, 3)
	145 #11 (1, 3)
	146 dadd (1, 3)
	147 dmul (1, 3)
	148 dstore (1, 3)
	149 #33 (1, 3)
	150 aload_0 (1, 3)
	151 getfield (1, 3)
	152 org/apache/commons/math3/optimization/univariate/BrentOptimizer.relativeThreshold:D (1, 3)
	154 dload (1, 3)
	155 #13 (1, 3)
	156 invokestatic (1, 3)
	157 org/apache/commons/math3/util/FastMath.abs:(D)D (1, 3)
	159 dmul (1, 3)
	160 aload_0 (1, 3)
	161 getfield (1, 3)
	162 org/apache/commons/math3/optimization/univariate/BrentOptimizer.absoluteThreshold:D (1, 3)
	164 dadd (1, 3)
	165 dstore (1, 3)
	166 #35 (1, 3)
	167 ldc2_w (1, 3)
	168 2.0 (1, 3)
	170 dload (1, 3)
	171 #35 (1, 3)
	172 dmul (1, 3)
	173 dstore (1, 3)
	174 #37 (1, 3)
	175 dload (1, 3)
	176 #13 (1, 3)
	177 dload (1, 3)
	178 #33 (1, 3)
	179 dsub (1, 3)
	180 invokestatic (1, 3)
	181 org/apache/commons/math3/util/FastMath.abs:(D)D (1, 3)
	183 dload (1, 3)
	184 #37 (1, 3)
	185 ldc2_w (1, 3)
	186 0.5 (1, 3)
	188 dload (1, 3)
	189 #11 (1, 3)
	190 dload (1, 3)
	191 #9 (1, 3)
	192 dsub (1, 3)
	193 dmul (1, 3)
	194 dsub (1, 3)
	195 dcmpg (1, 3)
	196 ifgt (1, 3)
	197 7 (1, 3)
	199 iconst_1 (1, 3)
	200 goto (1, 3)
	201 4 (1, 3)
	203 iconst_0 (1, 3)
	204 istore (1, 3)
	205 #39 (1, 3)
	206 iload (2, 1)
	207 #39 (2, 1)
	208 ifne (2, 1)
	209 567 (2, 1)
	211 dconst_0 (2, 1)
	212 dstore (2, 1)
	213 #40 (2, 1)
	214 dconst_0 (2, 1)
	215 dstore (2, 1)
	216 #42 (2, 1)
	217 dconst_0 (2, 1)
	218 dstore (2, 1)
	219 #44 (2, 1)
	220 dconst_0 (2, 1)
	221 dstore (2, 1)
	222 #46 (2, 1)
	223 dload (3, 1)
	224 #21 (3, 1)
	225 invokestatic (3, 1)
	226 org/apache/commons/math3/util/FastMath.abs:(D)D (3, 1)
	228 dload (3, 1)
	229 #35 (3, 1)
	230 dcmpl (3, 1)
	231 ifle (3, 1)
	232 231 (3, 1)
	234 dload (3, 1)
	235 #13 (3, 1)
	236 dload (3, 1)
	237 #17 (3, 1)
	238 dsub (3, 1)
	239 dload (3, 1)
	240 #23 (3, 1)
	241 dload (3, 1)
	242 #25 (3, 1)
	243 dsub (3, 1)
	244 dmul (3, 1)
	245 dstore (3, 1)
	246 #44 (3, 1)
	247 dload (3, 1)
	248 #13 (3, 1)
	249 dload (3, 1)
	250 #15 (3, 1)
	251 dsub (3, 1)
	252 dload (3, 1)
	253 #23 (3, 1)
	254 dload (3, 1)
	255 #27 (3, 1)
	256 dsub (3, 1)
	257 dmul (3, 1)
	258 dstore (3, 1)
	259 #42 (3, 1)
	260 dload (3, 1)
	261 #13 (3, 1)
	262 dload (3, 1)
	263 #15 (3, 1)
	264 dsub (3, 1)
	265 dload (3, 1)
	266 #42 (3, 1)
	267 dmul (3, 1)
	268 dload (3, 1)
	269 #13 (3, 1)
	270 dload (3, 1)
	271 #17 (3, 1)
	272 dsub (3, 1)
	273 dload (3, 1)
	274 #44 (3, 1)
	275 dmul (3, 1)
	276 dsub (3, 1)
	277 dstore (3, 1)
	278 #40 (3, 1)
	279 ldc2_w (3, 1)
	280 2.0 (3, 1)
	282 dload (3, 1)
	283 #42 (3, 1)
	284 dload (3, 1)
	285 #44 (3, 1)
	286 dsub (3, 1)
	287 dmul (3, 1)
	288 dstore (3, 1)
	289 #42 (3, 1)
	290 dload (4, 1)
	291 #42 (4, 1)
	292 dconst_0 (4, 1)
	293 dcmpl (4, 1)
	294 ifle (4, 1)
	295 11 (4, 1)
	297 dload (4, 1)
	298 #40 (4, 1)
	299 dneg (4, 1)
	300 dstore (4, 1)
	301 #40 (4, 1)
	302 goto (4, 1)
	303 8 (4, 1)
	305 dload (4, 2)
	306 #42 (4, 2)
	307 dneg (4, 2)
	308 dstore (4, 2)
	309 #42 (4, 2)
	310 dload (3, 1)
	311 #21 (3, 1)
	312 dstore (3, 1)
	313 #44 (3, 1)
	314 dload (3, 1)
	315 #19 (3, 1)
	316 dstore (3, 1)
	317 #21 (3, 1)
	318 dload (3, 1)
	319 #40 (3, 1)
	320 dload (3, 1)
	321 #42 (3, 1)
	322 dload (3, 1)
	323 #9 (3, 1)
	324 dload (3, 1)
	325 #13 (3, 1)
	326 dsub (3, 1)
	327 dmul (3, 1)
	328 dcmpl (3, 1)
	329 ifle (3, 1)
	330 97 (3, 1)
	332 dload (3, 1)
	333 #40 (3, 1)
	334 dload (3, 1)
	335 #42 (3, 1)
	336 dload (3, 1)
	337 #11 (3, 1)
	338 dload (3, 1)
	339 #13 (3, 1)
	340 dsub (3, 1)
	341 dmul (3, 1)
	342 dcmpg (3, 1)
	343 ifge (3, 1)
	344 83 (3, 1)
	346 dload (3, 1)
	347 #40 (3, 1)
	348 invokestatic (3, 1)
	349 org/apache/commons/math3/util/FastMath.abs:(D)D (3, 1)
	351 ldc2_w (3, 1)
	352 0.5 (3, 1)
	354 dload (3, 1)
	355 #42 (3, 1)
	356 dmul (3, 1)
	357 dload (3, 1)
	358 #44 (3, 1)
	359 dmul (3, 1)
	360 invokestatic (3, 1)
	361 org/apache/commons/math3/util/FastMath.abs:(D)D (3, 1)
	363 dcmpg (3, 1)
	364 ifge (3, 1)
	365 62 (3, 1)
	367 dload (3, 1)
	368 #40 (3, 1)
	369 dload (3, 1)
	370 #42 (3, 1)
	371 ddiv (3, 1)
	372 dstore (3, 1)
	373 #19 (3, 1)
	374 dload (3, 1)
	375 #13 (3, 1)
	376 dload (3, 1)
	377 #19 (3, 1)
	378 dadd (3, 1)
	379 dstore (3, 1)
	380 #46 (3, 1)
	381 dload (5, 1)
	382 #46 (5, 1)
	383 dload (5, 1)
	384 #9 (5, 1)
	385 dsub (5, 1)
	386 dload (5, 1)
	387 #37 (5, 1)
	388 dcmpg (5, 1)
	389 iflt (5, 1)
	390 14 (5, 1)
	392 dload (5, 1)
	393 #11 (5, 1)
	394 dload (5, 1)
	395 #46 (5, 1)
	396 dsub (5, 1)
	397 dload (5, 1)
	398 #37 (5, 1)
	399 dcmpg (5, 1)
	400 ifge (5, 1)
	401 95 (5, 1)
	403 dload (6, 1)
	404 #13 (6, 1)
	405 dload (6, 1)
	406 #33 (6, 1)
	407 dcmpg (6, 1)
	408 ifgt (6, 1)
	409 10 (6, 1)
	411 dload (6, 1)
	412 #35 (6, 1)
	413 dstore (6, 1)
	414 #19 (6, 1)
	415 goto (6, 1)
	416 80 (6, 1)
	418 dload (6, 2)
	419 #35 (6, 2)
	420 dneg (6, 2)
	421 dstore (6, 2)
	422 #19 (6, 2)
	423 goto (6, 2)
	424 72 (6, 2)
	426 dload (5, 1)
	427 #13 (5, 1)
	428 dload (5, 1)
	429 #33 (5, 1)
	430 dcmpg (5, 1)
	431 ifge (5, 1)
	432 13 (5, 1)
	434 dload (5, 1)
	435 #11 (5, 1)
	436 dload (5, 1)
	437 #13 (5, 1)
	438 dsub (5, 1)
	439 dstore (5, 1)
	440 #21 (5, 1)
	441 goto (5, 1)
	442 10 (5, 1)
	444 dload (5, 2)
	445 #9 (5, 2)
	446 dload (5, 2)
	447 #13 (5, 2)
	448 dsub (5, 2)
	449 dstore (5, 2)
	450 #21 (5, 2)
	451 getstatic (4, 2)
	452 org/apache/commons/math3/optimization/univariate/BrentOptimizer.GOLDEN_SECTION:D (4, 2)
	454 dload (4, 2)
	455 #21 (4, 2)
	456 dmul (4, 2)
	457 dstore (4, 2)
	458 #19 (4, 2)
	459 goto (4, 2)
	460 36 (4, 2)
	462 dload (4, 1)
	463 #13 (4, 1)
	464 dload (4, 1)
	465 #33 (4, 1)
	466 dcmpg (4, 1)
	467 ifge (4, 1)
	468 13 (4, 1)
	470 dload (4, 1)
	471 #11 (4, 1)
	472 dload (4, 1)
	473 #13 (4, 1)
	474 dsub (4, 1)
	475 dstore (4, 1)
	476 #21 (4, 1)
	477 goto (4, 1)
	478 10 (4, 1)
	480 dload (4, 2)
	481 #9 (4, 2)
	482 dload (4, 2)
	483 #13 (4, 2)
	484 dsub (4, 2)
	485 dstore (4, 2)
	486 #21 (4, 2)
	487 getstatic (3, 2)
	488 org/apache/commons/math3/optimization/univariate/BrentOptimizer.GOLDEN_SECTION:D (3, 2)
	490 dload (3, 2)
	491 #21 (3, 2)
	492 dmul (3, 2)
	493 dstore (3, 2)
	494 #19 (3, 2)
	495 dload (3, 1)
	496 #19 (3, 1)
	497 invokestatic (3, 1)
	498 org/apache/commons/math3/util/FastMath.abs:(D)D (3, 1)
	500 dload (3, 1)
	501 #35 (3, 1)
	502 dcmpg (3, 1)
	503 ifge (3, 1)
	504 30 (3, 1)
	506 dload (4, 1)
	507 #19 (4, 1)
	508 dconst_0 (4, 1)
	509 dcmpl (4, 1)
	510 iflt (4, 1)
	511 13 (4, 1)
	513 dload (4, 1)
	514 #13 (4, 1)
	515 dload (4, 1)
	516 #35 (4, 1)
	517 dadd (4, 1)
	518 dstore (4, 1)
	519 #46 (4, 1)
	520 goto (4, 1)
	521 20 (4, 1)
	523 dload (4, 2)
	524 #13 (4, 2)
	525 dload (4, 2)
	526 #35 (4, 2)
	527 dsub (4, 2)
	528 dstore (4, 2)
	529 #46 (4, 2)
	530 goto (4, 2)
	531 10 (4, 2)
	533 dload (3, 2)
	534 #13 (3, 2)
	535 dload (3, 2)
	536 #19 (3, 2)
	537 dadd (3, 2)
	538 dstore (3, 2)
	539 #46 (3, 2)
	540 aload_0 (2, 1)
	541 dload (2, 1)
	542 #46 (2, 1)
	543 invokevirtual (2, 1)
	544 org/apache/commons/math3/optimization/univariate/BrentOptimizer.computeObjectiveValue:(D)D (2, 1)
	546 dstore (2, 1)
	547 #48 (2, 1)
	548 iload_1 (3, 1)
	549 ifne (3, 1)
	550 8 (3, 1)
	552 dload (3, 1)
	553 #48 (3, 1)
	554 dneg (3, 1)
	555 dstore (3, 1)
	556 #48 (3, 1)
	557 aload (2, 1)
	558 #30 (2, 1)
	559 astore (2, 1)
	560 #29 (2, 1)
	561 new (2, 1)
	562 org/apache/commons/math3/optimization/univariate/UnivariatePointValuePair (2, 1)
	564 dup (2, 1)
	565 dload (2, 1)
	566 #46 (2, 1)
	567 iload_1 (2, 1)
	568 ifeq (2, 1)
	569 8 (2, 1)
	571 dload (2, 1)
	572 #48 (2, 1)
	573 goto (2, 1)
	574 6 (2, 1)
	576 dload (2, 1)
	577 #48 (2, 1)
	578 dneg (2, 1)
	579 invokespecial (2, 1)
	580 org/apache/commons/math3/optimization/univariate/UnivariatePointValuePair.<init>:(DD)V (2, 1)
	582 astore (2, 1)
	583 #30 (2, 1)
	584 aload_0 (2, 1)
	585 aload (2, 1)
	586 #31 (2, 1)
	587 aload_0 (2, 1)
	588 aload (2, 1)
	589 #29 (2, 1)
	590 aload (2, 1)
	591 #30 (2, 1)
	592 iload_1 (2, 1)
	593 invokespecial (2, 1)
	594 org/apache/commons/math3/optimization/univariate/BrentOptimizer.best:(Lorg/apache/commons/math3/optimization/univariate/UnivariatePointValuePair;Lorg/apache/commons/math3/optimization/univariate/UnivariatePointValuePair;Z)Lorg/apache/commons/math3/optimization/univariate/UnivariatePointValuePair; (2, 1)
	596 iload_1 (2, 1)
	597 invokespecial (2, 1)
	598 org/apache/commons/math3/optimization/univariate/BrentOptimizer.best:(Lorg/apache/commons/math3/optimization/univariate/UnivariatePointValuePair;Lorg/apache/commons/math3/optimization/univariate/UnivariatePointValuePair;Z)Lorg/apache/commons/math3/optimization/univariate/UnivariatePointValuePair; (2, 1)
	600 astore (2, 1)
	601 #31 (2, 1)
	602 aload (3, 1)
	603 #8 (3, 1)
	604 ifnull (3, 1)
	605 22 (3, 1)
	607 aload (3, 1)
	608 #8 (3, 1)
	609 iload (3, 1)
	610 #32 (3, 1)
	611 aload (3, 1)
	612 #29 (3, 1)
	613 aload (3, 1)
	614 #30 (3, 1)
	615 invokeinterface (3, 1)
	616 org/apache/commons/math3/optimization/ConvergenceChecker.org/apache/commons/math3/util/Precision (3, 1)
	618 0 (3, 1)
	620 ifeq (3, 1)
	621 6 (3, 1)
	623 aload (3, 1)
	624 #31 (3, 1)
	625 areturn (3, 1)
	626 dload (3, 1)
	627 #48 (3, 1)
	628 dload (3, 1)
	629 #23 (3, 1)
	630 dcmpg (3, 1)
	631 ifgt (3, 1)
	632 49 (3, 1)
	634 dload (4, 1)
	635 #46 (4, 1)
	636 dload (4, 1)
	637 #13 (4, 1)
	638 dcmpg (4, 1)
	639 ifge (4, 1)
	640 10 (4, 1)
	642 dload (4, 1)
	643 #13 (4, 1)
	644 dstore (4, 1)
	645 #11 (4, 1)
	646 goto (4, 1)
	647 7 (4, 1)
	649 dload (4, 2)
	650 #13 (4, 2)
	651 dstore (4, 2)
	652 #9 (4, 2)
	653 dload (3, 1)
	654 #17 (3, 1)
	655 dstore (3, 1)
	656 #15 (3, 1)
	657 dload (3, 1)
	658 #27 (3, 1)
	659 dstore (3, 1)
	660 #25 (3, 1)
	661 dload (3, 1)
	662 #13 (3, 1)
	663 dstore (3, 1)
	664 #17 (3, 1)
	665 dload (3, 1)
	666 #23 (3, 1)
	667 dstore (3, 1)
	668 #27 (3, 1)
	669 dload (3, 1)
	670 #46 (3, 1)
	671 dstore (3, 1)
	672 #13 (3, 1)
	673 dload (3, 1)
	674 #48 (3, 1)
	675 dstore (3, 1)
	676 #23 (3, 1)
	677 goto (3, 1)
	678 95 (3, 1)
	680 dload (4, 1)
	681 #46 (4, 1)
	682 dload (4, 1)
	683 #13 (4, 1)
	684 dcmpg (4, 1)
	685 ifge (4, 1)
	686 10 (4, 1)
	688 dload (4, 1)
	689 #46 (4, 1)
	690 dstore (4, 1)
	691 #9 (4, 1)
	692 goto (4, 1)
	693 7 (4, 1)
	695 dload (4, 2)
	696 #46 (4, 2)
	697 dstore (4, 2)
	698 #11 (4, 2)
	699 dload (3, 1)
	700 #48 (3, 1)
	701 dload (3, 1)
	702 #27 (3, 1)
	703 dcmpg (3, 1)
	704 ifle (3, 1)
	705 13 (3, 1)
	707 dload (3, 1)
	708 #17 (3, 1)
	709 dload (3, 1)
	710 #13 (3, 1)
	711 invokestatic (3, 1)
	712 org/apache/commons/math3/util/Precision.equals:(DD)Z (3, 1)
	714 ifeq (3, 1)
	715 22 (3, 1)
	717 dload (3, 1)
	718 #17 (3, 1)
	719 dstore (3, 1)
	720 #15 (3, 1)
	721 dload (3, 1)
	722 #27 (3, 1)
	723 dstore (3, 1)
	724 #25 (3, 1)
	725 dload (3, 1)
	726 #46 (3, 1)
	727 dstore (3, 1)
	728 #17 (3, 1)
	729 dload (3, 1)
	730 #48 (3, 1)
	731 dstore (3, 1)
	732 #27 (3, 1)
	733 goto (3, 1)
	734 39 (3, 1)
	736 dload (3, 1)
	737 #48 (3, 1)
	738 dload (3, 1)
	739 #25 (3, 1)
	740 dcmpg (3, 1)
	741 ifle (3, 1)
	742 23 (3, 1)
	744 dload (3, 1)
	745 #15 (3, 1)
	746 dload (3, 1)
	747 #13 (3, 1)
	748 invokestatic (3, 1)
	749 org/apache/commons/math3/util/Precision.equals:(DD)Z (3, 1)
	751 ifne (3, 1)
	752 13 (3, 1)
	754 dload (3, 1)
	755 #15 (3, 1)
	756 dload (3, 1)
	757 #17 (3, 1)
	758 invokestatic (3, 1)
	759 org/apache/commons/math3/util/Precision.equals:(DD)Z (3, 1)
	761 ifeq (3, 1)
	762 11 (3, 1)
	764 dload (3, 1)
	765 #46 (3, 1)
	766 dstore (3, 1)
	767 #15 (3, 1)
	768 dload (3, 1)
	769 #48 (3, 1)
	770 dstore (3, 1)
	771 #25 (3, 1)
	772 goto (2, 2)
	773 20 (2, 2)
	775 aload_0 (2, 2)
	776 aload (2, 2)
	777 #31 (2, 2)
	778 aload_0 (2, 2)
	779 aload (2, 2)
	780 #29 (2, 2)
	781 aload (2, 2)
	782 #30 (2, 2)
	783 iload_1 (2, 2)
	784 invokespecial (2, 2)
	785 org/apache/commons/math3/optimization/univariate/BrentOptimizer.best:(Lorg/apache/commons/math3/optimization/univariate/UnivariatePointValuePair;Lorg/apache/commons/math3/optimization/univariate/UnivariatePointValuePair;Z)Lorg/apache/commons/math3/optimization/univariate/UnivariatePointValuePair; (2, 2)
	787 iload_1 (2, 2)
	788 invokespecial (2, 2)
	789 org/apache/commons/math3/optimization/univariate/BrentOptimizer.best:(Lorg/apache/commons/math3/optimization/univariate/UnivariatePointValuePair;Lorg/apache/commons/math3/optimization/univariate/UnivariatePointValuePair;Z)Lorg/apache/commons/math3/optimization/univariate/UnivariatePointValuePair; (2, 2)
	791 areturn (2, 2)
	792 iinc (1, 3)
	793 #32 (1, 3)
	794 -89 (1, 3)
	795 goto (0, 0)
	796 -656 (0, 0)

Method: best
	0 aload_1 (1, 1)
	1 ifnonnull (1, 1)
	2 5 (1, 1)
	4 aload_2 (1, 1)
	5 areturn (1, 1)
	6 aload_2 (1, 1)
	7 ifnonnull (1, 1)
	8 5 (1, 1)
	10 aload_1 (1, 1)
	11 areturn (1, 1)
	12 iload_3 (1, 1)
	13 ifeq (1, 1)
	14 21 (1, 1)
	16 aload_1 (1, 1)
	17 invokevirtual (1, 1)
	18 org/apache/commons/math3/optimization/univariate/UnivariatePointValuePair.getValue:()D (1, 1)
	20 aload_2 (1, 1)
	21 invokevirtual (1, 1)
	22 org/apache/commons/math3/optimization/univariate/UnivariatePointValuePair.getValue:()D (1, 1)
	24 dcmpg (1, 1)
	25 ifgt (1, 1)
	26 7 (1, 1)
	28 aload_1 (1, 1)
	29 goto (1, 1)
	30 4 (1, 1)
	32 aload_2 (1, 1)
	33 areturn (1, 1)
	34 aload_1 (1, 2)
	35 invokevirtual (1, 2)
	36 org/apache/commons/math3/optimization/univariate/UnivariatePointValuePair.getValue:()D (1, 2)
	38 aload_2 (1, 2)
	39 invokevirtual (1, 2)
	40 org/apache/commons/math3/optimization/univariate/UnivariatePointValuePair.getValue:()D (1, 2)
	42 dcmpl (1, 2)
	43 iflt (1, 2)
	44 7 (1, 2)
	46 aload_1 (1, 2)
	47 goto (1, 2)
	48 4 (1, 2)
	50 aload_2 (1, 2)
	51 areturn (1, 2)

Method: <clinit>
	0 ldc2_w (0, 0)
	1 0.5 (0, 0)
	3 ldc2_w (0, 0)
	4 3.0 (0, 0)
	6 ldc2_w (0, 0)
	7 5.0 (0, 0)
	9 invokestatic (0, 0)
	10 org/apache/commons/math3/util/FastMath.sqrt:(D)D (0, 0)
	12 dsub (0, 0)
	13 dmul (0, 0)
	14 putstatic (0, 0)
	15 org/apache/commons/math3/optimization/univariate/BrentOptimizer.GOLDEN_SECTION:D (0, 0)
	17 ldc2_w (0, 0)
	18 2.0 (0, 0)
	20 dconst_1 (0, 0)
	21 invokestatic (0, 0)
	22 org/apache/commons/math3/util/FastMath.ulp:(D)D (0, 0)
	24 dmul (0, 0)
	25 putstatic (0, 0)
	26 org/apache/commons/math3/optimization/univariate/BrentOptimizer.MIN_RELATIVE_TOLERANCE:D (0, 0)
	28 return (0, 0)

