Method: <init>
	0 aload_0 (0, 0)
	1 invokespecial (0, 0)
	2 java/lang/Object.<init>:()V (0, 0)
	4 aload_1 (2, 1)
	5 ifnonnull (2, 1)
	6 11 (2, 1)
	8 new (2, 1)
	9 org/apache/commons/math3/exception/NullArgumentException (2, 1)
	11 dup (2, 1)
	12 invokespecial (2, 1)
	13 org/apache/commons/math3/exception/NullArgumentException.<init>:()V (2, 1)
	15 athrow (2, 1)
	16 aload_1 (2, 1)
	17 invokevirtual (2, 1)
	18 java/lang/String.length:()I (2, 1)
	20 ifne (2, 1)
	21 11 (2, 1)
	23 new (2, 1)
	24 org/apache/commons/math3/exception/NoDataException (2, 1)
	26 dup (2, 1)
	27 invokespecial (2, 1)
	28 org/apache/commons/math3/exception/NoDataException.<init>:()V (2, 1)
	30 athrow (2, 1)
	31 aload_3 (2, 1)
	32 ifnonnull (2, 1)
	33 18 (2, 1)
	35 new (2, 1)
	36 org/apache/commons/math3/exception/NullArgumentException (2, 1)
	38 dup (2, 1)
	39 getstatic (2, 1)
	40 org/apache/commons/math3/exception/util/LocalizedFormats.IMAGINARY_FORMAT:Lorg/apache/commons/math3/exception/util/LocalizedFormats; (2, 1)
	42 iconst_0 (2, 1)
	43 anewarray (2, 1)
	44 java/lang/Object (2, 1)
	46 invokespecial (2, 1)
	47 org/apache/commons/math3/exception/NullArgumentException.<init>:(Lorg/apache/commons/math3/exception/util/Localizable;[Ljava/lang/Object;)V (2, 1)
	49 athrow (2, 1)
	50 aload_2 (2, 1)
	51 ifnonnull (2, 1)
	52 18 (2, 1)
	54 new (2, 1)
	55 org/apache/commons/math3/exception/NullArgumentException (2, 1)
	57 dup (2, 1)
	58 getstatic (2, 1)
	59 org/apache/commons/math3/exception/util/LocalizedFormats.REAL_FORMAT:Lorg/apache/commons/math3/exception/util/LocalizedFormats; (2, 1)
	61 iconst_0 (2, 1)
	62 anewarray (2, 1)
	63 java/lang/Object (2, 1)
	65 invokespecial (2, 1)
	66 org/apache/commons/math3/exception/NullArgumentException.<init>:(Lorg/apache/commons/math3/exception/util/Localizable;[Ljava/lang/Object;)V (2, 1)
	68 athrow (2, 1)
	69 aload_0 (0, 0)
	70 aload_1 (0, 0)
	71 putfield (0, 0)
	72 org/apache/commons/math3/complex/ComplexFormat.imaginaryCharacter:Ljava/lang/String; (0, 0)
	74 aload_0 (0, 0)
	75 aload_3 (0, 0)
	76 putfield (0, 0)
	77 org/apache/commons/math3/complex/ComplexFormat.imaginaryFormat:Ljava/text/NumberFormat; (0, 0)
	79 aload_0 (0, 0)
	80 aload_2 (0, 0)
	81 putfield (0, 0)
	82 org/apache/commons/math3/complex/ComplexFormat.realFormat:Ljava/text/NumberFormat; (0, 0)
	84 return (0, 0)

Method: getAvailableLocales
	0 invokestatic (0, 0)
	1 java/text/NumberFormat.getAvailableLocales:()[Ljava/util/Locale; (0, 0)
	3 areturn (0, 0)

Method: format
	0 aconst_null (0, 0)
	1 astore (0, 0)
	2 #4 (0, 0)
	3 aload_1 (1, 1)
	4 instanceof (1, 1)
	5 org/apache/commons/math3/complex/Complex (1, 1)
	7 ifeq (1, 1)
	8 18 (1, 1)
	10 aload_0 (1, 4)
	11 aload_1 (1, 4)
	12 checkcast (1, 4)
	13 org/apache/commons/math3/complex/Complex (1, 4)
	15 aload_2 (1, 4)
	16 aload_3 (1, 4)
	17 invokevirtual (1, 4)
	18 org/apache/commons/math3/complex/ComplexFormat.format:(Lorg/apache/commons/math3/complex/Complex;Ljava/lang/StringBuffer;Ljava/text/FieldPosition;)Ljava/lang/StringBuffer; (1, 4)
	20 astore (1, 4)
	21 #4 (1, 4)
	22 goto (1, 4)
	23 61 (1, 4)
	25 aload_1 (1, 1)
	26 instanceof (1, 1)
	27 java/lang/Number (1, 1)
	29 ifeq (1, 1)
	30 29 (1, 1)
	32 aload_0 (1, 4)
	33 new (1, 4)
	34 org/apache/commons/math3/complex/Complex (1, 4)
	36 dup (1, 4)
	37 aload_1 (1, 4)
	38 checkcast (1, 4)
	39 java/lang/Number (1, 4)
	41 invokevirtual (1, 4)
	42 java/lang/Number.doubleValue:()D (1, 4)
	44 dconst_0 (1, 4)
	45 invokespecial (1, 4)
	46 org/apache/commons/math3/complex/Complex.<init>:(DD)V (1, 4)
	48 aload_2 (1, 4)
	49 aload_3 (1, 4)
	50 invokevirtual (1, 4)
	51 org/apache/commons/math3/complex/ComplexFormat.format:(Lorg/apache/commons/math3/complex/Complex;Ljava/lang/StringBuffer;Ljava/text/FieldPosition;)Ljava/lang/StringBuffer; (1, 4)
	53 astore (1, 4)
	54 #4 (1, 4)
	55 goto (1, 4)
	56 28 (1, 4)
	58 new (1, 2)
	59 org/apache/commons/math3/exception/MathIllegalArgumentException (1, 2)
	61 dup (1, 2)
	62 getstatic (1, 2)
	63 org/apache/commons/math3/exception/util/LocalizedFormats.CANNOT_FORMAT_INSTANCE_AS_COMPLEX:Lorg/apache/commons/math3/exception/util/LocalizedFormats; (1, 2)
	65 iconst_1 (1, 2)
	66 anewarray (1, 2)
	67 java/lang/Object (1, 2)
	69 dup (1, 2)
	70 iconst_0 (1, 2)
	71 aload_1 (1, 2)
	72 invokevirtual (1, 2)
	73 java/lang/Object.getClass:()Ljava/lang/Class; (1, 2)
	75 invokevirtual (1, 2)
	76 java/lang/Class.getName:()Ljava/lang/String; (1, 2)
	78 aastore (1, 2)
	79 invokespecial (1, 2)
	80 org/apache/commons/math3/exception/MathIllegalArgumentException.<init>:(Lorg/apache/commons/math3/exception/util/Localizable;[Ljava/lang/Object;)V (1, 2)
	82 athrow (1, 2)
	83 aload (0, 0)
	84 #4 (0, 0)
	85 areturn (0, 0)

Method: formatImaginary
	0 aload (0, 0)
	1 #4 (0, 0)
	2 iconst_0 (0, 0)
	3 invokevirtual (0, 0)
	4 java/text/FieldPosition.setBeginIndex:(I)V (0, 0)
	6 aload (0, 0)
	7 #4 (0, 0)
	8 iconst_0 (0, 0)
	9 invokevirtual (0, 0)
	10 java/text/FieldPosition.setEndIndex:(I)V (0, 0)
	12 dload_1 (0, 4)
	13 aload_0 (0, 4)
	14 invokevirtual (0, 4)
	15 org/apache/commons/math3/complex/ComplexFormat.getImaginaryFormat:()Ljava/text/NumberFormat; (0, 4)
	17 aload_3 (0, 4)
	18 aload (0, 4)
	19 #4 (0, 4)
	20 invokestatic (0, 4)
	21 org/apache/commons/math3/util/CompositeFormat.formatDouble:(DLjava/text/NumberFormat;Ljava/lang/StringBuffer;Ljava/text/FieldPosition;)Ljava/lang/StringBuffer; (0, 4)
	23 pop (0, 4)
	24 aload_3 (1, 1)
	25 invokevirtual (1, 1)
	26 java/lang/StringBuffer.toString:()Ljava/lang/String; (1, 1)
	28 ldc (1, 1)
	29 1 (1, 1)
	30 invokevirtual (1, 1)
	31 java/lang/String.equals:(Ljava/lang/Object;)Z (1, 1)
	33 ifeq (1, 1)
	34 8 (1, 1)
	36 aload_3 (1, 1)
	37 iconst_0 (1, 1)
	38 invokevirtual (1, 1)
	39 java/lang/StringBuffer.setLength:(I)V (1, 1)
	41 aload_3 (0, 4)
	42 areturn (0, 4)

Method: getImaginaryCharacter
	0 aload_0 (0, 0)
	1 getfield (0, 0)
	2 org/apache/commons/math3/complex/ComplexFormat.imaginaryCharacter:Ljava/lang/String; (0, 0)
	4 areturn (0, 0)

Method: getImaginaryFormat
	0 aload_0 (0, 0)
	1 getfield (0, 0)
	2 org/apache/commons/math3/complex/ComplexFormat.imaginaryFormat:Ljava/text/NumberFormat; (0, 0)
	4 areturn (0, 0)

Method: getInstance
	0 aload_1 (0, 0)
	1 invokestatic (0, 0)
	2 org/apache/commons/math3/util/CompositeFormat.getDefaultNumberFormat:(Ljava/util/Locale;)Ljava/text/NumberFormat; (0, 0)
	4 astore_2 (0, 0)
	5 new (0, 0)
	6 org/apache/commons/math3/complex/ComplexFormat (0, 0)
	8 dup (0, 0)
	9 aload_0 (0, 0)
	10 aload_2 (0, 0)
	11 invokespecial (0, 0)
	12 org/apache/commons/math3/complex/ComplexFormat.<init>:(Ljava/lang/String;Ljava/text/NumberFormat;)V (0, 0)
	14 areturn (0, 0)

Method: getRealFormat
	0 aload_0 (0, 0)
	1 getfield (0, 0)
	2 org/apache/commons/math3/complex/ComplexFormat.realFormat:Ljava/text/NumberFormat; (0, 0)
	4 areturn (0, 0)

Method: parse
	0 aload_2 (0, 0)
	1 invokevirtual (0, 0)
	2 java/text/ParsePosition.getIndex:()I (0, 0)
	4 istore_3 (0, 0)
	5 aload_1 (0, 0)
	6 aload_2 (0, 0)
	7 invokestatic (0, 0)
	8 org/apache/commons/math3/util/CompositeFormat.parseAndIgnoreWhitespace:(Ljava/lang/String;Ljava/text/ParsePosition;)V (0, 0)
	10 aload_1 (0, 0)
	11 aload_0 (0, 0)
	12 invokevirtual (0, 0)
	13 org/apache/commons/math3/complex/ComplexFormat.getRealFormat:()Ljava/text/NumberFormat; (0, 0)
	15 aload_2 (0, 0)
	16 invokestatic (0, 0)
	17 org/apache/commons/math3/util/CompositeFormat.parseNumber:(Ljava/lang/String;Ljava/text/NumberFormat;Ljava/text/ParsePosition;)Ljava/lang/Number; (0, 0)
	19 astore (0, 0)
	20 #4 (0, 0)
	21 aload (1, 1)
	22 #4 (1, 1)
	23 ifnonnull (1, 1)
	24 10 (1, 1)
	26 aload_2 (1, 1)
	27 iload_3 (1, 1)
	28 invokevirtual (1, 1)
	29 java/text/ParsePosition.setIndex:(I)V (1, 1)
	31 aconst_null (1, 1)
	32 areturn (1, 1)
	33 aload_2 (0, 0)
	34 invokevirtual (0, 0)
	35 java/text/ParsePosition.getIndex:()I (0, 0)
	37 istore (0, 0)
	38 #5 (0, 0)
	39 aload_1 (0, 0)
	40 aload_2 (0, 0)
	41 invokestatic (0, 0)
	42 org/apache/commons/math3/util/CompositeFormat.parseNextCharacter:(Ljava/lang/String;Ljava/text/ParsePosition;)C (0, 0)
	44 istore (0, 0)
	45 #6 (0, 0)
	46 iconst_0 (0, 0)
	47 istore (0, 0)
	48 #7 (0, 0)
	49 iload (1, 5)
	50 #6 (1, 5)
	51 lookupswitch (1, 5)
	52 0: 84 (1, 5)
	56 43: 104 (1, 5)
	60 45: 98 (1, 5)
	84 new (1, 5)
	85 org/apache/commons/math3/complex/Complex (1, 5)
	87 dup (1, 5)
	88 aload (1, 5)
	89 #4 (1, 5)
	90 invokevirtual (1, 5)
	91 java/lang/Number.doubleValue:()D (1, 5)
	93 dconst_0 (1, 5)
	94 invokespecial (1, 5)
	95 org/apache/commons/math3/complex/Complex.<init>:(DD)V (1, 5)
	97 areturn (1, 5)
	98 iconst_m1 (1, 5)
	99 istore (1, 5)
	100 #7 (1, 5)
	101 goto (1, 5)
	102 22 (1, 5)
	104 iconst_1 (1, 5)
	105 istore (1, 5)
	106 #7 (1, 5)
	107 goto (1, 5)
	108 16 (1, 5)
	110 aload_2 (1, 5)
	111 iload_3 (1, 5)
	112 invokevirtual (1, 5)
	113 java/text/ParsePosition.setIndex:(I)V (1, 5)
	115 aload_2 (1, 5)
	116 iload (1, 5)
	117 #5 (1, 5)
	118 invokevirtual (1, 5)
	119 java/text/ParsePosition.setErrorIndex:(I)V (1, 5)
	121 aconst_null (1, 5)
	122 areturn (1, 5)
	123 aload_1 (0, 0)
	124 aload_2 (0, 0)
	125 invokestatic (0, 0)
	126 org/apache/commons/math3/util/CompositeFormat.parseAndIgnoreWhitespace:(Ljava/lang/String;Ljava/text/ParsePosition;)V (0, 0)
	128 aload_1 (0, 0)
	129 aload_0 (0, 0)
	130 invokevirtual (0, 0)
	131 org/apache/commons/math3/complex/ComplexFormat.getRealFormat:()Ljava/text/NumberFormat; (0, 0)
	133 aload_2 (0, 0)
	134 invokestatic (0, 0)
	135 org/apache/commons/math3/util/CompositeFormat.parseNumber:(Ljava/lang/String;Ljava/text/NumberFormat;Ljava/text/ParsePosition;)Ljava/lang/Number; (0, 0)
	137 astore (0, 0)
	138 #8 (0, 0)
	139 aload (1, 1)
	140 #8 (1, 1)
	141 ifnonnull (1, 1)
	142 10 (1, 1)
	144 aload_2 (1, 1)
	145 iload_3 (1, 1)
	146 invokevirtual (1, 1)
	147 java/text/ParsePosition.setIndex:(I)V (1, 1)
	149 aconst_null (1, 1)
	150 areturn (1, 1)
	151 aload_1 (1, 1)
	152 aload_0 (1, 1)
	153 invokevirtual (1, 1)
	154 org/apache/commons/math3/complex/ComplexFormat.getImaginaryCharacter:()Ljava/lang/String; (1, 1)
	156 aload_2 (1, 1)
	157 invokestatic (1, 1)
	158 org/apache/commons/math3/util/CompositeFormat.parseFixedstring:(Ljava/lang/String;Ljava/lang/String;Ljava/text/ParsePosition;)Z (1, 1)
	160 ifne (1, 1)
	161 5 (1, 1)
	163 aconst_null (1, 1)
	164 areturn (1, 1)
	165 new (0, 0)
	166 org/apache/commons/math3/complex/Complex (0, 0)
	168 dup (0, 0)
	169 aload (0, 0)
	170 #4 (0, 0)
	171 invokevirtual (0, 0)
	172 java/lang/Number.doubleValue:()D (0, 0)
	174 aload (0, 0)
	175 #8 (0, 0)
	176 invokevirtual (0, 0)
	177 java/lang/Number.doubleValue:()D (0, 0)
	179 iload (0, 0)
	180 #7 (0, 0)
	181 i2d (0, 0)
	182 dmul (0, 0)
	183 invokespecial (0, 0)
	184 org/apache/commons/math3/complex/Complex.<init>:(DD)V (0, 0)
	186 areturn (0, 0)

