Method: <init>
	0 aload_0 (0, 0)
	1 invokespecial (0, 0)
	2 java/lang/Object.<init>:()V (0, 0)
	4 return (0, 0)

Method: getInstance
	0 invokestatic (0, 0)
	1 org/apache/commons/math3/complex/ComplexField$LazyHolder.access$000:()Lorg/apache/commons/math3/complex/ComplexField; (0, 0)
	3 areturn (0, 0)

Method: getOne
	0 aload_0 (0, 0)
	1 invokevirtual (0, 0)
	2 org/apache/commons/math3/complex/ComplexField.getOne:()Lorg/apache/commons/math3/complex/Complex; (0, 0)
	4 areturn (0, 0)

Method: getZero
	0 aload_0 (0, 0)
	1 invokevirtual (0, 0)
	2 org/apache/commons/math3/complex/ComplexField.getZero:()Lorg/apache/commons/math3/complex/Complex; (0, 0)
	4 areturn (0, 0)

Method: getRuntimeClass
	0 ldc (0, 0)
	1 org/apache/commons/math3/complex/Complex (0, 0)
	2 areturn (0, 0)

Method: readResolve
	0 invokestatic (0, 0)
	1 org/apache/commons/math3/complex/ComplexField$LazyHolder.access$000:()Lorg/apache/commons/math3/complex/ComplexField; (0, 0)
	3 areturn (0, 0)

