Method: <init>
	0 aload_0 (0, 0)
	1 dconst_0 (0, 0)
	2 aload_1 (0, 0)
	3 invokespecial (0, 0)
	6 return (0, 0)

Method: getConjugate
	0 new (0, 0)
	3 dup (0, 0)
	4 aload_0 (0, 0)
	5 getfield (0, 0)
	8 aload_0 (0, 0)
	9 getfield (0, 0)
	12 dneg (0, 0)
	13 aload_0 (0, 0)
	14 getfield (0, 0)
	17 dneg (0, 0)
	18 aload_0 (0, 0)
	19 getfield (0, 0)
	22 dneg (0, 0)
	23 invokespecial (0, 0)
	26 areturn (0, 0)

Method: multiply
	0 new (0, 0)
	3 dup (0, 0)
	4 dload_1 (0, 0)
	5 aload_0 (0, 0)
	6 getfield (0, 0)
	9 dmul (0, 0)
	10 dload_1 (0, 0)
	11 aload_0 (0, 0)
	12 getfield (0, 0)
	15 dmul (0, 0)
	16 dload_1 (0, 0)
	17 aload_0 (0, 0)
	18 getfield (0, 0)
	21 dmul (0, 0)
	22 dload_1 (0, 0)
	23 aload_0 (0, 0)
	24 getfield (0, 0)
	27 dmul (0, 0)
	28 invokespecial (0, 0)
	31 areturn (0, 0)

Method: add
	0 aload_0 (0, 0)
	1 aload_1 (0, 0)
	2 invokestatic (0, 0)
	5 areturn (0, 0)

Method: subtract
	0 aload_0 (0, 0)
	1 aload_1 (0, 0)
	2 invokestatic (0, 0)
	5 areturn (0, 0)

Method: dotProduct
	0 aload_0 (0, 0)
	1 aload_1 (0, 0)
	2 invokestatic (0, 0)
	5 dreturn (0, 0)

Method: getNorm
	0 aload_0 (0, 0)
	1 getfield (0, 0)
	4 aload_0 (0, 0)
	5 getfield (0, 0)
	8 dmul (0, 0)
	9 aload_0 (0, 0)
	10 getfield (0, 0)
	13 aload_0 (0, 0)
	14 getfield (0, 0)
	17 dmul (0, 0)
	18 dadd (0, 0)
	19 aload_0 (0, 0)
	20 getfield (0, 0)
	23 aload_0 (0, 0)
	24 getfield (0, 0)
	27 dmul (0, 0)
	28 dadd (0, 0)
	29 aload_0 (0, 0)
	30 getfield (0, 0)
	33 aload_0 (0, 0)
	34 getfield (0, 0)
	37 dmul (0, 0)
	38 dadd (0, 0)
	39 invokestatic (0, 0)
	42 dreturn (0, 0)

Method: normalize
	0 aload_0 (0, 0)
	1 invokevirtual (0, 0)
	4 dstore_1 (0, 0)
	5 dload_1 (1, 1)
	6 getstatic (1, 1)
	9 dcmpg (1, 1)
	10 ifge (1, 1)
	13 new (1, 1)
	16 dup (1, 1)
	17 getstatic (1, 1)
	20 iconst_1 (1, 1)
	21 anewarray (1, 1)
	24 dup (1, 1)
	25 iconst_0 (1, 1)
	26 dload_1 (1, 1)
	27 invokestatic (1, 1)
	30 aastore (1, 1)
	31 invokespecial (1, 1)
	34 athrow (1, 1)
	35 new (0, 0)
	38 dup (0, 0)
	39 aload_0 (0, 0)
	40 getfield (0, 0)
	43 dload_1 (0, 0)
	44 ddiv (0, 0)
	45 aload_0 (0, 0)
	46 getfield (0, 0)
	49 dload_1 (0, 0)
	50 ddiv (0, 0)
	51 aload_0 (0, 0)
	52 getfield (0, 0)
	55 dload_1 (0, 0)
	56 ddiv (0, 0)
	57 aload_0 (0, 0)
	58 getfield (0, 0)
	61 dload_1 (0, 0)
	62 ddiv (0, 0)
	63 invokespecial (0, 0)
	66 areturn (0, 0)

Method: equals
	0 aload_0 (0, 0)
	1 getfield (0, 0)
	4 aload_1 (0, 0)
	5 invokevirtual (0, 0)
	8 dload_2 (0, 0)
	9 invokestatic (0, 0)
	12 ifeq (0, 0)
	15 aload_0 (0, 0)
	16 getfield (0, 0)
	19 aload_1 (0, 0)
	20 invokevirtual (0, 0)
	23 dload_2 (0, 0)
	24 invokestatic (0, 0)
	27 ifeq (0, 0)
	30 aload_0 (0, 0)
	31 getfield (0, 0)
	34 aload_1 (0, 0)
	35 invokevirtual (0, 0)
	38 dload_2 (0, 0)
	39 invokestatic (0, 0)
	42 ifeq (0, 0)
	45 aload_0 (0, 0)
	46 getfield (0, 0)
	49 aload_1 (0, 0)
	50 invokevirtual (0, 0)
	53 dload_2 (0, 0)
	54 invokestatic (0, 0)
	57 ifeq (0, 0)
	60 iconst_1 (0, 0)
	61 goto (0, 0)
	64 iconst_0 (0, 0)
	65 ireturn (0, 0)

Method: hashCode
	0 bipush (0, 0)
	2 istore_1 (0, 0)
	3 iconst_4 (1, 4)
	4 newarray (1, 4)
	6 dup (1, 4)
	7 iconst_0 (1, 4)
	8 aload_0 (1, 4)
	9 getfield (1, 4)
	12 dastore (1, 4)
	13 dup (1, 4)
	14 iconst_1 (1, 4)
	15 aload_0 (1, 4)
	16 getfield (1, 4)
	19 dastore (1, 4)
	20 dup (1, 4)
	21 iconst_2 (1, 4)
	22 aload_0 (1, 4)
	23 getfield (1, 4)
	26 dastore (1, 4)
	27 dup (1, 4)
	28 iconst_3 (1, 4)
	29 aload_0 (1, 4)
	30 getfield (1, 4)
	33 dastore (1, 4)
	34 astore_2 (1, 4)
	35 aload_2 (1, 4)
	36 arraylength (1, 4)
	37 istore_3 (1, 4)
	38 iconst_0 (1, 4)
	39 istore (1, 4)
	41 iload (1, 4)
	43 iload_3 (1, 4)
	44 if_icmpge (1, 4)
	47 aload_2 (1, 4)
	48 iload (1, 4)
	50 daload (1, 4)
	51 dstore (1, 4)
	53 dload (1, 4)
	55 invokestatic (1, 4)
	58 istore (1, 4)
	60 bipush (1, 4)
	62 iload_1 (1, 4)
	63 imul (1, 4)
	64 iload (1, 4)
	66 iadd (1, 4)
	67 istore_1 (1, 4)
	68 iinc (1, 4)
	71 goto (1, 4)
	74 iload_1 (0, 0)
	75 ireturn (0, 0)

Method: isUnitQuaternion
	0 aload_0 (0, 0)
	1 invokevirtual (0, 0)
	4 dconst_1 (0, 0)
	5 dload_1 (0, 0)
	6 invokestatic (0, 0)
	9 ireturn (0, 0)

Method: isPureQuaternion
	0 aload_0 (0, 0)
	1 invokevirtual (0, 0)
	4 invokestatic (0, 0)
	7 dload_1 (0, 0)
	8 dcmpg (0, 0)
	9 ifgt (0, 0)
	12 iconst_1 (0, 0)
	13 goto (0, 0)
	16 iconst_0 (0, 0)
	17 ireturn (0, 0)

Method: getPositivePolarForm
	0 aload_0 (1, 1)
	1 invokevirtual (1, 1)
	4 dconst_0 (1, 1)
	5 dcmpg (1, 1)
	6 ifge (1, 1)
	9 aload_0 (1, 1)
	10 invokevirtual (1, 1)
	13 astore_1 (1, 1)
	14 new (1, 1)
	17 dup (1, 1)
	18 aload_1 (1, 1)
	19 invokevirtual (1, 1)
	22 dneg (1, 1)
	23 aload_1 (1, 1)
	24 invokevirtual (1, 1)
	27 dneg (1, 1)
	28 aload_1 (1, 1)
	29 invokevirtual (1, 1)
	32 dneg (1, 1)
	33 aload_1 (1, 1)
	34 invokevirtual (1, 1)
	37 dneg (1, 1)
	38 invokespecial (1, 1)
	41 areturn (1, 1)
	42 aload_0 (1, 2)
	43 invokevirtual (1, 2)
	46 areturn (1, 2)

Method: getInverse
	0 aload_0 (0, 0)
	1 getfield (0, 0)
	4 aload_0 (0, 0)
	5 getfield (0, 0)
	8 dmul (0, 0)
	9 aload_0 (0, 0)
	10 getfield (0, 0)
	13 aload_0 (0, 0)
	14 getfield (0, 0)
	17 dmul (0, 0)
	18 dadd (0, 0)
	19 aload_0 (0, 0)
	20 getfield (0, 0)
	23 aload_0 (0, 0)
	24 getfield (0, 0)
	27 dmul (0, 0)
	28 dadd (0, 0)
	29 aload_0 (0, 0)
	30 getfield (0, 0)
	33 aload_0 (0, 0)
	34 getfield (0, 0)
	37 dmul (0, 0)
	38 dadd (0, 0)
	39 dstore_1 (0, 0)
	40 dload_1 (1, 1)
	41 getstatic (1, 1)
	44 dcmpg (1, 1)
	45 ifge (1, 1)
	48 new (1, 1)
	51 dup (1, 1)
	52 getstatic (1, 1)
	55 iconst_1 (1, 1)
	56 anewarray (1, 1)
	59 dup (1, 1)
	60 iconst_0 (1, 1)
	61 dload_1 (1, 1)
	62 invokestatic (1, 1)
	65 aastore (1, 1)
	66 invokespecial (1, 1)
	69 athrow (1, 1)
	70 new (0, 0)
	73 dup (0, 0)
	74 aload_0 (0, 0)
	75 getfield (0, 0)
	78 dload_1 (0, 0)
	79 ddiv (0, 0)
	80 aload_0 (0, 0)
	81 getfield (0, 0)
	84 dneg (0, 0)
	85 dload_1 (0, 0)
	86 ddiv (0, 0)
	87 aload_0 (0, 0)
	88 getfield (0, 0)
	91 dneg (0, 0)
	92 dload_1 (0, 0)
	93 ddiv (0, 0)
	94 aload_0 (0, 0)
	95 getfield (0, 0)
	98 dneg (0, 0)
	99 dload_1 (0, 0)
	100 ddiv (0, 0)
	101 invokespecial (0, 0)
	104 areturn (0, 0)

Method: getQ0
	0 aload_0 (0, 0)
	1 getfield (0, 0)
	4 dreturn (0, 0)

Method: getQ1
	0 aload_0 (0, 0)
	1 getfield (0, 0)
	4 dreturn (0, 0)

Method: getQ2
	0 aload_0 (0, 0)
	1 getfield (0, 0)
	4 dreturn (0, 0)

Method: getQ3
	0 aload_0 (0, 0)
	1 getfield (0, 0)
	4 dreturn (0, 0)

Method: getScalarPart
	0 aload_0 (0, 0)
	1 invokevirtual (0, 0)
	4 dreturn (0, 0)

Method: getVectorPart
	0 iconst_3 (0, 0)
	1 newarray (0, 0)
	3 dup (0, 0)
	4 iconst_0 (0, 0)
	5 aload_0 (0, 0)
	6 invokevirtual (0, 0)
	9 dastore (0, 0)
	10 dup (0, 0)
	11 iconst_1 (0, 0)
	12 aload_0 (0, 0)
	13 invokevirtual (0, 0)
	16 dastore (0, 0)
	17 dup (0, 0)
	18 iconst_2 (0, 0)
	19 aload_0 (0, 0)
	20 invokevirtual (0, 0)
	23 dastore (0, 0)
	24 areturn (0, 0)

Method: toString
	0 ldc (0, 0)
	2 astore_1 (0, 0)
	3 new (0, 0)
	6 dup (0, 0)
	7 invokespecial (0, 0)
	10 astore_2 (0, 0)
	11 aload_2 (0, 0)
	12 ldc (0, 0)
	14 invokevirtual (0, 0)
	17 aload_0 (0, 0)
	18 getfield (0, 0)
	21 invokevirtual (0, 0)
	24 ldc (0, 0)
	26 invokevirtual (0, 0)
	29 aload_0 (0, 0)
	30 getfield (0, 0)
	33 invokevirtual (0, 0)
	36 ldc (0, 0)
	38 invokevirtual (0, 0)
	41 aload_0 (0, 0)
	42 getfield (0, 0)
	45 invokevirtual (0, 0)
	48 ldc (0, 0)
	50 invokevirtual (0, 0)
	53 aload_0 (0, 0)
	54 getfield (0, 0)
	57 invokevirtual (0, 0)
	60 ldc (0, 0)
	62 invokevirtual (0, 0)
	65 pop (0, 0)
	66 aload_2 (0, 0)
	67 invokevirtual (0, 0)
	70 areturn (0, 0)

Method: <clinit>
	0 new (0, 0)
	3 dup (0, 0)
	4 dconst_1 (0, 0)
	5 dconst_0 (0, 0)
	6 dconst_0 (0, 0)
	7 dconst_0 (0, 0)
	8 invokespecial (0, 0)
	11 putstatic (0, 0)
	14 new (0, 0)
	17 dup (0, 0)
	18 dconst_0 (0, 0)
	19 dconst_0 (0, 0)
	20 dconst_0 (0, 0)
	21 dconst_0 (0, 0)
	22 invokespecial (0, 0)
	25 putstatic (0, 0)
	28 new (0, 0)
	31 dup (0, 0)
	32 dconst_0 (0, 0)
	33 dconst_1 (0, 0)
	34 dconst_0 (0, 0)
	35 dconst_0 (0, 0)
	36 invokespecial (0, 0)
	39 putstatic (0, 0)
	42 new (0, 0)
	45 dup (0, 0)
	46 dconst_0 (0, 0)
	47 dconst_0 (0, 0)
	48 dconst_1 (0, 0)
	49 dconst_0 (0, 0)
	50 invokespecial (0, 0)
	53 putstatic (0, 0)
	56 new (0, 0)
	59 dup (0, 0)
	60 dconst_0 (0, 0)
	61 dconst_0 (0, 0)
	62 dconst_0 (0, 0)
	63 dconst_1 (0, 0)
	64 invokespecial (0, 0)
	67 putstatic (0, 0)
	70 return (0, 0)

