Method: <init>
	0 aload_0 (0, 0)
	1 invokespecial (0, 0)
	2 java/lang/Object.<init>:()V (0, 0)
	4 aload_0 (0, 0)
	5 iconst_0 (0, 0)
	6 putfield (0, 0)
	7 org/apache/commons/math3/complex/RootsOfUnity.omegaCount:I (0, 0)
	9 aload_0 (0, 0)
	10 aconst_null (0, 0)
	11 putfield (0, 0)
	12 org/apache/commons/math3/complex/RootsOfUnity.omegaReal:[D (0, 0)
	14 aload_0 (0, 0)
	15 aconst_null (0, 0)
	16 putfield (0, 0)
	17 org/apache/commons/math3/complex/RootsOfUnity.omegaImaginaryCounterClockwise:[D (0, 0)
	19 aload_0 (0, 0)
	20 aconst_null (0, 0)
	21 putfield (0, 0)
	22 org/apache/commons/math3/complex/RootsOfUnity.omegaImaginaryClockwise:[D (0, 0)
	24 aload_0 (0, 0)
	25 iconst_1 (0, 0)
	26 putfield (0, 0)
	27 org/apache/commons/math3/complex/RootsOfUnity.isCounterClockWise:Z (0, 0)
	29 return (0, 0)

Method: isCounterClockWise
	0 aload_0 (1, 1)
	1 getfield (1, 1)
	2 org/apache/commons/math3/complex/RootsOfUnity.omegaCount:I (1, 1)
	4 ifne (1, 1)
	5 18 (1, 1)
	7 new (1, 1)
	8 org/apache/commons/math3/exception/MathIllegalStateException (1, 1)
	10 dup (1, 1)
	11 getstatic (1, 1)
	12 org/apache/commons/math3/exception/util/LocalizedFormats.ROOTS_OF_UNITY_NOT_COMPUTED_YET:Lorg/apache/commons/math3/exception/util/LocalizedFormats; (1, 1)
	14 iconst_0 (1, 1)
	15 anewarray (1, 1)
	16 java/lang/Object (1, 1)
	18 invokespecial (1, 1)
	19 org/apache/commons/math3/exception/MathIllegalStateException.<init>:(Lorg/apache/commons/math3/exception/util/Localizable;[Ljava/lang/Object;)V (1, 1)
	21 athrow (1, 1)
	22 aload_0 (0, 0)
	23 getfield (0, 0)
	24 org/apache/commons/math3/complex/RootsOfUnity.isCounterClockWise:Z (0, 0)
	26 ireturn (0, 0)

Method: computeRoots
	0 iload_1 (1, 1)
	1 ifne (1, 1)
	2 18 (1, 1)
	4 new (1, 1)
	5 org/apache/commons/math3/exception/ZeroException (1, 1)
	7 dup (1, 1)
	8 getstatic (1, 1)
	9 org/apache/commons/math3/exception/util/LocalizedFormats.CANNOT_COMPUTE_0TH_ROOT_OF_UNITY:Lorg/apache/commons/math3/exception/util/LocalizedFormats; (1, 1)
	11 iconst_0 (1, 1)
	12 anewarray (1, 1)
	13 java/lang/Object (1, 1)
	15 invokespecial (1, 1)
	16 org/apache/commons/math3/exception/ZeroException.<init>:(Lorg/apache/commons/math3/exception/util/Localizable;[Ljava/lang/Object;)V (1, 1)
	18 athrow (1, 1)
	19 aload_0 (0, 0)
	20 iload_1 (0, 0)
	21 ifle (0, 0)
	22 7 (0, 0)
	24 iconst_1 (0, 0)
	25 goto (0, 0)
	26 4 (0, 0)
	28 iconst_0 (0, 0)
	29 putfield (0, 0)
	30 org/apache/commons/math3/complex/RootsOfUnity.isCounterClockWise:Z (0, 0)
	32 iload_1 (0, 0)
	33 invokestatic (0, 0)
	34 org/apache/commons/math3/util/FastMath.abs:(I)I (0, 0)
	36 istore_2 (0, 0)
	37 iload_2 (1, 1)
	38 aload_0 (1, 1)
	39 getfield (1, 1)
	40 org/apache/commons/math3/complex/RootsOfUnity.omegaCount:I (1, 1)
	42 if_icmpne (1, 1)
	43 4 (1, 1)
	45 return (1, 1)
	46 ldc2_w (0, 0)
	47 6.283185307179586 (0, 0)
	49 iload_2 (0, 0)
	50 i2d (0, 0)
	51 ddiv (0, 0)
	52 dstore_3 (0, 0)
	53 dload_3 (0, 0)
	54 invokestatic (0, 0)
	55 org/apache/commons/math3/util/FastMath.cos:(D)D (0, 0)
	57 dstore (0, 0)
	58 #5 (0, 0)
	59 dload_3 (0, 0)
	60 invokestatic (0, 0)
	61 org/apache/commons/math3/util/FastMath.sin:(D)D (0, 0)
	63 dstore (0, 0)
	64 #7 (0, 0)
	65 aload_0 (0, 0)
	66 iload_2 (0, 0)
	67 newarray (0, 0)
	68 7 (0, 0)
	69 putfield (0, 0)
	70 org/apache/commons/math3/complex/RootsOfUnity.omegaReal:[D (0, 0)
	72 aload_0 (0, 0)
	73 iload_2 (0, 0)
	74 newarray (0, 0)
	75 7 (0, 0)
	76 putfield (0, 0)
	77 org/apache/commons/math3/complex/RootsOfUnity.omegaImaginaryCounterClockwise:[D (0, 0)
	79 aload_0 (0, 0)
	80 iload_2 (0, 0)
	81 newarray (0, 0)
	82 7 (0, 0)
	83 putfield (0, 0)
	84 org/apache/commons/math3/complex/RootsOfUnity.omegaImaginaryClockwise:[D (0, 0)
	86 aload_0 (0, 0)
	87 getfield (0, 0)
	88 org/apache/commons/math3/complex/RootsOfUnity.omegaReal:[D (0, 0)
	90 iconst_0 (0, 0)
	91 dconst_1 (0, 0)
	92 dastore (0, 0)
	93 aload_0 (0, 0)
	94 getfield (0, 0)
	95 org/apache/commons/math3/complex/RootsOfUnity.omegaImaginaryCounterClockwise:[D (0, 0)
	97 iconst_0 (0, 0)
	98 dconst_0 (0, 0)
	99 dastore (0, 0)
	100 aload_0 (0, 0)
	101 getfield (0, 0)
	102 org/apache/commons/math3/complex/RootsOfUnity.omegaImaginaryClockwise:[D (0, 0)
	104 iconst_0 (0, 0)
	105 dconst_0 (0, 0)
	106 dastore (0, 0)
	107 iconst_1 (1, 4)
	108 istore (1, 4)
	109 #9 (1, 4)
	110 iload (1, 4)
	111 #9 (1, 4)
	112 iload_2 (1, 4)
	113 if_icmpge (1, 4)
	114 88 (1, 4)
	116 aload_0 (1, 4)
	117 getfield (1, 4)
	118 org/apache/commons/math3/complex/RootsOfUnity.omegaReal:[D (1, 4)
	120 iload (1, 4)
	121 #9 (1, 4)
	122 aload_0 (1, 4)
	123 getfield (1, 4)
	124 org/apache/commons/math3/complex/RootsOfUnity.omegaReal:[D (1, 4)
	126 iload (1, 4)
	127 #9 (1, 4)
	128 iconst_1 (1, 4)
	129 isub (1, 4)
	130 daload (1, 4)
	131 dload (1, 4)
	132 #5 (1, 4)
	133 dmul (1, 4)
	134 aload_0 (1, 4)
	135 getfield (1, 4)
	136 org/apache/commons/math3/complex/RootsOfUnity.omegaImaginaryCounterClockwise:[D (1, 4)
	138 iload (1, 4)
	139 #9 (1, 4)
	140 iconst_1 (1, 4)
	141 isub (1, 4)
	142 daload (1, 4)
	143 dload (1, 4)
	144 #7 (1, 4)
	145 dmul (1, 4)
	146 dsub (1, 4)
	147 dastore (1, 4)
	148 aload_0 (1, 4)
	149 getfield (1, 4)
	150 org/apache/commons/math3/complex/RootsOfUnity.omegaImaginaryCounterClockwise:[D (1, 4)
	152 iload (1, 4)
	153 #9 (1, 4)
	154 aload_0 (1, 4)
	155 getfield (1, 4)
	156 org/apache/commons/math3/complex/RootsOfUnity.omegaReal:[D (1, 4)
	158 iload (1, 4)
	159 #9 (1, 4)
	160 iconst_1 (1, 4)
	161 isub (1, 4)
	162 daload (1, 4)
	163 dload (1, 4)
	164 #7 (1, 4)
	165 dmul (1, 4)
	166 aload_0 (1, 4)
	167 getfield (1, 4)
	168 org/apache/commons/math3/complex/RootsOfUnity.omegaImaginaryCounterClockwise:[D (1, 4)
	170 iload (1, 4)
	171 #9 (1, 4)
	172 iconst_1 (1, 4)
	173 isub (1, 4)
	174 daload (1, 4)
	175 dload (1, 4)
	176 #5 (1, 4)
	177 dmul (1, 4)
	178 dadd (1, 4)
	179 dastore (1, 4)
	180 aload_0 (1, 4)
	181 getfield (1, 4)
	182 org/apache/commons/math3/complex/RootsOfUnity.omegaImaginaryClockwise:[D (1, 4)
	184 iload (1, 4)
	185 #9 (1, 4)
	186 aload_0 (1, 4)
	187 getfield (1, 4)
	188 org/apache/commons/math3/complex/RootsOfUnity.omegaImaginaryCounterClockwise:[D (1, 4)
	190 iload (1, 4)
	191 #9 (1, 4)
	192 daload (1, 4)
	193 dneg (1, 4)
	194 dastore (1, 4)
	195 iinc (1, 4)
	196 #9 (1, 4)
	197 -89 (1, 4)
	198 goto (1, 4)
	199 -88 (1, 4)
	201 aload_0 (0, 0)
	202 iload_2 (0, 0)
	203 putfield (0, 0)
	204 org/apache/commons/math3/complex/RootsOfUnity.omegaCount:I (0, 0)
	206 return (0, 0)

Method: getReal
	0 aload_0 (1, 1)
	1 getfield (1, 1)
	2 org/apache/commons/math3/complex/RootsOfUnity.omegaCount:I (1, 1)
	4 ifne (1, 1)
	5 18 (1, 1)
	7 new (1, 1)
	8 org/apache/commons/math3/exception/MathIllegalStateException (1, 1)
	10 dup (1, 1)
	11 getstatic (1, 1)
	12 org/apache/commons/math3/exception/util/LocalizedFormats.ROOTS_OF_UNITY_NOT_COMPUTED_YET:Lorg/apache/commons/math3/exception/util/LocalizedFormats; (1, 1)
	14 iconst_0 (1, 1)
	15 anewarray (1, 1)
	16 java/lang/Object (1, 1)
	18 invokespecial (1, 1)
	19 org/apache/commons/math3/exception/MathIllegalStateException.<init>:(Lorg/apache/commons/math3/exception/util/Localizable;[Ljava/lang/Object;)V (1, 1)
	21 athrow (1, 1)
	22 iload_1 (1, 1)
	23 iflt (1, 1)
	24 11 (1, 1)
	26 iload_1 (1, 1)
	27 aload_0 (1, 1)
	28 getfield (1, 1)
	29 org/apache/commons/math3/complex/RootsOfUnity.omegaCount:I (1, 1)
	31 if_icmplt (1, 1)
	32 31 (1, 1)
	34 new (1, 1)
	35 org/apache/commons/math3/exception/OutOfRangeException (1, 1)
	37 dup (1, 1)
	38 getstatic (1, 1)
	39 org/apache/commons/math3/exception/util/LocalizedFormats.OUT_OF_RANGE_ROOT_OF_UNITY_INDEX:Lorg/apache/commons/math3/exception/util/LocalizedFormats; (1, 1)
	41 iload_1 (1, 1)
	42 invokestatic (1, 1)
	43 java/lang/Integer.valueOf:(I)Ljava/lang/Integer; (1, 1)
	45 iconst_0 (1, 1)
	46 invokestatic (1, 1)
	47 java/lang/Integer.valueOf:(I)Ljava/lang/Integer; (1, 1)
	49 aload_0 (1, 1)
	50 getfield (1, 1)
	51 org/apache/commons/math3/complex/RootsOfUnity.omegaCount:I (1, 1)
	53 iconst_1 (1, 1)
	54 isub (1, 1)
	55 invokestatic (1, 1)
	56 java/lang/Integer.valueOf:(I)Ljava/lang/Integer; (1, 1)
	58 invokespecial (1, 1)
	59 org/apache/commons/math3/exception/OutOfRangeException.<init>:(Lorg/apache/commons/math3/exception/util/Localizable;Ljava/lang/Number;Ljava/lang/Number;Ljava/lang/Number;)V (1, 1)
	61 athrow (1, 1)
	62 aload_0 (0, 0)
	63 getfield (0, 0)
	64 org/apache/commons/math3/complex/RootsOfUnity.omegaReal:[D (0, 0)
	66 iload_1 (0, 0)
	67 daload (0, 0)
	68 dreturn (0, 0)

Method: getImaginary
	0 aload_0 (1, 1)
	1 getfield (1, 1)
	2 org/apache/commons/math3/complex/RootsOfUnity.omegaCount:I (1, 1)
	4 ifne (1, 1)
	5 18 (1, 1)
	7 new (1, 1)
	8 org/apache/commons/math3/exception/MathIllegalStateException (1, 1)
	10 dup (1, 1)
	11 getstatic (1, 1)
	12 org/apache/commons/math3/exception/util/LocalizedFormats.ROOTS_OF_UNITY_NOT_COMPUTED_YET:Lorg/apache/commons/math3/exception/util/LocalizedFormats; (1, 1)
	14 iconst_0 (1, 1)
	15 anewarray (1, 1)
	16 java/lang/Object (1, 1)
	18 invokespecial (1, 1)
	19 org/apache/commons/math3/exception/MathIllegalStateException.<init>:(Lorg/apache/commons/math3/exception/util/Localizable;[Ljava/lang/Object;)V (1, 1)
	21 athrow (1, 1)
	22 iload_1 (1, 1)
	23 iflt (1, 1)
	24 11 (1, 1)
	26 iload_1 (1, 1)
	27 aload_0 (1, 1)
	28 getfield (1, 1)
	29 org/apache/commons/math3/complex/RootsOfUnity.omegaCount:I (1, 1)
	31 if_icmplt (1, 1)
	32 31 (1, 1)
	34 new (1, 1)
	35 org/apache/commons/math3/exception/OutOfRangeException (1, 1)
	37 dup (1, 1)
	38 getstatic (1, 1)
	39 org/apache/commons/math3/exception/util/LocalizedFormats.OUT_OF_RANGE_ROOT_OF_UNITY_INDEX:Lorg/apache/commons/math3/exception/util/LocalizedFormats; (1, 1)
	41 iload_1 (1, 1)
	42 invokestatic (1, 1)
	43 java/lang/Integer.valueOf:(I)Ljava/lang/Integer; (1, 1)
	45 iconst_0 (1, 1)
	46 invokestatic (1, 1)
	47 java/lang/Integer.valueOf:(I)Ljava/lang/Integer; (1, 1)
	49 aload_0 (1, 1)
	50 getfield (1, 1)
	51 org/apache/commons/math3/complex/RootsOfUnity.omegaCount:I (1, 1)
	53 iconst_1 (1, 1)
	54 isub (1, 1)
	55 invokestatic (1, 1)
	56 java/lang/Integer.valueOf:(I)Ljava/lang/Integer; (1, 1)
	58 invokespecial (1, 1)
	59 org/apache/commons/math3/exception/OutOfRangeException.<init>:(Lorg/apache/commons/math3/exception/util/Localizable;Ljava/lang/Number;Ljava/lang/Number;Ljava/lang/Number;)V (1, 1)
	61 athrow (1, 1)
	62 aload_0 (0, 0)
	63 getfield (0, 0)
	64 org/apache/commons/math3/complex/RootsOfUnity.isCounterClockWise:Z (0, 0)
	66 ifeq (0, 0)
	67 12 (0, 0)
	69 aload_0 (0, 0)
	70 getfield (0, 0)
	71 org/apache/commons/math3/complex/RootsOfUnity.omegaImaginaryCounterClockwise:[D (0, 0)
	73 iload_1 (0, 0)
	74 daload (0, 0)
	75 goto (0, 0)
	76 9 (0, 0)
	78 aload_0 (0, 0)
	79 getfield (0, 0)
	80 org/apache/commons/math3/complex/RootsOfUnity.omegaImaginaryClockwise:[D (0, 0)
	82 iload_1 (0, 0)
	83 daload (0, 0)
	84 dreturn (0, 0)

Method: getNumberOfRoots
	0 aload_0 (0, 0)
	1 getfield (0, 0)
	2 org/apache/commons/math3/complex/RootsOfUnity.omegaCount:I (0, 0)
	4 ireturn (0, 0)

