Method: <init>
	0 aload_0 (0, 0)
	1 aload_1 (0, 0)
	2 putfield (0, 0)
	3 org/apache/commons/math3/optim/nonlinear/scalar/noderiv/CMAESOptimizer$FitnessFunction.this$0:Lorg/apache/commons/math3/optim/nonlinear/scalar/noderiv/CMAESOptimizer; (0, 0)
	5 aload_0 (0, 0)
	6 invokespecial (0, 0)
	7 java/lang/Object.<init>:()V (0, 0)
	9 aload_0 (0, 0)
	10 iconst_1 (0, 0)
	11 putfield (0, 0)
	12 org/apache/commons/math3/optim/nonlinear/scalar/noderiv/CMAESOptimizer$FitnessFunction.isRepairMode:Z (0, 0)
	14 return (0, 0)

Method: value
	0 dconst_0 (0, 0)
	1 dstore (0, 0)
	2 #4 (0, 0)
	3 aload_0 (1, 1)
	4 getfield (1, 1)
	5 org/apache/commons/math3/optim/nonlinear/scalar/noderiv/CMAESOptimizer$FitnessFunction.isRepairMode:Z (1, 1)
	7 ifeq (1, 1)
	8 32 (1, 1)
	10 aload_0 (1, 1)
	11 aload_1 (1, 1)
	12 invokespecial (1, 1)
	13 org/apache/commons/math3/optim/nonlinear/scalar/noderiv/CMAESOptimizer$FitnessFunction.repair:([D)[D (1, 1)
	15 astore (1, 1)
	16 #6 (1, 1)
	17 aload_0 (1, 1)
	18 getfield (1, 1)
	19 org/apache/commons/math3/optim/nonlinear/scalar/noderiv/CMAESOptimizer$FitnessFunction.this$0:Lorg/apache/commons/math3/optim/nonlinear/scalar/noderiv/CMAESOptimizer; (1, 1)
	21 aload (1, 1)
	22 #6 (1, 1)
	23 invokevirtual (1, 1)
	24 org/apache/commons/math3/optim/nonlinear/scalar/noderiv/CMAESOptimizer.computeObjectiveValue:([D)D (1, 1)
	26 dstore_2 (1, 1)
	27 aload_0 (1, 1)
	28 aload_1 (1, 1)
	29 aload (1, 1)
	30 #6 (1, 1)
	31 invokespecial (1, 1)
	32 org/apache/commons/math3/optim/nonlinear/scalar/noderiv/CMAESOptimizer$FitnessFunction.penalty:([D[D)D (1, 1)
	34 dstore (1, 1)
	35 #4 (1, 1)
	36 goto (2, 2)
	37 12 (2, 2)
	39 aload_0 (2, 2)
	40 getfield (2, 2)
	41 org/apache/commons/math3/optim/nonlinear/scalar/noderiv/CMAESOptimizer$FitnessFunction.this$0:Lorg/apache/commons/math3/optim/nonlinear/scalar/noderiv/CMAESOptimizer; (2, 2)
	43 aload_1 (2, 2)
	44 invokevirtual (2, 2)
	45 org/apache/commons/math3/optim/nonlinear/scalar/noderiv/CMAESOptimizer.computeObjectiveValue:([D)D (2, 2)
	47 dstore_2 (2, 2)
	48 aload_0 (0, 0)
	49 getfield (0, 0)
	50 org/apache/commons/math3/optim/nonlinear/scalar/noderiv/CMAESOptimizer$FitnessFunction.this$0:Lorg/apache/commons/math3/optim/nonlinear/scalar/noderiv/CMAESOptimizer; (0, 0)
	52 invokestatic (0, 0)
	53 org/apache/commons/math3/optim/nonlinear/scalar/noderiv/CMAESOptimizer.access$400:(Lorg/apache/commons/math3/optim/nonlinear/scalar/noderiv/CMAESOptimizer;)Z (0, 0)
	55 ifeq (0, 0)
	56 7 (0, 0)
	58 dload_2 (0, 0)
	59 goto (0, 0)
	60 5 (0, 0)
	62 dload_2 (0, 0)
	63 dneg (0, 0)
	64 dstore_2 (0, 0)
	65 aload_0 (0, 0)
	66 getfield (0, 0)
	67 org/apache/commons/math3/optim/nonlinear/scalar/noderiv/CMAESOptimizer$FitnessFunction.this$0:Lorg/apache/commons/math3/optim/nonlinear/scalar/noderiv/CMAESOptimizer; (0, 0)
	69 invokestatic (0, 0)
	70 org/apache/commons/math3/optim/nonlinear/scalar/noderiv/CMAESOptimizer.access$400:(Lorg/apache/commons/math3/optim/nonlinear/scalar/noderiv/CMAESOptimizer;)Z (0, 0)
	72 ifeq (0, 0)
	73 8 (0, 0)
	75 dload (0, 0)
	76 #4 (0, 0)
	77 goto (0, 0)
	78 6 (0, 0)
	80 dload (0, 0)
	81 #4 (0, 0)
	82 dneg (0, 0)
	83 dstore (0, 0)
	84 #4 (0, 0)
	85 new (0, 0)
	86 org/apache/commons/math3/optim/nonlinear/scalar/noderiv/CMAESOptimizer$ValuePenaltyPair (0, 0)
	88 dup (0, 0)
	89 dload_2 (0, 0)
	90 dload (0, 0)
	91 #4 (0, 0)
	92 invokespecial (0, 0)
	93 org/apache/commons/math3/optim/nonlinear/scalar/noderiv/CMAESOptimizer$ValuePenaltyPair.<init>:(DD)V (0, 0)
	95 areturn (0, 0)

Method: isFeasible
	0 aload_0 (0, 0)
	1 getfield (0, 0)
	2 org/apache/commons/math3/optim/nonlinear/scalar/noderiv/CMAESOptimizer$FitnessFunction.this$0:Lorg/apache/commons/math3/optim/nonlinear/scalar/noderiv/CMAESOptimizer; (0, 0)
	4 invokevirtual (0, 0)
	5 org/apache/commons/math3/optim/nonlinear/scalar/noderiv/CMAESOptimizer.getLowerBound:()[D (0, 0)
	7 astore_2 (0, 0)
	8 aload_0 (0, 0)
	9 getfield (0, 0)
	10 org/apache/commons/math3/optim/nonlinear/scalar/noderiv/CMAESOptimizer$FitnessFunction.this$0:Lorg/apache/commons/math3/optim/nonlinear/scalar/noderiv/CMAESOptimizer; (0, 0)
	12 invokevirtual (0, 0)
	13 org/apache/commons/math3/optim/nonlinear/scalar/noderiv/CMAESOptimizer.getUpperBound:()[D (0, 0)
	15 astore_3 (0, 0)
	16 iconst_0 (1, 4)
	17 istore (1, 4)
	18 #4 (1, 4)
	19 iload (1, 4)
	20 #4 (1, 4)
	21 aload_1 (1, 4)
	22 arraylength (1, 4)
	23 if_icmpge (1, 4)
	24 37 (1, 4)
	26 aload_1 (2, 1)
	27 iload (2, 1)
	28 #4 (2, 1)
	29 daload (2, 1)
	30 aload_2 (2, 1)
	31 iload (2, 1)
	32 #4 (2, 1)
	33 daload (2, 1)
	34 dcmpg (2, 1)
	35 ifge (2, 1)
	36 5 (2, 1)
	38 iconst_0 (2, 1)
	39 ireturn (2, 1)
	40 aload_1 (2, 1)
	41 iload (2, 1)
	42 #4 (2, 1)
	43 daload (2, 1)
	44 aload_3 (2, 1)
	45 iload (2, 1)
	46 #4 (2, 1)
	47 daload (2, 1)
	48 dcmpl (2, 1)
	49 ifle (2, 1)
	50 5 (2, 1)
	52 iconst_0 (2, 1)
	53 ireturn (2, 1)
	54 iinc (2, 1)
	55 #4 (2, 1)
	56 -89 (2, 1)
	57 goto (2, 1)
	58 -38 (2, 1)
	60 iconst_1 (1, 4)
	61 ireturn (1, 4)

Method: repair
	0 aload_0 (0, 0)
	1 getfield (0, 0)
	2 org/apache/commons/math3/optim/nonlinear/scalar/noderiv/CMAESOptimizer$FitnessFunction.this$0:Lorg/apache/commons/math3/optim/nonlinear/scalar/noderiv/CMAESOptimizer; (0, 0)
	4 invokevirtual (0, 0)
	5 org/apache/commons/math3/optim/nonlinear/scalar/noderiv/CMAESOptimizer.getLowerBound:()[D (0, 0)
	7 astore_2 (0, 0)
	8 aload_0 (0, 0)
	9 getfield (0, 0)
	10 org/apache/commons/math3/optim/nonlinear/scalar/noderiv/CMAESOptimizer$FitnessFunction.this$0:Lorg/apache/commons/math3/optim/nonlinear/scalar/noderiv/CMAESOptimizer; (0, 0)
	12 invokevirtual (0, 0)
	13 org/apache/commons/math3/optim/nonlinear/scalar/noderiv/CMAESOptimizer.getUpperBound:()[D (0, 0)
	15 astore_3 (0, 0)
	16 aload_1 (0, 0)
	17 arraylength (0, 0)
	18 newarray (0, 0)
	19 7 (0, 0)
	20 astore (0, 0)
	21 #4 (0, 0)
	22 iconst_0 (1, 4)
	23 istore (1, 4)
	24 #5 (1, 4)
	25 iload (1, 4)
	26 #5 (1, 4)
	27 aload_1 (1, 4)
	28 arraylength (1, 4)
	29 if_icmpge (1, 4)
	30 66 (1, 4)
	32 aload_1 (2, 1)
	33 iload (2, 1)
	34 #5 (2, 1)
	35 daload (2, 1)
	36 aload_2 (2, 1)
	37 iload (2, 1)
	38 #5 (2, 1)
	39 daload (2, 1)
	40 dcmpg (2, 1)
	41 ifge (2, 1)
	42 15 (2, 1)
	44 aload (2, 1)
	45 #4 (2, 1)
	46 iload (2, 1)
	47 #5 (2, 1)
	48 aload_2 (2, 1)
	49 iload (2, 1)
	50 #5 (2, 1)
	51 daload (2, 1)
	52 dastore (2, 1)
	53 goto (2, 1)
	54 36 (2, 1)
	56 aload_1 (3, 1)
	57 iload (3, 1)
	58 #5 (3, 1)
	59 daload (3, 1)
	60 aload_3 (3, 1)
	61 iload (3, 1)
	62 #5 (3, 1)
	63 daload (3, 1)
	64 dcmpl (3, 1)
	65 ifle (3, 1)
	66 15 (3, 1)
	68 aload (3, 1)
	69 #4 (3, 1)
	70 iload (3, 1)
	71 #5 (3, 1)
	72 aload_3 (3, 1)
	73 iload (3, 1)
	74 #5 (3, 1)
	75 daload (3, 1)
	76 dastore (3, 1)
	77 goto (3, 1)
	78 12 (3, 1)
	80 aload (4, 2)
	81 #4 (4, 2)
	82 iload (4, 2)
	83 #5 (4, 2)
	84 aload_1 (4, 2)
	85 iload (4, 2)
	86 #5 (4, 2)
	87 daload (4, 2)
	88 dastore (4, 2)
	89 iinc (4, 2)
	90 #5 (4, 2)
	91 -89 (4, 2)
	92 goto (4, 2)
	93 -67 (4, 2)
	95 aload (1, 4)
	96 #4 (1, 4)
	97 areturn (1, 4)

Method: penalty
	0 dconst_0 (0, 0)
	1 dstore_3 (0, 0)
	2 iconst_0 (1, 4)
	3 istore (1, 4)
	4 #5 (1, 4)
	5 iload (1, 4)
	6 #5 (1, 4)
	7 aload_1 (1, 4)
	8 arraylength (1, 4)
	9 if_icmpge (1, 4)
	10 28 (1, 4)
	12 aload_1 (2, 1)
	13 iload (2, 1)
	14 #5 (2, 1)
	15 daload (2, 1)
	16 aload_2 (2, 1)
	17 iload (2, 1)
	18 #5 (2, 1)
	19 daload (2, 1)
	20 dsub (2, 1)
	21 invokestatic (2, 1)
	22 org/apache/commons/math3/util/FastMath.abs:(D)D (2, 1)
	24 dstore (2, 1)
	25 #6 (2, 1)
	26 dload_3 (3, 1)
	27 dload (3, 1)
	28 #6 (3, 1)
	29 dadd (3, 1)
	30 dstore_3 (3, 1)
	31 iinc (3, 1)
	32 #5 (3, 1)
	33 -89 (3, 1)
	34 goto (3, 1)
	35 -29 (3, 1)
	37 aload_0 (0, 0)
	38 getfield (0, 0)
	39 org/apache/commons/math3/optim/nonlinear/scalar/noderiv/CMAESOptimizer$FitnessFunction.this$0:Lorg/apache/commons/math3/optim/nonlinear/scalar/noderiv/CMAESOptimizer; (0, 0)
	41 invokestatic (0, 0)
	42 org/apache/commons/math3/optim/nonlinear/scalar/noderiv/CMAESOptimizer.access$400:(Lorg/apache/commons/math3/optim/nonlinear/scalar/noderiv/CMAESOptimizer;)Z (0, 0)
	44 ifeq (0, 0)
	45 7 (0, 0)
	47 dload_3 (0, 0)
	48 goto (0, 0)
	49 5 (0, 0)
	51 dload_3 (0, 0)
	52 dneg (0, 0)
	53 dreturn (0, 0)

Method: access$200
	0 aload_0 (0, 0)
	1 aload_1 (0, 0)
	2 invokespecial (0, 0)
	3 org/apache/commons/math3/optim/nonlinear/scalar/noderiv/CMAESOptimizer$FitnessFunction.repair:([D)[D (0, 0)
	5 areturn (0, 0)

