Method: <init>
	0 aload_0 (0, 0)
	1 aload_1 (0, 0)
	2 invokespecial (0, 0)
	3 org/apache/commons/math3/optim/nonlinear/scalar/noderiv/AbstractSimplex.<init>:([[D)V (0, 0)
	5 aload_0 (0, 0)
	6 dload_2 (0, 0)
	7 putfield (0, 0)
	8 org/apache/commons/math3/optim/nonlinear/scalar/noderiv/MultiDirectionalSimplex.khi:D (0, 0)
	10 aload_0 (0, 0)
	11 dload (0, 0)
	12 #4 (0, 0)
	13 putfield (0, 0)
	14 org/apache/commons/math3/optim/nonlinear/scalar/noderiv/MultiDirectionalSimplex.gamma:D (0, 0)
	16 return (0, 0)

Method: iterate
	0 aload_0 (0, 0)
	1 invokevirtual (0, 0)
	2 org/apache/commons/math3/optim/nonlinear/scalar/noderiv/MultiDirectionalSimplex.getPoints:()[Lorg/apache/commons/math3/optim/PointValuePair; (0, 0)
	4 astore_3 (0, 0)
	5 aload_3 (0, 0)
	6 iconst_0 (0, 0)
	7 aaload (0, 0)
	8 astore (0, 0)
	9 #4 (0, 0)
	10 aload_0 (0, 4)
	11 aload_1 (0, 4)
	12 aload_3 (0, 4)
	13 dconst_1 (0, 4)
	14 aload_2 (0, 4)
	15 invokespecial (0, 4)
	16 org/apache/commons/math3/optim/nonlinear/scalar/noderiv/MultiDirectionalSimplex.evaluateNewSimplex:(Lorg/apache/commons/math3/analysis/MultivariateFunction;[Lorg/apache/commons/math3/optim/PointValuePair;DLjava/util/Comparator;)Lorg/apache/commons/math3/optim/PointValuePair; (0, 4)
	18 astore (0, 4)
	19 #5 (0, 4)
	20 aload_2 (1, 1)
	21 aload (1, 1)
	22 #5 (1, 1)
	23 aload (1, 1)
	24 #4 (1, 1)
	25 invokeinterface (1, 1)
	26 java/util/Comparator.setPoints:([Lorg/apache/commons/math3/optim/PointValuePair;)V (1, 1)
	28 0 (1, 1)
	30 ifge (1, 1)
	31 42 (1, 1)
	33 aload_0 (1, 1)
	34 invokevirtual (1, 1)
	35 org/apache/commons/math3/optim/nonlinear/scalar/noderiv/MultiDirectionalSimplex.getPoints:()[Lorg/apache/commons/math3/optim/PointValuePair; (1, 1)
	37 astore (1, 1)
	38 #6 (1, 1)
	39 aload_0 (1, 1)
	40 aload_1 (1, 1)
	41 aload_3 (1, 1)
	42 aload_0 (1, 1)
	43 getfield (1, 1)
	44 org/apache/commons/math3/optim/nonlinear/scalar/noderiv/MultiDirectionalSimplex.khi:D (1, 1)
	46 aload_2 (1, 1)
	47 invokespecial (1, 1)
	48 org/apache/commons/math3/optim/nonlinear/scalar/noderiv/MultiDirectionalSimplex.evaluateNewSimplex:(Lorg/apache/commons/math3/analysis/MultivariateFunction;[Lorg/apache/commons/math3/optim/PointValuePair;DLjava/util/Comparator;)Lorg/apache/commons/math3/optim/PointValuePair; (1, 1)
	50 astore (1, 1)
	51 #7 (1, 1)
	52 aload_2 (2, 1)
	53 aload (2, 1)
	54 #5 (2, 1)
	55 aload (2, 1)
	56 #7 (2, 1)
	57 invokeinterface (2, 1)
	58 java/util/Comparator.setPoints:([Lorg/apache/commons/math3/optim/PointValuePair;)V (2, 1)
	60 0 (2, 1)
	62 ifgt (2, 1)
	63 9 (2, 1)
	65 aload_0 (2, 1)
	66 aload (2, 1)
	67 #6 (2, 1)
	68 invokevirtual (2, 1)
	69 org/apache/commons/math3/optim/nonlinear/scalar/noderiv/MultiDirectionalSimplex.setPoints:([Lorg/apache/commons/math3/optim/PointValuePair;)V (2, 1)
	71 return (1, 1)
	72 aload_0 (0, 4)
	73 aload_1 (0, 4)
	74 aload_3 (0, 4)
	75 aload_0 (0, 4)
	76 getfield (0, 4)
	77 org/apache/commons/math3/optim/nonlinear/scalar/noderiv/MultiDirectionalSimplex.gamma:D (0, 4)
	79 aload_2 (0, 4)
	80 invokespecial (0, 4)
	81 org/apache/commons/math3/optim/nonlinear/scalar/noderiv/MultiDirectionalSimplex.evaluateNewSimplex:(Lorg/apache/commons/math3/analysis/MultivariateFunction;[Lorg/apache/commons/math3/optim/PointValuePair;DLjava/util/Comparator;)Lorg/apache/commons/math3/optim/PointValuePair; (0, 4)
	83 pop (0, 4)
	84 return (0, 4)

Method: evaluateNewSimplex
	0 aload_2 (0, 0)
	1 iconst_0 (0, 0)
	2 aaload (0, 0)
	3 invokevirtual (0, 0)
	4 org/apache/commons/math3/optim/PointValuePair.getPointRef:()[D (0, 0)
	6 astore (0, 0)
	7 #6 (0, 0)
	8 aload_0 (0, 4)
	9 iconst_0 (0, 4)
	10 aload_2 (0, 4)
	11 iconst_0 (0, 4)
	12 aaload (0, 4)
	13 invokevirtual (0, 4)
	14 org/apache/commons/math3/optim/nonlinear/scalar/noderiv/MultiDirectionalSimplex.setPoint:(ILorg/apache/commons/math3/optim/PointValuePair;)V (0, 4)
	16 aload_0 (0, 4)
	17 invokevirtual (0, 4)
	18 org/apache/commons/math3/optim/nonlinear/scalar/noderiv/MultiDirectionalSimplex.getDimension:()I (0, 4)
	20 istore (0, 4)
	21 #7 (0, 4)
	22 iconst_1 (1, 4)
	23 istore (1, 4)
	24 #8 (1, 4)
	25 iload (1, 4)
	26 #8 (1, 4)
	27 aload_0 (1, 4)
	28 invokevirtual (1, 4)
	29 org/apache/commons/math3/optim/nonlinear/scalar/noderiv/MultiDirectionalSimplex.getSize:()I (1, 4)
	31 if_icmpge (1, 4)
	32 83 (1, 4)
	34 aload_2 (1, 4)
	35 iload (1, 4)
	36 #8 (1, 4)
	37 aaload (1, 4)
	38 invokevirtual (1, 4)
	39 org/apache/commons/math3/optim/PointValuePair.getPointRef:()[D (1, 4)
	41 astore (1, 4)
	42 #9 (1, 4)
	43 iload (1, 4)
	44 #7 (1, 4)
	45 newarray (1, 4)
	46 7 (1, 4)
	47 astore (1, 4)
	48 #10 (1, 4)
	49 iconst_0 (2, 4)
	50 istore (2, 4)
	51 #11 (2, 4)
	52 iload (2, 4)
	53 #11 (2, 4)
	54 iload (2, 4)
	55 #7 (2, 4)
	56 if_icmpge (2, 4)
	57 33 (2, 4)
	59 aload (2, 4)
	60 #10 (2, 4)
	61 iload (2, 4)
	62 #11 (2, 4)
	63 aload (2, 4)
	64 #6 (2, 4)
	65 iload (2, 4)
	66 #11 (2, 4)
	67 daload (2, 4)
	68 dload_3 (2, 4)
	69 aload (2, 4)
	70 #6 (2, 4)
	71 iload (2, 4)
	72 #11 (2, 4)
	73 daload (2, 4)
	74 aload (2, 4)
	75 #9 (2, 4)
	76 iload (2, 4)
	77 #11 (2, 4)
	78 daload (2, 4)
	79 dsub (2, 4)
	80 dmul (2, 4)
	81 dadd (2, 4)
	82 dastore (2, 4)
	83 iinc (2, 4)
	84 #11 (2, 4)
	85 -89 (2, 4)
	86 goto (2, 4)
	87 -34 (2, 4)
	89 aload_0 (1, 4)
	90 iload (1, 4)
	91 #8 (1, 4)
	92 new (1, 4)
	93 org/apache/commons/math3/optim/PointValuePair (1, 4)
	95 dup (1, 4)
	96 aload (1, 4)
	97 #10 (1, 4)
	98 ldc2_w (1, 4)
	99 nan (1, 4)
	101 iconst_0 (1, 4)
	102 invokespecial (1, 4)
	103 org/apache/commons/math3/optim/PointValuePair.<init>:([DDZ)V (1, 4)
	105 invokevirtual (1, 4)
	106 org/apache/commons/math3/optim/nonlinear/scalar/noderiv/MultiDirectionalSimplex.setPoint:(ILorg/apache/commons/math3/optim/PointValuePair;)V (1, 4)
	108 iinc (1, 4)
	109 #8 (1, 4)
	110 -89 (1, 4)
	111 goto (1, 4)
	112 -86 (1, 4)
	114 aload_0 (0, 4)
	115 aload_1 (0, 4)
	116 aload (0, 4)
	117 #5 (0, 4)
	118 invokevirtual (0, 4)
	119 org/apache/commons/math3/optim/nonlinear/scalar/noderiv/MultiDirectionalSimplex.evaluate:(Lorg/apache/commons/math3/analysis/MultivariateFunction;Ljava/util/Comparator;)V (0, 4)
	121 aload_0 (0, 4)
	122 iconst_0 (0, 4)
	123 invokevirtual (0, 4)
	124 org/apache/commons/math3/optim/nonlinear/scalar/noderiv/MultiDirectionalSimplex.getPoint:(I)Lorg/apache/commons/math3/optim/PointValuePair; (0, 4)
	126 areturn (0, 4)

