Method: <init>
	0 aload_0 (0, 0)
	1 dload_1 (0, 0)
	2 dload_3 (0, 0)
	3 dload (0, 0)
	4 #5 (0, 0)
	5 dload (0, 0)
	6 #7 (0, 0)
	7 aconst_null (0, 0)
	8 invokespecial (0, 0)
	9 org/apache/commons/math3/optim/nonlinear/scalar/noderiv/PowellOptimizer.<init>:(DDDDLorg/apache/commons/math3/optim/ConvergenceChecker;)V (0, 0)
	11 return (0, 0)

Method: doOptimize
	0 aload_0 (0, 0)
	1 invokevirtual (0, 0)
	2 org/apache/commons/math3/optim/nonlinear/scalar/noderiv/PowellOptimizer.doOptimize:()Lorg/apache/commons/math3/optim/PointValuePair; (0, 0)
	4 areturn (0, 0)

Method: newPointAndDirection
	0 aload_1 (0, 0)
	1 arraylength (0, 0)
	2 istore (0, 0)
	3 #5 (0, 0)
	4 iload (0, 0)
	5 #5 (0, 0)
	6 newarray (0, 0)
	7 7 (0, 0)
	8 astore (0, 0)
	9 #6 (0, 0)
	10 iload (0, 0)
	11 #5 (0, 0)
	12 newarray (0, 0)
	13 7 (0, 0)
	14 astore (0, 0)
	15 #7 (0, 0)
	16 iconst_0 (1, 4)
	17 istore (1, 4)
	18 #8 (1, 4)
	19 iload (1, 4)
	20 #8 (1, 4)
	21 iload (1, 4)
	22 #5 (1, 4)
	23 if_icmpge (1, 4)
	24 35 (1, 4)
	26 aload (1, 4)
	27 #7 (1, 4)
	28 iload (1, 4)
	29 #8 (1, 4)
	30 aload_2 (1, 4)
	31 iload (1, 4)
	32 #8 (1, 4)
	33 daload (1, 4)
	34 dload_3 (1, 4)
	35 dmul (1, 4)
	36 dastore (1, 4)
	37 aload (1, 4)
	38 #6 (1, 4)
	39 iload (1, 4)
	40 #8 (1, 4)
	41 aload_1 (1, 4)
	42 iload (1, 4)
	43 #8 (1, 4)
	44 daload (1, 4)
	45 aload (1, 4)
	46 #7 (1, 4)
	47 iload (1, 4)
	48 #8 (1, 4)
	49 daload (1, 4)
	50 dadd (1, 4)
	51 dastore (1, 4)
	52 iinc (1, 4)
	53 #8 (1, 4)
	54 -89 (1, 4)
	55 goto (1, 4)
	56 -36 (1, 4)
	58 iconst_2 (0, 0)
	59 anewarray (0, 0)
	60 [D (0, 0)
	62 astore (0, 0)
	63 #8 (0, 0)
	64 aload (0, 0)
	65 #8 (0, 0)
	66 iconst_0 (0, 0)
	67 aload (0, 0)
	68 #6 (0, 0)
	69 aastore (0, 0)
	70 aload (0, 0)
	71 #8 (0, 0)
	72 iconst_1 (0, 0)
	73 aload (0, 0)
	74 #7 (0, 0)
	75 aastore (0, 0)
	76 aload (0, 0)
	77 #8 (0, 0)
	78 areturn (0, 0)

Method: checkParameters
	0 aload_0 (1, 1)
	1 invokevirtual (1, 1)
	2 org/apache/commons/math3/optim/nonlinear/scalar/noderiv/PowellOptimizer.getLowerBound:()[D (1, 1)
	4 ifnonnull (1, 1)
	5 10 (1, 1)
	7 aload_0 (1, 1)
	8 invokevirtual (1, 1)
	9 org/apache/commons/math3/optim/nonlinear/scalar/noderiv/PowellOptimizer.getUpperBound:()[D (1, 1)
	11 ifnull (1, 1)
	12 18 (1, 1)
	14 new (1, 1)
	15 org/apache/commons/math3/exception/MathUnsupportedOperationException (1, 1)
	17 dup (1, 1)
	18 getstatic (1, 1)
	19 org/apache/commons/math3/exception/util/LocalizedFormats.CONSTRAINT:Lorg/apache/commons/math3/exception/util/LocalizedFormats; (1, 1)
	21 iconst_0 (1, 1)
	22 anewarray (1, 1)
	23 java/lang/Object (1, 1)
	25 invokespecial (1, 1)
	26 org/apache/commons/math3/exception/MathUnsupportedOperationException.<init>:(Lorg/apache/commons/math3/exception/util/Localizable;[Ljava/lang/Object;)V (1, 1)
	28 athrow (1, 1)
	29 return (0, 1)

Method: <clinit>
	0 ldc2_w (0, 0)
	1 2.0 (0, 0)
	3 dconst_1 (0, 0)
	4 invokestatic (0, 0)
	5 org/apache/commons/math3/util/FastMath.ulp:(D)D (0, 0)
	7 dmul (0, 0)
	8 putstatic (0, 0)
	9 org/apache/commons/math3/optim/nonlinear/scalar/noderiv/PowellOptimizer.MIN_RELATIVE_TOLERANCE:D (0, 0)
	11 return (0, 0)

