Method: <init>
	0 aload_0 (0, 0)
	1 new (0, 0)
	2 org/apache/commons/math3/optim/SimpleValueChecker (0, 0)
	4 dup (0, 0)
	5 dload_1 (0, 0)
	6 dload_3 (0, 0)
	7 invokespecial (0, 0)
	8 org/apache/commons/math3/optim/SimpleValueChecker.<init>:(DD)V (0, 0)
	10 invokespecial (0, 0)
	11 org/apache/commons/math3/optim/nonlinear/scalar/noderiv/SimplexOptimizer.<init>:(Lorg/apache/commons/math3/optim/ConvergenceChecker;)V (0, 0)
	13 return (0, 0)

Method: optimize
	0 aload_0 (0, 0)
	1 aload_1 (0, 0)
	2 invokevirtual (0, 0)
	3 org/apache/commons/math3/optim/nonlinear/scalar/noderiv/SimplexOptimizer.optimize:([Lorg/apache/commons/math3/optim/OptimizationData;)Lorg/apache/commons/math3/optim/PointValuePair; (0, 0)
	5 areturn (0, 0)

Method: doOptimize
	0 aload_0 (0, 0)
	1 invokevirtual (0, 0)
	2 org/apache/commons/math3/optim/nonlinear/scalar/noderiv/SimplexOptimizer.doOptimize:()Lorg/apache/commons/math3/optim/PointValuePair; (0, 0)
	4 areturn (0, 0)

Method: parseOptimizationData
	0 aload_0 (0, 0)
	1 aload_1 (0, 0)
	2 invokespecial (0, 0)
	3 org/apache/commons/math3/optim/nonlinear/scalar/MultivariateOptimizer.parseOptimizationData:([Lorg/apache/commons/math3/optim/OptimizationData;)V (0, 0)
	5 aload_1 (1, 4)
	6 astore_2 (1, 4)
	7 aload_2 (1, 4)
	8 arraylength (1, 4)
	9 istore_3 (1, 4)
	10 iconst_0 (1, 4)
	11 istore (1, 4)
	12 #4 (1, 4)
	13 iload (1, 4)
	14 #4 (1, 4)
	15 iload_3 (1, 4)
	16 if_icmpge (1, 4)
	17 35 (1, 4)
	19 aload_2 (1, 4)
	20 iload (1, 4)
	21 #4 (1, 4)
	22 aaload (1, 4)
	23 astore (1, 4)
	24 #5 (1, 4)
	25 aload (2, 1)
	26 #5 (2, 1)
	27 instanceof (2, 1)
	28 org/apache/commons/math3/optim/nonlinear/scalar/noderiv/AbstractSimplex (2, 1)
	30 ifeq (2, 1)
	31 15 (2, 1)
	33 aload_0 (2, 1)
	34 aload (2, 1)
	35 #5 (2, 1)
	36 checkcast (2, 1)
	37 org/apache/commons/math3/optim/nonlinear/scalar/noderiv/AbstractSimplex (2, 1)
	39 putfield (2, 1)
	40 org/apache/commons/math3/optim/nonlinear/scalar/noderiv/SimplexOptimizer.simplex:Lorg/apache/commons/math3/optim/nonlinear/scalar/noderiv/AbstractSimplex; (2, 1)
	42 goto (2, 1)
	43 9 (2, 1)
	45 iinc (2, 1)
	46 #4 (2, 1)
	47 -89 (2, 1)
	48 goto (2, 1)
	49 -35 (2, 1)
	51 return (0, 1)

Method: checkParameters
	0 aload_0 (1, 1)
	1 getfield (1, 1)
	2 org/apache/commons/math3/optim/nonlinear/scalar/noderiv/SimplexOptimizer.simplex:Lorg/apache/commons/math3/optim/nonlinear/scalar/noderiv/AbstractSimplex; (1, 1)
	4 ifnonnull (1, 1)
	5 11 (1, 1)
	7 new (1, 1)
	8 org/apache/commons/math3/exception/NullArgumentException (1, 1)
	10 dup (1, 1)
	11 invokespecial (1, 1)
	12 org/apache/commons/math3/exception/NullArgumentException.<init>:()V (1, 1)
	14 athrow (1, 1)
	15 aload_0 (0, 1)
	16 invokevirtual (0, 1)
	17 org/apache/commons/math3/optim/nonlinear/scalar/noderiv/SimplexOptimizer.getLowerBound:()[D (0, 1)
	19 ifnonnull (0, 1)
	20 10 (0, 1)
	22 aload_0 (0, 1)
	23 invokevirtual (0, 1)
	24 org/apache/commons/math3/optim/nonlinear/scalar/noderiv/SimplexOptimizer.getUpperBound:()[D (0, 1)
	26 ifnull (0, 1)
	27 18 (0, 1)
	29 new (0, 1)
	30 org/apache/commons/math3/exception/MathUnsupportedOperationException (0, 1)
	32 dup (0, 1)
	33 getstatic (0, 1)
	34 org/apache/commons/math3/exception/util/LocalizedFormats.CONSTRAINT:Lorg/apache/commons/math3/exception/util/LocalizedFormats; (0, 1)
	36 iconst_0 (0, 1)
	37 anewarray (0, 1)
	38 java/lang/Object (0, 1)
	40 invokespecial (0, 1)
	41 org/apache/commons/math3/exception/MathUnsupportedOperationException.<init>:(Lorg/apache/commons/math3/exception/util/Localizable;[Ljava/lang/Object;)V (0, 1)
	43 athrow (0, 1)
	44 return (0, 1)

