Method: <init>
	0 aload_0 (0, 0)
	1 aload_1 (0, 0)
	2 putfield (0, 0)
	5 aload_0 (0, 0)
	6 invokespecial (0, 0)
	9 aload_0 (0, 0)
	10 new (0, 0)
	13 dup (0, 0)
	14 aload_0 (0, 0)
	15 getfield (0, 0)
	18 invokestatic (0, 0)
	21 invokevirtual (0, 0)
	24 iconst_0 (0, 0)
	25 invokespecial (0, 0)
	28 putfield (0, 0)
	31 aload_0 (0, 0)
	32 aload_0 (0, 0)
	33 getfield (0, 0)
	36 invokestatic (0, 0)
	39 invokevirtual (0, 0)
	42 putfield (0, 0)
	45 return (0, 0)

Method: compare
	0 aload_0 (0, 0)
	1 aload_1 (0, 0)
	2 checkcast (0, 0)
	5 aload_2 (0, 0)
	6 checkcast (0, 0)
	9 invokevirtual (0, 0)
	12 ireturn (0, 0)

Method: weightedResidual
	0 new (0, 0)
	3 dup (0, 0)
	4 aload_1 (0, 0)
	5 invokevirtual (0, 0)
	8 iconst_0 (0, 0)
	9 invokespecial (0, 0)
	12 astore_2 (0, 0)
	13 aload_0 (0, 0)
	14 getfield (0, 0)
	17 aload_2 (0, 0)
	18 invokevirtual (0, 0)
	21 astore_3 (0, 0)
	22 aload_3 (0, 0)
	23 aload_0 (0, 0)
	24 getfield (0, 0)
	27 aload_3 (0, 0)
	28 invokeinterface (0, 0)
	33 invokevirtual (0, 0)
	36 dreturn (0, 0)

