Method: <init>
	0 aload_0 (0, 0)
	1 aload_1 (0, 0)
	2 invokespecial (0, 0)
	3 org/apache/commons/math3/optim/BaseMultivariateOptimizer.<init>:(Lorg/apache/commons/math3/optim/ConvergenceChecker;)V (0, 0)
	5 return (0, 0)

Method: computeObjectiveValue
	0 aload_0 (0, 0)
	1 invokespecial (0, 0)
	2 org/apache/commons/math3/optim/BaseMultivariateOptimizer.incrementEvaluationCount:()V (0, 0)
	4 aload_0 (0, 0)
	5 getfield (0, 0)
	6 org/apache/commons/math3/optim/nonlinear/vector/MultivariateVectorOptimizer.model:Lorg/apache/commons/math3/analysis/MultivariateVectorFunction; (0, 0)
	8 aload_1 (0, 0)
	9 invokeinterface (0, 0)
	10 org/apache/commons/math3/analysis/MultivariateVectorFunction.optimize:([Lorg/apache/commons/math3/optim/OptimizationData;)Ljava/lang/Object; (0, 0)
	12 0 (0, 0)
	14 areturn (0, 0)

Method: optimize
	0 aload_0 (0, 0)
	1 aload_1 (0, 0)
	2 invokevirtual (0, 0)
	3 org/apache/commons/math3/optim/nonlinear/vector/MultivariateVectorOptimizer.optimize:([Lorg/apache/commons/math3/optim/OptimizationData;)Lorg/apache/commons/math3/optim/PointVectorValuePair; (0, 0)
	5 areturn (0, 0)

Method: getWeight
	0 aload_0 (0, 0)
	1 getfield (0, 0)
	2 org/apache/commons/math3/optim/nonlinear/vector/MultivariateVectorOptimizer.weightMatrix:Lorg/apache/commons/math3/linear/RealMatrix; (0, 0)
	4 invokeinterface (0, 0)
	5 org/apache/commons/math3/linear/RealMatrix.target:[D (0, 0)
	7 0 (0, 0)
	9 areturn (0, 0)

Method: getTarget
	0 aload_0 (0, 0)
	1 getfield (0, 0)
	2 org/apache/commons/math3/optim/nonlinear/vector/MultivariateVectorOptimizer.target:[D (0, 0)
	4 invokevirtual (0, 0)
	5 [D.clone:()Ljava/lang/Object; (0, 0)
	7 checkcast (0, 0)
	8 [D (0, 0)
	10 areturn (0, 0)

Method: getTargetSize
	0 aload_0 (0, 0)
	1 getfield (0, 0)
	2 org/apache/commons/math3/optim/nonlinear/vector/MultivariateVectorOptimizer.target:[D (0, 0)
	4 arraylength (0, 0)
	5 ireturn (0, 0)

Method: parseOptimizationData
	0 aload_0 (0, 0)
	1 aload_1 (0, 0)
	2 invokespecial (0, 0)
	3 org/apache/commons/math3/optim/BaseMultivariateOptimizer.parseOptimizationData:([Lorg/apache/commons/math3/optim/OptimizationData;)V (0, 0)
	5 aload_1 (2, 4)
	6 astore_2 (2, 4)
	7 aload_2 (2, 4)
	8 arraylength (2, 4)
	9 istore_3 (2, 4)
	10 iconst_0 (2, 4)
	11 istore (2, 4)
	12 #4 (2, 4)
	13 iload (2, 4)
	14 #4 (2, 4)
	15 iload_3 (2, 4)
	16 if_icmpge (2, 4)
	17 84 (2, 4)
	19 aload_2 (2, 4)
	20 iload (2, 4)
	21 #4 (2, 4)
	22 aaload (2, 4)
	23 astore (2, 4)
	24 #5 (2, 4)
	25 aload (3, 1)
	26 #5 (3, 1)
	27 instanceof (3, 1)
	28 org/apache/commons/math3/optim/nonlinear/vector/ModelFunction (3, 1)
	30 ifeq (3, 1)
	31 18 (3, 1)
	33 aload_0 (3, 1)
	34 aload (3, 1)
	35 #5 (3, 1)
	36 checkcast (3, 1)
	37 org/apache/commons/math3/optim/nonlinear/vector/ModelFunction (3, 1)
	39 invokevirtual (3, 1)
	40 org/apache/commons/math3/optim/nonlinear/vector/ModelFunction.getModelFunction:()Lorg/apache/commons/math3/analysis/MultivariateVectorFunction; (3, 1)
	42 putfield (3, 1)
	43 org/apache/commons/math3/optim/nonlinear/vector/MultivariateVectorOptimizer.model:Lorg/apache/commons/math3/analysis/MultivariateVectorFunction; (3, 1)
	45 goto (3, 1)
	46 49 (3, 1)
	48 aload (3, 1)
	49 #5 (3, 1)
	50 instanceof (3, 1)
	51 org/apache/commons/math3/optim/nonlinear/vector/Target (3, 1)
	53 ifeq (3, 1)
	54 18 (3, 1)
	56 aload_0 (3, 1)
	57 aload (3, 1)
	58 #5 (3, 1)
	59 checkcast (3, 1)
	60 org/apache/commons/math3/optim/nonlinear/vector/Target (3, 1)
	62 invokevirtual (3, 1)
	63 org/apache/commons/math3/optim/nonlinear/vector/Target.getTarget:()[D (3, 1)
	65 putfield (3, 1)
	66 org/apache/commons/math3/optim/nonlinear/vector/MultivariateVectorOptimizer.target:[D (3, 1)
	68 goto (3, 1)
	69 26 (3, 1)
	71 aload (3, 1)
	72 #5 (3, 1)
	73 instanceof (3, 1)
	74 org/apache/commons/math3/optim/nonlinear/vector/Weight (3, 1)
	76 ifeq (3, 1)
	77 18 (3, 1)
	79 aload_0 (3, 1)
	80 aload (3, 1)
	81 #5 (3, 1)
	82 checkcast (3, 1)
	83 org/apache/commons/math3/optim/nonlinear/vector/Weight (3, 1)
	85 invokevirtual (3, 1)
	86 org/apache/commons/math3/optim/nonlinear/vector/Weight.getWeight:()Lorg/apache/commons/math3/linear/RealMatrix; (3, 1)
	88 putfield (3, 1)
	89 org/apache/commons/math3/optim/nonlinear/vector/MultivariateVectorOptimizer.weightMatrix:Lorg/apache/commons/math3/linear/RealMatrix; (3, 1)
	91 goto (3, 1)
	92 3 (3, 1)
	94 iinc (3, 1)
	95 #4 (3, 1)
	96 -89 (3, 1)
	97 goto (3, 1)
	98 -84 (3, 1)
	100 aload_0 (2, 4)
	101 invokespecial (2, 4)
	102 org/apache/commons/math3/optim/nonlinear/vector/MultivariateVectorOptimizer.checkParameters:()V (2, 4)
	104 return (0, 1)

Method: checkParameters
	0 aload_0 (1, 1)
	1 getfield (1, 1)
	2 org/apache/commons/math3/optim/nonlinear/vector/MultivariateVectorOptimizer.target:[D (1, 1)
	4 arraylength (1, 1)
	5 aload_0 (1, 1)
	6 getfield (1, 1)
	7 org/apache/commons/math3/optim/nonlinear/vector/MultivariateVectorOptimizer.weightMatrix:Lorg/apache/commons/math3/linear/RealMatrix; (1, 1)
	9 invokeinterface (1, 1)
	10 org/apache/commons/math3/linear/RealMatrix.org/apache/commons/math3/exception/DimensionMismatchException (1, 1)
	12 0 (1, 1)
	14 if_icmpeq (1, 1)
	15 25 (1, 1)
	17 new (1, 1)
	18 org/apache/commons/math3/exception/DimensionMismatchException (1, 1)
	20 dup (1, 1)
	21 aload_0 (1, 1)
	22 getfield (1, 1)
	23 org/apache/commons/math3/optim/nonlinear/vector/MultivariateVectorOptimizer.target:[D (1, 1)
	25 arraylength (1, 1)
	26 aload_0 (1, 1)
	27 getfield (1, 1)
	28 org/apache/commons/math3/optim/nonlinear/vector/MultivariateVectorOptimizer.weightMatrix:Lorg/apache/commons/math3/linear/RealMatrix; (1, 1)
	30 invokeinterface (1, 1)
	31 org/apache/commons/math3/linear/RealMatrix.org/apache/commons/math3/exception/DimensionMismatchException (1, 1)
	33 0 (1, 1)
	35 invokespecial (1, 1)
	36 org/apache/commons/math3/exception/DimensionMismatchException.<init>:(II)V (1, 1)
	38 athrow (1, 1)
	39 return (0, 0)

