Method: <init>
	0 aload_0 (0, 0)
	1 invokespecial (0, 0)
	2 java/lang/Object.<init>:()V (0, 0)
	4 aload_1 (1, 1)
	5 invokeinterface (1, 1)
	6 org/apache/commons/math3/linear/RealMatrix.getRowDimension:()I (1, 1)
	8 0 (1, 1)
	10 aload_1 (1, 1)
	11 invokeinterface (1, 1)
	12 org/apache/commons/math3/linear/RealMatrix.org/apache/commons/math3/linear/NonSquareMatrixException (1, 1)
	14 0 (1, 1)
	16 if_icmpeq (1, 1)
	17 23 (1, 1)
	19 new (1, 1)
	20 org/apache/commons/math3/linear/NonSquareMatrixException (1, 1)
	22 dup (1, 1)
	23 aload_1 (1, 1)
	24 invokeinterface (1, 1)
	25 org/apache/commons/math3/linear/RealMatrix.getRowDimension:()I (1, 1)
	27 0 (1, 1)
	29 aload_1 (1, 1)
	30 invokeinterface (1, 1)
	31 org/apache/commons/math3/linear/RealMatrix.org/apache/commons/math3/linear/NonSquareMatrixException (1, 1)
	33 0 (1, 1)
	35 invokespecial (1, 1)
	36 org/apache/commons/math3/linear/NonSquareMatrixException.<init>:(II)V (1, 1)
	38 athrow (1, 1)
	39 aload_0 (0, 0)
	40 aload_1 (0, 0)
	41 invokeinterface (0, 0)
	42 org/apache/commons/math3/linear/RealMatrix.org/apache/commons/math3/optim/nonlinear/vector/Weight (0, 0)
	44 0 (0, 0)
	46 putfield (0, 0)
	47 org/apache/commons/math3/optim/nonlinear/vector/Weight.weightMatrix:Lorg/apache/commons/math3/linear/RealMatrix; (0, 0)
	49 return (0, 0)

Method: getWeight
	0 aload_0 (0, 0)
	1 getfield (0, 0)
	2 org/apache/commons/math3/optim/nonlinear/vector/Weight.weightMatrix:Lorg/apache/commons/math3/linear/RealMatrix; (0, 0)
	4 invokeinterface (0, 0)
	5 org/apache/commons/math3/linear/RealMatrix.org/apache/commons/math3/optim/nonlinear/vector/Weight (0, 0)
	7 0 (0, 0)
	9 areturn (0, 0)

