Method: <init>
	0 aload_0 (0, 0)
	1 aload_1 (0, 0)
	2 putfield (0, 0)
	5 aload_0 (0, 0)
	6 invokespecial (0, 0)
	9 aload_0 (0, 0)
	10 aload_2 (0, 0)
	11 putfield (0, 0)
	14 aload_0 (0, 0)
	15 aconst_null (0, 0)
	16 putfield (0, 0)
	19 aload_0 (0, 0)
	20 aconst_null (0, 0)
	21 putfield (0, 0)
	24 aload_0 (0, 0)
	25 aload_3 (0, 0)
	26 putfield (0, 0)
	29 aload_0 (0, 0)
	30 getstatic (0, 0)
	33 putfield (0, 0)
	36 return (0, 0)

Method: getElement
	0 aload_0 (0, 0)
	1 getfield (0, 0)
	4 areturn (0, 0)

Method: size
	0 iconst_1 (0, 0)
	1 aload_0 (0, 0)
	2 getfield (0, 0)
	5 ifnonnull (0, 0)
	8 iconst_0 (0, 0)
	9 goto (0, 0)
	12 aload_0 (0, 0)
	13 getfield (0, 0)
	16 invokevirtual (0, 0)
	19 iadd (0, 0)
	20 aload_0 (0, 0)
	21 getfield (0, 0)
	24 ifnonnull (0, 0)
	27 iconst_0 (0, 0)
	28 goto (0, 0)
	31 aload_0 (0, 0)
	32 getfield (0, 0)
	35 invokevirtual (0, 0)
	38 iadd (0, 0)
	39 ireturn (0, 0)

Method: getSmallest
	0 aload_0 (0, 0)
	1 astore_1 (0, 0)
	2 aload_1 (1, 3)
	3 getfield (1, 3)
	6 ifnull (1, 3)
	9 aload_1 (1, 3)
	10 getfield (1, 3)
	13 astore_1 (1, 3)
	14 goto (1, 3)
	17 aload_1 (0, 0)
	18 areturn (0, 0)

Method: getLargest
	0 aload_0 (0, 0)
	1 astore_1 (0, 0)
	2 aload_1 (1, 3)
	3 getfield (1, 3)
	6 ifnull (1, 3)
	9 aload_1 (1, 3)
	10 getfield (1, 3)
	13 astore_1 (1, 3)
	14 goto (1, 3)
	17 aload_1 (0, 0)
	18 areturn (0, 0)

Method: getPrevious
	0 aload_0 (1, 1)
	1 getfield (1, 1)
	4 ifnull (1, 1)
	7 aload_0 (1, 1)
	8 getfield (1, 1)
	11 invokevirtual (1, 1)
	14 astore_1 (1, 1)
	15 aload_1 (2, 1)
	16 ifnull (2, 1)
	19 aload_1 (2, 1)
	20 areturn (2, 1)
	21 aload_0 (1, 4)
	22 astore_1 (1, 4)
	23 aload_1 (1, 4)
	24 getfield (1, 4)
	27 ifnull (1, 4)
	30 aload_1 (2, 1)
	31 aload_1 (2, 1)
	32 getfield (2, 1)
	35 getfield (2, 1)
	38 if_acmpeq (2, 1)
	41 aload_1 (2, 1)
	42 getfield (2, 1)
	45 areturn (2, 1)
	46 aload_1 (2, 1)
	47 getfield (2, 1)
	50 astore_1 (2, 1)
	51 goto (2, 1)
	54 aconst_null (1, 4)
	55 areturn (1, 4)

Method: getNext
	0 aload_0 (1, 1)
	1 getfield (1, 1)
	4 ifnull (1, 1)
	7 aload_0 (1, 1)
	8 getfield (1, 1)
	11 invokevirtual (1, 1)
	14 astore_1 (1, 1)
	15 aload_1 (2, 1)
	16 ifnull (2, 1)
	19 aload_1 (2, 1)
	20 areturn (2, 1)
	21 aload_0 (1, 4)
	22 astore_1 (1, 4)
	23 aload_1 (1, 4)
	24 getfield (1, 4)
	27 ifnull (1, 4)
	30 aload_1 (2, 1)
	31 aload_1 (2, 1)
	32 getfield (2, 1)
	35 getfield (2, 1)
	38 if_acmpeq (2, 1)
	41 aload_1 (2, 1)
	42 getfield (2, 1)
	45 areturn (2, 1)
	46 aload_1 (2, 1)
	47 getfield (2, 1)
	50 astore_1 (2, 1)
	51 goto (2, 1)
	54 aconst_null (1, 4)
	55 areturn (1, 4)

Method: insert
	0 aload_1 (1, 1)
	1 aload_0 (1, 1)
	2 getfield (1, 1)
	5 invokeinterface (1, 1)
	10 ifge (1, 1)
	13 aload_0 (2, 1)
	14 getfield (2, 1)
	17 ifnonnull (2, 1)
	20 aload_0 (2, 1)
	21 new (2, 1)
	24 dup (2, 1)
	25 aload_0 (2, 1)
	26 getfield (2, 1)
	29 aload_1 (2, 1)
	30 aload_0 (2, 1)
	31 invokespecial (2, 1)
	34 putfield (2, 1)
	37 aload_0 (2, 1)
	38 invokespecial (2, 1)
	41 ireturn (2, 1)
	42 aload_0 (1, 1)
	43 getfield (1, 1)
	46 aload_1 (1, 1)
	47 invokevirtual (1, 1)
	50 ifeq (1, 1)
	53 aload_0 (1, 1)
	54 invokespecial (1, 1)
	57 goto (1, 1)
	60 iconst_0 (1, 1)
	61 ireturn (1, 1)
	62 aload_0 (1, 1)
	63 getfield (1, 1)
	66 ifnonnull (1, 1)
	69 aload_0 (1, 1)
	70 new (1, 1)
	73 dup (1, 1)
	74 aload_0 (1, 1)
	75 getfield (1, 1)
	78 aload_1 (1, 1)
	79 aload_0 (1, 1)
	80 invokespecial (1, 1)
	83 putfield (1, 1)
	86 aload_0 (1, 1)
	87 invokespecial (1, 1)
	90 ireturn (1, 1)
	91 aload_0 (0, 0)
	92 getfield (0, 0)
	95 aload_1 (0, 0)
	96 invokevirtual (0, 0)
	99 ifeq (0, 0)
	102 aload_0 (0, 0)
	103 invokespecial (0, 0)
	106 goto (0, 0)
	109 iconst_0 (0, 0)
	110 ireturn (0, 0)

Method: delete
	0 aload_0 (1, 1)
	1 getfield (1, 1)
	4 ifnonnull (1, 1)
	7 aload_0 (1, 1)
	8 getfield (1, 1)
	11 ifnonnull (1, 1)
	14 aload_0 (1, 1)
	15 getfield (1, 1)
	18 ifnonnull (1, 1)
	21 aload_0 (1, 1)
	22 aconst_null (1, 1)
	23 putfield (1, 1)
	26 aload_0 (1, 1)
	27 getfield (1, 1)
	30 aconst_null (1, 1)
	31 invokestatic (1, 1)
	34 pop (1, 1)
	35 goto (1, 1)
	38 aload_0 (2, 1)
	39 getfield (2, 1)
	42 ifnonnull (2, 1)
	45 aload_0 (2, 1)
	46 getfield (2, 1)
	49 ifnonnull (2, 1)
	52 aload_0 (2, 1)
	53 astore_1 (2, 1)
	54 aload_0 (2, 1)
	55 aconst_null (2, 1)
	56 putfield (2, 1)
	59 aload_1 (2, 1)
	60 aload_1 (2, 1)
	61 getfield (2, 1)
	64 getfield (2, 1)
	67 if_acmpne (2, 1)
	70 iconst_1 (2, 1)
	71 goto (2, 1)
	74 iconst_0 (2, 1)
	75 istore_3 (2, 1)
	76 aconst_null (2, 1)
	77 astore_2 (2, 1)
	78 goto (2, 1)
	81 aload_0 (2, 2)
	82 getfield (2, 2)
	85 ifnull (2, 2)
	88 aload_0 (2, 2)
	89 getfield (2, 2)
	92 invokevirtual (2, 2)
	95 goto (2, 2)
	98 aload_0 (2, 2)
	99 getfield (2, 2)
	102 invokevirtual (2, 2)
	105 astore_1 (2, 2)
	106 aload_0 (2, 2)
	107 aload_1 (2, 2)
	108 getfield (2, 2)
	111 putfield (2, 2)
	114 aload_1 (2, 2)
	115 aload_1 (2, 2)
	116 getfield (2, 2)
	119 getfield (2, 2)
	122 if_acmpne (2, 2)
	125 iconst_1 (2, 2)
	126 goto (2, 2)
	129 iconst_0 (2, 2)
	130 istore_3 (2, 2)
	131 aload_1 (2, 2)
	132 getfield (2, 2)
	135 ifnull (2, 2)
	138 aload_1 (2, 2)
	139 getfield (2, 2)
	142 goto (2, 2)
	145 aload_1 (2, 2)
	146 getfield (2, 2)
	149 astore_2 (2, 2)
	150 aload_1 (1, 1)
	151 getfield (1, 1)
	154 astore_1 (1, 1)
	155 iload_3 (2, 1)
	156 ifeq (2, 1)
	159 aload_1 (2, 1)
	160 aload_2 (2, 1)
	161 putfield (2, 1)
	164 goto (2, 1)
	167 aload_1 (2, 2)
	168 aload_2 (2, 2)
	169 putfield (2, 2)
	172 aload_2 (2, 1)
	173 ifnull (2, 1)
	176 aload_2 (2, 1)
	177 aload_1 (2, 1)
	178 putfield (2, 1)
	181 iload_3 (2, 3)
	182 ifeq (2, 3)
	185 aload_1 (2, 3)
	186 invokespecial (2, 3)
	189 ifeq (2, 3)
	192 goto (2, 3)
	195 aload_1 (2, 3)
	196 invokespecial (2, 3)
	199 ifeq (2, 3)
	202 aload_1 (3, 1)
	203 getfield (3, 1)
	206 ifnonnull (3, 1)
	209 return (3, 1)
	210 aload_1 (2, 3)
	211 aload_1 (2, 3)
	212 getfield (2, 3)
	215 getfield (2, 3)
	218 if_acmpne (2, 3)
	221 iconst_1 (2, 3)
	222 goto (2, 3)
	225 iconst_0 (2, 3)
	226 istore_3 (2, 3)
	227 aload_1 (2, 3)
	228 getfield (2, 3)
	231 astore_1 (2, 3)
	232 goto (2, 3)
	235 return (0, 2)

Method: rebalanceLeftGrown
	0 getstatic (1, 5)
	3 aload_0 (1, 5)
	4 getfield (1, 5)
	7 invokevirtual (1, 5)
	10 iaload (1, 5)
	11 lookupswitch (1, 5)
	36 aload_0 (2, 1)
	37 getfield (2, 1)
	40 getfield (2, 1)
	43 getstatic (2, 1)
	46 if_acmpne (2, 1)
	49 aload_0 (2, 1)
	50 invokespecial (2, 1)
	53 aload_0 (2, 1)
	54 getstatic (2, 1)
	57 putfield (2, 1)
	60 aload_0 (2, 1)
	61 getfield (2, 1)
	64 getstatic (2, 1)
	67 putfield (2, 1)
	70 goto (2, 1)
	73 aload_0 (2, 2)
	74 getfield (2, 2)
	77 getfield (2, 2)
	80 getfield (2, 2)
	83 astore_1 (2, 2)
	84 aload_0 (2, 2)
	85 getfield (2, 2)
	88 invokespecial (2, 2)
	91 aload_0 (2, 2)
	92 invokespecial (2, 2)
	95 getstatic (3, 5)
	98 aload_1 (3, 5)
	99 invokevirtual (3, 5)
	102 iaload (3, 5)
	103 lookupswitch (3, 5)
	128 aload_0 (3, 5)
	129 getfield (3, 5)
	132 getstatic (3, 5)
	135 putfield (3, 5)
	138 aload_0 (3, 5)
	139 getfield (3, 5)
	142 getstatic (3, 5)
	145 putfield (3, 5)
	148 goto (3, 5)
	151 aload_0 (3, 5)
	152 getfield (3, 5)
	155 getstatic (3, 5)
	158 putfield (3, 5)
	161 aload_0 (3, 5)
	162 getfield (3, 5)
	165 getstatic (3, 5)
	168 putfield (3, 5)
	171 goto (3, 5)
	174 aload_0 (3, 5)
	175 getfield (3, 5)
	178 getstatic (3, 5)
	181 putfield (3, 5)
	184 aload_0 (3, 5)
	185 getfield (3, 5)
	188 getstatic (3, 5)
	191 putfield (3, 5)
	194 aload_0 (2, 2)
	195 getstatic (2, 2)
	198 putfield (2, 2)
	201 iconst_0 (1, 1)
	202 ireturn (1, 1)
	203 aload_0 (1, 1)
	204 getstatic (1, 1)
	207 putfield (1, 1)
	210 iconst_0 (1, 1)
	211 ireturn (1, 1)
	212 aload_0 (1, 1)
	213 getstatic (1, 1)
	216 putfield (1, 1)
	219 iconst_1 (1, 1)
	220 ireturn (1, 1)

Method: rebalanceRightGrown
	0 getstatic (1, 5)
	3 aload_0 (1, 5)
	4 getfield (1, 5)
	7 invokevirtual (1, 5)
	10 iaload (1, 5)
	11 lookupswitch (1, 5)
	36 aload_0 (1, 5)
	37 getstatic (1, 5)
	40 putfield (1, 5)
	43 iconst_0 (1, 5)
	44 ireturn (1, 5)
	45 aload_0 (2, 1)
	46 getfield (2, 1)
	49 getfield (2, 1)
	52 getstatic (2, 1)
	55 if_acmpne (2, 1)
	58 aload_0 (2, 1)
	59 invokespecial (2, 1)
	62 aload_0 (2, 1)
	63 getstatic (2, 1)
	66 putfield (2, 1)
	69 aload_0 (2, 1)
	70 getfield (2, 1)
	73 getstatic (2, 1)
	76 putfield (2, 1)
	79 goto (2, 1)
	82 aload_0 (2, 2)
	83 getfield (2, 2)
	86 getfield (2, 2)
	89 getfield (2, 2)
	92 astore_1 (2, 2)
	93 aload_0 (2, 2)
	94 getfield (2, 2)
	97 invokespecial (2, 2)
	100 aload_0 (2, 2)
	101 invokespecial (2, 2)
	104 getstatic (3, 5)
	107 aload_1 (3, 5)
	108 invokevirtual (3, 5)
	111 iaload (3, 5)
	112 lookupswitch (3, 5)
	140 aload_0 (3, 5)
	141 getfield (3, 5)
	144 getstatic (3, 5)
	147 putfield (3, 5)
	150 aload_0 (3, 5)
	151 getfield (3, 5)
	154 getstatic (3, 5)
	157 putfield (3, 5)
	160 goto (3, 5)
	163 aload_0 (3, 5)
	164 getfield (3, 5)
	167 getstatic (3, 5)
	170 putfield (3, 5)
	173 aload_0 (3, 5)
	174 getfield (3, 5)
	177 getstatic (3, 5)
	180 putfield (3, 5)
	183 goto (3, 5)
	186 aload_0 (3, 5)
	187 getfield (3, 5)
	190 getstatic (3, 5)
	193 putfield (3, 5)
	196 aload_0 (3, 5)
	197 getfield (3, 5)
	200 getstatic (3, 5)
	203 putfield (3, 5)
	206 aload_0 (2, 2)
	207 getstatic (2, 2)
	210 putfield (2, 2)
	213 iconst_0 (1, 1)
	214 ireturn (1, 1)
	215 aload_0 (1, 1)
	216 getstatic (1, 1)
	219 putfield (1, 1)
	222 iconst_1 (1, 1)
	223 ireturn (1, 1)

Method: rebalanceLeftShrunk
	0 getstatic (1, 5)
	3 aload_0 (1, 5)
	4 getfield (1, 5)
	7 invokevirtual (1, 5)
	10 iaload (1, 5)
	11 lookupswitch (1, 5)
	36 aload_0 (1, 5)
	37 getstatic (1, 5)
	40 putfield (1, 5)
	43 iconst_1 (1, 5)
	44 ireturn (1, 5)
	45 aload_0 (2, 1)
	46 getfield (2, 1)
	49 getfield (2, 1)
	52 getstatic (2, 1)
	55 if_acmpne (2, 1)
	58 aload_0 (2, 1)
	59 invokespecial (2, 1)
	62 aload_0 (2, 1)
	63 getstatic (2, 1)
	66 putfield (2, 1)
	69 aload_0 (2, 1)
	70 getfield (2, 1)
	73 getstatic (2, 1)
	76 putfield (2, 1)
	79 iconst_1 (2, 1)
	80 ireturn (2, 1)
	81 aload_0 (2, 1)
	82 getfield (2, 1)
	85 getfield (2, 1)
	88 getstatic (2, 1)
	91 if_acmpne (2, 1)
	94 aload_0 (2, 1)
	95 invokespecial (2, 1)
	98 aload_0 (2, 1)
	99 getstatic (2, 1)
	102 putfield (2, 1)
	105 aload_0 (2, 1)
	106 getfield (2, 1)
	109 getstatic (2, 1)
	112 putfield (2, 1)
	115 iconst_0 (2, 1)
	116 ireturn (2, 1)
	117 aload_0 (2, 2)
	118 getfield (2, 2)
	121 getfield (2, 2)
	124 getfield (2, 2)
	127 astore_1 (2, 2)
	128 aload_0 (2, 2)
	129 getfield (2, 2)
	132 invokespecial (2, 2)
	135 aload_0 (2, 2)
	136 invokespecial (2, 2)
	139 getstatic (3, 5)
	142 aload_1 (3, 5)
	143 invokevirtual (3, 5)
	146 iaload (3, 5)
	147 lookupswitch (3, 5)
	172 aload_0 (3, 5)
	173 getfield (3, 5)
	176 getstatic (3, 5)
	179 putfield (3, 5)
	182 aload_0 (3, 5)
	183 getfield (3, 5)
	186 getstatic (3, 5)
	189 putfield (3, 5)
	192 goto (3, 5)
	195 aload_0 (3, 5)
	196 getfield (3, 5)
	199 getstatic (3, 5)
	202 putfield (3, 5)
	205 aload_0 (3, 5)
	206 getfield (3, 5)
	209 getstatic (3, 5)
	212 putfield (3, 5)
	215 goto (3, 5)
	218 aload_0 (3, 5)
	219 getfield (3, 5)
	222 getstatic (3, 5)
	225 putfield (3, 5)
	228 aload_0 (3, 5)
	229 getfield (3, 5)
	232 getstatic (3, 5)
	235 putfield (3, 5)
	238 aload_0 (2, 2)
	239 getstatic (2, 2)
	242 putfield (2, 2)
	245 iconst_1 (2, 2)
	246 ireturn (2, 2)
	247 aload_0 (1, 1)
	248 getstatic (1, 1)
	251 putfield (1, 1)
	254 iconst_0 (1, 1)
	255 ireturn (1, 1)

Method: rebalanceRightShrunk
	0 getstatic (1, 5)
	3 aload_0 (1, 5)
	4 getfield (1, 5)
	7 invokevirtual (1, 5)
	10 iaload (1, 5)
	11 lookupswitch (1, 5)
	36 aload_0 (1, 5)
	37 getstatic (1, 5)
	40 putfield (1, 5)
	43 iconst_1 (1, 5)
	44 ireturn (1, 5)
	45 aload_0 (2, 1)
	46 getfield (2, 1)
	49 getfield (2, 1)
	52 getstatic (2, 1)
	55 if_acmpne (2, 1)
	58 aload_0 (2, 1)
	59 invokespecial (2, 1)
	62 aload_0 (2, 1)
	63 getstatic (2, 1)
	66 putfield (2, 1)
	69 aload_0 (2, 1)
	70 getfield (2, 1)
	73 getstatic (2, 1)
	76 putfield (2, 1)
	79 iconst_1 (2, 1)
	80 ireturn (2, 1)
	81 aload_0 (2, 1)
	82 getfield (2, 1)
	85 getfield (2, 1)
	88 getstatic (2, 1)
	91 if_acmpne (2, 1)
	94 aload_0 (2, 1)
	95 invokespecial (2, 1)
	98 aload_0 (2, 1)
	99 getstatic (2, 1)
	102 putfield (2, 1)
	105 aload_0 (2, 1)
	106 getfield (2, 1)
	109 getstatic (2, 1)
	112 putfield (2, 1)
	115 iconst_0 (2, 1)
	116 ireturn (2, 1)
	117 aload_0 (2, 2)
	118 getfield (2, 2)
	121 getfield (2, 2)
	124 getfield (2, 2)
	127 astore_1 (2, 2)
	128 aload_0 (2, 2)
	129 getfield (2, 2)
	132 invokespecial (2, 2)
	135 aload_0 (2, 2)
	136 invokespecial (2, 2)
	139 getstatic (3, 5)
	142 aload_1 (3, 5)
	143 invokevirtual (3, 5)
	146 iaload (3, 5)
	147 lookupswitch (3, 5)
	172 aload_0 (3, 5)
	173 getfield (3, 5)
	176 getstatic (3, 5)
	179 putfield (3, 5)
	182 aload_0 (3, 5)
	183 getfield (3, 5)
	186 getstatic (3, 5)
	189 putfield (3, 5)
	192 goto (3, 5)
	195 aload_0 (3, 5)
	196 getfield (3, 5)
	199 getstatic (3, 5)
	202 putfield (3, 5)
	205 aload_0 (3, 5)
	206 getfield (3, 5)
	209 getstatic (3, 5)
	212 putfield (3, 5)
	215 goto (3, 5)
	218 aload_0 (3, 5)
	219 getfield (3, 5)
	222 getstatic (3, 5)
	225 putfield (3, 5)
	228 aload_0 (3, 5)
	229 getfield (3, 5)
	232 getstatic (3, 5)
	235 putfield (3, 5)
	238 aload_0 (2, 2)
	239 getstatic (2, 2)
	242 putfield (2, 2)
	245 iconst_1 (2, 2)
	246 ireturn (2, 2)
	247 aload_0 (1, 1)
	248 getstatic (1, 1)
	251 putfield (1, 1)
	254 iconst_0 (1, 1)
	255 ireturn (1, 1)

Method: rotateCW
	0 aload_0 (0, 0)
	1 getfield (0, 0)
	4 astore_1 (0, 0)
	5 aload_0 (0, 0)
	6 aload_0 (0, 0)
	7 getfield (0, 0)
	10 getfield (0, 0)
	13 putfield (0, 0)
	16 aload_0 (0, 0)
	17 getfield (0, 0)
	20 aload_1 (0, 0)
	21 putfield (0, 0)
	24 aload_0 (0, 0)
	25 getfield (0, 0)
	28 astore_2 (0, 0)
	29 aload_0 (0, 0)
	30 aload_2 (0, 0)
	31 getfield (0, 0)
	34 putfield (0, 0)
	37 aload_2 (0, 0)
	38 aload_2 (0, 0)
	39 getfield (0, 0)
	42 putfield (0, 0)
	45 aload_2 (0, 0)
	46 aload_0 (0, 0)
	47 getfield (0, 0)
	50 putfield (0, 0)
	53 aload_0 (0, 0)
	54 aload_2 (0, 0)
	55 putfield (0, 0)
	58 aload_0 (1, 1)
	59 getfield (1, 1)
	62 ifnull (1, 1)
	65 aload_0 (1, 1)
	66 getfield (1, 1)
	69 aload_0 (1, 1)
	70 putfield (1, 1)
	73 aload_0 (1, 1)
	74 getfield (1, 1)
	77 getfield (1, 1)
	80 ifnull (1, 1)
	83 aload_0 (1, 1)
	84 getfield (1, 1)
	87 getfield (1, 1)
	90 aload_0 (1, 1)
	91 getfield (1, 1)
	94 putfield (1, 1)
	97 return (0, 0)

Method: rotateCCW
	0 aload_0 (0, 0)
	1 getfield (0, 0)
	4 astore_1 (0, 0)
	5 aload_0 (0, 0)
	6 aload_0 (0, 0)
	7 getfield (0, 0)
	10 getfield (0, 0)
	13 putfield (0, 0)
	16 aload_0 (0, 0)
	17 getfield (0, 0)
	20 aload_1 (0, 0)
	21 putfield (0, 0)
	24 aload_0 (0, 0)
	25 getfield (0, 0)
	28 astore_2 (0, 0)
	29 aload_0 (0, 0)
	30 aload_2 (0, 0)
	31 getfield (0, 0)
	34 putfield (0, 0)
	37 aload_2 (0, 0)
	38 aload_2 (0, 0)
	39 getfield (0, 0)
	42 putfield (0, 0)
	45 aload_2 (0, 0)
	46 aload_0 (0, 0)
	47 getfield (0, 0)
	50 putfield (0, 0)
	53 aload_0 (0, 0)
	54 aload_2 (0, 0)
	55 putfield (0, 0)
	58 aload_0 (1, 1)
	59 getfield (1, 1)
	62 ifnull (1, 1)
	65 aload_0 (1, 1)
	66 getfield (1, 1)
	69 aload_0 (1, 1)
	70 putfield (1, 1)
	73 aload_0 (1, 1)
	74 getfield (1, 1)
	77 getfield (1, 1)
	80 ifnull (1, 1)
	83 aload_0 (1, 1)
	84 getfield (1, 1)
	87 getfield (1, 1)
	90 aload_0 (1, 1)
	91 getfield (1, 1)
	94 putfield (1, 1)
	97 return (0, 0)

Method: access$000
	0 aload_0 (0, 0)
	1 getfield (0, 0)
	4 areturn (0, 0)

Method: access$100
	0 aload_0 (0, 0)
	1 getfield (0, 0)
	4 areturn (0, 0)

Method: access$200
	0 aload_0 (0, 0)
	1 getfield (0, 0)
	4 areturn (0, 0)

