Method: <init>
	0 aload_0 (0, 0)
	1 invokespecial (0, 0)
	2 java/lang/Object.<init>:()V (0, 0)
	4 aload_0 (0, 0)
	5 aconst_null (0, 0)
	6 putfield (0, 0)
	7 org/apache/commons/math3/geometry/partitioning/utilities/AVLTree.top:Lorg/apache/commons/math3/geometry/partitioning/utilities/AVLTree$Node; (0, 0)
	9 return (0, 0)

Method: insert
	0 aload_1 (1, 1)
	1 ifnull (1, 1)
	2 36 (1, 1)
	4 aload_0 (2, 1)
	5 getfield (2, 1)
	6 org/apache/commons/math3/geometry/partitioning/utilities/AVLTree.top:Lorg/apache/commons/math3/geometry/partitioning/utilities/AVLTree$Node; (2, 1)
	8 ifnonnull (2, 1)
	9 20 (2, 1)
	11 aload_0 (2, 1)
	12 new (2, 1)
	13 org/apache/commons/math3/geometry/partitioning/utilities/AVLTree$Node (2, 1)
	15 dup (2, 1)
	16 aload_0 (2, 1)
	17 aload_1 (2, 1)
	18 aconst_null (2, 1)
	19 invokespecial (2, 1)
	20 org/apache/commons/math3/geometry/partitioning/utilities/AVLTree$Node.<init>:(Lorg/apache/commons/math3/geometry/partitioning/utilities/AVLTree;Ljava/lang/Comparable;Lorg/apache/commons/math3/geometry/partitioning/utilities/AVLTree$Node;)V (2, 1)
	22 putfield (2, 1)
	23 org/apache/commons/math3/geometry/partitioning/utilities/AVLTree.top:Lorg/apache/commons/math3/geometry/partitioning/utilities/AVLTree$Node; (2, 1)
	25 goto (2, 1)
	26 12 (2, 1)
	28 aload_0 (2, 2)
	29 getfield (2, 2)
	30 org/apache/commons/math3/geometry/partitioning/utilities/AVLTree.top:Lorg/apache/commons/math3/geometry/partitioning/utilities/AVLTree$Node; (2, 2)
	32 aload_1 (2, 2)
	33 invokevirtual (2, 2)
	34 org/apache/commons/math3/geometry/partitioning/utilities/AVLTree$Node.insert:(Ljava/lang/Comparable;)Z (2, 2)
	36 pop (2, 2)
	37 return (0, 0)

Method: delete
	0 aload_1 (1, 1)
	1 ifnull (1, 1)
	2 50 (1, 1)
	4 aload_0 (2, 4)
	5 aload_1 (2, 4)
	6 invokevirtual (2, 4)
	7 org/apache/commons/math3/geometry/partitioning/utilities/AVLTree.getNotSmaller:(Ljava/lang/Comparable;)Lorg/apache/commons/math3/geometry/partitioning/utilities/AVLTree$Node; (2, 4)
	9 astore_2 (2, 4)
	10 aload_2 (2, 4)
	11 ifnull (2, 4)
	12 40 (2, 4)
	14 aload_2 (3, 1)
	15 invokestatic (3, 1)
	16 org/apache/commons/math3/geometry/partitioning/utilities/AVLTree$Node.access$000:(Lorg/apache/commons/math3/geometry/partitioning/utilities/AVLTree$Node;)Ljava/lang/Comparable; (3, 1)
	18 aload_1 (3, 1)
	19 if_acmpne (3, 1)
	20 9 (3, 1)
	22 aload_2 (3, 1)
	23 invokevirtual (3, 1)
	24 org/apache/commons/math3/geometry/partitioning/utilities/AVLTree$Node.delete:()V (3, 1)
	26 iconst_1 (3, 1)
	27 ireturn (3, 1)
	28 aload_2 (3, 1)
	29 invokestatic (3, 1)
	30 org/apache/commons/math3/geometry/partitioning/utilities/AVLTree$Node.access$000:(Lorg/apache/commons/math3/geometry/partitioning/utilities/AVLTree$Node;)Ljava/lang/Comparable; (3, 1)
	32 aload_1 (3, 1)
	33 invokeinterface (3, 1)
	34 java/lang/Comparable.getNext:()Lorg/apache/commons/math3/geometry/partitioning/utilities/AVLTree$Node; (3, 1)
	36 0 (3, 1)
	38 ifle (3, 1)
	39 5 (3, 1)
	41 iconst_0 (3, 1)
	42 ireturn (3, 1)
	43 aload_2 (3, 1)
	44 invokevirtual (3, 1)
	45 org/apache/commons/math3/geometry/partitioning/utilities/AVLTree$Node.getNext:()Lorg/apache/commons/math3/geometry/partitioning/utilities/AVLTree$Node; (3, 1)
	47 astore_2 (3, 1)
	48 goto (3, 1)
	49 -38 (3, 1)
	51 iconst_0 (1, 1)
	52 ireturn (1, 1)

Method: isEmpty
	0 aload_0 (0, 0)
	1 getfield (0, 0)
	2 org/apache/commons/math3/geometry/partitioning/utilities/AVLTree.top:Lorg/apache/commons/math3/geometry/partitioning/utilities/AVLTree$Node; (0, 0)
	4 ifnonnull (0, 0)
	5 7 (0, 0)
	7 iconst_1 (0, 0)
	8 goto (0, 0)
	9 4 (0, 0)
	11 iconst_0 (0, 0)
	12 ireturn (0, 0)

Method: size
	0 aload_0 (0, 0)
	1 getfield (0, 0)
	2 org/apache/commons/math3/geometry/partitioning/utilities/AVLTree.top:Lorg/apache/commons/math3/geometry/partitioning/utilities/AVLTree$Node; (0, 0)
	4 ifnonnull (0, 0)
	5 7 (0, 0)
	7 iconst_0 (0, 0)
	8 goto (0, 0)
	9 10 (0, 0)
	11 aload_0 (0, 0)
	12 getfield (0, 0)
	13 org/apache/commons/math3/geometry/partitioning/utilities/AVLTree.top:Lorg/apache/commons/math3/geometry/partitioning/utilities/AVLTree$Node; (0, 0)
	15 invokevirtual (0, 0)
	16 org/apache/commons/math3/geometry/partitioning/utilities/AVLTree$Node.size:()I (0, 0)
	18 ireturn (0, 0)

Method: getSmallest
	0 aload_0 (0, 0)
	1 getfield (0, 0)
	2 org/apache/commons/math3/geometry/partitioning/utilities/AVLTree.top:Lorg/apache/commons/math3/geometry/partitioning/utilities/AVLTree$Node; (0, 0)
	4 ifnonnull (0, 0)
	5 7 (0, 0)
	7 aconst_null (0, 0)
	8 goto (0, 0)
	9 10 (0, 0)
	11 aload_0 (0, 0)
	12 getfield (0, 0)
	13 org/apache/commons/math3/geometry/partitioning/utilities/AVLTree.top:Lorg/apache/commons/math3/geometry/partitioning/utilities/AVLTree$Node; (0, 0)
	15 invokevirtual (0, 0)
	16 org/apache/commons/math3/geometry/partitioning/utilities/AVLTree$Node.getSmallest:()Lorg/apache/commons/math3/geometry/partitioning/utilities/AVLTree$Node; (0, 0)
	18 areturn (0, 0)

Method: getLargest
	0 aload_0 (0, 0)
	1 getfield (0, 0)
	2 org/apache/commons/math3/geometry/partitioning/utilities/AVLTree.top:Lorg/apache/commons/math3/geometry/partitioning/utilities/AVLTree$Node; (0, 0)
	4 ifnonnull (0, 0)
	5 7 (0, 0)
	7 aconst_null (0, 0)
	8 goto (0, 0)
	9 10 (0, 0)
	11 aload_0 (0, 0)
	12 getfield (0, 0)
	13 org/apache/commons/math3/geometry/partitioning/utilities/AVLTree.top:Lorg/apache/commons/math3/geometry/partitioning/utilities/AVLTree$Node; (0, 0)
	15 invokevirtual (0, 0)
	16 org/apache/commons/math3/geometry/partitioning/utilities/AVLTree$Node.getLargest:()Lorg/apache/commons/math3/geometry/partitioning/utilities/AVLTree$Node; (0, 0)
	18 areturn (0, 0)

Method: getNotSmaller
	0 aconst_null (0, 0)
	1 astore_2 (0, 0)
	2 aload_0 (1, 4)
	3 getfield (1, 4)
	4 org/apache/commons/math3/geometry/partitioning/utilities/AVLTree.top:Lorg/apache/commons/math3/geometry/partitioning/utilities/AVLTree$Node; (1, 4)
	6 astore_3 (1, 4)
	7 aload_3 (1, 4)
	8 ifnull (1, 4)
	9 52 (1, 4)
	11 aload_3 (2, 1)
	12 invokestatic (2, 1)
	13 org/apache/commons/math3/geometry/partitioning/utilities/AVLTree$Node.access$000:(Lorg/apache/commons/math3/geometry/partitioning/utilities/AVLTree$Node;)Ljava/lang/Comparable; (2, 1)
	15 aload_1 (2, 1)
	16 invokeinterface (2, 1)
	17 java/lang/Comparable.getNext:()Lorg/apache/commons/math3/geometry/partitioning/utilities/AVLTree$Node; (2, 1)
	19 0 (2, 1)
	21 ifge (2, 1)
	22 20 (2, 1)
	24 aload_3 (3, 1)
	25 invokestatic (3, 1)
	26 org/apache/commons/math3/geometry/partitioning/utilities/AVLTree$Node.access$100:(Lorg/apache/commons/math3/geometry/partitioning/utilities/AVLTree$Node;)Lorg/apache/commons/math3/geometry/partitioning/utilities/AVLTree$Node; (3, 1)
	28 ifnonnull (3, 1)
	29 5 (3, 1)
	31 aload_2 (3, 1)
	32 areturn (3, 1)
	33 aload_3 (2, 1)
	34 invokestatic (2, 1)
	35 org/apache/commons/math3/geometry/partitioning/utilities/AVLTree$Node.access$100:(Lorg/apache/commons/math3/geometry/partitioning/utilities/AVLTree$Node;)Lorg/apache/commons/math3/geometry/partitioning/utilities/AVLTree$Node; (2, 1)
	37 astore_3 (2, 1)
	38 goto (2, 1)
	39 -31 (2, 1)
	41 aload_3 (2, 2)
	42 astore_2 (2, 2)
	43 aload_3 (3, 1)
	44 invokestatic (3, 1)
	45 org/apache/commons/math3/geometry/partitioning/utilities/AVLTree$Node.access$200:(Lorg/apache/commons/math3/geometry/partitioning/utilities/AVLTree$Node;)Lorg/apache/commons/math3/geometry/partitioning/utilities/AVLTree$Node; (3, 1)
	47 ifnonnull (3, 1)
	48 5 (3, 1)
	50 aload_2 (3, 1)
	51 areturn (3, 1)
	52 aload_3 (2, 2)
	53 invokestatic (2, 2)
	54 org/apache/commons/math3/geometry/partitioning/utilities/AVLTree$Node.access$200:(Lorg/apache/commons/math3/geometry/partitioning/utilities/AVLTree$Node;)Lorg/apache/commons/math3/geometry/partitioning/utilities/AVLTree$Node; (2, 2)
	56 astore_3 (2, 2)
	57 goto (2, 2)
	58 -50 (2, 2)
	60 aconst_null (0, 0)
	61 areturn (0, 0)

Method: getNotLarger
	0 aconst_null (0, 0)
	1 astore_2 (0, 0)
	2 aload_0 (1, 4)
	3 getfield (1, 4)
	4 org/apache/commons/math3/geometry/partitioning/utilities/AVLTree.top:Lorg/apache/commons/math3/geometry/partitioning/utilities/AVLTree$Node; (1, 4)
	6 astore_3 (1, 4)
	7 aload_3 (1, 4)
	8 ifnull (1, 4)
	9 52 (1, 4)
	11 aload_3 (2, 1)
	12 invokestatic (2, 1)
	13 org/apache/commons/math3/geometry/partitioning/utilities/AVLTree$Node.access$000:(Lorg/apache/commons/math3/geometry/partitioning/utilities/AVLTree$Node;)Ljava/lang/Comparable; (2, 1)
	15 aload_1 (2, 1)
	16 invokeinterface (2, 1)
	17 java/lang/Comparable.getNext:()Lorg/apache/commons/math3/geometry/partitioning/utilities/AVLTree$Node; (2, 1)
	19 0 (2, 1)
	21 ifle (2, 1)
	22 20 (2, 1)
	24 aload_3 (3, 1)
	25 invokestatic (3, 1)
	26 org/apache/commons/math3/geometry/partitioning/utilities/AVLTree$Node.access$200:(Lorg/apache/commons/math3/geometry/partitioning/utilities/AVLTree$Node;)Lorg/apache/commons/math3/geometry/partitioning/utilities/AVLTree$Node; (3, 1)
	28 ifnonnull (3, 1)
	29 5 (3, 1)
	31 aload_2 (3, 1)
	32 areturn (3, 1)
	33 aload_3 (2, 1)
	34 invokestatic (2, 1)
	35 org/apache/commons/math3/geometry/partitioning/utilities/AVLTree$Node.access$200:(Lorg/apache/commons/math3/geometry/partitioning/utilities/AVLTree$Node;)Lorg/apache/commons/math3/geometry/partitioning/utilities/AVLTree$Node; (2, 1)
	37 astore_3 (2, 1)
	38 goto (2, 1)
	39 -31 (2, 1)
	41 aload_3 (2, 2)
	42 astore_2 (2, 2)
	43 aload_3 (3, 1)
	44 invokestatic (3, 1)
	45 org/apache/commons/math3/geometry/partitioning/utilities/AVLTree$Node.access$100:(Lorg/apache/commons/math3/geometry/partitioning/utilities/AVLTree$Node;)Lorg/apache/commons/math3/geometry/partitioning/utilities/AVLTree$Node; (3, 1)
	47 ifnonnull (3, 1)
	48 5 (3, 1)
	50 aload_2 (3, 1)
	51 areturn (3, 1)
	52 aload_3 (2, 2)
	53 invokestatic (2, 2)
	54 org/apache/commons/math3/geometry/partitioning/utilities/AVLTree$Node.access$100:(Lorg/apache/commons/math3/geometry/partitioning/utilities/AVLTree$Node;)Lorg/apache/commons/math3/geometry/partitioning/utilities/AVLTree$Node; (2, 2)
	56 astore_3 (2, 2)
	57 goto (2, 2)
	58 -50 (2, 2)
	60 aconst_null (0, 0)
	61 areturn (0, 0)

Method: access$302
	0 aload_0 (0, 0)
	1 aload_1 (0, 0)
	2 dup_x1 (0, 0)
	3 putfield (0, 0)
	4 org/apache/commons/math3/geometry/partitioning/utilities/AVLTree.top:Lorg/apache/commons/math3/geometry/partitioning/utilities/AVLTree$Node; (0, 0)
	6 areturn (0, 0)

