Method: <init>
	0 aload_0 (0, 0)
	1 aload_1 (0, 0)
	2 putfield (0, 0)
	3 org/apache/commons/math3/geometry/partitioning/utilities/AVLTree$Node.this$0:Lorg/apache/commons/math3/geometry/partitioning/utilities/AVLTree; (0, 0)
	5 aload_0 (0, 0)
	6 invokespecial (0, 0)
	7 java/lang/Object.<init>:()V (0, 0)
	9 aload_0 (0, 0)
	10 aload_2 (0, 0)
	11 putfield (0, 0)
	12 org/apache/commons/math3/geometry/partitioning/utilities/AVLTree$Node.element:Ljava/lang/Comparable; (0, 0)
	14 aload_0 (0, 0)
	15 aconst_null (0, 0)
	16 putfield (0, 0)
	17 org/apache/commons/math3/geometry/partitioning/utilities/AVLTree$Node.left:Lorg/apache/commons/math3/geometry/partitioning/utilities/AVLTree$Node; (0, 0)
	19 aload_0 (0, 0)
	20 aconst_null (0, 0)
	21 putfield (0, 0)
	22 org/apache/commons/math3/geometry/partitioning/utilities/AVLTree$Node.right:Lorg/apache/commons/math3/geometry/partitioning/utilities/AVLTree$Node; (0, 0)
	24 aload_0 (0, 0)
	25 aload_3 (0, 0)
	26 putfield (0, 0)
	27 org/apache/commons/math3/geometry/partitioning/utilities/AVLTree$Node.parent:Lorg/apache/commons/math3/geometry/partitioning/utilities/AVLTree$Node; (0, 0)
	29 aload_0 (0, 0)
	30 getstatic (0, 0)
	31 org/apache/commons/math3/geometry/partitioning/utilities/AVLTree$Skew.BALANCED:Lorg/apache/commons/math3/geometry/partitioning/utilities/AVLTree$Skew; (0, 0)
	33 putfield (0, 0)
	34 org/apache/commons/math3/geometry/partitioning/utilities/AVLTree$Node.skew:Lorg/apache/commons/math3/geometry/partitioning/utilities/AVLTree$Skew; (0, 0)
	36 return (0, 0)

Method: getElement
	0 aload_0 (0, 0)
	1 getfield (0, 0)
	2 org/apache/commons/math3/geometry/partitioning/utilities/AVLTree$Node.element:Ljava/lang/Comparable; (0, 0)
	4 areturn (0, 0)

Method: size
	0 iconst_1 (0, 0)
	1 aload_0 (0, 0)
	2 getfield (0, 0)
	3 org/apache/commons/math3/geometry/partitioning/utilities/AVLTree$Node.left:Lorg/apache/commons/math3/geometry/partitioning/utilities/AVLTree$Node; (0, 0)
	5 ifnonnull (0, 0)
	6 7 (0, 0)
	8 iconst_0 (0, 0)
	9 goto (0, 0)
	10 10 (0, 0)
	12 aload_0 (0, 0)
	13 getfield (0, 0)
	14 org/apache/commons/math3/geometry/partitioning/utilities/AVLTree$Node.left:Lorg/apache/commons/math3/geometry/partitioning/utilities/AVLTree$Node; (0, 0)
	16 invokevirtual (0, 0)
	17 org/apache/commons/math3/geometry/partitioning/utilities/AVLTree$Node.size:()I (0, 0)
	19 iadd (0, 0)
	20 aload_0 (0, 0)
	21 getfield (0, 0)
	22 org/apache/commons/math3/geometry/partitioning/utilities/AVLTree$Node.right:Lorg/apache/commons/math3/geometry/partitioning/utilities/AVLTree$Node; (0, 0)
	24 ifnonnull (0, 0)
	25 7 (0, 0)
	27 iconst_0 (0, 0)
	28 goto (0, 0)
	29 10 (0, 0)
	31 aload_0 (0, 0)
	32 getfield (0, 0)
	33 org/apache/commons/math3/geometry/partitioning/utilities/AVLTree$Node.right:Lorg/apache/commons/math3/geometry/partitioning/utilities/AVLTree$Node; (0, 0)
	35 invokevirtual (0, 0)
	36 org/apache/commons/math3/geometry/partitioning/utilities/AVLTree$Node.size:()I (0, 0)
	38 iadd (0, 0)
	39 ireturn (0, 0)

Method: getSmallest
	0 aload_0 (0, 0)
	1 astore_1 (0, 0)
	2 aload_1 (1, 3)
	3 getfield (1, 3)
	4 org/apache/commons/math3/geometry/partitioning/utilities/AVLTree$Node.left:Lorg/apache/commons/math3/geometry/partitioning/utilities/AVLTree$Node; (1, 3)
	6 ifnull (1, 3)
	7 11 (1, 3)
	9 aload_1 (1, 3)
	10 getfield (1, 3)
	11 org/apache/commons/math3/geometry/partitioning/utilities/AVLTree$Node.left:Lorg/apache/commons/math3/geometry/partitioning/utilities/AVLTree$Node; (1, 3)
	13 astore_1 (1, 3)
	14 goto (1, 3)
	15 -12 (1, 3)
	17 aload_1 (0, 0)
	18 areturn (0, 0)

Method: getLargest
	0 aload_0 (0, 0)
	1 astore_1 (0, 0)
	2 aload_1 (1, 3)
	3 getfield (1, 3)
	4 org/apache/commons/math3/geometry/partitioning/utilities/AVLTree$Node.right:Lorg/apache/commons/math3/geometry/partitioning/utilities/AVLTree$Node; (1, 3)
	6 ifnull (1, 3)
	7 11 (1, 3)
	9 aload_1 (1, 3)
	10 getfield (1, 3)
	11 org/apache/commons/math3/geometry/partitioning/utilities/AVLTree$Node.right:Lorg/apache/commons/math3/geometry/partitioning/utilities/AVLTree$Node; (1, 3)
	13 astore_1 (1, 3)
	14 goto (1, 3)
	15 -12 (1, 3)
	17 aload_1 (0, 0)
	18 areturn (0, 0)

Method: getPrevious
	0 aload_0 (1, 1)
	1 getfield (1, 1)
	2 org/apache/commons/math3/geometry/partitioning/utilities/AVLTree$Node.left:Lorg/apache/commons/math3/geometry/partitioning/utilities/AVLTree$Node; (1, 1)
	4 ifnull (1, 1)
	5 17 (1, 1)
	7 aload_0 (1, 1)
	8 getfield (1, 1)
	9 org/apache/commons/math3/geometry/partitioning/utilities/AVLTree$Node.left:Lorg/apache/commons/math3/geometry/partitioning/utilities/AVLTree$Node; (1, 1)
	11 invokevirtual (1, 1)
	12 org/apache/commons/math3/geometry/partitioning/utilities/AVLTree$Node.getLargest:()Lorg/apache/commons/math3/geometry/partitioning/utilities/AVLTree$Node; (1, 1)
	14 astore_1 (1, 1)
	15 aload_1 (2, 1)
	16 ifnull (2, 1)
	17 5 (2, 1)
	19 aload_1 (2, 1)
	20 areturn (2, 1)
	21 aload_0 (1, 4)
	22 astore_1 (1, 4)
	23 aload_1 (1, 4)
	24 getfield (1, 4)
	25 org/apache/commons/math3/geometry/partitioning/utilities/AVLTree$Node.parent:Lorg/apache/commons/math3/geometry/partitioning/utilities/AVLTree$Node; (1, 4)
	27 ifnull (1, 4)
	28 27 (1, 4)
	30 aload_1 (2, 1)
	31 aload_1 (2, 1)
	32 getfield (2, 1)
	33 org/apache/commons/math3/geometry/partitioning/utilities/AVLTree$Node.parent:Lorg/apache/commons/math3/geometry/partitioning/utilities/AVLTree$Node; (2, 1)
	35 getfield (2, 1)
	36 org/apache/commons/math3/geometry/partitioning/utilities/AVLTree$Node.left:Lorg/apache/commons/math3/geometry/partitioning/utilities/AVLTree$Node; (2, 1)
	38 if_acmpeq (2, 1)
	39 8 (2, 1)
	41 aload_1 (2, 1)
	42 getfield (2, 1)
	43 org/apache/commons/math3/geometry/partitioning/utilities/AVLTree$Node.parent:Lorg/apache/commons/math3/geometry/partitioning/utilities/AVLTree$Node; (2, 1)
	45 areturn (2, 1)
	46 aload_1 (2, 1)
	47 getfield (2, 1)
	48 org/apache/commons/math3/geometry/partitioning/utilities/AVLTree$Node.parent:Lorg/apache/commons/math3/geometry/partitioning/utilities/AVLTree$Node; (2, 1)
	50 astore_1 (2, 1)
	51 goto (2, 1)
	52 -28 (2, 1)
	54 aconst_null (1, 4)
	55 areturn (1, 4)

Method: getNext
	0 aload_0 (1, 1)
	1 getfield (1, 1)
	2 org/apache/commons/math3/geometry/partitioning/utilities/AVLTree$Node.right:Lorg/apache/commons/math3/geometry/partitioning/utilities/AVLTree$Node; (1, 1)
	4 ifnull (1, 1)
	5 17 (1, 1)
	7 aload_0 (1, 1)
	8 getfield (1, 1)
	9 org/apache/commons/math3/geometry/partitioning/utilities/AVLTree$Node.right:Lorg/apache/commons/math3/geometry/partitioning/utilities/AVLTree$Node; (1, 1)
	11 invokevirtual (1, 1)
	12 org/apache/commons/math3/geometry/partitioning/utilities/AVLTree$Node.getSmallest:()Lorg/apache/commons/math3/geometry/partitioning/utilities/AVLTree$Node; (1, 1)
	14 astore_1 (1, 1)
	15 aload_1 (2, 1)
	16 ifnull (2, 1)
	17 5 (2, 1)
	19 aload_1 (2, 1)
	20 areturn (2, 1)
	21 aload_0 (1, 4)
	22 astore_1 (1, 4)
	23 aload_1 (1, 4)
	24 getfield (1, 4)
	25 org/apache/commons/math3/geometry/partitioning/utilities/AVLTree$Node.parent:Lorg/apache/commons/math3/geometry/partitioning/utilities/AVLTree$Node; (1, 4)
	27 ifnull (1, 4)
	28 27 (1, 4)
	30 aload_1 (2, 1)
	31 aload_1 (2, 1)
	32 getfield (2, 1)
	33 org/apache/commons/math3/geometry/partitioning/utilities/AVLTree$Node.parent:Lorg/apache/commons/math3/geometry/partitioning/utilities/AVLTree$Node; (2, 1)
	35 getfield (2, 1)
	36 org/apache/commons/math3/geometry/partitioning/utilities/AVLTree$Node.right:Lorg/apache/commons/math3/geometry/partitioning/utilities/AVLTree$Node; (2, 1)
	38 if_acmpeq (2, 1)
	39 8 (2, 1)
	41 aload_1 (2, 1)
	42 getfield (2, 1)
	43 org/apache/commons/math3/geometry/partitioning/utilities/AVLTree$Node.parent:Lorg/apache/commons/math3/geometry/partitioning/utilities/AVLTree$Node; (2, 1)
	45 areturn (2, 1)
	46 aload_1 (2, 1)
	47 getfield (2, 1)
	48 org/apache/commons/math3/geometry/partitioning/utilities/AVLTree$Node.parent:Lorg/apache/commons/math3/geometry/partitioning/utilities/AVLTree$Node; (2, 1)
	50 astore_1 (2, 1)
	51 goto (2, 1)
	52 -28 (2, 1)
	54 aconst_null (1, 4)
	55 areturn (1, 4)

Method: insert
	0 aload_1 (1, 1)
	1 aload_0 (1, 1)
	2 getfield (1, 1)
	3 org/apache/commons/math3/geometry/partitioning/utilities/AVLTree$Node.element:Ljava/lang/Comparable; (1, 1)
	5 invokeinterface (1, 1)
	6 java/lang/Comparable.org/apache/commons/math3/geometry/partitioning/utilities/AVLTree (1, 1)
	8 0 (1, 1)
	10 ifge (1, 1)
	11 52 (1, 1)
	13 aload_0 (2, 1)
	14 getfield (2, 1)
	15 org/apache/commons/math3/geometry/partitioning/utilities/AVLTree$Node.left:Lorg/apache/commons/math3/geometry/partitioning/utilities/AVLTree$Node; (2, 1)
	17 ifnonnull (2, 1)
	18 25 (2, 1)
	20 aload_0 (2, 1)
	21 new (2, 1)
	22 org/apache/commons/math3/geometry/partitioning/utilities/AVLTree$Node (2, 1)
	24 dup (2, 1)
	25 aload_0 (2, 1)
	26 getfield (2, 1)
	27 org/apache/commons/math3/geometry/partitioning/utilities/AVLTree$Node.this$0:Lorg/apache/commons/math3/geometry/partitioning/utilities/AVLTree; (2, 1)
	29 aload_1 (2, 1)
	30 aload_0 (2, 1)
	31 invokespecial (2, 1)
	32 org/apache/commons/math3/geometry/partitioning/utilities/AVLTree$Node.<init>:(Lorg/apache/commons/math3/geometry/partitioning/utilities/AVLTree;Ljava/lang/Comparable;Lorg/apache/commons/math3/geometry/partitioning/utilities/AVLTree$Node;)V (2, 1)
	34 putfield (2, 1)
	35 org/apache/commons/math3/geometry/partitioning/utilities/AVLTree$Node.left:Lorg/apache/commons/math3/geometry/partitioning/utilities/AVLTree$Node; (2, 1)
	37 aload_0 (2, 1)
	38 invokespecial (2, 1)
	39 org/apache/commons/math3/geometry/partitioning/utilities/AVLTree$Node.rebalanceLeftGrown:()Z (2, 1)
	41 ireturn (2, 1)
	42 aload_0 (1, 1)
	43 getfield (1, 1)
	44 org/apache/commons/math3/geometry/partitioning/utilities/AVLTree$Node.left:Lorg/apache/commons/math3/geometry/partitioning/utilities/AVLTree$Node; (1, 1)
	46 aload_1 (1, 1)
	47 invokevirtual (1, 1)
	48 org/apache/commons/math3/geometry/partitioning/utilities/AVLTree$Node.insert:(Ljava/lang/Comparable;)Z (1, 1)
	50 ifeq (1, 1)
	51 10 (1, 1)
	53 aload_0 (1, 1)
	54 invokespecial (1, 1)
	55 org/apache/commons/math3/geometry/partitioning/utilities/AVLTree$Node.rebalanceLeftGrown:()Z (1, 1)
	57 goto (1, 1)
	58 4 (1, 1)
	60 iconst_0 (1, 1)
	61 ireturn (1, 1)
	62 aload_0 (1, 1)
	63 getfield (1, 1)
	64 org/apache/commons/math3/geometry/partitioning/utilities/AVLTree$Node.right:Lorg/apache/commons/math3/geometry/partitioning/utilities/AVLTree$Node; (1, 1)
	66 ifnonnull (1, 1)
	67 25 (1, 1)
	69 aload_0 (1, 1)
	70 new (1, 1)
	71 org/apache/commons/math3/geometry/partitioning/utilities/AVLTree$Node (1, 1)
	73 dup (1, 1)
	74 aload_0 (1, 1)
	75 getfield (1, 1)
	76 org/apache/commons/math3/geometry/partitioning/utilities/AVLTree$Node.this$0:Lorg/apache/commons/math3/geometry/partitioning/utilities/AVLTree; (1, 1)
	78 aload_1 (1, 1)
	79 aload_0 (1, 1)
	80 invokespecial (1, 1)
	81 org/apache/commons/math3/geometry/partitioning/utilities/AVLTree$Node.<init>:(Lorg/apache/commons/math3/geometry/partitioning/utilities/AVLTree;Ljava/lang/Comparable;Lorg/apache/commons/math3/geometry/partitioning/utilities/AVLTree$Node;)V (1, 1)
	83 putfield (1, 1)
	84 org/apache/commons/math3/geometry/partitioning/utilities/AVLTree$Node.right:Lorg/apache/commons/math3/geometry/partitioning/utilities/AVLTree$Node; (1, 1)
	86 aload_0 (1, 1)
	87 invokespecial (1, 1)
	88 org/apache/commons/math3/geometry/partitioning/utilities/AVLTree$Node.rebalanceRightGrown:()Z (1, 1)
	90 ireturn (1, 1)
	91 aload_0 (0, 0)
	92 getfield (0, 0)
	93 org/apache/commons/math3/geometry/partitioning/utilities/AVLTree$Node.right:Lorg/apache/commons/math3/geometry/partitioning/utilities/AVLTree$Node; (0, 0)
	95 aload_1 (0, 0)
	96 invokevirtual (0, 0)
	97 org/apache/commons/math3/geometry/partitioning/utilities/AVLTree$Node.insert:(Ljava/lang/Comparable;)Z (0, 0)
	99 ifeq (0, 0)
	100 10 (0, 0)
	102 aload_0 (0, 0)
	103 invokespecial (0, 0)
	104 org/apache/commons/math3/geometry/partitioning/utilities/AVLTree$Node.rebalanceRightGrown:()Z (0, 0)
	106 goto (0, 0)
	107 4 (0, 0)
	109 iconst_0 (0, 0)
	110 ireturn (0, 0)

Method: delete
	0 aload_0 (1, 1)
	1 getfield (1, 1)
	2 org/apache/commons/math3/geometry/partitioning/utilities/AVLTree$Node.parent:Lorg/apache/commons/math3/geometry/partitioning/utilities/AVLTree$Node; (1, 1)
	4 ifnonnull (1, 1)
	5 34 (1, 1)
	7 aload_0 (1, 1)
	8 getfield (1, 1)
	9 org/apache/commons/math3/geometry/partitioning/utilities/AVLTree$Node.left:Lorg/apache/commons/math3/geometry/partitioning/utilities/AVLTree$Node; (1, 1)
	11 ifnonnull (1, 1)
	12 27 (1, 1)
	14 aload_0 (1, 1)
	15 getfield (1, 1)
	16 org/apache/commons/math3/geometry/partitioning/utilities/AVLTree$Node.right:Lorg/apache/commons/math3/geometry/partitioning/utilities/AVLTree$Node; (1, 1)
	18 ifnonnull (1, 1)
	19 20 (1, 1)
	21 aload_0 (1, 1)
	22 aconst_null (1, 1)
	23 putfield (1, 1)
	24 org/apache/commons/math3/geometry/partitioning/utilities/AVLTree$Node.element:Ljava/lang/Comparable; (1, 1)
	26 aload_0 (1, 1)
	27 getfield (1, 1)
	28 org/apache/commons/math3/geometry/partitioning/utilities/AVLTree$Node.this$0:Lorg/apache/commons/math3/geometry/partitioning/utilities/AVLTree; (1, 1)
	30 aconst_null (1, 1)
	31 invokestatic (1, 1)
	32 org/apache/commons/math3/geometry/partitioning/utilities/AVLTree.access$302:(Lorg/apache/commons/math3/geometry/partitioning/utilities/AVLTree;Lorg/apache/commons/math3/geometry/partitioning/utilities/AVLTree$Node;)Lorg/apache/commons/math3/geometry/partitioning/utilities/AVLTree$Node; (1, 1)
	34 pop (1, 1)
	35 goto (1, 1)
	36 200 (1, 1)
	38 aload_0 (2, 1)
	39 getfield (2, 1)
	40 org/apache/commons/math3/geometry/partitioning/utilities/AVLTree$Node.left:Lorg/apache/commons/math3/geometry/partitioning/utilities/AVLTree$Node; (2, 1)
	42 ifnonnull (2, 1)
	43 39 (2, 1)
	45 aload_0 (2, 1)
	46 getfield (2, 1)
	47 org/apache/commons/math3/geometry/partitioning/utilities/AVLTree$Node.right:Lorg/apache/commons/math3/geometry/partitioning/utilities/AVLTree$Node; (2, 1)
	49 ifnonnull (2, 1)
	50 32 (2, 1)
	52 aload_0 (2, 1)
	53 astore_1 (2, 1)
	54 aload_0 (2, 1)
	55 aconst_null (2, 1)
	56 putfield (2, 1)
	57 org/apache/commons/math3/geometry/partitioning/utilities/AVLTree$Node.element:Ljava/lang/Comparable; (2, 1)
	59 aload_1 (2, 1)
	60 aload_1 (2, 1)
	61 getfield (2, 1)
	62 org/apache/commons/math3/geometry/partitioning/utilities/AVLTree$Node.parent:Lorg/apache/commons/math3/geometry/partitioning/utilities/AVLTree$Node; (2, 1)
	64 getfield (2, 1)
	65 org/apache/commons/math3/geometry/partitioning/utilities/AVLTree$Node.left:Lorg/apache/commons/math3/geometry/partitioning/utilities/AVLTree$Node; (2, 1)
	67 if_acmpne (2, 1)
	68 7 (2, 1)
	70 iconst_1 (2, 1)
	71 goto (2, 1)
	72 4 (2, 1)
	74 iconst_0 (2, 1)
	75 istore_3 (2, 1)
	76 aconst_null (2, 1)
	77 astore_2 (2, 1)
	78 goto (2, 1)
	79 72 (2, 1)
	81 aload_0 (2, 2)
	82 getfield (2, 2)
	83 org/apache/commons/math3/geometry/partitioning/utilities/AVLTree$Node.left:Lorg/apache/commons/math3/geometry/partitioning/utilities/AVLTree$Node; (2, 2)
	85 ifnull (2, 2)
	86 13 (2, 2)
	88 aload_0 (2, 2)
	89 getfield (2, 2)
	90 org/apache/commons/math3/geometry/partitioning/utilities/AVLTree$Node.left:Lorg/apache/commons/math3/geometry/partitioning/utilities/AVLTree$Node; (2, 2)
	92 invokevirtual (2, 2)
	93 org/apache/commons/math3/geometry/partitioning/utilities/AVLTree$Node.getLargest:()Lorg/apache/commons/math3/geometry/partitioning/utilities/AVLTree$Node; (2, 2)
	95 goto (2, 2)
	96 10 (2, 2)
	98 aload_0 (2, 2)
	99 getfield (2, 2)
	100 org/apache/commons/math3/geometry/partitioning/utilities/AVLTree$Node.right:Lorg/apache/commons/math3/geometry/partitioning/utilities/AVLTree$Node; (2, 2)
	102 invokevirtual (2, 2)
	103 org/apache/commons/math3/geometry/partitioning/utilities/AVLTree$Node.getSmallest:()Lorg/apache/commons/math3/geometry/partitioning/utilities/AVLTree$Node; (2, 2)
	105 astore_1 (2, 2)
	106 aload_0 (2, 2)
	107 aload_1 (2, 2)
	108 getfield (2, 2)
	109 org/apache/commons/math3/geometry/partitioning/utilities/AVLTree$Node.element:Ljava/lang/Comparable; (2, 2)
	111 putfield (2, 2)
	112 org/apache/commons/math3/geometry/partitioning/utilities/AVLTree$Node.element:Ljava/lang/Comparable; (2, 2)
	114 aload_1 (2, 2)
	115 aload_1 (2, 2)
	116 getfield (2, 2)
	117 org/apache/commons/math3/geometry/partitioning/utilities/AVLTree$Node.parent:Lorg/apache/commons/math3/geometry/partitioning/utilities/AVLTree$Node; (2, 2)
	119 getfield (2, 2)
	120 org/apache/commons/math3/geometry/partitioning/utilities/AVLTree$Node.left:Lorg/apache/commons/math3/geometry/partitioning/utilities/AVLTree$Node; (2, 2)
	122 if_acmpne (2, 2)
	123 7 (2, 2)
	125 iconst_1 (2, 2)
	126 goto (2, 2)
	127 4 (2, 2)
	129 iconst_0 (2, 2)
	130 istore_3 (2, 2)
	131 aload_1 (2, 2)
	132 getfield (2, 2)
	133 org/apache/commons/math3/geometry/partitioning/utilities/AVLTree$Node.left:Lorg/apache/commons/math3/geometry/partitioning/utilities/AVLTree$Node; (2, 2)
	135 ifnull (2, 2)
	136 10 (2, 2)
	138 aload_1 (2, 2)
	139 getfield (2, 2)
	140 org/apache/commons/math3/geometry/partitioning/utilities/AVLTree$Node.left:Lorg/apache/commons/math3/geometry/partitioning/utilities/AVLTree$Node; (2, 2)
	142 goto (2, 2)
	143 7 (2, 2)
	145 aload_1 (2, 2)
	146 getfield (2, 2)
	147 org/apache/commons/math3/geometry/partitioning/utilities/AVLTree$Node.right:Lorg/apache/commons/math3/geometry/partitioning/utilities/AVLTree$Node; (2, 2)
	149 astore_2 (2, 2)
	150 aload_1 (1, 2)
	151 getfield (1, 2)
	152 org/apache/commons/math3/geometry/partitioning/utilities/AVLTree$Node.parent:Lorg/apache/commons/math3/geometry/partitioning/utilities/AVLTree$Node; (1, 2)
	154 astore_1 (1, 2)
	155 iload_3 (2, 1)
	156 ifeq (2, 1)
	157 11 (2, 1)
	159 aload_1 (2, 1)
	160 aload_2 (2, 1)
	161 putfield (2, 1)
	162 org/apache/commons/math3/geometry/partitioning/utilities/AVLTree$Node.left:Lorg/apache/commons/math3/geometry/partitioning/utilities/AVLTree$Node; (2, 1)
	164 goto (2, 1)
	165 8 (2, 1)
	167 aload_1 (2, 2)
	168 aload_2 (2, 2)
	169 putfield (2, 2)
	170 org/apache/commons/math3/geometry/partitioning/utilities/AVLTree$Node.right:Lorg/apache/commons/math3/geometry/partitioning/utilities/AVLTree$Node; (2, 2)
	172 aload_2 (2, 1)
	173 ifnull (2, 1)
	174 8 (2, 1)
	176 aload_2 (2, 1)
	177 aload_1 (2, 1)
	178 putfield (2, 1)
	179 org/apache/commons/math3/geometry/partitioning/utilities/AVLTree$Node.parent:Lorg/apache/commons/math3/geometry/partitioning/utilities/AVLTree$Node; (2, 1)
	181 iload_3 (2, 3)
	182 ifeq (2, 3)
	183 13 (2, 3)
	185 aload_1 (2, 3)
	186 invokespecial (2, 3)
	187 org/apache/commons/math3/geometry/partitioning/utilities/AVLTree$Node.rebalanceLeftShrunk:()Z (2, 3)
	189 ifeq (2, 3)
	190 46 (2, 3)
	192 goto (2, 3)
	193 10 (2, 3)
	195 aload_1 (2, 3)
	196 invokespecial (2, 3)
	197 org/apache/commons/math3/geometry/partitioning/utilities/AVLTree$Node.rebalanceRightShrunk:()Z (2, 3)
	199 ifeq (2, 3)
	200 36 (2, 3)
	202 aload_1 (3, 1)
	203 getfield (3, 1)
	204 org/apache/commons/math3/geometry/partitioning/utilities/AVLTree$Node.parent:Lorg/apache/commons/math3/geometry/partitioning/utilities/AVLTree$Node; (3, 1)
	206 ifnonnull (3, 1)
	207 4 (3, 1)
	209 return (3, 1)
	210 aload_1 (2, 3)
	211 aload_1 (2, 3)
	212 getfield (2, 3)
	213 org/apache/commons/math3/geometry/partitioning/utilities/AVLTree$Node.parent:Lorg/apache/commons/math3/geometry/partitioning/utilities/AVLTree$Node; (2, 3)
	215 getfield (2, 3)
	216 org/apache/commons/math3/geometry/partitioning/utilities/AVLTree$Node.left:Lorg/apache/commons/math3/geometry/partitioning/utilities/AVLTree$Node; (2, 3)
	218 if_acmpne (2, 3)
	219 7 (2, 3)
	221 iconst_1 (2, 3)
	222 goto (2, 3)
	223 4 (2, 3)
	225 iconst_0 (2, 3)
	226 istore_3 (2, 3)
	227 aload_1 (2, 3)
	228 getfield (2, 3)
	229 org/apache/commons/math3/geometry/partitioning/utilities/AVLTree$Node.parent:Lorg/apache/commons/math3/geometry/partitioning/utilities/AVLTree$Node; (2, 3)
	231 astore_1 (2, 3)
	232 goto (2, 3)
	233 -51 (2, 3)
	235 return (0, 0)

Method: rebalanceLeftGrown
	0 getstatic (1, 5)
	1 org/apache/commons/math3/geometry/partitioning/utilities/AVLTree$1.$SwitchMap$org$apache$commons$math3$geometry$partitioning$utilities$AVLTree$Skew:[I (1, 5)
	3 aload_0 (1, 5)
	4 getfield (1, 5)
	5 org/apache/commons/math3/geometry/partitioning/utilities/AVLTree$Node.skew:Lorg/apache/commons/math3/geometry/partitioning/utilities/AVLTree$Skew; (1, 5)
	7 invokevirtual (1, 5)
	8 org/apache/commons/math3/geometry/partitioning/utilities/AVLTree$Skew.ordinal:()I (1, 5)
	10 iaload (1, 5)
	11 lookupswitch (1, 5)
	12 1: 36 (1, 5)
	16 2: 203 (1, 5)
	36 aload_0 (2, 1)
	37 getfield (2, 1)
	38 org/apache/commons/math3/geometry/partitioning/utilities/AVLTree$Node.left:Lorg/apache/commons/math3/geometry/partitioning/utilities/AVLTree$Node; (2, 1)
	40 getfield (2, 1)
	41 org/apache/commons/math3/geometry/partitioning/utilities/AVLTree$Node.skew:Lorg/apache/commons/math3/geometry/partitioning/utilities/AVLTree$Skew; (2, 1)
	43 getstatic (2, 1)
	44 org/apache/commons/math3/geometry/partitioning/utilities/AVLTree$Skew.LEFT_HIGH:Lorg/apache/commons/math3/geometry/partitioning/utilities/AVLTree$Skew; (2, 1)
	46 if_acmpne (2, 1)
	47 27 (2, 1)
	49 aload_0 (2, 1)
	50 invokespecial (2, 1)
	51 org/apache/commons/math3/geometry/partitioning/utilities/AVLTree$Node.rotateCW:()V (2, 1)
	53 aload_0 (2, 1)
	54 getstatic (2, 1)
	55 org/apache/commons/math3/geometry/partitioning/utilities/AVLTree$Skew.BALANCED:Lorg/apache/commons/math3/geometry/partitioning/utilities/AVLTree$Skew; (2, 1)
	57 putfield (2, 1)
	58 org/apache/commons/math3/geometry/partitioning/utilities/AVLTree$Node.skew:Lorg/apache/commons/math3/geometry/partitioning/utilities/AVLTree$Skew; (2, 1)
	60 aload_0 (2, 1)
	61 getfield (2, 1)
	62 org/apache/commons/math3/geometry/partitioning/utilities/AVLTree$Node.right:Lorg/apache/commons/math3/geometry/partitioning/utilities/AVLTree$Node; (2, 1)
	64 getstatic (2, 1)
	65 org/apache/commons/math3/geometry/partitioning/utilities/AVLTree$Skew.BALANCED:Lorg/apache/commons/math3/geometry/partitioning/utilities/AVLTree$Skew; (2, 1)
	67 putfield (2, 1)
	68 org/apache/commons/math3/geometry/partitioning/utilities/AVLTree$Node.skew:Lorg/apache/commons/math3/geometry/partitioning/utilities/AVLTree$Skew; (2, 1)
	70 goto (2, 1)
	71 131 (2, 1)
	73 aload_0 (2, 2)
	74 getfield (2, 2)
	75 org/apache/commons/math3/geometry/partitioning/utilities/AVLTree$Node.left:Lorg/apache/commons/math3/geometry/partitioning/utilities/AVLTree$Node; (2, 2)
	77 getfield (2, 2)
	78 org/apache/commons/math3/geometry/partitioning/utilities/AVLTree$Node.right:Lorg/apache/commons/math3/geometry/partitioning/utilities/AVLTree$Node; (2, 2)
	80 getfield (2, 2)
	81 org/apache/commons/math3/geometry/partitioning/utilities/AVLTree$Node.skew:Lorg/apache/commons/math3/geometry/partitioning/utilities/AVLTree$Skew; (2, 2)
	83 astore_1 (2, 2)
	84 aload_0 (2, 2)
	85 getfield (2, 2)
	86 org/apache/commons/math3/geometry/partitioning/utilities/AVLTree$Node.left:Lorg/apache/commons/math3/geometry/partitioning/utilities/AVLTree$Node; (2, 2)
	88 invokespecial (2, 2)
	89 org/apache/commons/math3/geometry/partitioning/utilities/AVLTree$Node.rotateCCW:()V (2, 2)
	91 aload_0 (2, 2)
	92 invokespecial (2, 2)
	93 org/apache/commons/math3/geometry/partitioning/utilities/AVLTree$Node.rotateCW:()V (2, 2)
	95 getstatic (3, 5)
	96 org/apache/commons/math3/geometry/partitioning/utilities/AVLTree$1.$SwitchMap$org$apache$commons$math3$geometry$partitioning$utilities$AVLTree$Skew:[I (3, 5)
	98 aload_1 (3, 5)
	99 invokevirtual (3, 5)
	100 org/apache/commons/math3/geometry/partitioning/utilities/AVLTree$Skew.ordinal:()I (3, 5)
	102 iaload (3, 5)
	103 lookupswitch (3, 5)
	104 1: 128 (3, 5)
	108 2: 151 (3, 5)
	128 aload_0 (3, 5)
	129 getfield (3, 5)
	130 org/apache/commons/math3/geometry/partitioning/utilities/AVLTree$Node.left:Lorg/apache/commons/math3/geometry/partitioning/utilities/AVLTree$Node; (3, 5)
	132 getstatic (3, 5)
	133 org/apache/commons/math3/geometry/partitioning/utilities/AVLTree$Skew.BALANCED:Lorg/apache/commons/math3/geometry/partitioning/utilities/AVLTree$Skew; (3, 5)
	135 putfield (3, 5)
	136 org/apache/commons/math3/geometry/partitioning/utilities/AVLTree$Node.skew:Lorg/apache/commons/math3/geometry/partitioning/utilities/AVLTree$Skew; (3, 5)
	138 aload_0 (3, 5)
	139 getfield (3, 5)
	140 org/apache/commons/math3/geometry/partitioning/utilities/AVLTree$Node.right:Lorg/apache/commons/math3/geometry/partitioning/utilities/AVLTree$Node; (3, 5)
	142 getstatic (3, 5)
	143 org/apache/commons/math3/geometry/partitioning/utilities/AVLTree$Skew.RIGHT_HIGH:Lorg/apache/commons/math3/geometry/partitioning/utilities/AVLTree$Skew; (3, 5)
	145 putfield (3, 5)
	146 org/apache/commons/math3/geometry/partitioning/utilities/AVLTree$Node.skew:Lorg/apache/commons/math3/geometry/partitioning/utilities/AVLTree$Skew; (3, 5)
	148 goto (3, 5)
	149 46 (3, 5)
	151 aload_0 (3, 5)
	152 getfield (3, 5)
	153 org/apache/commons/math3/geometry/partitioning/utilities/AVLTree$Node.left:Lorg/apache/commons/math3/geometry/partitioning/utilities/AVLTree$Node; (3, 5)
	155 getstatic (3, 5)
	156 org/apache/commons/math3/geometry/partitioning/utilities/AVLTree$Skew.LEFT_HIGH:Lorg/apache/commons/math3/geometry/partitioning/utilities/AVLTree$Skew; (3, 5)
	158 putfield (3, 5)
	159 org/apache/commons/math3/geometry/partitioning/utilities/AVLTree$Node.skew:Lorg/apache/commons/math3/geometry/partitioning/utilities/AVLTree$Skew; (3, 5)
	161 aload_0 (3, 5)
	162 getfield (3, 5)
	163 org/apache/commons/math3/geometry/partitioning/utilities/AVLTree$Node.right:Lorg/apache/commons/math3/geometry/partitioning/utilities/AVLTree$Node; (3, 5)
	165 getstatic (3, 5)
	166 org/apache/commons/math3/geometry/partitioning/utilities/AVLTree$Skew.BALANCED:Lorg/apache/commons/math3/geometry/partitioning/utilities/AVLTree$Skew; (3, 5)
	168 putfield (3, 5)
	169 org/apache/commons/math3/geometry/partitioning/utilities/AVLTree$Node.skew:Lorg/apache/commons/math3/geometry/partitioning/utilities/AVLTree$Skew; (3, 5)
	171 goto (3, 5)
	172 23 (3, 5)
	174 aload_0 (3, 5)
	175 getfield (3, 5)
	176 org/apache/commons/math3/geometry/partitioning/utilities/AVLTree$Node.left:Lorg/apache/commons/math3/geometry/partitioning/utilities/AVLTree$Node; (3, 5)
	178 getstatic (3, 5)
	179 org/apache/commons/math3/geometry/partitioning/utilities/AVLTree$Skew.BALANCED:Lorg/apache/commons/math3/geometry/partitioning/utilities/AVLTree$Skew; (3, 5)
	181 putfield (3, 5)
	182 org/apache/commons/math3/geometry/partitioning/utilities/AVLTree$Node.skew:Lorg/apache/commons/math3/geometry/partitioning/utilities/AVLTree$Skew; (3, 5)
	184 aload_0 (3, 5)
	185 getfield (3, 5)
	186 org/apache/commons/math3/geometry/partitioning/utilities/AVLTree$Node.right:Lorg/apache/commons/math3/geometry/partitioning/utilities/AVLTree$Node; (3, 5)
	188 getstatic (3, 5)
	189 org/apache/commons/math3/geometry/partitioning/utilities/AVLTree$Skew.BALANCED:Lorg/apache/commons/math3/geometry/partitioning/utilities/AVLTree$Skew; (3, 5)
	191 putfield (3, 5)
	192 org/apache/commons/math3/geometry/partitioning/utilities/AVLTree$Node.skew:Lorg/apache/commons/math3/geometry/partitioning/utilities/AVLTree$Skew; (3, 5)
	194 aload_0 (2, 2)
	195 getstatic (2, 2)
	196 org/apache/commons/math3/geometry/partitioning/utilities/AVLTree$Skew.BALANCED:Lorg/apache/commons/math3/geometry/partitioning/utilities/AVLTree$Skew; (2, 2)
	198 putfield (2, 2)
	199 org/apache/commons/math3/geometry/partitioning/utilities/AVLTree$Node.skew:Lorg/apache/commons/math3/geometry/partitioning/utilities/AVLTree$Skew; (2, 2)
	201 iconst_0 (1, 5)
	202 ireturn (1, 5)
	203 aload_0 (1, 5)
	204 getstatic (1, 5)
	205 org/apache/commons/math3/geometry/partitioning/utilities/AVLTree$Skew.BALANCED:Lorg/apache/commons/math3/geometry/partitioning/utilities/AVLTree$Skew; (1, 5)
	207 putfield (1, 5)
	208 org/apache/commons/math3/geometry/partitioning/utilities/AVLTree$Node.skew:Lorg/apache/commons/math3/geometry/partitioning/utilities/AVLTree$Skew; (1, 5)
	210 iconst_0 (1, 5)
	211 ireturn (1, 5)
	212 aload_0 (1, 5)
	213 getstatic (1, 5)
	214 org/apache/commons/math3/geometry/partitioning/utilities/AVLTree$Skew.LEFT_HIGH:Lorg/apache/commons/math3/geometry/partitioning/utilities/AVLTree$Skew; (1, 5)
	216 putfield (1, 5)
	217 org/apache/commons/math3/geometry/partitioning/utilities/AVLTree$Node.skew:Lorg/apache/commons/math3/geometry/partitioning/utilities/AVLTree$Skew; (1, 5)
	219 iconst_1 (1, 5)
	220 ireturn (1, 5)

Method: rebalanceRightGrown
	0 getstatic (1, 5)
	1 org/apache/commons/math3/geometry/partitioning/utilities/AVLTree$1.$SwitchMap$org$apache$commons$math3$geometry$partitioning$utilities$AVLTree$Skew:[I (1, 5)
	3 aload_0 (1, 5)
	4 getfield (1, 5)
	5 org/apache/commons/math3/geometry/partitioning/utilities/AVLTree$Node.skew:Lorg/apache/commons/math3/geometry/partitioning/utilities/AVLTree$Skew; (1, 5)
	7 invokevirtual (1, 5)
	8 org/apache/commons/math3/geometry/partitioning/utilities/AVLTree$Skew.ordinal:()I (1, 5)
	10 iaload (1, 5)
	11 lookupswitch (1, 5)
	12 1: 36 (1, 5)
	16 2: 45 (1, 5)
	36 aload_0 (1, 5)
	37 getstatic (1, 5)
	38 org/apache/commons/math3/geometry/partitioning/utilities/AVLTree$Skew.BALANCED:Lorg/apache/commons/math3/geometry/partitioning/utilities/AVLTree$Skew; (1, 5)
	40 putfield (1, 5)
	41 org/apache/commons/math3/geometry/partitioning/utilities/AVLTree$Node.skew:Lorg/apache/commons/math3/geometry/partitioning/utilities/AVLTree$Skew; (1, 5)
	43 iconst_0 (1, 5)
	44 ireturn (1, 5)
	45 aload_0 (2, 1)
	46 getfield (2, 1)
	47 org/apache/commons/math3/geometry/partitioning/utilities/AVLTree$Node.right:Lorg/apache/commons/math3/geometry/partitioning/utilities/AVLTree$Node; (2, 1)
	49 getfield (2, 1)
	50 org/apache/commons/math3/geometry/partitioning/utilities/AVLTree$Node.skew:Lorg/apache/commons/math3/geometry/partitioning/utilities/AVLTree$Skew; (2, 1)
	52 getstatic (2, 1)
	53 org/apache/commons/math3/geometry/partitioning/utilities/AVLTree$Skew.RIGHT_HIGH:Lorg/apache/commons/math3/geometry/partitioning/utilities/AVLTree$Skew; (2, 1)
	55 if_acmpne (2, 1)
	56 27 (2, 1)
	58 aload_0 (2, 1)
	59 invokespecial (2, 1)
	60 org/apache/commons/math3/geometry/partitioning/utilities/AVLTree$Node.rotateCCW:()V (2, 1)
	62 aload_0 (2, 1)
	63 getstatic (2, 1)
	64 org/apache/commons/math3/geometry/partitioning/utilities/AVLTree$Skew.BALANCED:Lorg/apache/commons/math3/geometry/partitioning/utilities/AVLTree$Skew; (2, 1)
	66 putfield (2, 1)
	67 org/apache/commons/math3/geometry/partitioning/utilities/AVLTree$Node.skew:Lorg/apache/commons/math3/geometry/partitioning/utilities/AVLTree$Skew; (2, 1)
	69 aload_0 (2, 1)
	70 getfield (2, 1)
	71 org/apache/commons/math3/geometry/partitioning/utilities/AVLTree$Node.left:Lorg/apache/commons/math3/geometry/partitioning/utilities/AVLTree$Node; (2, 1)
	73 getstatic (2, 1)
	74 org/apache/commons/math3/geometry/partitioning/utilities/AVLTree$Skew.BALANCED:Lorg/apache/commons/math3/geometry/partitioning/utilities/AVLTree$Skew; (2, 1)
	76 putfield (2, 1)
	77 org/apache/commons/math3/geometry/partitioning/utilities/AVLTree$Node.skew:Lorg/apache/commons/math3/geometry/partitioning/utilities/AVLTree$Skew; (2, 1)
	79 goto (2, 1)
	80 134 (2, 1)
	82 aload_0 (2, 2)
	83 getfield (2, 2)
	84 org/apache/commons/math3/geometry/partitioning/utilities/AVLTree$Node.right:Lorg/apache/commons/math3/geometry/partitioning/utilities/AVLTree$Node; (2, 2)
	86 getfield (2, 2)
	87 org/apache/commons/math3/geometry/partitioning/utilities/AVLTree$Node.left:Lorg/apache/commons/math3/geometry/partitioning/utilities/AVLTree$Node; (2, 2)
	89 getfield (2, 2)
	90 org/apache/commons/math3/geometry/partitioning/utilities/AVLTree$Node.skew:Lorg/apache/commons/math3/geometry/partitioning/utilities/AVLTree$Skew; (2, 2)
	92 astore_1 (2, 2)
	93 aload_0 (2, 2)
	94 getfield (2, 2)
	95 org/apache/commons/math3/geometry/partitioning/utilities/AVLTree$Node.right:Lorg/apache/commons/math3/geometry/partitioning/utilities/AVLTree$Node; (2, 2)
	97 invokespecial (2, 2)
	98 org/apache/commons/math3/geometry/partitioning/utilities/AVLTree$Node.rotateCW:()V (2, 2)
	100 aload_0 (2, 2)
	101 invokespecial (2, 2)
	102 org/apache/commons/math3/geometry/partitioning/utilities/AVLTree$Node.rotateCCW:()V (2, 2)
	104 getstatic (3, 5)
	105 org/apache/commons/math3/geometry/partitioning/utilities/AVLTree$1.$SwitchMap$org$apache$commons$math3$geometry$partitioning$utilities$AVLTree$Skew:[I (3, 5)
	107 aload_1 (3, 5)
	108 invokevirtual (3, 5)
	109 org/apache/commons/math3/geometry/partitioning/utilities/AVLTree$Skew.ordinal:()I (3, 5)
	111 iaload (3, 5)
	112 lookupswitch (3, 5)
	113 1: 140 (3, 5)
	117 2: 163 (3, 5)
	140 aload_0 (3, 5)
	141 getfield (3, 5)
	142 org/apache/commons/math3/geometry/partitioning/utilities/AVLTree$Node.left:Lorg/apache/commons/math3/geometry/partitioning/utilities/AVLTree$Node; (3, 5)
	144 getstatic (3, 5)
	145 org/apache/commons/math3/geometry/partitioning/utilities/AVLTree$Skew.BALANCED:Lorg/apache/commons/math3/geometry/partitioning/utilities/AVLTree$Skew; (3, 5)
	147 putfield (3, 5)
	148 org/apache/commons/math3/geometry/partitioning/utilities/AVLTree$Node.skew:Lorg/apache/commons/math3/geometry/partitioning/utilities/AVLTree$Skew; (3, 5)
	150 aload_0 (3, 5)
	151 getfield (3, 5)
	152 org/apache/commons/math3/geometry/partitioning/utilities/AVLTree$Node.right:Lorg/apache/commons/math3/geometry/partitioning/utilities/AVLTree$Node; (3, 5)
	154 getstatic (3, 5)
	155 org/apache/commons/math3/geometry/partitioning/utilities/AVLTree$Skew.RIGHT_HIGH:Lorg/apache/commons/math3/geometry/partitioning/utilities/AVLTree$Skew; (3, 5)
	157 putfield (3, 5)
	158 org/apache/commons/math3/geometry/partitioning/utilities/AVLTree$Node.skew:Lorg/apache/commons/math3/geometry/partitioning/utilities/AVLTree$Skew; (3, 5)
	160 goto (3, 5)
	161 46 (3, 5)
	163 aload_0 (3, 5)
	164 getfield (3, 5)
	165 org/apache/commons/math3/geometry/partitioning/utilities/AVLTree$Node.left:Lorg/apache/commons/math3/geometry/partitioning/utilities/AVLTree$Node; (3, 5)
	167 getstatic (3, 5)
	168 org/apache/commons/math3/geometry/partitioning/utilities/AVLTree$Skew.LEFT_HIGH:Lorg/apache/commons/math3/geometry/partitioning/utilities/AVLTree$Skew; (3, 5)
	170 putfield (3, 5)
	171 org/apache/commons/math3/geometry/partitioning/utilities/AVLTree$Node.skew:Lorg/apache/commons/math3/geometry/partitioning/utilities/AVLTree$Skew; (3, 5)
	173 aload_0 (3, 5)
	174 getfield (3, 5)
	175 org/apache/commons/math3/geometry/partitioning/utilities/AVLTree$Node.right:Lorg/apache/commons/math3/geometry/partitioning/utilities/AVLTree$Node; (3, 5)
	177 getstatic (3, 5)
	178 org/apache/commons/math3/geometry/partitioning/utilities/AVLTree$Skew.BALANCED:Lorg/apache/commons/math3/geometry/partitioning/utilities/AVLTree$Skew; (3, 5)
	180 putfield (3, 5)
	181 org/apache/commons/math3/geometry/partitioning/utilities/AVLTree$Node.skew:Lorg/apache/commons/math3/geometry/partitioning/utilities/AVLTree$Skew; (3, 5)
	183 goto (3, 5)
	184 23 (3, 5)
	186 aload_0 (3, 5)
	187 getfield (3, 5)
	188 org/apache/commons/math3/geometry/partitioning/utilities/AVLTree$Node.left:Lorg/apache/commons/math3/geometry/partitioning/utilities/AVLTree$Node; (3, 5)
	190 getstatic (3, 5)
	191 org/apache/commons/math3/geometry/partitioning/utilities/AVLTree$Skew.BALANCED:Lorg/apache/commons/math3/geometry/partitioning/utilities/AVLTree$Skew; (3, 5)
	193 putfield (3, 5)
	194 org/apache/commons/math3/geometry/partitioning/utilities/AVLTree$Node.skew:Lorg/apache/commons/math3/geometry/partitioning/utilities/AVLTree$Skew; (3, 5)
	196 aload_0 (3, 5)
	197 getfield (3, 5)
	198 org/apache/commons/math3/geometry/partitioning/utilities/AVLTree$Node.right:Lorg/apache/commons/math3/geometry/partitioning/utilities/AVLTree$Node; (3, 5)
	200 getstatic (3, 5)
	201 org/apache/commons/math3/geometry/partitioning/utilities/AVLTree$Skew.BALANCED:Lorg/apache/commons/math3/geometry/partitioning/utilities/AVLTree$Skew; (3, 5)
	203 putfield (3, 5)
	204 org/apache/commons/math3/geometry/partitioning/utilities/AVLTree$Node.skew:Lorg/apache/commons/math3/geometry/partitioning/utilities/AVLTree$Skew; (3, 5)
	206 aload_0 (2, 2)
	207 getstatic (2, 2)
	208 org/apache/commons/math3/geometry/partitioning/utilities/AVLTree$Skew.BALANCED:Lorg/apache/commons/math3/geometry/partitioning/utilities/AVLTree$Skew; (2, 2)
	210 putfield (2, 2)
	211 org/apache/commons/math3/geometry/partitioning/utilities/AVLTree$Node.skew:Lorg/apache/commons/math3/geometry/partitioning/utilities/AVLTree$Skew; (2, 2)
	213 iconst_0 (1, 5)
	214 ireturn (1, 5)
	215 aload_0 (1, 5)
	216 getstatic (1, 5)
	217 org/apache/commons/math3/geometry/partitioning/utilities/AVLTree$Skew.RIGHT_HIGH:Lorg/apache/commons/math3/geometry/partitioning/utilities/AVLTree$Skew; (1, 5)
	219 putfield (1, 5)
	220 org/apache/commons/math3/geometry/partitioning/utilities/AVLTree$Node.skew:Lorg/apache/commons/math3/geometry/partitioning/utilities/AVLTree$Skew; (1, 5)
	222 iconst_1 (1, 5)
	223 ireturn (1, 5)

Method: rebalanceLeftShrunk
	0 getstatic (1, 5)
	1 org/apache/commons/math3/geometry/partitioning/utilities/AVLTree$1.$SwitchMap$org$apache$commons$math3$geometry$partitioning$utilities$AVLTree$Skew:[I (1, 5)
	3 aload_0 (1, 5)
	4 getfield (1, 5)
	5 org/apache/commons/math3/geometry/partitioning/utilities/AVLTree$Node.skew:Lorg/apache/commons/math3/geometry/partitioning/utilities/AVLTree$Skew; (1, 5)
	7 invokevirtual (1, 5)
	8 org/apache/commons/math3/geometry/partitioning/utilities/AVLTree$Skew.ordinal:()I (1, 5)
	10 iaload (1, 5)
	11 lookupswitch (1, 5)
	12 1: 36 (1, 5)
	16 2: 45 (1, 5)
	36 aload_0 (1, 5)
	37 getstatic (1, 5)
	38 org/apache/commons/math3/geometry/partitioning/utilities/AVLTree$Skew.BALANCED:Lorg/apache/commons/math3/geometry/partitioning/utilities/AVLTree$Skew; (1, 5)
	40 putfield (1, 5)
	41 org/apache/commons/math3/geometry/partitioning/utilities/AVLTree$Node.skew:Lorg/apache/commons/math3/geometry/partitioning/utilities/AVLTree$Skew; (1, 5)
	43 iconst_1 (1, 5)
	44 ireturn (1, 5)
	45 aload_0 (2, 1)
	46 getfield (2, 1)
	47 org/apache/commons/math3/geometry/partitioning/utilities/AVLTree$Node.right:Lorg/apache/commons/math3/geometry/partitioning/utilities/AVLTree$Node; (2, 1)
	49 getfield (2, 1)
	50 org/apache/commons/math3/geometry/partitioning/utilities/AVLTree$Node.skew:Lorg/apache/commons/math3/geometry/partitioning/utilities/AVLTree$Skew; (2, 1)
	52 getstatic (2, 1)
	53 org/apache/commons/math3/geometry/partitioning/utilities/AVLTree$Skew.RIGHT_HIGH:Lorg/apache/commons/math3/geometry/partitioning/utilities/AVLTree$Skew; (2, 1)
	55 if_acmpne (2, 1)
	56 26 (2, 1)
	58 aload_0 (2, 1)
	59 invokespecial (2, 1)
	60 org/apache/commons/math3/geometry/partitioning/utilities/AVLTree$Node.rotateCCW:()V (2, 1)
	62 aload_0 (2, 1)
	63 getstatic (2, 1)
	64 org/apache/commons/math3/geometry/partitioning/utilities/AVLTree$Skew.BALANCED:Lorg/apache/commons/math3/geometry/partitioning/utilities/AVLTree$Skew; (2, 1)
	66 putfield (2, 1)
	67 org/apache/commons/math3/geometry/partitioning/utilities/AVLTree$Node.skew:Lorg/apache/commons/math3/geometry/partitioning/utilities/AVLTree$Skew; (2, 1)
	69 aload_0 (2, 1)
	70 getfield (2, 1)
	71 org/apache/commons/math3/geometry/partitioning/utilities/AVLTree$Node.left:Lorg/apache/commons/math3/geometry/partitioning/utilities/AVLTree$Node; (2, 1)
	73 getstatic (2, 1)
	74 org/apache/commons/math3/geometry/partitioning/utilities/AVLTree$Skew.BALANCED:Lorg/apache/commons/math3/geometry/partitioning/utilities/AVLTree$Skew; (2, 1)
	76 putfield (2, 1)
	77 org/apache/commons/math3/geometry/partitioning/utilities/AVLTree$Node.skew:Lorg/apache/commons/math3/geometry/partitioning/utilities/AVLTree$Skew; (2, 1)
	79 iconst_1 (2, 1)
	80 ireturn (2, 1)
	81 aload_0 (2, 1)
	82 getfield (2, 1)
	83 org/apache/commons/math3/geometry/partitioning/utilities/AVLTree$Node.right:Lorg/apache/commons/math3/geometry/partitioning/utilities/AVLTree$Node; (2, 1)
	85 getfield (2, 1)
	86 org/apache/commons/math3/geometry/partitioning/utilities/AVLTree$Node.skew:Lorg/apache/commons/math3/geometry/partitioning/utilities/AVLTree$Skew; (2, 1)
	88 getstatic (2, 1)
	89 org/apache/commons/math3/geometry/partitioning/utilities/AVLTree$Skew.BALANCED:Lorg/apache/commons/math3/geometry/partitioning/utilities/AVLTree$Skew; (2, 1)
	91 if_acmpne (2, 1)
	92 26 (2, 1)
	94 aload_0 (2, 1)
	95 invokespecial (2, 1)
	96 org/apache/commons/math3/geometry/partitioning/utilities/AVLTree$Node.rotateCCW:()V (2, 1)
	98 aload_0 (2, 1)
	99 getstatic (2, 1)
	100 org/apache/commons/math3/geometry/partitioning/utilities/AVLTree$Skew.LEFT_HIGH:Lorg/apache/commons/math3/geometry/partitioning/utilities/AVLTree$Skew; (2, 1)
	102 putfield (2, 1)
	103 org/apache/commons/math3/geometry/partitioning/utilities/AVLTree$Node.skew:Lorg/apache/commons/math3/geometry/partitioning/utilities/AVLTree$Skew; (2, 1)
	105 aload_0 (2, 1)
	106 getfield (2, 1)
	107 org/apache/commons/math3/geometry/partitioning/utilities/AVLTree$Node.left:Lorg/apache/commons/math3/geometry/partitioning/utilities/AVLTree$Node; (2, 1)
	109 getstatic (2, 1)
	110 org/apache/commons/math3/geometry/partitioning/utilities/AVLTree$Skew.RIGHT_HIGH:Lorg/apache/commons/math3/geometry/partitioning/utilities/AVLTree$Skew; (2, 1)
	112 putfield (2, 1)
	113 org/apache/commons/math3/geometry/partitioning/utilities/AVLTree$Node.skew:Lorg/apache/commons/math3/geometry/partitioning/utilities/AVLTree$Skew; (2, 1)
	115 iconst_0 (2, 1)
	116 ireturn (2, 1)
	117 aload_0 (2, 2)
	118 getfield (2, 2)
	119 org/apache/commons/math3/geometry/partitioning/utilities/AVLTree$Node.right:Lorg/apache/commons/math3/geometry/partitioning/utilities/AVLTree$Node; (2, 2)
	121 getfield (2, 2)
	122 org/apache/commons/math3/geometry/partitioning/utilities/AVLTree$Node.left:Lorg/apache/commons/math3/geometry/partitioning/utilities/AVLTree$Node; (2, 2)
	124 getfield (2, 2)
	125 org/apache/commons/math3/geometry/partitioning/utilities/AVLTree$Node.skew:Lorg/apache/commons/math3/geometry/partitioning/utilities/AVLTree$Skew; (2, 2)
	127 astore_1 (2, 2)
	128 aload_0 (2, 2)
	129 getfield (2, 2)
	130 org/apache/commons/math3/geometry/partitioning/utilities/AVLTree$Node.right:Lorg/apache/commons/math3/geometry/partitioning/utilities/AVLTree$Node; (2, 2)
	132 invokespecial (2, 2)
	133 org/apache/commons/math3/geometry/partitioning/utilities/AVLTree$Node.rotateCW:()V (2, 2)
	135 aload_0 (2, 2)
	136 invokespecial (2, 2)
	137 org/apache/commons/math3/geometry/partitioning/utilities/AVLTree$Node.rotateCCW:()V (2, 2)
	139 getstatic (3, 5)
	140 org/apache/commons/math3/geometry/partitioning/utilities/AVLTree$1.$SwitchMap$org$apache$commons$math3$geometry$partitioning$utilities$AVLTree$Skew:[I (3, 5)
	142 aload_1 (3, 5)
	143 invokevirtual (3, 5)
	144 org/apache/commons/math3/geometry/partitioning/utilities/AVLTree$Skew.ordinal:()I (3, 5)
	146 iaload (3, 5)
	147 lookupswitch (3, 5)
	148 1: 172 (3, 5)
	152 2: 195 (3, 5)
	172 aload_0 (3, 5)
	173 getfield (3, 5)
	174 org/apache/commons/math3/geometry/partitioning/utilities/AVLTree$Node.left:Lorg/apache/commons/math3/geometry/partitioning/utilities/AVLTree$Node; (3, 5)
	176 getstatic (3, 5)
	177 org/apache/commons/math3/geometry/partitioning/utilities/AVLTree$Skew.BALANCED:Lorg/apache/commons/math3/geometry/partitioning/utilities/AVLTree$Skew; (3, 5)
	179 putfield (3, 5)
	180 org/apache/commons/math3/geometry/partitioning/utilities/AVLTree$Node.skew:Lorg/apache/commons/math3/geometry/partitioning/utilities/AVLTree$Skew; (3, 5)
	182 aload_0 (3, 5)
	183 getfield (3, 5)
	184 org/apache/commons/math3/geometry/partitioning/utilities/AVLTree$Node.right:Lorg/apache/commons/math3/geometry/partitioning/utilities/AVLTree$Node; (3, 5)
	186 getstatic (3, 5)
	187 org/apache/commons/math3/geometry/partitioning/utilities/AVLTree$Skew.RIGHT_HIGH:Lorg/apache/commons/math3/geometry/partitioning/utilities/AVLTree$Skew; (3, 5)
	189 putfield (3, 5)
	190 org/apache/commons/math3/geometry/partitioning/utilities/AVLTree$Node.skew:Lorg/apache/commons/math3/geometry/partitioning/utilities/AVLTree$Skew; (3, 5)
	192 goto (3, 5)
	193 46 (3, 5)
	195 aload_0 (3, 5)
	196 getfield (3, 5)
	197 org/apache/commons/math3/geometry/partitioning/utilities/AVLTree$Node.left:Lorg/apache/commons/math3/geometry/partitioning/utilities/AVLTree$Node; (3, 5)
	199 getstatic (3, 5)
	200 org/apache/commons/math3/geometry/partitioning/utilities/AVLTree$Skew.LEFT_HIGH:Lorg/apache/commons/math3/geometry/partitioning/utilities/AVLTree$Skew; (3, 5)
	202 putfield (3, 5)
	203 org/apache/commons/math3/geometry/partitioning/utilities/AVLTree$Node.skew:Lorg/apache/commons/math3/geometry/partitioning/utilities/AVLTree$Skew; (3, 5)
	205 aload_0 (3, 5)
	206 getfield (3, 5)
	207 org/apache/commons/math3/geometry/partitioning/utilities/AVLTree$Node.right:Lorg/apache/commons/math3/geometry/partitioning/utilities/AVLTree$Node; (3, 5)
	209 getstatic (3, 5)
	210 org/apache/commons/math3/geometry/partitioning/utilities/AVLTree$Skew.BALANCED:Lorg/apache/commons/math3/geometry/partitioning/utilities/AVLTree$Skew; (3, 5)
	212 putfield (3, 5)
	213 org/apache/commons/math3/geometry/partitioning/utilities/AVLTree$Node.skew:Lorg/apache/commons/math3/geometry/partitioning/utilities/AVLTree$Skew; (3, 5)
	215 goto (3, 5)
	216 23 (3, 5)
	218 aload_0 (3, 5)
	219 getfield (3, 5)
	220 org/apache/commons/math3/geometry/partitioning/utilities/AVLTree$Node.left:Lorg/apache/commons/math3/geometry/partitioning/utilities/AVLTree$Node; (3, 5)
	222 getstatic (3, 5)
	223 org/apache/commons/math3/geometry/partitioning/utilities/AVLTree$Skew.BALANCED:Lorg/apache/commons/math3/geometry/partitioning/utilities/AVLTree$Skew; (3, 5)
	225 putfield (3, 5)
	226 org/apache/commons/math3/geometry/partitioning/utilities/AVLTree$Node.skew:Lorg/apache/commons/math3/geometry/partitioning/utilities/AVLTree$Skew; (3, 5)
	228 aload_0 (3, 5)
	229 getfield (3, 5)
	230 org/apache/commons/math3/geometry/partitioning/utilities/AVLTree$Node.right:Lorg/apache/commons/math3/geometry/partitioning/utilities/AVLTree$Node; (3, 5)
	232 getstatic (3, 5)
	233 org/apache/commons/math3/geometry/partitioning/utilities/AVLTree$Skew.BALANCED:Lorg/apache/commons/math3/geometry/partitioning/utilities/AVLTree$Skew; (3, 5)
	235 putfield (3, 5)
	236 org/apache/commons/math3/geometry/partitioning/utilities/AVLTree$Node.skew:Lorg/apache/commons/math3/geometry/partitioning/utilities/AVLTree$Skew; (3, 5)
	238 aload_0 (2, 2)
	239 getstatic (2, 2)
	240 org/apache/commons/math3/geometry/partitioning/utilities/AVLTree$Skew.BALANCED:Lorg/apache/commons/math3/geometry/partitioning/utilities/AVLTree$Skew; (2, 2)
	242 putfield (2, 2)
	243 org/apache/commons/math3/geometry/partitioning/utilities/AVLTree$Node.skew:Lorg/apache/commons/math3/geometry/partitioning/utilities/AVLTree$Skew; (2, 2)
	245 iconst_1 (2, 2)
	246 ireturn (2, 2)
	247 aload_0 (1, 5)
	248 getstatic (1, 5)
	249 org/apache/commons/math3/geometry/partitioning/utilities/AVLTree$Skew.RIGHT_HIGH:Lorg/apache/commons/math3/geometry/partitioning/utilities/AVLTree$Skew; (1, 5)
	251 putfield (1, 5)
	252 org/apache/commons/math3/geometry/partitioning/utilities/AVLTree$Node.skew:Lorg/apache/commons/math3/geometry/partitioning/utilities/AVLTree$Skew; (1, 5)
	254 iconst_0 (1, 5)
	255 ireturn (1, 5)

Method: rebalanceRightShrunk
	0 getstatic (1, 5)
	1 org/apache/commons/math3/geometry/partitioning/utilities/AVLTree$1.$SwitchMap$org$apache$commons$math3$geometry$partitioning$utilities$AVLTree$Skew:[I (1, 5)
	3 aload_0 (1, 5)
	4 getfield (1, 5)
	5 org/apache/commons/math3/geometry/partitioning/utilities/AVLTree$Node.skew:Lorg/apache/commons/math3/geometry/partitioning/utilities/AVLTree$Skew; (1, 5)
	7 invokevirtual (1, 5)
	8 org/apache/commons/math3/geometry/partitioning/utilities/AVLTree$Skew.ordinal:()I (1, 5)
	10 iaload (1, 5)
	11 lookupswitch (1, 5)
	12 1: 45 (1, 5)
	16 2: 36 (1, 5)
	36 aload_0 (1, 5)
	37 getstatic (1, 5)
	38 org/apache/commons/math3/geometry/partitioning/utilities/AVLTree$Skew.BALANCED:Lorg/apache/commons/math3/geometry/partitioning/utilities/AVLTree$Skew; (1, 5)
	40 putfield (1, 5)
	41 org/apache/commons/math3/geometry/partitioning/utilities/AVLTree$Node.skew:Lorg/apache/commons/math3/geometry/partitioning/utilities/AVLTree$Skew; (1, 5)
	43 iconst_1 (1, 5)
	44 ireturn (1, 5)
	45 aload_0 (2, 1)
	46 getfield (2, 1)
	47 org/apache/commons/math3/geometry/partitioning/utilities/AVLTree$Node.left:Lorg/apache/commons/math3/geometry/partitioning/utilities/AVLTree$Node; (2, 1)
	49 getfield (2, 1)
	50 org/apache/commons/math3/geometry/partitioning/utilities/AVLTree$Node.skew:Lorg/apache/commons/math3/geometry/partitioning/utilities/AVLTree$Skew; (2, 1)
	52 getstatic (2, 1)
	53 org/apache/commons/math3/geometry/partitioning/utilities/AVLTree$Skew.LEFT_HIGH:Lorg/apache/commons/math3/geometry/partitioning/utilities/AVLTree$Skew; (2, 1)
	55 if_acmpne (2, 1)
	56 26 (2, 1)
	58 aload_0 (2, 1)
	59 invokespecial (2, 1)
	60 org/apache/commons/math3/geometry/partitioning/utilities/AVLTree$Node.rotateCW:()V (2, 1)
	62 aload_0 (2, 1)
	63 getstatic (2, 1)
	64 org/apache/commons/math3/geometry/partitioning/utilities/AVLTree$Skew.BALANCED:Lorg/apache/commons/math3/geometry/partitioning/utilities/AVLTree$Skew; (2, 1)
	66 putfield (2, 1)
	67 org/apache/commons/math3/geometry/partitioning/utilities/AVLTree$Node.skew:Lorg/apache/commons/math3/geometry/partitioning/utilities/AVLTree$Skew; (2, 1)
	69 aload_0 (2, 1)
	70 getfield (2, 1)
	71 org/apache/commons/math3/geometry/partitioning/utilities/AVLTree$Node.right:Lorg/apache/commons/math3/geometry/partitioning/utilities/AVLTree$Node; (2, 1)
	73 getstatic (2, 1)
	74 org/apache/commons/math3/geometry/partitioning/utilities/AVLTree$Skew.BALANCED:Lorg/apache/commons/math3/geometry/partitioning/utilities/AVLTree$Skew; (2, 1)
	76 putfield (2, 1)
	77 org/apache/commons/math3/geometry/partitioning/utilities/AVLTree$Node.skew:Lorg/apache/commons/math3/geometry/partitioning/utilities/AVLTree$Skew; (2, 1)
	79 iconst_1 (2, 1)
	80 ireturn (2, 1)
	81 aload_0 (2, 1)
	82 getfield (2, 1)
	83 org/apache/commons/math3/geometry/partitioning/utilities/AVLTree$Node.left:Lorg/apache/commons/math3/geometry/partitioning/utilities/AVLTree$Node; (2, 1)
	85 getfield (2, 1)
	86 org/apache/commons/math3/geometry/partitioning/utilities/AVLTree$Node.skew:Lorg/apache/commons/math3/geometry/partitioning/utilities/AVLTree$Skew; (2, 1)
	88 getstatic (2, 1)
	89 org/apache/commons/math3/geometry/partitioning/utilities/AVLTree$Skew.BALANCED:Lorg/apache/commons/math3/geometry/partitioning/utilities/AVLTree$Skew; (2, 1)
	91 if_acmpne (2, 1)
	92 26 (2, 1)
	94 aload_0 (2, 1)
	95 invokespecial (2, 1)
	96 org/apache/commons/math3/geometry/partitioning/utilities/AVLTree$Node.rotateCW:()V (2, 1)
	98 aload_0 (2, 1)
	99 getstatic (2, 1)
	100 org/apache/commons/math3/geometry/partitioning/utilities/AVLTree$Skew.RIGHT_HIGH:Lorg/apache/commons/math3/geometry/partitioning/utilities/AVLTree$Skew; (2, 1)
	102 putfield (2, 1)
	103 org/apache/commons/math3/geometry/partitioning/utilities/AVLTree$Node.skew:Lorg/apache/commons/math3/geometry/partitioning/utilities/AVLTree$Skew; (2, 1)
	105 aload_0 (2, 1)
	106 getfield (2, 1)
	107 org/apache/commons/math3/geometry/partitioning/utilities/AVLTree$Node.right:Lorg/apache/commons/math3/geometry/partitioning/utilities/AVLTree$Node; (2, 1)
	109 getstatic (2, 1)
	110 org/apache/commons/math3/geometry/partitioning/utilities/AVLTree$Skew.LEFT_HIGH:Lorg/apache/commons/math3/geometry/partitioning/utilities/AVLTree$Skew; (2, 1)
	112 putfield (2, 1)
	113 org/apache/commons/math3/geometry/partitioning/utilities/AVLTree$Node.skew:Lorg/apache/commons/math3/geometry/partitioning/utilities/AVLTree$Skew; (2, 1)
	115 iconst_0 (2, 1)
	116 ireturn (2, 1)
	117 aload_0 (2, 2)
	118 getfield (2, 2)
	119 org/apache/commons/math3/geometry/partitioning/utilities/AVLTree$Node.left:Lorg/apache/commons/math3/geometry/partitioning/utilities/AVLTree$Node; (2, 2)
	121 getfield (2, 2)
	122 org/apache/commons/math3/geometry/partitioning/utilities/AVLTree$Node.right:Lorg/apache/commons/math3/geometry/partitioning/utilities/AVLTree$Node; (2, 2)
	124 getfield (2, 2)
	125 org/apache/commons/math3/geometry/partitioning/utilities/AVLTree$Node.skew:Lorg/apache/commons/math3/geometry/partitioning/utilities/AVLTree$Skew; (2, 2)
	127 astore_1 (2, 2)
	128 aload_0 (2, 2)
	129 getfield (2, 2)
	130 org/apache/commons/math3/geometry/partitioning/utilities/AVLTree$Node.left:Lorg/apache/commons/math3/geometry/partitioning/utilities/AVLTree$Node; (2, 2)
	132 invokespecial (2, 2)
	133 org/apache/commons/math3/geometry/partitioning/utilities/AVLTree$Node.rotateCCW:()V (2, 2)
	135 aload_0 (2, 2)
	136 invokespecial (2, 2)
	137 org/apache/commons/math3/geometry/partitioning/utilities/AVLTree$Node.rotateCW:()V (2, 2)
	139 getstatic (3, 5)
	140 org/apache/commons/math3/geometry/partitioning/utilities/AVLTree$1.$SwitchMap$org$apache$commons$math3$geometry$partitioning$utilities$AVLTree$Skew:[I (3, 5)
	142 aload_1 (3, 5)
	143 invokevirtual (3, 5)
	144 org/apache/commons/math3/geometry/partitioning/utilities/AVLTree$Skew.ordinal:()I (3, 5)
	146 iaload (3, 5)
	147 lookupswitch (3, 5)
	148 1: 172 (3, 5)
	152 2: 195 (3, 5)
	172 aload_0 (3, 5)
	173 getfield (3, 5)
	174 org/apache/commons/math3/geometry/partitioning/utilities/AVLTree$Node.left:Lorg/apache/commons/math3/geometry/partitioning/utilities/AVLTree$Node; (3, 5)
	176 getstatic (3, 5)
	177 org/apache/commons/math3/geometry/partitioning/utilities/AVLTree$Skew.BALANCED:Lorg/apache/commons/math3/geometry/partitioning/utilities/AVLTree$Skew; (3, 5)
	179 putfield (3, 5)
	180 org/apache/commons/math3/geometry/partitioning/utilities/AVLTree$Node.skew:Lorg/apache/commons/math3/geometry/partitioning/utilities/AVLTree$Skew; (3, 5)
	182 aload_0 (3, 5)
	183 getfield (3, 5)
	184 org/apache/commons/math3/geometry/partitioning/utilities/AVLTree$Node.right:Lorg/apache/commons/math3/geometry/partitioning/utilities/AVLTree$Node; (3, 5)
	186 getstatic (3, 5)
	187 org/apache/commons/math3/geometry/partitioning/utilities/AVLTree$Skew.RIGHT_HIGH:Lorg/apache/commons/math3/geometry/partitioning/utilities/AVLTree$Skew; (3, 5)
	189 putfield (3, 5)
	190 org/apache/commons/math3/geometry/partitioning/utilities/AVLTree$Node.skew:Lorg/apache/commons/math3/geometry/partitioning/utilities/AVLTree$Skew; (3, 5)
	192 goto (3, 5)
	193 46 (3, 5)
	195 aload_0 (3, 5)
	196 getfield (3, 5)
	197 org/apache/commons/math3/geometry/partitioning/utilities/AVLTree$Node.left:Lorg/apache/commons/math3/geometry/partitioning/utilities/AVLTree$Node; (3, 5)
	199 getstatic (3, 5)
	200 org/apache/commons/math3/geometry/partitioning/utilities/AVLTree$Skew.LEFT_HIGH:Lorg/apache/commons/math3/geometry/partitioning/utilities/AVLTree$Skew; (3, 5)
	202 putfield (3, 5)
	203 org/apache/commons/math3/geometry/partitioning/utilities/AVLTree$Node.skew:Lorg/apache/commons/math3/geometry/partitioning/utilities/AVLTree$Skew; (3, 5)
	205 aload_0 (3, 5)
	206 getfield (3, 5)
	207 org/apache/commons/math3/geometry/partitioning/utilities/AVLTree$Node.right:Lorg/apache/commons/math3/geometry/partitioning/utilities/AVLTree$Node; (3, 5)
	209 getstatic (3, 5)
	210 org/apache/commons/math3/geometry/partitioning/utilities/AVLTree$Skew.BALANCED:Lorg/apache/commons/math3/geometry/partitioning/utilities/AVLTree$Skew; (3, 5)
	212 putfield (3, 5)
	213 org/apache/commons/math3/geometry/partitioning/utilities/AVLTree$Node.skew:Lorg/apache/commons/math3/geometry/partitioning/utilities/AVLTree$Skew; (3, 5)
	215 goto (3, 5)
	216 23 (3, 5)
	218 aload_0 (3, 5)
	219 getfield (3, 5)
	220 org/apache/commons/math3/geometry/partitioning/utilities/AVLTree$Node.left:Lorg/apache/commons/math3/geometry/partitioning/utilities/AVLTree$Node; (3, 5)
	222 getstatic (3, 5)
	223 org/apache/commons/math3/geometry/partitioning/utilities/AVLTree$Skew.BALANCED:Lorg/apache/commons/math3/geometry/partitioning/utilities/AVLTree$Skew; (3, 5)
	225 putfield (3, 5)
	226 org/apache/commons/math3/geometry/partitioning/utilities/AVLTree$Node.skew:Lorg/apache/commons/math3/geometry/partitioning/utilities/AVLTree$Skew; (3, 5)
	228 aload_0 (3, 5)
	229 getfield (3, 5)
	230 org/apache/commons/math3/geometry/partitioning/utilities/AVLTree$Node.right:Lorg/apache/commons/math3/geometry/partitioning/utilities/AVLTree$Node; (3, 5)
	232 getstatic (3, 5)
	233 org/apache/commons/math3/geometry/partitioning/utilities/AVLTree$Skew.BALANCED:Lorg/apache/commons/math3/geometry/partitioning/utilities/AVLTree$Skew; (3, 5)
	235 putfield (3, 5)
	236 org/apache/commons/math3/geometry/partitioning/utilities/AVLTree$Node.skew:Lorg/apache/commons/math3/geometry/partitioning/utilities/AVLTree$Skew; (3, 5)
	238 aload_0 (2, 2)
	239 getstatic (2, 2)
	240 org/apache/commons/math3/geometry/partitioning/utilities/AVLTree$Skew.BALANCED:Lorg/apache/commons/math3/geometry/partitioning/utilities/AVLTree$Skew; (2, 2)
	242 putfield (2, 2)
	243 org/apache/commons/math3/geometry/partitioning/utilities/AVLTree$Node.skew:Lorg/apache/commons/math3/geometry/partitioning/utilities/AVLTree$Skew; (2, 2)
	245 iconst_1 (2, 2)
	246 ireturn (2, 2)
	247 aload_0 (1, 5)
	248 getstatic (1, 5)
	249 org/apache/commons/math3/geometry/partitioning/utilities/AVLTree$Skew.LEFT_HIGH:Lorg/apache/commons/math3/geometry/partitioning/utilities/AVLTree$Skew; (1, 5)
	251 putfield (1, 5)
	252 org/apache/commons/math3/geometry/partitioning/utilities/AVLTree$Node.skew:Lorg/apache/commons/math3/geometry/partitioning/utilities/AVLTree$Skew; (1, 5)
	254 iconst_0 (1, 5)
	255 ireturn (1, 5)

Method: rotateCW
	0 aload_0 (0, 0)
	1 getfield (0, 0)
	2 org/apache/commons/math3/geometry/partitioning/utilities/AVLTree$Node.element:Ljava/lang/Comparable; (0, 0)
	4 astore_1 (0, 0)
	5 aload_0 (0, 0)
	6 aload_0 (0, 0)
	7 getfield (0, 0)
	8 org/apache/commons/math3/geometry/partitioning/utilities/AVLTree$Node.left:Lorg/apache/commons/math3/geometry/partitioning/utilities/AVLTree$Node; (0, 0)
	10 getfield (0, 0)
	11 org/apache/commons/math3/geometry/partitioning/utilities/AVLTree$Node.element:Ljava/lang/Comparable; (0, 0)
	13 putfield (0, 0)
	14 org/apache/commons/math3/geometry/partitioning/utilities/AVLTree$Node.element:Ljava/lang/Comparable; (0, 0)
	16 aload_0 (0, 0)
	17 getfield (0, 0)
	18 org/apache/commons/math3/geometry/partitioning/utilities/AVLTree$Node.left:Lorg/apache/commons/math3/geometry/partitioning/utilities/AVLTree$Node; (0, 0)
	20 aload_1 (0, 0)
	21 putfield (0, 0)
	22 org/apache/commons/math3/geometry/partitioning/utilities/AVLTree$Node.element:Ljava/lang/Comparable; (0, 0)
	24 aload_0 (0, 0)
	25 getfield (0, 0)
	26 org/apache/commons/math3/geometry/partitioning/utilities/AVLTree$Node.left:Lorg/apache/commons/math3/geometry/partitioning/utilities/AVLTree$Node; (0, 0)
	28 astore_2 (0, 0)
	29 aload_0 (0, 0)
	30 aload_2 (0, 0)
	31 getfield (0, 0)
	32 org/apache/commons/math3/geometry/partitioning/utilities/AVLTree$Node.left:Lorg/apache/commons/math3/geometry/partitioning/utilities/AVLTree$Node; (0, 0)
	34 putfield (0, 0)
	35 org/apache/commons/math3/geometry/partitioning/utilities/AVLTree$Node.left:Lorg/apache/commons/math3/geometry/partitioning/utilities/AVLTree$Node; (0, 0)
	37 aload_2 (0, 0)
	38 aload_2 (0, 0)
	39 getfield (0, 0)
	40 org/apache/commons/math3/geometry/partitioning/utilities/AVLTree$Node.right:Lorg/apache/commons/math3/geometry/partitioning/utilities/AVLTree$Node; (0, 0)
	42 putfield (0, 0)
	43 org/apache/commons/math3/geometry/partitioning/utilities/AVLTree$Node.left:Lorg/apache/commons/math3/geometry/partitioning/utilities/AVLTree$Node; (0, 0)
	45 aload_2 (0, 0)
	46 aload_0 (0, 0)
	47 getfield (0, 0)
	48 org/apache/commons/math3/geometry/partitioning/utilities/AVLTree$Node.right:Lorg/apache/commons/math3/geometry/partitioning/utilities/AVLTree$Node; (0, 0)
	50 putfield (0, 0)
	51 org/apache/commons/math3/geometry/partitioning/utilities/AVLTree$Node.right:Lorg/apache/commons/math3/geometry/partitioning/utilities/AVLTree$Node; (0, 0)
	53 aload_0 (0, 0)
	54 aload_2 (0, 0)
	55 putfield (0, 0)
	56 org/apache/commons/math3/geometry/partitioning/utilities/AVLTree$Node.right:Lorg/apache/commons/math3/geometry/partitioning/utilities/AVLTree$Node; (0, 0)
	58 aload_0 (1, 1)
	59 getfield (1, 1)
	60 org/apache/commons/math3/geometry/partitioning/utilities/AVLTree$Node.left:Lorg/apache/commons/math3/geometry/partitioning/utilities/AVLTree$Node; (1, 1)
	62 ifnull (1, 1)
	63 11 (1, 1)
	65 aload_0 (1, 1)
	66 getfield (1, 1)
	67 org/apache/commons/math3/geometry/partitioning/utilities/AVLTree$Node.left:Lorg/apache/commons/math3/geometry/partitioning/utilities/AVLTree$Node; (1, 1)
	69 aload_0 (1, 1)
	70 putfield (1, 1)
	71 org/apache/commons/math3/geometry/partitioning/utilities/AVLTree$Node.parent:Lorg/apache/commons/math3/geometry/partitioning/utilities/AVLTree$Node; (1, 1)
	73 aload_0 (1, 1)
	74 getfield (1, 1)
	75 org/apache/commons/math3/geometry/partitioning/utilities/AVLTree$Node.right:Lorg/apache/commons/math3/geometry/partitioning/utilities/AVLTree$Node; (1, 1)
	77 getfield (1, 1)
	78 org/apache/commons/math3/geometry/partitioning/utilities/AVLTree$Node.right:Lorg/apache/commons/math3/geometry/partitioning/utilities/AVLTree$Node; (1, 1)
	80 ifnull (1, 1)
	81 17 (1, 1)
	83 aload_0 (1, 1)
	84 getfield (1, 1)
	85 org/apache/commons/math3/geometry/partitioning/utilities/AVLTree$Node.right:Lorg/apache/commons/math3/geometry/partitioning/utilities/AVLTree$Node; (1, 1)
	87 getfield (1, 1)
	88 org/apache/commons/math3/geometry/partitioning/utilities/AVLTree$Node.right:Lorg/apache/commons/math3/geometry/partitioning/utilities/AVLTree$Node; (1, 1)
	90 aload_0 (1, 1)
	91 getfield (1, 1)
	92 org/apache/commons/math3/geometry/partitioning/utilities/AVLTree$Node.right:Lorg/apache/commons/math3/geometry/partitioning/utilities/AVLTree$Node; (1, 1)
	94 putfield (1, 1)
	95 org/apache/commons/math3/geometry/partitioning/utilities/AVLTree$Node.parent:Lorg/apache/commons/math3/geometry/partitioning/utilities/AVLTree$Node; (1, 1)
	97 return (0, 0)

Method: rotateCCW
	0 aload_0 (0, 0)
	1 getfield (0, 0)
	2 org/apache/commons/math3/geometry/partitioning/utilities/AVLTree$Node.element:Ljava/lang/Comparable; (0, 0)
	4 astore_1 (0, 0)
	5 aload_0 (0, 0)
	6 aload_0 (0, 0)
	7 getfield (0, 0)
	8 org/apache/commons/math3/geometry/partitioning/utilities/AVLTree$Node.right:Lorg/apache/commons/math3/geometry/partitioning/utilities/AVLTree$Node; (0, 0)
	10 getfield (0, 0)
	11 org/apache/commons/math3/geometry/partitioning/utilities/AVLTree$Node.element:Ljava/lang/Comparable; (0, 0)
	13 putfield (0, 0)
	14 org/apache/commons/math3/geometry/partitioning/utilities/AVLTree$Node.element:Ljava/lang/Comparable; (0, 0)
	16 aload_0 (0, 0)
	17 getfield (0, 0)
	18 org/apache/commons/math3/geometry/partitioning/utilities/AVLTree$Node.right:Lorg/apache/commons/math3/geometry/partitioning/utilities/AVLTree$Node; (0, 0)
	20 aload_1 (0, 0)
	21 putfield (0, 0)
	22 org/apache/commons/math3/geometry/partitioning/utilities/AVLTree$Node.element:Ljava/lang/Comparable; (0, 0)
	24 aload_0 (0, 0)
	25 getfield (0, 0)
	26 org/apache/commons/math3/geometry/partitioning/utilities/AVLTree$Node.right:Lorg/apache/commons/math3/geometry/partitioning/utilities/AVLTree$Node; (0, 0)
	28 astore_2 (0, 0)
	29 aload_0 (0, 0)
	30 aload_2 (0, 0)
	31 getfield (0, 0)
	32 org/apache/commons/math3/geometry/partitioning/utilities/AVLTree$Node.right:Lorg/apache/commons/math3/geometry/partitioning/utilities/AVLTree$Node; (0, 0)
	34 putfield (0, 0)
	35 org/apache/commons/math3/geometry/partitioning/utilities/AVLTree$Node.right:Lorg/apache/commons/math3/geometry/partitioning/utilities/AVLTree$Node; (0, 0)
	37 aload_2 (0, 0)
	38 aload_2 (0, 0)
	39 getfield (0, 0)
	40 org/apache/commons/math3/geometry/partitioning/utilities/AVLTree$Node.left:Lorg/apache/commons/math3/geometry/partitioning/utilities/AVLTree$Node; (0, 0)
	42 putfield (0, 0)
	43 org/apache/commons/math3/geometry/partitioning/utilities/AVLTree$Node.right:Lorg/apache/commons/math3/geometry/partitioning/utilities/AVLTree$Node; (0, 0)
	45 aload_2 (0, 0)
	46 aload_0 (0, 0)
	47 getfield (0, 0)
	48 org/apache/commons/math3/geometry/partitioning/utilities/AVLTree$Node.left:Lorg/apache/commons/math3/geometry/partitioning/utilities/AVLTree$Node; (0, 0)
	50 putfield (0, 0)
	51 org/apache/commons/math3/geometry/partitioning/utilities/AVLTree$Node.left:Lorg/apache/commons/math3/geometry/partitioning/utilities/AVLTree$Node; (0, 0)
	53 aload_0 (0, 0)
	54 aload_2 (0, 0)
	55 putfield (0, 0)
	56 org/apache/commons/math3/geometry/partitioning/utilities/AVLTree$Node.left:Lorg/apache/commons/math3/geometry/partitioning/utilities/AVLTree$Node; (0, 0)
	58 aload_0 (1, 1)
	59 getfield (1, 1)
	60 org/apache/commons/math3/geometry/partitioning/utilities/AVLTree$Node.right:Lorg/apache/commons/math3/geometry/partitioning/utilities/AVLTree$Node; (1, 1)
	62 ifnull (1, 1)
	63 11 (1, 1)
	65 aload_0 (1, 1)
	66 getfield (1, 1)
	67 org/apache/commons/math3/geometry/partitioning/utilities/AVLTree$Node.right:Lorg/apache/commons/math3/geometry/partitioning/utilities/AVLTree$Node; (1, 1)
	69 aload_0 (1, 1)
	70 putfield (1, 1)
	71 org/apache/commons/math3/geometry/partitioning/utilities/AVLTree$Node.parent:Lorg/apache/commons/math3/geometry/partitioning/utilities/AVLTree$Node; (1, 1)
	73 aload_0 (1, 1)
	74 getfield (1, 1)
	75 org/apache/commons/math3/geometry/partitioning/utilities/AVLTree$Node.left:Lorg/apache/commons/math3/geometry/partitioning/utilities/AVLTree$Node; (1, 1)
	77 getfield (1, 1)
	78 org/apache/commons/math3/geometry/partitioning/utilities/AVLTree$Node.left:Lorg/apache/commons/math3/geometry/partitioning/utilities/AVLTree$Node; (1, 1)
	80 ifnull (1, 1)
	81 17 (1, 1)
	83 aload_0 (1, 1)
	84 getfield (1, 1)
	85 org/apache/commons/math3/geometry/partitioning/utilities/AVLTree$Node.left:Lorg/apache/commons/math3/geometry/partitioning/utilities/AVLTree$Node; (1, 1)
	87 getfield (1, 1)
	88 org/apache/commons/math3/geometry/partitioning/utilities/AVLTree$Node.left:Lorg/apache/commons/math3/geometry/partitioning/utilities/AVLTree$Node; (1, 1)
	90 aload_0 (1, 1)
	91 getfield (1, 1)
	92 org/apache/commons/math3/geometry/partitioning/utilities/AVLTree$Node.left:Lorg/apache/commons/math3/geometry/partitioning/utilities/AVLTree$Node; (1, 1)
	94 putfield (1, 1)
	95 org/apache/commons/math3/geometry/partitioning/utilities/AVLTree$Node.parent:Lorg/apache/commons/math3/geometry/partitioning/utilities/AVLTree$Node; (1, 1)
	97 return (0, 0)

Method: access$000
	0 aload_0 (0, 0)
	1 getfield (0, 0)
	2 org/apache/commons/math3/geometry/partitioning/utilities/AVLTree$Node.element:Ljava/lang/Comparable; (0, 0)
	4 areturn (0, 0)

Method: access$100
	0 aload_0 (0, 0)
	1 getfield (0, 0)
	2 org/apache/commons/math3/geometry/partitioning/utilities/AVLTree$Node.right:Lorg/apache/commons/math3/geometry/partitioning/utilities/AVLTree$Node; (0, 0)
	4 areturn (0, 0)

Method: access$200
	0 aload_0 (0, 0)
	1 getfield (0, 0)
	2 org/apache/commons/math3/geometry/partitioning/utilities/AVLTree$Node.left:Lorg/apache/commons/math3/geometry/partitioning/utilities/AVLTree$Node; (0, 0)
	4 areturn (0, 0)

