Method: values
	0 getstatic (0, 0)
	1 org/apache/commons/math3/geometry/partitioning/utilities/AVLTree$Skew.$VALUES:[Lorg/apache/commons/math3/geometry/partitioning/utilities/AVLTree$Skew; (0, 0)
	3 invokevirtual (0, 0)
	4 [Lorg/apache/commons/math3/geometry/partitioning/utilities/AVLTree$Skew;.clone:()Ljava/lang/Object; (0, 0)
	6 checkcast (0, 0)
	7 [Lorg/apache/commons/math3/geometry/partitioning/utilities/AVLTree$Skew; (0, 0)
	9 areturn (0, 0)

Method: valueOf
	0 ldc (0, 0)
	1 org/apache/commons/math3/geometry/partitioning/utilities/AVLTree$Skew (0, 0)
	2 aload_0 (0, 0)
	3 invokestatic (0, 0)
	4 java/lang/Enum.valueOf:(Ljava/lang/Class;Ljava/lang/String;)Ljava/lang/Enum; (0, 0)
	6 checkcast (0, 0)
	7 org/apache/commons/math3/geometry/partitioning/utilities/AVLTree$Skew (0, 0)
	9 areturn (0, 0)

Method: <clinit>
	0 new (0, 0)
	1 org/apache/commons/math3/geometry/partitioning/utilities/AVLTree$Skew (0, 0)
	3 dup (0, 0)
	4 ldc (0, 0)
	5 LEFT_HIGH (0, 0)
	6 iconst_0 (0, 0)
	7 invokespecial (0, 0)
	8 org/apache/commons/math3/geometry/partitioning/utilities/AVLTree$Skew.<init>:(Ljava/lang/String;I)V (0, 0)
	10 putstatic (0, 0)
	11 org/apache/commons/math3/geometry/partitioning/utilities/AVLTree$Skew.LEFT_HIGH:Lorg/apache/commons/math3/geometry/partitioning/utilities/AVLTree$Skew; (0, 0)
	13 new (0, 4)
	14 org/apache/commons/math3/geometry/partitioning/utilities/AVLTree$Skew (0, 4)
	16 dup (0, 4)
	17 ldc (0, 4)
	18 RIGHT_HIGH (0, 4)
	19 iconst_1 (0, 4)
	20 invokespecial (0, 4)
	21 org/apache/commons/math3/geometry/partitioning/utilities/AVLTree$Skew.<init>:(Ljava/lang/String;I)V (0, 4)
	23 putstatic (0, 4)
	24 org/apache/commons/math3/geometry/partitioning/utilities/AVLTree$Skew.RIGHT_HIGH:Lorg/apache/commons/math3/geometry/partitioning/utilities/AVLTree$Skew; (0, 4)
	26 new (0, 4)
	27 org/apache/commons/math3/geometry/partitioning/utilities/AVLTree$Skew (0, 4)
	29 dup (0, 4)
	30 ldc (0, 4)
	31 BALANCED (0, 4)
	32 iconst_2 (0, 4)
	33 invokespecial (0, 4)
	34 org/apache/commons/math3/geometry/partitioning/utilities/AVLTree$Skew.<init>:(Ljava/lang/String;I)V (0, 4)
	36 putstatic (0, 4)
	37 org/apache/commons/math3/geometry/partitioning/utilities/AVLTree$Skew.BALANCED:Lorg/apache/commons/math3/geometry/partitioning/utilities/AVLTree$Skew; (0, 4)
	39 iconst_3 (0, 4)
	40 anewarray (0, 4)
	41 org/apache/commons/math3/geometry/partitioning/utilities/AVLTree$Skew (0, 4)
	43 dup (0, 4)
	44 iconst_0 (0, 4)
	45 getstatic (0, 4)
	46 org/apache/commons/math3/geometry/partitioning/utilities/AVLTree$Skew.LEFT_HIGH:Lorg/apache/commons/math3/geometry/partitioning/utilities/AVLTree$Skew; (0, 4)
	48 aastore (0, 4)
	49 dup (0, 4)
	50 iconst_1 (0, 4)
	51 getstatic (0, 4)
	52 org/apache/commons/math3/geometry/partitioning/utilities/AVLTree$Skew.RIGHT_HIGH:Lorg/apache/commons/math3/geometry/partitioning/utilities/AVLTree$Skew; (0, 4)
	54 aastore (0, 4)
	55 dup (0, 4)
	56 iconst_2 (0, 4)
	57 getstatic (0, 4)
	58 org/apache/commons/math3/geometry/partitioning/utilities/AVLTree$Skew.BALANCED:Lorg/apache/commons/math3/geometry/partitioning/utilities/AVLTree$Skew; (0, 4)
	60 aastore (0, 4)
	61 putstatic (0, 4)
	62 org/apache/commons/math3/geometry/partitioning/utilities/AVLTree$Skew.$VALUES:[Lorg/apache/commons/math3/geometry/partitioning/utilities/AVLTree$Skew; (0, 4)
	64 return (0, 4)

