Method: <init>
	0 aload_0 (0, 0)
	1 invokespecial (0, 0)
	2 java/lang/Object.<init>:()V (0, 0)
	4 aload_0 (0, 0)
	5 aload_1 (0, 0)
	6 invokevirtual (0, 0)
	7 [D.clone:()Ljava/lang/Object; (0, 0)
	9 checkcast (0, 0)
	10 [D (0, 0)
	12 putfield (0, 0)
	13 org/apache/commons/math3/geometry/partitioning/utilities/OrderedTuple.components:[D (0, 0)
	15 ldc (0, 0)
	16 2147483648 (0, 0)
	17 istore_2 (0, 0)
	18 aload_0 (0, 0)
	19 ldc (0, 0)
	20 2147483647 (0, 0)
	21 putfield (0, 0)
	22 org/apache/commons/math3/geometry/partitioning/utilities/OrderedTuple.lsb:I (0, 0)
	24 aload_0 (0, 0)
	25 iconst_0 (0, 0)
	26 putfield (0, 0)
	27 org/apache/commons/math3/geometry/partitioning/utilities/OrderedTuple.posInf:Z (0, 0)
	29 aload_0 (0, 0)
	30 iconst_0 (0, 0)
	31 putfield (0, 0)
	32 org/apache/commons/math3/geometry/partitioning/utilities/OrderedTuple.negInf:Z (0, 0)
	34 aload_0 (0, 0)
	35 iconst_0 (0, 0)
	36 putfield (0, 0)
	37 org/apache/commons/math3/geometry/partitioning/utilities/OrderedTuple.nan:Z (0, 0)
	39 iconst_0 (2, 4)
	40 istore_3 (2, 4)
	41 iload_3 (2, 4)
	42 aload_1 (2, 4)
	43 arraylength (2, 4)
	44 if_icmpge (2, 4)
	45 120 (2, 4)
	47 aload_1 (3, 1)
	48 iload_3 (3, 1)
	49 daload (3, 1)
	50 invokestatic (3, 1)
	51 java/lang/Double.isInfinite:(D)Z (3, 1)
	53 ifeq (3, 1)
	54 27 (3, 1)
	56 aload_1 (4, 1)
	57 iload_3 (4, 1)
	58 daload (4, 1)
	59 dconst_0 (4, 1)
	60 dcmpg (4, 1)
	61 ifge (4, 1)
	62 11 (4, 1)
	64 aload_0 (4, 1)
	65 iconst_1 (4, 1)
	66 putfield (4, 1)
	67 org/apache/commons/math3/geometry/partitioning/utilities/OrderedTuple.negInf:Z (4, 1)
	69 goto (4, 1)
	70 89 (4, 1)
	72 aload_0 (4, 2)
	73 iconst_1 (4, 2)
	74 putfield (4, 2)
	75 org/apache/commons/math3/geometry/partitioning/utilities/OrderedTuple.posInf:Z (4, 2)
	77 goto (4, 2)
	78 81 (4, 2)
	80 aload_1 (3, 1)
	81 iload_3 (3, 1)
	82 daload (3, 1)
	83 invokestatic (3, 1)
	84 java/lang/Double.isNaN:(D)Z (3, 1)
	86 ifeq (3, 1)
	87 11 (3, 1)
	89 aload_0 (3, 1)
	90 iconst_1 (3, 1)
	91 putfield (3, 1)
	92 org/apache/commons/math3/geometry/partitioning/utilities/OrderedTuple.nan:Z (3, 1)
	94 goto (3, 1)
	95 64 (3, 1)
	97 aload_1 (3, 2)
	98 iload_3 (3, 2)
	99 daload (3, 2)
	100 invokestatic (3, 2)
	101 java/lang/Double.doubleToLongBits:(D)J (3, 2)
	103 lstore (3, 2)
	104 #4 (3, 2)
	105 lload (3, 2)
	106 #4 (3, 2)
	107 invokestatic (3, 2)
	108 org/apache/commons/math3/geometry/partitioning/utilities/OrderedTuple.mantissa:(J)J (3, 2)
	110 lstore (3, 2)
	111 #6 (3, 2)
	112 lload (4, 1)
	113 #6 (4, 1)
	114 lconst_0 (4, 1)
	115 lcmp (4, 1)
	116 ifeq (4, 1)
	117 42 (4, 1)
	119 lload (4, 1)
	120 #4 (4, 1)
	121 invokestatic (4, 1)
	122 org/apache/commons/math3/geometry/partitioning/utilities/OrderedTuple.exponent:(J)I (4, 1)
	124 istore (4, 1)
	125 #8 (4, 1)
	126 iload_2 (4, 1)
	127 iload (4, 1)
	128 #8 (4, 1)
	129 lload (4, 1)
	130 #6 (4, 1)
	131 invokestatic (4, 1)
	132 org/apache/commons/math3/geometry/partitioning/utilities/OrderedTuple.computeMSB:(J)I (4, 1)
	134 iadd (4, 1)
	135 invokestatic (4, 1)
	136 org/apache/commons/math3/util/FastMath.max:(II)I (4, 1)
	138 istore_2 (4, 1)
	139 aload_0 (4, 1)
	140 aload_0 (4, 1)
	141 getfield (4, 1)
	142 org/apache/commons/math3/geometry/partitioning/utilities/OrderedTuple.lsb:I (4, 1)
	144 iload (4, 1)
	145 #8 (4, 1)
	146 lload (4, 1)
	147 #6 (4, 1)
	148 invokestatic (4, 1)
	149 org/apache/commons/math3/geometry/partitioning/utilities/OrderedTuple.computeLSB:(J)I (4, 1)
	151 iadd (4, 1)
	152 invokestatic (4, 1)
	153 org/apache/commons/math3/util/FastMath.min:(II)I (4, 1)
	155 putfield (4, 1)
	156 org/apache/commons/math3/geometry/partitioning/utilities/OrderedTuple.lsb:I (4, 1)
	158 iinc (4, 1)
	159 #3 (4, 1)
	160 -89 (4, 1)
	161 goto (4, 1)
	162 -120 (4, 1)
	164 aload_0 (4, 1)
	165 getfield (4, 1)
	166 org/apache/commons/math3/geometry/partitioning/utilities/OrderedTuple.posInf:Z (4, 1)
	168 ifeq (4, 1)
	169 25 (4, 1)
	171 aload_0 (4, 1)
	172 getfield (4, 1)
	173 org/apache/commons/math3/geometry/partitioning/utilities/OrderedTuple.negInf:Z (4, 1)
	175 ifeq (4, 1)
	176 18 (4, 1)
	178 aload_0 (4, 1)
	179 iconst_0 (4, 1)
	180 putfield (4, 1)
	181 org/apache/commons/math3/geometry/partitioning/utilities/OrderedTuple.posInf:Z (4, 1)
	183 aload_0 (4, 1)
	184 iconst_0 (4, 1)
	185 putfield (4, 1)
	186 org/apache/commons/math3/geometry/partitioning/utilities/OrderedTuple.negInf:Z (4, 1)
	188 aload_0 (4, 1)
	189 iconst_1 (4, 1)
	190 putfield (4, 1)
	191 org/apache/commons/math3/geometry/partitioning/utilities/OrderedTuple.nan:Z (4, 1)
	193 aload_0 (4, 1)
	194 getfield (4, 1)
	195 org/apache/commons/math3/geometry/partitioning/utilities/OrderedTuple.lsb:I (4, 1)
	197 iload_2 (4, 1)
	198 if_icmpgt (4, 1)
	199 14 (4, 1)
	201 aload_0 (4, 1)
	202 iload_2 (4, 1)
	203 bipush (4, 1)
	204 16 (4, 1)
	205 iadd (4, 1)
	206 invokespecial (4, 1)
	207 org/apache/commons/math3/geometry/partitioning/utilities/OrderedTuple.encode:(I)V (4, 1)
	209 goto (4, 1)
	210 14 (4, 1)
	212 aload_0 (4, 2)
	213 iconst_1 (4, 2)
	214 newarray (4, 2)
	215 11 (4, 2)
	216 dup (4, 2)
	217 iconst_0 (4, 2)
	218 lconst_0 (4, 2)
	219 lastore (4, 2)
	220 putfield (4, 2)
	221 org/apache/commons/math3/geometry/partitioning/utilities/OrderedTuple.encoding:[J (4, 2)
	223 return (2, 4)

Method: encode
	0 aload_0 (0, 0)
	1 iload_1 (0, 0)
	2 bipush (0, 0)
	3 31 (0, 0)
	4 iadd (0, 0)
	5 putfield (0, 0)
	6 org/apache/commons/math3/geometry/partitioning/utilities/OrderedTuple.offset:I (0, 0)
	8 aload_0 (0, 0)
	9 dup (0, 0)
	10 getfield (0, 0)
	11 org/apache/commons/math3/geometry/partitioning/utilities/OrderedTuple.offset:I (0, 0)
	13 aload_0 (0, 0)
	14 getfield (0, 0)
	15 org/apache/commons/math3/geometry/partitioning/utilities/OrderedTuple.offset:I (0, 0)
	17 bipush (0, 0)
	18 32 (0, 0)
	19 irem (0, 0)
	20 isub (0, 0)
	21 putfield (0, 0)
	22 org/apache/commons/math3/geometry/partitioning/utilities/OrderedTuple.offset:I (0, 0)
	24 aload_0 (1, 1)
	25 getfield (1, 1)
	26 org/apache/commons/math3/geometry/partitioning/utilities/OrderedTuple.encoding:[J (1, 1)
	28 ifnull (1, 1)
	29 24 (1, 1)
	31 aload_0 (1, 1)
	32 getfield (1, 1)
	33 org/apache/commons/math3/geometry/partitioning/utilities/OrderedTuple.encoding:[J (1, 1)
	35 arraylength (1, 1)
	36 iconst_1 (1, 1)
	37 if_icmpne (1, 1)
	38 15 (1, 1)
	40 aload_0 (1, 1)
	41 getfield (1, 1)
	42 org/apache/commons/math3/geometry/partitioning/utilities/OrderedTuple.encoding:[J (1, 1)
	44 iconst_0 (1, 1)
	45 laload (1, 1)
	46 lconst_0 (1, 1)
	47 lcmp (1, 1)
	48 ifne (1, 1)
	49 4 (1, 1)
	51 return (1, 1)
	52 aload_0 (0, 0)
	53 getfield (0, 0)
	54 org/apache/commons/math3/geometry/partitioning/utilities/OrderedTuple.offset:I (0, 0)
	56 iconst_1 (0, 0)
	57 iadd (0, 0)
	58 aload_0 (0, 0)
	59 getfield (0, 0)
	60 org/apache/commons/math3/geometry/partitioning/utilities/OrderedTuple.lsb:I (0, 0)
	62 isub (0, 0)
	63 istore_2 (0, 0)
	64 iload_2 (0, 0)
	65 bipush (0, 0)
	66 62 (0, 0)
	67 iadd (0, 0)
	68 bipush (0, 0)
	69 63 (0, 0)
	70 idiv (0, 0)
	71 istore_3 (0, 0)
	72 aload_0 (0, 0)
	73 aload_0 (0, 0)
	74 getfield (0, 0)
	75 org/apache/commons/math3/geometry/partitioning/utilities/OrderedTuple.components:[D (0, 0)
	77 arraylength (0, 0)
	78 iload_3 (0, 0)
	79 imul (0, 0)
	80 newarray (0, 0)
	81 11 (0, 0)
	82 putfield (0, 0)
	83 org/apache/commons/math3/geometry/partitioning/utilities/OrderedTuple.encoding:[J (0, 0)
	85 iconst_0 (0, 0)
	86 istore (0, 0)
	87 #4 (0, 0)
	88 bipush (0, 1)
	89 62 (0, 1)
	90 istore (0, 1)
	91 #5 (0, 1)
	92 lconst_0 (0, 1)
	93 lstore (0, 1)
	94 #6 (0, 1)
	95 aload_0 (1, 4)
	96 getfield (1, 4)
	97 org/apache/commons/math3/geometry/partitioning/utilities/OrderedTuple.offset:I (1, 4)
	99 istore (1, 4)
	100 #8 (1, 4)
	101 iload (1, 4)
	102 #4 (1, 4)
	103 aload_0 (1, 4)
	104 getfield (1, 4)
	105 org/apache/commons/math3/geometry/partitioning/utilities/OrderedTuple.encoding:[J (1, 4)
	107 arraylength (1, 4)
	108 if_icmpge (1, 4)
	109 75 (1, 4)
	111 iconst_0 (2, 4)
	112 istore (2, 4)
	113 #9 (2, 4)
	114 iload (2, 4)
	115 #9 (2, 4)
	116 aload_0 (2, 4)
	117 getfield (2, 4)
	118 org/apache/commons/math3/geometry/partitioning/utilities/OrderedTuple.components:[D (2, 4)
	120 arraylength (2, 4)
	121 if_icmpge (2, 4)
	122 56 (2, 4)
	124 aload_0 (3, 1)
	125 iload (3, 1)
	126 #9 (3, 1)
	127 iload (3, 1)
	128 #8 (3, 1)
	129 invokespecial (3, 1)
	130 org/apache/commons/math3/geometry/partitioning/utilities/OrderedTuple.getBit:(II)I (3, 1)
	132 ifeq (3, 1)
	133 12 (3, 1)
	135 lload (3, 1)
	136 #6 (3, 1)
	137 lconst_1 (3, 1)
	138 iload (3, 1)
	139 #5 (3, 1)
	140 lshl (3, 1)
	141 lor (3, 1)
	142 lstore (3, 1)
	143 #6 (3, 1)
	144 iload (3, 1)
	145 #5 (3, 1)
	146 iinc (3, 1)
	147 #5 (3, 1)
	148 -102 (3, 1)
	149 ifne (3, 1)
	150 22 (3, 1)
	152 aload_0 (3, 1)
	153 getfield (3, 1)
	154 org/apache/commons/math3/geometry/partitioning/utilities/OrderedTuple.encoding:[J (3, 1)
	156 iload (3, 1)
	157 #4 (3, 1)
	158 iinc (3, 1)
	159 #4 (3, 1)
	160 22 (3, 1)
	161 lload (3, 1)
	162 #6 (3, 1)
	163 lastore (3, 1)
	164 lconst_0 (3, 1)
	165 lstore (3, 1)
	166 #6 (3, 1)
	167 bipush (3, 1)
	168 62 (3, 1)
	169 istore (3, 1)
	170 #5 (3, 1)
	171 iinc (3, 1)
	172 #9 (3, 1)
	173 -89 (3, 1)
	174 goto (3, 1)
	175 -60 (3, 1)
	177 iinc (3, 1)
	178 #8 (3, 1)
	179 -89 (3, 1)
	180 goto (3, 1)
	181 -79 (3, 1)
	183 return (1, 4)

Method: compareTo
	0 aload_0 (0, 0)
	1 aload_1 (0, 0)
	2 checkcast (0, 0)
	3 org/apache/commons/math3/geometry/partitioning/utilities/OrderedTuple (0, 0)
	5 invokevirtual (0, 0)
	6 org/apache/commons/math3/geometry/partitioning/utilities/OrderedTuple.compareTo:(Lorg/apache/commons/math3/geometry/partitioning/utilities/OrderedTuple;)I (0, 0)
	8 ireturn (0, 0)

Method: equals
	0 aload_0 (1, 1)
	1 aload_1 (1, 1)
	2 if_acmpne (1, 1)
	3 5 (1, 1)
	5 iconst_1 (1, 1)
	6 ireturn (1, 1)
	7 aload_1 (1, 1)
	8 instanceof (1, 1)
	9 org/apache/commons/math3/geometry/partitioning/utilities/OrderedTuple (1, 1)
	11 ifeq (1, 1)
	12 20 (1, 1)
	14 aload_0 (1, 1)
	15 aload_1 (1, 1)
	16 checkcast (1, 1)
	17 org/apache/commons/math3/geometry/partitioning/utilities/OrderedTuple (1, 1)
	19 invokevirtual (1, 1)
	20 org/apache/commons/math3/geometry/partitioning/utilities/OrderedTuple.compareTo:(Lorg/apache/commons/math3/geometry/partitioning/utilities/OrderedTuple;)I (1, 1)
	22 ifne (1, 1)
	23 7 (1, 1)
	25 iconst_1 (1, 1)
	26 goto (1, 1)
	27 4 (1, 1)
	29 iconst_0 (1, 1)
	30 ireturn (1, 1)
	31 iconst_0 (1, 2)
	32 ireturn (1, 2)

Method: hashCode
	0 bipush (0, 0)
	1 37 (0, 0)
	2 istore_1 (0, 0)
	3 bipush (0, 0)
	4 97 (0, 0)
	5 istore_2 (0, 0)
	6 bipush (0, 0)
	7 71 (0, 0)
	8 istore_3 (0, 0)
	9 aload_0 (0, 4)
	10 getfield (0, 4)
	11 org/apache/commons/math3/geometry/partitioning/utilities/OrderedTuple.components:[D (0, 4)
	13 invokestatic (0, 4)
	14 java/util/Arrays.hashCode:([D)I (0, 4)
	16 istore (0, 4)
	17 #4 (0, 4)
	18 iload (0, 4)
	19 #4 (0, 4)
	20 bipush (0, 4)
	21 37 (0, 4)
	22 imul (0, 4)
	23 aload_0 (0, 4)
	24 getfield (0, 4)
	25 org/apache/commons/math3/geometry/partitioning/utilities/OrderedTuple.offset:I (0, 4)
	27 iadd (0, 4)
	28 istore (0, 4)
	29 #4 (0, 4)
	30 iload (0, 4)
	31 #4 (0, 4)
	32 bipush (0, 4)
	33 37 (0, 4)
	34 imul (0, 4)
	35 aload_0 (0, 4)
	36 getfield (0, 4)
	37 org/apache/commons/math3/geometry/partitioning/utilities/OrderedTuple.lsb:I (0, 4)
	39 iadd (0, 4)
	40 istore (0, 4)
	41 #4 (0, 4)
	42 iload (0, 4)
	43 #4 (0, 4)
	44 bipush (0, 4)
	45 37 (0, 4)
	46 imul (0, 4)
	47 aload_0 (0, 4)
	48 getfield (0, 4)
	49 org/apache/commons/math3/geometry/partitioning/utilities/OrderedTuple.posInf:Z (0, 4)
	51 ifeq (0, 4)
	52 8 (0, 4)
	54 bipush (0, 4)
	55 97 (0, 4)
	56 goto (0, 4)
	57 5 (0, 4)
	59 bipush (0, 4)
	60 71 (0, 4)
	61 iadd (0, 4)
	62 istore (0, 4)
	63 #4 (0, 4)
	64 iload (0, 4)
	65 #4 (0, 4)
	66 bipush (0, 4)
	67 37 (0, 4)
	68 imul (0, 4)
	69 aload_0 (0, 4)
	70 getfield (0, 4)
	71 org/apache/commons/math3/geometry/partitioning/utilities/OrderedTuple.negInf:Z (0, 4)
	73 ifeq (0, 4)
	74 8 (0, 4)
	76 bipush (0, 4)
	77 97 (0, 4)
	78 goto (0, 4)
	79 5 (0, 4)
	81 bipush (0, 4)
	82 71 (0, 4)
	83 iadd (0, 4)
	84 istore (0, 4)
	85 #4 (0, 4)
	86 iload (0, 4)
	87 #4 (0, 4)
	88 bipush (0, 4)
	89 37 (0, 4)
	90 imul (0, 4)
	91 aload_0 (0, 4)
	92 getfield (0, 4)
	93 org/apache/commons/math3/geometry/partitioning/utilities/OrderedTuple.nan:Z (0, 4)
	95 ifeq (0, 4)
	96 8 (0, 4)
	98 bipush (0, 4)
	99 97 (0, 4)
	100 goto (0, 4)
	101 5 (0, 4)
	103 bipush (0, 4)
	104 71 (0, 4)
	105 iadd (0, 4)
	106 istore (0, 4)
	107 #4 (0, 4)
	108 iload (0, 4)
	109 #4 (0, 4)
	110 ireturn (0, 4)

Method: getComponents
	0 aload_0 (0, 0)
	1 getfield (0, 0)
	2 org/apache/commons/math3/geometry/partitioning/utilities/OrderedTuple.components:[D (0, 0)
	4 invokevirtual (0, 0)
	5 [D.clone:()Ljava/lang/Object; (0, 0)
	7 checkcast (0, 0)
	8 [D (0, 0)
	10 areturn (0, 0)

Method: sign
	0 lload_0 (0, 0)
	1 ldc2_w (0, 0)
	2 9223372036854775808 (0, 0)
	4 land (0, 0)
	5 lreturn (0, 0)

Method: exponent
	0 lload_0 (0, 0)
	1 ldc2_w (0, 0)
	2 9218868437227405312 (0, 0)
	4 land (0, 0)
	5 bipush (0, 0)
	6 52 (0, 0)
	7 lshr (0, 0)
	8 l2i (0, 0)
	9 sipush (0, 0)
	10 1075 (0, 0)
	12 isub (0, 0)
	13 ireturn (0, 0)

Method: mantissa
	0 lload_0 (0, 0)
	1 ldc2_w (0, 0)
	2 9218868437227405312 (0, 0)
	4 land (0, 0)
	5 lconst_0 (0, 0)
	6 lcmp (0, 0)
	7 ifne (0, 0)
	8 13 (0, 0)
	10 lload_0 (0, 0)
	11 ldc2_w (0, 0)
	12 4503599627370495 (0, 0)
	14 land (0, 0)
	15 iconst_1 (0, 0)
	16 lshl (0, 0)
	17 goto (0, 0)
	18 12 (0, 0)
	20 ldc2_w (0, 0)
	21 4503599627370496 (0, 0)
	23 lload_0 (0, 0)
	24 ldc2_w (0, 0)
	25 4503599627370495 (0, 0)
	27 land (0, 0)
	28 lor (0, 0)
	29 lreturn (0, 0)

Method: computeMSB
	0 lload_0 (0, 0)
	1 lstore_2 (0, 0)
	2 ldc2_w (0, 0)
	3 4294967295 (0, 0)
	5 lstore (0, 0)
	6 #4 (0, 0)
	7 bipush (0, 0)
	8 32 (0, 0)
	9 istore (0, 0)
	10 #6 (0, 0)
	11 iconst_0 (0, 0)
	12 istore (0, 0)
	13 #7 (0, 0)
	14 iload (1, 3)
	15 #6 (1, 3)
	16 ifeq (1, 3)
	17 40 (1, 3)
	19 lload_2 (2, 1)
	20 lload (2, 1)
	21 #4 (2, 1)
	22 land (2, 1)
	23 lload_2 (2, 1)
	24 lcmp (2, 1)
	25 ifeq (2, 1)
	26 15 (2, 1)
	28 iload (2, 1)
	29 #7 (2, 1)
	30 iload (2, 1)
	31 #6 (2, 1)
	32 ior (2, 1)
	33 istore (2, 1)
	34 #7 (2, 1)
	35 lload_2 (2, 1)
	36 iload (2, 1)
	37 #6 (2, 1)
	38 lshr (2, 1)
	39 lstore_2 (2, 1)
	40 iload (1, 3)
	41 #6 (1, 3)
	42 iconst_1 (1, 3)
	43 ishr (1, 3)
	44 istore (1, 3)
	45 #6 (1, 3)
	46 lload (1, 3)
	47 #4 (1, 3)
	48 iload (1, 3)
	49 #6 (1, 3)
	50 lshr (1, 3)
	51 lstore (1, 3)
	52 #4 (1, 3)
	53 goto (1, 3)
	54 -39 (1, 3)
	56 iload (0, 0)
	57 #7 (0, 0)
	58 ireturn (0, 0)

Method: computeLSB
	0 lload_0 (0, 0)
	1 lstore_2 (0, 0)
	2 ldc2_w (0, 0)
	3 18446744069414584320 (0, 0)
	5 lstore (0, 0)
	6 #4 (0, 0)
	7 bipush (0, 0)
	8 32 (0, 0)
	9 istore (0, 0)
	10 #6 (0, 0)
	11 iconst_0 (0, 0)
	12 istore (0, 0)
	13 #7 (0, 0)
	14 iload (1, 3)
	15 #6 (1, 3)
	16 ifeq (1, 3)
	17 40 (1, 3)
	19 lload_2 (2, 1)
	20 lload (2, 1)
	21 #4 (2, 1)
	22 land (2, 1)
	23 lload_2 (2, 1)
	24 lcmp (2, 1)
	25 ifne (2, 1)
	26 15 (2, 1)
	28 iload (2, 1)
	29 #7 (2, 1)
	30 iload (2, 1)
	31 #6 (2, 1)
	32 ior (2, 1)
	33 istore (2, 1)
	34 #7 (2, 1)
	35 lload_2 (2, 1)
	36 iload (2, 1)
	37 #6 (2, 1)
	38 lshr (2, 1)
	39 lstore_2 (2, 1)
	40 iload (1, 3)
	41 #6 (1, 3)
	42 iconst_1 (1, 3)
	43 ishr (1, 3)
	44 istore (1, 3)
	45 #6 (1, 3)
	46 lload (1, 3)
	47 #4 (1, 3)
	48 iload (1, 3)
	49 #6 (1, 3)
	50 lshr (1, 3)
	51 lstore (1, 3)
	52 #4 (1, 3)
	53 goto (1, 3)
	54 -39 (1, 3)
	56 iload (0, 0)
	57 #7 (0, 0)
	58 ireturn (0, 0)

Method: getBit
	0 aload_0 (0, 0)
	1 getfield (0, 0)
	2 org/apache/commons/math3/geometry/partitioning/utilities/OrderedTuple.components:[D (0, 0)
	4 iload_1 (0, 0)
	5 daload (0, 0)
	6 invokestatic (0, 0)
	7 java/lang/Double.doubleToLongBits:(D)J (0, 0)
	9 lstore_3 (0, 0)
	10 lload_3 (0, 0)
	11 invokestatic (0, 0)
	12 org/apache/commons/math3/geometry/partitioning/utilities/OrderedTuple.exponent:(J)I (0, 0)
	14 istore (0, 0)
	15 #5 (0, 0)
	16 iload_2 (1, 1)
	17 iload (1, 1)
	18 #5 (1, 1)
	19 if_icmplt (1, 1)
	20 11 (1, 1)
	22 iload_2 (1, 1)
	23 aload_0 (1, 1)
	24 getfield (1, 1)
	25 org/apache/commons/math3/geometry/partitioning/utilities/OrderedTuple.offset:I (1, 1)
	27 if_icmple (1, 1)
	28 5 (1, 1)
	30 iconst_0 (1, 1)
	31 ireturn (1, 1)
	32 iload_2 (1, 1)
	33 aload_0 (1, 1)
	34 getfield (1, 1)
	35 org/apache/commons/math3/geometry/partitioning/utilities/OrderedTuple.offset:I (1, 1)
	37 if_icmpne (1, 1)
	38 18 (1, 1)
	40 lload_3 (1, 1)
	41 invokestatic (1, 1)
	42 org/apache/commons/math3/geometry/partitioning/utilities/OrderedTuple.sign:(J)J (1, 1)
	44 lconst_0 (1, 1)
	45 lcmp (1, 1)
	46 ifne (1, 1)
	47 7 (1, 1)
	49 iconst_1 (1, 1)
	50 goto (1, 1)
	51 4 (1, 1)
	53 iconst_0 (1, 1)
	54 ireturn (1, 1)
	55 iload_2 (1, 1)
	56 iload (1, 1)
	57 #5 (1, 1)
	58 bipush (1, 1)
	59 52 (1, 1)
	60 iadd (1, 1)
	61 if_icmple (1, 1)
	62 18 (1, 1)
	64 lload_3 (1, 1)
	65 invokestatic (1, 1)
	66 org/apache/commons/math3/geometry/partitioning/utilities/OrderedTuple.sign:(J)J (1, 1)
	68 lconst_0 (1, 1)
	69 lcmp (1, 1)
	70 ifne (1, 1)
	71 7 (1, 1)
	73 iconst_0 (1, 1)
	74 goto (1, 1)
	75 4 (1, 1)
	77 iconst_1 (1, 1)
	78 ireturn (1, 1)
	79 lload_3 (1, 2)
	80 invokestatic (1, 2)
	81 org/apache/commons/math3/geometry/partitioning/utilities/OrderedTuple.sign:(J)J (1, 2)
	83 lconst_0 (1, 2)
	84 lcmp (1, 2)
	85 ifne (1, 2)
	86 10 (1, 2)
	88 lload_3 (1, 2)
	89 invokestatic (1, 2)
	90 org/apache/commons/math3/geometry/partitioning/utilities/OrderedTuple.mantissa:(J)J (1, 2)
	92 goto (1, 2)
	93 8 (1, 2)
	95 lload_3 (1, 2)
	96 invokestatic (1, 2)
	97 org/apache/commons/math3/geometry/partitioning/utilities/OrderedTuple.mantissa:(J)J (1, 2)
	99 lneg (1, 2)
	100 lstore (1, 2)
	101 #6 (1, 2)
	102 lload (1, 2)
	103 #6 (1, 2)
	104 iload_2 (1, 2)
	105 iload (1, 2)
	106 #5 (1, 2)
	107 isub (1, 2)
	108 lshr (1, 2)
	109 lconst_1 (1, 2)
	110 land (1, 2)
	111 l2i (1, 2)
	112 ireturn (1, 2)

