Method: setData
	0 aload_1 (1, 1)
	1 ifnonnull (1, 1)
	2 18 (1, 1)
	4 new (1, 1)
	5 org/apache/commons/math3/exception/NullArgumentException (1, 1)
	7 dup (1, 1)
	8 getstatic (1, 1)
	9 org/apache/commons/math3/exception/util/LocalizedFormats.INPUT_ARRAY:Lorg/apache/commons/math3/exception/util/LocalizedFormats; (1, 1)
	11 iconst_0 (1, 1)
	12 anewarray (1, 1)
	13 java/lang/Object (1, 1)
	15 invokespecial (1, 1)
	16 org/apache/commons/math3/exception/NullArgumentException.<init>:(Lorg/apache/commons/math3/exception/util/Localizable;[Ljava/lang/Object;)V (1, 1)
	18 athrow (1, 1)
	19 iload_2 (1, 1)
	20 ifge (1, 1)
	21 18 (1, 1)
	23 new (1, 1)
	24 org/apache/commons/math3/exception/NotPositiveException (1, 1)
	26 dup (1, 1)
	27 getstatic (1, 1)
	28 org/apache/commons/math3/exception/util/LocalizedFormats.START_POSITION:Lorg/apache/commons/math3/exception/util/LocalizedFormats; (1, 1)
	30 iload_2 (1, 1)
	31 invokestatic (1, 1)
	32 java/lang/Integer.valueOf:(I)Ljava/lang/Integer; (1, 1)
	34 invokespecial (1, 1)
	35 org/apache/commons/math3/exception/NotPositiveException.<init>:(Lorg/apache/commons/math3/exception/util/Localizable;Ljava/lang/Number;)V (1, 1)
	37 athrow (1, 1)
	38 iload_3 (1, 1)
	39 ifge (1, 1)
	40 18 (1, 1)
	42 new (1, 1)
	43 org/apache/commons/math3/exception/NotPositiveException (1, 1)
	45 dup (1, 1)
	46 getstatic (1, 1)
	47 org/apache/commons/math3/exception/util/LocalizedFormats.LENGTH:Lorg/apache/commons/math3/exception/util/LocalizedFormats; (1, 1)
	49 iload_3 (1, 1)
	50 invokestatic (1, 1)
	51 java/lang/Integer.valueOf:(I)Ljava/lang/Integer; (1, 1)
	53 invokespecial (1, 1)
	54 org/apache/commons/math3/exception/NotPositiveException.<init>:(Lorg/apache/commons/math3/exception/util/Localizable;Ljava/lang/Number;)V (1, 1)
	56 athrow (1, 1)
	57 iload_2 (1, 1)
	58 iload_3 (1, 1)
	59 iadd (1, 1)
	60 aload_1 (1, 1)
	61 arraylength (1, 1)
	62 if_icmple (1, 1)
	63 26 (1, 1)
	65 new (1, 1)
	66 org/apache/commons/math3/exception/NumberIsTooLargeException (1, 1)
	68 dup (1, 1)
	69 getstatic (1, 1)
	70 org/apache/commons/math3/exception/util/LocalizedFormats.SUBARRAY_ENDS_AFTER_ARRAY_END:Lorg/apache/commons/math3/exception/util/LocalizedFormats; (1, 1)
	72 iload_2 (1, 1)
	73 iload_3 (1, 1)
	74 iadd (1, 1)
	75 invokestatic (1, 1)
	76 java/lang/Integer.valueOf:(I)Ljava/lang/Integer; (1, 1)
	78 aload_1 (1, 1)
	79 arraylength (1, 1)
	80 invokestatic (1, 1)
	81 java/lang/Integer.valueOf:(I)Ljava/lang/Integer; (1, 1)
	83 iconst_1 (1, 1)
	84 invokespecial (1, 1)
	85 org/apache/commons/math3/exception/NumberIsTooLargeException.<init>:(Lorg/apache/commons/math3/exception/util/Localizable;Ljava/lang/Number;Ljava/lang/Number;Z)V (1, 1)
	87 athrow (1, 1)
	88 aload_0 (0, 0)
	89 iload_3 (0, 0)
	90 newarray (0, 0)
	91 7 (0, 0)
	92 putfield (0, 0)
	93 org/apache/commons/math3/stat/descriptive/AbstractUnivariateStatistic.storedData:[D (0, 0)
	95 aload_1 (0, 0)
	96 iload_2 (0, 0)
	97 aload_0 (0, 0)
	98 getfield (0, 0)
	99 org/apache/commons/math3/stat/descriptive/AbstractUnivariateStatistic.storedData:[D (0, 0)
	101 iconst_0 (0, 0)
	102 iload_3 (0, 0)
	103 invokestatic (0, 0)
	104 java/lang/System.arraycopy:(Ljava/lang/Object;ILjava/lang/Object;II)V (0, 0)
	106 return (0, 0)

Method: getData
	0 aload_0 (0, 0)
	1 getfield (0, 0)
	2 org/apache/commons/math3/stat/descriptive/AbstractUnivariateStatistic.storedData:[D (0, 0)
	4 ifnonnull (0, 0)
	5 7 (0, 0)
	7 aconst_null (0, 0)
	8 goto (0, 0)
	9 13 (0, 0)
	11 aload_0 (0, 0)
	12 getfield (0, 0)
	13 org/apache/commons/math3/stat/descriptive/AbstractUnivariateStatistic.storedData:[D (0, 0)
	15 invokevirtual (0, 0)
	16 [D.clone:()Ljava/lang/Object; (0, 0)
	18 checkcast (0, 0)
	19 [D (0, 0)
	21 areturn (0, 0)

Method: getDataRef
	0 aload_0 (0, 0)
	1 getfield (0, 0)
	2 org/apache/commons/math3/stat/descriptive/AbstractUnivariateStatistic.storedData:[D (0, 0)
	4 areturn (0, 0)

Method: evaluate
	0 aload_0 (0, 0)
	1 aload_1 (0, 0)
	2 iconst_0 (0, 0)
	3 iconst_0 (0, 0)
	4 invokevirtual (0, 0)
	5 org/apache/commons/math3/stat/descriptive/AbstractUnivariateStatistic.test:([DII)Z (0, 0)
	7 pop (0, 0)
	8 aload_0 (0, 0)
	9 aload_1 (0, 0)
	10 iconst_0 (0, 0)
	11 aload_1 (0, 0)
	12 arraylength (0, 0)
	13 invokevirtual (0, 0)
	14 org/apache/commons/math3/stat/descriptive/AbstractUnivariateStatistic.evaluate:([DII)D (0, 0)
	16 dreturn (0, 0)

Method: test
	0 aload_1 (1, 1)
	1 aload_2 (1, 1)
	2 iload_3 (1, 1)
	3 iload (1, 1)
	4 #4 (1, 1)
	5 iload (1, 1)
	6 #5 (1, 1)
	7 invokestatic (1, 1)
	8 org/apache/commons/math3/util/MathArrays.verifyValues:([D[DIIZ)Z (1, 1)
	10 ireturn (0, 1)

