Method: <init>
	0 aload_0 (0, 0)
	1 invokespecial (0, 0)
	4 aload_0 (0, 0)
	5 aload_1 (0, 0)
	6 ifnonnull (0, 0)
	9 new (0, 0)
	12 dup (0, 0)
	13 invokespecial (0, 0)
	16 goto (0, 0)
	19 aload_1 (0, 0)
	20 putfield (0, 0)
	23 aload_0 (0, 0)
	24 aload_2 (0, 0)
	25 ifnonnull (0, 0)
	28 new (0, 0)
	31 dup (0, 0)
	32 invokespecial (0, 0)
	35 goto (0, 0)
	38 aload_2 (0, 0)
	39 putfield (0, 0)
	42 return (0, 0)

Method: getMax
	0 aload_0 (0, 0)
	1 getfield (0, 0)
	4 dup (0, 0)
	5 astore_1 (0, 0)
	6 monitorenter (0, 0)
	7 aload_0 (0, 0)
	8 getfield (0, 0)
	11 invokevirtual (0, 0)
	14 aload_1 (0, 0)
	15 monitorexit (0, 0)
	16 dreturn (0, 0)
	17 astore_2 (0, 0)
	18 aload_1 (0, 0)
	19 monitorexit (0, 0)
	20 aload_2 (0, 0)
	21 athrow (0, 0)

Method: getMean
	0 aload_0 (0, 0)
	1 getfield (0, 0)
	4 dup (0, 0)
	5 astore_1 (0, 0)
	6 monitorenter (0, 0)
	7 aload_0 (0, 0)
	8 getfield (0, 0)
	11 invokevirtual (0, 0)
	14 aload_1 (0, 0)
	15 monitorexit (0, 0)
	16 dreturn (0, 0)
	17 astore_2 (0, 0)
	18 aload_1 (0, 0)
	19 monitorexit (0, 0)
	20 aload_2 (0, 0)
	21 athrow (0, 0)

Method: getMin
	0 aload_0 (0, 0)
	1 getfield (0, 0)
	4 dup (0, 0)
	5 astore_1 (0, 0)
	6 monitorenter (0, 0)
	7 aload_0 (0, 0)
	8 getfield (0, 0)
	11 invokevirtual (0, 0)
	14 aload_1 (0, 0)
	15 monitorexit (0, 0)
	16 dreturn (0, 0)
	17 astore_2 (0, 0)
	18 aload_1 (0, 0)
	19 monitorexit (0, 0)
	20 aload_2 (0, 0)
	21 athrow (0, 0)

Method: getN
	0 aload_0 (0, 0)
	1 getfield (0, 0)
	4 dup (0, 0)
	5 astore_1 (0, 0)
	6 monitorenter (0, 0)
	7 aload_0 (0, 0)
	8 getfield (0, 0)
	11 invokevirtual (0, 0)
	14 aload_1 (0, 0)
	15 monitorexit (0, 0)
	16 lreturn (0, 0)
	17 astore_2 (0, 0)
	18 aload_1 (0, 0)
	19 monitorexit (0, 0)
	20 aload_2 (0, 0)
	21 athrow (0, 0)

Method: getStandardDeviation
	0 aload_0 (0, 0)
	1 getfield (0, 0)
	4 dup (0, 0)
	5 astore_1 (0, 0)
	6 monitorenter (0, 0)
	7 aload_0 (0, 0)
	8 getfield (0, 0)
	11 invokevirtual (0, 0)
	14 aload_1 (0, 0)
	15 monitorexit (0, 0)
	16 dreturn (0, 0)
	17 astore_2 (0, 0)
	18 aload_1 (0, 0)
	19 monitorexit (0, 0)
	20 aload_2 (0, 0)
	21 athrow (0, 0)

Method: getSum
	0 aload_0 (0, 0)
	1 getfield (0, 0)
	4 dup (0, 0)
	5 astore_1 (0, 0)
	6 monitorenter (0, 0)
	7 aload_0 (0, 0)
	8 getfield (0, 0)
	11 invokevirtual (0, 0)
	14 aload_1 (0, 0)
	15 monitorexit (0, 0)
	16 dreturn (0, 0)
	17 astore_2 (0, 0)
	18 aload_1 (0, 0)
	19 monitorexit (0, 0)
	20 aload_2 (0, 0)
	21 athrow (0, 0)

Method: getVariance
	0 aload_0 (0, 0)
	1 getfield (0, 0)
	4 dup (0, 0)
	5 astore_1 (0, 0)
	6 monitorenter (0, 0)
	7 aload_0 (0, 0)
	8 getfield (0, 0)
	11 invokevirtual (0, 0)
	14 aload_1 (0, 0)
	15 monitorexit (0, 0)
	16 dreturn (0, 0)
	17 astore_2 (0, 0)
	18 aload_1 (0, 0)
	19 monitorexit (0, 0)
	20 aload_2 (0, 0)
	21 athrow (0, 0)

Method: getSumOfLogs
	0 aload_0 (0, 0)
	1 getfield (0, 0)
	4 dup (0, 0)
	5 astore_1 (0, 0)
	6 monitorenter (0, 0)
	7 aload_0 (0, 0)
	8 getfield (0, 0)
	11 invokevirtual (0, 0)
	14 aload_1 (0, 0)
	15 monitorexit (0, 0)
	16 dreturn (0, 0)
	17 astore_2 (0, 0)
	18 aload_1 (0, 0)
	19 monitorexit (0, 0)
	20 aload_2 (0, 0)
	21 athrow (0, 0)

Method: getGeometricMean
	0 aload_0 (0, 0)
	1 getfield (0, 0)
	4 dup (0, 0)
	5 astore_1 (0, 0)
	6 monitorenter (0, 0)
	7 aload_0 (0, 0)
	8 getfield (0, 0)
	11 invokevirtual (0, 0)
	14 aload_1 (0, 0)
	15 monitorexit (0, 0)
	16 dreturn (0, 0)
	17 astore_2 (0, 0)
	18 aload_1 (0, 0)
	19 monitorexit (0, 0)
	20 aload_2 (0, 0)
	21 athrow (0, 0)

Method: getSumsq
	0 aload_0 (0, 0)
	1 getfield (0, 0)
	4 dup (0, 0)
	5 astore_1 (0, 0)
	6 monitorenter (0, 0)
	7 aload_0 (0, 0)
	8 getfield (0, 0)
	11 invokevirtual (0, 0)
	14 aload_1 (0, 0)
	15 monitorexit (0, 0)
	16 dreturn (0, 0)
	17 astore_2 (0, 0)
	18 aload_1 (0, 0)
	19 monitorexit (0, 0)
	20 aload_2 (0, 0)
	21 athrow (0, 0)

Method: getSecondMoment
	0 aload_0 (0, 0)
	1 getfield (0, 0)
	4 dup (0, 0)
	5 astore_1 (0, 0)
	6 monitorenter (0, 0)
	7 aload_0 (0, 0)
	8 getfield (0, 0)
	11 invokevirtual (0, 0)
	14 aload_1 (0, 0)
	15 monitorexit (0, 0)
	16 dreturn (0, 0)
	17 astore_2 (0, 0)
	18 aload_1 (0, 0)
	19 monitorexit (0, 0)
	20 aload_2 (0, 0)
	21 athrow (0, 0)

Method: getSummary
	0 aload_0 (0, 0)
	1 getfield (0, 0)
	4 dup (0, 0)
	5 astore_1 (0, 0)
	6 monitorenter (0, 0)
	7 new (0, 0)
	10 dup (0, 0)
	11 aload_0 (0, 0)
	12 invokevirtual (0, 0)
	15 aload_0 (0, 0)
	16 invokevirtual (0, 0)
	19 aload_0 (0, 0)
	20 invokevirtual (0, 0)
	23 aload_0 (0, 0)
	24 invokevirtual (0, 0)
	27 aload_0 (0, 0)
	28 invokevirtual (0, 0)
	31 aload_0 (0, 0)
	32 invokevirtual (0, 0)
	35 invokespecial (0, 0)
	38 aload_1 (0, 0)
	39 monitorexit (0, 0)
	40 areturn (0, 0)
	41 astore_2 (0, 0)
	42 aload_1 (0, 0)
	43 monitorexit (0, 0)
	44 aload_2 (0, 0)
	45 athrow (0, 0)

Method: createContributingStatistics
	0 new (0, 0)
	3 dup (0, 0)
	4 aload_0 (0, 0)
	5 getfield (0, 0)
	8 invokespecial (0, 0)
	11 astore_1 (0, 0)
	12 aload_0 (0, 0)
	13 getfield (0, 0)
	16 aload_1 (0, 0)
	17 invokestatic (0, 0)
	20 aload_1 (0, 0)
	21 areturn (0, 0)

Method: aggregate
	0 aload_0 (1, 1)
	1 ifnonnull (1, 1)
	4 aconst_null (1, 1)
	5 areturn (1, 1)
	6 aload_0 (0, 0)
	7 invokeinterface (0, 0)
	12 astore_1 (0, 0)
	13 aload_1 (1, 1)
	14 invokeinterface (1, 1)
	19 ifne (1, 1)
	22 aconst_null (1, 1)
	23 areturn (1, 1)
	24 aload_1 (0, 0)
	25 invokeinterface (0, 0)
	30 checkcast (0, 0)
	33 astore_2 (0, 0)
	34 aload_2 (0, 0)
	35 invokeinterface (0, 0)
	40 lstore_3 (0, 0)
	41 aload_2 (0, 0)
	42 invokeinterface (0, 0)
	47 dstore (0, 0)
	49 aload_2 (0, 0)
	50 invokeinterface (0, 0)
	55 dstore (0, 0)
	57 aload_2 (0, 0)
	58 invokeinterface (0, 0)
	63 dstore (0, 0)
	65 aload_2 (0, 0)
	66 invokeinterface (0, 0)
	71 dstore (0, 0)
	73 dload (0, 0)
	75 lload_3 (0, 0)
	76 l2d (0, 0)
	77 dconst_1 (0, 0)
	78 dsub (0, 0)
	79 dmul (0, 0)
	80 dstore (0, 0)
	82 aload_2 (0, 0)
	83 invokeinterface (0, 0)
	88 dstore (0, 0)
	90 aload_1 (1, 3)
	91 invokeinterface (1, 3)
	96 ifeq (1, 3)
	99 aload_1 (1, 3)
	100 invokeinterface (1, 3)
	105 checkcast (1, 3)
	108 astore_2 (1, 3)
	109 aload_2 (2, 1)
	110 invokeinterface (2, 1)
	115 dload (2, 1)
	117 dcmpg (2, 1)
	118 iflt (2, 1)
	121 dload (2, 1)
	123 invokestatic (2, 1)
	126 ifeq (2, 1)
	129 aload_2 (2, 1)
	130 invokeinterface (2, 1)
	135 dstore (2, 1)
	137 aload_2 (2, 1)
	138 invokeinterface (2, 1)
	143 dload (2, 1)
	145 dcmpl (2, 1)
	146 ifgt (2, 1)
	149 dload (2, 1)
	151 invokestatic (2, 1)
	154 ifeq (2, 1)
	157 aload_2 (2, 1)
	158 invokeinterface (2, 1)
	163 dstore (2, 1)
	165 dload (1, 3)
	167 aload_2 (1, 3)
	168 invokeinterface (1, 3)
	173 dadd (1, 3)
	174 dstore (1, 3)
	176 lload_3 (1, 3)
	177 l2d (1, 3)
	178 dstore (1, 3)
	180 aload_2 (1, 3)
	181 invokeinterface (1, 3)
	186 l2d (1, 3)
	187 dstore (1, 3)
	189 lload_3 (1, 3)
	190 l2d (1, 3)
	191 dload (1, 3)
	193 dadd (1, 3)
	194 d2l (1, 3)
	195 lstore_3 (1, 3)
	196 aload_2 (1, 1)
	197 invokeinterface (1, 1)
	202 dload (1, 1)
	204 dsub (1, 1)
	205 dstore (1, 1)
	207 dload (1, 1)
	209 lload_3 (1, 1)
	210 l2d (1, 1)
	211 ddiv (1, 1)
	212 dstore (1, 1)
	214 aload_2 (1, 1)
	215 invokeinterface (1, 1)
	220 dload (1, 1)
	222 dconst_1 (1, 1)
	223 dsub (1, 1)
	224 dmul (1, 1)
	225 dstore (1, 1)
	227 dload (1, 1)
	229 dload (1, 1)
	231 dadd (1, 1)
	232 dload (1, 1)
	234 dload (1, 1)
	236 dmul (1, 1)
	237 dload (1, 1)
	239 dmul (1, 1)
	240 dload (1, 1)
	242 dmul (1, 1)
	243 lload_3 (1, 1)
	244 l2d (1, 1)
	245 ddiv (1, 1)
	246 dadd (1, 1)
	247 dstore (1, 1)
	249 goto (0, 1)
	252 lload_3 (1, 1)
	253 lconst_0 (1, 1)
	254 lcmp (1, 1)
	255 ifne (1, 1)
	258 ldc2_w (1, 1)
	261 dstore (1, 1)
	263 goto (1, 1)
	266 lload_3 (1, 1)
	267 lconst_1 (1, 1)
	268 lcmp (1, 1)
	269 ifne (1, 1)
	272 dconst_0 (1, 1)
	273 dstore (1, 1)
	275 goto (1, 1)
	278 dload (1, 2)
	280 lload_3 (1, 2)
	281 lconst_1 (1, 2)
	282 lsub (1, 2)
	283 l2d (1, 2)
	284 ddiv (1, 2)
	285 dstore (1, 2)
	287 new (0, 1)
	290 dup (0, 1)
	291 dload (0, 1)
	293 dload (0, 1)
	295 lload_3 (0, 1)
	296 dload (0, 1)
	298 dload (0, 1)
	300 dload (0, 1)
	302 invokespecial (0, 1)
	305 areturn (0, 1)

