Method: <init>
	0 aload_0 (0, 0)
	1 invokespecial (0, 0)
	2 org/apache/commons/math3/stat/descriptive/SummaryStatistics.<init>:()V (0, 0)
	4 aload_0 (0, 0)
	5 aload_1 (0, 0)
	6 putfield (0, 0)
	7 org/apache/commons/math3/stat/descriptive/AggregateSummaryStatistics$AggregatingSummaryStatistics.aggregateStatistics:Lorg/apache/commons/math3/stat/descriptive/SummaryStatistics; (0, 0)
	9 return (0, 0)

Method: addValue
	0 aload_0 (0, 0)
	1 dload_1 (0, 0)
	2 invokespecial (0, 0)
	3 org/apache/commons/math3/stat/descriptive/SummaryStatistics.addValue:(D)V (0, 0)
	5 aload_0 (0, 0)
	6 getfield (0, 0)
	7 org/apache/commons/math3/stat/descriptive/AggregateSummaryStatistics$AggregatingSummaryStatistics.aggregateStatistics:Lorg/apache/commons/math3/stat/descriptive/SummaryStatistics; (0, 0)
	9 dup (0, 0)
	10 astore_3 (0, 0)
	11 monitorenter (0, 0)
	12 aload_0 (0, 0)
	13 getfield (0, 0)
	14 org/apache/commons/math3/stat/descriptive/AggregateSummaryStatistics$AggregatingSummaryStatistics.aggregateStatistics:Lorg/apache/commons/math3/stat/descriptive/SummaryStatistics; (0, 0)
	16 dload_1 (0, 0)
	17 invokevirtual (0, 0)
	18 org/apache/commons/math3/stat/descriptive/SummaryStatistics.addValue:(D)V (0, 0)
	20 aload_3 (0, 0)
	21 monitorexit (0, 0)
	22 goto (0, 0)
	23 10 (0, 0)
	25 astore (0, 0)
	26 #4 (0, 0)
	27 aload_3 (0, 0)
	28 monitorexit (0, 0)
	29 aload (0, 0)
	30 #4 (0, 0)
	31 athrow (0, 0)
	32 return (0, 0)

Method: equals
	0 aload_1 (1, 1)
	1 aload_0 (1, 1)
	2 if_acmpne (1, 1)
	3 5 (1, 1)
	5 iconst_1 (1, 1)
	6 ireturn (1, 1)
	7 aload_1 (1, 1)
	8 instanceof (1, 1)
	9 org/apache/commons/math3/stat/descriptive/AggregateSummaryStatistics$AggregatingSummaryStatistics (1, 1)
	11 ifne (1, 1)
	12 5 (1, 1)
	14 iconst_0 (1, 1)
	15 ireturn (1, 1)
	16 aload_1 (0, 0)
	17 checkcast (0, 0)
	18 org/apache/commons/math3/stat/descriptive/AggregateSummaryStatistics$AggregatingSummaryStatistics (0, 0)
	20 astore_2 (0, 0)
	21 aload_0 (0, 0)
	22 aload_2 (0, 0)
	23 invokespecial (0, 0)
	24 org/apache/commons/math3/stat/descriptive/SummaryStatistics.equals:(Ljava/lang/Object;)Z (0, 0)
	26 ifeq (0, 0)
	27 21 (0, 0)
	29 aload_0 (0, 0)
	30 getfield (0, 0)
	31 org/apache/commons/math3/stat/descriptive/AggregateSummaryStatistics$AggregatingSummaryStatistics.aggregateStatistics:Lorg/apache/commons/math3/stat/descriptive/SummaryStatistics; (0, 0)
	33 aload_2 (0, 0)
	34 getfield (0, 0)
	35 org/apache/commons/math3/stat/descriptive/AggregateSummaryStatistics$AggregatingSummaryStatistics.aggregateStatistics:Lorg/apache/commons/math3/stat/descriptive/SummaryStatistics; (0, 0)
	37 invokevirtual (0, 0)
	38 org/apache/commons/math3/stat/descriptive/SummaryStatistics.equals:(Ljava/lang/Object;)Z (0, 0)
	40 ifeq (0, 0)
	41 7 (0, 0)
	43 iconst_1 (0, 0)
	44 goto (0, 0)
	45 4 (0, 0)
	47 iconst_0 (0, 0)
	48 ireturn (0, 0)

Method: hashCode
	0 bipush (0, 0)
	1 123 (0, 0)
	2 aload_0 (0, 0)
	3 invokespecial (0, 0)
	4 org/apache/commons/math3/stat/descriptive/SummaryStatistics.hashCode:()I (0, 0)
	6 iadd (0, 0)
	7 aload_0 (0, 0)
	8 getfield (0, 0)
	9 org/apache/commons/math3/stat/descriptive/AggregateSummaryStatistics$AggregatingSummaryStatistics.aggregateStatistics:Lorg/apache/commons/math3/stat/descriptive/SummaryStatistics; (0, 0)
	11 invokevirtual (0, 0)
	12 org/apache/commons/math3/stat/descriptive/SummaryStatistics.hashCode:()I (0, 0)
	14 iadd (0, 0)
	15 ireturn (0, 0)

