Method: <init>
	0 aload_0 (0, 0)
	1 invokespecial (0, 0)
	4 aload_0 (0, 0)
	5 iconst_m1 (0, 0)
	6 putfield (0, 0)
	9 aload_0 (0, 0)
	10 new (0, 0)
	13 dup (0, 0)
	14 invokespecial (0, 0)
	17 putfield (0, 0)
	20 aload_0 (0, 0)
	21 new (0, 0)
	24 dup (0, 0)
	25 invokespecial (0, 0)
	28 putfield (0, 0)
	31 aload_0 (0, 0)
	32 new (0, 0)
	35 dup (0, 0)
	36 invokespecial (0, 0)
	39 putfield (0, 0)
	42 aload_0 (0, 0)
	43 new (0, 0)
	46 dup (0, 0)
	47 invokespecial (0, 0)
	50 putfield (0, 0)
	53 aload_0 (0, 0)
	54 new (0, 0)
	57 dup (0, 0)
	58 invokespecial (0, 0)
	61 putfield (0, 0)
	64 aload_0 (0, 0)
	65 new (0, 0)
	68 dup (0, 0)
	69 invokespecial (0, 0)
	72 putfield (0, 0)
	75 aload_0 (0, 0)
	76 new (0, 0)
	79 dup (0, 0)
	80 invokespecial (0, 0)
	83 putfield (0, 0)
	86 aload_0 (0, 0)
	87 new (0, 0)
	90 dup (0, 0)
	91 invokespecial (0, 0)
	94 putfield (0, 0)
	97 aload_0 (0, 0)
	98 new (0, 0)
	101 dup (0, 0)
	102 invokespecial (0, 0)
	105 putfield (0, 0)
	108 aload_0 (0, 0)
	109 new (0, 0)
	112 dup (0, 0)
	113 invokespecial (0, 0)
	116 putfield (0, 0)
	119 aload_0 (0, 0)
	120 new (0, 0)
	123 dup (0, 0)
	124 invokespecial (0, 0)
	127 putfield (0, 0)
	130 aload_1 (1, 1)
	131 aload_0 (1, 1)
	132 invokestatic (1, 1)
	135 return (0, 0)

Method: addValue
	0 aload_0 (1, 1)
	1 getfield (1, 1)
	4 iconst_m1 (1, 1)
	5 if_icmpeq (1, 1)
	8 aload_0 (2, 1)
	9 invokevirtual (2, 1)
	12 aload_0 (2, 1)
	13 getfield (2, 1)
	16 i2l (2, 1)
	17 lcmp (2, 1)
	18 ifne (2, 1)
	21 aload_0 (2, 1)
	22 getfield (2, 1)
	25 dload_1 (2, 1)
	26 invokevirtual (2, 1)
	29 pop2 (2, 1)
	30 goto (2, 1)
	33 aload_0 (2, 1)
	34 invokevirtual (2, 1)
	37 aload_0 (2, 1)
	38 getfield (2, 1)
	41 i2l (2, 1)
	42 lcmp (2, 1)
	43 ifge (2, 1)
	46 aload_0 (2, 1)
	47 getfield (2, 1)
	50 dload_1 (2, 1)
	51 invokevirtual (2, 1)
	54 goto (2, 1)
	57 aload_0 (1, 2)
	58 getfield (1, 2)
	61 dload_1 (1, 2)
	62 invokevirtual (1, 2)
	65 return (0, 1)

Method: removeMostRecentValue
	0 aload_0 (0, 0)
	1 getfield (0, 0)
	4 iconst_1 (0, 0)
	5 invokevirtual (0, 0)
	8 goto (0, 0)
	11 astore_1 (0, 0)
	12 new (0, 0)
	15 dup (0, 0)
	16 getstatic (0, 0)
	19 iconst_0 (0, 0)
	20 anewarray (0, 0)
	23 invokespecial (0, 0)
	26 athrow (0, 0)
	27 return (0, 0)

Method: replaceMostRecentValue
	0 aload_0 (0, 0)
	1 getfield (0, 0)
	4 dload_1 (0, 0)
	5 invokevirtual (0, 0)
	8 dreturn (0, 0)

Method: getMean
	0 aload_0 (0, 0)
	1 aload_0 (0, 0)
	2 getfield (0, 0)
	5 invokevirtual (0, 0)
	8 dreturn (0, 0)

Method: getGeometricMean
	0 aload_0 (0, 0)
	1 aload_0 (0, 0)
	2 getfield (0, 0)
	5 invokevirtual (0, 0)
	8 dreturn (0, 0)

Method: getVariance
	0 aload_0 (0, 0)
	1 aload_0 (0, 0)
	2 getfield (0, 0)
	5 invokevirtual (0, 0)
	8 dreturn (0, 0)

Method: getPopulationVariance
	0 aload_0 (0, 0)
	1 new (0, 0)
	4 dup (0, 0)
	5 iconst_0 (0, 0)
	6 invokespecial (0, 0)
	9 invokevirtual (0, 0)
	12 dreturn (0, 0)

Method: getStandardDeviation
	0 ldc2_w (0, 0)
	3 dstore_1 (0, 0)
	4 aload_0 (1, 1)
	5 invokevirtual (1, 1)
	8 lconst_0 (1, 1)
	9 lcmp (1, 1)
	10 ifle (1, 1)
	13 aload_0 (2, 1)
	14 invokevirtual (2, 1)
	17 lconst_1 (2, 1)
	18 lcmp (2, 1)
	19 ifle (2, 1)
	22 aload_0 (2, 1)
	23 invokevirtual (2, 1)
	26 invokestatic (2, 1)
	29 dstore_1 (2, 1)
	30 goto (2, 1)
	33 dconst_0 (2, 2)
	34 dstore_1 (2, 2)
	35 dload_1 (0, 1)
	36 dreturn (0, 1)

Method: getQuadraticMean
	0 aload_0 (0, 0)
	1 invokevirtual (0, 0)
	4 lstore_1 (0, 0)
	5 lload_1 (0, 0)
	6 lconst_0 (0, 0)
	7 lcmp (0, 0)
	8 ifle (0, 0)
	11 aload_0 (0, 0)
	12 invokevirtual (0, 0)
	15 lload_1 (0, 0)
	16 l2d (0, 0)
	17 ddiv (0, 0)
	18 invokestatic (0, 0)
	21 goto (0, 0)
	24 ldc2_w (0, 0)
	27 dreturn (0, 0)

Method: getSkewness
	0 aload_0 (0, 0)
	1 aload_0 (0, 0)
	2 getfield (0, 0)
	5 invokevirtual (0, 0)
	8 dreturn (0, 0)

Method: getKurtosis
	0 aload_0 (0, 0)
	1 aload_0 (0, 0)
	2 getfield (0, 0)
	5 invokevirtual (0, 0)
	8 dreturn (0, 0)

Method: getMax
	0 aload_0 (0, 0)
	1 aload_0 (0, 0)
	2 getfield (0, 0)
	5 invokevirtual (0, 0)
	8 dreturn (0, 0)

Method: getMin
	0 aload_0 (0, 0)
	1 aload_0 (0, 0)
	2 getfield (0, 0)
	5 invokevirtual (0, 0)
	8 dreturn (0, 0)

Method: getN
	0 aload_0 (0, 0)
	1 getfield (0, 0)
	4 invokevirtual (0, 0)
	7 i2l (0, 0)
	8 lreturn (0, 0)

Method: getSum
	0 aload_0 (0, 0)
	1 aload_0 (0, 0)
	2 getfield (0, 0)
	5 invokevirtual (0, 0)
	8 dreturn (0, 0)

Method: getSumsq
	0 aload_0 (0, 0)
	1 aload_0 (0, 0)
	2 getfield (0, 0)
	5 invokevirtual (0, 0)
	8 dreturn (0, 0)

Method: clear
	0 aload_0 (0, 0)
	1 getfield (0, 0)
	4 invokevirtual (0, 0)
	7 return (0, 0)

Method: getWindowSize
	0 aload_0 (0, 0)
	1 getfield (0, 0)
	4 ireturn (0, 0)

Method: setWindowSize
	0 iload_1 (1, 1)
	1 iconst_1 (1, 1)
	2 if_icmpge (1, 1)
	5 iload_1 (1, 1)
	6 iconst_m1 (1, 1)
	7 if_icmpeq (1, 1)
	10 new (1, 1)
	13 dup (1, 1)
	14 getstatic (1, 1)
	17 iconst_1 (1, 1)
	18 anewarray (1, 1)
	21 dup (1, 1)
	22 iconst_0 (1, 1)
	23 iload_1 (1, 1)
	24 invokestatic (1, 1)
	27 aastore (1, 1)
	28 invokespecial (1, 1)
	31 athrow (1, 1)
	32 aload_0 (0, 0)
	33 iload_1 (0, 0)
	34 putfield (0, 0)
	37 iload_1 (1, 1)
	38 iconst_m1 (1, 1)
	39 if_icmpeq (1, 1)
	42 iload_1 (1, 1)
	43 aload_0 (1, 1)
	44 getfield (1, 1)
	47 invokevirtual (1, 1)
	50 if_icmpge (1, 1)
	53 aload_0 (1, 1)
	54 getfield (1, 1)
	57 aload_0 (1, 1)
	58 getfield (1, 1)
	61 invokevirtual (1, 1)
	64 iload_1 (1, 1)
	65 isub (1, 1)
	66 invokevirtual (1, 1)
	69 return (0, 0)

Method: getValues
	0 aload_0 (0, 0)
	1 getfield (0, 0)
	4 invokevirtual (0, 0)
	7 areturn (0, 0)

Method: getSortedValues
	0 aload_0 (0, 0)
	1 invokevirtual (0, 0)
	4 astore_1 (0, 0)
	5 aload_1 (0, 0)
	6 invokestatic (0, 0)
	9 aload_1 (0, 0)
	10 areturn (0, 0)

Method: getElement
	0 aload_0 (0, 0)
	1 getfield (0, 0)
	4 iload_1 (0, 0)
	5 invokevirtual (0, 0)
	8 dreturn (0, 0)

Method: getPercentile
	0 aload_0 (1, 1)
	1 getfield (1, 1)
	4 instanceof (1, 1)
	7 ifeq (1, 1)
	10 aload_0 (1, 1)
	11 getfield (1, 1)
	14 checkcast (1, 1)
	17 dload_1 (1, 1)
	18 invokevirtual (1, 1)
	21 goto (1, 1)
	24 aload_0 (2, 2)
	25 getfield (2, 2)
	28 invokevirtual (2, 2)
	31 ldc (2, 2)
	33 iconst_1 (2, 2)
	34 anewarray (2, 2)
	37 dup (2, 2)
	38 iconst_0 (2, 2)
	39 getstatic (2, 2)
	42 aastore (2, 2)
	43 invokevirtual (2, 2)
	46 aload_0 (2, 2)
	47 getfield (2, 2)
	50 iconst_1 (2, 2)
	51 anewarray (2, 2)
	54 dup (2, 2)
	55 iconst_0 (2, 2)
	56 dload_1 (2, 2)
	57 invokestatic (2, 2)
	60 aastore (2, 2)
	61 invokevirtual (2, 2)
	64 pop (2, 2)
	65 goto (1, 1)
	68 astore_3 (1, 1)
	69 new (1, 1)
	72 dup (1, 1)
	73 getstatic (1, 1)
	76 iconst_2 (1, 1)
	77 anewarray (1, 1)
	80 dup (1, 1)
	81 iconst_0 (1, 1)
	82 aload_0 (1, 1)
	83 getfield (1, 1)
	86 invokevirtual (1, 1)
	89 invokevirtual (1, 1)
	92 aastore (1, 1)
	93 dup (1, 1)
	94 iconst_1 (1, 1)
	95 ldc (1, 1)
	97 aastore (1, 1)
	98 invokespecial (1, 1)
	101 athrow (1, 1)
	102 astore_3 (1, 1)
	103 new (1, 1)
	106 dup (1, 1)
	107 getstatic (1, 1)
	110 iconst_2 (1, 1)
	111 anewarray (1, 1)
	114 dup (1, 1)
	115 iconst_0 (1, 1)
	116 ldc (1, 1)
	118 aastore (1, 1)
	119 dup (1, 1)
	120 iconst_1 (1, 1)
	121 aload_0 (1, 1)
	122 getfield (1, 1)
	125 invokevirtual (1, 1)
	128 invokevirtual (1, 1)
	131 aastore (1, 1)
	132 invokespecial (1, 1)
	135 athrow (1, 1)
	136 astore_3 (1, 1)
	137 new (1, 1)
	140 dup (1, 1)
	141 aload_3 (1, 1)
	142 invokevirtual (1, 1)
	145 invokespecial (1, 1)
	148 athrow (1, 1)
	149 aload_0 (0, 0)
	150 aload_0 (0, 0)
	151 getfield (0, 0)
	154 invokevirtual (0, 0)
	157 dreturn (0, 0)

Method: toString
	0 new (0, 0)
	3 dup (0, 0)
	4 invokespecial (0, 0)
	7 astore_1 (0, 0)
	8 ldc (0, 0)
	10 astore_2 (0, 0)
	11 aload_1 (0, 0)
	12 ldc (0, 0)
	14 invokevirtual (0, 0)
	17 aload_2 (0, 0)
	18 invokevirtual (0, 0)
	21 pop (0, 0)
	22 aload_1 (0, 0)
	23 ldc (0, 0)
	25 invokevirtual (0, 0)
	28 aload_0 (0, 0)
	29 invokevirtual (0, 0)
	32 invokevirtual (0, 0)
	35 aload_2 (0, 0)
	36 invokevirtual (0, 0)
	39 pop (0, 0)
	40 aload_1 (0, 0)
	41 ldc (0, 0)
	43 invokevirtual (0, 0)
	46 aload_0 (0, 0)
	47 invokevirtual (0, 0)
	50 invokevirtual (0, 0)
	53 aload_2 (0, 0)
	54 invokevirtual (0, 0)
	57 pop (0, 0)
	58 aload_1 (0, 0)
	59 ldc (0, 0)
	61 invokevirtual (0, 0)
	64 aload_0 (0, 0)
	65 invokevirtual (0, 0)
	68 invokevirtual (0, 0)
	71 aload_2 (0, 0)
	72 invokevirtual (0, 0)
	75 pop (0, 0)
	76 aload_1 (0, 0)
	77 ldc (0, 0)
	79 invokevirtual (0, 0)
	82 aload_0 (0, 0)
	83 invokevirtual (0, 0)
	86 invokevirtual (0, 0)
	89 aload_2 (0, 0)
	90 invokevirtual (0, 0)
	93 pop (0, 0)
	94 aload_1 (0, 0)
	95 ldc (0, 0)
	97 invokevirtual (0, 0)
	100 aload_0 (0, 0)
	101 invokevirtual (0, 0)
	104 invokevirtual (0, 0)
	107 aload_2 (0, 0)
	108 invokevirtual (0, 0)
	111 pop (0, 0)
	112 aload_1 (0, 4)
	113 ldc (0, 4)
	115 invokevirtual (0, 4)
	118 aload_0 (0, 4)
	119 ldc2_w (0, 4)
	122 invokevirtual (0, 4)
	125 invokevirtual (0, 4)
	128 aload_2 (0, 4)
	129 invokevirtual (0, 4)
	132 pop (0, 4)
	133 goto (-1, 0)
	136 astore_3 (-1, 0)
	137 aload_1 (-1, 0)
	138 ldc (-1, 0)
	140 invokevirtual (-1, 0)
	143 aload_2 (-1, 0)
	144 invokevirtual (-1, 0)
	147 pop (-1, 0)
	148 aload_1 (-1, 0)
	149 ldc (-1, 0)
	151 invokevirtual (-1, 0)
	154 aload_0 (-1, 0)
	155 invokevirtual (-1, 0)
	158 invokevirtual (-1, 0)
	161 aload_2 (-1, 0)
	162 invokevirtual (-1, 0)
	165 pop (-1, 0)
	166 aload_1 (-1, 0)
	167 ldc (-1, 0)
	169 invokevirtual (-1, 0)
	172 aload_0 (-1, 0)
	173 invokevirtual (-1, 0)
	176 invokevirtual (-1, 0)
	179 aload_2 (-1, 0)
	180 invokevirtual (-1, 0)
	183 pop (-1, 0)
	184 aload_1 (-1, 0)
	185 invokevirtual (-1, 0)
	188 areturn (0, 0)

Method: apply
	0 aload_0 (0, 0)
	1 getfield (0, 0)
	4 aload_1 (0, 0)
	5 invokevirtual (0, 0)
	8 dreturn (0, 0)

Method: getMeanImpl
	0 aload_0 (0, 0)
	1 getfield (0, 0)
	4 areturn (0, 0)

Method: setMeanImpl
	0 aload_0 (0, 0)
	1 aload_1 (0, 0)
	2 putfield (0, 0)
	5 return (0, 0)

Method: getGeometricMeanImpl
	0 aload_0 (0, 0)
	1 getfield (0, 0)
	4 areturn (0, 0)

Method: setGeometricMeanImpl
	0 aload_0 (0, 0)
	1 aload_1 (0, 0)
	2 putfield (0, 0)
	5 return (0, 0)

Method: getKurtosisImpl
	0 aload_0 (0, 0)
	1 getfield (0, 0)
	4 areturn (0, 0)

Method: setKurtosisImpl
	0 aload_0 (0, 0)
	1 aload_1 (0, 0)
	2 putfield (0, 0)
	5 return (0, 0)

Method: getMaxImpl
	0 aload_0 (0, 0)
	1 getfield (0, 0)
	4 areturn (0, 0)

Method: setMaxImpl
	0 aload_0 (0, 0)
	1 aload_1 (0, 0)
	2 putfield (0, 0)
	5 return (0, 0)

Method: getMinImpl
	0 aload_0 (0, 0)
	1 getfield (0, 0)
	4 areturn (0, 0)

Method: setMinImpl
	0 aload_0 (0, 0)
	1 aload_1 (0, 0)
	2 putfield (0, 0)
	5 return (0, 0)

Method: getPercentileImpl
	0 aload_0 (0, 0)
	1 getfield (0, 0)
	4 areturn (0, 0)

Method: setPercentileImpl
	0 aload_1 (0, 0)
	1 invokevirtual (0, 0)
	4 ldc (0, 0)
	6 iconst_1 (0, 0)
	7 anewarray (0, 0)
	10 dup (0, 0)
	11 iconst_0 (0, 0)
	12 getstatic (0, 0)
	15 aastore (0, 0)
	16 invokevirtual (0, 0)
	19 aload_1 (0, 0)
	20 iconst_1 (0, 0)
	21 anewarray (0, 0)
	24 dup (0, 0)
	25 iconst_0 (0, 0)
	26 ldc2_w (0, 0)
	29 invokestatic (0, 0)
	32 aastore (0, 0)
	33 invokevirtual (0, 0)
	36 pop (0, 0)
	37 goto (0, 0)
	40 astore_2 (0, 0)
	41 new (0, 0)
	44 dup (0, 0)
	45 getstatic (0, 0)
	48 iconst_2 (0, 0)
	49 anewarray (0, 0)
	52 dup (0, 0)
	53 iconst_0 (0, 0)
	54 aload_1 (0, 0)
	55 invokevirtual (0, 0)
	58 invokevirtual (0, 0)
	61 aastore (0, 0)
	62 dup (0, 0)
	63 iconst_1 (0, 0)
	64 ldc (0, 0)
	66 aastore (0, 0)
	67 invokespecial (0, 0)
	70 athrow (0, 0)
	71 astore_2 (0, 0)
	72 new (0, 0)
	75 dup (0, 0)
	76 getstatic (0, 0)
	79 iconst_2 (0, 0)
	80 anewarray (0, 0)
	83 dup (0, 0)
	84 iconst_0 (0, 0)
	85 ldc (0, 0)
	87 aastore (0, 0)
	88 dup (0, 0)
	89 iconst_1 (0, 0)
	90 aload_1 (0, 0)
	91 invokevirtual (0, 0)
	94 invokevirtual (0, 0)
	97 aastore (0, 0)
	98 invokespecial (0, 0)
	101 athrow (0, 0)
	102 astore_2 (0, 0)
	103 new (0, 0)
	106 dup (0, 0)
	107 aload_2 (0, 0)
	108 invokevirtual (0, 0)
	111 invokespecial (0, 0)
	114 athrow (0, 0)
	115 aload_0 (0, 0)
	116 aload_1 (0, 0)
	117 putfield (0, 0)
	120 return (0, 0)

Method: getSkewnessImpl
	0 aload_0 (0, 0)
	1 getfield (0, 0)
	4 areturn (0, 0)

Method: setSkewnessImpl
	0 aload_0 (0, 0)
	1 aload_1 (0, 0)
	2 putfield (0, 0)
	5 return (0, 0)

Method: getVarianceImpl
	0 aload_0 (0, 0)
	1 getfield (0, 0)
	4 areturn (0, 0)

Method: setVarianceImpl
	0 aload_0 (0, 0)
	1 aload_1 (0, 0)
	2 putfield (0, 0)
	5 return (0, 0)

Method: getSumsqImpl
	0 aload_0 (0, 0)
	1 getfield (0, 0)
	4 areturn (0, 0)

Method: setSumsqImpl
	0 aload_0 (0, 0)
	1 aload_1 (0, 0)
	2 putfield (0, 0)
	5 return (0, 0)

Method: getSumImpl
	0 aload_0 (0, 0)
	1 getfield (0, 0)
	4 areturn (0, 0)

Method: setSumImpl
	0 aload_0 (0, 0)
	1 aload_1 (0, 0)
	2 putfield (0, 0)
	5 return (0, 0)

Method: copy
	0 aload_0 (0, 0)
	1 invokestatic (0, 0)
	4 aload_1 (0, 0)
	5 invokestatic (0, 0)
	8 aload_1 (0, 0)
	9 aload_0 (0, 0)
	10 getfield (0, 0)
	13 invokevirtual (0, 0)
	16 putfield (0, 0)
	19 aload_1 (0, 0)
	20 aload_0 (0, 0)
	21 getfield (0, 0)
	24 putfield (0, 0)
	27 aload_1 (0, 0)
	28 aload_0 (0, 0)
	29 getfield (0, 0)
	32 invokeinterface (0, 0)
	37 putfield (0, 0)
	40 aload_1 (0, 0)
	41 aload_0 (0, 0)
	42 getfield (0, 0)
	45 invokeinterface (0, 0)
	50 putfield (0, 0)
	53 aload_1 (0, 0)
	54 aload_0 (0, 0)
	55 getfield (0, 0)
	58 invokeinterface (0, 0)
	63 putfield (0, 0)
	66 aload_1 (0, 0)
	67 aload_0 (0, 0)
	68 getfield (0, 0)
	71 invokeinterface (0, 0)
	76 putfield (0, 0)
	79 aload_1 (0, 0)
	80 aload_0 (0, 0)
	81 getfield (0, 0)
	84 invokeinterface (0, 0)
	89 putfield (0, 0)
	92 aload_1 (0, 0)
	93 aload_0 (0, 0)
	94 getfield (0, 0)
	97 invokeinterface (0, 0)
	102 putfield (0, 0)
	105 aload_1 (0, 0)
	106 aload_0 (0, 0)
	107 getfield (0, 0)
	110 invokeinterface (0, 0)
	115 putfield (0, 0)
	118 aload_1 (0, 0)
	119 aload_0 (0, 0)
	120 getfield (0, 0)
	123 putfield (0, 0)
	126 aload_1 (0, 0)
	127 aload_0 (0, 0)
	128 getfield (0, 0)
	131 putfield (0, 0)
	134 aload_1 (0, 0)
	135 aload_0 (0, 0)
	136 getfield (0, 0)
	139 putfield (0, 0)
	142 return (0, 0)

