Method: <init>
	0 aload_0 (0, 0)
	1 invokespecial (0, 0)
	2 java/lang/Object.<init>:()V (0, 0)
	4 aload_0 (0, 0)
	5 dload_1 (0, 0)
	6 putfield (0, 0)
	7 org/apache/commons/math3/stat/descriptive/StatisticalSummaryValues.mean:D (0, 0)
	9 aload_0 (0, 0)
	10 dload_3 (0, 0)
	11 putfield (0, 0)
	12 org/apache/commons/math3/stat/descriptive/StatisticalSummaryValues.variance:D (0, 0)
	14 aload_0 (0, 0)
	15 lload (0, 0)
	16 #5 (0, 0)
	17 putfield (0, 0)
	18 org/apache/commons/math3/stat/descriptive/StatisticalSummaryValues.n:J (0, 0)
	20 aload_0 (0, 0)
	21 dload (0, 0)
	22 #7 (0, 0)
	23 putfield (0, 0)
	24 org/apache/commons/math3/stat/descriptive/StatisticalSummaryValues.max:D (0, 0)
	26 aload_0 (0, 0)
	27 dload (0, 0)
	28 #9 (0, 0)
	29 putfield (0, 0)
	30 org/apache/commons/math3/stat/descriptive/StatisticalSummaryValues.min:D (0, 0)
	32 aload_0 (0, 0)
	33 dload (0, 0)
	34 #11 (0, 0)
	35 putfield (0, 0)
	36 org/apache/commons/math3/stat/descriptive/StatisticalSummaryValues.sum:D (0, 0)
	38 return (0, 0)

Method: getMax
	0 aload_0 (0, 0)
	1 getfield (0, 0)
	2 org/apache/commons/math3/stat/descriptive/StatisticalSummaryValues.max:D (0, 0)
	4 dreturn (0, 0)

Method: getMean
	0 aload_0 (0, 0)
	1 getfield (0, 0)
	2 org/apache/commons/math3/stat/descriptive/StatisticalSummaryValues.mean:D (0, 0)
	4 dreturn (0, 0)

Method: getMin
	0 aload_0 (0, 0)
	1 getfield (0, 0)
	2 org/apache/commons/math3/stat/descriptive/StatisticalSummaryValues.min:D (0, 0)
	4 dreturn (0, 0)

Method: getN
	0 aload_0 (0, 0)
	1 getfield (0, 0)
	2 org/apache/commons/math3/stat/descriptive/StatisticalSummaryValues.n:J (0, 0)
	4 lreturn (0, 0)

Method: getSum
	0 aload_0 (0, 0)
	1 getfield (0, 0)
	2 org/apache/commons/math3/stat/descriptive/StatisticalSummaryValues.sum:D (0, 0)
	4 dreturn (0, 0)

Method: getStandardDeviation
	0 aload_0 (0, 0)
	1 getfield (0, 0)
	2 org/apache/commons/math3/stat/descriptive/StatisticalSummaryValues.variance:D (0, 0)
	4 invokestatic (0, 0)
	5 org/apache/commons/math3/util/FastMath.sqrt:(D)D (0, 0)
	7 dreturn (0, 0)

Method: getVariance
	0 aload_0 (0, 0)
	1 getfield (0, 0)
	2 org/apache/commons/math3/stat/descriptive/StatisticalSummaryValues.variance:D (0, 0)
	4 dreturn (0, 0)

Method: equals
	0 aload_1 (1, 1)
	1 aload_0 (1, 1)
	2 if_acmpne (1, 1)
	3 5 (1, 1)
	5 iconst_1 (1, 1)
	6 ireturn (1, 1)
	7 aload_1 (1, 1)
	8 instanceof (1, 1)
	9 org/apache/commons/math3/stat/descriptive/StatisticalSummaryValues (1, 1)
	11 ifne (1, 1)
	12 5 (1, 1)
	14 iconst_0 (1, 1)
	15 ireturn (1, 1)
	16 aload_1 (0, 0)
	17 checkcast (0, 0)
	18 org/apache/commons/math3/stat/descriptive/StatisticalSummaryValues (0, 0)
	20 astore_2 (0, 0)
	21 aload_2 (0, 0)
	22 invokevirtual (0, 0)
	23 org/apache/commons/math3/stat/descriptive/StatisticalSummaryValues.getMax:()D (0, 0)
	25 aload_0 (0, 0)
	26 invokevirtual (0, 0)
	27 org/apache/commons/math3/stat/descriptive/StatisticalSummaryValues.getMax:()D (0, 0)
	29 invokestatic (0, 0)
	30 org/apache/commons/math3/util/Precision.equalsIncludingNaN:(DD)Z (0, 0)
	32 ifeq (0, 0)
	33 79 (0, 0)
	35 aload_2 (0, 0)
	36 invokevirtual (0, 0)
	37 org/apache/commons/math3/stat/descriptive/StatisticalSummaryValues.getMean:()D (0, 0)
	39 aload_0 (0, 0)
	40 invokevirtual (0, 0)
	41 org/apache/commons/math3/stat/descriptive/StatisticalSummaryValues.getMean:()D (0, 0)
	43 invokestatic (0, 0)
	44 org/apache/commons/math3/util/Precision.equalsIncludingNaN:(DD)Z (0, 0)
	46 ifeq (0, 0)
	47 65 (0, 0)
	49 aload_2 (0, 0)
	50 invokevirtual (0, 0)
	51 org/apache/commons/math3/stat/descriptive/StatisticalSummaryValues.getMin:()D (0, 0)
	53 aload_0 (0, 0)
	54 invokevirtual (0, 0)
	55 org/apache/commons/math3/stat/descriptive/StatisticalSummaryValues.getMin:()D (0, 0)
	57 invokestatic (0, 0)
	58 org/apache/commons/math3/util/Precision.equalsIncludingNaN:(DD)Z (0, 0)
	60 ifeq (0, 0)
	61 51 (0, 0)
	63 aload_2 (0, 0)
	64 invokevirtual (0, 0)
	65 org/apache/commons/math3/stat/descriptive/StatisticalSummaryValues.getN:()J (0, 0)
	67 l2f (0, 0)
	68 aload_0 (0, 0)
	69 invokevirtual (0, 0)
	70 org/apache/commons/math3/stat/descriptive/StatisticalSummaryValues.getN:()J (0, 0)
	72 l2f (0, 0)
	73 invokestatic (0, 0)
	74 org/apache/commons/math3/util/Precision.equalsIncludingNaN:(FF)Z (0, 0)
	76 ifeq (0, 0)
	77 35 (0, 0)
	79 aload_2 (0, 0)
	80 invokevirtual (0, 0)
	81 org/apache/commons/math3/stat/descriptive/StatisticalSummaryValues.getSum:()D (0, 0)
	83 aload_0 (0, 0)
	84 invokevirtual (0, 0)
	85 org/apache/commons/math3/stat/descriptive/StatisticalSummaryValues.getSum:()D (0, 0)
	87 invokestatic (0, 0)
	88 org/apache/commons/math3/util/Precision.equalsIncludingNaN:(DD)Z (0, 0)
	90 ifeq (0, 0)
	91 21 (0, 0)
	93 aload_2 (0, 0)
	94 invokevirtual (0, 0)
	95 org/apache/commons/math3/stat/descriptive/StatisticalSummaryValues.getVariance:()D (0, 0)
	97 aload_0 (0, 0)
	98 invokevirtual (0, 0)
	99 org/apache/commons/math3/stat/descriptive/StatisticalSummaryValues.getVariance:()D (0, 0)
	101 invokestatic (0, 0)
	102 org/apache/commons/math3/util/Precision.equalsIncludingNaN:(DD)Z (0, 0)
	104 ifeq (0, 0)
	105 7 (0, 0)
	107 iconst_1 (0, 0)
	108 goto (0, 0)
	109 4 (0, 0)
	111 iconst_0 (0, 0)
	112 ireturn (0, 0)

Method: hashCode
	0 bipush (0, 0)
	1 31 (0, 0)
	2 aload_0 (0, 0)
	3 invokevirtual (0, 0)
	4 org/apache/commons/math3/stat/descriptive/StatisticalSummaryValues.getMax:()D (0, 0)
	6 invokestatic (0, 0)
	7 org/apache/commons/math3/util/MathUtils.hash:(D)I (0, 0)
	9 iadd (0, 0)
	10 istore_1 (0, 0)
	11 iload_1 (0, 0)
	12 bipush (0, 0)
	13 31 (0, 0)
	14 imul (0, 0)
	15 aload_0 (0, 0)
	16 invokevirtual (0, 0)
	17 org/apache/commons/math3/stat/descriptive/StatisticalSummaryValues.getMean:()D (0, 0)
	19 invokestatic (0, 0)
	20 org/apache/commons/math3/util/MathUtils.hash:(D)I (0, 0)
	22 iadd (0, 0)
	23 istore_1 (0, 0)
	24 iload_1 (0, 0)
	25 bipush (0, 0)
	26 31 (0, 0)
	27 imul (0, 0)
	28 aload_0 (0, 0)
	29 invokevirtual (0, 0)
	30 org/apache/commons/math3/stat/descriptive/StatisticalSummaryValues.getMin:()D (0, 0)
	32 invokestatic (0, 0)
	33 org/apache/commons/math3/util/MathUtils.hash:(D)I (0, 0)
	35 iadd (0, 0)
	36 istore_1 (0, 0)
	37 iload_1 (0, 0)
	38 bipush (0, 0)
	39 31 (0, 0)
	40 imul (0, 0)
	41 aload_0 (0, 0)
	42 invokevirtual (0, 0)
	43 org/apache/commons/math3/stat/descriptive/StatisticalSummaryValues.getN:()J (0, 0)
	45 l2d (0, 0)
	46 invokestatic (0, 0)
	47 org/apache/commons/math3/util/MathUtils.hash:(D)I (0, 0)
	49 iadd (0, 0)
	50 istore_1 (0, 0)
	51 iload_1 (0, 0)
	52 bipush (0, 0)
	53 31 (0, 0)
	54 imul (0, 0)
	55 aload_0 (0, 0)
	56 invokevirtual (0, 0)
	57 org/apache/commons/math3/stat/descriptive/StatisticalSummaryValues.getSum:()D (0, 0)
	59 invokestatic (0, 0)
	60 org/apache/commons/math3/util/MathUtils.hash:(D)I (0, 0)
	62 iadd (0, 0)
	63 istore_1 (0, 0)
	64 iload_1 (0, 0)
	65 bipush (0, 0)
	66 31 (0, 0)
	67 imul (0, 0)
	68 aload_0 (0, 0)
	69 invokevirtual (0, 0)
	70 org/apache/commons/math3/stat/descriptive/StatisticalSummaryValues.getVariance:()D (0, 0)
	72 invokestatic (0, 0)
	73 org/apache/commons/math3/util/MathUtils.hash:(D)I (0, 0)
	75 iadd (0, 0)
	76 istore_1 (0, 0)
	77 iload_1 (0, 0)
	78 ireturn (0, 0)

Method: toString
	0 new (0, 0)
	1 java/lang/StringBuffer (0, 0)
	3 dup (0, 0)
	4 invokespecial (0, 0)
	5 java/lang/StringBuffer.<init>:()V (0, 0)
	7 astore_1 (0, 0)
	8 ldc (0, 0)
	9 
 (0, 0)
	10 astore_2 (0, 0)
	11 aload_1 (0, 0)
	12 ldc (0, 0)
	13 StatisticalSummaryValues: (0, 0)
	14 invokevirtual (0, 0)
	15 java/lang/StringBuffer.append:(Ljava/lang/String;)Ljava/lang/StringBuffer; (0, 0)
	17 aload_2 (0, 0)
	18 invokevirtual (0, 0)
	19 java/lang/StringBuffer.append:(Ljava/lang/String;)Ljava/lang/StringBuffer; (0, 0)
	21 pop (0, 0)
	22 aload_1 (0, 0)
	23 ldc (0, 0)
	24 n:  (0, 0)
	25 invokevirtual (0, 0)
	26 java/lang/StringBuffer.append:(Ljava/lang/String;)Ljava/lang/StringBuffer; (0, 0)
	28 aload_0 (0, 0)
	29 invokevirtual (0, 0)
	30 org/apache/commons/math3/stat/descriptive/StatisticalSummaryValues.getN:()J (0, 0)
	32 invokevirtual (0, 0)
	33 java/lang/StringBuffer.append:(J)Ljava/lang/StringBuffer; (0, 0)
	35 aload_2 (0, 0)
	36 invokevirtual (0, 0)
	37 java/lang/StringBuffer.append:(Ljava/lang/String;)Ljava/lang/StringBuffer; (0, 0)
	39 pop (0, 0)
	40 aload_1 (0, 0)
	41 ldc (0, 0)
	42 min:  (0, 0)
	43 invokevirtual (0, 0)
	44 java/lang/StringBuffer.append:(Ljava/lang/String;)Ljava/lang/StringBuffer; (0, 0)
	46 aload_0 (0, 0)
	47 invokevirtual (0, 0)
	48 org/apache/commons/math3/stat/descriptive/StatisticalSummaryValues.getMin:()D (0, 0)
	50 invokevirtual (0, 0)
	51 java/lang/StringBuffer.append:(D)Ljava/lang/StringBuffer; (0, 0)
	53 aload_2 (0, 0)
	54 invokevirtual (0, 0)
	55 java/lang/StringBuffer.append:(Ljava/lang/String;)Ljava/lang/StringBuffer; (0, 0)
	57 pop (0, 0)
	58 aload_1 (0, 0)
	59 ldc (0, 0)
	60 max:  (0, 0)
	61 invokevirtual (0, 0)
	62 java/lang/StringBuffer.append:(Ljava/lang/String;)Ljava/lang/StringBuffer; (0, 0)
	64 aload_0 (0, 0)
	65 invokevirtual (0, 0)
	66 org/apache/commons/math3/stat/descriptive/StatisticalSummaryValues.getMax:()D (0, 0)
	68 invokevirtual (0, 0)
	69 java/lang/StringBuffer.append:(D)Ljava/lang/StringBuffer; (0, 0)
	71 aload_2 (0, 0)
	72 invokevirtual (0, 0)
	73 java/lang/StringBuffer.append:(Ljava/lang/String;)Ljava/lang/StringBuffer; (0, 0)
	75 pop (0, 0)
	76 aload_1 (0, 0)
	77 ldc (0, 0)
	78 mean:  (0, 0)
	79 invokevirtual (0, 0)
	80 java/lang/StringBuffer.append:(Ljava/lang/String;)Ljava/lang/StringBuffer; (0, 0)
	82 aload_0 (0, 0)
	83 invokevirtual (0, 0)
	84 org/apache/commons/math3/stat/descriptive/StatisticalSummaryValues.getMean:()D (0, 0)
	86 invokevirtual (0, 0)
	87 java/lang/StringBuffer.append:(D)Ljava/lang/StringBuffer; (0, 0)
	89 aload_2 (0, 0)
	90 invokevirtual (0, 0)
	91 java/lang/StringBuffer.append:(Ljava/lang/String;)Ljava/lang/StringBuffer; (0, 0)
	93 pop (0, 0)
	94 aload_1 (0, 0)
	95 ldc (0, 0)
	96 std dev:  (0, 0)
	97 invokevirtual (0, 0)
	98 java/lang/StringBuffer.append:(Ljava/lang/String;)Ljava/lang/StringBuffer; (0, 0)
	100 aload_0 (0, 0)
	101 invokevirtual (0, 0)
	102 org/apache/commons/math3/stat/descriptive/StatisticalSummaryValues.getStandardDeviation:()D (0, 0)
	104 invokevirtual (0, 0)
	105 java/lang/StringBuffer.append:(D)Ljava/lang/StringBuffer; (0, 0)
	107 aload_2 (0, 0)
	108 invokevirtual (0, 0)
	109 java/lang/StringBuffer.append:(Ljava/lang/String;)Ljava/lang/StringBuffer; (0, 0)
	111 pop (0, 0)
	112 aload_1 (0, 0)
	113 ldc (0, 0)
	114 variance:  (0, 0)
	115 invokevirtual (0, 0)
	116 java/lang/StringBuffer.append:(Ljava/lang/String;)Ljava/lang/StringBuffer; (0, 0)
	118 aload_0 (0, 0)
	119 invokevirtual (0, 0)
	120 org/apache/commons/math3/stat/descriptive/StatisticalSummaryValues.getVariance:()D (0, 0)
	122 invokevirtual (0, 0)
	123 java/lang/StringBuffer.append:(D)Ljava/lang/StringBuffer; (0, 0)
	125 aload_2 (0, 0)
	126 invokevirtual (0, 0)
	127 java/lang/StringBuffer.append:(Ljava/lang/String;)Ljava/lang/StringBuffer; (0, 0)
	129 pop (0, 0)
	130 aload_1 (0, 0)
	131 ldc (0, 0)
	132 sum:  (0, 0)
	133 invokevirtual (0, 0)
	134 java/lang/StringBuffer.append:(Ljava/lang/String;)Ljava/lang/StringBuffer; (0, 0)
	136 aload_0 (0, 0)
	137 invokevirtual (0, 0)
	138 org/apache/commons/math3/stat/descriptive/StatisticalSummaryValues.getSum:()D (0, 0)
	140 invokevirtual (0, 0)
	141 java/lang/StringBuffer.append:(D)Ljava/lang/StringBuffer; (0, 0)
	143 aload_2 (0, 0)
	144 invokevirtual (0, 0)
	145 java/lang/StringBuffer.append:(Ljava/lang/String;)Ljava/lang/StringBuffer; (0, 0)
	147 pop (0, 0)
	148 aload_1 (0, 0)
	149 invokevirtual (0, 0)
	150 java/lang/StringBuffer.toString:()Ljava/lang/String; (0, 0)
	152 areturn (0, 0)

