Method: <init>
	0 aload_0 (0, 0)
	1 invokespecial (0, 0)
	4 aload_0 (0, 0)
	5 lconst_0 (0, 0)
	6 putfield (0, 0)
	9 aload_0 (0, 0)
	10 new (0, 0)
	13 dup (0, 0)
	14 invokespecial (0, 0)
	17 putfield (0, 0)
	20 aload_0 (0, 0)
	21 new (0, 0)
	24 dup (0, 0)
	25 invokespecial (0, 0)
	28 putfield (0, 0)
	31 aload_0 (0, 0)
	32 new (0, 0)
	35 dup (0, 0)
	36 invokespecial (0, 0)
	39 putfield (0, 0)
	42 aload_0 (0, 0)
	43 new (0, 0)
	46 dup (0, 0)
	47 invokespecial (0, 0)
	50 putfield (0, 0)
	53 aload_0 (0, 0)
	54 new (0, 0)
	57 dup (0, 0)
	58 invokespecial (0, 0)
	61 putfield (0, 0)
	64 aload_0 (0, 0)
	65 new (0, 0)
	68 dup (0, 0)
	69 invokespecial (0, 0)
	72 putfield (0, 0)
	75 aload_0 (0, 0)
	76 new (0, 0)
	79 dup (0, 0)
	80 aload_0 (0, 0)
	81 getfield (0, 0)
	84 invokespecial (0, 0)
	87 putfield (0, 0)
	90 aload_0 (0, 0)
	91 new (0, 0)
	94 dup (0, 0)
	95 aload_0 (0, 0)
	96 getfield (0, 0)
	99 invokespecial (0, 0)
	102 putfield (0, 0)
	105 aload_0 (0, 0)
	106 new (0, 0)
	109 dup (0, 0)
	110 aload_0 (0, 0)
	111 getfield (0, 0)
	114 invokespecial (0, 0)
	117 putfield (0, 0)
	120 aload_0 (0, 0)
	121 aload_0 (0, 0)
	122 getfield (0, 0)
	125 putfield (0, 0)
	128 aload_0 (0, 0)
	129 aload_0 (0, 0)
	130 getfield (0, 0)
	133 putfield (0, 0)
	136 aload_0 (0, 0)
	137 aload_0 (0, 0)
	138 getfield (0, 0)
	141 putfield (0, 0)
	144 aload_0 (0, 0)
	145 aload_0 (0, 0)
	146 getfield (0, 0)
	149 putfield (0, 0)
	152 aload_0 (0, 0)
	153 aload_0 (0, 0)
	154 getfield (0, 0)
	157 putfield (0, 0)
	160 aload_0 (0, 0)
	161 aload_0 (0, 0)
	162 getfield (0, 0)
	165 putfield (0, 0)
	168 aload_0 (0, 0)
	169 aload_0 (0, 0)
	170 getfield (0, 0)
	173 putfield (0, 0)
	176 aload_0 (0, 0)
	177 aload_0 (0, 0)
	178 getfield (0, 0)
	181 putfield (0, 0)
	184 aload_1 (1, 1)
	185 aload_0 (1, 1)
	186 invokestatic (1, 1)
	189 return (0, 0)

Method: getSummary
	0 new (0, 0)
	3 dup (0, 0)
	4 aload_0 (0, 0)
	5 invokevirtual (0, 0)
	8 aload_0 (0, 0)
	9 invokevirtual (0, 0)
	12 aload_0 (0, 0)
	13 invokevirtual (0, 0)
	16 aload_0 (0, 0)
	17 invokevirtual (0, 0)
	20 aload_0 (0, 0)
	21 invokevirtual (0, 0)
	24 aload_0 (0, 0)
	25 invokevirtual (0, 0)
	28 invokespecial (0, 0)
	31 areturn (0, 0)

Method: addValue
	0 aload_0 (0, 0)
	1 getfield (0, 0)
	4 dload_1 (0, 0)
	5 invokeinterface (0, 0)
	10 aload_0 (0, 0)
	11 getfield (0, 0)
	14 dload_1 (0, 0)
	15 invokeinterface (0, 0)
	20 aload_0 (0, 0)
	21 getfield (0, 0)
	24 dload_1 (0, 0)
	25 invokeinterface (0, 0)
	30 aload_0 (0, 0)
	31 getfield (0, 0)
	34 dload_1 (0, 0)
	35 invokeinterface (0, 0)
	40 aload_0 (0, 0)
	41 getfield (0, 0)
	44 dload_1 (0, 0)
	45 invokeinterface (0, 0)
	50 aload_0 (0, 0)
	51 getfield (0, 0)
	54 dload_1 (0, 0)
	55 invokevirtual (0, 0)
	58 aload_0 (1, 1)
	59 getfield (1, 1)
	62 aload_0 (1, 1)
	63 getfield (1, 1)
	66 if_acmpeq (1, 1)
	69 aload_0 (1, 1)
	70 getfield (1, 1)
	73 dload_1 (1, 1)
	74 invokeinterface (1, 1)
	79 aload_0 (1, 1)
	80 getfield (1, 1)
	83 aload_0 (1, 1)
	84 getfield (1, 1)
	87 if_acmpeq (1, 1)
	90 aload_0 (1, 1)
	91 getfield (1, 1)
	94 dload_1 (1, 1)
	95 invokeinterface (1, 1)
	100 aload_0 (1, 1)
	101 getfield (1, 1)
	104 aload_0 (1, 1)
	105 getfield (1, 1)
	108 if_acmpeq (1, 1)
	111 aload_0 (1, 1)
	112 getfield (1, 1)
	115 dload_1 (1, 1)
	116 invokeinterface (1, 1)
	121 aload_0 (0, 0)
	122 dup (0, 0)
	123 getfield (0, 0)
	126 lconst_1 (0, 0)
	127 ladd (0, 0)
	128 putfield (0, 0)
	131 return (0, 0)

Method: getN
	0 aload_0 (0, 0)
	1 getfield (0, 0)
	4 lreturn (0, 0)

Method: getSum
	0 aload_0 (0, 0)
	1 getfield (0, 0)
	4 invokeinterface (0, 0)
	9 dreturn (0, 0)

Method: getSumsq
	0 aload_0 (0, 0)
	1 getfield (0, 0)
	4 invokeinterface (0, 0)
	9 dreturn (0, 0)

Method: getMean
	0 aload_0 (0, 0)
	1 getfield (0, 0)
	4 invokeinterface (0, 0)
	9 dreturn (0, 0)

Method: getStandardDeviation
	0 ldc2_w (0, 0)
	3 dstore_1 (0, 0)
	4 aload_0 (1, 1)
	5 invokevirtual (1, 1)
	8 lconst_0 (1, 1)
	9 lcmp (1, 1)
	10 ifle (1, 1)
	13 aload_0 (2, 1)
	14 invokevirtual (2, 1)
	17 lconst_1 (2, 1)
	18 lcmp (2, 1)
	19 ifle (2, 1)
	22 aload_0 (2, 1)
	23 invokevirtual (2, 1)
	26 invokestatic (2, 1)
	29 dstore_1 (2, 1)
	30 goto (2, 1)
	33 dconst_0 (2, 2)
	34 dstore_1 (2, 2)
	35 dload_1 (0, 1)
	36 dreturn (0, 1)

Method: getQuadraticMean
	0 aload_0 (0, 0)
	1 invokevirtual (0, 0)
	4 lstore_1 (0, 0)
	5 lload_1 (0, 0)
	6 lconst_0 (0, 0)
	7 lcmp (0, 0)
	8 ifle (0, 0)
	11 aload_0 (0, 0)
	12 invokevirtual (0, 0)
	15 lload_1 (0, 0)
	16 l2d (0, 0)
	17 ddiv (0, 0)
	18 invokestatic (0, 0)
	21 goto (0, 0)
	24 ldc2_w (0, 0)
	27 dreturn (0, 0)

Method: getVariance
	0 aload_0 (0, 0)
	1 getfield (0, 0)
	4 invokeinterface (0, 0)
	9 dreturn (0, 0)

Method: getPopulationVariance
	0 new (0, 0)
	3 dup (0, 0)
	4 aload_0 (0, 0)
	5 getfield (0, 0)
	8 invokespecial (0, 0)
	11 astore_1 (0, 0)
	12 aload_1 (0, 0)
	13 iconst_0 (0, 0)
	14 invokevirtual (0, 0)
	17 aload_1 (0, 0)
	18 invokevirtual (0, 0)
	21 dreturn (0, 0)

Method: getMax
	0 aload_0 (0, 0)
	1 getfield (0, 0)
	4 invokeinterface (0, 0)
	9 dreturn (0, 0)

Method: getMin
	0 aload_0 (0, 0)
	1 getfield (0, 0)
	4 invokeinterface (0, 0)
	9 dreturn (0, 0)

Method: getGeometricMean
	0 aload_0 (0, 0)
	1 getfield (0, 0)
	4 invokeinterface (0, 0)
	9 dreturn (0, 0)

Method: getSumOfLogs
	0 aload_0 (0, 0)
	1 getfield (0, 0)
	4 invokeinterface (0, 0)
	9 dreturn (0, 0)

Method: getSecondMoment
	0 aload_0 (0, 0)
	1 getfield (0, 0)
	4 invokevirtual (0, 0)
	7 dreturn (0, 0)

Method: toString
	0 new (0, 0)
	3 dup (0, 0)
	4 invokespecial (0, 0)
	7 astore_1 (0, 0)
	8 ldc (0, 0)
	10 astore_2 (0, 0)
	11 aload_1 (0, 0)
	12 ldc (0, 0)
	14 invokevirtual (0, 0)
	17 aload_2 (0, 0)
	18 invokevirtual (0, 0)
	21 pop (0, 0)
	22 aload_1 (0, 0)
	23 ldc (0, 0)
	25 invokevirtual (0, 0)
	28 aload_0 (0, 0)
	29 invokevirtual (0, 0)
	32 invokevirtual (0, 0)
	35 aload_2 (0, 0)
	36 invokevirtual (0, 0)
	39 pop (0, 0)
	40 aload_1 (0, 0)
	41 ldc (0, 0)
	43 invokevirtual (0, 0)
	46 aload_0 (0, 0)
	47 invokevirtual (0, 0)
	50 invokevirtual (0, 0)
	53 aload_2 (0, 0)
	54 invokevirtual (0, 0)
	57 pop (0, 0)
	58 aload_1 (0, 0)
	59 ldc (0, 0)
	61 invokevirtual (0, 0)
	64 aload_0 (0, 0)
	65 invokevirtual (0, 0)
	68 invokevirtual (0, 0)
	71 aload_2 (0, 0)
	72 invokevirtual (0, 0)
	75 pop (0, 0)
	76 aload_1 (0, 0)
	77 ldc (0, 0)
	79 invokevirtual (0, 0)
	82 aload_0 (0, 0)
	83 invokevirtual (0, 0)
	86 invokevirtual (0, 0)
	89 aload_2 (0, 0)
	90 invokevirtual (0, 0)
	93 pop (0, 0)
	94 aload_1 (0, 0)
	95 ldc (0, 0)
	97 invokevirtual (0, 0)
	100 aload_0 (0, 0)
	101 invokevirtual (0, 0)
	104 invokevirtual (0, 0)
	107 aload_2 (0, 0)
	108 invokevirtual (0, 0)
	111 pop (0, 0)
	112 aload_1 (0, 0)
	113 ldc (0, 0)
	115 invokevirtual (0, 0)
	118 aload_0 (0, 0)
	119 invokevirtual (0, 0)
	122 invokevirtual (0, 0)
	125 aload_2 (0, 0)
	126 invokevirtual (0, 0)
	129 pop (0, 0)
	130 aload_1 (0, 0)
	131 ldc (0, 0)
	133 invokevirtual (0, 0)
	136 aload_0 (0, 0)
	137 invokevirtual (0, 0)
	140 invokevirtual (0, 0)
	143 aload_2 (0, 0)
	144 invokevirtual (0, 0)
	147 pop (0, 0)
	148 aload_1 (0, 0)
	149 ldc (0, 0)
	151 invokevirtual (0, 0)
	154 aload_0 (0, 0)
	155 invokevirtual (0, 0)
	158 invokevirtual (0, 0)
	161 aload_2 (0, 0)
	162 invokevirtual (0, 0)
	165 pop (0, 0)
	166 aload_1 (0, 0)
	167 ldc (0, 0)
	169 invokevirtual (0, 0)
	172 aload_0 (0, 0)
	173 invokevirtual (0, 0)
	176 invokevirtual (0, 0)
	179 aload_2 (0, 0)
	180 invokevirtual (0, 0)
	183 pop (0, 0)
	184 aload_1 (0, 0)
	185 ldc (0, 0)
	187 invokevirtual (0, 0)
	190 aload_0 (0, 0)
	191 invokevirtual (0, 0)
	194 invokevirtual (0, 0)
	197 aload_2 (0, 0)
	198 invokevirtual (0, 0)
	201 pop (0, 0)
	202 aload_1 (0, 0)
	203 ldc (0, 0)
	205 invokevirtual (0, 0)
	208 aload_0 (0, 0)
	209 invokevirtual (0, 0)
	212 invokevirtual (0, 0)
	215 aload_2 (0, 0)
	216 invokevirtual (0, 0)
	219 pop (0, 0)
	220 aload_1 (0, 0)
	221 ldc (0, 0)
	223 invokevirtual (0, 0)
	226 aload_0 (0, 0)
	227 invokevirtual (0, 0)
	230 invokevirtual (0, 0)
	233 aload_2 (0, 0)
	234 invokevirtual (0, 0)
	237 pop (0, 0)
	238 aload_1 (0, 0)
	239 invokevirtual (0, 0)
	242 areturn (0, 0)

Method: clear
	0 aload_0 (0, 0)
	1 lconst_0 (0, 0)
	2 putfield (0, 0)
	5 aload_0 (0, 0)
	6 getfield (0, 0)
	9 invokeinterface (0, 0)
	14 aload_0 (0, 0)
	15 getfield (0, 0)
	18 invokeinterface (0, 0)
	23 aload_0 (0, 0)
	24 getfield (0, 0)
	27 invokeinterface (0, 0)
	32 aload_0 (0, 0)
	33 getfield (0, 0)
	36 invokeinterface (0, 0)
	41 aload_0 (0, 0)
	42 getfield (0, 0)
	45 invokeinterface (0, 0)
	50 aload_0 (0, 0)
	51 getfield (0, 0)
	54 invokeinterface (0, 0)
	59 aload_0 (0, 0)
	60 getfield (0, 0)
	63 invokevirtual (0, 0)
	66 aload_0 (1, 1)
	67 getfield (1, 1)
	70 aload_0 (1, 1)
	71 getfield (1, 1)
	74 if_acmpeq (1, 1)
	77 aload_0 (1, 1)
	78 getfield (1, 1)
	81 invokeinterface (1, 1)
	86 aload_0 (1, 1)
	87 getfield (1, 1)
	90 aload_0 (1, 1)
	91 getfield (1, 1)
	94 if_acmpeq (1, 1)
	97 aload_0 (1, 1)
	98 getfield (1, 1)
	101 invokeinterface (1, 1)
	106 return (0, 0)

Method: equals
	0 aload_1 (1, 1)
	1 aload_0 (1, 1)
	2 if_acmpne (1, 1)
	5 iconst_1 (1, 1)
	6 ireturn (1, 1)
	7 aload_1 (1, 1)
	8 instanceof (1, 1)
	11 ifne (1, 1)
	14 iconst_0 (1, 1)
	15 ireturn (1, 1)
	16 aload_1 (0, 0)
	17 checkcast (0, 0)
	20 astore_2 (0, 0)
	21 aload_2 (0, 0)
	22 invokevirtual (0, 0)
	25 aload_0 (0, 0)
	26 invokevirtual (0, 0)
	29 invokestatic (0, 0)
	32 ifeq (0, 0)
	35 aload_2 (0, 0)
	36 invokevirtual (0, 0)
	39 aload_0 (0, 0)
	40 invokevirtual (0, 0)
	43 invokestatic (0, 0)
	46 ifeq (0, 0)
	49 aload_2 (0, 0)
	50 invokevirtual (0, 0)
	53 aload_0 (0, 0)
	54 invokevirtual (0, 0)
	57 invokestatic (0, 0)
	60 ifeq (0, 0)
	63 aload_2 (0, 0)
	64 invokevirtual (0, 0)
	67 aload_0 (0, 0)
	68 invokevirtual (0, 0)
	71 invokestatic (0, 0)
	74 ifeq (0, 0)
	77 aload_2 (0, 0)
	78 invokevirtual (0, 0)
	81 l2f (0, 0)
	82 aload_0 (0, 0)
	83 invokevirtual (0, 0)
	86 l2f (0, 0)
	87 invokestatic (0, 0)
	90 ifeq (0, 0)
	93 aload_2 (0, 0)
	94 invokevirtual (0, 0)
	97 aload_0 (0, 0)
	98 invokevirtual (0, 0)
	101 invokestatic (0, 0)
	104 ifeq (0, 0)
	107 aload_2 (0, 0)
	108 invokevirtual (0, 0)
	111 aload_0 (0, 0)
	112 invokevirtual (0, 0)
	115 invokestatic (0, 0)
	118 ifeq (0, 0)
	121 aload_2 (0, 0)
	122 invokevirtual (0, 0)
	125 aload_0 (0, 0)
	126 invokevirtual (0, 0)
	129 invokestatic (0, 0)
	132 ifeq (0, 0)
	135 iconst_1 (0, 0)
	136 goto (0, 0)
	139 iconst_0 (0, 0)
	140 ireturn (0, 0)

Method: hashCode
	0 bipush (0, 0)
	2 aload_0 (0, 0)
	3 invokevirtual (0, 0)
	6 invokestatic (0, 0)
	9 iadd (0, 0)
	10 istore_1 (0, 0)
	11 iload_1 (0, 0)
	12 bipush (0, 0)
	14 imul (0, 0)
	15 aload_0 (0, 0)
	16 invokevirtual (0, 0)
	19 invokestatic (0, 0)
	22 iadd (0, 0)
	23 istore_1 (0, 0)
	24 iload_1 (0, 0)
	25 bipush (0, 0)
	27 imul (0, 0)
	28 aload_0 (0, 0)
	29 invokevirtual (0, 0)
	32 invokestatic (0, 0)
	35 iadd (0, 0)
	36 istore_1 (0, 0)
	37 iload_1 (0, 0)
	38 bipush (0, 0)
	40 imul (0, 0)
	41 aload_0 (0, 0)
	42 invokevirtual (0, 0)
	45 invokestatic (0, 0)
	48 iadd (0, 0)
	49 istore_1 (0, 0)
	50 iload_1 (0, 0)
	51 bipush (0, 0)
	53 imul (0, 0)
	54 aload_0 (0, 0)
	55 invokevirtual (0, 0)
	58 invokestatic (0, 0)
	61 iadd (0, 0)
	62 istore_1 (0, 0)
	63 iload_1 (0, 0)
	64 bipush (0, 0)
	66 imul (0, 0)
	67 aload_0 (0, 0)
	68 invokevirtual (0, 0)
	71 l2d (0, 0)
	72 invokestatic (0, 0)
	75 iadd (0, 0)
	76 istore_1 (0, 0)
	77 iload_1 (0, 0)
	78 bipush (0, 0)
	80 imul (0, 0)
	81 aload_0 (0, 0)
	82 invokevirtual (0, 0)
	85 invokestatic (0, 0)
	88 iadd (0, 0)
	89 istore_1 (0, 0)
	90 iload_1 (0, 0)
	91 bipush (0, 0)
	93 imul (0, 0)
	94 aload_0 (0, 0)
	95 invokevirtual (0, 0)
	98 invokestatic (0, 0)
	101 iadd (0, 0)
	102 istore_1 (0, 0)
	103 iload_1 (0, 0)
	104 bipush (0, 0)
	106 imul (0, 0)
	107 aload_0 (0, 0)
	108 invokevirtual (0, 0)
	111 invokestatic (0, 0)
	114 iadd (0, 0)
	115 istore_1 (0, 0)
	116 iload_1 (0, 0)
	117 ireturn (0, 0)

Method: getSumImpl
	0 aload_0 (0, 0)
	1 getfield (0, 0)
	4 areturn (0, 0)

Method: setSumImpl
	0 aload_0 (0, 0)
	1 invokespecial (0, 0)
	4 aload_0 (0, 0)
	5 aload_1 (0, 0)
	6 putfield (0, 0)
	9 return (0, 0)

Method: getSumsqImpl
	0 aload_0 (0, 0)
	1 getfield (0, 0)
	4 areturn (0, 0)

Method: setSumsqImpl
	0 aload_0 (0, 0)
	1 invokespecial (0, 0)
	4 aload_0 (0, 0)
	5 aload_1 (0, 0)
	6 putfield (0, 0)
	9 return (0, 0)

Method: getMinImpl
	0 aload_0 (0, 0)
	1 getfield (0, 0)
	4 areturn (0, 0)

Method: setMinImpl
	0 aload_0 (0, 0)
	1 invokespecial (0, 0)
	4 aload_0 (0, 0)
	5 aload_1 (0, 0)
	6 putfield (0, 0)
	9 return (0, 0)

Method: getMaxImpl
	0 aload_0 (0, 0)
	1 getfield (0, 0)
	4 areturn (0, 0)

Method: setMaxImpl
	0 aload_0 (0, 0)
	1 invokespecial (0, 0)
	4 aload_0 (0, 0)
	5 aload_1 (0, 0)
	6 putfield (0, 0)
	9 return (0, 0)

Method: getSumLogImpl
	0 aload_0 (0, 0)
	1 getfield (0, 0)
	4 areturn (0, 0)

Method: setSumLogImpl
	0 aload_0 (0, 0)
	1 invokespecial (0, 0)
	4 aload_0 (0, 0)
	5 aload_1 (0, 0)
	6 putfield (0, 0)
	9 aload_0 (0, 0)
	10 getfield (0, 0)
	13 aload_1 (0, 0)
	14 invokevirtual (0, 0)
	17 return (0, 0)

Method: getGeoMeanImpl
	0 aload_0 (0, 0)
	1 getfield (0, 0)
	4 areturn (0, 0)

Method: setGeoMeanImpl
	0 aload_0 (0, 0)
	1 invokespecial (0, 0)
	4 aload_0 (0, 0)
	5 aload_1 (0, 0)
	6 putfield (0, 0)
	9 return (0, 0)

Method: getMeanImpl
	0 aload_0 (0, 0)
	1 getfield (0, 0)
	4 areturn (0, 0)

Method: setMeanImpl
	0 aload_0 (0, 0)
	1 invokespecial (0, 0)
	4 aload_0 (0, 0)
	5 aload_1 (0, 0)
	6 putfield (0, 0)
	9 return (0, 0)

Method: getVarianceImpl
	0 aload_0 (0, 0)
	1 getfield (0, 0)
	4 areturn (0, 0)

Method: setVarianceImpl
	0 aload_0 (0, 0)
	1 invokespecial (0, 0)
	4 aload_0 (0, 0)
	5 aload_1 (0, 0)
	6 putfield (0, 0)
	9 return (0, 0)

Method: checkEmpty
	0 aload_0 (1, 1)
	1 getfield (1, 1)
	4 lconst_0 (1, 1)
	5 lcmp (1, 1)
	6 ifle (1, 1)
	9 new (1, 1)
	12 dup (1, 1)
	13 getstatic (1, 1)
	16 iconst_1 (1, 1)
	17 anewarray (1, 1)
	20 dup (1, 1)
	21 iconst_0 (1, 1)
	22 aload_0 (1, 1)
	23 getfield (1, 1)
	26 invokestatic (1, 1)
	29 aastore (1, 1)
	30 invokespecial (1, 1)
	33 athrow (1, 1)
	34 return (0, 0)

Method: copy
	0 aload_0 (0, 0)
	1 invokestatic (0, 0)
	4 aload_1 (0, 0)
	5 invokestatic (0, 0)
	8 aload_1 (0, 0)
	9 aload_0 (0, 0)
	10 getfield (0, 0)
	13 invokeinterface (0, 0)
	18 putfield (0, 0)
	21 aload_1 (0, 0)
	22 aload_0 (0, 0)
	23 getfield (0, 0)
	26 invokeinterface (0, 0)
	31 putfield (0, 0)
	34 aload_1 (0, 0)
	35 aload_0 (0, 0)
	36 getfield (0, 0)
	39 invokeinterface (0, 0)
	44 putfield (0, 0)
	47 aload_1 (0, 0)
	48 aload_0 (0, 0)
	49 getfield (0, 0)
	52 invokeinterface (0, 0)
	57 putfield (0, 0)
	60 aload_1 (0, 0)
	61 aload_0 (0, 0)
	62 getfield (0, 0)
	65 invokeinterface (0, 0)
	70 putfield (0, 0)
	73 aload_1 (0, 0)
	74 aload_0 (0, 0)
	75 getfield (0, 0)
	78 invokevirtual (0, 0)
	81 putfield (0, 0)
	84 aload_1 (0, 0)
	85 aload_0 (0, 0)
	86 getfield (0, 0)
	89 putfield (0, 0)
	92 aload_0 (1, 1)
	93 invokevirtual (1, 1)
	96 instanceof (1, 1)
	99 ifeq (1, 1)
	102 aload_1 (1, 1)
	103 new (1, 1)
	106 dup (1, 1)
	107 aload_1 (1, 1)
	108 getfield (1, 1)
	111 invokespecial (1, 1)
	114 putfield (1, 1)
	117 goto (1, 1)
	120 aload_1 (1, 2)
	121 aload_0 (1, 2)
	122 getfield (1, 2)
	125 invokeinterface (1, 2)
	130 putfield (1, 2)
	133 aload_0 (1, 1)
	134 getfield (1, 1)
	137 instanceof (1, 1)
	140 ifeq (1, 1)
	143 aload_1 (1, 1)
	144 new (1, 1)
	147 dup (1, 1)
	148 aload_1 (1, 1)
	149 getfield (1, 1)
	152 invokespecial (1, 1)
	155 putfield (1, 1)
	158 goto (1, 1)
	161 aload_1 (1, 2)
	162 aload_0 (1, 2)
	163 getfield (1, 2)
	166 invokeinterface (1, 2)
	171 putfield (1, 2)
	174 aload_0 (1, 1)
	175 invokevirtual (1, 1)
	178 instanceof (1, 1)
	181 ifeq (1, 1)
	184 aload_1 (1, 1)
	185 new (1, 1)
	188 dup (1, 1)
	189 aload_1 (1, 1)
	190 getfield (1, 1)
	193 checkcast (1, 1)
	196 invokespecial (1, 1)
	199 putfield (1, 1)
	202 goto (1, 1)
	205 aload_1 (1, 2)
	206 aload_0 (1, 2)
	207 getfield (1, 2)
	210 invokeinterface (1, 2)
	215 putfield (1, 2)
	218 aload_0 (1, 1)
	219 getfield (1, 1)
	222 aload_0 (1, 1)
	223 getfield (1, 1)
	226 if_acmpne (1, 1)
	229 aload_1 (1, 1)
	230 aload_1 (1, 1)
	231 getfield (1, 1)
	234 checkcast (1, 1)
	237 putfield (1, 1)
	240 goto (1, 1)
	243 aload_0 (1, 2)
	244 getfield (1, 2)
	247 aload_1 (1, 2)
	248 getfield (1, 2)
	251 invokestatic (1, 2)
	254 aload_0 (1, 1)
	255 getfield (1, 1)
	258 aload_0 (1, 1)
	259 getfield (1, 1)
	262 if_acmpne (1, 1)
	265 aload_1 (1, 1)
	266 aload_1 (1, 1)
	267 getfield (1, 1)
	270 checkcast (1, 1)
	273 putfield (1, 1)
	276 goto (1, 1)
	279 aload_0 (1, 2)
	280 getfield (1, 2)
	283 aload_1 (1, 2)
	284 getfield (1, 2)
	287 invokestatic (1, 2)
	290 aload_0 (1, 1)
	291 getfield (1, 1)
	294 aload_0 (1, 1)
	295 getfield (1, 1)
	298 if_acmpne (1, 1)
	301 aload_1 (1, 1)
	302 aload_1 (1, 1)
	303 getfield (1, 1)
	306 checkcast (1, 1)
	309 putfield (1, 1)
	312 goto (1, 1)
	315 aload_0 (1, 2)
	316 getfield (1, 2)
	319 aload_1 (1, 2)
	320 getfield (1, 2)
	323 invokestatic (1, 2)
	326 aload_0 (1, 1)
	327 getfield (1, 1)
	330 aload_0 (1, 1)
	331 getfield (1, 1)
	334 if_acmpne (1, 1)
	337 aload_1 (1, 1)
	338 aload_1 (1, 1)
	339 getfield (1, 1)
	342 checkcast (1, 1)
	345 putfield (1, 1)
	348 goto (1, 1)
	351 aload_0 (1, 2)
	352 getfield (1, 2)
	355 aload_1 (1, 2)
	356 getfield (1, 2)
	359 invokestatic (1, 2)
	362 aload_0 (1, 1)
	363 getfield (1, 1)
	366 aload_0 (1, 1)
	367 getfield (1, 1)
	370 if_acmpne (1, 1)
	373 aload_1 (1, 1)
	374 aload_1 (1, 1)
	375 getfield (1, 1)
	378 checkcast (1, 1)
	381 putfield (1, 1)
	384 goto (1, 1)
	387 aload_0 (1, 2)
	388 getfield (1, 2)
	391 aload_1 (1, 2)
	392 getfield (1, 2)
	395 invokestatic (1, 2)
	398 aload_0 (1, 1)
	399 getfield (1, 1)
	402 aload_0 (1, 1)
	403 getfield (1, 1)
	406 if_acmpne (1, 1)
	409 aload_1 (1, 1)
	410 aload_1 (1, 1)
	411 getfield (1, 1)
	414 checkcast (1, 1)
	417 putfield (1, 1)
	420 goto (1, 1)
	423 aload_0 (1, 2)
	424 getfield (1, 2)
	427 aload_1 (1, 2)
	428 getfield (1, 2)
	431 invokestatic (1, 2)
	434 aload_0 (1, 1)
	435 getfield (1, 1)
	438 aload_0 (1, 1)
	439 getfield (1, 1)
	442 if_acmpne (1, 1)
	445 aload_1 (1, 1)
	446 aload_1 (1, 1)
	447 getfield (1, 1)
	450 checkcast (1, 1)
	453 putfield (1, 1)
	456 goto (1, 1)
	459 aload_0 (1, 2)
	460 getfield (1, 2)
	463 aload_1 (1, 2)
	464 getfield (1, 2)
	467 invokestatic (1, 2)
	470 aload_0 (1, 1)
	471 getfield (1, 1)
	474 aload_0 (1, 1)
	475 getfield (1, 1)
	478 if_acmpne (1, 1)
	481 aload_1 (1, 1)
	482 aload_1 (1, 1)
	483 getfield (1, 1)
	486 checkcast (1, 1)
	489 putfield (1, 1)
	492 goto (1, 1)
	495 aload_0 (1, 2)
	496 getfield (1, 2)
	499 aload_1 (1, 2)
	500 getfield (1, 2)
	503 invokestatic (1, 2)
	506 return (0, 1)

