Method: <init>
	0 aload_0 (0, 0)
	1 iload_1 (0, 0)
	2 iload_2 (0, 0)
	3 invokespecial (0, 0)
	4 org/apache/commons/math3/stat/descriptive/MultivariateSummaryStatistics.<init>:(IZ)V (0, 0)
	6 return (0, 0)

Method: addValue
	0 aload_0 (0, 0)
	1 aload_1 (0, 0)
	2 invokespecial (0, 0)
	3 org/apache/commons/math3/stat/descriptive/MultivariateSummaryStatistics.addValue:([D)V (0, 0)
	5 return (0, 0)

Method: getDimension
	0 aload_0 (0, 0)
	1 invokespecial (0, 0)
	2 org/apache/commons/math3/stat/descriptive/MultivariateSummaryStatistics.getDimension:()I (0, 0)
	4 ireturn (0, 0)

Method: getN
	0 aload_0 (0, 0)
	1 invokespecial (0, 0)
	2 org/apache/commons/math3/stat/descriptive/MultivariateSummaryStatistics.getN:()J (0, 0)
	4 lreturn (0, 0)

Method: getSum
	0 aload_0 (0, 0)
	1 invokespecial (0, 0)
	2 org/apache/commons/math3/stat/descriptive/MultivariateSummaryStatistics.getSum:()[D (0, 0)
	4 areturn (0, 0)

Method: getSumSq
	0 aload_0 (0, 0)
	1 invokespecial (0, 0)
	2 org/apache/commons/math3/stat/descriptive/MultivariateSummaryStatistics.getSumSq:()[D (0, 0)
	4 areturn (0, 0)

Method: getSumLog
	0 aload_0 (0, 0)
	1 invokespecial (0, 0)
	2 org/apache/commons/math3/stat/descriptive/MultivariateSummaryStatistics.getSumLog:()[D (0, 0)
	4 areturn (0, 0)

Method: getMean
	0 aload_0 (0, 0)
	1 invokespecial (0, 0)
	2 org/apache/commons/math3/stat/descriptive/MultivariateSummaryStatistics.getMean:()[D (0, 0)
	4 areturn (0, 0)

Method: getStandardDeviation
	0 aload_0 (0, 0)
	1 invokespecial (0, 0)
	2 org/apache/commons/math3/stat/descriptive/MultivariateSummaryStatistics.getStandardDeviation:()[D (0, 0)
	4 areturn (0, 0)

Method: getCovariance
	0 aload_0 (0, 0)
	1 invokespecial (0, 0)
	2 org/apache/commons/math3/stat/descriptive/MultivariateSummaryStatistics.getCovariance:()Lorg/apache/commons/math3/linear/RealMatrix; (0, 0)
	4 areturn (0, 0)

Method: getMax
	0 aload_0 (0, 0)
	1 invokespecial (0, 0)
	2 org/apache/commons/math3/stat/descriptive/MultivariateSummaryStatistics.getMax:()[D (0, 0)
	4 areturn (0, 0)

Method: getMin
	0 aload_0 (0, 0)
	1 invokespecial (0, 0)
	2 org/apache/commons/math3/stat/descriptive/MultivariateSummaryStatistics.getMin:()[D (0, 0)
	4 areturn (0, 0)

Method: getGeometricMean
	0 aload_0 (0, 0)
	1 invokespecial (0, 0)
	2 org/apache/commons/math3/stat/descriptive/MultivariateSummaryStatistics.getGeometricMean:()[D (0, 0)
	4 areturn (0, 0)

Method: toString
	0 aload_0 (0, 0)
	1 invokespecial (0, 0)
	2 org/apache/commons/math3/stat/descriptive/MultivariateSummaryStatistics.toString:()Ljava/lang/String; (0, 0)
	4 areturn (0, 0)

Method: clear
	0 aload_0 (0, 0)
	1 invokespecial (0, 0)
	2 org/apache/commons/math3/stat/descriptive/MultivariateSummaryStatistics.clear:()V (0, 0)
	4 return (0, 0)

Method: equals
	0 aload_0 (0, 0)
	1 aload_1 (0, 0)
	2 invokespecial (0, 0)
	3 org/apache/commons/math3/stat/descriptive/MultivariateSummaryStatistics.equals:(Ljava/lang/Object;)Z (0, 0)
	5 ireturn (0, 0)

Method: hashCode
	0 aload_0 (0, 0)
	1 invokespecial (0, 0)
	2 org/apache/commons/math3/stat/descriptive/MultivariateSummaryStatistics.hashCode:()I (0, 0)
	4 ireturn (0, 0)

Method: getSumImpl
	0 aload_0 (0, 0)
	1 invokespecial (0, 0)
	2 org/apache/commons/math3/stat/descriptive/MultivariateSummaryStatistics.getSumImpl:()[Lorg/apache/commons/math3/stat/descriptive/StorelessUnivariateStatistic; (0, 0)
	4 areturn (0, 0)

Method: setSumImpl
	0 aload_0 (0, 0)
	1 aload_1 (0, 0)
	2 invokespecial (0, 0)
	3 org/apache/commons/math3/stat/descriptive/MultivariateSummaryStatistics.setSumImpl:([Lorg/apache/commons/math3/stat/descriptive/StorelessUnivariateStatistic;)V (0, 0)
	5 return (0, 0)

Method: getSumsqImpl
	0 aload_0 (0, 0)
	1 invokespecial (0, 0)
	2 org/apache/commons/math3/stat/descriptive/MultivariateSummaryStatistics.getSumsqImpl:()[Lorg/apache/commons/math3/stat/descriptive/StorelessUnivariateStatistic; (0, 0)
	4 areturn (0, 0)

Method: setSumsqImpl
	0 aload_0 (0, 0)
	1 aload_1 (0, 0)
	2 invokespecial (0, 0)
	3 org/apache/commons/math3/stat/descriptive/MultivariateSummaryStatistics.setSumsqImpl:([Lorg/apache/commons/math3/stat/descriptive/StorelessUnivariateStatistic;)V (0, 0)
	5 return (0, 0)

Method: getMinImpl
	0 aload_0 (0, 0)
	1 invokespecial (0, 0)
	2 org/apache/commons/math3/stat/descriptive/MultivariateSummaryStatistics.getMinImpl:()[Lorg/apache/commons/math3/stat/descriptive/StorelessUnivariateStatistic; (0, 0)
	4 areturn (0, 0)

Method: setMinImpl
	0 aload_0 (0, 0)
	1 aload_1 (0, 0)
	2 invokespecial (0, 0)
	3 org/apache/commons/math3/stat/descriptive/MultivariateSummaryStatistics.setMinImpl:([Lorg/apache/commons/math3/stat/descriptive/StorelessUnivariateStatistic;)V (0, 0)
	5 return (0, 0)

Method: getMaxImpl
	0 aload_0 (0, 0)
	1 invokespecial (0, 0)
	2 org/apache/commons/math3/stat/descriptive/MultivariateSummaryStatistics.getMaxImpl:()[Lorg/apache/commons/math3/stat/descriptive/StorelessUnivariateStatistic; (0, 0)
	4 areturn (0, 0)

Method: setMaxImpl
	0 aload_0 (0, 0)
	1 aload_1 (0, 0)
	2 invokespecial (0, 0)
	3 org/apache/commons/math3/stat/descriptive/MultivariateSummaryStatistics.setMaxImpl:([Lorg/apache/commons/math3/stat/descriptive/StorelessUnivariateStatistic;)V (0, 0)
	5 return (0, 0)

Method: getSumLogImpl
	0 aload_0 (0, 0)
	1 invokespecial (0, 0)
	2 org/apache/commons/math3/stat/descriptive/MultivariateSummaryStatistics.getSumLogImpl:()[Lorg/apache/commons/math3/stat/descriptive/StorelessUnivariateStatistic; (0, 0)
	4 areturn (0, 0)

Method: setSumLogImpl
	0 aload_0 (0, 0)
	1 aload_1 (0, 0)
	2 invokespecial (0, 0)
	3 org/apache/commons/math3/stat/descriptive/MultivariateSummaryStatistics.setSumLogImpl:([Lorg/apache/commons/math3/stat/descriptive/StorelessUnivariateStatistic;)V (0, 0)
	5 return (0, 0)

Method: getGeoMeanImpl
	0 aload_0 (0, 0)
	1 invokespecial (0, 0)
	2 org/apache/commons/math3/stat/descriptive/MultivariateSummaryStatistics.getGeoMeanImpl:()[Lorg/apache/commons/math3/stat/descriptive/StorelessUnivariateStatistic; (0, 0)
	4 areturn (0, 0)

Method: setGeoMeanImpl
	0 aload_0 (0, 0)
	1 aload_1 (0, 0)
	2 invokespecial (0, 0)
	3 org/apache/commons/math3/stat/descriptive/MultivariateSummaryStatistics.setGeoMeanImpl:([Lorg/apache/commons/math3/stat/descriptive/StorelessUnivariateStatistic;)V (0, 0)
	5 return (0, 0)

Method: getMeanImpl
	0 aload_0 (0, 0)
	1 invokespecial (0, 0)
	2 org/apache/commons/math3/stat/descriptive/MultivariateSummaryStatistics.getMeanImpl:()[Lorg/apache/commons/math3/stat/descriptive/StorelessUnivariateStatistic; (0, 0)
	4 areturn (0, 0)

Method: setMeanImpl
	0 aload_0 (0, 0)
	1 aload_1 (0, 0)
	2 invokespecial (0, 0)
	3 org/apache/commons/math3/stat/descriptive/MultivariateSummaryStatistics.setMeanImpl:([Lorg/apache/commons/math3/stat/descriptive/StorelessUnivariateStatistic;)V (0, 0)
	5 return (0, 0)

