Method: <init>
	0 aload_0 (0, 0)
	1 invokespecial (0, 0)
	2 org/apache/commons/math3/stat/descriptive/SummaryStatistics.<init>:()V (0, 0)
	4 aload_1 (0, 0)
	5 aload_0 (0, 0)
	6 invokestatic (0, 0)
	7 org/apache/commons/math3/stat/descriptive/SynchronizedSummaryStatistics.copy:(Lorg/apache/commons/math3/stat/descriptive/SynchronizedSummaryStatistics;Lorg/apache/commons/math3/stat/descriptive/SynchronizedSummaryStatistics;)V (0, 0)
	9 return (0, 0)

Method: getSummary
	0 aload_0 (0, 0)
	1 invokespecial (0, 0)
	2 org/apache/commons/math3/stat/descriptive/SummaryStatistics.getSummary:()Lorg/apache/commons/math3/stat/descriptive/StatisticalSummary; (0, 0)
	4 areturn (0, 0)

Method: addValue
	0 aload_0 (0, 0)
	1 dload_1 (0, 0)
	2 invokespecial (0, 0)
	3 org/apache/commons/math3/stat/descriptive/SummaryStatistics.addValue:(D)V (0, 0)
	5 return (0, 0)

Method: getN
	0 aload_0 (0, 0)
	1 invokespecial (0, 0)
	2 org/apache/commons/math3/stat/descriptive/SummaryStatistics.getN:()J (0, 0)
	4 lreturn (0, 0)

Method: getSum
	0 aload_0 (0, 0)
	1 invokespecial (0, 0)
	2 org/apache/commons/math3/stat/descriptive/SummaryStatistics.getSum:()D (0, 0)
	4 dreturn (0, 0)

Method: getSumsq
	0 aload_0 (0, 0)
	1 invokespecial (0, 0)
	2 org/apache/commons/math3/stat/descriptive/SummaryStatistics.getSumsq:()D (0, 0)
	4 dreturn (0, 0)

Method: getMean
	0 aload_0 (0, 0)
	1 invokespecial (0, 0)
	2 org/apache/commons/math3/stat/descriptive/SummaryStatistics.getMean:()D (0, 0)
	4 dreturn (0, 0)

Method: getStandardDeviation
	0 aload_0 (0, 0)
	1 invokespecial (0, 0)
	2 org/apache/commons/math3/stat/descriptive/SummaryStatistics.getStandardDeviation:()D (0, 0)
	4 dreturn (0, 0)

Method: getQuadraticMean
	0 aload_0 (0, 0)
	1 invokespecial (0, 0)
	2 org/apache/commons/math3/stat/descriptive/SummaryStatistics.getQuadraticMean:()D (0, 0)
	4 dreturn (0, 0)

Method: getVariance
	0 aload_0 (0, 0)
	1 invokespecial (0, 0)
	2 org/apache/commons/math3/stat/descriptive/SummaryStatistics.getVariance:()D (0, 0)
	4 dreturn (0, 0)

Method: getPopulationVariance
	0 aload_0 (0, 0)
	1 invokespecial (0, 0)
	2 org/apache/commons/math3/stat/descriptive/SummaryStatistics.getPopulationVariance:()D (0, 0)
	4 dreturn (0, 0)

Method: getMax
	0 aload_0 (0, 0)
	1 invokespecial (0, 0)
	2 org/apache/commons/math3/stat/descriptive/SummaryStatistics.getMax:()D (0, 0)
	4 dreturn (0, 0)

Method: getMin
	0 aload_0 (0, 0)
	1 invokespecial (0, 0)
	2 org/apache/commons/math3/stat/descriptive/SummaryStatistics.getMin:()D (0, 0)
	4 dreturn (0, 0)

Method: getGeometricMean
	0 aload_0 (0, 0)
	1 invokespecial (0, 0)
	2 org/apache/commons/math3/stat/descriptive/SummaryStatistics.getGeometricMean:()D (0, 0)
	4 dreturn (0, 0)

Method: toString
	0 aload_0 (0, 0)
	1 invokespecial (0, 0)
	2 org/apache/commons/math3/stat/descriptive/SummaryStatistics.toString:()Ljava/lang/String; (0, 0)
	4 areturn (0, 0)

Method: clear
	0 aload_0 (0, 0)
	1 invokespecial (0, 0)
	2 org/apache/commons/math3/stat/descriptive/SummaryStatistics.clear:()V (0, 0)
	4 return (0, 0)

Method: equals
	0 aload_0 (0, 0)
	1 aload_1 (0, 0)
	2 invokespecial (0, 0)
	3 org/apache/commons/math3/stat/descriptive/SummaryStatistics.equals:(Ljava/lang/Object;)Z (0, 0)
	5 ireturn (0, 0)

Method: hashCode
	0 aload_0 (0, 0)
	1 invokespecial (0, 0)
	2 org/apache/commons/math3/stat/descriptive/SummaryStatistics.hashCode:()I (0, 0)
	4 ireturn (0, 0)

Method: getSumImpl
	0 aload_0 (0, 0)
	1 invokespecial (0, 0)
	2 org/apache/commons/math3/stat/descriptive/SummaryStatistics.getSumImpl:()Lorg/apache/commons/math3/stat/descriptive/StorelessUnivariateStatistic; (0, 0)
	4 areturn (0, 0)

Method: setSumImpl
	0 aload_0 (0, 0)
	1 aload_1 (0, 0)
	2 invokespecial (0, 0)
	3 org/apache/commons/math3/stat/descriptive/SummaryStatistics.setSumImpl:(Lorg/apache/commons/math3/stat/descriptive/StorelessUnivariateStatistic;)V (0, 0)
	5 return (0, 0)

Method: getSumsqImpl
	0 aload_0 (0, 0)
	1 invokespecial (0, 0)
	2 org/apache/commons/math3/stat/descriptive/SummaryStatistics.getSumsqImpl:()Lorg/apache/commons/math3/stat/descriptive/StorelessUnivariateStatistic; (0, 0)
	4 areturn (0, 0)

Method: setSumsqImpl
	0 aload_0 (0, 0)
	1 aload_1 (0, 0)
	2 invokespecial (0, 0)
	3 org/apache/commons/math3/stat/descriptive/SummaryStatistics.setSumsqImpl:(Lorg/apache/commons/math3/stat/descriptive/StorelessUnivariateStatistic;)V (0, 0)
	5 return (0, 0)

Method: getMinImpl
	0 aload_0 (0, 0)
	1 invokespecial (0, 0)
	2 org/apache/commons/math3/stat/descriptive/SummaryStatistics.getMinImpl:()Lorg/apache/commons/math3/stat/descriptive/StorelessUnivariateStatistic; (0, 0)
	4 areturn (0, 0)

Method: setMinImpl
	0 aload_0 (0, 0)
	1 aload_1 (0, 0)
	2 invokespecial (0, 0)
	3 org/apache/commons/math3/stat/descriptive/SummaryStatistics.setMinImpl:(Lorg/apache/commons/math3/stat/descriptive/StorelessUnivariateStatistic;)V (0, 0)
	5 return (0, 0)

Method: getMaxImpl
	0 aload_0 (0, 0)
	1 invokespecial (0, 0)
	2 org/apache/commons/math3/stat/descriptive/SummaryStatistics.getMaxImpl:()Lorg/apache/commons/math3/stat/descriptive/StorelessUnivariateStatistic; (0, 0)
	4 areturn (0, 0)

Method: setMaxImpl
	0 aload_0 (0, 0)
	1 aload_1 (0, 0)
	2 invokespecial (0, 0)
	3 org/apache/commons/math3/stat/descriptive/SummaryStatistics.setMaxImpl:(Lorg/apache/commons/math3/stat/descriptive/StorelessUnivariateStatistic;)V (0, 0)
	5 return (0, 0)

Method: getSumLogImpl
	0 aload_0 (0, 0)
	1 invokespecial (0, 0)
	2 org/apache/commons/math3/stat/descriptive/SummaryStatistics.getSumLogImpl:()Lorg/apache/commons/math3/stat/descriptive/StorelessUnivariateStatistic; (0, 0)
	4 areturn (0, 0)

Method: setSumLogImpl
	0 aload_0 (0, 0)
	1 aload_1 (0, 0)
	2 invokespecial (0, 0)
	3 org/apache/commons/math3/stat/descriptive/SummaryStatistics.setSumLogImpl:(Lorg/apache/commons/math3/stat/descriptive/StorelessUnivariateStatistic;)V (0, 0)
	5 return (0, 0)

Method: getGeoMeanImpl
	0 aload_0 (0, 0)
	1 invokespecial (0, 0)
	2 org/apache/commons/math3/stat/descriptive/SummaryStatistics.getGeoMeanImpl:()Lorg/apache/commons/math3/stat/descriptive/StorelessUnivariateStatistic; (0, 0)
	4 areturn (0, 0)

Method: setGeoMeanImpl
	0 aload_0 (0, 0)
	1 aload_1 (0, 0)
	2 invokespecial (0, 0)
	3 org/apache/commons/math3/stat/descriptive/SummaryStatistics.setGeoMeanImpl:(Lorg/apache/commons/math3/stat/descriptive/StorelessUnivariateStatistic;)V (0, 0)
	5 return (0, 0)

Method: getMeanImpl
	0 aload_0 (0, 0)
	1 invokespecial (0, 0)
	2 org/apache/commons/math3/stat/descriptive/SummaryStatistics.getMeanImpl:()Lorg/apache/commons/math3/stat/descriptive/StorelessUnivariateStatistic; (0, 0)
	4 areturn (0, 0)

Method: setMeanImpl
	0 aload_0 (0, 0)
	1 aload_1 (0, 0)
	2 invokespecial (0, 0)
	3 org/apache/commons/math3/stat/descriptive/SummaryStatistics.setMeanImpl:(Lorg/apache/commons/math3/stat/descriptive/StorelessUnivariateStatistic;)V (0, 0)
	5 return (0, 0)

Method: getVarianceImpl
	0 aload_0 (0, 0)
	1 invokespecial (0, 0)
	2 org/apache/commons/math3/stat/descriptive/SummaryStatistics.getVarianceImpl:()Lorg/apache/commons/math3/stat/descriptive/StorelessUnivariateStatistic; (0, 0)
	4 areturn (0, 0)

Method: setVarianceImpl
	0 aload_0 (0, 0)
	1 aload_1 (0, 0)
	2 invokespecial (0, 0)
	3 org/apache/commons/math3/stat/descriptive/SummaryStatistics.setVarianceImpl:(Lorg/apache/commons/math3/stat/descriptive/StorelessUnivariateStatistic;)V (0, 0)
	5 return (0, 0)

Method: copy
	0 aload_0 (0, 0)
	1 invokevirtual (0, 0)
	2 org/apache/commons/math3/stat/descriptive/SynchronizedSummaryStatistics.copy:()Lorg/apache/commons/math3/stat/descriptive/SynchronizedSummaryStatistics; (0, 0)
	4 areturn (0, 0)

