Method: <init>
	0 aload_0 (0, 0)
	1 invokespecial (0, 0)
	2 org/apache/commons/math3/stat/descriptive/DescriptiveStatistics.<init>:()V (0, 0)
	4 aload_1 (0, 0)
	5 aload_0 (0, 0)
	6 invokestatic (0, 0)
	7 org/apache/commons/math3/stat/descriptive/SynchronizedDescriptiveStatistics.copy:(Lorg/apache/commons/math3/stat/descriptive/SynchronizedDescriptiveStatistics;Lorg/apache/commons/math3/stat/descriptive/SynchronizedDescriptiveStatistics;)V (0, 0)
	9 return (0, 0)

Method: addValue
	0 aload_0 (0, 0)
	1 dload_1 (0, 0)
	2 invokespecial (0, 0)
	3 org/apache/commons/math3/stat/descriptive/DescriptiveStatistics.addValue:(D)V (0, 0)
	5 return (0, 0)

Method: apply
	0 aload_0 (0, 0)
	1 aload_1 (0, 0)
	2 invokespecial (0, 0)
	3 org/apache/commons/math3/stat/descriptive/DescriptiveStatistics.apply:(Lorg/apache/commons/math3/stat/descriptive/UnivariateStatistic;)D (0, 0)
	5 dreturn (0, 0)

Method: clear
	0 aload_0 (0, 0)
	1 invokespecial (0, 0)
	2 org/apache/commons/math3/stat/descriptive/DescriptiveStatistics.clear:()V (0, 0)
	4 return (0, 0)

Method: getElement
	0 aload_0 (0, 0)
	1 iload_1 (0, 0)
	2 invokespecial (0, 0)
	3 org/apache/commons/math3/stat/descriptive/DescriptiveStatistics.getElement:(I)D (0, 0)
	5 dreturn (0, 0)

Method: getN
	0 aload_0 (0, 0)
	1 invokespecial (0, 0)
	2 org/apache/commons/math3/stat/descriptive/DescriptiveStatistics.getN:()J (0, 0)
	4 lreturn (0, 0)

Method: getStandardDeviation
	0 aload_0 (0, 0)
	1 invokespecial (0, 0)
	2 org/apache/commons/math3/stat/descriptive/DescriptiveStatistics.getStandardDeviation:()D (0, 0)
	4 dreturn (0, 0)

Method: getQuadraticMean
	0 aload_0 (0, 0)
	1 invokespecial (0, 0)
	2 org/apache/commons/math3/stat/descriptive/DescriptiveStatistics.getQuadraticMean:()D (0, 0)
	4 dreturn (0, 0)

Method: getValues
	0 aload_0 (0, 0)
	1 invokespecial (0, 0)
	2 org/apache/commons/math3/stat/descriptive/DescriptiveStatistics.getValues:()[D (0, 0)
	4 areturn (0, 0)

Method: getWindowSize
	0 aload_0 (0, 0)
	1 invokespecial (0, 0)
	2 org/apache/commons/math3/stat/descriptive/DescriptiveStatistics.getWindowSize:()I (0, 0)
	4 ireturn (0, 0)

Method: setWindowSize
	0 aload_0 (0, 0)
	1 iload_1 (0, 0)
	2 invokespecial (0, 0)
	3 org/apache/commons/math3/stat/descriptive/DescriptiveStatistics.setWindowSize:(I)V (0, 0)
	5 return (0, 0)

Method: toString
	0 aload_0 (0, 0)
	1 invokespecial (0, 0)
	2 org/apache/commons/math3/stat/descriptive/DescriptiveStatistics.toString:()Ljava/lang/String; (0, 0)
	4 areturn (0, 0)

Method: copy
	0 aload_0 (0, 0)
	1 invokevirtual (0, 0)
	2 org/apache/commons/math3/stat/descriptive/SynchronizedDescriptiveStatistics.copy:()Lorg/apache/commons/math3/stat/descriptive/SynchronizedDescriptiveStatistics; (0, 0)
	4 areturn (0, 0)

