Method: <init>
	0 aload_0 (0, 0)
	1 aload_1 (0, 0)
	2 invokespecial (0, 0)
	3 org/apache/commons/math3/optimization/direct/BaseAbstractMultivariateOptimizer.<init>:(Lorg/apache/commons/math3/optimization/ConvergenceChecker;)V (0, 0)
	5 return (0, 0)

Method: computeObjectiveGradient
	0 aload_0 (0, 0)
	1 getfield (0, 0)
	2 org/apache/commons/math3/optimization/general/AbstractScalarDifferentiableOptimizer.gradient:Lorg/apache/commons/math3/analysis/MultivariateVectorFunction; (0, 0)
	4 aload_1 (0, 0)
	5 invokeinterface (0, 0)
	6 org/apache/commons/math3/analysis/MultivariateVectorFunction.gradient:()Lorg/apache/commons/math3/analysis/MultivariateVectorFunction; (0, 0)
	8 0 (0, 0)
	10 areturn (0, 0)

Method: optimizeInternal
	0 aload_0 (0, 0)
	1 iload_1 (0, 0)
	2 aload_2 (0, 0)
	3 checkcast (0, 0)
	4 org/apache/commons/math3/analysis/DifferentiableMultivariateFunction (0, 0)
	6 aload_3 (0, 0)
	7 aload (0, 0)
	8 #4 (0, 0)
	9 invokevirtual (0, 0)
	10 org/apache/commons/math3/optimization/general/AbstractScalarDifferentiableOptimizer.optimizeInternal:(ILorg/apache/commons/math3/analysis/DifferentiableMultivariateFunction;Lorg/apache/commons/math3/optimization/GoalType;[D)Lorg/apache/commons/math3/optimization/PointValuePair; (0, 0)
	12 areturn (0, 0)

Method: optimize
	0 aload_0 (0, 0)
	1 iload_1 (0, 0)
	2 aload_2 (0, 0)
	3 invokestatic (0, 1)
	4 org/apache/commons/math3/analysis/FunctionUtils.toDifferentiableMultivariateFunction:(Lorg/apache/commons/math3/analysis/differentiation/MultivariateDifferentiableFunction;)Lorg/apache/commons/math3/analysis/DifferentiableMultivariateFunction; (0, 1)
	6 aload_3 (0, 1)
	7 aload (0, 1)
	8 #4 (0, 1)
	9 invokevirtual (0, 1)
	10 org/apache/commons/math3/optimization/general/AbstractScalarDifferentiableOptimizer.optimizeInternal:(ILorg/apache/commons/math3/analysis/DifferentiableMultivariateFunction;Lorg/apache/commons/math3/optimization/GoalType;[D)Lorg/apache/commons/math3/optimization/PointValuePair; (0, 1)
	12 areturn (0, 1)

