Method: <init>
	0 aload_0 (0, 0)
	1 aload_1 (0, 0)
	2 invokespecial (0, 0)
	3 org/apache/commons/math3/optimization/direct/BaseAbstractMultivariateVectorOptimizer.<init>:(Lorg/apache/commons/math3/optimization/ConvergenceChecker;)V (0, 0)
	5 return (0, 0)

Method: getJacobianEvaluations
	0 aload_0 (0, 0)
	1 getfield (0, 0)
	2 org/apache/commons/math3/optimization/general/AbstractLeastSquaresOptimizer.jacobianEvaluations:I (0, 0)
	4 ireturn (0, 0)

Method: updateJacobian
	0 aload_0 (0, 0)
	1 aload_0 (0, 0)
	2 getfield (0, 0)
	3 org/apache/commons/math3/optimization/general/AbstractLeastSquaresOptimizer.point:[D (0, 0)
	5 invokevirtual (0, 0)
	6 org/apache/commons/math3/optimization/general/AbstractLeastSquaresOptimizer.computeWeightedJacobian:([D)Lorg/apache/commons/math3/linear/RealMatrix; (0, 0)
	8 astore_1 (0, 0)
	9 aload_0 (0, 0)
	10 aload_1 (0, 0)
	11 ldc2_w (0, 0)
	12 -1.0 (0, 0)
	14 invokeinterface (0, 0)
	15 org/apache/commons/math3/linear/RealMatrix.getData:()[[D (0, 0)
	17 0 (0, 0)
	19 invokeinterface (0, 0)
	20 org/apache/commons/math3/linear/RealMatrix.weightedResidualJacobian:[[D (0, 0)
	22 0 (0, 0)
	24 putfield (0, 0)
	25 org/apache/commons/math3/optimization/general/AbstractLeastSquaresOptimizer.weightedResidualJacobian:[[D (0, 0)
	27 return (0, 0)

Method: computeWeightedJacobian
	0 aload_0 (0, 0)
	1 dup (0, 0)
	2 getfield (0, 0)
	3 org/apache/commons/math3/optimization/general/AbstractLeastSquaresOptimizer.jacobianEvaluations:I (0, 0)
	5 iconst_1 (0, 0)
	6 iadd (0, 0)
	7 putfield (0, 0)
	8 org/apache/commons/math3/optimization/general/AbstractLeastSquaresOptimizer.jacobianEvaluations:I (0, 0)
	10 aload_1 (0, 0)
	11 arraylength (0, 0)
	12 anewarray (0, 0)
	13 org/apache/commons/math3/analysis/differentiation/DerivativeStructure (0, 0)
	15 astore_2 (0, 0)
	16 aload_1 (0, 0)
	17 arraylength (0, 0)
	18 istore_3 (0, 0)
	19 iconst_0 (1, 4)
	20 istore (1, 4)
	21 #4 (1, 4)
	22 iload (1, 4)
	23 #4 (1, 4)
	24 iload_3 (1, 4)
	25 if_icmpge (1, 4)
	26 28 (1, 4)
	28 aload_2 (1, 4)
	29 iload (1, 4)
	30 #4 (1, 4)
	31 new (1, 4)
	32 org/apache/commons/math3/analysis/differentiation/DerivativeStructure (1, 4)
	34 dup (1, 4)
	35 iload_3 (1, 4)
	36 iconst_1 (1, 4)
	37 iload (1, 4)
	38 #4 (1, 4)
	39 aload_1 (1, 4)
	40 iload (1, 4)
	41 #4 (1, 4)
	42 daload (1, 4)
	43 invokespecial (1, 4)
	44 org/apache/commons/math3/analysis/differentiation/DerivativeStructure.<init>:(IIID)V (1, 4)
	46 aastore (1, 4)
	47 iinc (1, 4)
	48 #4 (1, 4)
	49 -89 (1, 4)
	50 goto (1, 4)
	51 -28 (1, 4)
	53 aload_0 (0, 0)
	54 getfield (0, 0)
	55 org/apache/commons/math3/optimization/general/AbstractLeastSquaresOptimizer.jF:Lorg/apache/commons/math3/analysis/differentiation/MultivariateDifferentiableVectorFunction; (0, 0)
	57 aload_2 (0, 0)
	58 invokeinterface (0, 0)
	59 org/apache/commons/math3/analysis/differentiation/MultivariateDifferentiableVectorFunction.getTarget:()[D (0, 0)
	61 0 (0, 0)
	63 astore (0, 0)
	64 #4 (0, 0)
	65 aload_0 (0, 0)
	66 invokevirtual (0, 0)
	67 org/apache/commons/math3/optimization/general/AbstractLeastSquaresOptimizer.getTarget:()[D (0, 0)
	69 arraylength (0, 0)
	70 istore (0, 0)
	71 #5 (0, 0)
	72 aload (1, 1)
	73 #4 (1, 1)
	74 arraylength (1, 1)
	75 iload (1, 1)
	76 #5 (1, 1)
	77 if_icmpeq (1, 1)
	78 16 (1, 1)
	80 new (1, 1)
	81 org/apache/commons/math3/exception/DimensionMismatchException (1, 1)
	83 dup (1, 1)
	84 aload (1, 1)
	85 #4 (1, 1)
	86 arraylength (1, 1)
	87 iload (1, 1)
	88 #5 (1, 1)
	89 invokespecial (1, 1)
	90 org/apache/commons/math3/exception/DimensionMismatchException.<init>:(II)V (1, 1)
	92 athrow (1, 1)
	93 iload (0, 0)
	94 #5 (0, 0)
	95 iload_3 (0, 0)
	96 multianewarray (0, 0)
	97 [[D (0, 0)
	99 58 (0, 0)
	100 astore (0, 0)
	101 #6 (0, 0)
	102 iconst_0 (1, 4)
	103 istore (1, 4)
	104 #7 (1, 4)
	105 iload (1, 4)
	106 #7 (1, 4)
	107 iload (1, 4)
	108 #5 (1, 4)
	109 if_icmpge (1, 4)
	110 59 (1, 4)
	112 iload_3 (1, 4)
	113 newarray (1, 4)
	114 10 (1, 4)
	115 astore (1, 4)
	116 #8 (1, 4)
	117 iconst_0 (2, 4)
	118 istore (2, 4)
	119 #9 (2, 4)
	120 iload (2, 4)
	121 #9 (2, 4)
	122 iload_3 (2, 4)
	123 if_icmpge (2, 4)
	124 39 (2, 4)
	126 aload (2, 4)
	127 #8 (2, 4)
	128 iload (2, 4)
	129 #9 (2, 4)
	130 iconst_1 (2, 4)
	131 iastore (2, 4)
	132 aload (2, 4)
	133 #6 (2, 4)
	134 iload (2, 4)
	135 #7 (2, 4)
	136 aaload (2, 4)
	137 iload (2, 4)
	138 #9 (2, 4)
	139 aload (2, 4)
	140 #4 (2, 4)
	141 iload (2, 4)
	142 #7 (2, 4)
	143 aaload (2, 4)
	144 aload (2, 4)
	145 #8 (2, 4)
	146 invokevirtual (2, 4)
	147 org/apache/commons/math3/analysis/differentiation/DerivativeStructure.getPartialDerivative:([I)D (2, 4)
	149 dastore (2, 4)
	150 aload (2, 4)
	151 #8 (2, 4)
	152 iload (2, 4)
	153 #9 (2, 4)
	154 iconst_0 (2, 4)
	155 iastore (2, 4)
	156 iinc (2, 4)
	157 #9 (2, 4)
	158 -89 (2, 4)
	159 goto (2, 4)
	160 -39 (2, 4)
	162 iinc (2, 4)
	163 #7 (2, 4)
	164 -89 (2, 4)
	165 goto (2, 4)
	166 -60 (2, 4)
	168 aload_0 (1, 4)
	169 getfield (1, 4)
	170 org/apache/commons/math3/optimization/general/AbstractLeastSquaresOptimizer.weightMatrixSqrt:Lorg/apache/commons/math3/linear/RealMatrix; (1, 4)
	172 aload (1, 4)
	173 #6 (1, 4)
	174 invokestatic (1, 4)
	175 org/apache/commons/math3/linear/MatrixUtils.createRealMatrix:([[D)Lorg/apache/commons/math3/linear/RealMatrix; (1, 4)
	177 invokeinterface (1, 4)
	178 org/apache/commons/math3/linear/RealMatrix.computeObjectiveValue:([D)[D (1, 4)
	180 0 (1, 4)
	182 areturn (1, 4)

Method: updateResidualsAndCost
	0 aload_0 (0, 0)
	1 aload_0 (0, 0)
	2 aload_0 (0, 0)
	3 getfield (0, 0)
	4 org/apache/commons/math3/optimization/general/AbstractLeastSquaresOptimizer.point:[D (0, 0)
	6 invokevirtual (0, 0)
	7 org/apache/commons/math3/optimization/general/AbstractLeastSquaresOptimizer.computeObjectiveValue:([D)[D (0, 0)
	9 putfield (0, 0)
	10 org/apache/commons/math3/optimization/general/AbstractLeastSquaresOptimizer.objective:[D (0, 0)
	12 aload_0 (0, 0)
	13 aload_0 (0, 0)
	14 getfield (0, 0)
	15 org/apache/commons/math3/optimization/general/AbstractLeastSquaresOptimizer.objective:[D (0, 0)
	17 invokevirtual (0, 0)
	18 org/apache/commons/math3/optimization/general/AbstractLeastSquaresOptimizer.computeResiduals:([D)[D (0, 0)
	20 astore_1 (0, 0)
	21 aload_0 (0, 0)
	22 aload_0 (0, 0)
	23 aload_1 (0, 0)
	24 invokevirtual (0, 0)
	25 org/apache/commons/math3/optimization/general/AbstractLeastSquaresOptimizer.computeCost:([D)D (0, 0)
	27 putfield (0, 0)
	28 org/apache/commons/math3/optimization/general/AbstractLeastSquaresOptimizer.cost:D (0, 0)
	30 new (0, 0)
	31 org/apache/commons/math3/linear/ArrayRealVector (0, 0)
	33 dup (0, 0)
	34 aload_1 (0, 0)
	35 invokespecial (0, 0)
	36 org/apache/commons/math3/linear/ArrayRealVector.<init>:([D)V (0, 0)
	38 astore_2 (0, 0)
	39 aload_0 (0, 0)
	40 aload_0 (0, 0)
	41 getfield (0, 0)
	42 org/apache/commons/math3/optimization/general/AbstractLeastSquaresOptimizer.weightMatrixSqrt:Lorg/apache/commons/math3/linear/RealMatrix; (0, 0)
	44 aload_2 (0, 0)
	45 invokeinterface (0, 0)
	46 org/apache/commons/math3/linear/RealMatrix.org/apache/commons/math3/linear/RealVector (0, 0)
	48 0 (0, 0)
	50 invokevirtual (0, 0)
	51 org/apache/commons/math3/linear/RealVector.toArray:()[D (0, 0)
	53 putfield (0, 0)
	54 org/apache/commons/math3/optimization/general/AbstractLeastSquaresOptimizer.weightedResiduals:[D (0, 0)
	56 return (0, 0)

Method: computeCost
	0 new (0, 0)
	1 org/apache/commons/math3/linear/ArrayRealVector (0, 0)
	3 dup (0, 0)
	4 aload_1 (0, 0)
	5 invokespecial (0, 0)
	6 org/apache/commons/math3/linear/ArrayRealVector.<init>:([D)V (0, 0)
	8 astore_2 (0, 0)
	9 aload_2 (0, 0)
	10 aload_0 (0, 0)
	11 invokevirtual (0, 0)
	12 org/apache/commons/math3/optimization/general/AbstractLeastSquaresOptimizer.getWeight:()Lorg/apache/commons/math3/linear/RealMatrix; (0, 0)
	14 aload_2 (0, 0)
	15 invokeinterface (0, 0)
	16 org/apache/commons/math3/linear/RealMatrix.org/apache/commons/math3/linear/RealVector (0, 0)
	18 0 (0, 0)
	20 invokevirtual (0, 0)
	21 org/apache/commons/math3/linear/ArrayRealVector.dotProduct:(Lorg/apache/commons/math3/linear/RealVector;)D (0, 0)
	23 invokestatic (0, 0)
	24 org/apache/commons/math3/util/FastMath.sqrt:(D)D (0, 0)
	26 dreturn (0, 0)

Method: getRMS
	0 aload_0 (0, 0)
	1 invokevirtual (0, 0)
	2 org/apache/commons/math3/optimization/general/AbstractLeastSquaresOptimizer.getChiSquare:()D (0, 0)
	4 aload_0 (0, 0)
	5 getfield (0, 0)
	6 org/apache/commons/math3/optimization/general/AbstractLeastSquaresOptimizer.rows:I (0, 0)
	8 i2d (0, 0)
	9 ddiv (0, 0)
	10 invokestatic (0, 0)
	11 org/apache/commons/math3/util/FastMath.sqrt:(D)D (0, 0)
	13 dreturn (0, 0)

Method: getChiSquare
	0 aload_0 (0, 0)
	1 getfield (0, 0)
	2 org/apache/commons/math3/optimization/general/AbstractLeastSquaresOptimizer.cost:D (0, 0)
	4 aload_0 (0, 0)
	5 getfield (0, 0)
	6 org/apache/commons/math3/optimization/general/AbstractLeastSquaresOptimizer.cost:D (0, 0)
	8 dmul (0, 0)
	9 dreturn (0, 0)

Method: getWeightSquareRoot
	0 aload_0 (0, 0)
	1 getfield (0, 0)
	2 org/apache/commons/math3/optimization/general/AbstractLeastSquaresOptimizer.weightMatrixSqrt:Lorg/apache/commons/math3/linear/RealMatrix; (0, 0)
	4 invokeinterface (0, 0)
	5 org/apache/commons/math3/linear/RealMatrix.org/apache/commons/math3/optimization/general/AbstractLeastSquaresOptimizer (0, 0)
	7 0 (0, 0)
	9 areturn (0, 0)

Method: setCost
	0 aload_0 (0, 0)
	1 dload_1 (0, 0)
	2 putfield (0, 0)
	3 org/apache/commons/math3/optimization/general/AbstractLeastSquaresOptimizer.cost:D (0, 0)
	5 return (0, 0)

Method: getCovariances
	0 aload_0 (0, 0)
	1 aload_0 (0, 0)
	2 getfield (0, 0)
	3 org/apache/commons/math3/optimization/general/AbstractLeastSquaresOptimizer.point:[D (0, 0)
	5 dload_1 (0, 0)
	6 invokevirtual (0, 0)
	7 org/apache/commons/math3/optimization/general/AbstractLeastSquaresOptimizer.computeCovariances:([DD)[[D (0, 0)
	9 areturn (0, 0)

Method: computeCovariances
	0 aload_0 (0, 0)
	1 aload_1 (0, 0)
	2 invokevirtual (0, 0)
	3 org/apache/commons/math3/optimization/general/AbstractLeastSquaresOptimizer.computeWeightedJacobian:([D)Lorg/apache/commons/math3/linear/RealMatrix; (0, 0)
	5 astore (0, 0)
	6 #4 (0, 0)
	7 aload (0, 0)
	8 #4 (0, 0)
	9 invokeinterface (0, 0)
	10 org/apache/commons/math3/linear/RealMatrix.org/apache/commons/math3/linear/QRDecomposition (0, 0)
	12 0 (0, 0)
	14 aload (0, 0)
	15 #4 (0, 0)
	16 invokeinterface (0, 0)
	17 org/apache/commons/math3/linear/RealMatrix.computeObjectiveValue:([D)[D (0, 0)
	19 0 (0, 0)
	21 astore (0, 0)
	22 #5 (0, 0)
	23 new (0, 0)
	24 org/apache/commons/math3/linear/QRDecomposition (0, 0)
	26 dup (0, 0)
	27 aload (0, 0)
	28 #5 (0, 0)
	29 dload_2 (0, 0)
	30 invokespecial (0, 0)
	31 org/apache/commons/math3/linear/QRDecomposition.<init>:(Lorg/apache/commons/math3/linear/RealMatrix;D)V (0, 0)
	33 invokevirtual (0, 0)
	34 org/apache/commons/math3/linear/QRDecomposition.getSolver:()Lorg/apache/commons/math3/linear/DecompositionSolver; (0, 0)
	36 astore (0, 0)
	37 #6 (0, 0)
	38 aload (0, 0)
	39 #6 (0, 0)
	40 invokeinterface (0, 0)
	41 org/apache/commons/math3/linear/DecompositionSolver.cols:I (0, 0)
	43 0 (0, 0)
	45 invokeinterface (0, 0)
	46 org/apache/commons/math3/linear/RealMatrix.weightedResidualJacobian:[[D (0, 0)
	48 0 (0, 0)
	50 areturn (0, 0)

Method: guessParametersErrors
	0 aload_0 (1, 1)
	1 getfield (1, 1)
	2 org/apache/commons/math3/optimization/general/AbstractLeastSquaresOptimizer.rows:I (1, 1)
	4 aload_0 (1, 1)
	5 getfield (1, 1)
	6 org/apache/commons/math3/optimization/general/AbstractLeastSquaresOptimizer.cols:I (1, 1)
	8 if_icmpgt (1, 1)
	9 29 (1, 1)
	11 new (1, 1)
	12 org/apache/commons/math3/exception/NumberIsTooSmallException (1, 1)
	14 dup (1, 1)
	15 getstatic (1, 1)
	16 org/apache/commons/math3/exception/util/LocalizedFormats.NO_DEGREES_OF_FREEDOM:Lorg/apache/commons/math3/exception/util/LocalizedFormats; (1, 1)
	18 aload_0 (1, 1)
	19 getfield (1, 1)
	20 org/apache/commons/math3/optimization/general/AbstractLeastSquaresOptimizer.rows:I (1, 1)
	22 invokestatic (1, 1)
	23 java/lang/Integer.valueOf:(I)Ljava/lang/Integer; (1, 1)
	25 aload_0 (1, 1)
	26 getfield (1, 1)
	27 org/apache/commons/math3/optimization/general/AbstractLeastSquaresOptimizer.cols:I (1, 1)
	29 invokestatic (1, 1)
	30 java/lang/Integer.valueOf:(I)Ljava/lang/Integer; (1, 1)
	32 iconst_0 (1, 1)
	33 invokespecial (1, 1)
	34 org/apache/commons/math3/exception/NumberIsTooSmallException.<init>:(Lorg/apache/commons/math3/exception/util/Localizable;Ljava/lang/Number;Ljava/lang/Number;Z)V (1, 1)
	36 athrow (1, 1)
	37 aload_0 (0, 0)
	38 getfield (0, 0)
	39 org/apache/commons/math3/optimization/general/AbstractLeastSquaresOptimizer.cols:I (0, 0)
	41 newarray (0, 0)
	42 7 (0, 0)
	43 astore_1 (0, 0)
	44 aload_0 (0, 0)
	45 invokevirtual (0, 0)
	46 org/apache/commons/math3/optimization/general/AbstractLeastSquaresOptimizer.getChiSquare:()D (0, 0)
	48 aload_0 (0, 0)
	49 getfield (0, 0)
	50 org/apache/commons/math3/optimization/general/AbstractLeastSquaresOptimizer.rows:I (0, 0)
	52 aload_0 (0, 0)
	53 getfield (0, 0)
	54 org/apache/commons/math3/optimization/general/AbstractLeastSquaresOptimizer.cols:I (0, 0)
	56 isub (0, 0)
	57 i2d (0, 0)
	58 ddiv (0, 0)
	59 invokestatic (0, 0)
	60 org/apache/commons/math3/util/FastMath.sqrt:(D)D (0, 0)
	62 dstore_2 (0, 0)
	63 aload_0 (0, 0)
	64 aload_0 (0, 0)
	65 getfield (0, 0)
	66 org/apache/commons/math3/optimization/general/AbstractLeastSquaresOptimizer.point:[D (0, 0)
	68 ldc2_w (0, 0)
	69 1e-14 (0, 0)
	71 invokevirtual (0, 0)
	72 org/apache/commons/math3/optimization/general/AbstractLeastSquaresOptimizer.computeCovariances:([DD)[[D (0, 0)
	74 astore (0, 0)
	75 #4 (0, 0)
	76 iconst_0 (1, 4)
	77 istore (1, 4)
	78 #5 (1, 4)
	79 iload (1, 4)
	80 #5 (1, 4)
	81 aload_1 (1, 4)
	82 arraylength (1, 4)
	83 if_icmpge (1, 4)
	84 26 (1, 4)
	86 aload_1 (1, 4)
	87 iload (1, 4)
	88 #5 (1, 4)
	89 aload (1, 4)
	90 #4 (1, 4)
	91 iload (1, 4)
	92 #5 (1, 4)
	93 aaload (1, 4)
	94 iload (1, 4)
	95 #5 (1, 4)
	96 daload (1, 4)
	97 invokestatic (1, 4)
	98 org/apache/commons/math3/util/FastMath.sqrt:(D)D (1, 4)
	100 dload_2 (1, 4)
	101 dmul (1, 4)
	102 dastore (1, 4)
	103 iinc (1, 4)
	104 #5 (1, 4)
	105 -89 (1, 4)
	106 goto (1, 4)
	107 -27 (1, 4)
	109 aload_1 (0, 0)
	110 areturn (0, 0)

Method: computeSigma
	0 aload_1 (0, 0)
	1 arraylength (0, 0)
	2 istore (0, 0)
	3 #4 (0, 0)
	4 iload (0, 0)
	5 #4 (0, 0)
	6 newarray (0, 0)
	7 7 (0, 0)
	8 astore (0, 0)
	9 #5 (0, 0)
	10 aload_0 (0, 0)
	11 aload_1 (0, 0)
	12 dload_2 (0, 0)
	13 invokevirtual (0, 0)
	14 org/apache/commons/math3/optimization/general/AbstractLeastSquaresOptimizer.computeCovariances:([DD)[[D (0, 0)
	16 astore (0, 0)
	17 #6 (0, 0)
	18 iconst_0 (1, 4)
	19 istore (1, 4)
	20 #7 (1, 4)
	21 iload (1, 4)
	22 #7 (1, 4)
	23 iload (1, 4)
	24 #4 (1, 4)
	25 if_icmpge (1, 4)
	26 25 (1, 4)
	28 aload (1, 4)
	29 #5 (1, 4)
	30 iload (1, 4)
	31 #7 (1, 4)
	32 aload (1, 4)
	33 #6 (1, 4)
	34 iload (1, 4)
	35 #7 (1, 4)
	36 aaload (1, 4)
	37 iload (1, 4)
	38 #7 (1, 4)
	39 daload (1, 4)
	40 invokestatic (1, 4)
	41 org/apache/commons/math3/util/FastMath.sqrt:(D)D (1, 4)
	43 dastore (1, 4)
	44 iinc (1, 4)
	45 #7 (1, 4)
	46 -89 (1, 4)
	47 goto (1, 4)
	48 -26 (1, 4)
	50 aload (0, 0)
	51 #5 (0, 0)
	52 areturn (0, 0)

Method: optimize
	0 aload_0 (0, 0)
	1 iload_1 (0, 0)
	2 aload_2 (0, 0)
	3 checkcast (0, 0)
	4 org/apache/commons/math3/analysis/DifferentiableMultivariateVectorFunction (0, 0)
	6 aload_3 (0, 0)
	7 aload (0, 0)
	8 #4 (0, 0)
	9 aload (0, 0)
	10 #5 (0, 0)
	11 invokevirtual (0, 0)
	12 org/apache/commons/math3/optimization/general/AbstractLeastSquaresOptimizer.optimize:(ILorg/apache/commons/math3/analysis/DifferentiableMultivariateVectorFunction;[D[D[D)Lorg/apache/commons/math3/optimization/PointVectorValuePair; (0, 0)
	14 areturn (0, 0)

Method: optimizeInternal
	0 aload_0 (1, 1)
	1 iload_1 (1, 1)
	2 aload_2 (1, 1)
	3 invokestatic (1, 1)
	4 org/apache/commons/math3/analysis/FunctionUtils.toDifferentiableMultivariateVectorFunction:(Lorg/apache/commons/math3/analysis/differentiation/MultivariateDifferentiableVectorFunction;)Lorg/apache/commons/math3/analysis/DifferentiableMultivariateVectorFunction; (1, 1)
	6 aload_3 (1, 1)
	7 invokespecial (1, 1)
	8 org/apache/commons/math3/optimization/direct/BaseAbstractMultivariateVectorOptimizer.optimizeInternal:(ILorg/apache/commons/math3/analysis/MultivariateVectorFunction;[Lorg/apache/commons/math3/optimization/OptimizationData;)Lorg/apache/commons/math3/optimization/PointVectorValuePair; (1, 1)
	10 areturn (0, 1)

Method: setUp
	0 aload_0 (0, 0)
	1 invokespecial (0, 0)
	2 org/apache/commons/math3/optimization/direct/BaseAbstractMultivariateVectorOptimizer.setUp:()V (0, 0)
	4 aload_0 (0, 0)
	5 iconst_0 (0, 0)
	6 putfield (0, 0)
	7 org/apache/commons/math3/optimization/general/AbstractLeastSquaresOptimizer.jacobianEvaluations:I (0, 0)
	9 aload_0 (0, 0)
	10 aload_0 (0, 0)
	11 aload_0 (0, 0)
	12 invokevirtual (0, 0)
	13 org/apache/commons/math3/optimization/general/AbstractLeastSquaresOptimizer.getWeight:()Lorg/apache/commons/math3/linear/RealMatrix; (0, 0)
	15 invokespecial (0, 0)
	16 org/apache/commons/math3/optimization/general/AbstractLeastSquaresOptimizer.squareRoot:(Lorg/apache/commons/math3/linear/RealMatrix;)Lorg/apache/commons/math3/linear/RealMatrix; (0, 0)
	18 putfield (0, 0)
	19 org/apache/commons/math3/optimization/general/AbstractLeastSquaresOptimizer.weightMatrixSqrt:Lorg/apache/commons/math3/linear/RealMatrix; (0, 0)
	21 aload_0 (2, 1)
	22 aload_0 (2, 1)
	23 invokevirtual (2, 1)
	24 org/apache/commons/math3/optimization/general/AbstractLeastSquaresOptimizer.getObjectiveFunction:()Lorg/apache/commons/math3/analysis/MultivariateVectorFunction; (2, 1)
	26 checkcast (2, 1)
	27 org/apache/commons/math3/analysis/DifferentiableMultivariateVectorFunction (2, 1)
	29 invokestatic (2, 1)
	30 org/apache/commons/math3/analysis/FunctionUtils.toMultivariateDifferentiableVectorFunction:(Lorg/apache/commons/math3/analysis/DifferentiableMultivariateVectorFunction;)Lorg/apache/commons/math3/analysis/differentiation/MultivariateDifferentiableVectorFunction; (2, 1)
	32 putfield (2, 1)
	33 org/apache/commons/math3/optimization/general/AbstractLeastSquaresOptimizer.jF:Lorg/apache/commons/math3/analysis/differentiation/MultivariateDifferentiableVectorFunction; (2, 1)
	35 aload_0 (2, 1)
	36 aload_0 (2, 1)
	37 invokevirtual (2, 1)
	38 org/apache/commons/math3/optimization/general/AbstractLeastSquaresOptimizer.getStartPoint:()[D (2, 1)
	40 putfield (2, 1)
	41 org/apache/commons/math3/optimization/general/AbstractLeastSquaresOptimizer.point:[D (2, 1)
	43 aload_0 (2, 1)
	44 aload_0 (2, 1)
	45 invokevirtual (2, 1)
	46 org/apache/commons/math3/optimization/general/AbstractLeastSquaresOptimizer.getTarget:()[D (2, 1)
	48 arraylength (2, 1)
	49 putfield (2, 1)
	50 org/apache/commons/math3/optimization/general/AbstractLeastSquaresOptimizer.rows:I (2, 1)
	52 aload_0 (2, 1)
	53 aload_0 (2, 1)
	54 getfield (2, 1)
	55 org/apache/commons/math3/optimization/general/AbstractLeastSquaresOptimizer.point:[D (2, 1)
	57 arraylength (2, 1)
	58 putfield (2, 1)
	59 org/apache/commons/math3/optimization/general/AbstractLeastSquaresOptimizer.cols:I (2, 1)
	61 return (0, 1)

Method: computeResiduals
	0 aload_0 (0, 0)
	1 invokevirtual (0, 0)
	2 org/apache/commons/math3/optimization/general/AbstractLeastSquaresOptimizer.getTarget:()[D (0, 0)
	4 astore_2 (0, 0)
	5 aload_1 (1, 1)
	6 arraylength (1, 1)
	7 aload_2 (1, 1)
	8 arraylength (1, 1)
	9 if_icmpeq (1, 1)
	10 15 (1, 1)
	12 new (1, 1)
	13 org/apache/commons/math3/exception/DimensionMismatchException (1, 1)
	15 dup (1, 1)
	16 aload_2 (1, 1)
	17 arraylength (1, 1)
	18 aload_1 (1, 1)
	19 arraylength (1, 1)
	20 invokespecial (1, 1)
	21 org/apache/commons/math3/exception/DimensionMismatchException.<init>:(II)V (1, 1)
	23 athrow (1, 1)
	24 aload_2 (0, 0)
	25 arraylength (0, 0)
	26 newarray (0, 0)
	27 7 (0, 0)
	28 astore_3 (0, 0)
	29 iconst_0 (1, 4)
	30 istore (1, 4)
	31 #4 (1, 4)
	32 iload (1, 4)
	33 #4 (1, 4)
	34 aload_2 (1, 4)
	35 arraylength (1, 4)
	36 if_icmpge (1, 4)
	37 22 (1, 4)
	39 aload_3 (1, 4)
	40 iload (1, 4)
	41 #4 (1, 4)
	42 aload_2 (1, 4)
	43 iload (1, 4)
	44 #4 (1, 4)
	45 daload (1, 4)
	46 aload_1 (1, 4)
	47 iload (1, 4)
	48 #4 (1, 4)
	49 daload (1, 4)
	50 dsub (1, 4)
	51 dastore (1, 4)
	52 iinc (1, 4)
	53 #4 (1, 4)
	54 -89 (1, 4)
	55 goto (1, 4)
	56 -23 (1, 4)
	58 aload_3 (0, 0)
	59 areturn (0, 0)

Method: squareRoot
	0 aload_1 (1, 1)
	1 instanceof (1, 1)
	2 org/apache/commons/math3/linear/DiagonalMatrix (1, 1)
	4 ifeq (1, 1)
	5 59 (1, 1)
	7 aload_1 (1, 1)
	8 invokeinterface (1, 1)
	9 org/apache/commons/math3/linear/RealMatrix.<init>:(I)V (1, 1)
	11 0 (1, 1)
	13 istore_2 (1, 1)
	14 new (1, 1)
	15 org/apache/commons/math3/linear/DiagonalMatrix (1, 1)
	17 dup (1, 1)
	18 iload_2 (1, 1)
	19 invokespecial (1, 1)
	20 org/apache/commons/math3/linear/DiagonalMatrix.<init>:(I)V (1, 1)
	22 astore_3 (1, 1)
	23 iconst_0 (2, 4)
	24 istore (2, 4)
	25 #4 (2, 4)
	26 iload (2, 4)
	27 #4 (2, 4)
	28 iload_2 (2, 4)
	29 if_icmpge (2, 4)
	30 32 (2, 4)
	32 aload_3 (2, 4)
	33 iload (2, 4)
	34 #4 (2, 4)
	35 iload (2, 4)
	36 #4 (2, 4)
	37 aload_1 (2, 4)
	38 iload (2, 4)
	39 #4 (2, 4)
	40 iload (2, 4)
	41 #4 (2, 4)
	42 invokeinterface (2, 4)
	43 org/apache/commons/math3/linear/RealMatrix.setEntry:(IID)V (2, 4)
	45 0 (2, 4)
	47 invokestatic (2, 4)
	48 org/apache/commons/math3/util/FastMath.sqrt:(D)D (2, 4)
	50 invokeinterface (2, 4)
	51 org/apache/commons/math3/linear/RealMatrix.org/apache/commons/math3/linear/EigenDecomposition (2, 4)
	53 0 (2, 4)
	55 iinc (2, 4)
	56 #4 (2, 4)
	57 -89 (2, 4)
	58 goto (2, 4)
	59 -32 (2, 4)
	61 aload_3 (1, 1)
	62 areturn (1, 1)
	63 new (2, 2)
	64 org/apache/commons/math3/linear/EigenDecomposition (2, 2)
	66 dup (2, 2)
	67 aload_1 (2, 2)
	68 invokespecial (2, 2)
	69 org/apache/commons/math3/linear/EigenDecomposition.<init>:(Lorg/apache/commons/math3/linear/RealMatrix;)V (2, 2)
	71 astore_2 (2, 2)
	72 aload_2 (2, 2)
	73 invokevirtual (2, 2)
	74 org/apache/commons/math3/linear/EigenDecomposition.getSquareRoot:()Lorg/apache/commons/math3/linear/RealMatrix; (2, 2)
	76 areturn (1, 2)

