Method: <init>
	0 aload_0 (0, 0)
	1 aload_2 (0, 0)
	2 invokespecial (0, 0)
	3 org/apache/commons/math3/optimization/general/AbstractLeastSquaresOptimizer.<init>:(Lorg/apache/commons/math3/optimization/ConvergenceChecker;)V (0, 0)
	5 aload_0 (0, 0)
	6 iload_1 (0, 0)
	7 putfield (0, 0)
	8 org/apache/commons/math3/optimization/general/GaussNewtonOptimizer.useLU:Z (0, 0)
	10 return (0, 0)

Method: doOptimize
	0 aload_0 (0, 0)
	1 invokevirtual (0, 0)
	2 org/apache/commons/math3/optimization/general/GaussNewtonOptimizer.getConvergenceChecker:()Lorg/apache/commons/math3/optimization/ConvergenceChecker; (0, 0)
	4 astore_1 (0, 0)
	5 aload_1 (1, 1)
	6 ifnonnull (1, 1)
	7 11 (1, 1)
	9 new (1, 1)
	10 org/apache/commons/math3/exception/NullArgumentException (1, 1)
	12 dup (1, 1)
	13 invokespecial (1, 1)
	14 org/apache/commons/math3/exception/NullArgumentException.<init>:()V (1, 1)
	16 athrow (1, 1)
	17 aload_0 (0, 4)
	18 invokevirtual (0, 4)
	19 org/apache/commons/math3/optimization/general/GaussNewtonOptimizer.getTarget:()[D (0, 4)
	21 astore_2 (0, 4)
	22 aload_2 (0, 4)
	23 arraylength (0, 4)
	24 istore_3 (0, 4)
	25 aload_0 (0, 4)
	26 invokevirtual (0, 4)
	27 org/apache/commons/math3/optimization/general/GaussNewtonOptimizer.getWeight:()Lorg/apache/commons/math3/linear/RealMatrix; (0, 4)
	29 astore (0, 4)
	30 #4 (0, 4)
	31 iload_3 (0, 4)
	32 newarray (0, 4)
	33 7 (0, 4)
	34 astore (0, 4)
	35 #5 (0, 4)
	36 iconst_0 (1, 4)
	37 istore (1, 4)
	38 #6 (1, 4)
	39 iload (1, 4)
	40 #6 (1, 4)
	41 iload_3 (1, 4)
	42 if_icmpge (1, 4)
	43 25 (1, 4)
	45 aload (1, 4)
	46 #5 (1, 4)
	47 iload (1, 4)
	48 #6 (1, 4)
	49 aload (1, 4)
	50 #4 (1, 4)
	51 iload (1, 4)
	52 #6 (1, 4)
	53 iload (1, 4)
	54 #6 (1, 4)
	55 invokeinterface (1, 4)
	56 org/apache/commons/math3/linear/RealMatrix.getStartPoint:()[D (1, 4)
	58 0 (1, 4)
	60 dastore (1, 4)
	61 iinc (1, 4)
	62 #6 (1, 4)
	63 -89 (1, 4)
	64 goto (1, 4)
	65 -25 (1, 4)
	67 aload_0 (0, 4)
	68 invokevirtual (0, 4)
	69 org/apache/commons/math3/optimization/general/GaussNewtonOptimizer.getStartPoint:()[D (0, 4)
	71 astore (0, 4)
	72 #6 (0, 4)
	73 aload (0, 4)
	74 #6 (0, 4)
	75 arraylength (0, 4)
	76 istore (0, 4)
	77 #7 (0, 4)
	78 aconst_null (0, 4)
	79 astore (0, 4)
	80 #8 (0, 4)
	81 iconst_0 (0, 4)
	82 istore (0, 4)
	83 #9 (0, 4)
	84 iconst_0 (1, 4)
	85 istore (1, 4)
	86 #10 (1, 4)
	87 iload (1, 4)
	88 #10 (1, 4)
	89 ifne (1, 4)
	90 374 (1, 4)
	92 iinc (1, 4)
	93 #9 (1, 4)
	94 25 (1, 4)
	95 aload (1, 4)
	96 #8 (1, 4)
	97 astore (1, 4)
	98 #11 (1, 4)
	99 aload_0 (1, 4)
	100 aload (1, 4)
	101 #6 (1, 4)
	102 invokevirtual (1, 4)
	103 org/apache/commons/math3/optimization/general/GaussNewtonOptimizer.computeObjectiveValue:([D)[D (1, 4)
	105 astore (1, 4)
	106 #12 (1, 4)
	107 aload_0 (1, 4)
	108 aload (1, 4)
	109 #12 (1, 4)
	110 invokevirtual (1, 4)
	111 org/apache/commons/math3/optimization/general/GaussNewtonOptimizer.computeResiduals:([D)[D (1, 4)
	113 astore (1, 4)
	114 #13 (1, 4)
	115 aload_0 (1, 4)
	116 aload (1, 4)
	117 #6 (1, 4)
	118 invokevirtual (1, 4)
	119 org/apache/commons/math3/optimization/general/GaussNewtonOptimizer.computeWeightedJacobian:([D)Lorg/apache/commons/math3/linear/RealMatrix; (1, 4)
	121 astore (1, 4)
	122 #14 (1, 4)
	123 new (1, 4)
	124 org/apache/commons/math3/optimization/PointVectorValuePair (1, 4)
	126 dup (1, 4)
	127 aload (1, 4)
	128 #6 (1, 4)
	129 aload (1, 4)
	130 #12 (1, 4)
	131 invokespecial (1, 4)
	132 org/apache/commons/math3/optimization/PointVectorValuePair.<init>:([D[D)V (1, 4)
	134 astore (1, 4)
	135 #8 (1, 4)
	136 iload (1, 4)
	137 #7 (1, 4)
	138 newarray (1, 4)
	139 7 (1, 4)
	140 astore (1, 4)
	141 #15 (1, 4)
	142 iload (1, 4)
	143 #7 (1, 4)
	144 iload (1, 4)
	145 #7 (1, 4)
	146 multianewarray (1, 4)
	147 [[D (1, 4)
	149 58 (1, 4)
	150 astore (1, 4)
	151 #16 (1, 4)
	152 iconst_0 (2, 4)
	153 istore (2, 4)
	154 #17 (2, 4)
	155 iload (2, 4)
	156 #17 (2, 4)
	157 iload_3 (2, 4)
	158 if_icmpge (2, 4)
	159 138 (2, 4)
	161 aload (2, 4)
	162 #14 (2, 4)
	163 iload (2, 4)
	164 #17 (2, 4)
	165 invokeinterface (2, 4)
	166 org/apache/commons/math3/linear/RealMatrix.org/apache/commons/math3/linear/BlockRealMatrix (2, 4)
	168 0 (2, 4)
	170 astore (2, 4)
	171 #18 (2, 4)
	172 aload (2, 4)
	173 #5 (2, 4)
	174 iload (2, 4)
	175 #17 (2, 4)
	176 daload (2, 4)
	177 dstore (2, 4)
	178 #19 (2, 4)
	179 aload (2, 4)
	180 #13 (2, 4)
	181 iload (2, 4)
	182 #17 (2, 4)
	183 daload (2, 4)
	184 dstore (2, 4)
	185 #21 (2, 4)
	186 dload (2, 4)
	187 #19 (2, 4)
	188 dload (2, 4)
	189 #21 (2, 4)
	190 dmul (2, 4)
	191 dstore (2, 4)
	192 #23 (2, 4)
	193 iconst_0 (3, 4)
	194 istore (3, 4)
	195 #25 (3, 4)
	196 iload (3, 4)
	197 #25 (3, 4)
	198 iload (3, 4)
	199 #7 (3, 4)
	200 if_icmpge (3, 4)
	201 25 (3, 4)
	203 aload (3, 4)
	204 #15 (3, 4)
	205 iload (3, 4)
	206 #25 (3, 4)
	207 dup2 (3, 4)
	208 daload (3, 4)
	209 dload (3, 4)
	210 #23 (3, 4)
	211 aload (3, 4)
	212 #18 (3, 4)
	213 iload (3, 4)
	214 #25 (3, 4)
	215 daload (3, 4)
	216 dmul (3, 4)
	217 dadd (3, 4)
	218 dastore (3, 4)
	219 iinc (3, 4)
	220 #25 (3, 4)
	221 -89 (3, 4)
	222 goto (3, 4)
	223 -26 (3, 4)
	225 iconst_0 (3, 4)
	226 istore (3, 4)
	227 #25 (3, 4)
	228 iload (3, 4)
	229 #25 (3, 4)
	230 iload (3, 4)
	231 #7 (3, 4)
	232 if_icmpge (3, 4)
	233 58 (3, 4)
	235 aload (3, 4)
	236 #16 (3, 4)
	237 iload (3, 4)
	238 #25 (3, 4)
	239 aaload (3, 4)
	240 astore (3, 4)
	241 #26 (3, 4)
	242 dload (3, 4)
	243 #19 (3, 4)
	244 aload (3, 4)
	245 #18 (3, 4)
	246 iload (3, 4)
	247 #25 (3, 4)
	248 daload (3, 4)
	249 dmul (3, 4)
	250 dstore (3, 4)
	251 #27 (3, 4)
	252 iconst_0 (4, 4)
	253 istore (4, 4)
	254 #29 (4, 4)
	255 iload (4, 4)
	256 #29 (4, 4)
	257 iload (4, 4)
	258 #7 (4, 4)
	259 if_icmpge (4, 4)
	260 25 (4, 4)
	262 aload (4, 4)
	263 #26 (4, 4)
	264 iload (4, 4)
	265 #29 (4, 4)
	266 dup2 (4, 4)
	267 daload (4, 4)
	268 dload (4, 4)
	269 #27 (4, 4)
	270 aload (4, 4)
	271 #18 (4, 4)
	272 iload (4, 4)
	273 #29 (4, 4)
	274 daload (4, 4)
	275 dmul (4, 4)
	276 dadd (4, 4)
	277 dastore (4, 4)
	278 iinc (4, 4)
	279 #29 (4, 4)
	280 -89 (4, 4)
	281 goto (4, 4)
	282 -26 (4, 4)
	284 iinc (4, 4)
	285 #25 (4, 4)
	286 -89 (4, 4)
	287 goto (4, 4)
	288 -59 (4, 4)
	290 iinc (4, 4)
	291 #17 (4, 4)
	292 -89 (4, 4)
	293 goto (4, 4)
	294 -138 (4, 4)
	296 new (3, 4)
	297 org/apache/commons/math3/linear/BlockRealMatrix (3, 4)
	299 dup (3, 4)
	300 aload (3, 4)
	301 #16 (3, 4)
	302 invokespecial (3, 4)
	303 org/apache/commons/math3/linear/BlockRealMatrix.<init>:([[D)V (3, 4)
	305 astore (3, 4)
	306 #17 (3, 4)
	307 aload_0 (3, 4)
	308 getfield (3, 4)
	309 org/apache/commons/math3/optimization/general/GaussNewtonOptimizer.useLU:Z (3, 4)
	311 ifeq (3, 4)
	312 18 (3, 4)
	314 new (3, 4)
	315 org/apache/commons/math3/linear/LUDecomposition (3, 4)
	317 dup (3, 4)
	318 aload (3, 4)
	319 #17 (3, 4)
	320 invokespecial (3, 4)
	321 org/apache/commons/math3/linear/LUDecomposition.<init>:(Lorg/apache/commons/math3/linear/RealMatrix;)V (3, 4)
	323 invokevirtual (3, 4)
	324 org/apache/commons/math3/linear/LUDecomposition.getSolver:()Lorg/apache/commons/math3/linear/DecompositionSolver; (3, 4)
	326 goto (3, 4)
	327 15 (3, 4)
	329 new (3, 4)
	330 org/apache/commons/math3/linear/QRDecomposition (3, 4)
	332 dup (3, 4)
	333 aload (3, 4)
	334 #17 (3, 4)
	335 invokespecial (3, 4)
	336 org/apache/commons/math3/linear/QRDecomposition.<init>:(Lorg/apache/commons/math3/linear/RealMatrix;)V (3, 4)
	338 invokevirtual (3, 4)
	339 org/apache/commons/math3/linear/QRDecomposition.getSolver:()Lorg/apache/commons/math3/linear/DecompositionSolver; (3, 4)
	341 astore (3, 4)
	342 #18 (3, 4)
	343 aload (3, 4)
	344 #18 (3, 4)
	345 new (3, 4)
	346 org/apache/commons/math3/linear/ArrayRealVector (3, 4)
	348 dup (3, 4)
	349 aload (3, 4)
	350 #15 (3, 4)
	351 iconst_0 (3, 4)
	352 invokespecial (3, 4)
	353 org/apache/commons/math3/linear/ArrayRealVector.<init>:([DZ)V (3, 4)
	355 invokeinterface (3, 4)
	356 org/apache/commons/math3/linear/DecompositionSolver.org/apache/commons/math3/linear/RealVector (3, 4)
	358 0 (3, 4)
	360 invokevirtual (3, 4)
	361 org/apache/commons/math3/linear/RealVector.toArray:()[D (3, 4)
	363 astore (3, 4)
	364 #19 (3, 4)
	365 iconst_0 (5, 4)
	366 istore (5, 4)
	367 #20 (5, 4)
	368 iload (5, 4)
	369 #20 (5, 4)
	370 iload (5, 4)
	371 #7 (5, 4)
	372 if_icmpge (5, 4)
	373 22 (5, 4)
	375 aload (5, 4)
	376 #6 (5, 4)
	377 iload (5, 4)
	378 #20 (5, 4)
	379 dup2 (5, 4)
	380 daload (5, 4)
	381 aload (5, 4)
	382 #19 (5, 4)
	383 iload (5, 4)
	384 #20 (5, 4)
	385 daload (5, 4)
	386 dadd (5, 4)
	387 dastore (5, 4)
	388 iinc (5, 4)
	389 #20 (5, 4)
	390 -89 (5, 4)
	391 goto (5, 4)
	392 -23 (5, 4)
	394 goto (3, 4)
	395 20 (3, 4)
	397 astore (3, 4)
	398 #17 (3, 4)
	399 new (3, 4)
	400 org/apache/commons/math3/exception/ConvergenceException (3, 4)
	402 dup (3, 4)
	403 getstatic (3, 4)
	404 org/apache/commons/math3/exception/util/LocalizedFormats.UNABLE_TO_SOLVE_SINGULAR_PROBLEM:Lorg/apache/commons/math3/exception/util/LocalizedFormats; (3, 4)
	406 iconst_0 (3, 4)
	407 anewarray (3, 4)
	408 java/lang/Object (3, 4)
	410 invokespecial (3, 4)
	411 org/apache/commons/math3/exception/ConvergenceException.<init>:(Lorg/apache/commons/math3/exception/util/Localizable;[Ljava/lang/Object;)V (3, 4)
	413 athrow (3, 4)
	414 aload (3, 1)
	415 #11 (3, 1)
	416 ifnull (3, 1)
	417 44 (3, 1)
	419 aload_1 (3, 1)
	420 iload (3, 1)
	421 #9 (3, 1)
	422 aload (3, 1)
	423 #11 (3, 1)
	424 aload (3, 1)
	425 #8 (3, 1)
	426 invokeinterface (3, 1)
	427 org/apache/commons/math3/optimization/ConvergenceChecker.computeCost:([D)D (3, 1)
	429 0 (3, 1)
	431 istore (3, 1)
	432 #10 (3, 1)
	433 iload (4, 1)
	434 #10 (4, 1)
	435 ifeq (4, 1)
	436 25 (4, 1)
	438 aload_0 (4, 1)
	439 aload_0 (4, 1)
	440 aload (4, 1)
	441 #13 (4, 1)
	442 invokevirtual (4, 1)
	443 org/apache/commons/math3/optimization/general/GaussNewtonOptimizer.computeCost:([D)D (4, 1)
	445 putfield (4, 1)
	446 org/apache/commons/math3/optimization/general/GaussNewtonOptimizer.cost:D (4, 1)
	448 aload_0 (4, 1)
	449 aload (4, 1)
	450 #8 (4, 1)
	451 invokevirtual (4, 1)
	452 org/apache/commons/math3/optimization/PointVectorValuePair.getPoint:()[D (4, 1)
	454 putfield (4, 1)
	455 org/apache/commons/math3/optimization/general/GaussNewtonOptimizer.point:[D (4, 1)
	457 aload (4, 1)
	458 #8 (4, 1)
	459 areturn (4, 1)
	460 goto (1, 4)
	461 -373 (1, 4)
	463 new (1, 4)
	464 org/apache/commons/math3/exception/MathInternalError (1, 4)
	466 dup (1, 4)
	467 invokespecial (1, 4)
	468 org/apache/commons/math3/exception/MathInternalError.<init>:()V (1, 4)
	470 athrow (1, 4)

