Method: <init>
	0 aload_0 (0, 0)
	1 aconst_null (0, 0)
	2 invokespecial (0, 0)
	3 org/apache/commons/math3/optimization/general/AbstractLeastSquaresOptimizer.<init>:(Lorg/apache/commons/math3/optimization/ConvergenceChecker;)V (0, 0)
	5 aload_0 (0, 0)
	6 dload_1 (0, 0)
	7 putfield (0, 0)
	8 org/apache/commons/math3/optimization/general/LevenbergMarquardtOptimizer.initialStepBoundFactor:D (0, 0)
	10 aload_0 (0, 0)
	11 dload_3 (0, 0)
	12 putfield (0, 0)
	13 org/apache/commons/math3/optimization/general/LevenbergMarquardtOptimizer.costRelativeTolerance:D (0, 0)
	15 aload_0 (0, 0)
	16 dload (0, 0)
	17 #5 (0, 0)
	18 putfield (0, 0)
	19 org/apache/commons/math3/optimization/general/LevenbergMarquardtOptimizer.parRelativeTolerance:D (0, 0)
	21 aload_0 (0, 0)
	22 dload (0, 0)
	23 #7 (0, 0)
	24 putfield (0, 0)
	25 org/apache/commons/math3/optimization/general/LevenbergMarquardtOptimizer.orthoTolerance:D (0, 0)
	27 aload_0 (0, 0)
	28 dload (0, 0)
	29 #9 (0, 0)
	30 putfield (0, 0)
	31 org/apache/commons/math3/optimization/general/LevenbergMarquardtOptimizer.qrRankingThreshold:D (0, 0)
	33 return (0, 0)

Method: doOptimize
	0 aload_0 (0, 0)
	1 invokevirtual (0, 0)
	2 org/apache/commons/math3/optimization/general/LevenbergMarquardtOptimizer.getTarget:()[D (0, 0)
	4 arraylength (0, 0)
	5 istore_1 (0, 0)
	6 aload_0 (0, 0)
	7 invokevirtual (0, 0)
	8 org/apache/commons/math3/optimization/general/LevenbergMarquardtOptimizer.getStartPoint:()[D (0, 0)
	10 astore_2 (0, 0)
	11 aload_2 (0, 0)
	12 arraylength (0, 0)
	13 istore_3 (0, 0)
	14 aload_0 (0, 0)
	15 iload_1 (0, 0)
	16 iload_3 (0, 0)
	17 invokestatic (0, 0)
	18 org/apache/commons/math3/util/FastMath.min:(II)I (0, 0)
	20 putfield (0, 0)
	21 org/apache/commons/math3/optimization/general/LevenbergMarquardtOptimizer.solvedCols:I (0, 0)
	23 aload_0 (0, 0)
	24 iload_3 (0, 0)
	25 newarray (0, 0)
	26 7 (0, 0)
	27 putfield (0, 0)
	28 org/apache/commons/math3/optimization/general/LevenbergMarquardtOptimizer.diagR:[D (0, 0)
	30 aload_0 (0, 0)
	31 iload_3 (0, 0)
	32 newarray (0, 0)
	33 7 (0, 0)
	34 putfield (0, 0)
	35 org/apache/commons/math3/optimization/general/LevenbergMarquardtOptimizer.jacNorm:[D (0, 0)
	37 aload_0 (0, 0)
	38 iload_3 (0, 0)
	39 newarray (0, 0)
	40 7 (0, 0)
	41 putfield (0, 0)
	42 org/apache/commons/math3/optimization/general/LevenbergMarquardtOptimizer.beta:[D (0, 0)
	44 aload_0 (0, 0)
	45 iload_3 (0, 0)
	46 newarray (0, 0)
	47 10 (0, 0)
	48 putfield (0, 0)
	49 org/apache/commons/math3/optimization/general/LevenbergMarquardtOptimizer.permutation:[I (0, 0)
	51 aload_0 (0, 0)
	52 iload_3 (0, 0)
	53 newarray (0, 0)
	54 7 (0, 0)
	55 putfield (0, 0)
	56 org/apache/commons/math3/optimization/general/LevenbergMarquardtOptimizer.lmDir:[D (0, 0)
	58 dconst_0 (0, 0)
	59 dstore (0, 0)
	60 #4 (0, 0)
	61 dconst_0 (0, 0)
	62 dstore (0, 0)
	63 #6 (0, 0)
	64 iload_3 (0, 0)
	65 newarray (0, 0)
	66 7 (0, 0)
	67 astore (0, 0)
	68 #8 (0, 0)
	69 iload_3 (0, 0)
	70 newarray (0, 0)
	71 7 (0, 0)
	72 astore (0, 0)
	73 #9 (0, 0)
	74 iload_1 (0, 0)
	75 newarray (0, 0)
	76 7 (0, 0)
	77 astore (0, 0)
	78 #10 (0, 0)
	79 iload_1 (0, 0)
	80 newarray (0, 0)
	81 7 (0, 0)
	82 astore (0, 0)
	83 #11 (0, 0)
	84 iload_1 (0, 0)
	85 newarray (0, 0)
	86 7 (0, 0)
	87 astore (0, 0)
	88 #12 (0, 0)
	89 iload_3 (0, 0)
	90 newarray (0, 0)
	91 7 (0, 0)
	92 astore (0, 0)
	93 #13 (0, 0)
	94 iload_3 (0, 0)
	95 newarray (0, 0)
	96 7 (0, 0)
	97 astore (0, 0)
	98 #14 (0, 0)
	99 iload_3 (0, 0)
	100 newarray (0, 0)
	101 7 (0, 0)
	102 astore (0, 0)
	103 #15 (0, 0)
	104 aload_0 (0, 0)
	105 invokevirtual (0, 0)
	106 org/apache/commons/math3/optimization/general/LevenbergMarquardtOptimizer.getWeightSquareRoot:()Lorg/apache/commons/math3/linear/RealMatrix; (0, 0)
	108 astore (0, 0)
	109 #16 (0, 0)
	110 aload_0 (0, 0)
	111 aload_2 (0, 0)
	112 invokevirtual (0, 0)
	113 org/apache/commons/math3/optimization/general/LevenbergMarquardtOptimizer.computeObjectiveValue:([D)[D (0, 0)
	115 astore (0, 0)
	116 #17 (0, 0)
	117 aload_0 (0, 0)
	118 aload (0, 0)
	119 #17 (0, 0)
	120 invokevirtual (0, 0)
	121 org/apache/commons/math3/optimization/general/LevenbergMarquardtOptimizer.computeResiduals:([D)[D (0, 0)
	123 astore (0, 0)
	124 #18 (0, 0)
	125 new (0, 0)
	126 org/apache/commons/math3/optimization/PointVectorValuePair (0, 0)
	128 dup (0, 0)
	129 aload_2 (0, 0)
	130 aload (0, 0)
	131 #17 (0, 0)
	132 invokespecial (0, 0)
	133 org/apache/commons/math3/optimization/PointVectorValuePair.<init>:([D[D)V (0, 0)
	135 astore (0, 0)
	136 #19 (0, 0)
	137 aload_0 (0, 0)
	138 aload (0, 0)
	139 #18 (0, 0)
	140 invokevirtual (0, 0)
	141 org/apache/commons/math3/optimization/general/LevenbergMarquardtOptimizer.computeCost:([D)D (0, 0)
	143 dstore (0, 0)
	144 #20 (0, 0)
	145 aload_0 (0, 0)
	146 dconst_0 (0, 0)
	147 putfield (0, 0)
	148 org/apache/commons/math3/optimization/general/LevenbergMarquardtOptimizer.lmPar:D (0, 0)
	150 iconst_1 (0, 0)
	151 istore (0, 0)
	152 #22 (0, 0)
	153 iconst_0 (0, 0)
	154 istore (0, 0)
	155 #23 (0, 0)
	156 aload_0 (0, 0)
	157 invokevirtual (0, 0)
	158 org/apache/commons/math3/optimization/general/LevenbergMarquardtOptimizer.getConvergenceChecker:()Lorg/apache/commons/math3/optimization/ConvergenceChecker; (0, 0)
	160 astore (0, 0)
	161 #24 (0, 0)
	162 iinc (1, 3)
	163 #23 (1, 3)
	164 25 (1, 3)
	165 aload (1, 3)
	166 #19 (1, 3)
	167 astore (1, 3)
	168 #25 (1, 3)
	169 aload_0 (1, 3)
	170 aload_0 (1, 3)
	171 aload_2 (1, 3)
	172 invokevirtual (1, 3)
	173 org/apache/commons/math3/optimization/general/LevenbergMarquardtOptimizer.computeWeightedJacobian:([D)Lorg/apache/commons/math3/linear/RealMatrix; (1, 3)
	175 invokespecial (1, 3)
	176 org/apache/commons/math3/optimization/general/LevenbergMarquardtOptimizer.qrDecomposition:(Lorg/apache/commons/math3/linear/RealMatrix;)V (1, 3)
	178 aload_0 (1, 3)
	179 aload (1, 3)
	180 #16 (1, 3)
	181 aload (1, 3)
	182 #18 (1, 3)
	183 invokeinterface (1, 3)
	184 org/apache/commons/math3/linear/RealMatrix.weightedResidual:[D (1, 3)
	186 0 (1, 3)
	188 putfield (1, 3)
	189 org/apache/commons/math3/optimization/general/LevenbergMarquardtOptimizer.weightedResidual:[D (1, 3)
	191 iconst_0 (2, 4)
	192 istore (2, 4)
	193 #26 (2, 4)
	194 iload (2, 4)
	195 #26 (2, 4)
	196 iload_1 (2, 4)
	197 if_icmpge (2, 4)
	198 21 (2, 4)
	200 aload (2, 4)
	201 #12 (2, 4)
	202 iload (2, 4)
	203 #26 (2, 4)
	204 aload_0 (2, 4)
	205 getfield (2, 4)
	206 org/apache/commons/math3/optimization/general/LevenbergMarquardtOptimizer.weightedResidual:[D (2, 4)
	208 iload (2, 4)
	209 #26 (2, 4)
	210 daload (2, 4)
	211 dastore (2, 4)
	212 iinc (2, 4)
	213 #26 (2, 4)
	214 -89 (2, 4)
	215 goto (2, 4)
	216 -21 (2, 4)
	218 aload_0 (1, 3)
	219 aload (1, 3)
	220 #12 (1, 3)
	221 invokespecial (1, 3)
	222 org/apache/commons/math3/optimization/general/LevenbergMarquardtOptimizer.qTy:([D)V (1, 3)
	224 iconst_0 (2, 4)
	225 istore (2, 4)
	226 #26 (2, 4)
	227 iload (2, 4)
	228 #26 (2, 4)
	229 aload_0 (2, 4)
	230 getfield (2, 4)
	231 org/apache/commons/math3/optimization/general/LevenbergMarquardtOptimizer.solvedCols:I (2, 4)
	233 if_icmpge (2, 4)
	234 35 (2, 4)
	236 aload_0 (2, 4)
	237 getfield (2, 4)
	238 org/apache/commons/math3/optimization/general/LevenbergMarquardtOptimizer.permutation:[I (2, 4)
	240 iload (2, 4)
	241 #26 (2, 4)
	242 iaload (2, 4)
	243 istore (2, 4)
	244 #27 (2, 4)
	245 aload_0 (2, 4)
	246 getfield (2, 4)
	247 org/apache/commons/math3/optimization/general/LevenbergMarquardtOptimizer.weightedJacobian:[[D (2, 4)
	249 iload (2, 4)
	250 #26 (2, 4)
	251 aaload (2, 4)
	252 iload (2, 4)
	253 #27 (2, 4)
	254 aload_0 (2, 4)
	255 getfield (2, 4)
	256 org/apache/commons/math3/optimization/general/LevenbergMarquardtOptimizer.diagR:[D (2, 4)
	258 iload (2, 4)
	259 #27 (2, 4)
	260 daload (2, 4)
	261 dastore (2, 4)
	262 iinc (2, 4)
	263 #26 (2, 4)
	264 -89 (2, 4)
	265 goto (2, 4)
	266 -38 (2, 4)
	268 iload (2, 1)
	269 #22 (2, 1)
	270 ifeq (2, 1)
	271 96 (2, 1)
	273 dconst_0 (2, 1)
	274 dstore (2, 1)
	275 #6 (2, 1)
	276 iconst_0 (3, 4)
	277 istore (3, 4)
	278 #26 (3, 4)
	279 iload (3, 4)
	280 #26 (3, 4)
	281 iload_3 (3, 4)
	282 if_icmpge (3, 4)
	283 54 (3, 4)
	285 aload_0 (3, 4)
	286 getfield (3, 4)
	287 org/apache/commons/math3/optimization/general/LevenbergMarquardtOptimizer.jacNorm:[D (3, 4)
	289 iload (3, 4)
	290 #26 (3, 4)
	291 daload (3, 4)
	292 dstore (3, 4)
	293 #27 (3, 4)
	294 dload (4, 1)
	295 #27 (4, 1)
	296 dconst_0 (4, 1)
	297 dcmpl (4, 1)
	298 ifne (4, 1)
	299 6 (4, 1)
	301 dconst_1 (4, 1)
	302 dstore (4, 1)
	303 #27 (4, 1)
	304 dload (3, 4)
	305 #27 (3, 4)
	306 aload_2 (3, 4)
	307 iload (3, 4)
	308 #26 (3, 4)
	309 daload (3, 4)
	310 dmul (3, 4)
	311 dstore (3, 4)
	312 #29 (3, 4)
	313 dload (3, 4)
	314 #6 (3, 4)
	315 dload (3, 4)
	316 #29 (3, 4)
	317 dload (3, 4)
	318 #29 (3, 4)
	319 dmul (3, 4)
	320 dadd (3, 4)
	321 dstore (3, 4)
	322 #6 (3, 4)
	323 aload (3, 4)
	324 #8 (3, 4)
	325 iload (3, 4)
	326 #26 (3, 4)
	327 dload (3, 4)
	328 #27 (3, 4)
	329 dastore (3, 4)
	330 iinc (3, 4)
	331 #26 (3, 4)
	332 -89 (3, 4)
	333 goto (3, 4)
	334 -54 (3, 4)
	336 dload (2, 1)
	337 #6 (2, 1)
	338 invokestatic (2, 1)
	339 org/apache/commons/math3/util/FastMath.sqrt:(D)D (2, 1)
	341 dstore (2, 1)
	342 #6 (2, 1)
	343 dload (2, 1)
	344 #6 (2, 1)
	345 dconst_0 (2, 1)
	346 dcmpl (2, 1)
	347 ifne (2, 1)
	348 10 (2, 1)
	350 aload_0 (2, 1)
	351 getfield (2, 1)
	352 org/apache/commons/math3/optimization/general/LevenbergMarquardtOptimizer.initialStepBoundFactor:D (2, 1)
	354 goto (2, 1)
	355 10 (2, 1)
	357 aload_0 (2, 1)
	358 getfield (2, 1)
	359 org/apache/commons/math3/optimization/general/LevenbergMarquardtOptimizer.initialStepBoundFactor:D (2, 1)
	361 dload (2, 1)
	362 #6 (2, 1)
	363 dmul (2, 1)
	364 dstore (2, 1)
	365 #4 (2, 1)
	366 dconst_0 (1, 3)
	367 dstore (1, 3)
	368 #26 (1, 3)
	369 dload (2, 1)
	370 #20 (2, 1)
	371 dconst_0 (2, 1)
	372 dcmpl (2, 1)
	373 ifeq (2, 1)
	374 104 (2, 1)
	376 iconst_0 (3, 4)
	377 istore (3, 4)
	378 #28 (3, 4)
	379 iload (3, 4)
	380 #28 (3, 4)
	381 aload_0 (3, 4)
	382 getfield (3, 4)
	383 org/apache/commons/math3/optimization/general/LevenbergMarquardtOptimizer.solvedCols:I (3, 4)
	385 if_icmpge (3, 4)
	386 92 (3, 4)
	388 aload_0 (3, 4)
	389 getfield (3, 4)
	390 org/apache/commons/math3/optimization/general/LevenbergMarquardtOptimizer.permutation:[I (3, 4)
	392 iload (3, 4)
	393 #28 (3, 4)
	394 iaload (3, 4)
	395 istore (3, 4)
	396 #29 (3, 4)
	397 aload_0 (3, 4)
	398 getfield (3, 4)
	399 org/apache/commons/math3/optimization/general/LevenbergMarquardtOptimizer.jacNorm:[D (3, 4)
	401 iload (3, 4)
	402 #29 (3, 4)
	403 daload (3, 4)
	404 dstore (3, 4)
	405 #30 (3, 4)
	406 dload (4, 1)
	407 #30 (4, 1)
	408 dconst_0 (4, 1)
	409 dcmpl (4, 1)
	410 ifeq (4, 1)
	411 61 (4, 1)
	413 dconst_0 (4, 1)
	414 dstore (4, 1)
	415 #32 (4, 1)
	416 iconst_0 (5, 4)
	417 istore (5, 4)
	418 #34 (5, 4)
	419 iload (5, 4)
	420 #34 (5, 4)
	421 iload (5, 4)
	422 #28 (5, 4)
	423 if_icmpgt (5, 4)
	424 30 (5, 4)
	426 dload (5, 4)
	427 #32 (5, 4)
	428 aload_0 (5, 4)
	429 getfield (5, 4)
	430 org/apache/commons/math3/optimization/general/LevenbergMarquardtOptimizer.weightedJacobian:[[D (5, 4)
	432 iload (5, 4)
	433 #34 (5, 4)
	434 aaload (5, 4)
	435 iload (5, 4)
	436 #29 (5, 4)
	437 daload (5, 4)
	438 aload (5, 4)
	439 #12 (5, 4)
	440 iload (5, 4)
	441 #34 (5, 4)
	442 daload (5, 4)
	443 dmul (5, 4)
	444 dadd (5, 4)
	445 dstore (5, 4)
	446 #32 (5, 4)
	447 iinc (5, 4)
	448 #34 (5, 4)
	449 -89 (5, 4)
	450 goto (5, 4)
	451 -31 (5, 4)
	453 dload (4, 1)
	454 #26 (4, 1)
	455 dload (4, 1)
	456 #32 (4, 1)
	457 invokestatic (4, 1)
	458 org/apache/commons/math3/util/FastMath.abs:(D)D (4, 1)
	460 dload (4, 1)
	461 #30 (4, 1)
	462 dload (4, 1)
	463 #20 (4, 1)
	464 dmul (4, 1)
	465 ddiv (4, 1)
	466 invokestatic (4, 1)
	467 org/apache/commons/math3/util/FastMath.max:(DD)D (4, 1)
	469 dstore (4, 1)
	470 #26 (4, 1)
	471 iinc (4, 1)
	472 #28 (4, 1)
	473 -89 (4, 1)
	474 goto (4, 1)
	475 -95 (4, 1)
	477 dload (3, 1)
	478 #26 (3, 1)
	479 aload_0 (3, 1)
	480 getfield (3, 1)
	481 org/apache/commons/math3/optimization/general/LevenbergMarquardtOptimizer.orthoTolerance:D (3, 1)
	483 dcmpg (3, 1)
	484 ifgt (3, 1)
	485 21 (3, 1)
	487 aload_0 (3, 1)
	488 dload (3, 1)
	489 #20 (3, 1)
	490 invokevirtual (3, 1)
	491 org/apache/commons/math3/optimization/general/LevenbergMarquardtOptimizer.setCost:(D)V (3, 1)
	493 aload_0 (3, 1)
	494 aload (3, 1)
	495 #19 (3, 1)
	496 invokevirtual (3, 1)
	497 org/apache/commons/math3/optimization/PointVectorValuePair.getPoint:()[D (3, 1)
	499 putfield (3, 1)
	500 org/apache/commons/math3/optimization/general/LevenbergMarquardtOptimizer.point:[D (3, 1)
	502 aload (3, 1)
	503 #19 (3, 1)
	504 areturn (3, 1)
	505 iconst_0 (4, 4)
	506 istore (4, 4)
	507 #28 (4, 4)
	508 iload (4, 4)
	509 #28 (4, 4)
	510 iload_3 (4, 4)
	511 if_icmpge (4, 4)
	512 29 (4, 4)
	514 aload (4, 4)
	515 #8 (4, 4)
	516 iload (4, 4)
	517 #28 (4, 4)
	518 aload (4, 4)
	519 #8 (4, 4)
	520 iload (4, 4)
	521 #28 (4, 4)
	522 daload (4, 4)
	523 aload_0 (4, 4)
	524 getfield (4, 4)
	525 org/apache/commons/math3/optimization/general/LevenbergMarquardtOptimizer.jacNorm:[D (4, 4)
	527 iload (4, 4)
	528 #28 (4, 4)
	529 daload (4, 4)
	530 invokestatic (4, 4)
	531 org/apache/commons/math3/util/FastMath.max:(DD)D (4, 4)
	533 dastore (4, 4)
	534 iinc (4, 4)
	535 #28 (4, 4)
	536 -89 (4, 4)
	537 goto (4, 4)
	538 -29 (4, 4)
	540 dconst_0 (4, 4)
	541 dstore (4, 4)
	542 #28 (4, 4)
	543 dload (4, 4)
	544 #28 (4, 4)
	545 ldc2_w (4, 4)
	546 0.0001 (4, 4)
	548 dcmpg (4, 4)
	549 ifge (4, 4)
	550 949 (4, 4)
	552 iconst_0 (5, 4)
	553 istore (5, 4)
	554 #30 (5, 4)
	555 iload (5, 4)
	556 #30 (5, 4)
	557 aload_0 (5, 4)
	558 getfield (5, 4)
	559 org/apache/commons/math3/optimization/general/LevenbergMarquardtOptimizer.solvedCols:I (5, 4)
	561 if_icmpge (5, 4)
	562 27 (5, 4)
	564 aload_0 (5, 4)
	565 getfield (5, 4)
	566 org/apache/commons/math3/optimization/general/LevenbergMarquardtOptimizer.permutation:[I (5, 4)
	568 iload (5, 4)
	569 #30 (5, 4)
	570 iaload (5, 4)
	571 istore (5, 4)
	572 #31 (5, 4)
	573 aload (5, 4)
	574 #9 (5, 4)
	575 iload (5, 4)
	576 #31 (5, 4)
	577 aload_2 (5, 4)
	578 iload (5, 4)
	579 #31 (5, 4)
	580 daload (5, 4)
	581 dastore (5, 4)
	582 iinc (5, 4)
	583 #30 (5, 4)
	584 -89 (5, 4)
	585 goto (5, 4)
	586 -30 (5, 4)
	588 dload (4, 4)
	589 #20 (4, 4)
	590 dstore (4, 4)
	591 #30 (4, 4)
	592 aload_0 (4, 4)
	593 getfield (4, 4)
	594 org/apache/commons/math3/optimization/general/LevenbergMarquardtOptimizer.weightedResidual:[D (4, 4)
	596 astore (4, 4)
	597 #32 (4, 4)
	598 aload_0 (4, 4)
	599 aload (4, 4)
	600 #10 (4, 4)
	601 putfield (4, 4)
	602 org/apache/commons/math3/optimization/general/LevenbergMarquardtOptimizer.weightedResidual:[D (4, 4)
	604 aload (4, 4)
	605 #32 (4, 4)
	606 astore (4, 4)
	607 #10 (4, 4)
	608 aload (4, 4)
	609 #17 (4, 4)
	610 astore (4, 4)
	611 #32 (4, 4)
	612 aload (4, 4)
	613 #11 (4, 4)
	614 astore (4, 4)
	615 #17 (4, 4)
	616 aload (4, 4)
	617 #32 (4, 4)
	618 astore (4, 4)
	619 #11 (4, 4)
	620 aload_0 (4, 4)
	621 aload (4, 4)
	622 #12 (4, 4)
	623 dload (4, 4)
	624 #4 (4, 4)
	625 aload (4, 4)
	626 #8 (4, 4)
	627 aload (4, 4)
	628 #13 (4, 4)
	629 aload (4, 4)
	630 #14 (4, 4)
	631 aload (4, 4)
	632 #15 (4, 4)
	633 invokespecial (4, 4)
	634 org/apache/commons/math3/optimization/general/LevenbergMarquardtOptimizer.determineLMParameter:([DD[D[D[D[D)V (4, 4)
	636 dconst_0 (4, 4)
	637 dstore (4, 4)
	638 #33 (4, 4)
	639 iconst_0 (5, 4)
	640 istore (5, 4)
	641 #35 (5, 4)
	642 iload (5, 4)
	643 #35 (5, 4)
	644 aload_0 (5, 4)
	645 getfield (5, 4)
	646 org/apache/commons/math3/optimization/general/LevenbergMarquardtOptimizer.solvedCols:I (5, 4)
	648 if_icmpge (5, 4)
	649 75 (5, 4)
	651 aload_0 (5, 4)
	652 getfield (5, 4)
	653 org/apache/commons/math3/optimization/general/LevenbergMarquardtOptimizer.permutation:[I (5, 4)
	655 iload (5, 4)
	656 #35 (5, 4)
	657 iaload (5, 4)
	658 istore (5, 4)
	659 #36 (5, 4)
	660 aload_0 (5, 4)
	661 getfield (5, 4)
	662 org/apache/commons/math3/optimization/general/LevenbergMarquardtOptimizer.lmDir:[D (5, 4)
	664 iload (5, 4)
	665 #36 (5, 4)
	666 aload_0 (5, 4)
	667 getfield (5, 4)
	668 org/apache/commons/math3/optimization/general/LevenbergMarquardtOptimizer.lmDir:[D (5, 4)
	670 iload (5, 4)
	671 #36 (5, 4)
	672 daload (5, 4)
	673 dneg (5, 4)
	674 dastore (5, 4)
	675 aload_2 (5, 4)
	676 iload (5, 4)
	677 #36 (5, 4)
	678 aload (5, 4)
	679 #9 (5, 4)
	680 iload (5, 4)
	681 #36 (5, 4)
	682 daload (5, 4)
	683 aload_0 (5, 4)
	684 getfield (5, 4)
	685 org/apache/commons/math3/optimization/general/LevenbergMarquardtOptimizer.lmDir:[D (5, 4)
	687 iload (5, 4)
	688 #36 (5, 4)
	689 daload (5, 4)
	690 dadd (5, 4)
	691 dastore (5, 4)
	692 aload (5, 4)
	693 #8 (5, 4)
	694 iload (5, 4)
	695 #36 (5, 4)
	696 daload (5, 4)
	697 aload_0 (5, 4)
	698 getfield (5, 4)
	699 org/apache/commons/math3/optimization/general/LevenbergMarquardtOptimizer.lmDir:[D (5, 4)
	701 iload (5, 4)
	702 #36 (5, 4)
	703 daload (5, 4)
	704 dmul (5, 4)
	705 dstore (5, 4)
	706 #37 (5, 4)
	707 dload (5, 4)
	708 #33 (5, 4)
	709 dload (5, 4)
	710 #37 (5, 4)
	711 dload (5, 4)
	712 #37 (5, 4)
	713 dmul (5, 4)
	714 dadd (5, 4)
	715 dstore (5, 4)
	716 #33 (5, 4)
	717 iinc (5, 4)
	718 #35 (5, 4)
	719 -89 (5, 4)
	720 goto (5, 4)
	721 -78 (5, 4)
	723 dload (4, 4)
	724 #33 (4, 4)
	725 invokestatic (4, 4)
	726 org/apache/commons/math3/util/FastMath.sqrt:(D)D (4, 4)
	728 dstore (4, 4)
	729 #33 (4, 4)
	730 iload (5, 1)
	731 #22 (5, 1)
	732 ifeq (5, 1)
	733 12 (5, 1)
	735 dload (5, 1)
	736 #4 (5, 1)
	737 dload (5, 1)
	738 #33 (5, 1)
	739 invokestatic (5, 1)
	740 org/apache/commons/math3/util/FastMath.min:(DD)D (5, 1)
	742 dstore (5, 1)
	743 #4 (5, 1)
	744 aload_0 (4, 4)
	745 aload_2 (4, 4)
	746 invokevirtual (4, 4)
	747 org/apache/commons/math3/optimization/general/LevenbergMarquardtOptimizer.computeObjectiveValue:([D)[D (4, 4)
	749 astore (4, 4)
	750 #17 (4, 4)
	751 aload_0 (4, 4)
	752 aload (4, 4)
	753 #17 (4, 4)
	754 invokevirtual (4, 4)
	755 org/apache/commons/math3/optimization/general/LevenbergMarquardtOptimizer.computeResiduals:([D)[D (4, 4)
	757 astore (4, 4)
	758 #18 (4, 4)
	759 new (4, 4)
	760 org/apache/commons/math3/optimization/PointVectorValuePair (4, 4)
	762 dup (4, 4)
	763 aload_2 (4, 4)
	764 aload (4, 4)
	765 #17 (4, 4)
	766 invokespecial (4, 4)
	767 org/apache/commons/math3/optimization/PointVectorValuePair.<init>:([D[D)V (4, 4)
	769 astore (4, 4)
	770 #19 (4, 4)
	771 aload_0 (4, 4)
	772 aload (4, 4)
	773 #18 (4, 4)
	774 invokevirtual (4, 4)
	775 org/apache/commons/math3/optimization/general/LevenbergMarquardtOptimizer.computeCost:([D)D (4, 4)
	777 dstore (4, 4)
	778 #20 (4, 4)
	779 ldc2_w (4, 4)
	780 -1.0 (4, 4)
	782 dstore (4, 4)
	783 #35 (4, 4)
	784 ldc2_w (5, 1)
	785 0.1 (5, 1)
	787 dload (5, 1)
	788 #20 (5, 1)
	789 dmul (5, 1)
	790 dload (5, 1)
	791 #30 (5, 1)
	792 dcmpg (5, 1)
	793 ifge (5, 1)
	794 19 (5, 1)
	796 dload (5, 1)
	797 #20 (5, 1)
	798 dload (5, 1)
	799 #30 (5, 1)
	800 ddiv (5, 1)
	801 dstore (5, 1)
	802 #37 (5, 1)
	803 dconst_1 (5, 1)
	804 dload (5, 1)
	805 #37 (5, 1)
	806 dload (5, 1)
	807 #37 (5, 1)
	808 dmul (5, 1)
	809 dsub (5, 1)
	810 dstore (5, 1)
	811 #35 (5, 1)
	812 iconst_0 (5, 4)
	813 istore (5, 4)
	814 #37 (5, 4)
	815 iload (5, 4)
	816 #37 (5, 4)
	817 aload_0 (5, 4)
	818 getfield (5, 4)
	819 org/apache/commons/math3/optimization/general/LevenbergMarquardtOptimizer.solvedCols:I (5, 4)
	821 if_icmpge (5, 4)
	822 70 (5, 4)
	824 aload_0 (5, 4)
	825 getfield (5, 4)
	826 org/apache/commons/math3/optimization/general/LevenbergMarquardtOptimizer.permutation:[I (5, 4)
	828 iload (5, 4)
	829 #37 (5, 4)
	830 iaload (5, 4)
	831 istore (5, 4)
	832 #38 (5, 4)
	833 aload_0 (5, 4)
	834 getfield (5, 4)
	835 org/apache/commons/math3/optimization/general/LevenbergMarquardtOptimizer.lmDir:[D (5, 4)
	837 iload (5, 4)
	838 #38 (5, 4)
	839 daload (5, 4)
	840 dstore (5, 4)
	841 #39 (5, 4)
	842 aload (5, 4)
	843 #13 (5, 4)
	844 iload (5, 4)
	845 #37 (5, 4)
	846 dconst_0 (5, 4)
	847 dastore (5, 4)
	848 iconst_0 (6, 4)
	849 istore (6, 4)
	850 #41 (6, 4)
	851 iload (6, 4)
	852 #41 (6, 4)
	853 iload (6, 4)
	854 #37 (6, 4)
	855 if_icmpgt (6, 4)
	856 30 (6, 4)
	858 aload (6, 4)
	859 #13 (6, 4)
	860 iload (6, 4)
	861 #41 (6, 4)
	862 dup2 (6, 4)
	863 daload (6, 4)
	864 aload_0 (6, 4)
	865 getfield (6, 4)
	866 org/apache/commons/math3/optimization/general/LevenbergMarquardtOptimizer.weightedJacobian:[[D (6, 4)
	868 iload (6, 4)
	869 #41 (6, 4)
	870 aaload (6, 4)
	871 iload (6, 4)
	872 #38 (6, 4)
	873 daload (6, 4)
	874 dload (6, 4)
	875 #39 (6, 4)
	876 dmul (6, 4)
	877 dadd (6, 4)
	878 dastore (6, 4)
	879 iinc (6, 4)
	880 #41 (6, 4)
	881 -89 (6, 4)
	882 goto (6, 4)
	883 -31 (6, 4)
	885 iinc (6, 4)
	886 #37 (6, 4)
	887 -89 (6, 4)
	888 goto (6, 4)
	889 -73 (6, 4)
	891 dconst_0 (5, 4)
	892 dstore (5, 4)
	893 #37 (5, 4)
	894 iconst_0 (6, 4)
	895 istore (6, 4)
	896 #39 (6, 4)
	897 iload (6, 4)
	898 #39 (6, 4)
	899 aload_0 (6, 4)
	900 getfield (6, 4)
	901 org/apache/commons/math3/optimization/general/LevenbergMarquardtOptimizer.solvedCols:I (6, 4)
	903 if_icmpge (6, 4)
	904 25 (6, 4)
	906 dload (6, 4)
	907 #37 (6, 4)
	908 aload (6, 4)
	909 #13 (6, 4)
	910 iload (6, 4)
	911 #39 (6, 4)
	912 daload (6, 4)
	913 aload (6, 4)
	914 #13 (6, 4)
	915 iload (6, 4)
	916 #39 (6, 4)
	917 daload (6, 4)
	918 dmul (6, 4)
	919 dadd (6, 4)
	920 dstore (6, 4)
	921 #37 (6, 4)
	922 iinc (6, 4)
	923 #39 (6, 4)
	924 -89 (6, 4)
	925 goto (6, 4)
	926 -28 (6, 4)
	928 dload (5, 4)
	929 #30 (5, 4)
	930 dload (5, 4)
	931 #30 (5, 4)
	932 dmul (5, 4)
	933 dstore (5, 4)
	934 #39 (5, 4)
	935 dload (5, 4)
	936 #37 (5, 4)
	937 dload (5, 4)
	938 #39 (5, 4)
	939 ddiv (5, 4)
	940 dstore (5, 4)
	941 #37 (5, 4)
	942 aload_0 (5, 4)
	943 getfield (5, 4)
	944 org/apache/commons/math3/optimization/general/LevenbergMarquardtOptimizer.lmPar:D (5, 4)
	946 dload (5, 4)
	947 #33 (5, 4)
	948 dmul (5, 4)
	949 dload (5, 4)
	950 #33 (5, 4)
	951 dmul (5, 4)
	952 dload (5, 4)
	953 #39 (5, 4)
	954 ddiv (5, 4)
	955 dstore (5, 4)
	956 #41 (5, 4)
	957 dload (5, 4)
	958 #37 (5, 4)
	959 ldc2_w (5, 4)
	960 2.0 (5, 4)
	962 dload (5, 4)
	963 #41 (5, 4)
	964 dmul (5, 4)
	965 dadd (5, 4)
	966 dstore (5, 4)
	967 #43 (5, 4)
	968 dload (5, 4)
	969 #37 (5, 4)
	970 dload (5, 4)
	971 #41 (5, 4)
	972 dadd (5, 4)
	973 dneg (5, 4)
	974 dstore (5, 4)
	975 #45 (5, 4)
	976 dload (5, 4)
	977 #43 (5, 4)
	978 dconst_0 (5, 4)
	979 dcmpl (5, 4)
	980 ifne (5, 4)
	981 7 (5, 4)
	983 dconst_0 (5, 4)
	984 goto (5, 4)
	985 8 (5, 4)
	987 dload (5, 4)
	988 #35 (5, 4)
	989 dload (5, 4)
	990 #43 (5, 4)
	991 ddiv (5, 4)
	992 dstore (5, 4)
	993 #28 (5, 4)
	994 dload (6, 1)
	995 #28 (6, 1)
	996 ldc2_w (6, 1)
	997 0.25 (6, 1)
	999 dcmpg (6, 1)
	1000 ifgt (6, 1)
	1001 90 (6, 1)
	1003 dload (6, 1)
	1004 #35 (6, 1)
	1005 dconst_0 (6, 1)
	1006 dcmpg (6, 1)
	1007 ifge (6, 1)
	1008 22 (6, 1)
	1010 ldc2_w (6, 1)
	1011 0.5 (6, 1)
	1013 dload (6, 1)
	1014 #45 (6, 1)
	1015 dmul (6, 1)
	1016 dload (6, 1)
	1017 #45 (6, 1)
	1018 ldc2_w (6, 1)
	1019 0.5 (6, 1)
	1021 dload (6, 1)
	1022 #35 (6, 1)
	1023 dmul (6, 1)
	1024 dadd (6, 1)
	1025 ddiv (6, 1)
	1026 goto (6, 1)
	1027 6 (6, 1)
	1029 ldc2_w (6, 1)
	1030 0.5 (6, 1)
	1032 dstore (6, 1)
	1033 #47 (6, 1)
	1034 ldc2_w (7, 1)
	1035 0.1 (7, 1)
	1037 dload (7, 1)
	1038 #20 (7, 1)
	1039 dmul (7, 1)
	1040 dload (7, 1)
	1041 #30 (7, 1)
	1042 dcmpl (7, 1)
	1043 ifge (7, 1)
	1044 12 (7, 1)
	1046 dload (7, 1)
	1047 #47 (7, 1)
	1048 ldc2_w (7, 1)
	1049 0.1 (7, 1)
	1051 dcmpg (7, 1)
	1052 ifge (7, 1)
	1053 8 (7, 1)
	1055 ldc2_w (7, 1)
	1056 0.1 (7, 1)
	1058 dstore (7, 1)
	1059 #47 (7, 1)
	1060 dload (6, 1)
	1061 #47 (6, 1)
	1062 dload (6, 1)
	1063 #4 (6, 1)
	1064 ldc2_w (6, 1)
	1065 10.0 (6, 1)
	1067 dload (6, 1)
	1068 #33 (6, 1)
	1069 dmul (6, 1)
	1070 invokestatic (6, 1)
	1071 org/apache/commons/math3/util/FastMath.min:(DD)D (6, 1)
	1073 dmul (6, 1)
	1074 dstore (6, 1)
	1075 #4 (6, 1)
	1076 aload_0 (6, 1)
	1077 dup (6, 1)
	1078 getfield (6, 1)
	1079 org/apache/commons/math3/optimization/general/LevenbergMarquardtOptimizer.lmPar:D (6, 1)
	1081 dload (6, 1)
	1082 #47 (6, 1)
	1083 ddiv (6, 1)
	1084 putfield (6, 1)
	1085 org/apache/commons/math3/optimization/general/LevenbergMarquardtOptimizer.lmPar:D (6, 1)
	1087 goto (7, 1)
	1088 41 (7, 1)
	1090 aload_0 (7, 1)
	1091 getfield (7, 1)
	1092 org/apache/commons/math3/optimization/general/LevenbergMarquardtOptimizer.lmPar:D (7, 1)
	1094 dconst_0 (7, 1)
	1095 dcmpl (7, 1)
	1096 ifeq (7, 1)
	1097 12 (7, 1)
	1099 dload (7, 1)
	1100 #28 (7, 1)
	1101 ldc2_w (7, 1)
	1102 0.75 (7, 1)
	1104 dcmpl (7, 1)
	1105 iflt (7, 1)
	1106 23 (7, 1)
	1108 ldc2_w (7, 1)
	1109 2.0 (7, 1)
	1111 dload (7, 1)
	1112 #33 (7, 1)
	1113 dmul (7, 1)
	1114 dstore (7, 1)
	1115 #4 (7, 1)
	1116 aload_0 (7, 1)
	1117 dup (7, 1)
	1118 getfield (7, 1)
	1119 org/apache/commons/math3/optimization/general/LevenbergMarquardtOptimizer.lmPar:D (7, 1)
	1121 ldc2_w (7, 1)
	1122 0.5 (7, 1)
	1124 dmul (7, 1)
	1125 putfield (7, 1)
	1126 org/apache/commons/math3/optimization/general/LevenbergMarquardtOptimizer.lmPar:D (7, 1)
	1128 dload (7, 1)
	1129 #28 (7, 1)
	1130 ldc2_w (7, 1)
	1131 0.0001 (7, 1)
	1133 dcmpl (7, 1)
	1134 iflt (7, 1)
	1135 92 (7, 1)
	1137 iconst_0 (7, 1)
	1138 istore (7, 1)
	1139 #22 (7, 1)
	1140 dconst_0 (7, 1)
	1141 dstore (7, 1)
	1142 #6 (7, 1)
	1143 iconst_0 (8, 4)
	1144 istore (8, 4)
	1145 #47 (8, 4)
	1146 iload (8, 4)
	1147 #47 (8, 4)
	1148 iload_3 (8, 4)
	1149 if_icmpge (8, 4)
	1150 31 (8, 4)
	1152 aload (8, 4)
	1153 #8 (8, 4)
	1154 iload (8, 4)
	1155 #47 (8, 4)
	1156 daload (8, 4)
	1157 aload_2 (8, 4)
	1158 iload (8, 4)
	1159 #47 (8, 4)
	1160 daload (8, 4)
	1161 dmul (8, 4)
	1162 dstore (8, 4)
	1163 #48 (8, 4)
	1164 dload (8, 4)
	1165 #6 (8, 4)
	1166 dload (8, 4)
	1167 #48 (8, 4)
	1168 dload (8, 4)
	1169 #48 (8, 4)
	1170 dmul (8, 4)
	1171 dadd (8, 4)
	1172 dstore (8, 4)
	1173 #6 (8, 4)
	1174 iinc (8, 4)
	1175 #47 (8, 4)
	1176 -89 (8, 4)
	1177 goto (8, 4)
	1178 -31 (8, 4)
	1180 dload (7, 1)
	1181 #6 (7, 1)
	1182 invokestatic (7, 1)
	1183 org/apache/commons/math3/util/FastMath.sqrt:(D)D (7, 1)
	1185 dstore (7, 1)
	1186 #6 (7, 1)
	1187 aload (9, 1)
	1188 #24 (9, 1)
	1189 ifnull (9, 1)
	1190 117 (9, 1)
	1192 aload (9, 1)
	1193 #24 (9, 1)
	1194 iload (9, 1)
	1195 #23 (9, 1)
	1196 aload (9, 1)
	1197 #25 (9, 1)
	1198 aload (9, 1)
	1199 #19 (9, 1)
	1200 invokeinterface (9, 1)
	1201 org/apache/commons/math3/optimization/ConvergenceChecker.org/apache/commons/math3/exception/ConvergenceException (9, 1)
	1203 0 (9, 1)
	1205 ifeq (9, 1)
	1206 101 (9, 1)
	1208 aload_0 (9, 1)
	1209 dload (9, 1)
	1210 #20 (9, 1)
	1211 invokevirtual (9, 1)
	1212 org/apache/commons/math3/optimization/general/LevenbergMarquardtOptimizer.setCost:(D)V (9, 1)
	1214 aload_0 (9, 1)
	1215 aload (9, 1)
	1216 #19 (9, 1)
	1217 invokevirtual (9, 1)
	1218 org/apache/commons/math3/optimization/PointVectorValuePair.getPoint:()[D (9, 1)
	1220 putfield (9, 1)
	1221 org/apache/commons/math3/optimization/general/LevenbergMarquardtOptimizer.point:[D (9, 1)
	1223 aload (9, 1)
	1224 #19 (9, 1)
	1225 areturn (9, 1)
	1226 dload (9, 2)
	1227 #30 (9, 2)
	1228 dstore (9, 2)
	1229 #20 (9, 2)
	1230 iconst_0 (10, 4)
	1231 istore (10, 4)
	1232 #47 (10, 4)
	1233 iload (10, 4)
	1234 #47 (10, 4)
	1235 aload_0 (10, 4)
	1236 getfield (10, 4)
	1237 org/apache/commons/math3/optimization/general/LevenbergMarquardtOptimizer.solvedCols:I (10, 4)
	1239 if_icmpge (10, 4)
	1240 27 (10, 4)
	1242 aload_0 (10, 4)
	1243 getfield (10, 4)
	1244 org/apache/commons/math3/optimization/general/LevenbergMarquardtOptimizer.permutation:[I (10, 4)
	1246 iload (10, 4)
	1247 #47 (10, 4)
	1248 iaload (10, 4)
	1249 istore (10, 4)
	1250 #48 (10, 4)
	1251 aload_2 (10, 4)
	1252 iload (10, 4)
	1253 #48 (10, 4)
	1254 aload (10, 4)
	1255 #9 (10, 4)
	1256 iload (10, 4)
	1257 #48 (10, 4)
	1258 daload (10, 4)
	1259 dastore (10, 4)
	1260 iinc (10, 4)
	1261 #47 (10, 4)
	1262 -89 (10, 4)
	1263 goto (10, 4)
	1264 -30 (10, 4)
	1266 aload_0 (9, 2)
	1267 getfield (9, 2)
	1268 org/apache/commons/math3/optimization/general/LevenbergMarquardtOptimizer.weightedResidual:[D (9, 2)
	1270 astore (9, 2)
	1271 #32 (9, 2)
	1272 aload_0 (9, 2)
	1273 aload (9, 2)
	1274 #10 (9, 2)
	1275 putfield (9, 2)
	1276 org/apache/commons/math3/optimization/general/LevenbergMarquardtOptimizer.weightedResidual:[D (9, 2)
	1278 aload (9, 2)
	1279 #32 (9, 2)
	1280 astore (9, 2)
	1281 #10 (9, 2)
	1282 aload (9, 2)
	1283 #17 (9, 2)
	1284 astore (9, 2)
	1285 #32 (9, 2)
	1286 aload (9, 2)
	1287 #11 (9, 2)
	1288 astore (9, 2)
	1289 #17 (9, 2)
	1290 aload (9, 2)
	1291 #32 (9, 2)
	1292 astore (9, 2)
	1293 #11 (9, 2)
	1294 new (9, 2)
	1295 org/apache/commons/math3/optimization/PointVectorValuePair (9, 2)
	1297 dup (9, 2)
	1298 aload_2 (9, 2)
	1299 aload (9, 2)
	1300 #17 (9, 2)
	1301 invokespecial (9, 2)
	1302 org/apache/commons/math3/optimization/PointVectorValuePair.<init>:([D[D)V (9, 2)
	1304 astore (9, 2)
	1305 #19 (9, 2)
	1306 dload (7, 1)
	1307 #35 (7, 1)
	1308 invokestatic (7, 1)
	1309 org/apache/commons/math3/util/FastMath.abs:(D)D (7, 1)
	1311 aload_0 (7, 1)
	1312 getfield (7, 1)
	1313 org/apache/commons/math3/optimization/general/LevenbergMarquardtOptimizer.costRelativeTolerance:D (7, 1)
	1315 dcmpg (7, 1)
	1316 ifgt (7, 1)
	1317 22 (7, 1)
	1319 dload (7, 1)
	1320 #43 (7, 1)
	1321 aload_0 (7, 1)
	1322 getfield (7, 1)
	1323 org/apache/commons/math3/optimization/general/LevenbergMarquardtOptimizer.costRelativeTolerance:D (7, 1)
	1325 dcmpg (7, 1)
	1326 ifgt (7, 1)
	1327 12 (7, 1)
	1329 dload (7, 1)
	1330 #28 (7, 1)
	1331 ldc2_w (7, 1)
	1332 2.0 (7, 1)
	1334 dcmpg (7, 1)
	1335 ifle (7, 1)
	1336 16 (7, 1)
	1338 dload (7, 1)
	1339 #4 (7, 1)
	1340 aload_0 (7, 1)
	1341 getfield (7, 1)
	1342 org/apache/commons/math3/optimization/general/LevenbergMarquardtOptimizer.parRelativeTolerance:D (7, 1)
	1344 dload (7, 1)
	1345 #6 (7, 1)
	1346 dmul (7, 1)
	1347 dcmpg (7, 1)
	1348 ifgt (7, 1)
	1349 21 (7, 1)
	1351 aload_0 (7, 1)
	1352 dload (7, 1)
	1353 #20 (7, 1)
	1354 invokevirtual (7, 1)
	1355 org/apache/commons/math3/optimization/general/LevenbergMarquardtOptimizer.setCost:(D)V (7, 1)
	1357 aload_0 (7, 1)
	1358 aload (7, 1)
	1359 #19 (7, 1)
	1360 invokevirtual (7, 1)
	1361 org/apache/commons/math3/optimization/PointVectorValuePair.getPoint:()[D (7, 1)
	1363 putfield (7, 1)
	1364 org/apache/commons/math3/optimization/general/LevenbergMarquardtOptimizer.point:[D (7, 1)
	1366 aload (7, 1)
	1367 #19 (7, 1)
	1368 areturn (7, 1)
	1369 dload (10, 1)
	1370 #35 (10, 1)
	1371 invokestatic (10, 1)
	1372 org/apache/commons/math3/util/FastMath.abs:(D)D (10, 1)
	1374 ldc2_w (10, 1)
	1375 2.2204e-16 (10, 1)
	1377 dcmpg (10, 1)
	1378 ifgt (10, 1)
	1379 46 (10, 1)
	1381 dload (10, 1)
	1382 #43 (10, 1)
	1383 ldc2_w (10, 1)
	1384 2.2204e-16 (10, 1)
	1386 dcmpg (10, 1)
	1387 ifgt (10, 1)
	1388 37 (10, 1)
	1390 dload (10, 1)
	1391 #28 (10, 1)
	1392 ldc2_w (10, 1)
	1393 2.0 (10, 1)
	1395 dcmpg (10, 1)
	1396 ifgt (10, 1)
	1397 28 (10, 1)
	1399 new (10, 1)
	1400 org/apache/commons/math3/exception/ConvergenceException (10, 1)
	1402 dup (10, 1)
	1403 getstatic (10, 1)
	1404 org/apache/commons/math3/exception/util/LocalizedFormats.TOO_SMALL_COST_RELATIVE_TOLERANCE:Lorg/apache/commons/math3/exception/util/LocalizedFormats; (10, 1)
	1406 iconst_1 (10, 1)
	1407 anewarray (10, 1)
	1408 java/lang/Object (10, 1)
	1410 dup (10, 1)
	1411 iconst_0 (10, 1)
	1412 aload_0 (10, 1)
	1413 getfield (10, 1)
	1414 org/apache/commons/math3/optimization/general/LevenbergMarquardtOptimizer.costRelativeTolerance:D (10, 1)
	1416 invokestatic (10, 1)
	1417 java/lang/Double.valueOf:(D)Ljava/lang/Double; (10, 1)
	1419 aastore (10, 1)
	1420 invokespecial (10, 1)
	1421 org/apache/commons/math3/exception/ConvergenceException.<init>:(Lorg/apache/commons/math3/exception/util/Localizable;[Ljava/lang/Object;)V (10, 1)
	1423 athrow (10, 1)
	1424 dload (11, 1)
	1425 #4 (11, 1)
	1426 ldc2_w (11, 1)
	1427 2.2204e-16 (11, 1)
	1429 dload (11, 1)
	1430 #6 (11, 1)
	1431 dmul (11, 1)
	1432 dcmpg (11, 1)
	1433 ifgt (11, 1)
	1434 28 (11, 1)
	1436 new (11, 1)
	1437 org/apache/commons/math3/exception/ConvergenceException (11, 1)
	1439 dup (11, 1)
	1440 getstatic (11, 1)
	1441 org/apache/commons/math3/exception/util/LocalizedFormats.TOO_SMALL_PARAMETERS_RELATIVE_TOLERANCE:Lorg/apache/commons/math3/exception/util/LocalizedFormats; (11, 1)
	1443 iconst_1 (11, 1)
	1444 anewarray (11, 1)
	1445 java/lang/Object (11, 1)
	1447 dup (11, 1)
	1448 iconst_0 (11, 1)
	1449 aload_0 (11, 1)
	1450 getfield (11, 1)
	1451 org/apache/commons/math3/optimization/general/LevenbergMarquardtOptimizer.parRelativeTolerance:D (11, 1)
	1453 invokestatic (11, 1)
	1454 java/lang/Double.valueOf:(D)Ljava/lang/Double; (11, 1)
	1456 aastore (11, 1)
	1457 invokespecial (11, 1)
	1458 org/apache/commons/math3/exception/ConvergenceException.<init>:(Lorg/apache/commons/math3/exception/util/Localizable;[Ljava/lang/Object;)V (11, 1)
	1460 athrow (11, 1)
	1461 dload (12, 1)
	1462 #26 (12, 1)
	1463 ldc2_w (12, 1)
	1464 2.2204e-16 (12, 1)
	1466 dcmpg (12, 1)
	1467 ifgt (12, 1)
	1468 28 (12, 1)
	1470 new (12, 1)
	1471 org/apache/commons/math3/exception/ConvergenceException (12, 1)
	1473 dup (12, 1)
	1474 getstatic (12, 1)
	1475 org/apache/commons/math3/exception/util/LocalizedFormats.TOO_SMALL_ORTHOGONALITY_TOLERANCE:Lorg/apache/commons/math3/exception/util/LocalizedFormats; (12, 1)
	1477 iconst_1 (12, 1)
	1478 anewarray (12, 1)
	1479 java/lang/Object (12, 1)
	1481 dup (12, 1)
	1482 iconst_0 (12, 1)
	1483 aload_0 (12, 1)
	1484 getfield (12, 1)
	1485 org/apache/commons/math3/optimization/general/LevenbergMarquardtOptimizer.orthoTolerance:D (12, 1)
	1487 invokestatic (12, 1)
	1488 java/lang/Double.valueOf:(D)Ljava/lang/Double; (12, 1)
	1490 aastore (12, 1)
	1491 invokespecial (12, 1)
	1492 org/apache/commons/math3/exception/ConvergenceException.<init>:(Lorg/apache/commons/math3/exception/util/Localizable;[Ljava/lang/Object;)V (12, 1)
	1494 athrow (12, 1)
	1495 goto (4, 4)
	1496 -952 (4, 4)
	1498 goto (2, 1)
	1499 -1336 (3, 1)

Method: determineLMParameter
	0 aload_0 (0, 0)
	1 getfield (0, 0)
	2 org/apache/commons/math3/optimization/general/LevenbergMarquardtOptimizer.weightedJacobian:[[D (0, 0)
	4 iconst_0 (0, 0)
	5 aaload (0, 0)
	6 arraylength (0, 0)
	7 istore (0, 0)
	8 #8 (0, 0)
	9 iconst_0 (2, 4)
	10 istore (2, 4)
	11 #9 (2, 4)
	12 iload (2, 4)
	13 #9 (2, 4)
	14 aload_0 (2, 4)
	15 getfield (2, 4)
	16 org/apache/commons/math3/optimization/general/LevenbergMarquardtOptimizer.rank:I (2, 4)
	18 if_icmpge (2, 4)
	19 25 (2, 4)
	21 aload_0 (2, 4)
	22 getfield (2, 4)
	23 org/apache/commons/math3/optimization/general/LevenbergMarquardtOptimizer.lmDir:[D (2, 4)
	25 aload_0 (2, 4)
	26 getfield (2, 4)
	27 org/apache/commons/math3/optimization/general/LevenbergMarquardtOptimizer.permutation:[I (2, 4)
	29 iload (2, 4)
	30 #9 (2, 4)
	31 iaload (2, 4)
	32 aload_1 (2, 4)
	33 iload (2, 4)
	34 #9 (2, 4)
	35 daload (2, 4)
	36 dastore (2, 4)
	37 iinc (2, 4)
	38 #9 (2, 4)
	39 -89 (2, 4)
	40 goto (2, 4)
	41 -28 (2, 4)
	43 aload_0 (2, 4)
	44 getfield (2, 4)
	45 org/apache/commons/math3/optimization/general/LevenbergMarquardtOptimizer.rank:I (2, 4)
	47 istore (2, 4)
	48 #9 (2, 4)
	49 iload (2, 4)
	50 #9 (2, 4)
	51 iload (2, 4)
	52 #8 (2, 4)
	53 if_icmpge (2, 4)
	54 22 (2, 4)
	56 aload_0 (2, 4)
	57 getfield (2, 4)
	58 org/apache/commons/math3/optimization/general/LevenbergMarquardtOptimizer.lmDir:[D (2, 4)
	60 aload_0 (2, 4)
	61 getfield (2, 4)
	62 org/apache/commons/math3/optimization/general/LevenbergMarquardtOptimizer.permutation:[I (2, 4)
	64 iload (2, 4)
	65 #9 (2, 4)
	66 iaload (2, 4)
	67 dconst_0 (2, 4)
	68 dastore (2, 4)
	69 iinc (2, 4)
	70 #9 (2, 4)
	71 -89 (2, 4)
	72 goto (2, 4)
	73 -23 (2, 4)
	75 aload_0 (2, 4)
	76 getfield (2, 4)
	77 org/apache/commons/math3/optimization/general/LevenbergMarquardtOptimizer.rank:I (2, 4)
	79 iconst_1 (2, 4)
	80 isub (2, 4)
	81 istore (2, 4)
	82 #9 (2, 4)
	83 iload (2, 4)
	84 #9 (2, 4)
	85 iflt (2, 4)
	86 88 (2, 4)
	88 aload_0 (2, 4)
	89 getfield (2, 4)
	90 org/apache/commons/math3/optimization/general/LevenbergMarquardtOptimizer.permutation:[I (2, 4)
	92 iload (2, 4)
	93 #9 (2, 4)
	94 iaload (2, 4)
	95 istore (2, 4)
	96 #10 (2, 4)
	97 aload_0 (2, 4)
	98 getfield (2, 4)
	99 org/apache/commons/math3/optimization/general/LevenbergMarquardtOptimizer.lmDir:[D (2, 4)
	101 iload (2, 4)
	102 #10 (2, 4)
	103 daload (2, 4)
	104 aload_0 (2, 4)
	105 getfield (2, 4)
	106 org/apache/commons/math3/optimization/general/LevenbergMarquardtOptimizer.diagR:[D (2, 4)
	108 iload (2, 4)
	109 #10 (2, 4)
	110 daload (2, 4)
	111 ddiv (2, 4)
	112 dstore (2, 4)
	113 #11 (2, 4)
	114 iconst_0 (3, 4)
	115 istore (3, 4)
	116 #13 (3, 4)
	117 iload (3, 4)
	118 #13 (3, 4)
	119 iload (3, 4)
	120 #9 (3, 4)
	121 if_icmpge (3, 4)
	122 37 (3, 4)
	124 aload_0 (3, 4)
	125 getfield (3, 4)
	126 org/apache/commons/math3/optimization/general/LevenbergMarquardtOptimizer.lmDir:[D (3, 4)
	128 aload_0 (3, 4)
	129 getfield (3, 4)
	130 org/apache/commons/math3/optimization/general/LevenbergMarquardtOptimizer.permutation:[I (3, 4)
	132 iload (3, 4)
	133 #13 (3, 4)
	134 iaload (3, 4)
	135 dup2 (3, 4)
	136 daload (3, 4)
	137 dload (3, 4)
	138 #11 (3, 4)
	139 aload_0 (3, 4)
	140 getfield (3, 4)
	141 org/apache/commons/math3/optimization/general/LevenbergMarquardtOptimizer.weightedJacobian:[[D (3, 4)
	143 iload (3, 4)
	144 #13 (3, 4)
	145 aaload (3, 4)
	146 iload (3, 4)
	147 #10 (3, 4)
	148 daload (3, 4)
	149 dmul (3, 4)
	150 dsub (3, 4)
	151 dastore (3, 4)
	152 iinc (3, 4)
	153 #13 (3, 4)
	154 -89 (3, 4)
	155 goto (3, 4)
	156 -38 (3, 4)
	158 aload_0 (2, 4)
	159 getfield (2, 4)
	160 org/apache/commons/math3/optimization/general/LevenbergMarquardtOptimizer.lmDir:[D (2, 4)
	162 iload (2, 4)
	163 #10 (2, 4)
	164 dload (2, 4)
	165 #11 (2, 4)
	166 dastore (2, 4)
	167 iinc (2, 4)
	168 #9 (2, 4)
	169 -89 (2, 4)
	170 goto (2, 4)
	171 -87 (2, 4)
	173 dconst_0 (2, 4)
	174 dstore (2, 4)
	175 #9 (2, 4)
	176 iconst_0 (3, 4)
	177 istore (3, 4)
	178 #11 (3, 4)
	179 iload (3, 4)
	180 #11 (3, 4)
	181 aload_0 (3, 4)
	182 getfield (3, 4)
	183 org/apache/commons/math3/optimization/general/LevenbergMarquardtOptimizer.solvedCols:I (3, 4)
	185 if_icmpge (3, 4)
	186 50 (3, 4)
	188 aload_0 (3, 4)
	189 getfield (3, 4)
	190 org/apache/commons/math3/optimization/general/LevenbergMarquardtOptimizer.permutation:[I (3, 4)
	192 iload (3, 4)
	193 #11 (3, 4)
	194 iaload (3, 4)
	195 istore (3, 4)
	196 #12 (3, 4)
	197 aload (3, 4)
	198 #4 (3, 4)
	199 iload (3, 4)
	200 #12 (3, 4)
	201 daload (3, 4)
	202 aload_0 (3, 4)
	203 getfield (3, 4)
	204 org/apache/commons/math3/optimization/general/LevenbergMarquardtOptimizer.lmDir:[D (3, 4)
	206 iload (3, 4)
	207 #12 (3, 4)
	208 daload (3, 4)
	209 dmul (3, 4)
	210 dstore (3, 4)
	211 #13 (3, 4)
	212 aload (3, 4)
	213 #5 (3, 4)
	214 iload (3, 4)
	215 #12 (3, 4)
	216 dload (3, 4)
	217 #13 (3, 4)
	218 dastore (3, 4)
	219 dload (3, 4)
	220 #9 (3, 4)
	221 dload (3, 4)
	222 #13 (3, 4)
	223 dload (3, 4)
	224 #13 (3, 4)
	225 dmul (3, 4)
	226 dadd (3, 4)
	227 dstore (3, 4)
	228 #9 (3, 4)
	229 iinc (3, 4)
	230 #11 (3, 4)
	231 -89 (3, 4)
	232 goto (3, 4)
	233 -53 (3, 4)
	235 dload (2, 4)
	236 #9 (2, 4)
	237 invokestatic (2, 4)
	238 org/apache/commons/math3/util/FastMath.sqrt:(D)D (2, 4)
	240 dstore (2, 4)
	241 #9 (2, 4)
	242 dload (2, 4)
	243 #9 (2, 4)
	244 dload_2 (2, 4)
	245 dsub (2, 4)
	246 dstore (2, 4)
	247 #11 (2, 4)
	248 dload (3, 1)
	249 #11 (3, 1)
	250 ldc2_w (3, 1)
	251 0.1 (3, 1)
	253 dload_2 (3, 1)
	254 dmul (3, 1)
	255 dcmpg (3, 1)
	256 ifgt (3, 1)
	257 9 (3, 1)
	259 aload_0 (3, 1)
	260 dconst_0 (3, 1)
	261 putfield (3, 1)
	262 org/apache/commons/math3/optimization/general/LevenbergMarquardtOptimizer.lmPar:D (3, 1)
	264 return (3, 1)
	265 dconst_0 (4, 4)
	266 dstore (4, 4)
	267 #15 (4, 4)
	268 aload_0 (5, 1)
	269 getfield (5, 1)
	270 org/apache/commons/math3/optimization/general/LevenbergMarquardtOptimizer.rank:I (5, 1)
	272 aload_0 (5, 1)
	273 getfield (5, 1)
	274 org/apache/commons/math3/optimization/general/LevenbergMarquardtOptimizer.solvedCols:I (5, 1)
	276 if_icmpne (5, 1)
	277 165 (5, 1)
	279 iconst_0 (6, 4)
	280 istore (6, 4)
	281 #17 (6, 4)
	282 iload (6, 4)
	283 #17 (6, 4)
	284 aload_0 (6, 4)
	285 getfield (6, 4)
	286 org/apache/commons/math3/optimization/general/LevenbergMarquardtOptimizer.solvedCols:I (6, 4)
	288 if_icmpge (6, 4)
	289 34 (6, 4)
	291 aload_0 (6, 4)
	292 getfield (6, 4)
	293 org/apache/commons/math3/optimization/general/LevenbergMarquardtOptimizer.permutation:[I (6, 4)
	295 iload (6, 4)
	296 #17 (6, 4)
	297 iaload (6, 4)
	298 istore (6, 4)
	299 #18 (6, 4)
	300 aload (6, 4)
	301 #5 (6, 4)
	302 iload (6, 4)
	303 #18 (6, 4)
	304 dup2 (6, 4)
	305 daload (6, 4)
	306 aload (6, 4)
	307 #4 (6, 4)
	308 iload (6, 4)
	309 #18 (6, 4)
	310 daload (6, 4)
	311 dload (6, 4)
	312 #9 (6, 4)
	313 ddiv (6, 4)
	314 dmul (6, 4)
	315 dastore (6, 4)
	316 iinc (6, 4)
	317 #17 (6, 4)
	318 -89 (6, 4)
	319 goto (6, 4)
	320 -37 (6, 4)
	322 dconst_0 (5, 1)
	323 dstore (5, 1)
	324 #13 (5, 1)
	325 iconst_0 (6, 4)
	326 istore (6, 4)
	327 #17 (6, 4)
	328 iload (6, 4)
	329 #17 (6, 4)
	330 aload_0 (6, 4)
	331 getfield (6, 4)
	332 org/apache/commons/math3/optimization/general/LevenbergMarquardtOptimizer.solvedCols:I (6, 4)
	334 if_icmpge (6, 4)
	335 98 (6, 4)
	337 aload_0 (6, 4)
	338 getfield (6, 4)
	339 org/apache/commons/math3/optimization/general/LevenbergMarquardtOptimizer.permutation:[I (6, 4)
	341 iload (6, 4)
	342 #17 (6, 4)
	343 iaload (6, 4)
	344 istore (6, 4)
	345 #18 (6, 4)
	346 dconst_0 (6, 4)
	347 dstore (6, 4)
	348 #19 (6, 4)
	349 iconst_0 (7, 4)
	350 istore (7, 4)
	351 #21 (7, 4)
	352 iload (7, 4)
	353 #21 (7, 4)
	354 iload (7, 4)
	355 #17 (7, 4)
	356 if_icmpge (7, 4)
	357 35 (7, 4)
	359 dload (7, 4)
	360 #19 (7, 4)
	361 aload_0 (7, 4)
	362 getfield (7, 4)
	363 org/apache/commons/math3/optimization/general/LevenbergMarquardtOptimizer.weightedJacobian:[[D (7, 4)
	365 iload (7, 4)
	366 #21 (7, 4)
	367 aaload (7, 4)
	368 iload (7, 4)
	369 #18 (7, 4)
	370 daload (7, 4)
	371 aload (7, 4)
	372 #5 (7, 4)
	373 aload_0 (7, 4)
	374 getfield (7, 4)
	375 org/apache/commons/math3/optimization/general/LevenbergMarquardtOptimizer.permutation:[I (7, 4)
	377 iload (7, 4)
	378 #21 (7, 4)
	379 iaload (7, 4)
	380 daload (7, 4)
	381 dmul (7, 4)
	382 dadd (7, 4)
	383 dstore (7, 4)
	384 #19 (7, 4)
	385 iinc (7, 4)
	386 #21 (7, 4)
	387 -89 (7, 4)
	388 goto (7, 4)
	389 -36 (7, 4)
	391 aload (6, 4)
	392 #5 (6, 4)
	393 iload (6, 4)
	394 #18 (6, 4)
	395 daload (6, 4)
	396 dload (6, 4)
	397 #19 (6, 4)
	398 dsub (6, 4)
	399 aload_0 (6, 4)
	400 getfield (6, 4)
	401 org/apache/commons/math3/optimization/general/LevenbergMarquardtOptimizer.diagR:[D (6, 4)
	403 iload (6, 4)
	404 #18 (6, 4)
	405 daload (6, 4)
	406 ddiv (6, 4)
	407 dstore (6, 4)
	408 #21 (6, 4)
	409 aload (6, 4)
	410 #5 (6, 4)
	411 iload (6, 4)
	412 #18 (6, 4)
	413 dload (6, 4)
	414 #21 (6, 4)
	415 dastore (6, 4)
	416 dload (6, 4)
	417 #13 (6, 4)
	418 dload (6, 4)
	419 #21 (6, 4)
	420 dload (6, 4)
	421 #21 (6, 4)
	422 dmul (6, 4)
	423 dadd (6, 4)
	424 dstore (6, 4)
	425 #13 (6, 4)
	426 iinc (6, 4)
	427 #17 (6, 4)
	428 -89 (6, 4)
	429 goto (6, 4)
	430 -101 (6, 4)
	432 dload (5, 1)
	433 #11 (5, 1)
	434 dload_2 (5, 1)
	435 dload (5, 1)
	436 #13 (5, 1)
	437 dmul (5, 1)
	438 ddiv (5, 1)
	439 dstore (5, 1)
	440 #15 (5, 1)
	441 dconst_0 (5, 4)
	442 dstore (5, 4)
	443 #13 (5, 4)
	444 iconst_0 (6, 4)
	445 istore (6, 4)
	446 #17 (6, 4)
	447 iload (6, 4)
	448 #17 (6, 4)
	449 aload_0 (6, 4)
	450 getfield (6, 4)
	451 org/apache/commons/math3/optimization/general/LevenbergMarquardtOptimizer.solvedCols:I (6, 4)
	453 if_icmpge (6, 4)
	454 77 (6, 4)
	456 aload_0 (6, 4)
	457 getfield (6, 4)
	458 org/apache/commons/math3/optimization/general/LevenbergMarquardtOptimizer.permutation:[I (6, 4)
	460 iload (6, 4)
	461 #17 (6, 4)
	462 iaload (6, 4)
	463 istore (6, 4)
	464 #18 (6, 4)
	465 dconst_0 (6, 4)
	466 dstore (6, 4)
	467 #19 (6, 4)
	468 iconst_0 (7, 4)
	469 istore (7, 4)
	470 #21 (7, 4)
	471 iload (7, 4)
	472 #21 (7, 4)
	473 iload (7, 4)
	474 #17 (7, 4)
	475 if_icmpgt (7, 4)
	476 29 (7, 4)
	478 dload (7, 4)
	479 #19 (7, 4)
	480 aload_0 (7, 4)
	481 getfield (7, 4)
	482 org/apache/commons/math3/optimization/general/LevenbergMarquardtOptimizer.weightedJacobian:[[D (7, 4)
	484 iload (7, 4)
	485 #21 (7, 4)
	486 aaload (7, 4)
	487 iload (7, 4)
	488 #18 (7, 4)
	489 daload (7, 4)
	490 aload_1 (7, 4)
	491 iload (7, 4)
	492 #21 (7, 4)
	493 daload (7, 4)
	494 dmul (7, 4)
	495 dadd (7, 4)
	496 dstore (7, 4)
	497 #19 (7, 4)
	498 iinc (7, 4)
	499 #21 (7, 4)
	500 -89 (7, 4)
	501 goto (7, 4)
	502 -30 (7, 4)
	504 dload (6, 4)
	505 #19 (6, 4)
	506 aload (6, 4)
	507 #4 (6, 4)
	508 iload (6, 4)
	509 #18 (6, 4)
	510 daload (6, 4)
	511 ddiv (6, 4)
	512 dstore (6, 4)
	513 #19 (6, 4)
	514 dload (6, 4)
	515 #13 (6, 4)
	516 dload (6, 4)
	517 #19 (6, 4)
	518 dload (6, 4)
	519 #19 (6, 4)
	520 dmul (6, 4)
	521 dadd (6, 4)
	522 dstore (6, 4)
	523 #13 (6, 4)
	524 iinc (6, 4)
	525 #17 (6, 4)
	526 -89 (6, 4)
	527 goto (6, 4)
	528 -80 (6, 4)
	530 dload (5, 4)
	531 #13 (5, 4)
	532 invokestatic (5, 4)
	533 org/apache/commons/math3/util/FastMath.sqrt:(D)D (5, 4)
	535 dstore (5, 4)
	536 #17 (5, 4)
	537 dload (5, 4)
	538 #17 (5, 4)
	539 dload_2 (5, 4)
	540 ddiv (5, 4)
	541 dstore (5, 4)
	542 #19 (5, 4)
	543 dload (6, 1)
	544 #19 (6, 1)
	545 dconst_0 (6, 1)
	546 dcmpl (6, 1)
	547 ifne (6, 1)
	548 16 (6, 1)
	550 ldc2_w (7, 4)
	551 2.2251e-308 (7, 4)
	553 dload_2 (7, 4)
	554 ldc2_w (7, 4)
	555 0.1 (7, 4)
	557 invokestatic (7, 4)
	558 org/apache/commons/math3/util/FastMath.min:(DD)D (7, 4)
	560 ddiv (7, 4)
	561 dstore (7, 4)
	562 #19 (7, 4)
	563 aload_0 (6, 1)
	564 dload (6, 1)
	565 #19 (6, 1)
	566 aload_0 (6, 1)
	567 getfield (6, 1)
	568 org/apache/commons/math3/optimization/general/LevenbergMarquardtOptimizer.lmPar:D (6, 1)
	570 dload (6, 1)
	571 #15 (6, 1)
	572 invokestatic (6, 1)
	573 org/apache/commons/math3/util/FastMath.max:(DD)D (6, 1)
	575 invokestatic (6, 1)
	576 org/apache/commons/math3/util/FastMath.min:(DD)D (6, 1)
	578 putfield (6, 1)
	579 org/apache/commons/math3/optimization/general/LevenbergMarquardtOptimizer.lmPar:D (6, 1)
	581 aload_0 (7, 1)
	582 getfield (7, 1)
	583 org/apache/commons/math3/optimization/general/LevenbergMarquardtOptimizer.lmPar:D (7, 1)
	585 dconst_0 (7, 1)
	586 dcmpl (7, 1)
	587 ifne (7, 1)
	588 12 (7, 1)
	590 aload_0 (7, 1)
	591 dload (7, 1)
	592 #17 (7, 1)
	593 dload (7, 1)
	594 #9 (7, 1)
	595 ddiv (7, 1)
	596 putfield (7, 1)
	597 org/apache/commons/math3/optimization/general/LevenbergMarquardtOptimizer.lmPar:D (7, 1)
	599 bipush (7, 4)
	600 10 (7, 4)
	601 istore (7, 4)
	602 #21 (7, 4)
	603 iload (7, 4)
	604 #21 (7, 4)
	605 iflt (7, 4)
	606 457 (7, 4)
	608 aload_0 (8, 1)
	609 getfield (8, 1)
	610 org/apache/commons/math3/optimization/general/LevenbergMarquardtOptimizer.lmPar:D (8, 1)
	612 dconst_0 (8, 1)
	613 dcmpl (8, 1)
	614 ifne (8, 1)
	615 19 (8, 1)
	617 aload_0 (8, 1)
	618 ldc2_w (8, 1)
	619 2.2251e-308 (8, 1)
	621 ldc2_w (8, 1)
	622 0.001 (8, 1)
	624 dload (8, 1)
	625 #19 (8, 1)
	626 dmul (8, 1)
	627 invokestatic (8, 1)
	628 org/apache/commons/math3/util/FastMath.max:(DD)D (8, 1)
	630 putfield (8, 1)
	631 org/apache/commons/math3/optimization/general/LevenbergMarquardtOptimizer.lmPar:D (8, 1)
	633 aload_0 (7, 4)
	634 getfield (7, 4)
	635 org/apache/commons/math3/optimization/general/LevenbergMarquardtOptimizer.lmPar:D (7, 4)
	637 invokestatic (7, 4)
	638 org/apache/commons/math3/util/FastMath.sqrt:(D)D (7, 4)
	640 dstore (7, 4)
	641 #22 (7, 4)
	642 iconst_0 (8, 4)
	643 istore (8, 4)
	644 #24 (8, 4)
	645 iload (8, 4)
	646 #24 (8, 4)
	647 aload_0 (8, 4)
	648 getfield (8, 4)
	649 org/apache/commons/math3/optimization/general/LevenbergMarquardtOptimizer.solvedCols:I (8, 4)
	651 if_icmpge (8, 4)
	652 31 (8, 4)
	654 aload_0 (8, 4)
	655 getfield (8, 4)
	656 org/apache/commons/math3/optimization/general/LevenbergMarquardtOptimizer.permutation:[I (8, 4)
	658 iload (8, 4)
	659 #24 (8, 4)
	660 iaload (8, 4)
	661 istore (8, 4)
	662 #25 (8, 4)
	663 aload (8, 4)
	664 #5 (8, 4)
	665 iload (8, 4)
	666 #25 (8, 4)
	667 dload (8, 4)
	668 #22 (8, 4)
	669 aload (8, 4)
	670 #4 (8, 4)
	671 iload (8, 4)
	672 #25 (8, 4)
	673 daload (8, 4)
	674 dmul (8, 4)
	675 dastore (8, 4)
	676 iinc (8, 4)
	677 #24 (8, 4)
	678 -89 (8, 4)
	679 goto (8, 4)
	680 -34 (8, 4)
	682 aload_0 (7, 4)
	683 aload_1 (7, 4)
	684 aload (7, 4)
	685 #5 (7, 4)
	686 aload (7, 4)
	687 #6 (7, 4)
	688 aload (7, 4)
	689 #7 (7, 4)
	690 invokespecial (7, 4)
	691 org/apache/commons/math3/optimization/general/LevenbergMarquardtOptimizer.determineLMDirection:([D[D[D[D)V (7, 4)
	693 dconst_0 (7, 4)
	694 dstore (7, 4)
	695 #9 (7, 4)
	696 iconst_0 (8, 4)
	697 istore (8, 4)
	698 #24 (8, 4)
	699 iload (8, 4)
	700 #24 (8, 4)
	701 aload_0 (8, 4)
	702 getfield (8, 4)
	703 org/apache/commons/math3/optimization/general/LevenbergMarquardtOptimizer.solvedCols:I (8, 4)
	705 if_icmpge (8, 4)
	706 50 (8, 4)
	708 aload_0 (8, 4)
	709 getfield (8, 4)
	710 org/apache/commons/math3/optimization/general/LevenbergMarquardtOptimizer.permutation:[I (8, 4)
	712 iload (8, 4)
	713 #24 (8, 4)
	714 iaload (8, 4)
	715 istore (8, 4)
	716 #25 (8, 4)
	717 aload (8, 4)
	718 #4 (8, 4)
	719 iload (8, 4)
	720 #25 (8, 4)
	721 daload (8, 4)
	722 aload_0 (8, 4)
	723 getfield (8, 4)
	724 org/apache/commons/math3/optimization/general/LevenbergMarquardtOptimizer.lmDir:[D (8, 4)
	726 iload (8, 4)
	727 #25 (8, 4)
	728 daload (8, 4)
	729 dmul (8, 4)
	730 dstore (8, 4)
	731 #26 (8, 4)
	732 aload (8, 4)
	733 #7 (8, 4)
	734 iload (8, 4)
	735 #25 (8, 4)
	736 dload (8, 4)
	737 #26 (8, 4)
	738 dastore (8, 4)
	739 dload (8, 4)
	740 #9 (8, 4)
	741 dload (8, 4)
	742 #26 (8, 4)
	743 dload (8, 4)
	744 #26 (8, 4)
	745 dmul (8, 4)
	746 dadd (8, 4)
	747 dstore (8, 4)
	748 #9 (8, 4)
	749 iinc (8, 4)
	750 #24 (8, 4)
	751 -89 (8, 4)
	752 goto (8, 4)
	753 -53 (8, 4)
	755 dload (7, 4)
	756 #9 (7, 4)
	757 invokestatic (7, 4)
	758 org/apache/commons/math3/util/FastMath.sqrt:(D)D (7, 4)
	760 dstore (7, 4)
	761 #9 (7, 4)
	762 dload (7, 4)
	763 #11 (7, 4)
	764 dstore (7, 4)
	765 #24 (7, 4)
	766 dload (7, 4)
	767 #9 (7, 4)
	768 dload_2 (7, 4)
	769 dsub (7, 4)
	770 dstore (7, 4)
	771 #11 (7, 4)
	772 dload (10, 1)
	773 #11 (10, 1)
	774 invokestatic (10, 1)
	775 org/apache/commons/math3/util/FastMath.abs:(D)D (10, 1)
	777 ldc2_w (10, 1)
	778 0.1 (10, 1)
	780 dload_2 (10, 1)
	781 dmul (10, 1)
	782 dcmpg (10, 1)
	783 ifle (10, 1)
	784 25 (10, 1)
	786 dload (10, 1)
	787 #15 (10, 1)
	788 dconst_0 (10, 1)
	789 dcmpl (10, 1)
	790 ifne (10, 1)
	791 19 (10, 1)
	793 dload (10, 1)
	794 #11 (10, 1)
	795 dload (10, 1)
	796 #24 (10, 1)
	797 dcmpg (10, 1)
	798 ifgt (10, 1)
	799 11 (10, 1)
	801 dload (10, 1)
	802 #24 (10, 1)
	803 dconst_0 (10, 1)
	804 dcmpg (10, 1)
	805 ifge (10, 1)
	806 4 (10, 1)
	808 return (10, 1)
	809 iconst_0 (11, 4)
	810 istore (11, 4)
	811 #26 (11, 4)
	812 iload (11, 4)
	813 #26 (11, 4)
	814 aload_0 (11, 4)
	815 getfield (11, 4)
	816 org/apache/commons/math3/optimization/general/LevenbergMarquardtOptimizer.solvedCols:I (11, 4)
	818 if_icmpge (11, 4)
	819 37 (11, 4)
	821 aload_0 (11, 4)
	822 getfield (11, 4)
	823 org/apache/commons/math3/optimization/general/LevenbergMarquardtOptimizer.permutation:[I (11, 4)
	825 iload (11, 4)
	826 #26 (11, 4)
	827 iaload (11, 4)
	828 istore (11, 4)
	829 #27 (11, 4)
	830 aload (11, 4)
	831 #5 (11, 4)
	832 iload (11, 4)
	833 #27 (11, 4)
	834 aload (11, 4)
	835 #7 (11, 4)
	836 iload (11, 4)
	837 #27 (11, 4)
	838 daload (11, 4)
	839 aload (11, 4)
	840 #4 (11, 4)
	841 iload (11, 4)
	842 #27 (11, 4)
	843 daload (11, 4)
	844 dmul (11, 4)
	845 dload (11, 4)
	846 #9 (11, 4)
	847 ddiv (11, 4)
	848 dastore (11, 4)
	849 iinc (11, 4)
	850 #26 (11, 4)
	851 -89 (11, 4)
	852 goto (11, 4)
	853 -40 (11, 4)
	855 iconst_0 (11, 4)
	856 istore (11, 4)
	857 #26 (11, 4)
	858 iload (11, 4)
	859 #26 (11, 4)
	860 aload_0 (11, 4)
	861 getfield (11, 4)
	862 org/apache/commons/math3/optimization/general/LevenbergMarquardtOptimizer.solvedCols:I (11, 4)
	864 if_icmpge (11, 4)
	865 85 (11, 4)
	867 aload_0 (11, 4)
	868 getfield (11, 4)
	869 org/apache/commons/math3/optimization/general/LevenbergMarquardtOptimizer.permutation:[I (11, 4)
	871 iload (11, 4)
	872 #26 (11, 4)
	873 iaload (11, 4)
	874 istore (11, 4)
	875 #27 (11, 4)
	876 aload (11, 4)
	877 #5 (11, 4)
	878 iload (11, 4)
	879 #27 (11, 4)
	880 dup2 (11, 4)
	881 daload (11, 4)
	882 aload (11, 4)
	883 #6 (11, 4)
	884 iload (11, 4)
	885 #26 (11, 4)
	886 daload (11, 4)
	887 ddiv (11, 4)
	888 dastore (11, 4)
	889 aload (11, 4)
	890 #5 (11, 4)
	891 iload (11, 4)
	892 #27 (11, 4)
	893 daload (11, 4)
	894 dstore (11, 4)
	895 #28 (11, 4)
	896 iload (12, 4)
	897 #26 (12, 4)
	898 iconst_1 (12, 4)
	899 iadd (12, 4)
	900 istore (12, 4)
	901 #30 (12, 4)
	902 iload (12, 4)
	903 #30 (12, 4)
	904 aload_0 (12, 4)
	905 getfield (12, 4)
	906 org/apache/commons/math3/optimization/general/LevenbergMarquardtOptimizer.solvedCols:I (12, 4)
	908 if_icmpge (12, 4)
	909 35 (12, 4)
	911 aload (12, 4)
	912 #5 (12, 4)
	913 aload_0 (12, 4)
	914 getfield (12, 4)
	915 org/apache/commons/math3/optimization/general/LevenbergMarquardtOptimizer.permutation:[I (12, 4)
	917 iload (12, 4)
	918 #30 (12, 4)
	919 iaload (12, 4)
	920 dup2 (12, 4)
	921 daload (12, 4)
	922 aload_0 (12, 4)
	923 getfield (12, 4)
	924 org/apache/commons/math3/optimization/general/LevenbergMarquardtOptimizer.weightedJacobian:[[D (12, 4)
	926 iload (12, 4)
	927 #30 (12, 4)
	928 aaload (12, 4)
	929 iload (12, 4)
	930 #27 (12, 4)
	931 daload (12, 4)
	932 dload (12, 4)
	933 #28 (12, 4)
	934 dmul (12, 4)
	935 dsub (12, 4)
	936 dastore (12, 4)
	937 iinc (12, 4)
	938 #30 (12, 4)
	939 -89 (12, 4)
	940 goto (12, 4)
	941 -38 (12, 4)
	943 iinc (12, 4)
	944 #26 (12, 4)
	945 -89 (12, 4)
	946 goto (12, 4)
	947 -88 (12, 4)
	949 dconst_0 (11, 4)
	950 dstore (11, 4)
	951 #13 (11, 4)
	952 iconst_0 (12, 4)
	953 istore (12, 4)
	954 #26 (12, 4)
	955 iload (12, 4)
	956 #26 (12, 4)
	957 aload_0 (12, 4)
	958 getfield (12, 4)
	959 org/apache/commons/math3/optimization/general/LevenbergMarquardtOptimizer.solvedCols:I (12, 4)
	961 if_icmpge (12, 4)
	962 31 (12, 4)
	964 aload (12, 4)
	965 #5 (12, 4)
	966 aload_0 (12, 4)
	967 getfield (12, 4)
	968 org/apache/commons/math3/optimization/general/LevenbergMarquardtOptimizer.permutation:[I (12, 4)
	970 iload (12, 4)
	971 #26 (12, 4)
	972 iaload (12, 4)
	973 daload (12, 4)
	974 dstore (12, 4)
	975 #27 (12, 4)
	976 dload (12, 4)
	977 #13 (12, 4)
	978 dload (12, 4)
	979 #27 (12, 4)
	980 dload (12, 4)
	981 #27 (12, 4)
	982 dmul (12, 4)
	983 dadd (12, 4)
	984 dstore (12, 4)
	985 #13 (12, 4)
	986 iinc (12, 4)
	987 #26 (12, 4)
	988 -89 (12, 4)
	989 goto (12, 4)
	990 -34 (12, 4)
	992 dload (11, 4)
	993 #11 (11, 4)
	994 dload_2 (11, 4)
	995 dload (11, 4)
	996 #13 (11, 4)
	997 dmul (11, 4)
	998 ddiv (11, 4)
	999 dstore (11, 4)
	1000 #26 (11, 4)
	1001 dload (12, 1)
	1002 #11 (12, 1)
	1003 dconst_0 (12, 1)
	1004 dcmpl (12, 1)
	1005 ifle (12, 1)
	1006 17 (12, 1)
	1008 dload (12, 1)
	1009 #15 (12, 1)
	1010 aload_0 (12, 1)
	1011 getfield (12, 1)
	1012 org/apache/commons/math3/optimization/general/LevenbergMarquardtOptimizer.lmPar:D (12, 1)
	1014 invokestatic (12, 1)
	1015 org/apache/commons/math3/util/FastMath.max:(DD)D (12, 1)
	1017 dstore (12, 1)
	1018 #15 (12, 1)
	1019 goto (12, 1)
	1020 21 (12, 1)
	1022 dload (13, 1)
	1023 #11 (13, 1)
	1024 dconst_0 (13, 1)
	1025 dcmpg (13, 1)
	1026 ifge (13, 1)
	1027 14 (13, 1)
	1029 dload (13, 1)
	1030 #19 (13, 1)
	1031 aload_0 (13, 1)
	1032 getfield (13, 1)
	1033 org/apache/commons/math3/optimization/general/LevenbergMarquardtOptimizer.lmPar:D (13, 1)
	1035 invokestatic (13, 1)
	1036 org/apache/commons/math3/util/FastMath.min:(DD)D (13, 1)
	1038 dstore (13, 1)
	1039 #19 (13, 1)
	1040 aload_0 (12, 4)
	1041 dload (12, 4)
	1042 #15 (12, 4)
	1043 aload_0 (12, 4)
	1044 getfield (12, 4)
	1045 org/apache/commons/math3/optimization/general/LevenbergMarquardtOptimizer.lmPar:D (12, 4)
	1047 dload (12, 4)
	1048 #26 (12, 4)
	1049 dadd (12, 4)
	1050 invokestatic (12, 4)
	1051 org/apache/commons/math3/util/FastMath.max:(DD)D (12, 4)
	1053 putfield (12, 4)
	1054 org/apache/commons/math3/optimization/general/LevenbergMarquardtOptimizer.lmPar:D (12, 4)
	1056 iinc (12, 4)
	1057 #21 (12, 4)
	1058 -89 (12, 4)
	1059 goto (12, 4)
	1060 -456 (12, 4)
	1062 return (0, 1)

Method: determineLMDirection
	0 iconst_0 (1, 4)
	1 istore (1, 4)
	2 #5 (1, 4)
	3 iload (1, 4)
	4 #5 (1, 4)
	5 aload_0 (1, 4)
	6 getfield (1, 4)
	7 org/apache/commons/math3/optimization/general/LevenbergMarquardtOptimizer.solvedCols:I (1, 4)
	9 if_icmpge (1, 4)
	10 87 (1, 4)
	12 aload_0 (1, 4)
	13 getfield (1, 4)
	14 org/apache/commons/math3/optimization/general/LevenbergMarquardtOptimizer.permutation:[I (1, 4)
	16 iload (1, 4)
	17 #5 (1, 4)
	18 iaload (1, 4)
	19 istore (1, 4)
	20 #6 (1, 4)
	21 iload (2, 4)
	22 #5 (2, 4)
	23 iconst_1 (2, 4)
	24 iadd (2, 4)
	25 istore (2, 4)
	26 #7 (2, 4)
	27 iload (2, 4)
	28 #7 (2, 4)
	29 aload_0 (2, 4)
	30 getfield (2, 4)
	31 org/apache/commons/math3/optimization/general/LevenbergMarquardtOptimizer.solvedCols:I (2, 4)
	33 if_icmpge (2, 4)
	34 34 (2, 4)
	36 aload_0 (2, 4)
	37 getfield (2, 4)
	38 org/apache/commons/math3/optimization/general/LevenbergMarquardtOptimizer.weightedJacobian:[[D (2, 4)
	40 iload (2, 4)
	41 #7 (2, 4)
	42 aaload (2, 4)
	43 iload (2, 4)
	44 #6 (2, 4)
	45 aload_0 (2, 4)
	46 getfield (2, 4)
	47 org/apache/commons/math3/optimization/general/LevenbergMarquardtOptimizer.weightedJacobian:[[D (2, 4)
	49 iload (2, 4)
	50 #5 (2, 4)
	51 aaload (2, 4)
	52 aload_0 (2, 4)
	53 getfield (2, 4)
	54 org/apache/commons/math3/optimization/general/LevenbergMarquardtOptimizer.permutation:[I (2, 4)
	56 iload (2, 4)
	57 #7 (2, 4)
	58 iaload (2, 4)
	59 daload (2, 4)
	60 dastore (2, 4)
	61 iinc (2, 4)
	62 #7 (2, 4)
	63 -89 (2, 4)
	64 goto (2, 4)
	65 -37 (2, 4)
	67 aload_0 (1, 4)
	68 getfield (1, 4)
	69 org/apache/commons/math3/optimization/general/LevenbergMarquardtOptimizer.lmDir:[D (1, 4)
	71 iload (1, 4)
	72 #5 (1, 4)
	73 aload_0 (1, 4)
	74 getfield (1, 4)
	75 org/apache/commons/math3/optimization/general/LevenbergMarquardtOptimizer.diagR:[D (1, 4)
	77 iload (1, 4)
	78 #6 (1, 4)
	79 daload (1, 4)
	80 dastore (1, 4)
	81 aload (1, 4)
	82 #4 (1, 4)
	83 iload (1, 4)
	84 #5 (1, 4)
	85 aload_1 (1, 4)
	86 iload (1, 4)
	87 #5 (1, 4)
	88 daload (1, 4)
	89 dastore (1, 4)
	90 iinc (1, 4)
	91 #5 (1, 4)
	92 -89 (1, 4)
	93 goto (1, 4)
	94 -90 (1, 4)
	96 iconst_0 (1, 4)
	97 istore (1, 4)
	98 #5 (1, 4)
	99 iload (1, 4)
	100 #5 (1, 4)
	101 aload_0 (1, 4)
	102 getfield (1, 4)
	103 org/apache/commons/math3/optimization/general/LevenbergMarquardtOptimizer.solvedCols:I (1, 4)
	105 if_icmpge (1, 4)
	106 361 (1, 4)
	108 aload_0 (1, 4)
	109 getfield (1, 4)
	110 org/apache/commons/math3/optimization/general/LevenbergMarquardtOptimizer.permutation:[I (1, 4)
	112 iload (1, 4)
	113 #5 (1, 4)
	114 iaload (1, 4)
	115 istore (1, 4)
	116 #6 (1, 4)
	117 aload_2 (1, 4)
	118 iload (1, 4)
	119 #6 (1, 4)
	120 daload (1, 4)
	121 dstore (1, 4)
	122 #7 (1, 4)
	123 dload (2, 1)
	124 #7 (2, 1)
	125 dconst_0 (2, 1)
	126 dcmpl (2, 1)
	127 ifeq (2, 1)
	128 14 (2, 1)
	130 aload_3 (2, 1)
	131 iload (2, 1)
	132 #5 (2, 1)
	133 iconst_1 (2, 1)
	134 iadd (2, 1)
	135 aload_3 (2, 1)
	136 arraylength (2, 1)
	137 dconst_0 (2, 1)
	138 invokestatic (2, 1)
	139 java/util/Arrays.fill:([DIID)V (2, 1)
	141 aload_3 (1, 4)
	142 iload (1, 4)
	143 #5 (1, 4)
	144 dload (1, 4)
	145 #7 (1, 4)
	146 dastore (1, 4)
	147 dconst_0 (3, 1)
	148 dstore (3, 1)
	149 #9 (3, 1)
	150 iload (4, 4)
	151 #5 (4, 4)
	152 istore (4, 4)
	153 #11 (4, 4)
	154 iload (4, 4)
	155 #11 (4, 4)
	156 aload_0 (4, 4)
	157 getfield (4, 4)
	158 org/apache/commons/math3/optimization/general/LevenbergMarquardtOptimizer.solvedCols:I (4, 4)
	160 if_icmpge (4, 4)
	161 259 (4, 4)
	163 aload_0 (4, 4)
	164 getfield (4, 4)
	165 org/apache/commons/math3/optimization/general/LevenbergMarquardtOptimizer.permutation:[I (4, 4)
	167 iload (4, 4)
	168 #11 (4, 4)
	169 iaload (4, 4)
	170 istore (4, 4)
	171 #12 (4, 4)
	172 aload_3 (5, 1)
	173 iload (5, 1)
	174 #11 (5, 1)
	175 daload (5, 1)
	176 dconst_0 (5, 1)
	177 dcmpl (5, 1)
	178 ifeq (5, 1)
	179 235 (5, 1)
	181 aload_0 (5, 1)
	182 getfield (5, 1)
	183 org/apache/commons/math3/optimization/general/LevenbergMarquardtOptimizer.weightedJacobian:[[D (5, 1)
	185 iload (5, 1)
	186 #11 (5, 1)
	187 aaload (5, 1)
	188 iload (5, 1)
	189 #12 (5, 1)
	190 daload (5, 1)
	191 dstore (5, 1)
	192 #17 (5, 1)
	193 dload (6, 1)
	194 #17 (6, 1)
	195 invokestatic (6, 1)
	196 org/apache/commons/math3/util/FastMath.abs:(D)D (6, 1)
	198 aload_3 (6, 1)
	199 iload (6, 1)
	200 #11 (6, 1)
	201 daload (6, 1)
	202 invokestatic (6, 1)
	203 org/apache/commons/math3/util/FastMath.abs:(D)D (6, 1)
	205 dcmpg (6, 1)
	206 ifge (6, 1)
	207 36 (6, 1)
	209 dload (6, 1)
	210 #17 (6, 1)
	211 aload_3 (6, 1)
	212 iload (6, 1)
	213 #11 (6, 1)
	214 daload (6, 1)
	215 ddiv (6, 1)
	216 dstore (6, 1)
	217 #19 (6, 1)
	218 dconst_1 (6, 1)
	219 dconst_1 (6, 1)
	220 dload (6, 1)
	221 #19 (6, 1)
	222 dload (6, 1)
	223 #19 (6, 1)
	224 dmul (6, 1)
	225 dadd (6, 1)
	226 invokestatic (6, 1)
	227 org/apache/commons/math3/util/FastMath.sqrt:(D)D (6, 1)
	229 ddiv (6, 1)
	230 dstore (6, 1)
	231 #13 (6, 1)
	232 dload (6, 1)
	233 #13 (6, 1)
	234 dload (6, 1)
	235 #19 (6, 1)
	236 dmul (6, 1)
	237 dstore (6, 1)
	238 #15 (6, 1)
	239 goto (7, 2)
	240 33 (7, 2)
	242 aload_3 (7, 2)
	243 iload (7, 2)
	244 #11 (7, 2)
	245 daload (7, 2)
	246 dload (7, 2)
	247 #17 (7, 2)
	248 ddiv (7, 2)
	249 dstore (7, 2)
	250 #19 (7, 2)
	251 dconst_1 (7, 2)
	252 dconst_1 (7, 2)
	253 dload (7, 2)
	254 #19 (7, 2)
	255 dload (7, 2)
	256 #19 (7, 2)
	257 dmul (7, 2)
	258 dadd (7, 2)
	259 invokestatic (7, 2)
	260 org/apache/commons/math3/util/FastMath.sqrt:(D)D (7, 2)
	262 ddiv (7, 2)
	263 dstore (7, 2)
	264 #15 (7, 2)
	265 dload (7, 2)
	266 #15 (7, 2)
	267 dload (7, 2)
	268 #19 (7, 2)
	269 dmul (7, 2)
	270 dstore (7, 2)
	271 #13 (7, 2)
	272 aload_0 (7, 1)
	273 getfield (7, 1)
	274 org/apache/commons/math3/optimization/general/LevenbergMarquardtOptimizer.weightedJacobian:[[D (7, 1)
	276 iload (7, 1)
	277 #11 (7, 1)
	278 aaload (7, 1)
	279 iload (7, 1)
	280 #12 (7, 1)
	281 dload (7, 1)
	282 #15 (7, 1)
	283 dload (7, 1)
	284 #17 (7, 1)
	285 dmul (7, 1)
	286 dload (7, 1)
	287 #13 (7, 1)
	288 aload_3 (7, 1)
	289 iload (7, 1)
	290 #11 (7, 1)
	291 daload (7, 1)
	292 dmul (7, 1)
	293 dadd (7, 1)
	294 dastore (7, 1)
	295 dload (7, 1)
	296 #15 (7, 1)
	297 aload (7, 1)
	298 #4 (7, 1)
	299 iload (7, 1)
	300 #11 (7, 1)
	301 daload (7, 1)
	302 dmul (7, 1)
	303 dload (7, 1)
	304 #13 (7, 1)
	305 dload (7, 1)
	306 #9 (7, 1)
	307 dmul (7, 1)
	308 dadd (7, 1)
	309 dstore (7, 1)
	310 #19 (7, 1)
	311 dload (7, 1)
	312 #13 (7, 1)
	313 dneg (7, 1)
	314 aload (7, 1)
	315 #4 (7, 1)
	316 iload (7, 1)
	317 #11 (7, 1)
	318 daload (7, 1)
	319 dmul (7, 1)
	320 dload (7, 1)
	321 #15 (7, 1)
	322 dload (7, 1)
	323 #9 (7, 1)
	324 dmul (7, 1)
	325 dadd (7, 1)
	326 dstore (7, 1)
	327 #9 (7, 1)
	328 aload (7, 1)
	329 #4 (7, 1)
	330 iload (7, 1)
	331 #11 (7, 1)
	332 dload (7, 1)
	333 #19 (7, 1)
	334 dastore (7, 1)
	335 iload (9, 4)
	336 #11 (9, 4)
	337 iconst_1 (9, 4)
	338 iadd (9, 4)
	339 istore (9, 4)
	340 #21 (9, 4)
	341 iload (9, 4)
	342 #21 (9, 4)
	343 aload_0 (9, 4)
	344 getfield (9, 4)
	345 org/apache/commons/math3/optimization/general/LevenbergMarquardtOptimizer.solvedCols:I (9, 4)
	347 if_icmpge (9, 4)
	348 66 (9, 4)
	350 aload_0 (9, 4)
	351 getfield (9, 4)
	352 org/apache/commons/math3/optimization/general/LevenbergMarquardtOptimizer.weightedJacobian:[[D (9, 4)
	354 iload (9, 4)
	355 #21 (9, 4)
	356 aaload (9, 4)
	357 iload (9, 4)
	358 #12 (9, 4)
	359 daload (9, 4)
	360 dstore (9, 4)
	361 #22 (9, 4)
	362 dload (9, 4)
	363 #15 (9, 4)
	364 dload (9, 4)
	365 #22 (9, 4)
	366 dmul (9, 4)
	367 dload (9, 4)
	368 #13 (9, 4)
	369 aload_3 (9, 4)
	370 iload (9, 4)
	371 #21 (9, 4)
	372 daload (9, 4)
	373 dmul (9, 4)
	374 dadd (9, 4)
	375 dstore (9, 4)
	376 #24 (9, 4)
	377 aload_3 (9, 4)
	378 iload (9, 4)
	379 #21 (9, 4)
	380 dload (9, 4)
	381 #13 (9, 4)
	382 dneg (9, 4)
	383 dload (9, 4)
	384 #22 (9, 4)
	385 dmul (9, 4)
	386 dload (9, 4)
	387 #15 (9, 4)
	388 aload_3 (9, 4)
	389 iload (9, 4)
	390 #21 (9, 4)
	391 daload (9, 4)
	392 dmul (9, 4)
	393 dadd (9, 4)
	394 dastore (9, 4)
	395 aload_0 (9, 4)
	396 getfield (9, 4)
	397 org/apache/commons/math3/optimization/general/LevenbergMarquardtOptimizer.weightedJacobian:[[D (9, 4)
	399 iload (9, 4)
	400 #21 (9, 4)
	401 aaload (9, 4)
	402 iload (9, 4)
	403 #12 (9, 4)
	404 dload (9, 4)
	405 #24 (9, 4)
	406 dastore (9, 4)
	407 iinc (9, 4)
	408 #21 (9, 4)
	409 -89 (9, 4)
	410 goto (9, 4)
	411 -69 (9, 4)
	413 iinc (9, 4)
	414 #11 (9, 4)
	415 -89 (9, 4)
	416 goto (9, 4)
	417 -262 (9, 4)
	419 aload_3 (8, 4)
	420 iload (8, 4)
	421 #5 (8, 4)
	422 aload_0 (8, 4)
	423 getfield (8, 4)
	424 org/apache/commons/math3/optimization/general/LevenbergMarquardtOptimizer.weightedJacobian:[[D (8, 4)
	426 iload (8, 4)
	427 #5 (8, 4)
	428 aaload (8, 4)
	429 aload_0 (8, 4)
	430 getfield (8, 4)
	431 org/apache/commons/math3/optimization/general/LevenbergMarquardtOptimizer.permutation:[I (8, 4)
	433 iload (8, 4)
	434 #5 (8, 4)
	435 iaload (8, 4)
	436 daload (8, 4)
	437 dastore (8, 4)
	438 aload_0 (8, 4)
	439 getfield (8, 4)
	440 org/apache/commons/math3/optimization/general/LevenbergMarquardtOptimizer.weightedJacobian:[[D (8, 4)
	442 iload (8, 4)
	443 #5 (8, 4)
	444 aaload (8, 4)
	445 aload_0 (8, 4)
	446 getfield (8, 4)
	447 org/apache/commons/math3/optimization/general/LevenbergMarquardtOptimizer.permutation:[I (8, 4)
	449 iload (8, 4)
	450 #5 (8, 4)
	451 iaload (8, 4)
	452 aload_0 (8, 4)
	453 getfield (8, 4)
	454 org/apache/commons/math3/optimization/general/LevenbergMarquardtOptimizer.lmDir:[D (8, 4)
	456 iload (8, 4)
	457 #5 (8, 4)
	458 daload (8, 4)
	459 dastore (8, 4)
	460 iinc (8, 4)
	461 #5 (8, 4)
	462 -89 (8, 4)
	463 goto (8, 4)
	464 -364 (8, 4)
	466 aload_0 (5, 1)
	467 getfield (5, 1)
	468 org/apache/commons/math3/optimization/general/LevenbergMarquardtOptimizer.solvedCols:I (5, 1)
	470 istore (5, 1)
	471 #5 (5, 1)
	472 iconst_0 (6, 4)
	473 istore (6, 4)
	474 #6 (6, 4)
	475 iload (6, 4)
	476 #6 (6, 4)
	477 aload_0 (6, 4)
	478 getfield (6, 4)
	479 org/apache/commons/math3/optimization/general/LevenbergMarquardtOptimizer.solvedCols:I (6, 4)
	481 if_icmpge (6, 4)
	482 46 (6, 4)
	484 aload_3 (7, 1)
	485 iload (7, 1)
	486 #6 (7, 1)
	487 daload (7, 1)
	488 dconst_0 (7, 1)
	489 dcmpl (7, 1)
	490 ifne (7, 1)
	491 16 (7, 1)
	493 iload (7, 1)
	494 #5 (7, 1)
	495 aload_0 (7, 1)
	496 getfield (7, 1)
	497 org/apache/commons/math3/optimization/general/LevenbergMarquardtOptimizer.solvedCols:I (7, 1)
	499 if_icmpne (7, 1)
	500 7 (7, 1)
	502 iload (7, 1)
	503 #6 (7, 1)
	504 istore (7, 1)
	505 #5 (7, 1)
	506 iload (7, 1)
	507 #5 (7, 1)
	508 aload_0 (7, 1)
	509 getfield (7, 1)
	510 org/apache/commons/math3/optimization/general/LevenbergMarquardtOptimizer.solvedCols:I (7, 1)
	512 if_icmpge (7, 1)
	513 9 (7, 1)
	515 aload (7, 1)
	516 #4 (7, 1)
	517 iload (7, 1)
	518 #6 (7, 1)
	519 dconst_0 (7, 1)
	520 dastore (7, 1)
	521 iinc (7, 1)
	522 #6 (7, 1)
	523 -89 (7, 1)
	524 goto (7, 1)
	525 -49 (7, 1)
	527 iload (7, 1)
	528 #5 (7, 1)
	529 ifle (7, 1)
	530 90 (7, 1)
	532 iload (8, 4)
	533 #5 (8, 4)
	534 iconst_1 (8, 4)
	535 isub (8, 4)
	536 istore (8, 4)
	537 #6 (8, 4)
	538 iload (8, 4)
	539 #6 (8, 4)
	540 iflt (8, 4)
	541 79 (8, 4)
	543 aload_0 (8, 4)
	544 getfield (8, 4)
	545 org/apache/commons/math3/optimization/general/LevenbergMarquardtOptimizer.permutation:[I (8, 4)
	547 iload (8, 4)
	548 #6 (8, 4)
	549 iaload (8, 4)
	550 istore (8, 4)
	551 #7 (8, 4)
	552 dconst_0 (8, 4)
	553 dstore (8, 4)
	554 #8 (8, 4)
	555 iload (9, 4)
	556 #6 (9, 4)
	557 iconst_1 (9, 4)
	558 iadd (9, 4)
	559 istore (9, 4)
	560 #10 (9, 4)
	561 iload (9, 4)
	562 #10 (9, 4)
	563 iload (9, 4)
	564 #5 (9, 4)
	565 if_icmpge (9, 4)
	566 30 (9, 4)
	568 dload (9, 4)
	569 #8 (9, 4)
	570 aload_0 (9, 4)
	571 getfield (9, 4)
	572 org/apache/commons/math3/optimization/general/LevenbergMarquardtOptimizer.weightedJacobian:[[D (9, 4)
	574 iload (9, 4)
	575 #10 (9, 4)
	576 aaload (9, 4)
	577 iload (9, 4)
	578 #7 (9, 4)
	579 daload (9, 4)
	580 aload (9, 4)
	581 #4 (9, 4)
	582 iload (9, 4)
	583 #10 (9, 4)
	584 daload (9, 4)
	585 dmul (9, 4)
	586 dadd (9, 4)
	587 dstore (9, 4)
	588 #8 (9, 4)
	589 iinc (9, 4)
	590 #10 (9, 4)
	591 -89 (9, 4)
	592 goto (9, 4)
	593 -31 (9, 4)
	595 aload (8, 4)
	596 #4 (8, 4)
	597 iload (8, 4)
	598 #6 (8, 4)
	599 aload (8, 4)
	600 #4 (8, 4)
	601 iload (8, 4)
	602 #6 (8, 4)
	603 daload (8, 4)
	604 dload (8, 4)
	605 #8 (8, 4)
	606 dsub (8, 4)
	607 aload_3 (8, 4)
	608 iload (8, 4)
	609 #6 (8, 4)
	610 daload (8, 4)
	611 ddiv (8, 4)
	612 dastore (8, 4)
	613 iinc (8, 4)
	614 #6 (8, 4)
	615 -89 (8, 4)
	616 goto (8, 4)
	617 -78 (8, 4)
	619 iconst_0 (7, 4)
	620 istore (7, 4)
	621 #6 (7, 4)
	622 iload (7, 4)
	623 #6 (7, 4)
	624 aload_0 (7, 4)
	625 getfield (7, 4)
	626 org/apache/commons/math3/optimization/general/LevenbergMarquardtOptimizer.lmDir:[D (7, 4)
	628 arraylength (7, 4)
	629 if_icmpge (7, 4)
	630 26 (7, 4)
	632 aload_0 (7, 4)
	633 getfield (7, 4)
	634 org/apache/commons/math3/optimization/general/LevenbergMarquardtOptimizer.lmDir:[D (7, 4)
	636 aload_0 (7, 4)
	637 getfield (7, 4)
	638 org/apache/commons/math3/optimization/general/LevenbergMarquardtOptimizer.permutation:[I (7, 4)
	640 iload (7, 4)
	641 #6 (7, 4)
	642 iaload (7, 4)
	643 aload (7, 4)
	644 #4 (7, 4)
	645 iload (7, 4)
	646 #6 (7, 4)
	647 daload (7, 4)
	648 dastore (7, 4)
	649 iinc (7, 4)
	650 #6 (7, 4)
	651 -89 (7, 4)
	652 goto (7, 4)
	653 -30 (7, 4)
	655 return (2, 1)

Method: qrDecomposition
	0 aload_0 (0, 0)
	1 aload_1 (0, 0)
	2 ldc2_w (0, 0)
	3 -1.0 (0, 0)
	5 invokeinterface (0, 0)
	6 org/apache/commons/math3/linear/RealMatrix.getData:()[[D (0, 0)
	8 0 (0, 0)
	10 invokeinterface (0, 0)
	11 org/apache/commons/math3/linear/RealMatrix.java/lang/Double (0, 0)
	13 0 (0, 0)
	15 putfield (0, 0)
	16 org/apache/commons/math3/optimization/general/LevenbergMarquardtOptimizer.weightedJacobian:[[D (0, 0)
	18 aload_0 (0, 0)
	19 getfield (0, 0)
	20 org/apache/commons/math3/optimization/general/LevenbergMarquardtOptimizer.weightedJacobian:[[D (0, 0)
	22 arraylength (0, 0)
	23 istore_2 (0, 0)
	24 aload_0 (0, 0)
	25 getfield (0, 0)
	26 org/apache/commons/math3/optimization/general/LevenbergMarquardtOptimizer.weightedJacobian:[[D (0, 0)
	28 iconst_0 (0, 0)
	29 aaload (0, 0)
	30 arraylength (0, 0)
	31 istore_3 (0, 0)
	32 iconst_0 (1, 4)
	33 istore (1, 4)
	34 #4 (1, 4)
	35 iload (1, 4)
	36 #4 (1, 4)
	37 iload_3 (1, 4)
	38 if_icmpge (1, 4)
	39 70 (1, 4)
	41 aload_0 (1, 4)
	42 getfield (1, 4)
	43 org/apache/commons/math3/optimization/general/LevenbergMarquardtOptimizer.permutation:[I (1, 4)
	45 iload (1, 4)
	46 #4 (1, 4)
	47 iload (1, 4)
	48 #4 (1, 4)
	49 iastore (1, 4)
	50 dconst_0 (1, 4)
	51 dstore (1, 4)
	52 #5 (1, 4)
	53 iconst_0 (2, 4)
	54 istore (2, 4)
	55 #7 (2, 4)
	56 iload (2, 4)
	57 #7 (2, 4)
	58 iload_2 (2, 4)
	59 if_icmpge (2, 4)
	60 31 (2, 4)
	62 aload_0 (2, 4)
	63 getfield (2, 4)
	64 org/apache/commons/math3/optimization/general/LevenbergMarquardtOptimizer.weightedJacobian:[[D (2, 4)
	66 iload (2, 4)
	67 #7 (2, 4)
	68 aaload (2, 4)
	69 iload (2, 4)
	70 #4 (2, 4)
	71 daload (2, 4)
	72 dstore (2, 4)
	73 #8 (2, 4)
	74 dload (2, 4)
	75 #5 (2, 4)
	76 dload (2, 4)
	77 #8 (2, 4)
	78 dload (2, 4)
	79 #8 (2, 4)
	80 dmul (2, 4)
	81 dadd (2, 4)
	82 dstore (2, 4)
	83 #5 (2, 4)
	84 iinc (2, 4)
	85 #7 (2, 4)
	86 -89 (2, 4)
	87 goto (2, 4)
	88 -31 (2, 4)
	90 aload_0 (1, 4)
	91 getfield (1, 4)
	92 org/apache/commons/math3/optimization/general/LevenbergMarquardtOptimizer.jacNorm:[D (1, 4)
	94 iload (1, 4)
	95 #4 (1, 4)
	96 dload (1, 4)
	97 #5 (1, 4)
	98 invokestatic (1, 4)
	99 org/apache/commons/math3/util/FastMath.sqrt:(D)D (1, 4)
	101 dastore (1, 4)
	102 iinc (1, 4)
	103 #4 (1, 4)
	104 -89 (1, 4)
	105 goto (1, 4)
	106 -70 (1, 4)
	108 iconst_0 (2, 4)
	109 istore (2, 4)
	110 #4 (2, 4)
	111 iload (2, 4)
	112 #4 (2, 4)
	113 iload_3 (2, 4)
	114 if_icmpge (2, 4)
	115 398 (2, 4)
	117 iconst_m1 (2, 4)
	118 istore (2, 4)
	119 #5 (2, 4)
	120 ldc2_w (2, 4)
	121 -inf (2, 4)
	123 dstore (2, 4)
	124 #6 (2, 4)
	125 iload (3, 4)
	126 #4 (3, 4)
	127 istore (3, 4)
	128 #8 (3, 4)
	129 iload (3, 4)
	130 #8 (3, 4)
	131 iload_3 (3, 4)
	132 if_icmpge (3, 4)
	133 116 (3, 4)
	135 dconst_0 (3, 4)
	136 dstore (3, 4)
	137 #9 (3, 4)
	138 iload (4, 4)
	139 #4 (4, 4)
	140 istore (4, 4)
	141 #11 (4, 4)
	142 iload (4, 4)
	143 #11 (4, 4)
	144 iload_2 (4, 4)
	145 if_icmpge (4, 4)
	146 36 (4, 4)
	148 aload_0 (4, 4)
	149 getfield (4, 4)
	150 org/apache/commons/math3/optimization/general/LevenbergMarquardtOptimizer.weightedJacobian:[[D (4, 4)
	152 iload (4, 4)
	153 #11 (4, 4)
	154 aaload (4, 4)
	155 aload_0 (4, 4)
	156 getfield (4, 4)
	157 org/apache/commons/math3/optimization/general/LevenbergMarquardtOptimizer.permutation:[I (4, 4)
	159 iload (4, 4)
	160 #8 (4, 4)
	161 iaload (4, 4)
	162 daload (4, 4)
	163 dstore (4, 4)
	164 #12 (4, 4)
	165 dload (4, 4)
	166 #9 (4, 4)
	167 dload (4, 4)
	168 #12 (4, 4)
	169 dload (4, 4)
	170 #12 (4, 4)
	171 dmul (4, 4)
	172 dadd (4, 4)
	173 dstore (4, 4)
	174 #9 (4, 4)
	175 iinc (4, 4)
	176 #11 (4, 4)
	177 -89 (4, 4)
	178 goto (4, 4)
	179 -36 (4, 4)
	181 dload (4, 1)
	182 #9 (4, 1)
	183 invokestatic (4, 1)
	184 java/lang/Double.isInfinite:(D)Z (4, 1)
	186 ifne (4, 1)
	187 11 (4, 1)
	189 dload (4, 1)
	190 #9 (4, 1)
	191 invokestatic (4, 1)
	192 java/lang/Double.isNaN:(D)Z (4, 1)
	194 ifeq (4, 1)
	195 32 (4, 1)
	197 new (4, 1)
	198 org/apache/commons/math3/exception/ConvergenceException (4, 1)
	200 dup (4, 1)
	201 getstatic (4, 1)
	202 org/apache/commons/math3/exception/util/LocalizedFormats.UNABLE_TO_PERFORM_QR_DECOMPOSITION_ON_JACOBIAN:Lorg/apache/commons/math3/exception/util/LocalizedFormats; (4, 1)
	204 iconst_2 (4, 1)
	205 anewarray (4, 1)
	206 java/lang/Object (4, 1)
	208 dup (4, 1)
	209 iconst_0 (4, 1)
	210 iload_2 (4, 1)
	211 invokestatic (4, 1)
	212 java/lang/Integer.valueOf:(I)Ljava/lang/Integer; (4, 1)
	214 aastore (4, 1)
	215 dup (4, 1)
	216 iconst_1 (4, 1)
	217 iload_3 (4, 1)
	218 invokestatic (4, 1)
	219 java/lang/Integer.valueOf:(I)Ljava/lang/Integer; (4, 1)
	221 aastore (4, 1)
	222 invokespecial (4, 1)
	223 org/apache/commons/math3/exception/ConvergenceException.<init>:(Lorg/apache/commons/math3/exception/util/Localizable;[Ljava/lang/Object;)V (4, 1)
	225 athrow (4, 1)
	226 dload (4, 1)
	227 #9 (4, 1)
	228 dload (4, 1)
	229 #6 (4, 1)
	230 dcmpl (4, 1)
	231 ifle (4, 1)
	232 11 (4, 1)
	234 iload (4, 1)
	235 #8 (4, 1)
	236 istore (4, 1)
	237 #5 (4, 1)
	238 dload (4, 1)
	239 #9 (4, 1)
	240 dstore (4, 1)
	241 #6 (4, 1)
	242 iinc (4, 1)
	243 #8 (4, 1)
	244 -89 (4, 1)
	245 goto (4, 1)
	246 -116 (4, 1)
	248 dload (4, 1)
	249 #6 (4, 1)
	250 aload_0 (4, 1)
	251 getfield (4, 1)
	252 org/apache/commons/math3/optimization/general/LevenbergMarquardtOptimizer.qrRankingThreshold:D (4, 1)
	254 dcmpg (4, 1)
	255 ifgt (4, 1)
	256 10 (4, 1)
	258 aload_0 (4, 1)
	259 iload (4, 1)
	260 #4 (4, 1)
	261 putfield (4, 1)
	262 org/apache/commons/math3/optimization/general/LevenbergMarquardtOptimizer.rank:I (4, 1)
	264 return (4, 1)
	265 aload_0 (3, 4)
	266 getfield (3, 4)
	267 org/apache/commons/math3/optimization/general/LevenbergMarquardtOptimizer.permutation:[I (3, 4)
	269 iload (3, 4)
	270 #5 (3, 4)
	271 iaload (3, 4)
	272 istore (3, 4)
	273 #8 (3, 4)
	274 aload_0 (3, 4)
	275 getfield (3, 4)
	276 org/apache/commons/math3/optimization/general/LevenbergMarquardtOptimizer.permutation:[I (3, 4)
	278 iload (3, 4)
	279 #5 (3, 4)
	280 aload_0 (3, 4)
	281 getfield (3, 4)
	282 org/apache/commons/math3/optimization/general/LevenbergMarquardtOptimizer.permutation:[I (3, 4)
	284 iload (3, 4)
	285 #4 (3, 4)
	286 iaload (3, 4)
	287 iastore (3, 4)
	288 aload_0 (3, 4)
	289 getfield (3, 4)
	290 org/apache/commons/math3/optimization/general/LevenbergMarquardtOptimizer.permutation:[I (3, 4)
	292 iload (3, 4)
	293 #4 (3, 4)
	294 iload (3, 4)
	295 #8 (3, 4)
	296 iastore (3, 4)
	297 aload_0 (3, 4)
	298 getfield (3, 4)
	299 org/apache/commons/math3/optimization/general/LevenbergMarquardtOptimizer.weightedJacobian:[[D (3, 4)
	301 iload (3, 4)
	302 #4 (3, 4)
	303 aaload (3, 4)
	304 iload (3, 4)
	305 #8 (3, 4)
	306 daload (3, 4)
	307 dstore (3, 4)
	308 #9 (3, 4)
	309 dload (3, 4)
	310 #9 (3, 4)
	311 dconst_0 (3, 4)
	312 dcmpl (3, 4)
	313 ifle (3, 4)
	314 12 (3, 4)
	316 dload (3, 4)
	317 #6 (3, 4)
	318 invokestatic (3, 4)
	319 org/apache/commons/math3/util/FastMath.sqrt:(D)D (3, 4)
	321 dneg (3, 4)
	322 goto (3, 4)
	323 8 (3, 4)
	325 dload (3, 4)
	326 #6 (3, 4)
	327 invokestatic (3, 4)
	328 org/apache/commons/math3/util/FastMath.sqrt:(D)D (3, 4)
	330 dstore (3, 4)
	331 #11 (3, 4)
	332 dconst_1 (3, 4)
	333 dload (3, 4)
	334 #6 (3, 4)
	335 dload (3, 4)
	336 #9 (3, 4)
	337 dload (3, 4)
	338 #11 (3, 4)
	339 dmul (3, 4)
	340 dsub (3, 4)
	341 ddiv (3, 4)
	342 dstore (3, 4)
	343 #13 (3, 4)
	344 aload_0 (3, 4)
	345 getfield (3, 4)
	346 org/apache/commons/math3/optimization/general/LevenbergMarquardtOptimizer.beta:[D (3, 4)
	348 iload (3, 4)
	349 #8 (3, 4)
	350 dload (3, 4)
	351 #13 (3, 4)
	352 dastore (3, 4)
	353 aload_0 (4, 4)
	354 getfield (4, 4)
	355 org/apache/commons/math3/optimization/general/LevenbergMarquardtOptimizer.diagR:[D (4, 4)
	357 iload (4, 4)
	358 #8 (4, 4)
	359 dload (4, 4)
	360 #11 (4, 4)
	361 dastore (4, 4)
	362 aload_0 (4, 4)
	363 getfield (4, 4)
	364 org/apache/commons/math3/optimization/general/LevenbergMarquardtOptimizer.weightedJacobian:[[D (4, 4)
	366 iload (4, 4)
	367 #4 (4, 4)
	368 aaload (4, 4)
	369 iload (4, 4)
	370 #8 (4, 4)
	371 dup2 (4, 4)
	372 daload (4, 4)
	373 dload (4, 4)
	374 #11 (4, 4)
	375 dsub (4, 4)
	376 dastore (4, 4)
	377 iload_3 (6, 4)
	378 iconst_1 (6, 4)
	379 isub (6, 4)
	380 iload (6, 4)
	381 #4 (6, 4)
	382 isub (6, 4)
	383 istore (6, 4)
	384 #15 (6, 4)
	385 iload (6, 4)
	386 #15 (6, 4)
	387 ifle (6, 4)
	388 119 (6, 4)
	390 dconst_0 (6, 4)
	391 dstore (6, 4)
	392 #16 (6, 4)
	393 iload (7, 4)
	394 #4 (7, 4)
	395 istore (7, 4)
	396 #18 (7, 4)
	397 iload (7, 4)
	398 #18 (7, 4)
	399 iload_2 (7, 4)
	400 if_icmpge (7, 4)
	401 43 (7, 4)
	403 dload (7, 4)
	404 #16 (7, 4)
	405 aload_0 (7, 4)
	406 getfield (7, 4)
	407 org/apache/commons/math3/optimization/general/LevenbergMarquardtOptimizer.weightedJacobian:[[D (7, 4)
	409 iload (7, 4)
	410 #18 (7, 4)
	411 aaload (7, 4)
	412 iload (7, 4)
	413 #8 (7, 4)
	414 daload (7, 4)
	415 aload_0 (7, 4)
	416 getfield (7, 4)
	417 org/apache/commons/math3/optimization/general/LevenbergMarquardtOptimizer.weightedJacobian:[[D (7, 4)
	419 iload (7, 4)
	420 #18 (7, 4)
	421 aaload (7, 4)
	422 aload_0 (7, 4)
	423 getfield (7, 4)
	424 org/apache/commons/math3/optimization/general/LevenbergMarquardtOptimizer.permutation:[I (7, 4)
	426 iload (7, 4)
	427 #4 (7, 4)
	428 iload (7, 4)
	429 #15 (7, 4)
	430 iadd (7, 4)
	431 iaload (7, 4)
	432 daload (7, 4)
	433 dmul (7, 4)
	434 dadd (7, 4)
	435 dstore (7, 4)
	436 #16 (7, 4)
	437 iinc (7, 4)
	438 #18 (7, 4)
	439 -89 (7, 4)
	440 goto (7, 4)
	441 -43 (7, 4)
	443 dload (6, 4)
	444 #16 (6, 4)
	445 dload (6, 4)
	446 #13 (6, 4)
	447 dmul (6, 4)
	448 dstore (6, 4)
	449 #16 (6, 4)
	450 iload (7, 4)
	451 #4 (7, 4)
	452 istore (7, 4)
	453 #18 (7, 4)
	454 iload (7, 4)
	455 #18 (7, 4)
	456 iload_2 (7, 4)
	457 if_icmpge (7, 4)
	458 43 (7, 4)
	460 aload_0 (7, 4)
	461 getfield (7, 4)
	462 org/apache/commons/math3/optimization/general/LevenbergMarquardtOptimizer.weightedJacobian:[[D (7, 4)
	464 iload (7, 4)
	465 #18 (7, 4)
	466 aaload (7, 4)
	467 aload_0 (7, 4)
	468 getfield (7, 4)
	469 org/apache/commons/math3/optimization/general/LevenbergMarquardtOptimizer.permutation:[I (7, 4)
	471 iload (7, 4)
	472 #4 (7, 4)
	473 iload (7, 4)
	474 #15 (7, 4)
	475 iadd (7, 4)
	476 iaload (7, 4)
	477 dup2 (7, 4)
	478 daload (7, 4)
	479 dload (7, 4)
	480 #16 (7, 4)
	481 aload_0 (7, 4)
	482 getfield (7, 4)
	483 org/apache/commons/math3/optimization/general/LevenbergMarquardtOptimizer.weightedJacobian:[[D (7, 4)
	485 iload (7, 4)
	486 #18 (7, 4)
	487 aaload (7, 4)
	488 iload (7, 4)
	489 #8 (7, 4)
	490 daload (7, 4)
	491 dmul (7, 4)
	492 dsub (7, 4)
	493 dastore (7, 4)
	494 iinc (7, 4)
	495 #18 (7, 4)
	496 -89 (7, 4)
	497 goto (7, 4)
	498 -43 (7, 4)
	500 iinc (7, 4)
	501 #15 (7, 4)
	502 -89 (7, 4)
	503 goto (7, 4)
	504 -118 (7, 4)
	506 iinc (7, 4)
	507 #4 (7, 4)
	508 -89 (7, 4)
	509 goto (7, 4)
	510 -398 (7, 4)
	512 aload_0 (6, 4)
	513 aload_0 (6, 4)
	514 getfield (6, 4)
	515 org/apache/commons/math3/optimization/general/LevenbergMarquardtOptimizer.solvedCols:I (6, 4)
	517 putfield (6, 4)
	518 org/apache/commons/math3/optimization/general/LevenbergMarquardtOptimizer.rank:I (6, 4)
	520 return (2, 4)

Method: qTy
	0 aload_0 (0, 0)
	1 getfield (0, 0)
	2 org/apache/commons/math3/optimization/general/LevenbergMarquardtOptimizer.weightedJacobian:[[D (0, 0)
	4 arraylength (0, 0)
	5 istore_2 (0, 0)
	6 aload_0 (0, 0)
	7 getfield (0, 0)
	8 org/apache/commons/math3/optimization/general/LevenbergMarquardtOptimizer.weightedJacobian:[[D (0, 0)
	10 iconst_0 (0, 0)
	11 aaload (0, 0)
	12 arraylength (0, 0)
	13 istore_3 (0, 0)
	14 iconst_0 (1, 4)
	15 istore (1, 4)
	16 #4 (1, 4)
	17 iload (1, 4)
	18 #4 (1, 4)
	19 iload_3 (1, 4)
	20 if_icmpge (1, 4)
	21 105 (1, 4)
	23 aload_0 (1, 4)
	24 getfield (1, 4)
	25 org/apache/commons/math3/optimization/general/LevenbergMarquardtOptimizer.permutation:[I (1, 4)
	27 iload (1, 4)
	28 #4 (1, 4)
	29 iaload (1, 4)
	30 istore (1, 4)
	31 #5 (1, 4)
	32 dconst_0 (1, 4)
	33 dstore (1, 4)
	34 #6 (1, 4)
	35 iload (2, 4)
	36 #4 (2, 4)
	37 istore (2, 4)
	38 #8 (2, 4)
	39 iload (2, 4)
	40 #8 (2, 4)
	41 iload_2 (2, 4)
	42 if_icmpge (2, 4)
	43 29 (2, 4)
	45 dload (2, 4)
	46 #6 (2, 4)
	47 aload_0 (2, 4)
	48 getfield (2, 4)
	49 org/apache/commons/math3/optimization/general/LevenbergMarquardtOptimizer.weightedJacobian:[[D (2, 4)
	51 iload (2, 4)
	52 #8 (2, 4)
	53 aaload (2, 4)
	54 iload (2, 4)
	55 #5 (2, 4)
	56 daload (2, 4)
	57 aload_1 (2, 4)
	58 iload (2, 4)
	59 #8 (2, 4)
	60 daload (2, 4)
	61 dmul (2, 4)
	62 dadd (2, 4)
	63 dstore (2, 4)
	64 #6 (2, 4)
	65 iinc (2, 4)
	66 #8 (2, 4)
	67 -89 (2, 4)
	68 goto (2, 4)
	69 -29 (2, 4)
	71 dload (1, 4)
	72 #6 (1, 4)
	73 aload_0 (1, 4)
	74 getfield (1, 4)
	75 org/apache/commons/math3/optimization/general/LevenbergMarquardtOptimizer.beta:[D (1, 4)
	77 iload (1, 4)
	78 #5 (1, 4)
	79 daload (1, 4)
	80 dmul (1, 4)
	81 dstore (1, 4)
	82 #6 (1, 4)
	83 iload (2, 4)
	84 #4 (2, 4)
	85 istore (2, 4)
	86 #8 (2, 4)
	87 iload (2, 4)
	88 #8 (2, 4)
	89 iload_2 (2, 4)
	90 if_icmpge (2, 4)
	91 29 (2, 4)
	93 aload_1 (2, 4)
	94 iload (2, 4)
	95 #8 (2, 4)
	96 dup2 (2, 4)
	97 daload (2, 4)
	98 dload (2, 4)
	99 #6 (2, 4)
	100 aload_0 (2, 4)
	101 getfield (2, 4)
	102 org/apache/commons/math3/optimization/general/LevenbergMarquardtOptimizer.weightedJacobian:[[D (2, 4)
	104 iload (2, 4)
	105 #8 (2, 4)
	106 aaload (2, 4)
	107 iload (2, 4)
	108 #5 (2, 4)
	109 daload (2, 4)
	110 dmul (2, 4)
	111 dsub (2, 4)
	112 dastore (2, 4)
	113 iinc (2, 4)
	114 #8 (2, 4)
	115 -89 (2, 4)
	116 goto (2, 4)
	117 -29 (2, 4)
	119 iinc (2, 4)
	120 #4 (2, 4)
	121 -89 (2, 4)
	122 goto (2, 4)
	123 -105 (2, 4)
	125 return (0, 0)

