Method: <init>
	0 aload_0 (0, 0)
	1 aload_2 (0, 0)
	2 invokespecial (0, 0)
	3 org/apache/commons/math3/optimization/general/AbstractScalarDifferentiableOptimizer.<init>:(Lorg/apache/commons/math3/optimization/ConvergenceChecker;)V (0, 0)
	5 aload_0 (0, 0)
	6 aload_1 (0, 0)
	7 putfield (0, 0)
	8 org/apache/commons/math3/optimization/general/NonLinearConjugateGradientOptimizer.updateFormula:Lorg/apache/commons/math3/optimization/general/ConjugateGradientFormula; (0, 0)
	10 aload_0 (0, 0)
	11 aload_3 (0, 0)
	12 putfield (0, 0)
	13 org/apache/commons/math3/optimization/general/NonLinearConjugateGradientOptimizer.solver:Lorg/apache/commons/math3/analysis/solvers/UnivariateSolver; (0, 0)
	15 aload_0 (0, 0)
	16 aload (0, 0)
	17 #4 (0, 0)
	18 putfield (0, 0)
	19 org/apache/commons/math3/optimization/general/NonLinearConjugateGradientOptimizer.preconditioner:Lorg/apache/commons/math3/optimization/general/Preconditioner; (0, 0)
	21 aload_0 (0, 0)
	22 dconst_1 (0, 0)
	23 putfield (0, 0)
	24 org/apache/commons/math3/optimization/general/NonLinearConjugateGradientOptimizer.initialStep:D (0, 0)
	26 return (0, 0)

Method: setInitialStep
	0 dload_1 (1, 1)
	1 dconst_0 (1, 1)
	2 dcmpg (1, 1)
	3 ifgt (1, 1)
	4 11 (1, 1)
	6 aload_0 (1, 1)
	7 dconst_1 (1, 1)
	8 putfield (1, 1)
	9 org/apache/commons/math3/optimization/general/NonLinearConjugateGradientOptimizer.initialStep:D (1, 1)
	11 goto (1, 1)
	12 8 (1, 1)
	14 aload_0 (2, 2)
	15 dload_1 (2, 2)
	16 putfield (2, 2)
	17 org/apache/commons/math3/optimization/general/NonLinearConjugateGradientOptimizer.initialStep:D (2, 2)
	19 return (0, 0)

Method: doOptimize
	0 aload_0 (0, 0)
	1 invokevirtual (0, 0)
	2 org/apache/commons/math3/optimization/general/NonLinearConjugateGradientOptimizer.getConvergenceChecker:()Lorg/apache/commons/math3/optimization/ConvergenceChecker; (0, 0)
	4 astore_1 (0, 0)
	5 aload_0 (0, 0)
	6 aload_0 (0, 0)
	7 invokevirtual (0, 0)
	8 org/apache/commons/math3/optimization/general/NonLinearConjugateGradientOptimizer.getStartPoint:()[D (0, 0)
	10 putfield (0, 0)
	11 org/apache/commons/math3/optimization/general/NonLinearConjugateGradientOptimizer.point:[D (0, 0)
	13 aload_0 (0, 0)
	14 invokevirtual (0, 0)
	15 org/apache/commons/math3/optimization/general/NonLinearConjugateGradientOptimizer.getGoalType:()Lorg/apache/commons/math3/optimization/GoalType; (0, 0)
	17 astore_2 (0, 0)
	18 aload_0 (0, 0)
	19 getfield (0, 0)
	20 org/apache/commons/math3/optimization/general/NonLinearConjugateGradientOptimizer.point:[D (0, 0)
	22 arraylength (0, 0)
	23 istore_3 (0, 0)
	24 aload_0 (0, 0)
	25 aload_0 (0, 0)
	26 getfield (0, 0)
	27 org/apache/commons/math3/optimization/general/NonLinearConjugateGradientOptimizer.point:[D (0, 0)
	29 invokevirtual (0, 0)
	30 org/apache/commons/math3/optimization/general/NonLinearConjugateGradientOptimizer.computeObjectiveGradient:([D)[D (0, 0)
	32 astore (0, 0)
	33 #4 (0, 0)
	34 aload_2 (1, 1)
	35 getstatic (1, 1)
	36 org/apache/commons/math3/optimization/GoalType.MINIMIZE:Lorg/apache/commons/math3/optimization/GoalType; (1, 1)
	38 if_acmpne (1, 1)
	39 29 (1, 1)
	41 iconst_0 (2, 4)
	42 istore (2, 4)
	43 #5 (2, 4)
	44 iload (2, 4)
	45 #5 (2, 4)
	46 iload_3 (2, 4)
	47 if_icmpge (2, 4)
	48 20 (2, 4)
	50 aload (2, 4)
	51 #4 (2, 4)
	52 iload (2, 4)
	53 #5 (2, 4)
	54 aload (2, 4)
	55 #4 (2, 4)
	56 iload (2, 4)
	57 #5 (2, 4)
	58 daload (2, 4)
	59 dneg (2, 4)
	60 dastore (2, 4)
	61 iinc (2, 4)
	62 #5 (2, 4)
	63 -89 (2, 4)
	64 goto (2, 4)
	65 -20 (2, 4)
	67 aload_0 (0, 0)
	68 getfield (0, 0)
	69 org/apache/commons/math3/optimization/general/NonLinearConjugateGradientOptimizer.preconditioner:Lorg/apache/commons/math3/optimization/general/Preconditioner; (0, 0)
	71 aload_0 (0, 0)
	72 getfield (0, 0)
	73 org/apache/commons/math3/optimization/general/NonLinearConjugateGradientOptimizer.point:[D (0, 0)
	75 aload (0, 0)
	76 #4 (0, 0)
	77 invokeinterface (0, 0)
	78 org/apache/commons/math3/optimization/general/Preconditioner.[D (0, 0)
	80 0 (0, 0)
	82 astore (0, 0)
	83 #5 (0, 0)
	84 aload (0, 0)
	85 #5 (0, 0)
	86 invokevirtual (0, 0)
	87 [D.clone:()Ljava/lang/Object; (0, 0)
	89 checkcast (0, 0)
	90 [D (0, 0)
	92 astore (0, 0)
	93 #6 (0, 0)
	94 dconst_0 (0, 0)
	95 dstore (0, 0)
	96 #7 (0, 0)
	97 iconst_0 (1, 4)
	98 istore (1, 4)
	99 #9 (1, 4)
	100 iload (1, 4)
	101 #9 (1, 4)
	102 iload_3 (1, 4)
	103 if_icmpge (1, 4)
	104 25 (1, 4)
	106 dload (1, 4)
	107 #7 (1, 4)
	108 aload (1, 4)
	109 #4 (1, 4)
	110 iload (1, 4)
	111 #9 (1, 4)
	112 daload (1, 4)
	113 aload (1, 4)
	114 #6 (1, 4)
	115 iload (1, 4)
	116 #9 (1, 4)
	117 daload (1, 4)
	118 dmul (1, 4)
	119 dadd (1, 4)
	120 dstore (1, 4)
	121 #7 (1, 4)
	122 iinc (1, 4)
	123 #9 (1, 4)
	124 -89 (1, 4)
	125 goto (1, 4)
	126 -25 (1, 4)
	128 aconst_null (0, 0)
	129 astore (0, 0)
	130 #9 (0, 0)
	131 iconst_0 (0, 0)
	132 istore (0, 0)
	133 #10 (0, 0)
	134 aload_0 (0, 0)
	135 invokevirtual (0, 0)
	136 org/apache/commons/math3/optimization/general/NonLinearConjugateGradientOptimizer.getMaxEvaluations:()I (0, 0)
	138 istore (0, 0)
	139 #11 (0, 0)
	140 iinc (1, 3)
	141 #10 (1, 3)
	142 42 (1, 3)
	143 aload_0 (1, 3)
	144 aload_0 (1, 3)
	145 getfield (1, 3)
	146 org/apache/commons/math3/optimization/general/NonLinearConjugateGradientOptimizer.point:[D (1, 3)
	148 invokevirtual (1, 3)
	149 org/apache/commons/math3/optimization/general/NonLinearConjugateGradientOptimizer.computeObjectiveValue:([D)D (1, 3)
	151 dstore (1, 3)
	152 #12 (1, 3)
	153 aload (1, 3)
	154 #9 (1, 3)
	155 astore (1, 3)
	156 #14 (1, 3)
	157 new (1, 3)
	158 org/apache/commons/math3/optimization/PointValuePair (1, 3)
	160 dup (1, 3)
	161 aload_0 (1, 3)
	162 getfield (1, 3)
	163 org/apache/commons/math3/optimization/general/NonLinearConjugateGradientOptimizer.point:[D (1, 3)
	165 dload (1, 3)
	166 #12 (1, 3)
	167 invokespecial (1, 3)
	168 org/apache/commons/math3/optimization/PointValuePair.<init>:([DD)V (1, 3)
	170 astore (1, 3)
	171 #9 (1, 3)
	172 aload (2, 1)
	173 #14 (2, 1)
	174 ifnull (2, 1)
	175 21 (2, 1)
	177 aload_1 (2, 1)
	178 iload (2, 1)
	179 #10 (2, 1)
	180 aload (2, 1)
	181 #14 (2, 1)
	182 aload (2, 1)
	183 #9 (2, 1)
	184 invokeinterface (2, 1)
	185 org/apache/commons/math3/optimization/ConvergenceChecker.org/apache/commons/math3/optimization/general/NonLinearConjugateGradientOptimizer$LineSearchFunction (2, 1)
	187 0 (2, 1)
	189 ifeq (2, 1)
	190 6 (2, 1)
	192 aload (2, 1)
	193 #9 (2, 1)
	194 areturn (2, 1)
	195 new (1, 3)
	196 org/apache/commons/math3/optimization/general/NonLinearConjugateGradientOptimizer$LineSearchFunction (1, 3)
	198 dup (1, 3)
	199 aload_0 (1, 3)
	200 aload (1, 3)
	201 #6 (1, 3)
	202 invokespecial (1, 3)
	203 org/apache/commons/math3/optimization/general/NonLinearConjugateGradientOptimizer$LineSearchFunction.<init>:(Lorg/apache/commons/math3/optimization/general/NonLinearConjugateGradientOptimizer;[D)V (1, 3)
	205 astore (1, 3)
	206 #15 (1, 3)
	207 aload_0 (1, 3)
	208 aload (1, 3)
	209 #15 (1, 3)
	210 dconst_0 (1, 3)
	211 aload_0 (1, 3)
	212 getfield (1, 3)
	213 org/apache/commons/math3/optimization/general/NonLinearConjugateGradientOptimizer.initialStep:D (1, 3)
	215 invokespecial (1, 3)
	216 org/apache/commons/math3/optimization/general/NonLinearConjugateGradientOptimizer.findUpperBound:(Lorg/apache/commons/math3/analysis/UnivariateFunction;DD)D (1, 3)
	218 dstore (1, 3)
	219 #16 (1, 3)
	220 aload_0 (1, 3)
	221 getfield (1, 3)
	222 org/apache/commons/math3/optimization/general/NonLinearConjugateGradientOptimizer.solver:Lorg/apache/commons/math3/analysis/solvers/UnivariateSolver; (1, 3)
	224 iload (1, 3)
	225 #11 (1, 3)
	226 aload (1, 3)
	227 #15 (1, 3)
	228 dconst_0 (1, 3)
	229 dload (1, 3)
	230 #16 (1, 3)
	231 ldc2_w (1, 3)
	232 1e-15 (1, 3)
	234 invokeinterface (1, 3)
	235 org/apache/commons/math3/analysis/solvers/UnivariateSolver.getEvaluations:()I (1, 3)
	237 0 (1, 3)
	239 dstore (1, 3)
	240 #18 (1, 3)
	241 iload (1, 3)
	242 #11 (1, 3)
	243 aload_0 (1, 3)
	244 getfield (1, 3)
	245 org/apache/commons/math3/optimization/general/NonLinearConjugateGradientOptimizer.solver:Lorg/apache/commons/math3/analysis/solvers/UnivariateSolver; (1, 3)
	247 invokeinterface (1, 3)
	248 org/apache/commons/math3/analysis/solvers/UnivariateSolver.org/apache/commons/math3/optimization/general/ConjugateGradientFormula (1, 3)
	250 0 (1, 3)
	252 isub (1, 3)
	253 istore (1, 3)
	254 #11 (1, 3)
	255 iconst_0 (2, 4)
	256 istore (2, 4)
	257 #20 (2, 4)
	258 iload (2, 4)
	259 #20 (2, 4)
	260 aload_0 (2, 4)
	261 getfield (2, 4)
	262 org/apache/commons/math3/optimization/general/NonLinearConjugateGradientOptimizer.point:[D (2, 4)
	264 arraylength (2, 4)
	265 if_icmpge (2, 4)
	266 27 (2, 4)
	268 aload_0 (2, 4)
	269 getfield (2, 4)
	270 org/apache/commons/math3/optimization/general/NonLinearConjugateGradientOptimizer.point:[D (2, 4)
	272 iload (2, 4)
	273 #20 (2, 4)
	274 dup2 (2, 4)
	275 daload (2, 4)
	276 dload (2, 4)
	277 #18 (2, 4)
	278 aload (2, 4)
	279 #6 (2, 4)
	280 iload (2, 4)
	281 #20 (2, 4)
	282 daload (2, 4)
	283 dmul (2, 4)
	284 dadd (2, 4)
	285 dastore (2, 4)
	286 iinc (2, 4)
	287 #20 (2, 4)
	288 -89 (2, 4)
	289 goto (2, 4)
	290 -31 (2, 4)
	292 aload_0 (1, 3)
	293 aload_0 (1, 3)
	294 getfield (1, 3)
	295 org/apache/commons/math3/optimization/general/NonLinearConjugateGradientOptimizer.point:[D (1, 3)
	297 invokevirtual (1, 3)
	298 org/apache/commons/math3/optimization/general/NonLinearConjugateGradientOptimizer.computeObjectiveGradient:([D)[D (1, 3)
	300 astore (1, 3)
	301 #4 (1, 3)
	302 aload_2 (2, 1)
	303 getstatic (2, 1)
	304 org/apache/commons/math3/optimization/GoalType.MINIMIZE:Lorg/apache/commons/math3/optimization/GoalType; (2, 1)
	306 if_acmpne (2, 1)
	307 29 (2, 1)
	309 iconst_0 (3, 4)
	310 istore (3, 4)
	311 #20 (3, 4)
	312 iload (3, 4)
	313 #20 (3, 4)
	314 iload_3 (3, 4)
	315 if_icmpge (3, 4)
	316 20 (3, 4)
	318 aload (3, 4)
	319 #4 (3, 4)
	320 iload (3, 4)
	321 #20 (3, 4)
	322 aload (3, 4)
	323 #4 (3, 4)
	324 iload (3, 4)
	325 #20 (3, 4)
	326 daload (3, 4)
	327 dneg (3, 4)
	328 dastore (3, 4)
	329 iinc (3, 4)
	330 #20 (3, 4)
	331 -89 (3, 4)
	332 goto (3, 4)
	333 -20 (3, 4)
	335 dload (1, 3)
	336 #7 (1, 3)
	337 dstore (1, 3)
	338 #20 (1, 3)
	339 aload_0 (1, 3)
	340 getfield (1, 3)
	341 org/apache/commons/math3/optimization/general/NonLinearConjugateGradientOptimizer.preconditioner:Lorg/apache/commons/math3/optimization/general/Preconditioner; (1, 3)
	343 aload_0 (1, 3)
	344 getfield (1, 3)
	345 org/apache/commons/math3/optimization/general/NonLinearConjugateGradientOptimizer.point:[D (1, 3)
	347 aload (1, 3)
	348 #4 (1, 3)
	349 invokeinterface (1, 3)
	350 org/apache/commons/math3/optimization/general/Preconditioner.[D (1, 3)
	352 0 (1, 3)
	354 astore (1, 3)
	355 #22 (1, 3)
	356 dconst_0 (1, 3)
	357 dstore (1, 3)
	358 #7 (1, 3)
	359 iconst_0 (2, 4)
	360 istore (2, 4)
	361 #23 (2, 4)
	362 iload (2, 4)
	363 #23 (2, 4)
	364 iload_3 (2, 4)
	365 if_icmpge (2, 4)
	366 25 (2, 4)
	368 dload (2, 4)
	369 #7 (2, 4)
	370 aload (2, 4)
	371 #4 (2, 4)
	372 iload (2, 4)
	373 #23 (2, 4)
	374 daload (2, 4)
	375 aload (2, 4)
	376 #22 (2, 4)
	377 iload (2, 4)
	378 #23 (2, 4)
	379 daload (2, 4)
	380 dmul (2, 4)
	381 dadd (2, 4)
	382 dstore (2, 4)
	383 #7 (2, 4)
	384 iinc (2, 4)
	385 #23 (2, 4)
	386 -89 (2, 4)
	387 goto (2, 4)
	388 -25 (2, 4)
	390 aload_0 (2, 1)
	391 getfield (2, 1)
	392 org/apache/commons/math3/optimization/general/NonLinearConjugateGradientOptimizer.updateFormula:Lorg/apache/commons/math3/optimization/general/ConjugateGradientFormula; (2, 1)
	394 getstatic (2, 1)
	395 org/apache/commons/math3/optimization/general/ConjugateGradientFormula.FLETCHER_REEVES:Lorg/apache/commons/math3/optimization/general/ConjugateGradientFormula; (2, 1)
	397 if_acmpne (2, 1)
	398 13 (2, 1)
	400 dload (2, 1)
	401 #7 (2, 1)
	402 dload (2, 1)
	403 #20 (2, 1)
	404 ddiv (2, 1)
	405 dstore (2, 1)
	406 #23 (2, 1)
	407 goto (2, 1)
	408 49 (2, 1)
	410 dconst_0 (3, 2)
	411 dstore (3, 2)
	412 #25 (3, 2)
	413 iconst_0 (4, 4)
	414 istore (4, 4)
	415 #27 (4, 4)
	416 iload (4, 4)
	417 #27 (4, 4)
	418 aload (4, 4)
	419 #4 (4, 4)
	420 arraylength (4, 4)
	421 if_icmpge (4, 4)
	422 25 (4, 4)
	424 dload (4, 4)
	425 #25 (4, 4)
	426 aload (4, 4)
	427 #4 (4, 4)
	428 iload (4, 4)
	429 #27 (4, 4)
	430 daload (4, 4)
	431 aload (4, 4)
	432 #5 (4, 4)
	433 iload (4, 4)
	434 #27 (4, 4)
	435 daload (4, 4)
	436 dmul (4, 4)
	437 dadd (4, 4)
	438 dstore (4, 4)
	439 #25 (4, 4)
	440 iinc (4, 4)
	441 #27 (4, 4)
	442 -89 (4, 4)
	443 goto (4, 4)
	444 -27 (4, 4)
	446 dload (3, 2)
	447 #7 (3, 2)
	448 dload (3, 2)
	449 #25 (3, 2)
	450 dsub (3, 2)
	451 dload (3, 2)
	452 #20 (3, 2)
	453 ddiv (3, 2)
	454 dstore (3, 2)
	455 #23 (3, 2)
	456 aload (1, 3)
	457 #22 (1, 3)
	458 astore (1, 3)
	459 #5 (1, 3)
	460 iload (2, 1)
	461 #10 (2, 1)
	462 iload_3 (2, 1)
	463 irem (2, 1)
	464 ifeq (2, 1)
	465 10 (2, 1)
	467 dload (2, 1)
	468 #23 (2, 1)
	469 dconst_0 (2, 1)
	470 dcmpg (2, 1)
	471 ifge (2, 1)
	472 16 (2, 1)
	474 aload (2, 1)
	475 #5 (2, 1)
	476 invokevirtual (2, 1)
	477 [D.clone:()Ljava/lang/Object; (2, 1)
	479 checkcast (2, 1)
	480 [D (2, 1)
	482 astore (2, 1)
	483 #6 (2, 1)
	484 goto (2, 1)
	485 37 (2, 1)
	487 iconst_0 (4, 4)
	488 istore (4, 4)
	489 #25 (4, 4)
	490 iload (4, 4)
	491 #25 (4, 4)
	492 iload_3 (4, 4)
	493 if_icmpge (4, 4)
	494 28 (4, 4)
	496 aload (4, 4)
	497 #6 (4, 4)
	498 iload (4, 4)
	499 #25 (4, 4)
	500 aload (4, 4)
	501 #5 (4, 4)
	502 iload (4, 4)
	503 #25 (4, 4)
	504 daload (4, 4)
	505 dload (4, 4)
	506 #23 (4, 4)
	507 aload (4, 4)
	508 #6 (4, 4)
	509 iload (4, 4)
	510 #25 (4, 4)
	511 daload (4, 4)
	512 dmul (4, 4)
	513 dadd (4, 4)
	514 dastore (4, 4)
	515 iinc (4, 4)
	516 #25 (4, 4)
	517 -89 (4, 4)
	518 goto (4, 4)
	519 -28 (4, 4)
	521 goto (0, 0)
	522 -381 (0, 0)

Method: findUpperBound
	0 aload_1 (0, 0)
	1 dload_2 (0, 0)
	2 invokeinterface (0, 0)
	3 org/apache/commons/math3/analysis/UnivariateFunction.java/lang/Double (0, 0)
	5 0 (0, 0)
	7 dstore (0, 0)
	8 #6 (0, 0)
	9 dload (0, 0)
	10 #6 (0, 0)
	11 dstore (0, 0)
	12 #8 (0, 0)
	13 dload (1, 4)
	14 #4 (1, 4)
	15 dstore (1, 4)
	16 #10 (1, 4)
	17 dload (1, 4)
	18 #10 (1, 4)
	19 ldc2_w (1, 4)
	20 1.7976931348623157e+308 (1, 4)
	22 dcmpg (1, 4)
	23 ifge (1, 4)
	24 51 (1, 4)
	26 dload_2 (1, 4)
	27 dload (1, 4)
	28 #10 (1, 4)
	29 dadd (1, 4)
	30 dstore (1, 4)
	31 #12 (1, 4)
	32 aload_1 (1, 4)
	33 dload (1, 4)
	34 #12 (1, 4)
	35 invokeinterface (1, 4)
	36 org/apache/commons/math3/analysis/UnivariateFunction.java/lang/Double (1, 4)
	38 0 (1, 4)
	40 dstore (1, 4)
	41 #8 (1, 4)
	42 dload (2, 1)
	43 #6 (2, 1)
	44 dload (2, 1)
	45 #8 (2, 1)
	46 dmul (2, 1)
	47 dconst_0 (2, 1)
	48 dcmpg (2, 1)
	49 ifgt (2, 1)
	50 6 (2, 1)
	52 dload (2, 1)
	53 #12 (2, 1)
	54 dreturn (2, 1)
	55 dload (2, 1)
	56 #10 (2, 1)
	57 ldc2_w (2, 1)
	58 2.0 (2, 1)
	60 dload (2, 1)
	61 #6 (2, 1)
	62 dload (2, 1)
	63 #8 (2, 1)
	64 ddiv (2, 1)
	65 invokestatic (2, 1)
	66 org/apache/commons/math3/util/FastMath.max:(DD)D (2, 1)
	68 dmul (2, 1)
	69 dstore (2, 1)
	70 #10 (2, 1)
	71 goto (2, 1)
	72 -54 (2, 1)
	74 new (1, 4)
	75 org/apache/commons/math3/exception/MathIllegalStateException (1, 4)
	77 dup (1, 4)
	78 getstatic (1, 4)
	79 org/apache/commons/math3/exception/util/LocalizedFormats.UNABLE_TO_BRACKET_OPTIMUM_IN_LINE_SEARCH:Lorg/apache/commons/math3/exception/util/LocalizedFormats; (1, 4)
	81 iconst_0 (1, 4)
	82 anewarray (1, 4)
	83 java/lang/Object (1, 4)
	85 invokespecial (1, 4)
	86 org/apache/commons/math3/exception/MathIllegalStateException.<init>:(Lorg/apache/commons/math3/exception/util/Localizable;[Ljava/lang/Object;)V (1, 4)
	88 athrow (1, 4)

Method: access$000
	0 aload_0 (0, 0)
	1 getfield (0, 0)
	2 org/apache/commons/math3/optimization/general/NonLinearConjugateGradientOptimizer.point:[D (0, 0)
	4 areturn (0, 0)

