Method: g
	0 aload_1 (1, 1)
	1 arraylength (1, 1)
	2 iconst_2 (1, 1)
	3 if_icmpge (1, 1)
	4 14 (1, 1)
	6 new (1, 1)
	7 org/apache/commons/math3/exception/DimensionMismatchException (1, 1)
	9 dup (1, 1)
	10 aload_1 (1, 1)
	11 arraylength (1, 1)
	12 iconst_2 (1, 1)
	13 invokespecial (1, 1)
	14 org/apache/commons/math3/exception/DimensionMismatchException.<init>:(II)V (1, 1)
	16 athrow (1, 1)
	17 aload_1 (1, 1)
	18 arraylength (1, 1)
	19 aload_2 (1, 1)
	20 arraylength (1, 1)
	21 if_icmpeq (1, 1)
	22 15 (1, 1)
	24 new (1, 1)
	25 org/apache/commons/math3/exception/DimensionMismatchException (1, 1)
	27 dup (1, 1)
	28 aload_1 (1, 1)
	29 arraylength (1, 1)
	30 aload_2 (1, 1)
	31 arraylength (1, 1)
	32 invokespecial (1, 1)
	33 org/apache/commons/math3/exception/DimensionMismatchException.<init>:(II)V (1, 1)
	35 athrow (1, 1)
	36 aload_1 (0, 0)
	37 invokestatic (0, 0)
	38 org/apache/commons/math3/util/MathArrays.checkPositive:([D)V (0, 0)
	40 aload_2 (0, 0)
	41 invokestatic (0, 0)
	42 org/apache/commons/math3/util/MathArrays.checkNonNegative:([J)V (0, 0)
	44 dconst_0 (0, 0)
	45 dstore_3 (0, 0)
	46 dconst_0 (0, 0)
	47 dstore (0, 0)
	48 #5 (0, 0)
	49 iconst_0 (1, 4)
	50 istore (1, 4)
	51 #7 (1, 4)
	52 iload (1, 4)
	53 #7 (1, 4)
	54 aload_2 (1, 4)
	55 arraylength (1, 4)
	56 if_icmpge (1, 4)
	57 26 (1, 4)
	59 dload_3 (1, 4)
	60 aload_1 (1, 4)
	61 iload (1, 4)
	62 #7 (1, 4)
	63 daload (1, 4)
	64 dadd (1, 4)
	65 dstore_3 (1, 4)
	66 dload (1, 4)
	67 #5 (1, 4)
	68 aload_2 (1, 4)
	69 iload (1, 4)
	70 #7 (1, 4)
	71 laload (1, 4)
	72 l2d (1, 4)
	73 dadd (1, 4)
	74 dstore (1, 4)
	75 #5 (1, 4)
	76 iinc (1, 4)
	77 #7 (1, 4)
	78 -89 (1, 4)
	79 goto (1, 4)
	80 -27 (1, 4)
	82 dconst_1 (0, 0)
	83 dstore (0, 0)
	84 #7 (0, 0)
	85 iconst_0 (0, 0)
	86 istore (0, 0)
	87 #9 (0, 0)
	88 dload_3 (1, 1)
	89 dload (1, 1)
	90 #5 (1, 1)
	91 dsub (1, 1)
	92 invokestatic (1, 1)
	93 org/apache/commons/math3/util/FastMath.abs:(D)D (1, 1)
	95 ldc2_w (1, 1)
	96 1e-05 (1, 1)
	98 dcmpl (1, 1)
	99 ifle (1, 1)
	100 12 (1, 1)
	102 dload (1, 1)
	103 #5 (1, 1)
	104 dload_3 (1, 1)
	105 ddiv (1, 1)
	106 dstore (1, 1)
	107 #7 (1, 1)
	108 iconst_1 (1, 1)
	109 istore (1, 1)
	110 #9 (1, 1)
	111 dconst_0 (0, 0)
	112 dstore (0, 0)
	113 #10 (0, 0)
	114 iconst_0 (1, 4)
	115 istore (1, 4)
	116 #12 (1, 4)
	117 iload (1, 4)
	118 #12 (1, 4)
	119 aload_2 (1, 4)
	120 arraylength (1, 4)
	121 if_icmpge (1, 4)
	122 61 (1, 4)
	124 iload (1, 4)
	125 #9 (1, 4)
	126 ifeq (1, 4)
	127 22 (1, 4)
	129 aload_2 (1, 4)
	130 iload (1, 4)
	131 #12 (1, 4)
	132 laload (1, 4)
	133 l2d (1, 4)
	134 dload (1, 4)
	135 #7 (1, 4)
	136 aload_1 (1, 4)
	137 iload (1, 4)
	138 #12 (1, 4)
	139 daload (1, 4)
	140 dmul (1, 4)
	141 ddiv (1, 4)
	142 invokestatic (1, 4)
	143 org/apache/commons/math3/util/FastMath.log:(D)D (1, 4)
	145 goto (1, 4)
	146 16 (1, 4)
	148 aload_2 (1, 4)
	149 iload (1, 4)
	150 #12 (1, 4)
	151 laload (1, 4)
	152 l2d (1, 4)
	153 aload_1 (1, 4)
	154 iload (1, 4)
	155 #12 (1, 4)
	156 daload (1, 4)
	157 ddiv (1, 4)
	158 invokestatic (1, 4)
	159 org/apache/commons/math3/util/FastMath.log:(D)D (1, 4)
	161 dstore (1, 4)
	162 #13 (1, 4)
	163 dload (1, 4)
	164 #10 (1, 4)
	165 aload_2 (1, 4)
	166 iload (1, 4)
	167 #12 (1, 4)
	168 laload (1, 4)
	169 l2d (1, 4)
	170 dload (1, 4)
	171 #13 (1, 4)
	172 dmul (1, 4)
	173 dadd (1, 4)
	174 dstore (1, 4)
	175 #10 (1, 4)
	176 iinc (1, 4)
	177 #12 (1, 4)
	178 -89 (1, 4)
	179 goto (1, 4)
	180 -62 (1, 4)
	182 ldc2_w (0, 0)
	183 2.0 (0, 0)
	185 dload (0, 0)
	186 #10 (0, 0)
	187 dmul (0, 0)
	188 dreturn (0, 0)

Method: gTest
	0 dload_3 (1, 1)
	1 dconst_0 (1, 1)
	2 dcmpg (1, 1)
	3 ifle (1, 1)
	4 11 (1, 1)
	6 dload_3 (1, 1)
	7 ldc2_w (1, 1)
	8 0.5 (1, 1)
	10 dcmpl (1, 1)
	11 ifle (1, 1)
	12 28 (1, 1)
	14 new (1, 1)
	15 org/apache/commons/math3/exception/OutOfRangeException (1, 1)
	17 dup (1, 1)
	18 getstatic (1, 1)
	19 org/apache/commons/math3/exception/util/LocalizedFormats.OUT_OF_BOUND_SIGNIFICANCE_LEVEL:Lorg/apache/commons/math3/exception/util/LocalizedFormats; (1, 1)
	21 dload_3 (1, 1)
	22 invokestatic (1, 1)
	23 java/lang/Double.valueOf:(D)Ljava/lang/Double; (1, 1)
	25 iconst_0 (1, 1)
	26 invokestatic (1, 1)
	27 java/lang/Integer.valueOf:(I)Ljava/lang/Integer; (1, 1)
	29 ldc2_w (1, 1)
	30 0.5 (1, 1)
	32 invokestatic (1, 1)
	33 java/lang/Double.valueOf:(D)Ljava/lang/Double; (1, 1)
	35 invokespecial (1, 1)
	36 org/apache/commons/math3/exception/OutOfRangeException.<init>:(Lorg/apache/commons/math3/exception/util/Localizable;Ljava/lang/Number;Ljava/lang/Number;Ljava/lang/Number;)V (1, 1)
	38 athrow (1, 1)
	39 aload_0 (0, 0)
	40 aload_1 (0, 0)
	41 aload_2 (0, 0)
	42 invokevirtual (0, 0)
	43 org/apache/commons/math3/stat/inference/GTest.gTest:([D[J)D (0, 0)
	45 dload_3 (0, 0)
	46 dcmpg (0, 0)
	47 ifge (0, 0)
	48 7 (0, 0)
	50 iconst_1 (0, 0)
	51 goto (0, 0)
	52 4 (0, 0)
	54 iconst_0 (0, 0)
	55 ireturn (0, 0)

Method: gTestIntrinsic
	0 new (0, 0)
	1 org/apache/commons/math3/distribution/ChiSquaredDistribution (0, 0)
	3 dup (0, 0)
	4 aconst_null (0, 0)
	5 aload_1 (0, 0)
	6 arraylength (0, 0)
	7 i2d (0, 0)
	8 ldc2_w (0, 0)
	9 2.0 (0, 0)
	11 dsub (0, 0)
	12 invokespecial (0, 0)
	13 org/apache/commons/math3/distribution/ChiSquaredDistribution.<init>:(Lorg/apache/commons/math3/random/RandomGenerator;D)V (0, 0)
	15 astore_3 (0, 0)
	16 dconst_1 (0, 0)
	17 aload_3 (0, 0)
	18 aload_0 (0, 0)
	19 aload_1 (0, 0)
	20 aload_2 (0, 0)
	21 invokevirtual (0, 0)
	22 org/apache/commons/math3/stat/inference/GTest.g:([D[J)D (0, 0)
	24 invokevirtual (0, 0)
	25 org/apache/commons/math3/distribution/ChiSquaredDistribution.cumulativeProbability:(D)D (0, 0)
	27 dsub (0, 0)
	28 dreturn (0, 0)

Method: entropy
	0 dconst_0 (0, 0)
	1 dstore_2 (0, 0)
	2 dconst_0 (0, 0)
	3 dstore (0, 0)
	4 #4 (0, 0)
	5 iconst_0 (1, 4)
	6 istore (1, 4)
	7 #6 (1, 4)
	8 iload (1, 4)
	9 #6 (1, 4)
	10 aload_1 (1, 4)
	11 arraylength (1, 4)
	12 if_icmpge (1, 4)
	13 19 (1, 4)
	15 dload (1, 4)
	16 #4 (1, 4)
	17 aload_1 (1, 4)
	18 iload (1, 4)
	19 #6 (1, 4)
	20 laload (1, 4)
	21 l2d (1, 4)
	22 dadd (1, 4)
	23 dstore (1, 4)
	24 #4 (1, 4)
	25 iinc (1, 4)
	26 #6 (1, 4)
	27 -89 (1, 4)
	28 goto (1, 4)
	29 -20 (1, 4)
	31 iconst_0 (1, 4)
	32 istore (1, 4)
	33 #6 (1, 4)
	34 iload (1, 4)
	35 #6 (1, 4)
	36 aload_1 (1, 4)
	37 arraylength (1, 4)
	38 if_icmpge (1, 4)
	39 39 (1, 4)
	41 aload_1 (2, 1)
	42 iload (2, 1)
	43 #6 (2, 1)
	44 laload (2, 1)
	45 lconst_0 (2, 1)
	46 lcmp (2, 1)
	47 ifeq (2, 1)
	48 24 (2, 1)
	50 aload_1 (2, 1)
	51 iload (2, 1)
	52 #6 (2, 1)
	53 laload (2, 1)
	54 l2d (2, 1)
	55 dload (2, 1)
	56 #4 (2, 1)
	57 ddiv (2, 1)
	58 dstore (2, 1)
	59 #7 (2, 1)
	60 dload_2 (2, 1)
	61 dload (2, 1)
	62 #7 (2, 1)
	63 dload (2, 1)
	64 #7 (2, 1)
	65 invokestatic (2, 1)
	66 org/apache/commons/math3/util/FastMath.log:(D)D (2, 1)
	68 dmul (2, 1)
	69 dadd (2, 1)
	70 dstore_2 (2, 1)
	71 iinc (2, 1)
	72 #6 (2, 1)
	73 -89 (2, 1)
	74 goto (2, 1)
	75 -40 (2, 1)
	77 dload_2 (1, 4)
	78 dneg (1, 4)
	79 dreturn (1, 4)

Method: gDataSetsComparison
	0 aload_1 (1, 1)
	1 arraylength (1, 1)
	2 iconst_2 (1, 1)
	3 if_icmpge (1, 1)
	4 14 (1, 1)
	6 new (1, 1)
	7 org/apache/commons/math3/exception/DimensionMismatchException (1, 1)
	9 dup (1, 1)
	10 aload_1 (1, 1)
	11 arraylength (1, 1)
	12 iconst_2 (1, 1)
	13 invokespecial (1, 1)
	14 org/apache/commons/math3/exception/DimensionMismatchException.<init>:(II)V (1, 1)
	16 athrow (1, 1)
	17 aload_1 (1, 1)
	18 arraylength (1, 1)
	19 aload_2 (1, 1)
	20 arraylength (1, 1)
	21 if_icmpeq (1, 1)
	22 15 (1, 1)
	24 new (1, 1)
	25 org/apache/commons/math3/exception/DimensionMismatchException (1, 1)
	27 dup (1, 1)
	28 aload_1 (1, 1)
	29 arraylength (1, 1)
	30 aload_2 (1, 1)
	31 arraylength (1, 1)
	32 invokespecial (1, 1)
	33 org/apache/commons/math3/exception/DimensionMismatchException.<init>:(II)V (1, 1)
	35 athrow (1, 1)
	36 aload_1 (0, 0)
	37 invokestatic (0, 0)
	38 org/apache/commons/math3/util/MathArrays.checkNonNegative:([J)V (0, 0)
	40 aload_2 (0, 0)
	41 invokestatic (0, 0)
	42 org/apache/commons/math3/util/MathArrays.checkNonNegative:([J)V (0, 0)
	44 lconst_0 (0, 0)
	45 lstore_3 (0, 0)
	46 lconst_0 (0, 0)
	47 lstore (0, 0)
	48 #5 (0, 0)
	49 aload_1 (0, 0)
	50 arraylength (0, 0)
	51 newarray (0, 0)
	52 11 (0, 0)
	53 astore (0, 0)
	54 #7 (0, 0)
	55 iconst_2 (0, 0)
	56 aload_1 (0, 0)
	57 arraylength (0, 0)
	58 multianewarray (0, 0)
	59 [[J (0, 0)
	61 58 (0, 0)
	62 astore (0, 0)
	63 #8 (0, 0)
	64 iconst_0 (1, 4)
	65 istore (1, 4)
	66 #9 (1, 4)
	67 iload (1, 4)
	68 #9 (1, 4)
	69 aload_1 (1, 4)
	70 arraylength (1, 4)
	71 if_icmpge (1, 4)
	72 102 (1, 4)
	74 aload_1 (2, 1)
	75 iload (2, 1)
	76 #9 (2, 1)
	77 laload (2, 1)
	78 lconst_0 (2, 1)
	79 lcmp (2, 1)
	80 ifne (2, 1)
	81 35 (2, 1)
	83 aload_2 (2, 1)
	84 iload (2, 1)
	85 #9 (2, 1)
	86 laload (2, 1)
	87 lconst_0 (2, 1)
	88 lcmp (2, 1)
	89 ifne (2, 1)
	90 26 (2, 1)
	92 new (2, 1)
	93 org/apache/commons/math3/exception/ZeroException (2, 1)
	95 dup (2, 1)
	96 getstatic (2, 1)
	97 org/apache/commons/math3/exception/util/LocalizedFormats.OBSERVED_COUNTS_BOTTH_ZERO_FOR_ENTRY:Lorg/apache/commons/math3/exception/util/LocalizedFormats; (2, 1)
	99 iconst_1 (2, 1)
	100 anewarray (2, 1)
	101 java/lang/Object (2, 1)
	103 dup (2, 1)
	104 iconst_0 (2, 1)
	105 iload (2, 1)
	106 #9 (2, 1)
	107 invokestatic (2, 1)
	108 java/lang/Integer.valueOf:(I)Ljava/lang/Integer; (2, 1)
	110 aastore (2, 1)
	111 invokespecial (2, 1)
	112 org/apache/commons/math3/exception/ZeroException.<init>:(Lorg/apache/commons/math3/exception/util/Localizable;[Ljava/lang/Object;)V (2, 1)
	114 athrow (2, 1)
	115 lload_3 (2, 2)
	116 aload_1 (2, 2)
	117 iload (2, 2)
	118 #9 (2, 2)
	119 laload (2, 2)
	120 ladd (2, 2)
	121 lstore_3 (2, 2)
	122 lload (2, 2)
	123 #5 (2, 2)
	124 aload_2 (2, 2)
	125 iload (2, 2)
	126 #9 (2, 2)
	127 laload (2, 2)
	128 ladd (2, 2)
	129 lstore (2, 2)
	130 #5 (2, 2)
	131 aload (2, 2)
	132 #7 (2, 2)
	133 iload (2, 2)
	134 #9 (2, 2)
	135 aload_1 (2, 2)
	136 iload (2, 2)
	137 #9 (2, 2)
	138 laload (2, 2)
	139 aload_2 (2, 2)
	140 iload (2, 2)
	141 #9 (2, 2)
	142 laload (2, 2)
	143 ladd (2, 2)
	144 lastore (2, 2)
	145 aload (2, 2)
	146 #8 (2, 2)
	147 iconst_0 (2, 2)
	148 aaload (2, 2)
	149 iload (2, 2)
	150 #9 (2, 2)
	151 aload_1 (2, 2)
	152 iload (2, 2)
	153 #9 (2, 2)
	154 laload (2, 2)
	155 lastore (2, 2)
	156 aload (2, 2)
	157 #8 (2, 2)
	158 iconst_1 (2, 2)
	159 aaload (2, 2)
	160 iload (2, 2)
	161 #9 (2, 2)
	162 aload_2 (2, 2)
	163 iload (2, 2)
	164 #9 (2, 2)
	165 laload (2, 2)
	166 lastore (2, 2)
	167 iinc (2, 2)
	168 #9 (2, 2)
	169 -89 (2, 2)
	170 goto (2, 2)
	171 -103 (2, 2)
	173 lload_3 (2, 1)
	174 lconst_0 (2, 1)
	175 lcmp (2, 1)
	176 ifeq (2, 1)
	177 10 (2, 1)
	179 lload (2, 1)
	180 #5 (2, 1)
	181 lconst_0 (2, 1)
	182 lcmp (2, 1)
	183 ifne (2, 1)
	184 11 (2, 1)
	186 new (2, 1)
	187 org/apache/commons/math3/exception/ZeroException (2, 1)
	189 dup (2, 1)
	190 invokespecial (2, 1)
	191 org/apache/commons/math3/exception/ZeroException.<init>:()V (2, 1)
	193 athrow (2, 1)
	194 iconst_2 (1, 1)
	195 newarray (1, 1)
	196 11 (1, 1)
	197 dup (1, 1)
	198 iconst_0 (1, 1)
	199 lload_3 (1, 1)
	200 lastore (1, 1)
	201 dup (1, 1)
	202 iconst_1 (1, 1)
	203 lload (1, 1)
	204 #5 (1, 1)
	205 lastore (1, 1)
	206 astore (1, 1)
	207 #9 (1, 1)
	208 lload_3 (1, 1)
	209 l2d (1, 1)
	210 lload (1, 1)
	211 #5 (1, 1)
	212 l2d (1, 1)
	213 dadd (1, 1)
	214 dstore (1, 1)
	215 #10 (1, 1)
	216 ldc2_w (1, 1)
	217 2.0 (1, 1)
	219 dload (1, 1)
	220 #10 (1, 1)
	221 dmul (1, 1)
	222 aload_0 (1, 1)
	223 aload (1, 1)
	224 #9 (1, 1)
	225 invokespecial (1, 1)
	226 org/apache/commons/math3/stat/inference/GTest.entropy:([J)D (1, 1)
	228 aload_0 (1, 1)
	229 aload (1, 1)
	230 #7 (1, 1)
	231 invokespecial (1, 1)
	232 org/apache/commons/math3/stat/inference/GTest.entropy:([J)D (1, 1)
	234 dadd (1, 1)
	235 aload_0 (1, 1)
	236 aload (1, 1)
	237 #8 (1, 1)
	238 invokespecial (1, 1)
	239 org/apache/commons/math3/stat/inference/GTest.entropy:([[J)D (1, 1)
	241 dsub (1, 1)
	242 dmul (1, 1)
	243 dreturn (1, 1)

Method: rootLogLikelihoodRatio
	0 aload_0 (0, 0)
	1 iconst_2 (0, 0)
	2 newarray (0, 0)
	3 11 (0, 0)
	4 dup (0, 0)
	5 iconst_0 (0, 0)
	6 lload_1 (0, 0)
	7 lastore (0, 0)
	8 dup (0, 0)
	9 iconst_1 (0, 0)
	10 lload_3 (0, 0)
	11 lastore (0, 0)
	12 iconst_2 (0, 0)
	13 newarray (0, 0)
	14 11 (0, 0)
	15 dup (0, 0)
	16 iconst_0 (0, 0)
	17 lload (0, 0)
	18 #5 (0, 0)
	19 lastore (0, 0)
	20 dup (0, 0)
	21 iconst_1 (0, 0)
	22 lload (0, 0)
	23 #7 (0, 0)
	24 lastore (0, 0)
	25 invokevirtual (0, 0)
	26 org/apache/commons/math3/stat/inference/GTest.gDataSetsComparison:([J[J)D (0, 0)
	28 dstore (0, 0)
	29 #9 (0, 0)
	30 dload (0, 0)
	31 #9 (0, 0)
	32 invokestatic (0, 0)
	33 org/apache/commons/math3/util/FastMath.sqrt:(D)D (0, 0)
	35 dstore (0, 0)
	36 #11 (0, 0)
	37 lload_1 (1, 1)
	38 l2d (1, 1)
	39 lload_1 (1, 1)
	40 lload_3 (1, 1)
	41 ladd (1, 1)
	42 l2d (1, 1)
	43 ddiv (1, 1)
	44 lload (1, 1)
	45 #5 (1, 1)
	46 l2d (1, 1)
	47 lload (1, 1)
	48 #5 (1, 1)
	49 lload (1, 1)
	50 #7 (1, 1)
	51 ladd (1, 1)
	52 l2d (1, 1)
	53 ddiv (1, 1)
	54 dcmpg (1, 1)
	55 ifge (1, 1)
	56 8 (1, 1)
	58 dload (1, 1)
	59 #11 (1, 1)
	60 dneg (1, 1)
	61 dstore (1, 1)
	62 #11 (1, 1)
	63 dload (0, 0)
	64 #11 (0, 0)
	65 dreturn (0, 0)

Method: gTestDataSetsComparison
	0 dload_3 (1, 1)
	1 dconst_0 (1, 1)
	2 dcmpg (1, 1)
	3 ifle (1, 1)
	4 11 (1, 1)
	6 dload_3 (1, 1)
	7 ldc2_w (1, 1)
	8 0.5 (1, 1)
	10 dcmpl (1, 1)
	11 ifle (1, 1)
	12 28 (1, 1)
	14 new (1, 1)
	15 org/apache/commons/math3/exception/OutOfRangeException (1, 1)
	17 dup (1, 1)
	18 getstatic (1, 1)
	19 org/apache/commons/math3/exception/util/LocalizedFormats.OUT_OF_BOUND_SIGNIFICANCE_LEVEL:Lorg/apache/commons/math3/exception/util/LocalizedFormats; (1, 1)
	21 dload_3 (1, 1)
	22 invokestatic (1, 1)
	23 java/lang/Double.valueOf:(D)Ljava/lang/Double; (1, 1)
	25 iconst_0 (1, 1)
	26 invokestatic (1, 1)
	27 java/lang/Integer.valueOf:(I)Ljava/lang/Integer; (1, 1)
	29 ldc2_w (1, 1)
	30 0.5 (1, 1)
	32 invokestatic (1, 1)
	33 java/lang/Double.valueOf:(D)Ljava/lang/Double; (1, 1)
	35 invokespecial (1, 1)
	36 org/apache/commons/math3/exception/OutOfRangeException.<init>:(Lorg/apache/commons/math3/exception/util/Localizable;Ljava/lang/Number;Ljava/lang/Number;Ljava/lang/Number;)V (1, 1)
	38 athrow (1, 1)
	39 aload_0 (0, 0)
	40 aload_1 (0, 0)
	41 aload_2 (0, 0)
	42 invokevirtual (0, 0)
	43 org/apache/commons/math3/stat/inference/GTest.gTestDataSetsComparison:([J[J)D (0, 0)
	45 dload_3 (0, 0)
	46 dcmpg (0, 0)
	47 ifge (0, 0)
	48 7 (0, 0)
	50 iconst_1 (0, 0)
	51 goto (0, 0)
	52 4 (0, 0)
	54 iconst_0 (0, 0)
	55 ireturn (0, 0)

