Method: <init>
	0 aload_0 (0, 0)
	1 invokespecial (0, 0)
	4 aload_0 (0, 0)
	5 aload_1 (0, 0)
	6 putfield (0, 0)
	9 return (0, 0)

Method: kolmogorovSmirnovTest
	0 dload_3 (1, 1)
	1 dconst_0 (1, 1)
	2 dcmpg (1, 1)
	3 ifle (1, 1)
	6 dload_3 (1, 1)
	7 ldc2_w (1, 1)
	10 dcmpl (1, 1)
	11 ifle (1, 1)
	14 new (1, 1)
	17 dup (1, 1)
	18 getstatic (1, 1)
	21 dload_3 (1, 1)
	22 invokestatic (1, 1)
	25 iconst_0 (1, 1)
	26 invokestatic (1, 1)
	29 ldc2_w (1, 1)
	32 invokestatic (1, 1)
	35 invokespecial (1, 1)
	38 athrow (1, 1)
	39 aload_0 (0, 0)
	40 aload_1 (0, 0)
	41 aload_2 (0, 0)
	42 invokevirtual (0, 0)
	45 dload_3 (0, 0)
	46 dcmpg (0, 0)
	47 ifge (0, 0)
	50 iconst_1 (0, 0)
	51 goto (0, 0)
	54 iconst_0 (0, 0)
	55 ireturn (0, 0)

Method: kolmogorovSmirnovStatistic
	0 aload_0 (0, 0)
	1 aload_1 (0, 0)
	2 aload_2 (0, 0)
	3 invokespecial (0, 0)
	6 l2d (0, 0)
	7 aload_1 (0, 0)
	8 arraylength (0, 0)
	9 i2l (0, 0)
	10 aload_2 (0, 0)
	11 arraylength (0, 0)
	12 i2l (0, 0)
	13 lmul (0, 0)
	14 l2d (0, 0)
	15 ddiv (0, 0)
	16 dreturn (0, 0)

Method: integralKolmogorovSmirnovStatistic
	0 aload_0 (0, 0)
	1 aload_1 (0, 0)
	2 invokespecial (0, 0)
	5 aload_0 (0, 0)
	6 aload_2 (0, 0)
	7 invokespecial (0, 0)
	10 aload_1 (0, 0)
	11 invokestatic (0, 0)
	14 astore_3 (0, 0)
	15 aload_2 (0, 0)
	16 invokestatic (0, 0)
	19 astore (0, 0)
	21 aload_3 (0, 0)
	22 invokestatic (0, 0)
	25 aload (0, 0)
	27 invokestatic (0, 0)
	30 aload_3 (0, 0)
	31 arraylength (0, 0)
	32 istore (0, 0)
	34 aload (0, 0)
	36 arraylength (0, 0)
	37 istore (0, 0)
	39 iconst_0 (0, 0)
	40 istore (0, 0)
	42 iconst_0 (0, 0)
	43 istore (0, 0)
	45 lconst_0 (0, 0)
	46 lstore (0, 0)
	48 lconst_0 (0, 1)
	49 lstore (0, 1)
	51 aload_3 (1, 1)
	52 iload (1, 1)
	54 daload (1, 1)
	55 aload (1, 1)
	57 iload (1, 1)
	59 daload (1, 1)
	60 invokestatic (1, 1)
	63 ifgt (1, 1)
	66 aload_3 (1, 1)
	67 iload (1, 1)
	69 daload (1, 1)
	70 goto (1, 1)
	73 aload (1, 1)
	75 iload (1, 1)
	77 daload (1, 1)
	78 dstore (1, 1)
	80 iload (2, 3)
	82 iload (2, 3)
	84 if_icmpge (2, 3)
	87 aload_3 (2, 3)
	88 iload (2, 3)
	90 daload (2, 3)
	91 dload (2, 3)
	93 invokestatic (2, 3)
	96 ifne (2, 3)
	99 iinc (2, 3)
	102 lload (2, 3)
	104 iload (2, 3)
	106 i2l (2, 3)
	107 ladd (2, 3)
	108 lstore (2, 3)
	110 goto (2, 3)
	113 iload (2, 3)
	115 iload (2, 3)
	117 if_icmpge (2, 3)
	120 aload (2, 3)
	122 iload (2, 3)
	124 daload (2, 3)
	125 dload (2, 3)
	127 invokestatic (2, 3)
	130 ifne (2, 3)
	133 iinc (2, 3)
	136 lload (2, 3)
	138 iload (2, 3)
	140 i2l (2, 3)
	141 lsub (2, 3)
	142 lstore (2, 3)
	144 goto (2, 3)
	147 lload (2, 1)
	149 lload (2, 1)
	151 lcmp (2, 1)
	152 ifle (2, 1)
	155 lload (2, 1)
	157 lstore (2, 1)
	159 goto (2, 1)
	162 lload (2, 1)
	164 lneg (2, 1)
	165 lload (2, 1)
	167 lcmp (2, 1)
	168 ifle (2, 1)
	171 lload (2, 1)
	173 lneg (2, 1)
	174 lstore (2, 1)
	176 iload (0, 1)
	178 iload (0, 1)
	180 if_icmpge (0, 1)
	183 iload (0, 1)
	185 iload (0, 1)
	187 if_icmplt (0, 1)
	190 lload (0, 1)
	192 lreturn (0, 1)

Method: bootstrap
	0 aload_0 (0, 0)
	1 aload_1 (0, 0)
	2 aload_2 (0, 0)
	3 iload_3 (0, 0)
	4 iconst_1 (0, 0)
	5 invokevirtual (0, 0)
	8 dreturn (0, 0)

Method: cdf
	0 dconst_1 (0, 0)
	1 iload_3 (0, 0)
	2 i2d (0, 0)
	3 ddiv (0, 0)
	4 dstore (0, 0)
	6 ldc2_w (0, 0)
	9 dload (0, 0)
	11 dmul (0, 0)
	12 dstore (0, 0)
	14 dload_1 (1, 1)
	15 dload (1, 1)
	17 dcmpg (1, 1)
	18 ifgt (1, 1)
	21 dconst_0 (1, 1)
	22 dreturn (1, 1)
	23 dload (1, 1)
	25 dload_1 (1, 1)
	26 dcmpg (1, 1)
	27 ifge (1, 1)
	30 dload_1 (1, 1)
	31 dload (1, 1)
	33 dcmpg (1, 1)
	34 ifgt (1, 1)
	37 dconst_1 (1, 1)
	38 dstore (1, 1)
	40 ldc2_w (1, 1)
	43 dload_1 (1, 1)
	44 dmul (1, 1)
	45 dload (1, 1)
	47 dsub (1, 1)
	48 dstore (1, 1)
	50 iconst_1 (2, 4)
	51 istore (2, 4)
	53 iload (2, 4)
	55 iload_3 (2, 4)
	56 if_icmpgt (2, 4)
	59 dload (2, 4)
	61 iload (2, 4)
	63 i2d (2, 4)
	64 dload (2, 4)
	66 dmul (2, 4)
	67 dmul (2, 4)
	68 dstore (2, 4)
	70 iinc (2, 4)
	73 goto (2, 4)
	76 dload (1, 1)
	78 dreturn (1, 1)
	79 dconst_1 (1, 1)
	80 dload (1, 1)
	82 dsub (1, 1)
	83 dload_1 (1, 1)
	84 dcmpg (1, 1)
	85 ifgt (1, 1)
	88 dload_1 (1, 1)
	89 dconst_1 (1, 1)
	90 dcmpg (1, 1)
	91 ifge (1, 1)
	94 dconst_1 (1, 1)
	95 ldc2_w (1, 1)
	98 dconst_1 (1, 1)
	99 dload_1 (1, 1)
	100 dsub (1, 1)
	101 iload_3 (1, 1)
	102 i2d (1, 1)
	103 invokestatic (1, 1)
	106 dmul (1, 1)
	107 dsub (1, 1)
	108 dreturn (1, 1)
	109 dconst_1 (1, 1)
	110 dload_1 (1, 1)
	111 dcmpg (1, 1)
	112 ifgt (1, 1)
	115 dconst_1 (1, 1)
	116 dreturn (1, 1)
	117 iload (1, 1)
	119 ifeq (1, 1)
	122 aload_0 (1, 1)
	123 dload_1 (1, 1)
	124 iload_3 (1, 1)
	125 invokespecial (1, 1)
	128 dreturn (1, 1)
	129 iload_3 (1, 1)
	130 sipush (1, 1)
	133 if_icmpgt (1, 1)
	136 aload_0 (1, 1)
	137 dload_1 (1, 1)
	138 iload_3 (1, 1)
	139 invokespecial (1, 1)
	142 dreturn (1, 1)
	143 aload_0 (0, 1)
	144 dload_1 (0, 1)
	145 iload_3 (0, 1)
	146 invokevirtual (0, 1)
	149 dreturn (0, 1)

Method: cdfExact
	0 aload_0 (0, 0)
	1 dload_1 (0, 0)
	2 iload_3 (0, 0)
	3 iconst_1 (0, 0)
	4 invokevirtual (0, 0)
	7 dreturn (0, 0)

Method: exactK
	0 iload_3 (0, 0)
	1 i2d (0, 0)
	2 dload_1 (0, 0)
	3 dmul (0, 0)
	4 invokestatic (0, 0)
	7 d2i (0, 0)
	8 istore (0, 0)
	10 aload_0 (0, 0)
	11 dload_1 (0, 0)
	12 iload_3 (0, 0)
	13 invokespecial (0, 0)
	16 astore (0, 0)
	18 aload (0, 0)
	20 iload_3 (0, 0)
	21 invokeinterface (0, 0)
	26 astore (0, 0)
	28 aload (0, 0)
	30 iload (0, 0)
	32 iconst_1 (0, 0)
	33 isub (0, 0)
	34 iload (0, 0)
	36 iconst_1 (0, 0)
	37 isub (0, 0)
	38 invokeinterface (0, 0)
	43 checkcast (0, 0)
	46 astore (0, 0)
	48 iconst_1 (1, 4)
	49 istore (1, 4)
	51 iload (1, 4)
	53 iload_3 (1, 4)
	54 if_icmpgt (1, 4)
	57 aload (1, 4)
	59 iload (1, 4)
	61 invokevirtual (1, 4)
	64 iload_3 (1, 4)
	65 invokevirtual (1, 4)
	68 astore (1, 4)
	70 iinc (1, 4)
	73 goto (1, 4)
	76 aload (0, 0)
	78 bipush (0, 0)
	80 iconst_4 (0, 0)
	81 invokevirtual (0, 0)
	84 invokevirtual (0, 0)
	87 dreturn (0, 0)

Method: roundedK
	0 iload_3 (0, 0)
	1 i2d (0, 0)
	2 dload_1 (0, 0)
	3 dmul (0, 0)
	4 invokestatic (0, 0)
	7 d2i (0, 0)
	8 istore (0, 0)
	10 aload_0 (0, 0)
	11 dload_1 (0, 0)
	12 iload_3 (0, 0)
	13 invokespecial (0, 0)
	16 astore (0, 0)
	18 aload (0, 0)
	20 iload_3 (0, 0)
	21 invokeinterface (0, 0)
	26 astore (0, 0)
	28 aload (0, 0)
	30 iload (0, 0)
	32 iconst_1 (0, 0)
	33 isub (0, 0)
	34 iload (0, 0)
	36 iconst_1 (0, 0)
	37 isub (0, 0)
	38 invokeinterface (0, 0)
	43 dstore (0, 0)
	45 iconst_1 (1, 4)
	46 istore (1, 4)
	48 iload (1, 4)
	50 iload_3 (1, 4)
	51 if_icmpgt (1, 4)
	54 dload (1, 4)
	56 iload (1, 4)
	58 i2d (1, 4)
	59 iload_3 (1, 4)
	60 i2d (1, 4)
	61 ddiv (1, 4)
	62 dmul (1, 4)
	63 dstore (1, 4)
	65 iinc (1, 4)
	68 goto (1, 4)
	71 dload (0, 0)
	73 dreturn (0, 0)

Method: pelzGood
	0 iload_3 (0, 0)
	1 i2d (0, 0)
	2 invokestatic (0, 0)
	5 dstore (0, 0)
	7 dload_1 (0, 0)
	8 dload (0, 0)
	10 dmul (0, 0)
	11 dstore (0, 0)
	13 dload_1 (0, 0)
	14 dload_1 (0, 0)
	15 dmul (0, 0)
	16 iload_3 (0, 0)
	17 i2d (0, 0)
	18 dmul (0, 0)
	19 dstore (0, 0)
	21 dload (0, 0)
	23 dload (0, 0)
	25 dmul (0, 0)
	26 dstore (0, 0)
	28 dload (0, 0)
	30 dload (0, 0)
	32 dmul (0, 0)
	33 dstore (0, 0)
	35 dload (0, 0)
	37 dload (0, 0)
	39 dmul (0, 0)
	40 dstore (0, 0)
	42 dconst_0 (0, 0)
	43 dstore (0, 0)
	45 dconst_0 (0, 0)
	46 dstore (0, 0)
	48 dconst_0 (0, 0)
	49 dstore (0, 0)
	51 dconst_0 (0, 0)
	52 dstore (0, 0)
	54 ldc2_w (0, 0)
	57 ldc2_w (0, 0)
	60 dload (0, 0)
	62 dmul (0, 0)
	63 ddiv (0, 0)
	64 dstore (0, 0)
	66 iconst_1 (0, 0)
	67 istore (0, 0)
	69 iload (1, 4)
	71 ldc (1, 4)
	73 if_icmpge (1, 4)
	76 iconst_2 (1, 4)
	77 iload (1, 4)
	79 imul (1, 4)
	80 iconst_1 (1, 4)
	81 isub (1, 4)
	82 i2d (1, 4)
	83 dstore (1, 4)
	85 dload (1, 4)
	87 dneg (1, 4)
	88 dload (1, 4)
	90 dmul (1, 4)
	91 dload (1, 4)
	93 dmul (1, 4)
	94 invokestatic (1, 4)
	97 dstore (1, 4)
	99 dload (1, 4)
	101 dload (1, 4)
	103 dadd (1, 4)
	104 dstore (1, 4)
	106 dload (2, 1)
	108 ldc2_w (2, 1)
	111 dload (2, 1)
	113 dmul (2, 1)
	114 dcmpg (2, 1)
	115 ifgt (2, 1)
	118 goto (2, 1)
	121 iinc (2, 1)
	124 goto (2, 1)
	127 iload (2, 1)
	129 ldc (2, 1)
	131 if_icmpne (2, 1)
	134 new (2, 1)
	137 dup (2, 1)
	138 ldc (2, 1)
	140 invokestatic (2, 1)
	143 invokespecial (2, 1)
	146 athrow (2, 1)
	147 dload (1, 4)
	149 ldc2_w (1, 4)
	152 invokestatic (1, 4)
	155 dmul (1, 4)
	156 dload (1, 4)
	158 ddiv (1, 4)
	159 dstore (1, 4)
	161 ldc2_w (1, 4)
	164 dload (1, 4)
	166 dmul (1, 4)
	167 dstore (1, 4)
	169 dconst_0 (1, 4)
	170 dstore (1, 4)
	172 dconst_0 (1, 4)
	173 dstore (1, 4)
	175 dconst_0 (1, 4)
	176 dstore (1, 4)
	178 iconst_0 (2, 4)
	179 istore (2, 4)
	181 iload (2, 4)
	183 ldc (2, 4)
	185 if_icmpge (2, 4)
	188 iload (2, 4)
	190 i2d (2, 4)
	191 ldc2_w (2, 4)
	194 dadd (2, 4)
	195 dstore (2, 4)
	197 dload (2, 4)
	199 dload (2, 4)
	201 dmul (2, 4)
	202 dstore (2, 4)
	204 ldc2_w (2, 4)
	207 dload (2, 4)
	209 dmul (2, 4)
	210 dload (2, 4)
	212 dsub (2, 4)
	213 ldc2_w (2, 4)
	216 dload (2, 4)
	218 dmul (2, 4)
	219 dload (2, 4)
	221 ddiv (2, 4)
	222 invokestatic (2, 4)
	225 dmul (2, 4)
	226 dstore (2, 4)
	228 dload (2, 4)
	230 dload (2, 4)
	232 dadd (2, 4)
	233 dstore (2, 4)
	235 dload (3, 1)
	237 invokestatic (3, 1)
	240 ldc2_w (3, 1)
	243 dload (3, 1)
	245 invokestatic (3, 1)
	248 dmul (3, 1)
	249 dcmpg (3, 1)
	250 ifge (3, 1)
	253 goto (3, 1)
	256 iinc (3, 1)
	259 goto (3, 1)
	262 iload (3, 1)
	264 ldc (3, 1)
	266 if_icmpne (3, 1)
	269 new (3, 1)
	272 dup (3, 1)
	273 ldc (3, 1)
	275 invokestatic (3, 1)
	278 invokespecial (3, 1)
	281 athrow (3, 1)
	282 ldc2_w (2, 4)
	285 invokestatic (2, 4)
	288 dstore (2, 4)
	290 dload (2, 4)
	292 dload (2, 4)
	294 dload (2, 4)
	296 dmul (2, 4)
	297 ldc2_w (2, 4)
	300 dload (2, 4)
	302 dmul (2, 4)
	303 dload (2, 4)
	305 dmul (2, 4)
	306 ddiv (2, 4)
	307 dadd (2, 4)
	308 dstore (2, 4)
	310 ldc2_w (2, 4)
	313 dload (2, 4)
	315 dmul (2, 4)
	316 dstore (2, 4)
	318 ldc2_w (2, 4)
	321 dload (2, 4)
	323 dmul (2, 4)
	324 dstore (2, 4)
	326 ldc2_w (2, 4)
	329 dload (2, 4)
	331 dmul (2, 4)
	332 dstore (2, 4)
	334 ldc2_w (2, 4)
	337 dstore (2, 4)
	339 dconst_0 (2, 4)
	340 dstore (2, 4)
	342 dconst_0 (2, 4)
	343 dstore (2, 4)
	345 dconst_0 (2, 4)
	346 dstore (2, 4)
	348 iconst_0 (3, 4)
	349 istore (3, 4)
	351 iload (3, 4)
	353 ldc (3, 4)
	355 if_icmpge (3, 4)
	358 iload (3, 4)
	360 i2d (3, 4)
	361 ldc2_w (3, 4)
	364 dadd (3, 4)
	365 dstore (3, 4)
	367 dload (3, 4)
	369 dload (3, 4)
	371 dmul (3, 4)
	372 dstore (3, 4)
	374 dload (3, 4)
	376 dload (3, 4)
	378 dadd (3, 4)
	379 ldc2_w (3, 4)
	382 dload (3, 4)
	384 dload (3, 4)
	386 dsub (3, 4)
	387 dmul (3, 4)
	388 dload (3, 4)
	390 dmul (3, 4)
	391 dadd (3, 4)
	392 ldc2_w (3, 4)
	395 dconst_1 (3, 4)
	396 dload (3, 4)
	398 dsub (3, 4)
	399 dmul (3, 4)
	400 dload (3, 4)
	402 dmul (3, 4)
	403 dload (3, 4)
	405 dmul (3, 4)
	406 dadd (3, 4)
	407 ldc2_w (3, 4)
	410 dload (3, 4)
	412 dmul (3, 4)
	413 dload (3, 4)
	415 ddiv (3, 4)
	416 invokestatic (3, 4)
	419 dmul (3, 4)
	420 dstore (3, 4)
	422 dload (3, 4)
	424 dload (3, 4)
	426 dadd (3, 4)
	427 dstore (3, 4)
	429 dload (4, 1)
	431 invokestatic (4, 1)
	434 ldc2_w (4, 1)
	437 dload (4, 1)
	439 invokestatic (4, 1)
	442 dmul (4, 1)
	443 dcmpg (4, 1)
	444 ifge (4, 1)
	447 goto (4, 1)
	450 iinc (4, 1)
	453 goto (4, 1)
	456 iload (4, 1)
	458 ldc (4, 1)
	460 if_icmpne (4, 1)
	463 new (4, 1)
	466 dup (4, 1)
	467 ldc (4, 1)
	469 invokestatic (4, 1)
	472 invokespecial (4, 1)
	475 athrow (4, 1)
	476 dconst_0 (3, 4)
	477 dstore (3, 4)
	479 dconst_0 (3, 4)
	480 dstore (3, 4)
	482 iconst_1 (4, 4)
	483 istore (4, 4)
	485 iload (4, 4)
	487 ldc (4, 4)
	489 if_icmpge (4, 4)
	492 iload (4, 4)
	494 iload (4, 4)
	496 imul (4, 4)
	497 i2d (4, 4)
	498 dstore (4, 4)
	500 ldc2_w (4, 4)
	503 dload (4, 4)
	505 dmul (4, 4)
	506 ldc2_w (4, 4)
	509 dload (4, 4)
	511 dmul (4, 4)
	512 dload (4, 4)
	514 ddiv (4, 4)
	515 invokestatic (4, 4)
	518 dmul (4, 4)
	519 dstore (4, 4)
	521 dload (4, 4)
	523 dload (4, 4)
	525 dadd (4, 4)
	526 dstore (4, 4)
	528 dload (5, 1)
	530 invokestatic (5, 1)
	533 ldc2_w (5, 1)
	536 dload (5, 1)
	538 invokestatic (5, 1)
	541 dmul (5, 1)
	542 dcmpg (5, 1)
	543 ifge (5, 1)
	546 goto (5, 1)
	549 iinc (5, 1)
	552 goto (5, 1)
	555 iload (5, 1)
	557 ldc (5, 1)
	559 if_icmpne (5, 1)
	562 new (5, 1)
	565 dup (5, 1)
	566 ldc (5, 1)
	568 invokestatic (5, 1)
	571 invokespecial (5, 1)
	574 athrow (5, 1)
	575 dload (4, 4)
	577 dload (4, 4)
	579 iload_3 (4, 4)
	580 i2d (4, 4)
	581 ddiv (4, 4)
	582 dload (4, 4)
	584 ldc2_w (4, 4)
	587 dload (4, 4)
	589 dmul (4, 4)
	590 dload (4, 4)
	592 dmul (4, 4)
	593 dload (4, 4)
	595 dmul (4, 4)
	596 dload (4, 4)
	598 dmul (4, 4)
	599 ddiv (4, 4)
	600 dload (4, 4)
	602 ldc2_w (4, 4)
	605 dload (4, 4)
	607 dmul (4, 4)
	608 dload (4, 4)
	610 dmul (4, 4)
	611 ddiv (4, 4)
	612 dsub (4, 4)
	613 dmul (4, 4)
	614 dadd (4, 4)
	615 dstore (4, 4)
	617 ldc2_w (4, 4)
	620 dstore (4, 4)
	622 dconst_0 (4, 4)
	623 dstore (4, 4)
	625 dconst_0 (4, 4)
	626 dstore (4, 4)
	628 dconst_0 (4, 4)
	629 dstore (4, 4)
	631 iconst_0 (5, 4)
	632 istore (5, 4)
	634 iload (5, 4)
	636 ldc (5, 4)
	638 if_icmpge (5, 4)
	641 iload (5, 4)
	643 i2d (5, 4)
	644 ldc2_w (5, 4)
	647 dadd (5, 4)
	648 dstore (5, 4)
	650 dload (5, 4)
	652 dload (5, 4)
	654 dmul (5, 4)
	655 dstore (5, 4)
	657 dload (5, 4)
	659 dload (5, 4)
	661 dmul (5, 4)
	662 dstore (5, 4)
	664 dload (5, 4)
	666 dload (5, 4)
	668 dmul (5, 4)
	669 dstore (5, 4)
	671 ldc2_w (5, 4)
	674 dload (5, 4)
	676 dmul (5, 4)
	677 ldc2_w (5, 4)
	680 ldc2_w (5, 4)
	683 dload (5, 4)
	685 dmul (5, 4)
	686 dsub (5, 4)
	687 dmul (5, 4)
	688 ldc2_w (5, 4)
	691 dload (5, 4)
	693 dmul (5, 4)
	694 ldc2_w (5, 4)
	697 dload (5, 4)
	699 dmul (5, 4)
	700 ldc2_w (5, 4)
	703 dload (5, 4)
	705 dmul (5, 4)
	706 dadd (5, 4)
	707 dmul (5, 4)
	708 dadd (5, 4)
	709 ldc2_w (5, 4)
	712 dload (5, 4)
	714 dmul (5, 4)
	715 ldc2_w (5, 4)
	718 dload (5, 4)
	720 dmul (5, 4)
	721 ldc2_w (5, 4)
	724 dload (5, 4)
	726 dmul (5, 4)
	727 dsub (5, 4)
	728 dmul (5, 4)
	729 dadd (5, 4)
	730 ldc2_w (5, 4)
	733 dload (5, 4)
	735 dmul (5, 4)
	736 dsub (5, 4)
	737 ldc2_w (5, 4)
	740 dload (5, 4)
	742 dmul (5, 4)
	743 dsub (5, 4)
	744 ldc2_w (5, 4)
	747 dload (5, 4)
	749 dmul (5, 4)
	750 dload (5, 4)
	752 ddiv (5, 4)
	753 invokestatic (5, 4)
	756 dmul (5, 4)
	757 dstore (5, 4)
	759 dload (5, 4)
	761 dload (5, 4)
	763 dadd (5, 4)
	764 dstore (5, 4)
	766 dload (6, 1)
	768 invokestatic (6, 1)
	771 ldc2_w (6, 1)
	774 dload (6, 1)
	776 invokestatic (6, 1)
	779 dmul (6, 1)
	780 dcmpg (6, 1)
	781 ifge (6, 1)
	784 goto (6, 1)
	787 iinc (6, 1)
	790 goto (6, 1)
	793 iload (6, 1)
	795 ldc (6, 1)
	797 if_icmpne (6, 1)
	800 new (6, 1)
	803 dup (6, 1)
	804 ldc (6, 1)
	806 invokestatic (6, 1)
	809 invokespecial (6, 1)
	812 athrow (6, 1)
	813 dconst_0 (5, 4)
	814 dstore (5, 4)
	816 iconst_1 (6, 4)
	817 istore (6, 4)
	819 iload (6, 4)
	821 ldc (6, 4)
	823 if_icmpge (6, 4)
	826 iload (6, 4)
	828 iload (6, 4)
	830 imul (6, 4)
	831 i2d (6, 4)
	832 dstore (6, 4)
	834 dload (6, 4)
	836 dload (6, 4)
	838 dmul (6, 4)
	839 dstore (6, 4)
	841 ldc2_w (6, 4)
	844 dload (6, 4)
	846 dmul (6, 4)
	847 ldc2_w (6, 4)
	850 dload (6, 4)
	852 dmul (6, 4)
	853 dload (6, 4)
	855 dmul (6, 4)
	856 dadd (6, 4)
	857 ldc2_w (6, 4)
	860 dload (6, 4)
	862 dmul (6, 4)
	863 dload (6, 4)
	865 ddiv (6, 4)
	866 invokestatic (6, 4)
	869 dmul (6, 4)
	870 dstore (6, 4)
	872 dload (6, 4)
	874 dload (6, 4)
	876 dadd (6, 4)
	877 dstore (6, 4)
	879 dload (7, 1)
	881 invokestatic (7, 1)
	884 ldc2_w (7, 1)
	887 dload (7, 1)
	889 invokestatic (7, 1)
	892 dmul (7, 1)
	893 dcmpg (7, 1)
	894 ifge (7, 1)
	897 goto (7, 1)
	900 iinc (7, 1)
	903 goto (7, 1)
	906 iload (7, 1)
	908 ldc (7, 1)
	910 if_icmpne (7, 1)
	913 new (7, 1)
	916 dup (7, 1)
	917 ldc (7, 1)
	919 invokestatic (7, 1)
	922 invokespecial (7, 1)
	925 athrow (7, 1)
	926 dload (6, 4)
	928 dload (6, 4)
	930 dload (6, 4)
	932 iload_3 (6, 4)
	933 i2d (6, 4)
	934 dmul (6, 4)
	935 ddiv (6, 4)
	936 dload (6, 4)
	938 ldc2_w (6, 4)
	941 dload (6, 4)
	943 dmul (6, 4)
	944 dload (6, 4)
	946 dmul (6, 4)
	947 ddiv (6, 4)
	948 dload (6, 4)
	950 ldc2_w (6, 4)
	953 dload (6, 4)
	955 dmul (6, 4)
	956 ddiv (6, 4)
	957 dadd (6, 4)
	958 dmul (6, 4)
	959 dadd (6, 4)
	960 dreturn (6, 4)

Method: createExactH
	0 iload_3 (0, 0)
	1 i2d (0, 0)
	2 dload_1 (0, 0)
	3 dmul (0, 0)
	4 invokestatic (0, 0)
	7 d2i (0, 0)
	8 istore (0, 0)
	10 iconst_2 (0, 0)
	11 iload (0, 0)
	13 imul (0, 0)
	14 iconst_1 (0, 0)
	15 isub (0, 0)
	16 istore (0, 0)
	18 iload (0, 0)
	20 i2d (0, 0)
	21 iload_3 (0, 0)
	22 i2d (0, 0)
	23 dload_1 (0, 0)
	24 dmul (0, 0)
	25 dsub (0, 0)
	26 dstore (0, 0)
	28 dload (1, 1)
	30 dconst_1 (1, 1)
	31 dcmpl (1, 1)
	32 iflt (1, 1)
	35 new (1, 1)
	38 dup (1, 1)
	39 dload (1, 1)
	41 invokestatic (1, 1)
	44 dconst_1 (1, 1)
	45 invokestatic (1, 1)
	48 iconst_0 (1, 1)
	49 invokespecial (1, 1)
	52 athrow (1, 1)
	53 aconst_null (0, 0)
	54 astore (0, 0)
	56 new (0, 0)
	59 dup (0, 0)
	60 dload (0, 0)
	62 ldc2_w (0, 0)
	65 sipush (0, 0)
	68 invokespecial (0, 0)
	71 astore (0, 0)
	73 goto (0, 0)
	76 astore (0, 0)
	78 new (0, 0)
	81 dup (0, 0)
	82 dload (0, 0)
	84 ldc2_w (0, 0)
	87 sipush (0, 0)
	90 invokespecial (0, 0)
	93 astore (0, 0)
	95 goto (0, 0)
	98 astore (0, 0)
	100 new (0, 0)
	103 dup (0, 0)
	104 dload (0, 0)
	106 ldc2_w (0, 0)
	109 sipush (0, 0)
	112 invokespecial (0, 0)
	115 astore (0, 0)
	117 iload (0, 0)
	119 iload (0, 0)
	121 multianewarray (0, 0)
	125 astore (0, 0)
	127 iconst_0 (1, 4)
	128 istore (1, 4)
	130 iload (1, 4)
	132 iload (1, 4)
	134 if_icmpge (1, 4)
	137 iconst_0 (2, 4)
	138 istore (2, 4)
	140 iload (2, 4)
	142 iload (2, 4)
	144 if_icmpge (2, 4)
	147 iload (3, 1)
	149 iload (3, 1)
	151 isub (3, 1)
	152 iconst_1 (3, 1)
	153 iadd (3, 1)
	154 ifge (3, 1)
	157 aload (3, 1)
	159 iload (3, 1)
	161 aaload (3, 1)
	162 iload (3, 1)
	164 getstatic (3, 1)
	167 aastore (3, 1)
	168 goto (3, 1)
	171 aload (3, 2)
	173 iload (3, 2)
	175 aaload (3, 2)
	176 iload (3, 2)
	178 getstatic (3, 2)
	181 aastore (3, 2)
	182 iinc (3, 2)
	185 goto (3, 2)
	188 iinc (3, 2)
	191 goto (3, 2)
	194 iload (2, 2)
	196 anewarray (2, 2)
	199 astore (2, 2)
	201 aload (2, 2)
	203 iconst_0 (2, 2)
	204 aload (2, 2)
	206 aastore (2, 2)
	207 iconst_1 (3, 4)
	208 istore (3, 4)
	210 iload (3, 4)
	212 iload (3, 4)
	214 if_icmpge (3, 4)
	217 aload (3, 4)
	219 iload (3, 4)
	221 aload (3, 4)
	223 aload (3, 4)
	225 iload (3, 4)
	227 iconst_1 (3, 4)
	228 isub (3, 4)
	229 aaload (3, 4)
	230 invokevirtual (3, 4)
	233 aastore (3, 4)
	234 iinc (3, 4)
	237 goto (3, 4)
	240 iconst_0 (3, 4)
	241 istore (3, 4)
	243 iload (3, 4)
	245 iload (3, 4)
	247 if_icmpge (3, 4)
	250 aload (3, 4)
	252 iload (3, 4)
	254 aaload (3, 4)
	255 iconst_0 (3, 4)
	256 aload (3, 4)
	258 iload (3, 4)
	260 aaload (3, 4)
	261 iconst_0 (3, 4)
	262 aaload (3, 4)
	263 aload (3, 4)
	265 iload (3, 4)
	267 aaload (3, 4)
	268 invokevirtual (3, 4)
	271 aastore (3, 4)
	272 aload (3, 4)
	274 iload (3, 4)
	276 iconst_1 (3, 4)
	277 isub (3, 4)
	278 aaload (3, 4)
	279 iload (3, 4)
	281 aload (3, 4)
	283 iload (3, 4)
	285 iconst_1 (3, 4)
	286 isub (3, 4)
	287 aaload (3, 4)
	288 iload (3, 4)
	290 aaload (3, 4)
	291 aload (3, 4)
	293 iload (3, 4)
	295 iload (3, 4)
	297 isub (3, 4)
	298 iconst_1 (3, 4)
	299 isub (3, 4)
	300 aaload (3, 4)
	301 invokevirtual (3, 4)
	304 aastore (3, 4)
	305 iinc (3, 4)
	308 goto (3, 4)
	311 aload (3, 1)
	313 getstatic (3, 1)
	316 invokevirtual (3, 1)
	319 iconst_1 (3, 1)
	320 if_icmpne (3, 1)
	323 aload (3, 1)
	325 iload (3, 1)
	327 iconst_1 (3, 1)
	328 isub (3, 1)
	329 aaload (3, 1)
	330 iconst_0 (3, 1)
	331 aload (3, 1)
	333 iload (3, 1)
	335 iconst_1 (3, 1)
	336 isub (3, 1)
	337 aaload (3, 1)
	338 iconst_0 (3, 1)
	339 aaload (3, 1)
	340 aload (3, 1)
	342 iconst_2 (3, 1)
	343 invokevirtual (3, 1)
	346 iconst_1 (3, 1)
	347 invokevirtual (3, 1)
	350 iload (3, 1)
	352 invokevirtual (3, 1)
	355 invokevirtual (3, 1)
	358 aastore (3, 1)
	359 iconst_0 (3, 4)
	360 istore (3, 4)
	362 iload (3, 4)
	364 iload (3, 4)
	366 if_icmpge (3, 4)
	369 iconst_0 (4, 4)
	370 istore (4, 4)
	372 iload (4, 4)
	374 iload (4, 4)
	376 iconst_1 (4, 4)
	377 iadd (4, 4)
	378 if_icmpge (4, 4)
	381 iload (5, 1)
	383 iload (5, 1)
	385 isub (5, 1)
	386 iconst_1 (5, 1)
	387 iadd (5, 1)
	388 ifle (5, 1)
	391 iconst_2 (6, 4)
	392 istore (6, 4)
	394 iload (6, 4)
	396 iload (6, 4)
	398 iload (6, 4)
	400 isub (6, 4)
	401 iconst_1 (6, 4)
	402 iadd (6, 4)
	403 if_icmpgt (6, 4)
	406 aload (6, 4)
	408 iload (6, 4)
	410 aaload (6, 4)
	411 iload (6, 4)
	413 aload (6, 4)
	415 iload (6, 4)
	417 aaload (6, 4)
	418 iload (6, 4)
	420 aaload (6, 4)
	421 iload (6, 4)
	423 invokevirtual (6, 4)
	426 aastore (6, 4)
	427 iinc (6, 4)
	430 goto (6, 4)
	433 iinc (6, 4)
	436 goto (6, 4)
	439 iinc (6, 4)
	442 goto (6, 4)
	445 new (5, 1)
	448 dup (5, 1)
	449 invokestatic (5, 1)
	452 aload (5, 1)
	454 invokespecial (5, 1)
	457 areturn (5, 1)

Method: createRoundedH
	0 iload_3 (0, 0)
	1 i2d (0, 0)
	2 dload_1 (0, 0)
	3 dmul (0, 0)
	4 invokestatic (0, 0)
	7 d2i (0, 0)
	8 istore (0, 0)
	10 iconst_2 (0, 0)
	11 iload (0, 0)
	13 imul (0, 0)
	14 iconst_1 (0, 0)
	15 isub (0, 0)
	16 istore (0, 0)
	18 iload (0, 0)
	20 i2d (0, 0)
	21 iload_3 (0, 0)
	22 i2d (0, 0)
	23 dload_1 (0, 0)
	24 dmul (0, 0)
	25 dsub (0, 0)
	26 dstore (0, 0)
	28 dload (1, 1)
	30 dconst_1 (1, 1)
	31 dcmpl (1, 1)
	32 iflt (1, 1)
	35 new (1, 1)
	38 dup (1, 1)
	39 dload (1, 1)
	41 invokestatic (1, 1)
	44 dconst_1 (1, 1)
	45 invokestatic (1, 1)
	48 iconst_0 (1, 1)
	49 invokespecial (1, 1)
	52 athrow (1, 1)
	53 iload (0, 0)
	55 iload (0, 0)
	57 multianewarray (0, 0)
	61 astore (0, 0)
	63 iconst_0 (1, 4)
	64 istore (1, 4)
	66 iload (1, 4)
	68 iload (1, 4)
	70 if_icmpge (1, 4)
	73 iconst_0 (2, 4)
	74 istore (2, 4)
	76 iload (2, 4)
	78 iload (2, 4)
	80 if_icmpge (2, 4)
	83 iload (3, 1)
	85 iload (3, 1)
	87 isub (3, 1)
	88 iconst_1 (3, 1)
	89 iadd (3, 1)
	90 ifge (3, 1)
	93 aload (3, 1)
	95 iload (3, 1)
	97 aaload (3, 1)
	98 iload (3, 1)
	100 dconst_0 (3, 1)
	101 dastore (3, 1)
	102 goto (3, 1)
	105 aload (3, 2)
	107 iload (3, 2)
	109 aaload (3, 2)
	110 iload (3, 2)
	112 dconst_1 (3, 2)
	113 dastore (3, 2)
	114 iinc (3, 2)
	117 goto (3, 2)
	120 iinc (3, 2)
	123 goto (3, 2)
	126 iload (2, 2)
	128 newarray (2, 2)
	130 astore (2, 2)
	132 aload (2, 2)
	134 iconst_0 (2, 2)
	135 dload (2, 2)
	137 dastore (2, 2)
	138 iconst_1 (3, 4)
	139 istore (3, 4)
	141 iload (3, 4)
	143 iload (3, 4)
	145 if_icmpge (3, 4)
	148 aload (3, 4)
	150 iload (3, 4)
	152 dload (3, 4)
	154 aload (3, 4)
	156 iload (3, 4)
	158 iconst_1 (3, 4)
	159 isub (3, 4)
	160 daload (3, 4)
	161 dmul (3, 4)
	162 dastore (3, 4)
	163 iinc (3, 4)
	166 goto (3, 4)
	169 iconst_0 (3, 4)
	170 istore (3, 4)
	172 iload (3, 4)
	174 iload (3, 4)
	176 if_icmpge (3, 4)
	179 aload (3, 4)
	181 iload (3, 4)
	183 aaload (3, 4)
	184 iconst_0 (3, 4)
	185 aload (3, 4)
	187 iload (3, 4)
	189 aaload (3, 4)
	190 iconst_0 (3, 4)
	191 daload (3, 4)
	192 aload (3, 4)
	194 iload (3, 4)
	196 daload (3, 4)
	197 dsub (3, 4)
	198 dastore (3, 4)
	199 aload (3, 4)
	201 iload (3, 4)
	203 iconst_1 (3, 4)
	204 isub (3, 4)
	205 aaload (3, 4)
	206 iload (3, 4)
	208 dup2 (3, 4)
	209 daload (3, 4)
	210 aload (3, 4)
	212 iload (3, 4)
	214 iload (3, 4)
	216 isub (3, 4)
	217 iconst_1 (3, 4)
	218 isub (3, 4)
	219 daload (3, 4)
	220 dsub (3, 4)
	221 dastore (3, 4)
	222 iinc (3, 4)
	225 goto (3, 4)
	228 dload (3, 1)
	230 ldc2_w (3, 1)
	233 invokestatic (3, 1)
	236 ifle (3, 1)
	239 aload (3, 1)
	241 iload (3, 1)
	243 iconst_1 (3, 1)
	244 isub (3, 1)
	245 aaload (3, 1)
	246 iconst_0 (3, 1)
	247 dup2 (3, 1)
	248 daload (3, 1)
	249 ldc2_w (3, 1)
	252 dload (3, 1)
	254 dmul (3, 1)
	255 dconst_1 (3, 1)
	256 dsub (3, 1)
	257 iload (3, 1)
	259 invokestatic (3, 1)
	262 dadd (3, 1)
	263 dastore (3, 1)
	264 iconst_0 (3, 4)
	265 istore (3, 4)
	267 iload (3, 4)
	269 iload (3, 4)
	271 if_icmpge (3, 4)
	274 iconst_0 (4, 4)
	275 istore (4, 4)
	277 iload (4, 4)
	279 iload (4, 4)
	281 iconst_1 (4, 4)
	282 iadd (4, 4)
	283 if_icmpge (4, 4)
	286 iload (5, 1)
	288 iload (5, 1)
	290 isub (5, 1)
	291 iconst_1 (5, 1)
	292 iadd (5, 1)
	293 ifle (5, 1)
	296 iconst_2 (6, 4)
	297 istore (6, 4)
	299 iload (6, 4)
	301 iload (6, 4)
	303 iload (6, 4)
	305 isub (6, 4)
	306 iconst_1 (6, 4)
	307 iadd (6, 4)
	308 if_icmpgt (6, 4)
	311 aload (6, 4)
	313 iload (6, 4)
	315 aaload (6, 4)
	316 iload (6, 4)
	318 dup2 (6, 4)
	319 daload (6, 4)
	320 iload (6, 4)
	322 i2d (6, 4)
	323 ddiv (6, 4)
	324 dastore (6, 4)
	325 iinc (6, 4)
	328 goto (6, 4)
	331 iinc (6, 4)
	334 goto (6, 4)
	337 iinc (6, 4)
	340 goto (6, 4)
	343 aload (5, 1)
	345 invokestatic (5, 1)
	348 areturn (5, 1)

Method: checkArray
	0 aload_1 (1, 1)
	1 ifnonnull (1, 1)
	4 new (1, 1)
	7 dup (1, 1)
	8 getstatic (1, 1)
	11 iconst_0 (1, 1)
	12 anewarray (1, 1)
	15 invokespecial (1, 1)
	18 athrow (1, 1)
	19 aload_1 (1, 1)
	20 arraylength (1, 1)
	21 iconst_2 (1, 1)
	22 if_icmpge (1, 1)
	25 new (1, 1)
	28 dup (1, 1)
	29 getstatic (1, 1)
	32 iconst_2 (1, 1)
	33 anewarray (1, 1)
	36 dup (1, 1)
	37 iconst_0 (1, 1)
	38 aload_1 (1, 1)
	39 arraylength (1, 1)
	40 invokestatic (1, 1)
	43 aastore (1, 1)
	44 dup (1, 1)
	45 iconst_1 (1, 1)
	46 iconst_2 (1, 1)
	47 invokestatic (1, 1)
	50 aastore (1, 1)
	51 invokespecial (1, 1)
	54 athrow (1, 1)
	55 return (0, 0)

Method: ksSum
	0 dload_1 (1, 1)
	1 dconst_0 (1, 1)
	2 dcmpl (1, 1)
	3 ifne (1, 1)
	6 dconst_0 (1, 1)
	7 dreturn (1, 1)
	8 ldc2_w (0, 4)
	11 dload_1 (0, 4)
	12 dmul (0, 4)
	13 dload_1 (0, 4)
	14 dmul (0, 4)
	15 dstore (0, 4)
	17 iconst_m1 (0, 4)
	18 istore (0, 4)
	20 lconst_1 (0, 4)
	21 lstore (0, 4)
	23 ldc2_w (0, 4)
	26 dstore (0, 4)
	28 dconst_1 (0, 4)
	29 dstore (0, 4)
	31 dload (1, 3)
	33 dload_3 (1, 3)
	34 dcmpl (1, 3)
	35 ifle (1, 3)
	38 lload (1, 3)
	40 iload (1, 3)
	42 i2l (1, 3)
	43 lcmp (1, 3)
	44 ifge (1, 3)
	47 dload (1, 3)
	49 lload (1, 3)
	51 l2d (1, 3)
	52 dmul (1, 3)
	53 lload (1, 3)
	55 l2d (1, 3)
	56 dmul (1, 3)
	57 invokestatic (1, 3)
	60 dstore (1, 3)
	62 dload (1, 3)
	64 iload (1, 3)
	66 i2d (1, 3)
	67 dload (1, 3)
	69 dmul (1, 3)
	70 dadd (1, 3)
	71 dstore (1, 3)
	73 iload (1, 3)
	75 iconst_m1 (1, 3)
	76 imul (1, 3)
	77 istore (1, 3)
	79 lload (1, 3)
	81 lconst_1 (1, 3)
	82 ladd (1, 3)
	83 lstore (1, 3)
	85 goto (1, 3)
	88 lload (1, 1)
	90 iload (1, 1)
	92 i2l (1, 1)
	93 lcmp (1, 1)
	94 ifne (1, 1)
	97 new (1, 1)
	100 dup (1, 1)
	101 iload (1, 1)
	103 invokestatic (1, 1)
	106 invokespecial (1, 1)
	109 athrow (1, 1)
	110 dload (0, 4)
	112 ldc2_w (0, 4)
	115 dmul (0, 4)
	116 dreturn (0, 4)

Method: calculateIntegralD
	0 ldc2_w (0, 0)
	3 dstore (0, 0)
	5 iload_2 (0, 0)
	6 i2l (0, 0)
	7 iload_3 (0, 0)
	8 i2l (0, 0)
	9 lmul (0, 0)
	10 lstore (0, 0)
	12 dload_0 (0, 0)
	13 ldc2_w (0, 0)
	16 dsub (0, 0)
	17 lload (0, 0)
	19 l2d (0, 0)
	20 dmul (0, 0)
	21 invokestatic (0, 0)
	24 d2l (0, 0)
	25 lstore (0, 0)
	27 dload_0 (0, 0)
	28 ldc2_w (0, 0)
	31 dadd (0, 0)
	32 lload (0, 0)
	34 l2d (0, 0)
	35 dmul (0, 0)
	36 invokestatic (0, 0)
	39 d2l (0, 0)
	40 lstore (0, 0)
	42 iload (1, 1)
	44 ifeq (1, 1)
	47 lload (1, 1)
	49 lload (1, 1)
	51 lcmp (1, 1)
	52 ifne (1, 1)
	55 lload (1, 1)
	57 lconst_1 (1, 1)
	58 ladd (1, 1)
	59 lreturn (1, 1)
	60 lload (1, 2)
	62 lreturn (1, 2)

Method: exactP
	0 dconst_1 (0, 0)
	1 iload (0, 0)
	3 iload_3 (0, 0)
	4 iload (0, 0)
	6 iload_3 (0, 0)
	7 dload_1 (0, 0)
	8 iload (0, 0)
	10 iload_3 (0, 0)
	11 iload (0, 0)
	13 invokestatic (0, 0)
	16 iload (0, 0)
	18 invokestatic (0, 0)
	21 iload_3 (0, 0)
	22 iload (0, 0)
	24 iadd (0, 0)
	25 iload (0, 0)
	27 invokestatic (0, 0)
	30 ddiv (0, 0)
	31 dsub (0, 0)
	32 dreturn (0, 0)

Method: approximateP
	0 iload (0, 0)
	2 i2d (0, 0)
	3 dstore (0, 0)
	5 iload_3 (0, 0)
	6 i2d (0, 0)
	7 dstore (0, 0)
	9 dconst_1 (0, 0)
	10 aload_0 (0, 0)
	11 dload_1 (0, 0)
	12 dload (0, 0)
	14 dload (0, 0)
	16 dmul (0, 0)
	17 dload (0, 0)
	19 dload (0, 0)
	21 dadd (0, 0)
	22 ddiv (0, 0)
	23 invokestatic (0, 0)
	26 dmul (0, 0)
	27 ldc2_w (0, 0)
	30 ldc (0, 0)
	32 invokevirtual (0, 0)
	35 dsub (0, 0)
	36 dreturn (0, 0)

Method: fillBooleanArrayRandomlyWithFixedNumberTrueValues
	0 aload_0 (0, 0)
	1 iconst_1 (0, 0)
	2 invokestatic (0, 0)
	5 iload_1 (1, 4)
	6 istore_3 (1, 4)
	7 iload_3 (1, 4)
	8 aload_0 (1, 4)
	9 arraylength (1, 4)
	10 if_icmpge (1, 4)
	13 aload_2 (1, 4)
	14 iload_3 (1, 4)
	15 iconst_1 (1, 4)
	16 iadd (1, 4)
	17 invokeinterface (1, 4)
	22 istore (1, 4)
	24 aload_0 (1, 4)
	25 aload_0 (1, 4)
	26 iload (1, 4)
	28 baload (1, 4)
	29 ifeq (1, 4)
	32 iload (1, 4)
	34 goto (1, 4)
	37 iload_3 (1, 4)
	38 iconst_0 (1, 4)
	39 bastore (1, 4)
	40 iinc (1, 4)
	43 goto (1, 4)
	46 return (0, 0)

Method: monteCarloP
	0 aload_0 (0, 0)
	1 dload_1 (0, 0)
	2 iload_3 (0, 0)
	3 iload (0, 0)
	5 iload (0, 0)
	7 invokestatic (0, 0)
	10 iload_3 (0, 0)
	11 iload (0, 0)
	13 iload (0, 0)
	15 invokespecial (0, 0)
	18 dreturn (0, 0)

Method: integralMonteCarloP
	0 iload_3 (0, 0)
	1 iload (0, 0)
	3 invokestatic (0, 0)
	6 istore (0, 0)
	8 iload_3 (0, 0)
	9 iload (0, 0)
	11 invokestatic (0, 0)
	14 istore (0, 0)
	16 iload (0, 0)
	18 iload (0, 0)
	20 iadd (0, 0)
	21 istore (0, 0)
	23 iconst_0 (0, 0)
	24 istore (0, 0)
	26 iload (0, 0)
	28 newarray (0, 0)
	30 astore (0, 0)
	32 iconst_0 (1, 4)
	33 istore (1, 4)
	35 iload (1, 4)
	37 iload (1, 4)
	39 if_icmpge (1, 4)
	42 aload (1, 4)
	44 iload (1, 4)
	46 aload_0 (1, 4)
	47 getfield (1, 4)
	50 invokestatic (1, 4)
	53 lconst_0 (1, 4)
	54 lstore (1, 4)
	56 iconst_0 (2, 4)
	57 istore (2, 4)
	59 iload (2, 4)
	61 aload (2, 4)
	63 arraylength (2, 4)
	64 if_icmpge (2, 4)
	67 aload (3, 1)
	69 iload (3, 1)
	71 baload (3, 1)
	72 ifeq (3, 1)
	75 lload (3, 1)
	77 iload (3, 1)
	79 i2l (3, 1)
	80 ladd (3, 1)
	81 lstore (3, 1)
	83 lload (4, 1)
	85 lload_1 (4, 1)
	86 lcmp (4, 1)
	87 iflt (4, 1)
	90 iinc (4, 1)
	93 goto (4, 1)
	96 lload (3, 2)
	98 iload (3, 2)
	100 i2l (3, 2)
	101 lsub (3, 2)
	102 lstore (3, 2)
	104 lload (4, 1)
	106 lload_1 (4, 1)
	107 lneg (4, 1)
	108 lcmp (4, 1)
	109 ifgt (4, 1)
	112 iinc (4, 1)
	115 goto (4, 1)
	118 iinc (4, 1)
	121 goto (4, 1)
	124 iinc (4, 1)
	127 goto (4, 1)
	130 iload (3, 1)
	132 i2d (3, 1)
	133 iload (3, 1)
	135 i2d (3, 1)
	136 ddiv (3, 1)
	137 dreturn (3, 1)

Method: fixTies
	0 iconst_2 (0, 0)
	1 anewarray (0, 0)
	4 dup (0, 0)
	5 iconst_0 (0, 0)
	6 aload_0 (0, 0)
	7 aastore (0, 0)
	8 dup (0, 0)
	9 iconst_1 (0, 0)
	10 aload_1 (0, 0)
	11 aastore (0, 0)
	12 invokestatic (0, 0)
	15 invokestatic (0, 0)
	18 astore_2 (0, 0)
	19 aload_2 (1, 1)
	20 arraylength (1, 1)
	21 aload_0 (1, 1)
	22 arraylength (1, 1)
	23 aload_1 (1, 1)
	24 arraylength (1, 1)
	25 iadd (1, 1)
	26 if_icmpne (1, 1)
	29 return (1, 1)
	30 dconst_1 (0, 1)
	31 dstore_3 (0, 1)
	32 aload_2 (0, 1)
	33 iconst_0 (0, 1)
	34 daload (0, 1)
	35 dstore (0, 1)
	37 dconst_1 (0, 1)
	38 dstore (0, 1)
	40 iconst_1 (1, 4)
	41 istore (1, 4)
	43 iload (1, 4)
	45 aload_2 (1, 4)
	46 arraylength (1, 4)
	47 if_icmpge (1, 4)
	50 dload (1, 4)
	52 aload_2 (1, 4)
	53 iload (1, 4)
	55 daload (1, 4)
	56 dsub (1, 4)
	57 dstore (1, 4)
	59 dload (2, 1)
	61 dload_3 (2, 1)
	62 dcmpg (2, 1)
	63 ifge (2, 1)
	66 dload (2, 1)
	68 dstore_3 (2, 1)
	69 aload_2 (1, 4)
	70 iload (1, 4)
	72 daload (1, 4)
	73 dstore (1, 4)
	75 iinc (1, 4)
	78 goto (1, 4)
	81 dload_3 (0, 1)
	82 ldc2_w (0, 1)
	85 ddiv (0, 1)
	86 dstore_3 (0, 1)
	87 new (0, 1)
	90 dup (0, 1)
	91 new (0, 1)
	94 dup (0, 1)
	95 bipush (0, 1)
	97 invokespecial (0, 1)
	100 dload_3 (0, 1)
	101 dneg (0, 1)
	102 dload_3 (0, 1)
	103 invokespecial (0, 1)
	106 astore (0, 1)
	108 iconst_0 (0, 1)
	109 istore (0, 1)
	111 iconst_1 (0, 1)
	112 istore (0, 1)
	114 aload_0 (1, 1)
	115 aload (1, 1)
	117 invokestatic (1, 1)
	120 aload_1 (1, 1)
	121 aload (1, 1)
	123 invokestatic (1, 1)
	126 aload_0 (1, 1)
	127 aload_1 (1, 1)
	128 invokestatic (1, 1)
	131 istore (1, 1)
	133 iinc (1, 1)
	136 iload (0, 1)
	138 ifeq (0, 1)
	141 iload (0, 1)
	143 sipush (0, 1)
	146 if_icmplt (0, 1)
	149 iload (1, 1)
	151 ifeq (1, 1)
	154 new (1, 1)
	157 dup (1, 1)
	158 invokespecial (1, 1)
	161 athrow (1, 1)
	162 return (0, 1)

Method: hasTies
	0 new (0, 0)
	3 dup (0, 0)
	4 invokespecial (0, 0)
	7 astore_2 (0, 0)
	8 iconst_0 (1, 4)
	9 istore_3 (1, 4)
	10 iload_3 (1, 4)
	11 aload_0 (1, 4)
	12 arraylength (1, 4)
	13 if_icmpge (1, 4)
	16 aload_2 (2, 1)
	17 aload_0 (2, 1)
	18 iload_3 (2, 1)
	19 daload (2, 1)
	20 invokestatic (2, 1)
	23 invokevirtual (2, 1)
	26 ifne (2, 1)
	29 iconst_1 (2, 1)
	30 ireturn (2, 1)
	31 iinc (2, 1)
	34 goto (2, 1)
	37 iconst_0 (2, 4)
	38 istore_3 (2, 4)
	39 iload_3 (2, 4)
	40 aload_1 (2, 4)
	41 arraylength (2, 4)
	42 if_icmpge (2, 4)
	45 aload_2 (3, 1)
	46 aload_1 (3, 1)
	47 iload_3 (3, 1)
	48 daload (3, 1)
	49 invokestatic (3, 1)
	52 invokevirtual (3, 1)
	55 ifne (3, 1)
	58 iconst_1 (3, 1)
	59 ireturn (3, 1)
	60 iinc (3, 1)
	63 goto (3, 1)
	66 iconst_0 (2, 4)
	67 ireturn (2, 4)

Method: jitter
	0 iconst_0 (1, 4)
	1 istore_2 (1, 4)
	2 iload_2 (1, 4)
	3 aload_0 (1, 4)
	4 arraylength (1, 4)
	5 if_icmpge (1, 4)
	8 aload_0 (1, 4)
	9 iload_2 (1, 4)
	10 dup2 (1, 4)
	11 daload (1, 4)
	12 aload_1 (1, 4)
	13 invokeinterface (1, 4)
	18 dadd (1, 4)
	19 dastore (1, 4)
	20 iinc (1, 4)
	23 goto (1, 4)
	26 return (0, 0)

Method: c
	0 iload (1, 1)
	2 ifeq (1, 1)
	5 iload_0 (1, 1)
	6 i2l (1, 1)
	7 iload_3 (1, 1)
	8 i2l (1, 1)
	9 lmul (1, 1)
	10 iload_1 (1, 1)
	11 i2l (1, 1)
	12 iload_2 (1, 1)
	13 i2l (1, 1)
	14 lmul (1, 1)
	15 lsub (1, 1)
	16 invokestatic (1, 1)
	19 lload (1, 1)
	21 lcmp (1, 1)
	22 ifgt (1, 1)
	25 iconst_1 (1, 1)
	26 goto (1, 1)
	29 iconst_0 (1, 1)
	30 ireturn (1, 1)
	31 iload_0 (0, 0)
	32 i2l (0, 0)
	33 iload_3 (0, 0)
	34 i2l (0, 0)
	35 lmul (0, 0)
	36 iload_1 (0, 0)
	37 i2l (0, 0)
	38 iload_2 (0, 0)
	39 i2l (0, 0)
	40 lmul (0, 0)
	41 lsub (0, 0)
	42 invokestatic (0, 0)
	45 lload (0, 0)
	47 lcmp (0, 0)
	48 ifge (0, 0)
	51 iconst_1 (0, 0)
	52 goto (0, 0)
	55 iconst_0 (0, 0)
	56 ireturn (0, 0)

Method: n
	0 iload_3 (0, 0)
	1 newarray (0, 0)
	3 astore (0, 0)
	5 dconst_0 (0, 0)
	6 dstore (0, 0)
	8 iconst_0 (1, 4)
	9 istore (1, 4)
	11 iload (1, 4)
	13 iload_3 (1, 4)
	14 if_icmpge (1, 4)
	17 aload (1, 4)
	19 iload (1, 4)
	21 iconst_0 (1, 4)
	22 iload (1, 4)
	24 iconst_1 (1, 4)
	25 iadd (1, 4)
	26 iload_2 (1, 4)
	27 iload_3 (1, 4)
	28 lload (1, 4)
	30 iload (1, 4)
	32 invokestatic (1, 4)
	35 i2d (1, 4)
	36 dastore (1, 4)
	37 iinc (1, 4)
	40 goto (1, 4)
	43 iconst_1 (1, 4)
	44 istore (1, 4)
	46 iload (1, 4)
	48 iload_0 (1, 4)
	49 if_icmpgt (1, 4)
	52 iload (1, 4)
	54 iconst_0 (1, 4)
	55 iload_2 (1, 4)
	56 iload_3 (1, 4)
	57 lload (1, 4)
	59 iload (1, 4)
	61 invokestatic (1, 4)
	64 i2d (1, 4)
	65 dstore (1, 4)
	67 iconst_1 (2, 4)
	68 istore (2, 4)
	70 iload (2, 4)
	72 iload_1 (2, 4)
	73 if_icmpgt (2, 4)
	76 aload (2, 4)
	78 iload (2, 4)
	80 iconst_1 (2, 4)
	81 isub (2, 4)
	82 iload (2, 4)
	84 iload (2, 4)
	86 iload_2 (2, 4)
	87 iload_3 (2, 4)
	88 lload (2, 4)
	90 iload (2, 4)
	92 invokestatic (2, 4)
	95 i2d (2, 4)
	96 dload (2, 4)
	98 aload (2, 4)
	100 iload (2, 4)
	102 iconst_1 (2, 4)
	103 isub (2, 4)
	104 daload (2, 4)
	105 dadd (2, 4)
	106 dmul (2, 4)
	107 dastore (2, 4)
	108 aload (2, 4)
	110 iload (2, 4)
	112 iconst_1 (2, 4)
	113 isub (2, 4)
	114 daload (2, 4)
	115 dstore (2, 4)
	117 iinc (2, 4)
	120 goto (2, 4)
	123 iinc (2, 4)
	126 goto (2, 4)
	129 dload (1, 4)
	131 dreturn (1, 4)

