Method: <init>
	0 aload_0 (0, 0)
	1 invokespecial (0, 0)
	2 java/lang/Object.<init>:()V (0, 0)
	4 aload_0 (0, 0)
	5 new (0, 0)
	6 org/apache/commons/math3/stat/ranking/NaturalRanking (0, 0)
	8 dup (0, 0)
	9 aload_1 (0, 0)
	10 aload_2 (0, 0)
	11 invokespecial (0, 0)
	12 org/apache/commons/math3/stat/ranking/NaturalRanking.<init>:(Lorg/apache/commons/math3/stat/ranking/NaNStrategy;Lorg/apache/commons/math3/stat/ranking/TiesStrategy;)V (0, 0)
	14 putfield (0, 0)
	15 org/apache/commons/math3/stat/inference/MannWhitneyUTest.naturalRanking:Lorg/apache/commons/math3/stat/ranking/NaturalRanking; (0, 0)
	17 return (0, 0)

Method: ensureDataConformance
	0 aload_1 (1, 1)
	1 ifnull (1, 1)
	2 7 (1, 1)
	4 aload_2 (1, 1)
	5 ifnonnull (1, 1)
	6 11 (1, 1)
	8 new (1, 1)
	9 org/apache/commons/math3/exception/NullArgumentException (1, 1)
	11 dup (1, 1)
	12 invokespecial (1, 1)
	13 org/apache/commons/math3/exception/NullArgumentException.<init>:()V (1, 1)
	15 athrow (1, 1)
	16 aload_1 (2, 1)
	17 arraylength (2, 1)
	18 ifeq (2, 1)
	19 8 (2, 1)
	21 aload_2 (2, 1)
	22 arraylength (2, 1)
	23 ifne (2, 1)
	24 11 (2, 1)
	26 new (2, 1)
	27 org/apache/commons/math3/exception/NoDataException (2, 1)
	29 dup (2, 1)
	30 invokespecial (2, 1)
	31 org/apache/commons/math3/exception/NoDataException.<init>:()V (2, 1)
	33 athrow (2, 1)
	34 return (0, 1)

Method: concatenateSamples
	0 aload_1 (0, 0)
	1 arraylength (0, 0)
	2 aload_2 (0, 0)
	3 arraylength (0, 0)
	4 iadd (0, 0)
	5 newarray (0, 0)
	6 7 (0, 0)
	7 astore_3 (0, 0)
	8 aload_1 (0, 0)
	9 iconst_0 (0, 0)
	10 aload_3 (0, 0)
	11 iconst_0 (0, 0)
	12 aload_1 (0, 0)
	13 arraylength (0, 0)
	14 invokestatic (0, 0)
	15 java/lang/System.arraycopy:(Ljava/lang/Object;ILjava/lang/Object;II)V (0, 0)
	17 aload_2 (0, 0)
	18 iconst_0 (0, 0)
	19 aload_3 (0, 0)
	20 aload_1 (0, 0)
	21 arraylength (0, 0)
	22 aload_2 (0, 0)
	23 arraylength (0, 0)
	24 invokestatic (0, 0)
	25 java/lang/System.arraycopy:(Ljava/lang/Object;ILjava/lang/Object;II)V (0, 0)
	27 aload_3 (0, 0)
	28 areturn (0, 0)

Method: mannWhitneyU
	0 aload_0 (1, 4)
	1 aload_1 (1, 4)
	2 aload_2 (1, 4)
	3 invokespecial (1, 4)
	4 org/apache/commons/math3/stat/inference/MannWhitneyUTest.ensureDataConformance:([D[D)V (1, 4)
	6 aload_0 (1, 4)
	7 aload_1 (1, 4)
	8 aload_2 (1, 4)
	9 invokespecial (1, 4)
	10 org/apache/commons/math3/stat/inference/MannWhitneyUTest.concatenateSamples:([D[D)[D (1, 4)
	12 astore_3 (1, 4)
	13 aload_0 (1, 4)
	14 getfield (1, 4)
	15 org/apache/commons/math3/stat/inference/MannWhitneyUTest.naturalRanking:Lorg/apache/commons/math3/stat/ranking/NaturalRanking; (1, 4)
	17 aload_3 (1, 4)
	18 invokevirtual (1, 4)
	19 org/apache/commons/math3/stat/ranking/NaturalRanking.rank:([D)[D (1, 4)
	21 astore (1, 4)
	22 #4 (1, 4)
	23 dconst_0 (1, 4)
	24 dstore (1, 4)
	25 #5 (1, 4)
	26 iconst_0 (3, 4)
	27 istore (3, 4)
	28 #7 (3, 4)
	29 iload (3, 4)
	30 #7 (3, 4)
	31 aload_1 (3, 4)
	32 arraylength (3, 4)
	33 if_icmpge (3, 4)
	34 19 (3, 4)
	36 dload (3, 4)
	37 #5 (3, 4)
	38 aload (3, 4)
	39 #4 (3, 4)
	40 iload (3, 4)
	41 #7 (3, 4)
	42 daload (3, 4)
	43 dadd (3, 4)
	44 dstore (3, 4)
	45 #5 (3, 4)
	46 iinc (3, 4)
	47 #7 (3, 4)
	48 -89 (3, 4)
	49 goto (3, 4)
	50 -20 (3, 4)
	52 dload (3, 4)
	53 #5 (3, 4)
	54 aload_1 (3, 4)
	55 arraylength (3, 4)
	56 i2l (3, 4)
	57 aload_1 (3, 4)
	58 arraylength (3, 4)
	59 iconst_1 (3, 4)
	60 iadd (3, 4)
	61 i2l (3, 4)
	62 lmul (3, 4)
	63 ldc2_w (3, 4)
	64 2 (3, 4)
	66 ldiv (3, 4)
	67 l2d (3, 4)
	68 dsub (3, 4)
	69 dstore (3, 4)
	70 #7 (3, 4)
	71 aload_1 (3, 4)
	72 arraylength (3, 4)
	73 i2l (3, 4)
	74 aload_2 (3, 4)
	75 arraylength (3, 4)
	76 i2l (3, 4)
	77 lmul (3, 4)
	78 l2d (3, 4)
	79 dload (3, 4)
	80 #7 (3, 4)
	81 dsub (3, 4)
	82 dstore (3, 4)
	83 #9 (3, 4)
	84 dload (3, 4)
	85 #7 (3, 4)
	86 dload (3, 4)
	87 #9 (3, 4)
	88 invokestatic (3, 4)
	89 org/apache/commons/math3/util/FastMath.max:(DD)D (3, 4)
	91 dreturn (0, 4)

Method: calculateAsymptoticPValue
	0 iload_3 (0, 0)
	1 i2l (0, 0)
	2 iload (0, 0)
	3 #4 (0, 0)
	4 i2l (0, 0)
	5 lmul (0, 0)
	6 lstore (0, 0)
	7 #5 (0, 0)
	8 lload (0, 0)
	9 #5 (0, 0)
	10 l2d (0, 0)
	11 ldc2_w (0, 0)
	12 2.0 (0, 0)
	14 ddiv (0, 0)
	15 dstore (0, 0)
	16 #7 (0, 0)
	17 lload (0, 0)
	18 #5 (0, 0)
	19 iload_3 (0, 0)
	20 iload (0, 0)
	21 #4 (0, 0)
	22 iadd (0, 0)
	23 iconst_1 (0, 0)
	24 iadd (0, 0)
	25 i2l (0, 0)
	26 lmul (0, 0)
	27 l2d (0, 0)
	28 ldc2_w (0, 0)
	29 12.0 (0, 0)
	31 ddiv (0, 0)
	32 dstore (0, 0)
	33 #9 (0, 0)
	34 dload_1 (0, 0)
	35 dload (0, 0)
	36 #7 (0, 0)
	37 dsub (0, 0)
	38 dload (0, 0)
	39 #9 (0, 0)
	40 invokestatic (0, 0)
	41 org/apache/commons/math3/util/FastMath.sqrt:(D)D (0, 0)
	43 ddiv (0, 0)
	44 dstore (0, 0)
	45 #11 (0, 0)
	46 new (0, 0)
	47 org/apache/commons/math3/distribution/NormalDistribution (0, 0)
	49 dup (0, 0)
	50 aconst_null (0, 0)
	51 dconst_0 (0, 0)
	52 dconst_1 (0, 0)
	53 invokespecial (0, 0)
	54 org/apache/commons/math3/distribution/NormalDistribution.<init>:(Lorg/apache/commons/math3/random/RandomGenerator;DD)V (0, 0)
	56 astore (0, 0)
	57 #13 (0, 0)
	58 ldc2_w (0, 0)
	59 2.0 (0, 0)
	61 aload (0, 0)
	62 #13 (0, 0)
	63 dload (0, 0)
	64 #11 (0, 0)
	65 invokevirtual (0, 0)
	66 org/apache/commons/math3/distribution/NormalDistribution.cumulativeProbability:(D)D (0, 0)
	68 dmul (0, 0)
	69 dreturn (0, 0)

Method: mannWhitneyUTest
	0 aload_0 (1, 4)
	1 aload_1 (1, 4)
	2 aload_2 (1, 4)
	3 invokespecial (1, 4)
	4 org/apache/commons/math3/stat/inference/MannWhitneyUTest.ensureDataConformance:([D[D)V (1, 4)
	6 aload_0 (1, 4)
	7 aload_1 (1, 4)
	8 aload_2 (1, 4)
	9 invokevirtual (1, 4)
	10 org/apache/commons/math3/stat/inference/MannWhitneyUTest.mannWhitneyU:([D[D)D (1, 4)
	12 dstore_3 (1, 4)
	13 aload_1 (1, 4)
	14 arraylength (1, 4)
	15 i2l (1, 4)
	16 aload_2 (1, 4)
	17 arraylength (1, 4)
	18 i2l (1, 4)
	19 lmul (1, 4)
	20 l2d (1, 4)
	21 dload_3 (1, 4)
	22 dsub (1, 4)
	23 dstore (1, 4)
	24 #5 (1, 4)
	25 aload_0 (1, 4)
	26 dload (1, 4)
	27 #5 (1, 4)
	28 aload_1 (1, 4)
	29 arraylength (1, 4)
	30 aload_2 (1, 4)
	31 arraylength (1, 4)
	32 invokespecial (1, 4)
	33 org/apache/commons/math3/stat/inference/MannWhitneyUTest.calculateAsymptoticPValue:(DII)D (1, 4)
	35 dreturn (0, 4)

