Method: <init>
	0 aload_0 (0, 0)
	1 invokespecial (0, 0)
	2 java/lang/Object.<init>:()V (0, 0)
	4 return (0, 0)

Method: homoscedasticT
	0 getstatic (0, 0)
	1 org/apache/commons/math3/stat/inference/TestUtils.T_TEST:Lorg/apache/commons/math3/stat/inference/TTest; (0, 0)
	3 aload_0 (0, 0)
	4 aload_1 (0, 0)
	5 invokevirtual (0, 0)
	6 org/apache/commons/math3/stat/inference/TTest.homoscedasticT:(Lorg/apache/commons/math3/stat/descriptive/StatisticalSummary;Lorg/apache/commons/math3/stat/descriptive/StatisticalSummary;)D (0, 0)
	8 dreturn (0, 0)

Method: homoscedasticTTest
	0 getstatic (0, 0)
	1 org/apache/commons/math3/stat/inference/TestUtils.T_TEST:Lorg/apache/commons/math3/stat/inference/TTest; (0, 0)
	3 aload_0 (0, 0)
	4 aload_1 (0, 0)
	5 invokevirtual (0, 0)
	6 org/apache/commons/math3/stat/inference/TTest.homoscedasticTTest:(Lorg/apache/commons/math3/stat/descriptive/StatisticalSummary;Lorg/apache/commons/math3/stat/descriptive/StatisticalSummary;)D (0, 0)
	8 dreturn (0, 0)

Method: pairedT
	0 getstatic (0, 0)
	1 org/apache/commons/math3/stat/inference/TestUtils.T_TEST:Lorg/apache/commons/math3/stat/inference/TTest; (0, 0)
	3 aload_0 (0, 0)
	4 aload_1 (0, 0)
	5 invokevirtual (0, 0)
	6 org/apache/commons/math3/stat/inference/TTest.pairedT:([D[D)D (0, 0)
	8 dreturn (0, 0)

Method: pairedTTest
	0 getstatic (0, 0)
	1 org/apache/commons/math3/stat/inference/TestUtils.T_TEST:Lorg/apache/commons/math3/stat/inference/TTest; (0, 0)
	3 aload_0 (0, 0)
	4 aload_1 (0, 0)
	5 invokevirtual (0, 0)
	6 org/apache/commons/math3/stat/inference/TTest.pairedTTest:([D[D)D (0, 0)
	8 dreturn (0, 0)

Method: t
	0 getstatic (0, 0)
	1 org/apache/commons/math3/stat/inference/TestUtils.T_TEST:Lorg/apache/commons/math3/stat/inference/TTest; (0, 0)
	3 aload_0 (0, 0)
	4 aload_1 (0, 0)
	5 invokevirtual (0, 0)
	6 org/apache/commons/math3/stat/inference/TTest.t:(Lorg/apache/commons/math3/stat/descriptive/StatisticalSummary;Lorg/apache/commons/math3/stat/descriptive/StatisticalSummary;)D (0, 0)
	8 dreturn (0, 0)

Method: tTest
	0 getstatic (0, 0)
	1 org/apache/commons/math3/stat/inference/TestUtils.T_TEST:Lorg/apache/commons/math3/stat/inference/TTest; (0, 0)
	3 aload_0 (0, 0)
	4 aload_1 (0, 0)
	5 invokevirtual (0, 0)
	6 org/apache/commons/math3/stat/inference/TTest.tTest:(Lorg/apache/commons/math3/stat/descriptive/StatisticalSummary;Lorg/apache/commons/math3/stat/descriptive/StatisticalSummary;)D (0, 0)
	8 dreturn (0, 0)

Method: chiSquare
	0 getstatic (0, 0)
	1 org/apache/commons/math3/stat/inference/TestUtils.CHI_SQUARE_TEST:Lorg/apache/commons/math3/stat/inference/ChiSquareTest; (0, 0)
	3 aload_0 (0, 0)
	4 invokevirtual (0, 0)
	5 org/apache/commons/math3/stat/inference/ChiSquareTest.chiSquare:([[J)D (0, 0)
	7 dreturn (0, 0)

Method: chiSquareTest
	0 getstatic (0, 0)
	1 org/apache/commons/math3/stat/inference/TestUtils.CHI_SQUARE_TEST:Lorg/apache/commons/math3/stat/inference/ChiSquareTest; (0, 0)
	3 aload_0 (0, 0)
	4 invokevirtual (0, 0)
	5 org/apache/commons/math3/stat/inference/ChiSquareTest.chiSquareTest:([[J)D (0, 0)
	7 dreturn (0, 0)

Method: chiSquareDataSetsComparison
	0 getstatic (0, 0)
	1 org/apache/commons/math3/stat/inference/TestUtils.CHI_SQUARE_TEST:Lorg/apache/commons/math3/stat/inference/ChiSquareTest; (0, 0)
	3 aload_0 (0, 0)
	4 aload_1 (0, 0)
	5 invokevirtual (0, 0)
	6 org/apache/commons/math3/stat/inference/ChiSquareTest.chiSquareDataSetsComparison:([J[J)D (0, 0)
	8 dreturn (0, 0)

Method: chiSquareTestDataSetsComparison
	0 getstatic (0, 0)
	1 org/apache/commons/math3/stat/inference/TestUtils.CHI_SQUARE_TEST:Lorg/apache/commons/math3/stat/inference/ChiSquareTest; (0, 0)
	3 aload_0 (0, 0)
	4 aload_1 (0, 0)
	5 dload_2 (0, 0)
	6 invokevirtual (0, 0)
	7 org/apache/commons/math3/stat/inference/ChiSquareTest.chiSquareTestDataSetsComparison:([J[JD)Z (0, 0)
	9 ireturn (0, 0)

Method: oneWayAnovaFValue
	0 getstatic (0, 0)
	1 org/apache/commons/math3/stat/inference/TestUtils.ONE_WAY_ANANOVA:Lorg/apache/commons/math3/stat/inference/OneWayAnova; (0, 0)
	3 aload_0 (0, 0)
	4 invokevirtual (0, 0)
	5 org/apache/commons/math3/stat/inference/OneWayAnova.anovaFValue:(Ljava/util/Collection;)D (0, 0)
	7 dreturn (0, 0)

Method: oneWayAnovaPValue
	0 getstatic (0, 0)
	1 org/apache/commons/math3/stat/inference/TestUtils.ONE_WAY_ANANOVA:Lorg/apache/commons/math3/stat/inference/OneWayAnova; (0, 0)
	3 aload_0 (0, 0)
	4 invokevirtual (0, 0)
	5 org/apache/commons/math3/stat/inference/OneWayAnova.anovaPValue:(Ljava/util/Collection;)D (0, 0)
	7 dreturn (0, 0)

Method: oneWayAnovaTest
	0 getstatic (0, 0)
	1 org/apache/commons/math3/stat/inference/TestUtils.ONE_WAY_ANANOVA:Lorg/apache/commons/math3/stat/inference/OneWayAnova; (0, 0)
	3 aload_0 (0, 0)
	4 dload_1 (0, 0)
	5 invokevirtual (0, 0)
	6 org/apache/commons/math3/stat/inference/OneWayAnova.anovaTest:(Ljava/util/Collection;D)Z (0, 0)
	8 ireturn (0, 0)

Method: g
	0 getstatic (0, 0)
	1 org/apache/commons/math3/stat/inference/TestUtils.G_TEST:Lorg/apache/commons/math3/stat/inference/GTest; (0, 0)
	3 aload_0 (0, 0)
	4 aload_1 (0, 0)
	5 invokevirtual (0, 0)
	6 org/apache/commons/math3/stat/inference/GTest.g:([D[J)D (0, 0)
	8 dreturn (0, 0)

Method: gTest
	0 getstatic (0, 0)
	1 org/apache/commons/math3/stat/inference/TestUtils.G_TEST:Lorg/apache/commons/math3/stat/inference/GTest; (0, 0)
	3 aload_0 (0, 0)
	4 aload_1 (0, 0)
	5 dload_2 (0, 0)
	6 invokevirtual (0, 0)
	7 org/apache/commons/math3/stat/inference/GTest.gTest:([D[JD)Z (0, 0)
	9 ireturn (0, 0)

Method: gTestIntrinsic
	0 getstatic (0, 0)
	1 org/apache/commons/math3/stat/inference/TestUtils.G_TEST:Lorg/apache/commons/math3/stat/inference/GTest; (0, 0)
	3 aload_0 (0, 0)
	4 aload_1 (0, 0)
	5 invokevirtual (0, 0)
	6 org/apache/commons/math3/stat/inference/GTest.gTestIntrinsic:([D[J)D (0, 0)
	8 dreturn (0, 0)

Method: gDataSetsComparison
	0 getstatic (0, 0)
	1 org/apache/commons/math3/stat/inference/TestUtils.G_TEST:Lorg/apache/commons/math3/stat/inference/GTest; (0, 0)
	3 aload_0 (0, 0)
	4 aload_1 (0, 0)
	5 invokevirtual (0, 0)
	6 org/apache/commons/math3/stat/inference/GTest.gDataSetsComparison:([J[J)D (0, 0)
	8 dreturn (0, 0)

Method: rootLogLikelihoodRatio
	0 getstatic (0, 0)
	1 org/apache/commons/math3/stat/inference/TestUtils.G_TEST:Lorg/apache/commons/math3/stat/inference/GTest; (0, 0)
	3 lload_0 (0, 0)
	4 lload_2 (0, 0)
	5 lload (0, 0)
	6 #4 (0, 0)
	7 lload (0, 0)
	8 #6 (0, 0)
	9 invokevirtual (0, 0)
	10 org/apache/commons/math3/stat/inference/GTest.rootLogLikelihoodRatio:(JJJJ)D (0, 0)
	12 dreturn (0, 0)

Method: gTestDataSetsComparison
	0 getstatic (0, 0)
	1 org/apache/commons/math3/stat/inference/TestUtils.G_TEST:Lorg/apache/commons/math3/stat/inference/GTest; (0, 0)
	3 aload_0 (0, 0)
	4 aload_1 (0, 0)
	5 dload_2 (0, 0)
	6 invokevirtual (0, 0)
	7 org/apache/commons/math3/stat/inference/GTest.gTestDataSetsComparison:([J[JD)Z (0, 0)
	9 ireturn (0, 0)

Method: kolmogorovSmirnovStatistic
	0 getstatic (0, 0)
	1 org/apache/commons/math3/stat/inference/TestUtils.KS_TEST:Lorg/apache/commons/math3/stat/inference/KolmogorovSmirnovTest; (0, 0)
	3 aload_0 (0, 0)
	4 aload_1 (0, 0)
	5 invokevirtual (0, 0)
	6 org/apache/commons/math3/stat/inference/KolmogorovSmirnovTest.kolmogorovSmirnovStatistic:([D[D)D (0, 0)
	8 dreturn (0, 0)

Method: kolmogorovSmirnovTest
	0 getstatic (0, 0)
	1 org/apache/commons/math3/stat/inference/TestUtils.KS_TEST:Lorg/apache/commons/math3/stat/inference/KolmogorovSmirnovTest; (0, 0)
	3 aload_0 (0, 0)
	4 aload_1 (0, 0)
	5 iload_2 (0, 0)
	6 invokevirtual (0, 0)
	7 org/apache/commons/math3/stat/inference/KolmogorovSmirnovTest.kolmogorovSmirnovTest:([D[DZ)D (0, 0)
	9 dreturn (0, 0)

Method: exactP
	0 getstatic (0, 0)
	1 org/apache/commons/math3/stat/inference/TestUtils.KS_TEST:Lorg/apache/commons/math3/stat/inference/KolmogorovSmirnovTest; (0, 0)
	3 dload_0 (0, 0)
	4 iload_3 (0, 0)
	5 iload_2 (0, 0)
	6 iload (0, 0)
	7 #4 (0, 0)
	8 invokevirtual (0, 0)
	9 org/apache/commons/math3/stat/inference/KolmogorovSmirnovTest.exactP:(DIIZ)D (0, 0)
	11 dreturn (0, 0)

Method: approximateP
	0 getstatic (0, 0)
	1 org/apache/commons/math3/stat/inference/TestUtils.KS_TEST:Lorg/apache/commons/math3/stat/inference/KolmogorovSmirnovTest; (0, 0)
	3 dload_0 (0, 0)
	4 iload_2 (0, 0)
	5 iload_3 (0, 0)
	6 invokevirtual (0, 0)
	7 org/apache/commons/math3/stat/inference/KolmogorovSmirnovTest.approximateP:(DII)D (0, 0)
	9 dreturn (0, 0)

Method: monteCarloP
	0 getstatic (0, 0)
	1 org/apache/commons/math3/stat/inference/TestUtils.KS_TEST:Lorg/apache/commons/math3/stat/inference/KolmogorovSmirnovTest; (0, 0)
	3 dload_0 (0, 0)
	4 iload_2 (0, 0)
	5 iload_3 (0, 0)
	6 iload (0, 0)
	7 #4 (0, 0)
	8 iload (0, 0)
	9 #5 (0, 0)
	10 invokevirtual (0, 0)
	11 org/apache/commons/math3/stat/inference/KolmogorovSmirnovTest.monteCarloP:(DIIZI)D (0, 0)
	13 dreturn (0, 0)

Method: <clinit>
	0 new (0, 0)
	1 org/apache/commons/math3/stat/inference/TTest (0, 0)
	3 dup (0, 0)
	4 invokespecial (0, 0)
	5 org/apache/commons/math3/stat/inference/TTest.<init>:()V (0, 0)
	7 putstatic (0, 0)
	8 org/apache/commons/math3/stat/inference/TestUtils.T_TEST:Lorg/apache/commons/math3/stat/inference/TTest; (0, 0)
	10 new (0, 0)
	11 org/apache/commons/math3/stat/inference/ChiSquareTest (0, 0)
	13 dup (0, 0)
	14 invokespecial (0, 0)
	15 org/apache/commons/math3/stat/inference/ChiSquareTest.<init>:()V (0, 0)
	17 putstatic (0, 0)
	18 org/apache/commons/math3/stat/inference/TestUtils.CHI_SQUARE_TEST:Lorg/apache/commons/math3/stat/inference/ChiSquareTest; (0, 0)
	20 new (0, 0)
	21 org/apache/commons/math3/stat/inference/OneWayAnova (0, 0)
	23 dup (0, 0)
	24 invokespecial (0, 0)
	25 org/apache/commons/math3/stat/inference/OneWayAnova.<init>:()V (0, 0)
	27 putstatic (0, 0)
	28 org/apache/commons/math3/stat/inference/TestUtils.ONE_WAY_ANANOVA:Lorg/apache/commons/math3/stat/inference/OneWayAnova; (0, 0)
	30 new (0, 0)
	31 org/apache/commons/math3/stat/inference/GTest (0, 0)
	33 dup (0, 0)
	34 invokespecial (0, 0)
	35 org/apache/commons/math3/stat/inference/GTest.<init>:()V (0, 0)
	37 putstatic (0, 0)
	38 org/apache/commons/math3/stat/inference/TestUtils.G_TEST:Lorg/apache/commons/math3/stat/inference/GTest; (0, 0)
	40 new (0, 0)
	41 org/apache/commons/math3/stat/inference/KolmogorovSmirnovTest (0, 0)
	43 dup (0, 0)
	44 invokespecial (0, 0)
	45 org/apache/commons/math3/stat/inference/KolmogorovSmirnovTest.<init>:()V (0, 0)
	47 putstatic (0, 0)
	48 org/apache/commons/math3/stat/inference/TestUtils.KS_TEST:Lorg/apache/commons/math3/stat/inference/KolmogorovSmirnovTest; (0, 0)
	50 return (0, 0)

