Method: pairedT
	0 aload_0 (0, 0)
	1 aload_1 (0, 0)
	2 invokespecial (0, 0)
	3 org/apache/commons/math3/stat/inference/TTest.checkSampleData:([D)V (0, 0)
	5 aload_0 (0, 0)
	6 aload_2 (0, 0)
	7 invokespecial (0, 0)
	8 org/apache/commons/math3/stat/inference/TTest.checkSampleData:([D)V (0, 0)
	10 aload_1 (1, 1)
	11 aload_2 (1, 1)
	12 invokestatic (1, 1)
	13 org/apache/commons/math3/stat/StatUtils.meanDifference:([D[D)D (1, 1)
	15 dstore_3 (1, 1)
	16 aload_0 (2, 1)
	17 dload_3 (2, 1)
	18 dconst_0 (2, 1)
	19 aload_1 (2, 1)
	20 aload_2 (2, 1)
	21 dload_3 (2, 1)
	22 invokestatic (3, 1)
	23 org/apache/commons/math3/stat/StatUtils.varianceDifference:([D[DD)D (3, 1)
	25 aload_1 (3, 1)
	26 arraylength (3, 1)
	27 i2d (3, 1)
	28 invokevirtual (3, 1)
	29 org/apache/commons/math3/stat/inference/TTest.t:(DDDD)D (3, 1)
	31 dreturn (0, 1)

Method: pairedTTest
	0 aload_0 (1, 1)
	1 dload_3 (1, 1)
	2 invokespecial (1, 1)
	3 org/apache/commons/math3/stat/inference/TTest.checkSignificanceLevel:(D)V (1, 1)
	5 aload_0 (1, 1)
	6 aload_1 (1, 1)
	7 aload_2 (1, 1)
	8 invokevirtual (1, 1)
	9 org/apache/commons/math3/stat/inference/TTest.pairedTTest:([D[D)D (1, 1)
	11 dload_3 (1, 1)
	12 dcmpg (1, 1)
	13 ifge (1, 1)
	14 7 (1, 1)
	16 iconst_1 (1, 1)
	17 goto (1, 1)
	18 4 (1, 1)
	20 iconst_0 (1, 1)
	21 ireturn (0, 1)

Method: t
	0 dload_1 (0, 0)
	1 dload_3 (0, 0)
	2 dsub (0, 0)
	3 dload (0, 0)
	4 #5 (0, 0)
	5 dload (0, 0)
	6 #9 (0, 0)
	7 ddiv (0, 0)
	8 dload (0, 0)
	9 #7 (0, 0)
	10 dload (0, 0)
	11 #11 (0, 0)
	12 ddiv (0, 0)
	13 dadd (0, 0)
	14 invokestatic (0, 0)
	15 org/apache/commons/math3/util/FastMath.sqrt:(D)D (0, 0)
	17 ddiv (0, 0)
	18 dreturn (0, 0)

Method: homoscedasticT
	0 dload (0, 0)
	1 #9 (0, 0)
	2 dconst_1 (0, 0)
	3 dsub (0, 0)
	4 dload (0, 0)
	5 #5 (0, 0)
	6 dmul (0, 0)
	7 dload (0, 0)
	8 #11 (0, 0)
	9 dconst_1 (0, 0)
	10 dsub (0, 0)
	11 dload (0, 0)
	12 #7 (0, 0)
	13 dmul (0, 0)
	14 dadd (0, 0)
	15 dload (0, 0)
	16 #9 (0, 0)
	17 dload (0, 0)
	18 #11 (0, 0)
	19 dadd (0, 0)
	20 ldc2_w (0, 0)
	21 2.0 (0, 0)
	23 dsub (0, 0)
	24 ddiv (0, 0)
	25 dstore (0, 0)
	26 #13 (0, 0)
	27 dload_1 (0, 0)
	28 dload_3 (0, 0)
	29 dsub (0, 0)
	30 dload (0, 0)
	31 #13 (0, 0)
	32 dconst_1 (0, 0)
	33 dload (0, 0)
	34 #9 (0, 0)
	35 ddiv (0, 0)
	36 dconst_1 (0, 0)
	37 dload (0, 0)
	38 #11 (0, 0)
	39 ddiv (0, 0)
	40 dadd (0, 0)
	41 dmul (0, 0)
	42 invokestatic (0, 0)
	43 org/apache/commons/math3/util/FastMath.sqrt:(D)D (0, 0)
	45 ddiv (0, 0)
	46 dreturn (0, 0)

Method: tTest
	0 aload_0 (0, 0)
	1 dload_1 (0, 0)
	2 dload_3 (0, 0)
	3 dload (0, 0)
	4 #5 (0, 0)
	5 dload (0, 0)
	6 #7 (0, 0)
	7 dload (0, 0)
	8 #9 (0, 0)
	9 dload (0, 0)
	10 #11 (0, 0)
	11 invokevirtual (0, 0)
	12 org/apache/commons/math3/stat/inference/TTest.t:(DDDDDD)D (0, 0)
	14 invokestatic (0, 0)
	15 org/apache/commons/math3/util/FastMath.abs:(D)D (0, 0)
	17 dstore (0, 0)
	18 #13 (0, 0)
	19 aload_0 (0, 0)
	20 dload (0, 0)
	21 #5 (0, 0)
	22 dload (0, 0)
	23 #7 (0, 0)
	24 dload (0, 0)
	25 #9 (0, 0)
	26 dload (0, 0)
	27 #11 (0, 0)
	28 invokevirtual (0, 0)
	29 org/apache/commons/math3/stat/inference/TTest.df:(DDDD)D (0, 0)
	31 dstore (0, 0)
	32 #15 (0, 0)
	33 new (0, 0)
	34 org/apache/commons/math3/distribution/TDistribution (0, 0)
	36 dup (0, 0)
	37 aconst_null (0, 0)
	38 dload (0, 0)
	39 #15 (0, 0)
	40 invokespecial (0, 0)
	41 org/apache/commons/math3/distribution/TDistribution.<init>:(Lorg/apache/commons/math3/random/RandomGenerator;D)V (0, 0)
	43 astore (0, 0)
	44 #17 (0, 0)
	45 ldc2_w (0, 0)
	46 2.0 (0, 0)
	48 aload (0, 0)
	49 #17 (0, 0)
	50 dload (0, 0)
	51 #13 (0, 0)
	52 dneg (0, 0)
	53 invokevirtual (0, 0)
	54 org/apache/commons/math3/distribution/TDistribution.cumulativeProbability:(D)D (0, 0)
	56 dmul (0, 0)
	57 dreturn (0, 0)

Method: homoscedasticTTest
	0 aload_0 (0, 0)
	1 dload_1 (0, 0)
	2 dload_3 (0, 0)
	3 dload (0, 0)
	4 #5 (0, 0)
	5 dload (0, 0)
	6 #7 (0, 0)
	7 dload (0, 0)
	8 #9 (0, 0)
	9 dload (0, 0)
	10 #11 (0, 0)
	11 invokevirtual (0, 0)
	12 org/apache/commons/math3/stat/inference/TTest.homoscedasticT:(DDDDDD)D (0, 0)
	14 invokestatic (0, 0)
	15 org/apache/commons/math3/util/FastMath.abs:(D)D (0, 0)
	17 dstore (0, 0)
	18 #13 (0, 0)
	19 dload (0, 0)
	20 #9 (0, 0)
	21 dload (0, 0)
	22 #11 (0, 0)
	23 dadd (0, 0)
	24 ldc2_w (0, 0)
	25 2.0 (0, 0)
	27 dsub (0, 0)
	28 dstore (0, 0)
	29 #15 (0, 0)
	30 new (0, 0)
	31 org/apache/commons/math3/distribution/TDistribution (0, 0)
	33 dup (0, 0)
	34 aconst_null (0, 0)
	35 dload (0, 0)
	36 #15 (0, 0)
	37 invokespecial (0, 0)
	38 org/apache/commons/math3/distribution/TDistribution.<init>:(Lorg/apache/commons/math3/random/RandomGenerator;D)V (0, 0)
	40 astore (0, 0)
	41 #17 (0, 0)
	42 ldc2_w (0, 0)
	43 2.0 (0, 0)
	45 aload (0, 0)
	46 #17 (0, 0)
	47 dload (0, 0)
	48 #13 (0, 0)
	49 dneg (0, 0)
	50 invokevirtual (0, 0)
	51 org/apache/commons/math3/distribution/TDistribution.cumulativeProbability:(D)D (0, 0)
	53 dmul (0, 0)
	54 dreturn (0, 0)

Method: df
	0 dload_1 (0, 0)
	1 dload (0, 0)
	2 #5 (0, 0)
	3 ddiv (0, 0)
	4 dload_3 (0, 0)
	5 dload (0, 0)
	6 #7 (0, 0)
	7 ddiv (0, 0)
	8 dadd (0, 0)
	9 dload_1 (0, 0)
	10 dload (0, 0)
	11 #5 (0, 0)
	12 ddiv (0, 0)
	13 dload_3 (0, 0)
	14 dload (0, 0)
	15 #7 (0, 0)
	16 ddiv (0, 0)
	17 dadd (0, 0)
	18 dmul (0, 0)
	19 dload_1 (0, 0)
	20 dload_1 (0, 0)
	21 dmul (0, 0)
	22 dload (0, 0)
	23 #5 (0, 0)
	24 dload (0, 0)
	25 #5 (0, 0)
	26 dmul (0, 0)
	27 dload (0, 0)
	28 #5 (0, 0)
	29 dconst_1 (0, 0)
	30 dsub (0, 0)
	31 dmul (0, 0)
	32 ddiv (0, 0)
	33 dload_3 (0, 0)
	34 dload_3 (0, 0)
	35 dmul (0, 0)
	36 dload (0, 0)
	37 #7 (0, 0)
	38 dload (0, 0)
	39 #7 (0, 0)
	40 dmul (0, 0)
	41 dload (0, 0)
	42 #7 (0, 0)
	43 dconst_1 (0, 0)
	44 dsub (0, 0)
	45 dmul (0, 0)
	46 ddiv (0, 0)
	47 dadd (0, 0)
	48 ddiv (0, 0)
	49 dreturn (0, 0)

Method: checkSignificanceLevel
	0 dload_1 (1, 1)
	1 dconst_0 (1, 1)
	2 dcmpg (1, 1)
	3 ifle (1, 1)
	4 11 (1, 1)
	6 dload_1 (1, 1)
	7 ldc2_w (1, 1)
	8 0.5 (1, 1)
	10 dcmpl (1, 1)
	11 ifle (1, 1)
	12 28 (1, 1)
	14 new (1, 1)
	15 org/apache/commons/math3/exception/OutOfRangeException (1, 1)
	17 dup (1, 1)
	18 getstatic (1, 1)
	19 org/apache/commons/math3/exception/util/LocalizedFormats.SIGNIFICANCE_LEVEL:Lorg/apache/commons/math3/exception/util/LocalizedFormats; (1, 1)
	21 dload_1 (1, 1)
	22 invokestatic (1, 1)
	23 java/lang/Double.valueOf:(D)Ljava/lang/Double; (1, 1)
	25 dconst_0 (1, 1)
	26 invokestatic (1, 1)
	27 java/lang/Double.valueOf:(D)Ljava/lang/Double; (1, 1)
	29 ldc2_w (1, 1)
	30 0.5 (1, 1)
	32 invokestatic (1, 1)
	33 java/lang/Double.valueOf:(D)Ljava/lang/Double; (1, 1)
	35 invokespecial (1, 1)
	36 org/apache/commons/math3/exception/OutOfRangeException.<init>:(Lorg/apache/commons/math3/exception/util/Localizable;Ljava/lang/Number;Ljava/lang/Number;Ljava/lang/Number;)V (1, 1)
	38 athrow (1, 1)
	39 return (0, 0)

Method: checkSampleData
	0 aload_1 (1, 1)
	1 ifnonnull (1, 1)
	2 11 (1, 1)
	4 new (1, 1)
	5 org/apache/commons/math3/exception/NullArgumentException (1, 1)
	7 dup (1, 1)
	8 invokespecial (1, 1)
	9 org/apache/commons/math3/exception/NullArgumentException.<init>:()V (1, 1)
	11 athrow (1, 1)
	12 aload_1 (1, 1)
	13 invokeinterface (1, 1)
	14 org/apache/commons/math3/stat/descriptive/StatisticalSummary.homoscedasticT:(DDDDDD)D (1, 1)
	16 0 (1, 1)
	18 ldc2_w (1, 1)
	19 2 (1, 1)
	21 lcmp (1, 1)
	22 ifge (1, 1)
	23 28 (1, 1)
	25 new (1, 1)
	26 org/apache/commons/math3/exception/NumberIsTooSmallException (1, 1)
	28 dup (1, 1)
	29 getstatic (1, 1)
	30 org/apache/commons/math3/exception/util/LocalizedFormats.INSUFFICIENT_DATA_FOR_T_STATISTIC:Lorg/apache/commons/math3/exception/util/LocalizedFormats; (1, 1)
	32 aload_1 (1, 1)
	33 invokeinterface (1, 1)
	34 org/apache/commons/math3/stat/descriptive/StatisticalSummary.homoscedasticT:(DDDDDD)D (1, 1)
	36 0 (1, 1)
	38 invokestatic (1, 1)
	39 java/lang/Long.valueOf:(J)Ljava/lang/Long; (1, 1)
	41 iconst_2 (1, 1)
	42 invokestatic (1, 1)
	43 java/lang/Integer.valueOf:(I)Ljava/lang/Integer; (1, 1)
	45 iconst_1 (1, 1)
	46 invokespecial (1, 1)
	47 org/apache/commons/math3/exception/NumberIsTooSmallException.<init>:(Lorg/apache/commons/math3/exception/util/Localizable;Ljava/lang/Number;Ljava/lang/Number;Z)V (1, 1)
	49 athrow (1, 1)
	50 return (0, 0)

