Method: <init>
	0 aload_0 (0, 0)
	1 invokespecial (0, 0)
	2 java/lang/Object.<init>:()V (0, 0)
	4 aload_0 (0, 0)
	5 new (0, 0)
	6 org/apache/commons/math3/stat/ranking/NaturalRanking (0, 0)
	8 dup (0, 0)
	9 aload_1 (0, 0)
	10 aload_2 (0, 0)
	11 invokespecial (0, 0)
	12 org/apache/commons/math3/stat/ranking/NaturalRanking.<init>:(Lorg/apache/commons/math3/stat/ranking/NaNStrategy;Lorg/apache/commons/math3/stat/ranking/TiesStrategy;)V (0, 0)
	14 putfield (0, 0)
	15 org/apache/commons/math3/stat/inference/WilcoxonSignedRankTest.naturalRanking:Lorg/apache/commons/math3/stat/ranking/NaturalRanking; (0, 0)
	17 return (0, 0)

Method: ensureDataConformance
	0 aload_1 (0, 1)
	1 ifnull (0, 1)
	2 7 (0, 1)
	4 aload_2 (0, 1)
	5 ifnonnull (0, 1)
	6 11 (0, 1)
	8 new (0, 1)
	9 org/apache/commons/math3/exception/NullArgumentException (0, 1)
	11 dup (0, 1)
	12 invokespecial (0, 1)
	13 org/apache/commons/math3/exception/NullArgumentException.<init>:()V (0, 1)
	15 athrow (0, 1)
	16 aload_1 (0, 1)
	17 arraylength (0, 1)
	18 ifeq (0, 1)
	19 8 (0, 1)
	21 aload_2 (0, 1)
	22 arraylength (0, 1)
	23 ifne (0, 1)
	24 11 (0, 1)
	26 new (0, 1)
	27 org/apache/commons/math3/exception/NoDataException (0, 1)
	29 dup (0, 1)
	30 invokespecial (0, 1)
	31 org/apache/commons/math3/exception/NoDataException.<init>:()V (0, 1)
	33 athrow (0, 1)
	34 aload_2 (1, 1)
	35 arraylength (1, 1)
	36 aload_1 (1, 1)
	37 arraylength (1, 1)
	38 if_icmpeq (1, 1)
	39 15 (1, 1)
	41 new (1, 1)
	42 org/apache/commons/math3/exception/DimensionMismatchException (1, 1)
	44 dup (1, 1)
	45 aload_2 (1, 1)
	46 arraylength (1, 1)
	47 aload_1 (1, 1)
	48 arraylength (1, 1)
	49 invokespecial (1, 1)
	50 org/apache/commons/math3/exception/DimensionMismatchException.<init>:(II)V (1, 1)
	52 athrow (1, 1)
	53 return (0, 1)

Method: calculateDifferences
	0 aload_1 (0, 0)
	1 arraylength (0, 0)
	2 newarray (0, 0)
	3 7 (0, 0)
	4 astore_3 (0, 0)
	5 iconst_0 (1, 4)
	6 istore (1, 4)
	7 #4 (1, 4)
	8 iload (1, 4)
	9 #4 (1, 4)
	10 aload_1 (1, 4)
	11 arraylength (1, 4)
	12 if_icmpge (1, 4)
	13 22 (1, 4)
	15 aload_3 (1, 4)
	16 iload (1, 4)
	17 #4 (1, 4)
	18 aload_2 (1, 4)
	19 iload (1, 4)
	20 #4 (1, 4)
	21 daload (1, 4)
	22 aload_1 (1, 4)
	23 iload (1, 4)
	24 #4 (1, 4)
	25 daload (1, 4)
	26 dsub (1, 4)
	27 dastore (1, 4)
	28 iinc (1, 4)
	29 #4 (1, 4)
	30 -89 (1, 4)
	31 goto (1, 4)
	32 -23 (1, 4)
	34 aload_3 (0, 0)
	35 areturn (0, 0)

Method: calculateAbsoluteDifferences
	0 aload_1 (1, 1)
	1 ifnonnull (1, 1)
	2 11 (1, 1)
	4 new (1, 1)
	5 org/apache/commons/math3/exception/NullArgumentException (1, 1)
	7 dup (1, 1)
	8 invokespecial (1, 1)
	9 org/apache/commons/math3/exception/NullArgumentException.<init>:()V (1, 1)
	11 athrow (1, 1)
	12 aload_1 (1, 1)
	13 arraylength (1, 1)
	14 ifne (1, 1)
	15 11 (1, 1)
	17 new (1, 1)
	18 org/apache/commons/math3/exception/NoDataException (1, 1)
	20 dup (1, 1)
	21 invokespecial (1, 1)
	22 org/apache/commons/math3/exception/NoDataException.<init>:()V (1, 1)
	24 athrow (1, 1)
	25 aload_1 (0, 0)
	26 arraylength (0, 0)
	27 newarray (0, 0)
	28 7 (0, 0)
	29 astore_2 (0, 0)
	30 iconst_0 (1, 4)
	31 istore_3 (1, 4)
	32 iload_3 (1, 4)
	33 aload_1 (1, 4)
	34 arraylength (1, 4)
	35 if_icmpge (1, 4)
	36 18 (1, 4)
	38 aload_2 (1, 4)
	39 iload_3 (1, 4)
	40 aload_1 (1, 4)
	41 iload_3 (1, 4)
	42 daload (1, 4)
	43 invokestatic (1, 4)
	44 org/apache/commons/math3/util/FastMath.abs:(D)D (1, 4)
	46 dastore (1, 4)
	47 iinc (1, 4)
	48 #3 (1, 4)
	49 -89 (1, 4)
	50 goto (1, 4)
	51 -18 (1, 4)
	53 aload_2 (0, 0)
	54 areturn (0, 0)

Method: wilcoxonSignedRank
	0 aload_0 (0, 4)
	1 aload_1 (0, 4)
	2 aload_2 (0, 4)
	3 invokespecial (0, 4)
	4 org/apache/commons/math3/stat/inference/WilcoxonSignedRankTest.ensureDataConformance:([D[D)V (0, 4)
	6 aload_0 (0, 1)
	7 aload_1 (0, 1)
	8 aload_2 (0, 1)
	9 invokespecial (0, 1)
	10 org/apache/commons/math3/stat/inference/WilcoxonSignedRankTest.calculateDifferences:([D[D)[D (0, 1)
	12 astore_3 (0, 1)
	13 aload_0 (0, 1)
	14 aload_3 (0, 1)
	15 invokespecial (0, 1)
	16 org/apache/commons/math3/stat/inference/WilcoxonSignedRankTest.calculateAbsoluteDifferences:([D)[D (0, 1)
	18 astore (0, 1)
	19 #4 (0, 1)
	20 aload_0 (0, 1)
	21 getfield (0, 1)
	22 org/apache/commons/math3/stat/inference/WilcoxonSignedRankTest.naturalRanking:Lorg/apache/commons/math3/stat/ranking/NaturalRanking; (0, 1)
	24 aload (0, 1)
	25 #4 (0, 1)
	26 invokevirtual (0, 1)
	27 org/apache/commons/math3/stat/ranking/NaturalRanking.rank:([D)[D (0, 1)
	29 astore (0, 1)
	30 #5 (0, 1)
	31 dconst_0 (0, 1)
	32 dstore (0, 1)
	33 #6 (0, 1)
	34 iconst_0 (1, 4)
	35 istore (1, 4)
	36 #8 (1, 4)
	37 iload (1, 4)
	38 #8 (1, 4)
	39 aload_3 (1, 4)
	40 arraylength (1, 4)
	41 if_icmpge (1, 4)
	42 28 (1, 4)
	44 aload_3 (2, 1)
	45 iload (2, 1)
	46 #8 (2, 1)
	47 daload (2, 1)
	48 dconst_0 (2, 1)
	49 dcmpl (2, 1)
	50 ifle (2, 1)
	51 13 (2, 1)
	53 dload (2, 1)
	54 #6 (2, 1)
	55 aload (2, 1)
	56 #5 (2, 1)
	57 iload (2, 1)
	58 #8 (2, 1)
	59 daload (2, 1)
	60 dadd (2, 1)
	61 dstore (2, 1)
	62 #6 (2, 1)
	63 iinc (2, 1)
	64 #8 (2, 1)
	65 -89 (2, 1)
	66 goto (2, 1)
	67 -29 (2, 1)
	69 aload_1 (1, 4)
	70 arraylength (1, 4)
	71 istore (1, 4)
	72 #8 (1, 4)
	73 iload (1, 4)
	74 #8 (1, 4)
	75 iload (1, 4)
	76 #8 (1, 4)
	77 iconst_1 (1, 4)
	78 iadd (1, 4)
	79 imul (1, 4)
	80 i2d (1, 4)
	81 ldc2_w (1, 4)
	82 2.0 (1, 4)
	84 ddiv (1, 4)
	85 dload (1, 4)
	86 #6 (1, 4)
	87 dsub (1, 4)
	88 dstore (1, 4)
	89 #9 (1, 4)
	90 dload (1, 4)
	91 #6 (1, 4)
	92 dload (1, 4)
	93 #9 (1, 4)
	94 invokestatic (1, 4)
	95 org/apache/commons/math3/util/FastMath.max:(DD)D (1, 4)
	97 dreturn (1, 4)

Method: calculateExactPValue
	0 iconst_1 (0, 0)
	1 iload_3 (0, 0)
	2 ishl (0, 0)
	3 istore (0, 0)
	4 #4 (0, 0)
	5 iconst_0 (0, 0)
	6 istore (0, 0)
	7 #5 (0, 0)
	8 iconst_0 (1, 4)
	9 istore (1, 4)
	10 #6 (1, 4)
	11 iload (1, 4)
	12 #6 (1, 4)
	13 iload (1, 4)
	14 #4 (1, 4)
	15 if_icmpge (1, 4)
	16 58 (1, 4)
	18 iconst_0 (1, 4)
	19 istore (1, 4)
	20 #7 (1, 4)
	21 iconst_0 (2, 4)
	22 istore (2, 4)
	23 #8 (2, 4)
	24 iload (2, 4)
	25 #8 (2, 4)
	26 iload_3 (2, 4)
	27 if_icmpge (2, 4)
	28 29 (2, 4)
	30 iload (3, 1)
	31 #6 (3, 1)
	32 iload (3, 1)
	33 #8 (3, 1)
	34 ishr (3, 1)
	35 iconst_1 (3, 1)
	36 iand (3, 1)
	37 iconst_1 (3, 1)
	38 if_icmpne (3, 1)
	39 12 (3, 1)
	41 iload (3, 1)
	42 #7 (3, 1)
	43 iload (3, 1)
	44 #8 (3, 1)
	45 iconst_1 (3, 1)
	46 iadd (3, 1)
	47 iadd (3, 1)
	48 istore (3, 1)
	49 #7 (3, 1)
	50 iinc (3, 1)
	51 #8 (3, 1)
	52 -89 (3, 1)
	53 goto (3, 1)
	54 -29 (3, 1)
	56 iload (3, 1)
	57 #7 (3, 1)
	58 i2d (3, 1)
	59 dload_1 (3, 1)
	60 dcmpl (3, 1)
	61 iflt (3, 1)
	62 6 (3, 1)
	64 iinc (3, 1)
	65 #5 (3, 1)
	66 -124 (3, 1)
	67 iinc (3, 1)
	68 #6 (3, 1)
	69 -89 (3, 1)
	70 goto (3, 1)
	71 -59 (3, 1)
	73 ldc2_w (2, 4)
	74 2.0 (2, 4)
	76 iload (2, 4)
	77 #5 (2, 4)
	78 i2d (2, 4)
	79 dmul (2, 4)
	80 iload (2, 4)
	81 #4 (2, 4)
	82 i2d (2, 4)
	83 ddiv (2, 4)
	84 dreturn (2, 4)

Method: calculateAsymptoticPValue
	0 iload_3 (0, 0)
	1 iload_3 (0, 0)
	2 iconst_1 (0, 0)
	3 iadd (0, 0)
	4 imul (0, 0)
	5 i2d (0, 0)
	6 ldc2_w (0, 0)
	7 4.0 (0, 0)
	9 ddiv (0, 0)
	10 dstore (0, 0)
	11 #4 (0, 0)
	12 dload (0, 0)
	13 #4 (0, 0)
	14 iconst_2 (0, 0)
	15 iload_3 (0, 0)
	16 imul (0, 0)
	17 iconst_1 (0, 0)
	18 iadd (0, 0)
	19 i2d (0, 0)
	20 ldc2_w (0, 0)
	21 6.0 (0, 0)
	23 ddiv (0, 0)
	24 dmul (0, 0)
	25 dstore (0, 0)
	26 #6 (0, 0)
	27 dload_1 (0, 0)
	28 dload (0, 0)
	29 #4 (0, 0)
	30 dsub (0, 0)
	31 ldc2_w (0, 0)
	32 0.5 (0, 0)
	34 dsub (0, 0)
	35 dload (0, 0)
	36 #6 (0, 0)
	37 invokestatic (0, 0)
	38 org/apache/commons/math3/util/FastMath.sqrt:(D)D (0, 0)
	40 ddiv (0, 0)
	41 dstore (0, 0)
	42 #8 (0, 0)
	43 new (0, 0)
	44 org/apache/commons/math3/distribution/NormalDistribution (0, 0)
	46 dup (0, 0)
	47 aconst_null (0, 0)
	48 dconst_0 (0, 0)
	49 dconst_1 (0, 0)
	50 invokespecial (0, 0)
	51 org/apache/commons/math3/distribution/NormalDistribution.<init>:(Lorg/apache/commons/math3/random/RandomGenerator;DD)V (0, 0)
	53 astore (0, 0)
	54 #10 (0, 0)
	55 ldc2_w (0, 0)
	56 2.0 (0, 0)
	58 aload (0, 0)
	59 #10 (0, 0)
	60 dload (0, 0)
	61 #8 (0, 0)
	62 invokevirtual (0, 0)
	63 org/apache/commons/math3/distribution/NormalDistribution.cumulativeProbability:(D)D (0, 0)
	65 dmul (0, 0)
	66 dreturn (0, 0)

Method: wilcoxonSignedRankTest
	0 aload_0 (0, 4)
	1 aload_1 (0, 4)
	2 aload_2 (0, 4)
	3 invokespecial (0, 4)
	4 org/apache/commons/math3/stat/inference/WilcoxonSignedRankTest.ensureDataConformance:([D[D)V (0, 4)
	6 aload_1 (0, 4)
	7 arraylength (0, 4)
	8 istore (0, 4)
	9 #4 (0, 4)
	10 aload_0 (0, 4)
	11 aload_1 (0, 4)
	12 aload_2 (0, 4)
	13 invokevirtual (0, 4)
	14 org/apache/commons/math3/stat/inference/WilcoxonSignedRankTest.wilcoxonSignedRank:([D[D)D (0, 4)
	16 dstore (0, 4)
	17 #5 (0, 4)
	18 iload_3 (1, 1)
	19 ifeq (1, 1)
	20 29 (1, 1)
	22 iload (1, 1)
	23 #4 (1, 1)
	24 bipush (1, 1)
	25 30 (1, 1)
	26 if_icmple (1, 1)
	27 22 (1, 1)
	29 new (1, 1)
	30 org/apache/commons/math3/exception/NumberIsTooLargeException (1, 1)
	32 dup (1, 1)
	33 iload (1, 1)
	34 #4 (1, 1)
	35 invokestatic (1, 1)
	36 java/lang/Integer.valueOf:(I)Ljava/lang/Integer; (1, 1)
	38 bipush (1, 1)
	39 30 (1, 1)
	40 invokestatic (1, 1)
	41 java/lang/Integer.valueOf:(I)Ljava/lang/Integer; (1, 1)
	43 iconst_1 (1, 1)
	44 invokespecial (1, 1)
	45 org/apache/commons/math3/exception/NumberIsTooLargeException.<init>:(Ljava/lang/Number;Ljava/lang/Number;Z)V (1, 1)
	47 athrow (1, 1)
	48 iload_3 (1, 1)
	49 ifeq (1, 1)
	50 12 (1, 1)
	52 aload_0 (1, 1)
	53 dload (1, 1)
	54 #5 (1, 1)
	55 iload (1, 1)
	56 #4 (1, 1)
	57 invokespecial (1, 1)
	58 org/apache/commons/math3/stat/inference/WilcoxonSignedRankTest.calculateExactPValue:(DI)D (1, 1)
	60 dreturn (1, 1)
	61 iload (1, 2)
	62 #4 (1, 2)
	63 iload (1, 2)
	64 #4 (1, 2)
	65 iconst_1 (1, 2)
	66 iadd (1, 2)
	67 imul (1, 2)
	68 i2d (1, 2)
	69 ldc2_w (1, 2)
	70 2.0 (1, 2)
	72 ddiv (1, 2)
	73 dload (1, 2)
	74 #5 (1, 2)
	75 dsub (1, 2)
	76 dstore (1, 2)
	77 #7 (1, 2)
	78 aload_0 (1, 2)
	79 dload (1, 2)
	80 #7 (1, 2)
	81 iload (1, 2)
	82 #4 (1, 2)
	83 invokespecial (1, 2)
	84 org/apache/commons/math3/stat/inference/WilcoxonSignedRankTest.calculateAsymptoticPValue:(DI)D (1, 2)
	86 dreturn (1, 2)

