Method: values
	0 getstatic (0, 0)
	3 invokevirtual (0, 0)
	6 checkcast (0, 0)
	9 areturn (0, 0)

Method: valueOf
	0 ldc (0, 0)
	2 aload_0 (0, 0)
	3 invokestatic (0, 0)
	6 checkcast (0, 0)
	9 areturn (0, 0)

Method: <init>
	0 aload_0 (0, 0)
	1 aload_1 (0, 0)
	2 iload_2 (0, 0)
	3 invokespecial (0, 0)
	6 aload_0 (0, 0)
	7 aload_3 (0, 0)
	8 putfield (0, 0)
	11 return (0, 0)

Method: getSourceString
	0 aload_0 (0, 0)
	1 getfield (0, 0)
	4 areturn (0, 0)

Method: getLocalizedString
	0 ldc (0, 0)
	2 invokevirtual (0, 0)
	5 ldc (0, 0)
	7 ldc (0, 0)
	9 invokevirtual (0, 0)
	12 astore_2 (0, 0)
	13 new (0, 0)
	16 dup (0, 0)
	17 invokespecial (0, 0)
	20 ldc (0, 0)
	22 invokevirtual (0, 0)
	25 aload_2 (0, 0)
	26 invokevirtual (0, 0)
	29 invokevirtual (0, 0)
	32 aload_1 (0, 0)
	33 invokestatic (0, 0)
	36 astore_3 (0, 0)
	37 aload_3 (1, 1)
	38 invokevirtual (1, 1)
	41 invokevirtual (1, 1)
	44 aload_1 (1, 1)
	45 invokevirtual (1, 1)
	48 invokevirtual (1, 1)
	51 ifeq (1, 1)
	54 aload_3 (1, 4)
	55 aload_0 (1, 4)
	56 invokevirtual (1, 4)
	59 invokevirtual (1, 4)
	62 areturn (1, 4)
	63 goto (-1, 0)
	66 astore_2 (-1, 0)
	67 aload_0 (-1, 4)
	68 getfield (-1, 4)
	71 areturn (0, 4)

Method: <clinit>
	0 new (0, 0)
	3 dup (0, 0)
	4 ldc (0, 0)
	6 iconst_0 (0, 0)
	7 ldc (0, 0)
	9 invokespecial (0, 0)
	12 putstatic (0, 0)
	15 new (0, 0)
	18 dup (0, 0)
	19 ldc (0, 0)
	21 iconst_1 (0, 0)
	22 ldc (0, 0)
	24 invokespecial (0, 0)
	27 putstatic (0, 0)
	30 new (0, 1)
	33 dup (0, 1)
	34 ldc (0, 1)
	36 iconst_2 (0, 1)
	37 ldc (0, 1)
	39 invokespecial (0, 1)
	42 putstatic (0, 1)
	45 new (0, 1)
	48 dup (0, 1)
	49 ldc (0, 1)
	51 iconst_3 (0, 1)
	52 ldc (0, 1)
	54 invokespecial (0, 1)
	57 putstatic (0, 1)
	60 new (0, 1)
	63 dup (0, 1)
	64 ldc (0, 1)
	66 iconst_4 (0, 1)
	67 ldc (0, 1)
	69 invokespecial (0, 1)
	72 putstatic (0, 1)
	75 new (0, 1)
	78 dup (0, 1)
	79 ldc (0, 1)
	81 iconst_5 (0, 1)
	82 ldc (0, 1)
	84 invokespecial (0, 1)
	87 putstatic (0, 1)
	90 new (0, 1)
	93 dup (0, 1)
	94 ldc (0, 1)
	96 bipush (0, 1)
	98 ldc (0, 1)
	100 invokespecial (0, 1)
	103 putstatic (0, 1)
	106 new (0, 1)
	109 dup (0, 1)
	110 ldc (0, 1)
	112 bipush (0, 1)
	114 ldc (0, 1)
	116 invokespecial (0, 1)
	119 putstatic (0, 1)
	122 new (0, 4)
	125 dup (0, 4)
	126 ldc (0, 4)
	128 bipush (0, 4)
	130 ldc (0, 4)
	132 invokespecial (0, 4)
	135 putstatic (0, 4)
	138 new (0, 4)
	141 dup (0, 4)
	142 ldc (0, 4)
	144 bipush (0, 4)
	146 ldc (0, 4)
	148 invokespecial (0, 4)
	151 putstatic (0, 4)
	154 new (0, 4)
	157 dup (0, 4)
	158 ldc (0, 4)
	160 bipush (0, 4)
	162 ldc (0, 4)
	164 invokespecial (0, 4)
	167 putstatic (0, 4)
	170 new (0, 4)
	173 dup (0, 4)
	174 ldc (0, 4)
	176 bipush (0, 4)
	178 ldc (0, 4)
	180 invokespecial (0, 4)
	183 putstatic (0, 4)
	186 new (0, 4)
	189 dup (0, 4)
	190 ldc (0, 4)
	192 bipush (0, 4)
	194 ldc (0, 4)
	196 invokespecial (0, 4)
	199 putstatic (0, 4)
	202 new (0, 4)
	205 dup (0, 4)
	206 ldc (0, 4)
	208 bipush (0, 4)
	210 ldc (0, 4)
	212 invokespecial (0, 4)
	215 putstatic (0, 4)
	218 new (0, 4)
	221 dup (0, 4)
	222 ldc (0, 4)
	224 bipush (0, 4)
	226 ldc (0, 4)
	228 invokespecial (0, 4)
	231 putstatic (0, 4)
	234 new (0, 4)
	237 dup (0, 4)
	238 ldc (0, 4)
	240 bipush (0, 4)
	242 ldc (0, 4)
	244 invokespecial (0, 4)
	247 putstatic (0, 4)
	250 new (0, 4)
	253 dup (0, 4)
	254 ldc (0, 4)
	256 bipush (0, 4)
	258 ldc (0, 4)
	260 invokespecial (0, 4)
	263 putstatic (0, 4)
	266 new (0, 4)
	269 dup (0, 4)
	270 ldc (0, 4)
	272 bipush (0, 4)
	274 ldc (0, 4)
	276 invokespecial (0, 4)
	279 putstatic (0, 4)
	282 new (0, 4)
	285 dup (0, 4)
	286 ldc (0, 4)
	288 bipush (0, 4)
	290 ldc (0, 4)
	292 invokespecial (0, 4)
	295 putstatic (0, 4)
	298 new (0, 4)
	301 dup (0, 4)
	302 ldc (0, 4)
	304 bipush (0, 4)
	306 ldc (0, 4)
	308 invokespecial (0, 4)
	311 putstatic (0, 4)
	314 new (0, 4)
	317 dup (0, 4)
	318 ldc (0, 4)
	320 bipush (0, 4)
	322 ldc (0, 4)
	324 invokespecial (0, 4)
	327 putstatic (0, 4)
	330 new (0, 4)
	333 dup (0, 4)
	334 ldc (0, 4)
	336 bipush (0, 4)
	338 ldc (0, 4)
	340 invokespecial (0, 4)
	343 putstatic (0, 4)
	346 new (0, 4)
	349 dup (0, 4)
	350 ldc (0, 4)
	352 bipush (0, 4)
	354 ldc (0, 4)
	356 invokespecial (0, 4)
	359 putstatic (0, 4)
	362 new (0, 4)
	365 dup (0, 4)
	366 ldc (0, 4)
	368 bipush (0, 4)
	370 ldc (0, 4)
	372 invokespecial (0, 4)
	375 putstatic (0, 4)
	378 new (0, 4)
	381 dup (0, 4)
	382 ldc (0, 4)
	384 bipush (0, 4)
	386 ldc (0, 4)
	388 invokespecial (0, 4)
	391 putstatic (0, 4)
	394 new (0, 4)
	397 dup (0, 4)
	398 ldc (0, 4)
	400 bipush (0, 4)
	402 ldc (0, 4)
	404 invokespecial (0, 4)
	407 putstatic (0, 4)
	410 new (0, 4)
	413 dup (0, 4)
	414 ldc (0, 4)
	416 bipush (0, 4)
	418 ldc (0, 4)
	420 invokespecial (0, 4)
	423 putstatic (0, 4)
	426 new (0, 4)
	429 dup (0, 4)
	430 ldc (0, 4)
	432 bipush (0, 4)
	434 ldc (0, 4)
	436 invokespecial (0, 4)
	439 putstatic (0, 4)
	442 new (0, 4)
	445 dup (0, 4)
	446 ldc (0, 4)
	448 bipush (0, 4)
	450 ldc (0, 4)
	452 invokespecial (0, 4)
	455 putstatic (0, 4)
	458 new (0, 4)
	461 dup (0, 4)
	462 ldc (0, 4)
	464 bipush (0, 4)
	466 ldc (0, 4)
	468 invokespecial (0, 4)
	471 putstatic (0, 4)
	474 new (0, 4)
	477 dup (0, 4)
	478 ldc (0, 4)
	480 bipush (0, 4)
	482 ldc (0, 4)
	484 invokespecial (0, 4)
	487 putstatic (0, 4)
	490 new (0, 4)
	493 dup (0, 4)
	494 ldc (0, 4)
	496 bipush (0, 4)
	498 ldc (0, 4)
	500 invokespecial (0, 4)
	503 putstatic (0, 4)
	506 new (0, 4)
	509 dup (0, 4)
	510 ldc (0, 4)
	512 bipush (0, 4)
	514 ldc (0, 4)
	516 invokespecial (0, 4)
	519 putstatic (0, 4)
	522 new (0, 4)
	525 dup (0, 4)
	526 ldc (0, 4)
	528 bipush (0, 4)
	530 ldc (0, 4)
	532 invokespecial (0, 4)
	535 putstatic (0, 4)
	538 new (0, 4)
	541 dup (0, 4)
	542 ldc (0, 4)
	544 bipush (0, 4)
	546 ldc (0, 4)
	548 invokespecial (0, 4)
	551 putstatic (0, 4)
	554 new (0, 4)
	557 dup (0, 4)
	558 ldc (0, 4)
	560 bipush (0, 4)
	562 ldc (0, 4)
	564 invokespecial (0, 4)
	567 putstatic (0, 4)
	570 new (0, 4)
	573 dup (0, 4)
	574 ldc (0, 4)
	576 bipush (0, 4)
	578 ldc (0, 4)
	580 invokespecial (0, 4)
	583 putstatic (0, 4)
	586 new (0, 4)
	589 dup (0, 4)
	590 ldc (0, 4)
	592 bipush (0, 4)
	594 ldc (0, 4)
	596 invokespecial (0, 4)
	599 putstatic (0, 4)
	602 new (0, 4)
	605 dup (0, 4)
	606 ldc (0, 4)
	608 bipush (0, 4)
	610 ldc (0, 4)
	612 invokespecial (0, 4)
	615 putstatic (0, 4)
	618 new (0, 4)
	621 dup (0, 4)
	622 ldc (0, 4)
	624 bipush (0, 4)
	626 ldc (0, 4)
	628 invokespecial (0, 4)
	631 putstatic (0, 4)
	634 new (0, 4)
	637 dup (0, 4)
	638 ldc (0, 4)
	640 bipush (0, 4)
	642 ldc (0, 4)
	644 invokespecial (0, 4)
	647 putstatic (0, 4)
	650 new (0, 4)
	653 dup (0, 4)
	654 ldc (0, 4)
	656 bipush (0, 4)
	658 ldc (0, 4)
	660 invokespecial (0, 4)
	663 putstatic (0, 4)
	666 new (0, 4)
	669 dup (0, 4)
	670 ldc (0, 4)
	672 bipush (0, 4)
	674 ldc (0, 4)
	676 invokespecial (0, 4)
	679 putstatic (0, 4)
	682 new (0, 3)
	685 dup (0, 3)
	686 ldc (0, 3)
	688 bipush (0, 3)
	690 ldc (0, 3)
	692 invokespecial (0, 3)
	695 putstatic (0, 3)
	698 new (0, 3)
	701 dup (0, 3)
	702 ldc (0, 3)
	704 bipush (0, 3)
	706 ldc (0, 3)
	708 invokespecial (0, 3)
	711 putstatic (0, 3)
	714 new (0, 3)
	717 dup (0, 3)
	718 ldc (0, 3)
	720 bipush (0, 3)
	722 ldc (0, 3)
	724 invokespecial (0, 3)
	727 putstatic (0, 3)
	730 new (0, 3)
	733 dup (0, 3)
	734 ldc (0, 3)
	736 bipush (0, 3)
	738 ldc (0, 3)
	740 invokespecial (0, 3)
	743 putstatic (0, 3)
	746 new (0, 3)
	749 dup (0, 3)
	750 ldc (0, 3)
	752 bipush (0, 3)
	754 ldc (0, 3)
	756 invokespecial (0, 3)
	759 putstatic (0, 3)
	762 new (0, 3)
	765 dup (0, 3)
	766 ldc (0, 3)
	768 bipush (0, 3)
	770 ldc (0, 3)
	772 invokespecial (0, 3)
	775 putstatic (0, 3)
	778 new (0, 4)
	781 dup (0, 4)
	782 ldc (0, 4)
	784 bipush (0, 4)
	786 ldc (0, 4)
	788 invokespecial (0, 4)
	791 putstatic (0, 4)
	794 new (0, 4)
	797 dup (0, 4)
	798 ldc (0, 4)
	800 bipush (0, 4)
	802 ldc (0, 4)
	804 invokespecial (0, 4)
	807 putstatic (0, 4)
	810 new (0, 4)
	813 dup (0, 4)
	814 ldc (0, 4)
	816 bipush (0, 4)
	818 ldc (0, 4)
	820 invokespecial (0, 4)
	823 putstatic (0, 4)
	826 new (0, 4)
	829 dup (0, 4)
	830 ldc (0, 4)
	832 bipush (0, 4)
	834 ldc (0, 4)
	836 invokespecial (0, 4)
	839 putstatic (0, 4)
	842 new (0, 4)
	845 dup (0, 4)
	846 ldc (0, 4)
	848 bipush (0, 4)
	850 ldc (0, 4)
	852 invokespecial (0, 4)
	855 putstatic (0, 4)
	858 new (0, 4)
	861 dup (0, 4)
	862 ldc (0, 4)
	864 bipush (0, 4)
	866 ldc (0, 4)
	868 invokespecial (0, 4)
	871 putstatic (0, 4)
	874 new (0, 4)
	877 dup (0, 4)
	878 ldc (0, 4)
	880 bipush (0, 4)
	882 ldc (0, 4)
	884 invokespecial (0, 4)
	887 putstatic (0, 4)
	890 new (0, 4)
	893 dup (0, 4)
	894 ldc (0, 4)
	896 bipush (0, 4)
	898 ldc (0, 4)
	900 invokespecial (0, 4)
	903 putstatic (0, 4)
	906 new (0, 4)
	909 dup (0, 4)
	910 ldc (0, 4)
	912 bipush (0, 4)
	914 ldc (0, 4)
	916 invokespecial (0, 4)
	919 putstatic (0, 4)
	922 new (0, 4)
	925 dup (0, 4)
	926 ldc (0, 4)
	928 bipush (0, 4)
	930 ldc (0, 4)
	932 invokespecial (0, 4)
	935 putstatic (0, 4)
	938 new (0, 4)
	941 dup (0, 4)
	942 ldc (0, 4)
	944 bipush (0, 4)
	946 ldc (0, 4)
	948 invokespecial (0, 4)
	951 putstatic (0, 4)
	954 new (0, 1)
	957 dup (0, 1)
	958 ldc (0, 1)
	960 bipush (0, 1)
	962 ldc (0, 1)
	964 invokespecial (0, 1)
	967 putstatic (0, 1)
	970 new (0, 1)
	973 dup (0, 1)
	974 ldc (0, 1)
	976 bipush (0, 1)
	978 ldc (0, 1)
	980 invokespecial (0, 1)
	983 putstatic (0, 1)
	986 new (0, 1)
	989 dup (0, 1)
	990 ldc (0, 1)
	992 bipush (0, 1)
	994 ldc (0, 1)
	996 invokespecial (0, 1)
	999 putstatic (0, 1)
	1002 new (0, 1)
	1005 dup (0, 1)
	1006 ldc (0, 1)
	1008 bipush (0, 1)
	1010 ldc (0, 1)
	1012 invokespecial (0, 1)
	1015 putstatic (0, 1)
	1018 new (0, 1)
	1021 dup (0, 1)
	1022 ldc (0, 1)
	1024 bipush (0, 1)
	1026 ldc (0, 1)
	1028 invokespecial (0, 1)
	1031 putstatic (0, 1)
	1034 new (0, 1)
	1037 dup (0, 1)
	1038 ldc (0, 1)
	1040 bipush (0, 1)
	1042 ldc (0, 1)
	1044 invokespecial (0, 1)
	1047 putstatic (0, 1)
	1050 new (0, 4)
	1053 dup (0, 4)
	1054 ldc (0, 4)
	1056 bipush (0, 4)
	1058 ldc (0, 4)
	1060 invokespecial (0, 4)
	1063 putstatic (0, 4)
	1066 new (0, 4)
	1069 dup (0, 4)
	1070 ldc (0, 4)
	1072 bipush (0, 4)
	1074 ldc (0, 4)
	1076 invokespecial (0, 4)
	1079 putstatic (0, 4)
	1082 new (0, 4)
	1085 dup (0, 4)
	1086 ldc (0, 4)
	1088 bipush (0, 4)
	1090 ldc (0, 4)
	1092 invokespecial (0, 4)
	1095 putstatic (0, 4)
	1098 new (0, 4)
	1101 dup (0, 4)
	1102 ldc (0, 4)
	1104 bipush (0, 4)
	1106 ldc (0, 4)
	1108 invokespecial (0, 4)
	1111 putstatic (0, 4)
	1114 new (0, 4)
	1117 dup (0, 4)
	1118 ldc (0, 4)
	1120 bipush (0, 4)
	1122 ldc (0, 4)
	1124 invokespecial (0, 4)
	1127 putstatic (0, 4)
	1130 new (0, 4)
	1133 dup (0, 4)
	1134 ldc (0, 4)
	1136 bipush (0, 4)
	1138 ldc (0, 4)
	1140 invokespecial (0, 4)
	1143 putstatic (0, 4)
	1146 new (0, 4)
	1149 dup (0, 4)
	1150 ldc (0, 4)
	1152 bipush (0, 4)
	1154 ldc (0, 4)
	1156 invokespecial (0, 4)
	1159 putstatic (0, 4)
	1162 new (0, 1)
	1165 dup (0, 1)
	1166 ldc (0, 1)
	1168 bipush (0, 1)
	1170 ldc (0, 1)
	1172 invokespecial (0, 1)
	1175 putstatic (0, 1)
	1178 new (0, 1)
	1181 dup (0, 1)
	1182 ldc (0, 1)
	1184 bipush (0, 1)
	1186 ldc (0, 1)
	1188 invokespecial (0, 1)
	1191 putstatic (0, 1)
	1194 new (0, 1)
	1197 dup (0, 1)
	1198 ldc (0, 1)
	1200 bipush (0, 1)
	1202 ldc (0, 1)
	1204 invokespecial (0, 1)
	1207 putstatic (0, 1)
	1210 new (0, 1)
	1213 dup (0, 1)
	1214 ldc (0, 1)
	1216 bipush (0, 1)
	1218 ldc (0, 1)
	1220 invokespecial (0, 1)
	1223 putstatic (0, 1)
	1226 new (0, 1)
	1229 dup (0, 1)
	1230 ldc_w (0, 1)
	1233 bipush (0, 1)
	1235 ldc_w (0, 1)
	1238 invokespecial (0, 1)
	1241 putstatic (0, 1)
	1244 new (0, 1)
	1247 dup (0, 1)
	1248 ldc_w (0, 1)
	1251 bipush (0, 1)
	1253 ldc_w (0, 1)
	1256 invokespecial (0, 1)
	1259 putstatic (0, 1)
	1262 new (0, 1)
	1265 dup (0, 1)
	1266 ldc_w (0, 1)
	1269 bipush (0, 1)
	1271 ldc_w (0, 1)
	1274 invokespecial (0, 1)
	1277 putstatic (0, 1)
	1280 new (0, 1)
	1283 dup (0, 1)
	1284 ldc_w (0, 1)
	1287 bipush (0, 1)
	1289 ldc_w (0, 1)
	1292 invokespecial (0, 1)
	1295 putstatic (0, 1)
	1298 new (0, 1)
	1301 dup (0, 1)
	1302 ldc_w (0, 1)
	1305 bipush (0, 1)
	1307 ldc_w (0, 1)
	1310 invokespecial (0, 1)
	1313 putstatic (0, 1)
	1316 new (0, 1)
	1319 dup (0, 1)
	1320 ldc_w (0, 1)
	1323 bipush (0, 1)
	1325 ldc_w (0, 1)
	1328 invokespecial (0, 1)
	1331 putstatic (0, 1)
	1334 new (0, 1)
	1337 dup (0, 1)
	1338 ldc_w (0, 1)
	1341 bipush (0, 1)
	1343 ldc_w (0, 1)
	1346 invokespecial (0, 1)
	1349 putstatic (0, 1)
	1352 new (0, 1)
	1355 dup (0, 1)
	1356 ldc_w (0, 1)
	1359 bipush (0, 1)
	1361 ldc_w (0, 1)
	1364 invokespecial (0, 1)
	1367 putstatic (0, 1)
	1370 new (0, 1)
	1373 dup (0, 1)
	1374 ldc_w (0, 1)
	1377 bipush (0, 1)
	1379 ldc_w (0, 1)
	1382 invokespecial (0, 1)
	1385 putstatic (0, 1)
	1388 new (0, 1)
	1391 dup (0, 1)
	1392 ldc_w (0, 1)
	1395 bipush (0, 1)
	1397 ldc_w (0, 1)
	1400 invokespecial (0, 1)
	1403 putstatic (0, 1)
	1406 new (0, 1)
	1409 dup (0, 1)
	1410 ldc_w (0, 1)
	1413 bipush (0, 1)
	1415 ldc_w (0, 1)
	1418 invokespecial (0, 1)
	1421 putstatic (0, 1)
	1424 new (0, 1)
	1427 dup (0, 1)
	1428 ldc_w (0, 1)
	1431 bipush (0, 1)
	1433 ldc_w (0, 1)
	1436 invokespecial (0, 1)
	1439 putstatic (0, 1)
	1442 new (0, 1)
	1445 dup (0, 1)
	1446 ldc_w (0, 1)
	1449 bipush (0, 1)
	1451 ldc_w (0, 1)
	1454 invokespecial (0, 1)
	1457 putstatic (0, 1)
	1460 new (0, 1)
	1463 dup (0, 1)
	1464 ldc_w (0, 1)
	1467 bipush (0, 1)
	1469 ldc_w (0, 1)
	1472 invokespecial (0, 1)
	1475 putstatic (0, 1)
	1478 new (0, 1)
	1481 dup (0, 1)
	1482 ldc_w (0, 1)
	1485 bipush (0, 1)
	1487 ldc_w (0, 1)
	1490 invokespecial (0, 1)
	1493 putstatic (0, 1)
	1496 new (0, 1)
	1499 dup (0, 1)
	1500 ldc_w (0, 1)
	1503 bipush (0, 1)
	1505 ldc_w (0, 1)
	1508 invokespecial (0, 1)
	1511 putstatic (0, 1)
	1514 new (0, 1)
	1517 dup (0, 1)
	1518 ldc_w (0, 1)
	1521 bipush (0, 1)
	1523 ldc_w (0, 1)
	1526 invokespecial (0, 1)
	1529 putstatic (0, 1)
	1532 new (0, 1)
	1535 dup (0, 1)
	1536 ldc_w (0, 1)
	1539 bipush (0, 1)
	1541 ldc_w (0, 1)
	1544 invokespecial (0, 1)
	1547 putstatic (0, 1)
	1550 new (0, 4)
	1553 dup (0, 4)
	1554 ldc_w (0, 4)
	1557 bipush (0, 4)
	1559 ldc_w (0, 4)
	1562 invokespecial (0, 4)
	1565 putstatic (0, 4)
	1568 new (0, 4)
	1571 dup (0, 4)
	1572 ldc_w (0, 4)
	1575 bipush (0, 4)
	1577 ldc_w (0, 4)
	1580 invokespecial (0, 4)
	1583 putstatic (0, 4)
	1586 new (0, 4)
	1589 dup (0, 4)
	1590 ldc_w (0, 4)
	1593 bipush (0, 4)
	1595 ldc_w (0, 4)
	1598 invokespecial (0, 4)
	1601 putstatic (0, 4)
	1604 new (0, 4)
	1607 dup (0, 4)
	1608 ldc_w (0, 4)
	1611 bipush (0, 4)
	1613 ldc_w (0, 4)
	1616 invokespecial (0, 4)
	1619 putstatic (0, 4)
	1622 new (0, 4)
	1625 dup (0, 4)
	1626 ldc_w (0, 4)
	1629 bipush (0, 4)
	1631 ldc_w (0, 4)
	1634 invokespecial (0, 4)
	1637 putstatic (0, 4)
	1640 new (0, 4)
	1643 dup (0, 4)
	1644 ldc_w (0, 4)
	1647 bipush (0, 4)
	1649 ldc_w (0, 4)
	1652 invokespecial (0, 4)
	1655 putstatic (0, 4)
	1658 new (0, 4)
	1661 dup (0, 4)
	1662 ldc_w (0, 4)
	1665 bipush (0, 4)
	1667 ldc_w (0, 4)
	1670 invokespecial (0, 4)
	1673 putstatic (0, 4)
	1676 new (0, 4)
	1679 dup (0, 4)
	1680 ldc_w (0, 4)
	1683 bipush (0, 4)
	1685 ldc_w (0, 4)
	1688 invokespecial (0, 4)
	1691 putstatic (0, 4)
	1694 new (0, 4)
	1697 dup (0, 4)
	1698 ldc_w (0, 4)
	1701 bipush (0, 4)
	1703 ldc_w (0, 4)
	1706 invokespecial (0, 4)
	1709 putstatic (0, 4)
	1712 new (0, 4)
	1715 dup (0, 4)
	1716 ldc_w (0, 4)
	1719 bipush (0, 4)
	1721 ldc_w (0, 4)
	1724 invokespecial (0, 4)
	1727 putstatic (0, 4)
	1730 new (0, 4)
	1733 dup (0, 4)
	1734 ldc_w (0, 4)
	1737 bipush (0, 4)
	1739 ldc_w (0, 4)
	1742 invokespecial (0, 4)
	1745 putstatic (0, 4)
	1748 new (0, 4)
	1751 dup (0, 4)
	1752 ldc_w (0, 4)
	1755 bipush (0, 4)
	1757 ldc_w (0, 4)
	1760 invokespecial (0, 4)
	1763 putstatic (0, 4)
	1766 new (0, 4)
	1769 dup (0, 4)
	1770 ldc_w (0, 4)
	1773 bipush (0, 4)
	1775 ldc_w (0, 4)
	1778 invokespecial (0, 4)
	1781 putstatic (0, 4)
	1784 new (0, 4)
	1787 dup (0, 4)
	1788 ldc_w (0, 4)
	1791 bipush (0, 4)
	1793 ldc_w (0, 4)
	1796 invokespecial (0, 4)
	1799 putstatic (0, 4)
	1802 new (0, 4)
	1805 dup (0, 4)
	1806 ldc_w (0, 4)
	1809 bipush (0, 4)
	1811 ldc_w (0, 4)
	1814 invokespecial (0, 4)
	1817 putstatic (0, 4)
	1820 new (0, 4)
	1823 dup (0, 4)
	1824 ldc_w (0, 4)
	1827 bipush (0, 4)
	1829 ldc_w (0, 4)
	1832 invokespecial (0, 4)
	1835 putstatic (0, 4)
	1838 new (0, 4)
	1841 dup (0, 4)
	1842 ldc_w (0, 4)
	1845 bipush (0, 4)
	1847 ldc_w (0, 4)
	1850 invokespecial (0, 4)
	1853 putstatic (0, 4)
	1856 new (0, 4)
	1859 dup (0, 4)
	1860 ldc_w (0, 4)
	1863 bipush (0, 4)
	1865 ldc_w (0, 4)
	1868 invokespecial (0, 4)
	1871 putstatic (0, 4)
	1874 new (0, 4)
	1877 dup (0, 4)
	1878 ldc_w (0, 4)
	1881 bipush (0, 4)
	1883 ldc_w (0, 4)
	1886 invokespecial (0, 4)
	1889 putstatic (0, 4)
	1892 new (0, 4)
	1895 dup (0, 4)
	1896 ldc_w (0, 4)
	1899 bipush (0, 4)
	1901 ldc_w (0, 4)
	1904 invokespecial (0, 4)
	1907 putstatic (0, 4)
	1910 new (0, 4)
	1913 dup (0, 4)
	1914 ldc_w (0, 4)
	1917 bipush (0, 4)
	1919 ldc_w (0, 4)
	1922 invokespecial (0, 4)
	1925 putstatic (0, 4)
	1928 new (0, 4)
	1931 dup (0, 4)
	1932 ldc_w (0, 4)
	1935 bipush (0, 4)
	1937 ldc_w (0, 4)
	1940 invokespecial (0, 4)
	1943 putstatic (0, 4)
	1946 new (0, 4)
	1949 dup (0, 4)
	1950 ldc_w (0, 4)
	1953 bipush (0, 4)
	1955 ldc_w (0, 4)
	1958 invokespecial (0, 4)
	1961 putstatic (0, 4)
	1964 new (0, 4)
	1967 dup (0, 4)
	1968 ldc_w (0, 4)
	1971 bipush (0, 4)
	1973 ldc_w (0, 4)
	1976 invokespecial (0, 4)
	1979 putstatic (0, 4)
	1982 new (0, 4)
	1985 dup (0, 4)
	1986 ldc_w (0, 4)
	1989 bipush (0, 4)
	1991 ldc_w (0, 4)
	1994 invokespecial (0, 4)
	1997 putstatic (0, 4)
	2000 new (0, 4)
	2003 dup (0, 4)
	2004 ldc_w (0, 4)
	2007 bipush (0, 4)
	2009 ldc_w (0, 4)
	2012 invokespecial (0, 4)
	2015 putstatic (0, 4)
	2018 new (0, 4)
	2021 dup (0, 4)
	2022 ldc_w (0, 4)
	2025 bipush (0, 4)
	2027 ldc_w (0, 4)
	2030 invokespecial (0, 4)
	2033 putstatic (0, 4)
	2036 new (0, 1)
	2039 dup (0, 1)
	2040 ldc_w (0, 1)
	2043 bipush (0, 1)
	2045 ldc_w (0, 1)
	2048 invokespecial (0, 1)
	2051 putstatic (0, 1)
	2054 new (0, 1)
	2057 dup (0, 1)
	2058 ldc_w (0, 1)
	2061 bipush (0, 1)
	2063 ldc_w (0, 1)
	2066 invokespecial (0, 1)
	2069 putstatic (0, 1)
	2072 new (0, 1)
	2075 dup (0, 1)
	2076 ldc_w (0, 1)
	2079 bipush (0, 1)
	2081 ldc_w (0, 1)
	2084 invokespecial (0, 1)
	2087 putstatic (0, 1)
	2090 new (0, 1)
	2093 dup (0, 1)
	2094 ldc_w (0, 1)
	2097 bipush (0, 1)
	2099 ldc_w (0, 1)
	2102 invokespecial (0, 1)
	2105 putstatic (0, 1)
	2108 new (0, 1)
	2111 dup (0, 1)
	2112 ldc_w (0, 1)
	2115 bipush (0, 1)
	2117 ldc_w (0, 1)
	2120 invokespecial (0, 1)
	2123 putstatic (0, 1)
	2126 new (0, 1)
	2129 dup (0, 1)
	2130 ldc_w (0, 1)
	2133 bipush (0, 1)
	2135 ldc_w (0, 1)
	2138 invokespecial (0, 1)
	2141 putstatic (0, 1)
	2144 new (0, 1)
	2147 dup (0, 1)
	2148 ldc_w (0, 1)
	2151 sipush (0, 1)
	2154 ldc_w (0, 1)
	2157 invokespecial (0, 1)
	2160 putstatic (0, 1)
	2163 new (0, 1)
	2166 dup (0, 1)
	2167 ldc_w (0, 1)
	2170 sipush (0, 1)
	2173 ldc_w (0, 1)
	2176 invokespecial (0, 1)
	2179 putstatic (0, 1)
	2182 new (0, 1)
	2185 dup (0, 1)
	2186 ldc_w (0, 1)
	2189 sipush (0, 1)
	2192 ldc_w (0, 1)
	2195 invokespecial (0, 1)
	2198 putstatic (0, 1)
	2201 new (0, 1)
	2204 dup (0, 1)
	2205 ldc_w (0, 1)
	2208 sipush (0, 1)
	2211 ldc_w (0, 1)
	2214 invokespecial (0, 1)
	2217 putstatic (0, 1)
	2220 new (0, 1)
	2223 dup (0, 1)
	2224 ldc_w (0, 1)
	2227 sipush (0, 1)
	2230 ldc_w (0, 1)
	2233 invokespecial (0, 1)
	2236 putstatic (0, 1)
	2239 new (0, 1)
	2242 dup (0, 1)
	2243 ldc_w (0, 1)
	2246 sipush (0, 1)
	2249 ldc_w (0, 1)
	2252 invokespecial (0, 1)
	2255 putstatic (0, 1)
	2258 new (0, 1)
	2261 dup (0, 1)
	2262 ldc_w (0, 1)
	2265 sipush (0, 1)
	2268 ldc_w (0, 1)
	2271 invokespecial (0, 1)
	2274 putstatic (0, 1)
	2277 new (0, 1)
	2280 dup (0, 1)
	2281 ldc_w (0, 1)
	2284 sipush (0, 1)
	2287 ldc_w (0, 1)
	2290 invokespecial (0, 1)
	2293 putstatic (0, 1)
	2296 new (0, 1)
	2299 dup (0, 1)
	2300 ldc_w (0, 1)
	2303 sipush (0, 1)
	2306 ldc_w (0, 1)
	2309 invokespecial (0, 1)
	2312 putstatic (0, 1)
	2315 new (0, 1)
	2318 dup (0, 1)
	2319 ldc_w (0, 1)
	2322 sipush (0, 1)
	2325 ldc_w (0, 1)
	2328 invokespecial (0, 1)
	2331 putstatic (0, 1)
	2334 new (0, 1)
	2337 dup (0, 1)
	2338 ldc_w (0, 1)
	2341 sipush (0, 1)
	2344 ldc_w (0, 1)
	2347 invokespecial (0, 1)
	2350 putstatic (0, 1)
	2353 new (0, 1)
	2356 dup (0, 1)
	2357 ldc_w (0, 1)
	2360 sipush (0, 1)
	2363 ldc_w (0, 1)
	2366 invokespecial (0, 1)
	2369 putstatic (0, 1)
	2372 new (0, 1)
	2375 dup (0, 1)
	2376 ldc_w (0, 1)
	2379 sipush (0, 1)
	2382 ldc_w (0, 1)
	2385 invokespecial (0, 1)
	2388 putstatic (0, 1)
	2391 new (0, 4)
	2394 dup (0, 4)
	2395 ldc_w (0, 4)
	2398 sipush (0, 4)
	2401 ldc_w (0, 4)
	2404 invokespecial (0, 4)
	2407 putstatic (0, 4)
	2410 new (0, 4)
	2413 dup (0, 4)
	2414 ldc_w (0, 4)
	2417 sipush (0, 4)
	2420 ldc_w (0, 4)
	2423 invokespecial (0, 4)
	2426 putstatic (0, 4)
	2429 new (0, 4)
	2432 dup (0, 4)
	2433 ldc_w (0, 4)
	2436 sipush (0, 4)
	2439 ldc_w (0, 4)
	2442 invokespecial (0, 4)
	2445 putstatic (0, 4)
	2448 new (0, 4)
	2451 dup (0, 4)
	2452 ldc_w (0, 4)
	2455 sipush (0, 4)
	2458 ldc_w (0, 4)
	2461 invokespecial (0, 4)
	2464 putstatic (0, 4)
	2467 new (0, 4)
	2470 dup (0, 4)
	2471 ldc_w (0, 4)
	2474 sipush (0, 4)
	2477 ldc_w (0, 4)
	2480 invokespecial (0, 4)
	2483 putstatic (0, 4)
	2486 new (0, 4)
	2489 dup (0, 4)
	2490 ldc_w (0, 4)
	2493 sipush (0, 4)
	2496 ldc_w (0, 4)
	2499 invokespecial (0, 4)
	2502 putstatic (0, 4)
	2505 new (0, 4)
	2508 dup (0, 4)
	2509 ldc_w (0, 4)
	2512 sipush (0, 4)
	2515 ldc_w (0, 4)
	2518 invokespecial (0, 4)
	2521 putstatic (0, 4)
	2524 new (0, 4)
	2527 dup (0, 4)
	2528 ldc_w (0, 4)
	2531 sipush (0, 4)
	2534 ldc_w (0, 4)
	2537 invokespecial (0, 4)
	2540 putstatic (0, 4)
	2543 new (0, 4)
	2546 dup (0, 4)
	2547 ldc_w (0, 4)
	2550 sipush (0, 4)
	2553 ldc_w (0, 4)
	2556 invokespecial (0, 4)
	2559 putstatic (0, 4)
	2562 new (0, 4)
	2565 dup (0, 4)
	2566 ldc_w (0, 4)
	2569 sipush (0, 4)
	2572 ldc_w (0, 4)
	2575 invokespecial (0, 4)
	2578 putstatic (0, 4)
	2581 new (0, 4)
	2584 dup (0, 4)
	2585 ldc_w (0, 4)
	2588 sipush (0, 4)
	2591 ldc_w (0, 4)
	2594 invokespecial (0, 4)
	2597 putstatic (0, 4)
	2600 new (0, 4)
	2603 dup (0, 4)
	2604 ldc_w (0, 4)
	2607 sipush (0, 4)
	2610 ldc_w (0, 4)
	2613 invokespecial (0, 4)
	2616 putstatic (0, 4)
	2619 new (0, 4)
	2622 dup (0, 4)
	2623 ldc_w (0, 4)
	2626 sipush (0, 4)
	2629 ldc_w (0, 4)
	2632 invokespecial (0, 4)
	2635 putstatic (0, 4)
	2638 new (0, 4)
	2641 dup (0, 4)
	2642 ldc_w (0, 4)
	2645 sipush (0, 4)
	2648 ldc_w (0, 4)
	2651 invokespecial (0, 4)
	2654 putstatic (0, 4)
	2657 new (0, 4)
	2660 dup (0, 4)
	2661 ldc_w (0, 4)
	2664 sipush (0, 4)
	2667 ldc_w (0, 4)
	2670 invokespecial (0, 4)
	2673 putstatic (0, 4)
	2676 new (0, 4)
	2679 dup (0, 4)
	2680 ldc_w (0, 4)
	2683 sipush (0, 4)
	2686 ldc_w (0, 4)
	2689 invokespecial (0, 4)
	2692 putstatic (0, 4)
	2695 new (0, 4)
	2698 dup (0, 4)
	2699 ldc_w (0, 4)
	2702 sipush (0, 4)
	2705 ldc_w (0, 4)
	2708 invokespecial (0, 4)
	2711 putstatic (0, 4)
	2714 new (0, 4)
	2717 dup (0, 4)
	2718 ldc_w (0, 4)
	2721 sipush (0, 4)
	2724 ldc_w (0, 4)
	2727 invokespecial (0, 4)
	2730 putstatic (0, 4)
	2733 new (0, 4)
	2736 dup (0, 4)
	2737 ldc_w (0, 4)
	2740 sipush (0, 4)
	2743 ldc_w (0, 4)
	2746 invokespecial (0, 4)
	2749 putstatic (0, 4)
	2752 new (0, 4)
	2755 dup (0, 4)
	2756 ldc_w (0, 4)
	2759 sipush (0, 4)
	2762 ldc_w (0, 4)
	2765 invokespecial (0, 4)
	2768 putstatic (0, 4)
	2771 new (0, 4)
	2774 dup (0, 4)
	2775 ldc_w (0, 4)
	2778 sipush (0, 4)
	2781 ldc_w (0, 4)
	2784 invokespecial (0, 4)
	2787 putstatic (0, 4)
	2790 new (0, 4)
	2793 dup (0, 4)
	2794 ldc_w (0, 4)
	2797 sipush (0, 4)
	2800 ldc_w (0, 4)
	2803 invokespecial (0, 4)
	2806 putstatic (0, 4)
	2809 new (0, 4)
	2812 dup (0, 4)
	2813 ldc_w (0, 4)
	2816 sipush (0, 4)
	2819 ldc_w (0, 4)
	2822 invokespecial (0, 4)
	2825 putstatic (0, 4)
	2828 new (0, 4)
	2831 dup (0, 4)
	2832 ldc_w (0, 4)
	2835 sipush (0, 4)
	2838 ldc_w (0, 4)
	2841 invokespecial (0, 4)
	2844 putstatic (0, 4)
	2847 new (0, 4)
	2850 dup (0, 4)
	2851 ldc_w (0, 4)
	2854 sipush (0, 4)
	2857 ldc_w (0, 4)
	2860 invokespecial (0, 4)
	2863 putstatic (0, 4)
	2866 new (0, 4)
	2869 dup (0, 4)
	2870 ldc_w (0, 4)
	2873 sipush (0, 4)
	2876 ldc_w (0, 4)
	2879 invokespecial (0, 4)
	2882 putstatic (0, 4)
	2885 new (0, 4)
	2888 dup (0, 4)
	2889 ldc_w (0, 4)
	2892 sipush (0, 4)
	2895 ldc_w (0, 4)
	2898 invokespecial (0, 4)
	2901 putstatic (0, 4)
	2904 new (0, 4)
	2907 dup (0, 4)
	2908 ldc_w (0, 4)
	2911 sipush (0, 4)
	2914 ldc_w (0, 4)
	2917 invokespecial (0, 4)
	2920 putstatic (0, 4)
	2923 new (0, 4)
	2926 dup (0, 4)
	2927 ldc_w (0, 4)
	2930 sipush (0, 4)
	2933 ldc_w (0, 4)
	2936 invokespecial (0, 4)
	2939 putstatic (0, 4)
	2942 new (0, 4)
	2945 dup (0, 4)
	2946 ldc_w (0, 4)
	2949 sipush (0, 4)
	2952 ldc_w (0, 4)
	2955 invokespecial (0, 4)
	2958 putstatic (0, 4)
	2961 new (0, 4)
	2964 dup (0, 4)
	2965 ldc_w (0, 4)
	2968 sipush (0, 4)
	2971 ldc_w (0, 4)
	2974 invokespecial (0, 4)
	2977 putstatic (0, 4)
	2980 new (0, 4)
	2983 dup (0, 4)
	2984 ldc_w (0, 4)
	2987 sipush (0, 4)
	2990 ldc_w (0, 4)
	2993 invokespecial (0, 4)
	2996 putstatic (0, 4)
	2999 new (0, 4)
	3002 dup (0, 4)
	3003 ldc_w (0, 4)
	3006 sipush (0, 4)
	3009 ldc_w (0, 4)
	3012 invokespecial (0, 4)
	3015 putstatic (0, 4)
	3018 new (0, 4)
	3021 dup (0, 4)
	3022 ldc_w (0, 4)
	3025 sipush (0, 4)
	3028 ldc_w (0, 4)
	3031 invokespecial (0, 4)
	3034 putstatic (0, 4)
	3037 new (0, 4)
	3040 dup (0, 4)
	3041 ldc_w (0, 4)
	3044 sipush (0, 4)
	3047 ldc_w (0, 4)
	3050 invokespecial (0, 4)
	3053 putstatic (0, 4)
	3056 new (0, 4)
	3059 dup (0, 4)
	3060 ldc_w (0, 4)
	3063 sipush (0, 4)
	3066 ldc_w (0, 4)
	3069 invokespecial (0, 4)
	3072 putstatic (0, 4)
	3075 new (0, 4)
	3078 dup (0, 4)
	3079 ldc_w (0, 4)
	3082 sipush (0, 4)
	3085 ldc_w (0, 4)
	3088 invokespecial (0, 4)
	3091 putstatic (0, 4)
	3094 new (0, 4)
	3097 dup (0, 4)
	3098 ldc_w (0, 4)
	3101 sipush (0, 4)
	3104 ldc_w (0, 4)
	3107 invokespecial (0, 4)
	3110 putstatic (0, 4)
	3113 new (0, 4)
	3116 dup (0, 4)
	3117 ldc_w (0, 4)
	3120 sipush (0, 4)
	3123 ldc_w (0, 4)
	3126 invokespecial (0, 4)
	3129 putstatic (0, 4)
	3132 new (0, 4)
	3135 dup (0, 4)
	3136 ldc_w (0, 4)
	3139 sipush (0, 4)
	3142 ldc_w (0, 4)
	3145 invokespecial (0, 4)
	3148 putstatic (0, 4)
	3151 new (0, 4)
	3154 dup (0, 4)
	3155 ldc_w (0, 4)
	3158 sipush (0, 4)
	3161 ldc_w (0, 4)
	3164 invokespecial (0, 4)
	3167 putstatic (0, 4)
	3170 new (0, 4)
	3173 dup (0, 4)
	3174 ldc_w (0, 4)
	3177 sipush (0, 4)
	3180 ldc_w (0, 4)
	3183 invokespecial (0, 4)
	3186 putstatic (0, 4)
	3189 new (0, 4)
	3192 dup (0, 4)
	3193 ldc_w (0, 4)
	3196 sipush (0, 4)
	3199 ldc_w (0, 4)
	3202 invokespecial (0, 4)
	3205 putstatic (0, 4)
	3208 new (0, 4)
	3211 dup (0, 4)
	3212 ldc_w (0, 4)
	3215 sipush (0, 4)
	3218 ldc_w (0, 4)
	3221 invokespecial (0, 4)
	3224 putstatic (0, 4)
	3227 new (0, 4)
	3230 dup (0, 4)
	3231 ldc_w (0, 4)
	3234 sipush (0, 4)
	3237 ldc_w (0, 4)
	3240 invokespecial (0, 4)
	3243 putstatic (0, 4)
	3246 new (0, 4)
	3249 dup (0, 4)
	3250 ldc_w (0, 4)
	3253 sipush (0, 4)
	3256 ldc_w (0, 4)
	3259 invokespecial (0, 4)
	3262 putstatic (0, 4)
	3265 new (0, 4)
	3268 dup (0, 4)
	3269 ldc_w (0, 4)
	3272 sipush (0, 4)
	3275 ldc_w (0, 4)
	3278 invokespecial (0, 4)
	3281 putstatic (0, 4)
	3284 new (0, 4)
	3287 dup (0, 4)
	3288 ldc_w (0, 4)
	3291 sipush (0, 4)
	3294 ldc_w (0, 4)
	3297 invokespecial (0, 4)
	3300 putstatic (0, 4)
	3303 new (0, 4)
	3306 dup (0, 4)
	3307 ldc_w (0, 4)
	3310 sipush (0, 4)
	3313 ldc_w (0, 4)
	3316 invokespecial (0, 4)
	3319 putstatic (0, 4)
	3322 new (0, 4)
	3325 dup (0, 4)
	3326 ldc_w (0, 4)
	3329 sipush (0, 4)
	3332 ldc_w (0, 4)
	3335 invokespecial (0, 4)
	3338 putstatic (0, 4)
	3341 new (0, 4)
	3344 dup (0, 4)
	3345 ldc_w (0, 4)
	3348 sipush (0, 4)
	3351 ldc_w (0, 4)
	3354 invokespecial (0, 4)
	3357 putstatic (0, 4)
	3360 new (0, 4)
	3363 dup (0, 4)
	3364 ldc_w (0, 4)
	3367 sipush (0, 4)
	3370 ldc_w (0, 4)
	3373 invokespecial (0, 4)
	3376 putstatic (0, 4)
	3379 new (0, 4)
	3382 dup (0, 4)
	3383 ldc_w (0, 4)
	3386 sipush (0, 4)
	3389 ldc_w (0, 4)
	3392 invokespecial (0, 4)
	3395 putstatic (0, 4)
	3398 new (0, 4)
	3401 dup (0, 4)
	3402 ldc_w (0, 4)
	3405 sipush (0, 4)
	3408 ldc_w (0, 4)
	3411 invokespecial (0, 4)
	3414 putstatic (0, 4)
	3417 new (0, 4)
	3420 dup (0, 4)
	3421 ldc_w (0, 4)
	3424 sipush (0, 4)
	3427 ldc_w (0, 4)
	3430 invokespecial (0, 4)
	3433 putstatic (0, 4)
	3436 new (0, 4)
	3439 dup (0, 4)
	3440 ldc_w (0, 4)
	3443 sipush (0, 4)
	3446 ldc_w (0, 4)
	3449 invokespecial (0, 4)
	3452 putstatic (0, 4)
	3455 new (0, 4)
	3458 dup (0, 4)
	3459 ldc_w (0, 4)
	3462 sipush (0, 4)
	3465 ldc_w (0, 4)
	3468 invokespecial (0, 4)
	3471 putstatic (0, 4)
	3474 new (0, 4)
	3477 dup (0, 4)
	3478 ldc_w (0, 4)
	3481 sipush (0, 4)
	3484 ldc_w (0, 4)
	3487 invokespecial (0, 4)
	3490 putstatic (0, 4)
	3493 new (0, 4)
	3496 dup (0, 4)
	3497 ldc_w (0, 4)
	3500 sipush (0, 4)
	3503 ldc_w (0, 4)
	3506 invokespecial (0, 4)
	3509 putstatic (0, 4)
	3512 new (0, 4)
	3515 dup (0, 4)
	3516 ldc_w (0, 4)
	3519 sipush (0, 4)
	3522 ldc_w (0, 4)
	3525 invokespecial (0, 4)
	3528 putstatic (0, 4)
	3531 new (0, 4)
	3534 dup (0, 4)
	3535 ldc_w (0, 4)
	3538 sipush (0, 4)
	3541 ldc_w (0, 4)
	3544 invokespecial (0, 4)
	3547 putstatic (0, 4)
	3550 new (0, 4)
	3553 dup (0, 4)
	3554 ldc_w (0, 4)
	3557 sipush (0, 4)
	3560 ldc_w (0, 4)
	3563 invokespecial (0, 4)
	3566 putstatic (0, 4)
	3569 new (0, 4)
	3572 dup (0, 4)
	3573 ldc_w (0, 4)
	3576 sipush (0, 4)
	3579 ldc_w (0, 4)
	3582 invokespecial (0, 4)
	3585 putstatic (0, 4)
	3588 new (0, 4)
	3591 dup (0, 4)
	3592 ldc_w (0, 4)
	3595 sipush (0, 4)
	3598 ldc_w (0, 4)
	3601 invokespecial (0, 4)
	3604 putstatic (0, 4)
	3607 new (0, 4)
	3610 dup (0, 4)
	3611 ldc_w (0, 4)
	3614 sipush (0, 4)
	3617 ldc_w (0, 4)
	3620 invokespecial (0, 4)
	3623 putstatic (0, 4)
	3626 new (0, 4)
	3629 dup (0, 4)
	3630 ldc_w (0, 4)
	3633 sipush (0, 4)
	3636 ldc_w (0, 4)
	3639 invokespecial (0, 4)
	3642 putstatic (0, 4)
	3645 new (0, 4)
	3648 dup (0, 4)
	3649 ldc_w (0, 4)
	3652 sipush (0, 4)
	3655 ldc_w (0, 4)
	3658 invokespecial (0, 4)
	3661 putstatic (0, 4)
	3664 new (0, 1)
	3667 dup (0, 1)
	3668 ldc_w (0, 1)
	3671 sipush (0, 1)
	3674 ldc_w (0, 1)
	3677 invokespecial (0, 1)
	3680 putstatic (0, 1)
	3683 new (0, 1)
	3686 dup (0, 1)
	3687 ldc_w (0, 1)
	3690 sipush (0, 1)
	3693 ldc_w (0, 1)
	3696 invokespecial (0, 1)
	3699 putstatic (0, 1)
	3702 new (0, 1)
	3705 dup (0, 1)
	3706 ldc_w (0, 1)
	3709 sipush (0, 1)
	3712 ldc_w (0, 1)
	3715 invokespecial (0, 1)
	3718 putstatic (0, 1)
	3721 new (0, 1)
	3724 dup (0, 1)
	3725 ldc_w (0, 1)
	3728 sipush (0, 1)
	3731 ldc_w (0, 1)
	3734 invokespecial (0, 1)
	3737 putstatic (0, 1)
	3740 new (0, 1)
	3743 dup (0, 1)
	3744 ldc_w (0, 1)
	3747 sipush (0, 1)
	3750 ldc_w (0, 1)
	3753 invokespecial (0, 1)
	3756 putstatic (0, 1)
	3759 new (0, 1)
	3762 dup (0, 1)
	3763 ldc_w (0, 1)
	3766 sipush (0, 1)
	3769 ldc_w (0, 1)
	3772 invokespecial (0, 1)
	3775 putstatic (0, 1)
	3778 new (0, 1)
	3781 dup (0, 1)
	3782 ldc_w (0, 1)
	3785 sipush (0, 1)
	3788 ldc_w (0, 1)
	3791 invokespecial (0, 1)
	3794 putstatic (0, 1)
	3797 new (0, 1)
	3800 dup (0, 1)
	3801 ldc_w (0, 1)
	3804 sipush (0, 1)
	3807 ldc_w (0, 1)
	3810 invokespecial (0, 1)
	3813 putstatic (0, 1)
	3816 new (0, 1)
	3819 dup (0, 1)
	3820 ldc_w (0, 1)
	3823 sipush (0, 1)
	3826 ldc_w (0, 1)
	3829 invokespecial (0, 1)
	3832 putstatic (0, 1)
	3835 new (0, 1)
	3838 dup (0, 1)
	3839 ldc_w (0, 1)
	3842 sipush (0, 1)
	3845 ldc_w (0, 1)
	3848 invokespecial (0, 1)
	3851 putstatic (0, 1)
	3854 new (0, 1)
	3857 dup (0, 1)
	3858 ldc_w (0, 1)
	3861 sipush (0, 1)
	3864 ldc_w (0, 1)
	3867 invokespecial (0, 1)
	3870 putstatic (0, 1)
	3873 new (0, 1)
	3876 dup (0, 1)
	3877 ldc_w (0, 1)
	3880 sipush (0, 1)
	3883 ldc_w (0, 1)
	3886 invokespecial (0, 1)
	3889 putstatic (0, 1)
	3892 new (0, 1)
	3895 dup (0, 1)
	3896 ldc_w (0, 1)
	3899 sipush (0, 1)
	3902 ldc_w (0, 1)
	3905 invokespecial (0, 1)
	3908 putstatic (0, 1)
	3911 new (0, 1)
	3914 dup (0, 1)
	3915 ldc_w (0, 1)
	3918 sipush (0, 1)
	3921 ldc_w (0, 1)
	3924 invokespecial (0, 1)
	3927 putstatic (0, 1)
	3930 new (0, 1)
	3933 dup (0, 1)
	3934 ldc_w (0, 1)
	3937 sipush (0, 1)
	3940 ldc_w (0, 1)
	3943 invokespecial (0, 1)
	3946 putstatic (0, 1)
	3949 new (0, 1)
	3952 dup (0, 1)
	3953 ldc_w (0, 1)
	3956 sipush (0, 1)
	3959 ldc_w (0, 1)
	3962 invokespecial (0, 1)
	3965 putstatic (0, 1)
	3968 new (0, 4)
	3971 dup (0, 4)
	3972 ldc_w (0, 4)
	3975 sipush (0, 4)
	3978 ldc_w (0, 4)
	3981 invokespecial (0, 4)
	3984 putstatic (0, 4)
	3987 new (0, 4)
	3990 dup (0, 4)
	3991 ldc_w (0, 4)
	3994 sipush (0, 4)
	3997 ldc_w (0, 4)
	4000 invokespecial (0, 4)
	4003 putstatic (0, 4)
	4006 new (0, 4)
	4009 dup (0, 4)
	4010 ldc_w (0, 4)
	4013 sipush (0, 4)
	4016 ldc_w (0, 4)
	4019 invokespecial (0, 4)
	4022 putstatic (0, 4)
	4025 new (0, 4)
	4028 dup (0, 4)
	4029 ldc_w (0, 4)
	4032 sipush (0, 4)
	4035 ldc_w (0, 4)
	4038 invokespecial (0, 4)
	4041 putstatic (0, 4)
	4044 new (0, 4)
	4047 dup (0, 4)
	4048 ldc_w (0, 4)
	4051 sipush (0, 4)
	4054 ldc_w (0, 4)
	4057 invokespecial (0, 4)
	4060 putstatic (0, 4)
	4063 new (0, 4)
	4066 dup (0, 4)
	4067 ldc_w (0, 4)
	4070 sipush (0, 4)
	4073 ldc_w (0, 4)
	4076 invokespecial (0, 4)
	4079 putstatic (0, 4)
	4082 new (0, 4)
	4085 dup (0, 4)
	4086 ldc_w (0, 4)
	4089 sipush (0, 4)
	4092 ldc_w (0, 4)
	4095 invokespecial (0, 4)
	4098 putstatic (0, 4)
	4101 new (0, 4)
	4104 dup (0, 4)
	4105 ldc_w (0, 4)
	4108 sipush (0, 4)
	4111 ldc_w (0, 4)
	4114 invokespecial (0, 4)
	4117 putstatic (0, 4)
	4120 new (0, 4)
	4123 dup (0, 4)
	4124 ldc_w (0, 4)
	4127 sipush (0, 4)
	4130 ldc_w (0, 4)
	4133 invokespecial (0, 4)
	4136 putstatic (0, 4)
	4139 new (0, 4)
	4142 dup (0, 4)
	4143 ldc_w (0, 4)
	4146 sipush (0, 4)
	4149 ldc_w (0, 4)
	4152 invokespecial (0, 4)
	4155 putstatic (0, 4)
	4158 new (0, 4)
	4161 dup (0, 4)
	4162 ldc_w (0, 4)
	4165 sipush (0, 4)
	4168 ldc_w (0, 4)
	4171 invokespecial (0, 4)
	4174 putstatic (0, 4)
	4177 new (0, 4)
	4180 dup (0, 4)
	4181 ldc_w (0, 4)
	4184 sipush (0, 4)
	4187 ldc_w (0, 4)
	4190 invokespecial (0, 4)
	4193 putstatic (0, 4)
	4196 new (0, 4)
	4199 dup (0, 4)
	4200 ldc_w (0, 4)
	4203 sipush (0, 4)
	4206 ldc_w (0, 4)
	4209 invokespecial (0, 4)
	4212 putstatic (0, 4)
	4215 new (0, 4)
	4218 dup (0, 4)
	4219 ldc_w (0, 4)
	4222 sipush (0, 4)
	4225 ldc_w (0, 4)
	4228 invokespecial (0, 4)
	4231 putstatic (0, 4)
	4234 new (0, 4)
	4237 dup (0, 4)
	4238 ldc_w (0, 4)
	4241 sipush (0, 4)
	4244 ldc_w (0, 4)
	4247 invokespecial (0, 4)
	4250 putstatic (0, 4)
	4253 new (0, 4)
	4256 dup (0, 4)
	4257 ldc_w (0, 4)
	4260 sipush (0, 4)
	4263 ldc_w (0, 4)
	4266 invokespecial (0, 4)
	4269 putstatic (0, 4)
	4272 new (0, 4)
	4275 dup (0, 4)
	4276 ldc_w (0, 4)
	4279 sipush (0, 4)
	4282 ldc_w (0, 4)
	4285 invokespecial (0, 4)
	4288 putstatic (0, 4)
	4291 new (0, 4)
	4294 dup (0, 4)
	4295 ldc_w (0, 4)
	4298 sipush (0, 4)
	4301 ldc_w (0, 4)
	4304 invokespecial (0, 4)
	4307 putstatic (0, 4)
	4310 new (0, 4)
	4313 dup (0, 4)
	4314 ldc_w (0, 4)
	4317 sipush (0, 4)
	4320 ldc_w (0, 4)
	4323 invokespecial (0, 4)
	4326 putstatic (0, 4)
	4329 new (0, 1)
	4332 dup (0, 1)
	4333 ldc_w (0, 1)
	4336 sipush (0, 1)
	4339 ldc_w (0, 1)
	4342 invokespecial (0, 1)
	4345 putstatic (0, 1)
	4348 new (0, 1)
	4351 dup (0, 1)
	4352 ldc_w (0, 1)
	4355 sipush (0, 1)
	4358 ldc_w (0, 1)
	4361 invokespecial (0, 1)
	4364 putstatic (0, 1)
	4367 new (0, 1)
	4370 dup (0, 1)
	4371 ldc_w (0, 1)
	4374 sipush (0, 1)
	4377 ldc_w (0, 1)
	4380 invokespecial (0, 1)
	4383 putstatic (0, 1)
	4386 new (0, 1)
	4389 dup (0, 1)
	4390 ldc_w (0, 1)
	4393 sipush (0, 1)
	4396 ldc_w (0, 1)
	4399 invokespecial (0, 1)
	4402 putstatic (0, 1)
	4405 new (0, 1)
	4408 dup (0, 1)
	4409 ldc_w (0, 1)
	4412 sipush (0, 1)
	4415 ldc_w (0, 1)
	4418 invokespecial (0, 1)
	4421 putstatic (0, 1)
	4424 new (0, 1)
	4427 dup (0, 1)
	4428 ldc_w (0, 1)
	4431 sipush (0, 1)
	4434 ldc_w (0, 1)
	4437 invokespecial (0, 1)
	4440 putstatic (0, 1)
	4443 new (0, 1)
	4446 dup (0, 1)
	4447 ldc_w (0, 1)
	4450 sipush (0, 1)
	4453 ldc_w (0, 1)
	4456 invokespecial (0, 1)
	4459 putstatic (0, 1)
	4462 new (0, 1)
	4465 dup (0, 1)
	4466 ldc_w (0, 1)
	4469 sipush (0, 1)
	4472 ldc_w (0, 1)
	4475 invokespecial (0, 1)
	4478 putstatic (0, 1)
	4481 new (0, 1)
	4484 dup (0, 1)
	4485 ldc_w (0, 1)
	4488 sipush (0, 1)
	4491 ldc_w (0, 1)
	4494 invokespecial (0, 1)
	4497 putstatic (0, 1)
	4500 new (0, 1)
	4503 dup (0, 1)
	4504 ldc_w (0, 1)
	4507 sipush (0, 1)
	4510 ldc_w (0, 1)
	4513 invokespecial (0, 1)
	4516 putstatic (0, 1)
	4519 new (0, 1)
	4522 dup (0, 1)
	4523 ldc_w (0, 1)
	4526 sipush (0, 1)
	4529 ldc_w (0, 1)
	4532 invokespecial (0, 1)
	4535 putstatic (0, 1)
	4538 new (0, 1)
	4541 dup (0, 1)
	4542 ldc_w (0, 1)
	4545 sipush (0, 1)
	4548 ldc_w (0, 1)
	4551 invokespecial (0, 1)
	4554 putstatic (0, 1)
	4557 new (0, 1)
	4560 dup (0, 1)
	4561 ldc_w (0, 1)
	4564 sipush (0, 1)
	4567 ldc_w (0, 1)
	4570 invokespecial (0, 1)
	4573 putstatic (0, 1)
	4576 new (0, 1)
	4579 dup (0, 1)
	4580 ldc_w (0, 1)
	4583 sipush (0, 1)
	4586 ldc_w (0, 1)
	4589 invokespecial (0, 1)
	4592 putstatic (0, 1)
	4595 new (0, 1)
	4598 dup (0, 1)
	4599 ldc_w (0, 1)
	4602 sipush (0, 1)
	4605 ldc_w (0, 1)
	4608 invokespecial (0, 1)
	4611 putstatic (0, 1)
	4614 new (0, 1)
	4617 dup (0, 1)
	4618 ldc_w (0, 1)
	4621 sipush (0, 1)
	4624 ldc_w (0, 1)
	4627 invokespecial (0, 1)
	4630 putstatic (0, 1)
	4633 new (0, 1)
	4636 dup (0, 1)
	4637 ldc_w (0, 1)
	4640 sipush (0, 1)
	4643 ldc_w (0, 1)
	4646 invokespecial (0, 1)
	4649 putstatic (0, 1)
	4652 new (0, 1)
	4655 dup (0, 1)
	4656 ldc_w (0, 1)
	4659 sipush (0, 1)
	4662 ldc_w (0, 1)
	4665 invokespecial (0, 1)
	4668 putstatic (0, 1)
	4671 new (0, 1)
	4674 dup (0, 1)
	4675 ldc_w (0, 1)
	4678 sipush (0, 1)
	4681 ldc_w (0, 1)
	4684 invokespecial (0, 1)
	4687 putstatic (0, 1)
	4690 new (0, 1)
	4693 dup (0, 1)
	4694 ldc_w (0, 1)
	4697 sipush (0, 1)
	4700 ldc_w (0, 1)
	4703 invokespecial (0, 1)
	4706 putstatic (0, 1)
	4709 new (0, 1)
	4712 dup (0, 1)
	4713 ldc_w (0, 1)
	4716 sipush (0, 1)
	4719 ldc_w (0, 1)
	4722 invokespecial (0, 1)
	4725 putstatic (0, 1)
	4728 new (0, 1)
	4731 dup (0, 1)
	4732 ldc_w (0, 1)
	4735 sipush (0, 1)
	4738 ldc_w (0, 1)
	4741 invokespecial (0, 1)
	4744 putstatic (0, 1)
	4747 new (0, 1)
	4750 dup (0, 1)
	4751 ldc_w (0, 1)
	4754 sipush (0, 1)
	4757 ldc_w (0, 1)
	4760 invokespecial (0, 1)
	4763 putstatic (0, 1)
	4766 new (0, 1)
	4769 dup (0, 1)
	4770 ldc_w (0, 1)
	4773 sipush (0, 1)
	4776 ldc_w (0, 1)
	4779 invokespecial (0, 1)
	4782 putstatic (0, 1)
	4785 new (0, 1)
	4788 dup (0, 1)
	4789 ldc_w (0, 1)
	4792 sipush (0, 1)
	4795 ldc_w (0, 1)
	4798 invokespecial (0, 1)
	4801 putstatic (0, 1)
	4804 new (0, 1)
	4807 dup (0, 1)
	4808 ldc_w (0, 1)
	4811 sipush (0, 1)
	4814 ldc_w (0, 1)
	4817 invokespecial (0, 1)
	4820 putstatic (0, 1)
	4823 new (0, 1)
	4826 dup (0, 1)
	4827 ldc_w (0, 1)
	4830 sipush (0, 1)
	4833 ldc_w (0, 1)
	4836 invokespecial (0, 1)
	4839 putstatic (0, 1)
	4842 new (0, 1)
	4845 dup (0, 1)
	4846 ldc_w (0, 1)
	4849 sipush (0, 1)
	4852 ldc_w (0, 1)
	4855 invokespecial (0, 1)
	4858 putstatic (0, 1)
	4861 new (0, 1)
	4864 dup (0, 1)
	4865 ldc_w (0, 1)
	4868 sipush (0, 1)
	4871 ldc_w (0, 1)
	4874 invokespecial (0, 1)
	4877 putstatic (0, 1)
	4880 new (0, 1)
	4883 dup (0, 1)
	4884 ldc_w (0, 1)
	4887 sipush (0, 1)
	4890 ldc_w (0, 1)
	4893 invokespecial (0, 1)
	4896 putstatic (0, 1)
	4899 new (0, 1)
	4902 dup (0, 1)
	4903 ldc_w (0, 1)
	4906 sipush (0, 1)
	4909 ldc_w (0, 1)
	4912 invokespecial (0, 1)
	4915 putstatic (0, 1)
	4918 new (0, 1)
	4921 dup (0, 1)
	4922 ldc_w (0, 1)
	4925 sipush (0, 1)
	4928 ldc_w (0, 1)
	4931 invokespecial (0, 1)
	4934 putstatic (0, 1)
	4937 new (0, 1)
	4940 dup (0, 1)
	4941 ldc_w (0, 1)
	4944 sipush (0, 1)
	4947 ldc_w (0, 1)
	4950 invokespecial (0, 1)
	4953 putstatic (0, 1)
	4956 new (0, 1)
	4959 dup (0, 1)
	4960 ldc_w (0, 1)
	4963 sipush (0, 1)
	4966 ldc_w (0, 1)
	4969 invokespecial (0, 1)
	4972 putstatic (0, 1)
	4975 new (0, 1)
	4978 dup (0, 1)
	4979 ldc_w (0, 1)
	4982 sipush (0, 1)
	4985 ldc_w (0, 1)
	4988 invokespecial (0, 1)
	4991 putstatic (0, 1)
	4994 new (0, 1)
	4997 dup (0, 1)
	4998 ldc_w (0, 1)
	5001 sipush (0, 1)
	5004 ldc_w (0, 1)
	5007 invokespecial (0, 1)
	5010 putstatic (0, 1)
	5013 new (0, 1)
	5016 dup (0, 1)
	5017 ldc_w (0, 1)
	5020 sipush (0, 1)
	5023 ldc_w (0, 1)
	5026 invokespecial (0, 1)
	5029 putstatic (0, 1)
	5032 new (0, 1)
	5035 dup (0, 1)
	5036 ldc_w (0, 1)
	5039 sipush (0, 1)
	5042 ldc_w (0, 1)
	5045 invokespecial (0, 1)
	5048 putstatic (0, 1)
	5051 new (0, 1)
	5054 dup (0, 1)
	5055 ldc_w (0, 1)
	5058 sipush (0, 1)
	5061 ldc_w (0, 1)
	5064 invokespecial (0, 1)
	5067 putstatic (0, 1)
	5070 new (0, 1)
	5073 dup (0, 1)
	5074 ldc_w (0, 1)
	5077 sipush (0, 1)
	5080 ldc_w (0, 1)
	5083 invokespecial (0, 1)
	5086 putstatic (0, 1)
	5089 new (0, 1)
	5092 dup (0, 1)
	5093 ldc_w (0, 1)
	5096 sipush (0, 1)
	5099 ldc_w (0, 1)
	5102 invokespecial (0, 1)
	5105 putstatic (0, 1)
	5108 new (0, 1)
	5111 dup (0, 1)
	5112 ldc_w (0, 1)
	5115 sipush (0, 1)
	5118 ldc_w (0, 1)
	5121 invokespecial (0, 1)
	5124 putstatic (0, 1)
	5127 new (0, 1)
	5130 dup (0, 1)
	5131 ldc_w (0, 1)
	5134 sipush (0, 1)
	5137 ldc_w (0, 1)
	5140 invokespecial (0, 1)
	5143 putstatic (0, 1)
	5146 new (0, 1)
	5149 dup (0, 1)
	5150 ldc_w (0, 1)
	5153 sipush (0, 1)
	5156 ldc_w (0, 1)
	5159 invokespecial (0, 1)
	5162 putstatic (0, 1)
	5165 new (0, 1)
	5168 dup (0, 1)
	5169 ldc_w (0, 1)
	5172 sipush (0, 1)
	5175 ldc_w (0, 1)
	5178 invokespecial (0, 1)
	5181 putstatic (0, 1)
	5184 new (0, 1)
	5187 dup (0, 1)
	5188 ldc_w (0, 1)
	5191 sipush (0, 1)
	5194 ldc_w (0, 1)
	5197 invokespecial (0, 1)
	5200 putstatic (0, 1)
	5203 new (0, 1)
	5206 dup (0, 1)
	5207 ldc_w (0, 1)
	5210 sipush (0, 1)
	5213 ldc_w (0, 1)
	5216 invokespecial (0, 1)
	5219 putstatic (0, 1)
	5222 new (0, 1)
	5225 dup (0, 1)
	5226 ldc_w (0, 1)
	5229 sipush (0, 1)
	5232 ldc_w (0, 1)
	5235 invokespecial (0, 1)
	5238 putstatic (0, 1)
	5241 new (0, 1)
	5244 dup (0, 1)
	5245 ldc_w (0, 1)
	5248 sipush (0, 1)
	5251 ldc_w (0, 1)
	5254 invokespecial (0, 1)
	5257 putstatic (0, 1)
	5260 new (0, 1)
	5263 dup (0, 1)
	5264 ldc_w (0, 1)
	5267 sipush (0, 1)
	5270 ldc_w (0, 1)
	5273 invokespecial (0, 1)
	5276 putstatic (0, 1)
	5279 new (0, 1)
	5282 dup (0, 1)
	5283 ldc_w (0, 1)
	5286 sipush (0, 1)
	5289 ldc_w (0, 1)
	5292 invokespecial (0, 1)
	5295 putstatic (0, 1)
	5298 new (0, 1)
	5301 dup (0, 1)
	5302 ldc_w (0, 1)
	5305 sipush (0, 1)
	5308 ldc_w (0, 1)
	5311 invokespecial (0, 1)
	5314 putstatic (0, 1)
	5317 new (0, 1)
	5320 dup (0, 1)
	5321 ldc_w (0, 1)
	5324 sipush (0, 1)
	5327 ldc_w (0, 1)
	5330 invokespecial (0, 1)
	5333 putstatic (0, 1)
	5336 new (0, 1)
	5339 dup (0, 1)
	5340 ldc_w (0, 1)
	5343 sipush (0, 1)
	5346 ldc_w (0, 1)
	5349 invokespecial (0, 1)
	5352 putstatic (0, 1)
	5355 new (0, 4)
	5358 dup (0, 4)
	5359 ldc_w (0, 4)
	5362 sipush (0, 4)
	5365 ldc_w (0, 4)
	5368 invokespecial (0, 4)
	5371 putstatic (0, 4)
	5374 new (0, 4)
	5377 dup (0, 4)
	5378 ldc_w (0, 4)
	5381 sipush (0, 4)
	5384 ldc_w (0, 4)
	5387 invokespecial (0, 4)
	5390 putstatic (0, 4)
	5393 new (0, 4)
	5396 dup (0, 4)
	5397 ldc_w (0, 4)
	5400 sipush (0, 4)
	5403 ldc_w (0, 4)
	5406 invokespecial (0, 4)
	5409 putstatic (0, 4)
	5412 new (0, 4)
	5415 dup (0, 4)
	5416 ldc_w (0, 4)
	5419 sipush (0, 4)
	5422 ldc_w (0, 4)
	5425 invokespecial (0, 4)
	5428 putstatic (0, 4)
	5431 new (0, 4)
	5434 dup (0, 4)
	5435 ldc_w (0, 4)
	5438 sipush (0, 4)
	5441 ldc_w (0, 4)
	5444 invokespecial (0, 4)
	5447 putstatic (0, 4)
	5450 new (0, 4)
	5453 dup (0, 4)
	5454 ldc_w (0, 4)
	5457 sipush (0, 4)
	5460 ldc_w (0, 4)
	5463 invokespecial (0, 4)
	5466 putstatic (0, 4)
	5469 new (0, 4)
	5472 dup (0, 4)
	5473 ldc_w (0, 4)
	5476 sipush (0, 4)
	5479 ldc_w (0, 4)
	5482 invokespecial (0, 4)
	5485 putstatic (0, 4)
	5488 new (0, 4)
	5491 dup (0, 4)
	5492 ldc_w (0, 4)
	5495 sipush (0, 4)
	5498 ldc_w (0, 4)
	5501 invokespecial (0, 4)
	5504 putstatic (0, 4)
	5507 new (0, 4)
	5510 dup (0, 4)
	5511 ldc_w (0, 4)
	5514 sipush (0, 4)
	5517 ldc_w (0, 4)
	5520 invokespecial (0, 4)
	5523 putstatic (0, 4)
	5526 new (0, 4)
	5529 dup (0, 4)
	5530 ldc_w (0, 4)
	5533 sipush (0, 4)
	5536 ldc_w (0, 4)
	5539 invokespecial (0, 4)
	5542 putstatic (0, 4)
	5545 new (0, 4)
	5548 dup (0, 4)
	5549 ldc_w (0, 4)
	5552 sipush (0, 4)
	5555 ldc_w (0, 4)
	5558 invokespecial (0, 4)
	5561 putstatic (0, 4)
	5564 new (0, 4)
	5567 dup (0, 4)
	5568 ldc_w (0, 4)
	5571 sipush (0, 4)
	5574 ldc_w (0, 4)
	5577 invokespecial (0, 4)
	5580 putstatic (0, 4)
	5583 new (0, 4)
	5586 dup (0, 4)
	5587 ldc_w (0, 4)
	5590 sipush (0, 4)
	5593 ldc_w (0, 4)
	5596 invokespecial (0, 4)
	5599 putstatic (0, 4)
	5602 new (0, 4)
	5605 dup (0, 4)
	5606 ldc_w (0, 4)
	5609 sipush (0, 4)
	5612 ldc_w (0, 4)
	5615 invokespecial (0, 4)
	5618 putstatic (0, 4)
	5621 new (0, 4)
	5624 dup (0, 4)
	5625 ldc_w (0, 4)
	5628 sipush (0, 4)
	5631 ldc_w (0, 4)
	5634 invokespecial (0, 4)
	5637 putstatic (0, 4)
	5640 new (0, 4)
	5643 dup (0, 4)
	5644 ldc_w (0, 4)
	5647 sipush (0, 4)
	5650 ldc_w (0, 4)
	5653 invokespecial (0, 4)
	5656 putstatic (0, 4)
	5659 new (0, 4)
	5662 dup (0, 4)
	5663 ldc_w (0, 4)
	5666 sipush (0, 4)
	5669 ldc_w (0, 4)
	5672 invokespecial (0, 4)
	5675 putstatic (0, 4)
	5678 new (0, 4)
	5681 dup (0, 4)
	5682 ldc_w (0, 4)
	5685 sipush (0, 4)
	5688 ldc_w (0, 4)
	5691 invokespecial (0, 4)
	5694 putstatic (0, 4)
	5697 new (0, 4)
	5700 dup (0, 4)
	5701 ldc_w (0, 4)
	5704 sipush (0, 4)
	5707 ldc_w (0, 4)
	5710 invokespecial (0, 4)
	5713 putstatic (0, 4)
	5716 new (0, 4)
	5719 dup (0, 4)
	5720 ldc_w (0, 4)
	5723 sipush (0, 4)
	5726 ldc_w (0, 4)
	5729 invokespecial (0, 4)
	5732 putstatic (0, 4)
	5735 new (0, 4)
	5738 dup (0, 4)
	5739 ldc_w (0, 4)
	5742 sipush (0, 4)
	5745 ldc_w (0, 4)
	5748 invokespecial (0, 4)
	5751 putstatic (0, 4)
	5754 new (0, 4)
	5757 dup (0, 4)
	5758 ldc_w (0, 4)
	5761 sipush (0, 4)
	5764 ldc_w (0, 4)
	5767 invokespecial (0, 4)
	5770 putstatic (0, 4)
	5773 new (0, 4)
	5776 dup (0, 4)
	5777 ldc_w (0, 4)
	5780 sipush (0, 4)
	5783 ldc_w (0, 4)
	5786 invokespecial (0, 4)
	5789 putstatic (0, 4)
	5792 new (0, 4)
	5795 dup (0, 4)
	5796 ldc_w (0, 4)
	5799 sipush (0, 4)
	5802 ldc_w (0, 4)
	5805 invokespecial (0, 4)
	5808 putstatic (0, 4)
	5811 new (0, 1)
	5814 dup (0, 1)
	5815 ldc_w (0, 1)
	5818 sipush (0, 1)
	5821 ldc_w (0, 1)
	5824 invokespecial (0, 1)
	5827 putstatic (0, 1)
	5830 new (0, 1)
	5833 dup (0, 1)
	5834 ldc_w (0, 1)
	5837 sipush (0, 1)
	5840 ldc_w (0, 1)
	5843 invokespecial (0, 1)
	5846 putstatic (0, 1)
	5849 new (0, 1)
	5852 dup (0, 1)
	5853 ldc_w (0, 1)
	5856 sipush (0, 1)
	5859 ldc_w (0, 1)
	5862 invokespecial (0, 1)
	5865 putstatic (0, 1)
	5868 new (0, 1)
	5871 dup (0, 1)
	5872 ldc_w (0, 1)
	5875 sipush (0, 1)
	5878 ldc_w (0, 1)
	5881 invokespecial (0, 1)
	5884 putstatic (0, 1)
	5887 new (0, 4)
	5890 dup (0, 4)
	5891 ldc_w (0, 4)
	5894 sipush (0, 4)
	5897 ldc_w (0, 4)
	5900 invokespecial (0, 4)
	5903 putstatic (0, 4)
	5906 new (0, 4)
	5909 dup (0, 4)
	5910 ldc_w (0, 4)
	5913 sipush (0, 4)
	5916 ldc_w (0, 4)
	5919 invokespecial (0, 4)
	5922 putstatic (0, 4)
	5925 new (0, 4)
	5928 dup (0, 4)
	5929 ldc_w (0, 4)
	5932 sipush (0, 4)
	5935 ldc_w (0, 4)
	5938 invokespecial (0, 4)
	5941 putstatic (0, 4)
	5944 sipush (0, 4)
	5947 anewarray (0, 4)
	5950 dup (0, 4)
	5951 iconst_0 (0, 4)
	5952 getstatic (0, 4)
	5955 aastore (0, 4)
	5956 dup (0, 4)
	5957 iconst_1 (0, 4)
	5958 getstatic (0, 4)
	5961 aastore (0, 4)
	5962 dup (0, 4)
	5963 iconst_2 (0, 4)
	5964 getstatic (0, 4)
	5967 aastore (0, 4)
	5968 dup (0, 4)
	5969 iconst_3 (0, 4)
	5970 getstatic (0, 4)
	5973 aastore (0, 4)
	5974 dup (0, 4)
	5975 iconst_4 (0, 4)
	5976 getstatic (0, 4)
	5979 aastore (0, 4)
	5980 dup (0, 4)
	5981 iconst_5 (0, 4)
	5982 getstatic (0, 4)
	5985 aastore (0, 4)
	5986 dup (0, 4)
	5987 bipush (0, 4)
	5989 getstatic (0, 4)
	5992 aastore (0, 4)
	5993 dup (0, 4)
	5994 bipush (0, 4)
	5996 getstatic (0, 4)
	5999 aastore (0, 4)
	6000 dup (0, 4)
	6001 bipush (0, 4)
	6003 getstatic (0, 4)
	6006 aastore (0, 4)
	6007 dup (0, 4)
	6008 bipush (0, 4)
	6010 getstatic (0, 4)
	6013 aastore (0, 4)
	6014 dup (0, 4)
	6015 bipush (0, 4)
	6017 getstatic (0, 4)
	6020 aastore (0, 4)
	6021 dup (0, 4)
	6022 bipush (0, 4)
	6024 getstatic (0, 4)
	6027 aastore (0, 4)
	6028 dup (0, 4)
	6029 bipush (0, 4)
	6031 getstatic (0, 4)
	6034 aastore (0, 4)
	6035 dup (0, 4)
	6036 bipush (0, 4)
	6038 getstatic (0, 4)
	6041 aastore (0, 4)
	6042 dup (0, 4)
	6043 bipush (0, 4)
	6045 getstatic (0, 4)
	6048 aastore (0, 4)
	6049 dup (0, 4)
	6050 bipush (0, 4)
	6052 getstatic (0, 4)
	6055 aastore (0, 4)
	6056 dup (0, 4)
	6057 bipush (0, 4)
	6059 getstatic (0, 4)
	6062 aastore (0, 4)
	6063 dup (0, 4)
	6064 bipush (0, 4)
	6066 getstatic (0, 4)
	6069 aastore (0, 4)
	6070 dup (0, 4)
	6071 bipush (0, 4)
	6073 getstatic (0, 4)
	6076 aastore (0, 4)
	6077 dup (0, 4)
	6078 bipush (0, 4)
	6080 getstatic (0, 4)
	6083 aastore (0, 4)
	6084 dup (0, 4)
	6085 bipush (0, 4)
	6087 getstatic (0, 4)
	6090 aastore (0, 4)
	6091 dup (0, 4)
	6092 bipush (0, 4)
	6094 getstatic (0, 4)
	6097 aastore (0, 4)
	6098 dup (0, 4)
	6099 bipush (0, 4)
	6101 getstatic (0, 4)
	6104 aastore (0, 4)
	6105 dup (0, 4)
	6106 bipush (0, 4)
	6108 getstatic (0, 4)
	6111 aastore (0, 4)
	6112 dup (0, 4)
	6113 bipush (0, 4)
	6115 getstatic (0, 4)
	6118 aastore (0, 4)
	6119 dup (0, 4)
	6120 bipush (0, 4)
	6122 getstatic (0, 4)
	6125 aastore (0, 4)
	6126 dup (0, 4)
	6127 bipush (0, 4)
	6129 getstatic (0, 4)
	6132 aastore (0, 4)
	6133 dup (0, 4)
	6134 bipush (0, 4)
	6136 getstatic (0, 4)
	6139 aastore (0, 4)
	6140 dup (0, 4)
	6141 bipush (0, 4)
	6143 getstatic (0, 4)
	6146 aastore (0, 4)
	6147 dup (0, 4)
	6148 bipush (0, 4)
	6150 getstatic (0, 4)
	6153 aastore (0, 4)
	6154 dup (0, 4)
	6155 bipush (0, 4)
	6157 getstatic (0, 4)
	6160 aastore (0, 4)
	6161 dup (0, 4)
	6162 bipush (0, 4)
	6164 getstatic (0, 4)
	6167 aastore (0, 4)
	6168 dup (0, 4)
	6169 bipush (0, 4)
	6171 getstatic (0, 4)
	6174 aastore (0, 4)
	6175 dup (0, 4)
	6176 bipush (0, 4)
	6178 getstatic (0, 4)
	6181 aastore (0, 4)
	6182 dup (0, 4)
	6183 bipush (0, 4)
	6185 getstatic (0, 4)
	6188 aastore (0, 4)
	6189 dup (0, 4)
	6190 bipush (0, 4)
	6192 getstatic (0, 4)
	6195 aastore (0, 4)
	6196 dup (0, 4)
	6197 bipush (0, 4)
	6199 getstatic (0, 4)
	6202 aastore (0, 4)
	6203 dup (0, 4)
	6204 bipush (0, 4)
	6206 getstatic (0, 4)
	6209 aastore (0, 4)
	6210 dup (0, 4)
	6211 bipush (0, 4)
	6213 getstatic (0, 4)
	6216 aastore (0, 4)
	6217 dup (0, 4)
	6218 bipush (0, 4)
	6220 getstatic (0, 4)
	6223 aastore (0, 4)
	6224 dup (0, 4)
	6225 bipush (0, 4)
	6227 getstatic (0, 4)
	6230 aastore (0, 4)
	6231 dup (0, 4)
	6232 bipush (0, 4)
	6234 getstatic (0, 4)
	6237 aastore (0, 4)
	6238 dup (0, 4)
	6239 bipush (0, 4)
	6241 getstatic (0, 4)
	6244 aastore (0, 4)
	6245 dup (0, 4)
	6246 bipush (0, 4)
	6248 getstatic (0, 4)
	6251 aastore (0, 4)
	6252 dup (0, 4)
	6253 bipush (0, 4)
	6255 getstatic (0, 4)
	6258 aastore (0, 4)
	6259 dup (0, 4)
	6260 bipush (0, 4)
	6262 getstatic (0, 4)
	6265 aastore (0, 4)
	6266 dup (0, 4)
	6267 bipush (0, 4)
	6269 getstatic (0, 4)
	6272 aastore (0, 4)
	6273 dup (0, 4)
	6274 bipush (0, 4)
	6276 getstatic (0, 4)
	6279 aastore (0, 4)
	6280 dup (0, 4)
	6281 bipush (0, 4)
	6283 getstatic (0, 4)
	6286 aastore (0, 4)
	6287 dup (0, 4)
	6288 bipush (0, 4)
	6290 getstatic (0, 4)
	6293 aastore (0, 4)
	6294 dup (0, 4)
	6295 bipush (0, 4)
	6297 getstatic (0, 4)
	6300 aastore (0, 4)
	6301 dup (0, 4)
	6302 bipush (0, 4)
	6304 getstatic (0, 4)
	6307 aastore (0, 4)
	6308 dup (0, 4)
	6309 bipush (0, 4)
	6311 getstatic (0, 4)
	6314 aastore (0, 4)
	6315 dup (0, 4)
	6316 bipush (0, 4)
	6318 getstatic (0, 4)
	6321 aastore (0, 4)
	6322 dup (0, 4)
	6323 bipush (0, 4)
	6325 getstatic (0, 4)
	6328 aastore (0, 4)
	6329 dup (0, 4)
	6330 bipush (0, 4)
	6332 getstatic (0, 4)
	6335 aastore (0, 4)
	6336 dup (0, 4)
	6337 bipush (0, 4)
	6339 getstatic (0, 4)
	6342 aastore (0, 4)
	6343 dup (0, 4)
	6344 bipush (0, 4)
	6346 getstatic (0, 4)
	6349 aastore (0, 4)
	6350 dup (0, 4)
	6351 bipush (0, 4)
	6353 getstatic (0, 4)
	6356 aastore (0, 4)
	6357 dup (0, 4)
	6358 bipush (0, 4)
	6360 getstatic (0, 4)
	6363 aastore (0, 4)
	6364 dup (0, 4)
	6365 bipush (0, 4)
	6367 getstatic (0, 4)
	6370 aastore (0, 4)
	6371 dup (0, 4)
	6372 bipush (0, 4)
	6374 getstatic (0, 4)
	6377 aastore (0, 4)
	6378 dup (0, 4)
	6379 bipush (0, 4)
	6381 getstatic (0, 4)
	6384 aastore (0, 4)
	6385 dup (0, 4)
	6386 bipush (0, 4)
	6388 getstatic (0, 4)
	6391 aastore (0, 4)
	6392 dup (0, 4)
	6393 bipush (0, 4)
	6395 getstatic (0, 4)
	6398 aastore (0, 4)
	6399 dup (0, 4)
	6400 bipush (0, 4)
	6402 getstatic (0, 4)
	6405 aastore (0, 4)
	6406 dup (0, 4)
	6407 bipush (0, 4)
	6409 getstatic (0, 4)
	6412 aastore (0, 4)
	6413 dup (0, 4)
	6414 bipush (0, 4)
	6416 getstatic (0, 4)
	6419 aastore (0, 4)
	6420 dup (0, 4)
	6421 bipush (0, 4)
	6423 getstatic (0, 4)
	6426 aastore (0, 4)
	6427 dup (0, 4)
	6428 bipush (0, 4)
	6430 getstatic (0, 4)
	6433 aastore (0, 4)
	6434 dup (0, 4)
	6435 bipush (0, 4)
	6437 getstatic (0, 4)
	6440 aastore (0, 4)
	6441 dup (0, 4)
	6442 bipush (0, 4)
	6444 getstatic (0, 4)
	6447 aastore (0, 4)
	6448 dup (0, 4)
	6449 bipush (0, 4)
	6451 getstatic (0, 4)
	6454 aastore (0, 4)
	6455 dup (0, 4)
	6456 bipush (0, 4)
	6458 getstatic (0, 4)
	6461 aastore (0, 4)
	6462 dup (0, 4)
	6463 bipush (0, 4)
	6465 getstatic (0, 4)
	6468 aastore (0, 4)
	6469 dup (0, 4)
	6470 bipush (0, 4)
	6472 getstatic (0, 4)
	6475 aastore (0, 4)
	6476 dup (0, 4)
	6477 bipush (0, 4)
	6479 getstatic (0, 4)
	6482 aastore (0, 4)
	6483 dup (0, 4)
	6484 bipush (0, 4)
	6486 getstatic (0, 4)
	6489 aastore (0, 4)
	6490 dup (0, 4)
	6491 bipush (0, 4)
	6493 getstatic (0, 4)
	6496 aastore (0, 4)
	6497 dup (0, 4)
	6498 bipush (0, 4)
	6500 getstatic (0, 4)
	6503 aastore (0, 4)
	6504 dup (0, 4)
	6505 bipush (0, 4)
	6507 getstatic (0, 4)
	6510 aastore (0, 4)
	6511 dup (0, 4)
	6512 bipush (0, 4)
	6514 getstatic (0, 4)
	6517 aastore (0, 4)
	6518 dup (0, 4)
	6519 bipush (0, 4)
	6521 getstatic (0, 4)
	6524 aastore (0, 4)
	6525 dup (0, 4)
	6526 bipush (0, 4)
	6528 getstatic (0, 4)
	6531 aastore (0, 4)
	6532 dup (0, 4)
	6533 bipush (0, 4)
	6535 getstatic (0, 4)
	6538 aastore (0, 4)
	6539 dup (0, 4)
	6540 bipush (0, 4)
	6542 getstatic (0, 4)
	6545 aastore (0, 4)
	6546 dup (0, 4)
	6547 bipush (0, 4)
	6549 getstatic (0, 4)
	6552 aastore (0, 4)
	6553 dup (0, 4)
	6554 bipush (0, 4)
	6556 getstatic (0, 4)
	6559 aastore (0, 4)
	6560 dup (0, 4)
	6561 bipush (0, 4)
	6563 getstatic (0, 4)
	6566 aastore (0, 4)
	6567 dup (0, 4)
	6568 bipush (0, 4)
	6570 getstatic (0, 4)
	6573 aastore (0, 4)
	6574 dup (0, 4)
	6575 bipush (0, 4)
	6577 getstatic (0, 4)
	6580 aastore (0, 4)
	6581 dup (0, 4)
	6582 bipush (0, 4)
	6584 getstatic (0, 4)
	6587 aastore (0, 4)
	6588 dup (0, 4)
	6589 bipush (0, 4)
	6591 getstatic (0, 4)
	6594 aastore (0, 4)
	6595 dup (0, 4)
	6596 bipush (0, 4)
	6598 getstatic (0, 4)
	6601 aastore (0, 4)
	6602 dup (0, 4)
	6603 bipush (0, 4)
	6605 getstatic (0, 4)
	6608 aastore (0, 4)
	6609 dup (0, 4)
	6610 bipush (0, 4)
	6612 getstatic (0, 4)
	6615 aastore (0, 4)
	6616 dup (0, 4)
	6617 bipush (0, 4)
	6619 getstatic (0, 4)
	6622 aastore (0, 4)
	6623 dup (0, 4)
	6624 bipush (0, 4)
	6626 getstatic (0, 4)
	6629 aastore (0, 4)
	6630 dup (0, 4)
	6631 bipush (0, 4)
	6633 getstatic (0, 4)
	6636 aastore (0, 4)
	6637 dup (0, 4)
	6638 bipush (0, 4)
	6640 getstatic (0, 4)
	6643 aastore (0, 4)
	6644 dup (0, 4)
	6645 bipush (0, 4)
	6647 getstatic (0, 4)
	6650 aastore (0, 4)
	6651 dup (0, 4)
	6652 bipush (0, 4)
	6654 getstatic (0, 4)
	6657 aastore (0, 4)
	6658 dup (0, 4)
	6659 bipush (0, 4)
	6661 getstatic (0, 4)
	6664 aastore (0, 4)
	6665 dup (0, 4)
	6666 bipush (0, 4)
	6668 getstatic (0, 4)
	6671 aastore (0, 4)
	6672 dup (0, 4)
	6673 bipush (0, 4)
	6675 getstatic (0, 4)
	6678 aastore (0, 4)
	6679 dup (0, 4)
	6680 bipush (0, 4)
	6682 getstatic (0, 4)
	6685 aastore (0, 4)
	6686 dup (0, 4)
	6687 bipush (0, 4)
	6689 getstatic (0, 4)
	6692 aastore (0, 4)
	6693 dup (0, 4)
	6694 bipush (0, 4)
	6696 getstatic (0, 4)
	6699 aastore (0, 4)
	6700 dup (0, 4)
	6701 bipush (0, 4)
	6703 getstatic (0, 4)
	6706 aastore (0, 4)
	6707 dup (0, 4)
	6708 bipush (0, 4)
	6710 getstatic (0, 4)
	6713 aastore (0, 4)
	6714 dup (0, 4)
	6715 bipush (0, 4)
	6717 getstatic (0, 4)
	6720 aastore (0, 4)
	6721 dup (0, 4)
	6722 bipush (0, 4)
	6724 getstatic (0, 4)
	6727 aastore (0, 4)
	6728 dup (0, 4)
	6729 bipush (0, 4)
	6731 getstatic (0, 4)
	6734 aastore (0, 4)
	6735 dup (0, 4)
	6736 bipush (0, 4)
	6738 getstatic (0, 4)
	6741 aastore (0, 4)
	6742 dup (0, 4)
	6743 bipush (0, 4)
	6745 getstatic (0, 4)
	6748 aastore (0, 4)
	6749 dup (0, 4)
	6750 bipush (0, 4)
	6752 getstatic (0, 4)
	6755 aastore (0, 4)
	6756 dup (0, 4)
	6757 bipush (0, 4)
	6759 getstatic (0, 4)
	6762 aastore (0, 4)
	6763 dup (0, 4)
	6764 bipush (0, 4)
	6766 getstatic (0, 4)
	6769 aastore (0, 4)
	6770 dup (0, 4)
	6771 bipush (0, 4)
	6773 getstatic (0, 4)
	6776 aastore (0, 4)
	6777 dup (0, 4)
	6778 bipush (0, 4)
	6780 getstatic (0, 4)
	6783 aastore (0, 4)
	6784 dup (0, 4)
	6785 bipush (0, 4)
	6787 getstatic (0, 4)
	6790 aastore (0, 4)
	6791 dup (0, 4)
	6792 bipush (0, 4)
	6794 getstatic (0, 4)
	6797 aastore (0, 4)
	6798 dup (0, 4)
	6799 bipush (0, 4)
	6801 getstatic (0, 4)
	6804 aastore (0, 4)
	6805 dup (0, 4)
	6806 bipush (0, 4)
	6808 getstatic (0, 4)
	6811 aastore (0, 4)
	6812 dup (0, 4)
	6813 bipush (0, 4)
	6815 getstatic (0, 4)
	6818 aastore (0, 4)
	6819 dup (0, 4)
	6820 bipush (0, 4)
	6822 getstatic (0, 4)
	6825 aastore (0, 4)
	6826 dup (0, 4)
	6827 bipush (0, 4)
	6829 getstatic (0, 4)
	6832 aastore (0, 4)
	6833 dup (0, 4)
	6834 bipush (0, 4)
	6836 getstatic (0, 4)
	6839 aastore (0, 4)
	6840 dup (0, 4)
	6841 sipush (0, 4)
	6844 getstatic (0, 4)
	6847 aastore (0, 4)
	6848 dup (0, 4)
	6849 sipush (0, 4)
	6852 getstatic (0, 4)
	6855 aastore (0, 4)
	6856 dup (0, 4)
	6857 sipush (0, 4)
	6860 getstatic (0, 4)
	6863 aastore (0, 4)
	6864 dup (0, 4)
	6865 sipush (0, 4)
	6868 getstatic (0, 4)
	6871 aastore (0, 4)
	6872 dup (0, 4)
	6873 sipush (0, 4)
	6876 getstatic (0, 4)
	6879 aastore (0, 4)
	6880 dup (0, 4)
	6881 sipush (0, 4)
	6884 getstatic (0, 4)
	6887 aastore (0, 4)
	6888 dup (0, 4)
	6889 sipush (0, 4)
	6892 getstatic (0, 4)
	6895 aastore (0, 4)
	6896 dup (0, 4)
	6897 sipush (0, 4)
	6900 getstatic (0, 4)
	6903 aastore (0, 4)
	6904 dup (0, 4)
	6905 sipush (0, 4)
	6908 getstatic (0, 4)
	6911 aastore (0, 4)
	6912 dup (0, 4)
	6913 sipush (0, 4)
	6916 getstatic (0, 4)
	6919 aastore (0, 4)
	6920 dup (0, 4)
	6921 sipush (0, 4)
	6924 getstatic (0, 4)
	6927 aastore (0, 4)
	6928 dup (0, 4)
	6929 sipush (0, 4)
	6932 getstatic (0, 4)
	6935 aastore (0, 4)
	6936 dup (0, 4)
	6937 sipush (0, 4)
	6940 getstatic (0, 4)
	6943 aastore (0, 4)
	6944 dup (0, 4)
	6945 sipush (0, 4)
	6948 getstatic (0, 4)
	6951 aastore (0, 4)
	6952 dup (0, 4)
	6953 sipush (0, 4)
	6956 getstatic (0, 4)
	6959 aastore (0, 4)
	6960 dup (0, 4)
	6961 sipush (0, 4)
	6964 getstatic (0, 4)
	6967 aastore (0, 4)
	6968 dup (0, 4)
	6969 sipush (0, 4)
	6972 getstatic (0, 4)
	6975 aastore (0, 4)
	6976 dup (0, 4)
	6977 sipush (0, 4)
	6980 getstatic (0, 4)
	6983 aastore (0, 4)
	6984 dup (0, 4)
	6985 sipush (0, 4)
	6988 getstatic (0, 4)
	6991 aastore (0, 4)
	6992 dup (0, 4)
	6993 sipush (0, 4)
	6996 getstatic (0, 4)
	6999 aastore (0, 4)
	7000 dup (0, 4)
	7001 sipush (0, 4)
	7004 getstatic (0, 4)
	7007 aastore (0, 4)
	7008 dup (0, 4)
	7009 sipush (0, 4)
	7012 getstatic (0, 4)
	7015 aastore (0, 4)
	7016 dup (0, 4)
	7017 sipush (0, 4)
	7020 getstatic (0, 4)
	7023 aastore (0, 4)
	7024 dup (0, 4)
	7025 sipush (0, 4)
	7028 getstatic (0, 4)
	7031 aastore (0, 4)
	7032 dup (0, 4)
	7033 sipush (0, 4)
	7036 getstatic (0, 4)
	7039 aastore (0, 4)
	7040 dup (0, 4)
	7041 sipush (0, 4)
	7044 getstatic (0, 4)
	7047 aastore (0, 4)
	7048 dup (0, 4)
	7049 sipush (0, 4)
	7052 getstatic (0, 4)
	7055 aastore (0, 4)
	7056 dup (0, 4)
	7057 sipush (0, 4)
	7060 getstatic (0, 4)
	7063 aastore (0, 4)
	7064 dup (0, 4)
	7065 sipush (0, 4)
	7068 getstatic (0, 4)
	7071 aastore (0, 4)
	7072 dup (0, 4)
	7073 sipush (0, 4)
	7076 getstatic (0, 4)
	7079 aastore (0, 4)
	7080 dup (0, 4)
	7081 sipush (0, 4)
	7084 getstatic (0, 4)
	7087 aastore (0, 4)
	7088 dup (0, 4)
	7089 sipush (0, 4)
	7092 getstatic (0, 4)
	7095 aastore (0, 4)
	7096 dup (0, 4)
	7097 sipush (0, 4)
	7100 getstatic (0, 4)
	7103 aastore (0, 4)
	7104 dup (0, 4)
	7105 sipush (0, 4)
	7108 getstatic (0, 4)
	7111 aastore (0, 4)
	7112 dup (0, 4)
	7113 sipush (0, 4)
	7116 getstatic (0, 4)
	7119 aastore (0, 4)
	7120 dup (0, 4)
	7121 sipush (0, 4)
	7124 getstatic (0, 4)
	7127 aastore (0, 4)
	7128 dup (0, 4)
	7129 sipush (0, 4)
	7132 getstatic (0, 4)
	7135 aastore (0, 4)
	7136 dup (0, 4)
	7137 sipush (0, 4)
	7140 getstatic (0, 4)
	7143 aastore (0, 4)
	7144 dup (0, 4)
	7145 sipush (0, 4)
	7148 getstatic (0, 4)
	7151 aastore (0, 4)
	7152 dup (0, 4)
	7153 sipush (0, 4)
	7156 getstatic (0, 4)
	7159 aastore (0, 4)
	7160 dup (0, 4)
	7161 sipush (0, 4)
	7164 getstatic (0, 4)
	7167 aastore (0, 4)
	7168 dup (0, 4)
	7169 sipush (0, 4)
	7172 getstatic (0, 4)
	7175 aastore (0, 4)
	7176 dup (0, 4)
	7177 sipush (0, 4)
	7180 getstatic (0, 4)
	7183 aastore (0, 4)
	7184 dup (0, 4)
	7185 sipush (0, 4)
	7188 getstatic (0, 4)
	7191 aastore (0, 4)
	7192 dup (0, 4)
	7193 sipush (0, 4)
	7196 getstatic (0, 4)
	7199 aastore (0, 4)
	7200 dup (0, 4)
	7201 sipush (0, 4)
	7204 getstatic (0, 4)
	7207 aastore (0, 4)
	7208 dup (0, 4)
	7209 sipush (0, 4)
	7212 getstatic (0, 4)
	7215 aastore (0, 4)
	7216 dup (0, 4)
	7217 sipush (0, 4)
	7220 getstatic (0, 4)
	7223 aastore (0, 4)
	7224 dup (0, 4)
	7225 sipush (0, 4)
	7228 getstatic (0, 4)
	7231 aastore (0, 4)
	7232 dup (0, 4)
	7233 sipush (0, 4)
	7236 getstatic (0, 4)
	7239 aastore (0, 4)
	7240 dup (0, 4)
	7241 sipush (0, 4)
	7244 getstatic (0, 4)
	7247 aastore (0, 4)
	7248 dup (0, 4)
	7249 sipush (0, 4)
	7252 getstatic (0, 4)
	7255 aastore (0, 4)
	7256 dup (0, 4)
	7257 sipush (0, 4)
	7260 getstatic (0, 4)
	7263 aastore (0, 4)
	7264 dup (0, 4)
	7265 sipush (0, 4)
	7268 getstatic (0, 4)
	7271 aastore (0, 4)
	7272 dup (0, 4)
	7273 sipush (0, 4)
	7276 getstatic (0, 4)
	7279 aastore (0, 4)
	7280 dup (0, 4)
	7281 sipush (0, 4)
	7284 getstatic (0, 4)
	7287 aastore (0, 4)
	7288 dup (0, 4)
	7289 sipush (0, 4)
	7292 getstatic (0, 4)
	7295 aastore (0, 4)
	7296 dup (0, 4)
	7297 sipush (0, 4)
	7300 getstatic (0, 4)
	7303 aastore (0, 4)
	7304 dup (0, 4)
	7305 sipush (0, 4)
	7308 getstatic (0, 4)
	7311 aastore (0, 4)
	7312 dup (0, 4)
	7313 sipush (0, 4)
	7316 getstatic (0, 4)
	7319 aastore (0, 4)
	7320 dup (0, 4)
	7321 sipush (0, 4)
	7324 getstatic (0, 4)
	7327 aastore (0, 4)
	7328 dup (0, 4)
	7329 sipush (0, 4)
	7332 getstatic (0, 4)
	7335 aastore (0, 4)
	7336 dup (0, 4)
	7337 sipush (0, 4)
	7340 getstatic (0, 4)
	7343 aastore (0, 4)
	7344 dup (0, 4)
	7345 sipush (0, 4)
	7348 getstatic (0, 4)
	7351 aastore (0, 4)
	7352 dup (0, 4)
	7353 sipush (0, 4)
	7356 getstatic (0, 4)
	7359 aastore (0, 4)
	7360 dup (0, 4)
	7361 sipush (0, 4)
	7364 getstatic (0, 4)
	7367 aastore (0, 4)
	7368 dup (0, 4)
	7369 sipush (0, 4)
	7372 getstatic (0, 4)
	7375 aastore (0, 4)
	7376 dup (0, 4)
	7377 sipush (0, 4)
	7380 getstatic (0, 4)
	7383 aastore (0, 4)
	7384 dup (0, 4)
	7385 sipush (0, 4)
	7388 getstatic (0, 4)
	7391 aastore (0, 4)
	7392 dup (0, 4)
	7393 sipush (0, 4)
	7396 getstatic (0, 4)
	7399 aastore (0, 4)
	7400 dup (0, 4)
	7401 sipush (0, 4)
	7404 getstatic (0, 4)
	7407 aastore (0, 4)
	7408 dup (0, 4)
	7409 sipush (0, 4)
	7412 getstatic (0, 4)
	7415 aastore (0, 4)
	7416 dup (0, 4)
	7417 sipush (0, 4)
	7420 getstatic (0, 4)
	7423 aastore (0, 4)
	7424 dup (0, 4)
	7425 sipush (0, 4)
	7428 getstatic (0, 4)
	7431 aastore (0, 4)
	7432 dup (0, 4)
	7433 sipush (0, 4)
	7436 getstatic (0, 4)
	7439 aastore (0, 4)
	7440 dup (0, 4)
	7441 sipush (0, 4)
	7444 getstatic (0, 4)
	7447 aastore (0, 4)
	7448 dup (0, 4)
	7449 sipush (0, 4)
	7452 getstatic (0, 4)
	7455 aastore (0, 4)
	7456 dup (0, 4)
	7457 sipush (0, 4)
	7460 getstatic (0, 4)
	7463 aastore (0, 4)
	7464 dup (0, 4)
	7465 sipush (0, 4)
	7468 getstatic (0, 4)
	7471 aastore (0, 4)
	7472 dup (0, 4)
	7473 sipush (0, 4)
	7476 getstatic (0, 4)
	7479 aastore (0, 4)
	7480 dup (0, 4)
	7481 sipush (0, 4)
	7484 getstatic (0, 4)
	7487 aastore (0, 4)
	7488 dup (0, 4)
	7489 sipush (0, 4)
	7492 getstatic (0, 4)
	7495 aastore (0, 4)
	7496 dup (0, 4)
	7497 sipush (0, 4)
	7500 getstatic (0, 4)
	7503 aastore (0, 4)
	7504 dup (0, 4)
	7505 sipush (0, 4)
	7508 getstatic (0, 4)
	7511 aastore (0, 4)
	7512 dup (0, 4)
	7513 sipush (0, 4)
	7516 getstatic (0, 4)
	7519 aastore (0, 4)
	7520 dup (0, 4)
	7521 sipush (0, 4)
	7524 getstatic (0, 4)
	7527 aastore (0, 4)
	7528 dup (0, 4)
	7529 sipush (0, 4)
	7532 getstatic (0, 4)
	7535 aastore (0, 4)
	7536 dup (0, 4)
	7537 sipush (0, 4)
	7540 getstatic (0, 4)
	7543 aastore (0, 4)
	7544 dup (0, 4)
	7545 sipush (0, 4)
	7548 getstatic (0, 4)
	7551 aastore (0, 4)
	7552 dup (0, 4)
	7553 sipush (0, 4)
	7556 getstatic (0, 4)
	7559 aastore (0, 4)
	7560 dup (0, 4)
	7561 sipush (0, 4)
	7564 getstatic (0, 4)
	7567 aastore (0, 4)
	7568 dup (0, 4)
	7569 sipush (0, 4)
	7572 getstatic (0, 4)
	7575 aastore (0, 4)
	7576 dup (0, 4)
	7577 sipush (0, 4)
	7580 getstatic (0, 4)
	7583 aastore (0, 4)
	7584 dup (0, 4)
	7585 sipush (0, 4)
	7588 getstatic (0, 4)
	7591 aastore (0, 4)
	7592 dup (0, 4)
	7593 sipush (0, 4)
	7596 getstatic (0, 4)
	7599 aastore (0, 4)
	7600 dup (0, 4)
	7601 sipush (0, 4)
	7604 getstatic (0, 4)
	7607 aastore (0, 4)
	7608 dup (0, 4)
	7609 sipush (0, 4)
	7612 getstatic (0, 4)
	7615 aastore (0, 4)
	7616 dup (0, 4)
	7617 sipush (0, 4)
	7620 getstatic (0, 4)
	7623 aastore (0, 4)
	7624 dup (0, 4)
	7625 sipush (0, 4)
	7628 getstatic (0, 4)
	7631 aastore (0, 4)
	7632 dup (0, 4)
	7633 sipush (0, 4)
	7636 getstatic (0, 4)
	7639 aastore (0, 4)
	7640 dup (0, 4)
	7641 sipush (0, 4)
	7644 getstatic (0, 4)
	7647 aastore (0, 4)
	7648 dup (0, 4)
	7649 sipush (0, 4)
	7652 getstatic (0, 4)
	7655 aastore (0, 4)
	7656 dup (0, 4)
	7657 sipush (0, 4)
	7660 getstatic (0, 4)
	7663 aastore (0, 4)
	7664 dup (0, 4)
	7665 sipush (0, 4)
	7668 getstatic (0, 4)
	7671 aastore (0, 4)
	7672 dup (0, 4)
	7673 sipush (0, 4)
	7676 getstatic (0, 4)
	7679 aastore (0, 4)
	7680 dup (0, 4)
	7681 sipush (0, 4)
	7684 getstatic (0, 4)
	7687 aastore (0, 4)
	7688 dup (0, 4)
	7689 sipush (0, 4)
	7692 getstatic (0, 4)
	7695 aastore (0, 4)
	7696 dup (0, 4)
	7697 sipush (0, 4)
	7700 getstatic (0, 4)
	7703 aastore (0, 4)
	7704 dup (0, 4)
	7705 sipush (0, 4)
	7708 getstatic (0, 4)
	7711 aastore (0, 4)
	7712 dup (0, 4)
	7713 sipush (0, 4)
	7716 getstatic (0, 4)
	7719 aastore (0, 4)
	7720 dup (0, 4)
	7721 sipush (0, 4)
	7724 getstatic (0, 4)
	7727 aastore (0, 4)
	7728 dup (0, 4)
	7729 sipush (0, 4)
	7732 getstatic (0, 4)
	7735 aastore (0, 4)
	7736 dup (0, 4)
	7737 sipush (0, 4)
	7740 getstatic (0, 4)
	7743 aastore (0, 4)
	7744 dup (0, 4)
	7745 sipush (0, 4)
	7748 getstatic (0, 4)
	7751 aastore (0, 4)
	7752 dup (0, 4)
	7753 sipush (0, 4)
	7756 getstatic (0, 4)
	7759 aastore (0, 4)
	7760 dup (0, 4)
	7761 sipush (0, 4)
	7764 getstatic (0, 4)
	7767 aastore (0, 4)
	7768 dup (0, 4)
	7769 sipush (0, 4)
	7772 getstatic (0, 4)
	7775 aastore (0, 4)
	7776 dup (0, 4)
	7777 sipush (0, 4)
	7780 getstatic (0, 4)
	7783 aastore (0, 4)
	7784 dup (0, 4)
	7785 sipush (0, 4)
	7788 getstatic (0, 4)
	7791 aastore (0, 4)
	7792 dup (0, 4)
	7793 sipush (0, 4)
	7796 getstatic (0, 4)
	7799 aastore (0, 4)
	7800 dup (0, 4)
	7801 sipush (0, 4)
	7804 getstatic (0, 4)
	7807 aastore (0, 4)
	7808 dup (0, 4)
	7809 sipush (0, 4)
	7812 getstatic (0, 4)
	7815 aastore (0, 4)
	7816 dup (0, 4)
	7817 sipush (0, 4)
	7820 getstatic (0, 4)
	7823 aastore (0, 4)
	7824 dup (0, 4)
	7825 sipush (0, 4)
	7828 getstatic (0, 4)
	7831 aastore (0, 4)
	7832 dup (0, 4)
	7833 sipush (0, 4)
	7836 getstatic (0, 4)
	7839 aastore (0, 4)
	7840 dup (0, 4)
	7841 sipush (0, 4)
	7844 getstatic (0, 4)
	7847 aastore (0, 4)
	7848 dup (0, 4)
	7849 sipush (0, 4)
	7852 getstatic (0, 4)
	7855 aastore (0, 4)
	7856 dup (0, 4)
	7857 sipush (0, 4)
	7860 getstatic (0, 4)
	7863 aastore (0, 4)
	7864 dup (0, 4)
	7865 sipush (0, 4)
	7868 getstatic (0, 4)
	7871 aastore (0, 4)
	7872 dup (0, 4)
	7873 sipush (0, 4)
	7876 getstatic (0, 4)
	7879 aastore (0, 4)
	7880 dup (0, 4)
	7881 sipush (0, 4)
	7884 getstatic (0, 4)
	7887 aastore (0, 4)
	7888 dup (0, 4)
	7889 sipush (0, 4)
	7892 getstatic (0, 4)
	7895 aastore (0, 4)
	7896 dup (0, 4)
	7897 sipush (0, 4)
	7900 getstatic (0, 4)
	7903 aastore (0, 4)
	7904 dup (0, 4)
	7905 sipush (0, 4)
	7908 getstatic (0, 4)
	7911 aastore (0, 4)
	7912 dup (0, 4)
	7913 sipush (0, 4)
	7916 getstatic (0, 4)
	7919 aastore (0, 4)
	7920 dup (0, 4)
	7921 sipush (0, 4)
	7924 getstatic (0, 4)
	7927 aastore (0, 4)
	7928 dup (0, 4)
	7929 sipush (0, 4)
	7932 getstatic (0, 4)
	7935 aastore (0, 4)
	7936 dup (0, 4)
	7937 sipush (0, 4)
	7940 getstatic (0, 4)
	7943 aastore (0, 4)
	7944 dup (0, 4)
	7945 sipush (0, 4)
	7948 getstatic (0, 4)
	7951 aastore (0, 4)
	7952 dup (0, 4)
	7953 sipush (0, 4)
	7956 getstatic (0, 4)
	7959 aastore (0, 4)
	7960 dup (0, 4)
	7961 sipush (0, 4)
	7964 getstatic (0, 4)
	7967 aastore (0, 4)
	7968 dup (0, 4)
	7969 sipush (0, 4)
	7972 getstatic (0, 4)
	7975 aastore (0, 4)
	7976 dup (0, 4)
	7977 sipush (0, 4)
	7980 getstatic (0, 4)
	7983 aastore (0, 4)
	7984 dup (0, 4)
	7985 sipush (0, 4)
	7988 getstatic (0, 4)
	7991 aastore (0, 4)
	7992 dup (0, 4)
	7993 sipush (0, 4)
	7996 getstatic (0, 4)
	7999 aastore (0, 4)
	8000 dup (0, 4)
	8001 sipush (0, 4)
	8004 getstatic (0, 4)
	8007 aastore (0, 4)
	8008 dup (0, 4)
	8009 sipush (0, 4)
	8012 getstatic (0, 4)
	8015 aastore (0, 4)
	8016 dup (0, 4)
	8017 sipush (0, 4)
	8020 getstatic (0, 4)
	8023 aastore (0, 4)
	8024 dup (0, 4)
	8025 sipush (0, 4)
	8028 getstatic (0, 4)
	8031 aastore (0, 4)
	8032 dup (0, 4)
	8033 sipush (0, 4)
	8036 getstatic (0, 4)
	8039 aastore (0, 4)
	8040 dup (0, 4)
	8041 sipush (0, 4)
	8044 getstatic (0, 4)
	8047 aastore (0, 4)
	8048 dup (0, 4)
	8049 sipush (0, 4)
	8052 getstatic (0, 4)
	8055 aastore (0, 4)
	8056 dup (0, 4)
	8057 sipush (0, 4)
	8060 getstatic (0, 4)
	8063 aastore (0, 4)
	8064 dup (0, 4)
	8065 sipush (0, 4)
	8068 getstatic (0, 4)
	8071 aastore (0, 4)
	8072 dup (0, 4)
	8073 sipush (0, 4)
	8076 getstatic (0, 4)
	8079 aastore (0, 4)
	8080 dup (0, 4)
	8081 sipush (0, 4)
	8084 getstatic (0, 4)
	8087 aastore (0, 4)
	8088 dup (0, 4)
	8089 sipush (0, 4)
	8092 getstatic (0, 4)
	8095 aastore (0, 4)
	8096 dup (0, 4)
	8097 sipush (0, 4)
	8100 getstatic (0, 4)
	8103 aastore (0, 4)
	8104 dup (0, 4)
	8105 sipush (0, 4)
	8108 getstatic (0, 4)
	8111 aastore (0, 4)
	8112 dup (0, 4)
	8113 sipush (0, 4)
	8116 getstatic (0, 4)
	8119 aastore (0, 4)
	8120 dup (0, 4)
	8121 sipush (0, 4)
	8124 getstatic (0, 4)
	8127 aastore (0, 4)
	8128 dup (0, 4)
	8129 sipush (0, 4)
	8132 getstatic (0, 4)
	8135 aastore (0, 4)
	8136 dup (0, 4)
	8137 sipush (0, 4)
	8140 getstatic (0, 4)
	8143 aastore (0, 4)
	8144 dup (0, 4)
	8145 sipush (0, 4)
	8148 getstatic (0, 4)
	8151 aastore (0, 4)
	8152 dup (0, 4)
	8153 sipush (0, 4)
	8156 getstatic (0, 4)
	8159 aastore (0, 4)
	8160 dup (0, 4)
	8161 sipush (0, 4)
	8164 getstatic (0, 4)
	8167 aastore (0, 4)
	8168 dup (0, 4)
	8169 sipush (0, 4)
	8172 getstatic (0, 4)
	8175 aastore (0, 4)
	8176 dup (0, 4)
	8177 sipush (0, 4)
	8180 getstatic (0, 4)
	8183 aastore (0, 4)
	8184 dup (0, 4)
	8185 sipush (0, 4)
	8188 getstatic (0, 4)
	8191 aastore (0, 4)
	8192 dup (0, 4)
	8193 sipush (0, 4)
	8196 getstatic (0, 4)
	8199 aastore (0, 4)
	8200 dup (0, 4)
	8201 sipush (0, 4)
	8204 getstatic (0, 4)
	8207 aastore (0, 4)
	8208 dup (0, 4)
	8209 sipush (0, 4)
	8212 getstatic (0, 4)
	8215 aastore (0, 4)
	8216 dup (0, 4)
	8217 sipush (0, 4)
	8220 getstatic (0, 4)
	8223 aastore (0, 4)
	8224 dup (0, 4)
	8225 sipush (0, 4)
	8228 getstatic (0, 4)
	8231 aastore (0, 4)
	8232 dup (0, 4)
	8233 sipush (0, 4)
	8236 getstatic (0, 4)
	8239 aastore (0, 4)
	8240 dup (0, 4)
	8241 sipush (0, 4)
	8244 getstatic (0, 4)
	8247 aastore (0, 4)
	8248 dup (0, 4)
	8249 sipush (0, 4)
	8252 getstatic (0, 4)
	8255 aastore (0, 4)
	8256 dup (0, 4)
	8257 sipush (0, 4)
	8260 getstatic (0, 4)
	8263 aastore (0, 4)
	8264 dup (0, 4)
	8265 sipush (0, 4)
	8268 getstatic (0, 4)
	8271 aastore (0, 4)
	8272 dup (0, 4)
	8273 sipush (0, 4)
	8276 getstatic (0, 4)
	8279 aastore (0, 4)
	8280 dup (0, 4)
	8281 sipush (0, 4)
	8284 getstatic (0, 4)
	8287 aastore (0, 4)
	8288 dup (0, 4)
	8289 sipush (0, 4)
	8292 getstatic (0, 4)
	8295 aastore (0, 4)
	8296 dup (0, 4)
	8297 sipush (0, 4)
	8300 getstatic (0, 4)
	8303 aastore (0, 4)
	8304 dup (0, 4)
	8305 sipush (0, 4)
	8308 getstatic (0, 4)
	8311 aastore (0, 4)
	8312 dup (0, 4)
	8313 sipush (0, 4)
	8316 getstatic (0, 4)
	8319 aastore (0, 4)
	8320 dup (0, 4)
	8321 sipush (0, 4)
	8324 getstatic (0, 4)
	8327 aastore (0, 4)
	8328 dup (0, 4)
	8329 sipush (0, 4)
	8332 getstatic (0, 4)
	8335 aastore (0, 4)
	8336 dup (0, 4)
	8337 sipush (0, 4)
	8340 getstatic (0, 4)
	8343 aastore (0, 4)
	8344 dup (0, 4)
	8345 sipush (0, 4)
	8348 getstatic (0, 4)
	8351 aastore (0, 4)
	8352 dup (0, 4)
	8353 sipush (0, 4)
	8356 getstatic (0, 4)
	8359 aastore (0, 4)
	8360 dup (0, 4)
	8361 sipush (0, 4)
	8364 getstatic (0, 4)
	8367 aastore (0, 4)
	8368 dup (0, 4)
	8369 sipush (0, 4)
	8372 getstatic (0, 4)
	8375 aastore (0, 4)
	8376 dup (0, 4)
	8377 sipush (0, 4)
	8380 getstatic (0, 4)
	8383 aastore (0, 4)
	8384 dup (0, 4)
	8385 sipush (0, 4)
	8388 getstatic (0, 4)
	8391 aastore (0, 4)
	8392 dup (0, 4)
	8393 sipush (0, 4)
	8396 getstatic (0, 4)
	8399 aastore (0, 4)
	8400 dup (0, 4)
	8401 sipush (0, 4)
	8404 getstatic (0, 4)
	8407 aastore (0, 4)
	8408 dup (0, 4)
	8409 sipush (0, 4)
	8412 getstatic (0, 4)
	8415 aastore (0, 4)
	8416 dup (0, 4)
	8417 sipush (0, 4)
	8420 getstatic (0, 4)
	8423 aastore (0, 4)
	8424 dup (0, 4)
	8425 sipush (0, 4)
	8428 getstatic (0, 4)
	8431 aastore (0, 4)
	8432 dup (0, 4)
	8433 sipush (0, 4)
	8436 getstatic (0, 4)
	8439 aastore (0, 4)
	8440 putstatic (0, 4)
	8443 return (0, 4)

