Method: <init>
	0 aload_0 (0, 0)
	1 invokespecial (0, 0)
	2 org/apache/commons/math3/optimization/linear/AbstractLinearOptimizer.<init>:()V (0, 0)
	4 aload_0 (0, 0)
	5 dload_1 (0, 0)
	6 putfield (0, 0)
	7 org/apache/commons/math3/optimization/linear/SimplexSolver.epsilon:D (0, 0)
	9 aload_0 (0, 0)
	10 iload_3 (0, 0)
	11 putfield (0, 0)
	12 org/apache/commons/math3/optimization/linear/SimplexSolver.maxUlps:I (0, 0)
	14 return (0, 0)

Method: getPivotColumn
	0 dconst_0 (0, 0)
	1 dstore_2 (0, 0)
	2 aconst_null (0, 0)
	3 astore (0, 0)
	4 #4 (0, 0)
	5 aload_1 (1, 4)
	6 invokevirtual (1, 4)
	7 org/apache/commons/math3/optimization/linear/SimplexTableau.getNumObjectiveFunctions:()I (1, 4)
	9 istore (1, 4)
	10 #5 (1, 4)
	11 iload (1, 4)
	12 #5 (1, 4)
	13 aload_1 (1, 4)
	14 invokevirtual (1, 4)
	15 org/apache/commons/math3/optimization/linear/SimplexTableau.getWidth:()I (1, 4)
	17 iconst_1 (1, 4)
	18 isub (1, 4)
	19 if_icmpge (1, 4)
	20 35 (1, 4)
	22 aload_1 (1, 4)
	23 iconst_0 (1, 4)
	24 iload (1, 4)
	25 #5 (1, 4)
	26 invokevirtual (1, 4)
	27 org/apache/commons/math3/optimization/linear/SimplexTableau.getEntry:(II)D (1, 4)
	29 dstore (1, 4)
	30 #6 (1, 4)
	31 dload (3, 1)
	32 #6 (3, 1)
	33 dload_2 (3, 1)
	34 dcmpg (3, 1)
	35 ifge (3, 1)
	36 13 (3, 1)
	38 dload (3, 1)
	39 #6 (3, 1)
	40 dstore_2 (3, 1)
	41 iload (3, 1)
	42 #5 (3, 1)
	43 invokestatic (3, 1)
	44 java/lang/Integer.valueOf:(I)Ljava/lang/Integer; (3, 1)
	46 astore (3, 1)
	47 #4 (3, 1)
	48 iinc (3, 1)
	49 #5 (3, 1)
	50 -89 (3, 1)
	51 goto (3, 1)
	52 -40 (3, 1)
	54 aload (2, 1)
	55 #4 (2, 1)
	56 areturn (1, 1)

Method: getPivotRow
	0 new (0, 0)
	1 java/util/ArrayList (0, 0)
	3 dup (0, 0)
	4 invokespecial (0, 0)
	5 java/util/ArrayList.<init>:()V (0, 0)
	7 astore_3 (0, 0)
	8 ldc2_w (0, 0)
	9 1.7976931348623157e+308 (0, 0)
	11 dstore (0, 0)
	12 #4 (0, 0)
	13 aload_1 (1, 4)
	14 invokevirtual (1, 4)
	15 org/apache/commons/math3/optimization/linear/SimplexTableau.getNumObjectiveFunctions:()I (1, 4)
	17 istore (1, 4)
	18 #6 (1, 4)
	19 iload (1, 4)
	20 #6 (1, 4)
	21 aload_1 (1, 4)
	22 invokevirtual (1, 4)
	23 org/apache/commons/math3/optimization/linear/SimplexTableau.getHeight:()I (1, 4)
	25 if_icmpge (1, 4)
	26 110 (1, 4)
	28 aload_1 (1, 4)
	29 iload (1, 4)
	30 #6 (1, 4)
	31 aload_1 (1, 4)
	32 invokevirtual (1, 4)
	33 org/apache/commons/math3/optimization/linear/SimplexTableau.getWidth:()I (1, 4)
	35 iconst_1 (1, 4)
	36 isub (1, 4)
	37 invokevirtual (1, 4)
	38 org/apache/commons/math3/optimization/linear/SimplexTableau.getEntry:(II)D (1, 4)
	40 dstore (1, 4)
	41 #7 (1, 4)
	42 aload_1 (1, 4)
	43 iload (1, 4)
	44 #6 (1, 4)
	45 iload_2 (1, 4)
	46 invokevirtual (1, 4)
	47 org/apache/commons/math3/optimization/linear/SimplexTableau.getEntry:(II)D (1, 4)
	49 dstore (1, 4)
	50 #9 (1, 4)
	51 dload (2, 1)
	52 #9 (2, 1)
	53 dconst_0 (2, 1)
	54 aload_0 (2, 1)
	55 getfield (2, 1)
	56 org/apache/commons/math3/optimization/linear/SimplexSolver.maxUlps:I (2, 1)
	58 invokestatic (2, 1)
	59 org/apache/commons/math3/util/Precision.compareTo:(DDI)I (2, 1)
	61 ifle (2, 1)
	62 68 (2, 1)
	64 dload (2, 1)
	65 #7 (2, 1)
	66 dload (2, 1)
	67 #9 (2, 1)
	68 ddiv (2, 1)
	69 dstore (2, 1)
	70 #11 (2, 1)
	71 dload (3, 1)
	72 #11 (3, 1)
	73 dload (3, 1)
	74 #4 (3, 1)
	75 invokestatic (3, 1)
	76 java/lang/Double.compare:(DD)I (3, 1)
	78 istore (3, 1)
	79 #13 (3, 1)
	80 iload (4, 1)
	81 #13 (4, 1)
	82 ifne (4, 1)
	83 18 (4, 1)
	85 aload_3 (4, 1)
	86 iload (4, 1)
	87 #6 (4, 1)
	88 invokestatic (4, 1)
	89 java/lang/Integer.valueOf:(I)Ljava/lang/Integer; (4, 1)
	91 invokeinterface (4, 1)
	92 java/util/List.size:()I (4, 1)
	94 0 (4, 1)
	96 pop (4, 1)
	97 goto (4, 1)
	98 32 (4, 1)
	100 iload (5, 1)
	101 #13 (5, 1)
	102 ifge (5, 1)
	103 27 (5, 1)
	105 dload (5, 1)
	106 #11 (5, 1)
	107 dstore (5, 1)
	108 #4 (5, 1)
	109 new (5, 1)
	110 java/util/ArrayList (5, 1)
	112 dup (5, 1)
	113 invokespecial (5, 1)
	114 java/util/ArrayList.<init>:()V (5, 1)
	116 astore_3 (5, 1)
	117 aload_3 (5, 1)
	118 iload (5, 1)
	119 #6 (5, 1)
	120 invokestatic (5, 1)
	121 java/lang/Integer.valueOf:(I)Ljava/lang/Integer; (5, 1)
	123 invokeinterface (5, 1)
	124 java/util/List.size:()I (5, 1)
	126 0 (5, 1)
	128 pop (5, 1)
	129 iinc (5, 1)
	130 #6 (5, 1)
	131 -89 (5, 1)
	132 goto (5, 1)
	133 -113 (5, 1)
	135 aload_3 (4, 1)
	136 invokeinterface (4, 1)
	137 java/util/List.getNumArtificialVariables:()I (4, 1)
	139 0 (4, 1)
	141 ifne (4, 1)
	142 5 (4, 1)
	144 aconst_null (4, 1)
	145 areturn (4, 1)
	146 aload_3 (5, 1)
	147 invokeinterface (5, 1)
	148 java/util/List.getNumArtificialVariables:()I (5, 1)
	150 0 (5, 1)
	152 iconst_1 (5, 1)
	153 if_icmple (5, 1)
	154 250 (5, 1)
	156 aload_1 (7, 1)
	157 invokevirtual (7, 1)
	158 org/apache/commons/math3/optimization/linear/SimplexTableau.getNumArtificialVariables:()I (7, 1)
	160 ifle (7, 1)
	161 106 (7, 1)
	163 aload_3 (8, 4)
	164 invokeinterface (8, 4)
	165 java/util/List.java/util/Iterator (8, 4)
	167 0 (8, 4)
	169 astore (8, 4)
	170 #6 (8, 4)
	171 aload (8, 4)
	172 #6 (8, 4)
	173 invokeinterface (8, 4)
	174 java/util/Iterator.next:()Ljava/lang/Object; (8, 4)
	176 0 (8, 4)
	178 ifeq (8, 4)
	179 88 (8, 4)
	181 aload (8, 4)
	182 #6 (8, 4)
	183 invokeinterface (8, 4)
	184 java/util/Iterator.java/lang/Integer (8, 4)
	186 0 (8, 4)
	188 checkcast (8, 4)
	189 java/lang/Integer (8, 4)
	191 astore (8, 4)
	192 #7 (8, 4)
	193 iconst_0 (9, 1)
	194 istore (9, 1)
	195 #8 (9, 1)
	196 iload (9, 1)
	197 #8 (9, 1)
	198 aload_1 (9, 1)
	199 invokevirtual (9, 1)
	200 org/apache/commons/math3/optimization/linear/SimplexTableau.getNumArtificialVariables:()I (9, 1)
	202 if_icmpge (9, 1)
	203 61 (9, 1)
	205 iload (10, 1)
	206 #8 (10, 1)
	207 aload_1 (10, 1)
	208 invokevirtual (10, 1)
	209 org/apache/commons/math3/optimization/linear/SimplexTableau.getArtificialVariableOffset:()I (10, 1)
	211 iadd (10, 1)
	212 istore (10, 1)
	213 #9 (10, 1)
	214 aload_1 (10, 1)
	215 aload (10, 1)
	216 #7 (10, 1)
	217 invokevirtual (10, 1)
	218 java/lang/Integer.intValue:()I (10, 1)
	220 iload (10, 1)
	221 #9 (10, 1)
	222 invokevirtual (10, 1)
	223 org/apache/commons/math3/optimization/linear/SimplexTableau.getEntry:(II)D (10, 1)
	225 dstore (10, 1)
	226 #10 (10, 1)
	227 dload (11, 1)
	228 #10 (11, 1)
	229 dconst_1 (11, 1)
	230 aload_0 (11, 1)
	231 getfield (11, 1)
	232 org/apache/commons/math3/optimization/linear/SimplexSolver.maxUlps:I (11, 1)
	234 invokestatic (11, 1)
	235 org/apache/commons/math3/util/Precision.equals:(DDI)Z (11, 1)
	237 ifeq (11, 1)
	238 20 (11, 1)
	240 aload (11, 1)
	241 #7 (11, 1)
	242 aload_1 (11, 1)
	243 iload (11, 1)
	244 #9 (11, 1)
	245 invokevirtual (11, 1)
	246 org/apache/commons/math3/optimization/linear/SimplexTableau.getBasicRow:(I)Ljava/lang/Integer; (11, 1)
	248 invokevirtual (11, 1)
	249 java/lang/Integer.equals:(Ljava/lang/Object;)Z (11, 1)
	251 ifeq (11, 1)
	252 6 (11, 1)
	254 aload (11, 1)
	255 #7 (11, 1)
	256 areturn (11, 1)
	257 iinc (11, 1)
	258 #8 (11, 1)
	259 -89 (11, 1)
	260 goto (11, 1)
	261 -64 (11, 1)
	263 goto (8, 4)
	264 -92 (8, 4)
	266 aload_0 (12, 1)
	267 invokevirtual (12, 1)
	268 org/apache/commons/math3/optimization/linear/SimplexSolver.getIterations:()I (12, 1)
	270 aload_0 (12, 1)
	271 invokevirtual (12, 1)
	272 org/apache/commons/math3/optimization/linear/SimplexSolver.getMaxIterations:()I (12, 1)
	274 iconst_2 (12, 1)
	275 idiv (12, 1)
	276 if_icmpge (12, 1)
	277 127 (12, 1)
	279 aconst_null (12, 1)
	280 astore (12, 1)
	281 #6 (12, 1)
	282 aload_1 (12, 1)
	283 invokevirtual (12, 1)
	284 org/apache/commons/math3/optimization/linear/SimplexTableau.getWidth:()I (12, 1)
	286 istore (12, 1)
	287 #7 (12, 1)
	288 aload_1 (12, 1)
	289 invokevirtual (12, 1)
	290 org/apache/commons/math3/optimization/linear/SimplexTableau.getNumObjectiveFunctions:()I (12, 1)
	292 istore (12, 1)
	293 #8 (12, 1)
	294 aload_1 (12, 1)
	295 invokevirtual (12, 1)
	296 org/apache/commons/math3/optimization/linear/SimplexTableau.getWidth:()I (12, 1)
	298 iconst_1 (12, 1)
	299 isub (12, 1)
	300 istore (12, 1)
	301 #9 (12, 1)
	302 aload_3 (13, 4)
	303 invokeinterface (13, 4)
	304 java/util/List.java/util/Iterator (13, 4)
	306 0 (13, 4)
	308 astore (13, 4)
	309 #10 (13, 4)
	310 aload (13, 4)
	311 #10 (13, 4)
	312 invokeinterface (13, 4)
	313 java/util/Iterator.next:()Ljava/lang/Object; (13, 4)
	315 0 (13, 4)
	317 ifeq (13, 4)
	318 83 (13, 4)
	320 aload (13, 4)
	321 #10 (13, 4)
	322 invokeinterface (13, 4)
	323 java/util/Iterator.java/lang/Integer (13, 4)
	325 0 (13, 4)
	327 checkcast (13, 4)
	328 java/lang/Integer (13, 4)
	330 astore (13, 4)
	331 #11 (13, 4)
	332 iload (14, 4)
	333 #8 (14, 4)
	334 istore (14, 4)
	335 #12 (14, 4)
	336 iload (14, 4)
	337 #12 (14, 4)
	338 iload (14, 4)
	339 #9 (14, 4)
	340 if_icmpge (14, 4)
	341 57 (14, 4)
	343 aload (14, 4)
	344 #11 (14, 4)
	345 aload (14, 4)
	346 #6 (14, 4)
	347 invokevirtual (14, 4)
	348 java/lang/Integer.equals:(Ljava/lang/Object;)Z (14, 4)
	350 ifne (14, 4)
	351 47 (14, 4)
	353 aload_1 (14, 4)
	354 iload (14, 4)
	355 #12 (14, 4)
	356 invokevirtual (14, 4)
	357 org/apache/commons/math3/optimization/linear/SimplexTableau.getBasicRow:(I)Ljava/lang/Integer; (14, 4)
	359 astore (14, 4)
	360 #13 (14, 4)
	361 aload (15, 1)
	362 #13 (15, 1)
	363 ifnull (15, 1)
	364 28 (15, 1)
	366 aload (15, 1)
	367 #13 (15, 1)
	368 aload (15, 1)
	369 #11 (15, 1)
	370 invokevirtual (15, 1)
	371 java/lang/Integer.equals:(Ljava/lang/Object;)Z (15, 1)
	373 ifeq (15, 1)
	374 18 (15, 1)
	376 iload (15, 1)
	377 #12 (15, 1)
	378 iload (15, 1)
	379 #7 (15, 1)
	380 if_icmpge (15, 1)
	381 11 (15, 1)
	383 iload (15, 1)
	384 #12 (15, 1)
	385 istore (15, 1)
	386 #7 (15, 1)
	387 aload (15, 1)
	388 #11 (15, 1)
	389 astore (15, 1)
	390 #6 (15, 1)
	391 iinc (15, 1)
	392 #12 (15, 1)
	393 -89 (15, 1)
	394 goto (15, 1)
	395 -58 (15, 1)
	397 goto (13, 4)
	398 -87 (13, 4)
	400 aload (13, 4)
	401 #6 (13, 4)
	402 areturn (13, 4)
	403 aload_3 (11, 3)
	404 iconst_0 (11, 3)
	405 invokeinterface (11, 3)
	406 java/util/List.incrementIterationsCounter:()V (11, 3)
	408 0 (11, 3)
	410 checkcast (11, 3)
	411 java/lang/Integer (11, 3)
	413 areturn (4, 3)

Method: doIteration
	0 aload_0 (0, 0)
	1 invokevirtual (0, 0)
	2 org/apache/commons/math3/optimization/linear/SimplexSolver.incrementIterationsCounter:()V (0, 0)
	4 aload_0 (0, 0)
	5 aload_1 (0, 0)
	6 invokespecial (0, 0)
	7 org/apache/commons/math3/optimization/linear/SimplexSolver.getPivotColumn:(Lorg/apache/commons/math3/optimization/linear/SimplexTableau;)Ljava/lang/Integer; (0, 0)
	9 astore_2 (0, 0)
	10 aload_0 (0, 0)
	11 aload_1 (0, 0)
	12 aload_2 (0, 0)
	13 invokevirtual (0, 0)
	14 java/lang/Integer.intValue:()I (0, 0)
	16 invokespecial (0, 0)
	17 org/apache/commons/math3/optimization/linear/SimplexSolver.getPivotRow:(Lorg/apache/commons/math3/optimization/linear/SimplexTableau;I)Ljava/lang/Integer; (0, 0)
	19 astore_3 (0, 0)
	20 aload_3 (1, 1)
	21 ifnonnull (1, 1)
	22 11 (1, 1)
	24 new (1, 1)
	25 org/apache/commons/math3/optimization/linear/UnboundedSolutionException (1, 1)
	27 dup (1, 1)
	28 invokespecial (1, 1)
	29 org/apache/commons/math3/optimization/linear/UnboundedSolutionException.<init>:()V (1, 1)
	31 athrow (1, 1)
	32 aload_1 (0, 0)
	33 aload_3 (0, 0)
	34 invokevirtual (0, 0)
	35 java/lang/Integer.intValue:()I (0, 0)
	37 aload_2 (0, 0)
	38 invokevirtual (0, 0)
	39 java/lang/Integer.intValue:()I (0, 0)
	41 invokevirtual (0, 0)
	42 org/apache/commons/math3/optimization/linear/SimplexTableau.getEntry:(II)D (0, 0)
	44 dstore (0, 0)
	45 #4 (0, 0)
	46 aload_1 (0, 0)
	47 aload_3 (0, 0)
	48 invokevirtual (0, 0)
	49 java/lang/Integer.intValue:()I (0, 0)
	51 dload (0, 0)
	52 #4 (0, 0)
	53 invokevirtual (0, 0)
	54 org/apache/commons/math3/optimization/linear/SimplexTableau.divideRow:(ID)V (0, 0)
	56 iconst_0 (1, 4)
	57 istore (1, 4)
	58 #6 (1, 4)
	59 iload (1, 4)
	60 #6 (1, 4)
	61 aload_1 (1, 4)
	62 invokevirtual (1, 4)
	63 org/apache/commons/math3/optimization/linear/SimplexTableau.getHeight:()I (1, 4)
	65 if_icmpge (1, 4)
	66 42 (1, 4)
	68 iload (2, 1)
	69 #6 (2, 1)
	70 aload_3 (2, 1)
	71 invokevirtual (2, 1)
	72 java/lang/Integer.intValue:()I (2, 1)
	74 if_icmpeq (2, 1)
	75 27 (2, 1)
	77 aload_1 (2, 1)
	78 iload (2, 1)
	79 #6 (2, 1)
	80 aload_2 (2, 1)
	81 invokevirtual (2, 1)
	82 java/lang/Integer.intValue:()I (2, 1)
	84 invokevirtual (2, 1)
	85 org/apache/commons/math3/optimization/linear/SimplexTableau.getEntry:(II)D (2, 1)
	87 dstore (2, 1)
	88 #7 (2, 1)
	89 aload_1 (2, 1)
	90 iload (2, 1)
	91 #6 (2, 1)
	92 aload_3 (2, 1)
	93 invokevirtual (2, 1)
	94 java/lang/Integer.intValue:()I (2, 1)
	96 dload (2, 1)
	97 #7 (2, 1)
	98 invokevirtual (2, 1)
	99 org/apache/commons/math3/optimization/linear/SimplexTableau.subtractRow:(IID)V (2, 1)
	101 iinc (2, 1)
	102 #6 (2, 1)
	103 -89 (2, 1)
	104 goto (2, 1)
	105 -45 (2, 1)
	107 return (0, 0)

Method: solvePhase1
	0 aload_1 (1, 1)
	1 invokevirtual (1, 1)
	2 org/apache/commons/math3/optimization/linear/SimplexTableau.getNumArtificialVariables:()I (1, 1)
	4 ifne (1, 1)
	5 4 (1, 1)
	7 return (1, 1)
	8 aload_1 (1, 3)
	9 invokevirtual (1, 3)
	10 org/apache/commons/math3/optimization/linear/SimplexTableau.isOptimal:()Z (1, 3)
	12 ifne (1, 3)
	13 11 (1, 3)
	15 aload_0 (1, 3)
	16 aload_1 (1, 3)
	17 invokevirtual (1, 3)
	18 org/apache/commons/math3/optimization/linear/SimplexSolver.doIteration:(Lorg/apache/commons/math3/optimization/linear/SimplexTableau;)V (1, 3)
	20 goto (1, 3)
	21 -12 (1, 3)
	23 aload_1 (2, 1)
	24 iconst_0 (2, 1)
	25 aload_1 (2, 1)
	26 invokevirtual (2, 1)
	27 org/apache/commons/math3/optimization/linear/SimplexTableau.getRhsOffset:()I (2, 1)
	29 invokevirtual (2, 1)
	30 org/apache/commons/math3/optimization/linear/SimplexTableau.getEntry:(II)D (2, 1)
	32 dconst_0 (2, 1)
	33 aload_0 (2, 1)
	34 getfield (2, 1)
	35 org/apache/commons/math3/optimization/linear/SimplexSolver.epsilon:D (2, 1)
	37 invokestatic (2, 1)
	38 org/apache/commons/math3/util/Precision.equals:(DDD)Z (2, 1)
	40 ifne (2, 1)
	41 11 (2, 1)
	43 new (2, 1)
	44 org/apache/commons/math3/optimization/linear/NoFeasibleSolutionException (2, 1)
	46 dup (2, 1)
	47 invokespecial (2, 1)
	48 org/apache/commons/math3/optimization/linear/NoFeasibleSolutionException.<init>:()V (2, 1)
	50 athrow (2, 1)
	51 return (0, 1)

Method: doOptimize
	0 new (0, 0)
	1 org/apache/commons/math3/optimization/linear/SimplexTableau (0, 0)
	3 dup (0, 0)
	4 aload_0 (0, 0)
	5 invokevirtual (0, 0)
	6 org/apache/commons/math3/optimization/linear/SimplexSolver.getFunction:()Lorg/apache/commons/math3/optimization/linear/LinearObjectiveFunction; (0, 0)
	8 aload_0 (0, 0)
	9 invokevirtual (0, 0)
	10 org/apache/commons/math3/optimization/linear/SimplexSolver.getConstraints:()Ljava/util/Collection; (0, 0)
	12 aload_0 (0, 0)
	13 invokevirtual (0, 0)
	14 org/apache/commons/math3/optimization/linear/SimplexSolver.getGoalType:()Lorg/apache/commons/math3/optimization/GoalType; (0, 0)
	16 aload_0 (0, 0)
	17 invokevirtual (0, 0)
	18 org/apache/commons/math3/optimization/linear/SimplexSolver.restrictToNonNegative:()Z (0, 0)
	20 aload_0 (0, 0)
	21 getfield (0, 0)
	22 org/apache/commons/math3/optimization/linear/SimplexSolver.epsilon:D (0, 0)
	24 aload_0 (0, 0)
	25 getfield (0, 0)
	26 org/apache/commons/math3/optimization/linear/SimplexSolver.maxUlps:I (0, 0)
	28 invokespecial (0, 0)
	29 org/apache/commons/math3/optimization/linear/SimplexTableau.<init>:(Lorg/apache/commons/math3/optimization/linear/LinearObjectiveFunction;Ljava/util/Collection;Lorg/apache/commons/math3/optimization/GoalType;ZDI)V (0, 0)
	31 astore_1 (0, 0)
	32 aload_0 (0, 0)
	33 aload_1 (0, 0)
	34 invokevirtual (0, 0)
	35 org/apache/commons/math3/optimization/linear/SimplexSolver.solvePhase1:(Lorg/apache/commons/math3/optimization/linear/SimplexTableau;)V (0, 0)
	37 aload_1 (0, 0)
	38 invokevirtual (0, 0)
	39 org/apache/commons/math3/optimization/linear/SimplexTableau.dropPhase1Objective:()V (0, 0)
	41 aload_1 (1, 3)
	42 invokevirtual (1, 3)
	43 org/apache/commons/math3/optimization/linear/SimplexTableau.isOptimal:()Z (1, 3)
	45 ifne (1, 3)
	46 11 (1, 3)
	48 aload_0 (1, 3)
	49 aload_1 (1, 3)
	50 invokevirtual (1, 3)
	51 org/apache/commons/math3/optimization/linear/SimplexSolver.doIteration:(Lorg/apache/commons/math3/optimization/linear/SimplexTableau;)V (1, 3)
	53 goto (1, 3)
	54 -12 (1, 3)
	56 aload_1 (0, 0)
	57 invokevirtual (0, 0)
	58 org/apache/commons/math3/optimization/linear/SimplexTableau.getSolution:()Lorg/apache/commons/math3/optimization/PointValuePair; (0, 0)
	60 areturn (0, 0)

