Method: <init>
	0 aload_0 (0, 0)
	1 invokespecial (0, 0)
	2 java/lang/Object.<init>:()V (0, 0)
	4 aload_0 (1, 1)
	5 aload_1 (1, 1)
	6 putfield (1, 1)
	7 org/apache/commons/math3/dfp/Dfp.field:Lorg/apache/commons/math3/dfp/DfpField; (1, 1)
	9 aload_0 (1, 1)
	10 aload_1 (1, 1)
	11 invokevirtual (1, 1)
	12 org/apache/commons/math3/dfp/DfpField.getRadixDigits:()I (1, 1)
	14 newarray (1, 1)
	15 10 (1, 1)
	16 putfield (1, 1)
	17 org/apache/commons/math3/dfp/Dfp.mant:[I (1, 1)
	19 aload_0 (1, 1)
	20 iload_2 (1, 1)
	21 putfield (1, 1)
	22 org/apache/commons/math3/dfp/Dfp.sign:B (1, 1)
	24 aload_0 (0, 0)
	25 iconst_0 (0, 0)
	26 putfield (0, 0)
	27 org/apache/commons/math3/dfp/Dfp.exp:I (0, 0)
	29 aload_0 (0, 0)
	30 iload_3 (0, 0)
	31 putfield (0, 0)
	32 org/apache/commons/math3/dfp/Dfp.nans:B (0, 0)
	34 return (1, 1)

Method: newInstance
	0 aload_0 (0, 0)
	1 getfield (0, 0)
	2 org/apache/commons/math3/dfp/Dfp.field:Lorg/apache/commons/math3/dfp/DfpField; (0, 0)
	4 iload_1 (0, 0)
	5 iload_2 (0, 0)
	6 invokevirtual (0, 0)
	7 org/apache/commons/math3/dfp/DfpField.newDfp:(BB)Lorg/apache/commons/math3/dfp/Dfp; (0, 0)
	9 areturn (0, 0)

Method: getField
	0 aload_0 (1, 1)
	1 getfield (1, 1)
	2 org/apache/commons/math3/dfp/Dfp.field:Lorg/apache/commons/math3/dfp/DfpField; (1, 1)
	4 areturn (1, 1)

Method: getRadixDigits
	0 aload_0 (0, 0)
	1 getfield (0, 0)
	2 org/apache/commons/math3/dfp/Dfp.field:Lorg/apache/commons/math3/dfp/DfpField; (0, 0)
	4 invokevirtual (0, 0)
	5 org/apache/commons/math3/dfp/DfpField.getRadixDigits:()I (0, 0)
	7 ireturn (0, 0)

Method: getZero
	0 aload_0 (0, 0)
	1 getfield (0, 0)
	2 org/apache/commons/math3/dfp/Dfp.field:Lorg/apache/commons/math3/dfp/DfpField; (0, 0)
	4 invokevirtual (0, 0)
	5 org/apache/commons/math3/dfp/DfpField.getZero:()Lorg/apache/commons/math3/dfp/Dfp; (0, 0)
	7 areturn (0, 0)

Method: getOne
	0 aload_0 (0, 0)
	1 getfield (0, 0)
	2 org/apache/commons/math3/dfp/Dfp.field:Lorg/apache/commons/math3/dfp/DfpField; (0, 0)
	4 invokevirtual (0, 0)
	5 org/apache/commons/math3/dfp/DfpField.getOne:()Lorg/apache/commons/math3/dfp/Dfp; (0, 0)
	7 areturn (0, 0)

Method: getTwo
	0 aload_0 (0, 0)
	1 getfield (0, 0)
	2 org/apache/commons/math3/dfp/Dfp.field:Lorg/apache/commons/math3/dfp/DfpField; (0, 0)
	4 invokevirtual (0, 0)
	5 org/apache/commons/math3/dfp/DfpField.getTwo:()Lorg/apache/commons/math3/dfp/Dfp; (0, 0)
	7 areturn (0, 0)

Method: shiftLeft
	0 aload_0 (0, 0)
	1 getfield (0, 0)
	2 org/apache/commons/math3/dfp/Dfp.mant:[I (0, 0)
	4 arraylength (0, 0)
	5 iconst_1 (0, 0)
	6 isub (0, 0)
	7 istore_1 (0, 0)
	8 iload_1 (0, 0)
	9 ifle (0, 0)
	10 23 (0, 0)
	12 aload_0 (0, 0)
	13 getfield (0, 0)
	14 org/apache/commons/math3/dfp/Dfp.mant:[I (0, 0)
	16 iload_1 (0, 0)
	17 aload_0 (0, 0)
	18 getfield (0, 0)
	19 org/apache/commons/math3/dfp/Dfp.mant:[I (0, 0)
	21 iload_1 (0, 0)
	22 iconst_1 (0, 0)
	23 isub (0, 0)
	24 iaload (0, 0)
	25 iastore (0, 0)
	26 iinc (0, 0)
	27 #1 (0, 0)
	28 -89 (0, 0)
	29 goto (0, 0)
	30 -21 (0, 0)
	32 aload_0 (0, 0)
	33 getfield (0, 0)
	34 org/apache/commons/math3/dfp/Dfp.mant:[I (0, 0)
	36 iconst_0 (0, 0)
	37 iconst_0 (0, 0)
	38 iastore (0, 0)
	39 aload_0 (0, 0)
	40 dup (0, 0)
	41 getfield (0, 0)
	42 org/apache/commons/math3/dfp/Dfp.exp:I (0, 0)
	44 iconst_1 (0, 0)
	45 isub (0, 0)
	46 putfield (0, 0)
	47 org/apache/commons/math3/dfp/Dfp.exp:I (0, 0)
	49 return (0, 0)

Method: shiftRight
	0 iconst_0 (0, 4)
	1 istore_1 (0, 4)
	2 iload_1 (0, 4)
	3 aload_0 (0, 4)
	4 getfield (0, 4)
	5 org/apache/commons/math3/dfp/Dfp.mant:[I (0, 4)
	7 arraylength (0, 4)
	8 iconst_1 (0, 4)
	9 isub (0, 4)
	10 if_icmpge (0, 4)
	11 23 (0, 4)
	13 aload_0 (0, 4)
	14 getfield (0, 4)
	15 org/apache/commons/math3/dfp/Dfp.mant:[I (0, 4)
	17 iload_1 (0, 4)
	18 aload_0 (0, 4)
	19 getfield (0, 4)
	20 org/apache/commons/math3/dfp/Dfp.mant:[I (0, 4)
	22 iload_1 (0, 4)
	23 iconst_1 (0, 4)
	24 iadd (0, 4)
	25 iaload (0, 4)
	26 iastore (0, 4)
	27 iinc (0, 4)
	28 #1 (0, 4)
	29 -89 (0, 4)
	30 goto (0, 4)
	31 -28 (0, 4)
	33 aload_0 (0, 4)
	34 getfield (0, 4)
	35 org/apache/commons/math3/dfp/Dfp.mant:[I (0, 4)
	37 aload_0 (0, 4)
	38 getfield (0, 4)
	39 org/apache/commons/math3/dfp/Dfp.mant:[I (0, 4)
	41 arraylength (0, 4)
	42 iconst_1 (0, 4)
	43 isub (0, 4)
	44 iconst_0 (0, 4)
	45 iastore (0, 4)
	46 aload_0 (0, 4)
	47 dup (0, 4)
	48 getfield (0, 4)
	49 org/apache/commons/math3/dfp/Dfp.exp:I (0, 4)
	51 iconst_1 (0, 4)
	52 iadd (0, 4)
	53 putfield (0, 4)
	54 org/apache/commons/math3/dfp/Dfp.exp:I (0, 4)
	56 return (0, 4)

Method: align
	0 iconst_0 (0, 0)
	1 istore_2 (0, 0)
	2 iconst_0 (0, 0)
	3 istore_3 (0, 0)
	4 aload_0 (0, 4)
	5 getfield (0, 4)
	6 org/apache/commons/math3/dfp/Dfp.exp:I (0, 4)
	8 iload_1 (0, 4)
	9 isub (0, 4)
	10 istore (0, 4)
	11 #4 (0, 4)
	12 iload (0, 4)
	13 #4 (0, 4)
	14 istore (0, 4)
	15 #5 (0, 4)
	16 iload (0, 4)
	17 #5 (0, 4)
	18 ifge (0, 4)
	19 8 (0, 4)
	21 iload (0, 4)
	22 #5 (0, 4)
	23 ineg (0, 4)
	24 istore (0, 4)
	25 #5 (0, 4)
	26 iload (0, 4)
	27 #4 (0, 4)
	28 ifne (0, 4)
	29 5 (0, 4)
	31 iconst_0 (0, 4)
	32 ireturn (0, 4)
	33 iload (0, 4)
	34 #5 (0, 4)
	35 aload_0 (0, 4)
	36 getfield (0, 4)
	37 org/apache/commons/math3/dfp/Dfp.mant:[I (0, 4)
	39 arraylength (0, 4)
	40 iconst_1 (0, 4)
	41 iadd (0, 4)
	42 if_icmple (0, 4)
	43 38 (0, 4)
	45 aload_0 (0, 4)
	46 getfield (0, 4)
	47 org/apache/commons/math3/dfp/Dfp.mant:[I (0, 4)
	49 iconst_0 (0, 4)
	50 invokestatic (0, 4)
	51 java/util/Arrays.fill:([II)V (0, 4)
	53 aload_0 (0, 4)
	54 iload_1 (0, 4)
	55 putfield (0, 4)
	56 org/apache/commons/math3/dfp/Dfp.exp:I (0, 4)
	58 aload_0 (0, 4)
	59 getfield (0, 4)
	60 org/apache/commons/math3/dfp/Dfp.field:Lorg/apache/commons/math3/dfp/DfpField; (0, 4)
	62 bipush (0, 4)
	63 16 (0, 4)
	64 invokevirtual (0, 4)
	65 org/apache/commons/math3/dfp/DfpField.setIEEEFlagsBits:(I)V (0, 4)
	67 aload_0 (0, 4)
	68 bipush (0, 4)
	69 16 (0, 4)
	70 ldc (0, 4)
	71 align (0, 4)
	72 aload_0 (0, 4)
	73 aload_0 (0, 4)
	74 invokevirtual (0, 4)
	75 org/apache/commons/math3/dfp/Dfp.dotrap:(ILjava/lang/String;Lorg/apache/commons/math3/dfp/Dfp;Lorg/apache/commons/math3/dfp/Dfp;)Lorg/apache/commons/math3/dfp/Dfp; (0, 4)
	77 pop (0, 4)
	78 iconst_0 (0, 4)
	79 ireturn (0, 4)
	80 iconst_0 (0, 4)
	81 istore (0, 4)
	82 #6 (0, 4)
	83 iload (0, 4)
	84 #6 (0, 4)
	85 iload (0, 4)
	86 #5 (0, 4)
	87 if_icmpge (0, 4)
	88 38 (0, 4)
	90 iload (0, 4)
	91 #4 (0, 4)
	92 ifge (0, 4)
	93 23 (0, 4)
	95 iload_2 (0, 4)
	96 ifeq (0, 4)
	97 5 (0, 4)
	99 iconst_1 (0, 4)
	100 istore_3 (0, 4)
	101 aload_0 (0, 4)
	102 getfield (0, 4)
	103 org/apache/commons/math3/dfp/Dfp.mant:[I (0, 4)
	105 iconst_0 (0, 4)
	106 iaload (0, 4)
	107 istore_2 (0, 4)
	108 aload_0 (0, 4)
	109 invokevirtual (0, 4)
	110 org/apache/commons/math3/dfp/Dfp.shiftRight:()V (0, 4)
	112 goto (0, 4)
	113 7 (0, 4)
	115 aload_0 (0, 4)
	116 invokevirtual (0, 4)
	117 org/apache/commons/math3/dfp/Dfp.shiftLeft:()V (0, 4)
	119 iinc (0, 4)
	120 #6 (0, 4)
	121 -89 (0, 4)
	122 goto (0, 4)
	123 -39 (0, 4)
	125 iload_3 (3, 4)
	126 ifeq (3, 4)
	127 23 (3, 4)
	129 aload_0 (3, 4)
	130 getfield (3, 4)
	131 org/apache/commons/math3/dfp/Dfp.field:Lorg/apache/commons/math3/dfp/DfpField; (3, 4)
	133 bipush (3, 4)
	134 16 (3, 4)
	135 invokevirtual (3, 4)
	136 org/apache/commons/math3/dfp/DfpField.setIEEEFlagsBits:(I)V (3, 4)
	138 aload_0 (3, 4)
	139 bipush (3, 4)
	140 16 (3, 4)
	141 ldc (3, 4)
	142 align (3, 4)
	143 aload_0 (3, 4)
	144 aload_0 (3, 4)
	145 invokevirtual (3, 4)
	146 org/apache/commons/math3/dfp/Dfp.dotrap:(ILjava/lang/String;Lorg/apache/commons/math3/dfp/Dfp;Lorg/apache/commons/math3/dfp/Dfp;)Lorg/apache/commons/math3/dfp/Dfp; (3, 4)
	148 pop (3, 4)
	149 iload_2 (3, 4)
	150 ireturn (3, 4)

