Method: <init>
	0 aload_0 (0, 0)
	1 aload_1 (0, 0)
	2 iload_2 (0, 0)
	3 iload_3 (0, 0)
	4 invokespecial (0, 0)
	5 org/apache/commons/math3/dfp/Dfp.<init>:(Lorg/apache/commons/math3/dfp/DfpField;BB)V (0, 0)
	7 return (0, 0)

Method: newInstance
	0 new (0, 0)
	1 org/apache/commons/math3/dfp/DfpDec (0, 0)
	3 dup (0, 0)
	4 aload_0 (0, 0)
	5 invokevirtual (0, 0)
	6 org/apache/commons/math3/dfp/DfpDec.getField:()Lorg/apache/commons/math3/dfp/DfpField; (0, 0)
	8 iload_1 (0, 0)
	9 iload_2 (0, 0)
	10 invokespecial (0, 0)
	11 org/apache/commons/math3/dfp/DfpDec.<init>:(Lorg/apache/commons/math3/dfp/DfpField;BB)V (0, 0)
	13 areturn (0, 0)

Method: getDecimalDigits
	0 aload_0 (0, 0)
	1 invokevirtual (0, 0)
	2 org/apache/commons/math3/dfp/DfpDec.getRadixDigits:()I (0, 0)
	4 iconst_4 (0, 0)
	5 imul (0, 0)
	6 iconst_3 (0, 0)
	7 isub (0, 0)
	8 ireturn (0, 0)

Method: round
	0 aload_0 (0, 0)
	1 getfield (0, 0)
	2 org/apache/commons/math3/dfp/DfpDec.mant:[I (0, 0)
	4 aload_0 (0, 0)
	5 getfield (0, 0)
	6 org/apache/commons/math3/dfp/DfpDec.mant:[I (0, 0)
	8 arraylength (0, 0)
	9 iconst_1 (0, 0)
	10 isub (0, 0)
	11 iaload (0, 0)
	12 istore_2 (0, 0)
	13 iload_2 (1, 1)
	14 ifne (1, 1)
	15 5 (1, 1)
	17 iconst_0 (1, 1)
	18 ireturn (1, 1)
	19 aload_0 (0, 0)
	20 getfield (0, 0)
	21 org/apache/commons/math3/dfp/DfpDec.mant:[I (0, 0)
	23 arraylength (0, 0)
	24 iconst_4 (0, 0)
	25 imul (0, 0)
	26 istore_3 (0, 0)
	27 sipush (0, 0)
	28 1000 (0, 0)
	30 istore (0, 0)
	31 #4 (0, 0)
	32 iload (1, 3)
	33 #4 (1, 3)
	34 iload_2 (1, 3)
	35 if_icmple (1, 3)
	36 16 (1, 3)
	38 iload (1, 3)
	39 #4 (1, 3)
	40 bipush (1, 3)
	41 10 (1, 3)
	42 idiv (1, 3)
	43 istore (1, 3)
	44 #4 (1, 3)
	45 iinc (1, 3)
	46 #3 (1, 3)
	47 -89 (1, 3)
	48 goto (1, 3)
	49 -16 (1, 3)
	51 aload_0 (0, 0)
	52 invokevirtual (0, 0)
	53 org/apache/commons/math3/dfp/DfpDec.getDecimalDigits:()I (0, 0)
	55 istore (0, 0)
	56 #5 (0, 0)
	57 iload_3 (0, 1)
	58 iload (0, 1)
	59 #5 (0, 1)
	60 isub (0, 1)
	61 istore (0, 1)
	62 #6 (0, 1)
	63 iload (0, 1)
	64 #6 (0, 1)
	65 iconst_4 (0, 1)
	66 idiv (0, 1)
	67 istore (0, 1)
	68 #7 (0, 1)
	69 iconst_1 (0, 1)
	70 istore (0, 1)
	71 #4 (0, 1)
	72 iconst_0 (1, 1)
	73 istore (1, 1)
	74 #8 (1, 1)
	75 iload (1, 1)
	76 #8 (1, 1)
	77 iload (1, 1)
	78 #6 (1, 1)
	79 iconst_4 (1, 1)
	80 irem (1, 1)
	81 if_icmpge (1, 1)
	82 16 (1, 1)
	84 iload (1, 1)
	85 #4 (1, 1)
	86 bipush (1, 1)
	87 10 (1, 1)
	88 imul (1, 1)
	89 istore (1, 1)
	90 #4 (1, 1)
	91 iinc (1, 1)
	92 #8 (1, 1)
	93 -89 (1, 1)
	94 goto (1, 1)
	95 -19 (1, 1)
	97 aload_0 (0, 1)
	98 getfield (0, 1)
	99 org/apache/commons/math3/dfp/DfpDec.mant:[I (0, 1)
	101 iload (0, 1)
	102 #7 (0, 1)
	103 iaload (0, 1)
	104 istore (0, 1)
	105 #8 (0, 1)
	106 iload (1, 1)
	107 #4 (1, 1)
	108 iconst_1 (1, 1)
	109 if_icmpgt (1, 1)
	110 23 (1, 1)
	112 iload (1, 1)
	113 #5 (1, 1)
	114 iconst_4 (1, 1)
	115 aload_0 (1, 1)
	116 getfield (1, 1)
	117 org/apache/commons/math3/dfp/DfpDec.mant:[I (1, 1)
	119 arraylength (1, 1)
	120 imul (1, 1)
	121 iconst_3 (1, 1)
	122 isub (1, 1)
	123 if_icmpne (1, 1)
	124 9 (1, 1)
	126 aload_0 (1, 1)
	127 iload_1 (1, 1)
	128 invokespecial (1, 1)
	129 org/apache/commons/math3/dfp/Dfp.round:(I)I (1, 1)
	131 ireturn (1, 1)
	132 iload_1 (0, 1)
	133 istore (0, 1)
	134 #9 (0, 1)
	135 iload (1, 1)
	136 #4 (1, 1)
	137 iconst_1 (1, 1)
	138 if_icmpne (1, 1)
	139 53 (1, 1)
	141 aload_0 (1, 4)
	142 getfield (1, 4)
	143 org/apache/commons/math3/dfp/DfpDec.mant:[I (1, 4)
	145 iload (1, 4)
	146 #7 (1, 4)
	147 iconst_1 (1, 4)
	148 isub (1, 4)
	149 iaload (1, 4)
	150 sipush (1, 4)
	151 1000 (1, 4)
	153 idiv (1, 4)
	154 bipush (1, 4)
	155 10 (1, 4)
	156 irem (1, 4)
	157 istore (1, 4)
	158 #10 (1, 4)
	159 aload_0 (1, 4)
	160 getfield (1, 4)
	161 org/apache/commons/math3/dfp/DfpDec.mant:[I (1, 4)
	163 iload (1, 4)
	164 #7 (1, 4)
	165 iconst_1 (1, 4)
	166 isub (1, 4)
	167 dup2 (1, 4)
	168 iaload (1, 4)
	169 sipush (1, 4)
	170 1000 (1, 4)
	172 irem (1, 4)
	173 iastore (1, 4)
	174 iload (1, 4)
	175 #9 (1, 4)
	176 aload_0 (1, 4)
	177 getfield (1, 4)
	178 org/apache/commons/math3/dfp/DfpDec.mant:[I (1, 4)
	180 iload (1, 4)
	181 #7 (1, 4)
	182 iconst_1 (1, 4)
	183 isub (1, 4)
	184 iaload (1, 4)
	185 ior (1, 4)
	186 istore (1, 4)
	187 #9 (1, 4)
	188 goto (1, 4)
	189 29 (1, 4)
	191 iload (1, 2)
	192 #8 (1, 2)
	193 bipush (1, 2)
	194 10 (1, 2)
	195 imul (1, 2)
	196 iload (1, 2)
	197 #4 (1, 2)
	198 idiv (1, 2)
	199 bipush (1, 2)
	200 10 (1, 2)
	201 irem (1, 2)
	202 istore (1, 2)
	203 #10 (1, 2)
	204 iload (1, 2)
	205 #9 (1, 2)
	206 iload (1, 2)
	207 #8 (1, 2)
	208 iload (1, 2)
	209 #4 (1, 2)
	210 bipush (1, 2)
	211 10 (1, 2)
	212 idiv (1, 2)
	213 irem (1, 2)
	214 ior (1, 2)
	215 istore (1, 2)
	216 #9 (1, 2)
	217 iconst_0 (1, 4)
	218 istore (1, 4)
	219 #11 (1, 4)
	220 iload (1, 4)
	221 #11 (1, 4)
	222 iload (1, 4)
	223 #7 (1, 4)
	224 if_icmpge (1, 4)
	225 29 (1, 4)
	227 iload (1, 1)
	228 #9 (1, 1)
	229 aload_0 (1, 1)
	230 getfield (1, 1)
	231 org/apache/commons/math3/dfp/DfpDec.mant:[I (1, 1)
	233 iload (1, 1)
	234 #11 (1, 1)
	235 iaload (1, 1)
	236 ior (1, 1)
	237 istore (1, 1)
	238 #9 (1, 1)
	239 aload_0 (1, 1)
	240 getfield (1, 1)
	241 org/apache/commons/math3/dfp/DfpDec.mant:[I (1, 1)
	243 iload (1, 1)
	244 #11 (1, 1)
	245 iconst_0 (1, 1)
	246 iastore (1, 1)
	247 iinc (1, 1)
	248 #11 (1, 1)
	249 -89 (1, 1)
	250 goto (1, 1)
	251 -30 (1, 1)
	253 aload_0 (0, 1)
	254 getfield (0, 1)
	255 org/apache/commons/math3/dfp/DfpDec.mant:[I (0, 1)
	257 iload (0, 1)
	258 #7 (0, 1)
	259 iload (0, 1)
	260 #8 (0, 1)
	261 iload (0, 1)
	262 #4 (0, 1)
	263 idiv (0, 1)
	264 iload (0, 1)
	265 #4 (0, 1)
	266 imul (0, 1)
	267 iastore (0, 1)
	268 getstatic (1, 5)
	269 org/apache/commons/math3/dfp/DfpDec$1.$SwitchMap$org$apache$commons$math3$dfp$DfpField$RoundingMode:[I (1, 5)
	271 aload_0 (1, 5)
	272 invokevirtual (1, 5)
	273 org/apache/commons/math3/dfp/DfpDec.getField:()Lorg/apache/commons/math3/dfp/DfpField; (1, 5)
	275 invokevirtual (1, 5)
	276 org/apache/commons/math3/dfp/DfpField.getRoundingMode:()Lorg/apache/commons/math3/dfp/DfpField$RoundingMode; (1, 5)
	278 invokevirtual (1, 5)
	279 org/apache/commons/math3/dfp/DfpField$RoundingMode.ordinal:()I (1, 5)
	281 iaload (1, 5)
	282 tableswitch (1, 5)
	283 1 328 (1, 5)
	287 2 334 (1, 5)
	291 3 354 (1, 5)
	295 4 370 (1, 5)
	299 5 386 (1, 5)
	303 6 435 (1, 5)
	307 7 483 (1, 5)
	311 8 511 (1, 5)
	328 iconst_0 (1, 5)
	329 istore (1, 5)
	330 #11 (1, 5)
	331 goto (1, 5)
	332 205 (1, 5)
	334 iload (1, 1)
	335 #10 (1, 1)
	336 ifne (1, 1)
	337 8 (1, 1)
	339 iload (1, 1)
	340 #9 (1, 1)
	341 ifeq (1, 1)
	342 7 (1, 1)
	344 iconst_1 (1, 1)
	345 goto (1, 1)
	346 4 (1, 1)
	348 iconst_0 (1, 1)
	349 istore (1, 1)
	350 #11 (1, 1)
	351 goto (1, 1)
	352 185 (1, 1)
	354 iload (1, 1)
	355 #10 (1, 1)
	356 iconst_5 (1, 1)
	357 if_icmplt (1, 1)
	358 7 (1, 1)
	360 iconst_1 (1, 1)
	361 goto (1, 1)
	362 4 (1, 1)
	364 iconst_0 (1, 1)
	365 istore (1, 1)
	366 #11 (1, 1)
	367 goto (1, 1)
	368 169 (1, 1)
	370 iload (1, 1)
	371 #10 (1, 1)
	372 iconst_5 (1, 1)
	373 if_icmple (1, 1)
	374 7 (1, 1)
	376 iconst_1 (1, 1)
	377 goto (1, 1)
	378 4 (1, 1)
	380 iconst_0 (1, 1)
	381 istore (1, 1)
	382 #11 (1, 1)
	383 goto (1, 1)
	384 153 (1, 1)
	386 iload (1, 1)
	387 #10 (1, 1)
	388 iconst_5 (1, 1)
	389 if_icmpgt (1, 1)
	390 36 (1, 1)
	392 iload (1, 1)
	393 #10 (1, 1)
	394 iconst_5 (1, 1)
	395 if_icmpne (1, 1)
	396 8 (1, 1)
	398 iload (1, 1)
	399 #9 (1, 1)
	400 ifne (1, 1)
	401 25 (1, 1)
	403 iload (1, 1)
	404 #10 (1, 1)
	405 iconst_5 (1, 1)
	406 if_icmpne (1, 1)
	407 23 (1, 1)
	409 iload (1, 1)
	410 #9 (1, 1)
	411 ifne (1, 1)
	412 18 (1, 1)
	414 iload (1, 1)
	415 #8 (1, 1)
	416 iload (1, 1)
	417 #4 (1, 1)
	418 idiv (1, 1)
	419 iconst_1 (1, 1)
	420 iand (1, 1)
	421 iconst_1 (1, 1)
	422 if_icmpne (1, 1)
	423 7 (1, 1)
	425 iconst_1 (1, 1)
	426 goto (1, 1)
	427 4 (1, 1)
	429 iconst_0 (1, 1)
	430 istore (1, 1)
	431 #11 (1, 1)
	432 goto (1, 1)
	433 104 (1, 1)
	435 iload (1, 1)
	436 #10 (1, 1)
	437 iconst_5 (1, 1)
	438 if_icmpgt (1, 1)
	439 35 (1, 1)
	441 iload (1, 1)
	442 #10 (1, 1)
	443 iconst_5 (1, 1)
	444 if_icmpne (1, 1)
	445 8 (1, 1)
	447 iload (1, 1)
	448 #9 (1, 1)
	449 ifne (1, 1)
	450 24 (1, 1)
	452 iload (1, 1)
	453 #10 (1, 1)
	454 iconst_5 (1, 1)
	455 if_icmpne (1, 1)
	456 22 (1, 1)
	458 iload (1, 1)
	459 #9 (1, 1)
	460 ifne (1, 1)
	461 17 (1, 1)
	463 iload (1, 1)
	464 #8 (1, 1)
	465 iload (1, 1)
	466 #4 (1, 1)
	467 idiv (1, 1)
	468 iconst_1 (1, 1)
	469 iand (1, 1)
	470 ifne (1, 1)
	471 7 (1, 1)
	473 iconst_1 (1, 1)
	474 goto (1, 1)
	475 4 (1, 1)
	477 iconst_0 (1, 1)
	478 istore (1, 1)
	479 #11 (1, 1)
	480 goto (1, 1)
	481 56 (1, 1)
	483 aload_0 (1, 1)
	484 getfield (1, 1)
	485 org/apache/commons/math3/dfp/DfpDec.sign:B (1, 1)
	487 iconst_1 (1, 1)
	488 if_icmpne (1, 1)
	489 17 (1, 1)
	491 iload (1, 1)
	492 #10 (1, 1)
	493 ifne (1, 1)
	494 8 (1, 1)
	496 iload (1, 1)
	497 #9 (1, 1)
	498 ifeq (1, 1)
	499 7 (1, 1)
	501 iconst_1 (1, 1)
	502 goto (1, 1)
	503 4 (1, 1)
	505 iconst_0 (1, 1)
	506 istore (1, 1)
	507 #11 (1, 1)
	508 goto (1, 1)
	509 28 (1, 1)
	511 aload_0 (1, 1)
	512 getfield (1, 1)
	513 org/apache/commons/math3/dfp/DfpDec.sign:B (1, 1)
	515 iconst_m1 (1, 1)
	516 if_icmpne (1, 1)
	517 17 (1, 1)
	519 iload (1, 1)
	520 #10 (1, 1)
	521 ifne (1, 1)
	522 8 (1, 1)
	524 iload (1, 1)
	525 #9 (1, 1)
	526 ifeq (1, 1)
	527 7 (1, 1)
	529 iconst_1 (1, 1)
	530 goto (1, 1)
	531 4 (1, 1)
	533 iconst_0 (1, 1)
	534 istore (1, 1)
	535 #11 (1, 1)
	536 iload (1, 1)
	537 #11 (1, 1)
	538 ifeq (1, 1)
	539 83 (1, 1)
	541 iload (1, 1)
	542 #4 (1, 1)
	543 istore (1, 1)
	544 #12 (1, 1)
	545 iload (2, 4)
	546 #7 (2, 4)
	547 istore (2, 4)
	548 #13 (2, 4)
	549 iload (2, 4)
	550 #13 (2, 4)
	551 aload_0 (2, 4)
	552 getfield (2, 4)
	553 org/apache/commons/math3/dfp/DfpDec.mant:[I (2, 4)
	555 arraylength (2, 4)
	556 if_icmpge (2, 4)
	557 42 (2, 4)
	559 aload_0 (2, 4)
	560 getfield (2, 4)
	561 org/apache/commons/math3/dfp/DfpDec.mant:[I (2, 4)
	563 iload (2, 4)
	564 #13 (2, 4)
	565 iaload (2, 4)
	566 iload (2, 4)
	567 #12 (2, 4)
	568 iadd (2, 4)
	569 istore (2, 4)
	570 #14 (2, 4)
	571 iload (2, 4)
	572 #14 (2, 4)
	573 sipush (2, 4)
	574 10000 (2, 4)
	576 idiv (2, 4)
	577 istore (2, 4)
	578 #12 (2, 4)
	579 aload_0 (2, 4)
	580 getfield (2, 4)
	581 org/apache/commons/math3/dfp/DfpDec.mant:[I (2, 4)
	583 iload (2, 4)
	584 #13 (2, 4)
	585 iload (2, 4)
	586 #14 (2, 4)
	587 sipush (2, 4)
	588 10000 (2, 4)
	590 irem (2, 4)
	591 iastore (2, 4)
	592 iinc (2, 4)
	593 #13 (2, 4)
	594 -89 (2, 4)
	595 goto (2, 4)
	596 -46 (2, 4)
	598 iload (2, 1)
	599 #12 (2, 1)
	600 ifeq (2, 1)
	601 21 (2, 1)
	603 aload_0 (2, 1)
	604 invokevirtual (2, 1)
	605 org/apache/commons/math3/dfp/DfpDec.shiftRight:()V (2, 1)
	607 aload_0 (2, 1)
	608 getfield (2, 1)
	609 org/apache/commons/math3/dfp/DfpDec.mant:[I (2, 1)
	611 aload_0 (2, 1)
	612 getfield (2, 1)
	613 org/apache/commons/math3/dfp/DfpDec.mant:[I (2, 1)
	615 arraylength (2, 1)
	616 iconst_1 (2, 1)
	617 isub (2, 1)
	618 iload (2, 1)
	619 #12 (2, 1)
	620 iastore (2, 1)
	621 aload_0 (1, 1)
	622 getfield (1, 1)
	623 org/apache/commons/math3/dfp/DfpDec.exp:I (1, 1)
	625 sipush (1, 1)
	626 -32767 (1, 1)
	628 if_icmpge (1, 1)
	629 15 (1, 1)
	631 aload_0 (1, 1)
	632 invokevirtual (1, 1)
	633 org/apache/commons/math3/dfp/DfpDec.getField:()Lorg/apache/commons/math3/dfp/DfpField; (1, 1)
	635 bipush (1, 1)
	636 8 (1, 1)
	637 invokevirtual (1, 1)
	638 org/apache/commons/math3/dfp/DfpField.setIEEEFlagsBits:(I)V (1, 1)
	640 bipush (1, 1)
	641 8 (1, 1)
	642 ireturn (1, 1)
	643 aload_0 (1, 1)
	644 getfield (1, 1)
	645 org/apache/commons/math3/dfp/DfpDec.exp:I (1, 1)
	647 ldc (1, 1)
	648 32768 (1, 1)
	649 if_icmple (1, 1)
	650 13 (1, 1)
	652 aload_0 (1, 1)
	653 invokevirtual (1, 1)
	654 org/apache/commons/math3/dfp/DfpDec.getField:()Lorg/apache/commons/math3/dfp/DfpField; (1, 1)
	656 iconst_4 (1, 1)
	657 invokevirtual (1, 1)
	658 org/apache/commons/math3/dfp/DfpField.setIEEEFlagsBits:(I)V (1, 1)
	660 iconst_4 (1, 1)
	661 ireturn (1, 1)
	662 iload (1, 1)
	663 #10 (1, 1)
	664 ifne (1, 1)
	665 8 (1, 1)
	667 iload (1, 1)
	668 #9 (1, 1)
	669 ifeq (1, 1)
	670 15 (1, 1)
	672 aload_0 (1, 1)
	673 invokevirtual (1, 1)
	674 org/apache/commons/math3/dfp/DfpDec.getField:()Lorg/apache/commons/math3/dfp/DfpField; (1, 1)
	676 bipush (1, 1)
	677 16 (1, 1)
	678 invokevirtual (1, 1)
	679 org/apache/commons/math3/dfp/DfpField.setIEEEFlagsBits:(I)V (1, 1)
	681 bipush (1, 1)
	682 16 (1, 1)
	683 ireturn (1, 1)
	684 iconst_0 (0, 1)
	685 ireturn (0, 1)

Method: nextAfter
	0 ldc (0, 0)
	1 nextAfter (0, 0)
	2 astore_2 (0, 0)
	3 aload_0 (1, 1)
	4 invokevirtual (1, 1)
	5 org/apache/commons/math3/dfp/DfpDec.getField:()Lorg/apache/commons/math3/dfp/DfpField; (1, 1)
	7 invokevirtual (1, 1)
	8 org/apache/commons/math3/dfp/DfpField.getRadixDigits:()I (1, 1)
	10 aload_1 (1, 1)
	11 invokevirtual (1, 1)
	12 org/apache/commons/math3/dfp/Dfp.getField:()Lorg/apache/commons/math3/dfp/DfpField; (1, 1)
	14 invokevirtual (1, 1)
	15 org/apache/commons/math3/dfp/DfpField.getRadixDigits:()I (1, 1)
	17 if_icmpeq (1, 1)
	18 35 (1, 1)
	20 aload_0 (1, 1)
	21 invokevirtual (1, 1)
	22 org/apache/commons/math3/dfp/DfpDec.getField:()Lorg/apache/commons/math3/dfp/DfpField; (1, 1)
	24 iconst_1 (1, 1)
	25 invokevirtual (1, 1)
	26 org/apache/commons/math3/dfp/DfpField.setIEEEFlagsBits:(I)V (1, 1)
	28 aload_0 (1, 1)
	29 aload_0 (1, 1)
	30 invokevirtual (1, 1)
	31 org/apache/commons/math3/dfp/DfpDec.getZero:()Lorg/apache/commons/math3/dfp/Dfp; (1, 1)
	33 invokevirtual (1, 1)
	34 org/apache/commons/math3/dfp/DfpDec.newInstance:(Lorg/apache/commons/math3/dfp/Dfp;)Lorg/apache/commons/math3/dfp/Dfp; (1, 1)
	36 astore_3 (1, 1)
	37 aload_3 (1, 1)
	38 iconst_3 (1, 1)
	39 putfield (1, 1)
	40 org/apache/commons/math3/dfp/Dfp.nans:B (1, 1)
	42 aload_0 (1, 1)
	43 iconst_1 (1, 1)
	44 ldc (1, 1)
	45 nextAfter (1, 1)
	46 aload_1 (1, 1)
	47 aload_3 (1, 1)
	48 invokevirtual (1, 1)
	49 org/apache/commons/math3/dfp/DfpDec.dotrap:(ILjava/lang/String;Lorg/apache/commons/math3/dfp/Dfp;Lorg/apache/commons/math3/dfp/Dfp;)Lorg/apache/commons/math3/dfp/Dfp; (1, 1)
	51 areturn (1, 1)
	52 iconst_0 (0, 1)
	53 istore_3 (0, 1)
	54 aload_0 (1, 1)
	55 aload_1 (1, 1)
	56 invokevirtual (1, 1)
	57 org/apache/commons/math3/dfp/DfpDec.lessThan:(Lorg/apache/commons/math3/dfp/Dfp;)Z (1, 1)
	59 ifeq (1, 1)
	60 5 (1, 1)
	62 iconst_1 (1, 1)
	63 istore_3 (1, 1)
	64 aload_0 (1, 1)
	65 aload_1 (1, 1)
	66 invokevirtual (1, 1)
	67 org/apache/commons/math3/dfp/DfpDec.equals:(Ljava/lang/Object;)Z (1, 1)
	69 ifeq (1, 1)
	70 9 (1, 1)
	72 aload_0 (1, 1)
	73 aload_1 (1, 1)
	74 invokevirtual (1, 1)
	75 org/apache/commons/math3/dfp/DfpDec.newInstance:(Lorg/apache/commons/math3/dfp/Dfp;)Lorg/apache/commons/math3/dfp/Dfp; (1, 1)
	77 areturn (1, 1)
	78 aload_0 (1, 1)
	79 aload_0 (1, 1)
	80 invokevirtual (1, 1)
	81 org/apache/commons/math3/dfp/DfpDec.getZero:()Lorg/apache/commons/math3/dfp/Dfp; (1, 1)
	83 invokevirtual (1, 1)
	84 org/apache/commons/math3/dfp/DfpDec.lessThan:(Lorg/apache/commons/math3/dfp/Dfp;)Z (1, 1)
	86 ifeq (1, 1)
	87 13 (1, 1)
	89 iload_3 (1, 1)
	90 ifne (1, 1)
	91 7 (1, 1)
	93 iconst_1 (1, 1)
	94 goto (1, 1)
	95 4 (1, 1)
	97 iconst_0 (1, 1)
	98 istore_3 (1, 1)
	99 iload_3 (1, 1)
	100 ifeq (1, 1)
	101 96 (1, 1)
	103 aload_0 (1, 1)
	104 aload_0 (1, 1)
	105 invokevirtual (1, 1)
	106 org/apache/commons/math3/dfp/DfpDec.intLog10:()I (1, 1)
	108 aload_0 (1, 1)
	109 invokevirtual (1, 1)
	110 org/apache/commons/math3/dfp/DfpDec.getDecimalDigits:()I (1, 1)
	112 isub (1, 1)
	113 iconst_1 (1, 1)
	114 iadd (1, 1)
	115 invokevirtual (1, 1)
	116 org/apache/commons/math3/dfp/DfpDec.power10:(I)Lorg/apache/commons/math3/dfp/Dfp; (1, 1)
	118 astore (1, 1)
	119 #5 (1, 1)
	120 aload (1, 1)
	121 #5 (1, 1)
	122 aload_0 (1, 1)
	123 invokestatic (1, 1)
	124 org/apache/commons/math3/dfp/DfpDec.copysign:(Lorg/apache/commons/math3/dfp/Dfp;Lorg/apache/commons/math3/dfp/Dfp;)Lorg/apache/commons/math3/dfp/Dfp; (1, 1)
	126 astore (1, 1)
	127 #5 (1, 1)
	128 aload_0 (2, 1)
	129 aload_0 (2, 1)
	130 invokevirtual (2, 1)
	131 org/apache/commons/math3/dfp/DfpDec.getZero:()Lorg/apache/commons/math3/dfp/Dfp; (2, 1)
	133 invokevirtual (2, 1)
	134 org/apache/commons/math3/dfp/DfpDec.equals:(Ljava/lang/Object;)Z (2, 1)
	136 ifeq (2, 1)
	137 20 (2, 1)
	139 aload_0 (2, 1)
	140 sipush (2, 1)
	141 -32767 (2, 1)
	143 aload_0 (2, 1)
	144 getfield (2, 1)
	145 org/apache/commons/math3/dfp/DfpDec.mant:[I (2, 1)
	147 arraylength (2, 1)
	148 isub (2, 1)
	149 iconst_1 (2, 1)
	150 isub (2, 1)
	151 invokevirtual (2, 1)
	152 org/apache/commons/math3/dfp/DfpDec.power10K:(I)Lorg/apache/commons/math3/dfp/Dfp; (2, 1)
	154 astore (2, 1)
	155 #5 (2, 1)
	156 aload (2, 1)
	157 #5 (2, 1)
	158 aload_0 (2, 1)
	159 invokevirtual (2, 1)
	160 org/apache/commons/math3/dfp/DfpDec.getZero:()Lorg/apache/commons/math3/dfp/Dfp; (2, 1)
	162 invokevirtual (2, 1)
	163 org/apache/commons/math3/dfp/Dfp.equals:(Ljava/lang/Object;)Z (2, 1)
	165 ifeq (2, 1)
	166 20 (2, 1)
	168 aload_0 (2, 1)
	169 aload_0 (2, 1)
	170 invokevirtual (2, 1)
	171 org/apache/commons/math3/dfp/DfpDec.getZero:()Lorg/apache/commons/math3/dfp/Dfp; (2, 1)
	173 invokevirtual (2, 1)
	174 org/apache/commons/math3/dfp/DfpDec.newInstance:(Lorg/apache/commons/math3/dfp/Dfp;)Lorg/apache/commons/math3/dfp/Dfp; (2, 1)
	176 aload_0 (2, 1)
	177 invokestatic (2, 1)
	178 org/apache/commons/math3/dfp/DfpDec.copysign:(Lorg/apache/commons/math3/dfp/Dfp;Lorg/apache/commons/math3/dfp/Dfp;)Lorg/apache/commons/math3/dfp/Dfp; (2, 1)
	180 astore (2, 1)
	181 #4 (2, 1)
	182 goto (2, 1)
	183 141 (2, 1)
	185 aload_0 (2, 2)
	186 aload (2, 2)
	187 #5 (2, 2)
	188 invokevirtual (2, 2)
	189 org/apache/commons/math3/dfp/DfpDec.add:(Lorg/apache/commons/math3/dfp/Dfp;)Lorg/apache/commons/math3/dfp/Dfp; (2, 2)
	191 astore (2, 2)
	192 #4 (2, 2)
	193 goto (2, 2)
	194 130 (2, 2)
	196 aload_0 (1, 2)
	197 aload_0 (1, 2)
	198 invokevirtual (1, 2)
	199 org/apache/commons/math3/dfp/DfpDec.intLog10:()I (1, 2)
	201 invokevirtual (1, 2)
	202 org/apache/commons/math3/dfp/DfpDec.power10:(I)Lorg/apache/commons/math3/dfp/Dfp; (1, 2)
	204 astore (1, 2)
	205 #5 (1, 2)
	206 aload (1, 2)
	207 #5 (1, 2)
	208 aload_0 (1, 2)
	209 invokestatic (1, 2)
	210 org/apache/commons/math3/dfp/DfpDec.copysign:(Lorg/apache/commons/math3/dfp/Dfp;Lorg/apache/commons/math3/dfp/Dfp;)Lorg/apache/commons/math3/dfp/Dfp; (1, 2)
	212 astore (1, 2)
	213 #5 (1, 2)
	214 aload_0 (2, 1)
	215 aload (2, 1)
	216 #5 (2, 1)
	217 invokevirtual (2, 1)
	218 org/apache/commons/math3/dfp/DfpDec.equals:(Ljava/lang/Object;)Z (2, 1)
	220 ifeq (2, 1)
	221 21 (2, 1)
	223 aload (2, 1)
	224 #5 (2, 1)
	225 aload_0 (2, 1)
	226 aload_0 (2, 1)
	227 invokevirtual (2, 1)
	228 org/apache/commons/math3/dfp/DfpDec.getDecimalDigits:()I (2, 1)
	230 invokevirtual (2, 1)
	231 org/apache/commons/math3/dfp/DfpDec.power10:(I)Lorg/apache/commons/math3/dfp/Dfp; (2, 1)
	233 invokevirtual (2, 1)
	234 org/apache/commons/math3/dfp/Dfp.divide:(Lorg/apache/commons/math3/dfp/Dfp;)Lorg/apache/commons/math3/dfp/Dfp; (2, 1)
	236 astore (2, 1)
	237 #5 (2, 1)
	238 goto (2, 1)
	239 20 (2, 1)
	241 aload (2, 2)
	242 #5 (2, 2)
	243 aload_0 (2, 2)
	244 aload_0 (2, 2)
	245 invokevirtual (2, 2)
	246 org/apache/commons/math3/dfp/DfpDec.getDecimalDigits:()I (2, 2)
	248 iconst_1 (2, 2)
	249 isub (2, 2)
	250 invokevirtual (2, 2)
	251 org/apache/commons/math3/dfp/DfpDec.power10:(I)Lorg/apache/commons/math3/dfp/Dfp; (2, 2)
	253 invokevirtual (2, 2)
	254 org/apache/commons/math3/dfp/Dfp.divide:(Lorg/apache/commons/math3/dfp/Dfp;)Lorg/apache/commons/math3/dfp/Dfp; (2, 2)
	256 astore (2, 2)
	257 #5 (2, 2)
	258 aload_0 (2, 1)
	259 aload_0 (2, 1)
	260 invokevirtual (2, 1)
	261 org/apache/commons/math3/dfp/DfpDec.getZero:()Lorg/apache/commons/math3/dfp/Dfp; (2, 1)
	263 invokevirtual (2, 1)
	264 org/apache/commons/math3/dfp/DfpDec.equals:(Ljava/lang/Object;)Z (2, 1)
	266 ifeq (2, 1)
	267 20 (2, 1)
	269 aload_0 (2, 1)
	270 sipush (2, 1)
	271 -32767 (2, 1)
	273 aload_0 (2, 1)
	274 getfield (2, 1)
	275 org/apache/commons/math3/dfp/DfpDec.mant:[I (2, 1)
	277 arraylength (2, 1)
	278 isub (2, 1)
	279 iconst_1 (2, 1)
	280 isub (2, 1)
	281 invokevirtual (2, 1)
	282 org/apache/commons/math3/dfp/DfpDec.power10K:(I)Lorg/apache/commons/math3/dfp/Dfp; (2, 1)
	284 astore (2, 1)
	285 #5 (2, 1)
	286 aload (2, 1)
	287 #5 (2, 1)
	288 aload_0 (2, 1)
	289 invokevirtual (2, 1)
	290 org/apache/commons/math3/dfp/DfpDec.getZero:()Lorg/apache/commons/math3/dfp/Dfp; (2, 1)
	292 invokevirtual (2, 1)
	293 org/apache/commons/math3/dfp/Dfp.equals:(Ljava/lang/Object;)Z (2, 1)
	295 ifeq (2, 1)
	296 20 (2, 1)
	298 aload_0 (2, 1)
	299 aload_0 (2, 1)
	300 invokevirtual (2, 1)
	301 org/apache/commons/math3/dfp/DfpDec.getZero:()Lorg/apache/commons/math3/dfp/Dfp; (2, 1)
	303 invokevirtual (2, 1)
	304 org/apache/commons/math3/dfp/DfpDec.newInstance:(Lorg/apache/commons/math3/dfp/Dfp;)Lorg/apache/commons/math3/dfp/Dfp; (2, 1)
	306 aload_0 (2, 1)
	307 invokestatic (2, 1)
	308 org/apache/commons/math3/dfp/DfpDec.copysign:(Lorg/apache/commons/math3/dfp/Dfp;Lorg/apache/commons/math3/dfp/Dfp;)Lorg/apache/commons/math3/dfp/Dfp; (2, 1)
	310 astore (2, 1)
	311 #4 (2, 1)
	312 goto (2, 1)
	313 11 (2, 1)
	315 aload_0 (2, 2)
	316 aload (2, 2)
	317 #5 (2, 2)
	318 invokevirtual (2, 2)
	319 org/apache/commons/math3/dfp/DfpDec.subtract:(Lorg/apache/commons/math3/dfp/Dfp;)Lorg/apache/commons/math3/dfp/Dfp; (2, 2)
	321 astore (2, 2)
	322 #4 (2, 2)
	323 aload (1, 1)
	324 #4 (1, 1)
	325 invokevirtual (1, 1)
	326 org/apache/commons/math3/dfp/Dfp.classify:()I (1, 1)
	328 iconst_1 (1, 1)
	329 if_icmpne (1, 1)
	330 33 (1, 1)
	332 aload_0 (1, 1)
	333 invokevirtual (1, 1)
	334 org/apache/commons/math3/dfp/DfpDec.classify:()I (1, 1)
	336 iconst_1 (1, 1)
	337 if_icmpeq (1, 1)
	338 25 (1, 1)
	340 aload_0 (1, 1)
	341 invokevirtual (1, 1)
	342 org/apache/commons/math3/dfp/DfpDec.getField:()Lorg/apache/commons/math3/dfp/DfpField; (1, 1)
	344 bipush (1, 1)
	345 16 (1, 1)
	346 invokevirtual (1, 1)
	347 org/apache/commons/math3/dfp/DfpField.setIEEEFlagsBits:(I)V (1, 1)
	349 aload_0 (1, 1)
	350 bipush (1, 1)
	351 16 (1, 1)
	352 ldc (1, 1)
	353 nextAfter (1, 1)
	354 aload_1 (1, 1)
	355 aload (1, 1)
	356 #4 (1, 1)
	357 invokevirtual (1, 1)
	358 org/apache/commons/math3/dfp/DfpDec.dotrap:(ILjava/lang/String;Lorg/apache/commons/math3/dfp/Dfp;Lorg/apache/commons/math3/dfp/Dfp;)Lorg/apache/commons/math3/dfp/Dfp; (1, 1)
	360 astore (1, 1)
	361 #4 (1, 1)
	362 aload (1, 1)
	363 #4 (1, 1)
	364 aload_0 (1, 1)
	365 invokevirtual (1, 1)
	366 org/apache/commons/math3/dfp/DfpDec.getZero:()Lorg/apache/commons/math3/dfp/Dfp; (1, 1)
	368 invokevirtual (1, 1)
	369 org/apache/commons/math3/dfp/Dfp.equals:(Ljava/lang/Object;)Z (1, 1)
	371 ifeq (1, 1)
	372 36 (1, 1)
	374 aload_0 (1, 1)
	375 aload_0 (1, 1)
	376 invokevirtual (1, 1)
	377 org/apache/commons/math3/dfp/DfpDec.getZero:()Lorg/apache/commons/math3/dfp/Dfp; (1, 1)
	379 invokevirtual (1, 1)
	380 org/apache/commons/math3/dfp/DfpDec.equals:(Ljava/lang/Object;)Z (1, 1)
	382 ifne (1, 1)
	383 25 (1, 1)
	385 aload_0 (1, 1)
	386 invokevirtual (1, 1)
	387 org/apache/commons/math3/dfp/DfpDec.getField:()Lorg/apache/commons/math3/dfp/DfpField; (1, 1)
	389 bipush (1, 1)
	390 16 (1, 1)
	391 invokevirtual (1, 1)
	392 org/apache/commons/math3/dfp/DfpField.setIEEEFlagsBits:(I)V (1, 1)
	394 aload_0 (1, 1)
	395 bipush (1, 1)
	396 16 (1, 1)
	397 ldc (1, 1)
	398 nextAfter (1, 1)
	399 aload_1 (1, 1)
	400 aload (1, 1)
	401 #4 (1, 1)
	402 invokevirtual (1, 1)
	403 org/apache/commons/math3/dfp/DfpDec.dotrap:(ILjava/lang/String;Lorg/apache/commons/math3/dfp/Dfp;Lorg/apache/commons/math3/dfp/Dfp;)Lorg/apache/commons/math3/dfp/Dfp; (1, 1)
	405 astore (1, 1)
	406 #4 (1, 1)
	407 aload (0, 1)
	408 #4 (0, 1)
	409 areturn (0, 1)

