Method: values
	0 getstatic (0, 0)
	1 org/apache/commons/math3/dfp/DfpField$RoundingMode.$VALUES:[Lorg/apache/commons/math3/dfp/DfpField$RoundingMode; (0, 0)
	3 invokevirtual (0, 0)
	4 [Lorg/apache/commons/math3/dfp/DfpField$RoundingMode;.clone:()Ljava/lang/Object; (0, 0)
	6 checkcast (0, 0)
	7 [Lorg/apache/commons/math3/dfp/DfpField$RoundingMode; (0, 0)
	9 areturn (0, 0)

Method: valueOf
	0 ldc (0, 0)
	1 org/apache/commons/math3/dfp/DfpField$RoundingMode (0, 0)
	2 aload_0 (0, 0)
	3 invokestatic (0, 0)
	4 java/lang/Enum.valueOf:(Ljava/lang/Class;Ljava/lang/String;)Ljava/lang/Enum; (0, 0)
	6 checkcast (0, 0)
	7 org/apache/commons/math3/dfp/DfpField$RoundingMode (0, 0)
	9 areturn (0, 0)

Method: <clinit>
	0 new (0, 0)
	1 org/apache/commons/math3/dfp/DfpField$RoundingMode (0, 0)
	3 dup (0, 0)
	4 ldc (0, 0)
	5 ROUND_DOWN (0, 0)
	6 iconst_0 (0, 0)
	7 invokespecial (0, 0)
	8 org/apache/commons/math3/dfp/DfpField$RoundingMode.<init>:(Ljava/lang/String;I)V (0, 0)
	10 putstatic (0, 0)
	11 org/apache/commons/math3/dfp/DfpField$RoundingMode.ROUND_DOWN:Lorg/apache/commons/math3/dfp/DfpField$RoundingMode; (0, 0)
	13 new (1, 1)
	14 org/apache/commons/math3/dfp/DfpField$RoundingMode (1, 1)
	16 dup (1, 1)
	17 ldc (1, 1)
	18 ROUND_UP (1, 1)
	19 iconst_1 (1, 1)
	20 invokespecial (1, 1)
	21 org/apache/commons/math3/dfp/DfpField$RoundingMode.<init>:(Ljava/lang/String;I)V (1, 1)
	23 putstatic (1, 1)
	24 org/apache/commons/math3/dfp/DfpField$RoundingMode.ROUND_UP:Lorg/apache/commons/math3/dfp/DfpField$RoundingMode; (1, 1)
	26 new (1, 1)
	27 org/apache/commons/math3/dfp/DfpField$RoundingMode (1, 1)
	29 dup (1, 1)
	30 ldc (1, 1)
	31 ROUND_HALF_UP (1, 1)
	32 iconst_2 (1, 1)
	33 invokespecial (1, 1)
	34 org/apache/commons/math3/dfp/DfpField$RoundingMode.<init>:(Ljava/lang/String;I)V (1, 1)
	36 putstatic (1, 1)
	37 org/apache/commons/math3/dfp/DfpField$RoundingMode.ROUND_HALF_UP:Lorg/apache/commons/math3/dfp/DfpField$RoundingMode; (1, 1)
	39 new (1, 1)
	40 org/apache/commons/math3/dfp/DfpField$RoundingMode (1, 1)
	42 dup (1, 1)
	43 ldc (1, 1)
	44 ROUND_HALF_DOWN (1, 1)
	45 iconst_3 (1, 1)
	46 invokespecial (1, 1)
	47 org/apache/commons/math3/dfp/DfpField$RoundingMode.<init>:(Ljava/lang/String;I)V (1, 1)
	49 putstatic (1, 1)
	50 org/apache/commons/math3/dfp/DfpField$RoundingMode.ROUND_HALF_DOWN:Lorg/apache/commons/math3/dfp/DfpField$RoundingMode; (1, 1)
	52 new (2, 1)
	53 org/apache/commons/math3/dfp/DfpField$RoundingMode (2, 1)
	55 dup (2, 1)
	56 ldc (2, 1)
	57 ROUND_HALF_EVEN (2, 1)
	58 iconst_4 (2, 1)
	59 invokespecial (2, 1)
	60 org/apache/commons/math3/dfp/DfpField$RoundingMode.<init>:(Ljava/lang/String;I)V (2, 1)
	62 putstatic (2, 1)
	63 org/apache/commons/math3/dfp/DfpField$RoundingMode.ROUND_HALF_EVEN:Lorg/apache/commons/math3/dfp/DfpField$RoundingMode; (2, 1)
	65 new (2, 1)
	66 org/apache/commons/math3/dfp/DfpField$RoundingMode (2, 1)
	68 dup (2, 1)
	69 ldc (2, 1)
	70 ROUND_HALF_ODD (2, 1)
	71 iconst_5 (2, 1)
	72 invokespecial (2, 1)
	73 org/apache/commons/math3/dfp/DfpField$RoundingMode.<init>:(Ljava/lang/String;I)V (2, 1)
	75 putstatic (2, 1)
	76 org/apache/commons/math3/dfp/DfpField$RoundingMode.ROUND_HALF_ODD:Lorg/apache/commons/math3/dfp/DfpField$RoundingMode; (2, 1)
	78 new (2, 1)
	79 org/apache/commons/math3/dfp/DfpField$RoundingMode (2, 1)
	81 dup (2, 1)
	82 ldc (2, 1)
	83 ROUND_CEIL (2, 1)
	84 bipush (2, 1)
	85 6 (2, 1)
	86 invokespecial (2, 1)
	87 org/apache/commons/math3/dfp/DfpField$RoundingMode.<init>:(Ljava/lang/String;I)V (2, 1)
	89 putstatic (2, 1)
	90 org/apache/commons/math3/dfp/DfpField$RoundingMode.ROUND_CEIL:Lorg/apache/commons/math3/dfp/DfpField$RoundingMode; (2, 1)
	92 new (2, 1)
	93 org/apache/commons/math3/dfp/DfpField$RoundingMode (2, 1)
	95 dup (2, 1)
	96 ldc (2, 1)
	97 ROUND_FLOOR (2, 1)
	98 bipush (2, 1)
	99 7 (2, 1)
	100 invokespecial (2, 1)
	101 org/apache/commons/math3/dfp/DfpField$RoundingMode.<init>:(Ljava/lang/String;I)V (2, 1)
	103 putstatic (2, 1)
	104 org/apache/commons/math3/dfp/DfpField$RoundingMode.ROUND_FLOOR:Lorg/apache/commons/math3/dfp/DfpField$RoundingMode; (2, 1)
	106 bipush (2, 1)
	107 8 (2, 1)
	108 anewarray (2, 1)
	109 org/apache/commons/math3/dfp/DfpField$RoundingMode (2, 1)
	111 dup (2, 1)
	112 iconst_0 (2, 1)
	113 getstatic (2, 1)
	114 org/apache/commons/math3/dfp/DfpField$RoundingMode.ROUND_DOWN:Lorg/apache/commons/math3/dfp/DfpField$RoundingMode; (2, 1)
	116 aastore (2, 1)
	117 dup (2, 1)
	118 iconst_1 (2, 1)
	119 getstatic (2, 1)
	120 org/apache/commons/math3/dfp/DfpField$RoundingMode.ROUND_UP:Lorg/apache/commons/math3/dfp/DfpField$RoundingMode; (2, 1)
	122 aastore (2, 1)
	123 dup (2, 1)
	124 iconst_2 (2, 1)
	125 getstatic (2, 1)
	126 org/apache/commons/math3/dfp/DfpField$RoundingMode.ROUND_HALF_UP:Lorg/apache/commons/math3/dfp/DfpField$RoundingMode; (2, 1)
	128 aastore (2, 1)
	129 dup (2, 1)
	130 iconst_3 (2, 1)
	131 getstatic (2, 1)
	132 org/apache/commons/math3/dfp/DfpField$RoundingMode.ROUND_HALF_DOWN:Lorg/apache/commons/math3/dfp/DfpField$RoundingMode; (2, 1)
	134 aastore (2, 1)
	135 dup (2, 1)
	136 iconst_4 (2, 1)
	137 getstatic (2, 1)
	138 org/apache/commons/math3/dfp/DfpField$RoundingMode.ROUND_HALF_EVEN:Lorg/apache/commons/math3/dfp/DfpField$RoundingMode; (2, 1)
	140 aastore (2, 1)
	141 dup (2, 1)
	142 iconst_5 (2, 1)
	143 getstatic (2, 1)
	144 org/apache/commons/math3/dfp/DfpField$RoundingMode.ROUND_HALF_ODD:Lorg/apache/commons/math3/dfp/DfpField$RoundingMode; (2, 1)
	146 aastore (2, 1)
	147 dup (2, 1)
	148 bipush (2, 1)
	149 6 (2, 1)
	150 getstatic (2, 1)
	151 org/apache/commons/math3/dfp/DfpField$RoundingMode.ROUND_CEIL:Lorg/apache/commons/math3/dfp/DfpField$RoundingMode; (2, 1)
	153 aastore (2, 1)
	154 dup (2, 1)
	155 bipush (2, 1)
	156 7 (2, 1)
	157 getstatic (2, 1)
	158 org/apache/commons/math3/dfp/DfpField$RoundingMode.ROUND_FLOOR:Lorg/apache/commons/math3/dfp/DfpField$RoundingMode; (2, 1)
	160 aastore (2, 1)
	161 putstatic (2, 1)
	162 org/apache/commons/math3/dfp/DfpField$RoundingMode.$VALUES:[Lorg/apache/commons/math3/dfp/DfpField$RoundingMode; (2, 1)
	164 return (0, 1)

