Method: <init>
	0 aload_0 (0, 0)
	1 invokespecial (0, 0)
	2 java/lang/Object.<init>:()V (0, 0)
	4 aload_0 (0, 0)
	5 iload_1 (0, 0)
	6 bipush (0, 0)
	7 13 (0, 0)
	8 if_icmpge (0, 0)
	9 7 (0, 0)
	11 iconst_4 (0, 0)
	12 goto (0, 0)
	13 8 (0, 0)
	15 iload_1 (0, 0)
	16 iconst_3 (0, 0)
	17 iadd (0, 0)
	18 iconst_4 (0, 0)
	19 idiv (0, 0)
	20 putfield (0, 0)
	21 org/apache/commons/math3/dfp/DfpField.radixDigits:I (0, 0)
	23 aload_0 (0, 0)
	24 getstatic (0, 0)
	25 org/apache/commons/math3/dfp/DfpField$RoundingMode.ROUND_HALF_EVEN:Lorg/apache/commons/math3/dfp/DfpField$RoundingMode; (0, 0)
	27 putfield (0, 0)
	28 org/apache/commons/math3/dfp/DfpField.rMode:Lorg/apache/commons/math3/dfp/DfpField$RoundingMode; (0, 0)
	30 aload_0 (0, 0)
	31 iconst_0 (0, 0)
	32 putfield (0, 0)
	33 org/apache/commons/math3/dfp/DfpField.ieeeFlags:I (0, 0)
	35 aload_0 (0, 0)
	36 new (0, 0)
	37 org/apache/commons/math3/dfp/Dfp (0, 0)
	39 dup (0, 0)
	40 aload_0 (0, 0)
	41 iconst_0 (0, 0)
	42 invokespecial (0, 0)
	43 org/apache/commons/math3/dfp/Dfp.<init>:(Lorg/apache/commons/math3/dfp/DfpField;I)V (0, 0)
	45 putfield (0, 0)
	46 org/apache/commons/math3/dfp/DfpField.zero:Lorg/apache/commons/math3/dfp/Dfp; (0, 0)
	48 aload_0 (0, 0)
	49 new (0, 0)
	50 org/apache/commons/math3/dfp/Dfp (0, 0)
	52 dup (0, 0)
	53 aload_0 (0, 0)
	54 iconst_1 (0, 0)
	55 invokespecial (0, 0)
	56 org/apache/commons/math3/dfp/Dfp.<init>:(Lorg/apache/commons/math3/dfp/DfpField;I)V (0, 0)
	58 putfield (0, 0)
	59 org/apache/commons/math3/dfp/DfpField.one:Lorg/apache/commons/math3/dfp/Dfp; (0, 0)
	61 aload_0 (0, 0)
	62 new (0, 0)
	63 org/apache/commons/math3/dfp/Dfp (0, 0)
	65 dup (0, 0)
	66 aload_0 (0, 0)
	67 iconst_2 (0, 0)
	68 invokespecial (0, 0)
	69 org/apache/commons/math3/dfp/Dfp.<init>:(Lorg/apache/commons/math3/dfp/DfpField;I)V (0, 0)
	71 putfield (0, 0)
	72 org/apache/commons/math3/dfp/DfpField.two:Lorg/apache/commons/math3/dfp/Dfp; (0, 0)
	74 iload_2 (1, 1)
	75 ifeq (1, 1)
	76 231 (1, 1)
	78 ldc (1, 1)
	79 org/apache/commons/math3/dfp/DfpField (1, 1)
	80 dup (1, 1)
	81 astore_3 (1, 1)
	82 monitorenter (1, 1)
	83 iload_1 (1, 1)
	84 bipush (1, 1)
	85 67 (1, 1)
	86 if_icmpge (1, 1)
	87 9 (1, 1)
	89 sipush (1, 1)
	90 200 (1, 1)
	92 goto (1, 1)
	93 6 (1, 1)
	95 iconst_3 (1, 1)
	96 iload_1 (1, 1)
	97 imul (1, 1)
	98 invokestatic (1, 1)
	99 org/apache/commons/math3/dfp/DfpField.computeStringConstants:(I)V (1, 1)
	101 aload_0 (1, 1)
	102 new (1, 1)
	103 org/apache/commons/math3/dfp/Dfp (1, 1)
	105 dup (1, 1)
	106 aload_0 (1, 1)
	107 getstatic (1, 1)
	108 org/apache/commons/math3/dfp/DfpField.sqr2String:Ljava/lang/String; (1, 1)
	110 invokespecial (1, 1)
	111 org/apache/commons/math3/dfp/Dfp.<init>:(Lorg/apache/commons/math3/dfp/DfpField;Ljava/lang/String;)V (1, 1)
	113 putfield (1, 1)
	114 org/apache/commons/math3/dfp/DfpField.sqr2:Lorg/apache/commons/math3/dfp/Dfp; (1, 1)
	116 aload_0 (1, 1)
	117 aload_0 (1, 1)
	118 getstatic (1, 1)
	119 org/apache/commons/math3/dfp/DfpField.sqr2String:Ljava/lang/String; (1, 1)
	121 invokespecial (1, 1)
	122 org/apache/commons/math3/dfp/DfpField.split:(Ljava/lang/String;)[Lorg/apache/commons/math3/dfp/Dfp; (1, 1)
	124 putfield (1, 1)
	125 org/apache/commons/math3/dfp/DfpField.sqr2Split:[Lorg/apache/commons/math3/dfp/Dfp; (1, 1)
	127 aload_0 (1, 1)
	128 new (1, 1)
	129 org/apache/commons/math3/dfp/Dfp (1, 1)
	131 dup (1, 1)
	132 aload_0 (1, 1)
	133 getstatic (1, 1)
	134 org/apache/commons/math3/dfp/DfpField.sqr2ReciprocalString:Ljava/lang/String; (1, 1)
	136 invokespecial (1, 1)
	137 org/apache/commons/math3/dfp/Dfp.<init>:(Lorg/apache/commons/math3/dfp/DfpField;Ljava/lang/String;)V (1, 1)
	139 putfield (1, 1)
	140 org/apache/commons/math3/dfp/DfpField.sqr2Reciprocal:Lorg/apache/commons/math3/dfp/Dfp; (1, 1)
	142 aload_0 (1, 1)
	143 new (1, 1)
	144 org/apache/commons/math3/dfp/Dfp (1, 1)
	146 dup (1, 1)
	147 aload_0 (1, 1)
	148 getstatic (1, 1)
	149 org/apache/commons/math3/dfp/DfpField.sqr3String:Ljava/lang/String; (1, 1)
	151 invokespecial (1, 1)
	152 org/apache/commons/math3/dfp/Dfp.<init>:(Lorg/apache/commons/math3/dfp/DfpField;Ljava/lang/String;)V (1, 1)
	154 putfield (1, 1)
	155 org/apache/commons/math3/dfp/DfpField.sqr3:Lorg/apache/commons/math3/dfp/Dfp; (1, 1)
	157 aload_0 (1, 1)
	158 new (1, 1)
	159 org/apache/commons/math3/dfp/Dfp (1, 1)
	161 dup (1, 1)
	162 aload_0 (1, 1)
	163 getstatic (1, 1)
	164 org/apache/commons/math3/dfp/DfpField.sqr3ReciprocalString:Ljava/lang/String; (1, 1)
	166 invokespecial (1, 1)
	167 org/apache/commons/math3/dfp/Dfp.<init>:(Lorg/apache/commons/math3/dfp/DfpField;Ljava/lang/String;)V (1, 1)
	169 putfield (1, 1)
	170 org/apache/commons/math3/dfp/DfpField.sqr3Reciprocal:Lorg/apache/commons/math3/dfp/Dfp; (1, 1)
	172 aload_0 (1, 1)
	173 new (1, 1)
	174 org/apache/commons/math3/dfp/Dfp (1, 1)
	176 dup (1, 1)
	177 aload_0 (1, 1)
	178 getstatic (1, 1)
	179 org/apache/commons/math3/dfp/DfpField.piString:Ljava/lang/String; (1, 1)
	181 invokespecial (1, 1)
	182 org/apache/commons/math3/dfp/Dfp.<init>:(Lorg/apache/commons/math3/dfp/DfpField;Ljava/lang/String;)V (1, 1)
	184 putfield (1, 1)
	185 org/apache/commons/math3/dfp/DfpField.pi:Lorg/apache/commons/math3/dfp/Dfp; (1, 1)
	187 aload_0 (1, 1)
	188 aload_0 (1, 1)
	189 getstatic (1, 1)
	190 org/apache/commons/math3/dfp/DfpField.piString:Ljava/lang/String; (1, 1)
	192 invokespecial (1, 1)
	193 org/apache/commons/math3/dfp/DfpField.split:(Ljava/lang/String;)[Lorg/apache/commons/math3/dfp/Dfp; (1, 1)
	195 putfield (1, 1)
	196 org/apache/commons/math3/dfp/DfpField.piSplit:[Lorg/apache/commons/math3/dfp/Dfp; (1, 1)
	198 aload_0 (1, 1)
	199 new (1, 1)
	200 org/apache/commons/math3/dfp/Dfp (1, 1)
	202 dup (1, 1)
	203 aload_0 (1, 1)
	204 getstatic (1, 1)
	205 org/apache/commons/math3/dfp/DfpField.eString:Ljava/lang/String; (1, 1)
	207 invokespecial (1, 1)
	208 org/apache/commons/math3/dfp/Dfp.<init>:(Lorg/apache/commons/math3/dfp/DfpField;Ljava/lang/String;)V (1, 1)
	210 putfield (1, 1)
	211 org/apache/commons/math3/dfp/DfpField.e:Lorg/apache/commons/math3/dfp/Dfp; (1, 1)
	213 aload_0 (1, 1)
	214 aload_0 (1, 1)
	215 getstatic (1, 1)
	216 org/apache/commons/math3/dfp/DfpField.eString:Ljava/lang/String; (1, 1)
	218 invokespecial (1, 1)
	219 org/apache/commons/math3/dfp/DfpField.split:(Ljava/lang/String;)[Lorg/apache/commons/math3/dfp/Dfp; (1, 1)
	221 putfield (1, 1)
	222 org/apache/commons/math3/dfp/DfpField.eSplit:[Lorg/apache/commons/math3/dfp/Dfp; (1, 1)
	224 aload_0 (1, 1)
	225 new (1, 1)
	226 org/apache/commons/math3/dfp/Dfp (1, 1)
	228 dup (1, 1)
	229 aload_0 (1, 1)
	230 getstatic (1, 1)
	231 org/apache/commons/math3/dfp/DfpField.ln2String:Ljava/lang/String; (1, 1)
	233 invokespecial (1, 1)
	234 org/apache/commons/math3/dfp/Dfp.<init>:(Lorg/apache/commons/math3/dfp/DfpField;Ljava/lang/String;)V (1, 1)
	236 putfield (1, 1)
	237 org/apache/commons/math3/dfp/DfpField.ln2:Lorg/apache/commons/math3/dfp/Dfp; (1, 1)
	239 aload_0 (1, 1)
	240 aload_0 (1, 1)
	241 getstatic (1, 1)
	242 org/apache/commons/math3/dfp/DfpField.ln2String:Ljava/lang/String; (1, 1)
	244 invokespecial (1, 1)
	245 org/apache/commons/math3/dfp/DfpField.split:(Ljava/lang/String;)[Lorg/apache/commons/math3/dfp/Dfp; (1, 1)
	247 putfield (1, 1)
	248 org/apache/commons/math3/dfp/DfpField.ln2Split:[Lorg/apache/commons/math3/dfp/Dfp; (1, 1)
	250 aload_0 (1, 1)
	251 new (1, 1)
	252 org/apache/commons/math3/dfp/Dfp (1, 1)
	254 dup (1, 1)
	255 aload_0 (1, 1)
	256 getstatic (1, 1)
	257 org/apache/commons/math3/dfp/DfpField.ln5String:Ljava/lang/String; (1, 1)
	259 invokespecial (1, 1)
	260 org/apache/commons/math3/dfp/Dfp.<init>:(Lorg/apache/commons/math3/dfp/DfpField;Ljava/lang/String;)V (1, 1)
	262 putfield (1, 1)
	263 org/apache/commons/math3/dfp/DfpField.ln5:Lorg/apache/commons/math3/dfp/Dfp; (1, 1)
	265 aload_0 (1, 1)
	266 aload_0 (1, 1)
	267 getstatic (1, 1)
	268 org/apache/commons/math3/dfp/DfpField.ln5String:Ljava/lang/String; (1, 1)
	270 invokespecial (1, 1)
	271 org/apache/commons/math3/dfp/DfpField.split:(Ljava/lang/String;)[Lorg/apache/commons/math3/dfp/Dfp; (1, 1)
	273 putfield (1, 1)
	274 org/apache/commons/math3/dfp/DfpField.ln5Split:[Lorg/apache/commons/math3/dfp/Dfp; (1, 1)
	276 aload_0 (1, 1)
	277 new (1, 1)
	278 org/apache/commons/math3/dfp/Dfp (1, 1)
	280 dup (1, 1)
	281 aload_0 (1, 1)
	282 getstatic (1, 1)
	283 org/apache/commons/math3/dfp/DfpField.ln10String:Ljava/lang/String; (1, 1)
	285 invokespecial (1, 1)
	286 org/apache/commons/math3/dfp/Dfp.<init>:(Lorg/apache/commons/math3/dfp/DfpField;Ljava/lang/String;)V (1, 1)
	288 putfield (1, 1)
	289 org/apache/commons/math3/dfp/DfpField.ln10:Lorg/apache/commons/math3/dfp/Dfp; (1, 1)
	291 aload_3 (1, 1)
	292 monitorexit (1, 1)
	293 goto (1, 1)
	294 10 (1, 1)
	296 astore (1, 1)
	297 #4 (1, 1)
	298 aload_3 (1, 1)
	299 monitorexit (1, 1)
	300 aload (1, 1)
	301 #4 (1, 1)
	302 athrow (1, 1)
	303 goto (1, 1)
	304 73 (1, 1)
	306 aload_0 (3, 4)
	307 aconst_null (3, 4)
	308 putfield (3, 4)
	309 org/apache/commons/math3/dfp/DfpField.sqr2:Lorg/apache/commons/math3/dfp/Dfp; (3, 4)
	311 aload_0 (3, 4)
	312 aconst_null (3, 4)
	313 putfield (3, 4)
	314 org/apache/commons/math3/dfp/DfpField.sqr2Split:[Lorg/apache/commons/math3/dfp/Dfp; (3, 4)
	316 aload_0 (3, 4)
	317 aconst_null (3, 4)
	318 putfield (3, 4)
	319 org/apache/commons/math3/dfp/DfpField.sqr2Reciprocal:Lorg/apache/commons/math3/dfp/Dfp; (3, 4)
	321 aload_0 (3, 4)
	322 aconst_null (3, 4)
	323 putfield (3, 4)
	324 org/apache/commons/math3/dfp/DfpField.sqr3:Lorg/apache/commons/math3/dfp/Dfp; (3, 4)
	326 aload_0 (3, 4)
	327 aconst_null (3, 4)
	328 putfield (3, 4)
	329 org/apache/commons/math3/dfp/DfpField.sqr3Reciprocal:Lorg/apache/commons/math3/dfp/Dfp; (3, 4)
	331 aload_0 (3, 4)
	332 aconst_null (3, 4)
	333 putfield (3, 4)
	334 org/apache/commons/math3/dfp/DfpField.pi:Lorg/apache/commons/math3/dfp/Dfp; (3, 4)
	336 aload_0 (3, 4)
	337 aconst_null (3, 4)
	338 putfield (3, 4)
	339 org/apache/commons/math3/dfp/DfpField.piSplit:[Lorg/apache/commons/math3/dfp/Dfp; (3, 4)
	341 aload_0 (3, 4)
	342 aconst_null (3, 4)
	343 putfield (3, 4)
	344 org/apache/commons/math3/dfp/DfpField.e:Lorg/apache/commons/math3/dfp/Dfp; (3, 4)
	346 aload_0 (3, 4)
	347 aconst_null (3, 4)
	348 putfield (3, 4)
	349 org/apache/commons/math3/dfp/DfpField.eSplit:[Lorg/apache/commons/math3/dfp/Dfp; (3, 4)
	351 aload_0 (3, 4)
	352 aconst_null (3, 4)
	353 putfield (3, 4)
	354 org/apache/commons/math3/dfp/DfpField.ln2:Lorg/apache/commons/math3/dfp/Dfp; (3, 4)
	356 aload_0 (3, 4)
	357 aconst_null (3, 4)
	358 putfield (3, 4)
	359 org/apache/commons/math3/dfp/DfpField.ln2Split:[Lorg/apache/commons/math3/dfp/Dfp; (3, 4)
	361 aload_0 (3, 4)
	362 aconst_null (3, 4)
	363 putfield (3, 4)
	364 org/apache/commons/math3/dfp/DfpField.ln5:Lorg/apache/commons/math3/dfp/Dfp; (3, 4)
	366 aload_0 (3, 4)
	367 aconst_null (3, 4)
	368 putfield (3, 4)
	369 org/apache/commons/math3/dfp/DfpField.ln5Split:[Lorg/apache/commons/math3/dfp/Dfp; (3, 4)
	371 aload_0 (3, 4)
	372 aconst_null (3, 4)
	373 putfield (3, 4)
	374 org/apache/commons/math3/dfp/DfpField.ln10:Lorg/apache/commons/math3/dfp/Dfp; (3, 4)
	376 return (0, 0)

Method: getRadixDigits
	0 aload_0 (0, 0)
	1 getfield (0, 0)
	2 org/apache/commons/math3/dfp/DfpField.radixDigits:I (0, 0)
	4 ireturn (0, 0)

Method: setRoundingMode
	0 aload_0 (0, 0)
	1 aload_1 (0, 0)
	2 putfield (0, 0)
	3 org/apache/commons/math3/dfp/DfpField.rMode:Lorg/apache/commons/math3/dfp/DfpField$RoundingMode; (0, 0)
	5 return (0, 0)

Method: getRoundingMode
	0 aload_0 (0, 0)
	1 getfield (0, 0)
	2 org/apache/commons/math3/dfp/DfpField.rMode:Lorg/apache/commons/math3/dfp/DfpField$RoundingMode; (0, 0)
	4 areturn (0, 0)

Method: getIEEEFlags
	0 aload_0 (0, 0)
	1 getfield (0, 0)
	2 org/apache/commons/math3/dfp/DfpField.ieeeFlags:I (0, 0)
	4 ireturn (0, 0)

Method: clearIEEEFlags
	0 aload_0 (0, 0)
	1 iconst_0 (0, 0)
	2 putfield (0, 0)
	3 org/apache/commons/math3/dfp/DfpField.ieeeFlags:I (0, 0)
	5 return (0, 0)

Method: setIEEEFlags
	0 aload_0 (0, 0)
	1 iload_1 (0, 0)
	2 bipush (0, 0)
	3 31 (0, 0)
	4 iand (0, 0)
	5 putfield (0, 0)
	6 org/apache/commons/math3/dfp/DfpField.ieeeFlags:I (0, 0)
	8 return (0, 0)

Method: setIEEEFlagsBits
	0 aload_0 (0, 0)
	1 dup (0, 0)
	2 getfield (0, 0)
	3 org/apache/commons/math3/dfp/DfpField.ieeeFlags:I (0, 0)
	5 iload_1 (0, 0)
	6 bipush (0, 0)
	7 31 (0, 0)
	8 iand (0, 0)
	9 ior (0, 0)
	10 putfield (0, 0)
	11 org/apache/commons/math3/dfp/DfpField.ieeeFlags:I (0, 0)
	13 return (0, 0)

Method: newDfp
	0 new (0, 0)
	1 org/apache/commons/math3/dfp/Dfp (0, 0)
	3 dup (0, 0)
	4 aload_0 (0, 0)
	5 iload_1 (0, 0)
	6 iload_2 (0, 0)
	7 invokespecial (0, 0)
	8 org/apache/commons/math3/dfp/Dfp.<init>:(Lorg/apache/commons/math3/dfp/DfpField;BB)V (0, 0)
	10 areturn (0, 0)

Method: getZero
	0 aload_0 (0, 0)
	1 invokevirtual (0, 0)
	2 org/apache/commons/math3/dfp/DfpField.getZero:()Lorg/apache/commons/math3/dfp/Dfp; (0, 0)
	4 areturn (0, 0)

Method: getOne
	0 aload_0 (0, 0)
	1 invokevirtual (0, 0)
	2 org/apache/commons/math3/dfp/DfpField.getOne:()Lorg/apache/commons/math3/dfp/Dfp; (0, 0)
	4 areturn (0, 0)

Method: getRuntimeClass
	0 ldc (0, 0)
	1 org/apache/commons/math3/dfp/Dfp (0, 0)
	2 areturn (0, 0)

Method: getTwo
	0 aload_0 (0, 0)
	1 getfield (0, 0)
	2 org/apache/commons/math3/dfp/DfpField.two:Lorg/apache/commons/math3/dfp/Dfp; (0, 0)
	4 areturn (0, 0)

Method: getSqr2
	0 aload_0 (0, 0)
	1 getfield (0, 0)
	2 org/apache/commons/math3/dfp/DfpField.sqr2:Lorg/apache/commons/math3/dfp/Dfp; (0, 0)
	4 areturn (0, 0)

Method: getSqr2Split
	0 aload_0 (0, 0)
	1 getfield (0, 0)
	2 org/apache/commons/math3/dfp/DfpField.sqr2Split:[Lorg/apache/commons/math3/dfp/Dfp; (0, 0)
	4 invokevirtual (0, 0)
	5 [Lorg/apache/commons/math3/dfp/Dfp;.clone:()Ljava/lang/Object; (0, 0)
	7 checkcast (0, 0)
	8 [Lorg/apache/commons/math3/dfp/Dfp; (0, 0)
	10 areturn (0, 0)

Method: getSqr2Reciprocal
	0 aload_0 (0, 0)
	1 getfield (0, 0)
	2 org/apache/commons/math3/dfp/DfpField.sqr2Reciprocal:Lorg/apache/commons/math3/dfp/Dfp; (0, 0)
	4 areturn (0, 0)

Method: getSqr3
	0 aload_0 (0, 0)
	1 getfield (0, 0)
	2 org/apache/commons/math3/dfp/DfpField.sqr3:Lorg/apache/commons/math3/dfp/Dfp; (0, 0)
	4 areturn (0, 0)

Method: getSqr3Reciprocal
	0 aload_0 (0, 0)
	1 getfield (0, 0)
	2 org/apache/commons/math3/dfp/DfpField.sqr3Reciprocal:Lorg/apache/commons/math3/dfp/Dfp; (0, 0)
	4 areturn (0, 0)

Method: getPi
	0 aload_0 (0, 0)
	1 getfield (0, 0)
	2 org/apache/commons/math3/dfp/DfpField.pi:Lorg/apache/commons/math3/dfp/Dfp; (0, 0)
	4 areturn (0, 0)

Method: getPiSplit
	0 aload_0 (0, 0)
	1 getfield (0, 0)
	2 org/apache/commons/math3/dfp/DfpField.piSplit:[Lorg/apache/commons/math3/dfp/Dfp; (0, 0)
	4 invokevirtual (0, 0)
	5 [Lorg/apache/commons/math3/dfp/Dfp;.clone:()Ljava/lang/Object; (0, 0)
	7 checkcast (0, 0)
	8 [Lorg/apache/commons/math3/dfp/Dfp; (0, 0)
	10 areturn (0, 0)

Method: getE
	0 aload_0 (0, 0)
	1 getfield (0, 0)
	2 org/apache/commons/math3/dfp/DfpField.e:Lorg/apache/commons/math3/dfp/Dfp; (0, 0)
	4 areturn (0, 0)

Method: getESplit
	0 aload_0 (0, 0)
	1 getfield (0, 0)
	2 org/apache/commons/math3/dfp/DfpField.eSplit:[Lorg/apache/commons/math3/dfp/Dfp; (0, 0)
	4 invokevirtual (0, 0)
	5 [Lorg/apache/commons/math3/dfp/Dfp;.clone:()Ljava/lang/Object; (0, 0)
	7 checkcast (0, 0)
	8 [Lorg/apache/commons/math3/dfp/Dfp; (0, 0)
	10 areturn (0, 0)

Method: getLn2
	0 aload_0 (0, 0)
	1 getfield (0, 0)
	2 org/apache/commons/math3/dfp/DfpField.ln2:Lorg/apache/commons/math3/dfp/Dfp; (0, 0)
	4 areturn (0, 0)

Method: getLn2Split
	0 aload_0 (0, 0)
	1 getfield (0, 0)
	2 org/apache/commons/math3/dfp/DfpField.ln2Split:[Lorg/apache/commons/math3/dfp/Dfp; (0, 0)
	4 invokevirtual (0, 0)
	5 [Lorg/apache/commons/math3/dfp/Dfp;.clone:()Ljava/lang/Object; (0, 0)
	7 checkcast (0, 0)
	8 [Lorg/apache/commons/math3/dfp/Dfp; (0, 0)
	10 areturn (0, 0)

Method: getLn5
	0 aload_0 (0, 0)
	1 getfield (0, 0)
	2 org/apache/commons/math3/dfp/DfpField.ln5:Lorg/apache/commons/math3/dfp/Dfp; (0, 0)
	4 areturn (0, 0)

Method: getLn5Split
	0 aload_0 (0, 0)
	1 getfield (0, 0)
	2 org/apache/commons/math3/dfp/DfpField.ln5Split:[Lorg/apache/commons/math3/dfp/Dfp; (0, 0)
	4 invokevirtual (0, 0)
	5 [Lorg/apache/commons/math3/dfp/Dfp;.clone:()Ljava/lang/Object; (0, 0)
	7 checkcast (0, 0)
	8 [Lorg/apache/commons/math3/dfp/Dfp; (0, 0)
	10 areturn (0, 0)

Method: getLn10
	0 aload_0 (0, 0)
	1 getfield (0, 0)
	2 org/apache/commons/math3/dfp/DfpField.ln10:Lorg/apache/commons/math3/dfp/Dfp; (0, 0)
	4 areturn (0, 0)

Method: split
	0 iconst_2 (0, 0)
	1 anewarray (0, 0)
	2 org/apache/commons/math3/dfp/Dfp (0, 0)
	4 astore_2 (0, 0)
	5 iconst_1 (0, 0)
	6 istore_3 (0, 0)
	7 iconst_0 (0, 0)
	8 istore (0, 0)
	9 #4 (0, 0)
	10 iconst_0 (0, 0)
	11 istore (0, 0)
	12 #5 (0, 0)
	13 aload_1 (0, 0)
	14 invokevirtual (0, 0)
	15 java/lang/String.length:()I (0, 0)
	17 newarray (0, 0)
	18 5 (0, 0)
	19 astore (0, 0)
	20 #6 (0, 0)
	21 iconst_0 (1, 4)
	22 istore (1, 4)
	23 #7 (1, 4)
	24 iload (1, 4)
	25 #7 (1, 4)
	26 aload (1, 4)
	27 #6 (1, 4)
	28 arraylength (1, 4)
	29 if_icmpge (1, 4)
	30 114 (1, 4)
	32 aload (1, 4)
	33 #6 (1, 4)
	34 iload (1, 4)
	35 #7 (1, 4)
	36 aload_1 (1, 4)
	37 iload (1, 4)
	38 #7 (1, 4)
	39 invokevirtual (1, 4)
	40 java/lang/String.charAt:(I)C (1, 4)
	42 castore (1, 4)
	43 aload (2, 1)
	44 #6 (2, 1)
	45 iload (2, 1)
	46 #7 (2, 1)
	47 caload (2, 1)
	48 bipush (2, 1)
	49 49 (2, 1)
	50 if_icmplt (2, 1)
	51 15 (2, 1)
	53 aload (2, 1)
	54 #6 (2, 1)
	55 iload (2, 1)
	56 #7 (2, 1)
	57 caload (2, 1)
	58 bipush (2, 1)
	59 57 (2, 1)
	60 if_icmpgt (2, 1)
	61 5 (2, 1)
	63 iconst_0 (2, 1)
	64 istore_3 (2, 1)
	65 aload (2, 1)
	66 #6 (2, 1)
	67 iload (2, 1)
	68 #7 (2, 1)
	69 caload (2, 1)
	70 bipush (2, 1)
	71 46 (2, 1)
	72 if_icmpne (2, 1)
	73 18 (2, 1)
	75 iload (2, 1)
	76 #5 (2, 1)
	77 sipush (2, 1)
	78 400 (2, 1)
	80 iload (2, 1)
	81 #5 (2, 1)
	82 isub (2, 1)
	83 iconst_4 (2, 1)
	84 irem (2, 1)
	85 iadd (2, 1)
	86 istore (2, 1)
	87 #5 (2, 1)
	88 iconst_0 (2, 1)
	89 istore_3 (2, 1)
	90 iload (2, 1)
	91 #5 (2, 1)
	92 aload_0 (2, 1)
	93 getfield (2, 1)
	94 org/apache/commons/math3/dfp/DfpField.radixDigits:I (2, 1)
	96 iconst_2 (2, 1)
	97 idiv (2, 1)
	98 iconst_4 (2, 1)
	99 imul (2, 1)
	100 if_icmpne (2, 1)
	101 10 (2, 1)
	103 iload (2, 1)
	104 #7 (2, 1)
	105 istore (2, 1)
	106 #4 (2, 1)
	107 goto (2, 1)
	108 36 (2, 1)
	110 aload (2, 1)
	111 #6 (2, 1)
	112 iload (2, 1)
	113 #7 (2, 1)
	114 caload (2, 1)
	115 bipush (2, 1)
	116 48 (2, 1)
	117 if_icmplt (2, 1)
	118 20 (2, 1)
	120 aload (2, 1)
	121 #6 (2, 1)
	122 iload (2, 1)
	123 #7 (2, 1)
	124 caload (2, 1)
	125 bipush (2, 1)
	126 57 (2, 1)
	127 if_icmpgt (2, 1)
	128 10 (2, 1)
	130 iload_3 (2, 1)
	131 ifne (2, 1)
	132 6 (2, 1)
	134 iinc (2, 1)
	135 #5 (2, 1)
	136 -124 (2, 1)
	137 iinc (2, 1)
	138 #7 (2, 1)
	139 -89 (2, 1)
	140 goto (2, 1)
	141 -116 (2, 1)
	143 aload_2 (1, 4)
	144 iconst_0 (1, 4)
	145 new (1, 4)
	146 org/apache/commons/math3/dfp/Dfp (1, 4)
	148 dup (1, 4)
	149 aload_0 (1, 4)
	150 new (1, 4)
	151 java/lang/String (1, 4)
	153 dup (1, 4)
	154 aload (1, 4)
	155 #6 (1, 4)
	156 iconst_0 (1, 4)
	157 iload (1, 4)
	158 #4 (1, 4)
	159 invokespecial (1, 4)
	160 java/lang/String.<init>:([CII)V (1, 4)
	162 invokespecial (1, 4)
	163 org/apache/commons/math3/dfp/Dfp.<init>:(Lorg/apache/commons/math3/dfp/DfpField;Ljava/lang/String;)V (1, 4)
	165 aastore (1, 4)
	166 iconst_0 (2, 4)
	167 istore (2, 4)
	168 #7 (2, 4)
	169 iload (2, 4)
	170 #7 (2, 4)
	171 aload (2, 4)
	172 #6 (2, 4)
	173 arraylength (2, 4)
	174 if_icmpge (2, 4)
	175 54 (2, 4)
	177 aload (2, 4)
	178 #6 (2, 4)
	179 iload (2, 4)
	180 #7 (2, 4)
	181 aload_1 (2, 4)
	182 iload (2, 4)
	183 #7 (2, 4)
	184 invokevirtual (2, 4)
	185 java/lang/String.charAt:(I)C (2, 4)
	187 castore (2, 4)
	188 aload (3, 1)
	189 #6 (3, 1)
	190 iload (3, 1)
	191 #7 (3, 1)
	192 caload (3, 1)
	193 bipush (3, 1)
	194 48 (3, 1)
	195 if_icmplt (3, 1)
	196 27 (3, 1)
	198 aload (3, 1)
	199 #6 (3, 1)
	200 iload (3, 1)
	201 #7 (3, 1)
	202 caload (3, 1)
	203 bipush (3, 1)
	204 57 (3, 1)
	205 if_icmpgt (3, 1)
	206 17 (3, 1)
	208 iload (3, 1)
	209 #7 (3, 1)
	210 iload (3, 1)
	211 #4 (3, 1)
	212 if_icmpge (3, 1)
	213 10 (3, 1)
	215 aload (3, 1)
	216 #6 (3, 1)
	217 iload (3, 1)
	218 #7 (3, 1)
	219 bipush (3, 1)
	220 48 (3, 1)
	221 castore (3, 1)
	222 iinc (3, 1)
	223 #7 (3, 1)
	224 -89 (3, 1)
	225 goto (3, 1)
	226 -56 (3, 1)
	228 aload_2 (2, 4)
	229 iconst_1 (2, 4)
	230 new (2, 4)
	231 org/apache/commons/math3/dfp/Dfp (2, 4)
	233 dup (2, 4)
	234 aload_0 (2, 4)
	235 new (2, 4)
	236 java/lang/String (2, 4)
	238 dup (2, 4)
	239 aload (2, 4)
	240 #6 (2, 4)
	241 invokespecial (2, 4)
	242 java/lang/String.<init>:([C)V (2, 4)
	244 invokespecial (2, 4)
	245 org/apache/commons/math3/dfp/Dfp.<init>:(Lorg/apache/commons/math3/dfp/DfpField;Ljava/lang/String;)V (2, 4)
	247 aastore (2, 4)
	248 aload_2 (2, 4)
	249 areturn (2, 4)

Method: computeStringConstants
	0 getstatic (1, 1)
	1 org/apache/commons/math3/dfp/DfpField.sqr2String:Ljava/lang/String; (1, 1)
	3 ifnull (1, 1)
	4 15 (1, 1)
	6 getstatic (1, 1)
	7 org/apache/commons/math3/dfp/DfpField.sqr2String:Ljava/lang/String; (1, 1)
	9 invokevirtual (1, 1)
	10 java/lang/String.length:()I (1, 1)
	12 iload_0 (1, 1)
	13 iconst_3 (1, 1)
	14 isub (1, 1)
	15 if_icmpge (1, 1)
	16 174 (1, 1)
	18 new (1, 1)
	19 org/apache/commons/math3/dfp/DfpField (1, 1)
	21 dup (1, 1)
	22 iload_0 (1, 1)
	23 iconst_0 (1, 1)
	24 invokespecial (1, 1)
	25 org/apache/commons/math3/dfp/DfpField.<init>:(IZ)V (1, 1)
	27 astore_1 (1, 1)
	28 new (1, 1)
	29 org/apache/commons/math3/dfp/Dfp (1, 1)
	31 dup (1, 1)
	32 aload_1 (1, 1)
	33 iconst_1 (1, 1)
	34 invokespecial (1, 1)
	35 org/apache/commons/math3/dfp/Dfp.<init>:(Lorg/apache/commons/math3/dfp/DfpField;I)V (1, 1)
	37 astore_2 (1, 1)
	38 new (1, 1)
	39 org/apache/commons/math3/dfp/Dfp (1, 1)
	41 dup (1, 1)
	42 aload_1 (1, 1)
	43 iconst_2 (1, 1)
	44 invokespecial (1, 1)
	45 org/apache/commons/math3/dfp/Dfp.<init>:(Lorg/apache/commons/math3/dfp/DfpField;I)V (1, 1)
	47 astore_3 (1, 1)
	48 new (1, 1)
	49 org/apache/commons/math3/dfp/Dfp (1, 1)
	51 dup (1, 1)
	52 aload_1 (1, 1)
	53 iconst_3 (1, 1)
	54 invokespecial (1, 1)
	55 org/apache/commons/math3/dfp/Dfp.<init>:(Lorg/apache/commons/math3/dfp/DfpField;I)V (1, 1)
	57 astore (1, 1)
	58 #4 (1, 1)
	59 aload_3 (1, 1)
	60 invokevirtual (1, 1)
	61 org/apache/commons/math3/dfp/Dfp.sqrt:()Lorg/apache/commons/math3/dfp/Dfp; (1, 1)
	63 astore (1, 1)
	64 #5 (1, 1)
	65 aload (1, 1)
	66 #5 (1, 1)
	67 invokevirtual (1, 1)
	68 org/apache/commons/math3/dfp/Dfp.toString:()Ljava/lang/String; (1, 1)
	70 putstatic (1, 1)
	71 org/apache/commons/math3/dfp/DfpField.sqr2String:Ljava/lang/String; (1, 1)
	73 aload_2 (1, 1)
	74 aload (1, 1)
	75 #5 (1, 1)
	76 invokevirtual (1, 1)
	77 org/apache/commons/math3/dfp/Dfp.divide:(Lorg/apache/commons/math3/dfp/Dfp;)Lorg/apache/commons/math3/dfp/Dfp; (1, 1)
	79 invokevirtual (1, 1)
	80 org/apache/commons/math3/dfp/Dfp.toString:()Ljava/lang/String; (1, 1)
	82 putstatic (1, 1)
	83 org/apache/commons/math3/dfp/DfpField.sqr2ReciprocalString:Ljava/lang/String; (1, 1)
	85 aload (1, 1)
	86 #4 (1, 1)
	87 invokevirtual (1, 1)
	88 org/apache/commons/math3/dfp/Dfp.sqrt:()Lorg/apache/commons/math3/dfp/Dfp; (1, 1)
	90 astore (1, 1)
	91 #6 (1, 1)
	92 aload (1, 1)
	93 #6 (1, 1)
	94 invokevirtual (1, 1)
	95 org/apache/commons/math3/dfp/Dfp.toString:()Ljava/lang/String; (1, 1)
	97 putstatic (1, 1)
	98 org/apache/commons/math3/dfp/DfpField.sqr3String:Ljava/lang/String; (1, 1)
	100 aload_2 (1, 1)
	101 aload (1, 1)
	102 #6 (1, 1)
	103 invokevirtual (1, 1)
	104 org/apache/commons/math3/dfp/Dfp.divide:(Lorg/apache/commons/math3/dfp/Dfp;)Lorg/apache/commons/math3/dfp/Dfp; (1, 1)
	106 invokevirtual (1, 1)
	107 org/apache/commons/math3/dfp/Dfp.toString:()Ljava/lang/String; (1, 1)
	109 putstatic (1, 1)
	110 org/apache/commons/math3/dfp/DfpField.sqr3ReciprocalString:Ljava/lang/String; (1, 1)
	112 aload_2 (1, 1)
	113 aload_3 (1, 1)
	114 aload (1, 1)
	115 #4 (1, 1)
	116 invokestatic (1, 1)
	117 org/apache/commons/math3/dfp/DfpField.computePi:(Lorg/apache/commons/math3/dfp/Dfp;Lorg/apache/commons/math3/dfp/Dfp;Lorg/apache/commons/math3/dfp/Dfp;)Lorg/apache/commons/math3/dfp/Dfp; (1, 1)
	119 invokevirtual (1, 1)
	120 org/apache/commons/math3/dfp/Dfp.toString:()Ljava/lang/String; (1, 1)
	122 putstatic (1, 1)
	123 org/apache/commons/math3/dfp/DfpField.piString:Ljava/lang/String; (1, 1)
	125 aload_2 (1, 1)
	126 aload_2 (1, 1)
	127 invokestatic (1, 1)
	128 org/apache/commons/math3/dfp/DfpField.computeExp:(Lorg/apache/commons/math3/dfp/Dfp;Lorg/apache/commons/math3/dfp/Dfp;)Lorg/apache/commons/math3/dfp/Dfp; (1, 1)
	130 invokevirtual (1, 1)
	131 org/apache/commons/math3/dfp/Dfp.toString:()Ljava/lang/String; (1, 1)
	133 putstatic (1, 1)
	134 org/apache/commons/math3/dfp/DfpField.eString:Ljava/lang/String; (1, 1)
	136 aload_3 (1, 1)
	137 aload_2 (1, 1)
	138 aload_3 (1, 1)
	139 invokestatic (1, 1)
	140 org/apache/commons/math3/dfp/DfpField.computeLn:(Lorg/apache/commons/math3/dfp/Dfp;Lorg/apache/commons/math3/dfp/Dfp;Lorg/apache/commons/math3/dfp/Dfp;)Lorg/apache/commons/math3/dfp/Dfp; (1, 1)
	142 invokevirtual (1, 1)
	143 org/apache/commons/math3/dfp/Dfp.toString:()Ljava/lang/String; (1, 1)
	145 putstatic (1, 1)
	146 org/apache/commons/math3/dfp/DfpField.ln2String:Ljava/lang/String; (1, 1)
	148 new (1, 1)
	149 org/apache/commons/math3/dfp/Dfp (1, 1)
	151 dup (1, 1)
	152 aload_1 (1, 1)
	153 iconst_5 (1, 1)
	154 invokespecial (1, 1)
	155 org/apache/commons/math3/dfp/Dfp.<init>:(Lorg/apache/commons/math3/dfp/DfpField;I)V (1, 1)
	157 aload_2 (1, 1)
	158 aload_3 (1, 1)
	159 invokestatic (1, 1)
	160 org/apache/commons/math3/dfp/DfpField.computeLn:(Lorg/apache/commons/math3/dfp/Dfp;Lorg/apache/commons/math3/dfp/Dfp;Lorg/apache/commons/math3/dfp/Dfp;)Lorg/apache/commons/math3/dfp/Dfp; (1, 1)
	162 invokevirtual (1, 1)
	163 org/apache/commons/math3/dfp/Dfp.toString:()Ljava/lang/String; (1, 1)
	165 putstatic (1, 1)
	166 org/apache/commons/math3/dfp/DfpField.ln5String:Ljava/lang/String; (1, 1)
	168 new (1, 1)
	169 org/apache/commons/math3/dfp/Dfp (1, 1)
	171 dup (1, 1)
	172 aload_1 (1, 1)
	173 bipush (1, 1)
	174 10 (1, 1)
	175 invokespecial (1, 1)
	176 org/apache/commons/math3/dfp/Dfp.<init>:(Lorg/apache/commons/math3/dfp/DfpField;I)V (1, 1)
	178 aload_2 (1, 1)
	179 aload_3 (1, 1)
	180 invokestatic (1, 1)
	181 org/apache/commons/math3/dfp/DfpField.computeLn:(Lorg/apache/commons/math3/dfp/Dfp;Lorg/apache/commons/math3/dfp/Dfp;Lorg/apache/commons/math3/dfp/Dfp;)Lorg/apache/commons/math3/dfp/Dfp; (1, 1)
	183 invokevirtual (1, 1)
	184 org/apache/commons/math3/dfp/Dfp.toString:()Ljava/lang/String; (1, 1)
	186 putstatic (1, 1)
	187 org/apache/commons/math3/dfp/DfpField.ln10String:Ljava/lang/String; (1, 1)
	189 return (0, 0)

Method: computePi
	0 aload_1 (0, 0)
	1 invokevirtual (0, 0)
	2 org/apache/commons/math3/dfp/Dfp.sqrt:()Lorg/apache/commons/math3/dfp/Dfp; (0, 0)
	4 astore_3 (0, 0)
	5 aload_3 (0, 0)
	6 aload_0 (0, 0)
	7 invokevirtual (0, 0)
	8 org/apache/commons/math3/dfp/Dfp.subtract:(Lorg/apache/commons/math3/dfp/Dfp;)Lorg/apache/commons/math3/dfp/Dfp; (0, 0)
	10 astore (0, 0)
	11 #4 (0, 0)
	12 aload_1 (0, 0)
	13 aload_1 (0, 0)
	14 invokevirtual (0, 0)
	15 org/apache/commons/math3/dfp/Dfp.add:(Lorg/apache/commons/math3/dfp/Dfp;)Lorg/apache/commons/math3/dfp/Dfp; (0, 0)
	17 astore (0, 0)
	18 #5 (0, 0)
	19 aload_1 (0, 0)
	20 astore (0, 0)
	21 #6 (0, 0)
	22 aload_1 (0, 0)
	23 aload_2 (0, 0)
	24 aload_1 (0, 0)
	25 aload_3 (0, 0)
	26 invokevirtual (0, 0)
	27 org/apache/commons/math3/dfp/Dfp.multiply:(Lorg/apache/commons/math3/dfp/Dfp;)Lorg/apache/commons/math3/dfp/Dfp; (0, 0)
	29 invokevirtual (0, 0)
	30 org/apache/commons/math3/dfp/Dfp.subtract:(Lorg/apache/commons/math3/dfp/Dfp;)Lorg/apache/commons/math3/dfp/Dfp; (0, 0)
	32 invokevirtual (0, 0)
	33 org/apache/commons/math3/dfp/Dfp.multiply:(Lorg/apache/commons/math3/dfp/Dfp;)Lorg/apache/commons/math3/dfp/Dfp; (0, 0)
	35 astore (0, 0)
	36 #7 (0, 0)
	37 iconst_1 (4, 4)
	38 istore (4, 4)
	39 #8 (4, 4)
	40 iload (4, 4)
	41 #8 (4, 4)
	42 bipush (4, 4)
	43 20 (4, 4)
	44 if_icmpge (4, 4)
	45 144 (4, 4)
	47 aload (4, 4)
	48 #4 (4, 4)
	49 astore (4, 4)
	50 #9 (4, 4)
	51 aload (4, 4)
	52 #4 (4, 4)
	53 aload (4, 4)
	54 #4 (4, 4)
	55 invokevirtual (4, 4)
	56 org/apache/commons/math3/dfp/Dfp.multiply:(Lorg/apache/commons/math3/dfp/Dfp;)Lorg/apache/commons/math3/dfp/Dfp; (4, 4)
	58 astore (4, 4)
	59 #10 (4, 4)
	60 aload_0 (4, 4)
	61 aload (4, 4)
	62 #10 (4, 4)
	63 aload (4, 4)
	64 #10 (4, 4)
	65 invokevirtual (4, 4)
	66 org/apache/commons/math3/dfp/Dfp.multiply:(Lorg/apache/commons/math3/dfp/Dfp;)Lorg/apache/commons/math3/dfp/Dfp; (4, 4)
	68 invokevirtual (4, 4)
	69 org/apache/commons/math3/dfp/Dfp.subtract:(Lorg/apache/commons/math3/dfp/Dfp;)Lorg/apache/commons/math3/dfp/Dfp; (4, 4)
	71 astore (4, 4)
	72 #11 (4, 4)
	73 aload (4, 4)
	74 #11 (4, 4)
	75 invokevirtual (4, 4)
	76 org/apache/commons/math3/dfp/Dfp.sqrt:()Lorg/apache/commons/math3/dfp/Dfp; (4, 4)
	78 invokevirtual (4, 4)
	79 org/apache/commons/math3/dfp/Dfp.sqrt:()Lorg/apache/commons/math3/dfp/Dfp; (4, 4)
	81 astore (4, 4)
	82 #12 (4, 4)
	83 aload_0 (4, 4)
	84 aload (4, 4)
	85 #12 (4, 4)
	86 invokevirtual (4, 4)
	87 org/apache/commons/math3/dfp/Dfp.subtract:(Lorg/apache/commons/math3/dfp/Dfp;)Lorg/apache/commons/math3/dfp/Dfp; (4, 4)
	89 aload_0 (4, 4)
	90 aload (4, 4)
	91 #12 (4, 4)
	92 invokevirtual (4, 4)
	93 org/apache/commons/math3/dfp/Dfp.add:(Lorg/apache/commons/math3/dfp/Dfp;)Lorg/apache/commons/math3/dfp/Dfp; (4, 4)
	95 invokevirtual (4, 4)
	96 org/apache/commons/math3/dfp/Dfp.divide:(Lorg/apache/commons/math3/dfp/Dfp;)Lorg/apache/commons/math3/dfp/Dfp; (4, 4)
	98 astore (4, 4)
	99 #4 (4, 4)
	100 aload (4, 4)
	101 #6 (4, 4)
	102 aload (4, 4)
	103 #5 (4, 4)
	104 invokevirtual (4, 4)
	105 org/apache/commons/math3/dfp/Dfp.multiply:(Lorg/apache/commons/math3/dfp/Dfp;)Lorg/apache/commons/math3/dfp/Dfp; (4, 4)
	107 astore (4, 4)
	108 #6 (4, 4)
	109 aload_0 (4, 4)
	110 aload (4, 4)
	111 #4 (4, 4)
	112 invokevirtual (4, 4)
	113 org/apache/commons/math3/dfp/Dfp.add:(Lorg/apache/commons/math3/dfp/Dfp;)Lorg/apache/commons/math3/dfp/Dfp; (4, 4)
	115 astore (4, 4)
	116 #13 (4, 4)
	117 aload (4, 4)
	118 #13 (4, 4)
	119 aload (4, 4)
	120 #13 (4, 4)
	121 invokevirtual (4, 4)
	122 org/apache/commons/math3/dfp/Dfp.multiply:(Lorg/apache/commons/math3/dfp/Dfp;)Lorg/apache/commons/math3/dfp/Dfp; (4, 4)
	124 astore (4, 4)
	125 #14 (4, 4)
	126 aload (4, 4)
	127 #7 (4, 4)
	128 aload (4, 4)
	129 #14 (4, 4)
	130 aload (4, 4)
	131 #14 (4, 4)
	132 invokevirtual (4, 4)
	133 org/apache/commons/math3/dfp/Dfp.multiply:(Lorg/apache/commons/math3/dfp/Dfp;)Lorg/apache/commons/math3/dfp/Dfp; (4, 4)
	135 invokevirtual (4, 4)
	136 org/apache/commons/math3/dfp/Dfp.multiply:(Lorg/apache/commons/math3/dfp/Dfp;)Lorg/apache/commons/math3/dfp/Dfp; (4, 4)
	138 aload (4, 4)
	139 #6 (4, 4)
	140 aload (4, 4)
	141 #4 (4, 4)
	142 invokevirtual (4, 4)
	143 org/apache/commons/math3/dfp/Dfp.multiply:(Lorg/apache/commons/math3/dfp/Dfp;)Lorg/apache/commons/math3/dfp/Dfp; (4, 4)
	145 aload_0 (4, 4)
	146 aload (4, 4)
	147 #4 (4, 4)
	148 invokevirtual (4, 4)
	149 org/apache/commons/math3/dfp/Dfp.add:(Lorg/apache/commons/math3/dfp/Dfp;)Lorg/apache/commons/math3/dfp/Dfp; (4, 4)
	151 aload (4, 4)
	152 #4 (4, 4)
	153 aload (4, 4)
	154 #4 (4, 4)
	155 invokevirtual (4, 4)
	156 org/apache/commons/math3/dfp/Dfp.multiply:(Lorg/apache/commons/math3/dfp/Dfp;)Lorg/apache/commons/math3/dfp/Dfp; (4, 4)
	158 invokevirtual (4, 4)
	159 org/apache/commons/math3/dfp/Dfp.add:(Lorg/apache/commons/math3/dfp/Dfp;)Lorg/apache/commons/math3/dfp/Dfp; (4, 4)
	161 invokevirtual (4, 4)
	162 org/apache/commons/math3/dfp/Dfp.multiply:(Lorg/apache/commons/math3/dfp/Dfp;)Lorg/apache/commons/math3/dfp/Dfp; (4, 4)
	164 invokevirtual (4, 4)
	165 org/apache/commons/math3/dfp/Dfp.subtract:(Lorg/apache/commons/math3/dfp/Dfp;)Lorg/apache/commons/math3/dfp/Dfp; (4, 4)
	167 astore (4, 4)
	168 #7 (4, 4)
	169 aload (5, 1)
	170 #4 (5, 1)
	171 aload (5, 1)
	172 #9 (5, 1)
	173 invokevirtual (5, 1)
	174 org/apache/commons/math3/dfp/Dfp.equals:(Ljava/lang/Object;)Z (5, 1)
	176 ifeq (5, 1)
	177 6 (5, 1)
	179 goto (5, 1)
	180 9 (5, 1)
	182 iinc (5, 1)
	183 #8 (5, 1)
	184 -89 (5, 1)
	185 goto (5, 1)
	186 -145 (5, 1)
	188 aload_0 (4, 4)
	189 aload (4, 4)
	190 #7 (4, 4)
	191 invokevirtual (4, 4)
	192 org/apache/commons/math3/dfp/Dfp.divide:(Lorg/apache/commons/math3/dfp/Dfp;)Lorg/apache/commons/math3/dfp/Dfp; (4, 4)
	194 areturn (1, 4)

Method: computeExp
	0 new (0, 0)
	1 org/apache/commons/math3/dfp/Dfp (0, 0)
	3 dup (0, 0)
	4 aload_1 (0, 0)
	5 invokespecial (0, 0)
	6 org/apache/commons/math3/dfp/Dfp.<init>:(Lorg/apache/commons/math3/dfp/Dfp;)V (0, 0)
	8 astore_2 (0, 0)
	9 new (0, 0)
	10 org/apache/commons/math3/dfp/Dfp (0, 0)
	12 dup (0, 0)
	13 aload_1 (0, 0)
	14 invokespecial (0, 0)
	15 org/apache/commons/math3/dfp/Dfp.<init>:(Lorg/apache/commons/math3/dfp/Dfp;)V (0, 0)
	17 astore_3 (0, 0)
	18 new (0, 0)
	19 org/apache/commons/math3/dfp/Dfp (0, 0)
	21 dup (0, 0)
	22 aload_1 (0, 0)
	23 invokespecial (0, 0)
	24 org/apache/commons/math3/dfp/Dfp.<init>:(Lorg/apache/commons/math3/dfp/Dfp;)V (0, 0)
	26 astore (0, 0)
	27 #4 (0, 0)
	28 new (0, 0)
	29 org/apache/commons/math3/dfp/Dfp (0, 0)
	31 dup (0, 0)
	32 aload_1 (0, 0)
	33 invokespecial (0, 0)
	34 org/apache/commons/math3/dfp/Dfp.<init>:(Lorg/apache/commons/math3/dfp/Dfp;)V (0, 0)
	36 astore (0, 0)
	37 #5 (0, 0)
	38 new (0, 0)
	39 org/apache/commons/math3/dfp/Dfp (0, 0)
	41 dup (0, 0)
	42 aload_1 (0, 0)
	43 invokespecial (0, 0)
	44 org/apache/commons/math3/dfp/Dfp.<init>:(Lorg/apache/commons/math3/dfp/Dfp;)V (0, 0)
	46 astore (0, 0)
	47 #6 (0, 0)
	48 iconst_0 (1, 4)
	49 istore (1, 4)
	50 #7 (1, 4)
	51 iload (1, 4)
	52 #7 (1, 4)
	53 sipush (1, 4)
	54 10000 (1, 4)
	56 if_icmpge (1, 4)
	57 66 (1, 4)
	59 aload (1, 4)
	60 #6 (1, 4)
	61 aload_0 (1, 4)
	62 invokevirtual (1, 4)
	63 org/apache/commons/math3/dfp/Dfp.multiply:(Lorg/apache/commons/math3/dfp/Dfp;)Lorg/apache/commons/math3/dfp/Dfp; (1, 4)
	65 astore (1, 4)
	66 #6 (1, 4)
	67 aload_2 (1, 4)
	68 aload (1, 4)
	69 #6 (1, 4)
	70 aload (1, 4)
	71 #4 (1, 4)
	72 invokevirtual (1, 4)
	73 org/apache/commons/math3/dfp/Dfp.divide:(Lorg/apache/commons/math3/dfp/Dfp;)Lorg/apache/commons/math3/dfp/Dfp; (1, 4)
	75 invokevirtual (1, 4)
	76 org/apache/commons/math3/dfp/Dfp.add:(Lorg/apache/commons/math3/dfp/Dfp;)Lorg/apache/commons/math3/dfp/Dfp; (1, 4)
	78 astore_2 (1, 4)
	79 aload (1, 4)
	80 #5 (1, 4)
	81 aload_1 (1, 4)
	82 invokevirtual (1, 4)
	83 org/apache/commons/math3/dfp/Dfp.add:(Lorg/apache/commons/math3/dfp/Dfp;)Lorg/apache/commons/math3/dfp/Dfp; (1, 4)
	85 astore (1, 4)
	86 #5 (1, 4)
	87 aload (1, 4)
	88 #4 (1, 4)
	89 aload (1, 4)
	90 #5 (1, 4)
	91 invokevirtual (1, 4)
	92 org/apache/commons/math3/dfp/Dfp.multiply:(Lorg/apache/commons/math3/dfp/Dfp;)Lorg/apache/commons/math3/dfp/Dfp; (1, 4)
	94 astore (1, 4)
	95 #4 (1, 4)
	96 aload_2 (2, 1)
	97 aload_3 (2, 1)
	98 invokevirtual (2, 1)
	99 org/apache/commons/math3/dfp/Dfp.equals:(Ljava/lang/Object;)Z (2, 1)
	101 ifeq (2, 1)
	102 6 (2, 1)
	104 goto (2, 1)
	105 18 (2, 1)
	107 new (1, 4)
	108 org/apache/commons/math3/dfp/Dfp (1, 4)
	110 dup (1, 4)
	111 aload_2 (1, 4)
	112 invokespecial (1, 4)
	113 org/apache/commons/math3/dfp/Dfp.<init>:(Lorg/apache/commons/math3/dfp/Dfp;)V (1, 4)
	115 astore_3 (1, 4)
	116 iinc (1, 4)
	117 #7 (1, 4)
	118 -89 (1, 4)
	119 goto (1, 4)
	120 -68 (1, 4)
	122 aload_2 (0, 0)
	123 areturn (0, 0)

Method: computeLn
	0 iconst_1 (0, 0)
	1 istore_3 (0, 0)
	2 aload_0 (0, 0)
	3 new (0, 0)
	4 org/apache/commons/math3/dfp/Dfp (0, 0)
	6 dup (0, 0)
	7 aload_0 (0, 0)
	8 invokevirtual (0, 0)
	9 org/apache/commons/math3/dfp/Dfp.getField:()Lorg/apache/commons/math3/dfp/DfpField; (0, 0)
	11 iconst_m1 (0, 0)
	12 invokespecial (0, 0)
	13 org/apache/commons/math3/dfp/Dfp.<init>:(Lorg/apache/commons/math3/dfp/DfpField;I)V (0, 0)
	15 invokevirtual (0, 0)
	16 org/apache/commons/math3/dfp/Dfp.add:(Lorg/apache/commons/math3/dfp/Dfp;)Lorg/apache/commons/math3/dfp/Dfp; (0, 0)
	18 aload_0 (0, 0)
	19 aload_1 (0, 0)
	20 invokevirtual (0, 0)
	21 org/apache/commons/math3/dfp/Dfp.add:(Lorg/apache/commons/math3/dfp/Dfp;)Lorg/apache/commons/math3/dfp/Dfp; (0, 0)
	23 invokevirtual (0, 0)
	24 org/apache/commons/math3/dfp/Dfp.divide:(Lorg/apache/commons/math3/dfp/Dfp;)Lorg/apache/commons/math3/dfp/Dfp; (0, 0)
	26 astore (0, 0)
	27 #4 (0, 0)
	28 new (0, 0)
	29 org/apache/commons/math3/dfp/Dfp (0, 0)
	31 dup (0, 0)
	32 aload (0, 0)
	33 #4 (0, 0)
	34 invokespecial (0, 0)
	35 org/apache/commons/math3/dfp/Dfp.<init>:(Lorg/apache/commons/math3/dfp/Dfp;)V (0, 0)
	37 astore (0, 0)
	38 #5 (0, 0)
	39 new (0, 0)
	40 org/apache/commons/math3/dfp/Dfp (0, 0)
	42 dup (0, 0)
	43 aload (0, 0)
	44 #4 (0, 0)
	45 invokespecial (0, 0)
	46 org/apache/commons/math3/dfp/Dfp.<init>:(Lorg/apache/commons/math3/dfp/Dfp;)V (0, 0)
	48 astore (0, 0)
	49 #6 (0, 0)
	50 new (0, 0)
	51 org/apache/commons/math3/dfp/Dfp (0, 0)
	53 dup (0, 0)
	54 aload (0, 0)
	55 #5 (0, 0)
	56 invokespecial (0, 0)
	57 org/apache/commons/math3/dfp/Dfp.<init>:(Lorg/apache/commons/math3/dfp/Dfp;)V (0, 0)
	59 astore (0, 0)
	60 #7 (0, 0)
	61 iconst_0 (1, 4)
	62 istore (1, 4)
	63 #8 (1, 4)
	64 iload (1, 4)
	65 #8 (1, 4)
	66 sipush (1, 4)
	67 10000 (1, 4)
	69 if_icmpge (1, 4)
	70 71 (1, 4)
	72 aload (1, 4)
	73 #6 (1, 4)
	74 aload (1, 4)
	75 #4 (1, 4)
	76 invokevirtual (1, 4)
	77 org/apache/commons/math3/dfp/Dfp.multiply:(Lorg/apache/commons/math3/dfp/Dfp;)Lorg/apache/commons/math3/dfp/Dfp; (1, 4)
	79 astore (1, 4)
	80 #6 (1, 4)
	81 aload (1, 4)
	82 #6 (1, 4)
	83 aload (1, 4)
	84 #4 (1, 4)
	85 invokevirtual (1, 4)
	86 org/apache/commons/math3/dfp/Dfp.multiply:(Lorg/apache/commons/math3/dfp/Dfp;)Lorg/apache/commons/math3/dfp/Dfp; (1, 4)
	88 astore (1, 4)
	89 #6 (1, 4)
	90 iinc (1, 4)
	91 #3 (1, 4)
	92 25 (1, 4)
	93 aload (1, 4)
	94 #6 (1, 4)
	95 iload_3 (1, 4)
	96 invokevirtual (1, 4)
	97 org/apache/commons/math3/dfp/Dfp.divide:(I)Lorg/apache/commons/math3/dfp/Dfp; (1, 4)
	99 astore (1, 4)
	100 #9 (1, 4)
	101 aload (1, 4)
	102 #5 (1, 4)
	103 aload (1, 4)
	104 #9 (1, 4)
	105 invokevirtual (1, 4)
	106 org/apache/commons/math3/dfp/Dfp.add:(Lorg/apache/commons/math3/dfp/Dfp;)Lorg/apache/commons/math3/dfp/Dfp; (1, 4)
	108 astore (1, 4)
	109 #5 (1, 4)
	110 aload (2, 1)
	111 #5 (2, 1)
	112 aload (2, 1)
	113 #7 (2, 1)
	114 invokevirtual (2, 1)
	115 org/apache/commons/math3/dfp/Dfp.equals:(Ljava/lang/Object;)Z (2, 1)
	117 ifeq (2, 1)
	118 6 (2, 1)
	120 goto (2, 1)
	121 20 (2, 1)
	123 new (1, 4)
	124 org/apache/commons/math3/dfp/Dfp (1, 4)
	126 dup (1, 4)
	127 aload (1, 4)
	128 #5 (1, 4)
	129 invokespecial (1, 4)
	130 org/apache/commons/math3/dfp/Dfp.<init>:(Lorg/apache/commons/math3/dfp/Dfp;)V (1, 4)
	132 astore (1, 4)
	133 #7 (1, 4)
	134 iinc (1, 4)
	135 #8 (1, 4)
	136 -89 (1, 4)
	137 goto (1, 4)
	138 -73 (1, 4)
	140 aload (0, 0)
	141 #5 (0, 0)
	142 aload_2 (0, 0)
	143 invokevirtual (0, 0)
	144 org/apache/commons/math3/dfp/Dfp.multiply:(Lorg/apache/commons/math3/dfp/Dfp;)Lorg/apache/commons/math3/dfp/Dfp; (0, 0)
	146 areturn (0, 0)

