Method: <init>
	0 aload_0 (0, 0)
	1 invokespecial (0, 0)
	4 return (0, 0)

Method: split
	0 iconst_2 (0, 0)
	1 anewarray (0, 0)
	4 astore_1 (0, 0)
	5 aload_0 (0, 1)
	6 aload_0 (0, 1)
	7 aload_0 (0, 1)
	8 invokevirtual (0, 1)
	11 iconst_2 (0, 1)
	12 idiv (0, 1)
	13 invokevirtual (0, 1)
	16 invokevirtual (0, 1)
	19 astore_2 (0, 1)
	20 aload_1 (0, 1)
	21 iconst_0 (0, 1)
	22 aload_0 (0, 1)
	23 aload_2 (0, 1)
	24 invokevirtual (0, 1)
	27 aload_2 (0, 1)
	28 invokevirtual (0, 1)
	31 aastore (0, 1)
	32 aload_1 (0, 1)
	33 iconst_1 (0, 1)
	34 aload_0 (0, 1)
	35 aload_1 (0, 1)
	36 iconst_0 (0, 1)
	37 aaload (0, 1)
	38 invokevirtual (0, 1)
	41 aastore (0, 1)
	42 aload_1 (0, 1)
	43 areturn (0, 1)

Method: splitMult
	0 iconst_2 (0, 0)
	1 anewarray (0, 0)
	4 astore_2 (0, 0)
	5 aload_2 (0, 0)
	6 iconst_1 (0, 0)
	7 aload_0 (0, 0)
	8 iconst_0 (0, 0)
	9 aaload (0, 0)
	10 invokevirtual (0, 0)
	13 aastore (0, 0)
	14 aload_2 (0, 0)
	15 iconst_0 (0, 0)
	16 aload_0 (0, 0)
	17 iconst_0 (0, 0)
	18 aaload (0, 0)
	19 aload_1 (0, 0)
	20 iconst_0 (0, 0)
	21 aaload (0, 0)
	22 invokevirtual (0, 0)
	25 aastore (0, 0)
	26 aload_2 (1, 1)
	27 iconst_0 (1, 1)
	28 aaload (1, 1)
	29 invokevirtual (1, 1)
	32 iconst_1 (1, 1)
	33 if_icmpeq (1, 1)
	36 aload_2 (1, 1)
	37 iconst_0 (1, 1)
	38 aaload (1, 1)
	39 aload_2 (1, 1)
	40 iconst_1 (1, 1)
	41 aaload (1, 1)
	42 invokevirtual (1, 1)
	45 ifeq (1, 1)
	48 aload_2 (1, 1)
	49 areturn (1, 1)
	50 aload_2 (0, 0)
	51 iconst_1 (0, 0)
	52 aload_0 (0, 0)
	53 iconst_0 (0, 0)
	54 aaload (0, 0)
	55 aload_1 (0, 0)
	56 iconst_1 (0, 0)
	57 aaload (0, 0)
	58 invokevirtual (0, 0)
	61 aload_0 (0, 0)
	62 iconst_1 (0, 0)
	63 aaload (0, 0)
	64 aload_1 (0, 0)
	65 iconst_0 (0, 0)
	66 aaload (0, 0)
	67 invokevirtual (0, 0)
	70 invokevirtual (0, 0)
	73 aload_0 (0, 0)
	74 iconst_1 (0, 0)
	75 aaload (0, 0)
	76 aload_1 (0, 0)
	77 iconst_1 (0, 0)
	78 aaload (0, 0)
	79 invokevirtual (0, 0)
	82 invokevirtual (0, 0)
	85 aastore (0, 0)
	86 aload_2 (0, 0)
	87 areturn (0, 0)

Method: splitDiv
	0 iconst_2 (0, 0)
	1 anewarray (0, 0)
	4 astore_2 (0, 0)
	5 aload_2 (0, 0)
	6 iconst_0 (0, 0)
	7 aload_0 (0, 0)
	8 iconst_0 (0, 0)
	9 aaload (0, 0)
	10 aload_1 (0, 0)
	11 iconst_0 (0, 0)
	12 aaload (0, 0)
	13 invokevirtual (0, 0)
	16 aastore (0, 0)
	17 aload_2 (0, 0)
	18 iconst_1 (0, 0)
	19 aload_0 (0, 0)
	20 iconst_1 (0, 0)
	21 aaload (0, 0)
	22 aload_1 (0, 0)
	23 iconst_0 (0, 0)
	24 aaload (0, 0)
	25 invokevirtual (0, 0)
	28 aload_0 (0, 0)
	29 iconst_0 (0, 0)
	30 aaload (0, 0)
	31 aload_1 (0, 0)
	32 iconst_1 (0, 0)
	33 aaload (0, 0)
	34 invokevirtual (0, 0)
	37 invokevirtual (0, 0)
	40 aastore (0, 0)
	41 aload_2 (0, 0)
	42 iconst_1 (0, 0)
	43 aload_2 (0, 0)
	44 iconst_1 (0, 0)
	45 aaload (0, 0)
	46 aload_1 (0, 0)
	47 iconst_0 (0, 0)
	48 aaload (0, 0)
	49 aload_1 (0, 0)
	50 iconst_0 (0, 0)
	51 aaload (0, 0)
	52 invokevirtual (0, 0)
	55 aload_1 (0, 0)
	56 iconst_0 (0, 0)
	57 aaload (0, 0)
	58 aload_1 (0, 0)
	59 iconst_1 (0, 0)
	60 aaload (0, 0)
	61 invokevirtual (0, 0)
	64 invokevirtual (0, 0)
	67 invokevirtual (0, 0)
	70 aastore (0, 0)
	71 aload_2 (0, 0)
	72 areturn (0, 0)

Method: splitPow
	0 iconst_0 (0, 0)
	1 istore_2 (0, 0)
	2 iconst_2 (0, 0)
	3 anewarray (0, 0)
	6 astore_3 (0, 0)
	7 iconst_2 (0, 0)
	8 anewarray (0, 0)
	11 astore (0, 0)
	13 aload (0, 0)
	15 iconst_0 (0, 0)
	16 aload_0 (0, 0)
	17 iconst_0 (0, 0)
	18 aaload (0, 0)
	19 invokevirtual (0, 0)
	22 aastore (0, 0)
	23 aload (0, 0)
	25 iconst_1 (0, 0)
	26 aload_0 (0, 0)
	27 iconst_0 (0, 0)
	28 aaload (0, 0)
	29 invokevirtual (0, 0)
	32 aastore (0, 0)
	33 iload_1 (1, 1)
	34 ifne (1, 1)
	37 aload (1, 1)
	39 iconst_0 (1, 1)
	40 aaload (1, 1)
	41 aload (1, 1)
	43 iconst_1 (1, 1)
	44 aaload (1, 1)
	45 invokevirtual (1, 1)
	48 areturn (1, 1)
	49 iload_1 (1, 1)
	50 ifge (1, 1)
	53 iconst_1 (1, 1)
	54 istore_2 (1, 1)
	55 iload_1 (1, 1)
	56 ineg (1, 1)
	57 istore_1 (1, 1)
	58 aload_3 (0, 0)
	59 iconst_0 (0, 0)
	60 new (0, 0)
	63 dup (0, 0)
	64 aload_0 (0, 0)
	65 iconst_0 (0, 0)
	66 aaload (0, 0)
	67 invokespecial (0, 0)
	70 aastore (0, 0)
	71 aload_3 (0, 0)
	72 iconst_1 (0, 0)
	73 new (0, 0)
	76 dup (0, 0)
	77 aload_0 (0, 0)
	78 iconst_1 (0, 0)
	79 aaload (0, 0)
	80 invokespecial (0, 0)
	83 aastore (0, 0)
	84 iconst_1 (0, 0)
	85 istore (0, 0)
	87 iload (1, 3)
	89 istore (1, 3)
	91 iload (1, 3)
	93 iconst_2 (1, 3)
	94 imul (1, 3)
	95 istore (1, 3)
	97 iload (2, 1)
	99 iload_1 (2, 1)
	100 if_icmple (2, 1)
	103 goto (2, 1)
	106 aload_3 (1, 3)
	107 aload_3 (1, 3)
	108 invokestatic (1, 3)
	111 astore_3 (1, 3)
	112 goto (1, 3)
	115 iload (0, 0)
	117 istore (0, 0)
	119 iload_1 (0, 0)
	120 iload (0, 0)
	122 isub (0, 0)
	123 istore_1 (0, 0)
	124 aload (0, 0)
	126 aload_3 (0, 0)
	127 invokestatic (0, 0)
	130 astore (0, 0)
	132 iload_1 (-1, 0)
	133 iconst_1 (-1, 0)
	134 if_icmpge (-1, 0)
	137 aload (-1, 0)
	139 iconst_0 (-1, 0)
	140 aload (-1, 0)
	142 iconst_0 (-1, 0)
	143 aaload (-1, 0)
	144 aload (-1, 0)
	146 iconst_1 (-1, 0)
	147 aaload (-1, 0)
	148 invokevirtual (-1, 0)
	151 aastore (-1, 0)
	152 iload_2 (0, 1)
	153 ifeq (0, 1)
	156 aload (0, 1)
	158 iconst_0 (0, 1)
	159 aload_0 (0, 1)
	160 iconst_0 (0, 1)
	161 aaload (0, 1)
	162 invokevirtual (0, 1)
	165 aload (0, 1)
	167 iconst_0 (0, 1)
	168 aaload (0, 1)
	169 invokevirtual (0, 1)
	172 aastore (0, 1)
	173 aload (-1, 0)
	175 iconst_0 (-1, 0)
	176 aaload (-1, 0)
	177 areturn (0, 0)

Method: pow
	0 aload_0 (1, 1)
	1 invokevirtual (1, 1)
	4 invokevirtual (1, 1)
	7 aload_1 (1, 1)
	8 invokevirtual (1, 1)
	11 invokevirtual (1, 1)
	14 if_icmpeq (1, 1)
	17 aload_0 (1, 1)
	18 invokevirtual (1, 1)
	21 iconst_1 (1, 1)
	22 invokevirtual (1, 1)
	25 aload_0 (1, 1)
	26 aload_0 (1, 1)
	27 invokevirtual (1, 1)
	30 invokevirtual (1, 1)
	33 astore_2 (1, 1)
	34 aload_2 (1, 1)
	35 iconst_3 (1, 1)
	36 putfield (1, 1)
	39 aload_0 (1, 1)
	40 iconst_1 (1, 1)
	41 ldc (1, 1)
	43 aload_0 (1, 1)
	44 aload_2 (1, 1)
	45 invokevirtual (1, 1)
	48 areturn (1, 1)
	49 aload_0 (0, 0)
	50 invokevirtual (0, 0)
	53 astore_2 (0, 0)
	54 aload_0 (0, 0)
	55 invokevirtual (0, 0)
	58 astore_3 (0, 0)
	59 aload_0 (0, 0)
	60 invokevirtual (0, 0)
	63 astore (0, 0)
	65 iconst_0 (0, 0)
	66 istore (0, 0)
	68 aload_1 (1, 1)
	69 aload_2 (1, 1)
	70 invokevirtual (1, 1)
	73 ifeq (1, 1)
	76 aload_0 (1, 1)
	77 aload_3 (1, 1)
	78 invokevirtual (1, 1)
	81 areturn (1, 1)
	82 aload_1 (1, 1)
	83 aload_3 (1, 1)
	84 invokevirtual (1, 1)
	87 ifeq (1, 1)
	90 aload_0 (2, 1)
	91 invokevirtual (2, 1)
	94 ifeq (2, 1)
	97 aload_0 (2, 4)
	98 invokevirtual (2, 4)
	101 iconst_1 (2, 4)
	102 invokevirtual (2, 4)
	105 aload_0 (2, 4)
	106 iconst_1 (2, 4)
	107 ldc (2, 4)
	109 aload_0 (2, 4)
	110 aload_0 (2, 4)
	111 invokevirtual (2, 4)
	114 areturn (2, 4)
	115 aload_0 (1, 1)
	116 areturn (1, 1)
	117 aload_0 (1, 1)
	118 invokevirtual (1, 1)
	121 ifne (1, 1)
	124 aload_1 (1, 1)
	125 invokevirtual (1, 1)
	128 ifeq (1, 1)
	131 aload_0 (1, 4)
	132 invokevirtual (1, 4)
	135 iconst_1 (1, 4)
	136 invokevirtual (1, 4)
	139 aload_0 (1, 4)
	140 iconst_1 (1, 4)
	141 ldc (1, 4)
	143 aload_0 (1, 4)
	144 aload_0 (1, 4)
	145 iconst_1 (1, 4)
	146 iconst_3 (1, 4)
	147 invokevirtual (1, 4)
	150 invokevirtual (1, 4)
	153 areturn (1, 4)
	154 aload_0 (1, 1)
	155 aload_2 (1, 1)
	156 invokevirtual (1, 1)
	159 ifeq (1, 1)
	162 aload_3 (2, 1)
	163 aload_0 (2, 1)
	164 invokestatic (2, 1)
	167 aload_2 (2, 1)
	168 invokevirtual (2, 1)
	171 ifeq (2, 1)
	174 aload_1 (3, 1)
	175 aload_2 (3, 1)
	176 invokevirtual (3, 1)
	179 ifeq (3, 1)
	182 aload_0 (3, 1)
	183 aload_2 (3, 1)
	184 invokevirtual (3, 1)
	187 areturn (3, 1)
	188 aload_0 (3, 2)
	189 aload_0 (3, 2)
	190 iconst_1 (3, 2)
	191 iconst_1 (3, 2)
	192 invokevirtual (3, 2)
	195 invokevirtual (3, 2)
	198 areturn (3, 2)
	199 aload_1 (3, 1)
	200 invokevirtual (3, 1)
	203 ifne (3, 1)
	206 aload_1 (3, 1)
	207 invokevirtual (3, 1)
	210 aload_1 (3, 1)
	211 invokevirtual (3, 1)
	214 ifeq (3, 1)
	217 aload_1 (3, 1)
	218 aload (3, 1)
	220 invokevirtual (3, 1)
	223 aload_2 (3, 1)
	224 invokevirtual (3, 1)
	227 ifne (3, 1)
	230 aload_1 (4, 1)
	231 aload_2 (4, 1)
	232 invokevirtual (4, 1)
	235 ifeq (4, 1)
	238 aload_0 (4, 1)
	239 aload_2 (4, 1)
	240 invokevirtual (4, 1)
	243 invokevirtual (4, 1)
	246 areturn (4, 1)
	247 aload_0 (4, 2)
	248 aload_0 (4, 2)
	249 iconst_m1 (4, 2)
	250 iconst_1 (4, 2)
	251 invokevirtual (4, 2)
	254 invokevirtual (4, 2)
	257 areturn (4, 2)
	258 aload_1 (4, 1)
	259 aload_2 (4, 1)
	260 invokevirtual (4, 1)
	263 ifeq (4, 1)
	266 aload_0 (4, 1)
	267 aload_2 (4, 1)
	268 invokevirtual (4, 1)
	271 areturn (4, 1)
	272 aload_0 (4, 2)
	273 aload_0 (4, 2)
	274 iconst_1 (4, 2)
	275 iconst_1 (4, 2)
	276 invokevirtual (4, 2)
	279 invokevirtual (4, 2)
	282 areturn (4, 2)
	283 aload_0 (1, 1)
	284 aload_2 (1, 1)
	285 invokevirtual (1, 1)
	288 ifeq (1, 1)
	291 aload_0 (1, 1)
	292 invokevirtual (1, 1)
	295 astore_0 (1, 1)
	296 iconst_1 (1, 1)
	297 istore (1, 1)
	299 aload_0 (1, 1)
	300 aload_3 (1, 1)
	301 invokevirtual (1, 1)
	304 ifeq (1, 1)
	307 aload_1 (1, 1)
	308 invokevirtual (1, 1)
	311 iconst_1 (1, 1)
	312 if_icmpne (1, 1)
	315 aload_1 (2, 1)
	316 aload_2 (2, 1)
	317 invokevirtual (2, 1)
	320 ifeq (2, 1)
	323 aload_1 (2, 1)
	324 areturn (2, 1)
	325 aload_0 (2, 2)
	326 aload_2 (2, 2)
	327 invokevirtual (2, 2)
	330 areturn (2, 2)
	331 aload_0 (1, 1)
	332 aload_3 (1, 1)
	333 invokevirtual (1, 1)
	336 ifeq (1, 1)
	339 aload_1 (1, 1)
	340 invokevirtual (1, 1)
	343 iconst_1 (1, 1)
	344 if_icmpne (1, 1)
	347 aload_1 (2, 1)
	348 aload_2 (2, 1)
	349 invokevirtual (2, 1)
	352 ifeq (2, 1)
	355 aload_0 (2, 1)
	356 aload_2 (2, 1)
	357 invokevirtual (2, 1)
	360 areturn (2, 1)
	361 aload_0 (2, 2)
	362 aload_1 (2, 2)
	363 aload_3 (2, 2)
	364 invokestatic (2, 2)
	367 invokevirtual (2, 2)
	370 areturn (2, 2)
	371 aload_0 (1, 1)
	372 aload_3 (1, 1)
	373 invokevirtual (1, 1)
	376 ifeq (1, 1)
	379 aload_1 (1, 1)
	380 invokevirtual (1, 1)
	383 iconst_1 (1, 1)
	384 if_icmpne (1, 1)
	387 aload_0 (1, 1)
	388 invokevirtual (1, 1)
	391 iconst_1 (1, 1)
	392 invokevirtual (1, 1)
	395 aload_0 (1, 1)
	396 iconst_1 (1, 1)
	397 ldc (1, 1)
	399 aload_0 (1, 1)
	400 aload_0 (1, 1)
	401 iconst_1 (1, 1)
	402 iconst_3 (1, 1)
	403 invokevirtual (1, 1)
	406 invokevirtual (1, 1)
	409 areturn (1, 1)
	410 aload_0 (1, 1)
	411 invokevirtual (1, 1)
	414 iconst_1 (1, 1)
	415 if_icmpne (1, 1)
	418 iload (2, 1)
	420 ifeq (2, 1)
	423 aload_1 (3, 1)
	424 invokevirtual (3, 1)
	427 ifne (3, 1)
	430 aload_1 (3, 1)
	431 invokevirtual (3, 1)
	434 aload_1 (3, 1)
	435 invokevirtual (3, 1)
	438 ifeq (3, 1)
	441 aload_1 (3, 1)
	442 aload (3, 1)
	444 invokevirtual (3, 1)
	447 aload_2 (3, 1)
	448 invokevirtual (3, 1)
	451 ifne (3, 1)
	454 aload_1 (4, 1)
	455 aload_2 (4, 1)
	456 invokevirtual (4, 1)
	459 ifeq (4, 1)
	462 aload_0 (4, 1)
	463 aload_0 (4, 1)
	464 iconst_m1 (4, 1)
	465 iconst_1 (4, 1)
	466 invokevirtual (4, 1)
	469 invokevirtual (4, 1)
	472 areturn (4, 1)
	473 aload_0 (4, 2)
	474 aload_2 (4, 2)
	475 invokevirtual (4, 2)
	478 invokevirtual (4, 2)
	481 areturn (4, 2)
	482 aload_1 (4, 1)
	483 aload_2 (4, 1)
	484 invokevirtual (4, 1)
	487 ifeq (4, 1)
	490 aload_0 (4, 1)
	491 aload_0 (4, 1)
	492 iconst_1 (4, 1)
	493 iconst_1 (4, 1)
	494 invokevirtual (4, 1)
	497 invokevirtual (4, 1)
	500 areturn (4, 1)
	501 aload_0 (4, 2)
	502 aload_2 (4, 2)
	503 invokevirtual (4, 2)
	506 areturn (4, 2)
	507 aload_1 (3, 1)
	508 aload_2 (3, 1)
	509 invokevirtual (3, 1)
	512 ifeq (3, 1)
	515 aload_0 (3, 1)
	516 areturn (3, 1)
	517 aload_0 (3, 2)
	518 aload_2 (3, 2)
	519 invokevirtual (3, 2)
	522 areturn (3, 2)
	523 iload (1, 1)
	525 ifeq (1, 1)
	528 aload_1 (1, 1)
	529 invokevirtual (1, 1)
	532 aload_1 (1, 1)
	533 invokevirtual (1, 1)
	536 ifne (1, 1)
	539 aload_0 (1, 1)
	540 invokevirtual (1, 1)
	543 iconst_1 (1, 1)
	544 invokevirtual (1, 1)
	547 aload_0 (1, 1)
	548 iconst_1 (1, 1)
	549 ldc (1, 1)
	551 aload_0 (1, 1)
	552 aload_0 (1, 1)
	553 iconst_1 (1, 1)
	554 iconst_3 (1, 1)
	555 invokevirtual (1, 1)
	558 invokevirtual (1, 1)
	561 areturn (1, 1)
	562 aload_1 (1, 1)
	563 aload_0 (1, 1)
	564 ldc (1, 1)
	566 invokevirtual (1, 1)
	569 invokevirtual (1, 1)
	572 ifeq (1, 1)
	575 aload_1 (1, 1)
	576 aload_0 (1, 1)
	577 ldc (1, 1)
	579 invokevirtual (1, 1)
	582 invokevirtual (1, 1)
	585 ifeq (1, 1)
	588 aload_1 (1, 1)
	589 invokevirtual (1, 1)
	592 astore (1, 1)
	594 aload (1, 1)
	596 invokevirtual (1, 1)
	599 istore (1, 1)
	601 aload_1 (1, 1)
	602 aload (1, 1)
	604 invokevirtual (1, 1)
	607 astore (1, 1)
	609 aload (2, 1)
	611 aload_2 (2, 1)
	612 invokevirtual (2, 1)
	615 ifeq (2, 1)
	618 aload (2, 1)
	620 aload_0 (2, 1)
	621 invokestatic (2, 1)
	624 invokevirtual (2, 1)
	627 astore (2, 1)
	629 aload (2, 1)
	631 aload_0 (2, 1)
	632 invokevirtual (2, 1)
	635 invokevirtual (2, 1)
	638 invokevirtual (2, 1)
	641 invokevirtual (2, 1)
	644 astore (2, 1)
	646 aload (2, 1)
	648 aload (2, 1)
	650 aload_0 (2, 1)
	651 invokevirtual (2, 1)
	654 invokevirtual (2, 1)
	657 invokevirtual (2, 1)
	660 invokevirtual (2, 1)
	663 astore (2, 1)
	665 aload_0 (2, 1)
	666 invokestatic (2, 1)
	669 iload (2, 1)
	671 invokestatic (2, 1)
	674 astore (2, 1)
	676 aload (2, 1)
	678 aload (2, 1)
	680 aload (2, 1)
	682 invokevirtual (2, 1)
	685 invokestatic (2, 1)
	688 invokevirtual (2, 1)
	691 astore (2, 1)
	693 aload (2, 1)
	695 aload (2, 1)
	697 invokestatic (2, 1)
	700 invokevirtual (2, 1)
	703 astore (2, 1)
	705 goto (2, 2)
	708 aload_0 (2, 2)
	709 invokestatic (2, 2)
	712 iload (2, 2)
	714 invokestatic (2, 2)
	717 astore (2, 2)
	719 goto (1, 2)
	722 aload_0 (1, 2)
	723 invokestatic (1, 2)
	726 aload_1 (1, 2)
	727 invokevirtual (1, 2)
	730 invokestatic (1, 2)
	733 astore (1, 2)
	735 iload (1, 1)
	737 ifeq (1, 1)
	740 aload_1 (1, 1)
	741 invokevirtual (1, 1)
	744 aload_1 (1, 1)
	745 invokevirtual (1, 1)
	748 ifeq (1, 1)
	751 aload_1 (1, 1)
	752 aload (1, 1)
	754 invokevirtual (1, 1)
	757 aload_2 (1, 1)
	758 invokevirtual (1, 1)
	761 ifne (1, 1)
	764 aload (1, 1)
	766 invokevirtual (1, 1)
	769 astore (1, 1)
	771 aload_0 (0, 1)
	772 aload (0, 1)
	774 invokevirtual (0, 1)
	777 areturn (0, 1)

Method: exp
	0 aload_0 (0, 0)
	1 invokevirtual (0, 0)
	4 astore_1 (0, 0)
	5 aload_0 (0, 0)
	6 aload_1 (0, 0)
	7 invokevirtual (0, 0)
	10 astore_2 (0, 0)
	11 aload_1 (0, 0)
	12 invokevirtual (0, 0)
	15 istore_3 (0, 0)
	16 iload_3 (1, 1)
	17 ldc (1, 1)
	19 if_icmple (1, 1)
	22 aload_0 (1, 1)
	23 iconst_1 (1, 1)
	24 iconst_1 (1, 1)
	25 invokevirtual (1, 1)
	28 areturn (1, 1)
	29 iload_3 (1, 1)
	30 ldc (1, 1)
	32 if_icmpge (1, 1)
	35 aload_0 (1, 1)
	36 invokevirtual (1, 1)
	39 areturn (1, 1)
	40 aload_0 (0, 0)
	41 invokevirtual (0, 0)
	44 invokevirtual (0, 0)
	47 iload_3 (0, 0)
	48 invokestatic (0, 0)
	51 astore (0, 0)
	53 aload_2 (0, 0)
	54 invokestatic (0, 0)
	57 astore (0, 0)
	59 aload (0, 0)
	61 aload (0, 0)
	63 invokevirtual (0, 0)
	66 areturn (0, 0)

Method: expInternal
	0 aload_0 (0, 0)
	1 invokevirtual (0, 0)
	4 astore_1 (0, 0)
	5 aload_0 (0, 0)
	6 invokevirtual (0, 0)
	9 astore_2 (0, 0)
	10 aload_0 (0, 0)
	11 invokevirtual (0, 0)
	14 astore_3 (0, 0)
	15 new (0, 0)
	18 dup (0, 0)
	19 aload_1 (0, 0)
	20 invokespecial (0, 0)
	23 astore (0, 0)
	25 iconst_1 (1, 4)
	26 istore (1, 4)
	28 iload (1, 4)
	30 bipush (1, 4)
	32 if_icmpge (1, 4)
	35 aload_2 (1, 4)
	36 aload_0 (1, 4)
	37 invokevirtual (1, 4)
	40 astore_2 (1, 4)
	41 aload_3 (1, 4)
	42 iload (1, 4)
	44 invokevirtual (1, 4)
	47 astore_3 (1, 4)
	48 aload_1 (1, 4)
	49 aload_2 (1, 4)
	50 aload_3 (1, 4)
	51 invokevirtual (1, 4)
	54 invokevirtual (1, 4)
	57 astore_1 (1, 4)
	58 aload_1 (2, 1)
	59 aload (2, 1)
	61 invokevirtual (2, 1)
	64 ifeq (2, 1)
	67 goto (2, 1)
	70 new (1, 4)
	73 dup (1, 4)
	74 aload_1 (1, 4)
	75 invokespecial (1, 4)
	78 astore (1, 4)
	80 iinc (1, 4)
	83 goto (1, 4)
	86 aload_1 (0, 0)
	87 areturn (0, 0)

Method: log
	0 iconst_0 (0, 0)
	1 istore (0, 0)
	3 aload_0 (1, 1)
	4 aload_0 (1, 1)
	5 invokevirtual (1, 1)
	8 invokevirtual (1, 1)
	11 ifne (1, 1)
	14 aload_0 (1, 1)
	15 aload_0 (1, 1)
	16 invokevirtual (1, 1)
	19 invokevirtual (1, 1)
	22 ifne (1, 1)
	25 aload_0 (1, 1)
	26 invokevirtual (1, 1)
	29 ifeq (1, 1)
	32 aload_0 (1, 1)
	33 invokevirtual (1, 1)
	36 iconst_1 (1, 1)
	37 invokevirtual (1, 1)
	40 aload_0 (1, 1)
	41 iconst_1 (1, 1)
	42 ldc (1, 1)
	44 aload_0 (1, 1)
	45 aload_0 (1, 1)
	46 iconst_1 (1, 1)
	47 iconst_3 (1, 1)
	48 invokevirtual (1, 1)
	51 invokevirtual (1, 1)
	54 areturn (1, 1)
	55 aload_0 (1, 1)
	56 invokevirtual (1, 1)
	59 iconst_1 (1, 1)
	60 if_icmpne (1, 1)
	63 aload_0 (1, 1)
	64 areturn (1, 1)
	65 new (0, 0)
	68 dup (0, 0)
	69 aload_0 (0, 0)
	70 invokespecial (0, 0)
	73 astore_2 (0, 0)
	74 aload_2 (0, 0)
	75 invokevirtual (0, 0)
	78 istore_1 (0, 0)
	79 aload_2 (0, 0)
	80 aload_0 (0, 0)
	81 sipush (0, 0)
	84 invokevirtual (0, 0)
	87 iload_1 (0, 0)
	88 invokestatic (0, 0)
	91 invokevirtual (0, 0)
	94 astore_2 (0, 0)
	95 aload_2 (0, 0)
	96 invokevirtual (0, 0)
	99 invokevirtual (0, 0)
	102 istore_3 (0, 0)
	103 iload_3 (1, 3)
	104 iconst_2 (1, 3)
	105 if_icmple (1, 3)
	108 iload_3 (1, 3)
	109 iconst_1 (1, 3)
	110 ishr (1, 3)
	111 istore_3 (1, 3)
	112 iinc (1, 3)
	115 goto (1, 3)
	118 aload_2 (0, 0)
	119 invokestatic (0, 0)
	122 astore (0, 0)
	124 iconst_2 (0, 0)
	125 anewarray (0, 0)
	128 astore (0, 0)
	130 aload (0, 0)
	132 iconst_0 (0, 0)
	133 aload_0 (0, 0)
	134 invokevirtual (0, 0)
	137 iload (0, 0)
	139 invokestatic (0, 0)
	142 aastore (0, 0)
	143 aload (0, 0)
	145 iconst_0 (0, 0)
	146 aload (0, 0)
	148 iconst_0 (0, 0)
	149 aaload (0, 0)
	150 aload (0, 0)
	152 iconst_0 (0, 0)
	153 aaload (0, 0)
	154 invokevirtual (0, 0)
	157 aastore (0, 0)
	158 aload (0, 0)
	160 iconst_1 (0, 0)
	161 aload (0, 0)
	163 iconst_1 (0, 0)
	164 aaload (0, 0)
	165 aload (0, 0)
	167 iconst_0 (0, 0)
	168 aaload (0, 0)
	169 invokevirtual (0, 0)
	172 aastore (0, 0)
	173 aload (0, 4)
	175 iconst_0 (0, 4)
	176 aload_0 (0, 4)
	177 ldc (0, 4)
	179 invokevirtual (0, 4)
	182 aastore (0, 4)
	183 aload (1, 3)
	185 iconst_0 (1, 3)
	186 aaload (1, 3)
	187 aload (1, 3)
	189 iconst_1 (1, 3)
	190 aaload (1, 3)
	191 invokevirtual (1, 3)
	194 aload (1, 3)
	196 iconst_0 (1, 3)
	197 aaload (1, 3)
	198 invokevirtual (1, 3)
	201 ifeq (1, 3)
	204 aload (1, 3)
	206 iconst_0 (1, 3)
	207 aload (1, 3)
	209 iconst_0 (1, 3)
	210 aaload (1, 3)
	211 iconst_2 (1, 3)
	212 invokevirtual (1, 3)
	215 aastore (1, 3)
	216 aload (1, 3)
	218 iconst_1 (1, 3)
	219 aload (1, 3)
	221 iconst_1 (1, 3)
	222 aaload (1, 3)
	223 iconst_2 (1, 3)
	224 invokevirtual (1, 3)
	227 aastore (1, 3)
	228 iinc (1, 3)
	231 goto (1, 3)
	234 aload (0, 4)
	236 invokestatic (0, 4)
	239 astore (0, 4)
	241 aload (0, 4)
	243 iconst_0 (0, 4)
	244 aload_0 (0, 4)
	245 new (0, 4)
	248 dup (0, 4)
	249 invokespecial (0, 4)
	252 iload (0, 4)
	254 iconst_4 (0, 4)
	255 iload_1 (0, 4)
	256 imul (0, 4)
	257 iadd (0, 4)
	258 invokevirtual (0, 4)
	261 invokevirtual (0, 4)
	264 invokevirtual (0, 4)
	267 aastore (0, 4)
	268 aload (0, 4)
	270 iconst_1 (0, 4)
	271 aload_0 (0, 4)
	272 invokevirtual (0, 4)
	275 aastore (0, 4)
	276 aload_0 (0, 4)
	277 invokevirtual (0, 4)
	280 invokevirtual (0, 4)
	283 aload (0, 4)
	285 invokestatic (0, 4)
	288 astore (0, 4)
	290 aload (0, 4)
	292 iconst_0 (0, 4)
	293 aload (0, 4)
	295 iconst_0 (0, 4)
	296 aaload (0, 4)
	297 aload (0, 4)
	299 iconst_0 (0, 4)
	300 aaload (0, 4)
	301 invokevirtual (0, 4)
	304 aastore (0, 4)
	305 aload (0, 4)
	307 iconst_1 (0, 4)
	308 aload (0, 4)
	310 iconst_1 (0, 4)
	311 aaload (0, 4)
	312 aload (0, 4)
	314 iconst_1 (0, 4)
	315 aaload (0, 4)
	316 invokevirtual (0, 4)
	319 aastore (0, 4)
	320 aload (0, 4)
	322 iconst_0 (0, 4)
	323 aload_0 (0, 4)
	324 new (0, 4)
	327 dup (0, 4)
	328 invokespecial (0, 4)
	331 iconst_4 (0, 4)
	332 iload_1 (0, 4)
	333 imul (0, 4)
	334 invokevirtual (0, 4)
	337 invokevirtual (0, 4)
	340 invokevirtual (0, 4)
	343 aastore (0, 4)
	344 aload (0, 4)
	346 iconst_1 (0, 4)
	347 aload_0 (0, 4)
	348 invokevirtual (0, 4)
	351 aastore (0, 4)
	352 aload_0 (0, 4)
	353 invokevirtual (0, 4)
	356 invokevirtual (0, 4)
	359 aload (0, 4)
	361 invokestatic (0, 4)
	364 astore (0, 4)
	366 aload (0, 4)
	368 iconst_0 (0, 4)
	369 aload (0, 4)
	371 iconst_0 (0, 4)
	372 aaload (0, 4)
	373 aload (0, 4)
	375 iconst_0 (0, 4)
	376 aaload (0, 4)
	377 invokevirtual (0, 4)
	380 aastore (0, 4)
	381 aload (0, 4)
	383 iconst_1 (0, 4)
	384 aload (0, 4)
	386 iconst_1 (0, 4)
	387 aaload (0, 4)
	388 aload (0, 4)
	390 iconst_1 (0, 4)
	391 aaload (0, 4)
	392 invokevirtual (0, 4)
	395 aastore (0, 4)
	396 aload_0 (0, 4)
	397 aload (0, 4)
	399 iconst_0 (0, 4)
	400 aaload (0, 4)
	401 aload (0, 4)
	403 iconst_1 (0, 4)
	404 aaload (0, 4)
	405 invokevirtual (0, 4)
	408 invokevirtual (0, 4)
	411 areturn (0, 4)

Method: logInternal
	0 aload_0 (0, 0)
	1 iconst_0 (0, 0)
	2 aaload (0, 0)
	3 iconst_4 (0, 0)
	4 invokevirtual (0, 0)
	7 aload_0 (0, 0)
	8 iconst_1 (0, 0)
	9 aaload (0, 0)
	10 iconst_4 (0, 0)
	11 invokevirtual (0, 0)
	14 invokevirtual (0, 0)
	17 astore_1 (0, 0)
	18 aload_1 (0, 0)
	19 aload_0 (0, 0)
	20 iconst_0 (0, 0)
	21 aaload (0, 0)
	22 ldc (0, 0)
	24 invokevirtual (0, 0)
	27 invokevirtual (0, 0)
	30 aload_1 (0, 0)
	31 aload_0 (0, 0)
	32 iconst_0 (0, 0)
	33 aaload (0, 0)
	34 ldc (0, 0)
	36 invokevirtual (0, 0)
	39 invokevirtual (0, 0)
	42 invokevirtual (0, 0)
	45 astore_2 (0, 0)
	46 new (0, 0)
	49 dup (0, 0)
	50 aload_2 (0, 0)
	51 invokespecial (0, 0)
	54 astore_3 (0, 0)
	55 new (0, 0)
	58 dup (0, 0)
	59 aload_2 (0, 0)
	60 invokespecial (0, 0)
	63 astore (0, 0)
	65 new (0, 0)
	68 dup (0, 0)
	69 aload_3 (0, 0)
	70 invokespecial (0, 0)
	73 astore (0, 0)
	75 iconst_1 (0, 0)
	76 istore (0, 0)
	78 iconst_0 (1, 4)
	79 istore (1, 4)
	81 iload (1, 4)
	83 sipush (1, 4)
	86 if_icmpge (1, 4)
	89 aload (1, 4)
	91 aload_2 (1, 4)
	92 invokevirtual (1, 4)
	95 astore (1, 4)
	97 aload (1, 4)
	99 aload_2 (1, 4)
	100 invokevirtual (1, 4)
	103 astore (1, 4)
	105 iinc (1, 4)
	108 aload (1, 4)
	110 iload (1, 4)
	112 invokevirtual (1, 4)
	115 astore_1 (1, 4)
	116 aload_3 (1, 4)
	117 aload_1 (1, 4)
	118 invokevirtual (1, 4)
	121 astore_3 (1, 4)
	122 aload_3 (2, 1)
	123 aload (2, 1)
	125 invokevirtual (2, 1)
	128 ifeq (2, 1)
	131 goto (2, 1)
	134 new (1, 4)
	137 dup (1, 4)
	138 aload_3 (1, 4)
	139 invokespecial (1, 4)
	142 astore (1, 4)
	144 iinc (1, 4)
	147 goto (1, 4)
	150 aload_3 (0, 0)
	151 aload_0 (0, 0)
	152 iconst_0 (0, 0)
	153 aaload (0, 0)
	154 invokevirtual (0, 0)
	157 invokevirtual (0, 0)
	160 astore_3 (0, 0)
	161 aload_3 (0, 0)
	162 invokestatic (0, 0)
	165 areturn (0, 0)

Method: sinInternal
	0 aload_0 (0, 0)
	1 iconst_0 (0, 0)
	2 aaload (0, 0)
	3 aload_0 (0, 0)
	4 iconst_1 (0, 0)
	5 aaload (0, 0)
	6 invokevirtual (0, 0)
	9 astore_1 (0, 0)
	10 aload_1 (0, 0)
	11 astore_2 (0, 0)
	12 aload_1 (0, 0)
	13 aload_1 (0, 0)
	14 invokevirtual (0, 0)
	17 astore_1 (0, 0)
	18 aload_2 (0, 0)
	19 astore_3 (0, 0)
	20 aload_0 (0, 0)
	21 iconst_0 (0, 0)
	22 aaload (0, 0)
	23 invokevirtual (0, 0)
	26 astore (0, 0)
	28 new (0, 0)
	31 dup (0, 0)
	32 aload_2 (0, 0)
	33 invokespecial (0, 0)
	36 astore (0, 0)
	38 iconst_3 (1, 4)
	39 istore (1, 4)
	41 iload (1, 4)
	43 bipush (1, 4)
	45 if_icmpge (1, 4)
	48 aload_3 (1, 4)
	49 aload_1 (1, 4)
	50 invokevirtual (1, 4)
	53 astore_3 (1, 4)
	54 aload_3 (1, 4)
	55 invokevirtual (1, 4)
	58 astore_3 (1, 4)
	59 aload (1, 4)
	61 iload (1, 4)
	63 iconst_1 (1, 4)
	64 isub (1, 4)
	65 iload (1, 4)
	67 imul (1, 4)
	68 invokevirtual (1, 4)
	71 astore (1, 4)
	73 aload_2 (1, 4)
	74 aload_3 (1, 4)
	75 aload (1, 4)
	77 invokevirtual (1, 4)
	80 invokevirtual (1, 4)
	83 astore_2 (1, 4)
	84 aload_2 (2, 1)
	85 aload (2, 1)
	87 invokevirtual (2, 1)
	90 ifeq (2, 1)
	93 goto (2, 1)
	96 new (1, 4)
	99 dup (1, 4)
	100 aload_2 (1, 4)
	101 invokespecial (1, 4)
	104 astore (1, 4)
	106 iinc (1, 4)
	109 goto (1, 4)
	112 aload_2 (0, 0)
	113 areturn (0, 0)

Method: cosInternal
	0 aload_0 (0, 0)
	1 iconst_0 (0, 0)
	2 aaload (0, 0)
	3 invokevirtual (0, 0)
	6 astore_1 (0, 0)
	7 aload_1 (0, 0)
	8 astore_2 (0, 0)
	9 aload_1 (0, 0)
	10 astore_3 (0, 0)
	11 aload_0 (0, 0)
	12 iconst_0 (0, 0)
	13 aaload (0, 0)
	14 aload_0 (0, 0)
	15 iconst_1 (0, 0)
	16 aaload (0, 0)
	17 invokevirtual (0, 0)
	20 astore (0, 0)
	22 aload (0, 0)
	24 aload (0, 0)
	26 invokevirtual (0, 0)
	29 astore (0, 0)
	31 aload_1 (0, 0)
	32 astore (0, 0)
	34 new (0, 0)
	37 dup (0, 0)
	38 aload_3 (0, 0)
	39 invokespecial (0, 0)
	42 astore (0, 0)
	44 iconst_2 (1, 4)
	45 istore (1, 4)
	47 iload (1, 4)
	49 bipush (1, 4)
	51 if_icmpge (1, 4)
	54 aload_2 (1, 4)
	55 aload (1, 4)
	57 invokevirtual (1, 4)
	60 astore_2 (1, 4)
	61 aload_2 (1, 4)
	62 invokevirtual (1, 4)
	65 astore_2 (1, 4)
	66 aload (1, 4)
	68 iload (1, 4)
	70 iconst_1 (1, 4)
	71 isub (1, 4)
	72 iload (1, 4)
	74 imul (1, 4)
	75 invokevirtual (1, 4)
	78 astore (1, 4)
	80 aload_3 (1, 4)
	81 aload_2 (1, 4)
	82 aload (1, 4)
	84 invokevirtual (1, 4)
	87 invokevirtual (1, 4)
	90 astore_3 (1, 4)
	91 aload_3 (2, 1)
	92 aload (2, 1)
	94 invokevirtual (2, 1)
	97 ifeq (2, 1)
	100 goto (2, 1)
	103 new (1, 4)
	106 dup (1, 4)
	107 aload_3 (1, 4)
	108 invokespecial (1, 4)
	111 astore (1, 4)
	113 iinc (1, 4)
	116 goto (1, 4)
	119 aload_3 (0, 0)
	120 areturn (0, 0)

Method: sin
	0 aload_0 (0, 0)
	1 invokevirtual (0, 0)
	4 invokevirtual (0, 0)
	7 astore_1 (0, 0)
	8 aload_0 (0, 0)
	9 invokevirtual (0, 0)
	12 invokevirtual (0, 0)
	15 astore_2 (0, 0)
	16 iconst_0 (0, 0)
	17 istore_3 (0, 0)
	18 aload_0 (0, 0)
	19 aload_1 (0, 0)
	20 iconst_2 (0, 0)
	21 invokevirtual (0, 0)
	24 invokevirtual (0, 0)
	27 astore (0, 0)
	29 aload (1, 1)
	31 aload_2 (1, 1)
	32 invokevirtual (1, 1)
	35 ifeq (1, 1)
	38 aload (1, 1)
	40 invokevirtual (1, 1)
	43 astore (1, 1)
	45 iconst_1 (1, 1)
	46 istore_3 (1, 1)
	47 aload (1, 1)
	49 aload_1 (1, 1)
	50 iconst_2 (1, 1)
	51 invokevirtual (1, 1)
	54 invokevirtual (1, 1)
	57 ifeq (1, 1)
	60 aload_1 (1, 1)
	61 aload (1, 1)
	63 invokevirtual (1, 1)
	66 astore (1, 1)
	68 aload (1, 1)
	70 aload_1 (1, 1)
	71 iconst_4 (1, 1)
	72 invokevirtual (1, 1)
	75 invokevirtual (1, 1)
	78 ifeq (1, 1)
	81 aload (1, 1)
	83 invokestatic (1, 1)
	86 invokestatic (1, 1)
	89 astore (1, 1)
	91 goto (1, 1)
	94 iconst_2 (1, 2)
	95 anewarray (1, 2)
	98 astore (1, 2)
	100 aload_0 (1, 2)
	101 invokevirtual (1, 2)
	104 invokevirtual (1, 2)
	107 astore (1, 2)
	109 aload (1, 2)
	111 iconst_0 (1, 2)
	112 aload (1, 2)
	114 iconst_0 (1, 2)
	115 aaload (1, 2)
	116 iconst_2 (1, 2)
	117 invokevirtual (1, 2)
	120 aload (1, 2)
	122 invokevirtual (1, 2)
	125 aastore (1, 2)
	126 aload (1, 2)
	128 iconst_1 (1, 2)
	129 aload (1, 2)
	131 iconst_1 (1, 2)
	132 aaload (1, 2)
	133 iconst_2 (1, 2)
	134 invokevirtual (1, 2)
	137 aastore (1, 2)
	138 aload (1, 2)
	140 invokestatic (1, 2)
	143 astore (1, 2)
	145 iload_3 (1, 1)
	146 ifeq (1, 1)
	149 aload (1, 1)
	151 invokevirtual (1, 1)
	154 astore (1, 1)
	156 aload_0 (0, 1)
	157 aload (0, 1)
	159 invokevirtual (0, 1)
	162 areturn (0, 1)

Method: cos
	0 aload_0 (0, 0)
	1 invokevirtual (0, 0)
	4 invokevirtual (0, 0)
	7 astore_1 (0, 0)
	8 aload_0 (0, 0)
	9 invokevirtual (0, 0)
	12 invokevirtual (0, 0)
	15 astore_2 (0, 0)
	16 iconst_0 (0, 0)
	17 istore_3 (0, 0)
	18 aload_0 (0, 0)
	19 aload_1 (0, 0)
	20 iconst_2 (0, 0)
	21 invokevirtual (0, 0)
	24 invokevirtual (0, 0)
	27 astore (0, 0)
	29 aload (1, 1)
	31 aload_2 (1, 1)
	32 invokevirtual (1, 1)
	35 ifeq (1, 1)
	38 aload (1, 1)
	40 invokevirtual (1, 1)
	43 astore (1, 1)
	45 aload (1, 1)
	47 aload_1 (1, 1)
	48 iconst_2 (1, 1)
	49 invokevirtual (1, 1)
	52 invokevirtual (1, 1)
	55 ifeq (1, 1)
	58 aload_1 (1, 1)
	59 aload (1, 1)
	61 invokevirtual (1, 1)
	64 astore (1, 1)
	66 iconst_1 (1, 1)
	67 istore_3 (1, 1)
	68 aload (1, 1)
	70 aload_1 (1, 1)
	71 iconst_4 (1, 1)
	72 invokevirtual (1, 1)
	75 invokevirtual (1, 1)
	78 ifeq (1, 1)
	81 iconst_2 (1, 1)
	82 anewarray (1, 1)
	85 astore (1, 1)
	87 aload (1, 1)
	89 iconst_0 (1, 1)
	90 aload (1, 1)
	92 aastore (1, 1)
	93 aload (1, 1)
	95 iconst_1 (1, 1)
	96 aload_2 (1, 1)
	97 aastore (1, 1)
	98 aload (1, 1)
	100 invokestatic (1, 1)
	103 astore (1, 1)
	105 goto (1, 2)
	108 iconst_2 (1, 2)
	109 anewarray (1, 2)
	112 astore (1, 2)
	114 aload_0 (1, 2)
	115 invokevirtual (1, 2)
	118 invokevirtual (1, 2)
	121 astore (1, 2)
	123 aload (1, 2)
	125 iconst_0 (1, 2)
	126 aload (1, 2)
	128 iconst_0 (1, 2)
	129 aaload (1, 2)
	130 iconst_2 (1, 2)
	131 invokevirtual (1, 2)
	134 aload (1, 2)
	136 invokevirtual (1, 2)
	139 aastore (1, 2)
	140 aload (1, 2)
	142 iconst_1 (1, 2)
	143 aload (1, 2)
	145 iconst_1 (1, 2)
	146 aaload (1, 2)
	147 iconst_2 (1, 2)
	148 invokevirtual (1, 2)
	151 aastore (1, 2)
	152 aload (1, 2)
	154 invokestatic (1, 2)
	157 astore (1, 2)
	159 iload_3 (1, 1)
	160 ifeq (1, 1)
	163 aload (1, 1)
	165 invokevirtual (1, 1)
	168 astore (1, 1)
	170 aload_0 (0, 1)
	171 aload (0, 1)
	173 invokevirtual (0, 1)
	176 areturn (0, 1)

Method: tan
	0 aload_0 (0, 0)
	1 invokestatic (0, 0)
	4 aload_0 (0, 0)
	5 invokestatic (0, 0)
	8 invokevirtual (0, 0)
	11 areturn (0, 0)

Method: atanInternal
	0 new (0, 0)
	3 dup (0, 0)
	4 aload_0 (0, 0)
	5 invokespecial (0, 0)
	8 astore_1 (0, 0)
	9 new (0, 0)
	12 dup (0, 0)
	13 aload_1 (0, 0)
	14 invokespecial (0, 0)
	17 astore_2 (0, 0)
	18 new (0, 0)
	21 dup (0, 0)
	22 aload_1 (0, 0)
	23 invokespecial (0, 0)
	26 astore_3 (0, 0)
	27 iconst_3 (1, 4)
	28 istore (1, 4)
	30 iload (1, 4)
	32 bipush (1, 4)
	34 if_icmpge (1, 4)
	37 aload_2 (1, 4)
	38 aload_0 (1, 4)
	39 invokevirtual (1, 4)
	42 astore_2 (1, 4)
	43 aload_2 (1, 4)
	44 aload_0 (1, 4)
	45 invokevirtual (1, 4)
	48 astore_2 (1, 4)
	49 aload_2 (1, 4)
	50 invokevirtual (1, 4)
	53 astore_2 (1, 4)
	54 aload_1 (1, 4)
	55 aload_2 (1, 4)
	56 iload (1, 4)
	58 invokevirtual (1, 4)
	61 invokevirtual (1, 4)
	64 astore_1 (1, 4)
	65 aload_1 (2, 1)
	66 aload_3 (2, 1)
	67 invokevirtual (2, 1)
	70 ifeq (2, 1)
	73 goto (2, 1)
	76 new (1, 4)
	79 dup (1, 4)
	80 aload_1 (1, 4)
	81 invokespecial (1, 4)
	84 astore_3 (1, 4)
	85 iinc (1, 4)
	88 goto (1, 4)
	91 aload_1 (0, 0)
	92 areturn (0, 0)

Method: atan
	0 aload_0 (0, 0)
	1 invokevirtual (0, 0)
	4 invokevirtual (0, 0)
	7 astore_1 (0, 0)
	8 aload_0 (0, 0)
	9 invokevirtual (0, 0)
	12 invokevirtual (0, 0)
	15 astore_2 (0, 0)
	16 aload_0 (0, 0)
	17 invokevirtual (0, 0)
	20 invokevirtual (0, 0)
	23 astore_3 (0, 0)
	24 aload_0 (0, 0)
	25 invokevirtual (0, 0)
	28 invokevirtual (0, 0)
	31 astore (0, 0)
	33 iconst_0 (0, 0)
	34 istore (0, 0)
	36 iconst_0 (0, 0)
	37 istore (0, 0)
	39 iconst_0 (0, 0)
	40 istore (0, 0)
	42 aload_3 (0, 0)
	43 iconst_0 (0, 0)
	44 aaload (0, 0)
	45 aload_2 (0, 0)
	46 invokevirtual (0, 0)
	49 aload_3 (0, 0)
	50 iconst_1 (0, 0)
	51 aaload (0, 0)
	52 invokevirtual (0, 0)
	55 astore (0, 0)
	57 new (0, 0)
	60 dup (0, 0)
	61 aload_0 (0, 0)
	62 invokespecial (0, 0)
	65 astore (0, 0)
	67 aload (1, 1)
	69 aload_1 (1, 1)
	70 invokevirtual (1, 1)
	73 ifeq (1, 1)
	76 iconst_1 (1, 1)
	77 istore (1, 1)
	79 aload (1, 1)
	81 invokevirtual (1, 1)
	84 astore (1, 1)
	86 aload (1, 1)
	88 aload_2 (1, 1)
	89 invokevirtual (1, 1)
	92 ifeq (1, 1)
	95 iconst_1 (1, 1)
	96 istore (1, 1)
	98 aload_2 (1, 1)
	99 aload (1, 1)
	101 invokevirtual (1, 1)
	104 astore (1, 1)
	106 aload (1, 1)
	108 aload (1, 1)
	110 invokevirtual (1, 1)
	113 ifeq (1, 1)
	116 iconst_2 (1, 1)
	117 anewarray (1, 1)
	120 astore (1, 1)
	122 iconst_1 (1, 1)
	123 istore (1, 1)
	125 aload (1, 1)
	127 iconst_0 (1, 1)
	128 aload_3 (1, 1)
	129 iconst_0 (1, 1)
	130 aaload (1, 1)
	131 aload_2 (1, 1)
	132 invokevirtual (1, 1)
	135 aastore (1, 1)
	136 aload (1, 1)
	138 iconst_1 (1, 1)
	139 aload_3 (1, 1)
	140 iconst_1 (1, 1)
	141 aaload (1, 1)
	142 aastore (1, 1)
	143 aload (1, 1)
	145 invokestatic (1, 1)
	148 astore (1, 1)
	150 aload (1, 1)
	152 aload (1, 1)
	154 invokestatic (1, 1)
	157 astore (1, 1)
	159 aload (1, 1)
	161 iconst_0 (1, 1)
	162 aload (1, 1)
	164 iconst_0 (1, 1)
	165 aaload (1, 1)
	166 aload_2 (1, 1)
	167 invokevirtual (1, 1)
	170 aastore (1, 1)
	171 aload (1, 1)
	173 iconst_0 (1, 1)
	174 aload (1, 1)
	176 iconst_0 (1, 1)
	177 aaload (1, 1)
	178 aload (1, 1)
	180 iconst_0 (1, 1)
	181 aaload (1, 1)
	182 invokevirtual (1, 1)
	185 aastore (1, 1)
	186 aload (1, 1)
	188 iconst_1 (1, 1)
	189 aload (1, 1)
	191 iconst_1 (1, 1)
	192 aaload (1, 1)
	193 aload (1, 1)
	195 iconst_1 (1, 1)
	196 aaload (1, 1)
	197 invokevirtual (1, 1)
	200 aastore (1, 1)
	201 aload (1, 1)
	203 aload (1, 1)
	205 invokestatic (1, 1)
	208 astore (1, 1)
	210 aload (1, 1)
	212 iconst_0 (1, 1)
	213 aaload (1, 1)
	214 aload (1, 1)
	216 iconst_1 (1, 1)
	217 aaload (1, 1)
	218 invokevirtual (1, 1)
	221 astore (1, 1)
	223 aload (0, 0)
	225 invokestatic (0, 0)
	228 astore (0, 0)
	230 iload (1, 1)
	232 ifeq (1, 1)
	235 aload (1, 1)
	237 aload (1, 1)
	239 iconst_0 (1, 1)
	240 aaload (1, 1)
	241 bipush (1, 1)
	243 invokevirtual (1, 1)
	246 invokevirtual (1, 1)
	249 aload (1, 1)
	251 iconst_1 (1, 1)
	252 aaload (1, 1)
	253 bipush (1, 1)
	255 invokevirtual (1, 1)
	258 invokevirtual (1, 1)
	261 astore (1, 1)
	263 iload (1, 1)
	265 ifeq (1, 1)
	268 aload (1, 1)
	270 iconst_0 (1, 1)
	271 aaload (1, 1)
	272 iconst_2 (1, 1)
	273 invokevirtual (1, 1)
	276 aload (1, 1)
	278 invokevirtual (1, 1)
	281 aload (1, 1)
	283 iconst_1 (1, 1)
	284 aaload (1, 1)
	285 iconst_2 (1, 1)
	286 invokevirtual (1, 1)
	289 invokevirtual (1, 1)
	292 astore (1, 1)
	294 iload (1, 1)
	296 ifeq (1, 1)
	299 aload (1, 1)
	301 invokevirtual (1, 1)
	304 astore (1, 1)
	306 aload_0 (0, 0)
	307 aload (0, 0)
	309 invokevirtual (0, 0)
	312 areturn (0, 0)

Method: asin
	0 aload_0 (0, 0)
	1 aload_0 (0, 0)
	2 invokevirtual (0, 0)
	5 aload_0 (0, 0)
	6 aload_0 (0, 0)
	7 invokevirtual (0, 0)
	10 invokevirtual (0, 0)
	13 invokevirtual (0, 0)
	16 invokevirtual (0, 0)
	19 invokestatic (0, 0)
	22 areturn (0, 0)

Method: acos
	0 iconst_0 (0, 0)
	1 istore_2 (0, 0)
	2 aload_0 (1, 1)
	3 aload_0 (1, 1)
	4 invokevirtual (1, 1)
	7 invokevirtual (1, 1)
	10 ifeq (1, 1)
	13 iconst_1 (1, 1)
	14 istore_2 (1, 1)
	15 aload_0 (0, 0)
	16 aload_0 (0, 0)
	17 invokevirtual (0, 0)
	20 invokestatic (0, 0)
	23 astore_0 (0, 0)
	24 aload_0 (0, 0)
	25 invokevirtual (0, 0)
	28 aload_0 (0, 0)
	29 aload_0 (0, 0)
	30 invokevirtual (0, 0)
	33 invokevirtual (0, 0)
	36 invokevirtual (0, 0)
	39 aload_0 (0, 0)
	40 invokevirtual (0, 0)
	43 invokestatic (0, 0)
	46 astore_1 (0, 0)
	47 iload_2 (1, 1)
	48 ifeq (1, 1)
	51 aload_0 (1, 1)
	52 invokevirtual (1, 1)
	55 invokevirtual (1, 1)
	58 aload_1 (1, 1)
	59 invokevirtual (1, 1)
	62 astore_1 (1, 1)
	63 aload_0 (0, 0)
	64 aload_1 (0, 0)
	65 invokevirtual (0, 0)
	68 areturn (0, 0)

