Method: <init>
	0 aload_0 (0, 0)
	1 invokespecial (0, 0)
	2 java/lang/Object.<init>:()V (0, 0)
	4 return (0, 0)

Method: split
	0 iconst_2 (0, 0)
	1 anewarray (0, 0)
	2 org/apache/commons/math3/dfp/Dfp (0, 0)
	4 astore_1 (0, 0)
	5 aload_0 (1, 1)
	6 aload_0 (1, 1)
	7 aload_0 (1, 1)
	8 invokevirtual (1, 1)
	9 org/apache/commons/math3/dfp/Dfp.getRadixDigits:()I (1, 1)
	11 iconst_2 (1, 1)
	12 idiv (1, 1)
	13 invokevirtual (1, 1)
	14 org/apache/commons/math3/dfp/Dfp.power10K:(I)Lorg/apache/commons/math3/dfp/Dfp; (1, 1)
	16 invokevirtual (1, 1)
	17 org/apache/commons/math3/dfp/Dfp.multiply:(Lorg/apache/commons/math3/dfp/Dfp;)Lorg/apache/commons/math3/dfp/Dfp; (1, 1)
	19 astore_2 (1, 1)
	20 aload_1 (2, 1)
	21 iconst_0 (2, 1)
	22 aload_0 (2, 1)
	23 aload_2 (2, 1)
	24 invokevirtual (2, 1)
	25 org/apache/commons/math3/dfp/Dfp.add:(Lorg/apache/commons/math3/dfp/Dfp;)Lorg/apache/commons/math3/dfp/Dfp; (2, 1)
	27 aload_2 (2, 1)
	28 invokevirtual (2, 1)
	29 org/apache/commons/math3/dfp/Dfp.subtract:(Lorg/apache/commons/math3/dfp/Dfp;)Lorg/apache/commons/math3/dfp/Dfp; (2, 1)
	31 aastore (2, 1)
	32 aload_1 (2, 1)
	33 iconst_1 (2, 1)
	34 aload_0 (2, 1)
	35 aload_1 (2, 1)
	36 iconst_0 (2, 1)
	37 aaload (2, 1)
	38 invokevirtual (2, 1)
	39 org/apache/commons/math3/dfp/Dfp.subtract:(Lorg/apache/commons/math3/dfp/Dfp;)Lorg/apache/commons/math3/dfp/Dfp; (2, 1)
	41 aastore (2, 1)
	42 aload_1 (2, 1)
	43 areturn (0, 1)

Method: splitMult
	0 iconst_2 (0, 0)
	1 anewarray (0, 0)
	2 org/apache/commons/math3/dfp/Dfp (0, 0)
	4 astore_2 (0, 0)
	5 aload_2 (0, 0)
	6 iconst_1 (0, 0)
	7 aload_0 (0, 0)
	8 iconst_0 (0, 0)
	9 aaload (0, 0)
	10 invokevirtual (0, 0)
	11 org/apache/commons/math3/dfp/Dfp.getZero:()Lorg/apache/commons/math3/dfp/Dfp; (0, 0)
	13 aastore (0, 0)
	14 aload_2 (0, 0)
	15 iconst_0 (0, 0)
	16 aload_0 (0, 0)
	17 iconst_0 (0, 0)
	18 aaload (0, 0)
	19 aload_1 (0, 0)
	20 iconst_0 (0, 0)
	21 aaload (0, 0)
	22 invokevirtual (0, 0)
	23 org/apache/commons/math3/dfp/Dfp.multiply:(Lorg/apache/commons/math3/dfp/Dfp;)Lorg/apache/commons/math3/dfp/Dfp; (0, 0)
	25 aastore (0, 0)
	26 aload_2 (1, 1)
	27 iconst_0 (1, 1)
	28 aaload (1, 1)
	29 invokevirtual (1, 1)
	30 org/apache/commons/math3/dfp/Dfp.classify:()I (1, 1)
	32 iconst_1 (1, 1)
	33 if_icmpeq (1, 1)
	34 15 (1, 1)
	36 aload_2 (1, 1)
	37 iconst_0 (1, 1)
	38 aaload (1, 1)
	39 aload_2 (1, 1)
	40 iconst_1 (1, 1)
	41 aaload (1, 1)
	42 invokevirtual (1, 1)
	43 org/apache/commons/math3/dfp/Dfp.equals:(Ljava/lang/Object;)Z (1, 1)
	45 ifeq (1, 1)
	46 5 (1, 1)
	48 aload_2 (1, 1)
	49 areturn (1, 1)
	50 aload_2 (0, 0)
	51 iconst_1 (0, 0)
	52 aload_0 (0, 0)
	53 iconst_0 (0, 0)
	54 aaload (0, 0)
	55 aload_1 (0, 0)
	56 iconst_1 (0, 0)
	57 aaload (0, 0)
	58 invokevirtual (0, 0)
	59 org/apache/commons/math3/dfp/Dfp.multiply:(Lorg/apache/commons/math3/dfp/Dfp;)Lorg/apache/commons/math3/dfp/Dfp; (0, 0)
	61 aload_0 (0, 0)
	62 iconst_1 (0, 0)
	63 aaload (0, 0)
	64 aload_1 (0, 0)
	65 iconst_0 (0, 0)
	66 aaload (0, 0)
	67 invokevirtual (0, 0)
	68 org/apache/commons/math3/dfp/Dfp.multiply:(Lorg/apache/commons/math3/dfp/Dfp;)Lorg/apache/commons/math3/dfp/Dfp; (0, 0)
	70 invokevirtual (0, 0)
	71 org/apache/commons/math3/dfp/Dfp.add:(Lorg/apache/commons/math3/dfp/Dfp;)Lorg/apache/commons/math3/dfp/Dfp; (0, 0)
	73 aload_0 (0, 0)
	74 iconst_1 (0, 0)
	75 aaload (0, 0)
	76 aload_1 (0, 0)
	77 iconst_1 (0, 0)
	78 aaload (0, 0)
	79 invokevirtual (0, 0)
	80 org/apache/commons/math3/dfp/Dfp.multiply:(Lorg/apache/commons/math3/dfp/Dfp;)Lorg/apache/commons/math3/dfp/Dfp; (0, 0)
	82 invokevirtual (0, 0)
	83 org/apache/commons/math3/dfp/Dfp.add:(Lorg/apache/commons/math3/dfp/Dfp;)Lorg/apache/commons/math3/dfp/Dfp; (0, 0)
	85 aastore (0, 0)
	86 aload_2 (0, 0)
	87 areturn (0, 0)

Method: splitDiv
	0 iconst_2 (0, 0)
	1 anewarray (0, 0)
	2 org/apache/commons/math3/dfp/Dfp (0, 0)
	4 astore_2 (0, 0)
	5 aload_2 (0, 0)
	6 iconst_0 (0, 0)
	7 aload_0 (0, 0)
	8 iconst_0 (0, 0)
	9 aaload (0, 0)
	10 aload_1 (0, 0)
	11 iconst_0 (0, 0)
	12 aaload (0, 0)
	13 invokevirtual (0, 0)
	14 org/apache/commons/math3/dfp/Dfp.divide:(Lorg/apache/commons/math3/dfp/Dfp;)Lorg/apache/commons/math3/dfp/Dfp; (0, 0)
	16 aastore (0, 0)
	17 aload_2 (0, 0)
	18 iconst_1 (0, 0)
	19 aload_0 (0, 0)
	20 iconst_1 (0, 0)
	21 aaload (0, 0)
	22 aload_1 (0, 0)
	23 iconst_0 (0, 0)
	24 aaload (0, 0)
	25 invokevirtual (0, 0)
	26 org/apache/commons/math3/dfp/Dfp.multiply:(Lorg/apache/commons/math3/dfp/Dfp;)Lorg/apache/commons/math3/dfp/Dfp; (0, 0)
	28 aload_0 (0, 0)
	29 iconst_0 (0, 0)
	30 aaload (0, 0)
	31 aload_1 (0, 0)
	32 iconst_1 (0, 0)
	33 aaload (0, 0)
	34 invokevirtual (0, 0)
	35 org/apache/commons/math3/dfp/Dfp.multiply:(Lorg/apache/commons/math3/dfp/Dfp;)Lorg/apache/commons/math3/dfp/Dfp; (0, 0)
	37 invokevirtual (0, 0)
	38 org/apache/commons/math3/dfp/Dfp.subtract:(Lorg/apache/commons/math3/dfp/Dfp;)Lorg/apache/commons/math3/dfp/Dfp; (0, 0)
	40 aastore (0, 0)
	41 aload_2 (0, 0)
	42 iconst_1 (0, 0)
	43 aload_2 (0, 0)
	44 iconst_1 (0, 0)
	45 aaload (0, 0)
	46 aload_1 (0, 0)
	47 iconst_0 (0, 0)
	48 aaload (0, 0)
	49 aload_1 (0, 0)
	50 iconst_0 (0, 0)
	51 aaload (0, 0)
	52 invokevirtual (0, 0)
	53 org/apache/commons/math3/dfp/Dfp.multiply:(Lorg/apache/commons/math3/dfp/Dfp;)Lorg/apache/commons/math3/dfp/Dfp; (0, 0)
	55 aload_1 (0, 0)
	56 iconst_0 (0, 0)
	57 aaload (0, 0)
	58 aload_1 (0, 0)
	59 iconst_1 (0, 0)
	60 aaload (0, 0)
	61 invokevirtual (0, 0)
	62 org/apache/commons/math3/dfp/Dfp.multiply:(Lorg/apache/commons/math3/dfp/Dfp;)Lorg/apache/commons/math3/dfp/Dfp; (0, 0)
	64 invokevirtual (0, 0)
	65 org/apache/commons/math3/dfp/Dfp.add:(Lorg/apache/commons/math3/dfp/Dfp;)Lorg/apache/commons/math3/dfp/Dfp; (0, 0)
	67 invokevirtual (0, 0)
	68 org/apache/commons/math3/dfp/Dfp.divide:(Lorg/apache/commons/math3/dfp/Dfp;)Lorg/apache/commons/math3/dfp/Dfp; (0, 0)
	70 aastore (0, 0)
	71 aload_2 (0, 0)
	72 areturn (0, 0)

Method: splitPow
	0 iconst_0 (0, 0)
	1 istore_2 (0, 0)
	2 iconst_2 (0, 0)
	3 anewarray (0, 0)
	4 org/apache/commons/math3/dfp/Dfp (0, 0)
	6 astore_3 (0, 0)
	7 iconst_2 (0, 0)
	8 anewarray (0, 0)
	9 org/apache/commons/math3/dfp/Dfp (0, 0)
	11 astore (0, 0)
	12 #4 (0, 0)
	13 aload (0, 0)
	14 #4 (0, 0)
	15 iconst_0 (0, 0)
	16 aload_0 (0, 0)
	17 iconst_0 (0, 0)
	18 aaload (0, 0)
	19 invokevirtual (0, 0)
	20 org/apache/commons/math3/dfp/Dfp.getOne:()Lorg/apache/commons/math3/dfp/Dfp; (0, 0)
	22 aastore (0, 0)
	23 aload (0, 0)
	24 #4 (0, 0)
	25 iconst_1 (0, 0)
	26 aload_0 (0, 0)
	27 iconst_0 (0, 0)
	28 aaload (0, 0)
	29 invokevirtual (0, 0)
	30 org/apache/commons/math3/dfp/Dfp.getZero:()Lorg/apache/commons/math3/dfp/Dfp; (0, 0)
	32 aastore (0, 0)
	33 iload_1 (1, 1)
	34 ifne (1, 1)
	35 15 (1, 1)
	37 aload (1, 1)
	38 #4 (1, 1)
	39 iconst_0 (1, 1)
	40 aaload (1, 1)
	41 aload (1, 1)
	42 #4 (1, 1)
	43 iconst_1 (1, 1)
	44 aaload (1, 1)
	45 invokevirtual (1, 1)
	46 org/apache/commons/math3/dfp/Dfp.add:(Lorg/apache/commons/math3/dfp/Dfp;)Lorg/apache/commons/math3/dfp/Dfp; (1, 1)
	48 areturn (1, 1)
	49 iload_1 (1, 1)
	50 ifge (1, 1)
	51 8 (1, 1)
	53 iconst_1 (1, 1)
	54 istore_2 (1, 1)
	55 iload_1 (1, 1)
	56 ineg (1, 1)
	57 istore_1 (1, 1)
	58 aload_3 (0, 0)
	59 iconst_0 (0, 0)
	60 new (0, 0)
	61 org/apache/commons/math3/dfp/Dfp (0, 0)
	63 dup (0, 0)
	64 aload_0 (0, 0)
	65 iconst_0 (0, 0)
	66 aaload (0, 0)
	67 invokespecial (0, 0)
	68 org/apache/commons/math3/dfp/Dfp.<init>:(Lorg/apache/commons/math3/dfp/Dfp;)V (0, 0)
	70 aastore (0, 0)
	71 aload_3 (0, 0)
	72 iconst_1 (0, 0)
	73 new (0, 0)
	74 org/apache/commons/math3/dfp/Dfp (0, 0)
	76 dup (0, 0)
	77 aload_0 (0, 0)
	78 iconst_1 (0, 0)
	79 aaload (0, 0)
	80 invokespecial (0, 0)
	81 org/apache/commons/math3/dfp/Dfp.<init>:(Lorg/apache/commons/math3/dfp/Dfp;)V (0, 0)
	83 aastore (0, 0)
	84 iconst_1 (0, 0)
	85 istore (0, 0)
	86 #5 (0, 0)
	87 iload (1, 3)
	88 #5 (1, 3)
	89 istore (1, 3)
	90 #6 (1, 3)
	91 iload (1, 3)
	92 #5 (1, 3)
	93 iconst_2 (1, 3)
	94 imul (1, 3)
	95 istore (1, 3)
	96 #5 (1, 3)
	97 iload (2, 1)
	98 #5 (2, 1)
	99 iload_1 (2, 1)
	100 if_icmple (2, 1)
	101 6 (2, 1)
	103 goto (2, 1)
	104 12 (2, 1)
	106 aload_3 (1, 3)
	107 aload_3 (1, 3)
	108 invokestatic (1, 3)
	109 org/apache/commons/math3/dfp/DfpMath.splitMult:([Lorg/apache/commons/math3/dfp/Dfp;[Lorg/apache/commons/math3/dfp/Dfp;)[Lorg/apache/commons/math3/dfp/Dfp; (1, 3)
	111 astore_3 (1, 3)
	112 goto (1, 3)
	113 -25 (1, 3)
	115 iload (0, 0)
	116 #6 (0, 0)
	117 istore (0, 0)
	118 #5 (0, 0)
	119 iload_1 (0, 0)
	120 iload (0, 0)
	121 #5 (0, 0)
	122 isub (0, 0)
	123 istore_1 (0, 0)
	124 aload (0, 0)
	125 #4 (0, 0)
	126 aload_3 (0, 0)
	127 invokestatic (0, 0)
	128 org/apache/commons/math3/dfp/DfpMath.splitMult:([Lorg/apache/commons/math3/dfp/Dfp;[Lorg/apache/commons/math3/dfp/Dfp;)[Lorg/apache/commons/math3/dfp/Dfp; (0, 0)
	130 astore (0, 0)
	131 #4 (0, 0)
	132 iload_1 (1, 3)
	133 iconst_1 (1, 3)
	134 if_icmpge (1, 3)
	135 -76 (1, 3)
	137 aload (1, 3)
	138 #4 (1, 3)
	139 iconst_0 (1, 3)
	140 aload (1, 3)
	141 #4 (1, 3)
	142 iconst_0 (1, 3)
	143 aaload (1, 3)
	144 aload (1, 3)
	145 #4 (1, 3)
	146 iconst_1 (1, 3)
	147 aaload (1, 3)
	148 invokevirtual (1, 3)
	149 org/apache/commons/math3/dfp/Dfp.add:(Lorg/apache/commons/math3/dfp/Dfp;)Lorg/apache/commons/math3/dfp/Dfp; (1, 3)
	151 aastore (1, 3)
	152 iload_2 (2, 1)
	153 ifeq (2, 1)
	154 20 (2, 1)
	156 aload (2, 1)
	157 #4 (2, 1)
	158 iconst_0 (2, 1)
	159 aload_0 (2, 1)
	160 iconst_0 (2, 1)
	161 aaload (2, 1)
	162 invokevirtual (2, 1)
	163 org/apache/commons/math3/dfp/Dfp.getOne:()Lorg/apache/commons/math3/dfp/Dfp; (2, 1)
	165 aload (2, 1)
	166 #4 (2, 1)
	167 iconst_0 (2, 1)
	168 aaload (2, 1)
	169 invokevirtual (2, 1)
	170 org/apache/commons/math3/dfp/Dfp.divide:(Lorg/apache/commons/math3/dfp/Dfp;)Lorg/apache/commons/math3/dfp/Dfp; (2, 1)
	172 aastore (2, 1)
	173 aload (1, 3)
	174 #4 (1, 3)
	175 iconst_0 (1, 3)
	176 aaload (1, 3)
	177 areturn (0, 3)

Method: pow
	0 aload_0 (1, 1)
	1 invokevirtual (1, 1)
	2 org/apache/commons/math3/dfp/Dfp.getField:()Lorg/apache/commons/math3/dfp/DfpField; (1, 1)
	4 invokevirtual (1, 1)
	5 org/apache/commons/math3/dfp/DfpField.getRadixDigits:()I (1, 1)
	7 aload_1 (1, 1)
	8 invokevirtual (1, 1)
	9 org/apache/commons/math3/dfp/Dfp.getField:()Lorg/apache/commons/math3/dfp/DfpField; (1, 1)
	11 invokevirtual (1, 1)
	12 org/apache/commons/math3/dfp/DfpField.getRadixDigits:()I (1, 1)
	14 if_icmpeq (1, 1)
	15 35 (1, 1)
	17 aload_0 (1, 1)
	18 invokevirtual (1, 1)
	19 org/apache/commons/math3/dfp/Dfp.getField:()Lorg/apache/commons/math3/dfp/DfpField; (1, 1)
	21 iconst_1 (1, 1)
	22 invokevirtual (1, 1)
	23 org/apache/commons/math3/dfp/DfpField.setIEEEFlagsBits:(I)V (1, 1)
	25 aload_0 (1, 1)
	26 aload_0 (1, 1)
	27 invokevirtual (1, 1)
	28 org/apache/commons/math3/dfp/Dfp.getZero:()Lorg/apache/commons/math3/dfp/Dfp; (1, 1)
	30 invokevirtual (1, 1)
	31 org/apache/commons/math3/dfp/Dfp.newInstance:(Lorg/apache/commons/math3/dfp/Dfp;)Lorg/apache/commons/math3/dfp/Dfp; (1, 1)
	33 astore_2 (1, 1)
	34 aload_2 (1, 1)
	35 iconst_3 (1, 1)
	36 putfield (1, 1)
	37 org/apache/commons/math3/dfp/Dfp.nans:B (1, 1)
	39 aload_0 (1, 1)
	40 iconst_1 (1, 1)
	41 ldc (1, 1)
	42 pow (1, 1)
	43 aload_0 (1, 1)
	44 aload_2 (1, 1)
	45 invokevirtual (1, 1)
	46 org/apache/commons/math3/dfp/Dfp.dotrap:(ILjava/lang/String;Lorg/apache/commons/math3/dfp/Dfp;Lorg/apache/commons/math3/dfp/Dfp;)Lorg/apache/commons/math3/dfp/Dfp; (1, 1)
	48 areturn (1, 1)
	49 aload_0 (0, 0)
	50 invokevirtual (0, 0)
	51 org/apache/commons/math3/dfp/Dfp.getZero:()Lorg/apache/commons/math3/dfp/Dfp; (0, 0)
	53 astore_2 (0, 0)
	54 aload_0 (0, 0)
	55 invokevirtual (0, 0)
	56 org/apache/commons/math3/dfp/Dfp.getOne:()Lorg/apache/commons/math3/dfp/Dfp; (0, 0)
	58 astore_3 (0, 0)
	59 aload_0 (0, 0)
	60 invokevirtual (0, 0)
	61 org/apache/commons/math3/dfp/Dfp.getTwo:()Lorg/apache/commons/math3/dfp/Dfp; (0, 0)
	63 astore (0, 0)
	64 #4 (0, 0)
	65 iconst_0 (0, 0)
	66 istore (0, 0)
	67 #5 (0, 0)
	68 aload_1 (2, 1)
	69 aload_2 (2, 1)
	70 invokevirtual (2, 1)
	71 org/apache/commons/math3/dfp/Dfp.equals:(Ljava/lang/Object;)Z (2, 1)
	73 ifeq (2, 1)
	74 9 (2, 1)
	76 aload_0 (2, 1)
	77 aload_3 (2, 1)
	78 invokevirtual (2, 1)
	79 org/apache/commons/math3/dfp/Dfp.newInstance:(Lorg/apache/commons/math3/dfp/Dfp;)Lorg/apache/commons/math3/dfp/Dfp; (2, 1)
	81 areturn (2, 1)
	82 aload_1 (2, 1)
	83 aload_3 (2, 1)
	84 invokevirtual (2, 1)
	85 org/apache/commons/math3/dfp/Dfp.equals:(Ljava/lang/Object;)Z (2, 1)
	87 ifeq (2, 1)
	88 30 (2, 1)
	90 aload_0 (3, 1)
	91 invokevirtual (3, 1)
	92 org/apache/commons/math3/dfp/Dfp.isNaN:()Z (3, 1)
	94 ifeq (3, 1)
	95 21 (3, 1)
	97 aload_0 (4, 4)
	98 invokevirtual (4, 4)
	99 org/apache/commons/math3/dfp/Dfp.getField:()Lorg/apache/commons/math3/dfp/DfpField; (4, 4)
	101 iconst_1 (4, 4)
	102 invokevirtual (4, 4)
	103 org/apache/commons/math3/dfp/DfpField.setIEEEFlagsBits:(I)V (4, 4)
	105 aload_0 (4, 4)
	106 iconst_1 (4, 4)
	107 ldc (4, 4)
	108 pow (4, 4)
	109 aload_0 (4, 4)
	110 aload_0 (4, 4)
	111 invokevirtual (4, 4)
	112 org/apache/commons/math3/dfp/Dfp.dotrap:(ILjava/lang/String;Lorg/apache/commons/math3/dfp/Dfp;Lorg/apache/commons/math3/dfp/Dfp;)Lorg/apache/commons/math3/dfp/Dfp; (4, 4)
	114 areturn (4, 4)
	115 aload_0 (2, 1)
	116 areturn (2, 1)
	117 aload_0 (2, 1)
	118 invokevirtual (2, 1)
	119 org/apache/commons/math3/dfp/Dfp.isNaN:()Z (2, 1)
	121 ifne (2, 1)
	122 10 (2, 1)
	124 aload_1 (2, 1)
	125 invokevirtual (2, 1)
	126 org/apache/commons/math3/dfp/Dfp.isNaN:()Z (2, 1)
	128 ifeq (2, 1)
	129 26 (2, 1)
	131 aload_0 (3, 4)
	132 invokevirtual (3, 4)
	133 org/apache/commons/math3/dfp/Dfp.getField:()Lorg/apache/commons/math3/dfp/DfpField; (3, 4)
	135 iconst_1 (3, 4)
	136 invokevirtual (3, 4)
	137 org/apache/commons/math3/dfp/DfpField.setIEEEFlagsBits:(I)V (3, 4)
	139 aload_0 (3, 4)
	140 iconst_1 (3, 4)
	141 ldc (3, 4)
	142 pow (3, 4)
	143 aload_0 (3, 4)
	144 aload_0 (3, 4)
	145 iconst_1 (3, 4)
	146 iconst_3 (3, 4)
	147 invokevirtual (3, 4)
	148 org/apache/commons/math3/dfp/Dfp.newInstance:(BB)Lorg/apache/commons/math3/dfp/Dfp; (3, 4)
	150 invokevirtual (3, 4)
	151 org/apache/commons/math3/dfp/Dfp.dotrap:(ILjava/lang/String;Lorg/apache/commons/math3/dfp/Dfp;Lorg/apache/commons/math3/dfp/Dfp;)Lorg/apache/commons/math3/dfp/Dfp; (3, 4)
	153 areturn (3, 4)
	154 aload_0 (2, 1)
	155 aload_2 (2, 1)
	156 invokevirtual (2, 1)
	157 org/apache/commons/math3/dfp/Dfp.equals:(Ljava/lang/Object;)Z (2, 1)
	159 ifeq (2, 1)
	160 124 (2, 1)
	162 aload_3 (3, 1)
	163 aload_0 (3, 1)
	164 invokestatic (3, 1)
	165 org/apache/commons/math3/dfp/Dfp.copysign:(Lorg/apache/commons/math3/dfp/Dfp;Lorg/apache/commons/math3/dfp/Dfp;)Lorg/apache/commons/math3/dfp/Dfp; (3, 1)
	167 aload_2 (3, 1)
	168 invokevirtual (3, 1)
	169 org/apache/commons/math3/dfp/Dfp.greaterThan:(Lorg/apache/commons/math3/dfp/Dfp;)Z (3, 1)
	171 ifeq (3, 1)
	172 28 (3, 1)
	174 aload_1 (4, 1)
	175 aload_2 (4, 1)
	176 invokevirtual (4, 1)
	177 org/apache/commons/math3/dfp/Dfp.greaterThan:(Lorg/apache/commons/math3/dfp/Dfp;)Z (4, 1)
	179 ifeq (4, 1)
	180 9 (4, 1)
	182 aload_0 (4, 1)
	183 aload_2 (4, 1)
	184 invokevirtual (4, 1)
	185 org/apache/commons/math3/dfp/Dfp.newInstance:(Lorg/apache/commons/math3/dfp/Dfp;)Lorg/apache/commons/math3/dfp/Dfp; (4, 1)
	187 areturn (4, 1)
	188 aload_0 (5, 2)
	189 aload_0 (5, 2)
	190 iconst_1 (5, 2)
	191 iconst_1 (5, 2)
	192 invokevirtual (5, 2)
	193 org/apache/commons/math3/dfp/Dfp.newInstance:(BB)Lorg/apache/commons/math3/dfp/Dfp; (5, 2)
	195 invokevirtual (5, 2)
	196 org/apache/commons/math3/dfp/Dfp.newInstance:(Lorg/apache/commons/math3/dfp/Dfp;)Lorg/apache/commons/math3/dfp/Dfp; (5, 2)
	198 areturn (5, 2)
	199 aload_1 (5, 1)
	200 invokevirtual (5, 1)
	201 org/apache/commons/math3/dfp/Dfp.classify:()I (5, 1)
	203 ifne (5, 1)
	204 55 (5, 1)
	206 aload_1 (5, 1)
	207 invokevirtual (5, 1)
	208 org/apache/commons/math3/dfp/Dfp.rint:()Lorg/apache/commons/math3/dfp/Dfp; (5, 1)
	210 aload_1 (5, 1)
	211 invokevirtual (5, 1)
	212 org/apache/commons/math3/dfp/Dfp.equals:(Ljava/lang/Object;)Z (5, 1)
	214 ifeq (5, 1)
	215 44 (5, 1)
	217 aload_1 (5, 1)
	218 aload (5, 1)
	219 #4 (5, 1)
	220 invokevirtual (5, 1)
	221 org/apache/commons/math3/dfp/Dfp.remainder:(Lorg/apache/commons/math3/dfp/Dfp;)Lorg/apache/commons/math3/dfp/Dfp; (5, 1)
	223 aload_2 (5, 1)
	224 invokevirtual (5, 1)
	225 org/apache/commons/math3/dfp/Dfp.equals:(Ljava/lang/Object;)Z (5, 1)
	227 ifne (5, 1)
	228 31 (5, 1)
	230 aload_1 (6, 1)
	231 aload_2 (6, 1)
	232 invokevirtual (6, 1)
	233 org/apache/commons/math3/dfp/Dfp.greaterThan:(Lorg/apache/commons/math3/dfp/Dfp;)Z (6, 1)
	235 ifeq (6, 1)
	236 12 (6, 1)
	238 aload_0 (6, 1)
	239 aload_2 (6, 1)
	240 invokevirtual (6, 1)
	241 org/apache/commons/math3/dfp/Dfp.negate:()Lorg/apache/commons/math3/dfp/Dfp; (6, 1)
	243 invokevirtual (6, 1)
	244 org/apache/commons/math3/dfp/Dfp.newInstance:(Lorg/apache/commons/math3/dfp/Dfp;)Lorg/apache/commons/math3/dfp/Dfp; (6, 1)
	246 areturn (6, 1)
	247 aload_0 (7, 2)
	248 aload_0 (7, 2)
	249 iconst_m1 (7, 2)
	250 iconst_1 (7, 2)
	251 invokevirtual (7, 2)
	252 org/apache/commons/math3/dfp/Dfp.newInstance:(BB)Lorg/apache/commons/math3/dfp/Dfp; (7, 2)
	254 invokevirtual (7, 2)
	255 org/apache/commons/math3/dfp/Dfp.newInstance:(Lorg/apache/commons/math3/dfp/Dfp;)Lorg/apache/commons/math3/dfp/Dfp; (7, 2)
	257 areturn (7, 2)
	258 aload_1 (7, 1)
	259 aload_2 (7, 1)
	260 invokevirtual (7, 1)
	261 org/apache/commons/math3/dfp/Dfp.greaterThan:(Lorg/apache/commons/math3/dfp/Dfp;)Z (7, 1)
	263 ifeq (7, 1)
	264 9 (7, 1)
	266 aload_0 (7, 1)
	267 aload_2 (7, 1)
	268 invokevirtual (7, 1)
	269 org/apache/commons/math3/dfp/Dfp.newInstance:(Lorg/apache/commons/math3/dfp/Dfp;)Lorg/apache/commons/math3/dfp/Dfp; (7, 1)
	271 areturn (7, 1)
	272 aload_0 (8, 2)
	273 aload_0 (8, 2)
	274 iconst_1 (8, 2)
	275 iconst_1 (8, 2)
	276 invokevirtual (8, 2)
	277 org/apache/commons/math3/dfp/Dfp.newInstance:(BB)Lorg/apache/commons/math3/dfp/Dfp; (8, 2)
	279 invokevirtual (8, 2)
	280 org/apache/commons/math3/dfp/Dfp.newInstance:(Lorg/apache/commons/math3/dfp/Dfp;)Lorg/apache/commons/math3/dfp/Dfp; (8, 2)
	282 areturn (8, 2)
	283 aload_0 (2, 1)
	284 aload_2 (2, 1)
	285 invokevirtual (2, 1)
	286 org/apache/commons/math3/dfp/Dfp.lessThan:(Lorg/apache/commons/math3/dfp/Dfp;)Z (2, 1)
	288 ifeq (2, 1)
	289 11 (2, 1)
	291 aload_0 (2, 1)
	292 invokevirtual (2, 1)
	293 org/apache/commons/math3/dfp/Dfp.negate:()Lorg/apache/commons/math3/dfp/Dfp; (2, 1)
	295 astore_0 (2, 1)
	296 iconst_1 (2, 1)
	297 istore (2, 1)
	298 #5 (2, 1)
	299 aload_0 (2, 1)
	300 aload_3 (2, 1)
	301 invokevirtual (2, 1)
	302 org/apache/commons/math3/dfp/Dfp.greaterThan:(Lorg/apache/commons/math3/dfp/Dfp;)Z (2, 1)
	304 ifeq (2, 1)
	305 27 (2, 1)
	307 aload_1 (2, 1)
	308 invokevirtual (2, 1)
	309 org/apache/commons/math3/dfp/Dfp.classify:()I (2, 1)
	311 iconst_1 (2, 1)
	312 if_icmpne (2, 1)
	313 19 (2, 1)
	315 aload_1 (3, 1)
	316 aload_2 (3, 1)
	317 invokevirtual (3, 1)
	318 org/apache/commons/math3/dfp/Dfp.greaterThan:(Lorg/apache/commons/math3/dfp/Dfp;)Z (3, 1)
	320 ifeq (3, 1)
	321 5 (3, 1)
	323 aload_1 (3, 1)
	324 areturn (3, 1)
	325 aload_0 (4, 2)
	326 aload_2 (4, 2)
	327 invokevirtual (4, 2)
	328 org/apache/commons/math3/dfp/Dfp.newInstance:(Lorg/apache/commons/math3/dfp/Dfp;)Lorg/apache/commons/math3/dfp/Dfp; (4, 2)
	330 areturn (4, 2)
	331 aload_0 (2, 1)
	332 aload_3 (2, 1)
	333 invokevirtual (2, 1)
	334 org/apache/commons/math3/dfp/Dfp.lessThan:(Lorg/apache/commons/math3/dfp/Dfp;)Z (2, 1)
	336 ifeq (2, 1)
	337 35 (2, 1)
	339 aload_1 (2, 1)
	340 invokevirtual (2, 1)
	341 org/apache/commons/math3/dfp/Dfp.classify:()I (2, 1)
	343 iconst_1 (2, 1)
	344 if_icmpne (2, 1)
	345 27 (2, 1)
	347 aload_1 (3, 1)
	348 aload_2 (3, 1)
	349 invokevirtual (3, 1)
	350 org/apache/commons/math3/dfp/Dfp.greaterThan:(Lorg/apache/commons/math3/dfp/Dfp;)Z (3, 1)
	352 ifeq (3, 1)
	353 9 (3, 1)
	355 aload_0 (3, 1)
	356 aload_2 (3, 1)
	357 invokevirtual (3, 1)
	358 org/apache/commons/math3/dfp/Dfp.newInstance:(Lorg/apache/commons/math3/dfp/Dfp;)Lorg/apache/commons/math3/dfp/Dfp; (3, 1)
	360 areturn (3, 1)
	361 aload_0 (4, 2)
	362 aload_1 (4, 2)
	363 aload_3 (4, 2)
	364 invokestatic (4, 2)
	365 org/apache/commons/math3/dfp/Dfp.copysign:(Lorg/apache/commons/math3/dfp/Dfp;Lorg/apache/commons/math3/dfp/Dfp;)Lorg/apache/commons/math3/dfp/Dfp; (4, 2)
	367 invokevirtual (4, 2)
	368 org/apache/commons/math3/dfp/Dfp.newInstance:(Lorg/apache/commons/math3/dfp/Dfp;)Lorg/apache/commons/math3/dfp/Dfp; (4, 2)
	370 areturn (4, 2)
	371 aload_0 (2, 1)
	372 aload_3 (2, 1)
	373 invokevirtual (2, 1)
	374 org/apache/commons/math3/dfp/Dfp.equals:(Ljava/lang/Object;)Z (2, 1)
	376 ifeq (2, 1)
	377 34 (2, 1)
	379 aload_1 (2, 1)
	380 invokevirtual (2, 1)
	381 org/apache/commons/math3/dfp/Dfp.classify:()I (2, 1)
	383 iconst_1 (2, 1)
	384 if_icmpne (2, 1)
	385 26 (2, 1)
	387 aload_0 (2, 1)
	388 invokevirtual (2, 1)
	389 org/apache/commons/math3/dfp/Dfp.getField:()Lorg/apache/commons/math3/dfp/DfpField; (2, 1)
	391 iconst_1 (2, 1)
	392 invokevirtual (2, 1)
	393 org/apache/commons/math3/dfp/DfpField.setIEEEFlagsBits:(I)V (2, 1)
	395 aload_0 (2, 1)
	396 iconst_1 (2, 1)
	397 ldc (2, 1)
	398 pow (2, 1)
	399 aload_0 (2, 1)
	400 aload_0 (2, 1)
	401 iconst_1 (2, 1)
	402 iconst_3 (2, 1)
	403 invokevirtual (2, 1)
	404 org/apache/commons/math3/dfp/Dfp.newInstance:(BB)Lorg/apache/commons/math3/dfp/Dfp; (2, 1)
	406 invokevirtual (2, 1)
	407 org/apache/commons/math3/dfp/Dfp.dotrap:(ILjava/lang/String;Lorg/apache/commons/math3/dfp/Dfp;Lorg/apache/commons/math3/dfp/Dfp;)Lorg/apache/commons/math3/dfp/Dfp; (2, 1)
	409 areturn (2, 1)
	410 aload_0 (2, 1)
	411 invokevirtual (2, 1)
	412 org/apache/commons/math3/dfp/Dfp.classify:()I (2, 1)
	414 iconst_1 (2, 1)
	415 if_icmpne (2, 1)
	416 108 (2, 1)
	418 iload (3, 1)
	419 #5 (3, 1)
	420 ifeq (3, 1)
	421 87 (3, 1)
	423 aload_1 (4, 1)
	424 invokevirtual (4, 1)
	425 org/apache/commons/math3/dfp/Dfp.classify:()I (4, 1)
	427 ifne (4, 1)
	428 55 (4, 1)
	430 aload_1 (4, 1)
	431 invokevirtual (4, 1)
	432 org/apache/commons/math3/dfp/Dfp.rint:()Lorg/apache/commons/math3/dfp/Dfp; (4, 1)
	434 aload_1 (4, 1)
	435 invokevirtual (4, 1)
	436 org/apache/commons/math3/dfp/Dfp.equals:(Ljava/lang/Object;)Z (4, 1)
	438 ifeq (4, 1)
	439 44 (4, 1)
	441 aload_1 (4, 1)
	442 aload (4, 1)
	443 #4 (4, 1)
	444 invokevirtual (4, 1)
	445 org/apache/commons/math3/dfp/Dfp.remainder:(Lorg/apache/commons/math3/dfp/Dfp;)Lorg/apache/commons/math3/dfp/Dfp; (4, 1)
	447 aload_2 (4, 1)
	448 invokevirtual (4, 1)
	449 org/apache/commons/math3/dfp/Dfp.equals:(Ljava/lang/Object;)Z (4, 1)
	451 ifne (4, 1)
	452 31 (4, 1)
	454 aload_1 (5, 1)
	455 aload_2 (5, 1)
	456 invokevirtual (5, 1)
	457 org/apache/commons/math3/dfp/Dfp.greaterThan:(Lorg/apache/commons/math3/dfp/Dfp;)Z (5, 1)
	459 ifeq (5, 1)
	460 14 (5, 1)
	462 aload_0 (5, 1)
	463 aload_0 (5, 1)
	464 iconst_m1 (5, 1)
	465 iconst_1 (5, 1)
	466 invokevirtual (5, 1)
	467 org/apache/commons/math3/dfp/Dfp.newInstance:(BB)Lorg/apache/commons/math3/dfp/Dfp; (5, 1)
	469 invokevirtual (5, 1)
	470 org/apache/commons/math3/dfp/Dfp.newInstance:(Lorg/apache/commons/math3/dfp/Dfp;)Lorg/apache/commons/math3/dfp/Dfp; (5, 1)
	472 areturn (5, 1)
	473 aload_0 (6, 2)
	474 aload_2 (6, 2)
	475 invokevirtual (6, 2)
	476 org/apache/commons/math3/dfp/Dfp.negate:()Lorg/apache/commons/math3/dfp/Dfp; (6, 2)
	478 invokevirtual (6, 2)
	479 org/apache/commons/math3/dfp/Dfp.newInstance:(Lorg/apache/commons/math3/dfp/Dfp;)Lorg/apache/commons/math3/dfp/Dfp; (6, 2)
	481 areturn (6, 2)
	482 aload_1 (6, 1)
	483 aload_2 (6, 1)
	484 invokevirtual (6, 1)
	485 org/apache/commons/math3/dfp/Dfp.greaterThan:(Lorg/apache/commons/math3/dfp/Dfp;)Z (6, 1)
	487 ifeq (6, 1)
	488 14 (6, 1)
	490 aload_0 (6, 1)
	491 aload_0 (6, 1)
	492 iconst_1 (6, 1)
	493 iconst_1 (6, 1)
	494 invokevirtual (6, 1)
	495 org/apache/commons/math3/dfp/Dfp.newInstance:(BB)Lorg/apache/commons/math3/dfp/Dfp; (6, 1)
	497 invokevirtual (6, 1)
	498 org/apache/commons/math3/dfp/Dfp.newInstance:(Lorg/apache/commons/math3/dfp/Dfp;)Lorg/apache/commons/math3/dfp/Dfp; (6, 1)
	500 areturn (6, 1)
	501 aload_0 (7, 2)
	502 aload_2 (7, 2)
	503 invokevirtual (7, 2)
	504 org/apache/commons/math3/dfp/Dfp.newInstance:(Lorg/apache/commons/math3/dfp/Dfp;)Lorg/apache/commons/math3/dfp/Dfp; (7, 2)
	506 areturn (7, 2)
	507 aload_1 (5, 1)
	508 aload_2 (5, 1)
	509 invokevirtual (5, 1)
	510 org/apache/commons/math3/dfp/Dfp.greaterThan:(Lorg/apache/commons/math3/dfp/Dfp;)Z (5, 1)
	512 ifeq (5, 1)
	513 5 (5, 1)
	515 aload_0 (5, 1)
	516 areturn (5, 1)
	517 aload_0 (6, 2)
	518 aload_2 (6, 2)
	519 invokevirtual (6, 2)
	520 org/apache/commons/math3/dfp/Dfp.newInstance:(Lorg/apache/commons/math3/dfp/Dfp;)Lorg/apache/commons/math3/dfp/Dfp; (6, 2)
	522 areturn (6, 2)
	523 iload (2, 1)
	524 #5 (2, 1)
	525 ifeq (2, 1)
	526 37 (2, 1)
	528 aload_1 (2, 1)
	529 invokevirtual (2, 1)
	530 org/apache/commons/math3/dfp/Dfp.rint:()Lorg/apache/commons/math3/dfp/Dfp; (2, 1)
	532 aload_1 (2, 1)
	533 invokevirtual (2, 1)
	534 org/apache/commons/math3/dfp/Dfp.equals:(Ljava/lang/Object;)Z (2, 1)
	536 ifne (2, 1)
	537 26 (2, 1)
	539 aload_0 (2, 1)
	540 invokevirtual (2, 1)
	541 org/apache/commons/math3/dfp/Dfp.getField:()Lorg/apache/commons/math3/dfp/DfpField; (2, 1)
	543 iconst_1 (2, 1)
	544 invokevirtual (2, 1)
	545 org/apache/commons/math3/dfp/DfpField.setIEEEFlagsBits:(I)V (2, 1)
	547 aload_0 (2, 1)
	548 iconst_1 (2, 1)
	549 ldc (2, 1)
	550 pow (2, 1)
	551 aload_0 (2, 1)
	552 aload_0 (2, 1)
	553 iconst_1 (2, 1)
	554 iconst_3 (2, 1)
	555 invokevirtual (2, 1)
	556 org/apache/commons/math3/dfp/Dfp.newInstance:(BB)Lorg/apache/commons/math3/dfp/Dfp; (2, 1)
	558 invokevirtual (2, 1)
	559 org/apache/commons/math3/dfp/Dfp.dotrap:(ILjava/lang/String;Lorg/apache/commons/math3/dfp/Dfp;Lorg/apache/commons/math3/dfp/Dfp;)Lorg/apache/commons/math3/dfp/Dfp; (2, 1)
	561 areturn (2, 1)
	562 aload_1 (2, 1)
	563 aload_0 (2, 1)
	564 ldc (2, 1)
	565 100000000 (2, 1)
	566 invokevirtual (2, 1)
	567 org/apache/commons/math3/dfp/Dfp.newInstance:(I)Lorg/apache/commons/math3/dfp/Dfp; (2, 1)
	569 invokevirtual (2, 1)
	570 org/apache/commons/math3/dfp/Dfp.lessThan:(Lorg/apache/commons/math3/dfp/Dfp;)Z (2, 1)
	572 ifeq (2, 1)
	573 150 (2, 1)
	575 aload_1 (2, 1)
	576 aload_0 (2, 1)
	577 ldc (2, 1)
	578 4194967296 (2, 1)
	579 invokevirtual (2, 1)
	580 org/apache/commons/math3/dfp/Dfp.newInstance:(I)Lorg/apache/commons/math3/dfp/Dfp; (2, 1)
	582 invokevirtual (2, 1)
	583 org/apache/commons/math3/dfp/Dfp.greaterThan:(Lorg/apache/commons/math3/dfp/Dfp;)Z (2, 1)
	585 ifeq (2, 1)
	586 137 (2, 1)
	588 aload_1 (2, 1)
	589 invokevirtual (2, 1)
	590 org/apache/commons/math3/dfp/Dfp.rint:()Lorg/apache/commons/math3/dfp/Dfp; (2, 1)
	592 astore (2, 1)
	593 #8 (2, 1)
	594 aload (2, 1)
	595 #8 (2, 1)
	596 invokevirtual (2, 1)
	597 org/apache/commons/math3/dfp/Dfp.intValue:()I (2, 1)
	599 istore (2, 1)
	600 #6 (2, 1)
	601 aload_1 (2, 1)
	602 aload (2, 1)
	603 #8 (2, 1)
	604 invokevirtual (2, 1)
	605 org/apache/commons/math3/dfp/Dfp.subtract:(Lorg/apache/commons/math3/dfp/Dfp;)Lorg/apache/commons/math3/dfp/Dfp; (2, 1)
	607 astore (2, 1)
	608 #9 (2, 1)
	609 aload (3, 1)
	610 #9 (3, 1)
	611 aload_2 (3, 1)
	612 invokevirtual (3, 1)
	613 org/apache/commons/math3/dfp/Dfp.unequal:(Lorg/apache/commons/math3/dfp/Dfp;)Z (3, 1)
	615 ifeq (3, 1)
	616 93 (3, 1)
	618 aload (3, 1)
	619 #9 (3, 1)
	620 aload_0 (3, 1)
	621 invokestatic (3, 1)
	622 org/apache/commons/math3/dfp/DfpMath.log:(Lorg/apache/commons/math3/dfp/Dfp;)Lorg/apache/commons/math3/dfp/Dfp; (3, 1)
	624 invokevirtual (3, 1)
	625 org/apache/commons/math3/dfp/Dfp.multiply:(Lorg/apache/commons/math3/dfp/Dfp;)Lorg/apache/commons/math3/dfp/Dfp; (3, 1)
	627 astore (3, 1)
	628 #10 (3, 1)
	629 aload (3, 1)
	630 #10 (3, 1)
	631 aload_0 (3, 1)
	632 invokevirtual (3, 1)
	633 org/apache/commons/math3/dfp/Dfp.getField:()Lorg/apache/commons/math3/dfp/DfpField; (3, 1)
	635 invokevirtual (3, 1)
	636 org/apache/commons/math3/dfp/DfpField.getLn2:()Lorg/apache/commons/math3/dfp/Dfp; (3, 1)
	638 invokevirtual (3, 1)
	639 org/apache/commons/math3/dfp/Dfp.divide:(Lorg/apache/commons/math3/dfp/Dfp;)Lorg/apache/commons/math3/dfp/Dfp; (3, 1)
	641 invokevirtual (3, 1)
	642 org/apache/commons/math3/dfp/Dfp.rint:()Lorg/apache/commons/math3/dfp/Dfp; (3, 1)
	644 astore (3, 1)
	645 #11 (3, 1)
	646 aload (3, 1)
	647 #10 (3, 1)
	648 aload (3, 1)
	649 #11 (3, 1)
	650 aload_0 (3, 1)
	651 invokevirtual (3, 1)
	652 org/apache/commons/math3/dfp/Dfp.getField:()Lorg/apache/commons/math3/dfp/DfpField; (3, 1)
	654 invokevirtual (3, 1)
	655 org/apache/commons/math3/dfp/DfpField.getLn2:()Lorg/apache/commons/math3/dfp/Dfp; (3, 1)
	657 invokevirtual (3, 1)
	658 org/apache/commons/math3/dfp/Dfp.multiply:(Lorg/apache/commons/math3/dfp/Dfp;)Lorg/apache/commons/math3/dfp/Dfp; (3, 1)
	660 invokevirtual (3, 1)
	661 org/apache/commons/math3/dfp/Dfp.subtract:(Lorg/apache/commons/math3/dfp/Dfp;)Lorg/apache/commons/math3/dfp/Dfp; (3, 1)
	663 astore (3, 1)
	664 #12 (3, 1)
	665 aload_0 (3, 1)
	666 invokestatic (3, 1)
	667 org/apache/commons/math3/dfp/DfpMath.split:(Lorg/apache/commons/math3/dfp/Dfp;)[Lorg/apache/commons/math3/dfp/Dfp; (3, 1)
	669 iload (3, 1)
	670 #6 (3, 1)
	671 invokestatic (3, 1)
	672 org/apache/commons/math3/dfp/DfpMath.splitPow:([Lorg/apache/commons/math3/dfp/Dfp;I)Lorg/apache/commons/math3/dfp/Dfp; (3, 1)
	674 astore (3, 1)
	675 #7 (3, 1)
	676 aload (3, 1)
	677 #7 (3, 1)
	678 aload (3, 1)
	679 #4 (3, 1)
	680 aload (3, 1)
	681 #11 (3, 1)
	682 invokevirtual (3, 1)
	683 org/apache/commons/math3/dfp/Dfp.intValue:()I (3, 1)
	685 invokestatic (3, 1)
	686 org/apache/commons/math3/dfp/DfpMath.pow:(Lorg/apache/commons/math3/dfp/Dfp;I)Lorg/apache/commons/math3/dfp/Dfp; (3, 1)
	688 invokevirtual (3, 1)
	689 org/apache/commons/math3/dfp/Dfp.multiply:(Lorg/apache/commons/math3/dfp/Dfp;)Lorg/apache/commons/math3/dfp/Dfp; (3, 1)
	691 astore (3, 1)
	692 #7 (3, 1)
	693 aload (3, 1)
	694 #7 (3, 1)
	695 aload (3, 1)
	696 #12 (3, 1)
	697 invokestatic (3, 1)
	698 org/apache/commons/math3/dfp/DfpMath.exp:(Lorg/apache/commons/math3/dfp/Dfp;)Lorg/apache/commons/math3/dfp/Dfp; (3, 1)
	700 invokevirtual (3, 1)
	701 org/apache/commons/math3/dfp/Dfp.multiply:(Lorg/apache/commons/math3/dfp/Dfp;)Lorg/apache/commons/math3/dfp/Dfp; (3, 1)
	703 astore (3, 1)
	704 #7 (3, 1)
	705 goto (4, 2)
	706 14 (4, 2)
	708 aload_0 (4, 2)
	709 invokestatic (4, 2)
	710 org/apache/commons/math3/dfp/DfpMath.split:(Lorg/apache/commons/math3/dfp/Dfp;)[Lorg/apache/commons/math3/dfp/Dfp; (4, 2)
	712 iload (4, 2)
	713 #6 (4, 2)
	714 invokestatic (4, 2)
	715 org/apache/commons/math3/dfp/DfpMath.splitPow:([Lorg/apache/commons/math3/dfp/Dfp;I)Lorg/apache/commons/math3/dfp/Dfp; (4, 2)
	717 astore (4, 2)
	718 #7 (4, 2)
	719 goto (3, 2)
	720 16 (3, 2)
	722 aload_0 (3, 2)
	723 invokestatic (3, 2)
	724 org/apache/commons/math3/dfp/DfpMath.log:(Lorg/apache/commons/math3/dfp/Dfp;)Lorg/apache/commons/math3/dfp/Dfp; (3, 2)
	726 aload_1 (3, 2)
	727 invokevirtual (3, 2)
	728 org/apache/commons/math3/dfp/Dfp.multiply:(Lorg/apache/commons/math3/dfp/Dfp;)Lorg/apache/commons/math3/dfp/Dfp; (3, 2)
	730 invokestatic (3, 2)
	731 org/apache/commons/math3/dfp/DfpMath.exp:(Lorg/apache/commons/math3/dfp/Dfp;)Lorg/apache/commons/math3/dfp/Dfp; (3, 2)
	733 astore (3, 2)
	734 #7 (3, 2)
	735 iload (2, 1)
	736 #5 (2, 1)
	737 ifeq (2, 1)
	738 34 (2, 1)
	740 aload_1 (2, 1)
	741 invokevirtual (2, 1)
	742 org/apache/commons/math3/dfp/Dfp.rint:()Lorg/apache/commons/math3/dfp/Dfp; (2, 1)
	744 aload_1 (2, 1)
	745 invokevirtual (2, 1)
	746 org/apache/commons/math3/dfp/Dfp.equals:(Ljava/lang/Object;)Z (2, 1)
	748 ifeq (2, 1)
	749 23 (2, 1)
	751 aload_1 (2, 1)
	752 aload (2, 1)
	753 #4 (2, 1)
	754 invokevirtual (2, 1)
	755 org/apache/commons/math3/dfp/Dfp.remainder:(Lorg/apache/commons/math3/dfp/Dfp;)Lorg/apache/commons/math3/dfp/Dfp; (2, 1)
	757 aload_2 (2, 1)
	758 invokevirtual (2, 1)
	759 org/apache/commons/math3/dfp/Dfp.equals:(Ljava/lang/Object;)Z (2, 1)
	761 ifne (2, 1)
	762 10 (2, 1)
	764 aload (3, 1)
	765 #7 (3, 1)
	766 invokevirtual (3, 1)
	767 org/apache/commons/math3/dfp/Dfp.negate:()Lorg/apache/commons/math3/dfp/Dfp; (3, 1)
	769 astore (3, 1)
	770 #7 (3, 1)
	771 aload_0 (1, 4)
	772 aload (1, 4)
	773 #7 (1, 4)
	774 invokevirtual (1, 4)
	775 org/apache/commons/math3/dfp/Dfp.newInstance:(Lorg/apache/commons/math3/dfp/Dfp;)Lorg/apache/commons/math3/dfp/Dfp; (1, 4)
	777 areturn (0, 4)

Method: exp
	0 aload_0 (0, 0)
	1 invokevirtual (0, 0)
	2 org/apache/commons/math3/dfp/Dfp.rint:()Lorg/apache/commons/math3/dfp/Dfp; (0, 0)
	4 astore_1 (0, 0)
	5 aload_0 (0, 0)
	6 aload_1 (0, 0)
	7 invokevirtual (0, 0)
	8 org/apache/commons/math3/dfp/Dfp.subtract:(Lorg/apache/commons/math3/dfp/Dfp;)Lorg/apache/commons/math3/dfp/Dfp; (0, 0)
	10 astore_2 (0, 0)
	11 aload_1 (0, 0)
	12 invokevirtual (0, 0)
	13 org/apache/commons/math3/dfp/Dfp.intValue:()I (0, 0)
	15 istore_3 (0, 0)
	16 iload_3 (1, 1)
	17 ldc (1, 1)
	18 2147483646 (1, 1)
	19 if_icmple (1, 1)
	20 10 (1, 1)
	22 aload_0 (1, 1)
	23 iconst_1 (1, 1)
	24 iconst_1 (1, 1)
	25 invokevirtual (1, 1)
	26 org/apache/commons/math3/dfp/Dfp.newInstance:(BB)Lorg/apache/commons/math3/dfp/Dfp; (1, 1)
	28 areturn (1, 1)
	29 iload_3 (1, 1)
	30 ldc (1, 1)
	31 2147483650 (1, 1)
	32 if_icmpge (1, 1)
	33 8 (1, 1)
	35 aload_0 (1, 1)
	36 invokevirtual (1, 1)
	37 org/apache/commons/math3/dfp/Dfp.newInstance:()Lorg/apache/commons/math3/dfp/Dfp; (1, 1)
	39 areturn (1, 1)
	40 aload_0 (0, 0)
	41 invokevirtual (0, 0)
	42 org/apache/commons/math3/dfp/Dfp.getField:()Lorg/apache/commons/math3/dfp/DfpField; (0, 0)
	44 invokevirtual (0, 0)
	45 org/apache/commons/math3/dfp/DfpField.getESplit:()[Lorg/apache/commons/math3/dfp/Dfp; (0, 0)
	47 iload_3 (0, 0)
	48 invokestatic (0, 0)
	49 org/apache/commons/math3/dfp/DfpMath.splitPow:([Lorg/apache/commons/math3/dfp/Dfp;I)Lorg/apache/commons/math3/dfp/Dfp; (0, 0)
	51 astore (0, 0)
	52 #4 (0, 0)
	53 aload_2 (0, 0)
	54 invokestatic (0, 0)
	55 org/apache/commons/math3/dfp/DfpMath.expInternal:(Lorg/apache/commons/math3/dfp/Dfp;)Lorg/apache/commons/math3/dfp/Dfp; (0, 0)
	57 astore (0, 0)
	58 #5 (0, 0)
	59 aload (0, 0)
	60 #4 (0, 0)
	61 aload (0, 0)
	62 #5 (0, 0)
	63 invokevirtual (0, 0)
	64 org/apache/commons/math3/dfp/Dfp.multiply:(Lorg/apache/commons/math3/dfp/Dfp;)Lorg/apache/commons/math3/dfp/Dfp; (0, 0)
	66 areturn (0, 0)

Method: expInternal
	0 aload_0 (0, 0)
	1 invokevirtual (0, 0)
	2 org/apache/commons/math3/dfp/Dfp.getOne:()Lorg/apache/commons/math3/dfp/Dfp; (0, 0)
	4 astore_1 (0, 0)
	5 aload_0 (0, 0)
	6 invokevirtual (0, 0)
	7 org/apache/commons/math3/dfp/Dfp.getOne:()Lorg/apache/commons/math3/dfp/Dfp; (0, 0)
	9 astore_2 (0, 0)
	10 aload_0 (0, 0)
	11 invokevirtual (0, 0)
	12 org/apache/commons/math3/dfp/Dfp.getOne:()Lorg/apache/commons/math3/dfp/Dfp; (0, 0)
	14 astore_3 (0, 0)
	15 new (0, 0)
	16 org/apache/commons/math3/dfp/Dfp (0, 0)
	18 dup (0, 0)
	19 aload_1 (0, 0)
	20 invokespecial (0, 0)
	21 org/apache/commons/math3/dfp/Dfp.<init>:(Lorg/apache/commons/math3/dfp/Dfp;)V (0, 0)
	23 astore (0, 0)
	24 #4 (0, 0)
	25 iconst_1 (1, 4)
	26 istore (1, 4)
	27 #5 (1, 4)
	28 iload (1, 4)
	29 #5 (1, 4)
	30 bipush (1, 4)
	31 90 (1, 4)
	32 if_icmpge (1, 4)
	33 54 (1, 4)
	35 aload_2 (1, 4)
	36 aload_0 (1, 4)
	37 invokevirtual (1, 4)
	38 org/apache/commons/math3/dfp/Dfp.multiply:(Lorg/apache/commons/math3/dfp/Dfp;)Lorg/apache/commons/math3/dfp/Dfp; (1, 4)
	40 astore_2 (1, 4)
	41 aload_3 (1, 4)
	42 iload (1, 4)
	43 #5 (1, 4)
	44 invokevirtual (1, 4)
	45 org/apache/commons/math3/dfp/Dfp.divide:(I)Lorg/apache/commons/math3/dfp/Dfp; (1, 4)
	47 astore_3 (1, 4)
	48 aload_1 (1, 4)
	49 aload_2 (1, 4)
	50 aload_3 (1, 4)
	51 invokevirtual (1, 4)
	52 org/apache/commons/math3/dfp/Dfp.multiply:(Lorg/apache/commons/math3/dfp/Dfp;)Lorg/apache/commons/math3/dfp/Dfp; (1, 4)
	54 invokevirtual (1, 4)
	55 org/apache/commons/math3/dfp/Dfp.add:(Lorg/apache/commons/math3/dfp/Dfp;)Lorg/apache/commons/math3/dfp/Dfp; (1, 4)
	57 astore_1 (1, 4)
	58 aload_1 (2, 1)
	59 aload (2, 1)
	60 #4 (2, 1)
	61 invokevirtual (2, 1)
	62 org/apache/commons/math3/dfp/Dfp.equals:(Ljava/lang/Object;)Z (2, 1)
	64 ifeq (2, 1)
	65 6 (2, 1)
	67 goto (2, 1)
	68 19 (2, 1)
	70 new (1, 4)
	71 org/apache/commons/math3/dfp/Dfp (1, 4)
	73 dup (1, 4)
	74 aload_1 (1, 4)
	75 invokespecial (1, 4)
	76 org/apache/commons/math3/dfp/Dfp.<init>:(Lorg/apache/commons/math3/dfp/Dfp;)V (1, 4)
	78 astore (1, 4)
	79 #4 (1, 4)
	80 iinc (1, 4)
	81 #5 (1, 4)
	82 -89 (1, 4)
	83 goto (1, 4)
	84 -55 (1, 4)
	86 aload_1 (0, 0)
	87 areturn (0, 0)

Method: log
	0 iconst_0 (0, 0)
	1 istore (0, 0)
	2 #4 (0, 0)
	3 aload_0 (1, 1)
	4 aload_0 (1, 1)
	5 invokevirtual (1, 1)
	6 org/apache/commons/math3/dfp/Dfp.getZero:()Lorg/apache/commons/math3/dfp/Dfp; (1, 1)
	8 invokevirtual (1, 1)
	9 org/apache/commons/math3/dfp/Dfp.equals:(Ljava/lang/Object;)Z (1, 1)
	11 ifne (1, 1)
	12 21 (1, 1)
	14 aload_0 (1, 1)
	15 aload_0 (1, 1)
	16 invokevirtual (1, 1)
	17 org/apache/commons/math3/dfp/Dfp.getZero:()Lorg/apache/commons/math3/dfp/Dfp; (1, 1)
	19 invokevirtual (1, 1)
	20 org/apache/commons/math3/dfp/Dfp.lessThan:(Lorg/apache/commons/math3/dfp/Dfp;)Z (1, 1)
	22 ifne (1, 1)
	23 10 (1, 1)
	25 aload_0 (1, 1)
	26 invokevirtual (1, 1)
	27 org/apache/commons/math3/dfp/Dfp.isNaN:()Z (1, 1)
	29 ifeq (1, 1)
	30 26 (1, 1)
	32 aload_0 (1, 1)
	33 invokevirtual (1, 1)
	34 org/apache/commons/math3/dfp/Dfp.getField:()Lorg/apache/commons/math3/dfp/DfpField; (1, 1)
	36 iconst_1 (1, 1)
	37 invokevirtual (1, 1)
	38 org/apache/commons/math3/dfp/DfpField.setIEEEFlagsBits:(I)V (1, 1)
	40 aload_0 (1, 1)
	41 iconst_1 (1, 1)
	42 ldc (1, 1)
	43 ln (1, 1)
	44 aload_0 (1, 1)
	45 aload_0 (1, 1)
	46 iconst_1 (1, 1)
	47 iconst_3 (1, 1)
	48 invokevirtual (1, 1)
	49 org/apache/commons/math3/dfp/Dfp.newInstance:(BB)Lorg/apache/commons/math3/dfp/Dfp; (1, 1)
	51 invokevirtual (1, 1)
	52 org/apache/commons/math3/dfp/Dfp.dotrap:(ILjava/lang/String;Lorg/apache/commons/math3/dfp/Dfp;Lorg/apache/commons/math3/dfp/Dfp;)Lorg/apache/commons/math3/dfp/Dfp; (1, 1)
	54 areturn (1, 1)
	55 aload_0 (1, 1)
	56 invokevirtual (1, 1)
	57 org/apache/commons/math3/dfp/Dfp.classify:()I (1, 1)
	59 iconst_1 (1, 1)
	60 if_icmpne (1, 1)
	61 5 (1, 1)
	63 aload_0 (1, 1)
	64 areturn (1, 1)
	65 new (0, 0)
	66 org/apache/commons/math3/dfp/Dfp (0, 0)
	68 dup (0, 0)
	69 aload_0 (0, 0)
	70 invokespecial (0, 0)
	71 org/apache/commons/math3/dfp/Dfp.<init>:(Lorg/apache/commons/math3/dfp/Dfp;)V (0, 0)
	73 astore_2 (0, 0)
	74 aload_2 (0, 0)
	75 invokevirtual (0, 0)
	76 org/apache/commons/math3/dfp/Dfp.log10K:()I (0, 0)
	78 istore_1 (0, 0)
	79 aload_2 (0, 0)
	80 aload_0 (0, 0)
	81 sipush (0, 0)
	82 10000 (0, 0)
	84 invokevirtual (0, 0)
	85 org/apache/commons/math3/dfp/Dfp.newInstance:(I)Lorg/apache/commons/math3/dfp/Dfp; (0, 0)
	87 iload_1 (0, 0)
	88 invokestatic (0, 0)
	89 org/apache/commons/math3/dfp/DfpMath.pow:(Lorg/apache/commons/math3/dfp/Dfp;I)Lorg/apache/commons/math3/dfp/Dfp; (0, 0)
	91 invokevirtual (0, 0)
	92 org/apache/commons/math3/dfp/Dfp.divide:(Lorg/apache/commons/math3/dfp/Dfp;)Lorg/apache/commons/math3/dfp/Dfp; (0, 0)
	94 astore_2 (0, 0)
	95 aload_2 (0, 0)
	96 invokevirtual (0, 0)
	97 org/apache/commons/math3/dfp/Dfp.floor:()Lorg/apache/commons/math3/dfp/Dfp; (0, 0)
	99 invokevirtual (0, 0)
	100 org/apache/commons/math3/dfp/Dfp.intValue:()I (0, 0)
	102 istore_3 (0, 0)
	103 iload_3 (1, 3)
	104 iconst_2 (1, 3)
	105 if_icmple (1, 3)
	106 13 (1, 3)
	108 iload_3 (1, 3)
	109 iconst_1 (1, 3)
	110 ishr (1, 3)
	111 istore_3 (1, 3)
	112 iinc (1, 3)
	113 #4 (1, 3)
	114 -89 (1, 3)
	115 goto (1, 3)
	116 -12 (1, 3)
	118 aload_2 (0, 0)
	119 invokestatic (0, 0)
	120 org/apache/commons/math3/dfp/DfpMath.split:(Lorg/apache/commons/math3/dfp/Dfp;)[Lorg/apache/commons/math3/dfp/Dfp; (0, 0)
	122 astore (0, 0)
	123 #5 (0, 0)
	124 iconst_2 (0, 0)
	125 anewarray (0, 0)
	126 org/apache/commons/math3/dfp/Dfp (0, 0)
	128 astore (0, 0)
	129 #6 (0, 0)
	130 aload (0, 0)
	131 #6 (0, 0)
	132 iconst_0 (0, 0)
	133 aload_0 (0, 0)
	134 invokevirtual (0, 0)
	135 org/apache/commons/math3/dfp/Dfp.getTwo:()Lorg/apache/commons/math3/dfp/Dfp; (0, 0)
	137 iload (0, 0)
	138 #4 (0, 0)
	139 invokestatic (0, 0)
	140 org/apache/commons/math3/dfp/DfpMath.pow:(Lorg/apache/commons/math3/dfp/Dfp;I)Lorg/apache/commons/math3/dfp/Dfp; (0, 0)
	142 aastore (0, 0)
	143 aload (0, 0)
	144 #5 (0, 0)
	145 iconst_0 (0, 0)
	146 aload (0, 0)
	147 #5 (0, 0)
	148 iconst_0 (0, 0)
	149 aaload (0, 0)
	150 aload (0, 0)
	151 #6 (0, 0)
	152 iconst_0 (0, 0)
	153 aaload (0, 0)
	154 invokevirtual (0, 0)
	155 org/apache/commons/math3/dfp/Dfp.divide:(Lorg/apache/commons/math3/dfp/Dfp;)Lorg/apache/commons/math3/dfp/Dfp; (0, 0)
	157 aastore (0, 0)
	158 aload (0, 0)
	159 #5 (0, 0)
	160 iconst_1 (0, 0)
	161 aload (0, 0)
	162 #5 (0, 0)
	163 iconst_1 (0, 0)
	164 aaload (0, 0)
	165 aload (0, 0)
	166 #6 (0, 0)
	167 iconst_0 (0, 0)
	168 aaload (0, 0)
	169 invokevirtual (0, 0)
	170 org/apache/commons/math3/dfp/Dfp.divide:(Lorg/apache/commons/math3/dfp/Dfp;)Lorg/apache/commons/math3/dfp/Dfp; (0, 0)
	172 aastore (0, 0)
	173 aload (1, 4)
	174 #6 (1, 4)
	175 iconst_0 (1, 4)
	176 aload_0 (1, 4)
	177 ldc (1, 4)
	178 1.33333 (1, 4)
	179 invokevirtual (1, 4)
	180 org/apache/commons/math3/dfp/Dfp.newInstance:(Ljava/lang/String;)Lorg/apache/commons/math3/dfp/Dfp; (1, 4)
	182 aastore (1, 4)
	183 aload (2, 3)
	184 #5 (2, 3)
	185 iconst_0 (2, 3)
	186 aaload (2, 3)
	187 aload (2, 3)
	188 #5 (2, 3)
	189 iconst_1 (2, 3)
	190 aaload (2, 3)
	191 invokevirtual (2, 3)
	192 org/apache/commons/math3/dfp/Dfp.add:(Lorg/apache/commons/math3/dfp/Dfp;)Lorg/apache/commons/math3/dfp/Dfp; (2, 3)
	194 aload (2, 3)
	195 #6 (2, 3)
	196 iconst_0 (2, 3)
	197 aaload (2, 3)
	198 invokevirtual (2, 3)
	199 org/apache/commons/math3/dfp/Dfp.greaterThan:(Lorg/apache/commons/math3/dfp/Dfp;)Z (2, 3)
	201 ifeq (2, 3)
	202 33 (2, 3)
	204 aload (2, 3)
	205 #5 (2, 3)
	206 iconst_0 (2, 3)
	207 aload (2, 3)
	208 #5 (2, 3)
	209 iconst_0 (2, 3)
	210 aaload (2, 3)
	211 iconst_2 (2, 3)
	212 invokevirtual (2, 3)
	213 org/apache/commons/math3/dfp/Dfp.divide:(I)Lorg/apache/commons/math3/dfp/Dfp; (2, 3)
	215 aastore (2, 3)
	216 aload (2, 3)
	217 #5 (2, 3)
	218 iconst_1 (2, 3)
	219 aload (2, 3)
	220 #5 (2, 3)
	221 iconst_1 (2, 3)
	222 aaload (2, 3)
	223 iconst_2 (2, 3)
	224 invokevirtual (2, 3)
	225 org/apache/commons/math3/dfp/Dfp.divide:(I)Lorg/apache/commons/math3/dfp/Dfp; (2, 3)
	227 aastore (2, 3)
	228 iinc (2, 3)
	229 #4 (2, 3)
	230 -89 (2, 3)
	231 goto (2, 3)
	232 -48 (2, 3)
	234 aload (1, 4)
	235 #5 (1, 4)
	236 invokestatic (1, 4)
	237 org/apache/commons/math3/dfp/DfpMath.logInternal:([Lorg/apache/commons/math3/dfp/Dfp;)[Lorg/apache/commons/math3/dfp/Dfp; (1, 4)
	239 astore (1, 4)
	240 #7 (1, 4)
	241 aload (1, 4)
	242 #5 (1, 4)
	243 iconst_0 (1, 4)
	244 aload_0 (1, 4)
	245 new (1, 4)
	246 java/lang/StringBuilder (1, 4)
	248 dup (1, 4)
	249 invokespecial (1, 4)
	250 java/lang/StringBuilder.<init>:()V (1, 4)
	252 iload (1, 4)
	253 #4 (1, 4)
	254 iconst_4 (1, 4)
	255 iload_1 (1, 4)
	256 imul (1, 4)
	257 iadd (1, 4)
	258 invokevirtual (1, 4)
	259 java/lang/StringBuilder.append:(I)Ljava/lang/StringBuilder; (1, 4)
	261 invokevirtual (1, 4)
	262 java/lang/StringBuilder.toString:()Ljava/lang/String; (1, 4)
	264 invokevirtual (1, 4)
	265 org/apache/commons/math3/dfp/Dfp.newInstance:(Ljava/lang/String;)Lorg/apache/commons/math3/dfp/Dfp; (1, 4)
	267 aastore (1, 4)
	268 aload (1, 4)
	269 #5 (1, 4)
	270 iconst_1 (1, 4)
	271 aload_0 (1, 4)
	272 invokevirtual (1, 4)
	273 org/apache/commons/math3/dfp/Dfp.getZero:()Lorg/apache/commons/math3/dfp/Dfp; (1, 4)
	275 aastore (1, 4)
	276 aload_0 (1, 4)
	277 invokevirtual (1, 4)
	278 org/apache/commons/math3/dfp/Dfp.getField:()Lorg/apache/commons/math3/dfp/DfpField; (1, 4)
	280 invokevirtual (1, 4)
	281 org/apache/commons/math3/dfp/DfpField.getLn2Split:()[Lorg/apache/commons/math3/dfp/Dfp; (1, 4)
	283 aload (1, 4)
	284 #5 (1, 4)
	285 invokestatic (1, 4)
	286 org/apache/commons/math3/dfp/DfpMath.splitMult:([Lorg/apache/commons/math3/dfp/Dfp;[Lorg/apache/commons/math3/dfp/Dfp;)[Lorg/apache/commons/math3/dfp/Dfp; (1, 4)
	288 astore (1, 4)
	289 #6 (1, 4)
	290 aload (1, 4)
	291 #7 (1, 4)
	292 iconst_0 (1, 4)
	293 aload (1, 4)
	294 #7 (1, 4)
	295 iconst_0 (1, 4)
	296 aaload (1, 4)
	297 aload (1, 4)
	298 #6 (1, 4)
	299 iconst_0 (1, 4)
	300 aaload (1, 4)
	301 invokevirtual (1, 4)
	302 org/apache/commons/math3/dfp/Dfp.add:(Lorg/apache/commons/math3/dfp/Dfp;)Lorg/apache/commons/math3/dfp/Dfp; (1, 4)
	304 aastore (1, 4)
	305 aload (1, 4)
	306 #7 (1, 4)
	307 iconst_1 (1, 4)
	308 aload (1, 4)
	309 #7 (1, 4)
	310 iconst_1 (1, 4)
	311 aaload (1, 4)
	312 aload (1, 4)
	313 #6 (1, 4)
	314 iconst_1 (1, 4)
	315 aaload (1, 4)
	316 invokevirtual (1, 4)
	317 org/apache/commons/math3/dfp/Dfp.add:(Lorg/apache/commons/math3/dfp/Dfp;)Lorg/apache/commons/math3/dfp/Dfp; (1, 4)
	319 aastore (1, 4)
	320 aload (1, 4)
	321 #5 (1, 4)
	322 iconst_0 (1, 4)
	323 aload_0 (1, 4)
	324 new (1, 4)
	325 java/lang/StringBuilder (1, 4)
	327 dup (1, 4)
	328 invokespecial (1, 4)
	329 java/lang/StringBuilder.<init>:()V (1, 4)
	331 iconst_4 (1, 4)
	332 iload_1 (1, 4)
	333 imul (1, 4)
	334 invokevirtual (1, 4)
	335 java/lang/StringBuilder.append:(I)Ljava/lang/StringBuilder; (1, 4)
	337 invokevirtual (1, 4)
	338 java/lang/StringBuilder.toString:()Ljava/lang/String; (1, 4)
	340 invokevirtual (1, 4)
	341 org/apache/commons/math3/dfp/Dfp.newInstance:(Ljava/lang/String;)Lorg/apache/commons/math3/dfp/Dfp; (1, 4)
	343 aastore (1, 4)
	344 aload (1, 4)
	345 #5 (1, 4)
	346 iconst_1 (1, 4)
	347 aload_0 (1, 4)
	348 invokevirtual (1, 4)
	349 org/apache/commons/math3/dfp/Dfp.getZero:()Lorg/apache/commons/math3/dfp/Dfp; (1, 4)
	351 aastore (1, 4)
	352 aload_0 (1, 4)
	353 invokevirtual (1, 4)
	354 org/apache/commons/math3/dfp/Dfp.getField:()Lorg/apache/commons/math3/dfp/DfpField; (1, 4)
	356 invokevirtual (1, 4)
	357 org/apache/commons/math3/dfp/DfpField.getLn5Split:()[Lorg/apache/commons/math3/dfp/Dfp; (1, 4)
	359 aload (1, 4)
	360 #5 (1, 4)
	361 invokestatic (1, 4)
	362 org/apache/commons/math3/dfp/DfpMath.splitMult:([Lorg/apache/commons/math3/dfp/Dfp;[Lorg/apache/commons/math3/dfp/Dfp;)[Lorg/apache/commons/math3/dfp/Dfp; (1, 4)
	364 astore (1, 4)
	365 #6 (1, 4)
	366 aload (1, 4)
	367 #7 (1, 4)
	368 iconst_0 (1, 4)
	369 aload (1, 4)
	370 #7 (1, 4)
	371 iconst_0 (1, 4)
	372 aaload (1, 4)
	373 aload (1, 4)
	374 #6 (1, 4)
	375 iconst_0 (1, 4)
	376 aaload (1, 4)
	377 invokevirtual (1, 4)
	378 org/apache/commons/math3/dfp/Dfp.add:(Lorg/apache/commons/math3/dfp/Dfp;)Lorg/apache/commons/math3/dfp/Dfp; (1, 4)
	380 aastore (1, 4)
	381 aload (1, 4)
	382 #7 (1, 4)
	383 iconst_1 (1, 4)
	384 aload (1, 4)
	385 #7 (1, 4)
	386 iconst_1 (1, 4)
	387 aaload (1, 4)
	388 aload (1, 4)
	389 #6 (1, 4)
	390 iconst_1 (1, 4)
	391 aaload (1, 4)
	392 invokevirtual (1, 4)
	393 org/apache/commons/math3/dfp/Dfp.add:(Lorg/apache/commons/math3/dfp/Dfp;)Lorg/apache/commons/math3/dfp/Dfp; (1, 4)
	395 aastore (1, 4)
	396 aload_0 (1, 4)
	397 aload (1, 4)
	398 #7 (1, 4)
	399 iconst_0 (1, 4)
	400 aaload (1, 4)
	401 aload (1, 4)
	402 #7 (1, 4)
	403 iconst_1 (1, 4)
	404 aaload (1, 4)
	405 invokevirtual (1, 4)
	406 org/apache/commons/math3/dfp/Dfp.add:(Lorg/apache/commons/math3/dfp/Dfp;)Lorg/apache/commons/math3/dfp/Dfp; (1, 4)
	408 invokevirtual (1, 4)
	409 org/apache/commons/math3/dfp/Dfp.newInstance:(Lorg/apache/commons/math3/dfp/Dfp;)Lorg/apache/commons/math3/dfp/Dfp; (1, 4)
	411 areturn (0, 4)

Method: logInternal
	0 aload_0 (0, 0)
	1 iconst_0 (0, 0)
	2 aaload (0, 0)
	3 iconst_4 (0, 0)
	4 invokevirtual (0, 0)
	5 org/apache/commons/math3/dfp/Dfp.divide:(I)Lorg/apache/commons/math3/dfp/Dfp; (0, 0)
	7 aload_0 (0, 0)
	8 iconst_1 (0, 0)
	9 aaload (0, 0)
	10 iconst_4 (0, 0)
	11 invokevirtual (0, 0)
	12 org/apache/commons/math3/dfp/Dfp.divide:(I)Lorg/apache/commons/math3/dfp/Dfp; (0, 0)
	14 invokevirtual (0, 0)
	15 org/apache/commons/math3/dfp/Dfp.add:(Lorg/apache/commons/math3/dfp/Dfp;)Lorg/apache/commons/math3/dfp/Dfp; (0, 0)
	17 astore_1 (0, 0)
	18 aload_1 (0, 0)
	19 aload_0 (0, 0)
	20 iconst_0 (0, 0)
	21 aaload (0, 0)
	22 ldc (0, 0)
	23 -0.25 (0, 0)
	24 invokevirtual (0, 0)
	25 org/apache/commons/math3/dfp/Dfp.newInstance:(Ljava/lang/String;)Lorg/apache/commons/math3/dfp/Dfp; (0, 0)
	27 invokevirtual (0, 0)
	28 org/apache/commons/math3/dfp/Dfp.add:(Lorg/apache/commons/math3/dfp/Dfp;)Lorg/apache/commons/math3/dfp/Dfp; (0, 0)
	30 aload_1 (0, 0)
	31 aload_0 (0, 0)
	32 iconst_0 (0, 0)
	33 aaload (0, 0)
	34 ldc (0, 0)
	35 0.25 (0, 0)
	36 invokevirtual (0, 0)
	37 org/apache/commons/math3/dfp/Dfp.newInstance:(Ljava/lang/String;)Lorg/apache/commons/math3/dfp/Dfp; (0, 0)
	39 invokevirtual (0, 0)
	40 org/apache/commons/math3/dfp/Dfp.add:(Lorg/apache/commons/math3/dfp/Dfp;)Lorg/apache/commons/math3/dfp/Dfp; (0, 0)
	42 invokevirtual (0, 0)
	43 org/apache/commons/math3/dfp/Dfp.divide:(Lorg/apache/commons/math3/dfp/Dfp;)Lorg/apache/commons/math3/dfp/Dfp; (0, 0)
	45 astore_2 (0, 0)
	46 new (0, 0)
	47 org/apache/commons/math3/dfp/Dfp (0, 0)
	49 dup (0, 0)
	50 aload_2 (0, 0)
	51 invokespecial (0, 0)
	52 org/apache/commons/math3/dfp/Dfp.<init>:(Lorg/apache/commons/math3/dfp/Dfp;)V (0, 0)
	54 astore_3 (0, 0)
	55 new (0, 0)
	56 org/apache/commons/math3/dfp/Dfp (0, 0)
	58 dup (0, 0)
	59 aload_2 (0, 0)
	60 invokespecial (0, 0)
	61 org/apache/commons/math3/dfp/Dfp.<init>:(Lorg/apache/commons/math3/dfp/Dfp;)V (0, 0)
	63 astore (0, 0)
	64 #4 (0, 0)
	65 new (0, 0)
	66 org/apache/commons/math3/dfp/Dfp (0, 0)
	68 dup (0, 0)
	69 aload_3 (0, 0)
	70 invokespecial (0, 0)
	71 org/apache/commons/math3/dfp/Dfp.<init>:(Lorg/apache/commons/math3/dfp/Dfp;)V (0, 0)
	73 astore (0, 0)
	74 #5 (0, 0)
	75 iconst_1 (0, 0)
	76 istore (0, 0)
	77 #6 (0, 0)
	78 iconst_0 (1, 4)
	79 istore (1, 4)
	80 #7 (1, 4)
	81 iload (1, 4)
	82 #7 (1, 4)
	83 sipush (1, 4)
	84 10000 (1, 4)
	86 if_icmpge (1, 4)
	87 64 (1, 4)
	89 aload (1, 4)
	90 #4 (1, 4)
	91 aload_2 (1, 4)
	92 invokevirtual (1, 4)
	93 org/apache/commons/math3/dfp/Dfp.multiply:(Lorg/apache/commons/math3/dfp/Dfp;)Lorg/apache/commons/math3/dfp/Dfp; (1, 4)
	95 astore (1, 4)
	96 #4 (1, 4)
	97 aload (1, 4)
	98 #4 (1, 4)
	99 aload_2 (1, 4)
	100 invokevirtual (1, 4)
	101 org/apache/commons/math3/dfp/Dfp.multiply:(Lorg/apache/commons/math3/dfp/Dfp;)Lorg/apache/commons/math3/dfp/Dfp; (1, 4)
	103 astore (1, 4)
	104 #4 (1, 4)
	105 iinc (1, 4)
	106 #6 (1, 4)
	107 25 (1, 4)
	108 aload (1, 4)
	109 #4 (1, 4)
	110 iload (1, 4)
	111 #6 (1, 4)
	112 invokevirtual (1, 4)
	113 org/apache/commons/math3/dfp/Dfp.divide:(I)Lorg/apache/commons/math3/dfp/Dfp; (1, 4)
	115 astore_1 (1, 4)
	116 aload_3 (1, 4)
	117 aload_1 (1, 4)
	118 invokevirtual (1, 4)
	119 org/apache/commons/math3/dfp/Dfp.add:(Lorg/apache/commons/math3/dfp/Dfp;)Lorg/apache/commons/math3/dfp/Dfp; (1, 4)
	121 astore_3 (1, 4)
	122 aload_3 (2, 1)
	123 aload (2, 1)
	124 #5 (2, 1)
	125 invokevirtual (2, 1)
	126 org/apache/commons/math3/dfp/Dfp.equals:(Ljava/lang/Object;)Z (2, 1)
	128 ifeq (2, 1)
	129 6 (2, 1)
	131 goto (2, 1)
	132 19 (2, 1)
	134 new (1, 4)
	135 org/apache/commons/math3/dfp/Dfp (1, 4)
	137 dup (1, 4)
	138 aload_3 (1, 4)
	139 invokespecial (1, 4)
	140 org/apache/commons/math3/dfp/Dfp.<init>:(Lorg/apache/commons/math3/dfp/Dfp;)V (1, 4)
	142 astore (1, 4)
	143 #5 (1, 4)
	144 iinc (1, 4)
	145 #7 (1, 4)
	146 -89 (1, 4)
	147 goto (1, 4)
	148 -66 (1, 4)
	150 aload_3 (0, 0)
	151 aload_0 (0, 0)
	152 iconst_0 (0, 0)
	153 aaload (0, 0)
	154 invokevirtual (0, 0)
	155 org/apache/commons/math3/dfp/Dfp.getTwo:()Lorg/apache/commons/math3/dfp/Dfp; (0, 0)
	157 invokevirtual (0, 0)
	158 org/apache/commons/math3/dfp/Dfp.multiply:(Lorg/apache/commons/math3/dfp/Dfp;)Lorg/apache/commons/math3/dfp/Dfp; (0, 0)
	160 astore_3 (0, 0)
	161 aload_3 (0, 0)
	162 invokestatic (0, 0)
	163 org/apache/commons/math3/dfp/DfpMath.split:(Lorg/apache/commons/math3/dfp/Dfp;)[Lorg/apache/commons/math3/dfp/Dfp; (0, 0)
	165 areturn (0, 0)

Method: sinInternal
	0 aload_0 (0, 0)
	1 iconst_0 (0, 0)
	2 aaload (0, 0)
	3 aload_0 (0, 0)
	4 iconst_1 (0, 0)
	5 aaload (0, 0)
	6 invokevirtual (0, 0)
	7 org/apache/commons/math3/dfp/Dfp.add:(Lorg/apache/commons/math3/dfp/Dfp;)Lorg/apache/commons/math3/dfp/Dfp; (0, 0)
	9 astore_1 (0, 0)
	10 aload_1 (0, 0)
	11 astore_2 (0, 0)
	12 aload_1 (0, 0)
	13 aload_1 (0, 0)
	14 invokevirtual (0, 0)
	15 org/apache/commons/math3/dfp/Dfp.multiply:(Lorg/apache/commons/math3/dfp/Dfp;)Lorg/apache/commons/math3/dfp/Dfp; (0, 0)
	17 astore_1 (0, 0)
	18 aload_2 (0, 0)
	19 astore_3 (0, 0)
	20 aload_0 (0, 0)
	21 iconst_0 (0, 0)
	22 aaload (0, 0)
	23 invokevirtual (0, 0)
	24 org/apache/commons/math3/dfp/Dfp.getOne:()Lorg/apache/commons/math3/dfp/Dfp; (0, 0)
	26 astore (0, 0)
	27 #4 (0, 0)
	28 new (0, 0)
	29 org/apache/commons/math3/dfp/Dfp (0, 0)
	31 dup (0, 0)
	32 aload_2 (0, 0)
	33 invokespecial (0, 0)
	34 org/apache/commons/math3/dfp/Dfp.<init>:(Lorg/apache/commons/math3/dfp/Dfp;)V (0, 0)
	36 astore (0, 0)
	37 #5 (0, 0)
	38 iconst_3 (1, 4)
	39 istore (1, 4)
	40 #6 (1, 4)
	41 iload (1, 4)
	42 #6 (1, 4)
	43 bipush (1, 4)
	44 90 (1, 4)
	45 if_icmpge (1, 4)
	46 67 (1, 4)
	48 aload_3 (1, 4)
	49 aload_1 (1, 4)
	50 invokevirtual (1, 4)
	51 org/apache/commons/math3/dfp/Dfp.multiply:(Lorg/apache/commons/math3/dfp/Dfp;)Lorg/apache/commons/math3/dfp/Dfp; (1, 4)
	53 astore_3 (1, 4)
	54 aload_3 (1, 4)
	55 invokevirtual (1, 4)
	56 org/apache/commons/math3/dfp/Dfp.negate:()Lorg/apache/commons/math3/dfp/Dfp; (1, 4)
	58 astore_3 (1, 4)
	59 aload (1, 4)
	60 #4 (1, 4)
	61 iload (1, 4)
	62 #6 (1, 4)
	63 iconst_1 (1, 4)
	64 isub (1, 4)
	65 iload (1, 4)
	66 #6 (1, 4)
	67 imul (1, 4)
	68 invokevirtual (1, 4)
	69 org/apache/commons/math3/dfp/Dfp.divide:(I)Lorg/apache/commons/math3/dfp/Dfp; (1, 4)
	71 astore (1, 4)
	72 #4 (1, 4)
	73 aload_2 (1, 4)
	74 aload_3 (1, 4)
	75 aload (1, 4)
	76 #4 (1, 4)
	77 invokevirtual (1, 4)
	78 org/apache/commons/math3/dfp/Dfp.multiply:(Lorg/apache/commons/math3/dfp/Dfp;)Lorg/apache/commons/math3/dfp/Dfp; (1, 4)
	80 invokevirtual (1, 4)
	81 org/apache/commons/math3/dfp/Dfp.add:(Lorg/apache/commons/math3/dfp/Dfp;)Lorg/apache/commons/math3/dfp/Dfp; (1, 4)
	83 astore_2 (1, 4)
	84 aload_2 (2, 1)
	85 aload (2, 1)
	86 #5 (2, 1)
	87 invokevirtual (2, 1)
	88 org/apache/commons/math3/dfp/Dfp.equals:(Ljava/lang/Object;)Z (2, 1)
	90 ifeq (2, 1)
	91 6 (2, 1)
	93 goto (2, 1)
	94 19 (2, 1)
	96 new (1, 4)
	97 org/apache/commons/math3/dfp/Dfp (1, 4)
	99 dup (1, 4)
	100 aload_2 (1, 4)
	101 invokespecial (1, 4)
	102 org/apache/commons/math3/dfp/Dfp.<init>:(Lorg/apache/commons/math3/dfp/Dfp;)V (1, 4)
	104 astore (1, 4)
	105 #5 (1, 4)
	106 iinc (1, 4)
	107 #6 (1, 4)
	108 -89 (1, 4)
	109 goto (1, 4)
	110 -68 (1, 4)
	112 aload_2 (0, 0)
	113 areturn (0, 0)

Method: cosInternal
	0 aload_0 (0, 0)
	1 iconst_0 (0, 0)
	2 aaload (0, 0)
	3 invokevirtual (0, 0)
	4 org/apache/commons/math3/dfp/Dfp.getOne:()Lorg/apache/commons/math3/dfp/Dfp; (0, 0)
	6 astore_1 (0, 0)
	7 aload_1 (0, 0)
	8 astore_2 (0, 0)
	9 aload_1 (0, 0)
	10 astore_3 (0, 0)
	11 aload_0 (0, 0)
	12 iconst_0 (0, 0)
	13 aaload (0, 0)
	14 aload_0 (0, 0)
	15 iconst_1 (0, 0)
	16 aaload (0, 0)
	17 invokevirtual (0, 0)
	18 org/apache/commons/math3/dfp/Dfp.add:(Lorg/apache/commons/math3/dfp/Dfp;)Lorg/apache/commons/math3/dfp/Dfp; (0, 0)
	20 astore (0, 0)
	21 #4 (0, 0)
	22 aload (0, 0)
	23 #4 (0, 0)
	24 aload (0, 0)
	25 #4 (0, 0)
	26 invokevirtual (0, 0)
	27 org/apache/commons/math3/dfp/Dfp.multiply:(Lorg/apache/commons/math3/dfp/Dfp;)Lorg/apache/commons/math3/dfp/Dfp; (0, 0)
	29 astore (0, 0)
	30 #4 (0, 0)
	31 aload_1 (0, 0)
	32 astore (0, 0)
	33 #5 (0, 0)
	34 new (0, 0)
	35 org/apache/commons/math3/dfp/Dfp (0, 0)
	37 dup (0, 0)
	38 aload_3 (0, 0)
	39 invokespecial (0, 0)
	40 org/apache/commons/math3/dfp/Dfp.<init>:(Lorg/apache/commons/math3/dfp/Dfp;)V (0, 0)
	42 astore (0, 0)
	43 #6 (0, 0)
	44 iconst_2 (1, 4)
	45 istore (1, 4)
	46 #7 (1, 4)
	47 iload (1, 4)
	48 #7 (1, 4)
	49 bipush (1, 4)
	50 90 (1, 4)
	51 if_icmpge (1, 4)
	52 68 (1, 4)
	54 aload_2 (1, 4)
	55 aload (1, 4)
	56 #4 (1, 4)
	57 invokevirtual (1, 4)
	58 org/apache/commons/math3/dfp/Dfp.multiply:(Lorg/apache/commons/math3/dfp/Dfp;)Lorg/apache/commons/math3/dfp/Dfp; (1, 4)
	60 astore_2 (1, 4)
	61 aload_2 (1, 4)
	62 invokevirtual (1, 4)
	63 org/apache/commons/math3/dfp/Dfp.negate:()Lorg/apache/commons/math3/dfp/Dfp; (1, 4)
	65 astore_2 (1, 4)
	66 aload (1, 4)
	67 #5 (1, 4)
	68 iload (1, 4)
	69 #7 (1, 4)
	70 iconst_1 (1, 4)
	71 isub (1, 4)
	72 iload (1, 4)
	73 #7 (1, 4)
	74 imul (1, 4)
	75 invokevirtual (1, 4)
	76 org/apache/commons/math3/dfp/Dfp.divide:(I)Lorg/apache/commons/math3/dfp/Dfp; (1, 4)
	78 astore (1, 4)
	79 #5 (1, 4)
	80 aload_3 (1, 4)
	81 aload_2 (1, 4)
	82 aload (1, 4)
	83 #5 (1, 4)
	84 invokevirtual (1, 4)
	85 org/apache/commons/math3/dfp/Dfp.multiply:(Lorg/apache/commons/math3/dfp/Dfp;)Lorg/apache/commons/math3/dfp/Dfp; (1, 4)
	87 invokevirtual (1, 4)
	88 org/apache/commons/math3/dfp/Dfp.add:(Lorg/apache/commons/math3/dfp/Dfp;)Lorg/apache/commons/math3/dfp/Dfp; (1, 4)
	90 astore_3 (1, 4)
	91 aload_3 (2, 1)
	92 aload (2, 1)
	93 #6 (2, 1)
	94 invokevirtual (2, 1)
	95 org/apache/commons/math3/dfp/Dfp.equals:(Ljava/lang/Object;)Z (2, 1)
	97 ifeq (2, 1)
	98 6 (2, 1)
	100 goto (2, 1)
	101 19 (2, 1)
	103 new (1, 4)
	104 org/apache/commons/math3/dfp/Dfp (1, 4)
	106 dup (1, 4)
	107 aload_3 (1, 4)
	108 invokespecial (1, 4)
	109 org/apache/commons/math3/dfp/Dfp.<init>:(Lorg/apache/commons/math3/dfp/Dfp;)V (1, 4)
	111 astore (1, 4)
	112 #6 (1, 4)
	113 iinc (1, 4)
	114 #7 (1, 4)
	115 -89 (1, 4)
	116 goto (1, 4)
	117 -69 (1, 4)
	119 aload_3 (0, 0)
	120 areturn (0, 0)

Method: sin
	0 aload_0 (0, 0)
	1 invokevirtual (0, 0)
	2 org/apache/commons/math3/dfp/Dfp.getField:()Lorg/apache/commons/math3/dfp/DfpField; (0, 0)
	4 invokevirtual (0, 0)
	5 org/apache/commons/math3/dfp/DfpField.getPi:()Lorg/apache/commons/math3/dfp/Dfp; (0, 0)
	7 astore_1 (0, 0)
	8 aload_0 (0, 0)
	9 invokevirtual (0, 0)
	10 org/apache/commons/math3/dfp/Dfp.getField:()Lorg/apache/commons/math3/dfp/DfpField; (0, 0)
	12 invokevirtual (0, 0)
	13 org/apache/commons/math3/dfp/DfpField.getZero:()Lorg/apache/commons/math3/dfp/Dfp; (0, 0)
	15 astore_2 (0, 0)
	16 iconst_0 (0, 0)
	17 istore_3 (0, 0)
	18 aload_0 (0, 0)
	19 aload_1 (0, 0)
	20 iconst_2 (0, 0)
	21 invokevirtual (0, 0)
	22 org/apache/commons/math3/dfp/Dfp.multiply:(I)Lorg/apache/commons/math3/dfp/Dfp; (0, 0)
	24 invokevirtual (0, 0)
	25 org/apache/commons/math3/dfp/Dfp.remainder:(Lorg/apache/commons/math3/dfp/Dfp;)Lorg/apache/commons/math3/dfp/Dfp; (0, 0)
	27 astore (0, 0)
	28 #4 (0, 0)
	29 aload (2, 1)
	30 #4 (2, 1)
	31 aload_2 (2, 1)
	32 invokevirtual (2, 1)
	33 org/apache/commons/math3/dfp/Dfp.lessThan:(Lorg/apache/commons/math3/dfp/Dfp;)Z (2, 1)
	35 ifeq (2, 1)
	36 12 (2, 1)
	38 aload (2, 1)
	39 #4 (2, 1)
	40 invokevirtual (2, 1)
	41 org/apache/commons/math3/dfp/Dfp.negate:()Lorg/apache/commons/math3/dfp/Dfp; (2, 1)
	43 astore (2, 1)
	44 #4 (2, 1)
	45 iconst_1 (2, 1)
	46 istore_3 (2, 1)
	47 aload (2, 1)
	48 #4 (2, 1)
	49 aload_1 (2, 1)
	50 iconst_2 (2, 1)
	51 invokevirtual (2, 1)
	52 org/apache/commons/math3/dfp/Dfp.divide:(I)Lorg/apache/commons/math3/dfp/Dfp; (2, 1)
	54 invokevirtual (2, 1)
	55 org/apache/commons/math3/dfp/Dfp.greaterThan:(Lorg/apache/commons/math3/dfp/Dfp;)Z (2, 1)
	57 ifeq (2, 1)
	58 11 (2, 1)
	60 aload_1 (2, 1)
	61 aload (2, 1)
	62 #4 (2, 1)
	63 invokevirtual (2, 1)
	64 org/apache/commons/math3/dfp/Dfp.subtract:(Lorg/apache/commons/math3/dfp/Dfp;)Lorg/apache/commons/math3/dfp/Dfp; (2, 1)
	66 astore (2, 1)
	67 #4 (2, 1)
	68 aload (2, 1)
	69 #4 (2, 1)
	70 aload_1 (2, 1)
	71 iconst_4 (2, 1)
	72 invokevirtual (2, 1)
	73 org/apache/commons/math3/dfp/Dfp.divide:(I)Lorg/apache/commons/math3/dfp/Dfp; (2, 1)
	75 invokevirtual (2, 1)
	76 org/apache/commons/math3/dfp/Dfp.lessThan:(Lorg/apache/commons/math3/dfp/Dfp;)Z (2, 1)
	78 ifeq (2, 1)
	79 16 (2, 1)
	81 aload (2, 1)
	82 #4 (2, 1)
	83 invokestatic (2, 1)
	84 org/apache/commons/math3/dfp/DfpMath.split:(Lorg/apache/commons/math3/dfp/Dfp;)[Lorg/apache/commons/math3/dfp/Dfp; (2, 1)
	86 invokestatic (2, 1)
	87 org/apache/commons/math3/dfp/DfpMath.sinInternal:([Lorg/apache/commons/math3/dfp/Dfp;)Lorg/apache/commons/math3/dfp/Dfp; (2, 1)
	89 astore (2, 1)
	90 #5 (2, 1)
	91 goto (2, 1)
	92 54 (2, 1)
	94 iconst_2 (3, 2)
	95 anewarray (3, 2)
	96 org/apache/commons/math3/dfp/Dfp (3, 2)
	98 astore (3, 2)
	99 #6 (3, 2)
	100 aload_0 (3, 2)
	101 invokevirtual (3, 2)
	102 org/apache/commons/math3/dfp/Dfp.getField:()Lorg/apache/commons/math3/dfp/DfpField; (3, 2)
	104 invokevirtual (3, 2)
	105 org/apache/commons/math3/dfp/DfpField.getPiSplit:()[Lorg/apache/commons/math3/dfp/Dfp; (3, 2)
	107 astore (3, 2)
	108 #7 (3, 2)
	109 aload (3, 2)
	110 #6 (3, 2)
	111 iconst_0 (3, 2)
	112 aload (3, 2)
	113 #7 (3, 2)
	114 iconst_0 (3, 2)
	115 aaload (3, 2)
	116 iconst_2 (3, 2)
	117 invokevirtual (3, 2)
	118 org/apache/commons/math3/dfp/Dfp.divide:(I)Lorg/apache/commons/math3/dfp/Dfp; (3, 2)
	120 aload (3, 2)
	121 #4 (3, 2)
	122 invokevirtual (3, 2)
	123 org/apache/commons/math3/dfp/Dfp.subtract:(Lorg/apache/commons/math3/dfp/Dfp;)Lorg/apache/commons/math3/dfp/Dfp; (3, 2)
	125 aastore (3, 2)
	126 aload (3, 2)
	127 #6 (3, 2)
	128 iconst_1 (3, 2)
	129 aload (3, 2)
	130 #7 (3, 2)
	131 iconst_1 (3, 2)
	132 aaload (3, 2)
	133 iconst_2 (3, 2)
	134 invokevirtual (3, 2)
	135 org/apache/commons/math3/dfp/Dfp.divide:(I)Lorg/apache/commons/math3/dfp/Dfp; (3, 2)
	137 aastore (3, 2)
	138 aload (3, 2)
	139 #6 (3, 2)
	140 invokestatic (3, 2)
	141 org/apache/commons/math3/dfp/DfpMath.cosInternal:([Lorg/apache/commons/math3/dfp/Dfp;)Lorg/apache/commons/math3/dfp/Dfp; (3, 2)
	143 astore (3, 2)
	144 #5 (3, 2)
	145 iload_3 (2, 1)
	146 ifeq (2, 1)
	147 10 (2, 1)
	149 aload (2, 1)
	150 #5 (2, 1)
	151 invokevirtual (2, 1)
	152 org/apache/commons/math3/dfp/Dfp.negate:()Lorg/apache/commons/math3/dfp/Dfp; (2, 1)
	154 astore (2, 1)
	155 #5 (2, 1)
	156 aload_0 (1, 1)
	157 aload (1, 1)
	158 #5 (1, 1)
	159 invokevirtual (1, 1)
	160 org/apache/commons/math3/dfp/Dfp.newInstance:(Lorg/apache/commons/math3/dfp/Dfp;)Lorg/apache/commons/math3/dfp/Dfp; (1, 1)
	162 areturn (0, 1)

Method: cos
	0 aload_0 (0, 0)
	1 invokevirtual (0, 0)
	2 org/apache/commons/math3/dfp/Dfp.getField:()Lorg/apache/commons/math3/dfp/DfpField; (0, 0)
	4 invokevirtual (0, 0)
	5 org/apache/commons/math3/dfp/DfpField.getPi:()Lorg/apache/commons/math3/dfp/Dfp; (0, 0)
	7 astore_1 (0, 0)
	8 aload_0 (0, 0)
	9 invokevirtual (0, 0)
	10 org/apache/commons/math3/dfp/Dfp.getField:()Lorg/apache/commons/math3/dfp/DfpField; (0, 0)
	12 invokevirtual (0, 0)
	13 org/apache/commons/math3/dfp/DfpField.getZero:()Lorg/apache/commons/math3/dfp/Dfp; (0, 0)
	15 astore_2 (0, 0)
	16 iconst_0 (0, 0)
	17 istore_3 (0, 0)
	18 aload_0 (0, 0)
	19 aload_1 (0, 0)
	20 iconst_2 (0, 0)
	21 invokevirtual (0, 0)
	22 org/apache/commons/math3/dfp/Dfp.multiply:(I)Lorg/apache/commons/math3/dfp/Dfp; (0, 0)
	24 invokevirtual (0, 0)
	25 org/apache/commons/math3/dfp/Dfp.remainder:(Lorg/apache/commons/math3/dfp/Dfp;)Lorg/apache/commons/math3/dfp/Dfp; (0, 0)
	27 astore (0, 0)
	28 #4 (0, 0)
	29 aload (2, 1)
	30 #4 (2, 1)
	31 aload_2 (2, 1)
	32 invokevirtual (2, 1)
	33 org/apache/commons/math3/dfp/Dfp.lessThan:(Lorg/apache/commons/math3/dfp/Dfp;)Z (2, 1)
	35 ifeq (2, 1)
	36 10 (2, 1)
	38 aload (2, 1)
	39 #4 (2, 1)
	40 invokevirtual (2, 1)
	41 org/apache/commons/math3/dfp/Dfp.negate:()Lorg/apache/commons/math3/dfp/Dfp; (2, 1)
	43 astore (2, 1)
	44 #4 (2, 1)
	45 aload (2, 1)
	46 #4 (2, 1)
	47 aload_1 (2, 1)
	48 iconst_2 (2, 1)
	49 invokevirtual (2, 1)
	50 org/apache/commons/math3/dfp/Dfp.divide:(I)Lorg/apache/commons/math3/dfp/Dfp; (2, 1)
	52 invokevirtual (2, 1)
	53 org/apache/commons/math3/dfp/Dfp.greaterThan:(Lorg/apache/commons/math3/dfp/Dfp;)Z (2, 1)
	55 ifeq (2, 1)
	56 13 (2, 1)
	58 aload_1 (2, 1)
	59 aload (2, 1)
	60 #4 (2, 1)
	61 invokevirtual (2, 1)
	62 org/apache/commons/math3/dfp/Dfp.subtract:(Lorg/apache/commons/math3/dfp/Dfp;)Lorg/apache/commons/math3/dfp/Dfp; (2, 1)
	64 astore (2, 1)
	65 #4 (2, 1)
	66 iconst_1 (2, 1)
	67 istore_3 (2, 1)
	68 aload (2, 1)
	69 #4 (2, 1)
	70 aload_1 (2, 1)
	71 iconst_4 (2, 1)
	72 invokevirtual (2, 1)
	73 org/apache/commons/math3/dfp/Dfp.divide:(I)Lorg/apache/commons/math3/dfp/Dfp; (2, 1)
	75 invokevirtual (2, 1)
	76 org/apache/commons/math3/dfp/Dfp.lessThan:(Lorg/apache/commons/math3/dfp/Dfp;)Z (2, 1)
	78 ifeq (2, 1)
	79 30 (2, 1)
	81 iconst_2 (2, 1)
	82 anewarray (2, 1)
	83 org/apache/commons/math3/dfp/Dfp (2, 1)
	85 astore (2, 1)
	86 #6 (2, 1)
	87 aload (2, 1)
	88 #6 (2, 1)
	89 iconst_0 (2, 1)
	90 aload (2, 1)
	91 #4 (2, 1)
	92 aastore (2, 1)
	93 aload (2, 1)
	94 #6 (2, 1)
	95 iconst_1 (2, 1)
	96 aload_2 (2, 1)
	97 aastore (2, 1)
	98 aload (2, 1)
	99 #6 (2, 1)
	100 invokestatic (2, 1)
	101 org/apache/commons/math3/dfp/DfpMath.cosInternal:([Lorg/apache/commons/math3/dfp/Dfp;)Lorg/apache/commons/math3/dfp/Dfp; (2, 1)
	103 astore (2, 1)
	104 #5 (2, 1)
	105 goto (3, 2)
	106 54 (3, 2)
	108 iconst_2 (3, 2)
	109 anewarray (3, 2)
	110 org/apache/commons/math3/dfp/Dfp (3, 2)
	112 astore (3, 2)
	113 #6 (3, 2)
	114 aload_0 (3, 2)
	115 invokevirtual (3, 2)
	116 org/apache/commons/math3/dfp/Dfp.getField:()Lorg/apache/commons/math3/dfp/DfpField; (3, 2)
	118 invokevirtual (3, 2)
	119 org/apache/commons/math3/dfp/DfpField.getPiSplit:()[Lorg/apache/commons/math3/dfp/Dfp; (3, 2)
	121 astore (3, 2)
	122 #7 (3, 2)
	123 aload (3, 2)
	124 #6 (3, 2)
	125 iconst_0 (3, 2)
	126 aload (3, 2)
	127 #7 (3, 2)
	128 iconst_0 (3, 2)
	129 aaload (3, 2)
	130 iconst_2 (3, 2)
	131 invokevirtual (3, 2)
	132 org/apache/commons/math3/dfp/Dfp.divide:(I)Lorg/apache/commons/math3/dfp/Dfp; (3, 2)
	134 aload (3, 2)
	135 #4 (3, 2)
	136 invokevirtual (3, 2)
	137 org/apache/commons/math3/dfp/Dfp.subtract:(Lorg/apache/commons/math3/dfp/Dfp;)Lorg/apache/commons/math3/dfp/Dfp; (3, 2)
	139 aastore (3, 2)
	140 aload (3, 2)
	141 #6 (3, 2)
	142 iconst_1 (3, 2)
	143 aload (3, 2)
	144 #7 (3, 2)
	145 iconst_1 (3, 2)
	146 aaload (3, 2)
	147 iconst_2 (3, 2)
	148 invokevirtual (3, 2)
	149 org/apache/commons/math3/dfp/Dfp.divide:(I)Lorg/apache/commons/math3/dfp/Dfp; (3, 2)
	151 aastore (3, 2)
	152 aload (3, 2)
	153 #6 (3, 2)
	154 invokestatic (3, 2)
	155 org/apache/commons/math3/dfp/DfpMath.sinInternal:([Lorg/apache/commons/math3/dfp/Dfp;)Lorg/apache/commons/math3/dfp/Dfp; (3, 2)
	157 astore (3, 2)
	158 #5 (3, 2)
	159 iload_3 (2, 1)
	160 ifeq (2, 1)
	161 10 (2, 1)
	163 aload (2, 1)
	164 #5 (2, 1)
	165 invokevirtual (2, 1)
	166 org/apache/commons/math3/dfp/Dfp.negate:()Lorg/apache/commons/math3/dfp/Dfp; (2, 1)
	168 astore (2, 1)
	169 #5 (2, 1)
	170 aload_0 (1, 1)
	171 aload (1, 1)
	172 #5 (1, 1)
	173 invokevirtual (1, 1)
	174 org/apache/commons/math3/dfp/Dfp.newInstance:(Lorg/apache/commons/math3/dfp/Dfp;)Lorg/apache/commons/math3/dfp/Dfp; (1, 1)
	176 areturn (0, 1)

Method: tan
	0 aload_0 (0, 0)
	1 invokestatic (0, 0)
	2 org/apache/commons/math3/dfp/DfpMath.sin:(Lorg/apache/commons/math3/dfp/Dfp;)Lorg/apache/commons/math3/dfp/Dfp; (0, 0)
	4 aload_0 (0, 0)
	5 invokestatic (0, 0)
	6 org/apache/commons/math3/dfp/DfpMath.cos:(Lorg/apache/commons/math3/dfp/Dfp;)Lorg/apache/commons/math3/dfp/Dfp; (0, 0)
	8 invokevirtual (0, 0)
	9 org/apache/commons/math3/dfp/Dfp.divide:(Lorg/apache/commons/math3/dfp/Dfp;)Lorg/apache/commons/math3/dfp/Dfp; (0, 0)
	11 areturn (0, 0)

Method: atanInternal
	0 new (0, 0)
	1 org/apache/commons/math3/dfp/Dfp (0, 0)
	3 dup (0, 0)
	4 aload_0 (0, 0)
	5 invokespecial (0, 0)
	6 org/apache/commons/math3/dfp/Dfp.<init>:(Lorg/apache/commons/math3/dfp/Dfp;)V (0, 0)
	8 astore_1 (0, 0)
	9 new (0, 0)
	10 org/apache/commons/math3/dfp/Dfp (0, 0)
	12 dup (0, 0)
	13 aload_1 (0, 0)
	14 invokespecial (0, 0)
	15 org/apache/commons/math3/dfp/Dfp.<init>:(Lorg/apache/commons/math3/dfp/Dfp;)V (0, 0)
	17 astore_2 (0, 0)
	18 new (0, 0)
	19 org/apache/commons/math3/dfp/Dfp (0, 0)
	21 dup (0, 0)
	22 aload_1 (0, 0)
	23 invokespecial (0, 0)
	24 org/apache/commons/math3/dfp/Dfp.<init>:(Lorg/apache/commons/math3/dfp/Dfp;)V (0, 0)
	26 astore_3 (0, 0)
	27 iconst_3 (1, 4)
	28 istore (1, 4)
	29 #4 (1, 4)
	30 iload (1, 4)
	31 #4 (1, 4)
	32 bipush (1, 4)
	33 90 (1, 4)
	34 if_icmpge (1, 4)
	35 57 (1, 4)
	37 aload_2 (1, 4)
	38 aload_0 (1, 4)
	39 invokevirtual (1, 4)
	40 org/apache/commons/math3/dfp/Dfp.multiply:(Lorg/apache/commons/math3/dfp/Dfp;)Lorg/apache/commons/math3/dfp/Dfp; (1, 4)
	42 astore_2 (1, 4)
	43 aload_2 (1, 4)
	44 aload_0 (1, 4)
	45 invokevirtual (1, 4)
	46 org/apache/commons/math3/dfp/Dfp.multiply:(Lorg/apache/commons/math3/dfp/Dfp;)Lorg/apache/commons/math3/dfp/Dfp; (1, 4)
	48 astore_2 (1, 4)
	49 aload_2 (1, 4)
	50 invokevirtual (1, 4)
	51 org/apache/commons/math3/dfp/Dfp.negate:()Lorg/apache/commons/math3/dfp/Dfp; (1, 4)
	53 astore_2 (1, 4)
	54 aload_1 (1, 4)
	55 aload_2 (1, 4)
	56 iload (1, 4)
	57 #4 (1, 4)
	58 invokevirtual (1, 4)
	59 org/apache/commons/math3/dfp/Dfp.divide:(I)Lorg/apache/commons/math3/dfp/Dfp; (1, 4)
	61 invokevirtual (1, 4)
	62 org/apache/commons/math3/dfp/Dfp.add:(Lorg/apache/commons/math3/dfp/Dfp;)Lorg/apache/commons/math3/dfp/Dfp; (1, 4)
	64 astore_1 (1, 4)
	65 aload_1 (2, 1)
	66 aload_3 (2, 1)
	67 invokevirtual (2, 1)
	68 org/apache/commons/math3/dfp/Dfp.equals:(Ljava/lang/Object;)Z (2, 1)
	70 ifeq (2, 1)
	71 6 (2, 1)
	73 goto (2, 1)
	74 18 (2, 1)
	76 new (1, 4)
	77 org/apache/commons/math3/dfp/Dfp (1, 4)
	79 dup (1, 4)
	80 aload_1 (1, 4)
	81 invokespecial (1, 4)
	82 org/apache/commons/math3/dfp/Dfp.<init>:(Lorg/apache/commons/math3/dfp/Dfp;)V (1, 4)
	84 astore_3 (1, 4)
	85 iinc (1, 4)
	86 #4 (1, 4)
	87 -89 (1, 4)
	88 goto (1, 4)
	89 -58 (1, 4)
	91 aload_1 (0, 0)
	92 areturn (0, 0)

Method: atan
	0 aload_0 (0, 0)
	1 invokevirtual (0, 0)
	2 org/apache/commons/math3/dfp/Dfp.getField:()Lorg/apache/commons/math3/dfp/DfpField; (0, 0)
	4 invokevirtual (0, 0)
	5 org/apache/commons/math3/dfp/DfpField.getZero:()Lorg/apache/commons/math3/dfp/Dfp; (0, 0)
	7 astore_1 (0, 0)
	8 aload_0 (0, 0)
	9 invokevirtual (0, 0)
	10 org/apache/commons/math3/dfp/Dfp.getField:()Lorg/apache/commons/math3/dfp/DfpField; (0, 0)
	12 invokevirtual (0, 0)
	13 org/apache/commons/math3/dfp/DfpField.getOne:()Lorg/apache/commons/math3/dfp/Dfp; (0, 0)
	15 astore_2 (0, 0)
	16 aload_0 (0, 0)
	17 invokevirtual (0, 0)
	18 org/apache/commons/math3/dfp/Dfp.getField:()Lorg/apache/commons/math3/dfp/DfpField; (0, 0)
	20 invokevirtual (0, 0)
	21 org/apache/commons/math3/dfp/DfpField.getSqr2Split:()[Lorg/apache/commons/math3/dfp/Dfp; (0, 0)
	23 astore_3 (0, 0)
	24 aload_0 (0, 0)
	25 invokevirtual (0, 0)
	26 org/apache/commons/math3/dfp/Dfp.getField:()Lorg/apache/commons/math3/dfp/DfpField; (0, 0)
	28 invokevirtual (0, 0)
	29 org/apache/commons/math3/dfp/DfpField.getPiSplit:()[Lorg/apache/commons/math3/dfp/Dfp; (0, 0)
	31 astore (0, 0)
	32 #4 (0, 0)
	33 iconst_0 (0, 0)
	34 istore (0, 0)
	35 #5 (0, 0)
	36 iconst_0 (0, 0)
	37 istore (0, 0)
	38 #6 (0, 0)
	39 iconst_0 (0, 0)
	40 istore (0, 0)
	41 #7 (0, 0)
	42 aload_3 (0, 0)
	43 iconst_0 (0, 0)
	44 aaload (0, 0)
	45 aload_2 (0, 0)
	46 invokevirtual (0, 0)
	47 org/apache/commons/math3/dfp/Dfp.subtract:(Lorg/apache/commons/math3/dfp/Dfp;)Lorg/apache/commons/math3/dfp/Dfp; (0, 0)
	49 aload_3 (0, 0)
	50 iconst_1 (0, 0)
	51 aaload (0, 0)
	52 invokevirtual (0, 0)
	53 org/apache/commons/math3/dfp/Dfp.add:(Lorg/apache/commons/math3/dfp/Dfp;)Lorg/apache/commons/math3/dfp/Dfp; (0, 0)
	55 astore (0, 0)
	56 #8 (0, 0)
	57 new (0, 0)
	58 org/apache/commons/math3/dfp/Dfp (0, 0)
	60 dup (0, 0)
	61 aload_0 (0, 0)
	62 invokespecial (0, 0)
	63 org/apache/commons/math3/dfp/Dfp.<init>:(Lorg/apache/commons/math3/dfp/Dfp;)V (0, 0)
	65 astore (0, 0)
	66 #9 (0, 0)
	67 aload (1, 1)
	68 #9 (1, 1)
	69 aload_1 (1, 1)
	70 invokevirtual (1, 1)
	71 org/apache/commons/math3/dfp/Dfp.lessThan:(Lorg/apache/commons/math3/dfp/Dfp;)Z (1, 1)
	73 ifeq (1, 1)
	74 13 (1, 1)
	76 iconst_1 (1, 1)
	77 istore (1, 1)
	78 #6 (1, 1)
	79 aload (1, 1)
	80 #9 (1, 1)
	81 invokevirtual (1, 1)
	82 org/apache/commons/math3/dfp/Dfp.negate:()Lorg/apache/commons/math3/dfp/Dfp; (1, 1)
	84 astore (1, 1)
	85 #9 (1, 1)
	86 aload (1, 1)
	87 #9 (1, 1)
	88 aload_2 (1, 1)
	89 invokevirtual (1, 1)
	90 org/apache/commons/math3/dfp/Dfp.greaterThan:(Lorg/apache/commons/math3/dfp/Dfp;)Z (1, 1)
	92 ifeq (1, 1)
	93 14 (1, 1)
	95 iconst_1 (1, 1)
	96 istore (1, 1)
	97 #5 (1, 1)
	98 aload_2 (1, 1)
	99 aload (1, 1)
	100 #9 (1, 1)
	101 invokevirtual (1, 1)
	102 org/apache/commons/math3/dfp/Dfp.divide:(Lorg/apache/commons/math3/dfp/Dfp;)Lorg/apache/commons/math3/dfp/Dfp; (1, 1)
	104 astore (1, 1)
	105 #9 (1, 1)
	106 aload (1, 1)
	107 #9 (1, 1)
	108 aload (1, 1)
	109 #8 (1, 1)
	110 invokevirtual (1, 1)
	111 org/apache/commons/math3/dfp/Dfp.greaterThan:(Lorg/apache/commons/math3/dfp/Dfp;)Z (1, 1)
	113 ifeq (1, 1)
	114 110 (1, 1)
	116 iconst_2 (1, 1)
	117 anewarray (1, 1)
	118 org/apache/commons/math3/dfp/Dfp (1, 1)
	120 astore (1, 1)
	121 #10 (1, 1)
	122 iconst_1 (1, 1)
	123 istore (1, 1)
	124 #7 (1, 1)
	125 aload (1, 1)
	126 #10 (1, 1)
	127 iconst_0 (1, 1)
	128 aload_3 (1, 1)
	129 iconst_0 (1, 1)
	130 aaload (1, 1)
	131 aload_2 (1, 1)
	132 invokevirtual (1, 1)
	133 org/apache/commons/math3/dfp/Dfp.subtract:(Lorg/apache/commons/math3/dfp/Dfp;)Lorg/apache/commons/math3/dfp/Dfp; (1, 1)
	135 aastore (1, 1)
	136 aload (1, 1)
	137 #10 (1, 1)
	138 iconst_1 (1, 1)
	139 aload_3 (1, 1)
	140 iconst_1 (1, 1)
	141 aaload (1, 1)
	142 aastore (1, 1)
	143 aload (1, 1)
	144 #9 (1, 1)
	145 invokestatic (1, 1)
	146 org/apache/commons/math3/dfp/DfpMath.split:(Lorg/apache/commons/math3/dfp/Dfp;)[Lorg/apache/commons/math3/dfp/Dfp; (1, 1)
	148 astore (1, 1)
	149 #11 (1, 1)
	150 aload (1, 1)
	151 #11 (1, 1)
	152 aload (1, 1)
	153 #10 (1, 1)
	154 invokestatic (1, 1)
	155 org/apache/commons/math3/dfp/DfpMath.splitMult:([Lorg/apache/commons/math3/dfp/Dfp;[Lorg/apache/commons/math3/dfp/Dfp;)[Lorg/apache/commons/math3/dfp/Dfp; (1, 1)
	157 astore (1, 1)
	158 #12 (1, 1)
	159 aload (1, 1)
	160 #12 (1, 1)
	161 iconst_0 (1, 1)
	162 aload (1, 1)
	163 #12 (1, 1)
	164 iconst_0 (1, 1)
	165 aaload (1, 1)
	166 aload_2 (1, 1)
	167 invokevirtual (1, 1)
	168 org/apache/commons/math3/dfp/Dfp.add:(Lorg/apache/commons/math3/dfp/Dfp;)Lorg/apache/commons/math3/dfp/Dfp; (1, 1)
	170 aastore (1, 1)
	171 aload (1, 1)
	172 #11 (1, 1)
	173 iconst_0 (1, 1)
	174 aload (1, 1)
	175 #11 (1, 1)
	176 iconst_0 (1, 1)
	177 aaload (1, 1)
	178 aload (1, 1)
	179 #10 (1, 1)
	180 iconst_0 (1, 1)
	181 aaload (1, 1)
	182 invokevirtual (1, 1)
	183 org/apache/commons/math3/dfp/Dfp.subtract:(Lorg/apache/commons/math3/dfp/Dfp;)Lorg/apache/commons/math3/dfp/Dfp; (1, 1)
	185 aastore (1, 1)
	186 aload (1, 1)
	187 #11 (1, 1)
	188 iconst_1 (1, 1)
	189 aload (1, 1)
	190 #11 (1, 1)
	191 iconst_1 (1, 1)
	192 aaload (1, 1)
	193 aload (1, 1)
	194 #10 (1, 1)
	195 iconst_1 (1, 1)
	196 aaload (1, 1)
	197 invokevirtual (1, 1)
	198 org/apache/commons/math3/dfp/Dfp.subtract:(Lorg/apache/commons/math3/dfp/Dfp;)Lorg/apache/commons/math3/dfp/Dfp; (1, 1)
	200 aastore (1, 1)
	201 aload (1, 1)
	202 #11 (1, 1)
	203 aload (1, 1)
	204 #12 (1, 1)
	205 invokestatic (1, 1)
	206 org/apache/commons/math3/dfp/DfpMath.splitDiv:([Lorg/apache/commons/math3/dfp/Dfp;[Lorg/apache/commons/math3/dfp/Dfp;)[Lorg/apache/commons/math3/dfp/Dfp; (1, 1)
	208 astore (1, 1)
	209 #11 (1, 1)
	210 aload (1, 1)
	211 #11 (1, 1)
	212 iconst_0 (1, 1)
	213 aaload (1, 1)
	214 aload (1, 1)
	215 #11 (1, 1)
	216 iconst_1 (1, 1)
	217 aaload (1, 1)
	218 invokevirtual (1, 1)
	219 org/apache/commons/math3/dfp/Dfp.add:(Lorg/apache/commons/math3/dfp/Dfp;)Lorg/apache/commons/math3/dfp/Dfp; (1, 1)
	221 astore (1, 1)
	222 #9 (1, 1)
	223 aload (0, 0)
	224 #9 (0, 0)
	225 invokestatic (0, 0)
	226 org/apache/commons/math3/dfp/DfpMath.atanInternal:(Lorg/apache/commons/math3/dfp/Dfp;)Lorg/apache/commons/math3/dfp/Dfp; (0, 0)
	228 astore (0, 0)
	229 #10 (0, 0)
	230 iload (1, 1)
	231 #7 (1, 1)
	232 ifeq (1, 1)
	233 31 (1, 1)
	235 aload (1, 1)
	236 #10 (1, 1)
	237 aload (1, 1)
	238 #4 (1, 1)
	239 iconst_0 (1, 1)
	240 aaload (1, 1)
	241 bipush (1, 1)
	242 8 (1, 1)
	243 invokevirtual (1, 1)
	244 org/apache/commons/math3/dfp/Dfp.divide:(I)Lorg/apache/commons/math3/dfp/Dfp; (1, 1)
	246 invokevirtual (1, 1)
	247 org/apache/commons/math3/dfp/Dfp.add:(Lorg/apache/commons/math3/dfp/Dfp;)Lorg/apache/commons/math3/dfp/Dfp; (1, 1)
	249 aload (1, 1)
	250 #4 (1, 1)
	251 iconst_1 (1, 1)
	252 aaload (1, 1)
	253 bipush (1, 1)
	254 8 (1, 1)
	255 invokevirtual (1, 1)
	256 org/apache/commons/math3/dfp/Dfp.divide:(I)Lorg/apache/commons/math3/dfp/Dfp; (1, 1)
	258 invokevirtual (1, 1)
	259 org/apache/commons/math3/dfp/Dfp.add:(Lorg/apache/commons/math3/dfp/Dfp;)Lorg/apache/commons/math3/dfp/Dfp; (1, 1)
	261 astore (1, 1)
	262 #10 (1, 1)
	263 iload (1, 1)
	264 #5 (1, 1)
	265 ifeq (1, 1)
	266 29 (1, 1)
	268 aload (1, 1)
	269 #4 (1, 1)
	270 iconst_0 (1, 1)
	271 aaload (1, 1)
	272 iconst_2 (1, 1)
	273 invokevirtual (1, 1)
	274 org/apache/commons/math3/dfp/Dfp.divide:(I)Lorg/apache/commons/math3/dfp/Dfp; (1, 1)
	276 aload (1, 1)
	277 #10 (1, 1)
	278 invokevirtual (1, 1)
	279 org/apache/commons/math3/dfp/Dfp.subtract:(Lorg/apache/commons/math3/dfp/Dfp;)Lorg/apache/commons/math3/dfp/Dfp; (1, 1)
	281 aload (1, 1)
	282 #4 (1, 1)
	283 iconst_1 (1, 1)
	284 aaload (1, 1)
	285 iconst_2 (1, 1)
	286 invokevirtual (1, 1)
	287 org/apache/commons/math3/dfp/Dfp.divide:(I)Lorg/apache/commons/math3/dfp/Dfp; (1, 1)
	289 invokevirtual (1, 1)
	290 org/apache/commons/math3/dfp/Dfp.add:(Lorg/apache/commons/math3/dfp/Dfp;)Lorg/apache/commons/math3/dfp/Dfp; (1, 1)
	292 astore (1, 1)
	293 #10 (1, 1)
	294 iload (1, 1)
	295 #6 (1, 1)
	296 ifeq (1, 1)
	297 10 (1, 1)
	299 aload (1, 1)
	300 #10 (1, 1)
	301 invokevirtual (1, 1)
	302 org/apache/commons/math3/dfp/Dfp.negate:()Lorg/apache/commons/math3/dfp/Dfp; (1, 1)
	304 astore (1, 1)
	305 #10 (1, 1)
	306 aload_0 (0, 0)
	307 aload (0, 0)
	308 #10 (0, 0)
	309 invokevirtual (0, 0)
	310 org/apache/commons/math3/dfp/Dfp.newInstance:(Lorg/apache/commons/math3/dfp/Dfp;)Lorg/apache/commons/math3/dfp/Dfp; (0, 0)
	312 areturn (0, 0)

Method: asin
	0 aload_0 (0, 0)
	1 aload_0 (0, 0)
	2 invokevirtual (0, 0)
	3 org/apache/commons/math3/dfp/Dfp.getOne:()Lorg/apache/commons/math3/dfp/Dfp; (0, 0)
	5 aload_0 (0, 0)
	6 aload_0 (0, 0)
	7 invokevirtual (0, 0)
	8 org/apache/commons/math3/dfp/Dfp.multiply:(Lorg/apache/commons/math3/dfp/Dfp;)Lorg/apache/commons/math3/dfp/Dfp; (0, 0)
	10 invokevirtual (0, 0)
	11 org/apache/commons/math3/dfp/Dfp.subtract:(Lorg/apache/commons/math3/dfp/Dfp;)Lorg/apache/commons/math3/dfp/Dfp; (0, 0)
	13 invokevirtual (0, 0)
	14 org/apache/commons/math3/dfp/Dfp.sqrt:()Lorg/apache/commons/math3/dfp/Dfp; (0, 0)
	16 invokevirtual (0, 0)
	17 org/apache/commons/math3/dfp/Dfp.divide:(Lorg/apache/commons/math3/dfp/Dfp;)Lorg/apache/commons/math3/dfp/Dfp; (0, 0)
	19 invokestatic (0, 0)
	20 org/apache/commons/math3/dfp/DfpMath.atan:(Lorg/apache/commons/math3/dfp/Dfp;)Lorg/apache/commons/math3/dfp/Dfp; (0, 0)
	22 areturn (0, 0)

Method: acos
	0 iconst_0 (0, 0)
	1 istore_2 (0, 0)
	2 aload_0 (1, 1)
	3 aload_0 (1, 1)
	4 invokevirtual (1, 1)
	5 org/apache/commons/math3/dfp/Dfp.getZero:()Lorg/apache/commons/math3/dfp/Dfp; (1, 1)
	7 invokevirtual (1, 1)
	8 org/apache/commons/math3/dfp/Dfp.lessThan:(Lorg/apache/commons/math3/dfp/Dfp;)Z (1, 1)
	10 ifeq (1, 1)
	11 5 (1, 1)
	13 iconst_1 (1, 1)
	14 istore_2 (1, 1)
	15 aload_0 (0, 0)
	16 aload_0 (0, 0)
	17 invokevirtual (0, 0)
	18 org/apache/commons/math3/dfp/Dfp.getOne:()Lorg/apache/commons/math3/dfp/Dfp; (0, 0)
	20 invokestatic (0, 0)
	21 org/apache/commons/math3/dfp/Dfp.copysign:(Lorg/apache/commons/math3/dfp/Dfp;Lorg/apache/commons/math3/dfp/Dfp;)Lorg/apache/commons/math3/dfp/Dfp; (0, 0)
	23 astore_0 (0, 0)
	24 aload_0 (0, 0)
	25 invokevirtual (0, 0)
	26 org/apache/commons/math3/dfp/Dfp.getOne:()Lorg/apache/commons/math3/dfp/Dfp; (0, 0)
	28 aload_0 (0, 0)
	29 aload_0 (0, 0)
	30 invokevirtual (0, 0)
	31 org/apache/commons/math3/dfp/Dfp.multiply:(Lorg/apache/commons/math3/dfp/Dfp;)Lorg/apache/commons/math3/dfp/Dfp; (0, 0)
	33 invokevirtual (0, 0)
	34 org/apache/commons/math3/dfp/Dfp.subtract:(Lorg/apache/commons/math3/dfp/Dfp;)Lorg/apache/commons/math3/dfp/Dfp; (0, 0)
	36 invokevirtual (0, 0)
	37 org/apache/commons/math3/dfp/Dfp.sqrt:()Lorg/apache/commons/math3/dfp/Dfp; (0, 0)
	39 aload_0 (0, 0)
	40 invokevirtual (0, 0)
	41 org/apache/commons/math3/dfp/Dfp.divide:(Lorg/apache/commons/math3/dfp/Dfp;)Lorg/apache/commons/math3/dfp/Dfp; (0, 0)
	43 invokestatic (0, 0)
	44 org/apache/commons/math3/dfp/DfpMath.atan:(Lorg/apache/commons/math3/dfp/Dfp;)Lorg/apache/commons/math3/dfp/Dfp; (0, 0)
	46 astore_1 (0, 0)
	47 iload_2 (1, 1)
	48 ifeq (1, 1)
	49 15 (1, 1)
	51 aload_0 (1, 1)
	52 invokevirtual (1, 1)
	53 org/apache/commons/math3/dfp/Dfp.getField:()Lorg/apache/commons/math3/dfp/DfpField; (1, 1)
	55 invokevirtual (1, 1)
	56 org/apache/commons/math3/dfp/DfpField.getPi:()Lorg/apache/commons/math3/dfp/Dfp; (1, 1)
	58 aload_1 (1, 1)
	59 invokevirtual (1, 1)
	60 org/apache/commons/math3/dfp/Dfp.subtract:(Lorg/apache/commons/math3/dfp/Dfp;)Lorg/apache/commons/math3/dfp/Dfp; (1, 1)
	62 astore_1 (1, 1)
	63 aload_0 (0, 0)
	64 aload_1 (0, 0)
	65 invokevirtual (0, 0)
	66 org/apache/commons/math3/dfp/Dfp.newInstance:(Lorg/apache/commons/math3/dfp/Dfp;)Lorg/apache/commons/math3/dfp/Dfp; (0, 0)
	68 areturn (0, 0)

