Method: fit
	0 aload_0 (0, 0)
	1 invokevirtual (0, 0)
	2 org/apache/commons/math3/fitting/AbstractCurveFitter.getOptimizer:()Lorg/apache/commons/math3/fitting/leastsquares/LeastSquaresOptimizer; (0, 0)
	4 aload_0 (0, 0)
	5 aload_1 (0, 0)
	6 invokevirtual (0, 0)
	7 org/apache/commons/math3/fitting/AbstractCurveFitter.getProblem:(Ljava/util/Collection;)Lorg/apache/commons/math3/fitting/leastsquares/LeastSquaresProblem; (0, 0)
	9 invokeinterface (0, 0)
	10 org/apache/commons/math3/fitting/leastsquares/LeastSquaresOptimizer.org/apache/commons/math3/fitting/leastsquares/LeastSquaresOptimizer$Optimum (0, 0)
	12 0 (0, 0)
	14 invokeinterface (0, 0)
	15 org/apache/commons/math3/fitting/leastsquares/LeastSquaresOptimizer$Optimum.org/apache/commons/math3/linear/RealVector (0, 0)
	17 0 (0, 0)
	19 invokevirtual (0, 0)
	20 org/apache/commons/math3/linear/RealVector.toArray:()[D (0, 0)
	22 areturn (0, 0)

Method: getOptimizer
	0 new (0, 0)
	1 org/apache/commons/math3/fitting/leastsquares/LevenbergMarquardtOptimizer (0, 0)
	3 dup (0, 0)
	4 invokespecial (0, 0)
	5 org/apache/commons/math3/fitting/leastsquares/LevenbergMarquardtOptimizer.<init>:()V (0, 0)
	7 areturn (0, 0)

