Method: value
	0 aload_0 (0, 0)
	1 getfield (0, 0)
	2 org/apache/commons/math3/fitting/AbstractCurveFitter$TheoreticalValuesFunction$2.this$0:Lorg/apache/commons/math3/fitting/AbstractCurveFitter$TheoreticalValuesFunction; (0, 0)
	4 invokestatic (0, 0)
	5 org/apache/commons/math3/fitting/AbstractCurveFitter$TheoreticalValuesFunction.access$000:(Lorg/apache/commons/math3/fitting/AbstractCurveFitter$TheoreticalValuesFunction;)[D (0, 0)
	7 arraylength (0, 0)
	8 istore_2 (0, 0)
	9 iload_2 (0, 0)
	10 anewarray (0, 0)
	11 [D (0, 0)
	13 astore_3 (0, 0)
	14 iconst_0 (1, 4)
	15 istore (1, 4)
	16 #4 (1, 4)
	17 iload (1, 4)
	18 #4 (1, 4)
	19 iload_2 (1, 4)
	20 if_icmpge (1, 4)
	21 36 (1, 4)
	23 aload_3 (1, 4)
	24 iload (1, 4)
	25 #4 (1, 4)
	26 aload_0 (1, 4)
	27 getfield (1, 4)
	28 org/apache/commons/math3/fitting/AbstractCurveFitter$TheoreticalValuesFunction$2.this$0:Lorg/apache/commons/math3/fitting/AbstractCurveFitter$TheoreticalValuesFunction; (1, 4)
	30 invokestatic (1, 4)
	31 org/apache/commons/math3/fitting/AbstractCurveFitter$TheoreticalValuesFunction.access$100:(Lorg/apache/commons/math3/fitting/AbstractCurveFitter$TheoreticalValuesFunction;)Lorg/apache/commons/math3/analysis/ParametricUnivariateFunction; (1, 4)
	33 aload_0 (1, 4)
	34 getfield (1, 4)
	35 org/apache/commons/math3/fitting/AbstractCurveFitter$TheoreticalValuesFunction$2.this$0:Lorg/apache/commons/math3/fitting/AbstractCurveFitter$TheoreticalValuesFunction; (1, 4)
	37 invokestatic (1, 4)
	38 org/apache/commons/math3/fitting/AbstractCurveFitter$TheoreticalValuesFunction.access$000:(Lorg/apache/commons/math3/fitting/AbstractCurveFitter$TheoreticalValuesFunction;)[D (1, 4)
	40 iload (1, 4)
	41 #4 (1, 4)
	42 daload (1, 4)
	43 aload_1 (1, 4)
	44 invokeinterface (1, 4)
	45 org/apache/commons/math3/analysis/ParametricUnivariateFunction.org/apache/commons/math3/fitting/AbstractCurveFitter$TheoreticalValuesFunction$2 (1, 4)
	47 0 (1, 4)
	49 aastore (1, 4)
	50 iinc (1, 4)
	51 #4 (1, 4)
	52 -89 (1, 4)
	53 goto (1, 4)
	54 -36 (1, 4)
	56 aload_3 (0, 0)
	57 areturn (0, 0)

