Method: value
	0 aload_0 (0, 0)
	1 getfield (0, 0)
	4 getfield (0, 0)
	7 invokestatic (0, 0)
	10 invokeinterface (0, 0)
	15 anewarray (0, 0)
	18 astore_2 (0, 0)
	19 iconst_0 (0, 0)
	20 istore_3 (0, 0)
	21 aload_0 (1, 4)
	22 getfield (1, 4)
	25 getfield (1, 4)
	28 invokestatic (1, 4)
	31 invokeinterface (1, 4)
	36 astore (1, 4)
	38 aload (1, 4)
	40 invokeinterface (1, 4)
	45 ifeq (1, 4)
	48 aload (1, 4)
	50 invokeinterface (1, 4)
	55 checkcast (1, 4)
	58 astore (1, 4)
	60 aload_2 (1, 4)
	61 iload_3 (1, 4)
	62 iinc (1, 4)
	65 aload_0 (1, 4)
	66 getfield (1, 4)
	69 invokestatic (1, 4)
	72 aload (1, 4)
	74 invokevirtual (1, 4)
	77 aload_1 (1, 4)
	78 invokeinterface (1, 4)
	83 aastore (1, 4)
	84 goto (0, 0)
	87 aload_2 (0, 0)
	88 areturn (0, 0)

