Method: <init>
	0 aload_0 (0, 0)
	1 invokespecial (0, 0)
	4 aload_0 (0, 0)
	5 aload_1 (0, 0)
	6 putfield (0, 0)
	9 aload_0 (0, 0)
	10 new (0, 0)
	13 dup (0, 0)
	14 invokespecial (0, 0)
	17 putfield (0, 0)
	20 return (0, 0)

Method: addObservedPoint
	0 aload_0 (0, 0)
	1 getfield (0, 0)
	4 aload_1 (0, 0)
	5 invokeinterface (0, 0)
	10 pop (0, 0)
	11 return (0, 0)

Method: getObservations
	0 aload_0 (0, 0)
	1 getfield (0, 0)
	4 aload_0 (0, 0)
	5 getfield (0, 0)
	8 invokeinterface (0, 0)
	13 anewarray (0, 0)
	16 invokeinterface (0, 0)
	21 checkcast (0, 0)
	24 areturn (0, 0)

Method: clearObservations
	0 aload_0 (0, 0)
	1 getfield (0, 0)
	4 invokeinterface (0, 0)
	9 return (0, 0)

Method: fit
	0 aload_0 (0, 0)
	1 getfield (0, 0)
	4 invokeinterface (0, 0)
	9 newarray (0, 0)
	11 astore (0, 0)
	13 aload_0 (0, 0)
	14 getfield (0, 0)
	17 invokeinterface (0, 0)
	22 newarray (0, 0)
	24 astore (0, 0)
	26 iconst_0 (0, 0)
	27 istore (0, 0)
	29 aload_0 (1, 4)
	30 getfield (1, 4)
	33 invokeinterface (1, 4)
	38 astore (1, 4)
	40 aload (1, 4)
	42 invokeinterface (1, 4)
	47 ifeq (1, 4)
	50 aload (1, 4)
	52 invokeinterface (1, 4)
	57 checkcast (1, 4)
	60 astore (1, 4)
	62 aload (1, 4)
	64 iload (1, 4)
	66 aload (1, 4)
	68 invokevirtual (1, 4)
	71 dastore (1, 4)
	72 aload (1, 4)
	74 iload (1, 4)
	76 aload (1, 4)
	78 invokevirtual (1, 4)
	81 dastore (1, 4)
	82 iinc (1, 4)
	85 goto (0, 0)
	88 new (0, 0)
	91 dup (0, 0)
	92 aload_0 (0, 0)
	93 aload_2 (0, 0)
	94 invokespecial (0, 0)
	97 astore (0, 0)
	99 aload_0 (0, 4)
	100 getfield (0, 4)
	103 bipush (0, 4)
	105 anewarray (0, 4)
	108 dup (0, 4)
	109 iconst_0 (0, 4)
	110 new (0, 4)
	113 dup (0, 4)
	114 iload_1 (0, 4)
	115 invokespecial (0, 4)
	118 aastore (0, 4)
	119 dup (0, 4)
	120 iconst_1 (0, 4)
	121 aload (0, 4)
	123 invokevirtual (0, 4)
	126 aastore (0, 4)
	127 dup (0, 4)
	128 iconst_2 (0, 4)
	129 aload (0, 4)
	131 invokevirtual (0, 4)
	134 aastore (0, 4)
	135 dup (0, 4)
	136 iconst_3 (0, 4)
	137 new (0, 4)
	140 dup (0, 4)
	141 aload (0, 4)
	143 invokespecial (0, 4)
	146 aastore (0, 4)
	147 dup (0, 4)
	148 iconst_4 (0, 4)
	149 new (0, 4)
	152 dup (0, 4)
	153 aload (0, 4)
	155 invokespecial (0, 4)
	158 aastore (0, 4)
	159 dup (0, 4)
	160 iconst_5 (0, 4)
	161 new (0, 4)
	164 dup (0, 4)
	165 aload_3 (0, 4)
	166 invokespecial (0, 4)
	169 aastore (0, 4)
	170 invokevirtual (0, 4)
	173 astore (0, 4)
	175 aload (0, 4)
	177 invokevirtual (0, 4)
	180 areturn (0, 4)

Method: access$000
	0 aload_0 (0, 0)
	1 getfield (0, 0)
	4 areturn (0, 0)

