Method: <init>
	0 aload_0 (0, 0)
	1 aload_1 (0, 0)
	2 putfield (0, 0)
	3 org/apache/commons/math3/fitting/CurveFitter$TheoreticalValuesFunction.this$0:Lorg/apache/commons/math3/fitting/CurveFitter; (0, 0)
	5 aload_0 (0, 0)
	6 invokespecial (0, 0)
	7 java/lang/Object.<init>:()V (0, 0)
	9 aload_0 (0, 0)
	10 aload_2 (0, 0)
	11 putfield (0, 0)
	12 org/apache/commons/math3/fitting/CurveFitter$TheoreticalValuesFunction.f:Lorg/apache/commons/math3/analysis/ParametricUnivariateFunction; (0, 0)
	14 return (0, 0)

Method: getModelFunction
	0 new (0, 0)
	1 org/apache/commons/math3/optim/nonlinear/vector/ModelFunction (0, 0)
	3 dup (0, 0)
	4 new (0, 0)
	5 org/apache/commons/math3/fitting/CurveFitter$TheoreticalValuesFunction$1 (0, 0)
	7 dup (0, 0)
	8 aload_0 (0, 0)
	9 invokespecial (0, 0)
	10 org/apache/commons/math3/fitting/CurveFitter$TheoreticalValuesFunction$1.<init>:(Lorg/apache/commons/math3/fitting/CurveFitter$TheoreticalValuesFunction;)V (0, 0)
	12 invokespecial (0, 0)
	13 org/apache/commons/math3/optim/nonlinear/vector/ModelFunction.<init>:(Lorg/apache/commons/math3/analysis/MultivariateVectorFunction;)V (0, 0)
	15 areturn (0, 0)

Method: getModelFunctionJacobian
	0 new (0, 0)
	1 org/apache/commons/math3/optim/nonlinear/vector/ModelFunctionJacobian (0, 0)
	3 dup (0, 0)
	4 new (0, 0)
	5 org/apache/commons/math3/fitting/CurveFitter$TheoreticalValuesFunction$2 (0, 0)
	7 dup (0, 0)
	8 aload_0 (0, 0)
	9 invokespecial (0, 0)
	10 org/apache/commons/math3/fitting/CurveFitter$TheoreticalValuesFunction$2.<init>:(Lorg/apache/commons/math3/fitting/CurveFitter$TheoreticalValuesFunction;)V (0, 0)
	12 invokespecial (0, 0)
	13 org/apache/commons/math3/optim/nonlinear/vector/ModelFunctionJacobian.<init>:(Lorg/apache/commons/math3/analysis/MultivariateMatrixFunction;)V (0, 0)
	15 areturn (0, 0)

Method: access$100
	0 aload_0 (0, 0)
	1 getfield (0, 0)
	2 org/apache/commons/math3/fitting/CurveFitter$TheoreticalValuesFunction.f:Lorg/apache/commons/math3/analysis/ParametricUnivariateFunction; (0, 0)
	4 areturn (0, 0)

