Method: <init>
	0 aload_0 (0, 0)
	1 aload_1 (0, 0)
	2 invokespecial (0, 0)
	3 org/apache/commons/math3/fitting/CurveFitter.<init>:(Lorg/apache/commons/math3/optim/nonlinear/vector/MultivariateVectorOptimizer;)V (0, 0)
	5 return (0, 0)

Method: fit
	0 new (0, 0)
	1 org/apache/commons/math3/fitting/GaussianFitter$ParameterGuesser (0, 0)
	3 dup (0, 0)
	4 aload_0 (0, 0)
	5 invokevirtual (0, 0)
	6 org/apache/commons/math3/fitting/GaussianFitter.getObservations:()[Lorg/apache/commons/math3/fitting/WeightedObservedPoint; (0, 0)
	8 invokespecial (0, 0)
	9 org/apache/commons/math3/fitting/GaussianFitter$ParameterGuesser.<init>:([Lorg/apache/commons/math3/fitting/WeightedObservedPoint;)V (0, 0)
	11 invokevirtual (0, 0)
	12 org/apache/commons/math3/fitting/GaussianFitter$ParameterGuesser.guess:()[D (0, 0)
	14 astore_1 (0, 0)
	15 aload_0 (0, 0)
	16 aload_1 (0, 0)
	17 invokevirtual (0, 0)
	18 org/apache/commons/math3/fitting/GaussianFitter.fit:([D)[D (0, 0)
	20 areturn (0, 0)

