Method: <init>
	0 aload_0 (0, 0)
	1 invokespecial (0, 0)
	2 java/lang/Object.<init>:()V (0, 0)
	4 aload_1 (2, 1)
	5 ifnonnull (2, 1)
	6 18 (2, 1)
	8 new (2, 1)
	9 org/apache/commons/math3/exception/NullArgumentException (2, 1)
	11 dup (2, 1)
	12 getstatic (2, 1)
	13 org/apache/commons/math3/exception/util/LocalizedFormats.INPUT_ARRAY:Lorg/apache/commons/math3/exception/util/LocalizedFormats; (2, 1)
	15 iconst_0 (2, 1)
	16 anewarray (2, 1)
	17 java/lang/Object (2, 1)
	19 invokespecial (2, 1)
	20 org/apache/commons/math3/exception/NullArgumentException.<init>:(Lorg/apache/commons/math3/exception/util/Localizable;[Ljava/lang/Object;)V (2, 1)
	22 athrow (2, 1)
	23 aload_1 (2, 1)
	24 arraylength (2, 1)
	25 iconst_3 (2, 1)
	26 if_icmpge (2, 1)
	27 21 (2, 1)
	29 new (2, 1)
	30 org/apache/commons/math3/exception/NumberIsTooSmallException (2, 1)
	32 dup (2, 1)
	33 aload_1 (2, 1)
	34 arraylength (2, 1)
	35 invokestatic (2, 1)
	36 java/lang/Integer.valueOf:(I)Ljava/lang/Integer; (2, 1)
	38 iconst_3 (2, 1)
	39 invokestatic (2, 1)
	40 java/lang/Integer.valueOf:(I)Ljava/lang/Integer; (2, 1)
	42 iconst_1 (2, 1)
	43 invokespecial (2, 1)
	44 org/apache/commons/math3/exception/NumberIsTooSmallException.<init>:(Ljava/lang/Number;Ljava/lang/Number;Z)V (2, 1)
	46 athrow (2, 1)
	47 aload_0 (0, 0)
	48 aload_1 (0, 0)
	49 invokespecial (0, 0)
	50 org/apache/commons/math3/fitting/GaussianFitter$ParameterGuesser.sortObservations:([Lorg/apache/commons/math3/fitting/WeightedObservedPoint;)[Lorg/apache/commons/math3/fitting/WeightedObservedPoint; (0, 0)
	52 astore_2 (0, 0)
	53 aload_0 (0, 0)
	54 aload_2 (0, 0)
	55 invokespecial (0, 0)
	56 org/apache/commons/math3/fitting/GaussianFitter$ParameterGuesser.basicGuess:([Lorg/apache/commons/math3/fitting/WeightedObservedPoint;)[D (0, 0)
	58 astore_3 (0, 0)
	59 aload_0 (0, 0)
	60 aload_3 (0, 0)
	61 iconst_0 (0, 0)
	62 daload (0, 0)
	63 putfield (0, 0)
	64 org/apache/commons/math3/fitting/GaussianFitter$ParameterGuesser.norm:D (0, 0)
	66 aload_0 (0, 0)
	67 aload_3 (0, 0)
	68 iconst_1 (0, 0)
	69 daload (0, 0)
	70 putfield (0, 0)
	71 org/apache/commons/math3/fitting/GaussianFitter$ParameterGuesser.mean:D (0, 0)
	73 aload_0 (0, 0)
	74 aload_3 (0, 0)
	75 iconst_2 (0, 0)
	76 daload (0, 0)
	77 putfield (0, 0)
	78 org/apache/commons/math3/fitting/GaussianFitter$ParameterGuesser.sigma:D (0, 0)
	80 return (0, 0)

Method: guess
	0 iconst_3 (0, 0)
	1 newarray (0, 0)
	2 7 (0, 0)
	3 dup (0, 0)
	4 iconst_0 (0, 0)
	5 aload_0 (0, 0)
	6 getfield (0, 0)
	7 org/apache/commons/math3/fitting/GaussianFitter$ParameterGuesser.norm:D (0, 0)
	9 dastore (0, 0)
	10 dup (0, 0)
	11 iconst_1 (0, 0)
	12 aload_0 (0, 0)
	13 getfield (0, 0)
	14 org/apache/commons/math3/fitting/GaussianFitter$ParameterGuesser.mean:D (0, 0)
	16 dastore (0, 0)
	17 dup (0, 0)
	18 iconst_2 (0, 0)
	19 aload_0 (0, 0)
	20 getfield (0, 0)
	21 org/apache/commons/math3/fitting/GaussianFitter$ParameterGuesser.sigma:D (0, 0)
	23 dastore (0, 0)
	24 areturn (0, 0)

Method: sortObservations
	0 aload_1 (0, 0)
	1 invokevirtual (0, 0)
	2 [Lorg/apache/commons/math3/fitting/WeightedObservedPoint;.clone:()Ljava/lang/Object; (0, 0)
	4 checkcast (0, 0)
	5 [Lorg/apache/commons/math3/fitting/WeightedObservedPoint; (0, 0)
	7 astore_2 (0, 0)
	8 new (0, 0)
	9 org/apache/commons/math3/fitting/GaussianFitter$ParameterGuesser$1 (0, 0)
	11 dup (0, 0)
	12 aload_0 (0, 0)
	13 invokespecial (0, 0)
	14 org/apache/commons/math3/fitting/GaussianFitter$ParameterGuesser$1.<init>:(Lorg/apache/commons/math3/fitting/GaussianFitter$ParameterGuesser;)V (0, 0)
	16 astore_3 (0, 0)
	17 aload_2 (0, 0)
	18 aload_3 (0, 0)
	19 invokestatic (0, 0)
	20 java/util/Arrays.sort:([Ljava/lang/Object;Ljava/util/Comparator;)V (0, 0)
	22 aload_2 (0, 0)
	23 areturn (0, 0)

Method: basicGuess
	0 aload_0 (0, 0)
	1 aload_1 (0, 0)
	2 invokespecial (0, 0)
	3 org/apache/commons/math3/fitting/GaussianFitter$ParameterGuesser.findMaxY:([Lorg/apache/commons/math3/fitting/WeightedObservedPoint;)I (0, 0)
	5 istore_2 (0, 0)
	6 aload_1 (0, 0)
	7 iload_2 (0, 0)
	8 aaload (0, 0)
	9 invokevirtual (0, 0)
	10 org/apache/commons/math3/fitting/WeightedObservedPoint.getY:()D (0, 0)
	12 dstore_3 (0, 0)
	13 aload_1 (0, 0)
	14 iload_2 (0, 0)
	15 aaload (0, 0)
	16 invokevirtual (0, 0)
	17 org/apache/commons/math3/fitting/WeightedObservedPoint.getX:()D (0, 0)
	19 dstore (0, 0)
	20 #5 (0, 0)
	21 dload_3 (0, 0)
	22 dload (0, 0)
	23 #5 (0, 0)
	24 dload_3 (0, 0)
	25 dsub (0, 0)
	26 ldc2_w (0, 0)
	27 2.0 (0, 0)
	29 ddiv (0, 0)
	30 dadd (0, 0)
	31 dstore (0, 0)
	32 #9 (0, 0)
	33 aload_0 (0, 0)
	34 aload_1 (0, 0)
	35 iload_2 (0, 0)
	36 iconst_m1 (0, 0)
	37 dload (0, 0)
	38 #9 (0, 0)
	39 invokespecial (0, 0)
	40 org/apache/commons/math3/fitting/GaussianFitter$ParameterGuesser.interpolateXAtY:([Lorg/apache/commons/math3/fitting/WeightedObservedPoint;IID)D (0, 0)
	42 dstore (0, 0)
	43 #11 (0, 0)
	44 aload_0 (0, 0)
	45 aload_1 (0, 0)
	46 iload_2 (0, 0)
	47 iconst_1 (0, 0)
	48 dload (0, 0)
	49 #9 (0, 0)
	50 invokespecial (0, 0)
	51 org/apache/commons/math3/fitting/GaussianFitter$ParameterGuesser.interpolateXAtY:([Lorg/apache/commons/math3/fitting/WeightedObservedPoint;IID)D (0, 0)
	53 dstore (0, 0)
	54 #13 (0, 0)
	55 dload (0, 0)
	56 #13 (0, 0)
	57 dload (0, 0)
	58 #11 (0, 0)
	59 dsub (0, 0)
	60 dstore (0, 0)
	61 #7 (0, 0)
	62 goto (0, 0)
	63 23 (0, 0)
	65 astore (0, 0)
	66 #9 (0, 0)
	67 aload_1 (0, 4)
	68 aload_1 (0, 4)
	69 arraylength (0, 4)
	70 iconst_1 (0, 4)
	71 isub (0, 4)
	72 aaload (0, 4)
	73 invokevirtual (0, 4)
	74 org/apache/commons/math3/fitting/WeightedObservedPoint.getX:()D (0, 4)
	76 aload_1 (0, 4)
	77 iconst_0 (0, 4)
	78 aaload (0, 4)
	79 invokevirtual (0, 4)
	80 org/apache/commons/math3/fitting/WeightedObservedPoint.getX:()D (0, 4)
	82 dsub (0, 4)
	83 dstore (0, 4)
	84 #7 (0, 4)
	85 dload (0, 4)
	86 #7 (0, 4)
	87 ldc2_w (0, 4)
	88 2.0 (0, 4)
	90 ldc2_w (0, 4)
	91 2.0 (0, 4)
	93 ldc2_w (0, 4)
	94 2.0 (0, 4)
	96 invokestatic (0, 4)
	97 org/apache/commons/math3/util/FastMath.log:(D)D (0, 4)
	99 dmul (0, 4)
	100 invokestatic (0, 4)
	101 org/apache/commons/math3/util/FastMath.sqrt:(D)D (0, 4)
	103 dmul (0, 4)
	104 ddiv (0, 4)
	105 dstore (0, 4)
	106 #9 (0, 4)
	107 iconst_3 (0, 4)
	108 newarray (0, 4)
	109 7 (0, 4)
	110 dup (0, 4)
	111 iconst_0 (0, 4)
	112 dload_3 (0, 4)
	113 dastore (0, 4)
	114 dup (0, 4)
	115 iconst_1 (0, 4)
	116 dload (0, 4)
	117 #5 (0, 4)
	118 dastore (0, 4)
	119 dup (0, 4)
	120 iconst_2 (0, 4)
	121 dload (0, 4)
	122 #9 (0, 4)
	123 dastore (0, 4)
	124 areturn (0, 4)

Method: findMaxY
	0 iconst_0 (0, 0)
	1 istore_2 (0, 0)
	2 iconst_1 (1, 4)
	3 istore_3 (1, 4)
	4 iload_3 (1, 4)
	5 aload_1 (1, 4)
	6 arraylength (1, 4)
	7 if_icmpge (1, 4)
	8 27 (1, 4)
	10 aload_1 (2, 1)
	11 iload_3 (2, 1)
	12 aaload (2, 1)
	13 invokevirtual (2, 1)
	14 org/apache/commons/math3/fitting/WeightedObservedPoint.getY:()D (2, 1)
	16 aload_1 (2, 1)
	17 iload_2 (2, 1)
	18 aaload (2, 1)
	19 invokevirtual (2, 1)
	20 org/apache/commons/math3/fitting/WeightedObservedPoint.getY:()D (2, 1)
	22 dcmpl (2, 1)
	23 ifle (2, 1)
	24 5 (2, 1)
	26 iload_3 (2, 1)
	27 istore_2 (2, 1)
	28 iinc (2, 1)
	29 #3 (2, 1)
	30 -89 (2, 1)
	31 goto (2, 1)
	32 -27 (2, 1)
	34 iload_2 (1, 4)
	35 ireturn (1, 4)

Method: interpolateXAtY
	0 iload_3 (1, 1)
	1 ifne (1, 1)
	2 11 (1, 1)
	4 new (1, 1)
	5 org/apache/commons/math3/exception/ZeroException (1, 1)
	7 dup (1, 1)
	8 invokespecial (1, 1)
	9 org/apache/commons/math3/exception/ZeroException.<init>:()V (1, 1)
	11 athrow (1, 1)
	12 aload_0 (0, 0)
	13 aload_1 (0, 0)
	14 iload_2 (0, 0)
	15 iload_3 (0, 0)
	16 dload (0, 0)
	17 #4 (0, 0)
	18 invokespecial (0, 0)
	19 org/apache/commons/math3/fitting/GaussianFitter$ParameterGuesser.getInterpolationPointsForY:([Lorg/apache/commons/math3/fitting/WeightedObservedPoint;IID)[Lorg/apache/commons/math3/fitting/WeightedObservedPoint; (0, 0)
	21 astore (0, 0)
	22 #6 (0, 0)
	23 aload (0, 0)
	24 #6 (0, 0)
	25 iconst_0 (0, 0)
	26 aaload (0, 0)
	27 astore (0, 0)
	28 #7 (0, 0)
	29 aload (0, 0)
	30 #6 (0, 0)
	31 iconst_1 (0, 0)
	32 aaload (0, 0)
	33 astore (0, 0)
	34 #8 (0, 0)
	35 aload (1, 1)
	36 #7 (1, 1)
	37 invokevirtual (1, 1)
	38 org/apache/commons/math3/fitting/WeightedObservedPoint.getY:()D (1, 1)
	40 dload (1, 1)
	41 #4 (1, 1)
	42 dcmpl (1, 1)
	43 ifne (1, 1)
	44 9 (1, 1)
	46 aload (1, 1)
	47 #7 (1, 1)
	48 invokevirtual (1, 1)
	49 org/apache/commons/math3/fitting/WeightedObservedPoint.getX:()D (1, 1)
	51 dreturn (1, 1)
	52 aload (1, 1)
	53 #8 (1, 1)
	54 invokevirtual (1, 1)
	55 org/apache/commons/math3/fitting/WeightedObservedPoint.getY:()D (1, 1)
	57 dload (1, 1)
	58 #4 (1, 1)
	59 dcmpl (1, 1)
	60 ifne (1, 1)
	61 9 (1, 1)
	63 aload (1, 1)
	64 #8 (1, 1)
	65 invokevirtual (1, 1)
	66 org/apache/commons/math3/fitting/WeightedObservedPoint.getX:()D (1, 1)
	68 dreturn (1, 1)
	69 aload (0, 0)
	70 #7 (0, 0)
	71 invokevirtual (0, 0)
	72 org/apache/commons/math3/fitting/WeightedObservedPoint.getX:()D (0, 0)
	74 dload (0, 0)
	75 #4 (0, 0)
	76 aload (0, 0)
	77 #7 (0, 0)
	78 invokevirtual (0, 0)
	79 org/apache/commons/math3/fitting/WeightedObservedPoint.getY:()D (0, 0)
	81 dsub (0, 0)
	82 aload (0, 0)
	83 #8 (0, 0)
	84 invokevirtual (0, 0)
	85 org/apache/commons/math3/fitting/WeightedObservedPoint.getX:()D (0, 0)
	87 aload (0, 0)
	88 #7 (0, 0)
	89 invokevirtual (0, 0)
	90 org/apache/commons/math3/fitting/WeightedObservedPoint.getX:()D (0, 0)
	92 dsub (0, 0)
	93 dmul (0, 0)
	94 aload (0, 0)
	95 #8 (0, 0)
	96 invokevirtual (0, 0)
	97 org/apache/commons/math3/fitting/WeightedObservedPoint.getY:()D (0, 0)
	99 aload (0, 0)
	100 #7 (0, 0)
	101 invokevirtual (0, 0)
	102 org/apache/commons/math3/fitting/WeightedObservedPoint.getY:()D (0, 0)
	104 dsub (0, 0)
	105 ddiv (0, 0)
	106 dadd (0, 0)
	107 dreturn (0, 0)

Method: getInterpolationPointsForY
	0 iload_3 (1, 1)
	1 ifne (1, 1)
	2 11 (1, 1)
	4 new (1, 1)
	5 org/apache/commons/math3/exception/ZeroException (1, 1)
	7 dup (1, 1)
	8 invokespecial (1, 1)
	9 org/apache/commons/math3/exception/ZeroException.<init>:()V (1, 1)
	11 athrow (1, 1)
	12 iload_2 (0, 4)
	13 istore (0, 4)
	14 #6 (0, 4)
	15 iload_3 (0, 4)
	16 ifge (0, 4)
	17 13 (0, 4)
	19 iload (0, 4)
	20 #6 (0, 4)
	21 iload_3 (0, 4)
	22 iadd (0, 4)
	23 iflt (0, 4)
	24 91 (0, 4)
	26 goto (0, 4)
	27 12 (0, 4)
	29 iload (0, 4)
	30 #6 (0, 4)
	31 iload_3 (0, 4)
	32 iadd (0, 4)
	33 aload_1 (0, 4)
	34 arraylength (0, 4)
	35 if_icmpge (0, 4)
	36 79 (0, 4)
	38 aload_1 (0, 4)
	39 iload (0, 4)
	40 #6 (0, 4)
	41 aaload (0, 4)
	42 astore (0, 4)
	43 #7 (0, 4)
	44 aload_1 (0, 4)
	45 iload (0, 4)
	46 #6 (0, 4)
	47 iload_3 (0, 4)
	48 iadd (0, 4)
	49 aaload (0, 4)
	50 astore (0, 4)
	51 #8 (0, 4)
	52 aload_0 (2, 1)
	53 dload (2, 1)
	54 #4 (2, 1)
	55 aload (2, 1)
	56 #7 (2, 1)
	57 invokevirtual (2, 1)
	58 org/apache/commons/math3/fitting/WeightedObservedPoint.getY:()D (2, 1)
	60 aload (2, 1)
	61 #8 (2, 1)
	62 invokevirtual (2, 1)
	63 org/apache/commons/math3/fitting/WeightedObservedPoint.getY:()D (2, 1)
	65 invokespecial (2, 1)
	66 org/apache/commons/math3/fitting/GaussianFitter$ParameterGuesser.isBetween:(DDD)Z (2, 1)
	68 ifeq (2, 1)
	69 37 (2, 1)
	71 iload_3 (3, 1)
	72 ifge (3, 1)
	73 18 (3, 1)
	75 iconst_2 (3, 1)
	76 anewarray (3, 1)
	77 org/apache/commons/math3/fitting/WeightedObservedPoint (3, 1)
	79 dup (3, 1)
	80 iconst_0 (3, 1)
	81 aload (3, 1)
	82 #8 (3, 1)
	83 aastore (3, 1)
	84 dup (3, 1)
	85 iconst_1 (3, 1)
	86 aload (3, 1)
	87 #7 (3, 1)
	88 aastore (3, 1)
	89 areturn (3, 1)
	90 iconst_2 (3, 2)
	91 anewarray (3, 2)
	92 org/apache/commons/math3/fitting/WeightedObservedPoint (3, 2)
	94 dup (3, 2)
	95 iconst_0 (3, 2)
	96 aload (3, 2)
	97 #7 (3, 2)
	98 aastore (3, 2)
	99 dup (3, 2)
	100 iconst_1 (3, 2)
	101 aload (3, 2)
	102 #8 (3, 2)
	103 aastore (3, 2)
	104 areturn (3, 2)
	105 iload (3, 2)
	106 #6 (3, 2)
	107 iload_3 (3, 2)
	108 iadd (3, 2)
	109 istore (3, 2)
	110 #6 (3, 2)
	111 goto (3, 2)
	112 -96 (3, 2)
	114 new (2, 4)
	115 org/apache/commons/math3/exception/OutOfRangeException (2, 4)
	117 dup (2, 4)
	118 dload (2, 4)
	119 #4 (2, 4)
	120 invokestatic (2, 4)
	121 java/lang/Double.valueOf:(D)Ljava/lang/Double; (2, 4)
	123 ldc2_w (2, 4)
	124 -inf (2, 4)
	126 invokestatic (2, 4)
	127 java/lang/Double.valueOf:(D)Ljava/lang/Double; (2, 4)
	129 ldc2_w (2, 4)
	130 inf (2, 4)
	132 invokestatic (2, 4)
	133 java/lang/Double.valueOf:(D)Ljava/lang/Double; (2, 4)
	135 invokespecial (2, 4)
	136 org/apache/commons/math3/exception/OutOfRangeException.<init>:(Ljava/lang/Number;Ljava/lang/Number;Ljava/lang/Number;)V (2, 4)
	138 athrow (2, 4)

Method: isBetween
	0 dload_1 (0, 0)
	1 dload_3 (0, 0)
	2 dcmpl (0, 0)
	3 iflt (0, 0)
	4 10 (0, 0)
	6 dload_1 (0, 0)
	7 dload (0, 0)
	8 #5 (0, 0)
	9 dcmpg (0, 0)
	10 ifle (0, 0)
	11 16 (0, 0)
	13 dload_1 (0, 0)
	14 dload (0, 0)
	15 #5 (0, 0)
	16 dcmpl (0, 0)
	17 iflt (0, 0)
	18 13 (0, 0)
	20 dload_1 (0, 0)
	21 dload_3 (0, 0)
	22 dcmpg (0, 0)
	23 ifgt (0, 0)
	24 7 (0, 0)
	26 iconst_1 (0, 0)
	27 goto (0, 0)
	28 4 (0, 0)
	30 iconst_0 (0, 0)
	31 ireturn (0, 0)

