Method: <init>
	0 aload_0 (0, 0)
	1 invokespecial (0, 0)
	2 java/lang/Object.<init>:()V (0, 0)
	4 aload_1 (2, 1)
	5 invokeinterface (2, 1)
	6 java/util/Collection.org/apache/commons/math3/exception/NumberIsTooSmallException (2, 1)
	8 0 (2, 1)
	10 iconst_4 (2, 1)
	11 if_icmpge (2, 1)
	12 28 (2, 1)
	14 new (2, 1)
	15 org/apache/commons/math3/exception/NumberIsTooSmallException (2, 1)
	17 dup (2, 1)
	18 getstatic (2, 1)
	19 org/apache/commons/math3/exception/util/LocalizedFormats.INSUFFICIENT_OBSERVED_POINTS_IN_SAMPLE:Lorg/apache/commons/math3/exception/util/LocalizedFormats; (2, 1)
	21 aload_1 (2, 1)
	22 invokeinterface (2, 1)
	23 java/util/Collection.org/apache/commons/math3/exception/NumberIsTooSmallException (2, 1)
	25 0 (2, 1)
	27 invokestatic (2, 1)
	28 java/lang/Integer.valueOf:(I)Ljava/lang/Integer; (2, 1)
	30 iconst_4 (2, 1)
	31 invokestatic (2, 1)
	32 java/lang/Integer.valueOf:(I)Ljava/lang/Integer; (2, 1)
	34 iconst_1 (2, 1)
	35 invokespecial (2, 1)
	36 org/apache/commons/math3/exception/NumberIsTooSmallException.<init>:(Lorg/apache/commons/math3/exception/util/Localizable;Ljava/lang/Number;Ljava/lang/Number;Z)V (2, 1)
	38 athrow (2, 1)
	39 aload_0 (0, 0)
	40 aload_1 (0, 0)
	41 invokespecial (0, 0)
	42 org/apache/commons/math3/fitting/HarmonicCurveFitter$ParameterGuesser.sortObservations:(Ljava/util/Collection;)Ljava/util/List; (0, 0)
	44 iconst_0 (0, 0)
	45 anewarray (0, 0)
	46 org/apache/commons/math3/fitting/WeightedObservedPoint (0, 0)
	48 invokeinterface (0, 0)
	49 java/util/List.guessAOmega:([Lorg/apache/commons/math3/fitting/WeightedObservedPoint;)[D (0, 0)
	51 0 (0, 0)
	53 checkcast (0, 0)
	54 [Lorg/apache/commons/math3/fitting/WeightedObservedPoint; (0, 0)
	56 astore_2 (0, 0)
	57 aload_0 (0, 0)
	58 aload_2 (0, 0)
	59 invokespecial (0, 0)
	60 org/apache/commons/math3/fitting/HarmonicCurveFitter$ParameterGuesser.guessAOmega:([Lorg/apache/commons/math3/fitting/WeightedObservedPoint;)[D (0, 0)
	62 astore_3 (0, 0)
	63 aload_0 (0, 0)
	64 aload_3 (0, 0)
	65 iconst_0 (0, 0)
	66 daload (0, 0)
	67 putfield (0, 0)
	68 org/apache/commons/math3/fitting/HarmonicCurveFitter$ParameterGuesser.a:D (0, 0)
	70 aload_0 (0, 0)
	71 aload_3 (0, 0)
	72 iconst_1 (0, 0)
	73 daload (0, 0)
	74 putfield (0, 0)
	75 org/apache/commons/math3/fitting/HarmonicCurveFitter$ParameterGuesser.omega:D (0, 0)
	77 aload_0 (0, 0)
	78 aload_0 (0, 0)
	79 aload_2 (0, 0)
	80 invokespecial (0, 0)
	81 org/apache/commons/math3/fitting/HarmonicCurveFitter$ParameterGuesser.guessPhi:([Lorg/apache/commons/math3/fitting/WeightedObservedPoint;)D (0, 0)
	83 putfield (0, 0)
	84 org/apache/commons/math3/fitting/HarmonicCurveFitter$ParameterGuesser.phi:D (0, 0)
	86 return (0, 0)

Method: guess
	0 iconst_3 (0, 0)
	1 newarray (0, 0)
	2 7 (0, 0)
	3 dup (0, 0)
	4 iconst_0 (0, 0)
	5 aload_0 (0, 0)
	6 getfield (0, 0)
	7 org/apache/commons/math3/fitting/HarmonicCurveFitter$ParameterGuesser.a:D (0, 0)
	9 dastore (0, 0)
	10 dup (0, 0)
	11 iconst_1 (0, 0)
	12 aload_0 (0, 0)
	13 getfield (0, 0)
	14 org/apache/commons/math3/fitting/HarmonicCurveFitter$ParameterGuesser.omega:D (0, 0)
	16 dastore (0, 0)
	17 dup (0, 0)
	18 iconst_2 (0, 0)
	19 aload_0 (0, 0)
	20 getfield (0, 0)
	21 org/apache/commons/math3/fitting/HarmonicCurveFitter$ParameterGuesser.phi:D (0, 0)
	23 dastore (0, 0)
	24 areturn (0, 0)

Method: sortObservations
	0 new (0, 0)
	1 java/util/ArrayList (0, 0)
	3 dup (0, 0)
	4 aload_1 (0, 0)
	5 invokespecial (0, 0)
	6 java/util/ArrayList.<init>:(Ljava/util/Collection;)V (0, 0)
	8 astore_2 (0, 0)
	9 aload_2 (0, 0)
	10 iconst_0 (0, 0)
	11 invokeinterface (0, 0)
	12 java/util/List.getX:()D (0, 0)
	14 0 (0, 0)
	16 checkcast (0, 0)
	17 org/apache/commons/math3/fitting/WeightedObservedPoint (0, 0)
	19 astore_3 (0, 0)
	20 aload_2 (0, 0)
	21 invokeinterface (0, 0)
	22 java/util/List.org/apache/commons/math3/exception/NumberIsTooSmallException (0, 0)
	24 0 (0, 0)
	26 istore (0, 0)
	27 #4 (0, 0)
	28 iconst_1 (1, 4)
	29 istore (1, 4)
	30 #5 (1, 4)
	31 iload (1, 4)
	32 #5 (1, 4)
	33 iload (1, 4)
	34 #4 (1, 4)
	35 if_icmpge (1, 4)
	36 135 (1, 4)
	38 aload_3 (1, 4)
	39 astore (1, 4)
	40 #6 (1, 4)
	41 aload_2 (1, 4)
	42 iload (1, 4)
	43 #5 (1, 4)
	44 invokeinterface (1, 4)
	45 java/util/List.getX:()D (1, 4)
	47 0 (1, 4)
	49 checkcast (1, 4)
	50 org/apache/commons/math3/fitting/WeightedObservedPoint (1, 4)
	52 astore_3 (1, 4)
	53 aload_3 (2, 1)
	54 invokevirtual (2, 1)
	55 org/apache/commons/math3/fitting/WeightedObservedPoint.getX:()D (2, 1)
	57 aload (2, 1)
	58 #6 (2, 1)
	59 invokevirtual (2, 1)
	60 org/apache/commons/math3/fitting/WeightedObservedPoint.getX:()D (2, 1)
	62 dcmpg (2, 1)
	63 ifge (2, 1)
	64 101 (2, 1)
	66 iload (2, 1)
	67 #5 (2, 1)
	68 iconst_1 (2, 1)
	69 isub (2, 1)
	70 istore (2, 1)
	71 #7 (2, 1)
	72 aload_2 (2, 1)
	73 iload (2, 1)
	74 #7 (2, 1)
	75 invokeinterface (2, 1)
	76 java/util/List.getX:()D (2, 1)
	78 0 (2, 1)
	80 checkcast (2, 1)
	81 org/apache/commons/math3/fitting/WeightedObservedPoint (2, 1)
	83 astore (2, 1)
	84 #8 (2, 1)
	85 iload (3, 3)
	86 #7 (3, 3)
	87 iflt (3, 3)
	88 53 (3, 3)
	90 aload_3 (3, 3)
	91 invokevirtual (3, 3)
	92 org/apache/commons/math3/fitting/WeightedObservedPoint.getX:()D (3, 3)
	94 aload (3, 3)
	95 #8 (3, 3)
	96 invokevirtual (3, 3)
	97 org/apache/commons/math3/fitting/WeightedObservedPoint.getX:()D (3, 3)
	99 dcmpg (3, 3)
	100 ifge (3, 3)
	101 40 (3, 3)
	103 aload_2 (3, 3)
	104 iload (3, 3)
	105 #7 (3, 3)
	106 iconst_1 (3, 3)
	107 iadd (3, 3)
	108 aload (3, 3)
	109 #8 (3, 3)
	110 invokeinterface (3, 3)
	111 java/util/List.getY:()D (3, 3)
	113 0 (3, 3)
	115 pop (3, 3)
	116 iload (4, 1)
	117 #7 (4, 1)
	118 iinc (4, 1)
	119 #7 (4, 1)
	120 -103 (4, 1)
	121 ifeq (4, 1)
	122 -36 (4, 1)
	124 aload_2 (4, 1)
	125 iload (4, 1)
	126 #7 (4, 1)
	127 invokeinterface (4, 1)
	128 java/util/List.getX:()D (4, 1)
	130 0 (4, 1)
	132 checkcast (4, 1)
	133 org/apache/commons/math3/fitting/WeightedObservedPoint (4, 1)
	135 astore (4, 1)
	136 #8 (4, 1)
	137 goto (4, 1)
	138 -52 (4, 1)
	140 aload_2 (2, 1)
	141 iload (2, 1)
	142 #7 (2, 1)
	143 iconst_1 (2, 1)
	144 iadd (2, 1)
	145 aload_3 (2, 1)
	146 invokeinterface (2, 1)
	147 java/util/List.getY:()D (2, 1)
	149 0 (2, 1)
	151 pop (2, 1)
	152 aload_2 (2, 1)
	153 iload (2, 1)
	154 #5 (2, 1)
	155 invokeinterface (2, 1)
	156 java/util/List.getX:()D (2, 1)
	158 0 (2, 1)
	160 checkcast (2, 1)
	161 org/apache/commons/math3/fitting/WeightedObservedPoint (2, 1)
	163 astore_3 (2, 1)
	164 iinc (2, 1)
	165 #5 (2, 1)
	166 -89 (2, 1)
	167 goto (2, 1)
	168 -136 (2, 1)
	170 aload_2 (1, 4)
	171 areturn (1, 4)

Method: guessAOmega
	0 iconst_2 (0, 0)
	1 newarray (0, 0)
	2 7 (0, 0)
	3 astore_2 (0, 0)
	4 dconst_0 (0, 4)
	5 dstore_3 (0, 4)
	6 dconst_0 (0, 4)
	7 dstore (0, 4)
	8 #5 (0, 4)
	9 dconst_0 (0, 4)
	10 dstore (0, 4)
	11 #7 (0, 4)
	12 dconst_0 (0, 4)
	13 dstore (0, 4)
	14 #9 (0, 4)
	15 dconst_0 (0, 4)
	16 dstore (0, 4)
	17 #11 (0, 4)
	18 aload_1 (0, 4)
	19 iconst_0 (0, 4)
	20 aaload (0, 4)
	21 invokevirtual (0, 4)
	22 org/apache/commons/math3/fitting/WeightedObservedPoint.getX:()D (0, 4)
	24 dstore (0, 4)
	25 #13 (0, 4)
	26 aload_1 (0, 4)
	27 iconst_0 (0, 4)
	28 aaload (0, 4)
	29 invokevirtual (0, 4)
	30 org/apache/commons/math3/fitting/WeightedObservedPoint.getY:()D (0, 4)
	32 dstore (0, 4)
	33 #15 (0, 4)
	34 dconst_0 (0, 4)
	35 dstore (0, 4)
	36 #17 (0, 4)
	37 dconst_0 (0, 4)
	38 dstore (0, 4)
	39 #19 (0, 4)
	40 dload (0, 4)
	41 #13 (0, 4)
	42 dstore (0, 4)
	43 #21 (0, 4)
	44 iconst_1 (1, 4)
	45 istore (1, 4)
	46 #23 (1, 4)
	47 iload (1, 4)
	48 #23 (1, 4)
	49 aload_1 (1, 4)
	50 arraylength (1, 4)
	51 if_icmpge (1, 4)
	52 154 (1, 4)
	54 dload (1, 4)
	55 #13 (1, 4)
	56 dstore (1, 4)
	57 #24 (1, 4)
	58 dload (1, 4)
	59 #15 (1, 4)
	60 dstore (1, 4)
	61 #26 (1, 4)
	62 aload_1 (1, 4)
	63 iload (1, 4)
	64 #23 (1, 4)
	65 aaload (1, 4)
	66 invokevirtual (1, 4)
	67 org/apache/commons/math3/fitting/WeightedObservedPoint.getX:()D (1, 4)
	69 dstore (1, 4)
	70 #13 (1, 4)
	71 aload_1 (1, 4)
	72 iload (1, 4)
	73 #23 (1, 4)
	74 aaload (1, 4)
	75 invokevirtual (1, 4)
	76 org/apache/commons/math3/fitting/WeightedObservedPoint.getY:()D (1, 4)
	78 dstore (1, 4)
	79 #15 (1, 4)
	80 dload (1, 4)
	81 #13 (1, 4)
	82 dload (1, 4)
	83 #24 (1, 4)
	84 dsub (1, 4)
	85 dstore (1, 4)
	86 #28 (1, 4)
	87 dload (1, 4)
	88 #15 (1, 4)
	89 dload (1, 4)
	90 #26 (1, 4)
	91 dsub (1, 4)
	92 dstore (1, 4)
	93 #30 (1, 4)
	94 dload (1, 4)
	95 #28 (1, 4)
	96 dload (1, 4)
	97 #26 (1, 4)
	98 dload (1, 4)
	99 #26 (1, 4)
	100 dmul (1, 4)
	101 dload (1, 4)
	102 #26 (1, 4)
	103 dload (1, 4)
	104 #15 (1, 4)
	105 dmul (1, 4)
	106 dadd (1, 4)
	107 dload (1, 4)
	108 #15 (1, 4)
	109 dload (1, 4)
	110 #15 (1, 4)
	111 dmul (1, 4)
	112 dadd (1, 4)
	113 dmul (1, 4)
	114 ldc2_w (1, 4)
	115 3.0 (1, 4)
	117 ddiv (1, 4)
	118 dstore (1, 4)
	119 #32 (1, 4)
	120 dload (1, 4)
	121 #30 (1, 4)
	122 dload (1, 4)
	123 #30 (1, 4)
	124 dmul (1, 4)
	125 dload (1, 4)
	126 #28 (1, 4)
	127 ddiv (1, 4)
	128 dstore (1, 4)
	129 #34 (1, 4)
	130 dload (1, 4)
	131 #13 (1, 4)
	132 dload (1, 4)
	133 #21 (1, 4)
	134 dsub (1, 4)
	135 dstore (1, 4)
	136 #36 (1, 4)
	137 dload (1, 4)
	138 #17 (1, 4)
	139 dload (1, 4)
	140 #32 (1, 4)
	141 dadd (1, 4)
	142 dstore (1, 4)
	143 #17 (1, 4)
	144 dload (1, 4)
	145 #19 (1, 4)
	146 dload (1, 4)
	147 #34 (1, 4)
	148 dadd (1, 4)
	149 dstore (1, 4)
	150 #19 (1, 4)
	151 dload_3 (1, 4)
	152 dload (1, 4)
	153 #36 (1, 4)
	154 dload (1, 4)
	155 #36 (1, 4)
	156 dmul (1, 4)
	157 dadd (1, 4)
	158 dstore_3 (1, 4)
	159 dload (1, 4)
	160 #5 (1, 4)
	161 dload (1, 4)
	162 #17 (1, 4)
	163 dload (1, 4)
	164 #17 (1, 4)
	165 dmul (1, 4)
	166 dadd (1, 4)
	167 dstore (1, 4)
	168 #5 (1, 4)
	169 dload (1, 4)
	170 #7 (1, 4)
	171 dload (1, 4)
	172 #36 (1, 4)
	173 dload (1, 4)
	174 #17 (1, 4)
	175 dmul (1, 4)
	176 dadd (1, 4)
	177 dstore (1, 4)
	178 #7 (1, 4)
	179 dload (1, 4)
	180 #9 (1, 4)
	181 dload (1, 4)
	182 #36 (1, 4)
	183 dload (1, 4)
	184 #19 (1, 4)
	185 dmul (1, 4)
	186 dadd (1, 4)
	187 dstore (1, 4)
	188 #9 (1, 4)
	189 dload (1, 4)
	190 #11 (1, 4)
	191 dload (1, 4)
	192 #17 (1, 4)
	193 dload (1, 4)
	194 #19 (1, 4)
	195 dmul (1, 4)
	196 dadd (1, 4)
	197 dstore (1, 4)
	198 #11 (1, 4)
	199 iinc (1, 4)
	200 #23 (1, 4)
	201 -89 (1, 4)
	202 goto (1, 4)
	203 -155 (1, 4)
	205 dload (0, 4)
	206 #5 (0, 4)
	207 dload (0, 4)
	208 #9 (0, 4)
	209 dmul (0, 4)
	210 dload (0, 4)
	211 #7 (0, 4)
	212 dload (0, 4)
	213 #11 (0, 4)
	214 dmul (0, 4)
	215 dsub (0, 4)
	216 dstore (0, 4)
	217 #23 (0, 4)
	218 dload (0, 4)
	219 #7 (0, 4)
	220 dload (0, 4)
	221 #9 (0, 4)
	222 dmul (0, 4)
	223 dload_3 (0, 4)
	224 dload (0, 4)
	225 #11 (0, 4)
	226 dmul (0, 4)
	227 dsub (0, 4)
	228 dstore (0, 4)
	229 #25 (0, 4)
	230 dload_3 (0, 4)
	231 dload (0, 4)
	232 #5 (0, 4)
	233 dmul (0, 4)
	234 dload (0, 4)
	235 #7 (0, 4)
	236 dload (0, 4)
	237 #7 (0, 4)
	238 dmul (0, 4)
	239 dsub (0, 4)
	240 dstore (0, 4)
	241 #27 (0, 4)
	242 dload (1, 1)
	243 #23 (1, 1)
	244 dload (1, 1)
	245 #25 (1, 1)
	246 ddiv (1, 1)
	247 dconst_0 (1, 1)
	248 dcmpg (1, 1)
	249 iflt (1, 1)
	250 13 (1, 1)
	252 dload (1, 1)
	253 #25 (1, 1)
	254 dload (1, 1)
	255 #27 (1, 1)
	256 ddiv (1, 1)
	257 dconst_0 (1, 1)
	258 dcmpg (1, 1)
	259 ifge (1, 1)
	260 123 (1, 1)
	262 aload_1 (1, 1)
	263 arraylength (1, 1)
	264 iconst_1 (1, 1)
	265 isub (1, 1)
	266 istore (1, 1)
	267 #29 (1, 1)
	268 aload_1 (1, 1)
	269 iload (1, 1)
	270 #29 (1, 1)
	271 aaload (1, 1)
	272 invokevirtual (1, 1)
	273 org/apache/commons/math3/fitting/WeightedObservedPoint.getX:()D (1, 1)
	275 aload_1 (1, 1)
	276 iconst_0 (1, 1)
	277 aaload (1, 1)
	278 invokevirtual (1, 1)
	279 org/apache/commons/math3/fitting/WeightedObservedPoint.getX:()D (1, 1)
	281 dsub (1, 1)
	282 dstore (1, 1)
	283 #30 (1, 1)
	284 dload (2, 1)
	285 #30 (2, 1)
	286 dconst_0 (2, 1)
	287 dcmpl (2, 1)
	288 ifne (2, 1)
	289 11 (2, 1)
	291 new (2, 1)
	292 org/apache/commons/math3/exception/ZeroException (2, 1)
	294 dup (2, 1)
	295 invokespecial (2, 1)
	296 org/apache/commons/math3/exception/ZeroException.<init>:()V (2, 1)
	298 athrow (2, 1)
	299 aload_2 (1, 1)
	300 iconst_1 (1, 1)
	301 ldc2_w (1, 1)
	302 6.283185307179586 (1, 1)
	304 dload (1, 1)
	305 #30 (1, 1)
	306 ddiv (1, 1)
	307 dastore (1, 1)
	308 ldc2_w (1, 1)
	309 inf (1, 1)
	311 dstore (1, 1)
	312 #32 (1, 1)
	313 ldc2_w (1, 1)
	314 -inf (1, 1)
	316 dstore (1, 1)
	317 #34 (1, 1)
	318 iconst_1 (2, 4)
	319 istore (2, 4)
	320 #36 (2, 4)
	321 iload (2, 4)
	322 #36 (2, 4)
	323 aload_1 (2, 4)
	324 arraylength (2, 4)
	325 if_icmpge (2, 4)
	326 42 (2, 4)
	328 aload_1 (2, 4)
	329 iload (2, 4)
	330 #36 (2, 4)
	331 aaload (2, 4)
	332 invokevirtual (2, 4)
	333 org/apache/commons/math3/fitting/WeightedObservedPoint.getY:()D (2, 4)
	335 dstore (2, 4)
	336 #37 (2, 4)
	337 dload (3, 1)
	338 #37 (3, 1)
	339 dload (3, 1)
	340 #32 (3, 1)
	341 dcmpg (3, 1)
	342 ifge (3, 1)
	343 7 (3, 1)
	345 dload (3, 1)
	346 #37 (3, 1)
	347 dstore (3, 1)
	348 #32 (3, 1)
	349 dload (3, 1)
	350 #37 (3, 1)
	351 dload (3, 1)
	352 #34 (3, 1)
	353 dcmpl (3, 1)
	354 ifle (3, 1)
	355 7 (3, 1)
	357 dload (3, 1)
	358 #37 (3, 1)
	359 dstore (3, 1)
	360 #34 (3, 1)
	361 iinc (3, 1)
	362 #36 (3, 1)
	363 -89 (3, 1)
	364 goto (3, 1)
	365 -43 (3, 1)
	367 aload_2 (2, 4)
	368 iconst_0 (2, 4)
	369 ldc2_w (2, 4)
	370 0.5 (2, 4)
	372 dload (2, 4)
	373 #34 (2, 4)
	374 dload (2, 4)
	375 #32 (2, 4)
	376 dsub (2, 4)
	377 dmul (2, 4)
	378 dastore (2, 4)
	379 goto (2, 2)
	380 47 (2, 2)
	382 dload (3, 1)
	383 #25 (3, 1)
	384 dconst_0 (3, 1)
	385 dcmpl (3, 1)
	386 ifne (3, 1)
	387 18 (3, 1)
	389 new (3, 1)
	390 org/apache/commons/math3/exception/MathIllegalStateException (3, 1)
	392 dup (3, 1)
	393 getstatic (3, 1)
	394 org/apache/commons/math3/exception/util/LocalizedFormats.ZERO_DENOMINATOR:Lorg/apache/commons/math3/exception/util/LocalizedFormats; (3, 1)
	396 iconst_0 (3, 1)
	397 anewarray (3, 1)
	398 java/lang/Object (3, 1)
	400 invokespecial (3, 1)
	401 org/apache/commons/math3/exception/MathIllegalStateException.<init>:(Lorg/apache/commons/math3/exception/util/Localizable;[Ljava/lang/Object;)V (3, 1)
	403 athrow (3, 1)
	404 aload_2 (2, 2)
	405 iconst_0 (2, 2)
	406 dload (2, 2)
	407 #23 (2, 2)
	408 dload (2, 2)
	409 #25 (2, 2)
	410 ddiv (2, 2)
	411 invokestatic (2, 2)
	412 org/apache/commons/math3/util/FastMath.sqrt:(D)D (2, 2)
	414 dastore (2, 2)
	415 aload_2 (2, 2)
	416 iconst_1 (2, 2)
	417 dload (2, 2)
	418 #25 (2, 2)
	419 dload (2, 2)
	420 #27 (2, 2)
	421 ddiv (2, 2)
	422 invokestatic (2, 2)
	423 org/apache/commons/math3/util/FastMath.sqrt:(D)D (2, 2)
	425 dastore (2, 2)
	426 aload_2 (1, 1)
	427 areturn (1, 1)

Method: guessPhi
	0 dconst_0 (0, 0)
	1 dstore_2 (0, 0)
	2 dconst_0 (0, 0)
	3 dstore (0, 0)
	4 #4 (0, 0)
	5 aload_1 (0, 0)
	6 iconst_0 (0, 0)
	7 aaload (0, 0)
	8 invokevirtual (0, 0)
	9 org/apache/commons/math3/fitting/WeightedObservedPoint.getX:()D (0, 0)
	11 dstore (0, 0)
	12 #6 (0, 0)
	13 aload_1 (0, 0)
	14 iconst_0 (0, 0)
	15 aaload (0, 0)
	16 invokevirtual (0, 0)
	17 org/apache/commons/math3/fitting/WeightedObservedPoint.getY:()D (0, 0)
	19 dstore (0, 0)
	20 #8 (0, 0)
	21 iconst_1 (1, 4)
	22 istore (1, 4)
	23 #10 (1, 4)
	24 iload (1, 4)
	25 #10 (1, 4)
	26 aload_1 (1, 4)
	27 arraylength (1, 4)
	28 if_icmpge (1, 4)
	29 111 (1, 4)
	31 dload (1, 4)
	32 #6 (1, 4)
	33 dstore (1, 4)
	34 #11 (1, 4)
	35 dload (1, 4)
	36 #8 (1, 4)
	37 dstore (1, 4)
	38 #13 (1, 4)
	39 aload_1 (1, 4)
	40 iload (1, 4)
	41 #10 (1, 4)
	42 aaload (1, 4)
	43 invokevirtual (1, 4)
	44 org/apache/commons/math3/fitting/WeightedObservedPoint.getX:()D (1, 4)
	46 dstore (1, 4)
	47 #6 (1, 4)
	48 aload_1 (1, 4)
	49 iload (1, 4)
	50 #10 (1, 4)
	51 aaload (1, 4)
	52 invokevirtual (1, 4)
	53 org/apache/commons/math3/fitting/WeightedObservedPoint.getY:()D (1, 4)
	55 dstore (1, 4)
	56 #8 (1, 4)
	57 dload (1, 4)
	58 #8 (1, 4)
	59 dload (1, 4)
	60 #13 (1, 4)
	61 dsub (1, 4)
	62 dload (1, 4)
	63 #6 (1, 4)
	64 dload (1, 4)
	65 #11 (1, 4)
	66 dsub (1, 4)
	67 ddiv (1, 4)
	68 dstore (1, 4)
	69 #15 (1, 4)
	70 aload_0 (1, 4)
	71 getfield (1, 4)
	72 org/apache/commons/math3/fitting/HarmonicCurveFitter$ParameterGuesser.omega:D (1, 4)
	74 dload (1, 4)
	75 #6 (1, 4)
	76 dmul (1, 4)
	77 dstore (1, 4)
	78 #17 (1, 4)
	79 dload (1, 4)
	80 #17 (1, 4)
	81 invokestatic (1, 4)
	82 org/apache/commons/math3/util/FastMath.cos:(D)D (1, 4)
	84 dstore (1, 4)
	85 #19 (1, 4)
	86 dload (1, 4)
	87 #17 (1, 4)
	88 invokestatic (1, 4)
	89 org/apache/commons/math3/util/FastMath.sin:(D)D (1, 4)
	91 dstore (1, 4)
	92 #21 (1, 4)
	93 dload_2 (1, 4)
	94 aload_0 (1, 4)
	95 getfield (1, 4)
	96 org/apache/commons/math3/fitting/HarmonicCurveFitter$ParameterGuesser.omega:D (1, 4)
	98 dload (1, 4)
	99 #8 (1, 4)
	100 dmul (1, 4)
	101 dload (1, 4)
	102 #19 (1, 4)
	103 dmul (1, 4)
	104 dload (1, 4)
	105 #15 (1, 4)
	106 dload (1, 4)
	107 #21 (1, 4)
	108 dmul (1, 4)
	109 dsub (1, 4)
	110 dadd (1, 4)
	111 dstore_2 (1, 4)
	112 dload (1, 4)
	113 #4 (1, 4)
	114 aload_0 (1, 4)
	115 getfield (1, 4)
	116 org/apache/commons/math3/fitting/HarmonicCurveFitter$ParameterGuesser.omega:D (1, 4)
	118 dload (1, 4)
	119 #8 (1, 4)
	120 dmul (1, 4)
	121 dload (1, 4)
	122 #21 (1, 4)
	123 dmul (1, 4)
	124 dload (1, 4)
	125 #15 (1, 4)
	126 dload (1, 4)
	127 #19 (1, 4)
	128 dmul (1, 4)
	129 dadd (1, 4)
	130 dadd (1, 4)
	131 dstore (1, 4)
	132 #4 (1, 4)
	133 iinc (1, 4)
	134 #10 (1, 4)
	135 -89 (1, 4)
	136 goto (1, 4)
	137 -112 (1, 4)
	139 dload (0, 0)
	140 #4 (0, 0)
	141 dneg (0, 0)
	142 dload_2 (0, 0)
	143 invokestatic (0, 0)
	144 org/apache/commons/math3/util/FastMath.atan2:(DD)D (0, 0)
	146 dreturn (0, 0)

