Method: <init>
	0 aload_0 (0, 0)
	1 invokespecial (0, 0)
	2 org/apache/commons/math3/fitting/AbstractCurveFitter.<init>:()V (0, 0)
	4 aload_0 (0, 0)
	5 aload_1 (0, 0)
	6 putfield (0, 0)
	7 org/apache/commons/math3/fitting/PolynomialCurveFitter.initialGuess:[D (0, 0)
	9 aload_0 (0, 0)
	10 iload_2 (0, 0)
	11 putfield (0, 0)
	12 org/apache/commons/math3/fitting/PolynomialCurveFitter.maxIter:I (0, 0)
	14 return (0, 0)

Method: create
	0 new (0, 0)
	1 org/apache/commons/math3/fitting/PolynomialCurveFitter (0, 0)
	3 dup (0, 0)
	4 iload_0 (0, 0)
	5 iconst_1 (0, 0)
	6 iadd (0, 0)
	7 newarray (0, 0)
	8 7 (0, 0)
	9 ldc (0, 0)
	10 2147483647 (0, 0)
	11 invokespecial (0, 0)
	12 org/apache/commons/math3/fitting/PolynomialCurveFitter.<init>:([DI)V (0, 0)
	14 areturn (0, 0)

Method: withStartPoint
	0 new (0, 0)
	1 org/apache/commons/math3/fitting/PolynomialCurveFitter (0, 0)
	3 dup (0, 0)
	4 aload_1 (0, 0)
	5 invokevirtual (0, 0)
	6 [D.clone:()Ljava/lang/Object; (0, 0)
	8 checkcast (0, 0)
	9 [D (0, 0)
	11 aload_0 (0, 0)
	12 getfield (0, 0)
	13 org/apache/commons/math3/fitting/PolynomialCurveFitter.maxIter:I (0, 0)
	15 invokespecial (0, 0)
	16 org/apache/commons/math3/fitting/PolynomialCurveFitter.<init>:([DI)V (0, 0)
	18 areturn (0, 0)

Method: withMaxIterations
	0 new (0, 0)
	1 org/apache/commons/math3/fitting/PolynomialCurveFitter (0, 0)
	3 dup (0, 0)
	4 aload_0 (0, 0)
	5 getfield (0, 0)
	6 org/apache/commons/math3/fitting/PolynomialCurveFitter.initialGuess:[D (0, 0)
	8 iload_1 (0, 0)
	9 invokespecial (0, 0)
	10 org/apache/commons/math3/fitting/PolynomialCurveFitter.<init>:([DI)V (0, 0)
	12 areturn (0, 0)

Method: getProblem
	0 aload_1 (0, 0)
	1 invokeinterface (0, 0)
	2 java/util/Collection.iterator:()Ljava/util/Iterator; (0, 0)
	4 0 (0, 0)
	6 istore_2 (0, 0)
	7 iload_2 (0, 0)
	8 newarray (0, 0)
	9 7 (0, 0)
	10 astore_3 (0, 0)
	11 iload_2 (0, 0)
	12 newarray (0, 0)
	13 7 (0, 0)
	14 astore (0, 0)
	15 #4 (0, 0)
	16 iconst_0 (0, 0)
	17 istore (0, 0)
	18 #5 (0, 0)
	19 aload_1 (1, 4)
	20 invokeinterface (1, 4)
	21 java/util/Collection.java/util/Iterator (1, 4)
	23 0 (1, 4)
	25 astore (1, 4)
	26 #6 (1, 4)
	27 aload (1, 4)
	28 #6 (1, 4)
	29 invokeinterface (1, 4)
	30 java/util/Iterator.next:()Ljava/lang/Object; (1, 4)
	32 0 (1, 4)
	34 ifeq (1, 4)
	35 40 (1, 4)
	37 aload (1, 4)
	38 #6 (1, 4)
	39 invokeinterface (1, 4)
	40 java/util/Iterator.org/apache/commons/math3/fitting/WeightedObservedPoint (1, 4)
	42 0 (1, 4)
	44 checkcast (1, 4)
	45 org/apache/commons/math3/fitting/WeightedObservedPoint (1, 4)
	47 astore (1, 4)
	48 #7 (1, 4)
	49 aload_3 (1, 4)
	50 iload (1, 4)
	51 #5 (1, 4)
	52 aload (1, 4)
	53 #7 (1, 4)
	54 invokevirtual (1, 4)
	55 org/apache/commons/math3/fitting/WeightedObservedPoint.getY:()D (1, 4)
	57 dastore (1, 4)
	58 aload (1, 4)
	59 #4 (1, 4)
	60 iload (1, 4)
	61 #5 (1, 4)
	62 aload (1, 4)
	63 #7 (1, 4)
	64 invokevirtual (1, 4)
	65 org/apache/commons/math3/fitting/WeightedObservedPoint.getWeight:()D (1, 4)
	67 dastore (1, 4)
	68 iinc (1, 4)
	69 #5 (1, 4)
	70 -89 (1, 4)
	71 goto (0, 0)
	72 -44 (0, 0)
	74 new (0, 0)
	75 org/apache/commons/math3/fitting/AbstractCurveFitter$TheoreticalValuesFunction (0, 0)
	77 dup (0, 0)
	78 getstatic (0, 0)
	79 org/apache/commons/math3/fitting/PolynomialCurveFitter.FUNCTION:Lorg/apache/commons/math3/analysis/polynomials/PolynomialFunction$Parametric; (0, 0)
	81 aload_1 (0, 0)
	82 invokespecial (0, 0)
	83 org/apache/commons/math3/fitting/AbstractCurveFitter$TheoreticalValuesFunction.<init>:(Lorg/apache/commons/math3/analysis/ParametricUnivariateFunction;Ljava/util/Collection;)V (0, 0)
	85 astore (0, 0)
	86 #6 (0, 0)
	87 aload_0 (1, 1)
	88 getfield (1, 1)
	89 org/apache/commons/math3/fitting/PolynomialCurveFitter.initialGuess:[D (1, 1)
	91 ifnonnull (1, 1)
	92 11 (1, 1)
	94 new (1, 1)
	95 org/apache/commons/math3/exception/MathInternalError (1, 1)
	97 dup (1, 1)
	98 invokespecial (1, 1)
	99 org/apache/commons/math3/exception/MathInternalError.<init>:()V (1, 1)
	101 athrow (1, 1)
	102 new (0, 0)
	103 org/apache/commons/math3/fitting/leastsquares/LeastSquaresBuilder (0, 0)
	105 dup (0, 0)
	106 invokespecial (0, 0)
	107 org/apache/commons/math3/fitting/leastsquares/LeastSquaresBuilder.<init>:()V (0, 0)
	109 ldc (0, 0)
	110 2147483647 (0, 0)
	111 invokevirtual (0, 0)
	112 org/apache/commons/math3/fitting/leastsquares/LeastSquaresBuilder.maxEvaluations:(I)Lorg/apache/commons/math3/fitting/leastsquares/LeastSquaresBuilder; (0, 0)
	114 aload_0 (0, 0)
	115 getfield (0, 0)
	116 org/apache/commons/math3/fitting/PolynomialCurveFitter.maxIter:I (0, 0)
	118 invokevirtual (0, 0)
	119 org/apache/commons/math3/fitting/leastsquares/LeastSquaresBuilder.maxIterations:(I)Lorg/apache/commons/math3/fitting/leastsquares/LeastSquaresBuilder; (0, 0)
	121 aload_0 (0, 0)
	122 getfield (0, 0)
	123 org/apache/commons/math3/fitting/PolynomialCurveFitter.initialGuess:[D (0, 0)
	125 invokevirtual (0, 0)
	126 org/apache/commons/math3/fitting/leastsquares/LeastSquaresBuilder.start:([D)Lorg/apache/commons/math3/fitting/leastsquares/LeastSquaresBuilder; (0, 0)
	128 aload_3 (0, 0)
	129 invokevirtual (0, 0)
	130 org/apache/commons/math3/fitting/leastsquares/LeastSquaresBuilder.target:([D)Lorg/apache/commons/math3/fitting/leastsquares/LeastSquaresBuilder; (0, 0)
	132 new (0, 0)
	133 org/apache/commons/math3/linear/DiagonalMatrix (0, 0)
	135 dup (0, 0)
	136 aload (0, 0)
	137 #4 (0, 0)
	138 invokespecial (0, 0)
	139 org/apache/commons/math3/linear/DiagonalMatrix.<init>:([D)V (0, 0)
	141 invokevirtual (0, 0)
	142 org/apache/commons/math3/fitting/leastsquares/LeastSquaresBuilder.weight:(Lorg/apache/commons/math3/linear/RealMatrix;)Lorg/apache/commons/math3/fitting/leastsquares/LeastSquaresBuilder; (0, 0)
	144 aload (0, 0)
	145 #6 (0, 0)
	146 invokevirtual (0, 0)
	147 org/apache/commons/math3/fitting/AbstractCurveFitter$TheoreticalValuesFunction.getModelFunction:()Lorg/apache/commons/math3/analysis/MultivariateVectorFunction; (0, 0)
	149 aload (0, 0)
	150 #6 (0, 0)
	151 invokevirtual (0, 0)
	152 org/apache/commons/math3/fitting/AbstractCurveFitter$TheoreticalValuesFunction.getModelFunctionJacobian:()Lorg/apache/commons/math3/analysis/MultivariateMatrixFunction; (0, 0)
	154 invokevirtual (0, 0)
	155 org/apache/commons/math3/fitting/leastsquares/LeastSquaresBuilder.model:(Lorg/apache/commons/math3/analysis/MultivariateVectorFunction;Lorg/apache/commons/math3/analysis/MultivariateMatrixFunction;)Lorg/apache/commons/math3/fitting/leastsquares/LeastSquaresBuilder; (0, 0)
	157 invokevirtual (0, 0)
	158 org/apache/commons/math3/fitting/leastsquares/LeastSquaresBuilder.build:()Lorg/apache/commons/math3/fitting/leastsquares/LeastSquaresProblem; (0, 0)
	160 areturn (0, 0)

Method: <clinit>
	0 new (0, 0)
	1 org/apache/commons/math3/analysis/polynomials/PolynomialFunction$Parametric (0, 0)
	3 dup (0, 0)
	4 invokespecial (0, 0)
	5 org/apache/commons/math3/analysis/polynomials/PolynomialFunction$Parametric.<init>:()V (0, 0)
	7 putstatic (0, 0)
	8 org/apache/commons/math3/fitting/PolynomialCurveFitter.FUNCTION:Lorg/apache/commons/math3/analysis/polynomials/PolynomialFunction$Parametric; (0, 0)
	10 return (0, 0)

