Method: <init>
	0 aload_0 (0, 0)
	1 invokespecial (0, 0)
	2 java/lang/Object.<init>:()V (0, 0)
	4 iload_1 (2, 1)
	5 iconst_2 (2, 1)
	6 if_icmpge (2, 1)
	7 20 (2, 1)
	9 new (2, 1)
	10 org/apache/commons/math3/exception/NumberIsTooSmallException (2, 1)
	12 dup (2, 1)
	13 iload_1 (2, 1)
	14 invokestatic (2, 1)
	15 java/lang/Integer.valueOf:(I)Ljava/lang/Integer; (2, 1)
	17 iconst_2 (2, 1)
	18 invokestatic (2, 1)
	19 java/lang/Integer.valueOf:(I)Ljava/lang/Integer; (2, 1)
	21 iconst_1 (2, 1)
	22 invokespecial (2, 1)
	23 org/apache/commons/math3/exception/NumberIsTooSmallException.<init>:(Ljava/lang/Number;Ljava/lang/Number;Z)V (2, 1)
	25 athrow (2, 1)
	26 aload_0 (0, 0)
	27 iload_1 (0, 0)
	28 putfield (0, 0)
	29 org/apache/commons/math3/ml/neuralnet/oned/NeuronString.size:I (0, 0)
	31 aload_0 (0, 0)
	32 iload_2 (0, 0)
	33 putfield (0, 0)
	34 org/apache/commons/math3/ml/neuralnet/oned/NeuronString.wrap:Z (0, 0)
	36 aload_0 (1, 1)
	37 iload_1 (1, 1)
	38 newarray (1, 1)
	39 11 (1, 1)
	40 putfield (1, 1)
	41 org/apache/commons/math3/ml/neuralnet/oned/NeuronString.identifiers:[J (1, 1)
	43 aload_3 (1, 1)
	44 arraylength (1, 1)
	45 istore (1, 1)
	46 #4 (1, 1)
	47 aload_0 (1, 1)
	48 new (1, 1)
	49 org/apache/commons/math3/ml/neuralnet/Network (1, 1)
	51 dup (1, 1)
	52 lconst_0 (1, 1)
	53 iload (1, 1)
	54 #4 (1, 1)
	55 invokespecial (1, 1)
	56 org/apache/commons/math3/ml/neuralnet/Network.<init>:(JI)V (1, 1)
	58 putfield (1, 1)
	59 org/apache/commons/math3/ml/neuralnet/oned/NeuronString.network:Lorg/apache/commons/math3/ml/neuralnet/Network; (1, 1)
	61 iconst_0 (2, 4)
	62 istore (2, 4)
	63 #5 (2, 4)
	64 iload (2, 4)
	65 #5 (2, 4)
	66 iload_1 (2, 4)
	67 if_icmpge (2, 4)
	68 61 (2, 4)
	70 iload (2, 4)
	71 #4 (2, 4)
	72 newarray (2, 4)
	73 7 (2, 4)
	74 astore (2, 4)
	75 #6 (2, 4)
	76 iconst_0 (3, 4)
	77 istore (3, 4)
	78 #7 (3, 4)
	79 iload (3, 4)
	80 #7 (3, 4)
	81 iload (3, 4)
	82 #4 (3, 4)
	83 if_icmpge (3, 4)
	84 23 (3, 4)
	86 aload (3, 4)
	87 #6 (3, 4)
	88 iload (3, 4)
	89 #7 (3, 4)
	90 aload_3 (3, 4)
	91 iload (3, 4)
	92 #7 (3, 4)
	93 aaload (3, 4)
	94 invokeinterface (3, 4)
	95 org/apache/commons/math3/ml/neuralnet/FeatureInitializer.org/apache/commons/math3/exception/OutOfRangeException (3, 4)
	97 0 (3, 4)
	99 dastore (3, 4)
	100 iinc (3, 4)
	101 #7 (3, 4)
	102 -89 (3, 4)
	103 goto (3, 4)
	104 -24 (3, 4)
	106 aload_0 (2, 1)
	107 getfield (2, 1)
	108 org/apache/commons/math3/ml/neuralnet/oned/NeuronString.identifiers:[J (2, 1)
	110 iload (2, 1)
	111 #5 (2, 1)
	112 aload_0 (2, 1)
	113 getfield (2, 1)
	114 org/apache/commons/math3/ml/neuralnet/oned/NeuronString.network:Lorg/apache/commons/math3/ml/neuralnet/Network; (2, 1)
	116 aload (2, 1)
	117 #6 (2, 1)
	118 invokevirtual (2, 1)
	119 org/apache/commons/math3/ml/neuralnet/Network.createNeuron:([D)J (2, 1)
	121 lastore (2, 1)
	122 iinc (2, 1)
	123 #5 (2, 1)
	124 -89 (2, 1)
	125 goto (2, 1)
	126 -61 (2, 1)
	128 aload_0 (1, 1)
	129 invokespecial (1, 1)
	130 org/apache/commons/math3/ml/neuralnet/oned/NeuronString.createLinks:()V (1, 1)
	132 return (0, 0)

Method: getNetwork
	0 aload_0 (0, 0)
	1 getfield (0, 0)
	2 org/apache/commons/math3/ml/neuralnet/oned/NeuronString.network:Lorg/apache/commons/math3/ml/neuralnet/Network; (0, 0)
	4 areturn (0, 0)

Method: getSize
	0 aload_0 (0, 0)
	1 getfield (0, 0)
	2 org/apache/commons/math3/ml/neuralnet/oned/NeuronString.size:I (0, 0)
	4 ireturn (0, 0)

Method: getFeatures
	0 iload_1 (0, 1)
	1 iflt (0, 1)
	2 11 (0, 1)
	4 iload_1 (0, 1)
	5 aload_0 (0, 1)
	6 getfield (0, 1)
	7 org/apache/commons/math3/ml/neuralnet/oned/NeuronString.size:I (0, 1)
	9 if_icmplt (0, 1)
	10 28 (0, 1)
	12 new (0, 1)
	13 org/apache/commons/math3/exception/OutOfRangeException (0, 1)
	15 dup (0, 1)
	16 iload_1 (0, 1)
	17 invokestatic (0, 1)
	18 java/lang/Integer.valueOf:(I)Ljava/lang/Integer; (0, 1)
	20 iconst_0 (0, 1)
	21 invokestatic (0, 1)
	22 java/lang/Integer.valueOf:(I)Ljava/lang/Integer; (0, 1)
	24 aload_0 (0, 1)
	25 getfield (0, 1)
	26 org/apache/commons/math3/ml/neuralnet/oned/NeuronString.size:I (0, 1)
	28 iconst_1 (0, 1)
	29 isub (0, 1)
	30 invokestatic (0, 1)
	31 java/lang/Integer.valueOf:(I)Ljava/lang/Integer; (0, 1)
	33 invokespecial (0, 1)
	34 org/apache/commons/math3/exception/OutOfRangeException.<init>:(Ljava/lang/Number;Ljava/lang/Number;Ljava/lang/Number;)V (0, 1)
	36 athrow (0, 1)
	37 aload_0 (0, 1)
	38 getfield (0, 1)
	39 org/apache/commons/math3/ml/neuralnet/oned/NeuronString.network:Lorg/apache/commons/math3/ml/neuralnet/Network; (0, 1)
	41 aload_0 (0, 1)
	42 getfield (0, 1)
	43 org/apache/commons/math3/ml/neuralnet/oned/NeuronString.identifiers:[J (0, 1)
	45 iload_1 (0, 1)
	46 laload (0, 1)
	47 invokevirtual (0, 1)
	48 org/apache/commons/math3/ml/neuralnet/Network.getNeuron:(J)Lorg/apache/commons/math3/ml/neuralnet/Neuron; (0, 1)
	50 invokevirtual (0, 1)
	51 org/apache/commons/math3/ml/neuralnet/Neuron.getFeatures:()[D (0, 1)
	53 areturn (0, 1)

Method: createLinks
	0 iconst_0 (1, 4)
	1 istore_1 (1, 4)
	2 iload_1 (1, 4)
	3 aload_0 (1, 4)
	4 getfield (1, 4)
	5 org/apache/commons/math3/ml/neuralnet/oned/NeuronString.size:I (1, 4)
	7 iconst_1 (1, 4)
	8 isub (1, 4)
	9 if_icmpge (1, 4)
	10 36 (1, 4)
	12 aload_0 (1, 4)
	13 getfield (1, 4)
	14 org/apache/commons/math3/ml/neuralnet/oned/NeuronString.network:Lorg/apache/commons/math3/ml/neuralnet/Network; (1, 4)
	16 aload_0 (1, 4)
	17 getfield (1, 4)
	18 org/apache/commons/math3/ml/neuralnet/oned/NeuronString.network:Lorg/apache/commons/math3/ml/neuralnet/Network; (1, 4)
	20 iload_1 (1, 4)
	21 i2l (1, 4)
	22 invokevirtual (1, 4)
	23 org/apache/commons/math3/ml/neuralnet/Network.getNeuron:(J)Lorg/apache/commons/math3/ml/neuralnet/Neuron; (1, 4)
	25 aload_0 (1, 4)
	26 getfield (1, 4)
	27 org/apache/commons/math3/ml/neuralnet/oned/NeuronString.network:Lorg/apache/commons/math3/ml/neuralnet/Network; (1, 4)
	29 iload_1 (1, 4)
	30 iconst_1 (1, 4)
	31 iadd (1, 4)
	32 i2l (1, 4)
	33 invokevirtual (1, 4)
	34 org/apache/commons/math3/ml/neuralnet/Network.getNeuron:(J)Lorg/apache/commons/math3/ml/neuralnet/Neuron; (1, 4)
	36 invokevirtual (1, 4)
	37 org/apache/commons/math3/ml/neuralnet/Network.addLink:(Lorg/apache/commons/math3/ml/neuralnet/Neuron;Lorg/apache/commons/math3/ml/neuralnet/Neuron;)V (1, 4)
	39 iinc (1, 4)
	40 #1 (1, 4)
	41 -89 (1, 4)
	42 goto (1, 4)
	43 -40 (1, 4)
	45 aload_0 (1, 4)
	46 getfield (1, 4)
	47 org/apache/commons/math3/ml/neuralnet/oned/NeuronString.size:I (1, 4)
	49 iconst_1 (1, 4)
	50 isub (1, 4)
	51 istore_1 (1, 4)
	52 iload_1 (1, 4)
	53 ifle (1, 4)
	54 36 (1, 4)
	56 aload_0 (1, 4)
	57 getfield (1, 4)
	58 org/apache/commons/math3/ml/neuralnet/oned/NeuronString.network:Lorg/apache/commons/math3/ml/neuralnet/Network; (1, 4)
	60 aload_0 (1, 4)
	61 getfield (1, 4)
	62 org/apache/commons/math3/ml/neuralnet/oned/NeuronString.network:Lorg/apache/commons/math3/ml/neuralnet/Network; (1, 4)
	64 iload_1 (1, 4)
	65 i2l (1, 4)
	66 invokevirtual (1, 4)
	67 org/apache/commons/math3/ml/neuralnet/Network.getNeuron:(J)Lorg/apache/commons/math3/ml/neuralnet/Neuron; (1, 4)
	69 aload_0 (1, 4)
	70 getfield (1, 4)
	71 org/apache/commons/math3/ml/neuralnet/oned/NeuronString.network:Lorg/apache/commons/math3/ml/neuralnet/Network; (1, 4)
	73 iload_1 (1, 4)
	74 iconst_1 (1, 4)
	75 isub (1, 4)
	76 i2l (1, 4)
	77 invokevirtual (1, 4)
	78 org/apache/commons/math3/ml/neuralnet/Network.getNeuron:(J)Lorg/apache/commons/math3/ml/neuralnet/Neuron; (1, 4)
	80 invokevirtual (1, 4)
	81 org/apache/commons/math3/ml/neuralnet/Network.addLink:(Lorg/apache/commons/math3/ml/neuralnet/Neuron;Lorg/apache/commons/math3/ml/neuralnet/Neuron;)V (1, 4)
	83 iinc (1, 4)
	84 #1 (1, 4)
	85 -89 (1, 4)
	86 goto (1, 4)
	87 -34 (1, 4)
	89 aload_0 (1, 1)
	90 getfield (1, 1)
	91 org/apache/commons/math3/ml/neuralnet/oned/NeuronString.wrap:Z (1, 1)
	93 ifeq (1, 1)
	94 61 (1, 1)
	96 aload_0 (1, 1)
	97 getfield (1, 1)
	98 org/apache/commons/math3/ml/neuralnet/oned/NeuronString.network:Lorg/apache/commons/math3/ml/neuralnet/Network; (1, 1)
	100 aload_0 (1, 1)
	101 getfield (1, 1)
	102 org/apache/commons/math3/ml/neuralnet/oned/NeuronString.network:Lorg/apache/commons/math3/ml/neuralnet/Network; (1, 1)
	104 lconst_0 (1, 1)
	105 invokevirtual (1, 1)
	106 org/apache/commons/math3/ml/neuralnet/Network.getNeuron:(J)Lorg/apache/commons/math3/ml/neuralnet/Neuron; (1, 1)
	108 aload_0 (1, 1)
	109 getfield (1, 1)
	110 org/apache/commons/math3/ml/neuralnet/oned/NeuronString.network:Lorg/apache/commons/math3/ml/neuralnet/Network; (1, 1)
	112 aload_0 (1, 1)
	113 getfield (1, 1)
	114 org/apache/commons/math3/ml/neuralnet/oned/NeuronString.size:I (1, 1)
	116 iconst_1 (1, 1)
	117 isub (1, 1)
	118 i2l (1, 1)
	119 invokevirtual (1, 1)
	120 org/apache/commons/math3/ml/neuralnet/Network.getNeuron:(J)Lorg/apache/commons/math3/ml/neuralnet/Neuron; (1, 1)
	122 invokevirtual (1, 1)
	123 org/apache/commons/math3/ml/neuralnet/Network.addLink:(Lorg/apache/commons/math3/ml/neuralnet/Neuron;Lorg/apache/commons/math3/ml/neuralnet/Neuron;)V (1, 1)
	125 aload_0 (1, 1)
	126 getfield (1, 1)
	127 org/apache/commons/math3/ml/neuralnet/oned/NeuronString.network:Lorg/apache/commons/math3/ml/neuralnet/Network; (1, 1)
	129 aload_0 (1, 1)
	130 getfield (1, 1)
	131 org/apache/commons/math3/ml/neuralnet/oned/NeuronString.network:Lorg/apache/commons/math3/ml/neuralnet/Network; (1, 1)
	133 aload_0 (1, 1)
	134 getfield (1, 1)
	135 org/apache/commons/math3/ml/neuralnet/oned/NeuronString.size:I (1, 1)
	137 iconst_1 (1, 1)
	138 isub (1, 1)
	139 i2l (1, 1)
	140 invokevirtual (1, 1)
	141 org/apache/commons/math3/ml/neuralnet/Network.getNeuron:(J)Lorg/apache/commons/math3/ml/neuralnet/Neuron; (1, 1)
	143 aload_0 (1, 1)
	144 getfield (1, 1)
	145 org/apache/commons/math3/ml/neuralnet/oned/NeuronString.network:Lorg/apache/commons/math3/ml/neuralnet/Network; (1, 1)
	147 lconst_0 (1, 1)
	148 invokevirtual (1, 1)
	149 org/apache/commons/math3/ml/neuralnet/Network.getNeuron:(J)Lorg/apache/commons/math3/ml/neuralnet/Neuron; (1, 1)
	151 invokevirtual (1, 1)
	152 org/apache/commons/math3/ml/neuralnet/Network.addLink:(Lorg/apache/commons/math3/ml/neuralnet/Neuron;Lorg/apache/commons/math3/ml/neuralnet/Neuron;)V (1, 1)
	154 return (0, 0)

Method: readObject
	0 new (0, 0)
	1 java/lang/IllegalStateException (0, 0)
	3 dup (0, 0)
	4 invokespecial (0, 0)
	5 java/lang/IllegalStateException.<init>:()V (0, 0)
	7 athrow (0, 0)

Method: writeReplace
	0 aload_0 (0, 0)
	1 getfield (0, 0)
	2 org/apache/commons/math3/ml/neuralnet/oned/NeuronString.size:I (0, 0)
	4 anewarray (0, 0)
	5 [D (0, 0)
	7 astore_1 (0, 0)
	8 iconst_0 (1, 4)
	9 istore_2 (1, 4)
	10 iload_2 (1, 4)
	11 aload_0 (1, 4)
	12 getfield (1, 4)
	13 org/apache/commons/math3/ml/neuralnet/oned/NeuronString.size:I (1, 4)
	15 if_icmpge (1, 4)
	16 17 (1, 4)
	18 aload_1 (1, 4)
	19 iload_2 (1, 4)
	20 aload_0 (1, 4)
	21 iload_2 (1, 4)
	22 invokevirtual (1, 4)
	23 org/apache/commons/math3/ml/neuralnet/oned/NeuronString.getFeatures:(I)[D (1, 4)
	25 aastore (1, 4)
	26 iinc (1, 4)
	27 #2 (1, 4)
	28 -89 (1, 4)
	29 goto (1, 4)
	30 -19 (1, 4)
	32 new (0, 0)
	33 org/apache/commons/math3/ml/neuralnet/oned/NeuronString$SerializationProxy (0, 0)
	35 dup (0, 0)
	36 aload_0 (0, 0)
	37 getfield (0, 0)
	38 org/apache/commons/math3/ml/neuralnet/oned/NeuronString.wrap:Z (0, 0)
	40 aload_1 (0, 0)
	41 invokespecial (0, 0)
	42 org/apache/commons/math3/ml/neuralnet/oned/NeuronString$SerializationProxy.<init>:(Z[[D)V (0, 0)
	44 areturn (0, 0)

