Method: <init>
	0 aload_0 (0, 0)
	1 invokespecial (0, 0)
	2 java/lang/Object.<init>:()V (0, 0)
	4 dload_1 (2, 1)
	5 dconst_0 (2, 1)
	6 dcmpg (2, 1)
	7 ifgt (2, 1)
	8 15 (2, 1)
	10 new (2, 1)
	11 org/apache/commons/math3/exception/NotStrictlyPositiveException (2, 1)
	13 dup (2, 1)
	14 dload_1 (2, 1)
	15 invokestatic (2, 1)
	16 java/lang/Double.valueOf:(D)Ljava/lang/Double; (2, 1)
	18 invokespecial (2, 1)
	19 org/apache/commons/math3/exception/NotStrictlyPositiveException.<init>:(Ljava/lang/Number;)V (2, 1)
	21 athrow (2, 1)
	22 dload_3 (2, 1)
	23 dconst_0 (2, 1)
	24 dcmpl (2, 1)
	25 iflt (2, 1)
	26 20 (2, 1)
	28 new (2, 1)
	29 org/apache/commons/math3/exception/NumberIsTooLargeException (2, 1)
	31 dup (2, 1)
	32 dload_3 (2, 1)
	33 invokestatic (2, 1)
	34 java/lang/Double.valueOf:(D)Ljava/lang/Double; (2, 1)
	36 iconst_0 (2, 1)
	37 invokestatic (2, 1)
	38 java/lang/Integer.valueOf:(I)Ljava/lang/Integer; (2, 1)
	40 iconst_0 (2, 1)
	41 invokespecial (2, 1)
	42 org/apache/commons/math3/exception/NumberIsTooLargeException.<init>:(Ljava/lang/Number;Ljava/lang/Number;Z)V (2, 1)
	44 athrow (2, 1)
	45 lload (2, 1)
	46 #5 (2, 1)
	47 lconst_1 (2, 1)
	48 lcmp (2, 1)
	49 ifgt (2, 1)
	50 16 (2, 1)
	52 new (2, 1)
	53 org/apache/commons/math3/exception/NotStrictlyPositiveException (2, 1)
	55 dup (2, 1)
	56 lload (2, 1)
	57 #5 (2, 1)
	58 invokestatic (2, 1)
	59 java/lang/Long.valueOf:(J)Ljava/lang/Long; (2, 1)
	61 invokespecial (2, 1)
	62 org/apache/commons/math3/exception/NotStrictlyPositiveException.<init>:(Ljava/lang/Number;)V (2, 1)
	64 athrow (2, 1)
	65 dload_1 (0, 0)
	66 dstore (0, 0)
	67 #7 (0, 0)
	68 lload (0, 0)
	69 #5 (0, 0)
	70 l2d (0, 0)
	71 dstore (0, 0)
	72 #9 (0, 0)
	73 ldc2_w (0, 0)
	74 4.0 (0, 0)
	76 dload_3 (0, 0)
	77 dmul (0, 0)
	78 dload_1 (0, 0)
	79 ddiv (0, 0)
	80 dstore (0, 0)
	81 #11 (0, 0)
	82 dconst_1 (0, 0)
	83 dstore (0, 0)
	84 #13 (0, 0)
	85 dconst_0 (0, 0)
	86 dstore (0, 0)
	87 #15 (0, 0)
	88 dconst_1 (0, 0)
	89 dstore (0, 0)
	90 #17 (0, 0)
	91 aload_0 (0, 0)
	92 new (0, 0)
	93 org/apache/commons/math3/analysis/function/Logistic (0, 0)
	95 dup (0, 0)
	96 dload (0, 0)
	97 #7 (0, 0)
	98 dload (0, 0)
	99 #9 (0, 0)
	100 dload (0, 0)
	101 #11 (0, 0)
	102 dconst_1 (0, 0)
	103 dconst_0 (0, 0)
	104 dconst_1 (0, 0)
	105 invokespecial (0, 0)
	106 org/apache/commons/math3/analysis/function/Logistic.<init>:(DDDDDD)V (0, 0)
	108 putfield (0, 0)
	109 org/apache/commons/math3/ml/neuralnet/sofm/util/QuasiSigmoidDecayFunction.sigmoid:Lorg/apache/commons/math3/analysis/function/Logistic; (0, 0)
	111 aload_0 (0, 0)
	112 getfield (0, 0)
	113 org/apache/commons/math3/ml/neuralnet/sofm/util/QuasiSigmoidDecayFunction.sigmoid:Lorg/apache/commons/math3/analysis/function/Logistic; (0, 0)
	115 dconst_0 (0, 0)
	116 invokevirtual (0, 0)
	117 org/apache/commons/math3/analysis/function/Logistic.value:(D)D (0, 0)
	119 dstore (0, 0)
	120 #19 (0, 0)
	121 aload_0 (0, 0)
	122 dload (0, 0)
	123 #7 (0, 0)
	124 dload (0, 0)
	125 #19 (0, 0)
	126 ddiv (0, 0)
	127 putfield (0, 0)
	128 org/apache/commons/math3/ml/neuralnet/sofm/util/QuasiSigmoidDecayFunction.scale:D (0, 0)
	130 return (0, 0)

Method: value
	0 aload_0 (0, 0)
	1 getfield (0, 0)
	2 org/apache/commons/math3/ml/neuralnet/sofm/util/QuasiSigmoidDecayFunction.scale:D (0, 0)
	4 aload_0 (0, 0)
	5 getfield (0, 0)
	6 org/apache/commons/math3/ml/neuralnet/sofm/util/QuasiSigmoidDecayFunction.sigmoid:Lorg/apache/commons/math3/analysis/function/Logistic; (0, 0)
	8 lload_1 (0, 0)
	9 l2d (0, 0)
	10 invokevirtual (0, 0)
	11 org/apache/commons/math3/analysis/function/Logistic.value:(D)D (0, 0)
	13 dmul (0, 0)
	14 dreturn (0, 0)

