Method: <init>
	0 aload_0 (0, 0)
	1 invokespecial (0, 0)
	2 org/apache/commons/math3/stat/descriptive/AbstractStorelessUnivariateStatistic.<init>:()V (0, 0)
	4 aload_0 (0, 0)
	5 aload_1 (0, 0)
	6 putfield (0, 0)
	7 org/apache/commons/math3/stat/descriptive/moment/GeometricMean.sumOfLogs:Lorg/apache/commons/math3/stat/descriptive/StorelessUnivariateStatistic; (0, 0)
	9 return (0, 0)

Method: copy
	0 aload_0 (0, 0)
	1 invokevirtual (0, 0)
	2 org/apache/commons/math3/stat/descriptive/moment/GeometricMean.copy:()Lorg/apache/commons/math3/stat/descriptive/moment/GeometricMean; (0, 0)
	4 areturn (0, 0)

Method: increment
	0 aload_0 (0, 0)
	1 getfield (0, 0)
	2 org/apache/commons/math3/stat/descriptive/moment/GeometricMean.sumOfLogs:Lorg/apache/commons/math3/stat/descriptive/StorelessUnivariateStatistic; (0, 0)
	4 dload_1 (0, 0)
	5 invokeinterface (0, 0)
	6 org/apache/commons/math3/stat/descriptive/StorelessUnivariateStatistic.getN:()J (0, 0)
	8 0 (0, 0)
	10 return (0, 0)

Method: getResult
	0 aload_0 (1, 1)
	1 getfield (1, 1)
	2 org/apache/commons/math3/stat/descriptive/moment/GeometricMean.sumOfLogs:Lorg/apache/commons/math3/stat/descriptive/StorelessUnivariateStatistic; (1, 1)
	4 invokeinterface (1, 1)
	5 org/apache/commons/math3/stat/descriptive/StorelessUnivariateStatistic.getResult:()D (1, 1)
	7 0 (1, 1)
	9 lconst_0 (1, 1)
	10 lcmp (1, 1)
	11 ifle (1, 1)
	12 27 (1, 1)
	14 aload_0 (1, 1)
	15 getfield (1, 1)
	16 org/apache/commons/math3/stat/descriptive/moment/GeometricMean.sumOfLogs:Lorg/apache/commons/math3/stat/descriptive/StorelessUnivariateStatistic; (1, 1)
	18 invokeinterface (1, 1)
	19 org/apache/commons/math3/stat/descriptive/StorelessUnivariateStatistic.org/apache/commons/math3/util/FastMath (1, 1)
	21 0 (1, 1)
	23 aload_0 (1, 1)
	24 getfield (1, 1)
	25 org/apache/commons/math3/stat/descriptive/moment/GeometricMean.sumOfLogs:Lorg/apache/commons/math3/stat/descriptive/StorelessUnivariateStatistic; (1, 1)
	27 invokeinterface (1, 1)
	28 org/apache/commons/math3/stat/descriptive/StorelessUnivariateStatistic.getResult:()D (1, 1)
	30 0 (1, 1)
	32 l2d (1, 1)
	33 ddiv (1, 1)
	34 invokestatic (1, 1)
	35 org/apache/commons/math3/util/FastMath.exp:(D)D (1, 1)
	37 dreturn (1, 1)
	38 ldc2_w (2, 2)
	39 nan (2, 2)
	41 dreturn (1, 2)

Method: clear
	0 aload_0 (0, 0)
	1 getfield (0, 0)
	2 org/apache/commons/math3/stat/descriptive/moment/GeometricMean.sumOfLogs:Lorg/apache/commons/math3/stat/descriptive/StorelessUnivariateStatistic; (0, 0)
	4 invokeinterface (0, 0)
	5 org/apache/commons/math3/stat/descriptive/StorelessUnivariateStatistic.evaluate:([DII)D (0, 0)
	7 0 (0, 0)
	9 return (0, 0)

Method: evaluate
	0 aload_0 (0, 0)
	1 getfield (0, 0)
	2 org/apache/commons/math3/stat/descriptive/moment/GeometricMean.sumOfLogs:Lorg/apache/commons/math3/stat/descriptive/StorelessUnivariateStatistic; (0, 0)
	4 aload_1 (0, 0)
	5 iload_2 (0, 0)
	6 iload_3 (0, 0)
	7 invokeinterface (0, 0)
	8 org/apache/commons/math3/stat/descriptive/StorelessUnivariateStatistic.checkEmpty:()V (0, 0)
	10 0 (0, 0)
	12 iload_3 (0, 0)
	13 i2d (0, 0)
	14 ddiv (0, 0)
	15 invokestatic (0, 0)
	16 org/apache/commons/math3/util/FastMath.exp:(D)D (0, 0)
	18 dreturn (0, 0)

Method: getN
	0 aload_0 (0, 0)
	1 getfield (0, 0)
	2 org/apache/commons/math3/stat/descriptive/moment/GeometricMean.sumOfLogs:Lorg/apache/commons/math3/stat/descriptive/StorelessUnivariateStatistic; (0, 0)
	4 invokeinterface (0, 0)
	5 org/apache/commons/math3/stat/descriptive/StorelessUnivariateStatistic.getResult:()D (0, 0)
	7 0 (0, 0)
	9 lreturn (0, 0)

Method: setSumLogImpl
	0 aload_0 (0, 0)
	1 invokespecial (0, 0)
	2 org/apache/commons/math3/stat/descriptive/moment/GeometricMean.checkEmpty:()V (0, 0)
	4 aload_0 (0, 0)
	5 aload_1 (0, 0)
	6 putfield (0, 0)
	7 org/apache/commons/math3/stat/descriptive/moment/GeometricMean.sumOfLogs:Lorg/apache/commons/math3/stat/descriptive/StorelessUnivariateStatistic; (0, 0)
	9 return (0, 0)

Method: getSumLogImpl
	0 aload_0 (0, 0)
	1 getfield (0, 0)
	2 org/apache/commons/math3/stat/descriptive/moment/GeometricMean.sumOfLogs:Lorg/apache/commons/math3/stat/descriptive/StorelessUnivariateStatistic; (0, 0)
	4 areturn (0, 0)

Method: checkEmpty
	0 aload_0 (1, 1)
	1 invokevirtual (1, 1)
	2 org/apache/commons/math3/stat/descriptive/moment/GeometricMean.getN:()J (1, 1)
	4 lconst_0 (1, 1)
	5 lcmp (1, 1)
	6 ifle (1, 1)
	7 28 (1, 1)
	9 new (1, 1)
	10 org/apache/commons/math3/exception/MathIllegalStateException (1, 1)
	12 dup (1, 1)
	13 getstatic (1, 1)
	14 org/apache/commons/math3/exception/util/LocalizedFormats.VALUES_ADDED_BEFORE_CONFIGURING_STATISTIC:Lorg/apache/commons/math3/exception/util/LocalizedFormats; (1, 1)
	16 iconst_1 (1, 1)
	17 anewarray (1, 1)
	18 java/lang/Object (1, 1)
	20 dup (1, 1)
	21 iconst_0 (1, 1)
	22 aload_0 (1, 1)
	23 invokevirtual (1, 1)
	24 org/apache/commons/math3/stat/descriptive/moment/GeometricMean.getN:()J (1, 1)
	26 invokestatic (1, 1)
	27 java/lang/Long.valueOf:(J)Ljava/lang/Long; (1, 1)
	29 aastore (1, 1)
	30 invokespecial (1, 1)
	31 org/apache/commons/math3/exception/MathIllegalStateException.<init>:(Lorg/apache/commons/math3/exception/util/Localizable;[Ljava/lang/Object;)V (1, 1)
	33 athrow (1, 1)
	34 return (0, 0)

