Method: <init>
	0 aload_0 (0, 0)
	1 invokespecial (0, 0)
	2 org/apache/commons/math3/stat/descriptive/AbstractStorelessUnivariateStatistic.<init>:()V (0, 0)
	4 aload_1 (0, 0)
	5 aload_0 (0, 0)
	6 invokestatic (0, 0)
	7 org/apache/commons/math3/stat/descriptive/moment/Kurtosis.copy:(Lorg/apache/commons/math3/stat/descriptive/moment/Kurtosis;Lorg/apache/commons/math3/stat/descriptive/moment/Kurtosis;)V (0, 0)
	9 return (0, 0)

Method: increment
	0 aload_0 (1, 1)
	1 getfield (1, 1)
	2 org/apache/commons/math3/stat/descriptive/moment/Kurtosis.incMoment:Z (1, 1)
	4 ifeq (1, 1)
	5 11 (1, 1)
	7 aload_0 (1, 1)
	8 getfield (1, 1)
	9 org/apache/commons/math3/stat/descriptive/moment/Kurtosis.moment:Lorg/apache/commons/math3/stat/descriptive/moment/FourthMoment; (1, 1)
	11 dload_1 (1, 1)
	12 invokevirtual (1, 1)
	13 org/apache/commons/math3/stat/descriptive/moment/FourthMoment.increment:(D)V (1, 1)
	15 return (0, 0)

Method: getResult
	0 ldc2_w (0, 0)
	1 nan (0, 0)
	3 dstore_1 (0, 0)
	4 aload_0 (1, 1)
	5 getfield (1, 1)
	6 org/apache/commons/math3/stat/descriptive/moment/Kurtosis.moment:Lorg/apache/commons/math3/stat/descriptive/moment/FourthMoment; (1, 1)
	8 invokevirtual (1, 1)
	9 org/apache/commons/math3/stat/descriptive/moment/FourthMoment.getN:()J (1, 1)
	11 ldc2_w (1, 1)
	12 3 (1, 1)
	14 lcmp (1, 1)
	15 ifle (1, 1)
	16 123 (1, 1)
	18 aload_0 (1, 1)
	19 getfield (1, 1)
	20 org/apache/commons/math3/stat/descriptive/moment/Kurtosis.moment:Lorg/apache/commons/math3/stat/descriptive/moment/FourthMoment; (1, 1)
	22 getfield (1, 1)
	23 org/apache/commons/math3/stat/descriptive/moment/FourthMoment.m2:D (1, 1)
	25 aload_0 (1, 1)
	26 getfield (1, 1)
	27 org/apache/commons/math3/stat/descriptive/moment/Kurtosis.moment:Lorg/apache/commons/math3/stat/descriptive/moment/FourthMoment; (1, 1)
	29 getfield (1, 1)
	30 org/apache/commons/math3/stat/descriptive/moment/FourthMoment.n:J (1, 1)
	32 lconst_1 (1, 1)
	33 lsub (1, 1)
	34 l2d (1, 1)
	35 ddiv (1, 1)
	36 dstore_3 (1, 1)
	37 aload_0 (2, 1)
	38 getfield (2, 1)
	39 org/apache/commons/math3/stat/descriptive/moment/Kurtosis.moment:Lorg/apache/commons/math3/stat/descriptive/moment/FourthMoment; (2, 1)
	41 getfield (2, 1)
	42 org/apache/commons/math3/stat/descriptive/moment/FourthMoment.n:J (2, 1)
	44 ldc2_w (2, 1)
	45 3 (2, 1)
	47 lcmp (2, 1)
	48 ifle (2, 1)
	49 11 (2, 1)
	51 dload_3 (2, 1)
	52 ldc2_w (2, 1)
	53 1e-19 (2, 1)
	55 dcmpg (2, 1)
	56 ifge (2, 1)
	57 8 (2, 1)
	59 dconst_0 (2, 1)
	60 dstore_1 (2, 1)
	61 goto (2, 1)
	62 77 (2, 1)
	64 aload_0 (3, 2)
	65 getfield (3, 2)
	66 org/apache/commons/math3/stat/descriptive/moment/Kurtosis.moment:Lorg/apache/commons/math3/stat/descriptive/moment/FourthMoment; (3, 2)
	68 getfield (3, 2)
	69 org/apache/commons/math3/stat/descriptive/moment/FourthMoment.n:J (3, 2)
	71 l2d (3, 2)
	72 dstore (3, 2)
	73 #5 (3, 2)
	74 dload (3, 2)
	75 #5 (3, 2)
	76 dload (3, 2)
	77 #5 (3, 2)
	78 dconst_1 (3, 2)
	79 dadd (3, 2)
	80 dmul (3, 2)
	81 aload_0 (3, 2)
	82 getfield (3, 2)
	83 org/apache/commons/math3/stat/descriptive/moment/Kurtosis.moment:Lorg/apache/commons/math3/stat/descriptive/moment/FourthMoment; (3, 2)
	85 invokevirtual (3, 2)
	86 org/apache/commons/math3/stat/descriptive/moment/FourthMoment.getResult:()D (3, 2)
	88 dmul (3, 2)
	89 ldc2_w (3, 2)
	90 3.0 (3, 2)
	92 aload_0 (3, 2)
	93 getfield (3, 2)
	94 org/apache/commons/math3/stat/descriptive/moment/Kurtosis.moment:Lorg/apache/commons/math3/stat/descriptive/moment/FourthMoment; (3, 2)
	96 getfield (3, 2)
	97 org/apache/commons/math3/stat/descriptive/moment/FourthMoment.m2:D (3, 2)
	99 dmul (3, 2)
	100 aload_0 (3, 2)
	101 getfield (3, 2)
	102 org/apache/commons/math3/stat/descriptive/moment/Kurtosis.moment:Lorg/apache/commons/math3/stat/descriptive/moment/FourthMoment; (3, 2)
	104 getfield (3, 2)
	105 org/apache/commons/math3/stat/descriptive/moment/FourthMoment.m2:D (3, 2)
	107 dmul (3, 2)
	108 dload (3, 2)
	109 #5 (3, 2)
	110 dconst_1 (3, 2)
	111 dsub (3, 2)
	112 dmul (3, 2)
	113 dsub (3, 2)
	114 dload (3, 2)
	115 #5 (3, 2)
	116 dconst_1 (3, 2)
	117 dsub (3, 2)
	118 dload (3, 2)
	119 #5 (3, 2)
	120 ldc2_w (3, 2)
	121 2.0 (3, 2)
	123 dsub (3, 2)
	124 dmul (3, 2)
	125 dload (3, 2)
	126 #5 (3, 2)
	127 ldc2_w (3, 2)
	128 3.0 (3, 2)
	130 dsub (3, 2)
	131 dmul (3, 2)
	132 dload_3 (3, 2)
	133 dmul (3, 2)
	134 dload_3 (3, 2)
	135 dmul (3, 2)
	136 ddiv (3, 2)
	137 dstore_1 (3, 2)
	138 dload_1 (0, 0)
	139 dreturn (0, 0)

Method: clear
	0 aload_0 (1, 1)
	1 getfield (1, 1)
	2 org/apache/commons/math3/stat/descriptive/moment/Kurtosis.incMoment:Z (1, 1)
	4 ifeq (1, 1)
	5 10 (1, 1)
	7 aload_0 (1, 1)
	8 getfield (1, 1)
	9 org/apache/commons/math3/stat/descriptive/moment/Kurtosis.moment:Lorg/apache/commons/math3/stat/descriptive/moment/FourthMoment; (1, 1)
	11 invokevirtual (1, 1)
	12 org/apache/commons/math3/stat/descriptive/moment/FourthMoment.clear:()V (1, 1)
	14 return (0, 0)

Method: getN
	0 aload_0 (0, 0)
	1 getfield (0, 0)
	2 org/apache/commons/math3/stat/descriptive/moment/Kurtosis.moment:Lorg/apache/commons/math3/stat/descriptive/moment/FourthMoment; (0, 0)
	4 invokevirtual (0, 0)
	5 org/apache/commons/math3/stat/descriptive/moment/FourthMoment.getN:()J (0, 0)
	7 lreturn (0, 0)

Method: evaluate
	0 ldc2_w (0, 0)
	1 nan (0, 0)
	3 dstore (0, 0)
	4 #4 (0, 0)
	5 aload_0 (1, 1)
	6 aload_1 (1, 1)
	7 iload_2 (1, 1)
	8 iload_3 (1, 1)
	9 invokevirtual (1, 1)
	10 org/apache/commons/math3/stat/descriptive/moment/Kurtosis.test:([DII)Z (1, 1)
	12 ifeq (1, 1)
	13 168 (1, 1)
	15 iload_3 (1, 1)
	16 iconst_3 (1, 1)
	17 if_icmple (1, 1)
	18 163 (1, 1)
	20 new (1, 1)
	21 org/apache/commons/math3/stat/descriptive/moment/Variance (1, 1)
	23 dup (1, 1)
	24 invokespecial (1, 1)
	25 org/apache/commons/math3/stat/descriptive/moment/Variance.<init>:()V (1, 1)
	27 astore (1, 1)
	28 #6 (1, 1)
	29 aload (1, 1)
	30 #6 (1, 1)
	31 aload_1 (1, 1)
	32 iload_2 (1, 1)
	33 iload_3 (1, 1)
	34 invokevirtual (1, 1)
	35 org/apache/commons/math3/stat/descriptive/moment/Variance.incrementAll:([DII)V (1, 1)
	37 aload (1, 1)
	38 #6 (1, 1)
	39 getfield (1, 1)
	40 org/apache/commons/math3/stat/descriptive/moment/Variance.moment:Lorg/apache/commons/math3/stat/descriptive/moment/SecondMoment; (1, 1)
	42 getfield (1, 1)
	43 org/apache/commons/math3/stat/descriptive/moment/SecondMoment.m1:D (1, 1)
	45 dstore (1, 1)
	46 #7 (1, 1)
	47 aload (1, 1)
	48 #6 (1, 1)
	49 invokevirtual (1, 1)
	50 org/apache/commons/math3/stat/descriptive/moment/Variance.getResult:()D (1, 1)
	52 invokestatic (1, 1)
	53 org/apache/commons/math3/util/FastMath.sqrt:(D)D (1, 1)
	55 dstore (1, 1)
	56 #9 (1, 1)
	57 dconst_0 (1, 1)
	58 dstore (1, 1)
	59 #11 (1, 1)
	60 iload_2 (2, 4)
	61 istore (2, 4)
	62 #13 (2, 4)
	63 iload (2, 4)
	64 #13 (2, 4)
	65 iload_2 (2, 4)
	66 iload_3 (2, 4)
	67 iadd (2, 4)
	68 if_icmpge (2, 4)
	69 27 (2, 4)
	71 dload (2, 4)
	72 #11 (2, 4)
	73 aload_1 (2, 4)
	74 iload (2, 4)
	75 #13 (2, 4)
	76 daload (2, 4)
	77 dload (2, 4)
	78 #7 (2, 4)
	79 dsub (2, 4)
	80 ldc2_w (2, 4)
	81 4.0 (2, 4)
	83 invokestatic (2, 4)
	84 org/apache/commons/math3/util/FastMath.pow:(DD)D (2, 4)
	86 dadd (2, 4)
	87 dstore (2, 4)
	88 #11 (2, 4)
	89 iinc (2, 4)
	90 #13 (2, 4)
	91 -89 (2, 4)
	92 goto (2, 4)
	93 -29 (2, 4)
	95 dload (1, 1)
	96 #11 (1, 1)
	97 dload (1, 1)
	98 #9 (1, 1)
	99 ldc2_w (1, 1)
	100 4.0 (1, 1)
	102 invokestatic (1, 1)
	103 org/apache/commons/math3/util/FastMath.pow:(DD)D (1, 1)
	105 ddiv (1, 1)
	106 dstore (1, 1)
	107 #11 (1, 1)
	108 iload_3 (1, 1)
	109 i2d (1, 1)
	110 dstore (1, 1)
	111 #13 (1, 1)
	112 dload (1, 1)
	113 #13 (1, 1)
	114 dload (1, 1)
	115 #13 (1, 1)
	116 dconst_1 (1, 1)
	117 dadd (1, 1)
	118 dmul (1, 1)
	119 dload (1, 1)
	120 #13 (1, 1)
	121 dconst_1 (1, 1)
	122 dsub (1, 1)
	123 dload (1, 1)
	124 #13 (1, 1)
	125 ldc2_w (1, 1)
	126 2.0 (1, 1)
	128 dsub (1, 1)
	129 dmul (1, 1)
	130 dload (1, 1)
	131 #13 (1, 1)
	132 ldc2_w (1, 1)
	133 3.0 (1, 1)
	135 dsub (1, 1)
	136 dmul (1, 1)
	137 ddiv (1, 1)
	138 dstore (1, 1)
	139 #15 (1, 1)
	140 ldc2_w (1, 1)
	141 3.0 (1, 1)
	143 dload (1, 1)
	144 #13 (1, 1)
	145 dconst_1 (1, 1)
	146 dsub (1, 1)
	147 ldc2_w (1, 1)
	148 2.0 (1, 1)
	150 invokestatic (1, 1)
	151 org/apache/commons/math3/util/FastMath.pow:(DD)D (1, 1)
	153 dmul (1, 1)
	154 dload (1, 1)
	155 #13 (1, 1)
	156 ldc2_w (1, 1)
	157 2.0 (1, 1)
	159 dsub (1, 1)
	160 dload (1, 1)
	161 #13 (1, 1)
	162 ldc2_w (1, 1)
	163 3.0 (1, 1)
	165 dsub (1, 1)
	166 dmul (1, 1)
	167 ddiv (1, 1)
	168 dstore (1, 1)
	169 #17 (1, 1)
	170 dload (1, 1)
	171 #15 (1, 1)
	172 dload (1, 1)
	173 #11 (1, 1)
	174 dmul (1, 1)
	175 dload (1, 1)
	176 #17 (1, 1)
	177 dsub (1, 1)
	178 dstore (1, 1)
	179 #4 (1, 1)
	180 dload (0, 0)
	181 #4 (0, 0)
	182 dreturn (0, 0)

Method: copy
	0 aload_0 (0, 0)
	1 invokevirtual (0, 0)
	2 org/apache/commons/math3/stat/descriptive/moment/Kurtosis.copy:()Lorg/apache/commons/math3/stat/descriptive/moment/Kurtosis; (0, 0)
	4 areturn (0, 0)

