Method: <init>
	0 aload_0 (0, 0)
	1 aload_1 (0, 0)
	2 invokespecial (0, 0)
	3 org/apache/commons/math3/stat/descriptive/moment/FirstMoment.<init>:(Lorg/apache/commons/math3/stat/descriptive/moment/FirstMoment;)V (0, 0)
	5 aload_0 (0, 0)
	6 aload_1 (0, 0)
	7 getfield (0, 0)
	8 org/apache/commons/math3/stat/descriptive/moment/SecondMoment.m2:D (0, 0)
	10 putfield (0, 0)
	11 org/apache/commons/math3/stat/descriptive/moment/SecondMoment.m2:D (0, 0)
	13 return (0, 0)

Method: increment
	0 aload_0 (1, 1)
	1 getfield (1, 1)
	2 org/apache/commons/math3/stat/descriptive/moment/SecondMoment.n:J (1, 1)
	4 lconst_1 (1, 1)
	5 lcmp (1, 1)
	6 ifge (1, 1)
	7 13 (1, 1)
	9 aload_0 (1, 1)
	10 aload_0 (1, 1)
	11 dconst_0 (1, 1)
	12 dup2_x1 (1, 1)
	13 putfield (1, 1)
	14 org/apache/commons/math3/stat/descriptive/moment/SecondMoment.m2:D (1, 1)
	16 putfield (1, 1)
	17 org/apache/commons/math3/stat/descriptive/moment/SecondMoment.m1:D (1, 1)
	19 aload_0 (0, 0)
	20 dload_1 (0, 0)
	21 invokespecial (0, 0)
	22 org/apache/commons/math3/stat/descriptive/moment/FirstMoment.increment:(D)V (0, 0)
	24 aload_0 (0, 0)
	25 dup (0, 0)
	26 getfield (0, 0)
	27 org/apache/commons/math3/stat/descriptive/moment/SecondMoment.m2:D (0, 0)
	29 aload_0 (0, 0)
	30 getfield (0, 0)
	31 org/apache/commons/math3/stat/descriptive/moment/SecondMoment.n:J (0, 0)
	33 l2d (0, 0)
	34 dconst_1 (0, 0)
	35 dsub (0, 0)
	36 aload_0 (0, 0)
	37 getfield (0, 0)
	38 org/apache/commons/math3/stat/descriptive/moment/SecondMoment.dev:D (0, 0)
	40 dmul (0, 0)
	41 aload_0 (0, 0)
	42 getfield (0, 0)
	43 org/apache/commons/math3/stat/descriptive/moment/SecondMoment.nDev:D (0, 0)
	45 dmul (0, 0)
	46 dadd (0, 0)
	47 putfield (0, 0)
	48 org/apache/commons/math3/stat/descriptive/moment/SecondMoment.m2:D (0, 0)
	50 return (0, 0)

Method: clear
	0 aload_0 (0, 0)
	1 invokespecial (0, 0)
	2 org/apache/commons/math3/stat/descriptive/moment/FirstMoment.clear:()V (0, 0)
	4 aload_0 (0, 0)
	5 ldc2_w (0, 0)
	6 nan (0, 0)
	8 putfield (0, 0)
	9 org/apache/commons/math3/stat/descriptive/moment/SecondMoment.m2:D (0, 0)
	11 return (0, 0)

Method: getResult
	0 aload_0 (0, 0)
	1 getfield (0, 0)
	2 org/apache/commons/math3/stat/descriptive/moment/SecondMoment.m2:D (0, 0)
	4 dreturn (0, 0)

Method: copy
	0 aload_0 (0, 0)
	1 invokevirtual (0, 0)
	2 org/apache/commons/math3/stat/descriptive/moment/SecondMoment.copy:()Lorg/apache/commons/math3/stat/descriptive/moment/SecondMoment; (0, 0)
	4 areturn (0, 0)

Method: getN
	0 aload_0 (0, 0)
	1 invokespecial (0, 0)
	2 org/apache/commons/math3/stat/descriptive/moment/FirstMoment.getN:()J (0, 0)
	4 lreturn (0, 0)

