Method: <init>
	0 aload_0 (0, 0)
	1 invokespecial (0, 0)
	2 org/apache/commons/math3/stat/descriptive/AbstractUnivariateStatistic.<init>:()V (0, 0)
	4 aload_0 (0, 0)
	5 iconst_1 (0, 0)
	6 putfield (0, 0)
	7 org/apache/commons/math3/stat/descriptive/moment/SemiVariance.biasCorrected:Z (0, 0)
	9 aload_0 (0, 0)
	10 getstatic (0, 0)
	11 org/apache/commons/math3/stat/descriptive/moment/SemiVariance$Direction.DOWNSIDE:Lorg/apache/commons/math3/stat/descriptive/moment/SemiVariance$Direction; (0, 0)
	13 putfield (0, 0)
	14 org/apache/commons/math3/stat/descriptive/moment/SemiVariance.varianceDirection:Lorg/apache/commons/math3/stat/descriptive/moment/SemiVariance$Direction; (0, 0)
	16 aload_1 (9, 1)
	17 aload_0 (9, 1)
	18 invokestatic (9, 1)
	19 org/apache/commons/math3/stat/descriptive/moment/SemiVariance.copy:(Lorg/apache/commons/math3/stat/descriptive/moment/SemiVariance;Lorg/apache/commons/math3/stat/descriptive/moment/SemiVariance;)V (9, 1)
	21 return (1, 1)

Method: copy
	0 aload_0 (0, 0)
	1 invokevirtual (0, 0)
	2 org/apache/commons/math3/stat/descriptive/moment/SemiVariance.copy:()Lorg/apache/commons/math3/stat/descriptive/moment/SemiVariance; (0, 0)
	4 areturn (0, 0)

Method: evaluate
	0 aload_0 (0, 0)
	1 aload_1 (0, 0)
	2 iload (0, 0)
	3 #6 (0, 0)
	4 iload (0, 0)
	5 #7 (0, 0)
	6 invokevirtual (0, 0)
	7 org/apache/commons/math3/stat/descriptive/moment/SemiVariance.test:([DII)Z (0, 0)
	9 pop (0, 0)
	10 aload_1 (1, 1)
	11 arraylength (1, 1)
	12 ifne (1, 1)
	13 7 (1, 1)
	15 ldc2_w (1, 1)
	16 nan (1, 1)
	18 dreturn (1, 1)
	19 aload_1 (3, 1)
	20 arraylength (3, 1)
	21 iconst_1 (3, 1)
	22 if_icmpne (3, 1)
	23 5 (3, 1)
	25 dconst_0 (3, 1)
	26 dreturn (3, 1)
	27 aload (4, 2)
	28 #4 (4, 2)
	29 invokevirtual (4, 2)
	30 org/apache/commons/math3/stat/descriptive/moment/SemiVariance$Direction.getDirection:()Z (4, 2)
	32 istore (4, 2)
	33 #8 (4, 2)
	34 dconst_0 (4, 2)
	35 dstore (4, 2)
	36 #9 (4, 2)
	37 dconst_0 (4, 2)
	38 dstore (4, 2)
	39 #11 (4, 2)
	40 iload (5, 4)
	41 #6 (5, 4)
	42 istore (5, 4)
	43 #13 (5, 4)
	44 iload (5, 4)
	45 #13 (5, 4)
	46 iload (5, 4)
	47 #7 (5, 4)
	48 if_icmpge (5, 4)
	49 46 (5, 4)
	51 aload_1 (6, 1)
	52 iload (6, 1)
	53 #13 (6, 1)
	54 daload (6, 1)
	55 dload_2 (6, 1)
	56 dcmpl (6, 1)
	57 ifle (6, 1)
	58 7 (6, 1)
	60 iconst_1 (6, 1)
	61 goto (6, 1)
	62 4 (6, 1)
	64 iconst_0 (6, 1)
	65 iload (6, 1)
	66 #8 (6, 1)
	67 if_icmpne (6, 1)
	68 21 (6, 1)
	70 aload_1 (6, 1)
	71 iload (6, 1)
	72 #13 (6, 1)
	73 daload (6, 1)
	74 dload_2 (6, 1)
	75 dsub (6, 1)
	76 dstore (6, 1)
	77 #9 (6, 1)
	78 dload (6, 1)
	79 #11 (6, 1)
	80 dload (6, 1)
	81 #9 (6, 1)
	82 dload (6, 1)
	83 #9 (6, 1)
	84 dmul (6, 1)
	85 dadd (6, 1)
	86 dstore (6, 1)
	87 #11 (6, 1)
	88 iinc (6, 1)
	89 #13 (6, 1)
	90 -89 (6, 1)
	91 goto (6, 1)
	92 -47 (6, 1)
	94 iload (6, 1)
	95 #5 (6, 1)
	96 ifeq (6, 1)
	97 12 (6, 1)
	99 dload (6, 1)
	100 #11 (6, 1)
	101 iload (6, 1)
	102 #7 (6, 1)
	103 i2d (6, 1)
	104 dconst_1 (6, 1)
	105 dsub (6, 1)
	106 ddiv (6, 1)
	107 dreturn (6, 1)
	108 dload (7, 2)
	109 #11 (7, 2)
	110 iload (7, 2)
	111 #7 (7, 2)
	112 i2d (7, 2)
	113 ddiv (7, 2)
	114 dreturn (4, 2)

Method: isBiasCorrected
	0 aload_0 (0, 0)
	1 getfield (0, 0)
	2 org/apache/commons/math3/stat/descriptive/moment/SemiVariance.biasCorrected:Z (0, 0)
	4 ireturn (0, 0)

Method: setBiasCorrected
	0 aload_0 (0, 0)
	1 iload_1 (0, 0)
	2 putfield (0, 0)
	3 org/apache/commons/math3/stat/descriptive/moment/SemiVariance.biasCorrected:Z (0, 0)
	5 return (0, 0)

Method: getVarianceDirection
	0 aload_0 (0, 0)
	1 getfield (0, 0)
	2 org/apache/commons/math3/stat/descriptive/moment/SemiVariance.varianceDirection:Lorg/apache/commons/math3/stat/descriptive/moment/SemiVariance$Direction; (0, 0)
	4 areturn (0, 0)

Method: setVarianceDirection
	0 aload_0 (0, 0)
	1 aload_1 (0, 0)
	2 putfield (0, 0)
	3 org/apache/commons/math3/stat/descriptive/moment/SemiVariance.varianceDirection:Lorg/apache/commons/math3/stat/descriptive/moment/SemiVariance$Direction; (0, 0)
	5 return (0, 0)

Method: <clinit>
	0 getstatic (0, 0)
	1 org/apache/commons/math3/stat/descriptive/moment/SemiVariance$Direction.UPSIDE:Lorg/apache/commons/math3/stat/descriptive/moment/SemiVariance$Direction; (0, 0)
	3 putstatic (0, 0)
	4 org/apache/commons/math3/stat/descriptive/moment/SemiVariance.UPSIDE_VARIANCE:Lorg/apache/commons/math3/stat/descriptive/moment/SemiVariance$Direction; (0, 0)
	6 getstatic (1, 1)
	7 org/apache/commons/math3/stat/descriptive/moment/SemiVariance$Direction.DOWNSIDE:Lorg/apache/commons/math3/stat/descriptive/moment/SemiVariance$Direction; (1, 1)
	9 putstatic (1, 1)
	10 org/apache/commons/math3/stat/descriptive/moment/SemiVariance.DOWNSIDE_VARIANCE:Lorg/apache/commons/math3/stat/descriptive/moment/SemiVariance$Direction; (1, 1)
	12 return (0, 1)

