Method: values
	0 getstatic (0, 0)
	1 org/apache/commons/math3/stat/descriptive/moment/SemiVariance$Direction.$VALUES:[Lorg/apache/commons/math3/stat/descriptive/moment/SemiVariance$Direction; (0, 0)
	3 invokevirtual (0, 0)
	4 [Lorg/apache/commons/math3/stat/descriptive/moment/SemiVariance$Direction;.clone:()Ljava/lang/Object; (0, 0)
	6 checkcast (0, 0)
	7 [Lorg/apache/commons/math3/stat/descriptive/moment/SemiVariance$Direction; (0, 0)
	9 areturn (0, 0)

Method: valueOf
	0 ldc (0, 0)
	1 org/apache/commons/math3/stat/descriptive/moment/SemiVariance$Direction (0, 0)
	2 aload_0 (0, 0)
	3 invokestatic (0, 0)
	4 java/lang/Enum.valueOf:(Ljava/lang/Class;Ljava/lang/String;)Ljava/lang/Enum; (0, 0)
	6 checkcast (0, 0)
	7 org/apache/commons/math3/stat/descriptive/moment/SemiVariance$Direction (0, 0)
	9 areturn (0, 0)

Method: <init>
	0 aload_0 (0, 0)
	1 aload_1 (0, 0)
	2 iload_2 (0, 0)
	3 invokespecial (0, 0)
	4 java/lang/Enum.<init>:(Ljava/lang/String;I)V (0, 0)
	6 aload_0 (0, 0)
	7 iload_3 (0, 0)
	8 putfield (0, 0)
	9 org/apache/commons/math3/stat/descriptive/moment/SemiVariance$Direction.direction:Z (0, 0)
	11 return (0, 0)

Method: getDirection
	0 aload_0 (0, 0)
	1 getfield (0, 0)
	2 org/apache/commons/math3/stat/descriptive/moment/SemiVariance$Direction.direction:Z (0, 0)
	4 ireturn (0, 0)

Method: <clinit>
	0 new (0, 0)
	1 org/apache/commons/math3/stat/descriptive/moment/SemiVariance$Direction (0, 0)
	3 dup (0, 0)
	4 ldc (0, 0)
	5 UPSIDE (0, 0)
	6 iconst_0 (0, 0)
	7 iconst_1 (0, 0)
	8 invokespecial (0, 0)
	9 org/apache/commons/math3/stat/descriptive/moment/SemiVariance$Direction.<init>:(Ljava/lang/String;IZ)V (0, 0)
	11 putstatic (0, 0)
	12 org/apache/commons/math3/stat/descriptive/moment/SemiVariance$Direction.UPSIDE:Lorg/apache/commons/math3/stat/descriptive/moment/SemiVariance$Direction; (0, 0)
	14 new (0, 1)
	15 org/apache/commons/math3/stat/descriptive/moment/SemiVariance$Direction (0, 1)
	17 dup (0, 1)
	18 ldc (0, 1)
	19 DOWNSIDE (0, 1)
	20 iconst_1 (0, 1)
	21 iconst_0 (0, 1)
	22 invokespecial (0, 1)
	23 org/apache/commons/math3/stat/descriptive/moment/SemiVariance$Direction.<init>:(Ljava/lang/String;IZ)V (0, 1)
	25 putstatic (0, 1)
	26 org/apache/commons/math3/stat/descriptive/moment/SemiVariance$Direction.DOWNSIDE:Lorg/apache/commons/math3/stat/descriptive/moment/SemiVariance$Direction; (0, 1)
	28 iconst_2 (0, 1)
	29 anewarray (0, 1)
	30 org/apache/commons/math3/stat/descriptive/moment/SemiVariance$Direction (0, 1)
	32 dup (0, 1)
	33 iconst_0 (0, 1)
	34 getstatic (0, 1)
	35 org/apache/commons/math3/stat/descriptive/moment/SemiVariance$Direction.UPSIDE:Lorg/apache/commons/math3/stat/descriptive/moment/SemiVariance$Direction; (0, 1)
	37 aastore (0, 1)
	38 dup (0, 1)
	39 iconst_1 (0, 1)
	40 getstatic (0, 1)
	41 org/apache/commons/math3/stat/descriptive/moment/SemiVariance$Direction.DOWNSIDE:Lorg/apache/commons/math3/stat/descriptive/moment/SemiVariance$Direction; (0, 1)
	43 aastore (0, 1)
	44 putstatic (0, 1)
	45 org/apache/commons/math3/stat/descriptive/moment/SemiVariance$Direction.$VALUES:[Lorg/apache/commons/math3/stat/descriptive/moment/SemiVariance$Direction; (0, 1)
	47 return (0, 1)

