Method: <init>
	0 aload_0 (0, 0)
	1 invokespecial (0, 0)
	2 org/apache/commons/math3/stat/descriptive/AbstractStorelessUnivariateStatistic.<init>:()V (0, 0)
	4 aload_0 (0, 0)
	5 aconst_null (0, 0)
	6 putfield (0, 0)
	7 org/apache/commons/math3/stat/descriptive/moment/StandardDeviation.variance:Lorg/apache/commons/math3/stat/descriptive/moment/Variance; (0, 0)
	9 aload_0 (7, 4)
	10 new (7, 4)
	11 org/apache/commons/math3/stat/descriptive/moment/Variance (7, 4)
	13 dup (7, 4)
	14 iload_1 (7, 4)
	15 aload_2 (7, 4)
	16 invokespecial (7, 4)
	17 org/apache/commons/math3/stat/descriptive/moment/Variance.<init>:(ZLorg/apache/commons/math3/stat/descriptive/moment/SecondMoment;)V (7, 4)
	19 putfield (7, 4)
	20 org/apache/commons/math3/stat/descriptive/moment/StandardDeviation.variance:Lorg/apache/commons/math3/stat/descriptive/moment/Variance; (7, 4)
	22 return (1, 4)

Method: increment
	0 aload_0 (0, 0)
	1 getfield (0, 0)
	2 org/apache/commons/math3/stat/descriptive/moment/StandardDeviation.variance:Lorg/apache/commons/math3/stat/descriptive/moment/Variance; (0, 0)
	4 dload_1 (0, 0)
	5 invokevirtual (0, 0)
	6 org/apache/commons/math3/stat/descriptive/moment/Variance.increment:(D)V (0, 0)
	8 return (0, 0)

Method: getN
	0 aload_0 (0, 0)
	1 getfield (0, 0)
	2 org/apache/commons/math3/stat/descriptive/moment/StandardDeviation.variance:Lorg/apache/commons/math3/stat/descriptive/moment/Variance; (0, 0)
	4 invokevirtual (0, 0)
	5 org/apache/commons/math3/stat/descriptive/moment/Variance.getN:()J (0, 0)
	7 lreturn (0, 0)

Method: getResult
	0 aload_0 (0, 0)
	1 getfield (0, 0)
	2 org/apache/commons/math3/stat/descriptive/moment/StandardDeviation.variance:Lorg/apache/commons/math3/stat/descriptive/moment/Variance; (0, 0)
	4 invokevirtual (0, 0)
	5 org/apache/commons/math3/stat/descriptive/moment/Variance.getResult:()D (0, 0)
	7 invokestatic (0, 0)
	8 org/apache/commons/math3/util/FastMath.sqrt:(D)D (0, 0)
	10 dreturn (0, 0)

Method: clear
	0 aload_0 (0, 0)
	1 getfield (0, 0)
	2 org/apache/commons/math3/stat/descriptive/moment/StandardDeviation.variance:Lorg/apache/commons/math3/stat/descriptive/moment/Variance; (0, 0)
	4 invokevirtual (0, 0)
	5 org/apache/commons/math3/stat/descriptive/moment/Variance.clear:()V (0, 0)
	7 return (0, 0)

Method: evaluate
	0 aload_0 (0, 0)
	1 getfield (0, 0)
	2 org/apache/commons/math3/stat/descriptive/moment/StandardDeviation.variance:Lorg/apache/commons/math3/stat/descriptive/moment/Variance; (0, 0)
	4 aload_1 (0, 0)
	5 dload_2 (0, 0)
	6 invokevirtual (0, 0)
	7 org/apache/commons/math3/stat/descriptive/moment/Variance.evaluate:([DD)D (0, 0)
	9 invokestatic (0, 0)
	10 org/apache/commons/math3/util/FastMath.sqrt:(D)D (0, 0)
	12 dreturn (0, 0)

Method: isBiasCorrected
	0 aload_0 (0, 0)
	1 getfield (0, 0)
	2 org/apache/commons/math3/stat/descriptive/moment/StandardDeviation.variance:Lorg/apache/commons/math3/stat/descriptive/moment/Variance; (0, 0)
	4 invokevirtual (0, 0)
	5 org/apache/commons/math3/stat/descriptive/moment/Variance.isBiasCorrected:()Z (0, 0)
	7 ireturn (0, 0)

Method: setBiasCorrected
	0 aload_0 (0, 0)
	1 getfield (0, 0)
	2 org/apache/commons/math3/stat/descriptive/moment/StandardDeviation.variance:Lorg/apache/commons/math3/stat/descriptive/moment/Variance; (0, 0)
	4 iload_1 (0, 0)
	5 invokevirtual (0, 0)
	6 org/apache/commons/math3/stat/descriptive/moment/Variance.setBiasCorrected:(Z)V (0, 0)
	8 return (0, 0)

Method: copy
	0 aload_0 (0, 0)
	1 invokevirtual (0, 0)
	2 org/apache/commons/math3/stat/descriptive/moment/StandardDeviation.copy:()Lorg/apache/commons/math3/stat/descriptive/moment/StandardDeviation; (0, 0)
	4 areturn (0, 0)

