Method: <init>
	0 aload_0 (0, 0)
	1 invokespecial (0, 0)
	2 org/apache/commons/math3/stat/descriptive/AbstractStorelessUnivariateStatistic.<init>:()V (0, 0)
	4 aload_0 (0, 0)
	5 aconst_null (0, 0)
	6 putfield (0, 0)
	7 org/apache/commons/math3/stat/descriptive/moment/Variance.moment:Lorg/apache/commons/math3/stat/descriptive/moment/SecondMoment; (0, 0)
	9 aload_0 (0, 0)
	10 iconst_1 (0, 0)
	11 putfield (0, 0)
	12 org/apache/commons/math3/stat/descriptive/moment/Variance.incMoment:Z (0, 0)
	14 aload_0 (1, 4)
	15 iconst_1 (1, 4)
	16 putfield (1, 4)
	17 org/apache/commons/math3/stat/descriptive/moment/Variance.isBiasCorrected:Z (1, 4)
	19 aload_1 (6, 1)
	20 aload_0 (6, 1)
	21 invokestatic (6, 1)
	22 org/apache/commons/math3/stat/descriptive/moment/Variance.copy:(Lorg/apache/commons/math3/stat/descriptive/moment/Variance;Lorg/apache/commons/math3/stat/descriptive/moment/Variance;)V (6, 1)
	24 return (1, 1)

Method: increment
	0 aload_0 (1, 1)
	1 getfield (1, 1)
	2 org/apache/commons/math3/stat/descriptive/moment/Variance.incMoment:Z (1, 1)
	4 ifeq (1, 1)
	5 11 (1, 1)
	7 aload_0 (1, 1)
	8 getfield (1, 1)
	9 org/apache/commons/math3/stat/descriptive/moment/Variance.moment:Lorg/apache/commons/math3/stat/descriptive/moment/SecondMoment; (1, 1)
	11 dload_1 (1, 1)
	12 invokevirtual (1, 1)
	13 org/apache/commons/math3/stat/descriptive/moment/SecondMoment.increment:(D)V (1, 1)
	15 return (0, 0)

Method: getResult
	0 aload_0 (1, 1)
	1 getfield (1, 1)
	2 org/apache/commons/math3/stat/descriptive/moment/Variance.moment:Lorg/apache/commons/math3/stat/descriptive/moment/SecondMoment; (1, 1)
	4 getfield (1, 1)
	5 org/apache/commons/math3/stat/descriptive/moment/SecondMoment.n:J (1, 1)
	7 lconst_0 (1, 1)
	8 lcmp (1, 1)
	9 ifne (1, 1)
	10 7 (1, 1)
	12 ldc2_w (1, 1)
	13 nan (1, 1)
	15 dreturn (1, 1)
	16 aload_0 (2, 1)
	17 getfield (2, 1)
	18 org/apache/commons/math3/stat/descriptive/moment/Variance.moment:Lorg/apache/commons/math3/stat/descriptive/moment/SecondMoment; (2, 1)
	20 getfield (2, 1)
	21 org/apache/commons/math3/stat/descriptive/moment/SecondMoment.n:J (2, 1)
	23 lconst_1 (2, 1)
	24 lcmp (2, 1)
	25 ifne (2, 1)
	26 5 (2, 1)
	28 dconst_0 (2, 1)
	29 dreturn (2, 1)
	30 aload_0 (4, 1)
	31 getfield (4, 1)
	32 org/apache/commons/math3/stat/descriptive/moment/Variance.isBiasCorrected:Z (4, 1)
	34 ifeq (4, 1)
	35 22 (4, 1)
	37 aload_0 (4, 1)
	38 getfield (4, 1)
	39 org/apache/commons/math3/stat/descriptive/moment/Variance.moment:Lorg/apache/commons/math3/stat/descriptive/moment/SecondMoment; (4, 1)
	41 getfield (4, 1)
	42 org/apache/commons/math3/stat/descriptive/moment/SecondMoment.m2:D (4, 1)
	44 aload_0 (4, 1)
	45 getfield (4, 1)
	46 org/apache/commons/math3/stat/descriptive/moment/Variance.moment:Lorg/apache/commons/math3/stat/descriptive/moment/SecondMoment; (4, 1)
	48 getfield (4, 1)
	49 org/apache/commons/math3/stat/descriptive/moment/SecondMoment.n:J (4, 1)
	51 l2d (4, 1)
	52 dconst_1 (4, 1)
	53 dsub (4, 1)
	54 ddiv (4, 1)
	55 dreturn (4, 1)
	56 aload_0 (5, 2)
	57 getfield (5, 2)
	58 org/apache/commons/math3/stat/descriptive/moment/Variance.moment:Lorg/apache/commons/math3/stat/descriptive/moment/SecondMoment; (5, 2)
	60 getfield (5, 2)
	61 org/apache/commons/math3/stat/descriptive/moment/SecondMoment.m2:D (5, 2)
	63 aload_0 (5, 2)
	64 getfield (5, 2)
	65 org/apache/commons/math3/stat/descriptive/moment/Variance.moment:Lorg/apache/commons/math3/stat/descriptive/moment/SecondMoment; (5, 2)
	67 getfield (5, 2)
	68 org/apache/commons/math3/stat/descriptive/moment/SecondMoment.n:J (5, 2)
	70 l2d (5, 2)
	71 ddiv (5, 2)
	72 dreturn (2, 2)

Method: getN
	0 aload_0 (0, 0)
	1 getfield (0, 0)
	2 org/apache/commons/math3/stat/descriptive/moment/Variance.moment:Lorg/apache/commons/math3/stat/descriptive/moment/SecondMoment; (0, 0)
	4 invokevirtual (0, 0)
	5 org/apache/commons/math3/stat/descriptive/moment/SecondMoment.getN:()J (0, 0)
	7 lreturn (0, 0)

Method: clear
	0 aload_0 (1, 1)
	1 getfield (1, 1)
	2 org/apache/commons/math3/stat/descriptive/moment/Variance.incMoment:Z (1, 1)
	4 ifeq (1, 1)
	5 10 (1, 1)
	7 aload_0 (1, 1)
	8 getfield (1, 1)
	9 org/apache/commons/math3/stat/descriptive/moment/Variance.moment:Lorg/apache/commons/math3/stat/descriptive/moment/SecondMoment; (1, 1)
	11 invokevirtual (1, 1)
	12 org/apache/commons/math3/stat/descriptive/moment/SecondMoment.clear:()V (1, 1)
	14 return (0, 0)

Method: evaluate
	0 aload_0 (0, 0)
	1 aload_1 (0, 0)
	2 aload_2 (0, 0)
	3 dload_3 (0, 0)
	4 iconst_0 (0, 0)
	5 aload_1 (0, 0)
	6 arraylength (0, 0)
	7 invokevirtual (0, 0)
	8 org/apache/commons/math3/stat/descriptive/moment/Variance.evaluate:([D[DDII)D (0, 0)
	10 dreturn (0, 0)

Method: isBiasCorrected
	0 aload_0 (0, 0)
	1 getfield (0, 0)
	2 org/apache/commons/math3/stat/descriptive/moment/Variance.isBiasCorrected:Z (0, 0)
	4 ireturn (0, 0)

Method: setBiasCorrected
	0 aload_0 (0, 0)
	1 iload_1 (0, 0)
	2 putfield (0, 0)
	3 org/apache/commons/math3/stat/descriptive/moment/Variance.isBiasCorrected:Z (0, 0)
	5 return (0, 0)

Method: copy
	0 aload_0 (0, 0)
	1 invokevirtual (0, 0)
	2 org/apache/commons/math3/stat/descriptive/moment/Variance.copy:()Lorg/apache/commons/math3/stat/descriptive/moment/Variance; (0, 0)
	4 areturn (0, 0)

