Method: <init>
	0 aload_0 (0, 0)
	1 invokespecial (0, 0)
	2 java/lang/Object.<init>:()V (0, 0)
	4 aload_0 (0, 0)
	5 iload_1 (0, 0)
	6 newarray (0, 0)
	7 7 (0, 0)
	8 putfield (0, 0)
	9 org/apache/commons/math3/stat/descriptive/moment/VectorialCovariance.sums:[D (0, 0)
	11 aload_0 (0, 0)
	12 iload_1 (0, 0)
	13 iload_1 (0, 0)
	14 iconst_1 (0, 0)
	15 iadd (0, 0)
	16 imul (0, 0)
	17 iconst_2 (0, 0)
	18 idiv (0, 0)
	19 newarray (0, 0)
	20 7 (0, 0)
	21 putfield (0, 0)
	22 org/apache/commons/math3/stat/descriptive/moment/VectorialCovariance.productsSums:[D (0, 0)
	24 aload_0 (0, 0)
	25 lconst_0 (0, 0)
	26 putfield (0, 0)
	27 org/apache/commons/math3/stat/descriptive/moment/VectorialCovariance.n:J (0, 0)
	29 aload_0 (0, 0)
	30 iload_2 (0, 0)
	31 putfield (0, 0)
	32 org/apache/commons/math3/stat/descriptive/moment/VectorialCovariance.isBiasCorrected:Z (0, 0)
	34 return (0, 0)

Method: increment
	0 aload_1 (1, 1)
	1 arraylength (1, 1)
	2 aload_0 (1, 1)
	3 getfield (1, 1)
	4 org/apache/commons/math3/stat/descriptive/moment/VectorialCovariance.sums:[D (1, 1)
	6 arraylength (1, 1)
	7 if_icmpeq (1, 1)
	8 18 (1, 1)
	10 new (1, 1)
	11 org/apache/commons/math3/exception/DimensionMismatchException (1, 1)
	13 dup (1, 1)
	14 aload_1 (1, 1)
	15 arraylength (1, 1)
	16 aload_0 (1, 1)
	17 getfield (1, 1)
	18 org/apache/commons/math3/stat/descriptive/moment/VectorialCovariance.sums:[D (1, 1)
	20 arraylength (1, 1)
	21 invokespecial (1, 1)
	22 org/apache/commons/math3/exception/DimensionMismatchException.<init>:(II)V (1, 1)
	24 athrow (1, 1)
	25 iconst_0 (0, 0)
	26 istore_2 (0, 0)
	27 iconst_0 (1, 4)
	28 istore_3 (1, 4)
	29 iload_3 (1, 4)
	30 aload_1 (1, 4)
	31 arraylength (1, 4)
	32 if_icmpge (1, 4)
	33 56 (1, 4)
	35 aload_0 (1, 4)
	36 getfield (1, 4)
	37 org/apache/commons/math3/stat/descriptive/moment/VectorialCovariance.sums:[D (1, 4)
	39 iload_3 (1, 4)
	40 dup2 (1, 4)
	41 daload (1, 4)
	42 aload_1 (1, 4)
	43 iload_3 (1, 4)
	44 daload (1, 4)
	45 dadd (1, 4)
	46 dastore (1, 4)
	47 iconst_0 (2, 4)
	48 istore (2, 4)
	49 #4 (2, 4)
	50 iload (2, 4)
	51 #4 (2, 4)
	52 iload_3 (2, 4)
	53 if_icmpgt (2, 4)
	54 29 (2, 4)
	56 aload_0 (2, 4)
	57 getfield (2, 4)
	58 org/apache/commons/math3/stat/descriptive/moment/VectorialCovariance.productsSums:[D (2, 4)
	60 iload_2 (2, 4)
	61 iinc (2, 4)
	62 #2 (2, 4)
	63 92 (2, 4)
	64 dup2 (2, 4)
	65 daload (2, 4)
	66 aload_1 (2, 4)
	67 iload_3 (2, 4)
	68 daload (2, 4)
	69 aload_1 (2, 4)
	70 iload (2, 4)
	71 #4 (2, 4)
	72 daload (2, 4)
	73 dmul (2, 4)
	74 dadd (2, 4)
	75 dastore (2, 4)
	76 iinc (2, 4)
	77 #4 (2, 4)
	78 -89 (2, 4)
	79 goto (2, 4)
	80 -29 (2, 4)
	82 iinc (2, 4)
	83 #3 (2, 4)
	84 -89 (2, 4)
	85 goto (2, 4)
	86 -56 (2, 4)
	88 aload_0 (1, 4)
	89 dup (1, 4)
	90 getfield (1, 4)
	91 org/apache/commons/math3/stat/descriptive/moment/VectorialCovariance.n:J (1, 4)
	93 lconst_1 (1, 4)
	94 ladd (1, 4)
	95 putfield (1, 4)
	96 org/apache/commons/math3/stat/descriptive/moment/VectorialCovariance.n:J (1, 4)
	98 return (0, 0)

Method: getResult
	0 aload_0 (0, 0)
	1 getfield (0, 0)
	2 org/apache/commons/math3/stat/descriptive/moment/VectorialCovariance.sums:[D (0, 0)
	4 arraylength (0, 0)
	5 istore_1 (0, 0)
	6 iload_1 (0, 0)
	7 iload_1 (0, 0)
	8 invokestatic (0, 0)
	9 org/apache/commons/math3/linear/MatrixUtils.createRealMatrix:(II)Lorg/apache/commons/math3/linear/RealMatrix; (0, 0)
	11 astore_2 (0, 0)
	12 aload_0 (1, 1)
	13 getfield (1, 1)
	14 org/apache/commons/math3/stat/descriptive/moment/VectorialCovariance.n:J (1, 1)
	16 lconst_1 (1, 1)
	17 lcmp (1, 1)
	18 ifle (1, 1)
	19 126 (1, 1)
	21 dconst_1 (1, 1)
	22 aload_0 (1, 1)
	23 getfield (1, 1)
	24 org/apache/commons/math3/stat/descriptive/moment/VectorialCovariance.n:J (1, 1)
	26 aload_0 (1, 1)
	27 getfield (1, 1)
	28 org/apache/commons/math3/stat/descriptive/moment/VectorialCovariance.isBiasCorrected:Z (1, 1)
	30 ifeq (1, 1)
	31 12 (1, 1)
	33 aload_0 (1, 1)
	34 getfield (1, 1)
	35 org/apache/commons/math3/stat/descriptive/moment/VectorialCovariance.n:J (1, 1)
	37 lconst_1 (1, 1)
	38 lsub (1, 1)
	39 goto (1, 1)
	40 7 (1, 1)
	42 aload_0 (1, 1)
	43 getfield (1, 1)
	44 org/apache/commons/math3/stat/descriptive/moment/VectorialCovariance.n:J (1, 1)
	46 lmul (1, 1)
	47 l2d (1, 1)
	48 ddiv (1, 1)
	49 dstore_3 (1, 1)
	50 iconst_0 (1, 1)
	51 istore (1, 1)
	52 #5 (1, 1)
	53 iconst_0 (2, 4)
	54 istore (2, 4)
	55 #6 (2, 4)
	56 iload (2, 4)
	57 #6 (2, 4)
	58 iload_1 (2, 4)
	59 if_icmpge (2, 4)
	60 85 (2, 4)
	62 iconst_0 (3, 4)
	63 istore (3, 4)
	64 #7 (3, 4)
	65 iload (3, 4)
	66 #7 (3, 4)
	67 iload (3, 4)
	68 #6 (3, 4)
	69 if_icmpgt (3, 4)
	70 69 (3, 4)
	72 dload_3 (3, 4)
	73 aload_0 (3, 4)
	74 getfield (3, 4)
	75 org/apache/commons/math3/stat/descriptive/moment/VectorialCovariance.n:J (3, 4)
	77 l2d (3, 4)
	78 aload_0 (3, 4)
	79 getfield (3, 4)
	80 org/apache/commons/math3/stat/descriptive/moment/VectorialCovariance.productsSums:[D (3, 4)
	82 iload (3, 4)
	83 #5 (3, 4)
	84 iinc (3, 4)
	85 #5 (3, 4)
	86 49 (3, 4)
	87 daload (3, 4)
	88 dmul (3, 4)
	89 aload_0 (3, 4)
	90 getfield (3, 4)
	91 org/apache/commons/math3/stat/descriptive/moment/VectorialCovariance.sums:[D (3, 4)
	93 iload (3, 4)
	94 #6 (3, 4)
	95 daload (3, 4)
	96 aload_0 (3, 4)
	97 getfield (3, 4)
	98 org/apache/commons/math3/stat/descriptive/moment/VectorialCovariance.sums:[D (3, 4)
	100 iload (3, 4)
	101 #7 (3, 4)
	102 daload (3, 4)
	103 dmul (3, 4)
	104 dsub (3, 4)
	105 dmul (3, 4)
	106 dstore (3, 4)
	107 #8 (3, 4)
	108 aload_2 (3, 4)
	109 iload (3, 4)
	110 #6 (3, 4)
	111 iload (3, 4)
	112 #7 (3, 4)
	113 dload (3, 4)
	114 #8 (3, 4)
	115 invokeinterface (3, 4)
	116 org/apache/commons/math3/linear/RealMatrix.java/util/Arrays (3, 4)
	118 0 (3, 4)
	120 aload_2 (3, 4)
	121 iload (3, 4)
	122 #7 (3, 4)
	123 iload (3, 4)
	124 #6 (3, 4)
	125 dload (3, 4)
	126 #8 (3, 4)
	127 invokeinterface (3, 4)
	128 org/apache/commons/math3/linear/RealMatrix.java/util/Arrays (3, 4)
	130 0 (3, 4)
	132 iinc (3, 4)
	133 #7 (3, 4)
	134 -89 (3, 4)
	135 goto (3, 4)
	136 -70 (3, 4)
	138 iinc (3, 4)
	139 #6 (3, 4)
	140 -89 (3, 4)
	141 goto (3, 4)
	142 -85 (3, 4)
	144 aload_2 (1, 1)
	145 areturn (1, 1)

Method: getN
	0 aload_0 (0, 0)
	1 getfield (0, 0)
	2 org/apache/commons/math3/stat/descriptive/moment/VectorialCovariance.n:J (0, 0)
	4 lreturn (0, 0)

Method: clear
	0 aload_0 (0, 0)
	1 lconst_0 (0, 0)
	2 putfield (0, 0)
	3 org/apache/commons/math3/stat/descriptive/moment/VectorialCovariance.n:J (0, 0)
	5 aload_0 (0, 0)
	6 getfield (0, 0)
	7 org/apache/commons/math3/stat/descriptive/moment/VectorialCovariance.sums:[D (0, 0)
	9 dconst_0 (0, 0)
	10 invokestatic (0, 0)
	11 java/util/Arrays.fill:([DD)V (0, 0)
	13 aload_0 (0, 0)
	14 getfield (0, 0)
	15 org/apache/commons/math3/stat/descriptive/moment/VectorialCovariance.productsSums:[D (0, 0)
	17 dconst_0 (0, 0)
	18 invokestatic (0, 0)
	19 java/util/Arrays.fill:([DD)V (0, 0)
	21 return (0, 0)

Method: hashCode
	0 bipush (0, 0)
	1 31 (0, 0)
	2 istore_1 (0, 0)
	3 iconst_1 (0, 0)
	4 istore_2 (0, 0)
	5 bipush (0, 0)
	6 31 (0, 0)
	7 iload_2 (0, 0)
	8 imul (0, 0)
	9 aload_0 (0, 0)
	10 getfield (0, 0)
	11 org/apache/commons/math3/stat/descriptive/moment/VectorialCovariance.isBiasCorrected:Z (0, 0)
	13 ifeq (0, 0)
	14 9 (0, 0)
	16 sipush (0, 0)
	17 1231 (0, 0)
	19 goto (0, 0)
	20 6 (0, 0)
	22 sipush (0, 0)
	23 1237 (0, 0)
	25 iadd (0, 0)
	26 istore_2 (0, 0)
	27 bipush (0, 0)
	28 31 (0, 0)
	29 iload_2 (0, 0)
	30 imul (0, 0)
	31 aload_0 (0, 0)
	32 getfield (0, 0)
	33 org/apache/commons/math3/stat/descriptive/moment/VectorialCovariance.n:J (0, 0)
	35 aload_0 (0, 0)
	36 getfield (0, 0)
	37 org/apache/commons/math3/stat/descriptive/moment/VectorialCovariance.n:J (0, 0)
	39 bipush (0, 0)
	40 32 (0, 0)
	41 lushr (0, 0)
	42 lxor (0, 0)
	43 l2i (0, 0)
	44 iadd (0, 0)
	45 istore_2 (0, 0)
	46 bipush (0, 0)
	47 31 (0, 0)
	48 iload_2 (0, 0)
	49 imul (0, 0)
	50 aload_0 (0, 0)
	51 getfield (0, 0)
	52 org/apache/commons/math3/stat/descriptive/moment/VectorialCovariance.productsSums:[D (0, 0)
	54 invokestatic (0, 0)
	55 java/util/Arrays.hashCode:([D)I (0, 0)
	57 iadd (0, 0)
	58 istore_2 (0, 0)
	59 bipush (0, 0)
	60 31 (0, 0)
	61 iload_2 (0, 0)
	62 imul (0, 0)
	63 aload_0 (0, 0)
	64 getfield (0, 0)
	65 org/apache/commons/math3/stat/descriptive/moment/VectorialCovariance.sums:[D (0, 0)
	67 invokestatic (0, 0)
	68 java/util/Arrays.hashCode:([D)I (0, 0)
	70 iadd (0, 0)
	71 istore_2 (0, 0)
	72 iload_2 (0, 0)
	73 ireturn (0, 0)

Method: equals
	0 aload_0 (1, 1)
	1 aload_1 (1, 1)
	2 if_acmpne (1, 1)
	3 5 (1, 1)
	5 iconst_1 (1, 1)
	6 ireturn (1, 1)
	7 aload_1 (1, 1)
	8 instanceof (1, 1)
	9 org/apache/commons/math3/stat/descriptive/moment/VectorialCovariance (1, 1)
	11 ifne (1, 1)
	12 5 (1, 1)
	14 iconst_0 (1, 1)
	15 ireturn (1, 1)
	16 aload_1 (0, 0)
	17 checkcast (0, 0)
	18 org/apache/commons/math3/stat/descriptive/moment/VectorialCovariance (0, 0)
	20 astore_2 (0, 0)
	21 aload_0 (1, 1)
	22 getfield (1, 1)
	23 org/apache/commons/math3/stat/descriptive/moment/VectorialCovariance.isBiasCorrected:Z (1, 1)
	25 aload_2 (1, 1)
	26 getfield (1, 1)
	27 org/apache/commons/math3/stat/descriptive/moment/VectorialCovariance.isBiasCorrected:Z (1, 1)
	29 if_icmpeq (1, 1)
	30 5 (1, 1)
	32 iconst_0 (1, 1)
	33 ireturn (1, 1)
	34 aload_0 (1, 1)
	35 getfield (1, 1)
	36 org/apache/commons/math3/stat/descriptive/moment/VectorialCovariance.n:J (1, 1)
	38 aload_2 (1, 1)
	39 getfield (1, 1)
	40 org/apache/commons/math3/stat/descriptive/moment/VectorialCovariance.n:J (1, 1)
	42 lcmp (1, 1)
	43 ifeq (1, 1)
	44 5 (1, 1)
	46 iconst_0 (1, 1)
	47 ireturn (1, 1)
	48 aload_0 (1, 1)
	49 getfield (1, 1)
	50 org/apache/commons/math3/stat/descriptive/moment/VectorialCovariance.productsSums:[D (1, 1)
	52 aload_2 (1, 1)
	53 getfield (1, 1)
	54 org/apache/commons/math3/stat/descriptive/moment/VectorialCovariance.productsSums:[D (1, 1)
	56 invokestatic (1, 1)
	57 java/util/Arrays.equals:([D[D)Z (1, 1)
	59 ifne (1, 1)
	60 5 (1, 1)
	62 iconst_0 (1, 1)
	63 ireturn (1, 1)
	64 aload_0 (1, 1)
	65 getfield (1, 1)
	66 org/apache/commons/math3/stat/descriptive/moment/VectorialCovariance.sums:[D (1, 1)
	68 aload_2 (1, 1)
	69 getfield (1, 1)
	70 org/apache/commons/math3/stat/descriptive/moment/VectorialCovariance.sums:[D (1, 1)
	72 invokestatic (1, 1)
	73 java/util/Arrays.equals:([D[D)Z (1, 1)
	75 ifne (1, 1)
	76 5 (1, 1)
	78 iconst_0 (1, 1)
	79 ireturn (1, 1)
	80 iconst_1 (0, 0)
	81 ireturn (0, 0)

