Method: <init>
	0 aload_0 (0, 0)
	1 invokespecial (0, 0)
	2 java/lang/Object.<init>:()V (0, 0)
	4 aload_0 (0, 0)
	5 iload_1 (0, 0)
	6 anewarray (0, 0)
	7 org/apache/commons/math3/stat/descriptive/moment/Mean (0, 0)
	9 putfield (0, 0)
	10 org/apache/commons/math3/stat/descriptive/moment/VectorialMean.means:[Lorg/apache/commons/math3/stat/descriptive/moment/Mean; (0, 0)
	12 iconst_0 (2, 4)
	13 istore_2 (2, 4)
	14 iload_2 (2, 4)
	15 iload_1 (2, 4)
	16 if_icmpge (2, 4)
	17 22 (2, 4)
	19 aload_0 (2, 4)
	20 getfield (2, 4)
	21 org/apache/commons/math3/stat/descriptive/moment/VectorialMean.means:[Lorg/apache/commons/math3/stat/descriptive/moment/Mean; (2, 4)
	23 iload_2 (2, 4)
	24 new (2, 4)
	25 org/apache/commons/math3/stat/descriptive/moment/Mean (2, 4)
	27 dup (2, 4)
	28 invokespecial (2, 4)
	29 org/apache/commons/math3/stat/descriptive/moment/Mean.<init>:()V (2, 4)
	31 aastore (2, 4)
	32 iinc (2, 4)
	33 #2 (2, 4)
	34 -89 (2, 4)
	35 goto (2, 4)
	36 -21 (2, 4)
	38 return (0, 0)

Method: increment
	0 aload_1 (1, 1)
	1 arraylength (1, 1)
	2 aload_0 (1, 1)
	3 getfield (1, 1)
	4 org/apache/commons/math3/stat/descriptive/moment/VectorialMean.means:[Lorg/apache/commons/math3/stat/descriptive/moment/Mean; (1, 1)
	6 arraylength (1, 1)
	7 if_icmpeq (1, 1)
	8 18 (1, 1)
	10 new (1, 1)
	11 org/apache/commons/math3/exception/DimensionMismatchException (1, 1)
	13 dup (1, 1)
	14 aload_1 (1, 1)
	15 arraylength (1, 1)
	16 aload_0 (1, 1)
	17 getfield (1, 1)
	18 org/apache/commons/math3/stat/descriptive/moment/VectorialMean.means:[Lorg/apache/commons/math3/stat/descriptive/moment/Mean; (1, 1)
	20 arraylength (1, 1)
	21 invokespecial (1, 1)
	22 org/apache/commons/math3/exception/DimensionMismatchException.<init>:(II)V (1, 1)
	24 athrow (1, 1)
	25 iconst_0 (1, 4)
	26 istore_2 (1, 4)
	27 iload_2 (1, 4)
	28 aload_1 (1, 4)
	29 arraylength (1, 4)
	30 if_icmpge (1, 4)
	31 21 (1, 4)
	33 aload_0 (1, 4)
	34 getfield (1, 4)
	35 org/apache/commons/math3/stat/descriptive/moment/VectorialMean.means:[Lorg/apache/commons/math3/stat/descriptive/moment/Mean; (1, 4)
	37 iload_2 (1, 4)
	38 aaload (1, 4)
	39 aload_1 (1, 4)
	40 iload_2 (1, 4)
	41 daload (1, 4)
	42 invokevirtual (1, 4)
	43 org/apache/commons/math3/stat/descriptive/moment/Mean.increment:(D)V (1, 4)
	45 iinc (1, 4)
	46 #2 (1, 4)
	47 -89 (1, 4)
	48 goto (1, 4)
	49 -21 (1, 4)
	51 return (0, 0)

Method: getResult
	0 aload_0 (0, 0)
	1 getfield (0, 0)
	2 org/apache/commons/math3/stat/descriptive/moment/VectorialMean.means:[Lorg/apache/commons/math3/stat/descriptive/moment/Mean; (0, 0)
	4 arraylength (0, 0)
	5 newarray (0, 0)
	6 7 (0, 0)
	7 astore_1 (0, 0)
	8 iconst_0 (1, 4)
	9 istore_2 (1, 4)
	10 iload_2 (1, 4)
	11 aload_1 (1, 4)
	12 arraylength (1, 4)
	13 if_icmpge (1, 4)
	14 21 (1, 4)
	16 aload_1 (1, 4)
	17 iload_2 (1, 4)
	18 aload_0 (1, 4)
	19 getfield (1, 4)
	20 org/apache/commons/math3/stat/descriptive/moment/VectorialMean.means:[Lorg/apache/commons/math3/stat/descriptive/moment/Mean; (1, 4)
	22 iload_2 (1, 4)
	23 aaload (1, 4)
	24 invokevirtual (1, 4)
	25 org/apache/commons/math3/stat/descriptive/moment/Mean.getResult:()D (1, 4)
	27 dastore (1, 4)
	28 iinc (1, 4)
	29 #2 (1, 4)
	30 -89 (1, 4)
	31 goto (1, 4)
	32 -21 (1, 4)
	34 aload_1 (0, 0)
	35 areturn (0, 0)

Method: getN
	0 aload_0 (0, 0)
	1 getfield (0, 0)
	2 org/apache/commons/math3/stat/descriptive/moment/VectorialMean.means:[Lorg/apache/commons/math3/stat/descriptive/moment/Mean; (0, 0)
	4 arraylength (0, 0)
	5 ifne (0, 0)
	6 7 (0, 0)
	8 lconst_0 (0, 0)
	9 goto (0, 0)
	10 12 (0, 0)
	12 aload_0 (0, 0)
	13 getfield (0, 0)
	14 org/apache/commons/math3/stat/descriptive/moment/VectorialMean.means:[Lorg/apache/commons/math3/stat/descriptive/moment/Mean; (0, 0)
	16 iconst_0 (0, 0)
	17 aaload (0, 0)
	18 invokevirtual (0, 0)
	19 org/apache/commons/math3/stat/descriptive/moment/Mean.getN:()J (0, 0)
	21 lreturn (0, 0)

Method: hashCode
	0 bipush (0, 0)
	1 31 (0, 0)
	2 istore_1 (0, 0)
	3 iconst_1 (0, 0)
	4 istore_2 (0, 0)
	5 bipush (0, 0)
	6 31 (0, 0)
	7 iload_2 (0, 0)
	8 imul (0, 0)
	9 aload_0 (0, 0)
	10 getfield (0, 0)
	11 org/apache/commons/math3/stat/descriptive/moment/VectorialMean.means:[Lorg/apache/commons/math3/stat/descriptive/moment/Mean; (0, 0)
	13 invokestatic (0, 0)
	14 java/util/Arrays.hashCode:([Ljava/lang/Object;)I (0, 0)
	16 iadd (0, 0)
	17 istore_2 (0, 0)
	18 iload_2 (0, 0)
	19 ireturn (0, 0)

Method: equals
	0 aload_0 (1, 1)
	1 aload_1 (1, 1)
	2 if_acmpne (1, 1)
	3 5 (1, 1)
	5 iconst_1 (1, 1)
	6 ireturn (1, 1)
	7 aload_1 (1, 1)
	8 instanceof (1, 1)
	9 org/apache/commons/math3/stat/descriptive/moment/VectorialMean (1, 1)
	11 ifne (1, 1)
	12 5 (1, 1)
	14 iconst_0 (1, 1)
	15 ireturn (1, 1)
	16 aload_1 (0, 0)
	17 checkcast (0, 0)
	18 org/apache/commons/math3/stat/descriptive/moment/VectorialMean (0, 0)
	20 astore_2 (0, 0)
	21 aload_0 (1, 1)
	22 getfield (1, 1)
	23 org/apache/commons/math3/stat/descriptive/moment/VectorialMean.means:[Lorg/apache/commons/math3/stat/descriptive/moment/Mean; (1, 1)
	25 aload_2 (1, 1)
	26 getfield (1, 1)
	27 org/apache/commons/math3/stat/descriptive/moment/VectorialMean.means:[Lorg/apache/commons/math3/stat/descriptive/moment/Mean; (1, 1)
	29 invokestatic (1, 1)
	30 java/util/Arrays.equals:([Ljava/lang/Object;[Ljava/lang/Object;)Z (1, 1)
	32 ifne (1, 1)
	33 5 (1, 1)
	35 iconst_0 (1, 1)
	36 ireturn (1, 1)
	37 iconst_1 (0, 0)
	38 ireturn (0, 0)

