Method: value
	0 aload_1 (0, 0)
	1 iconst_0 (0, 0)
	2 aaload (0, 0)
	3 invokevirtual (0, 0)
	4 org/apache/commons/math3/analysis/differentiation/DerivativeStructure.getFreeParameters:()I (0, 0)
	6 istore_2 (0, 0)
	7 aload_1 (0, 0)
	8 iconst_0 (0, 0)
	9 aaload (0, 0)
	10 invokevirtual (0, 0)
	11 org/apache/commons/math3/analysis/differentiation/DerivativeStructure.getOrder:()I (0, 0)
	13 istore_3 (0, 0)
	14 aload_1 (0, 0)
	15 arraylength (0, 0)
	16 istore (0, 0)
	17 #4 (0, 0)
	18 iload_3 (1, 1)
	19 iconst_1 (1, 1)
	20 if_icmple (1, 1)
	21 20 (1, 1)
	23 new (1, 1)
	24 org/apache/commons/math3/exception/NumberIsTooLargeException (1, 1)
	26 dup (1, 1)
	27 iload_3 (1, 1)
	28 invokestatic (1, 1)
	29 java/lang/Integer.valueOf:(I)Ljava/lang/Integer; (1, 1)
	31 iconst_1 (1, 1)
	32 invokestatic (1, 1)
	33 java/lang/Integer.valueOf:(I)Ljava/lang/Integer; (1, 1)
	35 iconst_1 (1, 1)
	36 invokespecial (1, 1)
	37 org/apache/commons/math3/exception/NumberIsTooLargeException.<init>:(Ljava/lang/Number;Ljava/lang/Number;Z)V (1, 1)
	39 athrow (1, 1)
	40 iconst_0 (1, 4)
	41 istore (1, 4)
	42 #5 (1, 4)
	43 iload (1, 4)
	44 #5 (1, 4)
	45 iload (1, 4)
	46 #4 (1, 4)
	47 if_icmpge (1, 4)
	48 63 (1, 4)
	50 aload_1 (2, 1)
	51 iload (2, 1)
	52 #5 (2, 1)
	53 aaload (2, 1)
	54 invokevirtual (2, 1)
	55 org/apache/commons/math3/analysis/differentiation/DerivativeStructure.getFreeParameters:()I (2, 1)
	57 iload_2 (2, 1)
	58 if_icmpeq (2, 1)
	59 19 (2, 1)
	61 new (2, 1)
	62 org/apache/commons/math3/exception/DimensionMismatchException (2, 1)
	64 dup (2, 1)
	65 aload_1 (2, 1)
	66 iload (2, 1)
	67 #5 (2, 1)
	68 aaload (2, 1)
	69 invokevirtual (2, 1)
	70 org/apache/commons/math3/analysis/differentiation/DerivativeStructure.getFreeParameters:()I (2, 1)
	72 iload_2 (2, 1)
	73 invokespecial (2, 1)
	74 org/apache/commons/math3/exception/DimensionMismatchException.<init>:(II)V (2, 1)
	76 athrow (2, 1)
	77 aload_1 (2, 1)
	78 iload (2, 1)
	79 #5 (2, 1)
	80 aaload (2, 1)
	81 invokevirtual (2, 1)
	82 org/apache/commons/math3/analysis/differentiation/DerivativeStructure.getOrder:()I (2, 1)
	84 iload_3 (2, 1)
	85 if_icmpeq (2, 1)
	86 19 (2, 1)
	88 new (2, 1)
	89 org/apache/commons/math3/exception/DimensionMismatchException (2, 1)
	91 dup (2, 1)
	92 aload_1 (2, 1)
	93 iload (2, 1)
	94 #5 (2, 1)
	95 aaload (2, 1)
	96 invokevirtual (2, 1)
	97 org/apache/commons/math3/analysis/differentiation/DerivativeStructure.getOrder:()I (2, 1)
	99 iload_3 (2, 1)
	100 invokespecial (2, 1)
	101 org/apache/commons/math3/exception/DimensionMismatchException.<init>:(II)V (2, 1)
	103 athrow (2, 1)
	104 iinc (2, 1)
	105 #5 (2, 1)
	106 -89 (2, 1)
	107 goto (2, 1)
	108 -64 (2, 1)
	110 iload (1, 4)
	111 #4 (1, 4)
	112 newarray (1, 4)
	113 7 (1, 4)
	114 astore (1, 4)
	115 #5 (1, 4)
	116 iconst_0 (2, 4)
	117 istore (2, 4)
	118 #6 (2, 4)
	119 iload (2, 4)
	120 #6 (2, 4)
	121 iload (2, 4)
	122 #4 (2, 4)
	123 if_icmpge (2, 4)
	124 21 (2, 4)
	126 aload (2, 4)
	127 #5 (2, 4)
	128 iload (2, 4)
	129 #6 (2, 4)
	130 aload_1 (2, 4)
	131 iload (2, 4)
	132 #6 (2, 4)
	133 aaload (2, 4)
	134 invokevirtual (2, 4)
	135 org/apache/commons/math3/analysis/differentiation/DerivativeStructure.getValue:()D (2, 4)
	137 dastore (2, 4)
	138 iinc (2, 4)
	139 #6 (2, 4)
	140 -89 (2, 4)
	141 goto (2, 4)
	142 -22 (2, 4)
	144 aload_0 (1, 4)
	145 getfield (1, 4)
	146 org/apache/commons/math3/analysis/FunctionUtils$19.val$f:Lorg/apache/commons/math3/analysis/DifferentiableMultivariateVectorFunction; (1, 4)
	148 aload (1, 4)
	149 #5 (1, 4)
	150 invokeinterface (1, 4)
	151 org/apache/commons/math3/analysis/DifferentiableMultivariateVectorFunction.getFreeParameters:()I (1, 4)
	153 0 (1, 4)
	155 astore (1, 4)
	156 #6 (1, 4)
	157 aload_0 (1, 4)
	158 getfield (1, 4)
	159 org/apache/commons/math3/analysis/FunctionUtils$19.val$f:Lorg/apache/commons/math3/analysis/DifferentiableMultivariateVectorFunction; (1, 4)
	161 invokeinterface (1, 4)
	162 org/apache/commons/math3/analysis/DifferentiableMultivariateVectorFunction.org/apache/commons/math3/analysis/MultivariateMatrixFunction (1, 4)
	164 0 (1, 4)
	166 aload (1, 4)
	167 #5 (1, 4)
	168 invokeinterface (1, 4)
	169 org/apache/commons/math3/analysis/MultivariateMatrixFunction.org/apache/commons/math3/analysis/differentiation/DerivativeStructure (1, 4)
	171 0 (1, 4)
	173 astore (1, 4)
	174 #7 (1, 4)
	175 aload (1, 4)
	176 #6 (1, 4)
	177 arraylength (1, 4)
	178 anewarray (1, 4)
	179 org/apache/commons/math3/analysis/differentiation/DerivativeStructure (1, 4)
	181 astore (1, 4)
	182 #8 (1, 4)
	183 iconst_0 (2, 4)
	184 istore (2, 4)
	185 #9 (2, 4)
	186 iload (2, 4)
	187 #9 (2, 4)
	188 aload (2, 4)
	189 #8 (2, 4)
	190 arraylength (2, 4)
	191 if_icmpge (2, 4)
	192 117 (2, 4)
	194 iload_2 (2, 4)
	195 iconst_1 (2, 4)
	196 iadd (2, 4)
	197 newarray (2, 4)
	198 7 (2, 4)
	199 astore (2, 4)
	200 #10 (2, 4)
	201 aload (2, 4)
	202 #10 (2, 4)
	203 iconst_0 (2, 4)
	204 aload (2, 4)
	205 #6 (2, 4)
	206 iload (2, 4)
	207 #9 (2, 4)
	208 daload (2, 4)
	209 dastore (2, 4)
	210 iload_2 (2, 4)
	211 newarray (2, 4)
	212 10 (2, 4)
	213 astore (2, 4)
	214 #11 (2, 4)
	215 iconst_0 (3, 4)
	216 istore (3, 4)
	217 #12 (3, 4)
	218 iload (3, 4)
	219 #12 (3, 4)
	220 iload_2 (3, 4)
	221 if_icmpge (3, 4)
	222 65 (3, 4)
	224 aload (3, 4)
	225 #11 (3, 4)
	226 iload (3, 4)
	227 #12 (3, 4)
	228 iconst_1 (3, 4)
	229 iastore (3, 4)
	230 iconst_0 (4, 4)
	231 istore (4, 4)
	232 #13 (4, 4)
	233 iload (4, 4)
	234 #13 (4, 4)
	235 iload (4, 4)
	236 #4 (4, 4)
	237 if_icmpge (4, 4)
	238 37 (4, 4)
	240 aload (4, 4)
	241 #10 (4, 4)
	242 iload (4, 4)
	243 #12 (4, 4)
	244 iconst_1 (4, 4)
	245 iadd (4, 4)
	246 dup2 (4, 4)
	247 daload (4, 4)
	248 aload (4, 4)
	249 #7 (4, 4)
	250 iload (4, 4)
	251 #9 (4, 4)
	252 aaload (4, 4)
	253 iload (4, 4)
	254 #13 (4, 4)
	255 daload (4, 4)
	256 aload_1 (4, 4)
	257 iload (4, 4)
	258 #13 (4, 4)
	259 aaload (4, 4)
	260 aload (4, 4)
	261 #11 (4, 4)
	262 invokevirtual (4, 4)
	263 org/apache/commons/math3/analysis/differentiation/DerivativeStructure.getPartialDerivative:([I)D (4, 4)
	265 dmul (4, 4)
	266 dadd (4, 4)
	267 dastore (4, 4)
	268 iinc (4, 4)
	269 #13 (4, 4)
	270 -89 (4, 4)
	271 goto (4, 4)
	272 -38 (4, 4)
	274 aload (3, 4)
	275 #11 (3, 4)
	276 iload (3, 4)
	277 #12 (3, 4)
	278 iconst_0 (3, 4)
	279 iastore (3, 4)
	280 iinc (3, 4)
	281 #12 (3, 4)
	282 -89 (3, 4)
	283 goto (3, 4)
	284 -65 (3, 4)
	286 aload (2, 4)
	287 #8 (2, 4)
	288 iload (2, 4)
	289 #9 (2, 4)
	290 new (2, 4)
	291 org/apache/commons/math3/analysis/differentiation/DerivativeStructure (2, 4)
	293 dup (2, 4)
	294 iload_2 (2, 4)
	295 iload_3 (2, 4)
	296 aload (2, 4)
	297 #10 (2, 4)
	298 invokespecial (2, 4)
	299 org/apache/commons/math3/analysis/differentiation/DerivativeStructure.<init>:(II[D)V (2, 4)
	301 aastore (2, 4)
	302 iinc (2, 4)
	303 #9 (2, 4)
	304 -89 (2, 4)
	305 goto (2, 4)
	306 -119 (2, 4)
	308 aload (1, 4)
	309 #8 (1, 4)
	310 areturn (1, 4)

