Method: value
	0 aload_0 (0, 0)
	1 getfield (0, 0)
	2 org/apache/commons/math3/analysis/FunctionUtils$10.val$combiner:Lorg/apache/commons/math3/analysis/BivariateFunction; (0, 0)
	4 aload_0 (0, 0)
	5 getfield (0, 0)
	6 org/apache/commons/math3/analysis/FunctionUtils$10.val$f:Lorg/apache/commons/math3/analysis/UnivariateFunction; (0, 0)
	8 dload_1 (0, 0)
	9 invokeinterface (0, 0)
	10 org/apache/commons/math3/analysis/UnivariateFunction.org/apache/commons/math3/analysis/BivariateFunction (0, 0)
	12 0 (0, 0)
	14 aload_0 (0, 0)
	15 getfield (0, 0)
	16 org/apache/commons/math3/analysis/FunctionUtils$10.val$g:Lorg/apache/commons/math3/analysis/UnivariateFunction; (0, 0)
	18 dload_1 (0, 0)
	19 invokeinterface (0, 0)
	20 org/apache/commons/math3/analysis/UnivariateFunction.org/apache/commons/math3/analysis/BivariateFunction (0, 0)
	22 0 (0, 0)
	24 invokeinterface (0, 0)
	25 org/apache/commons/math3/analysis/BivariateFunction.org/apache/commons/math3/analysis/FunctionUtils$10 (0, 0)
	27 0 (0, 0)
	29 dreturn (0, 0)

