Method: value
	0 aload_0 (0, 0)
	1 getfield (0, 0)
	2 org/apache/commons/math3/analysis/FunctionUtils$9.val$f:[Lorg/apache/commons/math3/analysis/DifferentiableUnivariateFunction; (0, 0)
	4 iconst_0 (0, 0)
	5 aaload (0, 0)
	6 dload_1 (0, 0)
	7 invokeinterface (0, 0)
	8 org/apache/commons/math3/analysis/DifferentiableUnivariateFunction.org/apache/commons/math3/analysis/FunctionUtils$9$1 (0, 0)
	10 0 (0, 0)
	12 dstore_3 (0, 0)
	13 iconst_1 (1, 4)
	14 istore (1, 4)
	15 #5 (1, 4)
	16 iload (1, 4)
	17 #5 (1, 4)
	18 aload_0 (1, 4)
	19 getfield (1, 4)
	20 org/apache/commons/math3/analysis/FunctionUtils$9.val$f:[Lorg/apache/commons/math3/analysis/DifferentiableUnivariateFunction; (1, 4)
	22 arraylength (1, 4)
	23 if_icmpge (1, 4)
	24 25 (1, 4)
	26 dload_3 (1, 4)
	27 aload_0 (1, 4)
	28 getfield (1, 4)
	29 org/apache/commons/math3/analysis/FunctionUtils$9.val$f:[Lorg/apache/commons/math3/analysis/DifferentiableUnivariateFunction; (1, 4)
	31 iload (1, 4)
	32 #5 (1, 4)
	33 aaload (1, 4)
	34 dload_1 (1, 4)
	35 invokeinterface (1, 4)
	36 org/apache/commons/math3/analysis/DifferentiableUnivariateFunction.org/apache/commons/math3/analysis/FunctionUtils$9$1 (1, 4)
	38 0 (1, 4)
	40 dmul (1, 4)
	41 dstore_3 (1, 4)
	42 iinc (1, 4)
	43 #5 (1, 4)
	44 -89 (1, 4)
	45 goto (1, 4)
	46 -29 (1, 4)
	48 dload_3 (0, 0)
	49 dreturn (0, 0)

Method: derivative
	0 new (0, 0)
	1 org/apache/commons/math3/analysis/FunctionUtils$9$1 (0, 0)
	3 dup (0, 0)
	4 aload_0 (0, 0)
	5 invokespecial (0, 0)
	6 org/apache/commons/math3/analysis/FunctionUtils$9$1.<init>:(Lorg/apache/commons/math3/analysis/FunctionUtils$9;)V (0, 0)
	8 areturn (0, 0)

