Method: value
	0 aload_0 (0, 0)
	1 getfield (0, 0)
	2 org/apache/commons/math3/analysis/FunctionUtils$16.val$f:Lorg/apache/commons/math3/analysis/differentiation/MultivariateDifferentiableFunction; (0, 0)
	4 aload_1 (0, 0)
	5 invokeinterface (0, 0)
	6 org/apache/commons/math3/analysis/differentiation/MultivariateDifferentiableFunction.org/apache/commons/math3/analysis/FunctionUtils$16$1 (0, 0)
	8 0 (0, 0)
	10 dreturn (0, 0)

Method: partialDerivative
	0 new (0, 0)
	1 org/apache/commons/math3/analysis/FunctionUtils$16$1 (0, 0)
	3 dup (0, 0)
	4 aload_0 (0, 0)
	5 iload_1 (0, 0)
	6 invokespecial (0, 0)
	7 org/apache/commons/math3/analysis/FunctionUtils$16$1.<init>:(Lorg/apache/commons/math3/analysis/FunctionUtils$16;I)V (0, 0)
	9 areturn (0, 0)

Method: gradient
	0 new (0, 0)
	1 org/apache/commons/math3/analysis/FunctionUtils$16$2 (0, 0)
	3 dup (0, 0)
	4 aload_0 (0, 0)
	5 invokespecial (0, 0)
	6 org/apache/commons/math3/analysis/FunctionUtils$16$2.<init>:(Lorg/apache/commons/math3/analysis/FunctionUtils$16;)V (0, 0)
	8 areturn (0, 0)

