Method: value
	0 aload_0 (0, 0)
	1 getfield (0, 0)
	2 org/apache/commons/math3/analysis/FunctionUtils$18.val$f:Lorg/apache/commons/math3/analysis/differentiation/MultivariateDifferentiableVectorFunction; (0, 0)
	4 aload_1 (0, 0)
	5 invokeinterface (0, 0)
	6 org/apache/commons/math3/analysis/differentiation/MultivariateDifferentiableVectorFunction.org/apache/commons/math3/analysis/FunctionUtils$18$1 (0, 0)
	8 0 (0, 0)
	10 areturn (0, 0)

Method: jacobian
	0 new (0, 0)
	1 org/apache/commons/math3/analysis/FunctionUtils$18$1 (0, 0)
	3 dup (0, 0)
	4 aload_0 (0, 0)
	5 invokespecial (0, 0)
	6 org/apache/commons/math3/analysis/FunctionUtils$18$1.<init>:(Lorg/apache/commons/math3/analysis/FunctionUtils$18;)V (0, 0)
	8 areturn (0, 0)

