Method: compose
	0 new (1, 1)
	1 org/apache/commons/math3/analysis/FunctionUtils$3 (1, 1)
	3 dup (1, 1)
	4 aload_0 (1, 1)
	5 invokespecial (1, 1)
	6 org/apache/commons/math3/analysis/FunctionUtils$3.<init>:([Lorg/apache/commons/math3/analysis/DifferentiableUnivariateFunction;)V (1, 1)
	8 areturn (1, 1)

Method: add
	0 new (1, 1)
	1 org/apache/commons/math3/analysis/FunctionUtils$6 (1, 1)
	3 dup (1, 1)
	4 aload_0 (1, 1)
	5 invokespecial (1, 1)
	6 org/apache/commons/math3/analysis/FunctionUtils$6.<init>:([Lorg/apache/commons/math3/analysis/DifferentiableUnivariateFunction;)V (1, 1)
	8 areturn (1, 1)

Method: multiply
	0 new (1, 1)
	1 org/apache/commons/math3/analysis/FunctionUtils$9 (1, 1)
	3 dup (1, 1)
	4 aload_0 (1, 1)
	5 invokespecial (1, 1)
	6 org/apache/commons/math3/analysis/FunctionUtils$9.<init>:([Lorg/apache/commons/math3/analysis/DifferentiableUnivariateFunction;)V (1, 1)
	8 areturn (1, 1)

Method: combine
	0 new (0, 0)
	1 org/apache/commons/math3/analysis/FunctionUtils$10 (0, 0)
	3 dup (0, 0)
	4 aload_0 (0, 0)
	5 aload_1 (0, 0)
	6 aload_2 (0, 0)
	7 invokespecial (0, 0)
	8 org/apache/commons/math3/analysis/FunctionUtils$10.<init>:(Lorg/apache/commons/math3/analysis/BivariateFunction;Lorg/apache/commons/math3/analysis/UnivariateFunction;Lorg/apache/commons/math3/analysis/UnivariateFunction;)V (0, 0)
	10 areturn (0, 0)

Method: collector
	0 aload_0 (0, 0)
	1 new (0, 0)
	2 org/apache/commons/math3/analysis/function/Identity (0, 0)
	4 dup (0, 0)
	5 invokespecial (0, 0)
	6 org/apache/commons/math3/analysis/function/Identity.<init>:()V (0, 0)
	8 dload_1 (0, 0)
	9 invokestatic (0, 0)
	10 org/apache/commons/math3/analysis/FunctionUtils.collector:(Lorg/apache/commons/math3/analysis/BivariateFunction;Lorg/apache/commons/math3/analysis/UnivariateFunction;D)Lorg/apache/commons/math3/analysis/MultivariateFunction; (0, 0)
	12 areturn (0, 0)

Method: fix1stArgument
	0 new (0, 0)
	1 org/apache/commons/math3/analysis/FunctionUtils$12 (0, 0)
	3 dup (0, 0)
	4 aload_0 (0, 0)
	5 dload_1 (0, 0)
	6 invokespecial (0, 0)
	7 org/apache/commons/math3/analysis/FunctionUtils$12.<init>:(Lorg/apache/commons/math3/analysis/BivariateFunction;D)V (0, 0)
	9 areturn (0, 0)

Method: fix2ndArgument
	0 new (0, 0)
	1 org/apache/commons/math3/analysis/FunctionUtils$13 (0, 0)
	3 dup (0, 0)
	4 aload_0 (0, 0)
	5 dload_1 (0, 0)
	6 invokespecial (0, 0)
	7 org/apache/commons/math3/analysis/FunctionUtils$13.<init>:(Lorg/apache/commons/math3/analysis/BivariateFunction;D)V (0, 0)
	9 areturn (0, 0)

Method: sample
	0 iload (1, 1)
	1 #5 (1, 1)
	2 ifgt (1, 1)
	3 19 (1, 1)
	5 new (1, 1)
	6 org/apache/commons/math3/exception/NotStrictlyPositiveException (1, 1)
	8 dup (1, 1)
	9 getstatic (1, 1)
	10 org/apache/commons/math3/exception/util/LocalizedFormats.NOT_POSITIVE_NUMBER_OF_SAMPLES:Lorg/apache/commons/math3/exception/util/LocalizedFormats; (1, 1)
	12 iload (1, 1)
	13 #5 (1, 1)
	14 invokestatic (1, 1)
	15 java/lang/Integer.valueOf:(I)Ljava/lang/Integer; (1, 1)
	17 invokespecial (1, 1)
	18 org/apache/commons/math3/exception/NotStrictlyPositiveException.<init>:(Lorg/apache/commons/math3/exception/util/Localizable;Ljava/lang/Number;)V (1, 1)
	20 athrow (1, 1)
	21 dload_1 (1, 1)
	22 dload_3 (1, 1)
	23 dcmpl (1, 1)
	24 iflt (1, 1)
	25 20 (1, 1)
	27 new (1, 1)
	28 org/apache/commons/math3/exception/NumberIsTooLargeException (1, 1)
	30 dup (1, 1)
	31 dload_1 (1, 1)
	32 invokestatic (1, 1)
	33 java/lang/Double.valueOf:(D)Ljava/lang/Double; (1, 1)
	35 dload_3 (1, 1)
	36 invokestatic (1, 1)
	37 java/lang/Double.valueOf:(D)Ljava/lang/Double; (1, 1)
	39 iconst_0 (1, 1)
	40 invokespecial (1, 1)
	41 org/apache/commons/math3/exception/NumberIsTooLargeException.<init>:(Ljava/lang/Number;Ljava/lang/Number;Z)V (1, 1)
	43 athrow (1, 1)
	44 iload (0, 0)
	45 #5 (0, 0)
	46 newarray (0, 0)
	47 7 (0, 0)
	48 astore (0, 0)
	49 #6 (0, 0)
	50 dload_3 (0, 0)
	51 dload_1 (0, 0)
	52 dsub (0, 0)
	53 iload (0, 0)
	54 #5 (0, 0)
	55 i2d (0, 0)
	56 ddiv (0, 0)
	57 dstore (0, 0)
	58 #7 (0, 0)
	59 iconst_0 (1, 4)
	60 istore (1, 4)
	61 #9 (1, 4)
	62 iload (1, 4)
	63 #9 (1, 4)
	64 iload (1, 4)
	65 #5 (1, 4)
	66 if_icmpge (1, 4)
	67 28 (1, 4)
	69 aload (1, 4)
	70 #6 (1, 4)
	71 iload (1, 4)
	72 #9 (1, 4)
	73 aload_0 (1, 4)
	74 dload_1 (1, 4)
	75 iload (1, 4)
	76 #9 (1, 4)
	77 i2d (1, 4)
	78 dload (1, 4)
	79 #7 (1, 4)
	80 dmul (1, 4)
	81 dadd (1, 4)
	82 invokeinterface (1, 4)
	83 org/apache/commons/math3/analysis/UnivariateFunction.org/apache/commons/math3/analysis/FunctionUtils$14 (1, 4)
	85 0 (1, 4)
	87 dastore (1, 4)
	88 iinc (1, 4)
	89 #9 (1, 4)
	90 -89 (1, 4)
	91 goto (1, 4)
	92 -29 (1, 4)
	94 aload (0, 0)
	95 #6 (0, 0)
	96 areturn (0, 0)

Method: toDifferentiableUnivariateFunction
	0 new (1, 1)
	1 org/apache/commons/math3/analysis/FunctionUtils$14 (1, 1)
	3 dup (1, 1)
	4 aload_0 (1, 1)
	5 invokespecial (1, 1)
	6 org/apache/commons/math3/analysis/FunctionUtils$14.<init>:(Lorg/apache/commons/math3/analysis/differentiation/UnivariateDifferentiableFunction;)V (1, 1)
	8 areturn (1, 1)

Method: toUnivariateDifferential
	0 new (1, 1)
	1 org/apache/commons/math3/analysis/FunctionUtils$15 (1, 1)
	3 dup (1, 1)
	4 aload_0 (1, 1)
	5 invokespecial (1, 1)
	6 org/apache/commons/math3/analysis/FunctionUtils$15.<init>:(Lorg/apache/commons/math3/analysis/DifferentiableUnivariateFunction;)V (1, 1)
	8 areturn (1, 1)

Method: toDifferentiableMultivariateFunction
	0 new (1, 1)
	1 org/apache/commons/math3/analysis/FunctionUtils$16 (1, 1)
	3 dup (1, 1)
	4 aload_0 (1, 1)
	5 invokespecial (1, 1)
	6 org/apache/commons/math3/analysis/FunctionUtils$16.<init>:(Lorg/apache/commons/math3/analysis/differentiation/MultivariateDifferentiableFunction;)V (1, 1)
	8 areturn (1, 1)

Method: toMultivariateDifferentiableFunction
	0 new (1, 1)
	1 org/apache/commons/math3/analysis/FunctionUtils$17 (1, 1)
	3 dup (1, 1)
	4 aload_0 (1, 1)
	5 invokespecial (1, 1)
	6 org/apache/commons/math3/analysis/FunctionUtils$17.<init>:(Lorg/apache/commons/math3/analysis/DifferentiableMultivariateFunction;)V (1, 1)
	8 areturn (1, 1)

Method: toDifferentiableMultivariateVectorFunction
	0 new (1, 1)
	1 org/apache/commons/math3/analysis/FunctionUtils$18 (1, 1)
	3 dup (1, 1)
	4 aload_0 (1, 1)
	5 invokespecial (1, 1)
	6 org/apache/commons/math3/analysis/FunctionUtils$18.<init>:(Lorg/apache/commons/math3/analysis/differentiation/MultivariateDifferentiableVectorFunction;)V (1, 1)
	8 areturn (1, 1)

Method: toMultivariateDifferentiableVectorFunction
	0 new (1, 1)
	1 org/apache/commons/math3/analysis/FunctionUtils$19 (1, 1)
	3 dup (1, 1)
	4 aload_0 (1, 1)
	5 invokespecial (1, 1)
	6 org/apache/commons/math3/analysis/FunctionUtils$19.<init>:(Lorg/apache/commons/math3/analysis/DifferentiableMultivariateVectorFunction;)V (1, 1)
	8 areturn (1, 1)

