Method: value
	0 dconst_0 (0, 0)
	1 dstore_3 (0, 0)
	2 iconst_0 (1, 4)
	3 istore (1, 4)
	4 #5 (1, 4)
	5 iload (1, 4)
	6 #5 (1, 4)
	7 aload_0 (1, 4)
	8 getfield (1, 4)
	9 org/apache/commons/math3/analysis/FunctionUtils$9$1.this$0:Lorg/apache/commons/math3/analysis/FunctionUtils$9; (1, 4)
	11 getfield (1, 4)
	12 org/apache/commons/math3/analysis/FunctionUtils$9.val$f:[Lorg/apache/commons/math3/analysis/DifferentiableUnivariateFunction; (1, 4)
	14 arraylength (1, 4)
	15 if_icmpge (1, 4)
	16 87 (1, 4)
	18 aload_0 (1, 4)
	19 getfield (1, 4)
	20 org/apache/commons/math3/analysis/FunctionUtils$9$1.this$0:Lorg/apache/commons/math3/analysis/FunctionUtils$9; (1, 4)
	22 getfield (1, 4)
	23 org/apache/commons/math3/analysis/FunctionUtils$9.val$f:[Lorg/apache/commons/math3/analysis/DifferentiableUnivariateFunction; (1, 4)
	25 iload (1, 4)
	26 #5 (1, 4)
	27 aaload (1, 4)
	28 invokeinterface (1, 4)
	29 org/apache/commons/math3/analysis/DifferentiableUnivariateFunction.this$0:Lorg/apache/commons/math3/analysis/FunctionUtils$9; (1, 4)
	31 0 (1, 4)
	33 dload_1 (1, 4)
	34 invokeinterface (1, 4)
	35 org/apache/commons/math3/analysis/UnivariateFunction.org/apache/commons/math3/analysis/FunctionUtils$9$1 (1, 4)
	37 0 (1, 4)
	39 dstore (1, 4)
	40 #6 (1, 4)
	41 iconst_0 (2, 4)
	42 istore (2, 4)
	43 #8 (2, 4)
	44 iload (2, 4)
	45 #8 (2, 4)
	46 aload_0 (2, 4)
	47 getfield (2, 4)
	48 org/apache/commons/math3/analysis/FunctionUtils$9$1.this$0:Lorg/apache/commons/math3/analysis/FunctionUtils$9; (2, 4)
	50 getfield (2, 4)
	51 org/apache/commons/math3/analysis/FunctionUtils$9.val$f:[Lorg/apache/commons/math3/analysis/DifferentiableUnivariateFunction; (2, 4)
	53 arraylength (2, 4)
	54 if_icmpge (2, 4)
	55 37 (2, 4)
	57 iload (3, 1)
	58 #5 (3, 1)
	59 iload (3, 1)
	60 #8 (3, 1)
	61 if_icmpeq (3, 1)
	62 24 (3, 1)
	64 dload (3, 1)
	65 #6 (3, 1)
	66 aload_0 (3, 1)
	67 getfield (3, 1)
	68 org/apache/commons/math3/analysis/FunctionUtils$9$1.this$0:Lorg/apache/commons/math3/analysis/FunctionUtils$9; (3, 1)
	70 getfield (3, 1)
	71 org/apache/commons/math3/analysis/FunctionUtils$9.val$f:[Lorg/apache/commons/math3/analysis/DifferentiableUnivariateFunction; (3, 1)
	73 iload (3, 1)
	74 #8 (3, 1)
	75 aaload (3, 1)
	76 dload_1 (3, 1)
	77 invokeinterface (3, 1)
	78 org/apache/commons/math3/analysis/DifferentiableUnivariateFunction.org/apache/commons/math3/analysis/FunctionUtils$9$1 (3, 1)
	80 0 (3, 1)
	82 dmul (3, 1)
	83 dstore (3, 1)
	84 #6 (3, 1)
	85 iinc (3, 1)
	86 #8 (3, 1)
	87 -89 (3, 1)
	88 goto (3, 1)
	89 -44 (3, 1)
	91 dload_3 (2, 4)
	92 dload (2, 4)
	93 #6 (2, 4)
	94 dadd (2, 4)
	95 dstore_3 (2, 4)
	96 iinc (2, 4)
	97 #5 (2, 4)
	98 -89 (2, 4)
	99 goto (2, 4)
	100 -94 (2, 4)
	102 dload_3 (1, 4)
	103 dreturn (1, 4)

