Method: value
	0 aload_0 (0, 0)
	1 getfield (0, 0)
	2 org/apache/commons/math3/analysis/FunctionUtils$8.val$f:[Lorg/apache/commons/math3/analysis/differentiation/UnivariateDifferentiableFunction; (0, 0)
	4 iconst_0 (0, 0)
	5 aaload (0, 0)
	6 aload_1 (0, 0)
	7 invokeinterface (0, 0)
	8 org/apache/commons/math3/analysis/differentiation/UnivariateDifferentiableFunction.org/apache/commons/math3/analysis/differentiation/DerivativeStructure (0, 0)
	10 0 (0, 0)
	12 astore_2 (0, 0)
	13 iconst_1 (1, 4)
	14 istore_3 (1, 4)
	15 iload_3 (1, 4)
	16 aload_0 (1, 4)
	17 getfield (1, 4)
	18 org/apache/commons/math3/analysis/FunctionUtils$8.val$f:[Lorg/apache/commons/math3/analysis/differentiation/UnivariateDifferentiableFunction; (1, 4)
	20 arraylength (1, 4)
	21 if_icmpge (1, 4)
	22 26 (1, 4)
	24 aload_2 (1, 4)
	25 aload_0 (1, 4)
	26 getfield (1, 4)
	27 org/apache/commons/math3/analysis/FunctionUtils$8.val$f:[Lorg/apache/commons/math3/analysis/differentiation/UnivariateDifferentiableFunction; (1, 4)
	29 iload_3 (1, 4)
	30 aaload (1, 4)
	31 aload_1 (1, 4)
	32 invokeinterface (1, 4)
	33 org/apache/commons/math3/analysis/differentiation/UnivariateDifferentiableFunction.org/apache/commons/math3/analysis/differentiation/DerivativeStructure (1, 4)
	35 0 (1, 4)
	37 invokevirtual (1, 4)
	38 org/apache/commons/math3/analysis/differentiation/DerivativeStructure.multiply:(Lorg/apache/commons/math3/analysis/differentiation/DerivativeStructure;)Lorg/apache/commons/math3/analysis/differentiation/DerivativeStructure; (1, 4)
	40 astore_2 (1, 4)
	41 iinc (1, 4)
	42 #3 (1, 4)
	43 -89 (1, 4)
	44 goto (1, 4)
	45 -29 (1, 4)
	47 aload_2 (0, 0)
	48 areturn (0, 0)

