Method: value
	0 aload_0 (0, 0)
	1 getfield (0, 0)
	2 org/apache/commons/math3/analysis/FunctionUtils$11.val$combiner:Lorg/apache/commons/math3/analysis/BivariateFunction; (0, 0)
	4 aload_0 (0, 0)
	5 getfield (0, 0)
	6 org/apache/commons/math3/analysis/FunctionUtils$11.val$initialValue:D (0, 0)
	8 aload_0 (0, 0)
	9 getfield (0, 0)
	10 org/apache/commons/math3/analysis/FunctionUtils$11.val$f:Lorg/apache/commons/math3/analysis/UnivariateFunction; (0, 0)
	12 aload_1 (0, 0)
	13 iconst_0 (0, 0)
	14 daload (0, 0)
	15 invokeinterface (0, 0)
	16 org/apache/commons/math3/analysis/UnivariateFunction.org/apache/commons/math3/analysis/BivariateFunction (0, 0)
	18 0 (0, 0)
	20 invokeinterface (0, 0)
	21 org/apache/commons/math3/analysis/BivariateFunction.org/apache/commons/math3/analysis/FunctionUtils$11 (0, 0)
	23 0 (0, 0)
	25 dstore_2 (0, 0)
	26 iconst_1 (1, 4)
	27 istore (1, 4)
	28 #4 (1, 4)
	29 iload (1, 4)
	30 #4 (1, 4)
	31 aload_1 (1, 4)
	32 arraylength (1, 4)
	33 if_icmpge (1, 4)
	34 33 (1, 4)
	36 aload_0 (1, 4)
	37 getfield (1, 4)
	38 org/apache/commons/math3/analysis/FunctionUtils$11.val$combiner:Lorg/apache/commons/math3/analysis/BivariateFunction; (1, 4)
	40 dload_2 (1, 4)
	41 aload_0 (1, 4)
	42 getfield (1, 4)
	43 org/apache/commons/math3/analysis/FunctionUtils$11.val$f:Lorg/apache/commons/math3/analysis/UnivariateFunction; (1, 4)
	45 aload_1 (1, 4)
	46 iload (1, 4)
	47 #4 (1, 4)
	48 daload (1, 4)
	49 invokeinterface (1, 4)
	50 org/apache/commons/math3/analysis/UnivariateFunction.org/apache/commons/math3/analysis/BivariateFunction (1, 4)
	52 0 (1, 4)
	54 invokeinterface (1, 4)
	55 org/apache/commons/math3/analysis/BivariateFunction.org/apache/commons/math3/analysis/FunctionUtils$11 (1, 4)
	57 0 (1, 4)
	59 dstore_2 (1, 4)
	60 iinc (1, 4)
	61 #4 (1, 4)
	62 -89 (1, 4)
	63 goto (1, 4)
	64 -34 (1, 4)
	66 dload_2 (0, 0)
	67 dreturn (0, 0)

