Method: <init>
	0 aload_0 (0, 0)
	1 invokespecial (0, 0)
	2 java/lang/Object.<init>:()V (0, 0)
	4 aload_0 (0, 0)
	5 new (0, 0)
	6 java/util/TreeMap (0, 0)
	8 dup (0, 0)
	9 invokespecial (0, 0)
	10 java/util/TreeMap.<init>:()V (0, 0)
	12 putfield (0, 0)
	13 org/apache/commons/math3/analysis/integration/gauss/BaseRuleFactory.pointsAndWeights:Ljava/util/Map; (0, 0)
	15 aload_0 (1, 4)
	16 new (1, 4)
	17 java/util/TreeMap (1, 4)
	19 dup (1, 4)
	20 invokespecial (1, 4)
	21 java/util/TreeMap.<init>:()V (1, 4)
	23 putfield (1, 4)
	24 org/apache/commons/math3/analysis/integration/gauss/BaseRuleFactory.pointsAndWeightsDouble:Ljava/util/Map; (1, 4)
	26 return (1, 4)

Method: getRule
	0 iload_1 (1, 1)
	1 ifgt (1, 1)
	2 18 (1, 1)
	4 new (1, 1)
	5 org/apache/commons/math3/exception/NotStrictlyPositiveException (1, 1)
	7 dup (1, 1)
	8 getstatic (1, 1)
	9 org/apache/commons/math3/exception/util/LocalizedFormats.NUMBER_OF_POINTS:Lorg/apache/commons/math3/exception/util/LocalizedFormats; (1, 1)
	11 iload_1 (1, 1)
	12 invokestatic (1, 1)
	13 java/lang/Integer.valueOf:(I)Ljava/lang/Integer; (1, 1)
	15 invokespecial (1, 1)
	16 org/apache/commons/math3/exception/NotStrictlyPositiveException.<init>:(Lorg/apache/commons/math3/exception/util/Localizable;Ljava/lang/Number;)V (1, 1)
	18 athrow (1, 1)
	19 aload_0 (0, 0)
	20 getfield (0, 0)
	21 org/apache/commons/math3/analysis/integration/gauss/BaseRuleFactory.pointsAndWeightsDouble:Ljava/util/Map; (0, 0)
	23 iload_1 (0, 0)
	24 invokestatic (0, 0)
	25 java/lang/Integer.valueOf:(I)Ljava/lang/Integer; (0, 0)
	27 invokeinterface (0, 0)
	28 java/util/Map.org/apache/commons/math3/util/Pair (0, 0)
	30 0 (0, 0)
	32 checkcast (0, 0)
	33 org/apache/commons/math3/util/Pair (0, 0)
	35 astore_2 (0, 0)
	36 aload_2 (1, 1)
	37 ifnonnull (1, 1)
	38 29 (1, 1)
	40 aload_0 (1, 1)
	41 iload_1 (1, 1)
	42 invokevirtual (1, 1)
	43 org/apache/commons/math3/analysis/integration/gauss/BaseRuleFactory.getRuleInternal:(I)Lorg/apache/commons/math3/util/Pair; (1, 1)
	45 astore_3 (1, 1)
	46 aload_3 (1, 1)
	47 invokestatic (1, 1)
	48 org/apache/commons/math3/analysis/integration/gauss/BaseRuleFactory.convertToDouble:(Lorg/apache/commons/math3/util/Pair;)Lorg/apache/commons/math3/util/Pair; (1, 1)
	50 astore_2 (1, 1)
	51 aload_0 (1, 1)
	52 getfield (1, 1)
	53 org/apache/commons/math3/analysis/integration/gauss/BaseRuleFactory.pointsAndWeightsDouble:Ljava/util/Map; (1, 1)
	55 iload_1 (1, 1)
	56 invokestatic (1, 1)
	57 java/lang/Integer.valueOf:(I)Ljava/lang/Integer; (1, 1)
	59 aload_2 (1, 1)
	60 invokeinterface (1, 1)
	61 java/util/Map.getFirst:()Ljava/lang/Object; (1, 1)
	63 0 (1, 1)
	65 pop (1, 1)
	66 new (0, 0)
	67 org/apache/commons/math3/util/Pair (0, 0)
	69 dup (0, 0)
	70 aload_2 (0, 0)
	71 invokevirtual (0, 0)
	72 org/apache/commons/math3/util/Pair.getFirst:()Ljava/lang/Object; (0, 0)
	74 checkcast (0, 0)
	75 [D (0, 0)
	77 invokevirtual (0, 0)
	78 [D.clone:()Ljava/lang/Object; (0, 0)
	80 aload_2 (0, 0)
	81 invokevirtual (0, 0)
	82 org/apache/commons/math3/util/Pair.getSecond:()Ljava/lang/Object; (0, 0)
	84 checkcast (0, 0)
	85 [D (0, 0)
	87 invokevirtual (0, 0)
	88 [D.clone:()Ljava/lang/Object; (0, 0)
	90 invokespecial (0, 0)
	91 org/apache/commons/math3/util/Pair.<init>:(Ljava/lang/Object;Ljava/lang/Object;)V (0, 0)
	93 areturn (0, 0)

Method: getRuleInternal
	0 aload_0 (0, 0)
	1 getfield (0, 0)
	2 org/apache/commons/math3/analysis/integration/gauss/BaseRuleFactory.pointsAndWeights:Ljava/util/Map; (0, 0)
	4 iload_1 (0, 0)
	5 invokestatic (0, 0)
	6 java/lang/Integer.valueOf:(I)Ljava/lang/Integer; (0, 0)
	8 invokeinterface (0, 0)
	9 java/util/Map.org/apache/commons/math3/util/Pair (0, 0)
	11 0 (0, 0)
	13 checkcast (0, 0)
	14 org/apache/commons/math3/util/Pair (0, 0)
	16 astore_2 (0, 0)
	17 aload_2 (1, 1)
	18 ifnonnull (1, 1)
	19 18 (1, 1)
	21 aload_0 (1, 1)
	22 aload_0 (1, 1)
	23 iload_1 (1, 1)
	24 invokevirtual (1, 1)
	25 org/apache/commons/math3/analysis/integration/gauss/BaseRuleFactory.computeRule:(I)Lorg/apache/commons/math3/util/Pair; (1, 1)
	27 invokevirtual (1, 1)
	28 org/apache/commons/math3/analysis/integration/gauss/BaseRuleFactory.addRule:(Lorg/apache/commons/math3/util/Pair;)V (1, 1)
	30 aload_0 (1, 1)
	31 iload_1 (1, 1)
	32 invokevirtual (1, 1)
	33 org/apache/commons/math3/analysis/integration/gauss/BaseRuleFactory.getRuleInternal:(I)Lorg/apache/commons/math3/util/Pair; (1, 1)
	35 areturn (1, 1)
	36 aload_2 (0, 0)
	37 areturn (0, 0)

Method: addRule
	0 aload_1 (1, 1)
	1 invokevirtual (1, 1)
	2 org/apache/commons/math3/util/Pair.getFirst:()Ljava/lang/Object; (1, 1)
	4 checkcast (1, 1)
	5 [Ljava/lang/Number; (1, 1)
	7 arraylength (1, 1)
	8 aload_1 (1, 1)
	9 invokevirtual (1, 1)
	10 org/apache/commons/math3/util/Pair.getSecond:()Ljava/lang/Object; (1, 1)
	12 checkcast (1, 1)
	13 [Ljava/lang/Number; (1, 1)
	15 arraylength (1, 1)
	16 if_icmpeq (1, 1)
	17 27 (1, 1)
	19 new (1, 1)
	20 org/apache/commons/math3/exception/DimensionMismatchException (1, 1)
	22 dup (1, 1)
	23 aload_1 (1, 1)
	24 invokevirtual (1, 1)
	25 org/apache/commons/math3/util/Pair.getFirst:()Ljava/lang/Object; (1, 1)
	27 checkcast (1, 1)
	28 [Ljava/lang/Number; (1, 1)
	30 arraylength (1, 1)
	31 aload_1 (1, 1)
	32 invokevirtual (1, 1)
	33 org/apache/commons/math3/util/Pair.getSecond:()Ljava/lang/Object; (1, 1)
	35 checkcast (1, 1)
	36 [Ljava/lang/Number; (1, 1)
	38 arraylength (1, 1)
	39 invokespecial (1, 1)
	40 org/apache/commons/math3/exception/DimensionMismatchException.<init>:(II)V (1, 1)
	42 athrow (1, 1)
	43 aload_0 (0, 0)
	44 getfield (0, 0)
	45 org/apache/commons/math3/analysis/integration/gauss/BaseRuleFactory.pointsAndWeights:Ljava/util/Map; (0, 0)
	47 aload_1 (0, 0)
	48 invokevirtual (0, 0)
	49 org/apache/commons/math3/util/Pair.getFirst:()Ljava/lang/Object; (0, 0)
	51 checkcast (0, 0)
	52 [Ljava/lang/Number; (0, 0)
	54 arraylength (0, 0)
	55 invokestatic (0, 0)
	56 java/lang/Integer.valueOf:(I)Ljava/lang/Integer; (0, 0)
	58 aload_1 (0, 0)
	59 invokeinterface (0, 0)
	60 java/util/Map.getFirst:()Ljava/lang/Object; (0, 0)
	62 0 (0, 0)
	64 pop (0, 0)
	65 return (0, 0)

Method: convertToDouble
	0 aload_0 (0, 0)
	1 invokevirtual (0, 0)
	2 org/apache/commons/math3/util/Pair.getFirst:()Ljava/lang/Object; (0, 0)
	4 checkcast (0, 0)
	5 [Ljava/lang/Number; (0, 0)
	7 astore_1 (0, 0)
	8 aload_0 (0, 0)
	9 invokevirtual (0, 0)
	10 org/apache/commons/math3/util/Pair.getSecond:()Ljava/lang/Object; (0, 0)
	12 checkcast (0, 0)
	13 [Ljava/lang/Number; (0, 0)
	15 astore_2 (0, 0)
	16 aload_1 (0, 0)
	17 arraylength (0, 0)
	18 istore_3 (0, 0)
	19 iload_3 (0, 0)
	20 newarray (0, 0)
	21 7 (0, 0)
	22 astore (0, 0)
	23 #4 (0, 0)
	24 iload_3 (0, 0)
	25 newarray (0, 0)
	26 7 (0, 0)
	27 astore (0, 0)
	28 #5 (0, 0)
	29 iconst_0 (1, 4)
	30 istore (1, 4)
	31 #6 (1, 4)
	32 iload (1, 4)
	33 #6 (1, 4)
	34 iload_3 (1, 4)
	35 if_icmpge (1, 4)
	36 33 (1, 4)
	38 aload (1, 4)
	39 #4 (1, 4)
	40 iload (1, 4)
	41 #6 (1, 4)
	42 aload_1 (1, 4)
	43 iload (1, 4)
	44 #6 (1, 4)
	45 aaload (1, 4)
	46 invokevirtual (1, 4)
	47 java/lang/Number.doubleValue:()D (1, 4)
	49 dastore (1, 4)
	50 aload (1, 4)
	51 #5 (1, 4)
	52 iload (1, 4)
	53 #6 (1, 4)
	54 aload_2 (1, 4)
	55 iload (1, 4)
	56 #6 (1, 4)
	57 aaload (1, 4)
	58 invokevirtual (1, 4)
	59 java/lang/Number.doubleValue:()D (1, 4)
	61 dastore (1, 4)
	62 iinc (1, 4)
	63 #6 (1, 4)
	64 -89 (1, 4)
	65 goto (1, 4)
	66 -33 (1, 4)
	68 new (0, 0)
	69 org/apache/commons/math3/util/Pair (0, 0)
	71 dup (0, 0)
	72 aload (0, 0)
	73 #4 (0, 0)
	74 aload (0, 0)
	75 #5 (0, 0)
	76 invokespecial (0, 0)
	77 org/apache/commons/math3/util/Pair.<init>:(Ljava/lang/Object;Ljava/lang/Object;)V (0, 0)
	79 areturn (0, 0)

