Method: <init>
	0 aload_0 (0, 0)
	1 invokespecial (0, 0)
	2 java/lang/Object.<init>:()V (0, 0)
	4 aload_0 (0, 0)
	5 new (0, 0)
	6 org/apache/commons/math3/analysis/integration/gauss/LegendreRuleFactory (0, 0)
	8 dup (0, 0)
	9 invokespecial (0, 0)
	10 org/apache/commons/math3/analysis/integration/gauss/LegendreRuleFactory.<init>:()V (0, 0)
	12 putfield (0, 0)
	13 org/apache/commons/math3/analysis/integration/gauss/GaussIntegratorFactory.legendre:Lorg/apache/commons/math3/analysis/integration/gauss/BaseRuleFactory; (0, 0)
	15 aload_0 (0, 0)
	16 new (0, 0)
	17 org/apache/commons/math3/analysis/integration/gauss/LegendreHighPrecisionRuleFactory (0, 0)
	19 dup (0, 0)
	20 invokespecial (0, 0)
	21 org/apache/commons/math3/analysis/integration/gauss/LegendreHighPrecisionRuleFactory.<init>:()V (0, 0)
	23 putfield (0, 0)
	24 org/apache/commons/math3/analysis/integration/gauss/GaussIntegratorFactory.legendreHighPrecision:Lorg/apache/commons/math3/analysis/integration/gauss/BaseRuleFactory; (0, 0)
	26 aload_0 (0, 0)
	27 new (0, 0)
	28 org/apache/commons/math3/analysis/integration/gauss/HermiteRuleFactory (0, 0)
	30 dup (0, 0)
	31 invokespecial (0, 0)
	32 org/apache/commons/math3/analysis/integration/gauss/HermiteRuleFactory.<init>:()V (0, 0)
	34 putfield (0, 0)
	35 org/apache/commons/math3/analysis/integration/gauss/GaussIntegratorFactory.hermite:Lorg/apache/commons/math3/analysis/integration/gauss/BaseRuleFactory; (0, 0)
	37 return (0, 0)

Method: legendre
	0 new (0, 4)
	1 org/apache/commons/math3/analysis/integration/gauss/GaussIntegrator (0, 4)
	3 dup (0, 4)
	4 aload_0 (0, 4)
	5 getfield (0, 4)
	6 org/apache/commons/math3/analysis/integration/gauss/GaussIntegratorFactory.legendre:Lorg/apache/commons/math3/analysis/integration/gauss/BaseRuleFactory; (0, 4)
	8 iload_1 (0, 4)
	9 invokestatic (0, 4)
	10 org/apache/commons/math3/analysis/integration/gauss/GaussIntegratorFactory.getRule:(Lorg/apache/commons/math3/analysis/integration/gauss/BaseRuleFactory;I)Lorg/apache/commons/math3/util/Pair; (0, 4)
	12 dload_2 (0, 4)
	13 dload (0, 4)
	14 #4 (0, 4)
	15 invokestatic (0, 4)
	16 org/apache/commons/math3/analysis/integration/gauss/GaussIntegratorFactory.transform:(Lorg/apache/commons/math3/util/Pair;DD)Lorg/apache/commons/math3/util/Pair; (0, 4)
	18 invokespecial (0, 4)
	19 org/apache/commons/math3/analysis/integration/gauss/GaussIntegrator.<init>:(Lorg/apache/commons/math3/util/Pair;)V (0, 4)
	21 areturn (0, 4)

Method: legendreHighPrecision
	0 new (0, 4)
	1 org/apache/commons/math3/analysis/integration/gauss/GaussIntegrator (0, 4)
	3 dup (0, 4)
	4 aload_0 (0, 4)
	5 getfield (0, 4)
	6 org/apache/commons/math3/analysis/integration/gauss/GaussIntegratorFactory.legendreHighPrecision:Lorg/apache/commons/math3/analysis/integration/gauss/BaseRuleFactory; (0, 4)
	8 iload_1 (0, 4)
	9 invokestatic (0, 4)
	10 org/apache/commons/math3/analysis/integration/gauss/GaussIntegratorFactory.getRule:(Lorg/apache/commons/math3/analysis/integration/gauss/BaseRuleFactory;I)Lorg/apache/commons/math3/util/Pair; (0, 4)
	12 dload_2 (0, 4)
	13 dload (0, 4)
	14 #4 (0, 4)
	15 invokestatic (0, 4)
	16 org/apache/commons/math3/analysis/integration/gauss/GaussIntegratorFactory.transform:(Lorg/apache/commons/math3/util/Pair;DD)Lorg/apache/commons/math3/util/Pair; (0, 4)
	18 invokespecial (0, 4)
	19 org/apache/commons/math3/analysis/integration/gauss/GaussIntegrator.<init>:(Lorg/apache/commons/math3/util/Pair;)V (0, 4)
	21 areturn (0, 4)

Method: hermite
	0 new (0, 0)
	1 org/apache/commons/math3/analysis/integration/gauss/SymmetricGaussIntegrator (0, 0)
	3 dup (0, 0)
	4 aload_0 (0, 0)
	5 getfield (0, 0)
	6 org/apache/commons/math3/analysis/integration/gauss/GaussIntegratorFactory.hermite:Lorg/apache/commons/math3/analysis/integration/gauss/BaseRuleFactory; (0, 0)
	8 iload_1 (0, 0)
	9 invokestatic (0, 0)
	10 org/apache/commons/math3/analysis/integration/gauss/GaussIntegratorFactory.getRule:(Lorg/apache/commons/math3/analysis/integration/gauss/BaseRuleFactory;I)Lorg/apache/commons/math3/util/Pair; (0, 0)
	12 invokespecial (0, 0)
	13 org/apache/commons/math3/analysis/integration/gauss/SymmetricGaussIntegrator.<init>:(Lorg/apache/commons/math3/util/Pair;)V (0, 0)
	15 areturn (0, 0)

Method: getRule
	0 aload_0 (0, 0)
	1 iload_1 (0, 0)
	2 invokevirtual (0, 0)
	3 org/apache/commons/math3/analysis/integration/gauss/BaseRuleFactory.getRule:(I)Lorg/apache/commons/math3/util/Pair; (0, 0)
	5 areturn (0, 0)

Method: transform
	0 aload_0 (0, 0)
	1 invokevirtual (0, 0)
	2 org/apache/commons/math3/util/Pair.getFirst:()Ljava/lang/Object; (0, 0)
	4 checkcast (0, 0)
	5 [D (0, 0)
	7 astore (0, 0)
	8 #5 (0, 0)
	9 aload_0 (0, 0)
	10 invokevirtual (0, 0)
	11 org/apache/commons/math3/util/Pair.getSecond:()Ljava/lang/Object; (0, 0)
	13 checkcast (0, 0)
	14 [D (0, 0)
	16 astore (0, 0)
	17 #6 (0, 0)
	18 dload_3 (0, 0)
	19 dload_1 (0, 0)
	20 dsub (0, 0)
	21 ldc2_w (0, 0)
	22 2.0 (0, 0)
	24 ddiv (0, 0)
	25 dstore (0, 0)
	26 #7 (0, 0)
	27 dload_1 (0, 1)
	28 dload (0, 1)
	29 #7 (0, 1)
	30 dadd (0, 1)
	31 dstore (0, 1)
	32 #9 (0, 1)
	33 iconst_0 (1, 4)
	34 istore (1, 4)
	35 #11 (1, 4)
	36 iload (1, 4)
	37 #11 (1, 4)
	38 aload (1, 4)
	39 #5 (1, 4)
	40 arraylength (1, 4)
	41 if_icmpge (1, 4)
	42 35 (1, 4)
	44 aload (1, 1)
	45 #5 (1, 1)
	46 iload (1, 1)
	47 #11 (1, 1)
	48 aload (1, 1)
	49 #5 (1, 1)
	50 iload (1, 1)
	51 #11 (1, 1)
	52 daload (1, 1)
	53 dload (1, 1)
	54 #7 (1, 1)
	55 dmul (1, 1)
	56 dload (1, 1)
	57 #9 (1, 1)
	58 dadd (1, 1)
	59 dastore (1, 1)
	60 aload (1, 1)
	61 #6 (1, 1)
	62 iload (1, 1)
	63 #11 (1, 1)
	64 dup2 (1, 1)
	65 daload (1, 1)
	66 dload (1, 1)
	67 #7 (1, 1)
	68 dmul (1, 1)
	69 dastore (1, 1)
	70 iinc (1, 1)
	71 #11 (1, 1)
	72 -89 (1, 1)
	73 goto (1, 1)
	74 -37 (1, 1)
	76 new (0, 1)
	77 org/apache/commons/math3/util/Pair (0, 1)
	79 dup (0, 1)
	80 aload (0, 1)
	81 #5 (0, 1)
	82 aload (0, 1)
	83 #6 (0, 1)
	84 invokespecial (0, 1)
	85 org/apache/commons/math3/util/Pair.<init>:(Ljava/lang/Object;Ljava/lang/Object;)V (0, 1)
	87 areturn (0, 1)

