Method: <init>
	0 aload_0 (0, 0)
	1 aload_1 (0, 0)
	2 invokevirtual (0, 0)
	3 org/apache/commons/math3/util/Pair.getFirst:()Ljava/lang/Object; (0, 0)
	5 checkcast (0, 0)
	6 [D (0, 0)
	8 aload_1 (0, 0)
	9 invokevirtual (0, 0)
	10 org/apache/commons/math3/util/Pair.getSecond:()Ljava/lang/Object; (0, 0)
	12 checkcast (0, 0)
	13 [D (0, 0)
	15 invokespecial (0, 0)
	16 org/apache/commons/math3/analysis/integration/gauss/GaussIntegrator.<init>:([D[D)V (0, 0)
	18 return (0, 0)

Method: integrate
	0 dconst_0 (0, 0)
	1 dstore_2 (0, 0)
	2 dconst_0 (0, 0)
	3 dstore (0, 0)
	4 #4 (0, 0)
	5 iconst_0 (0, 0)
	6 istore (0, 0)
	7 #6 (0, 0)
	8 iload (0, 0)
	9 #6 (0, 0)
	10 aload_0 (0, 0)
	11 getfield (0, 0)
	12 org/apache/commons/math3/analysis/integration/gauss/GaussIntegrator.points:[D (0, 0)
	14 arraylength (0, 0)
	15 if_icmpge (0, 0)
	16 61 (0, 0)
	18 aload_0 (1, 4)
	19 getfield (1, 4)
	20 org/apache/commons/math3/analysis/integration/gauss/GaussIntegrator.points:[D (1, 4)
	22 iload (1, 4)
	23 #6 (1, 4)
	24 daload (1, 4)
	25 dstore (1, 4)
	26 #7 (1, 4)
	27 aload_0 (1, 4)
	28 getfield (1, 4)
	29 org/apache/commons/math3/analysis/integration/gauss/GaussIntegrator.weights:[D (1, 4)
	31 iload (1, 4)
	32 #6 (1, 4)
	33 daload (1, 4)
	34 dstore (1, 4)
	35 #9 (1, 4)
	36 dload (1, 4)
	37 #9 (1, 4)
	38 aload_1 (1, 4)
	39 dload (1, 4)
	40 #7 (1, 4)
	41 invokeinterface (1, 4)
	42 org/apache/commons/math3/analysis/UnivariateFunction.org/apache/commons/math3/analysis/integration/gauss/GaussIntegrator (1, 4)
	44 0 (1, 4)
	46 dmul (1, 4)
	47 dload (1, 4)
	48 #4 (1, 4)
	49 dsub (1, 4)
	50 dstore (1, 4)
	51 #11 (1, 4)
	52 dload_2 (1, 4)
	53 dload (1, 4)
	54 #11 (1, 4)
	55 dadd (1, 4)
	56 dstore (1, 4)
	57 #13 (1, 4)
	58 dload (1, 4)
	59 #13 (1, 4)
	60 dload_2 (1, 4)
	61 dsub (1, 4)
	62 dload (1, 4)
	63 #11 (1, 4)
	64 dsub (1, 4)
	65 dstore (1, 4)
	66 #4 (1, 4)
	67 dload (1, 4)
	68 #13 (1, 4)
	69 dstore_2 (1, 4)
	70 iinc (1, 4)
	71 #6 (1, 4)
	72 -89 (1, 4)
	73 goto (1, 4)
	74 -65 (1, 4)
	76 dload_2 (3, 1)
	77 dreturn (0, 1)

Method: getNumberOfPoints
	0 aload_0 (0, 0)
	1 getfield (0, 0)
	2 org/apache/commons/math3/analysis/integration/gauss/GaussIntegrator.points:[D (0, 0)
	4 arraylength (0, 0)
	5 ireturn (0, 0)

Method: getPoint
	0 aload_0 (0, 0)
	1 getfield (0, 0)
	2 org/apache/commons/math3/analysis/integration/gauss/GaussIntegrator.points:[D (0, 0)
	4 iload_1 (0, 0)
	5 daload (0, 0)
	6 dreturn (0, 0)

Method: getWeight
	0 aload_0 (0, 0)
	1 getfield (0, 0)
	2 org/apache/commons/math3/analysis/integration/gauss/GaussIntegrator.weights:[D (0, 0)
	4 iload_1 (0, 0)
	5 daload (0, 0)
	6 dreturn (0, 0)

