Method: <init>
	0 aload_0 (0, 0)
	1 invokespecial (0, 0)
	2 org/apache/commons/math3/analysis/integration/gauss/BaseRuleFactory.<init>:()V (0, 0)
	4 aload_0 (0, 0)
	5 aload_1 (0, 0)
	6 putfield (0, 0)
	7 org/apache/commons/math3/analysis/integration/gauss/LegendreHighPrecisionRuleFactory.mContext:Ljava/math/MathContext; (0, 0)
	9 aload_0 (0, 0)
	10 new (0, 0)
	11 java/math/BigDecimal (0, 0)
	13 dup (0, 0)
	14 ldc (0, 0)
	15 2 (0, 0)
	16 aload_1 (0, 0)
	17 invokespecial (0, 0)
	18 java/math/BigDecimal.<init>:(Ljava/lang/String;Ljava/math/MathContext;)V (0, 0)
	20 putfield (0, 0)
	21 org/apache/commons/math3/analysis/integration/gauss/LegendreHighPrecisionRuleFactory.two:Ljava/math/BigDecimal; (0, 0)
	23 aload_0 (0, 0)
	24 new (0, 0)
	25 java/math/BigDecimal (0, 0)
	27 dup (0, 0)
	28 ldc (0, 0)
	29 -1 (0, 0)
	30 aload_1 (0, 0)
	31 invokespecial (0, 0)
	32 java/math/BigDecimal.<init>:(Ljava/lang/String;Ljava/math/MathContext;)V (0, 0)
	34 putfield (0, 0)
	35 org/apache/commons/math3/analysis/integration/gauss/LegendreHighPrecisionRuleFactory.minusOne:Ljava/math/BigDecimal; (0, 0)
	37 aload_0 (0, 0)
	38 new (0, 0)
	39 java/math/BigDecimal (0, 0)
	41 dup (0, 0)
	42 ldc (0, 0)
	43 0.5 (0, 0)
	44 aload_1 (0, 0)
	45 invokespecial (0, 0)
	46 java/math/BigDecimal.<init>:(Ljava/lang/String;Ljava/math/MathContext;)V (0, 0)
	48 putfield (0, 0)
	49 org/apache/commons/math3/analysis/integration/gauss/LegendreHighPrecisionRuleFactory.oneHalf:Ljava/math/BigDecimal; (0, 0)
	51 return (0, 0)

Method: computeRule
	0 iload_1 (1, 1)
	1 iconst_1 (1, 1)
	2 if_icmpne (1, 1)
	3 32 (1, 1)
	5 new (1, 1)
	6 org/apache/commons/math3/util/Pair (1, 1)
	8 dup (1, 1)
	9 iconst_1 (1, 1)
	10 anewarray (1, 1)
	11 java/math/BigDecimal (1, 1)
	13 dup (1, 1)
	14 iconst_0 (1, 1)
	15 getstatic (1, 1)
	16 java/math/BigDecimal.ZERO:Ljava/math/BigDecimal; (1, 1)
	18 aastore (1, 1)
	19 iconst_1 (1, 1)
	20 anewarray (1, 1)
	21 java/math/BigDecimal (1, 1)
	23 dup (1, 1)
	24 iconst_0 (1, 1)
	25 aload_0 (1, 1)
	26 getfield (1, 1)
	27 org/apache/commons/math3/analysis/integration/gauss/LegendreHighPrecisionRuleFactory.two:Ljava/math/BigDecimal; (1, 1)
	29 aastore (1, 1)
	30 invokespecial (1, 1)
	31 org/apache/commons/math3/util/Pair.<init>:(Ljava/lang/Object;Ljava/lang/Object;)V (1, 1)
	33 areturn (1, 1)
	34 aload_0 (0, 0)
	35 iload_1 (0, 0)
	36 iconst_1 (0, 0)
	37 isub (0, 0)
	38 invokevirtual (0, 0)
	39 org/apache/commons/math3/analysis/integration/gauss/LegendreHighPrecisionRuleFactory.getRuleInternal:(I)Lorg/apache/commons/math3/util/Pair; (0, 0)
	41 invokevirtual (0, 0)
	42 org/apache/commons/math3/util/Pair.getFirst:()Ljava/lang/Object; (0, 0)
	44 checkcast (0, 0)
	45 [Ljava/math/BigDecimal; (0, 0)
	47 astore_2 (0, 0)
	48 iload_1 (0, 0)
	49 anewarray (0, 0)
	50 java/math/BigDecimal (0, 0)
	52 astore_3 (0, 0)
	53 iload_1 (0, 0)
	54 anewarray (0, 0)
	55 java/math/BigDecimal (0, 0)
	57 astore (0, 0)
	58 #4 (0, 0)
	59 iload_1 (0, 0)
	60 iconst_2 (0, 0)
	61 idiv (0, 0)
	62 istore (0, 0)
	63 #5 (0, 0)
	64 iconst_0 (1, 4)
	65 istore (1, 4)
	66 #6 (1, 4)
	67 iload (1, 4)
	68 #6 (1, 4)
	69 iload (1, 4)
	70 #5 (1, 4)
	71 if_icmpge (1, 4)
	72 738 (1, 4)
	74 iload (1, 4)
	75 #6 (1, 4)
	76 ifne (1, 4)
	77 10 (1, 4)
	79 aload_0 (1, 4)
	80 getfield (1, 4)
	81 org/apache/commons/math3/analysis/integration/gauss/LegendreHighPrecisionRuleFactory.minusOne:Ljava/math/BigDecimal; (1, 4)
	83 goto (1, 4)
	84 9 (1, 4)
	86 aload_2 (1, 4)
	87 iload (1, 4)
	88 #6 (1, 4)
	89 iconst_1 (1, 4)
	90 isub (1, 4)
	91 aaload (1, 4)
	92 astore (1, 4)
	93 #7 (1, 4)
	94 iload (1, 4)
	95 #5 (1, 4)
	96 iconst_1 (1, 4)
	97 if_icmpne (1, 4)
	98 9 (1, 4)
	100 getstatic (1, 4)
	101 java/math/BigDecimal.ONE:Ljava/math/BigDecimal; (1, 4)
	103 goto (1, 4)
	104 7 (1, 4)
	106 aload_2 (1, 4)
	107 iload (1, 4)
	108 #6 (1, 4)
	109 aaload (1, 4)
	110 astore (1, 4)
	111 #8 (1, 4)
	112 getstatic (1, 4)
	113 java/math/BigDecimal.ONE:Ljava/math/BigDecimal; (1, 4)
	115 astore (1, 4)
	116 #9 (1, 4)
	117 aload (1, 4)
	118 #7 (1, 4)
	119 astore (1, 4)
	120 #10 (1, 4)
	121 getstatic (1, 4)
	122 java/math/BigDecimal.ONE:Ljava/math/BigDecimal; (1, 4)
	124 astore (1, 4)
	125 #11 (1, 4)
	126 aload (1, 4)
	127 #8 (1, 4)
	128 astore (1, 4)
	129 #12 (1, 4)
	130 iconst_1 (2, 4)
	131 istore (2, 4)
	132 #13 (2, 4)
	133 iload (2, 4)
	134 #13 (2, 4)
	135 iload_1 (2, 4)
	136 if_icmpge (2, 4)
	137 206 (2, 4)
	139 new (2, 4)
	140 java/math/BigDecimal (2, 4)
	142 dup (2, 4)
	143 iconst_2 (2, 4)
	144 iload (2, 4)
	145 #13 (2, 4)
	146 imul (2, 4)
	147 iconst_1 (2, 4)
	148 iadd (2, 4)
	149 aload_0 (2, 4)
	150 getfield (2, 4)
	151 org/apache/commons/math3/analysis/integration/gauss/LegendreHighPrecisionRuleFactory.mContext:Ljava/math/MathContext; (2, 4)
	153 invokespecial (2, 4)
	154 java/math/BigDecimal.<init>:(ILjava/math/MathContext;)V (2, 4)
	156 astore (2, 4)
	157 #14 (2, 4)
	158 new (2, 4)
	159 java/math/BigDecimal (2, 4)
	161 dup (2, 4)
	162 iload (2, 4)
	163 #13 (2, 4)
	164 aload_0 (2, 4)
	165 getfield (2, 4)
	166 org/apache/commons/math3/analysis/integration/gauss/LegendreHighPrecisionRuleFactory.mContext:Ljava/math/MathContext; (2, 4)
	168 invokespecial (2, 4)
	169 java/math/BigDecimal.<init>:(ILjava/math/MathContext;)V (2, 4)
	171 astore (2, 4)
	172 #15 (2, 4)
	173 new (2, 4)
	174 java/math/BigDecimal (2, 4)
	176 dup (2, 4)
	177 iload (2, 4)
	178 #13 (2, 4)
	179 iconst_1 (2, 4)
	180 iadd (2, 4)
	181 aload_0 (2, 4)
	182 getfield (2, 4)
	183 org/apache/commons/math3/analysis/integration/gauss/LegendreHighPrecisionRuleFactory.mContext:Ljava/math/MathContext; (2, 4)
	185 invokespecial (2, 4)
	186 java/math/BigDecimal.<init>:(ILjava/math/MathContext;)V (2, 4)
	188 astore (2, 4)
	189 #16 (2, 4)
	190 aload (2, 4)
	191 #7 (2, 4)
	192 aload (2, 4)
	193 #14 (2, 4)
	194 aload_0 (2, 4)
	195 getfield (2, 4)
	196 org/apache/commons/math3/analysis/integration/gauss/LegendreHighPrecisionRuleFactory.mContext:Ljava/math/MathContext; (2, 4)
	198 invokevirtual (2, 4)
	199 java/math/BigDecimal.multiply:(Ljava/math/BigDecimal;Ljava/math/MathContext;)Ljava/math/BigDecimal; (2, 4)
	201 astore (2, 4)
	202 #17 (2, 4)
	203 aload (2, 4)
	204 #10 (2, 4)
	205 aload (2, 4)
	206 #17 (2, 4)
	207 aload_0 (2, 4)
	208 getfield (2, 4)
	209 org/apache/commons/math3/analysis/integration/gauss/LegendreHighPrecisionRuleFactory.mContext:Ljava/math/MathContext; (2, 4)
	211 invokevirtual (2, 4)
	212 java/math/BigDecimal.multiply:(Ljava/math/BigDecimal;Ljava/math/MathContext;)Ljava/math/BigDecimal; (2, 4)
	214 astore (2, 4)
	215 #17 (2, 4)
	216 aload (2, 4)
	217 #9 (2, 4)
	218 aload (2, 4)
	219 #15 (2, 4)
	220 aload_0 (2, 4)
	221 getfield (2, 4)
	222 org/apache/commons/math3/analysis/integration/gauss/LegendreHighPrecisionRuleFactory.mContext:Ljava/math/MathContext; (2, 4)
	224 invokevirtual (2, 4)
	225 java/math/BigDecimal.multiply:(Ljava/math/BigDecimal;Ljava/math/MathContext;)Ljava/math/BigDecimal; (2, 4)
	227 astore (2, 4)
	228 #18 (2, 4)
	229 aload (2, 4)
	230 #17 (2, 4)
	231 aload (2, 4)
	232 #18 (2, 4)
	233 aload_0 (2, 4)
	234 getfield (2, 4)
	235 org/apache/commons/math3/analysis/integration/gauss/LegendreHighPrecisionRuleFactory.mContext:Ljava/math/MathContext; (2, 4)
	237 invokevirtual (2, 4)
	238 java/math/BigDecimal.subtract:(Ljava/math/BigDecimal;Ljava/math/MathContext;)Ljava/math/BigDecimal; (2, 4)
	240 astore (2, 4)
	241 #19 (2, 4)
	242 aload (2, 4)
	243 #19 (2, 4)
	244 aload (2, 4)
	245 #16 (2, 4)
	246 aload_0 (2, 4)
	247 getfield (2, 4)
	248 org/apache/commons/math3/analysis/integration/gauss/LegendreHighPrecisionRuleFactory.mContext:Ljava/math/MathContext; (2, 4)
	250 invokevirtual (2, 4)
	251 java/math/BigDecimal.divide:(Ljava/math/BigDecimal;Ljava/math/MathContext;)Ljava/math/BigDecimal; (2, 4)
	253 astore (2, 4)
	254 #19 (2, 4)
	255 aload (2, 4)
	256 #8 (2, 4)
	257 aload (2, 4)
	258 #14 (2, 4)
	259 aload_0 (2, 4)
	260 getfield (2, 4)
	261 org/apache/commons/math3/analysis/integration/gauss/LegendreHighPrecisionRuleFactory.mContext:Ljava/math/MathContext; (2, 4)
	263 invokevirtual (2, 4)
	264 java/math/BigDecimal.multiply:(Ljava/math/BigDecimal;Ljava/math/MathContext;)Ljava/math/BigDecimal; (2, 4)
	266 astore (2, 4)
	267 #17 (2, 4)
	268 aload (2, 4)
	269 #12 (2, 4)
	270 aload (2, 4)
	271 #17 (2, 4)
	272 aload_0 (2, 4)
	273 getfield (2, 4)
	274 org/apache/commons/math3/analysis/integration/gauss/LegendreHighPrecisionRuleFactory.mContext:Ljava/math/MathContext; (2, 4)
	276 invokevirtual (2, 4)
	277 java/math/BigDecimal.multiply:(Ljava/math/BigDecimal;Ljava/math/MathContext;)Ljava/math/BigDecimal; (2, 4)
	279 astore (2, 4)
	280 #17 (2, 4)
	281 aload (2, 4)
	282 #11 (2, 4)
	283 aload (2, 4)
	284 #15 (2, 4)
	285 aload_0 (2, 4)
	286 getfield (2, 4)
	287 org/apache/commons/math3/analysis/integration/gauss/LegendreHighPrecisionRuleFactory.mContext:Ljava/math/MathContext; (2, 4)
	289 invokevirtual (2, 4)
	290 java/math/BigDecimal.multiply:(Ljava/math/BigDecimal;Ljava/math/MathContext;)Ljava/math/BigDecimal; (2, 4)
	292 astore (2, 4)
	293 #18 (2, 4)
	294 aload (2, 4)
	295 #17 (2, 4)
	296 aload (2, 4)
	297 #18 (2, 4)
	298 aload_0 (2, 4)
	299 getfield (2, 4)
	300 org/apache/commons/math3/analysis/integration/gauss/LegendreHighPrecisionRuleFactory.mContext:Ljava/math/MathContext; (2, 4)
	302 invokevirtual (2, 4)
	303 java/math/BigDecimal.subtract:(Ljava/math/BigDecimal;Ljava/math/MathContext;)Ljava/math/BigDecimal; (2, 4)
	305 astore (2, 4)
	306 #20 (2, 4)
	307 aload (2, 4)
	308 #20 (2, 4)
	309 aload (2, 4)
	310 #16 (2, 4)
	311 aload_0 (2, 4)
	312 getfield (2, 4)
	313 org/apache/commons/math3/analysis/integration/gauss/LegendreHighPrecisionRuleFactory.mContext:Ljava/math/MathContext; (2, 4)
	315 invokevirtual (2, 4)
	316 java/math/BigDecimal.divide:(Ljava/math/BigDecimal;Ljava/math/MathContext;)Ljava/math/BigDecimal; (2, 4)
	318 astore (2, 4)
	319 #20 (2, 4)
	320 aload (2, 4)
	321 #10 (2, 4)
	322 astore (2, 4)
	323 #9 (2, 4)
	324 aload (2, 4)
	325 #19 (2, 4)
	326 astore (2, 4)
	327 #10 (2, 4)
	328 aload (2, 4)
	329 #12 (2, 4)
	330 astore (2, 4)
	331 #11 (2, 4)
	332 aload (2, 4)
	333 #20 (2, 4)
	334 astore (2, 4)
	335 #12 (2, 4)
	336 iinc (2, 4)
	337 #13 (2, 4)
	338 -89 (2, 4)
	339 goto (2, 4)
	340 -206 (2, 4)
	342 aload (1, 4)
	343 #7 (1, 4)
	344 aload (1, 4)
	345 #8 (1, 4)
	346 aload_0 (1, 4)
	347 getfield (1, 4)
	348 org/apache/commons/math3/analysis/integration/gauss/LegendreHighPrecisionRuleFactory.mContext:Ljava/math/MathContext; (1, 4)
	350 invokevirtual (1, 4)
	351 java/math/BigDecimal.add:(Ljava/math/BigDecimal;Ljava/math/MathContext;)Ljava/math/BigDecimal; (1, 4)
	353 aload_0 (1, 4)
	354 getfield (1, 4)
	355 org/apache/commons/math3/analysis/integration/gauss/LegendreHighPrecisionRuleFactory.oneHalf:Ljava/math/BigDecimal; (1, 4)
	357 aload_0 (1, 4)
	358 getfield (1, 4)
	359 org/apache/commons/math3/analysis/integration/gauss/LegendreHighPrecisionRuleFactory.mContext:Ljava/math/MathContext; (1, 4)
	361 invokevirtual (1, 4)
	362 java/math/BigDecimal.multiply:(Ljava/math/BigDecimal;Ljava/math/MathContext;)Ljava/math/BigDecimal; (1, 4)
	364 astore (1, 4)
	365 #13 (1, 4)
	366 getstatic (1, 4)
	367 java/math/BigDecimal.ONE:Ljava/math/BigDecimal; (1, 4)
	369 astore (1, 4)
	370 #14 (1, 4)
	371 aload (1, 4)
	372 #13 (1, 4)
	373 astore (1, 4)
	374 #15 (1, 4)
	375 iconst_0 (1, 4)
	376 istore (1, 4)
	377 #16 (1, 4)
	378 iload (2, 3)
	379 #16 (2, 3)
	380 ifne (2, 3)
	381 271 (2, 3)
	383 aload (2, 3)
	384 #8 (2, 3)
	385 aload (2, 3)
	386 #7 (2, 3)
	387 aload_0 (2, 3)
	388 getfield (2, 3)
	389 org/apache/commons/math3/analysis/integration/gauss/LegendreHighPrecisionRuleFactory.mContext:Ljava/math/MathContext; (2, 3)
	391 invokevirtual (2, 3)
	392 java/math/BigDecimal.subtract:(Ljava/math/BigDecimal;Ljava/math/MathContext;)Ljava/math/BigDecimal; (2, 3)
	394 astore (2, 3)
	395 #17 (2, 3)
	396 aload (2, 3)
	397 #13 (2, 3)
	398 invokevirtual (2, 3)
	399 java/math/BigDecimal.ulp:()Ljava/math/BigDecimal; (2, 3)
	401 getstatic (2, 3)
	402 java/math/BigDecimal.TEN:Ljava/math/BigDecimal; (2, 3)
	404 aload_0 (2, 3)
	405 getfield (2, 3)
	406 org/apache/commons/math3/analysis/integration/gauss/LegendreHighPrecisionRuleFactory.mContext:Ljava/math/MathContext; (2, 3)
	408 invokevirtual (2, 3)
	409 java/math/BigDecimal.multiply:(Ljava/math/BigDecimal;Ljava/math/MathContext;)Ljava/math/BigDecimal; (2, 3)
	411 astore (2, 3)
	412 #18 (2, 3)
	413 aload (2, 3)
	414 #17 (2, 3)
	415 aload (2, 3)
	416 #18 (2, 3)
	417 invokevirtual (2, 3)
	418 java/math/BigDecimal.compareTo:(Ljava/math/BigDecimal;)I (2, 3)
	420 ifgt (2, 3)
	421 7 (2, 3)
	423 iconst_1 (2, 3)
	424 goto (2, 3)
	425 4 (2, 3)
	427 iconst_0 (2, 3)
	428 istore (2, 3)
	429 #16 (2, 3)
	430 getstatic (2, 3)
	431 java/math/BigDecimal.ONE:Ljava/math/BigDecimal; (2, 3)
	433 astore (2, 3)
	434 #14 (2, 3)
	435 aload (2, 3)
	436 #13 (2, 3)
	437 astore (2, 3)
	438 #15 (2, 3)
	439 iconst_1 (3, 4)
	440 istore (3, 4)
	441 #19 (3, 4)
	442 iload (3, 4)
	443 #19 (3, 4)
	444 iload_1 (3, 4)
	445 if_icmpge (3, 4)
	446 133 (3, 4)
	448 new (3, 4)
	449 java/math/BigDecimal (3, 4)
	451 dup (3, 4)
	452 iconst_2 (3, 4)
	453 iload (3, 4)
	454 #19 (3, 4)
	455 imul (3, 4)
	456 iconst_1 (3, 4)
	457 iadd (3, 4)
	458 aload_0 (3, 4)
	459 getfield (3, 4)
	460 org/apache/commons/math3/analysis/integration/gauss/LegendreHighPrecisionRuleFactory.mContext:Ljava/math/MathContext; (3, 4)
	462 invokespecial (3, 4)
	463 java/math/BigDecimal.<init>:(ILjava/math/MathContext;)V (3, 4)
	465 astore (3, 4)
	466 #20 (3, 4)
	467 new (3, 4)
	468 java/math/BigDecimal (3, 4)
	470 dup (3, 4)
	471 iload (3, 4)
	472 #19 (3, 4)
	473 aload_0 (3, 4)
	474 getfield (3, 4)
	475 org/apache/commons/math3/analysis/integration/gauss/LegendreHighPrecisionRuleFactory.mContext:Ljava/math/MathContext; (3, 4)
	477 invokespecial (3, 4)
	478 java/math/BigDecimal.<init>:(ILjava/math/MathContext;)V (3, 4)
	480 astore (3, 4)
	481 #21 (3, 4)
	482 new (3, 4)
	483 java/math/BigDecimal (3, 4)
	485 dup (3, 4)
	486 iload (3, 4)
	487 #19 (3, 4)
	488 iconst_1 (3, 4)
	489 iadd (3, 4)
	490 aload_0 (3, 4)
	491 getfield (3, 4)
	492 org/apache/commons/math3/analysis/integration/gauss/LegendreHighPrecisionRuleFactory.mContext:Ljava/math/MathContext; (3, 4)
	494 invokespecial (3, 4)
	495 java/math/BigDecimal.<init>:(ILjava/math/MathContext;)V (3, 4)
	497 astore (3, 4)
	498 #22 (3, 4)
	499 aload (3, 4)
	500 #13 (3, 4)
	501 aload (3, 4)
	502 #20 (3, 4)
	503 aload_0 (3, 4)
	504 getfield (3, 4)
	505 org/apache/commons/math3/analysis/integration/gauss/LegendreHighPrecisionRuleFactory.mContext:Ljava/math/MathContext; (3, 4)
	507 invokevirtual (3, 4)
	508 java/math/BigDecimal.multiply:(Ljava/math/BigDecimal;Ljava/math/MathContext;)Ljava/math/BigDecimal; (3, 4)
	510 astore (3, 4)
	511 #17 (3, 4)
	512 aload (3, 4)
	513 #15 (3, 4)
	514 aload (3, 4)
	515 #17 (3, 4)
	516 aload_0 (3, 4)
	517 getfield (3, 4)
	518 org/apache/commons/math3/analysis/integration/gauss/LegendreHighPrecisionRuleFactory.mContext:Ljava/math/MathContext; (3, 4)
	520 invokevirtual (3, 4)
	521 java/math/BigDecimal.multiply:(Ljava/math/BigDecimal;Ljava/math/MathContext;)Ljava/math/BigDecimal; (3, 4)
	523 astore (3, 4)
	524 #17 (3, 4)
	525 aload (3, 4)
	526 #14 (3, 4)
	527 aload (3, 4)
	528 #21 (3, 4)
	529 aload_0 (3, 4)
	530 getfield (3, 4)
	531 org/apache/commons/math3/analysis/integration/gauss/LegendreHighPrecisionRuleFactory.mContext:Ljava/math/MathContext; (3, 4)
	533 invokevirtual (3, 4)
	534 java/math/BigDecimal.multiply:(Ljava/math/BigDecimal;Ljava/math/MathContext;)Ljava/math/BigDecimal; (3, 4)
	536 astore (3, 4)
	537 #18 (3, 4)
	538 aload (3, 4)
	539 #17 (3, 4)
	540 aload (3, 4)
	541 #18 (3, 4)
	542 aload_0 (3, 4)
	543 getfield (3, 4)
	544 org/apache/commons/math3/analysis/integration/gauss/LegendreHighPrecisionRuleFactory.mContext:Ljava/math/MathContext; (3, 4)
	546 invokevirtual (3, 4)
	547 java/math/BigDecimal.subtract:(Ljava/math/BigDecimal;Ljava/math/MathContext;)Ljava/math/BigDecimal; (3, 4)
	549 astore (3, 4)
	550 #23 (3, 4)
	551 aload (3, 4)
	552 #23 (3, 4)
	553 aload (3, 4)
	554 #22 (3, 4)
	555 aload_0 (3, 4)
	556 getfield (3, 4)
	557 org/apache/commons/math3/analysis/integration/gauss/LegendreHighPrecisionRuleFactory.mContext:Ljava/math/MathContext; (3, 4)
	559 invokevirtual (3, 4)
	560 java/math/BigDecimal.divide:(Ljava/math/BigDecimal;Ljava/math/MathContext;)Ljava/math/BigDecimal; (3, 4)
	562 astore (3, 4)
	563 #23 (3, 4)
	564 aload (3, 4)
	565 #15 (3, 4)
	566 astore (3, 4)
	567 #14 (3, 4)
	568 aload (3, 4)
	569 #23 (3, 4)
	570 astore (3, 4)
	571 #15 (3, 4)
	572 iinc (3, 4)
	573 #19 (3, 4)
	574 -89 (3, 4)
	575 goto (3, 4)
	576 -133 (3, 4)
	578 iload (3, 1)
	579 #16 (3, 1)
	580 ifne (3, 1)
	581 68 (3, 1)
	583 aload (4, 1)
	584 #10 (4, 1)
	585 invokevirtual (4, 1)
	586 java/math/BigDecimal.signum:()I (4, 1)
	588 aload (4, 1)
	589 #15 (4, 1)
	590 invokevirtual (4, 1)
	591 java/math/BigDecimal.signum:()I (4, 1)
	593 imul (4, 1)
	594 ifgt (4, 1)
	595 18 (4, 1)
	597 aload (4, 1)
	598 #13 (4, 1)
	599 astore (4, 1)
	600 #8 (4, 1)
	601 aload (4, 1)
	602 #14 (4, 1)
	603 astore (4, 1)
	604 #11 (4, 1)
	605 aload (4, 1)
	606 #15 (4, 1)
	607 astore (4, 1)
	608 #12 (4, 1)
	609 goto (4, 1)
	610 15 (4, 1)
	612 aload (4, 2)
	613 #13 (4, 2)
	614 astore (4, 2)
	615 #7 (4, 2)
	616 aload (4, 2)
	617 #14 (4, 2)
	618 astore (4, 2)
	619 #9 (4, 2)
	620 aload (4, 2)
	621 #15 (4, 2)
	622 astore (4, 2)
	623 #10 (4, 2)
	624 aload (3, 1)
	625 #7 (3, 1)
	626 aload (3, 1)
	627 #8 (3, 1)
	628 aload_0 (3, 1)
	629 getfield (3, 1)
	630 org/apache/commons/math3/analysis/integration/gauss/LegendreHighPrecisionRuleFactory.mContext:Ljava/math/MathContext; (3, 1)
	632 invokevirtual (3, 1)
	633 java/math/BigDecimal.add:(Ljava/math/BigDecimal;Ljava/math/MathContext;)Ljava/math/BigDecimal; (3, 1)
	635 aload_0 (3, 1)
	636 getfield (3, 1)
	637 org/apache/commons/math3/analysis/integration/gauss/LegendreHighPrecisionRuleFactory.oneHalf:Ljava/math/BigDecimal; (3, 1)
	639 aload_0 (3, 1)
	640 getfield (3, 1)
	641 org/apache/commons/math3/analysis/integration/gauss/LegendreHighPrecisionRuleFactory.mContext:Ljava/math/MathContext; (3, 1)
	643 invokevirtual (3, 1)
	644 java/math/BigDecimal.multiply:(Ljava/math/BigDecimal;Ljava/math/MathContext;)Ljava/math/BigDecimal; (3, 1)
	646 astore (3, 1)
	647 #13 (3, 1)
	648 goto (1, 4)
	649 -270 (1, 4)
	651 new (1, 4)
	652 java/math/BigDecimal (1, 4)
	654 dup (1, 4)
	655 iload_1 (1, 4)
	656 aload_0 (1, 4)
	657 getfield (1, 4)
	658 org/apache/commons/math3/analysis/integration/gauss/LegendreHighPrecisionRuleFactory.mContext:Ljava/math/MathContext; (1, 4)
	660 invokespecial (1, 4)
	661 java/math/BigDecimal.<init>:(ILjava/math/MathContext;)V (1, 4)
	663 astore (1, 4)
	664 #17 (1, 4)
	665 aload (1, 4)
	666 #14 (1, 4)
	667 aload (1, 4)
	668 #13 (1, 4)
	669 aload (1, 4)
	670 #15 (1, 4)
	671 aload_0 (1, 4)
	672 getfield (1, 4)
	673 org/apache/commons/math3/analysis/integration/gauss/LegendreHighPrecisionRuleFactory.mContext:Ljava/math/MathContext; (1, 4)
	675 invokevirtual (1, 4)
	676 java/math/BigDecimal.multiply:(Ljava/math/BigDecimal;Ljava/math/MathContext;)Ljava/math/BigDecimal; (1, 4)
	678 aload_0 (1, 4)
	679 getfield (1, 4)
	680 org/apache/commons/math3/analysis/integration/gauss/LegendreHighPrecisionRuleFactory.mContext:Ljava/math/MathContext; (1, 4)
	682 invokevirtual (1, 4)
	683 java/math/BigDecimal.subtract:(Ljava/math/BigDecimal;Ljava/math/MathContext;)Ljava/math/BigDecimal; (1, 4)
	685 astore (1, 4)
	686 #18 (1, 4)
	687 aload (1, 4)
	688 #18 (1, 4)
	689 aload (1, 4)
	690 #17 (1, 4)
	691 invokevirtual (1, 4)
	692 java/math/BigDecimal.multiply:(Ljava/math/BigDecimal;)Ljava/math/BigDecimal; (1, 4)
	694 astore (1, 4)
	695 #18 (1, 4)
	696 aload (1, 4)
	697 #18 (1, 4)
	698 iconst_2 (1, 4)
	699 aload_0 (1, 4)
	700 getfield (1, 4)
	701 org/apache/commons/math3/analysis/integration/gauss/LegendreHighPrecisionRuleFactory.mContext:Ljava/math/MathContext; (1, 4)
	703 invokevirtual (1, 4)
	704 java/math/BigDecimal.pow:(ILjava/math/MathContext;)Ljava/math/BigDecimal; (1, 4)
	706 astore (1, 4)
	707 #18 (1, 4)
	708 aload (1, 4)
	709 #13 (1, 4)
	710 iconst_2 (1, 4)
	711 aload_0 (1, 4)
	712 getfield (1, 4)
	713 org/apache/commons/math3/analysis/integration/gauss/LegendreHighPrecisionRuleFactory.mContext:Ljava/math/MathContext; (1, 4)
	715 invokevirtual (1, 4)
	716 java/math/BigDecimal.pow:(ILjava/math/MathContext;)Ljava/math/BigDecimal; (1, 4)
	718 astore (1, 4)
	719 #19 (1, 4)
	720 getstatic (1, 4)
	721 java/math/BigDecimal.ONE:Ljava/math/BigDecimal; (1, 4)
	723 aload (1, 4)
	724 #19 (1, 4)
	725 aload_0 (1, 4)
	726 getfield (1, 4)
	727 org/apache/commons/math3/analysis/integration/gauss/LegendreHighPrecisionRuleFactory.mContext:Ljava/math/MathContext; (1, 4)
	729 invokevirtual (1, 4)
	730 java/math/BigDecimal.subtract:(Ljava/math/BigDecimal;Ljava/math/MathContext;)Ljava/math/BigDecimal; (1, 4)
	732 astore (1, 4)
	733 #19 (1, 4)
	734 aload (1, 4)
	735 #19 (1, 4)
	736 aload_0 (1, 4)
	737 getfield (1, 4)
	738 org/apache/commons/math3/analysis/integration/gauss/LegendreHighPrecisionRuleFactory.two:Ljava/math/BigDecimal; (1, 4)
	740 aload_0 (1, 4)
	741 getfield (1, 4)
	742 org/apache/commons/math3/analysis/integration/gauss/LegendreHighPrecisionRuleFactory.mContext:Ljava/math/MathContext; (1, 4)
	744 invokevirtual (1, 4)
	745 java/math/BigDecimal.multiply:(Ljava/math/BigDecimal;Ljava/math/MathContext;)Ljava/math/BigDecimal; (1, 4)
	747 astore (1, 4)
	748 #19 (1, 4)
	749 aload (1, 4)
	750 #19 (1, 4)
	751 aload (1, 4)
	752 #18 (1, 4)
	753 aload_0 (1, 4)
	754 getfield (1, 4)
	755 org/apache/commons/math3/analysis/integration/gauss/LegendreHighPrecisionRuleFactory.mContext:Ljava/math/MathContext; (1, 4)
	757 invokevirtual (1, 4)
	758 java/math/BigDecimal.divide:(Ljava/math/BigDecimal;Ljava/math/MathContext;)Ljava/math/BigDecimal; (1, 4)
	760 astore (1, 4)
	761 #19 (1, 4)
	762 aload_3 (1, 4)
	763 iload (1, 4)
	764 #6 (1, 4)
	765 aload (1, 4)
	766 #13 (1, 4)
	767 aastore (1, 4)
	768 aload (1, 4)
	769 #4 (1, 4)
	770 iload (1, 4)
	771 #6 (1, 4)
	772 aload (1, 4)
	773 #19 (1, 4)
	774 aastore (1, 4)
	775 iload_1 (1, 4)
	776 iload (1, 4)
	777 #6 (1, 4)
	778 isub (1, 4)
	779 iconst_1 (1, 4)
	780 isub (1, 4)
	781 istore (1, 4)
	782 #20 (1, 4)
	783 aload_3 (1, 4)
	784 iload (1, 4)
	785 #20 (1, 4)
	786 aload (1, 4)
	787 #13 (1, 4)
	788 aload_0 (1, 4)
	789 getfield (1, 4)
	790 org/apache/commons/math3/analysis/integration/gauss/LegendreHighPrecisionRuleFactory.mContext:Ljava/math/MathContext; (1, 4)
	792 invokevirtual (1, 4)
	793 java/math/BigDecimal.negate:(Ljava/math/MathContext;)Ljava/math/BigDecimal; (1, 4)
	795 aastore (1, 4)
	796 aload (1, 4)
	797 #4 (1, 4)
	798 iload (1, 4)
	799 #20 (1, 4)
	800 aload (1, 4)
	801 #19 (1, 4)
	802 aastore (1, 4)
	803 iinc (1, 4)
	804 #6 (1, 4)
	805 -89 (1, 4)
	806 goto (1, 4)
	807 -739 (1, 4)
	809 iload_1 (1, 1)
	810 iconst_2 (1, 1)
	811 irem (1, 1)
	812 ifeq (1, 1)
	813 160 (1, 1)
	815 getstatic (1, 1)
	816 java/math/BigDecimal.ONE:Ljava/math/BigDecimal; (1, 1)
	818 astore (1, 1)
	819 #6 (1, 1)
	820 iconst_1 (2, 4)
	821 istore (2, 4)
	822 #7 (2, 4)
	823 iload (2, 4)
	824 #7 (2, 4)
	825 iload_1 (2, 4)
	826 if_icmpge (2, 4)
	827 78 (2, 4)
	829 new (2, 4)
	830 java/math/BigDecimal (2, 4)
	832 dup (2, 4)
	833 iload (2, 4)
	834 #7 (2, 4)
	835 aload_0 (2, 4)
	836 getfield (2, 4)
	837 org/apache/commons/math3/analysis/integration/gauss/LegendreHighPrecisionRuleFactory.mContext:Ljava/math/MathContext; (2, 4)
	839 invokespecial (2, 4)
	840 java/math/BigDecimal.<init>:(ILjava/math/MathContext;)V (2, 4)
	842 astore (2, 4)
	843 #8 (2, 4)
	844 new (2, 4)
	845 java/math/BigDecimal (2, 4)
	847 dup (2, 4)
	848 iload (2, 4)
	849 #7 (2, 4)
	850 iconst_1 (2, 4)
	851 iadd (2, 4)
	852 aload_0 (2, 4)
	853 getfield (2, 4)
	854 org/apache/commons/math3/analysis/integration/gauss/LegendreHighPrecisionRuleFactory.mContext:Ljava/math/MathContext; (2, 4)
	856 invokespecial (2, 4)
	857 java/math/BigDecimal.<init>:(ILjava/math/MathContext;)V (2, 4)
	859 astore (2, 4)
	860 #9 (2, 4)
	861 aload (2, 4)
	862 #6 (2, 4)
	863 aload (2, 4)
	864 #8 (2, 4)
	865 aload_0 (2, 4)
	866 getfield (2, 4)
	867 org/apache/commons/math3/analysis/integration/gauss/LegendreHighPrecisionRuleFactory.mContext:Ljava/math/MathContext; (2, 4)
	869 invokevirtual (2, 4)
	870 java/math/BigDecimal.multiply:(Ljava/math/BigDecimal;Ljava/math/MathContext;)Ljava/math/BigDecimal; (2, 4)
	872 astore (2, 4)
	873 #6 (2, 4)
	874 aload (2, 4)
	875 #6 (2, 4)
	876 aload (2, 4)
	877 #9 (2, 4)
	878 aload_0 (2, 4)
	879 getfield (2, 4)
	880 org/apache/commons/math3/analysis/integration/gauss/LegendreHighPrecisionRuleFactory.mContext:Ljava/math/MathContext; (2, 4)
	882 invokevirtual (2, 4)
	883 java/math/BigDecimal.divide:(Ljava/math/BigDecimal;Ljava/math/MathContext;)Ljava/math/BigDecimal; (2, 4)
	885 astore (2, 4)
	886 #6 (2, 4)
	887 aload (2, 4)
	888 #6 (2, 4)
	889 aload_0 (2, 4)
	890 getfield (2, 4)
	891 org/apache/commons/math3/analysis/integration/gauss/LegendreHighPrecisionRuleFactory.mContext:Ljava/math/MathContext; (2, 4)
	893 invokevirtual (2, 4)
	894 java/math/BigDecimal.negate:(Ljava/math/MathContext;)Ljava/math/BigDecimal; (2, 4)
	896 astore (2, 4)
	897 #6 (2, 4)
	898 iinc (2, 4)
	899 #7 (2, 4)
	900 -89 (2, 4)
	901 goto (2, 4)
	902 -78 (2, 4)
	904 new (1, 1)
	905 java/math/BigDecimal (1, 1)
	907 dup (1, 1)
	908 iload_1 (1, 1)
	909 aload_0 (1, 1)
	910 getfield (1, 1)
	911 org/apache/commons/math3/analysis/integration/gauss/LegendreHighPrecisionRuleFactory.mContext:Ljava/math/MathContext; (1, 1)
	913 invokespecial (1, 1)
	914 java/math/BigDecimal.<init>:(ILjava/math/MathContext;)V (1, 1)
	916 astore (1, 1)
	917 #7 (1, 1)
	918 aload (1, 1)
	919 #6 (1, 1)
	920 aload (1, 1)
	921 #7 (1, 1)
	922 aload_0 (1, 1)
	923 getfield (1, 1)
	924 org/apache/commons/math3/analysis/integration/gauss/LegendreHighPrecisionRuleFactory.mContext:Ljava/math/MathContext; (1, 1)
	926 invokevirtual (1, 1)
	927 java/math/BigDecimal.multiply:(Ljava/math/BigDecimal;Ljava/math/MathContext;)Ljava/math/BigDecimal; (1, 1)
	929 astore (1, 1)
	930 #8 (1, 1)
	931 aload (1, 1)
	932 #8 (1, 1)
	933 iconst_2 (1, 1)
	934 aload_0 (1, 1)
	935 getfield (1, 1)
	936 org/apache/commons/math3/analysis/integration/gauss/LegendreHighPrecisionRuleFactory.mContext:Ljava/math/MathContext; (1, 1)
	938 invokevirtual (1, 1)
	939 java/math/BigDecimal.pow:(ILjava/math/MathContext;)Ljava/math/BigDecimal; (1, 1)
	941 astore (1, 1)
	942 #8 (1, 1)
	943 aload_0 (1, 1)
	944 getfield (1, 1)
	945 org/apache/commons/math3/analysis/integration/gauss/LegendreHighPrecisionRuleFactory.two:Ljava/math/BigDecimal; (1, 1)
	947 aload (1, 1)
	948 #8 (1, 1)
	949 aload_0 (1, 1)
	950 getfield (1, 1)
	951 org/apache/commons/math3/analysis/integration/gauss/LegendreHighPrecisionRuleFactory.mContext:Ljava/math/MathContext; (1, 1)
	953 invokevirtual (1, 1)
	954 java/math/BigDecimal.divide:(Ljava/math/BigDecimal;Ljava/math/MathContext;)Ljava/math/BigDecimal; (1, 1)
	956 astore (1, 1)
	957 #9 (1, 1)
	958 aload_3 (1, 1)
	959 iload (1, 1)
	960 #5 (1, 1)
	961 getstatic (1, 1)
	962 java/math/BigDecimal.ZERO:Ljava/math/BigDecimal; (1, 1)
	964 aastore (1, 1)
	965 aload (1, 1)
	966 #4 (1, 1)
	967 iload (1, 1)
	968 #5 (1, 1)
	969 aload (1, 1)
	970 #9 (1, 1)
	971 aastore (1, 1)
	972 new (0, 4)
	973 org/apache/commons/math3/util/Pair (0, 4)
	975 dup (0, 4)
	976 aload_3 (0, 4)
	977 aload (0, 4)
	978 #4 (0, 4)
	979 invokespecial (0, 4)
	980 org/apache/commons/math3/util/Pair.<init>:(Ljava/lang/Object;Ljava/lang/Object;)V (0, 4)
	982 areturn (0, 4)

