Method: <init>
	0 aload_0 (0, 0)
	1 aload_1 (0, 0)
	2 invokevirtual (0, 0)
	3 org/apache/commons/math3/util/Pair.getFirst:()Ljava/lang/Object; (0, 0)
	5 checkcast (0, 0)
	6 [D (0, 0)
	8 aload_1 (0, 0)
	9 invokevirtual (0, 0)
	10 org/apache/commons/math3/util/Pair.getSecond:()Ljava/lang/Object; (0, 0)
	12 checkcast (0, 0)
	13 [D (0, 0)
	15 invokespecial (0, 0)
	16 org/apache/commons/math3/analysis/integration/gauss/SymmetricGaussIntegrator.<init>:([D[D)V (0, 0)
	18 return (0, 0)

Method: integrate
	0 aload_0 (0, 0)
	1 invokevirtual (0, 0)
	2 org/apache/commons/math3/analysis/integration/gauss/SymmetricGaussIntegrator.getNumberOfPoints:()I (0, 0)
	4 istore_2 (0, 0)
	5 iload_2 (1, 1)
	6 iconst_1 (1, 1)
	7 if_icmpne (1, 1)
	8 17 (1, 1)
	10 aload_0 (1, 1)
	11 iconst_0 (1, 1)
	12 invokevirtual (1, 1)
	13 org/apache/commons/math3/analysis/integration/gauss/SymmetricGaussIntegrator.getWeight:(I)D (1, 1)
	15 aload_1 (1, 1)
	16 dconst_0 (1, 1)
	17 invokeinterface (1, 1)
	18 org/apache/commons/math3/analysis/UnivariateFunction.getPoint:(I)D (1, 1)
	20 0 (1, 1)
	22 dmul (1, 1)
	23 dreturn (1, 1)
	24 iload_2 (0, 0)
	25 iconst_2 (0, 0)
	26 idiv (0, 0)
	27 istore_3 (0, 0)
	28 dconst_0 (0, 0)
	29 dstore (0, 0)
	30 #4 (0, 0)
	31 dconst_0 (0, 0)
	32 dstore (0, 0)
	33 #6 (0, 0)
	34 iconst_0 (1, 4)
	35 istore (1, 4)
	36 #8 (1, 4)
	37 iload (1, 4)
	38 #8 (1, 4)
	39 iload_3 (1, 4)
	40 if_icmpge (1, 4)
	41 80 (1, 4)
	43 aload_0 (1, 4)
	44 iload (1, 4)
	45 #8 (1, 4)
	46 invokevirtual (1, 4)
	47 org/apache/commons/math3/analysis/integration/gauss/SymmetricGaussIntegrator.getPoint:(I)D (1, 4)
	49 dstore (1, 4)
	50 #9 (1, 4)
	51 aload_0 (1, 4)
	52 iload (1, 4)
	53 #8 (1, 4)
	54 invokevirtual (1, 4)
	55 org/apache/commons/math3/analysis/integration/gauss/SymmetricGaussIntegrator.getWeight:(I)D (1, 4)
	57 dstore (1, 4)
	58 #11 (1, 4)
	59 aload_1 (1, 4)
	60 dload (1, 4)
	61 #9 (1, 4)
	62 invokeinterface (1, 4)
	63 org/apache/commons/math3/analysis/UnivariateFunction.getPoint:(I)D (1, 4)
	65 0 (1, 4)
	67 dstore (1, 4)
	68 #13 (1, 4)
	69 aload_1 (1, 4)
	70 dload (1, 4)
	71 #9 (1, 4)
	72 dneg (1, 4)
	73 invokeinterface (1, 4)
	74 org/apache/commons/math3/analysis/UnivariateFunction.getPoint:(I)D (1, 4)
	76 0 (1, 4)
	78 dstore (1, 4)
	79 #15 (1, 4)
	80 dload (1, 4)
	81 #11 (1, 4)
	82 dload (1, 4)
	83 #13 (1, 4)
	84 dload (1, 4)
	85 #15 (1, 4)
	86 dadd (1, 4)
	87 dmul (1, 4)
	88 dload (1, 4)
	89 #6 (1, 4)
	90 dsub (1, 4)
	91 dstore (1, 4)
	92 #17 (1, 4)
	93 dload (1, 4)
	94 #4 (1, 4)
	95 dload (1, 4)
	96 #17 (1, 4)
	97 dadd (1, 4)
	98 dstore (1, 4)
	99 #19 (1, 4)
	100 dload (1, 4)
	101 #19 (1, 4)
	102 dload (1, 4)
	103 #4 (1, 4)
	104 dsub (1, 4)
	105 dload (1, 4)
	106 #17 (1, 4)
	107 dsub (1, 4)
	108 dstore (1, 4)
	109 #6 (1, 4)
	110 dload (1, 4)
	111 #19 (1, 4)
	112 dstore (1, 4)
	113 #4 (1, 4)
	114 iinc (1, 4)
	115 #8 (1, 4)
	116 -89 (1, 4)
	117 goto (1, 4)
	118 -80 (1, 4)
	120 iload_2 (1, 1)
	121 iconst_2 (1, 1)
	122 irem (1, 1)
	123 ifeq (1, 1)
	124 36 (1, 1)
	126 aload_0 (1, 1)
	127 iload_3 (1, 1)
	128 invokevirtual (1, 1)
	129 org/apache/commons/math3/analysis/integration/gauss/SymmetricGaussIntegrator.getWeight:(I)D (1, 1)
	131 dstore (1, 1)
	132 #8 (1, 1)
	133 dload (1, 1)
	134 #8 (1, 1)
	135 aload_1 (1, 1)
	136 dconst_0 (1, 1)
	137 invokeinterface (1, 1)
	138 org/apache/commons/math3/analysis/UnivariateFunction.getPoint:(I)D (1, 1)
	140 0 (1, 1)
	142 dmul (1, 1)
	143 dload (1, 1)
	144 #6 (1, 1)
	145 dsub (1, 1)
	146 dstore (1, 1)
	147 #10 (1, 1)
	148 dload (1, 1)
	149 #4 (1, 1)
	150 dload (1, 1)
	151 #10 (1, 1)
	152 dadd (1, 1)
	153 dstore (1, 1)
	154 #12 (1, 1)
	155 dload (1, 1)
	156 #12 (1, 1)
	157 dstore (1, 1)
	158 #4 (1, 1)
	159 dload (0, 0)
	160 #4 (0, 0)
	161 dreturn (0, 0)

