Method: values
	0 getstatic (0, 0)
	1 org/apache/commons/math3/stat/ranking/NaNStrategy.$VALUES:[Lorg/apache/commons/math3/stat/ranking/NaNStrategy; (0, 0)
	3 invokevirtual (0, 0)
	4 [Lorg/apache/commons/math3/stat/ranking/NaNStrategy;.clone:()Ljava/lang/Object; (0, 0)
	6 checkcast (0, 0)
	7 [Lorg/apache/commons/math3/stat/ranking/NaNStrategy; (0, 0)
	9 areturn (0, 0)

Method: valueOf
	0 ldc (0, 0)
	1 org/apache/commons/math3/stat/ranking/NaNStrategy (0, 0)
	2 aload_0 (0, 0)
	3 invokestatic (0, 0)
	4 java/lang/Enum.valueOf:(Ljava/lang/Class;Ljava/lang/String;)Ljava/lang/Enum; (0, 0)
	6 checkcast (0, 0)
	7 org/apache/commons/math3/stat/ranking/NaNStrategy (0, 0)
	9 areturn (0, 0)

Method: <clinit>
	0 new (0, 0)
	1 org/apache/commons/math3/stat/ranking/NaNStrategy (0, 0)
	3 dup (0, 0)
	4 ldc (0, 0)
	5 MINIMAL (0, 0)
	6 iconst_0 (0, 0)
	7 invokespecial (0, 0)
	8 org/apache/commons/math3/stat/ranking/NaNStrategy.<init>:(Ljava/lang/String;I)V (0, 0)
	10 putstatic (0, 0)
	11 org/apache/commons/math3/stat/ranking/NaNStrategy.MINIMAL:Lorg/apache/commons/math3/stat/ranking/NaNStrategy; (0, 0)
	13 new (0, 0)
	14 org/apache/commons/math3/stat/ranking/NaNStrategy (0, 0)
	16 dup (0, 0)
	17 ldc (0, 0)
	18 MAXIMAL (0, 0)
	19 iconst_1 (0, 0)
	20 invokespecial (0, 0)
	21 org/apache/commons/math3/stat/ranking/NaNStrategy.<init>:(Ljava/lang/String;I)V (0, 0)
	23 putstatic (0, 0)
	24 org/apache/commons/math3/stat/ranking/NaNStrategy.MAXIMAL:Lorg/apache/commons/math3/stat/ranking/NaNStrategy; (0, 0)
	26 new (1, 4)
	27 org/apache/commons/math3/stat/ranking/NaNStrategy (1, 4)
	29 dup (1, 4)
	30 ldc (1, 4)
	31 REMOVED (1, 4)
	32 iconst_2 (1, 4)
	33 invokespecial (1, 4)
	34 org/apache/commons/math3/stat/ranking/NaNStrategy.<init>:(Ljava/lang/String;I)V (1, 4)
	36 putstatic (1, 4)
	37 org/apache/commons/math3/stat/ranking/NaNStrategy.REMOVED:Lorg/apache/commons/math3/stat/ranking/NaNStrategy; (1, 4)
	39 new (1, 4)
	40 org/apache/commons/math3/stat/ranking/NaNStrategy (1, 4)
	42 dup (1, 4)
	43 ldc (1, 4)
	44 FIXED (1, 4)
	45 iconst_3 (1, 4)
	46 invokespecial (1, 4)
	47 org/apache/commons/math3/stat/ranking/NaNStrategy.<init>:(Ljava/lang/String;I)V (1, 4)
	49 putstatic (1, 4)
	50 org/apache/commons/math3/stat/ranking/NaNStrategy.FIXED:Lorg/apache/commons/math3/stat/ranking/NaNStrategy; (1, 4)
	52 new (1, 4)
	53 org/apache/commons/math3/stat/ranking/NaNStrategy (1, 4)
	55 dup (1, 4)
	56 ldc (1, 4)
	57 FAILED (1, 4)
	58 iconst_4 (1, 4)
	59 invokespecial (1, 4)
	60 org/apache/commons/math3/stat/ranking/NaNStrategy.<init>:(Ljava/lang/String;I)V (1, 4)
	62 putstatic (1, 4)
	63 org/apache/commons/math3/stat/ranking/NaNStrategy.FAILED:Lorg/apache/commons/math3/stat/ranking/NaNStrategy; (1, 4)
	65 iconst_5 (1, 4)
	66 anewarray (1, 4)
	67 org/apache/commons/math3/stat/ranking/NaNStrategy (1, 4)
	69 dup (1, 4)
	70 iconst_0 (1, 4)
	71 getstatic (1, 4)
	72 org/apache/commons/math3/stat/ranking/NaNStrategy.MINIMAL:Lorg/apache/commons/math3/stat/ranking/NaNStrategy; (1, 4)
	74 aastore (1, 4)
	75 dup (1, 4)
	76 iconst_1 (1, 4)
	77 getstatic (1, 4)
	78 org/apache/commons/math3/stat/ranking/NaNStrategy.MAXIMAL:Lorg/apache/commons/math3/stat/ranking/NaNStrategy; (1, 4)
	80 aastore (1, 4)
	81 dup (1, 4)
	82 iconst_2 (1, 4)
	83 getstatic (1, 4)
	84 org/apache/commons/math3/stat/ranking/NaNStrategy.REMOVED:Lorg/apache/commons/math3/stat/ranking/NaNStrategy; (1, 4)
	86 aastore (1, 4)
	87 dup (1, 4)
	88 iconst_3 (1, 4)
	89 getstatic (1, 4)
	90 org/apache/commons/math3/stat/ranking/NaNStrategy.FIXED:Lorg/apache/commons/math3/stat/ranking/NaNStrategy; (1, 4)
	92 aastore (1, 4)
	93 dup (1, 4)
	94 iconst_4 (1, 4)
	95 getstatic (1, 4)
	96 org/apache/commons/math3/stat/ranking/NaNStrategy.FAILED:Lorg/apache/commons/math3/stat/ranking/NaNStrategy; (1, 4)
	98 aastore (1, 4)
	99 putstatic (1, 4)
	100 org/apache/commons/math3/stat/ranking/NaNStrategy.$VALUES:[Lorg/apache/commons/math3/stat/ranking/NaNStrategy; (1, 4)
	102 return (0, 4)

