Method: <init>
	0 aload_0 (0, 0)
	1 invokespecial (0, 0)
	4 aload_0 (0, 0)
	5 aload_1 (0, 0)
	6 putfield (0, 0)
	9 aload_0 (0, 0)
	10 getstatic (0, 0)
	13 putfield (0, 0)
	16 aload_0 (0, 0)
	17 new (0, 0)
	20 dup (0, 0)
	21 aload_2 (0, 0)
	22 invokespecial (0, 0)
	25 putfield (0, 0)
	28 return (0, 0)

Method: getNanStrategy
	0 aload_0 (0, 0)
	1 getfield (0, 0)
	4 areturn (0, 0)

Method: getTiesStrategy
	0 aload_0 (0, 0)
	1 getfield (0, 0)
	4 areturn (0, 0)

Method: rank
	0 aload_1 (0, 0)
	1 arraylength (0, 0)
	2 anewarray (0, 0)
	5 astore_2 (0, 0)
	6 iconst_0 (1, 4)
	7 istore_3 (1, 4)
	8 iload_3 (1, 4)
	9 aload_1 (1, 4)
	10 arraylength (1, 4)
	11 if_icmpge (1, 4)
	14 aload_2 (1, 4)
	15 iload_3 (1, 4)
	16 new (1, 4)
	19 dup (1, 4)
	20 aload_1 (1, 4)
	21 iload_3 (1, 4)
	22 daload (1, 4)
	23 iload_3 (1, 4)
	24 invokespecial (1, 4)
	27 aastore (1, 4)
	28 iinc (1, 4)
	31 goto (1, 4)
	34 aconst_null (0, 0)
	35 astore_3 (0, 0)
	36 getstatic (1, 5)
	39 aload_0 (1, 5)
	40 getfield (1, 5)
	43 invokevirtual (1, 5)
	46 iaload (1, 5)
	47 tableswitch (1, 5)
	80 aload_0 (1, 5)
	81 aload_2 (1, 5)
	82 ldc2_w (1, 5)
	85 invokespecial (1, 5)
	88 goto (1, 5)
	91 aload_0 (1, 5)
	92 aload_2 (1, 5)
	93 ldc2_w (1, 5)
	96 invokespecial (1, 5)
	99 goto (1, 5)
	102 aload_0 (1, 5)
	103 aload_2 (1, 5)
	104 invokespecial (1, 5)
	107 astore_2 (1, 5)
	108 goto (1, 5)
	111 aload_0 (1, 5)
	112 aload_2 (1, 5)
	113 invokespecial (1, 5)
	116 astore_3 (1, 5)
	117 goto (1, 5)
	120 aload_0 (1, 5)
	121 aload_2 (1, 5)
	122 invokespecial (1, 5)
	125 astore_3 (1, 5)
	126 aload_3 (2, 1)
	127 invokeinterface (2, 1)
	132 ifle (2, 1)
	135 new (2, 1)
	138 dup (2, 1)
	139 invokespecial (2, 1)
	142 athrow (2, 1)
	143 new (1, 5)
	146 dup (1, 5)
	147 invokespecial (1, 5)
	150 athrow (1, 5)
	151 aload_2 (0, 0)
	152 invokestatic (0, 0)
	155 aload_2 (0, 0)
	156 arraylength (0, 0)
	157 newarray (0, 0)
	159 astore (0, 0)
	161 iconst_1 (0, 0)
	162 istore (0, 0)
	164 aload (0, 0)
	166 aload_2 (0, 0)
	167 iconst_0 (0, 0)
	168 aaload (0, 0)
	169 invokevirtual (0, 0)
	172 iload (0, 0)
	174 i2d (0, 0)
	175 dastore (0, 0)
	176 new (0, 0)
	179 dup (0, 0)
	180 invokespecial (0, 0)
	183 astore (0, 0)
	185 aload (0, 0)
	187 aload_2 (0, 0)
	188 iconst_0 (0, 0)
	189 aaload (0, 0)
	190 invokevirtual (0, 0)
	193 invokestatic (0, 0)
	196 invokeinterface (0, 0)
	201 pop (0, 0)
	202 iconst_1 (1, 4)
	203 istore (1, 4)
	205 iload (1, 4)
	207 aload_2 (1, 4)
	208 arraylength (1, 4)
	209 if_icmpge (1, 4)
	212 aload_2 (2, 1)
	213 iload (2, 1)
	215 aaload (2, 1)
	216 invokevirtual (2, 1)
	219 aload_2 (2, 1)
	220 iload (2, 1)
	222 iconst_1 (2, 1)
	223 isub (2, 1)
	224 aaload (2, 1)
	225 invokevirtual (2, 1)
	228 invokestatic (2, 1)
	231 ifle (2, 1)
	234 iload (2, 1)
	236 iconst_1 (2, 1)
	237 iadd (2, 1)
	238 istore (2, 1)
	240 aload (3, 1)
	242 invokeinterface (3, 1)
	247 iconst_1 (3, 1)
	248 if_icmple (3, 1)
	251 aload_0 (3, 1)
	252 aload (3, 1)
	254 aload (3, 1)
	256 invokespecial (3, 1)
	259 new (2, 1)
	262 dup (2, 1)
	263 invokespecial (2, 1)
	266 astore (2, 1)
	268 aload (2, 1)
	270 aload_2 (2, 1)
	271 iload (2, 1)
	273 aaload (2, 1)
	274 invokevirtual (2, 1)
	277 invokestatic (2, 1)
	280 invokeinterface (2, 1)
	285 pop (2, 1)
	286 goto (2, 1)
	289 aload (2, 2)
	291 aload_2 (2, 2)
	292 iload (2, 2)
	294 aaload (2, 2)
	295 invokevirtual (2, 2)
	298 invokestatic (2, 2)
	301 invokeinterface (2, 2)
	306 pop (2, 2)
	307 aload (1, 1)
	309 aload_2 (1, 1)
	310 iload (1, 1)
	312 aaload (1, 1)
	313 invokevirtual (1, 1)
	316 iload (1, 1)
	318 i2d (1, 1)
	319 dastore (1, 1)
	320 iinc (1, 1)
	323 goto (1, 1)
	326 aload (1, 1)
	328 invokeinterface (1, 1)
	333 iconst_1 (1, 1)
	334 if_icmple (1, 1)
	337 aload_0 (1, 1)
	338 aload (1, 1)
	340 aload (1, 1)
	342 invokespecial (1, 1)
	345 aload_0 (1, 1)
	346 getfield (1, 1)
	349 getstatic (1, 1)
	352 if_acmpne (1, 1)
	355 aload_0 (1, 1)
	356 aload (1, 1)
	358 aload_3 (1, 1)
	359 invokespecial (1, 1)
	362 aload (0, 1)
	364 areturn (0, 1)

Method: removeNaNs
	0 aload_0 (1, 1)
	1 aload_1 (1, 1)
	2 invokespecial (1, 1)
	5 ifne (1, 1)
	8 aload_1 (1, 1)
	9 areturn (1, 1)
	10 aload_1 (0, 0)
	11 arraylength (0, 0)
	12 anewarray (0, 0)
	15 astore_2 (0, 0)
	16 iconst_0 (0, 0)
	17 istore_3 (0, 0)
	18 iconst_0 (1, 4)
	19 istore (1, 4)
	21 iload (1, 4)
	23 aload_1 (1, 4)
	24 arraylength (1, 4)
	25 if_icmpge (1, 4)
	28 aload_1 (2, 1)
	29 iload (2, 1)
	31 aaload (2, 1)
	32 invokevirtual (2, 1)
	35 invokestatic (2, 1)
	38 ifeq (2, 1)
	41 iload (3, 4)
	43 iconst_1 (3, 4)
	44 iadd (3, 4)
	45 istore (3, 4)
	47 iload (3, 4)
	49 aload_1 (3, 4)
	50 arraylength (3, 4)
	51 if_icmpge (3, 4)
	54 aload_1 (3, 4)
	55 iload (3, 4)
	57 new (3, 4)
	60 dup (3, 4)
	61 aload_1 (3, 4)
	62 iload (3, 4)
	64 aaload (3, 4)
	65 invokevirtual (3, 4)
	68 aload_1 (3, 4)
	69 iload (3, 4)
	71 aaload (3, 4)
	72 invokevirtual (3, 4)
	75 iconst_1 (3, 4)
	76 isub (3, 4)
	77 invokespecial (3, 4)
	80 aastore (3, 4)
	81 iinc (3, 4)
	84 goto (3, 4)
	87 goto (3, 4)
	90 aload_2 (2, 2)
	91 iload_3 (2, 2)
	92 new (2, 2)
	95 dup (2, 2)
	96 aload_1 (2, 2)
	97 iload (2, 2)
	99 aaload (2, 2)
	100 invokevirtual (2, 2)
	103 aload_1 (2, 2)
	104 iload (2, 2)
	106 aaload (2, 2)
	107 invokevirtual (2, 2)
	110 invokespecial (2, 2)
	113 aastore (2, 2)
	114 iinc (2, 2)
	117 iinc (2, 2)
	120 goto (2, 2)
	123 iload_3 (1, 2)
	124 anewarray (1, 2)
	127 astore (1, 2)
	129 aload_2 (1, 2)
	130 iconst_0 (1, 2)
	131 aload (1, 2)
	133 iconst_0 (1, 2)
	134 iload_3 (1, 2)
	135 invokestatic (1, 2)
	138 aload (1, 2)
	140 areturn (1, 2)

Method: recodeNaNs
	0 iconst_0 (1, 4)
	1 istore (1, 4)
	3 iload (1, 4)
	5 aload_1 (1, 4)
	6 arraylength (1, 4)
	7 if_icmpge (1, 4)
	10 aload_1 (2, 1)
	11 iload (2, 1)
	13 aaload (2, 1)
	14 invokevirtual (2, 1)
	17 invokestatic (2, 1)
	20 ifeq (2, 1)
	23 aload_1 (2, 1)
	24 iload (2, 1)
	26 new (2, 1)
	29 dup (2, 1)
	30 dload_2 (2, 1)
	31 aload_1 (2, 1)
	32 iload (2, 1)
	34 aaload (2, 1)
	35 invokevirtual (2, 1)
	38 invokespecial (2, 1)
	41 aastore (2, 1)
	42 iinc (2, 1)
	45 goto (2, 1)
	48 return (0, 0)

Method: containsNaNs
	0 iconst_0 (1, 4)
	1 istore_2 (1, 4)
	2 iload_2 (1, 4)
	3 aload_1 (1, 4)
	4 arraylength (1, 4)
	5 if_icmpge (1, 4)
	8 aload_1 (2, 1)
	9 iload_2 (2, 1)
	10 aaload (2, 1)
	11 invokevirtual (2, 1)
	14 invokestatic (2, 1)
	17 ifeq (2, 1)
	20 iconst_1 (2, 1)
	21 ireturn (2, 1)
	22 iinc (2, 1)
	25 goto (2, 1)
	28 iconst_0 (1, 4)
	29 ireturn (1, 4)

Method: resolveTie
	0 aload_1 (0, 0)
	1 aload_2 (0, 0)
	2 iconst_0 (0, 0)
	3 invokeinterface (0, 0)
	8 checkcast (0, 0)
	11 invokevirtual (0, 0)
	14 daload (0, 0)
	15 dstore_3 (0, 0)
	16 aload_2 (0, 0)
	17 invokeinterface (0, 0)
	22 istore (0, 0)
	24 getstatic (1, 5)
	27 aload_0 (1, 5)
	28 getfield (1, 5)
	31 invokevirtual (1, 5)
	34 iaload (1, 5)
	35 tableswitch (1, 5)
	68 aload_0 (1, 5)
	69 aload_1 (1, 5)
	70 aload_2 (1, 5)
	71 ldc2_w (1, 5)
	74 dload_3 (1, 5)
	75 dmul (1, 5)
	76 iload (1, 5)
	78 i2d (1, 5)
	79 dadd (1, 5)
	80 dconst_1 (1, 5)
	81 dsub (1, 5)
	82 ldc2_w (1, 5)
	85 ddiv (1, 5)
	86 invokespecial (1, 5)
	89 goto (1, 5)
	92 aload_0 (1, 5)
	93 aload_1 (1, 5)
	94 aload_2 (1, 5)
	95 dload_3 (1, 5)
	96 iload (1, 5)
	98 i2d (1, 5)
	99 dadd (1, 5)
	100 dconst_1 (1, 5)
	101 dsub (1, 5)
	102 invokespecial (1, 5)
	105 goto (1, 5)
	108 aload_0 (1, 5)
	109 aload_1 (1, 5)
	110 aload_2 (1, 5)
	111 dload_3 (1, 5)
	112 invokespecial (1, 5)
	115 goto (1, 5)
	118 aload_2 (1, 5)
	119 invokeinterface (1, 5)
	124 astore (1, 5)
	126 dload_3 (1, 5)
	127 invokestatic (1, 5)
	130 lstore (1, 5)
	132 aload (2, 3)
	134 invokeinterface (2, 3)
	139 ifeq (2, 3)
	142 aload_1 (2, 3)
	143 aload (2, 3)
	145 invokeinterface (2, 3)
	150 checkcast (2, 3)
	153 invokevirtual (2, 3)
	156 aload_0 (2, 3)
	157 getfield (2, 3)
	160 lload (2, 3)
	162 lload (2, 3)
	164 iload (2, 3)
	166 i2l (2, 3)
	167 ladd (2, 3)
	168 lconst_1 (2, 3)
	169 lsub (2, 3)
	170 invokevirtual (2, 3)
	173 l2d (2, 3)
	174 dastore (2, 3)
	175 goto (2, 3)
	178 aload_2 (1, 5)
	179 invokeinterface (1, 5)
	184 astore (1, 5)
	186 dload_3 (1, 5)
	187 invokestatic (1, 5)
	190 lstore (1, 5)
	192 iconst_0 (1, 5)
	193 istore (1, 5)
	195 aload (2, 3)
	197 invokeinterface (2, 3)
	202 ifeq (2, 3)
	205 aload_1 (2, 3)
	206 aload (2, 3)
	208 invokeinterface (2, 3)
	213 checkcast (2, 3)
	216 invokevirtual (2, 3)
	219 lload (2, 3)
	221 iload (2, 3)
	223 iinc (2, 3)
	226 i2l (2, 3)
	227 ladd (2, 3)
	228 l2d (2, 3)
	229 dastore (2, 3)
	230 goto (2, 3)
	233 new (1, 5)
	236 dup (1, 5)
	237 invokespecial (1, 5)
	240 athrow (1, 5)
	241 return (0, 0)

Method: fill
	0 aload_2 (0, 0)
	1 invokeinterface (0, 0)
	6 astore (0, 0)
	8 aload (1, 3)
	10 invokeinterface (1, 3)
	15 ifeq (1, 3)
	18 aload_1 (1, 3)
	19 aload (1, 3)
	21 invokeinterface (1, 3)
	26 checkcast (1, 3)
	29 invokevirtual (1, 3)
	32 dload_3 (1, 3)
	33 dastore (1, 3)
	34 goto (1, 3)
	37 return (0, 0)

Method: restoreNaNs
	0 aload_2 (1, 1)
	1 invokeinterface (1, 1)
	6 ifne (1, 1)
	9 return (1, 1)
	10 aload_2 (0, 0)
	11 invokeinterface (0, 0)
	16 astore_3 (0, 0)
	17 aload_3 (1, 3)
	18 invokeinterface (1, 3)
	23 ifeq (1, 3)
	26 aload_1 (1, 3)
	27 aload_3 (1, 3)
	28 invokeinterface (1, 3)
	33 checkcast (1, 3)
	36 invokevirtual (1, 3)
	39 ldc2_w (1, 3)
	42 dastore (1, 3)
	43 goto (1, 3)
	46 return (0, 0)

Method: getNanPositions
	0 new (0, 0)
	3 dup (0, 0)
	4 invokespecial (0, 0)
	7 astore_2 (0, 0)
	8 iconst_0 (1, 4)
	9 istore_3 (1, 4)
	10 iload_3 (1, 4)
	11 aload_1 (1, 4)
	12 arraylength (1, 4)
	13 if_icmpge (1, 4)
	16 aload_1 (2, 1)
	17 iload_3 (2, 1)
	18 aaload (2, 1)
	19 invokevirtual (2, 1)
	22 invokestatic (2, 1)
	25 ifeq (2, 1)
	28 aload_2 (2, 1)
	29 iload_3 (2, 1)
	30 invokestatic (2, 1)
	33 invokevirtual (2, 1)
	36 pop (2, 1)
	37 iinc (2, 1)
	40 goto (2, 1)
	43 aload_2 (1, 4)
	44 areturn (1, 4)

Method: <clinit>
	0 getstatic (0, 0)
	3 putstatic (0, 0)
	6 getstatic (0, 0)
	9 putstatic (0, 0)
	12 return (0, 0)

