Method: <init>
	0 aload_0 (0, 0)
	1 invokespecial (0, 0)
	2 java/lang/Object.<init>:()V (0, 0)
	4 aload_0 (0, 0)
	5 dload_1 (0, 0)
	6 putfield (0, 0)
	7 org/apache/commons/math3/stat/ranking/NaturalRanking$IntDoublePair.value:D (0, 0)
	9 aload_0 (0, 0)
	10 iload_3 (0, 0)
	11 putfield (0, 0)
	12 org/apache/commons/math3/stat/ranking/NaturalRanking$IntDoublePair.position:I (0, 0)
	14 return (0, 0)

Method: compareTo
	0 aload_0 (0, 0)
	1 aload_1 (0, 0)
	2 checkcast (0, 0)
	3 org/apache/commons/math3/stat/ranking/NaturalRanking$IntDoublePair (0, 0)
	5 invokevirtual (0, 0)
	6 org/apache/commons/math3/stat/ranking/NaturalRanking$IntDoublePair.compareTo:(Lorg/apache/commons/math3/stat/ranking/NaturalRanking$IntDoublePair;)I (0, 0)
	8 ireturn (0, 0)

Method: getValue
	0 aload_0 (0, 0)
	1 getfield (0, 0)
	2 org/apache/commons/math3/stat/ranking/NaturalRanking$IntDoublePair.value:D (0, 0)
	4 dreturn (0, 0)

Method: getPosition
	0 aload_0 (0, 0)
	1 getfield (0, 0)
	2 org/apache/commons/math3/stat/ranking/NaturalRanking$IntDoublePair.position:I (0, 0)
	4 ireturn (0, 0)

