Method: <init>
	0 aload_0 (0, 0)
	1 invokespecial (0, 0)
	2 java/lang/Object.<init>:()V (0, 0)
	4 aload_0 (0, 0)
	5 aload_1 (0, 0)
	6 putfield (0, 0)
	7 org/apache/commons/math3/stat/ranking/NaturalRanking.nanStrategy:Lorg/apache/commons/math3/stat/ranking/NaNStrategy; (0, 0)
	9 aload_0 (0, 0)
	10 getstatic (0, 0)
	11 org/apache/commons/math3/stat/ranking/TiesStrategy.RANDOM:Lorg/apache/commons/math3/stat/ranking/TiesStrategy; (0, 0)
	13 putfield (0, 0)
	14 org/apache/commons/math3/stat/ranking/NaturalRanking.tiesStrategy:Lorg/apache/commons/math3/stat/ranking/TiesStrategy; (0, 0)
	16 aload_0 (0, 0)
	17 new (0, 0)
	18 org/apache/commons/math3/random/RandomDataGenerator (0, 0)
	20 dup (0, 0)
	21 aload_2 (0, 0)
	22 invokespecial (0, 0)
	23 org/apache/commons/math3/random/RandomDataGenerator.<init>:(Lorg/apache/commons/math3/random/RandomGenerator;)V (0, 0)
	25 putfield (0, 0)
	26 org/apache/commons/math3/stat/ranking/NaturalRanking.randomData:Lorg/apache/commons/math3/random/RandomDataGenerator; (0, 0)
	28 return (0, 0)

Method: getNanStrategy
	0 aload_0 (0, 0)
	1 getfield (0, 0)
	2 org/apache/commons/math3/stat/ranking/NaturalRanking.nanStrategy:Lorg/apache/commons/math3/stat/ranking/NaNStrategy; (0, 0)
	4 areturn (0, 0)

Method: getTiesStrategy
	0 aload_0 (0, 0)
	1 getfield (0, 0)
	2 org/apache/commons/math3/stat/ranking/NaturalRanking.tiesStrategy:Lorg/apache/commons/math3/stat/ranking/TiesStrategy; (0, 0)
	4 areturn (0, 0)

Method: rank
	0 aload_1 (0, 0)
	1 arraylength (0, 0)
	2 anewarray (0, 0)
	3 org/apache/commons/math3/stat/ranking/NaturalRanking$IntDoublePair (0, 0)
	5 astore_2 (0, 0)
	6 iconst_0 (1, 4)
	7 istore_3 (1, 4)
	8 iload_3 (1, 4)
	9 aload_1 (1, 4)
	10 arraylength (1, 4)
	11 if_icmpge (1, 4)
	12 23 (1, 4)
	14 aload_2 (1, 4)
	15 iload_3 (1, 4)
	16 new (1, 4)
	17 org/apache/commons/math3/stat/ranking/NaturalRanking$IntDoublePair (1, 4)
	19 dup (1, 4)
	20 aload_1 (1, 4)
	21 iload_3 (1, 4)
	22 daload (1, 4)
	23 iload_3 (1, 4)
	24 invokespecial (1, 4)
	25 org/apache/commons/math3/stat/ranking/NaturalRanking$IntDoublePair.<init>:(DI)V (1, 4)
	27 aastore (1, 4)
	28 iinc (1, 4)
	29 #3 (1, 4)
	30 -89 (1, 4)
	31 goto (1, 4)
	32 -23 (1, 4)
	34 aconst_null (0, 0)
	35 astore_3 (0, 0)
	36 getstatic (1, 5)
	37 org/apache/commons/math3/stat/ranking/NaturalRanking$1.$SwitchMap$org$apache$commons$math3$stat$ranking$NaNStrategy:[I (1, 5)
	39 aload_0 (1, 5)
	40 getfield (1, 5)
	41 org/apache/commons/math3/stat/ranking/NaturalRanking.nanStrategy:Lorg/apache/commons/math3/stat/ranking/NaNStrategy; (1, 5)
	43 invokevirtual (1, 5)
	44 org/apache/commons/math3/stat/ranking/NaNStrategy.ordinal:()I (1, 5)
	46 iaload (1, 5)
	47 tableswitch (1, 5)
	48 1 80 (1, 5)
	52 2 91 (1, 5)
	56 3 102 (1, 5)
	60 4 111 (1, 5)
	64 5 120 (1, 5)
	80 aload_0 (1, 5)
	81 aload_2 (1, 5)
	82 ldc2_w (1, 5)
	83 inf (1, 5)
	85 invokespecial (1, 5)
	86 org/apache/commons/math3/stat/ranking/NaturalRanking.recodeNaNs:([Lorg/apache/commons/math3/stat/ranking/NaturalRanking$IntDoublePair;D)V (1, 5)
	88 goto (1, 5)
	89 63 (1, 5)
	91 aload_0 (1, 5)
	92 aload_2 (1, 5)
	93 ldc2_w (1, 5)
	94 -inf (1, 5)
	96 invokespecial (1, 5)
	97 org/apache/commons/math3/stat/ranking/NaturalRanking.recodeNaNs:([Lorg/apache/commons/math3/stat/ranking/NaturalRanking$IntDoublePair;D)V (1, 5)
	99 goto (1, 5)
	100 52 (1, 5)
	102 aload_0 (1, 5)
	103 aload_2 (1, 5)
	104 invokespecial (1, 5)
	105 org/apache/commons/math3/stat/ranking/NaturalRanking.removeNaNs:([Lorg/apache/commons/math3/stat/ranking/NaturalRanking$IntDoublePair;)[Lorg/apache/commons/math3/stat/ranking/NaturalRanking$IntDoublePair; (1, 5)
	107 astore_2 (1, 5)
	108 goto (1, 5)
	109 43 (1, 5)
	111 aload_0 (1, 5)
	112 aload_2 (1, 5)
	113 invokespecial (1, 5)
	114 org/apache/commons/math3/stat/ranking/NaturalRanking.getNanPositions:([Lorg/apache/commons/math3/stat/ranking/NaturalRanking$IntDoublePair;)Ljava/util/List; (1, 5)
	116 astore_3 (1, 5)
	117 goto (1, 5)
	118 34 (1, 5)
	120 aload_0 (1, 5)
	121 aload_2 (1, 5)
	122 invokespecial (1, 5)
	123 org/apache/commons/math3/stat/ranking/NaturalRanking.getNanPositions:([Lorg/apache/commons/math3/stat/ranking/NaturalRanking$IntDoublePair;)Ljava/util/List; (1, 5)
	125 astore_3 (1, 5)
	126 aload_3 (2, 1)
	127 invokeinterface (2, 1)
	128 java/util/List.org/apache/commons/math3/exception/NotANumberException (2, 1)
	130 0 (2, 1)
	132 ifle (2, 1)
	133 19 (2, 1)
	135 new (2, 1)
	136 org/apache/commons/math3/exception/NotANumberException (2, 1)
	138 dup (2, 1)
	139 invokespecial (2, 1)
	140 org/apache/commons/math3/exception/NotANumberException.<init>:()V (2, 1)
	142 athrow (2, 1)
	143 new (1, 5)
	144 org/apache/commons/math3/exception/MathInternalError (1, 5)
	146 dup (1, 5)
	147 invokespecial (1, 5)
	148 org/apache/commons/math3/exception/MathInternalError.<init>:()V (1, 5)
	150 athrow (1, 5)
	151 aload_2 (0, 0)
	152 invokestatic (0, 0)
	153 java/util/Arrays.sort:([Ljava/lang/Object;)V (0, 0)
	155 aload_2 (0, 0)
	156 arraylength (0, 0)
	157 newarray (0, 0)
	158 7 (0, 0)
	159 astore (0, 0)
	160 #4 (0, 0)
	161 iconst_1 (0, 0)
	162 istore (0, 0)
	163 #5 (0, 0)
	164 aload (0, 0)
	165 #4 (0, 0)
	166 aload_2 (0, 0)
	167 iconst_0 (0, 0)
	168 aaload (0, 0)
	169 invokevirtual (0, 0)
	170 org/apache/commons/math3/stat/ranking/NaturalRanking$IntDoublePair.getPosition:()I (0, 0)
	172 iload (0, 0)
	173 #5 (0, 0)
	174 i2d (0, 0)
	175 dastore (0, 0)
	176 new (0, 0)
	177 java/util/ArrayList (0, 0)
	179 dup (0, 0)
	180 invokespecial (0, 0)
	181 java/util/ArrayList.<init>:()V (0, 0)
	183 astore (0, 0)
	184 #6 (0, 0)
	185 aload (0, 0)
	186 #6 (0, 0)
	187 aload_2 (0, 0)
	188 iconst_0 (0, 0)
	189 aaload (0, 0)
	190 invokevirtual (0, 0)
	191 org/apache/commons/math3/stat/ranking/NaturalRanking$IntDoublePair.getPosition:()I (0, 0)
	193 invokestatic (0, 0)
	194 java/lang/Integer.valueOf:(I)Ljava/lang/Integer; (0, 0)
	196 invokeinterface (0, 0)
	197 java/util/List.getValue:()D (0, 0)
	199 0 (0, 0)
	201 pop (0, 0)
	202 iconst_1 (1, 4)
	203 istore (1, 4)
	204 #7 (1, 4)
	205 iload (1, 4)
	206 #7 (1, 4)
	207 aload_2 (1, 4)
	208 arraylength (1, 4)
	209 if_icmpge (1, 4)
	210 117 (1, 4)
	212 aload_2 (2, 1)
	213 iload (2, 1)
	214 #7 (2, 1)
	215 aaload (2, 1)
	216 invokevirtual (2, 1)
	217 org/apache/commons/math3/stat/ranking/NaturalRanking$IntDoublePair.getValue:()D (2, 1)
	219 aload_2 (2, 1)
	220 iload (2, 1)
	221 #7 (2, 1)
	222 iconst_1 (2, 1)
	223 isub (2, 1)
	224 aaload (2, 1)
	225 invokevirtual (2, 1)
	226 org/apache/commons/math3/stat/ranking/NaturalRanking$IntDoublePair.getValue:()D (2, 1)
	228 invokestatic (2, 1)
	229 java/lang/Double.compare:(DD)I (2, 1)
	231 ifle (2, 1)
	232 58 (2, 1)
	234 iload (2, 1)
	235 #7 (2, 1)
	236 iconst_1 (2, 1)
	237 iadd (2, 1)
	238 istore (2, 1)
	239 #5 (2, 1)
	240 aload (3, 1)
	241 #6 (3, 1)
	242 invokeinterface (3, 1)
	243 java/util/List.org/apache/commons/math3/exception/NotANumberException (3, 1)
	245 0 (3, 1)
	247 iconst_1 (3, 1)
	248 if_icmple (3, 1)
	249 11 (3, 1)
	251 aload_0 (3, 1)
	252 aload (3, 1)
	253 #4 (3, 1)
	254 aload (3, 1)
	255 #6 (3, 1)
	256 invokespecial (3, 1)
	257 org/apache/commons/math3/stat/ranking/NaturalRanking.resolveTie:([DLjava/util/List;)V (3, 1)
	259 new (2, 1)
	260 java/util/ArrayList (2, 1)
	262 dup (2, 1)
	263 invokespecial (2, 1)
	264 java/util/ArrayList.<init>:()V (2, 1)
	266 astore (2, 1)
	267 #6 (2, 1)
	268 aload (2, 1)
	269 #6 (2, 1)
	270 aload_2 (2, 1)
	271 iload (2, 1)
	272 #7 (2, 1)
	273 aaload (2, 1)
	274 invokevirtual (2, 1)
	275 org/apache/commons/math3/stat/ranking/NaturalRanking$IntDoublePair.getPosition:()I (2, 1)
	277 invokestatic (2, 1)
	278 java/lang/Integer.valueOf:(I)Ljava/lang/Integer; (2, 1)
	280 invokeinterface (2, 1)
	281 java/util/List.getValue:()D (2, 1)
	283 0 (2, 1)
	285 pop (2, 1)
	286 goto (2, 1)
	287 21 (2, 1)
	289 aload (2, 2)
	290 #6 (2, 2)
	291 aload_2 (2, 2)
	292 iload (2, 2)
	293 #7 (2, 2)
	294 aaload (2, 2)
	295 invokevirtual (2, 2)
	296 org/apache/commons/math3/stat/ranking/NaturalRanking$IntDoublePair.getPosition:()I (2, 2)
	298 invokestatic (2, 2)
	299 java/lang/Integer.valueOf:(I)Ljava/lang/Integer; (2, 2)
	301 invokeinterface (2, 2)
	302 java/util/List.getValue:()D (2, 2)
	304 0 (2, 2)
	306 pop (2, 2)
	307 aload (1, 4)
	308 #4 (1, 4)
	309 aload_2 (1, 4)
	310 iload (1, 4)
	311 #7 (1, 4)
	312 aaload (1, 4)
	313 invokevirtual (1, 4)
	314 org/apache/commons/math3/stat/ranking/NaturalRanking$IntDoublePair.getPosition:()I (1, 4)
	316 iload (1, 4)
	317 #5 (1, 4)
	318 i2d (1, 4)
	319 dastore (1, 4)
	320 iinc (1, 4)
	321 #7 (1, 4)
	322 -89 (1, 4)
	323 goto (1, 4)
	324 -118 (1, 4)
	326 aload (1, 1)
	327 #6 (1, 1)
	328 invokeinterface (1, 1)
	329 java/util/List.org/apache/commons/math3/exception/NotANumberException (1, 1)
	331 0 (1, 1)
	333 iconst_1 (1, 1)
	334 if_icmple (1, 1)
	335 11 (1, 1)
	337 aload_0 (1, 1)
	338 aload (1, 1)
	339 #4 (1, 1)
	340 aload (1, 1)
	341 #6 (1, 1)
	342 invokespecial (1, 1)
	343 org/apache/commons/math3/stat/ranking/NaturalRanking.resolveTie:([DLjava/util/List;)V (1, 1)
	345 aload_0 (1, 1)
	346 getfield (1, 1)
	347 org/apache/commons/math3/stat/ranking/NaturalRanking.nanStrategy:Lorg/apache/commons/math3/stat/ranking/NaNStrategy; (1, 1)
	349 getstatic (1, 1)
	350 org/apache/commons/math3/stat/ranking/NaNStrategy.FIXED:Lorg/apache/commons/math3/stat/ranking/NaNStrategy; (1, 1)
	352 if_acmpne (1, 1)
	353 10 (1, 1)
	355 aload_0 (1, 1)
	356 aload (1, 1)
	357 #4 (1, 1)
	358 aload_3 (1, 1)
	359 invokespecial (1, 1)
	360 org/apache/commons/math3/stat/ranking/NaturalRanking.restoreNaNs:([DLjava/util/List;)V (1, 1)
	362 aload (0, 0)
	363 #4 (0, 0)
	364 areturn (0, 0)

Method: removeNaNs
	0 aload_0 (1, 1)
	1 aload_1 (1, 1)
	2 invokespecial (1, 1)
	3 org/apache/commons/math3/stat/ranking/NaturalRanking.containsNaNs:([Lorg/apache/commons/math3/stat/ranking/NaturalRanking$IntDoublePair;)Z (1, 1)
	5 ifne (1, 1)
	6 5 (1, 1)
	8 aload_1 (1, 1)
	9 areturn (1, 1)
	10 aload_1 (0, 0)
	11 arraylength (0, 0)
	12 anewarray (0, 0)
	13 org/apache/commons/math3/stat/ranking/NaturalRanking$IntDoublePair (0, 0)
	15 astore_2 (0, 0)
	16 iconst_0 (0, 0)
	17 istore_3 (0, 0)
	18 iconst_0 (1, 4)
	19 istore (1, 4)
	20 #4 (1, 4)
	21 iload (1, 4)
	22 #4 (1, 4)
	23 aload_1 (1, 4)
	24 arraylength (1, 4)
	25 if_icmpge (1, 4)
	26 98 (1, 4)
	28 aload_1 (2, 1)
	29 iload (2, 1)
	30 #4 (2, 1)
	31 aaload (2, 1)
	32 invokevirtual (2, 1)
	33 org/apache/commons/math3/stat/ranking/NaturalRanking$IntDoublePair.getValue:()D (2, 1)
	35 invokestatic (2, 1)
	36 java/lang/Double.isNaN:(D)Z (2, 1)
	38 ifeq (2, 1)
	39 52 (2, 1)
	41 iload (3, 4)
	42 #4 (3, 4)
	43 iconst_1 (3, 4)
	44 iadd (3, 4)
	45 istore (3, 4)
	46 #5 (3, 4)
	47 iload (3, 4)
	48 #5 (3, 4)
	49 aload_1 (3, 4)
	50 arraylength (3, 4)
	51 if_icmpge (3, 4)
	52 36 (3, 4)
	54 aload_1 (3, 4)
	55 iload (3, 4)
	56 #5 (3, 4)
	57 new (3, 4)
	58 org/apache/commons/math3/stat/ranking/NaturalRanking$IntDoublePair (3, 4)
	60 dup (3, 4)
	61 aload_1 (3, 4)
	62 iload (3, 4)
	63 #5 (3, 4)
	64 aaload (3, 4)
	65 invokevirtual (3, 4)
	66 org/apache/commons/math3/stat/ranking/NaturalRanking$IntDoublePair.getValue:()D (3, 4)
	68 aload_1 (3, 4)
	69 iload (3, 4)
	70 #5 (3, 4)
	71 aaload (3, 4)
	72 invokevirtual (3, 4)
	73 org/apache/commons/math3/stat/ranking/NaturalRanking$IntDoublePair.getPosition:()I (3, 4)
	75 iconst_1 (3, 4)
	76 isub (3, 4)
	77 invokespecial (3, 4)
	78 org/apache/commons/math3/stat/ranking/NaturalRanking$IntDoublePair.<init>:(DI)V (3, 4)
	80 aastore (3, 4)
	81 iinc (3, 4)
	82 #5 (3, 4)
	83 -89 (3, 4)
	84 goto (3, 4)
	85 -37 (3, 4)
	87 goto (3, 4)
	88 30 (3, 4)
	90 aload_2 (2, 2)
	91 iload_3 (2, 2)
	92 new (2, 2)
	93 org/apache/commons/math3/stat/ranking/NaturalRanking$IntDoublePair (2, 2)
	95 dup (2, 2)
	96 aload_1 (2, 2)
	97 iload (2, 2)
	98 #4 (2, 2)
	99 aaload (2, 2)
	100 invokevirtual (2, 2)
	101 org/apache/commons/math3/stat/ranking/NaturalRanking$IntDoublePair.getValue:()D (2, 2)
	103 aload_1 (2, 2)
	104 iload (2, 2)
	105 #4 (2, 2)
	106 aaload (2, 2)
	107 invokevirtual (2, 2)
	108 org/apache/commons/math3/stat/ranking/NaturalRanking$IntDoublePair.getPosition:()I (2, 2)
	110 invokespecial (2, 2)
	111 org/apache/commons/math3/stat/ranking/NaturalRanking$IntDoublePair.<init>:(DI)V (2, 2)
	113 aastore (2, 2)
	114 iinc (2, 2)
	115 #3 (2, 2)
	116 -124 (2, 2)
	117 iinc (2, 2)
	118 #4 (2, 2)
	119 -89 (2, 2)
	120 goto (2, 2)
	121 -99 (2, 2)
	123 iload_3 (1, 4)
	124 anewarray (1, 4)
	125 org/apache/commons/math3/stat/ranking/NaturalRanking$IntDoublePair (1, 4)
	127 astore (1, 4)
	128 #4 (1, 4)
	129 aload_2 (1, 4)
	130 iconst_0 (1, 4)
	131 aload (1, 4)
	132 #4 (1, 4)
	133 iconst_0 (1, 4)
	134 iload_3 (1, 4)
	135 invokestatic (1, 4)
	136 java/lang/System.arraycopy:(Ljava/lang/Object;ILjava/lang/Object;II)V (1, 4)
	138 aload (1, 4)
	139 #4 (1, 4)
	140 areturn (1, 4)

Method: recodeNaNs
	0 iconst_0 (1, 4)
	1 istore (1, 4)
	2 #4 (1, 4)
	3 iload (1, 4)
	4 #4 (1, 4)
	5 aload_1 (1, 4)
	6 arraylength (1, 4)
	7 if_icmpge (1, 4)
	8 41 (1, 4)
	10 aload_1 (2, 1)
	11 iload (2, 1)
	12 #4 (2, 1)
	13 aaload (2, 1)
	14 invokevirtual (2, 1)
	15 org/apache/commons/math3/stat/ranking/NaturalRanking$IntDoublePair.getValue:()D (2, 1)
	17 invokestatic (2, 1)
	18 java/lang/Double.isNaN:(D)Z (2, 1)
	20 ifeq (2, 1)
	21 22 (2, 1)
	23 aload_1 (2, 1)
	24 iload (2, 1)
	25 #4 (2, 1)
	26 new (2, 1)
	27 org/apache/commons/math3/stat/ranking/NaturalRanking$IntDoublePair (2, 1)
	29 dup (2, 1)
	30 dload_2 (2, 1)
	31 aload_1 (2, 1)
	32 iload (2, 1)
	33 #4 (2, 1)
	34 aaload (2, 1)
	35 invokevirtual (2, 1)
	36 org/apache/commons/math3/stat/ranking/NaturalRanking$IntDoublePair.getPosition:()I (2, 1)
	38 invokespecial (2, 1)
	39 org/apache/commons/math3/stat/ranking/NaturalRanking$IntDoublePair.<init>:(DI)V (2, 1)
	41 aastore (2, 1)
	42 iinc (2, 1)
	43 #4 (2, 1)
	44 -89 (2, 1)
	45 goto (2, 1)
	46 -42 (2, 1)
	48 return (0, 0)

Method: containsNaNs
	0 iconst_0 (1, 4)
	1 istore_2 (1, 4)
	2 iload_2 (1, 4)
	3 aload_1 (1, 4)
	4 arraylength (1, 4)
	5 if_icmpge (1, 4)
	6 23 (1, 4)
	8 aload_1 (2, 1)
	9 iload_2 (2, 1)
	10 aaload (2, 1)
	11 invokevirtual (2, 1)
	12 org/apache/commons/math3/stat/ranking/NaturalRanking$IntDoublePair.getValue:()D (2, 1)
	14 invokestatic (2, 1)
	15 java/lang/Double.isNaN:(D)Z (2, 1)
	17 ifeq (2, 1)
	18 5 (2, 1)
	20 iconst_1 (2, 1)
	21 ireturn (2, 1)
	22 iinc (2, 1)
	23 #2 (2, 1)
	24 -89 (2, 1)
	25 goto (2, 1)
	26 -23 (2, 1)
	28 iconst_0 (1, 4)
	29 ireturn (1, 4)

Method: resolveTie
	0 aload_1 (0, 0)
	1 aload_2 (0, 0)
	2 iconst_0 (0, 0)
	3 invokeinterface (0, 0)
	4 java/util/List.java/lang/Integer (0, 0)
	6 0 (0, 0)
	8 checkcast (0, 0)
	9 java/lang/Integer (0, 0)
	11 invokevirtual (0, 0)
	12 java/lang/Integer.intValue:()I (0, 0)
	14 daload (0, 0)
	15 dstore_3 (0, 0)
	16 aload_2 (0, 0)
	17 invokeinterface (0, 0)
	18 java/util/List.org/apache/commons/math3/exception/NotANumberException (0, 0)
	20 0 (0, 0)
	22 istore (0, 0)
	23 #5 (0, 0)
	24 getstatic (1, 5)
	25 org/apache/commons/math3/stat/ranking/NaturalRanking$1.$SwitchMap$org$apache$commons$math3$stat$ranking$TiesStrategy:[I (1, 5)
	27 aload_0 (1, 5)
	28 getfield (1, 5)
	29 org/apache/commons/math3/stat/ranking/NaturalRanking.tiesStrategy:Lorg/apache/commons/math3/stat/ranking/TiesStrategy; (1, 5)
	31 invokevirtual (1, 5)
	32 org/apache/commons/math3/stat/ranking/TiesStrategy.ordinal:()I (1, 5)
	34 iaload (1, 5)
	35 tableswitch (1, 5)
	36 1 68 (1, 5)
	40 2 92 (1, 5)
	44 3 108 (1, 5)
	48 4 118 (1, 5)
	52 5 178 (1, 5)
	68 aload_0 (1, 5)
	69 aload_1 (1, 5)
	70 aload_2 (1, 5)
	71 ldc2_w (1, 5)
	72 2.0 (1, 5)
	74 dload_3 (1, 5)
	75 dmul (1, 5)
	76 iload (1, 5)
	77 #5 (1, 5)
	78 i2d (1, 5)
	79 dadd (1, 5)
	80 dconst_1 (1, 5)
	81 dsub (1, 5)
	82 ldc2_w (1, 5)
	83 2.0 (1, 5)
	85 ddiv (1, 5)
	86 invokespecial (1, 5)
	87 org/apache/commons/math3/stat/ranking/NaturalRanking.fill:([DLjava/util/List;D)V (1, 5)
	89 goto (1, 5)
	90 152 (1, 5)
	92 aload_0 (1, 5)
	93 aload_1 (1, 5)
	94 aload_2 (1, 5)
	95 dload_3 (1, 5)
	96 iload (1, 5)
	97 #5 (1, 5)
	98 i2d (1, 5)
	99 dadd (1, 5)
	100 dconst_1 (1, 5)
	101 dsub (1, 5)
	102 invokespecial (1, 5)
	103 org/apache/commons/math3/stat/ranking/NaturalRanking.fill:([DLjava/util/List;D)V (1, 5)
	105 goto (1, 5)
	106 136 (1, 5)
	108 aload_0 (1, 5)
	109 aload_1 (1, 5)
	110 aload_2 (1, 5)
	111 dload_3 (1, 5)
	112 invokespecial (1, 5)
	113 org/apache/commons/math3/stat/ranking/NaturalRanking.fill:([DLjava/util/List;D)V (1, 5)
	115 goto (1, 5)
	116 126 (1, 5)
	118 aload_2 (1, 5)
	119 invokeinterface (1, 5)
	120 java/util/List.org/apache/commons/math3/util/FastMath (1, 5)
	122 0 (1, 5)
	124 astore (1, 5)
	125 #6 (1, 5)
	126 dload_3 (1, 5)
	127 invokestatic (1, 5)
	128 org/apache/commons/math3/util/FastMath.round:(D)J (1, 5)
	130 lstore (1, 5)
	131 #7 (1, 5)
	132 aload (2, 3)
	133 #6 (2, 3)
	134 invokeinterface (2, 3)
	135 java/util/Iterator.next:()Ljava/lang/Object; (2, 3)
	137 0 (2, 3)
	139 ifeq (2, 3)
	140 102 (2, 3)
	142 aload_1 (2, 3)
	143 aload (2, 3)
	144 #6 (2, 3)
	145 invokeinterface (2, 3)
	146 java/util/Iterator.nextLong:(JJ)J (2, 3)
	148 0 (2, 3)
	150 checkcast (2, 3)
	151 java/lang/Integer (2, 3)
	153 invokevirtual (2, 3)
	154 java/lang/Integer.intValue:()I (2, 3)
	156 aload_0 (2, 3)
	157 getfield (2, 3)
	158 org/apache/commons/math3/stat/ranking/NaturalRanking.randomData:Lorg/apache/commons/math3/random/RandomDataGenerator; (2, 3)
	160 lload (2, 3)
	161 #7 (2, 3)
	162 lload (2, 3)
	163 #7 (2, 3)
	164 iload (2, 3)
	165 #5 (2, 3)
	166 i2l (2, 3)
	167 ladd (2, 3)
	168 lconst_1 (2, 3)
	169 lsub (2, 3)
	170 invokevirtual (2, 3)
	171 org/apache/commons/math3/random/RandomDataGenerator.nextLong:(JJ)J (2, 3)
	173 l2d (2, 3)
	174 dastore (2, 3)
	175 goto (2, 3)
	176 -43 (2, 3)
	178 aload_2 (1, 5)
	179 invokeinterface (1, 5)
	180 java/util/List.org/apache/commons/math3/util/FastMath (1, 5)
	182 0 (1, 5)
	184 astore (1, 5)
	185 #6 (1, 5)
	186 dload_3 (1, 5)
	187 invokestatic (1, 5)
	188 org/apache/commons/math3/util/FastMath.round:(D)J (1, 5)
	190 lstore (1, 5)
	191 #7 (1, 5)
	192 iconst_0 (1, 5)
	193 istore (1, 5)
	194 #9 (1, 5)
	195 aload (2, 3)
	196 #6 (2, 3)
	197 invokeinterface (2, 3)
	198 java/util/Iterator.next:()Ljava/lang/Object; (2, 3)
	200 0 (2, 3)
	202 ifeq (2, 3)
	203 39 (2, 3)
	205 aload_1 (2, 3)
	206 aload (2, 3)
	207 #6 (2, 3)
	208 invokeinterface (2, 3)
	209 java/util/Iterator.nextLong:(JJ)J (2, 3)
	211 0 (2, 3)
	213 checkcast (2, 3)
	214 java/lang/Integer (2, 3)
	216 invokevirtual (2, 3)
	217 java/lang/Integer.intValue:()I (2, 3)
	219 lload (2, 3)
	220 #7 (2, 3)
	221 iload (2, 3)
	222 #9 (2, 3)
	223 iinc (2, 3)
	224 #9 (2, 3)
	225 -123 (2, 3)
	226 i2l (2, 3)
	227 ladd (2, 3)
	228 l2d (2, 3)
	229 dastore (2, 3)
	230 goto (2, 3)
	231 -35 (2, 3)
	233 new (1, 5)
	234 org/apache/commons/math3/exception/MathInternalError (1, 5)
	236 dup (1, 5)
	237 invokespecial (1, 5)
	238 org/apache/commons/math3/exception/MathInternalError.<init>:()V (1, 5)
	240 athrow (1, 5)
	241 return (0, 0)

Method: fill
	0 aload_2 (0, 0)
	1 invokeinterface (0, 0)
	2 java/util/List.org/apache/commons/math3/util/FastMath (0, 0)
	4 0 (0, 0)
	6 astore (0, 0)
	7 #5 (0, 0)
	8 aload (1, 3)
	9 #5 (1, 3)
	10 invokeinterface (1, 3)
	11 java/util/Iterator.next:()Ljava/lang/Object; (1, 3)
	13 0 (1, 3)
	15 ifeq (1, 3)
	16 22 (1, 3)
	18 aload_1 (1, 3)
	19 aload (1, 3)
	20 #5 (1, 3)
	21 invokeinterface (1, 3)
	22 java/util/Iterator.nextLong:(JJ)J (1, 3)
	24 0 (1, 3)
	26 checkcast (1, 3)
	27 java/lang/Integer (1, 3)
	29 invokevirtual (1, 3)
	30 java/lang/Integer.intValue:()I (1, 3)
	32 dload_3 (1, 3)
	33 dastore (1, 3)
	34 goto (1, 3)
	35 -26 (1, 3)
	37 return (0, 0)

Method: restoreNaNs
	0 aload_2 (1, 1)
	1 invokeinterface (1, 1)
	2 java/util/List.org/apache/commons/math3/exception/NotANumberException (1, 1)
	4 0 (1, 1)
	6 ifne (1, 1)
	7 4 (1, 1)
	9 return (1, 1)
	10 aload_2 (0, 0)
	11 invokeinterface (0, 0)
	12 java/util/List.org/apache/commons/math3/util/FastMath (0, 0)
	14 0 (0, 0)
	16 astore_3 (0, 0)
	17 aload_3 (1, 3)
	18 invokeinterface (1, 3)
	19 java/util/Iterator.next:()Ljava/lang/Object; (1, 3)
	21 0 (1, 3)
	23 ifeq (1, 3)
	24 23 (1, 3)
	26 aload_1 (1, 3)
	27 aload_3 (1, 3)
	28 invokeinterface (1, 3)
	29 java/util/Iterator.nextLong:(JJ)J (1, 3)
	31 0 (1, 3)
	33 checkcast (1, 3)
	34 java/lang/Integer (1, 3)
	36 invokevirtual (1, 3)
	37 java/lang/Integer.intValue:()I (1, 3)
	39 ldc2_w (1, 3)
	40 nan (1, 3)
	42 dastore (1, 3)
	43 goto (1, 3)
	44 -26 (1, 3)
	46 return (0, 0)

Method: getNanPositions
	0 new (0, 0)
	1 java/util/ArrayList (0, 0)
	3 dup (0, 0)
	4 invokespecial (0, 0)
	5 java/util/ArrayList.<init>:()V (0, 0)
	7 astore_2 (0, 0)
	8 iconst_0 (1, 4)
	9 istore_3 (1, 4)
	10 iload_3 (1, 4)
	11 aload_1 (1, 4)
	12 arraylength (1, 4)
	13 if_icmpge (1, 4)
	14 30 (1, 4)
	16 aload_1 (2, 1)
	17 iload_3 (2, 1)
	18 aaload (2, 1)
	19 invokevirtual (2, 1)
	20 org/apache/commons/math3/stat/ranking/NaturalRanking$IntDoublePair.getValue:()D (2, 1)
	22 invokestatic (2, 1)
	23 java/lang/Double.isNaN:(D)Z (2, 1)
	25 ifeq (2, 1)
	26 12 (2, 1)
	28 aload_2 (2, 1)
	29 iload_3 (2, 1)
	30 invokestatic (2, 1)
	31 java/lang/Integer.valueOf:(I)Ljava/lang/Integer; (2, 1)
	33 invokevirtual (2, 1)
	34 java/util/ArrayList.add:(Ljava/lang/Object;)Z (2, 1)
	36 pop (2, 1)
	37 iinc (2, 1)
	38 #3 (2, 1)
	39 -89 (2, 1)
	40 goto (2, 1)
	41 -30 (2, 1)
	43 aload_2 (1, 4)
	44 areturn (1, 4)

Method: <clinit>
	0 getstatic (0, 0)
	1 org/apache/commons/math3/stat/ranking/NaNStrategy.FAILED:Lorg/apache/commons/math3/stat/ranking/NaNStrategy; (0, 0)
	3 putstatic (0, 0)
	4 org/apache/commons/math3/stat/ranking/NaturalRanking.DEFAULT_NAN_STRATEGY:Lorg/apache/commons/math3/stat/ranking/NaNStrategy; (0, 0)
	6 getstatic (0, 0)
	7 org/apache/commons/math3/stat/ranking/TiesStrategy.AVERAGE:Lorg/apache/commons/math3/stat/ranking/TiesStrategy; (0, 0)
	9 putstatic (0, 0)
	10 org/apache/commons/math3/stat/ranking/NaturalRanking.DEFAULT_TIES_STRATEGY:Lorg/apache/commons/math3/stat/ranking/TiesStrategy; (0, 0)
	12 return (0, 0)

