Method: <init>
	0 aload_0 (0, 0)
	1 aload_1 (0, 0)
	2 iconst_1 (0, 0)
	3 invokespecial (0, 0)
	4 org/apache/commons/math3/stat/correlation/Covariance.<init>:(Lorg/apache/commons/math3/linear/RealMatrix;Z)V (0, 0)
	6 return (0, 0)

Method: getCovarianceMatrix
	0 aload_0 (0, 0)
	1 getfield (0, 0)
	2 org/apache/commons/math3/stat/correlation/Covariance.covarianceMatrix:Lorg/apache/commons/math3/linear/RealMatrix; (0, 0)
	4 areturn (0, 0)

Method: getN
	0 aload_0 (0, 0)
	1 getfield (0, 0)
	2 org/apache/commons/math3/stat/correlation/Covariance.n:I (0, 0)
	4 ireturn (0, 0)

Method: computeCovarianceMatrix
	0 aload_0 (0, 0)
	1 aload_1 (0, 0)
	2 iconst_1 (0, 0)
	3 invokevirtual (0, 0)
	4 org/apache/commons/math3/stat/correlation/Covariance.computeCovarianceMatrix:([[DZ)Lorg/apache/commons/math3/linear/RealMatrix; (0, 0)
	6 areturn (0, 0)

Method: covariance
	0 aload_0 (0, 0)
	1 aload_1 (0, 0)
	2 aload_2 (0, 0)
	3 iconst_1 (0, 0)
	4 invokevirtual (0, 0)
	5 org/apache/commons/math3/stat/correlation/Covariance.covariance:([D[DZ)D (0, 0)
	7 dreturn (0, 0)

Method: checkSufficientData
	0 aload_1 (0, 0)
	1 invokeinterface (0, 0)
	2 org/apache/commons/math3/linear/RealMatrix.computeCovarianceMatrix:(Lorg/apache/commons/math3/linear/RealMatrix;Z)Lorg/apache/commons/math3/linear/RealMatrix; (0, 0)
	4 0 (0, 0)
	6 istore_2 (0, 0)
	7 aload_1 (0, 0)
	8 invokeinterface (0, 0)
	9 org/apache/commons/math3/linear/RealMatrix.org/apache/commons/math3/stat/descriptive/moment/Variance (0, 0)
	11 0 (0, 0)
	13 istore_3 (0, 0)
	14 iload_2 (1, 1)
	15 iconst_2 (1, 1)
	16 if_icmplt (1, 1)
	17 8 (1, 1)
	19 iload_3 (1, 1)
	20 iconst_1 (1, 1)
	21 if_icmpge (1, 1)
	22 32 (1, 1)
	24 new (1, 1)
	25 org/apache/commons/math3/exception/MathIllegalArgumentException (1, 1)
	27 dup (1, 1)
	28 getstatic (1, 1)
	29 org/apache/commons/math3/exception/util/LocalizedFormats.INSUFFICIENT_ROWS_AND_COLUMNS:Lorg/apache/commons/math3/exception/util/LocalizedFormats; (1, 1)
	31 iconst_2 (1, 1)
	32 anewarray (1, 1)
	33 java/lang/Object (1, 1)
	35 dup (1, 1)
	36 iconst_0 (1, 1)
	37 iload_2 (1, 1)
	38 invokestatic (1, 1)
	39 java/lang/Integer.valueOf:(I)Ljava/lang/Integer; (1, 1)
	41 aastore (1, 1)
	42 dup (1, 1)
	43 iconst_1 (1, 1)
	44 iload_3 (1, 1)
	45 invokestatic (1, 1)
	46 java/lang/Integer.valueOf:(I)Ljava/lang/Integer; (1, 1)
	48 aastore (1, 1)
	49 invokespecial (1, 1)
	50 org/apache/commons/math3/exception/MathIllegalArgumentException.<init>:(Lorg/apache/commons/math3/exception/util/Localizable;[Ljava/lang/Object;)V (1, 1)
	52 athrow (1, 1)
	53 return (0, 0)

