Method: <init>
	0 aload_0 (0, 0)
	1 invokespecial (0, 0)
	2 java/lang/Object.<init>:()V (0, 0)
	4 aload_0 (0, 0)
	5 aload_0 (0, 0)
	6 aload_1 (0, 0)
	7 invokevirtual (0, 0)
	8 org/apache/commons/math3/stat/correlation/KendallsCorrelation.computeCorrelationMatrix:(Lorg/apache/commons/math3/linear/RealMatrix;)Lorg/apache/commons/math3/linear/RealMatrix; (0, 0)
	10 putfield (0, 0)
	11 org/apache/commons/math3/stat/correlation/KendallsCorrelation.correlationMatrix:Lorg/apache/commons/math3/linear/RealMatrix; (0, 0)
	13 return (0, 0)

Method: getCorrelationMatrix
	0 aload_0 (0, 0)
	1 getfield (0, 0)
	2 org/apache/commons/math3/stat/correlation/KendallsCorrelation.correlationMatrix:Lorg/apache/commons/math3/linear/RealMatrix; (0, 0)
	4 areturn (0, 0)

Method: computeCorrelationMatrix
	0 aload_0 (0, 0)
	1 new (0, 0)
	2 org/apache/commons/math3/linear/BlockRealMatrix (0, 0)
	4 dup (0, 0)
	5 aload_1 (0, 0)
	6 invokespecial (0, 0)
	7 org/apache/commons/math3/linear/BlockRealMatrix.<init>:([[D)V (0, 0)
	9 invokevirtual (0, 0)
	10 org/apache/commons/math3/stat/correlation/KendallsCorrelation.computeCorrelationMatrix:(Lorg/apache/commons/math3/linear/RealMatrix;)Lorg/apache/commons/math3/linear/RealMatrix; (0, 0)
	12 areturn (0, 0)

Method: correlation
	0 aload_1 (1, 1)
	1 arraylength (1, 1)
	2 aload_2 (1, 1)
	3 arraylength (1, 1)
	4 if_icmpeq (1, 1)
	5 15 (1, 1)
	7 new (1, 1)
	8 org/apache/commons/math3/exception/DimensionMismatchException (1, 1)
	10 dup (1, 1)
	11 aload_1 (1, 1)
	12 arraylength (1, 1)
	13 aload_2 (1, 1)
	14 arraylength (1, 1)
	15 invokespecial (1, 1)
	16 org/apache/commons/math3/exception/DimensionMismatchException.<init>:(II)V (1, 1)
	18 athrow (1, 1)
	19 aload_1 (0, 0)
	20 arraylength (0, 0)
	21 istore_3 (0, 0)
	22 iload_3 (0, 0)
	23 iconst_1 (0, 0)
	24 isub (0, 0)
	25 i2l (0, 0)
	26 invokestatic (0, 0)
	27 org/apache/commons/math3/stat/correlation/KendallsCorrelation.sum:(J)J (0, 0)
	29 lstore (0, 0)
	30 #4 (0, 0)
	31 iload_3 (0, 0)
	32 anewarray (0, 0)
	33 org/apache/commons/math3/util/Pair (0, 0)
	35 astore (0, 0)
	36 #6 (0, 0)
	37 iconst_0 (1, 4)
	38 istore (1, 4)
	39 #7 (1, 4)
	40 iload (1, 4)
	41 #7 (1, 4)
	42 iload_3 (1, 4)
	43 if_icmpge (1, 4)
	44 35 (1, 4)
	46 aload (1, 4)
	47 #6 (1, 4)
	48 iload (1, 4)
	49 #7 (1, 4)
	50 new (1, 4)
	51 org/apache/commons/math3/util/Pair (1, 4)
	53 dup (1, 4)
	54 aload_1 (1, 4)
	55 iload (1, 4)
	56 #7 (1, 4)
	57 daload (1, 4)
	58 invokestatic (1, 4)
	59 java/lang/Double.valueOf:(D)Ljava/lang/Double; (1, 4)
	61 aload_2 (1, 4)
	62 iload (1, 4)
	63 #7 (1, 4)
	64 daload (1, 4)
	65 invokestatic (1, 4)
	66 java/lang/Double.valueOf:(D)Ljava/lang/Double; (1, 4)
	68 invokespecial (1, 4)
	69 org/apache/commons/math3/util/Pair.<init>:(Ljava/lang/Object;Ljava/lang/Object;)V (1, 4)
	71 aastore (1, 4)
	72 iinc (1, 4)
	73 #7 (1, 4)
	74 -89 (1, 4)
	75 goto (1, 4)
	76 -35 (1, 4)
	78 aload (0, 0)
	79 #6 (0, 0)
	80 new (0, 0)
	81 org/apache/commons/math3/stat/correlation/KendallsCorrelation$1 (0, 0)
	83 dup (0, 0)
	84 aload_0 (0, 0)
	85 invokespecial (0, 0)
	86 org/apache/commons/math3/stat/correlation/KendallsCorrelation$1.<init>:(Lorg/apache/commons/math3/stat/correlation/KendallsCorrelation;)V (0, 0)
	88 invokestatic (0, 0)
	89 java/util/Arrays.sort:([Ljava/lang/Object;Ljava/util/Comparator;)V (0, 0)
	91 lconst_0 (0, 0)
	92 lstore (0, 0)
	93 #7 (0, 0)
	94 lconst_0 (0, 0)
	95 lstore (0, 0)
	96 #9 (0, 0)
	97 lconst_1 (0, 0)
	98 lstore (0, 0)
	99 #11 (0, 0)
	100 lconst_1 (0, 0)
	101 lstore (0, 0)
	102 #13 (0, 0)
	103 aload (0, 0)
	104 #6 (0, 0)
	105 iconst_0 (0, 0)
	106 aaload (0, 0)
	107 astore (0, 0)
	108 #15 (0, 0)
	109 iconst_1 (1, 4)
	110 istore (1, 4)
	111 #16 (1, 4)
	112 iload (1, 4)
	113 #16 (1, 4)
	114 iload_3 (1, 4)
	115 if_icmpge (1, 4)
	116 121 (1, 4)
	118 aload (1, 4)
	119 #6 (1, 4)
	120 iload (1, 4)
	121 #16 (1, 4)
	122 aaload (1, 4)
	123 astore (1, 4)
	124 #17 (1, 4)
	125 aload (2, 1)
	126 #17 (2, 1)
	127 invokevirtual (2, 1)
	128 org/apache/commons/math3/util/Pair.getFirst:()Ljava/lang/Object; (2, 1)
	130 checkcast (2, 1)
	131 java/lang/Double (2, 1)
	133 aload (2, 1)
	134 #15 (2, 1)
	135 invokevirtual (2, 1)
	136 org/apache/commons/math3/util/Pair.getFirst:()Ljava/lang/Object; (2, 1)
	138 invokevirtual (2, 1)
	139 java/lang/Double.equals:(Ljava/lang/Object;)Z (2, 1)
	141 ifeq (2, 1)
	142 55 (2, 1)
	144 lload (2, 1)
	145 #11 (2, 1)
	146 lconst_1 (2, 1)
	147 ladd (2, 1)
	148 lstore (2, 1)
	149 #11 (2, 1)
	150 aload (3, 1)
	151 #17 (3, 1)
	152 invokevirtual (3, 1)
	153 org/apache/commons/math3/util/Pair.getSecond:()Ljava/lang/Object; (3, 1)
	155 checkcast (3, 1)
	156 java/lang/Double (3, 1)
	158 aload (3, 1)
	159 #15 (3, 1)
	160 invokevirtual (3, 1)
	161 org/apache/commons/math3/util/Pair.getSecond:()Ljava/lang/Object; (3, 1)
	163 invokevirtual (3, 1)
	164 java/lang/Double.equals:(Ljava/lang/Object;)Z (3, 1)
	166 ifeq (3, 1)
	167 12 (3, 1)
	169 lload (3, 1)
	170 #13 (3, 1)
	171 lconst_1 (3, 1)
	172 ladd (3, 1)
	173 lstore (3, 1)
	174 #13 (3, 1)
	175 goto (3, 1)
	176 51 (3, 1)
	178 lload (4, 2)
	179 #9 (4, 2)
	180 lload (4, 2)
	181 #13 (4, 2)
	182 lconst_1 (4, 2)
	183 lsub (4, 2)
	184 invokestatic (4, 2)
	185 org/apache/commons/math3/stat/correlation/KendallsCorrelation.sum:(J)J (4, 2)
	187 ladd (4, 2)
	188 lstore (4, 2)
	189 #9 (4, 2)
	190 lconst_1 (4, 2)
	191 lstore (4, 2)
	192 #13 (4, 2)
	193 goto (4, 2)
	194 33 (4, 2)
	196 lload (3, 2)
	197 #7 (3, 2)
	198 lload (3, 2)
	199 #11 (3, 2)
	200 lconst_1 (3, 2)
	201 lsub (3, 2)
	202 invokestatic (3, 2)
	203 org/apache/commons/math3/stat/correlation/KendallsCorrelation.sum:(J)J (3, 2)
	205 ladd (3, 2)
	206 lstore (3, 2)
	207 #7 (3, 2)
	208 lconst_1 (3, 2)
	209 lstore (3, 2)
	210 #11 (3, 2)
	211 lload (3, 2)
	212 #9 (3, 2)
	213 lload (3, 2)
	214 #13 (3, 2)
	215 lconst_1 (3, 2)
	216 lsub (3, 2)
	217 invokestatic (3, 2)
	218 org/apache/commons/math3/stat/correlation/KendallsCorrelation.sum:(J)J (3, 2)
	220 ladd (3, 2)
	221 lstore (3, 2)
	222 #9 (3, 2)
	223 lconst_1 (3, 2)
	224 lstore (3, 2)
	225 #13 (3, 2)
	226 aload (1, 4)
	227 #17 (1, 4)
	228 astore (1, 4)
	229 #15 (1, 4)
	230 iinc (1, 4)
	231 #16 (1, 4)
	232 -89 (1, 4)
	233 goto (1, 4)
	234 -121 (1, 4)
	236 lload (0, 0)
	237 #7 (0, 0)
	238 lload (0, 0)
	239 #11 (0, 0)
	240 lconst_1 (0, 0)
	241 lsub (0, 0)
	242 invokestatic (0, 0)
	243 org/apache/commons/math3/stat/correlation/KendallsCorrelation.sum:(J)J (0, 0)
	245 ladd (0, 0)
	246 lstore (0, 0)
	247 #7 (0, 0)
	248 lload (0, 0)
	249 #9 (0, 0)
	250 lload (0, 0)
	251 #13 (0, 0)
	252 lconst_1 (0, 0)
	253 lsub (0, 0)
	254 invokestatic (0, 0)
	255 org/apache/commons/math3/stat/correlation/KendallsCorrelation.sum:(J)J (0, 0)
	257 ladd (0, 0)
	258 lstore (0, 0)
	259 #9 (0, 0)
	260 lconst_0 (0, 0)
	261 lstore (0, 0)
	262 #16 (0, 0)
	263 iload_3 (0, 0)
	264 anewarray (0, 0)
	265 org/apache/commons/math3/util/Pair (0, 0)
	267 astore (0, 0)
	268 #18 (0, 0)
	269 iconst_1 (1, 4)
	270 istore (1, 4)
	271 #19 (1, 4)
	272 iload (1, 4)
	273 #19 (1, 4)
	274 iload_3 (1, 4)
	275 if_icmpge (1, 4)
	276 213 (1, 4)
	278 iconst_0 (2, 4)
	279 istore (2, 4)
	280 #20 (2, 4)
	281 iload (2, 4)
	282 #20 (2, 4)
	283 iload_3 (2, 4)
	284 if_icmpge (2, 4)
	285 183 (2, 4)
	287 iload (2, 4)
	288 #20 (2, 4)
	289 istore (2, 4)
	290 #21 (2, 4)
	291 iload (2, 4)
	292 #21 (2, 4)
	293 iload (2, 4)
	294 #19 (2, 4)
	295 iadd (2, 4)
	296 iload_3 (2, 4)
	297 invokestatic (2, 4)
	298 org/apache/commons/math3/util/FastMath.min:(II)I (2, 4)
	300 istore (2, 4)
	301 #22 (2, 4)
	302 iload (2, 4)
	303 #22 (2, 4)
	304 istore (2, 4)
	305 #23 (2, 4)
	306 iload (2, 4)
	307 #23 (2, 4)
	308 iload (2, 4)
	309 #19 (2, 4)
	310 iadd (2, 4)
	311 iload_3 (2, 4)
	312 invokestatic (2, 4)
	313 org/apache/commons/math3/util/FastMath.min:(II)I (2, 4)
	315 istore (2, 4)
	316 #24 (2, 4)
	317 iload (2, 4)
	318 #20 (2, 4)
	319 istore (2, 4)
	320 #25 (2, 4)
	321 iload (3, 3)
	322 #21 (3, 3)
	323 iload (3, 3)
	324 #22 (3, 3)
	325 if_icmplt (3, 3)
	326 10 (3, 3)
	328 iload (3, 3)
	329 #23 (3, 3)
	330 iload (3, 3)
	331 #24 (3, 3)
	332 if_icmpge (3, 3)
	333 123 (3, 3)
	335 iload (4, 1)
	336 #21 (4, 1)
	337 iload (4, 1)
	338 #22 (4, 1)
	339 if_icmpge (4, 1)
	340 97 (4, 1)
	342 iload (5, 1)
	343 #23 (5, 1)
	344 iload (5, 1)
	345 #24 (5, 1)
	346 if_icmpge (5, 1)
	347 74 (5, 1)
	349 aload (6, 1)
	350 #6 (6, 1)
	351 iload (6, 1)
	352 #21 (6, 1)
	353 aaload (6, 1)
	354 invokevirtual (6, 1)
	355 org/apache/commons/math3/util/Pair.getSecond:()Ljava/lang/Object; (6, 1)
	357 checkcast (6, 1)
	358 java/lang/Double (6, 1)
	360 aload (6, 1)
	361 #6 (6, 1)
	362 iload (6, 1)
	363 #23 (6, 1)
	364 aaload (6, 1)
	365 invokevirtual (6, 1)
	366 org/apache/commons/math3/util/Pair.getSecond:()Ljava/lang/Object; (6, 1)
	368 checkcast (6, 1)
	369 java/lang/Double (6, 1)
	371 invokevirtual (6, 1)
	372 java/lang/Double.compareTo:(Ljava/lang/Double;)I (6, 1)
	374 ifgt (6, 1)
	375 19 (6, 1)
	377 aload (6, 1)
	378 #18 (6, 1)
	379 iload (6, 1)
	380 #25 (6, 1)
	381 aload (6, 1)
	382 #6 (6, 1)
	383 iload (6, 1)
	384 #21 (6, 1)
	385 aaload (6, 1)
	386 aastore (6, 1)
	387 iinc (6, 1)
	388 #21 (6, 1)
	389 -89 (6, 1)
	390 goto (6, 1)
	391 59 (6, 1)
	393 aload (7, 2)
	394 #18 (7, 2)
	395 iload (7, 2)
	396 #25 (7, 2)
	397 aload (7, 2)
	398 #6 (7, 2)
	399 iload (7, 2)
	400 #23 (7, 2)
	401 aaload (7, 2)
	402 aastore (7, 2)
	403 iinc (7, 2)
	404 #23 (7, 2)
	405 22 (7, 2)
	406 lload (7, 2)
	407 #16 (7, 2)
	408 iload (7, 2)
	409 #22 (7, 2)
	410 iload (7, 2)
	411 #21 (7, 2)
	412 isub (7, 2)
	413 i2l (7, 2)
	414 ladd (7, 2)
	415 lstore (7, 2)
	416 #16 (7, 2)
	417 goto (7, 2)
	418 32 (7, 2)
	420 aload (6, 2)
	421 #18 (6, 2)
	422 iload (6, 2)
	423 #25 (6, 2)
	424 aload (6, 2)
	425 #6 (6, 2)
	426 iload (6, 2)
	427 #21 (6, 2)
	428 aaload (6, 2)
	429 aastore (6, 2)
	430 iinc (6, 2)
	431 #21 (6, 2)
	432 -89 (6, 2)
	433 goto (6, 2)
	434 16 (6, 2)
	436 aload (5, 2)
	437 #18 (5, 2)
	438 iload (5, 2)
	439 #25 (5, 2)
	440 aload (5, 2)
	441 #6 (5, 2)
	442 iload (5, 2)
	443 #23 (5, 2)
	444 aaload (5, 2)
	445 aastore (5, 2)
	446 iinc (5, 2)
	447 #23 (5, 2)
	448 -124 (5, 2)
	449 iinc (3, 3)
	450 #25 (3, 3)
	451 -89 (3, 3)
	452 goto (3, 3)
	453 -131 (3, 3)
	455 iload (3, 3)
	456 #20 (3, 3)
	457 iconst_2 (3, 3)
	458 iload (3, 3)
	459 #19 (3, 3)
	460 imul (3, 3)
	461 iadd (3, 3)
	462 istore (3, 3)
	463 #20 (3, 3)
	464 goto (3, 3)
	465 -183 (3, 3)
	467 aload (2, 4)
	468 #6 (2, 4)
	469 astore (2, 4)
	470 #20 (2, 4)
	471 aload (2, 4)
	472 #18 (2, 4)
	473 astore (2, 4)
	474 #6 (2, 4)
	475 aload (2, 4)
	476 #20 (2, 4)
	477 astore (2, 4)
	478 #18 (2, 4)
	479 iload (2, 4)
	480 #19 (2, 4)
	481 iconst_1 (2, 4)
	482 ishl (2, 4)
	483 istore (2, 4)
	484 #19 (2, 4)
	485 goto (2, 4)
	486 -213 (2, 4)
	488 lconst_0 (1, 4)
	489 lstore (1, 4)
	490 #19 (1, 4)
	491 lconst_1 (1, 4)
	492 lstore (1, 4)
	493 #21 (1, 4)
	494 aload (1, 4)
	495 #6 (1, 4)
	496 iconst_0 (1, 4)
	497 aaload (1, 4)
	498 astore (1, 4)
	499 #15 (1, 4)
	500 iconst_1 (2, 4)
	501 istore (2, 4)
	502 #23 (2, 4)
	503 iload (2, 4)
	504 #23 (2, 4)
	505 iload_3 (2, 4)
	506 if_icmpge (2, 4)
	507 63 (2, 4)
	509 aload (2, 4)
	510 #6 (2, 4)
	511 iload (2, 4)
	512 #23 (2, 4)
	513 aaload (2, 4)
	514 astore (2, 4)
	515 #24 (2, 4)
	516 aload (3, 1)
	517 #24 (3, 1)
	518 invokevirtual (3, 1)
	519 org/apache/commons/math3/util/Pair.getSecond:()Ljava/lang/Object; (3, 1)
	521 checkcast (3, 1)
	522 java/lang/Double (3, 1)
	524 aload (3, 1)
	525 #15 (3, 1)
	526 invokevirtual (3, 1)
	527 org/apache/commons/math3/util/Pair.getSecond:()Ljava/lang/Object; (3, 1)
	529 invokevirtual (3, 1)
	530 java/lang/Double.equals:(Ljava/lang/Object;)Z (3, 1)
	532 ifeq (3, 1)
	533 12 (3, 1)
	535 lload (3, 1)
	536 #21 (3, 1)
	537 lconst_1 (3, 1)
	538 ladd (3, 1)
	539 lstore (3, 1)
	540 #21 (3, 1)
	541 goto (3, 1)
	542 18 (3, 1)
	544 lload (4, 2)
	545 #19 (4, 2)
	546 lload (4, 2)
	547 #21 (4, 2)
	548 lconst_1 (4, 2)
	549 lsub (4, 2)
	550 invokestatic (4, 2)
	551 org/apache/commons/math3/stat/correlation/KendallsCorrelation.sum:(J)J (4, 2)
	553 ladd (4, 2)
	554 lstore (4, 2)
	555 #19 (4, 2)
	556 lconst_1 (4, 2)
	557 lstore (4, 2)
	558 #21 (4, 2)
	559 aload (2, 4)
	560 #24 (2, 4)
	561 astore (2, 4)
	562 #15 (2, 4)
	563 iinc (2, 4)
	564 #23 (2, 4)
	565 -89 (2, 4)
	566 goto (2, 4)
	567 -63 (2, 4)
	569 lload (1, 4)
	570 #19 (1, 4)
	571 lload (1, 4)
	572 #21 (1, 4)
	573 lconst_1 (1, 4)
	574 lsub (1, 4)
	575 invokestatic (1, 4)
	576 org/apache/commons/math3/stat/correlation/KendallsCorrelation.sum:(J)J (1, 4)
	578 ladd (1, 4)
	579 lstore (1, 4)
	580 #19 (1, 4)
	581 lload (1, 4)
	582 #4 (1, 4)
	583 lload (1, 4)
	584 #7 (1, 4)
	585 lsub (1, 4)
	586 lload (1, 4)
	587 #19 (1, 4)
	588 lsub (1, 4)
	589 lload (1, 4)
	590 #9 (1, 4)
	591 ladd (1, 4)
	592 ldc2_w (1, 4)
	593 2 (1, 4)
	595 lload (1, 4)
	596 #16 (1, 4)
	597 lmul (1, 4)
	598 lsub (1, 4)
	599 lstore (1, 4)
	600 #23 (1, 4)
	601 lload (1, 4)
	602 #4 (1, 4)
	603 lload (1, 4)
	604 #7 (1, 4)
	605 lsub (1, 4)
	606 l2d (1, 4)
	607 lload (1, 4)
	608 #4 (1, 4)
	609 lload (1, 4)
	610 #19 (1, 4)
	611 lsub (1, 4)
	612 l2d (1, 4)
	613 dmul (1, 4)
	614 dstore (1, 4)
	615 #25 (1, 4)
	616 lload (1, 4)
	617 #23 (1, 4)
	618 l2d (1, 4)
	619 dload (1, 4)
	620 #25 (1, 4)
	621 invokestatic (1, 4)
	622 org/apache/commons/math3/util/FastMath.sqrt:(D)D (1, 4)
	624 ddiv (1, 4)
	625 dreturn (1, 4)

Method: sum
	0 lload_0 (0, 0)
	1 lload_0 (0, 0)
	2 lconst_1 (0, 0)
	3 ladd (0, 0)
	4 lmul (0, 0)
	5 ldc2_w (0, 0)
	6 2 (0, 0)
	8 ldiv (0, 0)
	9 lreturn (0, 0)

