Method: <init>
	0 aload_0 (0, 0)
	1 invokespecial (0, 0)
	2 java/lang/Object.<init>:()V (0, 0)
	4 aload_0 (0, 0)
	5 iload_2 (0, 0)
	6 putfield (0, 0)
	7 org/apache/commons/math3/stat/correlation/PearsonsCorrelation.nObs:I (0, 0)
	9 aload_0 (0, 0)
	10 aload_0 (0, 0)
	11 aload_1 (0, 0)
	12 invokevirtual (0, 0)
	13 org/apache/commons/math3/stat/correlation/PearsonsCorrelation.covarianceToCorrelation:(Lorg/apache/commons/math3/linear/RealMatrix;)Lorg/apache/commons/math3/linear/RealMatrix; (0, 0)
	15 putfield (0, 0)
	16 org/apache/commons/math3/stat/correlation/PearsonsCorrelation.correlationMatrix:Lorg/apache/commons/math3/linear/RealMatrix; (0, 0)
	18 return (0, 0)

Method: getCorrelationMatrix
	0 aload_0 (0, 0)
	1 getfield (0, 0)
	2 org/apache/commons/math3/stat/correlation/PearsonsCorrelation.correlationMatrix:Lorg/apache/commons/math3/linear/RealMatrix; (0, 0)
	4 areturn (0, 0)

Method: getCorrelationStandardErrors
	0 aload_0 (0, 0)
	1 getfield (0, 0)
	2 org/apache/commons/math3/stat/correlation/PearsonsCorrelation.correlationMatrix:Lorg/apache/commons/math3/linear/RealMatrix; (0, 0)
	4 invokeinterface (0, 0)
	5 org/apache/commons/math3/linear/RealMatrix.getEntry:(II)D (0, 0)
	7 0 (0, 0)
	9 istore_1 (0, 0)
	10 iload_1 (0, 0)
	11 iload_1 (0, 0)
	12 multianewarray (0, 0)
	13 [[D (0, 0)
	15 77 (0, 0)
	16 astore_2 (0, 0)
	17 iconst_0 (1, 4)
	18 istore_3 (1, 4)
	19 iload_3 (1, 4)
	20 iload_1 (1, 4)
	21 if_icmpge (1, 4)
	22 62 (1, 4)
	24 iconst_0 (2, 4)
	25 istore (2, 4)
	26 #4 (2, 4)
	27 iload (2, 4)
	28 #4 (2, 4)
	29 iload_1 (2, 4)
	30 if_icmpge (2, 4)
	31 47 (2, 4)
	33 aload_0 (2, 4)
	34 getfield (2, 4)
	35 org/apache/commons/math3/stat/correlation/PearsonsCorrelation.correlationMatrix:Lorg/apache/commons/math3/linear/RealMatrix; (2, 4)
	37 iload_3 (2, 4)
	38 iload (2, 4)
	39 #4 (2, 4)
	40 invokeinterface (2, 4)
	41 org/apache/commons/math3/linear/RealMatrix.org/apache/commons/math3/util/FastMath (2, 4)
	43 0 (2, 4)
	45 dstore (2, 4)
	46 #5 (2, 4)
	47 aload_2 (2, 4)
	48 iload_3 (2, 4)
	49 aaload (2, 4)
	50 iload (2, 4)
	51 #4 (2, 4)
	52 dconst_1 (2, 4)
	53 dload (2, 4)
	54 #5 (2, 4)
	55 dload (2, 4)
	56 #5 (2, 4)
	57 dmul (2, 4)
	58 dsub (2, 4)
	59 aload_0 (2, 4)
	60 getfield (2, 4)
	61 org/apache/commons/math3/stat/correlation/PearsonsCorrelation.nObs:I (2, 4)
	63 iconst_2 (2, 4)
	64 isub (2, 4)
	65 i2d (2, 4)
	66 ddiv (2, 4)
	67 invokestatic (2, 4)
	68 org/apache/commons/math3/util/FastMath.sqrt:(D)D (2, 4)
	70 dastore (2, 4)
	71 iinc (2, 4)
	72 #4 (2, 4)
	73 -89 (2, 4)
	74 goto (2, 4)
	75 -47 (2, 4)
	77 iinc (2, 4)
	78 #3 (2, 4)
	79 -89 (2, 4)
	80 goto (2, 4)
	81 -61 (2, 4)
	83 new (1, 4)
	84 org/apache/commons/math3/linear/BlockRealMatrix (1, 4)
	86 dup (1, 4)
	87 aload_2 (1, 4)
	88 invokespecial (1, 4)
	89 org/apache/commons/math3/linear/BlockRealMatrix.<init>:([[D)V (1, 4)
	91 areturn (1, 4)

Method: getCorrelationPValues
	0 new (0, 0)
	1 org/apache/commons/math3/distribution/TDistribution (0, 0)
	3 dup (0, 0)
	4 aload_0 (0, 0)
	5 getfield (0, 0)
	6 org/apache/commons/math3/stat/correlation/PearsonsCorrelation.nObs:I (0, 0)
	8 iconst_2 (0, 0)
	9 isub (0, 0)
	10 i2d (0, 0)
	11 invokespecial (0, 0)
	12 org/apache/commons/math3/distribution/TDistribution.<init>:(D)V (0, 0)
	14 astore_1 (0, 0)
	15 aload_0 (0, 0)
	16 getfield (0, 0)
	17 org/apache/commons/math3/stat/correlation/PearsonsCorrelation.correlationMatrix:Lorg/apache/commons/math3/linear/RealMatrix; (0, 0)
	19 invokeinterface (0, 0)
	20 org/apache/commons/math3/linear/RealMatrix.getEntry:(II)D (0, 0)
	22 0 (0, 0)
	24 istore_2 (0, 0)
	25 iload_2 (0, 0)
	26 iload_2 (0, 0)
	27 multianewarray (0, 0)
	28 [[D (0, 0)
	30 78 (0, 0)
	31 astore_3 (0, 0)
	32 iconst_0 (1, 4)
	33 istore (1, 4)
	34 #4 (1, 4)
	35 iload (1, 4)
	36 #4 (1, 4)
	37 iload_2 (1, 4)
	38 if_icmpge (1, 4)
	39 101 (1, 4)
	41 iconst_0 (2, 4)
	42 istore (2, 4)
	43 #5 (2, 4)
	44 iload (2, 4)
	45 #5 (2, 4)
	46 iload_2 (2, 4)
	47 if_icmpge (2, 4)
	48 86 (2, 4)
	50 iload (3, 1)
	51 #4 (3, 1)
	52 iload (3, 1)
	53 #5 (3, 1)
	54 if_icmpne (3, 1)
	55 14 (3, 1)
	57 aload_3 (3, 1)
	58 iload (3, 1)
	59 #4 (3, 1)
	60 aaload (3, 1)
	61 iload (3, 1)
	62 #5 (3, 1)
	63 dconst_0 (3, 1)
	64 dastore (3, 1)
	65 goto (3, 1)
	66 62 (3, 1)
	68 aload_0 (4, 2)
	69 getfield (4, 2)
	70 org/apache/commons/math3/stat/correlation/PearsonsCorrelation.correlationMatrix:Lorg/apache/commons/math3/linear/RealMatrix; (4, 2)
	72 iload (4, 2)
	73 #4 (4, 2)
	74 iload (4, 2)
	75 #5 (4, 2)
	76 invokeinterface (4, 2)
	77 org/apache/commons/math3/linear/RealMatrix.org/apache/commons/math3/util/FastMath (4, 2)
	79 0 (4, 2)
	81 dstore (4, 2)
	82 #6 (4, 2)
	83 dload (4, 2)
	84 #6 (4, 2)
	85 aload_0 (4, 2)
	86 getfield (4, 2)
	87 org/apache/commons/math3/stat/correlation/PearsonsCorrelation.nObs:I (4, 2)
	89 iconst_2 (4, 2)
	90 isub (4, 2)
	91 i2d (4, 2)
	92 dconst_1 (4, 2)
	93 dload (4, 2)
	94 #6 (4, 2)
	95 dload (4, 2)
	96 #6 (4, 2)
	97 dmul (4, 2)
	98 dsub (4, 2)
	99 ddiv (4, 2)
	100 invokestatic (4, 2)
	101 org/apache/commons/math3/util/FastMath.sqrt:(D)D (4, 2)
	103 dmul (4, 2)
	104 invokestatic (4, 2)
	105 org/apache/commons/math3/util/FastMath.abs:(D)D (4, 2)
	107 dstore (4, 2)
	108 #8 (4, 2)
	109 aload_3 (4, 2)
	110 iload (4, 2)
	111 #4 (4, 2)
	112 aaload (4, 2)
	113 iload (4, 2)
	114 #5 (4, 2)
	115 ldc2_w (4, 2)
	116 2.0 (4, 2)
	118 aload_1 (4, 2)
	119 dload (4, 2)
	120 #8 (4, 2)
	121 dneg (4, 2)
	122 invokevirtual (4, 2)
	123 org/apache/commons/math3/distribution/TDistribution.cumulativeProbability:(D)D (4, 2)
	125 dmul (4, 2)
	126 dastore (4, 2)
	127 iinc (4, 2)
	128 #5 (4, 2)
	129 -89 (4, 2)
	130 goto (4, 2)
	131 -86 (4, 2)
	133 iinc (4, 2)
	134 #4 (4, 2)
	135 -89 (4, 2)
	136 goto (4, 2)
	137 -101 (4, 2)
	139 new (2, 4)
	140 org/apache/commons/math3/linear/BlockRealMatrix (2, 4)
	142 dup (2, 4)
	143 aload_3 (2, 4)
	144 invokespecial (2, 4)
	145 org/apache/commons/math3/linear/BlockRealMatrix.<init>:([[D)V (2, 4)
	147 areturn (2, 4)

Method: computeCorrelationMatrix
	0 aload_0 (0, 0)
	1 new (0, 0)
	2 org/apache/commons/math3/linear/BlockRealMatrix (0, 0)
	4 dup (0, 0)
	5 aload_1 (0, 0)
	6 invokespecial (0, 0)
	7 org/apache/commons/math3/linear/BlockRealMatrix.<init>:([[D)V (0, 0)
	9 invokevirtual (0, 0)
	10 org/apache/commons/math3/stat/correlation/PearsonsCorrelation.computeCorrelationMatrix:(Lorg/apache/commons/math3/linear/RealMatrix;)Lorg/apache/commons/math3/linear/RealMatrix; (0, 0)
	12 areturn (0, 0)

Method: correlation
	0 new (0, 0)
	1 org/apache/commons/math3/stat/regression/SimpleRegression (0, 0)
	3 dup (0, 0)
	4 invokespecial (0, 0)
	5 org/apache/commons/math3/stat/regression/SimpleRegression.<init>:()V (0, 0)
	7 astore_3 (0, 0)
	8 aload_1 (1, 1)
	9 arraylength (1, 1)
	10 aload_2 (1, 1)
	11 arraylength (1, 1)
	12 if_icmpeq (1, 1)
	13 15 (1, 1)
	15 new (1, 1)
	16 org/apache/commons/math3/exception/DimensionMismatchException (1, 1)
	18 dup (1, 1)
	19 aload_1 (1, 1)
	20 arraylength (1, 1)
	21 aload_2 (1, 1)
	22 arraylength (1, 1)
	23 invokespecial (1, 1)
	24 org/apache/commons/math3/exception/DimensionMismatchException.<init>:(II)V (1, 1)
	26 athrow (1, 1)
	27 aload_1 (2, 1)
	28 arraylength (2, 1)
	29 iconst_2 (2, 1)
	30 if_icmpge (2, 1)
	31 33 (2, 1)
	33 new (2, 1)
	34 org/apache/commons/math3/exception/MathIllegalArgumentException (2, 1)
	36 dup (2, 1)
	37 getstatic (2, 1)
	38 org/apache/commons/math3/exception/util/LocalizedFormats.INSUFFICIENT_DIMENSION:Lorg/apache/commons/math3/exception/util/LocalizedFormats; (2, 1)
	40 iconst_2 (2, 1)
	41 anewarray (2, 1)
	42 java/lang/Object (2, 1)
	44 dup (2, 1)
	45 iconst_0 (2, 1)
	46 aload_1 (2, 1)
	47 arraylength (2, 1)
	48 invokestatic (2, 1)
	49 java/lang/Integer.valueOf:(I)Ljava/lang/Integer; (2, 1)
	51 aastore (2, 1)
	52 dup (2, 1)
	53 iconst_1 (2, 1)
	54 iconst_2 (2, 1)
	55 invokestatic (2, 1)
	56 java/lang/Integer.valueOf:(I)Ljava/lang/Integer; (2, 1)
	58 aastore (2, 1)
	59 invokespecial (2, 1)
	60 org/apache/commons/math3/exception/MathIllegalArgumentException.<init>:(Lorg/apache/commons/math3/exception/util/Localizable;[Ljava/lang/Object;)V (2, 1)
	62 athrow (2, 1)
	63 iconst_0 (4, 4)
	64 istore (4, 4)
	65 #4 (4, 4)
	66 iload (4, 4)
	67 #4 (4, 4)
	68 aload_1 (4, 4)
	69 arraylength (4, 4)
	70 if_icmpge (4, 4)
	71 21 (4, 4)
	73 aload_3 (4, 4)
	74 aload_1 (4, 4)
	75 iload (4, 4)
	76 #4 (4, 4)
	77 daload (4, 4)
	78 aload_2 (4, 4)
	79 iload (4, 4)
	80 #4 (4, 4)
	81 daload (4, 4)
	82 invokevirtual (4, 4)
	83 org/apache/commons/math3/stat/regression/SimpleRegression.addData:(DD)V (4, 4)
	85 iinc (4, 4)
	86 #4 (4, 4)
	87 -89 (4, 4)
	88 goto (4, 4)
	89 -22 (4, 4)
	91 aload_3 (3, 2)
	92 invokevirtual (3, 2)
	93 org/apache/commons/math3/stat/regression/SimpleRegression.getR:()D (3, 2)
	95 dreturn (1, 2)

Method: covarianceToCorrelation
	0 aload_1 (0, 0)
	1 invokeinterface (0, 0)
	2 org/apache/commons/math3/linear/RealMatrix.getEntry:(II)D (0, 0)
	4 0 (0, 0)
	6 istore_2 (0, 0)
	7 new (0, 0)
	8 org/apache/commons/math3/linear/BlockRealMatrix (0, 0)
	10 dup (0, 0)
	11 iload_2 (0, 0)
	12 iload_2 (0, 0)
	13 invokespecial (0, 0)
	14 org/apache/commons/math3/linear/BlockRealMatrix.<init>:(II)V (0, 0)
	16 astore_3 (0, 0)
	17 iconst_0 (1, 4)
	18 istore (1, 4)
	19 #4 (1, 4)
	20 iload (1, 4)
	21 #4 (1, 4)
	22 iload_2 (1, 4)
	23 if_icmpge (1, 4)
	24 104 (1, 4)
	26 aload_1 (1, 4)
	27 iload (1, 4)
	28 #4 (1, 4)
	29 iload (1, 4)
	30 #4 (1, 4)
	31 invokeinterface (1, 4)
	32 org/apache/commons/math3/linear/RealMatrix.org/apache/commons/math3/util/FastMath (1, 4)
	34 0 (1, 4)
	36 invokestatic (1, 4)
	37 org/apache/commons/math3/util/FastMath.sqrt:(D)D (1, 4)
	39 dstore (1, 4)
	40 #5 (1, 4)
	41 aload_3 (1, 4)
	42 iload (1, 4)
	43 #4 (1, 4)
	44 iload (1, 4)
	45 #4 (1, 4)
	46 dconst_1 (1, 4)
	47 invokeinterface (1, 4)
	48 org/apache/commons/math3/linear/RealMatrix.org/apache/commons/math3/stat/regression/SimpleRegression (1, 4)
	50 0 (1, 4)
	52 iconst_0 (2, 4)
	53 istore (2, 4)
	54 #7 (2, 4)
	55 iload (2, 4)
	56 #7 (2, 4)
	57 iload (2, 4)
	58 #4 (2, 4)
	59 if_icmpge (2, 4)
	60 62 (2, 4)
	62 aload_1 (2, 4)
	63 iload (2, 4)
	64 #4 (2, 4)
	65 iload (2, 4)
	66 #7 (2, 4)
	67 invokeinterface (2, 4)
	68 org/apache/commons/math3/linear/RealMatrix.org/apache/commons/math3/util/FastMath (2, 4)
	70 0 (2, 4)
	72 dload (2, 4)
	73 #5 (2, 4)
	74 aload_1 (2, 4)
	75 iload (2, 4)
	76 #7 (2, 4)
	77 iload (2, 4)
	78 #7 (2, 4)
	79 invokeinterface (2, 4)
	80 org/apache/commons/math3/linear/RealMatrix.org/apache/commons/math3/util/FastMath (2, 4)
	82 0 (2, 4)
	84 invokestatic (2, 4)
	85 org/apache/commons/math3/util/FastMath.sqrt:(D)D (2, 4)
	87 dmul (2, 4)
	88 ddiv (2, 4)
	89 dstore (2, 4)
	90 #8 (2, 4)
	91 aload_3 (2, 4)
	92 iload (2, 4)
	93 #4 (2, 4)
	94 iload (2, 4)
	95 #7 (2, 4)
	96 dload (2, 4)
	97 #8 (2, 4)
	98 invokeinterface (2, 4)
	99 org/apache/commons/math3/linear/RealMatrix.org/apache/commons/math3/stat/regression/SimpleRegression (2, 4)
	101 0 (2, 4)
	103 aload_3 (2, 4)
	104 iload (2, 4)
	105 #7 (2, 4)
	106 iload (2, 4)
	107 #4 (2, 4)
	108 dload (2, 4)
	109 #8 (2, 4)
	110 invokeinterface (2, 4)
	111 org/apache/commons/math3/linear/RealMatrix.org/apache/commons/math3/stat/regression/SimpleRegression (2, 4)
	113 0 (2, 4)
	115 iinc (2, 4)
	116 #7 (2, 4)
	117 -89 (2, 4)
	118 goto (2, 4)
	119 -63 (2, 4)
	121 iinc (2, 4)
	122 #4 (2, 4)
	123 -89 (2, 4)
	124 goto (2, 4)
	125 -104 (2, 4)
	127 aload_3 (1, 4)
	128 areturn (1, 4)

Method: checkSufficientData
	0 aload_1 (0, 0)
	1 invokeinterface (0, 0)
	2 org/apache/commons/math3/linear/RealMatrix.computeCorrelationMatrix:(Lorg/apache/commons/math3/linear/RealMatrix;)Lorg/apache/commons/math3/linear/RealMatrix; (0, 0)
	4 0 (0, 0)
	6 istore_2 (0, 0)
	7 aload_1 (0, 0)
	8 invokeinterface (0, 0)
	9 org/apache/commons/math3/linear/RealMatrix.getEntry:(II)D (0, 0)
	11 0 (0, 0)
	13 istore_3 (0, 0)
	14 iload_2 (1, 1)
	15 iconst_2 (1, 1)
	16 if_icmplt (1, 1)
	17 8 (1, 1)
	19 iload_3 (1, 1)
	20 iconst_2 (1, 1)
	21 if_icmpge (1, 1)
	22 32 (1, 1)
	24 new (1, 1)
	25 org/apache/commons/math3/exception/MathIllegalArgumentException (1, 1)
	27 dup (1, 1)
	28 getstatic (1, 1)
	29 org/apache/commons/math3/exception/util/LocalizedFormats.INSUFFICIENT_ROWS_AND_COLUMNS:Lorg/apache/commons/math3/exception/util/LocalizedFormats; (1, 1)
	31 iconst_2 (1, 1)
	32 anewarray (1, 1)
	33 java/lang/Object (1, 1)
	35 dup (1, 1)
	36 iconst_0 (1, 1)
	37 iload_2 (1, 1)
	38 invokestatic (1, 1)
	39 java/lang/Integer.valueOf:(I)Ljava/lang/Integer; (1, 1)
	41 aastore (1, 1)
	42 dup (1, 1)
	43 iconst_1 (1, 1)
	44 iload_3 (1, 1)
	45 invokestatic (1, 1)
	46 java/lang/Integer.valueOf:(I)Ljava/lang/Integer; (1, 1)
	48 aastore (1, 1)
	49 invokespecial (1, 1)
	50 org/apache/commons/math3/exception/MathIllegalArgumentException.<init>:(Lorg/apache/commons/math3/exception/util/Localizable;[Ljava/lang/Object;)V (1, 1)
	52 athrow (1, 1)
	53 return (0, 0)

