Method: <init>
	0 aload_0 (0, 0)
	1 invokespecial (0, 0)
	2 java/lang/Object.<init>:()V (0, 0)
	4 aload_0 (0, 0)
	5 aload_2 (0, 0)
	6 putfield (0, 0)
	7 org/apache/commons/math3/stat/correlation/SpearmansCorrelation.rankingAlgorithm:Lorg/apache/commons/math3/stat/ranking/RankingAlgorithm; (0, 0)
	9 aload_0 (1, 4)
	10 aload_0 (1, 4)
	11 aload_1 (1, 4)
	12 invokespecial (1, 4)
	13 org/apache/commons/math3/stat/correlation/SpearmansCorrelation.rankTransform:(Lorg/apache/commons/math3/linear/RealMatrix;)Lorg/apache/commons/math3/linear/RealMatrix; (1, 4)
	15 putfield (1, 4)
	16 org/apache/commons/math3/stat/correlation/SpearmansCorrelation.data:Lorg/apache/commons/math3/linear/RealMatrix; (1, 4)
	18 aload_0 (1, 4)
	19 new (1, 4)
	20 org/apache/commons/math3/stat/correlation/PearsonsCorrelation (1, 4)
	22 dup (1, 4)
	23 aload_0 (1, 4)
	24 getfield (1, 4)
	25 org/apache/commons/math3/stat/correlation/SpearmansCorrelation.data:Lorg/apache/commons/math3/linear/RealMatrix; (1, 4)
	27 invokespecial (1, 4)
	28 org/apache/commons/math3/stat/correlation/PearsonsCorrelation.<init>:(Lorg/apache/commons/math3/linear/RealMatrix;)V (1, 4)
	30 putfield (1, 4)
	31 org/apache/commons/math3/stat/correlation/SpearmansCorrelation.rankCorrelation:Lorg/apache/commons/math3/stat/correlation/PearsonsCorrelation; (1, 4)
	33 return (0, 0)

Method: getCorrelationMatrix
	0 aload_0 (0, 0)
	1 getfield (0, 0)
	2 org/apache/commons/math3/stat/correlation/SpearmansCorrelation.rankCorrelation:Lorg/apache/commons/math3/stat/correlation/PearsonsCorrelation; (0, 0)
	4 invokevirtual (0, 0)
	5 org/apache/commons/math3/stat/correlation/PearsonsCorrelation.getCorrelationMatrix:()Lorg/apache/commons/math3/linear/RealMatrix; (0, 0)
	7 areturn (0, 0)

Method: getRankCorrelation
	0 aload_0 (0, 0)
	1 getfield (0, 0)
	2 org/apache/commons/math3/stat/correlation/SpearmansCorrelation.rankCorrelation:Lorg/apache/commons/math3/stat/correlation/PearsonsCorrelation; (0, 0)
	4 areturn (0, 0)

Method: computeCorrelationMatrix
	0 aload_0 (0, 0)
	1 new (0, 0)
	2 org/apache/commons/math3/linear/BlockRealMatrix (0, 0)
	4 dup (0, 0)
	5 aload_1 (0, 0)
	6 invokespecial (0, 0)
	7 org/apache/commons/math3/linear/BlockRealMatrix.<init>:([[D)V (0, 0)
	9 invokevirtual (0, 0)
	10 org/apache/commons/math3/stat/correlation/SpearmansCorrelation.computeCorrelationMatrix:(Lorg/apache/commons/math3/linear/RealMatrix;)Lorg/apache/commons/math3/linear/RealMatrix; (0, 0)
	12 areturn (0, 0)

Method: correlation
	0 aload_1 (1, 1)
	1 arraylength (1, 1)
	2 aload_2 (1, 1)
	3 arraylength (1, 1)
	4 if_icmpeq (1, 1)
	5 15 (1, 1)
	7 new (1, 1)
	8 org/apache/commons/math3/exception/DimensionMismatchException (1, 1)
	10 dup (1, 1)
	11 aload_1 (1, 1)
	12 arraylength (1, 1)
	13 aload_2 (1, 1)
	14 arraylength (1, 1)
	15 invokespecial (1, 1)
	16 org/apache/commons/math3/exception/DimensionMismatchException.<init>:(II)V (1, 1)
	18 athrow (1, 1)
	19 aload_1 (1, 1)
	20 arraylength (1, 1)
	21 iconst_2 (1, 1)
	22 if_icmpge (1, 1)
	23 33 (1, 1)
	25 new (1, 1)
	26 org/apache/commons/math3/exception/MathIllegalArgumentException (1, 1)
	28 dup (1, 1)
	29 getstatic (1, 1)
	30 org/apache/commons/math3/exception/util/LocalizedFormats.INSUFFICIENT_DIMENSION:Lorg/apache/commons/math3/exception/util/LocalizedFormats; (1, 1)
	32 iconst_2 (1, 1)
	33 anewarray (1, 1)
	34 java/lang/Object (1, 1)
	36 dup (1, 1)
	37 iconst_0 (1, 1)
	38 aload_1 (1, 1)
	39 arraylength (1, 1)
	40 invokestatic (1, 1)
	41 java/lang/Integer.valueOf:(I)Ljava/lang/Integer; (1, 1)
	43 aastore (1, 1)
	44 dup (1, 1)
	45 iconst_1 (1, 1)
	46 iconst_2 (1, 1)
	47 invokestatic (1, 1)
	48 java/lang/Integer.valueOf:(I)Ljava/lang/Integer; (1, 1)
	50 aastore (1, 1)
	51 invokespecial (1, 1)
	52 org/apache/commons/math3/exception/MathIllegalArgumentException.<init>:(Lorg/apache/commons/math3/exception/util/Localizable;[Ljava/lang/Object;)V (1, 1)
	54 athrow (1, 1)
	55 aload_1 (1, 2)
	56 astore_3 (1, 2)
	57 aload_2 (1, 2)
	58 astore (1, 2)
	59 #4 (1, 2)
	60 aload_0 (1, 1)
	61 getfield (1, 1)
	62 org/apache/commons/math3/stat/correlation/SpearmansCorrelation.rankingAlgorithm:Lorg/apache/commons/math3/stat/ranking/RankingAlgorithm; (1, 1)
	64 instanceof (1, 1)
	65 org/apache/commons/math3/stat/ranking/NaturalRanking (1, 1)
	67 ifeq (1, 1)
	68 71 (1, 1)
	70 getstatic (1, 1)
	71 org/apache/commons/math3/stat/ranking/NaNStrategy.REMOVED:Lorg/apache/commons/math3/stat/ranking/NaNStrategy; (1, 1)
	73 aload_0 (1, 1)
	74 getfield (1, 1)
	75 org/apache/commons/math3/stat/correlation/SpearmansCorrelation.rankingAlgorithm:Lorg/apache/commons/math3/stat/ranking/RankingAlgorithm; (1, 1)
	77 checkcast (1, 1)
	78 org/apache/commons/math3/stat/ranking/NaturalRanking (1, 1)
	80 invokevirtual (1, 1)
	81 org/apache/commons/math3/stat/ranking/NaturalRanking.getNanStrategy:()Lorg/apache/commons/math3/stat/ranking/NaNStrategy; (1, 1)
	83 if_acmpne (1, 1)
	84 55 (1, 1)
	86 new (1, 1)
	87 java/util/HashSet (1, 1)
	89 dup (1, 1)
	90 invokespecial (1, 1)
	91 java/util/HashSet.<init>:()V (1, 1)
	93 astore (1, 1)
	94 #5 (1, 1)
	95 aload (1, 1)
	96 #5 (1, 1)
	97 aload_0 (1, 1)
	98 aload_1 (1, 1)
	99 invokespecial (1, 1)
	100 org/apache/commons/math3/stat/correlation/SpearmansCorrelation.getNaNPositions:([D)Ljava/util/List; (1, 1)
	102 invokeinterface (1, 1)
	103 java/util/Set.removeValues:([DLjava/util/Set;)[D (1, 1)
	105 0 (1, 1)
	107 pop (1, 1)
	108 aload (1, 1)
	109 #5 (1, 1)
	110 aload_0 (1, 1)
	111 aload_2 (1, 1)
	112 invokespecial (1, 1)
	113 org/apache/commons/math3/stat/correlation/SpearmansCorrelation.getNaNPositions:([D)Ljava/util/List; (1, 1)
	115 invokeinterface (1, 1)
	116 java/util/Set.removeValues:([DLjava/util/Set;)[D (1, 1)
	118 0 (1, 1)
	120 pop (1, 1)
	121 aload_0 (1, 1)
	122 aload_1 (1, 1)
	123 aload (1, 1)
	124 #5 (1, 1)
	125 invokespecial (1, 1)
	126 org/apache/commons/math3/stat/correlation/SpearmansCorrelation.removeValues:([DLjava/util/Set;)[D (1, 1)
	128 astore_3 (1, 1)
	129 aload_0 (1, 1)
	130 aload_2 (1, 1)
	131 aload (1, 1)
	132 #5 (1, 1)
	133 invokespecial (1, 1)
	134 org/apache/commons/math3/stat/correlation/SpearmansCorrelation.removeValues:([DLjava/util/Set;)[D (1, 1)
	136 astore (1, 1)
	137 #4 (1, 1)
	138 new (1, 1)
	139 org/apache/commons/math3/stat/correlation/PearsonsCorrelation (1, 1)
	141 dup (1, 1)
	142 invokespecial (1, 1)
	143 org/apache/commons/math3/stat/correlation/PearsonsCorrelation.<init>:()V (1, 1)
	145 aload_0 (1, 1)
	146 getfield (1, 1)
	147 org/apache/commons/math3/stat/correlation/SpearmansCorrelation.rankingAlgorithm:Lorg/apache/commons/math3/stat/ranking/RankingAlgorithm; (1, 1)
	149 aload_3 (1, 1)
	150 invokeinterface (1, 1)
	151 org/apache/commons/math3/stat/ranking/RankingAlgorithm.correlation:([D[D)D (1, 1)
	153 0 (1, 1)
	155 aload_0 (1, 1)
	156 getfield (1, 1)
	157 org/apache/commons/math3/stat/correlation/SpearmansCorrelation.rankingAlgorithm:Lorg/apache/commons/math3/stat/ranking/RankingAlgorithm; (1, 1)
	159 aload (1, 1)
	160 #4 (1, 1)
	161 invokeinterface (1, 1)
	162 org/apache/commons/math3/stat/ranking/RankingAlgorithm.correlation:([D[D)D (1, 1)
	164 0 (1, 1)
	166 invokevirtual (1, 1)
	167 org/apache/commons/math3/stat/correlation/PearsonsCorrelation.correlation:([D[D)D (1, 1)
	169 dreturn (1, 1)

Method: rankTransform
	0 aconst_null (0, 4)
	1 astore_2 (0, 4)
	2 aload_0 (0, 1)
	3 getfield (0, 1)
	4 org/apache/commons/math3/stat/correlation/SpearmansCorrelation.rankingAlgorithm:Lorg/apache/commons/math3/stat/ranking/RankingAlgorithm; (0, 1)
	6 instanceof (0, 1)
	7 org/apache/commons/math3/stat/ranking/NaturalRanking (0, 1)
	9 ifeq (0, 1)
	10 143 (0, 1)
	12 aload_0 (0, 1)
	13 getfield (0, 1)
	14 org/apache/commons/math3/stat/correlation/SpearmansCorrelation.rankingAlgorithm:Lorg/apache/commons/math3/stat/ranking/RankingAlgorithm; (0, 1)
	16 checkcast (0, 1)
	17 org/apache/commons/math3/stat/ranking/NaturalRanking (0, 1)
	19 invokevirtual (0, 1)
	20 org/apache/commons/math3/stat/ranking/NaturalRanking.getNanStrategy:()Lorg/apache/commons/math3/stat/ranking/NaNStrategy; (0, 1)
	22 getstatic (0, 1)
	23 org/apache/commons/math3/stat/ranking/NaNStrategy.REMOVED:Lorg/apache/commons/math3/stat/ranking/NaNStrategy; (0, 1)
	25 if_acmpne (0, 1)
	26 127 (0, 1)
	28 new (0, 1)
	29 java/util/HashSet (0, 1)
	31 dup (0, 1)
	32 invokespecial (0, 1)
	33 java/util/HashSet.<init>:()V (0, 1)
	35 astore_3 (0, 1)
	36 iconst_0 (2, 4)
	37 istore (2, 4)
	38 #4 (2, 4)
	39 iload (2, 4)
	40 #4 (2, 4)
	41 aload_1 (2, 4)
	42 invokeinterface (2, 4)
	43 org/apache/commons/math3/linear/RealMatrix.getColumn:(I)[D (2, 4)
	45 0 (2, 4)
	47 if_icmpge (2, 4)
	48 28 (2, 4)
	50 aload_3 (2, 4)
	51 aload_0 (2, 4)
	52 aload_1 (2, 4)
	53 iload (2, 4)
	54 #4 (2, 4)
	55 invokeinterface (2, 4)
	56 org/apache/commons/math3/linear/RealMatrix.isEmpty:()Z (2, 4)
	58 0 (2, 4)
	60 invokespecial (2, 4)
	61 org/apache/commons/math3/stat/correlation/SpearmansCorrelation.getNaNPositions:([D)Ljava/util/List; (2, 4)
	63 invokeinterface (2, 4)
	64 java/util/Set.removeValues:([DLjava/util/Set;)[D (2, 4)
	66 0 (2, 4)
	68 pop (2, 4)
	69 iinc (2, 4)
	70 #4 (2, 4)
	71 -89 (2, 4)
	72 goto (2, 4)
	73 -33 (2, 4)
	75 aload_3 (2, 1)
	76 invokeinterface (2, 1)
	77 java/util/Set.getRowDimension:()I (2, 1)
	79 0 (2, 1)
	81 ifne (2, 1)
	82 71 (2, 1)
	84 new (2, 4)
	85 org/apache/commons/math3/linear/BlockRealMatrix (2, 4)
	87 dup (2, 4)
	88 aload_1 (2, 4)
	89 invokeinterface (2, 4)
	90 org/apache/commons/math3/linear/RealMatrix.size:()I (2, 4)
	92 0 (2, 4)
	94 aload_3 (2, 4)
	95 invokeinterface (2, 4)
	96 java/util/Set.setColumn:(I[D)V (2, 4)
	98 0 (2, 4)
	100 isub (2, 4)
	101 aload_1 (2, 4)
	102 invokeinterface (2, 4)
	103 org/apache/commons/math3/linear/RealMatrix.getColumn:(I)[D (2, 4)
	105 0 (2, 4)
	107 invokespecial (2, 4)
	108 org/apache/commons/math3/linear/BlockRealMatrix.<init>:(II)V (2, 4)
	110 astore_2 (2, 4)
	111 iconst_0 (3, 4)
	112 istore (3, 4)
	113 #4 (3, 4)
	114 iload (3, 4)
	115 #4 (3, 4)
	116 aload_2 (3, 4)
	117 invokeinterface (3, 4)
	118 org/apache/commons/math3/linear/RealMatrix.getColumn:(I)[D (3, 4)
	120 0 (3, 4)
	122 if_icmpge (3, 4)
	123 30 (3, 4)
	125 aload_2 (3, 4)
	126 iload (3, 4)
	127 #4 (3, 4)
	128 aload_0 (3, 4)
	129 aload_1 (3, 4)
	130 iload (3, 4)
	131 #4 (3, 4)
	132 invokeinterface (3, 4)
	133 org/apache/commons/math3/linear/RealMatrix.isEmpty:()Z (3, 4)
	135 0 (3, 4)
	137 aload_3 (3, 4)
	138 invokespecial (3, 4)
	139 org/apache/commons/math3/stat/correlation/SpearmansCorrelation.removeValues:([DLjava/util/Set;)[D (3, 4)
	141 invokeinterface (3, 4)
	142 org/apache/commons/math3/linear/RealMatrix.copy:()Lorg/apache/commons/math3/linear/RealMatrix; (3, 4)
	144 0 (3, 4)
	146 iinc (3, 4)
	147 #4 (3, 4)
	148 -89 (3, 4)
	149 goto (3, 4)
	150 -35 (3, 4)
	152 aload_2 (1, 1)
	153 ifnonnull (1, 1)
	154 10 (1, 1)
	156 aload_1 (1, 4)
	157 invokeinterface (1, 4)
	158 org/apache/commons/math3/linear/RealMatrix.java/util/ArrayList (1, 4)
	160 0 (1, 4)
	162 astore_2 (1, 4)
	163 iconst_0 (1, 4)
	164 istore_3 (1, 4)
	165 iload_3 (1, 4)
	166 aload_2 (1, 4)
	167 invokeinterface (1, 4)
	168 org/apache/commons/math3/linear/RealMatrix.getColumn:(I)[D (1, 4)
	170 0 (1, 4)
	172 if_icmpge (1, 4)
	173 32 (1, 4)
	175 aload_2 (1, 4)
	176 iload_3 (1, 4)
	177 aload_0 (1, 4)
	178 getfield (1, 4)
	179 org/apache/commons/math3/stat/correlation/SpearmansCorrelation.rankingAlgorithm:Lorg/apache/commons/math3/stat/ranking/RankingAlgorithm; (1, 4)
	181 aload_2 (1, 4)
	182 iload_3 (1, 4)
	183 invokeinterface (1, 4)
	184 org/apache/commons/math3/linear/RealMatrix.isEmpty:()Z (1, 4)
	186 0 (1, 4)
	188 invokeinterface (1, 4)
	189 org/apache/commons/math3/stat/ranking/RankingAlgorithm.correlation:([D[D)D (1, 4)
	191 0 (1, 4)
	193 invokeinterface (1, 4)
	194 org/apache/commons/math3/linear/RealMatrix.copy:()Lorg/apache/commons/math3/linear/RealMatrix; (1, 4)
	196 0 (1, 4)
	198 iinc (1, 4)
	199 #3 (1, 4)
	200 -89 (1, 4)
	201 goto (1, 4)
	202 -36 (1, 4)
	204 aload_2 (0, 4)
	205 areturn (0, 4)

Method: getNaNPositions
	0 new (0, 0)
	1 java/util/ArrayList (0, 0)
	3 dup (0, 0)
	4 invokespecial (0, 0)
	5 java/util/ArrayList.<init>:()V (0, 0)
	7 astore_2 (0, 0)
	8 iconst_0 (1, 4)
	9 istore_3 (1, 4)
	10 iload_3 (1, 4)
	11 aload_1 (1, 4)
	12 arraylength (1, 4)
	13 if_icmpge (1, 4)
	14 29 (1, 4)
	16 aload_1 (2, 1)
	17 iload_3 (2, 1)
	18 daload (2, 1)
	19 invokestatic (2, 1)
	20 java/lang/Double.isNaN:(D)Z (2, 1)
	22 ifeq (2, 1)
	23 14 (2, 1)
	25 aload_2 (2, 1)
	26 iload_3 (2, 1)
	27 invokestatic (2, 1)
	28 java/lang/Integer.valueOf:(I)Ljava/lang/Integer; (2, 1)
	30 invokeinterface (2, 1)
	31 java/util/List.contains:(Ljava/lang/Object;)Z (2, 1)
	33 0 (2, 1)
	35 pop (2, 1)
	36 iinc (2, 1)
	37 #3 (2, 1)
	38 -89 (2, 1)
	39 goto (2, 1)
	40 -29 (2, 1)
	42 aload_2 (1, 4)
	43 areturn (1, 4)

Method: removeValues
	0 aload_2 (1, 1)
	1 invokeinterface (1, 1)
	2 java/util/Set.getRowDimension:()I (1, 1)
	4 0 (1, 1)
	6 ifeq (1, 1)
	7 5 (1, 1)
	9 aload_1 (1, 1)
	10 areturn (1, 1)
	11 aload_1 (0, 0)
	12 arraylength (0, 0)
	13 aload_2 (0, 0)
	14 invokeinterface (0, 0)
	15 java/util/Set.setColumn:(I[D)V (0, 0)
	17 0 (0, 0)
	19 isub (0, 0)
	20 newarray (0, 0)
	21 7 (0, 0)
	22 astore_3 (0, 0)
	23 iconst_0 (1, 4)
	24 istore (1, 4)
	25 #4 (1, 4)
	26 iconst_0 (1, 4)
	27 istore (1, 4)
	28 #5 (1, 4)
	29 iload (1, 4)
	30 #4 (1, 4)
	31 aload_1 (1, 4)
	32 arraylength (1, 4)
	33 if_icmpge (1, 4)
	34 34 (1, 4)
	36 aload_2 (2, 1)
	37 iload (2, 1)
	38 #4 (2, 1)
	39 invokestatic (2, 1)
	40 java/lang/Integer.valueOf:(I)Ljava/lang/Integer; (2, 1)
	42 invokeinterface (2, 1)
	43 java/util/Set.org/apache/commons/math3/stat/correlation/SpearmansCorrelation (2, 1)
	45 0 (2, 1)
	47 ifne (2, 1)
	48 14 (2, 1)
	50 aload_3 (2, 1)
	51 iload (2, 1)
	52 #5 (2, 1)
	53 iinc (2, 1)
	54 #5 (2, 1)
	55 43 (2, 1)
	56 aload_1 (2, 1)
	57 iload (2, 1)
	58 #4 (2, 1)
	59 daload (2, 1)
	60 dastore (2, 1)
	61 iinc (2, 1)
	62 #4 (2, 1)
	63 -89 (2, 1)
	64 goto (2, 1)
	65 -35 (2, 1)
	67 aload_3 (1, 4)
	68 areturn (1, 4)

