Method: <init>
	0 aload_0 (0, 0)
	1 invokespecial (0, 0)
	2 java/lang/Object.<init>:()V (0, 0)
	4 aload_0 (0, 0)
	5 aload_0 (0, 0)
	6 dconst_0 (0, 0)
	7 dup2_x1 (0, 0)
	8 putfield (0, 0)
	9 org/apache/commons/math3/stat/correlation/StorelessBivariateCovariance.meanY:D (0, 0)
	11 putfield (0, 0)
	12 org/apache/commons/math3/stat/correlation/StorelessBivariateCovariance.meanX:D (0, 0)
	14 aload_0 (0, 0)
	15 dconst_0 (0, 0)
	16 putfield (0, 0)
	17 org/apache/commons/math3/stat/correlation/StorelessBivariateCovariance.n:D (0, 0)
	19 aload_0 (0, 0)
	20 dconst_0 (0, 0)
	21 putfield (0, 0)
	22 org/apache/commons/math3/stat/correlation/StorelessBivariateCovariance.covarianceNumerator:D (0, 0)
	24 aload_0 (0, 0)
	25 iload_1 (0, 0)
	26 putfield (0, 0)
	27 org/apache/commons/math3/stat/correlation/StorelessBivariateCovariance.biasCorrected:Z (0, 0)
	29 return (0, 0)

Method: increment
	0 aload_0 (0, 0)
	1 dup (0, 0)
	2 getfield (0, 0)
	3 org/apache/commons/math3/stat/correlation/StorelessBivariateCovariance.n:D (0, 0)
	5 dconst_1 (0, 0)
	6 dadd (0, 0)
	7 putfield (0, 0)
	8 org/apache/commons/math3/stat/correlation/StorelessBivariateCovariance.n:D (0, 0)
	10 dload_1 (0, 0)
	11 aload_0 (0, 0)
	12 getfield (0, 0)
	13 org/apache/commons/math3/stat/correlation/StorelessBivariateCovariance.meanX:D (0, 0)
	15 dsub (0, 0)
	16 dstore (0, 0)
	17 #5 (0, 0)
	18 dload_3 (0, 0)
	19 aload_0 (0, 0)
	20 getfield (0, 0)
	21 org/apache/commons/math3/stat/correlation/StorelessBivariateCovariance.meanY:D (0, 0)
	23 dsub (0, 0)
	24 dstore (0, 0)
	25 #7 (0, 0)
	26 aload_0 (0, 0)
	27 dup (0, 0)
	28 getfield (0, 0)
	29 org/apache/commons/math3/stat/correlation/StorelessBivariateCovariance.meanX:D (0, 0)
	31 dload (0, 0)
	32 #5 (0, 0)
	33 aload_0 (0, 0)
	34 getfield (0, 0)
	35 org/apache/commons/math3/stat/correlation/StorelessBivariateCovariance.n:D (0, 0)
	37 ddiv (0, 0)
	38 dadd (0, 0)
	39 putfield (0, 0)
	40 org/apache/commons/math3/stat/correlation/StorelessBivariateCovariance.meanX:D (0, 0)
	42 aload_0 (0, 0)
	43 dup (0, 0)
	44 getfield (0, 0)
	45 org/apache/commons/math3/stat/correlation/StorelessBivariateCovariance.meanY:D (0, 0)
	47 dload (0, 0)
	48 #7 (0, 0)
	49 aload_0 (0, 0)
	50 getfield (0, 0)
	51 org/apache/commons/math3/stat/correlation/StorelessBivariateCovariance.n:D (0, 0)
	53 ddiv (0, 0)
	54 dadd (0, 0)
	55 putfield (0, 0)
	56 org/apache/commons/math3/stat/correlation/StorelessBivariateCovariance.meanY:D (0, 0)
	58 aload_0 (0, 0)
	59 dup (0, 0)
	60 getfield (0, 0)
	61 org/apache/commons/math3/stat/correlation/StorelessBivariateCovariance.covarianceNumerator:D (0, 0)
	63 aload_0 (0, 0)
	64 getfield (0, 0)
	65 org/apache/commons/math3/stat/correlation/StorelessBivariateCovariance.n:D (0, 0)
	67 dconst_1 (0, 0)
	68 dsub (0, 0)
	69 aload_0 (0, 0)
	70 getfield (0, 0)
	71 org/apache/commons/math3/stat/correlation/StorelessBivariateCovariance.n:D (0, 0)
	73 ddiv (0, 0)
	74 dload (0, 0)
	75 #5 (0, 0)
	76 dmul (0, 0)
	77 dload (0, 0)
	78 #7 (0, 0)
	79 dmul (0, 0)
	80 dadd (0, 0)
	81 putfield (0, 0)
	82 org/apache/commons/math3/stat/correlation/StorelessBivariateCovariance.covarianceNumerator:D (0, 0)
	84 return (0, 0)

Method: append
	0 aload_0 (0, 0)
	1 getfield (0, 0)
	2 org/apache/commons/math3/stat/correlation/StorelessBivariateCovariance.n:D (0, 0)
	4 dstore_2 (0, 0)
	5 aload_0 (0, 0)
	6 dup (0, 0)
	7 getfield (0, 0)
	8 org/apache/commons/math3/stat/correlation/StorelessBivariateCovariance.n:D (0, 0)
	10 aload_1 (0, 0)
	11 getfield (0, 0)
	12 org/apache/commons/math3/stat/correlation/StorelessBivariateCovariance.n:D (0, 0)
	14 dadd (0, 0)
	15 putfield (0, 0)
	16 org/apache/commons/math3/stat/correlation/StorelessBivariateCovariance.n:D (0, 0)
	18 aload_1 (0, 0)
	19 getfield (0, 0)
	20 org/apache/commons/math3/stat/correlation/StorelessBivariateCovariance.meanX:D (0, 0)
	22 aload_0 (0, 0)
	23 getfield (0, 0)
	24 org/apache/commons/math3/stat/correlation/StorelessBivariateCovariance.meanX:D (0, 0)
	26 dsub (0, 0)
	27 dstore (0, 0)
	28 #4 (0, 0)
	29 aload_1 (0, 0)
	30 getfield (0, 0)
	31 org/apache/commons/math3/stat/correlation/StorelessBivariateCovariance.meanY:D (0, 0)
	33 aload_0 (0, 0)
	34 getfield (0, 0)
	35 org/apache/commons/math3/stat/correlation/StorelessBivariateCovariance.meanY:D (0, 0)
	37 dsub (0, 0)
	38 dstore (0, 0)
	39 #6 (0, 0)
	40 aload_0 (0, 0)
	41 dup (0, 0)
	42 getfield (0, 0)
	43 org/apache/commons/math3/stat/correlation/StorelessBivariateCovariance.meanX:D (0, 0)
	45 dload (0, 0)
	46 #4 (0, 0)
	47 aload_1 (0, 0)
	48 getfield (0, 0)
	49 org/apache/commons/math3/stat/correlation/StorelessBivariateCovariance.n:D (0, 0)
	51 dmul (0, 0)
	52 aload_0 (0, 0)
	53 getfield (0, 0)
	54 org/apache/commons/math3/stat/correlation/StorelessBivariateCovariance.n:D (0, 0)
	56 ddiv (0, 0)
	57 dadd (0, 0)
	58 putfield (0, 0)
	59 org/apache/commons/math3/stat/correlation/StorelessBivariateCovariance.meanX:D (0, 0)
	61 aload_0 (0, 0)
	62 dup (0, 0)
	63 getfield (0, 0)
	64 org/apache/commons/math3/stat/correlation/StorelessBivariateCovariance.meanY:D (0, 0)
	66 dload (0, 0)
	67 #6 (0, 0)
	68 aload_1 (0, 0)
	69 getfield (0, 0)
	70 org/apache/commons/math3/stat/correlation/StorelessBivariateCovariance.n:D (0, 0)
	72 dmul (0, 0)
	73 aload_0 (0, 0)
	74 getfield (0, 0)
	75 org/apache/commons/math3/stat/correlation/StorelessBivariateCovariance.n:D (0, 0)
	77 ddiv (0, 0)
	78 dadd (0, 0)
	79 putfield (0, 0)
	80 org/apache/commons/math3/stat/correlation/StorelessBivariateCovariance.meanY:D (0, 0)
	82 aload_0 (0, 0)
	83 dup (0, 0)
	84 getfield (0, 0)
	85 org/apache/commons/math3/stat/correlation/StorelessBivariateCovariance.covarianceNumerator:D (0, 0)
	87 aload_1 (0, 0)
	88 getfield (0, 0)
	89 org/apache/commons/math3/stat/correlation/StorelessBivariateCovariance.covarianceNumerator:D (0, 0)
	91 dload_2 (0, 0)
	92 aload_1 (0, 0)
	93 getfield (0, 0)
	94 org/apache/commons/math3/stat/correlation/StorelessBivariateCovariance.n:D (0, 0)
	96 dmul (0, 0)
	97 aload_0 (0, 0)
	98 getfield (0, 0)
	99 org/apache/commons/math3/stat/correlation/StorelessBivariateCovariance.n:D (0, 0)
	101 ddiv (0, 0)
	102 dload (0, 0)
	103 #4 (0, 0)
	104 dmul (0, 0)
	105 dload (0, 0)
	106 #6 (0, 0)
	107 dmul (0, 0)
	108 dadd (0, 0)
	109 dadd (0, 0)
	110 putfield (0, 0)
	111 org/apache/commons/math3/stat/correlation/StorelessBivariateCovariance.covarianceNumerator:D (0, 0)
	113 return (0, 0)

Method: getN
	0 aload_0 (0, 0)
	1 getfield (0, 0)
	2 org/apache/commons/math3/stat/correlation/StorelessBivariateCovariance.n:D (0, 0)
	4 dreturn (0, 0)

Method: getResult
	0 aload_0 (1, 1)
	1 getfield (1, 1)
	2 org/apache/commons/math3/stat/correlation/StorelessBivariateCovariance.n:D (1, 1)
	4 ldc2_w (1, 1)
	5 2.0 (1, 1)
	7 dcmpg (1, 1)
	8 ifge (1, 1)
	9 26 (1, 1)
	11 new (1, 1)
	12 org/apache/commons/math3/exception/NumberIsTooSmallException (1, 1)
	14 dup (1, 1)
	15 getstatic (1, 1)
	16 org/apache/commons/math3/exception/util/LocalizedFormats.INSUFFICIENT_DIMENSION:Lorg/apache/commons/math3/exception/util/LocalizedFormats; (1, 1)
	18 aload_0 (1, 1)
	19 getfield (1, 1)
	20 org/apache/commons/math3/stat/correlation/StorelessBivariateCovariance.n:D (1, 1)
	22 invokestatic (1, 1)
	23 java/lang/Double.valueOf:(D)Ljava/lang/Double; (1, 1)
	25 iconst_2 (1, 1)
	26 invokestatic (1, 1)
	27 java/lang/Integer.valueOf:(I)Ljava/lang/Integer; (1, 1)
	29 iconst_1 (1, 1)
	30 invokespecial (1, 1)
	31 org/apache/commons/math3/exception/NumberIsTooSmallException.<init>:(Lorg/apache/commons/math3/exception/util/Localizable;Ljava/lang/Number;Ljava/lang/Number;Z)V (1, 1)
	33 athrow (1, 1)
	34 aload_0 (1, 1)
	35 getfield (1, 1)
	36 org/apache/commons/math3/stat/correlation/StorelessBivariateCovariance.biasCorrected:Z (1, 1)
	38 ifeq (1, 1)
	39 15 (1, 1)
	41 aload_0 (1, 1)
	42 getfield (1, 1)
	43 org/apache/commons/math3/stat/correlation/StorelessBivariateCovariance.covarianceNumerator:D (1, 1)
	45 aload_0 (1, 1)
	46 getfield (1, 1)
	47 org/apache/commons/math3/stat/correlation/StorelessBivariateCovariance.n:D (1, 1)
	49 dconst_1 (1, 1)
	50 dsub (1, 1)
	51 ddiv (1, 1)
	52 dreturn (1, 1)
	53 aload_0 (2, 2)
	54 getfield (2, 2)
	55 org/apache/commons/math3/stat/correlation/StorelessBivariateCovariance.covarianceNumerator:D (2, 2)
	57 aload_0 (2, 2)
	58 getfield (2, 2)
	59 org/apache/commons/math3/stat/correlation/StorelessBivariateCovariance.n:D (2, 2)
	61 ddiv (2, 2)
	62 dreturn (1, 2)

