Method: <init>
	0 aload_0 (0, 0)
	1 invokespecial (0, 0)
	2 org/apache/commons/math3/stat/correlation/Covariance.<init>:()V (0, 0)
	4 aload_0 (0, 0)
	5 iload_1 (0, 0)
	6 putfield (0, 0)
	7 org/apache/commons/math3/stat/correlation/StorelessCovariance.dimension:I (0, 0)
	9 aload_0 (0, 0)
	10 aload_0 (0, 0)
	11 getfield (0, 0)
	12 org/apache/commons/math3/stat/correlation/StorelessCovariance.dimension:I (0, 0)
	14 aload_0 (0, 0)
	15 getfield (0, 0)
	16 org/apache/commons/math3/stat/correlation/StorelessCovariance.dimension:I (0, 0)
	18 iconst_1 (0, 0)
	19 iadd (0, 0)
	20 imul (0, 0)
	21 iconst_2 (0, 0)
	22 idiv (0, 0)
	23 anewarray (0, 0)
	24 org/apache/commons/math3/stat/correlation/StorelessBivariateCovariance (0, 0)
	26 putfield (0, 0)
	27 org/apache/commons/math3/stat/correlation/StorelessCovariance.covMatrix:[Lorg/apache/commons/math3/stat/correlation/StorelessBivariateCovariance; (0, 0)
	29 aload_0 (0, 0)
	30 iload_2 (0, 0)
	31 invokespecial (0, 0)
	32 org/apache/commons/math3/stat/correlation/StorelessCovariance.initializeMatrix:(Z)V (0, 0)
	34 return (0, 0)

Method: initializeMatrix
	0 iconst_0 (1, 4)
	1 istore_2 (1, 4)
	2 iload_2 (1, 4)
	3 aload_0 (1, 4)
	4 getfield (1, 4)
	5 org/apache/commons/math3/stat/correlation/StorelessCovariance.dimension:I (1, 4)
	7 if_icmpge (1, 4)
	8 39 (1, 4)
	10 iconst_0 (2, 4)
	11 istore_3 (2, 4)
	12 iload_3 (2, 4)
	13 aload_0 (2, 4)
	14 getfield (2, 4)
	15 org/apache/commons/math3/stat/correlation/StorelessCovariance.dimension:I (2, 4)
	17 if_icmpge (2, 4)
	18 23 (2, 4)
	20 aload_0 (2, 4)
	21 iload_2 (2, 4)
	22 iload_3 (2, 4)
	23 new (2, 4)
	24 org/apache/commons/math3/stat/correlation/StorelessBivariateCovariance (2, 4)
	26 dup (2, 4)
	27 iload_1 (2, 4)
	28 invokespecial (2, 4)
	29 org/apache/commons/math3/stat/correlation/StorelessBivariateCovariance.<init>:(Z)V (2, 4)
	31 invokespecial (2, 4)
	32 org/apache/commons/math3/stat/correlation/StorelessCovariance.setElement:(IILorg/apache/commons/math3/stat/correlation/StorelessBivariateCovariance;)V (2, 4)
	34 iinc (2, 4)
	35 #3 (2, 4)
	36 -89 (2, 4)
	37 goto (2, 4)
	38 -25 (2, 4)
	40 iinc (2, 4)
	41 #2 (2, 4)
	42 -89 (2, 4)
	43 goto (2, 4)
	44 -41 (2, 4)
	46 return (0, 0)

Method: indexOf
	0 iload_2 (0, 0)
	1 iload_1 (0, 0)
	2 if_icmpge (0, 0)
	3 15 (0, 0)
	5 iload_1 (0, 0)
	6 iload_1 (0, 0)
	7 iconst_1 (0, 0)
	8 iadd (0, 0)
	9 imul (0, 0)
	10 iconst_2 (0, 0)
	11 idiv (0, 0)
	12 iload_2 (0, 0)
	13 iadd (0, 0)
	14 goto (0, 0)
	15 12 (0, 0)
	17 iload_2 (0, 0)
	18 iload_2 (0, 0)
	19 iconst_1 (0, 0)
	20 iadd (0, 0)
	21 imul (0, 0)
	22 iconst_2 (0, 0)
	23 idiv (0, 0)
	24 iload_1 (0, 0)
	25 iadd (0, 0)
	26 ireturn (0, 0)

Method: getElement
	0 aload_0 (0, 0)
	1 getfield (0, 0)
	2 org/apache/commons/math3/stat/correlation/StorelessCovariance.covMatrix:[Lorg/apache/commons/math3/stat/correlation/StorelessBivariateCovariance; (0, 0)
	4 aload_0 (0, 0)
	5 iload_1 (0, 0)
	6 iload_2 (0, 0)
	7 invokespecial (0, 0)
	8 org/apache/commons/math3/stat/correlation/StorelessCovariance.indexOf:(II)I (0, 0)
	10 aaload (0, 0)
	11 areturn (0, 0)

Method: setElement
	0 aload_0 (0, 0)
	1 getfield (0, 0)
	2 org/apache/commons/math3/stat/correlation/StorelessCovariance.covMatrix:[Lorg/apache/commons/math3/stat/correlation/StorelessBivariateCovariance; (0, 0)
	4 aload_0 (0, 0)
	5 iload_1 (0, 0)
	6 iload_2 (0, 0)
	7 invokespecial (0, 0)
	8 org/apache/commons/math3/stat/correlation/StorelessCovariance.indexOf:(II)I (0, 0)
	10 aload_3 (0, 0)
	11 aastore (0, 0)
	12 return (0, 0)

Method: getCovariance
	0 aload_0 (0, 0)
	1 iload_1 (0, 0)
	2 iload_2 (0, 0)
	3 invokespecial (0, 0)
	4 org/apache/commons/math3/stat/correlation/StorelessCovariance.getElement:(II)Lorg/apache/commons/math3/stat/correlation/StorelessBivariateCovariance; (0, 0)
	6 invokevirtual (0, 0)
	7 org/apache/commons/math3/stat/correlation/StorelessBivariateCovariance.getResult:()D (0, 0)
	9 dreturn (0, 0)

Method: increment
	0 aload_1 (0, 0)
	1 arraylength (0, 0)
	2 istore_2 (0, 0)
	3 iload_2 (1, 1)
	4 aload_0 (1, 1)
	5 getfield (1, 1)
	6 org/apache/commons/math3/stat/correlation/StorelessCovariance.dimension:I (1, 1)
	8 if_icmpeq (1, 1)
	9 16 (1, 1)
	11 new (1, 1)
	12 org/apache/commons/math3/exception/DimensionMismatchException (1, 1)
	14 dup (1, 1)
	15 iload_2 (1, 1)
	16 aload_0 (1, 1)
	17 getfield (1, 1)
	18 org/apache/commons/math3/stat/correlation/StorelessCovariance.dimension:I (1, 1)
	20 invokespecial (1, 1)
	21 org/apache/commons/math3/exception/DimensionMismatchException.<init>:(II)V (1, 1)
	23 athrow (1, 1)
	24 iconst_0 (1, 4)
	25 istore_3 (1, 4)
	26 iload_3 (1, 4)
	27 iload_2 (1, 4)
	28 if_icmpge (1, 4)
	29 41 (1, 4)
	31 iload_3 (2, 4)
	32 istore (2, 4)
	33 #4 (2, 4)
	34 iload (2, 4)
	35 #4 (2, 4)
	36 iload_2 (2, 4)
	37 if_icmpge (2, 4)
	38 26 (2, 4)
	40 aload_0 (2, 4)
	41 iload_3 (2, 4)
	42 iload (2, 4)
	43 #4 (2, 4)
	44 invokespecial (2, 4)
	45 org/apache/commons/math3/stat/correlation/StorelessCovariance.getElement:(II)Lorg/apache/commons/math3/stat/correlation/StorelessBivariateCovariance; (2, 4)
	47 aload_1 (2, 4)
	48 iload_3 (2, 4)
	49 daload (2, 4)
	50 aload_1 (2, 4)
	51 iload (2, 4)
	52 #4 (2, 4)
	53 daload (2, 4)
	54 invokevirtual (2, 4)
	55 org/apache/commons/math3/stat/correlation/StorelessBivariateCovariance.increment:(DD)V (2, 4)
	57 iinc (2, 4)
	58 #4 (2, 4)
	59 -89 (2, 4)
	60 goto (2, 4)
	61 -26 (2, 4)
	63 iinc (2, 4)
	64 #3 (2, 4)
	65 -89 (2, 4)
	66 goto (2, 4)
	67 -40 (2, 4)
	69 return (0, 0)

Method: append
	0 aload_1 (1, 1)
	1 getfield (1, 1)
	2 org/apache/commons/math3/stat/correlation/StorelessCovariance.dimension:I (1, 1)
	4 aload_0 (1, 1)
	5 getfield (1, 1)
	6 org/apache/commons/math3/stat/correlation/StorelessCovariance.dimension:I (1, 1)
	8 if_icmpeq (1, 1)
	9 19 (1, 1)
	11 new (1, 1)
	12 org/apache/commons/math3/exception/DimensionMismatchException (1, 1)
	14 dup (1, 1)
	15 aload_1 (1, 1)
	16 getfield (1, 1)
	17 org/apache/commons/math3/stat/correlation/StorelessCovariance.dimension:I (1, 1)
	19 aload_0 (1, 1)
	20 getfield (1, 1)
	21 org/apache/commons/math3/stat/correlation/StorelessCovariance.dimension:I (1, 1)
	23 invokespecial (1, 1)
	24 org/apache/commons/math3/exception/DimensionMismatchException.<init>:(II)V (1, 1)
	26 athrow (1, 1)
	27 iconst_0 (1, 4)
	28 istore_2 (1, 4)
	29 iload_2 (1, 4)
	30 aload_0 (1, 4)
	31 getfield (1, 4)
	32 org/apache/commons/math3/stat/correlation/StorelessCovariance.dimension:I (1, 4)
	34 if_icmpge (1, 4)
	35 40 (1, 4)
	37 iload_2 (2, 4)
	38 istore_3 (2, 4)
	39 iload_3 (2, 4)
	40 aload_0 (2, 4)
	41 getfield (2, 4)
	42 org/apache/commons/math3/stat/correlation/StorelessCovariance.dimension:I (2, 4)
	44 if_icmpge (2, 4)
	45 24 (2, 4)
	47 aload_0 (2, 4)
	48 iload_2 (2, 4)
	49 iload_3 (2, 4)
	50 invokespecial (2, 4)
	51 org/apache/commons/math3/stat/correlation/StorelessCovariance.getElement:(II)Lorg/apache/commons/math3/stat/correlation/StorelessBivariateCovariance; (2, 4)
	53 aload_1 (2, 4)
	54 iload_2 (2, 4)
	55 iload_3 (2, 4)
	56 invokespecial (2, 4)
	57 org/apache/commons/math3/stat/correlation/StorelessCovariance.getElement:(II)Lorg/apache/commons/math3/stat/correlation/StorelessBivariateCovariance; (2, 4)
	59 invokevirtual (2, 4)
	60 org/apache/commons/math3/stat/correlation/StorelessBivariateCovariance.append:(Lorg/apache/commons/math3/stat/correlation/StorelessBivariateCovariance;)V (2, 4)
	62 iinc (2, 4)
	63 #3 (2, 4)
	64 -89 (2, 4)
	65 goto (2, 4)
	66 -26 (2, 4)
	68 iinc (2, 4)
	69 #2 (2, 4)
	70 -89 (2, 4)
	71 goto (2, 4)
	72 -42 (2, 4)
	74 return (0, 0)

Method: getCovarianceMatrix
	0 aload_0 (0, 0)
	1 invokevirtual (0, 0)
	2 org/apache/commons/math3/stat/correlation/StorelessCovariance.getData:()[[D (0, 0)
	4 invokestatic (0, 0)
	5 org/apache/commons/math3/linear/MatrixUtils.createRealMatrix:([[D)Lorg/apache/commons/math3/linear/RealMatrix; (0, 0)
	7 areturn (0, 0)

Method: getData
	0 aload_0 (0, 0)
	1 getfield (0, 0)
	2 org/apache/commons/math3/stat/correlation/StorelessCovariance.dimension:I (0, 0)
	4 aload_0 (0, 0)
	5 getfield (0, 0)
	6 org/apache/commons/math3/stat/correlation/StorelessCovariance.dimension:I (0, 0)
	8 multianewarray (0, 0)
	9 [[D (0, 0)
	11 76 (0, 0)
	12 astore_1 (0, 0)
	13 iconst_0 (1, 4)
	14 istore_2 (1, 4)
	15 iload_2 (1, 4)
	16 aload_0 (1, 4)
	17 getfield (1, 4)
	18 org/apache/commons/math3/stat/correlation/StorelessCovariance.dimension:I (1, 4)
	20 if_icmpge (1, 4)
	21 39 (1, 4)
	23 iconst_0 (2, 4)
	24 istore_3 (2, 4)
	25 iload_3 (2, 4)
	26 aload_0 (2, 4)
	27 getfield (2, 4)
	28 org/apache/commons/math3/stat/correlation/StorelessCovariance.dimension:I (2, 4)
	30 if_icmpge (2, 4)
	31 23 (2, 4)
	33 aload_1 (2, 4)
	34 iload_2 (2, 4)
	35 aaload (2, 4)
	36 iload_3 (2, 4)
	37 aload_0 (2, 4)
	38 iload_2 (2, 4)
	39 iload_3 (2, 4)
	40 invokespecial (2, 4)
	41 org/apache/commons/math3/stat/correlation/StorelessCovariance.getElement:(II)Lorg/apache/commons/math3/stat/correlation/StorelessBivariateCovariance; (2, 4)
	43 invokevirtual (2, 4)
	44 org/apache/commons/math3/stat/correlation/StorelessBivariateCovariance.getResult:()D (2, 4)
	46 dastore (2, 4)
	47 iinc (2, 4)
	48 #3 (2, 4)
	49 -89 (2, 4)
	50 goto (2, 4)
	51 -25 (2, 4)
	53 iinc (2, 4)
	54 #2 (2, 4)
	55 -89 (2, 4)
	56 goto (2, 4)
	57 -41 (2, 4)
	59 aload_1 (1, 4)
	60 areturn (1, 4)

Method: getN
	0 new (0, 0)
	1 org/apache/commons/math3/exception/MathUnsupportedOperationException (0, 0)
	3 dup (0, 0)
	4 invokespecial (0, 0)
	5 org/apache/commons/math3/exception/MathUnsupportedOperationException.<init>:()V (0, 0)
	7 athrow (0, 0)

