Method: <init>
	0 aload_0 (0, 0)
	1 invokespecial (0, 0)
	2 java/lang/Object.<init>:()V (0, 0)
	4 aload_1 (1, 1)
	5 arraylength (1, 1)
	6 ifgt (1, 1)
	7 19 (1, 1)
	9 new (1, 1)
	10 org/apache/commons/math3/exception/NotStrictlyPositiveException (1, 1)
	12 dup (1, 1)
	13 getstatic (1, 1)
	14 org/apache/commons/math3/exception/util/LocalizedFormats.SIMPLEX_NEED_ONE_POINT:Lorg/apache/commons/math3/exception/util/LocalizedFormats; (1, 1)
	16 aload_1 (1, 1)
	17 arraylength (1, 1)
	18 invokestatic (1, 1)
	19 java/lang/Integer.valueOf:(I)Ljava/lang/Integer; (1, 1)
	21 invokespecial (1, 1)
	22 org/apache/commons/math3/exception/NotStrictlyPositiveException.<init>:(Lorg/apache/commons/math3/exception/util/Localizable;Ljava/lang/Number;)V (1, 1)
	24 athrow (1, 1)
	25 aload_0 (0, 0)
	26 aload_1 (0, 0)
	27 arraylength (0, 0)
	28 iconst_1 (0, 0)
	29 isub (0, 0)
	30 putfield (0, 0)
	31 org/apache/commons/math3/optimization/direct/AbstractSimplex.dimension:I (0, 0)
	33 aload_0 (0, 0)
	34 aload_0 (0, 0)
	35 getfield (0, 0)
	36 org/apache/commons/math3/optimization/direct/AbstractSimplex.dimension:I (0, 0)
	38 aload_0 (0, 0)
	39 getfield (0, 0)
	40 org/apache/commons/math3/optimization/direct/AbstractSimplex.dimension:I (0, 0)
	42 multianewarray (0, 0)
	43 [[D (0, 0)
	45 -75 (0, 0)
	46 putfield (0, 0)
	47 org/apache/commons/math3/optimization/direct/AbstractSimplex.startConfiguration:[[D (0, 0)
	49 aload_1 (0, 0)
	50 iconst_0 (0, 0)
	51 aaload (0, 0)
	52 astore_2 (0, 0)
	53 iconst_0 (1, 4)
	54 istore_3 (1, 4)
	55 iload_3 (1, 4)
	56 aload_1 (1, 4)
	57 arraylength (1, 4)
	58 if_icmpge (1, 4)
	59 183 (1, 4)
	61 aload_1 (1, 4)
	62 iload_3 (1, 4)
	63 aaload (1, 4)
	64 astore (1, 4)
	65 #4 (1, 4)
	66 aload (2, 1)
	67 #4 (2, 1)
	68 arraylength (2, 1)
	69 aload_0 (2, 1)
	70 getfield (2, 1)
	71 org/apache/commons/math3/optimization/direct/AbstractSimplex.dimension:I (2, 1)
	73 if_icmpeq (2, 1)
	74 18 (2, 1)
	76 new (2, 1)
	77 org/apache/commons/math3/exception/DimensionMismatchException (2, 1)
	79 dup (2, 1)
	80 aload (2, 1)
	81 #4 (2, 1)
	82 arraylength (2, 1)
	83 aload_0 (2, 1)
	84 getfield (2, 1)
	85 org/apache/commons/math3/optimization/direct/AbstractSimplex.dimension:I (2, 1)
	87 invokespecial (2, 1)
	88 org/apache/commons/math3/exception/DimensionMismatchException.<init>:(II)V (2, 1)
	90 athrow (2, 1)
	91 iconst_0 (2, 4)
	92 istore (2, 4)
	93 #5 (2, 4)
	94 iload (2, 4)
	95 #5 (2, 4)
	96 iload_3 (2, 4)
	97 if_icmpge (2, 4)
	98 91 (2, 4)
	100 aload_1 (2, 4)
	101 iload (2, 4)
	102 #5 (2, 4)
	103 aaload (2, 4)
	104 astore (2, 4)
	105 #6 (2, 4)
	106 iconst_1 (2, 4)
	107 istore (2, 4)
	108 #7 (2, 4)
	109 iconst_0 (3, 4)
	110 istore (3, 4)
	111 #8 (3, 4)
	112 iload (3, 4)
	113 #8 (3, 4)
	114 aload_0 (3, 4)
	115 getfield (3, 4)
	116 org/apache/commons/math3/optimization/direct/AbstractSimplex.dimension:I (3, 4)
	118 if_icmpge (3, 4)
	119 29 (3, 4)
	121 aload (4, 1)
	122 #4 (4, 1)
	123 iload (4, 1)
	124 #8 (4, 1)
	125 daload (4, 1)
	126 aload (4, 1)
	127 #6 (4, 1)
	128 iload (4, 1)
	129 #8 (4, 1)
	130 daload (4, 1)
	131 dcmpl (4, 1)
	132 ifeq (4, 1)
	133 9 (4, 1)
	135 iconst_0 (4, 1)
	136 istore (4, 1)
	137 #7 (4, 1)
	138 goto (4, 1)
	139 9 (4, 1)
	141 iinc (4, 1)
	142 #8 (4, 1)
	143 -89 (4, 1)
	144 goto (4, 1)
	145 -32 (4, 1)
	147 iload (4, 1)
	148 #7 (4, 1)
	149 ifeq (4, 1)
	150 33 (4, 1)
	152 new (4, 1)
	153 org/apache/commons/math3/exception/MathIllegalArgumentException (4, 1)
	155 dup (4, 1)
	156 getstatic (4, 1)
	157 org/apache/commons/math3/exception/util/LocalizedFormats.EQUAL_VERTICES_IN_SIMPLEX:Lorg/apache/commons/math3/exception/util/LocalizedFormats; (4, 1)
	159 iconst_2 (4, 1)
	160 anewarray (4, 1)
	161 java/lang/Object (4, 1)
	163 dup (4, 1)
	164 iconst_0 (4, 1)
	165 iload_3 (4, 1)
	166 invokestatic (4, 1)
	167 java/lang/Integer.valueOf:(I)Ljava/lang/Integer; (4, 1)
	169 aastore (4, 1)
	170 dup (4, 1)
	171 iconst_1 (4, 1)
	172 iload (4, 1)
	173 #5 (4, 1)
	174 invokestatic (4, 1)
	175 java/lang/Integer.valueOf:(I)Ljava/lang/Integer; (4, 1)
	177 aastore (4, 1)
	178 invokespecial (4, 1)
	179 org/apache/commons/math3/exception/MathIllegalArgumentException.<init>:(Lorg/apache/commons/math3/exception/util/Localizable;[Ljava/lang/Object;)V (4, 1)
	181 athrow (4, 1)
	182 iinc (4, 1)
	183 #5 (4, 1)
	184 -89 (4, 1)
	185 goto (4, 1)
	186 -91 (4, 1)
	188 iload_3 (4, 1)
	189 ifle (4, 1)
	190 46 (4, 1)
	192 aload_0 (4, 1)
	193 getfield (4, 1)
	194 org/apache/commons/math3/optimization/direct/AbstractSimplex.startConfiguration:[[D (4, 1)
	196 iload_3 (4, 1)
	197 iconst_1 (4, 1)
	198 isub (4, 1)
	199 aaload (4, 1)
	200 astore (4, 1)
	201 #5 (4, 1)
	202 iconst_0 (5, 4)
	203 istore (5, 4)
	204 #6 (5, 4)
	205 iload (5, 4)
	206 #6 (5, 4)
	207 aload_0 (5, 4)
	208 getfield (5, 4)
	209 org/apache/commons/math3/optimization/direct/AbstractSimplex.dimension:I (5, 4)
	211 if_icmpge (5, 4)
	212 24 (5, 4)
	214 aload (5, 4)
	215 #5 (5, 4)
	216 iload (5, 4)
	217 #6 (5, 4)
	218 aload (5, 4)
	219 #4 (5, 4)
	220 iload (5, 4)
	221 #6 (5, 4)
	222 daload (5, 4)
	223 aload_2 (5, 4)
	224 iload (5, 4)
	225 #6 (5, 4)
	226 daload (5, 4)
	227 dsub (5, 4)
	228 dastore (5, 4)
	229 iinc (5, 4)
	230 #6 (5, 4)
	231 -89 (5, 4)
	232 goto (5, 4)
	233 -27 (5, 4)
	235 iinc (5, 4)
	236 #3 (5, 4)
	237 -89 (5, 4)
	238 goto (5, 4)
	239 -183 (5, 4)
	241 return (4, 4)

Method: getDimension
	0 aload_0 (0, 0)
	1 getfield (0, 0)
	2 org/apache/commons/math3/optimization/direct/AbstractSimplex.dimension:I (0, 0)
	4 ireturn (0, 0)

Method: getSize
	0 aload_0 (0, 0)
	1 getfield (0, 0)
	2 org/apache/commons/math3/optimization/direct/AbstractSimplex.simplex:[Lorg/apache/commons/math3/optimization/PointValuePair; (0, 0)
	4 arraylength (0, 0)
	5 ireturn (0, 0)

Method: build
	0 aload_0 (1, 1)
	1 getfield (1, 1)
	2 org/apache/commons/math3/optimization/direct/AbstractSimplex.dimension:I (1, 1)
	4 aload_1 (1, 1)
	5 arraylength (1, 1)
	6 if_icmpeq (1, 1)
	7 17 (1, 1)
	9 new (1, 1)
	10 org/apache/commons/math3/exception/DimensionMismatchException (1, 1)
	12 dup (1, 1)
	13 aload_0 (1, 1)
	14 getfield (1, 1)
	15 org/apache/commons/math3/optimization/direct/AbstractSimplex.dimension:I (1, 1)
	17 aload_1 (1, 1)
	18 arraylength (1, 1)
	19 invokespecial (1, 1)
	20 org/apache/commons/math3/exception/DimensionMismatchException.<init>:(II)V (1, 1)
	22 athrow (1, 1)
	23 aload_0 (0, 0)
	24 aload_0 (0, 0)
	25 getfield (0, 0)
	26 org/apache/commons/math3/optimization/direct/AbstractSimplex.dimension:I (0, 0)
	28 iconst_1 (0, 0)
	29 iadd (0, 0)
	30 anewarray (0, 0)
	31 org/apache/commons/math3/optimization/PointValuePair (0, 0)
	33 putfield (0, 0)
	34 org/apache/commons/math3/optimization/direct/AbstractSimplex.simplex:[Lorg/apache/commons/math3/optimization/PointValuePair; (0, 0)
	36 aload_0 (0, 0)
	37 getfield (0, 0)
	38 org/apache/commons/math3/optimization/direct/AbstractSimplex.simplex:[Lorg/apache/commons/math3/optimization/PointValuePair; (0, 0)
	40 iconst_0 (0, 0)
	41 new (0, 0)
	42 org/apache/commons/math3/optimization/PointValuePair (0, 0)
	44 dup (0, 0)
	45 aload_1 (0, 0)
	46 ldc2_w (0, 0)
	47 nan (0, 0)
	49 invokespecial (0, 0)
	50 org/apache/commons/math3/optimization/PointValuePair.<init>:([DD)V (0, 0)
	52 aastore (0, 0)
	53 iconst_0 (1, 4)
	54 istore_2 (1, 4)
	55 iload_2 (1, 4)
	56 aload_0 (1, 4)
	57 getfield (1, 4)
	58 org/apache/commons/math3/optimization/direct/AbstractSimplex.dimension:I (1, 4)
	60 if_icmpge (1, 4)
	61 76 (1, 4)
	63 aload_0 (1, 4)
	64 getfield (1, 4)
	65 org/apache/commons/math3/optimization/direct/AbstractSimplex.startConfiguration:[[D (1, 4)
	67 iload_2 (1, 4)
	68 aaload (1, 4)
	69 astore_3 (1, 4)
	70 aload_0 (1, 4)
	71 getfield (1, 4)
	72 org/apache/commons/math3/optimization/direct/AbstractSimplex.dimension:I (1, 4)
	74 newarray (1, 4)
	75 7 (1, 4)
	76 astore (1, 4)
	77 #4 (1, 4)
	78 iconst_0 (2, 4)
	79 istore (2, 4)
	80 #5 (2, 4)
	81 iload (2, 4)
	82 #5 (2, 4)
	83 aload_0 (2, 4)
	84 getfield (2, 4)
	85 org/apache/commons/math3/optimization/direct/AbstractSimplex.dimension:I (2, 4)
	87 if_icmpge (2, 4)
	88 23 (2, 4)
	90 aload (2, 4)
	91 #4 (2, 4)
	92 iload (2, 4)
	93 #5 (2, 4)
	94 aload_1 (2, 4)
	95 iload (2, 4)
	96 #5 (2, 4)
	97 daload (2, 4)
	98 aload_3 (2, 4)
	99 iload (2, 4)
	100 #5 (2, 4)
	101 daload (2, 4)
	102 dadd (2, 4)
	103 dastore (2, 4)
	104 iinc (2, 4)
	105 #5 (2, 4)
	106 -89 (2, 4)
	107 goto (2, 4)
	108 -26 (2, 4)
	110 aload_0 (1, 4)
	111 getfield (1, 4)
	112 org/apache/commons/math3/optimization/direct/AbstractSimplex.simplex:[Lorg/apache/commons/math3/optimization/PointValuePair; (1, 4)
	114 iload_2 (1, 4)
	115 iconst_1 (1, 4)
	116 iadd (1, 4)
	117 new (1, 4)
	118 org/apache/commons/math3/optimization/PointValuePair (1, 4)
	120 dup (1, 4)
	121 aload (1, 4)
	122 #4 (1, 4)
	123 ldc2_w (1, 4)
	124 nan (1, 4)
	126 invokespecial (1, 4)
	127 org/apache/commons/math3/optimization/PointValuePair.<init>:([DD)V (1, 4)
	129 aastore (1, 4)
	130 iinc (1, 4)
	131 #2 (1, 4)
	132 -89 (1, 4)
	133 goto (1, 4)
	134 -78 (1, 4)
	136 return (0, 0)

Method: evaluate
	0 iconst_0 (1, 4)
	1 istore_3 (1, 4)
	2 iload_3 (1, 4)
	3 aload_0 (1, 4)
	4 getfield (1, 4)
	5 org/apache/commons/math3/optimization/direct/AbstractSimplex.simplex:[Lorg/apache/commons/math3/optimization/PointValuePair; (1, 4)
	7 arraylength (1, 4)
	8 if_icmpge (1, 4)
	9 65 (1, 4)
	11 aload_0 (1, 4)
	12 getfield (1, 4)
	13 org/apache/commons/math3/optimization/direct/AbstractSimplex.simplex:[Lorg/apache/commons/math3/optimization/PointValuePair; (1, 4)
	15 iload_3 (1, 4)
	16 aaload (1, 4)
	17 astore (1, 4)
	18 #4 (1, 4)
	19 aload (1, 4)
	20 #4 (1, 4)
	21 invokevirtual (1, 4)
	22 org/apache/commons/math3/optimization/PointValuePair.getPointRef:()[D (1, 4)
	24 astore (1, 4)
	25 #5 (1, 4)
	26 aload (2, 1)
	27 #4 (2, 1)
	28 invokevirtual (2, 1)
	29 org/apache/commons/math3/optimization/PointValuePair.getValue:()Ljava/lang/Object; (2, 1)
	31 checkcast (2, 1)
	32 java/lang/Double (2, 1)
	34 invokevirtual (2, 1)
	35 java/lang/Double.doubleValue:()D (2, 1)
	37 invokestatic (2, 1)
	38 java/lang/Double.isNaN:(D)Z (2, 1)
	40 ifeq (2, 1)
	41 27 (2, 1)
	43 aload_0 (2, 1)
	44 getfield (2, 1)
	45 org/apache/commons/math3/optimization/direct/AbstractSimplex.simplex:[Lorg/apache/commons/math3/optimization/PointValuePair; (2, 1)
	47 iload_3 (2, 1)
	48 new (2, 1)
	49 org/apache/commons/math3/optimization/PointValuePair (2, 1)
	51 dup (2, 1)
	52 aload (2, 1)
	53 #5 (2, 1)
	54 aload_1 (2, 1)
	55 aload (2, 1)
	56 #5 (2, 1)
	57 invokeinterface (2, 1)
	58 org/apache/commons/math3/analysis/MultivariateFunction.<init>:([DDZ)V (2, 1)
	60 0 (2, 1)
	62 iconst_0 (2, 1)
	63 invokespecial (2, 1)
	64 org/apache/commons/math3/optimization/PointValuePair.<init>:([DDZ)V (2, 1)
	66 aastore (2, 1)
	67 iinc (2, 1)
	68 #3 (2, 1)
	69 -89 (2, 1)
	70 goto (2, 1)
	71 -68 (2, 1)
	73 aload_0 (1, 4)
	74 getfield (1, 4)
	75 org/apache/commons/math3/optimization/direct/AbstractSimplex.simplex:[Lorg/apache/commons/math3/optimization/PointValuePair; (1, 4)
	77 aload_2 (1, 4)
	78 invokestatic (1, 4)
	79 java/util/Arrays.sort:([Ljava/lang/Object;Ljava/util/Comparator;)V (1, 4)
	81 return (0, 0)

Method: replaceWorstPoint
	0 iconst_0 (1, 4)
	1 istore_3 (1, 4)
	2 iload_3 (1, 4)
	3 aload_0 (1, 4)
	4 getfield (1, 4)
	5 org/apache/commons/math3/optimization/direct/AbstractSimplex.dimension:I (1, 4)
	7 if_icmpge (1, 4)
	8 43 (1, 4)
	10 aload_2 (2, 1)
	11 aload_0 (2, 1)
	12 getfield (2, 1)
	13 org/apache/commons/math3/optimization/direct/AbstractSimplex.simplex:[Lorg/apache/commons/math3/optimization/PointValuePair; (2, 1)
	15 iload_3 (2, 1)
	16 aaload (2, 1)
	17 aload_1 (2, 1)
	18 invokeinterface (2, 1)
	19 java/util/Comparator.org/apache/commons/math3/exception/OutOfRangeException (2, 1)
	21 0 (2, 1)
	23 ifle (2, 1)
	24 21 (2, 1)
	26 aload_0 (2, 1)
	27 getfield (2, 1)
	28 org/apache/commons/math3/optimization/direct/AbstractSimplex.simplex:[Lorg/apache/commons/math3/optimization/PointValuePair; (2, 1)
	30 iload_3 (2, 1)
	31 aaload (2, 1)
	32 astore (2, 1)
	33 #4 (2, 1)
	34 aload_0 (2, 1)
	35 getfield (2, 1)
	36 org/apache/commons/math3/optimization/direct/AbstractSimplex.simplex:[Lorg/apache/commons/math3/optimization/PointValuePair; (2, 1)
	38 iload_3 (2, 1)
	39 aload_1 (2, 1)
	40 aastore (2, 1)
	41 aload (2, 1)
	42 #4 (2, 1)
	43 astore_1 (2, 1)
	44 iinc (2, 1)
	45 #3 (2, 1)
	46 -89 (2, 1)
	47 goto (2, 1)
	48 -45 (2, 1)
	50 aload_0 (1, 4)
	51 getfield (1, 4)
	52 org/apache/commons/math3/optimization/direct/AbstractSimplex.simplex:[Lorg/apache/commons/math3/optimization/PointValuePair; (1, 4)
	54 aload_0 (1, 4)
	55 getfield (1, 4)
	56 org/apache/commons/math3/optimization/direct/AbstractSimplex.dimension:I (1, 4)
	58 aload_1 (1, 4)
	59 aastore (1, 4)
	60 return (0, 0)

Method: getPoints
	0 aload_0 (0, 0)
	1 getfield (0, 0)
	2 org/apache/commons/math3/optimization/direct/AbstractSimplex.simplex:[Lorg/apache/commons/math3/optimization/PointValuePair; (0, 0)
	4 arraylength (0, 0)
	5 anewarray (0, 0)
	6 org/apache/commons/math3/optimization/PointValuePair (0, 0)
	8 astore_1 (0, 0)
	9 aload_0 (0, 0)
	10 getfield (0, 0)
	11 org/apache/commons/math3/optimization/direct/AbstractSimplex.simplex:[Lorg/apache/commons/math3/optimization/PointValuePair; (0, 0)
	13 iconst_0 (0, 0)
	14 aload_1 (0, 0)
	15 iconst_0 (0, 0)
	16 aload_0 (0, 0)
	17 getfield (0, 0)
	18 org/apache/commons/math3/optimization/direct/AbstractSimplex.simplex:[Lorg/apache/commons/math3/optimization/PointValuePair; (0, 0)
	20 arraylength (0, 0)
	21 invokestatic (0, 0)
	22 java/lang/System.arraycopy:(Ljava/lang/Object;ILjava/lang/Object;II)V (0, 0)
	24 aload_1 (0, 0)
	25 areturn (0, 0)

Method: getPoint
	0 iload_1 (1, 1)
	1 iflt (1, 1)
	2 12 (1, 1)
	4 iload_1 (1, 1)
	5 aload_0 (1, 1)
	6 getfield (1, 1)
	7 org/apache/commons/math3/optimization/direct/AbstractSimplex.simplex:[Lorg/apache/commons/math3/optimization/PointValuePair; (1, 1)
	9 arraylength (1, 1)
	10 if_icmplt (1, 1)
	11 29 (1, 1)
	13 new (1, 1)
	14 org/apache/commons/math3/exception/OutOfRangeException (1, 1)
	16 dup (1, 1)
	17 iload_1 (1, 1)
	18 invokestatic (1, 1)
	19 java/lang/Integer.valueOf:(I)Ljava/lang/Integer; (1, 1)
	21 iconst_0 (1, 1)
	22 invokestatic (1, 1)
	23 java/lang/Integer.valueOf:(I)Ljava/lang/Integer; (1, 1)
	25 aload_0 (1, 1)
	26 getfield (1, 1)
	27 org/apache/commons/math3/optimization/direct/AbstractSimplex.simplex:[Lorg/apache/commons/math3/optimization/PointValuePair; (1, 1)
	29 arraylength (1, 1)
	30 iconst_1 (1, 1)
	31 isub (1, 1)
	32 invokestatic (1, 1)
	33 java/lang/Integer.valueOf:(I)Ljava/lang/Integer; (1, 1)
	35 invokespecial (1, 1)
	36 org/apache/commons/math3/exception/OutOfRangeException.<init>:(Ljava/lang/Number;Ljava/lang/Number;Ljava/lang/Number;)V (1, 1)
	38 athrow (1, 1)
	39 aload_0 (1, 1)
	40 getfield (1, 1)
	41 org/apache/commons/math3/optimization/direct/AbstractSimplex.simplex:[Lorg/apache/commons/math3/optimization/PointValuePair; (1, 1)
	43 iload_1 (1, 1)
	44 aaload (1, 1)
	45 areturn (0, 1)

Method: setPoint
	0 iload_1 (1, 1)
	1 iflt (1, 1)
	2 12 (1, 1)
	4 iload_1 (1, 1)
	5 aload_0 (1, 1)
	6 getfield (1, 1)
	7 org/apache/commons/math3/optimization/direct/AbstractSimplex.simplex:[Lorg/apache/commons/math3/optimization/PointValuePair; (1, 1)
	9 arraylength (1, 1)
	10 if_icmplt (1, 1)
	11 29 (1, 1)
	13 new (1, 1)
	14 org/apache/commons/math3/exception/OutOfRangeException (1, 1)
	16 dup (1, 1)
	17 iload_1 (1, 1)
	18 invokestatic (1, 1)
	19 java/lang/Integer.valueOf:(I)Ljava/lang/Integer; (1, 1)
	21 iconst_0 (1, 1)
	22 invokestatic (1, 1)
	23 java/lang/Integer.valueOf:(I)Ljava/lang/Integer; (1, 1)
	25 aload_0 (1, 1)
	26 getfield (1, 1)
	27 org/apache/commons/math3/optimization/direct/AbstractSimplex.simplex:[Lorg/apache/commons/math3/optimization/PointValuePair; (1, 1)
	29 arraylength (1, 1)
	30 iconst_1 (1, 1)
	31 isub (1, 1)
	32 invokestatic (1, 1)
	33 java/lang/Integer.valueOf:(I)Ljava/lang/Integer; (1, 1)
	35 invokespecial (1, 1)
	36 org/apache/commons/math3/exception/OutOfRangeException.<init>:(Ljava/lang/Number;Ljava/lang/Number;Ljava/lang/Number;)V (1, 1)
	38 athrow (1, 1)
	39 aload_0 (1, 1)
	40 getfield (1, 1)
	41 org/apache/commons/math3/optimization/direct/AbstractSimplex.simplex:[Lorg/apache/commons/math3/optimization/PointValuePair; (1, 1)
	43 iload_1 (1, 1)
	44 aload_2 (1, 1)
	45 aastore (1, 1)
	46 return (0, 1)

Method: setPoints
	0 aload_1 (1, 1)
	1 arraylength (1, 1)
	2 aload_0 (1, 1)
	3 getfield (1, 1)
	4 org/apache/commons/math3/optimization/direct/AbstractSimplex.simplex:[Lorg/apache/commons/math3/optimization/PointValuePair; (1, 1)
	6 arraylength (1, 1)
	7 if_icmpeq (1, 1)
	8 18 (1, 1)
	10 new (1, 1)
	11 org/apache/commons/math3/exception/DimensionMismatchException (1, 1)
	13 dup (1, 1)
	14 aload_1 (1, 1)
	15 arraylength (1, 1)
	16 aload_0 (1, 1)
	17 getfield (1, 1)
	18 org/apache/commons/math3/optimization/direct/AbstractSimplex.simplex:[Lorg/apache/commons/math3/optimization/PointValuePair; (1, 1)
	20 arraylength (1, 1)
	21 invokespecial (1, 1)
	22 org/apache/commons/math3/exception/DimensionMismatchException.<init>:(II)V (1, 1)
	24 athrow (1, 1)
	25 aload_0 (0, 0)
	26 aload_1 (0, 0)
	27 putfield (0, 0)
	28 org/apache/commons/math3/optimization/direct/AbstractSimplex.simplex:[Lorg/apache/commons/math3/optimization/PointValuePair; (0, 0)
	30 return (0, 0)

Method: createHypercubeSteps
	0 iload_0 (0, 0)
	1 newarray (0, 0)
	2 7 (0, 0)
	3 astore_3 (0, 0)
	4 iconst_0 (1, 4)
	5 istore (1, 4)
	6 #4 (1, 4)
	7 iload (1, 4)
	8 #4 (1, 4)
	9 iload_0 (1, 4)
	10 if_icmpge (1, 4)
	11 14 (1, 4)
	13 aload_3 (1, 4)
	14 iload (1, 4)
	15 #4 (1, 4)
	16 dload_1 (1, 4)
	17 dastore (1, 4)
	18 iinc (1, 4)
	19 #4 (1, 4)
	20 -89 (1, 4)
	21 goto (1, 4)
	22 -14 (1, 4)
	24 aload_3 (0, 0)
	25 areturn (0, 0)

