Method: <init>
	0 aload_0 (0, 0)
	1 invokespecial (0, 0)
	4 aload_0 (0, 0)
	5 new (0, 0)
	8 dup (0, 0)
	9 invokespecial (0, 0)
	12 putfield (0, 0)
	15 aload_0 (1, 4)
	16 aload_1 (1, 4)
	17 putfield (1, 4)
	20 return (0, 0)

Method: getMaxEvaluations
	0 aload_0 (0, 0)
	1 getfield (0, 0)
	4 invokevirtual (0, 0)
	7 ireturn (0, 0)

Method: getEvaluations
	0 aload_0 (0, 0)
	1 getfield (0, 0)
	4 invokevirtual (0, 0)
	7 ireturn (0, 0)

Method: getConvergenceChecker
	0 aload_0 (0, 0)
	1 getfield (0, 0)
	4 areturn (0, 0)

Method: computeObjectiveValue
	0 aload_0 (0, 0)
	1 getfield (0, 0)
	4 invokevirtual (0, 0)
	7 goto (0, 0)
	10 astore_2 (0, 0)
	11 new (0, 0)
	14 dup (0, 0)
	15 aload_2 (0, 0)
	16 invokevirtual (0, 0)
	19 invokespecial (0, 0)
	22 athrow (0, 0)
	23 aload_0 (0, 0)
	24 getfield (0, 0)
	27 aload_1 (0, 0)
	28 invokeinterface (0, 0)
	33 areturn (0, 0)

Method: optimize
	0 aload_0 (0, 0)
	1 iload_1 (0, 0)
	2 aload_2 (0, 0)
	3 aload_3 (0, 0)
	4 invokevirtual (0, 0)
	7 areturn (0, 0)

Method: optimizeInternal
	0 aload_0 (0, 0)
	1 getfield (0, 0)
	4 iload_1 (0, 0)
	5 invokevirtual (0, 0)
	8 aload_0 (0, 0)
	9 getfield (0, 0)
	12 invokevirtual (0, 0)
	15 aload_0 (0, 0)
	16 aload_2 (0, 0)
	17 putfield (0, 0)
	20 aload_0 (0, 0)
	21 aload_3 (0, 0)
	22 invokespecial (0, 0)
	25 aload_0 (0, 0)
	26 invokespecial (0, 0)
	29 aload_0 (0, 0)
	30 invokevirtual (0, 0)
	33 aload_0 (0, 4)
	34 invokevirtual (0, 4)
	37 areturn (0, 4)

Method: getStartPoint
	0 aload_0 (0, 0)
	1 getfield (0, 0)
	4 invokevirtual (0, 0)
	7 checkcast (0, 0)
	10 areturn (0, 0)

Method: getWeight
	0 aload_0 (0, 0)
	1 getfield (0, 0)
	4 invokeinterface (0, 0)
	9 areturn (0, 0)

Method: getTarget
	0 aload_0 (0, 0)
	1 getfield (0, 0)
	4 invokevirtual (0, 0)
	7 checkcast (0, 0)
	10 areturn (0, 0)

Method: getObjectiveFunction
	0 aload_0 (0, 0)
	1 getfield (0, 0)
	4 areturn (0, 0)

Method: getTargetRef
	0 aload_0 (0, 0)
	1 getfield (0, 0)
	4 areturn (0, 0)

Method: getWeightRef
	0 aload_0 (0, 0)
	1 getfield (0, 0)
	4 areturn (0, 0)

Method: setUp
	0 aload_0 (0, 0)
	1 getfield (0, 0)
	4 arraylength (0, 0)
	5 istore_1 (0, 0)
	6 aload_0 (0, 0)
	7 iload_1 (0, 0)
	8 newarray (0, 0)
	10 putfield (0, 0)
	13 iconst_0 (1, 4)
	14 istore_2 (1, 4)
	15 iload_2 (1, 4)
	16 iload_1 (1, 4)
	17 if_icmpge (1, 4)
	20 aload_0 (1, 4)
	21 getfield (1, 4)
	24 iload_2 (1, 4)
	25 aload_0 (1, 4)
	26 getfield (1, 4)
	29 iload_2 (1, 4)
	30 iload_2 (1, 4)
	31 invokeinterface (1, 4)
	36 dastore (1, 4)
	37 iinc (1, 4)
	40 goto (1, 4)
	43 return (0, 0)

Method: parseOptimizationData
	0 aload_1 (1, 4)
	1 astore_2 (1, 4)
	2 aload_2 (1, 4)
	3 arraylength (1, 4)
	4 istore_3 (1, 4)
	5 iconst_0 (1, 4)
	6 istore (1, 4)
	8 iload (1, 4)
	10 iload_3 (1, 4)
	11 if_icmpge (1, 4)
	14 aload_2 (1, 4)
	15 iload (1, 4)
	17 aaload (1, 4)
	18 astore (1, 4)
	20 aload (2, 1)
	22 instanceof (2, 1)
	25 ifeq (2, 1)
	28 aload_0 (2, 1)
	29 aload (2, 1)
	31 checkcast (2, 1)
	34 invokevirtual (2, 1)
	37 putfield (2, 1)
	40 goto (2, 1)
	43 aload (2, 1)
	45 instanceof (2, 1)
	48 ifeq (2, 1)
	51 aload_0 (2, 1)
	52 aload (2, 1)
	54 checkcast (2, 1)
	57 invokevirtual (2, 1)
	60 putfield (2, 1)
	63 goto (2, 1)
	66 aload (2, 1)
	68 instanceof (2, 1)
	71 ifeq (2, 1)
	74 aload_0 (2, 1)
	75 aload (2, 1)
	77 checkcast (2, 1)
	80 invokevirtual (2, 1)
	83 putfield (2, 1)
	86 goto (2, 1)
	89 iinc (2, 1)
	92 goto (2, 1)
	95 return (0, 0)

Method: checkParameters
	0 aload_0 (1, 1)
	1 getfield (1, 1)
	4 arraylength (1, 1)
	5 aload_0 (1, 1)
	6 getfield (1, 1)
	9 invokeinterface (1, 1)
	14 if_icmpeq (1, 1)
	17 new (1, 1)
	20 dup (1, 1)
	21 aload_0 (1, 1)
	22 getfield (1, 1)
	25 arraylength (1, 1)
	26 aload_0 (1, 1)
	27 getfield (1, 1)
	30 invokeinterface (1, 1)
	35 invokespecial (1, 1)
	38 athrow (1, 1)
	39 return (0, 0)

