Method: <init>
	0 aload_0 (0, 0)
	1 aload_1 (0, 0)
	2 invokespecial (0, 0)
	3 org/apache/commons/math3/optimization/direct/BaseAbstractMultivariateOptimizer.<init>:(Lorg/apache/commons/math3/optimization/ConvergenceChecker;)V (0, 0)
	5 return (0, 0)

Method: optimize
	0 aload_0 (0, 0)
	1 iload_1 (0, 0)
	2 aload_2 (0, 0)
	3 aload_3 (0, 0)
	4 iconst_2 (0, 0)
	5 anewarray (0, 0)
	6 org/apache/commons/math3/optimization/OptimizationData (0, 0)
	8 dup (0, 0)
	9 iconst_0 (0, 0)
	10 new (0, 0)
	11 org/apache/commons/math3/optimization/InitialGuess (0, 0)
	13 dup (0, 0)
	14 aload (0, 0)
	15 #4 (0, 0)
	16 invokespecial (0, 0)
	17 org/apache/commons/math3/optimization/InitialGuess.<init>:([D)V (0, 0)
	19 aastore (0, 0)
	20 dup (0, 0)
	21 iconst_1 (0, 0)
	22 new (0, 0)
	23 org/apache/commons/math3/optimization/SimpleBounds (0, 0)
	25 dup (0, 0)
	26 aload (0, 0)
	27 #5 (0, 0)
	28 aload (0, 0)
	29 #6 (0, 0)
	30 invokespecial (0, 0)
	31 org/apache/commons/math3/optimization/SimpleBounds.<init>:([D[D)V (0, 0)
	33 aastore (0, 0)
	34 invokespecial (0, 0)
	35 org/apache/commons/math3/optimization/direct/BaseAbstractMultivariateOptimizer.optimizeInternal:(ILorg/apache/commons/math3/analysis/MultivariateFunction;Lorg/apache/commons/math3/optimization/GoalType;[Lorg/apache/commons/math3/optimization/OptimizationData;)Lorg/apache/commons/math3/optimization/PointValuePair; (0, 0)
	37 areturn (0, 0)

