Method: <init>
	0 aload_0 (0, 0)
	1 aconst_null (0, 0)
	2 invokespecial (0, 0)
	5 aload_0 (0, 0)
	6 iload_1 (0, 0)
	7 putfield (0, 0)
	10 aload_0 (0, 0)
	11 dload_2 (0, 0)
	12 putfield (0, 0)
	15 aload_0 (0, 0)
	16 dload (0, 0)
	18 putfield (0, 0)
	21 return (0, 0)

Method: doOptimize
	0 aload_0 (0, 0)
	1 invokevirtual (0, 0)
	4 astore_1 (0, 0)
	5 aload_0 (0, 0)
	6 invokevirtual (0, 0)
	9 astore_2 (0, 0)
	10 aload_0 (0, 0)
	11 aload_1 (0, 0)
	12 aload_2 (0, 0)
	13 invokespecial (0, 0)
	16 aload_0 (0, 0)
	17 aload_0 (0, 0)
	18 invokevirtual (0, 0)
	21 getstatic (0, 0)
	24 if_acmpne (0, 0)
	27 iconst_1 (0, 0)
	28 goto (0, 0)
	31 iconst_0 (0, 0)
	32 putfield (0, 0)
	35 aload_0 (0, 0)
	36 new (0, 0)
	39 dup (0, 0)
	40 aload_0 (0, 0)
	41 invokevirtual (0, 0)
	44 invokespecial (0, 0)
	47 putfield (0, 0)
	50 aload_0 (0, 0)
	51 aload_1 (0, 0)
	52 aload_2 (0, 0)
	53 invokespecial (0, 0)
	56 dstore_3 (0, 0)
	57 new (0, 0)
	60 dup (0, 0)
	61 aload_0 (0, 0)
	62 getfield (0, 0)
	65 invokevirtual (0, 0)
	68 aload_0 (0, 0)
	69 getfield (0, 0)
	72 ifeq (0, 0)
	75 dload_3 (0, 0)
	76 goto (0, 0)
	79 dload_3 (0, 0)
	80 dneg (0, 0)
	81 invokespecial (0, 0)
	84 areturn (0, 0)

Method: bobyqa
	0 invokestatic (0, 0)
	3 aload_0 (0, 0)
	4 getfield (0, 0)
	7 invokevirtual (0, 0)
	10 istore_3 (0, 0)
	11 iconst_0 (1, 4)
	12 istore (1, 4)
	14 iload (1, 4)
	16 iload_3 (1, 4)
	17 if_icmpge (1, 4)
	20 aload_0 (1, 1)
	21 getfield (1, 1)
	24 iload (1, 1)
	26 daload (1, 1)
	27 dstore (1, 1)
	29 aload_0 (1, 1)
	30 getfield (1, 1)
	33 iload (1, 1)
	35 aload_1 (1, 1)
	36 iload (1, 1)
	38 daload (1, 1)
	39 aload_0 (1, 1)
	40 getfield (1, 1)
	43 iload (1, 1)
	45 invokevirtual (1, 1)
	48 dsub (1, 1)
	49 invokevirtual (1, 1)
	52 aload_0 (1, 1)
	53 getfield (1, 1)
	56 iload (1, 1)
	58 aload_2 (1, 1)
	59 iload (1, 1)
	61 daload (1, 1)
	62 aload_0 (1, 1)
	63 getfield (1, 1)
	66 iload (1, 1)
	68 invokevirtual (1, 1)
	71 dsub (1, 1)
	72 invokevirtual (1, 1)
	75 aload_0 (2, 1)
	76 getfield (2, 1)
	79 iload (2, 1)
	81 invokevirtual (2, 1)
	84 aload_0 (2, 1)
	85 getfield (2, 1)
	88 dneg (2, 1)
	89 dcmpl (2, 1)
	90 iflt (2, 1)
	93 aload_0 (3, 1)
	94 getfield (3, 1)
	97 iload (3, 1)
	99 invokevirtual (3, 1)
	102 dconst_0 (3, 1)
	103 dcmpl (3, 1)
	104 iflt (3, 1)
	107 aload_0 (3, 1)
	108 getfield (3, 1)
	111 iload (3, 1)
	113 aload_1 (3, 1)
	114 iload (3, 1)
	116 daload (3, 1)
	117 invokevirtual (3, 1)
	120 aload_0 (3, 1)
	121 getfield (3, 1)
	124 iload (3, 1)
	126 dconst_0 (3, 1)
	127 invokevirtual (3, 1)
	130 aload_0 (3, 1)
	131 getfield (3, 1)
	134 iload (3, 1)
	136 dload (3, 1)
	138 invokevirtual (3, 1)
	141 goto (3, 1)
	144 aload_0 (3, 2)
	145 getfield (3, 2)
	148 iload (3, 2)
	150 aload_1 (3, 2)
	151 iload (3, 2)
	153 daload (3, 2)
	154 aload_0 (3, 2)
	155 getfield (3, 2)
	158 dadd (3, 2)
	159 invokevirtual (3, 2)
	162 aload_0 (3, 1)
	163 getfield (3, 1)
	166 iload (3, 1)
	168 aload_0 (3, 1)
	169 getfield (3, 1)
	172 dneg (3, 1)
	173 invokevirtual (3, 1)
	176 aload_2 (3, 1)
	177 iload (3, 1)
	179 daload (3, 1)
	180 aload_0 (3, 1)
	181 getfield (3, 1)
	184 iload (3, 1)
	186 invokevirtual (3, 1)
	189 dsub (3, 1)
	190 dstore (3, 1)
	192 aload_0 (3, 1)
	193 getfield (3, 1)
	196 iload (3, 1)
	198 dload (3, 1)
	200 aload_0 (3, 1)
	201 getfield (3, 1)
	204 invokestatic (3, 1)
	207 invokevirtual (3, 1)
	210 goto (2, 1)
	213 aload_0 (2, 1)
	214 getfield (2, 1)
	217 iload (2, 1)
	219 invokevirtual (2, 1)
	222 aload_0 (2, 1)
	223 getfield (2, 1)
	226 dcmpg (2, 1)
	227 ifgt (2, 1)
	230 aload_0 (3, 1)
	231 getfield (3, 1)
	234 iload (3, 1)
	236 invokevirtual (3, 1)
	239 dconst_0 (3, 1)
	240 dcmpg (3, 1)
	241 ifgt (3, 1)
	244 aload_0 (3, 1)
	245 getfield (3, 1)
	248 iload (3, 1)
	250 aload_2 (3, 1)
	251 iload (3, 1)
	253 daload (3, 1)
	254 invokevirtual (3, 1)
	257 aload_0 (3, 1)
	258 getfield (3, 1)
	261 iload (3, 1)
	263 dload (3, 1)
	265 dneg (3, 1)
	266 invokevirtual (3, 1)
	269 aload_0 (3, 1)
	270 getfield (3, 1)
	273 iload (3, 1)
	275 dconst_0 (3, 1)
	276 invokevirtual (3, 1)
	279 goto (3, 1)
	282 aload_0 (3, 2)
	283 getfield (3, 2)
	286 iload (3, 2)
	288 aload_2 (3, 2)
	289 iload (3, 2)
	291 daload (3, 2)
	292 aload_0 (3, 2)
	293 getfield (3, 2)
	296 dsub (3, 2)
	297 invokevirtual (3, 2)
	300 aload_1 (3, 2)
	301 iload (3, 2)
	303 daload (3, 2)
	304 aload_0 (3, 2)
	305 getfield (3, 2)
	308 iload (3, 2)
	310 invokevirtual (3, 2)
	313 dsub (3, 2)
	314 dstore (3, 2)
	316 aload_0 (3, 2)
	317 getfield (3, 2)
	320 dneg (3, 2)
	321 dstore (3, 2)
	323 aload_0 (3, 1)
	324 getfield (3, 1)
	327 iload (3, 1)
	329 dload (3, 1)
	331 dload (3, 1)
	333 invokestatic (3, 1)
	336 invokevirtual (3, 1)
	339 aload_0 (3, 1)
	340 getfield (3, 1)
	343 iload (3, 1)
	345 aload_0 (3, 1)
	346 getfield (3, 1)
	349 invokevirtual (3, 1)
	352 iinc (3, 1)
	355 goto (3, 1)
	358 aload_0 (2, 1)
	359 aload_1 (2, 1)
	360 aload_2 (2, 1)
	361 invokespecial (2, 1)
	364 dreturn (2, 1)

Method: bobyqb
	0 invokestatic (0, 0)
	3 aload_0 (0, 0)
	4 getfield (0, 0)
	7 invokevirtual (0, 0)
	10 istore_3 (0, 0)
	11 aload_0 (0, 0)
	12 getfield (0, 0)
	15 istore (0, 0)
	17 iload_3 (0, 0)
	18 iconst_1 (0, 0)
	19 iadd (0, 0)
	20 istore (0, 0)
	22 iload (0, 0)
	24 iload (0, 0)
	26 isub (0, 0)
	27 istore (0, 0)
	29 iload_3 (0, 0)
	30 iload (0, 0)
	32 imul (0, 0)
	33 iconst_2 (0, 0)
	34 idiv (0, 0)
	35 istore (0, 0)
	37 new (0, 0)
	40 dup (0, 0)
	41 iload_3 (0, 0)
	42 invokespecial (0, 0)
	45 astore (0, 0)
	47 new (0, 0)
	50 dup (0, 0)
	51 iload (0, 0)
	53 invokespecial (0, 0)
	56 astore (0, 0)
	58 new (0, 0)
	61 dup (0, 0)
	62 iload (0, 0)
	64 invokespecial (0, 0)
	67 astore (0, 0)
	69 ldc2_w (0, 0)
	72 dstore (0, 0)
	74 ldc2_w (0, 0)
	77 dstore (0, 0)
	79 ldc2_w (0, 0)
	82 dstore (0, 0)
	84 ldc2_w (0, 0)
	87 dstore (0, 0)
	89 aload_0 (0, 1)
	90 iconst_0 (0, 1)
	91 putfield (0, 1)
	94 aload_0 (0, 1)
	95 aload_1 (0, 1)
	96 aload_2 (0, 1)
	97 invokespecial (0, 1)
	100 dconst_0 (0, 1)
	101 dstore (0, 1)
	103 iconst_0 (1, 4)
	104 istore (1, 4)
	106 iload (1, 4)
	108 iload_3 (1, 4)
	109 if_icmpge (1, 4)
	112 aload_0 (1, 4)
	113 getfield (1, 4)
	116 iload (1, 4)
	118 aload_0 (1, 4)
	119 getfield (1, 4)
	122 aload_0 (1, 4)
	123 getfield (1, 4)
	126 iload (1, 4)
	128 invokevirtual (1, 4)
	131 invokevirtual (1, 4)
	134 aload_0 (1, 4)
	135 getfield (1, 4)
	138 iload (1, 4)
	140 invokevirtual (1, 4)
	143 dstore (1, 4)
	145 dload (1, 4)
	147 dload (1, 4)
	149 dload (1, 4)
	151 dmul (1, 4)
	152 dadd (1, 4)
	153 dstore (1, 4)
	155 iinc (1, 4)
	158 goto (1, 4)
	161 aload_0 (0, 1)
	162 getfield (0, 1)
	165 iconst_0 (0, 1)
	166 invokevirtual (0, 1)
	169 dstore (0, 1)
	171 iconst_0 (0, 1)
	172 istore (0, 1)
	174 iconst_0 (0, 4)
	175 istore (0, 4)
	177 iconst_0 (0, 4)
	178 istore (0, 4)
	180 iconst_0 (0, 4)
	181 istore (0, 4)
	183 aload_0 (0, 4)
	184 invokevirtual (0, 4)
	187 istore (0, 4)
	189 aload_0 (0, 4)
	190 getfield (0, 4)
	193 dstore (0, 4)
	195 dload (0, 4)
	197 dstore (0, 4)
	199 dconst_0 (0, 1)
	200 dstore (0, 1)
	202 dconst_0 (0, 1)
	203 dstore (0, 1)
	205 dconst_0 (0, 1)
	206 dstore (0, 1)
	208 dconst_0 (0, 1)
	209 dstore (0, 1)
	211 dconst_0 (0, 1)
	212 dstore (0, 1)
	214 dconst_0 (0, 1)
	215 dstore (0, 1)
	217 dconst_0 (0, 1)
	218 dstore (0, 1)
	220 dconst_0 (0, 1)
	221 dstore (0, 1)
	223 dconst_0 (0, 1)
	224 dstore (0, 1)
	226 dconst_0 (0, 1)
	227 dstore (0, 1)
	229 dconst_0 (0, 1)
	230 dstore (0, 1)
	232 dconst_0 (0, 1)
	233 dstore (0, 1)
	235 bipush (0, 1)
	237 istore (0, 1)
	239 iload (2, 5)
	241 lookupswitch (2, 5)
	324 bipush (3, 5)
	326 invokestatic (3, 5)
	329 aload_0 (4, 1)
	330 getfield (4, 1)
	333 ifeq (4, 1)
	336 iconst_0 (4, 1)
	337 istore (4, 1)
	339 iconst_0 (5, 4)
	340 istore (5, 4)
	342 iload (5, 4)
	344 iload_3 (5, 4)
	345 if_icmpge (5, 4)
	348 iconst_0 (6, 4)
	349 istore (6, 4)
	351 iload (6, 4)
	353 iload (6, 4)
	355 if_icmpgt (6, 4)
	358 iload (7, 1)
	360 iload (7, 1)
	362 if_icmpge (7, 1)
	365 aload_0 (7, 1)
	366 getfield (7, 1)
	369 iload (7, 1)
	371 aload_0 (7, 1)
	372 getfield (7, 1)
	375 iload (7, 1)
	377 invokevirtual (7, 1)
	380 aload_0 (7, 1)
	381 getfield (7, 1)
	384 iload (7, 1)
	386 invokevirtual (7, 1)
	389 aload_0 (7, 1)
	390 getfield (7, 1)
	393 iload (7, 1)
	395 invokevirtual (7, 1)
	398 dmul (7, 1)
	399 dadd (7, 1)
	400 invokevirtual (7, 1)
	403 aload_0 (6, 4)
	404 getfield (6, 4)
	407 iload (6, 4)
	409 aload_0 (6, 4)
	410 getfield (6, 4)
	413 iload (6, 4)
	415 invokevirtual (6, 4)
	418 aload_0 (6, 4)
	419 getfield (6, 4)
	422 iload (6, 4)
	424 invokevirtual (6, 4)
	427 aload_0 (6, 4)
	428 getfield (6, 4)
	431 iload (6, 4)
	433 invokevirtual (6, 4)
	436 dmul (6, 4)
	437 dadd (6, 4)
	438 invokevirtual (6, 4)
	441 iinc (6, 4)
	444 iinc (6, 4)
	447 goto (6, 4)
	450 iinc (6, 4)
	453 goto (6, 4)
	456 aload_0 (6, 1)
	457 invokevirtual (6, 1)
	460 iload (6, 1)
	462 if_icmple (6, 1)
	465 iconst_0 (7, 4)
	466 istore (7, 4)
	468 iload (7, 4)
	470 iload (7, 4)
	472 if_icmpge (7, 4)
	475 dconst_0 (7, 4)
	476 dstore (7, 4)
	478 iconst_0 (8, 4)
	479 istore (8, 4)
	481 iload (8, 4)
	483 iload_3 (8, 4)
	484 if_icmpge (8, 4)
	487 dload (8, 4)
	489 aload_0 (8, 4)
	490 getfield (8, 4)
	493 iload (8, 4)
	495 iload (8, 4)
	497 invokevirtual (8, 4)
	500 aload_0 (8, 4)
	501 getfield (8, 4)
	504 iload (8, 4)
	506 invokevirtual (8, 4)
	509 dmul (8, 4)
	510 dadd (8, 4)
	511 dstore (8, 4)
	513 iinc (8, 4)
	516 goto (8, 4)
	519 dload (7, 4)
	521 aload_0 (7, 4)
	522 getfield (7, 4)
	525 iload (7, 4)
	527 invokevirtual (7, 4)
	530 dmul (7, 4)
	531 dstore (7, 4)
	533 iconst_0 (8, 4)
	534 istore (8, 4)
	536 iload (8, 4)
	538 iload_3 (8, 4)
	539 if_icmpge (8, 4)
	542 aload_0 (8, 4)
	543 getfield (8, 4)
	546 iload (8, 4)
	548 aload_0 (8, 4)
	549 getfield (8, 4)
	552 iload (8, 4)
	554 invokevirtual (8, 4)
	557 dload (8, 4)
	559 aload_0 (8, 4)
	560 getfield (8, 4)
	563 iload (8, 4)
	565 iload (8, 4)
	567 invokevirtual (8, 4)
	570 dmul (8, 4)
	571 dadd (8, 4)
	572 invokevirtual (8, 4)
	575 iinc (8, 4)
	578 goto (8, 4)
	581 iinc (8, 4)
	584 goto (8, 4)
	587 bipush (5, 1)
	589 invokestatic (5, 1)
	592 new (5, 1)
	595 dup (5, 1)
	596 iload_3 (5, 1)
	597 invokespecial (5, 1)
	600 astore (5, 1)
	602 new (5, 1)
	605 dup (5, 1)
	606 iload_3 (5, 1)
	607 invokespecial (5, 1)
	610 astore (5, 1)
	612 new (5, 1)
	615 dup (5, 1)
	616 iload_3 (5, 1)
	617 invokespecial (5, 1)
	620 astore (5, 1)
	622 new (5, 1)
	625 dup (5, 1)
	626 iload_3 (5, 1)
	627 invokespecial (5, 1)
	630 astore (5, 1)
	632 new (5, 1)
	635 dup (5, 1)
	636 iload_3 (5, 1)
	637 invokespecial (5, 1)
	640 astore (5, 1)
	642 aload_0 (5, 1)
	643 dload (5, 1)
	645 aload (5, 1)
	647 aload (5, 1)
	649 aload (5, 1)
	651 aload (5, 1)
	653 aload (5, 1)
	655 invokespecial (5, 1)
	658 astore (5, 1)
	660 aload (5, 1)
	662 iconst_0 (5, 1)
	663 daload (5, 1)
	664 dstore (5, 1)
	666 aload (5, 1)
	668 iconst_1 (5, 1)
	669 daload (5, 1)
	670 dstore (5, 1)
	672 dload (5, 1)
	674 dstore (5, 1)
	676 dload (5, 1)
	678 invokestatic (5, 1)
	681 dstore (5, 1)
	683 dload (5, 1)
	685 dload (5, 1)
	687 invokestatic (5, 1)
	690 dstore (5, 1)
	692 dload (6, 1)
	694 ldc2_w (6, 1)
	697 dload (6, 1)
	699 dmul (6, 1)
	700 dcmpg (6, 1)
	701 ifge (6, 1)
	704 iconst_m1 (6, 1)
	705 istore (6, 1)
	707 ldc2_w (6, 1)
	710 dload (6, 1)
	712 dmul (6, 1)
	713 dstore (6, 1)
	715 dload (6, 1)
	717 dload (6, 1)
	719 dmul (6, 1)
	720 dstore (6, 1)
	722 aload_0 (7, 1)
	723 invokevirtual (7, 1)
	726 iload (7, 1)
	728 iconst_2 (7, 1)
	729 iadd (7, 1)
	730 if_icmpgt (7, 1)
	733 sipush (7, 1)
	736 istore (7, 1)
	738 goto (7, 1)
	741 dload (6, 1)
	743 dload (6, 1)
	745 invokestatic (6, 1)
	748 dstore (6, 1)
	750 dload (6, 1)
	752 dload (6, 1)
	754 invokestatic (6, 1)
	757 dstore (6, 1)
	759 dload (6, 1)
	761 ldc2_w (6, 1)
	764 dmul (6, 1)
	765 dload (6, 1)
	767 dmul (6, 1)
	768 dstore (6, 1)
	770 dload (6, 1)
	772 dconst_0 (6, 1)
	773 dcmpl (6, 1)
	774 ifle (6, 1)
	777 dload (6, 1)
	779 dload (6, 1)
	781 dload (6, 1)
	783 dmul (6, 1)
	784 dcmpl (6, 1)
	785 ifle (6, 1)
	788 sipush (7, 1)
	791 istore (7, 1)
	793 goto (7, 1)
	796 dload (6, 1)
	798 dload (6, 1)
	800 ddiv (6, 1)
	801 dstore (6, 1)
	803 iconst_0 (7, 4)
	804 istore (7, 4)
	806 iload (7, 4)
	808 iload_3 (7, 4)
	809 if_icmpge (7, 4)
	812 dload (7, 4)
	814 dstore (7, 4)
	816 aload_0 (8, 1)
	817 getfield (8, 1)
	820 iload (8, 1)
	822 invokevirtual (8, 1)
	825 aload_0 (8, 1)
	826 getfield (8, 1)
	829 iload (8, 1)
	831 invokevirtual (8, 1)
	834 dcmpl (8, 1)
	835 ifne (8, 1)
	838 aload (8, 1)
	840 iload (8, 1)
	842 invokevirtual (8, 1)
	845 dstore (8, 1)
	847 aload_0 (8, 1)
	848 getfield (8, 1)
	851 iload (8, 1)
	853 invokevirtual (8, 1)
	856 aload_0 (8, 1)
	857 getfield (8, 1)
	860 iload (8, 1)
	862 invokevirtual (8, 1)
	865 dcmpl (8, 1)
	866 ifne (8, 1)
	869 aload (8, 1)
	871 iload (8, 1)
	873 invokevirtual (8, 1)
	876 dneg (8, 1)
	877 dstore (8, 1)
	879 dload (8, 1)
	881 dload (8, 1)
	883 dcmpg (8, 1)
	884 ifge (8, 1)
	887 aload_0 (8, 1)
	888 getfield (8, 1)
	891 iload (8, 1)
	893 iload (8, 1)
	895 iload (8, 1)
	897 imul (8, 1)
	898 iadd (8, 1)
	899 iconst_2 (8, 1)
	900 idiv (8, 1)
	901 invokevirtual (8, 1)
	904 dstore (8, 1)
	906 iconst_0 (9, 4)
	907 istore (9, 4)
	909 iload (9, 4)
	911 iload (9, 4)
	913 if_icmpge (9, 4)
	916 aload_0 (9, 4)
	917 getfield (9, 4)
	920 iload (9, 4)
	922 iload (9, 4)
	924 invokevirtual (9, 4)
	927 dstore (9, 4)
	929 dload (9, 4)
	931 aload_0 (9, 4)
	932 getfield (9, 4)
	935 iload (9, 4)
	937 invokevirtual (9, 4)
	940 dload (9, 4)
	942 dload (9, 4)
	944 dmul (9, 4)
	945 dmul (9, 4)
	946 dadd (9, 4)
	947 dstore (9, 4)
	949 iinc (9, 4)
	952 goto (9, 4)
	955 dload (8, 1)
	957 ldc2_w (8, 1)
	960 dload (8, 1)
	962 dmul (8, 1)
	963 dload (8, 1)
	965 dmul (8, 1)
	966 dadd (8, 1)
	967 dstore (8, 1)
	969 dload (9, 1)
	971 dload (9, 1)
	973 dcmpg (9, 1)
	974 ifge (9, 1)
	977 sipush (9, 1)
	980 istore (9, 1)
	982 goto (9, 1)
	985 iinc (9, 1)
	988 goto (9, 1)
	991 sipush (8, 1)
	994 istore (8, 1)
	996 goto (8, 1)
	999 iinc (7, 4)
	1002 bipush (7, 1)
	1004 invokestatic (7, 1)
	1007 dload (8, 1)
	1009 dload (8, 1)
	1011 ldc2_w (8, 1)
	1014 dmul (8, 1)
	1015 dcmpg (8, 1)
	1016 ifgt (8, 1)
	1019 dload (8, 1)
	1021 ldc2_w (8, 1)
	1024 dmul (8, 1)
	1025 dstore (8, 1)
	1027 dconst_0 (8, 1)
	1028 dstore (8, 1)
	1030 iconst_0 (9, 4)
	1031 istore (9, 4)
	1033 iload (9, 4)
	1035 iload (9, 4)
	1037 if_icmpge (9, 4)
	1040 dload (9, 4)
	1042 aload_0 (9, 4)
	1043 getfield (9, 4)
	1046 iload (9, 4)
	1048 invokevirtual (9, 4)
	1051 dadd (9, 4)
	1052 dstore (9, 4)
	1054 ldc2_w (9, 4)
	1057 dload (9, 4)
	1059 dmul (9, 4)
	1060 dstore (9, 4)
	1062 iconst_0 (10, 4)
	1063 istore (10, 4)
	1065 iload (10, 4)
	1067 iload_3 (10, 4)
	1068 if_icmpge (10, 4)
	1071 dload (10, 4)
	1073 aload_0 (10, 4)
	1074 getfield (10, 4)
	1077 iload (10, 4)
	1079 iload (10, 4)
	1081 invokevirtual (10, 4)
	1084 aload_0 (10, 4)
	1085 getfield (10, 4)
	1088 iload (10, 4)
	1090 invokevirtual (10, 4)
	1093 dmul (10, 4)
	1094 dadd (10, 4)
	1095 dstore (10, 4)
	1097 iinc (10, 4)
	1100 goto (10, 4)
	1103 aload (9, 1)
	1105 iload (9, 1)
	1107 dload (9, 1)
	1109 invokevirtual (9, 1)
	1112 dload (9, 1)
	1114 ldc2_w (9, 1)
	1117 dload (9, 1)
	1119 dmul (9, 1)
	1120 dsub (9, 1)
	1121 dstore (9, 1)
	1123 iconst_0 (10, 4)
	1124 istore (10, 4)
	1126 iload (10, 4)
	1128 iload_3 (10, 4)
	1129 if_icmpge (10, 4)
	1132 aload (10, 4)
	1134 iload (10, 4)
	1136 aload_0 (10, 4)
	1137 getfield (10, 4)
	1140 iload (10, 4)
	1142 iload (10, 4)
	1144 invokevirtual (10, 4)
	1147 invokevirtual (10, 4)
	1150 aload_0 (10, 4)
	1151 getfield (10, 4)
	1154 iload (10, 4)
	1156 dload (10, 4)
	1158 aload_0 (10, 4)
	1159 getfield (10, 4)
	1162 iload (10, 4)
	1164 iload (10, 4)
	1166 invokevirtual (10, 4)
	1169 dmul (10, 4)
	1170 dload (10, 4)
	1172 aload_0 (10, 4)
	1173 getfield (10, 4)
	1176 iload (10, 4)
	1178 invokevirtual (10, 4)
	1181 dmul (10, 4)
	1182 dadd (10, 4)
	1183 invokevirtual (10, 4)
	1186 iload (10, 4)
	1188 iload (10, 4)
	1190 iadd (10, 4)
	1191 istore (10, 4)
	1193 iconst_0 (11, 4)
	1194 istore (11, 4)
	1196 iload (11, 4)
	1198 iload (11, 4)
	1200 if_icmpgt (11, 4)
	1203 aload_0 (11, 4)
	1204 getfield (11, 4)
	1207 iload (11, 4)
	1209 iload (11, 4)
	1211 aload_0 (11, 4)
	1212 getfield (11, 4)
	1215 iload (11, 4)
	1217 iload (11, 4)
	1219 invokevirtual (11, 4)
	1222 aload (11, 4)
	1224 iload (11, 4)
	1226 invokevirtual (11, 4)
	1229 aload_0 (11, 4)
	1230 getfield (11, 4)
	1233 iload (11, 4)
	1235 invokevirtual (11, 4)
	1238 dmul (11, 4)
	1239 dadd (11, 4)
	1240 aload_0 (11, 4)
	1241 getfield (11, 4)
	1244 iload (11, 4)
	1246 invokevirtual (11, 4)
	1249 aload (11, 4)
	1251 iload (11, 4)
	1253 invokevirtual (11, 4)
	1256 dmul (11, 4)
	1257 dadd (11, 4)
	1258 invokevirtual (11, 4)
	1261 iinc (11, 4)
	1264 goto (11, 4)
	1267 iinc (11, 4)
	1270 goto (11, 4)
	1273 iinc (11, 4)
	1276 goto (11, 4)
	1279 iconst_0 (11, 4)
	1280 istore (11, 4)
	1282 iload (11, 4)
	1284 iload (11, 4)
	1286 if_icmpge (11, 4)
	1289 dconst_0 (11, 4)
	1290 dstore (11, 4)
	1292 dconst_0 (11, 4)
	1293 dstore (11, 4)
	1295 iconst_0 (12, 4)
	1296 istore (12, 4)
	1298 iload (12, 4)
	1300 iload (12, 4)
	1302 if_icmpge (12, 4)
	1305 dload (12, 4)
	1307 aload_0 (12, 4)
	1308 getfield (12, 4)
	1311 iload (12, 4)
	1313 iload (12, 4)
	1315 invokevirtual (12, 4)
	1318 dadd (12, 4)
	1319 dstore (12, 4)
	1321 aload_0 (12, 4)
	1322 getfield (12, 4)
	1325 iload (12, 4)
	1327 aload (12, 4)
	1329 iload (12, 4)
	1331 invokevirtual (12, 4)
	1334 aload_0 (12, 4)
	1335 getfield (12, 4)
	1338 iload (12, 4)
	1340 iload (12, 4)
	1342 invokevirtual (12, 4)
	1345 dmul (12, 4)
	1346 invokevirtual (12, 4)
	1349 dload (12, 4)
	1351 aload_0 (12, 4)
	1352 getfield (12, 4)
	1355 iload (12, 4)
	1357 invokevirtual (12, 4)
	1360 dadd (12, 4)
	1361 dstore (12, 4)
	1363 iinc (12, 4)
	1366 goto (12, 4)
	1369 iconst_0 (12, 4)
	1370 istore (12, 4)
	1372 iload (12, 4)
	1374 iload_3 (12, 4)
	1375 if_icmpge (12, 4)
	1378 dload (12, 4)
	1380 dload (12, 4)
	1382 dmul (12, 4)
	1383 ldc2_w (12, 4)
	1386 dload (12, 4)
	1388 dmul (12, 4)
	1389 dsub (12, 4)
	1390 aload_0 (12, 4)
	1391 getfield (12, 4)
	1394 iload (12, 4)
	1396 invokevirtual (12, 4)
	1399 dmul (12, 4)
	1400 dstore (12, 4)
	1402 iconst_0 (13, 4)
	1403 istore (13, 4)
	1405 iload (13, 4)
	1407 iload (13, 4)
	1409 if_icmpge (13, 4)
	1412 dload (13, 4)
	1414 aload_0 (13, 4)
	1415 getfield (13, 4)
	1418 iload (13, 4)
	1420 invokevirtual (13, 4)
	1423 aload_0 (13, 4)
	1424 getfield (13, 4)
	1427 iload (13, 4)
	1429 iload (13, 4)
	1431 invokevirtual (13, 4)
	1434 dmul (13, 4)
	1435 dadd (13, 4)
	1436 dstore (13, 4)
	1438 iinc (13, 4)
	1441 goto (13, 4)
	1444 aload (12, 4)
	1446 iload (12, 4)
	1448 dload (12, 4)
	1450 invokevirtual (12, 4)
	1453 iconst_0 (13, 4)
	1454 istore (13, 4)
	1456 iload (13, 4)
	1458 iload (13, 4)
	1460 if_icmpge (13, 4)
	1463 aload_0 (13, 4)
	1464 getfield (13, 4)
	1467 iload (13, 4)
	1469 iload (13, 4)
	1471 aload_0 (13, 4)
	1472 getfield (13, 4)
	1475 iload (13, 4)
	1477 iload (13, 4)
	1479 invokevirtual (13, 4)
	1482 dload (13, 4)
	1484 aload_0 (13, 4)
	1485 getfield (13, 4)
	1488 iload (13, 4)
	1490 iload (13, 4)
	1492 invokevirtual (13, 4)
	1495 dmul (13, 4)
	1496 dadd (13, 4)
	1497 invokevirtual (13, 4)
	1500 iinc (13, 4)
	1503 goto (13, 4)
	1506 iinc (13, 4)
	1509 goto (13, 4)
	1512 iconst_0 (13, 4)
	1513 istore (13, 4)
	1515 iload (13, 4)
	1517 iload_3 (13, 4)
	1518 if_icmpge (13, 4)
	1521 iload (13, 4)
	1523 iload (13, 4)
	1525 iadd (13, 4)
	1526 istore (13, 4)
	1528 aload (13, 4)
	1530 iload (13, 4)
	1532 invokevirtual (13, 4)
	1535 dstore (13, 4)
	1537 iconst_0 (14, 4)
	1538 istore (14, 4)
	1540 iload (14, 4)
	1542 iload (14, 4)
	1544 if_icmpgt (14, 4)
	1547 aload_0 (14, 4)
	1548 getfield (14, 4)
	1551 iload (14, 4)
	1553 iload (14, 4)
	1555 aload_0 (14, 4)
	1556 getfield (14, 4)
	1559 iload (14, 4)
	1561 iload (14, 4)
	1563 invokevirtual (14, 4)
	1566 dload (14, 4)
	1568 aload (14, 4)
	1570 iload (14, 4)
	1572 invokevirtual (14, 4)
	1575 dmul (14, 4)
	1576 dadd (14, 4)
	1577 invokevirtual (14, 4)
	1580 iinc (14, 4)
	1583 goto (14, 4)
	1586 iinc (14, 4)
	1589 goto (14, 4)
	1592 iinc (14, 4)
	1595 goto (14, 4)
	1598 iconst_0 (13, 1)
	1599 istore (13, 1)
	1601 iconst_0 (14, 4)
	1602 istore (14, 4)
	1604 iload (14, 4)
	1606 iload_3 (14, 4)
	1607 if_icmpge (14, 4)
	1610 aload (14, 4)
	1612 iload (14, 4)
	1614 ldc2_w (14, 4)
	1617 dload (14, 4)
	1619 dmul (14, 4)
	1620 aload_0 (14, 4)
	1621 getfield (14, 4)
	1624 iload (14, 4)
	1626 invokevirtual (14, 4)
	1629 dmul (14, 4)
	1630 invokevirtual (14, 4)
	1633 iconst_0 (15, 4)
	1634 istore (15, 4)
	1636 iload (15, 4)
	1638 iload (15, 4)
	1640 if_icmpge (15, 4)
	1643 aload (15, 4)
	1645 iload (15, 4)
	1647 aload (15, 4)
	1649 iload (15, 4)
	1651 invokevirtual (15, 4)
	1654 aload_0 (15, 4)
	1655 getfield (15, 4)
	1658 iload (15, 4)
	1660 invokevirtual (15, 4)
	1663 aload_0 (15, 4)
	1664 getfield (15, 4)
	1667 iload (15, 4)
	1669 iload (15, 4)
	1671 invokevirtual (15, 4)
	1674 dmul (15, 4)
	1675 dadd (15, 4)
	1676 invokevirtual (15, 4)
	1679 aload_0 (15, 4)
	1680 getfield (15, 4)
	1683 iload (15, 4)
	1685 iload (15, 4)
	1687 aload_0 (15, 4)
	1688 getfield (15, 4)
	1691 iload (15, 4)
	1693 iload (15, 4)
	1695 invokevirtual (15, 4)
	1698 aload_0 (15, 4)
	1699 getfield (15, 4)
	1702 iload (15, 4)
	1704 invokevirtual (15, 4)
	1707 dsub (15, 4)
	1708 invokevirtual (15, 4)
	1711 iinc (15, 4)
	1714 goto (15, 4)
	1717 iconst_0 (15, 4)
	1718 istore (15, 4)
	1720 iload (15, 4)
	1722 iload (15, 4)
	1724 if_icmpgt (15, 4)
	1727 aload_0 (15, 4)
	1728 getfield (15, 4)
	1731 iload (15, 4)
	1733 aload_0 (15, 4)
	1734 getfield (15, 4)
	1737 iload (15, 4)
	1739 invokevirtual (15, 4)
	1742 aload (15, 4)
	1744 iload (15, 4)
	1746 invokevirtual (15, 4)
	1749 aload_0 (15, 4)
	1750 getfield (15, 4)
	1753 iload (15, 4)
	1755 invokevirtual (15, 4)
	1758 dmul (15, 4)
	1759 dadd (15, 4)
	1760 aload_0 (15, 4)
	1761 getfield (15, 4)
	1764 iload (15, 4)
	1766 invokevirtual (15, 4)
	1769 aload (15, 4)
	1771 iload (15, 4)
	1773 invokevirtual (15, 4)
	1776 dmul (15, 4)
	1777 dadd (15, 4)
	1778 invokevirtual (15, 4)
	1781 aload_0 (15, 4)
	1782 getfield (15, 4)
	1785 iload (15, 4)
	1787 iload (15, 4)
	1789 iadd (15, 4)
	1790 iload (15, 4)
	1792 aload_0 (15, 4)
	1793 getfield (15, 4)
	1796 iload (15, 4)
	1798 iload (15, 4)
	1800 iadd (15, 4)
	1801 iload (15, 4)
	1803 invokevirtual (15, 4)
	1806 invokevirtual (15, 4)
	1809 iinc (15, 4)
	1812 iinc (15, 4)
	1815 goto (15, 4)
	1818 iinc (15, 4)
	1821 goto (15, 4)
	1824 iconst_0 (15, 4)
	1825 istore (15, 4)
	1827 iload (15, 4)
	1829 iload_3 (15, 4)
	1830 if_icmpge (15, 4)
	1833 aload_0 (15, 1)
	1834 getfield (15, 1)
	1837 iload (15, 1)
	1839 aload_0 (15, 1)
	1840 getfield (15, 1)
	1843 iload (15, 1)
	1845 invokevirtual (15, 1)
	1848 aload_0 (15, 1)
	1849 getfield (15, 1)
	1852 iload (15, 1)
	1854 invokevirtual (15, 1)
	1857 dadd (15, 1)
	1858 invokevirtual (15, 1)
	1861 aload_0 (15, 1)
	1862 getfield (15, 1)
	1865 iload (15, 1)
	1867 aload_0 (15, 1)
	1868 getfield (15, 1)
	1871 iload (15, 1)
	1873 invokevirtual (15, 1)
	1876 aload_0 (15, 1)
	1877 getfield (15, 1)
	1880 iload (15, 1)
	1882 invokevirtual (15, 1)
	1885 dsub (15, 1)
	1886 invokevirtual (15, 1)
	1889 aload_0 (15, 1)
	1890 getfield (15, 1)
	1893 iload (15, 1)
	1895 aload_0 (15, 1)
	1896 getfield (15, 1)
	1899 iload (15, 1)
	1901 invokevirtual (15, 1)
	1904 aload_0 (15, 1)
	1905 getfield (15, 1)
	1908 iload (15, 1)
	1910 invokevirtual (15, 1)
	1913 dsub (15, 1)
	1914 invokevirtual (15, 1)
	1917 aload_0 (15, 1)
	1918 getfield (15, 1)
	1921 iload (15, 1)
	1923 aload_0 (15, 1)
	1924 getfield (15, 1)
	1927 iload (15, 1)
	1929 invokevirtual (15, 1)
	1932 aload_0 (15, 1)
	1933 getfield (15, 1)
	1936 iload (15, 1)
	1938 invokevirtual (15, 1)
	1941 dsub (15, 1)
	1942 invokevirtual (15, 1)
	1945 aload_0 (15, 1)
	1946 getfield (15, 1)
	1949 iload (15, 1)
	1951 dconst_0 (15, 1)
	1952 invokevirtual (15, 1)
	1955 iinc (15, 1)
	1958 goto (15, 1)
	1961 dconst_0 (14, 1)
	1962 dstore (14, 1)
	1964 iload (14, 1)
	1966 ifne (14, 1)
	1969 sipush (14, 1)
	1972 istore (14, 1)
	1974 goto (14, 1)
	1977 sipush (13, 1)
	1980 istore (13, 1)
	1982 goto (13, 1)
	1985 sipush (13, 1)
	1988 invokestatic (13, 1)
	1991 aload_0 (13, 1)
	1992 iload (13, 1)
	1994 dload (13, 1)
	1996 invokespecial (13, 1)
	1999 astore (13, 1)
	2001 aload (13, 1)
	2003 iconst_0 (13, 1)
	2004 daload (13, 1)
	2005 dstore (13, 1)
	2007 aload (13, 1)
	2009 iconst_1 (13, 1)
	2010 daload (13, 1)
	2011 dstore (13, 1)
	2013 iconst_0 (14, 4)
	2014 istore (14, 4)
	2016 iload (14, 4)
	2018 iload_3 (14, 4)
	2019 if_icmpge (14, 4)
	2022 aload_0 (14, 4)
	2023 getfield (14, 4)
	2026 iload (14, 4)
	2028 aload_0 (14, 4)
	2029 getfield (14, 4)
	2032 iload (14, 4)
	2034 invokevirtual (14, 4)
	2037 aload_0 (14, 4)
	2038 getfield (14, 4)
	2041 iload (14, 4)
	2043 invokevirtual (14, 4)
	2046 dsub (14, 4)
	2047 invokevirtual (14, 4)
	2050 iinc (14, 4)
	2053 goto (14, 4)
	2056 sipush (13, 4)
	2059 invokestatic (13, 4)
	2062 iconst_0 (14, 4)
	2063 istore (14, 4)
	2065 iload (14, 4)
	2067 iload (14, 4)
	2069 if_icmpge (14, 4)
	2072 dconst_0 (14, 4)
	2073 dstore (14, 4)
	2075 dconst_0 (14, 4)
	2076 dstore (14, 4)
	2078 dconst_0 (14, 4)
	2079 dstore (14, 4)
	2081 iconst_0 (15, 4)
	2082 istore (15, 4)
	2084 iload (15, 4)
	2086 iload_3 (15, 4)
	2087 if_icmpge (15, 4)
	2090 dload (15, 4)
	2092 aload_0 (15, 4)
	2093 getfield (15, 4)
	2096 iload (15, 4)
	2098 iload (15, 4)
	2100 invokevirtual (15, 4)
	2103 aload_0 (15, 4)
	2104 getfield (15, 4)
	2107 iload (15, 4)
	2109 invokevirtual (15, 4)
	2112 dmul (15, 4)
	2113 dadd (15, 4)
	2114 dstore (15, 4)
	2116 dload (15, 4)
	2118 aload_0 (15, 4)
	2119 getfield (15, 4)
	2122 iload (15, 4)
	2124 iload (15, 4)
	2126 invokevirtual (15, 4)
	2129 aload_0 (15, 4)
	2130 getfield (15, 4)
	2133 iload (15, 4)
	2135 invokevirtual (15, 4)
	2138 dmul (15, 4)
	2139 dadd (15, 4)
	2140 dstore (15, 4)
	2142 dload (15, 4)
	2144 aload_0 (15, 4)
	2145 getfield (15, 4)
	2148 iload (15, 4)
	2150 iload (15, 4)
	2152 invokevirtual (15, 4)
	2155 aload_0 (15, 4)
	2156 getfield (15, 4)
	2159 iload (15, 4)
	2161 invokevirtual (15, 4)
	2164 dmul (15, 4)
	2165 dadd (15, 4)
	2166 dstore (15, 4)
	2168 iinc (15, 4)
	2171 goto (15, 4)
	2174 aload (14, 4)
	2176 iload (14, 4)
	2178 dload (14, 4)
	2180 ldc2_w (14, 4)
	2183 dload (14, 4)
	2185 dmul (14, 4)
	2186 dload (14, 4)
	2188 dadd (14, 4)
	2189 dmul (14, 4)
	2190 invokevirtual (14, 4)
	2193 aload_0 (14, 4)
	2194 getfield (14, 4)
	2197 iload (14, 4)
	2199 dload (14, 4)
	2201 invokevirtual (14, 4)
	2204 aload (14, 4)
	2206 iload (14, 4)
	2208 dload (14, 4)
	2210 invokevirtual (14, 4)
	2213 iinc (14, 4)
	2216 goto (14, 4)
	2219 dconst_0 (13, 4)
	2220 dstore (13, 4)
	2222 iconst_0 (14, 4)
	2223 istore (14, 4)
	2225 iload (14, 4)
	2227 iload (14, 4)
	2229 if_icmpge (14, 4)
	2232 dconst_0 (14, 4)
	2233 dstore (14, 4)
	2235 iconst_0 (15, 4)
	2236 istore (15, 4)
	2238 iload (15, 4)
	2240 iload (15, 4)
	2242 if_icmpge (15, 4)
	2245 dload (15, 4)
	2247 aload_0 (15, 4)
	2248 getfield (15, 4)
	2251 iload (15, 4)
	2253 iload (15, 4)
	2255 invokevirtual (15, 4)
	2258 aload (15, 4)
	2260 iload (15, 4)
	2262 invokevirtual (15, 4)
	2265 dmul (15, 4)
	2266 dadd (15, 4)
	2267 dstore (15, 4)
	2269 iinc (15, 4)
	2272 goto (15, 4)
	2275 dload (14, 4)
	2277 dload (14, 4)
	2279 dload (14, 4)
	2281 dmul (14, 4)
	2282 dsub (14, 4)
	2283 dstore (14, 4)
	2285 iconst_0 (15, 4)
	2286 istore (15, 4)
	2288 iload (15, 4)
	2290 iload (15, 4)
	2292 if_icmpge (15, 4)
	2295 aload_0 (15, 4)
	2296 getfield (15, 4)
	2299 iload (15, 4)
	2301 aload_0 (15, 4)
	2302 getfield (15, 4)
	2305 iload (15, 4)
	2307 invokevirtual (15, 4)
	2310 dload (15, 4)
	2312 aload_0 (15, 4)
	2313 getfield (15, 4)
	2316 iload (15, 4)
	2318 iload (15, 4)
	2320 invokevirtual (15, 4)
	2323 dmul (15, 4)
	2324 dadd (15, 4)
	2325 invokevirtual (15, 4)
	2328 iinc (15, 4)
	2331 goto (15, 4)
	2334 iinc (15, 4)
	2337 goto (15, 4)
	2340 dconst_0 (14, 4)
	2341 dstore (14, 4)
	2343 dconst_0 (14, 4)
	2344 dstore (14, 4)
	2346 dconst_0 (14, 4)
	2347 dstore (14, 4)
	2349 iconst_0 (15, 4)
	2350 istore (15, 4)
	2352 iload (15, 4)
	2354 iload_3 (15, 4)
	2355 if_icmpge (15, 4)
	2358 aload_0 (15, 4)
	2359 getfield (15, 4)
	2362 iload (15, 4)
	2364 invokevirtual (15, 4)
	2367 dstore (15, 4)
	2369 dload (15, 4)
	2371 dload (15, 4)
	2373 dload (15, 4)
	2375 dmul (15, 4)
	2376 dadd (15, 4)
	2377 dstore (15, 4)
	2379 dconst_0 (15, 4)
	2380 dstore (15, 4)
	2382 iconst_0 (16, 4)
	2383 istore (16, 4)
	2385 iload (16, 4)
	2387 iload (16, 4)
	2389 if_icmpge (16, 4)
	2392 dload (16, 4)
	2394 aload (16, 4)
	2396 iload (16, 4)
	2398 invokevirtual (16, 4)
	2401 aload_0 (16, 4)
	2402 getfield (16, 4)
	2405 iload (16, 4)
	2407 iload (16, 4)
	2409 invokevirtual (16, 4)
	2412 dmul (16, 4)
	2413 dadd (16, 4)
	2414 dstore (16, 4)
	2416 iinc (16, 4)
	2419 goto (16, 4)
	2422 dload (15, 4)
	2424 dload (15, 4)
	2426 aload_0 (15, 4)
	2427 getfield (15, 4)
	2430 iload (15, 4)
	2432 invokevirtual (15, 4)
	2435 dmul (15, 4)
	2436 dadd (15, 4)
	2437 dstore (15, 4)
	2439 iload (15, 4)
	2441 iload (15, 4)
	2443 iadd (15, 4)
	2444 istore (15, 4)
	2446 iconst_0 (16, 4)
	2447 istore (16, 4)
	2449 iload (16, 4)
	2451 iload_3 (16, 4)
	2452 if_icmpge (16, 4)
	2455 dload (16, 4)
	2457 aload_0 (16, 4)
	2458 getfield (16, 4)
	2461 iload (16, 4)
	2463 iload (16, 4)
	2465 invokevirtual (16, 4)
	2468 aload_0 (16, 4)
	2469 getfield (16, 4)
	2472 iload (16, 4)
	2474 invokevirtual (16, 4)
	2477 dmul (16, 4)
	2478 dadd (16, 4)
	2479 dstore (16, 4)
	2481 iinc (16, 4)
	2484 goto (16, 4)
	2487 aload_0 (15, 4)
	2488 getfield (15, 4)
	2491 iload (15, 4)
	2493 dload (15, 4)
	2495 invokevirtual (15, 4)
	2498 dload (15, 4)
	2500 dload (15, 4)
	2502 aload_0 (15, 4)
	2503 getfield (15, 4)
	2506 iload (15, 4)
	2508 invokevirtual (15, 4)
	2511 dmul (15, 4)
	2512 dadd (15, 4)
	2513 dstore (15, 4)
	2515 dload (15, 4)
	2517 aload_0 (15, 4)
	2518 getfield (15, 4)
	2521 iload (15, 4)
	2523 invokevirtual (15, 4)
	2526 aload_0 (15, 4)
	2527 getfield (15, 4)
	2530 iload (15, 4)
	2532 invokevirtual (15, 4)
	2535 dmul (15, 4)
	2536 dadd (15, 4)
	2537 dstore (15, 4)
	2539 iinc (15, 4)
	2542 goto (15, 4)
	2545 dload (14, 4)
	2547 dload (14, 4)
	2549 dmul (14, 4)
	2550 dload (14, 4)
	2552 dload (14, 4)
	2554 dload (14, 4)
	2556 dadd (14, 4)
	2557 dload (14, 4)
	2559 dadd (14, 4)
	2560 ldc2_w (14, 4)
	2563 dload (14, 4)
	2565 dmul (14, 4)
	2566 dadd (14, 4)
	2567 dmul (14, 4)
	2568 dadd (14, 4)
	2569 dload (14, 4)
	2571 dadd (14, 4)
	2572 dload (14, 4)
	2574 dsub (14, 4)
	2575 dstore (14, 4)
	2577 aload_0 (14, 1)
	2578 getfield (14, 1)
	2581 aload_0 (14, 1)
	2582 getfield (14, 1)
	2585 aload_0 (14, 1)
	2586 getfield (14, 1)
	2589 aload_0 (14, 1)
	2590 getfield (14, 1)
	2593 invokevirtual (14, 1)
	2596 dconst_1 (14, 1)
	2597 dadd (14, 1)
	2598 invokevirtual (14, 1)
	2601 iload (15, 1)
	2603 ifne (15, 1)
	2606 aload_0 (15, 1)
	2607 getfield (15, 1)
	2610 iload (15, 1)
	2612 invokevirtual (15, 1)
	2615 dstore (15, 1)
	2617 dload (15, 1)
	2619 dload (15, 1)
	2621 dmul (15, 1)
	2622 dload (15, 1)
	2624 dload (15, 1)
	2626 dmul (15, 1)
	2627 dadd (15, 1)
	2628 dstore (15, 1)
	2630 dload (16, 1)
	2632 dload (16, 1)
	2634 dcmpg (16, 1)
	2635 ifge (16, 1)
	2638 dload (16, 1)
	2640 dconst_0 (16, 1)
	2641 dcmpl (16, 1)
	2642 ifle (16, 1)
	2645 iconst_0 (17, 4)
	2646 istore (17, 4)
	2648 iload (17, 4)
	2650 iload_3 (17, 4)
	2651 if_icmpge (17, 4)
	2654 aload_0 (17, 4)
	2655 getfield (17, 4)
	2658 iload (17, 4)
	2660 aload_0 (17, 4)
	2661 getfield (17, 4)
	2664 iload (17, 4)
	2666 invokevirtual (17, 4)
	2669 invokevirtual (17, 4)
	2672 aload_0 (17, 4)
	2673 getfield (17, 4)
	2676 iload (17, 4)
	2678 aload_0 (17, 4)
	2679 getfield (17, 4)
	2682 iload (17, 4)
	2684 invokevirtual (17, 4)
	2687 aload_0 (17, 4)
	2688 getfield (17, 4)
	2691 iload (17, 4)
	2693 invokevirtual (17, 4)
	2696 dsub (17, 4)
	2697 invokevirtual (17, 4)
	2700 iinc (17, 4)
	2703 goto (17, 4)
	2706 dconst_0 (16, 1)
	2707 dstore (16, 1)
	2709 sipush (16, 1)
	2712 istore (16, 1)
	2714 goto (16, 1)
	2717 goto (15, 2)
	2720 dload (15, 2)
	2722 dload (15, 2)
	2724 dmul (15, 2)
	2725 dstore (15, 2)
	2727 dconst_0 (15, 2)
	2728 dstore (15, 2)
	2730 dconst_0 (15, 2)
	2731 dstore (15, 2)
	2733 iconst_0 (15, 2)
	2734 istore (15, 2)
	2736 iconst_0 (16, 4)
	2737 istore (16, 4)
	2739 iload (16, 4)
	2741 iload (16, 4)
	2743 if_icmpge (16, 4)
	2746 iload (17, 1)
	2748 aload_0 (17, 1)
	2749 getfield (17, 1)
	2752 if_icmpne (17, 1)
	2755 goto (17, 1)
	2758 dconst_0 (16, 4)
	2759 dstore (16, 4)
	2761 iconst_0 (17, 4)
	2762 istore (17, 4)
	2764 iload (17, 4)
	2766 iload (17, 4)
	2768 if_icmpge (17, 4)
	2771 aload_0 (17, 4)
	2772 getfield (17, 4)
	2775 iload (17, 4)
	2777 iload (17, 4)
	2779 invokevirtual (17, 4)
	2782 dstore (17, 4)
	2784 dload (17, 4)
	2786 dload (17, 4)
	2788 dload (17, 4)
	2790 dmul (17, 4)
	2791 dadd (17, 4)
	2792 dstore (17, 4)
	2794 iinc (17, 4)
	2797 goto (17, 4)
	2800 aload_0 (16, 4)
	2801 getfield (16, 4)
	2804 iload (16, 4)
	2806 invokevirtual (16, 4)
	2809 dstore (16, 4)
	2811 dload (16, 4)
	2813 dload (16, 4)
	2815 dmul (16, 4)
	2816 dload (16, 4)
	2818 dload (16, 4)
	2820 dmul (16, 4)
	2821 dadd (16, 4)
	2822 dstore (16, 4)
	2824 dconst_0 (16, 4)
	2825 dstore (16, 4)
	2827 iconst_0 (17, 4)
	2828 istore (17, 4)
	2830 iload (17, 4)
	2832 iload_3 (17, 4)
	2833 if_icmpge (17, 4)
	2836 aload_0 (17, 4)
	2837 getfield (17, 4)
	2840 iload (17, 4)
	2842 iload (17, 4)
	2844 invokevirtual (17, 4)
	2847 aload_0 (17, 4)
	2848 getfield (17, 4)
	2851 iload (17, 4)
	2853 invokevirtual (17, 4)
	2856 dsub (17, 4)
	2857 dstore (17, 4)
	2859 dload (17, 4)
	2861 dload (17, 4)
	2863 dload (17, 4)
	2865 dmul (17, 4)
	2866 dadd (17, 4)
	2867 dstore (17, 4)
	2869 iinc (17, 4)
	2872 goto (17, 4)
	2875 dload (16, 4)
	2877 dload (16, 4)
	2879 ddiv (16, 4)
	2880 dstore (16, 4)
	2882 dconst_1 (16, 4)
	2883 dload (16, 4)
	2885 dload (16, 4)
	2887 dmul (16, 4)
	2888 invokestatic (16, 4)
	2891 dstore (16, 4)
	2893 dload (17, 1)
	2895 dload (17, 1)
	2897 dmul (17, 1)
	2898 dload (17, 1)
	2900 dcmpl (17, 1)
	2901 ifle (17, 1)
	2904 dload (17, 1)
	2906 dload (17, 1)
	2908 dmul (17, 1)
	2909 dstore (17, 1)
	2911 iload (17, 1)
	2913 istore (17, 1)
	2915 dload (17, 1)
	2917 dstore (17, 1)
	2919 aload_0 (16, 4)
	2920 getfield (16, 4)
	2923 iload (16, 4)
	2925 invokevirtual (16, 4)
	2928 dstore (16, 4)
	2930 dload (16, 4)
	2932 dload (16, 4)
	2934 dload (16, 4)
	2936 dload (16, 4)
	2938 dmul (16, 4)
	2939 dmul (16, 4)
	2940 invokestatic (16, 4)
	2943 dstore (16, 4)
	2945 iinc (16, 4)
	2948 goto (16, 4)
	2951 sipush (14, 4)
	2954 invokestatic (14, 4)
	2957 iconst_0 (15, 4)
	2958 istore (15, 4)
	2960 iload (15, 4)
	2962 iload_3 (15, 4)
	2963 if_icmpge (15, 4)
	2966 aload_1 (15, 4)
	2967 iload (15, 4)
	2969 daload (15, 4)
	2970 dstore (15, 4)
	2972 aload_0 (15, 1)
	2973 getfield (15, 1)
	2976 iload (15, 1)
	2978 invokevirtual (15, 1)
	2981 aload_0 (15, 1)
	2982 getfield (15, 1)
	2985 iload (15, 1)
	2987 invokevirtual (15, 1)
	2990 dadd (15, 1)
	2991 dstore (15, 1)
	2993 dload (15, 1)
	2995 dload (15, 1)
	2997 invokestatic (15, 1)
	3000 dstore (15, 1)
	3002 aload_2 (15, 1)
	3003 iload (15, 1)
	3005 daload (15, 1)
	3006 dstore (15, 1)
	3008 aload_0 (15, 1)
	3009 getfield (15, 1)
	3012 iload (15, 1)
	3014 dload (15, 1)
	3016 dload (15, 1)
	3018 invokestatic (15, 1)
	3021 invokevirtual (15, 1)
	3024 aload_0 (16, 1)
	3025 getfield (16, 1)
	3028 iload (16, 1)
	3030 invokevirtual (16, 1)
	3033 aload_0 (16, 1)
	3034 getfield (16, 1)
	3037 iload (16, 1)
	3039 invokevirtual (16, 1)
	3042 dcmpl (16, 1)
	3043 ifne (16, 1)
	3046 aload_0 (16, 1)
	3047 getfield (16, 1)
	3050 iload (16, 1)
	3052 aload_1 (16, 1)
	3053 iload (16, 1)
	3055 daload (16, 1)
	3056 invokevirtual (16, 1)
	3059 aload_0 (16, 1)
	3060 getfield (16, 1)
	3063 iload (16, 1)
	3065 invokevirtual (16, 1)
	3068 aload_0 (16, 1)
	3069 getfield (16, 1)
	3072 iload (16, 1)
	3074 invokevirtual (16, 1)
	3077 dcmpl (16, 1)
	3078 ifne (16, 1)
	3081 aload_0 (16, 1)
	3082 getfield (16, 1)
	3085 iload (16, 1)
	3087 aload_2 (16, 1)
	3088 iload (16, 1)
	3090 daload (16, 1)
	3091 invokevirtual (16, 1)
	3094 iinc (16, 1)
	3097 goto (16, 1)
	3100 aload_0 (15, 1)
	3101 aload_0 (15, 1)
	3102 getfield (15, 1)
	3105 invokevirtual (15, 1)
	3108 invokevirtual (15, 1)
	3111 dstore (15, 1)
	3113 aload_0 (16, 1)
	3114 getfield (16, 1)
	3117 ifne (16, 1)
	3120 dload (16, 1)
	3122 dneg (16, 1)
	3123 dstore (16, 1)
	3125 iload (16, 1)
	3127 iconst_m1 (16, 1)
	3128 if_icmpne (16, 1)
	3131 dload (16, 1)
	3133 dstore (16, 1)
	3135 sipush (16, 1)
	3138 istore (16, 1)
	3140 goto (16, 1)
	3143 aload_0 (15, 1)
	3144 getfield (15, 1)
	3147 aload_0 (15, 1)
	3148 getfield (15, 1)
	3151 invokevirtual (15, 1)
	3154 dstore (15, 1)
	3156 dconst_0 (15, 1)
	3157 dstore (15, 1)
	3159 iconst_0 (15, 1)
	3160 istore (15, 1)
	3162 iconst_0 (16, 4)
	3163 istore (16, 4)
	3165 iload (16, 4)
	3167 iload_3 (16, 4)
	3168 if_icmpge (16, 4)
	3171 dload (16, 4)
	3173 aload_0 (16, 4)
	3174 getfield (16, 4)
	3177 iload (16, 4)
	3179 invokevirtual (16, 4)
	3182 aload_0 (16, 4)
	3183 getfield (16, 4)
	3186 iload (16, 4)
	3188 invokevirtual (16, 4)
	3191 dmul (16, 4)
	3192 dadd (16, 4)
	3193 dstore (16, 4)
	3195 iconst_0 (17, 4)
	3196 istore (17, 4)
	3198 iload (17, 4)
	3200 iload (17, 4)
	3202 if_icmpgt (17, 4)
	3205 aload_0 (17, 4)
	3206 getfield (17, 4)
	3209 iload (17, 4)
	3211 invokevirtual (17, 4)
	3214 aload_0 (17, 4)
	3215 getfield (17, 4)
	3218 iload (17, 4)
	3220 invokevirtual (17, 4)
	3223 dmul (17, 4)
	3224 dstore (17, 4)
	3226 iload (18, 1)
	3228 iload (18, 1)
	3230 if_icmpne (18, 1)
	3233 dload (18, 1)
	3235 ldc2_w (18, 1)
	3238 dmul (18, 1)
	3239 dstore (18, 1)
	3241 dload (17, 4)
	3243 aload_0 (17, 4)
	3244 getfield (17, 4)
	3247 iload (17, 4)
	3249 invokevirtual (17, 4)
	3252 dload (17, 4)
	3254 dmul (17, 4)
	3255 dadd (17, 4)
	3256 dstore (17, 4)
	3258 iinc (17, 4)
	3261 iinc (17, 4)
	3264 goto (17, 4)
	3267 iinc (17, 4)
	3270 goto (17, 4)
	3273 iconst_0 (17, 4)
	3274 istore (17, 4)
	3276 iload (17, 4)
	3278 iload (17, 4)
	3280 if_icmpge (17, 4)
	3283 aload (17, 4)
	3285 iload (17, 4)
	3287 invokevirtual (17, 4)
	3290 dstore (17, 4)
	3292 dload (17, 4)
	3294 dload (17, 4)
	3296 dmul (17, 4)
	3297 dstore (17, 4)
	3299 dload (17, 4)
	3301 ldc2_w (17, 4)
	3304 aload_0 (17, 4)
	3305 getfield (17, 4)
	3308 iload (17, 4)
	3310 invokevirtual (17, 4)
	3313 dmul (17, 4)
	3314 dload (17, 4)
	3316 dmul (17, 4)
	3317 dadd (17, 4)
	3318 dstore (17, 4)
	3320 iinc (17, 4)
	3323 goto (17, 4)
	3326 dload (16, 1)
	3328 dload (16, 1)
	3330 dsub (16, 1)
	3331 dload (16, 1)
	3333 dsub (16, 1)
	3334 dstore (16, 1)
	3336 dload (16, 1)
	3338 dstore (16, 1)
	3340 dload (16, 1)
	3342 dstore (16, 1)
	3344 dload (16, 1)
	3346 invokestatic (16, 1)
	3349 dstore (16, 1)
	3351 dload (17, 1)
	3353 dload (17, 1)
	3355 dcmpl (17, 1)
	3356 ifle (17, 1)
	3359 aload_0 (17, 1)
	3360 invokevirtual (17, 1)
	3363 istore (17, 1)
	3365 iload (17, 1)
	3367 ifle (17, 1)
	3370 dload (18, 1)
	3372 dconst_0 (18, 1)
	3373 dcmpl (18, 1)
	3374 iflt (18, 1)
	3377 new (18, 1)
	3380 dup (18, 1)
	3381 getstatic (18, 1)
	3384 iconst_1 (18, 1)
	3385 anewarray (18, 1)
	3388 dup (18, 1)
	3389 iconst_0 (18, 1)
	3390 dload (18, 1)
	3392 invokestatic (18, 1)
	3395 aastore (18, 1)
	3396 invokespecial (18, 1)
	3399 athrow (18, 1)
	3400 dload (17, 1)
	3402 dload (17, 1)
	3404 dsub (17, 1)
	3405 dload (17, 1)
	3407 ddiv (17, 1)
	3408 dstore (17, 1)
	3410 ldc2_w (17, 1)
	3413 dload (17, 1)
	3415 dmul (17, 1)
	3416 dstore (17, 1)
	3418 dload (18, 1)
	3420 ldc2_w (18, 1)
	3423 dcmpg (18, 1)
	3424 ifgt (18, 1)
	3427 dload (18, 1)
	3429 dload (18, 1)
	3431 invokestatic (18, 1)
	3434 dstore (18, 1)
	3436 goto (18, 1)
	3439 dload (18, 1)
	3441 ldc2_w (18, 1)
	3444 dcmpg (18, 1)
	3445 ifgt (18, 1)
	3448 dload (18, 1)
	3450 dload (18, 1)
	3452 invokestatic (18, 1)
	3455 dstore (18, 1)
	3457 goto (18, 1)
	3460 dload (18, 2)
	3462 ldc2_w (18, 2)
	3465 dload (18, 2)
	3467 dmul (18, 2)
	3468 invokestatic (18, 2)
	3471 dstore (18, 2)
	3473 dload (18, 1)
	3475 dload (18, 1)
	3477 ldc2_w (18, 1)
	3480 dmul (18, 1)
	3481 dcmpg (18, 1)
	3482 ifgt (18, 1)
	3485 dload (18, 1)
	3487 dstore (18, 1)
	3489 dload (18, 1)
	3491 dload (18, 1)
	3493 dcmpg (18, 1)
	3494 ifge (18, 1)
	3497 iload (18, 1)
	3499 istore (18, 1)
	3501 dload (18, 1)
	3503 dstore (18, 1)
	3505 dload (18, 1)
	3507 dload (18, 1)
	3509 dmul (18, 1)
	3510 dstore (18, 1)
	3512 dconst_0 (18, 1)
	3513 dstore (18, 1)
	3515 dconst_0 (18, 1)
	3516 dstore (18, 1)
	3518 iconst_0 (18, 1)
	3519 istore (18, 1)
	3521 iconst_0 (19, 4)
	3522 istore (19, 4)
	3524 iload (19, 4)
	3526 iload (19, 4)
	3528 if_icmpge (19, 4)
	3531 dconst_0 (19, 4)
	3532 dstore (19, 4)
	3534 iconst_0 (20, 4)
	3535 istore (20, 4)
	3537 iload (20, 4)
	3539 iload (20, 4)
	3541 if_icmpge (20, 4)
	3544 aload_0 (20, 4)
	3545 getfield (20, 4)
	3548 iload (20, 4)
	3550 iload (20, 4)
	3552 invokevirtual (20, 4)
	3555 dstore (20, 4)
	3557 dload (20, 4)
	3559 dload (20, 4)
	3561 dload (20, 4)
	3563 dmul (20, 4)
	3564 dadd (20, 4)
	3565 dstore (20, 4)
	3567 iinc (20, 4)
	3570 goto (20, 4)
	3573 aload_0 (19, 4)
	3574 getfield (19, 4)
	3577 iload (19, 4)
	3579 invokevirtual (19, 4)
	3582 dstore (19, 4)
	3584 dload (19, 4)
	3586 dload (19, 4)
	3588 dmul (19, 4)
	3589 dload (19, 4)
	3591 dload (19, 4)
	3593 dmul (19, 4)
	3594 dadd (19, 4)
	3595 dstore (19, 4)
	3597 dconst_0 (19, 4)
	3598 dstore (19, 4)
	3600 iconst_0 (20, 4)
	3601 istore (20, 4)
	3603 iload (20, 4)
	3605 iload_3 (20, 4)
	3606 if_icmpge (20, 4)
	3609 aload_0 (20, 4)
	3610 getfield (20, 4)
	3613 iload (20, 4)
	3615 iload (20, 4)
	3617 invokevirtual (20, 4)
	3620 aload_0 (20, 4)
	3621 getfield (20, 4)
	3624 iload (20, 4)
	3626 invokevirtual (20, 4)
	3629 dsub (20, 4)
	3630 dstore (20, 4)
	3632 dload (20, 4)
	3634 dload (20, 4)
	3636 dload (20, 4)
	3638 dmul (20, 4)
	3639 dadd (20, 4)
	3640 dstore (20, 4)
	3642 iinc (20, 4)
	3645 goto (20, 4)
	3648 dload (19, 4)
	3650 dload (19, 4)
	3652 ddiv (19, 4)
	3653 dstore (19, 4)
	3655 dconst_1 (19, 4)
	3656 dload (19, 4)
	3658 dload (19, 4)
	3660 dmul (19, 4)
	3661 invokestatic (19, 4)
	3664 dstore (19, 4)
	3666 dload (20, 1)
	3668 dload (20, 1)
	3670 dmul (20, 1)
	3671 dload (20, 1)
	3673 dcmpl (20, 1)
	3674 ifle (20, 1)
	3677 dload (20, 1)
	3679 dload (20, 1)
	3681 dmul (20, 1)
	3682 dstore (20, 1)
	3684 iload (20, 1)
	3686 istore (20, 1)
	3688 dload (20, 1)
	3690 dstore (20, 1)
	3692 aload_0 (19, 4)
	3693 getfield (19, 4)
	3696 iload (19, 4)
	3698 invokevirtual (19, 4)
	3701 dstore (19, 4)
	3703 dload (19, 4)
	3705 dload (19, 4)
	3707 dload (19, 4)
	3709 dmul (19, 4)
	3710 dmul (19, 4)
	3711 dstore (19, 4)
	3713 dload (19, 4)
	3715 dload (19, 4)
	3717 invokestatic (19, 4)
	3720 dstore (19, 4)
	3722 iinc (19, 4)
	3725 goto (19, 4)
	3728 dload (19, 1)
	3730 ldc2_w (19, 1)
	3733 dload (19, 1)
	3735 dmul (19, 1)
	3736 dcmpg (19, 1)
	3737 ifgt (19, 1)
	3740 iload (19, 1)
	3742 istore (19, 1)
	3744 dload (19, 1)
	3746 dstore (19, 1)
	3748 aload_0 (16, 1)
	3749 dload (16, 1)
	3751 dload (16, 1)
	3753 iload (16, 1)
	3755 invokespecial (16, 1)
	3758 iconst_0 (16, 1)
	3759 istore (16, 1)
	3761 aload_0 (16, 1)
	3762 getfield (16, 1)
	3765 iload (16, 1)
	3767 invokevirtual (16, 1)
	3770 dstore (16, 1)
	3772 aload_0 (16, 1)
	3773 getfield (16, 1)
	3776 iload (16, 1)
	3778 dconst_0 (16, 1)
	3779 invokevirtual (16, 1)
	3782 iconst_0 (17, 4)
	3783 istore (17, 4)
	3785 iload (17, 4)
	3787 iload_3 (17, 4)
	3788 if_icmpge (17, 4)
	3791 dload (17, 4)
	3793 aload_0 (17, 4)
	3794 getfield (17, 4)
	3797 iload (17, 4)
	3799 iload (17, 4)
	3801 invokevirtual (17, 4)
	3804 dmul (17, 4)
	3805 dstore (17, 4)
	3807 iconst_0 (18, 4)
	3808 istore (18, 4)
	3810 iload (18, 4)
	3812 iload (18, 4)
	3814 if_icmpgt (18, 4)
	3817 aload_0 (18, 4)
	3818 getfield (18, 4)
	3821 iload (18, 4)
	3823 aload_0 (18, 4)
	3824 getfield (18, 4)
	3827 iload (18, 4)
	3829 invokevirtual (18, 4)
	3832 dload (18, 4)
	3834 aload_0 (18, 4)
	3835 getfield (18, 4)
	3838 iload (18, 4)
	3840 iload (18, 4)
	3842 invokevirtual (18, 4)
	3845 dmul (18, 4)
	3846 dadd (18, 4)
	3847 invokevirtual (18, 4)
	3850 iinc (18, 4)
	3853 iinc (18, 4)
	3856 goto (18, 4)
	3859 iinc (18, 4)
	3862 goto (18, 4)
	3865 iconst_0 (18, 4)
	3866 istore (18, 4)
	3868 iload (18, 4)
	3870 iload (18, 4)
	3872 if_icmpge (18, 4)
	3875 dload (18, 1)
	3877 aload_0 (18, 1)
	3878 getfield (18, 1)
	3881 iload (18, 1)
	3883 iload (18, 1)
	3885 invokevirtual (18, 1)
	3888 dmul (18, 1)
	3889 dstore (18, 1)
	3891 iconst_0 (19, 4)
	3892 istore (19, 4)
	3894 iload (19, 4)
	3896 iload (19, 4)
	3898 if_icmpge (19, 4)
	3901 aload_0 (19, 4)
	3902 getfield (19, 4)
	3905 iload (19, 4)
	3907 aload_0 (19, 4)
	3908 getfield (19, 4)
	3911 iload (19, 4)
	3913 invokevirtual (19, 4)
	3916 dload (19, 4)
	3918 aload_0 (19, 4)
	3919 getfield (19, 4)
	3922 iload (19, 4)
	3924 iload (19, 4)
	3926 invokevirtual (19, 4)
	3929 dmul (19, 4)
	3930 dadd (19, 4)
	3931 invokevirtual (19, 4)
	3934 iinc (19, 4)
	3937 goto (19, 4)
	3940 iinc (19, 4)
	3943 goto (19, 4)
	3946 aload_0 (18, 4)
	3947 getfield (18, 4)
	3950 iload (18, 4)
	3952 dload (18, 4)
	3954 invokevirtual (18, 4)
	3957 iconst_0 (19, 4)
	3958 istore (19, 4)
	3960 iload (19, 4)
	3962 iload_3 (19, 4)
	3963 if_icmpge (19, 4)
	3966 aload_0 (19, 4)
	3967 getfield (19, 4)
	3970 iload (19, 4)
	3972 iload (19, 4)
	3974 aload_0 (19, 4)
	3975 getfield (19, 4)
	3978 iload (19, 4)
	3980 invokevirtual (19, 4)
	3983 invokevirtual (19, 4)
	3986 aload (19, 4)
	3988 iload (19, 4)
	3990 aload_0 (19, 4)
	3991 getfield (19, 4)
	3994 iload (19, 4)
	3996 iload (19, 4)
	3998 invokevirtual (19, 4)
	4001 invokevirtual (19, 4)
	4004 iinc (19, 4)
	4007 goto (19, 4)
	4010 iconst_0 (19, 4)
	4011 istore (19, 4)
	4013 iload (19, 4)
	4015 iload (19, 4)
	4017 if_icmpge (19, 4)
	4020 dconst_0 (19, 4)
	4021 dstore (19, 4)
	4023 iconst_0 (20, 4)
	4024 istore (20, 4)
	4026 iload (20, 4)
	4028 iload (20, 4)
	4030 if_icmpge (20, 4)
	4033 dload (20, 4)
	4035 aload_0 (20, 4)
	4036 getfield (20, 4)
	4039 iload (20, 4)
	4041 iload (20, 4)
	4043 invokevirtual (20, 4)
	4046 aload_0 (20, 4)
	4047 getfield (20, 4)
	4050 iload (20, 4)
	4052 iload (20, 4)
	4054 invokevirtual (20, 4)
	4057 dmul (20, 4)
	4058 dadd (20, 4)
	4059 dstore (20, 4)
	4061 iinc (20, 4)
	4064 goto (20, 4)
	4067 dconst_0 (19, 4)
	4068 dstore (19, 4)
	4070 iconst_0 (20, 4)
	4071 istore (20, 4)
	4073 iload (20, 4)
	4075 iload_3 (20, 4)
	4076 if_icmpge (20, 4)
	4079 dload (20, 4)
	4081 aload_0 (20, 4)
	4082 getfield (20, 4)
	4085 iload (20, 4)
	4087 iload (20, 4)
	4089 invokevirtual (20, 4)
	4092 aload_0 (20, 4)
	4093 getfield (20, 4)
	4096 iload (20, 4)
	4098 invokevirtual (20, 4)
	4101 dmul (20, 4)
	4102 dadd (20, 4)
	4103 dstore (20, 4)
	4105 iinc (20, 4)
	4108 goto (20, 4)
	4111 dload (19, 4)
	4113 dload (19, 4)
	4115 dmul (19, 4)
	4116 dstore (19, 4)
	4118 iconst_0 (20, 4)
	4119 istore (20, 4)
	4121 iload (20, 4)
	4123 iload_3 (20, 4)
	4124 if_icmpge (20, 4)
	4127 aload (20, 4)
	4129 iload (20, 4)
	4131 aload (20, 4)
	4133 iload (20, 4)
	4135 invokevirtual (20, 4)
	4138 dload (20, 4)
	4140 aload_0 (20, 4)
	4141 getfield (20, 4)
	4144 iload (20, 4)
	4146 iload (20, 4)
	4148 invokevirtual (20, 4)
	4151 dmul (20, 4)
	4152 dadd (20, 4)
	4153 invokevirtual (20, 4)
	4156 iinc (20, 4)
	4159 goto (20, 4)
	4162 iinc (20, 4)
	4165 goto (20, 4)
	4168 iconst_0 (20, 4)
	4169 istore (20, 4)
	4171 iload (20, 4)
	4173 iload_3 (20, 4)
	4174 if_icmpge (20, 4)
	4177 aload_0 (20, 1)
	4178 getfield (20, 1)
	4181 iload (20, 1)
	4183 aload_0 (20, 1)
	4184 getfield (20, 1)
	4187 iload (20, 1)
	4189 invokevirtual (20, 1)
	4192 dload (20, 1)
	4194 aload (20, 1)
	4196 iload (20, 1)
	4198 invokevirtual (20, 1)
	4201 dmul (20, 1)
	4202 dadd (20, 1)
	4203 invokevirtual (20, 1)
	4206 iinc (20, 1)
	4209 goto (20, 1)
	4212 dload (20, 1)
	4214 dload (20, 1)
	4216 dcmpg (20, 1)
	4217 ifge (20, 1)
	4220 aload_0 (20, 1)
	4221 iload (20, 1)
	4223 putfield (20, 1)
	4226 dconst_0 (20, 1)
	4227 dstore (20, 1)
	4229 iconst_0 (20, 1)
	4230 istore (20, 1)
	4232 iconst_0 (21, 4)
	4233 istore (21, 4)
	4235 iload (21, 4)
	4237 iload_3 (21, 4)
	4238 if_icmpge (21, 4)
	4241 aload_0 (21, 4)
	4242 getfield (21, 4)
	4245 iload (21, 4)
	4247 aload_0 (21, 4)
	4248 getfield (21, 4)
	4251 iload (21, 4)
	4253 invokevirtual (21, 4)
	4256 invokevirtual (21, 4)
	4259 aload_0 (21, 4)
	4260 getfield (21, 4)
	4263 iload (21, 4)
	4265 invokevirtual (21, 4)
	4268 dstore (21, 4)
	4270 dload (21, 4)
	4272 dload (21, 4)
	4274 dload (21, 4)
	4276 dmul (21, 4)
	4277 dadd (21, 4)
	4278 dstore (21, 4)
	4280 iconst_0 (22, 4)
	4281 istore (22, 4)
	4283 iload (22, 4)
	4285 iload (22, 4)
	4287 if_icmpgt (22, 4)
	4290 iload (23, 1)
	4292 iload (23, 1)
	4294 if_icmpge (23, 1)
	4297 aload_0 (23, 1)
	4298 getfield (23, 1)
	4301 iload (23, 1)
	4303 aload_0 (23, 1)
	4304 getfield (23, 1)
	4307 iload (23, 1)
	4309 invokevirtual (23, 1)
	4312 aload_0 (23, 1)
	4313 getfield (23, 1)
	4316 iload (23, 1)
	4318 invokevirtual (23, 1)
	4321 aload_0 (23, 1)
	4322 getfield (23, 1)
	4325 iload (23, 1)
	4327 invokevirtual (23, 1)
	4330 dmul (23, 1)
	4331 dadd (23, 1)
	4332 invokevirtual (23, 1)
	4335 aload_0 (22, 4)
	4336 getfield (22, 4)
	4339 iload (22, 4)
	4341 aload_0 (22, 4)
	4342 getfield (22, 4)
	4345 iload (22, 4)
	4347 invokevirtual (22, 4)
	4350 aload_0 (22, 4)
	4351 getfield (22, 4)
	4354 iload (22, 4)
	4356 invokevirtual (22, 4)
	4359 aload_0 (22, 4)
	4360 getfield (22, 4)
	4363 iload (22, 4)
	4365 invokevirtual (22, 4)
	4368 dmul (22, 4)
	4369 dadd (22, 4)
	4370 invokevirtual (22, 4)
	4373 iinc (22, 4)
	4376 iinc (22, 4)
	4379 goto (22, 4)
	4382 iinc (22, 4)
	4385 goto (22, 4)
	4388 iconst_0 (22, 4)
	4389 istore (22, 4)
	4391 iload (22, 4)
	4393 iload (22, 4)
	4395 if_icmpge (22, 4)
	4398 dconst_0 (22, 4)
	4399 dstore (22, 4)
	4401 iconst_0 (23, 4)
	4402 istore (23, 4)
	4404 iload (23, 4)
	4406 iload_3 (23, 4)
	4407 if_icmpge (23, 4)
	4410 dload (23, 4)
	4412 aload_0 (23, 4)
	4413 getfield (23, 4)
	4416 iload (23, 4)
	4418 iload (23, 4)
	4420 invokevirtual (23, 4)
	4423 aload_0 (23, 4)
	4424 getfield (23, 4)
	4427 iload (23, 4)
	4429 invokevirtual (23, 4)
	4432 dmul (23, 4)
	4433 dadd (23, 4)
	4434 dstore (23, 4)
	4436 iinc (23, 4)
	4439 goto (23, 4)
	4442 dload (22, 4)
	4444 aload_0 (22, 4)
	4445 getfield (22, 4)
	4448 iload (22, 4)
	4450 invokevirtual (22, 4)
	4453 dmul (22, 4)
	4454 dstore (22, 4)
	4456 iconst_0 (23, 4)
	4457 istore (23, 4)
	4459 iload (23, 4)
	4461 iload_3 (23, 4)
	4462 if_icmpge (23, 4)
	4465 aload_0 (23, 4)
	4466 getfield (23, 4)
	4469 iload (23, 4)
	4471 aload_0 (23, 4)
	4472 getfield (23, 4)
	4475 iload (23, 4)
	4477 invokevirtual (23, 4)
	4480 dload (23, 4)
	4482 aload_0 (23, 4)
	4483 getfield (23, 4)
	4486 iload (23, 4)
	4488 iload (23, 4)
	4490 invokevirtual (23, 4)
	4493 dmul (23, 4)
	4494 dadd (23, 4)
	4495 invokevirtual (23, 4)
	4498 iinc (23, 4)
	4501 goto (23, 4)
	4504 iinc (23, 4)
	4507 goto (23, 4)
	4510 iload (22, 1)
	4512 ifle (22, 1)
	4515 iconst_0 (23, 4)
	4516 istore (23, 4)
	4518 iload (23, 4)
	4520 iload (23, 4)
	4522 if_icmpge (23, 4)
	4525 aload_0 (23, 4)
	4526 getfield (23, 4)
	4529 iload (23, 4)
	4531 aload_0 (23, 4)
	4532 getfield (23, 4)
	4535 iload (23, 4)
	4537 invokevirtual (23, 4)
	4540 aload_0 (23, 4)
	4541 getfield (23, 4)
	4544 aload_0 (23, 4)
	4545 getfield (23, 4)
	4548 invokevirtual (23, 4)
	4551 dsub (23, 4)
	4552 invokevirtual (23, 4)
	4555 aload (23, 4)
	4557 iload (23, 4)
	4559 dconst_0 (23, 4)
	4560 invokevirtual (23, 4)
	4563 iinc (23, 4)
	4566 goto (23, 4)
	4569 iconst_0 (23, 4)
	4570 istore (23, 4)
	4572 iload (23, 4)
	4574 iload (23, 4)
	4576 if_icmpge (23, 4)
	4579 dconst_0 (23, 4)
	4580 dstore (23, 4)
	4582 iconst_0 (24, 4)
	4583 istore (24, 4)
	4585 iload (24, 4)
	4587 iload (24, 4)
	4589 if_icmpge (24, 4)
	4592 dload (24, 4)
	4594 aload_0 (24, 4)
	4595 getfield (24, 4)
	4598 iload (24, 4)
	4600 iload (24, 4)
	4602 invokevirtual (24, 4)
	4605 aload_0 (24, 4)
	4606 getfield (24, 4)
	4609 iload (24, 4)
	4611 invokevirtual (24, 4)
	4614 dmul (24, 4)
	4615 dadd (24, 4)
	4616 dstore (24, 4)
	4618 iinc (24, 4)
	4621 goto (24, 4)
	4624 iconst_0 (24, 4)
	4625 istore (24, 4)
	4627 iload (24, 4)
	4629 iload (24, 4)
	4631 if_icmpge (24, 4)
	4634 aload (24, 4)
	4636 iload (24, 4)
	4638 aload (24, 4)
	4640 iload (24, 4)
	4642 invokevirtual (24, 4)
	4645 dload (24, 4)
	4647 aload_0 (24, 4)
	4648 getfield (24, 4)
	4651 iload (24, 4)
	4653 iload (24, 4)
	4655 invokevirtual (24, 4)
	4658 dmul (24, 4)
	4659 dadd (24, 4)
	4660 invokevirtual (24, 4)
	4663 iinc (24, 4)
	4666 goto (24, 4)
	4669 iinc (24, 4)
	4672 goto (24, 4)
	4675 iconst_0 (24, 4)
	4676 istore (24, 4)
	4678 iload (24, 4)
	4680 iload (24, 4)
	4682 if_icmpge (24, 4)
	4685 dconst_0 (24, 4)
	4686 dstore (24, 4)
	4688 iconst_0 (25, 4)
	4689 istore (25, 4)
	4691 iload (25, 4)
	4693 iload_3 (25, 4)
	4694 if_icmpge (25, 4)
	4697 dload (25, 4)
	4699 aload_0 (25, 4)
	4700 getfield (25, 4)
	4703 iload (25, 4)
	4705 iload (25, 4)
	4707 invokevirtual (25, 4)
	4710 aload_0 (25, 4)
	4711 getfield (25, 4)
	4714 iload (25, 4)
	4716 invokevirtual (25, 4)
	4719 dmul (25, 4)
	4720 dadd (25, 4)
	4721 dstore (25, 4)
	4723 iinc (25, 4)
	4726 goto (25, 4)
	4729 aload (24, 4)
	4731 iload (24, 4)
	4733 aload (24, 4)
	4735 iload (24, 4)
	4737 invokevirtual (24, 4)
	4740 invokevirtual (24, 4)
	4743 aload (24, 4)
	4745 iload (24, 4)
	4747 dload (24, 4)
	4749 aload (24, 4)
	4751 iload (24, 4)
	4753 invokevirtual (24, 4)
	4756 dmul (24, 4)
	4757 invokevirtual (24, 4)
	4760 iinc (24, 4)
	4763 goto (24, 4)
	4766 dconst_0 (23, 4)
	4767 dstore (23, 4)
	4769 dconst_0 (23, 4)
	4770 dstore (23, 4)
	4772 iconst_0 (24, 4)
	4773 istore (24, 4)
	4775 iload (24, 4)
	4777 iload_3 (24, 4)
	4778 if_icmpge (24, 4)
	4781 dconst_0 (24, 4)
	4782 dstore (24, 4)
	4784 iconst_0 (25, 4)
	4785 istore (25, 4)
	4787 iload (25, 4)
	4789 iload (25, 4)
	4791 if_icmpge (25, 4)
	4794 dload (25, 4)
	4796 aload_0 (25, 4)
	4797 getfield (25, 4)
	4800 iload (25, 4)
	4802 iload (25, 4)
	4804 invokevirtual (25, 4)
	4807 aload_0 (25, 4)
	4808 getfield (25, 4)
	4811 iload (25, 4)
	4813 invokevirtual (25, 4)
	4816 dmul (25, 4)
	4817 aload_0 (25, 4)
	4818 getfield (25, 4)
	4821 iload (25, 4)
	4823 iload (25, 4)
	4825 invokevirtual (25, 4)
	4828 aload (25, 4)
	4830 iload (25, 4)
	4832 invokevirtual (25, 4)
	4835 dmul (25, 4)
	4836 dadd (25, 4)
	4837 dadd (25, 4)
	4838 dstore (25, 4)
	4840 iinc (25, 4)
	4843 goto (25, 4)
	4846 aload_0 (25, 1)
	4847 getfield (25, 1)
	4850 iload (25, 1)
	4852 invokevirtual (25, 1)
	4855 aload_0 (25, 1)
	4856 getfield (25, 1)
	4859 iload (25, 1)
	4861 invokevirtual (25, 1)
	4864 dcmpl (25, 1)
	4865 ifne (25, 1)
	4868 dconst_0 (25, 1)
	4869 aload_0 (25, 1)
	4870 getfield (25, 1)
	4873 iload (25, 1)
	4875 invokevirtual (25, 1)
	4878 invokestatic (25, 1)
	4881 dstore (25, 1)
	4883 dload (25, 1)
	4885 dload (25, 1)
	4887 dload (25, 1)
	4889 dmul (25, 1)
	4890 dadd (25, 1)
	4891 dstore (25, 1)
	4893 dconst_0 (25, 1)
	4894 dload (25, 1)
	4896 invokestatic (25, 1)
	4899 dstore (25, 1)
	4901 dload (25, 1)
	4903 dload (25, 1)
	4905 dload (25, 1)
	4907 dmul (25, 1)
	4908 dadd (25, 1)
	4909 dstore (25, 1)
	4911 goto (25, 1)
	4914 aload_0 (25, 1)
	4915 getfield (25, 1)
	4918 iload (25, 1)
	4920 invokevirtual (25, 1)
	4923 aload_0 (25, 1)
	4924 getfield (25, 1)
	4927 iload (25, 1)
	4929 invokevirtual (25, 1)
	4932 dcmpl (25, 1)
	4933 ifne (25, 1)
	4936 dconst_0 (25, 1)
	4937 aload_0 (25, 1)
	4938 getfield (25, 1)
	4941 iload (25, 1)
	4943 invokevirtual (25, 1)
	4946 invokestatic (25, 1)
	4949 dstore (25, 1)
	4951 dload (25, 1)
	4953 dload (25, 1)
	4955 dload (25, 1)
	4957 dmul (25, 1)
	4958 dadd (25, 1)
	4959 dstore (25, 1)
	4961 dconst_0 (25, 1)
	4962 dload (25, 1)
	4964 invokestatic (25, 1)
	4967 dstore (25, 1)
	4969 dload (25, 1)
	4971 dload (25, 1)
	4973 dload (25, 1)
	4975 dmul (25, 1)
	4976 dadd (25, 1)
	4977 dstore (25, 1)
	4979 goto (25, 2)
	4982 aload_0 (25, 2)
	4983 getfield (25, 2)
	4986 iload (25, 2)
	4988 invokevirtual (25, 2)
	4991 dstore (25, 2)
	4993 dload (25, 2)
	4995 dload (25, 2)
	4997 dload (25, 2)
	4999 dmul (25, 2)
	5000 dadd (25, 2)
	5001 dstore (25, 2)
	5003 dload (25, 2)
	5005 dload (25, 2)
	5007 dload (25, 2)
	5009 dmul (25, 2)
	5010 dadd (25, 2)
	5011 dstore (25, 2)
	5013 aload_0 (24, 1)
	5014 getfield (24, 1)
	5017 iload (24, 1)
	5019 iload (24, 1)
	5021 iadd (24, 1)
	5022 dload (24, 1)
	5024 invokevirtual (24, 1)
	5027 iinc (24, 1)
	5030 goto (24, 1)
	5033 iinc (23, 1)
	5036 dload (24, 1)
	5038 ldc2_w (24, 1)
	5041 dload (24, 1)
	5043 dmul (24, 1)
	5044 dcmpg (24, 1)
	5045 ifge (24, 1)
	5048 iconst_0 (24, 1)
	5049 istore (24, 1)
	5051 iload (24, 1)
	5053 iconst_3 (24, 1)
	5054 if_icmplt (24, 1)
	5057 iconst_0 (25, 4)
	5058 istore (25, 4)
	5060 iload (25, 4)
	5062 iload (25, 4)
	5064 invokestatic (25, 4)
	5067 istore (25, 4)
	5069 iload (25, 4)
	5071 iload (25, 4)
	5073 if_icmpge (25, 4)
	5076 iload (26, 1)
	5078 iload_3 (26, 1)
	5079 if_icmpge (26, 1)
	5082 aload_0 (26, 1)
	5083 getfield (26, 1)
	5086 iload (26, 1)
	5088 aload_0 (26, 1)
	5089 getfield (26, 1)
	5092 iload (26, 1)
	5094 iload (26, 1)
	5096 iadd (26, 1)
	5097 invokevirtual (26, 1)
	5100 invokevirtual (26, 1)
	5103 iload (26, 1)
	5105 iload (26, 1)
	5107 if_icmpge (26, 1)
	5110 aload_0 (26, 1)
	5111 getfield (26, 1)
	5114 iload (26, 1)
	5116 aload (26, 1)
	5118 iload (26, 1)
	5120 invokevirtual (26, 1)
	5123 invokevirtual (26, 1)
	5126 iload (26, 1)
	5128 iload (26, 1)
	5130 if_icmpge (26, 1)
	5133 aload_0 (26, 1)
	5134 getfield (26, 1)
	5137 iload (26, 1)
	5139 dconst_0 (26, 1)
	5140 invokevirtual (26, 1)
	5143 iconst_0 (25, 4)
	5144 istore (25, 4)
	5146 iinc (25, 4)
	5149 goto (25, 4)
	5152 iload (23, 1)
	5154 ifne (23, 1)
	5157 bipush (23, 1)
	5159 istore (23, 1)
	5161 goto (23, 1)
	5164 dload (23, 1)
	5166 dload (23, 1)
	5168 ldc2_w (23, 1)
	5171 dload (23, 1)
	5173 dmul (23, 1)
	5174 dadd (23, 1)
	5175 dcmpg (23, 1)
	5176 ifgt (23, 1)
	5179 bipush (23, 1)
	5181 istore (23, 1)
	5183 goto (23, 1)
	5186 ldc2_w (22, 1)
	5189 dload (22, 1)
	5191 dmul (22, 1)
	5192 dstore (22, 1)
	5194 ldc2_w (22, 1)
	5197 dload (22, 1)
	5199 dmul (22, 1)
	5200 dstore (22, 1)
	5202 dload (22, 1)
	5204 dload (22, 1)
	5206 dmul (22, 1)
	5207 dload (22, 1)
	5209 dload (22, 1)
	5211 dmul (22, 1)
	5212 invokestatic (22, 1)
	5215 dstore (22, 1)
	5217 sipush (22, 4)
	5220 invokestatic (22, 4)
	5223 iconst_m1 (22, 4)
	5224 istore (22, 4)
	5226 iconst_0 (23, 4)
	5227 istore (23, 4)
	5229 iload (23, 4)
	5231 iload (23, 4)
	5233 if_icmpge (23, 4)
	5236 dconst_0 (23, 4)
	5237 dstore (23, 4)
	5239 iconst_0 (24, 4)
	5240 istore (24, 4)
	5242 iload (24, 4)
	5244 iload_3 (24, 4)
	5245 if_icmpge (24, 4)
	5248 aload_0 (24, 4)
	5249 getfield (24, 4)
	5252 iload (24, 4)
	5254 iload (24, 4)
	5256 invokevirtual (24, 4)
	5259 aload_0 (24, 4)
	5260 getfield (24, 4)
	5263 iload (24, 4)
	5265 invokevirtual (24, 4)
	5268 dsub (24, 4)
	5269 dstore (24, 4)
	5271 dload (24, 4)
	5273 dload (24, 4)
	5275 dload (24, 4)
	5277 dmul (24, 4)
	5278 dadd (24, 4)
	5279 dstore (24, 4)
	5281 iinc (24, 4)
	5284 goto (24, 4)
	5287 dload (24, 1)
	5289 dload (24, 1)
	5291 dcmpl (24, 1)
	5292 ifle (24, 1)
	5295 iload (24, 1)
	5297 istore (24, 1)
	5299 dload (24, 1)
	5301 dstore (24, 1)
	5303 iinc (24, 1)
	5306 goto (24, 1)
	5309 iload (24, 1)
	5311 iflt (24, 1)
	5314 dload (24, 1)
	5316 invokestatic (24, 1)
	5319 dstore (24, 1)
	5321 iload (25, 1)
	5323 iconst_m1 (25, 1)
	5324 if_icmpne (25, 1)
	5327 ldc2_w (25, 1)
	5330 dload (25, 1)
	5332 dmul (25, 1)
	5333 ldc2_w (25, 1)
	5336 dload (25, 1)
	5338 dmul (25, 1)
	5339 invokestatic (25, 1)
	5342 dstore (25, 1)
	5344 dload (26, 1)
	5346 dload (26, 1)
	5348 ldc2_w (26, 1)
	5351 dmul (26, 1)
	5352 dcmpg (26, 1)
	5353 ifgt (26, 1)
	5356 dload (26, 1)
	5358 dstore (26, 1)
	5360 iconst_0 (24, 1)
	5361 istore (24, 1)
	5363 ldc2_w (24, 1)
	5366 dload (24, 1)
	5368 dmul (24, 1)
	5369 dload (24, 1)
	5371 invokestatic (24, 1)
	5374 dstore (24, 1)
	5376 dload (24, 1)
	5378 dload (24, 1)
	5380 invokestatic (24, 1)
	5383 dstore (24, 1)
	5385 dload (24, 1)
	5387 dload (24, 1)
	5389 dmul (24, 1)
	5390 dstore (24, 1)
	5392 bipush (24, 1)
	5394 istore (24, 1)
	5396 goto (24, 1)
	5399 iload (24, 1)
	5401 iconst_m1 (24, 1)
	5402 if_icmpne (24, 1)
	5405 sipush (24, 1)
	5408 istore (24, 1)
	5410 goto (24, 1)
	5413 dload (24, 1)
	5415 dconst_0 (24, 1)
	5416 dcmpl (24, 1)
	5417 ifle (24, 1)
	5420 bipush (24, 1)
	5422 istore (24, 1)
	5424 goto (24, 1)
	5427 dload (24, 1)
	5429 dload (24, 1)
	5431 invokestatic (24, 1)
	5434 dload (24, 1)
	5436 dcmpl (24, 1)
	5437 ifle (24, 1)
	5440 bipush (24, 1)
	5442 istore (24, 1)
	5444 goto (24, 1)
	5447 sipush (23, 4)
	5450 invokestatic (23, 4)
	5453 dload (24, 1)
	5455 aload_0 (24, 1)
	5456 getfield (24, 1)
	5459 dcmpl (24, 1)
	5460 ifle (24, 1)
	5463 ldc2_w (24, 1)
	5466 dload (24, 1)
	5468 dmul (24, 1)
	5469 dstore (24, 1)
	5471 dload (24, 1)
	5473 aload_0 (24, 1)
	5474 getfield (24, 1)
	5477 ddiv (24, 1)
	5478 dstore (24, 1)
	5480 dload (25, 1)
	5482 ldc2_w (25, 1)
	5485 dcmpg (25, 1)
	5486 ifgt (25, 1)
	5489 aload_0 (25, 1)
	5490 getfield (25, 1)
	5493 dstore (25, 1)
	5495 goto (25, 1)
	5498 dload (25, 1)
	5500 ldc2_w (25, 1)
	5503 dcmpg (25, 1)
	5504 ifgt (25, 1)
	5507 dload (25, 1)
	5509 invokestatic (25, 1)
	5512 aload_0 (25, 1)
	5513 getfield (25, 1)
	5516 dmul (25, 1)
	5517 dstore (25, 1)
	5519 goto (25, 1)
	5522 dload (25, 2)
	5524 ldc2_w (25, 2)
	5527 dmul (25, 2)
	5528 dstore (25, 2)
	5530 dload (24, 1)
	5532 dload (24, 1)
	5534 invokestatic (24, 1)
	5537 dstore (24, 1)
	5539 iconst_0 (24, 1)
	5540 istore (24, 1)
	5542 aload_0 (24, 1)
	5543 invokevirtual (24, 1)
	5546 istore (24, 1)
	5548 bipush (24, 1)
	5550 istore (24, 1)
	5552 goto (24, 1)
	5555 iload (24, 1)
	5557 iconst_m1 (24, 1)
	5558 if_icmpne (24, 1)
	5561 sipush (24, 1)
	5564 istore (24, 1)
	5566 goto (24, 1)
	5569 sipush (23, 1)
	5572 invokestatic (23, 1)
	5575 aload_0 (24, 1)
	5576 getfield (24, 1)
	5579 aload_0 (24, 1)
	5580 getfield (24, 1)
	5583 invokevirtual (24, 1)
	5586 dload (24, 1)
	5588 dcmpg (24, 1)
	5589 ifgt (24, 1)
	5592 iconst_0 (25, 4)
	5593 istore (25, 4)
	5595 iload (25, 4)
	5597 iload_3 (25, 4)
	5598 if_icmpge (25, 4)
	5601 aload_1 (25, 4)
	5602 iload (25, 4)
	5604 daload (25, 4)
	5605 dstore (25, 4)
	5607 aload_0 (25, 1)
	5608 getfield (25, 1)
	5611 iload (25, 1)
	5613 invokevirtual (25, 1)
	5616 aload_0 (25, 1)
	5617 getfield (25, 1)
	5620 iload (25, 1)
	5622 invokevirtual (25, 1)
	5625 dadd (25, 1)
	5626 dstore (25, 1)
	5628 dload (25, 1)
	5630 dload (25, 1)
	5632 invokestatic (25, 1)
	5635 dstore (25, 1)
	5637 aload_2 (25, 1)
	5638 iload (25, 1)
	5640 daload (25, 1)
	5641 dstore (25, 1)
	5643 aload_0 (25, 1)
	5644 getfield (25, 1)
	5647 iload (25, 1)
	5649 dload (25, 1)
	5651 dload (25, 1)
	5653 invokestatic (25, 1)
	5656 invokevirtual (25, 1)
	5659 aload_0 (26, 1)
	5660 getfield (26, 1)
	5663 iload (26, 1)
	5665 invokevirtual (26, 1)
	5668 aload_0 (26, 1)
	5669 getfield (26, 1)
	5672 iload (26, 1)
	5674 invokevirtual (26, 1)
	5677 dcmpl (26, 1)
	5678 ifne (26, 1)
	5681 aload_0 (26, 1)
	5682 getfield (26, 1)
	5685 iload (26, 1)
	5687 aload_1 (26, 1)
	5688 iload (26, 1)
	5690 daload (26, 1)
	5691 invokevirtual (26, 1)
	5694 aload_0 (26, 1)
	5695 getfield (26, 1)
	5698 iload (26, 1)
	5700 invokevirtual (26, 1)
	5703 aload_0 (26, 1)
	5704 getfield (26, 1)
	5707 iload (26, 1)
	5709 invokevirtual (26, 1)
	5712 dcmpl (26, 1)
	5713 ifne (26, 1)
	5716 aload_0 (26, 1)
	5717 getfield (26, 1)
	5720 iload (26, 1)
	5722 aload_2 (26, 1)
	5723 iload (26, 1)
	5725 daload (26, 1)
	5726 invokevirtual (26, 1)
	5729 iinc (26, 1)
	5732 goto (26, 1)
	5735 aload_0 (25, 1)
	5736 getfield (25, 1)
	5739 aload_0 (25, 1)
	5740 getfield (25, 1)
	5743 invokevirtual (25, 1)
	5746 dstore (25, 1)
	5748 dload (24, 1)
	5750 dreturn (24, 1)
	5751 new (24, 4)
	5754 dup (24, 4)
	5755 getstatic (24, 4)
	5758 iconst_1 (24, 4)
	5759 anewarray (24, 4)
	5762 dup (24, 4)
	5763 iconst_0 (24, 4)
	5764 ldc (24, 4)
	5766 aastore (24, 4)
	5767 invokespecial (24, 4)
	5770 athrow (24, 4)

Method: altmov
	0 invokestatic (0, 0)
	3 aload_0 (0, 0)
	4 getfield (0, 0)
	7 invokevirtual (0, 0)
	10 istore (0, 0)
	12 aload_0 (0, 0)
	13 getfield (0, 0)
	16 istore (0, 0)
	18 new (0, 0)
	21 dup (0, 0)
	22 iload (0, 0)
	24 invokespecial (0, 0)
	27 astore (0, 0)
	29 new (0, 0)
	32 dup (0, 0)
	33 iload (0, 0)
	35 invokespecial (0, 0)
	38 astore (0, 0)
	40 new (0, 0)
	43 dup (0, 0)
	44 iload (0, 0)
	46 invokespecial (0, 0)
	49 astore (0, 0)
	51 new (0, 0)
	54 dup (0, 0)
	55 iload (0, 0)
	57 invokespecial (0, 0)
	60 astore (0, 0)
	62 iconst_0 (1, 4)
	63 istore (1, 4)
	65 iload (1, 4)
	67 iload (1, 4)
	69 if_icmpge (1, 4)
	72 aload (1, 4)
	74 iload (1, 4)
	76 dconst_0 (1, 4)
	77 invokevirtual (1, 4)
	80 iinc (1, 4)
	83 goto (1, 4)
	86 iconst_0 (1, 4)
	87 istore (1, 4)
	89 iload (1, 4)
	91 iload (1, 4)
	93 isub (1, 4)
	94 iconst_1 (1, 4)
	95 isub (1, 4)
	96 istore (1, 4)
	98 iload (1, 4)
	100 iload (1, 4)
	102 if_icmpge (1, 4)
	105 aload_0 (1, 4)
	106 getfield (1, 4)
	109 iload_1 (1, 4)
	110 iload (1, 4)
	112 invokevirtual (1, 4)
	115 dstore (1, 4)
	117 iconst_0 (2, 4)
	118 istore (2, 4)
	120 iload (2, 4)
	122 iload (2, 4)
	124 if_icmpge (2, 4)
	127 aload (2, 4)
	129 iload (2, 4)
	131 aload (2, 4)
	133 iload (2, 4)
	135 invokevirtual (2, 4)
	138 dload (2, 4)
	140 aload_0 (2, 4)
	141 getfield (2, 4)
	144 iload (2, 4)
	146 iload (2, 4)
	148 invokevirtual (2, 4)
	151 dmul (2, 4)
	152 dadd (2, 4)
	153 invokevirtual (2, 4)
	156 iinc (2, 4)
	159 goto (2, 4)
	162 iinc (2, 4)
	165 goto (2, 4)
	168 aload (1, 4)
	170 iload_1 (1, 4)
	171 invokevirtual (1, 4)
	174 dstore (1, 4)
	176 ldc2_w (1, 4)
	179 dload (1, 4)
	181 dmul (1, 4)
	182 dstore (1, 4)
	184 iconst_0 (2, 4)
	185 istore (2, 4)
	187 iload (2, 4)
	189 iload (2, 4)
	191 if_icmpge (2, 4)
	194 aload (2, 4)
	196 iload (2, 4)
	198 aload_0 (2, 4)
	199 getfield (2, 4)
	202 iload_1 (2, 4)
	203 iload (2, 4)
	205 invokevirtual (2, 4)
	208 invokevirtual (2, 4)
	211 iinc (2, 4)
	214 goto (2, 4)
	217 iconst_0 (2, 4)
	218 istore (2, 4)
	220 iload (2, 4)
	222 iload (2, 4)
	224 if_icmpge (2, 4)
	227 dconst_0 (2, 4)
	228 dstore (2, 4)
	230 iconst_0 (3, 4)
	231 istore (3, 4)
	233 iload (3, 4)
	235 iload (3, 4)
	237 if_icmpge (3, 4)
	240 dload (3, 4)
	242 aload_0 (3, 4)
	243 getfield (3, 4)
	246 iload (3, 4)
	248 iload (3, 4)
	250 invokevirtual (3, 4)
	253 aload_0 (3, 4)
	254 getfield (3, 4)
	257 iload (3, 4)
	259 invokevirtual (3, 4)
	262 dmul (3, 4)
	263 dadd (3, 4)
	264 dstore (3, 4)
	266 iinc (3, 4)
	269 goto (3, 4)
	272 dload (2, 4)
	274 aload (2, 4)
	276 iload (2, 4)
	278 invokevirtual (2, 4)
	281 dmul (2, 4)
	282 dstore (2, 4)
	284 iconst_0 (3, 4)
	285 istore (3, 4)
	287 iload (3, 4)
	289 iload (3, 4)
	291 if_icmpge (3, 4)
	294 aload (3, 4)
	296 iload (3, 4)
	298 aload (3, 4)
	300 iload (3, 4)
	302 invokevirtual (3, 4)
	305 dload (3, 4)
	307 aload_0 (3, 4)
	308 getfield (3, 4)
	311 iload (3, 4)
	313 iload (3, 4)
	315 invokevirtual (3, 4)
	318 dmul (3, 4)
	319 dadd (3, 4)
	320 invokevirtual (3, 4)
	323 iinc (3, 4)
	326 goto (3, 4)
	329 iinc (3, 4)
	332 goto (3, 4)
	335 dconst_0 (2, 4)
	336 dstore (2, 4)
	338 ldc2_w (2, 4)
	341 dstore (2, 4)
	343 iconst_0 (2, 4)
	344 istore (2, 4)
	346 iconst_0 (2, 4)
	347 istore (2, 4)
	349 dconst_0 (2, 4)
	350 dstore (2, 4)
	352 iconst_0 (3, 4)
	353 istore (3, 4)
	355 iload (3, 4)
	357 iload (3, 4)
	359 if_icmpge (3, 4)
	362 iload (4, 1)
	364 aload_0 (4, 1)
	365 getfield (4, 1)
	368 if_icmpne (4, 1)
	371 goto (4, 1)
	374 dconst_0 (3, 4)
	375 dstore (3, 4)
	377 dconst_0 (3, 4)
	378 dstore (3, 4)
	380 iconst_0 (4, 4)
	381 istore (4, 4)
	383 iload (4, 4)
	385 iload (4, 4)
	387 if_icmpge (4, 4)
	390 aload_0 (4, 4)
	391 getfield (4, 4)
	394 iload (4, 4)
	396 iload (4, 4)
	398 invokevirtual (4, 4)
	401 aload_0 (4, 4)
	402 getfield (4, 4)
	405 iload (4, 4)
	407 invokevirtual (4, 4)
	410 dsub (4, 4)
	411 dstore (4, 4)
	413 dload (4, 4)
	415 aload (4, 4)
	417 iload (4, 4)
	419 invokevirtual (4, 4)
	422 dload (4, 4)
	424 dmul (4, 4)
	425 dadd (4, 4)
	426 dstore (4, 4)
	428 dload (4, 4)
	430 dload (4, 4)
	432 dload (4, 4)
	434 dmul (4, 4)
	435 dadd (4, 4)
	436 dstore (4, 4)
	438 iinc (4, 4)
	441 goto (4, 4)
	444 dload_2 (3, 4)
	445 dload (3, 4)
	447 invokestatic (3, 4)
	450 ddiv (3, 4)
	451 dstore (3, 4)
	453 dload (3, 4)
	455 dneg (3, 4)
	456 dstore (3, 4)
	458 iconst_0 (3, 4)
	459 istore (3, 4)
	461 iconst_0 (3, 4)
	462 istore (3, 4)
	464 dconst_1 (3, 4)
	465 dload (3, 4)
	467 invokestatic (3, 4)
	470 dstore (3, 4)
	472 iconst_0 (4, 4)
	473 istore (4, 4)
	475 iload (4, 4)
	477 iload (4, 4)
	479 if_icmpge (4, 4)
	482 aload_0 (4, 4)
	483 getfield (4, 4)
	486 iload (4, 4)
	488 iload (4, 4)
	490 invokevirtual (4, 4)
	493 aload_0 (4, 4)
	494 getfield (4, 4)
	497 iload (4, 4)
	499 invokevirtual (4, 4)
	502 dsub (4, 4)
	503 dstore (4, 4)
	505 dload (5, 1)
	507 dconst_0 (5, 1)
	508 dcmpl (5, 1)
	509 ifle (5, 1)
	512 dload (6, 1)
	514 dload (6, 1)
	516 dmul (6, 1)
	517 aload_0 (6, 1)
	518 getfield (6, 1)
	521 iload (6, 1)
	523 invokevirtual (6, 1)
	526 aload_0 (6, 1)
	527 getfield (6, 1)
	530 iload (6, 1)
	532 invokevirtual (6, 1)
	535 dsub (6, 1)
	536 dcmpg (6, 1)
	537 ifge (6, 1)
	540 aload_0 (6, 1)
	541 getfield (6, 1)
	544 iload (6, 1)
	546 invokevirtual (6, 1)
	549 aload_0 (6, 1)
	550 getfield (6, 1)
	553 iload (6, 1)
	555 invokevirtual (6, 1)
	558 dsub (6, 1)
	559 dload (6, 1)
	561 ddiv (6, 1)
	562 dstore (6, 1)
	564 iload (6, 1)
	566 ineg (6, 1)
	567 iconst_1 (6, 1)
	568 isub (6, 1)
	569 istore (6, 1)
	571 dload (6, 1)
	573 dload (6, 1)
	575 dmul (6, 1)
	576 aload_0 (6, 1)
	577 getfield (6, 1)
	580 iload (6, 1)
	582 invokevirtual (6, 1)
	585 aload_0 (6, 1)
	586 getfield (6, 1)
	589 iload (6, 1)
	591 invokevirtual (6, 1)
	594 dsub (6, 1)
	595 dcmpl (6, 1)
	596 ifle (6, 1)
	599 dload (6, 1)
	601 aload_0 (6, 1)
	602 getfield (6, 1)
	605 iload (6, 1)
	607 invokevirtual (6, 1)
	610 aload_0 (6, 1)
	611 getfield (6, 1)
	614 iload (6, 1)
	616 invokevirtual (6, 1)
	619 dsub (6, 1)
	620 dload (6, 1)
	622 ddiv (6, 1)
	623 invokestatic (6, 1)
	626 dstore (6, 1)
	628 iload (6, 1)
	630 iconst_1 (6, 1)
	631 iadd (6, 1)
	632 istore (6, 1)
	634 goto (6, 1)
	637 dload (5, 1)
	639 dconst_0 (5, 1)
	640 dcmpg (5, 1)
	641 ifge (5, 1)
	644 dload (6, 1)
	646 dload (6, 1)
	648 dmul (6, 1)
	649 aload_0 (6, 1)
	650 getfield (6, 1)
	653 iload (6, 1)
	655 invokevirtual (6, 1)
	658 aload_0 (6, 1)
	659 getfield (6, 1)
	662 iload (6, 1)
	664 invokevirtual (6, 1)
	667 dsub (6, 1)
	668 dcmpl (6, 1)
	669 ifle (6, 1)
	672 aload_0 (6, 1)
	673 getfield (6, 1)
	676 iload (6, 1)
	678 invokevirtual (6, 1)
	681 aload_0 (6, 1)
	682 getfield (6, 1)
	685 iload (6, 1)
	687 invokevirtual (6, 1)
	690 dsub (6, 1)
	691 dload (6, 1)
	693 ddiv (6, 1)
	694 dstore (6, 1)
	696 iload (6, 1)
	698 iconst_1 (6, 1)
	699 iadd (6, 1)
	700 istore (6, 1)
	702 dload (6, 1)
	704 dload (6, 1)
	706 dmul (6, 1)
	707 aload_0 (6, 1)
	708 getfield (6, 1)
	711 iload (6, 1)
	713 invokevirtual (6, 1)
	716 aload_0 (6, 1)
	717 getfield (6, 1)
	720 iload (6, 1)
	722 invokevirtual (6, 1)
	725 dsub (6, 1)
	726 dcmpg (6, 1)
	727 ifge (6, 1)
	730 dload (6, 1)
	732 aload_0 (6, 1)
	733 getfield (6, 1)
	736 iload (6, 1)
	738 invokevirtual (6, 1)
	741 aload_0 (6, 1)
	742 getfield (6, 1)
	745 iload (6, 1)
	747 invokevirtual (6, 1)
	750 dsub (6, 1)
	751 dload (6, 1)
	753 ddiv (6, 1)
	754 invokestatic (6, 1)
	757 dstore (6, 1)
	759 iload (6, 1)
	761 ineg (6, 1)
	762 iconst_1 (6, 1)
	763 isub (6, 1)
	764 istore (6, 1)
	766 iinc (6, 1)
	769 goto (6, 1)
	772 dload (5, 1)
	774 dstore (5, 1)
	776 iload (5, 1)
	778 istore (5, 1)
	780 ldc2_w (5, 1)
	783 dstore (5, 1)
	785 iload (6, 1)
	787 iload_1 (6, 1)
	788 if_icmpne (6, 1)
	791 dload (6, 1)
	793 dconst_1 (6, 1)
	794 dsub (6, 1)
	795 dstore (6, 1)
	797 dload (6, 1)
	799 dload (6, 1)
	801 dload (6, 1)
	803 dload (6, 1)
	805 dmul (6, 1)
	806 dsub (6, 1)
	807 dmul (6, 1)
	808 dstore (6, 1)
	810 dload (6, 1)
	812 dload (6, 1)
	814 dload (6, 1)
	816 dload (6, 1)
	818 dmul (6, 1)
	819 dsub (6, 1)
	820 dmul (6, 1)
	821 dstore (6, 1)
	823 dload (7, 1)
	825 invokestatic (7, 1)
	828 dload (7, 1)
	830 invokestatic (7, 1)
	833 dcmpl (7, 1)
	834 ifle (7, 1)
	837 dload (7, 1)
	839 dstore (7, 1)
	841 dload (7, 1)
	843 dstore (7, 1)
	845 iload (7, 1)
	847 istore (7, 1)
	849 ldc2_w (6, 1)
	852 dload (6, 1)
	854 dmul (6, 1)
	855 dstore (6, 1)
	857 dload (6, 1)
	859 dload (6, 1)
	861 dload (6, 1)
	863 dmul (6, 1)
	864 dsub (6, 1)
	865 dstore (6, 1)
	867 dload (6, 1)
	869 dload (6, 1)
	871 dload (6, 1)
	873 dmul (6, 1)
	874 dsub (6, 1)
	875 dstore (6, 1)
	877 dload (7, 1)
	879 dload (7, 1)
	881 dmul (7, 1)
	882 dconst_0 (7, 1)
	883 dcmpg (7, 1)
	884 ifge (7, 1)
	887 dload (7, 1)
	889 dload (7, 1)
	891 dmul (7, 1)
	892 dload (7, 1)
	894 ddiv (7, 1)
	895 dstore (7, 1)
	897 dload (8, 1)
	899 invokestatic (8, 1)
	902 dload (8, 1)
	904 invokestatic (8, 1)
	907 dcmpl (8, 1)
	908 ifle (8, 1)
	911 dload (8, 1)
	913 dload (8, 1)
	915 ddiv (8, 1)
	916 dstore (8, 1)
	918 dload (8, 1)
	920 dstore (8, 1)
	922 iconst_0 (8, 1)
	923 istore (8, 1)
	925 goto (6, 2)
	928 dload (6, 2)
	930 dconst_1 (6, 2)
	931 dload (6, 2)
	933 dsub (6, 2)
	934 dmul (6, 2)
	935 dstore (6, 2)
	937 dload (6, 2)
	939 dconst_1 (6, 2)
	940 dload (6, 2)
	942 dsub (6, 2)
	943 dmul (6, 2)
	944 dstore (6, 2)
	946 dload (7, 1)
	948 invokestatic (7, 1)
	951 dload (7, 1)
	953 invokestatic (7, 1)
	956 dcmpl (7, 1)
	957 ifle (7, 1)
	960 dload (7, 1)
	962 dstore (7, 1)
	964 dload (7, 1)
	966 dstore (7, 1)
	968 iload (7, 1)
	970 istore (7, 1)
	972 dload (7, 1)
	974 ldc2_w (7, 1)
	977 dcmpl (7, 1)
	978 ifle (7, 1)
	981 dload (7, 1)
	983 invokestatic (7, 1)
	986 ldc2_w (7, 1)
	989 dcmpg (7, 1)
	990 ifge (7, 1)
	993 ldc2_w (7, 1)
	996 dstore (7, 1)
	998 ldc2_w (7, 1)
	1001 dstore (7, 1)
	1003 iconst_0 (7, 1)
	1004 istore (7, 1)
	1006 dload (6, 2)
	1008 dload (6, 2)
	1010 dmul (6, 2)
	1011 dstore (6, 2)
	1013 dload (5, 4)
	1015 dconst_1 (5, 4)
	1016 dload (5, 4)
	1018 dsub (5, 4)
	1019 dmul (5, 4)
	1020 dload (5, 4)
	1022 dmul (5, 4)
	1023 dstore (5, 4)
	1025 dload (5, 4)
	1027 dload (5, 4)
	1029 dmul (5, 4)
	1030 dload (5, 4)
	1032 dload (5, 4)
	1034 dmul (5, 4)
	1035 dload (5, 4)
	1037 dload (5, 4)
	1039 dmul (5, 4)
	1040 dload (5, 4)
	1042 dmul (5, 4)
	1043 dadd (5, 4)
	1044 dmul (5, 4)
	1045 dstore (5, 4)
	1047 dload (6, 1)
	1049 dload (6, 1)
	1051 dcmpl (6, 1)
	1052 ifle (6, 1)
	1055 dload (6, 1)
	1057 dstore (6, 1)
	1059 iload (6, 1)
	1061 istore (6, 1)
	1063 dload (6, 1)
	1065 dstore (6, 1)
	1067 iload (6, 1)
	1069 istore (6, 1)
	1071 iinc (6, 1)
	1074 goto (6, 1)
	1077 iconst_0 (6, 4)
	1078 istore (6, 4)
	1080 iload (6, 4)
	1082 iload (6, 4)
	1084 if_icmpge (6, 4)
	1087 aload_0 (6, 4)
	1088 getfield (6, 4)
	1091 iload (6, 4)
	1093 invokevirtual (6, 4)
	1096 dload (6, 4)
	1098 aload_0 (6, 4)
	1099 getfield (6, 4)
	1102 iload (6, 4)
	1104 iload (6, 4)
	1106 invokevirtual (6, 4)
	1109 aload_0 (6, 4)
	1110 getfield (6, 4)
	1113 iload (6, 4)
	1115 invokevirtual (6, 4)
	1118 dsub (6, 4)
	1119 dmul (6, 4)
	1120 dadd (6, 4)
	1121 dstore (6, 4)
	1123 aload_0 (6, 1)
	1124 getfield (6, 1)
	1127 iload (6, 1)
	1129 aload_0 (6, 1)
	1130 getfield (6, 1)
	1133 iload (6, 1)
	1135 invokevirtual (6, 1)
	1138 aload_0 (6, 1)
	1139 getfield (6, 1)
	1142 iload (6, 1)
	1144 invokevirtual (6, 1)
	1147 dload (6, 1)
	1149 invokestatic (6, 1)
	1152 invokestatic (6, 1)
	1155 invokevirtual (6, 1)
	1158 iinc (6, 1)
	1161 goto (6, 1)
	1164 iload (6, 1)
	1166 ifge (6, 1)
	1169 aload_0 (6, 1)
	1170 getfield (6, 1)
	1173 iload (6, 1)
	1175 ineg (6, 1)
	1176 iconst_1 (6, 1)
	1177 isub (6, 1)
	1178 aload_0 (6, 1)
	1179 getfield (6, 1)
	1182 iload (6, 1)
	1184 ineg (6, 1)
	1185 iconst_1 (6, 1)
	1186 isub (6, 1)
	1187 invokevirtual (6, 1)
	1190 invokevirtual (6, 1)
	1193 iload (6, 1)
	1195 ifle (6, 1)
	1198 aload_0 (6, 1)
	1199 getfield (6, 1)
	1202 iload (6, 1)
	1204 iconst_1 (6, 1)
	1205 isub (6, 1)
	1206 aload_0 (6, 1)
	1207 getfield (6, 1)
	1210 iload (6, 1)
	1212 iconst_1 (6, 1)
	1213 isub (6, 1)
	1214 invokevirtual (6, 1)
	1217 invokevirtual (6, 1)
	1220 dload_2 (5, 4)
	1221 dload_2 (5, 4)
	1222 dadd (5, 4)
	1223 dstore (5, 4)
	1225 iconst_0 (5, 1)
	1226 istore (5, 1)
	1228 ldc2_w (5, 1)
	1231 dstore (5, 1)
	1233 dconst_0 (5, 1)
	1234 dstore (5, 1)
	1236 dconst_0 (6, 3)
	1237 dstore (6, 3)
	1239 dconst_0 (6, 3)
	1240 dstore (6, 3)
	1242 iconst_0 (7, 4)
	1243 istore (7, 4)
	1245 iload (7, 4)
	1247 iload (7, 4)
	1249 if_icmpge (7, 4)
	1252 aload (7, 4)
	1254 iload (7, 4)
	1256 invokevirtual (7, 4)
	1259 dstore (7, 4)
	1261 aload (7, 4)
	1263 iload (7, 4)
	1265 dconst_0 (7, 4)
	1266 invokevirtual (7, 4)
	1269 aload_0 (7, 1)
	1270 getfield (7, 1)
	1273 iload (7, 1)
	1275 invokevirtual (7, 1)
	1278 aload_0 (7, 1)
	1279 getfield (7, 1)
	1282 iload (7, 1)
	1284 invokevirtual (7, 1)
	1287 dsub (7, 1)
	1288 dload (7, 1)
	1290 invokestatic (7, 1)
	1293 dconst_0 (7, 1)
	1294 dcmpl (7, 1)
	1295 ifgt (7, 1)
	1298 aload_0 (7, 1)
	1299 getfield (7, 1)
	1302 iload (7, 1)
	1304 invokevirtual (8, 1)
	1307 aload_0 (8, 1)
	1308 getfield (8, 1)
	1311 iload (8, 1)
	1313 invokevirtual (8, 1)
	1316 dsub (8, 1)
	1317 dload (8, 1)
	1319 invokestatic (8, 1)
	1322 dconst_0 (8, 1)
	1323 dcmpg (8, 1)
	1324 ifge (8, 1)
	1327 aload (8, 1)
	1329 iload (8, 1)
	1331 dload (8, 1)
	1333 invokevirtual (8, 1)
	1336 dload (8, 1)
	1338 dload (8, 1)
	1340 dload (8, 1)
	1342 dmul (8, 1)
	1343 dadd (8, 1)
	1344 dstore (8, 1)
	1346 iinc (8, 1)
	1349 goto (8, 1)
	1352 dload (8, 1)
	1354 dconst_0 (8, 1)
	1355 dcmpl (8, 1)
	1356 ifne (8, 1)
	1359 iconst_2 (8, 1)
	1360 newarray (8, 1)
	1362 dup (8, 1)
	1363 iconst_0 (8, 1)
	1364 dload (8, 1)
	1366 dastore (8, 1)
	1367 dup (8, 1)
	1368 iconst_1 (8, 1)
	1369 dconst_0 (8, 1)
	1370 dastore (8, 1)
	1371 areturn (8, 1)
	1372 dload_2 (7, 1)
	1373 dload_2 (7, 1)
	1374 dmul (7, 1)
	1375 dload (7, 1)
	1377 dsub (7, 1)
	1378 dstore (7, 1)
	1380 dload (8, 1)
	1382 dconst_0 (8, 1)
	1383 dcmpl (8, 1)
	1384 ifle (8, 1)
	1387 dload (8, 1)
	1389 dload (8, 1)
	1391 ddiv (8, 1)
	1392 invokestatic (8, 1)
	1395 dstore (8, 1)
	1397 dconst_0 (8, 1)
	1398 dstore (8, 1)
	1400 iconst_0 (9, 4)
	1401 istore (9, 4)
	1403 iload (9, 4)
	1405 iload (9, 4)
	1407 if_icmpge (9, 4)
	1410 aload (10, 1)
	1412 iload (10, 1)
	1414 invokevirtual (10, 1)
	1417 dload (10, 1)
	1419 dcmpl (10, 1)
	1420 ifne (10, 1)
	1423 aload_0 (10, 1)
	1424 getfield (10, 1)
	1427 iload (10, 1)
	1429 invokevirtual (10, 1)
	1432 dload (10, 1)
	1434 aload (10, 1)
	1436 iload (10, 1)
	1438 invokevirtual (10, 1)
	1441 dmul (10, 1)
	1442 dsub (10, 1)
	1443 dstore (10, 1)
	1445 dload (11, 1)
	1447 aload_0 (11, 1)
	1448 getfield (11, 1)
	1451 iload (11, 1)
	1453 invokevirtual (11, 1)
	1456 dcmpg (11, 1)
	1457 ifgt (11, 1)
	1460 aload (11, 1)
	1462 iload (11, 1)
	1464 aload_0 (11, 1)
	1465 getfield (11, 1)
	1468 iload (11, 1)
	1470 invokevirtual (11, 1)
	1473 aload_0 (11, 1)
	1474 getfield (11, 1)
	1477 iload (11, 1)
	1479 invokevirtual (11, 1)
	1482 dsub (11, 1)
	1483 invokevirtual (11, 1)
	1486 aload (11, 1)
	1488 iload (11, 1)
	1490 invokevirtual (11, 1)
	1493 dstore (11, 1)
	1495 dload (11, 1)
	1497 dload (11, 1)
	1499 dload (11, 1)
	1501 dmul (11, 1)
	1502 dadd (11, 1)
	1503 dstore (11, 1)
	1505 goto (11, 1)
	1508 dload (11, 1)
	1510 aload_0 (11, 1)
	1511 getfield (11, 1)
	1514 iload (11, 1)
	1516 invokevirtual (11, 1)
	1519 dcmpl (11, 1)
	1520 iflt (11, 1)
	1523 aload (11, 1)
	1525 iload (11, 1)
	1527 aload_0 (11, 1)
	1528 getfield (11, 1)
	1531 iload (11, 1)
	1533 invokevirtual (11, 1)
	1536 aload_0 (11, 1)
	1537 getfield (11, 1)
	1540 iload (11, 1)
	1542 invokevirtual (11, 1)
	1545 dsub (11, 1)
	1546 invokevirtual (11, 1)
	1549 aload (11, 1)
	1551 iload (11, 1)
	1553 invokevirtual (11, 1)
	1556 dstore (11, 1)
	1558 dload (11, 1)
	1560 dload (11, 1)
	1562 dload (11, 1)
	1564 dmul (11, 1)
	1565 dadd (11, 1)
	1566 dstore (11, 1)
	1568 goto (11, 2)
	1571 aload (11, 2)
	1573 iload (11, 2)
	1575 invokevirtual (11, 2)
	1578 dstore (11, 2)
	1580 dload (11, 2)
	1582 dload (11, 2)
	1584 dload (11, 2)
	1586 dmul (11, 2)
	1587 dadd (11, 2)
	1588 dstore (11, 2)
	1590 iinc (11, 2)
	1593 goto (11, 2)
	1596 dconst_0 (9, 1)
	1597 dstore (9, 1)
	1599 iconst_0 (10, 4)
	1600 istore (10, 4)
	1602 iload (10, 4)
	1604 iload (10, 4)
	1606 if_icmpge (10, 4)
	1609 aload (10, 4)
	1611 iload (10, 4)
	1613 invokevirtual (10, 4)
	1616 dstore (10, 4)
	1618 aload (11, 1)
	1620 iload (11, 1)
	1622 invokevirtual (11, 1)
	1625 dload (11, 1)
	1627 dcmpl (11, 1)
	1628 ifne (11, 1)
	1631 aload (11, 1)
	1633 iload (11, 1)
	1635 dload (11, 1)
	1637 dneg (11, 1)
	1638 dload (11, 1)
	1640 dmul (11, 1)
	1641 invokevirtual (11, 1)
	1644 aload_0 (11, 1)
	1645 getfield (11, 1)
	1648 iload (11, 1)
	1650 invokevirtual (11, 1)
	1653 aload_0 (11, 1)
	1654 getfield (11, 1)
	1657 iload (11, 1)
	1659 invokevirtual (11, 1)
	1662 aload (11, 1)
	1664 iload (11, 1)
	1666 invokevirtual (11, 1)
	1669 dadd (11, 1)
	1670 invokestatic (11, 1)
	1673 dstore (11, 1)
	1675 aload_0 (11, 1)
	1676 getfield (11, 1)
	1679 iload (11, 1)
	1681 aload_0 (11, 1)
	1682 getfield (11, 1)
	1685 iload (11, 1)
	1687 invokevirtual (11, 1)
	1690 dload (11, 1)
	1692 invokestatic (11, 1)
	1695 invokevirtual (11, 1)
	1698 goto (11, 1)
	1701 aload (11, 1)
	1703 iload (11, 1)
	1705 invokevirtual (11, 1)
	1708 dconst_0 (11, 1)
	1709 dcmpl (11, 1)
	1710 ifne (11, 1)
	1713 aload_0 (11, 1)
	1714 getfield (11, 1)
	1717 iload (11, 1)
	1719 aload_0 (11, 1)
	1720 getfield (11, 1)
	1723 iload (11, 1)
	1725 invokevirtual (11, 1)
	1728 invokevirtual (11, 1)
	1731 goto (11, 1)
	1734 dload (11, 1)
	1736 dconst_0 (11, 1)
	1737 dcmpl (11, 1)
	1738 ifle (11, 1)
	1741 aload_0 (11, 1)
	1742 getfield (11, 1)
	1745 iload (11, 1)
	1747 aload_0 (11, 1)
	1748 getfield (11, 1)
	1751 iload (11, 1)
	1753 invokevirtual (11, 1)
	1756 invokevirtual (11, 1)
	1759 goto (11, 1)
	1762 aload_0 (11, 1)
	1763 getfield (11, 1)
	1766 iload (11, 1)
	1768 aload_0 (11, 1)
	1769 getfield (11, 1)
	1772 iload (11, 1)
	1774 invokevirtual (11, 1)
	1777 invokevirtual (11, 1)
	1780 dload (10, 2)
	1782 dload (10, 2)
	1784 aload (10, 2)
	1786 iload (10, 2)
	1788 invokevirtual (10, 2)
	1791 dmul (10, 2)
	1792 dadd (10, 2)
	1793 dstore (10, 2)
	1795 iinc (10, 2)
	1798 goto (10, 2)
	1801 dconst_0 (9, 1)
	1802 dstore (9, 1)
	1804 iconst_0 (10, 4)
	1805 istore (10, 4)
	1807 iload (10, 4)
	1809 iload (10, 4)
	1811 if_icmpge (10, 4)
	1814 dconst_0 (10, 4)
	1815 dstore (10, 4)
	1817 iconst_0 (11, 4)
	1818 istore (11, 4)
	1820 iload (11, 4)
	1822 iload (11, 4)
	1824 if_icmpge (11, 4)
	1827 dload (11, 4)
	1829 aload_0 (11, 4)
	1830 getfield (11, 4)
	1833 iload (11, 4)
	1835 iload (11, 4)
	1837 invokevirtual (11, 4)
	1840 aload (11, 4)
	1842 iload (11, 4)
	1844 invokevirtual (11, 4)
	1847 dmul (11, 4)
	1848 dadd (11, 4)
	1849 dstore (11, 4)
	1851 iinc (11, 4)
	1854 goto (11, 4)
	1857 dload (10, 4)
	1859 aload (10, 4)
	1861 iload (10, 4)
	1863 invokevirtual (10, 4)
	1866 dload (10, 4)
	1868 dmul (10, 4)
	1869 dload (10, 4)
	1871 dmul (10, 4)
	1872 dadd (10, 4)
	1873 dstore (10, 4)
	1875 iinc (10, 4)
	1878 goto (10, 4)
	1881 iload (10, 1)
	1883 iconst_1 (10, 1)
	1884 if_icmpne (10, 1)
	1887 dload (10, 1)
	1889 dneg (10, 1)
	1890 dstore (10, 1)
	1892 dload (9, 1)
	1894 dload (9, 1)
	1896 dneg (9, 1)
	1897 dcmpl (9, 1)
	1898 ifle (9, 1)
	1901 dload (9, 1)
	1903 dload (9, 1)
	1905 dneg (9, 1)
	1906 dconst_1 (9, 1)
	1907 ldc2_w (9, 1)
	1910 invokestatic (10, 1)
	1913 dadd (10, 1)
	1914 dmul (10, 1)
	1915 dcmpg (10, 1)
	1916 ifge (10, 1)
	1919 dload (10, 1)
	1921 dneg (10, 1)
	1922 dload (10, 1)
	1924 ddiv (10, 1)
	1925 dstore (10, 1)
	1927 iconst_0 (11, 4)
	1928 istore (11, 4)
	1930 iload (11, 4)
	1932 iload (11, 4)
	1934 if_icmpge (11, 4)
	1937 aload_0 (11, 4)
	1938 getfield (11, 4)
	1941 iload (11, 4)
	1943 invokevirtual (11, 4)
	1946 dload (11, 4)
	1948 aload (11, 4)
	1950 iload (11, 4)
	1952 invokevirtual (11, 4)
	1955 dmul (11, 4)
	1956 dadd (11, 4)
	1957 dstore (11, 4)
	1959 aload_0 (11, 1)
	1960 getfield (11, 1)
	1963 iload (11, 1)
	1965 aload_0 (11, 1)
	1966 getfield (11, 1)
	1969 iload (11, 1)
	1971 invokevirtual (11, 1)
	1974 aload_0 (11, 1)
	1975 getfield (11, 1)
	1978 iload (11, 1)
	1980 invokevirtual (11, 1)
	1983 dload (11, 1)
	1985 invokestatic (11, 1)
	1988 invokestatic (11, 1)
	1991 invokevirtual (11, 1)
	1994 iinc (11, 1)
	1997 goto (11, 1)
	2000 ldc2_w (10, 1)
	2003 dload (10, 1)
	2005 dmul (10, 1)
	2006 dload (10, 1)
	2008 dmul (10, 1)
	2009 dstore (10, 1)
	2011 dload (10, 1)
	2013 dload (10, 1)
	2015 dmul (10, 1)
	2016 dstore (10, 1)
	2018 goto (10, 2)
	2021 dload (10, 2)
	2023 ldc2_w (10, 2)
	2026 dload (10, 2)
	2028 dmul (10, 2)
	2029 dadd (10, 2)
	2030 dstore (10, 2)
	2032 dload (10, 2)
	2034 dload (10, 2)
	2036 dmul (10, 2)
	2037 dstore (10, 2)
	2039 iload (10, 1)
	2041 ifne (10, 1)
	2044 iconst_0 (11, 4)
	2045 istore (11, 4)
	2047 iload (11, 4)
	2049 iload (11, 4)
	2051 if_icmpge (11, 4)
	2054 aload (11, 4)
	2056 iload (11, 4)
	2058 aload (11, 4)
	2060 iload (11, 4)
	2062 invokevirtual (11, 4)
	2065 dneg (11, 4)
	2066 invokevirtual (11, 4)
	2069 aload (11, 4)
	2071 iload (11, 4)
	2073 aload_0 (11, 4)
	2074 getfield (11, 4)
	2077 iload (11, 4)
	2079 invokevirtual (11, 4)
	2082 invokevirtual (11, 4)
	2085 iinc (11, 4)
	2088 goto (11, 4)
	2091 dload (10, 1)
	2093 dstore (10, 1)
	2095 iconst_1 (10, 1)
	2096 istore (10, 1)
	2098 goto (8, 1)
	2101 dload (9, 1)
	2103 dload (9, 1)
	2105 dcmpl (9, 1)
	2106 ifle (9, 1)
	2109 iconst_0 (10, 4)
	2110 istore (10, 4)
	2112 iload (10, 4)
	2114 iload (10, 4)
	2116 if_icmpge (10, 4)
	2119 aload_0 (10, 4)
	2120 getfield (10, 4)
	2123 iload (10, 4)
	2125 aload (10, 4)
	2127 iload (10, 4)
	2129 invokevirtual (10, 4)
	2132 invokevirtual (10, 4)
	2135 iinc (10, 4)
	2138 goto (10, 4)
	2141 dload (9, 1)
	2143 dstore (9, 1)
	2145 iconst_2 (8, 1)
	2146 newarray (8, 1)
	2148 dup (8, 1)
	2149 iconst_0 (8, 1)
	2150 dload (8, 1)
	2152 dastore (8, 1)
	2153 dup (8, 1)
	2154 iconst_1 (8, 1)
	2155 dload (8, 1)
	2157 dastore (8, 1)
	2158 areturn (8, 1)

Method: prelim
	0 invokestatic (0, 0)
	3 aload_0 (0, 0)
	4 getfield (0, 0)
	7 invokevirtual (0, 0)
	10 istore_3 (0, 0)
	11 aload_0 (0, 0)
	12 getfield (0, 0)
	15 istore (0, 0)
	17 aload_0 (0, 0)
	18 getfield (0, 0)
	21 invokevirtual (0, 0)
	24 istore (0, 0)
	26 aload_0 (0, 0)
	27 getfield (0, 0)
	30 aload_0 (0, 0)
	31 getfield (0, 0)
	34 dmul (0, 0)
	35 dstore (0, 0)
	37 dconst_1 (0, 0)
	38 dload (0, 0)
	40 ddiv (0, 0)
	41 dstore (0, 0)
	43 iload_3 (0, 0)
	44 iconst_1 (0, 0)
	45 iadd (0, 0)
	46 istore (0, 0)
	48 iconst_0 (1, 4)
	49 istore (1, 4)
	51 iload (1, 4)
	53 iload_3 (1, 4)
	54 if_icmpge (1, 4)
	57 aload_0 (1, 1)
	58 getfield (1, 1)
	61 iload (1, 1)
	63 aload_0 (1, 1)
	64 getfield (1, 1)
	67 iload (1, 1)
	69 invokevirtual (1, 1)
	72 invokevirtual (1, 1)
	75 iconst_0 (2, 4)
	76 istore (2, 4)
	78 iload (2, 4)
	80 iload (2, 4)
	82 if_icmpge (2, 4)
	85 aload_0 (2, 4)
	86 getfield (2, 4)
	89 iload (2, 4)
	91 iload (2, 4)
	93 dconst_0 (2, 4)
	94 invokevirtual (2, 4)
	97 iinc (2, 4)
	100 goto (2, 4)
	103 iconst_0 (2, 4)
	104 istore (2, 4)
	106 iload (2, 4)
	108 iload (2, 4)
	110 if_icmpge (2, 4)
	113 aload_0 (2, 4)
	114 getfield (2, 4)
	117 iload (2, 4)
	119 iload (2, 4)
	121 dconst_0 (2, 4)
	122 invokevirtual (2, 4)
	125 iinc (2, 4)
	128 goto (2, 4)
	131 iinc (2, 4)
	134 goto (2, 4)
	137 iconst_0 (2, 4)
	138 istore (2, 4)
	140 iload_3 (2, 4)
	141 iload (2, 4)
	143 imul (2, 4)
	144 iconst_2 (2, 4)
	145 idiv (2, 4)
	146 istore (2, 4)
	148 iload (2, 4)
	150 iload (2, 4)
	152 if_icmpge (2, 4)
	155 aload_0 (2, 4)
	156 getfield (2, 4)
	159 iload (2, 4)
	161 dconst_0 (2, 4)
	162 invokevirtual (2, 4)
	165 iinc (2, 4)
	168 goto (2, 4)
	171 iconst_0 (2, 4)
	172 istore (2, 4)
	174 iload (2, 4)
	176 iload (2, 4)
	178 if_icmpge (2, 4)
	181 aload_0 (2, 4)
	182 getfield (2, 4)
	185 iload (2, 4)
	187 dconst_0 (2, 4)
	188 invokevirtual (2, 4)
	191 iconst_0 (3, 4)
	192 istore (3, 4)
	194 iload (3, 4)
	196 iload (3, 4)
	198 isub (3, 4)
	199 istore (3, 4)
	201 iload (3, 4)
	203 iload (3, 4)
	205 if_icmpge (3, 4)
	208 aload_0 (3, 4)
	209 getfield (3, 4)
	212 iload (3, 4)
	214 iload (3, 4)
	216 dconst_0 (3, 4)
	217 invokevirtual (3, 4)
	220 iinc (3, 4)
	223 goto (3, 4)
	226 iinc (3, 4)
	229 goto (3, 4)
	232 iconst_0 (2, 4)
	233 istore (2, 4)
	235 iconst_0 (2, 4)
	236 istore (2, 4)
	238 ldc2_w (2, 4)
	241 dstore (2, 4)
	243 aload_0 (3, 4)
	244 invokevirtual (3, 4)
	247 istore (3, 4)
	249 iload (3, 4)
	251 iload_3 (3, 4)
	252 isub (3, 4)
	253 istore (3, 4)
	255 iload (3, 4)
	257 iconst_1 (3, 4)
	258 isub (3, 4)
	259 istore (3, 4)
	261 iload (3, 4)
	263 iconst_1 (3, 4)
	264 isub (3, 4)
	265 istore (3, 4)
	267 dconst_0 (3, 4)
	268 dstore (3, 4)
	270 dconst_0 (3, 4)
	271 dstore (3, 4)
	273 iload (4, 1)
	275 iconst_2 (4, 1)
	276 iload_3 (4, 1)
	277 imul (4, 1)
	278 if_icmpgt (4, 1)
	281 iload (4, 1)
	283 iconst_1 (4, 1)
	284 if_icmplt (4, 1)
	287 iload (4, 1)
	289 iload_3 (4, 1)
	290 if_icmpgt (4, 1)
	293 aload_0 (5, 1)
	294 getfield (5, 1)
	297 dstore (5, 1)
	299 aload_0 (6, 1)
	300 getfield (6, 1)
	303 iload (6, 1)
	305 invokevirtual (6, 1)
	308 dconst_0 (6, 1)
	309 dcmpl (6, 1)
	310 ifne (6, 1)
	313 dload (6, 1)
	315 dneg (6, 1)
	316 dstore (6, 1)
	318 aload_0 (5, 1)
	319 getfield (5, 1)
	322 iload (5, 1)
	324 iload (5, 1)
	326 dload (5, 1)
	328 invokevirtual (5, 1)
	331 goto (5, 1)
	334 iload (5, 1)
	336 iload_3 (5, 1)
	337 if_icmple (5, 1)
	340 aload_0 (5, 1)
	341 getfield (5, 1)
	344 iload (5, 1)
	346 iload (5, 1)
	348 invokevirtual (5, 1)
	351 dstore (5, 1)
	353 aload_0 (5, 1)
	354 getfield (5, 1)
	357 dneg (5, 1)
	358 dstore (5, 1)
	360 aload_0 (6, 1)
	361 getfield (6, 1)
	364 iload (6, 1)
	366 invokevirtual (6, 1)
	369 dconst_0 (6, 1)
	370 dcmpl (6, 1)
	371 ifne (6, 1)
	374 ldc2_w (6, 1)
	377 aload_0 (6, 1)
	378 getfield (6, 1)
	381 dmul (6, 1)
	382 aload_0 (6, 1)
	383 getfield (6, 1)
	386 iload (6, 1)
	388 invokevirtual (6, 1)
	391 invokestatic (6, 1)
	394 dstore (6, 1)
	396 aload_0 (6, 1)
	397 getfield (6, 1)
	400 iload (6, 1)
	402 invokevirtual (6, 1)
	405 dconst_0 (6, 1)
	406 dcmpl (6, 1)
	407 ifne (6, 1)
	410 ldc2_w (6, 1)
	413 aload_0 (6, 1)
	414 getfield (6, 1)
	417 dmul (6, 1)
	418 aload_0 (6, 1)
	419 getfield (6, 1)
	422 iload (6, 1)
	424 invokevirtual (6, 1)
	427 invokestatic (6, 1)
	430 dstore (6, 1)
	432 aload_0 (5, 1)
	433 getfield (5, 1)
	436 iload (5, 1)
	438 iload (5, 1)
	440 dload (5, 1)
	442 invokevirtual (5, 1)
	445 goto (5, 1)
	448 iload (4, 2)
	450 iload (4, 2)
	452 isub (4, 2)
	453 iload_3 (4, 2)
	454 idiv (4, 2)
	455 istore (4, 2)
	457 iload (4, 2)
	459 iload (4, 2)
	461 iload_3 (4, 2)
	462 imul (4, 2)
	463 isub (4, 2)
	464 iload_3 (4, 2)
	465 isub (4, 2)
	466 istore (4, 2)
	468 iload (4, 2)
	470 iload (4, 2)
	472 iadd (4, 2)
	473 istore (4, 2)
	475 iload (5, 1)
	477 iload_3 (5, 1)
	478 if_icmple (5, 1)
	481 iload (5, 1)
	483 istore (5, 1)
	485 iload (5, 1)
	487 iload_3 (5, 1)
	488 isub (5, 1)
	489 istore (5, 1)
	491 iload (5, 1)
	493 istore (5, 1)
	495 iload (4, 2)
	497 iconst_1 (4, 2)
	498 isub (4, 2)
	499 istore (4, 2)
	501 iload (4, 2)
	503 iconst_1 (4, 2)
	504 isub (4, 2)
	505 istore (4, 2)
	507 aload_0 (4, 2)
	508 getfield (4, 2)
	511 iload (4, 2)
	513 iload (4, 2)
	515 aload_0 (4, 2)
	516 getfield (4, 2)
	519 iload (4, 2)
	521 iload (4, 2)
	523 invokevirtual (4, 2)
	526 invokevirtual (4, 2)
	529 aload_0 (4, 2)
	530 getfield (4, 2)
	533 iload (4, 2)
	535 iload (4, 2)
	537 aload_0 (4, 2)
	538 getfield (4, 2)
	541 iload (4, 2)
	543 iload (4, 2)
	545 invokevirtual (4, 2)
	548 invokevirtual (4, 2)
	551 iconst_0 (4, 4)
	552 istore (4, 4)
	554 iload (4, 4)
	556 iload_3 (4, 4)
	557 if_icmpge (4, 4)
	560 aload_0 (4, 4)
	561 getfield (4, 4)
	564 iload (4, 4)
	566 aload_1 (4, 4)
	567 iload (4, 4)
	569 daload (4, 4)
	570 aload_0 (4, 4)
	571 getfield (4, 4)
	574 iload (4, 4)
	576 invokevirtual (4, 1)
	579 aload_0 (4, 1)
	580 getfield (4, 1)
	583 iload (4, 1)
	585 iload (4, 1)
	587 invokevirtual (4, 1)
	590 dadd (4, 1)
	591 invokestatic (4, 1)
	594 aload_2 (4, 1)
	595 iload (4, 1)
	597 daload (4, 1)
	598 invokestatic (4, 1)
	601 invokevirtual (4, 1)
	604 aload_0 (5, 1)
	605 getfield (5, 1)
	608 iload (5, 1)
	610 iload (5, 1)
	612 invokevirtual (5, 1)
	615 aload_0 (5, 1)
	616 getfield (5, 1)
	619 iload (5, 1)
	621 invokevirtual (5, 1)
	624 dcmpl (5, 1)
	625 ifne (5, 1)
	628 aload_0 (5, 1)
	629 getfield (5, 1)
	632 iload (5, 1)
	634 aload_1 (5, 1)
	635 iload (5, 1)
	637 daload (5, 1)
	638 invokevirtual (5, 1)
	641 aload_0 (5, 1)
	642 getfield (5, 1)
	645 iload (5, 1)
	647 iload (5, 1)
	649 invokevirtual (5, 1)
	652 aload_0 (5, 1)
	653 getfield (5, 1)
	656 iload (5, 1)
	658 invokevirtual (5, 1)
	661 dcmpl (5, 1)
	662 ifne (5, 1)
	665 aload_0 (5, 1)
	666 getfield (5, 1)
	669 iload (5, 1)
	671 aload_2 (5, 1)
	672 iload (5, 1)
	674 daload (5, 1)
	675 invokevirtual (5, 1)
	678 iinc (5, 1)
	681 goto (5, 1)
	684 aload_0 (4, 1)
	685 aload_0 (4, 1)
	686 getfield (4, 1)
	689 invokevirtual (4, 1)
	692 invokevirtual (4, 1)
	695 dstore (4, 1)
	697 aload_0 (4, 1)
	698 getfield (4, 1)
	701 ifeq (4, 1)
	704 dload (4, 1)
	706 goto (4, 1)
	709 dload (4, 1)
	711 dneg (4, 1)
	712 dstore (4, 1)
	714 aload_0 (4, 1)
	715 invokevirtual (4, 1)
	718 istore (4, 1)
	720 aload_0 (4, 1)
	721 getfield (4, 1)
	724 iload (4, 1)
	726 dload (4, 1)
	728 invokevirtual (4, 1)
	731 iload (5, 1)
	733 iconst_1 (5, 1)
	734 if_icmpne (5, 1)
	737 dload (5, 1)
	739 dstore (5, 1)
	741 aload_0 (5, 1)
	742 iconst_0 (5, 1)
	743 putfield (5, 1)
	746 goto (5, 1)
	749 dload (5, 1)
	751 aload_0 (5, 1)
	752 getfield (5, 1)
	755 aload_0 (5, 1)
	756 getfield (5, 1)
	759 invokevirtual (5, 1)
	762 dcmpg (5, 1)
	763 ifge (5, 1)
	766 aload_0 (5, 1)
	767 iload (5, 1)
	769 putfield (5, 1)
	772 iload (5, 1)
	774 iconst_2 (5, 1)
	775 iload_3 (5, 1)
	776 imul (5, 1)
	777 iconst_1 (5, 1)
	778 iadd (5, 1)
	779 if_icmpgt (5, 1)
	782 iload (5, 1)
	784 iconst_2 (5, 1)
	785 if_icmplt (5, 1)
	788 iload (5, 1)
	790 iload_3 (5, 1)
	791 iconst_1 (5, 1)
	792 iadd (5, 1)
	793 if_icmpgt (5, 1)
	796 aload_0 (6, 1)
	797 getfield (6, 1)
	800 iload (6, 1)
	802 dload (6, 1)
	804 dload (6, 1)
	806 dsub (6, 1)
	807 dload (6, 1)
	809 ddiv (6, 1)
	810 invokevirtual (6, 1)
	813 iload (7, 1)
	815 iload (7, 1)
	817 iload_3 (7, 1)
	818 iadd (7, 1)
	819 if_icmpge (7, 1)
	822 dconst_1 (7, 1)
	823 dload (7, 1)
	825 ddiv (7, 1)
	826 dstore (7, 1)
	828 aload_0 (7, 1)
	829 getfield (7, 1)
	832 iconst_0 (7, 1)
	833 iload (7, 1)
	835 dload (7, 1)
	837 dneg (7, 1)
	838 invokevirtual (7, 1)
	841 aload_0 (7, 1)
	842 getfield (7, 1)
	845 iload (7, 1)
	847 iload (7, 1)
	849 dload (7, 1)
	851 invokevirtual (7, 1)
	854 aload_0 (7, 1)
	855 getfield (7, 1)
	858 iload (7, 1)
	860 iload (7, 1)
	862 iadd (7, 1)
	863 iload (7, 1)
	865 ldc2_w (7, 1)
	868 dload (7, 1)
	870 dmul (7, 1)
	871 invokevirtual (7, 1)
	874 goto (6, 1)
	877 iload (6, 1)
	879 iload_3 (6, 1)
	880 iconst_2 (6, 1)
	881 iadd (6, 1)
	882 if_icmplt (6, 1)
	885 iload (6, 1)
	887 iload (6, 1)
	889 iconst_1 (6, 1)
	890 iadd (6, 1)
	891 imul (6, 1)
	892 iconst_2 (6, 1)
	893 idiv (6, 1)
	894 iconst_1 (6, 1)
	895 isub (6, 1)
	896 istore (6, 1)
	898 dload (6, 1)
	900 dload (6, 1)
	902 dsub (6, 1)
	903 dload (6, 1)
	905 ddiv (6, 1)
	906 dstore (6, 1)
	908 dload (6, 1)
	910 dload (6, 1)
	912 dsub (6, 1)
	913 dstore (6, 1)
	915 aload_0 (6, 1)
	916 getfield (6, 1)
	919 iload (6, 1)
	921 ldc2_w (6, 1)
	924 dload (6, 1)
	926 aload_0 (6, 1)
	927 getfield (6, 1)
	930 iload (6, 1)
	932 invokevirtual (6, 1)
	935 dsub (6, 1)
	936 dmul (6, 1)
	937 dload (6, 1)
	939 ddiv (6, 1)
	940 invokevirtual (6, 1)
	943 aload_0 (6, 1)
	944 getfield (6, 1)
	947 iload (6, 1)
	949 aload_0 (6, 1)
	950 getfield (6, 1)
	953 iload (6, 1)
	955 invokevirtual (6, 1)
	958 dload (6, 1)
	960 dmul (6, 1)
	961 dload (6, 1)
	963 dload (6, 1)
	965 dmul (6, 1)
	966 dsub (6, 1)
	967 dload (6, 1)
	969 ddiv (6, 1)
	970 invokevirtual (6, 1)
	973 dload (7, 1)
	975 dload (7, 1)
	977 dmul (7, 1)
	978 dconst_0 (7, 1)
	979 dcmpg (7, 1)
	980 ifge (7, 1)
	983 dload (7, 1)
	985 aload_0 (7, 1)
	986 getfield (7, 1)
	989 iload (7, 1)
	991 iload_3 (7, 1)
	992 isub (7, 1)
	993 invokevirtual (7, 1)
	996 dcmpg (7, 1)
	997 ifge (7, 1)
	1000 aload_0 (7, 1)
	1001 getfield (7, 1)
	1004 iload (7, 1)
	1006 aload_0 (7, 1)
	1007 getfield (7, 1)
	1010 iload (7, 1)
	1012 iload_3 (7, 1)
	1013 isub (7, 1)
	1014 invokevirtual (7, 1)
	1017 invokevirtual (7, 1)
	1020 aload_0 (7, 1)
	1021 getfield (7, 1)
	1024 iload (7, 1)
	1026 iload_3 (7, 1)
	1027 isub (7, 1)
	1028 dload (7, 1)
	1030 invokevirtual (7, 1)
	1033 aload_0 (8, 1)
	1034 getfield (8, 1)
	1037 iload (8, 1)
	1039 if_icmpne (8, 1)
	1042 aload_0 (8, 1)
	1043 iload (8, 1)
	1045 iload_3 (8, 1)
	1046 isub (8, 1)
	1047 putfield (8, 1)
	1050 aload_0 (7, 1)
	1051 getfield (7, 1)
	1054 iload (7, 1)
	1056 iload_3 (7, 1)
	1057 isub (7, 1)
	1058 iload (7, 1)
	1060 dload (7, 1)
	1062 invokevirtual (7, 1)
	1065 aload_0 (7, 1)
	1066 getfield (7, 1)
	1069 iload (7, 1)
	1071 iload (7, 1)
	1073 dload (7, 1)
	1075 invokevirtual (7, 1)
	1078 aload_0 (6, 1)
	1079 getfield (6, 1)
	1082 iconst_0 (6, 1)
	1083 iload (6, 1)
	1085 dload (6, 1)
	1087 dload (6, 1)
	1089 dadd (6, 1)
	1090 dneg (6, 1)
	1091 dload (6, 1)
	1093 dload (6, 1)
	1095 dmul (6, 1)
	1096 ddiv (6, 1)
	1097 invokevirtual (6, 1)
	1100 aload_0 (6, 1)
	1101 getfield (6, 1)
	1104 iload (6, 1)
	1106 iload (6, 1)
	1108 ldc2_w (6, 1)
	1111 aload_0 (6, 1)
	1112 getfield (6, 1)
	1115 iload (6, 1)
	1117 iload_3 (6, 1)
	1118 isub (6, 1)
	1119 iload (6, 1)
	1121 invokevirtual (6, 1)
	1124 ddiv (6, 1)
	1125 invokevirtual (6, 1)
	1128 aload_0 (6, 1)
	1129 getfield (6, 1)
	1132 iload (6, 1)
	1134 iload_3 (6, 1)
	1135 isub (6, 1)
	1136 iload (6, 1)
	1138 aload_0 (6, 1)
	1139 getfield (6, 1)
	1142 iconst_0 (6, 1)
	1143 iload (6, 1)
	1145 invokevirtual (6, 1)
	1148 dneg (6, 1)
	1149 aload_0 (6, 1)
	1150 getfield (6, 1)
	1153 iload (6, 1)
	1155 iload (6, 1)
	1157 invokevirtual (6, 1)
	1160 dsub (6, 1)
	1161 invokevirtual (6, 1)
	1164 aload_0 (6, 1)
	1165 getfield (6, 1)
	1168 iconst_0 (6, 1)
	1169 iload (6, 1)
	1171 ldc2_w (6, 1)
	1174 invokestatic (6, 1)
	1177 dload (6, 1)
	1179 dload (6, 1)
	1181 dmul (6, 1)
	1182 ddiv (6, 1)
	1183 invokevirtual (6, 1)
	1186 aload_0 (6, 1)
	1187 getfield (6, 1)
	1190 iload (6, 1)
	1192 iload (6, 1)
	1194 ldc2_w (6, 1)
	1197 invokestatic (6, 1)
	1200 dload (6, 1)
	1202 ddiv (6, 1)
	1203 invokevirtual (6, 1)
	1206 aload_0 (6, 1)
	1207 getfield (6, 1)
	1210 iload (6, 1)
	1212 iload_3 (6, 1)
	1213 isub (6, 1)
	1214 iload (6, 1)
	1216 aload_0 (6, 1)
	1217 getfield (6, 1)
	1220 iconst_0 (6, 1)
	1221 iload (6, 1)
	1223 invokevirtual (6, 1)
	1226 dneg (6, 1)
	1227 aload_0 (6, 1)
	1228 getfield (6, 1)
	1231 iload (6, 1)
	1233 iload (6, 1)
	1235 invokevirtual (6, 1)
	1238 dsub (6, 1)
	1239 invokevirtual (6, 1)
	1242 goto (5, 1)
	1245 aload_0 (5, 2)
	1246 getfield (5, 2)
	1249 iconst_0 (5, 2)
	1250 iload (5, 2)
	1252 dload (5, 2)
	1254 invokevirtual (5, 2)
	1257 aload_0 (5, 2)
	1258 getfield (5, 2)
	1261 iload (5, 2)
	1263 iload (5, 2)
	1265 dload (5, 2)
	1267 invokevirtual (5, 2)
	1270 aload_0 (5, 2)
	1271 getfield (5, 2)
	1274 iload (5, 2)
	1276 iload (5, 2)
	1278 dload (5, 2)
	1280 dneg (5, 2)
	1281 invokevirtual (5, 2)
	1284 aload_0 (5, 2)
	1285 getfield (5, 2)
	1288 iload (5, 2)
	1290 iload (5, 2)
	1292 dload (5, 2)
	1294 dneg (5, 2)
	1295 invokevirtual (5, 2)
	1298 iload (5, 2)
	1300 iload (5, 2)
	1302 iconst_1 (5, 2)
	1303 isub (5, 2)
	1304 imul (5, 2)
	1305 iconst_2 (5, 2)
	1306 idiv (5, 2)
	1307 iload (5, 2)
	1309 iadd (5, 2)
	1310 iconst_1 (5, 2)
	1311 isub (5, 2)
	1312 istore (5, 2)
	1314 aload_0 (5, 2)
	1315 getfield (5, 2)
	1318 iload (5, 2)
	1320 iload (5, 2)
	1322 iconst_1 (5, 2)
	1323 isub (5, 2)
	1324 invokevirtual (5, 2)
	1327 aload_0 (5, 2)
	1328 getfield (5, 2)
	1331 iload (5, 2)
	1333 iload (5, 2)
	1335 iconst_1 (5, 2)
	1336 isub (5, 2)
	1337 invokevirtual (5, 2)
	1340 dmul (5, 2)
	1341 dstore (5, 2)
	1343 aload_0 (5, 2)
	1344 getfield (5, 2)
	1347 iload (5, 2)
	1349 dload (5, 2)
	1351 aload_0 (5, 2)
	1352 getfield (5, 2)
	1355 iload (5, 2)
	1357 invokevirtual (5, 2)
	1360 dsub (5, 2)
	1361 aload_0 (5, 2)
	1362 getfield (5, 2)
	1365 iload (5, 2)
	1367 invokevirtual (5, 2)
	1370 dsub (5, 2)
	1371 dload (5, 2)
	1373 dadd (5, 2)
	1374 dload (5, 2)
	1376 ddiv (5, 2)
	1377 invokevirtual (5, 2)
	1380 aload_0 (3, 1)
	1381 invokevirtual (3, 1)
	1384 iload (3, 1)
	1386 if_icmplt (3, 1)
	1389 return (2, 1)

Method: trsbox
	0 invokestatic (0, 0)
	3 aload_0 (0, 0)
	4 getfield (0, 0)
	7 invokevirtual (0, 0)
	10 istore (0, 0)
	12 aload_0 (0, 0)
	13 getfield (0, 0)
	16 istore (0, 0)
	18 ldc2_w (0, 0)
	21 dstore (0, 0)
	23 ldc2_w (0, 0)
	26 dstore (0, 0)
	28 dconst_0 (0, 0)
	29 dstore (0, 0)
	31 iconst_m1 (0, 0)
	32 istore (0, 0)
	34 iconst_0 (0, 0)
	35 istore (0, 0)
	37 dconst_0 (0, 0)
	38 dstore (0, 0)
	40 dconst_0 (0, 0)
	41 dstore (0, 0)
	43 dconst_0 (0, 0)
	44 dstore (0, 0)
	46 dconst_0 (0, 0)
	47 dstore (0, 0)
	49 dconst_0 (0, 0)
	50 dstore (0, 0)
	52 dconst_0 (0, 0)
	53 dstore (0, 0)
	55 dconst_0 (0, 0)
	56 dstore (0, 0)
	58 dconst_0 (0, 0)
	59 dstore (0, 0)
	61 dconst_0 (0, 0)
	62 dstore (0, 0)
	64 dconst_0 (0, 0)
	65 dstore (0, 0)
	67 dconst_0 (0, 0)
	68 dstore (0, 0)
	70 dconst_0 (0, 0)
	71 dstore (0, 0)
	73 dconst_0 (0, 0)
	74 dstore (0, 0)
	76 dconst_0 (0, 0)
	77 dstore (0, 0)
	79 dconst_0 (0, 0)
	80 dstore (0, 0)
	82 dconst_0 (0, 0)
	83 dstore (0, 0)
	85 dconst_0 (0, 0)
	86 dstore (0, 0)
	88 iconst_0 (0, 0)
	89 istore (0, 0)
	91 dconst_0 (0, 0)
	92 dstore (0, 0)
	94 dconst_0 (0, 0)
	95 dstore (0, 0)
	97 dconst_0 (0, 0)
	98 dstore (0, 0)
	100 dconst_0 (0, 0)
	101 dstore (0, 0)
	103 iconst_0 (0, 0)
	104 istore (0, 0)
	106 iconst_0 (0, 4)
	107 istore (0, 4)
	109 iconst_0 (0, 4)
	110 istore (0, 4)
	112 iconst_0 (1, 4)
	113 istore (1, 4)
	115 iload (1, 4)
	117 iload (1, 4)
	119 if_icmpge (1, 4)
	122 aload (1, 4)
	124 iload (1, 4)
	126 dconst_0 (1, 4)
	127 invokevirtual (1, 4)
	130 aload_0 (2, 1)
	131 getfield (2, 1)
	134 iload (2, 1)
	136 invokevirtual (2, 1)
	139 aload_0 (2, 1)
	140 getfield (2, 1)
	143 iload (2, 1)
	145 invokevirtual (2, 1)
	148 dcmpg (2, 1)
	149 ifgt (2, 1)
	152 aload_0 (3, 1)
	153 getfield (3, 1)
	156 iload (3, 1)
	158 invokevirtual (3, 1)
	161 dconst_0 (3, 1)
	162 dcmpl (3, 1)
	163 iflt (3, 1)
	166 aload (3, 1)
	168 iload (3, 1)
	170 ldc2_w (3, 1)
	173 invokevirtual (3, 1)
	176 goto (3, 1)
	179 aload_0 (1, 1)
	180 getfield (1, 1)
	183 iload (1, 1)
	185 invokevirtual (1, 1)
	188 aload_0 (1, 1)
	189 getfield (1, 1)
	192 iload (1, 1)
	194 invokevirtual (1, 1)
	197 dcmpl (1, 1)
	198 iflt (1, 1)
	201 aload_0 (1, 1)
	202 getfield (1, 1)
	205 iload (1, 1)
	207 invokevirtual (2, 1)
	210 dconst_0 (2, 1)
	211 dcmpg (2, 1)
	212 ifgt (2, 1)
	215 aload (2, 1)
	217 iload (2, 1)
	219 dconst_1 (2, 1)
	220 invokevirtual (2, 1)
	223 aload (2, 1)
	225 iload (2, 1)
	227 invokevirtual (2, 1)
	230 dconst_0 (2, 1)
	231 dcmpl (2, 1)
	232 ifeq (2, 1)
	235 iinc (2, 1)
	238 aload_0 (1, 4)
	239 getfield (1, 4)
	242 iload (1, 4)
	244 dconst_0 (1, 4)
	245 invokevirtual (1, 4)
	248 aload_3 (1, 4)
	249 iload (1, 4)
	251 aload_0 (1, 4)
	252 getfield (1, 4)
	255 iload (1, 4)
	257 invokevirtual (1, 4)
	260 invokevirtual (1, 4)
	263 iinc (1, 4)
	266 goto (1, 4)
	269 dload_1 (0, 4)
	270 dload_1 (0, 4)
	271 dmul (0, 4)
	272 dstore (0, 4)
	274 dconst_0 (0, 4)
	275 dstore (0, 4)
	277 ldc2_w (0, 4)
	280 dstore (0, 4)
	282 bipush (0, 4)
	284 istore (0, 4)
	286 iload (2, 5)
	288 lookupswitch (2, 5)
	372 bipush (3, 5)
	374 invokestatic (3, 5)
	377 dconst_0 (3, 5)
	378 dstore (3, 5)
	380 bipush (3, 4)
	382 invokestatic (3, 4)
	385 dconst_0 (3, 4)
	386 dstore (3, 4)
	388 iconst_0 (4, 4)
	389 istore (4, 4)
	391 iload (4, 4)
	393 iload (4, 4)
	395 if_icmpge (4, 4)
	398 aload (5, 1)
	400 iload (5, 1)
	402 invokevirtual (5, 1)
	405 dconst_0 (5, 1)
	406 dcmpl (5, 1)
	407 ifeq (5, 1)
	410 aload (5, 1)
	412 iload (5, 1)
	414 dconst_0 (5, 1)
	415 invokevirtual (5, 1)
	418 goto (5, 1)
	421 dload (5, 1)
	423 dconst_0 (5, 1)
	424 dcmpl (5, 1)
	425 ifne (5, 1)
	428 aload (5, 1)
	430 iload (5, 1)
	432 aload_3 (5, 1)
	433 iload (5, 1)
	435 invokevirtual (5, 1)
	438 dneg (5, 1)
	439 invokevirtual (5, 1)
	442 goto (5, 1)
	445 aload (5, 2)
	447 iload (5, 2)
	449 dload (5, 2)
	451 aload (5, 2)
	453 iload (5, 2)
	455 invokevirtual (5, 2)
	458 dmul (5, 2)
	459 aload_3 (5, 2)
	460 iload (5, 2)
	462 invokevirtual (5, 2)
	465 dsub (5, 2)
	466 invokevirtual (5, 2)
	469 aload (4, 1)
	471 iload (4, 1)
	473 invokevirtual (4, 1)
	476 dstore (4, 1)
	478 dload (4, 1)
	480 dload (4, 1)
	482 dload (4, 1)
	484 dmul (4, 1)
	485 dadd (4, 1)
	486 dstore (4, 1)
	488 iinc (4, 1)
	491 goto (4, 1)
	494 dload (4, 1)
	496 dconst_0 (4, 1)
	497 dcmpl (4, 1)
	498 ifne (4, 1)
	501 sipush (4, 1)
	504 istore (4, 1)
	506 goto (4, 1)
	509 dload (4, 1)
	511 dconst_0 (4, 1)
	512 dcmpl (4, 1)
	513 ifne (4, 1)
	516 dload (4, 1)
	518 dstore (4, 1)
	520 iload (4, 1)
	522 iload (4, 1)
	524 iadd (4, 1)
	525 iload (4, 1)
	527 isub (4, 1)
	528 istore (4, 1)
	530 dload (4, 1)
	532 dload (4, 1)
	534 dmul (4, 1)
	535 dload (4, 1)
	537 ldc2_w (4, 1)
	540 dmul (4, 1)
	541 dload (4, 1)
	543 dmul (4, 1)
	544 dcmpg (4, 1)
	545 ifgt (4, 1)
	548 sipush (4, 1)
	551 istore (4, 1)
	553 goto (4, 1)
	556 sipush (3, 4)
	559 istore (3, 4)
	561 goto (3, 4)
	564 bipush (3, 1)
	566 invokestatic (3, 1)
	569 dload (3, 1)
	571 dstore (3, 1)
	573 dconst_0 (3, 1)
	574 dstore (3, 1)
	576 dconst_0 (3, 1)
	577 dstore (3, 1)
	579 iconst_0 (4, 4)
	580 istore (4, 4)
	582 iload (4, 4)
	584 iload (4, 4)
	586 if_icmpge (4, 4)
	589 aload (5, 1)
	591 iload (5, 1)
	593 invokevirtual (5, 1)
	596 dconst_0 (5, 1)
	597 dcmpl (5, 1)
	598 ifne (5, 1)
	601 aload_0 (5, 1)
	602 getfield (5, 1)
	605 iload (5, 1)
	607 invokevirtual (5, 1)
	610 dstore (5, 1)
	612 dload (5, 1)
	614 dload (5, 1)
	616 dload (5, 1)
	618 dmul (5, 1)
	619 dsub (5, 1)
	620 dstore (5, 1)
	622 dload (5, 1)
	624 aload (5, 1)
	626 iload (5, 1)
	628 invokevirtual (5, 1)
	631 aload_0 (5, 1)
	632 getfield (5, 1)
	635 iload (5, 1)
	637 invokevirtual (5, 1)
	640 dmul (5, 1)
	641 dadd (5, 1)
	642 dstore (5, 1)
	644 dload (5, 1)
	646 aload (5, 1)
	648 iload (5, 1)
	650 invokevirtual (5, 1)
	653 aload (5, 1)
	655 iload (5, 1)
	657 invokevirtual (5, 1)
	660 dmul (5, 1)
	661 dadd (5, 1)
	662 dstore (5, 1)
	664 iinc (5, 1)
	667 goto (5, 1)
	670 dload (5, 1)
	672 dconst_0 (5, 1)
	673 dcmpg (5, 1)
	674 ifgt (5, 1)
	677 bipush (5, 1)
	679 istore (5, 1)
	681 goto (5, 1)
	684 dload (4, 4)
	686 dload (4, 4)
	688 dmul (4, 4)
	689 dload (4, 4)
	691 dload (4, 4)
	693 dmul (4, 4)
	694 dadd (4, 4)
	695 invokestatic (4, 4)
	698 dstore (4, 4)
	700 dload (5, 1)
	702 dconst_0 (5, 1)
	703 dcmpg (5, 1)
	704 ifge (5, 1)
	707 dload (5, 1)
	709 dload (5, 1)
	711 dsub (5, 1)
	712 dload (5, 1)
	714 ddiv (5, 1)
	715 dstore (5, 1)
	717 goto (5, 1)
	720 dload (5, 2)
	722 dload (5, 2)
	724 dload (5, 2)
	726 dadd (5, 2)
	727 ddiv (5, 2)
	728 dstore (5, 2)
	730 dload (4, 1)
	732 dstore (4, 1)
	734 dload (5, 1)
	736 dconst_0 (5, 1)
	737 dcmpl (5, 1)
	738 ifle (5, 1)
	741 dload (5, 1)
	743 dload (5, 1)
	745 dload (5, 1)
	747 ddiv (5, 1)
	748 invokestatic (5, 1)
	751 dstore (5, 1)
	753 iconst_m1 (4, 1)
	754 istore (4, 1)
	756 iconst_0 (5, 4)
	757 istore (5, 4)
	759 iload (5, 4)
	761 iload (5, 4)
	763 if_icmpge (5, 4)
	766 aload (6, 1)
	768 iload (6, 1)
	770 invokevirtual (6, 1)
	773 dconst_0 (6, 1)
	774 dcmpl (6, 1)
	775 ifeq (6, 1)
	778 aload_0 (6, 1)
	779 getfield (6, 1)
	782 iload (6, 1)
	784 invokevirtual (6, 1)
	787 aload_0 (6, 1)
	788 getfield (6, 1)
	791 iload (6, 1)
	793 invokevirtual (6, 1)
	796 dadd (6, 1)
	797 dstore (6, 1)
	799 aload (7, 1)
	801 iload (7, 1)
	803 invokevirtual (7, 1)
	806 dconst_0 (7, 1)
	807 dcmpl (7, 1)
	808 ifle (7, 1)
	811 aload_0 (7, 1)
	812 getfield (7, 1)
	815 iload (7, 1)
	817 invokevirtual (7, 1)
	820 dload (7, 1)
	822 dsub (7, 1)
	823 aload (7, 1)
	825 iload (7, 1)
	827 invokevirtual (7, 1)
	830 ddiv (7, 1)
	831 dstore (7, 1)
	833 goto (7, 1)
	836 aload_0 (7, 1)
	837 getfield (7, 1)
	840 iload (7, 1)
	842 invokevirtual (7, 1)
	845 dload (7, 1)
	847 dsub (7, 1)
	848 aload (7, 1)
	850 iload (7, 1)
	852 invokevirtual (7, 1)
	855 ddiv (7, 1)
	856 dstore (7, 1)
	858 dload (7, 1)
	860 dload (7, 1)
	862 dcmpg (7, 1)
	863 ifge (7, 1)
	866 dload (7, 1)
	868 dstore (7, 1)
	870 iload (7, 1)
	872 istore (7, 1)
	874 iinc (7, 1)
	877 goto (7, 1)
	880 dconst_0 (6, 1)
	881 dstore (6, 1)
	883 dload (7, 1)
	885 dconst_0 (7, 1)
	886 dcmpl (7, 1)
	887 ifle (7, 1)
	890 iinc (7, 1)
	893 dload (7, 1)
	895 dload (7, 1)
	897 ddiv (7, 1)
	898 dstore (7, 1)
	900 iload (8, 1)
	902 iconst_m1 (8, 1)
	903 if_icmpne (8, 1)
	906 dload (8, 1)
	908 dconst_0 (8, 1)
	909 dcmpl (8, 1)
	910 ifle (8, 1)
	913 dload (8, 1)
	915 dload (8, 1)
	917 invokestatic (8, 1)
	920 dstore (8, 1)
	922 dload (9, 1)
	924 ldc2_w (9, 1)
	927 dcmpl (9, 1)
	928 ifne (9, 1)
	931 dload (9, 1)
	933 dstore (9, 1)
	935 dload (7, 1)
	937 dstore (7, 1)
	939 dconst_0 (7, 1)
	940 dstore (7, 1)
	942 iconst_0 (8, 4)
	943 istore (8, 4)
	945 iload (8, 4)
	947 iload (8, 4)
	949 if_icmpge (8, 4)
	952 aload_3 (8, 4)
	953 iload (8, 4)
	955 aload_3 (8, 4)
	956 iload (8, 4)
	958 invokevirtual (8, 4)
	961 dload (8, 4)
	963 aload (8, 4)
	965 iload (8, 4)
	967 invokevirtual (8, 4)
	970 dmul (8, 4)
	971 dadd (8, 4)
	972 invokevirtual (8, 4)
	975 aload (9, 1)
	977 iload (9, 1)
	979 invokevirtual (9, 1)
	982 dconst_0 (9, 1)
	983 dcmpl (9, 1)
	984 ifne (9, 1)
	987 aload_3 (9, 1)
	988 iload (9, 1)
	990 invokevirtual (9, 1)
	993 dstore (9, 1)
	995 dload (9, 1)
	997 dload (9, 1)
	999 dload (9, 1)
	1001 dmul (9, 1)
	1002 dadd (9, 1)
	1003 dstore (9, 1)
	1005 aload_0 (8, 4)
	1006 getfield (8, 4)
	1009 iload (8, 4)
	1011 aload_0 (8, 4)
	1012 getfield (8, 4)
	1015 iload (8, 4)
	1017 invokevirtual (8, 4)
	1020 dload (8, 4)
	1022 aload (8, 4)
	1024 iload (8, 4)
	1026 invokevirtual (8, 4)
	1029 dmul (8, 4)
	1030 dadd (8, 4)
	1031 invokevirtual (8, 4)
	1034 iinc (8, 4)
	1037 goto (8, 4)
	1040 dload (7, 1)
	1042 dload (7, 1)
	1044 ldc2_w (7, 1)
	1047 dload (7, 1)
	1049 dmul (7, 1)
	1050 dload (7, 1)
	1052 dmul (7, 1)
	1053 dsub (7, 1)
	1054 dmul (7, 1)
	1055 dstore (7, 1)
	1057 dload (7, 1)
	1059 dconst_0 (7, 1)
	1060 invokestatic (7, 1)
	1063 dstore (7, 1)
	1065 dload (7, 1)
	1067 dload (7, 1)
	1069 dadd (7, 1)
	1070 dstore (7, 1)
	1072 iload (7, 1)
	1074 iflt (7, 1)
	1077 iinc (7, 1)
	1080 aload (7, 1)
	1082 iload (7, 1)
	1084 dconst_1 (7, 1)
	1085 invokevirtual (7, 1)
	1088 aload (8, 1)
	1090 iload (8, 1)
	1092 invokevirtual (8, 1)
	1095 dconst_0 (8, 1)
	1096 dcmpg (8, 1)
	1097 ifge (8, 1)
	1100 aload (8, 1)
	1102 iload (8, 1)
	1104 ldc2_w (8, 1)
	1107 invokevirtual (8, 1)
	1110 aload_0 (7, 1)
	1111 getfield (7, 1)
	1114 iload (7, 1)
	1116 invokevirtual (7, 1)
	1119 dstore (7, 1)
	1121 dload (7, 1)
	1123 dload (7, 1)
	1125 dload (7, 1)
	1127 dmul (7, 1)
	1128 dsub (7, 1)
	1129 dstore (7, 1)
	1131 dload (8, 1)
	1133 dconst_0 (8, 1)
	1134 dcmpg (8, 1)
	1135 ifgt (8, 1)
	1138 sipush (8, 1)
	1141 istore (8, 1)
	1143 goto (8, 1)
	1146 bipush (7, 1)
	1148 istore (7, 1)
	1150 goto (7, 1)
	1153 dload (7, 1)
	1155 dload (7, 1)
	1157 dcmpg (7, 1)
	1158 ifge (7, 1)
	1161 iload (8, 1)
	1163 iload (8, 1)
	1165 if_icmpne (8, 1)
	1168 sipush (8, 1)
	1171 istore (8, 1)
	1173 goto (8, 1)
	1176 dload (8, 1)
	1178 dload (8, 1)
	1180 ldc2_w (8, 1)
	1183 dmul (8, 1)
	1184 dcmpg (8, 1)
	1185 ifgt (8, 1)
	1188 sipush (8, 1)
	1191 istore (8, 1)
	1193 goto (8, 1)
	1196 dload (7, 1)
	1198 dload (7, 1)
	1200 ddiv (7, 1)
	1201 dstore (7, 1)
	1203 bipush (7, 1)
	1205 istore (7, 1)
	1207 goto (7, 1)
	1210 bipush (6, 1)
	1212 invokestatic (6, 1)
	1215 dconst_0 (6, 1)
	1216 dstore (6, 1)
	1218 bipush (6, 1)
	1220 invokestatic (6, 1)
	1223 iload (7, 1)
	1225 iload (7, 1)
	1227 iconst_1 (7, 1)
	1228 isub (7, 1)
	1229 if_icmplt (7, 1)
	1232 sipush (7, 1)
	1235 istore (7, 1)
	1237 goto (7, 1)
	1240 dconst_0 (6, 1)
	1241 dstore (6, 1)
	1243 dconst_0 (6, 1)
	1244 dstore (6, 1)
	1246 dconst_0 (6, 1)
	1247 dstore (6, 1)
	1249 iconst_0 (7, 4)
	1250 istore (7, 4)
	1252 iload (7, 4)
	1254 iload (7, 4)
	1256 if_icmpge (7, 4)
	1259 aload (8, 1)
	1261 iload (8, 1)
	1263 invokevirtual (8, 1)
	1266 dconst_0 (8, 1)
	1267 dcmpl (8, 1)
	1268 ifne (8, 1)
	1271 aload_0 (8, 1)
	1272 getfield (8, 1)
	1275 iload (8, 1)
	1277 invokevirtual (8, 1)
	1280 dstore (8, 1)
	1282 dload (8, 1)
	1284 dload (8, 1)
	1286 dload (8, 1)
	1288 dmul (8, 1)
	1289 dadd (8, 1)
	1290 dstore (8, 1)
	1292 dload (8, 1)
	1294 aload_0 (8, 1)
	1295 getfield (8, 1)
	1298 iload (8, 1)
	1300 invokevirtual (8, 1)
	1303 aload_3 (8, 1)
	1304 iload (8, 1)
	1306 invokevirtual (8, 1)
	1309 dmul (8, 1)
	1310 dadd (8, 1)
	1311 dstore (8, 1)
	1313 aload_3 (8, 1)
	1314 iload (8, 1)
	1316 invokevirtual (8, 1)
	1319 dstore (8, 1)
	1321 dload (8, 1)
	1323 dload (8, 1)
	1325 dload (8, 1)
	1327 dmul (8, 1)
	1328 dadd (8, 1)
	1329 dstore (8, 1)
	1331 aload (8, 1)
	1333 iload (8, 1)
	1335 aload_0 (8, 1)
	1336 getfield (8, 1)
	1339 iload (8, 1)
	1341 invokevirtual (8, 1)
	1344 invokevirtual (8, 1)
	1347 goto (8, 2)
	1350 aload (8, 2)
	1352 iload (8, 2)
	1354 dconst_0 (8, 2)
	1355 invokevirtual (8, 2)
	1358 iinc (8, 2)
	1361 goto (8, 2)
	1364 iload (7, 2)
	1366 istore (7, 2)
	1368 sipush (7, 2)
	1371 istore (7, 2)
	1373 goto (7, 2)
	1376 bipush (7, 1)
	1378 invokestatic (7, 1)
	1381 iinc (7, 1)
	1384 dload (7, 1)
	1386 dload (7, 1)
	1388 dmul (7, 1)
	1389 dload (7, 1)
	1391 dload (7, 1)
	1393 dmul (7, 1)
	1394 dsub (7, 1)
	1395 dstore (7, 1)
	1397 dload (8, 1)
	1399 dload (8, 1)
	1401 ldc2_w (8, 1)
	1404 dmul (8, 1)
	1405 dload (8, 1)
	1407 dmul (8, 1)
	1408 dcmpg (8, 1)
	1409 ifgt (8, 1)
	1412 sipush (8, 1)
	1415 istore (8, 1)
	1417 goto (8, 1)
	1420 dload (7, 1)
	1422 invokestatic (7, 1)
	1425 dstore (7, 1)
	1427 iconst_0 (8, 4)
	1428 istore (8, 4)
	1430 iload (8, 4)
	1432 iload (8, 4)
	1434 if_icmpge (8, 4)
	1437 aload (9, 1)
	1439 iload (9, 1)
	1441 invokevirtual (9, 1)
	1444 dconst_0 (9, 1)
	1445 dcmpl (9, 1)
	1446 ifne (9, 1)
	1449 aload (9, 1)
	1451 iload (9, 1)
	1453 dload (9, 1)
	1455 aload_0 (9, 1)
	1456 getfield (9, 1)
	1459 iload (9, 1)
	1461 invokevirtual (9, 1)
	1464 dmul (9, 1)
	1465 dload (9, 1)
	1467 aload_3 (9, 1)
	1468 iload (9, 1)
	1470 invokevirtual (9, 1)
	1473 dmul (9, 1)
	1474 dsub (9, 1)
	1475 dload (9, 1)
	1477 ddiv (9, 1)
	1478 invokevirtual (9, 1)
	1481 goto (9, 1)
	1484 aload (9, 2)
	1486 iload (9, 2)
	1488 dconst_0 (9, 2)
	1489 invokevirtual (9, 2)
	1492 iinc (9, 2)
	1495 goto (9, 2)
	1498 dload (8, 2)
	1500 dneg (8, 2)
	1501 dstore (8, 2)
	1503 dconst_1 (8, 1)
	1504 dstore (8, 1)
	1506 iconst_m1 (8, 1)
	1507 istore (8, 1)
	1509 iconst_0 (9, 4)
	1510 istore (9, 4)
	1512 iload (9, 4)
	1514 iload (9, 4)
	1516 if_icmpge (9, 4)
	1519 aload (10, 1)
	1521 iload (10, 1)
	1523 invokevirtual (10, 1)
	1526 dconst_0 (10, 1)
	1527 dcmpl (10, 1)
	1528 ifne (10, 1)
	1531 aload_0 (10, 1)
	1532 getfield (10, 1)
	1535 iload (10, 1)
	1537 invokevirtual (10, 1)
	1540 aload_0 (10, 1)
	1541 getfield (10, 1)
	1544 iload (10, 1)
	1546 invokevirtual (10, 1)
	1549 dadd (10, 1)
	1550 aload_0 (10, 1)
	1551 getfield (10, 1)
	1554 iload (10, 1)
	1556 invokevirtual (10, 1)
	1559 dsub (10, 1)
	1560 dstore (10, 1)
	1562 aload_0 (10, 1)
	1563 getfield (10, 1)
	1566 iload (10, 1)
	1568 invokevirtual (10, 1)
	1571 aload_0 (10, 1)
	1572 getfield (10, 1)
	1575 iload (10, 1)
	1577 invokevirtual (10, 1)
	1580 dsub (10, 1)
	1581 aload_0 (10, 1)
	1582 getfield (10, 1)
	1585 iload (10, 1)
	1587 invokevirtual (10, 1)
	1590 dsub (10, 1)
	1591 dstore (10, 1)
	1593 dload (11, 1)
	1595 dconst_0 (11, 1)
	1596 dcmpg (11, 1)
	1597 ifgt (11, 1)
	1600 iinc (11, 1)
	1603 aload (11, 1)
	1605 iload (11, 1)
	1607 ldc2_w (11, 1)
	1610 invokevirtual (11, 1)
	1613 bipush (11, 1)
	1615 istore (11, 1)
	1617 goto (11, 1)
	1620 dload (11, 1)
	1622 dconst_0 (11, 1)
	1623 dcmpg (11, 1)
	1624 ifgt (11, 1)
	1627 iinc (11, 1)
	1630 aload (11, 1)
	1632 iload (11, 1)
	1634 dconst_1 (11, 1)
	1635 invokevirtual (11, 1)
	1638 bipush (11, 1)
	1640 istore (11, 1)
	1642 goto (11, 1)
	1645 aload_0 (10, 1)
	1646 getfield (10, 1)
	1649 iload (10, 1)
	1651 invokevirtual (10, 1)
	1654 dstore (10, 1)
	1656 aload (10, 1)
	1658 iload (10, 1)
	1660 invokevirtual (10, 1)
	1663 dstore (10, 1)
	1665 dload (10, 1)
	1667 dload (10, 1)
	1669 dmul (10, 1)
	1670 dload (10, 1)
	1672 dload (10, 1)
	1674 dmul (10, 1)
	1675 dadd (10, 1)
	1676 dstore (10, 1)
	1678 aload_0 (10, 1)
	1679 getfield (10, 1)
	1682 iload (10, 1)
	1684 invokevirtual (10, 1)
	1687 aload_0 (10, 1)
	1688 getfield (10, 1)
	1691 iload (10, 1)
	1693 invokevirtual (10, 1)
	1696 dsub (10, 1)
	1697 dstore (10, 1)
	1699 dload (10, 1)
	1701 dload (10, 1)
	1703 dload (10, 1)
	1705 dmul (10, 1)
	1706 dsub (10, 1)
	1707 dstore (10, 1)
	1709 dload (11, 1)
	1711 dconst_0 (11, 1)
	1712 dcmpl (11, 1)
	1713 ifle (11, 1)
	1716 dload (11, 1)
	1718 invokestatic (11, 1)
	1721 aload (11, 1)
	1723 iload (11, 1)
	1725 invokevirtual (11, 1)
	1728 dsub (11, 1)
	1729 dstore (11, 1)
	1731 dload (12, 1)
	1733 dload (12, 1)
	1735 dmul (12, 1)
	1736 dload (12, 1)
	1738 dcmpl (12, 1)
	1739 ifle (12, 1)
	1742 dload (12, 1)
	1744 dload (12, 1)
	1746 ddiv (12, 1)
	1747 dstore (12, 1)
	1749 iload (12, 1)
	1751 istore (12, 1)
	1753 ldc2_w (12, 1)
	1756 dstore (12, 1)
	1758 aload_0 (10, 1)
	1759 getfield (10, 1)
	1762 iload (10, 1)
	1764 invokevirtual (10, 1)
	1767 aload_0 (10, 1)
	1768 getfield (10, 1)
	1771 iload (10, 1)
	1773 invokevirtual (10, 1)
	1776 dsub (10, 1)
	1777 dstore (10, 1)
	1779 dload (10, 1)
	1781 dload (10, 1)
	1783 dload (10, 1)
	1785 dmul (10, 1)
	1786 dsub (10, 1)
	1787 dstore (10, 1)
	1789 dload (11, 1)
	1791 dconst_0 (11, 1)
	1792 dcmpl (11, 1)
	1793 ifle (11, 1)
	1796 dload (11, 1)
	1798 invokestatic (11, 1)
	1801 aload (11, 1)
	1803 iload (11, 1)
	1805 invokevirtual (11, 1)
	1808 dadd (11, 1)
	1809 dstore (11, 1)
	1811 dload (12, 1)
	1813 dload (12, 1)
	1815 dmul (12, 1)
	1816 dload (12, 1)
	1818 dcmpl (12, 1)
	1819 ifle (12, 1)
	1822 dload (12, 1)
	1824 dload (12, 1)
	1826 ddiv (12, 1)
	1827 dstore (12, 1)
	1829 iload (12, 1)
	1831 istore (12, 1)
	1833 dconst_1 (12, 1)
	1834 dstore (12, 1)
	1836 iinc (12, 1)
	1839 goto (12, 1)
	1842 sipush (11, 4)
	1845 istore (11, 4)
	1847 goto (11, 4)
	1850 sipush (11, 1)
	1853 invokestatic (11, 1)
	1856 dconst_0 (11, 1)
	1857 dstore (11, 1)
	1859 dconst_0 (11, 1)
	1860 dstore (11, 1)
	1862 dconst_0 (11, 1)
	1863 dstore (11, 1)
	1865 iconst_0 (12, 4)
	1866 istore (12, 4)
	1868 iload (12, 4)
	1870 iload (12, 4)
	1872 if_icmpge (12, 4)
	1875 aload (13, 1)
	1877 iload (13, 1)
	1879 invokevirtual (13, 1)
	1882 dconst_0 (13, 1)
	1883 dcmpl (13, 1)
	1884 ifne (13, 1)
	1887 dload (13, 1)
	1889 aload (13, 1)
	1891 iload (13, 1)
	1893 invokevirtual (13, 1)
	1896 aload (13, 1)
	1898 iload (13, 1)
	1900 invokevirtual (13, 1)
	1903 dmul (13, 1)
	1904 dadd (13, 1)
	1905 dstore (13, 1)
	1907 dload (13, 1)
	1909 aload_0 (13, 1)
	1910 getfield (13, 1)
	1913 iload (13, 1)
	1915 invokevirtual (13, 1)
	1918 aload (13, 1)
	1920 iload (13, 1)
	1922 invokevirtual (13, 1)
	1925 dmul (13, 1)
	1926 dadd (13, 1)
	1927 dstore (13, 1)
	1929 dload (13, 1)
	1931 aload_0 (13, 1)
	1932 getfield (13, 1)
	1935 iload (13, 1)
	1937 invokevirtual (13, 1)
	1940 aload (13, 1)
	1942 iload (13, 1)
	1944 invokevirtual (13, 1)
	1947 dmul (13, 1)
	1948 dadd (13, 1)
	1949 dstore (13, 1)
	1951 iinc (13, 1)
	1954 goto (13, 1)
	1957 dconst_0 (12, 4)
	1958 dstore (12, 4)
	1960 iconst_m1 (12, 4)
	1961 istore (12, 4)
	1963 dconst_0 (12, 4)
	1964 dstore (12, 4)
	1966 dload (12, 4)
	1968 ldc2_w (12, 4)
	1971 dmul (12, 4)
	1972 ldc2_w (12, 4)
	1975 dadd (12, 4)
	1976 d2i (12, 4)
	1977 istore (12, 4)
	1979 iconst_0 (13, 4)
	1980 istore (13, 4)
	1982 iload (13, 4)
	1984 iload (13, 4)
	1986 if_icmpge (13, 4)
	1989 dload (13, 4)
	1991 iload (13, 4)
	1993 i2d (13, 4)
	1994 dmul (13, 4)
	1995 iload (13, 4)
	1997 i2d (13, 4)
	1998 ddiv (13, 4)
	1999 dstore (13, 4)
	2001 dload (13, 4)
	2003 dload (13, 4)
	2005 dadd (13, 4)
	2006 dconst_1 (13, 4)
	2007 dload (13, 4)
	2009 dload (13, 4)
	2011 dmul (13, 4)
	2012 dadd (13, 4)
	2013 ddiv (13, 4)
	2014 dstore (13, 4)
	2016 dload (13, 4)
	2018 dload (13, 4)
	2020 dload (13, 4)
	2022 dload (13, 4)
	2024 dmul (13, 4)
	2025 dload (13, 4)
	2027 dsub (13, 4)
	2028 dload (13, 4)
	2030 dsub (13, 4)
	2031 dmul (13, 4)
	2032 dadd (13, 4)
	2033 dstore (13, 4)
	2035 dload (13, 4)
	2037 dload (13, 4)
	2039 dload (13, 4)
	2041 dmul (13, 4)
	2042 dload (13, 4)
	2044 dsub (13, 4)
	2045 ldc2_w (13, 4)
	2048 dload (13, 4)
	2050 dmul (13, 4)
	2051 dload (13, 4)
	2053 dmul (13, 4)
	2054 dsub (13, 4)
	2055 dmul (13, 4)
	2056 dstore (13, 4)
	2058 dload (14, 1)
	2060 dload (14, 1)
	2062 dcmpl (14, 1)
	2063 ifle (14, 1)
	2066 dload (14, 1)
	2068 dstore (14, 1)
	2070 iload (14, 1)
	2072 istore (14, 1)
	2074 dload (14, 1)
	2076 dstore (14, 1)
	2078 goto (14, 1)
	2081 iload (14, 1)
	2083 iload (14, 1)
	2085 iconst_1 (14, 1)
	2086 iadd (14, 1)
	2087 if_icmpne (14, 1)
	2090 dload (14, 1)
	2092 dstore (14, 1)
	2094 dload (13, 1)
	2096 dstore (13, 1)
	2098 iinc (13, 1)
	2101 goto (13, 1)
	2104 iload (13, 1)
	2106 ifge (13, 1)
	2109 sipush (13, 1)
	2112 istore (13, 1)
	2114 goto (13, 1)
	2117 iload (13, 1)
	2119 iload (13, 1)
	2121 if_icmpge (13, 1)
	2124 dload (13, 1)
	2126 dload (13, 1)
	2128 dsub (13, 1)
	2129 dload (13, 1)
	2131 dload (13, 1)
	2133 dadd (13, 1)
	2134 dload (13, 1)
	2136 dsub (13, 1)
	2137 dload (13, 1)
	2139 dsub (13, 1)
	2140 ddiv (13, 1)
	2141 dstore (13, 1)
	2143 dload (13, 1)
	2145 iload (13, 1)
	2147 i2d (13, 1)
	2148 ldc2_w (13, 1)
	2151 dload (13, 1)
	2153 dmul (13, 1)
	2154 dadd (13, 1)
	2155 dmul (13, 1)
	2156 iload (13, 1)
	2158 i2d (13, 1)
	2159 ddiv (13, 1)
	2160 dstore (13, 1)
	2162 dconst_1 (12, 1)
	2163 dload (12, 1)
	2165 dload (12, 1)
	2167 dmul (12, 1)
	2168 dsub (12, 1)
	2169 dconst_1 (12, 1)
	2170 dload (12, 1)
	2172 dload (12, 1)
	2174 dmul (12, 1)
	2175 dadd (12, 1)
	2176 ddiv (12, 1)
	2177 dstore (12, 1)
	2179 dload (12, 1)
	2181 dload (12, 1)
	2183 dadd (12, 1)
	2184 dconst_1 (12, 1)
	2185 dload (12, 1)
	2187 dload (12, 1)
	2189 dmul (12, 1)
	2190 dadd (12, 1)
	2191 ddiv (12, 1)
	2192 dstore (12, 1)
	2194 dload (12, 1)
	2196 dload (12, 1)
	2198 dload (12, 1)
	2200 dload (12, 1)
	2202 dmul (12, 1)
	2203 dload (12, 1)
	2205 dsub (12, 1)
	2206 dload (12, 1)
	2208 dsub (12, 1)
	2209 dmul (12, 1)
	2210 dadd (12, 1)
	2211 dstore (12, 1)
	2213 dload (12, 1)
	2215 dload (12, 1)
	2217 dload (12, 1)
	2219 dmul (12, 1)
	2220 dload (12, 1)
	2222 dsub (12, 1)
	2223 ldc2_w (12, 1)
	2226 dload (12, 1)
	2228 dmul (12, 1)
	2229 dload (12, 1)
	2231 dmul (12, 1)
	2232 dsub (12, 1)
	2233 dmul (12, 1)
	2234 dstore (12, 1)
	2236 dload (13, 1)
	2238 dconst_0 (13, 1)
	2239 dcmpg (13, 1)
	2240 ifgt (13, 1)
	2243 sipush (13, 1)
	2246 istore (13, 1)
	2248 goto (13, 1)
	2251 dconst_0 (12, 1)
	2252 dstore (12, 1)
	2254 dconst_0 (12, 1)
	2255 dstore (12, 1)
	2257 iconst_0 (13, 4)
	2258 istore (13, 4)
	2260 iload (13, 4)
	2262 iload (13, 4)
	2264 if_icmpge (13, 4)
	2267 aload_3 (13, 4)
	2268 iload (13, 4)
	2270 aload_3 (13, 4)
	2271 iload (13, 4)
	2273 invokevirtual (13, 4)
	2276 dload (13, 4)
	2278 dconst_1 (13, 4)
	2279 dsub (13, 4)
	2280 aload (13, 4)
	2282 iload (13, 4)
	2284 invokevirtual (13, 4)
	2287 dmul (13, 4)
	2288 dadd (13, 4)
	2289 dload (13, 4)
	2291 aload (13, 4)
	2293 iload (13, 4)
	2295 invokevirtual (13, 4)
	2298 dmul (13, 4)
	2299 dadd (13, 4)
	2300 invokevirtual (13, 4)
	2303 aload (14, 1)
	2305 iload (14, 1)
	2307 invokevirtual (14, 1)
	2310 dconst_0 (14, 1)
	2311 dcmpl (14, 1)
	2312 ifne (14, 1)
	2315 aload_0 (14, 1)
	2316 getfield (14, 1)
	2319 iload (14, 1)
	2321 dload (14, 1)
	2323 aload_0 (14, 1)
	2324 getfield (14, 1)
	2327 iload (14, 1)
	2329 invokevirtual (14, 1)
	2332 dmul (14, 1)
	2333 dload (14, 1)
	2335 aload (14, 1)
	2337 iload (14, 1)
	2339 invokevirtual (14, 1)
	2342 dmul (14, 1)
	2343 dadd (14, 1)
	2344 invokevirtual (14, 1)
	2347 dload (14, 1)
	2349 aload_0 (14, 1)
	2350 getfield (14, 1)
	2353 iload (14, 1)
	2355 invokevirtual (14, 1)
	2358 aload_3 (14, 1)
	2359 iload (14, 1)
	2361 invokevirtual (14, 1)
	2364 dmul (14, 1)
	2365 dadd (14, 1)
	2366 dstore (14, 1)
	2368 aload_3 (14, 1)
	2369 iload (14, 1)
	2371 invokevirtual (14, 1)
	2374 dstore (14, 1)
	2376 dload (14, 1)
	2378 dload (14, 1)
	2380 dload (14, 1)
	2382 dmul (14, 1)
	2383 dadd (14, 1)
	2384 dstore (14, 1)
	2386 aload (13, 4)
	2388 iload (13, 4)
	2390 dload (13, 4)
	2392 aload (13, 4)
	2394 iload (13, 4)
	2396 invokevirtual (13, 4)
	2399 dmul (13, 4)
	2400 dload (13, 4)
	2402 aload (13, 4)
	2404 iload (13, 4)
	2406 invokevirtual (13, 4)
	2409 dmul (13, 4)
	2410 dadd (13, 4)
	2411 invokevirtual (13, 4)
	2414 iinc (13, 4)
	2417 goto (13, 4)
	2420 dload (12, 1)
	2422 dload (12, 1)
	2424 dadd (12, 1)
	2425 dstore (12, 1)
	2427 iload (13, 1)
	2429 iflt (13, 1)
	2432 iload (13, 1)
	2434 iload (13, 1)
	2436 if_icmpne (13, 1)
	2439 iinc (13, 1)
	2442 aload (13, 1)
	2444 iload (13, 1)
	2446 dload (13, 1)
	2448 invokevirtual (13, 1)
	2451 bipush (13, 1)
	2453 istore (13, 1)
	2455 goto (13, 1)
	2458 dload (13, 1)
	2460 dload (13, 1)
	2462 ldc2_w (13, 1)
	2465 dmul (13, 1)
	2466 dcmpl (13, 1)
	2467 ifle (13, 1)
	2470 bipush (13, 1)
	2472 istore (13, 1)
	2474 goto (13, 1)
	2477 sipush (12, 1)
	2480 invokestatic (12, 1)
	2483 dconst_0 (12, 1)
	2484 dstore (12, 1)
	2486 iconst_0 (13, 4)
	2487 istore (13, 4)
	2489 iload (13, 4)
	2491 iload (13, 4)
	2493 if_icmpge (13, 4)
	2496 aload_0 (13, 4)
	2497 getfield (13, 4)
	2500 iload (13, 4)
	2502 invokevirtual (13, 4)
	2505 aload_0 (13, 4)
	2506 getfield (13, 4)
	2509 iload (13, 4)
	2511 invokevirtual (13, 4)
	2514 dadd (13, 4)
	2515 aload_0 (13, 4)
	2516 getfield (13, 4)
	2519 iload (13, 4)
	2521 invokevirtual (13, 1)
	2524 invokestatic (13, 1)
	2527 dstore (13, 1)
	2529 aload_0 (13, 1)
	2530 getfield (13, 1)
	2533 iload (13, 1)
	2535 dload (13, 1)
	2537 aload_0 (13, 1)
	2538 getfield (13, 1)
	2541 iload (13, 1)
	2543 invokevirtual (13, 1)
	2546 invokestatic (13, 1)
	2549 invokevirtual (13, 1)
	2552 aload (14, 1)
	2554 iload (14, 1)
	2556 invokevirtual (14, 1)
	2559 ldc2_w (14, 1)
	2562 dcmpl (14, 1)
	2563 ifne (14, 1)
	2566 aload_0 (14, 1)
	2567 getfield (14, 1)
	2570 iload (14, 1)
	2572 aload_0 (14, 1)
	2573 getfield (14, 1)
	2576 iload (14, 1)
	2578 invokevirtual (14, 1)
	2581 invokevirtual (14, 1)
	2584 aload (14, 1)
	2586 iload (14, 1)
	2588 invokevirtual (14, 1)
	2591 dconst_1 (14, 1)
	2592 dcmpl (14, 1)
	2593 ifne (14, 1)
	2596 aload_0 (14, 1)
	2597 getfield (14, 1)
	2600 iload (14, 1)
	2602 aload_0 (14, 1)
	2603 getfield (14, 1)
	2606 iload (14, 1)
	2608 invokevirtual (14, 1)
	2611 invokevirtual (14, 1)
	2614 aload_0 (13, 1)
	2615 getfield (13, 1)
	2618 iload (13, 1)
	2620 aload_0 (13, 1)
	2621 getfield (13, 1)
	2624 iload (13, 1)
	2626 invokevirtual (13, 1)
	2629 aload_0 (13, 1)
	2630 getfield (13, 1)
	2633 iload (13, 1)
	2635 invokevirtual (13, 1)
	2638 dsub (13, 1)
	2639 invokevirtual (13, 1)
	2642 aload_0 (13, 1)
	2643 getfield (13, 1)
	2646 iload (13, 1)
	2648 invokevirtual (13, 1)
	2651 dstore (13, 1)
	2653 dload (13, 1)
	2655 dload (13, 1)
	2657 dload (13, 1)
	2659 dmul (13, 1)
	2660 dadd (13, 1)
	2661 dstore (13, 1)
	2663 iinc (13, 1)
	2666 goto (13, 1)
	2669 iconst_2 (12, 1)
	2670 newarray (12, 1)
	2672 dup (12, 1)
	2673 iconst_0 (12, 1)
	2674 dload (12, 1)
	2676 dastore (12, 1)
	2677 dup (12, 1)
	2678 iconst_1 (12, 1)
	2679 dload (12, 1)
	2681 dastore (12, 1)
	2682 areturn (12, 1)
	2683 sipush (12, 1)
	2686 invokestatic (12, 1)
	2689 iconst_0 (12, 1)
	2690 istore (12, 1)
	2692 iconst_0 (13, 4)
	2693 istore (13, 4)
	2695 iload (13, 4)
	2697 iload (13, 4)
	2699 if_icmpge (13, 4)
	2702 aload (13, 4)
	2704 iload (13, 4)
	2706 dconst_0 (13, 4)
	2707 invokevirtual (13, 4)
	2710 iconst_0 (14, 4)
	2711 istore (14, 4)
	2713 iload (14, 4)
	2715 iload (14, 4)
	2717 if_icmpgt (14, 4)
	2720 iload (15, 1)
	2722 iload (15, 1)
	2724 if_icmpge (15, 1)
	2727 aload (15, 1)
	2729 iload (15, 1)
	2731 aload (15, 1)
	2733 iload (15, 1)
	2735 invokevirtual (15, 1)
	2738 aload_0 (15, 1)
	2739 getfield (15, 1)
	2742 iload (15, 1)
	2744 invokevirtual (15, 1)
	2747 aload (15, 1)
	2749 iload (15, 1)
	2751 invokevirtual (15, 1)
	2754 dmul (15, 1)
	2755 dadd (15, 1)
	2756 invokevirtual (15, 1)
	2759 aload (14, 4)
	2761 iload (14, 4)
	2763 aload (14, 4)
	2765 iload (14, 4)
	2767 invokevirtual (14, 4)
	2770 aload_0 (14, 4)
	2771 getfield (14, 4)
	2774 iload (14, 4)
	2776 invokevirtual (14, 4)
	2779 aload (14, 4)
	2781 iload (14, 4)
	2783 invokevirtual (14, 4)
	2786 dmul (14, 4)
	2787 dadd (14, 4)
	2788 invokevirtual (14, 4)
	2791 iinc (14, 4)
	2794 iinc (14, 4)
	2797 goto (14, 4)
	2800 iinc (14, 4)
	2803 goto (14, 4)
	2806 aload_0 (13, 4)
	2807 getfield (13, 4)
	2810 aload (13, 4)
	2812 invokevirtual (13, 4)
	2815 aload_0 (13, 4)
	2816 getfield (13, 4)
	2819 invokevirtual (13, 4)
	2822 astore (13, 4)
	2824 iconst_0 (14, 4)
	2825 istore (14, 4)
	2827 iload (14, 4)
	2829 iload (14, 4)
	2831 if_icmpge (14, 4)
	2834 aload_0 (15, 1)
	2835 getfield (15, 1)
	2838 iload (15, 1)
	2840 invokevirtual (15, 1)
	2843 dconst_0 (15, 1)
	2844 dcmpl (15, 1)
	2845 ifeq (15, 1)
	2848 iconst_0 (16, 4)
	2849 istore (16, 4)
	2851 iload (16, 4)
	2853 iload (16, 4)
	2855 if_icmpge (16, 4)
	2858 aload (16, 4)
	2860 iload (16, 4)
	2862 aload (16, 4)
	2864 iload (16, 4)
	2866 invokevirtual (16, 4)
	2869 aload (16, 4)
	2871 iload (16, 4)
	2873 invokevirtual (16, 4)
	2876 aload_0 (16, 4)
	2877 getfield (16, 4)
	2880 iload (16, 4)
	2882 iload (16, 4)
	2884 invokevirtual (16, 4)
	2887 dmul (16, 4)
	2888 dadd (16, 4)
	2889 invokevirtual (16, 4)
	2892 iinc (16, 4)
	2895 goto (16, 4)
	2898 iinc (16, 4)
	2901 goto (16, 4)
	2904 dload (16, 1)
	2906 dconst_0 (16, 1)
	2907 dcmpl (16, 1)
	2908 ifeq (16, 1)
	2911 bipush (16, 1)
	2913 istore (16, 1)
	2915 goto (16, 1)
	2918 iload (16, 1)
	2920 iload (16, 1)
	2922 if_icmple (16, 1)
	2925 sipush (16, 1)
	2928 istore (16, 1)
	2930 goto (16, 1)
	2933 iconst_0 (16, 4)
	2934 istore (16, 4)
	2936 iload (16, 4)
	2938 iload (16, 4)
	2940 if_icmpge (16, 4)
	2943 aload (16, 4)
	2945 iload (16, 4)
	2947 aload (16, 4)
	2949 iload (16, 4)
	2951 invokevirtual (16, 4)
	2954 invokevirtual (16, 4)
	2957 iinc (16, 4)
	2960 goto (16, 4)
	2963 bipush (15, 1)
	2965 istore (15, 1)
	2967 goto (15, 1)
	2970 new (15, 4)
	2973 dup (15, 4)
	2974 getstatic (15, 4)
	2977 iconst_1 (15, 4)
	2978 anewarray (15, 4)
	2981 dup (15, 4)
	2982 iconst_0 (15, 4)
	2983 ldc (15, 4)
	2985 aastore (15, 4)
	2986 invokespecial (15, 4)
	2989 athrow (15, 4)

Method: update
	0 invokestatic (0, 0)
	3 aload_0 (0, 0)
	4 getfield (0, 0)
	7 invokevirtual (0, 0)
	10 istore (0, 0)
	12 aload_0 (0, 0)
	13 getfield (0, 0)
	16 istore (0, 0)
	18 iload (0, 0)
	20 iload (0, 0)
	22 isub (0, 0)
	23 iconst_1 (0, 0)
	24 isub (0, 0)
	25 istore (0, 0)
	27 new (0, 0)
	30 dup (0, 0)
	31 iload (0, 0)
	33 iload (0, 0)
	35 iadd (0, 0)
	36 invokespecial (0, 0)
	39 astore (0, 0)
	41 dconst_0 (0, 0)
	42 dstore (0, 0)
	44 iconst_0 (1, 4)
	45 istore (1, 4)
	47 iload (1, 4)
	49 iload (1, 4)
	51 if_icmpge (1, 4)
	54 iconst_0 (2, 4)
	55 istore (2, 4)
	57 iload (2, 4)
	59 iload (2, 4)
	61 if_icmpge (2, 4)
	64 dload (2, 4)
	66 aload_0 (2, 4)
	67 getfield (2, 4)
	70 iload (2, 4)
	72 iload (2, 4)
	74 invokevirtual (2, 4)
	77 invokestatic (2, 4)
	80 invokestatic (2, 4)
	83 dstore (2, 4)
	85 iinc (2, 4)
	88 goto (2, 4)
	91 iinc (2, 4)
	94 goto (2, 4)
	97 dload (1, 4)
	99 ldc2_w (1, 4)
	102 dmul (1, 4)
	103 dstore (1, 4)
	105 iconst_1 (2, 4)
	106 istore (2, 4)
	108 iload (2, 4)
	110 iload (2, 4)
	112 if_icmpge (2, 4)
	115 aload_0 (2, 4)
	116 getfield (2, 4)
	119 iload (2, 4)
	121 iload (2, 4)
	123 invokevirtual (2, 4)
	126 dstore (2, 4)
	128 dload (3, 1)
	130 invokestatic (3, 1)
	133 dload (3, 1)
	135 dcmpl (3, 1)
	136 ifle (3, 1)
	139 aload_0 (3, 1)
	140 getfield (3, 1)
	143 iload (3, 1)
	145 iconst_0 (3, 1)
	146 invokevirtual (3, 1)
	149 dstore (3, 1)
	151 aload_0 (3, 1)
	152 getfield (3, 1)
	155 iload (3, 1)
	157 iload (3, 1)
	159 invokevirtual (3, 1)
	162 dstore (3, 1)
	164 dload (3, 1)
	166 dload (3, 1)
	168 dmul (3, 1)
	169 dload (3, 1)
	171 dload (3, 1)
	173 dmul (3, 1)
	174 dadd (3, 1)
	175 invokestatic (3, 1)
	178 dstore (3, 1)
	180 aload_0 (3, 1)
	181 getfield (3, 1)
	184 iload (3, 1)
	186 iconst_0 (3, 1)
	187 invokevirtual (3, 1)
	190 dload (3, 1)
	192 ddiv (3, 1)
	193 dstore (3, 1)
	195 aload_0 (3, 1)
	196 getfield (3, 1)
	199 iload (3, 1)
	201 iload (3, 1)
	203 invokevirtual (3, 1)
	206 dload (3, 1)
	208 ddiv (3, 1)
	209 dstore (3, 1)
	211 iconst_0 (4, 4)
	212 istore (4, 4)
	214 iload (4, 4)
	216 iload (4, 4)
	218 if_icmpge (4, 4)
	221 dload (4, 4)
	223 aload_0 (4, 4)
	224 getfield (4, 4)
	227 iload (4, 4)
	229 iconst_0 (4, 4)
	230 invokevirtual (4, 4)
	233 dmul (4, 4)
	234 dload (4, 4)
	236 aload_0 (4, 4)
	237 getfield (4, 4)
	240 iload (4, 4)
	242 iload (4, 4)
	244 invokevirtual (4, 4)
	247 dmul (4, 4)
	248 dadd (4, 4)
	249 dstore (4, 4)
	251 aload_0 (4, 4)
	252 getfield (4, 4)
	255 iload (4, 4)
	257 iload (4, 4)
	259 dload (4, 4)
	261 aload_0 (4, 4)
	262 getfield (4, 4)
	265 iload (4, 4)
	267 iload (4, 4)
	269 invokevirtual (4, 4)
	272 dmul (4, 4)
	273 dload (4, 4)
	275 aload_0 (4, 4)
	276 getfield (4, 4)
	279 iload (4, 4)
	281 iconst_0 (4, 4)
	282 invokevirtual (4, 4)
	285 dmul (4, 4)
	286 dsub (4, 4)
	287 invokevirtual (4, 4)
	290 aload_0 (4, 4)
	291 getfield (4, 4)
	294 iload (4, 4)
	296 iconst_0 (4, 4)
	297 dload (4, 4)
	299 invokevirtual (4, 4)
	302 iinc (4, 4)
	305 goto (4, 4)
	308 aload_0 (2, 4)
	309 getfield (2, 4)
	312 iload (2, 4)
	314 iload (2, 4)
	316 dconst_0 (2, 4)
	317 invokevirtual (2, 4)
	320 iinc (2, 4)
	323 goto (2, 4)
	326 iconst_0 (2, 4)
	327 istore (2, 4)
	329 iload (2, 4)
	331 iload (2, 4)
	333 if_icmpge (2, 4)
	336 aload (2, 4)
	338 iload (2, 4)
	340 aload_0 (2, 4)
	341 getfield (2, 4)
	344 iload (2, 4)
	346 iconst_0 (2, 4)
	347 invokevirtual (2, 4)
	350 aload_0 (2, 4)
	351 getfield (2, 4)
	354 iload (2, 4)
	356 iconst_0 (2, 4)
	357 invokevirtual (2, 4)
	360 dmul (2, 4)
	361 invokevirtual (2, 4)
	364 iinc (2, 4)
	367 goto (2, 4)
	370 aload (1, 4)
	372 iload (1, 4)
	374 invokevirtual (1, 4)
	377 dstore (1, 4)
	379 aload_0 (1, 4)
	380 getfield (1, 4)
	383 iload (1, 4)
	385 invokevirtual (1, 4)
	388 dstore (1, 4)
	390 aload_0 (1, 4)
	391 getfield (1, 4)
	394 iload (1, 4)
	396 aload_0 (1, 4)
	397 getfield (1, 4)
	400 iload (1, 4)
	402 invokevirtual (1, 4)
	405 dconst_1 (1, 4)
	406 dsub (1, 4)
	407 invokevirtual (1, 4)
	410 dload_3 (1, 4)
	411 invokestatic (1, 4)
	414 dstore (1, 4)
	416 dload (1, 4)
	418 dload (1, 4)
	420 ddiv (1, 4)
	421 dstore (1, 4)
	423 aload_0 (1, 4)
	424 getfield (1, 4)
	427 iload (1, 4)
	429 iconst_0 (1, 4)
	430 invokevirtual (1, 4)
	433 dload (1, 4)
	435 ddiv (1, 4)
	436 dstore (1, 4)
	438 iconst_0 (2, 4)
	439 istore (2, 4)
	441 iload (2, 4)
	443 iload (2, 4)
	445 if_icmpge (2, 4)
	448 aload_0 (2, 4)
	449 getfield (2, 4)
	452 iload (2, 4)
	454 iconst_0 (2, 4)
	455 dload (2, 4)
	457 aload_0 (2, 4)
	458 getfield (2, 4)
	461 iload (2, 4)
	463 iconst_0 (2, 4)
	464 invokevirtual (2, 4)
	467 dmul (2, 4)
	468 dload (2, 4)
	470 aload_0 (2, 4)
	471 getfield (2, 4)
	474 iload (2, 4)
	476 invokevirtual (2, 4)
	479 dmul (2, 4)
	480 dsub (2, 4)
	481 invokevirtual (2, 4)
	484 iinc (2, 4)
	487 goto (2, 4)
	490 iconst_0 (2, 4)
	491 istore (2, 4)
	493 iload (2, 4)
	495 iload (2, 4)
	497 if_icmpge (2, 4)
	500 iload (2, 4)
	502 iload (2, 4)
	504 iadd (2, 4)
	505 istore (2, 4)
	507 aload (2, 4)
	509 iload (2, 4)
	511 aload_0 (2, 4)
	512 getfield (2, 4)
	515 iload (2, 4)
	517 iload (2, 4)
	519 invokevirtual (2, 4)
	522 invokevirtual (2, 4)
	525 dload (2, 4)
	527 aload_0 (2, 4)
	528 getfield (2, 4)
	531 iload (2, 4)
	533 invokevirtual (2, 4)
	536 dmul (2, 4)
	537 dload (2, 4)
	539 aload (2, 4)
	541 iload (2, 4)
	543 invokevirtual (2, 4)
	546 dmul (2, 4)
	547 dsub (2, 4)
	548 dload_3 (2, 4)
	549 ddiv (2, 4)
	550 dstore (2, 4)
	552 dload_1 (2, 4)
	553 dneg (2, 4)
	554 aload (2, 4)
	556 iload (2, 4)
	558 invokevirtual (2, 4)
	561 dmul (2, 4)
	562 dload (2, 4)
	564 aload_0 (2, 4)
	565 getfield (2, 4)
	568 iload (2, 4)
	570 invokevirtual (2, 4)
	573 dmul (2, 4)
	574 dsub (2, 4)
	575 dload_3 (2, 4)
	576 ddiv (2, 4)
	577 dstore (2, 4)
	579 iconst_0 (3, 4)
	580 istore (3, 4)
	582 iload (3, 4)
	584 iload (3, 4)
	586 if_icmpgt (3, 4)
	589 aload_0 (3, 4)
	590 getfield (3, 4)
	593 iload (3, 4)
	595 iload (3, 4)
	597 aload_0 (3, 4)
	598 getfield (3, 4)
	601 iload (3, 4)
	603 iload (3, 4)
	605 invokevirtual (3, 4)
	608 dload (3, 4)
	610 aload_0 (3, 4)
	611 getfield (3, 4)
	614 iload (3, 4)
	616 invokevirtual (3, 4)
	619 dmul (3, 4)
	620 dadd (3, 4)
	621 dload (3, 4)
	623 aload (3, 4)
	625 iload (3, 4)
	627 invokevirtual (3, 4)
	630 dmul (3, 4)
	631 dadd (3, 4)
	632 invokevirtual (3, 4)
	635 iload (4, 1)
	637 iload (4, 1)
	639 if_icmplt (4, 1)
	642 aload_0 (4, 1)
	643 getfield (4, 1)
	646 iload (4, 1)
	648 iload (4, 1)
	650 iload (4, 1)
	652 isub (4, 1)
	653 aload_0 (4, 1)
	654 getfield (4, 1)
	657 iload (4, 1)
	659 iload (4, 1)
	661 invokevirtual (4, 1)
	664 invokevirtual (4, 1)
	667 iinc (4, 1)
	670 goto (4, 1)
	673 iinc (4, 1)
	676 goto (4, 1)
	679 return (2, 4)

Method: setup
	0 invokestatic (0, 0)
	3 aload_0 (0, 0)
	4 invokevirtual (0, 0)
	7 astore_3 (0, 0)
	8 aload_3 (0, 0)
	9 arraylength (0, 0)
	10 istore (0, 0)
	12 iload (1, 1)
	14 iconst_2 (1, 1)
	15 if_icmpge (1, 1)
	18 new (1, 1)
	21 dup (1, 1)
	22 iload (1, 1)
	24 invokestatic (1, 1)
	27 iconst_2 (1, 1)
	28 invokestatic (1, 1)
	31 iconst_1 (1, 1)
	32 invokespecial (1, 1)
	35 athrow (1, 1)
	36 iconst_2 (0, 0)
	37 newarray (0, 0)
	39 dup (0, 0)
	40 iconst_0 (0, 0)
	41 iload (0, 0)
	43 iconst_2 (0, 0)
	44 iadd (0, 0)
	45 iastore (0, 0)
	46 dup (0, 0)
	47 iconst_1 (0, 0)
	48 iload (0, 0)
	50 iconst_2 (0, 0)
	51 iadd (0, 0)
	52 iload (0, 0)
	54 iconst_1 (0, 0)
	55 iadd (0, 0)
	56 imul (0, 0)
	57 iconst_2 (0, 0)
	58 idiv (0, 0)
	59 iastore (0, 0)
	60 astore (0, 0)
	62 aload_0 (0, 1)
	63 getfield (0, 1)
	66 aload (0, 1)
	68 iconst_0 (0, 1)
	69 iaload (0, 1)
	70 if_icmplt (0, 1)
	73 aload_0 (0, 1)
	74 getfield (0, 1)
	77 aload (0, 1)
	79 iconst_1 (0, 1)
	80 iaload (0, 1)
	81 if_icmple (0, 1)
	84 new (1, 1)
	87 dup (1, 1)
	88 getstatic (1, 1)
	91 aload_0 (1, 1)
	92 getfield (1, 1)
	95 invokestatic (1, 1)
	98 aload (1, 1)
	100 iconst_0 (1, 1)
	101 iaload (1, 1)
	102 invokestatic (1, 1)
	105 aload (1, 1)
	107 iconst_1 (1, 1)
	108 iaload (1, 1)
	109 invokestatic (1, 1)
	112 invokespecial (1, 1)
	115 athrow (1, 1)
	116 aload_0 (0, 1)
	117 iload (0, 1)
	119 newarray (0, 1)
	121 putfield (0, 1)
	124 ldc2_w (0, 1)
	127 aload_0 (0, 1)
	128 getfield (0, 1)
	131 dmul (0, 1)
	132 dstore (0, 1)
	134 ldc2_w (0, 1)
	137 dstore (0, 1)
	139 iconst_0 (1, 4)
	140 istore (1, 4)
	142 iload (1, 4)
	144 iload (1, 4)
	146 if_icmpge (1, 4)
	149 aload_0 (1, 1)
	150 getfield (1, 1)
	153 iload (1, 1)
	155 aload_2 (1, 1)
	156 iload (1, 1)
	158 daload (1, 1)
	159 aload_1 (1, 1)
	160 iload (1, 1)
	162 daload (1, 1)
	163 dsub (1, 1)
	164 dastore (1, 1)
	165 dload (1, 1)
	167 aload_0 (1, 1)
	168 getfield (1, 1)
	171 iload (1, 1)
	173 daload (1, 1)
	174 invokestatic (1, 1)
	177 dstore (1, 1)
	179 iinc (1, 1)
	182 goto (1, 1)
	185 dload (1, 1)
	187 dload (1, 1)
	189 dcmpg (1, 1)
	190 ifge (1, 1)
	193 aload_0 (1, 1)
	194 dload (1, 1)
	196 ldc2_w (1, 1)
	199 ddiv (1, 1)
	200 putfield (1, 1)
	203 aload_0 (0, 1)
	204 new (0, 1)
	207 dup (0, 1)
	208 iload (0, 1)
	210 aload_0 (0, 1)
	211 getfield (0, 1)
	214 iadd (0, 1)
	215 iload (0, 1)
	217 invokespecial (0, 1)
	220 putfield (0, 1)
	223 aload_0 (0, 1)
	224 new (0, 1)
	227 dup (0, 1)
	228 aload_0 (0, 1)
	229 getfield (0, 1)
	232 aload_0 (0, 1)
	233 getfield (0, 1)
	236 iload (0, 1)
	238 isub (0, 1)
	239 iconst_1 (0, 1)
	240 isub (0, 1)
	241 invokespecial (0, 1)
	244 putfield (0, 1)
	247 aload_0 (0, 1)
	248 new (0, 1)
	251 dup (0, 1)
	252 aload_0 (0, 1)
	253 getfield (0, 1)
	256 iload (0, 1)
	258 invokespecial (0, 1)
	261 putfield (0, 1)
	264 aload_0 (0, 1)
	265 new (0, 1)
	268 dup (0, 1)
	269 iload (0, 1)
	271 invokespecial (0, 1)
	274 putfield (0, 1)
	277 aload_0 (0, 1)
	278 new (0, 1)
	281 dup (0, 1)
	282 aload_0 (0, 1)
	283 getfield (0, 1)
	286 invokespecial (0, 1)
	289 putfield (0, 1)
	292 aload_0 (0, 1)
	293 new (0, 1)
	296 dup (0, 1)
	297 iload (0, 1)
	299 invokespecial (0, 1)
	302 putfield (0, 1)
	305 aload_0 (0, 1)
	306 new (0, 1)
	309 dup (0, 1)
	310 iload (0, 1)
	312 invokespecial (0, 1)
	315 putfield (0, 1)
	318 aload_0 (0, 1)
	319 new (0, 1)
	322 dup (0, 1)
	323 iload (0, 1)
	325 invokespecial (0, 1)
	328 putfield (0, 1)
	331 aload_0 (0, 1)
	332 new (0, 1)
	335 dup (0, 1)
	336 iload (0, 1)
	338 invokespecial (0, 1)
	341 putfield (0, 1)
	344 aload_0 (0, 1)
	345 new (0, 1)
	348 dup (0, 1)
	349 aload_0 (0, 1)
	350 getfield (0, 1)
	353 invokespecial (0, 1)
	356 putfield (0, 1)
	359 aload_0 (0, 1)
	360 new (0, 1)
	363 dup (0, 1)
	364 iload (0, 1)
	366 invokespecial (0, 1)
	369 putfield (0, 1)
	372 aload_0 (0, 1)
	373 new (0, 1)
	376 dup (0, 1)
	377 iload (0, 1)
	379 invokespecial (0, 1)
	382 putfield (0, 1)
	385 aload_0 (0, 1)
	386 new (0, 1)
	389 dup (0, 1)
	390 iload (0, 1)
	392 invokespecial (0, 1)
	395 putfield (0, 1)
	398 aload_0 (0, 1)
	399 new (0, 1)
	402 dup (0, 1)
	403 iload (0, 1)
	405 aload_0 (0, 1)
	406 getfield (0, 1)
	409 iadd (0, 1)
	410 invokespecial (0, 1)
	413 putfield (0, 1)
	416 aload_0 (0, 1)
	417 new (0, 1)
	420 dup (0, 1)
	421 iload (0, 1)
	423 iload (0, 1)
	425 iconst_1 (0, 1)
	426 iadd (0, 1)
	427 imul (0, 1)
	428 iconst_2 (0, 1)
	429 idiv (0, 1)
	430 invokespecial (0, 1)
	433 putfield (0, 1)
	436 return (0, 1)

Method: caller
	0 new (0, 0)
	3 dup (0, 0)
	4 invokespecial (0, 0)
	7 astore_1 (0, 0)
	8 aload_1 (0, 0)
	9 invokevirtual (0, 0)
	12 astore_2 (0, 0)
	13 aload_2 (0, 0)
	14 iload_0 (0, 0)
	15 aaload (0, 0)
	16 astore_3 (0, 0)
	17 new (0, 0)
	20 dup (0, 0)
	21 invokespecial (0, 0)
	24 aload_3 (0, 0)
	25 invokevirtual (0, 0)
	28 invokevirtual (0, 0)
	31 ldc (0, 0)
	33 invokevirtual (0, 0)
	36 aload_3 (0, 0)
	37 invokevirtual (0, 0)
	40 invokevirtual (0, 0)
	43 ldc (0, 0)
	45 invokevirtual (0, 0)
	48 invokevirtual (0, 0)
	51 areturn (0, 0)

Method: printState
	0 return (0, 0)

Method: printMethod
	0 return (0, 0)

Method: access$000
	0 iload_0 (0, 0)
	1 invokestatic (0, 0)
	4 areturn (0, 0)

