Method: <init>
	0 aload_0 (0, 0)
	1 invokespecial (0, 0)
	2 java/lang/Object.<init>:()V (0, 0)
	4 iconst_0 (2, 4)
	5 istore_2 (2, 4)
	6 iload_2 (2, 4)
	7 aload_1 (2, 4)
	8 arraylength (2, 4)
	9 if_icmpge (2, 4)
	10 31 (2, 4)
	12 aload_1 (3, 1)
	13 iload_2 (3, 1)
	14 daload (3, 1)
	15 dconst_0 (3, 1)
	16 dcmpg (3, 1)
	17 ifge (3, 1)
	18 17 (3, 1)
	20 new (3, 1)
	21 org/apache/commons/math3/exception/NotPositiveException (3, 1)
	23 dup (3, 1)
	24 aload_1 (3, 1)
	25 iload_2 (3, 1)
	26 daload (3, 1)
	27 invokestatic (3, 1)
	28 java/lang/Double.valueOf:(D)Ljava/lang/Double; (3, 1)
	30 invokespecial (3, 1)
	31 org/apache/commons/math3/exception/NotPositiveException.<init>:(Ljava/lang/Number;)V (3, 1)
	33 athrow (3, 1)
	34 iinc (3, 1)
	35 #2 (3, 1)
	36 -89 (3, 1)
	37 goto (3, 1)
	38 -31 (3, 1)
	40 aload_0 (2, 4)
	41 aload_1 (2, 4)
	42 invokevirtual (2, 4)
	43 [D.clone:()Ljava/lang/Object; (2, 4)
	45 checkcast (2, 4)
	46 [D (2, 4)
	48 putfield (2, 4)
	49 org/apache/commons/math3/optimization/direct/CMAESOptimizer$Sigma.sigma:[D (2, 4)
	51 return (0, 0)

Method: getSigma
	0 aload_0 (0, 0)
	1 getfield (0, 0)
	2 org/apache/commons/math3/optimization/direct/CMAESOptimizer$Sigma.sigma:[D (0, 0)
	4 invokevirtual (0, 0)
	5 [D.clone:()Ljava/lang/Object; (0, 0)
	7 checkcast (0, 0)
	8 [D (0, 0)
	10 areturn (0, 0)

