Method: <init>
	0 aload_0 (0, 0)
	1 aload (0, 0)
	2 #9 (0, 0)
	3 invokespecial (0, 0)
	4 org/apache/commons/math3/optimization/direct/BaseAbstractMultivariateSimpleBoundsOptimizer.<init>:(Lorg/apache/commons/math3/optimization/ConvergenceChecker;)V (0, 0)
	6 aload_0 (0, 0)
	7 iconst_0 (0, 0)
	8 putfield (0, 0)
	9 org/apache/commons/math3/optimization/direct/CMAESOptimizer.diagonalOnly:I (0, 0)
	11 aload_0 (0, 0)
	12 iconst_1 (0, 0)
	13 putfield (0, 0)
	14 org/apache/commons/math3/optimization/direct/CMAESOptimizer.isMinimize:Z (0, 0)
	16 aload_0 (0, 0)
	17 iconst_0 (0, 0)
	18 putfield (0, 0)
	19 org/apache/commons/math3/optimization/direct/CMAESOptimizer.generateStatistics:Z (0, 0)
	21 aload_0 (0, 4)
	22 new (0, 4)
	23 java/util/ArrayList (0, 4)
	25 dup (0, 4)
	26 invokespecial (0, 4)
	27 java/util/ArrayList.<init>:()V (0, 4)
	29 putfield (0, 4)
	30 org/apache/commons/math3/optimization/direct/CMAESOptimizer.statisticsSigmaHistory:Ljava/util/List; (0, 4)
	32 aload_0 (0, 4)
	33 new (0, 4)
	34 java/util/ArrayList (0, 4)
	36 dup (0, 4)
	37 invokespecial (0, 4)
	38 java/util/ArrayList.<init>:()V (0, 4)
	40 putfield (0, 4)
	41 org/apache/commons/math3/optimization/direct/CMAESOptimizer.statisticsMeanHistory:Ljava/util/List; (0, 4)
	43 aload_0 (0, 4)
	44 new (0, 4)
	45 java/util/ArrayList (0, 4)
	47 dup (0, 4)
	48 invokespecial (0, 4)
	49 java/util/ArrayList.<init>:()V (0, 4)
	51 putfield (0, 4)
	52 org/apache/commons/math3/optimization/direct/CMAESOptimizer.statisticsFitnessHistory:Ljava/util/List; (0, 4)
	54 aload_0 (0, 4)
	55 new (0, 4)
	56 java/util/ArrayList (0, 4)
	58 dup (0, 4)
	59 invokespecial (0, 4)
	60 java/util/ArrayList.<init>:()V (0, 4)
	62 putfield (0, 4)
	63 org/apache/commons/math3/optimization/direct/CMAESOptimizer.statisticsDHistory:Ljava/util/List; (0, 4)
	65 aload_0 (0, 1)
	66 iload_1 (0, 1)
	67 putfield (0, 1)
	68 org/apache/commons/math3/optimization/direct/CMAESOptimizer.maxIterations:I (0, 1)
	70 aload_0 (0, 1)
	71 dload_2 (0, 1)
	72 putfield (0, 1)
	73 org/apache/commons/math3/optimization/direct/CMAESOptimizer.stopFitness:D (0, 1)
	75 aload_0 (0, 1)
	76 iload (0, 1)
	77 #4 (0, 1)
	78 putfield (0, 1)
	79 org/apache/commons/math3/optimization/direct/CMAESOptimizer.isActiveCMA:Z (0, 1)
	81 aload_0 (0, 1)
	82 iload (0, 1)
	83 #5 (0, 1)
	84 putfield (0, 1)
	85 org/apache/commons/math3/optimization/direct/CMAESOptimizer.diagonalOnly:I (0, 1)
	87 aload_0 (0, 1)
	88 iload (0, 1)
	89 #6 (0, 1)
	90 putfield (0, 1)
	91 org/apache/commons/math3/optimization/direct/CMAESOptimizer.checkFeasableCount:I (0, 1)
	93 aload_0 (0, 1)
	94 aload (0, 1)
	95 #7 (0, 1)
	96 putfield (0, 1)
	97 org/apache/commons/math3/optimization/direct/CMAESOptimizer.random:Lorg/apache/commons/math3/random/RandomGenerator; (0, 1)
	99 aload_0 (0, 1)
	100 iload (0, 1)
	101 #8 (0, 1)
	102 putfield (0, 1)
	103 org/apache/commons/math3/optimization/direct/CMAESOptimizer.generateStatistics:Z (0, 1)
	105 return (0, 1)

Method: getStatisticsSigmaHistory
	0 aload_0 (0, 0)
	1 getfield (0, 0)
	2 org/apache/commons/math3/optimization/direct/CMAESOptimizer.statisticsSigmaHistory:Ljava/util/List; (0, 0)
	4 areturn (0, 0)

Method: getStatisticsMeanHistory
	0 aload_0 (0, 0)
	1 getfield (0, 0)
	2 org/apache/commons/math3/optimization/direct/CMAESOptimizer.statisticsMeanHistory:Ljava/util/List; (0, 0)
	4 areturn (0, 0)

Method: getStatisticsFitnessHistory
	0 aload_0 (0, 0)
	1 getfield (0, 0)
	2 org/apache/commons/math3/optimization/direct/CMAESOptimizer.statisticsFitnessHistory:Ljava/util/List; (0, 0)
	4 areturn (0, 0)

Method: getStatisticsDHistory
	0 aload_0 (0, 0)
	1 getfield (0, 0)
	2 org/apache/commons/math3/optimization/direct/CMAESOptimizer.statisticsDHistory:Ljava/util/List; (0, 0)
	4 areturn (0, 0)

Method: optimizeInternal
	0 aload_0 (0, 0)
	1 aload (0, 0)
	2 #4 (0, 0)
	3 invokespecial (0, 0)
	4 org/apache/commons/math3/optimization/direct/CMAESOptimizer.parseOptimizationData:([Lorg/apache/commons/math3/optimization/OptimizationData;)V (0, 0)
	6 aload_0 (0, 0)
	7 iload_1 (0, 0)
	8 aload_2 (0, 0)
	9 aload_3 (0, 0)
	10 aload (0, 0)
	11 #4 (0, 0)
	12 invokespecial (0, 0)
	13 org/apache/commons/math3/optimization/direct/BaseAbstractMultivariateSimpleBoundsOptimizer.optimizeInternal:(ILorg/apache/commons/math3/analysis/MultivariateFunction;Lorg/apache/commons/math3/optimization/GoalType;[Lorg/apache/commons/math3/optimization/OptimizationData;)Lorg/apache/commons/math3/optimization/PointValuePair; (0, 0)
	15 areturn (0, 0)

Method: doOptimize
	0 aload_0 (0, 0)
	1 invokespecial (0, 0)
	2 org/apache/commons/math3/optimization/direct/CMAESOptimizer.checkParameters:()V (0, 0)
	4 aload_0 (0, 0)
	5 aload_0 (0, 0)
	6 invokevirtual (0, 0)
	7 org/apache/commons/math3/optimization/direct/CMAESOptimizer.getGoalType:()Lorg/apache/commons/math3/optimization/GoalType; (0, 0)
	9 getstatic (0, 0)
	10 org/apache/commons/math3/optimization/GoalType.MINIMIZE:Lorg/apache/commons/math3/optimization/GoalType; (0, 0)
	12 invokevirtual (0, 0)
	13 org/apache/commons/math3/optimization/GoalType.equals:(Ljava/lang/Object;)Z (0, 0)
	15 putfield (0, 0)
	16 org/apache/commons/math3/optimization/direct/CMAESOptimizer.isMinimize:Z (0, 0)
	18 new (0, 0)
	19 org/apache/commons/math3/optimization/direct/CMAESOptimizer$FitnessFunction (0, 0)
	21 dup (0, 0)
	22 aload_0 (0, 0)
	23 invokespecial (0, 0)
	24 org/apache/commons/math3/optimization/direct/CMAESOptimizer$FitnessFunction.<init>:(Lorg/apache/commons/math3/optimization/direct/CMAESOptimizer;)V (0, 0)
	26 astore_1 (0, 0)
	27 aload_0 (0, 0)
	28 invokevirtual (0, 0)
	29 org/apache/commons/math3/optimization/direct/CMAESOptimizer.getStartPoint:()[D (0, 0)
	31 astore_2 (0, 0)
	32 aload_0 (0, 0)
	33 aload_2 (0, 0)
	34 arraylength (0, 0)
	35 putfield (0, 0)
	36 org/apache/commons/math3/optimization/direct/CMAESOptimizer.dimension:I (0, 0)
	38 aload_0 (0, 0)
	39 aload_2 (0, 0)
	40 invokespecial (0, 0)
	41 org/apache/commons/math3/optimization/direct/CMAESOptimizer.initializeCMA:([D)V (0, 0)
	43 aload_0 (0, 0)
	44 iconst_0 (0, 0)
	45 putfield (0, 0)
	46 org/apache/commons/math3/optimization/direct/CMAESOptimizer.iterations:I (0, 0)
	48 aload_1 (0, 0)
	49 aload_2 (0, 0)
	50 invokevirtual (0, 0)
	51 org/apache/commons/math3/optimization/direct/CMAESOptimizer$FitnessFunction.value:([D)D (0, 0)
	53 dstore_3 (0, 0)
	54 aload_0 (0, 0)
	55 getfield (0, 0)
	56 org/apache/commons/math3/optimization/direct/CMAESOptimizer.fitnessHistory:[D (0, 0)
	58 dload_3 (0, 0)
	59 invokestatic (0, 0)
	60 org/apache/commons/math3/optimization/direct/CMAESOptimizer.push:([DD)V (0, 0)
	62 new (0, 0)
	63 org/apache/commons/math3/optimization/PointValuePair (0, 0)
	65 dup (0, 0)
	66 aload_0 (0, 0)
	67 invokevirtual (0, 0)
	68 org/apache/commons/math3/optimization/direct/CMAESOptimizer.getStartPoint:()[D (0, 0)
	70 aload_0 (0, 0)
	71 getfield (0, 0)
	72 org/apache/commons/math3/optimization/direct/CMAESOptimizer.isMinimize:Z (0, 0)
	74 ifeq (0, 0)
	75 7 (0, 0)
	77 dload_3 (0, 0)
	78 goto (0, 0)
	79 5 (0, 0)
	81 dload_3 (0, 0)
	82 dneg (0, 0)
	83 invokespecial (0, 0)
	84 org/apache/commons/math3/optimization/PointValuePair.<init>:([DD)V (0, 0)
	86 astore (0, 0)
	87 #5 (0, 0)
	88 aconst_null (0, 0)
	89 astore (0, 0)
	90 #6 (0, 0)
	91 aload_0 (1, 4)
	92 iconst_1 (1, 4)
	93 putfield (1, 4)
	94 org/apache/commons/math3/optimization/direct/CMAESOptimizer.iterations:I (1, 4)
	96 aload_0 (1, 4)
	97 getfield (1, 4)
	98 org/apache/commons/math3/optimization/direct/CMAESOptimizer.iterations:I (1, 4)
	100 aload_0 (1, 4)
	101 getfield (1, 4)
	102 org/apache/commons/math3/optimization/direct/CMAESOptimizer.maxIterations:I (1, 4)
	104 if_icmpgt (1, 4)
	105 1065 (1, 4)
	107 aload_0 (1, 4)
	108 aload_0 (1, 4)
	109 getfield (1, 4)
	110 org/apache/commons/math3/optimization/direct/CMAESOptimizer.dimension:I (1, 4)
	112 aload_0 (1, 4)
	113 getfield (1, 4)
	114 org/apache/commons/math3/optimization/direct/CMAESOptimizer.lambda:I (1, 4)
	116 invokespecial (1, 4)
	117 org/apache/commons/math3/optimization/direct/CMAESOptimizer.randn1:(II)Lorg/apache/commons/math3/linear/RealMatrix; (1, 4)
	119 astore (1, 4)
	120 #7 (1, 4)
	121 aload_0 (1, 4)
	122 getfield (1, 4)
	123 org/apache/commons/math3/optimization/direct/CMAESOptimizer.dimension:I (1, 4)
	125 aload_0 (1, 4)
	126 getfield (1, 4)
	127 org/apache/commons/math3/optimization/direct/CMAESOptimizer.lambda:I (1, 4)
	129 invokestatic (1, 4)
	130 org/apache/commons/math3/optimization/direct/CMAESOptimizer.zeros:(II)Lorg/apache/commons/math3/linear/RealMatrix; (1, 4)
	132 astore (1, 4)
	133 #8 (1, 4)
	134 aload_0 (1, 4)
	135 getfield (1, 4)
	136 org/apache/commons/math3/optimization/direct/CMAESOptimizer.lambda:I (1, 4)
	138 newarray (1, 4)
	139 7 (1, 4)
	140 astore (1, 4)
	141 #9 (1, 4)
	142 iconst_0 (2, 4)
	143 istore (2, 4)
	144 #10 (2, 4)
	145 iload (2, 4)
	146 #10 (2, 4)
	147 aload_0 (2, 4)
	148 getfield (2, 4)
	149 org/apache/commons/math3/optimization/direct/CMAESOptimizer.lambda:I (2, 4)
	151 if_icmpge (2, 4)
	152 196 (2, 4)
	154 aconst_null (2, 4)
	155 astore (2, 4)
	156 #11 (2, 4)
	157 iconst_0 (3, 4)
	158 istore (3, 4)
	159 #12 (3, 4)
	160 iload (3, 4)
	161 #12 (3, 4)
	162 aload_0 (3, 4)
	163 getfield (3, 4)
	164 org/apache/commons/math3/optimization/direct/CMAESOptimizer.checkFeasableCount:I (3, 4)
	166 iconst_1 (3, 4)
	167 iadd (3, 4)
	168 if_icmpge (3, 4)
	169 137 (3, 4)
	171 aload_0 (4, 1)
	172 getfield (4, 1)
	173 org/apache/commons/math3/optimization/direct/CMAESOptimizer.diagonalOnly:I (4, 1)
	175 ifgt (4, 1)
	176 44 (4, 1)
	178 aload_0 (4, 1)
	179 getfield (4, 1)
	180 org/apache/commons/math3/optimization/direct/CMAESOptimizer.xmean:Lorg/apache/commons/math3/linear/RealMatrix; (4, 1)
	182 aload_0 (4, 1)
	183 getfield (4, 1)
	184 org/apache/commons/math3/optimization/direct/CMAESOptimizer.BD:Lorg/apache/commons/math3/linear/RealMatrix; (4, 1)
	186 aload (4, 1)
	187 #7 (4, 1)
	188 iload (4, 1)
	189 #10 (4, 1)
	190 invokeinterface (4, 1)
	191 org/apache/commons/math3/linear/RealMatrix.multiply:(Lorg/apache/commons/math3/linear/RealMatrix;)Lorg/apache/commons/math3/linear/RealMatrix; (4, 1)
	193 0 (4, 1)
	195 invokeinterface (4, 1)
	196 org/apache/commons/math3/linear/RealMatrix.sigma:D (4, 1)
	198 0 (4, 1)
	200 aload_0 (4, 1)
	201 getfield (4, 1)
	202 org/apache/commons/math3/optimization/direct/CMAESOptimizer.sigma:D (4, 1)
	204 invokeinterface (4, 1)
	205 org/apache/commons/math3/linear/RealMatrix.add:(Lorg/apache/commons/math3/linear/RealMatrix;)Lorg/apache/commons/math3/linear/RealMatrix; (4, 1)
	207 0 (4, 1)
	209 invokeinterface (4, 1)
	210 org/apache/commons/math3/linear/RealMatrix.diagD:Lorg/apache/commons/math3/linear/RealMatrix; (4, 1)
	212 0 (4, 1)
	214 astore (4, 1)
	215 #11 (4, 1)
	216 goto (4, 1)
	217 39 (4, 1)
	219 aload_0 (4, 2)
	220 getfield (4, 2)
	221 org/apache/commons/math3/optimization/direct/CMAESOptimizer.xmean:Lorg/apache/commons/math3/linear/RealMatrix; (4, 2)
	223 aload_0 (4, 2)
	224 getfield (4, 2)
	225 org/apache/commons/math3/optimization/direct/CMAESOptimizer.diagD:Lorg/apache/commons/math3/linear/RealMatrix; (4, 2)
	227 aload (4, 2)
	228 #7 (4, 2)
	229 iload (4, 2)
	230 #10 (4, 2)
	231 invokeinterface (4, 2)
	232 org/apache/commons/math3/linear/RealMatrix.multiply:(Lorg/apache/commons/math3/linear/RealMatrix;)Lorg/apache/commons/math3/linear/RealMatrix; (4, 2)
	234 0 (4, 2)
	236 invokestatic (4, 2)
	237 org/apache/commons/math3/optimization/direct/CMAESOptimizer.times:(Lorg/apache/commons/math3/linear/RealMatrix;Lorg/apache/commons/math3/linear/RealMatrix;)Lorg/apache/commons/math3/linear/RealMatrix; (4, 2)
	239 aload_0 (4, 2)
	240 getfield (4, 2)
	241 org/apache/commons/math3/optimization/direct/CMAESOptimizer.sigma:D (4, 2)
	243 invokeinterface (4, 2)
	244 org/apache/commons/math3/linear/RealMatrix.add:(Lorg/apache/commons/math3/linear/RealMatrix;)Lorg/apache/commons/math3/linear/RealMatrix; (4, 2)
	246 0 (4, 2)
	248 invokeinterface (4, 2)
	249 org/apache/commons/math3/linear/RealMatrix.diagD:Lorg/apache/commons/math3/linear/RealMatrix; (4, 2)
	251 0 (4, 2)
	253 astore (4, 2)
	254 #11 (4, 2)
	255 iload (3, 1)
	256 #12 (3, 1)
	257 aload_0 (3, 1)
	258 getfield (3, 1)
	259 org/apache/commons/math3/optimization/direct/CMAESOptimizer.checkFeasableCount:I (3, 1)
	261 if_icmpge (3, 1)
	262 44 (3, 1)
	264 aload_1 (3, 1)
	265 aload (3, 1)
	266 #11 (3, 1)
	267 iconst_0 (3, 1)
	268 invokeinterface (3, 1)
	269 org/apache/commons/math3/linear/RealMatrix.isFeasible:([D)Z (3, 1)
	271 0 (3, 1)
	273 invokevirtual (3, 1)
	274 org/apache/commons/math3/optimization/direct/CMAESOptimizer$FitnessFunction.isFeasible:([D)Z (3, 1)
	276 ifeq (3, 1)
	277 6 (3, 1)
	279 goto (3, 1)
	280 26 (3, 1)
	282 aload (3, 4)
	283 #7 (3, 4)
	284 iload (3, 4)
	285 #10 (3, 4)
	286 aload_0 (3, 4)
	287 aload_0 (3, 4)
	288 getfield (3, 4)
	289 org/apache/commons/math3/optimization/direct/CMAESOptimizer.dimension:I (3, 4)
	291 invokespecial (3, 4)
	292 org/apache/commons/math3/optimization/direct/CMAESOptimizer.randn:(I)[D (3, 4)
	294 invokeinterface (3, 4)
	295 org/apache/commons/math3/linear/RealMatrix.copyColumn:(Lorg/apache/commons/math3/linear/RealMatrix;ILorg/apache/commons/math3/linear/RealMatrix;I)V (3, 4)
	297 0 (3, 4)
	299 iinc (3, 4)
	300 #12 (3, 4)
	301 -89 (3, 4)
	302 goto (3, 4)
	303 -142 (3, 4)
	305 aload (2, 4)
	306 #11 (2, 4)
	307 iconst_0 (2, 4)
	308 aload (2, 4)
	309 #8 (2, 4)
	310 iload (2, 4)
	311 #10 (2, 4)
	312 invokestatic (2, 4)
	313 org/apache/commons/math3/optimization/direct/CMAESOptimizer.copyColumn:(Lorg/apache/commons/math3/linear/RealMatrix;ILorg/apache/commons/math3/linear/RealMatrix;I)V (2, 4)
	315 aload (2, 4)
	316 #9 (2, 4)
	317 iload (2, 4)
	318 #10 (2, 4)
	319 aload_1 (2, 4)
	320 aload (2, 4)
	321 #8 (2, 4)
	322 iload (2, 4)
	323 #10 (2, 4)
	324 invokeinterface (2, 4)
	325 org/apache/commons/math3/linear/RealMatrix.isFeasible:([D)Z (2, 4)
	327 0 (2, 4)
	329 invokevirtual (2, 4)
	330 org/apache/commons/math3/optimization/direct/CMAESOptimizer$FitnessFunction.value:([D)D (2, 4)
	332 dastore (2, 4)
	333 goto (2, 4)
	334 8 (2, 4)
	336 astore (2, 4)
	337 #12 (2, 4)
	338 goto (2, 4)
	339 831 (2, 4)
	341 iinc (2, 4)
	342 #10 (2, 4)
	343 -89 (2, 4)
	344 goto (2, 4)
	345 -199 (2, 4)
	347 aload_0 (1, 4)
	348 aload (1, 4)
	349 #9 (1, 4)
	350 invokespecial (1, 4)
	351 org/apache/commons/math3/optimization/direct/CMAESOptimizer.sortedIndices:([D)[I (1, 4)
	353 astore (1, 4)
	354 #10 (1, 4)
	355 aload_0 (1, 4)
	356 getfield (1, 4)
	357 org/apache/commons/math3/optimization/direct/CMAESOptimizer.xmean:Lorg/apache/commons/math3/linear/RealMatrix; (1, 4)
	359 astore (1, 4)
	360 #11 (1, 4)
	361 aload (1, 4)
	362 #8 (1, 4)
	363 aload (1, 4)
	364 #10 (1, 4)
	365 aload_0 (1, 4)
	366 getfield (1, 4)
	367 org/apache/commons/math3/optimization/direct/CMAESOptimizer.mu:I (1, 4)
	369 invokestatic (1, 4)
	370 org/apache/commons/math3/util/MathArrays.copyOf:([II)[I (1, 4)
	372 invokestatic (1, 4)
	373 org/apache/commons/math3/optimization/direct/CMAESOptimizer.selectColumns:(Lorg/apache/commons/math3/linear/RealMatrix;[I)Lorg/apache/commons/math3/linear/RealMatrix; (1, 4)
	375 astore (1, 4)
	376 #12 (1, 4)
	377 aload_0 (1, 4)
	378 aload (1, 4)
	379 #12 (1, 4)
	380 aload_0 (1, 4)
	381 getfield (1, 4)
	382 org/apache/commons/math3/optimization/direct/CMAESOptimizer.weights:Lorg/apache/commons/math3/linear/RealMatrix; (1, 4)
	384 invokeinterface (1, 4)
	385 org/apache/commons/math3/linear/RealMatrix.sigma:D (1, 4)
	387 0 (1, 4)
	389 putfield (1, 4)
	390 org/apache/commons/math3/optimization/direct/CMAESOptimizer.xmean:Lorg/apache/commons/math3/linear/RealMatrix; (1, 4)
	392 aload (1, 4)
	393 #7 (1, 4)
	394 aload (1, 4)
	395 #10 (1, 4)
	396 aload_0 (1, 4)
	397 getfield (1, 4)
	398 org/apache/commons/math3/optimization/direct/CMAESOptimizer.mu:I (1, 4)
	400 invokestatic (1, 4)
	401 org/apache/commons/math3/util/MathArrays.copyOf:([II)[I (1, 4)
	403 invokestatic (1, 4)
	404 org/apache/commons/math3/optimization/direct/CMAESOptimizer.selectColumns:(Lorg/apache/commons/math3/linear/RealMatrix;[I)Lorg/apache/commons/math3/linear/RealMatrix; (1, 4)
	406 astore (1, 4)
	407 #13 (1, 4)
	408 aload (1, 4)
	409 #13 (1, 4)
	410 aload_0 (1, 4)
	411 getfield (1, 4)
	412 org/apache/commons/math3/optimization/direct/CMAESOptimizer.weights:Lorg/apache/commons/math3/linear/RealMatrix; (1, 4)
	414 invokeinterface (1, 4)
	415 org/apache/commons/math3/linear/RealMatrix.sigma:D (1, 4)
	417 0 (1, 4)
	419 astore (1, 4)
	420 #14 (1, 4)
	421 aload_0 (1, 4)
	422 aload (1, 4)
	423 #14 (1, 4)
	424 aload (1, 4)
	425 #11 (1, 4)
	426 invokespecial (1, 4)
	427 org/apache/commons/math3/optimization/direct/CMAESOptimizer.updateEvolutionPaths:(Lorg/apache/commons/math3/linear/RealMatrix;Lorg/apache/commons/math3/linear/RealMatrix;)Z (1, 4)
	429 istore (1, 4)
	430 #15 (1, 4)
	431 aload_0 (2, 1)
	432 getfield (2, 1)
	433 org/apache/commons/math3/optimization/direct/CMAESOptimizer.diagonalOnly:I (2, 1)
	435 ifgt (2, 1)
	436 20 (2, 1)
	438 aload_0 (2, 1)
	439 iload (2, 1)
	440 #15 (2, 1)
	441 aload (2, 1)
	442 #12 (2, 1)
	443 aload (2, 1)
	444 #7 (2, 1)
	445 aload (2, 1)
	446 #10 (2, 1)
	447 aload (2, 1)
	448 #11 (2, 1)
	449 invokespecial (2, 1)
	450 org/apache/commons/math3/optimization/direct/CMAESOptimizer.updateCovariance:(ZLorg/apache/commons/math3/linear/RealMatrix;Lorg/apache/commons/math3/linear/RealMatrix;[ILorg/apache/commons/math3/linear/RealMatrix;)V (2, 1)
	452 goto (2, 1)
	453 11 (2, 1)
	455 aload_0 (2, 2)
	456 iload (2, 2)
	457 #15 (2, 2)
	458 aload (2, 2)
	459 #13 (2, 2)
	460 invokespecial (2, 2)
	461 org/apache/commons/math3/optimization/direct/CMAESOptimizer.updateCovarianceDiagonalOnly:(ZLorg/apache/commons/math3/linear/RealMatrix;)V (2, 2)
	463 aload_0 (1, 4)
	464 dup (1, 4)
	465 getfield (1, 4)
	466 org/apache/commons/math3/optimization/direct/CMAESOptimizer.sigma:D (1, 4)
	468 dconst_1 (1, 4)
	469 aload_0 (1, 4)
	470 getfield (1, 4)
	471 org/apache/commons/math3/optimization/direct/CMAESOptimizer.normps:D (1, 4)
	473 aload_0 (1, 4)
	474 getfield (1, 4)
	475 org/apache/commons/math3/optimization/direct/CMAESOptimizer.chiN:D (1, 4)
	477 ddiv (1, 4)
	478 dconst_1 (1, 4)
	479 dsub (1, 4)
	480 aload_0 (1, 4)
	481 getfield (1, 4)
	482 org/apache/commons/math3/optimization/direct/CMAESOptimizer.cs:D (1, 4)
	484 dmul (1, 4)
	485 aload_0 (1, 4)
	486 getfield (1, 4)
	487 org/apache/commons/math3/optimization/direct/CMAESOptimizer.damps:D (1, 4)
	489 ddiv (1, 4)
	490 invokestatic (1, 4)
	491 org/apache/commons/math3/util/FastMath.min:(DD)D (1, 4)
	493 invokestatic (1, 4)
	494 org/apache/commons/math3/util/FastMath.exp:(D)D (1, 4)
	496 dmul (1, 4)
	497 putfield (1, 4)
	498 org/apache/commons/math3/optimization/direct/CMAESOptimizer.sigma:D (1, 4)
	500 aload (1, 4)
	501 #9 (1, 4)
	502 aload (1, 4)
	503 #10 (1, 4)
	504 iconst_0 (1, 4)
	505 iaload (1, 4)
	506 daload (1, 4)
	507 dstore (1, 4)
	508 #16 (1, 4)
	509 aload (1, 4)
	510 #9 (1, 4)
	511 aload (1, 4)
	512 #10 (1, 4)
	513 aload (1, 4)
	514 #10 (1, 4)
	515 arraylength (1, 4)
	516 iconst_1 (1, 4)
	517 isub (1, 4)
	518 iaload (1, 4)
	519 daload (1, 4)
	520 dstore (1, 4)
	521 #18 (1, 4)
	522 dload_3 (2, 1)
	523 dload (2, 1)
	524 #16 (2, 1)
	525 dcmpl (2, 1)
	526 ifle (2, 1)
	527 81 (2, 1)
	529 dload (2, 1)
	530 #16 (2, 1)
	531 dstore_3 (2, 1)
	532 aload (2, 1)
	533 #5 (2, 1)
	534 astore (2, 1)
	535 #6 (2, 1)
	536 new (2, 1)
	537 org/apache/commons/math3/optimization/PointValuePair (2, 1)
	539 dup (2, 1)
	540 aload_1 (2, 1)
	541 aload (2, 1)
	542 #12 (2, 1)
	543 iconst_0 (2, 1)
	544 invokeinterface (2, 1)
	545 org/apache/commons/math3/linear/RealMatrix.isFeasible:([D)Z (2, 1)
	547 0 (2, 1)
	549 invokestatic (2, 1)
	550 org/apache/commons/math3/optimization/direct/CMAESOptimizer$FitnessFunction.access$000:(Lorg/apache/commons/math3/optimization/direct/CMAESOptimizer$FitnessFunction;[D)[D (2, 1)
	552 aload_0 (2, 1)
	553 getfield (2, 1)
	554 org/apache/commons/math3/optimization/direct/CMAESOptimizer.isMinimize:Z (2, 1)
	556 ifeq (2, 1)
	557 8 (2, 1)
	559 dload (2, 1)
	560 #16 (2, 1)
	561 goto (2, 1)
	562 6 (2, 1)
	564 dload (2, 1)
	565 #16 (2, 1)
	566 dneg (2, 1)
	567 invokespecial (2, 1)
	568 org/apache/commons/math3/optimization/PointValuePair.<init>:([DD)V (2, 1)
	570 astore (2, 1)
	571 #5 (2, 1)
	572 aload_0 (2, 1)
	573 invokevirtual (2, 1)
	574 org/apache/commons/math3/optimization/direct/CMAESOptimizer.getConvergenceChecker:()Lorg/apache/commons/math3/optimization/ConvergenceChecker; (2, 1)
	576 ifnull (2, 1)
	577 31 (2, 1)
	579 aload (2, 1)
	580 #6 (2, 1)
	581 ifnull (2, 1)
	582 26 (2, 1)
	584 aload_0 (2, 1)
	585 invokevirtual (2, 1)
	586 org/apache/commons/math3/optimization/direct/CMAESOptimizer.getConvergenceChecker:()Lorg/apache/commons/math3/optimization/ConvergenceChecker; (2, 1)
	588 aload_0 (2, 1)
	589 getfield (2, 1)
	590 org/apache/commons/math3/optimization/direct/CMAESOptimizer.iterations:I (2, 1)
	592 aload (2, 1)
	593 #5 (2, 1)
	594 aload (2, 1)
	595 #6 (2, 1)
	596 invokeinterface (2, 1)
	597 org/apache/commons/math3/optimization/ConvergenceChecker.diagC:Lorg/apache/commons/math3/linear/RealMatrix; (2, 1)
	599 0 (2, 1)
	601 ifeq (2, 1)
	602 6 (2, 1)
	604 goto (2, 1)
	605 565 (2, 1)
	607 aload_0 (2, 1)
	608 getfield (2, 1)
	609 org/apache/commons/math3/optimization/direct/CMAESOptimizer.stopFitness:D (2, 1)
	611 dconst_0 (2, 1)
	612 dcmpl (2, 1)
	613 ifeq (2, 1)
	614 31 (2, 1)
	616 dload (2, 1)
	617 #16 (2, 1)
	618 aload_0 (2, 1)
	619 getfield (2, 1)
	620 org/apache/commons/math3/optimization/direct/CMAESOptimizer.isMinimize:Z (2, 1)
	622 ifeq (2, 1)
	623 10 (2, 1)
	625 aload_0 (2, 1)
	626 getfield (2, 1)
	627 org/apache/commons/math3/optimization/direct/CMAESOptimizer.stopFitness:D (2, 1)
	629 goto (2, 1)
	630 8 (2, 1)
	632 aload_0 (2, 1)
	633 getfield (2, 1)
	634 org/apache/commons/math3/optimization/direct/CMAESOptimizer.stopFitness:D (2, 1)
	636 dneg (2, 1)
	637 dcmpg (2, 1)
	638 ifge (2, 1)
	639 6 (2, 1)
	641 goto (2, 1)
	642 528 (2, 1)
	644 aload_0 (1, 1)
	645 getfield (1, 1)
	646 org/apache/commons/math3/optimization/direct/CMAESOptimizer.diagC:Lorg/apache/commons/math3/linear/RealMatrix; (1, 1)
	648 invokestatic (1, 1)
	649 org/apache/commons/math3/optimization/direct/CMAESOptimizer.sqrt:(Lorg/apache/commons/math3/linear/RealMatrix;)Lorg/apache/commons/math3/linear/RealMatrix; (1, 1)
	651 iconst_0 (1, 1)
	652 invokeinterface (1, 1)
	653 org/apache/commons/math3/linear/RealMatrix.isFeasible:([D)Z (1, 1)
	655 0 (1, 1)
	657 astore (1, 1)
	658 #20 (1, 1)
	659 aload_0 (1, 1)
	660 getfield (1, 1)
	661 org/apache/commons/math3/optimization/direct/CMAESOptimizer.pc:Lorg/apache/commons/math3/linear/RealMatrix; (1, 1)
	663 iconst_0 (1, 1)
	664 invokeinterface (1, 1)
	665 org/apache/commons/math3/linear/RealMatrix.isFeasible:([D)Z (1, 1)
	667 0 (1, 1)
	669 astore (1, 1)
	670 #21 (1, 1)
	671 iconst_0 (2, 4)
	672 istore (2, 4)
	673 #22 (2, 4)
	674 iload (2, 4)
	675 #22 (2, 4)
	676 aload_0 (2, 4)
	677 getfield (2, 4)
	678 org/apache/commons/math3/optimization/direct/CMAESOptimizer.dimension:I (2, 4)
	680 if_icmpge (2, 4)
	681 55 (2, 4)
	683 aload_0 (3, 1)
	684 getfield (3, 1)
	685 org/apache/commons/math3/optimization/direct/CMAESOptimizer.sigma:D (3, 1)
	687 aload (3, 1)
	688 #21 (3, 1)
	689 iload (3, 1)
	690 #22 (3, 1)
	691 daload (3, 1)
	692 invokestatic (3, 1)
	693 org/apache/commons/math3/util/FastMath.abs:(D)D (3, 1)
	695 aload (3, 1)
	696 #20 (3, 1)
	697 iload (3, 1)
	698 #22 (3, 1)
	699 daload (3, 1)
	700 invokestatic (3, 1)
	701 org/apache/commons/math3/util/FastMath.max:(DD)D (3, 1)
	703 dmul (3, 1)
	704 aload_0 (3, 1)
	705 getfield (3, 1)
	706 org/apache/commons/math3/optimization/direct/CMAESOptimizer.stopTolX:D (3, 1)
	708 dcmpl (3, 1)
	709 ifle (3, 1)
	710 6 (3, 1)
	712 goto (3, 1)
	713 23 (3, 1)
	715 iload (3, 1)
	716 #22 (3, 1)
	717 aload_0 (3, 1)
	718 getfield (3, 1)
	719 org/apache/commons/math3/optimization/direct/CMAESOptimizer.dimension:I (3, 1)
	721 iconst_1 (3, 1)
	722 isub (3, 1)
	723 if_icmplt (3, 1)
	724 6 (3, 1)
	726 goto (3, 1)
	727 443 (3, 1)
	729 iinc (3, 1)
	730 #22 (3, 1)
	731 -89 (3, 1)
	732 goto (3, 1)
	733 -58 (3, 1)
	735 iconst_0 (3, 4)
	736 istore (3, 4)
	737 #22 (3, 4)
	738 iload (3, 4)
	739 #22 (3, 4)
	740 aload_0 (3, 4)
	741 getfield (3, 4)
	742 org/apache/commons/math3/optimization/direct/CMAESOptimizer.dimension:I (3, 4)
	744 if_icmpge (3, 4)
	745 30 (3, 4)
	747 aload_0 (4, 1)
	748 getfield (4, 1)
	749 org/apache/commons/math3/optimization/direct/CMAESOptimizer.sigma:D (4, 1)
	751 aload (4, 1)
	752 #20 (4, 1)
	753 iload (4, 1)
	754 #22 (4, 1)
	755 daload (4, 1)
	756 dmul (4, 1)
	757 aload_0 (4, 1)
	758 getfield (4, 1)
	759 org/apache/commons/math3/optimization/direct/CMAESOptimizer.stopTolUpX:D (4, 1)
	761 dcmpl (4, 1)
	762 ifle (4, 1)
	763 6 (4, 1)
	765 goto (4, 1)
	766 404 (4, 1)
	768 iinc (4, 1)
	769 #22 (4, 1)
	770 -89 (4, 1)
	771 goto (4, 1)
	772 -33 (4, 1)
	774 aload_0 (3, 4)
	775 getfield (3, 4)
	776 org/apache/commons/math3/optimization/direct/CMAESOptimizer.fitnessHistory:[D (3, 4)
	778 invokestatic (3, 4)
	779 org/apache/commons/math3/optimization/direct/CMAESOptimizer.min:([D)D (3, 4)
	781 dstore (3, 4)
	782 #22 (3, 4)
	783 aload_0 (3, 4)
	784 getfield (3, 4)
	785 org/apache/commons/math3/optimization/direct/CMAESOptimizer.fitnessHistory:[D (3, 4)
	787 invokestatic (3, 4)
	788 org/apache/commons/math3/optimization/direct/CMAESOptimizer.max:([D)D (3, 4)
	790 dstore (3, 4)
	791 #24 (3, 4)
	792 aload_0 (3, 1)
	793 getfield (3, 1)
	794 org/apache/commons/math3/optimization/direct/CMAESOptimizer.iterations:I (3, 1)
	796 iconst_2 (3, 1)
	797 if_icmple (3, 1)
	798 29 (3, 1)
	800 dload (3, 1)
	801 #24 (3, 1)
	802 dload (3, 1)
	803 #18 (3, 1)
	804 invokestatic (3, 1)
	805 org/apache/commons/math3/util/FastMath.max:(DD)D (3, 1)
	807 dload (3, 1)
	808 #22 (3, 1)
	809 dload (3, 1)
	810 #16 (3, 1)
	811 invokestatic (3, 1)
	812 org/apache/commons/math3/util/FastMath.min:(DD)D (3, 1)
	814 dsub (3, 1)
	815 aload_0 (3, 1)
	816 getfield (3, 1)
	817 org/apache/commons/math3/optimization/direct/CMAESOptimizer.stopTolFun:D (3, 1)
	819 dcmpg (3, 1)
	820 ifge (3, 1)
	821 6 (3, 1)
	823 goto (3, 1)
	824 346 (3, 1)
	826 aload_0 (3, 1)
	827 getfield (3, 1)
	828 org/apache/commons/math3/optimization/direct/CMAESOptimizer.iterations:I (3, 1)
	830 aload_0 (3, 1)
	831 getfield (3, 1)
	832 org/apache/commons/math3/optimization/direct/CMAESOptimizer.fitnessHistory:[D (3, 1)
	834 arraylength (3, 1)
	835 if_icmple (3, 1)
	836 19 (3, 1)
	838 dload (3, 1)
	839 #24 (3, 1)
	840 dload (3, 1)
	841 #22 (3, 1)
	842 dsub (3, 1)
	843 aload_0 (3, 1)
	844 getfield (3, 1)
	845 org/apache/commons/math3/optimization/direct/CMAESOptimizer.stopTolHistFun:D (3, 1)
	847 dcmpg (3, 1)
	848 ifge (3, 1)
	849 6 (3, 1)
	851 goto (3, 1)
	852 318 (3, 1)
	854 aload_0 (4, 1)
	855 getfield (4, 1)
	856 org/apache/commons/math3/optimization/direct/CMAESOptimizer.diagD:Lorg/apache/commons/math3/linear/RealMatrix; (4, 1)
	858 invokestatic (4, 1)
	859 org/apache/commons/math3/optimization/direct/CMAESOptimizer.max:(Lorg/apache/commons/math3/linear/RealMatrix;)D (4, 1)
	861 aload_0 (4, 1)
	862 getfield (4, 1)
	863 org/apache/commons/math3/optimization/direct/CMAESOptimizer.diagD:Lorg/apache/commons/math3/linear/RealMatrix; (4, 1)
	865 invokestatic (4, 1)
	866 org/apache/commons/math3/optimization/direct/CMAESOptimizer.min:(Lorg/apache/commons/math3/linear/RealMatrix;)D (4, 1)
	868 ddiv (4, 1)
	869 ldc2_w (4, 1)
	870 10000000.0 (4, 1)
	872 dcmpl (4, 1)
	873 ifle (4, 1)
	874 6 (4, 1)
	876 goto (4, 1)
	877 293 (4, 1)
	879 aload_0 (4, 1)
	880 invokevirtual (4, 1)
	881 org/apache/commons/math3/optimization/direct/CMAESOptimizer.getConvergenceChecker:()Lorg/apache/commons/math3/optimization/ConvergenceChecker; (4, 1)
	883 ifnull (4, 1)
	884 67 (4, 1)
	886 new (4, 1)
	887 org/apache/commons/math3/optimization/PointValuePair (4, 1)
	889 dup (4, 1)
	890 aload (4, 1)
	891 #12 (4, 1)
	892 iconst_0 (4, 1)
	893 invokeinterface (4, 1)
	894 org/apache/commons/math3/linear/RealMatrix.isFeasible:([D)Z (4, 1)
	896 0 (4, 1)
	898 aload_0 (4, 1)
	899 getfield (4, 1)
	900 org/apache/commons/math3/optimization/direct/CMAESOptimizer.isMinimize:Z (4, 1)
	902 ifeq (4, 1)
	903 8 (4, 1)
	905 dload (4, 1)
	906 #16 (4, 1)
	907 goto (4, 1)
	908 6 (4, 1)
	910 dload (4, 1)
	911 #16 (4, 1)
	912 dneg (4, 1)
	913 invokespecial (4, 1)
	914 org/apache/commons/math3/optimization/PointValuePair.<init>:([DD)V (4, 1)
	916 astore (4, 1)
	917 #26 (4, 1)
	918 aload (4, 1)
	919 #6 (4, 1)
	920 ifnull (4, 1)
	921 26 (4, 1)
	923 aload_0 (4, 1)
	924 invokevirtual (4, 1)
	925 org/apache/commons/math3/optimization/direct/CMAESOptimizer.getConvergenceChecker:()Lorg/apache/commons/math3/optimization/ConvergenceChecker; (4, 1)
	927 aload_0 (4, 1)
	928 getfield (4, 1)
	929 org/apache/commons/math3/optimization/direct/CMAESOptimizer.iterations:I (4, 1)
	931 aload (4, 1)
	932 #26 (4, 1)
	933 aload (4, 1)
	934 #6 (4, 1)
	935 invokeinterface (4, 1)
	936 org/apache/commons/math3/optimization/ConvergenceChecker.diagC:Lorg/apache/commons/math3/linear/RealMatrix; (4, 1)
	938 0 (4, 1)
	940 ifeq (4, 1)
	941 6 (4, 1)
	943 goto (4, 1)
	944 226 (4, 1)
	946 aload (4, 1)
	947 #26 (4, 1)
	948 astore (4, 1)
	949 #6 (4, 1)
	950 dload_3 (4, 1)
	951 aload (4, 1)
	952 #9 (4, 1)
	953 aload (4, 1)
	954 #10 (4, 1)
	955 ldc2_w (4, 1)
	956 0.1 (4, 1)
	958 aload_0 (4, 1)
	959 getfield (4, 1)
	960 org/apache/commons/math3/optimization/direct/CMAESOptimizer.lambda:I (4, 1)
	962 i2d (4, 1)
	963 ldc2_w (4, 1)
	964 4.0 (4, 1)
	966 ddiv (4, 1)
	967 dadd (4, 1)
	968 d2i (4, 1)
	969 iaload (4, 1)
	970 daload (4, 1)
	971 dcmpl (4, 1)
	972 ifne (4, 1)
	973 28 (4, 1)
	975 aload_0 (4, 1)
	976 dup (4, 1)
	977 getfield (4, 1)
	978 org/apache/commons/math3/optimization/direct/CMAESOptimizer.sigma:D (4, 1)
	980 ldc2_w (4, 1)
	981 0.2 (4, 1)
	983 aload_0 (4, 1)
	984 getfield (4, 1)
	985 org/apache/commons/math3/optimization/direct/CMAESOptimizer.cs:D (4, 1)
	987 aload_0 (4, 1)
	988 getfield (4, 1)
	989 org/apache/commons/math3/optimization/direct/CMAESOptimizer.damps:D (4, 1)
	991 ddiv (4, 1)
	992 dadd (4, 1)
	993 invokestatic (4, 1)
	994 org/apache/commons/math3/util/FastMath.exp:(D)D (4, 1)
	996 dmul (4, 1)
	997 putfield (4, 1)
	998 org/apache/commons/math3/optimization/direct/CMAESOptimizer.sigma:D (4, 1)
	1000 aload_0 (3, 1)
	1001 getfield (3, 1)
	1002 org/apache/commons/math3/optimization/direct/CMAESOptimizer.iterations:I (3, 1)
	1004 iconst_2 (3, 1)
	1005 if_icmple (3, 1)
	1006 48 (3, 1)
	1008 dload (3, 1)
	1009 #24 (3, 1)
	1010 dload (3, 1)
	1011 #16 (3, 1)
	1012 invokestatic (3, 1)
	1013 org/apache/commons/math3/util/FastMath.max:(DD)D (3, 1)
	1015 dload (3, 1)
	1016 #22 (3, 1)
	1017 dload (3, 1)
	1018 #16 (3, 1)
	1019 invokestatic (3, 1)
	1020 org/apache/commons/math3/util/FastMath.min:(DD)D (3, 1)
	1022 dsub (3, 1)
	1023 dconst_0 (3, 1)
	1024 dcmpl (3, 1)
	1025 ifne (3, 1)
	1026 28 (3, 1)
	1028 aload_0 (3, 1)
	1029 dup (3, 1)
	1030 getfield (3, 1)
	1031 org/apache/commons/math3/optimization/direct/CMAESOptimizer.sigma:D (3, 1)
	1033 ldc2_w (3, 1)
	1034 0.2 (3, 1)
	1036 aload_0 (3, 1)
	1037 getfield (3, 1)
	1038 org/apache/commons/math3/optimization/direct/CMAESOptimizer.cs:D (3, 1)
	1040 aload_0 (3, 1)
	1041 getfield (3, 1)
	1042 org/apache/commons/math3/optimization/direct/CMAESOptimizer.damps:D (3, 1)
	1044 ddiv (3, 1)
	1045 dadd (3, 1)
	1046 invokestatic (3, 1)
	1047 org/apache/commons/math3/util/FastMath.exp:(D)D (3, 1)
	1049 dmul (3, 1)
	1050 putfield (3, 1)
	1051 org/apache/commons/math3/optimization/direct/CMAESOptimizer.sigma:D (3, 1)
	1053 aload_0 (3, 1)
	1054 getfield (3, 1)
	1055 org/apache/commons/math3/optimization/direct/CMAESOptimizer.fitnessHistory:[D (3, 1)
	1057 dload (3, 1)
	1058 #16 (3, 1)
	1059 invokestatic (3, 1)
	1060 org/apache/commons/math3/optimization/direct/CMAESOptimizer.push:([DD)V (3, 1)
	1062 aload_1 (3, 1)
	1063 dload (3, 1)
	1064 #18 (3, 1)
	1065 dload (3, 1)
	1066 #16 (3, 1)
	1067 dsub (3, 1)
	1068 invokevirtual (3, 1)
	1069 org/apache/commons/math3/optimization/direct/CMAESOptimizer$FitnessFunction.setValueRange:(D)V (3, 1)
	1071 aload_0 (4, 1)
	1072 getfield (4, 1)
	1073 org/apache/commons/math3/optimization/direct/CMAESOptimizer.generateStatistics:Z (4, 1)
	1075 ifeq (4, 1)
	1076 81 (4, 1)
	1078 aload_0 (4, 1)
	1079 getfield (4, 1)
	1080 org/apache/commons/math3/optimization/direct/CMAESOptimizer.statisticsSigmaHistory:Ljava/util/List; (4, 1)
	1082 aload_0 (4, 1)
	1083 getfield (4, 1)
	1084 org/apache/commons/math3/optimization/direct/CMAESOptimizer.sigma:D (4, 1)
	1086 invokestatic (4, 1)
	1087 java/lang/Double.valueOf:(D)Ljava/lang/Double; (4, 1)
	1089 invokeinterface (4, 1)
	1090 java/util/List.transpose:()Lorg/apache/commons/math3/linear/RealMatrix; (4, 1)
	1092 0 (4, 1)
	1094 pop (4, 1)
	1095 aload_0 (4, 1)
	1096 getfield (4, 1)
	1097 org/apache/commons/math3/optimization/direct/CMAESOptimizer.statisticsFitnessHistory:Ljava/util/List; (4, 1)
	1099 dload (4, 1)
	1100 #16 (4, 1)
	1101 invokestatic (4, 1)
	1102 java/lang/Double.valueOf:(D)Ljava/lang/Double; (4, 1)
	1104 invokeinterface (4, 1)
	1105 java/util/List.transpose:()Lorg/apache/commons/math3/linear/RealMatrix; (4, 1)
	1107 0 (4, 1)
	1109 pop (4, 1)
	1110 aload_0 (4, 1)
	1111 getfield (4, 1)
	1112 org/apache/commons/math3/optimization/direct/CMAESOptimizer.statisticsMeanHistory:Ljava/util/List; (4, 1)
	1114 aload_0 (4, 1)
	1115 getfield (4, 1)
	1116 org/apache/commons/math3/optimization/direct/CMAESOptimizer.xmean:Lorg/apache/commons/math3/linear/RealMatrix; (4, 1)
	1118 invokeinterface (4, 1)
	1119 org/apache/commons/math3/linear/RealMatrix.org/apache/commons/math3/optimization/direct/CMAESOptimizer$Sigma (4, 1)
	1121 0 (4, 1)
	1123 invokeinterface (4, 1)
	1124 java/util/List.transpose:()Lorg/apache/commons/math3/linear/RealMatrix; (4, 1)
	1126 0 (4, 1)
	1128 pop (4, 1)
	1129 aload_0 (4, 1)
	1130 getfield (4, 1)
	1131 org/apache/commons/math3/optimization/direct/CMAESOptimizer.statisticsDHistory:Ljava/util/List; (4, 1)
	1133 aload_0 (4, 1)
	1134 getfield (4, 1)
	1135 org/apache/commons/math3/optimization/direct/CMAESOptimizer.diagD:Lorg/apache/commons/math3/linear/RealMatrix; (4, 1)
	1137 invokeinterface (4, 1)
	1138 org/apache/commons/math3/linear/RealMatrix.org/apache/commons/math3/optimization/direct/CMAESOptimizer$Sigma (4, 1)
	1140 0 (4, 1)
	1142 ldc2_w (4, 1)
	1143 100000.0 (4, 1)
	1145 invokeinterface (4, 1)
	1146 org/apache/commons/math3/linear/RealMatrix.add:(Lorg/apache/commons/math3/linear/RealMatrix;)Lorg/apache/commons/math3/linear/RealMatrix; (4, 1)
	1148 0 (4, 1)
	1150 invokeinterface (4, 1)
	1151 java/util/List.transpose:()Lorg/apache/commons/math3/linear/RealMatrix; (4, 1)
	1153 0 (4, 1)
	1155 pop (4, 1)
	1156 aload_0 (4, 1)
	1157 dup (4, 1)
	1158 getfield (4, 1)
	1159 org/apache/commons/math3/optimization/direct/CMAESOptimizer.iterations:I (4, 1)
	1161 iconst_1 (4, 1)
	1162 iadd (4, 1)
	1163 putfield (4, 1)
	1164 org/apache/commons/math3/optimization/direct/CMAESOptimizer.iterations:I (4, 1)
	1166 goto (4, 1)
	1167 -1070 (4, 1)
	1169 aload (3, 1)
	1170 #5 (3, 1)
	1171 areturn (3, 1)

Method: parseOptimizationData
	0 aload_1 (1, 4)
	1 astore_2 (1, 4)
	2 aload_2 (1, 4)
	3 arraylength (1, 4)
	4 istore_3 (1, 4)
	5 iconst_0 (1, 4)
	6 istore (1, 4)
	7 #4 (1, 4)
	8 iload (1, 4)
	9 #4 (1, 4)
	10 iload_3 (1, 4)
	11 if_icmpge (1, 4)
	12 61 (1, 4)
	14 aload_2 (1, 4)
	15 iload (1, 4)
	16 #4 (1, 4)
	17 aaload (1, 4)
	18 astore (1, 4)
	19 #5 (1, 4)
	20 aload (2, 1)
	21 #5 (2, 1)
	22 instanceof (2, 1)
	23 org/apache/commons/math3/optimization/direct/CMAESOptimizer$Sigma (2, 1)
	25 ifeq (2, 1)
	26 18 (2, 1)
	28 aload_0 (2, 1)
	29 aload (2, 1)
	30 #5 (2, 1)
	31 checkcast (2, 1)
	32 org/apache/commons/math3/optimization/direct/CMAESOptimizer$Sigma (2, 1)
	34 invokevirtual (2, 1)
	35 org/apache/commons/math3/optimization/direct/CMAESOptimizer$Sigma.getSigma:()[D (2, 1)
	37 putfield (2, 1)
	38 org/apache/commons/math3/optimization/direct/CMAESOptimizer.inputSigma:[D (2, 1)
	40 goto (2, 1)
	41 26 (2, 1)
	43 aload (2, 1)
	44 #5 (2, 1)
	45 instanceof (2, 1)
	46 org/apache/commons/math3/optimization/direct/CMAESOptimizer$PopulationSize (2, 1)
	48 ifeq (2, 1)
	49 18 (2, 1)
	51 aload_0 (2, 1)
	52 aload (2, 1)
	53 #5 (2, 1)
	54 checkcast (2, 1)
	55 org/apache/commons/math3/optimization/direct/CMAESOptimizer$PopulationSize (2, 1)
	57 invokevirtual (2, 1)
	58 org/apache/commons/math3/optimization/direct/CMAESOptimizer$PopulationSize.getPopulationSize:()I (2, 1)
	60 putfield (2, 1)
	61 org/apache/commons/math3/optimization/direct/CMAESOptimizer.lambda:I (2, 1)
	63 goto (2, 1)
	64 3 (2, 1)
	66 iinc (2, 1)
	67 #4 (2, 1)
	68 -89 (2, 1)
	69 goto (2, 1)
	70 -61 (2, 1)
	72 return (0, 0)

Method: checkParameters
	0 aload_0 (0, 0)
	1 invokevirtual (0, 0)
	2 org/apache/commons/math3/optimization/direct/CMAESOptimizer.getStartPoint:()[D (0, 0)
	4 astore_1 (0, 0)
	5 aload_0 (0, 0)
	6 invokevirtual (0, 0)
	7 org/apache/commons/math3/optimization/direct/CMAESOptimizer.getLowerBound:()[D (0, 0)
	9 astore_2 (0, 0)
	10 aload_0 (0, 0)
	11 invokevirtual (0, 0)
	12 org/apache/commons/math3/optimization/direct/CMAESOptimizer.getUpperBound:()[D (0, 0)
	14 astore_3 (0, 0)
	15 aload_0 (1, 1)
	16 getfield (1, 1)
	17 org/apache/commons/math3/optimization/direct/CMAESOptimizer.inputSigma:[D (1, 1)
	19 ifnull (1, 1)
	20 128 (1, 1)
	22 aload_0 (2, 1)
	23 getfield (2, 1)
	24 org/apache/commons/math3/optimization/direct/CMAESOptimizer.inputSigma:[D (2, 1)
	26 arraylength (2, 1)
	27 aload_1 (2, 1)
	28 arraylength (2, 1)
	29 if_icmpeq (2, 1)
	30 18 (2, 1)
	32 new (2, 1)
	33 org/apache/commons/math3/exception/DimensionMismatchException (2, 1)
	35 dup (2, 1)
	36 aload_0 (2, 1)
	37 getfield (2, 1)
	38 org/apache/commons/math3/optimization/direct/CMAESOptimizer.inputSigma:[D (2, 1)
	40 arraylength (2, 1)
	41 aload_1 (2, 1)
	42 arraylength (2, 1)
	43 invokespecial (2, 1)
	44 org/apache/commons/math3/exception/DimensionMismatchException.<init>:(II)V (2, 1)
	46 athrow (2, 1)
	47 iconst_0 (2, 4)
	48 istore (2, 4)
	49 #4 (2, 4)
	50 iload (2, 4)
	51 #4 (2, 4)
	52 aload_1 (2, 4)
	53 arraylength (2, 4)
	54 if_icmpge (2, 4)
	55 93 (2, 4)
	57 aload_0 (3, 1)
	58 getfield (3, 1)
	59 org/apache/commons/math3/optimization/direct/CMAESOptimizer.inputSigma:[D (3, 1)
	61 iload (3, 1)
	62 #4 (3, 1)
	63 daload (3, 1)
	64 dconst_0 (3, 1)
	65 dcmpg (3, 1)
	66 ifge (3, 1)
	67 21 (3, 1)
	69 new (3, 4)
	70 org/apache/commons/math3/exception/NotPositiveException (3, 4)
	72 dup (3, 4)
	73 aload_0 (3, 4)
	74 getfield (3, 4)
	75 org/apache/commons/math3/optimization/direct/CMAESOptimizer.inputSigma:[D (3, 4)
	77 iload (3, 4)
	78 #4 (3, 4)
	79 daload (3, 4)
	80 invokestatic (3, 4)
	81 java/lang/Double.valueOf:(D)Ljava/lang/Double; (3, 4)
	83 invokespecial (3, 4)
	84 org/apache/commons/math3/exception/NotPositiveException.<init>:(Ljava/lang/Number;)V (3, 4)
	86 athrow (3, 4)
	87 aload_0 (3, 1)
	88 getfield (3, 1)
	89 org/apache/commons/math3/optimization/direct/CMAESOptimizer.inputSigma:[D (3, 1)
	91 iload (3, 1)
	92 #4 (3, 1)
	93 daload (3, 1)
	94 aload_3 (3, 1)
	95 iload (3, 1)
	96 #4 (3, 1)
	97 daload (3, 1)
	98 aload_2 (3, 1)
	99 iload (3, 1)
	100 #4 (3, 1)
	101 daload (3, 1)
	102 dsub (3, 1)
	103 dcmpl (3, 1)
	104 ifle (3, 1)
	105 37 (3, 1)
	107 new (3, 1)
	108 org/apache/commons/math3/exception/OutOfRangeException (3, 1)
	110 dup (3, 1)
	111 aload_0 (3, 1)
	112 getfield (3, 1)
	113 org/apache/commons/math3/optimization/direct/CMAESOptimizer.inputSigma:[D (3, 1)
	115 iload (3, 1)
	116 #4 (3, 1)
	117 daload (3, 1)
	118 invokestatic (3, 1)
	119 java/lang/Double.valueOf:(D)Ljava/lang/Double; (3, 1)
	121 iconst_0 (3, 1)
	122 invokestatic (3, 1)
	123 java/lang/Integer.valueOf:(I)Ljava/lang/Integer; (3, 1)
	125 aload_3 (3, 1)
	126 iload (3, 1)
	127 #4 (3, 1)
	128 daload (3, 1)
	129 aload_2 (3, 1)
	130 iload (3, 1)
	131 #4 (3, 1)
	132 daload (3, 1)
	133 dsub (3, 1)
	134 invokestatic (3, 1)
	135 java/lang/Double.valueOf:(D)Ljava/lang/Double; (3, 1)
	137 invokespecial (3, 1)
	138 org/apache/commons/math3/exception/OutOfRangeException.<init>:(Ljava/lang/Number;Ljava/lang/Number;Ljava/lang/Number;)V (3, 1)
	140 athrow (3, 1)
	141 iinc (3, 1)
	142 #4 (3, 1)
	143 -89 (3, 1)
	144 goto (3, 1)
	145 -94 (3, 1)
	147 return (0, 0)

Method: initializeCMA
	0 aload_0 (1, 1)
	1 getfield (1, 1)
	2 org/apache/commons/math3/optimization/direct/CMAESOptimizer.lambda:I (1, 1)
	4 ifgt (1, 1)
	5 22 (1, 1)
	7 aload_0 (1, 1)
	8 iconst_4 (1, 1)
	9 ldc2_w (1, 1)
	10 3.0 (1, 1)
	12 aload_0 (1, 1)
	13 getfield (1, 1)
	14 org/apache/commons/math3/optimization/direct/CMAESOptimizer.dimension:I (1, 1)
	16 i2d (1, 1)
	17 invokestatic (1, 1)
	18 org/apache/commons/math3/util/FastMath.log:(D)D (1, 1)
	20 dmul (1, 1)
	21 d2i (1, 1)
	22 iadd (1, 1)
	23 putfield (1, 1)
	24 org/apache/commons/math3/optimization/direct/CMAESOptimizer.lambda:I (1, 1)
	26 aload_1 (0, 0)
	27 arraylength (0, 0)
	28 iconst_1 (0, 0)
	29 multianewarray (0, 0)
	30 [[D (0, 0)
	32 77 (0, 0)
	33 astore_2 (0, 0)
	34 iconst_0 (1, 4)
	35 istore_3 (1, 4)
	36 iload_3 (1, 4)
	37 aload_1 (1, 4)
	38 arraylength (1, 4)
	39 if_icmpge (1, 4)
	40 33 (1, 4)
	42 aload_2 (1, 4)
	43 iload_3 (1, 4)
	44 aaload (1, 4)
	45 iconst_0 (1, 4)
	46 aload_0 (1, 4)
	47 getfield (1, 4)
	48 org/apache/commons/math3/optimization/direct/CMAESOptimizer.inputSigma:[D (1, 4)
	50 ifnonnull (1, 4)
	51 9 (1, 4)
	53 ldc2_w (1, 4)
	54 0.3 (1, 4)
	56 goto (1, 4)
	57 9 (1, 4)
	59 aload_0 (1, 4)
	60 getfield (1, 4)
	61 org/apache/commons/math3/optimization/direct/CMAESOptimizer.inputSigma:[D (1, 4)
	63 iload_3 (1, 4)
	64 daload (1, 4)
	65 dastore (1, 4)
	66 iinc (1, 4)
	67 #3 (1, 4)
	68 -89 (1, 4)
	69 goto (1, 4)
	70 -33 (1, 4)
	72 new (0, 0)
	73 org/apache/commons/math3/linear/Array2DRowRealMatrix (0, 0)
	75 dup (0, 0)
	76 aload_2 (0, 0)
	77 iconst_0 (0, 0)
	78 invokespecial (0, 0)
	79 org/apache/commons/math3/linear/Array2DRowRealMatrix.<init>:([[DZ)V (0, 0)
	81 astore_3 (0, 0)
	82 aload_0 (0, 0)
	83 aload_3 (0, 0)
	84 invokestatic (0, 0)
	85 org/apache/commons/math3/optimization/direct/CMAESOptimizer.max:(Lorg/apache/commons/math3/linear/RealMatrix;)D (0, 0)
	87 putfield (0, 0)
	88 org/apache/commons/math3/optimization/direct/CMAESOptimizer.sigma:D (0, 0)
	90 aload_0 (0, 0)
	91 ldc2_w (0, 0)
	92 1000.0 (0, 0)
	94 aload_3 (0, 0)
	95 invokestatic (0, 0)
	96 org/apache/commons/math3/optimization/direct/CMAESOptimizer.max:(Lorg/apache/commons/math3/linear/RealMatrix;)D (0, 0)
	98 dmul (0, 0)
	99 putfield (0, 0)
	100 org/apache/commons/math3/optimization/direct/CMAESOptimizer.stopTolUpX:D (0, 0)
	102 aload_0 (0, 0)
	103 ldc2_w (0, 0)
	104 1e-11 (0, 0)
	106 aload_3 (0, 0)
	107 invokestatic (0, 0)
	108 org/apache/commons/math3/optimization/direct/CMAESOptimizer.max:(Lorg/apache/commons/math3/linear/RealMatrix;)D (0, 0)
	110 dmul (0, 0)
	111 putfield (0, 0)
	112 org/apache/commons/math3/optimization/direct/CMAESOptimizer.stopTolX:D (0, 0)
	114 aload_0 (0, 0)
	115 ldc2_w (0, 0)
	116 1e-12 (0, 0)
	118 putfield (0, 0)
	119 org/apache/commons/math3/optimization/direct/CMAESOptimizer.stopTolFun:D (0, 0)
	121 aload_0 (0, 0)
	122 ldc2_w (0, 0)
	123 1e-13 (0, 0)
	125 putfield (0, 0)
	126 org/apache/commons/math3/optimization/direct/CMAESOptimizer.stopTolHistFun:D (0, 0)
	128 aload_0 (0, 4)
	129 aload_0 (0, 4)
	130 getfield (0, 4)
	131 org/apache/commons/math3/optimization/direct/CMAESOptimizer.lambda:I (0, 4)
	133 iconst_2 (0, 4)
	134 idiv (0, 4)
	135 putfield (0, 4)
	136 org/apache/commons/math3/optimization/direct/CMAESOptimizer.mu:I (0, 4)
	138 aload_0 (0, 4)
	139 aload_0 (0, 4)
	140 getfield (0, 4)
	141 org/apache/commons/math3/optimization/direct/CMAESOptimizer.mu:I (0, 4)
	143 i2d (0, 4)
	144 ldc2_w (0, 4)
	145 0.5 (0, 4)
	147 dadd (0, 4)
	148 invokestatic (0, 4)
	149 org/apache/commons/math3/util/FastMath.log:(D)D (0, 4)
	151 putfield (0, 4)
	152 org/apache/commons/math3/optimization/direct/CMAESOptimizer.logMu2:D (0, 4)
	154 aload_0 (0, 4)
	155 dconst_1 (0, 4)
	156 aload_0 (0, 4)
	157 getfield (0, 4)
	158 org/apache/commons/math3/optimization/direct/CMAESOptimizer.mu:I (0, 4)
	160 i2d (0, 4)
	161 dconst_1 (0, 4)
	162 invokestatic (0, 4)
	163 org/apache/commons/math3/optimization/direct/CMAESOptimizer.sequence:(DDD)Lorg/apache/commons/math3/linear/RealMatrix; (0, 4)
	165 invokestatic (0, 4)
	166 org/apache/commons/math3/optimization/direct/CMAESOptimizer.log:(Lorg/apache/commons/math3/linear/RealMatrix;)Lorg/apache/commons/math3/linear/RealMatrix; (0, 4)
	168 ldc2_w (0, 4)
	169 -1.0 (0, 4)
	171 invokeinterface (0, 4)
	172 org/apache/commons/math3/linear/RealMatrix.add:(Lorg/apache/commons/math3/linear/RealMatrix;)Lorg/apache/commons/math3/linear/RealMatrix; (0, 4)
	174 0 (0, 4)
	176 aload_0 (0, 4)
	177 getfield (0, 4)
	178 org/apache/commons/math3/optimization/direct/CMAESOptimizer.logMu2:D (0, 4)
	180 invokeinterface (0, 4)
	181 org/apache/commons/math3/linear/RealMatrix.getEntry:(II)D (0, 4)
	183 0 (0, 4)
	185 putfield (0, 4)
	186 org/apache/commons/math3/optimization/direct/CMAESOptimizer.weights:Lorg/apache/commons/math3/linear/RealMatrix; (0, 4)
	188 dconst_0 (0, 4)
	189 dstore (0, 4)
	190 #4 (0, 4)
	191 dconst_0 (0, 4)
	192 dstore (0, 4)
	193 #6 (0, 4)
	194 iconst_0 (1, 4)
	195 istore (1, 4)
	196 #8 (1, 4)
	197 iload (1, 4)
	198 #8 (1, 4)
	199 aload_0 (1, 4)
	200 getfield (1, 4)
	201 org/apache/commons/math3/optimization/direct/CMAESOptimizer.mu:I (1, 4)
	203 if_icmpge (1, 4)
	204 40 (1, 4)
	206 aload_0 (1, 4)
	207 getfield (1, 4)
	208 org/apache/commons/math3/optimization/direct/CMAESOptimizer.weights:Lorg/apache/commons/math3/linear/RealMatrix; (1, 4)
	210 iload (1, 4)
	211 #8 (1, 4)
	212 iconst_0 (1, 4)
	213 invokeinterface (1, 4)
	214 org/apache/commons/math3/linear/RealMatrix.mueff:D (1, 4)
	216 0 (1, 4)
	218 dstore (1, 4)
	219 #9 (1, 4)
	220 dload (1, 4)
	221 #4 (1, 4)
	222 dload (1, 4)
	223 #9 (1, 4)
	224 dadd (1, 4)
	225 dstore (1, 4)
	226 #4 (1, 4)
	227 dload (1, 4)
	228 #6 (1, 4)
	229 dload (1, 4)
	230 #9 (1, 4)
	231 dload (1, 4)
	232 #9 (1, 4)
	233 dmul (1, 4)
	234 dadd (1, 4)
	235 dstore (1, 4)
	236 #6 (1, 4)
	237 iinc (1, 4)
	238 #8 (1, 4)
	239 -89 (1, 4)
	240 goto (1, 4)
	241 -43 (1, 4)
	243 aload_0 (0, 4)
	244 aload_0 (0, 4)
	245 getfield (0, 4)
	246 org/apache/commons/math3/optimization/direct/CMAESOptimizer.weights:Lorg/apache/commons/math3/linear/RealMatrix; (0, 4)
	248 dconst_1 (0, 4)
	249 dload (0, 4)
	250 #4 (0, 4)
	251 ddiv (0, 4)
	252 invokeinterface (0, 4)
	253 org/apache/commons/math3/linear/RealMatrix.add:(Lorg/apache/commons/math3/linear/RealMatrix;)Lorg/apache/commons/math3/linear/RealMatrix; (0, 4)
	255 0 (0, 4)
	257 putfield (0, 4)
	258 org/apache/commons/math3/optimization/direct/CMAESOptimizer.weights:Lorg/apache/commons/math3/linear/RealMatrix; (0, 4)
	260 aload_0 (0, 4)
	261 dload (0, 4)
	262 #4 (0, 4)
	263 dload (0, 4)
	264 #4 (0, 4)
	265 dmul (0, 4)
	266 dload (0, 4)
	267 #6 (0, 4)
	268 ddiv (0, 4)
	269 putfield (0, 4)
	270 org/apache/commons/math3/optimization/direct/CMAESOptimizer.mueff:D (0, 4)
	272 aload_0 (0, 4)
	273 ldc2_w (0, 4)
	274 4.0 (0, 4)
	276 aload_0 (0, 4)
	277 getfield (0, 4)
	278 org/apache/commons/math3/optimization/direct/CMAESOptimizer.mueff:D (0, 4)
	280 aload_0 (0, 4)
	281 getfield (0, 4)
	282 org/apache/commons/math3/optimization/direct/CMAESOptimizer.dimension:I (0, 4)
	284 i2d (0, 4)
	285 ddiv (0, 4)
	286 dadd (0, 4)
	287 aload_0 (0, 4)
	288 getfield (0, 4)
	289 org/apache/commons/math3/optimization/direct/CMAESOptimizer.dimension:I (0, 4)
	291 iconst_4 (0, 4)
	292 iadd (0, 4)
	293 i2d (0, 4)
	294 ldc2_w (0, 4)
	295 2.0 (0, 4)
	297 aload_0 (0, 4)
	298 getfield (0, 4)
	299 org/apache/commons/math3/optimization/direct/CMAESOptimizer.mueff:D (0, 4)
	301 dmul (0, 4)
	302 aload_0 (0, 4)
	303 getfield (0, 4)
	304 org/apache/commons/math3/optimization/direct/CMAESOptimizer.dimension:I (0, 4)
	306 i2d (0, 4)
	307 ddiv (0, 4)
	308 dadd (0, 4)
	309 ddiv (0, 4)
	310 putfield (0, 4)
	311 org/apache/commons/math3/optimization/direct/CMAESOptimizer.cc:D (0, 4)
	313 aload_0 (0, 4)
	314 aload_0 (0, 4)
	315 getfield (0, 4)
	316 org/apache/commons/math3/optimization/direct/CMAESOptimizer.mueff:D (0, 4)
	318 ldc2_w (0, 4)
	319 2.0 (0, 4)
	321 dadd (0, 4)
	322 aload_0 (0, 4)
	323 getfield (0, 4)
	324 org/apache/commons/math3/optimization/direct/CMAESOptimizer.dimension:I (0, 4)
	326 i2d (0, 4)
	327 aload_0 (0, 4)
	328 getfield (0, 4)
	329 org/apache/commons/math3/optimization/direct/CMAESOptimizer.mueff:D (0, 4)
	331 dadd (0, 4)
	332 ldc2_w (0, 4)
	333 3.0 (0, 4)
	335 dadd (0, 4)
	336 ddiv (0, 4)
	337 putfield (0, 4)
	338 org/apache/commons/math3/optimization/direct/CMAESOptimizer.cs:D (0, 4)
	340 aload_0 (0, 4)
	341 dconst_1 (0, 4)
	342 ldc2_w (0, 4)
	343 2.0 (0, 4)
	345 dconst_0 (0, 4)
	346 aload_0 (0, 4)
	347 getfield (0, 4)
	348 org/apache/commons/math3/optimization/direct/CMAESOptimizer.mueff:D (0, 4)
	350 dconst_1 (0, 4)
	351 dsub (0, 4)
	352 aload_0 (0, 4)
	353 getfield (0, 4)
	354 org/apache/commons/math3/optimization/direct/CMAESOptimizer.dimension:I (0, 4)
	356 iconst_1 (0, 4)
	357 iadd (0, 4)
	358 i2d (0, 4)
	359 ddiv (0, 4)
	360 invokestatic (0, 4)
	361 org/apache/commons/math3/util/FastMath.sqrt:(D)D (0, 4)
	363 dconst_1 (0, 4)
	364 dsub (0, 4)
	365 invokestatic (0, 4)
	366 org/apache/commons/math3/util/FastMath.max:(DD)D (0, 4)
	368 dmul (0, 4)
	369 dadd (0, 4)
	370 ldc2_w (0, 4)
	371 0.3 (0, 4)
	373 dconst_1 (0, 4)
	374 aload_0 (0, 4)
	375 getfield (0, 4)
	376 org/apache/commons/math3/optimization/direct/CMAESOptimizer.dimension:I (0, 4)
	378 i2d (0, 4)
	379 ldc2_w (0, 4)
	380 1e-06 (0, 4)
	382 aload_0 (0, 4)
	383 getfield (0, 4)
	384 org/apache/commons/math3/optimization/direct/CMAESOptimizer.maxIterations:I (0, 4)
	386 i2d (0, 4)
	387 dadd (0, 4)
	388 ddiv (0, 4)
	389 dsub (0, 4)
	390 invokestatic (0, 4)
	391 org/apache/commons/math3/util/FastMath.max:(DD)D (0, 4)
	393 dmul (0, 4)
	394 aload_0 (0, 4)
	395 getfield (0, 4)
	396 org/apache/commons/math3/optimization/direct/CMAESOptimizer.cs:D (0, 4)
	398 dadd (0, 4)
	399 putfield (0, 4)
	400 org/apache/commons/math3/optimization/direct/CMAESOptimizer.damps:D (0, 4)
	402 aload_0 (0, 4)
	403 ldc2_w (0, 4)
	404 2.0 (0, 4)
	406 aload_0 (0, 4)
	407 getfield (0, 4)
	408 org/apache/commons/math3/optimization/direct/CMAESOptimizer.dimension:I (0, 4)
	410 i2d (0, 4)
	411 ldc2_w (0, 4)
	412 1.3 (0, 4)
	414 dadd (0, 4)
	415 aload_0 (0, 4)
	416 getfield (0, 4)
	417 org/apache/commons/math3/optimization/direct/CMAESOptimizer.dimension:I (0, 4)
	419 i2d (0, 4)
	420 ldc2_w (0, 4)
	421 1.3 (0, 4)
	423 dadd (0, 4)
	424 dmul (0, 4)
	425 aload_0 (0, 4)
	426 getfield (0, 4)
	427 org/apache/commons/math3/optimization/direct/CMAESOptimizer.mueff:D (0, 4)
	429 dadd (0, 4)
	430 ddiv (0, 4)
	431 putfield (0, 4)
	432 org/apache/commons/math3/optimization/direct/CMAESOptimizer.ccov1:D (0, 4)
	434 aload_0 (0, 4)
	435 dconst_1 (0, 4)
	436 aload_0 (0, 4)
	437 getfield (0, 4)
	438 org/apache/commons/math3/optimization/direct/CMAESOptimizer.ccov1:D (0, 4)
	440 dsub (0, 4)
	441 ldc2_w (0, 4)
	442 2.0 (0, 4)
	444 aload_0 (0, 4)
	445 getfield (0, 4)
	446 org/apache/commons/math3/optimization/direct/CMAESOptimizer.mueff:D (0, 4)
	448 ldc2_w (0, 4)
	449 2.0 (0, 4)
	451 dsub (0, 4)
	452 dconst_1 (0, 4)
	453 aload_0 (0, 4)
	454 getfield (0, 4)
	455 org/apache/commons/math3/optimization/direct/CMAESOptimizer.mueff:D (0, 4)
	457 ddiv (0, 4)
	458 dadd (0, 4)
	459 dmul (0, 4)
	460 aload_0 (0, 4)
	461 getfield (0, 4)
	462 org/apache/commons/math3/optimization/direct/CMAESOptimizer.dimension:I (0, 4)
	464 iconst_2 (0, 4)
	465 iadd (0, 4)
	466 aload_0 (0, 4)
	467 getfield (0, 4)
	468 org/apache/commons/math3/optimization/direct/CMAESOptimizer.dimension:I (0, 4)
	470 iconst_2 (0, 4)
	471 iadd (0, 4)
	472 imul (0, 4)
	473 i2d (0, 4)
	474 aload_0 (0, 4)
	475 getfield (0, 4)
	476 org/apache/commons/math3/optimization/direct/CMAESOptimizer.mueff:D (0, 4)
	478 dadd (0, 4)
	479 ddiv (0, 4)
	480 invokestatic (0, 4)
	481 org/apache/commons/math3/util/FastMath.min:(DD)D (0, 4)
	483 putfield (0, 4)
	484 org/apache/commons/math3/optimization/direct/CMAESOptimizer.ccovmu:D (0, 4)
	486 aload_0 (0, 4)
	487 dconst_1 (0, 4)
	488 aload_0 (0, 4)
	489 getfield (0, 4)
	490 org/apache/commons/math3/optimization/direct/CMAESOptimizer.ccov1:D (0, 4)
	492 aload_0 (0, 4)
	493 getfield (0, 4)
	494 org/apache/commons/math3/optimization/direct/CMAESOptimizer.dimension:I (0, 4)
	496 i2d (0, 4)
	497 ldc2_w (0, 4)
	498 1.5 (0, 4)
	500 dadd (0, 4)
	501 dmul (0, 4)
	502 ldc2_w (0, 4)
	503 3.0 (0, 4)
	505 ddiv (0, 4)
	506 invokestatic (0, 4)
	507 org/apache/commons/math3/util/FastMath.min:(DD)D (0, 4)
	509 putfield (0, 4)
	510 org/apache/commons/math3/optimization/direct/CMAESOptimizer.ccov1Sep:D (0, 4)
	512 aload_0 (0, 4)
	513 dconst_1 (0, 4)
	514 aload_0 (0, 4)
	515 getfield (0, 4)
	516 org/apache/commons/math3/optimization/direct/CMAESOptimizer.ccov1:D (0, 4)
	518 dsub (0, 4)
	519 aload_0 (0, 4)
	520 getfield (0, 4)
	521 org/apache/commons/math3/optimization/direct/CMAESOptimizer.ccovmu:D (0, 4)
	523 aload_0 (0, 4)
	524 getfield (0, 4)
	525 org/apache/commons/math3/optimization/direct/CMAESOptimizer.dimension:I (0, 4)
	527 i2d (0, 4)
	528 ldc2_w (0, 4)
	529 1.5 (0, 4)
	531 dadd (0, 4)
	532 dmul (0, 4)
	533 ldc2_w (0, 4)
	534 3.0 (0, 4)
	536 ddiv (0, 4)
	537 invokestatic (0, 4)
	538 org/apache/commons/math3/util/FastMath.min:(DD)D (0, 4)
	540 putfield (0, 4)
	541 org/apache/commons/math3/optimization/direct/CMAESOptimizer.ccovmuSep:D (0, 4)
	543 aload_0 (0, 4)
	544 aload_0 (0, 4)
	545 getfield (0, 4)
	546 org/apache/commons/math3/optimization/direct/CMAESOptimizer.dimension:I (0, 4)
	548 i2d (0, 4)
	549 invokestatic (0, 4)
	550 org/apache/commons/math3/util/FastMath.sqrt:(D)D (0, 4)
	552 dconst_1 (0, 4)
	553 dconst_1 (0, 4)
	554 ldc2_w (0, 4)
	555 4.0 (0, 4)
	557 aload_0 (0, 4)
	558 getfield (0, 4)
	559 org/apache/commons/math3/optimization/direct/CMAESOptimizer.dimension:I (0, 4)
	561 i2d (0, 4)
	562 dmul (0, 4)
	563 ddiv (0, 4)
	564 dsub (0, 4)
	565 dconst_1 (0, 4)
	566 ldc2_w (0, 4)
	567 21.0 (0, 4)
	569 aload_0 (0, 4)
	570 getfield (0, 4)
	571 org/apache/commons/math3/optimization/direct/CMAESOptimizer.dimension:I (0, 4)
	573 i2d (0, 4)
	574 dmul (0, 4)
	575 aload_0 (0, 4)
	576 getfield (0, 4)
	577 org/apache/commons/math3/optimization/direct/CMAESOptimizer.dimension:I (0, 4)
	579 i2d (0, 4)
	580 dmul (0, 4)
	581 ddiv (0, 4)
	582 dadd (0, 4)
	583 dmul (0, 4)
	584 putfield (0, 4)
	585 org/apache/commons/math3/optimization/direct/CMAESOptimizer.chiN:D (0, 4)
	587 aload_0 (0, 4)
	588 aload_1 (0, 4)
	589 invokestatic (0, 4)
	590 org/apache/commons/math3/linear/MatrixUtils.createColumnRealMatrix:([D)Lorg/apache/commons/math3/linear/RealMatrix; (0, 4)
	592 putfield (0, 4)
	593 org/apache/commons/math3/optimization/direct/CMAESOptimizer.xmean:Lorg/apache/commons/math3/linear/RealMatrix; (0, 4)
	595 aload_0 (0, 4)
	596 aload_3 (0, 4)
	597 dconst_1 (0, 4)
	598 aload_0 (0, 4)
	599 getfield (0, 4)
	600 org/apache/commons/math3/optimization/direct/CMAESOptimizer.sigma:D (0, 4)
	602 ddiv (0, 4)
	603 invokeinterface (0, 4)
	604 org/apache/commons/math3/linear/RealMatrix.add:(Lorg/apache/commons/math3/linear/RealMatrix;)Lorg/apache/commons/math3/linear/RealMatrix; (0, 4)
	606 0 (0, 4)
	608 putfield (0, 4)
	609 org/apache/commons/math3/optimization/direct/CMAESOptimizer.diagD:Lorg/apache/commons/math3/linear/RealMatrix; (0, 4)
	611 aload_0 (0, 4)
	612 aload_0 (0, 4)
	613 getfield (0, 4)
	614 org/apache/commons/math3/optimization/direct/CMAESOptimizer.diagD:Lorg/apache/commons/math3/linear/RealMatrix; (0, 4)
	616 invokestatic (0, 4)
	617 org/apache/commons/math3/optimization/direct/CMAESOptimizer.square:(Lorg/apache/commons/math3/linear/RealMatrix;)Lorg/apache/commons/math3/linear/RealMatrix; (0, 4)
	619 putfield (0, 4)
	620 org/apache/commons/math3/optimization/direct/CMAESOptimizer.diagC:Lorg/apache/commons/math3/linear/RealMatrix; (0, 4)
	622 aload_0 (0, 4)
	623 aload_0 (0, 4)
	624 getfield (0, 4)
	625 org/apache/commons/math3/optimization/direct/CMAESOptimizer.dimension:I (0, 4)
	627 iconst_1 (0, 4)
	628 invokestatic (0, 4)
	629 org/apache/commons/math3/optimization/direct/CMAESOptimizer.zeros:(II)Lorg/apache/commons/math3/linear/RealMatrix; (0, 4)
	631 putfield (0, 4)
	632 org/apache/commons/math3/optimization/direct/CMAESOptimizer.pc:Lorg/apache/commons/math3/linear/RealMatrix; (0, 4)
	634 aload_0 (0, 4)
	635 aload_0 (0, 4)
	636 getfield (0, 4)
	637 org/apache/commons/math3/optimization/direct/CMAESOptimizer.dimension:I (0, 4)
	639 iconst_1 (0, 4)
	640 invokestatic (0, 4)
	641 org/apache/commons/math3/optimization/direct/CMAESOptimizer.zeros:(II)Lorg/apache/commons/math3/linear/RealMatrix; (0, 4)
	643 putfield (0, 4)
	644 org/apache/commons/math3/optimization/direct/CMAESOptimizer.ps:Lorg/apache/commons/math3/linear/RealMatrix; (0, 4)
	646 aload_0 (0, 4)
	647 aload_0 (0, 4)
	648 getfield (0, 4)
	649 org/apache/commons/math3/optimization/direct/CMAESOptimizer.ps:Lorg/apache/commons/math3/linear/RealMatrix; (0, 4)
	651 invokeinterface (0, 4)
	652 org/apache/commons/math3/linear/RealMatrix.eye:(II)Lorg/apache/commons/math3/linear/RealMatrix; (0, 4)
	654 0 (0, 4)
	656 putfield (0, 4)
	657 org/apache/commons/math3/optimization/direct/CMAESOptimizer.normps:D (0, 4)
	659 aload_0 (0, 4)
	660 aload_0 (0, 4)
	661 getfield (0, 4)
	662 org/apache/commons/math3/optimization/direct/CMAESOptimizer.dimension:I (0, 4)
	664 aload_0 (0, 4)
	665 getfield (0, 4)
	666 org/apache/commons/math3/optimization/direct/CMAESOptimizer.dimension:I (0, 4)
	668 invokestatic (0, 4)
	669 org/apache/commons/math3/optimization/direct/CMAESOptimizer.eye:(II)Lorg/apache/commons/math3/linear/RealMatrix; (0, 4)
	671 putfield (0, 4)
	672 org/apache/commons/math3/optimization/direct/CMAESOptimizer.B:Lorg/apache/commons/math3/linear/RealMatrix; (0, 4)
	674 aload_0 (0, 4)
	675 aload_0 (0, 4)
	676 getfield (0, 4)
	677 org/apache/commons/math3/optimization/direct/CMAESOptimizer.dimension:I (0, 4)
	679 iconst_1 (0, 4)
	680 invokestatic (0, 4)
	681 org/apache/commons/math3/optimization/direct/CMAESOptimizer.ones:(II)Lorg/apache/commons/math3/linear/RealMatrix; (0, 4)
	683 putfield (0, 4)
	684 org/apache/commons/math3/optimization/direct/CMAESOptimizer.D:Lorg/apache/commons/math3/linear/RealMatrix; (0, 4)
	686 aload_0 (0, 4)
	687 aload_0 (0, 4)
	688 getfield (0, 4)
	689 org/apache/commons/math3/optimization/direct/CMAESOptimizer.B:Lorg/apache/commons/math3/linear/RealMatrix; (0, 4)
	691 aload_0 (0, 4)
	692 getfield (0, 4)
	693 org/apache/commons/math3/optimization/direct/CMAESOptimizer.diagD:Lorg/apache/commons/math3/linear/RealMatrix; (0, 4)
	695 invokeinterface (0, 4)
	696 org/apache/commons/math3/linear/RealMatrix.org/apache/commons/math3/optimization/direct/CMAESOptimizer$Sigma (0, 4)
	698 0 (0, 4)
	700 aload_0 (0, 4)
	701 getfield (0, 4)
	702 org/apache/commons/math3/optimization/direct/CMAESOptimizer.dimension:I (0, 4)
	704 iconst_1 (0, 4)
	705 invokestatic (0, 4)
	706 org/apache/commons/math3/optimization/direct/CMAESOptimizer.repmat:(Lorg/apache/commons/math3/linear/RealMatrix;II)Lorg/apache/commons/math3/linear/RealMatrix; (0, 4)
	708 invokestatic (0, 4)
	709 org/apache/commons/math3/optimization/direct/CMAESOptimizer.times:(Lorg/apache/commons/math3/linear/RealMatrix;Lorg/apache/commons/math3/linear/RealMatrix;)Lorg/apache/commons/math3/linear/RealMatrix; (0, 4)
	711 putfield (0, 4)
	712 org/apache/commons/math3/optimization/direct/CMAESOptimizer.BD:Lorg/apache/commons/math3/linear/RealMatrix; (0, 4)
	714 aload_0 (0, 4)
	715 aload_0 (0, 4)
	716 getfield (0, 4)
	717 org/apache/commons/math3/optimization/direct/CMAESOptimizer.B:Lorg/apache/commons/math3/linear/RealMatrix; (0, 4)
	719 aload_0 (0, 4)
	720 getfield (0, 4)
	721 org/apache/commons/math3/optimization/direct/CMAESOptimizer.D:Lorg/apache/commons/math3/linear/RealMatrix; (0, 4)
	723 invokestatic (0, 4)
	724 org/apache/commons/math3/optimization/direct/CMAESOptimizer.square:(Lorg/apache/commons/math3/linear/RealMatrix;)Lorg/apache/commons/math3/linear/RealMatrix; (0, 4)
	726 invokestatic (0, 4)
	727 org/apache/commons/math3/optimization/direct/CMAESOptimizer.diag:(Lorg/apache/commons/math3/linear/RealMatrix;)Lorg/apache/commons/math3/linear/RealMatrix; (0, 4)
	729 aload_0 (0, 4)
	730 getfield (0, 4)
	731 org/apache/commons/math3/optimization/direct/CMAESOptimizer.B:Lorg/apache/commons/math3/linear/RealMatrix; (0, 4)
	733 invokeinterface (0, 4)
	734 org/apache/commons/math3/linear/RealMatrix.org/apache/commons/math3/optimization/direct/CMAESOptimizer$Sigma (0, 4)
	736 0 (0, 4)
	738 invokeinterface (0, 4)
	739 org/apache/commons/math3/linear/RealMatrix.sigma:D (0, 4)
	741 0 (0, 4)
	743 invokeinterface (0, 4)
	744 org/apache/commons/math3/linear/RealMatrix.sigma:D (0, 4)
	746 0 (0, 4)
	748 putfield (0, 4)
	749 org/apache/commons/math3/optimization/direct/CMAESOptimizer.C:Lorg/apache/commons/math3/linear/RealMatrix; (0, 4)
	751 aload_0 (0, 4)
	752 bipush (0, 4)
	753 10 (0, 4)
	754 bipush (0, 4)
	755 30 (0, 4)
	756 aload_0 (0, 4)
	757 getfield (0, 4)
	758 org/apache/commons/math3/optimization/direct/CMAESOptimizer.dimension:I (0, 4)
	760 imul (0, 4)
	761 i2d (0, 4)
	762 aload_0 (0, 4)
	763 getfield (0, 4)
	764 org/apache/commons/math3/optimization/direct/CMAESOptimizer.lambda:I (0, 4)
	766 i2d (0, 4)
	767 ddiv (0, 4)
	768 d2i (0, 4)
	769 iadd (0, 4)
	770 putfield (0, 4)
	771 org/apache/commons/math3/optimization/direct/CMAESOptimizer.historySize:I (0, 4)
	773 aload_0 (0, 4)
	774 aload_0 (0, 4)
	775 getfield (0, 4)
	776 org/apache/commons/math3/optimization/direct/CMAESOptimizer.historySize:I (0, 4)
	778 newarray (0, 4)
	779 7 (0, 4)
	780 putfield (0, 4)
	781 org/apache/commons/math3/optimization/direct/CMAESOptimizer.fitnessHistory:[D (0, 4)
	783 iconst_0 (1, 4)
	784 istore (1, 4)
	785 #8 (1, 4)
	786 iload (1, 4)
	787 #8 (1, 4)
	788 aload_0 (1, 4)
	789 getfield (1, 4)
	790 org/apache/commons/math3/optimization/direct/CMAESOptimizer.historySize:I (1, 4)
	792 if_icmpge (1, 4)
	793 19 (1, 4)
	795 aload_0 (1, 4)
	796 getfield (1, 4)
	797 org/apache/commons/math3/optimization/direct/CMAESOptimizer.fitnessHistory:[D (1, 4)
	799 iload (1, 4)
	800 #8 (1, 4)
	801 ldc2_w (1, 4)
	802 1.7976931348623157e+308 (1, 4)
	804 dastore (1, 4)
	805 iinc (1, 4)
	806 #8 (1, 4)
	807 -89 (1, 4)
	808 goto (1, 4)
	809 -22 (1, 4)
	811 return (0, 4)

Method: updateEvolutionPaths
	0 aload_0 (0, 0)
	1 aload_0 (0, 0)
	2 getfield (0, 0)
	3 org/apache/commons/math3/optimization/direct/CMAESOptimizer.ps:Lorg/apache/commons/math3/linear/RealMatrix; (0, 0)
	5 dconst_1 (0, 0)
	6 aload_0 (0, 0)
	7 getfield (0, 0)
	8 org/apache/commons/math3/optimization/direct/CMAESOptimizer.cs:D (0, 0)
	10 dsub (0, 0)
	11 invokeinterface (0, 0)
	12 org/apache/commons/math3/linear/RealMatrix.add:(Lorg/apache/commons/math3/linear/RealMatrix;)Lorg/apache/commons/math3/linear/RealMatrix; (0, 0)
	14 0 (0, 0)
	16 aload_0 (0, 0)
	17 getfield (0, 0)
	18 org/apache/commons/math3/optimization/direct/CMAESOptimizer.B:Lorg/apache/commons/math3/linear/RealMatrix; (0, 0)
	20 aload_1 (0, 0)
	21 invokeinterface (0, 0)
	22 org/apache/commons/math3/linear/RealMatrix.sigma:D (0, 0)
	24 0 (0, 0)
	26 aload_0 (0, 0)
	27 getfield (0, 0)
	28 org/apache/commons/math3/optimization/direct/CMAESOptimizer.cs:D (0, 0)
	30 ldc2_w (0, 0)
	31 2.0 (0, 0)
	33 aload_0 (0, 0)
	34 getfield (0, 0)
	35 org/apache/commons/math3/optimization/direct/CMAESOptimizer.cs:D (0, 0)
	37 dsub (0, 0)
	38 dmul (0, 0)
	39 aload_0 (0, 0)
	40 getfield (0, 0)
	41 org/apache/commons/math3/optimization/direct/CMAESOptimizer.mueff:D (0, 0)
	43 dmul (0, 0)
	44 invokestatic (0, 0)
	45 org/apache/commons/math3/util/FastMath.sqrt:(D)D (0, 0)
	47 invokeinterface (0, 0)
	48 org/apache/commons/math3/linear/RealMatrix.add:(Lorg/apache/commons/math3/linear/RealMatrix;)Lorg/apache/commons/math3/linear/RealMatrix; (0, 0)
	50 0 (0, 0)
	52 invokeinterface (0, 0)
	53 org/apache/commons/math3/linear/RealMatrix.diagD:Lorg/apache/commons/math3/linear/RealMatrix; (0, 0)
	55 0 (0, 0)
	57 putfield (0, 0)
	58 org/apache/commons/math3/optimization/direct/CMAESOptimizer.ps:Lorg/apache/commons/math3/linear/RealMatrix; (0, 0)
	60 aload_0 (0, 0)
	61 aload_0 (0, 0)
	62 getfield (0, 0)
	63 org/apache/commons/math3/optimization/direct/CMAESOptimizer.ps:Lorg/apache/commons/math3/linear/RealMatrix; (0, 0)
	65 invokeinterface (0, 0)
	66 org/apache/commons/math3/linear/RealMatrix.eye:(II)Lorg/apache/commons/math3/linear/RealMatrix; (0, 0)
	68 0 (0, 0)
	70 putfield (0, 0)
	71 org/apache/commons/math3/optimization/direct/CMAESOptimizer.normps:D (0, 0)
	73 aload_0 (0, 0)
	74 getfield (0, 0)
	75 org/apache/commons/math3/optimization/direct/CMAESOptimizer.normps:D (0, 0)
	77 dconst_1 (0, 0)
	78 dconst_1 (0, 0)
	79 aload_0 (0, 0)
	80 getfield (0, 0)
	81 org/apache/commons/math3/optimization/direct/CMAESOptimizer.cs:D (0, 0)
	83 dsub (0, 0)
	84 iconst_2 (0, 0)
	85 aload_0 (0, 0)
	86 getfield (0, 0)
	87 org/apache/commons/math3/optimization/direct/CMAESOptimizer.iterations:I (0, 0)
	89 imul (0, 0)
	90 invokestatic (0, 0)
	91 org/apache/commons/math3/util/FastMath.pow:(DI)D (0, 0)
	93 dsub (0, 0)
	94 invokestatic (0, 0)
	95 org/apache/commons/math3/util/FastMath.sqrt:(D)D (0, 0)
	97 ddiv (0, 0)
	98 aload_0 (0, 0)
	99 getfield (0, 0)
	100 org/apache/commons/math3/optimization/direct/CMAESOptimizer.chiN:D (0, 0)
	102 ddiv (0, 0)
	103 ldc2_w (0, 0)
	104 1.4 (0, 0)
	106 ldc2_w (0, 0)
	107 2.0 (0, 0)
	109 aload_0 (0, 0)
	110 getfield (0, 0)
	111 org/apache/commons/math3/optimization/direct/CMAESOptimizer.dimension:I (0, 0)
	113 i2d (0, 0)
	114 dconst_1 (0, 0)
	115 dadd (0, 0)
	116 ddiv (0, 0)
	117 dadd (0, 0)
	118 dcmpg (0, 0)
	119 ifge (0, 0)
	120 7 (0, 0)
	122 iconst_1 (0, 0)
	123 goto (0, 0)
	124 4 (0, 0)
	126 iconst_0 (0, 0)
	127 istore_3 (0, 0)
	128 aload_0 (0, 0)
	129 aload_0 (0, 0)
	130 getfield (0, 0)
	131 org/apache/commons/math3/optimization/direct/CMAESOptimizer.pc:Lorg/apache/commons/math3/linear/RealMatrix; (0, 0)
	133 dconst_1 (0, 0)
	134 aload_0 (0, 0)
	135 getfield (0, 0)
	136 org/apache/commons/math3/optimization/direct/CMAESOptimizer.cc:D (0, 0)
	138 dsub (0, 0)
	139 invokeinterface (0, 0)
	140 org/apache/commons/math3/linear/RealMatrix.add:(Lorg/apache/commons/math3/linear/RealMatrix;)Lorg/apache/commons/math3/linear/RealMatrix; (0, 0)
	142 0 (0, 0)
	144 putfield (0, 0)
	145 org/apache/commons/math3/optimization/direct/CMAESOptimizer.pc:Lorg/apache/commons/math3/linear/RealMatrix; (0, 0)
	147 iload_3 (1, 1)
	148 ifeq (1, 1)
	149 57 (1, 1)
	151 aload_0 (1, 1)
	152 aload_0 (1, 1)
	153 getfield (1, 1)
	154 org/apache/commons/math3/optimization/direct/CMAESOptimizer.pc:Lorg/apache/commons/math3/linear/RealMatrix; (1, 1)
	156 aload_0 (1, 1)
	157 getfield (1, 1)
	158 org/apache/commons/math3/optimization/direct/CMAESOptimizer.xmean:Lorg/apache/commons/math3/linear/RealMatrix; (1, 1)
	160 aload_2 (1, 1)
	161 invokeinterface (1, 1)
	162 org/apache/commons/math3/linear/RealMatrix.pow:(DD)D (1, 1)
	164 0 (1, 1)
	166 aload_0 (1, 1)
	167 getfield (1, 1)
	168 org/apache/commons/math3/optimization/direct/CMAESOptimizer.cc:D (1, 1)
	170 ldc2_w (1, 1)
	171 2.0 (1, 1)
	173 aload_0 (1, 1)
	174 getfield (1, 1)
	175 org/apache/commons/math3/optimization/direct/CMAESOptimizer.cc:D (1, 1)
	177 dsub (1, 1)
	178 dmul (1, 1)
	179 aload_0 (1, 1)
	180 getfield (1, 1)
	181 org/apache/commons/math3/optimization/direct/CMAESOptimizer.mueff:D (1, 1)
	183 dmul (1, 1)
	184 invokestatic (1, 1)
	185 org/apache/commons/math3/util/FastMath.sqrt:(D)D (1, 1)
	187 aload_0 (1, 1)
	188 getfield (1, 1)
	189 org/apache/commons/math3/optimization/direct/CMAESOptimizer.sigma:D (1, 1)
	191 ddiv (1, 1)
	192 invokeinterface (1, 1)
	193 org/apache/commons/math3/linear/RealMatrix.add:(Lorg/apache/commons/math3/linear/RealMatrix;)Lorg/apache/commons/math3/linear/RealMatrix; (1, 1)
	195 0 (1, 1)
	197 invokeinterface (1, 1)
	198 org/apache/commons/math3/linear/RealMatrix.diagD:Lorg/apache/commons/math3/linear/RealMatrix; (1, 1)
	200 0 (1, 1)
	202 putfield (1, 1)
	203 org/apache/commons/math3/optimization/direct/CMAESOptimizer.pc:Lorg/apache/commons/math3/linear/RealMatrix; (1, 1)
	205 iload_3 (0, 0)
	206 ireturn (0, 0)

Method: updateCovarianceDiagonalOnly
	0 iload_1 (0, 0)
	1 ifeq (0, 0)
	2 7 (0, 0)
	4 dconst_0 (0, 0)
	5 goto (0, 0)
	6 21 (0, 0)
	8 aload_0 (0, 0)
	9 getfield (0, 0)
	10 org/apache/commons/math3/optimization/direct/CMAESOptimizer.ccov1Sep:D (0, 0)
	12 aload_0 (0, 0)
	13 getfield (0, 0)
	14 org/apache/commons/math3/optimization/direct/CMAESOptimizer.cc:D (0, 0)
	16 dmul (0, 0)
	17 ldc2_w (0, 0)
	18 2.0 (0, 0)
	20 aload_0 (0, 0)
	21 getfield (0, 0)
	22 org/apache/commons/math3/optimization/direct/CMAESOptimizer.cc:D (0, 0)
	24 dsub (0, 0)
	25 dmul (0, 0)
	26 dstore_3 (0, 0)
	27 dload_3 (0, 0)
	28 dconst_1 (0, 0)
	29 aload_0 (0, 0)
	30 getfield (0, 0)
	31 org/apache/commons/math3/optimization/direct/CMAESOptimizer.ccov1Sep:D (0, 0)
	33 dsub (0, 0)
	34 aload_0 (0, 0)
	35 getfield (0, 0)
	36 org/apache/commons/math3/optimization/direct/CMAESOptimizer.ccovmuSep:D (0, 0)
	38 dsub (0, 0)
	39 dadd (0, 0)
	40 dstore_3 (0, 0)
	41 aload_0 (0, 0)
	42 aload_0 (0, 0)
	43 getfield (0, 0)
	44 org/apache/commons/math3/optimization/direct/CMAESOptimizer.diagC:Lorg/apache/commons/math3/linear/RealMatrix; (0, 0)
	46 dload_3 (0, 0)
	47 invokeinterface (0, 0)
	48 org/apache/commons/math3/linear/RealMatrix.add:(Lorg/apache/commons/math3/linear/RealMatrix;)Lorg/apache/commons/math3/linear/RealMatrix; (0, 0)
	50 0 (0, 0)
	52 aload_0 (0, 0)
	53 getfield (0, 0)
	54 org/apache/commons/math3/optimization/direct/CMAESOptimizer.pc:Lorg/apache/commons/math3/linear/RealMatrix; (0, 0)
	56 invokestatic (0, 0)
	57 org/apache/commons/math3/optimization/direct/CMAESOptimizer.square:(Lorg/apache/commons/math3/linear/RealMatrix;)Lorg/apache/commons/math3/linear/RealMatrix; (0, 0)
	59 aload_0 (0, 0)
	60 getfield (0, 0)
	61 org/apache/commons/math3/optimization/direct/CMAESOptimizer.ccov1Sep:D (0, 0)
	63 invokeinterface (0, 0)
	64 org/apache/commons/math3/linear/RealMatrix.add:(Lorg/apache/commons/math3/linear/RealMatrix;)Lorg/apache/commons/math3/linear/RealMatrix; (0, 0)
	66 0 (0, 0)
	68 invokeinterface (0, 0)
	69 org/apache/commons/math3/linear/RealMatrix.diagD:Lorg/apache/commons/math3/linear/RealMatrix; (0, 0)
	71 0 (0, 0)
	73 aload_0 (0, 0)
	74 getfield (0, 0)
	75 org/apache/commons/math3/optimization/direct/CMAESOptimizer.diagC:Lorg/apache/commons/math3/linear/RealMatrix; (0, 0)
	77 aload_2 (0, 0)
	78 invokestatic (0, 0)
	79 org/apache/commons/math3/optimization/direct/CMAESOptimizer.square:(Lorg/apache/commons/math3/linear/RealMatrix;)Lorg/apache/commons/math3/linear/RealMatrix; (0, 0)
	81 aload_0 (0, 0)
	82 getfield (0, 0)
	83 org/apache/commons/math3/optimization/direct/CMAESOptimizer.weights:Lorg/apache/commons/math3/linear/RealMatrix; (0, 0)
	85 invokeinterface (0, 0)
	86 org/apache/commons/math3/linear/RealMatrix.sigma:D (0, 0)
	88 0 (0, 0)
	90 invokestatic (0, 0)
	91 org/apache/commons/math3/optimization/direct/CMAESOptimizer.times:(Lorg/apache/commons/math3/linear/RealMatrix;Lorg/apache/commons/math3/linear/RealMatrix;)Lorg/apache/commons/math3/linear/RealMatrix; (0, 0)
	93 aload_0 (0, 0)
	94 getfield (0, 0)
	95 org/apache/commons/math3/optimization/direct/CMAESOptimizer.ccovmuSep:D (0, 0)
	97 invokeinterface (0, 0)
	98 org/apache/commons/math3/linear/RealMatrix.add:(Lorg/apache/commons/math3/linear/RealMatrix;)Lorg/apache/commons/math3/linear/RealMatrix; (0, 0)
	100 0 (0, 0)
	102 invokeinterface (0, 0)
	103 org/apache/commons/math3/linear/RealMatrix.diagD:Lorg/apache/commons/math3/linear/RealMatrix; (0, 0)
	105 0 (0, 0)
	107 putfield (0, 0)
	108 org/apache/commons/math3/optimization/direct/CMAESOptimizer.diagC:Lorg/apache/commons/math3/linear/RealMatrix; (0, 0)
	110 aload_0 (0, 0)
	111 aload_0 (0, 0)
	112 getfield (0, 0)
	113 org/apache/commons/math3/optimization/direct/CMAESOptimizer.diagC:Lorg/apache/commons/math3/linear/RealMatrix; (0, 0)
	115 invokestatic (0, 0)
	116 org/apache/commons/math3/optimization/direct/CMAESOptimizer.sqrt:(Lorg/apache/commons/math3/linear/RealMatrix;)Lorg/apache/commons/math3/linear/RealMatrix; (0, 0)
	118 putfield (0, 0)
	119 org/apache/commons/math3/optimization/direct/CMAESOptimizer.diagD:Lorg/apache/commons/math3/linear/RealMatrix; (0, 0)
	121 aload_0 (0, 1)
	122 getfield (0, 1)
	123 org/apache/commons/math3/optimization/direct/CMAESOptimizer.diagonalOnly:I (0, 1)
	125 iconst_1 (0, 1)
	126 if_icmple (0, 1)
	127 56 (0, 1)
	129 aload_0 (0, 1)
	130 getfield (0, 1)
	131 org/apache/commons/math3/optimization/direct/CMAESOptimizer.iterations:I (0, 1)
	133 aload_0 (0, 1)
	134 getfield (0, 1)
	135 org/apache/commons/math3/optimization/direct/CMAESOptimizer.diagonalOnly:I (0, 1)
	137 if_icmple (0, 1)
	138 45 (0, 1)
	140 aload_0 (0, 1)
	141 iconst_0 (0, 1)
	142 putfield (0, 1)
	143 org/apache/commons/math3/optimization/direct/CMAESOptimizer.diagonalOnly:I (0, 1)
	145 aload_0 (0, 1)
	146 aload_0 (0, 1)
	147 getfield (0, 1)
	148 org/apache/commons/math3/optimization/direct/CMAESOptimizer.dimension:I (0, 1)
	150 aload_0 (0, 1)
	151 getfield (0, 1)
	152 org/apache/commons/math3/optimization/direct/CMAESOptimizer.dimension:I (0, 1)
	154 invokestatic (0, 1)
	155 org/apache/commons/math3/optimization/direct/CMAESOptimizer.eye:(II)Lorg/apache/commons/math3/linear/RealMatrix; (0, 1)
	157 putfield (0, 1)
	158 org/apache/commons/math3/optimization/direct/CMAESOptimizer.B:Lorg/apache/commons/math3/linear/RealMatrix; (0, 1)
	160 aload_0 (0, 1)
	161 aload_0 (0, 1)
	162 getfield (0, 1)
	163 org/apache/commons/math3/optimization/direct/CMAESOptimizer.diagD:Lorg/apache/commons/math3/linear/RealMatrix; (0, 1)
	165 invokestatic (0, 1)
	166 org/apache/commons/math3/optimization/direct/CMAESOptimizer.diag:(Lorg/apache/commons/math3/linear/RealMatrix;)Lorg/apache/commons/math3/linear/RealMatrix; (0, 1)
	168 putfield (0, 1)
	169 org/apache/commons/math3/optimization/direct/CMAESOptimizer.BD:Lorg/apache/commons/math3/linear/RealMatrix; (0, 1)
	171 aload_0 (0, 1)
	172 aload_0 (0, 1)
	173 getfield (0, 1)
	174 org/apache/commons/math3/optimization/direct/CMAESOptimizer.diagC:Lorg/apache/commons/math3/linear/RealMatrix; (0, 1)
	176 invokestatic (0, 1)
	177 org/apache/commons/math3/optimization/direct/CMAESOptimizer.diag:(Lorg/apache/commons/math3/linear/RealMatrix;)Lorg/apache/commons/math3/linear/RealMatrix; (0, 1)
	179 putfield (0, 1)
	180 org/apache/commons/math3/optimization/direct/CMAESOptimizer.C:Lorg/apache/commons/math3/linear/RealMatrix; (0, 1)
	182 return (0, 1)

Method: updateCovariance
	0 dconst_0 (0, 0)
	1 dstore (0, 0)
	2 #6 (0, 0)
	3 aload_0 (1, 1)
	4 getfield (1, 1)
	5 org/apache/commons/math3/optimization/direct/CMAESOptimizer.ccov1:D (1, 1)
	7 aload_0 (1, 1)
	8 getfield (1, 1)
	9 org/apache/commons/math3/optimization/direct/CMAESOptimizer.ccovmu:D (1, 1)
	11 dadd (1, 1)
	12 dconst_0 (1, 1)
	13 dcmpl (1, 1)
	14 ifle (1, 1)
	15 523 (1, 1)
	17 aload_2 (1, 1)
	18 aload (1, 1)
	19 #5 (1, 1)
	20 iconst_1 (1, 1)
	21 aload_0 (1, 1)
	22 getfield (1, 1)
	23 org/apache/commons/math3/optimization/direct/CMAESOptimizer.mu:I (1, 1)
	25 invokestatic (1, 1)
	26 org/apache/commons/math3/optimization/direct/CMAESOptimizer.repmat:(Lorg/apache/commons/math3/linear/RealMatrix;II)Lorg/apache/commons/math3/linear/RealMatrix; (1, 1)
	28 invokeinterface (1, 1)
	29 org/apache/commons/math3/linear/RealMatrix.pow:(DD)D (1, 1)
	31 0 (1, 1)
	33 dconst_1 (1, 1)
	34 aload_0 (1, 1)
	35 getfield (1, 1)
	36 org/apache/commons/math3/optimization/direct/CMAESOptimizer.sigma:D (1, 1)
	38 ddiv (1, 1)
	39 invokeinterface (1, 1)
	40 org/apache/commons/math3/linear/RealMatrix.add:(Lorg/apache/commons/math3/linear/RealMatrix;)Lorg/apache/commons/math3/linear/RealMatrix; (1, 1)
	42 0 (1, 1)
	44 astore (1, 1)
	45 #8 (1, 1)
	46 aload_0 (1, 1)
	47 getfield (1, 1)
	48 org/apache/commons/math3/optimization/direct/CMAESOptimizer.pc:Lorg/apache/commons/math3/linear/RealMatrix; (1, 1)
	50 aload_0 (1, 1)
	51 getfield (1, 1)
	52 org/apache/commons/math3/optimization/direct/CMAESOptimizer.pc:Lorg/apache/commons/math3/linear/RealMatrix; (1, 1)
	54 invokeinterface (1, 1)
	55 org/apache/commons/math3/linear/RealMatrix.org/apache/commons/math3/optimization/direct/CMAESOptimizer$Sigma (1, 1)
	57 0 (1, 1)
	59 invokeinterface (1, 1)
	60 org/apache/commons/math3/linear/RealMatrix.sigma:D (1, 1)
	62 0 (1, 1)
	64 aload_0 (1, 1)
	65 getfield (1, 1)
	66 org/apache/commons/math3/optimization/direct/CMAESOptimizer.ccov1:D (1, 1)
	68 invokeinterface (1, 1)
	69 org/apache/commons/math3/linear/RealMatrix.add:(Lorg/apache/commons/math3/linear/RealMatrix;)Lorg/apache/commons/math3/linear/RealMatrix; (1, 1)
	71 0 (1, 1)
	73 astore (1, 1)
	74 #9 (1, 1)
	75 iload_1 (1, 1)
	76 ifeq (1, 1)
	77 7 (1, 1)
	79 dconst_0 (1, 1)
	80 goto (1, 1)
	81 21 (1, 1)
	83 aload_0 (1, 1)
	84 getfield (1, 1)
	85 org/apache/commons/math3/optimization/direct/CMAESOptimizer.ccov1:D (1, 1)
	87 aload_0 (1, 1)
	88 getfield (1, 1)
	89 org/apache/commons/math3/optimization/direct/CMAESOptimizer.cc:D (1, 1)
	91 dmul (1, 1)
	92 ldc2_w (1, 1)
	93 2.0 (1, 1)
	95 aload_0 (1, 1)
	96 getfield (1, 1)
	97 org/apache/commons/math3/optimization/direct/CMAESOptimizer.cc:D (1, 1)
	99 dsub (1, 1)
	100 dmul (1, 1)
	101 dstore (1, 1)
	102 #10 (1, 1)
	103 dload (1, 1)
	104 #10 (1, 1)
	105 dconst_1 (1, 1)
	106 aload_0 (1, 1)
	107 getfield (1, 1)
	108 org/apache/commons/math3/optimization/direct/CMAESOptimizer.ccov1:D (1, 1)
	110 dsub (1, 1)
	111 aload_0 (1, 1)
	112 getfield (1, 1)
	113 org/apache/commons/math3/optimization/direct/CMAESOptimizer.ccovmu:D (1, 1)
	115 dsub (1, 1)
	116 dadd (1, 1)
	117 dstore (1, 1)
	118 #10 (1, 1)
	119 aload_0 (2, 1)
	120 getfield (2, 1)
	121 org/apache/commons/math3/optimization/direct/CMAESOptimizer.isActiveCMA:Z (2, 1)
	123 ifeq (2, 1)
	124 349 (2, 1)
	126 dconst_1 (2, 1)
	127 aload_0 (2, 1)
	128 getfield (2, 1)
	129 org/apache/commons/math3/optimization/direct/CMAESOptimizer.ccovmu:D (2, 1)
	131 dsub (2, 1)
	132 ldc2_w (2, 1)
	133 0.25 (2, 1)
	135 dmul (2, 1)
	136 aload_0 (2, 1)
	137 getfield (2, 1)
	138 org/apache/commons/math3/optimization/direct/CMAESOptimizer.mueff:D (2, 1)
	140 dmul (2, 1)
	141 aload_0 (2, 1)
	142 getfield (2, 1)
	143 org/apache/commons/math3/optimization/direct/CMAESOptimizer.dimension:I (2, 1)
	145 iconst_2 (2, 1)
	146 iadd (2, 1)
	147 i2d (2, 1)
	148 ldc2_w (2, 1)
	149 1.5 (2, 1)
	151 invokestatic (2, 1)
	152 org/apache/commons/math3/util/FastMath.pow:(DD)D (2, 1)
	154 ldc2_w (2, 1)
	155 2.0 (2, 1)
	157 aload_0 (2, 1)
	158 getfield (2, 1)
	159 org/apache/commons/math3/optimization/direct/CMAESOptimizer.mueff:D (2, 1)
	161 dmul (2, 1)
	162 dadd (2, 1)
	163 ddiv (2, 1)
	164 dstore (2, 1)
	165 #6 (2, 1)
	166 ldc2_w (2, 1)
	167 0.66 (2, 1)
	169 dstore (2, 1)
	170 #12 (2, 1)
	171 ldc2_w (2, 4)
	172 0.5 (2, 4)
	174 dstore (2, 4)
	175 #14 (2, 4)
	176 aload (2, 4)
	177 #4 (2, 4)
	178 invokestatic (2, 4)
	179 org/apache/commons/math3/optimization/direct/CMAESOptimizer.reverse:([I)[I (2, 4)
	181 astore (2, 4)
	182 #16 (2, 4)
	183 aload_3 (2, 4)
	184 aload (2, 4)
	185 #16 (2, 4)
	186 aload_0 (2, 4)
	187 getfield (2, 4)
	188 org/apache/commons/math3/optimization/direct/CMAESOptimizer.mu:I (2, 4)
	190 invokestatic (2, 4)
	191 org/apache/commons/math3/util/MathArrays.copyOf:([II)[I (2, 4)
	193 invokestatic (2, 4)
	194 org/apache/commons/math3/optimization/direct/CMAESOptimizer.selectColumns:(Lorg/apache/commons/math3/linear/RealMatrix;[I)Lorg/apache/commons/math3/linear/RealMatrix; (2, 4)
	196 astore (2, 4)
	197 #17 (2, 4)
	198 aload (2, 4)
	199 #17 (2, 4)
	200 invokestatic (2, 4)
	201 org/apache/commons/math3/optimization/direct/CMAESOptimizer.square:(Lorg/apache/commons/math3/linear/RealMatrix;)Lorg/apache/commons/math3/linear/RealMatrix; (2, 4)
	203 invokestatic (2, 4)
	204 org/apache/commons/math3/optimization/direct/CMAESOptimizer.sumRows:(Lorg/apache/commons/math3/linear/RealMatrix;)Lorg/apache/commons/math3/linear/RealMatrix; (2, 4)
	206 invokestatic (2, 4)
	207 org/apache/commons/math3/optimization/direct/CMAESOptimizer.sqrt:(Lorg/apache/commons/math3/linear/RealMatrix;)Lorg/apache/commons/math3/linear/RealMatrix; (2, 4)
	209 astore (2, 4)
	210 #18 (2, 4)
	211 aload_0 (2, 4)
	212 aload (2, 4)
	213 #18 (2, 4)
	214 iconst_0 (2, 4)
	215 invokeinterface (2, 4)
	216 org/apache/commons/math3/linear/RealMatrix.divide:(Lorg/apache/commons/math3/linear/RealMatrix;Lorg/apache/commons/math3/linear/RealMatrix;)Lorg/apache/commons/math3/linear/RealMatrix; (2, 4)
	218 0 (2, 4)
	220 invokespecial (2, 4)
	221 org/apache/commons/math3/optimization/direct/CMAESOptimizer.sortedIndices:([D)[I (2, 4)
	223 astore (2, 4)
	224 #19 (2, 4)
	225 aload (2, 4)
	226 #18 (2, 4)
	227 aload (2, 4)
	228 #19 (2, 4)
	229 invokestatic (2, 4)
	230 org/apache/commons/math3/optimization/direct/CMAESOptimizer.selectColumns:(Lorg/apache/commons/math3/linear/RealMatrix;[I)Lorg/apache/commons/math3/linear/RealMatrix; (2, 4)
	232 astore (2, 4)
	233 #20 (2, 4)
	234 aload (2, 4)
	235 #19 (2, 4)
	236 invokestatic (2, 4)
	237 org/apache/commons/math3/optimization/direct/CMAESOptimizer.reverse:([I)[I (2, 4)
	239 astore (2, 4)
	240 #21 (2, 4)
	241 aload (2, 4)
	242 #18 (2, 4)
	243 aload (2, 4)
	244 #21 (2, 4)
	245 invokestatic (2, 4)
	246 org/apache/commons/math3/optimization/direct/CMAESOptimizer.selectColumns:(Lorg/apache/commons/math3/linear/RealMatrix;[I)Lorg/apache/commons/math3/linear/RealMatrix; (2, 4)
	248 astore (2, 4)
	249 #22 (2, 4)
	250 aload (2, 4)
	251 #22 (2, 4)
	252 aload (2, 4)
	253 #20 (2, 4)
	254 invokestatic (2, 4)
	255 org/apache/commons/math3/optimization/direct/CMAESOptimizer.divide:(Lorg/apache/commons/math3/linear/RealMatrix;Lorg/apache/commons/math3/linear/RealMatrix;)Lorg/apache/commons/math3/linear/RealMatrix; (2, 4)
	257 astore (2, 4)
	258 #18 (2, 4)
	259 aload (2, 4)
	260 #19 (2, 4)
	261 invokestatic (2, 4)
	262 org/apache/commons/math3/optimization/direct/CMAESOptimizer.inverse:([I)[I (2, 4)
	264 astore (2, 4)
	265 #23 (2, 4)
	266 aload (2, 4)
	267 #18 (2, 4)
	268 aload (2, 4)
	269 #23 (2, 4)
	270 invokestatic (2, 4)
	271 org/apache/commons/math3/optimization/direct/CMAESOptimizer.selectColumns:(Lorg/apache/commons/math3/linear/RealMatrix;[I)Lorg/apache/commons/math3/linear/RealMatrix; (2, 4)
	273 astore (2, 4)
	274 #24 (2, 4)
	275 ldc2_w (2, 4)
	276 0.33999999999999997 (2, 4)
	278 aload (2, 4)
	279 #24 (2, 4)
	280 invokestatic (2, 4)
	281 org/apache/commons/math3/optimization/direct/CMAESOptimizer.square:(Lorg/apache/commons/math3/linear/RealMatrix;)Lorg/apache/commons/math3/linear/RealMatrix; (2, 4)
	283 aload_0 (2, 4)
	284 getfield (2, 4)
	285 org/apache/commons/math3/optimization/direct/CMAESOptimizer.weights:Lorg/apache/commons/math3/linear/RealMatrix; (2, 4)
	287 invokeinterface (2, 4)
	288 org/apache/commons/math3/linear/RealMatrix.sigma:D (2, 4)
	290 0 (2, 4)
	292 iconst_0 (2, 4)
	293 iconst_0 (2, 4)
	294 invokeinterface (2, 4)
	295 org/apache/commons/math3/linear/RealMatrix.mueff:D (2, 4)
	297 0 (2, 4)
	299 ddiv (2, 4)
	300 dstore (2, 4)
	301 #25 (2, 4)
	302 dload (3, 1)
	303 #6 (3, 1)
	304 dload (3, 1)
	305 #25 (3, 1)
	306 dcmpl (3, 1)
	307 ifle (3, 1)
	308 7 (3, 1)
	310 dload (3, 1)
	311 #25 (3, 1)
	312 dstore (3, 1)
	313 #6 (3, 1)
	314 aload (2, 4)
	315 #17 (2, 4)
	316 aload (2, 4)
	317 #24 (2, 4)
	318 aload_0 (2, 4)
	319 getfield (2, 4)
	320 org/apache/commons/math3/optimization/direct/CMAESOptimizer.dimension:I (2, 4)
	322 iconst_1 (2, 4)
	323 invokestatic (2, 4)
	324 org/apache/commons/math3/optimization/direct/CMAESOptimizer.repmat:(Lorg/apache/commons/math3/linear/RealMatrix;II)Lorg/apache/commons/math3/linear/RealMatrix; (2, 4)
	326 invokestatic (2, 4)
	327 org/apache/commons/math3/optimization/direct/CMAESOptimizer.times:(Lorg/apache/commons/math3/linear/RealMatrix;Lorg/apache/commons/math3/linear/RealMatrix;)Lorg/apache/commons/math3/linear/RealMatrix; (2, 4)
	329 astore (2, 4)
	330 #17 (2, 4)
	331 aload_0 (2, 4)
	332 getfield (2, 4)
	333 org/apache/commons/math3/optimization/direct/CMAESOptimizer.BD:Lorg/apache/commons/math3/linear/RealMatrix; (2, 4)
	335 aload (2, 4)
	336 #17 (2, 4)
	337 invokeinterface (2, 4)
	338 org/apache/commons/math3/linear/RealMatrix.sigma:D (2, 4)
	340 0 (2, 4)
	342 astore (2, 4)
	343 #27 (2, 4)
	344 aload (2, 4)
	345 #27 (2, 4)
	346 aload_0 (2, 4)
	347 getfield (2, 4)
	348 org/apache/commons/math3/optimization/direct/CMAESOptimizer.weights:Lorg/apache/commons/math3/linear/RealMatrix; (2, 4)
	350 invokestatic (2, 4)
	351 org/apache/commons/math3/optimization/direct/CMAESOptimizer.diag:(Lorg/apache/commons/math3/linear/RealMatrix;)Lorg/apache/commons/math3/linear/RealMatrix; (2, 4)
	353 invokeinterface (2, 4)
	354 org/apache/commons/math3/linear/RealMatrix.sigma:D (2, 4)
	356 0 (2, 4)
	358 aload (2, 4)
	359 #27 (2, 4)
	360 invokeinterface (2, 4)
	361 org/apache/commons/math3/linear/RealMatrix.org/apache/commons/math3/optimization/direct/CMAESOptimizer$Sigma (2, 4)
	363 0 (2, 4)
	365 invokeinterface (2, 4)
	366 org/apache/commons/math3/linear/RealMatrix.sigma:D (2, 4)
	368 0 (2, 4)
	370 astore (2, 4)
	371 #28 (2, 4)
	372 dload (2, 4)
	373 #10 (2, 4)
	374 ldc2_w (2, 4)
	375 0.5 (2, 4)
	377 dload (2, 4)
	378 #6 (2, 4)
	379 dmul (2, 4)
	380 dadd (2, 4)
	381 dstore (2, 4)
	382 #10 (2, 4)
	383 aload_0 (2, 4)
	384 aload_0 (2, 4)
	385 getfield (2, 4)
	386 org/apache/commons/math3/optimization/direct/CMAESOptimizer.C:Lorg/apache/commons/math3/linear/RealMatrix; (2, 4)
	388 dload (2, 4)
	389 #10 (2, 4)
	390 invokeinterface (2, 4)
	391 org/apache/commons/math3/linear/RealMatrix.add:(Lorg/apache/commons/math3/linear/RealMatrix;)Lorg/apache/commons/math3/linear/RealMatrix; (2, 4)
	393 0 (2, 4)
	395 aload (2, 4)
	396 #9 (2, 4)
	397 invokeinterface (2, 4)
	398 org/apache/commons/math3/linear/RealMatrix.diagD:Lorg/apache/commons/math3/linear/RealMatrix; (2, 4)
	400 0 (2, 4)
	402 aload (2, 4)
	403 #8 (2, 4)
	404 aload_0 (2, 4)
	405 getfield (2, 4)
	406 org/apache/commons/math3/optimization/direct/CMAESOptimizer.ccovmu:D (2, 4)
	408 ldc2_w (2, 4)
	409 0.5 (2, 4)
	411 dload (2, 4)
	412 #6 (2, 4)
	413 dmul (2, 4)
	414 dadd (2, 4)
	415 invokeinterface (2, 4)
	416 org/apache/commons/math3/linear/RealMatrix.add:(Lorg/apache/commons/math3/linear/RealMatrix;)Lorg/apache/commons/math3/linear/RealMatrix; (2, 4)
	418 0 (2, 4)
	420 aload_0 (2, 4)
	421 getfield (2, 4)
	422 org/apache/commons/math3/optimization/direct/CMAESOptimizer.weights:Lorg/apache/commons/math3/linear/RealMatrix; (2, 4)
	424 iconst_1 (2, 4)
	425 aload_0 (2, 4)
	426 getfield (2, 4)
	427 org/apache/commons/math3/optimization/direct/CMAESOptimizer.dimension:I (2, 4)
	429 invokestatic (2, 4)
	430 org/apache/commons/math3/optimization/direct/CMAESOptimizer.repmat:(Lorg/apache/commons/math3/linear/RealMatrix;II)Lorg/apache/commons/math3/linear/RealMatrix; (2, 4)
	432 aload (2, 4)
	433 #8 (2, 4)
	434 invokeinterface (2, 4)
	435 org/apache/commons/math3/linear/RealMatrix.org/apache/commons/math3/optimization/direct/CMAESOptimizer$Sigma (2, 4)
	437 0 (2, 4)
	439 invokestatic (2, 4)
	440 org/apache/commons/math3/optimization/direct/CMAESOptimizer.times:(Lorg/apache/commons/math3/linear/RealMatrix;Lorg/apache/commons/math3/linear/RealMatrix;)Lorg/apache/commons/math3/linear/RealMatrix; (2, 4)
	442 invokeinterface (2, 4)
	443 org/apache/commons/math3/linear/RealMatrix.sigma:D (2, 4)
	445 0 (2, 4)
	447 invokeinterface (2, 4)
	448 org/apache/commons/math3/linear/RealMatrix.diagD:Lorg/apache/commons/math3/linear/RealMatrix; (2, 4)
	450 0 (2, 4)
	452 aload (2, 4)
	453 #28 (2, 4)
	454 dload (2, 4)
	455 #6 (2, 4)
	456 invokeinterface (2, 4)
	457 org/apache/commons/math3/linear/RealMatrix.add:(Lorg/apache/commons/math3/linear/RealMatrix;)Lorg/apache/commons/math3/linear/RealMatrix; (2, 4)
	459 0 (2, 4)
	461 invokeinterface (2, 4)
	462 org/apache/commons/math3/linear/RealMatrix.pow:(DD)D (2, 4)
	464 0 (2, 4)
	466 putfield (2, 4)
	467 org/apache/commons/math3/optimization/direct/CMAESOptimizer.C:Lorg/apache/commons/math3/linear/RealMatrix; (2, 4)
	469 goto (2, 2)
	470 68 (2, 2)
	472 aload_0 (2, 2)
	473 aload_0 (2, 2)
	474 getfield (2, 2)
	475 org/apache/commons/math3/optimization/direct/CMAESOptimizer.C:Lorg/apache/commons/math3/linear/RealMatrix; (2, 2)
	477 dload (2, 2)
	478 #10 (2, 2)
	479 invokeinterface (2, 2)
	480 org/apache/commons/math3/linear/RealMatrix.add:(Lorg/apache/commons/math3/linear/RealMatrix;)Lorg/apache/commons/math3/linear/RealMatrix; (2, 2)
	482 0 (2, 2)
	484 aload (2, 2)
	485 #9 (2, 2)
	486 invokeinterface (2, 2)
	487 org/apache/commons/math3/linear/RealMatrix.diagD:Lorg/apache/commons/math3/linear/RealMatrix; (2, 2)
	489 0 (2, 2)
	491 aload (2, 2)
	492 #8 (2, 2)
	493 aload_0 (2, 2)
	494 getfield (2, 2)
	495 org/apache/commons/math3/optimization/direct/CMAESOptimizer.ccovmu:D (2, 2)
	497 invokeinterface (2, 2)
	498 org/apache/commons/math3/linear/RealMatrix.add:(Lorg/apache/commons/math3/linear/RealMatrix;)Lorg/apache/commons/math3/linear/RealMatrix; (2, 2)
	500 0 (2, 2)
	502 aload_0 (2, 2)
	503 getfield (2, 2)
	504 org/apache/commons/math3/optimization/direct/CMAESOptimizer.weights:Lorg/apache/commons/math3/linear/RealMatrix; (2, 2)
	506 iconst_1 (2, 2)
	507 aload_0 (2, 2)
	508 getfield (2, 2)
	509 org/apache/commons/math3/optimization/direct/CMAESOptimizer.dimension:I (2, 2)
	511 invokestatic (2, 2)
	512 org/apache/commons/math3/optimization/direct/CMAESOptimizer.repmat:(Lorg/apache/commons/math3/linear/RealMatrix;II)Lorg/apache/commons/math3/linear/RealMatrix; (2, 2)
	514 aload (2, 2)
	515 #8 (2, 2)
	516 invokeinterface (2, 2)
	517 org/apache/commons/math3/linear/RealMatrix.org/apache/commons/math3/optimization/direct/CMAESOptimizer$Sigma (2, 2)
	519 0 (2, 2)
	521 invokestatic (2, 2)
	522 org/apache/commons/math3/optimization/direct/CMAESOptimizer.times:(Lorg/apache/commons/math3/linear/RealMatrix;Lorg/apache/commons/math3/linear/RealMatrix;)Lorg/apache/commons/math3/linear/RealMatrix; (2, 2)
	524 invokeinterface (2, 2)
	525 org/apache/commons/math3/linear/RealMatrix.sigma:D (2, 2)
	527 0 (2, 2)
	529 invokeinterface (2, 2)
	530 org/apache/commons/math3/linear/RealMatrix.diagD:Lorg/apache/commons/math3/linear/RealMatrix; (2, 2)
	532 0 (2, 2)
	534 putfield (2, 2)
	535 org/apache/commons/math3/optimization/direct/CMAESOptimizer.C:Lorg/apache/commons/math3/linear/RealMatrix; (2, 2)
	537 aload_0 (0, 0)
	538 dload (0, 0)
	539 #6 (0, 0)
	540 invokespecial (0, 0)
	541 org/apache/commons/math3/optimization/direct/CMAESOptimizer.updateBD:(D)V (0, 0)
	543 return (0, 0)

Method: updateBD
	0 aload_0 (0, 1)
	1 getfield (0, 1)
	2 org/apache/commons/math3/optimization/direct/CMAESOptimizer.ccov1:D (0, 1)
	4 aload_0 (0, 1)
	5 getfield (0, 1)
	6 org/apache/commons/math3/optimization/direct/CMAESOptimizer.ccovmu:D (0, 1)
	8 dadd (0, 1)
	9 dload_1 (0, 1)
	10 dadd (0, 1)
	11 dconst_0 (0, 1)
	12 dcmpl (0, 1)
	13 ifle (0, 1)
	14 390 (0, 1)
	16 aload_0 (0, 1)
	17 getfield (0, 1)
	18 org/apache/commons/math3/optimization/direct/CMAESOptimizer.iterations:I (0, 1)
	20 i2d (0, 1)
	21 dconst_1 (0, 1)
	22 drem (0, 1)
	23 aload_0 (0, 1)
	24 getfield (0, 1)
	25 org/apache/commons/math3/optimization/direct/CMAESOptimizer.ccov1:D (0, 1)
	27 aload_0 (0, 1)
	28 getfield (0, 1)
	29 org/apache/commons/math3/optimization/direct/CMAESOptimizer.ccovmu:D (0, 1)
	31 dadd (0, 1)
	32 dload_1 (0, 1)
	33 dadd (0, 1)
	34 ddiv (0, 1)
	35 aload_0 (0, 1)
	36 getfield (0, 1)
	37 org/apache/commons/math3/optimization/direct/CMAESOptimizer.dimension:I (0, 1)
	39 i2d (0, 1)
	40 ddiv (0, 1)
	41 ldc2_w (0, 1)
	42 10.0 (0, 1)
	44 ddiv (0, 1)
	45 dconst_1 (0, 1)
	46 dcmpg (0, 1)
	47 ifge (0, 1)
	48 356 (0, 1)
	50 aload_0 (0, 1)
	51 aload_0 (0, 1)
	52 getfield (0, 1)
	53 org/apache/commons/math3/optimization/direct/CMAESOptimizer.C:Lorg/apache/commons/math3/linear/RealMatrix; (0, 1)
	55 iconst_0 (0, 1)
	56 invokestatic (0, 1)
	57 org/apache/commons/math3/optimization/direct/CMAESOptimizer.triu:(Lorg/apache/commons/math3/linear/RealMatrix;I)Lorg/apache/commons/math3/linear/RealMatrix; (0, 1)
	59 aload_0 (0, 1)
	60 getfield (0, 1)
	61 org/apache/commons/math3/optimization/direct/CMAESOptimizer.C:Lorg/apache/commons/math3/linear/RealMatrix; (0, 1)
	63 iconst_1 (0, 1)
	64 invokestatic (0, 1)
	65 org/apache/commons/math3/optimization/direct/CMAESOptimizer.triu:(Lorg/apache/commons/math3/linear/RealMatrix;I)Lorg/apache/commons/math3/linear/RealMatrix; (0, 1)
	67 invokeinterface (0, 1)
	68 org/apache/commons/math3/linear/RealMatrix.org/apache/commons/math3/optimization/direct/CMAESOptimizer$Sigma (0, 1)
	70 0 (0, 1)
	72 invokeinterface (0, 1)
	73 org/apache/commons/math3/linear/RealMatrix.diagD:Lorg/apache/commons/math3/linear/RealMatrix; (0, 1)
	75 0 (0, 1)
	77 putfield (0, 1)
	78 org/apache/commons/math3/optimization/direct/CMAESOptimizer.C:Lorg/apache/commons/math3/linear/RealMatrix; (0, 1)
	80 new (1, 4)
	81 org/apache/commons/math3/linear/EigenDecomposition (1, 4)
	83 dup (1, 4)
	84 aload_0 (1, 4)
	85 getfield (1, 4)
	86 org/apache/commons/math3/optimization/direct/CMAESOptimizer.C:Lorg/apache/commons/math3/linear/RealMatrix; (1, 4)
	88 invokespecial (1, 4)
	89 org/apache/commons/math3/linear/EigenDecomposition.<init>:(Lorg/apache/commons/math3/linear/RealMatrix;)V (1, 4)
	91 astore_3 (1, 4)
	92 aload_0 (1, 4)
	93 aload_3 (1, 4)
	94 invokevirtual (1, 4)
	95 org/apache/commons/math3/linear/EigenDecomposition.getV:()Lorg/apache/commons/math3/linear/RealMatrix; (1, 4)
	97 putfield (1, 4)
	98 org/apache/commons/math3/optimization/direct/CMAESOptimizer.B:Lorg/apache/commons/math3/linear/RealMatrix; (1, 4)
	100 aload_0 (1, 4)
	101 aload_3 (1, 4)
	102 invokevirtual (1, 4)
	103 org/apache/commons/math3/linear/EigenDecomposition.getD:()Lorg/apache/commons/math3/linear/RealMatrix; (1, 4)
	105 putfield (1, 4)
	106 org/apache/commons/math3/optimization/direct/CMAESOptimizer.D:Lorg/apache/commons/math3/linear/RealMatrix; (1, 4)
	108 aload_0 (1, 4)
	109 aload_0 (1, 4)
	110 getfield (1, 4)
	111 org/apache/commons/math3/optimization/direct/CMAESOptimizer.D:Lorg/apache/commons/math3/linear/RealMatrix; (1, 4)
	113 invokestatic (1, 4)
	114 org/apache/commons/math3/optimization/direct/CMAESOptimizer.diag:(Lorg/apache/commons/math3/linear/RealMatrix;)Lorg/apache/commons/math3/linear/RealMatrix; (1, 4)
	116 putfield (1, 4)
	117 org/apache/commons/math3/optimization/direct/CMAESOptimizer.diagD:Lorg/apache/commons/math3/linear/RealMatrix; (1, 4)
	119 aload_0 (2, 1)
	120 getfield (2, 1)
	121 org/apache/commons/math3/optimization/direct/CMAESOptimizer.diagD:Lorg/apache/commons/math3/linear/RealMatrix; (2, 1)
	123 invokestatic (2, 1)
	124 org/apache/commons/math3/optimization/direct/CMAESOptimizer.min:(Lorg/apache/commons/math3/linear/RealMatrix;)D (2, 1)
	126 dconst_0 (2, 1)
	127 dcmpg (2, 1)
	128 ifgt (2, 1)
	129 123 (2, 1)
	131 iconst_0 (3, 4)
	132 istore (3, 4)
	133 #4 (3, 4)
	134 iload (3, 4)
	135 #4 (3, 4)
	136 aload_0 (3, 4)
	137 getfield (3, 4)
	138 org/apache/commons/math3/optimization/direct/CMAESOptimizer.dimension:I (3, 4)
	140 if_icmpge (3, 4)
	141 39 (3, 4)
	143 aload_0 (4, 1)
	144 getfield (4, 1)
	145 org/apache/commons/math3/optimization/direct/CMAESOptimizer.diagD:Lorg/apache/commons/math3/linear/RealMatrix; (4, 1)
	147 iload (4, 1)
	148 #4 (4, 1)
	149 iconst_0 (4, 1)
	150 invokeinterface (4, 1)
	151 org/apache/commons/math3/linear/RealMatrix.mueff:D (4, 1)
	153 0 (4, 1)
	155 dconst_0 (4, 1)
	156 dcmpg (4, 1)
	157 ifge (4, 1)
	158 16 (4, 1)
	160 aload_0 (4, 1)
	161 getfield (4, 1)
	162 org/apache/commons/math3/optimization/direct/CMAESOptimizer.diagD:Lorg/apache/commons/math3/linear/RealMatrix; (4, 1)
	164 iload (4, 1)
	165 #4 (4, 1)
	166 iconst_0 (4, 1)
	167 dconst_0 (4, 1)
	168 invokeinterface (4, 1)
	169 org/apache/commons/math3/linear/RealMatrix.org/apache/commons/math3/optimization/direct/CMAESOptimizer$DoubleIndex (4, 1)
	171 0 (4, 1)
	173 iinc (4, 1)
	174 #4 (4, 1)
	175 -89 (4, 1)
	176 goto (4, 1)
	177 -42 (4, 1)
	179 aload_0 (3, 4)
	180 getfield (3, 4)
	181 org/apache/commons/math3/optimization/direct/CMAESOptimizer.diagD:Lorg/apache/commons/math3/linear/RealMatrix; (3, 4)
	183 invokestatic (3, 4)
	184 org/apache/commons/math3/optimization/direct/CMAESOptimizer.max:(Lorg/apache/commons/math3/linear/RealMatrix;)D (3, 4)
	186 ldc2_w (3, 4)
	187 100000000000000.0 (3, 4)
	189 ddiv (3, 4)
	190 dstore (3, 4)
	191 #4 (3, 4)
	192 aload_0 (3, 4)
	193 aload_0 (3, 4)
	194 getfield (3, 4)
	195 org/apache/commons/math3/optimization/direct/CMAESOptimizer.C:Lorg/apache/commons/math3/linear/RealMatrix; (3, 4)
	197 aload_0 (3, 4)
	198 getfield (3, 4)
	199 org/apache/commons/math3/optimization/direct/CMAESOptimizer.dimension:I (3, 4)
	201 aload_0 (3, 4)
	202 getfield (3, 4)
	203 org/apache/commons/math3/optimization/direct/CMAESOptimizer.dimension:I (3, 4)
	205 invokestatic (3, 4)
	206 org/apache/commons/math3/optimization/direct/CMAESOptimizer.eye:(II)Lorg/apache/commons/math3/linear/RealMatrix; (3, 4)
	208 dload (3, 4)
	209 #4 (3, 4)
	210 invokeinterface (3, 4)
	211 org/apache/commons/math3/linear/RealMatrix.add:(Lorg/apache/commons/math3/linear/RealMatrix;)Lorg/apache/commons/math3/linear/RealMatrix; (3, 4)
	213 0 (3, 4)
	215 invokeinterface (3, 4)
	216 org/apache/commons/math3/linear/RealMatrix.diagD:Lorg/apache/commons/math3/linear/RealMatrix; (3, 4)
	218 0 (3, 4)
	220 putfield (3, 4)
	221 org/apache/commons/math3/optimization/direct/CMAESOptimizer.C:Lorg/apache/commons/math3/linear/RealMatrix; (3, 4)
	223 aload_0 (3, 4)
	224 aload_0 (3, 4)
	225 getfield (3, 4)
	226 org/apache/commons/math3/optimization/direct/CMAESOptimizer.diagD:Lorg/apache/commons/math3/linear/RealMatrix; (3, 4)
	228 aload_0 (3, 4)
	229 getfield (3, 4)
	230 org/apache/commons/math3/optimization/direct/CMAESOptimizer.dimension:I (3, 4)
	232 iconst_1 (3, 4)
	233 invokestatic (3, 4)
	234 org/apache/commons/math3/optimization/direct/CMAESOptimizer.ones:(II)Lorg/apache/commons/math3/linear/RealMatrix; (3, 4)
	236 dload (3, 4)
	237 #4 (3, 4)
	238 invokeinterface (3, 4)
	239 org/apache/commons/math3/linear/RealMatrix.add:(Lorg/apache/commons/math3/linear/RealMatrix;)Lorg/apache/commons/math3/linear/RealMatrix; (3, 4)
	241 0 (3, 4)
	243 invokeinterface (3, 4)
	244 org/apache/commons/math3/linear/RealMatrix.diagD:Lorg/apache/commons/math3/linear/RealMatrix; (3, 4)
	246 0 (3, 4)
	248 putfield (3, 4)
	249 org/apache/commons/math3/optimization/direct/CMAESOptimizer.diagD:Lorg/apache/commons/math3/linear/RealMatrix; (3, 4)
	251 aload_0 (3, 1)
	252 getfield (3, 1)
	253 org/apache/commons/math3/optimization/direct/CMAESOptimizer.diagD:Lorg/apache/commons/math3/linear/RealMatrix; (3, 1)
	255 invokestatic (3, 1)
	256 org/apache/commons/math3/optimization/direct/CMAESOptimizer.max:(Lorg/apache/commons/math3/linear/RealMatrix;)D (3, 1)
	258 ldc2_w (3, 1)
	259 100000000000000.0 (3, 1)
	261 aload_0 (3, 1)
	262 getfield (3, 1)
	263 org/apache/commons/math3/optimization/direct/CMAESOptimizer.diagD:Lorg/apache/commons/math3/linear/RealMatrix; (3, 1)
	265 invokestatic (3, 1)
	266 org/apache/commons/math3/optimization/direct/CMAESOptimizer.min:(Lorg/apache/commons/math3/linear/RealMatrix;)D (3, 1)
	268 dmul (3, 1)
	269 dcmpl (3, 1)
	270 ifle (3, 1)
	271 83 (3, 1)
	273 aload_0 (3, 1)
	274 getfield (3, 1)
	275 org/apache/commons/math3/optimization/direct/CMAESOptimizer.diagD:Lorg/apache/commons/math3/linear/RealMatrix; (3, 1)
	277 invokestatic (3, 1)
	278 org/apache/commons/math3/optimization/direct/CMAESOptimizer.max:(Lorg/apache/commons/math3/linear/RealMatrix;)D (3, 1)
	280 ldc2_w (3, 1)
	281 100000000000000.0 (3, 1)
	283 ddiv (3, 1)
	284 aload_0 (3, 1)
	285 getfield (3, 1)
	286 org/apache/commons/math3/optimization/direct/CMAESOptimizer.diagD:Lorg/apache/commons/math3/linear/RealMatrix; (3, 1)
	288 invokestatic (3, 1)
	289 org/apache/commons/math3/optimization/direct/CMAESOptimizer.min:(Lorg/apache/commons/math3/linear/RealMatrix;)D (3, 1)
	291 dsub (3, 1)
	292 dstore (3, 1)
	293 #4 (3, 1)
	294 aload_0 (3, 1)
	295 aload_0 (3, 1)
	296 getfield (3, 1)
	297 org/apache/commons/math3/optimization/direct/CMAESOptimizer.C:Lorg/apache/commons/math3/linear/RealMatrix; (3, 1)
	299 aload_0 (3, 1)
	300 getfield (3, 1)
	301 org/apache/commons/math3/optimization/direct/CMAESOptimizer.dimension:I (3, 1)
	303 aload_0 (3, 1)
	304 getfield (3, 1)
	305 org/apache/commons/math3/optimization/direct/CMAESOptimizer.dimension:I (3, 1)
	307 invokestatic (3, 1)
	308 org/apache/commons/math3/optimization/direct/CMAESOptimizer.eye:(II)Lorg/apache/commons/math3/linear/RealMatrix; (3, 1)
	310 dload (3, 1)
	311 #4 (3, 1)
	312 invokeinterface (3, 1)
	313 org/apache/commons/math3/linear/RealMatrix.add:(Lorg/apache/commons/math3/linear/RealMatrix;)Lorg/apache/commons/math3/linear/RealMatrix; (3, 1)
	315 0 (3, 1)
	317 invokeinterface (3, 1)
	318 org/apache/commons/math3/linear/RealMatrix.diagD:Lorg/apache/commons/math3/linear/RealMatrix; (3, 1)
	320 0 (3, 1)
	322 putfield (3, 1)
	323 org/apache/commons/math3/optimization/direct/CMAESOptimizer.C:Lorg/apache/commons/math3/linear/RealMatrix; (3, 1)
	325 aload_0 (3, 1)
	326 aload_0 (3, 1)
	327 getfield (3, 1)
	328 org/apache/commons/math3/optimization/direct/CMAESOptimizer.diagD:Lorg/apache/commons/math3/linear/RealMatrix; (3, 1)
	330 aload_0 (3, 1)
	331 getfield (3, 1)
	332 org/apache/commons/math3/optimization/direct/CMAESOptimizer.dimension:I (3, 1)
	334 iconst_1 (3, 1)
	335 invokestatic (3, 1)
	336 org/apache/commons/math3/optimization/direct/CMAESOptimizer.ones:(II)Lorg/apache/commons/math3/linear/RealMatrix; (3, 1)
	338 dload (3, 1)
	339 #4 (3, 1)
	340 invokeinterface (3, 1)
	341 org/apache/commons/math3/linear/RealMatrix.add:(Lorg/apache/commons/math3/linear/RealMatrix;)Lorg/apache/commons/math3/linear/RealMatrix; (3, 1)
	343 0 (3, 1)
	345 invokeinterface (3, 1)
	346 org/apache/commons/math3/linear/RealMatrix.diagD:Lorg/apache/commons/math3/linear/RealMatrix; (3, 1)
	348 0 (3, 1)
	350 putfield (3, 1)
	351 org/apache/commons/math3/optimization/direct/CMAESOptimizer.diagD:Lorg/apache/commons/math3/linear/RealMatrix; (3, 1)
	353 aload_0 (2, 1)
	354 aload_0 (2, 1)
	355 getfield (2, 1)
	356 org/apache/commons/math3/optimization/direct/CMAESOptimizer.C:Lorg/apache/commons/math3/linear/RealMatrix; (2, 1)
	358 invokestatic (2, 1)
	359 org/apache/commons/math3/optimization/direct/CMAESOptimizer.diag:(Lorg/apache/commons/math3/linear/RealMatrix;)Lorg/apache/commons/math3/linear/RealMatrix; (2, 1)
	361 putfield (2, 1)
	362 org/apache/commons/math3/optimization/direct/CMAESOptimizer.diagC:Lorg/apache/commons/math3/linear/RealMatrix; (2, 1)
	364 aload_0 (2, 1)
	365 aload_0 (2, 1)
	366 getfield (2, 1)
	367 org/apache/commons/math3/optimization/direct/CMAESOptimizer.diagD:Lorg/apache/commons/math3/linear/RealMatrix; (2, 1)
	369 invokestatic (2, 1)
	370 org/apache/commons/math3/optimization/direct/CMAESOptimizer.sqrt:(Lorg/apache/commons/math3/linear/RealMatrix;)Lorg/apache/commons/math3/linear/RealMatrix; (2, 1)
	372 putfield (2, 1)
	373 org/apache/commons/math3/optimization/direct/CMAESOptimizer.diagD:Lorg/apache/commons/math3/linear/RealMatrix; (2, 1)
	375 aload_0 (2, 1)
	376 aload_0 (2, 1)
	377 getfield (2, 1)
	378 org/apache/commons/math3/optimization/direct/CMAESOptimizer.B:Lorg/apache/commons/math3/linear/RealMatrix; (2, 1)
	380 aload_0 (2, 1)
	381 getfield (2, 1)
	382 org/apache/commons/math3/optimization/direct/CMAESOptimizer.diagD:Lorg/apache/commons/math3/linear/RealMatrix; (2, 1)
	384 invokeinterface (2, 1)
	385 org/apache/commons/math3/linear/RealMatrix.org/apache/commons/math3/optimization/direct/CMAESOptimizer$Sigma (2, 1)
	387 0 (2, 1)
	389 aload_0 (2, 1)
	390 getfield (2, 1)
	391 org/apache/commons/math3/optimization/direct/CMAESOptimizer.dimension:I (2, 1)
	393 iconst_1 (2, 1)
	394 invokestatic (2, 1)
	395 org/apache/commons/math3/optimization/direct/CMAESOptimizer.repmat:(Lorg/apache/commons/math3/linear/RealMatrix;II)Lorg/apache/commons/math3/linear/RealMatrix; (2, 1)
	397 invokestatic (2, 1)
	398 org/apache/commons/math3/optimization/direct/CMAESOptimizer.times:(Lorg/apache/commons/math3/linear/RealMatrix;Lorg/apache/commons/math3/linear/RealMatrix;)Lorg/apache/commons/math3/linear/RealMatrix; (2, 1)
	400 putfield (2, 1)
	401 org/apache/commons/math3/optimization/direct/CMAESOptimizer.BD:Lorg/apache/commons/math3/linear/RealMatrix; (2, 1)
	403 return (0, 1)

Method: push
	0 aload_0 (1, 4)
	1 arraylength (1, 4)
	2 iconst_1 (1, 4)
	3 isub (1, 4)
	4 istore_3 (1, 4)
	5 iload_3 (1, 4)
	6 ifle (1, 4)
	7 17 (1, 4)
	9 aload_0 (1, 4)
	10 iload_3 (1, 4)
	11 aload_0 (1, 4)
	12 iload_3 (1, 4)
	13 iconst_1 (1, 4)
	14 isub (1, 4)
	15 daload (1, 4)
	16 dastore (1, 4)
	17 iinc (1, 4)
	18 #3 (1, 4)
	19 -89 (1, 4)
	20 goto (1, 4)
	21 -15 (1, 4)
	23 aload_0 (0, 0)
	24 iconst_0 (0, 0)
	25 dload_1 (0, 0)
	26 dastore (0, 0)
	27 return (0, 0)

Method: sortedIndices
	0 aload_1 (0, 0)
	1 arraylength (0, 0)
	2 anewarray (0, 0)
	3 org/apache/commons/math3/optimization/direct/CMAESOptimizer$DoubleIndex (0, 0)
	5 astore_2 (0, 0)
	6 iconst_0 (1, 4)
	7 istore_3 (1, 4)
	8 iload_3 (1, 4)
	9 aload_1 (1, 4)
	10 arraylength (1, 4)
	11 if_icmpge (1, 4)
	12 23 (1, 4)
	14 aload_2 (1, 4)
	15 iload_3 (1, 4)
	16 new (1, 4)
	17 org/apache/commons/math3/optimization/direct/CMAESOptimizer$DoubleIndex (1, 4)
	19 dup (1, 4)
	20 aload_1 (1, 4)
	21 iload_3 (1, 4)
	22 daload (1, 4)
	23 iload_3 (1, 4)
	24 invokespecial (1, 4)
	25 org/apache/commons/math3/optimization/direct/CMAESOptimizer$DoubleIndex.<init>:(DI)V (1, 4)
	27 aastore (1, 4)
	28 iinc (1, 4)
	29 #3 (1, 4)
	30 -89 (1, 4)
	31 goto (1, 4)
	32 -23 (1, 4)
	34 aload_2 (0, 0)
	35 invokestatic (0, 0)
	36 java/util/Arrays.sort:([Ljava/lang/Object;)V (0, 0)
	38 aload_1 (0, 0)
	39 arraylength (0, 0)
	40 newarray (0, 0)
	41 10 (0, 0)
	42 astore_3 (0, 0)
	43 iconst_0 (1, 4)
	44 istore (1, 4)
	45 #4 (1, 4)
	46 iload (1, 4)
	47 #4 (1, 4)
	48 aload_1 (1, 4)
	49 arraylength (1, 4)
	50 if_icmpge (1, 4)
	51 20 (1, 4)
	53 aload_3 (1, 4)
	54 iload (1, 4)
	55 #4 (1, 4)
	56 aload_2 (1, 4)
	57 iload (1, 4)
	58 #4 (1, 4)
	59 aaload (1, 4)
	60 invokestatic (1, 4)
	61 org/apache/commons/math3/optimization/direct/CMAESOptimizer$DoubleIndex.access$100:(Lorg/apache/commons/math3/optimization/direct/CMAESOptimizer$DoubleIndex;)I (1, 4)
	63 iastore (1, 4)
	64 iinc (1, 4)
	65 #4 (1, 4)
	66 -89 (1, 4)
	67 goto (1, 4)
	68 -21 (1, 4)
	70 aload_3 (0, 0)
	71 areturn (0, 0)

Method: log
	0 aload_0 (0, 0)
	1 invokeinterface (0, 0)
	2 org/apache/commons/math3/linear/RealMatrix.getColumnDimension:()I (0, 0)
	4 0 (0, 0)
	6 aload_0 (0, 0)
	7 invokeinterface (0, 0)
	8 org/apache/commons/math3/linear/RealMatrix.fill:([DD)V (0, 0)
	10 0 (0, 0)
	12 multianewarray (0, 0)
	13 [[D (0, 0)
	15 76 (0, 0)
	16 astore_1 (0, 0)
	17 iconst_0 (1, 4)
	18 istore_2 (1, 4)
	19 iload_2 (1, 4)
	20 aload_0 (1, 4)
	21 invokeinterface (1, 4)
	22 org/apache/commons/math3/linear/RealMatrix.getColumnDimension:()I (1, 4)
	24 0 (1, 4)
	26 if_icmpge (1, 4)
	27 43 (1, 4)
	29 iconst_0 (2, 4)
	30 istore_3 (2, 4)
	31 iload_3 (2, 4)
	32 aload_0 (2, 4)
	33 invokeinterface (2, 4)
	34 org/apache/commons/math3/linear/RealMatrix.fill:([DD)V (2, 4)
	36 0 (2, 4)
	38 if_icmpge (2, 4)
	39 25 (2, 4)
	41 aload_1 (2, 4)
	42 iload_2 (2, 4)
	43 aaload (2, 4)
	44 iload_3 (2, 4)
	45 aload_0 (2, 4)
	46 iload_2 (2, 4)
	47 iload_3 (2, 4)
	48 invokeinterface (2, 4)
	49 org/apache/commons/math3/linear/RealMatrix.mueff:D (2, 4)
	51 0 (2, 4)
	53 invokestatic (2, 4)
	54 org/apache/commons/math3/util/FastMath.log:(D)D (2, 4)
	56 dastore (2, 4)
	57 iinc (2, 4)
	58 #3 (2, 4)
	59 -89 (2, 4)
	60 goto (2, 4)
	61 -29 (2, 4)
	63 iinc (2, 4)
	64 #2 (2, 4)
	65 -89 (2, 4)
	66 goto (2, 4)
	67 -47 (2, 4)
	69 new (1, 4)
	70 org/apache/commons/math3/linear/Array2DRowRealMatrix (1, 4)
	72 dup (1, 4)
	73 aload_1 (1, 4)
	74 iconst_0 (1, 4)
	75 invokespecial (1, 4)
	76 org/apache/commons/math3/linear/Array2DRowRealMatrix.<init>:([[DZ)V (1, 4)
	78 areturn (1, 4)

Method: sqrt
	0 aload_0 (0, 0)
	1 invokeinterface (0, 0)
	2 org/apache/commons/math3/linear/RealMatrix.getColumnDimension:()I (0, 0)
	4 0 (0, 0)
	6 aload_0 (0, 0)
	7 invokeinterface (0, 0)
	8 org/apache/commons/math3/linear/RealMatrix.fill:([DD)V (0, 0)
	10 0 (0, 0)
	12 multianewarray (0, 0)
	13 [[D (0, 0)
	15 76 (0, 0)
	16 astore_1 (0, 0)
	17 iconst_0 (1, 4)
	18 istore_2 (1, 4)
	19 iload_2 (1, 4)
	20 aload_0 (1, 4)
	21 invokeinterface (1, 4)
	22 org/apache/commons/math3/linear/RealMatrix.getColumnDimension:()I (1, 4)
	24 0 (1, 4)
	26 if_icmpge (1, 4)
	27 43 (1, 4)
	29 iconst_0 (2, 4)
	30 istore_3 (2, 4)
	31 iload_3 (2, 4)
	32 aload_0 (2, 4)
	33 invokeinterface (2, 4)
	34 org/apache/commons/math3/linear/RealMatrix.fill:([DD)V (2, 4)
	36 0 (2, 4)
	38 if_icmpge (2, 4)
	39 25 (2, 4)
	41 aload_1 (2, 4)
	42 iload_2 (2, 4)
	43 aaload (2, 4)
	44 iload_3 (2, 4)
	45 aload_0 (2, 4)
	46 iload_2 (2, 4)
	47 iload_3 (2, 4)
	48 invokeinterface (2, 4)
	49 org/apache/commons/math3/linear/RealMatrix.mueff:D (2, 4)
	51 0 (2, 4)
	53 invokestatic (2, 4)
	54 org/apache/commons/math3/util/FastMath.sqrt:(D)D (2, 4)
	56 dastore (2, 4)
	57 iinc (2, 4)
	58 #3 (2, 4)
	59 -89 (2, 4)
	60 goto (2, 4)
	61 -29 (2, 4)
	63 iinc (2, 4)
	64 #2 (2, 4)
	65 -89 (2, 4)
	66 goto (2, 4)
	67 -47 (2, 4)
	69 new (1, 4)
	70 org/apache/commons/math3/linear/Array2DRowRealMatrix (1, 4)
	72 dup (1, 4)
	73 aload_1 (1, 4)
	74 iconst_0 (1, 4)
	75 invokespecial (1, 4)
	76 org/apache/commons/math3/linear/Array2DRowRealMatrix.<init>:([[DZ)V (1, 4)
	78 areturn (1, 4)

Method: square
	0 aload_0 (0, 0)
	1 invokeinterface (0, 0)
	2 org/apache/commons/math3/linear/RealMatrix.getColumnDimension:()I (0, 0)
	4 0 (0, 0)
	6 aload_0 (0, 0)
	7 invokeinterface (0, 0)
	8 org/apache/commons/math3/linear/RealMatrix.fill:([DD)V (0, 0)
	10 0 (0, 0)
	12 multianewarray (0, 0)
	13 [[D (0, 0)
	15 76 (0, 0)
	16 astore_1 (0, 0)
	17 iconst_0 (1, 4)
	18 istore_2 (1, 4)
	19 iload_2 (1, 4)
	20 aload_0 (1, 4)
	21 invokeinterface (1, 4)
	22 org/apache/commons/math3/linear/RealMatrix.getColumnDimension:()I (1, 4)
	24 0 (1, 4)
	26 if_icmpge (1, 4)
	27 47 (1, 4)
	29 iconst_0 (2, 4)
	30 istore_3 (2, 4)
	31 iload_3 (2, 4)
	32 aload_0 (2, 4)
	33 invokeinterface (2, 4)
	34 org/apache/commons/math3/linear/RealMatrix.fill:([DD)V (2, 4)
	36 0 (2, 4)
	38 if_icmpge (2, 4)
	39 29 (2, 4)
	41 aload_0 (2, 4)
	42 iload_2 (2, 4)
	43 iload_3 (2, 4)
	44 invokeinterface (2, 4)
	45 org/apache/commons/math3/linear/RealMatrix.mueff:D (2, 4)
	47 0 (2, 4)
	49 dstore (2, 4)
	50 #4 (2, 4)
	51 aload_1 (2, 4)
	52 iload_2 (2, 4)
	53 aaload (2, 4)
	54 iload_3 (2, 4)
	55 dload (2, 4)
	56 #4 (2, 4)
	57 dload (2, 4)
	58 #4 (2, 4)
	59 dmul (2, 4)
	60 dastore (2, 4)
	61 iinc (2, 4)
	62 #3 (2, 4)
	63 -89 (2, 4)
	64 goto (2, 4)
	65 -33 (2, 4)
	67 iinc (2, 4)
	68 #2 (2, 4)
	69 -89 (2, 4)
	70 goto (2, 4)
	71 -51 (2, 4)
	73 new (1, 4)
	74 org/apache/commons/math3/linear/Array2DRowRealMatrix (1, 4)
	76 dup (1, 4)
	77 aload_1 (1, 4)
	78 iconst_0 (1, 4)
	79 invokespecial (1, 4)
	80 org/apache/commons/math3/linear/Array2DRowRealMatrix.<init>:([[DZ)V (1, 4)
	82 areturn (1, 4)

Method: times
	0 aload_0 (0, 0)
	1 invokeinterface (0, 0)
	2 org/apache/commons/math3/linear/RealMatrix.getColumnDimension:()I (0, 0)
	4 0 (0, 0)
	6 aload_0 (0, 0)
	7 invokeinterface (0, 0)
	8 org/apache/commons/math3/linear/RealMatrix.fill:([DD)V (0, 0)
	10 0 (0, 0)
	12 multianewarray (0, 0)
	13 [[D (0, 0)
	15 77 (0, 0)
	16 astore_2 (0, 0)
	17 iconst_0 (1, 4)
	18 istore_3 (1, 4)
	19 iload_3 (1, 4)
	20 aload_0 (1, 4)
	21 invokeinterface (1, 4)
	22 org/apache/commons/math3/linear/RealMatrix.getColumnDimension:()I (1, 4)
	24 0 (1, 4)
	26 if_icmpge (1, 4)
	27 54 (1, 4)
	29 iconst_0 (2, 4)
	30 istore (2, 4)
	31 #4 (2, 4)
	32 iload (2, 4)
	33 #4 (2, 4)
	34 aload_0 (2, 4)
	35 invokeinterface (2, 4)
	36 org/apache/commons/math3/linear/RealMatrix.fill:([DD)V (2, 4)
	38 0 (2, 4)
	40 if_icmpge (2, 4)
	41 34 (2, 4)
	43 aload_2 (2, 4)
	44 iload_3 (2, 4)
	45 aaload (2, 4)
	46 iload (2, 4)
	47 #4 (2, 4)
	48 aload_0 (2, 4)
	49 iload_3 (2, 4)
	50 iload (2, 4)
	51 #4 (2, 4)
	52 invokeinterface (2, 4)
	53 org/apache/commons/math3/linear/RealMatrix.mueff:D (2, 4)
	55 0 (2, 4)
	57 aload_1 (2, 4)
	58 iload_3 (2, 4)
	59 iload (2, 4)
	60 #4 (2, 4)
	61 invokeinterface (2, 4)
	62 org/apache/commons/math3/linear/RealMatrix.mueff:D (2, 4)
	64 0 (2, 4)
	66 dmul (2, 4)
	67 dastore (2, 4)
	68 iinc (2, 4)
	69 #4 (2, 4)
	70 -89 (2, 4)
	71 goto (2, 4)
	72 -39 (2, 4)
	74 iinc (2, 4)
	75 #3 (2, 4)
	76 -89 (2, 4)
	77 goto (2, 4)
	78 -58 (2, 4)
	80 new (1, 4)
	81 org/apache/commons/math3/linear/Array2DRowRealMatrix (1, 4)
	83 dup (1, 4)
	84 aload_2 (1, 4)
	85 iconst_0 (1, 4)
	86 invokespecial (1, 4)
	87 org/apache/commons/math3/linear/Array2DRowRealMatrix.<init>:([[DZ)V (1, 4)
	89 areturn (1, 4)

Method: divide
	0 aload_0 (0, 0)
	1 invokeinterface (0, 0)
	2 org/apache/commons/math3/linear/RealMatrix.getColumnDimension:()I (0, 0)
	4 0 (0, 0)
	6 aload_0 (0, 0)
	7 invokeinterface (0, 0)
	8 org/apache/commons/math3/linear/RealMatrix.fill:([DD)V (0, 0)
	10 0 (0, 0)
	12 multianewarray (0, 0)
	13 [[D (0, 0)
	15 77 (0, 0)
	16 astore_2 (0, 0)
	17 iconst_0 (1, 4)
	18 istore_3 (1, 4)
	19 iload_3 (1, 4)
	20 aload_0 (1, 4)
	21 invokeinterface (1, 4)
	22 org/apache/commons/math3/linear/RealMatrix.getColumnDimension:()I (1, 4)
	24 0 (1, 4)
	26 if_icmpge (1, 4)
	27 54 (1, 4)
	29 iconst_0 (2, 4)
	30 istore (2, 4)
	31 #4 (2, 4)
	32 iload (2, 4)
	33 #4 (2, 4)
	34 aload_0 (2, 4)
	35 invokeinterface (2, 4)
	36 org/apache/commons/math3/linear/RealMatrix.fill:([DD)V (2, 4)
	38 0 (2, 4)
	40 if_icmpge (2, 4)
	41 34 (2, 4)
	43 aload_2 (2, 4)
	44 iload_3 (2, 4)
	45 aaload (2, 4)
	46 iload (2, 4)
	47 #4 (2, 4)
	48 aload_0 (2, 4)
	49 iload_3 (2, 4)
	50 iload (2, 4)
	51 #4 (2, 4)
	52 invokeinterface (2, 4)
	53 org/apache/commons/math3/linear/RealMatrix.mueff:D (2, 4)
	55 0 (2, 4)
	57 aload_1 (2, 4)
	58 iload_3 (2, 4)
	59 iload (2, 4)
	60 #4 (2, 4)
	61 invokeinterface (2, 4)
	62 org/apache/commons/math3/linear/RealMatrix.mueff:D (2, 4)
	64 0 (2, 4)
	66 ddiv (2, 4)
	67 dastore (2, 4)
	68 iinc (2, 4)
	69 #4 (2, 4)
	70 -89 (2, 4)
	71 goto (2, 4)
	72 -39 (2, 4)
	74 iinc (2, 4)
	75 #3 (2, 4)
	76 -89 (2, 4)
	77 goto (2, 4)
	78 -58 (2, 4)
	80 new (1, 4)
	81 org/apache/commons/math3/linear/Array2DRowRealMatrix (1, 4)
	83 dup (1, 4)
	84 aload_2 (1, 4)
	85 iconst_0 (1, 4)
	86 invokespecial (1, 4)
	87 org/apache/commons/math3/linear/Array2DRowRealMatrix.<init>:([[DZ)V (1, 4)
	89 areturn (1, 4)

Method: selectColumns
	0 aload_0 (0, 0)
	1 invokeinterface (0, 0)
	2 org/apache/commons/math3/linear/RealMatrix.getColumnDimension:()I (0, 0)
	4 0 (0, 0)
	6 aload_1 (0, 0)
	7 arraylength (0, 0)
	8 multianewarray (0, 0)
	9 [[D (0, 0)
	11 77 (0, 0)
	12 astore_2 (0, 0)
	13 iconst_0 (1, 4)
	14 istore_3 (1, 4)
	15 iload_3 (1, 4)
	16 aload_0 (1, 4)
	17 invokeinterface (1, 4)
	18 org/apache/commons/math3/linear/RealMatrix.getColumnDimension:()I (1, 4)
	20 0 (1, 4)
	22 if_icmpge (1, 4)
	23 42 (1, 4)
	25 iconst_0 (2, 4)
	26 istore (2, 4)
	27 #4 (2, 4)
	28 iload (2, 4)
	29 #4 (2, 4)
	30 aload_1 (2, 4)
	31 arraylength (2, 4)
	32 if_icmpge (2, 4)
	33 26 (2, 4)
	35 aload_2 (2, 4)
	36 iload_3 (2, 4)
	37 aaload (2, 4)
	38 iload (2, 4)
	39 #4 (2, 4)
	40 aload_0 (2, 4)
	41 iload_3 (2, 4)
	42 aload_1 (2, 4)
	43 iload (2, 4)
	44 #4 (2, 4)
	45 iaload (2, 4)
	46 invokeinterface (2, 4)
	47 org/apache/commons/math3/linear/RealMatrix.mueff:D (2, 4)
	49 0 (2, 4)
	51 dastore (2, 4)
	52 iinc (2, 4)
	53 #4 (2, 4)
	54 -89 (2, 4)
	55 goto (2, 4)
	56 -27 (2, 4)
	58 iinc (2, 4)
	59 #3 (2, 4)
	60 -89 (2, 4)
	61 goto (2, 4)
	62 -46 (2, 4)
	64 new (1, 4)
	65 org/apache/commons/math3/linear/Array2DRowRealMatrix (1, 4)
	67 dup (1, 4)
	68 aload_2 (1, 4)
	69 iconst_0 (1, 4)
	70 invokespecial (1, 4)
	71 org/apache/commons/math3/linear/Array2DRowRealMatrix.<init>:([[DZ)V (1, 4)
	73 areturn (1, 4)

Method: triu
	0 aload_0 (0, 0)
	1 invokeinterface (0, 0)
	2 org/apache/commons/math3/linear/RealMatrix.getColumnDimension:()I (0, 0)
	4 0 (0, 0)
	6 aload_0 (0, 0)
	7 invokeinterface (0, 0)
	8 org/apache/commons/math3/linear/RealMatrix.fill:([DD)V (0, 0)
	10 0 (0, 0)
	12 multianewarray (0, 0)
	13 [[D (0, 0)
	15 77 (0, 0)
	16 astore_2 (0, 0)
	17 iconst_0 (1, 4)
	18 istore_3 (1, 4)
	19 iload_3 (1, 4)
	20 aload_0 (1, 4)
	21 invokeinterface (1, 4)
	22 org/apache/commons/math3/linear/RealMatrix.getColumnDimension:()I (1, 4)
	24 0 (1, 4)
	26 if_icmpge (1, 4)
	27 56 (1, 4)
	29 iconst_0 (2, 4)
	30 istore (2, 4)
	31 #4 (2, 4)
	32 iload (2, 4)
	33 #4 (2, 4)
	34 aload_0 (2, 4)
	35 invokeinterface (2, 4)
	36 org/apache/commons/math3/linear/RealMatrix.fill:([DD)V (2, 4)
	38 0 (2, 4)
	40 if_icmpge (2, 4)
	41 36 (2, 4)
	43 aload_2 (2, 4)
	44 iload_3 (2, 4)
	45 aaload (2, 4)
	46 iload (2, 4)
	47 #4 (2, 4)
	48 iload_3 (2, 4)
	49 iload (2, 4)
	50 #4 (2, 4)
	51 iload_1 (2, 4)
	52 isub (2, 4)
	53 if_icmpgt (2, 4)
	54 15 (2, 4)
	56 aload_0 (2, 4)
	57 iload_3 (2, 4)
	58 iload (2, 4)
	59 #4 (2, 4)
	60 invokeinterface (2, 4)
	61 org/apache/commons/math3/linear/RealMatrix.mueff:D (2, 4)
	63 0 (2, 4)
	65 goto (2, 4)
	66 4 (2, 4)
	68 dconst_0 (2, 4)
	69 dastore (2, 4)
	70 iinc (2, 4)
	71 #4 (2, 4)
	72 -89 (2, 4)
	73 goto (2, 4)
	74 -41 (2, 4)
	76 iinc (2, 4)
	77 #3 (2, 4)
	78 -89 (2, 4)
	79 goto (2, 4)
	80 -60 (2, 4)
	82 new (1, 4)
	83 org/apache/commons/math3/linear/Array2DRowRealMatrix (1, 4)
	85 dup (1, 4)
	86 aload_2 (1, 4)
	87 iconst_0 (1, 4)
	88 invokespecial (1, 4)
	89 org/apache/commons/math3/linear/Array2DRowRealMatrix.<init>:([[DZ)V (1, 4)
	91 areturn (1, 4)

Method: sumRows
	0 iconst_1 (0, 0)
	1 aload_0 (0, 0)
	2 invokeinterface (0, 0)
	3 org/apache/commons/math3/linear/RealMatrix.fill:([DD)V (0, 0)
	5 0 (0, 0)
	7 multianewarray (0, 0)
	8 [[D (0, 0)
	10 76 (0, 0)
	11 astore_1 (0, 0)
	12 iconst_0 (1, 4)
	13 istore_2 (1, 4)
	14 iload_2 (1, 4)
	15 aload_0 (1, 4)
	16 invokeinterface (1, 4)
	17 org/apache/commons/math3/linear/RealMatrix.fill:([DD)V (1, 4)
	19 0 (1, 4)
	21 if_icmpge (1, 4)
	22 49 (1, 4)
	24 dconst_0 (1, 4)
	25 dstore_3 (1, 4)
	26 iconst_0 (2, 4)
	27 istore (2, 4)
	28 #5 (2, 4)
	29 iload (2, 4)
	30 #5 (2, 4)
	31 aload_0 (2, 4)
	32 invokeinterface (2, 4)
	33 org/apache/commons/math3/linear/RealMatrix.getColumnDimension:()I (2, 4)
	35 0 (2, 4)
	37 if_icmpge (2, 4)
	38 21 (2, 4)
	40 dload_3 (2, 4)
	41 aload_0 (2, 4)
	42 iload (2, 4)
	43 #5 (2, 4)
	44 iload_2 (2, 4)
	45 invokeinterface (2, 4)
	46 org/apache/commons/math3/linear/RealMatrix.mueff:D (2, 4)
	48 0 (2, 4)
	50 dadd (2, 4)
	51 dstore_3 (2, 4)
	52 iinc (2, 4)
	53 #5 (2, 4)
	54 -89 (2, 4)
	55 goto (2, 4)
	56 -26 (2, 4)
	58 aload_1 (1, 4)
	59 iconst_0 (1, 4)
	60 aaload (1, 4)
	61 iload_2 (1, 4)
	62 dload_3 (1, 4)
	63 dastore (1, 4)
	64 iinc (1, 4)
	65 #2 (1, 4)
	66 -89 (1, 4)
	67 goto (1, 4)
	68 -53 (1, 4)
	70 new (0, 0)
	71 org/apache/commons/math3/linear/Array2DRowRealMatrix (0, 0)
	73 dup (0, 0)
	74 aload_1 (0, 0)
	75 iconst_0 (0, 0)
	76 invokespecial (0, 0)
	77 org/apache/commons/math3/linear/Array2DRowRealMatrix.<init>:([[DZ)V (0, 0)
	79 areturn (0, 0)

Method: diag
	0 aload_0 (1, 1)
	1 invokeinterface (1, 1)
	2 org/apache/commons/math3/linear/RealMatrix.fill:([DD)V (1, 1)
	4 0 (1, 1)
	6 iconst_1 (1, 1)
	7 if_icmpne (1, 1)
	8 61 (1, 1)
	10 aload_0 (1, 1)
	11 invokeinterface (1, 1)
	12 org/apache/commons/math3/linear/RealMatrix.getColumnDimension:()I (1, 1)
	14 0 (1, 1)
	16 aload_0 (1, 1)
	17 invokeinterface (1, 1)
	18 org/apache/commons/math3/linear/RealMatrix.getColumnDimension:()I (1, 1)
	20 0 (1, 1)
	22 multianewarray (1, 1)
	23 [[D (1, 1)
	25 76 (1, 1)
	26 astore_1 (1, 1)
	27 iconst_0 (2, 4)
	28 istore_2 (2, 4)
	29 iload_2 (2, 4)
	30 aload_0 (2, 4)
	31 invokeinterface (2, 4)
	32 org/apache/commons/math3/linear/RealMatrix.getColumnDimension:()I (2, 4)
	34 0 (2, 4)
	36 if_icmpge (2, 4)
	37 22 (2, 4)
	39 aload_1 (2, 4)
	40 iload_2 (2, 4)
	41 aaload (2, 4)
	42 iload_2 (2, 4)
	43 aload_0 (2, 4)
	44 iload_2 (2, 4)
	45 iconst_0 (2, 4)
	46 invokeinterface (2, 4)
	47 org/apache/commons/math3/linear/RealMatrix.mueff:D (2, 4)
	49 0 (2, 4)
	51 dastore (2, 4)
	52 iinc (2, 4)
	53 #2 (2, 4)
	54 -89 (2, 4)
	55 goto (2, 4)
	56 -26 (2, 4)
	58 new (1, 1)
	59 org/apache/commons/math3/linear/Array2DRowRealMatrix (1, 1)
	61 dup (1, 1)
	62 aload_1 (1, 1)
	63 iconst_0 (1, 1)
	64 invokespecial (1, 1)
	65 org/apache/commons/math3/linear/Array2DRowRealMatrix.<init>:([[DZ)V (1, 1)
	67 areturn (1, 1)
	68 aload_0 (1, 2)
	69 invokeinterface (1, 2)
	70 org/apache/commons/math3/linear/RealMatrix.getColumnDimension:()I (1, 2)
	72 0 (1, 2)
	74 iconst_1 (1, 2)
	75 multianewarray (1, 2)
	76 [[D (1, 2)
	78 76 (1, 2)
	79 astore_1 (1, 2)
	80 iconst_0 (2, 4)
	81 istore_2 (2, 4)
	82 iload_2 (2, 4)
	83 aload_0 (2, 4)
	84 invokeinterface (2, 4)
	85 org/apache/commons/math3/linear/RealMatrix.fill:([DD)V (2, 4)
	87 0 (2, 4)
	89 if_icmpge (2, 4)
	90 22 (2, 4)
	92 aload_1 (2, 4)
	93 iload_2 (2, 4)
	94 aaload (2, 4)
	95 iconst_0 (2, 4)
	96 aload_0 (2, 4)
	97 iload_2 (2, 4)
	98 iload_2 (2, 4)
	99 invokeinterface (2, 4)
	100 org/apache/commons/math3/linear/RealMatrix.mueff:D (2, 4)
	102 0 (2, 4)
	104 dastore (2, 4)
	105 iinc (2, 4)
	106 #2 (2, 4)
	107 -89 (2, 4)
	108 goto (2, 4)
	109 -26 (2, 4)
	111 new (1, 2)
	112 org/apache/commons/math3/linear/Array2DRowRealMatrix (1, 2)
	114 dup (1, 2)
	115 aload_1 (1, 2)
	116 iconst_0 (1, 2)
	117 invokespecial (1, 2)
	118 org/apache/commons/math3/linear/Array2DRowRealMatrix.<init>:([[DZ)V (1, 2)
	120 areturn (1, 2)

Method: copyColumn
	0 iconst_0 (1, 4)
	1 istore (1, 4)
	2 #4 (1, 4)
	3 iload (1, 4)
	4 #4 (1, 4)
	5 aload_0 (1, 4)
	6 invokeinterface (1, 4)
	7 org/apache/commons/math3/linear/RealMatrix.getColumnDimension:()I (1, 4)
	9 0 (1, 4)
	11 if_icmpge (1, 4)
	12 27 (1, 4)
	14 aload_2 (1, 4)
	15 iload (1, 4)
	16 #4 (1, 4)
	17 iload_3 (1, 4)
	18 aload_0 (1, 4)
	19 iload (1, 4)
	20 #4 (1, 4)
	21 iload_1 (1, 4)
	22 invokeinterface (1, 4)
	23 org/apache/commons/math3/linear/RealMatrix.mueff:D (1, 4)
	25 0 (1, 4)
	27 invokeinterface (1, 4)
	28 org/apache/commons/math3/linear/RealMatrix.org/apache/commons/math3/optimization/direct/CMAESOptimizer$DoubleIndex (1, 4)
	30 0 (1, 4)
	32 iinc (1, 4)
	33 #4 (1, 4)
	34 -89 (1, 4)
	35 goto (1, 4)
	36 -32 (1, 4)
	38 return (0, 0)

Method: ones
	0 iload_0 (0, 0)
	1 iload_1 (0, 0)
	2 multianewarray (0, 0)
	3 [[D (0, 0)
	5 77 (0, 0)
	6 astore_2 (0, 0)
	7 iconst_0 (1, 4)
	8 istore_3 (1, 4)
	9 iload_3 (1, 4)
	10 iload_0 (1, 4)
	11 if_icmpge (1, 4)
	12 16 (1, 4)
	14 aload_2 (1, 4)
	15 iload_3 (1, 4)
	16 aaload (1, 4)
	17 dconst_1 (1, 4)
	18 invokestatic (1, 4)
	19 java/util/Arrays.fill:([DD)V (1, 4)
	21 iinc (1, 4)
	22 #3 (1, 4)
	23 -89 (1, 4)
	24 goto (1, 4)
	25 -15 (1, 4)
	27 new (0, 0)
	28 org/apache/commons/math3/linear/Array2DRowRealMatrix (0, 0)
	30 dup (0, 0)
	31 aload_2 (0, 0)
	32 iconst_0 (0, 0)
	33 invokespecial (0, 0)
	34 org/apache/commons/math3/linear/Array2DRowRealMatrix.<init>:([[DZ)V (0, 0)
	36 areturn (0, 0)

Method: eye
	0 iload_0 (0, 0)
	1 iload_1 (0, 0)
	2 multianewarray (0, 0)
	3 [[D (0, 0)
	5 77 (0, 0)
	6 astore_2 (0, 0)
	7 iconst_0 (1, 4)
	8 istore_3 (1, 4)
	9 iload_3 (1, 4)
	10 iload_0 (1, 4)
	11 if_icmpge (1, 4)
	12 20 (1, 4)
	14 iload_3 (2, 1)
	15 iload_1 (2, 1)
	16 if_icmpge (2, 1)
	17 9 (2, 1)
	19 aload_2 (2, 1)
	20 iload_3 (2, 1)
	21 aaload (2, 1)
	22 iload_3 (2, 1)
	23 dconst_1 (2, 1)
	24 dastore (2, 1)
	25 iinc (2, 1)
	26 #3 (2, 1)
	27 -89 (2, 1)
	28 goto (2, 1)
	29 -19 (2, 1)
	31 new (1, 4)
	32 org/apache/commons/math3/linear/Array2DRowRealMatrix (1, 4)
	34 dup (1, 4)
	35 aload_2 (1, 4)
	36 iconst_0 (1, 4)
	37 invokespecial (1, 4)
	38 org/apache/commons/math3/linear/Array2DRowRealMatrix.<init>:([[DZ)V (1, 4)
	40 areturn (1, 4)

Method: zeros
	0 new (0, 0)
	1 org/apache/commons/math3/linear/Array2DRowRealMatrix (0, 0)
	3 dup (0, 0)
	4 iload_0 (0, 0)
	5 iload_1 (0, 0)
	6 invokespecial (0, 0)
	7 org/apache/commons/math3/linear/Array2DRowRealMatrix.<init>:(II)V (0, 0)
	9 areturn (0, 0)

Method: repmat
	0 aload_0 (0, 0)
	1 invokeinterface (0, 0)
	2 org/apache/commons/math3/linear/RealMatrix.getColumnDimension:()I (0, 0)
	4 0 (0, 0)
	6 istore_3 (0, 0)
	7 aload_0 (0, 0)
	8 invokeinterface (0, 0)
	9 org/apache/commons/math3/linear/RealMatrix.fill:([DD)V (0, 0)
	11 0 (0, 0)
	13 istore (0, 0)
	14 #4 (0, 0)
	15 iload_1 (0, 0)
	16 iload_3 (0, 0)
	17 imul (0, 0)
	18 iload_2 (0, 0)
	19 iload (0, 0)
	20 #4 (0, 0)
	21 imul (0, 0)
	22 multianewarray (0, 0)
	23 [[D (0, 0)
	25 58 (0, 0)
	26 astore (0, 0)
	27 #5 (0, 0)
	28 iconst_0 (1, 4)
	29 istore (1, 4)
	30 #6 (1, 4)
	31 iload (1, 4)
	32 #6 (1, 4)
	33 iload_1 (1, 4)
	34 iload_3 (1, 4)
	35 imul (1, 4)
	36 if_icmpge (1, 4)
	37 50 (1, 4)
	39 iconst_0 (2, 4)
	40 istore (2, 4)
	41 #7 (2, 4)
	42 iload (2, 4)
	43 #7 (2, 4)
	44 iload_2 (2, 4)
	45 iload (2, 4)
	46 #4 (2, 4)
	47 imul (2, 4)
	48 if_icmpge (2, 4)
	49 32 (2, 4)
	51 aload (2, 4)
	52 #5 (2, 4)
	53 iload (2, 4)
	54 #6 (2, 4)
	55 aaload (2, 4)
	56 iload (2, 4)
	57 #7 (2, 4)
	58 aload_0 (2, 4)
	59 iload (2, 4)
	60 #6 (2, 4)
	61 iload_3 (2, 4)
	62 irem (2, 4)
	63 iload (2, 4)
	64 #7 (2, 4)
	65 iload (2, 4)
	66 #4 (2, 4)
	67 irem (2, 4)
	68 invokeinterface (2, 4)
	69 org/apache/commons/math3/linear/RealMatrix.mueff:D (2, 4)
	71 0 (2, 4)
	73 dastore (2, 4)
	74 iinc (2, 4)
	75 #7 (2, 4)
	76 -89 (2, 4)
	77 goto (2, 4)
	78 -35 (2, 4)
	80 iinc (2, 4)
	81 #6 (2, 4)
	82 -89 (2, 4)
	83 goto (2, 4)
	84 -52 (2, 4)
	86 new (1, 4)
	87 org/apache/commons/math3/linear/Array2DRowRealMatrix (1, 4)
	89 dup (1, 4)
	90 aload (1, 4)
	91 #5 (1, 4)
	92 iconst_0 (1, 4)
	93 invokespecial (1, 4)
	94 org/apache/commons/math3/linear/Array2DRowRealMatrix.<init>:([[DZ)V (1, 4)
	96 areturn (1, 4)

Method: sequence
	0 dload_2 (0, 0)
	1 dload_0 (0, 0)
	2 dsub (0, 0)
	3 dload (0, 0)
	4 #4 (0, 0)
	5 ddiv (0, 0)
	6 dconst_1 (0, 0)
	7 dadd (0, 0)
	8 d2i (0, 0)
	9 istore (0, 0)
	10 #6 (0, 0)
	11 iload (0, 0)
	12 #6 (0, 0)
	13 iconst_1 (0, 0)
	14 multianewarray (0, 0)
	15 [[D (0, 0)
	17 58 (0, 0)
	18 astore (0, 0)
	19 #7 (0, 0)
	20 dload_0 (0, 0)
	21 dstore (0, 0)
	22 #8 (0, 0)
	23 iconst_0 (1, 4)
	24 istore (1, 4)
	25 #10 (1, 4)
	26 iload (1, 4)
	27 #10 (1, 4)
	28 iload (1, 4)
	29 #6 (1, 4)
	30 if_icmpge (1, 4)
	31 25 (1, 4)
	33 aload (1, 4)
	34 #7 (1, 4)
	35 iload (1, 4)
	36 #10 (1, 4)
	37 aaload (1, 4)
	38 iconst_0 (1, 4)
	39 dload (1, 4)
	40 #8 (1, 4)
	41 dastore (1, 4)
	42 dload (1, 4)
	43 #8 (1, 4)
	44 dload (1, 4)
	45 #4 (1, 4)
	46 dadd (1, 4)
	47 dstore (1, 4)
	48 #8 (1, 4)
	49 iinc (1, 4)
	50 #10 (1, 4)
	51 -89 (1, 4)
	52 goto (1, 4)
	53 -26 (1, 4)
	55 new (0, 0)
	56 org/apache/commons/math3/linear/Array2DRowRealMatrix (0, 0)
	58 dup (0, 0)
	59 aload (0, 0)
	60 #7 (0, 0)
	61 iconst_0 (0, 0)
	62 invokespecial (0, 0)
	63 org/apache/commons/math3/linear/Array2DRowRealMatrix.<init>:([[DZ)V (0, 0)
	65 areturn (0, 0)

Method: max
	0 ldc2_w (0, 0)
	1 -1.7976931348623157e+308 (0, 0)
	3 dstore_1 (0, 0)
	4 iconst_0 (1, 4)
	5 istore_3 (1, 4)
	6 iload_3 (1, 4)
	7 aload_0 (1, 4)
	8 arraylength (1, 4)
	9 if_icmpge (1, 4)
	10 21 (1, 4)
	12 dload_1 (2, 1)
	13 aload_0 (2, 1)
	14 iload_3 (2, 1)
	15 daload (2, 1)
	16 dcmpg (2, 1)
	17 ifge (2, 1)
	18 7 (2, 1)
	20 aload_0 (2, 1)
	21 iload_3 (2, 1)
	22 daload (2, 1)
	23 dstore_1 (2, 1)
	24 iinc (2, 1)
	25 #3 (2, 1)
	26 -89 (2, 1)
	27 goto (2, 1)
	28 -21 (2, 1)
	30 dload_1 (1, 4)
	31 dreturn (1, 4)

Method: min
	0 ldc2_w (0, 0)
	1 1.7976931348623157e+308 (0, 0)
	3 dstore_1 (0, 0)
	4 iconst_0 (1, 4)
	5 istore_3 (1, 4)
	6 iload_3 (1, 4)
	7 aload_0 (1, 4)
	8 arraylength (1, 4)
	9 if_icmpge (1, 4)
	10 21 (1, 4)
	12 dload_1 (2, 1)
	13 aload_0 (2, 1)
	14 iload_3 (2, 1)
	15 daload (2, 1)
	16 dcmpl (2, 1)
	17 ifle (2, 1)
	18 7 (2, 1)
	20 aload_0 (2, 1)
	21 iload_3 (2, 1)
	22 daload (2, 1)
	23 dstore_1 (2, 1)
	24 iinc (2, 1)
	25 #3 (2, 1)
	26 -89 (2, 1)
	27 goto (2, 1)
	28 -21 (2, 1)
	30 dload_1 (1, 4)
	31 dreturn (1, 4)

Method: inverse
	0 aload_0 (0, 0)
	1 arraylength (0, 0)
	2 newarray (0, 0)
	3 10 (0, 0)
	4 astore_1 (0, 0)
	5 iconst_0 (1, 4)
	6 istore_2 (1, 4)
	7 iload_2 (1, 4)
	8 aload_0 (1, 4)
	9 arraylength (1, 4)
	10 if_icmpge (1, 4)
	11 15 (1, 4)
	13 aload_1 (1, 4)
	14 aload_0 (1, 4)
	15 iload_2 (1, 4)
	16 iaload (1, 4)
	17 iload_2 (1, 4)
	18 iastore (1, 4)
	19 iinc (1, 4)
	20 #2 (1, 4)
	21 -89 (1, 4)
	22 goto (1, 4)
	23 -15 (1, 4)
	25 aload_1 (0, 0)
	26 areturn (0, 0)

Method: reverse
	0 aload_0 (0, 0)
	1 arraylength (0, 0)
	2 newarray (0, 0)
	3 10 (0, 0)
	4 astore_1 (0, 0)
	5 iconst_0 (1, 4)
	6 istore_2 (1, 4)
	7 iload_2 (1, 4)
	8 aload_0 (1, 4)
	9 arraylength (1, 4)
	10 if_icmpge (1, 4)
	11 20 (1, 4)
	13 aload_1 (1, 4)
	14 iload_2 (1, 4)
	15 aload_0 (1, 4)
	16 aload_0 (1, 4)
	17 arraylength (1, 4)
	18 iload_2 (1, 4)
	19 isub (1, 4)
	20 iconst_1 (1, 4)
	21 isub (1, 4)
	22 iaload (1, 4)
	23 iastore (1, 4)
	24 iinc (1, 4)
	25 #2 (1, 4)
	26 -89 (1, 4)
	27 goto (1, 4)
	28 -20 (1, 4)
	30 aload_1 (0, 0)
	31 areturn (0, 0)

Method: randn
	0 iload_1 (0, 0)
	1 newarray (0, 0)
	2 7 (0, 0)
	3 astore_2 (0, 0)
	4 iconst_0 (1, 4)
	5 istore_3 (1, 4)
	6 iload_3 (1, 4)
	7 iload_1 (1, 4)
	8 if_icmpge (1, 4)
	9 21 (1, 4)
	11 aload_2 (1, 4)
	12 iload_3 (1, 4)
	13 aload_0 (1, 4)
	14 getfield (1, 4)
	15 org/apache/commons/math3/optimization/direct/CMAESOptimizer.random:Lorg/apache/commons/math3/random/RandomGenerator; (1, 4)
	17 invokeinterface (1, 4)
	18 org/apache/commons/math3/random/RandomGenerator.org/apache/commons/math3/random/MersenneTwister (1, 4)
	20 0 (1, 4)
	22 dastore (1, 4)
	23 iinc (1, 4)
	24 #3 (1, 4)
	25 -89 (1, 4)
	26 goto (1, 4)
	27 -20 (1, 4)
	29 aload_2 (0, 0)
	30 areturn (0, 0)

Method: randn1
	0 iload_1 (0, 0)
	1 iload_2 (0, 0)
	2 multianewarray (0, 0)
	3 [[D (0, 0)
	5 78 (0, 0)
	6 astore_3 (0, 0)
	7 iconst_0 (1, 4)
	8 istore (1, 4)
	9 #4 (1, 4)
	10 iload (1, 4)
	11 #4 (1, 4)
	12 iload_1 (1, 4)
	13 if_icmpge (1, 4)
	14 40 (1, 4)
	16 iconst_0 (2, 4)
	17 istore (2, 4)
	18 #5 (2, 4)
	19 iload (2, 4)
	20 #5 (2, 4)
	21 iload_2 (2, 4)
	22 if_icmpge (2, 4)
	23 25 (2, 4)
	25 aload_3 (2, 4)
	26 iload (2, 4)
	27 #4 (2, 4)
	28 aaload (2, 4)
	29 iload (2, 4)
	30 #5 (2, 4)
	31 aload_0 (2, 4)
	32 getfield (2, 4)
	33 org/apache/commons/math3/optimization/direct/CMAESOptimizer.random:Lorg/apache/commons/math3/random/RandomGenerator; (2, 4)
	35 invokeinterface (2, 4)
	36 org/apache/commons/math3/random/RandomGenerator.org/apache/commons/math3/random/MersenneTwister (2, 4)
	38 0 (2, 4)
	40 dastore (2, 4)
	41 iinc (2, 4)
	42 #5 (2, 4)
	43 -89 (2, 4)
	44 goto (2, 4)
	45 -25 (2, 4)
	47 iinc (2, 4)
	48 #4 (2, 4)
	49 -89 (2, 4)
	50 goto (2, 4)
	51 -40 (2, 4)
	53 new (1, 4)
	54 org/apache/commons/math3/linear/Array2DRowRealMatrix (1, 4)
	56 dup (1, 4)
	57 aload_3 (1, 4)
	58 iconst_0 (1, 4)
	59 invokespecial (1, 4)
	60 org/apache/commons/math3/linear/Array2DRowRealMatrix.<init>:([[DZ)V (1, 4)
	62 areturn (1, 4)

Method: access$200
	0 aload_0 (0, 0)
	1 getfield (0, 0)
	2 org/apache/commons/math3/optimization/direct/CMAESOptimizer.isMinimize:Z (0, 0)
	4 ireturn (0, 0)

Method: <clinit>
	0 new (0, 0)
	1 org/apache/commons/math3/random/MersenneTwister (0, 0)
	3 dup (0, 0)
	4 invokespecial (0, 0)
	5 org/apache/commons/math3/random/MersenneTwister.<init>:()V (0, 0)
	7 putstatic (0, 0)
	8 org/apache/commons/math3/optimization/direct/CMAESOptimizer.DEFAULT_RANDOMGENERATOR:Lorg/apache/commons/math3/random/RandomGenerator; (0, 0)
	10 return (0, 0)

