Method: <init>
	0 aload_0 (0, 0)
	1 invokespecial (0, 0)
	4 aload_0 (0, 0)
	5 dload_1 (0, 0)
	6 putfield (0, 0)
	9 aload_0 (0, 0)
	10 iload_3 (0, 0)
	11 putfield (0, 0)
	14 return (0, 0)

Method: compareTo
	0 aload_0 (0, 0)
	1 aload_1 (0, 0)
	2 checkcast (0, 0)
	5 invokevirtual (0, 0)
	8 ireturn (0, 0)

Method: equals
	0 aload_0 (1, 1)
	1 aload_1 (1, 1)
	2 if_acmpne (1, 1)
	5 iconst_1 (1, 1)
	6 ireturn (1, 1)
	7 aload_1 (1, 1)
	8 instanceof (1, 1)
	11 ifeq (1, 1)
	14 aload_0 (1, 1)
	15 getfield (1, 1)
	18 aload_1 (1, 1)
	19 checkcast (1, 1)
	22 getfield (1, 1)
	25 invokestatic (1, 1)
	28 ifne (1, 1)
	31 iconst_1 (1, 1)
	32 goto (1, 1)
	35 iconst_0 (1, 1)
	36 ireturn (1, 1)
	37 iconst_0 (0, 0)
	38 ireturn (0, 0)

Method: hashCode
	0 aload_0 (0, 0)
	1 getfield (0, 0)
	4 invokestatic (0, 0)
	7 lstore_1 (0, 0)
	8 ldc2_w (0, 0)
	11 lload_1 (0, 0)
	12 bipush (0, 0)
	14 lushr (0, 0)
	15 lxor (0, 0)
	16 lload_1 (0, 0)
	17 lxor (0, 0)
	18 ldc2_w (0, 0)
	21 land (0, 0)
	22 l2i (0, 0)
	23 ireturn (0, 0)

Method: access$100
	0 aload_0 (0, 0)
	1 getfield (0, 0)
	4 ireturn (0, 0)

