Method: <init>
	0 aload_0 (0, 0)
	1 aload (0, 0)
	3 invokespecial (0, 0)
	6 aload_0 (0, 0)
	7 iconst_0 (0, 0)
	8 putfield (0, 0)
	11 aload_0 (0, 0)
	12 iconst_1 (0, 0)
	13 putfield (0, 0)
	16 aload_0 (0, 0)
	17 iconst_0 (0, 0)
	18 putfield (0, 0)
	21 aload_0 (0, 4)
	22 new (0, 4)
	25 dup (0, 4)
	26 invokespecial (0, 4)
	29 putfield (0, 4)
	32 aload_0 (0, 4)
	33 new (0, 4)
	36 dup (0, 4)
	37 invokespecial (0, 4)
	40 putfield (0, 4)
	43 aload_0 (0, 4)
	44 new (0, 4)
	47 dup (0, 4)
	48 invokespecial (0, 4)
	51 putfield (0, 4)
	54 aload_0 (0, 4)
	55 new (0, 4)
	58 dup (0, 4)
	59 invokespecial (0, 4)
	62 putfield (0, 4)
	65 aload_0 (1, 1)
	66 iload_1 (1, 1)
	67 putfield (1, 1)
	70 aload_0 (1, 1)
	71 dload_2 (1, 1)
	72 putfield (1, 1)
	75 aload_0 (1, 1)
	76 iload (1, 1)
	78 putfield (1, 1)
	81 aload_0 (1, 1)
	82 iload (1, 1)
	84 putfield (1, 1)
	87 aload_0 (1, 1)
	88 iload (1, 1)
	90 putfield (1, 1)
	93 aload_0 (1, 1)
	94 aload (1, 1)
	96 putfield (1, 1)
	99 aload_0 (1, 1)
	100 iload (1, 1)
	102 putfield (1, 1)
	105 return (0, 4)

Method: getStatisticsSigmaHistory
	0 aload_0 (0, 0)
	1 getfield (0, 0)
	4 areturn (0, 0)

Method: getStatisticsMeanHistory
	0 aload_0 (0, 0)
	1 getfield (0, 0)
	4 areturn (0, 0)

Method: getStatisticsFitnessHistory
	0 aload_0 (0, 0)
	1 getfield (0, 0)
	4 areturn (0, 0)

Method: getStatisticsDHistory
	0 aload_0 (0, 0)
	1 getfield (0, 0)
	4 areturn (0, 0)

Method: optimizeInternal
	0 aload_0 (0, 0)
	1 aload (0, 0)
	3 invokespecial (0, 0)
	6 aload_0 (0, 0)
	7 iload_1 (0, 0)
	8 aload_2 (0, 0)
	9 aload_3 (0, 0)
	10 aload (0, 0)
	12 invokespecial (0, 0)
	15 areturn (0, 0)

Method: doOptimize
	0 aload_0 (0, 0)
	1 invokespecial (0, 0)
	4 aload_0 (0, 0)
	5 aload_0 (0, 0)
	6 invokevirtual (0, 0)
	9 getstatic (0, 0)
	12 invokevirtual (0, 0)
	15 putfield (0, 0)
	18 new (0, 0)
	21 dup (0, 0)
	22 aload_0 (0, 0)
	23 invokespecial (0, 0)
	26 astore_1 (0, 0)
	27 aload_0 (0, 0)
	28 invokevirtual (0, 0)
	31 astore_2 (0, 0)
	32 aload_0 (0, 0)
	33 aload_2 (0, 0)
	34 arraylength (0, 0)
	35 putfield (0, 0)
	38 aload_0 (0, 0)
	39 aload_2 (0, 0)
	40 invokespecial (0, 0)
	43 aload_0 (0, 0)
	44 iconst_0 (0, 0)
	45 putfield (0, 0)
	48 aload_1 (0, 0)
	49 aload_2 (0, 0)
	50 invokevirtual (0, 0)
	53 dstore_3 (0, 0)
	54 aload_0 (0, 0)
	55 getfield (0, 0)
	58 dload_3 (0, 0)
	59 invokestatic (0, 0)
	62 new (0, 0)
	65 dup (0, 0)
	66 aload_0 (0, 0)
	67 invokevirtual (0, 0)
	70 aload_0 (0, 0)
	71 getfield (0, 0)
	74 ifeq (0, 0)
	77 dload_3 (0, 0)
	78 goto (0, 0)
	81 dload_3 (0, 0)
	82 dneg (0, 0)
	83 invokespecial (0, 0)
	86 astore (0, 0)
	88 aconst_null (0, 0)
	89 astore (0, 0)
	91 aload_0 (1, 4)
	92 iconst_1 (1, 4)
	93 putfield (1, 4)
	96 aload_0 (1, 4)
	97 getfield (1, 4)
	100 aload_0 (1, 4)
	101 getfield (1, 4)
	104 if_icmpgt (1, 4)
	107 aload_0 (1, 4)
	108 aload_0 (1, 4)
	109 getfield (1, 4)
	112 aload_0 (1, 4)
	113 getfield (1, 4)
	116 invokespecial (1, 4)
	119 astore (1, 4)
	121 aload_0 (1, 4)
	122 getfield (1, 4)
	125 aload_0 (1, 4)
	126 getfield (1, 4)
	129 invokestatic (1, 4)
	132 astore (1, 4)
	134 aload_0 (1, 4)
	135 getfield (1, 4)
	138 newarray (1, 4)
	140 astore (1, 4)
	142 iconst_0 (2, 4)
	143 istore (2, 4)
	145 iload (2, 4)
	147 aload_0 (2, 4)
	148 getfield (2, 4)
	151 if_icmpge (2, 4)
	154 aconst_null (2, 4)
	155 astore (2, 4)
	157 iconst_0 (3, 4)
	158 istore (3, 4)
	160 iload (3, 4)
	162 aload_0 (3, 4)
	163 getfield (3, 4)
	166 iconst_1 (3, 4)
	167 iadd (3, 4)
	168 if_icmpge (3, 4)
	171 aload_0 (4, 1)
	172 getfield (4, 1)
	175 ifgt (4, 1)
	178 aload_0 (4, 1)
	179 getfield (4, 1)
	182 aload_0 (4, 1)
	183 getfield (4, 1)
	186 aload (4, 1)
	188 iload (4, 1)
	190 invokeinterface (4, 1)
	195 invokeinterface (4, 1)
	200 aload_0 (4, 1)
	201 getfield (4, 1)
	204 invokeinterface (4, 1)
	209 invokeinterface (4, 1)
	214 astore (4, 1)
	216 goto (4, 1)
	219 aload_0 (4, 2)
	220 getfield (4, 2)
	223 aload_0 (4, 2)
	224 getfield (4, 2)
	227 aload (4, 2)
	229 iload (4, 2)
	231 invokeinterface (4, 2)
	236 invokestatic (4, 2)
	239 aload_0 (4, 2)
	240 getfield (4, 2)
	243 invokeinterface (4, 2)
	248 invokeinterface (4, 2)
	253 astore (4, 2)
	255 iload (3, 1)
	257 aload_0 (3, 1)
	258 getfield (3, 1)
	261 if_icmpge (3, 1)
	264 aload_1 (3, 1)
	265 aload (3, 1)
	267 iconst_0 (3, 1)
	268 invokeinterface (4, 1)
	273 invokevirtual (4, 1)
	276 ifeq (4, 1)
	279 goto (4, 1)
	282 aload (3, 4)
	284 iload (3, 4)
	286 aload_0 (3, 4)
	287 aload_0 (3, 4)
	288 getfield (3, 4)
	291 invokespecial (3, 4)
	294 invokeinterface (3, 4)
	299 iinc (3, 4)
	302 goto (3, 4)
	305 aload (2, 1)
	307 iconst_0 (2, 1)
	308 aload (2, 1)
	310 iload (2, 1)
	312 invokestatic (2, 1)
	315 aload (3, 1)
	317 iload (3, 1)
	319 aload_1 (3, 1)
	320 aload (3, 1)
	322 iload (3, 1)
	324 invokeinterface (3, 1)
	329 invokevirtual (3, 1)
	332 dastore (3, 1)
	333 goto (2, 4)
	336 astore (2, 4)
	338 goto (2, 4)
	341 iinc (2, 4)
	344 goto (2, 4)
	347 aload_0 (1, 4)
	348 aload (1, 4)
	350 invokespecial (1, 4)
	353 astore (1, 4)
	355 aload_0 (1, 4)
	356 getfield (1, 4)
	359 astore (1, 4)
	361 aload (1, 4)
	363 aload (1, 4)
	365 aload_0 (1, 4)
	366 getfield (1, 4)
	369 invokestatic (1, 4)
	372 invokestatic (1, 4)
	375 astore (1, 4)
	377 aload_0 (1, 4)
	378 aload (1, 4)
	380 aload_0 (1, 4)
	381 getfield (1, 4)
	384 invokeinterface (1, 4)
	389 putfield (1, 4)
	392 aload (1, 4)
	394 aload (1, 4)
	396 aload_0 (1, 4)
	397 getfield (1, 4)
	400 invokestatic (1, 4)
	403 invokestatic (1, 4)
	406 astore (1, 4)
	408 aload (1, 4)
	410 aload_0 (1, 4)
	411 getfield (1, 4)
	414 invokeinterface (1, 4)
	419 astore (1, 4)
	421 aload_0 (1, 4)
	422 aload (1, 4)
	424 aload (1, 4)
	426 invokespecial (1, 4)
	429 istore (1, 4)
	431 aload_0 (2, 1)
	432 getfield (2, 1)
	435 ifgt (2, 1)
	438 aload_0 (2, 1)
	439 iload (2, 1)
	441 aload (2, 1)
	443 aload (2, 1)
	445 aload (2, 1)
	447 aload (2, 1)
	449 invokespecial (2, 1)
	452 goto (2, 1)
	455 aload_0 (2, 2)
	456 iload (2, 2)
	458 aload (2, 2)
	460 invokespecial (2, 2)
	463 aload_0 (1, 1)
	464 dup (1, 1)
	465 getfield (1, 1)
	468 dconst_1 (1, 1)
	469 aload_0 (1, 1)
	470 getfield (1, 1)
	473 aload_0 (1, 1)
	474 getfield (1, 1)
	477 ddiv (1, 1)
	478 dconst_1 (1, 1)
	479 dsub (1, 1)
	480 aload_0 (1, 1)
	481 getfield (1, 1)
	484 dmul (1, 1)
	485 aload_0 (1, 1)
	486 getfield (1, 1)
	489 ddiv (1, 1)
	490 invokestatic (1, 1)
	493 invokestatic (1, 1)
	496 dmul (1, 1)
	497 putfield (1, 1)
	500 aload (1, 1)
	502 aload (1, 1)
	504 iconst_0 (1, 1)
	505 iaload (1, 1)
	506 daload (1, 1)
	507 dstore (1, 1)
	509 aload (1, 1)
	511 aload (1, 1)
	513 aload (1, 1)
	515 arraylength (1, 1)
	516 iconst_1 (1, 1)
	517 isub (1, 1)
	518 iaload (1, 1)
	519 daload (1, 1)
	520 dstore (1, 1)
	522 dload_3 (2, 1)
	523 dload (2, 1)
	525 dcmpl (2, 1)
	526 ifle (2, 1)
	529 dload (2, 1)
	531 dstore_3 (2, 1)
	532 aload (2, 1)
	534 astore (2, 1)
	536 new (2, 1)
	539 dup (2, 1)
	540 aload_1 (2, 1)
	541 aload (2, 1)
	543 iconst_0 (2, 1)
	544 invokeinterface (2, 1)
	549 invokestatic (2, 1)
	552 aload_0 (2, 1)
	553 getfield (2, 1)
	556 ifeq (2, 1)
	559 dload (2, 1)
	561 goto (2, 1)
	564 dload (2, 1)
	566 dneg (2, 1)
	567 invokespecial (2, 1)
	570 astore (2, 1)
	572 aload_0 (2, 1)
	573 invokevirtual (2, 1)
	576 ifnull (2, 1)
	579 aload (2, 1)
	581 ifnull (2, 1)
	584 aload_0 (2, 1)
	585 invokevirtual (3, 1)
	588 aload_0 (3, 1)
	589 getfield (3, 1)
	592 aload (3, 1)
	594 aload (3, 1)
	596 invokeinterface (3, 1)
	601 ifeq (3, 1)
	604 goto (3, 1)
	607 aload_0 (2, 1)
	608 getfield (2, 1)
	611 dconst_0 (2, 1)
	612 dcmpl (2, 1)
	613 ifeq (2, 1)
	616 dload (2, 1)
	618 aload_0 (2, 1)
	619 getfield (2, 1)
	622 ifeq (2, 1)
	625 aload_0 (2, 1)
	626 getfield (2, 1)
	629 goto (2, 1)
	632 aload_0 (2, 1)
	633 getfield (2, 1)
	636 dneg (2, 1)
	637 dcmpg (2, 1)
	638 ifge (2, 1)
	641 goto (2, 1)
	644 aload_0 (1, 1)
	645 getfield (1, 1)
	648 invokestatic (1, 1)
	651 iconst_0 (1, 1)
	652 invokeinterface (1, 1)
	657 astore (1, 1)
	659 aload_0 (1, 1)
	660 getfield (1, 1)
	663 iconst_0 (1, 1)
	664 invokeinterface (1, 1)
	669 astore (1, 1)
	671 iconst_0 (2, 4)
	672 istore (2, 4)
	674 iload (2, 4)
	676 aload_0 (2, 4)
	677 getfield (2, 4)
	680 if_icmpge (2, 4)
	683 aload_0 (3, 1)
	684 getfield (3, 1)
	687 aload (3, 1)
	689 iload (3, 1)
	691 daload (3, 1)
	692 invokestatic (3, 1)
	695 aload (3, 1)
	697 iload (3, 1)
	699 daload (3, 1)
	700 invokestatic (3, 1)
	703 dmul (3, 1)
	704 aload_0 (3, 1)
	705 getfield (3, 1)
	708 dcmpl (3, 1)
	709 ifle (3, 1)
	712 goto (3, 1)
	715 iload (3, 1)
	717 aload_0 (3, 1)
	718 getfield (3, 1)
	721 iconst_1 (3, 1)
	722 isub (3, 1)
	723 if_icmplt (3, 1)
	726 goto (3, 1)
	729 iinc (3, 1)
	732 goto (3, 1)
	735 iconst_0 (3, 4)
	736 istore (3, 4)
	738 iload (3, 4)
	740 aload_0 (3, 4)
	741 getfield (3, 4)
	744 if_icmpge (3, 4)
	747 aload_0 (4, 1)
	748 getfield (4, 1)
	751 aload (4, 1)
	753 iload (4, 1)
	755 daload (4, 1)
	756 dmul (4, 1)
	757 aload_0 (4, 1)
	758 getfield (4, 1)
	761 dcmpl (4, 1)
	762 ifle (4, 1)
	765 goto (4, 1)
	768 iinc (4, 1)
	771 goto (4, 1)
	774 aload_0 (3, 4)
	775 getfield (3, 4)
	778 invokestatic (3, 4)
	781 dstore (3, 4)
	783 aload_0 (3, 4)
	784 getfield (3, 4)
	787 invokestatic (3, 4)
	790 dstore (3, 4)
	792 aload_0 (3, 1)
	793 getfield (3, 1)
	796 iconst_2 (3, 1)
	797 if_icmple (3, 1)
	800 dload (3, 1)
	802 dload (3, 1)
	804 invokestatic (3, 1)
	807 dload (3, 1)
	809 dload (3, 1)
	811 invokestatic (4, 1)
	814 dsub (4, 1)
	815 aload_0 (4, 1)
	816 getfield (4, 1)
	819 dcmpg (4, 1)
	820 ifge (4, 1)
	823 goto (4, 1)
	826 aload_0 (3, 1)
	827 getfield (3, 1)
	830 aload_0 (3, 1)
	831 getfield (3, 1)
	834 arraylength (3, 1)
	835 if_icmple (3, 1)
	838 dload (3, 1)
	840 dload (3, 1)
	842 dsub (3, 1)
	843 aload_0 (3, 1)
	844 getfield (3, 1)
	847 dcmpg (3, 1)
	848 ifge (3, 1)
	851 goto (4, 1)
	854 aload_0 (4, 1)
	855 getfield (4, 1)
	858 invokestatic (4, 1)
	861 aload_0 (4, 1)
	862 getfield (4, 1)
	865 invokestatic (4, 1)
	868 ddiv (4, 1)
	869 ldc2_w (4, 1)
	872 dcmpl (4, 1)
	873 ifle (4, 1)
	876 goto (4, 1)
	879 aload_0 (4, 1)
	880 invokevirtual (4, 1)
	883 ifnull (4, 1)
	886 new (4, 1)
	889 dup (4, 1)
	890 aload (4, 1)
	892 iconst_0 (4, 1)
	893 invokeinterface (4, 1)
	898 aload_0 (4, 1)
	899 getfield (4, 1)
	902 ifeq (4, 1)
	905 dload (4, 1)
	907 goto (4, 1)
	910 dload (4, 1)
	912 dneg (4, 1)
	913 invokespecial (4, 1)
	916 astore (4, 1)
	918 aload (4, 1)
	920 ifnull (4, 1)
	923 aload_0 (4, 1)
	924 invokevirtual (5, 1)
	927 aload_0 (5, 1)
	928 getfield (5, 1)
	931 aload (5, 1)
	933 aload (5, 1)
	935 invokeinterface (5, 1)
	940 ifeq (5, 1)
	943 goto (5, 1)
	946 aload (4, 1)
	948 astore (4, 1)
	950 dload_3 (4, 1)
	951 aload (4, 1)
	953 aload (4, 1)
	955 ldc2_w (4, 1)
	958 aload_0 (4, 1)
	959 getfield (4, 1)
	962 i2d (4, 1)
	963 ldc2_w (4, 1)
	966 ddiv (4, 1)
	967 dadd (4, 1)
	968 d2i (4, 1)
	969 iaload (4, 1)
	970 daload (4, 1)
	971 dcmpl (4, 1)
	972 ifne (4, 1)
	975 aload_0 (4, 1)
	976 dup (4, 1)
	977 getfield (4, 1)
	980 ldc2_w (4, 1)
	983 aload_0 (4, 1)
	984 getfield (4, 1)
	987 aload_0 (4, 1)
	988 getfield (4, 1)
	991 ddiv (4, 1)
	992 dadd (4, 1)
	993 invokestatic (4, 1)
	996 dmul (4, 1)
	997 putfield (4, 1)
	1000 aload_0 (3, 1)
	1001 getfield (3, 1)
	1004 iconst_2 (3, 1)
	1005 if_icmple (3, 1)
	1008 dload (3, 1)
	1010 dload (3, 1)
	1012 invokestatic (3, 1)
	1015 dload (3, 1)
	1017 dload (3, 1)
	1019 invokestatic (4, 1)
	1022 dsub (4, 1)
	1023 dconst_0 (4, 1)
	1024 dcmpl (4, 1)
	1025 ifne (4, 1)
	1028 aload_0 (4, 1)
	1029 dup (4, 1)
	1030 getfield (4, 1)
	1033 ldc2_w (4, 1)
	1036 aload_0 (4, 1)
	1037 getfield (4, 1)
	1040 aload_0 (4, 1)
	1041 getfield (4, 1)
	1044 ddiv (4, 1)
	1045 dadd (4, 1)
	1046 invokestatic (4, 1)
	1049 dmul (4, 1)
	1050 putfield (4, 1)
	1053 aload_0 (3, 4)
	1054 getfield (3, 4)
	1057 dload (3, 4)
	1059 invokestatic (3, 4)
	1062 aload_1 (3, 4)
	1063 dload (3, 4)
	1065 dload (3, 4)
	1067 dsub (3, 4)
	1068 invokevirtual (3, 4)
	1071 aload_0 (4, 1)
	1072 getfield (4, 1)
	1075 ifeq (4, 1)
	1078 aload_0 (4, 1)
	1079 getfield (4, 1)
	1082 aload_0 (4, 1)
	1083 getfield (4, 1)
	1086 invokestatic (4, 1)
	1089 invokeinterface (4, 1)
	1094 pop (4, 1)
	1095 aload_0 (4, 1)
	1096 getfield (4, 1)
	1099 dload (4, 1)
	1101 invokestatic (4, 1)
	1104 invokeinterface (4, 1)
	1109 pop (4, 1)
	1110 aload_0 (4, 1)
	1111 getfield (4, 1)
	1114 aload_0 (4, 1)
	1115 getfield (4, 1)
	1118 invokeinterface (4, 1)
	1123 invokeinterface (4, 1)
	1128 pop (4, 1)
	1129 aload_0 (4, 1)
	1130 getfield (4, 1)
	1133 aload_0 (4, 1)
	1134 getfield (4, 1)
	1137 invokeinterface (4, 1)
	1142 ldc2_w (4, 1)
	1145 invokeinterface (4, 1)
	1150 invokeinterface (4, 1)
	1155 pop (4, 1)
	1156 aload_0 (4, 1)
	1157 dup (4, 1)
	1158 getfield (4, 1)
	1161 iconst_1 (4, 1)
	1162 iadd (4, 1)
	1163 putfield (4, 1)
	1166 goto (4, 1)
	1169 aload (3, 1)
	1171 areturn (3, 1)

Method: parseOptimizationData
	0 aload_1 (1, 4)
	1 astore_2 (1, 4)
	2 aload_2 (1, 4)
	3 arraylength (1, 4)
	4 istore_3 (1, 4)
	5 iconst_0 (1, 4)
	6 istore (1, 4)
	8 iload (1, 4)
	10 iload_3 (1, 4)
	11 if_icmpge (1, 4)
	14 aload_2 (1, 4)
	15 iload (1, 4)
	17 aaload (1, 4)
	18 astore (1, 4)
	20 aload (2, 1)
	22 instanceof (2, 1)
	25 ifeq (2, 1)
	28 aload_0 (2, 1)
	29 aload (2, 1)
	31 checkcast (2, 1)
	34 invokevirtual (2, 1)
	37 putfield (2, 1)
	40 goto (2, 1)
	43 aload (2, 1)
	45 instanceof (2, 1)
	48 ifeq (2, 1)
	51 aload_0 (2, 1)
	52 aload (2, 1)
	54 checkcast (2, 1)
	57 invokevirtual (2, 1)
	60 putfield (2, 1)
	63 goto (2, 1)
	66 iinc (2, 1)
	69 goto (2, 1)
	72 return (0, 0)

Method: checkParameters
	0 aload_0 (0, 0)
	1 invokevirtual (0, 0)
	4 astore_1 (0, 0)
	5 aload_0 (0, 0)
	6 invokevirtual (0, 0)
	9 astore_2 (0, 0)
	10 aload_0 (0, 0)
	11 invokevirtual (0, 0)
	14 astore_3 (0, 0)
	15 aload_0 (1, 1)
	16 getfield (1, 1)
	19 ifnull (1, 1)
	22 aload_0 (2, 1)
	23 getfield (2, 1)
	26 arraylength (2, 1)
	27 aload_1 (2, 1)
	28 arraylength (2, 1)
	29 if_icmpeq (2, 1)
	32 new (2, 1)
	35 dup (2, 1)
	36 aload_0 (2, 1)
	37 getfield (2, 1)
	40 arraylength (2, 1)
	41 aload_1 (2, 1)
	42 arraylength (2, 1)
	43 invokespecial (2, 1)
	46 athrow (2, 1)
	47 iconst_0 (2, 4)
	48 istore (2, 4)
	50 iload (2, 4)
	52 aload_1 (2, 4)
	53 arraylength (2, 4)
	54 if_icmpge (2, 4)
	57 aload_0 (3, 1)
	58 getfield (3, 1)
	61 iload (3, 1)
	63 daload (3, 1)
	64 dconst_0 (3, 1)
	65 dcmpg (3, 1)
	66 ifge (3, 1)
	69 new (3, 4)
	72 dup (3, 4)
	73 aload_0 (3, 4)
	74 getfield (3, 4)
	77 iload (3, 4)
	79 daload (3, 4)
	80 invokestatic (3, 4)
	83 invokespecial (3, 4)
	86 athrow (3, 4)
	87 aload_0 (3, 1)
	88 getfield (3, 1)
	91 iload (3, 1)
	93 daload (3, 1)
	94 aload_3 (3, 1)
	95 iload (3, 1)
	97 daload (3, 1)
	98 aload_2 (3, 1)
	99 iload (3, 1)
	101 daload (3, 1)
	102 dsub (3, 1)
	103 dcmpl (3, 1)
	104 ifle (3, 1)
	107 new (3, 1)
	110 dup (3, 1)
	111 aload_0 (3, 1)
	112 getfield (3, 1)
	115 iload (3, 1)
	117 daload (3, 1)
	118 invokestatic (3, 1)
	121 iconst_0 (3, 1)
	122 invokestatic (3, 1)
	125 aload_3 (3, 1)
	126 iload (3, 1)
	128 daload (3, 1)
	129 aload_2 (3, 1)
	130 iload (3, 1)
	132 daload (3, 1)
	133 dsub (3, 1)
	134 invokestatic (3, 1)
	137 invokespecial (3, 1)
	140 athrow (3, 1)
	141 iinc (3, 1)
	144 goto (3, 1)
	147 return (0, 4)

Method: initializeCMA
	0 aload_0 (1, 1)
	1 getfield (1, 1)
	4 ifgt (1, 1)
	7 aload_0 (1, 1)
	8 iconst_4 (1, 1)
	9 ldc2_w (1, 1)
	12 aload_0 (1, 1)
	13 getfield (1, 1)
	16 i2d (1, 1)
	17 invokestatic (1, 1)
	20 dmul (1, 1)
	21 d2i (1, 1)
	22 iadd (1, 1)
	23 putfield (1, 1)
	26 aload_1 (0, 0)
	27 arraylength (0, 0)
	28 iconst_1 (0, 0)
	29 multianewarray (0, 0)
	33 astore_2 (0, 0)
	34 iconst_0 (1, 4)
	35 istore_3 (1, 4)
	36 iload_3 (1, 4)
	37 aload_1 (1, 4)
	38 arraylength (1, 4)
	39 if_icmpge (1, 4)
	42 aload_2 (1, 4)
	43 iload_3 (1, 4)
	44 aaload (1, 4)
	45 iconst_0 (1, 4)
	46 aload_0 (1, 4)
	47 getfield (1, 4)
	50 ifnonnull (1, 4)
	53 ldc2_w (1, 4)
	56 goto (1, 4)
	59 aload_0 (1, 4)
	60 getfield (1, 4)
	63 iload_3 (1, 4)
	64 daload (1, 4)
	65 dastore (1, 4)
	66 iinc (1, 4)
	69 goto (1, 4)
	72 new (0, 0)
	75 dup (0, 0)
	76 aload_2 (0, 0)
	77 iconst_0 (0, 0)
	78 invokespecial (0, 0)
	81 astore_3 (0, 0)
	82 aload_0 (0, 0)
	83 aload_3 (0, 0)
	84 invokestatic (0, 0)
	87 putfield (0, 0)
	90 aload_0 (0, 0)
	91 ldc2_w (0, 0)
	94 aload_3 (0, 0)
	95 invokestatic (0, 0)
	98 dmul (0, 0)
	99 putfield (0, 0)
	102 aload_0 (0, 0)
	103 ldc2_w (0, 0)
	106 aload_3 (0, 0)
	107 invokestatic (0, 0)
	110 dmul (0, 0)
	111 putfield (0, 0)
	114 aload_0 (0, 0)
	115 ldc2_w (0, 0)
	118 putfield (0, 0)
	121 aload_0 (0, 0)
	122 ldc2_w (0, 0)
	125 putfield (0, 0)
	128 aload_0 (0, 4)
	129 aload_0 (0, 4)
	130 getfield (0, 4)
	133 iconst_2 (0, 4)
	134 idiv (0, 4)
	135 putfield (0, 4)
	138 aload_0 (0, 4)
	139 aload_0 (0, 4)
	140 getfield (0, 4)
	143 i2d (0, 4)
	144 ldc2_w (0, 4)
	147 dadd (0, 4)
	148 invokestatic (0, 4)
	151 putfield (0, 4)
	154 aload_0 (0, 4)
	155 dconst_1 (0, 4)
	156 aload_0 (0, 4)
	157 getfield (0, 4)
	160 i2d (0, 4)
	161 dconst_1 (0, 4)
	162 invokestatic (0, 4)
	165 invokestatic (0, 4)
	168 ldc2_w (0, 4)
	171 invokeinterface (0, 4)
	176 aload_0 (0, 4)
	177 getfield (0, 4)
	180 invokeinterface (0, 4)
	185 putfield (0, 4)
	188 dconst_0 (0, 4)
	189 dstore (0, 4)
	191 dconst_0 (0, 4)
	192 dstore (0, 4)
	194 iconst_0 (1, 4)
	195 istore (1, 4)
	197 iload (1, 4)
	199 aload_0 (1, 4)
	200 getfield (1, 4)
	203 if_icmpge (1, 4)
	206 aload_0 (1, 4)
	207 getfield (1, 4)
	210 iload (1, 4)
	212 iconst_0 (1, 4)
	213 invokeinterface (1, 4)
	218 dstore (1, 4)
	220 dload (1, 4)
	222 dload (1, 4)
	224 dadd (1, 4)
	225 dstore (1, 4)
	227 dload (1, 4)
	229 dload (1, 4)
	231 dload (1, 4)
	233 dmul (1, 4)
	234 dadd (1, 4)
	235 dstore (1, 4)
	237 iinc (1, 4)
	240 goto (1, 4)
	243 aload_0 (0, 4)
	244 aload_0 (0, 4)
	245 getfield (0, 4)
	248 dconst_1 (0, 4)
	249 dload (0, 4)
	251 ddiv (0, 4)
	252 invokeinterface (0, 4)
	257 putfield (0, 4)
	260 aload_0 (0, 4)
	261 dload (0, 4)
	263 dload (0, 4)
	265 dmul (0, 4)
	266 dload (0, 4)
	268 ddiv (0, 4)
	269 putfield (0, 4)
	272 aload_0 (0, 4)
	273 ldc2_w (0, 4)
	276 aload_0 (0, 4)
	277 getfield (0, 4)
	280 aload_0 (0, 4)
	281 getfield (0, 4)
	284 i2d (0, 4)
	285 ddiv (0, 4)
	286 dadd (0, 4)
	287 aload_0 (0, 4)
	288 getfield (0, 4)
	291 iconst_4 (0, 4)
	292 iadd (0, 4)
	293 i2d (0, 4)
	294 ldc2_w (0, 4)
	297 aload_0 (0, 4)
	298 getfield (0, 4)
	301 dmul (0, 4)
	302 aload_0 (0, 4)
	303 getfield (0, 4)
	306 i2d (0, 4)
	307 ddiv (0, 4)
	308 dadd (0, 4)
	309 ddiv (0, 4)
	310 putfield (0, 4)
	313 aload_0 (0, 4)
	314 aload_0 (0, 4)
	315 getfield (0, 4)
	318 ldc2_w (0, 4)
	321 dadd (0, 4)
	322 aload_0 (0, 4)
	323 getfield (0, 4)
	326 i2d (0, 4)
	327 aload_0 (0, 4)
	328 getfield (0, 4)
	331 dadd (0, 4)
	332 ldc2_w (0, 4)
	335 dadd (0, 4)
	336 ddiv (0, 4)
	337 putfield (0, 4)
	340 aload_0 (0, 4)
	341 dconst_1 (0, 4)
	342 ldc2_w (0, 4)
	345 dconst_0 (0, 4)
	346 aload_0 (0, 4)
	347 getfield (0, 4)
	350 dconst_1 (0, 4)
	351 dsub (0, 4)
	352 aload_0 (0, 4)
	353 getfield (0, 4)
	356 iconst_1 (0, 4)
	357 iadd (0, 4)
	358 i2d (0, 4)
	359 ddiv (0, 4)
	360 invokestatic (0, 4)
	363 dconst_1 (0, 4)
	364 dsub (0, 4)
	365 invokestatic (0, 4)
	368 dmul (0, 4)
	369 dadd (0, 4)
	370 ldc2_w (0, 4)
	373 dconst_1 (0, 4)
	374 aload_0 (0, 4)
	375 getfield (0, 4)
	378 i2d (0, 4)
	379 ldc2_w (0, 4)
	382 aload_0 (0, 4)
	383 getfield (0, 4)
	386 i2d (0, 4)
	387 dadd (0, 4)
	388 ddiv (0, 4)
	389 dsub (0, 4)
	390 invokestatic (0, 4)
	393 dmul (0, 4)
	394 aload_0 (0, 4)
	395 getfield (0, 4)
	398 dadd (0, 4)
	399 putfield (0, 4)
	402 aload_0 (0, 4)
	403 ldc2_w (0, 4)
	406 aload_0 (0, 4)
	407 getfield (0, 4)
	410 i2d (0, 4)
	411 ldc2_w (0, 4)
	414 dadd (0, 4)
	415 aload_0 (0, 4)
	416 getfield (0, 4)
	419 i2d (0, 4)
	420 ldc2_w (0, 4)
	423 dadd (0, 4)
	424 dmul (0, 4)
	425 aload_0 (0, 4)
	426 getfield (0, 4)
	429 dadd (0, 4)
	430 ddiv (0, 4)
	431 putfield (0, 4)
	434 aload_0 (0, 4)
	435 dconst_1 (0, 4)
	436 aload_0 (0, 4)
	437 getfield (0, 4)
	440 dsub (0, 4)
	441 ldc2_w (0, 4)
	444 aload_0 (0, 4)
	445 getfield (0, 4)
	448 ldc2_w (0, 4)
	451 dsub (0, 4)
	452 dconst_1 (0, 4)
	453 aload_0 (0, 4)
	454 getfield (0, 4)
	457 ddiv (0, 4)
	458 dadd (0, 4)
	459 dmul (0, 4)
	460 aload_0 (0, 4)
	461 getfield (0, 4)
	464 iconst_2 (0, 4)
	465 iadd (0, 4)
	466 aload_0 (0, 4)
	467 getfield (0, 4)
	470 iconst_2 (0, 4)
	471 iadd (0, 4)
	472 imul (0, 4)
	473 i2d (0, 4)
	474 aload_0 (0, 4)
	475 getfield (0, 4)
	478 dadd (0, 4)
	479 ddiv (0, 4)
	480 invokestatic (0, 4)
	483 putfield (0, 4)
	486 aload_0 (0, 4)
	487 dconst_1 (0, 4)
	488 aload_0 (0, 4)
	489 getfield (0, 4)
	492 aload_0 (0, 4)
	493 getfield (0, 4)
	496 i2d (0, 4)
	497 ldc2_w (0, 4)
	500 dadd (0, 4)
	501 dmul (0, 4)
	502 ldc2_w (0, 4)
	505 ddiv (0, 4)
	506 invokestatic (0, 4)
	509 putfield (0, 4)
	512 aload_0 (0, 4)
	513 dconst_1 (0, 4)
	514 aload_0 (0, 4)
	515 getfield (0, 4)
	518 dsub (0, 4)
	519 aload_0 (0, 4)
	520 getfield (0, 4)
	523 aload_0 (0, 4)
	524 getfield (0, 4)
	527 i2d (0, 4)
	528 ldc2_w (0, 4)
	531 dadd (0, 4)
	532 dmul (0, 4)
	533 ldc2_w (0, 4)
	536 ddiv (0, 4)
	537 invokestatic (0, 4)
	540 putfield (0, 4)
	543 aload_0 (0, 4)
	544 aload_0 (0, 4)
	545 getfield (0, 4)
	548 i2d (0, 4)
	549 invokestatic (0, 4)
	552 dconst_1 (0, 4)
	553 dconst_1 (0, 4)
	554 ldc2_w (0, 4)
	557 aload_0 (0, 4)
	558 getfield (0, 4)
	561 i2d (0, 4)
	562 dmul (0, 4)
	563 ddiv (0, 4)
	564 dsub (0, 4)
	565 dconst_1 (0, 4)
	566 ldc2_w (0, 4)
	569 aload_0 (0, 4)
	570 getfield (0, 4)
	573 i2d (0, 4)
	574 dmul (0, 4)
	575 aload_0 (0, 4)
	576 getfield (0, 4)
	579 i2d (0, 4)
	580 dmul (0, 4)
	581 ddiv (0, 4)
	582 dadd (0, 4)
	583 dmul (0, 4)
	584 putfield (0, 4)
	587 aload_0 (0, 4)
	588 aload_1 (0, 4)
	589 invokestatic (0, 4)
	592 putfield (0, 4)
	595 aload_0 (0, 4)
	596 aload_3 (0, 4)
	597 dconst_1 (0, 4)
	598 aload_0 (0, 4)
	599 getfield (0, 4)
	602 ddiv (0, 4)
	603 invokeinterface (0, 4)
	608 putfield (0, 4)
	611 aload_0 (0, 4)
	612 aload_0 (0, 4)
	613 getfield (0, 4)
	616 invokestatic (0, 4)
	619 putfield (0, 4)
	622 aload_0 (0, 4)
	623 aload_0 (0, 4)
	624 getfield (0, 4)
	627 iconst_1 (0, 4)
	628 invokestatic (0, 4)
	631 putfield (0, 4)
	634 aload_0 (0, 4)
	635 aload_0 (0, 4)
	636 getfield (0, 4)
	639 iconst_1 (0, 4)
	640 invokestatic (0, 4)
	643 putfield (0, 4)
	646 aload_0 (0, 4)
	647 aload_0 (0, 4)
	648 getfield (0, 4)
	651 invokeinterface (0, 4)
	656 putfield (0, 4)
	659 aload_0 (0, 4)
	660 aload_0 (0, 4)
	661 getfield (0, 4)
	664 aload_0 (0, 4)
	665 getfield (0, 4)
	668 invokestatic (0, 4)
	671 putfield (0, 4)
	674 aload_0 (0, 4)
	675 aload_0 (0, 4)
	676 getfield (0, 4)
	679 iconst_1 (0, 4)
	680 invokestatic (0, 4)
	683 putfield (0, 4)
	686 aload_0 (0, 4)
	687 aload_0 (0, 4)
	688 getfield (0, 4)
	691 aload_0 (0, 4)
	692 getfield (0, 4)
	695 invokeinterface (0, 4)
	700 aload_0 (0, 4)
	701 getfield (0, 4)
	704 iconst_1 (0, 4)
	705 invokestatic (0, 4)
	708 invokestatic (0, 4)
	711 putfield (0, 4)
	714 aload_0 (0, 4)
	715 aload_0 (0, 4)
	716 getfield (0, 4)
	719 aload_0 (0, 4)
	720 getfield (0, 4)
	723 invokestatic (0, 4)
	726 invokestatic (0, 4)
	729 aload_0 (0, 4)
	730 getfield (0, 4)
	733 invokeinterface (0, 4)
	738 invokeinterface (0, 4)
	743 invokeinterface (0, 4)
	748 putfield (0, 4)
	751 aload_0 (0, 4)
	752 bipush (0, 4)
	754 bipush (0, 4)
	756 aload_0 (0, 4)
	757 getfield (0, 4)
	760 imul (0, 4)
	761 i2d (0, 4)
	762 aload_0 (0, 4)
	763 getfield (0, 4)
	766 i2d (0, 4)
	767 ddiv (0, 4)
	768 d2i (0, 4)
	769 iadd (0, 4)
	770 putfield (0, 4)
	773 aload_0 (0, 4)
	774 aload_0 (0, 4)
	775 getfield (0, 4)
	778 newarray (0, 4)
	780 putfield (0, 4)
	783 iconst_0 (1, 4)
	784 istore (1, 4)
	786 iload (1, 4)
	788 aload_0 (1, 4)
	789 getfield (1, 4)
	792 if_icmpge (1, 4)
	795 aload_0 (1, 4)
	796 getfield (1, 4)
	799 iload (1, 4)
	801 ldc2_w (1, 4)
	804 dastore (1, 4)
	805 iinc (1, 4)
	808 goto (1, 4)
	811 return (0, 4)

Method: updateEvolutionPaths
	0 aload_0 (0, 0)
	1 aload_0 (0, 0)
	2 getfield (0, 0)
	5 dconst_1 (0, 0)
	6 aload_0 (0, 0)
	7 getfield (0, 0)
	10 dsub (0, 0)
	11 invokeinterface (0, 0)
	16 aload_0 (0, 0)
	17 getfield (0, 0)
	20 aload_1 (0, 0)
	21 invokeinterface (0, 0)
	26 aload_0 (0, 0)
	27 getfield (0, 0)
	30 ldc2_w (0, 0)
	33 aload_0 (0, 0)
	34 getfield (0, 0)
	37 dsub (0, 0)
	38 dmul (0, 0)
	39 aload_0 (0, 0)
	40 getfield (0, 0)
	43 dmul (0, 0)
	44 invokestatic (0, 0)
	47 invokeinterface (0, 0)
	52 invokeinterface (0, 0)
	57 putfield (0, 0)
	60 aload_0 (0, 0)
	61 aload_0 (0, 0)
	62 getfield (0, 0)
	65 invokeinterface (0, 0)
	70 putfield (0, 0)
	73 aload_0 (0, 0)
	74 getfield (0, 0)
	77 dconst_1 (0, 0)
	78 dconst_1 (0, 0)
	79 aload_0 (0, 0)
	80 getfield (0, 0)
	83 dsub (0, 0)
	84 iconst_2 (0, 0)
	85 aload_0 (0, 0)
	86 getfield (0, 0)
	89 imul (0, 0)
	90 invokestatic (0, 0)
	93 dsub (0, 0)
	94 invokestatic (0, 0)
	97 ddiv (0, 0)
	98 aload_0 (0, 0)
	99 getfield (0, 0)
	102 ddiv (0, 0)
	103 ldc2_w (0, 0)
	106 ldc2_w (0, 0)
	109 aload_0 (0, 0)
	110 getfield (0, 0)
	113 i2d (0, 0)
	114 dconst_1 (0, 0)
	115 dadd (0, 0)
	116 ddiv (0, 0)
	117 dadd (0, 0)
	118 dcmpg (0, 0)
	119 ifge (0, 0)
	122 iconst_1 (0, 0)
	123 goto (0, 0)
	126 iconst_0 (0, 0)
	127 istore_3 (0, 0)
	128 aload_0 (0, 0)
	129 aload_0 (0, 0)
	130 getfield (0, 0)
	133 dconst_1 (0, 0)
	134 aload_0 (0, 0)
	135 getfield (0, 0)
	138 dsub (0, 0)
	139 invokeinterface (0, 0)
	144 putfield (0, 0)
	147 iload_3 (1, 1)
	148 ifeq (1, 1)
	151 aload_0 (1, 1)
	152 aload_0 (1, 1)
	153 getfield (1, 1)
	156 aload_0 (1, 1)
	157 getfield (1, 1)
	160 aload_2 (1, 1)
	161 invokeinterface (1, 1)
	166 aload_0 (1, 1)
	167 getfield (1, 1)
	170 ldc2_w (1, 1)
	173 aload_0 (1, 1)
	174 getfield (1, 1)
	177 dsub (1, 1)
	178 dmul (1, 1)
	179 aload_0 (1, 1)
	180 getfield (1, 1)
	183 dmul (1, 1)
	184 invokestatic (1, 1)
	187 aload_0 (1, 1)
	188 getfield (1, 1)
	191 ddiv (1, 1)
	192 invokeinterface (1, 1)
	197 invokeinterface (1, 1)
	202 putfield (1, 1)
	205 iload_3 (0, 0)
	206 ireturn (0, 0)

Method: updateCovarianceDiagonalOnly
	0 iload_1 (0, 0)
	1 ifeq (0, 0)
	4 dconst_0 (0, 0)
	5 goto (0, 0)
	8 aload_0 (0, 0)
	9 getfield (0, 0)
	12 aload_0 (0, 0)
	13 getfield (0, 0)
	16 dmul (0, 0)
	17 ldc2_w (0, 0)
	20 aload_0 (0, 0)
	21 getfield (0, 0)
	24 dsub (0, 0)
	25 dmul (0, 0)
	26 dstore_3 (0, 0)
	27 dload_3 (0, 0)
	28 dconst_1 (0, 0)
	29 aload_0 (0, 0)
	30 getfield (0, 0)
	33 dsub (0, 0)
	34 aload_0 (0, 0)
	35 getfield (0, 0)
	38 dsub (0, 0)
	39 dadd (0, 0)
	40 dstore_3 (0, 0)
	41 aload_0 (0, 0)
	42 aload_0 (0, 0)
	43 getfield (0, 0)
	46 dload_3 (0, 0)
	47 invokeinterface (0, 0)
	52 aload_0 (0, 0)
	53 getfield (0, 0)
	56 invokestatic (0, 0)
	59 aload_0 (0, 0)
	60 getfield (0, 0)
	63 invokeinterface (0, 0)
	68 invokeinterface (0, 0)
	73 aload_0 (0, 0)
	74 getfield (0, 0)
	77 aload_2 (0, 0)
	78 invokestatic (0, 0)
	81 aload_0 (0, 0)
	82 getfield (0, 0)
	85 invokeinterface (0, 0)
	90 invokestatic (0, 0)
	93 aload_0 (0, 0)
	94 getfield (0, 0)
	97 invokeinterface (0, 0)
	102 invokeinterface (0, 0)
	107 putfield (0, 0)
	110 aload_0 (0, 0)
	111 aload_0 (0, 0)
	112 getfield (0, 0)
	115 invokestatic (0, 0)
	118 putfield (0, 0)
	121 aload_0 (0, 1)
	122 getfield (0, 1)
	125 iconst_1 (0, 1)
	126 if_icmple (0, 1)
	129 aload_0 (0, 1)
	130 getfield (0, 1)
	133 aload_0 (0, 1)
	134 getfield (0, 1)
	137 if_icmple (0, 1)
	140 aload_0 (1, 1)
	141 iconst_0 (1, 1)
	142 putfield (1, 1)
	145 aload_0 (1, 1)
	146 aload_0 (1, 1)
	147 getfield (1, 1)
	150 aload_0 (1, 1)
	151 getfield (1, 1)
	154 invokestatic (1, 1)
	157 putfield (1, 1)
	160 aload_0 (1, 1)
	161 aload_0 (1, 1)
	162 getfield (1, 1)
	165 invokestatic (1, 1)
	168 putfield (1, 1)
	171 aload_0 (1, 1)
	172 aload_0 (1, 1)
	173 getfield (1, 1)
	176 invokestatic (1, 1)
	179 putfield (1, 1)
	182 return (0, 0)

Method: updateCovariance
	0 dconst_0 (0, 0)
	1 dstore (0, 0)
	3 aload_0 (1, 1)
	4 getfield (1, 1)
	7 aload_0 (1, 1)
	8 getfield (1, 1)
	11 dadd (1, 1)
	12 dconst_0 (1, 1)
	13 dcmpl (1, 1)
	14 ifle (1, 1)
	17 aload_2 (1, 1)
	18 aload (1, 1)
	20 iconst_1 (1, 1)
	21 aload_0 (1, 1)
	22 getfield (1, 1)
	25 invokestatic (1, 1)
	28 invokeinterface (1, 1)
	33 dconst_1 (1, 1)
	34 aload_0 (1, 1)
	35 getfield (1, 1)
	38 ddiv (1, 1)
	39 invokeinterface (1, 1)
	44 astore (1, 1)
	46 aload_0 (1, 1)
	47 getfield (1, 1)
	50 aload_0 (1, 1)
	51 getfield (1, 1)
	54 invokeinterface (1, 1)
	59 invokeinterface (1, 1)
	64 aload_0 (1, 1)
	65 getfield (1, 1)
	68 invokeinterface (1, 1)
	73 astore (1, 1)
	75 iload_1 (1, 1)
	76 ifeq (1, 1)
	79 dconst_0 (1, 1)
	80 goto (1, 1)
	83 aload_0 (1, 1)
	84 getfield (1, 1)
	87 aload_0 (1, 1)
	88 getfield (1, 1)
	91 dmul (1, 1)
	92 ldc2_w (1, 1)
	95 aload_0 (1, 1)
	96 getfield (1, 1)
	99 dsub (1, 1)
	100 dmul (1, 1)
	101 dstore (1, 1)
	103 dload (1, 1)
	105 dconst_1 (1, 1)
	106 aload_0 (1, 1)
	107 getfield (1, 1)
	110 dsub (1, 1)
	111 aload_0 (1, 1)
	112 getfield (1, 1)
	115 dsub (1, 1)
	116 dadd (1, 1)
	117 dstore (1, 1)
	119 aload_0 (2, 1)
	120 getfield (2, 1)
	123 ifeq (2, 1)
	126 dconst_1 (2, 1)
	127 aload_0 (2, 1)
	128 getfield (2, 1)
	131 dsub (2, 1)
	132 ldc2_w (2, 1)
	135 dmul (2, 1)
	136 aload_0 (2, 1)
	137 getfield (2, 1)
	140 dmul (2, 1)
	141 aload_0 (2, 1)
	142 getfield (2, 1)
	145 iconst_2 (2, 1)
	146 iadd (2, 1)
	147 i2d (2, 1)
	148 ldc2_w (2, 1)
	151 invokestatic (2, 1)
	154 ldc2_w (2, 1)
	157 aload_0 (2, 1)
	158 getfield (2, 1)
	161 dmul (2, 1)
	162 dadd (2, 1)
	163 ddiv (2, 1)
	164 dstore (2, 1)
	166 ldc2_w (2, 1)
	169 dstore (2, 1)
	171 ldc2_w (2, 4)
	174 dstore (2, 4)
	176 aload (2, 4)
	178 invokestatic (2, 4)
	181 astore (2, 4)
	183 aload_3 (2, 4)
	184 aload (2, 4)
	186 aload_0 (2, 4)
	187 getfield (2, 4)
	190 invokestatic (2, 4)
	193 invokestatic (2, 4)
	196 astore (2, 4)
	198 aload (2, 4)
	200 invokestatic (2, 4)
	203 invokestatic (2, 4)
	206 invokestatic (2, 4)
	209 astore (2, 4)
	211 aload_0 (2, 4)
	212 aload (2, 4)
	214 iconst_0 (2, 4)
	215 invokeinterface (2, 4)
	220 invokespecial (2, 4)
	223 astore (2, 4)
	225 aload (2, 4)
	227 aload (2, 4)
	229 invokestatic (2, 4)
	232 astore (2, 4)
	234 aload (2, 4)
	236 invokestatic (2, 4)
	239 astore (2, 4)
	241 aload (2, 4)
	243 aload (2, 4)
	245 invokestatic (2, 4)
	248 astore (2, 4)
	250 aload (2, 4)
	252 aload (2, 4)
	254 invokestatic (2, 4)
	257 astore (2, 4)
	259 aload (2, 4)
	261 invokestatic (2, 4)
	264 astore (2, 4)
	266 aload (2, 4)
	268 aload (2, 4)
	270 invokestatic (2, 4)
	273 astore (2, 4)
	275 ldc2_w (2, 4)
	278 aload (2, 4)
	280 invokestatic (2, 4)
	283 aload_0 (2, 4)
	284 getfield (2, 4)
	287 invokeinterface (2, 4)
	292 iconst_0 (2, 4)
	293 iconst_0 (2, 4)
	294 invokeinterface (2, 4)
	299 ddiv (2, 4)
	300 dstore (2, 4)
	302 dload (3, 1)
	304 dload (3, 1)
	306 dcmpl (3, 1)
	307 ifle (3, 1)
	310 dload (3, 1)
	312 dstore (3, 1)
	314 aload (2, 4)
	316 aload (2, 4)
	318 aload_0 (2, 4)
	319 getfield (2, 4)
	322 iconst_1 (2, 4)
	323 invokestatic (2, 4)
	326 invokestatic (2, 4)
	329 astore (2, 4)
	331 aload_0 (2, 4)
	332 getfield (2, 4)
	335 aload (2, 4)
	337 invokeinterface (2, 4)
	342 astore (2, 4)
	344 aload (2, 4)
	346 aload_0 (2, 4)
	347 getfield (2, 4)
	350 invokestatic (2, 4)
	353 invokeinterface (2, 4)
	358 aload (2, 4)
	360 invokeinterface (2, 4)
	365 invokeinterface (2, 4)
	370 astore (2, 4)
	372 dload (2, 4)
	374 ldc2_w (2, 4)
	377 dload (2, 4)
	379 dmul (2, 4)
	380 dadd (2, 4)
	381 dstore (2, 4)
	383 aload_0 (2, 4)
	384 aload_0 (2, 4)
	385 getfield (2, 4)
	388 dload (2, 4)
	390 invokeinterface (2, 4)
	395 aload (2, 4)
	397 invokeinterface (2, 4)
	402 aload (2, 4)
	404 aload_0 (2, 4)
	405 getfield (2, 4)
	408 ldc2_w (2, 4)
	411 dload (2, 4)
	413 dmul (2, 4)
	414 dadd (2, 4)
	415 invokeinterface (2, 4)
	420 aload_0 (2, 4)
	421 getfield (2, 4)
	424 iconst_1 (2, 4)
	425 aload_0 (2, 4)
	426 getfield (2, 4)
	429 invokestatic (2, 4)
	432 aload (2, 4)
	434 invokeinterface (2, 4)
	439 invokestatic (2, 4)
	442 invokeinterface (2, 4)
	447 invokeinterface (2, 4)
	452 aload (2, 4)
	454 dload (2, 4)
	456 invokeinterface (2, 4)
	461 invokeinterface (2, 4)
	466 putfield (2, 4)
	469 goto (2, 2)
	472 aload_0 (2, 2)
	473 aload_0 (2, 2)
	474 getfield (2, 2)
	477 dload (2, 2)
	479 invokeinterface (2, 2)
	484 aload (2, 2)
	486 invokeinterface (2, 2)
	491 aload (2, 2)
	493 aload_0 (2, 2)
	494 getfield (2, 2)
	497 invokeinterface (2, 2)
	502 aload_0 (2, 2)
	503 getfield (2, 2)
	506 iconst_1 (2, 2)
	507 aload_0 (2, 2)
	508 getfield (2, 2)
	511 invokestatic (2, 2)
	514 aload (2, 2)
	516 invokeinterface (2, 2)
	521 invokestatic (2, 2)
	524 invokeinterface (2, 2)
	529 invokeinterface (2, 2)
	534 putfield (2, 2)
	537 aload_0 (0, 1)
	538 dload (0, 1)
	540 invokespecial (0, 1)
	543 return (0, 1)

Method: updateBD
	0 aload_0 (0, 1)
	1 getfield (0, 1)
	4 aload_0 (0, 1)
	5 getfield (0, 1)
	8 dadd (0, 1)
	9 dload_1 (0, 1)
	10 dadd (0, 1)
	11 dconst_0 (0, 1)
	12 dcmpl (0, 1)
	13 ifle (0, 1)
	16 aload_0 (0, 1)
	17 getfield (0, 1)
	20 i2d (0, 1)
	21 dconst_1 (0, 1)
	22 drem (0, 1)
	23 aload_0 (0, 1)
	24 getfield (0, 1)
	27 aload_0 (0, 1)
	28 getfield (0, 1)
	31 dadd (0, 1)
	32 dload_1 (0, 1)
	33 dadd (0, 1)
	34 ddiv (0, 1)
	35 aload_0 (0, 1)
	36 getfield (0, 1)
	39 i2d (0, 1)
	40 ddiv (0, 1)
	41 ldc2_w (0, 1)
	44 ddiv (0, 1)
	45 dconst_1 (0, 1)
	46 dcmpg (0, 1)
	47 ifge (0, 1)
	50 aload_0 (1, 1)
	51 aload_0 (1, 1)
	52 getfield (1, 1)
	55 iconst_0 (1, 1)
	56 invokestatic (1, 1)
	59 aload_0 (1, 1)
	60 getfield (1, 1)
	63 iconst_1 (1, 1)
	64 invokestatic (1, 1)
	67 invokeinterface (1, 1)
	72 invokeinterface (1, 1)
	77 putfield (1, 1)
	80 new (1, 4)
	83 dup (1, 4)
	84 aload_0 (1, 4)
	85 getfield (1, 4)
	88 invokespecial (1, 4)
	91 astore_3 (1, 4)
	92 aload_0 (1, 4)
	93 aload_3 (1, 4)
	94 invokevirtual (1, 4)
	97 putfield (1, 4)
	100 aload_0 (1, 4)
	101 aload_3 (1, 4)
	102 invokevirtual (1, 4)
	105 putfield (1, 4)
	108 aload_0 (1, 4)
	109 aload_0 (1, 4)
	110 getfield (1, 4)
	113 invokestatic (1, 4)
	116 putfield (1, 4)
	119 aload_0 (2, 1)
	120 getfield (2, 1)
	123 invokestatic (2, 1)
	126 dconst_0 (2, 1)
	127 dcmpg (2, 1)
	128 ifgt (2, 1)
	131 iconst_0 (3, 4)
	132 istore (3, 4)
	134 iload (3, 4)
	136 aload_0 (3, 4)
	137 getfield (3, 4)
	140 if_icmpge (3, 4)
	143 aload_0 (4, 1)
	144 getfield (4, 1)
	147 iload (4, 1)
	149 iconst_0 (4, 1)
	150 invokeinterface (4, 1)
	155 dconst_0 (4, 1)
	156 dcmpg (4, 1)
	157 ifge (4, 1)
	160 aload_0 (4, 1)
	161 getfield (4, 1)
	164 iload (4, 1)
	166 iconst_0 (4, 1)
	167 dconst_0 (4, 1)
	168 invokeinterface (4, 1)
	173 iinc (4, 1)
	176 goto (4, 1)
	179 aload_0 (3, 4)
	180 getfield (3, 4)
	183 invokestatic (3, 4)
	186 ldc2_w (3, 4)
	189 ddiv (3, 4)
	190 dstore (3, 4)
	192 aload_0 (3, 4)
	193 aload_0 (3, 4)
	194 getfield (3, 4)
	197 aload_0 (3, 4)
	198 getfield (3, 4)
	201 aload_0 (3, 4)
	202 getfield (3, 4)
	205 invokestatic (3, 4)
	208 dload (3, 4)
	210 invokeinterface (3, 4)
	215 invokeinterface (3, 4)
	220 putfield (3, 4)
	223 aload_0 (3, 4)
	224 aload_0 (3, 4)
	225 getfield (3, 4)
	228 aload_0 (3, 4)
	229 getfield (3, 4)
	232 iconst_1 (3, 4)
	233 invokestatic (3, 4)
	236 dload (3, 4)
	238 invokeinterface (3, 4)
	243 invokeinterface (3, 4)
	248 putfield (3, 4)
	251 aload_0 (3, 1)
	252 getfield (3, 1)
	255 invokestatic (3, 1)
	258 ldc2_w (3, 1)
	261 aload_0 (3, 1)
	262 getfield (3, 1)
	265 invokestatic (3, 1)
	268 dmul (3, 1)
	269 dcmpl (3, 1)
	270 ifle (3, 1)
	273 aload_0 (3, 1)
	274 getfield (3, 1)
	277 invokestatic (3, 1)
	280 ldc2_w (3, 1)
	283 ddiv (3, 1)
	284 aload_0 (3, 1)
	285 getfield (3, 1)
	288 invokestatic (3, 1)
	291 dsub (3, 1)
	292 dstore (3, 1)
	294 aload_0 (3, 1)
	295 aload_0 (3, 1)
	296 getfield (3, 1)
	299 aload_0 (3, 1)
	300 getfield (3, 1)
	303 aload_0 (3, 1)
	304 getfield (3, 1)
	307 invokestatic (3, 1)
	310 dload (3, 1)
	312 invokeinterface (3, 1)
	317 invokeinterface (3, 1)
	322 putfield (3, 1)
	325 aload_0 (3, 1)
	326 aload_0 (3, 1)
	327 getfield (3, 1)
	330 aload_0 (3, 1)
	331 getfield (3, 1)
	334 iconst_1 (3, 1)
	335 invokestatic (3, 1)
	338 dload (3, 1)
	340 invokeinterface (3, 1)
	345 invokeinterface (3, 1)
	350 putfield (3, 1)
	353 aload_0 (2, 1)
	354 aload_0 (2, 1)
	355 getfield (2, 1)
	358 invokestatic (2, 1)
	361 putfield (2, 1)
	364 aload_0 (2, 1)
	365 aload_0 (2, 1)
	366 getfield (2, 1)
	369 invokestatic (2, 1)
	372 putfield (2, 1)
	375 aload_0 (2, 1)
	376 aload_0 (2, 1)
	377 getfield (2, 1)
	380 aload_0 (2, 1)
	381 getfield (2, 1)
	384 invokeinterface (2, 1)
	389 aload_0 (2, 1)
	390 getfield (2, 1)
	393 iconst_1 (2, 1)
	394 invokestatic (2, 1)
	397 invokestatic (2, 1)
	400 putfield (2, 1)
	403 return (0, 1)

Method: push
	0 aload_0 (1, 4)
	1 arraylength (1, 4)
	2 iconst_1 (1, 4)
	3 isub (1, 4)
	4 istore_3 (1, 4)
	5 iload_3 (1, 4)
	6 ifle (1, 4)
	9 aload_0 (1, 4)
	10 iload_3 (1, 4)
	11 aload_0 (1, 4)
	12 iload_3 (1, 4)
	13 iconst_1 (1, 4)
	14 isub (1, 4)
	15 daload (1, 4)
	16 dastore (1, 4)
	17 iinc (1, 4)
	20 goto (1, 4)
	23 aload_0 (0, 0)
	24 iconst_0 (0, 0)
	25 dload_1 (0, 0)
	26 dastore (0, 0)
	27 return (0, 0)

Method: sortedIndices
	0 aload_1 (0, 0)
	1 arraylength (0, 0)
	2 anewarray (0, 0)
	5 astore_2 (0, 0)
	6 iconst_0 (1, 4)
	7 istore_3 (1, 4)
	8 iload_3 (1, 4)
	9 aload_1 (1, 4)
	10 arraylength (1, 4)
	11 if_icmpge (1, 4)
	14 aload_2 (1, 4)
	15 iload_3 (1, 4)
	16 new (1, 4)
	19 dup (1, 4)
	20 aload_1 (1, 4)
	21 iload_3 (1, 4)
	22 daload (1, 4)
	23 iload_3 (1, 4)
	24 invokespecial (1, 4)
	27 aastore (1, 4)
	28 iinc (1, 4)
	31 goto (1, 4)
	34 aload_2 (0, 0)
	35 invokestatic (0, 0)
	38 aload_1 (0, 0)
	39 arraylength (0, 0)
	40 newarray (0, 0)
	42 astore_3 (0, 0)
	43 iconst_0 (1, 4)
	44 istore (1, 4)
	46 iload (1, 4)
	48 aload_1 (1, 4)
	49 arraylength (1, 4)
	50 if_icmpge (1, 4)
	53 aload_3 (1, 4)
	54 iload (1, 4)
	56 aload_2 (1, 4)
	57 iload (1, 4)
	59 aaload (1, 4)
	60 invokestatic (1, 4)
	63 iastore (1, 4)
	64 iinc (1, 4)
	67 goto (1, 4)
	70 aload_3 (0, 0)
	71 areturn (0, 0)

Method: log
	0 aload_0 (0, 0)
	1 invokeinterface (0, 0)
	6 aload_0 (0, 0)
	7 invokeinterface (0, 0)
	12 multianewarray (0, 0)
	16 astore_1 (0, 0)
	17 iconst_0 (1, 4)
	18 istore_2 (1, 4)
	19 iload_2 (1, 4)
	20 aload_0 (1, 4)
	21 invokeinterface (1, 4)
	26 if_icmpge (1, 4)
	29 iconst_0 (2, 4)
	30 istore_3 (2, 4)
	31 iload_3 (2, 4)
	32 aload_0 (2, 4)
	33 invokeinterface (2, 4)
	38 if_icmpge (2, 4)
	41 aload_1 (2, 4)
	42 iload_2 (2, 4)
	43 aaload (2, 4)
	44 iload_3 (2, 4)
	45 aload_0 (2, 4)
	46 iload_2 (2, 4)
	47 iload_3 (2, 4)
	48 invokeinterface (2, 4)
	53 invokestatic (2, 4)
	56 dastore (2, 4)
	57 iinc (2, 4)
	60 goto (2, 4)
	63 iinc (2, 4)
	66 goto (2, 4)
	69 new (1, 4)
	72 dup (1, 4)
	73 aload_1 (1, 4)
	74 iconst_0 (1, 4)
	75 invokespecial (1, 4)
	78 areturn (1, 4)

Method: sqrt
	0 aload_0 (0, 0)
	1 invokeinterface (0, 0)
	6 aload_0 (0, 0)
	7 invokeinterface (0, 0)
	12 multianewarray (0, 0)
	16 astore_1 (0, 0)
	17 iconst_0 (1, 4)
	18 istore_2 (1, 4)
	19 iload_2 (1, 4)
	20 aload_0 (1, 4)
	21 invokeinterface (1, 4)
	26 if_icmpge (1, 4)
	29 iconst_0 (2, 4)
	30 istore_3 (2, 4)
	31 iload_3 (2, 4)
	32 aload_0 (2, 4)
	33 invokeinterface (2, 4)
	38 if_icmpge (2, 4)
	41 aload_1 (2, 4)
	42 iload_2 (2, 4)
	43 aaload (2, 4)
	44 iload_3 (2, 4)
	45 aload_0 (2, 4)
	46 iload_2 (2, 4)
	47 iload_3 (2, 4)
	48 invokeinterface (2, 4)
	53 invokestatic (2, 4)
	56 dastore (2, 4)
	57 iinc (2, 4)
	60 goto (2, 4)
	63 iinc (2, 4)
	66 goto (2, 4)
	69 new (1, 4)
	72 dup (1, 4)
	73 aload_1 (1, 4)
	74 iconst_0 (1, 4)
	75 invokespecial (1, 4)
	78 areturn (1, 4)

Method: square
	0 aload_0 (0, 0)
	1 invokeinterface (0, 0)
	6 aload_0 (0, 0)
	7 invokeinterface (0, 0)
	12 multianewarray (0, 0)
	16 astore_1 (0, 0)
	17 iconst_0 (1, 4)
	18 istore_2 (1, 4)
	19 iload_2 (1, 4)
	20 aload_0 (1, 4)
	21 invokeinterface (1, 4)
	26 if_icmpge (1, 4)
	29 iconst_0 (2, 4)
	30 istore_3 (2, 4)
	31 iload_3 (2, 4)
	32 aload_0 (2, 4)
	33 invokeinterface (2, 4)
	38 if_icmpge (2, 4)
	41 aload_0 (2, 4)
	42 iload_2 (2, 4)
	43 iload_3 (2, 4)
	44 invokeinterface (2, 4)
	49 dstore (2, 4)
	51 aload_1 (2, 4)
	52 iload_2 (2, 4)
	53 aaload (2, 4)
	54 iload_3 (2, 4)
	55 dload (2, 4)
	57 dload (2, 4)
	59 dmul (2, 4)
	60 dastore (2, 4)
	61 iinc (2, 4)
	64 goto (2, 4)
	67 iinc (2, 4)
	70 goto (2, 4)
	73 new (1, 4)
	76 dup (1, 4)
	77 aload_1 (1, 4)
	78 iconst_0 (1, 4)
	79 invokespecial (1, 4)
	82 areturn (1, 4)

Method: times
	0 aload_0 (0, 0)
	1 invokeinterface (0, 0)
	6 aload_0 (0, 0)
	7 invokeinterface (0, 0)
	12 multianewarray (0, 0)
	16 astore_2 (0, 0)
	17 iconst_0 (1, 4)
	18 istore_3 (1, 4)
	19 iload_3 (1, 4)
	20 aload_0 (1, 4)
	21 invokeinterface (1, 4)
	26 if_icmpge (1, 4)
	29 iconst_0 (2, 4)
	30 istore (2, 4)
	32 iload (2, 4)
	34 aload_0 (2, 4)
	35 invokeinterface (2, 4)
	40 if_icmpge (2, 4)
	43 aload_2 (2, 4)
	44 iload_3 (2, 4)
	45 aaload (2, 4)
	46 iload (2, 4)
	48 aload_0 (2, 4)
	49 iload_3 (2, 4)
	50 iload (2, 4)
	52 invokeinterface (2, 4)
	57 aload_1 (2, 4)
	58 iload_3 (2, 4)
	59 iload (2, 4)
	61 invokeinterface (2, 4)
	66 dmul (2, 4)
	67 dastore (2, 4)
	68 iinc (2, 4)
	71 goto (2, 4)
	74 iinc (2, 4)
	77 goto (2, 4)
	80 new (1, 4)
	83 dup (1, 4)
	84 aload_2 (1, 4)
	85 iconst_0 (1, 4)
	86 invokespecial (1, 4)
	89 areturn (1, 4)

Method: divide
	0 aload_0 (0, 0)
	1 invokeinterface (0, 0)
	6 aload_0 (0, 0)
	7 invokeinterface (0, 0)
	12 multianewarray (0, 0)
	16 astore_2 (0, 0)
	17 iconst_0 (1, 4)
	18 istore_3 (1, 4)
	19 iload_3 (1, 4)
	20 aload_0 (1, 4)
	21 invokeinterface (1, 4)
	26 if_icmpge (1, 4)
	29 iconst_0 (2, 4)
	30 istore (2, 4)
	32 iload (2, 4)
	34 aload_0 (2, 4)
	35 invokeinterface (2, 4)
	40 if_icmpge (2, 4)
	43 aload_2 (2, 4)
	44 iload_3 (2, 4)
	45 aaload (2, 4)
	46 iload (2, 4)
	48 aload_0 (2, 4)
	49 iload_3 (2, 4)
	50 iload (2, 4)
	52 invokeinterface (2, 4)
	57 aload_1 (2, 4)
	58 iload_3 (2, 4)
	59 iload (2, 4)
	61 invokeinterface (2, 4)
	66 ddiv (2, 4)
	67 dastore (2, 4)
	68 iinc (2, 4)
	71 goto (2, 4)
	74 iinc (2, 4)
	77 goto (2, 4)
	80 new (1, 4)
	83 dup (1, 4)
	84 aload_2 (1, 4)
	85 iconst_0 (1, 4)
	86 invokespecial (1, 4)
	89 areturn (1, 4)

Method: selectColumns
	0 aload_0 (0, 0)
	1 invokeinterface (0, 0)
	6 aload_1 (0, 0)
	7 arraylength (0, 0)
	8 multianewarray (0, 0)
	12 astore_2 (0, 0)
	13 iconst_0 (1, 4)
	14 istore_3 (1, 4)
	15 iload_3 (1, 4)
	16 aload_0 (1, 4)
	17 invokeinterface (1, 4)
	22 if_icmpge (1, 4)
	25 iconst_0 (2, 4)
	26 istore (2, 4)
	28 iload (2, 4)
	30 aload_1 (2, 4)
	31 arraylength (2, 4)
	32 if_icmpge (2, 4)
	35 aload_2 (2, 4)
	36 iload_3 (2, 4)
	37 aaload (2, 4)
	38 iload (2, 4)
	40 aload_0 (2, 4)
	41 iload_3 (2, 4)
	42 aload_1 (2, 4)
	43 iload (2, 4)
	45 iaload (2, 4)
	46 invokeinterface (2, 4)
	51 dastore (2, 4)
	52 iinc (2, 4)
	55 goto (2, 4)
	58 iinc (2, 4)
	61 goto (2, 4)
	64 new (1, 4)
	67 dup (1, 4)
	68 aload_2 (1, 4)
	69 iconst_0 (1, 4)
	70 invokespecial (1, 4)
	73 areturn (1, 4)

Method: triu
	0 aload_0 (0, 0)
	1 invokeinterface (0, 0)
	6 aload_0 (0, 0)
	7 invokeinterface (0, 0)
	12 multianewarray (0, 0)
	16 astore_2 (0, 0)
	17 iconst_0 (1, 4)
	18 istore_3 (1, 4)
	19 iload_3 (1, 4)
	20 aload_0 (1, 4)
	21 invokeinterface (1, 4)
	26 if_icmpge (1, 4)
	29 iconst_0 (2, 4)
	30 istore (2, 4)
	32 iload (2, 4)
	34 aload_0 (2, 4)
	35 invokeinterface (2, 4)
	40 if_icmpge (2, 4)
	43 aload_2 (2, 4)
	44 iload_3 (2, 4)
	45 aaload (2, 4)
	46 iload (2, 4)
	48 iload_3 (2, 4)
	49 iload (2, 4)
	51 iload_1 (2, 4)
	52 isub (2, 4)
	53 if_icmpgt (2, 4)
	56 aload_0 (2, 4)
	57 iload_3 (2, 4)
	58 iload (2, 4)
	60 invokeinterface (2, 4)
	65 goto (2, 4)
	68 dconst_0 (2, 4)
	69 dastore (2, 4)
	70 iinc (2, 4)
	73 goto (2, 4)
	76 iinc (2, 4)
	79 goto (2, 4)
	82 new (1, 4)
	85 dup (1, 4)
	86 aload_2 (1, 4)
	87 iconst_0 (1, 4)
	88 invokespecial (1, 4)
	91 areturn (1, 4)

Method: sumRows
	0 iconst_1 (0, 0)
	1 aload_0 (0, 0)
	2 invokeinterface (0, 0)
	7 multianewarray (0, 0)
	11 astore_1 (0, 0)
	12 iconst_0 (1, 4)
	13 istore_2 (1, 4)
	14 iload_2 (1, 4)
	15 aload_0 (1, 4)
	16 invokeinterface (1, 4)
	21 if_icmpge (1, 4)
	24 dconst_0 (1, 4)
	25 dstore_3 (1, 4)
	26 iconst_0 (2, 4)
	27 istore (2, 4)
	29 iload (2, 4)
	31 aload_0 (2, 4)
	32 invokeinterface (2, 4)
	37 if_icmpge (2, 4)
	40 dload_3 (2, 4)
	41 aload_0 (2, 4)
	42 iload (2, 4)
	44 iload_2 (2, 4)
	45 invokeinterface (2, 4)
	50 dadd (2, 4)
	51 dstore_3 (2, 4)
	52 iinc (2, 4)
	55 goto (2, 4)
	58 aload_1 (1, 4)
	59 iconst_0 (1, 4)
	60 aaload (1, 4)
	61 iload_2 (1, 4)
	62 dload_3 (1, 4)
	63 dastore (1, 4)
	64 iinc (1, 4)
	67 goto (1, 4)
	70 new (0, 0)
	73 dup (0, 0)
	74 aload_1 (0, 0)
	75 iconst_0 (0, 0)
	76 invokespecial (0, 0)
	79 areturn (0, 0)

Method: diag
	0 aload_0 (1, 1)
	1 invokeinterface (1, 1)
	6 iconst_1 (1, 1)
	7 if_icmpne (1, 1)
	10 aload_0 (1, 1)
	11 invokeinterface (1, 1)
	16 aload_0 (1, 1)
	17 invokeinterface (1, 1)
	22 multianewarray (1, 1)
	26 astore_1 (1, 1)
	27 iconst_0 (2, 4)
	28 istore_2 (2, 4)
	29 iload_2 (2, 4)
	30 aload_0 (2, 4)
	31 invokeinterface (2, 4)
	36 if_icmpge (2, 4)
	39 aload_1 (2, 4)
	40 iload_2 (2, 4)
	41 aaload (2, 4)
	42 iload_2 (2, 4)
	43 aload_0 (2, 4)
	44 iload_2 (2, 4)
	45 iconst_0 (2, 4)
	46 invokeinterface (2, 4)
	51 dastore (2, 4)
	52 iinc (2, 4)
	55 goto (2, 4)
	58 new (1, 1)
	61 dup (1, 1)
	62 aload_1 (1, 1)
	63 iconst_0 (1, 1)
	64 invokespecial (1, 1)
	67 areturn (1, 1)
	68 aload_0 (1, 2)
	69 invokeinterface (1, 2)
	74 iconst_1 (1, 2)
	75 multianewarray (1, 2)
	79 astore_1 (1, 2)
	80 iconst_0 (2, 4)
	81 istore_2 (2, 4)
	82 iload_2 (2, 4)
	83 aload_0 (2, 4)
	84 invokeinterface (2, 4)
	89 if_icmpge (2, 4)
	92 aload_1 (2, 4)
	93 iload_2 (2, 4)
	94 aaload (2, 4)
	95 iconst_0 (2, 4)
	96 aload_0 (2, 4)
	97 iload_2 (2, 4)
	98 iload_2 (2, 4)
	99 invokeinterface (2, 4)
	104 dastore (2, 4)
	105 iinc (2, 4)
	108 goto (2, 4)
	111 new (1, 2)
	114 dup (1, 2)
	115 aload_1 (1, 2)
	116 iconst_0 (1, 2)
	117 invokespecial (1, 2)
	120 areturn (1, 2)

Method: copyColumn
	0 iconst_0 (1, 4)
	1 istore (1, 4)
	3 iload (1, 4)
	5 aload_0 (1, 4)
	6 invokeinterface (1, 4)
	11 if_icmpge (1, 4)
	14 aload_2 (1, 4)
	15 iload (1, 4)
	17 iload_3 (1, 4)
	18 aload_0 (1, 4)
	19 iload (1, 4)
	21 iload_1 (1, 4)
	22 invokeinterface (1, 4)
	27 invokeinterface (1, 4)
	32 iinc (1, 4)
	35 goto (1, 4)
	38 return (0, 0)

Method: ones
	0 iload_0 (0, 0)
	1 iload_1 (0, 0)
	2 multianewarray (0, 0)
	6 astore_2 (0, 0)
	7 iconst_0 (1, 4)
	8 istore_3 (1, 4)
	9 iload_3 (1, 4)
	10 iload_0 (1, 4)
	11 if_icmpge (1, 4)
	14 aload_2 (1, 4)
	15 iload_3 (1, 4)
	16 aaload (1, 4)
	17 dconst_1 (1, 4)
	18 invokestatic (1, 4)
	21 iinc (1, 4)
	24 goto (1, 4)
	27 new (0, 0)
	30 dup (0, 0)
	31 aload_2 (0, 0)
	32 iconst_0 (0, 0)
	33 invokespecial (0, 0)
	36 areturn (0, 0)

Method: eye
	0 iload_0 (0, 0)
	1 iload_1 (0, 0)
	2 multianewarray (0, 0)
	6 astore_2 (0, 0)
	7 iconst_0 (1, 4)
	8 istore_3 (1, 4)
	9 iload_3 (1, 4)
	10 iload_0 (1, 4)
	11 if_icmpge (1, 4)
	14 iload_3 (2, 1)
	15 iload_1 (2, 1)
	16 if_icmpge (2, 1)
	19 aload_2 (2, 1)
	20 iload_3 (2, 1)
	21 aaload (2, 1)
	22 iload_3 (2, 1)
	23 dconst_1 (2, 1)
	24 dastore (2, 1)
	25 iinc (2, 1)
	28 goto (2, 1)
	31 new (1, 4)
	34 dup (1, 4)
	35 aload_2 (1, 4)
	36 iconst_0 (1, 4)
	37 invokespecial (1, 4)
	40 areturn (1, 4)

Method: zeros
	0 new (0, 0)
	3 dup (0, 0)
	4 iload_0 (0, 0)
	5 iload_1 (0, 0)
	6 invokespecial (0, 0)
	9 areturn (0, 0)

Method: repmat
	0 aload_0 (0, 0)
	1 invokeinterface (0, 0)
	6 istore_3 (0, 0)
	7 aload_0 (0, 0)
	8 invokeinterface (0, 0)
	13 istore (0, 0)
	15 iload_1 (0, 0)
	16 iload_3 (0, 0)
	17 imul (0, 0)
	18 iload_2 (0, 0)
	19 iload (0, 0)
	21 imul (0, 0)
	22 multianewarray (0, 0)
	26 astore (0, 0)
	28 iconst_0 (1, 4)
	29 istore (1, 4)
	31 iload (1, 4)
	33 iload_1 (1, 4)
	34 iload_3 (1, 4)
	35 imul (1, 4)
	36 if_icmpge (1, 4)
	39 iconst_0 (2, 4)
	40 istore (2, 4)
	42 iload (2, 4)
	44 iload_2 (2, 4)
	45 iload (2, 4)
	47 imul (2, 4)
	48 if_icmpge (2, 4)
	51 aload (2, 4)
	53 iload (2, 4)
	55 aaload (2, 4)
	56 iload (2, 4)
	58 aload_0 (2, 4)
	59 iload (2, 4)
	61 iload_3 (2, 4)
	62 irem (2, 4)
	63 iload (2, 4)
	65 iload (2, 4)
	67 irem (2, 4)
	68 invokeinterface (2, 4)
	73 dastore (2, 4)
	74 iinc (2, 4)
	77 goto (2, 4)
	80 iinc (2, 4)
	83 goto (2, 4)
	86 new (1, 4)
	89 dup (1, 4)
	90 aload (1, 4)
	92 iconst_0 (1, 4)
	93 invokespecial (1, 4)
	96 areturn (1, 4)

Method: sequence
	0 dload_2 (0, 0)
	1 dload_0 (0, 0)
	2 dsub (0, 0)
	3 dload (0, 0)
	5 ddiv (0, 0)
	6 dconst_1 (0, 0)
	7 dadd (0, 0)
	8 d2i (0, 0)
	9 istore (0, 0)
	11 iload (0, 0)
	13 iconst_1 (0, 0)
	14 multianewarray (0, 0)
	18 astore (0, 0)
	20 dload_0 (0, 0)
	21 dstore (0, 0)
	23 iconst_0 (1, 4)
	24 istore (1, 4)
	26 iload (1, 4)
	28 iload (1, 4)
	30 if_icmpge (1, 4)
	33 aload (1, 4)
	35 iload (1, 4)
	37 aaload (1, 4)
	38 iconst_0 (1, 4)
	39 dload (1, 4)
	41 dastore (1, 4)
	42 dload (1, 4)
	44 dload (1, 4)
	46 dadd (1, 4)
	47 dstore (1, 4)
	49 iinc (1, 4)
	52 goto (1, 4)
	55 new (0, 0)
	58 dup (0, 0)
	59 aload (0, 0)
	61 iconst_0 (0, 0)
	62 invokespecial (0, 0)
	65 areturn (0, 0)

Method: max
	0 ldc2_w (0, 0)
	3 dstore_1 (0, 0)
	4 iconst_0 (1, 4)
	5 istore_3 (1, 4)
	6 iload_3 (1, 4)
	7 aload_0 (1, 4)
	8 arraylength (1, 4)
	9 if_icmpge (1, 4)
	12 dload_1 (2, 1)
	13 aload_0 (2, 1)
	14 iload_3 (2, 1)
	15 daload (2, 1)
	16 dcmpg (2, 1)
	17 ifge (2, 1)
	20 aload_0 (2, 1)
	21 iload_3 (2, 1)
	22 daload (2, 1)
	23 dstore_1 (2, 1)
	24 iinc (2, 1)
	27 goto (2, 1)
	30 dload_1 (1, 4)
	31 dreturn (1, 4)

Method: min
	0 ldc2_w (0, 0)
	3 dstore_1 (0, 0)
	4 iconst_0 (1, 4)
	5 istore_3 (1, 4)
	6 iload_3 (1, 4)
	7 aload_0 (1, 4)
	8 arraylength (1, 4)
	9 if_icmpge (1, 4)
	12 dload_1 (2, 1)
	13 aload_0 (2, 1)
	14 iload_3 (2, 1)
	15 daload (2, 1)
	16 dcmpl (2, 1)
	17 ifle (2, 1)
	20 aload_0 (2, 1)
	21 iload_3 (2, 1)
	22 daload (2, 1)
	23 dstore_1 (2, 1)
	24 iinc (2, 1)
	27 goto (2, 1)
	30 dload_1 (1, 4)
	31 dreturn (1, 4)

Method: inverse
	0 aload_0 (0, 0)
	1 arraylength (0, 0)
	2 newarray (0, 0)
	4 astore_1 (0, 0)
	5 iconst_0 (1, 4)
	6 istore_2 (1, 4)
	7 iload_2 (1, 4)
	8 aload_0 (1, 4)
	9 arraylength (1, 4)
	10 if_icmpge (1, 4)
	13 aload_1 (1, 4)
	14 aload_0 (1, 4)
	15 iload_2 (1, 4)
	16 iaload (1, 4)
	17 iload_2 (1, 4)
	18 iastore (1, 4)
	19 iinc (1, 4)
	22 goto (1, 4)
	25 aload_1 (0, 0)
	26 areturn (0, 0)

Method: reverse
	0 aload_0 (0, 0)
	1 arraylength (0, 0)
	2 newarray (0, 0)
	4 astore_1 (0, 0)
	5 iconst_0 (1, 4)
	6 istore_2 (1, 4)
	7 iload_2 (1, 4)
	8 aload_0 (1, 4)
	9 arraylength (1, 4)
	10 if_icmpge (1, 4)
	13 aload_1 (1, 4)
	14 iload_2 (1, 4)
	15 aload_0 (1, 4)
	16 aload_0 (1, 4)
	17 arraylength (1, 4)
	18 iload_2 (1, 4)
	19 isub (1, 4)
	20 iconst_1 (1, 4)
	21 isub (1, 4)
	22 iaload (1, 4)
	23 iastore (1, 4)
	24 iinc (1, 4)
	27 goto (1, 4)
	30 aload_1 (0, 0)
	31 areturn (0, 0)

Method: randn
	0 iload_1 (0, 0)
	1 newarray (0, 0)
	3 astore_2 (0, 0)
	4 iconst_0 (1, 4)
	5 istore_3 (1, 4)
	6 iload_3 (1, 4)
	7 iload_1 (1, 4)
	8 if_icmpge (1, 4)
	11 aload_2 (1, 4)
	12 iload_3 (1, 4)
	13 aload_0 (1, 4)
	14 getfield (1, 4)
	17 invokeinterface (1, 4)
	22 dastore (1, 4)
	23 iinc (1, 4)
	26 goto (1, 4)
	29 aload_2 (0, 0)
	30 areturn (0, 0)

Method: randn1
	0 iload_1 (0, 0)
	1 iload_2 (0, 0)
	2 multianewarray (0, 0)
	6 astore_3 (0, 0)
	7 iconst_0 (1, 4)
	8 istore (1, 4)
	10 iload (1, 4)
	12 iload_1 (1, 4)
	13 if_icmpge (1, 4)
	16 iconst_0 (2, 4)
	17 istore (2, 4)
	19 iload (2, 4)
	21 iload_2 (2, 4)
	22 if_icmpge (2, 4)
	25 aload_3 (2, 4)
	26 iload (2, 4)
	28 aaload (2, 4)
	29 iload (2, 4)
	31 aload_0 (2, 4)
	32 getfield (2, 4)
	35 invokeinterface (2, 4)
	40 dastore (2, 4)
	41 iinc (2, 4)
	44 goto (2, 4)
	47 iinc (2, 4)
	50 goto (2, 4)
	53 new (1, 4)
	56 dup (1, 4)
	57 aload_3 (1, 4)
	58 iconst_0 (1, 4)
	59 invokespecial (1, 4)
	62 areturn (1, 4)

Method: access$200
	0 aload_0 (0, 0)
	1 getfield (0, 0)
	4 ireturn (0, 0)

Method: <clinit>
	0 new (0, 0)
	3 dup (0, 0)
	4 invokespecial (0, 0)
	7 putstatic (0, 0)
	10 return (0, 0)

