Method: <init>
	0 aload_0 (0, 0)
	1 invokespecial (0, 0)
	2 java/lang/Object.<init>:()V (0, 0)
	4 aload_0 (0, 0)
	5 dload_1 (0, 0)
	6 putfield (0, 0)
	7 org/apache/commons/math3/optimization/direct/MultivariateFunctionMappingAdapter$UpperBoundMapper.upper:D (0, 0)
	9 return (0, 0)

Method: unboundedToBounded
	0 aload_0 (0, 0)
	1 getfield (0, 0)
	2 org/apache/commons/math3/optimization/direct/MultivariateFunctionMappingAdapter$UpperBoundMapper.upper:D (0, 0)
	4 dload_1 (0, 0)
	5 dneg (0, 0)
	6 invokestatic (0, 0)
	7 org/apache/commons/math3/util/FastMath.exp:(D)D (0, 0)
	9 dsub (0, 0)
	10 dreturn (0, 0)

Method: boundedToUnbounded
	0 aload_0 (0, 0)
	1 getfield (0, 0)
	2 org/apache/commons/math3/optimization/direct/MultivariateFunctionMappingAdapter$UpperBoundMapper.upper:D (0, 0)
	4 dload_1 (0, 0)
	5 dsub (0, 0)
	6 invokestatic (0, 0)
	7 org/apache/commons/math3/util/FastMath.log:(D)D (0, 0)
	9 dneg (0, 0)
	10 dreturn (0, 0)

