Method: <init>
	0 aload_0 (0, 0)
	1 invokespecial (0, 0)
	4 aload_0 (0, 0)
	5 new (0, 0)
	8 dup (0, 0)
	9 dload_1 (0, 0)
	10 dload_3 (0, 0)
	11 invokespecial (0, 0)
	14 putfield (0, 0)
	17 aload_0 (0, 0)
	18 new (0, 0)
	21 dup (0, 0)
	22 dload_1 (0, 0)
	23 dload_3 (0, 0)
	24 invokespecial (0, 0)
	27 putfield (0, 0)
	30 return (0, 0)

Method: unboundedToBounded
	0 aload_0 (0, 0)
	1 getfield (0, 0)
	4 dload_1 (0, 0)
	5 invokeinterface (0, 0)
	10 dreturn (0, 0)

Method: boundedToUnbounded
	0 aload_0 (0, 0)
	1 getfield (0, 0)
	4 dload_1 (0, 0)
	5 invokeinterface (0, 0)
	10 dreturn (0, 0)

