Method: <init>
	0 aload_0 (0, 0)
	1 aload_1 (0, 0)
	2 invokespecial (0, 0)
	3 org/apache/commons/math3/optimization/direct/AbstractSimplex.<init>:([[D)V (0, 0)
	5 aload_0 (0, 0)
	6 dload_2 (0, 0)
	7 putfield (0, 0)
	8 org/apache/commons/math3/optimization/direct/NelderMeadSimplex.rho:D (0, 0)
	10 aload_0 (0, 0)
	11 dload (0, 0)
	12 #4 (0, 0)
	13 putfield (0, 0)
	14 org/apache/commons/math3/optimization/direct/NelderMeadSimplex.khi:D (0, 0)
	16 aload_0 (0, 0)
	17 dload (0, 0)
	18 #6 (0, 0)
	19 putfield (0, 0)
	20 org/apache/commons/math3/optimization/direct/NelderMeadSimplex.gamma:D (0, 0)
	22 aload_0 (0, 0)
	23 dload (0, 0)
	24 #8 (0, 0)
	25 putfield (0, 0)
	26 org/apache/commons/math3/optimization/direct/NelderMeadSimplex.sigma:D (0, 0)
	28 return (0, 0)

Method: iterate
	0 aload_0 (0, 0)
	1 invokevirtual (0, 0)
	2 org/apache/commons/math3/optimization/direct/NelderMeadSimplex.getDimension:()I (0, 0)
	4 istore_3 (0, 0)
	5 aload_0 (0, 0)
	6 iconst_0 (0, 0)
	7 invokevirtual (0, 0)
	8 org/apache/commons/math3/optimization/direct/NelderMeadSimplex.getPoint:(I)Lorg/apache/commons/math3/optimization/PointValuePair; (0, 0)
	10 astore (0, 0)
	11 #4 (0, 0)
	12 aload_0 (0, 0)
	13 iload_3 (0, 0)
	14 iconst_1 (0, 0)
	15 isub (0, 0)
	16 invokevirtual (0, 0)
	17 org/apache/commons/math3/optimization/direct/NelderMeadSimplex.getPoint:(I)Lorg/apache/commons/math3/optimization/PointValuePair; (0, 0)
	19 astore (0, 0)
	20 #5 (0, 0)
	21 aload_0 (0, 0)
	22 iload_3 (0, 0)
	23 invokevirtual (0, 0)
	24 org/apache/commons/math3/optimization/direct/NelderMeadSimplex.getPoint:(I)Lorg/apache/commons/math3/optimization/PointValuePair; (0, 0)
	26 astore (0, 0)
	27 #6 (0, 0)
	28 aload (0, 0)
	29 #6 (0, 0)
	30 invokevirtual (0, 0)
	31 org/apache/commons/math3/optimization/PointValuePair.getPointRef:()[D (0, 0)
	33 astore (0, 0)
	34 #7 (0, 0)
	35 iload_3 (0, 0)
	36 newarray (0, 0)
	37 7 (0, 0)
	38 astore (0, 0)
	39 #8 (0, 0)
	40 iconst_0 (1, 4)
	41 istore (1, 4)
	42 #9 (1, 4)
	43 iload (1, 4)
	44 #9 (1, 4)
	45 iload_3 (1, 4)
	46 if_icmpge (1, 4)
	47 48 (1, 4)
	49 aload_0 (1, 4)
	50 iload (1, 4)
	51 #9 (1, 4)
	52 invokevirtual (1, 4)
	53 org/apache/commons/math3/optimization/direct/NelderMeadSimplex.getPoint:(I)Lorg/apache/commons/math3/optimization/PointValuePair; (1, 4)
	55 invokevirtual (1, 4)
	56 org/apache/commons/math3/optimization/PointValuePair.getPointRef:()[D (1, 4)
	58 astore (1, 4)
	59 #10 (1, 4)
	60 iconst_0 (2, 4)
	61 istore (2, 4)
	62 #11 (2, 4)
	63 iload (2, 4)
	64 #11 (2, 4)
	65 iload_3 (2, 4)
	66 if_icmpge (2, 4)
	67 22 (2, 4)
	69 aload (2, 4)
	70 #8 (2, 4)
	71 iload (2, 4)
	72 #11 (2, 4)
	73 dup2 (2, 4)
	74 daload (2, 4)
	75 aload (2, 4)
	76 #10 (2, 4)
	77 iload (2, 4)
	78 #11 (2, 4)
	79 daload (2, 4)
	80 dadd (2, 4)
	81 dastore (2, 4)
	82 iinc (2, 4)
	83 #11 (2, 4)
	84 -89 (2, 4)
	85 goto (2, 4)
	86 -22 (2, 4)
	88 iinc (2, 4)
	89 #9 (2, 4)
	90 -89 (2, 4)
	91 goto (2, 4)
	92 -48 (2, 4)
	94 dconst_1 (1, 4)
	95 iload_3 (1, 4)
	96 i2d (1, 4)
	97 ddiv (1, 4)
	98 dstore (1, 4)
	99 #9 (1, 4)
	100 iconst_0 (2, 4)
	101 istore (2, 4)
	102 #11 (2, 4)
	103 iload (2, 4)
	104 #11 (2, 4)
	105 iload_3 (2, 4)
	106 if_icmpge (2, 4)
	107 19 (2, 4)
	109 aload (2, 4)
	110 #8 (2, 4)
	111 iload (2, 4)
	112 #11 (2, 4)
	113 dup2 (2, 4)
	114 daload (2, 4)
	115 dload (2, 4)
	116 #9 (2, 4)
	117 dmul (2, 4)
	118 dastore (2, 4)
	119 iinc (2, 4)
	120 #11 (2, 4)
	121 -89 (2, 4)
	122 goto (2, 4)
	123 -19 (2, 4)
	125 iload_3 (1, 4)
	126 newarray (1, 4)
	127 7 (1, 4)
	128 astore (1, 4)
	129 #11 (1, 4)
	130 iconst_0 (2, 4)
	131 istore (2, 4)
	132 #12 (2, 4)
	133 iload (2, 4)
	134 #12 (2, 4)
	135 iload_3 (2, 4)
	136 if_icmpge (2, 4)
	137 36 (2, 4)
	139 aload (2, 4)
	140 #11 (2, 4)
	141 iload (2, 4)
	142 #12 (2, 4)
	143 aload (2, 4)
	144 #8 (2, 4)
	145 iload (2, 4)
	146 #12 (2, 4)
	147 daload (2, 4)
	148 aload_0 (2, 4)
	149 getfield (2, 4)
	150 org/apache/commons/math3/optimization/direct/NelderMeadSimplex.rho:D (2, 4)
	152 aload (2, 4)
	153 #8 (2, 4)
	154 iload (2, 4)
	155 #12 (2, 4)
	156 daload (2, 4)
	157 aload (2, 4)
	158 #7 (2, 4)
	159 iload (2, 4)
	160 #12 (2, 4)
	161 daload (2, 4)
	162 dsub (2, 4)
	163 dmul (2, 4)
	164 dadd (2, 4)
	165 dastore (2, 4)
	166 iinc (2, 4)
	167 #12 (2, 4)
	168 -89 (2, 4)
	169 goto (2, 4)
	170 -36 (2, 4)
	172 new (1, 4)
	173 org/apache/commons/math3/optimization/PointValuePair (1, 4)
	175 dup (1, 4)
	176 aload (1, 4)
	177 #11 (1, 4)
	178 aload_1 (1, 4)
	179 aload (1, 4)
	180 #11 (1, 4)
	181 invokeinterface (1, 4)
	182 org/apache/commons/math3/analysis/MultivariateFunction.<init>:([DDZ)V (1, 4)
	184 0 (1, 4)
	186 iconst_0 (1, 4)
	187 invokespecial (1, 4)
	188 org/apache/commons/math3/optimization/PointValuePair.<init>:([DDZ)V (1, 4)
	190 astore (1, 4)
	191 #12 (1, 4)
	192 aload_2 (1, 1)
	193 aload (1, 1)
	194 #4 (1, 1)
	195 aload (1, 1)
	196 #12 (1, 1)
	197 invokeinterface (1, 1)
	198 java/util/Comparator.replaceWorstPoint:(Lorg/apache/commons/math3/optimization/PointValuePair;Ljava/util/Comparator;)V (1, 1)
	200 0 (1, 1)
	202 ifgt (1, 1)
	203 26 (1, 1)
	205 aload_2 (1, 1)
	206 aload (1, 1)
	207 #12 (1, 1)
	208 aload (1, 1)
	209 #5 (1, 1)
	210 invokeinterface (1, 1)
	211 java/util/Comparator.replaceWorstPoint:(Lorg/apache/commons/math3/optimization/PointValuePair;Ljava/util/Comparator;)V (1, 1)
	213 0 (1, 1)
	215 ifge (1, 1)
	216 13 (1, 1)
	218 aload_0 (1, 1)
	219 aload (1, 1)
	220 #12 (1, 1)
	221 aload_2 (1, 1)
	222 invokevirtual (1, 1)
	223 org/apache/commons/math3/optimization/direct/NelderMeadSimplex.replaceWorstPoint:(Lorg/apache/commons/math3/optimization/PointValuePair;Ljava/util/Comparator;)V (1, 1)
	225 goto (1, 1)
	226 411 (1, 1)
	228 aload_2 (2, 1)
	229 aload (2, 1)
	230 #12 (2, 1)
	231 aload (2, 1)
	232 #4 (2, 1)
	233 invokeinterface (2, 1)
	234 java/util/Comparator.replaceWorstPoint:(Lorg/apache/commons/math3/optimization/PointValuePair;Ljava/util/Comparator;)V (2, 1)
	236 0 (2, 1)
	238 ifge (2, 1)
	239 103 (2, 1)
	241 iload_3 (2, 1)
	242 newarray (2, 1)
	243 7 (2, 1)
	244 astore (2, 1)
	245 #13 (2, 1)
	246 iconst_0 (3, 4)
	247 istore (3, 4)
	248 #14 (3, 4)
	249 iload (3, 4)
	250 #14 (3, 4)
	251 iload_3 (3, 4)
	252 if_icmpge (3, 4)
	253 36 (3, 4)
	255 aload (3, 4)
	256 #13 (3, 4)
	257 iload (3, 4)
	258 #14 (3, 4)
	259 aload (3, 4)
	260 #8 (3, 4)
	261 iload (3, 4)
	262 #14 (3, 4)
	263 daload (3, 4)
	264 aload_0 (3, 4)
	265 getfield (3, 4)
	266 org/apache/commons/math3/optimization/direct/NelderMeadSimplex.khi:D (3, 4)
	268 aload (3, 4)
	269 #11 (3, 4)
	270 iload (3, 4)
	271 #14 (3, 4)
	272 daload (3, 4)
	273 aload (3, 4)
	274 #8 (3, 4)
	275 iload (3, 4)
	276 #14 (3, 4)
	277 daload (3, 4)
	278 dsub (3, 4)
	279 dmul (3, 4)
	280 dadd (3, 4)
	281 dastore (3, 4)
	282 iinc (3, 4)
	283 #14 (3, 4)
	284 -89 (3, 4)
	285 goto (3, 4)
	286 -36 (3, 4)
	288 new (2, 1)
	289 org/apache/commons/math3/optimization/PointValuePair (2, 1)
	291 dup (2, 1)
	292 aload (2, 1)
	293 #13 (2, 1)
	294 aload_1 (2, 1)
	295 aload (2, 1)
	296 #13 (2, 1)
	297 invokeinterface (2, 1)
	298 org/apache/commons/math3/analysis/MultivariateFunction.<init>:([DDZ)V (2, 1)
	300 0 (2, 1)
	302 iconst_0 (2, 1)
	303 invokespecial (2, 1)
	304 org/apache/commons/math3/optimization/PointValuePair.<init>:([DDZ)V (2, 1)
	306 astore (2, 1)
	307 #14 (2, 1)
	308 aload_2 (3, 1)
	309 aload (3, 1)
	310 #14 (3, 1)
	311 aload (3, 1)
	312 #12 (3, 1)
	313 invokeinterface (3, 1)
	314 java/util/Comparator.replaceWorstPoint:(Lorg/apache/commons/math3/optimization/PointValuePair;Ljava/util/Comparator;)V (3, 1)
	316 0 (3, 1)
	318 ifge (3, 1)
	319 13 (3, 1)
	321 aload_0 (3, 1)
	322 aload (3, 1)
	323 #14 (3, 1)
	324 aload_2 (3, 1)
	325 invokevirtual (3, 1)
	326 org/apache/commons/math3/optimization/direct/NelderMeadSimplex.replaceWorstPoint:(Lorg/apache/commons/math3/optimization/PointValuePair;Ljava/util/Comparator;)V (3, 1)
	328 goto (3, 1)
	329 10 (3, 1)
	331 aload_0 (3, 2)
	332 aload (3, 2)
	333 #12 (3, 2)
	334 aload_2 (3, 2)
	335 invokevirtual (3, 2)
	336 org/apache/commons/math3/optimization/direct/NelderMeadSimplex.replaceWorstPoint:(Lorg/apache/commons/math3/optimization/PointValuePair;Ljava/util/Comparator;)V (3, 2)
	338 goto (2, 2)
	339 298 (2, 2)
	341 aload_2 (3, 1)
	342 aload (3, 1)
	343 #12 (3, 1)
	344 aload (3, 1)
	345 #6 (3, 1)
	346 invokeinterface (3, 1)
	347 java/util/Comparator.replaceWorstPoint:(Lorg/apache/commons/math3/optimization/PointValuePair;Ljava/util/Comparator;)V (3, 1)
	349 0 (3, 1)
	351 ifge (3, 1)
	352 94 (3, 1)
	354 iload_3 (3, 4)
	355 newarray (3, 4)
	356 7 (3, 4)
	357 astore (3, 4)
	358 #13 (3, 4)
	359 iconst_0 (4, 4)
	360 istore (4, 4)
	361 #14 (4, 4)
	362 iload (4, 4)
	363 #14 (4, 4)
	364 iload_3 (4, 4)
	365 if_icmpge (4, 4)
	366 36 (4, 4)
	368 aload (4, 4)
	369 #13 (4, 4)
	370 iload (4, 4)
	371 #14 (4, 4)
	372 aload (4, 4)
	373 #8 (4, 4)
	374 iload (4, 4)
	375 #14 (4, 4)
	376 daload (4, 4)
	377 aload_0 (4, 4)
	378 getfield (4, 4)
	379 org/apache/commons/math3/optimization/direct/NelderMeadSimplex.gamma:D (4, 4)
	381 aload (4, 4)
	382 #11 (4, 4)
	383 iload (4, 4)
	384 #14 (4, 4)
	385 daload (4, 4)
	386 aload (4, 4)
	387 #8 (4, 4)
	388 iload (4, 4)
	389 #14 (4, 4)
	390 daload (4, 4)
	391 dsub (4, 4)
	392 dmul (4, 4)
	393 dadd (4, 4)
	394 dastore (4, 4)
	395 iinc (4, 4)
	396 #14 (4, 4)
	397 -89 (4, 4)
	398 goto (4, 4)
	399 -36 (4, 4)
	401 new (3, 4)
	402 org/apache/commons/math3/optimization/PointValuePair (3, 4)
	404 dup (3, 4)
	405 aload (3, 4)
	406 #13 (3, 4)
	407 aload_1 (3, 4)
	408 aload (3, 4)
	409 #13 (3, 4)
	410 invokeinterface (3, 4)
	411 org/apache/commons/math3/analysis/MultivariateFunction.<init>:([DDZ)V (3, 4)
	413 0 (3, 4)
	415 iconst_0 (3, 4)
	416 invokespecial (3, 4)
	417 org/apache/commons/math3/optimization/PointValuePair.<init>:([DDZ)V (3, 4)
	419 astore (3, 4)
	420 #14 (3, 4)
	421 aload_2 (4, 1)
	422 aload (4, 1)
	423 #14 (4, 1)
	424 aload (4, 1)
	425 #12 (4, 1)
	426 invokeinterface (4, 1)
	427 java/util/Comparator.replaceWorstPoint:(Lorg/apache/commons/math3/optimization/PointValuePair;Ljava/util/Comparator;)V (4, 1)
	429 0 (4, 1)
	431 ifgt (4, 1)
	432 11 (4, 1)
	434 aload_0 (4, 1)
	435 aload (4, 1)
	436 #14 (4, 1)
	437 aload_2 (4, 1)
	438 invokevirtual (4, 1)
	439 org/apache/commons/math3/optimization/direct/NelderMeadSimplex.replaceWorstPoint:(Lorg/apache/commons/math3/optimization/PointValuePair;Ljava/util/Comparator;)V (4, 1)
	441 return (4, 1)
	442 goto (3, 2)
	443 91 (3, 2)
	445 iload_3 (3, 4)
	446 newarray (3, 4)
	447 7 (3, 4)
	448 astore (3, 4)
	449 #13 (3, 4)
	450 iconst_0 (4, 4)
	451 istore (4, 4)
	452 #14 (4, 4)
	453 iload (4, 4)
	454 #14 (4, 4)
	455 iload_3 (4, 4)
	456 if_icmpge (4, 4)
	457 36 (4, 4)
	459 aload (4, 4)
	460 #13 (4, 4)
	461 iload (4, 4)
	462 #14 (4, 4)
	463 aload (4, 4)
	464 #8 (4, 4)
	465 iload (4, 4)
	466 #14 (4, 4)
	467 daload (4, 4)
	468 aload_0 (4, 4)
	469 getfield (4, 4)
	470 org/apache/commons/math3/optimization/direct/NelderMeadSimplex.gamma:D (4, 4)
	472 aload (4, 4)
	473 #8 (4, 4)
	474 iload (4, 4)
	475 #14 (4, 4)
	476 daload (4, 4)
	477 aload (4, 4)
	478 #7 (4, 4)
	479 iload (4, 4)
	480 #14 (4, 4)
	481 daload (4, 4)
	482 dsub (4, 4)
	483 dmul (4, 4)
	484 dsub (4, 4)
	485 dastore (4, 4)
	486 iinc (4, 4)
	487 #14 (4, 4)
	488 -89 (4, 4)
	489 goto (4, 4)
	490 -36 (4, 4)
	492 new (3, 4)
	493 org/apache/commons/math3/optimization/PointValuePair (3, 4)
	495 dup (3, 4)
	496 aload (3, 4)
	497 #13 (3, 4)
	498 aload_1 (3, 4)
	499 aload (3, 4)
	500 #13 (3, 4)
	501 invokeinterface (3, 4)
	502 org/apache/commons/math3/analysis/MultivariateFunction.<init>:([DDZ)V (3, 4)
	504 0 (3, 4)
	506 iconst_0 (3, 4)
	507 invokespecial (3, 4)
	508 org/apache/commons/math3/optimization/PointValuePair.<init>:([DDZ)V (3, 4)
	510 astore (3, 4)
	511 #14 (3, 4)
	512 aload_2 (4, 1)
	513 aload (4, 1)
	514 #14 (4, 1)
	515 aload (4, 1)
	516 #6 (4, 1)
	517 invokeinterface (4, 1)
	518 java/util/Comparator.replaceWorstPoint:(Lorg/apache/commons/math3/optimization/PointValuePair;Ljava/util/Comparator;)V (4, 1)
	520 0 (4, 1)
	522 ifge (4, 1)
	523 11 (4, 1)
	525 aload_0 (4, 1)
	526 aload (4, 1)
	527 #14 (4, 1)
	528 aload_2 (4, 1)
	529 invokevirtual (4, 1)
	530 org/apache/commons/math3/optimization/direct/NelderMeadSimplex.replaceWorstPoint:(Lorg/apache/commons/math3/optimization/PointValuePair;Ljava/util/Comparator;)V (4, 1)
	532 return (4, 1)
	533 aload_0 (2, 4)
	534 iconst_0 (2, 4)
	535 invokevirtual (2, 4)
	536 org/apache/commons/math3/optimization/direct/NelderMeadSimplex.getPoint:(I)Lorg/apache/commons/math3/optimization/PointValuePair; (2, 4)
	538 invokevirtual (2, 4)
	539 org/apache/commons/math3/optimization/PointValuePair.getPointRef:()[D (2, 4)
	541 astore (2, 4)
	542 #13 (2, 4)
	543 iconst_1 (3, 4)
	544 istore (3, 4)
	545 #14 (3, 4)
	546 iload (3, 4)
	547 #14 (3, 4)
	548 iload_3 (3, 4)
	549 if_icmpgt (3, 4)
	550 81 (3, 4)
	552 aload_0 (3, 4)
	553 iload (3, 4)
	554 #14 (3, 4)
	555 invokevirtual (3, 4)
	556 org/apache/commons/math3/optimization/direct/NelderMeadSimplex.getPoint:(I)Lorg/apache/commons/math3/optimization/PointValuePair; (3, 4)
	558 invokevirtual (3, 4)
	559 org/apache/commons/math3/optimization/PointValuePair.getPoint:()[D (3, 4)
	561 astore (3, 4)
	562 #15 (3, 4)
	563 iconst_0 (4, 4)
	564 istore (4, 4)
	565 #16 (4, 4)
	566 iload (4, 4)
	567 #16 (4, 4)
	568 iload_3 (4, 4)
	569 if_icmpge (4, 4)
	570 36 (4, 4)
	572 aload (4, 4)
	573 #15 (4, 4)
	574 iload (4, 4)
	575 #16 (4, 4)
	576 aload (4, 4)
	577 #13 (4, 4)
	578 iload (4, 4)
	579 #16 (4, 4)
	580 daload (4, 4)
	581 aload_0 (4, 4)
	582 getfield (4, 4)
	583 org/apache/commons/math3/optimization/direct/NelderMeadSimplex.sigma:D (4, 4)
	585 aload (4, 4)
	586 #15 (4, 4)
	587 iload (4, 4)
	588 #16 (4, 4)
	589 daload (4, 4)
	590 aload (4, 4)
	591 #13 (4, 4)
	592 iload (4, 4)
	593 #16 (4, 4)
	594 daload (4, 4)
	595 dsub (4, 4)
	596 dmul (4, 4)
	597 dadd (4, 4)
	598 dastore (4, 4)
	599 iinc (4, 4)
	600 #16 (4, 4)
	601 -89 (4, 4)
	602 goto (4, 4)
	603 -36 (4, 4)
	605 aload_0 (3, 4)
	606 iload (3, 4)
	607 #14 (3, 4)
	608 new (3, 4)
	609 org/apache/commons/math3/optimization/PointValuePair (3, 4)
	611 dup (3, 4)
	612 aload (3, 4)
	613 #15 (3, 4)
	614 ldc2_w (3, 4)
	615 nan (3, 4)
	617 iconst_0 (3, 4)
	618 invokespecial (3, 4)
	619 org/apache/commons/math3/optimization/PointValuePair.<init>:([DDZ)V (3, 4)
	621 invokevirtual (3, 4)
	622 org/apache/commons/math3/optimization/direct/NelderMeadSimplex.setPoint:(ILorg/apache/commons/math3/optimization/PointValuePair;)V (3, 4)
	624 iinc (3, 4)
	625 #14 (3, 4)
	626 -89 (3, 4)
	627 goto (3, 4)
	628 -81 (3, 4)
	630 aload_0 (2, 4)
	631 aload_1 (2, 4)
	632 aload_2 (2, 4)
	633 invokevirtual (2, 4)
	634 org/apache/commons/math3/optimization/direct/NelderMeadSimplex.evaluate:(Lorg/apache/commons/math3/analysis/MultivariateFunction;Ljava/util/Comparator;)V (2, 4)
	636 return (0, 0)

