Method: <init>
	0 aload_0 (0, 0)
	1 dload_1 (0, 0)
	2 dload_3 (0, 0)
	3 dload (0, 0)
	4 #5 (0, 0)
	5 dload (0, 0)
	6 #7 (0, 0)
	7 aconst_null (0, 0)
	8 invokespecial (0, 0)
	9 org/apache/commons/math3/optimization/direct/PowellOptimizer.<init>:(DDDDLorg/apache/commons/math3/optimization/ConvergenceChecker;)V (0, 0)
	11 return (0, 0)

Method: doOptimize
	0 aload_0 (0, 0)
	1 invokevirtual (0, 0)
	2 org/apache/commons/math3/optimization/direct/PowellOptimizer.getGoalType:()Lorg/apache/commons/math3/optimization/GoalType; (0, 0)
	4 astore_1 (0, 0)
	5 aload_0 (0, 0)
	6 invokevirtual (0, 0)
	7 org/apache/commons/math3/optimization/direct/PowellOptimizer.getStartPoint:()[D (0, 0)
	9 astore_2 (0, 0)
	10 aload_2 (0, 0)
	11 arraylength (0, 0)
	12 istore_3 (0, 0)
	13 iload_3 (0, 0)
	14 iload_3 (0, 0)
	15 multianewarray (0, 0)
	16 [[D (0, 0)
	18 58 (0, 0)
	19 astore (0, 0)
	20 #4 (0, 0)
	21 iconst_0 (1, 4)
	22 istore (1, 4)
	23 #5 (1, 4)
	24 iload (1, 4)
	25 #5 (1, 4)
	26 iload_3 (1, 4)
	27 if_icmpge (1, 4)
	28 18 (1, 4)
	30 aload (1, 4)
	31 #4 (1, 4)
	32 iload (1, 4)
	33 #5 (1, 4)
	34 aaload (1, 4)
	35 iload (1, 4)
	36 #5 (1, 4)
	37 dconst_1 (1, 4)
	38 dastore (1, 4)
	39 iinc (1, 4)
	40 #5 (1, 4)
	41 -89 (1, 4)
	42 goto (1, 4)
	43 -18 (1, 4)
	45 aload_0 (0, 0)
	46 invokevirtual (0, 0)
	47 org/apache/commons/math3/optimization/direct/PowellOptimizer.getConvergenceChecker:()Lorg/apache/commons/math3/optimization/ConvergenceChecker; (0, 0)
	49 astore (0, 0)
	50 #5 (0, 0)
	51 aload_2 (0, 0)
	52 astore (0, 0)
	53 #6 (0, 0)
	54 aload_0 (0, 0)
	55 aload (0, 0)
	56 #6 (0, 0)
	57 invokevirtual (0, 0)
	58 org/apache/commons/math3/optimization/direct/PowellOptimizer.computeObjectiveValue:([D)D (0, 0)
	60 dstore (0, 0)
	61 #7 (0, 0)
	62 aload (0, 0)
	63 #6 (0, 0)
	64 invokevirtual (0, 0)
	65 [D.clone:()Ljava/lang/Object; (0, 0)
	67 checkcast (0, 0)
	68 [D (0, 0)
	70 astore (0, 0)
	71 #9 (0, 0)
	72 iconst_0 (0, 0)
	73 istore (0, 0)
	74 #10 (0, 0)
	75 iinc (1, 3)
	76 #10 (1, 3)
	77 24 (1, 3)
	78 dload (1, 3)
	79 #7 (1, 3)
	80 dstore (1, 3)
	81 #11 (1, 3)
	82 dconst_0 (1, 3)
	83 dstore (1, 3)
	84 #13 (1, 3)
	85 dconst_0 (1, 3)
	86 dstore (1, 3)
	87 #15 (1, 3)
	88 iconst_0 (1, 3)
	89 istore (1, 3)
	90 #17 (1, 3)
	91 dconst_0 (1, 3)
	92 dstore (1, 3)
	93 #18 (1, 3)
	94 iconst_0 (2, 4)
	95 istore (2, 4)
	96 #20 (2, 4)
	97 iload (2, 4)
	98 #20 (2, 4)
	99 iload_3 (2, 4)
	100 if_icmpge (2, 4)
	101 90 (2, 4)
	103 aload (2, 4)
	104 #4 (2, 4)
	105 iload (2, 4)
	106 #20 (2, 4)
	107 aaload (2, 4)
	108 invokestatic (2, 4)
	109 org/apache/commons/math3/util/MathArrays.copyOf:([D)[D (2, 4)
	111 astore (2, 4)
	112 #21 (2, 4)
	113 dload (2, 4)
	114 #7 (2, 4)
	115 dstore (2, 4)
	116 #13 (2, 4)
	117 aload_0 (2, 4)
	118 getfield (2, 4)
	119 org/apache/commons/math3/optimization/direct/PowellOptimizer.line:Lorg/apache/commons/math3/optimization/direct/PowellOptimizer$LineSearch; (2, 4)
	121 aload (2, 4)
	122 #6 (2, 4)
	123 aload (2, 4)
	124 #21 (2, 4)
	125 invokevirtual (2, 4)
	126 org/apache/commons/math3/optimization/direct/PowellOptimizer$LineSearch.search:([D[D)Lorg/apache/commons/math3/optimization/univariate/UnivariatePointValuePair; (2, 4)
	128 astore (2, 4)
	129 #22 (2, 4)
	130 aload (2, 4)
	131 #22 (2, 4)
	132 invokevirtual (2, 4)
	133 org/apache/commons/math3/optimization/univariate/UnivariatePointValuePair.getValue:()D (2, 4)
	135 dstore (2, 4)
	136 #7 (2, 4)
	137 aload (2, 4)
	138 #22 (2, 4)
	139 invokevirtual (2, 4)
	140 org/apache/commons/math3/optimization/univariate/UnivariatePointValuePair.getPoint:()D (2, 4)
	142 dstore (2, 4)
	143 #18 (2, 4)
	144 aload_0 (2, 4)
	145 aload (2, 4)
	146 #6 (2, 4)
	147 aload (2, 4)
	148 #21 (2, 4)
	149 dload (2, 4)
	150 #18 (2, 4)
	151 invokespecial (2, 4)
	152 org/apache/commons/math3/optimization/direct/PowellOptimizer.newPointAndDirection:([D[DD)[[D (2, 4)
	154 astore (2, 4)
	155 #23 (2, 4)
	156 aload (2, 4)
	157 #23 (2, 4)
	158 iconst_0 (2, 4)
	159 aaload (2, 4)
	160 astore (2, 4)
	161 #6 (2, 4)
	162 dload (3, 1)
	163 #13 (3, 1)
	164 dload (3, 1)
	165 #7 (3, 1)
	166 dsub (3, 1)
	167 dload (3, 1)
	168 #15 (3, 1)
	169 dcmpl (3, 1)
	170 ifle (3, 1)
	171 14 (3, 1)
	173 dload (3, 1)
	174 #13 (3, 1)
	175 dload (3, 1)
	176 #7 (3, 1)
	177 dsub (3, 1)
	178 dstore (3, 1)
	179 #15 (3, 1)
	180 iload (3, 1)
	181 #20 (3, 1)
	182 istore (3, 1)
	183 #17 (3, 1)
	184 iinc (3, 1)
	185 #20 (3, 1)
	186 -89 (3, 1)
	187 goto (3, 1)
	188 -90 (3, 1)
	190 ldc2_w (2, 4)
	191 2.0 (2, 4)
	193 dload (2, 4)
	194 #11 (2, 4)
	195 dload (2, 4)
	196 #7 (2, 4)
	197 dsub (2, 4)
	198 dmul (2, 4)
	199 aload_0 (2, 4)
	200 getfield (2, 4)
	201 org/apache/commons/math3/optimization/direct/PowellOptimizer.relativeThreshold:D (2, 4)
	203 dload (2, 4)
	204 #11 (2, 4)
	205 invokestatic (2, 4)
	206 org/apache/commons/math3/util/FastMath.abs:(D)D (2, 4)
	208 dload (2, 4)
	209 #7 (2, 4)
	210 invokestatic (2, 4)
	211 org/apache/commons/math3/util/FastMath.abs:(D)D (2, 4)
	213 dadd (2, 4)
	214 dmul (2, 4)
	215 aload_0 (2, 4)
	216 getfield (2, 4)
	217 org/apache/commons/math3/optimization/direct/PowellOptimizer.absoluteThreshold:D (2, 4)
	219 dadd (2, 4)
	220 dcmpg (2, 4)
	221 ifgt (2, 4)
	222 7 (2, 4)
	224 iconst_1 (2, 4)
	225 goto (2, 4)
	226 4 (2, 4)
	228 iconst_0 (2, 4)
	229 istore (2, 4)
	230 #20 (2, 4)
	231 new (2, 4)
	232 org/apache/commons/math3/optimization/PointValuePair (2, 4)
	234 dup (2, 4)
	235 aload (2, 4)
	236 #9 (2, 4)
	237 dload (2, 4)
	238 #11 (2, 4)
	239 invokespecial (2, 4)
	240 org/apache/commons/math3/optimization/PointValuePair.<init>:([DD)V (2, 4)
	242 astore (2, 4)
	243 #21 (2, 4)
	244 new (2, 4)
	245 org/apache/commons/math3/optimization/PointValuePair (2, 4)
	247 dup (2, 4)
	248 aload (2, 4)
	249 #6 (2, 4)
	250 dload (2, 4)
	251 #7 (2, 4)
	252 invokespecial (2, 4)
	253 org/apache/commons/math3/optimization/PointValuePair.<init>:([DD)V (2, 4)
	255 astore (2, 4)
	256 #22 (2, 4)
	257 iload (3, 1)
	258 #20 (3, 1)
	259 ifne (3, 1)
	260 23 (3, 1)
	262 aload (3, 1)
	263 #5 (3, 1)
	264 ifnull (3, 1)
	265 18 (3, 1)
	267 aload (3, 1)
	268 #5 (3, 1)
	269 iload (3, 1)
	270 #10 (3, 1)
	271 aload (3, 1)
	272 #21 (3, 1)
	273 aload (3, 1)
	274 #22 (3, 1)
	275 invokeinterface (3, 1)
	276 org/apache/commons/math3/optimization/ConvergenceChecker.org/apache/commons/math3/optimization/GoalType (3, 1)
	278 0 (3, 1)
	280 istore (3, 1)
	281 #20 (3, 1)
	282 iload (3, 1)
	283 #20 (3, 1)
	284 ifeq (3, 1)
	285 42 (3, 1)
	287 aload_1 (4, 1)
	288 getstatic (4, 1)
	289 org/apache/commons/math3/optimization/GoalType.MINIMIZE:Lorg/apache/commons/math3/optimization/GoalType; (4, 1)
	291 if_acmpne (4, 1)
	292 19 (4, 1)
	294 dload (4, 1)
	295 #7 (4, 1)
	296 dload (4, 1)
	297 #11 (4, 1)
	298 dcmpg (4, 1)
	299 ifge (4, 1)
	300 8 (4, 1)
	302 aload (4, 1)
	303 #22 (4, 1)
	304 goto (4, 1)
	305 5 (4, 1)
	307 aload (4, 1)
	308 #21 (4, 1)
	309 areturn (4, 1)
	310 dload (4, 2)
	311 #7 (4, 2)
	312 dload (4, 2)
	313 #11 (4, 2)
	314 dcmpl (4, 2)
	315 ifle (4, 2)
	316 8 (4, 2)
	318 aload (4, 2)
	319 #22 (4, 2)
	320 goto (4, 2)
	321 5 (4, 2)
	323 aload (4, 2)
	324 #21 (4, 2)
	325 areturn (4, 2)
	326 iload_3 (2, 4)
	327 newarray (2, 4)
	328 7 (2, 4)
	329 astore (2, 4)
	330 #23 (2, 4)
	331 iload_3 (2, 4)
	332 newarray (2, 4)
	333 7 (2, 4)
	334 astore (2, 4)
	335 #24 (2, 4)
	336 iconst_0 (3, 4)
	337 istore (3, 4)
	338 #25 (3, 4)
	339 iload (3, 4)
	340 #25 (3, 4)
	341 iload_3 (3, 4)
	342 if_icmpge (3, 4)
	343 45 (3, 4)
	345 aload (3, 4)
	346 #23 (3, 4)
	347 iload (3, 4)
	348 #25 (3, 4)
	349 aload (3, 4)
	350 #6 (3, 4)
	351 iload (3, 4)
	352 #25 (3, 4)
	353 daload (3, 4)
	354 aload (3, 4)
	355 #9 (3, 4)
	356 iload (3, 4)
	357 #25 (3, 4)
	358 daload (3, 4)
	359 dsub (3, 4)
	360 dastore (3, 4)
	361 aload (3, 4)
	362 #24 (3, 4)
	363 iload (3, 4)
	364 #25 (3, 4)
	365 ldc2_w (3, 4)
	366 2.0 (3, 4)
	368 aload (3, 4)
	369 #6 (3, 4)
	370 iload (3, 4)
	371 #25 (3, 4)
	372 daload (3, 4)
	373 dmul (3, 4)
	374 aload (3, 4)
	375 #9 (3, 4)
	376 iload (3, 4)
	377 #25 (3, 4)
	378 daload (3, 4)
	379 dsub (3, 4)
	380 dastore (3, 4)
	381 iinc (3, 4)
	382 #25 (3, 4)
	383 -89 (3, 4)
	384 goto (3, 4)
	385 -45 (3, 4)
	387 aload (2, 4)
	388 #6 (2, 4)
	389 invokevirtual (2, 4)
	390 [D.clone:()Ljava/lang/Object; (2, 4)
	392 checkcast (2, 4)
	393 [D (2, 4)
	395 astore (2, 4)
	396 #9 (2, 4)
	397 aload_0 (2, 4)
	398 aload (2, 4)
	399 #24 (2, 4)
	400 invokevirtual (2, 4)
	401 org/apache/commons/math3/optimization/direct/PowellOptimizer.computeObjectiveValue:([D)D (2, 4)
	403 dstore (2, 4)
	404 #13 (2, 4)
	405 dload (3, 1)
	406 #11 (3, 1)
	407 dload (3, 1)
	408 #13 (3, 1)
	409 dcmpl (3, 1)
	410 ifle (3, 1)
	411 137 (3, 1)
	413 ldc2_w (3, 1)
	414 2.0 (3, 1)
	416 dload (3, 1)
	417 #11 (3, 1)
	418 dload (3, 1)
	419 #13 (3, 1)
	420 dadd (3, 1)
	421 ldc2_w (3, 1)
	422 2.0 (3, 1)
	424 dload (3, 1)
	425 #7 (3, 1)
	426 dmul (3, 1)
	427 dsub (3, 1)
	428 dmul (3, 1)
	429 dstore (3, 1)
	430 #25 (3, 1)
	431 dload (3, 1)
	432 #11 (3, 1)
	433 dload (3, 1)
	434 #7 (3, 1)
	435 dsub (3, 1)
	436 dload (3, 1)
	437 #15 (3, 1)
	438 dsub (3, 1)
	439 dstore (3, 1)
	440 #27 (3, 1)
	441 dload (3, 1)
	442 #25 (3, 1)
	443 dload (3, 1)
	444 #27 (3, 1)
	445 dload (3, 1)
	446 #27 (3, 1)
	447 dmul (3, 1)
	448 dmul (3, 1)
	449 dstore (3, 1)
	450 #25 (3, 1)
	451 dload (3, 1)
	452 #11 (3, 1)
	453 dload (3, 1)
	454 #13 (3, 1)
	455 dsub (3, 1)
	456 dstore (3, 1)
	457 #27 (3, 1)
	458 dload (3, 1)
	459 #25 (3, 1)
	460 dload (3, 1)
	461 #15 (3, 1)
	462 dload (3, 1)
	463 #27 (3, 1)
	464 dmul (3, 1)
	465 dload (3, 1)
	466 #27 (3, 1)
	467 dmul (3, 1)
	468 dsub (3, 1)
	469 dstore (3, 1)
	470 #25 (3, 1)
	471 dload (4, 1)
	472 #25 (4, 1)
	473 dconst_0 (4, 1)
	474 dcmpg (4, 1)
	475 ifge (4, 1)
	476 72 (4, 1)
	478 aload_0 (4, 1)
	479 getfield (4, 1)
	480 org/apache/commons/math3/optimization/direct/PowellOptimizer.line:Lorg/apache/commons/math3/optimization/direct/PowellOptimizer$LineSearch; (4, 1)
	482 aload (4, 1)
	483 #6 (4, 1)
	484 aload (4, 1)
	485 #23 (4, 1)
	486 invokevirtual (4, 1)
	487 org/apache/commons/math3/optimization/direct/PowellOptimizer$LineSearch.search:([D[D)Lorg/apache/commons/math3/optimization/univariate/UnivariatePointValuePair; (4, 1)
	489 astore (4, 1)
	490 #29 (4, 1)
	491 aload (4, 1)
	492 #29 (4, 1)
	493 invokevirtual (4, 1)
	494 org/apache/commons/math3/optimization/univariate/UnivariatePointValuePair.getValue:()D (4, 1)
	496 dstore (4, 1)
	497 #7 (4, 1)
	498 aload (4, 1)
	499 #29 (4, 1)
	500 invokevirtual (4, 1)
	501 org/apache/commons/math3/optimization/univariate/UnivariatePointValuePair.getPoint:()D (4, 1)
	503 dstore (4, 1)
	504 #18 (4, 1)
	505 aload_0 (4, 1)
	506 aload (4, 1)
	507 #6 (4, 1)
	508 aload (4, 1)
	509 #23 (4, 1)
	510 dload (4, 1)
	511 #18 (4, 1)
	512 invokespecial (4, 1)
	513 org/apache/commons/math3/optimization/direct/PowellOptimizer.newPointAndDirection:([D[DD)[[D (4, 1)
	515 astore (4, 1)
	516 #30 (4, 1)
	517 aload (4, 1)
	518 #30 (4, 1)
	519 iconst_0 (4, 1)
	520 aaload (4, 1)
	521 astore (4, 1)
	522 #6 (4, 1)
	523 iload_3 (4, 1)
	524 iconst_1 (4, 1)
	525 isub (4, 1)
	526 istore (4, 1)
	527 #31 (4, 1)
	528 aload (4, 1)
	529 #4 (4, 1)
	530 iload (4, 1)
	531 #17 (4, 1)
	532 aload (4, 1)
	533 #4 (4, 1)
	534 iload (4, 1)
	535 #31 (4, 1)
	536 aaload (4, 1)
	537 aastore (4, 1)
	538 aload (4, 1)
	539 #4 (4, 1)
	540 iload (4, 1)
	541 #31 (4, 1)
	542 aload (4, 1)
	543 #30 (4, 1)
	544 iconst_1 (4, 1)
	545 aaload (4, 1)
	546 aastore (4, 1)
	547 goto (1, 3)
	548 -472 (1, 3)

Method: newPointAndDirection
	0 aload_1 (0, 0)
	1 arraylength (0, 0)
	2 istore (0, 0)
	3 #5 (0, 0)
	4 iload (0, 0)
	5 #5 (0, 0)
	6 newarray (0, 0)
	7 7 (0, 0)
	8 astore (0, 0)
	9 #6 (0, 0)
	10 iload (0, 0)
	11 #5 (0, 0)
	12 newarray (0, 0)
	13 7 (0, 0)
	14 astore (0, 0)
	15 #7 (0, 0)
	16 iconst_0 (1, 4)
	17 istore (1, 4)
	18 #8 (1, 4)
	19 iload (1, 4)
	20 #8 (1, 4)
	21 iload (1, 4)
	22 #5 (1, 4)
	23 if_icmpge (1, 4)
	24 35 (1, 4)
	26 aload (1, 4)
	27 #7 (1, 4)
	28 iload (1, 4)
	29 #8 (1, 4)
	30 aload_2 (1, 4)
	31 iload (1, 4)
	32 #8 (1, 4)
	33 daload (1, 4)
	34 dload_3 (1, 4)
	35 dmul (1, 4)
	36 dastore (1, 4)
	37 aload (1, 4)
	38 #6 (1, 4)
	39 iload (1, 4)
	40 #8 (1, 4)
	41 aload_1 (1, 4)
	42 iload (1, 4)
	43 #8 (1, 4)
	44 daload (1, 4)
	45 aload (1, 4)
	46 #7 (1, 4)
	47 iload (1, 4)
	48 #8 (1, 4)
	49 daload (1, 4)
	50 dadd (1, 4)
	51 dastore (1, 4)
	52 iinc (1, 4)
	53 #8 (1, 4)
	54 -89 (1, 4)
	55 goto (1, 4)
	56 -36 (1, 4)
	58 iconst_2 (0, 0)
	59 anewarray (0, 0)
	60 [D (0, 0)
	62 astore (0, 0)
	63 #8 (0, 0)
	64 aload (0, 0)
	65 #8 (0, 0)
	66 iconst_0 (0, 0)
	67 aload (0, 0)
	68 #6 (0, 0)
	69 aastore (0, 0)
	70 aload (0, 0)
	71 #8 (0, 0)
	72 iconst_1 (0, 0)
	73 aload (0, 0)
	74 #7 (0, 0)
	75 aastore (0, 0)
	76 aload (0, 0)
	77 #8 (0, 0)
	78 areturn (0, 0)

Method: <clinit>
	0 ldc2_w (0, 0)
	1 2.0 (0, 0)
	3 dconst_1 (0, 0)
	4 invokestatic (0, 0)
	5 org/apache/commons/math3/util/FastMath.ulp:(D)D (0, 0)
	7 dmul (0, 0)
	8 putstatic (0, 0)
	9 org/apache/commons/math3/optimization/direct/PowellOptimizer.MIN_RELATIVE_TOLERANCE:D (0, 0)
	11 return (0, 0)

