Method: value
	0 aload_0 (0, 0)
	1 getfield (0, 0)
	2 org/apache/commons/math3/optimization/direct/PowellOptimizer$LineSearch$1.val$n:I (0, 0)
	4 newarray (0, 0)
	5 7 (0, 0)
	6 astore_3 (0, 0)
	7 iconst_0 (1, 4)
	8 istore (1, 4)
	9 #4 (1, 4)
	10 iload (1, 4)
	11 #4 (1, 4)
	12 aload_0 (1, 4)
	13 getfield (1, 4)
	14 org/apache/commons/math3/optimization/direct/PowellOptimizer$LineSearch$1.val$n:I (1, 4)
	16 if_icmpge (1, 4)
	17 30 (1, 4)
	19 aload_3 (1, 4)
	20 iload (1, 4)
	21 #4 (1, 4)
	22 aload_0 (1, 4)
	23 getfield (1, 4)
	24 org/apache/commons/math3/optimization/direct/PowellOptimizer$LineSearch$1.val$p:[D (1, 4)
	26 iload (1, 4)
	27 #4 (1, 4)
	28 daload (1, 4)
	29 dload_1 (1, 4)
	30 aload_0 (1, 4)
	31 getfield (1, 4)
	32 org/apache/commons/math3/optimization/direct/PowellOptimizer$LineSearch$1.val$d:[D (1, 4)
	34 iload (1, 4)
	35 #4 (1, 4)
	36 daload (1, 4)
	37 dmul (1, 4)
	38 dadd (1, 4)
	39 dastore (1, 4)
	40 iinc (1, 4)
	41 #4 (1, 4)
	42 -89 (1, 4)
	43 goto (1, 4)
	44 -33 (1, 4)
	46 aload_0 (0, 0)
	47 getfield (0, 0)
	48 org/apache/commons/math3/optimization/direct/PowellOptimizer$LineSearch$1.this$1:Lorg/apache/commons/math3/optimization/direct/PowellOptimizer$LineSearch; (0, 0)
	50 getfield (0, 0)
	51 org/apache/commons/math3/optimization/direct/PowellOptimizer$LineSearch.this$0:Lorg/apache/commons/math3/optimization/direct/PowellOptimizer; (0, 0)
	53 aload_3 (0, 0)
	54 invokevirtual (0, 0)
	55 org/apache/commons/math3/optimization/direct/PowellOptimizer.computeObjectiveValue:([D)D (0, 0)
	57 dstore (0, 0)
	58 #4 (0, 0)
	59 dload (0, 0)
	60 #4 (0, 0)
	61 dreturn (0, 0)

