Method: <init>
	0 aload_0 (0, 0)
	1 new (0, 0)
	2 org/apache/commons/math3/optimization/SimpleValueChecker (0, 0)
	4 dup (0, 0)
	5 dload_1 (0, 0)
	6 dload_3 (0, 0)
	7 invokespecial (0, 0)
	8 org/apache/commons/math3/optimization/SimpleValueChecker.<init>:(DD)V (0, 0)
	10 invokespecial (0, 0)
	11 org/apache/commons/math3/optimization/direct/SimplexOptimizer.<init>:(Lorg/apache/commons/math3/optimization/ConvergenceChecker;)V (0, 0)
	13 return (0, 0)

Method: setSimplex
	0 aload_0 (0, 0)
	1 iconst_1 (0, 0)
	2 anewarray (0, 0)
	3 org/apache/commons/math3/optimization/OptimizationData (0, 0)
	5 dup (0, 0)
	6 iconst_0 (0, 0)
	7 aload_1 (0, 0)
	8 aastore (0, 0)
	9 invokespecial (0, 0)
	10 org/apache/commons/math3/optimization/direct/SimplexOptimizer.parseOptimizationData:([Lorg/apache/commons/math3/optimization/OptimizationData;)V (0, 0)
	12 return (0, 0)

Method: optimizeInternal
	0 aload_0 (0, 0)
	1 aload (0, 0)
	2 #4 (0, 0)
	3 invokespecial (0, 0)
	4 org/apache/commons/math3/optimization/direct/SimplexOptimizer.parseOptimizationData:([Lorg/apache/commons/math3/optimization/OptimizationData;)V (0, 0)
	6 aload_0 (0, 0)
	7 iload_1 (0, 0)
	8 aload_2 (0, 0)
	9 aload_3 (0, 0)
	10 aload (0, 0)
	11 #4 (0, 0)
	12 invokespecial (0, 0)
	13 org/apache/commons/math3/optimization/direct/BaseAbstractMultivariateOptimizer.optimizeInternal:(ILorg/apache/commons/math3/analysis/MultivariateFunction;Lorg/apache/commons/math3/optimization/GoalType;[Lorg/apache/commons/math3/optimization/OptimizationData;)Lorg/apache/commons/math3/optimization/PointValuePair; (0, 0)
	15 areturn (0, 0)

Method: parseOptimizationData
	0 aload_1 (1, 4)
	1 astore_2 (1, 4)
	2 aload_2 (1, 4)
	3 arraylength (1, 4)
	4 istore_3 (1, 4)
	5 iconst_0 (1, 4)
	6 istore (1, 4)
	7 #4 (1, 4)
	8 iload (1, 4)
	9 #4 (1, 4)
	10 iload_3 (1, 4)
	11 if_icmpge (1, 4)
	12 35 (1, 4)
	14 aload_2 (1, 4)
	15 iload (1, 4)
	16 #4 (1, 4)
	17 aaload (1, 4)
	18 astore (1, 4)
	19 #5 (1, 4)
	20 aload (2, 1)
	21 #5 (2, 1)
	22 instanceof (2, 1)
	23 org/apache/commons/math3/optimization/direct/AbstractSimplex (2, 1)
	25 ifeq (2, 1)
	26 15 (2, 1)
	28 aload_0 (2, 1)
	29 aload (2, 1)
	30 #5 (2, 1)
	31 checkcast (2, 1)
	32 org/apache/commons/math3/optimization/direct/AbstractSimplex (2, 1)
	34 putfield (2, 1)
	35 org/apache/commons/math3/optimization/direct/SimplexOptimizer.simplex:Lorg/apache/commons/math3/optimization/direct/AbstractSimplex; (2, 1)
	37 goto (2, 1)
	38 3 (2, 1)
	40 iinc (2, 1)
	41 #4 (2, 1)
	42 -89 (2, 1)
	43 goto (2, 1)
	44 -35 (2, 1)
	46 return (0, 0)

Method: doOptimize
	0 aload_0 (1, 1)
	1 getfield (1, 1)
	2 org/apache/commons/math3/optimization/direct/SimplexOptimizer.simplex:Lorg/apache/commons/math3/optimization/direct/AbstractSimplex; (1, 1)
	4 ifnonnull (1, 1)
	5 11 (1, 1)
	7 new (1, 1)
	8 org/apache/commons/math3/exception/NullArgumentException (1, 1)
	10 dup (1, 1)
	11 invokespecial (1, 1)
	12 org/apache/commons/math3/exception/NullArgumentException.<init>:()V (1, 1)
	14 athrow (1, 1)
	15 new (0, 0)
	16 org/apache/commons/math3/optimization/direct/SimplexOptimizer$1 (0, 0)
	18 dup (0, 0)
	19 aload_0 (0, 0)
	20 invokespecial (0, 0)
	21 org/apache/commons/math3/optimization/direct/SimplexOptimizer$1.<init>:(Lorg/apache/commons/math3/optimization/direct/SimplexOptimizer;)V (0, 0)
	23 astore_1 (0, 0)
	24 aload_0 (0, 0)
	25 invokevirtual (0, 0)
	26 org/apache/commons/math3/optimization/direct/SimplexOptimizer.getGoalType:()Lorg/apache/commons/math3/optimization/GoalType; (0, 0)
	28 getstatic (0, 0)
	29 org/apache/commons/math3/optimization/GoalType.MINIMIZE:Lorg/apache/commons/math3/optimization/GoalType; (0, 0)
	31 if_acmpne (0, 0)
	32 7 (0, 0)
	34 iconst_1 (0, 0)
	35 goto (0, 0)
	36 4 (0, 0)
	38 iconst_0 (0, 0)
	39 istore_2 (0, 0)
	40 new (0, 0)
	41 org/apache/commons/math3/optimization/direct/SimplexOptimizer$2 (0, 0)
	43 dup (0, 0)
	44 aload_0 (0, 0)
	45 iload_2 (0, 0)
	46 invokespecial (0, 0)
	47 org/apache/commons/math3/optimization/direct/SimplexOptimizer$2.<init>:(Lorg/apache/commons/math3/optimization/direct/SimplexOptimizer;Z)V (0, 0)
	49 astore_3 (0, 0)
	50 aload_0 (0, 0)
	51 getfield (0, 0)
	52 org/apache/commons/math3/optimization/direct/SimplexOptimizer.simplex:Lorg/apache/commons/math3/optimization/direct/AbstractSimplex; (0, 0)
	54 aload_0 (0, 0)
	55 invokevirtual (0, 0)
	56 org/apache/commons/math3/optimization/direct/SimplexOptimizer.getStartPoint:()[D (0, 0)
	58 invokevirtual (0, 0)
	59 org/apache/commons/math3/optimization/direct/AbstractSimplex.build:([D)V (0, 0)
	61 aload_0 (0, 0)
	62 getfield (0, 0)
	63 org/apache/commons/math3/optimization/direct/SimplexOptimizer.simplex:Lorg/apache/commons/math3/optimization/direct/AbstractSimplex; (0, 0)
	65 aload_1 (0, 0)
	66 aload_3 (0, 0)
	67 invokevirtual (0, 0)
	68 org/apache/commons/math3/optimization/direct/AbstractSimplex.evaluate:(Lorg/apache/commons/math3/analysis/MultivariateFunction;Ljava/util/Comparator;)V (0, 0)
	70 aconst_null (0, 0)
	71 astore (0, 0)
	72 #4 (0, 0)
	73 iconst_0 (0, 0)
	74 istore (0, 0)
	75 #5 (0, 0)
	76 aload_0 (0, 0)
	77 invokevirtual (0, 0)
	78 org/apache/commons/math3/optimization/direct/SimplexOptimizer.getConvergenceChecker:()Lorg/apache/commons/math3/optimization/ConvergenceChecker; (0, 0)
	80 astore (0, 0)
	81 #6 (0, 0)
	82 iload (2, 1)
	83 #5 (2, 1)
	84 ifle (2, 1)
	85 83 (2, 1)
	87 iconst_1 (2, 1)
	88 istore (2, 1)
	89 #7 (2, 1)
	90 iconst_0 (3, 4)
	91 istore (3, 4)
	92 #8 (3, 4)
	93 iload (3, 4)
	94 #8 (3, 4)
	95 aload_0 (3, 4)
	96 getfield (3, 4)
	97 org/apache/commons/math3/optimization/direct/SimplexOptimizer.simplex:Lorg/apache/commons/math3/optimization/direct/AbstractSimplex; (3, 4)
	99 invokevirtual (3, 4)
	100 org/apache/commons/math3/optimization/direct/AbstractSimplex.getSize:()I (3, 4)
	102 if_icmpge (3, 4)
	103 51 (3, 4)
	105 aload (3, 4)
	106 #4 (3, 4)
	107 iload (3, 4)
	108 #8 (3, 4)
	109 aaload (3, 4)
	110 astore (3, 4)
	111 #9 (3, 4)
	112 iload (3, 4)
	113 #7 (3, 4)
	114 ifeq (3, 4)
	115 30 (3, 4)
	117 aload (3, 4)
	118 #6 (3, 4)
	119 iload (3, 4)
	120 #5 (3, 4)
	121 aload (3, 4)
	122 #9 (3, 4)
	123 aload_0 (3, 4)
	124 getfield (3, 4)
	125 org/apache/commons/math3/optimization/direct/SimplexOptimizer.simplex:Lorg/apache/commons/math3/optimization/direct/AbstractSimplex; (3, 4)
	127 iload (3, 4)
	128 #8 (3, 4)
	129 invokevirtual (3, 4)
	130 org/apache/commons/math3/optimization/direct/AbstractSimplex.getPoint:(I)Lorg/apache/commons/math3/optimization/PointValuePair; (3, 4)
	132 invokeinterface (3, 4)
	133 org/apache/commons/math3/optimization/ConvergenceChecker.getPoints:()[Lorg/apache/commons/math3/optimization/PointValuePair; (3, 4)
	135 0 (3, 4)
	137 ifeq (3, 4)
	138 7 (3, 4)
	140 iconst_1 (3, 4)
	141 goto (3, 4)
	142 4 (3, 4)
	144 iconst_0 (3, 4)
	145 istore (3, 4)
	146 #7 (3, 4)
	147 iinc (3, 4)
	148 #8 (3, 4)
	149 -89 (3, 4)
	150 goto (3, 4)
	151 -57 (3, 4)
	153 iload (3, 1)
	154 #7 (3, 1)
	155 ifeq (3, 1)
	156 12 (3, 1)
	158 aload_0 (3, 1)
	159 getfield (3, 1)
	160 org/apache/commons/math3/optimization/direct/SimplexOptimizer.simplex:Lorg/apache/commons/math3/optimization/direct/AbstractSimplex; (3, 1)
	162 iconst_0 (3, 1)
	163 invokevirtual (3, 1)
	164 org/apache/commons/math3/optimization/direct/AbstractSimplex.getPoint:(I)Lorg/apache/commons/math3/optimization/PointValuePair; (3, 1)
	166 areturn (3, 1)
	167 aload_0 (1, 3)
	168 getfield (1, 3)
	169 org/apache/commons/math3/optimization/direct/SimplexOptimizer.simplex:Lorg/apache/commons/math3/optimization/direct/AbstractSimplex; (1, 3)
	171 invokevirtual (1, 3)
	172 org/apache/commons/math3/optimization/direct/AbstractSimplex.getPoints:()[Lorg/apache/commons/math3/optimization/PointValuePair; (1, 3)
	174 astore (1, 3)
	175 #4 (1, 3)
	176 aload_0 (1, 3)
	177 getfield (1, 3)
	178 org/apache/commons/math3/optimization/direct/SimplexOptimizer.simplex:Lorg/apache/commons/math3/optimization/direct/AbstractSimplex; (1, 3)
	180 aload_1 (1, 3)
	181 aload_3 (1, 3)
	182 invokevirtual (1, 3)
	183 org/apache/commons/math3/optimization/direct/AbstractSimplex.iterate:(Lorg/apache/commons/math3/analysis/MultivariateFunction;Ljava/util/Comparator;)V (1, 3)
	185 iinc (1, 3)
	186 #5 (1, 3)
	187 -89 (1, 3)
	188 goto (1, 3)
	189 -106 (1, 3)

