Method: <init>
	0 aload_0 (0, 0)
	1 invokespecial (0, 0)
	2 java/lang/Object.<init>:()V (0, 0)
	4 aload_0 (0, 0)
	5 iload_1 (0, 0)
	6 putfield (0, 0)
	7 org/apache/commons/math3/geometry/euclidean/twod/hull/AbstractConvexHullGenerator2D.includeCollinearPoints:Z (0, 0)
	9 aload_0 (0, 0)
	10 dload_2 (0, 0)
	11 putfield (0, 0)
	12 org/apache/commons/math3/geometry/euclidean/twod/hull/AbstractConvexHullGenerator2D.tolerance:D (0, 0)
	14 return (0, 0)

Method: getTolerance
	0 aload_0 (0, 0)
	1 getfield (0, 0)
	2 org/apache/commons/math3/geometry/euclidean/twod/hull/AbstractConvexHullGenerator2D.tolerance:D (0, 0)
	4 dreturn (0, 0)

Method: isIncludeCollinearPoints
	0 aload_0 (0, 0)
	1 getfield (0, 0)
	2 org/apache/commons/math3/geometry/euclidean/twod/hull/AbstractConvexHullGenerator2D.includeCollinearPoints:Z (0, 0)
	4 ireturn (0, 0)

Method: generate
	0 aload_0 (0, 0)
	1 aload_1 (0, 0)
	2 invokevirtual (0, 0)
	3 org/apache/commons/math3/geometry/euclidean/twod/hull/AbstractConvexHullGenerator2D.generate:(Ljava/util/Collection;)Lorg/apache/commons/math3/geometry/euclidean/twod/hull/ConvexHull2D; (0, 0)
	5 areturn (0, 0)

