Method: <init>
	0 aload_0 (0, 0)
	1 invokespecial (0, 0)
	2 java/lang/Object.<init>:()V (0, 0)
	4 aload_0 (0, 0)
	5 dload_2 (0, 0)
	6 putfield (0, 0)
	7 org/apache/commons/math3/geometry/euclidean/twod/hull/ConvexHull2D.tolerance:D (0, 0)
	9 aload_0 (1, 1)
	10 aload_1 (1, 1)
	11 invokespecial (1, 1)
	12 org/apache/commons/math3/geometry/euclidean/twod/hull/ConvexHull2D.isConvex:([Lorg/apache/commons/math3/geometry/euclidean/twod/Vector2D;)Z (1, 1)
	14 ifne (1, 1)
	15 18 (1, 1)
	17 new (1, 1)
	18 org/apache/commons/math3/exception/MathIllegalArgumentException (1, 1)
	20 dup (1, 1)
	21 getstatic (1, 1)
	22 org/apache/commons/math3/exception/util/LocalizedFormats.NOT_CONVEX:Lorg/apache/commons/math3/exception/util/LocalizedFormats; (1, 1)
	24 iconst_0 (1, 1)
	25 anewarray (1, 1)
	26 java/lang/Object (1, 1)
	28 invokespecial (1, 1)
	29 org/apache/commons/math3/exception/MathIllegalArgumentException.<init>:(Lorg/apache/commons/math3/exception/util/Localizable;[Ljava/lang/Object;)V (1, 1)
	31 athrow (1, 1)
	32 aload_0 (0, 0)
	33 aload_1 (0, 0)
	34 invokevirtual (0, 0)
	35 [Lorg/apache/commons/math3/geometry/euclidean/twod/Vector2D;.clone:()Ljava/lang/Object; (0, 0)
	37 checkcast (0, 0)
	38 [Lorg/apache/commons/math3/geometry/euclidean/twod/Vector2D; (0, 0)
	40 putfield (0, 0)
	41 org/apache/commons/math3/geometry/euclidean/twod/hull/ConvexHull2D.vertices:[Lorg/apache/commons/math3/geometry/euclidean/twod/Vector2D; (0, 0)
	43 return (0, 0)

Method: isConvex
	0 aload_1 (1, 1)
	1 arraylength (1, 1)
	2 iconst_3 (1, 1)
	3 if_icmpge (1, 1)
	4 5 (1, 1)
	6 iconst_1 (1, 1)
	7 ireturn (1, 1)
	8 iconst_0 (0, 0)
	9 istore_2 (0, 0)
	10 iconst_0 (1, 4)
	11 istore_3 (1, 4)
	12 iload_3 (1, 4)
	13 aload_1 (1, 4)
	14 arraylength (1, 4)
	15 if_icmpge (1, 4)
	16 133 (1, 4)
	18 aload_1 (1, 4)
	19 iload_3 (1, 4)
	20 ifne (1, 4)
	21 10 (1, 4)
	23 aload_1 (1, 4)
	24 arraylength (1, 4)
	25 iconst_1 (1, 4)
	26 isub (1, 4)
	27 goto (1, 4)
	28 6 (1, 4)
	30 iload_3 (1, 4)
	31 iconst_1 (1, 4)
	32 isub (1, 4)
	33 aaload (1, 4)
	34 astore (1, 4)
	35 #4 (1, 4)
	36 aload_1 (1, 4)
	37 iload_3 (1, 4)
	38 aaload (1, 4)
	39 astore (1, 4)
	40 #5 (1, 4)
	41 aload_1 (1, 4)
	42 iload_3 (1, 4)
	43 aload_1 (1, 4)
	44 arraylength (1, 4)
	45 iconst_1 (1, 4)
	46 isub (1, 4)
	47 if_icmpne (1, 4)
	48 7 (1, 4)
	50 iconst_0 (1, 4)
	51 goto (1, 4)
	52 6 (1, 4)
	54 iload_3 (1, 4)
	55 iconst_1 (1, 4)
	56 iadd (1, 4)
	57 aaload (1, 4)
	58 astore (1, 4)
	59 #6 (1, 4)
	60 aload (1, 4)
	61 #5 (1, 4)
	62 aload (1, 4)
	63 #4 (1, 4)
	64 invokevirtual (1, 4)
	65 org/apache/commons/math3/geometry/euclidean/twod/Vector2D.subtract:(Lorg/apache/commons/math3/geometry/Vector;)Lorg/apache/commons/math3/geometry/euclidean/twod/Vector2D; (1, 4)
	67 astore (1, 4)
	68 #7 (1, 4)
	69 aload (1, 4)
	70 #6 (1, 4)
	71 aload (1, 4)
	72 #5 (1, 4)
	73 invokevirtual (1, 4)
	74 org/apache/commons/math3/geometry/euclidean/twod/Vector2D.subtract:(Lorg/apache/commons/math3/geometry/Vector;)Lorg/apache/commons/math3/geometry/euclidean/twod/Vector2D; (1, 4)
	76 astore (1, 4)
	77 #8 (1, 4)
	78 aload (1, 4)
	79 #7 (1, 4)
	80 invokevirtual (1, 4)
	81 org/apache/commons/math3/geometry/euclidean/twod/Vector2D.getX:()D (1, 4)
	83 aload (1, 4)
	84 #8 (1, 4)
	85 invokevirtual (1, 4)
	86 org/apache/commons/math3/geometry/euclidean/twod/Vector2D.getY:()D (1, 4)
	88 aload (1, 4)
	89 #7 (1, 4)
	90 invokevirtual (1, 4)
	91 org/apache/commons/math3/geometry/euclidean/twod/Vector2D.getY:()D (1, 4)
	93 dneg (1, 4)
	94 aload (1, 4)
	95 #8 (1, 4)
	96 invokevirtual (1, 4)
	97 org/apache/commons/math3/geometry/euclidean/twod/Vector2D.getX:()D (1, 4)
	99 invokestatic (1, 4)
	100 org/apache/commons/math3/util/MathArrays.linearCombination:(DDDD)D (1, 4)
	102 dstore (1, 4)
	103 #9 (1, 4)
	104 dload (1, 4)
	105 #9 (1, 4)
	106 dconst_0 (1, 4)
	107 aload_0 (1, 4)
	108 getfield (1, 4)
	109 org/apache/commons/math3/geometry/euclidean/twod/hull/ConvexHull2D.tolerance:D (1, 4)
	111 invokestatic (1, 4)
	112 org/apache/commons/math3/util/Precision.compareTo:(DDD)I (1, 4)
	114 istore (1, 4)
	115 #11 (1, 4)
	116 iload (2, 1)
	117 #11 (2, 1)
	118 i2d (2, 1)
	119 dconst_0 (2, 1)
	120 dcmpl (2, 1)
	121 ifeq (2, 1)
	122 21 (2, 1)
	124 iload_2 (3, 1)
	125 i2d (3, 1)
	126 dconst_0 (3, 1)
	127 dcmpl (3, 1)
	128 ifeq (3, 1)
	129 11 (3, 1)
	131 iload (3, 1)
	132 #11 (3, 1)
	133 iload_2 (3, 1)
	134 if_icmpeq (3, 1)
	135 5 (3, 1)
	137 iconst_0 (3, 1)
	138 ireturn (3, 1)
	139 iload (2, 1)
	140 #11 (2, 1)
	141 istore_2 (2, 1)
	142 iinc (2, 1)
	143 #3 (2, 1)
	144 -89 (2, 1)
	145 goto (2, 1)
	146 -133 (2, 1)
	148 iconst_1 (1, 4)
	149 ireturn (1, 4)

Method: getVertices
	0 aload_0 (0, 0)
	1 invokevirtual (0, 0)
	2 org/apache/commons/math3/geometry/euclidean/twod/hull/ConvexHull2D.getVertices:()[Lorg/apache/commons/math3/geometry/euclidean/twod/Vector2D; (0, 0)
	4 areturn (0, 0)

Method: getLineSegments
	0 aload_0 (0, 0)
	1 invokespecial (0, 0)
	2 org/apache/commons/math3/geometry/euclidean/twod/hull/ConvexHull2D.retrieveLineSegments:()[Lorg/apache/commons/math3/geometry/euclidean/twod/Segment; (0, 0)
	4 invokevirtual (0, 0)
	5 [Lorg/apache/commons/math3/geometry/euclidean/twod/Segment;.clone:()Ljava/lang/Object; (0, 0)
	7 checkcast (0, 0)
	8 [Lorg/apache/commons/math3/geometry/euclidean/twod/Segment; (0, 0)
	10 areturn (0, 0)

Method: retrieveLineSegments
	0 aload_0 (1, 1)
	1 getfield (1, 1)
	2 org/apache/commons/math3/geometry/euclidean/twod/hull/ConvexHull2D.lineSegments:[Lorg/apache/commons/math3/geometry/euclidean/twod/Segment; (1, 1)
	4 ifnonnull (1, 1)
	5 211 (1, 1)
	7 aload_0 (1, 1)
	8 getfield (1, 1)
	9 org/apache/commons/math3/geometry/euclidean/twod/hull/ConvexHull2D.vertices:[Lorg/apache/commons/math3/geometry/euclidean/twod/Vector2D; (1, 1)
	11 arraylength (1, 1)
	12 istore_1 (1, 1)
	13 iload_1 (2, 1)
	14 iconst_1 (2, 1)
	15 if_icmpgt (2, 1)
	16 14 (2, 1)
	18 aload_0 (2, 1)
	19 iconst_0 (2, 1)
	20 anewarray (2, 1)
	21 org/apache/commons/math3/geometry/euclidean/twod/Segment (2, 1)
	23 putfield (2, 1)
	24 org/apache/commons/math3/geometry/euclidean/twod/hull/ConvexHull2D.lineSegments:[Lorg/apache/commons/math3/geometry/euclidean/twod/Segment; (2, 1)
	26 goto (2, 1)
	27 189 (2, 1)
	29 iload_1 (3, 1)
	30 iconst_2 (3, 1)
	31 if_icmpne (3, 1)
	32 56 (3, 1)
	34 aload_0 (3, 1)
	35 iconst_1 (3, 1)
	36 anewarray (3, 1)
	37 org/apache/commons/math3/geometry/euclidean/twod/Segment (3, 1)
	39 putfield (3, 1)
	40 org/apache/commons/math3/geometry/euclidean/twod/hull/ConvexHull2D.lineSegments:[Lorg/apache/commons/math3/geometry/euclidean/twod/Segment; (3, 1)
	42 aload_0 (3, 1)
	43 getfield (3, 1)
	44 org/apache/commons/math3/geometry/euclidean/twod/hull/ConvexHull2D.vertices:[Lorg/apache/commons/math3/geometry/euclidean/twod/Vector2D; (3, 1)
	46 iconst_0 (3, 1)
	47 aaload (3, 1)
	48 astore_2 (3, 1)
	49 aload_0 (3, 1)
	50 getfield (3, 1)
	51 org/apache/commons/math3/geometry/euclidean/twod/hull/ConvexHull2D.vertices:[Lorg/apache/commons/math3/geometry/euclidean/twod/Vector2D; (3, 1)
	53 iconst_1 (3, 1)
	54 aaload (3, 1)
	55 astore_3 (3, 1)
	56 aload_0 (3, 1)
	57 getfield (3, 1)
	58 org/apache/commons/math3/geometry/euclidean/twod/hull/ConvexHull2D.lineSegments:[Lorg/apache/commons/math3/geometry/euclidean/twod/Segment; (3, 1)
	60 iconst_0 (3, 1)
	61 new (3, 1)
	62 org/apache/commons/math3/geometry/euclidean/twod/Segment (3, 1)
	64 dup (3, 1)
	65 aload_2 (3, 1)
	66 aload_3 (3, 1)
	67 new (3, 1)
	68 org/apache/commons/math3/geometry/euclidean/twod/Line (3, 1)
	70 dup (3, 1)
	71 aload_2 (3, 1)
	72 aload_3 (3, 1)
	73 aload_0 (3, 1)
	74 getfield (3, 1)
	75 org/apache/commons/math3/geometry/euclidean/twod/hull/ConvexHull2D.tolerance:D (3, 1)
	77 invokespecial (3, 1)
	78 org/apache/commons/math3/geometry/euclidean/twod/Line.<init>:(Lorg/apache/commons/math3/geometry/euclidean/twod/Vector2D;Lorg/apache/commons/math3/geometry/euclidean/twod/Vector2D;D)V (3, 1)
	80 invokespecial (3, 1)
	81 org/apache/commons/math3/geometry/euclidean/twod/Segment.<init>:(Lorg/apache/commons/math3/geometry/euclidean/twod/Vector2D;Lorg/apache/commons/math3/geometry/euclidean/twod/Vector2D;Lorg/apache/commons/math3/geometry/euclidean/twod/Line;)V (3, 1)
	83 aastore (3, 1)
	84 goto (4, 2)
	85 131 (4, 2)
	87 aload_0 (4, 2)
	88 iload_1 (4, 2)
	89 anewarray (4, 2)
	90 org/apache/commons/math3/geometry/euclidean/twod/Segment (4, 2)
	92 putfield (4, 2)
	93 org/apache/commons/math3/geometry/euclidean/twod/hull/ConvexHull2D.lineSegments:[Lorg/apache/commons/math3/geometry/euclidean/twod/Segment; (4, 2)
	95 aconst_null (4, 2)
	96 astore_2 (4, 2)
	97 aconst_null (4, 2)
	98 astore_3 (4, 2)
	99 iconst_0 (4, 2)
	100 istore (4, 2)
	101 #4 (4, 2)
	102 aload_0 (5, 4)
	103 getfield (5, 4)
	104 org/apache/commons/math3/geometry/euclidean/twod/hull/ConvexHull2D.vertices:[Lorg/apache/commons/math3/geometry/euclidean/twod/Vector2D; (5, 4)
	106 astore (5, 4)
	107 #5 (5, 4)
	108 aload (5, 4)
	109 #5 (5, 4)
	110 arraylength (5, 4)
	111 istore (5, 4)
	112 #6 (5, 4)
	113 iconst_0 (5, 4)
	114 istore (5, 4)
	115 #7 (5, 4)
	116 iload (5, 4)
	117 #7 (5, 4)
	118 iload (5, 4)
	119 #6 (5, 4)
	120 if_icmpge (5, 4)
	121 66 (5, 4)
	123 aload (5, 4)
	124 #5 (5, 4)
	125 iload (5, 4)
	126 #7 (5, 4)
	127 aaload (5, 4)
	128 astore (5, 4)
	129 #8 (5, 4)
	130 aload_3 (6, 1)
	131 ifnonnull (6, 1)
	132 12 (6, 1)
	134 aload (6, 1)
	135 #8 (6, 1)
	136 astore_2 (6, 1)
	137 aload (6, 1)
	138 #8 (6, 1)
	139 astore_3 (6, 1)
	140 goto (6, 1)
	141 40 (6, 1)
	143 aload_0 (7, 2)
	144 getfield (7, 2)
	145 org/apache/commons/math3/geometry/euclidean/twod/hull/ConvexHull2D.lineSegments:[Lorg/apache/commons/math3/geometry/euclidean/twod/Segment; (7, 2)
	147 iload (7, 2)
	148 #4 (7, 2)
	149 iinc (7, 2)
	150 #4 (7, 2)
	151 -69 (7, 2)
	152 new (7, 2)
	153 org/apache/commons/math3/geometry/euclidean/twod/Segment (7, 2)
	155 dup (7, 2)
	156 aload_3 (7, 2)
	157 aload (7, 2)
	158 #8 (7, 2)
	159 new (7, 2)
	160 org/apache/commons/math3/geometry/euclidean/twod/Line (7, 2)
	162 dup (7, 2)
	163 aload_3 (7, 2)
	164 aload (7, 2)
	165 #8 (7, 2)
	166 aload_0 (7, 2)
	167 getfield (7, 2)
	168 org/apache/commons/math3/geometry/euclidean/twod/hull/ConvexHull2D.tolerance:D (7, 2)
	170 invokespecial (7, 2)
	171 org/apache/commons/math3/geometry/euclidean/twod/Line.<init>:(Lorg/apache/commons/math3/geometry/euclidean/twod/Vector2D;Lorg/apache/commons/math3/geometry/euclidean/twod/Vector2D;D)V (7, 2)
	173 invokespecial (7, 2)
	174 org/apache/commons/math3/geometry/euclidean/twod/Segment.<init>:(Lorg/apache/commons/math3/geometry/euclidean/twod/Vector2D;Lorg/apache/commons/math3/geometry/euclidean/twod/Vector2D;Lorg/apache/commons/math3/geometry/euclidean/twod/Line;)V (7, 2)
	176 aastore (7, 2)
	177 aload (7, 2)
	178 #8 (7, 2)
	179 astore_3 (7, 2)
	180 iinc (7, 2)
	181 #7 (7, 2)
	182 -89 (7, 2)
	183 goto (7, 2)
	184 -67 (7, 2)
	186 aload_0 (5, 4)
	187 getfield (5, 4)
	188 org/apache/commons/math3/geometry/euclidean/twod/hull/ConvexHull2D.lineSegments:[Lorg/apache/commons/math3/geometry/euclidean/twod/Segment; (5, 4)
	190 iload (5, 4)
	191 #4 (5, 4)
	192 new (5, 4)
	193 org/apache/commons/math3/geometry/euclidean/twod/Segment (5, 4)
	195 dup (5, 4)
	196 aload_3 (5, 4)
	197 aload_2 (5, 4)
	198 new (5, 4)
	199 org/apache/commons/math3/geometry/euclidean/twod/Line (5, 4)
	201 dup (5, 4)
	202 aload_3 (5, 4)
	203 aload_2 (5, 4)
	204 aload_0 (5, 4)
	205 getfield (5, 4)
	206 org/apache/commons/math3/geometry/euclidean/twod/hull/ConvexHull2D.tolerance:D (5, 4)
	208 invokespecial (5, 4)
	209 org/apache/commons/math3/geometry/euclidean/twod/Line.<init>:(Lorg/apache/commons/math3/geometry/euclidean/twod/Vector2D;Lorg/apache/commons/math3/geometry/euclidean/twod/Vector2D;D)V (5, 4)
	211 invokespecial (5, 4)
	212 org/apache/commons/math3/geometry/euclidean/twod/Segment.<init>:(Lorg/apache/commons/math3/geometry/euclidean/twod/Vector2D;Lorg/apache/commons/math3/geometry/euclidean/twod/Vector2D;Lorg/apache/commons/math3/geometry/euclidean/twod/Line;)V (5, 4)
	214 aastore (5, 4)
	215 aload_0 (1, 1)
	216 getfield (1, 1)
	217 org/apache/commons/math3/geometry/euclidean/twod/hull/ConvexHull2D.lineSegments:[Lorg/apache/commons/math3/geometry/euclidean/twod/Segment; (1, 1)
	219 areturn (1, 1)

Method: createRegion
	0 aload_0 (1, 1)
	1 getfield (1, 1)
	2 org/apache/commons/math3/geometry/euclidean/twod/hull/ConvexHull2D.vertices:[Lorg/apache/commons/math3/geometry/euclidean/twod/Vector2D; (1, 1)
	4 arraylength (1, 1)
	5 iconst_3 (1, 1)
	6 if_icmpge (1, 1)
	7 11 (1, 1)
	9 new (1, 1)
	10 org/apache/commons/math3/exception/InsufficientDataException (1, 1)
	12 dup (1, 1)
	13 invokespecial (1, 1)
	14 org/apache/commons/math3/exception/InsufficientDataException.<init>:()V (1, 1)
	16 athrow (1, 1)
	17 new (0, 0)
	18 org/apache/commons/math3/geometry/partitioning/RegionFactory (0, 0)
	20 dup (0, 0)
	21 invokespecial (0, 0)
	22 org/apache/commons/math3/geometry/partitioning/RegionFactory.<init>:()V (0, 0)
	24 astore_1 (0, 0)
	25 aload_0 (0, 0)
	26 invokespecial (0, 0)
	27 org/apache/commons/math3/geometry/euclidean/twod/hull/ConvexHull2D.retrieveLineSegments:()[Lorg/apache/commons/math3/geometry/euclidean/twod/Segment; (0, 0)
	29 astore_2 (0, 0)
	30 aload_2 (0, 0)
	31 arraylength (0, 0)
	32 anewarray (0, 0)
	33 org/apache/commons/math3/geometry/euclidean/twod/Line (0, 0)
	35 astore_3 (0, 0)
	36 iconst_0 (1, 4)
	37 istore (1, 4)
	38 #4 (1, 4)
	39 iload (1, 4)
	40 #4 (1, 4)
	41 aload_2 (1, 4)
	42 arraylength (1, 4)
	43 if_icmpge (1, 4)
	44 20 (1, 4)
	46 aload_3 (1, 4)
	47 iload (1, 4)
	48 #4 (1, 4)
	49 aload_2 (1, 4)
	50 iload (1, 4)
	51 #4 (1, 4)
	52 aaload (1, 4)
	53 invokevirtual (1, 4)
	54 org/apache/commons/math3/geometry/euclidean/twod/Segment.getLine:()Lorg/apache/commons/math3/geometry/euclidean/twod/Line; (1, 4)
	56 aastore (1, 4)
	57 iinc (1, 4)
	58 #4 (1, 4)
	59 -89 (1, 4)
	60 goto (1, 4)
	61 -21 (1, 4)
	63 aload_1 (0, 0)
	64 aload_3 (0, 0)
	65 invokevirtual (0, 0)
	66 org/apache/commons/math3/geometry/partitioning/RegionFactory.buildConvex:([Lorg/apache/commons/math3/geometry/partitioning/Hyperplane;)Lorg/apache/commons/math3/geometry/partitioning/Region; (0, 0)
	68 areturn (0, 0)

