Method: <init>
	0 aload_0 (0, 0)
	1 iload_1 (0, 0)
	2 dload_2 (0, 0)
	3 invokespecial (0, 0)
	4 org/apache/commons/math3/geometry/euclidean/twod/hull/AbstractConvexHullGenerator2D.<init>:(ZD)V (0, 0)
	6 return (0, 0)

Method: findHullVertices
	0 new (0, 0)
	1 java/util/ArrayList (0, 0)
	3 dup (0, 0)
	4 aload_1 (0, 0)
	5 invokespecial (0, 0)
	6 java/util/ArrayList.<init>:(Ljava/util/Collection;)V (0, 0)
	8 astore_2 (0, 0)
	9 aload_2 (0, 0)
	10 new (0, 0)
	11 org/apache/commons/math3/geometry/euclidean/twod/hull/MonotoneChain$1 (0, 0)
	13 dup (0, 0)
	14 aload_0 (0, 0)
	15 invokespecial (0, 0)
	16 org/apache/commons/math3/geometry/euclidean/twod/hull/MonotoneChain$1.<init>:(Lorg/apache/commons/math3/geometry/euclidean/twod/hull/MonotoneChain;)V (0, 0)
	18 invokestatic (0, 0)
	19 java/util/Collections.sort:(Ljava/util/List;Ljava/util/Comparator;)V (0, 0)
	21 new (0, 0)
	22 java/util/ArrayList (0, 0)
	24 dup (0, 0)
	25 invokespecial (0, 0)
	26 java/util/ArrayList.<init>:()V (0, 0)
	28 astore_3 (0, 0)
	29 aload_2 (1, 4)
	30 invokeinterface (1, 4)
	31 java/util/List.java/util/Iterator (1, 4)
	33 0 (1, 4)
	35 astore (1, 4)
	36 #4 (1, 4)
	37 aload (1, 4)
	38 #4 (1, 4)
	39 invokeinterface (1, 4)
	40 java/util/Iterator.next:()Ljava/lang/Object; (1, 4)
	42 0 (1, 4)
	44 ifeq (1, 4)
	45 25 (1, 4)
	47 aload (1, 4)
	48 #4 (1, 4)
	49 invokeinterface (1, 4)
	50 java/util/Iterator.org/apache/commons/math3/geometry/euclidean/twod/Vector2D (1, 4)
	52 0 (1, 4)
	54 checkcast (1, 4)
	55 org/apache/commons/math3/geometry/euclidean/twod/Vector2D (1, 4)
	57 astore (1, 4)
	58 #5 (1, 4)
	59 aload_0 (1, 4)
	60 aload (1, 4)
	61 #5 (1, 4)
	62 aload_3 (1, 4)
	63 invokespecial (1, 4)
	64 org/apache/commons/math3/geometry/euclidean/twod/hull/MonotoneChain.updateHull:(Lorg/apache/commons/math3/geometry/euclidean/twod/Vector2D;Ljava/util/List;)V (1, 4)
	66 goto (0, 0)
	67 -29 (0, 0)
	69 new (0, 0)
	70 java/util/ArrayList (0, 0)
	72 dup (0, 0)
	73 invokespecial (0, 0)
	74 java/util/ArrayList.<init>:()V (0, 0)
	76 astore (0, 0)
	77 #4 (0, 0)
	78 aload_2 (1, 4)
	79 invokeinterface (1, 4)
	80 java/util/List.get:(I)Ljava/lang/Object; (1, 4)
	82 0 (1, 4)
	84 iconst_1 (1, 4)
	85 isub (1, 4)
	86 istore (1, 4)
	87 #5 (1, 4)
	88 iload (1, 4)
	89 #5 (1, 4)
	90 iflt (1, 4)
	91 30 (1, 4)
	93 aload_2 (1, 4)
	94 iload (1, 4)
	95 #5 (1, 4)
	96 invokeinterface (1, 4)
	97 java/util/List.<init>:(I)V (1, 4)
	99 0 (1, 4)
	101 checkcast (1, 4)
	102 org/apache/commons/math3/geometry/euclidean/twod/Vector2D (1, 4)
	104 astore (1, 4)
	105 #6 (1, 4)
	106 aload_0 (1, 4)
	107 aload (1, 4)
	108 #6 (1, 4)
	109 aload (1, 4)
	110 #4 (1, 4)
	111 invokespecial (1, 4)
	112 org/apache/commons/math3/geometry/euclidean/twod/hull/MonotoneChain.updateHull:(Lorg/apache/commons/math3/geometry/euclidean/twod/Vector2D;Ljava/util/List;)V (1, 4)
	114 iinc (1, 4)
	115 #5 (1, 4)
	116 -89 (1, 4)
	117 goto (1, 4)
	118 -29 (1, 4)
	120 new (0, 0)
	121 java/util/ArrayList (0, 0)
	123 dup (0, 0)
	124 aload_3 (0, 0)
	125 invokeinterface (0, 0)
	126 java/util/List.get:(I)Ljava/lang/Object; (0, 0)
	128 0 (0, 0)
	130 aload (0, 0)
	131 #4 (0, 0)
	132 invokeinterface (0, 0)
	133 java/util/List.get:(I)Ljava/lang/Object; (0, 0)
	135 0 (0, 0)
	137 iadd (0, 0)
	138 iconst_2 (0, 0)
	139 isub (0, 0)
	140 invokespecial (0, 0)
	141 java/util/ArrayList.<init>:(I)V (0, 0)
	143 astore (0, 0)
	144 #5 (0, 0)
	145 iconst_0 (1, 4)
	146 istore (1, 4)
	147 #6 (1, 4)
	148 iload (1, 4)
	149 #6 (1, 4)
	150 aload_3 (1, 4)
	151 invokeinterface (1, 4)
	152 java/util/List.get:(I)Ljava/lang/Object; (1, 4)
	154 0 (1, 4)
	156 iconst_1 (1, 4)
	157 isub (1, 4)
	158 if_icmpge (1, 4)
	159 25 (1, 4)
	161 aload (1, 4)
	162 #5 (1, 4)
	163 aload_3 (1, 4)
	164 iload (1, 4)
	165 #6 (1, 4)
	166 invokeinterface (1, 4)
	167 java/util/List.<init>:(I)V (1, 4)
	169 0 (1, 4)
	171 invokeinterface (1, 4)
	172 java/util/List.isEmpty:()Z (1, 4)
	174 0 (1, 4)
	176 pop (1, 4)
	177 iinc (1, 4)
	178 #6 (1, 4)
	179 -89 (1, 4)
	180 goto (1, 4)
	181 -32 (1, 4)
	183 iconst_0 (1, 4)
	184 istore (1, 4)
	185 #6 (1, 4)
	186 iload (1, 4)
	187 #6 (1, 4)
	188 aload (1, 4)
	189 #4 (1, 4)
	190 invokeinterface (1, 4)
	191 java/util/List.get:(I)Ljava/lang/Object; (1, 4)
	193 0 (1, 4)
	195 iconst_1 (1, 4)
	196 isub (1, 4)
	197 if_icmpge (1, 4)
	198 26 (1, 4)
	200 aload (1, 4)
	201 #5 (1, 4)
	202 aload (1, 4)
	203 #4 (1, 4)
	204 iload (1, 4)
	205 #6 (1, 4)
	206 invokeinterface (1, 4)
	207 java/util/List.<init>:(I)V (1, 4)
	209 0 (1, 4)
	211 invokeinterface (1, 4)
	212 java/util/List.isEmpty:()Z (1, 4)
	214 0 (1, 4)
	216 pop (1, 4)
	217 iinc (1, 4)
	218 #6 (1, 4)
	219 -89 (1, 4)
	220 goto (1, 4)
	221 -34 (1, 4)
	223 aload (2, 1)
	224 #5 (2, 1)
	225 invokeinterface (2, 1)
	226 java/util/List.getTolerance:()D (2, 1)
	228 0 (2, 1)
	230 ifeq (2, 1)
	231 27 (2, 1)
	233 aload_3 (2, 1)
	234 invokeinterface (2, 1)
	235 java/util/List.getTolerance:()D (2, 1)
	237 0 (2, 1)
	239 ifne (2, 1)
	240 18 (2, 1)
	242 aload (2, 1)
	243 #5 (2, 1)
	244 aload_3 (2, 1)
	245 iconst_0 (2, 1)
	246 invokeinterface (2, 1)
	247 java/util/List.<init>:(I)V (2, 1)
	249 0 (2, 1)
	251 invokeinterface (2, 1)
	252 java/util/List.isEmpty:()Z (2, 1)
	254 0 (2, 1)
	256 pop (2, 1)
	257 aload (1, 1)
	258 #5 (1, 1)
	259 areturn (0, 1)

Method: updateHull
	0 aload_0 (0, 0)
	1 invokevirtual (0, 0)
	2 org/apache/commons/math3/geometry/euclidean/twod/hull/MonotoneChain.getTolerance:()D (0, 0)
	4 dstore_3 (0, 0)
	5 aload_2 (1, 1)
	6 invokeinterface (1, 1)
	7 java/util/List.get:(I)Ljava/lang/Object; (1, 1)
	9 0 (1, 1)
	11 iconst_1 (1, 1)
	12 if_icmpne (1, 1)
	13 27 (1, 1)
	15 aload_2 (1, 1)
	16 iconst_0 (1, 1)
	17 invokeinterface (1, 1)
	18 java/util/List.<init>:(I)V (1, 1)
	20 0 (1, 1)
	22 checkcast (1, 1)
	23 org/apache/commons/math3/geometry/euclidean/twod/Vector2D (1, 1)
	25 astore (1, 1)
	26 #5 (1, 1)
	27 aload (2, 1)
	28 #5 (2, 1)
	29 aload_1 (2, 1)
	30 invokevirtual (2, 1)
	31 org/apache/commons/math3/geometry/euclidean/twod/Vector2D.distance:(Lorg/apache/commons/math3/geometry/Vector;)D (2, 1)
	33 dload_3 (2, 1)
	34 dcmpg (2, 1)
	35 ifge (2, 1)
	36 4 (2, 1)
	38 return (2, 1)
	39 aload_2 (1, 3)
	40 invokeinterface (1, 3)
	41 java/util/List.get:(I)Ljava/lang/Object; (1, 3)
	43 0 (1, 3)
	45 iconst_2 (1, 3)
	46 if_icmplt (1, 3)
	47 192 (1, 3)
	49 aload_2 (1, 3)
	50 invokeinterface (1, 3)
	51 java/util/List.get:(I)Ljava/lang/Object; (1, 3)
	53 0 (1, 3)
	55 istore (1, 3)
	56 #5 (1, 3)
	57 aload_2 (1, 3)
	58 iload (1, 3)
	59 #5 (1, 3)
	60 iconst_2 (1, 3)
	61 isub (1, 3)
	62 invokeinterface (1, 3)
	63 java/util/List.<init>:(I)V (1, 3)
	65 0 (1, 3)
	67 checkcast (1, 3)
	68 org/apache/commons/math3/geometry/euclidean/twod/Vector2D (1, 3)
	70 astore (1, 3)
	71 #6 (1, 3)
	72 aload_2 (1, 3)
	73 iload (1, 3)
	74 #5 (1, 3)
	75 iconst_1 (1, 3)
	76 isub (1, 3)
	77 invokeinterface (1, 3)
	78 java/util/List.<init>:(I)V (1, 3)
	80 0 (1, 3)
	82 checkcast (1, 3)
	83 org/apache/commons/math3/geometry/euclidean/twod/Vector2D (1, 3)
	85 astore (1, 3)
	86 #7 (1, 3)
	87 new (1, 3)
	88 org/apache/commons/math3/geometry/euclidean/twod/Line (1, 3)
	90 dup (1, 3)
	91 aload (1, 3)
	92 #6 (1, 3)
	93 aload (1, 3)
	94 #7 (1, 3)
	95 dload_3 (1, 3)
	96 invokespecial (1, 3)
	97 org/apache/commons/math3/geometry/euclidean/twod/Line.<init>:(Lorg/apache/commons/math3/geometry/euclidean/twod/Vector2D;Lorg/apache/commons/math3/geometry/euclidean/twod/Vector2D;D)V (1, 3)
	99 aload_1 (1, 3)
	100 invokevirtual (1, 3)
	101 org/apache/commons/math3/geometry/euclidean/twod/Line.getOffset:(Lorg/apache/commons/math3/geometry/Vector;)D (1, 3)
	103 dstore (1, 3)
	104 #8 (1, 3)
	105 dload (2, 1)
	106 #8 (2, 1)
	107 invokestatic (2, 1)
	108 org/apache/commons/math3/util/FastMath.abs:(D)D (2, 1)
	110 dload_3 (2, 1)
	111 dcmpg (2, 1)
	112 ifge (2, 1)
	113 105 (2, 1)
	115 aload (2, 1)
	116 #6 (2, 1)
	117 aload_1 (2, 1)
	118 invokevirtual (2, 1)
	119 org/apache/commons/math3/geometry/euclidean/twod/Vector2D.distance:(Lorg/apache/commons/math3/geometry/Vector;)D (2, 1)
	121 dstore (2, 1)
	122 #10 (2, 1)
	123 dload (3, 1)
	124 #10 (3, 1)
	125 dload_3 (3, 1)
	126 dcmpg (3, 1)
	127 iflt (3, 1)
	128 14 (3, 1)
	130 aload (3, 1)
	131 #7 (3, 1)
	132 aload_1 (3, 1)
	133 invokevirtual (3, 1)
	134 org/apache/commons/math3/geometry/euclidean/twod/Vector2D.distance:(Lorg/apache/commons/math3/geometry/Vector;)D (3, 1)
	136 dload_3 (3, 1)
	137 dcmpg (3, 1)
	138 ifge (3, 1)
	139 4 (3, 1)
	141 return (3, 1)
	142 aload (2, 1)
	143 #6 (2, 1)
	144 aload (2, 1)
	145 #7 (2, 1)
	146 invokevirtual (2, 1)
	147 org/apache/commons/math3/geometry/euclidean/twod/Vector2D.distance:(Lorg/apache/commons/math3/geometry/Vector;)D (2, 1)
	149 dstore (2, 1)
	150 #12 (2, 1)
	151 aload_0 (3, 1)
	152 invokevirtual (3, 1)
	153 org/apache/commons/math3/geometry/euclidean/twod/hull/MonotoneChain.isIncludeCollinearPoints:()Z (3, 1)
	155 ifeq (3, 1)
	156 34 (3, 1)
	158 dload (3, 1)
	159 #10 (3, 1)
	160 dload (3, 1)
	161 #12 (3, 1)
	162 dcmpg (3, 1)
	163 ifge (3, 1)
	164 10 (3, 1)
	166 iload (3, 1)
	167 #5 (3, 1)
	168 iconst_1 (3, 1)
	169 isub (3, 1)
	170 goto (3, 1)
	171 5 (3, 1)
	173 iload (3, 1)
	174 #5 (3, 1)
	175 istore (3, 1)
	176 #14 (3, 1)
	177 aload_2 (3, 1)
	178 iload (3, 1)
	179 #14 (3, 1)
	180 aload_1 (3, 1)
	181 invokeinterface (3, 1)
	182 java/util/List.remove:(I)Ljava/lang/Object; (3, 1)
	184 0 (3, 1)
	186 goto (4, 2)
	187 30 (4, 2)
	189 dload (5, 1)
	190 #10 (5, 1)
	191 dload (5, 1)
	192 #12 (5, 1)
	193 dcmpl (5, 1)
	194 ifle (5, 1)
	195 22 (5, 1)
	197 aload_2 (5, 1)
	198 iload (5, 1)
	199 #5 (5, 1)
	200 iconst_1 (5, 1)
	201 isub (5, 1)
	202 invokeinterface (5, 1)
	203 java/util/List.generate:(Ljava/util/Collection;)Lorg/apache/commons/math3/geometry/euclidean/twod/hull/ConvexHull2D; (5, 1)
	205 0 (5, 1)
	207 pop (5, 1)
	208 aload_2 (5, 1)
	209 aload_1 (5, 1)
	210 invokeinterface (5, 1)
	211 java/util/List.isEmpty:()Z (5, 1)
	213 0 (5, 1)
	215 pop (5, 1)
	216 return (2, 1)
	217 dload (3, 1)
	218 #8 (3, 1)
	219 dconst_0 (3, 1)
	220 dcmpl (3, 1)
	221 ifle (3, 1)
	222 17 (3, 1)
	224 aload_2 (3, 1)
	225 iload (3, 1)
	226 #5 (3, 1)
	227 iconst_1 (3, 1)
	228 isub (3, 1)
	229 invokeinterface (3, 1)
	230 java/util/List.generate:(Ljava/util/Collection;)Lorg/apache/commons/math3/geometry/euclidean/twod/hull/ConvexHull2D; (3, 1)
	232 0 (3, 1)
	234 pop (3, 1)
	235 goto (0, 0)
	236 -196 (0, 0)
	238 aload_2 (0, 0)
	239 aload_1 (0, 0)
	240 invokeinterface (0, 0)
	241 java/util/List.isEmpty:()Z (0, 0)
	243 0 (0, 0)
	245 pop (0, 0)
	246 return (0, 0)

Method: generate
	0 aload_0 (0, 0)
	1 aload_1 (0, 0)
	2 invokespecial (0, 0)
	3 org/apache/commons/math3/geometry/euclidean/twod/hull/AbstractConvexHullGenerator2D.generate:(Ljava/util/Collection;)Lorg/apache/commons/math3/geometry/euclidean/twod/hull/ConvexHull2D; (0, 0)
	5 areturn (0, 0)

Method: isIncludeCollinearPoints
	0 aload_0 (0, 0)
	1 invokespecial (0, 0)
	2 org/apache/commons/math3/geometry/euclidean/twod/hull/AbstractConvexHullGenerator2D.isIncludeCollinearPoints:()Z (0, 0)
	4 ireturn (0, 0)

Method: getTolerance
	0 aload_0 (0, 0)
	1 invokespecial (0, 0)
	2 org/apache/commons/math3/geometry/euclidean/twod/hull/AbstractConvexHullGenerator2D.getTolerance:()D (0, 0)
	4 dreturn (0, 0)

