Method: <init>
	0 aload_0 (0, 0)
	1 aload_1 (0, 0)
	2 putfield (0, 0)
	3 org/apache/commons/math3/optimization/fitting/CurveFitter$OldTheoreticalValuesFunction.this$0:Lorg/apache/commons/math3/optimization/fitting/CurveFitter; (0, 0)
	5 aload_0 (0, 0)
	6 invokespecial (0, 0)
	7 java/lang/Object.<init>:()V (0, 0)
	9 aload_0 (0, 0)
	10 aload_2 (0, 0)
	11 putfield (0, 0)
	12 org/apache/commons/math3/optimization/fitting/CurveFitter$OldTheoreticalValuesFunction.f:Lorg/apache/commons/math3/analysis/ParametricUnivariateFunction; (0, 0)
	14 return (0, 0)

Method: jacobian
	0 new (0, 0)
	1 org/apache/commons/math3/optimization/fitting/CurveFitter$OldTheoreticalValuesFunction$1 (0, 0)
	3 dup (0, 0)
	4 aload_0 (0, 0)
	5 invokespecial (0, 0)
	6 org/apache/commons/math3/optimization/fitting/CurveFitter$OldTheoreticalValuesFunction$1.<init>:(Lorg/apache/commons/math3/optimization/fitting/CurveFitter$OldTheoreticalValuesFunction;)V (0, 0)
	8 areturn (0, 0)

Method: value
	0 aload_0 (0, 0)
	1 getfield (0, 0)
	2 org/apache/commons/math3/optimization/fitting/CurveFitter$OldTheoreticalValuesFunction.this$0:Lorg/apache/commons/math3/optimization/fitting/CurveFitter; (0, 0)
	4 invokestatic (0, 0)
	5 org/apache/commons/math3/optimization/fitting/CurveFitter.access$000:(Lorg/apache/commons/math3/optimization/fitting/CurveFitter;)Ljava/util/List; (0, 0)
	7 invokeinterface (0, 0)
	8 java/util/List.iterator:()Ljava/util/Iterator; (0, 0)
	10 0 (0, 0)
	12 newarray (0, 0)
	13 7 (0, 0)
	14 astore_2 (0, 0)
	15 iconst_0 (0, 0)
	16 istore_3 (0, 0)
	17 aload_0 (1, 4)
	18 getfield (1, 4)
	19 org/apache/commons/math3/optimization/fitting/CurveFitter$OldTheoreticalValuesFunction.this$0:Lorg/apache/commons/math3/optimization/fitting/CurveFitter; (1, 4)
	21 invokestatic (1, 4)
	22 org/apache/commons/math3/optimization/fitting/CurveFitter.access$000:(Lorg/apache/commons/math3/optimization/fitting/CurveFitter;)Ljava/util/List; (1, 4)
	24 invokeinterface (1, 4)
	25 java/util/List.java/util/Iterator (1, 4)
	27 0 (1, 4)
	29 astore (1, 4)
	30 #4 (1, 4)
	31 aload (1, 4)
	32 #4 (1, 4)
	33 invokeinterface (1, 4)
	34 java/util/Iterator.next:()Ljava/lang/Object; (1, 4)
	36 0 (1, 4)
	38 ifeq (1, 4)
	39 39 (1, 4)
	41 aload (1, 4)
	42 #4 (1, 4)
	43 invokeinterface (1, 4)
	44 java/util/Iterator.org/apache/commons/math3/optimization/fitting/WeightedObservedPoint (1, 4)
	46 0 (1, 4)
	48 checkcast (1, 4)
	49 org/apache/commons/math3/optimization/fitting/WeightedObservedPoint (1, 4)
	51 astore (1, 4)
	52 #5 (1, 4)
	53 aload_2 (1, 4)
	54 iload_3 (1, 4)
	55 iinc (1, 4)
	56 #3 (1, 4)
	57 42 (1, 4)
	58 aload_0 (1, 4)
	59 getfield (1, 4)
	60 org/apache/commons/math3/optimization/fitting/CurveFitter$OldTheoreticalValuesFunction.f:Lorg/apache/commons/math3/analysis/ParametricUnivariateFunction; (1, 4)
	62 aload (1, 4)
	63 #5 (1, 4)
	64 invokevirtual (1, 4)
	65 org/apache/commons/math3/optimization/fitting/WeightedObservedPoint.getX:()D (1, 4)
	67 aload_1 (1, 4)
	68 invokeinterface (1, 4)
	69 org/apache/commons/math3/analysis/ParametricUnivariateFunction.org/apache/commons/math3/optimization/fitting/CurveFitter$OldTheoreticalValuesFunction (1, 4)
	71 0 (1, 4)
	73 dastore (1, 4)
	74 goto (0, 0)
	75 -43 (0, 0)
	77 aload_2 (0, 0)
	78 areturn (0, 0)

Method: access$100
	0 aload_0 (0, 0)
	1 getfield (0, 0)
	2 org/apache/commons/math3/optimization/fitting/CurveFitter$OldTheoreticalValuesFunction.f:Lorg/apache/commons/math3/analysis/ParametricUnivariateFunction; (0, 0)
	4 areturn (0, 0)

