Method: <init>
	0 aload_0 (1, 1)
	1 invokespecial (1, 1)
	2 java/lang/Object.<init>:()V (1, 1)
	4 aload_0 (1, 1)
	5 aconst_null (1, 1)
	6 putfield (1, 1)
	7 org/apache/commons/math3/optimization/fitting/CurveFitter.oldOptimizer:Lorg/apache/commons/math3/optimization/DifferentiableMultivariateVectorOptimizer; (1, 1)
	9 aload_0 (1, 1)
	10 aload_1 (1, 1)
	11 putfield (1, 1)
	12 org/apache/commons/math3/optimization/fitting/CurveFitter.optimizer:Lorg/apache/commons/math3/optimization/MultivariateDifferentiableVectorOptimizer; (1, 1)
	14 aload_0 (1, 1)
	15 new (1, 1)
	16 java/util/ArrayList (1, 1)
	18 dup (1, 1)
	19 invokespecial (1, 1)
	20 java/util/ArrayList.<init>:()V (1, 1)
	22 putfield (1, 1)
	23 org/apache/commons/math3/optimization/fitting/CurveFitter.observations:Ljava/util/List; (1, 1)
	25 return (0, 0)

Method: addObservedPoint
	0 aload_0 (0, 0)
	1 getfield (0, 0)
	2 org/apache/commons/math3/optimization/fitting/CurveFitter.observations:Ljava/util/List; (0, 0)
	4 aload_1 (0, 0)
	5 invokeinterface (0, 0)
	6 java/util/List.size:()I (0, 0)
	8 0 (0, 0)
	10 pop (0, 0)
	11 return (0, 0)

Method: getObservations
	0 aload_0 (0, 0)
	1 getfield (0, 0)
	2 org/apache/commons/math3/optimization/fitting/CurveFitter.observations:Ljava/util/List; (0, 0)
	4 aload_0 (0, 0)
	5 getfield (0, 0)
	6 org/apache/commons/math3/optimization/fitting/CurveFitter.observations:Ljava/util/List; (0, 0)
	8 invokeinterface (0, 0)
	9 java/util/List.toArray:([Ljava/lang/Object;)[Ljava/lang/Object; (0, 0)
	11 0 (0, 0)
	13 anewarray (0, 0)
	14 org/apache/commons/math3/optimization/fitting/WeightedObservedPoint (0, 0)
	16 invokeinterface (0, 0)
	17 java/util/List.[Lorg/apache/commons/math3/optimization/fitting/WeightedObservedPoint; (0, 0)
	19 0 (0, 0)
	21 checkcast (0, 0)
	22 [Lorg/apache/commons/math3/optimization/fitting/WeightedObservedPoint; (0, 0)
	24 areturn (0, 0)

Method: clearObservations
	0 aload_0 (0, 0)
	1 getfield (0, 0)
	2 org/apache/commons/math3/optimization/fitting/CurveFitter.observations:Ljava/util/List; (0, 0)
	4 invokeinterface (0, 0)
	5 java/util/List.java/lang/Integer (0, 0)
	7 0 (0, 0)
	9 return (0, 0)

Method: fit
	0 aload_0 (0, 0)
	1 getfield (0, 0)
	2 org/apache/commons/math3/optimization/fitting/CurveFitter.observations:Ljava/util/List; (0, 0)
	4 invokeinterface (0, 0)
	5 java/util/List.toArray:([Ljava/lang/Object;)[Ljava/lang/Object; (0, 0)
	7 0 (0, 0)
	9 newarray (0, 0)
	10 7 (0, 0)
	11 astore (0, 0)
	12 #4 (0, 0)
	13 aload_0 (0, 0)
	14 getfield (0, 0)
	15 org/apache/commons/math3/optimization/fitting/CurveFitter.observations:Ljava/util/List; (0, 0)
	17 invokeinterface (0, 0)
	18 java/util/List.toArray:([Ljava/lang/Object;)[Ljava/lang/Object; (0, 0)
	20 0 (0, 0)
	22 newarray (0, 0)
	23 7 (0, 0)
	24 astore (0, 0)
	25 #5 (0, 0)
	26 iconst_0 (0, 0)
	27 istore (0, 0)
	28 #6 (0, 0)
	29 aload_0 (1, 4)
	30 getfield (1, 4)
	31 org/apache/commons/math3/optimization/fitting/CurveFitter.observations:Ljava/util/List; (1, 4)
	33 invokeinterface (1, 4)
	34 java/util/List.java/util/Iterator (1, 4)
	36 0 (1, 4)
	38 astore (1, 4)
	39 #7 (1, 4)
	40 aload (1, 4)
	41 #7 (1, 4)
	42 invokeinterface (1, 4)
	43 java/util/Iterator.next:()Ljava/lang/Object; (1, 4)
	45 0 (1, 4)
	47 ifeq (1, 4)
	48 41 (1, 4)
	50 aload (1, 4)
	51 #7 (1, 4)
	52 invokeinterface (1, 4)
	53 java/util/Iterator.getY:()D (1, 4)
	55 0 (1, 4)
	57 checkcast (1, 4)
	58 org/apache/commons/math3/optimization/fitting/WeightedObservedPoint (1, 4)
	60 astore (1, 4)
	61 #8 (1, 4)
	62 aload (1, 4)
	63 #4 (1, 4)
	64 iload (1, 4)
	65 #6 (1, 4)
	66 aload (1, 4)
	67 #8 (1, 4)
	68 invokevirtual (1, 4)
	69 org/apache/commons/math3/optimization/fitting/WeightedObservedPoint.getY:()D (1, 4)
	71 dastore (1, 4)
	72 aload (1, 4)
	73 #5 (1, 4)
	74 iload (1, 4)
	75 #6 (1, 4)
	76 aload (1, 4)
	77 #8 (1, 4)
	78 invokevirtual (1, 4)
	79 org/apache/commons/math3/optimization/fitting/WeightedObservedPoint.getWeight:()D (1, 4)
	81 dastore (1, 4)
	82 iinc (1, 4)
	83 #6 (1, 4)
	84 -89 (1, 4)
	85 goto (0, 0)
	86 -45 (0, 0)
	88 aload_0 (2, 1)
	89 getfield (2, 1)
	90 org/apache/commons/math3/optimization/fitting/CurveFitter.optimizer:Lorg/apache/commons/math3/optimization/MultivariateDifferentiableVectorOptimizer; (2, 1)
	92 ifnonnull (2, 1)
	93 32 (2, 1)
	95 aload_0 (2, 1)
	96 getfield (2, 1)
	97 org/apache/commons/math3/optimization/fitting/CurveFitter.oldOptimizer:Lorg/apache/commons/math3/optimization/DifferentiableMultivariateVectorOptimizer; (2, 1)
	99 iload_1 (2, 1)
	100 new (2, 1)
	101 org/apache/commons/math3/optimization/fitting/CurveFitter$OldTheoreticalValuesFunction (2, 1)
	103 dup (2, 1)
	104 aload_0 (2, 1)
	105 aload_2 (2, 1)
	106 invokespecial (2, 1)
	107 org/apache/commons/math3/optimization/fitting/CurveFitter$OldTheoreticalValuesFunction.<init>:(Lorg/apache/commons/math3/optimization/fitting/CurveFitter;Lorg/apache/commons/math3/analysis/ParametricUnivariateFunction;)V (2, 1)
	109 aload (2, 1)
	110 #4 (2, 1)
	111 aload (2, 1)
	112 #5 (2, 1)
	113 aload_3 (2, 1)
	114 invokeinterface (2, 1)
	115 org/apache/commons/math3/optimization/DifferentiableMultivariateVectorOptimizer.org/apache/commons/math3/optimization/fitting/CurveFitter$TheoreticalValuesFunction (2, 1)
	117 0 (2, 1)
	119 astore (2, 1)
	120 #7 (2, 1)
	121 goto (2, 1)
	122 29 (2, 1)
	124 aload_0 (3, 2)
	125 getfield (3, 2)
	126 org/apache/commons/math3/optimization/fitting/CurveFitter.optimizer:Lorg/apache/commons/math3/optimization/MultivariateDifferentiableVectorOptimizer; (3, 2)
	128 iload_1 (3, 2)
	129 new (3, 2)
	130 org/apache/commons/math3/optimization/fitting/CurveFitter$TheoreticalValuesFunction (3, 2)
	132 dup (3, 2)
	133 aload_0 (3, 2)
	134 aload_2 (3, 2)
	135 invokespecial (3, 2)
	136 org/apache/commons/math3/optimization/fitting/CurveFitter$TheoreticalValuesFunction.<init>:(Lorg/apache/commons/math3/optimization/fitting/CurveFitter;Lorg/apache/commons/math3/analysis/ParametricUnivariateFunction;)V (3, 2)
	138 aload (3, 2)
	139 #4 (3, 2)
	140 aload (3, 2)
	141 #5 (3, 2)
	142 aload_3 (3, 2)
	143 invokeinterface (3, 2)
	144 org/apache/commons/math3/optimization/MultivariateDifferentiableVectorOptimizer.org/apache/commons/math3/optimization/fitting/CurveFitter$TheoreticalValuesFunction (3, 2)
	146 0 (3, 2)
	148 astore (3, 2)
	149 #7 (3, 2)
	150 aload (1, 4)
	151 #7 (1, 4)
	152 invokevirtual (1, 4)
	153 org/apache/commons/math3/optimization/PointVectorValuePair.getPointRef:()[D (1, 4)
	155 areturn (0, 4)

Method: access$000
	0 aload_0 (0, 0)
	1 getfield (0, 0)
	2 org/apache/commons/math3/optimization/fitting/CurveFitter.observations:Ljava/util/List; (0, 0)
	4 areturn (0, 0)

