Method: value
	0 ldc2_w (0, 0)
	1 inf (0, 0)
	3 dstore (0, 0)
	4 #4 (0, 0)
	5 aload_0 (0, 0)
	6 dload_1 (0, 0)
	7 aload_3 (0, 0)
	8 invokespecial (0, 0)
	9 org/apache/commons/math3/analysis/function/Gaussian$Parametric.value:(D[D)D (0, 0)
	11 dstore (0, 0)
	12 #4 (0, 0)
	13 goto (0, 0)
	14 5 (0, 0)
	16 astore (0, 0)
	17 #6 (0, 0)
	18 dload (0, 0)
	19 #4 (0, 0)
	20 dreturn (0, 0)

Method: gradient
	0 iconst_3 (0, 0)
	1 newarray (0, 0)
	2 7 (0, 0)
	3 dup (0, 0)
	4 iconst_0 (0, 0)
	5 ldc2_w (0, 0)
	6 inf (0, 0)
	8 dastore (0, 0)
	9 dup (0, 0)
	10 iconst_1 (0, 0)
	11 ldc2_w (0, 0)
	12 inf (0, 0)
	14 dastore (0, 0)
	15 dup (0, 0)
	16 iconst_2 (0, 0)
	17 ldc2_w (0, 0)
	18 inf (0, 0)
	20 dastore (0, 0)
	21 astore (0, 0)
	22 #4 (0, 0)
	23 aload_0 (0, 0)
	24 dload_1 (0, 0)
	25 aload_3 (0, 0)
	26 invokespecial (0, 0)
	27 org/apache/commons/math3/analysis/function/Gaussian$Parametric.gradient:(D[D)[D (0, 0)
	29 astore (0, 0)
	30 #4 (0, 0)
	31 goto (0, 0)
	32 5 (0, 0)
	34 astore (0, 0)
	35 #5 (0, 0)
	36 aload (0, 0)
	37 #4 (0, 0)
	38 areturn (0, 0)

