Method: <init>
	0 aload_0 (0, 0)
	1 aload_1 (0, 0)
	2 invokespecial (0, 0)
	3 org/apache/commons/math3/optimization/fitting/CurveFitter.<init>:(Lorg/apache/commons/math3/optimization/DifferentiableMultivariateVectorOptimizer;)V (0, 0)
	5 return (0, 0)

Method: fit
	0 aload_0 (0, 0)
	1 new (0, 0)
	2 org/apache/commons/math3/optimization/fitting/HarmonicFitter$ParameterGuesser (0, 0)
	4 dup (0, 0)
	5 aload_0 (0, 0)
	6 invokevirtual (0, 0)
	7 org/apache/commons/math3/optimization/fitting/HarmonicFitter.getObservations:()[Lorg/apache/commons/math3/optimization/fitting/WeightedObservedPoint; (0, 0)
	9 invokespecial (0, 0)
	10 org/apache/commons/math3/optimization/fitting/HarmonicFitter$ParameterGuesser.<init>:([Lorg/apache/commons/math3/optimization/fitting/WeightedObservedPoint;)V (0, 0)
	12 invokevirtual (0, 0)
	13 org/apache/commons/math3/optimization/fitting/HarmonicFitter$ParameterGuesser.guess:()[D (0, 0)
	15 invokevirtual (0, 0)
	16 org/apache/commons/math3/optimization/fitting/HarmonicFitter.fit:([D)[D (0, 0)
	18 areturn (0, 0)

