Method: <init>
	0 aload_0 (0, 0)
	1 aload_1 (0, 0)
	2 getfield (0, 0)
	3 org/apache/commons/math3/geometry/spherical/twod/Circle.pole:Lorg/apache/commons/math3/geometry/euclidean/threed/Vector3D; (0, 0)
	5 aload_1 (0, 0)
	6 getfield (0, 0)
	7 org/apache/commons/math3/geometry/spherical/twod/Circle.x:Lorg/apache/commons/math3/geometry/euclidean/threed/Vector3D; (0, 0)
	9 aload_1 (0, 0)
	10 getfield (0, 0)
	11 org/apache/commons/math3/geometry/spherical/twod/Circle.y:Lorg/apache/commons/math3/geometry/euclidean/threed/Vector3D; (0, 0)
	13 aload_1 (0, 0)
	14 getfield (0, 0)
	15 org/apache/commons/math3/geometry/spherical/twod/Circle.tolerance:D (0, 0)
	17 invokespecial (0, 0)
	18 org/apache/commons/math3/geometry/spherical/twod/Circle.<init>:(Lorg/apache/commons/math3/geometry/euclidean/threed/Vector3D;Lorg/apache/commons/math3/geometry/euclidean/threed/Vector3D;Lorg/apache/commons/math3/geometry/euclidean/threed/Vector3D;D)V (0, 0)
	20 return (0, 0)

Method: copySelf
	0 aload_0 (0, 0)
	1 invokevirtual (0, 0)
	2 org/apache/commons/math3/geometry/spherical/twod/Circle.copySelf:()Lorg/apache/commons/math3/geometry/spherical/twod/Circle; (0, 0)
	4 areturn (0, 0)

Method: reset
	0 aload_0 (0, 0)
	1 aload_1 (0, 0)
	2 invokevirtual (0, 0)
	3 org/apache/commons/math3/geometry/euclidean/threed/Vector3D.normalize:()Lorg/apache/commons/math3/geometry/euclidean/threed/Vector3D; (0, 0)
	5 putfield (0, 0)
	6 org/apache/commons/math3/geometry/spherical/twod/Circle.pole:Lorg/apache/commons/math3/geometry/euclidean/threed/Vector3D; (0, 0)
	8 aload_0 (0, 0)
	9 aload_1 (0, 0)
	10 invokevirtual (0, 0)
	11 org/apache/commons/math3/geometry/euclidean/threed/Vector3D.orthogonal:()Lorg/apache/commons/math3/geometry/euclidean/threed/Vector3D; (0, 0)
	13 putfield (0, 0)
	14 org/apache/commons/math3/geometry/spherical/twod/Circle.x:Lorg/apache/commons/math3/geometry/euclidean/threed/Vector3D; (0, 0)
	16 aload_0 (0, 0)
	17 aload_1 (0, 0)
	18 aload_0 (0, 0)
	19 getfield (0, 0)
	20 org/apache/commons/math3/geometry/spherical/twod/Circle.x:Lorg/apache/commons/math3/geometry/euclidean/threed/Vector3D; (0, 0)
	22 invokestatic (0, 0)
	23 org/apache/commons/math3/geometry/euclidean/threed/Vector3D.crossProduct:(Lorg/apache/commons/math3/geometry/euclidean/threed/Vector3D;Lorg/apache/commons/math3/geometry/euclidean/threed/Vector3D;)Lorg/apache/commons/math3/geometry/euclidean/threed/Vector3D; (0, 0)
	25 invokevirtual (0, 0)
	26 org/apache/commons/math3/geometry/euclidean/threed/Vector3D.normalize:()Lorg/apache/commons/math3/geometry/euclidean/threed/Vector3D; (0, 0)
	28 putfield (0, 0)
	29 org/apache/commons/math3/geometry/spherical/twod/Circle.y:Lorg/apache/commons/math3/geometry/euclidean/threed/Vector3D; (0, 0)
	31 return (0, 0)

Method: revertSelf
	0 aload_0 (0, 0)
	1 aload_0 (0, 0)
	2 getfield (0, 0)
	3 org/apache/commons/math3/geometry/spherical/twod/Circle.y:Lorg/apache/commons/math3/geometry/euclidean/threed/Vector3D; (0, 0)
	5 invokevirtual (0, 0)
	6 org/apache/commons/math3/geometry/euclidean/threed/Vector3D.negate:()Lorg/apache/commons/math3/geometry/euclidean/threed/Vector3D; (0, 0)
	8 putfield (0, 0)
	9 org/apache/commons/math3/geometry/spherical/twod/Circle.y:Lorg/apache/commons/math3/geometry/euclidean/threed/Vector3D; (0, 0)
	11 aload_0 (0, 0)
	12 aload_0 (0, 0)
	13 getfield (0, 0)
	14 org/apache/commons/math3/geometry/spherical/twod/Circle.pole:Lorg/apache/commons/math3/geometry/euclidean/threed/Vector3D; (0, 0)
	16 invokevirtual (0, 0)
	17 org/apache/commons/math3/geometry/euclidean/threed/Vector3D.negate:()Lorg/apache/commons/math3/geometry/euclidean/threed/Vector3D; (0, 0)
	19 putfield (0, 0)
	20 org/apache/commons/math3/geometry/spherical/twod/Circle.pole:Lorg/apache/commons/math3/geometry/euclidean/threed/Vector3D; (0, 0)
	22 return (0, 0)

Method: getReverse
	0 new (0, 0)
	1 org/apache/commons/math3/geometry/spherical/twod/Circle (0, 0)
	3 dup (0, 0)
	4 aload_0 (0, 0)
	5 getfield (0, 0)
	6 org/apache/commons/math3/geometry/spherical/twod/Circle.pole:Lorg/apache/commons/math3/geometry/euclidean/threed/Vector3D; (0, 0)
	8 invokevirtual (0, 0)
	9 org/apache/commons/math3/geometry/euclidean/threed/Vector3D.negate:()Lorg/apache/commons/math3/geometry/euclidean/threed/Vector3D; (0, 0)
	11 aload_0 (0, 0)
	12 getfield (0, 0)
	13 org/apache/commons/math3/geometry/spherical/twod/Circle.x:Lorg/apache/commons/math3/geometry/euclidean/threed/Vector3D; (0, 0)
	15 aload_0 (0, 0)
	16 getfield (0, 0)
	17 org/apache/commons/math3/geometry/spherical/twod/Circle.y:Lorg/apache/commons/math3/geometry/euclidean/threed/Vector3D; (0, 0)
	19 invokevirtual (0, 0)
	20 org/apache/commons/math3/geometry/euclidean/threed/Vector3D.negate:()Lorg/apache/commons/math3/geometry/euclidean/threed/Vector3D; (0, 0)
	22 aload_0 (0, 0)
	23 getfield (0, 0)
	24 org/apache/commons/math3/geometry/spherical/twod/Circle.tolerance:D (0, 0)
	26 invokespecial (0, 0)
	27 org/apache/commons/math3/geometry/spherical/twod/Circle.<init>:(Lorg/apache/commons/math3/geometry/euclidean/threed/Vector3D;Lorg/apache/commons/math3/geometry/euclidean/threed/Vector3D;Lorg/apache/commons/math3/geometry/euclidean/threed/Vector3D;D)V (0, 0)
	29 areturn (0, 0)

Method: project
	0 aload_0 (0, 0)
	1 aload_0 (0, 0)
	2 aload_1 (0, 0)
	3 invokevirtual (0, 0)
	4 org/apache/commons/math3/geometry/spherical/twod/Circle.toSubSpace:(Lorg/apache/commons/math3/geometry/Point;)Lorg/apache/commons/math3/geometry/spherical/oned/S1Point; (0, 0)
	6 invokevirtual (0, 0)
	7 org/apache/commons/math3/geometry/spherical/twod/Circle.toSpace:(Lorg/apache/commons/math3/geometry/Point;)Lorg/apache/commons/math3/geometry/spherical/twod/S2Point; (0, 0)
	9 areturn (0, 0)

Method: getTolerance
	0 aload_0 (0, 0)
	1 getfield (0, 0)
	2 org/apache/commons/math3/geometry/spherical/twod/Circle.tolerance:D (0, 0)
	4 dreturn (0, 0)

Method: toSubSpace
	0 aload_0 (0, 0)
	1 aload_1 (0, 0)
	2 invokevirtual (0, 0)
	3 org/apache/commons/math3/geometry/spherical/twod/Circle.toSubSpace:(Lorg/apache/commons/math3/geometry/Point;)Lorg/apache/commons/math3/geometry/spherical/oned/S1Point; (0, 0)
	5 areturn (0, 0)

Method: getPhase
	0 ldc2_w (0, 0)
	1 3.141592653589793 (0, 0)
	3 aload_1 (0, 0)
	4 aload_0 (0, 0)
	5 getfield (0, 0)
	6 org/apache/commons/math3/geometry/spherical/twod/Circle.y:Lorg/apache/commons/math3/geometry/euclidean/threed/Vector3D; (0, 0)
	8 invokevirtual (0, 0)
	9 org/apache/commons/math3/geometry/euclidean/threed/Vector3D.dotProduct:(Lorg/apache/commons/math3/geometry/Vector;)D (0, 0)
	11 dneg (0, 0)
	12 aload_1 (0, 0)
	13 aload_0 (0, 0)
	14 getfield (0, 0)
	15 org/apache/commons/math3/geometry/spherical/twod/Circle.x:Lorg/apache/commons/math3/geometry/euclidean/threed/Vector3D; (0, 0)
	17 invokevirtual (0, 0)
	18 org/apache/commons/math3/geometry/euclidean/threed/Vector3D.dotProduct:(Lorg/apache/commons/math3/geometry/Vector;)D (0, 0)
	20 dneg (0, 0)
	21 invokestatic (0, 0)
	22 org/apache/commons/math3/util/FastMath.atan2:(DD)D (0, 0)
	24 dadd (0, 0)
	25 dreturn (0, 0)

Method: toSpace
	0 aload_0 (0, 0)
	1 aload_1 (0, 0)
	2 invokevirtual (0, 0)
	3 org/apache/commons/math3/geometry/spherical/twod/Circle.toSpace:(Lorg/apache/commons/math3/geometry/Point;)Lorg/apache/commons/math3/geometry/spherical/twod/S2Point; (0, 0)
	5 areturn (0, 0)

Method: getPointAt
	0 new (0, 0)
	1 org/apache/commons/math3/geometry/euclidean/threed/Vector3D (0, 0)
	3 dup (0, 0)
	4 dload_1 (0, 0)
	5 invokestatic (0, 0)
	6 org/apache/commons/math3/util/FastMath.cos:(D)D (0, 0)
	8 aload_0 (0, 0)
	9 getfield (0, 0)
	10 org/apache/commons/math3/geometry/spherical/twod/Circle.x:Lorg/apache/commons/math3/geometry/euclidean/threed/Vector3D; (0, 0)
	12 dload_1 (0, 0)
	13 invokestatic (0, 0)
	14 org/apache/commons/math3/util/FastMath.sin:(D)D (0, 0)
	16 aload_0 (0, 0)
	17 getfield (0, 0)
	18 org/apache/commons/math3/geometry/spherical/twod/Circle.y:Lorg/apache/commons/math3/geometry/euclidean/threed/Vector3D; (0, 0)
	20 invokespecial (0, 0)
	21 org/apache/commons/math3/geometry/euclidean/threed/Vector3D.<init>:(DLorg/apache/commons/math3/geometry/euclidean/threed/Vector3D;DLorg/apache/commons/math3/geometry/euclidean/threed/Vector3D;)V (0, 0)
	23 areturn (0, 0)

Method: getXAxis
	0 aload_0 (0, 0)
	1 getfield (0, 0)
	2 org/apache/commons/math3/geometry/spherical/twod/Circle.x:Lorg/apache/commons/math3/geometry/euclidean/threed/Vector3D; (0, 0)
	4 areturn (0, 0)

Method: getYAxis
	0 aload_0 (0, 0)
	1 getfield (0, 0)
	2 org/apache/commons/math3/geometry/spherical/twod/Circle.y:Lorg/apache/commons/math3/geometry/euclidean/threed/Vector3D; (0, 0)
	4 areturn (0, 0)

Method: getPole
	0 aload_0 (0, 0)
	1 getfield (0, 0)
	2 org/apache/commons/math3/geometry/spherical/twod/Circle.pole:Lorg/apache/commons/math3/geometry/euclidean/threed/Vector3D; (0, 0)
	4 areturn (0, 0)

Method: getInsideArc
	0 aload_0 (0, 0)
	1 aload_1 (0, 0)
	2 getfield (0, 0)
	3 org/apache/commons/math3/geometry/spherical/twod/Circle.pole:Lorg/apache/commons/math3/geometry/euclidean/threed/Vector3D; (0, 0)
	5 invokevirtual (0, 0)
	6 org/apache/commons/math3/geometry/spherical/twod/Circle.getPhase:(Lorg/apache/commons/math3/geometry/euclidean/threed/Vector3D;)D (0, 0)
	8 dstore_2 (0, 0)
	9 ldc2_w (0, 0)
	10 1.5707963267948966 (0, 0)
	12 dstore (0, 0)
	13 #4 (0, 0)
	14 new (0, 0)
	15 org/apache/commons/math3/geometry/spherical/oned/Arc (0, 0)
	17 dup (0, 0)
	18 dload_2 (0, 0)
	19 ldc2_w (0, 0)
	20 1.5707963267948966 (0, 0)
	22 dsub (0, 0)
	23 dload_2 (0, 0)
	24 ldc2_w (0, 0)
	25 1.5707963267948966 (0, 0)
	27 dadd (0, 0)
	28 aload_0 (0, 0)
	29 getfield (0, 0)
	30 org/apache/commons/math3/geometry/spherical/twod/Circle.tolerance:D (0, 0)
	32 invokespecial (0, 0)
	33 org/apache/commons/math3/geometry/spherical/oned/Arc.<init>:(DDD)V (0, 0)
	35 areturn (0, 0)

Method: wholeHyperplane
	0 aload_0 (0, 0)
	1 invokevirtual (0, 0)
	2 org/apache/commons/math3/geometry/spherical/twod/Circle.wholeHyperplane:()Lorg/apache/commons/math3/geometry/spherical/twod/SubCircle; (0, 0)
	4 areturn (0, 0)

Method: wholeSpace
	0 aload_0 (0, 0)
	1 invokevirtual (0, 0)
	2 org/apache/commons/math3/geometry/spherical/twod/Circle.wholeSpace:()Lorg/apache/commons/math3/geometry/spherical/twod/SphericalPolygonsSet; (0, 0)
	4 areturn (0, 0)

Method: getOffset
	0 aload_0 (0, 0)
	1 getfield (0, 0)
	2 org/apache/commons/math3/geometry/spherical/twod/Circle.pole:Lorg/apache/commons/math3/geometry/euclidean/threed/Vector3D; (0, 0)
	4 aload_1 (0, 0)
	5 invokestatic (0, 0)
	6 org/apache/commons/math3/geometry/euclidean/threed/Vector3D.angle:(Lorg/apache/commons/math3/geometry/euclidean/threed/Vector3D;Lorg/apache/commons/math3/geometry/euclidean/threed/Vector3D;)D (0, 0)
	8 ldc2_w (0, 0)
	9 1.5707963267948966 (0, 0)
	11 dsub (0, 0)
	12 dreturn (0, 0)

Method: sameOrientationAs
	0 aload_1 (0, 0)
	1 checkcast (0, 0)
	2 org/apache/commons/math3/geometry/spherical/twod/Circle (0, 0)
	4 astore_2 (0, 0)
	5 aload_0 (0, 0)
	6 getfield (0, 0)
	7 org/apache/commons/math3/geometry/spherical/twod/Circle.pole:Lorg/apache/commons/math3/geometry/euclidean/threed/Vector3D; (0, 0)
	9 aload_2 (0, 0)
	10 getfield (0, 0)
	11 org/apache/commons/math3/geometry/spherical/twod/Circle.pole:Lorg/apache/commons/math3/geometry/euclidean/threed/Vector3D; (0, 0)
	13 invokestatic (0, 0)
	14 org/apache/commons/math3/geometry/euclidean/threed/Vector3D.dotProduct:(Lorg/apache/commons/math3/geometry/euclidean/threed/Vector3D;Lorg/apache/commons/math3/geometry/euclidean/threed/Vector3D;)D (0, 0)
	16 dconst_0 (0, 0)
	17 dcmpl (0, 0)
	18 iflt (0, 0)
	19 7 (0, 0)
	21 iconst_1 (0, 0)
	22 goto (0, 0)
	23 4 (0, 0)
	25 iconst_0 (0, 0)
	26 ireturn (0, 0)

Method: getTransform
	0 new (1, 4)
	1 org/apache/commons/math3/geometry/spherical/twod/Circle$CircleTransform (1, 4)
	3 dup (1, 4)
	4 aload_0 (1, 4)
	5 invokespecial (1, 4)
	6 org/apache/commons/math3/geometry/spherical/twod/Circle$CircleTransform.<init>:(Lorg/apache/commons/math3/geometry/euclidean/threed/Rotation;)V (1, 4)
	8 areturn (0, 4)

Method: access$000
	0 aload_0 (0, 0)
	1 getfield (0, 0)
	2 org/apache/commons/math3/geometry/spherical/twod/Circle.pole:Lorg/apache/commons/math3/geometry/euclidean/threed/Vector3D; (0, 0)
	4 areturn (0, 0)

Method: access$100
	0 aload_0 (0, 0)
	1 getfield (0, 0)
	2 org/apache/commons/math3/geometry/spherical/twod/Circle.x:Lorg/apache/commons/math3/geometry/euclidean/threed/Vector3D; (0, 0)
	4 areturn (0, 0)

Method: access$200
	0 aload_0 (0, 0)
	1 getfield (0, 0)
	2 org/apache/commons/math3/geometry/spherical/twod/Circle.y:Lorg/apache/commons/math3/geometry/euclidean/threed/Vector3D; (0, 0)
	4 areturn (0, 0)

Method: access$300
	0 aload_0 (0, 0)
	1 getfield (0, 0)
	2 org/apache/commons/math3/geometry/spherical/twod/Circle.tolerance:D (0, 0)
	4 dreturn (0, 0)

