Method: <init>
	0 aload_0 (0, 0)
	1 invokespecial (0, 0)
	2 java/lang/Object.<init>:()V (0, 0)
	4 aload_0 (0, 0)
	5 aload_1 (0, 0)
	6 putfield (0, 0)
	7 org/apache/commons/math3/geometry/spherical/twod/Edge.start:Lorg/apache/commons/math3/geometry/spherical/twod/Vertex; (0, 0)
	9 aload_0 (0, 0)
	10 aload_2 (0, 0)
	11 putfield (0, 0)
	12 org/apache/commons/math3/geometry/spherical/twod/Edge.end:Lorg/apache/commons/math3/geometry/spherical/twod/Vertex; (0, 0)
	14 aload_0 (0, 0)
	15 dload_3 (0, 0)
	16 putfield (0, 0)
	17 org/apache/commons/math3/geometry/spherical/twod/Edge.length:D (0, 0)
	19 aload_0 (0, 0)
	20 aload (0, 0)
	21 #5 (0, 0)
	22 putfield (0, 0)
	23 org/apache/commons/math3/geometry/spherical/twod/Edge.circle:Lorg/apache/commons/math3/geometry/spherical/twod/Circle; (0, 0)
	25 aload_1 (0, 0)
	26 aload_0 (0, 0)
	27 invokevirtual (0, 0)
	28 org/apache/commons/math3/geometry/spherical/twod/Vertex.setOutgoing:(Lorg/apache/commons/math3/geometry/spherical/twod/Edge;)V (0, 0)
	30 aload_2 (0, 0)
	31 aload_0 (0, 0)
	32 invokevirtual (0, 0)
	33 org/apache/commons/math3/geometry/spherical/twod/Vertex.setIncoming:(Lorg/apache/commons/math3/geometry/spherical/twod/Edge;)V (0, 0)
	35 return (0, 0)

Method: getStart
	0 aload_0 (0, 0)
	1 getfield (0, 0)
	2 org/apache/commons/math3/geometry/spherical/twod/Edge.start:Lorg/apache/commons/math3/geometry/spherical/twod/Vertex; (0, 0)
	4 areturn (0, 0)

Method: getEnd
	0 aload_0 (1, 1)
	1 getfield (1, 1)
	2 org/apache/commons/math3/geometry/spherical/twod/Edge.end:Lorg/apache/commons/math3/geometry/spherical/twod/Vertex; (1, 1)
	4 areturn (1, 1)

Method: getLength
	0 aload_0 (0, 0)
	1 getfield (0, 0)
	2 org/apache/commons/math3/geometry/spherical/twod/Edge.length:D (0, 0)
	4 dreturn (0, 0)

Method: getCircle
	0 aload_0 (0, 0)
	1 getfield (0, 0)
	2 org/apache/commons/math3/geometry/spherical/twod/Edge.circle:Lorg/apache/commons/math3/geometry/spherical/twod/Circle; (0, 0)
	4 areturn (0, 0)

Method: getPointAt
	0 aload_0 (0, 0)
	1 getfield (0, 0)
	2 org/apache/commons/math3/geometry/spherical/twod/Edge.circle:Lorg/apache/commons/math3/geometry/spherical/twod/Circle; (0, 0)
	4 dload_1 (0, 0)
	5 aload_0 (0, 0)
	6 getfield (0, 0)
	7 org/apache/commons/math3/geometry/spherical/twod/Edge.circle:Lorg/apache/commons/math3/geometry/spherical/twod/Circle; (0, 0)
	9 aload_0 (0, 0)
	10 getfield (0, 0)
	11 org/apache/commons/math3/geometry/spherical/twod/Edge.start:Lorg/apache/commons/math3/geometry/spherical/twod/Vertex; (0, 0)
	13 invokevirtual (0, 0)
	14 org/apache/commons/math3/geometry/spherical/twod/Vertex.getLocation:()Lorg/apache/commons/math3/geometry/spherical/twod/S2Point; (0, 0)
	16 invokevirtual (0, 0)
	17 org/apache/commons/math3/geometry/spherical/twod/S2Point.getVector:()Lorg/apache/commons/math3/geometry/euclidean/threed/Vector3D; (0, 0)
	19 invokevirtual (0, 0)
	20 org/apache/commons/math3/geometry/spherical/twod/Circle.getPhase:(Lorg/apache/commons/math3/geometry/euclidean/threed/Vector3D;)D (0, 0)
	22 dadd (0, 0)
	23 invokevirtual (0, 0)
	24 org/apache/commons/math3/geometry/spherical/twod/Circle.getPointAt:(D)Lorg/apache/commons/math3/geometry/euclidean/threed/Vector3D; (0, 0)
	26 areturn (0, 0)

Method: setNextEdge
	0 aload_0 (0, 0)
	1 aload_1 (0, 0)
	2 invokevirtual (0, 0)
	3 org/apache/commons/math3/geometry/spherical/twod/Edge.getStart:()Lorg/apache/commons/math3/geometry/spherical/twod/Vertex; (0, 0)
	5 putfield (0, 0)
	6 org/apache/commons/math3/geometry/spherical/twod/Edge.end:Lorg/apache/commons/math3/geometry/spherical/twod/Vertex; (0, 0)
	8 aload_0 (0, 0)
	9 getfield (0, 0)
	10 org/apache/commons/math3/geometry/spherical/twod/Edge.end:Lorg/apache/commons/math3/geometry/spherical/twod/Vertex; (0, 0)
	12 aload_0 (0, 0)
	13 invokevirtual (0, 0)
	14 org/apache/commons/math3/geometry/spherical/twod/Vertex.setIncoming:(Lorg/apache/commons/math3/geometry/spherical/twod/Edge;)V (0, 0)
	16 aload_0 (0, 0)
	17 getfield (0, 0)
	18 org/apache/commons/math3/geometry/spherical/twod/Edge.end:Lorg/apache/commons/math3/geometry/spherical/twod/Vertex; (0, 0)
	20 aload_0 (0, 0)
	21 invokevirtual (0, 0)
	22 org/apache/commons/math3/geometry/spherical/twod/Edge.getCircle:()Lorg/apache/commons/math3/geometry/spherical/twod/Circle; (0, 0)
	24 invokevirtual (0, 0)
	25 org/apache/commons/math3/geometry/spherical/twod/Vertex.bindWith:(Lorg/apache/commons/math3/geometry/spherical/twod/Circle;)V (0, 0)
	27 return (0, 1)

