Method: <init>
	0 aload_0 (0, 0)
	1 invokespecial (0, 0)
	2 java/lang/Object.<init>:()V (0, 0)
	4 aload_0 (0, 0)
	5 dload_1 (0, 0)
	6 putfield (0, 0)
	7 org/apache/commons/math3/geometry/spherical/twod/S2Point.theta:D (0, 0)
	9 aload_0 (0, 0)
	10 dload_3 (0, 0)
	11 putfield (0, 0)
	12 org/apache/commons/math3/geometry/spherical/twod/S2Point.phi:D (0, 0)
	14 aload_0 (0, 0)
	15 aload (0, 0)
	16 #5 (0, 0)
	17 putfield (0, 0)
	18 org/apache/commons/math3/geometry/spherical/twod/S2Point.vector:Lorg/apache/commons/math3/geometry/euclidean/threed/Vector3D; (0, 0)
	20 return (0, 0)

Method: vector
	0 dload_2 (1, 1)
	1 dconst_0 (1, 1)
	2 dcmpg (1, 1)
	3 iflt (1, 1)
	4 11 (1, 1)
	6 dload_2 (1, 1)
	7 ldc2_w (1, 1)
	8 3.141592653589793 (1, 1)
	10 dcmpl (1, 1)
	11 ifle (1, 1)
	12 25 (1, 1)
	14 new (1, 1)
	15 org/apache/commons/math3/exception/OutOfRangeException (1, 1)
	17 dup (1, 1)
	18 dload_2 (1, 1)
	19 invokestatic (1, 1)
	20 java/lang/Double.valueOf:(D)Ljava/lang/Double; (1, 1)
	22 iconst_0 (1, 1)
	23 invokestatic (1, 1)
	24 java/lang/Integer.valueOf:(I)Ljava/lang/Integer; (1, 1)
	26 ldc2_w (1, 1)
	27 3.141592653589793 (1, 1)
	29 invokestatic (1, 1)
	30 java/lang/Double.valueOf:(D)Ljava/lang/Double; (1, 1)
	32 invokespecial (1, 1)
	33 org/apache/commons/math3/exception/OutOfRangeException.<init>:(Ljava/lang/Number;Ljava/lang/Number;Ljava/lang/Number;)V (1, 1)
	35 athrow (1, 1)
	36 dload_0 (0, 0)
	37 invokestatic (0, 0)
	38 org/apache/commons/math3/util/FastMath.cos:(D)D (0, 0)
	40 dstore (0, 0)
	41 #4 (0, 0)
	42 dload_0 (0, 0)
	43 invokestatic (0, 0)
	44 org/apache/commons/math3/util/FastMath.sin:(D)D (0, 0)
	46 dstore (0, 0)
	47 #6 (0, 0)
	48 dload_2 (0, 0)
	49 invokestatic (0, 0)
	50 org/apache/commons/math3/util/FastMath.cos:(D)D (0, 0)
	52 dstore (0, 0)
	53 #8 (0, 0)
	54 dload_2 (0, 0)
	55 invokestatic (0, 0)
	56 org/apache/commons/math3/util/FastMath.sin:(D)D (0, 0)
	58 dstore (0, 0)
	59 #10 (0, 0)
	60 new (0, 0)
	61 org/apache/commons/math3/geometry/euclidean/threed/Vector3D (0, 0)
	63 dup (0, 0)
	64 dload (0, 0)
	65 #4 (0, 0)
	66 dload (0, 0)
	67 #10 (0, 0)
	68 dmul (0, 0)
	69 dload (0, 0)
	70 #6 (0, 0)
	71 dload (0, 0)
	72 #10 (0, 0)
	73 dmul (0, 0)
	74 dload (0, 0)
	75 #8 (0, 0)
	76 invokespecial (0, 0)
	77 org/apache/commons/math3/geometry/euclidean/threed/Vector3D.<init>:(DDD)V (0, 0)
	79 areturn (0, 0)

Method: getTheta
	0 aload_0 (0, 0)
	1 getfield (0, 0)
	2 org/apache/commons/math3/geometry/spherical/twod/S2Point.theta:D (0, 0)
	4 dreturn (0, 0)

Method: getPhi
	0 aload_0 (0, 0)
	1 getfield (0, 0)
	2 org/apache/commons/math3/geometry/spherical/twod/S2Point.phi:D (0, 0)
	4 dreturn (0, 0)

Method: getVector
	0 aload_0 (0, 0)
	1 getfield (0, 0)
	2 org/apache/commons/math3/geometry/spherical/twod/S2Point.vector:Lorg/apache/commons/math3/geometry/euclidean/threed/Vector3D; (0, 0)
	4 areturn (0, 0)

Method: getSpace
	0 invokestatic (0, 0)
	1 org/apache/commons/math3/geometry/spherical/twod/Sphere2D.getInstance:()Lorg/apache/commons/math3/geometry/spherical/twod/Sphere2D; (0, 0)
	3 areturn (0, 0)

Method: isNaN
	0 aload_0 (0, 0)
	1 getfield (0, 0)
	2 org/apache/commons/math3/geometry/spherical/twod/S2Point.theta:D (0, 0)
	4 invokestatic (0, 0)
	5 java/lang/Double.isNaN:(D)Z (0, 0)
	7 ifne (0, 0)
	8 13 (0, 0)
	10 aload_0 (0, 0)
	11 getfield (0, 0)
	12 org/apache/commons/math3/geometry/spherical/twod/S2Point.phi:D (0, 0)
	14 invokestatic (0, 0)
	15 java/lang/Double.isNaN:(D)Z (0, 0)
	17 ifeq (0, 0)
	18 7 (0, 0)
	20 iconst_1 (0, 0)
	21 goto (0, 0)
	22 4 (0, 0)
	24 iconst_0 (0, 0)
	25 ireturn (0, 0)

Method: negate
	0 new (0, 0)
	1 org/apache/commons/math3/geometry/spherical/twod/S2Point (0, 0)
	3 dup (0, 0)
	4 aload_0 (0, 0)
	5 getfield (0, 0)
	6 org/apache/commons/math3/geometry/spherical/twod/S2Point.theta:D (0, 0)
	8 dneg (0, 0)
	9 ldc2_w (0, 0)
	10 3.141592653589793 (0, 0)
	12 aload_0 (0, 0)
	13 getfield (0, 0)
	14 org/apache/commons/math3/geometry/spherical/twod/S2Point.phi:D (0, 0)
	16 dsub (0, 0)
	17 aload_0 (0, 0)
	18 getfield (0, 0)
	19 org/apache/commons/math3/geometry/spherical/twod/S2Point.vector:Lorg/apache/commons/math3/geometry/euclidean/threed/Vector3D; (0, 0)
	21 invokevirtual (0, 0)
	22 org/apache/commons/math3/geometry/euclidean/threed/Vector3D.negate:()Lorg/apache/commons/math3/geometry/euclidean/threed/Vector3D; (0, 0)
	24 invokespecial (0, 0)
	25 org/apache/commons/math3/geometry/spherical/twod/S2Point.<init>:(DDLorg/apache/commons/math3/geometry/euclidean/threed/Vector3D;)V (0, 0)
	27 areturn (0, 0)

Method: distance
	0 aload_0 (0, 0)
	1 getfield (0, 0)
	2 org/apache/commons/math3/geometry/spherical/twod/S2Point.vector:Lorg/apache/commons/math3/geometry/euclidean/threed/Vector3D; (0, 0)
	4 aload_1 (0, 0)
	5 getfield (0, 0)
	6 org/apache/commons/math3/geometry/spherical/twod/S2Point.vector:Lorg/apache/commons/math3/geometry/euclidean/threed/Vector3D; (0, 0)
	8 invokestatic (0, 0)
	9 org/apache/commons/math3/geometry/euclidean/threed/Vector3D.angle:(Lorg/apache/commons/math3/geometry/euclidean/threed/Vector3D;Lorg/apache/commons/math3/geometry/euclidean/threed/Vector3D;)D (0, 0)
	11 dreturn (0, 0)

Method: equals
	0 aload_0 (1, 1)
	1 aload_1 (1, 1)
	2 if_acmpne (1, 1)
	3 5 (1, 1)
	5 iconst_1 (1, 1)
	6 ireturn (1, 1)
	7 aload_1 (1, 1)
	8 instanceof (1, 1)
	9 org/apache/commons/math3/geometry/spherical/twod/S2Point (1, 1)
	11 ifeq (1, 1)
	12 50 (1, 1)
	14 aload_1 (1, 1)
	15 checkcast (1, 1)
	16 org/apache/commons/math3/geometry/spherical/twod/S2Point (1, 1)
	18 astore_2 (1, 1)
	19 aload_2 (2, 1)
	20 invokevirtual (2, 1)
	21 org/apache/commons/math3/geometry/spherical/twod/S2Point.isNaN:()Z (2, 1)
	23 ifeq (2, 1)
	24 8 (2, 1)
	26 aload_0 (2, 1)
	27 invokevirtual (2, 1)
	28 org/apache/commons/math3/geometry/spherical/twod/S2Point.isNaN:()Z (2, 1)
	30 ireturn (2, 1)
	31 aload_0 (1, 1)
	32 getfield (1, 1)
	33 org/apache/commons/math3/geometry/spherical/twod/S2Point.theta:D (1, 1)
	35 aload_2 (1, 1)
	36 getfield (1, 1)
	37 org/apache/commons/math3/geometry/spherical/twod/S2Point.theta:D (1, 1)
	39 dcmpl (1, 1)
	40 ifne (1, 1)
	41 19 (1, 1)
	43 aload_0 (1, 1)
	44 getfield (1, 1)
	45 org/apache/commons/math3/geometry/spherical/twod/S2Point.phi:D (1, 1)
	47 aload_2 (1, 1)
	48 getfield (1, 1)
	49 org/apache/commons/math3/geometry/spherical/twod/S2Point.phi:D (1, 1)
	51 dcmpl (1, 1)
	52 ifne (1, 1)
	53 7 (1, 1)
	55 iconst_1 (1, 1)
	56 goto (1, 1)
	57 4 (1, 1)
	59 iconst_0 (1, 1)
	60 ireturn (1, 1)
	61 iconst_0 (0, 0)
	62 ireturn (0, 0)

Method: hashCode
	0 aload_0 (1, 1)
	1 invokevirtual (1, 1)
	2 org/apache/commons/math3/geometry/spherical/twod/S2Point.isNaN:()Z (1, 1)
	4 ifeq (1, 1)
	5 7 (1, 1)
	7 sipush (1, 1)
	8 542 (1, 1)
	10 ireturn (1, 1)
	11 sipush (0, 0)
	12 134 (0, 0)
	14 bipush (0, 0)
	15 37 (0, 0)
	16 aload_0 (0, 0)
	17 getfield (0, 0)
	18 org/apache/commons/math3/geometry/spherical/twod/S2Point.theta:D (0, 0)
	20 invokestatic (0, 0)
	21 org/apache/commons/math3/util/MathUtils.hash:(D)I (0, 0)
	23 imul (0, 0)
	24 aload_0 (0, 0)
	25 getfield (0, 0)
	26 org/apache/commons/math3/geometry/spherical/twod/S2Point.phi:D (0, 0)
	28 invokestatic (0, 0)
	29 org/apache/commons/math3/util/MathUtils.hash:(D)I (0, 0)
	31 iadd (0, 0)
	32 imul (0, 0)
	33 ireturn (0, 0)

Method: <clinit>
	0 new (0, 0)
	1 org/apache/commons/math3/geometry/spherical/twod/S2Point (0, 0)
	3 dup (0, 0)
	4 dconst_0 (0, 0)
	5 ldc2_w (0, 0)
	6 1.5707963267948966 (0, 0)
	8 getstatic (0, 0)
	9 org/apache/commons/math3/geometry/euclidean/threed/Vector3D.PLUS_I:Lorg/apache/commons/math3/geometry/euclidean/threed/Vector3D; (0, 0)
	11 invokespecial (0, 0)
	12 org/apache/commons/math3/geometry/spherical/twod/S2Point.<init>:(DDLorg/apache/commons/math3/geometry/euclidean/threed/Vector3D;)V (0, 0)
	14 putstatic (0, 0)
	15 org/apache/commons/math3/geometry/spherical/twod/S2Point.PLUS_I:Lorg/apache/commons/math3/geometry/spherical/twod/S2Point; (0, 0)
	17 new (0, 0)
	18 org/apache/commons/math3/geometry/spherical/twod/S2Point (0, 0)
	20 dup (0, 0)
	21 ldc2_w (0, 0)
	22 1.5707963267948966 (0, 0)
	24 ldc2_w (0, 0)
	25 1.5707963267948966 (0, 0)
	27 getstatic (0, 0)
	28 org/apache/commons/math3/geometry/euclidean/threed/Vector3D.PLUS_J:Lorg/apache/commons/math3/geometry/euclidean/threed/Vector3D; (0, 0)
	30 invokespecial (0, 0)
	31 org/apache/commons/math3/geometry/spherical/twod/S2Point.<init>:(DDLorg/apache/commons/math3/geometry/euclidean/threed/Vector3D;)V (0, 0)
	33 putstatic (0, 0)
	34 org/apache/commons/math3/geometry/spherical/twod/S2Point.PLUS_J:Lorg/apache/commons/math3/geometry/spherical/twod/S2Point; (0, 0)
	36 new (0, 0)
	37 org/apache/commons/math3/geometry/spherical/twod/S2Point (0, 0)
	39 dup (0, 0)
	40 dconst_0 (0, 0)
	41 dconst_0 (0, 0)
	42 getstatic (0, 0)
	43 org/apache/commons/math3/geometry/euclidean/threed/Vector3D.PLUS_K:Lorg/apache/commons/math3/geometry/euclidean/threed/Vector3D; (0, 0)
	45 invokespecial (0, 0)
	46 org/apache/commons/math3/geometry/spherical/twod/S2Point.<init>:(DDLorg/apache/commons/math3/geometry/euclidean/threed/Vector3D;)V (0, 0)
	48 putstatic (0, 0)
	49 org/apache/commons/math3/geometry/spherical/twod/S2Point.PLUS_K:Lorg/apache/commons/math3/geometry/spherical/twod/S2Point; (0, 0)
	51 new (0, 0)
	52 org/apache/commons/math3/geometry/spherical/twod/S2Point (0, 0)
	54 dup (0, 0)
	55 ldc2_w (0, 0)
	56 3.141592653589793 (0, 0)
	58 ldc2_w (0, 0)
	59 1.5707963267948966 (0, 0)
	61 getstatic (0, 0)
	62 org/apache/commons/math3/geometry/euclidean/threed/Vector3D.MINUS_I:Lorg/apache/commons/math3/geometry/euclidean/threed/Vector3D; (0, 0)
	64 invokespecial (0, 0)
	65 org/apache/commons/math3/geometry/spherical/twod/S2Point.<init>:(DDLorg/apache/commons/math3/geometry/euclidean/threed/Vector3D;)V (0, 0)
	67 putstatic (0, 0)
	68 org/apache/commons/math3/geometry/spherical/twod/S2Point.MINUS_I:Lorg/apache/commons/math3/geometry/spherical/twod/S2Point; (0, 0)
	70 new (0, 0)
	71 org/apache/commons/math3/geometry/spherical/twod/S2Point (0, 0)
	73 dup (0, 0)
	74 ldc2_w (0, 0)
	75 4.71238898038469 (0, 0)
	77 ldc2_w (0, 0)
	78 1.5707963267948966 (0, 0)
	80 getstatic (0, 0)
	81 org/apache/commons/math3/geometry/euclidean/threed/Vector3D.MINUS_J:Lorg/apache/commons/math3/geometry/euclidean/threed/Vector3D; (0, 0)
	83 invokespecial (0, 0)
	84 org/apache/commons/math3/geometry/spherical/twod/S2Point.<init>:(DDLorg/apache/commons/math3/geometry/euclidean/threed/Vector3D;)V (0, 0)
	86 putstatic (0, 0)
	87 org/apache/commons/math3/geometry/spherical/twod/S2Point.MINUS_J:Lorg/apache/commons/math3/geometry/spherical/twod/S2Point; (0, 0)
	89 new (0, 0)
	90 org/apache/commons/math3/geometry/spherical/twod/S2Point (0, 0)
	92 dup (0, 0)
	93 dconst_0 (0, 0)
	94 ldc2_w (0, 0)
	95 3.141592653589793 (0, 0)
	97 getstatic (0, 0)
	98 org/apache/commons/math3/geometry/euclidean/threed/Vector3D.MINUS_K:Lorg/apache/commons/math3/geometry/euclidean/threed/Vector3D; (0, 0)
	100 invokespecial (0, 0)
	101 org/apache/commons/math3/geometry/spherical/twod/S2Point.<init>:(DDLorg/apache/commons/math3/geometry/euclidean/threed/Vector3D;)V (0, 0)
	103 putstatic (0, 0)
	104 org/apache/commons/math3/geometry/spherical/twod/S2Point.MINUS_K:Lorg/apache/commons/math3/geometry/spherical/twod/S2Point; (0, 0)
	106 new (0, 0)
	107 org/apache/commons/math3/geometry/spherical/twod/S2Point (0, 0)
	109 dup (0, 0)
	110 ldc2_w (0, 0)
	111 nan (0, 0)
	113 ldc2_w (0, 0)
	114 nan (0, 0)
	116 getstatic (0, 0)
	117 org/apache/commons/math3/geometry/euclidean/threed/Vector3D.NaN:Lorg/apache/commons/math3/geometry/euclidean/threed/Vector3D; (0, 0)
	119 invokespecial (0, 0)
	120 org/apache/commons/math3/geometry/spherical/twod/S2Point.<init>:(DDLorg/apache/commons/math3/geometry/euclidean/threed/Vector3D;)V (0, 0)
	122 putstatic (0, 0)
	123 org/apache/commons/math3/geometry/spherical/twod/S2Point.NaN:Lorg/apache/commons/math3/geometry/spherical/twod/S2Point; (0, 0)
	125 return (0, 0)

