Method: <init>
	0 aload_0 (0, 0)
	1 invokespecial (0, 0)
	4 aload_0 (0, 0)
	5 dload_1 (0, 0)
	6 putfield (0, 0)
	9 aload_0 (0, 0)
	10 dload_3 (0, 0)
	11 putfield (0, 0)
	14 aload_0 (0, 0)
	15 aload (0, 0)
	17 putfield (0, 0)
	20 return (0, 0)

Method: vector
	0 dload_2 (1, 1)
	1 dconst_0 (1, 1)
	2 dcmpg (1, 1)
	3 iflt (1, 1)
	6 dload_2 (1, 1)
	7 ldc2_w (1, 1)
	10 dcmpl (1, 1)
	11 ifle (1, 1)
	14 new (1, 1)
	17 dup (1, 1)
	18 dload_2 (1, 1)
	19 invokestatic (1, 1)
	22 iconst_0 (1, 1)
	23 invokestatic (1, 1)
	26 ldc2_w (1, 1)
	29 invokestatic (1, 1)
	32 invokespecial (1, 1)
	35 athrow (1, 1)
	36 dload_0 (0, 0)
	37 invokestatic (0, 0)
	40 dstore (0, 0)
	42 dload_0 (0, 0)
	43 invokestatic (0, 0)
	46 dstore (0, 0)
	48 dload_2 (0, 0)
	49 invokestatic (0, 0)
	52 dstore (0, 0)
	54 dload_2 (0, 0)
	55 invokestatic (0, 0)
	58 dstore (0, 0)
	60 new (0, 0)
	63 dup (0, 0)
	64 dload (0, 0)
	66 dload (0, 0)
	68 dmul (0, 0)
	69 dload (0, 0)
	71 dload (0, 0)
	73 dmul (0, 0)
	74 dload (0, 0)
	76 invokespecial (0, 0)
	79 areturn (0, 0)

Method: getTheta
	0 aload_0 (0, 0)
	1 getfield (0, 0)
	4 dreturn (0, 0)

Method: getPhi
	0 aload_0 (0, 0)
	1 getfield (0, 0)
	4 dreturn (0, 0)

Method: getVector
	0 aload_0 (0, 0)
	1 getfield (0, 0)
	4 areturn (0, 0)

Method: getSpace
	0 invokestatic (0, 0)
	3 areturn (0, 0)

Method: isNaN
	0 aload_0 (0, 0)
	1 getfield (0, 0)
	4 invokestatic (0, 0)
	7 ifne (0, 0)
	10 aload_0 (0, 0)
	11 getfield (0, 0)
	14 invokestatic (0, 0)
	17 ifeq (0, 0)
	20 iconst_1 (0, 0)
	21 goto (0, 0)
	24 iconst_0 (0, 0)
	25 ireturn (0, 0)

Method: negate
	0 new (0, 0)
	3 dup (0, 0)
	4 aload_0 (0, 0)
	5 getfield (0, 0)
	8 dneg (0, 0)
	9 ldc2_w (0, 0)
	12 aload_0 (0, 0)
	13 getfield (0, 0)
	16 dsub (0, 0)
	17 aload_0 (0, 0)
	18 getfield (0, 0)
	21 invokevirtual (0, 0)
	24 invokespecial (0, 0)
	27 areturn (0, 0)

Method: distance
	0 aload_0 (0, 0)
	1 getfield (0, 0)
	4 aload_1 (0, 0)
	5 getfield (0, 0)
	8 invokestatic (0, 0)
	11 dreturn (0, 0)

Method: equals
	0 aload_0 (1, 1)
	1 aload_1 (1, 1)
	2 if_acmpne (1, 1)
	5 iconst_1 (1, 1)
	6 ireturn (1, 1)
	7 aload_1 (1, 1)
	8 instanceof (1, 1)
	11 ifeq (1, 1)
	14 aload_1 (1, 1)
	15 checkcast (1, 1)
	18 astore_2 (1, 1)
	19 aload_2 (2, 1)
	20 invokevirtual (2, 1)
	23 ifeq (2, 1)
	26 aload_0 (2, 1)
	27 invokevirtual (2, 1)
	30 ireturn (2, 1)
	31 aload_0 (1, 1)
	32 getfield (1, 1)
	35 aload_2 (1, 1)
	36 getfield (1, 1)
	39 dcmpl (1, 1)
	40 ifne (1, 1)
	43 aload_0 (1, 1)
	44 getfield (1, 1)
	47 aload_2 (1, 1)
	48 getfield (1, 1)
	51 dcmpl (1, 1)
	52 ifne (1, 1)
	55 iconst_1 (1, 1)
	56 goto (1, 1)
	59 iconst_0 (1, 1)
	60 ireturn (1, 1)
	61 iconst_0 (0, 0)
	62 ireturn (0, 0)

Method: hashCode
	0 aload_0 (1, 1)
	1 invokevirtual (1, 1)
	4 ifeq (1, 1)
	7 sipush (1, 1)
	10 ireturn (1, 1)
	11 sipush (0, 0)
	14 bipush (0, 0)
	16 aload_0 (0, 0)
	17 getfield (0, 0)
	20 invokestatic (0, 0)
	23 imul (0, 0)
	24 aload_0 (0, 0)
	25 getfield (0, 0)
	28 invokestatic (0, 0)
	31 iadd (0, 0)
	32 imul (0, 0)
	33 ireturn (0, 0)

Method: <clinit>
	0 new (0, 0)
	3 dup (0, 0)
	4 dconst_0 (0, 0)
	5 ldc2_w (0, 0)
	8 getstatic (0, 0)
	11 invokespecial (0, 0)
	14 putstatic (0, 0)
	17 new (0, 0)
	20 dup (0, 0)
	21 ldc2_w (0, 0)
	24 ldc2_w (0, 0)
	27 getstatic (0, 0)
	30 invokespecial (0, 0)
	33 putstatic (0, 0)
	36 new (0, 0)
	39 dup (0, 0)
	40 dconst_0 (0, 0)
	41 dconst_0 (0, 0)
	42 getstatic (0, 0)
	45 invokespecial (0, 0)
	48 putstatic (0, 0)
	51 new (0, 0)
	54 dup (0, 0)
	55 ldc2_w (0, 0)
	58 ldc2_w (0, 0)
	61 getstatic (0, 0)
	64 invokespecial (0, 0)
	67 putstatic (0, 0)
	70 new (0, 0)
	73 dup (0, 0)
	74 ldc2_w (0, 0)
	77 ldc2_w (0, 0)
	80 getstatic (0, 0)
	83 invokespecial (0, 0)
	86 putstatic (0, 0)
	89 new (0, 0)
	92 dup (0, 0)
	93 dconst_0 (0, 0)
	94 ldc2_w (0, 0)
	97 getstatic (0, 0)
	100 invokespecial (0, 0)
	103 putstatic (0, 0)
	106 new (0, 0)
	109 dup (0, 0)
	110 ldc2_w (0, 0)
	113 ldc2_w (0, 0)
	116 getstatic (0, 0)
	119 invokespecial (0, 0)
	122 putstatic (0, 0)
	125 return (0, 0)

