Method: <init>
	0 aload_0 (0, 0)
	1 invokespecial (0, 0)
	2 java/lang/Object.<init>:()V (0, 0)
	4 return (0, 0)

Method: getInstance
	0 invokestatic (0, 0)
	1 org/apache/commons/math3/geometry/spherical/twod/Sphere2D$LazyHolder.access$000:()Lorg/apache/commons/math3/geometry/spherical/twod/Sphere2D; (0, 0)
	3 areturn (0, 0)

Method: getDimension
	0 iconst_2 (0, 0)
	1 ireturn (0, 0)

Method: getSubSpace
	0 aload_0 (0, 0)
	1 invokevirtual (0, 0)
	2 org/apache/commons/math3/geometry/spherical/twod/Sphere2D.getSubSpace:()Lorg/apache/commons/math3/geometry/spherical/oned/Sphere1D; (0, 0)
	4 areturn (0, 0)

Method: readResolve
	0 invokestatic (0, 0)
	1 org/apache/commons/math3/geometry/spherical/twod/Sphere2D$LazyHolder.access$000:()Lorg/apache/commons/math3/geometry/spherical/twod/Sphere2D; (0, 0)
	3 areturn (0, 0)

