Method: <init>
	0 aload_0 (0, 0)
	1 invokespecial (0, 0)
	2 java/lang/Object.<init>:()V (0, 0)
	4 aload_0 (0, 0)
	5 new (0, 0)
	6 org/apache/commons/math3/random/RandomDataImpl (0, 0)
	8 dup (0, 0)
	9 invokespecial (0, 0)
	10 org/apache/commons/math3/random/RandomDataImpl.<init>:()V (0, 0)
	12 putfield (0, 0)
	13 org/apache/commons/math3/distribution/AbstractRealDistribution.randomData:Lorg/apache/commons/math3/random/RandomDataImpl; (0, 0)
	15 aload_0 (1, 4)
	16 ldc2_w (1, 4)
	17 1e-06 (1, 4)
	19 putfield (1, 4)
	20 org/apache/commons/math3/distribution/AbstractRealDistribution.solverAbsoluteAccuracy:D (1, 4)
	22 aload_0 (1, 4)
	23 aload_1 (1, 4)
	24 putfield (1, 4)
	25 org/apache/commons/math3/distribution/AbstractRealDistribution.random:Lorg/apache/commons/math3/random/RandomGenerator; (1, 4)
	27 return (1, 4)

Method: cumulativeProbability
	0 aload_0 (0, 0)
	1 dload_1 (0, 0)
	2 dload_3 (0, 0)
	3 invokevirtual (0, 0)
	4 org/apache/commons/math3/distribution/AbstractRealDistribution.probability:(DD)D (0, 0)
	6 dreturn (0, 0)

Method: probability
	0 dconst_0 (0, 0)
	1 dreturn (0, 0)

Method: inverseCumulativeProbability
	0 dload_1 (1, 1)
	1 dconst_0 (1, 1)
	2 dcmpg (1, 1)
	3 iflt (1, 1)
	4 9 (1, 1)
	6 dload_1 (1, 1)
	7 dconst_1 (1, 1)
	8 dcmpl (1, 1)
	9 ifle (1, 1)
	10 23 (1, 1)
	12 new (1, 1)
	13 org/apache/commons/math3/exception/OutOfRangeException (1, 1)
	15 dup (1, 1)
	16 dload_1 (1, 1)
	17 invokestatic (1, 1)
	18 java/lang/Double.valueOf:(D)Ljava/lang/Double; (1, 1)
	20 iconst_0 (1, 1)
	21 invokestatic (1, 1)
	22 java/lang/Integer.valueOf:(I)Ljava/lang/Integer; (1, 1)
	24 iconst_1 (1, 1)
	25 invokestatic (1, 1)
	26 java/lang/Integer.valueOf:(I)Ljava/lang/Integer; (1, 1)
	28 invokespecial (1, 1)
	29 org/apache/commons/math3/exception/OutOfRangeException.<init>:(Ljava/lang/Number;Ljava/lang/Number;Ljava/lang/Number;)V (1, 1)
	31 athrow (1, 1)
	32 aload_0 (0, 0)
	33 invokevirtual (0, 0)
	34 org/apache/commons/math3/distribution/AbstractRealDistribution.getSupportLowerBound:()D (0, 0)
	36 dstore_3 (0, 0)
	37 dload_1 (1, 1)
	38 dconst_0 (1, 1)
	39 dcmpl (1, 1)
	40 ifne (1, 1)
	41 5 (1, 1)
	43 dload_3 (1, 1)
	44 dreturn (1, 1)
	45 aload_0 (0, 0)
	46 invokevirtual (0, 0)
	47 org/apache/commons/math3/distribution/AbstractRealDistribution.getSupportUpperBound:()D (0, 0)
	49 dstore (0, 0)
	50 #5 (0, 0)
	51 dload_1 (1, 1)
	52 dconst_1 (1, 1)
	53 dcmpl (1, 1)
	54 ifne (1, 1)
	55 6 (1, 1)
	57 dload (1, 1)
	58 #5 (1, 1)
	59 dreturn (1, 1)
	60 aload_0 (0, 0)
	61 invokevirtual (0, 0)
	62 org/apache/commons/math3/distribution/AbstractRealDistribution.getNumericalMean:()D (0, 0)
	64 dstore (0, 0)
	65 #7 (0, 0)
	66 aload_0 (0, 0)
	67 invokevirtual (0, 0)
	68 org/apache/commons/math3/distribution/AbstractRealDistribution.getNumericalVariance:()D (0, 0)
	70 invokestatic (0, 0)
	71 org/apache/commons/math3/util/FastMath.sqrt:(D)D (0, 0)
	73 dstore (0, 0)
	74 #9 (0, 0)
	75 dload (0, 0)
	76 #7 (0, 0)
	77 invokestatic (0, 0)
	78 java/lang/Double.isInfinite:(D)Z (0, 0)
	80 ifne (0, 0)
	81 31 (0, 0)
	83 dload (0, 0)
	84 #7 (0, 0)
	85 invokestatic (0, 0)
	86 java/lang/Double.isNaN:(D)Z (0, 0)
	88 ifne (0, 0)
	89 23 (0, 0)
	91 dload (0, 0)
	92 #9 (0, 0)
	93 invokestatic (0, 0)
	94 java/lang/Double.isInfinite:(D)Z (0, 0)
	96 ifne (0, 0)
	97 15 (0, 0)
	99 dload (0, 0)
	100 #9 (0, 0)
	101 invokestatic (0, 0)
	102 java/lang/Double.isNaN:(D)Z (0, 0)
	104 ifne (0, 0)
	105 7 (0, 0)
	107 iconst_1 (0, 0)
	108 goto (0, 0)
	109 4 (0, 0)
	111 iconst_0 (0, 0)
	112 istore (0, 0)
	113 #11 (0, 0)
	114 dload_3 (1, 1)
	115 ldc2_w (1, 1)
	116 -inf (1, 1)
	118 dcmpl (1, 1)
	119 ifne (1, 1)
	120 49 (1, 1)
	122 iload (2, 1)
	123 #11 (2, 1)
	124 ifeq (2, 1)
	125 21 (2, 1)
	127 dload (2, 1)
	128 #7 (2, 1)
	129 dload (2, 1)
	130 #9 (2, 1)
	131 dconst_1 (2, 1)
	132 dload_1 (2, 1)
	133 dsub (2, 1)
	134 dload_1 (2, 1)
	135 ddiv (2, 1)
	136 invokestatic (2, 1)
	137 org/apache/commons/math3/util/FastMath.sqrt:(D)D (2, 1)
	139 dmul (2, 1)
	140 dsub (2, 1)
	141 dstore_3 (2, 1)
	142 goto (2, 1)
	143 26 (2, 1)
	145 ldc2_w (3, 2)
	146 -1.0 (3, 2)
	148 dstore_3 (3, 2)
	149 aload_0 (4, 3)
	150 dload_3 (4, 3)
	151 invokevirtual (4, 3)
	152 org/apache/commons/math3/distribution/AbstractRealDistribution.cumulativeProbability:(D)D (4, 3)
	154 dload_1 (4, 3)
	155 dcmpl (4, 3)
	156 iflt (4, 3)
	157 12 (4, 3)
	159 dload_3 (4, 3)
	160 ldc2_w (4, 3)
	161 2.0 (4, 3)
	163 dmul (4, 3)
	164 dstore_3 (4, 3)
	165 goto (4, 3)
	166 -16 (4, 3)
	168 dload (1, 1)
	169 #5 (1, 1)
	170 ldc2_w (1, 1)
	171 inf (1, 1)
	173 dcmpl (1, 1)
	174 ifne (1, 1)
	175 52 (1, 1)
	177 iload (2, 1)
	178 #11 (2, 1)
	179 ifeq (2, 1)
	180 22 (2, 1)
	182 dload (2, 1)
	183 #7 (2, 1)
	184 dload (2, 1)
	185 #9 (2, 1)
	186 dload_1 (2, 1)
	187 dconst_1 (2, 1)
	188 dload_1 (2, 1)
	189 dsub (2, 1)
	190 ddiv (2, 1)
	191 invokestatic (2, 1)
	192 org/apache/commons/math3/util/FastMath.sqrt:(D)D (2, 1)
	194 dmul (2, 1)
	195 dadd (2, 1)
	196 dstore (2, 1)
	197 #5 (2, 1)
	198 goto (2, 1)
	199 28 (2, 1)
	201 dconst_1 (3, 2)
	202 dstore (3, 2)
	203 #5 (3, 2)
	204 aload_0 (4, 3)
	205 dload (4, 3)
	206 #5 (4, 3)
	207 invokevirtual (4, 3)
	208 org/apache/commons/math3/distribution/AbstractRealDistribution.cumulativeProbability:(D)D (4, 3)
	210 dload_1 (4, 3)
	211 dcmpg (4, 3)
	212 ifge (4, 3)
	213 14 (4, 3)
	215 dload (4, 3)
	216 #5 (4, 3)
	217 ldc2_w (4, 3)
	218 2.0 (4, 3)
	220 dmul (4, 3)
	221 dstore (4, 3)
	222 #5 (4, 3)
	223 goto (4, 3)
	224 -19 (4, 3)
	226 new (0, 0)
	227 org/apache/commons/math3/distribution/AbstractRealDistribution$1 (0, 0)
	229 dup (0, 0)
	230 aload_0 (0, 0)
	231 dload_1 (0, 0)
	232 invokespecial (0, 0)
	233 org/apache/commons/math3/distribution/AbstractRealDistribution$1.<init>:(Lorg/apache/commons/math3/distribution/AbstractRealDistribution;D)V (0, 0)
	235 astore (0, 0)
	236 #12 (0, 0)
	237 aload (0, 0)
	238 #12 (0, 0)
	239 dload_3 (0, 0)
	240 dload (0, 0)
	241 #5 (0, 0)
	242 aload_0 (0, 0)
	243 invokevirtual (0, 0)
	244 org/apache/commons/math3/distribution/AbstractRealDistribution.getSolverAbsoluteAccuracy:()D (0, 0)
	246 invokestatic (0, 0)
	247 org/apache/commons/math3/analysis/solvers/UnivariateSolverUtils.solve:(Lorg/apache/commons/math3/analysis/UnivariateFunction;DDD)D (0, 0)
	249 dstore (0, 0)
	250 #13 (0, 0)
	251 aload_0 (1, 1)
	252 invokevirtual (1, 1)
	253 org/apache/commons/math3/distribution/AbstractRealDistribution.isSupportConnected:()Z (1, 1)
	255 ifne (1, 1)
	256 97 (1, 1)
	258 aload_0 (2, 4)
	259 invokevirtual (2, 4)
	260 org/apache/commons/math3/distribution/AbstractRealDistribution.getSolverAbsoluteAccuracy:()D (2, 4)
	262 dstore (2, 4)
	263 #15 (2, 4)
	264 dload (3, 1)
	265 #13 (3, 1)
	266 dload (3, 1)
	267 #15 (3, 1)
	268 dsub (3, 1)
	269 aload_0 (3, 1)
	270 invokevirtual (3, 1)
	271 org/apache/commons/math3/distribution/AbstractRealDistribution.getSupportLowerBound:()D (3, 1)
	273 dcmpl (3, 1)
	274 iflt (3, 1)
	275 78 (3, 1)
	277 aload_0 (3, 1)
	278 dload (3, 1)
	279 #13 (3, 1)
	280 invokevirtual (3, 1)
	281 org/apache/commons/math3/distribution/AbstractRealDistribution.cumulativeProbability:(D)D (3, 1)
	283 dstore (3, 1)
	284 #17 (3, 1)
	285 aload_0 (4, 1)
	286 dload (4, 1)
	287 #13 (4, 1)
	288 dload (4, 1)
	289 #15 (4, 1)
	290 dsub (4, 1)
	291 invokevirtual (4, 1)
	292 org/apache/commons/math3/distribution/AbstractRealDistribution.cumulativeProbability:(D)D (4, 1)
	294 dload (4, 1)
	295 #17 (4, 1)
	296 dcmpl (4, 1)
	297 ifne (4, 1)
	298 55 (4, 1)
	300 dload (4, 1)
	301 #13 (4, 1)
	302 dstore (4, 1)
	303 #5 (4, 1)
	304 dload (5, 3)
	305 #5 (5, 3)
	306 dload_3 (5, 3)
	307 dsub (5, 3)
	308 dload (5, 3)
	309 #15 (5, 3)
	310 dcmpl (5, 3)
	311 ifle (5, 3)
	312 38 (5, 3)
	314 ldc2_w (5, 3)
	315 0.5 (5, 3)
	317 dload_3 (5, 3)
	318 dload (5, 3)
	319 #5 (5, 3)
	320 dadd (5, 3)
	321 dmul (5, 3)
	322 dstore (5, 3)
	323 #19 (5, 3)
	324 aload_0 (6, 1)
	325 dload (6, 1)
	326 #19 (6, 1)
	327 invokevirtual (6, 1)
	328 org/apache/commons/math3/distribution/AbstractRealDistribution.cumulativeProbability:(D)D (6, 1)
	330 dload (6, 1)
	331 #17 (6, 1)
	332 dcmpg (6, 1)
	333 ifge (6, 1)
	334 9 (6, 1)
	336 dload (6, 1)
	337 #19 (6, 1)
	338 dstore_3 (6, 1)
	339 goto (6, 1)
	340 7 (6, 1)
	342 dload (7, 2)
	343 #19 (7, 2)
	344 dstore (7, 2)
	345 #5 (7, 2)
	346 goto (4, 1)
	347 -42 (4, 1)
	349 dload (4, 1)
	350 #5 (4, 1)
	351 dreturn (4, 1)
	352 dload (0, 0)
	353 #13 (0, 0)
	354 dreturn (0, 0)

Method: getSolverAbsoluteAccuracy
	0 aload_0 (0, 0)
	1 getfield (0, 0)
	2 org/apache/commons/math3/distribution/AbstractRealDistribution.solverAbsoluteAccuracy:D (0, 0)
	4 dreturn (0, 0)

Method: reseedRandomGenerator
	0 aload_0 (0, 0)
	1 getfield (0, 0)
	2 org/apache/commons/math3/distribution/AbstractRealDistribution.random:Lorg/apache/commons/math3/random/RandomGenerator; (0, 0)
	4 lload_1 (0, 0)
	5 invokeinterface (0, 0)
	6 org/apache/commons/math3/random/RandomGenerator.reSeed:(J)V (0, 0)
	8 0 (0, 0)
	10 aload_0 (0, 0)
	11 getfield (0, 0)
	12 org/apache/commons/math3/distribution/AbstractRealDistribution.randomData:Lorg/apache/commons/math3/random/RandomDataImpl; (0, 0)
	14 lload_1 (0, 0)
	15 invokevirtual (0, 0)
	16 org/apache/commons/math3/random/RandomDataImpl.reSeed:(J)V (0, 0)
	18 return (0, 0)

Method: sample
	0 iload_1 (1, 1)
	1 ifgt (1, 1)
	2 18 (1, 1)
	4 new (1, 1)
	5 org/apache/commons/math3/exception/NotStrictlyPositiveException (1, 1)
	7 dup (1, 1)
	8 getstatic (1, 1)
	9 org/apache/commons/math3/exception/util/LocalizedFormats.NUMBER_OF_SAMPLES:Lorg/apache/commons/math3/exception/util/LocalizedFormats; (1, 1)
	11 iload_1 (1, 1)
	12 invokestatic (1, 1)
	13 java/lang/Integer.valueOf:(I)Ljava/lang/Integer; (1, 1)
	15 invokespecial (1, 1)
	16 org/apache/commons/math3/exception/NotStrictlyPositiveException.<init>:(Lorg/apache/commons/math3/exception/util/Localizable;Ljava/lang/Number;)V (1, 1)
	18 athrow (1, 1)
	19 iload_1 (0, 0)
	20 newarray (0, 0)
	21 7 (0, 0)
	22 astore_2 (0, 0)
	23 iconst_0 (1, 4)
	24 istore_3 (1, 4)
	25 iload_3 (1, 4)
	26 iload_1 (1, 4)
	27 if_icmpge (1, 4)
	28 16 (1, 4)
	30 aload_2 (1, 4)
	31 iload_3 (1, 4)
	32 aload_0 (1, 4)
	33 invokevirtual (1, 4)
	34 org/apache/commons/math3/distribution/AbstractRealDistribution.sample:()D (1, 4)
	36 dastore (1, 4)
	37 iinc (1, 4)
	38 #3 (1, 4)
	39 -89 (1, 4)
	40 goto (1, 4)
	41 -15 (1, 4)
	43 aload_2 (0, 0)
	44 areturn (0, 0)

Method: logDensity
	0 aload_0 (0, 0)
	1 dload_1 (0, 0)
	2 invokevirtual (0, 0)
	3 org/apache/commons/math3/distribution/AbstractRealDistribution.density:(D)D (0, 0)
	5 invokestatic (0, 0)
	6 org/apache/commons/math3/util/FastMath.log:(D)D (0, 0)
	8 dreturn (0, 0)

