Method: sample
	0 dload_1 (0, 0)
	1 dload_3 (0, 0)
	2 invokestatic (0, 0)
	3 org/apache/commons/math3/util/FastMath.min:(DD)D (0, 0)
	5 dstore (0, 0)
	6 #5 (0, 0)
	7 dload_1 (0, 0)
	8 dload_3 (0, 0)
	9 invokestatic (0, 0)
	10 org/apache/commons/math3/util/FastMath.max:(DD)D (0, 0)
	12 dstore (0, 0)
	13 #7 (0, 0)
	14 dload (1, 1)
	15 #5 (1, 1)
	16 dconst_1 (1, 1)
	17 dcmpl (1, 1)
	18 ifle (1, 1)
	19 13 (1, 1)
	21 aload_0 (1, 1)
	22 dload_1 (1, 1)
	23 dload (1, 1)
	24 #5 (1, 1)
	25 dload (1, 1)
	26 #7 (1, 1)
	27 invokestatic (1, 1)
	28 org/apache/commons/math3/distribution/BetaDistribution$ChengBetaSampler.algorithmBB:(Lorg/apache/commons/math3/random/RandomGenerator;DDD)D (1, 1)
	30 dreturn (1, 1)
	31 aload_0 (1, 2)
	32 dload_1 (1, 2)
	33 dload (1, 2)
	34 #7 (1, 2)
	35 dload (1, 2)
	36 #5 (1, 2)
	37 invokestatic (1, 2)
	38 org/apache/commons/math3/distribution/BetaDistribution$ChengBetaSampler.algorithmBC:(Lorg/apache/commons/math3/random/RandomGenerator;DDD)D (1, 2)
	40 dreturn (1, 2)

Method: algorithmBB
	0 dload_3 (0, 0)
	1 dload (0, 0)
	2 #5 (0, 0)
	3 dadd (0, 0)
	4 dstore (0, 0)
	5 #7 (0, 0)
	6 dload (0, 0)
	7 #7 (0, 0)
	8 ldc2_w (0, 0)
	9 2.0 (0, 0)
	11 dsub (0, 0)
	12 ldc2_w (0, 0)
	13 2.0 (0, 0)
	15 dload_3 (0, 0)
	16 dmul (0, 0)
	17 dload (0, 0)
	18 #5 (0, 0)
	19 dmul (0, 0)
	20 dload (0, 0)
	21 #7 (0, 0)
	22 dsub (0, 0)
	23 ddiv (0, 0)
	24 invokestatic (0, 0)
	25 org/apache/commons/math3/util/FastMath.sqrt:(D)D (0, 0)
	27 dstore (0, 0)
	28 #9 (0, 0)
	29 dload_3 (0, 0)
	30 dconst_1 (0, 0)
	31 dload (0, 0)
	32 #9 (0, 0)
	33 ddiv (0, 0)
	34 dadd (0, 0)
	35 dstore (0, 0)
	36 #11 (0, 0)
	37 aload_0 (0, 0)
	38 invokeinterface (0, 0)
	39 org/apache/commons/math3/random/RandomGenerator.log:(D)D (0, 0)
	41 0 (0, 0)
	43 dstore (0, 0)
	44 #19 (0, 0)
	45 aload_0 (0, 0)
	46 invokeinterface (0, 0)
	47 org/apache/commons/math3/random/RandomGenerator.log:(D)D (0, 0)
	49 0 (0, 0)
	51 dstore (0, 0)
	52 #21 (0, 0)
	53 dload (0, 0)
	54 #9 (0, 0)
	55 dload (0, 0)
	56 #19 (0, 0)
	57 invokestatic (0, 0)
	58 org/apache/commons/math3/util/FastMath.log:(D)D (0, 0)
	60 dload (0, 0)
	61 #19 (0, 0)
	62 dneg (0, 0)
	63 invokestatic (0, 0)
	64 org/apache/commons/math3/util/FastMath.log1p:(D)D (0, 0)
	66 dsub (0, 0)
	67 dmul (0, 0)
	68 dstore (0, 0)
	69 #23 (0, 0)
	70 dload_3 (0, 0)
	71 dload (0, 0)
	72 #23 (0, 0)
	73 invokestatic (0, 0)
	74 org/apache/commons/math3/util/FastMath.exp:(D)D (0, 0)
	76 dmul (0, 0)
	77 dstore (0, 0)
	78 #15 (0, 0)
	79 dload (0, 0)
	80 #19 (0, 0)
	81 dload (0, 0)
	82 #19 (0, 0)
	83 dmul (0, 0)
	84 dload (0, 0)
	85 #21 (0, 0)
	86 dmul (0, 0)
	87 dstore (0, 0)
	88 #25 (0, 0)
	89 dload (0, 0)
	90 #11 (0, 0)
	91 dload (0, 0)
	92 #23 (0, 0)
	93 dmul (0, 0)
	94 ldc2_w (0, 0)
	95 1.3862944 (0, 0)
	97 dsub (0, 0)
	98 dstore (0, 0)
	99 #13 (0, 0)
	100 dload_3 (0, 0)
	101 dload (0, 0)
	102 #13 (0, 0)
	103 dadd (0, 0)
	104 dload (0, 0)
	105 #15 (0, 0)
	106 dsub (0, 0)
	107 dstore (0, 0)
	108 #27 (0, 0)
	109 dload (2, 1)
	110 #27 (2, 1)
	111 ldc2_w (2, 1)
	112 2.609438 (2, 1)
	114 dadd (2, 1)
	115 ldc2_w (2, 1)
	116 5.0 (2, 1)
	118 dload (2, 1)
	119 #25 (2, 1)
	120 dmul (2, 1)
	121 dcmpl (2, 1)
	122 iflt (2, 1)
	123 6 (2, 1)
	125 goto (2, 1)
	126 47 (2, 1)
	128 dload (0, 0)
	129 #25 (0, 0)
	130 invokestatic (0, 0)
	131 org/apache/commons/math3/util/FastMath.log:(D)D (0, 0)
	133 dstore (0, 0)
	134 #17 (0, 0)
	135 dload (2, 1)
	136 #27 (2, 1)
	137 dload (2, 1)
	138 #17 (2, 1)
	139 dcmpl (2, 1)
	140 iflt (2, 1)
	141 6 (2, 1)
	143 goto (2, 1)
	144 29 (2, 1)
	146 dload (0, 3)
	147 #13 (0, 3)
	148 dload (0, 3)
	149 #7 (0, 3)
	150 dload (0, 3)
	151 #7 (0, 3)
	152 invokestatic (0, 3)
	153 org/apache/commons/math3/util/FastMath.log:(D)D (0, 3)
	155 dload (0, 3)
	156 #5 (0, 3)
	157 dload (0, 3)
	158 #15 (0, 3)
	159 dadd (0, 3)
	160 invokestatic (0, 3)
	161 org/apache/commons/math3/util/FastMath.log:(D)D (0, 3)
	163 dsub (0, 3)
	164 dmul (0, 3)
	165 dadd (0, 3)
	166 dload (0, 3)
	167 #17 (0, 3)
	168 dcmpg (0, 3)
	169 iflt (0, 3)
	170 -132 (0, 3)
	172 dload (0, 3)
	173 #15 (0, 3)
	174 ldc2_w (0, 3)
	175 1.7976931348623157e+308 (0, 3)
	177 invokestatic (0, 3)
	178 org/apache/commons/math3/util/FastMath.min:(DD)D (0, 3)
	180 dstore (0, 3)
	181 #15 (0, 3)
	182 dload_3 (0, 3)
	183 dload_1 (0, 3)
	184 invokestatic (0, 3)
	185 org/apache/commons/math3/util/Precision.equals:(DD)Z (0, 3)
	187 ifeq (0, 3)
	188 14 (0, 3)
	190 dload (0, 3)
	191 #15 (0, 3)
	192 dload (0, 3)
	193 #5 (0, 3)
	194 dload (0, 3)
	195 #15 (0, 3)
	196 dadd (0, 3)
	197 ddiv (0, 3)
	198 goto (0, 3)
	199 11 (0, 3)
	201 dload (0, 3)
	202 #5 (0, 3)
	203 dload (0, 3)
	204 #5 (0, 3)
	205 dload (0, 3)
	206 #15 (0, 3)
	207 dadd (0, 3)
	208 ddiv (0, 3)
	209 dreturn (0, 3)

Method: algorithmBC
	0 dload_3 (0, 0)
	1 dload (0, 0)
	2 #5 (0, 0)
	3 dadd (0, 0)
	4 dstore (0, 0)
	5 #7 (0, 0)
	6 dconst_1 (0, 0)
	7 dload (0, 0)
	8 #5 (0, 0)
	9 ddiv (0, 0)
	10 dstore (0, 0)
	11 #9 (0, 0)
	12 dconst_1 (0, 0)
	13 dload_3 (0, 0)
	14 dadd (0, 0)
	15 dload (0, 0)
	16 #5 (0, 0)
	17 dsub (0, 0)
	18 dstore (0, 0)
	19 #11 (0, 0)
	20 dload (0, 0)
	21 #11 (0, 0)
	22 ldc2_w (0, 0)
	23 0.0138889 (0, 0)
	25 ldc2_w (0, 0)
	26 0.0416667 (0, 0)
	28 dload (0, 0)
	29 #5 (0, 0)
	30 dmul (0, 0)
	31 dadd (0, 0)
	32 dmul (0, 0)
	33 dload_3 (0, 0)
	34 dload (0, 0)
	35 #9 (0, 0)
	36 dmul (0, 0)
	37 ldc2_w (0, 0)
	38 0.777778 (0, 0)
	40 dsub (0, 0)
	41 ddiv (0, 0)
	42 dstore (0, 0)
	43 #13 (0, 0)
	44 ldc2_w (0, 0)
	45 0.25 (0, 0)
	47 ldc2_w (0, 0)
	48 0.5 (0, 0)
	50 ldc2_w (0, 0)
	51 0.25 (0, 0)
	53 dload (0, 0)
	54 #11 (0, 0)
	55 ddiv (0, 0)
	56 dadd (0, 0)
	57 dload (0, 0)
	58 #5 (0, 0)
	59 dmul (0, 0)
	60 dadd (0, 0)
	61 dstore (0, 0)
	62 #15 (0, 0)
	63 aload_0 (1, 4)
	64 invokeinterface (1, 4)
	65 org/apache/commons/math3/random/RandomGenerator.log:(D)D (1, 4)
	67 0 (1, 4)
	69 dstore (1, 4)
	70 #19 (1, 4)
	71 aload_0 (1, 4)
	72 invokeinterface (1, 4)
	73 org/apache/commons/math3/random/RandomGenerator.log:(D)D (1, 4)
	75 0 (1, 4)
	77 dstore (1, 4)
	78 #21 (1, 4)
	79 dload (1, 4)
	80 #19 (1, 4)
	81 dload (1, 4)
	82 #21 (1, 4)
	83 dmul (1, 4)
	84 dstore (1, 4)
	85 #23 (1, 4)
	86 dload (1, 4)
	87 #19 (1, 4)
	88 dload (1, 4)
	89 #23 (1, 4)
	90 dmul (1, 4)
	91 dstore (1, 4)
	92 #25 (1, 4)
	93 dload (2, 1)
	94 #19 (2, 1)
	95 ldc2_w (2, 1)
	96 0.5 (2, 1)
	98 dcmpg (2, 1)
	99 ifge (2, 1)
	100 24 (2, 1)
	102 ldc2_w (3, 1)
	103 0.25 (3, 1)
	105 dload (3, 1)
	106 #21 (3, 1)
	107 dmul (3, 1)
	108 dload (3, 1)
	109 #25 (3, 1)
	110 dadd (3, 1)
	111 dload (3, 1)
	112 #23 (3, 1)
	113 dsub (3, 1)
	114 dload (3, 1)
	115 #13 (3, 1)
	116 dcmpl (3, 1)
	117 iflt (3, 1)
	118 55 (3, 1)
	120 goto (3, 1)
	121 -57 (3, 1)
	123 dload (3, 1)
	124 #25 (3, 1)
	125 ldc2_w (3, 1)
	126 0.25 (3, 1)
	128 dcmpg (3, 1)
	129 ifgt (3, 1)
	130 32 (3, 1)
	132 dload (3, 1)
	133 #9 (3, 1)
	134 dload (3, 1)
	135 #19 (3, 1)
	136 invokestatic (3, 1)
	137 org/apache/commons/math3/util/FastMath.log:(D)D (3, 1)
	139 dload (3, 1)
	140 #19 (3, 1)
	141 dneg (3, 1)
	142 invokestatic (3, 1)
	143 org/apache/commons/math3/util/FastMath.log1p:(D)D (3, 1)
	145 dsub (3, 1)
	146 dmul (3, 1)
	147 dstore (3, 1)
	148 #27 (3, 1)
	149 dload_3 (3, 1)
	150 dload (3, 1)
	151 #27 (3, 1)
	152 invokestatic (3, 1)
	153 org/apache/commons/math3/util/FastMath.exp:(D)D (3, 1)
	155 dmul (3, 1)
	156 dstore (3, 1)
	157 #17 (3, 1)
	158 goto (3, 1)
	159 79 (3, 1)
	161 dload (3, 1)
	162 #25 (3, 1)
	163 dload (3, 1)
	164 #15 (3, 1)
	165 dcmpl (3, 1)
	166 iflt (3, 1)
	167 6 (3, 1)
	169 goto (3, 1)
	170 -106 (3, 1)
	172 dload (1, 4)
	173 #9 (1, 4)
	174 dload (1, 4)
	175 #19 (1, 4)
	176 invokestatic (1, 4)
	177 org/apache/commons/math3/util/FastMath.log:(D)D (1, 4)
	179 dload (1, 4)
	180 #19 (1, 4)
	181 dneg (1, 4)
	182 invokestatic (1, 4)
	183 org/apache/commons/math3/util/FastMath.log1p:(D)D (1, 4)
	185 dsub (1, 4)
	186 dmul (1, 4)
	187 dstore (1, 4)
	188 #27 (1, 4)
	189 dload_3 (1, 4)
	190 dload (1, 4)
	191 #27 (1, 4)
	192 invokestatic (1, 4)
	193 org/apache/commons/math3/util/FastMath.exp:(D)D (1, 4)
	195 dmul (1, 4)
	196 dstore (1, 4)
	197 #17 (1, 4)
	198 dload (2, 1)
	199 #7 (2, 1)
	200 dload (2, 1)
	201 #7 (2, 1)
	202 invokestatic (2, 1)
	203 org/apache/commons/math3/util/FastMath.log:(D)D (2, 1)
	205 dload (2, 1)
	206 #5 (2, 1)
	207 dload (2, 1)
	208 #17 (2, 1)
	209 dadd (2, 1)
	210 invokestatic (2, 1)
	211 org/apache/commons/math3/util/FastMath.log:(D)D (2, 1)
	213 dsub (2, 1)
	214 dload (2, 1)
	215 #27 (2, 1)
	216 dadd (2, 1)
	217 dmul (2, 1)
	218 ldc2_w (2, 1)
	219 1.3862944 (2, 1)
	221 dsub (2, 1)
	222 dload (2, 1)
	223 #25 (2, 1)
	224 invokestatic (2, 1)
	225 org/apache/commons/math3/util/FastMath.log:(D)D (2, 1)
	227 dcmpl (2, 1)
	228 iflt (2, 1)
	229 6 (2, 1)
	231 goto (2, 1)
	232 6 (2, 1)
	234 goto (0, 0)
	235 -171 (0, 0)
	237 dload (0, 0)
	238 #17 (0, 0)
	239 ldc2_w (0, 0)
	240 1.7976931348623157e+308 (0, 0)
	242 invokestatic (0, 0)
	243 org/apache/commons/math3/util/FastMath.min:(DD)D (0, 0)
	245 dstore (0, 0)
	246 #17 (0, 0)
	247 dload_3 (0, 0)
	248 dload_1 (0, 0)
	249 invokestatic (0, 0)
	250 org/apache/commons/math3/util/Precision.equals:(DD)Z (0, 0)
	252 ifeq (0, 0)
	253 14 (0, 0)
	255 dload (0, 0)
	256 #17 (0, 0)
	257 dload (0, 0)
	258 #5 (0, 0)
	259 dload (0, 0)
	260 #17 (0, 0)
	261 dadd (0, 0)
	262 ddiv (0, 0)
	263 goto (0, 0)
	264 11 (0, 0)
	266 dload (0, 0)
	267 #5 (0, 0)
	268 dload (0, 0)
	269 #5 (0, 0)
	270 dload (0, 0)
	271 #17 (0, 0)
	272 dadd (0, 0)
	273 ddiv (0, 0)
	274 dreturn (0, 0)

