Method: <init>
	0 aload_0 (0, 0)
	1 aload_1 (0, 0)
	2 invokespecial (0, 0)
	3 org/apache/commons/math3/distribution/AbstractIntegerDistribution.<init>:(Lorg/apache/commons/math3/random/RandomGenerator;)V (0, 0)
	5 iload_2 (1, 1)
	6 ifge (1, 1)
	7 18 (1, 1)
	9 new (1, 1)
	10 org/apache/commons/math3/exception/NotPositiveException (1, 1)
	12 dup (1, 1)
	13 getstatic (1, 1)
	14 org/apache/commons/math3/exception/util/LocalizedFormats.NUMBER_OF_TRIALS:Lorg/apache/commons/math3/exception/util/LocalizedFormats; (1, 1)
	16 iload_2 (1, 1)
	17 invokestatic (1, 1)
	18 java/lang/Integer.valueOf:(I)Ljava/lang/Integer; (1, 1)
	20 invokespecial (1, 1)
	21 org/apache/commons/math3/exception/NotPositiveException.<init>:(Lorg/apache/commons/math3/exception/util/Localizable;Ljava/lang/Number;)V (1, 1)
	23 athrow (1, 1)
	24 dload_3 (1, 1)
	25 dconst_0 (1, 1)
	26 dcmpg (1, 1)
	27 iflt (1, 1)
	28 9 (1, 1)
	30 dload_3 (1, 1)
	31 dconst_1 (1, 1)
	32 dcmpl (1, 1)
	33 ifle (1, 1)
	34 23 (1, 1)
	36 new (1, 1)
	37 org/apache/commons/math3/exception/OutOfRangeException (1, 1)
	39 dup (1, 1)
	40 dload_3 (1, 1)
	41 invokestatic (1, 1)
	42 java/lang/Double.valueOf:(D)Ljava/lang/Double; (1, 1)
	44 iconst_0 (1, 1)
	45 invokestatic (1, 1)
	46 java/lang/Integer.valueOf:(I)Ljava/lang/Integer; (1, 1)
	48 iconst_1 (1, 1)
	49 invokestatic (1, 1)
	50 java/lang/Integer.valueOf:(I)Ljava/lang/Integer; (1, 1)
	52 invokespecial (1, 1)
	53 org/apache/commons/math3/exception/OutOfRangeException.<init>:(Ljava/lang/Number;Ljava/lang/Number;Ljava/lang/Number;)V (1, 1)
	55 athrow (1, 1)
	56 aload_0 (0, 0)
	57 dload_3 (0, 0)
	58 putfield (0, 0)
	59 org/apache/commons/math3/distribution/BinomialDistribution.probabilityOfSuccess:D (0, 0)
	61 aload_0 (0, 0)
	62 iload_2 (0, 0)
	63 putfield (0, 0)
	64 org/apache/commons/math3/distribution/BinomialDistribution.numberOfTrials:I (0, 0)
	66 return (0, 0)

Method: getNumberOfTrials
	0 aload_0 (0, 0)
	1 getfield (0, 0)
	2 org/apache/commons/math3/distribution/BinomialDistribution.numberOfTrials:I (0, 0)
	4 ireturn (0, 0)

Method: getProbabilityOfSuccess
	0 aload_0 (0, 0)
	1 getfield (0, 0)
	2 org/apache/commons/math3/distribution/BinomialDistribution.probabilityOfSuccess:D (0, 0)
	4 dreturn (0, 0)

Method: probability
	0 aload_0 (0, 0)
	1 iload_1 (0, 0)
	2 invokevirtual (0, 0)
	3 org/apache/commons/math3/distribution/BinomialDistribution.logProbability:(I)D (0, 0)
	5 dstore_2 (0, 0)
	6 dload_2 (0, 0)
	7 ldc2_w (0, 0)
	8 -inf (0, 0)
	10 dcmpl (0, 0)
	11 ifne (0, 0)
	12 7 (0, 0)
	14 dconst_0 (0, 0)
	15 goto (0, 0)
	16 7 (0, 0)
	18 dload_2 (0, 0)
	19 invokestatic (0, 0)
	20 org/apache/commons/math3/util/FastMath.exp:(D)D (0, 0)
	22 dreturn (0, 0)

Method: logProbability
	0 aload_0 (1, 1)
	1 getfield (1, 1)
	2 org/apache/commons/math3/distribution/BinomialDistribution.numberOfTrials:I (1, 1)
	4 ifne (1, 1)
	5 15 (1, 1)
	7 iload_1 (1, 1)
	8 ifne (1, 1)
	9 7 (1, 1)
	11 dconst_0 (1, 1)
	12 goto (1, 1)
	13 6 (1, 1)
	15 ldc2_w (1, 1)
	16 -inf (1, 1)
	18 dreturn (1, 1)
	19 iload_1 (1, 1)
	20 iflt (1, 1)
	21 11 (1, 1)
	23 iload_1 (1, 1)
	24 aload_0 (1, 1)
	25 getfield (1, 1)
	26 org/apache/commons/math3/distribution/BinomialDistribution.numberOfTrials:I (1, 1)
	28 if_icmple (1, 1)
	29 10 (1, 1)
	31 ldc2_w (1, 1)
	32 -inf (1, 1)
	34 dstore_2 (1, 1)
	35 goto (1, 1)
	36 22 (1, 1)
	38 iload_1 (2, 2)
	39 aload_0 (2, 2)
	40 getfield (2, 2)
	41 org/apache/commons/math3/distribution/BinomialDistribution.numberOfTrials:I (2, 2)
	43 aload_0 (2, 2)
	44 getfield (2, 2)
	45 org/apache/commons/math3/distribution/BinomialDistribution.probabilityOfSuccess:D (2, 2)
	47 dconst_1 (2, 2)
	48 aload_0 (2, 2)
	49 getfield (2, 2)
	50 org/apache/commons/math3/distribution/BinomialDistribution.probabilityOfSuccess:D (2, 2)
	52 dsub (2, 2)
	53 invokestatic (2, 2)
	54 org/apache/commons/math3/distribution/SaddlePointExpansion.logBinomialProbability:(IIDD)D (2, 2)
	56 dstore_2 (2, 2)
	57 dload_2 (0, 0)
	58 dreturn (0, 0)

Method: cumulativeProbability
	0 iload_1 (1, 1)
	1 ifge (1, 1)
	2 8 (1, 1)
	4 dconst_0 (1, 1)
	5 dstore_2 (1, 1)
	6 goto (1, 1)
	7 37 (1, 1)
	9 iload_1 (2, 1)
	10 aload_0 (2, 1)
	11 getfield (2, 1)
	12 org/apache/commons/math3/distribution/BinomialDistribution.numberOfTrials:I (2, 1)
	14 if_icmplt (2, 1)
	15 8 (2, 1)
	17 dconst_1 (2, 1)
	18 dstore_2 (2, 1)
	19 goto (2, 1)
	20 24 (2, 1)
	22 dconst_1 (3, 2)
	23 aload_0 (3, 2)
	24 getfield (3, 2)
	25 org/apache/commons/math3/distribution/BinomialDistribution.probabilityOfSuccess:D (3, 2)
	27 iload_1 (3, 2)
	28 i2d (3, 2)
	29 dconst_1 (3, 2)
	30 dadd (3, 2)
	31 aload_0 (3, 2)
	32 getfield (3, 2)
	33 org/apache/commons/math3/distribution/BinomialDistribution.numberOfTrials:I (3, 2)
	35 iload_1 (3, 2)
	36 isub (3, 2)
	37 i2d (3, 2)
	38 invokestatic (3, 2)
	39 org/apache/commons/math3/special/Beta.regularizedBeta:(DDD)D (3, 2)
	41 dsub (3, 2)
	42 dstore_2 (3, 2)
	43 dload_2 (0, 0)
	44 dreturn (0, 0)

Method: getNumericalMean
	0 aload_0 (0, 0)
	1 getfield (0, 0)
	2 org/apache/commons/math3/distribution/BinomialDistribution.numberOfTrials:I (0, 0)
	4 i2d (0, 0)
	5 aload_0 (0, 0)
	6 getfield (0, 0)
	7 org/apache/commons/math3/distribution/BinomialDistribution.probabilityOfSuccess:D (0, 0)
	9 dmul (0, 0)
	10 dreturn (0, 0)

Method: getNumericalVariance
	0 aload_0 (0, 0)
	1 getfield (0, 0)
	2 org/apache/commons/math3/distribution/BinomialDistribution.probabilityOfSuccess:D (0, 0)
	4 dstore_1 (0, 0)
	5 aload_0 (0, 0)
	6 getfield (0, 0)
	7 org/apache/commons/math3/distribution/BinomialDistribution.numberOfTrials:I (0, 0)
	9 i2d (0, 0)
	10 dload_1 (0, 0)
	11 dmul (0, 0)
	12 dconst_1 (0, 0)
	13 dload_1 (0, 0)
	14 dsub (0, 0)
	15 dmul (0, 0)
	16 dreturn (0, 0)

Method: getSupportLowerBound
	0 aload_0 (0, 0)
	1 getfield (0, 0)
	2 org/apache/commons/math3/distribution/BinomialDistribution.probabilityOfSuccess:D (0, 0)
	4 dconst_1 (0, 0)
	5 dcmpg (0, 0)
	6 ifge (0, 0)
	7 7 (0, 0)
	9 iconst_0 (0, 0)
	10 goto (0, 0)
	11 7 (0, 0)
	13 aload_0 (0, 0)
	14 getfield (0, 0)
	15 org/apache/commons/math3/distribution/BinomialDistribution.numberOfTrials:I (0, 0)
	17 ireturn (0, 0)

Method: getSupportUpperBound
	0 aload_0 (0, 0)
	1 getfield (0, 0)
	2 org/apache/commons/math3/distribution/BinomialDistribution.probabilityOfSuccess:D (0, 0)
	4 dconst_0 (0, 0)
	5 dcmpl (0, 0)
	6 ifle (0, 0)
	7 10 (0, 0)
	9 aload_0 (0, 0)
	10 getfield (0, 0)
	11 org/apache/commons/math3/distribution/BinomialDistribution.numberOfTrials:I (0, 0)
	13 goto (0, 0)
	14 4 (0, 0)
	16 iconst_0 (0, 0)
	17 ireturn (0, 0)

Method: isSupportConnected
	0 iconst_1 (0, 0)
	1 ireturn (0, 0)

