Method: <init>
	0 aload_0 (0, 0)
	1 invokespecial (0, 0)
	2 java/lang/Object.<init>:()V (0, 0)
	4 aload_0 (0, 0)
	5 aload_1 (0, 0)
	6 putfield (0, 0)
	7 org/apache/commons/math3/distribution/EnumeratedDistribution.random:Lorg/apache/commons/math3/random/RandomGenerator; (0, 0)
	9 aload_0 (0, 0)
	10 new (0, 0)
	11 java/util/ArrayList (0, 0)
	13 dup (0, 0)
	14 aload_2 (0, 0)
	15 invokeinterface (0, 0)
	16 java/util/List.<init>:(I)V (0, 0)
	18 0 (0, 0)
	20 invokespecial (0, 0)
	21 java/util/ArrayList.<init>:(I)V (0, 0)
	23 putfield (0, 0)
	24 org/apache/commons/math3/distribution/EnumeratedDistribution.singletons:Ljava/util/List; (0, 0)
	26 aload_2 (0, 0)
	27 invokeinterface (0, 0)
	28 java/util/List.<init>:(I)V (0, 0)
	30 0 (0, 0)
	32 newarray (0, 0)
	33 7 (0, 0)
	34 astore_3 (0, 0)
	35 iconst_0 (2, 4)
	36 istore (2, 4)
	37 #4 (2, 4)
	38 iload (2, 4)
	39 #4 (2, 4)
	40 aload_2 (2, 4)
	41 invokeinterface (2, 4)
	42 java/util/List.<init>:(I)V (2, 4)
	44 0 (2, 4)
	46 if_icmpge (2, 4)
	47 120 (2, 4)
	49 aload_2 (2, 4)
	50 iload (2, 4)
	51 #4 (2, 4)
	52 invokeinterface (2, 4)
	53 java/util/List.org/apache/commons/math3/util/Pair (2, 4)
	55 0 (2, 4)
	57 checkcast (2, 4)
	58 org/apache/commons/math3/util/Pair (2, 4)
	60 astore (2, 4)
	61 #5 (2, 4)
	62 aload_0 (2, 4)
	63 getfield (2, 4)
	64 org/apache/commons/math3/distribution/EnumeratedDistribution.singletons:Ljava/util/List; (2, 4)
	66 aload (2, 4)
	67 #5 (2, 4)
	68 invokevirtual (2, 4)
	69 org/apache/commons/math3/util/Pair.getKey:()Ljava/lang/Object; (2, 4)
	71 invokeinterface (2, 4)
	72 java/util/List.getValue:()Ljava/lang/Object; (2, 4)
	74 0 (2, 4)
	76 pop (2, 4)
	77 aload (2, 4)
	78 #5 (2, 4)
	79 invokevirtual (2, 4)
	80 org/apache/commons/math3/util/Pair.getValue:()Ljava/lang/Object; (2, 4)
	82 checkcast (2, 4)
	83 java/lang/Double (2, 4)
	85 invokevirtual (2, 4)
	86 java/lang/Double.doubleValue:()D (2, 4)
	88 dstore (2, 4)
	89 #6 (2, 4)
	90 dload (3, 1)
	91 #6 (3, 1)
	92 dconst_0 (3, 1)
	93 dcmpg (3, 1)
	94 ifge (3, 1)
	95 19 (3, 1)
	97 new (3, 1)
	98 org/apache/commons/math3/exception/NotPositiveException (3, 1)
	100 dup (3, 1)
	101 aload (3, 1)
	102 #5 (3, 1)
	103 invokevirtual (3, 1)
	104 org/apache/commons/math3/util/Pair.getValue:()Ljava/lang/Object; (3, 1)
	106 checkcast (3, 1)
	107 java/lang/Number (3, 1)
	109 invokespecial (3, 1)
	110 org/apache/commons/math3/exception/NotPositiveException.<init>:(Ljava/lang/Number;)V (3, 1)
	112 athrow (3, 1)
	113 dload (3, 1)
	114 #6 (3, 1)
	115 invokestatic (3, 1)
	116 java/lang/Double.isInfinite:(D)Z (3, 1)
	118 ifeq (3, 1)
	119 20 (3, 1)
	121 new (3, 1)
	122 org/apache/commons/math3/exception/NotFiniteNumberException (3, 1)
	124 dup (3, 1)
	125 dload (3, 1)
	126 #6 (3, 1)
	127 invokestatic (3, 1)
	128 java/lang/Double.valueOf:(D)Ljava/lang/Double; (3, 1)
	130 iconst_0 (3, 1)
	131 anewarray (3, 1)
	132 java/lang/Object (3, 1)
	134 invokespecial (3, 1)
	135 org/apache/commons/math3/exception/NotFiniteNumberException.<init>:(Ljava/lang/Number;[Ljava/lang/Object;)V (3, 1)
	137 athrow (3, 1)
	138 dload (3, 1)
	139 #6 (3, 1)
	140 invokestatic (3, 1)
	141 java/lang/Double.isNaN:(D)Z (3, 1)
	143 ifeq (3, 1)
	144 11 (3, 1)
	146 new (3, 1)
	147 org/apache/commons/math3/exception/NotANumberException (3, 1)
	149 dup (3, 1)
	150 invokespecial (3, 1)
	151 org/apache/commons/math3/exception/NotANumberException.<init>:()V (3, 1)
	153 athrow (3, 1)
	154 aload_3 (2, 4)
	155 iload (2, 4)
	156 #4 (2, 4)
	157 dload (2, 4)
	158 #6 (2, 4)
	159 dastore (2, 4)
	160 iinc (2, 4)
	161 #4 (2, 4)
	162 -89 (2, 4)
	163 goto (2, 4)
	164 -125 (2, 4)
	166 aload_0 (0, 0)
	167 aload_3 (0, 0)
	168 dconst_1 (0, 0)
	169 invokestatic (0, 0)
	170 org/apache/commons/math3/util/MathArrays.normalizeArray:([DD)[D (0, 0)
	172 putfield (0, 0)
	173 org/apache/commons/math3/distribution/EnumeratedDistribution.probabilities:[D (0, 0)
	175 aload_0 (0, 0)
	176 aload_0 (0, 0)
	177 getfield (0, 0)
	178 org/apache/commons/math3/distribution/EnumeratedDistribution.probabilities:[D (0, 0)
	180 arraylength (0, 0)
	181 newarray (0, 0)
	182 7 (0, 0)
	183 putfield (0, 0)
	184 org/apache/commons/math3/distribution/EnumeratedDistribution.cumulativeProbabilities:[D (0, 0)
	186 dconst_0 (0, 0)
	187 dstore (0, 0)
	188 #4 (0, 0)
	189 iconst_0 (2, 4)
	190 istore (2, 4)
	191 #6 (2, 4)
	192 iload (2, 4)
	193 #6 (2, 4)
	194 aload_0 (2, 4)
	195 getfield (2, 4)
	196 org/apache/commons/math3/distribution/EnumeratedDistribution.probabilities:[D (2, 4)
	198 arraylength (2, 4)
	199 if_icmpge (2, 4)
	200 30 (2, 4)
	202 dload (2, 4)
	203 #4 (2, 4)
	204 aload_0 (2, 4)
	205 getfield (2, 4)
	206 org/apache/commons/math3/distribution/EnumeratedDistribution.probabilities:[D (2, 4)
	208 iload (2, 4)
	209 #6 (2, 4)
	210 daload (2, 4)
	211 dadd (2, 4)
	212 dstore (2, 4)
	213 #4 (2, 4)
	214 aload_0 (2, 4)
	215 getfield (2, 4)
	216 org/apache/commons/math3/distribution/EnumeratedDistribution.cumulativeProbabilities:[D (2, 4)
	218 iload (2, 4)
	219 #6 (2, 4)
	220 dload (2, 4)
	221 #4 (2, 4)
	222 dastore (2, 4)
	223 iinc (2, 4)
	224 #6 (2, 4)
	225 -89 (2, 4)
	226 goto (2, 4)
	227 -34 (2, 4)
	229 return (0, 0)

Method: reseedRandomGenerator
	0 aload_0 (0, 0)
	1 getfield (0, 0)
	2 org/apache/commons/math3/distribution/EnumeratedDistribution.random:Lorg/apache/commons/math3/random/RandomGenerator; (0, 0)
	4 lload_1 (0, 0)
	5 invokeinterface (0, 0)
	6 org/apache/commons/math3/random/RandomGenerator.equals:(Ljava/lang/Object;)Z (0, 0)
	8 0 (0, 0)
	10 return (0, 0)

Method: probability
	0 dconst_0 (0, 0)
	1 dstore_2 (0, 0)
	2 iconst_0 (1, 4)
	3 istore (1, 4)
	4 #4 (1, 4)
	5 iload (1, 4)
	6 #4 (1, 4)
	7 aload_0 (1, 4)
	8 getfield (1, 4)
	9 org/apache/commons/math3/distribution/EnumeratedDistribution.probabilities:[D (1, 4)
	11 arraylength (1, 4)
	12 if_icmpge (1, 4)
	13 59 (1, 4)
	15 aload_1 (1, 1)
	16 ifnonnull (1, 1)
	17 17 (1, 1)
	19 aload_0 (1, 1)
	20 getfield (1, 1)
	21 org/apache/commons/math3/distribution/EnumeratedDistribution.singletons:Ljava/util/List; (1, 1)
	23 iload (1, 1)
	24 #4 (1, 1)
	25 invokeinterface (1, 1)
	26 java/util/List.org/apache/commons/math3/util/Pair (1, 1)
	28 0 (1, 1)
	30 ifnull (1, 1)
	31 25 (1, 1)
	33 aload_1 (1, 1)
	34 ifnull (1, 1)
	35 31 (1, 1)
	37 aload_1 (1, 1)
	38 aload_0 (1, 1)
	39 getfield (1, 1)
	40 org/apache/commons/math3/distribution/EnumeratedDistribution.singletons:Ljava/util/List; (1, 1)
	42 iload (1, 1)
	43 #4 (1, 1)
	44 invokeinterface (1, 1)
	45 java/util/List.org/apache/commons/math3/util/Pair (1, 1)
	47 0 (1, 1)
	49 invokevirtual (1, 1)
	50 java/lang/Object.equals:(Ljava/lang/Object;)Z (1, 1)
	52 ifeq (1, 1)
	53 13 (1, 1)
	55 dload_2 (1, 1)
	56 aload_0 (1, 1)
	57 getfield (1, 1)
	58 org/apache/commons/math3/distribution/EnumeratedDistribution.probabilities:[D (1, 1)
	60 iload (1, 1)
	61 #4 (1, 1)
	62 daload (1, 1)
	63 dadd (1, 1)
	64 dstore_2 (1, 1)
	65 iinc (1, 1)
	66 #4 (1, 1)
	67 -89 (1, 1)
	68 goto (1, 1)
	69 -63 (1, 1)
	71 dload_2 (1, 1)
	72 dreturn (1, 1)

Method: getPmf
	0 new (0, 0)
	1 java/util/ArrayList (0, 0)
	3 dup (0, 0)
	4 aload_0 (0, 0)
	5 getfield (0, 0)
	6 org/apache/commons/math3/distribution/EnumeratedDistribution.probabilities:[D (0, 0)
	8 arraylength (0, 0)
	9 invokespecial (0, 0)
	10 java/util/ArrayList.<init>:(I)V (0, 0)
	12 astore_1 (0, 0)
	13 iconst_0 (1, 4)
	14 istore_2 (1, 4)
	15 iload_2 (1, 4)
	16 aload_0 (1, 4)
	17 getfield (1, 4)
	18 org/apache/commons/math3/distribution/EnumeratedDistribution.probabilities:[D (1, 4)
	20 arraylength (1, 4)
	21 if_icmpge (1, 4)
	22 42 (1, 4)
	24 aload_1 (1, 4)
	25 new (1, 4)
	26 org/apache/commons/math3/util/Pair (1, 4)
	28 dup (1, 4)
	29 aload_0 (1, 4)
	30 getfield (1, 4)
	31 org/apache/commons/math3/distribution/EnumeratedDistribution.singletons:Ljava/util/List; (1, 4)
	33 iload_2 (1, 4)
	34 invokeinterface (1, 4)
	35 java/util/List.org/apache/commons/math3/util/Pair (1, 4)
	37 0 (1, 4)
	39 aload_0 (1, 4)
	40 getfield (1, 4)
	41 org/apache/commons/math3/distribution/EnumeratedDistribution.probabilities:[D (1, 4)
	43 iload_2 (1, 4)
	44 daload (1, 4)
	45 invokestatic (1, 4)
	46 java/lang/Double.valueOf:(D)Ljava/lang/Double; (1, 4)
	48 invokespecial (1, 4)
	49 org/apache/commons/math3/util/Pair.<init>:(Ljava/lang/Object;Ljava/lang/Object;)V (1, 4)
	51 invokeinterface (1, 4)
	52 java/util/List.getValue:()Ljava/lang/Object; (1, 4)
	54 0 (1, 4)
	56 pop (1, 4)
	57 iinc (1, 4)
	58 #2 (1, 4)
	59 -89 (1, 4)
	60 goto (1, 4)
	61 -45 (1, 4)
	63 aload_1 (0, 0)
	64 areturn (0, 0)

Method: sample
	0 iload_1 (1, 1)
	1 ifgt (1, 1)
	2 18 (1, 1)
	4 new (1, 1)
	5 org/apache/commons/math3/exception/NotStrictlyPositiveException (1, 1)
	7 dup (1, 1)
	8 getstatic (1, 1)
	9 org/apache/commons/math3/exception/util/LocalizedFormats.NUMBER_OF_SAMPLES:Lorg/apache/commons/math3/exception/util/LocalizedFormats; (1, 1)
	11 iload_1 (1, 1)
	12 invokestatic (1, 1)
	13 java/lang/Integer.valueOf:(I)Ljava/lang/Integer; (1, 1)
	15 invokespecial (1, 1)
	16 org/apache/commons/math3/exception/NotStrictlyPositiveException.<init>:(Lorg/apache/commons/math3/exception/util/Localizable;Ljava/lang/Number;)V (1, 1)
	18 athrow (1, 1)
	19 aload_2 (1, 1)
	20 ifnonnull (1, 1)
	21 18 (1, 1)
	23 new (1, 1)
	24 org/apache/commons/math3/exception/NullArgumentException (1, 1)
	26 dup (1, 1)
	27 getstatic (1, 1)
	28 org/apache/commons/math3/exception/util/LocalizedFormats.INPUT_ARRAY:Lorg/apache/commons/math3/exception/util/LocalizedFormats; (1, 1)
	30 iconst_0 (1, 1)
	31 anewarray (1, 1)
	32 java/lang/Object (1, 1)
	34 invokespecial (1, 1)
	35 org/apache/commons/math3/exception/NullArgumentException.<init>:(Lorg/apache/commons/math3/exception/util/Localizable;[Ljava/lang/Object;)V (1, 1)
	37 athrow (1, 1)
	38 aload_2 (1, 1)
	39 arraylength (1, 1)
	40 iload_1 (1, 1)
	41 if_icmpge (1, 1)
	42 28 (1, 1)
	44 aload_2 (1, 1)
	45 invokevirtual (1, 1)
	46 java/lang/Object.getClass:()Ljava/lang/Class; (1, 1)
	48 invokevirtual (1, 1)
	49 java/lang/Class.getComponentType:()Ljava/lang/Class; (1, 1)
	51 iload_1 (1, 1)
	52 invokestatic (1, 1)
	53 java/lang/reflect/Array.newInstance:(Ljava/lang/Class;I)Ljava/lang/Object; (1, 1)
	55 checkcast (1, 1)
	56 [Ljava/lang/Object; (1, 1)
	58 checkcast (1, 1)
	59 [Ljava/lang/Object; (1, 1)
	61 astore (1, 1)
	62 #4 (1, 1)
	63 aload (1, 1)
	64 #4 (1, 1)
	65 astore_3 (1, 1)
	66 goto (1, 2)
	67 5 (1, 2)
	69 aload_2 (1, 2)
	70 astore_3 (1, 2)
	71 iconst_0 (1, 4)
	72 istore (1, 4)
	73 #4 (1, 4)
	74 iload (1, 4)
	75 #4 (1, 4)
	76 iload_1 (1, 4)
	77 if_icmpge (1, 4)
	78 17 (1, 4)
	80 aload_3 (1, 4)
	81 iload (1, 4)
	82 #4 (1, 4)
	83 aload_0 (1, 4)
	84 invokevirtual (1, 4)
	85 org/apache/commons/math3/distribution/EnumeratedDistribution.sample:()Ljava/lang/Object; (1, 4)
	87 aastore (1, 4)
	88 iinc (1, 4)
	89 #4 (1, 4)
	90 -89 (1, 4)
	91 goto (1, 4)
	92 -17 (1, 4)
	94 aload_3 (0, 0)
	95 areturn (0, 0)

