Method: <init>
	0 aload_0 (0, 0)
	1 aload_1 (0, 0)
	2 invokespecial (0, 0)
	3 org/apache/commons/math3/distribution/AbstractRealDistribution.<init>:(Lorg/apache/commons/math3/random/RandomGenerator;)V (0, 0)
	5 dload_2 (1, 1)
	6 dconst_0 (1, 1)
	7 dcmpg (1, 1)
	8 ifgt (1, 1)
	9 18 (1, 1)
	11 new (1, 1)
	12 org/apache/commons/math3/exception/NotStrictlyPositiveException (1, 1)
	14 dup (1, 1)
	15 getstatic (1, 1)
	16 org/apache/commons/math3/exception/util/LocalizedFormats.MEAN:Lorg/apache/commons/math3/exception/util/LocalizedFormats; (1, 1)
	18 dload_2 (1, 1)
	19 invokestatic (1, 1)
	20 java/lang/Double.valueOf:(D)Ljava/lang/Double; (1, 1)
	22 invokespecial (1, 1)
	23 org/apache/commons/math3/exception/NotStrictlyPositiveException.<init>:(Lorg/apache/commons/math3/exception/util/Localizable;Ljava/lang/Number;)V (1, 1)
	25 athrow (1, 1)
	26 aload_0 (0, 0)
	27 dload_2 (0, 0)
	28 putfield (0, 0)
	29 org/apache/commons/math3/distribution/ExponentialDistribution.mean:D (0, 0)
	31 aload_0 (0, 0)
	32 dload_2 (0, 0)
	33 invokestatic (0, 0)
	34 org/apache/commons/math3/util/FastMath.log:(D)D (0, 0)
	36 putfield (0, 0)
	37 org/apache/commons/math3/distribution/ExponentialDistribution.logMean:D (0, 0)
	39 aload_0 (0, 0)
	40 dload (0, 0)
	41 #4 (0, 0)
	42 putfield (0, 0)
	43 org/apache/commons/math3/distribution/ExponentialDistribution.solverAbsoluteAccuracy:D (0, 0)
	45 return (0, 0)

Method: getMean
	0 aload_0 (0, 0)
	1 getfield (0, 0)
	2 org/apache/commons/math3/distribution/ExponentialDistribution.mean:D (0, 0)
	4 dreturn (0, 0)

Method: density
	0 aload_0 (0, 0)
	1 dload_1 (0, 0)
	2 invokevirtual (0, 0)
	3 org/apache/commons/math3/distribution/ExponentialDistribution.logDensity:(D)D (0, 0)
	5 dstore_3 (0, 0)
	6 dload_3 (0, 0)
	7 ldc2_w (0, 0)
	8 -inf (0, 0)
	10 dcmpl (0, 0)
	11 ifne (0, 0)
	12 7 (0, 0)
	14 dconst_0 (0, 0)
	15 goto (0, 0)
	16 7 (0, 0)
	18 dload_3 (0, 0)
	19 invokestatic (0, 0)
	20 org/apache/commons/math3/util/FastMath.exp:(D)D (0, 0)
	22 dreturn (0, 0)

Method: logDensity
	0 dload_1 (1, 1)
	1 dconst_0 (1, 1)
	2 dcmpg (1, 1)
	3 ifge (1, 1)
	4 7 (1, 1)
	6 ldc2_w (1, 1)
	7 -inf (1, 1)
	9 dreturn (1, 1)
	10 dload_1 (0, 0)
	11 dneg (0, 0)
	12 aload_0 (0, 0)
	13 getfield (0, 0)
	14 org/apache/commons/math3/distribution/ExponentialDistribution.mean:D (0, 0)
	16 ddiv (0, 0)
	17 aload_0 (0, 0)
	18 getfield (0, 0)
	19 org/apache/commons/math3/distribution/ExponentialDistribution.logMean:D (0, 0)
	21 dsub (0, 0)
	22 dreturn (0, 0)

Method: cumulativeProbability
	0 dload_1 (1, 1)
	1 dconst_0 (1, 1)
	2 dcmpg (1, 1)
	3 ifgt (1, 1)
	4 8 (1, 1)
	6 dconst_0 (1, 1)
	7 dstore_3 (1, 1)
	8 goto (1, 1)
	9 16 (1, 1)
	11 dconst_1 (2, 2)
	12 dload_1 (2, 2)
	13 dneg (2, 2)
	14 aload_0 (2, 2)
	15 getfield (2, 2)
	16 org/apache/commons/math3/distribution/ExponentialDistribution.mean:D (2, 2)
	18 ddiv (2, 2)
	19 invokestatic (2, 2)
	20 org/apache/commons/math3/util/FastMath.exp:(D)D (2, 2)
	22 dsub (2, 2)
	23 dstore_3 (2, 2)
	24 dload_3 (0, 0)
	25 dreturn (0, 0)

Method: inverseCumulativeProbability
	0 dload_1 (1, 1)
	1 dconst_0 (1, 1)
	2 dcmpg (1, 1)
	3 iflt (1, 1)
	4 9 (1, 1)
	6 dload_1 (1, 1)
	7 dconst_1 (1, 1)
	8 dcmpl (1, 1)
	9 ifle (1, 1)
	10 23 (1, 1)
	12 new (1, 1)
	13 org/apache/commons/math3/exception/OutOfRangeException (1, 1)
	15 dup (1, 1)
	16 dload_1 (1, 1)
	17 invokestatic (1, 1)
	18 java/lang/Double.valueOf:(D)Ljava/lang/Double; (1, 1)
	20 dconst_0 (1, 1)
	21 invokestatic (1, 1)
	22 java/lang/Double.valueOf:(D)Ljava/lang/Double; (1, 1)
	24 dconst_1 (1, 1)
	25 invokestatic (1, 1)
	26 java/lang/Double.valueOf:(D)Ljava/lang/Double; (1, 1)
	28 invokespecial (1, 1)
	29 org/apache/commons/math3/exception/OutOfRangeException.<init>:(Ljava/lang/Number;Ljava/lang/Number;Ljava/lang/Number;)V (1, 1)
	31 athrow (1, 1)
	32 dload_1 (2, 1)
	33 dconst_1 (2, 1)
	34 dcmpl (2, 1)
	35 ifne (2, 1)
	36 10 (2, 1)
	38 ldc2_w (2, 1)
	39 inf (2, 1)
	41 dstore_3 (2, 1)
	42 goto (2, 1)
	43 16 (2, 1)
	45 aload_0 (3, 2)
	46 getfield (3, 2)
	47 org/apache/commons/math3/distribution/ExponentialDistribution.mean:D (3, 2)
	49 dneg (3, 2)
	50 dconst_1 (3, 2)
	51 dload_1 (3, 2)
	52 dsub (3, 2)
	53 invokestatic (3, 2)
	54 org/apache/commons/math3/util/FastMath.log:(D)D (3, 2)
	56 dmul (3, 2)
	57 dstore_3 (3, 2)
	58 dload_3 (0, 0)
	59 dreturn (0, 0)

Method: sample
	0 dconst_0 (0, 0)
	1 dstore_1 (0, 0)
	2 aload_0 (0, 0)
	3 getfield (0, 0)
	4 org/apache/commons/math3/distribution/ExponentialDistribution.random:Lorg/apache/commons/math3/random/RandomGenerator; (0, 0)
	6 invokeinterface (0, 0)
	7 org/apache/commons/math3/random/RandomGenerator.EXPONENTIAL_SA_QI:[D (0, 0)
	9 0 (0, 0)
	11 dstore_3 (0, 0)
	12 dload_3 (1, 3)
	13 ldc2_w (1, 3)
	14 0.5 (1, 3)
	16 dcmpg (1, 3)
	17 ifge (1, 3)
	18 20 (1, 3)
	20 dload_1 (1, 3)
	21 getstatic (1, 3)
	22 org/apache/commons/math3/distribution/ExponentialDistribution.EXPONENTIAL_SA_QI:[D (1, 3)
	24 iconst_0 (1, 3)
	25 daload (1, 3)
	26 dadd (1, 3)
	27 dstore_1 (1, 3)
	28 dload_3 (1, 3)
	29 ldc2_w (1, 3)
	30 2.0 (1, 3)
	32 dmul (1, 3)
	33 dstore_3 (1, 3)
	34 goto (1, 3)
	35 -22 (1, 3)
	37 dload_3 (0, 0)
	38 dload_3 (0, 0)
	39 dconst_1 (0, 0)
	40 dsub (0, 0)
	41 dadd (0, 0)
	42 dstore_3 (0, 0)
	43 dload_3 (1, 1)
	44 getstatic (1, 1)
	45 org/apache/commons/math3/distribution/ExponentialDistribution.EXPONENTIAL_SA_QI:[D (1, 1)
	47 iconst_0 (1, 1)
	48 daload (1, 1)
	49 dcmpg (1, 1)
	50 ifgt (1, 1)
	51 12 (1, 1)
	53 aload_0 (1, 1)
	54 getfield (1, 1)
	55 org/apache/commons/math3/distribution/ExponentialDistribution.mean:D (1, 1)
	57 dload_1 (1, 1)
	58 dload_3 (1, 1)
	59 dadd (1, 1)
	60 dmul (1, 1)
	61 dreturn (1, 1)
	62 iconst_0 (1, 3)
	63 istore (1, 3)
	64 #5 (1, 3)
	65 aload_0 (1, 3)
	66 getfield (1, 3)
	67 org/apache/commons/math3/distribution/ExponentialDistribution.random:Lorg/apache/commons/math3/random/RandomGenerator; (1, 3)
	69 invokeinterface (1, 3)
	70 org/apache/commons/math3/random/RandomGenerator.EXPONENTIAL_SA_QI:[D (1, 3)
	72 0 (1, 3)
	74 dstore (1, 3)
	75 #6 (1, 3)
	76 dload (1, 3)
	77 #6 (1, 3)
	78 dstore (1, 3)
	79 #8 (1, 3)
	80 iinc (1, 3)
	81 #5 (1, 3)
	82 42 (1, 3)
	83 aload_0 (1, 3)
	84 getfield (1, 3)
	85 org/apache/commons/math3/distribution/ExponentialDistribution.random:Lorg/apache/commons/math3/random/RandomGenerator; (1, 3)
	87 invokeinterface (1, 3)
	88 org/apache/commons/math3/random/RandomGenerator.EXPONENTIAL_SA_QI:[D (1, 3)
	90 0 (1, 3)
	92 dstore (1, 3)
	93 #6 (1, 3)
	94 dload (2, 1)
	95 #6 (2, 1)
	96 dload (2, 1)
	97 #8 (2, 1)
	98 dcmpg (2, 1)
	99 ifge (2, 1)
	100 7 (2, 1)
	102 dload (2, 1)
	103 #6 (2, 1)
	104 dstore (2, 1)
	105 #8 (2, 1)
	106 dload_3 (2, 3)
	107 getstatic (2, 3)
	108 org/apache/commons/math3/distribution/ExponentialDistribution.EXPONENTIAL_SA_QI:[D (2, 3)
	110 iload (2, 3)
	111 #5 (2, 3)
	112 daload (2, 3)
	113 dcmpl (2, 3)
	114 ifgt (2, 3)
	115 -34 (2, 3)
	117 aload_0 (2, 3)
	118 getfield (2, 3)
	119 org/apache/commons/math3/distribution/ExponentialDistribution.mean:D (2, 3)
	121 dload_1 (2, 3)
	122 dload (2, 3)
	123 #8 (2, 3)
	124 getstatic (2, 3)
	125 org/apache/commons/math3/distribution/ExponentialDistribution.EXPONENTIAL_SA_QI:[D (2, 3)
	127 iconst_0 (2, 3)
	128 daload (2, 3)
	129 dmul (2, 3)
	130 dadd (2, 3)
	131 dmul (2, 3)
	132 dreturn (0, 3)

Method: getSolverAbsoluteAccuracy
	0 aload_0 (0, 0)
	1 getfield (0, 0)
	2 org/apache/commons/math3/distribution/ExponentialDistribution.solverAbsoluteAccuracy:D (0, 0)
	4 dreturn (0, 0)

Method: getNumericalMean
	0 aload_0 (0, 0)
	1 invokevirtual (0, 0)
	2 org/apache/commons/math3/distribution/ExponentialDistribution.getMean:()D (0, 0)
	4 dreturn (0, 0)

Method: getNumericalVariance
	0 aload_0 (0, 0)
	1 invokevirtual (0, 0)
	2 org/apache/commons/math3/distribution/ExponentialDistribution.getMean:()D (0, 0)
	4 dstore_1 (0, 0)
	5 dload_1 (0, 0)
	6 dload_1 (0, 0)
	7 dmul (0, 0)
	8 dreturn (0, 0)

Method: getSupportLowerBound
	0 dconst_0 (0, 0)
	1 dreturn (0, 0)

Method: getSupportUpperBound
	0 ldc2_w (0, 0)
	1 inf (0, 0)
	3 dreturn (0, 0)

Method: isSupportLowerBoundInclusive
	0 iconst_1 (0, 0)
	1 ireturn (0, 0)

Method: isSupportUpperBoundInclusive
	0 iconst_0 (0, 0)
	1 ireturn (0, 0)

Method: isSupportConnected
	0 iconst_1 (0, 0)
	1 ireturn (0, 0)

Method: <clinit>
	0 ldc2_w (0, 0)
	1 2.0 (0, 0)
	3 invokestatic (0, 0)
	4 org/apache/commons/math3/util/FastMath.log:(D)D (0, 0)
	6 dstore_0 (0, 0)
	7 dconst_0 (0, 0)
	8 dstore_2 (0, 0)
	9 iconst_1 (0, 0)
	10 istore (0, 0)
	11 #4 (0, 0)
	12 new (0, 0)
	13 org/apache/commons/math3/util/ResizableDoubleArray (0, 0)
	15 dup (0, 0)
	16 bipush (0, 0)
	17 20 (0, 0)
	18 invokespecial (0, 0)
	19 org/apache/commons/math3/util/ResizableDoubleArray.<init>:(I)V (0, 0)
	21 astore (0, 0)
	22 #5 (0, 0)
	23 dload_2 (1, 3)
	24 dconst_1 (1, 3)
	25 dcmpg (1, 3)
	26 ifge (1, 3)
	27 31 (1, 3)
	29 dload_2 (1, 3)
	30 dload_0 (1, 3)
	31 iload (1, 3)
	32 #4 (1, 3)
	33 invokestatic (1, 3)
	34 org/apache/commons/math3/util/FastMath.pow:(DI)D (1, 3)
	36 iload (1, 3)
	37 #4 (1, 3)
	38 invokestatic (1, 3)
	39 org/apache/commons/math3/util/CombinatoricsUtils.factorial:(I)J (1, 3)
	41 l2d (1, 3)
	42 ddiv (1, 3)
	43 dadd (1, 3)
	44 dstore_2 (1, 3)
	45 aload (1, 3)
	46 #5 (1, 3)
	47 dload_2 (1, 3)
	48 invokevirtual (1, 3)
	49 org/apache/commons/math3/util/ResizableDoubleArray.addElement:(D)V (1, 3)
	51 iinc (1, 3)
	52 #4 (1, 3)
	53 -89 (1, 3)
	54 goto (1, 3)
	55 -31 (1, 3)
	57 aload (0, 0)
	58 #5 (0, 0)
	59 invokevirtual (0, 0)
	60 org/apache/commons/math3/util/ResizableDoubleArray.getElements:()[D (0, 0)
	62 putstatic (0, 0)
	63 org/apache/commons/math3/distribution/ExponentialDistribution.EXPONENTIAL_SA_QI:[D (0, 0)
	65 return (0, 0)

