Method: <init>
	0 aload_0 (0, 0)
	1 aload_1 (0, 0)
	2 invokespecial (0, 0)
	3 org/apache/commons/math3/distribution/AbstractRealDistribution.<init>:(Lorg/apache/commons/math3/random/RandomGenerator;)V (0, 0)
	5 aload_0 (0, 0)
	6 ldc2_w (0, 0)
	7 nan (0, 0)
	9 putfield (0, 0)
	10 org/apache/commons/math3/distribution/FDistribution.numericalVariance:D (0, 0)
	12 aload_0 (0, 0)
	13 iconst_0 (0, 0)
	14 putfield (0, 0)
	15 org/apache/commons/math3/distribution/FDistribution.numericalVarianceIsCalculated:Z (0, 0)
	17 dload_2 (2, 1)
	18 dconst_0 (2, 1)
	19 dcmpg (2, 1)
	20 ifgt (2, 1)
	21 18 (2, 1)
	23 new (2, 1)
	24 org/apache/commons/math3/exception/NotStrictlyPositiveException (2, 1)
	26 dup (2, 1)
	27 getstatic (2, 1)
	28 org/apache/commons/math3/exception/util/LocalizedFormats.DEGREES_OF_FREEDOM:Lorg/apache/commons/math3/exception/util/LocalizedFormats; (2, 1)
	30 dload_2 (2, 1)
	31 invokestatic (2, 1)
	32 java/lang/Double.valueOf:(D)Ljava/lang/Double; (2, 1)
	34 invokespecial (2, 1)
	35 org/apache/commons/math3/exception/NotStrictlyPositiveException.<init>:(Lorg/apache/commons/math3/exception/util/Localizable;Ljava/lang/Number;)V (2, 1)
	37 athrow (2, 1)
	38 dload (2, 1)
	39 #4 (2, 1)
	40 dconst_0 (2, 1)
	41 dcmpg (2, 1)
	42 ifgt (2, 1)
	43 19 (2, 1)
	45 new (2, 1)
	46 org/apache/commons/math3/exception/NotStrictlyPositiveException (2, 1)
	48 dup (2, 1)
	49 getstatic (2, 1)
	50 org/apache/commons/math3/exception/util/LocalizedFormats.DEGREES_OF_FREEDOM:Lorg/apache/commons/math3/exception/util/LocalizedFormats; (2, 1)
	52 dload (2, 1)
	53 #4 (2, 1)
	54 invokestatic (2, 1)
	55 java/lang/Double.valueOf:(D)Ljava/lang/Double; (2, 1)
	57 invokespecial (2, 1)
	58 org/apache/commons/math3/exception/NotStrictlyPositiveException.<init>:(Lorg/apache/commons/math3/exception/util/Localizable;Ljava/lang/Number;)V (2, 1)
	60 athrow (2, 1)
	61 aload_0 (0, 1)
	62 dload_2 (0, 1)
	63 putfield (0, 1)
	64 org/apache/commons/math3/distribution/FDistribution.numeratorDegreesOfFreedom:D (0, 1)
	66 aload_0 (0, 1)
	67 dload (0, 1)
	68 #4 (0, 1)
	69 putfield (0, 1)
	70 org/apache/commons/math3/distribution/FDistribution.denominatorDegreesOfFreedom:D (0, 1)
	72 aload_0 (0, 1)
	73 dload (0, 1)
	74 #6 (0, 1)
	75 putfield (0, 1)
	76 org/apache/commons/math3/distribution/FDistribution.solverAbsoluteAccuracy:D (0, 1)
	78 return (0, 1)

Method: density
	0 aload_0 (0, 0)
	1 dload_1 (0, 0)
	2 invokevirtual (0, 0)
	3 org/apache/commons/math3/distribution/FDistribution.logDensity:(D)D (0, 0)
	5 invokestatic (0, 0)
	6 org/apache/commons/math3/util/FastMath.exp:(D)D (0, 0)
	8 dreturn (0, 0)

Method: logDensity
	0 aload_0 (0, 0)
	1 getfield (0, 0)
	2 org/apache/commons/math3/distribution/FDistribution.numeratorDegreesOfFreedom:D (0, 0)
	4 ldc2_w (0, 0)
	5 2.0 (0, 0)
	7 ddiv (0, 0)
	8 dstore_3 (0, 0)
	9 aload_0 (0, 0)
	10 getfield (0, 0)
	11 org/apache/commons/math3/distribution/FDistribution.denominatorDegreesOfFreedom:D (0, 0)
	13 ldc2_w (0, 0)
	14 2.0 (0, 0)
	16 ddiv (0, 0)
	17 dstore (0, 0)
	18 #5 (0, 0)
	19 dload_1 (0, 0)
	20 invokestatic (0, 0)
	21 org/apache/commons/math3/util/FastMath.log:(D)D (0, 0)
	23 dstore (0, 0)
	24 #7 (0, 0)
	25 aload_0 (0, 0)
	26 getfield (0, 0)
	27 org/apache/commons/math3/distribution/FDistribution.numeratorDegreesOfFreedom:D (0, 0)
	29 invokestatic (0, 0)
	30 org/apache/commons/math3/util/FastMath.log:(D)D (0, 0)
	32 dstore (0, 0)
	33 #9 (0, 0)
	34 aload_0 (0, 0)
	35 getfield (0, 0)
	36 org/apache/commons/math3/distribution/FDistribution.denominatorDegreesOfFreedom:D (0, 0)
	38 invokestatic (0, 0)
	39 org/apache/commons/math3/util/FastMath.log:(D)D (0, 0)
	41 dstore (0, 0)
	42 #11 (0, 0)
	43 aload_0 (0, 0)
	44 getfield (0, 0)
	45 org/apache/commons/math3/distribution/FDistribution.numeratorDegreesOfFreedom:D (0, 0)
	47 dload_1 (0, 0)
	48 dmul (0, 0)
	49 aload_0 (0, 0)
	50 getfield (0, 0)
	51 org/apache/commons/math3/distribution/FDistribution.denominatorDegreesOfFreedom:D (0, 0)
	53 dadd (0, 0)
	54 invokestatic (0, 0)
	55 org/apache/commons/math3/util/FastMath.log:(D)D (0, 0)
	57 dstore (0, 0)
	58 #13 (0, 0)
	59 dload_3 (0, 0)
	60 dload (0, 0)
	61 #9 (0, 0)
	62 dmul (0, 0)
	63 dload_3 (0, 0)
	64 dload (0, 0)
	65 #7 (0, 0)
	66 dmul (0, 0)
	67 dadd (0, 0)
	68 dload (0, 0)
	69 #7 (0, 0)
	70 dsub (0, 0)
	71 dload (0, 0)
	72 #5 (0, 0)
	73 dload (0, 0)
	74 #11 (0, 0)
	75 dmul (0, 0)
	76 dadd (0, 0)
	77 dload_3 (0, 0)
	78 dload (0, 0)
	79 #13 (0, 0)
	80 dmul (0, 0)
	81 dsub (0, 0)
	82 dload (0, 0)
	83 #5 (0, 0)
	84 dload (0, 0)
	85 #13 (0, 0)
	86 dmul (0, 0)
	87 dsub (0, 0)
	88 dload_3 (0, 0)
	89 dload (0, 0)
	90 #5 (0, 0)
	91 invokestatic (0, 0)
	92 org/apache/commons/math3/special/Beta.logBeta:(DD)D (0, 0)
	94 dsub (0, 0)
	95 dreturn (0, 0)

Method: cumulativeProbability
	0 dload_1 (1, 1)
	1 dconst_0 (1, 1)
	2 dcmpg (1, 1)
	3 ifgt (1, 1)
	4 8 (1, 1)
	6 dconst_0 (1, 1)
	7 dstore_3 (1, 1)
	8 goto (1, 1)
	9 43 (1, 1)
	11 aload_0 (1, 2)
	12 getfield (1, 2)
	13 org/apache/commons/math3/distribution/FDistribution.numeratorDegreesOfFreedom:D (1, 2)
	15 dstore (1, 2)
	16 #5 (1, 2)
	17 aload_0 (1, 2)
	18 getfield (1, 2)
	19 org/apache/commons/math3/distribution/FDistribution.denominatorDegreesOfFreedom:D (1, 2)
	21 dstore (1, 2)
	22 #7 (1, 2)
	23 dload (1, 2)
	24 #5 (1, 2)
	25 dload_1 (1, 2)
	26 dmul (1, 2)
	27 dload (1, 2)
	28 #7 (1, 2)
	29 dload (1, 2)
	30 #5 (1, 2)
	31 dload_1 (1, 2)
	32 dmul (1, 2)
	33 dadd (1, 2)
	34 ddiv (1, 2)
	35 ldc2_w (1, 2)
	36 0.5 (1, 2)
	38 dload (1, 2)
	39 #5 (1, 2)
	40 dmul (1, 2)
	41 ldc2_w (1, 2)
	42 0.5 (1, 2)
	44 dload (1, 2)
	45 #7 (1, 2)
	46 dmul (1, 2)
	47 invokestatic (1, 2)
	48 org/apache/commons/math3/special/Beta.regularizedBeta:(DDD)D (1, 2)
	50 dstore_3 (1, 2)
	51 dload_3 (0, 0)
	52 dreturn (0, 0)

Method: getNumeratorDegreesOfFreedom
	0 aload_0 (0, 0)
	1 getfield (0, 0)
	2 org/apache/commons/math3/distribution/FDistribution.numeratorDegreesOfFreedom:D (0, 0)
	4 dreturn (0, 0)

Method: getDenominatorDegreesOfFreedom
	0 aload_0 (0, 0)
	1 getfield (0, 0)
	2 org/apache/commons/math3/distribution/FDistribution.denominatorDegreesOfFreedom:D (0, 0)
	4 dreturn (0, 0)

Method: getSolverAbsoluteAccuracy
	0 aload_0 (0, 0)
	1 getfield (0, 0)
	2 org/apache/commons/math3/distribution/FDistribution.solverAbsoluteAccuracy:D (0, 0)
	4 dreturn (0, 0)

Method: getNumericalMean
	0 aload_0 (0, 0)
	1 invokevirtual (0, 0)
	2 org/apache/commons/math3/distribution/FDistribution.getDenominatorDegreesOfFreedom:()D (0, 0)
	4 dstore_1 (0, 0)
	5 dload_1 (1, 1)
	6 ldc2_w (1, 1)
	7 2.0 (1, 1)
	9 dcmpl (1, 1)
	10 ifle (1, 1)
	11 11 (1, 1)
	13 dload_1 (1, 1)
	14 dload_1 (1, 1)
	15 ldc2_w (1, 1)
	16 2.0 (1, 1)
	18 dsub (1, 1)
	19 ddiv (1, 1)
	20 dreturn (1, 1)
	21 ldc2_w (0, 0)
	22 nan (0, 0)
	24 dreturn (0, 0)

Method: getNumericalVariance
	0 aload_0 (1, 1)
	1 getfield (1, 1)
	2 org/apache/commons/math3/distribution/FDistribution.numericalVarianceIsCalculated:Z (1, 1)
	4 ifne (1, 1)
	5 16 (1, 1)
	7 aload_0 (1, 1)
	8 aload_0 (1, 1)
	9 invokevirtual (1, 1)
	10 org/apache/commons/math3/distribution/FDistribution.calculateNumericalVariance:()D (1, 1)
	12 putfield (1, 1)
	13 org/apache/commons/math3/distribution/FDistribution.numericalVariance:D (1, 1)
	15 aload_0 (1, 1)
	16 iconst_1 (1, 1)
	17 putfield (1, 1)
	18 org/apache/commons/math3/distribution/FDistribution.numericalVarianceIsCalculated:Z (1, 1)
	20 aload_0 (0, 0)
	21 getfield (0, 0)
	22 org/apache/commons/math3/distribution/FDistribution.numericalVariance:D (0, 0)
	24 dreturn (0, 0)

Method: calculateNumericalVariance
	0 aload_0 (0, 0)
	1 invokevirtual (0, 0)
	2 org/apache/commons/math3/distribution/FDistribution.getDenominatorDegreesOfFreedom:()D (0, 0)
	4 dstore_1 (0, 0)
	5 dload_1 (1, 1)
	6 ldc2_w (1, 1)
	7 4.0 (1, 1)
	9 dcmpl (1, 1)
	10 ifle (1, 1)
	11 45 (1, 1)
	13 aload_0 (1, 1)
	14 invokevirtual (1, 1)
	15 org/apache/commons/math3/distribution/FDistribution.getNumeratorDegreesOfFreedom:()D (1, 1)
	17 dstore_3 (1, 1)
	18 dload_1 (1, 1)
	19 ldc2_w (1, 1)
	20 2.0 (1, 1)
	22 dsub (1, 1)
	23 dstore (1, 1)
	24 #5 (1, 1)
	25 ldc2_w (1, 1)
	26 2.0 (1, 1)
	28 dload_1 (1, 1)
	29 dload_1 (1, 1)
	30 dmul (1, 1)
	31 dmul (1, 1)
	32 dload_3 (1, 1)
	33 dload_1 (1, 1)
	34 dadd (1, 1)
	35 ldc2_w (1, 1)
	36 2.0 (1, 1)
	38 dsub (1, 1)
	39 dmul (1, 1)
	40 dload_3 (1, 1)
	41 dload (1, 1)
	42 #5 (1, 1)
	43 dload (1, 1)
	44 #5 (1, 1)
	45 dmul (1, 1)
	46 dmul (1, 1)
	47 dload_1 (1, 1)
	48 ldc2_w (1, 1)
	49 4.0 (1, 1)
	51 dsub (1, 1)
	52 dmul (1, 1)
	53 ddiv (1, 1)
	54 dreturn (1, 1)
	55 ldc2_w (0, 0)
	56 nan (0, 0)
	58 dreturn (0, 0)

Method: getSupportLowerBound
	0 dconst_0 (0, 0)
	1 dreturn (0, 0)

Method: getSupportUpperBound
	0 ldc2_w (0, 0)
	1 inf (0, 0)
	3 dreturn (0, 0)

Method: isSupportLowerBoundInclusive
	0 iconst_0 (0, 0)
	1 ireturn (0, 0)

Method: isSupportUpperBoundInclusive
	0 iconst_0 (0, 0)
	1 ireturn (0, 0)

Method: isSupportConnected
	0 iconst_1 (0, 0)
	1 ireturn (0, 0)

