Method: <init>
	0 aload_0 (0, 0)
	1 aload_1 (0, 0)
	2 invokespecial (0, 0)
	3 org/apache/commons/math3/distribution/AbstractRealDistribution.<init>:(Lorg/apache/commons/math3/random/RandomGenerator;)V (0, 0)
	5 dload_2 (1, 1)
	6 dconst_0 (1, 1)
	7 dcmpg (1, 1)
	8 ifgt (1, 1)
	9 18 (1, 1)
	11 new (1, 1)
	12 org/apache/commons/math3/exception/NotStrictlyPositiveException (1, 1)
	14 dup (1, 1)
	15 getstatic (1, 1)
	16 org/apache/commons/math3/exception/util/LocalizedFormats.SHAPE:Lorg/apache/commons/math3/exception/util/LocalizedFormats; (1, 1)
	18 dload_2 (1, 1)
	19 invokestatic (1, 1)
	20 java/lang/Double.valueOf:(D)Ljava/lang/Double; (1, 1)
	22 invokespecial (1, 1)
	23 org/apache/commons/math3/exception/NotStrictlyPositiveException.<init>:(Lorg/apache/commons/math3/exception/util/Localizable;Ljava/lang/Number;)V (1, 1)
	25 athrow (1, 1)
	26 dload (1, 1)
	27 #4 (1, 1)
	28 dconst_0 (1, 1)
	29 dcmpg (1, 1)
	30 ifgt (1, 1)
	31 19 (1, 1)
	33 new (1, 1)
	34 org/apache/commons/math3/exception/NotStrictlyPositiveException (1, 1)
	36 dup (1, 1)
	37 getstatic (1, 1)
	38 org/apache/commons/math3/exception/util/LocalizedFormats.SCALE:Lorg/apache/commons/math3/exception/util/LocalizedFormats; (1, 1)
	40 dload (1, 1)
	41 #4 (1, 1)
	42 invokestatic (1, 1)
	43 java/lang/Double.valueOf:(D)Ljava/lang/Double; (1, 1)
	45 invokespecial (1, 1)
	46 org/apache/commons/math3/exception/NotStrictlyPositiveException.<init>:(Lorg/apache/commons/math3/exception/util/Localizable;Ljava/lang/Number;)V (1, 1)
	48 athrow (1, 1)
	49 aload_0 (0, 0)
	50 dload_2 (0, 0)
	51 putfield (0, 0)
	52 org/apache/commons/math3/distribution/GammaDistribution.shape:D (0, 0)
	54 aload_0 (0, 0)
	55 dload (0, 0)
	56 #4 (0, 0)
	57 putfield (0, 0)
	58 org/apache/commons/math3/distribution/GammaDistribution.scale:D (0, 0)
	60 aload_0 (0, 0)
	61 dload (0, 0)
	62 #6 (0, 0)
	63 putfield (0, 0)
	64 org/apache/commons/math3/distribution/GammaDistribution.solverAbsoluteAccuracy:D (0, 0)
	66 aload_0 (0, 1)
	67 dload_2 (0, 1)
	68 ldc2_w (0, 1)
	69 4.7421875 (0, 1)
	71 dadd (0, 1)
	72 ldc2_w (0, 1)
	73 0.5 (0, 1)
	75 dadd (0, 1)
	76 putfield (0, 1)
	77 org/apache/commons/math3/distribution/GammaDistribution.shiftedShape:D (0, 1)
	79 ldc2_w (0, 1)
	80 2.718281828459045 (0, 1)
	82 ldc2_w (0, 1)
	83 6.283185307179586 (0, 1)
	85 aload_0 (0, 1)
	86 getfield (0, 1)
	87 org/apache/commons/math3/distribution/GammaDistribution.shiftedShape:D (0, 1)
	89 dmul (0, 1)
	90 ddiv (0, 1)
	91 dstore (0, 1)
	92 #8 (0, 1)
	93 aload_0 (0, 1)
	94 dload_2 (0, 1)
	95 dload (0, 1)
	96 #8 (0, 1)
	97 invokestatic (0, 1)
	98 org/apache/commons/math3/util/FastMath.sqrt:(D)D (0, 1)
	100 dmul (0, 1)
	101 dload_2 (0, 1)
	102 invokestatic (0, 1)
	103 org/apache/commons/math3/special/Gamma.lanczos:(D)D (0, 1)
	105 ddiv (0, 1)
	106 putfield (0, 1)
	107 org/apache/commons/math3/distribution/GammaDistribution.densityPrefactor2:D (0, 1)
	109 aload_0 (0, 1)
	110 dload_2 (0, 1)
	111 invokestatic (0, 1)
	112 org/apache/commons/math3/util/FastMath.log:(D)D (0, 1)
	114 ldc2_w (0, 1)
	115 0.5 (0, 1)
	117 dload (0, 1)
	118 #8 (0, 1)
	119 invokestatic (0, 1)
	120 org/apache/commons/math3/util/FastMath.log:(D)D (0, 1)
	122 dmul (0, 1)
	123 dadd (0, 1)
	124 dload_2 (0, 1)
	125 invokestatic (0, 1)
	126 org/apache/commons/math3/special/Gamma.lanczos:(D)D (0, 1)
	128 invokestatic (0, 1)
	129 org/apache/commons/math3/util/FastMath.log:(D)D (0, 1)
	131 dsub (0, 1)
	132 putfield (0, 1)
	133 org/apache/commons/math3/distribution/GammaDistribution.logDensityPrefactor2:D (0, 1)
	135 aload_0 (0, 1)
	136 aload_0 (0, 1)
	137 getfield (0, 1)
	138 org/apache/commons/math3/distribution/GammaDistribution.densityPrefactor2:D (0, 1)
	140 dload (0, 1)
	141 #4 (0, 1)
	142 ddiv (0, 1)
	143 aload_0 (0, 1)
	144 getfield (0, 1)
	145 org/apache/commons/math3/distribution/GammaDistribution.shiftedShape:D (0, 1)
	147 dload_2 (0, 1)
	148 dneg (0, 1)
	149 invokestatic (0, 1)
	150 org/apache/commons/math3/util/FastMath.pow:(DD)D (0, 1)
	152 dmul (0, 1)
	153 dload_2 (0, 1)
	154 ldc2_w (0, 1)
	155 4.7421875 (0, 1)
	157 dadd (0, 1)
	158 invokestatic (0, 1)
	159 org/apache/commons/math3/util/FastMath.exp:(D)D (0, 1)
	161 dmul (0, 1)
	162 putfield (0, 1)
	163 org/apache/commons/math3/distribution/GammaDistribution.densityPrefactor1:D (0, 1)
	165 aload_0 (0, 1)
	166 aload_0 (0, 1)
	167 getfield (0, 1)
	168 org/apache/commons/math3/distribution/GammaDistribution.logDensityPrefactor2:D (0, 1)
	170 dload (0, 1)
	171 #4 (0, 1)
	172 invokestatic (0, 1)
	173 org/apache/commons/math3/util/FastMath.log:(D)D (0, 1)
	175 dsub (0, 1)
	176 aload_0 (0, 1)
	177 getfield (0, 1)
	178 org/apache/commons/math3/distribution/GammaDistribution.shiftedShape:D (0, 1)
	180 invokestatic (0, 1)
	181 org/apache/commons/math3/util/FastMath.log:(D)D (0, 1)
	183 dload_2 (0, 1)
	184 dmul (0, 1)
	185 dsub (0, 1)
	186 dload_2 (0, 1)
	187 dadd (0, 1)
	188 ldc2_w (0, 1)
	189 4.7421875 (0, 1)
	191 dadd (0, 1)
	192 putfield (0, 1)
	193 org/apache/commons/math3/distribution/GammaDistribution.logDensityPrefactor1:D (0, 1)
	195 aload_0 (0, 1)
	196 dload_2 (0, 1)
	197 ldc2_w (0, 1)
	198 4.7421875 (0, 1)
	200 dadd (0, 1)
	201 ldc2_w (0, 1)
	202 1.7976931348623157e+308 (0, 1)
	204 invokestatic (0, 1)
	205 org/apache/commons/math3/util/FastMath.log:(D)D (0, 1)
	207 dsub (0, 1)
	208 putfield (0, 1)
	209 org/apache/commons/math3/distribution/GammaDistribution.minY:D (0, 1)
	211 aload_0 (0, 1)
	212 ldc2_w (0, 1)
	213 1.7976931348623157e+308 (0, 1)
	215 invokestatic (0, 1)
	216 org/apache/commons/math3/util/FastMath.log:(D)D (0, 1)
	218 dload_2 (0, 1)
	219 dconst_1 (0, 1)
	220 dsub (0, 1)
	221 ddiv (0, 1)
	222 putfield (0, 1)
	223 org/apache/commons/math3/distribution/GammaDistribution.maxLogY:D (0, 1)
	225 return (0, 1)

Method: getAlpha
	0 aload_0 (0, 0)
	1 getfield (0, 0)
	2 org/apache/commons/math3/distribution/GammaDistribution.shape:D (0, 0)
	4 dreturn (0, 0)

Method: getShape
	0 aload_0 (0, 0)
	1 getfield (0, 0)
	2 org/apache/commons/math3/distribution/GammaDistribution.shape:D (0, 0)
	4 dreturn (0, 0)

Method: getBeta
	0 aload_0 (0, 0)
	1 getfield (0, 0)
	2 org/apache/commons/math3/distribution/GammaDistribution.scale:D (0, 0)
	4 dreturn (0, 0)

Method: getScale
	0 aload_0 (0, 0)
	1 getfield (0, 0)
	2 org/apache/commons/math3/distribution/GammaDistribution.scale:D (0, 0)
	4 dreturn (0, 0)

Method: density
	0 dload_1 (1, 1)
	1 dconst_0 (1, 1)
	2 dcmpg (1, 1)
	3 ifge (1, 1)
	4 5 (1, 1)
	6 dconst_0 (1, 1)
	7 dreturn (1, 1)
	8 dload_1 (0, 0)
	9 aload_0 (0, 0)
	10 getfield (0, 0)
	11 org/apache/commons/math3/distribution/GammaDistribution.scale:D (0, 0)
	13 ddiv (0, 0)
	14 dstore_3 (0, 0)
	15 dload_3 (1, 1)
	16 aload_0 (1, 1)
	17 getfield (1, 1)
	18 org/apache/commons/math3/distribution/GammaDistribution.minY:D (1, 1)
	20 dcmpg (1, 1)
	21 ifle (1, 1)
	22 15 (1, 1)
	24 dload_3 (1, 1)
	25 invokestatic (1, 1)
	26 org/apache/commons/math3/util/FastMath.log:(D)D (1, 1)
	28 aload_0 (1, 1)
	29 getfield (1, 1)
	30 org/apache/commons/math3/distribution/GammaDistribution.maxLogY:D (1, 1)
	32 dcmpl (1, 1)
	33 iflt (1, 1)
	34 64 (1, 1)
	36 dload_3 (1, 1)
	37 aload_0 (1, 1)
	38 getfield (1, 1)
	39 org/apache/commons/math3/distribution/GammaDistribution.shiftedShape:D (1, 1)
	41 dsub (1, 1)
	42 aload_0 (1, 1)
	43 getfield (1, 1)
	44 org/apache/commons/math3/distribution/GammaDistribution.shiftedShape:D (1, 1)
	46 ddiv (1, 1)
	47 dstore (1, 1)
	48 #5 (1, 1)
	49 aload_0 (1, 1)
	50 getfield (1, 1)
	51 org/apache/commons/math3/distribution/GammaDistribution.shape:D (1, 1)
	53 dload (1, 1)
	54 #5 (1, 1)
	55 invokestatic (1, 1)
	56 org/apache/commons/math3/util/FastMath.log1p:(D)D (1, 1)
	58 dload (1, 1)
	59 #5 (1, 1)
	60 dsub (1, 1)
	61 dmul (1, 1)
	62 dstore (1, 1)
	63 #7 (1, 1)
	64 dload_3 (1, 1)
	65 dneg (1, 1)
	66 ldc2_w (1, 1)
	67 5.2421875 (1, 1)
	69 dmul (1, 1)
	70 aload_0 (1, 1)
	71 getfield (1, 1)
	72 org/apache/commons/math3/distribution/GammaDistribution.shiftedShape:D (1, 1)
	74 ddiv (1, 1)
	75 ldc2_w (1, 1)
	76 4.7421875 (1, 1)
	78 dadd (1, 1)
	79 dload (1, 1)
	80 #7 (1, 1)
	81 dadd (1, 1)
	82 dstore (1, 1)
	83 #9 (1, 1)
	84 aload_0 (1, 1)
	85 getfield (1, 1)
	86 org/apache/commons/math3/distribution/GammaDistribution.densityPrefactor2:D (1, 1)
	88 dload_1 (1, 1)
	89 ddiv (1, 1)
	90 dload (1, 1)
	91 #9 (1, 1)
	92 invokestatic (1, 1)
	93 org/apache/commons/math3/util/FastMath.exp:(D)D (1, 1)
	95 dmul (1, 1)
	96 dreturn (1, 1)
	97 aload_0 (0, 0)
	98 getfield (0, 0)
	99 org/apache/commons/math3/distribution/GammaDistribution.densityPrefactor1:D (0, 0)
	101 dload_3 (0, 0)
	102 dneg (0, 0)
	103 invokestatic (0, 0)
	104 org/apache/commons/math3/util/FastMath.exp:(D)D (0, 0)
	106 dmul (0, 0)
	107 dload_3 (0, 0)
	108 aload_0 (0, 0)
	109 getfield (0, 0)
	110 org/apache/commons/math3/distribution/GammaDistribution.shape:D (0, 0)
	112 dconst_1 (0, 0)
	113 dsub (0, 0)
	114 invokestatic (0, 0)
	115 org/apache/commons/math3/util/FastMath.pow:(DD)D (0, 0)
	117 dmul (0, 0)
	118 dreturn (0, 0)

Method: logDensity
	0 dload_1 (1, 1)
	1 dconst_0 (1, 1)
	2 dcmpg (1, 1)
	3 ifge (1, 1)
	4 7 (1, 1)
	6 ldc2_w (1, 1)
	7 -inf (1, 1)
	9 dreturn (1, 1)
	10 dload_1 (0, 0)
	11 aload_0 (0, 0)
	12 getfield (0, 0)
	13 org/apache/commons/math3/distribution/GammaDistribution.scale:D (0, 0)
	15 ddiv (0, 0)
	16 dstore_3 (0, 0)
	17 dload_3 (1, 1)
	18 aload_0 (1, 1)
	19 getfield (1, 1)
	20 org/apache/commons/math3/distribution/GammaDistribution.minY:D (1, 1)
	22 dcmpg (1, 1)
	23 ifle (1, 1)
	24 15 (1, 1)
	26 dload_3 (1, 1)
	27 invokestatic (1, 1)
	28 org/apache/commons/math3/util/FastMath.log:(D)D (1, 1)
	30 aload_0 (1, 1)
	31 getfield (1, 1)
	32 org/apache/commons/math3/distribution/GammaDistribution.maxLogY:D (1, 1)
	34 dcmpl (1, 1)
	35 iflt (1, 1)
	36 64 (1, 1)
	38 dload_3 (1, 1)
	39 aload_0 (1, 1)
	40 getfield (1, 1)
	41 org/apache/commons/math3/distribution/GammaDistribution.shiftedShape:D (1, 1)
	43 dsub (1, 1)
	44 aload_0 (1, 1)
	45 getfield (1, 1)
	46 org/apache/commons/math3/distribution/GammaDistribution.shiftedShape:D (1, 1)
	48 ddiv (1, 1)
	49 dstore (1, 1)
	50 #5 (1, 1)
	51 aload_0 (1, 1)
	52 getfield (1, 1)
	53 org/apache/commons/math3/distribution/GammaDistribution.shape:D (1, 1)
	55 dload (1, 1)
	56 #5 (1, 1)
	57 invokestatic (1, 1)
	58 org/apache/commons/math3/util/FastMath.log1p:(D)D (1, 1)
	60 dload (1, 1)
	61 #5 (1, 1)
	62 dsub (1, 1)
	63 dmul (1, 1)
	64 dstore (1, 1)
	65 #7 (1, 1)
	66 dload_3 (1, 1)
	67 dneg (1, 1)
	68 ldc2_w (1, 1)
	69 5.2421875 (1, 1)
	71 dmul (1, 1)
	72 aload_0 (1, 1)
	73 getfield (1, 1)
	74 org/apache/commons/math3/distribution/GammaDistribution.shiftedShape:D (1, 1)
	76 ddiv (1, 1)
	77 ldc2_w (1, 1)
	78 4.7421875 (1, 1)
	80 dadd (1, 1)
	81 dload (1, 1)
	82 #7 (1, 1)
	83 dadd (1, 1)
	84 dstore (1, 1)
	85 #9 (1, 1)
	86 aload_0 (1, 1)
	87 getfield (1, 1)
	88 org/apache/commons/math3/distribution/GammaDistribution.logDensityPrefactor2:D (1, 1)
	90 dload_1 (1, 1)
	91 invokestatic (1, 1)
	92 org/apache/commons/math3/util/FastMath.log:(D)D (1, 1)
	94 dsub (1, 1)
	95 dload (1, 1)
	96 #9 (1, 1)
	97 dadd (1, 1)
	98 dreturn (1, 1)
	99 aload_0 (0, 0)
	100 getfield (0, 0)
	101 org/apache/commons/math3/distribution/GammaDistribution.logDensityPrefactor1:D (0, 0)
	103 dload_3 (0, 0)
	104 dsub (0, 0)
	105 dload_3 (0, 0)
	106 invokestatic (0, 0)
	107 org/apache/commons/math3/util/FastMath.log:(D)D (0, 0)
	109 aload_0 (0, 0)
	110 getfield (0, 0)
	111 org/apache/commons/math3/distribution/GammaDistribution.shape:D (0, 0)
	113 dconst_1 (0, 0)
	114 dsub (0, 0)
	115 dmul (0, 0)
	116 dadd (0, 0)
	117 dreturn (0, 0)

Method: cumulativeProbability
	0 dload_1 (1, 1)
	1 dconst_0 (1, 1)
	2 dcmpg (1, 1)
	3 ifgt (1, 1)
	4 8 (1, 1)
	6 dconst_0 (1, 1)
	7 dstore_3 (1, 1)
	8 goto (1, 1)
	9 17 (1, 1)
	11 aload_0 (1, 2)
	12 getfield (1, 2)
	13 org/apache/commons/math3/distribution/GammaDistribution.shape:D (1, 2)
	15 dload_1 (1, 2)
	16 aload_0 (1, 2)
	17 getfield (1, 2)
	18 org/apache/commons/math3/distribution/GammaDistribution.scale:D (1, 2)
	20 ddiv (1, 2)
	21 invokestatic (1, 2)
	22 org/apache/commons/math3/special/Gamma.regularizedGammaP:(DD)D (1, 2)
	24 dstore_3 (1, 2)
	25 dload_3 (0, 0)
	26 dreturn (0, 0)

Method: getSolverAbsoluteAccuracy
	0 aload_0 (0, 0)
	1 getfield (0, 0)
	2 org/apache/commons/math3/distribution/GammaDistribution.solverAbsoluteAccuracy:D (0, 0)
	4 dreturn (0, 0)

Method: getNumericalMean
	0 aload_0 (0, 0)
	1 getfield (0, 0)
	2 org/apache/commons/math3/distribution/GammaDistribution.shape:D (0, 0)
	4 aload_0 (0, 0)
	5 getfield (0, 0)
	6 org/apache/commons/math3/distribution/GammaDistribution.scale:D (0, 0)
	8 dmul (0, 0)
	9 dreturn (0, 0)

Method: getNumericalVariance
	0 aload_0 (0, 0)
	1 getfield (0, 0)
	2 org/apache/commons/math3/distribution/GammaDistribution.shape:D (0, 0)
	4 aload_0 (0, 0)
	5 getfield (0, 0)
	6 org/apache/commons/math3/distribution/GammaDistribution.scale:D (0, 0)
	8 dmul (0, 0)
	9 aload_0 (0, 0)
	10 getfield (0, 0)
	11 org/apache/commons/math3/distribution/GammaDistribution.scale:D (0, 0)
	13 dmul (0, 0)
	14 dreturn (0, 0)

Method: getSupportLowerBound
	0 dconst_0 (0, 0)
	1 dreturn (0, 0)

Method: getSupportUpperBound
	0 ldc2_w (0, 0)
	1 inf (0, 0)
	3 dreturn (0, 0)

Method: isSupportLowerBoundInclusive
	0 iconst_1 (0, 0)
	1 ireturn (0, 0)

Method: isSupportUpperBoundInclusive
	0 iconst_0 (0, 0)
	1 ireturn (0, 0)

Method: isSupportConnected
	0 iconst_1 (0, 0)
	1 ireturn (0, 0)

Method: sample
	0 aload_0 (1, 1)
	1 getfield (1, 1)
	2 org/apache/commons/math3/distribution/GammaDistribution.shape:D (1, 1)
	4 dconst_1 (1, 1)
	5 dcmpg (1, 1)
	6 ifge (1, 1)
	7 140 (1, 1)
	9 aload_0 (2, 3)
	10 getfield (2, 3)
	11 org/apache/commons/math3/distribution/GammaDistribution.random:Lorg/apache/commons/math3/random/RandomGenerator; (2, 3)
	13 invokeinterface (2, 3)
	14 org/apache/commons/math3/random/RandomGenerator.nextGaussian:()D (2, 3)
	16 0 (2, 3)
	18 dstore_1 (2, 3)
	19 dconst_1 (2, 3)
	20 aload_0 (2, 3)
	21 getfield (2, 3)
	22 org/apache/commons/math3/distribution/GammaDistribution.shape:D (2, 3)
	24 ldc2_w (2, 3)
	25 2.718281828459045 (2, 3)
	27 ddiv (2, 3)
	28 dadd (2, 3)
	29 dstore_3 (2, 3)
	30 dload_3 (2, 3)
	31 dload_1 (2, 3)
	32 dmul (2, 3)
	33 dstore (2, 3)
	34 #5 (2, 3)
	35 dload (3, 1)
	36 #5 (3, 1)
	37 dconst_1 (3, 1)
	38 dcmpg (3, 1)
	39 ifgt (3, 1)
	40 50 (3, 1)
	42 dload (3, 1)
	43 #5 (3, 1)
	44 dconst_1 (3, 1)
	45 aload_0 (3, 1)
	46 getfield (3, 1)
	47 org/apache/commons/math3/distribution/GammaDistribution.shape:D (3, 1)
	49 ddiv (3, 1)
	50 invokestatic (3, 1)
	51 org/apache/commons/math3/util/FastMath.pow:(DD)D (3, 1)
	53 dstore (3, 1)
	54 #7 (3, 1)
	55 aload_0 (3, 1)
	56 getfield (3, 1)
	57 org/apache/commons/math3/distribution/GammaDistribution.random:Lorg/apache/commons/math3/random/RandomGenerator; (3, 1)
	59 invokeinterface (3, 1)
	60 org/apache/commons/math3/random/RandomGenerator.nextGaussian:()D (3, 1)
	62 0 (3, 1)
	64 dstore (3, 1)
	65 #9 (3, 1)
	66 dload (4, 1)
	67 #9 (4, 1)
	68 dload (4, 1)
	69 #7 (4, 1)
	70 dneg (4, 1)
	71 invokestatic (4, 1)
	72 org/apache/commons/math3/util/FastMath.exp:(D)D (4, 1)
	74 dcmpl (4, 1)
	75 ifle (4, 1)
	76 6 (4, 1)
	78 goto (4, 1)
	79 -69 (4, 1)
	81 aload_0 (4, 2)
	82 getfield (4, 2)
	83 org/apache/commons/math3/distribution/GammaDistribution.scale:D (4, 2)
	85 dload (4, 2)
	86 #7 (4, 2)
	87 dmul (4, 2)
	88 dreturn (4, 2)
	89 ldc2_w (3, 2)
	90 -1.0 (3, 2)
	92 dload_3 (3, 2)
	93 dload (3, 2)
	94 #5 (3, 2)
	95 dsub (3, 2)
	96 aload_0 (3, 2)
	97 getfield (3, 2)
	98 org/apache/commons/math3/distribution/GammaDistribution.shape:D (3, 2)
	100 ddiv (3, 2)
	101 invokestatic (3, 2)
	102 org/apache/commons/math3/util/FastMath.log:(D)D (3, 2)
	104 dmul (3, 2)
	105 dstore (3, 2)
	106 #7 (3, 2)
	107 aload_0 (3, 2)
	108 getfield (3, 2)
	109 org/apache/commons/math3/distribution/GammaDistribution.random:Lorg/apache/commons/math3/random/RandomGenerator; (3, 2)
	111 invokeinterface (3, 2)
	112 org/apache/commons/math3/random/RandomGenerator.nextGaussian:()D (3, 2)
	114 0 (3, 2)
	116 dstore (3, 2)
	117 #9 (3, 2)
	118 dload (4, 1)
	119 #9 (4, 1)
	120 dload (4, 1)
	121 #7 (4, 1)
	122 aload_0 (4, 1)
	123 getfield (4, 1)
	124 org/apache/commons/math3/distribution/GammaDistribution.shape:D (4, 1)
	126 dconst_1 (4, 1)
	127 dsub (4, 1)
	128 invokestatic (4, 1)
	129 org/apache/commons/math3/util/FastMath.pow:(DD)D (4, 1)
	131 dcmpl (4, 1)
	132 ifle (4, 1)
	133 6 (4, 1)
	135 goto (4, 1)
	136 -126 (4, 1)
	138 aload_0 (4, 2)
	139 getfield (4, 2)
	140 org/apache/commons/math3/distribution/GammaDistribution.scale:D (4, 2)
	142 dload (4, 2)
	143 #7 (4, 2)
	144 dmul (4, 2)
	145 dreturn (4, 2)
	146 aload_0 (0, 0)
	147 getfield (0, 0)
	148 org/apache/commons/math3/distribution/GammaDistribution.shape:D (0, 0)
	150 ldc2_w (0, 0)
	151 0.3333333333333333 (0, 0)
	153 dsub (0, 0)
	154 dstore_1 (0, 0)
	155 dconst_1 (0, 0)
	156 ldc2_w (0, 0)
	157 3.0 (0, 0)
	159 dload_1 (0, 0)
	160 invokestatic (0, 0)
	161 org/apache/commons/math3/util/FastMath.sqrt:(D)D (0, 0)
	163 dmul (0, 0)
	164 ddiv (0, 0)
	165 dstore_3 (0, 0)
	166 aload_0 (1, 3)
	167 getfield (1, 3)
	168 org/apache/commons/math3/distribution/GammaDistribution.random:Lorg/apache/commons/math3/random/RandomGenerator; (1, 3)
	170 invokeinterface (1, 3)
	171 org/apache/commons/math3/random/RandomGenerator.org/apache/commons/math3/distribution/AbstractRealDistribution (1, 3)
	173 0 (1, 3)
	175 dstore (1, 3)
	176 #5 (1, 3)
	177 dconst_1 (1, 3)
	178 dload_3 (1, 3)
	179 dload (1, 3)
	180 #5 (1, 3)
	181 dmul (1, 3)
	182 dadd (1, 3)
	183 dconst_1 (1, 3)
	184 dload_3 (1, 3)
	185 dload (1, 3)
	186 #5 (1, 3)
	187 dmul (1, 3)
	188 dadd (1, 3)
	189 dmul (1, 3)
	190 dconst_1 (1, 3)
	191 dload_3 (1, 3)
	192 dload (1, 3)
	193 #5 (1, 3)
	194 dmul (1, 3)
	195 dadd (1, 3)
	196 dmul (1, 3)
	197 dstore (1, 3)
	198 #7 (1, 3)
	199 dload (2, 1)
	200 #7 (2, 1)
	201 dconst_0 (2, 1)
	202 dcmpg (2, 1)
	203 ifgt (2, 1)
	204 6 (2, 1)
	206 goto (2, 1)
	207 -40 (2, 1)
	209 dload (1, 3)
	210 #5 (1, 3)
	211 dload (1, 3)
	212 #5 (1, 3)
	213 dmul (1, 3)
	214 dstore (1, 3)
	215 #9 (1, 3)
	216 aload_0 (1, 3)
	217 getfield (1, 3)
	218 org/apache/commons/math3/distribution/GammaDistribution.random:Lorg/apache/commons/math3/random/RandomGenerator; (1, 3)
	220 invokeinterface (1, 3)
	221 org/apache/commons/math3/random/RandomGenerator.nextGaussian:()D (1, 3)
	223 0 (1, 3)
	225 dstore (1, 3)
	226 #11 (1, 3)
	227 dload (2, 1)
	228 #11 (2, 1)
	229 dconst_1 (2, 1)
	230 ldc2_w (2, 1)
	231 0.0331 (2, 1)
	233 dload (2, 1)
	234 #9 (2, 1)
	235 dmul (2, 1)
	236 dload (2, 1)
	237 #9 (2, 1)
	238 dmul (2, 1)
	239 dsub (2, 1)
	240 dcmpg (2, 1)
	241 ifge (2, 1)
	242 13 (2, 1)
	244 aload_0 (2, 1)
	245 getfield (2, 1)
	246 org/apache/commons/math3/distribution/GammaDistribution.scale:D (2, 1)
	248 dload_1 (2, 1)
	249 dmul (2, 1)
	250 dload (2, 1)
	251 #7 (2, 1)
	252 dmul (2, 1)
	253 dreturn (2, 1)
	254 dload (2, 1)
	255 #11 (2, 1)
	256 invokestatic (2, 1)
	257 org/apache/commons/math3/util/FastMath.log:(D)D (2, 1)
	259 ldc2_w (2, 1)
	260 0.5 (2, 1)
	262 dload (2, 1)
	263 #9 (2, 1)
	264 dmul (2, 1)
	265 dload_1 (2, 1)
	266 dconst_1 (2, 1)
	267 dload (2, 1)
	268 #7 (2, 1)
	269 dsub (2, 1)
	270 dload (2, 1)
	271 #7 (2, 1)
	272 invokestatic (2, 1)
	273 org/apache/commons/math3/util/FastMath.log:(D)D (2, 1)
	275 dadd (2, 1)
	276 dmul (2, 1)
	277 dadd (2, 1)
	278 dcmpg (2, 1)
	279 ifge (2, 1)
	280 13 (2, 1)
	282 aload_0 (2, 1)
	283 getfield (2, 1)
	284 org/apache/commons/math3/distribution/GammaDistribution.scale:D (2, 1)
	286 dload_1 (2, 1)
	287 dmul (2, 1)
	288 dload (2, 1)
	289 #7 (2, 1)
	290 dmul (2, 1)
	291 dreturn (2, 1)
	292 goto (0, 0)
	293 -126 (0, 0)

