Method: <init>
	0 aload_0 (0, 0)
	1 aload_1 (0, 0)
	2 invokespecial (0, 0)
	3 org/apache/commons/math3/distribution/AbstractIntegerDistribution.<init>:(Lorg/apache/commons/math3/random/RandomGenerator;)V (0, 0)
	5 aload_0 (0, 0)
	6 ldc2_w (0, 0)
	7 nan (0, 0)
	9 putfield (0, 0)
	10 org/apache/commons/math3/distribution/HypergeometricDistribution.numericalVariance:D (0, 0)
	12 aload_0 (0, 0)
	13 iconst_0 (0, 0)
	14 putfield (0, 0)
	15 org/apache/commons/math3/distribution/HypergeometricDistribution.numericalVarianceIsCalculated:Z (0, 0)
	17 iload_2 (10, 1)
	18 ifgt (10, 1)
	19 18 (10, 1)
	21 new (10, 1)
	22 org/apache/commons/math3/exception/NotStrictlyPositiveException (10, 1)
	24 dup (10, 1)
	25 getstatic (10, 1)
	26 org/apache/commons/math3/exception/util/LocalizedFormats.POPULATION_SIZE:Lorg/apache/commons/math3/exception/util/LocalizedFormats; (10, 1)
	28 iload_2 (10, 1)
	29 invokestatic (10, 1)
	30 java/lang/Integer.valueOf:(I)Ljava/lang/Integer; (10, 1)
	32 invokespecial (10, 1)
	33 org/apache/commons/math3/exception/NotStrictlyPositiveException.<init>:(Lorg/apache/commons/math3/exception/util/Localizable;Ljava/lang/Number;)V (10, 1)
	35 athrow (10, 1)
	36 iload_3 (10, 1)
	37 ifge (10, 1)
	38 18 (10, 1)
	40 new (10, 1)
	41 org/apache/commons/math3/exception/NotPositiveException (10, 1)
	43 dup (10, 1)
	44 getstatic (10, 1)
	45 org/apache/commons/math3/exception/util/LocalizedFormats.NUMBER_OF_SUCCESSES:Lorg/apache/commons/math3/exception/util/LocalizedFormats; (10, 1)
	47 iload_3 (10, 1)
	48 invokestatic (10, 1)
	49 java/lang/Integer.valueOf:(I)Ljava/lang/Integer; (10, 1)
	51 invokespecial (10, 1)
	52 org/apache/commons/math3/exception/NotPositiveException.<init>:(Lorg/apache/commons/math3/exception/util/Localizable;Ljava/lang/Number;)V (10, 1)
	54 athrow (10, 1)
	55 iload (10, 1)
	56 #4 (10, 1)
	57 ifge (10, 1)
	58 19 (10, 1)
	60 new (10, 1)
	61 org/apache/commons/math3/exception/NotPositiveException (10, 1)
	63 dup (10, 1)
	64 getstatic (10, 1)
	65 org/apache/commons/math3/exception/util/LocalizedFormats.NUMBER_OF_SAMPLES:Lorg/apache/commons/math3/exception/util/LocalizedFormats; (10, 1)
	67 iload (10, 1)
	68 #4 (10, 1)
	69 invokestatic (10, 1)
	70 java/lang/Integer.valueOf:(I)Ljava/lang/Integer; (10, 1)
	72 invokespecial (10, 1)
	73 org/apache/commons/math3/exception/NotPositiveException.<init>:(Lorg/apache/commons/math3/exception/util/Localizable;Ljava/lang/Number;)V (10, 1)
	75 athrow (10, 1)
	76 iload_3 (10, 1)
	77 iload_2 (10, 1)
	78 if_icmple (10, 1)
	79 23 (10, 1)
	81 new (10, 1)
	82 org/apache/commons/math3/exception/NumberIsTooLargeException (10, 1)
	84 dup (10, 1)
	85 getstatic (10, 1)
	86 org/apache/commons/math3/exception/util/LocalizedFormats.NUMBER_OF_SUCCESS_LARGER_THAN_POPULATION_SIZE:Lorg/apache/commons/math3/exception/util/LocalizedFormats; (10, 1)
	88 iload_3 (10, 1)
	89 invokestatic (10, 1)
	90 java/lang/Integer.valueOf:(I)Ljava/lang/Integer; (10, 1)
	92 iload_2 (10, 1)
	93 invokestatic (10, 1)
	94 java/lang/Integer.valueOf:(I)Ljava/lang/Integer; (10, 1)
	96 iconst_1 (10, 1)
	97 invokespecial (10, 1)
	98 org/apache/commons/math3/exception/NumberIsTooLargeException.<init>:(Lorg/apache/commons/math3/exception/util/Localizable;Ljava/lang/Number;Ljava/lang/Number;Z)V (10, 1)
	100 athrow (10, 1)
	101 iload (10, 1)
	102 #4 (10, 1)
	103 iload_2 (10, 1)
	104 if_icmple (10, 1)
	105 24 (10, 1)
	107 new (10, 1)
	108 org/apache/commons/math3/exception/NumberIsTooLargeException (10, 1)
	110 dup (10, 1)
	111 getstatic (10, 1)
	112 org/apache/commons/math3/exception/util/LocalizedFormats.SAMPLE_SIZE_LARGER_THAN_POPULATION_SIZE:Lorg/apache/commons/math3/exception/util/LocalizedFormats; (10, 1)
	114 iload (10, 1)
	115 #4 (10, 1)
	116 invokestatic (10, 1)
	117 java/lang/Integer.valueOf:(I)Ljava/lang/Integer; (10, 1)
	119 iload_2 (10, 1)
	120 invokestatic (10, 1)
	121 java/lang/Integer.valueOf:(I)Ljava/lang/Integer; (10, 1)
	123 iconst_1 (10, 1)
	124 invokespecial (10, 1)
	125 org/apache/commons/math3/exception/NumberIsTooLargeException.<init>:(Lorg/apache/commons/math3/exception/util/Localizable;Ljava/lang/Number;Ljava/lang/Number;Z)V (10, 1)
	127 athrow (10, 1)
	128 aload_0 (9, 1)
	129 iload_3 (9, 1)
	130 putfield (9, 1)
	131 org/apache/commons/math3/distribution/HypergeometricDistribution.numberOfSuccesses:I (9, 1)
	133 aload_0 (9, 1)
	134 iload_2 (9, 1)
	135 putfield (9, 1)
	136 org/apache/commons/math3/distribution/HypergeometricDistribution.populationSize:I (9, 1)
	138 aload_0 (9, 1)
	139 iload (9, 1)
	140 #4 (9, 1)
	141 putfield (9, 1)
	142 org/apache/commons/math3/distribution/HypergeometricDistribution.sampleSize:I (9, 1)
	144 return (0, 1)

Method: cumulativeProbability
	0 aload_0 (0, 0)
	1 aload_0 (0, 0)
	2 getfield (0, 0)
	3 org/apache/commons/math3/distribution/HypergeometricDistribution.populationSize:I (0, 0)
	5 aload_0 (0, 0)
	6 getfield (0, 0)
	7 org/apache/commons/math3/distribution/HypergeometricDistribution.numberOfSuccesses:I (0, 0)
	9 aload_0 (0, 0)
	10 getfield (0, 0)
	11 org/apache/commons/math3/distribution/HypergeometricDistribution.sampleSize:I (0, 0)
	13 invokespecial (0, 0)
	14 org/apache/commons/math3/distribution/HypergeometricDistribution.getDomain:(III)[I (0, 0)
	16 astore (0, 0)
	17 #4 (0, 0)
	18 iload_1 (1, 1)
	19 aload (1, 1)
	20 #4 (1, 1)
	21 iconst_0 (1, 1)
	22 iaload (1, 1)
	23 if_icmpge (1, 1)
	24 8 (1, 1)
	26 dconst_0 (1, 1)
	27 dstore_2 (1, 1)
	28 goto (1, 1)
	29 27 (1, 1)
	31 iload_1 (2, 1)
	32 aload (2, 1)
	33 #4 (2, 1)
	34 iconst_1 (2, 1)
	35 iaload (2, 1)
	36 if_icmplt (2, 1)
	37 8 (2, 1)
	39 dconst_1 (2, 1)
	40 dstore_2 (2, 1)
	41 goto (2, 1)
	42 14 (2, 1)
	44 aload_0 (3, 2)
	45 aload (3, 2)
	46 #4 (3, 2)
	47 iconst_0 (3, 2)
	48 iaload (3, 2)
	49 iload_1 (3, 2)
	50 iconst_1 (3, 2)
	51 invokespecial (3, 2)
	52 org/apache/commons/math3/distribution/HypergeometricDistribution.innerCumulativeProbability:(III)D (3, 2)
	54 dstore_2 (3, 2)
	55 dload_2 (0, 0)
	56 dreturn (0, 0)

Method: getDomain
	0 iconst_2 (0, 0)
	1 newarray (0, 0)
	2 10 (0, 0)
	3 dup (0, 0)
	4 iconst_0 (0, 0)
	5 aload_0 (0, 0)
	6 iload_1 (0, 0)
	7 iload_2 (0, 0)
	8 iload_3 (0, 0)
	9 invokespecial (0, 0)
	10 org/apache/commons/math3/distribution/HypergeometricDistribution.getLowerDomain:(III)I (0, 0)
	12 iastore (0, 0)
	13 dup (0, 0)
	14 iconst_1 (0, 0)
	15 aload_0 (0, 0)
	16 iload_2 (0, 0)
	17 iload_3 (0, 0)
	18 invokespecial (0, 0)
	19 org/apache/commons/math3/distribution/HypergeometricDistribution.getUpperDomain:(II)I (0, 0)
	21 iastore (0, 0)
	22 areturn (0, 0)

Method: getLowerDomain
	0 iconst_0 (0, 0)
	1 iload_2 (0, 0)
	2 iload_1 (0, 0)
	3 iload_3 (0, 0)
	4 isub (0, 0)
	5 isub (0, 0)
	6 invokestatic (0, 0)
	7 org/apache/commons/math3/util/FastMath.max:(II)I (0, 0)
	9 ireturn (0, 0)

Method: getNumberOfSuccesses
	0 aload_0 (0, 0)
	1 getfield (0, 0)
	2 org/apache/commons/math3/distribution/HypergeometricDistribution.numberOfSuccesses:I (0, 0)
	4 ireturn (0, 0)

Method: getPopulationSize
	0 aload_0 (0, 0)
	1 getfield (0, 0)
	2 org/apache/commons/math3/distribution/HypergeometricDistribution.populationSize:I (0, 0)
	4 ireturn (0, 0)

Method: getSampleSize
	0 aload_0 (0, 0)
	1 getfield (0, 0)
	2 org/apache/commons/math3/distribution/HypergeometricDistribution.sampleSize:I (0, 0)
	4 ireturn (0, 0)

Method: getUpperDomain
	0 iload_2 (0, 0)
	1 iload_1 (0, 0)
	2 invokestatic (0, 0)
	3 org/apache/commons/math3/util/FastMath.min:(II)I (0, 0)
	5 ireturn (0, 0)

Method: probability
	0 aload_0 (0, 0)
	1 iload_1 (0, 0)
	2 invokevirtual (0, 0)
	3 org/apache/commons/math3/distribution/HypergeometricDistribution.logProbability:(I)D (0, 0)
	5 dstore_2 (0, 0)
	6 dload_2 (0, 0)
	7 ldc2_w (0, 0)
	8 -inf (0, 0)
	10 dcmpl (0, 0)
	11 ifne (0, 0)
	12 7 (0, 0)
	14 dconst_0 (0, 0)
	15 goto (0, 0)
	16 7 (0, 0)
	18 dload_2 (0, 0)
	19 invokestatic (0, 0)
	20 org/apache/commons/math3/util/FastMath.exp:(D)D (0, 0)
	22 dreturn (0, 0)

Method: logProbability
	0 aload_0 (0, 0)
	1 aload_0 (0, 0)
	2 getfield (0, 0)
	3 org/apache/commons/math3/distribution/HypergeometricDistribution.populationSize:I (0, 0)
	5 aload_0 (0, 0)
	6 getfield (0, 0)
	7 org/apache/commons/math3/distribution/HypergeometricDistribution.numberOfSuccesses:I (0, 0)
	9 aload_0 (0, 0)
	10 getfield (0, 0)
	11 org/apache/commons/math3/distribution/HypergeometricDistribution.sampleSize:I (0, 0)
	13 invokespecial (0, 0)
	14 org/apache/commons/math3/distribution/HypergeometricDistribution.getDomain:(III)[I (0, 0)
	16 astore (0, 0)
	17 #4 (0, 0)
	18 iload_1 (1, 1)
	19 aload (1, 1)
	20 #4 (1, 1)
	21 iconst_0 (1, 1)
	22 iaload (1, 1)
	23 if_icmplt (1, 1)
	24 11 (1, 1)
	26 iload_1 (1, 1)
	27 aload (1, 1)
	28 #4 (1, 1)
	29 iconst_1 (1, 1)
	30 iaload (1, 1)
	31 if_icmple (1, 1)
	32 10 (1, 1)
	34 ldc2_w (1, 1)
	35 -inf (1, 1)
	37 dstore_2 (1, 1)
	38 goto (1, 1)
	39 98 (1, 1)
	41 aload_0 (2, 2)
	42 getfield (2, 2)
	43 org/apache/commons/math3/distribution/HypergeometricDistribution.sampleSize:I (2, 2)
	45 i2d (2, 2)
	46 aload_0 (2, 2)
	47 getfield (2, 2)
	48 org/apache/commons/math3/distribution/HypergeometricDistribution.populationSize:I (2, 2)
	50 i2d (2, 2)
	51 ddiv (2, 2)
	52 dstore (2, 2)
	53 #5 (2, 2)
	54 aload_0 (2, 2)
	55 getfield (2, 2)
	56 org/apache/commons/math3/distribution/HypergeometricDistribution.populationSize:I (2, 2)
	58 aload_0 (2, 2)
	59 getfield (2, 2)
	60 org/apache/commons/math3/distribution/HypergeometricDistribution.sampleSize:I (2, 2)
	62 isub (2, 2)
	63 i2d (2, 2)
	64 aload_0 (2, 2)
	65 getfield (2, 2)
	66 org/apache/commons/math3/distribution/HypergeometricDistribution.populationSize:I (2, 2)
	68 i2d (2, 2)
	69 ddiv (2, 2)
	70 dstore (2, 2)
	71 #7 (2, 2)
	72 iload_1 (2, 2)
	73 aload_0 (2, 2)
	74 getfield (2, 2)
	75 org/apache/commons/math3/distribution/HypergeometricDistribution.numberOfSuccesses:I (2, 2)
	77 dload (2, 2)
	78 #5 (2, 2)
	79 dload (2, 2)
	80 #7 (2, 2)
	81 invokestatic (2, 2)
	82 org/apache/commons/math3/distribution/SaddlePointExpansion.logBinomialProbability:(IIDD)D (2, 2)
	84 dstore (2, 2)
	85 #9 (2, 2)
	86 aload_0 (2, 2)
	87 getfield (2, 2)
	88 org/apache/commons/math3/distribution/HypergeometricDistribution.sampleSize:I (2, 2)
	90 iload_1 (2, 2)
	91 isub (2, 2)
	92 aload_0 (2, 2)
	93 getfield (2, 2)
	94 org/apache/commons/math3/distribution/HypergeometricDistribution.populationSize:I (2, 2)
	96 aload_0 (2, 2)
	97 getfield (2, 2)
	98 org/apache/commons/math3/distribution/HypergeometricDistribution.numberOfSuccesses:I (2, 2)
	100 isub (2, 2)
	101 dload (2, 2)
	102 #5 (2, 2)
	103 dload (2, 2)
	104 #7 (2, 2)
	105 invokestatic (2, 2)
	106 org/apache/commons/math3/distribution/SaddlePointExpansion.logBinomialProbability:(IIDD)D (2, 2)
	108 dstore (2, 2)
	109 #11 (2, 2)
	110 aload_0 (2, 2)
	111 getfield (2, 2)
	112 org/apache/commons/math3/distribution/HypergeometricDistribution.sampleSize:I (2, 2)
	114 aload_0 (2, 2)
	115 getfield (2, 2)
	116 org/apache/commons/math3/distribution/HypergeometricDistribution.populationSize:I (2, 2)
	118 dload (2, 2)
	119 #5 (2, 2)
	120 dload (2, 2)
	121 #7 (2, 2)
	122 invokestatic (2, 2)
	123 org/apache/commons/math3/distribution/SaddlePointExpansion.logBinomialProbability:(IIDD)D (2, 2)
	125 dstore (2, 2)
	126 #13 (2, 2)
	127 dload (2, 2)
	128 #9 (2, 2)
	129 dload (2, 2)
	130 #11 (2, 2)
	131 dadd (2, 2)
	132 dload (2, 2)
	133 #13 (2, 2)
	134 dsub (2, 2)
	135 dstore_2 (2, 2)
	136 dload_2 (0, 0)
	137 dreturn (0, 0)

Method: upperCumulativeProbability
	0 aload_0 (0, 0)
	1 aload_0 (0, 0)
	2 getfield (0, 0)
	3 org/apache/commons/math3/distribution/HypergeometricDistribution.populationSize:I (0, 0)
	5 aload_0 (0, 0)
	6 getfield (0, 0)
	7 org/apache/commons/math3/distribution/HypergeometricDistribution.numberOfSuccesses:I (0, 0)
	9 aload_0 (0, 0)
	10 getfield (0, 0)
	11 org/apache/commons/math3/distribution/HypergeometricDistribution.sampleSize:I (0, 0)
	13 invokespecial (0, 0)
	14 org/apache/commons/math3/distribution/HypergeometricDistribution.getDomain:(III)[I (0, 0)
	16 astore (0, 0)
	17 #4 (0, 0)
	18 iload_1 (1, 1)
	19 aload (1, 1)
	20 #4 (1, 1)
	21 iconst_0 (1, 1)
	22 iaload (1, 1)
	23 if_icmpgt (1, 1)
	24 8 (1, 1)
	26 dconst_1 (1, 1)
	27 dstore_2 (1, 1)
	28 goto (1, 1)
	29 27 (1, 1)
	31 iload_1 (2, 1)
	32 aload (2, 1)
	33 #4 (2, 1)
	34 iconst_1 (2, 1)
	35 iaload (2, 1)
	36 if_icmple (2, 1)
	37 8 (2, 1)
	39 dconst_0 (2, 1)
	40 dstore_2 (2, 1)
	41 goto (2, 1)
	42 14 (2, 1)
	44 aload_0 (3, 2)
	45 aload (3, 2)
	46 #4 (3, 2)
	47 iconst_1 (3, 2)
	48 iaload (3, 2)
	49 iload_1 (3, 2)
	50 iconst_m1 (3, 2)
	51 invokespecial (3, 2)
	52 org/apache/commons/math3/distribution/HypergeometricDistribution.innerCumulativeProbability:(III)D (3, 2)
	54 dstore_2 (3, 2)
	55 dload_2 (0, 0)
	56 dreturn (0, 0)

Method: innerCumulativeProbability
	0 aload_0 (0, 0)
	1 iload_1 (0, 0)
	2 invokevirtual (0, 0)
	3 org/apache/commons/math3/distribution/HypergeometricDistribution.probability:(I)D (0, 0)
	5 dstore (0, 0)
	6 #4 (0, 0)
	7 iload_1 (1, 3)
	8 iload_2 (1, 3)
	9 if_icmpeq (1, 3)
	10 20 (1, 3)
	12 iload_1 (1, 3)
	13 iload_3 (1, 3)
	14 iadd (1, 3)
	15 istore_1 (1, 3)
	16 dload (1, 3)
	17 #4 (1, 3)
	18 aload_0 (1, 3)
	19 iload_1 (1, 3)
	20 invokevirtual (1, 3)
	21 org/apache/commons/math3/distribution/HypergeometricDistribution.probability:(I)D (1, 3)
	23 dadd (1, 3)
	24 dstore (1, 3)
	25 #4 (1, 3)
	26 goto (1, 3)
	27 -19 (1, 3)
	29 dload (0, 0)
	30 #4 (0, 0)
	31 dreturn (0, 0)

Method: getNumericalMean
	0 aload_0 (0, 0)
	1 invokevirtual (0, 0)
	2 org/apache/commons/math3/distribution/HypergeometricDistribution.getSampleSize:()I (0, 0)
	4 i2d (0, 0)
	5 aload_0 (0, 0)
	6 invokevirtual (0, 0)
	7 org/apache/commons/math3/distribution/HypergeometricDistribution.getNumberOfSuccesses:()I (0, 0)
	9 i2d (0, 0)
	10 aload_0 (0, 0)
	11 invokevirtual (0, 0)
	12 org/apache/commons/math3/distribution/HypergeometricDistribution.getPopulationSize:()I (0, 0)
	14 i2d (0, 0)
	15 ddiv (0, 0)
	16 dmul (0, 0)
	17 dreturn (0, 0)

Method: getNumericalVariance
	0 aload_0 (1, 1)
	1 getfield (1, 1)
	2 org/apache/commons/math3/distribution/HypergeometricDistribution.numericalVarianceIsCalculated:Z (1, 1)
	4 ifne (1, 1)
	5 16 (1, 1)
	7 aload_0 (1, 1)
	8 aload_0 (1, 1)
	9 invokevirtual (1, 1)
	10 org/apache/commons/math3/distribution/HypergeometricDistribution.calculateNumericalVariance:()D (1, 1)
	12 putfield (1, 1)
	13 org/apache/commons/math3/distribution/HypergeometricDistribution.numericalVariance:D (1, 1)
	15 aload_0 (1, 1)
	16 iconst_1 (1, 1)
	17 putfield (1, 1)
	18 org/apache/commons/math3/distribution/HypergeometricDistribution.numericalVarianceIsCalculated:Z (1, 1)
	20 aload_0 (0, 0)
	21 getfield (0, 0)
	22 org/apache/commons/math3/distribution/HypergeometricDistribution.numericalVariance:D (0, 0)
	24 dreturn (0, 0)

Method: calculateNumericalVariance
	0 aload_0 (0, 0)
	1 invokevirtual (0, 0)
	2 org/apache/commons/math3/distribution/HypergeometricDistribution.getPopulationSize:()I (0, 0)
	4 i2d (0, 0)
	5 dstore_1 (0, 0)
	6 aload_0 (0, 0)
	7 invokevirtual (0, 0)
	8 org/apache/commons/math3/distribution/HypergeometricDistribution.getNumberOfSuccesses:()I (0, 0)
	10 i2d (0, 0)
	11 dstore_3 (0, 0)
	12 aload_0 (0, 0)
	13 invokevirtual (0, 0)
	14 org/apache/commons/math3/distribution/HypergeometricDistribution.getSampleSize:()I (0, 0)
	16 i2d (0, 0)
	17 dstore (0, 0)
	18 #5 (0, 0)
	19 dload (0, 0)
	20 #5 (0, 0)
	21 dload_3 (0, 0)
	22 dmul (0, 0)
	23 dload_1 (0, 0)
	24 dload (0, 0)
	25 #5 (0, 0)
	26 dsub (0, 0)
	27 dmul (0, 0)
	28 dload_1 (0, 0)
	29 dload_3 (0, 0)
	30 dsub (0, 0)
	31 dmul (0, 0)
	32 dload_1 (0, 0)
	33 dload_1 (0, 0)
	34 dmul (0, 0)
	35 dload_1 (0, 0)
	36 dconst_1 (0, 0)
	37 dsub (0, 0)
	38 dmul (0, 0)
	39 ddiv (0, 0)
	40 dreturn (0, 0)

Method: getSupportLowerBound
	0 iconst_0 (0, 0)
	1 aload_0 (0, 0)
	2 invokevirtual (0, 0)
	3 org/apache/commons/math3/distribution/HypergeometricDistribution.getSampleSize:()I (0, 0)
	5 aload_0 (0, 0)
	6 invokevirtual (0, 0)
	7 org/apache/commons/math3/distribution/HypergeometricDistribution.getNumberOfSuccesses:()I (0, 0)
	9 iadd (0, 0)
	10 aload_0 (0, 0)
	11 invokevirtual (0, 0)
	12 org/apache/commons/math3/distribution/HypergeometricDistribution.getPopulationSize:()I (0, 0)
	14 isub (0, 0)
	15 invokestatic (0, 0)
	16 org/apache/commons/math3/util/FastMath.max:(II)I (0, 0)
	18 ireturn (0, 0)

Method: getSupportUpperBound
	0 aload_0 (0, 0)
	1 invokevirtual (0, 0)
	2 org/apache/commons/math3/distribution/HypergeometricDistribution.getNumberOfSuccesses:()I (0, 0)
	4 aload_0 (0, 0)
	5 invokevirtual (0, 0)
	6 org/apache/commons/math3/distribution/HypergeometricDistribution.getSampleSize:()I (0, 0)
	8 invokestatic (0, 0)
	9 org/apache/commons/math3/util/FastMath.min:(II)I (0, 0)
	11 ireturn (0, 0)

Method: isSupportConnected
	0 iconst_1 (0, 0)
	1 ireturn (0, 0)

