Method: <init>
	0 aload_0 (0, 0)
	1 aload_1 (0, 0)
	2 aload_2 (0, 0)
	3 invokespecial (0, 0)
	4 org/apache/commons/math3/distribution/MixtureMultivariateRealDistribution.<init>:(Lorg/apache/commons/math3/random/RandomGenerator;Ljava/util/List;)V (0, 0)
	6 return (0, 0)

Method: createComponents
	0 new (0, 0)
	1 java/util/ArrayList (0, 0)
	3 dup (0, 0)
	4 aload_0 (0, 0)
	5 arraylength (0, 0)
	6 invokespecial (0, 0)
	7 java/util/ArrayList.<init>:(I)V (0, 0)
	9 astore_3 (0, 0)
	10 iconst_0 (1, 4)
	11 istore (1, 4)
	12 #4 (1, 4)
	13 iload (1, 4)
	14 #4 (1, 4)
	15 aload_0 (1, 4)
	16 arraylength (1, 4)
	17 if_icmpge (1, 4)
	18 49 (1, 4)
	20 new (1, 4)
	21 org/apache/commons/math3/distribution/MultivariateNormalDistribution (1, 4)
	23 dup (1, 4)
	24 aload_1 (1, 4)
	25 iload (1, 4)
	26 #4 (1, 4)
	27 aaload (1, 4)
	28 aload_2 (1, 4)
	29 iload (1, 4)
	30 #4 (1, 4)
	31 aaload (1, 4)
	32 invokespecial (1, 4)
	33 org/apache/commons/math3/distribution/MultivariateNormalDistribution.<init>:([D[[D)V (1, 4)
	35 astore (1, 4)
	36 #5 (1, 4)
	37 aload_3 (1, 4)
	38 new (1, 4)
	39 org/apache/commons/math3/util/Pair (1, 4)
	41 dup (1, 4)
	42 aload_0 (1, 4)
	43 iload (1, 4)
	44 #4 (1, 4)
	45 daload (1, 4)
	46 invokestatic (1, 4)
	47 java/lang/Double.valueOf:(D)Ljava/lang/Double; (1, 4)
	49 aload (1, 4)
	50 #5 (1, 4)
	51 invokespecial (1, 4)
	52 org/apache/commons/math3/util/Pair.<init>:(Ljava/lang/Object;Ljava/lang/Object;)V (1, 4)
	54 invokeinterface (1, 4)
	55 java/util/List.org/apache/commons/math3/distribution/MixtureMultivariateNormalDistribution (1, 4)
	57 0 (1, 4)
	59 pop (1, 4)
	60 iinc (1, 4)
	61 #4 (1, 4)
	62 -89 (1, 4)
	63 goto (1, 4)
	64 -50 (1, 4)
	66 aload_3 (0, 0)
	67 areturn (0, 0)

