Method: <init>
	0 aload_0 (0, 0)
	1 aload_1 (0, 0)
	2 aload_2 (0, 0)
	3 iconst_0 (0, 0)
	4 invokeinterface (0, 0)
	5 java/util/List.org/apache/commons/math3/util/Pair (0, 0)
	7 0 (0, 0)
	9 checkcast (0, 0)
	10 org/apache/commons/math3/util/Pair (0, 0)
	12 invokevirtual (0, 0)
	13 org/apache/commons/math3/util/Pair.getSecond:()Ljava/lang/Object; (0, 0)
	15 checkcast (0, 0)
	16 org/apache/commons/math3/distribution/MultivariateRealDistribution (0, 0)
	18 invokeinterface (0, 0)
	19 org/apache/commons/math3/distribution/MultivariateRealDistribution.<init>:(Lorg/apache/commons/math3/random/RandomGenerator;I)V (0, 0)
	21 0 (0, 0)
	23 invokespecial (0, 0)
	24 org/apache/commons/math3/distribution/AbstractMultivariateRealDistribution.<init>:(Lorg/apache/commons/math3/random/RandomGenerator;I)V (0, 0)
	26 aload_2 (0, 0)
	27 invokeinterface (0, 0)
	28 java/util/List.org/apache/commons/math3/exception/DimensionMismatchException (0, 0)
	30 0 (0, 0)
	32 istore_3 (0, 0)
	33 aload_0 (0, 0)
	34 invokevirtual (0, 0)
	35 org/apache/commons/math3/distribution/MixtureMultivariateRealDistribution.getDimension:()I (0, 0)
	37 istore (0, 0)
	38 #4 (0, 0)
	39 dconst_0 (0, 0)
	40 dstore (0, 0)
	41 #5 (0, 0)
	42 iconst_0 (1, 4)
	43 istore (1, 4)
	44 #7 (1, 4)
	45 iload (1, 4)
	46 #7 (1, 4)
	47 iload_3 (1, 4)
	48 if_icmpge (1, 4)
	49 111 (1, 4)
	51 aload_2 (1, 4)
	52 iload (1, 4)
	53 #7 (1, 4)
	54 invokeinterface (1, 4)
	55 java/util/List.org/apache/commons/math3/util/Pair (1, 4)
	57 0 (1, 4)
	59 checkcast (1, 4)
	60 org/apache/commons/math3/util/Pair (1, 4)
	62 astore (1, 4)
	63 #8 (1, 4)
	64 aload (2, 1)
	65 #8 (2, 1)
	66 invokevirtual (2, 1)
	67 org/apache/commons/math3/util/Pair.getSecond:()Ljava/lang/Object; (2, 1)
	69 checkcast (2, 1)
	70 org/apache/commons/math3/distribution/MultivariateRealDistribution (2, 1)
	72 invokeinterface (2, 1)
	73 org/apache/commons/math3/distribution/MultivariateRealDistribution.<init>:(Lorg/apache/commons/math3/random/RandomGenerator;I)V (2, 1)
	75 0 (2, 1)
	77 iload (2, 1)
	78 #4 (2, 1)
	79 if_icmpeq (2, 1)
	80 26 (2, 1)
	82 new (2, 1)
	83 org/apache/commons/math3/exception/DimensionMismatchException (2, 1)
	85 dup (2, 1)
	86 aload (2, 1)
	87 #8 (2, 1)
	88 invokevirtual (2, 1)
	89 org/apache/commons/math3/util/Pair.getSecond:()Ljava/lang/Object; (2, 1)
	91 checkcast (2, 1)
	92 org/apache/commons/math3/distribution/MultivariateRealDistribution (2, 1)
	94 invokeinterface (2, 1)
	95 org/apache/commons/math3/distribution/MultivariateRealDistribution.<init>:(Lorg/apache/commons/math3/random/RandomGenerator;I)V (2, 1)
	97 0 (2, 1)
	99 iload (2, 1)
	100 #4 (2, 1)
	101 invokespecial (2, 1)
	102 org/apache/commons/math3/exception/DimensionMismatchException.<init>:(II)V (2, 1)
	104 athrow (2, 1)
	105 aload (2, 1)
	106 #8 (2, 1)
	107 invokevirtual (2, 1)
	108 org/apache/commons/math3/util/Pair.getFirst:()Ljava/lang/Object; (2, 1)
	110 checkcast (2, 1)
	111 java/lang/Double (2, 1)
	113 invokevirtual (2, 1)
	114 java/lang/Double.doubleValue:()D (2, 1)
	116 dconst_0 (2, 1)
	117 dcmpg (2, 1)
	118 ifge (2, 1)
	119 19 (2, 1)
	121 new (2, 1)
	122 org/apache/commons/math3/exception/NotPositiveException (2, 1)
	124 dup (2, 1)
	125 aload (2, 1)
	126 #8 (2, 1)
	127 invokevirtual (2, 1)
	128 org/apache/commons/math3/util/Pair.getFirst:()Ljava/lang/Object; (2, 1)
	130 checkcast (2, 1)
	131 java/lang/Number (2, 1)
	133 invokespecial (2, 1)
	134 org/apache/commons/math3/exception/NotPositiveException.<init>:(Ljava/lang/Number;)V (2, 1)
	136 athrow (2, 1)
	137 dload (1, 4)
	138 #5 (1, 4)
	139 aload (1, 4)
	140 #8 (1, 4)
	141 invokevirtual (1, 4)
	142 org/apache/commons/math3/util/Pair.getFirst:()Ljava/lang/Object; (1, 4)
	144 checkcast (1, 4)
	145 java/lang/Double (1, 4)
	147 invokevirtual (1, 4)
	148 java/lang/Double.doubleValue:()D (1, 4)
	150 dadd (1, 4)
	151 dstore (1, 4)
	152 #5 (1, 4)
	153 iinc (1, 4)
	154 #7 (1, 4)
	155 -89 (1, 4)
	156 goto (1, 4)
	157 -111 (1, 4)
	159 dload (2, 1)
	160 #5 (2, 1)
	161 invokestatic (2, 1)
	162 java/lang/Double.isInfinite:(D)Z (2, 1)
	164 ifeq (2, 1)
	165 18 (2, 1)
	167 new (2, 1)
	168 org/apache/commons/math3/exception/MathArithmeticException (2, 1)
	170 dup (2, 1)
	171 getstatic (2, 1)
	172 org/apache/commons/math3/exception/util/LocalizedFormats.OVERFLOW:Lorg/apache/commons/math3/exception/util/LocalizedFormats; (2, 1)
	174 iconst_0 (2, 1)
	175 anewarray (2, 1)
	176 java/lang/Object (2, 1)
	178 invokespecial (2, 1)
	179 org/apache/commons/math3/exception/MathArithmeticException.<init>:(Lorg/apache/commons/math3/exception/util/Localizable;[Ljava/lang/Object;)V (2, 1)
	181 athrow (2, 1)
	182 aload_0 (1, 4)
	183 new (1, 4)
	184 java/util/ArrayList (1, 4)
	186 dup (1, 4)
	187 invokespecial (1, 4)
	188 java/util/ArrayList.<init>:()V (1, 4)
	190 putfield (1, 4)
	191 org/apache/commons/math3/distribution/MixtureMultivariateRealDistribution.distribution:Ljava/util/List; (1, 4)
	193 aload_0 (1, 4)
	194 iload_3 (1, 4)
	195 newarray (1, 4)
	196 7 (1, 4)
	197 putfield (1, 4)
	198 org/apache/commons/math3/distribution/MixtureMultivariateRealDistribution.weight:[D (1, 4)
	200 iconst_0 (2, 4)
	201 istore (2, 4)
	202 #7 (2, 4)
	203 iload (2, 4)
	204 #7 (2, 4)
	205 iload_3 (2, 4)
	206 if_icmpge (2, 4)
	207 58 (2, 4)
	209 aload_2 (2, 4)
	210 iload (2, 4)
	211 #7 (2, 4)
	212 invokeinterface (2, 4)
	213 java/util/List.org/apache/commons/math3/util/Pair (2, 4)
	215 0 (2, 4)
	217 checkcast (2, 4)
	218 org/apache/commons/math3/util/Pair (2, 4)
	220 astore (2, 4)
	221 #8 (2, 4)
	222 aload_0 (2, 4)
	223 getfield (2, 4)
	224 org/apache/commons/math3/distribution/MixtureMultivariateRealDistribution.weight:[D (2, 4)
	226 iload (2, 4)
	227 #7 (2, 4)
	228 aload (2, 4)
	229 #8 (2, 4)
	230 invokevirtual (2, 4)
	231 org/apache/commons/math3/util/Pair.getFirst:()Ljava/lang/Object; (2, 4)
	233 checkcast (2, 4)
	234 java/lang/Double (2, 4)
	236 invokevirtual (2, 4)
	237 java/lang/Double.doubleValue:()D (2, 4)
	239 dload (2, 4)
	240 #5 (2, 4)
	241 ddiv (2, 4)
	242 dastore (2, 4)
	243 aload_0 (2, 4)
	244 getfield (2, 4)
	245 org/apache/commons/math3/distribution/MixtureMultivariateRealDistribution.distribution:Ljava/util/List; (2, 4)
	247 aload (2, 4)
	248 #8 (2, 4)
	249 invokevirtual (2, 4)
	250 org/apache/commons/math3/util/Pair.getSecond:()Ljava/lang/Object; (2, 4)
	252 invokeinterface (2, 4)
	253 java/util/List.density:([D)D (2, 4)
	255 0 (2, 4)
	257 pop (2, 4)
	258 iinc (2, 4)
	259 #7 (2, 4)
	260 -89 (2, 4)
	261 goto (2, 4)
	262 -58 (2, 4)
	264 return (0, 4)

Method: density
	0 dconst_0 (0, 0)
	1 dstore_2 (0, 0)
	2 iconst_0 (1, 4)
	3 istore (1, 4)
	4 #4 (1, 4)
	5 iload (1, 4)
	6 #4 (1, 4)
	7 aload_0 (1, 4)
	8 getfield (1, 4)
	9 org/apache/commons/math3/distribution/MixtureMultivariateRealDistribution.weight:[D (1, 4)
	11 arraylength (1, 4)
	12 if_icmpge (1, 4)
	13 40 (1, 4)
	15 dload_2 (1, 4)
	16 aload_0 (1, 4)
	17 getfield (1, 4)
	18 org/apache/commons/math3/distribution/MixtureMultivariateRealDistribution.weight:[D (1, 4)
	20 iload (1, 4)
	21 #4 (1, 4)
	22 daload (1, 4)
	23 aload_0 (1, 4)
	24 getfield (1, 4)
	25 org/apache/commons/math3/distribution/MixtureMultivariateRealDistribution.distribution:Ljava/util/List; (1, 4)
	27 iload (1, 4)
	28 #4 (1, 4)
	29 invokeinterface (1, 4)
	30 java/util/List.org/apache/commons/math3/util/Pair (1, 4)
	32 0 (1, 4)
	34 checkcast (1, 4)
	35 org/apache/commons/math3/distribution/MultivariateRealDistribution (1, 4)
	37 aload_1 (1, 4)
	38 invokeinterface (1, 4)
	39 org/apache/commons/math3/distribution/MultivariateRealDistribution.random:Lorg/apache/commons/math3/random/RandomGenerator; (1, 4)
	41 0 (1, 4)
	43 dmul (1, 4)
	44 dadd (1, 4)
	45 dstore_2 (1, 4)
	46 iinc (1, 4)
	47 #4 (1, 4)
	48 -89 (1, 4)
	49 goto (1, 4)
	50 -44 (1, 4)
	52 dload_2 (0, 0)
	53 dreturn (0, 0)

Method: sample
	0 aconst_null (0, 0)
	1 astore_1 (0, 0)
	2 aload_0 (0, 0)
	3 getfield (0, 0)
	4 org/apache/commons/math3/distribution/MixtureMultivariateRealDistribution.random:Lorg/apache/commons/math3/random/RandomGenerator; (0, 0)
	6 invokeinterface (0, 0)
	7 org/apache/commons/math3/random/RandomGenerator.sample:()[D (0, 0)
	9 0 (0, 0)
	11 dstore_2 (0, 0)
	12 dconst_0 (0, 0)
	13 dstore (0, 0)
	14 #4 (0, 0)
	15 iconst_0 (1, 4)
	16 istore (1, 4)
	17 #6 (1, 4)
	18 iload (1, 4)
	19 #6 (1, 4)
	20 aload_0 (1, 4)
	21 getfield (1, 4)
	22 org/apache/commons/math3/distribution/MixtureMultivariateRealDistribution.weight:[D (1, 4)
	24 arraylength (1, 4)
	25 if_icmpge (1, 4)
	26 51 (1, 4)
	28 dload (1, 4)
	29 #4 (1, 4)
	30 aload_0 (1, 4)
	31 getfield (1, 4)
	32 org/apache/commons/math3/distribution/MixtureMultivariateRealDistribution.weight:[D (1, 4)
	34 iload (1, 4)
	35 #6 (1, 4)
	36 daload (1, 4)
	37 dadd (1, 4)
	38 dstore (1, 4)
	39 #4 (1, 4)
	40 dload_2 (2, 1)
	41 dload (2, 1)
	42 #4 (2, 1)
	43 dcmpg (2, 1)
	44 ifgt (2, 1)
	45 26 (2, 1)
	47 aload_0 (2, 1)
	48 getfield (2, 1)
	49 org/apache/commons/math3/distribution/MixtureMultivariateRealDistribution.distribution:Ljava/util/List; (2, 1)
	51 iload (2, 1)
	52 #6 (2, 1)
	53 invokeinterface (2, 1)
	54 java/util/List.org/apache/commons/math3/util/Pair (2, 1)
	56 0 (2, 1)
	58 checkcast (2, 1)
	59 org/apache/commons/math3/distribution/MultivariateRealDistribution (2, 1)
	61 invokeinterface (2, 1)
	62 org/apache/commons/math3/distribution/MultivariateRealDistribution.reseedRandomGenerator:(J)V (2, 1)
	64 0 (2, 1)
	66 astore_1 (2, 1)
	67 goto (2, 1)
	68 9 (2, 1)
	70 iinc (2, 1)
	71 #6 (2, 1)
	72 -89 (2, 1)
	73 goto (2, 1)
	74 -55 (2, 1)
	76 aload_1 (2, 1)
	77 ifnonnull (2, 1)
	78 28 (2, 1)
	80 aload_0 (2, 1)
	81 getfield (2, 1)
	82 org/apache/commons/math3/distribution/MixtureMultivariateRealDistribution.distribution:Ljava/util/List; (2, 1)
	84 aload_0 (2, 1)
	85 getfield (2, 1)
	86 org/apache/commons/math3/distribution/MixtureMultivariateRealDistribution.weight:[D (2, 1)
	88 arraylength (2, 1)
	89 iconst_1 (2, 1)
	90 isub (2, 1)
	91 invokeinterface (2, 1)
	92 java/util/List.org/apache/commons/math3/util/Pair (2, 1)
	94 0 (2, 1)
	96 checkcast (2, 1)
	97 org/apache/commons/math3/distribution/MultivariateRealDistribution (2, 1)
	99 invokeinterface (2, 1)
	100 org/apache/commons/math3/distribution/MultivariateRealDistribution.reseedRandomGenerator:(J)V (2, 1)
	102 0 (2, 1)
	104 astore_1 (2, 1)
	105 aload_1 (1, 4)
	106 areturn (1, 4)

Method: reseedRandomGenerator
	0 aload_0 (0, 0)
	1 lload_1 (0, 0)
	2 invokespecial (0, 0)
	3 org/apache/commons/math3/distribution/AbstractMultivariateRealDistribution.reseedRandomGenerator:(J)V (0, 0)
	5 iconst_0 (1, 4)
	6 istore_3 (1, 4)
	7 iload_3 (1, 4)
	8 aload_0 (1, 4)
	9 getfield (1, 4)
	10 org/apache/commons/math3/distribution/MixtureMultivariateRealDistribution.distribution:Ljava/util/List; (1, 4)
	12 invokeinterface (1, 4)
	13 java/util/List.org/apache/commons/math3/exception/DimensionMismatchException (1, 4)
	15 0 (1, 4)
	17 if_icmpge (1, 4)
	18 33 (1, 4)
	20 aload_0 (2, 1)
	21 getfield (2, 1)
	22 org/apache/commons/math3/distribution/MixtureMultivariateRealDistribution.distribution:Ljava/util/List; (2, 1)
	24 iload_3 (2, 1)
	25 invokeinterface (2, 1)
	26 java/util/List.org/apache/commons/math3/util/Pair (2, 1)
	28 0 (2, 1)
	30 checkcast (2, 1)
	31 org/apache/commons/math3/distribution/MultivariateRealDistribution (2, 1)
	33 iload_3 (2, 1)
	34 iconst_1 (2, 1)
	35 iadd (2, 1)
	36 i2l (2, 1)
	37 lload_1 (2, 1)
	38 ladd (2, 1)
	39 invokeinterface (2, 1)
	40 org/apache/commons/math3/distribution/MultivariateRealDistribution.<init>:(I)V (2, 1)
	42 0 (2, 1)
	44 iinc (2, 1)
	45 #3 (2, 1)
	46 -89 (2, 1)
	47 goto (2, 1)
	48 -40 (2, 1)
	50 return (0, 0)

Method: getComponents
	0 new (0, 0)
	1 java/util/ArrayList (0, 0)
	3 dup (0, 0)
	4 aload_0 (0, 0)
	5 getfield (0, 0)
	6 org/apache/commons/math3/distribution/MixtureMultivariateRealDistribution.weight:[D (0, 0)
	8 arraylength (0, 0)
	9 invokespecial (0, 0)
	10 java/util/ArrayList.<init>:(I)V (0, 0)
	12 astore_1 (0, 0)
	13 iconst_0 (1, 4)
	14 istore_2 (1, 4)
	15 iload_2 (1, 4)
	16 aload_0 (1, 4)
	17 getfield (1, 4)
	18 org/apache/commons/math3/distribution/MixtureMultivariateRealDistribution.weight:[D (1, 4)
	20 arraylength (1, 4)
	21 if_icmpge (1, 4)
	22 42 (1, 4)
	24 aload_1 (1, 4)
	25 new (1, 4)
	26 org/apache/commons/math3/util/Pair (1, 4)
	28 dup (1, 4)
	29 aload_0 (1, 4)
	30 getfield (1, 4)
	31 org/apache/commons/math3/distribution/MixtureMultivariateRealDistribution.weight:[D (1, 4)
	33 iload_2 (1, 4)
	34 daload (1, 4)
	35 invokestatic (1, 4)
	36 java/lang/Double.valueOf:(D)Ljava/lang/Double; (1, 4)
	38 aload_0 (1, 4)
	39 getfield (1, 4)
	40 org/apache/commons/math3/distribution/MixtureMultivariateRealDistribution.distribution:Ljava/util/List; (1, 4)
	42 iload_2 (1, 4)
	43 invokeinterface (1, 4)
	44 java/util/List.org/apache/commons/math3/util/Pair (1, 4)
	46 0 (1, 4)
	48 invokespecial (1, 4)
	49 org/apache/commons/math3/util/Pair.<init>:(Ljava/lang/Object;Ljava/lang/Object;)V (1, 4)
	51 invokeinterface (1, 4)
	52 java/util/List.density:([D)D (1, 4)
	54 0 (1, 4)
	56 pop (1, 4)
	57 iinc (1, 4)
	58 #2 (1, 4)
	59 -89 (1, 4)
	60 goto (1, 4)
	61 -45 (1, 4)
	63 aload_1 (0, 0)
	64 areturn (0, 0)

