Method: <init>
	0 aload_0 (0, 0)
	1 aload_1 (0, 0)
	2 aload_2 (0, 0)
	3 arraylength (0, 0)
	4 invokespecial (0, 0)
	5 org/apache/commons/math3/distribution/AbstractMultivariateRealDistribution.<init>:(Lorg/apache/commons/math3/random/RandomGenerator;I)V (0, 0)
	7 aload_2 (0, 0)
	8 arraylength (0, 0)
	9 istore (0, 0)
	10 #4 (0, 0)
	11 aload_3 (1, 1)
	12 arraylength (1, 1)
	13 iload (1, 1)
	14 #4 (1, 1)
	15 if_icmpeq (1, 1)
	16 15 (1, 1)
	18 new (1, 1)
	19 org/apache/commons/math3/exception/DimensionMismatchException (1, 1)
	21 dup (1, 1)
	22 aload_3 (1, 1)
	23 arraylength (1, 1)
	24 iload (1, 1)
	25 #4 (1, 1)
	26 invokespecial (1, 1)
	27 org/apache/commons/math3/exception/DimensionMismatchException.<init>:(II)V (1, 1)
	29 athrow (1, 1)
	30 iconst_0 (1, 4)
	31 istore (1, 4)
	32 #5 (1, 4)
	33 iload (1, 4)
	34 #5 (1, 4)
	35 iload (1, 4)
	36 #4 (1, 4)
	37 if_icmpge (1, 4)
	38 34 (1, 4)
	40 iload (2, 1)
	41 #4 (2, 1)
	42 aload_3 (2, 1)
	43 iload (2, 1)
	44 #5 (2, 1)
	45 aaload (2, 1)
	46 arraylength (2, 1)
	47 if_icmpeq (2, 1)
	48 18 (2, 1)
	50 new (2, 1)
	51 org/apache/commons/math3/exception/DimensionMismatchException (2, 1)
	53 dup (2, 1)
	54 aload_3 (2, 1)
	55 iload (2, 1)
	56 #5 (2, 1)
	57 aaload (2, 1)
	58 arraylength (2, 1)
	59 iload (2, 1)
	60 #4 (2, 1)
	61 invokespecial (2, 1)
	62 org/apache/commons/math3/exception/DimensionMismatchException.<init>:(II)V (2, 1)
	64 athrow (2, 1)
	65 iinc (2, 1)
	66 #5 (2, 1)
	67 -89 (2, 1)
	68 goto (2, 1)
	69 -35 (2, 1)
	71 aload_0 (1, 4)
	72 aload_2 (1, 4)
	73 invokestatic (1, 4)
	74 org/apache/commons/math3/util/MathArrays.copyOf:([D)[D (1, 4)
	76 putfield (1, 4)
	77 org/apache/commons/math3/distribution/MultivariateNormalDistribution.means:[D (1, 4)
	79 aload_0 (1, 4)
	80 new (1, 4)
	81 org/apache/commons/math3/linear/Array2DRowRealMatrix (1, 4)
	83 dup (1, 4)
	84 aload_3 (1, 4)
	85 invokespecial (1, 4)
	86 org/apache/commons/math3/linear/Array2DRowRealMatrix.<init>:([[D)V (1, 4)
	88 putfield (1, 4)
	89 org/apache/commons/math3/distribution/MultivariateNormalDistribution.covarianceMatrix:Lorg/apache/commons/math3/linear/RealMatrix; (1, 4)
	91 new (1, 4)
	92 org/apache/commons/math3/linear/EigenDecomposition (1, 4)
	94 dup (1, 4)
	95 aload_0 (1, 4)
	96 getfield (1, 4)
	97 org/apache/commons/math3/distribution/MultivariateNormalDistribution.covarianceMatrix:Lorg/apache/commons/math3/linear/RealMatrix; (1, 4)
	99 invokespecial (1, 4)
	100 org/apache/commons/math3/linear/EigenDecomposition.<init>:(Lorg/apache/commons/math3/linear/RealMatrix;)V (1, 4)
	102 astore (1, 4)
	103 #5 (1, 4)
	104 aload_0 (1, 4)
	105 aload (1, 4)
	106 #5 (1, 4)
	107 invokevirtual (1, 4)
	108 org/apache/commons/math3/linear/EigenDecomposition.getSolver:()Lorg/apache/commons/math3/linear/DecompositionSolver; (1, 4)
	110 invokeinterface (1, 4)
	111 org/apache/commons/math3/linear/DecompositionSolver.covarianceMatrixInverse:Lorg/apache/commons/math3/linear/RealMatrix; (1, 4)
	113 0 (1, 4)
	115 putfield (1, 4)
	116 org/apache/commons/math3/distribution/MultivariateNormalDistribution.covarianceMatrixInverse:Lorg/apache/commons/math3/linear/RealMatrix; (1, 4)
	118 aload_0 (1, 4)
	119 aload (1, 4)
	120 #5 (1, 4)
	121 invokevirtual (1, 4)
	122 org/apache/commons/math3/linear/EigenDecomposition.getDeterminant:()D (1, 4)
	124 putfield (1, 4)
	125 org/apache/commons/math3/distribution/MultivariateNormalDistribution.covarianceMatrixDeterminant:D (1, 4)
	127 aload (1, 4)
	128 #5 (1, 4)
	129 invokevirtual (1, 4)
	130 org/apache/commons/math3/linear/EigenDecomposition.getRealEigenvalues:()[D (1, 4)
	132 astore (1, 4)
	133 #6 (1, 4)
	134 iconst_0 (2, 4)
	135 istore (2, 4)
	136 #7 (2, 4)
	137 iload (2, 4)
	138 #7 (2, 4)
	139 aload (2, 4)
	140 #6 (2, 4)
	141 arraylength (2, 4)
	142 if_icmpge (2, 4)
	143 35 (2, 4)
	145 aload (3, 1)
	146 #6 (3, 1)
	147 iload (3, 1)
	148 #7 (3, 1)
	149 daload (3, 1)
	150 dconst_0 (3, 1)
	151 dcmpg (3, 1)
	152 ifge (3, 1)
	153 19 (3, 1)
	155 new (3, 1)
	156 org/apache/commons/math3/linear/NonPositiveDefiniteMatrixException (3, 1)
	158 dup (3, 1)
	159 aload (3, 1)
	160 #6 (3, 1)
	161 iload (3, 1)
	162 #7 (3, 1)
	163 daload (3, 1)
	164 iload (3, 1)
	165 #7 (3, 1)
	166 dconst_0 (3, 1)
	167 invokespecial (3, 1)
	168 org/apache/commons/math3/linear/NonPositiveDefiniteMatrixException.<init>:(DID)V (3, 1)
	170 athrow (3, 1)
	171 iinc (3, 1)
	172 #7 (3, 1)
	173 -89 (3, 1)
	174 goto (3, 1)
	175 -37 (3, 1)
	177 new (2, 4)
	178 org/apache/commons/math3/linear/Array2DRowRealMatrix (2, 4)
	180 dup (2, 4)
	181 iload (2, 4)
	182 #4 (2, 4)
	183 iload (2, 4)
	184 #4 (2, 4)
	185 invokespecial (2, 4)
	186 org/apache/commons/math3/linear/Array2DRowRealMatrix.<init>:(II)V (2, 4)
	188 astore (2, 4)
	189 #7 (2, 4)
	190 iconst_0 (3, 4)
	191 istore (3, 4)
	192 #8 (3, 4)
	193 iload (3, 4)
	194 #8 (3, 4)
	195 iload (3, 4)
	196 #4 (3, 4)
	197 if_icmpge (3, 4)
	198 30 (3, 4)
	200 aload (3, 4)
	201 #5 (3, 4)
	202 iload (3, 4)
	203 #8 (3, 4)
	204 invokevirtual (3, 4)
	205 org/apache/commons/math3/linear/EigenDecomposition.getEigenvector:(I)Lorg/apache/commons/math3/linear/RealVector; (3, 4)
	207 invokevirtual (3, 4)
	208 org/apache/commons/math3/linear/RealVector.toArray:()[D (3, 4)
	210 astore (3, 4)
	211 #9 (3, 4)
	212 aload (3, 4)
	213 #7 (3, 4)
	214 iload (3, 4)
	215 #8 (3, 4)
	216 aload (3, 4)
	217 #9 (3, 4)
	218 invokevirtual (3, 4)
	219 org/apache/commons/math3/linear/Array2DRowRealMatrix.setColumn:(I[D)V (3, 4)
	221 iinc (3, 4)
	222 #8 (3, 4)
	223 -89 (3, 4)
	224 goto (3, 4)
	225 -31 (3, 4)
	227 aload (2, 4)
	228 #7 (2, 4)
	229 invokevirtual (2, 4)
	230 org/apache/commons/math3/linear/Array2DRowRealMatrix.transpose:()Lorg/apache/commons/math3/linear/RealMatrix; (2, 4)
	232 astore (2, 4)
	233 #8 (2, 4)
	234 iconst_0 (3, 4)
	235 istore (3, 4)
	236 #9 (3, 4)
	237 iload (3, 4)
	238 #9 (3, 4)
	239 iload (3, 4)
	240 #4 (3, 4)
	241 if_icmpge (3, 4)
	242 48 (3, 4)
	244 aload (3, 4)
	245 #6 (3, 4)
	246 iload (3, 4)
	247 #9 (3, 4)
	248 daload (3, 4)
	249 invokestatic (3, 4)
	250 org/apache/commons/math3/util/FastMath.sqrt:(D)D (3, 4)
	252 dstore (3, 4)
	253 #10 (3, 4)
	254 iconst_0 (4, 4)
	255 istore (4, 4)
	256 #12 (4, 4)
	257 iload (4, 4)
	258 #12 (4, 4)
	259 iload (4, 4)
	260 #4 (4, 4)
	261 if_icmpge (4, 4)
	262 22 (4, 4)
	264 aload (4, 4)
	265 #8 (4, 4)
	266 iload (4, 4)
	267 #9 (4, 4)
	268 iload (4, 4)
	269 #12 (4, 4)
	270 dload (4, 4)
	271 #10 (4, 4)
	272 invokeinterface (4, 4)
	273 org/apache/commons/math3/linear/RealMatrix.multiply:(Lorg/apache/commons/math3/linear/RealMatrix;)Lorg/apache/commons/math3/linear/RealMatrix; (4, 4)
	275 0 (4, 4)
	277 iinc (4, 4)
	278 #12 (4, 4)
	279 -89 (4, 4)
	280 goto (4, 4)
	281 -23 (4, 4)
	283 iinc (4, 4)
	284 #9 (4, 4)
	285 -89 (4, 4)
	286 goto (4, 4)
	287 -49 (4, 4)
	289 aload_0 (3, 4)
	290 aload (3, 4)
	291 #7 (3, 4)
	292 aload (3, 4)
	293 #8 (3, 4)
	294 invokevirtual (3, 4)
	295 org/apache/commons/math3/linear/Array2DRowRealMatrix.multiply:(Lorg/apache/commons/math3/linear/RealMatrix;)Lorg/apache/commons/math3/linear/RealMatrix; (3, 4)
	297 putfield (3, 4)
	298 org/apache/commons/math3/distribution/MultivariateNormalDistribution.samplingMatrix:Lorg/apache/commons/math3/linear/RealMatrix; (3, 4)
	300 return (2, 4)

Method: getMeans
	0 aload_0 (0, 0)
	1 getfield (0, 0)
	2 org/apache/commons/math3/distribution/MultivariateNormalDistribution.means:[D (0, 0)
	4 invokestatic (0, 0)
	5 org/apache/commons/math3/util/MathArrays.copyOf:([D)[D (0, 0)
	7 areturn (0, 0)

Method: getCovariances
	0 aload_0 (0, 0)
	1 getfield (0, 0)
	2 org/apache/commons/math3/distribution/MultivariateNormalDistribution.covarianceMatrix:Lorg/apache/commons/math3/linear/RealMatrix; (0, 0)
	4 invokeinterface (0, 0)
	5 org/apache/commons/math3/linear/RealMatrix.getDimension:()I (0, 0)
	7 0 (0, 0)
	9 areturn (0, 0)

Method: density
	0 aload_0 (0, 0)
	1 invokevirtual (0, 0)
	2 org/apache/commons/math3/distribution/MultivariateNormalDistribution.getDimension:()I (0, 0)
	4 istore_2 (0, 0)
	5 aload_1 (1, 1)
	6 arraylength (1, 1)
	7 iload_2 (1, 1)
	8 if_icmpeq (1, 1)
	9 14 (1, 1)
	11 new (1, 1)
	12 org/apache/commons/math3/exception/DimensionMismatchException (1, 1)
	14 dup (1, 1)
	15 aload_1 (1, 1)
	16 arraylength (1, 1)
	17 iload_2 (1, 1)
	18 invokespecial (1, 1)
	19 org/apache/commons/math3/exception/DimensionMismatchException.<init>:(II)V (1, 1)
	21 athrow (1, 1)
	22 ldc2_w (0, 0)
	23 6.283185307179586 (0, 0)
	25 ldc2_w (0, 0)
	26 -0.5 (0, 0)
	28 iload_2 (0, 0)
	29 i2d (0, 0)
	30 dmul (0, 0)
	31 invokestatic (0, 0)
	32 org/apache/commons/math3/util/FastMath.pow:(DD)D (0, 0)
	34 aload_0 (0, 0)
	35 getfield (0, 0)
	36 org/apache/commons/math3/distribution/MultivariateNormalDistribution.covarianceMatrixDeterminant:D (0, 0)
	38 ldc2_w (0, 0)
	39 -0.5 (0, 0)
	41 invokestatic (0, 0)
	42 org/apache/commons/math3/util/FastMath.pow:(DD)D (0, 0)
	44 dmul (0, 0)
	45 aload_0 (0, 0)
	46 aload_1 (0, 0)
	47 invokespecial (0, 0)
	48 org/apache/commons/math3/distribution/MultivariateNormalDistribution.getExponentTerm:([D)D (0, 0)
	50 dmul (0, 0)
	51 dreturn (0, 0)

Method: getStandardDeviations
	0 aload_0 (0, 0)
	1 invokevirtual (0, 0)
	2 org/apache/commons/math3/distribution/MultivariateNormalDistribution.getDimension:()I (0, 0)
	4 istore_1 (0, 0)
	5 iload_1 (0, 0)
	6 newarray (0, 0)
	7 7 (0, 0)
	8 astore_2 (0, 0)
	9 aload_0 (0, 0)
	10 getfield (0, 0)
	11 org/apache/commons/math3/distribution/MultivariateNormalDistribution.covarianceMatrix:Lorg/apache/commons/math3/linear/RealMatrix; (0, 0)
	13 invokeinterface (0, 0)
	14 org/apache/commons/math3/linear/RealMatrix.random:Lorg/apache/commons/math3/random/RandomGenerator; (0, 0)
	16 0 (0, 0)
	18 astore_3 (0, 0)
	19 iconst_0 (1, 4)
	20 istore (1, 4)
	21 #4 (1, 4)
	22 iload (1, 4)
	23 #4 (1, 4)
	24 iload_1 (1, 4)
	25 if_icmpge (1, 4)
	26 23 (1, 4)
	28 aload_2 (1, 4)
	29 iload (1, 4)
	30 #4 (1, 4)
	31 aload_3 (1, 4)
	32 iload (1, 4)
	33 #4 (1, 4)
	34 aaload (1, 4)
	35 iload (1, 4)
	36 #4 (1, 4)
	37 daload (1, 4)
	38 invokestatic (1, 4)
	39 org/apache/commons/math3/util/FastMath.sqrt:(D)D (1, 4)
	41 dastore (1, 4)
	42 iinc (1, 4)
	43 #4 (1, 4)
	44 -89 (1, 4)
	45 goto (1, 4)
	46 -23 (1, 4)
	48 aload_2 (0, 0)
	49 areturn (0, 0)

Method: sample
	0 aload_0 (0, 0)
	1 invokevirtual (0, 0)
	2 org/apache/commons/math3/distribution/MultivariateNormalDistribution.getDimension:()I (0, 0)
	4 istore_1 (0, 0)
	5 iload_1 (0, 0)
	6 newarray (0, 0)
	7 7 (0, 0)
	8 astore_2 (0, 0)
	9 iconst_0 (1, 4)
	10 istore_3 (1, 4)
	11 iload_3 (1, 4)
	12 iload_1 (1, 4)
	13 if_icmpge (1, 4)
	14 21 (1, 4)
	16 aload_2 (1, 4)
	17 iload_3 (1, 4)
	18 aload_0 (1, 4)
	19 getfield (1, 4)
	20 org/apache/commons/math3/distribution/MultivariateNormalDistribution.random:Lorg/apache/commons/math3/random/RandomGenerator; (1, 4)
	22 invokeinterface (1, 4)
	23 org/apache/commons/math3/random/RandomGenerator.operate:([D)[D (1, 4)
	25 0 (1, 4)
	27 dastore (1, 4)
	28 iinc (1, 4)
	29 #3 (1, 4)
	30 -89 (1, 4)
	31 goto (1, 4)
	32 -20 (1, 4)
	34 aload_0 (0, 0)
	35 getfield (0, 0)
	36 org/apache/commons/math3/distribution/MultivariateNormalDistribution.samplingMatrix:Lorg/apache/commons/math3/linear/RealMatrix; (0, 0)
	38 aload_2 (0, 0)
	39 invokeinterface (0, 0)
	40 org/apache/commons/math3/linear/RealMatrix.getMeans:()[D (0, 0)
	42 0 (0, 0)
	44 astore_3 (0, 0)
	45 iconst_0 (1, 4)
	46 istore (1, 4)
	47 #4 (1, 4)
	48 iload (1, 4)
	49 #4 (1, 4)
	50 iload_1 (1, 4)
	51 if_icmpge (1, 4)
	52 23 (1, 4)
	54 aload_3 (1, 4)
	55 iload (1, 4)
	56 #4 (1, 4)
	57 dup2 (1, 4)
	58 daload (1, 4)
	59 aload_0 (1, 4)
	60 getfield (1, 4)
	61 org/apache/commons/math3/distribution/MultivariateNormalDistribution.means:[D (1, 4)
	63 iload (1, 4)
	64 #4 (1, 4)
	65 daload (1, 4)
	66 dadd (1, 4)
	67 dastore (1, 4)
	68 iinc (1, 4)
	69 #4 (1, 4)
	70 -89 (1, 4)
	71 goto (1, 4)
	72 -23 (1, 4)
	74 aload_3 (0, 0)
	75 areturn (0, 0)

Method: getExponentTerm
	0 aload_1 (0, 0)
	1 arraylength (0, 0)
	2 newarray (0, 0)
	3 7 (0, 0)
	4 astore_2 (0, 0)
	5 iconst_0 (1, 4)
	6 istore_3 (1, 4)
	7 iload_3 (1, 4)
	8 aload_2 (1, 4)
	9 arraylength (1, 4)
	10 if_icmpge (1, 4)
	11 22 (1, 4)
	13 aload_2 (1, 4)
	14 iload_3 (1, 4)
	15 aload_1 (1, 4)
	16 iload_3 (1, 4)
	17 daload (1, 4)
	18 aload_0 (1, 4)
	19 invokevirtual (1, 4)
	20 org/apache/commons/math3/distribution/MultivariateNormalDistribution.getMeans:()[D (1, 4)
	22 iload_3 (1, 4)
	23 daload (1, 4)
	24 dsub (1, 4)
	25 dastore (1, 4)
	26 iinc (1, 4)
	27 #3 (1, 4)
	28 -89 (1, 4)
	29 goto (1, 4)
	30 -22 (1, 4)
	32 aload_0 (0, 0)
	33 getfield (0, 0)
	34 org/apache/commons/math3/distribution/MultivariateNormalDistribution.covarianceMatrixInverse:Lorg/apache/commons/math3/linear/RealMatrix; (0, 0)
	36 aload_2 (0, 0)
	37 invokeinterface (0, 0)
	38 org/apache/commons/math3/linear/RealMatrix.exp:(D)D (0, 0)
	40 0 (0, 0)
	42 astore_3 (0, 0)
	43 dconst_0 (0, 0)
	44 dstore (0, 0)
	45 #4 (0, 0)
	46 iconst_0 (1, 4)
	47 istore (1, 4)
	48 #6 (1, 4)
	49 iload (1, 4)
	50 #6 (1, 4)
	51 aload_3 (1, 4)
	52 arraylength (1, 4)
	53 if_icmpge (1, 4)
	54 23 (1, 4)
	56 dload (1, 4)
	57 #4 (1, 4)
	58 aload_3 (1, 4)
	59 iload (1, 4)
	60 #6 (1, 4)
	61 daload (1, 4)
	62 aload_2 (1, 4)
	63 iload (1, 4)
	64 #6 (1, 4)
	65 daload (1, 4)
	66 dmul (1, 4)
	67 dadd (1, 4)
	68 dstore (1, 4)
	69 #4 (1, 4)
	70 iinc (1, 4)
	71 #6 (1, 4)
	72 -89 (1, 4)
	73 goto (1, 4)
	74 -24 (1, 4)
	76 ldc2_w (0, 0)
	77 -0.5 (0, 0)
	79 dload (0, 0)
	80 #4 (0, 0)
	81 dmul (0, 0)
	82 invokestatic (0, 0)
	83 org/apache/commons/math3/util/FastMath.exp:(D)D (0, 0)
	85 dreturn (0, 0)

