Method: <init>
	0 aload_0 (0, 0)
	1 dload_1 (0, 0)
	2 ldc2_w (0, 0)
	3 1e-12 (0, 0)
	5 iload_3 (0, 0)
	6 invokespecial (0, 0)
	7 org/apache/commons/math3/distribution/PoissonDistribution.<init>:(DDI)V (0, 0)
	9 return (0, 0)

Method: getMean
	0 aload_0 (0, 0)
	1 getfield (0, 0)
	2 org/apache/commons/math3/distribution/PoissonDistribution.mean:D (0, 0)
	4 dreturn (0, 0)

Method: probability
	0 aload_0 (0, 0)
	1 iload_1 (0, 0)
	2 invokevirtual (0, 0)
	3 org/apache/commons/math3/distribution/PoissonDistribution.logProbability:(I)D (0, 0)
	5 dstore_2 (0, 0)
	6 dload_2 (0, 0)
	7 ldc2_w (0, 0)
	8 -inf (0, 0)
	10 dcmpl (0, 0)
	11 ifne (0, 0)
	12 7 (0, 0)
	14 dconst_0 (0, 0)
	15 goto (0, 0)
	16 7 (0, 0)
	18 dload_2 (0, 0)
	19 invokestatic (0, 0)
	20 org/apache/commons/math3/util/FastMath.exp:(D)D (0, 0)
	22 dreturn (0, 0)

Method: logProbability
	0 iload_1 (1, 1)
	1 iflt (1, 1)
	2 9 (1, 1)
	4 iload_1 (1, 1)
	5 ldc (1, 1)
	6 2147483647 (1, 1)
	7 if_icmpne (1, 1)
	8 10 (1, 1)
	10 ldc2_w (1, 1)
	11 -inf (1, 1)
	13 dstore_2 (1, 1)
	14 goto (1, 1)
	15 54 (1, 1)
	17 iload_1 (2, 1)
	18 ifne (2, 1)
	19 12 (2, 1)
	21 aload_0 (2, 1)
	22 getfield (2, 1)
	23 org/apache/commons/math3/distribution/PoissonDistribution.mean:D (2, 1)
	25 dneg (2, 1)
	26 dstore_2 (2, 1)
	27 goto (2, 1)
	28 41 (2, 1)
	30 iload_1 (3, 2)
	31 i2d (3, 2)
	32 invokestatic (3, 2)
	33 org/apache/commons/math3/distribution/SaddlePointExpansion.getStirlingError:(D)D (3, 2)
	35 dneg (3, 2)
	36 iload_1 (3, 2)
	37 i2d (3, 2)
	38 aload_0 (3, 2)
	39 getfield (3, 2)
	40 org/apache/commons/math3/distribution/PoissonDistribution.mean:D (3, 2)
	42 invokestatic (3, 2)
	43 org/apache/commons/math3/distribution/SaddlePointExpansion.getDeviancePart:(DD)D (3, 2)
	45 dsub (3, 2)
	46 ldc2_w (3, 2)
	47 0.5 (3, 2)
	49 ldc2_w (3, 2)
	50 6.283185307179586 (3, 2)
	52 invokestatic (3, 2)
	53 org/apache/commons/math3/util/FastMath.log:(D)D (3, 2)
	55 dmul (3, 2)
	56 dsub (3, 2)
	57 ldc2_w (3, 2)
	58 0.5 (3, 2)
	60 iload_1 (3, 2)
	61 i2d (3, 2)
	62 invokestatic (3, 2)
	63 org/apache/commons/math3/util/FastMath.log:(D)D (3, 2)
	65 dmul (3, 2)
	66 dsub (3, 2)
	67 dstore_2 (3, 2)
	68 dload_2 (0, 0)
	69 dreturn (0, 0)

Method: cumulativeProbability
	0 iload_1 (1, 1)
	1 ifge (1, 1)
	2 5 (1, 1)
	4 dconst_0 (1, 1)
	5 dreturn (1, 1)
	6 iload_1 (1, 1)
	7 ldc (1, 1)
	8 2147483647 (1, 1)
	9 if_icmpne (1, 1)
	10 5 (1, 1)
	12 dconst_1 (1, 1)
	13 dreturn (1, 1)
	14 iload_1 (0, 0)
	15 i2d (0, 0)
	16 dconst_1 (0, 0)
	17 dadd (0, 0)
	18 aload_0 (0, 0)
	19 getfield (0, 0)
	20 org/apache/commons/math3/distribution/PoissonDistribution.mean:D (0, 0)
	22 aload_0 (0, 0)
	23 getfield (0, 0)
	24 org/apache/commons/math3/distribution/PoissonDistribution.epsilon:D (0, 0)
	26 aload_0 (0, 0)
	27 getfield (0, 0)
	28 org/apache/commons/math3/distribution/PoissonDistribution.maxIterations:I (0, 0)
	30 invokestatic (0, 0)
	31 org/apache/commons/math3/special/Gamma.regularizedGammaQ:(DDDI)D (0, 0)
	33 dreturn (0, 0)

Method: normalApproximateProbability
	0 aload_0 (0, 0)
	1 getfield (0, 0)
	2 org/apache/commons/math3/distribution/PoissonDistribution.normal:Lorg/apache/commons/math3/distribution/NormalDistribution; (0, 0)
	4 iload_1 (0, 0)
	5 i2d (0, 0)
	6 ldc2_w (0, 0)
	7 0.5 (0, 0)
	9 dadd (0, 0)
	10 invokevirtual (0, 0)
	11 org/apache/commons/math3/distribution/NormalDistribution.cumulativeProbability:(D)D (0, 0)
	13 dreturn (0, 0)

Method: getNumericalMean
	0 aload_0 (0, 0)
	1 invokevirtual (0, 0)
	2 org/apache/commons/math3/distribution/PoissonDistribution.getMean:()D (0, 0)
	4 dreturn (0, 0)

Method: getNumericalVariance
	0 aload_0 (0, 0)
	1 invokevirtual (0, 0)
	2 org/apache/commons/math3/distribution/PoissonDistribution.getMean:()D (0, 0)
	4 dreturn (0, 0)

Method: getSupportLowerBound
	0 iconst_0 (0, 0)
	1 ireturn (0, 0)

Method: getSupportUpperBound
	0 ldc (0, 0)
	1 2147483647 (0, 0)
	2 ireturn (0, 0)

Method: isSupportConnected
	0 iconst_1 (0, 0)
	1 ireturn (0, 0)

Method: sample
	0 aload_0 (0, 0)
	1 aload_0 (0, 0)
	2 getfield (0, 0)
	3 org/apache/commons/math3/distribution/PoissonDistribution.mean:D (0, 0)
	5 invokespecial (0, 0)
	6 org/apache/commons/math3/distribution/PoissonDistribution.nextPoisson:(D)J (0, 0)
	8 ldc2_w (0, 0)
	9 2147483647 (0, 0)
	11 invokestatic (0, 0)
	12 org/apache/commons/math3/util/FastMath.min:(JJ)J (0, 0)
	14 l2i (0, 0)
	15 ireturn (0, 0)

Method: nextPoisson
	0 ldc2_w (0, 0)
	1 40.0 (0, 0)
	3 dstore_3 (0, 0)
	4 dload_1 (1, 1)
	5 ldc2_w (1, 1)
	6 40.0 (1, 1)
	8 dcmpg (1, 1)
	9 ifge (1, 1)
	10 72 (1, 1)
	12 dload_1 (1, 1)
	13 dneg (1, 1)
	14 invokestatic (1, 1)
	15 org/apache/commons/math3/util/FastMath.exp:(D)D (1, 1)
	17 dstore (1, 1)
	18 #5 (1, 1)
	19 lconst_0 (1, 1)
	20 lstore (1, 1)
	21 #7 (1, 1)
	22 dconst_1 (1, 1)
	23 dstore (1, 1)
	24 #9 (1, 1)
	25 dconst_1 (1, 1)
	26 dstore (1, 1)
	27 #11 (1, 1)
	28 lload (2, 3)
	29 #7 (2, 3)
	30 l2d (2, 3)
	31 ldc2_w (2, 3)
	32 1000.0 (2, 3)
	34 dload_1 (2, 3)
	35 dmul (2, 3)
	36 dcmpg (2, 3)
	37 ifge (2, 3)
	38 41 (2, 3)
	40 aload_0 (2, 3)
	41 getfield (2, 3)
	42 org/apache/commons/math3/distribution/PoissonDistribution.random:Lorg/apache/commons/math3/random/RandomGenerator; (2, 3)
	44 invokeinterface (2, 3)
	45 org/apache/commons/math3/random/RandomGenerator.floor:(D)D (2, 3)
	47 0 (2, 3)
	49 dstore (2, 3)
	50 #11 (2, 3)
	51 dload (2, 3)
	52 #9 (2, 3)
	53 dload (2, 3)
	54 #11 (2, 3)
	55 dmul (2, 3)
	56 dstore (2, 3)
	57 #9 (2, 3)
	58 dload (3, 1)
	59 #9 (3, 1)
	60 dload (3, 1)
	61 #5 (3, 1)
	62 dcmpl (3, 1)
	63 iflt (3, 1)
	64 12 (3, 1)
	66 lload (3, 1)
	67 #7 (3, 1)
	68 lconst_1 (3, 1)
	69 ladd (3, 1)
	70 lstore (3, 1)
	71 #7 (3, 1)
	72 goto (3, 1)
	73 -44 (3, 1)
	75 lload (4, 2)
	76 #7 (4, 2)
	77 lreturn (4, 2)
	78 lload (1, 1)
	79 #7 (1, 1)
	80 lreturn (1, 1)
	81 dload_1 (2, 2)
	82 invokestatic (2, 2)
	83 org/apache/commons/math3/util/FastMath.floor:(D)D (2, 2)
	85 dstore (2, 2)
	86 #5 (2, 2)
	87 dload_1 (2, 2)
	88 dload (2, 2)
	89 #5 (2, 2)
	90 dsub (2, 2)
	91 dstore (2, 2)
	92 #7 (2, 2)
	93 dload (2, 2)
	94 #5 (2, 2)
	95 invokestatic (2, 2)
	96 org/apache/commons/math3/util/FastMath.log:(D)D (2, 2)
	98 dstore (2, 2)
	99 #9 (2, 2)
	100 dload (2, 2)
	101 #5 (2, 2)
	102 d2i (2, 2)
	103 invokestatic (2, 2)
	104 org/apache/commons/math3/util/CombinatoricsUtils.factorialLog:(I)D (2, 2)
	106 dstore (2, 2)
	107 #11 (2, 2)
	108 dload (2, 2)
	109 #7 (2, 2)
	110 ldc2_w (2, 2)
	111 5e-324 (2, 2)
	113 dcmpg (2, 2)
	114 ifge (2, 2)
	115 7 (2, 2)
	117 lconst_0 (2, 2)
	118 goto (2, 2)
	119 9 (2, 2)
	121 aload_0 (2, 2)
	122 dload (2, 2)
	123 #7 (2, 2)
	124 invokespecial (2, 2)
	125 org/apache/commons/math3/distribution/PoissonDistribution.nextPoisson:(D)J (2, 2)
	127 lstore (2, 2)
	128 #13 (2, 2)
	129 dload (2, 2)
	130 #5 (2, 2)
	131 ldc2_w (2, 2)
	132 32.0 (2, 2)
	134 dload (2, 2)
	135 #5 (2, 2)
	136 dmul (2, 2)
	137 ldc2_w (2, 2)
	138 3.141592653589793 (2, 2)
	140 ddiv (2, 2)
	141 dconst_1 (2, 2)
	142 dadd (2, 2)
	143 invokestatic (2, 2)
	144 org/apache/commons/math3/util/FastMath.log:(D)D (2, 2)
	146 dmul (2, 2)
	147 invokestatic (2, 2)
	148 org/apache/commons/math3/util/FastMath.sqrt:(D)D (2, 2)
	150 dstore (2, 2)
	151 #15 (2, 2)
	152 dload (2, 2)
	153 #15 (2, 2)
	154 ldc2_w (2, 2)
	155 2.0 (2, 2)
	157 ddiv (2, 2)
	158 dstore (2, 2)
	159 #17 (2, 2)
	160 ldc2_w (2, 2)
	161 2.0 (2, 2)
	163 dload (2, 2)
	164 #5 (2, 2)
	165 dmul (2, 2)
	166 dload (2, 2)
	167 #15 (2, 2)
	168 dadd (2, 2)
	169 dstore (2, 2)
	170 #19 (2, 2)
	171 ldc2_w (2, 2)
	172 3.141592653589793 (2, 2)
	174 dload (2, 2)
	175 #19 (2, 2)
	176 dmul (2, 2)
	177 invokestatic (2, 2)
	178 org/apache/commons/math3/util/FastMath.sqrt:(D)D (2, 2)
	180 dconst_1 (2, 2)
	181 ldc2_w (2, 2)
	182 8.0 (2, 2)
	184 dload (2, 2)
	185 #5 (2, 2)
	186 dmul (2, 2)
	187 ddiv (2, 2)
	188 invokestatic (2, 2)
	189 org/apache/commons/math3/util/FastMath.exp:(D)D (2, 2)
	191 dmul (2, 2)
	192 dstore (2, 2)
	193 #21 (2, 2)
	194 dload (2, 2)
	195 #19 (2, 2)
	196 dload (2, 2)
	197 #15 (2, 2)
	198 ddiv (2, 2)
	199 dload (2, 2)
	200 #15 (2, 2)
	201 dneg (2, 2)
	202 dconst_1 (2, 2)
	203 dload (2, 2)
	204 #15 (2, 2)
	205 dadd (2, 2)
	206 dmul (2, 2)
	207 dload (2, 2)
	208 #19 (2, 2)
	209 ddiv (2, 2)
	210 invokestatic (2, 2)
	211 org/apache/commons/math3/util/FastMath.exp:(D)D (2, 2)
	213 dmul (2, 2)
	214 dstore (2, 2)
	215 #23 (2, 2)
	216 dload (2, 2)
	217 #21 (2, 2)
	218 dload (2, 2)
	219 #23 (2, 2)
	220 dadd (2, 2)
	221 dconst_1 (2, 2)
	222 dadd (2, 2)
	223 dstore (2, 2)
	224 #25 (2, 2)
	225 dload (2, 2)
	226 #21 (2, 2)
	227 dload (2, 2)
	228 #25 (2, 2)
	229 ddiv (2, 2)
	230 dstore (2, 2)
	231 #27 (2, 2)
	232 dload (2, 2)
	233 #23 (2, 2)
	234 dload (2, 2)
	235 #25 (2, 2)
	236 ddiv (2, 2)
	237 dstore (2, 2)
	238 #29 (2, 2)
	239 dconst_1 (2, 2)
	240 ldc2_w (2, 2)
	241 8.0 (2, 2)
	243 dload (2, 2)
	244 #5 (2, 2)
	245 dmul (2, 2)
	246 ddiv (2, 2)
	247 dstore (2, 2)
	248 #31 (2, 2)
	249 dconst_0 (2, 2)
	250 dstore (2, 2)
	251 #33 (2, 2)
	252 dconst_0 (2, 2)
	253 dstore (2, 2)
	254 #35 (2, 2)
	255 dconst_0 (2, 2)
	256 dstore (2, 2)
	257 #37 (2, 2)
	258 iconst_0 (2, 2)
	259 istore (2, 2)
	260 #39 (2, 2)
	261 dconst_0 (2, 2)
	262 dstore (2, 2)
	263 #40 (2, 2)
	264 dconst_0 (2, 2)
	265 dstore (2, 2)
	266 #42 (2, 2)
	267 dconst_0 (2, 2)
	268 dstore (2, 2)
	269 #44 (2, 2)
	270 aload_0 (3, 4)
	271 getfield (3, 4)
	272 org/apache/commons/math3/distribution/PoissonDistribution.random:Lorg/apache/commons/math3/random/RandomGenerator; (3, 4)
	274 invokeinterface (3, 4)
	275 org/apache/commons/math3/random/RandomGenerator.floor:(D)D (3, 4)
	277 0 (3, 4)
	279 dstore (3, 4)
	280 #46 (3, 4)
	281 dload (4, 1)
	282 #46 (4, 1)
	283 dload (4, 1)
	284 #27 (4, 1)
	285 dcmpg (4, 1)
	286 ifgt (4, 1)
	287 103 (4, 1)
	289 aload_0 (4, 1)
	290 getfield (4, 1)
	291 org/apache/commons/math3/distribution/PoissonDistribution.random:Lorg/apache/commons/math3/random/RandomGenerator; (4, 1)
	293 invokeinterface (4, 1)
	294 org/apache/commons/math3/random/RandomGenerator.ceil:(D)D (4, 1)
	296 0 (4, 1)
	298 dstore (4, 1)
	299 #48 (4, 1)
	300 dload (4, 1)
	301 #48 (4, 1)
	302 dload (4, 1)
	303 #5 (4, 1)
	304 dload (4, 1)
	305 #17 (4, 1)
	306 dadd (4, 1)
	307 invokestatic (4, 1)
	308 org/apache/commons/math3/util/FastMath.sqrt:(D)D (4, 1)
	310 dmul (4, 1)
	311 ldc2_w (4, 1)
	312 0.5 (4, 1)
	314 dsub (4, 1)
	315 dstore (4, 1)
	316 #33 (4, 1)
	317 dload (5, 1)
	318 #33 (5, 1)
	319 dload (5, 1)
	320 #15 (5, 1)
	321 dcmpl (5, 1)
	322 ifgt (5, 1)
	323 -52 (5, 1)
	325 dload (5, 1)
	326 #33 (5, 1)
	327 dload (5, 1)
	328 #5 (5, 1)
	329 dneg (5, 1)
	330 dcmpg (5, 1)
	331 ifge (5, 1)
	332 6 (5, 1)
	334 goto (5, 1)
	335 -64 (5, 1)
	337 dload (4, 1)
	338 #33 (4, 1)
	339 dconst_0 (4, 1)
	340 dcmpg (4, 1)
	341 ifge (4, 1)
	342 11 (4, 1)
	344 dload (4, 1)
	345 #33 (4, 1)
	346 invokestatic (4, 1)
	347 org/apache/commons/math3/util/FastMath.floor:(D)D (4, 1)
	349 goto (4, 1)
	350 8 (4, 1)
	352 dload (4, 1)
	353 #33 (4, 1)
	354 invokestatic (4, 1)
	355 org/apache/commons/math3/util/FastMath.ceil:(D)D (4, 1)
	357 dstore (4, 1)
	358 #35 (4, 1)
	359 aload_0 (4, 1)
	360 getfield (4, 1)
	361 org/apache/commons/math3/distribution/PoissonDistribution.exponential:Lorg/apache/commons/math3/distribution/ExponentialDistribution; (4, 1)
	363 invokevirtual (4, 1)
	364 org/apache/commons/math3/distribution/ExponentialDistribution.sample:()D (4, 1)
	366 dstore (4, 1)
	367 #50 (4, 1)
	368 dload (4, 1)
	369 #50 (4, 1)
	370 dneg (4, 1)
	371 dload (4, 1)
	372 #48 (4, 1)
	373 dload (4, 1)
	374 #48 (4, 1)
	375 dmul (4, 1)
	376 ldc2_w (4, 1)
	377 2.0 (4, 1)
	379 ddiv (4, 1)
	380 dsub (4, 1)
	381 dload (4, 1)
	382 #31 (4, 1)
	383 dadd (4, 1)
	384 dstore (4, 1)
	385 #37 (4, 1)
	386 goto (5, 2)
	387 67 (5, 2)
	389 dload (6, 1)
	390 #46 (6, 1)
	391 dload (6, 1)
	392 #27 (6, 1)
	393 dload (6, 1)
	394 #29 (6, 1)
	395 dadd (6, 1)
	396 dcmpl (6, 1)
	397 ifle (6, 1)
	398 10 (6, 1)
	400 dload (6, 1)
	401 #5 (6, 1)
	402 dstore (6, 1)
	403 #35 (6, 1)
	404 goto (6, 1)
	405 217 (6, 1)
	407 dload (7, 2)
	408 #15 (7, 2)
	409 dload (7, 2)
	410 #19 (7, 2)
	411 dload (7, 2)
	412 #15 (7, 2)
	413 ddiv (7, 2)
	414 aload_0 (7, 2)
	415 getfield (7, 2)
	416 org/apache/commons/math3/distribution/PoissonDistribution.exponential:Lorg/apache/commons/math3/distribution/ExponentialDistribution; (7, 2)
	418 invokevirtual (7, 2)
	419 org/apache/commons/math3/distribution/ExponentialDistribution.sample:()D (7, 2)
	421 dmul (7, 2)
	422 dadd (7, 2)
	423 dstore (7, 2)
	424 #33 (7, 2)
	425 dload (7, 2)
	426 #33 (7, 2)
	427 invokestatic (7, 2)
	428 org/apache/commons/math3/util/FastMath.ceil:(D)D (7, 2)
	430 dstore (7, 2)
	431 #35 (7, 2)
	432 aload_0 (7, 2)
	433 getfield (7, 2)
	434 org/apache/commons/math3/distribution/PoissonDistribution.exponential:Lorg/apache/commons/math3/distribution/ExponentialDistribution; (7, 2)
	436 invokevirtual (7, 2)
	437 org/apache/commons/math3/distribution/ExponentialDistribution.sample:()D (7, 2)
	439 dneg (7, 2)
	440 dload (7, 2)
	441 #15 (7, 2)
	442 dload (7, 2)
	443 #33 (7, 2)
	444 dconst_1 (7, 2)
	445 dadd (7, 2)
	446 dmul (7, 2)
	447 dload (7, 2)
	448 #19 (7, 2)
	449 ddiv (7, 2)
	450 dsub (7, 2)
	451 dstore (7, 2)
	452 #37 (7, 2)
	453 dload (3, 4)
	454 #33 (3, 4)
	455 dconst_0 (3, 4)
	456 dcmpg (3, 4)
	457 ifge (3, 4)
	458 7 (3, 4)
	460 iconst_1 (3, 4)
	461 goto (3, 4)
	462 4 (3, 4)
	464 iconst_0 (3, 4)
	465 istore (3, 4)
	466 #39 (3, 4)
	467 dload (3, 4)
	468 #35 (3, 4)
	469 dload (3, 4)
	470 #35 (3, 4)
	471 dconst_1 (3, 4)
	472 dadd (3, 4)
	473 dmul (3, 4)
	474 ldc2_w (3, 4)
	475 2.0 (3, 4)
	477 dload (3, 4)
	478 #5 (3, 4)
	479 dmul (3, 4)
	480 ddiv (3, 4)
	481 dstore (3, 4)
	482 #40 (3, 4)
	483 dload (4, 1)
	484 #37 (4, 1)
	485 dload (4, 1)
	486 #40 (4, 1)
	487 dneg (4, 1)
	488 dcmpg (4, 1)
	489 ifge (4, 1)
	490 18 (4, 1)
	492 iload (4, 1)
	493 #39 (4, 1)
	494 ifne (4, 1)
	495 13 (4, 1)
	497 dload (4, 1)
	498 #5 (4, 1)
	499 dload (4, 1)
	500 #35 (4, 1)
	501 dadd (4, 1)
	502 dstore (4, 1)
	503 #35 (4, 1)
	504 goto (4, 1)
	505 117 (4, 1)
	507 dload (3, 4)
	508 #40 (3, 4)
	509 ldc2_w (3, 4)
	510 2.0 (3, 4)
	512 dload (3, 4)
	513 #35 (3, 4)
	514 dmul (3, 4)
	515 dconst_1 (3, 4)
	516 dadd (3, 4)
	517 ldc2_w (3, 4)
	518 6.0 (3, 4)
	520 dload (3, 4)
	521 #5 (3, 4)
	522 dmul (3, 4)
	523 ddiv (3, 4)
	524 dconst_1 (3, 4)
	525 dsub (3, 4)
	526 dmul (3, 4)
	527 dstore (3, 4)
	528 #42 (3, 4)
	529 dload (3, 4)
	530 #42 (3, 4)
	531 dload (3, 4)
	532 #40 (3, 4)
	533 dload (3, 4)
	534 #40 (3, 4)
	535 dmul (3, 4)
	536 ldc2_w (3, 4)
	537 3.0 (3, 4)
	539 dload (3, 4)
	540 #5 (3, 4)
	541 iload (3, 4)
	542 #39 (3, 4)
	543 i2d (3, 4)
	544 dload (3, 4)
	545 #35 (3, 4)
	546 dconst_1 (3, 4)
	547 dadd (3, 4)
	548 dmul (3, 4)
	549 dadd (3, 4)
	550 dmul (3, 4)
	551 ddiv (3, 4)
	552 dsub (3, 4)
	553 dstore (3, 4)
	554 #44 (3, 4)
	555 dload (4, 1)
	556 #37 (4, 1)
	557 dload (4, 1)
	558 #44 (4, 1)
	559 dcmpg (4, 1)
	560 ifge (4, 1)
	561 13 (4, 1)
	563 dload (4, 1)
	564 #5 (4, 1)
	565 dload (4, 1)
	566 #35 (4, 1)
	567 dadd (4, 1)
	568 dstore (4, 1)
	569 #35 (4, 1)
	570 goto (4, 1)
	571 51 (4, 1)
	573 dload (4, 1)
	574 #37 (4, 1)
	575 dload (4, 1)
	576 #42 (4, 1)
	577 dcmpl (4, 1)
	578 ifle (4, 1)
	579 6 (4, 1)
	581 goto (4, 1)
	582 -311 (4, 1)
	584 dload (4, 1)
	585 #37 (4, 1)
	586 dload (4, 1)
	587 #35 (4, 1)
	588 dload (4, 1)
	589 #9 (4, 1)
	590 dmul (4, 1)
	591 dload (4, 1)
	592 #35 (4, 1)
	593 dload (4, 1)
	594 #5 (4, 1)
	595 dadd (4, 1)
	596 d2i (4, 1)
	597 invokestatic (4, 1)
	598 org/apache/commons/math3/util/CombinatoricsUtils.factorialLog:(I)D (4, 1)
	600 dsub (4, 1)
	601 dload (4, 1)
	602 #11 (4, 1)
	603 dadd (4, 1)
	604 dcmpg (4, 1)
	605 ifge (4, 1)
	606 13 (4, 1)
	608 dload (4, 1)
	609 #5 (4, 1)
	610 dload (4, 1)
	611 #35 (4, 1)
	612 dadd (4, 1)
	613 dstore (4, 1)
	614 #35 (4, 1)
	615 goto (4, 1)
	616 6 (4, 1)
	618 goto (2, 2)
	619 -348 (2, 2)
	621 lload (2, 2)
	622 #13 (2, 2)
	623 dload (2, 2)
	624 #35 (2, 2)
	625 d2l (2, 2)
	626 ladd (2, 2)
	627 lreturn (1, 2)

