Method: <init>
	0 aload_0 (0, 0)
	1 invokespecial (0, 0)
	2 java/lang/Object.<init>:()V (0, 0)
	4 return (0, 0)

Method: getStirlingError
	0 dload_0 (1, 1)
	1 ldc2_w (1, 1)
	2 15.0 (1, 1)
	4 dcmpg (1, 1)
	5 ifge (1, 1)
	6 59 (1, 1)
	8 ldc2_w (1, 1)
	9 2.0 (1, 1)
	11 dload_0 (1, 1)
	12 dmul (1, 1)
	13 dstore (1, 1)
	14 #4 (1, 1)
	15 dload (2, 1)
	16 #4 (2, 1)
	17 invokestatic (2, 1)
	18 org/apache/commons/math3/util/FastMath.floor:(D)D (2, 1)
	20 dload (2, 1)
	21 #4 (2, 1)
	22 dcmpl (2, 1)
	23 ifne (2, 1)
	24 14 (2, 1)
	26 getstatic (2, 1)
	27 org/apache/commons/math3/distribution/SaddlePointExpansion.EXACT_STIRLING_ERRORS:[D (2, 1)
	29 dload (2, 1)
	30 #4 (2, 1)
	31 d2i (2, 1)
	32 daload (2, 1)
	33 dstore_2 (2, 1)
	34 goto (2, 1)
	35 27 (2, 1)
	37 dload_0 (3, 2)
	38 dconst_1 (3, 2)
	39 dadd (3, 2)
	40 invokestatic (3, 2)
	41 org/apache/commons/math3/special/Gamma.logGamma:(D)D (3, 2)
	43 dload_0 (3, 2)
	44 ldc2_w (3, 2)
	45 0.5 (3, 2)
	47 dadd (3, 2)
	48 dload_0 (3, 2)
	49 invokestatic (3, 2)
	50 org/apache/commons/math3/util/FastMath.log:(D)D (3, 2)
	52 dmul (3, 2)
	53 dsub (3, 2)
	54 dload_0 (3, 2)
	55 dadd (3, 2)
	56 getstatic (3, 2)
	57 org/apache/commons/math3/distribution/SaddlePointExpansion.HALF_LOG_2_PI:D (3, 2)
	59 dsub (3, 2)
	60 dstore_2 (3, 2)
	61 goto (2, 2)
	62 42 (2, 2)
	64 dload_0 (2, 2)
	65 dload_0 (2, 2)
	66 dmul (2, 2)
	67 dstore (2, 2)
	68 #4 (2, 2)
	69 ldc2_w (2, 2)
	70 0.08333333333333333 (2, 2)
	72 ldc2_w (2, 2)
	73 0.002777777777777778 (2, 2)
	75 ldc2_w (2, 2)
	76 0.0007936507936507937 (2, 2)
	78 ldc2_w (2, 2)
	79 0.0005952380952380953 (2, 2)
	81 ldc2_w (2, 2)
	82 0.0008417508417508417 (2, 2)
	84 dload (2, 2)
	85 #4 (2, 2)
	86 ddiv (2, 2)
	87 dsub (2, 2)
	88 dload (2, 2)
	89 #4 (2, 2)
	90 ddiv (2, 2)
	91 dsub (2, 2)
	92 dload (2, 2)
	93 #4 (2, 2)
	94 ddiv (2, 2)
	95 dsub (2, 2)
	96 dload (2, 2)
	97 #4 (2, 2)
	98 ddiv (2, 2)
	99 dsub (2, 2)
	100 dload_0 (2, 2)
	101 ddiv (2, 2)
	102 dstore_2 (2, 2)
	103 dload_2 (0, 0)
	104 dreturn (0, 0)

Method: getDeviancePart
	0 dload_0 (1, 1)
	1 dload_2 (1, 1)
	2 dsub (1, 1)
	3 invokestatic (1, 1)
	4 org/apache/commons/math3/util/FastMath.abs:(D)D (1, 1)
	6 ldc2_w (1, 1)
	7 0.1 (1, 1)
	9 dload_0 (1, 1)
	10 dload_2 (1, 1)
	11 dadd (1, 1)
	12 dmul (1, 1)
	13 dcmpg (1, 1)
	14 ifge (1, 1)
	15 95 (1, 1)
	17 dload_0 (1, 1)
	18 dload_2 (1, 1)
	19 dsub (1, 1)
	20 dstore (1, 1)
	21 #6 (1, 1)
	22 dload (1, 1)
	23 #6 (1, 1)
	24 dload_0 (1, 1)
	25 dload_2 (1, 1)
	26 dadd (1, 1)
	27 ddiv (1, 1)
	28 dstore (1, 1)
	29 #8 (1, 1)
	30 dload (1, 1)
	31 #8 (1, 1)
	32 dload (1, 1)
	33 #6 (1, 1)
	34 dmul (1, 1)
	35 dstore (1, 1)
	36 #10 (1, 1)
	37 ldc2_w (1, 1)
	38 nan (1, 1)
	40 dstore (1, 1)
	41 #12 (1, 1)
	42 ldc2_w (1, 1)
	43 2.0 (1, 1)
	45 dload_0 (1, 1)
	46 dmul (1, 1)
	47 dload (1, 1)
	48 #8 (1, 1)
	49 dmul (1, 1)
	50 dstore (1, 1)
	51 #14 (1, 1)
	52 dload (1, 1)
	53 #8 (1, 1)
	54 dload (1, 1)
	55 #8 (1, 1)
	56 dmul (1, 1)
	57 dstore (1, 1)
	58 #8 (1, 1)
	59 iconst_1 (1, 1)
	60 istore (1, 1)
	61 #16 (1, 1)
	62 dload (2, 3)
	63 #10 (2, 3)
	64 dload (2, 3)
	65 #12 (2, 3)
	66 dcmpl (2, 3)
	67 ifeq (2, 3)
	68 35 (2, 3)
	70 dload (2, 3)
	71 #10 (2, 3)
	72 dstore (2, 3)
	73 #12 (2, 3)
	74 dload (2, 3)
	75 #14 (2, 3)
	76 dload (2, 3)
	77 #8 (2, 3)
	78 dmul (2, 3)
	79 dstore (2, 3)
	80 #14 (2, 3)
	81 dload (2, 3)
	82 #12 (2, 3)
	83 dload (2, 3)
	84 #14 (2, 3)
	85 iload (2, 3)
	86 #16 (2, 3)
	87 iconst_2 (2, 3)
	88 imul (2, 3)
	89 iconst_1 (2, 3)
	90 iadd (2, 3)
	91 i2d (2, 3)
	92 ddiv (2, 3)
	93 dadd (2, 3)
	94 dstore (2, 3)
	95 #10 (2, 3)
	96 iinc (2, 3)
	97 #16 (2, 3)
	98 -89 (2, 3)
	99 goto (2, 3)
	100 -37 (2, 3)
	102 dload (1, 1)
	103 #10 (1, 1)
	104 dstore (1, 1)
	105 #4 (1, 1)
	106 goto (2, 2)
	107 17 (2, 2)
	109 dload_0 (2, 2)
	110 dload_0 (2, 2)
	111 dload_2 (2, 2)
	112 ddiv (2, 2)
	113 invokestatic (2, 2)
	114 org/apache/commons/math3/util/FastMath.log:(D)D (2, 2)
	116 dmul (2, 2)
	117 dload_2 (2, 2)
	118 dadd (2, 2)
	119 dload_0 (2, 2)
	120 dsub (2, 2)
	121 dstore (2, 2)
	122 #4 (2, 2)
	123 dload (0, 0)
	124 #4 (0, 0)
	125 dreturn (0, 0)

Method: logBinomialProbability
	0 iload_0 (1, 1)
	1 ifne (1, 1)
	2 45 (1, 1)
	4 dload_2 (2, 1)
	5 ldc2_w (2, 1)
	6 0.1 (2, 1)
	8 dcmpg (2, 1)
	9 ifge (2, 1)
	10 24 (2, 1)
	12 iload_1 (2, 1)
	13 i2d (2, 1)
	14 iload_1 (2, 1)
	15 i2d (2, 1)
	16 dload (2, 1)
	17 #4 (2, 1)
	18 dmul (2, 1)
	19 invokestatic (2, 1)
	20 org/apache/commons/math3/distribution/SaddlePointExpansion.getDeviancePart:(DD)D (2, 1)
	22 dneg (2, 1)
	23 iload_1 (2, 1)
	24 i2d (2, 1)
	25 dload_2 (2, 1)
	26 dmul (2, 1)
	27 dsub (2, 1)
	28 dstore (2, 1)
	29 #6 (2, 1)
	30 goto (2, 1)
	31 137 (2, 1)
	33 iload_1 (3, 2)
	34 i2d (3, 2)
	35 dload (3, 2)
	36 #4 (3, 2)
	37 invokestatic (3, 2)
	38 org/apache/commons/math3/util/FastMath.log:(D)D (3, 2)
	40 dmul (3, 2)
	41 dstore (3, 2)
	42 #6 (3, 2)
	43 goto (3, 2)
	44 124 (3, 2)
	46 iload_0 (2, 1)
	47 iload_1 (2, 1)
	48 if_icmpne (2, 1)
	49 45 (2, 1)
	51 dload (3, 1)
	52 #4 (3, 1)
	53 ldc2_w (3, 1)
	54 0.1 (3, 1)
	56 dcmpg (3, 1)
	57 ifge (3, 1)
	58 24 (3, 1)
	60 iload_1 (3, 1)
	61 i2d (3, 1)
	62 iload_1 (3, 1)
	63 i2d (3, 1)
	64 dload_2 (3, 1)
	65 dmul (3, 1)
	66 invokestatic (3, 1)
	67 org/apache/commons/math3/distribution/SaddlePointExpansion.getDeviancePart:(DD)D (3, 1)
	69 dneg (3, 1)
	70 iload_1 (3, 1)
	71 i2d (3, 1)
	72 dload (3, 1)
	73 #4 (3, 1)
	74 dmul (3, 1)
	75 dsub (3, 1)
	76 dstore (3, 1)
	77 #6 (3, 1)
	78 goto (3, 1)
	79 89 (3, 1)
	81 iload_1 (4, 2)
	82 i2d (4, 2)
	83 dload_2 (4, 2)
	84 invokestatic (4, 2)
	85 org/apache/commons/math3/util/FastMath.log:(D)D (4, 2)
	87 dmul (4, 2)
	88 dstore (4, 2)
	89 #6 (4, 2)
	90 goto (4, 2)
	91 77 (4, 2)
	93 iload_1 (3, 2)
	94 i2d (3, 2)
	95 invokestatic (3, 2)
	96 org/apache/commons/math3/distribution/SaddlePointExpansion.getStirlingError:(D)D (3, 2)
	98 iload_0 (3, 2)
	99 i2d (3, 2)
	100 invokestatic (3, 2)
	101 org/apache/commons/math3/distribution/SaddlePointExpansion.getStirlingError:(D)D (3, 2)
	103 dsub (3, 2)
	104 iload_1 (3, 2)
	105 iload_0 (3, 2)
	106 isub (3, 2)
	107 i2d (3, 2)
	108 invokestatic (3, 2)
	109 org/apache/commons/math3/distribution/SaddlePointExpansion.getStirlingError:(D)D (3, 2)
	111 dsub (3, 2)
	112 iload_0 (3, 2)
	113 i2d (3, 2)
	114 iload_1 (3, 2)
	115 i2d (3, 2)
	116 dload_2 (3, 2)
	117 dmul (3, 2)
	118 invokestatic (3, 2)
	119 org/apache/commons/math3/distribution/SaddlePointExpansion.getDeviancePart:(DD)D (3, 2)
	121 dsub (3, 2)
	122 iload_1 (3, 2)
	123 iload_0 (3, 2)
	124 isub (3, 2)
	125 i2d (3, 2)
	126 iload_1 (3, 2)
	127 i2d (3, 2)
	128 dload (3, 2)
	129 #4 (3, 2)
	130 dmul (3, 2)
	131 invokestatic (3, 2)
	132 org/apache/commons/math3/distribution/SaddlePointExpansion.getDeviancePart:(DD)D (3, 2)
	134 dsub (3, 2)
	135 dstore (3, 2)
	136 #6 (3, 2)
	137 ldc2_w (3, 2)
	138 6.283185307179586 (3, 2)
	140 iload_0 (3, 2)
	141 i2d (3, 2)
	142 dmul (3, 2)
	143 iload_1 (3, 2)
	144 iload_0 (3, 2)
	145 isub (3, 2)
	146 i2d (3, 2)
	147 dmul (3, 2)
	148 iload_1 (3, 2)
	149 i2d (3, 2)
	150 ddiv (3, 2)
	151 dstore (3, 2)
	152 #8 (3, 2)
	153 ldc2_w (3, 2)
	154 -0.5 (3, 2)
	156 dload (3, 2)
	157 #8 (3, 2)
	158 invokestatic (3, 2)
	159 org/apache/commons/math3/util/FastMath.log:(D)D (3, 2)
	161 dmul (3, 2)
	162 dload (3, 2)
	163 #6 (3, 2)
	164 dadd (3, 2)
	165 dstore (3, 2)
	166 #6 (3, 2)
	167 dload (0, 0)
	168 #6 (0, 0)
	169 dreturn (0, 0)

Method: <clinit>
	0 ldc2_w (0, 0)
	1 0.5 (0, 0)
	3 ldc2_w (0, 0)
	4 6.283185307179586 (0, 0)
	6 invokestatic (0, 0)
	7 org/apache/commons/math3/util/FastMath.log:(D)D (0, 0)
	9 dmul (0, 0)
	10 putstatic (0, 0)
	11 org/apache/commons/math3/distribution/SaddlePointExpansion.HALF_LOG_2_PI:D (0, 0)
	13 bipush (1, 4)
	14 31 (1, 4)
	15 newarray (1, 4)
	16 7 (1, 4)
	17 dup (1, 4)
	18 iconst_0 (1, 4)
	19 dconst_0 (1, 4)
	20 dastore (1, 4)
	21 dup (1, 4)
	22 iconst_1 (1, 4)
	23 ldc2_w (1, 4)
	24 0.15342640972002736 (1, 4)
	26 dastore (1, 4)
	27 dup (1, 4)
	28 iconst_2 (1, 4)
	29 ldc2_w (1, 4)
	30 0.08106146679532726 (1, 4)
	32 dastore (1, 4)
	33 dup (1, 4)
	34 iconst_3 (1, 4)
	35 ldc2_w (1, 4)
	36 0.05481412105191765 (1, 4)
	38 dastore (1, 4)
	39 dup (1, 4)
	40 iconst_4 (1, 4)
	41 ldc2_w (1, 4)
	42 0.0413406959554093 (1, 4)
	44 dastore (1, 4)
	45 dup (1, 4)
	46 iconst_5 (1, 4)
	47 ldc2_w (1, 4)
	48 0.03316287351993629 (1, 4)
	50 dastore (1, 4)
	51 dup (1, 4)
	52 bipush (1, 4)
	53 6 (1, 4)
	54 ldc2_w (1, 4)
	55 0.02767792568499834 (1, 4)
	57 dastore (1, 4)
	58 dup (1, 4)
	59 bipush (1, 4)
	60 7 (1, 4)
	61 ldc2_w (1, 4)
	62 0.023746163656297496 (1, 4)
	64 dastore (1, 4)
	65 dup (1, 4)
	66 bipush (1, 4)
	67 8 (1, 4)
	68 ldc2_w (1, 4)
	69 0.020790672103765093 (1, 4)
	71 dastore (1, 4)
	72 dup (1, 4)
	73 bipush (1, 4)
	74 9 (1, 4)
	75 ldc2_w (1, 4)
	76 0.018488450532673187 (1, 4)
	78 dastore (1, 4)
	79 dup (1, 4)
	80 bipush (1, 4)
	81 10 (1, 4)
	82 ldc2_w (1, 4)
	83 0.016644691189821193 (1, 4)
	85 dastore (1, 4)
	86 dup (1, 4)
	87 bipush (1, 4)
	88 11 (1, 4)
	89 ldc2_w (1, 4)
	90 0.015134973221917378 (1, 4)
	92 dastore (1, 4)
	93 dup (1, 4)
	94 bipush (1, 4)
	95 12 (1, 4)
	96 ldc2_w (1, 4)
	97 0.013876128823070748 (1, 4)
	99 dastore (1, 4)
	100 dup (1, 4)
	101 bipush (1, 4)
	102 13 (1, 4)
	103 ldc2_w (1, 4)
	104 0.012810465242920227 (1, 4)
	106 dastore (1, 4)
	107 dup (1, 4)
	108 bipush (1, 4)
	109 14 (1, 4)
	110 ldc2_w (1, 4)
	111 0.01189670994589177 (1, 4)
	113 dastore (1, 4)
	114 dup (1, 4)
	115 bipush (1, 4)
	116 15 (1, 4)
	117 ldc2_w (1, 4)
	118 0.011104559758206917 (1, 4)
	120 dastore (1, 4)
	121 dup (1, 4)
	122 bipush (1, 4)
	123 16 (1, 4)
	124 ldc2_w (1, 4)
	125 0.010411265261972096 (1, 4)
	127 dastore (1, 4)
	128 dup (1, 4)
	129 bipush (1, 4)
	130 17 (1, 4)
	131 ldc2_w (1, 4)
	132 0.009799416126158804 (1, 4)
	134 dastore (1, 4)
	135 dup (1, 4)
	136 bipush (1, 4)
	137 18 (1, 4)
	138 ldc2_w (1, 4)
	139 0.009255462182712733 (1, 4)
	141 dastore (1, 4)
	142 dup (1, 4)
	143 bipush (1, 4)
	144 19 (1, 4)
	145 ldc2_w (1, 4)
	146 0.008768700134139386 (1, 4)
	148 dastore (1, 4)
	149 dup (1, 4)
	150 bipush (1, 4)
	151 20 (1, 4)
	152 ldc2_w (1, 4)
	153 0.00833056343336287 (1, 4)
	155 dastore (1, 4)
	156 dup (1, 4)
	157 bipush (1, 4)
	158 21 (1, 4)
	159 ldc2_w (1, 4)
	160 0.00793411456431402 (1, 4)
	162 dastore (1, 4)
	163 dup (1, 4)
	164 bipush (1, 4)
	165 22 (1, 4)
	166 ldc2_w (1, 4)
	167 0.007573675487951841 (1, 4)
	169 dastore (1, 4)
	170 dup (1, 4)
	171 bipush (1, 4)
	172 23 (1, 4)
	173 ldc2_w (1, 4)
	174 0.007244554301320383 (1, 4)
	176 dastore (1, 4)
	177 dup (1, 4)
	178 bipush (1, 4)
	179 24 (1, 4)
	180 ldc2_w (1, 4)
	181 0.00694284010720953 (1, 4)
	183 dastore (1, 4)
	184 dup (1, 4)
	185 bipush (1, 4)
	186 25 (1, 4)
	187 ldc2_w (1, 4)
	188 0.006665247032707682 (1, 4)
	190 dastore (1, 4)
	191 dup (1, 4)
	192 bipush (1, 4)
	193 26 (1, 4)
	194 ldc2_w (1, 4)
	195 0.006408994188004207 (1, 4)
	197 dastore (1, 4)
	198 dup (1, 4)
	199 bipush (1, 4)
	200 27 (1, 4)
	201 ldc2_w (1, 4)
	202 0.006171712263039458 (1, 4)
	204 dastore (1, 4)
	205 dup (1, 4)
	206 bipush (1, 4)
	207 28 (1, 4)
	208 ldc2_w (1, 4)
	209 0.0059513701127588475 (1, 4)
	211 dastore (1, 4)
	212 dup (1, 4)
	213 bipush (1, 4)
	214 29 (1, 4)
	215 ldc2_w (1, 4)
	216 0.0057462165130101155 (1, 4)
	218 dastore (1, 4)
	219 dup (1, 4)
	220 bipush (1, 4)
	221 30 (1, 4)
	222 ldc2_w (1, 4)
	223 0.005554733551962801 (1, 4)
	225 dastore (1, 4)
	226 putstatic (1, 4)
	227 org/apache/commons/math3/distribution/SaddlePointExpansion.EXACT_STIRLING_ERRORS:[D (1, 4)
	229 return (0, 4)

