Method: <init>
	0 aload_0 (0, 0)
	1 aload_1 (0, 0)
	2 invokespecial (0, 0)
	3 org/apache/commons/math3/distribution/AbstractRealDistribution.<init>:(Lorg/apache/commons/math3/random/RandomGenerator;)V (0, 0)
	5 dload_2 (1, 1)
	6 dload (1, 1)
	7 #6 (1, 1)
	8 dcmpl (1, 1)
	9 iflt (1, 1)
	10 24 (1, 1)
	12 new (1, 1)
	13 org/apache/commons/math3/exception/NumberIsTooLargeException (1, 1)
	15 dup (1, 1)
	16 getstatic (1, 1)
	17 org/apache/commons/math3/exception/util/LocalizedFormats.LOWER_BOUND_NOT_BELOW_UPPER_BOUND:Lorg/apache/commons/math3/exception/util/LocalizedFormats; (1, 1)
	19 dload_2 (1, 1)
	20 invokestatic (1, 1)
	21 java/lang/Double.valueOf:(D)Ljava/lang/Double; (1, 1)
	23 dload (1, 1)
	24 #6 (1, 1)
	25 invokestatic (1, 1)
	26 java/lang/Double.valueOf:(D)Ljava/lang/Double; (1, 1)
	28 iconst_0 (1, 1)
	29 invokespecial (1, 1)
	30 org/apache/commons/math3/exception/NumberIsTooLargeException.<init>:(Lorg/apache/commons/math3/exception/util/Localizable;Ljava/lang/Number;Ljava/lang/Number;Z)V (1, 1)
	32 athrow (1, 1)
	33 dload (1, 1)
	34 #4 (1, 1)
	35 dload_2 (1, 1)
	36 dcmpg (1, 1)
	37 ifge (1, 1)
	38 24 (1, 1)
	40 new (1, 1)
	41 org/apache/commons/math3/exception/NumberIsTooSmallException (1, 1)
	43 dup (1, 1)
	44 getstatic (1, 1)
	45 org/apache/commons/math3/exception/util/LocalizedFormats.NUMBER_TOO_SMALL:Lorg/apache/commons/math3/exception/util/LocalizedFormats; (1, 1)
	47 dload (1, 1)
	48 #4 (1, 1)
	49 invokestatic (1, 1)
	50 java/lang/Double.valueOf:(D)Ljava/lang/Double; (1, 1)
	52 dload_2 (1, 1)
	53 invokestatic (1, 1)
	54 java/lang/Double.valueOf:(D)Ljava/lang/Double; (1, 1)
	56 iconst_1 (1, 1)
	57 invokespecial (1, 1)
	58 org/apache/commons/math3/exception/NumberIsTooSmallException.<init>:(Lorg/apache/commons/math3/exception/util/Localizable;Ljava/lang/Number;Ljava/lang/Number;Z)V (1, 1)
	60 athrow (1, 1)
	61 dload (1, 1)
	62 #4 (1, 1)
	63 dload (1, 1)
	64 #6 (1, 1)
	65 dcmpl (1, 1)
	66 ifle (1, 1)
	67 25 (1, 1)
	69 new (1, 1)
	70 org/apache/commons/math3/exception/NumberIsTooLargeException (1, 1)
	72 dup (1, 1)
	73 getstatic (1, 1)
	74 org/apache/commons/math3/exception/util/LocalizedFormats.NUMBER_TOO_LARGE:Lorg/apache/commons/math3/exception/util/LocalizedFormats; (1, 1)
	76 dload (1, 1)
	77 #4 (1, 1)
	78 invokestatic (1, 1)
	79 java/lang/Double.valueOf:(D)Ljava/lang/Double; (1, 1)
	81 dload (1, 1)
	82 #6 (1, 1)
	83 invokestatic (1, 1)
	84 java/lang/Double.valueOf:(D)Ljava/lang/Double; (1, 1)
	86 iconst_1 (1, 1)
	87 invokespecial (1, 1)
	88 org/apache/commons/math3/exception/NumberIsTooLargeException.<init>:(Lorg/apache/commons/math3/exception/util/Localizable;Ljava/lang/Number;Ljava/lang/Number;Z)V (1, 1)
	90 athrow (1, 1)
	91 aload_0 (0, 0)
	92 dload_2 (0, 0)
	93 putfield (0, 0)
	94 org/apache/commons/math3/distribution/TriangularDistribution.a:D (0, 0)
	96 aload_0 (0, 0)
	97 dload (0, 0)
	98 #4 (0, 0)
	99 putfield (0, 0)
	100 org/apache/commons/math3/distribution/TriangularDistribution.c:D (0, 0)
	102 aload_0 (0, 0)
	103 dload (0, 0)
	104 #6 (0, 0)
	105 putfield (0, 0)
	106 org/apache/commons/math3/distribution/TriangularDistribution.b:D (0, 0)
	108 aload_0 (0, 0)
	109 dload_2 (0, 0)
	110 invokestatic (0, 0)
	111 org/apache/commons/math3/util/FastMath.ulp:(D)D (0, 0)
	113 dload (0, 0)
	114 #6 (0, 0)
	115 invokestatic (0, 0)
	116 org/apache/commons/math3/util/FastMath.ulp:(D)D (0, 0)
	118 invokestatic (0, 0)
	119 org/apache/commons/math3/util/FastMath.max:(DD)D (0, 0)
	121 putfield (0, 0)
	122 org/apache/commons/math3/distribution/TriangularDistribution.solverAbsoluteAccuracy:D (0, 0)
	124 return (0, 0)

Method: getMode
	0 aload_0 (0, 0)
	1 getfield (0, 0)
	2 org/apache/commons/math3/distribution/TriangularDistribution.c:D (0, 0)
	4 dreturn (0, 0)

Method: getSolverAbsoluteAccuracy
	0 aload_0 (0, 0)
	1 getfield (0, 0)
	2 org/apache/commons/math3/distribution/TriangularDistribution.solverAbsoluteAccuracy:D (0, 0)
	4 dreturn (0, 0)

Method: density
	0 dload_1 (1, 1)
	1 aload_0 (1, 1)
	2 getfield (1, 1)
	3 org/apache/commons/math3/distribution/TriangularDistribution.a:D (1, 1)
	5 dcmpg (1, 1)
	6 ifge (1, 1)
	7 5 (1, 1)
	9 dconst_0 (1, 1)
	10 dreturn (1, 1)
	11 aload_0 (1, 1)
	12 getfield (1, 1)
	13 org/apache/commons/math3/distribution/TriangularDistribution.a:D (1, 1)
	15 dload_1 (1, 1)
	16 dcmpg (1, 1)
	17 ifgt (1, 1)
	18 49 (1, 1)
	20 dload_1 (1, 1)
	21 aload_0 (1, 1)
	22 getfield (1, 1)
	23 org/apache/commons/math3/distribution/TriangularDistribution.c:D (1, 1)
	25 dcmpg (1, 1)
	26 ifge (1, 1)
	27 40 (1, 1)
	29 ldc2_w (1, 1)
	30 2.0 (1, 1)
	32 dload_1 (1, 1)
	33 aload_0 (1, 1)
	34 getfield (1, 1)
	35 org/apache/commons/math3/distribution/TriangularDistribution.a:D (1, 1)
	37 dsub (1, 1)
	38 dmul (1, 1)
	39 dstore_3 (1, 1)
	40 aload_0 (1, 1)
	41 getfield (1, 1)
	42 org/apache/commons/math3/distribution/TriangularDistribution.b:D (1, 1)
	44 aload_0 (1, 1)
	45 getfield (1, 1)
	46 org/apache/commons/math3/distribution/TriangularDistribution.a:D (1, 1)
	48 dsub (1, 1)
	49 aload_0 (1, 1)
	50 getfield (1, 1)
	51 org/apache/commons/math3/distribution/TriangularDistribution.c:D (1, 1)
	53 aload_0 (1, 1)
	54 getfield (1, 1)
	55 org/apache/commons/math3/distribution/TriangularDistribution.a:D (1, 1)
	57 dsub (1, 1)
	58 dmul (1, 1)
	59 dstore (1, 1)
	60 #5 (1, 1)
	61 dload_3 (1, 1)
	62 dload (1, 1)
	63 #5 (1, 1)
	64 ddiv (1, 1)
	65 dreturn (1, 1)
	66 dload_1 (1, 1)
	67 aload_0 (1, 1)
	68 getfield (1, 1)
	69 org/apache/commons/math3/distribution/TriangularDistribution.c:D (1, 1)
	71 dcmpl (1, 1)
	72 ifne (1, 1)
	73 17 (1, 1)
	75 ldc2_w (1, 1)
	76 2.0 (1, 1)
	78 aload_0 (1, 1)
	79 getfield (1, 1)
	80 org/apache/commons/math3/distribution/TriangularDistribution.b:D (1, 1)
	82 aload_0 (1, 1)
	83 getfield (1, 1)
	84 org/apache/commons/math3/distribution/TriangularDistribution.a:D (1, 1)
	86 dsub (1, 1)
	87 ddiv (1, 1)
	88 dreturn (1, 1)
	89 aload_0 (1, 1)
	90 getfield (1, 1)
	91 org/apache/commons/math3/distribution/TriangularDistribution.c:D (1, 1)
	93 dload_1 (1, 1)
	94 dcmpg (1, 1)
	95 ifge (1, 1)
	96 49 (1, 1)
	98 dload_1 (1, 1)
	99 aload_0 (1, 1)
	100 getfield (1, 1)
	101 org/apache/commons/math3/distribution/TriangularDistribution.b:D (1, 1)
	103 dcmpg (1, 1)
	104 ifgt (1, 1)
	105 40 (1, 1)
	107 ldc2_w (1, 1)
	108 2.0 (1, 1)
	110 aload_0 (1, 1)
	111 getfield (1, 1)
	112 org/apache/commons/math3/distribution/TriangularDistribution.b:D (1, 1)
	114 dload_1 (1, 1)
	115 dsub (1, 1)
	116 dmul (1, 1)
	117 dstore_3 (1, 1)
	118 aload_0 (1, 1)
	119 getfield (1, 1)
	120 org/apache/commons/math3/distribution/TriangularDistribution.b:D (1, 1)
	122 aload_0 (1, 1)
	123 getfield (1, 1)
	124 org/apache/commons/math3/distribution/TriangularDistribution.a:D (1, 1)
	126 dsub (1, 1)
	127 aload_0 (1, 1)
	128 getfield (1, 1)
	129 org/apache/commons/math3/distribution/TriangularDistribution.b:D (1, 1)
	131 aload_0 (1, 1)
	132 getfield (1, 1)
	133 org/apache/commons/math3/distribution/TriangularDistribution.c:D (1, 1)
	135 dsub (1, 1)
	136 dmul (1, 1)
	137 dstore (1, 1)
	138 #5 (1, 1)
	139 dload_3 (1, 1)
	140 dload (1, 1)
	141 #5 (1, 1)
	142 ddiv (1, 1)
	143 dreturn (1, 1)
	144 dconst_0 (0, 0)
	145 dreturn (0, 0)

Method: cumulativeProbability
	0 dload_1 (1, 1)
	1 aload_0 (1, 1)
	2 getfield (1, 1)
	3 org/apache/commons/math3/distribution/TriangularDistribution.a:D (1, 1)
	5 dcmpg (1, 1)
	6 ifge (1, 1)
	7 5 (1, 1)
	9 dconst_0 (1, 1)
	10 dreturn (1, 1)
	11 aload_0 (1, 1)
	12 getfield (1, 1)
	13 org/apache/commons/math3/distribution/TriangularDistribution.a:D (1, 1)
	15 dload_1 (1, 1)
	16 dcmpg (1, 1)
	17 ifgt (1, 1)
	18 52 (1, 1)
	20 dload_1 (1, 1)
	21 aload_0 (1, 1)
	22 getfield (1, 1)
	23 org/apache/commons/math3/distribution/TriangularDistribution.c:D (1, 1)
	25 dcmpg (1, 1)
	26 ifge (1, 1)
	27 43 (1, 1)
	29 dload_1 (1, 1)
	30 aload_0 (1, 1)
	31 getfield (1, 1)
	32 org/apache/commons/math3/distribution/TriangularDistribution.a:D (1, 1)
	34 dsub (1, 1)
	35 dload_1 (1, 1)
	36 aload_0 (1, 1)
	37 getfield (1, 1)
	38 org/apache/commons/math3/distribution/TriangularDistribution.a:D (1, 1)
	40 dsub (1, 1)
	41 dmul (1, 1)
	42 dstore_3 (1, 1)
	43 aload_0 (1, 1)
	44 getfield (1, 1)
	45 org/apache/commons/math3/distribution/TriangularDistribution.b:D (1, 1)
	47 aload_0 (1, 1)
	48 getfield (1, 1)
	49 org/apache/commons/math3/distribution/TriangularDistribution.a:D (1, 1)
	51 dsub (1, 1)
	52 aload_0 (1, 1)
	53 getfield (1, 1)
	54 org/apache/commons/math3/distribution/TriangularDistribution.c:D (1, 1)
	56 aload_0 (1, 1)
	57 getfield (1, 1)
	58 org/apache/commons/math3/distribution/TriangularDistribution.a:D (1, 1)
	60 dsub (1, 1)
	61 dmul (1, 1)
	62 dstore (1, 1)
	63 #5 (1, 1)
	64 dload_3 (1, 1)
	65 dload (1, 1)
	66 #5 (1, 1)
	67 ddiv (1, 1)
	68 dreturn (1, 1)
	69 dload_1 (1, 1)
	70 aload_0 (1, 1)
	71 getfield (1, 1)
	72 org/apache/commons/math3/distribution/TriangularDistribution.c:D (1, 1)
	74 dcmpl (1, 1)
	75 ifne (1, 1)
	76 23 (1, 1)
	78 aload_0 (1, 1)
	79 getfield (1, 1)
	80 org/apache/commons/math3/distribution/TriangularDistribution.c:D (1, 1)
	82 aload_0 (1, 1)
	83 getfield (1, 1)
	84 org/apache/commons/math3/distribution/TriangularDistribution.a:D (1, 1)
	86 dsub (1, 1)
	87 aload_0 (1, 1)
	88 getfield (1, 1)
	89 org/apache/commons/math3/distribution/TriangularDistribution.b:D (1, 1)
	91 aload_0 (1, 1)
	92 getfield (1, 1)
	93 org/apache/commons/math3/distribution/TriangularDistribution.a:D (1, 1)
	95 dsub (1, 1)
	96 ddiv (1, 1)
	97 dreturn (1, 1)
	98 aload_0 (1, 1)
	99 getfield (1, 1)
	100 org/apache/commons/math3/distribution/TriangularDistribution.c:D (1, 1)
	102 dload_1 (1, 1)
	103 dcmpg (1, 1)
	104 ifge (1, 1)
	105 54 (1, 1)
	107 dload_1 (1, 1)
	108 aload_0 (1, 1)
	109 getfield (1, 1)
	110 org/apache/commons/math3/distribution/TriangularDistribution.b:D (1, 1)
	112 dcmpg (1, 1)
	113 ifgt (1, 1)
	114 45 (1, 1)
	116 aload_0 (1, 1)
	117 getfield (1, 1)
	118 org/apache/commons/math3/distribution/TriangularDistribution.b:D (1, 1)
	120 dload_1 (1, 1)
	121 dsub (1, 1)
	122 aload_0 (1, 1)
	123 getfield (1, 1)
	124 org/apache/commons/math3/distribution/TriangularDistribution.b:D (1, 1)
	126 dload_1 (1, 1)
	127 dsub (1, 1)
	128 dmul (1, 1)
	129 dstore_3 (1, 1)
	130 aload_0 (1, 1)
	131 getfield (1, 1)
	132 org/apache/commons/math3/distribution/TriangularDistribution.b:D (1, 1)
	134 aload_0 (1, 1)
	135 getfield (1, 1)
	136 org/apache/commons/math3/distribution/TriangularDistribution.a:D (1, 1)
	138 dsub (1, 1)
	139 aload_0 (1, 1)
	140 getfield (1, 1)
	141 org/apache/commons/math3/distribution/TriangularDistribution.b:D (1, 1)
	143 aload_0 (1, 1)
	144 getfield (1, 1)
	145 org/apache/commons/math3/distribution/TriangularDistribution.c:D (1, 1)
	147 dsub (1, 1)
	148 dmul (1, 1)
	149 dstore (1, 1)
	150 #5 (1, 1)
	151 dconst_1 (1, 1)
	152 dload_3 (1, 1)
	153 dload (1, 1)
	154 #5 (1, 1)
	155 ddiv (1, 1)
	156 dsub (1, 1)
	157 dreturn (1, 1)
	158 dconst_1 (0, 0)
	159 dreturn (0, 0)

Method: getNumericalMean
	0 aload_0 (0, 0)
	1 getfield (0, 0)
	2 org/apache/commons/math3/distribution/TriangularDistribution.a:D (0, 0)
	4 aload_0 (0, 0)
	5 getfield (0, 0)
	6 org/apache/commons/math3/distribution/TriangularDistribution.b:D (0, 0)
	8 dadd (0, 0)
	9 aload_0 (0, 0)
	10 getfield (0, 0)
	11 org/apache/commons/math3/distribution/TriangularDistribution.c:D (0, 0)
	13 dadd (0, 0)
	14 ldc2_w (0, 0)
	15 3.0 (0, 0)
	17 ddiv (0, 0)
	18 dreturn (0, 0)

Method: getNumericalVariance
	0 aload_0 (0, 0)
	1 getfield (0, 0)
	2 org/apache/commons/math3/distribution/TriangularDistribution.a:D (0, 0)
	4 aload_0 (0, 0)
	5 getfield (0, 0)
	6 org/apache/commons/math3/distribution/TriangularDistribution.a:D (0, 0)
	8 dmul (0, 0)
	9 aload_0 (0, 0)
	10 getfield (0, 0)
	11 org/apache/commons/math3/distribution/TriangularDistribution.b:D (0, 0)
	13 aload_0 (0, 0)
	14 getfield (0, 0)
	15 org/apache/commons/math3/distribution/TriangularDistribution.b:D (0, 0)
	17 dmul (0, 0)
	18 dadd (0, 0)
	19 aload_0 (0, 0)
	20 getfield (0, 0)
	21 org/apache/commons/math3/distribution/TriangularDistribution.c:D (0, 0)
	23 aload_0 (0, 0)
	24 getfield (0, 0)
	25 org/apache/commons/math3/distribution/TriangularDistribution.c:D (0, 0)
	27 dmul (0, 0)
	28 dadd (0, 0)
	29 aload_0 (0, 0)
	30 getfield (0, 0)
	31 org/apache/commons/math3/distribution/TriangularDistribution.a:D (0, 0)
	33 aload_0 (0, 0)
	34 getfield (0, 0)
	35 org/apache/commons/math3/distribution/TriangularDistribution.b:D (0, 0)
	37 dmul (0, 0)
	38 dsub (0, 0)
	39 aload_0 (0, 0)
	40 getfield (0, 0)
	41 org/apache/commons/math3/distribution/TriangularDistribution.a:D (0, 0)
	43 aload_0 (0, 0)
	44 getfield (0, 0)
	45 org/apache/commons/math3/distribution/TriangularDistribution.c:D (0, 0)
	47 dmul (0, 0)
	48 dsub (0, 0)
	49 aload_0 (0, 0)
	50 getfield (0, 0)
	51 org/apache/commons/math3/distribution/TriangularDistribution.b:D (0, 0)
	53 aload_0 (0, 0)
	54 getfield (0, 0)
	55 org/apache/commons/math3/distribution/TriangularDistribution.c:D (0, 0)
	57 dmul (0, 0)
	58 dsub (0, 0)
	59 ldc2_w (0, 0)
	60 18.0 (0, 0)
	62 ddiv (0, 0)
	63 dreturn (0, 0)

Method: getSupportLowerBound
	0 aload_0 (0, 0)
	1 getfield (0, 0)
	2 org/apache/commons/math3/distribution/TriangularDistribution.a:D (0, 0)
	4 dreturn (0, 0)

Method: getSupportUpperBound
	0 aload_0 (0, 0)
	1 getfield (0, 0)
	2 org/apache/commons/math3/distribution/TriangularDistribution.b:D (0, 0)
	4 dreturn (0, 0)

Method: isSupportLowerBoundInclusive
	0 iconst_1 (0, 0)
	1 ireturn (0, 0)

Method: isSupportUpperBoundInclusive
	0 iconst_1 (0, 0)
	1 ireturn (0, 0)

Method: isSupportConnected
	0 iconst_1 (0, 0)
	1 ireturn (0, 0)

Method: inverseCumulativeProbability
	0 dload_1 (1, 1)
	1 dconst_0 (1, 1)
	2 dcmpg (1, 1)
	3 iflt (1, 1)
	4 9 (1, 1)
	6 dload_1 (1, 1)
	7 dconst_1 (1, 1)
	8 dcmpl (1, 1)
	9 ifle (1, 1)
	10 23 (1, 1)
	12 new (1, 1)
	13 org/apache/commons/math3/exception/OutOfRangeException (1, 1)
	15 dup (1, 1)
	16 dload_1 (1, 1)
	17 invokestatic (1, 1)
	18 java/lang/Double.valueOf:(D)Ljava/lang/Double; (1, 1)
	20 iconst_0 (1, 1)
	21 invokestatic (1, 1)
	22 java/lang/Integer.valueOf:(I)Ljava/lang/Integer; (1, 1)
	24 iconst_1 (1, 1)
	25 invokestatic (1, 1)
	26 java/lang/Integer.valueOf:(I)Ljava/lang/Integer; (1, 1)
	28 invokespecial (1, 1)
	29 org/apache/commons/math3/exception/OutOfRangeException.<init>:(Ljava/lang/Number;Ljava/lang/Number;Ljava/lang/Number;)V (1, 1)
	31 athrow (1, 1)
	32 dload_1 (1, 1)
	33 dconst_0 (1, 1)
	34 dcmpl (1, 1)
	35 ifne (1, 1)
	36 8 (1, 1)
	38 aload_0 (1, 1)
	39 getfield (1, 1)
	40 org/apache/commons/math3/distribution/TriangularDistribution.a:D (1, 1)
	42 dreturn (1, 1)
	43 dload_1 (1, 1)
	44 dconst_1 (1, 1)
	45 dcmpl (1, 1)
	46 ifne (1, 1)
	47 8 (1, 1)
	49 aload_0 (1, 1)
	50 getfield (1, 1)
	51 org/apache/commons/math3/distribution/TriangularDistribution.b:D (1, 1)
	53 dreturn (1, 1)
	54 dload_1 (1, 1)
	55 aload_0 (1, 1)
	56 getfield (1, 1)
	57 org/apache/commons/math3/distribution/TriangularDistribution.c:D (1, 1)
	59 aload_0 (1, 1)
	60 getfield (1, 1)
	61 org/apache/commons/math3/distribution/TriangularDistribution.a:D (1, 1)
	63 dsub (1, 1)
	64 aload_0 (1, 1)
	65 getfield (1, 1)
	66 org/apache/commons/math3/distribution/TriangularDistribution.b:D (1, 1)
	68 aload_0 (1, 1)
	69 getfield (1, 1)
	70 org/apache/commons/math3/distribution/TriangularDistribution.a:D (1, 1)
	72 dsub (1, 1)
	73 ddiv (1, 1)
	74 dcmpg (1, 1)
	75 ifge (1, 1)
	76 33 (1, 1)
	78 aload_0 (1, 1)
	79 getfield (1, 1)
	80 org/apache/commons/math3/distribution/TriangularDistribution.a:D (1, 1)
	82 dload_1 (1, 1)
	83 aload_0 (1, 1)
	84 getfield (1, 1)
	85 org/apache/commons/math3/distribution/TriangularDistribution.b:D (1, 1)
	87 aload_0 (1, 1)
	88 getfield (1, 1)
	89 org/apache/commons/math3/distribution/TriangularDistribution.a:D (1, 1)
	91 dsub (1, 1)
	92 dmul (1, 1)
	93 aload_0 (1, 1)
	94 getfield (1, 1)
	95 org/apache/commons/math3/distribution/TriangularDistribution.c:D (1, 1)
	97 aload_0 (1, 1)
	98 getfield (1, 1)
	99 org/apache/commons/math3/distribution/TriangularDistribution.a:D (1, 1)
	101 dsub (1, 1)
	102 dmul (1, 1)
	103 invokestatic (1, 1)
	104 org/apache/commons/math3/util/FastMath.sqrt:(D)D (1, 1)
	106 dadd (1, 1)
	107 dreturn (1, 1)
	108 aload_0 (0, 0)
	109 getfield (0, 0)
	110 org/apache/commons/math3/distribution/TriangularDistribution.b:D (0, 0)
	112 dconst_1 (0, 0)
	113 dload_1 (0, 0)
	114 dsub (0, 0)
	115 aload_0 (0, 0)
	116 getfield (0, 0)
	117 org/apache/commons/math3/distribution/TriangularDistribution.b:D (0, 0)
	119 aload_0 (0, 0)
	120 getfield (0, 0)
	121 org/apache/commons/math3/distribution/TriangularDistribution.a:D (0, 0)
	123 dsub (0, 0)
	124 dmul (0, 0)
	125 aload_0 (0, 0)
	126 getfield (0, 0)
	127 org/apache/commons/math3/distribution/TriangularDistribution.b:D (0, 0)
	129 aload_0 (0, 0)
	130 getfield (0, 0)
	131 org/apache/commons/math3/distribution/TriangularDistribution.c:D (0, 0)
	133 dsub (0, 0)
	134 dmul (0, 0)
	135 invokestatic (0, 0)
	136 org/apache/commons/math3/util/FastMath.sqrt:(D)D (0, 0)
	138 dsub (0, 0)
	139 dreturn (0, 0)

