Method: <init>
	0 aload_0 (0, 0)
	1 aload_1 (0, 0)
	2 invokespecial (0, 0)
	3 org/apache/commons/math3/distribution/AbstractIntegerDistribution.<init>:(Lorg/apache/commons/math3/random/RandomGenerator;)V (0, 0)
	5 iload_2 (1, 1)
	6 iload_3 (1, 1)
	7 if_icmple (1, 1)
	8 23 (1, 1)
	10 new (1, 1)
	11 org/apache/commons/math3/exception/NumberIsTooLargeException (1, 1)
	13 dup (1, 1)
	14 getstatic (1, 1)
	15 org/apache/commons/math3/exception/util/LocalizedFormats.LOWER_BOUND_NOT_BELOW_UPPER_BOUND:Lorg/apache/commons/math3/exception/util/LocalizedFormats; (1, 1)
	17 iload_2 (1, 1)
	18 invokestatic (1, 1)
	19 java/lang/Integer.valueOf:(I)Ljava/lang/Integer; (1, 1)
	21 iload_3 (1, 1)
	22 invokestatic (1, 1)
	23 java/lang/Integer.valueOf:(I)Ljava/lang/Integer; (1, 1)
	25 iconst_1 (1, 1)
	26 invokespecial (1, 1)
	27 org/apache/commons/math3/exception/NumberIsTooLargeException.<init>:(Lorg/apache/commons/math3/exception/util/Localizable;Ljava/lang/Number;Ljava/lang/Number;Z)V (1, 1)
	29 athrow (1, 1)
	30 aload_0 (0, 0)
	31 iload_2 (0, 0)
	32 putfield (0, 0)
	33 org/apache/commons/math3/distribution/UniformIntegerDistribution.lower:I (0, 0)
	35 aload_0 (0, 0)
	36 iload_3 (0, 0)
	37 putfield (0, 0)
	38 org/apache/commons/math3/distribution/UniformIntegerDistribution.upper:I (0, 0)
	40 return (0, 0)

Method: probability
	0 iload_1 (1, 1)
	1 aload_0 (1, 1)
	2 getfield (1, 1)
	3 org/apache/commons/math3/distribution/UniformIntegerDistribution.lower:I (1, 1)
	5 if_icmplt (1, 1)
	6 11 (1, 1)
	8 iload_1 (1, 1)
	9 aload_0 (1, 1)
	10 getfield (1, 1)
	11 org/apache/commons/math3/distribution/UniformIntegerDistribution.upper:I (1, 1)
	13 if_icmple (1, 1)
	14 5 (1, 1)
	16 dconst_0 (1, 1)
	17 dreturn (1, 1)
	18 dconst_1 (0, 0)
	19 aload_0 (0, 0)
	20 getfield (0, 0)
	21 org/apache/commons/math3/distribution/UniformIntegerDistribution.upper:I (0, 0)
	23 aload_0 (0, 0)
	24 getfield (0, 0)
	25 org/apache/commons/math3/distribution/UniformIntegerDistribution.lower:I (0, 0)
	27 isub (0, 0)
	28 iconst_1 (0, 0)
	29 iadd (0, 0)
	30 i2d (0, 0)
	31 ddiv (0, 0)
	32 dreturn (0, 0)

Method: cumulativeProbability
	0 iload_1 (1, 1)
	1 aload_0 (1, 1)
	2 getfield (1, 1)
	3 org/apache/commons/math3/distribution/UniformIntegerDistribution.lower:I (1, 1)
	5 if_icmpge (1, 1)
	6 5 (1, 1)
	8 dconst_0 (1, 1)
	9 dreturn (1, 1)
	10 iload_1 (1, 1)
	11 aload_0 (1, 1)
	12 getfield (1, 1)
	13 org/apache/commons/math3/distribution/UniformIntegerDistribution.upper:I (1, 1)
	15 if_icmple (1, 1)
	16 5 (1, 1)
	18 dconst_1 (1, 1)
	19 dreturn (1, 1)
	20 iload_1 (0, 0)
	21 aload_0 (0, 0)
	22 getfield (0, 0)
	23 org/apache/commons/math3/distribution/UniformIntegerDistribution.lower:I (0, 0)
	25 isub (0, 0)
	26 i2d (0, 0)
	27 dconst_1 (0, 0)
	28 dadd (0, 0)
	29 aload_0 (0, 0)
	30 getfield (0, 0)
	31 org/apache/commons/math3/distribution/UniformIntegerDistribution.upper:I (0, 0)
	33 aload_0 (0, 0)
	34 getfield (0, 0)
	35 org/apache/commons/math3/distribution/UniformIntegerDistribution.lower:I (0, 0)
	37 isub (0, 0)
	38 i2d (0, 0)
	39 dconst_1 (0, 0)
	40 dadd (0, 0)
	41 ddiv (0, 0)
	42 dreturn (0, 0)

Method: getNumericalMean
	0 ldc2_w (0, 0)
	1 0.5 (0, 0)
	3 aload_0 (0, 0)
	4 getfield (0, 0)
	5 org/apache/commons/math3/distribution/UniformIntegerDistribution.lower:I (0, 0)
	7 aload_0 (0, 0)
	8 getfield (0, 0)
	9 org/apache/commons/math3/distribution/UniformIntegerDistribution.upper:I (0, 0)
	11 iadd (0, 0)
	12 i2d (0, 0)
	13 dmul (0, 0)
	14 dreturn (0, 0)

Method: getNumericalVariance
	0 aload_0 (0, 0)
	1 getfield (0, 0)
	2 org/apache/commons/math3/distribution/UniformIntegerDistribution.upper:I (0, 0)
	4 aload_0 (0, 0)
	5 getfield (0, 0)
	6 org/apache/commons/math3/distribution/UniformIntegerDistribution.lower:I (0, 0)
	8 isub (0, 0)
	9 iconst_1 (0, 0)
	10 iadd (0, 0)
	11 i2d (0, 0)
	12 dstore_1 (0, 0)
	13 dload_1 (0, 0)
	14 dload_1 (0, 0)
	15 dmul (0, 0)
	16 dconst_1 (0, 0)
	17 dsub (0, 0)
	18 ldc2_w (0, 0)
	19 12.0 (0, 0)
	21 ddiv (0, 0)
	22 dreturn (0, 0)

Method: getSupportLowerBound
	0 aload_0 (0, 0)
	1 getfield (0, 0)
	2 org/apache/commons/math3/distribution/UniformIntegerDistribution.lower:I (0, 0)
	4 ireturn (0, 0)

Method: getSupportUpperBound
	0 aload_0 (0, 0)
	1 getfield (0, 0)
	2 org/apache/commons/math3/distribution/UniformIntegerDistribution.upper:I (0, 0)
	4 ireturn (0, 0)

Method: isSupportConnected
	0 iconst_1 (0, 0)
	1 ireturn (0, 0)

Method: sample
	0 aload_0 (0, 0)
	1 getfield (0, 0)
	2 org/apache/commons/math3/distribution/UniformIntegerDistribution.upper:I (0, 0)
	4 aload_0 (0, 0)
	5 getfield (0, 0)
	6 org/apache/commons/math3/distribution/UniformIntegerDistribution.lower:I (0, 0)
	8 isub (0, 0)
	9 iconst_1 (0, 0)
	10 iadd (0, 0)
	11 istore_1 (0, 0)
	12 iload_1 (1, 1)
	13 ifgt (1, 1)
	14 34 (1, 1)
	16 aload_0 (2, 3)
	17 getfield (2, 3)
	18 org/apache/commons/math3/distribution/UniformIntegerDistribution.random:Lorg/apache/commons/math3/random/RandomGenerator; (2, 3)
	20 invokeinterface (2, 3)
	21 org/apache/commons/math3/random/RandomGenerator.nextInt:(I)I (2, 3)
	23 0 (2, 3)
	25 istore_2 (2, 3)
	26 iload_2 (2, 1)
	27 aload_0 (2, 1)
	28 getfield (2, 1)
	29 org/apache/commons/math3/distribution/UniformIntegerDistribution.lower:I (2, 1)
	31 if_icmplt (2, 1)
	32 13 (2, 1)
	34 iload_2 (2, 1)
	35 aload_0 (2, 1)
	36 getfield (2, 1)
	37 org/apache/commons/math3/distribution/UniformIntegerDistribution.upper:I (2, 1)
	39 if_icmpgt (2, 1)
	40 5 (2, 1)
	42 iload_2 (2, 1)
	43 ireturn (2, 1)
	44 goto (1, 1)
	45 -28 (1, 1)
	47 aload_0 (1, 1)
	48 getfield (1, 1)
	49 org/apache/commons/math3/distribution/UniformIntegerDistribution.lower:I (1, 1)
	51 aload_0 (1, 1)
	52 getfield (1, 1)
	53 org/apache/commons/math3/distribution/UniformIntegerDistribution.random:Lorg/apache/commons/math3/random/RandomGenerator; (1, 1)
	55 iload_1 (1, 1)
	56 invokeinterface (1, 1)
	57 org/apache/commons/math3/random/RandomGenerator.org/apache/commons/math3/distribution/UniformIntegerDistribution (1, 1)
	59 0 (1, 1)
	61 iadd (1, 1)
	62 ireturn (1, 1)

