Method: <init>
	0 aload_0 (0, 0)
	1 invokespecial (0, 0)
	2 java/lang/Object.<init>:()V (0, 0)
	4 aload_0 (0, 0)
	5 dload_2 (0, 0)
	6 putfield (0, 0)
	7 org/apache/commons/math3/distribution/ZipfDistribution$ZipfRejectionInversionSampler.exponent:D (0, 0)
	9 aload_0 (0, 0)
	10 iload_1 (0, 0)
	11 putfield (0, 0)
	12 org/apache/commons/math3/distribution/ZipfDistribution$ZipfRejectionInversionSampler.numberOfElements:I (0, 0)
	14 aload_0 (0, 0)
	15 aload_0 (0, 0)
	16 ldc2_w (0, 0)
	17 1.5 (0, 0)
	19 invokespecial (0, 0)
	20 org/apache/commons/math3/distribution/ZipfDistribution$ZipfRejectionInversionSampler.hIntegral:(D)D (0, 0)
	22 dconst_1 (0, 0)
	23 dsub (0, 0)
	24 putfield (0, 0)
	25 org/apache/commons/math3/distribution/ZipfDistribution$ZipfRejectionInversionSampler.hIntegralX1:D (0, 0)
	27 aload_0 (0, 0)
	28 aload_0 (0, 0)
	29 iload_1 (0, 0)
	30 i2d (0, 0)
	31 ldc2_w (0, 0)
	32 0.5 (0, 0)
	34 dadd (0, 0)
	35 invokespecial (0, 0)
	36 org/apache/commons/math3/distribution/ZipfDistribution$ZipfRejectionInversionSampler.hIntegral:(D)D (0, 0)
	38 putfield (0, 0)
	39 org/apache/commons/math3/distribution/ZipfDistribution$ZipfRejectionInversionSampler.hIntegralNumberOfElements:D (0, 0)
	41 aload_0 (0, 0)
	42 ldc2_w (0, 0)
	43 2.0 (0, 0)
	45 aload_0 (0, 0)
	46 aload_0 (0, 0)
	47 ldc2_w (0, 0)
	48 2.5 (0, 0)
	50 invokespecial (0, 0)
	51 org/apache/commons/math3/distribution/ZipfDistribution$ZipfRejectionInversionSampler.hIntegral:(D)D (0, 0)
	53 aload_0 (0, 0)
	54 ldc2_w (0, 0)
	55 2.0 (0, 0)
	57 invokespecial (0, 0)
	58 org/apache/commons/math3/distribution/ZipfDistribution$ZipfRejectionInversionSampler.h:(D)D (0, 0)
	60 dsub (0, 0)
	61 invokespecial (0, 0)
	62 org/apache/commons/math3/distribution/ZipfDistribution$ZipfRejectionInversionSampler.hIntegralInverse:(D)D (0, 0)
	64 dsub (0, 0)
	65 putfield (0, 0)
	66 org/apache/commons/math3/distribution/ZipfDistribution$ZipfRejectionInversionSampler.s:D (0, 0)
	68 return (0, 0)

Method: sample
	0 aload_0 (0, 0)
	1 getfield (0, 0)
	2 org/apache/commons/math3/distribution/ZipfDistribution$ZipfRejectionInversionSampler.hIntegralNumberOfElements:D (0, 0)
	4 aload_1 (0, 0)
	5 invokeinterface (0, 0)
	6 org/apache/commons/math3/random/RandomGenerator.org/apache/commons/math3/util/FastMath (0, 0)
	8 0 (0, 0)
	10 aload_0 (0, 0)
	11 getfield (0, 0)
	12 org/apache/commons/math3/distribution/ZipfDistribution$ZipfRejectionInversionSampler.hIntegralX1:D (0, 0)
	14 aload_0 (0, 0)
	15 getfield (0, 0)
	16 org/apache/commons/math3/distribution/ZipfDistribution$ZipfRejectionInversionSampler.hIntegralNumberOfElements:D (0, 0)
	18 dsub (0, 0)
	19 dmul (0, 0)
	20 dadd (0, 0)
	21 dstore_2 (0, 0)
	22 aload_0 (1, 1)
	23 dload_2 (1, 1)
	24 invokespecial (1, 1)
	25 org/apache/commons/math3/distribution/ZipfDistribution$ZipfRejectionInversionSampler.hIntegralInverse:(D)D (1, 1)
	27 dstore (1, 1)
	28 #4 (1, 1)
	29 dload (1, 1)
	30 #4 (1, 1)
	31 ldc2_w (1, 1)
	32 0.5 (1, 1)
	34 dadd (1, 1)
	35 d2i (1, 1)
	36 istore (1, 1)
	37 #6 (1, 1)
	38 iload (2, 1)
	39 #6 (2, 1)
	40 iconst_1 (2, 1)
	41 if_icmpge (2, 1)
	42 9 (2, 1)
	44 iconst_1 (2, 1)
	45 istore (2, 1)
	46 #6 (2, 1)
	47 goto (2, 1)
	48 18 (2, 1)
	50 iload (2, 1)
	51 #6 (2, 1)
	52 aload_0 (2, 1)
	53 getfield (2, 1)
	54 org/apache/commons/math3/distribution/ZipfDistribution$ZipfRejectionInversionSampler.numberOfElements:I (2, 1)
	56 if_icmple (2, 1)
	57 9 (2, 1)
	59 aload_0 (2, 1)
	60 getfield (2, 1)
	61 org/apache/commons/math3/distribution/ZipfDistribution$ZipfRejectionInversionSampler.numberOfElements:I (2, 1)
	63 istore (2, 1)
	64 #6 (2, 1)
	65 iload (3, 1)
	66 #6 (3, 1)
	67 i2d (3, 1)
	68 dload (3, 1)
	69 #4 (3, 1)
	70 dsub (3, 1)
	71 aload_0 (3, 1)
	72 getfield (3, 1)
	73 org/apache/commons/math3/distribution/ZipfDistribution$ZipfRejectionInversionSampler.s:D (3, 1)
	75 dcmpg (3, 1)
	76 ifle (3, 1)
	77 27 (3, 1)
	79 dload_2 (3, 1)
	80 aload_0 (3, 1)
	81 iload (3, 1)
	82 #6 (3, 1)
	83 i2d (3, 1)
	84 ldc2_w (3, 1)
	85 0.5 (3, 1)
	87 dadd (3, 1)
	88 invokespecial (3, 1)
	89 org/apache/commons/math3/distribution/ZipfDistribution$ZipfRejectionInversionSampler.hIntegral:(D)D (3, 1)
	91 aload_0 (3, 1)
	92 iload (3, 1)
	93 #6 (3, 1)
	94 i2d (3, 1)
	95 invokespecial (3, 1)
	96 org/apache/commons/math3/distribution/ZipfDistribution$ZipfRejectionInversionSampler.h:(D)D (3, 1)
	98 dsub (3, 1)
	99 dcmpl (3, 1)
	100 iflt (3, 1)
	101 6 (3, 1)
	103 iload (6, 4)
	104 #6 (6, 4)
	105 ireturn (6, 4)
	106 goto (0, 4)
	107 -106 (2, 4)

Method: hIntegral
	0 dload_1 (0, 0)
	1 invokestatic (0, 0)
	2 org/apache/commons/math3/util/FastMath.log:(D)D (0, 0)
	4 dstore_3 (0, 0)
	5 dconst_1 (0, 0)
	6 aload_0 (0, 0)
	7 getfield (0, 0)
	8 org/apache/commons/math3/distribution/ZipfDistribution$ZipfRejectionInversionSampler.exponent:D (0, 0)
	10 dsub (0, 0)
	11 dload_3 (0, 0)
	12 dmul (0, 0)
	13 invokestatic (0, 0)
	14 org/apache/commons/math3/distribution/ZipfDistribution$ZipfRejectionInversionSampler.helper2:(D)D (0, 0)
	16 dload_3 (0, 0)
	17 dmul (0, 0)
	18 dreturn (0, 0)

Method: h
	0 aload_0 (0, 0)
	1 getfield (0, 0)
	2 org/apache/commons/math3/distribution/ZipfDistribution$ZipfRejectionInversionSampler.exponent:D (0, 0)
	4 dneg (0, 0)
	5 dload_1 (0, 0)
	6 invokestatic (0, 0)
	7 org/apache/commons/math3/util/FastMath.log:(D)D (0, 0)
	9 dmul (0, 0)
	10 invokestatic (0, 0)
	11 org/apache/commons/math3/util/FastMath.exp:(D)D (0, 0)
	13 dreturn (0, 0)

Method: hIntegralInverse
	0 dload_1 (0, 0)
	1 dconst_1 (0, 0)
	2 aload_0 (0, 0)
	3 getfield (0, 0)
	4 org/apache/commons/math3/distribution/ZipfDistribution$ZipfRejectionInversionSampler.exponent:D (0, 0)
	6 dsub (0, 0)
	7 dmul (0, 0)
	8 dstore_3 (0, 0)
	9 dload_3 (1, 1)
	10 ldc2_w (1, 1)
	11 -1.0 (1, 1)
	13 dcmpg (1, 1)
	14 ifge (1, 1)
	15 7 (1, 1)
	17 ldc2_w (1, 1)
	18 -1.0 (1, 1)
	20 dstore_3 (1, 1)
	21 dload_3 (0, 0)
	22 invokestatic (0, 0)
	23 org/apache/commons/math3/distribution/ZipfDistribution$ZipfRejectionInversionSampler.helper1:(D)D (0, 0)
	25 dload_1 (0, 0)
	26 dmul (0, 0)
	27 invokestatic (0, 0)
	28 org/apache/commons/math3/util/FastMath.exp:(D)D (0, 0)
	30 dreturn (0, 0)

Method: helper1
	0 dload_0 (1, 1)
	1 invokestatic (1, 1)
	2 org/apache/commons/math3/util/FastMath.abs:(D)D (1, 1)
	4 ldc2_w (1, 1)
	5 1e-08 (1, 1)
	7 dcmpl (1, 1)
	8 ifle (1, 1)
	9 10 (1, 1)
	11 dload_0 (1, 1)
	12 invokestatic (1, 1)
	13 org/apache/commons/math3/util/FastMath.log1p:(D)D (1, 1)
	15 dload_0 (1, 1)
	16 ddiv (1, 1)
	17 dreturn (1, 1)
	18 dconst_1 (1, 2)
	19 dload_0 (1, 2)
	20 ldc2_w (1, 2)
	21 0.5 (1, 2)
	23 dload_0 (1, 2)
	24 ldc2_w (1, 2)
	25 0.3333333333333333 (1, 2)
	27 dload_0 (1, 2)
	28 ldc2_w (1, 2)
	29 0.25 (1, 2)
	31 dmul (1, 2)
	32 dsub (1, 2)
	33 dmul (1, 2)
	34 dsub (1, 2)
	35 dmul (1, 2)
	36 dsub (1, 2)
	37 dreturn (1, 2)

Method: helper2
	0 dload_0 (1, 1)
	1 invokestatic (1, 1)
	2 org/apache/commons/math3/util/FastMath.abs:(D)D (1, 1)
	4 ldc2_w (1, 1)
	5 1e-08 (1, 1)
	7 dcmpl (1, 1)
	8 ifle (1, 1)
	9 10 (1, 1)
	11 dload_0 (1, 1)
	12 invokestatic (1, 1)
	13 org/apache/commons/math3/util/FastMath.expm1:(D)D (1, 1)
	15 dload_0 (1, 1)
	16 ddiv (1, 1)
	17 dreturn (1, 1)
	18 dconst_1 (1, 2)
	19 dload_0 (1, 2)
	20 ldc2_w (1, 2)
	21 0.5 (1, 2)
	23 dmul (1, 2)
	24 dconst_1 (1, 2)
	25 dload_0 (1, 2)
	26 ldc2_w (1, 2)
	27 0.3333333333333333 (1, 2)
	29 dmul (1, 2)
	30 dconst_1 (1, 2)
	31 dload_0 (1, 2)
	32 ldc2_w (1, 2)
	33 0.25 (1, 2)
	35 dmul (1, 2)
	36 dadd (1, 2)
	37 dmul (1, 2)
	38 dadd (1, 2)
	39 dmul (1, 2)
	40 dadd (1, 2)
	41 dreturn (1, 2)

