Method: <init>
	0 aload_0 (0, 0)
	1 aload_1 (0, 0)
	2 invokespecial (0, 0)
	3 org/apache/commons/math3/distribution/AbstractIntegerDistribution.<init>:(Lorg/apache/commons/math3/random/RandomGenerator;)V (0, 0)
	5 aload_0 (0, 0)
	6 ldc2_w (0, 0)
	7 nan (0, 0)
	9 putfield (0, 0)
	10 org/apache/commons/math3/distribution/ZipfDistribution.numericalMean:D (0, 0)
	12 aload_0 (0, 0)
	13 iconst_0 (0, 0)
	14 putfield (0, 0)
	15 org/apache/commons/math3/distribution/ZipfDistribution.numericalMeanIsCalculated:Z (0, 0)
	17 aload_0 (0, 0)
	18 ldc2_w (0, 0)
	19 nan (0, 0)
	21 putfield (0, 0)
	22 org/apache/commons/math3/distribution/ZipfDistribution.numericalVariance:D (0, 0)
	24 aload_0 (0, 0)
	25 iconst_0 (0, 0)
	26 putfield (0, 0)
	27 org/apache/commons/math3/distribution/ZipfDistribution.numericalVarianceIsCalculated:Z (0, 0)
	29 iload_2 (6, 1)
	30 ifgt (6, 1)
	31 18 (6, 1)
	33 new (6, 1)
	34 org/apache/commons/math3/exception/NotStrictlyPositiveException (6, 1)
	36 dup (6, 1)
	37 getstatic (6, 1)
	38 org/apache/commons/math3/exception/util/LocalizedFormats.DIMENSION:Lorg/apache/commons/math3/exception/util/LocalizedFormats; (6, 1)
	40 iload_2 (6, 1)
	41 invokestatic (6, 1)
	42 java/lang/Integer.valueOf:(I)Ljava/lang/Integer; (6, 1)
	44 invokespecial (6, 1)
	45 org/apache/commons/math3/exception/NotStrictlyPositiveException.<init>:(Lorg/apache/commons/math3/exception/util/Localizable;Ljava/lang/Number;)V (6, 1)
	47 athrow (6, 1)
	48 dload_3 (6, 1)
	49 dconst_0 (6, 1)
	50 dcmpg (6, 1)
	51 ifgt (6, 1)
	52 18 (6, 1)
	54 new (6, 1)
	55 org/apache/commons/math3/exception/NotStrictlyPositiveException (6, 1)
	57 dup (6, 1)
	58 getstatic (6, 1)
	59 org/apache/commons/math3/exception/util/LocalizedFormats.EXPONENT:Lorg/apache/commons/math3/exception/util/LocalizedFormats; (6, 1)
	61 dload_3 (6, 1)
	62 invokestatic (6, 1)
	63 java/lang/Double.valueOf:(D)Ljava/lang/Double; (6, 1)
	65 invokespecial (6, 1)
	66 org/apache/commons/math3/exception/NotStrictlyPositiveException.<init>:(Lorg/apache/commons/math3/exception/util/Localizable;Ljava/lang/Number;)V (6, 1)
	68 athrow (6, 1)
	69 aload_0 (5, 1)
	70 iload_2 (5, 1)
	71 putfield (5, 1)
	72 org/apache/commons/math3/distribution/ZipfDistribution.numberOfElements:I (5, 1)
	74 aload_0 (5, 1)
	75 dload_3 (5, 1)
	76 putfield (5, 1)
	77 org/apache/commons/math3/distribution/ZipfDistribution.exponent:D (5, 1)
	79 return (0, 1)

Method: getNumberOfElements
	0 aload_0 (0, 0)
	1 getfield (0, 0)
	2 org/apache/commons/math3/distribution/ZipfDistribution.numberOfElements:I (0, 0)
	4 ireturn (0, 0)

Method: getExponent
	0 aload_0 (0, 0)
	1 getfield (0, 0)
	2 org/apache/commons/math3/distribution/ZipfDistribution.exponent:D (0, 0)
	4 dreturn (0, 0)

Method: probability
	0 iload_1 (1, 1)
	1 ifle (1, 1)
	2 11 (1, 1)
	4 iload_1 (1, 1)
	5 aload_0 (1, 1)
	6 getfield (1, 1)
	7 org/apache/commons/math3/distribution/ZipfDistribution.numberOfElements:I (1, 1)
	9 if_icmple (1, 1)
	10 5 (1, 1)
	12 dconst_0 (1, 1)
	13 dreturn (1, 1)
	14 dconst_1 (0, 0)
	15 iload_1 (0, 0)
	16 i2d (0, 0)
	17 aload_0 (0, 0)
	18 getfield (0, 0)
	19 org/apache/commons/math3/distribution/ZipfDistribution.exponent:D (0, 0)
	21 invokestatic (0, 0)
	22 org/apache/commons/math3/util/FastMath.pow:(DD)D (0, 0)
	24 ddiv (0, 0)
	25 aload_0 (0, 0)
	26 aload_0 (0, 0)
	27 getfield (0, 0)
	28 org/apache/commons/math3/distribution/ZipfDistribution.numberOfElements:I (0, 0)
	30 aload_0 (0, 0)
	31 getfield (0, 0)
	32 org/apache/commons/math3/distribution/ZipfDistribution.exponent:D (0, 0)
	34 invokespecial (0, 0)
	35 org/apache/commons/math3/distribution/ZipfDistribution.generalizedHarmonic:(ID)D (0, 0)
	37 ddiv (0, 0)
	38 dreturn (0, 0)

Method: logProbability
	0 iload_1 (1, 1)
	1 ifle (1, 1)
	2 11 (1, 1)
	4 iload_1 (1, 1)
	5 aload_0 (1, 1)
	6 getfield (1, 1)
	7 org/apache/commons/math3/distribution/ZipfDistribution.numberOfElements:I (1, 1)
	9 if_icmple (1, 1)
	10 7 (1, 1)
	12 ldc2_w (1, 1)
	13 -inf (1, 1)
	15 dreturn (1, 1)
	16 iload_1 (0, 0)
	17 i2d (0, 0)
	18 invokestatic (0, 0)
	19 org/apache/commons/math3/util/FastMath.log:(D)D (0, 0)
	21 dneg (0, 0)
	22 aload_0 (0, 0)
	23 getfield (0, 0)
	24 org/apache/commons/math3/distribution/ZipfDistribution.exponent:D (0, 0)
	26 dmul (0, 0)
	27 aload_0 (0, 0)
	28 aload_0 (0, 0)
	29 getfield (0, 0)
	30 org/apache/commons/math3/distribution/ZipfDistribution.numberOfElements:I (0, 0)
	32 aload_0 (0, 0)
	33 getfield (0, 0)
	34 org/apache/commons/math3/distribution/ZipfDistribution.exponent:D (0, 0)
	36 invokespecial (0, 0)
	37 org/apache/commons/math3/distribution/ZipfDistribution.generalizedHarmonic:(ID)D (0, 0)
	39 invokestatic (0, 0)
	40 org/apache/commons/math3/util/FastMath.log:(D)D (0, 0)
	42 dsub (0, 0)
	43 dreturn (0, 0)

Method: cumulativeProbability
	0 iload_1 (1, 1)
	1 ifgt (1, 1)
	2 5 (1, 1)
	4 dconst_0 (1, 1)
	5 dreturn (1, 1)
	6 iload_1 (2, 1)
	7 aload_0 (2, 1)
	8 getfield (2, 1)
	9 org/apache/commons/math3/distribution/ZipfDistribution.numberOfElements:I (2, 1)
	11 if_icmplt (2, 1)
	12 5 (2, 1)
	14 dconst_1 (2, 1)
	15 dreturn (2, 1)
	16 aload_0 (0, 0)
	17 iload_1 (0, 0)
	18 aload_0 (0, 0)
	19 getfield (0, 0)
	20 org/apache/commons/math3/distribution/ZipfDistribution.exponent:D (0, 0)
	22 invokespecial (0, 0)
	23 org/apache/commons/math3/distribution/ZipfDistribution.generalizedHarmonic:(ID)D (0, 0)
	25 aload_0 (0, 0)
	26 aload_0 (0, 0)
	27 getfield (0, 0)
	28 org/apache/commons/math3/distribution/ZipfDistribution.numberOfElements:I (0, 0)
	30 aload_0 (0, 0)
	31 getfield (0, 0)
	32 org/apache/commons/math3/distribution/ZipfDistribution.exponent:D (0, 0)
	34 invokespecial (0, 0)
	35 org/apache/commons/math3/distribution/ZipfDistribution.generalizedHarmonic:(ID)D (0, 0)
	37 ddiv (0, 0)
	38 dreturn (0, 0)

Method: getNumericalMean
	0 aload_0 (1, 1)
	1 getfield (1, 1)
	2 org/apache/commons/math3/distribution/ZipfDistribution.numericalMeanIsCalculated:Z (1, 1)
	4 ifne (1, 1)
	5 16 (1, 1)
	7 aload_0 (1, 1)
	8 aload_0 (1, 1)
	9 invokevirtual (1, 1)
	10 org/apache/commons/math3/distribution/ZipfDistribution.calculateNumericalMean:()D (1, 1)
	12 putfield (1, 1)
	13 org/apache/commons/math3/distribution/ZipfDistribution.numericalMean:D (1, 1)
	15 aload_0 (1, 1)
	16 iconst_1 (1, 1)
	17 putfield (1, 1)
	18 org/apache/commons/math3/distribution/ZipfDistribution.numericalMeanIsCalculated:Z (1, 1)
	20 aload_0 (0, 0)
	21 getfield (0, 0)
	22 org/apache/commons/math3/distribution/ZipfDistribution.numericalMean:D (0, 0)
	24 dreturn (0, 0)

Method: calculateNumericalMean
	0 aload_0 (0, 0)
	1 invokevirtual (0, 0)
	2 org/apache/commons/math3/distribution/ZipfDistribution.getNumberOfElements:()I (0, 0)
	4 istore_1 (0, 0)
	5 aload_0 (0, 0)
	6 invokevirtual (0, 0)
	7 org/apache/commons/math3/distribution/ZipfDistribution.getExponent:()D (0, 0)
	9 dstore_2 (0, 0)
	10 aload_0 (0, 0)
	11 iload_1 (0, 0)
	12 dload_2 (0, 0)
	13 dconst_1 (0, 0)
	14 dsub (0, 0)
	15 invokespecial (0, 0)
	16 org/apache/commons/math3/distribution/ZipfDistribution.generalizedHarmonic:(ID)D (0, 0)
	18 dstore (0, 0)
	19 #4 (0, 0)
	20 aload_0 (0, 0)
	21 iload_1 (0, 0)
	22 dload_2 (0, 0)
	23 invokespecial (0, 0)
	24 org/apache/commons/math3/distribution/ZipfDistribution.generalizedHarmonic:(ID)D (0, 0)
	26 dstore (0, 0)
	27 #6 (0, 0)
	28 dload (0, 0)
	29 #4 (0, 0)
	30 dload (0, 0)
	31 #6 (0, 0)
	32 ddiv (0, 0)
	33 dreturn (0, 0)

Method: getNumericalVariance
	0 aload_0 (1, 1)
	1 getfield (1, 1)
	2 org/apache/commons/math3/distribution/ZipfDistribution.numericalVarianceIsCalculated:Z (1, 1)
	4 ifne (1, 1)
	5 16 (1, 1)
	7 aload_0 (1, 1)
	8 aload_0 (1, 1)
	9 invokevirtual (1, 1)
	10 org/apache/commons/math3/distribution/ZipfDistribution.calculateNumericalVariance:()D (1, 1)
	12 putfield (1, 1)
	13 org/apache/commons/math3/distribution/ZipfDistribution.numericalVariance:D (1, 1)
	15 aload_0 (1, 1)
	16 iconst_1 (1, 1)
	17 putfield (1, 1)
	18 org/apache/commons/math3/distribution/ZipfDistribution.numericalVarianceIsCalculated:Z (1, 1)
	20 aload_0 (0, 0)
	21 getfield (0, 0)
	22 org/apache/commons/math3/distribution/ZipfDistribution.numericalVariance:D (0, 0)
	24 dreturn (0, 0)

Method: calculateNumericalVariance
	0 aload_0 (0, 0)
	1 invokevirtual (0, 0)
	2 org/apache/commons/math3/distribution/ZipfDistribution.getNumberOfElements:()I (0, 0)
	4 istore_1 (0, 0)
	5 aload_0 (0, 0)
	6 invokevirtual (0, 0)
	7 org/apache/commons/math3/distribution/ZipfDistribution.getExponent:()D (0, 0)
	9 dstore_2 (0, 0)
	10 aload_0 (0, 0)
	11 iload_1 (0, 0)
	12 dload_2 (0, 0)
	13 ldc2_w (0, 0)
	14 2.0 (0, 0)
	16 dsub (0, 0)
	17 invokespecial (0, 0)
	18 org/apache/commons/math3/distribution/ZipfDistribution.generalizedHarmonic:(ID)D (0, 0)
	20 dstore (0, 0)
	21 #4 (0, 0)
	22 aload_0 (0, 0)
	23 iload_1 (0, 0)
	24 dload_2 (0, 0)
	25 dconst_1 (0, 0)
	26 dsub (0, 0)
	27 invokespecial (0, 0)
	28 org/apache/commons/math3/distribution/ZipfDistribution.generalizedHarmonic:(ID)D (0, 0)
	30 dstore (0, 0)
	31 #6 (0, 0)
	32 aload_0 (0, 0)
	33 iload_1 (0, 0)
	34 dload_2 (0, 0)
	35 invokespecial (0, 0)
	36 org/apache/commons/math3/distribution/ZipfDistribution.generalizedHarmonic:(ID)D (0, 0)
	38 dstore (0, 0)
	39 #8 (0, 0)
	40 dload (0, 0)
	41 #4 (0, 0)
	42 dload (0, 0)
	43 #8 (0, 0)
	44 ddiv (0, 0)
	45 dload (0, 0)
	46 #6 (0, 0)
	47 dload (0, 0)
	48 #6 (0, 0)
	49 dmul (0, 0)
	50 dload (0, 0)
	51 #8 (0, 0)
	52 dload (0, 0)
	53 #8 (0, 0)
	54 dmul (0, 0)
	55 ddiv (0, 0)
	56 dsub (0, 0)
	57 dreturn (0, 0)

Method: generalizedHarmonic
	0 dconst_0 (0, 0)
	1 dstore (0, 0)
	2 #4 (0, 0)
	3 iload_1 (1, 4)
	4 istore (1, 4)
	5 #6 (1, 4)
	6 iload (1, 4)
	7 #6 (1, 4)
	8 ifle (1, 4)
	9 23 (1, 4)
	11 dload (1, 4)
	12 #4 (1, 4)
	13 dconst_1 (1, 4)
	14 iload (1, 4)
	15 #6 (1, 4)
	16 i2d (1, 4)
	17 dload_2 (1, 4)
	18 invokestatic (1, 4)
	19 org/apache/commons/math3/util/FastMath.pow:(DD)D (1, 4)
	21 ddiv (1, 4)
	22 dadd (1, 4)
	23 dstore (1, 4)
	24 #4 (1, 4)
	25 iinc (1, 4)
	26 #6 (1, 4)
	27 -89 (1, 4)
	28 goto (1, 4)
	29 -22 (1, 4)
	31 dload (0, 0)
	32 #4 (0, 0)
	33 dreturn (0, 0)

Method: getSupportLowerBound
	0 iconst_1 (0, 0)
	1 ireturn (0, 0)

Method: getSupportUpperBound
	0 aload_0 (0, 0)
	1 invokevirtual (0, 0)
	2 org/apache/commons/math3/distribution/ZipfDistribution.getNumberOfElements:()I (0, 0)
	4 ireturn (0, 0)

Method: isSupportConnected
	0 iconst_1 (0, 0)
	1 ireturn (0, 0)

Method: sample
	0 aload_0 (1, 1)
	1 getfield (1, 1)
	2 org/apache/commons/math3/distribution/ZipfDistribution.sampler:Lorg/apache/commons/math3/distribution/ZipfDistribution$ZipfRejectionInversionSampler; (1, 1)
	4 ifnonnull (1, 1)
	5 22 (1, 1)
	7 aload_0 (1, 1)
	8 new (1, 1)
	9 org/apache/commons/math3/distribution/ZipfDistribution$ZipfRejectionInversionSampler (1, 1)
	11 dup (1, 1)
	12 aload_0 (1, 1)
	13 getfield (1, 1)
	14 org/apache/commons/math3/distribution/ZipfDistribution.numberOfElements:I (1, 1)
	16 aload_0 (1, 1)
	17 getfield (1, 1)
	18 org/apache/commons/math3/distribution/ZipfDistribution.exponent:D (1, 1)
	20 invokespecial (1, 1)
	21 org/apache/commons/math3/distribution/ZipfDistribution$ZipfRejectionInversionSampler.<init>:(ID)V (1, 1)
	23 putfield (1, 1)
	24 org/apache/commons/math3/distribution/ZipfDistribution.sampler:Lorg/apache/commons/math3/distribution/ZipfDistribution$ZipfRejectionInversionSampler; (1, 1)
	26 aload_0 (0, 0)
	27 getfield (0, 0)
	28 org/apache/commons/math3/distribution/ZipfDistribution.sampler:Lorg/apache/commons/math3/distribution/ZipfDistribution$ZipfRejectionInversionSampler; (0, 0)
	30 aload_0 (0, 0)
	31 getfield (0, 0)
	32 org/apache/commons/math3/distribution/ZipfDistribution.random:Lorg/apache/commons/math3/random/RandomGenerator; (0, 0)
	34 invokevirtual (0, 0)
	35 org/apache/commons/math3/distribution/ZipfDistribution$ZipfRejectionInversionSampler.sample:(Lorg/apache/commons/math3/random/RandomGenerator;)I (0, 0)
	37 ireturn (0, 0)

