Method: values
	0 getstatic (0, 0)
	1 org/apache/commons/math3/stat/clustering/KMeansPlusPlusClusterer$EmptyClusterStrategy.$VALUES:[Lorg/apache/commons/math3/stat/clustering/KMeansPlusPlusClusterer$EmptyClusterStrategy; (0, 0)
	3 invokevirtual (0, 0)
	4 [Lorg/apache/commons/math3/stat/clustering/KMeansPlusPlusClusterer$EmptyClusterStrategy;.clone:()Ljava/lang/Object; (0, 0)
	6 checkcast (0, 0)
	7 [Lorg/apache/commons/math3/stat/clustering/KMeansPlusPlusClusterer$EmptyClusterStrategy; (0, 0)
	9 areturn (0, 0)

Method: valueOf
	0 ldc (0, 0)
	1 org/apache/commons/math3/stat/clustering/KMeansPlusPlusClusterer$EmptyClusterStrategy (0, 0)
	2 aload_0 (0, 0)
	3 invokestatic (0, 0)
	4 java/lang/Enum.valueOf:(Ljava/lang/Class;Ljava/lang/String;)Ljava/lang/Enum; (0, 0)
	6 checkcast (0, 0)
	7 org/apache/commons/math3/stat/clustering/KMeansPlusPlusClusterer$EmptyClusterStrategy (0, 0)
	9 areturn (0, 0)

Method: <clinit>
	0 new (0, 0)
	1 org/apache/commons/math3/stat/clustering/KMeansPlusPlusClusterer$EmptyClusterStrategy (0, 0)
	3 dup (0, 0)
	4 ldc (0, 0)
	5 LARGEST_VARIANCE (0, 0)
	6 iconst_0 (0, 0)
	7 invokespecial (0, 0)
	8 org/apache/commons/math3/stat/clustering/KMeansPlusPlusClusterer$EmptyClusterStrategy.<init>:(Ljava/lang/String;I)V (0, 0)
	10 putstatic (0, 0)
	11 org/apache/commons/math3/stat/clustering/KMeansPlusPlusClusterer$EmptyClusterStrategy.LARGEST_VARIANCE:Lorg/apache/commons/math3/stat/clustering/KMeansPlusPlusClusterer$EmptyClusterStrategy; (0, 0)
	13 new (0, 0)
	14 org/apache/commons/math3/stat/clustering/KMeansPlusPlusClusterer$EmptyClusterStrategy (0, 0)
	16 dup (0, 0)
	17 ldc (0, 0)
	18 LARGEST_POINTS_NUMBER (0, 0)
	19 iconst_1 (0, 0)
	20 invokespecial (0, 0)
	21 org/apache/commons/math3/stat/clustering/KMeansPlusPlusClusterer$EmptyClusterStrategy.<init>:(Ljava/lang/String;I)V (0, 0)
	23 putstatic (0, 0)
	24 org/apache/commons/math3/stat/clustering/KMeansPlusPlusClusterer$EmptyClusterStrategy.LARGEST_POINTS_NUMBER:Lorg/apache/commons/math3/stat/clustering/KMeansPlusPlusClusterer$EmptyClusterStrategy; (0, 0)
	26 new (0, 0)
	27 org/apache/commons/math3/stat/clustering/KMeansPlusPlusClusterer$EmptyClusterStrategy (0, 0)
	29 dup (0, 0)
	30 ldc (0, 0)
	31 FARTHEST_POINT (0, 0)
	32 iconst_2 (0, 0)
	33 invokespecial (0, 0)
	34 org/apache/commons/math3/stat/clustering/KMeansPlusPlusClusterer$EmptyClusterStrategy.<init>:(Ljava/lang/String;I)V (0, 0)
	36 putstatic (0, 0)
	37 org/apache/commons/math3/stat/clustering/KMeansPlusPlusClusterer$EmptyClusterStrategy.FARTHEST_POINT:Lorg/apache/commons/math3/stat/clustering/KMeansPlusPlusClusterer$EmptyClusterStrategy; (0, 0)
	39 new (0, 0)
	40 org/apache/commons/math3/stat/clustering/KMeansPlusPlusClusterer$EmptyClusterStrategy (0, 0)
	42 dup (0, 0)
	43 ldc (0, 0)
	44 ERROR (0, 0)
	45 iconst_3 (0, 0)
	46 invokespecial (0, 0)
	47 org/apache/commons/math3/stat/clustering/KMeansPlusPlusClusterer$EmptyClusterStrategy.<init>:(Ljava/lang/String;I)V (0, 0)
	49 putstatic (0, 0)
	50 org/apache/commons/math3/stat/clustering/KMeansPlusPlusClusterer$EmptyClusterStrategy.ERROR:Lorg/apache/commons/math3/stat/clustering/KMeansPlusPlusClusterer$EmptyClusterStrategy; (0, 0)
	52 iconst_4 (0, 0)
	53 anewarray (0, 0)
	54 org/apache/commons/math3/stat/clustering/KMeansPlusPlusClusterer$EmptyClusterStrategy (0, 0)
	56 dup (0, 0)
	57 iconst_0 (0, 0)
	58 getstatic (0, 0)
	59 org/apache/commons/math3/stat/clustering/KMeansPlusPlusClusterer$EmptyClusterStrategy.LARGEST_VARIANCE:Lorg/apache/commons/math3/stat/clustering/KMeansPlusPlusClusterer$EmptyClusterStrategy; (0, 0)
	61 aastore (0, 0)
	62 dup (0, 0)
	63 iconst_1 (0, 0)
	64 getstatic (0, 0)
	65 org/apache/commons/math3/stat/clustering/KMeansPlusPlusClusterer$EmptyClusterStrategy.LARGEST_POINTS_NUMBER:Lorg/apache/commons/math3/stat/clustering/KMeansPlusPlusClusterer$EmptyClusterStrategy; (0, 0)
	67 aastore (0, 0)
	68 dup (0, 0)
	69 iconst_2 (0, 0)
	70 getstatic (0, 0)
	71 org/apache/commons/math3/stat/clustering/KMeansPlusPlusClusterer$EmptyClusterStrategy.FARTHEST_POINT:Lorg/apache/commons/math3/stat/clustering/KMeansPlusPlusClusterer$EmptyClusterStrategy; (0, 0)
	73 aastore (0, 0)
	74 dup (0, 0)
	75 iconst_3 (0, 0)
	76 getstatic (0, 0)
	77 org/apache/commons/math3/stat/clustering/KMeansPlusPlusClusterer$EmptyClusterStrategy.ERROR:Lorg/apache/commons/math3/stat/clustering/KMeansPlusPlusClusterer$EmptyClusterStrategy; (0, 0)
	79 aastore (0, 0)
	80 putstatic (0, 0)
	81 org/apache/commons/math3/stat/clustering/KMeansPlusPlusClusterer$EmptyClusterStrategy.$VALUES:[Lorg/apache/commons/math3/stat/clustering/KMeansPlusPlusClusterer$EmptyClusterStrategy; (0, 0)
	83 return (0, 0)

