Method: <clinit>
	0 invokestatic (1, 5)
	1 org/apache/commons/math3/stat/clustering/KMeansPlusPlusClusterer$EmptyClusterStrategy.values:()[Lorg/apache/commons/math3/stat/clustering/KMeansPlusPlusClusterer$EmptyClusterStrategy; (1, 5)
	3 arraylength (1, 5)
	4 newarray (1, 5)
	5 10 (1, 5)
	6 putstatic (1, 5)
	7 org/apache/commons/math3/stat/clustering/KMeansPlusPlusClusterer$1.$SwitchMap$org$apache$commons$math3$stat$clustering$KMeansPlusPlusClusterer$EmptyClusterStrategy:[I (1, 5)
	9 getstatic (1, 5)
	10 org/apache/commons/math3/stat/clustering/KMeansPlusPlusClusterer$1.$SwitchMap$org$apache$commons$math3$stat$clustering$KMeansPlusPlusClusterer$EmptyClusterStrategy:[I (1, 5)
	12 getstatic (1, 5)
	13 org/apache/commons/math3/stat/clustering/KMeansPlusPlusClusterer$EmptyClusterStrategy.LARGEST_VARIANCE:Lorg/apache/commons/math3/stat/clustering/KMeansPlusPlusClusterer$EmptyClusterStrategy; (1, 5)
	15 invokevirtual (1, 5)
	16 org/apache/commons/math3/stat/clustering/KMeansPlusPlusClusterer$EmptyClusterStrategy.ordinal:()I (1, 5)
	18 iconst_1 (1, 5)
	19 iastore (1, 5)
	20 goto (1, 5)
	21 4 (1, 5)
	23 astore_0 (1, 5)
	24 getstatic (1, 5)
	25 org/apache/commons/math3/stat/clustering/KMeansPlusPlusClusterer$1.$SwitchMap$org$apache$commons$math3$stat$clustering$KMeansPlusPlusClusterer$EmptyClusterStrategy:[I (1, 5)
	27 getstatic (1, 5)
	28 org/apache/commons/math3/stat/clustering/KMeansPlusPlusClusterer$EmptyClusterStrategy.LARGEST_POINTS_NUMBER:Lorg/apache/commons/math3/stat/clustering/KMeansPlusPlusClusterer$EmptyClusterStrategy; (1, 5)
	30 invokevirtual (1, 5)
	31 org/apache/commons/math3/stat/clustering/KMeansPlusPlusClusterer$EmptyClusterStrategy.ordinal:()I (1, 5)
	33 iconst_2 (1, 5)
	34 iastore (1, 5)
	35 goto (1, 5)
	36 4 (1, 5)
	38 astore_0 (1, 5)
	39 getstatic (1, 5)
	40 org/apache/commons/math3/stat/clustering/KMeansPlusPlusClusterer$1.$SwitchMap$org$apache$commons$math3$stat$clustering$KMeansPlusPlusClusterer$EmptyClusterStrategy:[I (1, 5)
	42 getstatic (1, 5)
	43 org/apache/commons/math3/stat/clustering/KMeansPlusPlusClusterer$EmptyClusterStrategy.FARTHEST_POINT:Lorg/apache/commons/math3/stat/clustering/KMeansPlusPlusClusterer$EmptyClusterStrategy; (1, 5)
	45 invokevirtual (1, 5)
	46 org/apache/commons/math3/stat/clustering/KMeansPlusPlusClusterer$EmptyClusterStrategy.ordinal:()I (1, 5)
	48 iconst_3 (1, 5)
	49 iastore (1, 5)
	50 goto (1, 5)
	51 4 (1, 5)
	53 astore_0 (1, 5)
	54 return (1, 5)

