Method: <init>
	0 aload_0 (0, 0)
	1 invokespecial (0, 0)
	2 java/text/NumberFormat.<init>:()V (0, 0)
	4 aload_0 (0, 0)
	5 aload_1 (0, 0)
	6 putfield (0, 0)
	7 org/apache/commons/math3/fraction/AbstractFormat.numeratorFormat:Ljava/text/NumberFormat; (0, 0)
	9 aload_0 (0, 0)
	10 aload_2 (0, 0)
	11 putfield (0, 0)
	12 org/apache/commons/math3/fraction/AbstractFormat.denominatorFormat:Ljava/text/NumberFormat; (0, 0)
	14 return (0, 0)

Method: getDefaultNumberFormat
	0 aload_0 (0, 0)
	1 invokestatic (0, 0)
	2 java/text/NumberFormat.getNumberInstance:(Ljava/util/Locale;)Ljava/text/NumberFormat; (0, 0)
	4 astore_1 (0, 0)
	5 aload_1 (0, 0)
	6 iconst_0 (0, 0)
	7 invokevirtual (0, 0)
	8 java/text/NumberFormat.setMaximumFractionDigits:(I)V (0, 0)
	10 aload_1 (0, 0)
	11 iconst_1 (0, 0)
	12 invokevirtual (0, 0)
	13 java/text/NumberFormat.setParseIntegerOnly:(Z)V (0, 0)
	15 aload_1 (0, 0)
	16 areturn (0, 0)

Method: getDenominatorFormat
	0 aload_0 (0, 0)
	1 getfield (0, 0)
	2 org/apache/commons/math3/fraction/AbstractFormat.denominatorFormat:Ljava/text/NumberFormat; (0, 0)
	4 areturn (0, 0)

Method: getNumeratorFormat
	0 aload_0 (0, 0)
	1 getfield (0, 0)
	2 org/apache/commons/math3/fraction/AbstractFormat.numeratorFormat:Ljava/text/NumberFormat; (0, 0)
	4 areturn (0, 0)

Method: setDenominatorFormat
	0 aload_1 (1, 1)
	1 ifnonnull (1, 1)
	2 18 (1, 1)
	4 new (1, 1)
	5 org/apache/commons/math3/exception/NullArgumentException (1, 1)
	7 dup (1, 1)
	8 getstatic (1, 1)
	9 org/apache/commons/math3/exception/util/LocalizedFormats.DENOMINATOR_FORMAT:Lorg/apache/commons/math3/exception/util/LocalizedFormats; (1, 1)
	11 iconst_0 (1, 1)
	12 anewarray (1, 1)
	13 java/lang/Object (1, 1)
	15 invokespecial (1, 1)
	16 org/apache/commons/math3/exception/NullArgumentException.<init>:(Lorg/apache/commons/math3/exception/util/Localizable;[Ljava/lang/Object;)V (1, 1)
	18 athrow (1, 1)
	19 aload_0 (0, 4)
	20 aload_1 (0, 4)
	21 putfield (0, 4)
	22 org/apache/commons/math3/fraction/AbstractFormat.denominatorFormat:Ljava/text/NumberFormat; (0, 4)
	24 return (0, 4)

Method: setNumeratorFormat
	0 aload_1 (1, 1)
	1 ifnonnull (1, 1)
	2 18 (1, 1)
	4 new (1, 1)
	5 org/apache/commons/math3/exception/NullArgumentException (1, 1)
	7 dup (1, 1)
	8 getstatic (1, 1)
	9 org/apache/commons/math3/exception/util/LocalizedFormats.NUMERATOR_FORMAT:Lorg/apache/commons/math3/exception/util/LocalizedFormats; (1, 1)
	11 iconst_0 (1, 1)
	12 anewarray (1, 1)
	13 java/lang/Object (1, 1)
	15 invokespecial (1, 1)
	16 org/apache/commons/math3/exception/NullArgumentException.<init>:(Lorg/apache/commons/math3/exception/util/Localizable;[Ljava/lang/Object;)V (1, 1)
	18 athrow (1, 1)
	19 aload_0 (0, 4)
	20 aload_1 (0, 4)
	21 putfield (0, 4)
	22 org/apache/commons/math3/fraction/AbstractFormat.numeratorFormat:Ljava/text/NumberFormat; (0, 4)
	24 return (0, 4)

Method: parseAndIgnoreWhitespace
	0 aload_0 (0, 0)
	1 aload_1 (0, 0)
	2 invokestatic (0, 0)
	3 org/apache/commons/math3/fraction/AbstractFormat.parseNextCharacter:(Ljava/lang/String;Ljava/text/ParsePosition;)C (0, 0)
	5 pop (0, 0)
	6 aload_1 (0, 0)
	7 aload_1 (0, 0)
	8 invokevirtual (0, 0)
	9 java/text/ParsePosition.getIndex:()I (0, 0)
	11 iconst_1 (0, 0)
	12 isub (0, 0)
	13 invokevirtual (0, 0)
	14 java/text/ParsePosition.setIndex:(I)V (0, 0)
	16 return (0, 0)

Method: parseNextCharacter
	0 aload_1 (0, 0)
	1 invokevirtual (0, 0)
	2 java/text/ParsePosition.getIndex:()I (0, 0)
	4 istore_2 (0, 0)
	5 aload_0 (0, 0)
	6 invokevirtual (0, 0)
	7 java/lang/String.length:()I (0, 0)
	9 istore_3 (0, 0)
	10 iconst_0 (0, 0)
	11 istore (0, 0)
	12 #4 (0, 0)
	13 iload_2 (1, 1)
	14 iload_3 (1, 1)
	15 if_icmpge (1, 1)
	16 40 (1, 1)
	18 aload_0 (1, 1)
	19 iload_2 (1, 1)
	20 iinc (1, 1)
	21 #2 (1, 1)
	22 -74 (1, 1)
	23 invokevirtual (1, 1)
	24 java/lang/String.charAt:(I)C (1, 1)
	26 istore (1, 1)
	27 #5 (1, 1)
	28 iload (1, 3)
	29 #5 (1, 3)
	30 invokestatic (1, 3)
	31 java/lang/Character.isWhitespace:(C)Z (1, 3)
	33 ifeq (1, 3)
	34 8 (1, 3)
	36 iload_2 (1, 3)
	37 iload_3 (1, 3)
	38 if_icmplt (1, 3)
	39 -20 (1, 3)
	41 aload_1 (1, 3)
	42 iload_2 (1, 3)
	43 invokevirtual (1, 3)
	44 java/text/ParsePosition.setIndex:(I)V (1, 3)
	46 iload_2 (2, 1)
	47 iload_3 (2, 1)
	48 if_icmpge (2, 1)
	49 7 (2, 1)
	51 iload (2, 1)
	52 #5 (2, 1)
	53 istore (2, 1)
	54 #4 (2, 1)
	55 iload (0, 0)
	56 #4 (0, 0)
	57 ireturn (0, 0)

Method: format
	0 aload_0 (0, 4)
	1 lload_1 (0, 4)
	2 invokestatic (0, 4)
	3 java/lang/Long.valueOf:(J)Ljava/lang/Long; (0, 4)
	5 aload_3 (0, 4)
	6 aload (0, 4)
	7 #4 (0, 4)
	8 invokevirtual (0, 4)
	9 org/apache/commons/math3/fraction/AbstractFormat.format:(Ljava/lang/Object;Ljava/lang/StringBuffer;Ljava/text/FieldPosition;)Ljava/lang/StringBuffer; (0, 4)
	11 areturn (0, 4)

