Method: <init>
	0 aload_0 (0, 0)
	1 invokespecial (0, 0)
	4 aload_0 (0, 0)
	5 aload_1 (0, 0)
	6 putfield (0, 0)
	9 aload_0 (0, 0)
	10 aload_2 (0, 0)
	11 putfield (0, 0)
	14 return (0, 0)

Method: getDefaultNumberFormat
	0 aload_0 (0, 0)
	1 invokestatic (0, 0)
	4 astore_1 (0, 0)
	5 aload_1 (0, 0)
	6 iconst_0 (0, 0)
	7 invokevirtual (0, 0)
	10 aload_1 (0, 0)
	11 iconst_1 (0, 0)
	12 invokevirtual (0, 0)
	15 aload_1 (0, 0)
	16 areturn (0, 0)

Method: getDenominatorFormat
	0 aload_0 (0, 0)
	1 getfield (0, 0)
	4 areturn (0, 0)

Method: getNumeratorFormat
	0 aload_0 (0, 0)
	1 getfield (0, 0)
	4 areturn (0, 0)

Method: setDenominatorFormat
	0 aload_1 (1, 1)
	1 ifnonnull (1, 1)
	4 new (1, 1)
	7 dup (1, 1)
	8 getstatic (1, 1)
	11 iconst_0 (1, 1)
	12 anewarray (1, 1)
	15 invokespecial (1, 1)
	18 athrow (1, 1)
	19 aload_0 (0, 4)
	20 aload_1 (0, 4)
	21 putfield (0, 4)
	24 return (0, 0)

Method: setNumeratorFormat
	0 aload_1 (1, 1)
	1 ifnonnull (1, 1)
	4 new (1, 1)
	7 dup (1, 1)
	8 getstatic (1, 1)
	11 iconst_0 (1, 1)
	12 anewarray (1, 1)
	15 invokespecial (1, 1)
	18 athrow (1, 1)
	19 aload_0 (0, 4)
	20 aload_1 (0, 4)
	21 putfield (0, 4)
	24 return (0, 0)

Method: parseAndIgnoreWhitespace
	0 aload_0 (0, 0)
	1 aload_1 (0, 0)
	2 invokestatic (0, 0)
	5 pop (0, 0)
	6 aload_1 (0, 0)
	7 aload_1 (0, 0)
	8 invokevirtual (0, 0)
	11 iconst_1 (0, 0)
	12 isub (0, 0)
	13 invokevirtual (0, 0)
	16 return (0, 0)

Method: parseNextCharacter
	0 aload_1 (0, 0)
	1 invokevirtual (0, 0)
	4 istore_2 (0, 0)
	5 aload_0 (0, 0)
	6 invokevirtual (0, 0)
	9 istore_3 (0, 0)
	10 iconst_0 (0, 0)
	11 istore (0, 0)
	13 iload_2 (1, 1)
	14 iload_3 (1, 1)
	15 if_icmpge (1, 1)
	18 aload_0 (2, 1)
	19 iload_2 (2, 1)
	20 iinc (2, 1)
	23 invokevirtual (2, 1)
	26 istore (2, 1)
	28 iload (1, 1)
	30 invokestatic (1, 1)
	33 ifeq (1, 1)
	36 iload_2 (1, 1)
	37 iload_3 (1, 1)
	38 if_icmplt (1, 1)
	41 aload_1 (1, 1)
	42 iload_2 (1, 1)
	43 invokevirtual (1, 1)
	46 iload_2 (2, 1)
	47 iload_3 (2, 1)
	48 if_icmpge (2, 1)
	51 iload (2, 1)
	53 istore (2, 1)
	55 iload (0, 0)
	57 ireturn (0, 0)

Method: format
	0 aload_0 (0, 4)
	1 lload_1 (0, 4)
	2 invokestatic (0, 4)
	5 aload_3 (0, 4)
	6 aload (0, 4)
	8 invokevirtual (0, 4)
	11 areturn (0, 4)

