Method: <init>
	0 aload_0 (0, 0)
	1 aload_1 (0, 0)
	2 aload_2 (0, 0)
	3 invokespecial (0, 0)
	4 org/apache/commons/math3/fraction/AbstractFormat.<init>:(Ljava/text/NumberFormat;Ljava/text/NumberFormat;)V (0, 0)
	6 return (0, 0)

Method: getAvailableLocales
	0 invokestatic (0, 0)
	1 java/text/NumberFormat.getAvailableLocales:()[Ljava/util/Locale; (0, 0)
	3 areturn (0, 0)

Method: formatBigFraction
	0 invokestatic (1, 4)
	1 org/apache/commons/math3/fraction/BigFractionFormat.getImproperInstance:()Lorg/apache/commons/math3/fraction/BigFractionFormat; (1, 4)
	3 aload_0 (1, 4)
	4 invokevirtual (1, 4)
	5 org/apache/commons/math3/fraction/BigFractionFormat.format:(Ljava/lang/Object;)Ljava/lang/String; (1, 4)
	7 areturn (0, 4)

Method: getImproperInstance
	0 new (0, 0)
	1 org/apache/commons/math3/fraction/BigFractionFormat (0, 0)
	3 dup (0, 0)
	4 aload_0 (0, 0)
	5 invokestatic (0, 0)
	6 org/apache/commons/math3/fraction/BigFractionFormat.getDefaultNumberFormat:(Ljava/util/Locale;)Ljava/text/NumberFormat; (0, 0)
	8 invokespecial (0, 0)
	9 org/apache/commons/math3/fraction/BigFractionFormat.<init>:(Ljava/text/NumberFormat;)V (0, 0)
	11 areturn (0, 0)

Method: getProperInstance
	0 new (0, 0)
	1 org/apache/commons/math3/fraction/ProperBigFractionFormat (0, 0)
	3 dup (0, 0)
	4 aload_0 (0, 0)
	5 invokestatic (0, 0)
	6 org/apache/commons/math3/fraction/BigFractionFormat.getDefaultNumberFormat:(Ljava/util/Locale;)Ljava/text/NumberFormat; (0, 0)
	8 invokespecial (0, 0)
	9 org/apache/commons/math3/fraction/ProperBigFractionFormat.<init>:(Ljava/text/NumberFormat;)V (0, 0)
	11 areturn (0, 0)

Method: format
	0 aload_1 (1, 1)
	1 instanceof (1, 1)
	2 org/apache/commons/math3/fraction/BigFraction (1, 1)
	4 ifeq (1, 1)
	5 18 (1, 1)
	7 aload_0 (2, 4)
	8 aload_1 (2, 4)
	9 checkcast (2, 4)
	10 org/apache/commons/math3/fraction/BigFraction (2, 4)
	12 aload_2 (2, 4)
	13 aload_3 (2, 4)
	14 invokevirtual (2, 4)
	15 org/apache/commons/math3/fraction/BigFractionFormat.format:(Lorg/apache/commons/math3/fraction/BigFraction;Ljava/lang/StringBuffer;Ljava/text/FieldPosition;)Ljava/lang/StringBuffer; (2, 4)
	17 astore (2, 4)
	18 #4 (2, 4)
	19 goto (2, 4)
	20 79 (2, 4)
	22 aload_1 (3, 1)
	23 instanceof (3, 1)
	24 java/math/BigInteger (3, 1)
	26 ifeq (3, 1)
	27 25 (3, 1)
	29 aload_0 (4, 4)
	30 new (4, 4)
	31 org/apache/commons/math3/fraction/BigFraction (4, 4)
	33 dup (4, 4)
	34 aload_1 (4, 4)
	35 checkcast (4, 4)
	36 java/math/BigInteger (4, 4)
	38 invokespecial (4, 4)
	39 org/apache/commons/math3/fraction/BigFraction.<init>:(Ljava/math/BigInteger;)V (4, 4)
	41 aload_2 (4, 4)
	42 aload_3 (4, 4)
	43 invokevirtual (4, 4)
	44 org/apache/commons/math3/fraction/BigFractionFormat.format:(Lorg/apache/commons/math3/fraction/BigFraction;Ljava/lang/StringBuffer;Ljava/text/FieldPosition;)Ljava/lang/StringBuffer; (4, 4)
	46 astore (4, 4)
	47 #4 (4, 4)
	48 goto (4, 4)
	49 50 (4, 4)
	51 aload_1 (5, 1)
	52 instanceof (5, 1)
	53 java/lang/Number (5, 1)
	55 ifeq (5, 1)
	56 28 (5, 1)
	58 aload_0 (6, 4)
	59 new (6, 4)
	60 org/apache/commons/math3/fraction/BigFraction (6, 4)
	62 dup (6, 4)
	63 aload_1 (6, 4)
	64 checkcast (6, 4)
	65 java/lang/Number (6, 4)
	67 invokevirtual (6, 4)
	68 java/lang/Number.doubleValue:()D (6, 4)
	70 invokespecial (6, 4)
	71 org/apache/commons/math3/fraction/BigFraction.<init>:(D)V (6, 4)
	73 aload_2 (6, 4)
	74 aload_3 (6, 4)
	75 invokevirtual (6, 4)
	76 org/apache/commons/math3/fraction/BigFractionFormat.format:(Lorg/apache/commons/math3/fraction/BigFraction;Ljava/lang/StringBuffer;Ljava/text/FieldPosition;)Ljava/lang/StringBuffer; (6, 4)
	78 astore (6, 4)
	79 #4 (6, 4)
	80 goto (6, 4)
	81 18 (6, 4)
	83 new (7, 2)
	84 org/apache/commons/math3/exception/MathIllegalArgumentException (7, 2)
	86 dup (7, 2)
	87 getstatic (7, 2)
	88 org/apache/commons/math3/exception/util/LocalizedFormats.CANNOT_FORMAT_OBJECT_TO_FRACTION:Lorg/apache/commons/math3/exception/util/LocalizedFormats; (7, 2)
	90 iconst_0 (7, 2)
	91 anewarray (7, 2)
	92 java/lang/Object (7, 2)
	94 invokespecial (7, 2)
	95 org/apache/commons/math3/exception/MathIllegalArgumentException.<init>:(Lorg/apache/commons/math3/exception/util/Localizable;[Ljava/lang/Object;)V (7, 2)
	97 athrow (7, 2)
	98 aload (0, 0)
	99 #4 (0, 0)
	100 areturn (0, 0)

Method: parse
	0 aload_0 (0, 0)
	1 aload_1 (0, 0)
	2 aload_2 (0, 0)
	3 invokevirtual (0, 0)
	4 org/apache/commons/math3/fraction/BigFractionFormat.parse:(Ljava/lang/String;Ljava/text/ParsePosition;)Lorg/apache/commons/math3/fraction/BigFraction; (0, 0)
	6 areturn (0, 0)

Method: parseNextBigInteger
	0 aload_2 (0, 0)
	1 invokevirtual (0, 0)
	2 java/text/ParsePosition.getIndex:()I (0, 0)
	4 istore_3 (0, 0)
	5 aload_1 (0, 0)
	6 iload_3 (0, 0)
	7 invokevirtual (0, 0)
	8 java/lang/String.charAt:(I)C (0, 0)
	10 bipush (0, 0)
	11 45 (0, 0)
	12 if_icmpne (0, 0)
	13 9 (0, 0)
	15 iload_3 (0, 0)
	16 iconst_1 (0, 0)
	17 iadd (0, 0)
	18 goto (0, 0)
	19 4 (0, 0)
	21 iload_3 (0, 0)
	22 istore (0, 0)
	23 #4 (0, 0)
	24 iload (1, 3)
	25 #4 (1, 3)
	26 aload_1 (1, 3)
	27 invokevirtual (1, 3)
	28 java/lang/String.length:()I (1, 3)
	30 if_icmpge (1, 3)
	31 21 (1, 3)
	33 aload_1 (1, 3)
	34 iload (1, 3)
	35 #4 (1, 3)
	36 invokevirtual (1, 3)
	37 java/lang/String.charAt:(I)C (1, 3)
	39 invokestatic (1, 3)
	40 java/lang/Character.isDigit:(C)Z (1, 3)
	42 ifeq (1, 3)
	43 9 (1, 3)
	45 iinc (1, 3)
	46 #4 (1, 3)
	47 -89 (1, 3)
	48 goto (1, 3)
	49 -24 (1, 3)
	51 new (1, 3)
	52 java/math/BigInteger (1, 3)
	54 dup (1, 3)
	55 aload_1 (1, 3)
	56 iload_3 (1, 3)
	57 iload (1, 3)
	58 #4 (1, 3)
	59 invokevirtual (1, 3)
	60 java/lang/String.substring:(II)Ljava/lang/String; (1, 3)
	62 invokespecial (1, 3)
	63 java/math/BigInteger.<init>:(Ljava/lang/String;)V (1, 3)
	65 astore (1, 3)
	66 #5 (1, 3)
	67 aload_2 (1, 3)
	68 iload (1, 3)
	69 #4 (1, 3)
	70 invokevirtual (1, 3)
	71 java/text/ParsePosition.setIndex:(I)V (1, 3)
	73 aload (1, 3)
	74 #5 (1, 3)
	75 areturn (1, 3)
	76 astore (1, 3)
	77 #5 (1, 3)
	78 aload_2 (1, 3)
	79 iload_3 (1, 3)
	80 invokevirtual (1, 3)
	81 java/text/ParsePosition.setErrorIndex:(I)V (1, 3)
	83 aconst_null (1, 3)
	84 areturn (0, 3)

