Method: access$000
	0 getstatic (0, 0)
	1 org/apache/commons/math3/fraction/BigFractionField$LazyHolder.INSTANCE:Lorg/apache/commons/math3/fraction/BigFractionField; (0, 0)
	3 areturn (0, 0)

Method: <clinit>
	0 new (0, 0)
	1 org/apache/commons/math3/fraction/BigFractionField (0, 0)
	3 dup (0, 0)
	4 aconst_null (0, 0)
	5 invokespecial (0, 0)
	6 org/apache/commons/math3/fraction/BigFractionField.<init>:(Lorg/apache/commons/math3/fraction/BigFractionField$1;)V (0, 0)
	8 putstatic (0, 0)
	9 org/apache/commons/math3/fraction/BigFractionField$LazyHolder.INSTANCE:Lorg/apache/commons/math3/fraction/BigFractionField; (0, 0)
	11 return (0, 0)

