Method: <init>
	0 aload_0 (0, 0)
	1 aload_1 (0, 0)
	2 aload_2 (0, 0)
	3 invokespecial (0, 0)
	6 return (0, 0)

Method: getAvailableLocales
	0 invokestatic (0, 0)
	3 areturn (0, 0)

Method: formatBigFraction
	0 invokestatic (0, 4)
	3 aload_0 (0, 4)
	4 invokevirtual (0, 4)
	7 areturn (0, 4)

Method: getImproperInstance
	0 new (0, 0)
	3 dup (0, 0)
	4 aload_0 (0, 0)
	5 invokestatic (0, 0)
	8 invokespecial (0, 0)
	11 areturn (0, 0)

Method: getProperInstance
	0 new (0, 0)
	3 dup (0, 0)
	4 aload_0 (0, 0)
	5 invokestatic (0, 0)
	8 invokespecial (0, 0)
	11 areturn (0, 0)

Method: format
	0 aload_1 (1, 1)
	1 instanceof (1, 1)
	4 ifeq (1, 1)
	7 aload_0 (1, 4)
	8 aload_1 (1, 4)
	9 checkcast (1, 4)
	12 aload_2 (1, 4)
	13 aload_3 (1, 4)
	14 invokevirtual (1, 4)
	17 astore (1, 4)
	19 goto (1, 4)
	22 aload_1 (1, 1)
	23 instanceof (1, 1)
	26 ifeq (1, 1)
	29 aload_0 (1, 4)
	30 new (1, 4)
	33 dup (1, 4)
	34 aload_1 (1, 4)
	35 checkcast (1, 4)
	38 invokespecial (1, 4)
	41 aload_2 (1, 4)
	42 aload_3 (1, 4)
	43 invokevirtual (1, 4)
	46 astore (1, 4)
	48 goto (1, 4)
	51 aload_1 (1, 1)
	52 instanceof (1, 1)
	55 ifeq (1, 1)
	58 aload_0 (1, 4)
	59 new (1, 4)
	62 dup (1, 4)
	63 aload_1 (1, 4)
	64 checkcast (1, 4)
	67 invokevirtual (1, 4)
	70 invokespecial (1, 4)
	73 aload_2 (1, 4)
	74 aload_3 (1, 4)
	75 invokevirtual (1, 4)
	78 astore (1, 4)
	80 goto (1, 4)
	83 new (1, 2)
	86 dup (1, 2)
	87 getstatic (1, 2)
	90 iconst_0 (1, 2)
	91 anewarray (1, 2)
	94 invokespecial (1, 2)
	97 athrow (1, 2)
	98 aload (0, 4)
	100 areturn (0, 4)

Method: parse
	0 aload_0 (0, 0)
	1 aload_1 (0, 0)
	2 aload_2 (0, 0)
	3 invokevirtual (0, 0)
	6 areturn (0, 0)

Method: parseNextBigInteger
	0 aload_2 (0, 0)
	1 invokevirtual (0, 0)
	4 istore_3 (0, 0)
	5 aload_1 (0, 0)
	6 iload_3 (0, 0)
	7 invokevirtual (0, 0)
	10 bipush (0, 0)
	12 if_icmpne (0, 0)
	15 iload_3 (0, 0)
	16 iconst_1 (0, 0)
	17 iadd (0, 0)
	18 goto (0, 0)
	21 iload_3 (0, 0)
	22 istore (0, 0)
	24 iload (0, 3)
	26 aload_1 (0, 3)
	27 invokevirtual (0, 3)
	30 if_icmpge (0, 3)
	33 aload_1 (0, 3)
	34 iload (0, 3)
	36 invokevirtual (1, 3)
	39 invokestatic (1, 3)
	42 ifeq (1, 3)
	45 iinc (1, 3)
	48 goto (1, 3)
	51 new (0, 0)
	54 dup (0, 0)
	55 aload_1 (0, 0)
	56 iload_3 (0, 0)
	57 iload (0, 0)
	59 invokevirtual (0, 0)
	62 invokespecial (0, 0)
	65 astore (0, 0)
	67 aload_2 (0, 0)
	68 iload (0, 0)
	70 invokevirtual (0, 0)
	73 aload (0, 0)
	75 areturn (0, 0)
	76 astore (0, 0)
	78 aload_2 (0, 0)
	79 iload_3 (0, 0)
	80 invokevirtual (0, 0)
	83 aconst_null (0, 0)
	84 areturn (0, 0)

