Method: <init>
	0 aload_0 (0, 0)
	1 aload_2 (0, 0)
	2 aload_3 (0, 0)
	3 invokespecial (0, 0)
	6 aload_0 (0, 0)
	7 aload_1 (0, 0)
	8 invokevirtual (0, 0)
	11 return (0, 0)

Method: format
	0 aload_3 (0, 0)
	1 iconst_0 (0, 0)
	2 invokevirtual (0, 0)
	5 aload_3 (0, 0)
	6 iconst_0 (0, 0)
	7 invokevirtual (0, 0)
	10 aload_1 (0, 0)
	11 invokevirtual (0, 0)
	14 astore (0, 0)
	16 aload_1 (0, 0)
	17 invokevirtual (0, 0)
	20 astore (0, 0)
	22 aload (0, 0)
	24 aload (0, 0)
	26 invokevirtual (0, 0)
	29 astore (0, 0)
	31 aload (0, 0)
	33 aload (0, 0)
	35 invokevirtual (0, 0)
	38 astore (0, 0)
	40 getstatic (1, 1)
	43 aload (1, 1)
	45 invokevirtual (1, 1)
	48 ifne (1, 1)
	51 aload_0 (1, 4)
	52 invokevirtual (1, 4)
	55 aload (1, 4)
	57 aload_2 (1, 4)
	58 aload_3 (1, 4)
	59 invokevirtual (1, 4)
	62 pop (1, 4)
	63 aload_2 (1, 4)
	64 bipush (1, 4)
	66 invokevirtual (1, 4)
	69 pop (1, 4)
	70 aload (2, 1)
	72 getstatic (2, 1)
	75 invokevirtual (2, 1)
	78 ifge (2, 1)
	81 aload (2, 1)
	83 invokevirtual (2, 1)
	86 astore (2, 1)
	88 aload_0 (0, 4)
	89 invokevirtual (0, 4)
	92 aload (0, 4)
	94 aload_2 (0, 4)
	95 aload_3 (0, 4)
	96 invokevirtual (0, 4)
	99 pop (0, 4)
	100 aload_2 (0, 4)
	101 ldc (0, 4)
	103 invokevirtual (0, 4)
	106 pop (0, 4)
	107 aload_0 (0, 4)
	108 invokevirtual (0, 4)
	111 aload (0, 4)
	113 aload_2 (0, 4)
	114 aload_3 (0, 4)
	115 invokevirtual (0, 4)
	118 pop (0, 4)
	119 aload_2 (0, 4)
	120 areturn (0, 4)

Method: getWholeFormat
	0 aload_0 (0, 0)
	1 getfield (0, 0)
	4 areturn (0, 0)

Method: parse
	0 aload_0 (0, 0)
	1 aload_1 (0, 0)
	2 aload_2 (0, 0)
	3 invokevirtual (0, 0)
	6 areturn (0, 0)

Method: setWholeFormat
	0 aload_1 (1, 1)
	1 ifnonnull (1, 1)
	4 new (1, 1)
	7 dup (1, 1)
	8 getstatic (1, 1)
	11 iconst_0 (1, 1)
	12 anewarray (1, 1)
	15 invokespecial (1, 1)
	18 athrow (1, 1)
	19 aload_0 (0, 4)
	20 aload_1 (0, 4)
	21 putfield (0, 4)
	24 return (0, 0)

