Method: <init>
	0 aload_0 (0, 0)
	1 invokespecial (0, 0)
	4 return (0, 0)

Method: addAndCheck
	0 lload_0 (0, 0)
	1 lload_2 (0, 0)
	2 ladd (0, 0)
	3 lstore (0, 0)
	5 lload_0 (1, 1)
	6 lload_2 (1, 1)
	7 lxor (1, 1)
	8 lconst_0 (1, 1)
	9 lcmp (1, 1)
	10 ifge (1, 1)
	13 iconst_1 (1, 1)
	14 goto (1, 1)
	17 iconst_0 (1, 1)
	18 lload_0 (1, 1)
	19 lload (1, 1)
	21 lxor (1, 1)
	22 lconst_0 (1, 1)
	23 lcmp (1, 1)
	24 iflt (1, 1)
	27 iconst_1 (1, 1)
	28 goto (1, 1)
	31 iconst_0 (1, 1)
	32 ior (1, 1)
	33 ifne (1, 1)
	36 new (1, 1)
	39 dup (1, 1)
	40 aload (1, 1)
	42 iconst_2 (1, 1)
	43 anewarray (1, 1)
	46 dup (1, 1)
	47 iconst_0 (1, 1)
	48 lload_0 (1, 1)
	49 invokestatic (1, 1)
	52 aastore (1, 1)
	53 dup (1, 1)
	54 iconst_1 (1, 1)
	55 lload_2 (1, 1)
	56 invokestatic (1, 1)
	59 aastore (1, 1)
	60 invokespecial (1, 1)
	63 athrow (1, 1)
	64 lload (0, 0)
	66 lreturn (0, 0)

Method: binomialCoefficient
	0 iload_0 (0, 0)
	1 iload_1 (0, 0)
	2 invokestatic (0, 0)
	5 lreturn (0, 0)

Method: binomialCoefficientDouble
	0 iload_0 (0, 0)
	1 iload_1 (0, 0)
	2 invokestatic (0, 0)
	5 dreturn (0, 0)

Method: binomialCoefficientLog
	0 iload_0 (0, 0)
	1 iload_1 (0, 0)
	2 invokestatic (0, 0)
	5 dreturn (0, 0)

Method: factorial
	0 iload_0 (0, 0)
	1 invokestatic (0, 0)
	4 lreturn (0, 0)

Method: factorialDouble
	0 iload_0 (0, 0)
	1 invokestatic (0, 0)
	4 dreturn (0, 0)

Method: factorialLog
	0 iload_0 (0, 0)
	1 invokestatic (0, 0)
	4 dreturn (0, 0)

Method: gcd
	0 lload_0 (0, 0)
	1 lstore (0, 0)
	3 lload_2 (0, 0)
	4 lstore (0, 0)
	6 lload (1, 1)
	8 lconst_0 (1, 1)
	9 lcmp (1, 1)
	10 ifeq (1, 1)
	13 lload (1, 1)
	15 lconst_0 (1, 1)
	16 lcmp (1, 1)
	17 ifne (1, 1)
	20 lload (2, 1)
	22 ldc2_w (2, 1)
	25 lcmp (2, 1)
	26 ifeq (2, 1)
	29 lload (2, 1)
	31 ldc2_w (2, 1)
	34 lcmp (2, 1)
	35 ifne (2, 1)
	38 new (2, 1)
	41 dup (2, 1)
	42 getstatic (2, 1)
	45 iconst_2 (2, 1)
	46 anewarray (2, 1)
	49 dup (2, 1)
	50 iconst_0 (2, 1)
	51 lload_0 (2, 1)
	52 invokestatic (2, 1)
	55 aastore (2, 1)
	56 dup (2, 1)
	57 iconst_1 (2, 1)
	58 lload_2 (2, 1)
	59 invokestatic (2, 1)
	62 aastore (2, 1)
	63 invokespecial (2, 1)
	66 athrow (2, 1)
	67 lload (1, 1)
	69 invokestatic (1, 1)
	72 lload (1, 1)
	74 invokestatic (1, 1)
	77 ladd (1, 1)
	78 lreturn (1, 1)
	79 lload (1, 1)
	81 lconst_0 (1, 1)
	82 lcmp (1, 1)
	83 ifle (1, 1)
	86 lload (1, 1)
	88 lneg (1, 1)
	89 lstore (1, 1)
	91 lload (1, 1)
	93 lconst_0 (1, 1)
	94 lcmp (1, 1)
	95 ifle (1, 1)
	98 lload (1, 1)
	100 lneg (1, 1)
	101 lstore (1, 1)
	103 iconst_0 (0, 3)
	104 istore (0, 3)
	106 lload (1, 3)
	108 lconst_1 (1, 3)
	109 land (1, 3)
	110 lconst_0 (1, 3)
	111 lcmp (1, 3)
	112 ifne (1, 3)
	115 lload (1, 3)
	117 lconst_1 (1, 3)
	118 land (1, 3)
	119 lconst_0 (1, 3)
	120 lcmp (1, 3)
	121 ifne (1, 3)
	124 iload (1, 3)
	126 bipush (1, 3)
	128 if_icmpge (1, 3)
	131 lload (1, 3)
	133 ldc2_w (1, 3)
	136 ldiv (1, 3)
	137 lstore (1, 3)
	139 lload (1, 3)
	141 ldc2_w (1, 3)
	144 ldiv (1, 3)
	145 lstore (1, 3)
	147 iinc (1, 3)
	150 goto (1, 3)
	153 iload (1, 1)
	155 bipush (1, 1)
	157 if_icmpne (1, 1)
	160 new (1, 1)
	163 dup (1, 1)
	164 getstatic (1, 1)
	167 iconst_2 (1, 1)
	168 anewarray (1, 1)
	171 dup (1, 1)
	172 iconst_0 (1, 1)
	173 lload_0 (1, 1)
	174 invokestatic (1, 1)
	177 aastore (1, 1)
	178 dup (1, 1)
	179 iconst_1 (1, 1)
	180 lload_2 (1, 1)
	181 invokestatic (1, 1)
	184 aastore (1, 1)
	185 invokespecial (1, 1)
	188 athrow (1, 1)
	189 lload (0, 3)
	191 lconst_1 (0, 3)
	192 land (0, 3)
	193 lconst_1 (0, 3)
	194 lcmp (0, 3)
	195 ifne (0, 3)
	198 lload (0, 3)
	200 goto (0, 3)
	203 lload (0, 3)
	205 ldc2_w (0, 3)
	208 ldiv (0, 3)
	209 lneg (0, 3)
	210 lstore (0, 3)
	212 lload (2, 3)
	214 lconst_1 (2, 3)
	215 land (2, 3)
	216 lconst_0 (2, 3)
	217 lcmp (2, 3)
	218 ifne (2, 3)
	221 lload (2, 3)
	223 ldc2_w (2, 3)
	226 ldiv (2, 3)
	227 lstore (2, 3)
	229 goto (2, 3)
	232 lload (2, 1)
	234 lconst_0 (2, 1)
	235 lcmp (2, 1)
	236 ifle (2, 1)
	239 lload (2, 1)
	241 lneg (2, 1)
	242 lstore (2, 1)
	244 goto (2, 1)
	247 lload (2, 2)
	249 lstore (2, 2)
	251 lload (1, 1)
	253 lload (1, 1)
	255 lsub (1, 1)
	256 ldc2_w (1, 1)
	259 ldiv (1, 1)
	260 lstore (1, 1)
	262 lload (0, 1)
	264 lconst_0 (0, 1)
	265 lcmp (0, 1)
	266 ifne (0, 1)
	269 lload (0, 1)
	271 lneg (0, 1)
	272 lconst_1 (0, 1)
	273 iload (0, 1)
	275 lshl (0, 1)
	276 lmul (0, 1)
	277 lreturn (0, 1)

Method: gcdPositive
	0 iload_0 (1, 1)
	1 ifne (1, 1)
	4 iload_1 (1, 1)
	5 ireturn (1, 1)
	6 iload_1 (1, 1)
	7 ifne (1, 1)
	10 iload_0 (1, 1)
	11 ireturn (1, 1)
	12 iload_0 (0, 0)
	13 invokestatic (0, 0)
	16 istore_2 (0, 0)
	17 iload_0 (0, 0)
	18 iload_2 (0, 0)
	19 ishr (0, 0)
	20 istore_0 (0, 0)
	21 iload_1 (0, 0)
	22 invokestatic (0, 0)
	25 istore_3 (0, 0)
	26 iload_1 (0, 0)
	27 iload_3 (0, 0)
	28 ishr (0, 0)
	29 istore_1 (0, 0)
	30 iload_2 (0, 1)
	31 iload_3 (0, 1)
	32 invokestatic (0, 1)
	35 istore (0, 1)
	37 iload_0 (1, 3)
	38 iload_1 (1, 3)
	39 if_icmpeq (1, 3)
	42 iload_0 (1, 3)
	43 iload_1 (1, 3)
	44 isub (1, 3)
	45 istore (1, 3)
	47 iload_0 (1, 3)
	48 iload_1 (1, 3)
	49 invokestatic (1, 3)
	52 istore_1 (1, 3)
	53 iload (1, 3)
	55 invokestatic (1, 3)
	58 istore_0 (1, 3)
	59 iload_0 (1, 3)
	60 iload_0 (1, 3)
	61 invokestatic (1, 3)
	64 ishr (1, 3)
	65 istore_0 (1, 3)
	66 goto (0, 1)
	69 iload_0 (0, 1)
	70 iload (0, 1)
	72 ishl (0, 1)
	73 ireturn (0, 1)

Method: lcm
	0 lload_0 (1, 1)
	1 lconst_0 (1, 1)
	2 lcmp (1, 1)
	3 ifeq (1, 1)
	6 lload_2 (1, 1)
	7 lconst_0 (1, 1)
	8 lcmp (1, 1)
	9 ifne (1, 1)
	12 lconst_0 (1, 1)
	13 lreturn (1, 1)
	14 lload_0 (0, 0)
	15 lload_0 (0, 0)
	16 lload_2 (0, 0)
	17 invokestatic (0, 0)
	20 ldiv (0, 0)
	21 lload_2 (0, 0)
	22 invokestatic (0, 0)
	25 invokestatic (0, 0)
	28 lstore (0, 0)
	30 lload (1, 1)
	32 ldc2_w (1, 1)
	35 lcmp (1, 1)
	36 ifne (1, 1)
	39 new (1, 1)
	42 dup (1, 1)
	43 getstatic (1, 1)
	46 iconst_2 (1, 1)
	47 anewarray (1, 1)
	50 dup (1, 1)
	51 iconst_0 (1, 1)
	52 lload_0 (1, 1)
	53 invokestatic (1, 1)
	56 aastore (1, 1)
	57 dup (1, 1)
	58 iconst_1 (1, 1)
	59 lload_2 (1, 1)
	60 invokestatic (1, 1)
	63 aastore (1, 1)
	64 invokespecial (1, 1)
	67 athrow (1, 1)
	68 lload (0, 0)
	70 lreturn (0, 0)

Method: mulAndCheck
	0 lload_0 (1, 1)
	1 lload_2 (1, 1)
	2 lcmp (1, 1)
	3 ifle (1, 1)
	6 lload_2 (1, 1)
	7 lload_0 (1, 1)
	8 invokestatic (1, 1)
	11 lstore (1, 1)
	13 goto (1, 1)
	16 lload_0 (2, 1)
	17 lconst_0 (2, 1)
	18 lcmp (2, 1)
	19 ifge (2, 1)
	22 lload_2 (3, 1)
	23 lconst_0 (3, 1)
	24 lcmp (3, 1)
	25 ifge (3, 1)
	28 lload_0 (4, 1)
	29 ldc2_w (4, 1)
	32 lload_2 (4, 1)
	33 ldiv (4, 1)
	34 lcmp (4, 1)
	35 iflt (4, 1)
	38 lload_0 (4, 1)
	39 lload_2 (4, 1)
	40 lmul (4, 1)
	41 lstore (4, 1)
	43 goto (4, 1)
	46 new (4, 2)
	49 dup (4, 2)
	50 invokespecial (4, 2)
	53 athrow (4, 2)
	54 lload_2 (3, 1)
	55 lconst_0 (3, 1)
	56 lcmp (3, 1)
	57 ifle (3, 1)
	60 ldc2_w (4, 1)
	63 lload_2 (4, 1)
	64 ldiv (4, 1)
	65 lload_0 (4, 1)
	66 lcmp (4, 1)
	67 ifgt (4, 1)
	70 lload_0 (4, 1)
	71 lload_2 (4, 1)
	72 lmul (4, 1)
	73 lstore (4, 1)
	75 goto (4, 1)
	78 new (4, 2)
	81 dup (4, 2)
	82 invokespecial (4, 2)
	85 athrow (4, 2)
	86 lconst_0 (3, 2)
	87 lstore (3, 2)
	89 goto (3, 2)
	92 lload_0 (2, 1)
	93 lconst_0 (2, 1)
	94 lcmp (2, 1)
	95 ifle (2, 1)
	98 lload_0 (3, 1)
	99 ldc2_w (3, 1)
	102 lload_2 (3, 1)
	103 ldiv (3, 1)
	104 lcmp (3, 1)
	105 ifgt (3, 1)
	108 lload_0 (3, 1)
	109 lload_2 (3, 1)
	110 lmul (3, 1)
	111 lstore (3, 1)
	113 goto (3, 1)
	116 new (3, 2)
	119 dup (3, 2)
	120 invokespecial (3, 2)
	123 athrow (3, 2)
	124 lconst_0 (2, 2)
	125 lstore (2, 2)
	127 lload (0, 4)
	129 lreturn (0, 4)

Method: subAndCheck
	0 lload_2 (1, 1)
	1 ldc2_w (1, 1)
	4 lcmp (1, 1)
	5 ifne (1, 1)
	8 lload_0 (2, 1)
	9 lconst_0 (2, 1)
	10 lcmp (2, 1)
	11 ifge (2, 1)
	14 lload_0 (2, 1)
	15 lload_2 (2, 1)
	16 lsub (2, 1)
	17 lstore (2, 1)
	19 goto (2, 1)
	22 new (2, 2)
	25 dup (2, 2)
	26 getstatic (2, 2)
	29 iconst_2 (2, 2)
	30 anewarray (2, 2)
	33 dup (2, 2)
	34 iconst_0 (2, 2)
	35 lload_0 (2, 2)
	36 invokestatic (2, 2)
	39 aastore (2, 2)
	40 dup (2, 2)
	41 iconst_1 (2, 2)
	42 lload_2 (2, 2)
	43 lneg (2, 2)
	44 invokestatic (2, 2)
	47 aastore (2, 2)
	48 invokespecial (2, 2)
	51 athrow (2, 2)
	52 lload_0 (1, 2)
	53 lload_2 (1, 2)
	54 lneg (1, 2)
	55 getstatic (1, 2)
	58 invokestatic (1, 2)
	61 lstore (1, 2)
	63 lload (0, 1)
	65 lreturn (0, 1)

Method: pow
	0 aload_1 (1, 1)
	1 getstatic (1, 1)
	4 invokevirtual (1, 1)
	7 ifge (1, 1)
	10 new (1, 1)
	13 dup (1, 1)
	14 getstatic (1, 1)
	17 aload_1 (1, 1)
	18 invokespecial (1, 1)
	21 athrow (1, 1)
	22 getstatic (0, 0)
	25 astore_2 (0, 0)
	26 aload_0 (0, 0)
	27 astore_3 (0, 0)
	28 getstatic (1, 3)
	31 aload_1 (1, 3)
	32 invokevirtual (1, 3)
	35 ifne (1, 3)
	38 aload_1 (2, 1)
	39 iconst_0 (2, 1)
	40 invokevirtual (2, 1)
	43 ifeq (2, 1)
	46 aload_2 (2, 1)
	47 aload_3 (2, 1)
	48 invokevirtual (2, 1)
	51 astore_2 (2, 1)
	52 aload_3 (1, 3)
	53 aload_3 (1, 3)
	54 invokevirtual (1, 3)
	57 astore_3 (1, 3)
	58 aload_1 (1, 1)
	59 iconst_1 (1, 1)
	60 invokevirtual (1, 1)
	63 astore_1 (1, 1)
	64 goto (1, 1)
	67 aload_2 (0, 3)
	68 areturn (0, 3)

Method: stirlingS2
	0 iload_0 (0, 0)
	1 iload_1 (0, 0)
	2 invokestatic (0, 0)
	5 lreturn (0, 0)

Method: isPowerOfTwo
	0 lload_0 (0, 0)
	1 lconst_0 (0, 0)
	2 lcmp (0, 0)
	3 ifle (0, 0)
	6 lload_0 (0, 0)
	7 lload_0 (0, 0)
	8 lconst_1 (0, 0)
	9 lsub (0, 0)
	10 land (0, 0)
	11 lconst_0 (0, 0)
	12 lcmp (0, 0)
	13 ifne (0, 0)
	16 iconst_1 (0, 0)
	17 goto (0, 0)
	20 iconst_0 (0, 0)
	21 ireturn (0, 0)

