Method: <init>
	0 aload_0 (0, 0)
	1 invokespecial (0, 0)
	2 java/lang/Object.<init>:()V (0, 0)
	4 aload_0 (0, 0)
	5 getstatic (0, 0)
	6 java/math/RoundingMode.HALF_UP:Ljava/math/RoundingMode; (0, 0)
	8 putfield (0, 0)
	9 org/apache/commons/math3/util/BigReal.roundingMode:Ljava/math/RoundingMode; (0, 0)
	11 aload_0 (0, 0)
	12 bipush (0, 0)
	13 64 (0, 0)
	14 putfield (0, 0)
	15 org/apache/commons/math3/util/BigReal.scale:I (0, 0)
	17 aload_0 (0, 4)
	18 new (0, 4)
	19 java/math/BigDecimal (0, 4)
	21 dup (0, 4)
	22 aload_1 (0, 4)
	23 iload_2 (0, 4)
	24 invokespecial (0, 4)
	25 java/math/BigDecimal.<init>:(Ljava/math/BigInteger;I)V (0, 4)
	27 putfield (0, 4)
	28 org/apache/commons/math3/util/BigReal.d:Ljava/math/BigDecimal; (0, 4)
	30 return (0, 4)

