Method: <init>
	0 aload_0 (0, 0)
	1 invokespecial (0, 0)
	2 java/lang/Object.<init>:()V (0, 0)
	4 iload_1 (0, 0)
	5 iload_2 (0, 0)
	6 invokestatic (0, 0)
	7 org/apache/commons/math3/util/CombinatoricsUtils.checkBinomial:(II)V (0, 0)
	9 aload_0 (0, 0)
	10 iload_1 (0, 0)
	11 putfield (0, 0)
	12 org/apache/commons/math3/util/Combinations.n:I (0, 0)
	14 aload_0 (0, 0)
	15 iload_2 (0, 0)
	16 putfield (0, 0)
	17 org/apache/commons/math3/util/Combinations.k:I (0, 0)
	19 aload_0 (0, 0)
	20 aload_3 (0, 0)
	21 putfield (0, 0)
	22 org/apache/commons/math3/util/Combinations.iterationOrder:Lorg/apache/commons/math3/util/Combinations$IterationOrder; (0, 0)
	24 return (0, 0)

Method: getN
	0 aload_0 (0, 0)
	1 getfield (0, 0)
	2 org/apache/commons/math3/util/Combinations.n:I (0, 0)
	4 ireturn (0, 0)

Method: getK
	0 aload_0 (0, 0)
	1 getfield (0, 0)
	2 org/apache/commons/math3/util/Combinations.k:I (0, 0)
	4 ireturn (0, 0)

Method: iterator
	0 aload_0 (0, 1)
	1 getfield (0, 1)
	2 org/apache/commons/math3/util/Combinations.k:I (0, 1)
	4 ifeq (0, 1)
	5 14 (0, 1)
	7 aload_0 (0, 1)
	8 getfield (0, 1)
	9 org/apache/commons/math3/util/Combinations.k:I (0, 1)
	11 aload_0 (0, 1)
	12 getfield (0, 1)
	13 org/apache/commons/math3/util/Combinations.n:I (0, 1)
	15 if_icmpne (0, 1)
	16 18 (0, 1)
	18 new (0, 1)
	19 org/apache/commons/math3/util/Combinations$SingletonIterator (0, 1)
	21 dup (0, 1)
	22 aload_0 (0, 1)
	23 getfield (0, 1)
	24 org/apache/commons/math3/util/Combinations.k:I (0, 1)
	26 invokestatic (0, 1)
	27 org/apache/commons/math3/util/MathArrays.natural:(I)[I (0, 1)
	29 invokespecial (0, 1)
	30 org/apache/commons/math3/util/Combinations$SingletonIterator.<init>:([I)V (0, 1)
	32 areturn (0, 1)
	33 getstatic (1, 5)
	34 org/apache/commons/math3/util/Combinations$1.$SwitchMap$org$apache$commons$math3$util$Combinations$IterationOrder:[I (1, 5)
	36 aload_0 (1, 5)
	37 getfield (1, 5)
	38 org/apache/commons/math3/util/Combinations.iterationOrder:Lorg/apache/commons/math3/util/Combinations$IterationOrder; (1, 5)
	40 invokevirtual (1, 5)
	41 org/apache/commons/math3/util/Combinations$IterationOrder.ordinal:()I (1, 5)
	43 iaload (1, 5)
	44 lookupswitch (1, 5)
	45 1: 64 (1, 5)
	64 new (1, 5)
	65 org/apache/commons/math3/util/Combinations$LexicographicIterator (1, 5)
	67 dup (1, 5)
	68 aload_0 (1, 5)
	69 getfield (1, 5)
	70 org/apache/commons/math3/util/Combinations.n:I (1, 5)
	72 aload_0 (1, 5)
	73 getfield (1, 5)
	74 org/apache/commons/math3/util/Combinations.k:I (1, 5)
	76 invokespecial (1, 5)
	77 org/apache/commons/math3/util/Combinations$LexicographicIterator.<init>:(II)V (1, 5)
	79 areturn (1, 5)
	80 new (1, 5)
	81 org/apache/commons/math3/exception/MathInternalError (1, 5)
	83 dup (1, 5)
	84 invokespecial (1, 5)
	85 org/apache/commons/math3/exception/MathInternalError.<init>:()V (1, 5)
	87 athrow (1, 5)

Method: comparator
	0 new (0, 0)
	1 org/apache/commons/math3/util/Combinations$LexicographicComparator (0, 0)
	3 dup (0, 0)
	4 aload_0 (0, 0)
	5 getfield (0, 0)
	6 org/apache/commons/math3/util/Combinations.n:I (0, 0)
	8 aload_0 (0, 0)
	9 getfield (0, 0)
	10 org/apache/commons/math3/util/Combinations.k:I (0, 0)
	12 invokespecial (0, 0)
	13 org/apache/commons/math3/util/Combinations$LexicographicComparator.<init>:(II)V (0, 0)
	15 areturn (0, 0)

