Method: <init>
	0 aload_0 (0, 0)
	1 invokespecial (0, 0)
	2 java/lang/Object.<init>:()V (0, 0)
	4 aload_0 (0, 0)
	5 iconst_1 (0, 0)
	6 putfield (0, 0)
	7 org/apache/commons/math3/util/Combinations$LexicographicIterator.more:Z (0, 0)
	9 aload_0 (0, 0)
	10 iload_2 (0, 0)
	11 putfield (0, 0)
	12 org/apache/commons/math3/util/Combinations$LexicographicIterator.k:I (0, 0)
	14 aload_0 (0, 0)
	15 iload_2 (0, 0)
	16 iconst_3 (0, 0)
	17 iadd (0, 0)
	18 newarray (0, 0)
	19 10 (0, 0)
	20 putfield (0, 0)
	21 org/apache/commons/math3/util/Combinations$LexicographicIterator.c:[I (0, 0)
	23 iload_2 (3, 1)
	24 ifeq (3, 1)
	25 8 (3, 1)
	27 iload_2 (3, 1)
	28 iload_1 (3, 1)
	29 if_icmplt (3, 1)
	30 9 (3, 1)
	32 aload_0 (3, 1)
	33 iconst_0 (3, 1)
	34 putfield (3, 1)
	35 org/apache/commons/math3/util/Combinations$LexicographicIterator.more:Z (3, 1)
	37 return (3, 1)
	38 iconst_1 (3, 4)
	39 istore_3 (3, 4)
	40 iload_3 (3, 4)
	41 iload_2 (3, 4)
	42 if_icmpgt (3, 4)
	43 18 (3, 4)
	45 aload_0 (3, 4)
	46 getfield (3, 4)
	47 org/apache/commons/math3/util/Combinations$LexicographicIterator.c:[I (3, 4)
	49 iload_3 (3, 4)
	50 iload_3 (3, 4)
	51 iconst_1 (3, 4)
	52 isub (3, 4)
	53 iastore (3, 4)
	54 iinc (3, 4)
	55 #3 (3, 4)
	56 -89 (3, 4)
	57 goto (3, 4)
	58 -17 (3, 4)
	60 aload_0 (0, 0)
	61 getfield (0, 0)
	62 org/apache/commons/math3/util/Combinations$LexicographicIterator.c:[I (0, 0)
	64 iload_2 (0, 0)
	65 iconst_1 (0, 0)
	66 iadd (0, 0)
	67 iload_1 (0, 0)
	68 iastore (0, 0)
	69 aload_0 (0, 0)
	70 getfield (0, 0)
	71 org/apache/commons/math3/util/Combinations$LexicographicIterator.c:[I (0, 0)
	73 iload_2 (0, 0)
	74 iconst_2 (0, 0)
	75 iadd (0, 0)
	76 iconst_0 (0, 0)
	77 iastore (0, 0)
	78 aload_0 (0, 0)
	79 iload_2 (0, 0)
	80 putfield (0, 0)
	81 org/apache/commons/math3/util/Combinations$LexicographicIterator.j:I (0, 0)
	83 return (0, 0)

Method: hasNext
	0 aload_0 (0, 0)
	1 getfield (0, 0)
	2 org/apache/commons/math3/util/Combinations$LexicographicIterator.more:Z (0, 0)
	4 ireturn (0, 0)

Method: next
	0 aload_0 (0, 0)
	1 invokevirtual (0, 0)
	2 org/apache/commons/math3/util/Combinations$LexicographicIterator.next:()[I (0, 0)
	4 areturn (0, 0)

Method: remove
	0 new (0, 0)
	1 java/lang/UnsupportedOperationException (0, 0)
	3 dup (0, 0)
	4 invokespecial (0, 0)
	5 java/lang/UnsupportedOperationException.<init>:()V (0, 0)
	7 athrow (0, 0)

