Method: binomialCoefficient
	0 iload_0 (0, 0)
	1 iload_1 (0, 0)
	2 invokestatic (0, 0)
	5 iload_0 (1, 1)
	6 iload_1 (1, 1)
	7 if_icmpeq (1, 1)
	10 iload_1 (1, 1)
	11 ifne (1, 1)
	14 lconst_1 (1, 1)
	15 lreturn (1, 1)
	16 iload_1 (1, 1)
	17 iconst_1 (1, 1)
	18 if_icmpeq (1, 1)
	21 iload_1 (1, 1)
	22 iload_0 (1, 1)
	23 iconst_1 (1, 1)
	24 isub (1, 1)
	25 if_icmpne (1, 1)
	28 iload_0 (1, 1)
	29 i2l (1, 1)
	30 lreturn (1, 1)
	31 iload_1 (1, 1)
	32 iload_0 (1, 1)
	33 iconst_2 (1, 1)
	34 idiv (1, 1)
	35 if_icmple (1, 1)
	38 iload_0 (1, 1)
	39 iload_0 (1, 1)
	40 iload_1 (1, 1)
	41 isub (1, 1)
	42 invokestatic (1, 1)
	45 lreturn (1, 1)
	46 lconst_1 (0, 4)
	47 lstore_2 (0, 4)
	48 iload_0 (1, 1)
	49 bipush (1, 1)
	51 if_icmpgt (1, 1)
	54 iload_0 (1, 1)
	55 iload_1 (1, 1)
	56 isub (1, 1)
	57 iconst_1 (1, 1)
	58 iadd (1, 1)
	59 istore (1, 1)
	61 iconst_1 (2, 4)
	62 istore (2, 4)
	64 iload (2, 4)
	66 iload_1 (2, 4)
	67 if_icmpgt (2, 4)
	70 lload_2 (2, 4)
	71 iload (2, 4)
	73 i2l (2, 4)
	74 lmul (2, 4)
	75 iload (2, 4)
	77 i2l (2, 4)
	78 ldiv (2, 4)
	79 lstore_2 (2, 4)
	80 iinc (2, 4)
	83 iinc (2, 4)
	86 goto (2, 4)
	89 goto (1, 1)
	92 iload_0 (1, 1)
	93 bipush (1, 1)
	95 if_icmpgt (1, 1)
	98 iload_0 (1, 1)
	99 iload_1 (1, 1)
	100 isub (1, 1)
	101 iconst_1 (1, 1)
	102 iadd (1, 1)
	103 istore (1, 1)
	105 iconst_1 (2, 4)
	106 istore (2, 4)
	108 iload (2, 4)
	110 iload_1 (2, 4)
	111 if_icmpgt (2, 4)
	114 iload (2, 4)
	116 iload (2, 4)
	118 invokestatic (2, 4)
	121 i2l (2, 4)
	122 lstore (2, 4)
	124 lload_2 (2, 4)
	125 iload (2, 4)
	127 i2l (2, 4)
	128 lload (2, 4)
	130 ldiv (2, 4)
	131 ldiv (2, 4)
	132 iload (2, 4)
	134 i2l (2, 4)
	135 lload (2, 4)
	137 ldiv (2, 4)
	138 lmul (2, 4)
	139 lstore_2 (2, 4)
	140 iinc (2, 4)
	143 iinc (2, 4)
	146 goto (2, 4)
	149 goto (1, 2)
	152 iload_0 (1, 2)
	153 iload_1 (1, 2)
	154 isub (1, 2)
	155 iconst_1 (1, 2)
	156 iadd (1, 2)
	157 istore (1, 2)
	159 iconst_1 (2, 4)
	160 istore (2, 4)
	162 iload (2, 4)
	164 iload_1 (2, 4)
	165 if_icmpgt (2, 4)
	168 iload (2, 4)
	170 iload (2, 4)
	172 invokestatic (2, 4)
	175 i2l (2, 4)
	176 lstore (2, 4)
	178 lload_2 (2, 4)
	179 iload (2, 4)
	181 i2l (2, 4)
	182 lload (2, 4)
	184 ldiv (2, 4)
	185 ldiv (2, 4)
	186 iload (2, 4)
	188 i2l (2, 4)
	189 lload (2, 4)
	191 ldiv (2, 4)
	192 invokestatic (2, 4)
	195 lstore_2 (2, 4)
	196 iinc (2, 4)
	199 iinc (2, 4)
	202 goto (2, 4)
	205 lload_2 (0, 1)
	206 lreturn (0, 1)

Method: binomialCoefficientDouble
	0 iload_0 (0, 0)
	1 iload_1 (0, 0)
	2 invokestatic (0, 0)
	5 iload_0 (1, 1)
	6 iload_1 (1, 1)
	7 if_icmpeq (1, 1)
	10 iload_1 (1, 1)
	11 ifne (1, 1)
	14 dconst_1 (1, 1)
	15 dreturn (1, 1)
	16 iload_1 (1, 1)
	17 iconst_1 (1, 1)
	18 if_icmpeq (1, 1)
	21 iload_1 (1, 1)
	22 iload_0 (1, 1)
	23 iconst_1 (1, 1)
	24 isub (1, 1)
	25 if_icmpne (1, 1)
	28 iload_0 (1, 1)
	29 i2d (1, 1)
	30 dreturn (1, 1)
	31 iload_1 (1, 1)
	32 iload_0 (1, 1)
	33 iconst_2 (1, 1)
	34 idiv (1, 1)
	35 if_icmple (1, 1)
	38 iload_0 (1, 1)
	39 iload_0 (1, 1)
	40 iload_1 (1, 1)
	41 isub (1, 1)
	42 invokestatic (1, 1)
	45 dreturn (1, 1)
	46 iload_0 (1, 1)
	47 bipush (1, 1)
	49 if_icmpge (1, 1)
	52 iload_0 (1, 1)
	53 iload_1 (1, 1)
	54 invokestatic (1, 1)
	57 l2d (1, 1)
	58 dreturn (1, 1)
	59 dconst_1 (0, 0)
	60 dstore_2 (0, 0)
	61 iconst_1 (1, 4)
	62 istore (1, 4)
	64 iload (1, 4)
	66 iload_1 (1, 4)
	67 if_icmpgt (1, 4)
	70 dload_2 (1, 4)
	71 iload_0 (1, 4)
	72 iload_1 (1, 4)
	73 isub (1, 4)
	74 iload (1, 4)
	76 iadd (1, 4)
	77 i2d (1, 4)
	78 iload (1, 4)
	80 i2d (1, 4)
	81 ddiv (1, 4)
	82 dmul (1, 4)
	83 dstore_2 (1, 4)
	84 iinc (1, 4)
	87 goto (1, 4)
	90 dload_2 (0, 0)
	91 ldc2_w (0, 0)
	94 dadd (0, 0)
	95 invokestatic (0, 0)
	98 dreturn (0, 0)

Method: binomialCoefficientLog
	0 iload_0 (0, 0)
	1 iload_1 (0, 0)
	2 invokestatic (0, 0)
	5 iload_0 (1, 1)
	6 iload_1 (1, 1)
	7 if_icmpeq (1, 1)
	10 iload_1 (1, 1)
	11 ifne (1, 1)
	14 dconst_0 (1, 1)
	15 dreturn (1, 1)
	16 iload_1 (1, 1)
	17 iconst_1 (1, 1)
	18 if_icmpeq (1, 1)
	21 iload_1 (1, 1)
	22 iload_0 (1, 1)
	23 iconst_1 (1, 1)
	24 isub (1, 1)
	25 if_icmpne (1, 1)
	28 iload_0 (1, 1)
	29 i2d (1, 1)
	30 invokestatic (1, 1)
	33 dreturn (1, 1)
	34 iload_0 (1, 1)
	35 bipush (1, 1)
	37 if_icmpge (1, 1)
	40 iload_0 (1, 1)
	41 iload_1 (1, 1)
	42 invokestatic (1, 1)
	45 l2d (1, 1)
	46 invokestatic (1, 1)
	49 dreturn (1, 1)
	50 iload_0 (1, 1)
	51 sipush (1, 1)
	54 if_icmpge (1, 1)
	57 iload_0 (1, 1)
	58 iload_1 (1, 1)
	59 invokestatic (1, 1)
	62 invokestatic (1, 1)
	65 dreturn (1, 1)
	66 iload_1 (1, 1)
	67 iload_0 (1, 1)
	68 iconst_2 (1, 1)
	69 idiv (1, 1)
	70 if_icmple (1, 1)
	73 iload_0 (1, 1)
	74 iload_0 (1, 1)
	75 iload_1 (1, 1)
	76 isub (1, 1)
	77 invokestatic (1, 1)
	80 dreturn (1, 1)
	81 dconst_0 (0, 4)
	82 dstore_2 (0, 4)
	83 iload_0 (1, 4)
	84 iload_1 (1, 4)
	85 isub (1, 4)
	86 iconst_1 (1, 4)
	87 iadd (1, 4)
	88 istore (1, 4)
	90 iload (1, 4)
	92 iload_0 (1, 4)
	93 if_icmpgt (1, 4)
	96 dload_2 (1, 4)
	97 iload (1, 4)
	99 i2d (1, 4)
	100 invokestatic (1, 4)
	103 dadd (1, 4)
	104 dstore_2 (1, 4)
	105 iinc (1, 4)
	108 goto (1, 4)
	111 iconst_2 (1, 4)
	112 istore (1, 4)
	114 iload (1, 4)
	116 iload_1 (1, 4)
	117 if_icmpgt (1, 4)
	120 dload_2 (1, 4)
	121 iload (1, 4)
	123 i2d (1, 4)
	124 invokestatic (1, 4)
	127 dsub (1, 4)
	128 dstore_2 (1, 4)
	129 iinc (1, 4)
	132 goto (1, 4)
	135 dload_2 (0, 4)
	136 dreturn (0, 4)

Method: factorial
	0 iload_0 (1, 1)
	1 ifge (1, 1)
	4 new (1, 1)
	7 dup (1, 1)
	8 getstatic (1, 1)
	11 iload_0 (1, 1)
	12 invokestatic (1, 1)
	15 invokespecial (1, 1)
	18 athrow (1, 1)
	19 iload_0 (1, 1)
	20 bipush (1, 1)
	22 if_icmple (1, 1)
	25 new (1, 1)
	28 dup (1, 1)
	29 invokespecial (1, 1)
	32 athrow (1, 1)
	33 getstatic (0, 0)
	36 iload_0 (0, 0)
	37 laload (0, 0)
	38 lreturn (0, 0)

Method: factorialDouble
	0 iload_0 (1, 1)
	1 ifge (1, 1)
	4 new (1, 1)
	7 dup (1, 1)
	8 getstatic (1, 1)
	11 iload_0 (1, 1)
	12 invokestatic (1, 1)
	15 invokespecial (1, 1)
	18 athrow (1, 1)
	19 iload_0 (1, 1)
	20 bipush (1, 1)
	22 if_icmpge (1, 1)
	25 getstatic (1, 1)
	28 iload_0 (1, 1)
	29 laload (1, 1)
	30 l2d (1, 1)
	31 dreturn (1, 1)
	32 iload_0 (0, 0)
	33 invokestatic (0, 0)
	36 invokestatic (0, 0)
	39 ldc2_w (0, 0)
	42 dadd (0, 0)
	43 invokestatic (0, 0)
	46 dreturn (0, 0)

Method: factorialLog
	0 iload_0 (1, 1)
	1 ifge (1, 1)
	4 new (1, 1)
	7 dup (1, 1)
	8 getstatic (1, 1)
	11 iload_0 (1, 1)
	12 invokestatic (1, 1)
	15 invokespecial (1, 1)
	18 athrow (1, 1)
	19 iload_0 (1, 1)
	20 bipush (1, 1)
	22 if_icmpge (1, 1)
	25 getstatic (1, 1)
	28 iload_0 (1, 1)
	29 laload (1, 1)
	30 l2d (1, 1)
	31 invokestatic (1, 1)
	34 dreturn (1, 1)
	35 dconst_0 (0, 0)
	36 dstore_1 (0, 0)
	37 iconst_2 (1, 4)
	38 istore_3 (1, 4)
	39 iload_3 (1, 4)
	40 iload_0 (1, 4)
	41 if_icmpgt (1, 4)
	44 dload_1 (1, 4)
	45 iload_3 (1, 4)
	46 i2d (1, 4)
	47 invokestatic (1, 4)
	50 dadd (1, 4)
	51 dstore_1 (1, 4)
	52 iinc (1, 4)
	55 goto (1, 4)
	58 dload_1 (0, 0)
	59 dreturn (0, 0)

Method: stirlingS2
	0 iload_1 (1, 1)
	1 ifge (1, 1)
	4 new (1, 1)
	7 dup (1, 1)
	8 iload_1 (1, 1)
	9 invokestatic (1, 1)
	12 invokespecial (1, 1)
	15 athrow (1, 1)
	16 iload_1 (1, 1)
	17 iload_0 (1, 1)
	18 if_icmple (1, 1)
	21 new (1, 1)
	24 dup (1, 1)
	25 iload_1 (1, 1)
	26 invokestatic (1, 1)
	29 iload_0 (1, 1)
	30 invokestatic (1, 1)
	33 iconst_1 (1, 1)
	34 invokespecial (1, 1)
	37 athrow (1, 1)
	38 getstatic (0, 0)
	41 invokevirtual (0, 0)
	44 checkcast (0, 0)
	47 astore_2 (0, 0)
	48 aload_2 (1, 1)
	49 ifnonnull (1, 1)
	52 bipush (1, 1)
	54 istore_3 (1, 1)
	55 bipush (1, 1)
	57 anewarray (1, 1)
	60 astore_2 (1, 1)
	61 aload_2 (1, 1)
	62 iconst_0 (1, 1)
	63 iconst_1 (1, 1)
	64 newarray (1, 1)
	66 dup (1, 1)
	67 iconst_0 (1, 1)
	68 lconst_1 (1, 1)
	69 lastore (1, 1)
	70 aastore (1, 1)
	71 iconst_1 (2, 4)
	72 istore (2, 4)
	74 iload (2, 4)
	76 aload_2 (2, 4)
	77 arraylength (2, 4)
	78 if_icmpge (2, 4)
	81 aload_2 (2, 4)
	82 iload (2, 4)
	84 iload (2, 4)
	86 iconst_1 (2, 4)
	87 iadd (2, 4)
	88 newarray (2, 4)
	90 aastore (2, 4)
	91 aload_2 (2, 4)
	92 iload (2, 4)
	94 aaload (2, 4)
	95 iconst_0 (2, 4)
	96 lconst_0 (2, 4)
	97 lastore (2, 4)
	98 aload_2 (2, 4)
	99 iload (2, 4)
	101 aaload (2, 4)
	102 iconst_1 (2, 4)
	103 lconst_1 (2, 4)
	104 lastore (2, 4)
	105 aload_2 (2, 4)
	106 iload (2, 4)
	108 aaload (2, 4)
	109 iload (2, 4)
	111 lconst_1 (2, 4)
	112 lastore (2, 4)
	113 iconst_2 (3, 4)
	114 istore (3, 4)
	116 iload (3, 4)
	118 iload (3, 4)
	120 if_icmpge (3, 4)
	123 aload_2 (3, 4)
	124 iload (3, 4)
	126 aaload (3, 4)
	127 iload (3, 4)
	129 iload (3, 4)
	131 i2l (3, 4)
	132 aload_2 (3, 4)
	133 iload (3, 4)
	135 iconst_1 (3, 4)
	136 isub (3, 4)
	137 aaload (3, 4)
	138 iload (3, 4)
	140 laload (3, 4)
	141 lmul (3, 4)
	142 aload_2 (3, 4)
	143 iload (3, 4)
	145 iconst_1 (3, 4)
	146 isub (3, 4)
	147 aaload (3, 4)
	148 iload (3, 4)
	150 iconst_1 (3, 4)
	151 isub (3, 4)
	152 laload (3, 4)
	153 ladd (3, 4)
	154 lastore (3, 4)
	155 iinc (3, 4)
	158 goto (3, 4)
	161 iinc (3, 4)
	164 goto (3, 4)
	167 getstatic (2, 4)
	170 aconst_null (2, 4)
	171 aload_2 (2, 4)
	172 invokevirtual (2, 4)
	175 pop (2, 4)
	176 iload_0 (2, 1)
	177 aload_2 (2, 1)
	178 arraylength (2, 1)
	179 if_icmpge (2, 1)
	182 aload_2 (2, 1)
	183 iload_0 (2, 1)
	184 aaload (2, 1)
	185 iload_1 (2, 1)
	186 laload (2, 1)
	187 lreturn (2, 1)
	188 iload_1 (3, 1)
	189 ifne (3, 1)
	192 lconst_0 (3, 1)
	193 lreturn (3, 1)
	194 iload_1 (3, 1)
	195 iconst_1 (3, 1)
	196 if_icmpeq (3, 1)
	199 iload_1 (3, 1)
	200 iload_0 (3, 1)
	201 if_icmpne (3, 1)
	204 lconst_1 (3, 1)
	205 lreturn (3, 1)
	206 iload_1 (3, 1)
	207 iconst_2 (3, 1)
	208 if_icmpne (3, 1)
	211 lconst_1 (3, 1)
	212 iload_0 (3, 1)
	213 iconst_1 (3, 1)
	214 isub (3, 1)
	215 lshl (3, 1)
	216 lconst_1 (3, 1)
	217 lsub (3, 1)
	218 lreturn (3, 1)
	219 iload_1 (3, 1)
	220 iload_0 (3, 1)
	221 iconst_1 (3, 1)
	222 isub (3, 1)
	223 if_icmpne (3, 1)
	226 iload_0 (3, 1)
	227 iconst_2 (3, 1)
	228 invokestatic (3, 1)
	231 lreturn (3, 1)
	232 lconst_0 (3, 4)
	233 lstore_3 (3, 4)
	234 iload_1 (3, 4)
	235 iconst_1 (3, 4)
	236 iand (3, 4)
	237 ifne (3, 4)
	240 lconst_1 (3, 4)
	241 goto (3, 4)
	244 ldc2_w (3, 4)
	247 lstore (3, 4)
	249 iconst_1 (4, 4)
	250 istore (4, 4)
	252 iload (4, 4)
	254 iload_1 (4, 4)
	255 if_icmpgt (4, 4)
	258 lload (4, 4)
	260 lneg (4, 4)
	261 lstore (4, 4)
	263 lload_3 (4, 4)
	264 lload (4, 4)
	266 iload_1 (4, 4)
	267 iload (4, 4)
	269 invokestatic (4, 4)
	272 lmul (4, 4)
	273 iload (4, 4)
	275 iload_0 (4, 4)
	276 invokestatic (4, 4)
	279 i2l (4, 4)
	280 lmul (4, 4)
	281 ladd (4, 4)
	282 lstore_3 (4, 4)
	283 lload_3 (5, 1)
	284 lconst_0 (5, 1)
	285 lcmp (5, 1)
	286 ifge (5, 1)
	289 new (5, 1)
	292 dup (5, 1)
	293 getstatic (5, 1)
	296 iconst_3 (5, 1)
	297 anewarray (5, 1)
	300 dup (5, 1)
	301 iconst_0 (5, 1)
	302 iload_0 (5, 1)
	303 invokestatic (5, 1)
	306 aastore (5, 1)
	307 dup (5, 1)
	308 iconst_1 (5, 1)
	309 iconst_0 (5, 1)
	310 invokestatic (5, 1)
	313 aastore (5, 1)
	314 dup (5, 1)
	315 iconst_2 (5, 1)
	316 aload_2 (5, 1)
	317 arraylength (5, 1)
	318 iconst_1 (5, 1)
	319 isub (5, 1)
	320 invokestatic (5, 1)
	323 aastore (5, 1)
	324 invokespecial (5, 1)
	327 athrow (5, 1)
	328 iinc (5, 1)
	331 goto (5, 1)
	334 lload_3 (4, 4)
	335 iload_1 (4, 4)
	336 invokestatic (4, 4)
	339 ldiv (4, 4)
	340 lreturn (4, 4)

Method: combinationsIterator
	0 new (0, 0)
	3 dup (0, 0)
	4 iload_0 (0, 0)
	5 iload_1 (0, 0)
	6 invokespecial (0, 0)
	9 invokevirtual (0, 0)
	12 areturn (0, 0)

Method: checkBinomial
	0 iload_0 (1, 1)
	1 iload_1 (1, 1)
	2 if_icmpge (1, 1)
	5 new (1, 1)
	8 dup (1, 1)
	9 getstatic (1, 1)
	12 iload_1 (1, 1)
	13 invokestatic (1, 1)
	16 iload_0 (1, 1)
	17 invokestatic (1, 1)
	20 iconst_1 (1, 1)
	21 invokespecial (1, 1)
	24 athrow (1, 1)
	25 iload_0 (1, 1)
	26 ifge (1, 1)
	29 new (1, 1)
	32 dup (1, 1)
	33 getstatic (1, 1)
	36 iload_0 (1, 1)
	37 invokestatic (1, 1)
	40 invokespecial (1, 1)
	43 athrow (1, 1)
	44 return (0, 0)

Method: <clinit>
	0 bipush (0, 0)
	2 newarray (0, 0)
	4 dup (0, 0)
	5 iconst_0 (0, 0)
	6 lconst_1 (0, 0)
	7 lastore (0, 0)
	8 dup (0, 0)
	9 iconst_1 (0, 0)
	10 lconst_1 (0, 0)
	11 lastore (0, 0)
	12 dup (0, 0)
	13 iconst_2 (0, 0)
	14 ldc2_w (0, 0)
	17 lastore (0, 0)
	18 dup (0, 0)
	19 iconst_3 (0, 0)
	20 ldc2_w (0, 0)
	23 lastore (0, 0)
	24 dup (0, 0)
	25 iconst_4 (0, 0)
	26 ldc2_w (0, 0)
	29 lastore (0, 0)
	30 dup (0, 0)
	31 iconst_5 (0, 0)
	32 ldc2_w (0, 0)
	35 lastore (0, 0)
	36 dup (0, 0)
	37 bipush (0, 0)
	39 ldc2_w (0, 0)
	42 lastore (0, 0)
	43 dup (0, 0)
	44 bipush (0, 0)
	46 ldc2_w (0, 0)
	49 lastore (0, 0)
	50 dup (0, 0)
	51 bipush (0, 0)
	53 ldc2_w (0, 0)
	56 lastore (0, 0)
	57 dup (0, 0)
	58 bipush (0, 0)
	60 ldc2_w (0, 0)
	63 lastore (0, 0)
	64 dup (0, 0)
	65 bipush (0, 0)
	67 ldc2_w (0, 0)
	70 lastore (0, 0)
	71 dup (0, 0)
	72 bipush (0, 0)
	74 ldc2_w (0, 0)
	77 lastore (0, 0)
	78 dup (0, 0)
	79 bipush (0, 0)
	81 ldc2_w (0, 0)
	84 lastore (0, 0)
	85 dup (0, 0)
	86 bipush (0, 0)
	88 ldc2_w (0, 0)
	91 lastore (0, 0)
	92 dup (0, 0)
	93 bipush (0, 0)
	95 ldc2_w (0, 0)
	98 lastore (0, 0)
	99 dup (0, 0)
	100 bipush (0, 0)
	102 ldc2_w (0, 0)
	105 lastore (0, 0)
	106 dup (0, 0)
	107 bipush (0, 0)
	109 ldc2_w (0, 0)
	112 lastore (0, 0)
	113 dup (0, 0)
	114 bipush (0, 0)
	116 ldc2_w (0, 0)
	119 lastore (0, 0)
	120 dup (0, 0)
	121 bipush (0, 0)
	123 ldc2_w (0, 0)
	126 lastore (0, 0)
	127 dup (0, 0)
	128 bipush (0, 0)
	130 ldc2_w (0, 0)
	133 lastore (0, 0)
	134 dup (0, 0)
	135 bipush (0, 0)
	137 ldc2_w (0, 0)
	140 lastore (0, 0)
	141 putstatic (0, 0)
	144 new (0, 0)
	147 dup (0, 0)
	148 aconst_null (0, 0)
	149 invokespecial (0, 0)
	152 putstatic (0, 0)
	155 return (0, 0)

