Method: <init>
	0 aload_0 (0, 0)
	1 invokespecial (0, 0)
	2 java/lang/Object.<init>:()V (0, 0)
	4 aload_0 (0, 0)
	5 iload_1 (0, 0)
	6 putfield (0, 0)
	7 org/apache/commons/math3/util/Combinations$LexicographicComparator.n:I (0, 0)
	9 aload_0 (0, 0)
	10 iload_2 (0, 0)
	11 putfield (0, 0)
	12 org/apache/commons/math3/util/Combinations$LexicographicComparator.k:I (0, 0)
	14 return (0, 0)

Method: compare
	0 aload_0 (0, 0)
	1 aload_1 (0, 0)
	2 checkcast (0, 0)
	3 [I (0, 0)
	5 aload_2 (0, 0)
	6 checkcast (0, 0)
	7 [I (0, 0)
	9 invokevirtual (0, 0)
	10 org/apache/commons/math3/util/Combinations$LexicographicComparator.compare:([I[I)I (0, 0)
	12 ireturn (0, 0)

Method: lexNorm
	0 lconst_0 (0, 0)
	1 lstore_2 (0, 0)
	2 iconst_0 (1, 4)
	3 istore (1, 4)
	4 #4 (1, 4)
	5 iload (1, 4)
	6 #4 (1, 4)
	7 aload_1 (1, 4)
	8 arraylength (1, 4)
	9 if_icmpge (1, 4)
	10 73 (1, 4)
	12 aload_1 (1, 4)
	13 iload (1, 4)
	14 #4 (1, 4)
	15 iaload (1, 4)
	16 istore (1, 4)
	17 #5 (1, 4)
	18 iload (1, 1)
	19 #5 (1, 1)
	20 iflt (1, 1)
	21 12 (1, 1)
	23 iload (1, 1)
	24 #5 (1, 1)
	25 aload_0 (1, 1)
	26 getfield (1, 1)
	27 org/apache/commons/math3/util/Combinations$LexicographicComparator.n:I (1, 1)
	29 if_icmplt (1, 1)
	30 29 (1, 1)
	32 new (1, 1)
	33 org/apache/commons/math3/exception/OutOfRangeException (1, 1)
	35 dup (1, 1)
	36 iload (1, 1)
	37 #5 (1, 1)
	38 invokestatic (1, 1)
	39 java/lang/Integer.valueOf:(I)Ljava/lang/Integer; (1, 1)
	41 iconst_0 (1, 1)
	42 invokestatic (1, 1)
	43 java/lang/Integer.valueOf:(I)Ljava/lang/Integer; (1, 1)
	45 aload_0 (1, 1)
	46 getfield (1, 1)
	47 org/apache/commons/math3/util/Combinations$LexicographicComparator.n:I (1, 1)
	49 iconst_1 (1, 1)
	50 isub (1, 1)
	51 invokestatic (1, 1)
	52 java/lang/Integer.valueOf:(I)Ljava/lang/Integer; (1, 1)
	54 invokespecial (1, 1)
	55 org/apache/commons/math3/exception/OutOfRangeException.<init>:(Ljava/lang/Number;Ljava/lang/Number;Ljava/lang/Number;)V (1, 1)
	57 athrow (1, 1)
	58 lload_2 (1, 1)
	59 aload_1 (1, 1)
	60 iload (1, 1)
	61 #4 (1, 1)
	62 iaload (1, 1)
	63 aload_0 (1, 1)
	64 getfield (1, 1)
	65 org/apache/commons/math3/util/Combinations$LexicographicComparator.n:I (1, 1)
	67 iload (1, 1)
	68 #4 (1, 1)
	69 invokestatic (1, 1)
	70 org/apache/commons/math3/util/ArithmeticUtils.pow:(II)I (1, 1)
	72 imul (1, 1)
	73 i2l (1, 1)
	74 ladd (1, 1)
	75 lstore_2 (1, 1)
	76 iinc (1, 1)
	77 #4 (1, 1)
	78 -89 (1, 1)
	79 goto (1, 1)
	80 -74 (1, 1)
	82 lload_2 (0, 0)
	83 lreturn (0, 0)

