Method: <clinit>
	0 invokestatic (1, 5)
	1 org/apache/commons/math3/util/Combinations$IterationOrder.values:()[Lorg/apache/commons/math3/util/Combinations$IterationOrder; (1, 5)
	3 arraylength (1, 5)
	4 newarray (1, 5)
	5 10 (1, 5)
	6 putstatic (1, 5)
	7 org/apache/commons/math3/util/Combinations$1.$SwitchMap$org$apache$commons$math3$util$Combinations$IterationOrder:[I (1, 5)
	9 getstatic (1, 5)
	10 org/apache/commons/math3/util/Combinations$1.$SwitchMap$org$apache$commons$math3$util$Combinations$IterationOrder:[I (1, 5)
	12 getstatic (1, 5)
	13 org/apache/commons/math3/util/Combinations$IterationOrder.LEXICOGRAPHIC:Lorg/apache/commons/math3/util/Combinations$IterationOrder; (1, 5)
	15 invokevirtual (1, 5)
	16 org/apache/commons/math3/util/Combinations$IterationOrder.ordinal:()I (1, 5)
	18 iconst_1 (1, 5)
	19 iastore (1, 5)
	20 goto (1, 5)
	21 4 (1, 5)
	23 astore_0 (1, 5)
	24 return (1, 5)

