Method: getDefaultNumberFormat
	0 aload_0 (0, 0)
	1 invokestatic (0, 0)
	2 java/text/NumberFormat.getInstance:(Ljava/util/Locale;)Ljava/text/NumberFormat; (0, 0)
	4 astore_1 (0, 0)
	5 aload_1 (0, 0)
	6 bipush (0, 0)
	7 10 (0, 0)
	8 invokevirtual (0, 0)
	9 java/text/NumberFormat.setMaximumFractionDigits:(I)V (0, 0)
	11 aload_1 (0, 0)
	12 areturn (0, 0)

Method: parseAndIgnoreWhitespace
	0 aload_0 (0, 0)
	1 aload_1 (0, 0)
	2 invokestatic (0, 0)
	3 org/apache/commons/math3/util/CompositeFormat.parseNextCharacter:(Ljava/lang/String;Ljava/text/ParsePosition;)C (0, 0)
	5 pop (0, 0)
	6 aload_1 (0, 0)
	7 aload_1 (0, 0)
	8 invokevirtual (0, 0)
	9 java/text/ParsePosition.getIndex:()I (0, 0)
	11 iconst_1 (0, 0)
	12 isub (0, 0)
	13 invokevirtual (0, 0)
	14 java/text/ParsePosition.setIndex:(I)V (0, 0)
	16 return (0, 0)

Method: parseNextCharacter
	0 aload_1 (0, 0)
	1 invokevirtual (0, 0)
	2 java/text/ParsePosition.getIndex:()I (0, 0)
	4 istore_2 (0, 0)
	5 aload_0 (0, 0)
	6 invokevirtual (0, 0)
	7 java/lang/String.length:()I (0, 0)
	9 istore_3 (0, 0)
	10 iconst_0 (0, 0)
	11 istore (0, 0)
	12 #4 (0, 0)
	13 iload_2 (1, 1)
	14 iload_3 (1, 1)
	15 if_icmpge (1, 1)
	16 40 (1, 1)
	18 aload_0 (1, 1)
	19 iload_2 (1, 1)
	20 iinc (1, 1)
	21 #2 (1, 1)
	22 -74 (1, 1)
	23 invokevirtual (1, 1)
	24 java/lang/String.charAt:(I)C (1, 1)
	26 istore (1, 1)
	27 #5 (1, 1)
	28 iload (1, 3)
	29 #5 (1, 3)
	30 invokestatic (1, 3)
	31 java/lang/Character.isWhitespace:(C)Z (1, 3)
	33 ifeq (1, 3)
	34 8 (1, 3)
	36 iload_2 (1, 3)
	37 iload_3 (1, 3)
	38 if_icmplt (1, 3)
	39 -20 (1, 3)
	41 aload_1 (1, 3)
	42 iload_2 (1, 3)
	43 invokevirtual (1, 3)
	44 java/text/ParsePosition.setIndex:(I)V (1, 3)
	46 iload_2 (2, 1)
	47 iload_3 (2, 1)
	48 if_icmpge (2, 1)
	49 7 (2, 1)
	51 iload (2, 1)
	52 #5 (2, 1)
	53 istore (2, 1)
	54 #4 (2, 1)
	55 iload (0, 0)
	56 #4 (0, 0)
	57 ireturn (0, 0)

Method: parseNumber
	0 aload_2 (0, 0)
	1 invokevirtual (0, 0)
	2 java/text/ParsePosition.getIndex:()I (0, 0)
	4 istore_3 (0, 0)
	5 aload_1 (0, 4)
	6 aload_0 (0, 4)
	7 aload_2 (0, 4)
	8 invokevirtual (0, 4)
	9 java/text/NumberFormat.parse:(Ljava/lang/String;Ljava/text/ParsePosition;)Ljava/lang/Number; (0, 4)
	11 astore (0, 4)
	12 #4 (0, 4)
	13 aload_2 (0, 4)
	14 invokevirtual (0, 4)
	15 java/text/ParsePosition.getIndex:()I (0, 4)
	17 istore (0, 4)
	18 #5 (0, 4)
	19 iload_3 (1, 1)
	20 iload (1, 1)
	21 #5 (1, 1)
	22 if_icmpne (1, 1)
	23 63 (1, 1)
	25 iconst_3 (1, 1)
	26 newarray (1, 1)
	27 7 (1, 1)
	28 dup (1, 1)
	29 iconst_0 (1, 1)
	30 ldc2_w (1, 1)
	31 nan (1, 1)
	33 dastore (1, 1)
	34 dup (1, 1)
	35 iconst_1 (1, 1)
	36 ldc2_w (1, 1)
	37 inf (1, 1)
	39 dastore (1, 1)
	40 dup (1, 1)
	41 iconst_2 (1, 1)
	42 ldc2_w (1, 1)
	43 -inf (1, 1)
	45 dastore (1, 1)
	46 astore (1, 1)
	47 #6 (1, 1)
	48 iconst_0 (2, 4)
	49 istore (2, 4)
	50 #7 (2, 4)
	51 iload (2, 4)
	52 #7 (2, 4)
	53 aload (2, 4)
	54 #6 (2, 4)
	55 arraylength (2, 4)
	56 if_icmpge (2, 4)
	57 29 (2, 4)
	59 aload_0 (2, 4)
	60 aload (2, 4)
	61 #6 (2, 4)
	62 iload (2, 4)
	63 #7 (2, 4)
	64 daload (2, 4)
	65 aload_2 (2, 4)
	66 invokestatic (2, 4)
	67 org/apache/commons/math3/util/CompositeFormat.parseNumber:(Ljava/lang/String;DLjava/text/ParsePosition;)Ljava/lang/Number; (2, 4)
	69 astore (2, 4)
	70 #4 (2, 4)
	71 aload (3, 1)
	72 #4 (3, 1)
	73 ifnull (3, 1)
	74 6 (3, 1)
	76 goto (3, 1)
	77 9 (3, 1)
	79 iinc (3, 1)
	80 #7 (3, 1)
	81 -89 (3, 1)
	82 goto (3, 1)
	83 -31 (3, 1)
	85 aload (1, 1)
	86 #4 (1, 1)
	87 areturn (1, 1)

Method: parseFixedstring
	0 aload_2 (0, 0)
	1 invokevirtual (0, 0)
	2 java/text/ParsePosition.getIndex:()I (0, 0)
	4 istore_3 (0, 0)
	5 iload_3 (0, 0)
	6 aload_1 (0, 0)
	7 invokevirtual (0, 0)
	8 java/lang/String.length:()I (0, 0)
	10 iadd (0, 0)
	11 istore (0, 0)
	12 #4 (0, 0)
	13 iload_3 (0, 1)
	14 aload_0 (0, 1)
	15 invokevirtual (0, 1)
	16 java/lang/String.length:()I (0, 1)
	18 if_icmpge (0, 1)
	19 26 (0, 1)
	21 iload (0, 1)
	22 #4 (0, 1)
	23 aload_0 (0, 1)
	24 invokevirtual (0, 1)
	25 java/lang/String.length:()I (0, 1)
	27 if_icmpgt (0, 1)
	28 17 (0, 1)
	30 aload_0 (0, 1)
	31 iload_3 (0, 1)
	32 iload (0, 1)
	33 #4 (0, 1)
	34 invokevirtual (0, 1)
	35 java/lang/String.substring:(II)Ljava/lang/String; (0, 1)
	37 aload_1 (0, 1)
	38 invokevirtual (0, 1)
	39 java/lang/String.compareTo:(Ljava/lang/String;)I (0, 1)
	41 ifeq (0, 1)
	42 15 (0, 1)
	44 aload_2 (0, 1)
	45 iload_3 (0, 1)
	46 invokevirtual (0, 1)
	47 java/text/ParsePosition.setIndex:(I)V (0, 1)
	49 aload_2 (0, 1)
	50 iload_3 (0, 1)
	51 invokevirtual (0, 1)
	52 java/text/ParsePosition.setErrorIndex:(I)V (0, 1)
	54 iconst_0 (0, 1)
	55 ireturn (0, 1)
	56 aload_2 (0, 1)
	57 iload (0, 1)
	58 #4 (0, 1)
	59 invokevirtual (0, 1)
	60 java/text/ParsePosition.setIndex:(I)V (0, 1)
	62 iconst_1 (0, 1)
	63 ireturn (0, 1)

Method: formatDouble
	0 dload_0 (1, 1)
	1 invokestatic (1, 1)
	2 java/lang/Double.isNaN:(D)Z (1, 1)
	4 ifne (1, 1)
	5 10 (1, 1)
	7 dload_0 (1, 1)
	8 invokestatic (1, 1)
	9 java/lang/Double.isInfinite:(D)Z (1, 1)
	11 ifeq (1, 1)
	12 26 (1, 1)
	14 aload_3 (1, 1)
	15 bipush (1, 1)
	16 40 (1, 1)
	17 invokevirtual (1, 1)
	18 java/lang/StringBuffer.append:(C)Ljava/lang/StringBuffer; (1, 1)
	20 pop (1, 1)
	21 aload_3 (1, 1)
	22 dload_0 (1, 1)
	23 invokevirtual (1, 1)
	24 java/lang/StringBuffer.append:(D)Ljava/lang/StringBuffer; (1, 1)
	26 pop (1, 1)
	27 aload_3 (1, 1)
	28 bipush (1, 1)
	29 41 (1, 1)
	30 invokevirtual (1, 1)
	31 java/lang/StringBuffer.append:(C)Ljava/lang/StringBuffer; (1, 1)
	33 pop (1, 1)
	34 goto (1, 1)
	35 12 (1, 1)
	37 aload_2 (1, 4)
	38 dload_0 (1, 4)
	39 aload_3 (1, 4)
	40 aload (1, 4)
	41 #4 (1, 4)
	42 invokevirtual (1, 4)
	43 java/text/NumberFormat.format:(DLjava/lang/StringBuffer;Ljava/text/FieldPosition;)Ljava/lang/StringBuffer; (1, 4)
	45 pop (1, 4)
	46 aload_3 (0, 0)
	47 areturn (0, 0)

