Method: getDefaultNumberFormat
	0 aload_0 (0, 0)
	1 invokestatic (0, 0)
	4 astore_1 (0, 0)
	5 aload_1 (0, 0)
	6 bipush (0, 0)
	8 invokevirtual (0, 0)
	11 aload_1 (0, 0)
	12 areturn (0, 0)

Method: parseAndIgnoreWhitespace
	0 aload_0 (0, 0)
	1 aload_1 (0, 0)
	2 invokestatic (0, 0)
	5 pop (0, 0)
	6 aload_1 (0, 0)
	7 aload_1 (0, 0)
	8 invokevirtual (0, 0)
	11 iconst_1 (0, 0)
	12 isub (0, 0)
	13 invokevirtual (0, 0)
	16 return (0, 0)

Method: parseNextCharacter
	0 aload_1 (0, 0)
	1 invokevirtual (0, 0)
	4 istore_2 (0, 0)
	5 aload_0 (0, 0)
	6 invokevirtual (0, 0)
	9 istore_3 (0, 0)
	10 iconst_0 (0, 0)
	11 istore (0, 0)
	13 iload_2 (1, 1)
	14 iload_3 (1, 1)
	15 if_icmpge (1, 1)
	18 aload_0 (2, 1)
	19 iload_2 (2, 1)
	20 iinc (2, 1)
	23 invokevirtual (2, 1)
	26 istore (2, 1)
	28 iload (1, 1)
	30 invokestatic (1, 1)
	33 ifeq (1, 1)
	36 iload_2 (1, 1)
	37 iload_3 (1, 1)
	38 if_icmplt (1, 1)
	41 aload_1 (1, 1)
	42 iload_2 (1, 1)
	43 invokevirtual (1, 1)
	46 iload_2 (2, 1)
	47 iload_3 (2, 1)
	48 if_icmpge (2, 1)
	51 iload (2, 1)
	53 istore (2, 1)
	55 iload (0, 0)
	57 ireturn (0, 0)

Method: parseNumber
	0 aload_2 (0, 0)
	1 invokevirtual (0, 0)
	4 istore_3 (0, 0)
	5 aload_1 (0, 4)
	6 aload_0 (0, 4)
	7 aload_2 (0, 4)
	8 invokevirtual (0, 4)
	11 astore (0, 4)
	13 aload_2 (0, 4)
	14 invokevirtual (0, 4)
	17 istore (0, 4)
	19 iload_3 (1, 1)
	20 iload (1, 1)
	22 if_icmpne (1, 1)
	25 iconst_3 (2, 1)
	26 newarray (2, 1)
	28 dup (2, 1)
	29 iconst_0 (2, 1)
	30 ldc2_w (2, 1)
	33 dastore (2, 1)
	34 dup (2, 1)
	35 iconst_1 (2, 1)
	36 ldc2_w (2, 1)
	39 dastore (2, 1)
	40 dup (2, 1)
	41 iconst_2 (2, 1)
	42 ldc2_w (2, 1)
	45 dastore (2, 1)
	46 astore (2, 1)
	48 iconst_0 (2, 4)
	49 istore (2, 4)
	51 iload (2, 4)
	53 aload (2, 4)
	55 arraylength (2, 4)
	56 if_icmpge (2, 4)
	59 aload_0 (2, 4)
	60 aload (2, 4)
	62 iload (2, 4)
	64 daload (2, 4)
	65 aload_2 (2, 4)
	66 invokestatic (2, 4)
	69 astore (2, 4)
	71 aload (3, 1)
	73 ifnull (3, 1)
	76 goto (3, 1)
	79 iinc (3, 1)
	82 goto (3, 1)
	85 aload (1, 4)
	87 areturn (1, 4)

Method: parseFixedstring
	0 aload_2 (0, 0)
	1 invokevirtual (0, 0)
	4 istore_3 (0, 0)
	5 iload_3 (0, 0)
	6 aload_1 (0, 0)
	7 invokevirtual (0, 0)
	10 iadd (0, 0)
	11 istore (0, 0)
	13 iload_3 (0, 1)
	14 aload_0 (0, 1)
	15 invokevirtual (0, 1)
	18 if_icmpge (0, 1)
	21 iload (0, 1)
	23 aload_0 (0, 1)
	24 invokevirtual (0, 1)
	27 if_icmpgt (0, 1)
	30 aload_0 (0, 1)
	31 iload_3 (0, 1)
	32 iload (0, 1)
	34 invokevirtual (1, 1)
	37 aload_1 (1, 1)
	38 invokevirtual (1, 1)
	41 ifeq (1, 1)
	44 aload_2 (1, 1)
	45 iload_3 (1, 1)
	46 invokevirtual (1, 1)
	49 aload_2 (1, 1)
	50 iload_3 (1, 1)
	51 invokevirtual (1, 1)
	54 iconst_0 (1, 1)
	55 ireturn (1, 1)
	56 aload_2 (0, 0)
	57 iload (0, 0)
	59 invokevirtual (0, 0)
	62 iconst_1 (0, 0)
	63 ireturn (0, 0)

Method: formatDouble
	0 dload_0 (1, 1)
	1 invokestatic (1, 1)
	4 ifne (1, 1)
	7 dload_0 (1, 1)
	8 invokestatic (1, 1)
	11 ifeq (1, 1)
	14 aload_3 (1, 1)
	15 bipush (1, 1)
	17 invokevirtual (1, 1)
	20 pop (1, 1)
	21 aload_3 (1, 1)
	22 dload_0 (1, 1)
	23 invokevirtual (1, 1)
	26 pop (1, 1)
	27 aload_3 (1, 1)
	28 bipush (1, 1)
	30 invokevirtual (1, 1)
	33 pop (1, 1)
	34 goto (1, 1)
	37 aload_2 (1, 4)
	38 dload_0 (1, 4)
	39 aload_3 (1, 4)
	40 aload (1, 4)
	42 invokevirtual (1, 4)
	45 pop (1, 4)
	46 aload_3 (0, 2)
	47 areturn (0, 2)

