Method: <init>
	0 aload_0 (0, 0)
	1 invokespecial (0, 0)
	2 java/lang/Object.<init>:()V (0, 0)
	4 return (0, 0)

Method: evaluate
	0 ldc2_w (0, 0)
	1 1e-50 (0, 0)
	3 dstore (0, 0)
	4 #6 (0, 0)
	5 aload_0 (0, 0)
	6 iconst_0 (0, 0)
	7 dload_1 (0, 0)
	8 invokevirtual (0, 0)
	9 org/apache/commons/math3/util/ContinuedFraction.getA:(ID)D (0, 0)
	11 dstore (0, 0)
	12 #8 (0, 0)
	13 dload (2, 1)
	14 #8 (2, 1)
	15 dconst_0 (2, 1)
	16 ldc2_w (2, 1)
	17 1e-50 (2, 1)
	19 invokestatic (2, 1)
	20 org/apache/commons/math3/util/Precision.equals:(DDD)Z (2, 1)
	22 ifeq (2, 1)
	23 8 (2, 1)
	25 ldc2_w (2, 1)
	26 1e-50 (2, 1)
	28 dstore (2, 1)
	29 #8 (2, 1)
	30 iconst_1 (1, 4)
	31 istore (1, 4)
	32 #10 (1, 4)
	33 dconst_0 (1, 4)
	34 dstore (1, 4)
	35 #11 (1, 4)
	36 dload (1, 4)
	37 #8 (1, 4)
	38 dstore (1, 4)
	39 #13 (1, 4)
	40 dload (1, 4)
	41 #8 (1, 4)
	42 dstore (1, 4)
	43 #15 (1, 4)
	44 iload (2, 3)
	45 #10 (2, 3)
	46 iload (2, 3)
	47 #5 (2, 3)
	48 if_icmpge (2, 3)
	49 188 (2, 3)
	51 aload_0 (2, 3)
	52 iload (2, 3)
	53 #10 (2, 3)
	54 dload_1 (2, 3)
	55 invokevirtual (2, 3)
	56 org/apache/commons/math3/util/ContinuedFraction.getA:(ID)D (2, 3)
	58 dstore (2, 3)
	59 #17 (2, 3)
	60 aload_0 (2, 3)
	61 iload (2, 3)
	62 #10 (2, 3)
	63 dload_1 (2, 3)
	64 invokevirtual (2, 3)
	65 org/apache/commons/math3/util/ContinuedFraction.getB:(ID)D (2, 3)
	67 dstore (2, 3)
	68 #19 (2, 3)
	69 dload (2, 3)
	70 #17 (2, 3)
	71 dload (2, 3)
	72 #19 (2, 3)
	73 dload (2, 3)
	74 #11 (2, 3)
	75 dmul (2, 3)
	76 dadd (2, 3)
	77 dstore (2, 3)
	78 #21 (2, 3)
	79 dload (3, 1)
	80 #21 (3, 1)
	81 dconst_0 (3, 1)
	82 ldc2_w (3, 1)
	83 1e-50 (3, 1)
	85 invokestatic (3, 1)
	86 org/apache/commons/math3/util/Precision.equals:(DDD)Z (3, 1)
	88 ifeq (3, 1)
	89 8 (3, 1)
	91 ldc2_w (3, 1)
	92 1e-50 (3, 1)
	94 dstore (3, 1)
	95 #21 (3, 1)
	96 dload (2, 3)
	97 #17 (2, 3)
	98 dload (2, 3)
	99 #19 (2, 3)
	100 dload (2, 3)
	101 #13 (2, 3)
	102 ddiv (2, 3)
	103 dadd (2, 3)
	104 dstore (2, 3)
	105 #23 (2, 3)
	106 dload (3, 1)
	107 #23 (3, 1)
	108 dconst_0 (3, 1)
	109 ldc2_w (3, 1)
	110 1e-50 (3, 1)
	112 invokestatic (3, 1)
	113 org/apache/commons/math3/util/Precision.equals:(DDD)Z (3, 1)
	115 ifeq (3, 1)
	116 8 (3, 1)
	118 ldc2_w (3, 1)
	119 1e-50 (3, 1)
	121 dstore (3, 1)
	122 #23 (3, 1)
	123 dconst_1 (2, 3)
	124 dload (2, 3)
	125 #21 (2, 3)
	126 ddiv (2, 3)
	127 dstore (2, 3)
	128 #21 (2, 3)
	129 dload (2, 3)
	130 #23 (2, 3)
	131 dload (2, 3)
	132 #21 (2, 3)
	133 dmul (2, 3)
	134 dstore (2, 3)
	135 #25 (2, 3)
	136 dload (2, 3)
	137 #8 (2, 3)
	138 dload (2, 3)
	139 #25 (2, 3)
	140 dmul (2, 3)
	141 dstore (2, 3)
	142 #15 (2, 3)
	143 dload (3, 1)
	144 #15 (3, 1)
	145 invokestatic (3, 1)
	146 java/lang/Double.isInfinite:(D)Z (3, 1)
	148 ifeq (3, 1)
	149 25 (3, 1)
	151 new (3, 1)
	152 org/apache/commons/math3/exception/ConvergenceException (3, 1)
	154 dup (3, 1)
	155 getstatic (3, 1)
	156 org/apache/commons/math3/exception/util/LocalizedFormats.CONTINUED_FRACTION_INFINITY_DIVERGENCE:Lorg/apache/commons/math3/exception/util/LocalizedFormats; (3, 1)
	158 iconst_1 (3, 1)
	159 anewarray (3, 1)
	160 java/lang/Object (3, 1)
	162 dup (3, 1)
	163 iconst_0 (3, 1)
	164 dload_1 (3, 1)
	165 invokestatic (3, 1)
	166 java/lang/Double.valueOf:(D)Ljava/lang/Double; (3, 1)
	168 aastore (3, 1)
	169 invokespecial (3, 1)
	170 org/apache/commons/math3/exception/ConvergenceException.<init>:(Lorg/apache/commons/math3/exception/util/Localizable;[Ljava/lang/Object;)V (3, 1)
	172 athrow (3, 1)
	173 dload (3, 1)
	174 #15 (3, 1)
	175 invokestatic (3, 1)
	176 java/lang/Double.isNaN:(D)Z (3, 1)
	178 ifeq (3, 1)
	179 25 (3, 1)
	181 new (3, 1)
	182 org/apache/commons/math3/exception/ConvergenceException (3, 1)
	184 dup (3, 1)
	185 getstatic (3, 1)
	186 org/apache/commons/math3/exception/util/LocalizedFormats.CONTINUED_FRACTION_NAN_DIVERGENCE:Lorg/apache/commons/math3/exception/util/LocalizedFormats; (3, 1)
	188 iconst_1 (3, 1)
	189 anewarray (3, 1)
	190 java/lang/Object (3, 1)
	192 dup (3, 1)
	193 iconst_0 (3, 1)
	194 dload_1 (3, 1)
	195 invokestatic (3, 1)
	196 java/lang/Double.valueOf:(D)Ljava/lang/Double; (3, 1)
	198 aastore (3, 1)
	199 invokespecial (3, 1)
	200 org/apache/commons/math3/exception/ConvergenceException.<init>:(Lorg/apache/commons/math3/exception/util/Localizable;[Ljava/lang/Object;)V (3, 1)
	202 athrow (3, 1)
	203 dload (3, 1)
	204 #25 (3, 1)
	205 dconst_1 (3, 1)
	206 dsub (3, 1)
	207 invokestatic (3, 1)
	208 org/apache/commons/math3/util/FastMath.abs:(D)D (3, 1)
	210 dload_3 (3, 1)
	211 dcmpg (3, 1)
	212 ifge (3, 1)
	213 6 (3, 1)
	215 goto (3, 1)
	216 21 (3, 1)
	218 dload (2, 3)
	219 #21 (2, 3)
	220 dstore (2, 3)
	221 #11 (2, 3)
	222 dload (2, 3)
	223 #23 (2, 3)
	224 dstore (2, 3)
	225 #13 (2, 3)
	226 dload (2, 3)
	227 #15 (2, 3)
	228 dstore (2, 3)
	229 #8 (2, 3)
	230 iinc (2, 3)
	231 #10 (2, 3)
	232 -89 (2, 3)
	233 goto (1, 4)
	234 -189 (1, 4)
	236 iload (2, 1)
	237 #10 (2, 1)
	238 iload (2, 1)
	239 #5 (2, 1)
	240 if_icmplt (2, 1)
	241 30 (2, 1)
	243 new (2, 1)
	244 org/apache/commons/math3/exception/MaxCountExceededException (2, 1)
	246 dup (2, 1)
	247 getstatic (2, 1)
	248 org/apache/commons/math3/exception/util/LocalizedFormats.NON_CONVERGENT_CONTINUED_FRACTION:Lorg/apache/commons/math3/exception/util/LocalizedFormats; (2, 1)
	250 iload (2, 1)
	251 #5 (2, 1)
	252 invokestatic (2, 1)
	253 java/lang/Integer.valueOf:(I)Ljava/lang/Integer; (2, 1)
	255 iconst_1 (2, 1)
	256 anewarray (2, 1)
	257 java/lang/Object (2, 1)
	259 dup (2, 1)
	260 iconst_0 (2, 1)
	261 dload_1 (2, 1)
	262 invokestatic (2, 1)
	263 java/lang/Double.valueOf:(D)Ljava/lang/Double; (2, 1)
	265 aastore (2, 1)
	266 invokespecial (2, 1)
	267 org/apache/commons/math3/exception/MaxCountExceededException.<init>:(Lorg/apache/commons/math3/exception/util/Localizable;Ljava/lang/Number;[Ljava/lang/Object;)V (2, 1)
	269 athrow (2, 1)
	270 dload (1, 4)
	271 #15 (1, 4)
	272 dreturn (0, 4)

