Method: <init>
	0 aload_0 (0, 0)
	1 invokespecial (0, 0)
	2 java/lang/Number.<init>:()V (0, 0)
	4 aload_0 (0, 0)
	5 dload_1 (0, 0)
	6 putfield (0, 0)
	7 org/apache/commons/math3/util/Decimal64.value:D (0, 0)
	9 return (0, 0)

Method: getField
	0 invokestatic (0, 0)
	1 org/apache/commons/math3/util/Decimal64Field.getInstance:()Lorg/apache/commons/math3/util/Decimal64Field; (0, 0)
	3 areturn (0, 0)

Method: add
	0 aload_0 (0, 0)
	1 aload_1 (0, 0)
	2 checkcast (0, 0)
	3 org/apache/commons/math3/util/Decimal64 (0, 0)
	5 invokevirtual (0, 0)
	6 org/apache/commons/math3/util/Decimal64.add:(Lorg/apache/commons/math3/util/Decimal64;)Lorg/apache/commons/math3/util/Decimal64; (0, 0)
	8 areturn (0, 0)

Method: subtract
	0 aload_0 (0, 0)
	1 aload_1 (0, 0)
	2 checkcast (0, 0)
	3 org/apache/commons/math3/util/Decimal64 (0, 0)
	5 invokevirtual (0, 0)
	6 org/apache/commons/math3/util/Decimal64.subtract:(Lorg/apache/commons/math3/util/Decimal64;)Lorg/apache/commons/math3/util/Decimal64; (0, 0)
	8 areturn (0, 0)

Method: negate
	0 aload_0 (0, 0)
	1 invokevirtual (0, 0)
	2 org/apache/commons/math3/util/Decimal64.negate:()Lorg/apache/commons/math3/util/Decimal64; (0, 0)
	4 areturn (0, 0)

Method: multiply
	0 aload_0 (0, 0)
	1 iload_1 (0, 0)
	2 invokevirtual (0, 0)
	3 org/apache/commons/math3/util/Decimal64.multiply:(I)Lorg/apache/commons/math3/util/Decimal64; (0, 0)
	5 areturn (0, 0)

Method: divide
	0 aload_0 (0, 0)
	1 aload_1 (0, 0)
	2 checkcast (0, 0)
	3 org/apache/commons/math3/util/Decimal64 (0, 0)
	5 invokevirtual (0, 0)
	6 org/apache/commons/math3/util/Decimal64.divide:(Lorg/apache/commons/math3/util/Decimal64;)Lorg/apache/commons/math3/util/Decimal64; (0, 0)
	8 areturn (0, 0)

Method: reciprocal
	0 aload_0 (0, 0)
	1 invokevirtual (0, 0)
	2 org/apache/commons/math3/util/Decimal64.reciprocal:()Lorg/apache/commons/math3/util/Decimal64; (0, 0)
	4 areturn (0, 0)

Method: byteValue
	0 aload_0 (0, 0)
	1 getfield (0, 0)
	2 org/apache/commons/math3/util/Decimal64.value:D (0, 0)
	4 d2i (0, 0)
	5 i2b (0, 0)
	6 ireturn (0, 0)

Method: shortValue
	0 aload_0 (0, 0)
	1 getfield (0, 0)
	2 org/apache/commons/math3/util/Decimal64.value:D (0, 0)
	4 d2i (0, 0)
	5 i2s (0, 0)
	6 ireturn (0, 0)

Method: intValue
	0 aload_0 (0, 0)
	1 getfield (0, 0)
	2 org/apache/commons/math3/util/Decimal64.value:D (0, 0)
	4 d2i (0, 0)
	5 ireturn (0, 0)

Method: longValue
	0 aload_0 (0, 0)
	1 getfield (0, 0)
	2 org/apache/commons/math3/util/Decimal64.value:D (0, 0)
	4 d2l (0, 0)
	5 lreturn (0, 0)

Method: floatValue
	0 aload_0 (0, 0)
	1 getfield (0, 0)
	2 org/apache/commons/math3/util/Decimal64.value:D (0, 0)
	4 d2f (0, 0)
	5 freturn (0, 0)

Method: doubleValue
	0 aload_0 (0, 0)
	1 getfield (0, 0)
	2 org/apache/commons/math3/util/Decimal64.value:D (0, 0)
	4 dreturn (0, 0)

Method: compareTo
	0 aload_0 (0, 0)
	1 aload_1 (0, 0)
	2 checkcast (0, 0)
	3 org/apache/commons/math3/util/Decimal64 (0, 0)
	5 invokevirtual (0, 0)
	6 org/apache/commons/math3/util/Decimal64.compareTo:(Lorg/apache/commons/math3/util/Decimal64;)I (0, 0)
	8 ireturn (0, 0)

Method: equals
	0 aload_1 (1, 1)
	1 instanceof (1, 1)
	2 org/apache/commons/math3/util/Decimal64 (1, 1)
	4 ifeq (1, 1)
	5 32 (1, 1)
	7 aload_1 (1, 1)
	8 checkcast (1, 1)
	9 org/apache/commons/math3/util/Decimal64 (1, 1)
	11 astore_2 (1, 1)
	12 aload_0 (1, 1)
	13 getfield (1, 1)
	14 org/apache/commons/math3/util/Decimal64.value:D (1, 1)
	16 invokestatic (1, 1)
	17 java/lang/Double.doubleToLongBits:(D)J (1, 1)
	19 aload_2 (1, 1)
	20 getfield (1, 1)
	21 org/apache/commons/math3/util/Decimal64.value:D (1, 1)
	23 invokestatic (1, 1)
	24 java/lang/Double.doubleToLongBits:(D)J (1, 1)
	26 lcmp (1, 1)
	27 ifne (1, 1)
	28 7 (1, 1)
	30 iconst_1 (1, 1)
	31 goto (1, 1)
	32 4 (1, 1)
	34 iconst_0 (1, 1)
	35 ireturn (1, 1)
	36 iconst_0 (0, 0)
	37 ireturn (0, 0)

Method: hashCode
	0 aload_0 (0, 0)
	1 getfield (0, 0)
	2 org/apache/commons/math3/util/Decimal64.value:D (0, 0)
	4 invokestatic (0, 0)
	5 java/lang/Double.doubleToLongBits:(D)J (0, 0)
	7 lstore_1 (0, 0)
	8 lload_1 (0, 0)
	9 lload_1 (0, 0)
	10 bipush (0, 0)
	11 32 (0, 0)
	12 lushr (0, 0)
	13 lxor (0, 0)
	14 l2i (0, 0)
	15 ireturn (0, 0)

Method: toString
	0 aload_0 (0, 0)
	1 getfield (0, 0)
	2 org/apache/commons/math3/util/Decimal64.value:D (0, 0)
	4 invokestatic (0, 0)
	5 java/lang/Double.toString:(D)Ljava/lang/String; (0, 0)
	7 areturn (0, 0)

Method: isInfinite
	0 aload_0 (0, 0)
	1 getfield (0, 0)
	2 org/apache/commons/math3/util/Decimal64.value:D (0, 0)
	4 invokestatic (0, 0)
	5 java/lang/Double.isInfinite:(D)Z (0, 0)
	7 ireturn (0, 0)

Method: isNaN
	0 aload_0 (0, 0)
	1 getfield (0, 0)
	2 org/apache/commons/math3/util/Decimal64.value:D (0, 0)
	4 invokestatic (0, 0)
	5 java/lang/Double.isNaN:(D)Z (0, 0)
	7 ireturn (0, 0)

Method: getReal
	0 aload_0 (0, 0)
	1 getfield (0, 0)
	2 org/apache/commons/math3/util/Decimal64.value:D (0, 0)
	4 dreturn (0, 0)

Method: remainder
	0 aload_0 (0, 0)
	1 dload_1 (0, 0)
	2 invokevirtual (0, 0)
	3 org/apache/commons/math3/util/Decimal64.remainder:(D)Lorg/apache/commons/math3/util/Decimal64; (0, 0)
	5 areturn (0, 0)

Method: abs
	0 aload_0 (0, 0)
	1 invokevirtual (0, 0)
	2 org/apache/commons/math3/util/Decimal64.abs:()Lorg/apache/commons/math3/util/Decimal64; (0, 0)
	4 areturn (0, 0)

Method: ceil
	0 aload_0 (0, 0)
	1 invokevirtual (0, 0)
	2 org/apache/commons/math3/util/Decimal64.ceil:()Lorg/apache/commons/math3/util/Decimal64; (0, 0)
	4 areturn (0, 0)

Method: floor
	0 aload_0 (0, 0)
	1 invokevirtual (0, 0)
	2 org/apache/commons/math3/util/Decimal64.floor:()Lorg/apache/commons/math3/util/Decimal64; (0, 0)
	4 areturn (0, 0)

Method: rint
	0 aload_0 (0, 0)
	1 invokevirtual (0, 0)
	2 org/apache/commons/math3/util/Decimal64.rint:()Lorg/apache/commons/math3/util/Decimal64; (0, 0)
	4 areturn (0, 0)

Method: round
	0 aload_0 (0, 0)
	1 getfield (0, 0)
	2 org/apache/commons/math3/util/Decimal64.value:D (0, 0)
	4 invokestatic (0, 0)
	5 org/apache/commons/math3/util/FastMath.round:(D)J (0, 0)
	7 lreturn (0, 0)

Method: signum
	0 aload_0 (0, 0)
	1 invokevirtual (0, 0)
	2 org/apache/commons/math3/util/Decimal64.signum:()Lorg/apache/commons/math3/util/Decimal64; (0, 0)
	4 areturn (0, 0)

Method: copySign
	0 aload_0 (0, 0)
	1 aload_1 (0, 0)
	2 checkcast (0, 0)
	3 org/apache/commons/math3/util/Decimal64 (0, 0)
	5 invokevirtual (0, 0)
	6 org/apache/commons/math3/util/Decimal64.copySign:(Lorg/apache/commons/math3/util/Decimal64;)Lorg/apache/commons/math3/util/Decimal64; (0, 0)
	8 areturn (0, 0)

Method: scalb
	0 aload_0 (0, 0)
	1 iload_1 (0, 0)
	2 invokevirtual (0, 0)
	3 org/apache/commons/math3/util/Decimal64.scalb:(I)Lorg/apache/commons/math3/util/Decimal64; (0, 0)
	5 areturn (0, 0)

Method: hypot
	0 aload_0 (0, 0)
	1 aload_1 (0, 0)
	2 checkcast (0, 0)
	3 org/apache/commons/math3/util/Decimal64 (0, 0)
	5 invokevirtual (0, 0)
	6 org/apache/commons/math3/util/Decimal64.hypot:(Lorg/apache/commons/math3/util/Decimal64;)Lorg/apache/commons/math3/util/Decimal64; (0, 0)
	8 areturn (0, 0)

Method: sqrt
	0 aload_0 (0, 0)
	1 invokevirtual (0, 0)
	2 org/apache/commons/math3/util/Decimal64.sqrt:()Lorg/apache/commons/math3/util/Decimal64; (0, 0)
	4 areturn (0, 0)

Method: cbrt
	0 aload_0 (0, 0)
	1 invokevirtual (0, 0)
	2 org/apache/commons/math3/util/Decimal64.cbrt:()Lorg/apache/commons/math3/util/Decimal64; (0, 0)
	4 areturn (0, 0)

Method: rootN
	0 aload_0 (0, 0)
	1 iload_1 (0, 0)
	2 invokevirtual (0, 0)
	3 org/apache/commons/math3/util/Decimal64.rootN:(I)Lorg/apache/commons/math3/util/Decimal64; (0, 0)
	5 areturn (0, 0)

Method: pow
	0 aload_0 (0, 0)
	1 dload_1 (0, 0)
	2 invokevirtual (0, 0)
	3 org/apache/commons/math3/util/Decimal64.pow:(D)Lorg/apache/commons/math3/util/Decimal64; (0, 0)
	5 areturn (0, 0)

Method: exp
	0 aload_0 (0, 0)
	1 invokevirtual (0, 0)
	2 org/apache/commons/math3/util/Decimal64.exp:()Lorg/apache/commons/math3/util/Decimal64; (0, 0)
	4 areturn (0, 0)

Method: expm1
	0 aload_0 (0, 0)
	1 invokevirtual (0, 0)
	2 org/apache/commons/math3/util/Decimal64.expm1:()Lorg/apache/commons/math3/util/Decimal64; (0, 0)
	4 areturn (0, 0)

Method: log
	0 aload_0 (0, 0)
	1 invokevirtual (0, 0)
	2 org/apache/commons/math3/util/Decimal64.log:()Lorg/apache/commons/math3/util/Decimal64; (0, 0)
	4 areturn (0, 0)

Method: log1p
	0 aload_0 (0, 0)
	1 invokevirtual (0, 0)
	2 org/apache/commons/math3/util/Decimal64.log1p:()Lorg/apache/commons/math3/util/Decimal64; (0, 0)
	4 areturn (0, 0)

Method: log10
	0 new (0, 0)
	1 org/apache/commons/math3/util/Decimal64 (0, 0)
	3 dup (0, 0)
	4 aload_0 (0, 0)
	5 getfield (0, 0)
	6 org/apache/commons/math3/util/Decimal64.value:D (0, 0)
	8 invokestatic (0, 0)
	9 org/apache/commons/math3/util/FastMath.log10:(D)D (0, 0)
	11 invokespecial (0, 0)
	12 org/apache/commons/math3/util/Decimal64.<init>:(D)V (0, 0)
	14 areturn (0, 0)

Method: cos
	0 aload_0 (0, 0)
	1 invokevirtual (0, 0)
	2 org/apache/commons/math3/util/Decimal64.cos:()Lorg/apache/commons/math3/util/Decimal64; (0, 0)
	4 areturn (0, 0)

Method: sin
	0 aload_0 (0, 0)
	1 invokevirtual (0, 0)
	2 org/apache/commons/math3/util/Decimal64.sin:()Lorg/apache/commons/math3/util/Decimal64; (0, 0)
	4 areturn (0, 0)

Method: tan
	0 aload_0 (0, 0)
	1 invokevirtual (0, 0)
	2 org/apache/commons/math3/util/Decimal64.tan:()Lorg/apache/commons/math3/util/Decimal64; (0, 0)
	4 areturn (0, 0)

Method: acos
	0 aload_0 (0, 0)
	1 invokevirtual (0, 0)
	2 org/apache/commons/math3/util/Decimal64.acos:()Lorg/apache/commons/math3/util/Decimal64; (0, 0)
	4 areturn (0, 0)

Method: asin
	0 aload_0 (0, 0)
	1 invokevirtual (0, 0)
	2 org/apache/commons/math3/util/Decimal64.asin:()Lorg/apache/commons/math3/util/Decimal64; (0, 0)
	4 areturn (0, 0)

Method: atan
	0 aload_0 (0, 0)
	1 invokevirtual (0, 0)
	2 org/apache/commons/math3/util/Decimal64.atan:()Lorg/apache/commons/math3/util/Decimal64; (0, 0)
	4 areturn (0, 0)

Method: atan2
	0 aload_0 (0, 0)
	1 aload_1 (0, 0)
	2 checkcast (0, 0)
	3 org/apache/commons/math3/util/Decimal64 (0, 0)
	5 invokevirtual (0, 0)
	6 org/apache/commons/math3/util/Decimal64.atan2:(Lorg/apache/commons/math3/util/Decimal64;)Lorg/apache/commons/math3/util/Decimal64; (0, 0)
	8 areturn (0, 0)

Method: cosh
	0 aload_0 (0, 0)
	1 invokevirtual (0, 0)
	2 org/apache/commons/math3/util/Decimal64.cosh:()Lorg/apache/commons/math3/util/Decimal64; (0, 0)
	4 areturn (0, 0)

Method: sinh
	0 aload_0 (0, 0)
	1 invokevirtual (0, 0)
	2 org/apache/commons/math3/util/Decimal64.sinh:()Lorg/apache/commons/math3/util/Decimal64; (0, 0)
	4 areturn (0, 0)

Method: tanh
	0 aload_0 (0, 0)
	1 invokevirtual (0, 0)
	2 org/apache/commons/math3/util/Decimal64.tanh:()Lorg/apache/commons/math3/util/Decimal64; (0, 0)
	4 areturn (0, 0)

Method: acosh
	0 aload_0 (0, 0)
	1 invokevirtual (0, 0)
	2 org/apache/commons/math3/util/Decimal64.acosh:()Lorg/apache/commons/math3/util/Decimal64; (0, 0)
	4 areturn (0, 0)

Method: asinh
	0 aload_0 (0, 0)
	1 invokevirtual (0, 0)
	2 org/apache/commons/math3/util/Decimal64.asinh:()Lorg/apache/commons/math3/util/Decimal64; (0, 0)
	4 areturn (0, 0)

Method: atanh
	0 aload_0 (0, 0)
	1 invokevirtual (0, 0)
	2 org/apache/commons/math3/util/Decimal64.atanh:()Lorg/apache/commons/math3/util/Decimal64; (0, 0)
	4 areturn (0, 0)

Method: linearCombination
	0 aload_0 (0, 0)
	1 aload_1 (0, 0)
	2 checkcast (0, 0)
	3 [Lorg/apache/commons/math3/util/Decimal64; (0, 0)
	5 aload_2 (0, 0)
	6 checkcast (0, 0)
	7 [Lorg/apache/commons/math3/util/Decimal64; (0, 0)
	9 invokevirtual (0, 0)
	10 org/apache/commons/math3/util/Decimal64.linearCombination:([Lorg/apache/commons/math3/util/Decimal64;[Lorg/apache/commons/math3/util/Decimal64;)Lorg/apache/commons/math3/util/Decimal64; (0, 0)
	12 areturn (0, 0)

Method: <clinit>
	0 new (0, 0)
	1 org/apache/commons/math3/util/Decimal64 (0, 0)
	3 dup (0, 0)
	4 dconst_0 (0, 0)
	5 invokespecial (0, 0)
	6 org/apache/commons/math3/util/Decimal64.<init>:(D)V (0, 0)
	8 putstatic (0, 0)
	9 org/apache/commons/math3/util/Decimal64.ZERO:Lorg/apache/commons/math3/util/Decimal64; (0, 0)
	11 new (0, 0)
	12 org/apache/commons/math3/util/Decimal64 (0, 0)
	14 dup (0, 0)
	15 dconst_1 (0, 0)
	16 invokespecial (0, 0)
	17 org/apache/commons/math3/util/Decimal64.<init>:(D)V (0, 0)
	19 putstatic (0, 0)
	20 org/apache/commons/math3/util/Decimal64.ONE:Lorg/apache/commons/math3/util/Decimal64; (0, 0)
	22 new (0, 0)
	23 org/apache/commons/math3/util/Decimal64 (0, 0)
	25 dup (0, 0)
	26 ldc2_w (0, 0)
	27 -inf (0, 0)
	29 invokespecial (0, 0)
	30 org/apache/commons/math3/util/Decimal64.<init>:(D)V (0, 0)
	32 putstatic (0, 0)
	33 org/apache/commons/math3/util/Decimal64.NEGATIVE_INFINITY:Lorg/apache/commons/math3/util/Decimal64; (0, 0)
	35 new (0, 0)
	36 org/apache/commons/math3/util/Decimal64 (0, 0)
	38 dup (0, 0)
	39 ldc2_w (0, 0)
	40 inf (0, 0)
	42 invokespecial (0, 0)
	43 org/apache/commons/math3/util/Decimal64.<init>:(D)V (0, 0)
	45 putstatic (0, 0)
	46 org/apache/commons/math3/util/Decimal64.POSITIVE_INFINITY:Lorg/apache/commons/math3/util/Decimal64; (0, 0)
	48 new (0, 0)
	49 org/apache/commons/math3/util/Decimal64 (0, 0)
	51 dup (0, 0)
	52 ldc2_w (0, 0)
	53 nan (0, 0)
	55 invokespecial (0, 0)
	56 org/apache/commons/math3/util/Decimal64.<init>:(D)V (0, 0)
	58 putstatic (0, 0)
	59 org/apache/commons/math3/util/Decimal64.NAN:Lorg/apache/commons/math3/util/Decimal64; (0, 0)
	61 return (0, 0)

