Method: <init>
	0 aload_0 (0, 0)
	1 invokespecial (0, 0)
	2 java/lang/Object.<init>:()V (0, 0)
	4 return (0, 0)

Method: getInstance
	0 getstatic (0, 0)
	1 org/apache/commons/math3/util/Decimal64Field.INSTANCE:Lorg/apache/commons/math3/util/Decimal64Field; (0, 0)
	3 areturn (0, 0)

Method: getZero
	0 aload_0 (0, 0)
	1 invokevirtual (0, 0)
	2 org/apache/commons/math3/util/Decimal64Field.getZero:()Lorg/apache/commons/math3/util/Decimal64; (0, 0)
	4 areturn (0, 0)

Method: getOne
	0 aload_0 (0, 0)
	1 invokevirtual (0, 0)
	2 org/apache/commons/math3/util/Decimal64Field.getOne:()Lorg/apache/commons/math3/util/Decimal64; (0, 0)
	4 areturn (0, 0)

Method: getRuntimeClass
	0 ldc (0, 0)
	1 org/apache/commons/math3/util/Decimal64 (0, 0)
	2 areturn (0, 0)

Method: <clinit>
	0 new (0, 0)
	1 org/apache/commons/math3/util/Decimal64Field (0, 0)
	3 dup (0, 0)
	4 invokespecial (0, 0)
	5 org/apache/commons/math3/util/Decimal64Field.<init>:()V (0, 0)
	7 putstatic (0, 0)
	8 org/apache/commons/math3/util/Decimal64Field.INSTANCE:Lorg/apache/commons/math3/util/Decimal64Field; (0, 0)
	10 return (0, 0)

