Method: transform
	0 aload_1 (1, 1)
	1 ifnonnull (1, 1)
	2 18 (1, 1)
	4 new (1, 1)
	5 org/apache/commons/math3/exception/NullArgumentException (1, 1)
	7 dup (1, 1)
	8 getstatic (1, 1)
	9 org/apache/commons/math3/exception/util/LocalizedFormats.OBJECT_TRANSFORMATION:Lorg/apache/commons/math3/exception/util/LocalizedFormats; (1, 1)
	11 iconst_0 (1, 1)
	12 anewarray (1, 1)
	13 java/lang/Object (1, 1)
	15 invokespecial (1, 1)
	16 org/apache/commons/math3/exception/NullArgumentException.<init>:(Lorg/apache/commons/math3/exception/util/Localizable;[Ljava/lang/Object;)V (1, 1)
	18 athrow (1, 1)
	19 aload_1 (1, 1)
	20 instanceof (1, 1)
	21 java/lang/Number (1, 1)
	23 ifeq (1, 1)
	24 11 (1, 1)
	26 aload_1 (1, 1)
	27 checkcast (1, 1)
	28 java/lang/Number (1, 1)
	30 invokevirtual (1, 1)
	31 java/lang/Number.doubleValue:()D (1, 1)
	33 dreturn (1, 1)
	34 aload_1 (0, 0)
	35 invokevirtual (0, 0)
	36 java/lang/Object.toString:()Ljava/lang/String; (0, 0)
	38 invokestatic (0, 0)
	39 java/lang/Double.parseDouble:(Ljava/lang/String;)D (0, 0)
	41 dreturn (0, 0)
	42 astore_2 (0, 0)
	43 new (0, 0)
	44 org/apache/commons/math3/exception/MathIllegalArgumentException (0, 0)
	46 dup (0, 0)
	47 getstatic (0, 0)
	48 org/apache/commons/math3/exception/util/LocalizedFormats.CANNOT_TRANSFORM_TO_DOUBLE:Lorg/apache/commons/math3/exception/util/LocalizedFormats; (0, 0)
	50 iconst_1 (0, 0)
	51 anewarray (0, 0)
	52 java/lang/Object (0, 0)
	54 dup (0, 0)
	55 iconst_0 (0, 0)
	56 aload_1 (0, 0)
	57 invokevirtual (0, 0)
	58 java/lang/Object.toString:()Ljava/lang/String; (0, 0)
	60 aastore (0, 0)
	61 invokespecial (0, 0)
	62 org/apache/commons/math3/exception/MathIllegalArgumentException.<init>:(Lorg/apache/commons/math3/exception/util/Localizable;[Ljava/lang/Object;)V (0, 0)
	64 athrow (0, 0)

Method: equals
	0 aload_0 (1, 1)
	1 aload_1 (1, 1)
	2 if_acmpne (1, 1)
	3 5 (1, 1)
	5 iconst_1 (1, 1)
	6 ireturn (1, 1)
	7 aload_1 (1, 4)
	8 instanceof (1, 4)
	9 org/apache/commons/math3/util/DefaultTransformer (1, 4)
	11 ireturn (0, 4)

Method: hashCode
	0 ldc (0, 0)
	1 401993047 (0, 0)
	2 ireturn (0, 0)

