Method: <init>
	0 aload_0 (0, 0)
	1 invokespecial (0, 0)
	2 java/lang/Object.<init>:()V (0, 0)
	4 return (0, 0)

Method: buildSinCosTables
	0 iconst_2 (0, 0)
	1 newarray (0, 0)
	2 7 (0, 0)
	3 astore (0, 0)
	4 #7 (0, 0)
	5 iconst_0 (1, 4)
	6 istore (1, 4)
	7 #8 (1, 4)
	8 iload (1, 4)
	9 #8 (1, 4)
	10 bipush (1, 4)
	11 7 (1, 4)
	12 if_icmpge (1, 4)
	13 66 (1, 4)
	15 iload (1, 4)
	16 #8 (1, 4)
	17 i2d (1, 4)
	18 ldc2_w (1, 4)
	19 8.0 (1, 4)
	21 ddiv (1, 4)
	22 dstore (1, 4)
	23 #9 (1, 4)
	24 dload (1, 4)
	25 #9 (1, 4)
	26 aload (1, 4)
	27 #7 (1, 4)
	28 invokestatic (1, 4)
	29 org/apache/commons/math3/util/FastMathCalc.slowSin:(D[D)D (1, 4)
	31 pop2 (1, 4)
	32 aload_0 (1, 4)
	33 iload (1, 4)
	34 #8 (1, 4)
	35 aload (1, 4)
	36 #7 (1, 4)
	37 iconst_0 (1, 4)
	38 daload (1, 4)
	39 dastore (1, 4)
	40 aload_1 (1, 4)
	41 iload (1, 4)
	42 #8 (1, 4)
	43 aload (1, 4)
	44 #7 (1, 4)
	45 iconst_1 (1, 4)
	46 daload (1, 4)
	47 dastore (1, 4)
	48 dload (1, 4)
	49 #9 (1, 4)
	50 aload (1, 4)
	51 #7 (1, 4)
	52 invokestatic (1, 4)
	53 org/apache/commons/math3/util/FastMathCalc.slowCos:(D[D)D (1, 4)
	55 pop2 (1, 4)
	56 aload_2 (1, 4)
	57 iload (1, 4)
	58 #8 (1, 4)
	59 aload (1, 4)
	60 #7 (1, 4)
	61 iconst_0 (1, 4)
	62 daload (1, 4)
	63 dastore (1, 4)
	64 aload_3 (1, 4)
	65 iload (1, 4)
	66 #8 (1, 4)
	67 aload (1, 4)
	68 #7 (1, 4)
	69 iconst_1 (1, 4)
	70 daload (1, 4)
	71 dastore (1, 4)
	72 iinc (1, 4)
	73 #8 (1, 4)
	74 -89 (1, 4)
	75 goto (1, 4)
	76 -67 (1, 4)
	78 bipush (1, 4)
	79 7 (1, 4)
	80 istore (1, 4)
	81 #8 (1, 4)
	82 iload (1, 4)
	83 #8 (1, 4)
	84 iload (1, 4)
	85 #4 (1, 4)
	86 if_icmpge (1, 4)
	87 370 (1, 4)
	89 iconst_2 (1, 4)
	90 newarray (1, 4)
	91 7 (1, 4)
	92 astore (1, 4)
	93 #9 (1, 4)
	94 iconst_2 (1, 4)
	95 newarray (1, 4)
	96 7 (1, 4)
	97 astore (1, 4)
	98 #10 (1, 4)
	99 iconst_2 (1, 4)
	100 newarray (1, 4)
	101 7 (1, 4)
	102 astore (1, 4)
	103 #11 (1, 4)
	104 iconst_2 (1, 4)
	105 newarray (1, 4)
	106 7 (1, 4)
	107 astore (1, 4)
	108 #12 (1, 4)
	109 iconst_2 (1, 4)
	110 newarray (1, 4)
	111 7 (1, 4)
	112 astore (1, 4)
	113 #13 (1, 4)
	114 iload (2, 1)
	115 #8 (2, 1)
	116 iconst_1 (2, 1)
	117 iand (2, 1)
	118 ifne (2, 1)
	119 140 (2, 1)
	121 aload (2, 1)
	122 #9 (2, 1)
	123 iconst_0 (2, 1)
	124 aload_0 (2, 1)
	125 iload (2, 1)
	126 #8 (2, 1)
	127 iconst_2 (2, 1)
	128 idiv (2, 1)
	129 daload (2, 1)
	130 dastore (2, 1)
	131 aload (2, 1)
	132 #9 (2, 1)
	133 iconst_1 (2, 1)
	134 aload_1 (2, 1)
	135 iload (2, 1)
	136 #8 (2, 1)
	137 iconst_2 (2, 1)
	138 idiv (2, 1)
	139 daload (2, 1)
	140 dastore (2, 1)
	141 aload (2, 1)
	142 #10 (2, 1)
	143 iconst_0 (2, 1)
	144 aload_2 (2, 1)
	145 iload (2, 1)
	146 #8 (2, 1)
	147 iconst_2 (2, 1)
	148 idiv (2, 1)
	149 daload (2, 1)
	150 dastore (2, 1)
	151 aload (2, 1)
	152 #10 (2, 1)
	153 iconst_1 (2, 1)
	154 aload_3 (2, 1)
	155 iload (2, 1)
	156 #8 (2, 1)
	157 iconst_2 (2, 1)
	158 idiv (2, 1)
	159 daload (2, 1)
	160 dastore (2, 1)
	161 aload (2, 1)
	162 #9 (2, 1)
	163 aload (2, 1)
	164 #10 (2, 1)
	165 aload (2, 1)
	166 #7 (2, 1)
	167 invokestatic (2, 1)
	168 org/apache/commons/math3/util/FastMathCalc.splitMult:([D[D[D)V (2, 1)
	170 aload_0 (2, 1)
	171 iload (2, 1)
	172 #8 (2, 1)
	173 aload (2, 1)
	174 #7 (2, 1)
	175 iconst_0 (2, 1)
	176 daload (2, 1)
	177 ldc2_w (2, 1)
	178 2.0 (2, 1)
	180 dmul (2, 1)
	181 dastore (2, 1)
	182 aload_1 (2, 1)
	183 iload (2, 1)
	184 #8 (2, 1)
	185 aload (2, 1)
	186 #7 (2, 1)
	187 iconst_1 (2, 1)
	188 daload (2, 1)
	189 ldc2_w (2, 1)
	190 2.0 (2, 1)
	192 dmul (2, 1)
	193 dastore (2, 1)
	194 aload (2, 1)
	195 #10 (2, 1)
	196 aload (2, 1)
	197 #10 (2, 1)
	198 aload (2, 1)
	199 #11 (2, 1)
	200 invokestatic (2, 1)
	201 org/apache/commons/math3/util/FastMathCalc.splitMult:([D[D[D)V (2, 1)
	203 aload (2, 1)
	204 #9 (2, 1)
	205 aload (2, 1)
	206 #9 (2, 1)
	207 aload (2, 1)
	208 #13 (2, 1)
	209 invokestatic (2, 1)
	210 org/apache/commons/math3/util/FastMathCalc.splitMult:([D[D[D)V (2, 1)
	212 aload (2, 1)
	213 #13 (2, 1)
	214 iconst_0 (2, 1)
	215 aload (2, 1)
	216 #13 (2, 1)
	217 iconst_0 (2, 1)
	218 daload (2, 1)
	219 dneg (2, 1)
	220 dastore (2, 1)
	221 aload (2, 1)
	222 #13 (2, 1)
	223 iconst_1 (2, 1)
	224 aload (2, 1)
	225 #13 (2, 1)
	226 iconst_1 (2, 1)
	227 daload (2, 1)
	228 dneg (2, 1)
	229 dastore (2, 1)
	230 aload (2, 1)
	231 #11 (2, 1)
	232 aload (2, 1)
	233 #13 (2, 1)
	234 aload (2, 1)
	235 #7 (2, 1)
	236 invokestatic (2, 1)
	237 org/apache/commons/math3/util/FastMathCalc.splitAdd:([D[D[D)V (2, 1)
	239 aload_2 (2, 1)
	240 iload (2, 1)
	241 #8 (2, 1)
	242 aload (2, 1)
	243 #7 (2, 1)
	244 iconst_0 (2, 1)
	245 daload (2, 1)
	246 dastore (2, 1)
	247 aload_3 (2, 1)
	248 iload (2, 1)
	249 #8 (2, 1)
	250 aload (2, 1)
	251 #7 (2, 1)
	252 iconst_1 (2, 1)
	253 daload (2, 1)
	254 dastore (2, 1)
	255 goto (2, 1)
	256 195 (2, 1)
	258 aload (2, 2)
	259 #9 (2, 2)
	260 iconst_0 (2, 2)
	261 aload_0 (2, 2)
	262 iload (2, 2)
	263 #8 (2, 2)
	264 iconst_2 (2, 2)
	265 idiv (2, 2)
	266 daload (2, 2)
	267 dastore (2, 2)
	268 aload (2, 2)
	269 #9 (2, 2)
	270 iconst_1 (2, 2)
	271 aload_1 (2, 2)
	272 iload (2, 2)
	273 #8 (2, 2)
	274 iconst_2 (2, 2)
	275 idiv (2, 2)
	276 daload (2, 2)
	277 dastore (2, 2)
	278 aload (2, 2)
	279 #10 (2, 2)
	280 iconst_0 (2, 2)
	281 aload_2 (2, 2)
	282 iload (2, 2)
	283 #8 (2, 2)
	284 iconst_2 (2, 2)
	285 idiv (2, 2)
	286 daload (2, 2)
	287 dastore (2, 2)
	288 aload (2, 2)
	289 #10 (2, 2)
	290 iconst_1 (2, 2)
	291 aload_3 (2, 2)
	292 iload (2, 2)
	293 #8 (2, 2)
	294 iconst_2 (2, 2)
	295 idiv (2, 2)
	296 daload (2, 2)
	297 dastore (2, 2)
	298 aload (2, 2)
	299 #11 (2, 2)
	300 iconst_0 (2, 2)
	301 aload_0 (2, 2)
	302 iload (2, 2)
	303 #8 (2, 2)
	304 iconst_2 (2, 2)
	305 idiv (2, 2)
	306 iconst_1 (2, 2)
	307 iadd (2, 2)
	308 daload (2, 2)
	309 dastore (2, 2)
	310 aload (2, 2)
	311 #11 (2, 2)
	312 iconst_1 (2, 2)
	313 aload_1 (2, 2)
	314 iload (2, 2)
	315 #8 (2, 2)
	316 iconst_2 (2, 2)
	317 idiv (2, 2)
	318 iconst_1 (2, 2)
	319 iadd (2, 2)
	320 daload (2, 2)
	321 dastore (2, 2)
	322 aload (2, 2)
	323 #12 (2, 2)
	324 iconst_0 (2, 2)
	325 aload_2 (2, 2)
	326 iload (2, 2)
	327 #8 (2, 2)
	328 iconst_2 (2, 2)
	329 idiv (2, 2)
	330 iconst_1 (2, 2)
	331 iadd (2, 2)
	332 daload (2, 2)
	333 dastore (2, 2)
	334 aload (2, 2)
	335 #12 (2, 2)
	336 iconst_1 (2, 2)
	337 aload_3 (2, 2)
	338 iload (2, 2)
	339 #8 (2, 2)
	340 iconst_2 (2, 2)
	341 idiv (2, 2)
	342 iconst_1 (2, 2)
	343 iadd (2, 2)
	344 daload (2, 2)
	345 dastore (2, 2)
	346 aload (2, 2)
	347 #9 (2, 2)
	348 aload (2, 2)
	349 #12 (2, 2)
	350 aload (2, 2)
	351 #13 (2, 2)
	352 invokestatic (2, 2)
	353 org/apache/commons/math3/util/FastMathCalc.splitMult:([D[D[D)V (2, 2)
	355 aload (2, 2)
	356 #10 (2, 2)
	357 aload (2, 2)
	358 #11 (2, 2)
	359 aload (2, 2)
	360 #7 (2, 2)
	361 invokestatic (2, 2)
	362 org/apache/commons/math3/util/FastMathCalc.splitMult:([D[D[D)V (2, 2)
	364 aload (2, 2)
	365 #7 (2, 2)
	366 aload (2, 2)
	367 #13 (2, 2)
	368 aload (2, 2)
	369 #7 (2, 2)
	370 invokestatic (2, 2)
	371 org/apache/commons/math3/util/FastMathCalc.splitAdd:([D[D[D)V (2, 2)
	373 aload_0 (2, 2)
	374 iload (2, 2)
	375 #8 (2, 2)
	376 aload (2, 2)
	377 #7 (2, 2)
	378 iconst_0 (2, 2)
	379 daload (2, 2)
	380 dastore (2, 2)
	381 aload_1 (2, 2)
	382 iload (2, 2)
	383 #8 (2, 2)
	384 aload (2, 2)
	385 #7 (2, 2)
	386 iconst_1 (2, 2)
	387 daload (2, 2)
	388 dastore (2, 2)
	389 aload (2, 2)
	390 #10 (2, 2)
	391 aload (2, 2)
	392 #12 (2, 2)
	393 aload (2, 2)
	394 #7 (2, 2)
	395 invokestatic (2, 2)
	396 org/apache/commons/math3/util/FastMathCalc.splitMult:([D[D[D)V (2, 2)
	398 aload (2, 2)
	399 #9 (2, 2)
	400 aload (2, 2)
	401 #11 (2, 2)
	402 aload (2, 2)
	403 #13 (2, 2)
	404 invokestatic (2, 2)
	405 org/apache/commons/math3/util/FastMathCalc.splitMult:([D[D[D)V (2, 2)
	407 aload (2, 2)
	408 #13 (2, 2)
	409 iconst_0 (2, 2)
	410 aload (2, 2)
	411 #13 (2, 2)
	412 iconst_0 (2, 2)
	413 daload (2, 2)
	414 dneg (2, 2)
	415 dastore (2, 2)
	416 aload (2, 2)
	417 #13 (2, 2)
	418 iconst_1 (2, 2)
	419 aload (2, 2)
	420 #13 (2, 2)
	421 iconst_1 (2, 2)
	422 daload (2, 2)
	423 dneg (2, 2)
	424 dastore (2, 2)
	425 aload (2, 2)
	426 #7 (2, 2)
	427 aload (2, 2)
	428 #13 (2, 2)
	429 aload (2, 2)
	430 #7 (2, 2)
	431 invokestatic (2, 2)
	432 org/apache/commons/math3/util/FastMathCalc.splitAdd:([D[D[D)V (2, 2)
	434 aload_2 (2, 2)
	435 iload (2, 2)
	436 #8 (2, 2)
	437 aload (2, 2)
	438 #7 (2, 2)
	439 iconst_0 (2, 2)
	440 daload (2, 2)
	441 dastore (2, 2)
	442 aload_3 (2, 2)
	443 iload (2, 2)
	444 #8 (2, 2)
	445 aload (2, 2)
	446 #7 (2, 2)
	447 iconst_1 (2, 2)
	448 daload (2, 2)
	449 dastore (2, 2)
	450 iinc (2, 2)
	451 #8 (2, 2)
	452 -89 (2, 2)
	453 goto (2, 2)
	454 -371 (2, 2)
	456 iconst_0 (2, 4)
	457 istore (2, 4)
	458 #8 (2, 4)
	459 iload (2, 4)
	460 #8 (2, 4)
	461 iload (2, 4)
	462 #4 (2, 4)
	463 if_icmpge (2, 4)
	464 90 (2, 4)
	466 iconst_2 (2, 4)
	467 newarray (2, 4)
	468 7 (2, 4)
	469 astore (2, 4)
	470 #9 (2, 4)
	471 iconst_2 (2, 4)
	472 newarray (2, 4)
	473 7 (2, 4)
	474 astore (2, 4)
	475 #10 (2, 4)
	476 iconst_2 (2, 4)
	477 newarray (2, 4)
	478 7 (2, 4)
	479 astore (2, 4)
	480 #11 (2, 4)
	481 aload (2, 4)
	482 #11 (2, 4)
	483 iconst_0 (2, 4)
	484 aload_2 (2, 4)
	485 iload (2, 4)
	486 #8 (2, 4)
	487 daload (2, 4)
	488 dastore (2, 4)
	489 aload (2, 4)
	490 #11 (2, 4)
	491 iconst_1 (2, 4)
	492 aload_3 (2, 4)
	493 iload (2, 4)
	494 #8 (2, 4)
	495 daload (2, 4)
	496 dastore (2, 4)
	497 aload (2, 4)
	498 #11 (2, 4)
	499 aload (2, 4)
	500 #10 (2, 4)
	501 invokestatic (2, 4)
	502 org/apache/commons/math3/util/FastMathCalc.splitReciprocal:([D[D)V (2, 4)
	504 aload (2, 4)
	505 #9 (2, 4)
	506 iconst_0 (2, 4)
	507 aload_0 (2, 4)
	508 iload (2, 4)
	509 #8 (2, 4)
	510 daload (2, 4)
	511 dastore (2, 4)
	512 aload (2, 4)
	513 #9 (2, 4)
	514 iconst_1 (2, 4)
	515 aload_1 (2, 4)
	516 iload (2, 4)
	517 #8 (2, 4)
	518 daload (2, 4)
	519 dastore (2, 4)
	520 aload (2, 4)
	521 #9 (2, 4)
	522 aload (2, 4)
	523 #10 (2, 4)
	524 aload (2, 4)
	525 #11 (2, 4)
	526 invokestatic (2, 4)
	527 org/apache/commons/math3/util/FastMathCalc.splitMult:([D[D[D)V (2, 4)
	529 aload (2, 4)
	530 #5 (2, 4)
	531 iload (2, 4)
	532 #8 (2, 4)
	533 aload (2, 4)
	534 #11 (2, 4)
	535 iconst_0 (2, 4)
	536 daload (2, 4)
	537 dastore (2, 4)
	538 aload (2, 4)
	539 #6 (2, 4)
	540 iload (2, 4)
	541 #8 (2, 4)
	542 aload (2, 4)
	543 #11 (2, 4)
	544 iconst_1 (2, 4)
	545 daload (2, 4)
	546 dastore (2, 4)
	547 iinc (2, 4)
	548 #8 (2, 4)
	549 -89 (2, 4)
	550 goto (2, 4)
	551 -91 (2, 4)
	553 return (0, 4)

Method: slowCos
	0 iconst_2 (0, 0)
	1 newarray (0, 0)
	2 7 (0, 0)
	3 astore_3 (0, 0)
	4 iconst_2 (0, 0)
	5 newarray (0, 0)
	6 7 (0, 0)
	7 astore (0, 0)
	8 #4 (0, 0)
	9 iconst_2 (0, 0)
	10 newarray (0, 0)
	11 7 (0, 0)
	12 astore (0, 0)
	13 #5 (0, 0)
	14 iconst_2 (0, 0)
	15 newarray (0, 0)
	16 7 (0, 0)
	17 astore (0, 0)
	18 #6 (0, 0)
	19 dload_0 (0, 0)
	20 aload_3 (0, 0)
	21 invokestatic (0, 0)
	22 org/apache/commons/math3/util/FastMathCalc.split:(D[D)V (0, 0)
	24 aload (0, 0)
	25 #4 (0, 0)
	26 iconst_0 (0, 0)
	27 aload (0, 0)
	28 #4 (0, 0)
	29 iconst_1 (0, 0)
	30 dconst_0 (0, 0)
	31 dup2_x2 (0, 0)
	32 dastore (0, 0)
	33 dastore (0, 0)
	34 getstatic (1, 4)
	35 org/apache/commons/math3/util/FastMathCalc.FACT:[D (1, 4)
	37 arraylength (1, 4)
	38 iconst_1 (1, 4)
	39 isub (1, 4)
	40 istore (1, 4)
	41 #7 (1, 4)
	42 iload (1, 4)
	43 #7 (1, 4)
	44 iflt (1, 4)
	45 111 (1, 4)
	47 aload_3 (1, 4)
	48 aload (1, 4)
	49 #4 (1, 4)
	50 aload (1, 4)
	51 #6 (1, 4)
	52 invokestatic (1, 4)
	53 org/apache/commons/math3/util/FastMathCalc.splitMult:([D[D[D)V (1, 4)
	55 aload (1, 4)
	56 #4 (1, 4)
	57 iconst_0 (1, 4)
	58 aload (1, 4)
	59 #6 (1, 4)
	60 iconst_0 (1, 4)
	61 daload (1, 4)
	62 dastore (1, 4)
	63 aload (1, 4)
	64 #4 (1, 4)
	65 iconst_1 (1, 4)
	66 aload (1, 4)
	67 #6 (1, 4)
	68 iconst_1 (1, 4)
	69 daload (1, 4)
	70 dastore (1, 4)
	71 iload (2, 1)
	72 #7 (2, 1)
	73 iconst_1 (2, 1)
	74 iand (2, 1)
	75 ifeq (2, 1)
	76 6 (2, 1)
	78 goto (2, 1)
	79 71 (2, 1)
	81 getstatic (1, 4)
	82 org/apache/commons/math3/util/FastMathCalc.FACT:[D (1, 4)
	84 iload (1, 4)
	85 #7 (1, 4)
	86 daload (1, 4)
	87 aload (1, 4)
	88 #6 (1, 4)
	89 invokestatic (1, 4)
	90 org/apache/commons/math3/util/FastMathCalc.split:(D[D)V (1, 4)
	92 aload (1, 4)
	93 #6 (1, 4)
	94 aload (1, 4)
	95 #5 (1, 4)
	96 invokestatic (1, 4)
	97 org/apache/commons/math3/util/FastMathCalc.splitReciprocal:([D[D)V (1, 4)
	99 iload (2, 1)
	100 #7 (2, 1)
	101 iconst_2 (2, 1)
	102 iand (2, 1)
	103 ifeq (2, 1)
	104 21 (2, 1)
	106 aload (2, 1)
	107 #5 (2, 1)
	108 iconst_0 (2, 1)
	109 aload (2, 1)
	110 #5 (2, 1)
	111 iconst_0 (2, 1)
	112 daload (2, 1)
	113 dneg (2, 1)
	114 dastore (2, 1)
	115 aload (2, 1)
	116 #5 (2, 1)
	117 iconst_1 (2, 1)
	118 aload (2, 1)
	119 #5 (2, 1)
	120 iconst_1 (2, 1)
	121 daload (2, 1)
	122 dneg (2, 1)
	123 dastore (2, 1)
	124 aload (1, 4)
	125 #4 (1, 4)
	126 aload (1, 4)
	127 #5 (1, 4)
	128 aload (1, 4)
	129 #6 (1, 4)
	130 invokestatic (1, 4)
	131 org/apache/commons/math3/util/FastMathCalc.splitAdd:([D[D[D)V (1, 4)
	133 aload (1, 4)
	134 #4 (1, 4)
	135 iconst_0 (1, 4)
	136 aload (1, 4)
	137 #6 (1, 4)
	138 iconst_0 (1, 4)
	139 daload (1, 4)
	140 dastore (1, 4)
	141 aload (1, 4)
	142 #4 (1, 4)
	143 iconst_1 (1, 4)
	144 aload (1, 4)
	145 #6 (1, 4)
	146 iconst_1 (1, 4)
	147 daload (1, 4)
	148 dastore (1, 4)
	149 iinc (1, 4)
	150 #7 (1, 4)
	151 -89 (1, 4)
	152 goto (1, 4)
	153 -110 (1, 4)
	155 aload_2 (1, 1)
	156 ifnull (1, 1)
	157 17 (1, 1)
	159 aload_2 (1, 1)
	160 iconst_0 (1, 1)
	161 aload (1, 1)
	162 #4 (1, 1)
	163 iconst_0 (1, 1)
	164 daload (1, 1)
	165 dastore (1, 1)
	166 aload_2 (1, 1)
	167 iconst_1 (1, 1)
	168 aload (1, 1)
	169 #4 (1, 1)
	170 iconst_1 (1, 1)
	171 daload (1, 1)
	172 dastore (1, 1)
	173 aload (0, 0)
	174 #4 (0, 0)
	175 iconst_0 (0, 0)
	176 daload (0, 0)
	177 aload (0, 0)
	178 #4 (0, 0)
	179 iconst_1 (0, 0)
	180 daload (0, 0)
	181 dadd (0, 0)
	182 dreturn (0, 0)

Method: slowSin
	0 iconst_2 (0, 0)
	1 newarray (0, 0)
	2 7 (0, 0)
	3 astore_3 (0, 0)
	4 iconst_2 (0, 0)
	5 newarray (0, 0)
	6 7 (0, 0)
	7 astore (0, 0)
	8 #4 (0, 0)
	9 iconst_2 (0, 0)
	10 newarray (0, 0)
	11 7 (0, 0)
	12 astore (0, 0)
	13 #5 (0, 0)
	14 iconst_2 (0, 0)
	15 newarray (0, 0)
	16 7 (0, 0)
	17 astore (0, 0)
	18 #6 (0, 0)
	19 dload_0 (0, 0)
	20 aload_3 (0, 0)
	21 invokestatic (0, 0)
	22 org/apache/commons/math3/util/FastMathCalc.split:(D[D)V (0, 0)
	24 aload (0, 0)
	25 #4 (0, 0)
	26 iconst_0 (0, 0)
	27 aload (0, 0)
	28 #4 (0, 0)
	29 iconst_1 (0, 0)
	30 dconst_0 (0, 0)
	31 dup2_x2 (0, 0)
	32 dastore (0, 0)
	33 dastore (0, 0)
	34 getstatic (1, 4)
	35 org/apache/commons/math3/util/FastMathCalc.FACT:[D (1, 4)
	37 arraylength (1, 4)
	38 iconst_1 (1, 4)
	39 isub (1, 4)
	40 istore (1, 4)
	41 #7 (1, 4)
	42 iload (1, 4)
	43 #7 (1, 4)
	44 iflt (1, 4)
	45 111 (1, 4)
	47 aload_3 (1, 4)
	48 aload (1, 4)
	49 #4 (1, 4)
	50 aload (1, 4)
	51 #6 (1, 4)
	52 invokestatic (1, 4)
	53 org/apache/commons/math3/util/FastMathCalc.splitMult:([D[D[D)V (1, 4)
	55 aload (1, 4)
	56 #4 (1, 4)
	57 iconst_0 (1, 4)
	58 aload (1, 4)
	59 #6 (1, 4)
	60 iconst_0 (1, 4)
	61 daload (1, 4)
	62 dastore (1, 4)
	63 aload (1, 4)
	64 #4 (1, 4)
	65 iconst_1 (1, 4)
	66 aload (1, 4)
	67 #6 (1, 4)
	68 iconst_1 (1, 4)
	69 daload (1, 4)
	70 dastore (1, 4)
	71 iload (2, 1)
	72 #7 (2, 1)
	73 iconst_1 (2, 1)
	74 iand (2, 1)
	75 ifne (2, 1)
	76 6 (2, 1)
	78 goto (2, 1)
	79 71 (2, 1)
	81 getstatic (1, 4)
	82 org/apache/commons/math3/util/FastMathCalc.FACT:[D (1, 4)
	84 iload (1, 4)
	85 #7 (1, 4)
	86 daload (1, 4)
	87 aload (1, 4)
	88 #6 (1, 4)
	89 invokestatic (1, 4)
	90 org/apache/commons/math3/util/FastMathCalc.split:(D[D)V (1, 4)
	92 aload (1, 4)
	93 #6 (1, 4)
	94 aload (1, 4)
	95 #5 (1, 4)
	96 invokestatic (1, 4)
	97 org/apache/commons/math3/util/FastMathCalc.splitReciprocal:([D[D)V (1, 4)
	99 iload (2, 1)
	100 #7 (2, 1)
	101 iconst_2 (2, 1)
	102 iand (2, 1)
	103 ifeq (2, 1)
	104 21 (2, 1)
	106 aload (2, 1)
	107 #5 (2, 1)
	108 iconst_0 (2, 1)
	109 aload (2, 1)
	110 #5 (2, 1)
	111 iconst_0 (2, 1)
	112 daload (2, 1)
	113 dneg (2, 1)
	114 dastore (2, 1)
	115 aload (2, 1)
	116 #5 (2, 1)
	117 iconst_1 (2, 1)
	118 aload (2, 1)
	119 #5 (2, 1)
	120 iconst_1 (2, 1)
	121 daload (2, 1)
	122 dneg (2, 1)
	123 dastore (2, 1)
	124 aload (1, 4)
	125 #4 (1, 4)
	126 aload (1, 4)
	127 #5 (1, 4)
	128 aload (1, 4)
	129 #6 (1, 4)
	130 invokestatic (1, 4)
	131 org/apache/commons/math3/util/FastMathCalc.splitAdd:([D[D[D)V (1, 4)
	133 aload (1, 4)
	134 #4 (1, 4)
	135 iconst_0 (1, 4)
	136 aload (1, 4)
	137 #6 (1, 4)
	138 iconst_0 (1, 4)
	139 daload (1, 4)
	140 dastore (1, 4)
	141 aload (1, 4)
	142 #4 (1, 4)
	143 iconst_1 (1, 4)
	144 aload (1, 4)
	145 #6 (1, 4)
	146 iconst_1 (1, 4)
	147 daload (1, 4)
	148 dastore (1, 4)
	149 iinc (1, 4)
	150 #7 (1, 4)
	151 -89 (1, 4)
	152 goto (1, 4)
	153 -110 (1, 4)
	155 aload_2 (1, 1)
	156 ifnull (1, 1)
	157 17 (1, 1)
	159 aload_2 (1, 1)
	160 iconst_0 (1, 1)
	161 aload (1, 1)
	162 #4 (1, 1)
	163 iconst_0 (1, 1)
	164 daload (1, 1)
	165 dastore (1, 1)
	166 aload_2 (1, 1)
	167 iconst_1 (1, 1)
	168 aload (1, 1)
	169 #4 (1, 1)
	170 iconst_1 (1, 1)
	171 daload (1, 1)
	172 dastore (1, 1)
	173 aload (0, 0)
	174 #4 (0, 0)
	175 iconst_0 (0, 0)
	176 daload (0, 0)
	177 aload (0, 0)
	178 #4 (0, 0)
	179 iconst_1 (0, 0)
	180 daload (0, 0)
	181 dadd (0, 0)
	182 dreturn (0, 0)

Method: slowexp
	0 iconst_2 (0, 0)
	1 newarray (0, 0)
	2 7 (0, 0)
	3 astore_3 (0, 0)
	4 iconst_2 (0, 0)
	5 newarray (0, 0)
	6 7 (0, 0)
	7 astore (0, 0)
	8 #4 (0, 0)
	9 iconst_2 (0, 0)
	10 newarray (0, 0)
	11 7 (0, 0)
	12 astore (0, 0)
	13 #5 (0, 0)
	14 iconst_2 (0, 0)
	15 newarray (0, 0)
	16 7 (0, 0)
	17 astore (0, 0)
	18 #6 (0, 0)
	19 dload_0 (0, 0)
	20 aload_3 (0, 0)
	21 invokestatic (0, 0)
	22 org/apache/commons/math3/util/FastMathCalc.split:(D[D)V (0, 0)
	24 aload (0, 0)
	25 #4 (0, 0)
	26 iconst_0 (0, 0)
	27 aload (0, 0)
	28 #4 (0, 0)
	29 iconst_1 (0, 0)
	30 dconst_0 (0, 0)
	31 dup2_x2 (0, 0)
	32 dastore (0, 0)
	33 dastore (0, 0)
	34 getstatic (1, 4)
	35 org/apache/commons/math3/util/FastMathCalc.FACT:[D (1, 4)
	37 arraylength (1, 4)
	38 iconst_1 (1, 4)
	39 isub (1, 4)
	40 istore (1, 4)
	41 #7 (1, 4)
	42 iload (1, 4)
	43 #7 (1, 4)
	44 iflt (1, 4)
	45 76 (1, 4)
	47 aload_3 (1, 4)
	48 aload (1, 4)
	49 #4 (1, 4)
	50 aload (1, 4)
	51 #6 (1, 4)
	52 invokestatic (1, 4)
	53 org/apache/commons/math3/util/FastMathCalc.splitMult:([D[D[D)V (1, 4)
	55 aload (1, 4)
	56 #4 (1, 4)
	57 iconst_0 (1, 4)
	58 aload (1, 4)
	59 #6 (1, 4)
	60 iconst_0 (1, 4)
	61 daload (1, 4)
	62 dastore (1, 4)
	63 aload (1, 4)
	64 #4 (1, 4)
	65 iconst_1 (1, 4)
	66 aload (1, 4)
	67 #6 (1, 4)
	68 iconst_1 (1, 4)
	69 daload (1, 4)
	70 dastore (1, 4)
	71 getstatic (1, 4)
	72 org/apache/commons/math3/util/FastMathCalc.FACT:[D (1, 4)
	74 iload (1, 4)
	75 #7 (1, 4)
	76 daload (1, 4)
	77 aload (1, 4)
	78 #6 (1, 4)
	79 invokestatic (1, 4)
	80 org/apache/commons/math3/util/FastMathCalc.split:(D[D)V (1, 4)
	82 aload (1, 4)
	83 #6 (1, 4)
	84 aload (1, 4)
	85 #5 (1, 4)
	86 invokestatic (1, 4)
	87 org/apache/commons/math3/util/FastMathCalc.splitReciprocal:([D[D)V (1, 4)
	89 aload (1, 4)
	90 #4 (1, 4)
	91 aload (1, 4)
	92 #5 (1, 4)
	93 aload (1, 4)
	94 #6 (1, 4)
	95 invokestatic (1, 4)
	96 org/apache/commons/math3/util/FastMathCalc.splitAdd:([D[D[D)V (1, 4)
	98 aload (1, 4)
	99 #4 (1, 4)
	100 iconst_0 (1, 4)
	101 aload (1, 4)
	102 #6 (1, 4)
	103 iconst_0 (1, 4)
	104 daload (1, 4)
	105 dastore (1, 4)
	106 aload (1, 4)
	107 #4 (1, 4)
	108 iconst_1 (1, 4)
	109 aload (1, 4)
	110 #6 (1, 4)
	111 iconst_1 (1, 4)
	112 daload (1, 4)
	113 dastore (1, 4)
	114 iinc (1, 4)
	115 #7 (1, 4)
	116 -89 (1, 4)
	117 goto (1, 4)
	118 -75 (1, 4)
	120 aload_2 (1, 1)
	121 ifnull (1, 1)
	122 17 (1, 1)
	124 aload_2 (1, 1)
	125 iconst_0 (1, 1)
	126 aload (1, 1)
	127 #4 (1, 1)
	128 iconst_0 (1, 1)
	129 daload (1, 1)
	130 dastore (1, 1)
	131 aload_2 (1, 1)
	132 iconst_1 (1, 1)
	133 aload (1, 1)
	134 #4 (1, 1)
	135 iconst_1 (1, 1)
	136 daload (1, 1)
	137 dastore (1, 1)
	138 aload (0, 0)
	139 #4 (0, 0)
	140 iconst_0 (0, 0)
	141 daload (0, 0)
	142 aload (0, 0)
	143 #4 (0, 0)
	144 iconst_1 (0, 0)
	145 daload (0, 0)
	146 dadd (0, 0)
	147 dreturn (0, 0)

Method: split
	0 dload_0 (1, 1)
	1 ldc2_w (1, 1)
	2 8e+298 (1, 1)
	4 dcmpg (1, 1)
	5 ifge (1, 1)
	6 36 (1, 1)
	8 dload_0 (1, 1)
	9 ldc2_w (1, 1)
	10 -8e+298 (1, 1)
	12 dcmpl (1, 1)
	13 ifle (1, 1)
	14 28 (1, 1)
	16 dload_0 (1, 1)
	17 ldc2_w (1, 1)
	18 1073741824.0 (1, 1)
	20 dmul (1, 1)
	21 dstore_3 (1, 1)
	22 aload_2 (1, 1)
	23 iconst_0 (1, 1)
	24 dload_0 (1, 1)
	25 dload_3 (1, 1)
	26 dadd (1, 1)
	27 dload_3 (1, 1)
	28 dsub (1, 1)
	29 dastore (1, 1)
	30 aload_2 (1, 1)
	31 iconst_1 (1, 1)
	32 dload_0 (1, 1)
	33 aload_2 (1, 1)
	34 iconst_0 (1, 1)
	35 daload (1, 1)
	36 dsub (1, 1)
	37 dastore (1, 1)
	38 goto (1, 2)
	39 29 (1, 2)
	41 dload_0 (1, 2)
	42 ldc2_w (1, 2)
	43 9.313225746154785e-10 (1, 2)
	45 dmul (1, 2)
	46 dstore_3 (1, 2)
	47 aload_2 (1, 2)
	48 iconst_0 (1, 2)
	49 dload_0 (1, 2)
	50 dload_3 (1, 2)
	51 dadd (1, 2)
	52 dload_0 (1, 2)
	53 dsub (1, 2)
	54 ldc2_w (1, 2)
	55 1073741824.0 (1, 2)
	57 dmul (1, 2)
	58 dastore (1, 2)
	59 aload_2 (1, 2)
	60 iconst_1 (1, 2)
	61 dload_0 (1, 2)
	62 aload_2 (1, 2)
	63 iconst_0 (1, 2)
	64 daload (1, 2)
	65 dsub (1, 2)
	66 dastore (1, 2)
	67 return (0, 0)

Method: resplit
	0 aload_0 (0, 0)
	1 iconst_0 (0, 0)
	2 daload (0, 0)
	3 aload_0 (0, 0)
	4 iconst_1 (0, 0)
	5 daload (0, 0)
	6 dadd (0, 0)
	7 dstore_1 (0, 0)
	8 dload_1 (0, 0)
	9 aload_0 (0, 0)
	10 iconst_0 (0, 0)
	11 daload (0, 0)
	12 dsub (0, 0)
	13 aload_0 (0, 0)
	14 iconst_1 (0, 0)
	15 daload (0, 0)
	16 dsub (0, 0)
	17 dneg (0, 0)
	18 dstore_3 (0, 0)
	19 dload_1 (1, 1)
	20 ldc2_w (1, 1)
	21 8e+298 (1, 1)
	23 dcmpg (1, 1)
	24 ifge (1, 1)
	25 41 (1, 1)
	27 dload_1 (1, 1)
	28 ldc2_w (1, 1)
	29 -8e+298 (1, 1)
	31 dcmpl (1, 1)
	32 ifle (1, 1)
	33 33 (1, 1)
	35 dload_1 (1, 1)
	36 ldc2_w (1, 1)
	37 1073741824.0 (1, 1)
	39 dmul (1, 1)
	40 dstore (1, 1)
	41 #5 (1, 1)
	42 aload_0 (1, 1)
	43 iconst_0 (1, 1)
	44 dload_1 (1, 1)
	45 dload (1, 1)
	46 #5 (1, 1)
	47 dadd (1, 1)
	48 dload (1, 1)
	49 #5 (1, 1)
	50 dsub (1, 1)
	51 dastore (1, 1)
	52 aload_0 (1, 1)
	53 iconst_1 (1, 1)
	54 dload_1 (1, 1)
	55 aload_0 (1, 1)
	56 iconst_0 (1, 1)
	57 daload (1, 1)
	58 dsub (1, 1)
	59 dload_3 (1, 1)
	60 dadd (1, 1)
	61 dastore (1, 1)
	62 goto (1, 2)
	63 33 (1, 2)
	65 dload_1 (1, 2)
	66 ldc2_w (1, 2)
	67 9.313225746154785e-10 (1, 2)
	69 dmul (1, 2)
	70 dstore (1, 2)
	71 #5 (1, 2)
	72 aload_0 (1, 2)
	73 iconst_0 (1, 2)
	74 dload_1 (1, 2)
	75 dload (1, 2)
	76 #5 (1, 2)
	77 dadd (1, 2)
	78 dload_1 (1, 2)
	79 dsub (1, 2)
	80 ldc2_w (1, 2)
	81 1073741824.0 (1, 2)
	83 dmul (1, 2)
	84 dastore (1, 2)
	85 aload_0 (1, 2)
	86 iconst_1 (1, 2)
	87 dload_1 (1, 2)
	88 aload_0 (1, 2)
	89 iconst_0 (1, 2)
	90 daload (1, 2)
	91 dsub (1, 2)
	92 dload_3 (1, 2)
	93 dadd (1, 2)
	94 dastore (1, 2)
	95 return (0, 0)

Method: splitMult
	0 aload_2 (0, 0)
	1 iconst_0 (0, 0)
	2 aload_0 (0, 0)
	3 iconst_0 (0, 0)
	4 daload (0, 0)
	5 aload_1 (0, 0)
	6 iconst_0 (0, 0)
	7 daload (0, 0)
	8 dmul (0, 0)
	9 dastore (0, 0)
	10 aload_2 (0, 0)
	11 iconst_1 (0, 0)
	12 aload_0 (0, 0)
	13 iconst_0 (0, 0)
	14 daload (0, 0)
	15 aload_1 (0, 0)
	16 iconst_1 (0, 0)
	17 daload (0, 0)
	18 dmul (0, 0)
	19 aload_0 (0, 0)
	20 iconst_1 (0, 0)
	21 daload (0, 0)
	22 aload_1 (0, 0)
	23 iconst_0 (0, 0)
	24 daload (0, 0)
	25 dmul (0, 0)
	26 dadd (0, 0)
	27 aload_0 (0, 0)
	28 iconst_1 (0, 0)
	29 daload (0, 0)
	30 aload_1 (0, 0)
	31 iconst_1 (0, 0)
	32 daload (0, 0)
	33 dmul (0, 0)
	34 dadd (0, 0)
	35 dastore (0, 0)
	36 aload_2 (0, 0)
	37 invokestatic (0, 0)
	38 org/apache/commons/math3/util/FastMathCalc.resplit:([D)V (0, 0)
	40 return (0, 0)

Method: splitAdd
	0 aload_2 (0, 0)
	1 iconst_0 (0, 0)
	2 aload_0 (0, 0)
	3 iconst_0 (0, 0)
	4 daload (0, 0)
	5 aload_1 (0, 0)
	6 iconst_0 (0, 0)
	7 daload (0, 0)
	8 dadd (0, 0)
	9 dastore (0, 0)
	10 aload_2 (0, 0)
	11 iconst_1 (0, 0)
	12 aload_0 (0, 0)
	13 iconst_1 (0, 0)
	14 daload (0, 0)
	15 aload_1 (0, 0)
	16 iconst_1 (0, 0)
	17 daload (0, 0)
	18 dadd (0, 0)
	19 dastore (0, 0)
	20 aload_2 (0, 0)
	21 invokestatic (0, 0)
	22 org/apache/commons/math3/util/FastMathCalc.resplit:([D)V (0, 0)
	24 return (0, 0)

Method: splitReciprocal
	0 ldc2_w (0, 0)
	1 2.384185791015625e-07 (0, 0)
	3 dstore_2 (0, 0)
	4 ldc2_w (0, 0)
	5 0.9999997615814209 (0, 0)
	7 dstore (0, 0)
	8 #4 (0, 0)
	9 aload_0 (1, 1)
	10 iconst_0 (1, 1)
	11 daload (1, 1)
	12 dconst_0 (1, 1)
	13 dcmpl (1, 1)
	14 ifne (1, 1)
	15 13 (1, 1)
	17 aload_0 (1, 1)
	18 iconst_0 (1, 1)
	19 aload_0 (1, 1)
	20 iconst_1 (1, 1)
	21 daload (1, 1)
	22 dastore (1, 1)
	23 aload_0 (1, 1)
	24 iconst_1 (1, 1)
	25 dconst_0 (1, 1)
	26 dastore (1, 1)
	27 aload_1 (0, 0)
	28 iconst_0 (0, 0)
	29 ldc2_w (0, 0)
	30 0.9999997615814209 (0, 0)
	32 aload_0 (0, 0)
	33 iconst_0 (0, 0)
	34 daload (0, 0)
	35 ddiv (0, 0)
	36 dastore (0, 0)
	37 aload_1 (0, 0)
	38 iconst_1 (0, 0)
	39 ldc2_w (0, 0)
	40 2.384185791015625e-07 (0, 0)
	42 aload_0 (0, 0)
	43 iconst_0 (0, 0)
	44 daload (0, 0)
	45 dmul (0, 0)
	46 ldc2_w (0, 0)
	47 0.9999997615814209 (0, 0)
	49 aload_0 (0, 0)
	50 iconst_1 (0, 0)
	51 daload (0, 0)
	52 dmul (0, 0)
	53 dsub (0, 0)
	54 aload_0 (0, 0)
	55 iconst_0 (0, 0)
	56 daload (0, 0)
	57 aload_0 (0, 0)
	58 iconst_0 (0, 0)
	59 daload (0, 0)
	60 dmul (0, 0)
	61 aload_0 (0, 0)
	62 iconst_0 (0, 0)
	63 daload (0, 0)
	64 aload_0 (0, 0)
	65 iconst_1 (0, 0)
	66 daload (0, 0)
	67 dmul (0, 0)
	68 dadd (0, 0)
	69 ddiv (0, 0)
	70 dastore (0, 0)
	71 aload_1 (1, 1)
	72 iconst_1 (1, 1)
	73 daload (1, 1)
	74 aload_1 (1, 1)
	75 iconst_1 (1, 1)
	76 daload (1, 1)
	77 dcmpl (1, 1)
	78 ifeq (1, 1)
	79 7 (1, 1)
	81 aload_1 (1, 1)
	82 iconst_1 (1, 1)
	83 dconst_0 (1, 1)
	84 dastore (1, 1)
	85 aload_1 (0, 0)
	86 invokestatic (0, 0)
	87 org/apache/commons/math3/util/FastMathCalc.resplit:([D)V (0, 0)
	89 iconst_0 (1, 4)
	90 istore (1, 4)
	91 #6 (1, 4)
	92 iload (1, 4)
	93 #6 (1, 4)
	94 iconst_2 (1, 4)
	95 if_icmpge (1, 4)
	96 64 (1, 4)
	98 dconst_1 (1, 4)
	99 aload_1 (1, 4)
	100 iconst_0 (1, 4)
	101 daload (1, 4)
	102 aload_0 (1, 4)
	103 iconst_0 (1, 4)
	104 daload (1, 4)
	105 dmul (1, 4)
	106 dsub (1, 4)
	107 aload_1 (1, 4)
	108 iconst_0 (1, 4)
	109 daload (1, 4)
	110 aload_0 (1, 4)
	111 iconst_1 (1, 4)
	112 daload (1, 4)
	113 dmul (1, 4)
	114 dsub (1, 4)
	115 aload_1 (1, 4)
	116 iconst_1 (1, 4)
	117 daload (1, 4)
	118 aload_0 (1, 4)
	119 iconst_0 (1, 4)
	120 daload (1, 4)
	121 dmul (1, 4)
	122 dsub (1, 4)
	123 aload_1 (1, 4)
	124 iconst_1 (1, 4)
	125 daload (1, 4)
	126 aload_0 (1, 4)
	127 iconst_1 (1, 4)
	128 daload (1, 4)
	129 dmul (1, 4)
	130 dsub (1, 4)
	131 dstore (1, 4)
	132 #7 (1, 4)
	133 dload (1, 4)
	134 #7 (1, 4)
	135 aload_1 (1, 4)
	136 iconst_0 (1, 4)
	137 daload (1, 4)
	138 aload_1 (1, 4)
	139 iconst_1 (1, 4)
	140 daload (1, 4)
	141 dadd (1, 4)
	142 dmul (1, 4)
	143 dstore (1, 4)
	144 #7 (1, 4)
	145 aload_1 (1, 4)
	146 iconst_1 (1, 4)
	147 dup2 (1, 4)
	148 daload (1, 4)
	149 dload (1, 4)
	150 #7 (1, 4)
	151 dadd (1, 4)
	152 dastore (1, 4)
	153 iinc (1, 4)
	154 #6 (1, 4)
	155 -89 (1, 4)
	156 goto (1, 4)
	157 -64 (1, 4)
	159 return (0, 0)

Method: quadMult
	0 iconst_2 (0, 0)
	1 newarray (0, 0)
	2 7 (0, 0)
	3 astore_3 (0, 0)
	4 iconst_2 (0, 0)
	5 newarray (0, 0)
	6 7 (0, 0)
	7 astore (0, 0)
	8 #4 (0, 0)
	9 iconst_2 (0, 0)
	10 newarray (0, 0)
	11 7 (0, 0)
	12 astore (0, 0)
	13 #5 (0, 0)
	14 aload_0 (0, 0)
	15 iconst_0 (0, 0)
	16 daload (0, 0)
	17 aload_3 (0, 0)
	18 invokestatic (0, 0)
	19 org/apache/commons/math3/util/FastMathCalc.split:(D[D)V (0, 0)
	21 aload_1 (0, 0)
	22 iconst_0 (0, 0)
	23 daload (0, 0)
	24 aload (0, 0)
	25 #4 (0, 0)
	26 invokestatic (0, 0)
	27 org/apache/commons/math3/util/FastMathCalc.split:(D[D)V (0, 0)
	29 aload_3 (0, 0)
	30 aload (0, 0)
	31 #4 (0, 0)
	32 aload (0, 0)
	33 #5 (0, 0)
	34 invokestatic (0, 0)
	35 org/apache/commons/math3/util/FastMathCalc.splitMult:([D[D[D)V (0, 0)
	37 aload_2 (0, 0)
	38 iconst_0 (0, 0)
	39 aload (0, 0)
	40 #5 (0, 0)
	41 iconst_0 (0, 0)
	42 daload (0, 0)
	43 dastore (0, 0)
	44 aload_2 (0, 0)
	45 iconst_1 (0, 0)
	46 aload (0, 0)
	47 #5 (0, 0)
	48 iconst_1 (0, 0)
	49 daload (0, 0)
	50 dastore (0, 0)
	51 aload_1 (0, 0)
	52 iconst_1 (0, 0)
	53 daload (0, 0)
	54 aload (0, 0)
	55 #4 (0, 0)
	56 invokestatic (0, 0)
	57 org/apache/commons/math3/util/FastMathCalc.split:(D[D)V (0, 0)
	59 aload_3 (0, 0)
	60 aload (0, 0)
	61 #4 (0, 0)
	62 aload (0, 0)
	63 #5 (0, 0)
	64 invokestatic (0, 0)
	65 org/apache/commons/math3/util/FastMathCalc.splitMult:([D[D[D)V (0, 0)
	67 aload_2 (0, 0)
	68 iconst_0 (0, 0)
	69 daload (0, 0)
	70 aload (0, 0)
	71 #5 (0, 0)
	72 iconst_0 (0, 0)
	73 daload (0, 0)
	74 dadd (0, 0)
	75 dstore (0, 0)
	76 #6 (0, 0)
	77 aload_2 (0, 0)
	78 iconst_1 (0, 0)
	79 dup2 (0, 0)
	80 daload (0, 0)
	81 dload (0, 0)
	82 #6 (0, 0)
	83 aload_2 (0, 0)
	84 iconst_0 (0, 0)
	85 daload (0, 0)
	86 dsub (0, 0)
	87 aload (0, 0)
	88 #5 (0, 0)
	89 iconst_0 (0, 0)
	90 daload (0, 0)
	91 dsub (0, 0)
	92 dsub (0, 0)
	93 dastore (0, 0)
	94 aload_2 (0, 0)
	95 iconst_0 (0, 0)
	96 dload (0, 0)
	97 #6 (0, 0)
	98 dastore (0, 0)
	99 aload_2 (0, 0)
	100 iconst_0 (0, 0)
	101 daload (0, 0)
	102 aload (0, 0)
	103 #5 (0, 0)
	104 iconst_1 (0, 0)
	105 daload (0, 0)
	106 dadd (0, 0)
	107 dstore (0, 0)
	108 #6 (0, 0)
	109 aload_2 (0, 0)
	110 iconst_1 (0, 0)
	111 dup2 (0, 0)
	112 daload (0, 0)
	113 dload (0, 0)
	114 #6 (0, 0)
	115 aload_2 (0, 0)
	116 iconst_0 (0, 0)
	117 daload (0, 0)
	118 dsub (0, 0)
	119 aload (0, 0)
	120 #5 (0, 0)
	121 iconst_1 (0, 0)
	122 daload (0, 0)
	123 dsub (0, 0)
	124 dsub (0, 0)
	125 dastore (0, 0)
	126 aload_2 (0, 0)
	127 iconst_0 (0, 0)
	128 dload (0, 0)
	129 #6 (0, 0)
	130 dastore (0, 0)
	131 aload_0 (0, 0)
	132 iconst_1 (0, 0)
	133 daload (0, 0)
	134 aload_3 (0, 0)
	135 invokestatic (0, 0)
	136 org/apache/commons/math3/util/FastMathCalc.split:(D[D)V (0, 0)
	138 aload_1 (0, 0)
	139 iconst_0 (0, 0)
	140 daload (0, 0)
	141 aload (0, 0)
	142 #4 (0, 0)
	143 invokestatic (0, 0)
	144 org/apache/commons/math3/util/FastMathCalc.split:(D[D)V (0, 0)
	146 aload_3 (0, 0)
	147 aload (0, 0)
	148 #4 (0, 0)
	149 aload (0, 0)
	150 #5 (0, 0)
	151 invokestatic (0, 0)
	152 org/apache/commons/math3/util/FastMathCalc.splitMult:([D[D[D)V (0, 0)
	154 aload_2 (0, 0)
	155 iconst_0 (0, 0)
	156 daload (0, 0)
	157 aload (0, 0)
	158 #5 (0, 0)
	159 iconst_0 (0, 0)
	160 daload (0, 0)
	161 dadd (0, 0)
	162 dstore (0, 0)
	163 #6 (0, 0)
	164 aload_2 (0, 0)
	165 iconst_1 (0, 0)
	166 dup2 (0, 0)
	167 daload (0, 0)
	168 dload (0, 0)
	169 #6 (0, 0)
	170 aload_2 (0, 0)
	171 iconst_0 (0, 0)
	172 daload (0, 0)
	173 dsub (0, 0)
	174 aload (0, 0)
	175 #5 (0, 0)
	176 iconst_0 (0, 0)
	177 daload (0, 0)
	178 dsub (0, 0)
	179 dsub (0, 0)
	180 dastore (0, 0)
	181 aload_2 (0, 0)
	182 iconst_0 (0, 0)
	183 dload (0, 0)
	184 #6 (0, 0)
	185 dastore (0, 0)
	186 aload_2 (0, 0)
	187 iconst_0 (0, 0)
	188 daload (0, 0)
	189 aload (0, 0)
	190 #5 (0, 0)
	191 iconst_1 (0, 0)
	192 daload (0, 0)
	193 dadd (0, 0)
	194 dstore (0, 0)
	195 #6 (0, 0)
	196 aload_2 (0, 0)
	197 iconst_1 (0, 0)
	198 dup2 (0, 0)
	199 daload (0, 0)
	200 dload (0, 0)
	201 #6 (0, 0)
	202 aload_2 (0, 0)
	203 iconst_0 (0, 0)
	204 daload (0, 0)
	205 dsub (0, 0)
	206 aload (0, 0)
	207 #5 (0, 0)
	208 iconst_1 (0, 0)
	209 daload (0, 0)
	210 dsub (0, 0)
	211 dsub (0, 0)
	212 dastore (0, 0)
	213 aload_2 (0, 0)
	214 iconst_0 (0, 0)
	215 dload (0, 0)
	216 #6 (0, 0)
	217 dastore (0, 0)
	218 aload_0 (0, 0)
	219 iconst_1 (0, 0)
	220 daload (0, 0)
	221 aload_3 (0, 0)
	222 invokestatic (0, 0)
	223 org/apache/commons/math3/util/FastMathCalc.split:(D[D)V (0, 0)
	225 aload_1 (0, 0)
	226 iconst_1 (0, 0)
	227 daload (0, 0)
	228 aload (0, 0)
	229 #4 (0, 0)
	230 invokestatic (0, 0)
	231 org/apache/commons/math3/util/FastMathCalc.split:(D[D)V (0, 0)
	233 aload_3 (0, 0)
	234 aload (0, 0)
	235 #4 (0, 0)
	236 aload (0, 0)
	237 #5 (0, 0)
	238 invokestatic (0, 0)
	239 org/apache/commons/math3/util/FastMathCalc.splitMult:([D[D[D)V (0, 0)
	241 aload_2 (0, 0)
	242 iconst_0 (0, 0)
	243 daload (0, 0)
	244 aload (0, 0)
	245 #5 (0, 0)
	246 iconst_0 (0, 0)
	247 daload (0, 0)
	248 dadd (0, 0)
	249 dstore (0, 0)
	250 #6 (0, 0)
	251 aload_2 (0, 0)
	252 iconst_1 (0, 0)
	253 dup2 (0, 0)
	254 daload (0, 0)
	255 dload (0, 0)
	256 #6 (0, 0)
	257 aload_2 (0, 0)
	258 iconst_0 (0, 0)
	259 daload (0, 0)
	260 dsub (0, 0)
	261 aload (0, 0)
	262 #5 (0, 0)
	263 iconst_0 (0, 0)
	264 daload (0, 0)
	265 dsub (0, 0)
	266 dsub (0, 0)
	267 dastore (0, 0)
	268 aload_2 (0, 0)
	269 iconst_0 (0, 0)
	270 dload (0, 0)
	271 #6 (0, 0)
	272 dastore (0, 0)
	273 aload_2 (0, 0)
	274 iconst_0 (0, 0)
	275 daload (0, 0)
	276 aload (0, 0)
	277 #5 (0, 0)
	278 iconst_1 (0, 0)
	279 daload (0, 0)
	280 dadd (0, 0)
	281 dstore (0, 0)
	282 #6 (0, 0)
	283 aload_2 (0, 0)
	284 iconst_1 (0, 0)
	285 dup2 (0, 0)
	286 daload (0, 0)
	287 dload (0, 0)
	288 #6 (0, 0)
	289 aload_2 (0, 0)
	290 iconst_0 (0, 0)
	291 daload (0, 0)
	292 dsub (0, 0)
	293 aload (0, 0)
	294 #5 (0, 0)
	295 iconst_1 (0, 0)
	296 daload (0, 0)
	297 dsub (0, 0)
	298 dsub (0, 0)
	299 dastore (0, 0)
	300 aload_2 (0, 0)
	301 iconst_0 (0, 0)
	302 dload (0, 0)
	303 #6 (0, 0)
	304 dastore (0, 0)
	305 return (0, 0)

Method: expint
	0 iconst_2 (0, 0)
	1 newarray (0, 0)
	2 7 (0, 0)
	3 astore_2 (0, 0)
	4 iconst_2 (0, 0)
	5 newarray (0, 0)
	6 7 (0, 0)
	7 astore_3 (0, 0)
	8 iconst_2 (0, 0)
	9 newarray (0, 0)
	10 7 (0, 0)
	11 astore (0, 0)
	12 #4 (0, 0)
	13 aload_2 (0, 0)
	14 iconst_0 (0, 0)
	15 ldc2_w (0, 0)
	16 2.718281828459045 (0, 0)
	18 dastore (0, 0)
	19 aload_2 (0, 0)
	20 iconst_1 (0, 0)
	21 ldc2_w (0, 0)
	22 1.4456468917292502e-16 (0, 0)
	24 dastore (0, 0)
	25 dconst_1 (0, 0)
	26 aload (0, 0)
	27 #4 (0, 0)
	28 invokestatic (0, 0)
	29 org/apache/commons/math3/util/FastMathCalc.split:(D[D)V (0, 0)
	31 iload_0 (1, 3)
	32 ifle (1, 3)
	33 55 (1, 3)
	35 iload_0 (2, 1)
	36 iconst_1 (2, 1)
	37 iand (2, 1)
	38 ifeq (2, 1)
	39 24 (2, 1)
	41 aload (2, 1)
	42 #4 (2, 1)
	43 aload_2 (2, 1)
	44 aload_3 (2, 1)
	45 invokestatic (2, 1)
	46 org/apache/commons/math3/util/FastMathCalc.quadMult:([D[D[D)V (2, 1)
	48 aload (2, 1)
	49 #4 (2, 1)
	50 iconst_0 (2, 1)
	51 aload_3 (2, 1)
	52 iconst_0 (2, 1)
	53 daload (2, 1)
	54 dastore (2, 1)
	55 aload (2, 1)
	56 #4 (2, 1)
	57 iconst_1 (2, 1)
	58 aload_3 (2, 1)
	59 iconst_1 (2, 1)
	60 daload (2, 1)
	61 dastore (2, 1)
	62 aload_2 (1, 3)
	63 aload_2 (1, 3)
	64 aload_3 (1, 3)
	65 invokestatic (1, 3)
	66 org/apache/commons/math3/util/FastMathCalc.quadMult:([D[D[D)V (1, 3)
	68 aload_2 (1, 3)
	69 iconst_0 (1, 3)
	70 aload_3 (1, 3)
	71 iconst_0 (1, 3)
	72 daload (1, 3)
	73 dastore (1, 3)
	74 aload_2 (1, 3)
	75 iconst_1 (1, 3)
	76 aload_3 (1, 3)
	77 iconst_1 (1, 3)
	78 daload (1, 3)
	79 dastore (1, 3)
	80 iload_0 (1, 3)
	81 iconst_1 (1, 3)
	82 ishr (1, 3)
	83 istore_0 (1, 3)
	84 goto (1, 3)
	85 -53 (1, 3)
	87 aload_1 (1, 1)
	88 ifnull (1, 1)
	89 21 (1, 1)
	91 aload_1 (1, 1)
	92 iconst_0 (1, 1)
	93 aload (1, 1)
	94 #4 (1, 1)
	95 iconst_0 (1, 1)
	96 daload (1, 1)
	97 dastore (1, 1)
	98 aload_1 (1, 1)
	99 iconst_1 (1, 1)
	100 aload (1, 1)
	101 #4 (1, 1)
	102 iconst_1 (1, 1)
	103 daload (1, 1)
	104 dastore (1, 1)
	105 aload_1 (1, 1)
	106 invokestatic (1, 1)
	107 org/apache/commons/math3/util/FastMathCalc.resplit:([D)V (1, 1)
	109 aload (0, 0)
	110 #4 (0, 0)
	111 iconst_0 (0, 0)
	112 daload (0, 0)
	113 aload (0, 0)
	114 #4 (0, 0)
	115 iconst_1 (0, 0)
	116 daload (0, 0)
	117 dadd (0, 0)
	118 dreturn (0, 0)

Method: slowLog
	0 iconst_2 (0, 0)
	1 newarray (0, 0)
	2 7 (0, 0)
	3 astore_2 (0, 0)
	4 iconst_2 (0, 0)
	5 newarray (0, 0)
	6 7 (0, 0)
	7 astore_3 (0, 0)
	8 iconst_2 (0, 0)
	9 newarray (0, 0)
	10 7 (0, 0)
	11 astore (0, 0)
	12 #4 (0, 0)
	13 iconst_2 (0, 0)
	14 newarray (0, 0)
	15 7 (0, 0)
	16 astore (0, 0)
	17 #5 (0, 0)
	18 dload_0 (0, 0)
	19 aload_2 (0, 0)
	20 invokestatic (0, 0)
	21 org/apache/commons/math3/util/FastMathCalc.split:(D[D)V (0, 0)
	23 aload_2 (0, 0)
	24 iconst_0 (0, 0)
	25 dup2 (0, 0)
	26 daload (0, 0)
	27 dconst_1 (0, 0)
	28 dadd (0, 0)
	29 dastore (0, 0)
	30 aload_2 (0, 0)
	31 invokestatic (0, 0)
	32 org/apache/commons/math3/util/FastMathCalc.resplit:([D)V (0, 0)
	34 aload_2 (0, 0)
	35 aload (0, 0)
	36 #5 (0, 0)
	37 invokestatic (0, 0)
	38 org/apache/commons/math3/util/FastMathCalc.splitReciprocal:([D[D)V (0, 0)
	40 aload_2 (0, 0)
	41 iconst_0 (0, 0)
	42 dup2 (0, 0)
	43 daload (0, 0)
	44 ldc2_w (0, 0)
	45 2.0 (0, 0)
	47 dsub (0, 0)
	48 dastore (0, 0)
	49 aload_2 (0, 0)
	50 invokestatic (0, 0)
	51 org/apache/commons/math3/util/FastMathCalc.resplit:([D)V (0, 0)
	53 aload_2 (0, 0)
	54 aload (0, 0)
	55 #5 (0, 0)
	56 aload (0, 0)
	57 #4 (0, 0)
	58 invokestatic (0, 0)
	59 org/apache/commons/math3/util/FastMathCalc.splitMult:([D[D[D)V (0, 0)
	61 aload_2 (0, 0)
	62 iconst_0 (0, 0)
	63 aload (0, 0)
	64 #4 (0, 0)
	65 iconst_0 (0, 0)
	66 daload (0, 0)
	67 dastore (0, 0)
	68 aload_2 (0, 0)
	69 iconst_1 (0, 0)
	70 aload (0, 0)
	71 #4 (0, 0)
	72 iconst_1 (0, 0)
	73 daload (0, 0)
	74 dastore (0, 0)
	75 aload_2 (0, 0)
	76 aload_2 (0, 0)
	77 aload_3 (0, 0)
	78 invokestatic (0, 0)
	79 org/apache/commons/math3/util/FastMathCalc.splitMult:([D[D[D)V (0, 0)
	81 aload (0, 0)
	82 #4 (0, 0)
	83 iconst_0 (0, 0)
	84 getstatic (0, 0)
	85 org/apache/commons/math3/util/FastMathCalc.LN_SPLIT_COEF:[[D (0, 0)
	87 getstatic (0, 0)
	88 org/apache/commons/math3/util/FastMathCalc.LN_SPLIT_COEF:[[D (0, 0)
	90 arraylength (0, 0)
	91 iconst_1 (0, 0)
	92 isub (0, 0)
	93 aaload (0, 0)
	94 iconst_0 (0, 0)
	95 daload (0, 0)
	96 dastore (0, 0)
	97 aload (0, 0)
	98 #4 (0, 0)
	99 iconst_1 (0, 0)
	100 getstatic (0, 0)
	101 org/apache/commons/math3/util/FastMathCalc.LN_SPLIT_COEF:[[D (0, 0)
	103 getstatic (0, 0)
	104 org/apache/commons/math3/util/FastMathCalc.LN_SPLIT_COEF:[[D (0, 0)
	106 arraylength (0, 0)
	107 iconst_1 (0, 0)
	108 isub (0, 0)
	109 aaload (0, 0)
	110 iconst_1 (0, 0)
	111 daload (0, 0)
	112 dastore (0, 0)
	113 getstatic (1, 4)
	114 org/apache/commons/math3/util/FastMathCalc.LN_SPLIT_COEF:[[D (1, 4)
	116 arraylength (1, 4)
	117 iconst_2 (1, 4)
	118 isub (1, 4)
	119 istore (1, 4)
	120 #6 (1, 4)
	121 iload (1, 4)
	122 #6 (1, 4)
	123 iflt (1, 4)
	124 62 (1, 4)
	126 aload (1, 4)
	127 #4 (1, 4)
	128 aload_3 (1, 4)
	129 aload (1, 4)
	130 #5 (1, 4)
	131 invokestatic (1, 4)
	132 org/apache/commons/math3/util/FastMathCalc.splitMult:([D[D[D)V (1, 4)
	134 aload (1, 4)
	135 #4 (1, 4)
	136 iconst_0 (1, 4)
	137 aload (1, 4)
	138 #5 (1, 4)
	139 iconst_0 (1, 4)
	140 daload (1, 4)
	141 dastore (1, 4)
	142 aload (1, 4)
	143 #4 (1, 4)
	144 iconst_1 (1, 4)
	145 aload (1, 4)
	146 #5 (1, 4)
	147 iconst_1 (1, 4)
	148 daload (1, 4)
	149 dastore (1, 4)
	150 aload (1, 4)
	151 #4 (1, 4)
	152 getstatic (1, 4)
	153 org/apache/commons/math3/util/FastMathCalc.LN_SPLIT_COEF:[[D (1, 4)
	155 iload (1, 4)
	156 #6 (1, 4)
	157 aaload (1, 4)
	158 aload (1, 4)
	159 #5 (1, 4)
	160 invokestatic (1, 4)
	161 org/apache/commons/math3/util/FastMathCalc.splitAdd:([D[D[D)V (1, 4)
	163 aload (1, 4)
	164 #4 (1, 4)
	165 iconst_0 (1, 4)
	166 aload (1, 4)
	167 #5 (1, 4)
	168 iconst_0 (1, 4)
	169 daload (1, 4)
	170 dastore (1, 4)
	171 aload (1, 4)
	172 #4 (1, 4)
	173 iconst_1 (1, 4)
	174 aload (1, 4)
	175 #5 (1, 4)
	176 iconst_1 (1, 4)
	177 daload (1, 4)
	178 dastore (1, 4)
	179 iinc (1, 4)
	180 #6 (1, 4)
	181 -89 (1, 4)
	182 goto (1, 4)
	183 -61 (1, 4)
	185 aload (0, 0)
	186 #4 (0, 0)
	187 aload_2 (0, 0)
	188 aload (0, 0)
	189 #5 (0, 0)
	190 invokestatic (0, 0)
	191 org/apache/commons/math3/util/FastMathCalc.splitMult:([D[D[D)V (0, 0)
	193 aload (0, 0)
	194 #4 (0, 0)
	195 iconst_0 (0, 0)
	196 aload (0, 0)
	197 #5 (0, 0)
	198 iconst_0 (0, 0)
	199 daload (0, 0)
	200 dastore (0, 0)
	201 aload (0, 0)
	202 #4 (0, 0)
	203 iconst_1 (0, 0)
	204 aload (0, 0)
	205 #5 (0, 0)
	206 iconst_1 (0, 0)
	207 daload (0, 0)
	208 dastore (0, 0)
	209 aload (0, 0)
	210 #4 (0, 0)
	211 areturn (0, 0)

Method: printarray
	0 aload_0 (0, 0)
	1 new (0, 0)
	2 java/lang/StringBuilder (0, 0)
	4 dup (0, 0)
	5 invokespecial (0, 0)
	6 java/lang/StringBuilder.<init>:()V (0, 0)
	8 aload_1 (0, 0)
	9 invokevirtual (0, 0)
	10 java/lang/StringBuilder.append:(Ljava/lang/String;)Ljava/lang/StringBuilder; (0, 0)
	12 ldc (0, 0)
	13 = (0, 0)
	14 invokevirtual (0, 0)
	15 java/lang/StringBuilder.append:(Ljava/lang/String;)Ljava/lang/StringBuilder; (0, 0)
	17 invokevirtual (0, 0)
	18 java/lang/StringBuilder.toString:()Ljava/lang/String; (0, 0)
	20 invokevirtual (0, 0)
	21 java/io/PrintStream.println:(Ljava/lang/String;)V (0, 0)
	23 iload_2 (0, 0)
	24 aload_3 (0, 0)
	25 arraylength (0, 0)
	26 invokestatic (0, 0)
	27 org/apache/commons/math3/util/FastMathCalc.checkLen:(II)V (0, 0)
	29 aload_0 (0, 0)
	30 ldc (0, 0)
	31     { (0, 0)
	32 invokevirtual (0, 0)
	33 java/io/PrintStream.println:(Ljava/lang/String;)V (0, 0)
	35 aload_3 (1, 4)
	36 astore (1, 4)
	37 #4 (1, 4)
	38 aload (1, 4)
	39 #4 (1, 4)
	40 arraylength (1, 4)
	41 istore (1, 4)
	42 #5 (1, 4)
	43 iconst_0 (1, 4)
	44 istore (1, 4)
	45 #6 (1, 4)
	46 iload (1, 4)
	47 #6 (1, 4)
	48 iload (1, 4)
	49 #5 (1, 4)
	50 if_icmpge (1, 4)
	51 35 (1, 4)
	53 aload (1, 4)
	54 #4 (1, 4)
	55 iload (1, 4)
	56 #6 (1, 4)
	57 daload (1, 4)
	58 dstore (1, 4)
	59 #7 (1, 4)
	60 aload_0 (1, 4)
	61 ldc (1, 4)
	62         %s%n (1, 4)
	63 iconst_1 (1, 4)
	64 anewarray (1, 4)
	65 java/lang/Object (1, 4)
	67 dup (1, 4)
	68 iconst_0 (1, 4)
	69 dload (1, 4)
	70 #7 (1, 4)
	71 invokestatic (1, 4)
	72 org/apache/commons/math3/util/FastMathCalc.format:(D)Ljava/lang/String; (1, 4)
	74 aastore (1, 4)
	75 invokevirtual (1, 4)
	76 java/io/PrintStream.printf:(Ljava/lang/String;[Ljava/lang/Object;)Ljava/io/PrintStream; (1, 4)
	78 pop (1, 4)
	79 iinc (1, 4)
	80 #6 (1, 4)
	81 -89 (1, 4)
	82 goto (1, 4)
	83 -36 (1, 4)
	85 aload_0 (0, 0)
	86 ldc (0, 0)
	87     }; (0, 0)
	88 invokevirtual (0, 0)
	89 java/io/PrintStream.println:(Ljava/lang/String;)V (0, 0)
	91 return (0, 0)

Method: format
	0 dload_0 (1, 1)
	1 dload_0 (1, 1)
	2 dcmpl (1, 1)
	3 ifeq (1, 1)
	4 6 (1, 1)
	6 ldc (1, 1)
	7 Double.NaN, (1, 1)
	8 areturn (1, 1)
	9 new (1, 2)
	10 java/lang/StringBuilder (1, 2)
	12 dup (1, 2)
	13 invokespecial (1, 2)
	14 java/lang/StringBuilder.<init>:()V (1, 2)
	16 dload_0 (1, 2)
	17 dconst_0 (1, 2)
	18 dcmpl (1, 2)
	19 iflt (1, 2)
	20 8 (1, 2)
	22 ldc (1, 2)
	23 + (1, 2)
	24 goto (1, 2)
	25 5 (1, 2)
	27 ldc (1, 2)
	28  (1, 2)
	29 invokevirtual (1, 2)
	30 java/lang/StringBuilder.append:(Ljava/lang/String;)Ljava/lang/StringBuilder; (1, 2)
	32 dload_0 (1, 2)
	33 invokestatic (1, 2)
	34 java/lang/Double.toString:(D)Ljava/lang/String; (1, 2)
	36 invokevirtual (1, 2)
	37 java/lang/StringBuilder.append:(Ljava/lang/String;)Ljava/lang/StringBuilder; (1, 2)
	39 ldc (1, 2)
	40 d, (1, 2)
	41 invokevirtual (1, 2)
	42 java/lang/StringBuilder.append:(Ljava/lang/String;)Ljava/lang/StringBuilder; (1, 2)
	44 invokevirtual (1, 2)
	45 java/lang/StringBuilder.toString:()Ljava/lang/String; (1, 2)
	47 areturn (1, 2)

Method: checkLen
	0 iload_0 (1, 1)
	1 iload_1 (1, 1)
	2 if_icmpeq (1, 1)
	3 13 (1, 1)
	5 new (1, 1)
	6 org/apache/commons/math3/exception/DimensionMismatchException (1, 1)
	8 dup (1, 1)
	9 iload_1 (1, 1)
	10 iload_0 (1, 1)
	11 invokespecial (1, 1)
	12 org/apache/commons/math3/exception/DimensionMismatchException.<init>:(II)V (1, 1)
	14 athrow (1, 1)
	15 return (0, 0)

Method: <clinit>
	0 bipush (0, 0)
	1 20 (0, 0)
	2 newarray (0, 0)
	3 7 (0, 0)
	4 dup (0, 0)
	5 iconst_0 (0, 0)
	6 dconst_1 (0, 0)
	7 dastore (0, 0)
	8 dup (0, 0)
	9 iconst_1 (0, 0)
	10 dconst_1 (0, 0)
	11 dastore (0, 0)
	12 dup (0, 0)
	13 iconst_2 (0, 0)
	14 ldc2_w (0, 0)
	15 2.0 (0, 0)
	17 dastore (0, 0)
	18 dup (0, 0)
	19 iconst_3 (0, 0)
	20 ldc2_w (0, 0)
	21 6.0 (0, 0)
	23 dastore (0, 0)
	24 dup (0, 0)
	25 iconst_4 (0, 0)
	26 ldc2_w (0, 0)
	27 24.0 (0, 0)
	29 dastore (0, 0)
	30 dup (0, 0)
	31 iconst_5 (0, 0)
	32 ldc2_w (0, 0)
	33 120.0 (0, 0)
	35 dastore (0, 0)
	36 dup (0, 0)
	37 bipush (0, 0)
	38 6 (0, 0)
	39 ldc2_w (0, 0)
	40 720.0 (0, 0)
	42 dastore (0, 0)
	43 dup (0, 0)
	44 bipush (0, 0)
	45 7 (0, 0)
	46 ldc2_w (0, 0)
	47 5040.0 (0, 0)
	49 dastore (0, 0)
	50 dup (0, 0)
	51 bipush (0, 0)
	52 8 (0, 0)
	53 ldc2_w (0, 0)
	54 40320.0 (0, 0)
	56 dastore (0, 0)
	57 dup (0, 0)
	58 bipush (0, 0)
	59 9 (0, 0)
	60 ldc2_w (0, 0)
	61 362880.0 (0, 0)
	63 dastore (0, 0)
	64 dup (0, 0)
	65 bipush (0, 0)
	66 10 (0, 0)
	67 ldc2_w (0, 0)
	68 3628800.0 (0, 0)
	70 dastore (0, 0)
	71 dup (0, 0)
	72 bipush (0, 0)
	73 11 (0, 0)
	74 ldc2_w (0, 0)
	75 39916800.0 (0, 0)
	77 dastore (0, 0)
	78 dup (0, 0)
	79 bipush (0, 0)
	80 12 (0, 0)
	81 ldc2_w (0, 0)
	82 479001600.0 (0, 0)
	84 dastore (0, 0)
	85 dup (0, 0)
	86 bipush (0, 0)
	87 13 (0, 0)
	88 ldc2_w (0, 0)
	89 6227020800.0 (0, 0)
	91 dastore (0, 0)
	92 dup (0, 0)
	93 bipush (0, 0)
	94 14 (0, 0)
	95 ldc2_w (0, 0)
	96 87178291200.0 (0, 0)
	98 dastore (0, 0)
	99 dup (0, 0)
	100 bipush (0, 0)
	101 15 (0, 0)
	102 ldc2_w (0, 0)
	103 1307674368000.0 (0, 0)
	105 dastore (0, 0)
	106 dup (0, 0)
	107 bipush (0, 0)
	108 16 (0, 0)
	109 ldc2_w (0, 0)
	110 20922789888000.0 (0, 0)
	112 dastore (0, 0)
	113 dup (0, 0)
	114 bipush (0, 0)
	115 17 (0, 0)
	116 ldc2_w (0, 0)
	117 355687428096000.0 (0, 0)
	119 dastore (0, 0)
	120 dup (0, 0)
	121 bipush (0, 0)
	122 18 (0, 0)
	123 ldc2_w (0, 0)
	124 6402373705728000.0 (0, 0)
	126 dastore (0, 0)
	127 dup (0, 0)
	128 bipush (0, 0)
	129 19 (0, 0)
	130 ldc2_w (0, 0)
	131 1.21645100408832e+17 (0, 0)
	133 dastore (0, 0)
	134 putstatic (0, 0)
	135 org/apache/commons/math3/util/FastMathCalc.FACT:[D (0, 0)
	137 bipush (0, 4)
	138 16 (0, 4)
	139 anewarray (0, 4)
	140 [D (0, 4)
	142 dup (0, 4)
	143 iconst_0 (0, 4)
	144 iconst_2 (0, 4)
	145 newarray (0, 4)
	146 7 (0, 4)
	147 dup (0, 4)
	148 iconst_0 (0, 4)
	149 ldc2_w (0, 4)
	150 2.0 (0, 4)
	152 dastore (0, 4)
	153 dup (0, 4)
	154 iconst_1 (0, 4)
	155 dconst_0 (0, 4)
	156 dastore (0, 4)
	157 aastore (0, 4)
	158 dup (0, 4)
	159 iconst_1 (0, 4)
	160 iconst_2 (0, 4)
	161 newarray (0, 4)
	162 7 (0, 4)
	163 dup (0, 4)
	164 iconst_0 (0, 4)
	165 ldc2_w (0, 4)
	166 0.6666666269302368 (0, 4)
	168 dastore (0, 4)
	169 dup (0, 4)
	170 iconst_1 (0, 4)
	171 ldc2_w (0, 4)
	172 3.9736429850260626e-08 (0, 4)
	174 dastore (0, 4)
	175 aastore (0, 4)
	176 dup (0, 4)
	177 iconst_2 (0, 4)
	178 iconst_2 (0, 4)
	179 newarray (0, 4)
	180 7 (0, 4)
	181 dup (0, 4)
	182 iconst_0 (0, 4)
	183 ldc2_w (0, 4)
	184 0.3999999761581421 (0, 4)
	186 dastore (0, 4)
	187 dup (0, 4)
	188 iconst_1 (0, 4)
	189 ldc2_w (0, 4)
	190 2.3841857910019882e-08 (0, 4)
	192 dastore (0, 4)
	193 aastore (0, 4)
	194 dup (0, 4)
	195 iconst_3 (0, 4)
	196 iconst_2 (0, 4)
	197 newarray (0, 4)
	198 7 (0, 4)
	199 dup (0, 4)
	200 iconst_0 (0, 4)
	201 ldc2_w (0, 4)
	202 0.2857142686843872 (0, 4)
	204 dastore (0, 4)
	205 dup (0, 4)
	206 iconst_1 (0, 4)
	207 ldc2_w (0, 4)
	208 1.7029898543501842e-08 (0, 4)
	210 dastore (0, 4)
	211 aastore (0, 4)
	212 dup (0, 4)
	213 iconst_4 (0, 4)
	214 iconst_2 (0, 4)
	215 newarray (0, 4)
	216 7 (0, 4)
	217 dup (0, 4)
	218 iconst_0 (0, 4)
	219 ldc2_w (0, 4)
	220 0.2222222089767456 (0, 4)
	222 dastore (0, 4)
	223 dup (0, 4)
	224 iconst_1 (0, 4)
	225 ldc2_w (0, 4)
	226 1.3245471311735498e-08 (0, 4)
	228 dastore (0, 4)
	229 aastore (0, 4)
	230 dup (0, 4)
	231 iconst_5 (0, 4)
	232 iconst_2 (0, 4)
	233 newarray (0, 4)
	234 7 (0, 4)
	235 dup (0, 4)
	236 iconst_0 (0, 4)
	237 ldc2_w (0, 4)
	238 0.1818181574344635 (0, 4)
	240 dastore (0, 4)
	241 dup (0, 4)
	242 iconst_1 (0, 4)
	243 ldc2_w (0, 4)
	244 2.4384203044354907e-08 (0, 4)
	246 dastore (0, 4)
	247 aastore (0, 4)
	248 dup (0, 4)
	249 bipush (0, 4)
	250 6 (0, 4)
	251 iconst_2 (0, 4)
	252 newarray (0, 4)
	253 7 (0, 4)
	254 dup (0, 4)
	255 iconst_0 (0, 4)
	256 ldc2_w (0, 4)
	257 0.1538461446762085 (0, 4)
	259 dastore (0, 4)
	260 dup (0, 4)
	261 iconst_1 (0, 4)
	262 ldc2_w (0, 4)
	263 9.140260083262505e-09 (0, 4)
	265 dastore (0, 4)
	266 aastore (0, 4)
	267 dup (0, 4)
	268 bipush (0, 4)
	269 7 (0, 4)
	270 iconst_2 (0, 4)
	271 newarray (0, 4)
	272 7 (0, 4)
	273 dup (0, 4)
	274 iconst_0 (0, 4)
	275 ldc2_w (0, 4)
	276 0.13333332538604736 (0, 4)
	278 dastore (0, 4)
	279 dup (0, 4)
	280 iconst_1 (0, 4)
	281 ldc2_w (0, 4)
	282 9.220590270857665e-09 (0, 4)
	284 dastore (0, 4)
	285 aastore (0, 4)
	286 dup (0, 4)
	287 bipush (0, 4)
	288 8 (0, 4)
	289 iconst_2 (0, 4)
	290 newarray (0, 4)
	291 7 (0, 4)
	292 dup (0, 4)
	293 iconst_0 (0, 4)
	294 ldc2_w (0, 4)
	295 0.11764700710773468 (0, 4)
	297 dastore (0, 4)
	298 dup (0, 4)
	299 iconst_1 (0, 4)
	300 ldc2_w (0, 4)
	301 1.2393345855018391e-08 (0, 4)
	303 dastore (0, 4)
	304 aastore (0, 4)
	305 dup (0, 4)
	306 bipush (0, 4)
	307 9 (0, 4)
	308 iconst_2 (0, 4)
	309 newarray (0, 4)
	310 7 (0, 4)
	311 dup (0, 4)
	312 iconst_0 (0, 4)
	313 ldc2_w (0, 4)
	314 0.10526403784751892 (0, 4)
	316 dastore (0, 4)
	317 dup (0, 4)
	318 iconst_1 (0, 4)
	319 ldc2_w (0, 4)
	320 8.251545029714408e-09 (0, 4)
	322 dastore (0, 4)
	323 aastore (0, 4)
	324 dup (0, 4)
	325 bipush (0, 4)
	326 10 (0, 4)
	327 iconst_2 (0, 4)
	328 newarray (0, 4)
	329 7 (0, 4)
	330 dup (0, 4)
	331 iconst_0 (0, 4)
	332 ldc2_w (0, 4)
	333 0.0952233225107193 (0, 4)
	335 dastore (0, 4)
	336 dup (0, 4)
	337 iconst_1 (0, 4)
	338 ldc2_w (0, 4)
	339 1.2675934823758863e-08 (0, 4)
	341 dastore (0, 4)
	342 aastore (0, 4)
	343 dup (0, 4)
	344 bipush (0, 4)
	345 11 (0, 4)
	346 iconst_2 (0, 4)
	347 newarray (0, 4)
	348 7 (0, 4)
	349 dup (0, 4)
	350 iconst_0 (0, 4)
	351 ldc2_w (0, 4)
	352 0.08713622391223907 (0, 4)
	354 dastore (0, 4)
	355 dup (0, 4)
	356 iconst_1 (0, 4)
	357 ldc2_w (0, 4)
	358 1.1430250008909141e-08 (0, 4)
	360 dastore (0, 4)
	361 aastore (0, 4)
	362 dup (0, 4)
	363 bipush (0, 4)
	364 12 (0, 4)
	365 iconst_2 (0, 4)
	366 newarray (0, 4)
	367 7 (0, 4)
	368 dup (0, 4)
	369 iconst_0 (0, 4)
	370 ldc2_w (0, 4)
	371 0.07842259109020233 (0, 4)
	373 dastore (0, 4)
	374 dup (0, 4)
	375 iconst_1 (0, 4)
	376 ldc2_w (0, 4)
	377 2.404307984052299e-09 (0, 4)
	379 dastore (0, 4)
	380 aastore (0, 4)
	381 dup (0, 4)
	382 bipush (0, 4)
	383 13 (0, 4)
	384 iconst_2 (0, 4)
	385 newarray (0, 4)
	386 7 (0, 4)
	387 dup (0, 4)
	388 iconst_0 (0, 4)
	389 ldc2_w (0, 4)
	390 0.08371849358081818 (0, 4)
	392 dastore (0, 4)
	393 dup (0, 4)
	394 iconst_1 (0, 4)
	395 ldc2_w (0, 4)
	396 1.176342548272881e-08 (0, 4)
	398 dastore (0, 4)
	399 aastore (0, 4)
	400 dup (0, 4)
	401 bipush (0, 4)
	402 14 (0, 4)
	403 iconst_2 (0, 4)
	404 newarray (0, 4)
	405 7 (0, 4)
	406 dup (0, 4)
	407 iconst_0 (0, 4)
	408 ldc2_w (0, 4)
	409 0.030589580535888672 (0, 4)
	411 dastore (0, 4)
	412 dup (0, 4)
	413 iconst_1 (0, 4)
	414 ldc2_w (0, 4)
	415 1.2958646899018938e-09 (0, 4)
	417 dastore (0, 4)
	418 aastore (0, 4)
	419 dup (0, 4)
	420 bipush (0, 4)
	421 15 (0, 4)
	422 iconst_2 (0, 4)
	423 newarray (0, 4)
	424 7 (0, 4)
	425 dup (0, 4)
	426 iconst_0 (0, 4)
	427 ldc2_w (0, 4)
	428 0.14982303977012634 (0, 4)
	430 dastore (0, 4)
	431 dup (0, 4)
	432 iconst_1 (0, 4)
	433 ldc2_w (0, 4)
	434 1.225743062930824e-08 (0, 4)
	436 dastore (0, 4)
	437 aastore (0, 4)
	438 putstatic (0, 4)
	439 org/apache/commons/math3/util/FastMathCalc.LN_SPLIT_COEF:[[D (0, 4)
	441 return (0, 4)

