Method: <init>
	0 aload_0 (0, 0)
	1 aload_1 (0, 0)
	2 putfield (0, 0)
	3 org/apache/commons/math3/util/Incrementor$2.val$incrementor:Lorg/apache/commons/math3/util/IntegerSequence$Incrementor; (0, 0)
	5 aload_0 (0, 0)
	6 invokespecial (0, 0)
	7 org/apache/commons/math3/util/Incrementor.<init>:()V (0, 0)
	9 aload_0 (0, 0)
	10 aload_0 (0, 0)
	11 getfield (0, 0)
	12 org/apache/commons/math3/util/Incrementor$2.val$incrementor:Lorg/apache/commons/math3/util/IntegerSequence$Incrementor; (0, 0)
	14 putfield (0, 0)
	15 org/apache/commons/math3/util/Incrementor$2.delegate:Lorg/apache/commons/math3/util/IntegerSequence$Incrementor; (0, 0)
	17 aload_0 (0, 0)
	18 aload_0 (0, 0)
	19 getfield (0, 0)
	20 org/apache/commons/math3/util/Incrementor$2.delegate:Lorg/apache/commons/math3/util/IntegerSequence$Incrementor; (0, 0)
	22 invokevirtual (0, 0)
	23 org/apache/commons/math3/util/IntegerSequence$Incrementor.getMaximalCount:()I (0, 0)
	25 invokespecial (0, 0)
	26 org/apache/commons/math3/util/Incrementor.setMaximalCount:(I)V (0, 0)
	28 aload_0 (0, 0)
	29 aload_0 (0, 0)
	30 getfield (0, 0)
	31 org/apache/commons/math3/util/Incrementor$2.delegate:Lorg/apache/commons/math3/util/IntegerSequence$Incrementor; (0, 0)
	33 invokevirtual (0, 0)
	34 org/apache/commons/math3/util/IntegerSequence$Incrementor.getCount:()I (0, 0)
	36 invokespecial (0, 0)
	37 org/apache/commons/math3/util/Incrementor.incrementCount:(I)V (0, 0)
	39 return (0, 0)

Method: setMaximalCount
	0 aload_0 (0, 0)
	1 iload_1 (0, 0)
	2 invokespecial (0, 0)
	3 org/apache/commons/math3/util/Incrementor.setMaximalCount:(I)V (0, 0)
	5 aload_0 (0, 0)
	6 aload_0 (0, 0)
	7 getfield (0, 0)
	8 org/apache/commons/math3/util/Incrementor$2.delegate:Lorg/apache/commons/math3/util/IntegerSequence$Incrementor; (0, 0)
	10 iload_1 (0, 0)
	11 invokevirtual (0, 0)
	12 org/apache/commons/math3/util/IntegerSequence$Incrementor.withMaximalCount:(I)Lorg/apache/commons/math3/util/IntegerSequence$Incrementor; (0, 0)
	14 putfield (0, 0)
	15 org/apache/commons/math3/util/Incrementor$2.delegate:Lorg/apache/commons/math3/util/IntegerSequence$Incrementor; (0, 0)
	17 return (0, 0)

Method: resetCount
	0 aload_0 (0, 0)
	1 invokespecial (0, 0)
	2 org/apache/commons/math3/util/Incrementor.resetCount:()V (0, 0)
	4 aload_0 (0, 0)
	5 aload_0 (0, 0)
	6 getfield (0, 0)
	7 org/apache/commons/math3/util/Incrementor$2.delegate:Lorg/apache/commons/math3/util/IntegerSequence$Incrementor; (0, 0)
	9 iconst_0 (0, 0)
	10 invokevirtual (0, 0)
	11 org/apache/commons/math3/util/IntegerSequence$Incrementor.withStart:(I)Lorg/apache/commons/math3/util/IntegerSequence$Incrementor; (0, 0)
	13 putfield (0, 0)
	14 org/apache/commons/math3/util/Incrementor$2.delegate:Lorg/apache/commons/math3/util/IntegerSequence$Incrementor; (0, 0)
	16 return (0, 0)

Method: incrementCount
	0 aload_0 (0, 0)
	1 invokespecial (0, 0)
	2 org/apache/commons/math3/util/Incrementor.incrementCount:()V (0, 0)
	4 aload_0 (0, 0)
	5 getfield (0, 0)
	6 org/apache/commons/math3/util/Incrementor$2.delegate:Lorg/apache/commons/math3/util/IntegerSequence$Incrementor; (0, 0)
	8 invokevirtual (0, 0)
	9 org/apache/commons/math3/util/IntegerSequence$Incrementor.increment:()V (0, 0)
	11 return (0, 0)

