Method: <init>
	0 aload_0 (0, 0)
	1 invokespecial (0, 0)
	2 java/lang/Object.<init>:()V (0, 0)
	4 aload_0 (0, 0)
	5 iconst_0 (0, 0)
	6 putfield (0, 0)
	7 org/apache/commons/math3/util/Incrementor.count:I (0, 0)
	9 aload_2 (3, 1)
	10 ifnonnull (3, 1)
	11 11 (3, 1)
	13 new (3, 1)
	14 org/apache/commons/math3/exception/NullArgumentException (3, 1)
	16 dup (3, 1)
	17 invokespecial (3, 1)
	18 org/apache/commons/math3/exception/NullArgumentException.<init>:()V (3, 1)
	20 athrow (3, 1)
	21 aload_0 (1, 1)
	22 iload_1 (1, 1)
	23 putfield (1, 1)
	24 org/apache/commons/math3/util/Incrementor.maximalCount:I (1, 1)
	26 aload_0 (1, 1)
	27 aload_2 (1, 1)
	28 putfield (1, 1)
	29 org/apache/commons/math3/util/Incrementor.maxCountCallback:Lorg/apache/commons/math3/util/Incrementor$MaxCountExceededCallback; (1, 1)
	31 return (1, 1)

Method: setMaximalCount
	0 aload_0 (0, 0)
	1 iload_1 (0, 0)
	2 putfield (0, 0)
	3 org/apache/commons/math3/util/Incrementor.maximalCount:I (0, 0)
	5 return (0, 0)

Method: getMaximalCount
	0 aload_0 (0, 0)
	1 getfield (0, 0)
	2 org/apache/commons/math3/util/Incrementor.maximalCount:I (0, 0)
	4 ireturn (0, 0)

Method: getCount
	0 aload_0 (0, 0)
	1 getfield (0, 0)
	2 org/apache/commons/math3/util/Incrementor.count:I (0, 0)
	4 ireturn (0, 0)

Method: canIncrement
	0 aload_0 (0, 0)
	1 getfield (0, 0)
	2 org/apache/commons/math3/util/Incrementor.count:I (0, 0)
	4 aload_0 (0, 0)
	5 getfield (0, 0)
	6 org/apache/commons/math3/util/Incrementor.maximalCount:I (0, 0)
	8 if_icmpge (0, 0)
	9 7 (0, 0)
	11 iconst_1 (0, 0)
	12 goto (0, 0)
	13 4 (0, 0)
	15 iconst_0 (0, 0)
	16 ireturn (0, 0)

Method: incrementCount
	0 aload_0 (1, 1)
	1 dup (1, 1)
	2 getfield (1, 1)
	3 org/apache/commons/math3/util/Incrementor.count:I (1, 1)
	5 iconst_1 (1, 1)
	6 iadd (1, 1)
	7 dup_x1 (1, 1)
	8 putfield (1, 1)
	9 org/apache/commons/math3/util/Incrementor.count:I (1, 1)
	11 aload_0 (1, 1)
	12 getfield (1, 1)
	13 org/apache/commons/math3/util/Incrementor.maximalCount:I (1, 1)
	15 if_icmple (1, 1)
	16 16 (1, 1)
	18 aload_0 (1, 1)
	19 getfield (1, 1)
	20 org/apache/commons/math3/util/Incrementor.maxCountCallback:Lorg/apache/commons/math3/util/Incrementor$MaxCountExceededCallback; (1, 1)
	22 aload_0 (1, 1)
	23 getfield (1, 1)
	24 org/apache/commons/math3/util/Incrementor.maximalCount:I (1, 1)
	26 invokeinterface (1, 1)
	27 org/apache/commons/math3/util/Incrementor$MaxCountExceededCallback.org/apache/commons/math3/util/Incrementor$2 (1, 1)
	29 0 (1, 1)
	31 return (0, 0)

Method: resetCount
	0 aload_0 (0, 0)
	1 iconst_0 (0, 0)
	2 putfield (0, 0)
	3 org/apache/commons/math3/util/Incrementor.count:I (0, 0)
	5 return (0, 0)

Method: wrap
	0 new (0, 0)
	1 org/apache/commons/math3/util/Incrementor$2 (0, 0)
	3 dup (0, 0)
	4 aload_0 (0, 0)
	5 invokespecial (0, 0)
	6 org/apache/commons/math3/util/Incrementor$2.<init>:(Lorg/apache/commons/math3/util/IntegerSequence$Incrementor;)V (0, 0)
	8 areturn (0, 0)

