Method: <init>
	0 aload_0 (0, 0)
	1 invokespecial (0, 0)
	2 java/lang/Object.<init>:()V (0, 0)
	4 aload_0 (0, 0)
	5 iload_1 (0, 0)
	6 putfield (0, 0)
	7 org/apache/commons/math3/util/IntegerSequence$Range.start:I (0, 0)
	9 aload_0 (0, 0)
	10 iload_2 (0, 0)
	11 putfield (0, 0)
	12 org/apache/commons/math3/util/IntegerSequence$Range.max:I (0, 0)
	14 aload_0 (0, 0)
	15 iload_3 (0, 0)
	16 putfield (0, 0)
	17 org/apache/commons/math3/util/IntegerSequence$Range.step:I (0, 0)
	19 iload_2 (0, 0)
	20 iload_1 (0, 0)
	21 isub (0, 0)
	22 iload_3 (0, 0)
	23 idiv (0, 0)
	24 iconst_1 (0, 0)
	25 iadd (0, 0)
	26 istore (0, 0)
	27 #4 (0, 0)
	28 aload_0 (0, 0)
	29 iload (0, 0)
	30 #4 (0, 0)
	31 ifge (0, 0)
	32 7 (0, 0)
	34 iconst_0 (0, 0)
	35 goto (0, 0)
	36 5 (0, 0)
	38 iload (0, 0)
	39 #4 (0, 0)
	40 putfield (0, 0)
	41 org/apache/commons/math3/util/IntegerSequence$Range.size:I (0, 0)
	43 return (0, 0)

Method: size
	0 aload_0 (0, 0)
	1 getfield (0, 0)
	2 org/apache/commons/math3/util/IntegerSequence$Range.size:I (0, 0)
	4 ireturn (0, 0)

Method: iterator
	0 invokestatic (0, 0)
	1 org/apache/commons/math3/util/IntegerSequence$Incrementor.create:()Lorg/apache/commons/math3/util/IntegerSequence$Incrementor; (0, 0)
	3 aload_0 (0, 0)
	4 getfield (0, 0)
	5 org/apache/commons/math3/util/IntegerSequence$Range.start:I (0, 0)
	7 invokevirtual (0, 0)
	8 org/apache/commons/math3/util/IntegerSequence$Incrementor.withStart:(I)Lorg/apache/commons/math3/util/IntegerSequence$Incrementor; (0, 0)
	10 aload_0 (0, 0)
	11 getfield (0, 0)
	12 org/apache/commons/math3/util/IntegerSequence$Range.max:I (0, 0)
	14 aload_0 (0, 0)
	15 getfield (0, 0)
	16 org/apache/commons/math3/util/IntegerSequence$Range.step:I (0, 0)
	18 ifle (0, 0)
	19 7 (0, 0)
	21 iconst_1 (0, 0)
	22 goto (0, 0)
	23 4 (0, 0)
	25 iconst_m1 (0, 0)
	26 iadd (0, 0)
	27 invokevirtual (0, 0)
	28 org/apache/commons/math3/util/IntegerSequence$Incrementor.withMaximalCount:(I)Lorg/apache/commons/math3/util/IntegerSequence$Incrementor; (0, 0)
	30 aload_0 (0, 0)
	31 getfield (0, 0)
	32 org/apache/commons/math3/util/IntegerSequence$Range.step:I (0, 0)
	34 invokevirtual (0, 0)
	35 org/apache/commons/math3/util/IntegerSequence$Incrementor.withIncrement:(I)Lorg/apache/commons/math3/util/IntegerSequence$Incrementor; (0, 0)
	37 areturn (0, 0)

