Method: <init>
	0 aload_0 (0, 0)
	1 invokespecial (0, 0)
	4 aload_0 (0, 0)
	5 invokestatic (0, 0)
	8 iload_1 (0, 0)
	9 invokevirtual (0, 0)
	12 aload_2 (0, 0)
	13 invokevirtual (0, 0)
	16 putfield (0, 0)
	19 aload_0 (0, 0)
	20 new (0, 0)
	23 dup (0, 0)
	24 invokespecial (0, 0)
	27 putfield (0, 0)
	30 return (0, 0)

Method: addIterationListener
	0 aload_0 (0, 0)
	1 getfield (0, 0)
	4 aload_1 (0, 0)
	5 invokeinterface (0, 0)
	10 pop (0, 0)
	11 return (0, 0)

Method: fireInitializationEvent
	0 aload_0 (1, 4)
	1 getfield (1, 4)
	4 invokeinterface (1, 4)
	9 astore_2 (1, 4)
	10 aload_2 (1, 4)
	11 invokeinterface (1, 4)
	16 ifeq (1, 4)
	19 aload_2 (1, 4)
	20 invokeinterface (1, 4)
	25 checkcast (1, 4)
	28 astore_3 (1, 4)
	29 aload_3 (1, 4)
	30 aload_1 (1, 4)
	31 invokeinterface (1, 4)
	36 goto (0, 4)
	39 return (0, 0)

Method: fireIterationPerformedEvent
	0 aload_0 (1, 4)
	1 getfield (1, 4)
	4 invokeinterface (1, 4)
	9 astore_2 (1, 4)
	10 aload_2 (1, 4)
	11 invokeinterface (1, 4)
	16 ifeq (1, 4)
	19 aload_2 (1, 4)
	20 invokeinterface (1, 4)
	25 checkcast (1, 4)
	28 astore_3 (1, 4)
	29 aload_3 (1, 4)
	30 aload_1 (1, 4)
	31 invokeinterface (1, 4)
	36 goto (0, 4)
	39 return (0, 0)

Method: fireIterationStartedEvent
	0 aload_0 (1, 4)
	1 getfield (1, 4)
	4 invokeinterface (1, 4)
	9 astore_2 (1, 4)
	10 aload_2 (1, 4)
	11 invokeinterface (1, 4)
	16 ifeq (1, 4)
	19 aload_2 (1, 4)
	20 invokeinterface (1, 4)
	25 checkcast (1, 4)
	28 astore_3 (1, 4)
	29 aload_3 (1, 4)
	30 aload_1 (1, 4)
	31 invokeinterface (1, 4)
	36 goto (0, 0)
	39 return (0, 0)

Method: fireTerminationEvent
	0 aload_0 (1, 4)
	1 getfield (1, 4)
	4 invokeinterface (1, 4)
	9 astore_2 (1, 4)
	10 aload_2 (1, 4)
	11 invokeinterface (1, 4)
	16 ifeq (1, 4)
	19 aload_2 (1, 4)
	20 invokeinterface (1, 4)
	25 checkcast (1, 4)
	28 astore_3 (1, 4)
	29 aload_3 (1, 4)
	30 aload_1 (1, 4)
	31 invokeinterface (1, 4)
	36 goto (0, 4)
	39 return (0, 0)

Method: getIterations
	0 aload_0 (0, 0)
	1 getfield (0, 0)
	4 invokevirtual (0, 0)
	7 ireturn (0, 0)

Method: getMaxIterations
	0 aload_0 (0, 0)
	1 getfield (0, 0)
	4 invokevirtual (0, 0)
	7 ireturn (0, 0)

Method: incrementIterationCount
	0 aload_0 (0, 0)
	1 getfield (0, 0)
	4 invokevirtual (0, 0)
	7 return (0, 0)

Method: removeIterationListener
	0 aload_0 (0, 0)
	1 getfield (0, 0)
	4 aload_1 (0, 0)
	5 invokeinterface (0, 0)
	10 pop (0, 0)
	11 return (0, 0)

Method: resetIterationCount
	0 aload_0 (0, 0)
	1 aload_0 (0, 0)
	2 getfield (0, 0)
	5 iconst_0 (0, 0)
	6 invokevirtual (0, 0)
	9 putfield (0, 0)
	12 return (0, 0)

