Method: <init>
	0 aload_0 (0, 0)
	1 invokespecial (0, 0)
	2 java/lang/Object.<init>:()V (0, 0)
	4 aload_1 (0, 0)
	5 invokestatic (0, 0)
	6 org/apache/commons/math3/util/MathUtils.checkNotNull:(Ljava/lang/Object;)V (0, 0)
	8 aload_0 (0, 0)
	9 aload_1 (0, 0)
	10 putfield (0, 0)
	11 org/apache/commons/math3/util/KthSelector.pivotingStrategy:Lorg/apache/commons/math3/util/PivotingStrategyInterface; (0, 0)
	13 return (0, 0)

Method: getPivotingStrategy
	0 aload_0 (0, 0)
	1 getfield (0, 0)
	2 org/apache/commons/math3/util/KthSelector.pivotingStrategy:Lorg/apache/commons/math3/util/PivotingStrategyInterface; (0, 0)
	4 areturn (0, 0)

Method: select
	0 iconst_0 (0, 0)
	1 istore (0, 0)
	2 #4 (0, 0)
	3 aload_1 (0, 0)
	4 arraylength (0, 0)
	5 istore (0, 0)
	6 #5 (0, 0)
	7 iconst_0 (0, 0)
	8 istore (0, 0)
	9 #6 (0, 0)
	10 aload_2 (0, 0)
	11 ifnull (0, 0)
	12 7 (0, 0)
	14 iconst_1 (0, 0)
	15 goto (0, 0)
	16 4 (0, 0)
	18 iconst_0 (0, 0)
	19 istore (0, 0)
	20 #7 (0, 0)
	21 iload (1, 3)
	22 #5 (1, 3)
	23 iload (1, 3)
	24 #4 (1, 3)
	25 isub (1, 3)
	26 bipush (1, 3)
	27 15 (1, 3)
	28 if_icmple (1, 3)
	29 152 (1, 3)
	31 iload (1, 1)
	32 #7 (1, 1)
	33 ifeq (1, 1)
	34 26 (1, 1)
	36 iload (1, 1)
	37 #6 (1, 1)
	38 aload_2 (1, 1)
	39 arraylength (1, 1)
	40 if_icmpge (1, 1)
	41 19 (1, 1)
	43 aload_2 (1, 1)
	44 iload (1, 1)
	45 #6 (1, 1)
	46 iaload (1, 1)
	47 iflt (1, 1)
	48 12 (1, 1)
	50 aload_2 (1, 1)
	51 iload (1, 1)
	52 #6 (1, 1)
	53 iaload (1, 1)
	54 istore (1, 1)
	55 #8 (1, 1)
	56 goto (1, 1)
	57 46 (1, 1)
	59 aload_0 (2, 2)
	60 aload_1 (2, 2)
	61 iload (2, 2)
	62 #4 (2, 2)
	63 iload (2, 2)
	64 #5 (2, 2)
	65 aload_0 (2, 2)
	66 getfield (2, 2)
	67 org/apache/commons/math3/util/KthSelector.pivotingStrategy:Lorg/apache/commons/math3/util/PivotingStrategyInterface; (2, 2)
	69 aload_1 (2, 2)
	70 iload (2, 2)
	71 #4 (2, 2)
	72 iload (2, 2)
	73 #5 (2, 2)
	74 invokeinterface (2, 2)
	75 org/apache/commons/math3/util/PivotingStrategyInterface.partition:([DIII)I (2, 2)
	77 0 (2, 2)
	79 invokespecial (2, 2)
	80 org/apache/commons/math3/util/KthSelector.partition:([DIII)I (2, 2)
	82 istore (2, 2)
	83 #8 (2, 2)
	84 iload (3, 1)
	85 #7 (3, 1)
	86 ifeq (3, 1)
	87 16 (3, 1)
	89 iload (3, 1)
	90 #6 (3, 1)
	91 aload_2 (3, 1)
	92 arraylength (3, 1)
	93 if_icmpge (3, 1)
	94 9 (3, 1)
	96 aload_2 (3, 1)
	97 iload (3, 1)
	98 #6 (3, 1)
	99 iload (3, 1)
	100 #8 (3, 1)
	101 iastore (3, 1)
	102 iload_3 (2, 1)
	103 iload (2, 1)
	104 #8 (2, 1)
	105 if_icmpne (2, 1)
	106 7 (2, 1)
	108 aload_1 (2, 1)
	109 iload_3 (2, 1)
	110 daload (2, 1)
	111 dreturn (2, 1)
	112 iload_3 (2, 1)
	113 iload (2, 1)
	114 #8 (2, 1)
	115 if_icmpge (2, 1)
	116 33 (2, 1)
	118 iload (2, 1)
	119 #8 (2, 1)
	120 istore (2, 1)
	121 #5 (2, 1)
	122 iconst_2 (2, 1)
	123 iload (2, 1)
	124 #6 (2, 1)
	125 imul (2, 1)
	126 iconst_1 (2, 1)
	127 iadd (2, 1)
	128 iload (2, 1)
	129 #7 (2, 1)
	130 ifeq (2, 1)
	131 8 (2, 1)
	133 aload_2 (2, 1)
	134 arraylength (2, 1)
	135 goto (2, 1)
	136 5 (2, 1)
	138 iload (2, 1)
	139 #5 (2, 1)
	140 invokestatic (2, 1)
	141 org/apache/commons/math3/util/FastMath.min:(II)I (2, 1)
	143 istore (2, 1)
	144 #6 (2, 1)
	145 goto (2, 1)
	146 32 (2, 1)
	148 iload (2, 2)
	149 #8 (2, 2)
	150 iconst_1 (2, 2)
	151 iadd (2, 2)
	152 istore (2, 2)
	153 #4 (2, 2)
	154 iconst_2 (2, 2)
	155 iload (2, 2)
	156 #6 (2, 2)
	157 imul (2, 2)
	158 iconst_2 (2, 2)
	159 iadd (2, 2)
	160 iload (2, 2)
	161 #7 (2, 2)
	162 ifeq (2, 2)
	163 8 (2, 2)
	165 aload_2 (2, 2)
	166 arraylength (2, 2)
	167 goto (2, 2)
	168 5 (2, 2)
	170 iload (2, 2)
	171 #5 (2, 2)
	172 invokestatic (2, 2)
	173 org/apache/commons/math3/util/FastMath.min:(II)I (2, 2)
	175 istore (2, 2)
	176 #6 (2, 2)
	177 goto (0, 0)
	178 -156 (0, 0)
	180 aload_1 (0, 0)
	181 iload (0, 0)
	182 #4 (0, 0)
	183 iload (0, 0)
	184 #5 (0, 0)
	185 invokestatic (0, 0)
	186 java/util/Arrays.sort:([DII)V (0, 0)
	188 aload_1 (0, 0)
	189 iload_3 (0, 0)
	190 daload (0, 0)
	191 dreturn (0, 0)

Method: partition
	0 aload_1 (0, 0)
	1 iload (0, 0)
	2 #4 (0, 0)
	3 daload (0, 0)
	4 dstore (0, 0)
	5 #5 (0, 0)
	6 aload_1 (0, 0)
	7 iload (0, 0)
	8 #4 (0, 0)
	9 aload_1 (0, 0)
	10 iload_2 (0, 0)
	11 daload (0, 0)
	12 dastore (0, 0)
	13 iload_2 (0, 0)
	14 iconst_1 (0, 0)
	15 iadd (0, 0)
	16 istore (0, 0)
	17 #7 (0, 0)
	18 iload_3 (0, 0)
	19 iconst_1 (0, 0)
	20 isub (0, 0)
	21 istore (0, 0)
	22 #8 (0, 0)
	23 iload (1, 3)
	24 #7 (1, 3)
	25 iload (1, 3)
	26 #8 (1, 3)
	27 if_icmpge (1, 3)
	28 85 (1, 3)
	30 iload (2, 3)
	31 #7 (2, 3)
	32 iload (2, 3)
	33 #8 (2, 3)
	34 if_icmpge (2, 3)
	35 19 (2, 3)
	37 aload_1 (2, 3)
	38 iload (2, 3)
	39 #8 (2, 3)
	40 daload (2, 3)
	41 dload (2, 3)
	42 #5 (2, 3)
	43 dcmpl (2, 3)
	44 ifle (2, 3)
	45 9 (2, 3)
	47 iinc (2, 3)
	48 #8 (2, 3)
	49 -89 (2, 3)
	50 goto (2, 3)
	51 -20 (2, 3)
	53 iload (2, 3)
	54 #7 (2, 3)
	55 iload (2, 3)
	56 #8 (2, 3)
	57 if_icmpge (2, 3)
	58 19 (2, 3)
	60 aload_1 (2, 3)
	61 iload (2, 3)
	62 #7 (2, 3)
	63 daload (2, 3)
	64 dload (2, 3)
	65 #5 (2, 3)
	66 dcmpg (2, 3)
	67 ifge (2, 3)
	68 9 (2, 3)
	70 iinc (2, 3)
	71 #7 (2, 3)
	72 -89 (2, 3)
	73 goto (2, 3)
	74 -20 (2, 3)
	76 iload (2, 1)
	77 #7 (2, 1)
	78 iload (2, 1)
	79 #8 (2, 1)
	80 if_icmpge (2, 1)
	81 -57 (2, 1)
	83 aload_1 (2, 1)
	84 iload (2, 1)
	85 #7 (2, 1)
	86 daload (2, 1)
	87 dstore (2, 1)
	88 #9 (2, 1)
	89 aload_1 (2, 1)
	90 iload (2, 1)
	91 #7 (2, 1)
	92 iinc (2, 1)
	93 #7 (2, 1)
	94 43 (2, 1)
	95 aload_1 (2, 1)
	96 iload (2, 1)
	97 #8 (2, 1)
	98 daload (2, 1)
	99 dastore (2, 1)
	100 aload_1 (2, 1)
	101 iload (2, 1)
	102 #8 (2, 1)
	103 iinc (2, 1)
	104 #8 (2, 1)
	105 24 (2, 1)
	106 dload (2, 1)
	107 #9 (2, 1)
	108 dastore (2, 1)
	109 goto (1, 3)
	110 -86 (1, 3)
	112 iload (1, 1)
	113 #7 (1, 1)
	114 iload_3 (1, 1)
	115 if_icmpge (1, 1)
	116 13 (1, 1)
	118 aload_1 (1, 1)
	119 iload (1, 1)
	120 #7 (1, 1)
	121 daload (1, 1)
	122 dload (1, 1)
	123 #5 (1, 1)
	124 dcmpl (1, 1)
	125 ifle (1, 1)
	126 6 (1, 1)
	128 iinc (1, 1)
	129 #7 (1, 1)
	130 43 (1, 1)
	131 aload_1 (0, 0)
	132 iload_2 (0, 0)
	133 aload_1 (0, 0)
	134 iload (0, 0)
	135 #7 (0, 0)
	136 daload (0, 0)
	137 dastore (0, 0)
	138 aload_1 (0, 0)
	139 iload (0, 0)
	140 #7 (0, 0)
	141 dload (0, 0)
	142 #5 (0, 0)
	143 dastore (0, 0)
	144 iload (0, 0)
	145 #7 (0, 0)
	146 ireturn (0, 0)

