Method: hash
	0 aload_0 (0, 0)
	1 invokestatic (0, 0)
	2 java/util/Arrays.hashCode:([D)I (0, 0)
	4 ireturn (0, 0)

Method: equals
	0 new (0, 0)
	1 java/lang/Double (0, 0)
	3 dup (0, 0)
	4 dload_0 (0, 0)
	5 invokespecial (0, 0)
	6 java/lang/Double.<init>:(D)V (0, 0)
	8 new (0, 0)
	9 java/lang/Double (0, 0)
	11 dup (0, 0)
	12 dload_2 (0, 0)
	13 invokespecial (0, 0)
	14 java/lang/Double.<init>:(D)V (0, 0)
	16 invokevirtual (0, 0)
	17 java/lang/Double.equals:(Ljava/lang/Object;)Z (0, 0)
	19 ireturn (0, 0)

Method: normalizeAngle
	0 dload_0 (0, 0)
	1 ldc2_w (0, 0)
	2 6.283185307179586 (0, 0)
	4 dload_0 (0, 0)
	5 ldc2_w (0, 0)
	6 3.141592653589793 (0, 0)
	8 dadd (0, 0)
	9 dload_2 (0, 0)
	10 dsub (0, 0)
	11 ldc2_w (0, 0)
	12 6.283185307179586 (0, 0)
	14 ddiv (0, 0)
	15 invokestatic (0, 0)
	16 org/apache/commons/math3/util/FastMath.floor:(D)D (0, 0)
	18 dmul (0, 0)
	19 dsub (0, 0)
	20 dreturn (0, 0)

Method: max
	0 aload_0 (0, 0)
	1 aload_1 (0, 0)
	2 invokeinterface (0, 0)
	3 org/apache/commons/math3/RealFieldElement.org/apache/commons/math3/RealFieldElement (0, 0)
	5 0 (0, 0)
	7 checkcast (0, 0)
	8 org/apache/commons/math3/RealFieldElement (0, 0)
	10 invokeinterface (0, 0)
	11 org/apache/commons/math3/RealFieldElement.abs:(D)D (0, 0)
	13 0 (0, 0)
	15 dconst_0 (0, 0)
	16 dcmpl (0, 0)
	17 iflt (0, 0)
	18 7 (0, 0)
	20 aload_0 (0, 0)
	21 goto (0, 0)
	22 4 (0, 0)
	24 aload_1 (0, 0)
	25 areturn (0, 0)

Method: min
	0 aload_0 (0, 0)
	1 aload_1 (0, 0)
	2 invokeinterface (0, 0)
	3 org/apache/commons/math3/RealFieldElement.org/apache/commons/math3/RealFieldElement (0, 0)
	5 0 (0, 0)
	7 checkcast (0, 0)
	8 org/apache/commons/math3/RealFieldElement (0, 0)
	10 invokeinterface (0, 0)
	11 org/apache/commons/math3/RealFieldElement.abs:(D)D (0, 0)
	13 0 (0, 0)
	15 dconst_0 (0, 0)
	16 dcmpl (0, 0)
	17 iflt (0, 0)
	18 7 (0, 0)
	20 aload_1 (0, 0)
	21 goto (0, 0)
	22 4 (0, 0)
	24 aload_0 (0, 0)
	25 areturn (0, 0)

Method: reduce
	0 dload_2 (0, 0)
	1 invokestatic (0, 0)
	2 org/apache/commons/math3/util/FastMath.abs:(D)D (0, 0)
	4 dstore (0, 0)
	5 #6 (0, 0)
	6 dload_0 (0, 0)
	7 dload (0, 0)
	8 #6 (0, 0)
	9 dload_0 (0, 0)
	10 dload (0, 0)
	11 #4 (0, 0)
	12 dsub (0, 0)
	13 dload (0, 0)
	14 #6 (0, 0)
	15 ddiv (0, 0)
	16 invokestatic (0, 0)
	17 org/apache/commons/math3/util/FastMath.floor:(D)D (0, 0)
	19 dmul (0, 0)
	20 dsub (0, 0)
	21 dload (0, 0)
	22 #4 (0, 0)
	23 dsub (0, 0)
	24 dreturn (0, 0)

Method: copySign
	0 lload_0 (1, 1)
	1 lconst_0 (1, 1)
	2 lcmp (1, 1)
	3 iflt (1, 1)
	4 9 (1, 1)
	6 lload_2 (1, 1)
	7 lconst_0 (1, 1)
	8 lcmp (1, 1)
	9 ifge (1, 1)
	10 15 (1, 1)
	12 lload_0 (1, 1)
	13 lconst_0 (1, 1)
	14 lcmp (1, 1)
	15 ifge (1, 1)
	16 11 (1, 1)
	18 lload_2 (1, 1)
	19 lconst_0 (1, 1)
	20 lcmp (1, 1)
	21 ifge (1, 1)
	22 5 (1, 1)
	24 lload_0 (1, 1)
	25 lreturn (1, 1)
	26 lload_2 (2, 1)
	27 lconst_0 (2, 1)
	28 lcmp (2, 1)
	29 iflt (2, 1)
	30 26 (2, 1)
	32 lload_0 (2, 1)
	33 ldc2_w (2, 1)
	34 9223372036854775808 (2, 1)
	36 lcmp (2, 1)
	37 ifne (2, 1)
	38 18 (2, 1)
	40 new (2, 1)
	41 org/apache/commons/math3/exception/MathArithmeticException (2, 1)
	43 dup (2, 1)
	44 getstatic (2, 1)
	45 org/apache/commons/math3/exception/util/LocalizedFormats.OVERFLOW:Lorg/apache/commons/math3/exception/util/LocalizedFormats; (2, 1)
	47 iconst_0 (2, 1)
	48 anewarray (2, 1)
	49 java/lang/Object (2, 1)
	51 invokespecial (2, 1)
	52 org/apache/commons/math3/exception/MathArithmeticException.<init>:(Lorg/apache/commons/math3/exception/util/Localizable;[Ljava/lang/Object;)V (2, 1)
	54 athrow (2, 1)
	55 lload_0 (3, 2)
	56 lneg (3, 2)
	57 lreturn (1, 2)

Method: checkFinite
	0 iconst_0 (1, 4)
	1 istore_1 (1, 4)
	2 iload_1 (1, 4)
	3 aload_0 (1, 4)
	4 arraylength (1, 4)
	5 if_icmpge (1, 4)
	6 53 (1, 4)
	8 aload_0 (1, 4)
	9 iload_1 (1, 4)
	10 daload (1, 4)
	11 dstore_2 (1, 4)
	12 dload_2 (2, 1)
	13 invokestatic (2, 1)
	14 java/lang/Double.isInfinite:(D)Z (2, 1)
	16 ifne (2, 1)
	17 10 (2, 1)
	19 dload_2 (2, 1)
	20 invokestatic (2, 1)
	21 java/lang/Double.isNaN:(D)Z (2, 1)
	23 ifeq (2, 1)
	24 29 (2, 1)
	26 new (2, 1)
	27 org/apache/commons/math3/exception/NotFiniteNumberException (2, 1)
	29 dup (2, 1)
	30 getstatic (2, 1)
	31 org/apache/commons/math3/exception/util/LocalizedFormats.ARRAY_ELEMENT:Lorg/apache/commons/math3/exception/util/LocalizedFormats; (2, 1)
	33 dload_2 (2, 1)
	34 invokestatic (2, 1)
	35 java/lang/Double.valueOf:(D)Ljava/lang/Double; (2, 1)
	37 iconst_1 (2, 1)
	38 anewarray (2, 1)
	39 java/lang/Object (2, 1)
	41 dup (2, 1)
	42 iconst_0 (2, 1)
	43 iload_1 (2, 1)
	44 invokestatic (2, 1)
	45 java/lang/Integer.valueOf:(I)Ljava/lang/Integer; (2, 1)
	47 aastore (2, 1)
	48 invokespecial (2, 1)
	49 org/apache/commons/math3/exception/NotFiniteNumberException.<init>:(Lorg/apache/commons/math3/exception/util/Localizable;Ljava/lang/Number;[Ljava/lang/Object;)V (2, 1)
	51 athrow (2, 1)
	52 iinc (2, 1)
	53 #1 (2, 1)
	54 -89 (2, 1)
	55 goto (2, 1)
	56 -53 (2, 1)
	58 return (0, 0)

Method: checkNotNull
	0 aload_0 (1, 1)
	1 ifnonnull (1, 1)
	2 11 (1, 1)
	4 new (1, 1)
	5 org/apache/commons/math3/exception/NullArgumentException (1, 1)
	7 dup (1, 1)
	8 invokespecial (1, 1)
	9 org/apache/commons/math3/exception/NullArgumentException.<init>:()V (1, 1)
	11 athrow (1, 1)
	12 return (0, 0)

