Method: scale
	0 aload_2 (0, 0)
	1 arraylength (0, 0)
	2 newarray (0, 0)
	4 astore_3 (0, 0)
	5 iconst_0 (1, 4)
	6 istore (1, 4)
	8 iload (1, 4)
	10 aload_2 (1, 4)
	11 arraylength (1, 4)
	12 if_icmpge (1, 4)
	15 aload_3 (1, 4)
	16 iload (1, 4)
	18 aload_2 (1, 4)
	19 iload (1, 4)
	21 daload (1, 4)
	22 dload_0 (1, 4)
	23 dmul (1, 4)
	24 dastore (1, 4)
	25 iinc (1, 4)
	28 goto (1, 4)
	31 aload_3 (0, 0)
	32 areturn (0, 0)

Method: scaleInPlace
	0 iconst_0 (1, 4)
	1 istore_3 (1, 4)
	2 iload_3 (1, 4)
	3 aload_2 (1, 4)
	4 arraylength (1, 4)
	5 if_icmpge (1, 4)
	8 aload_2 (1, 4)
	9 iload_3 (1, 4)
	10 dup2 (1, 4)
	11 daload (1, 4)
	12 dload_0 (1, 4)
	13 dmul (1, 4)
	14 dastore (1, 4)
	15 iinc (1, 4)
	18 goto (1, 4)
	21 return (0, 0)

Method: ebeAdd
	0 aload_0 (0, 0)
	1 aload_1 (0, 0)
	2 invokestatic (0, 0)
	5 aload_0 (0, 0)
	6 invokevirtual (0, 0)
	9 checkcast (0, 0)
	12 astore_2 (0, 0)
	13 iconst_0 (1, 4)
	14 istore_3 (1, 4)
	15 iload_3 (1, 4)
	16 aload_0 (1, 4)
	17 arraylength (1, 4)
	18 if_icmpge (1, 4)
	21 aload_2 (1, 4)
	22 iload_3 (1, 4)
	23 dup2 (1, 4)
	24 daload (1, 4)
	25 aload_1 (1, 4)
	26 iload_3 (1, 4)
	27 daload (1, 4)
	28 dadd (1, 4)
	29 dastore (1, 4)
	30 iinc (1, 4)
	33 goto (1, 4)
	36 aload_2 (0, 0)
	37 areturn (0, 0)

Method: ebeSubtract
	0 aload_0 (0, 0)
	1 aload_1 (0, 0)
	2 invokestatic (0, 0)
	5 aload_0 (0, 0)
	6 invokevirtual (0, 0)
	9 checkcast (0, 0)
	12 astore_2 (0, 0)
	13 iconst_0 (1, 4)
	14 istore_3 (1, 4)
	15 iload_3 (1, 4)
	16 aload_0 (1, 4)
	17 arraylength (1, 4)
	18 if_icmpge (1, 4)
	21 aload_2 (1, 4)
	22 iload_3 (1, 4)
	23 dup2 (1, 4)
	24 daload (1, 4)
	25 aload_1 (1, 4)
	26 iload_3 (1, 4)
	27 daload (1, 4)
	28 dsub (1, 4)
	29 dastore (1, 4)
	30 iinc (1, 4)
	33 goto (1, 4)
	36 aload_2 (0, 0)
	37 areturn (0, 0)

Method: ebeMultiply
	0 aload_0 (0, 0)
	1 aload_1 (0, 0)
	2 invokestatic (0, 0)
	5 aload_0 (0, 0)
	6 invokevirtual (0, 0)
	9 checkcast (0, 0)
	12 astore_2 (0, 0)
	13 iconst_0 (1, 4)
	14 istore_3 (1, 4)
	15 iload_3 (1, 4)
	16 aload_0 (1, 4)
	17 arraylength (1, 4)
	18 if_icmpge (1, 4)
	21 aload_2 (1, 4)
	22 iload_3 (1, 4)
	23 dup2 (1, 4)
	24 daload (1, 4)
	25 aload_1 (1, 4)
	26 iload_3 (1, 4)
	27 daload (1, 4)
	28 dmul (1, 4)
	29 dastore (1, 4)
	30 iinc (1, 4)
	33 goto (1, 4)
	36 aload_2 (0, 0)
	37 areturn (0, 0)

Method: ebeDivide
	0 aload_0 (0, 0)
	1 aload_1 (0, 0)
	2 invokestatic (0, 0)
	5 aload_0 (0, 0)
	6 invokevirtual (0, 0)
	9 checkcast (0, 0)
	12 astore_2 (0, 0)
	13 iconst_0 (1, 4)
	14 istore_3 (1, 4)
	15 iload_3 (1, 4)
	16 aload_0 (1, 4)
	17 arraylength (1, 4)
	18 if_icmpge (1, 4)
	21 aload_2 (1, 4)
	22 iload_3 (1, 4)
	23 dup2 (1, 4)
	24 daload (1, 4)
	25 aload_1 (1, 4)
	26 iload_3 (1, 4)
	27 daload (1, 4)
	28 ddiv (1, 4)
	29 dastore (1, 4)
	30 iinc (1, 4)
	33 goto (1, 4)
	36 aload_2 (0, 0)
	37 areturn (0, 0)

Method: distance1
	0 aload_0 (0, 0)
	1 aload_1 (0, 0)
	2 invokestatic (0, 0)
	5 iconst_0 (0, 0)
	6 istore_2 (0, 0)
	7 iconst_0 (1, 4)
	8 istore_3 (1, 4)
	9 iload_3 (1, 4)
	10 aload_0 (1, 4)
	11 arraylength (1, 4)
	12 if_icmpge (1, 4)
	15 iload_2 (1, 4)
	16 aload_0 (1, 4)
	17 iload_3 (1, 4)
	18 iaload (1, 4)
	19 aload_1 (1, 4)
	20 iload_3 (1, 4)
	21 iaload (1, 4)
	22 isub (1, 4)
	23 invokestatic (1, 4)
	26 iadd (1, 4)
	27 istore_2 (1, 4)
	28 iinc (1, 4)
	31 goto (1, 4)
	34 iload_2 (0, 0)
	35 ireturn (0, 0)

Method: distance
	0 aload_0 (0, 0)
	1 aload_1 (0, 0)
	2 invokestatic (0, 0)
	5 dconst_0 (0, 0)
	6 dstore_2 (0, 0)
	7 iconst_0 (1, 4)
	8 istore (1, 4)
	10 iload (1, 4)
	12 aload_0 (1, 4)
	13 arraylength (1, 4)
	14 if_icmpge (1, 4)
	17 aload_0 (1, 4)
	18 iload (1, 4)
	20 iaload (1, 4)
	21 aload_1 (1, 4)
	22 iload (1, 4)
	24 iaload (1, 4)
	25 isub (1, 4)
	26 i2d (1, 4)
	27 dstore (1, 4)
	29 dload_2 (1, 4)
	30 dload (1, 4)
	32 dload (1, 4)
	34 dmul (1, 4)
	35 dadd (1, 4)
	36 dstore_2 (1, 4)
	37 iinc (1, 4)
	40 goto (1, 4)
	43 dload_2 (0, 0)
	44 invokestatic (0, 0)
	47 dreturn (0, 0)

Method: cosAngle
	0 aload_0 (0, 0)
	1 aload_1 (0, 0)
	2 invokestatic (0, 0)
	5 aload_0 (0, 0)
	6 invokestatic (0, 0)
	9 aload_1 (0, 0)
	10 invokestatic (0, 0)
	13 dmul (0, 0)
	14 ddiv (0, 0)
	15 dreturn (0, 0)

Method: distanceInf
	0 aload_0 (0, 0)
	1 aload_1 (0, 0)
	2 invokestatic (0, 0)
	5 iconst_0 (0, 0)
	6 istore_2 (0, 0)
	7 iconst_0 (1, 4)
	8 istore_3 (1, 4)
	9 iload_3 (1, 4)
	10 aload_0 (1, 4)
	11 arraylength (1, 4)
	12 if_icmpge (1, 4)
	15 iload_2 (1, 4)
	16 aload_0 (1, 4)
	17 iload_3 (1, 4)
	18 iaload (1, 4)
	19 aload_1 (1, 4)
	20 iload_3 (1, 4)
	21 iaload (1, 4)
	22 isub (1, 4)
	23 invokestatic (1, 4)
	26 invokestatic (1, 4)
	29 istore_2 (1, 4)
	30 iinc (1, 4)
	33 goto (1, 4)
	36 iload_2 (0, 0)
	37 ireturn (0, 0)

Method: isMonotonic
	0 aload_0 (0, 0)
	1 aload_1 (0, 0)
	2 iload_2 (0, 0)
	3 iconst_0 (0, 0)
	4 invokestatic (0, 0)
	7 ireturn (0, 0)

Method: checkEqualLength
	0 aload_0 (0, 0)
	1 aload_1 (0, 0)
	2 iconst_1 (0, 0)
	3 invokestatic (0, 0)
	6 pop (0, 0)
	7 return (0, 0)

Method: checkOrder
	0 aload_0 (0, 0)
	1 getstatic (0, 0)
	4 iconst_1 (0, 0)
	5 invokestatic (0, 0)
	8 return (0, 0)

Method: checkRectangular
	0 aload_0 (0, 0)
	1 invokestatic (0, 0)
	4 iconst_1 (1, 4)
	5 istore_1 (1, 4)
	6 iload_1 (1, 4)
	7 aload_0 (1, 4)
	8 arraylength (1, 4)
	9 if_icmpge (1, 4)
	12 aload_0 (2, 1)
	13 iload_1 (2, 1)
	14 aaload (2, 1)
	15 arraylength (2, 1)
	16 aload_0 (2, 1)
	17 iconst_0 (2, 1)
	18 aaload (2, 1)
	19 arraylength (2, 1)
	20 if_icmpeq (2, 1)
	23 new (2, 1)
	26 dup (2, 1)
	27 getstatic (2, 1)
	30 aload_0 (2, 1)
	31 iload_1 (2, 1)
	32 aaload (2, 1)
	33 arraylength (2, 1)
	34 aload_0 (2, 1)
	35 iconst_0 (2, 1)
	36 aaload (2, 1)
	37 arraylength (2, 1)
	38 invokespecial (2, 1)
	41 athrow (2, 1)
	42 iinc (2, 1)
	45 goto (2, 1)
	48 return (0, 0)

Method: checkPositive
	0 iconst_0 (1, 4)
	1 istore_1 (1, 4)
	2 iload_1 (1, 4)
	3 aload_0 (1, 4)
	4 arraylength (1, 4)
	5 if_icmpge (1, 4)
	8 aload_0 (2, 1)
	9 iload_1 (2, 1)
	10 daload (2, 1)
	11 dconst_0 (2, 1)
	12 dcmpg (2, 1)
	13 ifgt (2, 1)
	16 new (2, 1)
	19 dup (2, 1)
	20 aload_0 (2, 1)
	21 iload_1 (2, 1)
	22 daload (2, 1)
	23 invokestatic (2, 1)
	26 invokespecial (2, 1)
	29 athrow (2, 1)
	30 iinc (2, 1)
	33 goto (2, 1)
	36 return (0, 0)

Method: checkNotNaN
	0 iconst_0 (1, 4)
	1 istore_1 (1, 4)
	2 iload_1 (1, 4)
	3 aload_0 (1, 4)
	4 arraylength (1, 4)
	5 if_icmpge (1, 4)
	8 aload_0 (2, 1)
	9 iload_1 (2, 1)
	10 daload (2, 1)
	11 invokestatic (2, 1)
	14 ifeq (2, 1)
	17 new (2, 1)
	20 dup (2, 1)
	21 invokespecial (2, 1)
	24 athrow (2, 1)
	25 iinc (2, 1)
	28 goto (2, 1)
	31 return (0, 0)

Method: checkNonNegative
	0 iconst_0 (1, 4)
	1 istore_1 (1, 4)
	2 iload_1 (1, 4)
	3 aload_0 (1, 4)
	4 arraylength (1, 4)
	5 if_icmpge (1, 4)
	8 iconst_0 (2, 4)
	9 istore_2 (2, 4)
	10 iload_2 (2, 4)
	11 aload_0 (2, 4)
	12 iload_1 (2, 4)
	13 aaload (2, 4)
	14 arraylength (2, 4)
	15 if_icmpge (2, 4)
	18 aload_0 (3, 1)
	19 iload_1 (3, 1)
	20 aaload (3, 1)
	21 iload_2 (3, 1)
	22 laload (3, 1)
	23 lconst_0 (3, 1)
	24 lcmp (3, 1)
	25 ifge (3, 1)
	28 new (3, 1)
	31 dup (3, 1)
	32 aload_0 (3, 1)
	33 iload_1 (3, 1)
	34 aaload (3, 1)
	35 iload_2 (3, 1)
	36 laload (3, 1)
	37 invokestatic (3, 1)
	40 invokespecial (3, 1)
	43 athrow (3, 1)
	44 iinc (3, 1)
	47 goto (3, 1)
	50 iinc (3, 1)
	53 goto (3, 1)
	56 return (1, 4)

Method: safeNorm
	0 ldc2_w (0, 0)
	3 dstore_1 (0, 0)
	4 ldc2_w (0, 0)
	7 dstore_3 (0, 0)
	8 dconst_0 (0, 0)
	9 dstore (0, 0)
	11 dconst_0 (0, 0)
	12 dstore (0, 0)
	14 dconst_0 (0, 0)
	15 dstore (0, 0)
	17 dconst_0 (0, 0)
	18 dstore (0, 0)
	20 dconst_0 (0, 0)
	21 dstore (0, 0)
	23 aload_0 (0, 0)
	24 arraylength (0, 0)
	25 i2d (0, 0)
	26 dstore (0, 0)
	28 dload_3 (0, 0)
	29 dload (0, 0)
	31 ddiv (0, 0)
	32 dstore (0, 0)
	34 iconst_0 (1, 4)
	35 istore (1, 4)
	37 iload (1, 4)
	39 aload_0 (1, 4)
	40 arraylength (1, 4)
	41 if_icmpge (1, 4)
	44 aload_0 (1, 4)
	45 iload (1, 4)
	47 daload (1, 4)
	48 invokestatic (1, 4)
	51 dstore (1, 4)
	53 dload (2, 1)
	55 dload_1 (2, 1)
	56 dcmpg (2, 1)
	57 iflt (2, 1)
	60 dload (2, 1)
	62 dload (2, 1)
	64 dcmpl (2, 1)
	65 ifle (2, 1)
	68 dload (3, 1)
	70 dload_1 (3, 1)
	71 dcmpl (3, 1)
	72 ifle (3, 1)
	75 dload (4, 1)
	77 dload (4, 1)
	79 dcmpl (4, 1)
	80 ifle (4, 1)
	83 dload (4, 1)
	85 dload (4, 1)
	87 ddiv (4, 1)
	88 dstore (4, 1)
	90 dconst_1 (4, 1)
	91 dload (4, 1)
	93 dload (4, 1)
	95 dmul (4, 1)
	96 dload (4, 1)
	98 dmul (4, 1)
	99 dadd (4, 1)
	100 dstore (4, 1)
	102 dload (4, 1)
	104 dstore (4, 1)
	106 goto (4, 2)
	109 dload (4, 2)
	111 dload (4, 2)
	113 ddiv (4, 2)
	114 dstore (4, 2)
	116 dload (4, 2)
	118 dload (4, 2)
	120 dload (4, 2)
	122 dmul (4, 2)
	123 dadd (4, 2)
	124 dstore (4, 2)
	126 goto (3, 1)
	129 dload (4, 1)
	131 dload (4, 1)
	133 dcmpl (4, 1)
	134 ifle (4, 1)
	137 dload (4, 1)
	139 dload (4, 1)
	141 ddiv (4, 1)
	142 dstore (4, 1)
	144 dconst_1 (4, 1)
	145 dload (4, 1)
	147 dload (4, 1)
	149 dmul (4, 1)
	150 dload (4, 1)
	152 dmul (4, 1)
	153 dadd (4, 1)
	154 dstore (4, 1)
	156 dload (4, 1)
	158 dstore (4, 1)
	160 goto (4, 2)
	163 dload (5, 1)
	165 dconst_0 (5, 1)
	166 dcmpl (5, 1)
	167 ifeq (5, 1)
	170 dload (5, 1)
	172 dload (5, 1)
	174 ddiv (5, 1)
	175 dstore (5, 1)
	177 dload (5, 1)
	179 dload (5, 1)
	181 dload (5, 1)
	183 dmul (5, 1)
	184 dadd (5, 1)
	185 dstore (5, 1)
	187 goto (4, 2)
	190 dload (2, 2)
	192 dload (2, 2)
	194 dload (2, 2)
	196 dmul (2, 2)
	197 dadd (2, 2)
	198 dstore (2, 2)
	200 iinc (2, 2)
	203 goto (2, 2)
	206 dload (2, 1)
	208 dconst_0 (2, 1)
	209 dcmpl (2, 1)
	210 ifeq (2, 1)
	213 dload (2, 1)
	215 dload (2, 1)
	217 dload (2, 1)
	219 dload (2, 1)
	221 ddiv (2, 1)
	222 dload (2, 1)
	224 ddiv (2, 1)
	225 dadd (2, 1)
	226 invokestatic (2, 1)
	229 dmul (2, 1)
	230 dstore (2, 1)
	232 goto (2, 1)
	235 dload (3, 1)
	237 dconst_0 (3, 1)
	238 dcmpl (3, 1)
	239 ifne (3, 1)
	242 dload (3, 1)
	244 dload (3, 1)
	246 invokestatic (3, 1)
	249 dmul (3, 1)
	250 dstore (3, 1)
	252 goto (3, 1)
	255 dload (4, 1)
	257 dload (4, 1)
	259 dcmpl (4, 1)
	260 iflt (4, 1)
	263 dload (4, 1)
	265 dconst_1 (4, 1)
	266 dload (4, 1)
	268 dload (4, 1)
	270 ddiv (4, 1)
	271 dload (4, 1)
	273 dload (4, 1)
	275 dmul (4, 1)
	276 dmul (4, 1)
	277 dadd (4, 1)
	278 dmul (4, 1)
	279 invokestatic (4, 1)
	282 dstore (4, 1)
	284 goto (4, 1)
	287 dload (4, 2)
	289 dload (4, 2)
	291 dload (4, 2)
	293 ddiv (4, 2)
	294 dload (4, 2)
	296 dload (4, 2)
	298 dmul (4, 2)
	299 dadd (4, 2)
	300 dmul (4, 2)
	301 invokestatic (4, 2)
	304 dstore (4, 2)
	306 dload (1, 1)
	308 dreturn (1, 1)

Method: sortInPlace
	0 aload_0 (1, 1)
	1 ifnonnull (1, 1)
	4 new (1, 1)
	7 dup (1, 1)
	8 invokespecial (1, 1)
	11 athrow (1, 1)
	12 aload_2 (0, 0)
	13 arraylength (0, 0)
	14 istore_3 (0, 0)
	15 aload_0 (0, 0)
	16 arraylength (0, 0)
	17 istore (0, 0)
	19 iconst_0 (1, 4)
	20 istore (1, 4)
	22 iload (1, 4)
	24 iload_3 (1, 4)
	25 if_icmpge (1, 4)
	28 aload_2 (1, 4)
	29 iload (1, 4)
	31 aaload (1, 4)
	32 astore (1, 4)
	34 aload (2, 1)
	36 ifnonnull (2, 1)
	39 new (2, 1)
	42 dup (2, 1)
	43 invokespecial (2, 1)
	46 athrow (2, 1)
	47 aload (2, 1)
	49 arraylength (2, 1)
	50 iload (2, 1)
	52 if_icmpeq (2, 1)
	55 new (2, 1)
	58 dup (2, 1)
	59 aload (2, 1)
	61 arraylength (2, 1)
	62 iload (2, 1)
	64 invokespecial (2, 1)
	67 athrow (2, 1)
	68 iinc (2, 1)
	71 goto (2, 1)
	74 new (1, 4)
	77 dup (1, 4)
	78 iload (1, 4)
	80 invokespecial (1, 4)
	83 astore (1, 4)
	85 iconst_0 (2, 4)
	86 istore (2, 4)
	88 iload (2, 4)
	90 iload (2, 4)
	92 if_icmpge (2, 4)
	95 aload (2, 4)
	97 new (2, 4)
	100 dup (2, 4)
	101 aload_0 (2, 4)
	102 iload (2, 4)
	104 daload (2, 4)
	105 iload (2, 4)
	107 invokespecial (2, 4)
	110 invokeinterface (2, 4)
	115 pop (2, 4)
	116 iinc (2, 4)
	119 goto (2, 4)
	122 aload_1 (1, 4)
	123 getstatic (1, 4)
	126 if_acmpne (1, 4)
	129 new (1, 4)
	132 dup (1, 4)
	133 invokespecial (1, 4)
	136 goto (1, 4)
	139 new (1, 4)
	142 dup (1, 4)
	143 invokespecial (1, 4)
	146 astore (1, 4)
	148 aload (2, 0)
	150 aload (2, 0)
	152 invokestatic (2, 0)
	155 iload (2, 1)
	157 newarray (2, 1)
	159 astore (2, 1)
	161 iconst_0 (3, 4)
	162 istore (3, 4)
	164 iload (3, 4)
	166 iload (3, 4)
	168 if_icmpge (3, 4)
	171 aload (3, 4)
	173 iload (3, 4)
	175 invokeinterface (3, 4)
	180 checkcast (3, 4)
	183 astore (3, 4)
	185 aload_0 (3, 4)
	186 iload (3, 4)
	188 aload (3, 4)
	190 invokevirtual (3, 4)
	193 dastore (3, 4)
	194 aload (3, 4)
	196 iload (3, 4)
	198 aload (3, 4)
	200 invokevirtual (3, 4)
	203 iastore (3, 4)
	204 iinc (3, 4)
	207 goto (3, 4)
	210 iconst_0 (3, 4)
	211 istore (3, 4)
	213 iload (3, 4)
	215 iload_3 (3, 4)
	216 if_icmpge (3, 4)
	219 aload_2 (3, 1)
	220 iload (3, 1)
	222 aaload (3, 1)
	223 astore (3, 1)
	225 aload (3, 1)
	227 invokevirtual (3, 1)
	230 checkcast (3, 1)
	233 astore (3, 1)
	235 iconst_0 (4, 4)
	236 istore (4, 4)
	238 iload (4, 4)
	240 iload (4, 4)
	242 if_icmpge (4, 4)
	245 aload (4, 4)
	247 iload (4, 4)
	249 aload (4, 4)
	251 aload (4, 4)
	253 iload (4, 4)
	255 iaload (4, 4)
	256 daload (4, 4)
	257 dastore (4, 4)
	258 iinc (4, 4)
	261 goto (4, 4)
	264 iinc (4, 4)
	267 goto (4, 4)
	270 return (2, 1)

Method: copyOf
	0 iload_1 (0, 0)
	1 newarray (0, 0)
	3 astore_2 (0, 0)
	4 aload_0 (0, 0)
	5 iconst_0 (0, 0)
	6 aload_2 (0, 0)
	7 iconst_0 (0, 0)
	8 iload_1 (0, 0)
	9 aload_0 (0, 0)
	10 arraylength (0, 0)
	11 invokestatic (0, 0)
	14 invokestatic (0, 0)
	17 aload_2 (0, 0)
	18 areturn (0, 0)

Method: copyOfRange
	0 iload_2 (0, 0)
	1 iload_1 (0, 0)
	2 isub (0, 0)
	3 istore_3 (0, 0)
	4 iload_3 (0, 0)
	5 newarray (0, 0)
	7 astore (0, 0)
	9 aload_0 (0, 0)
	10 iload_1 (0, 0)
	11 aload (0, 0)
	13 iconst_0 (0, 0)
	14 iload_3 (0, 0)
	15 aload_0 (0, 0)
	16 arraylength (0, 0)
	17 iload_1 (0, 0)
	18 isub (0, 0)
	19 invokestatic (0, 0)
	22 invokestatic (0, 0)
	25 aload (0, 0)
	27 areturn (0, 0)

Method: linearCombination
	0 dload_0 (0, 0)
	1 invokestatic (0, 0)
	4 ldc2_w (0, 0)
	7 land (0, 0)
	8 invokestatic (0, 0)
	11 dstore (0, 0)
	13 dload_0 (0, 0)
	14 dload (0, 0)
	16 dsub (0, 0)
	17 dstore (0, 0)
	19 dload_2 (0, 0)
	20 invokestatic (0, 0)
	23 ldc2_w (0, 0)
	26 land (0, 0)
	27 invokestatic (0, 0)
	30 dstore (0, 0)
	32 dload_2 (0, 0)
	33 dload (0, 0)
	35 dsub (0, 0)
	36 dstore (0, 0)
	38 dload_0 (0, 0)
	39 dload_2 (0, 0)
	40 dmul (0, 0)
	41 dstore (0, 0)
	43 dload (0, 0)
	45 dload (0, 0)
	47 dmul (0, 0)
	48 dload (0, 0)
	50 dload (0, 0)
	52 dload (0, 0)
	54 dmul (0, 0)
	55 dsub (0, 0)
	56 dload (0, 0)
	58 dload (0, 0)
	60 dmul (0, 0)
	61 dsub (0, 0)
	62 dload (0, 0)
	64 dload (0, 0)
	66 dmul (0, 0)
	67 dsub (0, 0)
	68 dsub (0, 0)
	69 dstore (0, 0)
	71 dload (0, 0)
	73 invokestatic (0, 0)
	76 ldc2_w (0, 0)
	79 land (0, 0)
	80 invokestatic (0, 0)
	83 dstore (0, 0)
	85 dload (0, 0)
	87 dload (0, 0)
	89 dsub (0, 0)
	90 dstore (0, 0)
	92 dload (0, 0)
	94 invokestatic (0, 0)
	97 ldc2_w (0, 0)
	100 land (0, 0)
	101 invokestatic (0, 0)
	104 dstore (0, 0)
	106 dload (0, 0)
	108 dload (0, 0)
	110 dsub (0, 0)
	111 dstore (0, 0)
	113 dload (0, 0)
	115 dload (0, 0)
	117 dmul (0, 0)
	118 dstore (0, 0)
	120 dload (0, 0)
	122 dload (0, 0)
	124 dmul (0, 0)
	125 dload (0, 0)
	127 dload (0, 0)
	129 dload (0, 0)
	131 dmul (0, 0)
	132 dsub (0, 0)
	133 dload (0, 0)
	135 dload (0, 0)
	137 dmul (0, 0)
	138 dsub (0, 0)
	139 dload (0, 0)
	141 dload (0, 0)
	143 dmul (0, 0)
	144 dsub (0, 0)
	145 dsub (0, 0)
	146 dstore (0, 0)
	148 dload (0, 0)
	150 invokestatic (0, 0)
	153 ldc2_w (0, 0)
	156 land (0, 0)
	157 invokestatic (0, 0)
	160 dstore (0, 0)
	162 dload (0, 0)
	164 dload (0, 0)
	166 dsub (0, 0)
	167 dstore (0, 0)
	169 dload (0, 0)
	171 invokestatic (0, 0)
	174 ldc2_w (0, 0)
	177 land (0, 0)
	178 invokestatic (0, 0)
	181 dstore (0, 0)
	183 dload (0, 0)
	185 dload (0, 0)
	187 dsub (0, 0)
	188 dstore (0, 0)
	190 dload (0, 0)
	192 dload (0, 0)
	194 dmul (0, 0)
	195 dstore (0, 0)
	197 dload (0, 0)
	199 dload (0, 0)
	201 dmul (0, 0)
	202 dload (0, 0)
	204 dload (0, 0)
	206 dload (0, 0)
	208 dmul (0, 0)
	209 dsub (0, 0)
	210 dload (0, 0)
	212 dload (0, 0)
	214 dmul (0, 0)
	215 dsub (0, 0)
	216 dload (0, 0)
	218 dload (0, 0)
	220 dmul (0, 0)
	221 dsub (0, 0)
	222 dsub (0, 0)
	223 dstore (0, 0)
	225 dload (0, 0)
	227 invokestatic (0, 0)
	230 ldc2_w (0, 0)
	233 land (0, 0)
	234 invokestatic (0, 0)
	237 dstore (0, 0)
	239 dload (0, 0)
	241 dload (0, 0)
	243 dsub (0, 0)
	244 dstore (0, 0)
	246 dload (0, 0)
	248 invokestatic (0, 0)
	251 ldc2_w (0, 0)
	254 land (0, 0)
	255 invokestatic (0, 0)
	258 dstore (0, 0)
	260 dload (0, 0)
	262 dload (0, 0)
	264 dsub (0, 0)
	265 dstore (0, 0)
	267 dload (0, 0)
	269 dload (0, 0)
	271 dmul (0, 0)
	272 dstore (0, 0)
	274 dload (0, 0)
	276 dload (0, 0)
	278 dmul (0, 0)
	279 dload (0, 0)
	281 dload (0, 0)
	283 dload (0, 0)
	285 dmul (0, 0)
	286 dsub (0, 0)
	287 dload (0, 0)
	289 dload (0, 0)
	291 dmul (0, 0)
	292 dsub (0, 0)
	293 dload (0, 0)
	295 dload (0, 0)
	297 dmul (0, 0)
	298 dsub (0, 0)
	299 dsub (0, 0)
	300 dstore (0, 0)
	302 dload (0, 0)
	304 dload (0, 0)
	306 dadd (0, 0)
	307 dstore (0, 0)
	309 dload (0, 0)
	311 dload (0, 0)
	313 dsub (0, 0)
	314 dstore (0, 0)
	316 dload (0, 0)
	318 dload (0, 0)
	320 dload (0, 0)
	322 dsub (0, 0)
	323 dsub (0, 0)
	324 dload (0, 0)
	326 dload (0, 0)
	328 dsub (0, 0)
	329 dadd (0, 0)
	330 dstore (0, 0)
	332 dload (0, 0)
	334 dload (0, 0)
	336 dadd (0, 0)
	337 dstore (0, 0)
	339 dload (0, 0)
	341 dload (0, 0)
	343 dsub (0, 0)
	344 dstore (0, 0)
	346 dload (0, 0)
	348 dload (0, 0)
	350 dload (0, 0)
	352 dsub (0, 0)
	353 dsub (0, 0)
	354 dload (0, 0)
	356 dload (0, 0)
	358 dsub (0, 0)
	359 dadd (0, 0)
	360 dstore (0, 0)
	362 dload (0, 0)
	364 dload (0, 0)
	366 dadd (0, 0)
	367 dstore (0, 0)
	369 dload (0, 0)
	371 dload (0, 0)
	373 dsub (0, 0)
	374 dstore (0, 0)
	376 dload (0, 0)
	378 dload (0, 0)
	380 dload (0, 0)
	382 dsub (0, 0)
	383 dsub (0, 0)
	384 dload (0, 0)
	386 dload (0, 0)
	388 dsub (0, 0)
	389 dadd (0, 0)
	390 dstore (0, 0)
	392 dload (0, 0)
	394 dload (0, 0)
	396 dload (0, 0)
	398 dadd (0, 0)
	399 dload (0, 0)
	401 dadd (0, 0)
	402 dload (0, 0)
	404 dadd (0, 0)
	405 dload (0, 0)
	407 dadd (0, 0)
	408 dload (0, 0)
	410 dadd (0, 0)
	411 dload (0, 0)
	413 dadd (0, 0)
	414 dadd (0, 0)
	415 dstore (0, 0)
	417 dload (1, 1)
	419 invokestatic (1, 1)
	422 ifeq (1, 1)
	425 dload_0 (1, 1)
	426 dload_2 (1, 1)
	427 dmul (1, 1)
	428 dload (1, 1)
	430 dload (1, 1)
	432 dmul (1, 1)
	433 dadd (1, 1)
	434 dload (1, 1)
	436 dload (1, 1)
	438 dmul (1, 1)
	439 dadd (1, 1)
	440 dload (1, 1)
	442 dload (1, 1)
	444 dmul (1, 1)
	445 dadd (1, 1)
	446 dstore (1, 1)
	448 dload (0, 0)
	450 dreturn (0, 0)

Method: equals
	0 aload_0 (1, 1)
	1 ifnull (1, 1)
	4 aload_1 (1, 1)
	5 ifnonnull (1, 1)
	8 aload_0 (1, 1)
	9 ifnonnull (1, 1)
	12 iconst_1 (1, 1)
	13 goto (1, 1)
	16 iconst_0 (1, 1)
	17 aload_1 (1, 1)
	18 ifnonnull (1, 1)
	21 iconst_1 (1, 1)
	22 goto (1, 1)
	25 iconst_0 (1, 1)
	26 ixor (1, 1)
	27 ifne (1, 1)
	30 iconst_1 (1, 1)
	31 goto (1, 1)
	34 iconst_0 (1, 1)
	35 ireturn (1, 1)
	36 aload_0 (1, 1)
	37 arraylength (1, 1)
	38 aload_1 (1, 1)
	39 arraylength (1, 1)
	40 if_icmpeq (1, 1)
	43 iconst_0 (1, 1)
	44 ireturn (1, 1)
	45 iconst_0 (1, 4)
	46 istore_2 (1, 4)
	47 iload_2 (1, 4)
	48 aload_0 (1, 4)
	49 arraylength (1, 4)
	50 if_icmpge (1, 4)
	53 aload_0 (2, 1)
	54 iload_2 (2, 1)
	55 daload (2, 1)
	56 aload_1 (2, 1)
	57 iload_2 (2, 1)
	58 daload (2, 1)
	59 invokestatic (2, 1)
	62 ifne (2, 1)
	65 iconst_0 (2, 1)
	66 ireturn (2, 1)
	67 iinc (2, 1)
	70 goto (2, 1)
	73 iconst_1 (1, 4)
	74 ireturn (1, 4)

Method: equalsIncludingNaN
	0 aload_0 (1, 1)
	1 ifnull (1, 1)
	4 aload_1 (1, 1)
	5 ifnonnull (1, 1)
	8 aload_0 (1, 1)
	9 ifnonnull (1, 1)
	12 iconst_1 (1, 1)
	13 goto (1, 1)
	16 iconst_0 (1, 1)
	17 aload_1 (1, 1)
	18 ifnonnull (1, 1)
	21 iconst_1 (1, 1)
	22 goto (1, 1)
	25 iconst_0 (1, 1)
	26 ixor (1, 1)
	27 ifne (1, 1)
	30 iconst_1 (1, 1)
	31 goto (1, 1)
	34 iconst_0 (1, 1)
	35 ireturn (1, 1)
	36 aload_0 (1, 1)
	37 arraylength (1, 1)
	38 aload_1 (1, 1)
	39 arraylength (1, 1)
	40 if_icmpeq (1, 1)
	43 iconst_0 (1, 1)
	44 ireturn (1, 1)
	45 iconst_0 (1, 4)
	46 istore_2 (1, 4)
	47 iload_2 (1, 4)
	48 aload_0 (1, 4)
	49 arraylength (1, 4)
	50 if_icmpge (1, 4)
	53 aload_0 (2, 1)
	54 iload_2 (2, 1)
	55 daload (2, 1)
	56 aload_1 (2, 1)
	57 iload_2 (2, 1)
	58 daload (2, 1)
	59 invokestatic (2, 1)
	62 ifne (2, 1)
	65 iconst_0 (2, 1)
	66 ireturn (2, 1)
	67 iinc (2, 1)
	70 goto (2, 1)
	73 iconst_1 (1, 4)
	74 ireturn (1, 4)

Method: normalizeArray
	0 dload_1 (1, 1)
	1 invokestatic (1, 1)
	4 ifeq (1, 1)
	7 new (1, 1)
	10 dup (1, 1)
	11 getstatic (1, 1)
	14 iconst_0 (1, 1)
	15 anewarray (1, 1)
	18 invokespecial (1, 1)
	21 athrow (1, 1)
	22 dload_1 (1, 1)
	23 invokestatic (1, 1)
	26 ifeq (1, 1)
	29 new (1, 1)
	32 dup (1, 1)
	33 getstatic (1, 1)
	36 iconst_0 (1, 1)
	37 anewarray (1, 1)
	40 invokespecial (1, 1)
	43 athrow (1, 1)
	44 dconst_0 (0, 0)
	45 dstore_3 (0, 0)
	46 aload_0 (0, 0)
	47 arraylength (0, 0)
	48 istore (0, 0)
	50 iload (0, 0)
	52 newarray (0, 0)
	54 astore (0, 0)
	56 iconst_0 (1, 4)
	57 istore (1, 4)
	59 iload (1, 4)
	61 iload (1, 4)
	63 if_icmpge (1, 4)
	66 aload_0 (2, 1)
	67 iload (2, 1)
	69 daload (2, 1)
	70 invokestatic (2, 1)
	73 ifeq (2, 1)
	76 new (2, 1)
	79 dup (2, 1)
	80 getstatic (2, 1)
	83 iconst_2 (2, 1)
	84 anewarray (2, 1)
	87 dup (2, 1)
	88 iconst_0 (2, 1)
	89 aload_0 (2, 1)
	90 iload (2, 1)
	92 daload (2, 1)
	93 invokestatic (2, 1)
	96 aastore (2, 1)
	97 dup (2, 1)
	98 iconst_1 (2, 1)
	99 iload (2, 1)
	101 invokestatic (2, 1)
	104 aastore (2, 1)
	105 invokespecial (2, 1)
	108 athrow (2, 1)
	109 aload_0 (2, 1)
	110 iload (2, 1)
	112 daload (2, 1)
	113 invokestatic (2, 1)
	116 ifne (2, 1)
	119 dload_3 (2, 1)
	120 aload_0 (2, 1)
	121 iload (2, 1)
	123 daload (2, 1)
	124 dadd (2, 1)
	125 dstore_3 (2, 1)
	126 iinc (2, 1)
	129 goto (2, 1)
	132 dload_3 (2, 1)
	133 dconst_0 (2, 1)
	134 dcmpl (2, 1)
	135 ifne (2, 1)
	138 new (2, 1)
	141 dup (2, 1)
	142 getstatic (2, 1)
	145 iconst_0 (2, 1)
	146 anewarray (2, 1)
	149 invokespecial (2, 1)
	152 athrow (2, 1)
	153 iconst_0 (2, 4)
	154 istore (2, 4)
	156 iload (2, 4)
	158 iload (2, 4)
	160 if_icmpge (2, 4)
	163 aload_0 (3, 1)
	164 iload (3, 1)
	166 daload (3, 1)
	167 invokestatic (3, 1)
	170 ifeq (3, 1)
	173 aload (3, 1)
	175 iload (3, 1)
	177 ldc2_w (3, 1)
	180 dastore (3, 1)
	181 goto (3, 1)
	184 aload (3, 2)
	186 iload (3, 2)
	188 aload_0 (3, 2)
	189 iload (3, 2)
	191 daload (3, 2)
	192 dload_1 (3, 2)
	193 dmul (3, 2)
	194 dload_3 (3, 2)
	195 ddiv (3, 2)
	196 dastore (3, 2)
	197 iinc (3, 2)
	200 goto (3, 2)
	203 aload (2, 2)
	205 areturn (2, 2)

Method: buildArray
	0 iload_2 (1, 1)
	1 ifge (1, 1)
	4 aload_0 (1, 1)
	5 iconst_0 (1, 1)
	6 invokestatic (1, 1)
	9 astore (1, 1)
	11 aload (1, 1)
	13 invokevirtual (1, 1)
	16 iload_1 (1, 1)
	17 invokestatic (1, 1)
	20 checkcast (1, 1)
	23 checkcast (1, 1)
	26 astore_3 (1, 1)
	27 goto (1, 2)
	30 aload_0 (1, 2)
	31 invokeinterface (1, 2)
	36 iconst_2 (1, 2)
	37 newarray (1, 2)
	39 dup (1, 2)
	40 iconst_0 (1, 2)
	41 iload_1 (1, 2)
	42 iastore (1, 2)
	43 dup (1, 2)
	44 iconst_1 (1, 2)
	45 iload_2 (1, 2)
	46 iastore (1, 2)
	47 invokestatic (1, 2)
	50 checkcast (1, 2)
	53 checkcast (1, 2)
	56 astore_3 (1, 2)
	57 iconst_0 (2, 4)
	58 istore (2, 4)
	60 iload (2, 4)
	62 iload_1 (2, 4)
	63 if_icmpge (2, 4)
	66 aload_3 (2, 4)
	67 iload (2, 4)
	69 aaload (2, 4)
	70 aload_0 (2, 4)
	71 invokeinterface (2, 4)
	76 invokestatic (2, 4)
	79 iinc (2, 4)
	82 goto (2, 4)
	85 aload_3 (0, 0)
	86 areturn (0, 0)

Method: convolve
	0 aload_0 (0, 0)
	1 invokestatic (0, 0)
	4 aload_1 (0, 0)
	5 invokestatic (0, 0)
	8 aload_0 (0, 0)
	9 arraylength (0, 0)
	10 istore_2 (0, 0)
	11 aload_1 (0, 0)
	12 arraylength (0, 0)
	13 istore_3 (0, 0)
	14 iload_2 (1, 1)
	15 ifeq (1, 1)
	18 iload_3 (1, 1)
	19 ifne (1, 1)
	22 new (1, 1)
	25 dup (1, 1)
	26 invokespecial (1, 1)
	29 athrow (1, 1)
	30 iload_2 (0, 0)
	31 iload_3 (0, 0)
	32 iadd (0, 0)
	33 iconst_1 (0, 0)
	34 isub (0, 0)
	35 istore (0, 0)
	37 iload (0, 0)
	39 newarray (0, 0)
	41 astore (0, 0)
	43 iconst_0 (1, 4)
	44 istore (1, 4)
	46 iload (1, 4)
	48 iload (1, 4)
	50 if_icmpge (1, 4)
	53 dconst_0 (1, 4)
	54 dstore (1, 4)
	56 iconst_0 (1, 4)
	57 iload (1, 4)
	59 iconst_1 (1, 4)
	60 iadd (1, 4)
	61 iload_2 (1, 4)
	62 isub (1, 4)
	63 invokestatic (1, 4)
	66 istore (1, 4)
	68 iload (1, 4)
	70 iload (1, 4)
	72 isub (1, 4)
	73 istore (1, 4)
	75 iload (2, 3)
	77 iload_3 (2, 3)
	78 if_icmpge (2, 3)
	81 iload (2, 3)
	83 iflt (2, 3)
	86 dload (2, 3)
	88 aload_0 (2, 3)
	89 iload (2, 3)
	91 iinc (2, 3)
	94 daload (2, 3)
	95 aload_1 (2, 3)
	96 iload (2, 3)
	98 iinc (2, 3)
	101 daload (2, 3)
	102 dmul (2, 3)
	103 dadd (2, 3)
	104 dstore (2, 3)
	106 goto (2, 3)
	109 aload (1, 4)
	111 iload (1, 4)
	113 dload (1, 4)
	115 dastore (1, 4)
	116 iinc (1, 4)
	119 goto (1, 4)
	122 aload (0, 4)
	124 areturn (0, 4)

Method: shuffle
	0 aload_0 (0, 0)
	1 new (0, 0)
	4 dup (0, 0)
	5 invokespecial (0, 0)
	8 invokestatic (0, 0)
	11 return (0, 0)

Method: natural
	0 iload_0 (0, 0)
	1 iconst_0 (0, 0)
	2 iconst_1 (0, 0)
	3 invokestatic (0, 0)
	6 areturn (0, 0)

Method: sequence
	0 iload_0 (0, 0)
	1 newarray (0, 0)
	3 astore_3 (0, 0)
	4 iconst_0 (1, 4)
	5 istore (1, 4)
	7 iload (1, 4)
	9 iload_0 (1, 4)
	10 if_icmpge (1, 4)
	13 aload_3 (1, 4)
	14 iload (1, 4)
	16 iload_1 (1, 4)
	17 iload (1, 4)
	19 iload_2 (1, 4)
	20 imul (1, 4)
	21 iadd (1, 4)
	22 iastore (1, 4)
	23 iinc (1, 4)
	26 goto (1, 4)
	29 aload_3 (0, 0)
	30 areturn (0, 0)

Method: verifyValues
	0 aload_1 (1, 1)
	1 ifnull (1, 1)
	4 aload_0 (1, 1)
	5 ifnonnull (1, 1)
	8 new (1, 1)
	11 dup (1, 1)
	12 getstatic (1, 1)
	15 iconst_0 (1, 1)
	16 anewarray (1, 1)
	19 invokespecial (1, 1)
	22 athrow (1, 1)
	23 aload_1 (0, 0)
	24 aload_0 (0, 0)
	25 invokestatic (0, 0)
	28 iconst_0 (0, 0)
	29 istore (0, 0)
	31 iload_2 (1, 4)
	32 istore (1, 4)
	34 iload (1, 4)
	36 iload_2 (1, 4)
	37 iload_3 (1, 4)
	38 iadd (1, 4)
	39 if_icmpge (1, 4)
	42 aload_1 (1, 4)
	43 iload (1, 4)
	45 daload (1, 4)
	46 dstore (1, 4)
	48 dload (2, 1)
	50 invokestatic (2, 1)
	53 ifeq (2, 1)
	56 new (2, 1)
	59 dup (2, 1)
	60 getstatic (2, 1)
	63 iconst_1 (2, 1)
	64 anewarray (2, 1)
	67 dup (2, 1)
	68 iconst_0 (2, 1)
	69 iload (2, 1)
	71 invokestatic (2, 1)
	74 aastore (2, 1)
	75 invokespecial (2, 1)
	78 athrow (2, 1)
	79 dload (2, 1)
	81 invokestatic (2, 1)
	84 ifeq (2, 1)
	87 new (2, 1)
	90 dup (2, 1)
	91 getstatic (2, 1)
	94 iconst_2 (2, 1)
	95 anewarray (2, 1)
	98 dup (2, 1)
	99 iconst_0 (2, 1)
	100 dload (2, 1)
	102 invokestatic (2, 1)
	105 aastore (2, 1)
	106 dup (2, 1)
	107 iconst_1 (2, 1)
	108 iload (2, 1)
	110 invokestatic (2, 1)
	113 aastore (2, 1)
	114 invokespecial (2, 1)
	117 athrow (2, 1)
	118 dload (2, 1)
	120 dconst_0 (2, 1)
	121 dcmpg (2, 1)
	122 ifge (2, 1)
	125 new (2, 1)
	128 dup (2, 1)
	129 getstatic (2, 1)
	132 iconst_2 (2, 1)
	133 anewarray (2, 1)
	136 dup (2, 1)
	137 iconst_0 (2, 1)
	138 iload (2, 1)
	140 invokestatic (2, 1)
	143 aastore (2, 1)
	144 dup (2, 1)
	145 iconst_1 (2, 1)
	146 dload (2, 1)
	148 invokestatic (2, 1)
	151 aastore (2, 1)
	152 invokespecial (2, 1)
	155 athrow (2, 1)
	156 iload (2, 1)
	158 ifne (2, 1)
	161 dload (2, 1)
	163 dconst_0 (2, 1)
	164 dcmpl (2, 1)
	165 ifle (2, 1)
	168 iconst_1 (2, 1)
	169 istore (2, 1)
	171 iinc (2, 1)
	174 goto (2, 1)
	177 iload (2, 1)
	179 ifne (2, 1)
	182 new (2, 1)
	185 dup (2, 1)
	186 getstatic (2, 1)
	189 iconst_0 (2, 1)
	190 anewarray (2, 1)
	193 invokespecial (2, 1)
	196 athrow (2, 1)
	197 aload_0 (1, 1)
	198 iload_2 (1, 1)
	199 iload_3 (1, 1)
	200 iload (1, 1)
	202 invokestatic (1, 1)
	205 ireturn (1, 1)

Method: concatenate
	0 iconst_0 (0, 0)
	1 istore_1 (0, 0)
	2 aload_0 (1, 4)
	3 astore_2 (1, 4)
	4 aload_2 (1, 4)
	5 arraylength (1, 4)
	6 istore_3 (1, 4)
	7 iconst_0 (1, 4)
	8 istore (1, 4)
	10 iload (1, 4)
	12 iload_3 (1, 4)
	13 if_icmpge (1, 4)
	16 aload_2 (1, 4)
	17 iload (1, 4)
	19 aaload (1, 4)
	20 astore (1, 4)
	22 iload_1 (1, 4)
	23 aload (1, 4)
	25 arraylength (1, 4)
	26 iadd (1, 4)
	27 istore_1 (1, 4)
	28 iinc (1, 4)
	31 goto (1, 4)
	34 iconst_0 (0, 0)
	35 istore_2 (0, 0)
	36 iconst_0 (0, 0)
	37 istore_3 (0, 0)
	38 iload_1 (0, 0)
	39 newarray (0, 0)
	41 astore (0, 0)
	43 iconst_0 (1, 4)
	44 istore (1, 4)
	46 iload (1, 4)
	48 aload_0 (1, 4)
	49 arraylength (1, 4)
	50 if_icmpge (1, 4)
	53 aload_0 (1, 4)
	54 iload (1, 4)
	56 aaload (1, 4)
	57 arraylength (1, 4)
	58 istore_3 (1, 4)
	59 aload_0 (1, 4)
	60 iload (1, 4)
	62 aaload (1, 4)
	63 iconst_0 (1, 4)
	64 aload (1, 4)
	66 iload_2 (1, 4)
	67 iload_3 (1, 4)
	68 invokestatic (1, 4)
	71 iload_2 (1, 4)
	72 iload_3 (1, 4)
	73 iadd (1, 4)
	74 istore_2 (1, 4)
	75 iinc (1, 4)
	78 goto (1, 4)
	81 aload (0, 0)
	83 areturn (0, 0)

Method: unique
	0 new (0, 0)
	3 dup (0, 0)
	4 invokespecial (0, 0)
	7 astore_1 (0, 0)
	8 iconst_0 (1, 4)
	9 istore_2 (1, 4)
	10 iload_2 (1, 4)
	11 aload_0 (1, 4)
	12 arraylength (1, 4)
	13 if_icmpge (1, 4)
	16 aload_1 (1, 4)
	17 aload_0 (1, 4)
	18 iload_2 (1, 4)
	19 daload (1, 4)
	20 invokestatic (1, 4)
	23 invokevirtual (1, 4)
	26 pop (1, 4)
	27 iinc (1, 4)
	30 goto (1, 4)
	33 aload_1 (0, 0)
	34 invokevirtual (0, 0)
	37 istore_2 (0, 0)
	38 iload_2 (0, 0)
	39 newarray (0, 0)
	41 astore_3 (0, 0)
	42 aload_1 (0, 0)
	43 invokevirtual (0, 0)
	46 astore (0, 0)
	48 iconst_0 (0, 0)
	49 istore (0, 0)
	51 aload (1, 3)
	53 invokeinterface (1, 3)
	58 ifeq (1, 3)
	61 aload_3 (1, 3)
	62 iload_2 (1, 3)
	63 iinc (1, 3)
	66 iload (1, 3)
	68 isub (1, 3)
	69 aload (1, 3)
	71 invokeinterface (1, 3)
	76 checkcast (1, 3)
	79 invokevirtual (1, 3)
	82 dastore (1, 3)
	83 goto (1, 3)
	86 aload_3 (0, 0)
	87 areturn (0, 0)

