Method: hash
	0 aload_0 (0, 0)
	1 invokestatic (0, 0)
	4 ireturn (0, 0)

Method: equals
	0 new (0, 0)
	3 dup (0, 0)
	4 dload_0 (0, 0)
	5 invokespecial (0, 0)
	8 new (0, 0)
	11 dup (0, 0)
	12 dload_2 (0, 0)
	13 invokespecial (0, 0)
	16 invokevirtual (0, 0)
	19 ireturn (0, 0)

Method: normalizeAngle
	0 dload_0 (0, 0)
	1 ldc2_w (0, 0)
	4 dload_0 (0, 0)
	5 ldc2_w (0, 0)
	8 dadd (0, 0)
	9 dload_2 (0, 0)
	10 dsub (0, 0)
	11 ldc2_w (0, 0)
	14 ddiv (0, 0)
	15 invokestatic (0, 0)
	18 dmul (0, 0)
	19 dsub (0, 0)
	20 dreturn (0, 0)

Method: max
	0 aload_0 (0, 0)
	1 aload_1 (0, 0)
	2 invokeinterface (0, 0)
	7 checkcast (0, 0)
	10 invokeinterface (0, 0)
	15 dconst_0 (0, 0)
	16 dcmpl (0, 0)
	17 iflt (0, 0)
	20 aload_0 (0, 0)
	21 goto (0, 0)
	24 aload_1 (0, 0)
	25 areturn (0, 0)

Method: min
	0 aload_0 (0, 0)
	1 aload_1 (0, 0)
	2 invokeinterface (0, 0)
	7 checkcast (0, 0)
	10 invokeinterface (0, 0)
	15 dconst_0 (0, 0)
	16 dcmpl (0, 0)
	17 iflt (0, 0)
	20 aload_1 (0, 0)
	21 goto (0, 0)
	24 aload_0 (0, 0)
	25 areturn (0, 0)

Method: reduce
	0 dload_2 (0, 0)
	1 invokestatic (0, 0)
	4 dstore (0, 0)
	6 dload_0 (0, 0)
	7 dload (0, 0)
	9 dload_0 (0, 0)
	10 dload (0, 0)
	12 dsub (0, 0)
	13 dload (0, 0)
	15 ddiv (0, 0)
	16 invokestatic (0, 0)
	19 dmul (0, 0)
	20 dsub (0, 0)
	21 dload (0, 0)
	23 dsub (0, 0)
	24 dreturn (0, 0)

Method: copySign
	0 lload_0 (0, 1)
	1 lconst_0 (0, 1)
	2 lcmp (0, 1)
	3 iflt (0, 1)
	6 lload_2 (0, 1)
	7 lconst_0 (0, 1)
	8 lcmp (0, 1)
	9 ifge (0, 1)
	12 lload_0 (0, 1)
	13 lconst_0 (0, 1)
	14 lcmp (0, 1)
	15 ifge (0, 1)
	18 lload_2 (0, 1)
	19 lconst_0 (0, 1)
	20 lcmp (0, 1)
	21 ifge (0, 1)
	24 lload_0 (1, 1)
	25 lreturn (1, 1)
	26 lload_2 (0, 1)
	27 lconst_0 (0, 1)
	28 lcmp (0, 1)
	29 iflt (0, 1)
	32 lload_0 (0, 1)
	33 ldc2_w (0, 1)
	36 lcmp (0, 1)
	37 ifne (0, 1)
	40 new (1, 1)
	43 dup (1, 1)
	44 getstatic (1, 1)
	47 iconst_0 (1, 1)
	48 anewarray (1, 1)
	51 invokespecial (1, 1)
	54 athrow (1, 1)
	55 lload_0 (1, 2)
	56 lneg (1, 2)
	57 lreturn (1, 2)

Method: checkFinite
	0 iconst_0 (1, 4)
	1 istore_1 (1, 4)
	2 iload_1 (1, 4)
	3 aload_0 (1, 4)
	4 arraylength (1, 4)
	5 if_icmpge (1, 4)
	8 aload_0 (1, 4)
	9 iload_1 (1, 4)
	10 daload (1, 4)
	11 dstore_2 (1, 4)
	12 dload_2 (2, 1)
	13 invokestatic (2, 1)
	16 ifne (2, 1)
	19 dload_2 (2, 1)
	20 invokestatic (2, 1)
	23 ifeq (2, 1)
	26 new (2, 1)
	29 dup (2, 1)
	30 getstatic (2, 1)
	33 dload_2 (2, 1)
	34 invokestatic (2, 1)
	37 iconst_1 (2, 1)
	38 anewarray (2, 1)
	41 dup (2, 1)
	42 iconst_0 (2, 1)
	43 iload_1 (2, 1)
	44 invokestatic (2, 1)
	47 aastore (2, 1)
	48 invokespecial (2, 1)
	51 athrow (2, 1)
	52 iinc (2, 1)
	55 goto (2, 1)
	58 return (0, 0)

Method: checkNotNull
	0 aload_0 (1, 1)
	1 ifnonnull (1, 1)
	4 new (1, 1)
	7 dup (1, 1)
	8 invokespecial (1, 1)
	11 athrow (1, 1)
	12 return (0, 0)

