Method: <init>
	0 aload_0 (0, 0)
	1 invokespecial (0, 0)
	2 java/lang/Object.<init>:()V (0, 0)
	4 aload_0 (0, 0)
	5 aload_1 (0, 0)
	6 arraylength (0, 0)
	7 putfield (0, 0)
	8 org/apache/commons/math3/util/MultidimensionalCounter.dimension:I (0, 0)
	10 aload_0 (0, 0)
	11 aload_1 (0, 0)
	12 invokestatic (0, 0)
	13 org/apache/commons/math3/util/MathArrays.copyOf:([I)[I (0, 0)
	15 putfield (0, 0)
	16 org/apache/commons/math3/util/MultidimensionalCounter.size:[I (0, 0)
	18 aload_0 (0, 0)
	19 aload_0 (0, 0)
	20 getfield (0, 0)
	21 org/apache/commons/math3/util/MultidimensionalCounter.dimension:I (0, 0)
	23 newarray (0, 0)
	24 10 (0, 0)
	25 putfield (0, 0)
	26 org/apache/commons/math3/util/MultidimensionalCounter.uniCounterOffset:[I (0, 0)
	28 aload_0 (0, 0)
	29 aload_0 (0, 0)
	30 getfield (0, 0)
	31 org/apache/commons/math3/util/MultidimensionalCounter.dimension:I (0, 0)
	33 iconst_1 (0, 0)
	34 isub (0, 0)
	35 putfield (0, 0)
	36 org/apache/commons/math3/util/MultidimensionalCounter.last:I (0, 0)
	38 aload_1 (0, 0)
	39 aload_0 (0, 0)
	40 getfield (0, 0)
	41 org/apache/commons/math3/util/MultidimensionalCounter.last:I (0, 0)
	43 iaload (0, 0)
	44 istore_2 (0, 0)
	45 iconst_0 (1, 4)
	46 istore_3 (1, 4)
	47 iload_3 (1, 4)
	48 aload_0 (1, 4)
	49 getfield (1, 4)
	50 org/apache/commons/math3/util/MultidimensionalCounter.last:I (1, 4)
	52 if_icmpge (1, 4)
	53 55 (1, 4)
	55 iconst_1 (1, 4)
	56 istore (1, 4)
	57 #4 (1, 4)
	58 iload_3 (2, 4)
	59 iconst_1 (2, 4)
	60 iadd (2, 4)
	61 istore (2, 4)
	62 #5 (2, 4)
	63 iload (2, 4)
	64 #5 (2, 4)
	65 aload_0 (2, 4)
	66 getfield (2, 4)
	67 org/apache/commons/math3/util/MultidimensionalCounter.dimension:I (2, 4)
	69 if_icmpge (2, 4)
	70 18 (2, 4)
	72 iload (2, 4)
	73 #4 (2, 4)
	74 aload_1 (2, 4)
	75 iload (2, 4)
	76 #5 (2, 4)
	77 iaload (2, 4)
	78 imul (2, 4)
	79 istore (2, 4)
	80 #4 (2, 4)
	81 iinc (2, 4)
	82 #5 (2, 4)
	83 -89 (2, 4)
	84 goto (2, 4)
	85 -21 (2, 4)
	87 aload_0 (1, 4)
	88 getfield (1, 4)
	89 org/apache/commons/math3/util/MultidimensionalCounter.uniCounterOffset:[I (1, 4)
	91 iload_3 (1, 4)
	92 iload (1, 4)
	93 #4 (1, 4)
	94 iastore (1, 4)
	95 iload_2 (1, 4)
	96 aload_1 (1, 4)
	97 iload_3 (1, 4)
	98 iaload (1, 4)
	99 imul (1, 4)
	100 istore_2 (1, 4)
	101 iinc (1, 4)
	102 #3 (1, 4)
	103 -89 (1, 4)
	104 goto (1, 4)
	105 -57 (1, 4)
	107 aload_0 (0, 0)
	108 getfield (0, 0)
	109 org/apache/commons/math3/util/MultidimensionalCounter.uniCounterOffset:[I (0, 0)
	111 aload_0 (0, 0)
	112 getfield (0, 0)
	113 org/apache/commons/math3/util/MultidimensionalCounter.last:I (0, 0)
	115 iconst_0 (0, 0)
	116 iastore (0, 0)
	117 iload_2 (1, 1)
	118 ifgt (1, 1)
	119 15 (1, 1)
	121 new (1, 1)
	122 org/apache/commons/math3/exception/NotStrictlyPositiveException (1, 1)
	124 dup (1, 1)
	125 iload_2 (1, 1)
	126 invokestatic (1, 1)
	127 java/lang/Integer.valueOf:(I)Ljava/lang/Integer; (1, 1)
	129 invokespecial (1, 1)
	130 org/apache/commons/math3/exception/NotStrictlyPositiveException.<init>:(Ljava/lang/Number;)V (1, 1)
	132 athrow (1, 1)
	133 aload_0 (0, 0)
	134 iload_2 (0, 0)
	135 putfield (0, 0)
	136 org/apache/commons/math3/util/MultidimensionalCounter.totalSize:I (0, 0)
	138 return (0, 0)

Method: iterator
	0 aload_0 (0, 0)
	1 invokevirtual (0, 0)
	2 org/apache/commons/math3/util/MultidimensionalCounter.iterator:()Lorg/apache/commons/math3/util/MultidimensionalCounter$Iterator; (0, 0)
	4 areturn (0, 0)

Method: getDimension
	0 aload_0 (0, 0)
	1 getfield (0, 0)
	2 org/apache/commons/math3/util/MultidimensionalCounter.dimension:I (0, 0)
	4 ireturn (0, 0)

Method: getCounts
	0 iload_1 (1, 1)
	1 iflt (1, 1)
	2 11 (1, 1)
	4 iload_1 (1, 1)
	5 aload_0 (1, 1)
	6 getfield (1, 1)
	7 org/apache/commons/math3/util/MultidimensionalCounter.totalSize:I (1, 1)
	9 if_icmplt (1, 1)
	10 26 (1, 1)
	12 new (1, 1)
	13 org/apache/commons/math3/exception/OutOfRangeException (1, 1)
	15 dup (1, 1)
	16 iload_1 (1, 1)
	17 invokestatic (1, 1)
	18 java/lang/Integer.valueOf:(I)Ljava/lang/Integer; (1, 1)
	20 iconst_0 (1, 1)
	21 invokestatic (1, 1)
	22 java/lang/Integer.valueOf:(I)Ljava/lang/Integer; (1, 1)
	24 aload_0 (1, 1)
	25 getfield (1, 1)
	26 org/apache/commons/math3/util/MultidimensionalCounter.totalSize:I (1, 1)
	28 invokestatic (1, 1)
	29 java/lang/Integer.valueOf:(I)Ljava/lang/Integer; (1, 1)
	31 invokespecial (1, 1)
	32 org/apache/commons/math3/exception/OutOfRangeException.<init>:(Ljava/lang/Number;Ljava/lang/Number;Ljava/lang/Number;)V (1, 1)
	34 athrow (1, 1)
	35 aload_0 (1, 1)
	36 getfield (1, 1)
	37 org/apache/commons/math3/util/MultidimensionalCounter.dimension:I (1, 1)
	39 newarray (1, 1)
	40 10 (1, 1)
	41 astore_2 (1, 1)
	42 iconst_0 (1, 1)
	43 istore_3 (1, 1)
	44 iconst_0 (2, 4)
	45 istore (2, 4)
	46 #4 (2, 4)
	47 iload (2, 4)
	48 #4 (2, 4)
	49 aload_0 (2, 4)
	50 getfield (2, 4)
	51 org/apache/commons/math3/util/MultidimensionalCounter.last:I (2, 4)
	53 if_icmpge (2, 4)
	54 51 (2, 4)
	56 iconst_0 (2, 4)
	57 istore (2, 4)
	58 #5 (2, 4)
	59 aload_0 (2, 4)
	60 getfield (2, 4)
	61 org/apache/commons/math3/util/MultidimensionalCounter.uniCounterOffset:[I (2, 4)
	63 iload (2, 4)
	64 #4 (2, 4)
	65 iaload (2, 4)
	66 istore (2, 4)
	67 #6 (2, 4)
	68 iload_3 (3, 3)
	69 iload_1 (3, 3)
	70 if_icmpgt (3, 3)
	71 14 (3, 3)
	73 iload_3 (3, 3)
	74 iload (3, 3)
	75 #6 (3, 3)
	76 iadd (3, 3)
	77 istore_3 (3, 3)
	78 iinc (3, 3)
	79 #5 (3, 3)
	80 -89 (3, 3)
	81 goto (3, 3)
	82 -13 (3, 3)
	84 iinc (2, 4)
	85 #5 (2, 4)
	86 29 (2, 4)
	87 iload_3 (2, 4)
	88 iload (2, 4)
	89 #6 (2, 4)
	90 isub (2, 4)
	91 istore_3 (2, 4)
	92 aload_2 (2, 4)
	93 iload (2, 4)
	94 #4 (2, 4)
	95 iload (2, 4)
	96 #5 (2, 4)
	97 iastore (2, 4)
	98 iinc (2, 4)
	99 #4 (2, 4)
	100 -89 (2, 4)
	101 goto (2, 4)
	102 -54 (2, 4)
	104 aload_2 (1, 1)
	105 aload_0 (1, 1)
	106 getfield (1, 1)
	107 org/apache/commons/math3/util/MultidimensionalCounter.last:I (1, 1)
	109 iload_1 (1, 1)
	110 iload_3 (1, 1)
	111 isub (1, 1)
	112 iastore (1, 1)
	113 aload_2 (1, 1)
	114 areturn (0, 1)

Method: getCount
	0 aload_1 (1, 1)
	1 arraylength (1, 1)
	2 aload_0 (1, 1)
	3 getfield (1, 1)
	4 org/apache/commons/math3/util/MultidimensionalCounter.dimension:I (1, 1)
	6 if_icmpeq (1, 1)
	7 17 (1, 1)
	9 new (1, 1)
	10 org/apache/commons/math3/exception/DimensionMismatchException (1, 1)
	12 dup (1, 1)
	13 aload_1 (1, 1)
	14 arraylength (1, 1)
	15 aload_0 (1, 1)
	16 getfield (1, 1)
	17 org/apache/commons/math3/util/MultidimensionalCounter.dimension:I (1, 1)
	19 invokespecial (1, 1)
	20 org/apache/commons/math3/exception/DimensionMismatchException.<init>:(II)V (1, 1)
	22 athrow (1, 1)
	23 iconst_0 (0, 0)
	24 istore_2 (0, 0)
	25 iconst_0 (1, 4)
	26 istore_3 (1, 4)
	27 iload_3 (1, 4)
	28 aload_0 (1, 4)
	29 getfield (1, 4)
	30 org/apache/commons/math3/util/MultidimensionalCounter.dimension:I (1, 4)
	32 if_icmpge (1, 4)
	33 71 (1, 4)
	35 aload_1 (1, 4)
	36 iload_3 (1, 4)
	37 iaload (1, 4)
	38 istore (1, 4)
	39 #4 (1, 4)
	40 iload (2, 1)
	41 #4 (2, 1)
	42 iflt (2, 1)
	43 14 (2, 1)
	45 iload (2, 1)
	46 #4 (2, 1)
	47 aload_0 (2, 1)
	48 getfield (2, 1)
	49 org/apache/commons/math3/util/MultidimensionalCounter.size:[I (2, 1)
	51 iload_3 (2, 1)
	52 iaload (2, 1)
	53 if_icmplt (2, 1)
	54 31 (2, 1)
	56 new (2, 1)
	57 org/apache/commons/math3/exception/OutOfRangeException (2, 1)
	59 dup (2, 1)
	60 iload (2, 1)
	61 #4 (2, 1)
	62 invokestatic (2, 1)
	63 java/lang/Integer.valueOf:(I)Ljava/lang/Integer; (2, 1)
	65 iconst_0 (2, 1)
	66 invokestatic (2, 1)
	67 java/lang/Integer.valueOf:(I)Ljava/lang/Integer; (2, 1)
	69 aload_0 (2, 1)
	70 getfield (2, 1)
	71 org/apache/commons/math3/util/MultidimensionalCounter.size:[I (2, 1)
	73 iload_3 (2, 1)
	74 iaload (2, 1)
	75 iconst_1 (2, 1)
	76 isub (2, 1)
	77 invokestatic (2, 1)
	78 java/lang/Integer.valueOf:(I)Ljava/lang/Integer; (2, 1)
	80 invokespecial (2, 1)
	81 org/apache/commons/math3/exception/OutOfRangeException.<init>:(Ljava/lang/Number;Ljava/lang/Number;Ljava/lang/Number;)V (2, 1)
	83 athrow (2, 1)
	84 iload_2 (2, 1)
	85 aload_0 (2, 1)
	86 getfield (2, 1)
	87 org/apache/commons/math3/util/MultidimensionalCounter.uniCounterOffset:[I (2, 1)
	89 iload_3 (2, 1)
	90 iaload (2, 1)
	91 aload_1 (2, 1)
	92 iload_3 (2, 1)
	93 iaload (2, 1)
	94 imul (2, 1)
	95 iadd (2, 1)
	96 istore_2 (2, 1)
	97 iinc (2, 1)
	98 #3 (2, 1)
	99 -89 (2, 1)
	100 goto (2, 1)
	101 -73 (2, 1)
	103 iload_2 (0, 0)
	104 aload_1 (0, 0)
	105 aload_0 (0, 0)
	106 getfield (0, 0)
	107 org/apache/commons/math3/util/MultidimensionalCounter.last:I (0, 0)
	109 iaload (0, 0)
	110 iadd (0, 0)
	111 ireturn (0, 0)

Method: getSize
	0 aload_0 (0, 0)
	1 getfield (0, 0)
	2 org/apache/commons/math3/util/MultidimensionalCounter.totalSize:I (0, 0)
	4 ireturn (0, 0)

Method: getSizes
	0 aload_0 (0, 0)
	1 getfield (0, 0)
	2 org/apache/commons/math3/util/MultidimensionalCounter.size:[I (0, 0)
	4 invokestatic (0, 0)
	5 org/apache/commons/math3/util/MathArrays.copyOf:([I)[I (0, 0)
	7 areturn (0, 0)

Method: toString
	0 new (0, 0)
	1 java/lang/StringBuilder (0, 0)
	3 dup (0, 0)
	4 invokespecial (0, 0)
	5 java/lang/StringBuilder.<init>:()V (0, 0)
	7 astore_1 (0, 0)
	8 iconst_0 (1, 4)
	9 istore_2 (1, 4)
	10 iload_2 (1, 4)
	11 aload_0 (1, 4)
	12 getfield (1, 4)
	13 org/apache/commons/math3/util/MultidimensionalCounter.dimension:I (1, 4)
	15 if_icmpge (1, 4)
	16 35 (1, 4)
	18 aload_1 (1, 4)
	19 ldc (1, 4)
	20 [ (1, 4)
	21 invokevirtual (1, 4)
	22 java/lang/StringBuilder.append:(Ljava/lang/String;)Ljava/lang/StringBuilder; (1, 4)
	24 aload_0 (1, 4)
	25 iconst_1 (1, 4)
	26 newarray (1, 4)
	27 10 (1, 4)
	28 dup (1, 4)
	29 iconst_0 (1, 4)
	30 iload_2 (1, 4)
	31 iastore (1, 4)
	32 invokevirtual (1, 4)
	33 org/apache/commons/math3/util/MultidimensionalCounter.getCount:([I)I (1, 4)
	35 invokevirtual (1, 4)
	36 java/lang/StringBuilder.append:(I)Ljava/lang/StringBuilder; (1, 4)
	38 ldc (1, 4)
	39 ] (1, 4)
	40 invokevirtual (1, 4)
	41 java/lang/StringBuilder.append:(Ljava/lang/String;)Ljava/lang/StringBuilder; (1, 4)
	43 pop (1, 4)
	44 iinc (1, 4)
	45 #2 (1, 4)
	46 -89 (1, 4)
	47 goto (1, 4)
	48 -37 (1, 4)
	50 aload_1 (0, 0)
	51 invokevirtual (0, 0)
	52 java/lang/StringBuilder.toString:()Ljava/lang/String; (0, 0)
	54 areturn (0, 0)

Method: access$000
	0 aload_0 (0, 0)
	1 getfield (0, 0)
	2 org/apache/commons/math3/util/MultidimensionalCounter.dimension:I (0, 0)
	4 ireturn (0, 0)

Method: access$100
	0 aload_0 (0, 0)
	1 getfield (0, 0)
	2 org/apache/commons/math3/util/MultidimensionalCounter.totalSize:I (0, 0)
	4 ireturn (0, 0)

Method: access$200
	0 aload_0 (0, 0)
	1 getfield (0, 0)
	2 org/apache/commons/math3/util/MultidimensionalCounter.last:I (0, 0)
	4 ireturn (0, 0)

Method: access$300
	0 aload_0 (0, 0)
	1 getfield (0, 0)
	2 org/apache/commons/math3/util/MultidimensionalCounter.size:[I (0, 0)
	4 areturn (0, 0)

