Method: <init>
	0 aload_0 (0, 0)
	1 aload_1 (0, 0)
	2 putfield (0, 0)
	3 org/apache/commons/math3/util/OpenIntToFieldHashMap$Iterator.this$0:Lorg/apache/commons/math3/util/OpenIntToFieldHashMap; (0, 0)
	5 aload_0 (0, 0)
	6 invokespecial (0, 0)
	7 java/lang/Object.<init>:()V (0, 0)
	9 aload_0 (1, 1)
	10 aload_1 (1, 1)
	11 invokestatic (1, 1)
	12 org/apache/commons/math3/util/OpenIntToFieldHashMap.access$100:(Lorg/apache/commons/math3/util/OpenIntToFieldHashMap;)I (1, 1)
	14 putfield (1, 1)
	15 org/apache/commons/math3/util/OpenIntToFieldHashMap$Iterator.referenceCount:I (1, 1)
	17 aload_0 (1, 1)
	18 iconst_m1 (1, 1)
	19 putfield (1, 1)
	20 org/apache/commons/math3/util/OpenIntToFieldHashMap$Iterator.next:I (1, 1)
	22 aload_0 (1, 1)
	23 invokevirtual (1, 1)
	24 org/apache/commons/math3/util/OpenIntToFieldHashMap$Iterator.advance:()V (1, 1)
	26 goto (1, 1)
	27 4 (1, 1)
	29 astore_2 (1, 1)
	30 return (0, 0)

Method: hasNext
	0 aload_0 (0, 0)
	1 getfield (0, 0)
	2 org/apache/commons/math3/util/OpenIntToFieldHashMap$Iterator.next:I (0, 0)
	4 iflt (0, 0)
	5 7 (0, 0)
	7 iconst_1 (0, 0)
	8 goto (0, 0)
	9 4 (0, 0)
	11 iconst_0 (0, 0)
	12 ireturn (0, 0)

Method: key
	0 aload_0 (1, 1)
	1 getfield (1, 1)
	2 org/apache/commons/math3/util/OpenIntToFieldHashMap$Iterator.referenceCount:I (1, 1)
	4 aload_0 (1, 1)
	5 getfield (1, 1)
	6 org/apache/commons/math3/util/OpenIntToFieldHashMap$Iterator.this$0:Lorg/apache/commons/math3/util/OpenIntToFieldHashMap; (1, 1)
	8 invokestatic (1, 1)
	9 org/apache/commons/math3/util/OpenIntToFieldHashMap.access$100:(Lorg/apache/commons/math3/util/OpenIntToFieldHashMap;)I (1, 1)
	11 if_icmpeq (1, 1)
	12 11 (1, 1)
	14 new (1, 1)
	15 java/util/ConcurrentModificationException (1, 1)
	17 dup (1, 1)
	18 invokespecial (1, 1)
	19 java/util/ConcurrentModificationException.<init>:()V (1, 1)
	21 athrow (1, 1)
	22 aload_0 (1, 1)
	23 getfield (1, 1)
	24 org/apache/commons/math3/util/OpenIntToFieldHashMap$Iterator.current:I (1, 1)
	26 ifge (1, 1)
	27 11 (1, 1)
	29 new (1, 1)
	30 java/util/NoSuchElementException (1, 1)
	32 dup (1, 1)
	33 invokespecial (1, 1)
	34 java/util/NoSuchElementException.<init>:()V (1, 1)
	36 athrow (1, 1)
	37 aload_0 (0, 0)
	38 getfield (0, 0)
	39 org/apache/commons/math3/util/OpenIntToFieldHashMap$Iterator.this$0:Lorg/apache/commons/math3/util/OpenIntToFieldHashMap; (0, 0)
	41 invokestatic (0, 0)
	42 org/apache/commons/math3/util/OpenIntToFieldHashMap.access$200:(Lorg/apache/commons/math3/util/OpenIntToFieldHashMap;)[I (0, 0)
	44 aload_0 (0, 0)
	45 getfield (0, 0)
	46 org/apache/commons/math3/util/OpenIntToFieldHashMap$Iterator.current:I (0, 0)
	48 iaload (0, 0)
	49 ireturn (0, 0)

Method: value
	0 aload_0 (1, 1)
	1 getfield (1, 1)
	2 org/apache/commons/math3/util/OpenIntToFieldHashMap$Iterator.referenceCount:I (1, 1)
	4 aload_0 (1, 1)
	5 getfield (1, 1)
	6 org/apache/commons/math3/util/OpenIntToFieldHashMap$Iterator.this$0:Lorg/apache/commons/math3/util/OpenIntToFieldHashMap; (1, 1)
	8 invokestatic (1, 1)
	9 org/apache/commons/math3/util/OpenIntToFieldHashMap.access$100:(Lorg/apache/commons/math3/util/OpenIntToFieldHashMap;)I (1, 1)
	11 if_icmpeq (1, 1)
	12 11 (1, 1)
	14 new (1, 1)
	15 java/util/ConcurrentModificationException (1, 1)
	17 dup (1, 1)
	18 invokespecial (1, 1)
	19 java/util/ConcurrentModificationException.<init>:()V (1, 1)
	21 athrow (1, 1)
	22 aload_0 (1, 1)
	23 getfield (1, 1)
	24 org/apache/commons/math3/util/OpenIntToFieldHashMap$Iterator.current:I (1, 1)
	26 ifge (1, 1)
	27 11 (1, 1)
	29 new (1, 1)
	30 java/util/NoSuchElementException (1, 1)
	32 dup (1, 1)
	33 invokespecial (1, 1)
	34 java/util/NoSuchElementException.<init>:()V (1, 1)
	36 athrow (1, 1)
	37 aload_0 (0, 0)
	38 getfield (0, 0)
	39 org/apache/commons/math3/util/OpenIntToFieldHashMap$Iterator.this$0:Lorg/apache/commons/math3/util/OpenIntToFieldHashMap; (0, 0)
	41 invokestatic (0, 0)
	42 org/apache/commons/math3/util/OpenIntToFieldHashMap.access$300:(Lorg/apache/commons/math3/util/OpenIntToFieldHashMap;)[Lorg/apache/commons/math3/FieldElement; (0, 0)
	44 aload_0 (0, 0)
	45 getfield (0, 0)
	46 org/apache/commons/math3/util/OpenIntToFieldHashMap$Iterator.current:I (0, 0)
	48 aaload (0, 0)
	49 areturn (0, 0)

Method: advance
	0 aload_0 (1, 1)
	1 getfield (1, 1)
	2 org/apache/commons/math3/util/OpenIntToFieldHashMap$Iterator.referenceCount:I (1, 1)
	4 aload_0 (1, 1)
	5 getfield (1, 1)
	6 org/apache/commons/math3/util/OpenIntToFieldHashMap$Iterator.this$0:Lorg/apache/commons/math3/util/OpenIntToFieldHashMap; (1, 1)
	8 invokestatic (1, 1)
	9 org/apache/commons/math3/util/OpenIntToFieldHashMap.access$100:(Lorg/apache/commons/math3/util/OpenIntToFieldHashMap;)I (1, 1)
	11 if_icmpeq (1, 1)
	12 11 (1, 1)
	14 new (1, 1)
	15 java/util/ConcurrentModificationException (1, 1)
	17 dup (1, 1)
	18 invokespecial (1, 1)
	19 java/util/ConcurrentModificationException.<init>:()V (1, 1)
	21 athrow (1, 1)
	22 aload_0 (0, 0)
	23 aload_0 (0, 0)
	24 getfield (0, 0)
	25 org/apache/commons/math3/util/OpenIntToFieldHashMap$Iterator.next:I (0, 0)
	27 putfield (0, 0)
	28 org/apache/commons/math3/util/OpenIntToFieldHashMap$Iterator.current:I (0, 0)
	30 aload_0 (2, 3)
	31 getfield (2, 3)
	32 org/apache/commons/math3/util/OpenIntToFieldHashMap$Iterator.this$0:Lorg/apache/commons/math3/util/OpenIntToFieldHashMap; (2, 3)
	34 invokestatic (2, 3)
	35 org/apache/commons/math3/util/OpenIntToFieldHashMap.access$400:(Lorg/apache/commons/math3/util/OpenIntToFieldHashMap;)[B (2, 3)
	37 aload_0 (2, 3)
	38 dup (2, 3)
	39 getfield (2, 3)
	40 org/apache/commons/math3/util/OpenIntToFieldHashMap$Iterator.next:I (2, 3)
	42 iconst_1 (2, 3)
	43 iadd (2, 3)
	44 dup_x1 (2, 3)
	45 putfield (2, 3)
	46 org/apache/commons/math3/util/OpenIntToFieldHashMap$Iterator.next:I (2, 3)
	48 baload (2, 3)
	49 iconst_1 (2, 3)
	50 if_icmpeq (2, 3)
	51 6 (2, 3)
	53 goto (2, 3)
	54 -23 (2, 3)
	56 goto (0, 0)
	57 25 (0, 0)
	59 astore_1 (0, 0)
	60 aload_0 (0, 0)
	61 bipush (0, 0)
	62 -2 (0, 0)
	63 putfield (0, 0)
	64 org/apache/commons/math3/util/OpenIntToFieldHashMap$Iterator.next:I (0, 0)
	66 aload_0 (1, 1)
	67 getfield (1, 1)
	68 org/apache/commons/math3/util/OpenIntToFieldHashMap$Iterator.current:I (1, 1)
	70 ifge (1, 1)
	71 11 (1, 1)
	73 new (1, 1)
	74 java/util/NoSuchElementException (1, 1)
	76 dup (1, 1)
	77 invokespecial (1, 1)
	78 java/util/NoSuchElementException.<init>:()V (1, 1)
	80 athrow (1, 1)
	81 return (0, 0)

