Method: <init>
	0 aload_0 (0, 0)
	1 invokespecial (0, 0)
	2 java/lang/Object.<init>:()V (0, 0)
	4 aload_1 (0, 0)
	5 getfield (0, 0)
	6 org/apache/commons/math3/util/OpenIntToDoubleHashMap.keys:[I (0, 0)
	8 arraylength (0, 0)
	9 istore_2 (0, 0)
	10 aload_0 (0, 0)
	11 iload_2 (0, 0)
	12 newarray (0, 0)
	13 10 (0, 0)
	14 putfield (0, 0)
	15 org/apache/commons/math3/util/OpenIntToDoubleHashMap.keys:[I (0, 0)
	17 aload_1 (0, 0)
	18 getfield (0, 0)
	19 org/apache/commons/math3/util/OpenIntToDoubleHashMap.keys:[I (0, 0)
	21 iconst_0 (0, 0)
	22 aload_0 (0, 0)
	23 getfield (0, 0)
	24 org/apache/commons/math3/util/OpenIntToDoubleHashMap.keys:[I (0, 0)
	26 iconst_0 (0, 0)
	27 iload_2 (0, 0)
	28 invokestatic (0, 0)
	29 java/lang/System.arraycopy:(Ljava/lang/Object;ILjava/lang/Object;II)V (0, 0)
	31 aload_0 (0, 0)
	32 iload_2 (0, 0)
	33 newarray (0, 0)
	34 7 (0, 0)
	35 putfield (0, 0)
	36 org/apache/commons/math3/util/OpenIntToDoubleHashMap.values:[D (0, 0)
	38 aload_1 (0, 0)
	39 getfield (0, 0)
	40 org/apache/commons/math3/util/OpenIntToDoubleHashMap.values:[D (0, 0)
	42 iconst_0 (0, 0)
	43 aload_0 (0, 0)
	44 getfield (0, 0)
	45 org/apache/commons/math3/util/OpenIntToDoubleHashMap.values:[D (0, 0)
	47 iconst_0 (0, 0)
	48 iload_2 (0, 0)
	49 invokestatic (0, 0)
	50 java/lang/System.arraycopy:(Ljava/lang/Object;ILjava/lang/Object;II)V (0, 0)
	52 aload_0 (0, 0)
	53 iload_2 (0, 0)
	54 newarray (0, 0)
	55 8 (0, 0)
	56 putfield (0, 0)
	57 org/apache/commons/math3/util/OpenIntToDoubleHashMap.states:[B (0, 0)
	59 aload_1 (0, 0)
	60 getfield (0, 0)
	61 org/apache/commons/math3/util/OpenIntToDoubleHashMap.states:[B (0, 0)
	63 iconst_0 (0, 0)
	64 aload_0 (0, 0)
	65 getfield (0, 0)
	66 org/apache/commons/math3/util/OpenIntToDoubleHashMap.states:[B (0, 0)
	68 iconst_0 (0, 0)
	69 iload_2 (0, 0)
	70 invokestatic (0, 0)
	71 java/lang/System.arraycopy:(Ljava/lang/Object;ILjava/lang/Object;II)V (0, 0)
	73 aload_0 (0, 0)
	74 aload_1 (0, 0)
	75 getfield (0, 0)
	76 org/apache/commons/math3/util/OpenIntToDoubleHashMap.missingEntries:D (0, 0)
	78 putfield (0, 0)
	79 org/apache/commons/math3/util/OpenIntToDoubleHashMap.missingEntries:D (0, 0)
	81 aload_0 (0, 0)
	82 aload_1 (0, 0)
	83 getfield (0, 0)
	84 org/apache/commons/math3/util/OpenIntToDoubleHashMap.size:I (0, 0)
	86 putfield (0, 0)
	87 org/apache/commons/math3/util/OpenIntToDoubleHashMap.size:I (0, 0)
	89 aload_0 (0, 0)
	90 aload_1 (0, 0)
	91 getfield (0, 0)
	92 org/apache/commons/math3/util/OpenIntToDoubleHashMap.mask:I (0, 0)
	94 putfield (0, 0)
	95 org/apache/commons/math3/util/OpenIntToDoubleHashMap.mask:I (0, 0)
	97 aload_0 (0, 0)
	98 aload_1 (0, 0)
	99 getfield (0, 0)
	100 org/apache/commons/math3/util/OpenIntToDoubleHashMap.count:I (0, 0)
	102 putfield (0, 0)
	103 org/apache/commons/math3/util/OpenIntToDoubleHashMap.count:I (0, 0)
	105 return (0, 0)

Method: computeCapacity
	0 iload_0 (1, 1)
	1 ifne (1, 1)
	2 5 (1, 1)
	4 iconst_1 (1, 1)
	5 ireturn (1, 1)
	6 iload_0 (0, 0)
	7 i2f (0, 0)
	8 ldc (0, 0)
	9 0.5 (0, 0)
	10 fdiv (0, 0)
	11 f2d (0, 0)
	12 invokestatic (0, 0)
	13 org/apache/commons/math3/util/FastMath.ceil:(D)D (0, 0)
	15 d2i (0, 0)
	16 istore_1 (0, 0)
	17 iload_1 (0, 0)
	18 invokestatic (0, 0)
	19 java/lang/Integer.highestOneBit:(I)I (0, 0)
	21 istore_2 (0, 0)
	22 iload_2 (1, 1)
	23 iload_1 (1, 1)
	24 if_icmpne (1, 1)
	25 5 (1, 1)
	27 iload_1 (1, 1)
	28 ireturn (1, 1)
	29 iload_1 (0, 0)
	30 invokestatic (0, 0)
	31 org/apache/commons/math3/util/OpenIntToDoubleHashMap.nextPowerOfTwo:(I)I (0, 0)
	33 ireturn (0, 0)

Method: nextPowerOfTwo
	0 iload_0 (0, 0)
	1 invokestatic (0, 0)
	2 java/lang/Integer.highestOneBit:(I)I (0, 0)
	4 iconst_1 (0, 0)
	5 ishl (0, 0)
	6 ireturn (0, 0)

Method: get
	0 iload_1 (0, 0)
	1 invokestatic (0, 0)
	2 org/apache/commons/math3/util/OpenIntToDoubleHashMap.hashOf:(I)I (0, 0)
	4 istore_2 (0, 0)
	5 iload_2 (0, 0)
	6 aload_0 (0, 0)
	7 getfield (0, 0)
	8 org/apache/commons/math3/util/OpenIntToDoubleHashMap.mask:I (0, 0)
	10 iand (0, 0)
	11 istore_3 (0, 0)
	12 aload_0 (1, 1)
	13 iload_1 (1, 1)
	14 iload_3 (1, 1)
	15 invokespecial (1, 1)
	16 org/apache/commons/math3/util/OpenIntToDoubleHashMap.containsKey:(II)Z (1, 1)
	18 ifeq (1, 1)
	19 10 (1, 1)
	21 aload_0 (1, 1)
	22 getfield (1, 1)
	23 org/apache/commons/math3/util/OpenIntToDoubleHashMap.values:[D (1, 1)
	25 iload_3 (1, 1)
	26 daload (1, 1)
	27 dreturn (1, 1)
	28 aload_0 (1, 1)
	29 getfield (1, 1)
	30 org/apache/commons/math3/util/OpenIntToDoubleHashMap.states:[B (1, 1)
	32 iload_3 (1, 1)
	33 baload (1, 1)
	34 ifne (1, 1)
	35 8 (1, 1)
	37 aload_0 (1, 1)
	38 getfield (1, 1)
	39 org/apache/commons/math3/util/OpenIntToDoubleHashMap.missingEntries:D (1, 1)
	41 dreturn (1, 1)
	42 iload_3 (0, 0)
	43 istore (0, 0)
	44 #4 (0, 0)
	45 iload_2 (1, 4)
	46 invokestatic (1, 4)
	47 org/apache/commons/math3/util/OpenIntToDoubleHashMap.perturb:(I)I (1, 4)
	49 istore (1, 4)
	50 #5 (1, 4)
	51 aload_0 (1, 4)
	52 getfield (1, 4)
	53 org/apache/commons/math3/util/OpenIntToDoubleHashMap.states:[B (1, 4)
	55 iload_3 (1, 4)
	56 baload (1, 4)
	57 ifeq (1, 4)
	58 45 (1, 4)
	60 iload (1, 4)
	61 #5 (1, 4)
	62 iload (1, 4)
	63 #4 (1, 4)
	64 invokestatic (1, 4)
	65 org/apache/commons/math3/util/OpenIntToDoubleHashMap.probe:(II)I (1, 4)
	67 istore (1, 4)
	68 #4 (1, 4)
	69 iload (1, 4)
	70 #4 (1, 4)
	71 aload_0 (1, 4)
	72 getfield (1, 4)
	73 org/apache/commons/math3/util/OpenIntToDoubleHashMap.mask:I (1, 4)
	75 iand (1, 4)
	76 istore_3 (1, 4)
	77 aload_0 (2, 1)
	78 iload_1 (2, 1)
	79 iload_3 (2, 1)
	80 invokespecial (2, 1)
	81 org/apache/commons/math3/util/OpenIntToDoubleHashMap.containsKey:(II)Z (2, 1)
	83 ifeq (2, 1)
	84 10 (2, 1)
	86 aload_0 (2, 1)
	87 getfield (2, 1)
	88 org/apache/commons/math3/util/OpenIntToDoubleHashMap.values:[D (2, 1)
	90 iload_3 (2, 1)
	91 daload (2, 1)
	92 dreturn (2, 1)
	93 iload (2, 1)
	94 #5 (2, 1)
	95 iconst_5 (2, 1)
	96 ishr (2, 1)
	97 istore (2, 1)
	98 #5 (2, 1)
	99 goto (2, 1)
	100 -48 (2, 1)
	102 aload_0 (1, 4)
	103 getfield (1, 4)
	104 org/apache/commons/math3/util/OpenIntToDoubleHashMap.missingEntries:D (1, 4)
	106 dreturn (1, 4)

Method: containsKey
	0 iload_1 (0, 0)
	1 ifne (0, 0)
	2 13 (0, 0)
	4 aload_0 (0, 0)
	5 getfield (0, 0)
	6 org/apache/commons/math3/util/OpenIntToDoubleHashMap.states:[B (0, 0)
	8 iload_2 (0, 0)
	9 baload (0, 0)
	10 iconst_1 (0, 0)
	11 if_icmpne (0, 0)
	12 17 (0, 0)
	14 aload_0 (0, 0)
	15 getfield (0, 0)
	16 org/apache/commons/math3/util/OpenIntToDoubleHashMap.keys:[I (0, 0)
	18 iload_2 (0, 0)
	19 iaload (0, 0)
	20 iload_1 (0, 0)
	21 if_icmpne (0, 0)
	22 7 (0, 0)
	24 iconst_1 (0, 0)
	25 goto (0, 0)
	26 4 (0, 0)
	28 iconst_0 (0, 0)
	29 ireturn (0, 0)

Method: iterator
	0 new (0, 0)
	1 org/apache/commons/math3/util/OpenIntToDoubleHashMap$Iterator (0, 0)
	3 dup (0, 0)
	4 aload_0 (0, 0)
	5 aconst_null (0, 0)
	6 invokespecial (0, 0)
	7 org/apache/commons/math3/util/OpenIntToDoubleHashMap$Iterator.<init>:(Lorg/apache/commons/math3/util/OpenIntToDoubleHashMap;Lorg/apache/commons/math3/util/OpenIntToDoubleHashMap$1;)V (0, 0)
	9 areturn (0, 0)

Method: perturb
	0 iload_0 (0, 0)
	1 ldc (0, 0)
	2 2147483647 (0, 0)
	3 iand (0, 0)
	4 ireturn (0, 0)

Method: findInsertionIndex
	0 iload_2 (0, 0)
	1 invokestatic (0, 0)
	2 org/apache/commons/math3/util/OpenIntToDoubleHashMap.hashOf:(I)I (0, 0)
	4 istore (0, 0)
	5 #4 (0, 0)
	6 iload (0, 0)
	7 #4 (0, 0)
	8 iload_3 (0, 0)
	9 iand (0, 0)
	10 istore (0, 0)
	11 #5 (0, 0)
	12 aload_1 (1, 1)
	13 iload (1, 1)
	14 #5 (1, 1)
	15 baload (1, 1)
	16 ifne (1, 1)
	17 6 (1, 1)
	19 iload (1, 1)
	20 #5 (1, 1)
	21 ireturn (1, 1)
	22 aload_1 (1, 1)
	23 iload (1, 1)
	24 #5 (1, 1)
	25 baload (1, 1)
	26 iconst_1 (1, 1)
	27 if_icmpne (1, 1)
	28 17 (1, 1)
	30 aload_0 (1, 1)
	31 iload (1, 1)
	32 #5 (1, 1)
	33 iaload (1, 1)
	34 iload_2 (1, 1)
	35 if_icmpne (1, 1)
	36 9 (1, 1)
	38 iload (1, 1)
	39 #5 (1, 1)
	40 invokestatic (1, 1)
	41 org/apache/commons/math3/util/OpenIntToDoubleHashMap.changeIndexSign:(I)I (1, 1)
	43 ireturn (1, 1)
	44 iload (0, 0)
	45 #4 (0, 0)
	46 invokestatic (0, 0)
	47 org/apache/commons/math3/util/OpenIntToDoubleHashMap.perturb:(I)I (0, 0)
	49 istore (0, 0)
	50 #6 (0, 0)
	51 iload (0, 0)
	52 #5 (0, 0)
	53 istore (0, 0)
	54 #7 (0, 0)
	55 aload_1 (1, 1)
	56 iload (1, 1)
	57 #5 (1, 1)
	58 baload (1, 1)
	59 iconst_1 (1, 1)
	60 if_icmpne (1, 1)
	61 43 (1, 1)
	63 iload (2, 3)
	64 #6 (2, 3)
	65 iload (2, 3)
	66 #7 (2, 3)
	67 invokestatic (2, 3)
	68 org/apache/commons/math3/util/OpenIntToDoubleHashMap.probe:(II)I (2, 3)
	70 istore (2, 3)
	71 #7 (2, 3)
	72 iload (2, 3)
	73 #7 (2, 3)
	74 iload_3 (2, 3)
	75 iand (2, 3)
	76 istore (2, 3)
	77 #5 (2, 3)
	78 iload (2, 3)
	79 #6 (2, 3)
	80 iconst_5 (2, 3)
	81 ishr (2, 3)
	82 istore (2, 3)
	83 #6 (2, 3)
	84 aload_1 (3, 1)
	85 iload (3, 1)
	86 #5 (3, 1)
	87 baload (3, 1)
	88 iconst_1 (3, 1)
	89 if_icmpne (3, 1)
	90 14 (3, 1)
	92 aload_0 (3, 1)
	93 iload (3, 1)
	94 #5 (3, 1)
	95 iaload (3, 1)
	96 iload_2 (3, 1)
	97 if_icmpne (3, 1)
	98 -34 (3, 1)
	100 goto (3, 1)
	101 3 (3, 1)
	103 aload_1 (1, 1)
	104 iload (1, 1)
	105 #5 (1, 1)
	106 baload (1, 1)
	107 ifne (1, 1)
	108 6 (1, 1)
	110 iload (1, 1)
	111 #5 (1, 1)
	112 ireturn (1, 1)
	113 aload_1 (1, 1)
	114 iload (1, 1)
	115 #5 (1, 1)
	116 baload (1, 1)
	117 iconst_1 (1, 1)
	118 if_icmpne (1, 1)
	119 9 (1, 1)
	121 iload (1, 1)
	122 #5 (1, 1)
	123 invokestatic (1, 1)
	124 org/apache/commons/math3/util/OpenIntToDoubleHashMap.changeIndexSign:(I)I (1, 1)
	126 ireturn (1, 1)
	127 iload (0, 0)
	128 #5 (0, 0)
	129 istore (0, 0)
	130 #8 (0, 0)
	131 iload (1, 3)
	132 #6 (1, 3)
	133 iload (1, 3)
	134 #7 (1, 3)
	135 invokestatic (1, 3)
	136 org/apache/commons/math3/util/OpenIntToDoubleHashMap.probe:(II)I (1, 3)
	138 istore (1, 3)
	139 #7 (1, 3)
	140 iload (1, 3)
	141 #7 (1, 3)
	142 iload_3 (1, 3)
	143 iand (1, 3)
	144 istore (1, 3)
	145 #5 (1, 3)
	146 aload_1 (2, 1)
	147 iload (2, 1)
	148 #5 (2, 1)
	149 baload (2, 1)
	150 ifne (2, 1)
	151 6 (2, 1)
	153 iload (2, 1)
	154 #8 (2, 1)
	155 ireturn (2, 1)
	156 aload_1 (2, 1)
	157 iload (2, 1)
	158 #5 (2, 1)
	159 baload (2, 1)
	160 iconst_1 (2, 1)
	161 if_icmpne (2, 1)
	162 17 (2, 1)
	164 aload_0 (2, 1)
	165 iload (2, 1)
	166 #5 (2, 1)
	167 iaload (2, 1)
	168 iload_2 (2, 1)
	169 if_icmpne (2, 1)
	170 9 (2, 1)
	172 iload (2, 1)
	173 #5 (2, 1)
	174 invokestatic (2, 1)
	175 org/apache/commons/math3/util/OpenIntToDoubleHashMap.changeIndexSign:(I)I (2, 1)
	177 ireturn (2, 1)
	178 iload (1, 3)
	179 #6 (1, 3)
	180 iconst_5 (1, 3)
	181 ishr (1, 3)
	182 istore (1, 3)
	183 #6 (1, 3)
	184 goto (1, 3)
	185 -53 (1, 3)

Method: probe
	0 iload_1 (0, 0)
	1 iconst_2 (0, 0)
	2 ishl (0, 0)
	3 iload_1 (0, 0)
	4 iadd (0, 0)
	5 iload_0 (0, 0)
	6 iadd (0, 0)
	7 iconst_1 (0, 0)
	8 iadd (0, 0)
	9 ireturn (0, 0)

Method: changeIndexSign
	0 iload_0 (0, 0)
	1 ineg (0, 0)
	2 iconst_1 (0, 0)
	3 isub (0, 0)
	4 ireturn (0, 0)

Method: size
	0 aload_0 (0, 0)
	1 getfield (0, 0)
	2 org/apache/commons/math3/util/OpenIntToDoubleHashMap.size:I (0, 0)
	4 ireturn (0, 0)

Method: remove
	0 iload_1 (0, 0)
	1 invokestatic (0, 0)
	2 org/apache/commons/math3/util/OpenIntToDoubleHashMap.hashOf:(I)I (0, 0)
	4 istore_2 (0, 0)
	5 iload_2 (0, 0)
	6 aload_0 (0, 0)
	7 getfield (0, 0)
	8 org/apache/commons/math3/util/OpenIntToDoubleHashMap.mask:I (0, 0)
	10 iand (0, 0)
	11 istore_3 (0, 0)
	12 aload_0 (1, 1)
	13 iload_1 (1, 1)
	14 iload_3 (1, 1)
	15 invokespecial (1, 1)
	16 org/apache/commons/math3/util/OpenIntToDoubleHashMap.containsKey:(II)Z (1, 1)
	18 ifeq (1, 1)
	19 9 (1, 1)
	21 aload_0 (1, 1)
	22 iload_3 (1, 1)
	23 invokespecial (1, 1)
	24 org/apache/commons/math3/util/OpenIntToDoubleHashMap.doRemove:(I)D (1, 1)
	26 dreturn (1, 1)
	27 aload_0 (1, 1)
	28 getfield (1, 1)
	29 org/apache/commons/math3/util/OpenIntToDoubleHashMap.states:[B (1, 1)
	31 iload_3 (1, 1)
	32 baload (1, 1)
	33 ifne (1, 1)
	34 8 (1, 1)
	36 aload_0 (1, 1)
	37 getfield (1, 1)
	38 org/apache/commons/math3/util/OpenIntToDoubleHashMap.missingEntries:D (1, 1)
	40 dreturn (1, 1)
	41 iload_3 (0, 0)
	42 istore (0, 0)
	43 #4 (0, 0)
	44 iload_2 (1, 4)
	45 invokestatic (1, 4)
	46 org/apache/commons/math3/util/OpenIntToDoubleHashMap.perturb:(I)I (1, 4)
	48 istore (1, 4)
	49 #5 (1, 4)
	50 aload_0 (1, 4)
	51 getfield (1, 4)
	52 org/apache/commons/math3/util/OpenIntToDoubleHashMap.states:[B (1, 4)
	54 iload_3 (1, 4)
	55 baload (1, 4)
	56 ifeq (1, 4)
	57 44 (1, 4)
	59 iload (1, 4)
	60 #5 (1, 4)
	61 iload (1, 4)
	62 #4 (1, 4)
	63 invokestatic (1, 4)
	64 org/apache/commons/math3/util/OpenIntToDoubleHashMap.probe:(II)I (1, 4)
	66 istore (1, 4)
	67 #4 (1, 4)
	68 iload (1, 4)
	69 #4 (1, 4)
	70 aload_0 (1, 4)
	71 getfield (1, 4)
	72 org/apache/commons/math3/util/OpenIntToDoubleHashMap.mask:I (1, 4)
	74 iand (1, 4)
	75 istore_3 (1, 4)
	76 aload_0 (2, 1)
	77 iload_1 (2, 1)
	78 iload_3 (2, 1)
	79 invokespecial (2, 1)
	80 org/apache/commons/math3/util/OpenIntToDoubleHashMap.containsKey:(II)Z (2, 1)
	82 ifeq (2, 1)
	83 9 (2, 1)
	85 aload_0 (2, 1)
	86 iload_3 (2, 1)
	87 invokespecial (2, 1)
	88 org/apache/commons/math3/util/OpenIntToDoubleHashMap.doRemove:(I)D (2, 1)
	90 dreturn (2, 1)
	91 iload (2, 1)
	92 #5 (2, 1)
	93 iconst_5 (2, 1)
	94 ishr (2, 1)
	95 istore (2, 1)
	96 #5 (2, 1)
	97 goto (2, 1)
	98 -47 (2, 1)
	100 aload_0 (1, 4)
	101 getfield (1, 4)
	102 org/apache/commons/math3/util/OpenIntToDoubleHashMap.missingEntries:D (1, 4)
	104 dreturn (1, 4)

Method: doRemove
	0 aload_0 (0, 0)
	1 getfield (0, 0)
	2 org/apache/commons/math3/util/OpenIntToDoubleHashMap.keys:[I (0, 0)
	4 iload_1 (0, 0)
	5 iconst_0 (0, 0)
	6 iastore (0, 0)
	7 aload_0 (0, 0)
	8 getfield (0, 0)
	9 org/apache/commons/math3/util/OpenIntToDoubleHashMap.states:[B (0, 0)
	11 iload_1 (0, 0)
	12 iconst_2 (0, 0)
	13 bastore (0, 0)
	14 aload_0 (0, 0)
	15 getfield (0, 0)
	16 org/apache/commons/math3/util/OpenIntToDoubleHashMap.values:[D (0, 0)
	18 iload_1 (0, 0)
	19 daload (0, 0)
	20 dstore_2 (0, 0)
	21 aload_0 (0, 0)
	22 getfield (0, 0)
	23 org/apache/commons/math3/util/OpenIntToDoubleHashMap.values:[D (0, 0)
	25 iload_1 (0, 0)
	26 aload_0 (0, 0)
	27 getfield (0, 0)
	28 org/apache/commons/math3/util/OpenIntToDoubleHashMap.missingEntries:D (0, 0)
	30 dastore (0, 0)
	31 aload_0 (0, 0)
	32 dup (0, 0)
	33 getfield (0, 0)
	34 org/apache/commons/math3/util/OpenIntToDoubleHashMap.size:I (0, 0)
	36 iconst_1 (0, 0)
	37 isub (0, 0)
	38 putfield (0, 0)
	39 org/apache/commons/math3/util/OpenIntToDoubleHashMap.size:I (0, 0)
	41 aload_0 (0, 0)
	42 dup (0, 0)
	43 getfield (0, 0)
	44 org/apache/commons/math3/util/OpenIntToDoubleHashMap.count:I (0, 0)
	46 iconst_1 (0, 0)
	47 iadd (0, 0)
	48 putfield (0, 0)
	49 org/apache/commons/math3/util/OpenIntToDoubleHashMap.count:I (0, 0)
	51 dload_2 (0, 0)
	52 dreturn (0, 0)

Method: put
	0 aload_0 (0, 0)
	1 iload_1 (0, 0)
	2 invokespecial (0, 0)
	3 org/apache/commons/math3/util/OpenIntToDoubleHashMap.findInsertionIndex:(I)I (0, 0)
	5 istore (0, 0)
	6 #4 (0, 0)
	7 aload_0 (0, 0)
	8 getfield (0, 0)
	9 org/apache/commons/math3/util/OpenIntToDoubleHashMap.missingEntries:D (0, 0)
	11 dstore (0, 0)
	12 #5 (0, 0)
	13 iconst_1 (0, 0)
	14 istore (0, 0)
	15 #7 (0, 0)
	16 iload (1, 1)
	17 #4 (1, 1)
	18 ifge (1, 1)
	19 22 (1, 1)
	21 iload (1, 1)
	22 #4 (1, 1)
	23 invokestatic (1, 1)
	24 org/apache/commons/math3/util/OpenIntToDoubleHashMap.changeIndexSign:(I)I (1, 1)
	26 istore (1, 1)
	27 #4 (1, 1)
	28 aload_0 (1, 1)
	29 getfield (1, 1)
	30 org/apache/commons/math3/util/OpenIntToDoubleHashMap.values:[D (1, 1)
	32 iload (1, 1)
	33 #4 (1, 1)
	34 daload (1, 1)
	35 dstore (1, 1)
	36 #5 (1, 1)
	37 iconst_0 (1, 1)
	38 istore (1, 1)
	39 #7 (1, 1)
	40 aload_0 (0, 0)
	41 getfield (0, 0)
	42 org/apache/commons/math3/util/OpenIntToDoubleHashMap.keys:[I (0, 0)
	44 iload (0, 0)
	45 #4 (0, 0)
	46 iload_1 (0, 0)
	47 iastore (0, 0)
	48 aload_0 (0, 0)
	49 getfield (0, 0)
	50 org/apache/commons/math3/util/OpenIntToDoubleHashMap.states:[B (0, 0)
	52 iload (0, 0)
	53 #4 (0, 0)
	54 iconst_1 (0, 0)
	55 bastore (0, 0)
	56 aload_0 (0, 0)
	57 getfield (0, 0)
	58 org/apache/commons/math3/util/OpenIntToDoubleHashMap.values:[D (0, 0)
	60 iload (0, 0)
	61 #4 (0, 0)
	62 dload_2 (0, 0)
	63 dastore (0, 0)
	64 iload (1, 1)
	65 #7 (1, 1)
	66 ifeq (1, 1)
	67 34 (1, 1)
	69 aload_0 (1, 1)
	70 dup (1, 1)
	71 getfield (1, 1)
	72 org/apache/commons/math3/util/OpenIntToDoubleHashMap.size:I (1, 1)
	74 iconst_1 (1, 1)
	75 iadd (1, 1)
	76 putfield (1, 1)
	77 org/apache/commons/math3/util/OpenIntToDoubleHashMap.size:I (1, 1)
	79 aload_0 (2, 1)
	80 invokespecial (2, 1)
	81 org/apache/commons/math3/util/OpenIntToDoubleHashMap.shouldGrowTable:()Z (2, 1)
	83 ifeq (2, 1)
	84 7 (2, 1)
	86 aload_0 (2, 1)
	87 invokespecial (2, 1)
	88 org/apache/commons/math3/util/OpenIntToDoubleHashMap.growTable:()V (2, 1)
	90 aload_0 (1, 1)
	91 dup (1, 1)
	92 getfield (1, 1)
	93 org/apache/commons/math3/util/OpenIntToDoubleHashMap.count:I (1, 1)
	95 iconst_1 (1, 1)
	96 iadd (1, 1)
	97 putfield (1, 1)
	98 org/apache/commons/math3/util/OpenIntToDoubleHashMap.count:I (1, 1)
	100 dload (0, 0)
	101 #5 (0, 0)
	102 dreturn (0, 0)

Method: growTable
	0 aload_0 (0, 0)
	1 getfield (0, 0)
	2 org/apache/commons/math3/util/OpenIntToDoubleHashMap.states:[B (0, 0)
	4 arraylength (0, 0)
	5 istore_1 (0, 0)
	6 aload_0 (0, 0)
	7 getfield (0, 0)
	8 org/apache/commons/math3/util/OpenIntToDoubleHashMap.keys:[I (0, 0)
	10 astore_2 (0, 0)
	11 aload_0 (0, 0)
	12 getfield (0, 0)
	13 org/apache/commons/math3/util/OpenIntToDoubleHashMap.values:[D (0, 0)
	15 astore_3 (0, 0)
	16 aload_0 (0, 0)
	17 getfield (0, 0)
	18 org/apache/commons/math3/util/OpenIntToDoubleHashMap.states:[B (0, 0)
	20 astore (0, 0)
	21 #4 (0, 0)
	22 iconst_2 (0, 0)
	23 iload_1 (0, 0)
	24 imul (0, 0)
	25 istore (0, 0)
	26 #5 (0, 0)
	27 iload (0, 0)
	28 #5 (0, 0)
	29 newarray (0, 0)
	30 10 (0, 0)
	31 astore (0, 0)
	32 #6 (0, 0)
	33 iload (0, 0)
	34 #5 (0, 0)
	35 newarray (0, 0)
	36 7 (0, 0)
	37 astore (0, 0)
	38 #7 (0, 0)
	39 iload (0, 0)
	40 #5 (0, 0)
	41 newarray (0, 0)
	42 8 (0, 0)
	43 astore (0, 0)
	44 #8 (0, 0)
	45 iload (0, 0)
	46 #5 (0, 0)
	47 iconst_1 (0, 0)
	48 isub (0, 0)
	49 istore (0, 0)
	50 #9 (0, 0)
	51 iconst_0 (1, 4)
	52 istore (1, 4)
	53 #10 (1, 4)
	54 iload (1, 4)
	55 #10 (1, 4)
	56 iload_1 (1, 4)
	57 if_icmpge (1, 4)
	58 59 (1, 4)
	60 aload (2, 1)
	61 #4 (2, 1)
	62 iload (2, 1)
	63 #10 (2, 1)
	64 baload (2, 1)
	65 iconst_1 (2, 1)
	66 if_icmpne (2, 1)
	67 44 (2, 1)
	69 aload_2 (2, 1)
	70 iload (2, 1)
	71 #10 (2, 1)
	72 iaload (2, 1)
	73 istore (2, 1)
	74 #11 (2, 1)
	75 aload (2, 1)
	76 #6 (2, 1)
	77 aload (2, 1)
	78 #8 (2, 1)
	79 iload (2, 1)
	80 #11 (2, 1)
	81 iload (2, 1)
	82 #9 (2, 1)
	83 invokestatic (2, 1)
	84 org/apache/commons/math3/util/OpenIntToDoubleHashMap.findInsertionIndex:([I[BII)I (2, 1)
	86 istore (2, 1)
	87 #12 (2, 1)
	88 aload (2, 1)
	89 #6 (2, 1)
	90 iload (2, 1)
	91 #12 (2, 1)
	92 iload (2, 1)
	93 #11 (2, 1)
	94 iastore (2, 1)
	95 aload (2, 1)
	96 #7 (2, 1)
	97 iload (2, 1)
	98 #12 (2, 1)
	99 aload_3 (2, 1)
	100 iload (2, 1)
	101 #10 (2, 1)
	102 daload (2, 1)
	103 dastore (2, 1)
	104 aload (2, 1)
	105 #8 (2, 1)
	106 iload (2, 1)
	107 #12 (2, 1)
	108 iconst_1 (2, 1)
	109 bastore (2, 1)
	110 iinc (2, 1)
	111 #10 (2, 1)
	112 -89 (2, 1)
	113 goto (2, 1)
	114 -59 (2, 1)
	116 aload_0 (1, 4)
	117 iload (1, 4)
	118 #9 (1, 4)
	119 putfield (1, 4)
	120 org/apache/commons/math3/util/OpenIntToDoubleHashMap.mask:I (1, 4)
	122 aload_0 (1, 4)
	123 aload (1, 4)
	124 #6 (1, 4)
	125 putfield (1, 4)
	126 org/apache/commons/math3/util/OpenIntToDoubleHashMap.keys:[I (1, 4)
	128 aload_0 (1, 4)
	129 aload (1, 4)
	130 #7 (1, 4)
	131 putfield (1, 4)
	132 org/apache/commons/math3/util/OpenIntToDoubleHashMap.values:[D (1, 4)
	134 aload_0 (1, 4)
	135 aload (1, 4)
	136 #8 (1, 4)
	137 putfield (1, 4)
	138 org/apache/commons/math3/util/OpenIntToDoubleHashMap.states:[B (1, 4)
	140 return (0, 0)

Method: shouldGrowTable
	0 aload_0 (0, 0)
	1 getfield (0, 0)
	2 org/apache/commons/math3/util/OpenIntToDoubleHashMap.size:I (0, 0)
	4 i2f (0, 0)
	5 aload_0 (0, 0)
	6 getfield (0, 0)
	7 org/apache/commons/math3/util/OpenIntToDoubleHashMap.mask:I (0, 0)
	9 iconst_1 (0, 0)
	10 iadd (0, 0)
	11 i2f (0, 0)
	12 ldc (0, 0)
	13 0.5 (0, 0)
	14 fmul (0, 0)
	15 fcmpl (0, 0)
	16 ifle (0, 0)
	17 7 (0, 0)
	19 iconst_1 (0, 0)
	20 goto (0, 0)
	21 4 (0, 0)
	23 iconst_0 (0, 0)
	24 ireturn (0, 0)

Method: hashOf
	0 iload_0 (0, 0)
	1 iload_0 (0, 0)
	2 bipush (0, 0)
	3 20 (0, 0)
	4 iushr (0, 0)
	5 iload_0 (0, 0)
	6 bipush (0, 0)
	7 12 (0, 0)
	8 iushr (0, 0)
	9 ixor (0, 0)
	10 ixor (0, 0)
	11 istore_1 (0, 0)
	12 iload_1 (0, 0)
	13 iload_1 (0, 0)
	14 bipush (0, 0)
	15 7 (0, 0)
	16 iushr (0, 0)
	17 ixor (0, 0)
	18 iload_1 (0, 0)
	19 iconst_4 (0, 0)
	20 iushr (0, 0)
	21 ixor (0, 0)
	22 ireturn (0, 0)

Method: readObject
	0 aload_1 (0, 0)
	1 invokevirtual (0, 0)
	2 java/io/ObjectInputStream.defaultReadObject:()V (0, 0)
	4 aload_0 (0, 0)
	5 iconst_0 (0, 0)
	6 putfield (0, 0)
	7 org/apache/commons/math3/util/OpenIntToDoubleHashMap.count:I (0, 0)
	9 return (0, 0)

Method: access$100
	0 aload_0 (0, 0)
	1 getfield (0, 0)
	2 org/apache/commons/math3/util/OpenIntToDoubleHashMap.count:I (0, 0)
	4 ireturn (0, 0)

Method: access$200
	0 aload_0 (0, 0)
	1 getfield (0, 0)
	2 org/apache/commons/math3/util/OpenIntToDoubleHashMap.keys:[I (0, 0)
	4 areturn (0, 0)

Method: access$300
	0 aload_0 (0, 0)
	1 getfield (0, 0)
	2 org/apache/commons/math3/util/OpenIntToDoubleHashMap.values:[D (0, 0)
	4 areturn (0, 0)

Method: access$400
	0 aload_0 (0, 0)
	1 getfield (0, 0)
	2 org/apache/commons/math3/util/OpenIntToDoubleHashMap.states:[B (0, 0)
	4 areturn (0, 0)

