Method: <init>
	0 aload_0 (0, 0)
	1 aload_1 (0, 0)
	2 putfield (0, 0)
	5 aload_0 (0, 0)
	6 invokespecial (0, 0)
	9 aload_0 (0, 1)
	10 aload_1 (0, 1)
	11 invokestatic (0, 1)
	14 putfield (0, 1)
	17 aload_0 (0, 1)
	18 iconst_m1 (0, 1)
	19 putfield (0, 1)
	22 aload_0 (1, 1)
	23 invokevirtual (1, 1)
	26 goto (0, 0)
	29 astore_2 (0, 0)
	30 return (0, 0)

Method: hasNext
	0 aload_0 (0, 0)
	1 getfield (0, 0)
	4 iflt (0, 0)
	7 iconst_1 (0, 0)
	8 goto (0, 0)
	11 iconst_0 (0, 0)
	12 ireturn (0, 0)

Method: key
	0 aload_0 (1, 1)
	1 getfield (1, 1)
	4 aload_0 (1, 1)
	5 getfield (1, 1)
	8 invokestatic (1, 1)
	11 if_icmpeq (1, 1)
	14 new (1, 1)
	17 dup (1, 1)
	18 invokespecial (1, 1)
	21 athrow (1, 1)
	22 aload_0 (1, 1)
	23 getfield (1, 1)
	26 ifge (1, 1)
	29 new (1, 1)
	32 dup (1, 1)
	33 invokespecial (1, 1)
	36 athrow (1, 1)
	37 aload_0 (0, 1)
	38 getfield (0, 1)
	41 invokestatic (0, 1)
	44 aload_0 (0, 1)
	45 getfield (0, 1)
	48 iaload (0, 1)
	49 ireturn (0, 1)

Method: value
	0 aload_0 (1, 1)
	1 getfield (1, 1)
	4 aload_0 (1, 1)
	5 getfield (1, 1)
	8 invokestatic (1, 1)
	11 if_icmpeq (1, 1)
	14 new (1, 1)
	17 dup (1, 1)
	18 invokespecial (1, 1)
	21 athrow (1, 1)
	22 aload_0 (1, 1)
	23 getfield (1, 1)
	26 ifge (1, 1)
	29 new (1, 1)
	32 dup (1, 1)
	33 invokespecial (1, 1)
	36 athrow (1, 1)
	37 aload_0 (0, 1)
	38 getfield (0, 1)
	41 invokestatic (0, 1)
	44 aload_0 (0, 1)
	45 getfield (0, 1)
	48 daload (0, 1)
	49 dreturn (0, 1)

Method: advance
	0 aload_0 (1, 1)
	1 getfield (1, 1)
	4 aload_0 (1, 1)
	5 getfield (1, 1)
	8 invokestatic (1, 1)
	11 if_icmpeq (1, 1)
	14 new (1, 1)
	17 dup (1, 1)
	18 invokespecial (1, 1)
	21 athrow (1, 1)
	22 aload_0 (0, 1)
	23 aload_0 (0, 1)
	24 getfield (0, 1)
	27 putfield (0, 1)
	30 aload_0 (2, 3)
	31 getfield (2, 3)
	34 invokestatic (2, 3)
	37 aload_0 (2, 3)
	38 dup (2, 3)
	39 getfield (2, 3)
	42 iconst_1 (2, 3)
	43 iadd (2, 3)
	44 dup_x1 (2, 3)
	45 putfield (2, 3)
	48 baload (2, 3)
	49 iconst_1 (2, 3)
	50 if_icmpeq (2, 3)
	53 goto (2, 3)
	56 goto (0, 0)
	59 astore_1 (0, 0)
	60 aload_0 (0, 0)
	61 bipush (0, 0)
	63 putfield (0, 0)
	66 aload_0 (1, 1)
	67 getfield (1, 1)
	70 ifge (1, 1)
	73 new (1, 1)
	76 dup (1, 1)
	77 invokespecial (1, 1)
	80 athrow (1, 1)
	81 return (0, 0)

