Method: <init>
	0 aload_0 (0, 0)
	1 aload_1 (0, 0)
	2 invokevirtual (0, 0)
	3 org/apache/commons/math3/util/Pair.getKey:()Ljava/lang/Object; (0, 0)
	5 aload_1 (0, 0)
	6 invokevirtual (0, 0)
	7 org/apache/commons/math3/util/Pair.getValue:()Ljava/lang/Object; (0, 0)
	9 invokespecial (0, 0)
	10 org/apache/commons/math3/util/Pair.<init>:(Ljava/lang/Object;Ljava/lang/Object;)V (0, 0)
	12 return (0, 0)

Method: getKey
	0 aload_0 (0, 0)
	1 getfield (0, 0)
	2 org/apache/commons/math3/util/Pair.key:Ljava/lang/Object; (0, 0)
	4 areturn (0, 0)

Method: getValue
	0 aload_0 (0, 0)
	1 getfield (0, 0)
	2 org/apache/commons/math3/util/Pair.value:Ljava/lang/Object; (0, 0)
	4 areturn (0, 0)

Method: getFirst
	0 aload_0 (0, 0)
	1 getfield (0, 0)
	2 org/apache/commons/math3/util/Pair.key:Ljava/lang/Object; (0, 0)
	4 areturn (0, 0)

Method: getSecond
	0 aload_0 (0, 0)
	1 getfield (0, 0)
	2 org/apache/commons/math3/util/Pair.value:Ljava/lang/Object; (0, 0)
	4 areturn (0, 0)

Method: equals
	0 aload_0 (1, 1)
	1 aload_1 (1, 1)
	2 if_acmpne (1, 1)
	3 5 (1, 1)
	5 iconst_1 (1, 1)
	6 ireturn (1, 1)
	7 aload_1 (1, 1)
	8 instanceof (1, 1)
	9 org/apache/commons/math3/util/Pair (1, 1)
	11 ifne (1, 1)
	12 5 (1, 1)
	14 iconst_0 (1, 1)
	15 ireturn (1, 1)
	16 aload_1 (1, 2)
	17 checkcast (1, 2)
	18 org/apache/commons/math3/util/Pair (1, 2)
	20 astore_2 (1, 2)
	21 aload_0 (1, 2)
	22 getfield (1, 2)
	23 org/apache/commons/math3/util/Pair.key:Ljava/lang/Object; (1, 2)
	25 ifnonnull (1, 2)
	26 13 (1, 2)
	28 aload_2 (1, 2)
	29 getfield (1, 2)
	30 org/apache/commons/math3/util/Pair.key:Ljava/lang/Object; (1, 2)
	32 ifnonnull (1, 2)
	33 55 (1, 2)
	35 goto (1, 2)
	36 17 (1, 2)
	38 aload_0 (1, 2)
	39 getfield (1, 2)
	40 org/apache/commons/math3/util/Pair.key:Ljava/lang/Object; (1, 2)
	42 aload_2 (1, 2)
	43 getfield (1, 2)
	44 org/apache/commons/math3/util/Pair.key:Ljava/lang/Object; (1, 2)
	46 invokevirtual (1, 2)
	47 java/lang/Object.equals:(Ljava/lang/Object;)Z (1, 2)
	49 ifeq (1, 2)
	50 38 (1, 2)
	52 aload_0 (1, 2)
	53 getfield (1, 2)
	54 org/apache/commons/math3/util/Pair.value:Ljava/lang/Object; (1, 2)
	56 ifnonnull (1, 2)
	57 13 (1, 2)
	59 aload_2 (1, 2)
	60 getfield (1, 2)
	61 org/apache/commons/math3/util/Pair.value:Ljava/lang/Object; (1, 2)
	63 ifnonnull (1, 2)
	64 24 (1, 2)
	66 goto (1, 2)
	67 17 (1, 2)
	69 aload_0 (1, 2)
	70 getfield (1, 2)
	71 org/apache/commons/math3/util/Pair.value:Ljava/lang/Object; (1, 2)
	73 aload_2 (1, 2)
	74 getfield (1, 2)
	75 org/apache/commons/math3/util/Pair.value:Ljava/lang/Object; (1, 2)
	77 invokevirtual (1, 2)
	78 java/lang/Object.equals:(Ljava/lang/Object;)Z (1, 2)
	80 ifeq (1, 2)
	81 7 (1, 2)
	83 iconst_1 (1, 2)
	84 goto (1, 2)
	85 4 (1, 2)
	87 iconst_0 (1, 2)
	88 ireturn (1, 2)

Method: hashCode
	0 aload_0 (0, 0)
	1 getfield (0, 0)
	2 org/apache/commons/math3/util/Pair.key:Ljava/lang/Object; (0, 0)
	4 ifnonnull (0, 0)
	5 7 (0, 0)
	7 iconst_0 (0, 0)
	8 goto (0, 0)
	9 10 (0, 0)
	11 aload_0 (0, 0)
	12 getfield (0, 0)
	13 org/apache/commons/math3/util/Pair.key:Ljava/lang/Object; (0, 0)
	15 invokevirtual (0, 0)
	16 java/lang/Object.hashCode:()I (0, 0)
	18 istore_1 (0, 0)
	19 aload_0 (0, 0)
	20 getfield (0, 0)
	21 org/apache/commons/math3/util/Pair.value:Ljava/lang/Object; (0, 0)
	23 ifnonnull (0, 0)
	24 7 (0, 0)
	26 iconst_0 (0, 0)
	27 goto (0, 0)
	28 10 (0, 0)
	30 aload_0 (0, 0)
	31 getfield (0, 0)
	32 org/apache/commons/math3/util/Pair.value:Ljava/lang/Object; (0, 0)
	34 invokevirtual (0, 0)
	35 java/lang/Object.hashCode:()I (0, 0)
	37 istore_2 (0, 0)
	38 bipush (0, 0)
	39 37 (0, 0)
	40 iload_1 (0, 0)
	41 imul (0, 0)
	42 iload_2 (0, 0)
	43 iadd (0, 0)
	44 iload_2 (0, 0)
	45 bipush (0, 0)
	46 16 (0, 0)
	47 iushr (0, 0)
	48 ixor (0, 0)
	49 istore_1 (0, 0)
	50 iload_1 (0, 0)
	51 ireturn (0, 0)

Method: toString
	0 new (0, 0)
	1 java/lang/StringBuilder (0, 0)
	3 dup (0, 0)
	4 invokespecial (0, 0)
	5 java/lang/StringBuilder.<init>:()V (0, 0)
	7 ldc (0, 0)
	8 [ (0, 0)
	9 invokevirtual (0, 0)
	10 java/lang/StringBuilder.append:(Ljava/lang/String;)Ljava/lang/StringBuilder; (0, 0)
	12 aload_0 (0, 0)
	13 invokevirtual (0, 0)
	14 org/apache/commons/math3/util/Pair.getKey:()Ljava/lang/Object; (0, 0)
	16 invokevirtual (0, 0)
	17 java/lang/StringBuilder.append:(Ljava/lang/Object;)Ljava/lang/StringBuilder; (0, 0)
	19 ldc (0, 0)
	20 ,  (0, 0)
	21 invokevirtual (0, 0)
	22 java/lang/StringBuilder.append:(Ljava/lang/String;)Ljava/lang/StringBuilder; (0, 0)
	24 aload_0 (0, 0)
	25 invokevirtual (0, 0)
	26 org/apache/commons/math3/util/Pair.getValue:()Ljava/lang/Object; (0, 0)
	28 invokevirtual (0, 0)
	29 java/lang/StringBuilder.append:(Ljava/lang/Object;)Ljava/lang/StringBuilder; (0, 0)
	31 ldc (0, 0)
	32 ] (0, 0)
	33 invokevirtual (0, 0)
	34 java/lang/StringBuilder.append:(Ljava/lang/String;)Ljava/lang/StringBuilder; (0, 0)
	36 invokevirtual (0, 0)
	37 java/lang/StringBuilder.toString:()Ljava/lang/String; (0, 0)
	39 areturn (0, 0)

Method: create
	0 new (0, 0)
	1 org/apache/commons/math3/util/Pair (0, 0)
	3 dup (0, 0)
	4 aload_0 (0, 0)
	5 aload_1 (0, 0)
	6 invokespecial (0, 0)
	7 org/apache/commons/math3/util/Pair.<init>:(Ljava/lang/Object;Ljava/lang/Object;)V (0, 0)
	9 areturn (0, 0)

