Method: compareTo
	0 dload_0 (1, 1)
	1 dload_2 (1, 1)
	2 iload (1, 1)
	4 invokestatic (1, 1)
	7 ifeq (1, 1)
	10 iconst_0 (1, 1)
	11 ireturn (1, 1)
	12 dload_0 (1, 1)
	13 dload_2 (1, 1)
	14 dcmpg (1, 1)
	15 ifge (1, 1)
	18 iconst_m1 (1, 1)
	19 ireturn (1, 1)
	20 iconst_1 (0, 1)
	21 ireturn (0, 1)

Method: equals
	0 dload_0 (0, 0)
	1 invokestatic (0, 0)
	4 lstore (0, 0)
	6 dload_2 (0, 0)
	7 invokestatic (0, 0)
	10 lstore (0, 0)
	12 lload (1, 1)
	14 lload (1, 1)
	16 lxor (1, 1)
	17 ldc2_w (1, 1)
	20 land (1, 1)
	21 lconst_0 (1, 1)
	22 lcmp (1, 1)
	23 ifne (1, 1)
	26 lload (1, 1)
	28 lload (1, 1)
	30 lsub (1, 1)
	31 invokestatic (1, 1)
	34 iload (1, 1)
	36 i2l (1, 1)
	37 lcmp (1, 1)
	38 ifgt (1, 1)
	41 iconst_1 (1, 1)
	42 goto (1, 1)
	45 iconst_0 (1, 1)
	46 istore (1, 1)
	48 goto (1, 1)
	51 lload (2, 1)
	53 lload (2, 1)
	55 lcmp (2, 1)
	56 ifge (2, 1)
	59 lload (2, 1)
	61 getstatic (2, 1)
	64 lsub (2, 1)
	65 lstore (2, 1)
	67 lload (2, 1)
	69 getstatic (2, 1)
	72 lsub (2, 1)
	73 lstore (2, 1)
	75 goto (2, 1)
	78 lload (2, 2)
	80 getstatic (2, 2)
	83 lsub (2, 2)
	84 lstore (2, 2)
	86 lload (2, 2)
	88 getstatic (2, 2)
	91 lsub (2, 2)
	92 lstore (2, 2)
	94 lload (2, 1)
	96 iload (2, 1)
	98 i2l (2, 1)
	99 lcmp (2, 1)
	100 ifle (2, 1)
	103 iconst_0 (2, 1)
	104 istore (2, 1)
	106 goto (2, 1)
	109 lload (2, 2)
	111 iload (2, 2)
	113 i2l (2, 2)
	114 lload (2, 2)
	116 lsub (2, 2)
	117 lcmp (2, 2)
	118 ifgt (2, 2)
	121 iconst_1 (2, 2)
	122 goto (2, 2)
	125 iconst_0 (2, 2)
	126 istore (2, 2)
	128 iload (0, 1)
	130 ifeq (0, 1)
	133 dload_0 (0, 1)
	134 invokestatic (0, 1)
	137 ifne (0, 1)
	140 dload_2 (0, 1)
	141 invokestatic (0, 1)
	144 ifne (0, 1)
	147 iconst_1 (0, 1)
	148 goto (0, 1)
	151 iconst_0 (0, 1)
	152 ireturn (0, 1)

Method: equalsIncludingNaN
	0 dload_0 (0, 0)
	1 dload_0 (0, 0)
	2 dcmpl (0, 0)
	3 ifne (0, 0)
	6 dload_2 (0, 0)
	7 dload_2 (0, 0)
	8 dcmpl (0, 0)
	9 ifeq (0, 0)
	12 dload_0 (0, 0)
	13 dload_0 (0, 0)
	14 dcmpl (0, 0)
	15 ifeq (0, 0)
	18 iconst_1 (0, 0)
	19 goto (0, 0)
	22 iconst_0 (0, 0)
	23 dload_2 (0, 0)
	24 dload_2 (0, 0)
	25 dcmpl (0, 0)
	26 ifeq (0, 0)
	29 iconst_1 (0, 0)
	30 goto (0, 0)
	33 iconst_0 (0, 0)
	34 ixor (0, 0)
	35 ifne (0, 0)
	38 iconst_1 (0, 0)
	39 goto (0, 0)
	42 iconst_0 (0, 0)
	43 goto (0, 0)
	46 dload_0 (0, 0)
	47 dload_2 (0, 0)
	48 iload (0, 0)
	50 invokestatic (0, 0)
	53 ireturn (0, 0)

Method: equalsWithRelativeTolerance
	0 dload_0 (1, 1)
	1 dload_2 (1, 1)
	2 iconst_1 (1, 1)
	3 invokestatic (1, 1)
	6 ifeq (1, 1)
	9 iconst_1 (1, 1)
	10 ireturn (1, 1)
	11 dload_0 (0, 0)
	12 invokestatic (0, 0)
	15 dload_2 (0, 0)
	16 invokestatic (0, 0)
	19 invokestatic (0, 0)
	22 dstore (0, 0)
	24 dload_0 (0, 1)
	25 dload_2 (0, 1)
	26 dsub (0, 1)
	27 dload (0, 1)
	29 ddiv (0, 1)
	30 invokestatic (0, 1)
	33 dstore (0, 1)
	35 dload (0, 1)
	37 dload (0, 1)
	39 dcmpg (0, 1)
	40 ifgt (0, 1)
	43 iconst_1 (0, 1)
	44 goto (0, 1)
	47 iconst_0 (0, 1)
	48 ireturn (0, 1)

Method: round
	0 fconst_1 (0, 0)
	1 fload_0 (0, 0)
	2 invokestatic (0, 0)
	5 fstore_3 (0, 0)
	6 ldc2_w (0, 0)
	9 iload_1 (0, 0)
	10 invokestatic (0, 0)
	13 d2f (0, 0)
	14 fload_3 (0, 0)
	15 fmul (0, 0)
	16 fstore (0, 0)
	18 fload_0 (0, 0)
	19 fload (0, 0)
	21 fmul (0, 0)
	22 f2d (0, 0)
	23 fload_3 (0, 0)
	24 f2d (0, 0)
	25 iload_2 (0, 0)
	26 invokestatic (0, 0)
	29 d2f (0, 0)
	30 fload (0, 0)
	32 fdiv (0, 0)
	33 freturn (0, 0)

Method: roundUnscaled
	0 iload (1, 5)
	2 tableswitch (1, 5)
	48 dload_2 (2, 1)
	49 ldc2_w (2, 1)
	52 dcmpl (2, 1)
	53 ifne (2, 1)
	56 dload_0 (2, 1)
	57 ldc2_w (2, 1)
	60 invokestatic (2, 1)
	63 invokestatic (2, 1)
	66 dstore_0 (2, 1)
	67 goto (2, 1)
	70 dload_0 (2, 2)
	71 ldc2_w (2, 2)
	74 invokestatic (2, 2)
	77 invokestatic (2, 2)
	80 dstore_0 (2, 2)
	81 goto (1, 1)
	84 dload_0 (1, 1)
	85 ldc2_w (1, 1)
	88 invokestatic (1, 1)
	91 invokestatic (1, 1)
	94 dstore_0 (1, 1)
	95 goto (1, 1)
	98 dload_2 (2, 1)
	99 ldc2_w (2, 1)
	102 dcmpl (2, 1)
	103 ifne (2, 1)
	106 dload_0 (2, 1)
	107 ldc2_w (2, 1)
	110 invokestatic (2, 1)
	113 invokestatic (2, 1)
	116 dstore_0 (2, 1)
	117 goto (2, 1)
	120 dload_0 (2, 2)
	121 ldc2_w (2, 2)
	124 invokestatic (2, 2)
	127 invokestatic (2, 2)
	130 dstore_0 (2, 2)
	131 goto (1, 1)
	134 dload_0 (2, 1)
	135 ldc2_w (2, 1)
	138 invokestatic (2, 1)
	141 dstore_0 (2, 1)
	142 dload_0 (2, 1)
	143 dload_0 (2, 1)
	144 invokestatic (2, 1)
	147 dsub (2, 1)
	148 dstore (2, 1)
	150 dload (3, 1)
	152 ldc2_w (3, 1)
	155 dcmpl (3, 1)
	156 ifle (3, 1)
	159 dload_0 (3, 1)
	160 invokestatic (3, 1)
	163 dstore_0 (3, 1)
	164 goto (3, 1)
	167 dload_0 (3, 2)
	168 invokestatic (3, 2)
	171 dstore_0 (3, 2)
	172 goto (2, 1)
	175 dload_0 (2, 1)
	176 dload_0 (2, 1)
	177 invokestatic (2, 1)
	180 dsub (2, 1)
	181 dstore (2, 1)
	183 dload (3, 1)
	185 ldc2_w (3, 1)
	188 dcmpl (3, 1)
	189 ifle (3, 1)
	192 dload_0 (3, 1)
	193 invokestatic (3, 1)
	196 dstore_0 (3, 1)
	197 goto (3, 1)
	200 dload (3, 1)
	202 ldc2_w (3, 1)
	205 dcmpg (3, 1)
	206 ifge (3, 1)
	209 dload_0 (3, 1)
	210 invokestatic (3, 1)
	213 dstore_0 (3, 1)
	214 goto (3, 1)
	217 dload_0 (4, 1)
	218 invokestatic (4, 1)
	221 ldc2_w (4, 1)
	224 ddiv (4, 1)
	225 dload_0 (4, 1)
	226 invokestatic (4, 1)
	229 ldc2_w (4, 1)
	232 ddiv (4, 1)
	233 invokestatic (4, 1)
	236 dcmpl (4, 1)
	237 ifne (4, 1)
	240 dload_0 (4, 1)
	241 invokestatic (4, 1)
	244 dstore_0 (4, 1)
	245 goto (4, 1)
	248 dload_0 (4, 2)
	249 invokestatic (4, 2)
	252 dstore_0 (4, 2)
	253 goto (2, 4)
	256 dload_0 (2, 2)
	257 ldc2_w (2, 2)
	260 invokestatic (2, 2)
	263 dstore_0 (2, 2)
	264 dload_0 (2, 2)
	265 dload_0 (2, 2)
	266 invokestatic (2, 2)
	269 dsub (2, 2)
	270 dstore (2, 2)
	272 dload (3, 1)
	274 ldc2_w (3, 1)
	277 dcmpl (3, 1)
	278 iflt (3, 1)
	281 dload_0 (3, 1)
	282 invokestatic (3, 1)
	285 dstore_0 (3, 1)
	286 goto (3, 1)
	289 dload_0 (3, 2)
	290 invokestatic (3, 2)
	293 dstore_0 (3, 2)
	294 goto (2, 1)
	297 dload_0 (2, 1)
	298 dload_0 (2, 1)
	299 invokestatic (2, 1)
	302 dcmpl (2, 1)
	303 ifeq (2, 1)
	306 new (2, 1)
	309 dup (2, 1)
	310 invokespecial (2, 1)
	313 athrow (2, 1)
	314 dload_0 (2, 1)
	315 dload_0 (2, 1)
	316 invokestatic (2, 1)
	319 dcmpl (2, 1)
	320 ifeq (2, 1)
	323 dload_0 (2, 1)
	324 ldc2_w (2, 1)
	327 invokestatic (2, 1)
	330 invokestatic (2, 1)
	333 dstore_0 (2, 1)
	334 goto (2, 1)
	337 new (1, 1)
	340 dup (1, 1)
	341 getstatic (1, 1)
	344 bipush (1, 1)
	346 anewarray (1, 1)
	349 dup (1, 1)
	350 iconst_0 (1, 1)
	351 iload (1, 1)
	353 invokestatic (1, 1)
	356 aastore (1, 1)
	357 dup (1, 1)
	358 iconst_1 (1, 1)
	359 ldc (1, 1)
	361 aastore (1, 1)
	362 dup (1, 1)
	363 iconst_2 (1, 1)
	364 iconst_2 (1, 1)
	365 invokestatic (1, 1)
	368 aastore (1, 1)
	369 dup (1, 1)
	370 iconst_3 (1, 1)
	371 ldc (1, 1)
	373 aastore (1, 1)
	374 dup (1, 1)
	375 iconst_4 (1, 1)
	376 iconst_1 (1, 1)
	377 invokestatic (1, 1)
	380 aastore (1, 1)
	381 dup (1, 1)
	382 iconst_5 (1, 1)
	383 ldc (1, 1)
	385 aastore (1, 1)
	386 dup (1, 1)
	387 bipush (1, 1)
	389 iconst_3 (1, 1)
	390 invokestatic (1, 1)
	393 aastore (1, 1)
	394 dup (1, 1)
	395 bipush (1, 1)
	397 ldc (1, 1)
	399 aastore (1, 1)
	400 dup (1, 1)
	401 bipush (1, 1)
	403 iconst_5 (1, 1)
	404 invokestatic (1, 1)
	407 aastore (1, 1)
	408 dup (1, 1)
	409 bipush (1, 1)
	411 ldc (1, 1)
	413 aastore (1, 1)
	414 dup (1, 1)
	415 bipush (1, 1)
	417 bipush (1, 1)
	419 invokestatic (1, 1)
	422 aastore (1, 1)
	423 dup (1, 1)
	424 bipush (1, 1)
	426 ldc (1, 1)
	428 aastore (1, 1)
	429 dup (1, 1)
	430 bipush (1, 1)
	432 iconst_4 (1, 1)
	433 invokestatic (1, 1)
	436 aastore (1, 1)
	437 dup (1, 1)
	438 bipush (1, 1)
	440 ldc (1, 1)
	442 aastore (1, 1)
	443 dup (1, 1)
	444 bipush (1, 1)
	446 bipush (1, 1)
	448 invokestatic (1, 1)
	451 aastore (1, 1)
	452 dup (1, 1)
	453 bipush (1, 1)
	455 ldc (1, 1)
	457 aastore (1, 1)
	458 dup (1, 1)
	459 bipush (1, 1)
	461 iconst_0 (1, 1)
	462 invokestatic (1, 1)
	465 aastore (1, 1)
	466 invokespecial (1, 1)
	469 athrow (1, 1)
	470 dload_0 (0, 2)
	471 dreturn (0, 2)

Method: representableDelta
	0 dload_0 (0, 0)
	1 dload_2 (0, 0)
	2 dadd (0, 0)
	3 dload_0 (0, 0)
	4 dsub (0, 0)
	5 dreturn (0, 0)

Method: <clinit>
	0 dconst_0 (0, 0)
	1 invokestatic (0, 0)
	4 putstatic (0, 0)
	7 ldc2_w (0, 0)
	10 invokestatic (0, 0)
	13 putstatic (0, 0)
	16 fconst_0 (0, 0)
	17 invokestatic (0, 0)
	20 putstatic (0, 0)
	23 ldc (0, 0)
	25 invokestatic (0, 0)
	28 putstatic (0, 0)
	31 ldc2_w (0, 0)
	34 invokestatic (0, 0)
	37 putstatic (0, 0)
	40 ldc2_w (0, 0)
	43 invokestatic (0, 0)
	46 putstatic (0, 0)
	49 return (0, 0)

