Method: compareTo
	0 dload_0 (1, 1)
	1 dload_2 (1, 1)
	2 iload (1, 1)
	3 #4 (1, 1)
	4 invokestatic (1, 1)
	5 org/apache/commons/math3/util/Precision.equals:(DDI)Z (1, 1)
	7 ifeq (1, 1)
	8 5 (1, 1)
	10 iconst_0 (1, 1)
	11 ireturn (1, 1)
	12 dload_0 (1, 1)
	13 dload_2 (1, 1)
	14 dcmpg (1, 1)
	15 ifge (1, 1)
	16 5 (1, 1)
	18 iconst_m1 (1, 1)
	19 ireturn (1, 1)
	20 iconst_1 (0, 0)
	21 ireturn (0, 0)

Method: equals
	0 dload_0 (0, 0)
	1 invokestatic (0, 0)
	2 java/lang/Double.doubleToRawLongBits:(D)J (0, 0)
	4 lstore (0, 0)
	5 #5 (0, 0)
	6 dload_2 (0, 0)
	7 invokestatic (0, 0)
	8 java/lang/Double.doubleToRawLongBits:(D)J (0, 0)
	10 lstore (0, 0)
	11 #7 (0, 0)
	12 lload (1, 1)
	13 #5 (1, 1)
	14 lload (1, 1)
	15 #7 (1, 1)
	16 lxor (1, 1)
	17 ldc2_w (1, 1)
	18 9223372036854775808 (1, 1)
	20 land (1, 1)
	21 lconst_0 (1, 1)
	22 lcmp (1, 1)
	23 ifne (1, 1)
	24 28 (1, 1)
	26 lload (1, 1)
	27 #5 (1, 1)
	28 lload (1, 1)
	29 #7 (1, 1)
	30 lsub (1, 1)
	31 invokestatic (1, 1)
	32 org/apache/commons/math3/util/FastMath.abs:(J)J (1, 1)
	34 iload (1, 1)
	35 #4 (1, 1)
	36 i2l (1, 1)
	37 lcmp (1, 1)
	38 ifgt (1, 1)
	39 7 (1, 1)
	41 iconst_1 (1, 1)
	42 goto (1, 1)
	43 4 (1, 1)
	45 iconst_0 (1, 1)
	46 istore (1, 1)
	47 #9 (1, 1)
	48 goto (1, 1)
	49 80 (1, 1)
	51 lload (2, 1)
	52 #5 (2, 1)
	53 lload (2, 1)
	54 #7 (2, 1)
	55 lcmp (2, 1)
	56 ifge (2, 1)
	57 22 (2, 1)
	59 lload (2, 1)
	60 #7 (2, 1)
	61 getstatic (2, 1)
	62 org/apache/commons/math3/util/Precision.POSITIVE_ZERO_DOUBLE_BITS:J (2, 1)
	64 lsub (2, 1)
	65 lstore (2, 1)
	66 #10 (2, 1)
	67 lload (2, 1)
	68 #5 (2, 1)
	69 getstatic (2, 1)
	70 org/apache/commons/math3/util/Precision.NEGATIVE_ZERO_DOUBLE_BITS:J (2, 1)
	72 lsub (2, 1)
	73 lstore (2, 1)
	74 #12 (2, 1)
	75 goto (2, 1)
	76 19 (2, 1)
	78 lload (2, 2)
	79 #5 (2, 2)
	80 getstatic (2, 2)
	81 org/apache/commons/math3/util/Precision.POSITIVE_ZERO_DOUBLE_BITS:J (2, 2)
	83 lsub (2, 2)
	84 lstore (2, 2)
	85 #10 (2, 2)
	86 lload (2, 2)
	87 #7 (2, 2)
	88 getstatic (2, 2)
	89 org/apache/commons/math3/util/Precision.NEGATIVE_ZERO_DOUBLE_BITS:J (2, 2)
	91 lsub (2, 2)
	92 lstore (2, 2)
	93 #12 (2, 2)
	94 lload (2, 1)
	95 #10 (2, 1)
	96 iload (2, 1)
	97 #4 (2, 1)
	98 i2l (2, 1)
	99 lcmp (2, 1)
	100 ifle (2, 1)
	101 9 (2, 1)
	103 iconst_0 (2, 1)
	104 istore (2, 1)
	105 #9 (2, 1)
	106 goto (2, 1)
	107 22 (2, 1)
	109 lload (2, 2)
	110 #12 (2, 2)
	111 iload (2, 2)
	112 #4 (2, 2)
	113 i2l (2, 2)
	114 lload (2, 2)
	115 #10 (2, 2)
	116 lsub (2, 2)
	117 lcmp (2, 2)
	118 ifgt (2, 2)
	119 7 (2, 2)
	121 iconst_1 (2, 2)
	122 goto (2, 2)
	123 4 (2, 2)
	125 iconst_0 (2, 2)
	126 istore (2, 2)
	127 #9 (2, 2)
	128 iload (0, 0)
	129 #9 (0, 0)
	130 ifeq (0, 0)
	131 21 (0, 0)
	133 dload_0 (0, 0)
	134 invokestatic (0, 0)
	135 java/lang/Double.isNaN:(D)Z (0, 0)
	137 ifne (0, 0)
	138 14 (0, 0)
	140 dload_2 (0, 0)
	141 invokestatic (0, 0)
	142 java/lang/Double.isNaN:(D)Z (0, 0)
	144 ifne (0, 0)
	145 7 (0, 0)
	147 iconst_1 (0, 0)
	148 goto (0, 0)
	149 4 (0, 0)
	151 iconst_0 (0, 0)
	152 ireturn (0, 0)

Method: equalsIncludingNaN
	0 dload_0 (0, 0)
	1 dload_0 (0, 0)
	2 dcmpl (0, 0)
	3 ifne (0, 0)
	4 9 (0, 0)
	6 dload_2 (0, 0)
	7 dload_2 (0, 0)
	8 dcmpl (0, 0)
	9 ifeq (0, 0)
	10 37 (0, 0)
	12 dload_0 (0, 0)
	13 dload_0 (0, 0)
	14 dcmpl (0, 0)
	15 ifeq (0, 0)
	16 7 (0, 0)
	18 iconst_1 (0, 0)
	19 goto (0, 0)
	20 4 (0, 0)
	22 iconst_0 (0, 0)
	23 dload_2 (0, 0)
	24 dload_2 (0, 0)
	25 dcmpl (0, 0)
	26 ifeq (0, 0)
	27 7 (0, 0)
	29 iconst_1 (0, 0)
	30 goto (0, 0)
	31 4 (0, 0)
	33 iconst_0 (0, 0)
	34 ixor (0, 0)
	35 ifne (0, 0)
	36 7 (0, 0)
	38 iconst_1 (0, 0)
	39 goto (0, 0)
	40 14 (0, 0)
	42 iconst_0 (0, 0)
	43 goto (0, 0)
	44 10 (0, 0)
	46 dload_0 (0, 0)
	47 dload_2 (0, 0)
	48 iload (0, 0)
	49 #4 (0, 0)
	50 invokestatic (0, 0)
	51 org/apache/commons/math3/util/Precision.equals:(DDI)Z (0, 0)
	53 ireturn (0, 0)

Method: equalsWithRelativeTolerance
	0 dload_0 (1, 1)
	1 dload_2 (1, 1)
	2 iconst_1 (1, 1)
	3 invokestatic (1, 1)
	4 org/apache/commons/math3/util/Precision.equals:(DDI)Z (1, 1)
	6 ifeq (1, 1)
	7 5 (1, 1)
	9 iconst_1 (1, 1)
	10 ireturn (1, 1)
	11 dload_0 (0, 0)
	12 invokestatic (0, 0)
	13 org/apache/commons/math3/util/FastMath.abs:(D)D (0, 0)
	15 dload_2 (0, 0)
	16 invokestatic (0, 0)
	17 org/apache/commons/math3/util/FastMath.abs:(D)D (0, 0)
	19 invokestatic (0, 0)
	20 org/apache/commons/math3/util/FastMath.max:(DD)D (0, 0)
	22 dstore (0, 0)
	23 #6 (0, 0)
	24 dload_0 (0, 1)
	25 dload_2 (0, 1)
	26 dsub (0, 1)
	27 dload (0, 1)
	28 #6 (0, 1)
	29 ddiv (0, 1)
	30 invokestatic (0, 1)
	31 org/apache/commons/math3/util/FastMath.abs:(D)D (0, 1)
	33 dstore (0, 1)
	34 #8 (0, 1)
	35 dload (0, 1)
	36 #8 (0, 1)
	37 dload (0, 1)
	38 #4 (0, 1)
	39 dcmpg (0, 1)
	40 ifgt (0, 1)
	41 7 (0, 1)
	43 iconst_1 (0, 1)
	44 goto (0, 1)
	45 4 (0, 1)
	47 iconst_0 (0, 1)
	48 ireturn (0, 1)

Method: round
	0 fconst_1 (0, 0)
	1 fload_0 (0, 0)
	2 invokestatic (0, 0)
	3 org/apache/commons/math3/util/FastMath.copySign:(FF)F (0, 0)
	5 fstore_3 (0, 0)
	6 ldc2_w (0, 0)
	7 10.0 (0, 0)
	9 iload_1 (0, 0)
	10 invokestatic (0, 0)
	11 org/apache/commons/math3/util/FastMath.pow:(DI)D (0, 0)
	13 d2f (0, 0)
	14 fload_3 (0, 0)
	15 fmul (0, 0)
	16 fstore (0, 0)
	17 #4 (0, 0)
	18 fload_0 (0, 0)
	19 fload (0, 0)
	20 #4 (0, 0)
	21 fmul (0, 0)
	22 f2d (0, 0)
	23 fload_3 (0, 0)
	24 f2d (0, 0)
	25 iload_2 (0, 0)
	26 invokestatic (0, 0)
	27 org/apache/commons/math3/util/Precision.roundUnscaled:(DDI)D (0, 0)
	29 d2f (0, 0)
	30 fload (0, 0)
	31 #4 (0, 0)
	32 fdiv (0, 0)
	33 freturn (0, 0)

Method: roundUnscaled
	0 iload (1, 5)
	1 #4 (1, 5)
	2 tableswitch (1, 5)
	3 0 314 (1, 5)
	7 1 84 (1, 5)
	11 2 48 (1, 5)
	15 3 98 (1, 5)
	19 4 256 (1, 5)
	23 5 134 (1, 5)
	27 6 175 (1, 5)
	31 7 297 (1, 5)
	48 dload_2 (2, 1)
	49 ldc2_w (2, 1)
	50 -1.0 (2, 1)
	52 dcmpl (2, 1)
	53 ifne (2, 1)
	54 17 (2, 1)
	56 dload_0 (2, 1)
	57 ldc2_w (2, 1)
	58 -inf (2, 1)
	60 invokestatic (2, 1)
	61 org/apache/commons/math3/util/FastMath.nextAfter:(DD)D (2, 1)
	63 invokestatic (2, 1)
	64 org/apache/commons/math3/util/FastMath.floor:(D)D (2, 1)
	66 dstore_0 (2, 1)
	67 goto (2, 1)
	68 403 (2, 1)
	70 dload_0 (2, 2)
	71 ldc2_w (2, 2)
	72 inf (2, 2)
	74 invokestatic (2, 2)
	75 org/apache/commons/math3/util/FastMath.nextAfter:(DD)D (2, 2)
	77 invokestatic (2, 2)
	78 org/apache/commons/math3/util/FastMath.ceil:(D)D (2, 2)
	80 dstore_0 (2, 2)
	81 goto (1, 5)
	82 389 (1, 5)
	84 dload_0 (1, 5)
	85 ldc2_w (1, 5)
	86 -inf (1, 5)
	88 invokestatic (1, 5)
	89 org/apache/commons/math3/util/FastMath.nextAfter:(DD)D (1, 5)
	91 invokestatic (1, 5)
	92 org/apache/commons/math3/util/FastMath.floor:(D)D (1, 5)
	94 dstore_0 (1, 5)
	95 goto (1, 5)
	96 375 (1, 5)
	98 dload_2 (2, 1)
	99 ldc2_w (2, 1)
	100 -1.0 (2, 1)
	102 dcmpl (2, 1)
	103 ifne (2, 1)
	104 17 (2, 1)
	106 dload_0 (2, 1)
	107 ldc2_w (2, 1)
	108 inf (2, 1)
	110 invokestatic (2, 1)
	111 org/apache/commons/math3/util/FastMath.nextAfter:(DD)D (2, 1)
	113 invokestatic (2, 1)
	114 org/apache/commons/math3/util/FastMath.ceil:(D)D (2, 1)
	116 dstore_0 (2, 1)
	117 goto (2, 1)
	118 353 (2, 1)
	120 dload_0 (2, 2)
	121 ldc2_w (2, 2)
	122 -inf (2, 2)
	124 invokestatic (2, 2)
	125 org/apache/commons/math3/util/FastMath.nextAfter:(DD)D (2, 2)
	127 invokestatic (2, 2)
	128 org/apache/commons/math3/util/FastMath.floor:(D)D (2, 2)
	130 dstore_0 (2, 2)
	131 goto (1, 5)
	132 339 (1, 5)
	134 dload_0 (1, 5)
	135 ldc2_w (1, 5)
	136 -inf (1, 5)
	138 invokestatic (1, 5)
	139 org/apache/commons/math3/util/FastMath.nextAfter:(DD)D (1, 5)
	141 dstore_0 (1, 5)
	142 dload_0 (1, 5)
	143 dload_0 (1, 5)
	144 invokestatic (1, 5)
	145 org/apache/commons/math3/util/FastMath.floor:(D)D (1, 5)
	147 dsub (1, 5)
	148 dstore (1, 5)
	149 #5 (1, 5)
	150 dload (3, 1)
	151 #5 (3, 1)
	152 ldc2_w (3, 1)
	153 0.5 (3, 1)
	155 dcmpl (3, 1)
	156 ifle (3, 1)
	157 11 (3, 1)
	159 dload_0 (3, 1)
	160 invokestatic (3, 1)
	161 org/apache/commons/math3/util/FastMath.ceil:(D)D (3, 1)
	163 dstore_0 (3, 1)
	164 goto (3, 1)
	165 306 (3, 1)
	167 dload_0 (3, 2)
	168 invokestatic (3, 2)
	169 org/apache/commons/math3/util/FastMath.floor:(D)D (3, 2)
	171 dstore_0 (3, 2)
	172 goto (1, 5)
	173 298 (1, 5)
	175 dload_0 (1, 5)
	176 dload_0 (1, 5)
	177 invokestatic (1, 5)
	178 org/apache/commons/math3/util/FastMath.floor:(D)D (1, 5)
	180 dsub (1, 5)
	181 dstore (1, 5)
	182 #5 (1, 5)
	183 dload (3, 1)
	184 #5 (3, 1)
	185 ldc2_w (3, 1)
	186 0.5 (3, 1)
	188 dcmpl (3, 1)
	189 ifle (3, 1)
	190 11 (3, 1)
	192 dload_0 (3, 1)
	193 invokestatic (3, 1)
	194 org/apache/commons/math3/util/FastMath.ceil:(D)D (3, 1)
	196 dstore_0 (3, 1)
	197 goto (3, 1)
	198 273 (3, 1)
	200 dload (3, 1)
	201 #5 (3, 1)
	202 ldc2_w (3, 1)
	203 0.5 (3, 1)
	205 dcmpg (3, 1)
	206 ifge (3, 1)
	207 11 (3, 1)
	209 dload_0 (3, 1)
	210 invokestatic (3, 1)
	211 org/apache/commons/math3/util/FastMath.floor:(D)D (3, 1)
	213 dstore_0 (3, 1)
	214 goto (3, 1)
	215 256 (3, 1)
	217 dload_0 (4, 1)
	218 invokestatic (4, 1)
	219 org/apache/commons/math3/util/FastMath.floor:(D)D (4, 1)
	221 ldc2_w (4, 1)
	222 2.0 (4, 1)
	224 ddiv (4, 1)
	225 dload_0 (4, 1)
	226 invokestatic (4, 1)
	227 org/apache/commons/math3/util/FastMath.floor:(D)D (4, 1)
	229 ldc2_w (4, 1)
	230 2.0 (4, 1)
	232 ddiv (4, 1)
	233 invokestatic (4, 1)
	234 org/apache/commons/math3/util/FastMath.floor:(D)D (4, 1)
	236 dcmpl (4, 1)
	237 ifne (4, 1)
	238 11 (4, 1)
	240 dload_0 (4, 1)
	241 invokestatic (4, 1)
	242 org/apache/commons/math3/util/FastMath.floor:(D)D (4, 1)
	244 dstore_0 (4, 1)
	245 goto (4, 1)
	246 225 (4, 1)
	248 dload_0 (4, 2)
	249 invokestatic (4, 2)
	250 org/apache/commons/math3/util/FastMath.ceil:(D)D (4, 2)
	252 dstore_0 (4, 2)
	253 goto (1, 5)
	254 217 (1, 5)
	256 dload_0 (1, 5)
	257 ldc2_w (1, 5)
	258 inf (1, 5)
	260 invokestatic (1, 5)
	261 org/apache/commons/math3/util/FastMath.nextAfter:(DD)D (1, 5)
	263 dstore_0 (1, 5)
	264 dload_0 (1, 5)
	265 dload_0 (1, 5)
	266 invokestatic (1, 5)
	267 org/apache/commons/math3/util/FastMath.floor:(D)D (1, 5)
	269 dsub (1, 5)
	270 dstore (1, 5)
	271 #5 (1, 5)
	272 dload (3, 1)
	273 #5 (3, 1)
	274 ldc2_w (3, 1)
	275 0.5 (3, 1)
	277 dcmpl (3, 1)
	278 iflt (3, 1)
	279 11 (3, 1)
	281 dload_0 (3, 1)
	282 invokestatic (3, 1)
	283 org/apache/commons/math3/util/FastMath.ceil:(D)D (3, 1)
	285 dstore_0 (3, 1)
	286 goto (3, 1)
	287 184 (3, 1)
	289 dload_0 (3, 2)
	290 invokestatic (3, 2)
	291 org/apache/commons/math3/util/FastMath.floor:(D)D (3, 2)
	293 dstore_0 (3, 2)
	294 goto (1, 5)
	295 176 (1, 5)
	297 dload_0 (2, 1)
	298 dload_0 (2, 1)
	299 invokestatic (2, 1)
	300 org/apache/commons/math3/util/FastMath.floor:(D)D (2, 1)
	302 dcmpl (2, 1)
	303 ifeq (2, 1)
	304 167 (2, 1)
	306 new (2, 1)
	307 org/apache/commons/math3/exception/MathArithmeticException (2, 1)
	309 dup (2, 1)
	310 invokespecial (2, 1)
	311 org/apache/commons/math3/exception/MathArithmeticException.<init>:()V (2, 1)
	313 athrow (2, 1)
	314 dload_0 (2, 1)
	315 dload_0 (2, 1)
	316 invokestatic (2, 1)
	317 org/apache/commons/math3/util/FastMath.floor:(D)D (2, 1)
	319 dcmpl (2, 1)
	320 ifeq (2, 1)
	321 150 (2, 1)
	323 dload_0 (2, 1)
	324 ldc2_w (2, 1)
	325 inf (2, 1)
	327 invokestatic (2, 1)
	328 org/apache/commons/math3/util/FastMath.nextAfter:(DD)D (2, 1)
	330 invokestatic (2, 1)
	331 org/apache/commons/math3/util/FastMath.ceil:(D)D (2, 1)
	333 dstore_0 (2, 1)
	334 goto (2, 1)
	335 136 (2, 1)
	337 new (1, 1)
	338 org/apache/commons/math3/exception/MathIllegalArgumentException (1, 1)
	340 dup (1, 1)
	341 getstatic (1, 1)
	342 org/apache/commons/math3/exception/util/LocalizedFormats.INVALID_ROUNDING_METHOD:Lorg/apache/commons/math3/exception/util/LocalizedFormats; (1, 1)
	344 bipush (1, 1)
	345 17 (1, 1)
	346 anewarray (1, 1)
	347 java/lang/Object (1, 1)
	349 dup (1, 1)
	350 iconst_0 (1, 1)
	351 iload (1, 1)
	352 #4 (1, 1)
	353 invokestatic (1, 1)
	354 java/lang/Integer.valueOf:(I)Ljava/lang/Integer; (1, 1)
	356 aastore (1, 1)
	357 dup (1, 1)
	358 iconst_1 (1, 1)
	359 ldc (1, 1)
	360 ROUND_CEILING (1, 1)
	361 aastore (1, 1)
	362 dup (1, 1)
	363 iconst_2 (1, 1)
	364 iconst_2 (1, 1)
	365 invokestatic (1, 1)
	366 java/lang/Integer.valueOf:(I)Ljava/lang/Integer; (1, 1)
	368 aastore (1, 1)
	369 dup (1, 1)
	370 iconst_3 (1, 1)
	371 ldc (1, 1)
	372 ROUND_DOWN (1, 1)
	373 aastore (1, 1)
	374 dup (1, 1)
	375 iconst_4 (1, 1)
	376 iconst_1 (1, 1)
	377 invokestatic (1, 1)
	378 java/lang/Integer.valueOf:(I)Ljava/lang/Integer; (1, 1)
	380 aastore (1, 1)
	381 dup (1, 1)
	382 iconst_5 (1, 1)
	383 ldc (1, 1)
	384 ROUND_FLOOR (1, 1)
	385 aastore (1, 1)
	386 dup (1, 1)
	387 bipush (1, 1)
	388 6 (1, 1)
	389 iconst_3 (1, 1)
	390 invokestatic (1, 1)
	391 java/lang/Integer.valueOf:(I)Ljava/lang/Integer; (1, 1)
	393 aastore (1, 1)
	394 dup (1, 1)
	395 bipush (1, 1)
	396 7 (1, 1)
	397 ldc (1, 1)
	398 ROUND_HALF_DOWN (1, 1)
	399 aastore (1, 1)
	400 dup (1, 1)
	401 bipush (1, 1)
	402 8 (1, 1)
	403 iconst_5 (1, 1)
	404 invokestatic (1, 1)
	405 java/lang/Integer.valueOf:(I)Ljava/lang/Integer; (1, 1)
	407 aastore (1, 1)
	408 dup (1, 1)
	409 bipush (1, 1)
	410 9 (1, 1)
	411 ldc (1, 1)
	412 ROUND_HALF_EVEN (1, 1)
	413 aastore (1, 1)
	414 dup (1, 1)
	415 bipush (1, 1)
	416 10 (1, 1)
	417 bipush (1, 1)
	418 6 (1, 1)
	419 invokestatic (1, 1)
	420 java/lang/Integer.valueOf:(I)Ljava/lang/Integer; (1, 1)
	422 aastore (1, 1)
	423 dup (1, 1)
	424 bipush (1, 1)
	425 11 (1, 1)
	426 ldc (1, 1)
	427 ROUND_HALF_UP (1, 1)
	428 aastore (1, 1)
	429 dup (1, 1)
	430 bipush (1, 1)
	431 12 (1, 1)
	432 iconst_4 (1, 1)
	433 invokestatic (1, 1)
	434 java/lang/Integer.valueOf:(I)Ljava/lang/Integer; (1, 1)
	436 aastore (1, 1)
	437 dup (1, 1)
	438 bipush (1, 1)
	439 13 (1, 1)
	440 ldc (1, 1)
	441 ROUND_UNNECESSARY (1, 1)
	442 aastore (1, 1)
	443 dup (1, 1)
	444 bipush (1, 1)
	445 14 (1, 1)
	446 bipush (1, 1)
	447 7 (1, 1)
	448 invokestatic (1, 1)
	449 java/lang/Integer.valueOf:(I)Ljava/lang/Integer; (1, 1)
	451 aastore (1, 1)
	452 dup (1, 1)
	453 bipush (1, 1)
	454 15 (1, 1)
	455 ldc (1, 1)
	456 ROUND_UP (1, 1)
	457 aastore (1, 1)
	458 dup (1, 1)
	459 bipush (1, 1)
	460 16 (1, 1)
	461 iconst_0 (1, 1)
	462 invokestatic (1, 1)
	463 java/lang/Integer.valueOf:(I)Ljava/lang/Integer; (1, 1)
	465 aastore (1, 1)
	466 invokespecial (1, 1)
	467 org/apache/commons/math3/exception/MathIllegalArgumentException.<init>:(Lorg/apache/commons/math3/exception/util/Localizable;[Ljava/lang/Object;)V (1, 1)
	469 athrow (1, 1)
	470 dload_0 (0, 0)
	471 dreturn (0, 0)

Method: representableDelta
	0 dload_0 (0, 0)
	1 dload_2 (0, 0)
	2 dadd (0, 0)
	3 dload_0 (0, 0)
	4 dsub (0, 0)
	5 dreturn (0, 0)

Method: <clinit>
	0 dconst_0 (0, 0)
	1 invokestatic (0, 0)
	2 java/lang/Double.doubleToRawLongBits:(D)J (0, 0)
	4 putstatic (0, 0)
	5 org/apache/commons/math3/util/Precision.POSITIVE_ZERO_DOUBLE_BITS:J (0, 0)
	7 ldc2_w (0, 0)
	8 -0.0 (0, 0)
	10 invokestatic (0, 0)
	11 java/lang/Double.doubleToRawLongBits:(D)J (0, 0)
	13 putstatic (0, 0)
	14 org/apache/commons/math3/util/Precision.NEGATIVE_ZERO_DOUBLE_BITS:J (0, 0)
	16 fconst_0 (0, 0)
	17 invokestatic (0, 0)
	18 java/lang/Float.floatToRawIntBits:(F)I (0, 0)
	20 putstatic (0, 0)
	21 org/apache/commons/math3/util/Precision.POSITIVE_ZERO_FLOAT_BITS:I (0, 0)
	23 ldc (0, 0)
	24 -0.0 (0, 0)
	25 invokestatic (0, 0)
	26 java/lang/Float.floatToRawIntBits:(F)I (0, 0)
	28 putstatic (0, 0)
	29 org/apache/commons/math3/util/Precision.NEGATIVE_ZERO_FLOAT_BITS:I (0, 0)
	31 ldc2_w (0, 0)
	32 4368491638549381120 (0, 0)
	34 invokestatic (0, 0)
	35 java/lang/Double.longBitsToDouble:(J)D (0, 0)
	37 putstatic (0, 0)
	38 org/apache/commons/math3/util/Precision.EPSILON:D (0, 0)
	40 ldc2_w (0, 0)
	41 4503599627370496 (0, 0)
	43 invokestatic (0, 0)
	44 java/lang/Double.longBitsToDouble:(J)D (0, 0)
	46 putstatic (0, 0)
	47 org/apache/commons/math3/util/Precision.SAFE_MIN:D (0, 0)
	49 return (0, 0)

