Method: <init>
	0 aload_0 (0, 0)
	1 invokespecial (0, 0)
	2 java/lang/Object.<init>:()V (0, 0)
	4 aload_0 (0, 0)
	5 aload_1 (0, 0)
	6 putfield (0, 0)
	7 org/apache/commons/math3/util/RandomPivotingStrategy.random:Lorg/apache/commons/math3/random/RandomGenerator; (0, 0)
	9 return (0, 0)

Method: pivotIndex
	0 aload_1 (0, 1)
	1 iload_2 (0, 1)
	2 iload_3 (0, 1)
	3 iload_2 (0, 1)
	4 isub (0, 1)
	5 invokestatic (0, 1)
	6 org/apache/commons/math3/util/MathArrays.verifyValues:([DII)Z (0, 1)
	8 pop (0, 1)
	9 iload_2 (0, 1)
	10 aload_0 (0, 1)
	11 getfield (0, 1)
	12 org/apache/commons/math3/util/RandomPivotingStrategy.random:Lorg/apache/commons/math3/random/RandomGenerator; (0, 1)
	14 iload_3 (0, 1)
	15 iload_2 (0, 1)
	16 isub (0, 1)
	17 iconst_1 (0, 1)
	18 isub (0, 1)
	19 invokeinterface (0, 1)
	20 org/apache/commons/math3/random/RandomGenerator.org/apache/commons/math3/util/RandomPivotingStrategy (0, 1)
	22 0 (0, 1)
	24 iadd (0, 1)
	25 ireturn (0, 1)

