Method: <init>
	0 aload_0 (0, 0)
	1 invokespecial (0, 0)
	2 java/lang/Object.<init>:()V (0, 0)
	4 aload_0 (0, 0)
	5 ldc2_w (0, 0)
	6 2.5 (0, 0)
	8 putfield (0, 0)
	9 org/apache/commons/math3/util/ResizableDoubleArray.contractionCriterion:D (0, 0)
	11 aload_0 (1, 1)
	12 ldc2_w (1, 1)
	13 2.0 (1, 1)
	15 putfield (1, 1)
	16 org/apache/commons/math3/util/ResizableDoubleArray.expansionFactor:D (1, 1)
	18 aload_0 (1, 1)
	19 getstatic (1, 1)
	20 org/apache/commons/math3/util/ResizableDoubleArray$ExpansionMode.MULTIPLICATIVE:Lorg/apache/commons/math3/util/ResizableDoubleArray$ExpansionMode; (1, 1)
	22 putfield (1, 1)
	23 org/apache/commons/math3/util/ResizableDoubleArray.expansionMode:Lorg/apache/commons/math3/util/ResizableDoubleArray$ExpansionMode; (1, 1)
	25 aload_0 (1, 1)
	26 iconst_0 (1, 1)
	27 putfield (1, 1)
	28 org/apache/commons/math3/util/ResizableDoubleArray.numElements:I (1, 1)
	30 aload_0 (1, 1)
	31 iconst_0 (1, 1)
	32 putfield (1, 1)
	33 org/apache/commons/math3/util/ResizableDoubleArray.startIndex:I (1, 1)
	35 aload_1 (1, 1)
	36 invokestatic (1, 1)
	37 org/apache/commons/math3/util/MathUtils.checkNotNull:(Ljava/lang/Object;)V (1, 1)
	39 aload_1 (1, 1)
	40 aload_0 (1, 1)
	41 invokestatic (1, 1)
	42 org/apache/commons/math3/util/ResizableDoubleArray.copy:(Lorg/apache/commons/math3/util/ResizableDoubleArray;Lorg/apache/commons/math3/util/ResizableDoubleArray;)V (1, 1)
	44 return (1, 1)

Method: addElement
	0 aload_0 (1, 1)
	1 getfield (1, 1)
	2 org/apache/commons/math3/util/ResizableDoubleArray.internalArray:[D (1, 1)
	4 arraylength (1, 1)
	5 aload_0 (1, 1)
	6 getfield (1, 1)
	7 org/apache/commons/math3/util/ResizableDoubleArray.startIndex:I (1, 1)
	9 aload_0 (1, 1)
	10 getfield (1, 1)
	11 org/apache/commons/math3/util/ResizableDoubleArray.numElements:I (1, 1)
	13 iadd (1, 1)
	14 if_icmpgt (1, 1)
	15 7 (1, 1)
	17 aload_0 (1, 1)
	18 invokevirtual (1, 1)
	19 org/apache/commons/math3/util/ResizableDoubleArray.expand:()V (1, 1)
	21 aload_0 (0, 0)
	22 getfield (0, 0)
	23 org/apache/commons/math3/util/ResizableDoubleArray.internalArray:[D (0, 0)
	25 aload_0 (0, 0)
	26 getfield (0, 0)
	27 org/apache/commons/math3/util/ResizableDoubleArray.startIndex:I (0, 0)
	29 aload_0 (0, 0)
	30 dup (0, 0)
	31 getfield (0, 0)
	32 org/apache/commons/math3/util/ResizableDoubleArray.numElements:I (0, 0)
	34 dup_x1 (0, 0)
	35 iconst_1 (0, 0)
	36 iadd (0, 0)
	37 putfield (0, 0)
	38 org/apache/commons/math3/util/ResizableDoubleArray.numElements:I (0, 0)
	40 iadd (0, 0)
	41 dload_1 (0, 0)
	42 dastore (0, 0)
	43 return (0, 0)

Method: addElements
	0 aload_0 (0, 0)
	1 getfield (0, 0)
	2 org/apache/commons/math3/util/ResizableDoubleArray.numElements:I (0, 0)
	4 aload_1 (0, 0)
	5 arraylength (0, 0)
	6 iadd (0, 0)
	7 iconst_1 (0, 0)
	8 iadd (0, 0)
	9 newarray (0, 0)
	10 7 (0, 0)
	11 astore_2 (0, 0)
	12 aload_0 (0, 0)
	13 getfield (0, 0)
	14 org/apache/commons/math3/util/ResizableDoubleArray.internalArray:[D (0, 0)
	16 aload_0 (0, 0)
	17 getfield (0, 0)
	18 org/apache/commons/math3/util/ResizableDoubleArray.startIndex:I (0, 0)
	20 aload_2 (0, 0)
	21 iconst_0 (0, 0)
	22 aload_0 (0, 0)
	23 getfield (0, 0)
	24 org/apache/commons/math3/util/ResizableDoubleArray.numElements:I (0, 0)
	26 invokestatic (0, 0)
	27 java/lang/System.arraycopy:(Ljava/lang/Object;ILjava/lang/Object;II)V (0, 0)
	29 aload_1 (0, 0)
	30 iconst_0 (0, 0)
	31 aload_2 (0, 0)
	32 aload_0 (0, 0)
	33 getfield (0, 0)
	34 org/apache/commons/math3/util/ResizableDoubleArray.numElements:I (0, 0)
	36 aload_1 (0, 0)
	37 arraylength (0, 0)
	38 invokestatic (0, 0)
	39 java/lang/System.arraycopy:(Ljava/lang/Object;ILjava/lang/Object;II)V (0, 0)
	41 aload_0 (0, 0)
	42 aload_2 (0, 0)
	43 putfield (0, 0)
	44 org/apache/commons/math3/util/ResizableDoubleArray.internalArray:[D (0, 0)
	46 aload_0 (0, 0)
	47 iconst_0 (0, 0)
	48 putfield (0, 0)
	49 org/apache/commons/math3/util/ResizableDoubleArray.startIndex:I (0, 0)
	51 aload_0 (0, 0)
	52 dup (0, 0)
	53 getfield (0, 0)
	54 org/apache/commons/math3/util/ResizableDoubleArray.numElements:I (0, 0)
	56 aload_1 (0, 0)
	57 arraylength (0, 0)
	58 iadd (0, 0)
	59 putfield (0, 0)
	60 org/apache/commons/math3/util/ResizableDoubleArray.numElements:I (0, 0)
	62 return (0, 0)

Method: addElementRolling
	0 aload_0 (0, 0)
	1 getfield (0, 0)
	2 org/apache/commons/math3/util/ResizableDoubleArray.internalArray:[D (0, 0)
	4 aload_0 (0, 0)
	5 getfield (0, 0)
	6 org/apache/commons/math3/util/ResizableDoubleArray.startIndex:I (0, 0)
	8 daload (0, 0)
	9 dstore_3 (0, 0)
	10 aload_0 (1, 1)
	11 getfield (1, 1)
	12 org/apache/commons/math3/util/ResizableDoubleArray.startIndex:I (1, 1)
	14 aload_0 (1, 1)
	15 getfield (1, 1)
	16 org/apache/commons/math3/util/ResizableDoubleArray.numElements:I (1, 1)
	18 iconst_1 (1, 1)
	19 iadd (1, 1)
	20 iadd (1, 1)
	21 aload_0 (1, 1)
	22 getfield (1, 1)
	23 org/apache/commons/math3/util/ResizableDoubleArray.internalArray:[D (1, 1)
	25 arraylength (1, 1)
	26 if_icmple (1, 1)
	27 7 (1, 1)
	29 aload_0 (1, 1)
	30 invokevirtual (1, 1)
	31 org/apache/commons/math3/util/ResizableDoubleArray.expand:()V (1, 1)
	33 aload_0 (0, 0)
	34 dup (0, 0)
	35 getfield (0, 0)
	36 org/apache/commons/math3/util/ResizableDoubleArray.startIndex:I (0, 0)
	38 iconst_1 (0, 0)
	39 iadd (0, 0)
	40 putfield (0, 0)
	41 org/apache/commons/math3/util/ResizableDoubleArray.startIndex:I (0, 0)
	43 aload_0 (0, 0)
	44 getfield (0, 0)
	45 org/apache/commons/math3/util/ResizableDoubleArray.internalArray:[D (0, 0)
	47 aload_0 (0, 0)
	48 getfield (0, 0)
	49 org/apache/commons/math3/util/ResizableDoubleArray.startIndex:I (0, 0)
	51 aload_0 (0, 0)
	52 getfield (0, 0)
	53 org/apache/commons/math3/util/ResizableDoubleArray.numElements:I (0, 0)
	55 iconst_1 (0, 0)
	56 isub (0, 0)
	57 iadd (0, 0)
	58 dload_1 (0, 0)
	59 dastore (0, 0)
	60 aload_0 (1, 1)
	61 invokespecial (1, 1)
	62 org/apache/commons/math3/util/ResizableDoubleArray.shouldContract:()Z (1, 1)
	64 ifeq (1, 1)
	65 7 (1, 1)
	67 aload_0 (1, 1)
	68 invokevirtual (1, 1)
	69 org/apache/commons/math3/util/ResizableDoubleArray.contract:()V (1, 1)
	71 dload_3 (0, 0)
	72 dreturn (0, 0)

Method: substituteMostRecentElement
	0 aload_0 (1, 1)
	1 getfield (1, 1)
	2 org/apache/commons/math3/util/ResizableDoubleArray.numElements:I (1, 1)
	4 iconst_1 (1, 1)
	5 if_icmpge (1, 1)
	6 18 (1, 1)
	8 new (1, 1)
	9 org/apache/commons/math3/exception/MathIllegalStateException (1, 1)
	11 dup (1, 1)
	12 getstatic (1, 1)
	13 org/apache/commons/math3/exception/util/LocalizedFormats.CANNOT_SUBSTITUTE_ELEMENT_FROM_EMPTY_ARRAY:Lorg/apache/commons/math3/exception/util/LocalizedFormats; (1, 1)
	15 iconst_0 (1, 1)
	16 anewarray (1, 1)
	17 java/lang/Object (1, 1)
	19 invokespecial (1, 1)
	20 org/apache/commons/math3/exception/MathIllegalStateException.<init>:(Lorg/apache/commons/math3/exception/util/Localizable;[Ljava/lang/Object;)V (1, 1)
	22 athrow (1, 1)
	23 aload_0 (0, 0)
	24 getfield (0, 0)
	25 org/apache/commons/math3/util/ResizableDoubleArray.startIndex:I (0, 0)
	27 aload_0 (0, 0)
	28 getfield (0, 0)
	29 org/apache/commons/math3/util/ResizableDoubleArray.numElements:I (0, 0)
	31 iconst_1 (0, 0)
	32 isub (0, 0)
	33 iadd (0, 0)
	34 istore_3 (0, 0)
	35 aload_0 (0, 0)
	36 getfield (0, 0)
	37 org/apache/commons/math3/util/ResizableDoubleArray.internalArray:[D (0, 0)
	39 iload_3 (0, 0)
	40 daload (0, 0)
	41 dstore (0, 0)
	42 #4 (0, 0)
	43 aload_0 (0, 0)
	44 getfield (0, 0)
	45 org/apache/commons/math3/util/ResizableDoubleArray.internalArray:[D (0, 0)
	47 iload_3 (0, 0)
	48 dload_1 (0, 0)
	49 dastore (0, 0)
	50 dload (0, 0)
	51 #4 (0, 0)
	52 dreturn (0, 0)

Method: checkContractExpand
	0 dload_1 (1, 1)
	1 dload_3 (1, 1)
	2 dcmpg (1, 1)
	3 ifge (1, 1)
	4 53 (1, 1)
	6 new (1, 1)
	7 org/apache/commons/math3/exception/NumberIsTooSmallException (1, 1)
	9 dup (1, 1)
	10 dload_1 (1, 1)
	11 invokestatic (1, 1)
	12 java/lang/Double.valueOf:(D)Ljava/lang/Double; (1, 1)
	14 iconst_1 (1, 1)
	15 invokestatic (1, 1)
	16 java/lang/Integer.valueOf:(I)Ljava/lang/Integer; (1, 1)
	18 iconst_1 (1, 1)
	19 invokespecial (1, 1)
	20 org/apache/commons/math3/exception/NumberIsTooSmallException.<init>:(Ljava/lang/Number;Ljava/lang/Number;Z)V (1, 1)
	22 astore (1, 1)
	23 #5 (1, 1)
	24 aload (1, 1)
	25 #5 (1, 1)
	26 invokevirtual (1, 1)
	27 org/apache/commons/math3/exception/NumberIsTooSmallException.getContext:()Lorg/apache/commons/math3/exception/util/ExceptionContext; (1, 1)
	29 getstatic (1, 1)
	30 org/apache/commons/math3/exception/util/LocalizedFormats.CONTRACTION_CRITERIA_SMALLER_THAN_EXPANSION_FACTOR:Lorg/apache/commons/math3/exception/util/LocalizedFormats; (1, 1)
	32 iconst_2 (1, 1)
	33 anewarray (1, 1)
	34 java/lang/Object (1, 1)
	36 dup (1, 1)
	37 iconst_0 (1, 1)
	38 dload_1 (1, 1)
	39 invokestatic (1, 1)
	40 java/lang/Double.valueOf:(D)Ljava/lang/Double; (1, 1)
	42 aastore (1, 1)
	43 dup (1, 1)
	44 iconst_1 (1, 1)
	45 dload_3 (1, 1)
	46 invokestatic (1, 1)
	47 java/lang/Double.valueOf:(D)Ljava/lang/Double; (1, 1)
	49 aastore (1, 1)
	50 invokevirtual (1, 1)
	51 org/apache/commons/math3/exception/util/ExceptionContext.addMessage:(Lorg/apache/commons/math3/exception/util/Localizable;[Ljava/lang/Object;)V (1, 1)
	53 aload (1, 1)
	54 #5 (1, 1)
	55 athrow (1, 1)
	56 dload_1 (1, 1)
	57 dconst_1 (1, 1)
	58 dcmpg (1, 1)
	59 ifgt (1, 1)
	60 46 (1, 1)
	62 new (1, 1)
	63 org/apache/commons/math3/exception/NumberIsTooSmallException (1, 1)
	65 dup (1, 1)
	66 dload_1 (1, 1)
	67 invokestatic (1, 1)
	68 java/lang/Double.valueOf:(D)Ljava/lang/Double; (1, 1)
	70 iconst_1 (1, 1)
	71 invokestatic (1, 1)
	72 java/lang/Integer.valueOf:(I)Ljava/lang/Integer; (1, 1)
	74 iconst_0 (1, 1)
	75 invokespecial (1, 1)
	76 org/apache/commons/math3/exception/NumberIsTooSmallException.<init>:(Ljava/lang/Number;Ljava/lang/Number;Z)V (1, 1)
	78 astore (1, 1)
	79 #5 (1, 1)
	80 aload (1, 1)
	81 #5 (1, 1)
	82 invokevirtual (1, 1)
	83 org/apache/commons/math3/exception/NumberIsTooSmallException.getContext:()Lorg/apache/commons/math3/exception/util/ExceptionContext; (1, 1)
	85 getstatic (1, 1)
	86 org/apache/commons/math3/exception/util/LocalizedFormats.CONTRACTION_CRITERIA_SMALLER_THAN_ONE:Lorg/apache/commons/math3/exception/util/LocalizedFormats; (1, 1)
	88 iconst_1 (1, 1)
	89 anewarray (1, 1)
	90 java/lang/Object (1, 1)
	92 dup (1, 1)
	93 iconst_0 (1, 1)
	94 dload_1 (1, 1)
	95 invokestatic (1, 1)
	96 java/lang/Double.valueOf:(D)Ljava/lang/Double; (1, 1)
	98 aastore (1, 1)
	99 invokevirtual (1, 1)
	100 org/apache/commons/math3/exception/util/ExceptionContext.addMessage:(Lorg/apache/commons/math3/exception/util/Localizable;[Ljava/lang/Object;)V (1, 1)
	102 aload (1, 1)
	103 #5 (1, 1)
	104 athrow (1, 1)
	105 dload_3 (1, 1)
	106 dconst_1 (1, 1)
	107 dcmpg (1, 1)
	108 ifgt (1, 1)
	109 46 (1, 1)
	111 new (1, 1)
	112 org/apache/commons/math3/exception/NumberIsTooSmallException (1, 1)
	114 dup (1, 1)
	115 dload_1 (1, 1)
	116 invokestatic (1, 1)
	117 java/lang/Double.valueOf:(D)Ljava/lang/Double; (1, 1)
	119 iconst_1 (1, 1)
	120 invokestatic (1, 1)
	121 java/lang/Integer.valueOf:(I)Ljava/lang/Integer; (1, 1)
	123 iconst_0 (1, 1)
	124 invokespecial (1, 1)
	125 org/apache/commons/math3/exception/NumberIsTooSmallException.<init>:(Ljava/lang/Number;Ljava/lang/Number;Z)V (1, 1)
	127 astore (1, 1)
	128 #5 (1, 1)
	129 aload (1, 1)
	130 #5 (1, 1)
	131 invokevirtual (1, 1)
	132 org/apache/commons/math3/exception/NumberIsTooSmallException.getContext:()Lorg/apache/commons/math3/exception/util/ExceptionContext; (1, 1)
	134 getstatic (1, 1)
	135 org/apache/commons/math3/exception/util/LocalizedFormats.EXPANSION_FACTOR_SMALLER_THAN_ONE:Lorg/apache/commons/math3/exception/util/LocalizedFormats; (1, 1)
	137 iconst_1 (1, 1)
	138 anewarray (1, 1)
	139 java/lang/Object (1, 1)
	141 dup (1, 1)
	142 iconst_0 (1, 1)
	143 dload_3 (1, 1)
	144 invokestatic (1, 1)
	145 java/lang/Double.valueOf:(D)Ljava/lang/Double; (1, 1)
	147 aastore (1, 1)
	148 invokevirtual (1, 1)
	149 org/apache/commons/math3/exception/util/ExceptionContext.addMessage:(Lorg/apache/commons/math3/exception/util/Localizable;[Ljava/lang/Object;)V (1, 1)
	151 aload (1, 1)
	152 #5 (1, 1)
	153 athrow (1, 1)
	154 return (0, 0)

Method: clear
	0 aload_0 (0, 0)
	1 iconst_0 (0, 0)
	2 putfield (0, 0)
	3 org/apache/commons/math3/util/ResizableDoubleArray.numElements:I (0, 0)
	5 aload_0 (0, 0)
	6 iconst_0 (0, 0)
	7 putfield (0, 0)
	8 org/apache/commons/math3/util/ResizableDoubleArray.startIndex:I (0, 0)
	10 return (0, 0)

Method: contract
	0 aload_0 (0, 0)
	1 getfield (0, 0)
	2 org/apache/commons/math3/util/ResizableDoubleArray.numElements:I (0, 0)
	4 iconst_1 (0, 0)
	5 iadd (0, 0)
	6 newarray (0, 0)
	7 7 (0, 0)
	8 astore_1 (0, 0)
	9 aload_0 (0, 0)
	10 getfield (0, 0)
	11 org/apache/commons/math3/util/ResizableDoubleArray.internalArray:[D (0, 0)
	13 aload_0 (0, 0)
	14 getfield (0, 0)
	15 org/apache/commons/math3/util/ResizableDoubleArray.startIndex:I (0, 0)
	17 aload_1 (0, 0)
	18 iconst_0 (0, 0)
	19 aload_0 (0, 0)
	20 getfield (0, 0)
	21 org/apache/commons/math3/util/ResizableDoubleArray.numElements:I (0, 0)
	23 invokestatic (0, 0)
	24 java/lang/System.arraycopy:(Ljava/lang/Object;ILjava/lang/Object;II)V (0, 0)
	26 aload_0 (0, 0)
	27 aload_1 (0, 0)
	28 putfield (0, 0)
	29 org/apache/commons/math3/util/ResizableDoubleArray.internalArray:[D (0, 0)
	31 aload_0 (0, 0)
	32 iconst_0 (0, 0)
	33 putfield (0, 0)
	34 org/apache/commons/math3/util/ResizableDoubleArray.startIndex:I (0, 0)
	36 return (0, 0)

Method: discardFrontElements
	0 aload_0 (0, 0)
	1 iload_1 (0, 0)
	2 iconst_1 (0, 0)
	3 invokespecial (0, 0)
	4 org/apache/commons/math3/util/ResizableDoubleArray.discardExtremeElements:(IZ)V (0, 0)
	6 return (0, 0)

Method: discardMostRecentElements
	0 aload_0 (0, 0)
	1 iload_1 (0, 0)
	2 iconst_0 (0, 0)
	3 invokespecial (0, 0)
	4 org/apache/commons/math3/util/ResizableDoubleArray.discardExtremeElements:(IZ)V (0, 0)
	6 return (0, 0)

Method: discardExtremeElements
	0 iload_1 (1, 1)
	1 aload_0 (1, 1)
	2 getfield (1, 1)
	3 org/apache/commons/math3/util/ResizableDoubleArray.numElements:I (1, 1)
	5 if_icmple (1, 1)
	6 35 (1, 1)
	8 new (1, 1)
	9 org/apache/commons/math3/exception/MathIllegalArgumentException (1, 1)
	11 dup (1, 1)
	12 getstatic (1, 1)
	13 org/apache/commons/math3/exception/util/LocalizedFormats.TOO_MANY_ELEMENTS_TO_DISCARD_FROM_ARRAY:Lorg/apache/commons/math3/exception/util/LocalizedFormats; (1, 1)
	15 iconst_2 (1, 1)
	16 anewarray (1, 1)
	17 java/lang/Object (1, 1)
	19 dup (1, 1)
	20 iconst_0 (1, 1)
	21 iload_1 (1, 1)
	22 invokestatic (1, 1)
	23 java/lang/Integer.valueOf:(I)Ljava/lang/Integer; (1, 1)
	25 aastore (1, 1)
	26 dup (1, 1)
	27 iconst_1 (1, 1)
	28 aload_0 (1, 1)
	29 getfield (1, 1)
	30 org/apache/commons/math3/util/ResizableDoubleArray.numElements:I (1, 1)
	32 invokestatic (1, 1)
	33 java/lang/Integer.valueOf:(I)Ljava/lang/Integer; (1, 1)
	35 aastore (1, 1)
	36 invokespecial (1, 1)
	37 org/apache/commons/math3/exception/MathIllegalArgumentException.<init>:(Lorg/apache/commons/math3/exception/util/Localizable;[Ljava/lang/Object;)V (1, 1)
	39 athrow (1, 1)
	40 iload_1 (1, 1)
	41 ifge (1, 1)
	42 25 (1, 1)
	44 new (1, 1)
	45 org/apache/commons/math3/exception/MathIllegalArgumentException (1, 1)
	47 dup (1, 1)
	48 getstatic (1, 1)
	49 org/apache/commons/math3/exception/util/LocalizedFormats.CANNOT_DISCARD_NEGATIVE_NUMBER_OF_ELEMENTS:Lorg/apache/commons/math3/exception/util/LocalizedFormats; (1, 1)
	51 iconst_1 (1, 1)
	52 anewarray (1, 1)
	53 java/lang/Object (1, 1)
	55 dup (1, 1)
	56 iconst_0 (1, 1)
	57 iload_1 (1, 1)
	58 invokestatic (1, 1)
	59 java/lang/Integer.valueOf:(I)Ljava/lang/Integer; (1, 1)
	61 aastore (1, 1)
	62 invokespecial (1, 1)
	63 org/apache/commons/math3/exception/MathIllegalArgumentException.<init>:(Lorg/apache/commons/math3/exception/util/Localizable;[Ljava/lang/Object;)V (1, 1)
	65 athrow (1, 1)
	66 aload_0 (1, 2)
	67 dup (1, 2)
	68 getfield (1, 2)
	69 org/apache/commons/math3/util/ResizableDoubleArray.numElements:I (1, 2)
	71 iload_1 (1, 2)
	72 isub (1, 2)
	73 putfield (1, 2)
	74 org/apache/commons/math3/util/ResizableDoubleArray.numElements:I (1, 2)
	76 iload_2 (2, 1)
	77 ifeq (2, 1)
	78 13 (2, 1)
	80 aload_0 (2, 1)
	81 dup (2, 1)
	82 getfield (2, 1)
	83 org/apache/commons/math3/util/ResizableDoubleArray.startIndex:I (2, 1)
	85 iload_1 (2, 1)
	86 iadd (2, 1)
	87 putfield (2, 1)
	88 org/apache/commons/math3/util/ResizableDoubleArray.startIndex:I (2, 1)
	90 aload_0 (1, 1)
	91 invokespecial (1, 1)
	92 org/apache/commons/math3/util/ResizableDoubleArray.shouldContract:()Z (1, 1)
	94 ifeq (1, 1)
	95 7 (1, 1)
	97 aload_0 (1, 1)
	98 invokevirtual (1, 1)
	99 org/apache/commons/math3/util/ResizableDoubleArray.contract:()V (1, 1)
	101 return (0, 0)

Method: expand
	0 iconst_0 (0, 0)
	1 istore_1 (0, 0)
	2 aload_0 (1, 1)
	3 getfield (1, 1)
	4 org/apache/commons/math3/util/ResizableDoubleArray.expansionMode:Lorg/apache/commons/math3/util/ResizableDoubleArray$ExpansionMode; (1, 1)
	6 getstatic (1, 1)
	7 org/apache/commons/math3/util/ResizableDoubleArray$ExpansionMode.MULTIPLICATIVE:Lorg/apache/commons/math3/util/ResizableDoubleArray$ExpansionMode; (1, 1)
	9 if_acmpne (1, 1)
	10 22 (1, 1)
	12 aload_0 (1, 1)
	13 getfield (1, 1)
	14 org/apache/commons/math3/util/ResizableDoubleArray.internalArray:[D (1, 1)
	16 arraylength (1, 1)
	17 i2d (1, 1)
	18 aload_0 (1, 1)
	19 getfield (1, 1)
	20 org/apache/commons/math3/util/ResizableDoubleArray.expansionFactor:D (1, 1)
	22 dmul (1, 1)
	23 invokestatic (1, 1)
	24 org/apache/commons/math3/util/FastMath.ceil:(D)D (1, 1)
	26 d2i (1, 1)
	27 istore_1 (1, 1)
	28 goto (1, 1)
	29 19 (1, 1)
	31 aload_0 (1, 2)
	32 getfield (1, 2)
	33 org/apache/commons/math3/util/ResizableDoubleArray.internalArray:[D (1, 2)
	35 arraylength (1, 2)
	36 i2l (1, 2)
	37 aload_0 (1, 2)
	38 getfield (1, 2)
	39 org/apache/commons/math3/util/ResizableDoubleArray.expansionFactor:D (1, 2)
	41 invokestatic (1, 2)
	42 org/apache/commons/math3/util/FastMath.round:(D)J (1, 2)
	44 ladd (1, 2)
	45 l2i (1, 2)
	46 istore_1 (1, 2)
	47 iload_1 (0, 0)
	48 newarray (0, 0)
	49 7 (0, 0)
	50 astore_2 (0, 0)
	51 aload_0 (0, 0)
	52 getfield (0, 0)
	53 org/apache/commons/math3/util/ResizableDoubleArray.internalArray:[D (0, 0)
	55 iconst_0 (0, 0)
	56 aload_2 (0, 0)
	57 iconst_0 (0, 0)
	58 aload_0 (0, 0)
	59 getfield (0, 0)
	60 org/apache/commons/math3/util/ResizableDoubleArray.internalArray:[D (0, 0)
	62 arraylength (0, 0)
	63 invokestatic (0, 0)
	64 java/lang/System.arraycopy:(Ljava/lang/Object;ILjava/lang/Object;II)V (0, 0)
	66 aload_0 (0, 0)
	67 aload_2 (0, 0)
	68 putfield (0, 0)
	69 org/apache/commons/math3/util/ResizableDoubleArray.internalArray:[D (0, 0)
	71 return (0, 0)

Method: expandTo
	0 iload_1 (0, 0)
	1 newarray (0, 0)
	2 7 (0, 0)
	3 astore_2 (0, 0)
	4 aload_0 (0, 0)
	5 getfield (0, 0)
	6 org/apache/commons/math3/util/ResizableDoubleArray.internalArray:[D (0, 0)
	8 iconst_0 (0, 0)
	9 aload_2 (0, 0)
	10 iconst_0 (0, 0)
	11 aload_0 (0, 0)
	12 getfield (0, 0)
	13 org/apache/commons/math3/util/ResizableDoubleArray.internalArray:[D (0, 0)
	15 arraylength (0, 0)
	16 invokestatic (0, 0)
	17 java/lang/System.arraycopy:(Ljava/lang/Object;ILjava/lang/Object;II)V (0, 0)
	19 aload_0 (0, 0)
	20 aload_2 (0, 0)
	21 putfield (0, 0)
	22 org/apache/commons/math3/util/ResizableDoubleArray.internalArray:[D (0, 0)
	24 return (0, 0)

Method: getContractionCriteria
	0 aload_0 (0, 0)
	1 invokevirtual (0, 0)
	2 org/apache/commons/math3/util/ResizableDoubleArray.getContractionCriterion:()D (0, 0)
	4 d2f (0, 0)
	5 freturn (0, 0)

Method: getContractionCriterion
	0 aload_0 (0, 0)
	1 getfield (0, 0)
	2 org/apache/commons/math3/util/ResizableDoubleArray.contractionCriterion:D (0, 0)
	4 dreturn (0, 0)

Method: getElement
	0 iload_1 (1, 1)
	1 aload_0 (1, 1)
	2 getfield (1, 1)
	3 org/apache/commons/math3/util/ResizableDoubleArray.numElements:I (1, 1)
	5 if_icmplt (1, 1)
	6 12 (1, 1)
	8 new (1, 1)
	9 java/lang/ArrayIndexOutOfBoundsException (1, 1)
	11 dup (1, 1)
	12 iload_1 (1, 1)
	13 invokespecial (1, 1)
	14 java/lang/ArrayIndexOutOfBoundsException.<init>:(I)V (1, 1)
	16 athrow (1, 1)
	17 iload_1 (1, 1)
	18 iflt (1, 1)
	19 15 (1, 1)
	21 aload_0 (1, 1)
	22 getfield (1, 1)
	23 org/apache/commons/math3/util/ResizableDoubleArray.internalArray:[D (1, 1)
	25 aload_0 (1, 1)
	26 getfield (1, 1)
	27 org/apache/commons/math3/util/ResizableDoubleArray.startIndex:I (1, 1)
	29 iload_1 (1, 1)
	30 iadd (1, 1)
	31 daload (1, 1)
	32 dreturn (1, 1)
	33 new (1, 2)
	34 java/lang/ArrayIndexOutOfBoundsException (1, 2)
	36 dup (1, 2)
	37 iload_1 (1, 2)
	38 invokespecial (1, 2)
	39 java/lang/ArrayIndexOutOfBoundsException.<init>:(I)V (1, 2)
	41 athrow (1, 2)

Method: getElements
	0 aload_0 (0, 0)
	1 getfield (0, 0)
	2 org/apache/commons/math3/util/ResizableDoubleArray.numElements:I (0, 0)
	4 newarray (0, 0)
	5 7 (0, 0)
	6 astore_1 (0, 0)
	7 aload_0 (0, 0)
	8 getfield (0, 0)
	9 org/apache/commons/math3/util/ResizableDoubleArray.internalArray:[D (0, 0)
	11 aload_0 (0, 0)
	12 getfield (0, 0)
	13 org/apache/commons/math3/util/ResizableDoubleArray.startIndex:I (0, 0)
	15 aload_1 (0, 0)
	16 iconst_0 (0, 0)
	17 aload_0 (0, 0)
	18 getfield (0, 0)
	19 org/apache/commons/math3/util/ResizableDoubleArray.numElements:I (0, 0)
	21 invokestatic (0, 0)
	22 java/lang/System.arraycopy:(Ljava/lang/Object;ILjava/lang/Object;II)V (0, 0)
	24 aload_1 (0, 0)
	25 areturn (0, 0)

Method: getExpansionFactor
	0 aload_0 (0, 0)
	1 getfield (0, 0)
	2 org/apache/commons/math3/util/ResizableDoubleArray.expansionFactor:D (0, 0)
	4 d2f (0, 0)
	5 freturn (0, 0)

Method: getExpansionMode
	0 aload_0 (0, 0)
	1 dup (0, 0)
	2 astore_1 (0, 0)
	3 monitorenter (0, 0)
	4 getstatic (2, 5)
	5 org/apache/commons/math3/util/ResizableDoubleArray$1.$SwitchMap$org$apache$commons$math3$util$ResizableDoubleArray$ExpansionMode:[I (2, 5)
	7 aload_0 (2, 5)
	8 getfield (2, 5)
	9 org/apache/commons/math3/util/ResizableDoubleArray.expansionMode:Lorg/apache/commons/math3/util/ResizableDoubleArray$ExpansionMode; (2, 5)
	11 invokevirtual (2, 5)
	12 org/apache/commons/math3/util/ResizableDoubleArray$ExpansionMode.ordinal:()I (2, 5)
	14 iaload (2, 5)
	15 lookupswitch (2, 5)
	16 1: 40 (2, 5)
	20 2: 44 (2, 5)
	40 iconst_0 (2, 5)
	41 aload_1 (2, 5)
	42 monitorexit (2, 5)
	43 ireturn (2, 5)
	44 iconst_1 (2, 5)
	45 aload_1 (2, 5)
	46 monitorexit (2, 5)
	47 ireturn (2, 5)
	48 new (2, 5)
	49 org/apache/commons/math3/exception/MathInternalError (2, 5)
	51 dup (2, 5)
	52 invokespecial (2, 5)
	53 org/apache/commons/math3/exception/MathInternalError.<init>:()V (2, 5)
	55 athrow (2, 5)
	56 astore_2 (0, 0)
	57 aload_1 (0, 0)
	58 monitorexit (0, 0)
	59 aload_2 (0, 0)
	60 athrow (0, 0)

Method: getInternalLength
	0 aload_0 (0, 0)
	1 getfield (0, 0)
	2 org/apache/commons/math3/util/ResizableDoubleArray.internalArray:[D (0, 0)
	4 arraylength (0, 0)
	5 ireturn (0, 0)

Method: getCapacity
	0 aload_0 (0, 0)
	1 getfield (0, 0)
	2 org/apache/commons/math3/util/ResizableDoubleArray.internalArray:[D (0, 0)
	4 arraylength (0, 0)
	5 ireturn (0, 0)

Method: getNumElements
	0 aload_0 (0, 0)
	1 getfield (0, 0)
	2 org/apache/commons/math3/util/ResizableDoubleArray.numElements:I (0, 0)
	4 ireturn (0, 0)

Method: getInternalValues
	0 aload_0 (0, 0)
	1 getfield (0, 0)
	2 org/apache/commons/math3/util/ResizableDoubleArray.internalArray:[D (0, 0)
	4 areturn (0, 0)

Method: getArrayRef
	0 aload_0 (0, 0)
	1 getfield (0, 0)
	2 org/apache/commons/math3/util/ResizableDoubleArray.internalArray:[D (0, 0)
	4 areturn (0, 0)

Method: getStartIndex
	0 aload_0 (0, 0)
	1 getfield (0, 0)
	2 org/apache/commons/math3/util/ResizableDoubleArray.startIndex:I (0, 0)
	4 ireturn (0, 0)

Method: setContractionCriteria
	0 aload_0 (0, 0)
	1 fload_1 (0, 0)
	2 aload_0 (0, 0)
	3 invokevirtual (0, 0)
	4 org/apache/commons/math3/util/ResizableDoubleArray.getExpansionFactor:()F (0, 0)
	6 invokevirtual (0, 0)
	7 org/apache/commons/math3/util/ResizableDoubleArray.checkContractExpand:(FF)V (0, 0)
	9 aload_0 (0, 0)
	10 dup (0, 0)
	11 astore_2 (0, 0)
	12 monitorenter (0, 0)
	13 aload_0 (0, 0)
	14 fload_1 (0, 0)
	15 f2d (0, 0)
	16 putfield (0, 0)
	17 org/apache/commons/math3/util/ResizableDoubleArray.contractionCriterion:D (0, 0)
	19 aload_2 (0, 0)
	20 monitorexit (0, 0)
	21 goto (0, 0)
	22 8 (0, 0)
	24 astore_3 (0, 0)
	25 aload_2 (0, 0)
	26 monitorexit (0, 0)
	27 aload_3 (0, 0)
	28 athrow (0, 0)
	29 return (0, 0)

Method: compute
	0 aload_0 (0, 0)
	1 dup (0, 0)
	2 astore (0, 0)
	3 #5 (0, 0)
	4 monitorenter (0, 0)
	5 aload_0 (0, 0)
	6 getfield (0, 0)
	7 org/apache/commons/math3/util/ResizableDoubleArray.internalArray:[D (0, 0)
	9 astore_2 (0, 0)
	10 aload_0 (0, 0)
	11 getfield (0, 0)
	12 org/apache/commons/math3/util/ResizableDoubleArray.startIndex:I (0, 0)
	14 istore_3 (0, 0)
	15 aload_0 (0, 0)
	16 getfield (0, 0)
	17 org/apache/commons/math3/util/ResizableDoubleArray.numElements:I (0, 0)
	19 istore (0, 0)
	20 #4 (0, 0)
	21 aload (0, 0)
	22 #5 (0, 0)
	23 monitorexit (0, 0)
	24 goto (0, 0)
	25 11 (0, 0)
	27 astore (0, 0)
	28 #6 (0, 0)
	29 aload (0, 0)
	30 #5 (0, 0)
	31 monitorexit (0, 0)
	32 aload (0, 0)
	33 #6 (0, 0)
	34 athrow (0, 0)
	35 aload_1 (0, 0)
	36 aload_2 (0, 0)
	37 iload_3 (0, 0)
	38 iload (0, 0)
	39 #4 (0, 0)
	40 invokeinterface (0, 0)
	41 org/apache/commons/math3/util/MathArrays$Function.expandTo:(I)V (0, 0)
	43 0 (0, 0)
	45 dreturn (0, 0)

Method: setElement
	0 iload_1 (1, 1)
	1 ifge (1, 1)
	2 12 (1, 1)
	4 new (1, 1)
	5 java/lang/ArrayIndexOutOfBoundsException (1, 1)
	7 dup (1, 1)
	8 iload_1 (1, 1)
	9 invokespecial (1, 1)
	10 java/lang/ArrayIndexOutOfBoundsException.<init>:(I)V (1, 1)
	12 athrow (1, 1)
	13 iload_1 (1, 1)
	14 iconst_1 (1, 1)
	15 iadd (1, 1)
	16 aload_0 (1, 1)
	17 getfield (1, 1)
	18 org/apache/commons/math3/util/ResizableDoubleArray.numElements:I (1, 1)
	20 if_icmple (1, 1)
	21 10 (1, 1)
	23 aload_0 (1, 1)
	24 iload_1 (1, 1)
	25 iconst_1 (1, 1)
	26 iadd (1, 1)
	27 putfield (1, 1)
	28 org/apache/commons/math3/util/ResizableDoubleArray.numElements:I (1, 1)
	30 aload_0 (1, 1)
	31 getfield (1, 1)
	32 org/apache/commons/math3/util/ResizableDoubleArray.startIndex:I (1, 1)
	34 iload_1 (1, 1)
	35 iadd (1, 1)
	36 aload_0 (1, 1)
	37 getfield (1, 1)
	38 org/apache/commons/math3/util/ResizableDoubleArray.internalArray:[D (1, 1)
	40 arraylength (1, 1)
	41 if_icmplt (1, 1)
	42 15 (1, 1)
	44 aload_0 (1, 1)
	45 aload_0 (1, 1)
	46 getfield (1, 1)
	47 org/apache/commons/math3/util/ResizableDoubleArray.startIndex:I (1, 1)
	49 iload_1 (1, 1)
	50 iconst_1 (1, 1)
	51 iadd (1, 1)
	52 iadd (1, 1)
	53 invokespecial (1, 1)
	54 org/apache/commons/math3/util/ResizableDoubleArray.expandTo:(I)V (1, 1)
	56 aload_0 (0, 0)
	57 getfield (0, 0)
	58 org/apache/commons/math3/util/ResizableDoubleArray.internalArray:[D (0, 0)
	60 aload_0 (0, 0)
	61 getfield (0, 0)
	62 org/apache/commons/math3/util/ResizableDoubleArray.startIndex:I (0, 0)
	64 iload_1 (0, 0)
	65 iadd (0, 0)
	66 dload_2 (0, 0)
	67 dastore (0, 0)
	68 return (0, 0)

Method: setExpansionFactor
	0 aload_0 (0, 0)
	1 aload_0 (0, 0)
	2 invokevirtual (0, 0)
	3 org/apache/commons/math3/util/ResizableDoubleArray.getContractionCriterion:()D (0, 0)
	5 fload_1 (0, 0)
	6 f2d (0, 0)
	7 invokevirtual (0, 0)
	8 org/apache/commons/math3/util/ResizableDoubleArray.checkContractExpand:(DD)V (0, 0)
	10 aload_0 (0, 1)
	11 dup (0, 1)
	12 astore_2 (0, 1)
	13 monitorenter (0, 1)
	14 aload_0 (0, 1)
	15 fload_1 (0, 1)
	16 f2d (0, 1)
	17 putfield (0, 1)
	18 org/apache/commons/math3/util/ResizableDoubleArray.expansionFactor:D (0, 1)
	20 aload_2 (0, 1)
	21 monitorexit (0, 1)
	22 goto (0, 1)
	23 8 (0, 1)
	25 astore_3 (0, 1)
	26 aload_2 (0, 1)
	27 monitorexit (0, 1)
	28 aload_3 (0, 1)
	29 athrow (0, 1)
	30 return (0, 1)

Method: setExpansionMode
	0 aload_0 (0, 0)
	1 dup (0, 0)
	2 astore_2 (0, 0)
	3 monitorenter (0, 0)
	4 aload_0 (0, 0)
	5 aload_1 (0, 0)
	6 putfield (0, 0)
	7 org/apache/commons/math3/util/ResizableDoubleArray.expansionMode:Lorg/apache/commons/math3/util/ResizableDoubleArray$ExpansionMode; (0, 0)
	9 aload_2 (0, 0)
	10 monitorexit (0, 0)
	11 goto (0, 0)
	12 8 (0, 0)
	14 astore_3 (0, 0)
	15 aload_2 (0, 0)
	16 monitorexit (0, 0)
	17 aload_3 (0, 0)
	18 athrow (0, 0)
	19 return (0, 0)

Method: setInitialCapacity
	0 return (0, 0)

Method: setNumElements
	0 iload_1 (1, 1)
	1 ifge (1, 1)
	2 25 (1, 1)
	4 new (1, 1)
	5 org/apache/commons/math3/exception/MathIllegalArgumentException (1, 1)
	7 dup (1, 1)
	8 getstatic (1, 1)
	9 org/apache/commons/math3/exception/util/LocalizedFormats.INDEX_NOT_POSITIVE:Lorg/apache/commons/math3/exception/util/LocalizedFormats; (1, 1)
	11 iconst_1 (1, 1)
	12 anewarray (1, 1)
	13 java/lang/Object (1, 1)
	15 dup (1, 1)
	16 iconst_0 (1, 1)
	17 iload_1 (1, 1)
	18 invokestatic (1, 1)
	19 java/lang/Integer.valueOf:(I)Ljava/lang/Integer; (1, 1)
	21 aastore (1, 1)
	22 invokespecial (1, 1)
	23 org/apache/commons/math3/exception/MathIllegalArgumentException.<init>:(Lorg/apache/commons/math3/exception/util/Localizable;[Ljava/lang/Object;)V (1, 1)
	25 athrow (1, 1)
	26 aload_0 (0, 1)
	27 getfield (0, 1)
	28 org/apache/commons/math3/util/ResizableDoubleArray.startIndex:I (0, 1)
	30 iload_1 (0, 1)
	31 iadd (0, 1)
	32 istore_2 (0, 1)
	33 iload_2 (1, 1)
	34 aload_0 (1, 1)
	35 getfield (1, 1)
	36 org/apache/commons/math3/util/ResizableDoubleArray.internalArray:[D (1, 1)
	38 arraylength (1, 1)
	39 if_icmple (1, 1)
	40 8 (1, 1)
	42 aload_0 (1, 1)
	43 iload_2 (1, 1)
	44 invokespecial (1, 1)
	45 org/apache/commons/math3/util/ResizableDoubleArray.expandTo:(I)V (1, 1)
	47 aload_0 (0, 1)
	48 iload_1 (0, 1)
	49 putfield (0, 1)
	50 org/apache/commons/math3/util/ResizableDoubleArray.numElements:I (0, 1)
	52 return (0, 1)

Method: shouldContract
	0 aload_0 (1, 1)
	1 getfield (1, 1)
	2 org/apache/commons/math3/util/ResizableDoubleArray.expansionMode:Lorg/apache/commons/math3/util/ResizableDoubleArray$ExpansionMode; (1, 1)
	4 getstatic (1, 1)
	5 org/apache/commons/math3/util/ResizableDoubleArray$ExpansionMode.MULTIPLICATIVE:Lorg/apache/commons/math3/util/ResizableDoubleArray$ExpansionMode; (1, 1)
	7 if_acmpne (1, 1)
	8 30 (1, 1)
	10 aload_0 (1, 1)
	11 getfield (1, 1)
	12 org/apache/commons/math3/util/ResizableDoubleArray.internalArray:[D (1, 1)
	14 arraylength (1, 1)
	15 i2f (1, 1)
	16 aload_0 (1, 1)
	17 getfield (1, 1)
	18 org/apache/commons/math3/util/ResizableDoubleArray.numElements:I (1, 1)
	20 i2f (1, 1)
	21 fdiv (1, 1)
	22 f2d (1, 1)
	23 aload_0 (1, 1)
	24 getfield (1, 1)
	25 org/apache/commons/math3/util/ResizableDoubleArray.contractionCriterion:D (1, 1)
	27 dcmpl (1, 1)
	28 ifle (1, 1)
	29 7 (1, 1)
	31 iconst_1 (1, 1)
	32 goto (1, 1)
	33 4 (1, 1)
	35 iconst_0 (1, 1)
	36 ireturn (1, 1)
	37 aload_0 (1, 2)
	38 getfield (1, 2)
	39 org/apache/commons/math3/util/ResizableDoubleArray.internalArray:[D (1, 2)
	41 arraylength (1, 2)
	42 aload_0 (1, 2)
	43 getfield (1, 2)
	44 org/apache/commons/math3/util/ResizableDoubleArray.numElements:I (1, 2)
	46 isub (1, 2)
	47 i2d (1, 2)
	48 aload_0 (1, 2)
	49 getfield (1, 2)
	50 org/apache/commons/math3/util/ResizableDoubleArray.contractionCriterion:D (1, 2)
	52 dcmpl (1, 2)
	53 ifle (1, 2)
	54 7 (1, 2)
	56 iconst_1 (1, 2)
	57 goto (1, 2)
	58 4 (1, 2)
	60 iconst_0 (1, 2)
	61 ireturn (1, 2)

Method: start
	0 aload_0 (0, 0)
	1 getfield (0, 0)
	2 org/apache/commons/math3/util/ResizableDoubleArray.startIndex:I (0, 0)
	4 ireturn (0, 0)

Method: copy
	0 new (0, 0)
	1 org/apache/commons/math3/util/ResizableDoubleArray (0, 0)
	3 dup (0, 0)
	4 invokespecial (0, 0)
	5 org/apache/commons/math3/util/ResizableDoubleArray.<init>:()V (0, 0)
	7 astore_1 (0, 0)
	8 aload_0 (0, 0)
	9 aload_1 (0, 0)
	10 invokestatic (0, 0)
	11 org/apache/commons/math3/util/ResizableDoubleArray.copy:(Lorg/apache/commons/math3/util/ResizableDoubleArray;Lorg/apache/commons/math3/util/ResizableDoubleArray;)V (0, 0)
	13 aload_1 (0, 0)
	14 areturn (0, 0)

Method: equals
	0 aload_1 (1, 1)
	1 aload_0 (1, 1)
	2 if_acmpne (1, 1)
	3 5 (1, 1)
	5 iconst_1 (1, 1)
	6 ireturn (1, 1)
	7 aload_1 (1, 1)
	8 instanceof (1, 1)
	9 org/apache/commons/math3/util/ResizableDoubleArray (1, 1)
	11 ifne (1, 1)
	12 5 (1, 1)
	14 iconst_0 (1, 1)
	15 ireturn (1, 1)
	16 aload_0 (0, 0)
	17 dup (0, 0)
	18 astore_2 (0, 0)
	19 monitorenter (0, 0)
	20 aload_1 (0, 0)
	21 dup (0, 0)
	22 astore_3 (0, 0)
	23 monitorenter (0, 0)
	24 iconst_1 (0, 0)
	25 istore (0, 0)
	26 #4 (0, 0)
	27 aload_1 (0, 0)
	28 checkcast (0, 0)
	29 org/apache/commons/math3/util/ResizableDoubleArray (0, 0)
	31 astore (0, 0)
	32 #5 (0, 0)
	33 iload (0, 0)
	34 #4 (0, 0)
	35 ifeq (0, 0)
	36 20 (0, 0)
	38 aload (0, 0)
	39 #5 (0, 0)
	40 getfield (0, 0)
	41 org/apache/commons/math3/util/ResizableDoubleArray.contractionCriterion:D (0, 0)
	43 aload_0 (0, 0)
	44 getfield (0, 0)
	45 org/apache/commons/math3/util/ResizableDoubleArray.contractionCriterion:D (0, 0)
	47 dcmpl (0, 0)
	48 ifne (0, 0)
	49 7 (0, 0)
	51 iconst_1 (0, 0)
	52 goto (0, 0)
	53 4 (0, 0)
	55 iconst_0 (0, 0)
	56 istore (0, 0)
	57 #4 (0, 0)
	58 iload (0, 0)
	59 #4 (0, 0)
	60 ifeq (0, 0)
	61 20 (0, 0)
	63 aload (0, 0)
	64 #5 (0, 0)
	65 getfield (0, 0)
	66 org/apache/commons/math3/util/ResizableDoubleArray.expansionFactor:D (0, 0)
	68 aload_0 (0, 0)
	69 getfield (0, 0)
	70 org/apache/commons/math3/util/ResizableDoubleArray.expansionFactor:D (0, 0)
	72 dcmpl (0, 0)
	73 ifne (0, 0)
	74 7 (0, 0)
	76 iconst_1 (0, 0)
	77 goto (0, 0)
	78 4 (0, 0)
	80 iconst_0 (0, 0)
	81 istore (0, 0)
	82 #4 (0, 0)
	83 iload (0, 0)
	84 #4 (0, 0)
	85 ifeq (0, 0)
	86 19 (0, 0)
	88 aload (0, 0)
	89 #5 (0, 0)
	90 getfield (0, 0)
	91 org/apache/commons/math3/util/ResizableDoubleArray.expansionMode:Lorg/apache/commons/math3/util/ResizableDoubleArray$ExpansionMode; (0, 0)
	93 aload_0 (0, 0)
	94 getfield (0, 0)
	95 org/apache/commons/math3/util/ResizableDoubleArray.expansionMode:Lorg/apache/commons/math3/util/ResizableDoubleArray$ExpansionMode; (0, 0)
	97 if_acmpne (0, 0)
	98 7 (0, 0)
	100 iconst_1 (0, 0)
	101 goto (0, 0)
	102 4 (0, 0)
	104 iconst_0 (0, 0)
	105 istore (0, 0)
	106 #4 (0, 0)
	107 iload (0, 0)
	108 #4 (0, 0)
	109 ifeq (0, 0)
	110 19 (0, 0)
	112 aload (0, 0)
	113 #5 (0, 0)
	114 getfield (0, 0)
	115 org/apache/commons/math3/util/ResizableDoubleArray.numElements:I (0, 0)
	117 aload_0 (0, 0)
	118 getfield (0, 0)
	119 org/apache/commons/math3/util/ResizableDoubleArray.numElements:I (0, 0)
	121 if_icmpne (0, 0)
	122 7 (0, 0)
	124 iconst_1 (0, 0)
	125 goto (0, 0)
	126 4 (0, 0)
	128 iconst_0 (0, 0)
	129 istore (0, 0)
	130 #4 (0, 0)
	131 iload (0, 0)
	132 #4 (0, 0)
	133 ifeq (0, 0)
	134 19 (0, 0)
	136 aload (0, 0)
	137 #5 (0, 0)
	138 getfield (0, 0)
	139 org/apache/commons/math3/util/ResizableDoubleArray.startIndex:I (0, 0)
	141 aload_0 (0, 0)
	142 getfield (0, 0)
	143 org/apache/commons/math3/util/ResizableDoubleArray.startIndex:I (0, 0)
	145 if_icmpne (0, 0)
	146 7 (0, 0)
	148 iconst_1 (0, 0)
	149 goto (0, 0)
	150 4 (0, 0)
	152 iconst_0 (0, 0)
	153 istore (0, 0)
	154 #4 (0, 0)
	155 iload (3, 1)
	156 #4 (3, 1)
	157 ifne (3, 1)
	158 9 (3, 1)
	160 iconst_0 (3, 1)
	161 aload_3 (3, 1)
	162 monitorexit (3, 1)
	163 aload_2 (3, 1)
	164 monitorexit (3, 1)
	165 ireturn (3, 1)
	166 aload_0 (3, 2)
	167 getfield (3, 2)
	168 org/apache/commons/math3/util/ResizableDoubleArray.internalArray:[D (3, 2)
	170 aload (3, 2)
	171 #5 (3, 2)
	172 getfield (3, 2)
	173 org/apache/commons/math3/util/ResizableDoubleArray.internalArray:[D (3, 2)
	175 invokestatic (3, 2)
	176 java/util/Arrays.equals:([D[D)Z (3, 2)
	178 aload_3 (3, 2)
	179 monitorexit (3, 2)
	180 aload_2 (3, 2)
	181 monitorexit (3, 2)
	182 ireturn (3, 2)
	183 astore (0, 0)
	184 #6 (0, 0)
	185 aload_3 (0, 0)
	186 monitorexit (0, 0)
	187 aload (0, 0)
	188 #6 (0, 0)
	189 athrow (0, 0)
	190 astore (0, 0)
	191 #7 (0, 0)
	192 aload_2 (0, 0)
	193 monitorexit (0, 0)
	194 aload (0, 0)
	195 #7 (0, 0)
	196 athrow (0, 0)

Method: hashCode
	0 bipush (0, 0)
	1 6 (0, 0)
	2 newarray (0, 0)
	3 10 (0, 0)
	4 astore_1 (0, 0)
	5 aload_1 (0, 0)
	6 iconst_0 (0, 0)
	7 aload_0 (0, 0)
	8 getfield (0, 0)
	9 org/apache/commons/math3/util/ResizableDoubleArray.expansionFactor:D (0, 0)
	11 invokestatic (0, 0)
	12 java/lang/Double.valueOf:(D)Ljava/lang/Double; (0, 0)
	14 invokevirtual (0, 0)
	15 java/lang/Double.hashCode:()I (0, 0)
	17 iastore (0, 0)
	18 aload_1 (0, 0)
	19 iconst_1 (0, 0)
	20 aload_0 (0, 0)
	21 getfield (0, 0)
	22 org/apache/commons/math3/util/ResizableDoubleArray.contractionCriterion:D (0, 0)
	24 invokestatic (0, 0)
	25 java/lang/Double.valueOf:(D)Ljava/lang/Double; (0, 0)
	27 invokevirtual (0, 0)
	28 java/lang/Double.hashCode:()I (0, 0)
	30 iastore (0, 0)
	31 aload_1 (0, 0)
	32 iconst_2 (0, 0)
	33 aload_0 (0, 0)
	34 getfield (0, 0)
	35 org/apache/commons/math3/util/ResizableDoubleArray.expansionMode:Lorg/apache/commons/math3/util/ResizableDoubleArray$ExpansionMode; (0, 0)
	37 invokevirtual (0, 0)
	38 org/apache/commons/math3/util/ResizableDoubleArray$ExpansionMode.hashCode:()I (0, 0)
	40 iastore (0, 0)
	41 aload_1 (0, 0)
	42 iconst_3 (0, 0)
	43 aload_0 (0, 0)
	44 getfield (0, 0)
	45 org/apache/commons/math3/util/ResizableDoubleArray.internalArray:[D (0, 0)
	47 invokestatic (0, 0)
	48 java/util/Arrays.hashCode:([D)I (0, 0)
	50 iastore (0, 0)
	51 aload_1 (0, 0)
	52 iconst_4 (0, 0)
	53 aload_0 (0, 0)
	54 getfield (0, 0)
	55 org/apache/commons/math3/util/ResizableDoubleArray.numElements:I (0, 0)
	57 iastore (0, 0)
	58 aload_1 (0, 0)
	59 iconst_5 (0, 0)
	60 aload_0 (0, 0)
	61 getfield (0, 0)
	62 org/apache/commons/math3/util/ResizableDoubleArray.startIndex:I (0, 0)
	64 iastore (0, 0)
	65 aload_1 (0, 0)
	66 invokestatic (0, 0)
	67 java/util/Arrays.hashCode:([I)I (0, 0)
	69 ireturn (0, 0)

