Method: <init>
	0 aload_0 (1, 4)
	1 invokespecial (1, 4)
	2 java/lang/Object.<init>:()V (1, 4)
	4 aload_0 (1, 4)
	5 aconst_null (1, 4)
	6 putfield (1, 4)
	7 org/apache/commons/math3/util/TransformerMap.defaultTransformer:Lorg/apache/commons/math3/util/NumberTransformer; (1, 4)
	9 aload_0 (2, 4)
	10 aconst_null (2, 4)
	11 putfield (2, 4)
	12 org/apache/commons/math3/util/TransformerMap.map:Ljava/util/Map; (2, 4)
	14 aload_0 (5, 4)
	15 new (5, 4)
	16 java/util/HashMap (5, 4)
	18 dup (5, 4)
	19 invokespecial (5, 4)
	20 java/util/HashMap.<init>:()V (5, 4)
	22 putfield (5, 4)
	23 org/apache/commons/math3/util/TransformerMap.map:Ljava/util/Map; (5, 4)
	25 aload_0 (6, 4)
	26 new (6, 4)
	27 org/apache/commons/math3/util/DefaultTransformer (6, 4)
	29 dup (6, 4)
	30 invokespecial (6, 4)
	31 org/apache/commons/math3/util/DefaultTransformer.<init>:()V (6, 4)
	33 putfield (6, 4)
	34 org/apache/commons/math3/util/TransformerMap.defaultTransformer:Lorg/apache/commons/math3/util/NumberTransformer; (6, 4)
	36 return (1, 4)

Method: containsClass
	0 aload_0 (0, 0)
	1 getfield (0, 0)
	2 org/apache/commons/math3/util/TransformerMap.map:Ljava/util/Map; (0, 0)
	4 aload_1 (0, 0)
	5 invokeinterface (0, 0)
	6 java/util/Map.containsValue:(Ljava/lang/Object;)Z (0, 0)
	8 0 (0, 0)
	10 ireturn (0, 0)

Method: containsTransformer
	0 aload_0 (0, 0)
	1 getfield (0, 0)
	2 org/apache/commons/math3/util/TransformerMap.map:Ljava/util/Map; (0, 0)
	4 aload_1 (0, 0)
	5 invokeinterface (0, 0)
	6 java/util/Map.get:(Ljava/lang/Object;)Ljava/lang/Object; (0, 0)
	8 0 (0, 0)
	10 ireturn (0, 0)

Method: getTransformer
	0 aload_0 (0, 0)
	1 getfield (0, 0)
	2 org/apache/commons/math3/util/TransformerMap.map:Ljava/util/Map; (0, 0)
	4 aload_1 (0, 0)
	5 invokeinterface (0, 0)
	6 java/util/Map.org/apache/commons/math3/util/NumberTransformer (0, 0)
	8 0 (0, 0)
	10 checkcast (0, 0)
	11 org/apache/commons/math3/util/NumberTransformer (0, 0)
	13 areturn (0, 0)

Method: putTransformer
	0 aload_0 (1, 4)
	1 getfield (1, 4)
	2 org/apache/commons/math3/util/TransformerMap.map:Ljava/util/Map; (1, 4)
	4 aload_1 (1, 4)
	5 aload_2 (1, 4)
	6 invokeinterface (1, 4)
	7 java/util/Map.remove:(Ljava/lang/Object;)Ljava/lang/Object; (1, 4)
	9 0 (1, 4)
	11 checkcast (1, 4)
	12 org/apache/commons/math3/util/NumberTransformer (1, 4)
	14 areturn (0, 4)

Method: removeTransformer
	0 aload_0 (0, 0)
	1 getfield (0, 0)
	2 org/apache/commons/math3/util/TransformerMap.map:Ljava/util/Map; (0, 0)
	4 aload_1 (0, 0)
	5 invokeinterface (0, 0)
	6 java/util/Map.clear:()V (0, 0)
	8 0 (0, 0)
	10 checkcast (0, 0)
	11 org/apache/commons/math3/util/NumberTransformer (0, 0)
	13 areturn (0, 0)

Method: clear
	0 aload_0 (0, 0)
	1 getfield (0, 0)
	2 org/apache/commons/math3/util/TransformerMap.map:Ljava/util/Map; (0, 0)
	4 invokeinterface (0, 0)
	5 java/util/Map.keySet:()Ljava/util/Set; (0, 0)
	7 0 (0, 0)
	9 return (0, 0)

Method: classes
	0 aload_0 (0, 0)
	1 getfield (0, 0)
	2 org/apache/commons/math3/util/TransformerMap.map:Ljava/util/Map; (0, 0)
	4 invokeinterface (0, 0)
	5 java/util/Map.values:()Ljava/util/Collection; (0, 0)
	7 0 (0, 0)
	9 areturn (0, 0)

Method: transformers
	0 aload_0 (0, 0)
	1 getfield (0, 0)
	2 org/apache/commons/math3/util/TransformerMap.map:Ljava/util/Map; (0, 0)
	4 invokeinterface (0, 0)
	5 java/util/Map.java/lang/Double (0, 0)
	7 0 (0, 0)
	9 areturn (0, 0)

Method: transform
	0 ldc2_w (0, 0)
	1 nan (0, 0)
	3 dstore_2 (0, 0)
	4 aload_1 (1, 1)
	5 instanceof (1, 1)
	6 java/lang/Number (1, 1)
	8 ifne (1, 1)
	9 10 (1, 1)
	11 aload_1 (1, 1)
	12 instanceof (1, 1)
	13 java/lang/String (1, 1)
	15 ifeq (1, 1)
	16 17 (1, 1)
	18 aload_0 (2, 4)
	19 getfield (2, 4)
	20 org/apache/commons/math3/util/TransformerMap.defaultTransformer:Lorg/apache/commons/math3/util/NumberTransformer; (2, 4)
	22 aload_1 (2, 4)
	23 invokeinterface (2, 4)
	24 org/apache/commons/math3/util/NumberTransformer.getClass:()Ljava/lang/Class; (2, 4)
	26 0 (2, 4)
	28 dstore_2 (2, 4)
	29 goto (2, 4)
	30 27 (2, 4)
	32 aload_0 (4, 4)
	33 aload_1 (4, 4)
	34 invokevirtual (4, 4)
	35 java/lang/Object.getClass:()Ljava/lang/Class; (4, 4)
	37 invokevirtual (4, 4)
	38 org/apache/commons/math3/util/TransformerMap.getTransformer:(Ljava/lang/Class;)Lorg/apache/commons/math3/util/NumberTransformer; (4, 4)
	40 astore (4, 4)
	41 #4 (4, 4)
	42 aload (5, 1)
	43 #4 (5, 1)
	44 ifnull (5, 1)
	45 12 (5, 1)
	47 aload (6, 4)
	48 #4 (6, 4)
	49 aload_1 (6, 4)
	50 invokeinterface (6, 4)
	51 org/apache/commons/math3/util/NumberTransformer.getClass:()Ljava/lang/Class; (6, 4)
	53 0 (6, 4)
	55 dstore_2 (6, 4)
	56 dload_2 (0, 0)
	57 dreturn (0, 0)

Method: equals
	0 aload_0 (1, 1)
	1 aload_1 (1, 1)
	2 if_acmpne (1, 1)
	3 5 (1, 1)
	5 iconst_1 (1, 1)
	6 ireturn (1, 1)
	7 aload_1 (1, 1)
	8 instanceof (1, 1)
	9 org/apache/commons/math3/util/TransformerMap (1, 1)
	11 ifeq (1, 1)
	12 121 (1, 1)
	14 aload_1 (2, 4)
	15 checkcast (2, 4)
	16 org/apache/commons/math3/util/TransformerMap (2, 4)
	18 astore_2 (2, 4)
	19 aload_0 (3, 1)
	20 getfield (3, 1)
	21 org/apache/commons/math3/util/TransformerMap.defaultTransformer:Lorg/apache/commons/math3/util/NumberTransformer; (3, 1)
	23 aload_2 (3, 1)
	24 getfield (3, 1)
	25 org/apache/commons/math3/util/TransformerMap.defaultTransformer:Lorg/apache/commons/math3/util/NumberTransformer; (3, 1)
	27 invokevirtual (3, 1)
	28 java/lang/Object.equals:(Ljava/lang/Object;)Z (3, 1)
	30 ifne (3, 1)
	31 5 (3, 1)
	33 iconst_0 (3, 1)
	34 ireturn (3, 1)
	35 aload_0 (3, 1)
	36 getfield (3, 1)
	37 org/apache/commons/math3/util/TransformerMap.map:Ljava/util/Map; (3, 1)
	39 invokeinterface (3, 1)
	40 java/util/Map.entrySet:()Ljava/util/Set; (3, 1)
	42 0 (3, 1)
	44 aload_2 (3, 1)
	45 getfield (3, 1)
	46 org/apache/commons/math3/util/TransformerMap.map:Ljava/util/Map; (3, 1)
	48 invokeinterface (3, 1)
	49 java/util/Map.entrySet:()Ljava/util/Set; (3, 1)
	51 0 (3, 1)
	53 if_icmpeq (3, 1)
	54 5 (3, 1)
	56 iconst_0 (3, 1)
	57 ireturn (3, 1)
	58 aload_0 (3, 4)
	59 getfield (3, 4)
	60 org/apache/commons/math3/util/TransformerMap.map:Ljava/util/Map; (3, 4)
	62 invokeinterface (3, 4)
	63 java/util/Map.java/util/Set (3, 4)
	65 0 (3, 4)
	67 invokeinterface (3, 4)
	68 java/util/Set.java/util/Iterator (3, 4)
	70 0 (3, 4)
	72 astore_3 (3, 4)
	73 aload_3 (3, 4)
	74 invokeinterface (3, 4)
	75 java/util/Iterator.next:()Ljava/lang/Object; (3, 4)
	77 0 (3, 4)
	79 ifeq (3, 4)
	80 51 (3, 4)
	82 aload_3 (3, 4)
	83 invokeinterface (3, 4)
	84 java/util/Iterator.java/util/Map$Entry (3, 4)
	86 0 (3, 4)
	88 checkcast (3, 4)
	89 java/util/Map$Entry (3, 4)
	91 astore (3, 4)
	92 #4 (3, 4)
	93 aload (4, 1)
	94 #4 (4, 1)
	95 invokeinterface (4, 1)
	96 java/util/Map$Entry.getKey:()Ljava/lang/Object; (4, 1)
	98 0 (4, 1)
	100 checkcast (4, 1)
	101 org/apache/commons/math3/util/NumberTransformer (4, 1)
	103 aload_2 (4, 1)
	104 getfield (4, 1)
	105 org/apache/commons/math3/util/TransformerMap.map:Ljava/util/Map; (4, 1)
	107 aload (4, 1)
	108 #4 (4, 1)
	109 invokeinterface (4, 1)
	110 java/util/Map$Entry.hashCode:()I (4, 1)
	112 0 (4, 1)
	114 invokeinterface (4, 1)
	115 java/util/Map.org/apache/commons/math3/util/NumberTransformer (4, 1)
	117 0 (4, 1)
	119 invokevirtual (4, 1)
	120 java/lang/Object.equals:(Ljava/lang/Object;)Z (4, 1)
	122 ifne (4, 1)
	123 5 (4, 1)
	125 iconst_0 (4, 1)
	126 ireturn (4, 1)
	127 goto (2, 4)
	128 -54 (2, 4)
	130 iconst_1 (2, 4)
	131 ireturn (2, 4)
	132 iconst_0 (0, 0)
	133 ireturn (0, 0)

Method: hashCode
	0 aload_0 (1, 4)
	1 getfield (1, 4)
	2 org/apache/commons/math3/util/TransformerMap.defaultTransformer:Lorg/apache/commons/math3/util/NumberTransformer; (1, 4)
	4 invokevirtual (1, 4)
	5 java/lang/Object.hashCode:()I (1, 4)
	7 istore_1 (1, 4)
	8 aload_0 (2, 4)
	9 getfield (2, 4)
	10 org/apache/commons/math3/util/TransformerMap.map:Ljava/util/Map; (2, 4)
	12 invokeinterface (2, 4)
	13 java/util/Map.java/lang/Double (2, 4)
	15 0 (2, 4)
	17 invokeinterface (2, 4)
	18 java/util/Collection.java/util/Iterator (2, 4)
	20 0 (2, 4)
	22 astore_2 (2, 4)
	23 aload_2 (2, 4)
	24 invokeinterface (2, 4)
	25 java/util/Iterator.next:()Ljava/lang/Object; (2, 4)
	27 0 (2, 4)
	29 ifeq (2, 4)
	30 26 (2, 4)
	32 aload_2 (2, 4)
	33 invokeinterface (2, 4)
	34 java/util/Iterator.java/util/Map$Entry (2, 4)
	36 0 (2, 4)
	38 checkcast (2, 4)
	39 org/apache/commons/math3/util/NumberTransformer (2, 4)
	41 astore_3 (2, 4)
	42 iload_1 (2, 4)
	43 bipush (2, 4)
	44 31 (2, 4)
	45 imul (2, 4)
	46 aload_3 (2, 4)
	47 invokevirtual (2, 4)
	48 java/lang/Object.hashCode:()I (2, 4)
	50 iadd (2, 4)
	51 istore_1 (2, 4)
	52 goto (1, 4)
	53 -29 (1, 4)
	55 iload_1 (1, 4)
	56 ireturn (0, 4)

