Method: <init>
	0 aload_0 (1, 4)
	1 invokespecial (1, 4)
	4 aload_0 (1, 4)
	5 aconst_null (1, 4)
	6 putfield (1, 4)
	9 aload_0 (1, 4)
	10 aconst_null (1, 4)
	11 putfield (1, 4)
	14 aload_0 (2, 4)
	15 new (2, 4)
	18 dup (2, 4)
	19 invokespecial (2, 4)
	22 putfield (2, 4)
	25 aload_0 (2, 4)
	26 new (2, 4)
	29 dup (2, 4)
	30 invokespecial (2, 4)
	33 putfield (2, 4)
	36 return (1, 4)

Method: containsClass
	0 aload_0 (0, 0)
	1 getfield (0, 0)
	4 aload_1 (0, 0)
	5 invokeinterface (0, 0)
	10 ireturn (0, 0)

Method: containsTransformer
	0 aload_0 (0, 0)
	1 getfield (0, 0)
	4 aload_1 (0, 0)
	5 invokeinterface (0, 0)
	10 ireturn (0, 0)

Method: getTransformer
	0 aload_0 (0, 0)
	1 getfield (0, 0)
	4 aload_1 (0, 0)
	5 invokeinterface (0, 0)
	10 checkcast (0, 0)
	13 areturn (0, 0)

Method: putTransformer
	0 aload_0 (0, 4)
	1 getfield (0, 4)
	4 aload_1 (0, 4)
	5 aload_2 (0, 4)
	6 invokeinterface (0, 4)
	11 checkcast (0, 4)
	14 areturn (0, 4)

Method: removeTransformer
	0 aload_0 (0, 0)
	1 getfield (0, 0)
	4 aload_1 (0, 0)
	5 invokeinterface (0, 0)
	10 checkcast (0, 0)
	13 areturn (0, 0)

Method: clear
	0 aload_0 (0, 0)
	1 getfield (0, 0)
	4 invokeinterface (0, 0)
	9 return (0, 0)

Method: classes
	0 aload_0 (0, 0)
	1 getfield (0, 0)
	4 invokeinterface (0, 0)
	9 areturn (0, 0)

Method: transformers
	0 aload_0 (0, 0)
	1 getfield (0, 0)
	4 invokeinterface (0, 0)
	9 areturn (0, 0)

Method: transform
	0 ldc2_w (0, 0)
	3 dstore_2 (0, 0)
	4 aload_1 (1, 1)
	5 instanceof (1, 1)
	8 ifne (1, 1)
	11 aload_1 (1, 1)
	12 instanceof (1, 1)
	15 ifeq (1, 1)
	18 aload_0 (1, 4)
	19 getfield (1, 4)
	22 aload_1 (1, 4)
	23 invokeinterface (1, 4)
	28 dstore_2 (1, 4)
	29 goto (1, 4)
	32 aload_0 (1, 4)
	33 aload_1 (1, 4)
	34 invokevirtual (1, 4)
	37 invokevirtual (1, 4)
	40 astore (1, 4)
	42 aload (2, 1)
	44 ifnull (2, 1)
	47 aload (2, 4)
	49 aload_1 (2, 4)
	50 invokeinterface (2, 4)
	55 dstore_2 (2, 4)
	56 dload_2 (0, 4)
	57 dreturn (0, 4)

Method: equals
	0 aload_0 (1, 1)
	1 aload_1 (1, 1)
	2 if_acmpne (1, 1)
	5 iconst_1 (1, 1)
	6 ireturn (1, 1)
	7 aload_1 (1, 1)
	8 instanceof (1, 1)
	11 ifeq (1, 1)
	14 aload_1 (1, 4)
	15 checkcast (1, 4)
	18 astore_2 (1, 4)
	19 aload_0 (2, 1)
	20 getfield (2, 1)
	23 aload_2 (2, 1)
	24 getfield (2, 1)
	27 invokevirtual (2, 1)
	30 ifne (2, 1)
	33 iconst_0 (2, 1)
	34 ireturn (2, 1)
	35 aload_0 (2, 1)
	36 getfield (2, 1)
	39 invokeinterface (2, 1)
	44 aload_2 (2, 1)
	45 getfield (2, 1)
	48 invokeinterface (2, 1)
	53 if_icmpeq (2, 1)
	56 iconst_0 (2, 1)
	57 ireturn (2, 1)
	58 aload_0 (2, 4)
	59 getfield (2, 4)
	62 invokeinterface (2, 4)
	67 invokeinterface (2, 4)
	72 astore_3 (2, 4)
	73 aload_3 (2, 4)
	74 invokeinterface (2, 4)
	79 ifeq (2, 4)
	82 aload_3 (2, 4)
	83 invokeinterface (2, 4)
	88 checkcast (2, 4)
	91 astore (2, 4)
	93 aload (3, 1)
	95 invokeinterface (3, 1)
	100 checkcast (3, 1)
	103 aload_2 (3, 1)
	104 getfield (3, 1)
	107 aload (3, 1)
	109 invokeinterface (3, 1)
	114 invokeinterface (3, 1)
	119 invokevirtual (3, 1)
	122 ifne (3, 1)
	125 iconst_0 (3, 1)
	126 ireturn (3, 1)
	127 goto (1, 4)
	130 iconst_1 (1, 4)
	131 ireturn (1, 4)
	132 iconst_0 (0, 1)
	133 ireturn (0, 1)

Method: hashCode
	0 aload_0 (0, 4)
	1 getfield (0, 4)
	4 invokevirtual (0, 4)
	7 istore_1 (0, 4)
	8 aload_0 (1, 4)
	9 getfield (1, 4)
	12 invokeinterface (1, 4)
	17 invokeinterface (1, 4)
	22 astore_2 (1, 4)
	23 aload_2 (1, 4)
	24 invokeinterface (1, 4)
	29 ifeq (1, 4)
	32 aload_2 (1, 4)
	33 invokeinterface (1, 4)
	38 checkcast (1, 4)
	41 astore_3 (1, 4)
	42 iload_1 (1, 4)
	43 bipush (1, 4)
	45 imul (1, 4)
	46 aload_3 (1, 4)
	47 invokevirtual (1, 4)
	50 iadd (1, 4)
	51 istore_1 (1, 4)
	52 goto (0, 4)
	55 iload_1 (0, 4)
	56 ireturn (0, 4)

