Method: <init>
	0 aload_0 (0, 0)
	1 invokespecial (0, 0)
	2 java/lang/Object.<init>:()V (0, 0)
	4 aload_0 (0, 0)
	5 dconst_0 (0, 0)
	6 putfield (0, 0)
	7 org/apache/commons/math3/distribution/fitting/MultivariateNormalMixtureExpectationMaximization.logLikelihood:D (0, 0)
	9 aload_1 (4, 1)
	10 arraylength (4, 1)
	11 iconst_1 (4, 1)
	12 if_icmpge (4, 1)
	13 16 (4, 1)
	15 new (4, 1)
	16 org/apache/commons/math3/exception/NotStrictlyPositiveException (4, 1)
	18 dup (4, 1)
	19 aload_1 (4, 1)
	20 arraylength (4, 1)
	21 invokestatic (4, 1)
	22 java/lang/Integer.valueOf:(I)Ljava/lang/Integer; (4, 1)
	24 invokespecial (4, 1)
	25 org/apache/commons/math3/exception/NotStrictlyPositiveException.<init>:(Ljava/lang/Number;)V (4, 1)
	27 athrow (4, 1)
	28 aload_0 (3, 1)
	29 aload_1 (3, 1)
	30 arraylength (3, 1)
	31 aload_1 (3, 1)
	32 iconst_0 (3, 1)
	33 aaload (3, 1)
	34 arraylength (3, 1)
	35 multianewarray (3, 1)
	36 [[D (3, 1)
	38 -75 (3, 1)
	39 putfield (3, 1)
	40 org/apache/commons/math3/distribution/fitting/MultivariateNormalMixtureExpectationMaximization.data:[[D (3, 1)
	42 iconst_0 (4, 4)
	43 istore_2 (4, 4)
	44 iload_2 (4, 4)
	45 aload_1 (4, 4)
	46 arraylength (4, 4)
	47 if_icmpge (4, 4)
	48 83 (4, 4)
	50 aload_1 (5, 1)
	51 iload_2 (5, 1)
	52 aaload (5, 1)
	53 arraylength (5, 1)
	54 aload_1 (5, 1)
	55 iconst_0 (5, 1)
	56 aaload (5, 1)
	57 arraylength (5, 1)
	58 if_icmpeq (5, 1)
	59 19 (5, 1)
	61 new (5, 1)
	62 org/apache/commons/math3/exception/DimensionMismatchException (5, 1)
	64 dup (5, 1)
	65 aload_1 (5, 1)
	66 iload_2 (5, 1)
	67 aaload (5, 1)
	68 arraylength (5, 1)
	69 aload_1 (5, 1)
	70 iconst_0 (5, 1)
	71 aaload (5, 1)
	72 arraylength (5, 1)
	73 invokespecial (5, 1)
	74 org/apache/commons/math3/exception/DimensionMismatchException.<init>:(II)V (5, 1)
	76 athrow (5, 1)
	77 aload_1 (5, 1)
	78 iload_2 (5, 1)
	79 aaload (5, 1)
	80 arraylength (5, 1)
	81 iconst_2 (5, 1)
	82 if_icmpge (5, 1)
	83 26 (5, 1)
	85 new (5, 1)
	86 org/apache/commons/math3/exception/NumberIsTooSmallException (5, 1)
	88 dup (5, 1)
	89 getstatic (5, 1)
	90 org/apache/commons/math3/exception/util/LocalizedFormats.NUMBER_TOO_SMALL:Lorg/apache/commons/math3/exception/util/LocalizedFormats; (5, 1)
	92 aload_1 (5, 1)
	93 iload_2 (5, 1)
	94 aaload (5, 1)
	95 arraylength (5, 1)
	96 invokestatic (5, 1)
	97 java/lang/Integer.valueOf:(I)Ljava/lang/Integer; (5, 1)
	99 iconst_2 (5, 1)
	100 invokestatic (5, 1)
	101 java/lang/Integer.valueOf:(I)Ljava/lang/Integer; (5, 1)
	103 iconst_1 (5, 1)
	104 invokespecial (5, 1)
	105 org/apache/commons/math3/exception/NumberIsTooSmallException.<init>:(Lorg/apache/commons/math3/exception/util/Localizable;Ljava/lang/Number;Ljava/lang/Number;Z)V (5, 1)
	107 athrow (5, 1)
	108 aload_0 (4, 4)
	109 getfield (4, 4)
	110 org/apache/commons/math3/distribution/fitting/MultivariateNormalMixtureExpectationMaximization.data:[[D (4, 4)
	112 iload_2 (4, 4)
	113 aload_1 (4, 4)
	114 iload_2 (4, 4)
	115 aaload (4, 4)
	116 aload_1 (4, 4)
	117 iload_2 (4, 4)
	118 aaload (4, 4)
	119 arraylength (4, 4)
	120 invokestatic (4, 4)
	121 org/apache/commons/math3/util/MathArrays.copyOf:([DI)[D (4, 4)
	123 aastore (4, 4)
	124 iinc (4, 4)
	125 #2 (4, 4)
	126 -89 (4, 4)
	127 goto (4, 4)
	128 -83 (4, 4)
	130 return (1, 1)

Method: fit
	0 aload_0 (0, 0)
	1 aload_1 (0, 0)
	2 sipush (0, 0)
	3 1000 (0, 0)
	5 ldc2_w (0, 0)
	6 1e-05 (0, 0)
	8 invokevirtual (0, 0)
	9 org/apache/commons/math3/distribution/fitting/MultivariateNormalMixtureExpectationMaximization.fit:(Lorg/apache/commons/math3/distribution/MixtureMultivariateNormalDistribution;ID)V (0, 0)
	11 return (0, 0)

Method: estimate
	0 aload_0 (1, 1)
	1 arraylength (1, 1)
	2 iconst_2 (1, 1)
	3 if_icmpge (1, 1)
	4 16 (1, 1)
	6 new (1, 1)
	7 org/apache/commons/math3/exception/NotStrictlyPositiveException (1, 1)
	9 dup (1, 1)
	10 aload_0 (1, 1)
	11 arraylength (1, 1)
	12 invokestatic (1, 1)
	13 java/lang/Integer.valueOf:(I)Ljava/lang/Integer; (1, 1)
	15 invokespecial (1, 1)
	16 org/apache/commons/math3/exception/NotStrictlyPositiveException.<init>:(Ljava/lang/Number;)V (1, 1)
	18 athrow (1, 1)
	19 iload_1 (1, 1)
	20 iconst_2 (1, 1)
	21 if_icmpge (1, 1)
	22 20 (1, 1)
	24 new (1, 1)
	25 org/apache/commons/math3/exception/NumberIsTooSmallException (1, 1)
	27 dup (1, 1)
	28 iload_1 (1, 1)
	29 invokestatic (1, 1)
	30 java/lang/Integer.valueOf:(I)Ljava/lang/Integer; (1, 1)
	32 iconst_2 (1, 1)
	33 invokestatic (1, 1)
	34 java/lang/Integer.valueOf:(I)Ljava/lang/Integer; (1, 1)
	36 iconst_1 (1, 1)
	37 invokespecial (1, 1)
	38 org/apache/commons/math3/exception/NumberIsTooSmallException.<init>:(Ljava/lang/Number;Ljava/lang/Number;Z)V (1, 1)
	40 athrow (1, 1)
	41 iload_1 (1, 1)
	42 aload_0 (1, 1)
	43 arraylength (1, 1)
	44 if_icmple (1, 1)
	45 21 (1, 1)
	47 new (1, 1)
	48 org/apache/commons/math3/exception/NumberIsTooLargeException (1, 1)
	50 dup (1, 1)
	51 iload_1 (1, 1)
	52 invokestatic (1, 1)
	53 java/lang/Integer.valueOf:(I)Ljava/lang/Integer; (1, 1)
	55 aload_0 (1, 1)
	56 arraylength (1, 1)
	57 invokestatic (1, 1)
	58 java/lang/Integer.valueOf:(I)Ljava/lang/Integer; (1, 1)
	60 iconst_1 (1, 1)
	61 invokespecial (1, 1)
	62 org/apache/commons/math3/exception/NumberIsTooLargeException.<init>:(Ljava/lang/Number;Ljava/lang/Number;Z)V (1, 1)
	64 athrow (1, 1)
	65 aload_0 (0, 0)
	66 arraylength (0, 0)
	67 istore_2 (0, 0)
	68 aload_0 (0, 0)
	69 iconst_0 (0, 0)
	70 aaload (0, 0)
	71 arraylength (0, 0)
	72 istore_3 (0, 0)
	73 iload_2 (0, 0)
	74 anewarray (0, 0)
	75 org/apache/commons/math3/distribution/fitting/MultivariateNormalMixtureExpectationMaximization$DataRow (0, 0)
	77 astore (0, 0)
	78 #4 (0, 0)
	79 iconst_0 (1, 4)
	80 istore (1, 4)
	81 #5 (1, 4)
	82 iload (1, 4)
	83 #5 (1, 4)
	84 iload_2 (1, 4)
	85 if_icmpge (1, 4)
	86 25 (1, 4)
	88 aload (1, 4)
	89 #4 (1, 4)
	90 iload (1, 4)
	91 #5 (1, 4)
	92 new (1, 4)
	93 org/apache/commons/math3/distribution/fitting/MultivariateNormalMixtureExpectationMaximization$DataRow (1, 4)
	95 dup (1, 4)
	96 aload_0 (1, 4)
	97 iload (1, 4)
	98 #5 (1, 4)
	99 aaload (1, 4)
	100 invokespecial (1, 4)
	101 org/apache/commons/math3/distribution/fitting/MultivariateNormalMixtureExpectationMaximization$DataRow.<init>:([D)V (1, 4)
	103 aastore (1, 4)
	104 iinc (1, 4)
	105 #5 (1, 4)
	106 -89 (1, 4)
	107 goto (1, 4)
	108 -25 (1, 4)
	110 aload (0, 0)
	111 #4 (0, 0)
	112 invokestatic (0, 0)
	113 java/util/Arrays.sort:([Ljava/lang/Object;)V (0, 0)
	115 dconst_1 (1, 1)
	116 iload_1 (1, 1)
	117 i2d (1, 1)
	118 ddiv (1, 1)
	119 dstore (1, 1)
	120 #5 (1, 1)
	121 new (1, 1)
	122 java/util/ArrayList (1, 1)
	124 dup (1, 1)
	125 iload_1 (1, 1)
	126 invokespecial (1, 1)
	127 java/util/ArrayList.<init>:(I)V (1, 1)
	129 astore (1, 1)
	130 #7 (1, 1)
	131 iconst_0 (2, 4)
	132 istore (2, 4)
	133 #8 (2, 4)
	134 iload (2, 4)
	135 #8 (2, 4)
	136 iload_1 (2, 4)
	137 if_icmpge (2, 4)
	138 183 (2, 4)
	140 iload (3, 4)
	141 #8 (3, 4)
	142 iload_2 (3, 4)
	143 imul (3, 4)
	144 iload_1 (3, 4)
	145 idiv (3, 4)
	146 istore (3, 4)
	147 #9 (3, 4)
	148 iload (4, 4)
	149 #8 (4, 4)
	150 iconst_1 (4, 4)
	151 iadd (4, 4)
	152 iload_2 (4, 4)
	153 imul (4, 4)
	154 iload_1 (4, 4)
	155 idiv (4, 4)
	156 istore (4, 4)
	157 #10 (4, 4)
	158 iload (4, 4)
	159 #10 (4, 4)
	160 iload (4, 4)
	161 #9 (4, 4)
	162 isub (4, 4)
	163 istore (4, 4)
	164 #11 (4, 4)
	165 iload (5, 4)
	166 #11 (5, 4)
	167 iload_3 (5, 4)
	168 multianewarray (5, 4)
	169 [[D (5, 4)
	171 58 (5, 4)
	172 astore (5, 4)
	173 #12 (5, 4)
	174 iload_3 (6, 4)
	175 newarray (6, 4)
	176 7 (6, 4)
	177 astore (6, 4)
	178 #13 (6, 4)
	179 iload (7, 4)
	180 #9 (7, 4)
	181 istore (7, 4)
	182 #14 (7, 4)
	183 iconst_0 (7, 4)
	184 istore (7, 4)
	185 #15 (7, 4)
	186 iload (7, 4)
	187 #14 (7, 4)
	188 iload (7, 4)
	189 #10 (7, 4)
	190 if_icmpge (7, 4)
	191 60 (7, 4)
	193 iconst_0 (8, 4)
	194 istore (8, 4)
	195 #16 (8, 4)
	196 iload (8, 4)
	197 #16 (8, 4)
	198 iload_3 (8, 4)
	199 if_icmpge (8, 4)
	200 42 (8, 4)
	202 aload (8, 4)
	203 #4 (8, 4)
	204 iload (8, 4)
	205 #14 (8, 4)
	206 aaload (8, 4)
	207 invokevirtual (8, 4)
	208 org/apache/commons/math3/distribution/fitting/MultivariateNormalMixtureExpectationMaximization$DataRow.getRow:()[D (8, 4)
	210 iload (8, 4)
	211 #16 (8, 4)
	212 daload (8, 4)
	213 dstore (8, 4)
	214 #17 (8, 4)
	215 aload (8, 4)
	216 #13 (8, 4)
	217 iload (8, 4)
	218 #16 (8, 4)
	219 dup2 (8, 4)
	220 daload (8, 4)
	221 dload (8, 4)
	222 #17 (8, 4)
	223 dadd (8, 4)
	224 dastore (8, 4)
	225 aload (8, 4)
	226 #12 (8, 4)
	227 iload (8, 4)
	228 #15 (8, 4)
	229 aaload (8, 4)
	230 iload (8, 4)
	231 #16 (8, 4)
	232 dload (8, 4)
	233 #17 (8, 4)
	234 dastore (8, 4)
	235 iinc (8, 4)
	236 #16 (8, 4)
	237 -89 (8, 4)
	238 goto (8, 4)
	239 -42 (8, 4)
	241 iinc (8, 4)
	242 #14 (8, 4)
	243 -124 (8, 4)
	244 iinc (8, 4)
	245 #15 (8, 4)
	246 -89 (8, 4)
	247 goto (8, 4)
	248 -61 (8, 4)
	250 dconst_1 (7, 4)
	251 iload (7, 4)
	252 #11 (7, 4)
	253 i2d (7, 4)
	254 ddiv (7, 4)
	255 aload (7, 4)
	256 #13 (7, 4)
	257 invokestatic (7, 4)
	258 org/apache/commons/math3/util/MathArrays.scaleInPlace:(D[D)V (7, 4)
	260 new (8, 4)
	261 org/apache/commons/math3/stat/correlation/Covariance (8, 4)
	263 dup (8, 4)
	264 aload (8, 4)
	265 #12 (8, 4)
	266 invokespecial (8, 4)
	267 org/apache/commons/math3/stat/correlation/Covariance.<init>:([[D)V (8, 4)
	269 invokevirtual (8, 4)
	270 org/apache/commons/math3/stat/correlation/Covariance.getCovarianceMatrix:()Lorg/apache/commons/math3/linear/RealMatrix; (8, 4)
	272 invokeinterface (8, 4)
	273 org/apache/commons/math3/linear/RealMatrix.<init>:([D[[D[[[D)V (8, 4)
	275 0 (8, 4)
	277 astore (8, 4)
	278 #14 (8, 4)
	279 new (8, 4)
	280 org/apache/commons/math3/distribution/MultivariateNormalDistribution (8, 4)
	282 dup (8, 4)
	283 aload (8, 4)
	284 #13 (8, 4)
	285 aload (8, 4)
	286 #14 (8, 4)
	287 invokespecial (8, 4)
	288 org/apache/commons/math3/distribution/MultivariateNormalDistribution.<init>:([D[[D)V (8, 4)
	290 astore (8, 4)
	291 #15 (8, 4)
	292 aload (8, 4)
	293 #7 (8, 4)
	294 new (8, 4)
	295 org/apache/commons/math3/util/Pair (8, 4)
	297 dup (8, 4)
	298 dload (8, 4)
	299 #5 (8, 4)
	300 invokestatic (8, 4)
	301 java/lang/Double.valueOf:(D)Ljava/lang/Double; (8, 4)
	303 aload (8, 4)
	304 #15 (8, 4)
	305 invokespecial (8, 4)
	306 org/apache/commons/math3/util/Pair.<init>:(Ljava/lang/Object;Ljava/lang/Object;)V (8, 4)
	308 invokeinterface (8, 4)
	309 java/util/List.java/lang/Object (8, 4)
	311 0 (8, 4)
	313 pop (8, 4)
	314 iinc (8, 4)
	315 #8 (8, 4)
	316 -89 (8, 4)
	317 goto (8, 4)
	318 -183 (8, 4)
	320 new (6, 4)
	321 org/apache/commons/math3/distribution/MixtureMultivariateNormalDistribution (6, 4)
	323 dup (6, 4)
	324 aload (6, 4)
	325 #7 (6, 4)
	326 invokespecial (6, 4)
	327 org/apache/commons/math3/distribution/MixtureMultivariateNormalDistribution.<init>:(Ljava/util/List;)V (6, 4)
	329 areturn (1, 4)

Method: getLogLikelihood
	0 aload_0 (0, 0)
	1 getfield (0, 0)
	2 org/apache/commons/math3/distribution/fitting/MultivariateNormalMixtureExpectationMaximization.logLikelihood:D (0, 0)
	4 dreturn (0, 0)

Method: getFittedModel
	0 new (0, 0)
	1 org/apache/commons/math3/distribution/MixtureMultivariateNormalDistribution (0, 0)
	3 dup (0, 0)
	4 aload_0 (0, 0)
	5 getfield (0, 0)
	6 org/apache/commons/math3/distribution/fitting/MultivariateNormalMixtureExpectationMaximization.fittedModel:Lorg/apache/commons/math3/distribution/MixtureMultivariateNormalDistribution; (0, 0)
	8 invokevirtual (0, 0)
	9 org/apache/commons/math3/distribution/MixtureMultivariateNormalDistribution.getComponents:()Ljava/util/List; (0, 0)
	11 invokespecial (0, 0)
	12 org/apache/commons/math3/distribution/MixtureMultivariateNormalDistribution.<init>:(Ljava/util/List;)V (0, 0)
	14 areturn (0, 0)

