Method: <init>
	0 aload_0 (0, 0)
	1 invokespecial (0, 0)
	4 aload_0 (0, 0)
	5 aload_1 (0, 0)
	6 putfield (0, 0)
	9 aload_0 (0, 0)
	10 dconst_0 (0, 0)
	11 invokestatic (0, 0)
	14 putfield (0, 0)
	17 iconst_0 (1, 4)
	18 istore_2 (1, 4)
	19 iload_2 (1, 4)
	20 aload_1 (1, 4)
	21 arraylength (1, 4)
	22 if_icmpge (1, 4)
	25 aload_0 (1, 4)
	26 aload_0 (1, 4)
	27 getfield (1, 4)
	30 invokevirtual (1, 4)
	33 aload_1 (1, 4)
	34 iload_2 (1, 4)
	35 daload (1, 4)
	36 dadd (1, 4)
	37 invokestatic (1, 4)
	40 putfield (1, 4)
	43 iinc (1, 4)
	46 goto (1, 4)
	49 aload_0 (0, 0)
	50 aload_0 (0, 0)
	51 getfield (0, 0)
	54 invokevirtual (0, 0)
	57 aload_1 (0, 0)
	58 arraylength (0, 0)
	59 i2d (0, 0)
	60 ddiv (0, 0)
	61 invokestatic (0, 0)
	64 putfield (0, 0)
	67 return (0, 0)

Method: compareTo
	0 aload_0 (0, 0)
	1 aload_1 (0, 0)
	2 checkcast (0, 0)
	5 invokevirtual (0, 0)
	8 ireturn (0, 0)

Method: equals
	0 aload_0 (1, 1)
	1 aload_1 (1, 1)
	2 if_acmpne (1, 1)
	5 iconst_1 (1, 1)
	6 ireturn (1, 1)
	7 aload_1 (1, 1)
	8 instanceof (1, 1)
	11 ifeq (1, 1)
	14 aload_0 (1, 1)
	15 getfield (1, 1)
	18 aload_1 (1, 1)
	19 checkcast (1, 1)
	22 getfield (1, 1)
	25 invokestatic (1, 1)
	28 ireturn (1, 1)
	29 iconst_0 (0, 0)
	30 ireturn (0, 0)

Method: hashCode
	0 aload_0 (0, 0)
	1 getfield (0, 0)
	4 invokestatic (0, 0)
	7 ireturn (0, 0)

Method: getRow
	0 aload_0 (0, 0)
	1 getfield (0, 0)
	4 areturn (0, 0)

