Method: <init>
	0 aload_0 (0, 0)
	1 invokespecial (0, 0)
	2 java/lang/Object.<init>:()V (0, 0)
	4 dload_1 (1, 1)
	5 dconst_0 (1, 1)
	6 dcmpg (1, 1)
	7 ifgt (1, 1)
	8 15 (1, 1)
	10 new (1, 1)
	11 org/apache/commons/math3/exception/NotStrictlyPositiveException (1, 1)
	13 dup (1, 1)
	14 dload_1 (1, 1)
	15 invokestatic (1, 1)
	16 java/lang/Double.valueOf:(D)Ljava/lang/Double; (1, 1)
	18 invokespecial (1, 1)
	19 org/apache/commons/math3/exception/NotStrictlyPositiveException.<init>:(Ljava/lang/Number;)V (1, 1)
	21 athrow (1, 1)
	22 iload_3 (1, 1)
	23 ifgt (1, 1)
	24 15 (1, 1)
	26 new (1, 1)
	27 org/apache/commons/math3/exception/NotStrictlyPositiveException (1, 1)
	29 dup (1, 1)
	30 iload_3 (1, 1)
	31 invokestatic (1, 1)
	32 java/lang/Integer.valueOf:(I)Ljava/lang/Integer; (1, 1)
	34 invokespecial (1, 1)
	35 org/apache/commons/math3/exception/NotStrictlyPositiveException.<init>:(Ljava/lang/Number;)V (1, 1)
	37 athrow (1, 1)
	38 aload_0 (0, 0)
	39 dload_1 (0, 0)
	40 putfield (0, 0)
	41 org/apache/commons/math3/optim/univariate/BracketFinder.growLimit:D (0, 0)
	43 aload_0 (0, 0)
	44 invokestatic (0, 0)
	45 org/apache/commons/math3/util/IntegerSequence$Incrementor.create:()Lorg/apache/commons/math3/util/IntegerSequence$Incrementor; (0, 0)
	47 iload_3 (0, 0)
	48 invokevirtual (0, 0)
	49 org/apache/commons/math3/util/IntegerSequence$Incrementor.withMaximalCount:(I)Lorg/apache/commons/math3/util/IntegerSequence$Incrementor; (0, 0)
	51 putfield (0, 0)
	52 org/apache/commons/math3/optim/univariate/BracketFinder.evaluations:Lorg/apache/commons/math3/util/IntegerSequence$Incrementor; (0, 0)
	54 return (0, 0)

Method: search
	0 aload_0 (0, 0)
	1 aload_0 (0, 0)
	2 getfield (0, 0)
	3 org/apache/commons/math3/optim/univariate/BracketFinder.evaluations:Lorg/apache/commons/math3/util/IntegerSequence$Incrementor; (0, 0)
	5 iconst_0 (0, 0)
	6 invokevirtual (0, 0)
	7 org/apache/commons/math3/util/IntegerSequence$Incrementor.withStart:(I)Lorg/apache/commons/math3/util/IntegerSequence$Incrementor; (0, 0)
	9 putfield (0, 0)
	10 org/apache/commons/math3/optim/univariate/BracketFinder.evaluations:Lorg/apache/commons/math3/util/IntegerSequence$Incrementor; (0, 0)
	12 aload_2 (0, 0)
	13 getstatic (0, 0)
	14 org/apache/commons/math3/optim/nonlinear/scalar/GoalType.MINIMIZE:Lorg/apache/commons/math3/optim/nonlinear/scalar/GoalType; (0, 0)
	16 if_acmpne (0, 0)
	17 7 (0, 0)
	19 iconst_1 (0, 0)
	20 goto (0, 0)
	21 4 (0, 0)
	23 iconst_0 (0, 0)
	24 istore (0, 0)
	25 #7 (0, 0)
	26 aload_0 (0, 0)
	27 aload_1 (0, 0)
	28 dload_3 (0, 0)
	29 invokespecial (0, 0)
	30 org/apache/commons/math3/optim/univariate/BracketFinder.eval:(Lorg/apache/commons/math3/analysis/UnivariateFunction;D)D (0, 0)
	32 dstore (0, 0)
	33 #8 (0, 0)
	34 aload_0 (0, 0)
	35 aload_1 (0, 0)
	36 dload (0, 0)
	37 #5 (0, 0)
	38 invokespecial (0, 0)
	39 org/apache/commons/math3/optim/univariate/BracketFinder.eval:(Lorg/apache/commons/math3/analysis/UnivariateFunction;D)D (0, 0)
	41 dstore (0, 0)
	42 #10 (0, 0)
	43 iload (1, 1)
	44 #7 (1, 1)
	45 ifeq (1, 1)
	46 14 (1, 1)
	48 dload (1, 1)
	49 #8 (1, 1)
	50 dload (1, 1)
	51 #10 (1, 1)
	52 dcmpg (1, 1)
	53 ifge (1, 1)
	54 36 (1, 1)
	56 goto (1, 1)
	57 11 (1, 1)
	59 dload (1, 1)
	60 #8 (1, 1)
	61 dload (1, 1)
	62 #10 (1, 1)
	63 dcmpl (1, 1)
	64 ifle (1, 1)
	65 25 (1, 1)
	67 dload_3 (1, 1)
	68 dstore (1, 1)
	69 #12 (1, 1)
	70 dload (1, 1)
	71 #5 (1, 1)
	72 dstore_3 (1, 1)
	73 dload (1, 1)
	74 #12 (1, 1)
	75 dstore (1, 1)
	76 #5 (1, 1)
	77 dload (1, 1)
	78 #8 (1, 1)
	79 dstore (1, 1)
	80 #12 (1, 1)
	81 dload (1, 1)
	82 #10 (1, 1)
	83 dstore (1, 1)
	84 #8 (1, 1)
	85 dload (1, 1)
	86 #12 (1, 1)
	87 dstore (1, 1)
	88 #10 (1, 1)
	89 dload (1, 1)
	90 #5 (1, 1)
	91 ldc2_w (1, 1)
	92 1.618034 (1, 1)
	94 dload (1, 1)
	95 #5 (1, 1)
	96 dload_3 (1, 1)
	97 dsub (1, 1)
	98 dmul (1, 1)
	99 dadd (1, 1)
	100 dstore (1, 1)
	101 #12 (1, 1)
	102 aload_0 (1, 1)
	103 aload_1 (1, 1)
	104 dload (1, 1)
	105 #12 (1, 1)
	106 invokespecial (1, 1)
	107 org/apache/commons/math3/optim/univariate/BracketFinder.eval:(Lorg/apache/commons/math3/analysis/UnivariateFunction;D)D (1, 1)
	109 dstore (1, 1)
	110 #14 (1, 1)
	111 iload (2, 3)
	112 #7 (2, 3)
	113 ifeq (2, 3)
	114 14 (2, 3)
	116 dload (2, 3)
	117 #14 (2, 3)
	118 dload (2, 3)
	119 #10 (2, 3)
	120 dcmpg (2, 3)
	121 ifge (2, 3)
	122 411 (2, 3)
	124 goto (2, 3)
	125 11 (2, 3)
	127 dload (2, 3)
	128 #14 (2, 3)
	129 dload (2, 3)
	130 #10 (2, 3)
	131 dcmpl (2, 3)
	132 ifle (2, 3)
	133 400 (2, 3)
	135 dload (2, 3)
	136 #5 (2, 3)
	137 dload_3 (2, 3)
	138 dsub (2, 3)
	139 dload (2, 3)
	140 #10 (2, 3)
	141 dload (2, 3)
	142 #14 (2, 3)
	143 dsub (2, 3)
	144 dmul (2, 3)
	145 dstore (2, 3)
	146 #16 (2, 3)
	147 dload (2, 3)
	148 #5 (2, 3)
	149 dload (2, 3)
	150 #12 (2, 3)
	151 dsub (2, 3)
	152 dload (2, 3)
	153 #10 (2, 3)
	154 dload (2, 3)
	155 #8 (2, 3)
	156 dsub (2, 3)
	157 dmul (2, 3)
	158 dstore (2, 3)
	159 #18 (2, 3)
	160 dload (2, 3)
	161 #18 (2, 3)
	162 dload (2, 3)
	163 #16 (2, 3)
	164 dsub (2, 3)
	165 dstore (2, 3)
	166 #20 (2, 3)
	167 dload (2, 3)
	168 #20 (2, 3)
	169 invokestatic (2, 3)
	170 org/apache/commons/math3/util/FastMath.abs:(D)D (2, 3)
	172 ldc2_w (2, 3)
	173 1e-21 (2, 3)
	175 dcmpg (2, 3)
	176 ifge (2, 3)
	177 9 (2, 3)
	179 ldc2_w (2, 3)
	180 2e-21 (2, 3)
	182 goto (2, 3)
	183 9 (2, 3)
	185 ldc2_w (2, 3)
	186 2.0 (2, 3)
	188 dload (2, 3)
	189 #20 (2, 3)
	190 dmul (2, 3)
	191 dstore (2, 3)
	192 #22 (2, 3)
	193 dload (2, 3)
	194 #5 (2, 3)
	195 dload (2, 3)
	196 #5 (2, 3)
	197 dload (2, 3)
	198 #12 (2, 3)
	199 dsub (2, 3)
	200 dload (2, 3)
	201 #18 (2, 3)
	202 dmul (2, 3)
	203 dload (2, 3)
	204 #5 (2, 3)
	205 dload_3 (2, 3)
	206 dsub (2, 3)
	207 dload (2, 3)
	208 #16 (2, 3)
	209 dmul (2, 3)
	210 dsub (2, 3)
	211 dload (2, 3)
	212 #22 (2, 3)
	213 ddiv (2, 3)
	214 dsub (2, 3)
	215 dstore (2, 3)
	216 #24 (2, 3)
	217 dload (2, 3)
	218 #5 (2, 3)
	219 aload_0 (2, 3)
	220 getfield (2, 3)
	221 org/apache/commons/math3/optim/univariate/BracketFinder.growLimit:D (2, 3)
	223 dload (2, 3)
	224 #12 (2, 3)
	225 dload (2, 3)
	226 #5 (2, 3)
	227 dsub (2, 3)
	228 dmul (2, 3)
	229 dadd (2, 3)
	230 dstore (2, 3)
	231 #26 (2, 3)
	232 dload (3, 1)
	233 #24 (3, 1)
	234 dload (3, 1)
	235 #12 (3, 1)
	236 dsub (3, 1)
	237 dload (3, 1)
	238 #5 (3, 1)
	239 dload (3, 1)
	240 #24 (3, 1)
	241 dsub (3, 1)
	242 dmul (3, 1)
	243 dconst_0 (3, 1)
	244 dcmpl (3, 1)
	245 ifle (3, 1)
	246 115 (3, 1)
	248 aload_0 (3, 1)
	249 aload_1 (3, 1)
	250 dload (3, 1)
	251 #24 (3, 1)
	252 invokespecial (3, 1)
	253 org/apache/commons/math3/optim/univariate/BracketFinder.eval:(Lorg/apache/commons/math3/analysis/UnivariateFunction;D)D (3, 1)
	255 dstore (3, 1)
	256 #28 (3, 1)
	257 iload (4, 1)
	258 #7 (4, 1)
	259 ifeq (4, 1)
	260 14 (4, 1)
	262 dload (4, 1)
	263 #28 (4, 1)
	264 dload (4, 1)
	265 #14 (4, 1)
	266 dcmpg (4, 1)
	267 ifge (4, 1)
	268 32 (4, 1)
	270 goto (4, 1)
	271 11 (4, 1)
	273 dload (4, 1)
	274 #28 (4, 1)
	275 dload (4, 1)
	276 #14 (4, 1)
	277 dcmpl (4, 1)
	278 ifle (4, 1)
	279 21 (4, 1)
	281 dload (4, 1)
	282 #5 (4, 1)
	283 dstore_3 (4, 1)
	284 dload (4, 1)
	285 #24 (4, 1)
	286 dstore (4, 1)
	287 #5 (4, 1)
	288 dload (4, 1)
	289 #10 (4, 1)
	290 dstore (4, 1)
	291 #8 (4, 1)
	292 dload (4, 1)
	293 #28 (4, 1)
	294 dstore (4, 1)
	295 #10 (4, 1)
	296 goto (4, 1)
	297 236 (4, 1)
	299 iload (5, 1)
	300 #7 (5, 1)
	301 ifeq (5, 1)
	302 14 (5, 1)
	304 dload (5, 1)
	305 #28 (5, 1)
	306 dload (5, 1)
	307 #10 (5, 1)
	308 dcmpl (5, 1)
	309 ifle (5, 1)
	310 25 (5, 1)
	312 goto (5, 1)
	313 11 (5, 1)
	315 dload (5, 1)
	316 #28 (5, 1)
	317 dload (5, 1)
	318 #10 (5, 1)
	319 dcmpg (5, 1)
	320 ifge (5, 1)
	321 14 (5, 1)
	323 dload (5, 1)
	324 #24 (5, 1)
	325 dstore (5, 1)
	326 #12 (5, 1)
	327 dload (5, 1)
	328 #28 (5, 1)
	329 dstore (5, 1)
	330 #14 (5, 1)
	331 goto (5, 1)
	332 201 (5, 1)
	334 dload (5, 1)
	335 #12 (5, 1)
	336 ldc2_w (5, 1)
	337 1.618034 (5, 1)
	339 dload (5, 1)
	340 #12 (5, 1)
	341 dload (5, 1)
	342 #5 (5, 1)
	343 dsub (5, 1)
	344 dmul (5, 1)
	345 dadd (5, 1)
	346 dstore (5, 1)
	347 #24 (5, 1)
	348 aload_0 (5, 1)
	349 aload_1 (5, 1)
	350 dload (5, 1)
	351 #24 (5, 1)
	352 invokespecial (5, 1)
	353 org/apache/commons/math3/optim/univariate/BracketFinder.eval:(Lorg/apache/commons/math3/analysis/UnivariateFunction;D)D (5, 1)
	355 dstore (5, 1)
	356 #28 (5, 1)
	357 goto (5, 1)
	358 149 (5, 1)
	360 dload (6, 1)
	361 #24 (6, 1)
	362 dload (6, 1)
	363 #26 (6, 1)
	364 dsub (6, 1)
	365 dload (6, 1)
	366 #26 (6, 1)
	367 dload (6, 1)
	368 #12 (6, 1)
	369 dsub (6, 1)
	370 dmul (6, 1)
	371 dconst_0 (6, 1)
	372 dcmpl (6, 1)
	373 iflt (6, 1)
	374 19 (6, 1)
	376 dload (6, 1)
	377 #26 (6, 1)
	378 dstore (6, 1)
	379 #24 (6, 1)
	380 aload_0 (6, 1)
	381 aload_1 (6, 1)
	382 dload (6, 1)
	383 #24 (6, 1)
	384 invokespecial (6, 1)
	385 org/apache/commons/math3/optim/univariate/BracketFinder.eval:(Lorg/apache/commons/math3/analysis/UnivariateFunction;D)D (6, 1)
	387 dstore (6, 1)
	388 #28 (6, 1)
	389 goto (6, 1)
	390 117 (6, 1)
	392 dload (7, 1)
	393 #24 (7, 1)
	394 dload (7, 1)
	395 #26 (7, 1)
	396 dsub (7, 1)
	397 dload (7, 1)
	398 #12 (7, 1)
	399 dload (7, 1)
	400 #24 (7, 1)
	401 dsub (7, 1)
	402 dmul (7, 1)
	403 dconst_0 (7, 1)
	404 dcmpl (7, 1)
	405 ifle (7, 1)
	406 78 (7, 1)
	408 aload_0 (7, 1)
	409 aload_1 (7, 1)
	410 dload (7, 1)
	411 #24 (7, 1)
	412 invokespecial (7, 1)
	413 org/apache/commons/math3/optim/univariate/BracketFinder.eval:(Lorg/apache/commons/math3/analysis/UnivariateFunction;D)D (7, 1)
	415 dstore (7, 1)
	416 #28 (7, 1)
	417 iload (8, 1)
	418 #7 (8, 1)
	419 ifeq (8, 1)
	420 14 (8, 1)
	422 dload (8, 1)
	423 #28 (8, 1)
	424 dload (8, 1)
	425 #14 (8, 1)
	426 dcmpg (8, 1)
	427 ifge (8, 1)
	428 79 (8, 1)
	430 goto (8, 1)
	431 11 (8, 1)
	433 dload (8, 1)
	434 #28 (8, 1)
	435 dload (8, 1)
	436 #14 (8, 1)
	437 dcmpl (8, 1)
	438 ifle (8, 1)
	439 68 (8, 1)
	441 dload (8, 1)
	442 #12 (8, 1)
	443 dstore (8, 1)
	444 #5 (8, 1)
	445 dload (8, 1)
	446 #24 (8, 1)
	447 dstore (8, 1)
	448 #12 (8, 1)
	449 dload (8, 1)
	450 #12 (8, 1)
	451 ldc2_w (8, 1)
	452 1.618034 (8, 1)
	454 dload (8, 1)
	455 #12 (8, 1)
	456 dload (8, 1)
	457 #5 (8, 1)
	458 dsub (8, 1)
	459 dmul (8, 1)
	460 dadd (8, 1)
	461 dstore (8, 1)
	462 #24 (8, 1)
	463 dload (8, 1)
	464 #14 (8, 1)
	465 dstore (8, 1)
	466 #10 (8, 1)
	467 dload (8, 1)
	468 #28 (8, 1)
	469 dstore (8, 1)
	470 #14 (8, 1)
	471 aload_0 (8, 1)
	472 aload_1 (8, 1)
	473 dload (8, 1)
	474 #24 (8, 1)
	475 invokespecial (8, 1)
	476 org/apache/commons/math3/optim/univariate/BracketFinder.eval:(Lorg/apache/commons/math3/analysis/UnivariateFunction;D)D (8, 1)
	478 dstore (8, 1)
	479 #28 (8, 1)
	480 goto (8, 1)
	481 26 (8, 1)
	483 dload (9, 2)
	484 #12 (9, 2)
	485 ldc2_w (9, 2)
	486 1.618034 (9, 2)
	488 dload (9, 2)
	489 #12 (9, 2)
	490 dload (9, 2)
	491 #5 (9, 2)
	492 dsub (9, 2)
	493 dmul (9, 2)
	494 dadd (9, 2)
	495 dstore (9, 2)
	496 #24 (9, 2)
	497 aload_0 (9, 2)
	498 aload_1 (9, 2)
	499 dload (9, 2)
	500 #24 (9, 2)
	501 invokespecial (9, 2)
	502 org/apache/commons/math3/optim/univariate/BracketFinder.eval:(Lorg/apache/commons/math3/analysis/UnivariateFunction;D)D (9, 2)
	504 dstore (9, 2)
	505 #28 (9, 2)
	506 dload (2, 3)
	507 #5 (2, 3)
	508 dstore_3 (2, 3)
	509 dload (2, 3)
	510 #10 (2, 3)
	511 dstore (2, 3)
	512 #8 (2, 3)
	513 dload (2, 3)
	514 #12 (2, 3)
	515 dstore (2, 3)
	516 #5 (2, 3)
	517 dload (2, 3)
	518 #14 (2, 3)
	519 dstore (2, 3)
	520 #10 (2, 3)
	521 dload (2, 3)
	522 #24 (2, 3)
	523 dstore (2, 3)
	524 #12 (2, 3)
	525 dload (2, 3)
	526 #28 (2, 3)
	527 dstore (2, 3)
	528 #14 (2, 3)
	529 goto (1, 1)
	530 -418 (1, 1)
	532 aload_0 (1, 1)
	533 dload_3 (1, 1)
	534 putfield (1, 1)
	535 org/apache/commons/math3/optim/univariate/BracketFinder.lo:D (1, 1)
	537 aload_0 (1, 1)
	538 dload (1, 1)
	539 #8 (1, 1)
	540 putfield (1, 1)
	541 org/apache/commons/math3/optim/univariate/BracketFinder.fLo:D (1, 1)
	543 aload_0 (1, 1)
	544 dload (1, 1)
	545 #5 (1, 1)
	546 putfield (1, 1)
	547 org/apache/commons/math3/optim/univariate/BracketFinder.mid:D (1, 1)
	549 aload_0 (1, 1)
	550 dload (1, 1)
	551 #10 (1, 1)
	552 putfield (1, 1)
	553 org/apache/commons/math3/optim/univariate/BracketFinder.fMid:D (1, 1)
	555 aload_0 (1, 1)
	556 dload (1, 1)
	557 #12 (1, 1)
	558 putfield (1, 1)
	559 org/apache/commons/math3/optim/univariate/BracketFinder.hi:D (1, 1)
	561 aload_0 (1, 1)
	562 dload (1, 1)
	563 #14 (1, 1)
	564 putfield (1, 1)
	565 org/apache/commons/math3/optim/univariate/BracketFinder.fHi:D (1, 1)
	567 aload_0 (2, 1)
	568 getfield (2, 1)
	569 org/apache/commons/math3/optim/univariate/BracketFinder.lo:D (2, 1)
	571 aload_0 (2, 1)
	572 getfield (2, 1)
	573 org/apache/commons/math3/optim/univariate/BracketFinder.hi:D (2, 1)
	575 dcmpl (2, 1)
	576 ifle (2, 1)
	577 43 (2, 1)
	579 aload_0 (2, 1)
	580 getfield (2, 1)
	581 org/apache/commons/math3/optim/univariate/BracketFinder.lo:D (2, 1)
	583 dstore (2, 1)
	584 #16 (2, 1)
	585 aload_0 (2, 1)
	586 aload_0 (2, 1)
	587 getfield (2, 1)
	588 org/apache/commons/math3/optim/univariate/BracketFinder.hi:D (2, 1)
	590 putfield (2, 1)
	591 org/apache/commons/math3/optim/univariate/BracketFinder.lo:D (2, 1)
	593 aload_0 (2, 1)
	594 dload (2, 1)
	595 #16 (2, 1)
	596 putfield (2, 1)
	597 org/apache/commons/math3/optim/univariate/BracketFinder.hi:D (2, 1)
	599 aload_0 (2, 1)
	600 getfield (2, 1)
	601 org/apache/commons/math3/optim/univariate/BracketFinder.fLo:D (2, 1)
	603 dstore (2, 1)
	604 #16 (2, 1)
	605 aload_0 (2, 1)
	606 aload_0 (2, 1)
	607 getfield (2, 1)
	608 org/apache/commons/math3/optim/univariate/BracketFinder.fHi:D (2, 1)
	610 putfield (2, 1)
	611 org/apache/commons/math3/optim/univariate/BracketFinder.fLo:D (2, 1)
	613 aload_0 (2, 1)
	614 dload (2, 1)
	615 #16 (2, 1)
	616 putfield (2, 1)
	617 org/apache/commons/math3/optim/univariate/BracketFinder.fHi:D (2, 1)
	619 return (0, 1)

Method: getMaxEvaluations
	0 aload_0 (0, 0)
	1 getfield (0, 0)
	2 org/apache/commons/math3/optim/univariate/BracketFinder.evaluations:Lorg/apache/commons/math3/util/IntegerSequence$Incrementor; (0, 0)
	4 invokevirtual (0, 0)
	5 org/apache/commons/math3/util/IntegerSequence$Incrementor.getMaximalCount:()I (0, 0)
	7 ireturn (0, 0)

Method: getEvaluations
	0 aload_0 (0, 0)
	1 getfield (0, 0)
	2 org/apache/commons/math3/optim/univariate/BracketFinder.evaluations:Lorg/apache/commons/math3/util/IntegerSequence$Incrementor; (0, 0)
	4 invokevirtual (0, 0)
	5 org/apache/commons/math3/util/IntegerSequence$Incrementor.getCount:()I (0, 0)
	7 ireturn (0, 0)

Method: getLo
	0 aload_0 (0, 0)
	1 getfield (0, 0)
	2 org/apache/commons/math3/optim/univariate/BracketFinder.lo:D (0, 0)
	4 dreturn (0, 0)

Method: getFLo
	0 aload_0 (0, 0)
	1 getfield (0, 0)
	2 org/apache/commons/math3/optim/univariate/BracketFinder.fLo:D (0, 0)
	4 dreturn (0, 0)

Method: getHi
	0 aload_0 (0, 0)
	1 getfield (0, 0)
	2 org/apache/commons/math3/optim/univariate/BracketFinder.hi:D (0, 0)
	4 dreturn (0, 0)

Method: getFHi
	0 aload_0 (0, 0)
	1 getfield (0, 0)
	2 org/apache/commons/math3/optim/univariate/BracketFinder.fHi:D (0, 0)
	4 dreturn (0, 0)

Method: getMid
	0 aload_0 (0, 0)
	1 getfield (0, 0)
	2 org/apache/commons/math3/optim/univariate/BracketFinder.mid:D (0, 0)
	4 dreturn (0, 0)

Method: getFMid
	0 aload_0 (0, 0)
	1 getfield (0, 0)
	2 org/apache/commons/math3/optim/univariate/BracketFinder.fMid:D (0, 0)
	4 dreturn (0, 0)

Method: eval
	0 aload_0 (0, 0)
	1 getfield (0, 0)
	2 org/apache/commons/math3/optim/univariate/BracketFinder.evaluations:Lorg/apache/commons/math3/util/IntegerSequence$Incrementor; (0, 0)
	4 invokevirtual (0, 0)
	5 org/apache/commons/math3/util/IntegerSequence$Incrementor.increment:()V (0, 0)
	7 goto (0, 0)
	8 18 (0, 0)
	10 astore (0, 0)
	11 #4 (0, 0)
	12 new (0, 0)
	13 org/apache/commons/math3/exception/TooManyEvaluationsException (0, 0)
	15 dup (0, 0)
	16 aload (0, 0)
	17 #4 (0, 0)
	18 invokevirtual (0, 0)
	19 org/apache/commons/math3/exception/MaxCountExceededException.getMax:()Ljava/lang/Number; (0, 0)
	21 invokespecial (0, 0)
	22 org/apache/commons/math3/exception/TooManyEvaluationsException.<init>:(Ljava/lang/Number;)V (0, 0)
	24 athrow (0, 0)
	25 aload_1 (0, 0)
	26 dload_2 (0, 0)
	27 invokeinterface (0, 0)
	28 org/apache/commons/math3/analysis/UnivariateFunction.java/lang/Object (0, 0)
	30 0 (0, 0)
	32 dreturn (0, 0)

