Method: <init>
	0 aload_0 (0, 0)
	1 dload_1 (0, 0)
	2 dload_3 (0, 0)
	3 aconst_null (0, 0)
	4 invokespecial (0, 0)
	5 org/apache/commons/math3/optim/univariate/BrentOptimizer.<init>:(DDLorg/apache/commons/math3/optim/ConvergenceChecker;)V (0, 0)
	7 return (0, 0)

Method: doOptimize
	0 aload_0 (0, 0)
	1 invokevirtual (0, 0)
	2 org/apache/commons/math3/optim/univariate/BrentOptimizer.doOptimize:()Lorg/apache/commons/math3/optim/univariate/UnivariatePointValuePair; (0, 0)
	4 areturn (0, 0)

Method: best
	0 aload_1 (1, 1)
	1 ifnonnull (1, 1)
	2 5 (1, 1)
	4 aload_2 (1, 1)
	5 areturn (1, 1)
	6 aload_2 (1, 1)
	7 ifnonnull (1, 1)
	8 5 (1, 1)
	10 aload_1 (1, 1)
	11 areturn (1, 1)
	12 iload_3 (1, 1)
	13 ifeq (1, 1)
	14 21 (1, 1)
	16 aload_1 (1, 1)
	17 invokevirtual (1, 1)
	18 org/apache/commons/math3/optim/univariate/UnivariatePointValuePair.getValue:()D (1, 1)
	20 aload_2 (1, 1)
	21 invokevirtual (1, 1)
	22 org/apache/commons/math3/optim/univariate/UnivariatePointValuePair.getValue:()D (1, 1)
	24 dcmpg (1, 1)
	25 ifgt (1, 1)
	26 7 (1, 1)
	28 aload_1 (1, 1)
	29 goto (1, 1)
	30 4 (1, 1)
	32 aload_2 (1, 1)
	33 areturn (1, 1)
	34 aload_1 (2, 2)
	35 invokevirtual (2, 2)
	36 org/apache/commons/math3/optim/univariate/UnivariatePointValuePair.getValue:()D (2, 2)
	38 aload_2 (2, 2)
	39 invokevirtual (2, 2)
	40 org/apache/commons/math3/optim/univariate/UnivariatePointValuePair.getValue:()D (2, 2)
	42 dcmpl (2, 2)
	43 iflt (2, 2)
	44 7 (2, 2)
	46 aload_1 (2, 2)
	47 goto (2, 2)
	48 4 (2, 2)
	50 aload_2 (2, 2)
	51 areturn (1, 2)

Method: <clinit>
	0 ldc2_w (0, 0)
	1 0.5 (0, 0)
	3 ldc2_w (0, 0)
	4 3.0 (0, 0)
	6 ldc2_w (0, 0)
	7 5.0 (0, 0)
	9 invokestatic (0, 0)
	10 org/apache/commons/math3/util/FastMath.sqrt:(D)D (0, 0)
	12 dsub (0, 0)
	13 dmul (0, 0)
	14 putstatic (0, 0)
	15 org/apache/commons/math3/optim/univariate/BrentOptimizer.GOLDEN_SECTION:D (0, 0)
	17 ldc2_w (0, 0)
	18 2.0 (0, 0)
	20 dconst_1 (0, 0)
	21 invokestatic (0, 0)
	22 org/apache/commons/math3/util/FastMath.ulp:(D)D (0, 0)
	24 dmul (0, 0)
	25 putstatic (0, 0)
	26 org/apache/commons/math3/optim/univariate/BrentOptimizer.MIN_RELATIVE_TOLERANCE:D (0, 0)
	28 return (0, 0)

