Method: <init>
	0 aload_0 (0, 0)
	1 aload_1 (0, 0)
	2 invokevirtual (0, 0)
	3 org/apache/commons/math3/optim/univariate/UnivariateOptimizer.getConvergenceChecker:()Lorg/apache/commons/math3/optim/ConvergenceChecker; (0, 0)
	5 invokespecial (0, 0)
	6 org/apache/commons/math3/optim/univariate/UnivariateOptimizer.<init>:(Lorg/apache/commons/math3/optim/ConvergenceChecker;)V (0, 0)
	8 aload_0 (0, 0)
	9 iconst_m1 (0, 0)
	10 putfield (0, 0)
	11 org/apache/commons/math3/optim/univariate/MultiStartUnivariateOptimizer.maxEvalIndex:I (0, 0)
	13 aload_0 (0, 0)
	14 iconst_m1 (0, 0)
	15 putfield (0, 0)
	16 org/apache/commons/math3/optim/univariate/MultiStartUnivariateOptimizer.searchIntervalIndex:I (0, 0)
	18 iload_2 (4, 1)
	19 iconst_1 (4, 1)
	20 if_icmpge (4, 1)
	21 15 (4, 1)
	23 new (4, 1)
	24 org/apache/commons/math3/exception/NotStrictlyPositiveException (4, 1)
	26 dup (4, 1)
	27 iload_2 (4, 1)
	28 invokestatic (4, 1)
	29 java/lang/Integer.valueOf:(I)Ljava/lang/Integer; (4, 1)
	31 invokespecial (4, 1)
	32 org/apache/commons/math3/exception/NotStrictlyPositiveException.<init>:(Ljava/lang/Number;)V (4, 1)
	34 athrow (4, 1)
	35 aload_0 (3, 1)
	36 aload_1 (3, 1)
	37 putfield (3, 1)
	38 org/apache/commons/math3/optim/univariate/MultiStartUnivariateOptimizer.optimizer:Lorg/apache/commons/math3/optim/univariate/UnivariateOptimizer; (3, 1)
	40 aload_0 (3, 1)
	41 iload_2 (3, 1)
	42 putfield (3, 1)
	43 org/apache/commons/math3/optim/univariate/MultiStartUnivariateOptimizer.starts:I (3, 1)
	45 aload_0 (3, 1)
	46 aload_3 (3, 1)
	47 putfield (3, 1)
	48 org/apache/commons/math3/optim/univariate/MultiStartUnivariateOptimizer.generator:Lorg/apache/commons/math3/random/RandomGenerator; (3, 1)
	50 return (0, 1)

Method: getEvaluations
	0 aload_0 (0, 0)
	1 getfield (0, 0)
	2 org/apache/commons/math3/optim/univariate/MultiStartUnivariateOptimizer.totalEvaluations:I (0, 0)
	4 ireturn (0, 0)

Method: getOptima
	0 aload_0 (1, 1)
	1 getfield (1, 1)
	2 org/apache/commons/math3/optim/univariate/MultiStartUnivariateOptimizer.optima:[Lorg/apache/commons/math3/optim/univariate/UnivariatePointValuePair; (1, 1)
	4 ifnonnull (1, 1)
	5 18 (1, 1)
	7 new (1, 1)
	8 org/apache/commons/math3/exception/MathIllegalStateException (1, 1)
	10 dup (1, 1)
	11 getstatic (1, 1)
	12 org/apache/commons/math3/exception/util/LocalizedFormats.NO_OPTIMUM_COMPUTED_YET:Lorg/apache/commons/math3/exception/util/LocalizedFormats; (1, 1)
	14 iconst_0 (1, 1)
	15 anewarray (1, 1)
	16 java/lang/Object (1, 1)
	18 invokespecial (1, 1)
	19 org/apache/commons/math3/exception/MathIllegalStateException.<init>:(Lorg/apache/commons/math3/exception/util/Localizable;[Ljava/lang/Object;)V (1, 1)
	21 athrow (1, 1)
	22 aload_0 (0, 0)
	23 getfield (0, 0)
	24 org/apache/commons/math3/optim/univariate/MultiStartUnivariateOptimizer.optima:[Lorg/apache/commons/math3/optim/univariate/UnivariatePointValuePair; (0, 0)
	26 invokevirtual (0, 0)
	27 [Lorg/apache/commons/math3/optim/univariate/UnivariatePointValuePair;.clone:()Ljava/lang/Object; (0, 0)
	29 checkcast (0, 0)
	30 [Lorg/apache/commons/math3/optim/univariate/UnivariatePointValuePair; (0, 0)
	32 areturn (0, 0)

Method: optimize
	0 aload_0 (0, 0)
	1 aload_1 (0, 0)
	2 invokevirtual (0, 0)
	3 org/apache/commons/math3/optim/univariate/MultiStartUnivariateOptimizer.optimize:([Lorg/apache/commons/math3/optim/OptimizationData;)Lorg/apache/commons/math3/optim/univariate/UnivariatePointValuePair; (0, 0)
	5 areturn (0, 0)

Method: doOptimize
	0 aload_0 (0, 0)
	1 invokevirtual (0, 0)
	2 org/apache/commons/math3/optim/univariate/MultiStartUnivariateOptimizer.doOptimize:()Lorg/apache/commons/math3/optim/univariate/UnivariatePointValuePair; (0, 0)
	4 areturn (0, 0)

Method: sortPairs
	0 aload_0 (0, 0)
	1 getfield (0, 0)
	2 org/apache/commons/math3/optim/univariate/MultiStartUnivariateOptimizer.optima:[Lorg/apache/commons/math3/optim/univariate/UnivariatePointValuePair; (0, 0)
	4 new (0, 0)
	5 org/apache/commons/math3/optim/univariate/MultiStartUnivariateOptimizer$1 (0, 0)
	7 dup (0, 0)
	8 aload_0 (0, 0)
	9 aload_1 (0, 0)
	10 invokespecial (0, 0)
	11 org/apache/commons/math3/optim/univariate/MultiStartUnivariateOptimizer$1.<init>:(Lorg/apache/commons/math3/optim/univariate/MultiStartUnivariateOptimizer;Lorg/apache/commons/math3/optim/nonlinear/scalar/GoalType;)V (0, 0)
	13 invokestatic (0, 0)
	14 java/util/Arrays.sort:([Ljava/lang/Object;Ljava/util/Comparator;)V (0, 0)
	16 return (0, 0)

