Method: <init>
	0 aload_0 (0, 0)
	1 aload_1 (0, 0)
	2 invokespecial (0, 0)
	3 org/apache/commons/math3/optim/BaseOptimizer.<init>:(Lorg/apache/commons/math3/optim/ConvergenceChecker;)V (0, 0)
	5 return (0, 0)

Method: optimize
	0 aload_0 (0, 0)
	1 aload_1 (0, 0)
	2 invokevirtual (0, 0)
	3 org/apache/commons/math3/optim/univariate/UnivariateOptimizer.optimize:([Lorg/apache/commons/math3/optim/OptimizationData;)Lorg/apache/commons/math3/optim/univariate/UnivariatePointValuePair; (0, 0)
	5 areturn (0, 0)

Method: getGoalType
	0 aload_0 (0, 0)
	1 getfield (0, 0)
	2 org/apache/commons/math3/optim/univariate/UnivariateOptimizer.goal:Lorg/apache/commons/math3/optim/nonlinear/scalar/GoalType; (0, 0)
	4 areturn (0, 0)

Method: parseOptimizationData
	0 aload_0 (0, 0)
	1 aload_1 (0, 0)
	2 invokespecial (0, 0)
	3 org/apache/commons/math3/optim/BaseOptimizer.parseOptimizationData:([Lorg/apache/commons/math3/optim/OptimizationData;)V (0, 0)
	5 aload_1 (2, 4)
	6 astore_2 (2, 4)
	7 aload_2 (2, 4)
	8 arraylength (2, 4)
	9 istore_3 (2, 4)
	10 iconst_0 (2, 4)
	11 istore (2, 4)
	12 #4 (2, 4)
	13 iload (2, 4)
	14 #4 (2, 4)
	15 iload_3 (2, 4)
	16 if_icmpge (2, 4)
	17 103 (2, 4)
	19 aload_2 (2, 4)
	20 iload (2, 4)
	21 #4 (2, 4)
	22 aaload (2, 4)
	23 astore (2, 4)
	24 #5 (2, 4)
	25 aload (3, 1)
	26 #5 (3, 1)
	27 instanceof (3, 1)
	28 org/apache/commons/math3/optim/univariate/SearchInterval (3, 1)
	30 ifeq (3, 1)
	31 40 (3, 1)
	33 aload (3, 1)
	34 #5 (3, 1)
	35 checkcast (3, 1)
	36 org/apache/commons/math3/optim/univariate/SearchInterval (3, 1)
	38 astore (3, 1)
	39 #6 (3, 1)
	40 aload_0 (3, 1)
	41 aload (3, 1)
	42 #6 (3, 1)
	43 invokevirtual (3, 1)
	44 org/apache/commons/math3/optim/univariate/SearchInterval.getMin:()D (3, 1)
	46 putfield (3, 1)
	47 org/apache/commons/math3/optim/univariate/UnivariateOptimizer.min:D (3, 1)
	49 aload_0 (3, 1)
	50 aload (3, 1)
	51 #6 (3, 1)
	52 invokevirtual (3, 1)
	53 org/apache/commons/math3/optim/univariate/SearchInterval.getMax:()D (3, 1)
	55 putfield (3, 1)
	56 org/apache/commons/math3/optim/univariate/UnivariateOptimizer.max:D (3, 1)
	58 aload_0 (3, 1)
	59 aload (3, 1)
	60 #6 (3, 1)
	61 invokevirtual (3, 1)
	62 org/apache/commons/math3/optim/univariate/SearchInterval.getStartValue:()D (3, 1)
	64 putfield (3, 1)
	65 org/apache/commons/math3/optim/univariate/UnivariateOptimizer.start:D (3, 1)
	67 goto (3, 1)
	68 46 (3, 1)
	70 aload (3, 1)
	71 #5 (3, 1)
	72 instanceof (3, 1)
	73 org/apache/commons/math3/optim/univariate/UnivariateObjectiveFunction (3, 1)
	75 ifeq (3, 1)
	76 18 (3, 1)
	78 aload_0 (3, 1)
	79 aload (3, 1)
	80 #5 (3, 1)
	81 checkcast (3, 1)
	82 org/apache/commons/math3/optim/univariate/UnivariateObjectiveFunction (3, 1)
	84 invokevirtual (3, 1)
	85 org/apache/commons/math3/optim/univariate/UnivariateObjectiveFunction.getObjectiveFunction:()Lorg/apache/commons/math3/analysis/UnivariateFunction; (3, 1)
	87 putfield (3, 1)
	88 org/apache/commons/math3/optim/univariate/UnivariateOptimizer.function:Lorg/apache/commons/math3/analysis/UnivariateFunction; (3, 1)
	90 goto (3, 1)
	91 23 (3, 1)
	93 aload (3, 1)
	94 #5 (3, 1)
	95 instanceof (3, 1)
	96 org/apache/commons/math3/optim/nonlinear/scalar/GoalType (3, 1)
	98 ifeq (3, 1)
	99 15 (3, 1)
	101 aload_0 (3, 1)
	102 aload (3, 1)
	103 #5 (3, 1)
	104 checkcast (3, 1)
	105 org/apache/commons/math3/optim/nonlinear/scalar/GoalType (3, 1)
	107 putfield (3, 1)
	108 org/apache/commons/math3/optim/univariate/UnivariateOptimizer.goal:Lorg/apache/commons/math3/optim/nonlinear/scalar/GoalType; (3, 1)
	110 goto (3, 1)
	111 3 (3, 1)
	113 iinc (3, 1)
	114 #4 (3, 1)
	115 -89 (3, 1)
	116 goto (3, 1)
	117 -103 (3, 1)
	119 return (0, 1)

Method: getStartValue
	0 aload_0 (0, 0)
	1 getfield (0, 0)
	2 org/apache/commons/math3/optim/univariate/UnivariateOptimizer.start:D (0, 0)
	4 dreturn (0, 0)

Method: getMin
	0 aload_0 (0, 0)
	1 getfield (0, 0)
	2 org/apache/commons/math3/optim/univariate/UnivariateOptimizer.min:D (0, 0)
	4 dreturn (0, 0)

Method: getMax
	0 aload_0 (0, 0)
	1 getfield (0, 0)
	2 org/apache/commons/math3/optim/univariate/UnivariateOptimizer.max:D (0, 0)
	4 dreturn (0, 0)

Method: computeObjectiveValue
	0 aload_0 (0, 0)
	1 invokespecial (0, 0)
	2 org/apache/commons/math3/optim/BaseOptimizer.incrementEvaluationCount:()V (0, 0)
	4 aload_0 (0, 0)
	5 getfield (0, 0)
	6 org/apache/commons/math3/optim/univariate/UnivariateOptimizer.function:Lorg/apache/commons/math3/analysis/UnivariateFunction; (0, 0)
	8 dload_1 (0, 0)
	9 invokeinterface (0, 0)
	10 org/apache/commons/math3/analysis/UnivariateFunction.optimize:([Lorg/apache/commons/math3/optim/OptimizationData;)Lorg/apache/commons/math3/optim/univariate/UnivariatePointValuePair; (0, 0)
	12 0 (0, 0)
	14 dreturn (0, 0)

