Method: newSampleData
	0 aload_0 (0, 0)
	1 aload_2 (0, 0)
	2 aload_1 (0, 0)
	3 invokevirtual (0, 0)
	6 aload_0 (0, 0)
	7 aload_1 (0, 0)
	8 invokevirtual (0, 0)
	11 aload_0 (0, 0)
	12 aload_2 (0, 0)
	13 invokevirtual (0, 0)
	16 aload_0 (0, 0)
	17 aload_2 (0, 0)
	18 aload_3 (0, 0)
	19 invokevirtual (0, 0)
	22 aload_0 (0, 0)
	23 aload_3 (0, 0)
	24 invokevirtual (0, 0)
	27 return (0, 0)

Method: newCovarianceData
	0 aload_0 (0, 0)
	1 new (0, 0)
	4 dup (0, 0)
	5 aload_1 (0, 0)
	6 invokespecial (0, 0)
	9 putfield (0, 0)
	12 aload_0 (0, 0)
	13 aconst_null (0, 0)
	14 putfield (0, 0)
	17 return (0, 0)

Method: getOmegaInverse
	0 aload_0 (1, 1)
	1 getfield (1, 1)
	4 ifnonnull (1, 1)
	7 aload_0 (1, 1)
	8 new (1, 1)
	11 dup (1, 1)
	12 aload_0 (1, 1)
	13 getfield (1, 1)
	16 invokespecial (1, 1)
	19 invokevirtual (1, 1)
	22 invokeinterface (1, 1)
	27 putfield (1, 1)
	30 aload_0 (0, 0)
	31 getfield (0, 0)
	34 areturn (0, 0)

Method: calculateBeta
	0 aload_0 (0, 0)
	1 invokevirtual (0, 0)
	4 astore_1 (0, 0)
	5 aload_0 (0, 0)
	6 invokevirtual (0, 0)
	9 invokeinterface (0, 0)
	14 astore_2 (0, 0)
	15 aload_2 (0, 0)
	16 aload_1 (0, 0)
	17 invokeinterface (0, 0)
	22 aload_0 (0, 0)
	23 invokevirtual (0, 0)
	26 invokeinterface (0, 0)
	31 astore_3 (0, 0)
	32 new (0, 0)
	35 dup (0, 0)
	36 aload_3 (0, 0)
	37 invokespecial (0, 0)
	40 invokevirtual (0, 0)
	43 invokeinterface (0, 0)
	48 astore (0, 0)
	50 aload (0, 0)
	52 aload_2 (0, 0)
	53 invokeinterface (0, 0)
	58 aload_1 (0, 0)
	59 invokeinterface (0, 0)
	64 aload_0 (0, 0)
	65 invokevirtual (0, 0)
	68 invokeinterface (0, 0)
	73 areturn (0, 0)

Method: calculateBetaVariance
	0 aload_0 (0, 0)
	1 invokevirtual (0, 0)
	4 astore_1 (0, 0)
	5 aload_0 (0, 0)
	6 invokevirtual (0, 0)
	9 invokeinterface (0, 0)
	14 aload_1 (0, 0)
	15 invokeinterface (0, 0)
	20 aload_0 (0, 0)
	21 invokevirtual (0, 0)
	24 invokeinterface (0, 0)
	29 astore_2 (0, 0)
	30 new (0, 0)
	33 dup (0, 0)
	34 aload_2 (0, 0)
	35 invokespecial (0, 0)
	38 invokevirtual (0, 0)
	41 invokeinterface (0, 0)
	46 areturn (0, 0)

Method: calculateErrorVariance
	0 aload_0 (0, 0)
	1 invokevirtual (0, 0)
	4 astore_1 (0, 0)
	5 aload_1 (0, 0)
	6 aload_0 (0, 0)
	7 invokevirtual (0, 0)
	10 aload_1 (0, 0)
	11 invokeinterface (0, 0)
	16 invokevirtual (0, 0)
	19 dstore_2 (0, 0)
	20 dload_2 (0, 0)
	21 aload_0 (0, 0)
	22 invokevirtual (0, 0)
	25 invokeinterface (0, 0)
	30 aload_0 (0, 0)
	31 invokevirtual (0, 0)
	34 invokeinterface (0, 0)
	39 isub (0, 0)
	40 i2d (0, 0)
	41 ddiv (0, 0)
	42 dreturn (0, 0)

