Method: <init>
	0 aload_0 (0, 0)
	1 iload_1 (0, 0)
	2 iload_2 (0, 0)
	3 getstatic (0, 0)
	4 org/apache/commons/math3/util/Precision.EPSILON:D (0, 0)
	6 invokespecial (0, 0)
	7 org/apache/commons/math3/stat/regression/MillerUpdatingRegression.<init>:(IZD)V (0, 0)
	9 return (0, 0)

Method: hasIntercept
	0 aload_0 (0, 0)
	1 getfield (0, 0)
	2 org/apache/commons/math3/stat/regression/MillerUpdatingRegression.hasIntercept:Z (0, 0)
	4 ireturn (0, 0)

Method: getN
	0 aload_0 (0, 0)
	1 getfield (0, 0)
	2 org/apache/commons/math3/stat/regression/MillerUpdatingRegression.nobs:J (0, 0)
	4 lreturn (0, 0)

Method: addObservation
	0 aload_0 (1, 1)
	1 getfield (1, 1)
	2 org/apache/commons/math3/stat/regression/MillerUpdatingRegression.hasIntercept:Z (1, 1)
	4 ifne (1, 1)
	5 12 (1, 1)
	7 aload_1 (1, 1)
	8 arraylength (1, 1)
	9 aload_0 (1, 1)
	10 getfield (1, 1)
	11 org/apache/commons/math3/stat/regression/MillerUpdatingRegression.nvars:I (1, 1)
	13 if_icmpne (1, 1)
	14 21 (1, 1)
	16 aload_0 (1, 1)
	17 getfield (1, 1)
	18 org/apache/commons/math3/stat/regression/MillerUpdatingRegression.hasIntercept:Z (1, 1)
	20 ifeq (1, 1)
	21 47 (1, 1)
	23 aload_1 (1, 1)
	24 arraylength (1, 1)
	25 iconst_1 (1, 1)
	26 iadd (1, 1)
	27 aload_0 (1, 1)
	28 getfield (1, 1)
	29 org/apache/commons/math3/stat/regression/MillerUpdatingRegression.nvars:I (1, 1)
	31 if_icmpeq (1, 1)
	32 36 (1, 1)
	34 new (2, 1)
	35 org/apache/commons/math3/stat/regression/ModelSpecificationException (2, 1)
	37 dup (2, 1)
	38 getstatic (2, 1)
	39 org/apache/commons/math3/exception/util/LocalizedFormats.INVALID_REGRESSION_OBSERVATION:Lorg/apache/commons/math3/exception/util/LocalizedFormats; (2, 1)
	41 iconst_2 (2, 1)
	42 anewarray (2, 1)
	43 java/lang/Object (2, 1)
	45 dup (2, 1)
	46 iconst_0 (2, 1)
	47 aload_1 (2, 1)
	48 arraylength (2, 1)
	49 invokestatic (2, 1)
	50 java/lang/Integer.valueOf:(I)Ljava/lang/Integer; (2, 1)
	52 aastore (2, 1)
	53 dup (2, 1)
	54 iconst_1 (2, 1)
	55 aload_0 (2, 1)
	56 getfield (2, 1)
	57 org/apache/commons/math3/stat/regression/MillerUpdatingRegression.nvars:I (2, 1)
	59 invokestatic (2, 1)
	60 java/lang/Integer.valueOf:(I)Ljava/lang/Integer; (2, 1)
	62 aastore (2, 1)
	63 invokespecial (2, 1)
	64 org/apache/commons/math3/stat/regression/ModelSpecificationException.<init>:(Lorg/apache/commons/math3/exception/util/Localizable;[Ljava/lang/Object;)V (2, 1)
	66 athrow (2, 1)
	67 aload_0 (2, 1)
	68 getfield (2, 1)
	69 org/apache/commons/math3/stat/regression/MillerUpdatingRegression.hasIntercept:Z (2, 1)
	71 ifne (2, 1)
	72 18 (2, 1)
	74 aload_0 (2, 1)
	75 aload_1 (2, 1)
	76 aload_1 (2, 1)
	77 arraylength (2, 1)
	78 invokestatic (2, 1)
	79 org/apache/commons/math3/util/MathArrays.copyOf:([DI)[D (2, 1)
	81 dconst_1 (2, 1)
	82 dload_2 (2, 1)
	83 invokespecial (2, 1)
	84 org/apache/commons/math3/stat/regression/MillerUpdatingRegression.include:([DDD)V (2, 1)
	86 goto (2, 1)
	87 34 (2, 1)
	89 aload_1 (3, 2)
	90 arraylength (3, 2)
	91 iconst_1 (3, 2)
	92 iadd (3, 2)
	93 newarray (3, 2)
	94 7 (3, 2)
	95 astore (3, 2)
	96 #4 (3, 2)
	97 aload_1 (3, 2)
	98 iconst_0 (3, 2)
	99 aload (3, 2)
	100 #4 (3, 2)
	101 iconst_1 (3, 2)
	102 aload_1 (3, 2)
	103 arraylength (3, 2)
	104 invokestatic (3, 2)
	105 java/lang/System.arraycopy:(Ljava/lang/Object;ILjava/lang/Object;II)V (3, 2)
	107 aload (3, 2)
	108 #4 (3, 2)
	109 iconst_0 (3, 2)
	110 dconst_1 (3, 2)
	111 dastore (3, 2)
	112 aload_0 (3, 2)
	113 aload (3, 2)
	114 #4 (3, 2)
	115 dconst_1 (3, 2)
	116 dload_2 (3, 2)
	117 invokespecial (3, 2)
	118 org/apache/commons/math3/stat/regression/MillerUpdatingRegression.include:([DDD)V (3, 2)
	120 aload_0 (1, 1)
	121 dup (1, 1)
	122 getfield (1, 1)
	123 org/apache/commons/math3/stat/regression/MillerUpdatingRegression.nobs:J (1, 1)
	125 lconst_1 (1, 1)
	126 ladd (1, 1)
	127 putfield (1, 1)
	128 org/apache/commons/math3/stat/regression/MillerUpdatingRegression.nobs:J (1, 1)
	130 return (0, 1)

Method: addObservations
	0 aload_1 (1, 1)
	1 ifnull (1, 1)
	2 14 (1, 1)
	4 aload_2 (1, 1)
	5 ifnull (1, 1)
	6 10 (1, 1)
	8 aload_1 (1, 1)
	9 arraylength (1, 1)
	10 aload_2 (1, 1)
	11 arraylength (1, 1)
	12 if_icmpeq (1, 1)
	13 50 (1, 1)
	15 new (2, 1)
	16 org/apache/commons/math3/stat/regression/ModelSpecificationException (2, 1)
	18 dup (2, 1)
	19 getstatic (2, 1)
	20 org/apache/commons/math3/exception/util/LocalizedFormats.DIMENSIONS_MISMATCH_SIMPLE:Lorg/apache/commons/math3/exception/util/LocalizedFormats; (2, 1)
	22 iconst_2 (2, 1)
	23 anewarray (2, 1)
	24 java/lang/Object (2, 1)
	26 dup (2, 1)
	27 iconst_0 (2, 1)
	28 aload_1 (2, 1)
	29 ifnonnull (2, 1)
	30 7 (2, 1)
	32 iconst_0 (2, 1)
	33 goto (2, 1)
	34 5 (2, 1)
	36 aload_1 (2, 1)
	37 arraylength (2, 1)
	38 invokestatic (2, 1)
	39 java/lang/Integer.valueOf:(I)Ljava/lang/Integer; (2, 1)
	41 aastore (2, 1)
	42 dup (2, 1)
	43 iconst_1 (2, 1)
	44 aload_2 (2, 1)
	45 ifnonnull (2, 1)
	46 7 (2, 1)
	48 iconst_0 (2, 1)
	49 goto (2, 1)
	50 5 (2, 1)
	52 aload_2 (2, 1)
	53 arraylength (2, 1)
	54 invokestatic (2, 1)
	55 java/lang/Integer.valueOf:(I)Ljava/lang/Integer; (2, 1)
	57 aastore (2, 1)
	58 invokespecial (2, 1)
	59 org/apache/commons/math3/stat/regression/ModelSpecificationException.<init>:(Lorg/apache/commons/math3/exception/util/Localizable;[Ljava/lang/Object;)V (2, 1)
	61 athrow (2, 1)
	62 aload_1 (1, 1)
	63 arraylength (1, 1)
	64 ifne (1, 1)
	65 18 (1, 1)
	67 new (2, 1)
	68 org/apache/commons/math3/stat/regression/ModelSpecificationException (2, 1)
	70 dup (2, 1)
	71 getstatic (2, 1)
	72 org/apache/commons/math3/exception/util/LocalizedFormats.NO_DATA:Lorg/apache/commons/math3/exception/util/LocalizedFormats; (2, 1)
	74 iconst_0 (2, 1)
	75 anewarray (2, 1)
	76 java/lang/Object (2, 1)
	78 invokespecial (2, 1)
	79 org/apache/commons/math3/stat/regression/ModelSpecificationException.<init>:(Lorg/apache/commons/math3/exception/util/Localizable;[Ljava/lang/Object;)V (2, 1)
	81 athrow (2, 1)
	82 aload_1 (1, 1)
	83 iconst_0 (1, 1)
	84 aaload (1, 1)
	85 arraylength (1, 1)
	86 iconst_1 (1, 1)
	87 iadd (1, 1)
	88 aload_1 (1, 1)
	89 arraylength (1, 1)
	90 if_icmple (1, 1)
	91 36 (1, 1)
	93 new (2, 1)
	94 org/apache/commons/math3/stat/regression/ModelSpecificationException (2, 1)
	96 dup (2, 1)
	97 getstatic (2, 1)
	98 org/apache/commons/math3/exception/util/LocalizedFormats.NOT_ENOUGH_DATA_FOR_NUMBER_OF_PREDICTORS:Lorg/apache/commons/math3/exception/util/LocalizedFormats; (2, 1)
	100 iconst_2 (2, 1)
	101 anewarray (2, 1)
	102 java/lang/Object (2, 1)
	104 dup (2, 1)
	105 iconst_0 (2, 1)
	106 aload_1 (2, 1)
	107 arraylength (2, 1)
	108 invokestatic (2, 1)
	109 java/lang/Integer.valueOf:(I)Ljava/lang/Integer; (2, 1)
	111 aastore (2, 1)
	112 dup (2, 1)
	113 iconst_1 (2, 1)
	114 aload_1 (2, 1)
	115 iconst_0 (2, 1)
	116 aaload (2, 1)
	117 arraylength (2, 1)
	118 invokestatic (2, 1)
	119 java/lang/Integer.valueOf:(I)Ljava/lang/Integer; (2, 1)
	121 aastore (2, 1)
	122 invokespecial (2, 1)
	123 org/apache/commons/math3/stat/regression/ModelSpecificationException.<init>:(Lorg/apache/commons/math3/exception/util/Localizable;[Ljava/lang/Object;)V (2, 1)
	125 athrow (2, 1)
	126 iconst_0 (1, 4)
	127 istore_3 (1, 4)
	128 iload_3 (1, 4)
	129 aload_1 (1, 4)
	130 arraylength (1, 4)
	131 if_icmpge (1, 4)
	132 19 (1, 4)
	134 aload_0 (1, 4)
	135 aload_1 (1, 4)
	136 iload_3 (1, 4)
	137 aaload (1, 4)
	138 aload_2 (1, 4)
	139 iload_3 (1, 4)
	140 daload (1, 4)
	141 invokevirtual (1, 4)
	142 org/apache/commons/math3/stat/regression/MillerUpdatingRegression.addObservation:([DD)V (1, 4)
	144 iinc (1, 4)
	145 #3 (1, 4)
	146 -89 (1, 4)
	147 goto (1, 4)
	148 -19 (1, 4)
	150 return (0, 0)

Method: include
	0 iconst_0 (0, 0)
	1 istore (0, 0)
	2 #6 (0, 0)
	3 dload_2 (0, 0)
	4 dstore (0, 0)
	5 #7 (0, 0)
	6 dload (0, 0)
	7 #4 (0, 0)
	8 dstore (0, 0)
	9 #9 (0, 0)
	10 aload_0 (0, 0)
	11 iconst_0 (0, 0)
	12 putfield (0, 0)
	13 org/apache/commons/math3/stat/regression/MillerUpdatingRegression.rss_set:Z (0, 0)
	15 aload_0 (0, 0)
	16 aload_0 (0, 0)
	17 dload (0, 0)
	18 #4 (0, 0)
	19 aload_0 (0, 0)
	20 getfield (0, 0)
	21 org/apache/commons/math3/stat/regression/MillerUpdatingRegression.sumy:D (0, 0)
	23 invokespecial (0, 0)
	24 org/apache/commons/math3/stat/regression/MillerUpdatingRegression.smartAdd:(DD)D (0, 0)
	26 putfield (0, 0)
	27 org/apache/commons/math3/stat/regression/MillerUpdatingRegression.sumy:D (0, 0)
	29 aload_0 (0, 0)
	30 aload_0 (0, 0)
	31 aload_0 (0, 0)
	32 getfield (0, 0)
	33 org/apache/commons/math3/stat/regression/MillerUpdatingRegression.sumsqy:D (0, 0)
	35 dload (0, 0)
	36 #4 (0, 0)
	37 dload (0, 0)
	38 #4 (0, 0)
	39 dmul (0, 0)
	40 invokespecial (0, 0)
	41 org/apache/commons/math3/stat/regression/MillerUpdatingRegression.smartAdd:(DD)D (0, 0)
	43 putfield (0, 0)
	44 org/apache/commons/math3/stat/regression/MillerUpdatingRegression.sumsqy:D (0, 0)
	46 iconst_0 (1, 4)
	47 istore (1, 4)
	48 #23 (1, 4)
	49 iload (1, 4)
	50 #23 (1, 4)
	51 aload_1 (1, 4)
	52 arraylength (1, 4)
	53 if_icmpge (1, 4)
	54 320 (1, 4)
	56 dload (2, 1)
	57 #7 (2, 1)
	58 dconst_0 (2, 1)
	59 dcmpl (2, 1)
	60 ifne (2, 1)
	61 4 (2, 1)
	63 return (2, 1)
	64 aload_1 (1, 4)
	65 iload (1, 4)
	66 #23 (1, 4)
	67 daload (1, 4)
	68 dstore (1, 4)
	69 #11 (1, 4)
	70 dload (2, 1)
	71 #11 (2, 1)
	72 dconst_0 (2, 1)
	73 dcmpl (2, 1)
	74 ifne (2, 1)
	75 20 (2, 1)
	77 iload (2, 1)
	78 #6 (2, 1)
	79 aload_0 (2, 1)
	80 getfield (2, 1)
	81 org/apache/commons/math3/stat/regression/MillerUpdatingRegression.nvars:I (2, 1)
	83 iload (2, 1)
	84 #23 (2, 1)
	85 isub (2, 1)
	86 iconst_1 (2, 1)
	87 isub (2, 1)
	88 iadd (2, 1)
	89 istore (2, 1)
	90 #6 (2, 1)
	91 goto (2, 1)
	92 276 (2, 1)
	94 aload_0 (1, 4)
	95 getfield (1, 4)
	96 org/apache/commons/math3/stat/regression/MillerUpdatingRegression.d:[D (1, 4)
	98 iload (1, 4)
	99 #23 (1, 4)
	100 daload (1, 4)
	101 dstore (1, 4)
	102 #13 (1, 4)
	103 dload (1, 4)
	104 #7 (1, 4)
	105 dload (1, 4)
	106 #11 (1, 4)
	107 dmul (1, 4)
	108 dstore (1, 4)
	109 #15 (1, 4)
	110 dload (1, 4)
	111 #7 (1, 4)
	112 dstore (1, 4)
	113 #21 (1, 4)
	114 dload (2, 1)
	115 #13 (2, 1)
	116 dconst_0 (2, 1)
	117 dcmpl (2, 1)
	118 ifeq (2, 1)
	119 51 (2, 1)
	121 aload_0 (2, 1)
	122 dload (2, 1)
	123 #13 (2, 1)
	124 dload (2, 1)
	125 #15 (2, 1)
	126 dload (2, 1)
	127 #11 (2, 1)
	128 dmul (2, 1)
	129 invokespecial (2, 1)
	130 org/apache/commons/math3/stat/regression/MillerUpdatingRegression.smartAdd:(DD)D (2, 1)
	132 dstore (2, 1)
	133 #17 (2, 1)
	134 dload (2, 1)
	135 #15 (2, 1)
	136 dload (2, 1)
	137 #11 (2, 1)
	138 dmul (2, 1)
	139 dload (2, 1)
	140 #13 (2, 1)
	141 ddiv (2, 1)
	142 dstore (2, 1)
	143 #24 (2, 1)
	144 dload (3, 1)
	145 #24 (3, 1)
	146 invokestatic (3, 1)
	147 org/apache/commons/math3/util/FastMath.abs:(D)D (3, 1)
	149 getstatic (3, 1)
	150 org/apache/commons/math3/util/Precision.EPSILON:D (3, 1)
	152 dcmpl (3, 1)
	153 ifle (3, 1)
	154 13 (3, 1)
	156 dload (3, 1)
	157 #13 (3, 1)
	158 dload (3, 1)
	159 #7 (3, 1)
	160 dmul (3, 1)
	161 dload (3, 1)
	162 #17 (3, 1)
	163 ddiv (3, 1)
	164 dstore (3, 1)
	165 #7 (3, 1)
	166 goto (3, 2)
	167 13 (3, 2)
	169 dload (3, 2)
	170 #15 (3, 2)
	171 dload (3, 2)
	172 #11 (3, 2)
	173 dmul (3, 2)
	174 dstore (3, 2)
	175 #17 (3, 2)
	176 dconst_0 (3, 2)
	177 dstore (3, 2)
	178 #7 (3, 2)
	179 aload_0 (1, 4)
	180 getfield (1, 4)
	181 org/apache/commons/math3/stat/regression/MillerUpdatingRegression.d:[D (1, 4)
	183 iload (1, 4)
	184 #23 (1, 4)
	185 dload (1, 4)
	186 #17 (1, 4)
	187 dastore (1, 4)
	188 iload (2, 4)
	189 #23 (2, 4)
	190 iconst_1 (2, 4)
	191 iadd (2, 4)
	192 istore (2, 4)
	193 #24 (2, 4)
	194 iload (2, 4)
	195 #24 (2, 4)
	196 aload_0 (2, 4)
	197 getfield (2, 4)
	198 org/apache/commons/math3/stat/regression/MillerUpdatingRegression.nvars:I (2, 4)
	200 if_icmpge (2, 4)
	201 93 (2, 4)
	203 aload_1 (2, 4)
	204 iload (2, 4)
	205 #24 (2, 4)
	206 daload (2, 4)
	207 dstore (2, 4)
	208 #19 (2, 4)
	209 aload_1 (2, 4)
	210 iload (2, 4)
	211 #24 (2, 4)
	212 aload_0 (2, 4)
	213 dload (2, 4)
	214 #19 (2, 4)
	215 dload (2, 4)
	216 #11 (2, 4)
	217 dneg (2, 4)
	218 aload_0 (2, 4)
	219 getfield (2, 4)
	220 org/apache/commons/math3/stat/regression/MillerUpdatingRegression.r:[D (2, 4)
	222 iload (2, 4)
	223 #6 (2, 4)
	224 daload (2, 4)
	225 dmul (2, 4)
	226 invokespecial (2, 4)
	227 org/apache/commons/math3/stat/regression/MillerUpdatingRegression.smartAdd:(DD)D (2, 4)
	229 dastore (2, 4)
	230 dload (3, 1)
	231 #13 (3, 1)
	232 dconst_0 (3, 1)
	233 dcmpl (3, 1)
	234 ifeq (3, 1)
	235 38 (3, 1)
	237 aload_0 (3, 1)
	238 getfield (3, 1)
	239 org/apache/commons/math3/stat/regression/MillerUpdatingRegression.r:[D (3, 1)
	241 iload (3, 1)
	242 #6 (3, 1)
	243 aload_0 (3, 1)
	244 dload (3, 1)
	245 #13 (3, 1)
	246 aload_0 (3, 1)
	247 getfield (3, 1)
	248 org/apache/commons/math3/stat/regression/MillerUpdatingRegression.r:[D (3, 1)
	250 iload (3, 1)
	251 #6 (3, 1)
	252 daload (3, 1)
	253 dmul (3, 1)
	254 dload (3, 1)
	255 #21 (3, 1)
	256 dload (3, 1)
	257 #11 (3, 1)
	258 dmul (3, 1)
	259 dload (3, 1)
	260 #19 (3, 1)
	261 dmul (3, 1)
	262 invokespecial (3, 1)
	263 org/apache/commons/math3/stat/regression/MillerUpdatingRegression.smartAdd:(DD)D (3, 1)
	265 dload (3, 1)
	266 #17 (3, 1)
	267 ddiv (3, 1)
	268 dastore (3, 1)
	269 goto (3, 1)
	270 15 (3, 1)
	272 aload_0 (4, 2)
	273 getfield (4, 2)
	274 org/apache/commons/math3/stat/regression/MillerUpdatingRegression.r:[D (4, 2)
	276 iload (4, 2)
	277 #6 (4, 2)
	278 dload (4, 2)
	279 #19 (4, 2)
	280 dload (4, 2)
	281 #11 (4, 2)
	282 ddiv (4, 2)
	283 dastore (4, 2)
	284 iinc (2, 4)
	285 #6 (2, 4)
	286 -124 (2, 4)
	287 iinc (2, 4)
	288 #24 (2, 4)
	289 -89 (2, 4)
	290 goto (2, 4)
	291 -96 (2, 4)
	293 dload (1, 4)
	294 #9 (1, 4)
	295 dstore (1, 4)
	296 #19 (1, 4)
	297 aload_0 (1, 4)
	298 dload (1, 4)
	299 #19 (1, 4)
	300 dload (1, 4)
	301 #11 (1, 4)
	302 dneg (1, 4)
	303 aload_0 (1, 4)
	304 getfield (1, 4)
	305 org/apache/commons/math3/stat/regression/MillerUpdatingRegression.rhs:[D (1, 4)
	307 iload (1, 4)
	308 #23 (1, 4)
	309 daload (1, 4)
	310 dmul (1, 4)
	311 invokespecial (1, 4)
	312 org/apache/commons/math3/stat/regression/MillerUpdatingRegression.smartAdd:(DD)D (1, 4)
	314 dstore (1, 4)
	315 #9 (1, 4)
	316 dload (2, 1)
	317 #13 (2, 1)
	318 dconst_0 (2, 1)
	319 dcmpl (2, 1)
	320 ifeq (2, 1)
	321 35 (2, 1)
	323 aload_0 (2, 1)
	324 getfield (2, 1)
	325 org/apache/commons/math3/stat/regression/MillerUpdatingRegression.rhs:[D (2, 1)
	327 iload (2, 1)
	328 #23 (2, 1)
	329 aload_0 (2, 1)
	330 dload (2, 1)
	331 #13 (2, 1)
	332 aload_0 (2, 1)
	333 getfield (2, 1)
	334 org/apache/commons/math3/stat/regression/MillerUpdatingRegression.rhs:[D (2, 1)
	336 iload (2, 1)
	337 #23 (2, 1)
	338 daload (2, 1)
	339 dmul (2, 1)
	340 dload (2, 1)
	341 #15 (2, 1)
	342 dload (2, 1)
	343 #19 (2, 1)
	344 dmul (2, 1)
	345 invokespecial (2, 1)
	346 org/apache/commons/math3/stat/regression/MillerUpdatingRegression.smartAdd:(DD)D (2, 1)
	348 dload (2, 1)
	349 #17 (2, 1)
	350 ddiv (2, 1)
	351 dastore (2, 1)
	352 goto (2, 1)
	353 15 (2, 1)
	355 aload_0 (3, 2)
	356 getfield (3, 2)
	357 org/apache/commons/math3/stat/regression/MillerUpdatingRegression.rhs:[D (3, 2)
	359 iload (3, 2)
	360 #23 (3, 2)
	361 dload (3, 2)
	362 #19 (3, 2)
	363 dload (3, 2)
	364 #11 (3, 2)
	365 ddiv (3, 2)
	366 dastore (3, 2)
	367 iinc (3, 2)
	368 #23 (3, 2)
	369 -89 (3, 2)
	370 goto (3, 2)
	371 -321 (3, 2)
	373 aload_0 (1, 4)
	374 aload_0 (1, 4)
	375 aload_0 (1, 4)
	376 getfield (1, 4)
	377 org/apache/commons/math3/stat/regression/MillerUpdatingRegression.sserr:D (1, 4)
	379 dload (1, 4)
	380 #7 (1, 4)
	381 dload (1, 4)
	382 #9 (1, 4)
	383 dmul (1, 4)
	384 dload (1, 4)
	385 #9 (1, 4)
	386 dmul (1, 4)
	387 invokespecial (1, 4)
	388 org/apache/commons/math3/stat/regression/MillerUpdatingRegression.smartAdd:(DD)D (1, 4)
	390 putfield (1, 4)
	391 org/apache/commons/math3/stat/regression/MillerUpdatingRegression.sserr:D (1, 4)
	393 return (0, 0)

Method: smartAdd
	0 dload_1 (0, 0)
	1 invokestatic (0, 0)
	2 org/apache/commons/math3/util/FastMath.abs:(D)D (0, 0)
	4 dstore (0, 0)
	5 #5 (0, 0)
	6 dload_3 (0, 0)
	7 invokestatic (0, 0)
	8 org/apache/commons/math3/util/FastMath.abs:(D)D (0, 0)
	10 dstore (0, 0)
	11 #7 (0, 0)
	12 dload (1, 1)
	13 #5 (1, 1)
	14 dload (1, 1)
	15 #7 (1, 1)
	16 dcmpl (1, 1)
	17 ifle (1, 1)
	18 25 (1, 1)
	20 dload (1, 1)
	21 #5 (1, 1)
	22 getstatic (1, 1)
	23 org/apache/commons/math3/util/Precision.EPSILON:D (1, 1)
	25 dmul (1, 1)
	26 dstore (1, 1)
	27 #9 (1, 1)
	28 dload (2, 1)
	29 #7 (2, 1)
	30 dload (2, 1)
	31 #9 (2, 1)
	32 dcmpl (2, 1)
	33 ifle (2, 1)
	34 7 (2, 1)
	36 dload_1 (2, 1)
	37 dload_3 (2, 1)
	38 dadd (2, 1)
	39 dreturn (2, 1)
	40 dload_1 (1, 1)
	41 dreturn (1, 1)
	42 dload (2, 2)
	43 #7 (2, 2)
	44 getstatic (2, 2)
	45 org/apache/commons/math3/util/Precision.EPSILON:D (2, 2)
	47 dmul (2, 2)
	48 dstore (2, 2)
	49 #9 (2, 2)
	50 dload (3, 1)
	51 #5 (3, 1)
	52 dload (3, 1)
	53 #9 (3, 1)
	54 dcmpl (3, 1)
	55 ifle (3, 1)
	56 7 (3, 1)
	58 dload_1 (3, 1)
	59 dload_3 (3, 1)
	60 dadd (3, 1)
	61 dreturn (3, 1)
	62 dload_3 (2, 2)
	63 dreturn (1, 2)

Method: clear
	0 aload_0 (0, 0)
	1 getfield (0, 0)
	2 org/apache/commons/math3/stat/regression/MillerUpdatingRegression.d:[D (0, 0)
	4 dconst_0 (0, 0)
	5 invokestatic (0, 0)
	6 java/util/Arrays.fill:([DD)V (0, 0)
	8 aload_0 (0, 0)
	9 getfield (0, 0)
	10 org/apache/commons/math3/stat/regression/MillerUpdatingRegression.rhs:[D (0, 0)
	12 dconst_0 (0, 0)
	13 invokestatic (0, 0)
	14 java/util/Arrays.fill:([DD)V (0, 0)
	16 aload_0 (0, 0)
	17 getfield (0, 0)
	18 org/apache/commons/math3/stat/regression/MillerUpdatingRegression.r:[D (0, 0)
	20 dconst_0 (0, 0)
	21 invokestatic (0, 0)
	22 java/util/Arrays.fill:([DD)V (0, 0)
	24 aload_0 (0, 0)
	25 getfield (0, 0)
	26 org/apache/commons/math3/stat/regression/MillerUpdatingRegression.tol:[D (0, 0)
	28 dconst_0 (0, 0)
	29 invokestatic (0, 0)
	30 java/util/Arrays.fill:([DD)V (0, 0)
	32 aload_0 (0, 0)
	33 getfield (0, 0)
	34 org/apache/commons/math3/stat/regression/MillerUpdatingRegression.rss:[D (0, 0)
	36 dconst_0 (0, 0)
	37 invokestatic (0, 0)
	38 java/util/Arrays.fill:([DD)V (0, 0)
	40 aload_0 (0, 0)
	41 getfield (0, 0)
	42 org/apache/commons/math3/stat/regression/MillerUpdatingRegression.work_tolset:[D (0, 0)
	44 dconst_0 (0, 0)
	45 invokestatic (0, 0)
	46 java/util/Arrays.fill:([DD)V (0, 0)
	48 aload_0 (0, 0)
	49 getfield (0, 0)
	50 org/apache/commons/math3/stat/regression/MillerUpdatingRegression.work_sing:[D (0, 0)
	52 dconst_0 (0, 0)
	53 invokestatic (0, 0)
	54 java/util/Arrays.fill:([DD)V (0, 0)
	56 aload_0 (0, 0)
	57 getfield (0, 0)
	58 org/apache/commons/math3/stat/regression/MillerUpdatingRegression.x_sing:[D (0, 0)
	60 dconst_0 (0, 0)
	61 invokestatic (0, 0)
	62 java/util/Arrays.fill:([DD)V (0, 0)
	64 aload_0 (0, 0)
	65 getfield (0, 0)
	66 org/apache/commons/math3/stat/regression/MillerUpdatingRegression.lindep:[Z (0, 0)
	68 iconst_0 (0, 0)
	69 invokestatic (0, 0)
	70 java/util/Arrays.fill:([ZZ)V (0, 0)
	72 iconst_0 (1, 4)
	73 istore_1 (1, 4)
	74 iload_1 (1, 4)
	75 aload_0 (1, 4)
	76 getfield (1, 4)
	77 org/apache/commons/math3/stat/regression/MillerUpdatingRegression.nvars:I (1, 4)
	79 if_icmpge (1, 4)
	80 16 (1, 4)
	82 aload_0 (1, 4)
	83 getfield (1, 4)
	84 org/apache/commons/math3/stat/regression/MillerUpdatingRegression.vorder:[I (1, 4)
	86 iload_1 (1, 4)
	87 iload_1 (1, 4)
	88 iastore (1, 4)
	89 iinc (1, 4)
	90 #1 (1, 4)
	91 -89 (1, 4)
	92 goto (1, 4)
	93 -18 (1, 4)
	95 aload_0 (0, 0)
	96 lconst_0 (0, 0)
	97 putfield (0, 0)
	98 org/apache/commons/math3/stat/regression/MillerUpdatingRegression.nobs:J (0, 0)
	100 aload_0 (0, 0)
	101 dconst_0 (0, 0)
	102 putfield (0, 0)
	103 org/apache/commons/math3/stat/regression/MillerUpdatingRegression.sserr:D (0, 0)
	105 aload_0 (0, 0)
	106 dconst_0 (0, 0)
	107 putfield (0, 0)
	108 org/apache/commons/math3/stat/regression/MillerUpdatingRegression.sumy:D (0, 0)
	110 aload_0 (0, 0)
	111 dconst_0 (0, 0)
	112 putfield (0, 0)
	113 org/apache/commons/math3/stat/regression/MillerUpdatingRegression.sumsqy:D (0, 0)
	115 aload_0 (0, 0)
	116 iconst_0 (0, 0)
	117 putfield (0, 0)
	118 org/apache/commons/math3/stat/regression/MillerUpdatingRegression.rss_set:Z (0, 0)
	120 aload_0 (0, 0)
	121 iconst_0 (0, 0)
	122 putfield (0, 0)
	123 org/apache/commons/math3/stat/regression/MillerUpdatingRegression.tol_set:Z (0, 0)
	125 return (0, 0)

Method: tolset
	0 aload_0 (0, 0)
	1 getfield (0, 0)
	2 org/apache/commons/math3/stat/regression/MillerUpdatingRegression.epsilon:D (0, 0)
	4 dstore (0, 0)
	5 #4 (0, 0)
	6 iconst_0 (1, 4)
	7 istore (1, 4)
	8 #6 (1, 4)
	9 iload (1, 4)
	10 #6 (1, 4)
	11 aload_0 (1, 4)
	12 getfield (1, 4)
	13 org/apache/commons/math3/stat/regression/MillerUpdatingRegression.nvars:I (1, 4)
	15 if_icmpge (1, 4)
	16 26 (1, 4)
	18 aload_0 (1, 4)
	19 getfield (1, 4)
	20 org/apache/commons/math3/stat/regression/MillerUpdatingRegression.work_tolset:[D (1, 4)
	22 iload (1, 4)
	23 #6 (1, 4)
	24 aload_0 (1, 4)
	25 getfield (1, 4)
	26 org/apache/commons/math3/stat/regression/MillerUpdatingRegression.d:[D (1, 4)
	28 iload (1, 4)
	29 #6 (1, 4)
	30 daload (1, 4)
	31 invokestatic (1, 4)
	32 org/apache/commons/math3/util/FastMath.sqrt:(D)D (1, 4)
	34 dastore (1, 4)
	35 iinc (1, 4)
	36 #6 (1, 4)
	37 -89 (1, 4)
	38 goto (1, 4)
	39 -29 (1, 4)
	41 aload_0 (0, 0)
	42 getfield (0, 0)
	43 org/apache/commons/math3/stat/regression/MillerUpdatingRegression.tol:[D (0, 0)
	45 iconst_0 (0, 0)
	46 dload (0, 0)
	47 #4 (0, 0)
	48 aload_0 (0, 0)
	49 getfield (0, 0)
	50 org/apache/commons/math3/stat/regression/MillerUpdatingRegression.work_tolset:[D (0, 0)
	52 iconst_0 (0, 0)
	53 daload (0, 0)
	54 dmul (0, 0)
	55 dastore (0, 0)
	56 iconst_1 (1, 4)
	57 istore (1, 4)
	58 #6 (1, 4)
	59 iload (1, 4)
	60 #6 (1, 4)
	61 aload_0 (1, 4)
	62 getfield (1, 4)
	63 org/apache/commons/math3/stat/regression/MillerUpdatingRegression.nvars:I (1, 4)
	65 if_icmpge (1, 4)
	66 81 (1, 4)
	68 iload (1, 4)
	69 #6 (1, 4)
	70 iconst_1 (1, 4)
	71 isub (1, 4)
	72 istore_1 (1, 4)
	73 aload_0 (1, 4)
	74 getfield (1, 4)
	75 org/apache/commons/math3/stat/regression/MillerUpdatingRegression.work_tolset:[D (1, 4)
	77 iload (1, 4)
	78 #6 (1, 4)
	79 daload (1, 4)
	80 dstore_2 (1, 4)
	81 iconst_0 (2, 4)
	82 istore (2, 4)
	83 #7 (2, 4)
	84 iload (2, 4)
	85 #7 (2, 4)
	86 iload (2, 4)
	87 #6 (2, 4)
	88 if_icmpge (2, 4)
	89 41 (2, 4)
	91 dload_2 (2, 4)
	92 aload_0 (2, 4)
	93 getfield (2, 4)
	94 org/apache/commons/math3/stat/regression/MillerUpdatingRegression.r:[D (2, 4)
	96 iload_1 (2, 4)
	97 daload (2, 4)
	98 invokestatic (2, 4)
	99 org/apache/commons/math3/util/FastMath.abs:(D)D (2, 4)
	101 aload_0 (2, 4)
	102 getfield (2, 4)
	103 org/apache/commons/math3/stat/regression/MillerUpdatingRegression.work_tolset:[D (2, 4)
	105 iload (2, 4)
	106 #7 (2, 4)
	107 daload (2, 4)
	108 dmul (2, 4)
	109 dadd (2, 4)
	110 dstore_2 (2, 4)
	111 iload_1 (2, 4)
	112 aload_0 (2, 4)
	113 getfield (2, 4)
	114 org/apache/commons/math3/stat/regression/MillerUpdatingRegression.nvars:I (2, 4)
	116 iload (2, 4)
	117 #7 (2, 4)
	118 isub (2, 4)
	119 iconst_2 (2, 4)
	120 isub (2, 4)
	121 iadd (2, 4)
	122 istore_1 (2, 4)
	123 iinc (2, 4)
	124 #7 (2, 4)
	125 -89 (2, 4)
	126 goto (2, 4)
	127 -42 (2, 4)
	129 aload_0 (1, 4)
	130 getfield (1, 4)
	131 org/apache/commons/math3/stat/regression/MillerUpdatingRegression.tol:[D (1, 4)
	133 iload (1, 4)
	134 #6 (1, 4)
	135 dload (1, 4)
	136 #4 (1, 4)
	137 dload_2 (1, 4)
	138 dmul (1, 4)
	139 dastore (1, 4)
	140 iinc (1, 4)
	141 #6 (1, 4)
	142 -89 (1, 4)
	143 goto (1, 4)
	144 -84 (1, 4)
	146 aload_0 (0, 0)
	147 iconst_1 (0, 0)
	148 putfield (0, 0)
	149 org/apache/commons/math3/stat/regression/MillerUpdatingRegression.tol_set:Z (0, 0)
	151 return (0, 0)

Method: regcf
	0 iload_1 (1, 1)
	1 iconst_1 (1, 1)
	2 if_icmpge (1, 1)
	3 18 (1, 1)
	5 new (2, 1)
	6 org/apache/commons/math3/stat/regression/ModelSpecificationException (2, 1)
	8 dup (2, 1)
	9 getstatic (2, 1)
	10 org/apache/commons/math3/exception/util/LocalizedFormats.NO_REGRESSORS:Lorg/apache/commons/math3/exception/util/LocalizedFormats; (2, 1)
	12 iconst_0 (2, 1)
	13 anewarray (2, 1)
	14 java/lang/Object (2, 1)
	16 invokespecial (2, 1)
	17 org/apache/commons/math3/stat/regression/ModelSpecificationException.<init>:(Lorg/apache/commons/math3/exception/util/Localizable;[Ljava/lang/Object;)V (2, 1)
	19 athrow (2, 1)
	20 iload_1 (1, 1)
	21 aload_0 (1, 1)
	22 getfield (1, 1)
	23 org/apache/commons/math3/stat/regression/MillerUpdatingRegression.nvars:I (1, 1)
	25 if_icmple (1, 1)
	26 35 (1, 1)
	28 new (2, 1)
	29 org/apache/commons/math3/stat/regression/ModelSpecificationException (2, 1)
	31 dup (2, 1)
	32 getstatic (2, 1)
	33 org/apache/commons/math3/exception/util/LocalizedFormats.TOO_MANY_REGRESSORS:Lorg/apache/commons/math3/exception/util/LocalizedFormats; (2, 1)
	35 iconst_2 (2, 1)
	36 anewarray (2, 1)
	37 java/lang/Object (2, 1)
	39 dup (2, 1)
	40 iconst_0 (2, 1)
	41 iload_1 (2, 1)
	42 invokestatic (2, 1)
	43 java/lang/Integer.valueOf:(I)Ljava/lang/Integer; (2, 1)
	45 aastore (2, 1)
	46 dup (2, 1)
	47 iconst_1 (2, 1)
	48 aload_0 (2, 1)
	49 getfield (2, 1)
	50 org/apache/commons/math3/stat/regression/MillerUpdatingRegression.nvars:I (2, 1)
	52 invokestatic (2, 1)
	53 java/lang/Integer.valueOf:(I)Ljava/lang/Integer; (2, 1)
	55 aastore (2, 1)
	56 invokespecial (2, 1)
	57 org/apache/commons/math3/stat/regression/ModelSpecificationException.<init>:(Lorg/apache/commons/math3/exception/util/Localizable;[Ljava/lang/Object;)V (2, 1)
	59 athrow (2, 1)
	60 aload_0 (1, 1)
	61 getfield (1, 1)
	62 org/apache/commons/math3/stat/regression/MillerUpdatingRegression.tol_set:Z (1, 1)
	64 ifne (1, 1)
	65 7 (1, 1)
	67 aload_0 (1, 1)
	68 invokespecial (1, 1)
	69 org/apache/commons/math3/stat/regression/MillerUpdatingRegression.tolset:()V (1, 1)
	71 iload_1 (0, 0)
	72 newarray (0, 0)
	73 7 (0, 0)
	74 astore_3 (0, 0)
	75 iconst_0 (0, 0)
	76 istore (0, 0)
	77 #4 (0, 0)
	78 iload_1 (1, 4)
	79 iconst_1 (1, 4)
	80 isub (1, 4)
	81 istore (1, 4)
	82 #5 (1, 4)
	83 iload (1, 4)
	84 #5 (1, 4)
	85 iconst_m1 (1, 4)
	86 if_icmple (1, 4)
	87 125 (1, 4)
	89 aload_0 (2, 1)
	90 getfield (2, 1)
	91 org/apache/commons/math3/stat/regression/MillerUpdatingRegression.d:[D (2, 1)
	93 iload (2, 1)
	94 #5 (2, 1)
	95 daload (2, 1)
	96 invokestatic (2, 1)
	97 org/apache/commons/math3/util/FastMath.sqrt:(D)D (2, 1)
	99 aload_0 (2, 1)
	100 getfield (2, 1)
	101 org/apache/commons/math3/stat/regression/MillerUpdatingRegression.tol:[D (2, 1)
	103 iload (2, 1)
	104 #5 (2, 1)
	105 daload (2, 1)
	106 dcmpg (2, 1)
	107 ifge (2, 1)
	108 22 (2, 1)
	110 aload_3 (2, 1)
	111 iload (2, 1)
	112 #5 (2, 1)
	113 dconst_0 (2, 1)
	114 dastore (2, 1)
	115 aload_0 (2, 1)
	116 getfield (2, 1)
	117 org/apache/commons/math3/stat/regression/MillerUpdatingRegression.d:[D (2, 1)
	119 iload (2, 1)
	120 #5 (2, 1)
	121 dconst_0 (2, 1)
	122 dastore (2, 1)
	123 iconst_1 (2, 1)
	124 istore (2, 1)
	125 #4 (2, 1)
	126 goto (2, 1)
	127 79 (2, 1)
	129 aload_3 (3, 2)
	130 iload (3, 2)
	131 #5 (3, 2)
	132 aload_0 (3, 2)
	133 getfield (3, 2)
	134 org/apache/commons/math3/stat/regression/MillerUpdatingRegression.rhs:[D (3, 2)
	136 iload (3, 2)
	137 #5 (3, 2)
	138 daload (3, 2)
	139 dastore (3, 2)
	140 iload (3, 2)
	141 #5 (3, 2)
	142 aload_0 (3, 2)
	143 getfield (3, 2)
	144 org/apache/commons/math3/stat/regression/MillerUpdatingRegression.nvars:I (3, 2)
	146 aload_0 (3, 2)
	147 getfield (3, 2)
	148 org/apache/commons/math3/stat/regression/MillerUpdatingRegression.nvars:I (3, 2)
	150 iadd (3, 2)
	151 iload (3, 2)
	152 #5 (3, 2)
	153 isub (3, 2)
	154 iconst_1 (3, 2)
	155 isub (3, 2)
	156 imul (3, 2)
	157 iconst_2 (3, 2)
	158 idiv (3, 2)
	159 istore_2 (3, 2)
	160 iload (4, 4)
	161 #5 (4, 4)
	162 iconst_1 (4, 4)
	163 iadd (4, 4)
	164 istore (4, 4)
	165 #6 (4, 4)
	166 iload (4, 4)
	167 #6 (4, 4)
	168 iload_1 (4, 4)
	169 if_icmpge (4, 4)
	170 36 (4, 4)
	172 aload_3 (4, 4)
	173 iload (4, 4)
	174 #5 (4, 4)
	175 aload_0 (4, 4)
	176 aload_3 (4, 4)
	177 iload (4, 4)
	178 #5 (4, 4)
	179 daload (4, 4)
	180 aload_0 (4, 4)
	181 getfield (4, 4)
	182 org/apache/commons/math3/stat/regression/MillerUpdatingRegression.r:[D (4, 4)
	184 iload_2 (4, 4)
	185 daload (4, 4)
	186 dneg (4, 4)
	187 aload_3 (4, 4)
	188 iload (4, 4)
	189 #6 (4, 4)
	190 daload (4, 4)
	191 dmul (4, 4)
	192 invokespecial (4, 4)
	193 org/apache/commons/math3/stat/regression/MillerUpdatingRegression.smartAdd:(DD)D (4, 4)
	195 dastore (4, 4)
	196 iinc (4, 4)
	197 #2 (4, 4)
	198 -124 (4, 4)
	199 iinc (4, 4)
	200 #6 (4, 4)
	201 -89 (4, 4)
	202 goto (4, 4)
	203 -36 (4, 4)
	205 iinc (4, 4)
	206 #5 (4, 4)
	207 -89 (4, 4)
	208 goto (4, 4)
	209 -125 (4, 4)
	211 iload (4, 1)
	212 #4 (4, 1)
	213 ifeq (4, 1)
	214 35 (4, 1)
	216 iconst_0 (5, 4)
	217 istore (5, 4)
	218 #5 (5, 4)
	219 iload (5, 4)
	220 #5 (5, 4)
	221 iload_1 (5, 4)
	222 if_icmpge (5, 4)
	223 26 (5, 4)
	225 aload_0 (6, 1)
	226 getfield (6, 1)
	227 org/apache/commons/math3/stat/regression/MillerUpdatingRegression.lindep:[Z (6, 1)
	229 iload (6, 1)
	230 #5 (6, 1)
	231 baload (6, 1)
	232 ifeq (6, 1)
	233 10 (6, 1)
	235 aload_3 (6, 1)
	236 iload (6, 1)
	237 #5 (6, 1)
	238 ldc2_w (6, 1)
	239 nan (6, 1)
	241 dastore (6, 1)
	242 iinc (6, 1)
	243 #5 (6, 1)
	244 -89 (6, 1)
	245 goto (6, 1)
	246 -26 (6, 1)
	248 aload_3 (4, 1)
	249 areturn (3, 1)

Method: singcheck
	0 iconst_0 (1, 4)
	1 istore_2 (1, 4)
	2 iload_2 (1, 4)
	3 aload_0 (1, 4)
	4 getfield (1, 4)
	5 org/apache/commons/math3/stat/regression/MillerUpdatingRegression.nvars:I (1, 4)
	7 if_icmpge (1, 4)
	8 24 (1, 4)
	10 aload_0 (1, 4)
	11 getfield (1, 4)
	12 org/apache/commons/math3/stat/regression/MillerUpdatingRegression.work_sing:[D (1, 4)
	14 iload_2 (1, 4)
	15 aload_0 (1, 4)
	16 getfield (1, 4)
	17 org/apache/commons/math3/stat/regression/MillerUpdatingRegression.d:[D (1, 4)
	19 iload_2 (1, 4)
	20 daload (1, 4)
	21 invokestatic (1, 4)
	22 org/apache/commons/math3/util/FastMath.sqrt:(D)D (1, 4)
	24 dastore (1, 4)
	25 iinc (1, 4)
	26 #2 (1, 4)
	27 -89 (1, 4)
	28 goto (1, 4)
	29 -26 (1, 4)
	31 iconst_0 (1, 4)
	32 istore_2 (1, 4)
	33 iload_2 (1, 4)
	34 aload_0 (1, 4)
	35 getfield (1, 4)
	36 org/apache/commons/math3/stat/regression/MillerUpdatingRegression.nvars:I (1, 4)
	38 if_icmpge (1, 4)
	39 259 (1, 4)
	41 aload_0 (2, 1)
	42 getfield (2, 1)
	43 org/apache/commons/math3/stat/regression/MillerUpdatingRegression.tol:[D (2, 1)
	45 iload_2 (2, 1)
	46 daload (2, 1)
	47 dstore_3 (2, 1)
	48 iload_2 (2, 1)
	49 iconst_1 (2, 1)
	50 isub (2, 1)
	51 istore_1 (2, 1)
	52 iconst_0 (3, 4)
	53 istore (3, 4)
	54 #5 (3, 4)
	55 iload (3, 4)
	56 #5 (3, 4)
	57 iload_2 (3, 4)
	58 iconst_1 (3, 4)
	59 isub (3, 4)
	60 if_icmpge (3, 4)
	61 50 (3, 4)
	63 aload_0 (4, 1)
	64 getfield (4, 1)
	65 org/apache/commons/math3/stat/regression/MillerUpdatingRegression.r:[D (4, 1)
	67 iload_1 (4, 1)
	68 daload (4, 1)
	69 invokestatic (4, 1)
	70 org/apache/commons/math3/util/FastMath.abs:(D)D (4, 1)
	72 aload_0 (4, 1)
	73 getfield (4, 1)
	74 org/apache/commons/math3/stat/regression/MillerUpdatingRegression.work_sing:[D (4, 1)
	76 iload (4, 1)
	77 #5 (4, 1)
	78 daload (4, 1)
	79 dmul (4, 1)
	80 dload_3 (4, 1)
	81 dcmpg (4, 1)
	82 ifge (4, 1)
	83 10 (4, 1)
	85 aload_0 (4, 1)
	86 getfield (4, 1)
	87 org/apache/commons/math3/stat/regression/MillerUpdatingRegression.r:[D (4, 1)
	89 iload_1 (4, 1)
	90 dconst_0 (4, 1)
	91 dastore (4, 1)
	92 iload_1 (3, 4)
	93 aload_0 (3, 4)
	94 getfield (3, 4)
	95 org/apache/commons/math3/stat/regression/MillerUpdatingRegression.nvars:I (3, 4)
	97 iload (3, 4)
	98 #5 (3, 4)
	99 isub (3, 4)
	100 iconst_2 (3, 4)
	101 isub (3, 4)
	102 iadd (3, 4)
	103 istore_1 (3, 4)
	104 iinc (3, 4)
	105 #5 (3, 4)
	106 -89 (3, 4)
	107 goto (3, 4)
	108 -52 (3, 4)
	110 aload_0 (2, 1)
	111 getfield (2, 1)
	112 org/apache/commons/math3/stat/regression/MillerUpdatingRegression.lindep:[Z (2, 1)
	114 iload_2 (2, 1)
	115 iconst_0 (2, 1)
	116 bastore (2, 1)
	117 aload_0 (3, 1)
	118 getfield (3, 1)
	119 org/apache/commons/math3/stat/regression/MillerUpdatingRegression.work_sing:[D (3, 1)
	121 iload_2 (3, 1)
	122 daload (3, 1)
	123 dload_3 (3, 1)
	124 dcmpg (3, 1)
	125 ifge (3, 1)
	126 166 (3, 1)
	128 aload_0 (3, 1)
	129 getfield (3, 1)
	130 org/apache/commons/math3/stat/regression/MillerUpdatingRegression.lindep:[Z (3, 1)
	132 iload_2 (3, 1)
	133 iconst_1 (3, 1)
	134 bastore (3, 1)
	135 iload_2 (4, 1)
	136 aload_0 (4, 1)
	137 getfield (4, 1)
	138 org/apache/commons/math3/stat/regression/MillerUpdatingRegression.nvars:I (4, 1)
	140 iconst_1 (4, 1)
	141 isub (4, 1)
	142 if_icmpge (4, 1)
	143 120 (4, 1)
	145 aload_0 (4, 1)
	146 getfield (4, 1)
	147 org/apache/commons/math3/stat/regression/MillerUpdatingRegression.x_sing:[D (4, 1)
	149 dconst_0 (4, 1)
	150 invokestatic (4, 1)
	151 java/util/Arrays.fill:([DD)V (4, 1)
	153 iload_2 (4, 1)
	154 aload_0 (4, 1)
	155 getfield (4, 1)
	156 org/apache/commons/math3/stat/regression/MillerUpdatingRegression.nvars:I (4, 1)
	158 aload_0 (4, 1)
	159 getfield (4, 1)
	160 org/apache/commons/math3/stat/regression/MillerUpdatingRegression.nvars:I (4, 1)
	162 iadd (4, 1)
	163 iload_2 (4, 1)
	164 isub (4, 1)
	165 iconst_1 (4, 1)
	166 isub (4, 1)
	167 imul (4, 1)
	168 iconst_2 (4, 1)
	169 idiv (4, 1)
	170 istore (4, 1)
	171 #5 (4, 1)
	172 iload_2 (5, 4)
	173 iconst_1 (5, 4)
	174 iadd (5, 4)
	175 istore (5, 4)
	176 #6 (5, 4)
	177 iload (5, 4)
	178 #6 (5, 4)
	179 aload_0 (5, 4)
	180 getfield (5, 4)
	181 org/apache/commons/math3/stat/regression/MillerUpdatingRegression.nvars:I (5, 4)
	183 if_icmpge (5, 4)
	184 34 (5, 4)
	186 aload_0 (5, 4)
	187 getfield (5, 4)
	188 org/apache/commons/math3/stat/regression/MillerUpdatingRegression.x_sing:[D (5, 4)
	190 iload (5, 4)
	191 #6 (5, 4)
	192 aload_0 (5, 4)
	193 getfield (5, 4)
	194 org/apache/commons/math3/stat/regression/MillerUpdatingRegression.r:[D (5, 4)
	196 iload (5, 4)
	197 #5 (5, 4)
	198 daload (5, 4)
	199 dastore (5, 4)
	200 aload_0 (5, 4)
	201 getfield (5, 4)
	202 org/apache/commons/math3/stat/regression/MillerUpdatingRegression.r:[D (5, 4)
	204 iload (5, 4)
	205 #5 (5, 4)
	206 dconst_0 (5, 4)
	207 dastore (5, 4)
	208 iinc (5, 4)
	209 #6 (5, 4)
	210 -124 (5, 4)
	211 iinc (5, 4)
	212 #5 (5, 4)
	213 -89 (5, 4)
	214 goto (5, 4)
	215 -37 (5, 4)
	217 aload_0 (4, 1)
	218 getfield (4, 1)
	219 org/apache/commons/math3/stat/regression/MillerUpdatingRegression.rhs:[D (4, 1)
	221 iload_2 (4, 1)
	222 daload (4, 1)
	223 dstore (4, 1)
	224 #6 (4, 1)
	225 aload_0 (4, 1)
	226 getfield (4, 1)
	227 org/apache/commons/math3/stat/regression/MillerUpdatingRegression.d:[D (4, 1)
	229 iload_2 (4, 1)
	230 daload (4, 1)
	231 dstore (4, 1)
	232 #8 (4, 1)
	233 aload_0 (4, 1)
	234 getfield (4, 1)
	235 org/apache/commons/math3/stat/regression/MillerUpdatingRegression.d:[D (4, 1)
	237 iload_2 (4, 1)
	238 dconst_0 (4, 1)
	239 dastore (4, 1)
	240 aload_0 (4, 1)
	241 getfield (4, 1)
	242 org/apache/commons/math3/stat/regression/MillerUpdatingRegression.rhs:[D (4, 1)
	244 iload_2 (4, 1)
	245 dconst_0 (4, 1)
	246 dastore (4, 1)
	247 aload_0 (4, 1)
	248 aload_0 (4, 1)
	249 getfield (4, 1)
	250 org/apache/commons/math3/stat/regression/MillerUpdatingRegression.x_sing:[D (4, 1)
	252 dload (4, 1)
	253 #8 (4, 1)
	254 dload (4, 1)
	255 #6 (4, 1)
	256 invokespecial (4, 1)
	257 org/apache/commons/math3/stat/regression/MillerUpdatingRegression.include:([DDD)V (4, 1)
	259 goto (5, 2)
	260 32 (5, 2)
	262 aload_0 (5, 2)
	263 dup (5, 2)
	264 getfield (5, 2)
	265 org/apache/commons/math3/stat/regression/MillerUpdatingRegression.sserr:D (5, 2)
	267 aload_0 (5, 2)
	268 getfield (5, 2)
	269 org/apache/commons/math3/stat/regression/MillerUpdatingRegression.d:[D (5, 2)
	271 iload_2 (5, 2)
	272 daload (5, 2)
	273 aload_0 (5, 2)
	274 getfield (5, 2)
	275 org/apache/commons/math3/stat/regression/MillerUpdatingRegression.rhs:[D (5, 2)
	277 iload_2 (5, 2)
	278 daload (5, 2)
	279 dmul (5, 2)
	280 aload_0 (5, 2)
	281 getfield (5, 2)
	282 org/apache/commons/math3/stat/regression/MillerUpdatingRegression.rhs:[D (5, 2)
	284 iload_2 (5, 2)
	285 daload (5, 2)
	286 dmul (5, 2)
	287 dadd (5, 2)
	288 putfield (5, 2)
	289 org/apache/commons/math3/stat/regression/MillerUpdatingRegression.sserr:D (5, 2)
	291 iinc (5, 2)
	292 #2 (5, 2)
	293 -89 (5, 2)
	294 goto (5, 2)
	295 -261 (5, 2)
	297 return (1, 1)

Method: ss
	0 aload_0 (0, 0)
	1 getfield (0, 0)
	2 org/apache/commons/math3/stat/regression/MillerUpdatingRegression.sserr:D (0, 0)
	4 dstore_1 (0, 0)
	5 aload_0 (0, 0)
	6 getfield (0, 0)
	7 org/apache/commons/math3/stat/regression/MillerUpdatingRegression.rss:[D (0, 0)
	9 aload_0 (0, 0)
	10 getfield (0, 0)
	11 org/apache/commons/math3/stat/regression/MillerUpdatingRegression.nvars:I (0, 0)
	13 iconst_1 (0, 0)
	14 isub (0, 0)
	15 aload_0 (0, 0)
	16 getfield (0, 0)
	17 org/apache/commons/math3/stat/regression/MillerUpdatingRegression.sserr:D (0, 0)
	19 dastore (0, 0)
	20 aload_0 (1, 4)
	21 getfield (1, 4)
	22 org/apache/commons/math3/stat/regression/MillerUpdatingRegression.nvars:I (1, 4)
	24 iconst_1 (1, 4)
	25 isub (1, 4)
	26 istore_3 (1, 4)
	27 iload_3 (1, 4)
	28 ifle (1, 4)
	29 41 (1, 4)
	31 dload_1 (1, 4)
	32 aload_0 (1, 4)
	33 getfield (1, 4)
	34 org/apache/commons/math3/stat/regression/MillerUpdatingRegression.d:[D (1, 4)
	36 iload_3 (1, 4)
	37 daload (1, 4)
	38 aload_0 (1, 4)
	39 getfield (1, 4)
	40 org/apache/commons/math3/stat/regression/MillerUpdatingRegression.rhs:[D (1, 4)
	42 iload_3 (1, 4)
	43 daload (1, 4)
	44 dmul (1, 4)
	45 aload_0 (1, 4)
	46 getfield (1, 4)
	47 org/apache/commons/math3/stat/regression/MillerUpdatingRegression.rhs:[D (1, 4)
	49 iload_3 (1, 4)
	50 daload (1, 4)
	51 dmul (1, 4)
	52 dadd (1, 4)
	53 dstore_1 (1, 4)
	54 aload_0 (1, 4)
	55 getfield (1, 4)
	56 org/apache/commons/math3/stat/regression/MillerUpdatingRegression.rss:[D (1, 4)
	58 iload_3 (1, 4)
	59 iconst_1 (1, 4)
	60 isub (1, 4)
	61 dload_1 (1, 4)
	62 dastore (1, 4)
	63 iinc (1, 4)
	64 #3 (1, 4)
	65 -89 (1, 4)
	66 goto (1, 4)
	67 -39 (1, 4)
	69 aload_0 (0, 0)
	70 iconst_1 (0, 0)
	71 putfield (0, 0)
	72 org/apache/commons/math3/stat/regression/MillerUpdatingRegression.rss_set:Z (0, 0)
	74 return (0, 0)

Method: cov
	0 aload_0 (1, 1)
	1 getfield (1, 1)
	2 org/apache/commons/math3/stat/regression/MillerUpdatingRegression.nobs:J (1, 1)
	4 iload_1 (1, 1)
	5 i2l (1, 1)
	6 lcmp (1, 1)
	7 ifgt (1, 1)
	8 5 (1, 1)
	10 aconst_null (1, 1)
	11 areturn (1, 1)
	12 dconst_0 (0, 0)
	13 dstore_2 (0, 0)
	14 iconst_0 (1, 4)
	15 istore (1, 4)
	16 #4 (1, 4)
	17 iload (1, 4)
	18 #4 (1, 4)
	19 iload_1 (1, 4)
	20 if_icmpge (1, 4)
	21 23 (1, 4)
	23 aload_0 (2, 1)
	24 getfield (2, 1)
	25 org/apache/commons/math3/stat/regression/MillerUpdatingRegression.lindep:[Z (2, 1)
	27 iload (2, 1)
	28 #4 (2, 1)
	29 baload (2, 1)
	30 ifne (2, 1)
	31 7 (2, 1)
	33 dload_2 (2, 1)
	34 dconst_1 (2, 1)
	35 dadd (2, 1)
	36 dstore_2 (2, 1)
	37 iinc (2, 1)
	38 #4 (2, 1)
	39 -89 (2, 1)
	40 goto (2, 1)
	41 -23 (2, 1)
	43 aload_0 (1, 4)
	44 getfield (1, 4)
	45 org/apache/commons/math3/stat/regression/MillerUpdatingRegression.rss:[D (1, 4)
	47 iload_1 (1, 4)
	48 iconst_1 (1, 4)
	49 isub (1, 4)
	50 daload (1, 4)
	51 aload_0 (1, 4)
	52 getfield (1, 4)
	53 org/apache/commons/math3/stat/regression/MillerUpdatingRegression.nobs:J (1, 4)
	55 l2d (1, 4)
	56 dload_2 (1, 4)
	57 dsub (1, 4)
	58 ddiv (1, 4)
	59 dstore (1, 4)
	60 #4 (1, 4)
	61 iload_1 (1, 4)
	62 iload_1 (1, 4)
	63 iconst_1 (1, 4)
	64 isub (1, 4)
	65 imul (1, 4)
	66 iconst_2 (1, 4)
	67 idiv (1, 4)
	68 newarray (1, 4)
	69 7 (1, 4)
	70 astore (1, 4)
	71 #6 (1, 4)
	72 aload_0 (1, 4)
	73 aload (1, 4)
	74 #6 (1, 4)
	75 iload_1 (1, 4)
	76 invokespecial (1, 4)
	77 org/apache/commons/math3/stat/regression/MillerUpdatingRegression.inverse:([DI)V (1, 4)
	79 iload_1 (1, 4)
	80 iload_1 (1, 4)
	81 iconst_1 (1, 4)
	82 iadd (1, 4)
	83 imul (1, 4)
	84 iconst_2 (1, 4)
	85 idiv (1, 4)
	86 newarray (1, 4)
	87 7 (1, 4)
	88 astore (1, 4)
	89 #7 (1, 4)
	90 aload (1, 4)
	91 #7 (1, 4)
	92 ldc2_w (1, 4)
	93 nan (1, 4)
	95 invokestatic (1, 4)
	96 java/util/Arrays.fill:([DD)V (1, 4)
	98 iconst_0 (1, 4)
	99 istore (1, 4)
	100 #10 (1, 4)
	101 dconst_0 (1, 4)
	102 dstore (1, 4)
	103 #11 (1, 4)
	104 iconst_0 (2, 4)
	105 istore (2, 4)
	106 #13 (2, 4)
	107 iload (2, 4)
	108 #13 (2, 4)
	109 iload_1 (2, 4)
	110 if_icmpge (2, 4)
	111 200 (2, 4)
	113 iload (2, 4)
	114 #10 (2, 4)
	115 istore (2, 4)
	116 #8 (2, 4)
	117 aload_0 (3, 1)
	118 getfield (3, 1)
	119 org/apache/commons/math3/stat/regression/MillerUpdatingRegression.lindep:[Z (3, 1)
	121 iload (3, 1)
	122 #13 (3, 1)
	123 baload (3, 1)
	124 ifne (3, 1)
	125 169 (3, 1)
	127 iload (4, 4)
	128 #13 (4, 4)
	129 istore (4, 4)
	130 #14 (4, 4)
	131 iload (4, 4)
	132 #14 (4, 4)
	133 iload_1 (4, 4)
	134 if_icmpge (4, 4)
	135 159 (4, 4)
	137 aload_0 (5, 1)
	138 getfield (5, 1)
	139 org/apache/commons/math3/stat/regression/MillerUpdatingRegression.lindep:[Z (5, 1)
	141 iload (5, 1)
	142 #14 (5, 1)
	143 baload (5, 1)
	144 ifne (5, 1)
	145 132 (5, 1)
	147 iload (5, 1)
	148 #10 (5, 1)
	149 iload (5, 1)
	150 #14 (5, 1)
	151 iadd (5, 1)
	152 iload (5, 1)
	153 #13 (5, 1)
	154 isub (5, 1)
	155 istore (5, 1)
	156 #9 (5, 1)
	157 iload (6, 1)
	158 #13 (6, 1)
	159 iload (6, 1)
	160 #14 (6, 1)
	161 if_icmpne (6, 1)
	162 17 (6, 1)
	164 dconst_1 (6, 1)
	165 aload_0 (6, 1)
	166 getfield (6, 1)
	167 org/apache/commons/math3/stat/regression/MillerUpdatingRegression.d:[D (6, 1)
	169 iload (6, 1)
	170 #14 (6, 1)
	171 daload (6, 1)
	172 ddiv (6, 1)
	173 dstore (6, 1)
	174 #11 (6, 1)
	175 goto (6, 1)
	176 20 (6, 1)
	178 aload (7, 2)
	179 #6 (7, 2)
	180 iload (7, 2)
	181 #9 (7, 2)
	182 iconst_1 (7, 2)
	183 isub (7, 2)
	184 daload (7, 2)
	185 aload_0 (7, 2)
	186 getfield (7, 2)
	187 org/apache/commons/math3/stat/regression/MillerUpdatingRegression.d:[D (7, 2)
	189 iload (7, 2)
	190 #14 (7, 2)
	191 daload (7, 2)
	192 ddiv (7, 2)
	193 dstore (7, 2)
	194 #11 (7, 2)
	195 iload (6, 4)
	196 #14 (6, 4)
	197 iconst_1 (6, 4)
	198 iadd (6, 4)
	199 istore (6, 4)
	200 #15 (6, 4)
	201 iload (6, 4)
	202 #15 (6, 4)
	203 iload_1 (6, 4)
	204 if_icmpge (6, 4)
	205 49 (6, 4)
	207 aload_0 (7, 1)
	208 getfield (7, 1)
	209 org/apache/commons/math3/stat/regression/MillerUpdatingRegression.lindep:[Z (7, 1)
	211 iload (7, 1)
	212 #15 (7, 1)
	213 baload (7, 1)
	214 ifne (7, 1)
	215 27 (7, 1)
	217 dload (7, 1)
	218 #11 (7, 1)
	219 aload (7, 1)
	220 #6 (7, 1)
	221 iload (7, 1)
	222 #9 (7, 1)
	223 daload (7, 1)
	224 aload (7, 1)
	225 #6 (7, 1)
	226 iload (7, 1)
	227 #8 (7, 1)
	228 daload (7, 1)
	229 dmul (7, 1)
	230 aload_0 (7, 1)
	231 getfield (7, 1)
	232 org/apache/commons/math3/stat/regression/MillerUpdatingRegression.d:[D (7, 1)
	234 iload (7, 1)
	235 #15 (7, 1)
	236 daload (7, 1)
	237 ddiv (7, 1)
	238 dadd (7, 1)
	239 dstore (7, 1)
	240 #11 (7, 1)
	241 iinc (6, 4)
	242 #9 (6, 4)
	243 -124 (6, 4)
	244 iinc (6, 4)
	245 #8 (6, 4)
	246 -124 (6, 4)
	247 iinc (6, 4)
	248 #15 (6, 4)
	249 -89 (6, 4)
	250 goto (6, 4)
	251 -49 (6, 4)
	253 aload (5, 1)
	254 #7 (5, 1)
	255 iload (5, 1)
	256 #14 (5, 1)
	257 iconst_1 (5, 1)
	258 iadd (5, 1)
	259 iload (5, 1)
	260 #14 (5, 1)
	261 imul (5, 1)
	262 iconst_2 (5, 1)
	263 idiv (5, 1)
	264 iload (5, 1)
	265 #13 (5, 1)
	266 iadd (5, 1)
	267 dload (5, 1)
	268 #11 (5, 1)
	269 dload (5, 1)
	270 #4 (5, 1)
	271 dmul (5, 1)
	272 dastore (5, 1)
	273 goto (5, 1)
	274 14 (5, 1)
	276 iload (6, 2)
	277 #8 (6, 2)
	278 iload_1 (6, 2)
	279 iload (6, 2)
	280 #14 (6, 2)
	281 isub (6, 2)
	282 iconst_1 (6, 2)
	283 isub (6, 2)
	284 iadd (6, 2)
	285 istore (6, 2)
	286 #8 (6, 2)
	287 iinc (6, 2)
	288 #14 (6, 2)
	289 -89 (6, 2)
	290 goto (6, 2)
	291 -159 (6, 2)
	293 iload (3, 1)
	294 #10 (3, 1)
	295 iload_1 (3, 1)
	296 iload (3, 1)
	297 #13 (3, 1)
	298 isub (3, 1)
	299 iconst_1 (3, 1)
	300 isub (3, 1)
	301 iadd (3, 1)
	302 istore (3, 1)
	303 #10 (3, 1)
	304 iinc (3, 1)
	305 #13 (3, 1)
	306 -89 (3, 1)
	307 goto (3, 1)
	308 -200 (3, 1)
	310 aload (2, 4)
	311 #7 (2, 4)
	312 areturn (2, 4)

Method: inverse
	0 iload_2 (0, 0)
	1 iload_2 (0, 0)
	2 iconst_1 (0, 0)
	3 isub (0, 0)
	4 imul (0, 0)
	5 iconst_2 (0, 0)
	6 idiv (0, 0)
	7 iconst_1 (0, 0)
	8 isub (0, 0)
	9 istore_3 (0, 0)
	10 iconst_m1 (0, 0)
	11 istore (0, 0)
	12 #4 (0, 0)
	13 iconst_m1 (0, 0)
	14 istore (0, 0)
	15 #5 (0, 0)
	16 dconst_0 (0, 0)
	17 dstore (0, 0)
	18 #6 (0, 0)
	19 aload_1 (0, 0)
	20 ldc2_w (0, 0)
	21 nan (0, 0)
	23 invokestatic (0, 0)
	24 java/util/Arrays.fill:([DD)V (0, 0)
	26 iload_2 (1, 4)
	27 iconst_1 (1, 4)
	28 isub (1, 4)
	29 istore (1, 4)
	30 #8 (1, 4)
	31 iload (1, 4)
	32 #8 (1, 4)
	33 ifle (1, 4)
	34 153 (1, 4)
	36 aload_0 (2, 1)
	37 getfield (2, 1)
	38 org/apache/commons/math3/stat/regression/MillerUpdatingRegression.lindep:[Z (2, 1)
	40 iload (2, 1)
	41 #8 (2, 1)
	42 baload (2, 1)
	43 ifne (2, 1)
	44 130 (2, 1)
	46 iload (2, 1)
	47 #8 (2, 1)
	48 iconst_1 (2, 1)
	49 isub (2, 1)
	50 aload_0 (2, 1)
	51 getfield (2, 1)
	52 org/apache/commons/math3/stat/regression/MillerUpdatingRegression.nvars:I (2, 1)
	54 aload_0 (2, 1)
	55 getfield (2, 1)
	56 org/apache/commons/math3/stat/regression/MillerUpdatingRegression.nvars:I (2, 1)
	58 iadd (2, 1)
	59 iload (2, 1)
	60 #8 (2, 1)
	61 isub (2, 1)
	62 imul (2, 1)
	63 iconst_2 (2, 1)
	64 idiv (2, 1)
	65 istore (2, 1)
	66 #9 (2, 1)
	67 iload_2 (3, 4)
	68 istore (3, 4)
	69 #10 (3, 4)
	70 iload (3, 4)
	71 #10 (3, 4)
	72 iload (3, 4)
	73 #8 (3, 4)
	74 if_icmple (3, 4)
	75 96 (3, 4)
	77 iload (3, 4)
	78 #9 (3, 4)
	79 istore (3, 4)
	80 #4 (3, 4)
	81 iload_3 (3, 4)
	82 istore (3, 4)
	83 #5 (3, 4)
	84 dconst_0 (3, 4)
	85 dstore (3, 4)
	86 #6 (3, 4)
	87 iload (4, 4)
	88 #8 (4, 4)
	89 istore (4, 4)
	90 #11 (4, 4)
	91 iload (4, 4)
	92 #11 (4, 4)
	93 iload (4, 4)
	94 #10 (4, 4)
	95 iconst_1 (4, 4)
	96 isub (4, 4)
	97 if_icmpge (4, 4)
	98 51 (4, 4)
	100 iload (4, 4)
	101 #5 (4, 4)
	102 iload_2 (4, 4)
	103 iload (4, 4)
	104 #11 (4, 4)
	105 isub (4, 4)
	106 iconst_1 (4, 4)
	107 isub (4, 4)
	108 iadd (4, 4)
	109 istore (4, 4)
	110 #5 (4, 4)
	111 aload_0 (5, 1)
	112 getfield (5, 1)
	113 org/apache/commons/math3/stat/regression/MillerUpdatingRegression.lindep:[Z (5, 1)
	115 iload (5, 1)
	116 #11 (5, 1)
	117 baload (5, 1)
	118 ifne (5, 1)
	119 21 (5, 1)
	121 dload (5, 1)
	122 #6 (5, 1)
	123 aload_0 (5, 1)
	124 getfield (5, 1)
	125 org/apache/commons/math3/stat/regression/MillerUpdatingRegression.r:[D (5, 1)
	127 iload (5, 1)
	128 #4 (5, 1)
	129 daload (5, 1)
	130 dneg (5, 1)
	131 aload_1 (5, 1)
	132 iload (5, 1)
	133 #5 (5, 1)
	134 daload (5, 1)
	135 dmul (5, 1)
	136 dadd (5, 1)
	137 dstore (5, 1)
	138 #6 (5, 1)
	139 iinc (4, 4)
	140 #4 (4, 4)
	141 -124 (4, 4)
	142 iinc (4, 4)
	143 #11 (4, 4)
	144 -89 (4, 4)
	145 goto (4, 4)
	146 -54 (4, 4)
	148 aload_1 (3, 4)
	149 iload_3 (3, 4)
	150 dload (3, 4)
	151 #6 (3, 4)
	152 aload_0 (3, 4)
	153 getfield (3, 4)
	154 org/apache/commons/math3/stat/regression/MillerUpdatingRegression.r:[D (3, 4)
	156 iload (3, 4)
	157 #4 (3, 4)
	158 daload (3, 4)
	159 dsub (3, 4)
	160 dastore (3, 4)
	161 iinc (3, 4)
	162 #3 (3, 4)
	163 -124 (3, 4)
	164 iinc (3, 4)
	165 #10 (3, 4)
	166 -89 (3, 4)
	167 goto (3, 4)
	168 -97 (3, 4)
	170 goto (3, 2)
	171 10 (3, 2)
	173 iload_3 (3, 2)
	174 iload_2 (3, 2)
	175 iload (3, 2)
	176 #8 (3, 2)
	177 isub (3, 2)
	178 isub (3, 2)
	179 istore_3 (3, 2)
	180 iinc (3, 2)
	181 #8 (3, 2)
	182 -89 (3, 2)
	183 goto (3, 2)
	184 -152 (3, 2)
	186 return (0, 0)

Method: getPartialCorrelations
	0 aload_0 (0, 0)
	1 getfield (0, 0)
	2 org/apache/commons/math3/stat/regression/MillerUpdatingRegression.nvars:I (0, 0)
	4 iload_1 (0, 0)
	5 isub (0, 0)
	6 iconst_1 (0, 0)
	7 iadd (0, 0)
	8 aload_0 (0, 0)
	9 getfield (0, 0)
	10 org/apache/commons/math3/stat/regression/MillerUpdatingRegression.nvars:I (0, 0)
	12 iload_1 (0, 0)
	13 isub (0, 0)
	14 imul (0, 0)
	15 iconst_2 (0, 0)
	16 idiv (0, 0)
	17 newarray (0, 0)
	18 7 (0, 0)
	19 astore_2 (0, 0)
	20 iload_1 (0, 0)
	21 ineg (0, 0)
	22 istore (0, 0)
	23 #6 (0, 0)
	24 iload_1 (0, 0)
	25 iconst_1 (0, 0)
	26 iadd (0, 0)
	27 ineg (0, 0)
	28 istore (0, 0)
	29 #7 (0, 0)
	30 aload_0 (0, 0)
	31 getfield (0, 0)
	32 org/apache/commons/math3/stat/regression/MillerUpdatingRegression.nvars:I (0, 0)
	34 iload_1 (0, 0)
	35 isub (0, 0)
	36 newarray (0, 0)
	37 7 (0, 0)
	38 astore (0, 0)
	39 #8 (0, 0)
	40 aload_0 (0, 0)
	41 getfield (0, 0)
	42 org/apache/commons/math3/stat/regression/MillerUpdatingRegression.nvars:I (0, 0)
	44 iload_1 (0, 0)
	45 isub (0, 0)
	46 iconst_1 (0, 0)
	47 isub (0, 0)
	48 newarray (0, 0)
	49 7 (0, 0)
	50 astore (0, 0)
	51 #9 (0, 0)
	52 aload_0 (0, 0)
	53 getfield (0, 0)
	54 org/apache/commons/math3/stat/regression/MillerUpdatingRegression.nvars:I (0, 0)
	56 iload_1 (0, 0)
	57 isub (0, 0)
	58 aload_0 (0, 0)
	59 getfield (0, 0)
	60 org/apache/commons/math3/stat/regression/MillerUpdatingRegression.nvars:I (0, 0)
	62 iload_1 (0, 0)
	63 isub (0, 0)
	64 iconst_1 (0, 0)
	65 isub (0, 0)
	66 imul (0, 0)
	67 iconst_2 (0, 0)
	68 idiv (0, 0)
	69 istore (0, 0)
	70 #16 (0, 0)
	71 iload_1 (1, 1)
	72 iconst_m1 (1, 1)
	73 if_icmplt (1, 1)
	74 11 (1, 1)
	76 iload_1 (1, 1)
	77 aload_0 (1, 1)
	78 getfield (1, 1)
	79 org/apache/commons/math3/stat/regression/MillerUpdatingRegression.nvars:I (1, 1)
	81 if_icmplt (1, 1)
	82 5 (1, 1)
	84 aconst_null (1, 1)
	85 areturn (1, 1)
	86 aload_0 (0, 0)
	87 getfield (0, 0)
	88 org/apache/commons/math3/stat/regression/MillerUpdatingRegression.nvars:I (0, 0)
	90 iconst_1 (0, 0)
	91 isub (0, 0)
	92 istore (0, 0)
	93 #17 (0, 0)
	94 aload_0 (0, 0)
	95 getfield (0, 0)
	96 org/apache/commons/math3/stat/regression/MillerUpdatingRegression.r:[D (0, 0)
	98 arraylength (0, 0)
	99 iload (0, 0)
	100 #17 (0, 0)
	101 iload_1 (0, 0)
	102 isub (0, 0)
	103 iload (0, 0)
	104 #17 (0, 0)
	105 iload_1 (0, 0)
	106 isub (0, 0)
	107 iconst_1 (0, 0)
	108 iadd (0, 0)
	109 imul (0, 0)
	110 iconst_2 (0, 0)
	111 idiv (0, 0)
	112 isub (0, 0)
	113 istore (0, 0)
	114 #18 (0, 0)
	115 aload_0 (1, 1)
	116 getfield (1, 1)
	117 org/apache/commons/math3/stat/regression/MillerUpdatingRegression.d:[D (1, 1)
	119 iload_1 (1, 1)
	120 daload (1, 1)
	121 dconst_0 (1, 1)
	122 dcmpl (1, 1)
	123 ifle (1, 1)
	124 21 (1, 1)
	126 aload (1, 1)
	127 #8 (1, 1)
	128 iload_1 (1, 1)
	129 iload (1, 1)
	130 #6 (1, 1)
	131 iadd (1, 1)
	132 dconst_1 (1, 1)
	133 aload_0 (1, 1)
	134 getfield (1, 1)
	135 org/apache/commons/math3/stat/regression/MillerUpdatingRegression.d:[D (1, 1)
	137 iload_1 (1, 1)
	138 daload (1, 1)
	139 invokestatic (1, 1)
	140 org/apache/commons/math3/util/FastMath.sqrt:(D)D (1, 1)
	142 ddiv (1, 1)
	143 dastore (1, 1)
	144 iload_1 (1, 4)
	145 iconst_1 (1, 4)
	146 iadd (1, 4)
	147 istore (1, 4)
	148 #19 (1, 4)
	149 iload (1, 4)
	150 #19 (1, 4)
	151 aload_0 (1, 4)
	152 getfield (1, 4)
	153 org/apache/commons/math3/stat/regression/MillerUpdatingRegression.nvars:I (1, 4)
	155 if_icmpge (1, 4)
	156 116 (1, 4)
	158 iload (1, 4)
	159 #18 (1, 4)
	160 iload (1, 4)
	161 #19 (1, 4)
	162 iadd (1, 4)
	163 iconst_1 (1, 4)
	164 isub (1, 4)
	165 iload_1 (1, 4)
	166 isub (1, 4)
	167 istore_3 (1, 4)
	168 aload_0 (1, 4)
	169 getfield (1, 4)
	170 org/apache/commons/math3/stat/regression/MillerUpdatingRegression.d:[D (1, 4)
	172 iload (1, 4)
	173 #19 (1, 4)
	174 daload (1, 4)
	175 dstore (1, 4)
	176 #10 (1, 4)
	177 iload_1 (2, 4)
	178 istore (2, 4)
	179 #20 (2, 4)
	180 iload (2, 4)
	181 #20 (2, 4)
	182 iload (2, 4)
	183 #19 (2, 4)
	184 if_icmpge (2, 4)
	185 47 (2, 4)
	187 dload (2, 4)
	188 #10 (2, 4)
	189 aload_0 (2, 4)
	190 getfield (2, 4)
	191 org/apache/commons/math3/stat/regression/MillerUpdatingRegression.d:[D (2, 4)
	193 iload (2, 4)
	194 #20 (2, 4)
	195 daload (2, 4)
	196 aload_0 (2, 4)
	197 getfield (2, 4)
	198 org/apache/commons/math3/stat/regression/MillerUpdatingRegression.r:[D (2, 4)
	200 iload_3 (2, 4)
	201 daload (2, 4)
	202 dmul (2, 4)
	203 aload_0 (2, 4)
	204 getfield (2, 4)
	205 org/apache/commons/math3/stat/regression/MillerUpdatingRegression.r:[D (2, 4)
	207 iload_3 (2, 4)
	208 daload (2, 4)
	209 dmul (2, 4)
	210 dadd (2, 4)
	211 dstore (2, 4)
	212 #10 (2, 4)
	213 iload_3 (2, 4)
	214 aload_0 (2, 4)
	215 getfield (2, 4)
	216 org/apache/commons/math3/stat/regression/MillerUpdatingRegression.nvars:I (2, 4)
	218 iload (2, 4)
	219 #20 (2, 4)
	220 isub (2, 4)
	221 iconst_2 (2, 4)
	222 isub (2, 4)
	223 iadd (2, 4)
	224 istore_3 (2, 4)
	225 iinc (2, 4)
	226 #20 (2, 4)
	227 -89 (2, 4)
	228 goto (2, 4)
	229 -48 (2, 4)
	231 dload (2, 1)
	232 #10 (2, 1)
	233 dconst_0 (2, 1)
	234 dcmpl (2, 1)
	235 ifle (2, 1)
	236 21 (2, 1)
	238 aload (2, 1)
	239 #8 (2, 1)
	240 iload (2, 1)
	241 #19 (2, 1)
	242 iload (2, 1)
	243 #6 (2, 1)
	244 iadd (2, 1)
	245 dconst_1 (2, 1)
	246 dload (2, 1)
	247 #10 (2, 1)
	248 invokestatic (2, 1)
	249 org/apache/commons/math3/util/FastMath.sqrt:(D)D (2, 1)
	251 ddiv (2, 1)
	252 dastore (2, 1)
	253 goto (2, 1)
	254 12 (2, 1)
	256 aload (3, 2)
	257 #8 (3, 2)
	258 iload (3, 2)
	259 #19 (3, 2)
	260 iload (3, 2)
	261 #6 (3, 2)
	262 iadd (3, 2)
	263 dconst_0 (3, 2)
	264 dastore (3, 2)
	265 iinc (3, 2)
	266 #19 (3, 2)
	267 -89 (3, 2)
	268 goto (3, 2)
	269 -119 (3, 2)
	271 aload_0 (1, 4)
	272 getfield (1, 4)
	273 org/apache/commons/math3/stat/regression/MillerUpdatingRegression.sserr:D (1, 4)
	275 dstore (1, 4)
	276 #14 (1, 4)
	277 iload_1 (2, 4)
	278 istore (2, 4)
	279 #19 (2, 4)
	280 iload (2, 4)
	281 #19 (2, 4)
	282 aload_0 (2, 4)
	283 getfield (2, 4)
	284 org/apache/commons/math3/stat/regression/MillerUpdatingRegression.nvars:I (2, 4)
	286 if_icmpge (2, 4)
	287 37 (2, 4)
	289 dload (2, 4)
	290 #14 (2, 4)
	291 aload_0 (2, 4)
	292 getfield (2, 4)
	293 org/apache/commons/math3/stat/regression/MillerUpdatingRegression.d:[D (2, 4)
	295 iload (2, 4)
	296 #19 (2, 4)
	297 daload (2, 4)
	298 aload_0 (2, 4)
	299 getfield (2, 4)
	300 org/apache/commons/math3/stat/regression/MillerUpdatingRegression.rhs:[D (2, 4)
	302 iload (2, 4)
	303 #19 (2, 4)
	304 daload (2, 4)
	305 dmul (2, 4)
	306 aload_0 (2, 4)
	307 getfield (2, 4)
	308 org/apache/commons/math3/stat/regression/MillerUpdatingRegression.rhs:[D (2, 4)
	310 iload (2, 4)
	311 #19 (2, 4)
	312 daload (2, 4)
	313 dmul (2, 4)
	314 dadd (2, 4)
	315 dstore (2, 4)
	316 #14 (2, 4)
	317 iinc (2, 4)
	318 #19 (2, 4)
	319 -89 (2, 4)
	320 goto (2, 4)
	321 -40 (2, 4)
	323 dload (2, 1)
	324 #14 (2, 1)
	325 dconst_0 (2, 1)
	326 dcmpl (2, 1)
	327 ifle (2, 1)
	328 12 (2, 1)
	330 dconst_1 (2, 1)
	331 dload (2, 1)
	332 #14 (2, 1)
	333 invokestatic (2, 1)
	334 org/apache/commons/math3/util/FastMath.sqrt:(D)D (2, 1)
	336 ddiv (2, 1)
	337 dstore (2, 1)
	338 #14 (2, 1)
	339 iconst_0 (1, 4)
	340 istore_3 (1, 4)
	341 iload_1 (2, 4)
	342 istore (2, 4)
	343 #19 (2, 4)
	344 iload (2, 4)
	345 #19 (2, 4)
	346 aload_0 (2, 4)
	347 getfield (2, 4)
	348 org/apache/commons/math3/stat/regression/MillerUpdatingRegression.nvars:I (2, 4)
	350 if_icmpge (2, 4)
	351 300 (2, 4)
	353 dconst_0 (2, 4)
	354 dstore (2, 4)
	355 #12 (2, 4)
	356 aload (2, 4)
	357 #9 (2, 4)
	358 dconst_0 (2, 4)
	359 invokestatic (2, 4)
	360 java/util/Arrays.fill:([DD)V (2, 4)
	362 iload (2, 4)
	363 #18 (2, 4)
	364 iload (2, 4)
	365 #19 (2, 4)
	366 iadd (2, 4)
	367 iload_1 (2, 4)
	368 isub (2, 4)
	369 iconst_1 (2, 4)
	370 isub (2, 4)
	371 istore (2, 4)
	372 #4 (2, 4)
	373 iload_1 (3, 4)
	374 istore (3, 4)
	375 #20 (3, 4)
	376 iload (3, 4)
	377 #20 (3, 4)
	378 iload (3, 4)
	379 #19 (3, 4)
	380 if_icmpge (3, 4)
	381 115 (3, 4)
	383 iload (3, 4)
	384 #4 (3, 4)
	385 iconst_1 (3, 4)
	386 iadd (3, 4)
	387 istore (3, 4)
	388 #5 (3, 4)
	389 iload (4, 4)
	390 #19 (4, 4)
	391 iconst_1 (4, 4)
	392 iadd (4, 4)
	393 istore (4, 4)
	394 #21 (4, 4)
	395 iload (4, 4)
	396 #21 (4, 4)
	397 aload_0 (4, 4)
	398 getfield (4, 4)
	399 org/apache/commons/math3/stat/regression/MillerUpdatingRegression.nvars:I (4, 4)
	401 if_icmpge (4, 4)
	402 46 (4, 4)
	404 aload (4, 4)
	405 #9 (4, 4)
	406 iload (4, 4)
	407 #21 (4, 4)
	408 iload (4, 4)
	409 #7 (4, 4)
	410 iadd (4, 4)
	411 dup2 (4, 4)
	412 daload (4, 4)
	413 aload_0 (4, 4)
	414 getfield (4, 4)
	415 org/apache/commons/math3/stat/regression/MillerUpdatingRegression.d:[D (4, 4)
	417 iload (4, 4)
	418 #20 (4, 4)
	419 daload (4, 4)
	420 aload_0 (4, 4)
	421 getfield (4, 4)
	422 org/apache/commons/math3/stat/regression/MillerUpdatingRegression.r:[D (4, 4)
	424 iload (4, 4)
	425 #4 (4, 4)
	426 daload (4, 4)
	427 dmul (4, 4)
	428 aload_0 (4, 4)
	429 getfield (4, 4)
	430 org/apache/commons/math3/stat/regression/MillerUpdatingRegression.r:[D (4, 4)
	432 iload (4, 4)
	433 #5 (4, 4)
	434 daload (4, 4)
	435 dmul (4, 4)
	436 dadd (4, 4)
	437 dastore (4, 4)
	438 iinc (4, 4)
	439 #5 (4, 4)
	440 -124 (4, 4)
	441 iinc (4, 4)
	442 #21 (4, 4)
	443 -89 (4, 4)
	444 goto (4, 4)
	445 -49 (4, 4)
	447 dload (3, 4)
	448 #12 (3, 4)
	449 aload_0 (3, 4)
	450 getfield (3, 4)
	451 org/apache/commons/math3/stat/regression/MillerUpdatingRegression.d:[D (3, 4)
	453 iload (3, 4)
	454 #20 (3, 4)
	455 daload (3, 4)
	456 aload_0 (3, 4)
	457 getfield (3, 4)
	458 org/apache/commons/math3/stat/regression/MillerUpdatingRegression.r:[D (3, 4)
	460 iload (3, 4)
	461 #4 (3, 4)
	462 daload (3, 4)
	463 dmul (3, 4)
	464 aload_0 (3, 4)
	465 getfield (3, 4)
	466 org/apache/commons/math3/stat/regression/MillerUpdatingRegression.rhs:[D (3, 4)
	468 iload (3, 4)
	469 #20 (3, 4)
	470 daload (3, 4)
	471 dmul (3, 4)
	472 dadd (3, 4)
	473 dstore (3, 4)
	474 #12 (3, 4)
	475 iload (3, 4)
	476 #4 (3, 4)
	477 aload_0 (3, 4)
	478 getfield (3, 4)
	479 org/apache/commons/math3/stat/regression/MillerUpdatingRegression.nvars:I (3, 4)
	481 iload (3, 4)
	482 #20 (3, 4)
	483 isub (3, 4)
	484 iconst_2 (3, 4)
	485 isub (3, 4)
	486 iadd (3, 4)
	487 istore (3, 4)
	488 #4 (3, 4)
	489 iinc (3, 4)
	490 #20 (3, 4)
	491 -89 (3, 4)
	492 goto (3, 4)
	493 -116 (3, 4)
	495 iload (2, 4)
	496 #4 (2, 4)
	497 iconst_1 (2, 4)
	498 iadd (2, 4)
	499 istore (2, 4)
	500 #5 (2, 4)
	501 iload (3, 4)
	502 #19 (3, 4)
	503 iconst_1 (3, 4)
	504 iadd (3, 4)
	505 istore (3, 4)
	506 #20 (3, 4)
	507 iload (3, 4)
	508 #20 (3, 4)
	509 aload_0 (3, 4)
	510 getfield (3, 4)
	511 org/apache/commons/math3/stat/regression/MillerUpdatingRegression.nvars:I (3, 4)
	513 if_icmpge (3, 4)
	514 87 (3, 4)
	516 aload (3, 4)
	517 #9 (3, 4)
	518 iload (3, 4)
	519 #20 (3, 4)
	520 iload (3, 4)
	521 #7 (3, 4)
	522 iadd (3, 4)
	523 dup2 (3, 4)
	524 daload (3, 4)
	525 aload_0 (3, 4)
	526 getfield (3, 4)
	527 org/apache/commons/math3/stat/regression/MillerUpdatingRegression.d:[D (3, 4)
	529 iload (3, 4)
	530 #19 (3, 4)
	531 daload (3, 4)
	532 aload_0 (3, 4)
	533 getfield (3, 4)
	534 org/apache/commons/math3/stat/regression/MillerUpdatingRegression.r:[D (3, 4)
	536 iload (3, 4)
	537 #5 (3, 4)
	538 daload (3, 4)
	539 dmul (3, 4)
	540 dadd (3, 4)
	541 dastore (3, 4)
	542 iinc (3, 4)
	543 #5 (3, 4)
	544 44 (3, 4)
	545 aload_2 (3, 4)
	546 iload (3, 4)
	547 #20 (3, 4)
	548 iconst_1 (3, 4)
	549 isub (3, 4)
	550 iload_1 (3, 4)
	551 isub (3, 4)
	552 iload (3, 4)
	553 #20 (3, 4)
	554 iload_1 (3, 4)
	555 isub (3, 4)
	556 imul (3, 4)
	557 iconst_2 (3, 4)
	558 idiv (3, 4)
	559 iload (3, 4)
	560 #19 (3, 4)
	561 iadd (3, 4)
	562 iload_1 (3, 4)
	563 isub (3, 4)
	564 aload (3, 4)
	565 #9 (3, 4)
	566 iload (3, 4)
	567 #20 (3, 4)
	568 iload (3, 4)
	569 #7 (3, 4)
	570 iadd (3, 4)
	571 daload (3, 4)
	572 aload (3, 4)
	573 #8 (3, 4)
	574 iload (3, 4)
	575 #19 (3, 4)
	576 iload (3, 4)
	577 #6 (3, 4)
	578 iadd (3, 4)
	579 daload (3, 4)
	580 dmul (3, 4)
	581 aload (3, 4)
	582 #8 (3, 4)
	583 iload (3, 4)
	584 #20 (3, 4)
	585 iload (3, 4)
	586 #6 (3, 4)
	587 iadd (3, 4)
	588 daload (3, 4)
	589 dmul (3, 4)
	590 dastore (3, 4)
	591 iinc (3, 4)
	592 #3 (3, 4)
	593 -124 (3, 4)
	594 iinc (3, 4)
	595 #20 (3, 4)
	596 -89 (3, 4)
	597 goto (3, 4)
	598 -90 (3, 4)
	600 dload (2, 4)
	601 #12 (2, 4)
	602 aload_0 (2, 4)
	603 getfield (2, 4)
	604 org/apache/commons/math3/stat/regression/MillerUpdatingRegression.d:[D (2, 4)
	606 iload (2, 4)
	607 #19 (2, 4)
	608 daload (2, 4)
	609 aload_0 (2, 4)
	610 getfield (2, 4)
	611 org/apache/commons/math3/stat/regression/MillerUpdatingRegression.rhs:[D (2, 4)
	613 iload (2, 4)
	614 #19 (2, 4)
	615 daload (2, 4)
	616 dmul (2, 4)
	617 dadd (2, 4)
	618 dstore (2, 4)
	619 #12 (2, 4)
	620 aload_2 (2, 4)
	621 iload (2, 4)
	622 #19 (2, 4)
	623 iload (2, 4)
	624 #6 (2, 4)
	625 iadd (2, 4)
	626 iload (2, 4)
	627 #16 (2, 4)
	628 iadd (2, 4)
	629 dload (2, 4)
	630 #12 (2, 4)
	631 aload (2, 4)
	632 #8 (2, 4)
	633 iload (2, 4)
	634 #19 (2, 4)
	635 iload (2, 4)
	636 #6 (2, 4)
	637 iadd (2, 4)
	638 daload (2, 4)
	639 dmul (2, 4)
	640 dload (2, 4)
	641 #14 (2, 4)
	642 dmul (2, 4)
	643 dastore (2, 4)
	644 iinc (2, 4)
	645 #19 (2, 4)
	646 -89 (2, 4)
	647 goto (2, 4)
	648 -303 (2, 4)
	650 aload_2 (1, 4)
	651 areturn (1, 4)

Method: vmove
	0 iconst_0 (0, 0)
	1 istore (0, 0)
	2 #25 (0, 0)
	3 iload_1 (1, 1)
	4 iload_2 (1, 1)
	5 if_icmpne (1, 1)
	6 4 (1, 1)
	8 return (1, 1)
	9 aload_0 (1, 1)
	10 getfield (1, 1)
	11 org/apache/commons/math3/stat/regression/MillerUpdatingRegression.rss_set:Z (1, 1)
	13 ifne (1, 1)
	14 7 (1, 1)
	16 aload_0 (1, 1)
	17 invokespecial (1, 1)
	18 org/apache/commons/math3/stat/regression/MillerUpdatingRegression.ss:()V (1, 1)
	20 iconst_0 (0, 0)
	21 istore (0, 0)
	22 #26 (0, 0)
	23 iload_1 (1, 1)
	24 iload_2 (1, 1)
	25 if_icmpge (1, 1)
	26 17 (1, 1)
	28 iload_1 (1, 1)
	29 istore (1, 1)
	30 #19 (1, 1)
	31 iconst_1 (1, 1)
	32 istore (1, 1)
	33 #20 (1, 1)
	34 iload_2 (1, 1)
	35 iload_1 (1, 1)
	36 isub (1, 1)
	37 istore (1, 1)
	38 #26 (1, 1)
	39 goto (1, 1)
	40 16 (1, 1)
	42 iload_1 (2, 2)
	43 iconst_1 (2, 2)
	44 isub (2, 2)
	45 istore (2, 2)
	46 #19 (2, 2)
	47 iconst_m1 (2, 2)
	48 istore (2, 2)
	49 #20 (2, 2)
	50 iload_1 (2, 2)
	51 iload_2 (2, 2)
	52 isub (2, 2)
	53 istore (2, 2)
	54 #26 (2, 2)
	55 iload (0, 0)
	56 #19 (0, 0)
	57 istore (0, 0)
	58 #27 (0, 0)
	59 iconst_0 (0, 0)
	60 istore (0, 0)
	61 #28 (0, 0)
	62 iload (1, 3)
	63 #28 (1, 3)
	64 iload (1, 3)
	65 #26 (1, 3)
	66 if_icmpge (1, 3)
	67 735 (1, 3)
	69 iload (1, 3)
	70 #27 (1, 3)
	71 aload_0 (1, 3)
	72 getfield (1, 3)
	73 org/apache/commons/math3/stat/regression/MillerUpdatingRegression.nvars:I (1, 3)
	75 aload_0 (1, 3)
	76 getfield (1, 3)
	77 org/apache/commons/math3/stat/regression/MillerUpdatingRegression.nvars:I (1, 3)
	79 iadd (1, 3)
	80 iload (1, 3)
	81 #27 (1, 3)
	82 isub (1, 3)
	83 iconst_1 (1, 3)
	84 isub (1, 3)
	85 imul (1, 3)
	86 iconst_2 (1, 3)
	87 idiv (1, 3)
	88 istore (1, 3)
	89 #21 (1, 3)
	90 iload (1, 3)
	91 #21 (1, 3)
	92 aload_0 (1, 3)
	93 getfield (1, 3)
	94 org/apache/commons/math3/stat/regression/MillerUpdatingRegression.nvars:I (1, 3)
	96 iadd (1, 3)
	97 iload (1, 3)
	98 #27 (1, 3)
	99 isub (1, 3)
	100 iconst_1 (1, 3)
	101 isub (1, 3)
	102 istore (1, 3)
	103 #22 (1, 3)
	104 iload (1, 3)
	105 #27 (1, 3)
	106 iconst_1 (1, 3)
	107 iadd (1, 3)
	108 istore (1, 3)
	109 #23 (1, 3)
	110 aload_0 (1, 3)
	111 getfield (1, 3)
	112 org/apache/commons/math3/stat/regression/MillerUpdatingRegression.d:[D (1, 3)
	114 iload (1, 3)
	115 #27 (1, 3)
	116 daload (1, 3)
	117 dstore_3 (1, 3)
	118 aload_0 (1, 3)
	119 getfield (1, 3)
	120 org/apache/commons/math3/stat/regression/MillerUpdatingRegression.d:[D (1, 3)
	122 iload (1, 3)
	123 #23 (1, 3)
	124 daload (1, 3)
	125 dstore (1, 3)
	126 #5 (1, 3)
	127 dload_3 (2, 1)
	128 aload_0 (2, 1)
	129 getfield (2, 1)
	130 org/apache/commons/math3/stat/regression/MillerUpdatingRegression.epsilon:D (2, 1)
	132 dcmpl (2, 1)
	133 ifgt (2, 1)
	134 13 (2, 1)
	136 dload (2, 1)
	137 #5 (2, 1)
	138 aload_0 (2, 1)
	139 getfield (2, 1)
	140 org/apache/commons/math3/stat/regression/MillerUpdatingRegression.epsilon:D (2, 1)
	142 dcmpl (2, 1)
	143 ifle (2, 1)
	144 468 (2, 1)
	146 aload_0 (2, 1)
	147 getfield (2, 1)
	148 org/apache/commons/math3/stat/regression/MillerUpdatingRegression.r:[D (2, 1)
	150 iload (2, 1)
	151 #21 (2, 1)
	152 daload (2, 1)
	153 dstore (2, 1)
	154 #7 (2, 1)
	155 dload (3, 1)
	156 #7 (3, 1)
	157 invokestatic (3, 1)
	158 org/apache/commons/math3/util/FastMath.abs:(D)D (3, 1)
	160 dload_3 (3, 1)
	161 invokestatic (3, 1)
	162 org/apache/commons/math3/util/FastMath.sqrt:(D)D (3, 1)
	164 dmul (3, 1)
	165 aload_0 (3, 1)
	166 getfield (3, 1)
	167 org/apache/commons/math3/stat/regression/MillerUpdatingRegression.tol:[D (3, 1)
	169 iload (3, 1)
	170 #23 (3, 1)
	171 daload (3, 1)
	172 dcmpg (3, 1)
	173 ifge (3, 1)
	174 6 (3, 1)
	176 dconst_0 (3, 1)
	177 dstore (3, 1)
	178 #7 (3, 1)
	179 dload_3 (3, 1)
	180 aload_0 (3, 1)
	181 getfield (3, 1)
	182 org/apache/commons/math3/stat/regression/MillerUpdatingRegression.epsilon:D (3, 1)
	184 dcmpg (3, 1)
	185 iflt (3, 1)
	186 16 (3, 1)
	188 dload (3, 1)
	189 #7 (3, 1)
	190 invokestatic (3, 1)
	191 org/apache/commons/math3/util/FastMath.abs:(D)D (3, 1)
	193 aload_0 (3, 1)
	194 getfield (3, 1)
	195 org/apache/commons/math3/stat/regression/MillerUpdatingRegression.epsilon:D (3, 1)
	197 dcmpg (3, 1)
	198 ifge (3, 1)
	199 125 (3, 1)
	201 aload_0 (3, 1)
	202 getfield (3, 1)
	203 org/apache/commons/math3/stat/regression/MillerUpdatingRegression.d:[D (3, 1)
	205 iload (3, 1)
	206 #27 (3, 1)
	207 dload (3, 1)
	208 #5 (3, 1)
	209 dastore (3, 1)
	210 aload_0 (3, 1)
	211 getfield (3, 1)
	212 org/apache/commons/math3/stat/regression/MillerUpdatingRegression.d:[D (3, 1)
	214 iload (3, 1)
	215 #23 (3, 1)
	216 dload_3 (3, 1)
	217 dastore (3, 1)
	218 aload_0 (3, 1)
	219 getfield (3, 1)
	220 org/apache/commons/math3/stat/regression/MillerUpdatingRegression.r:[D (3, 1)
	222 iload (3, 1)
	223 #21 (3, 1)
	224 dconst_0 (3, 1)
	225 dastore (3, 1)
	226 iload (4, 4)
	227 #27 (4, 4)
	228 iconst_2 (4, 4)
	229 iadd (4, 4)
	230 istore (4, 4)
	231 #29 (4, 4)
	232 iload (4, 4)
	233 #29 (4, 4)
	234 aload_0 (4, 4)
	235 getfield (4, 4)
	236 org/apache/commons/math3/stat/regression/MillerUpdatingRegression.nvars:I (4, 4)
	238 if_icmpge (4, 4)
	239 47 (4, 4)
	241 iinc (4, 4)
	242 #21 (4, 4)
	243 42 (4, 4)
	244 aload_0 (4, 4)
	245 getfield (4, 4)
	246 org/apache/commons/math3/stat/regression/MillerUpdatingRegression.r:[D (4, 4)
	248 iload (4, 4)
	249 #21 (4, 4)
	250 daload (4, 4)
	251 dstore (4, 4)
	252 #7 (4, 4)
	253 aload_0 (4, 4)
	254 getfield (4, 4)
	255 org/apache/commons/math3/stat/regression/MillerUpdatingRegression.r:[D (4, 4)
	257 iload (4, 4)
	258 #21 (4, 4)
	259 aload_0 (4, 4)
	260 getfield (4, 4)
	261 org/apache/commons/math3/stat/regression/MillerUpdatingRegression.r:[D (4, 4)
	263 iload (4, 4)
	264 #22 (4, 4)
	265 daload (4, 4)
	266 dastore (4, 4)
	267 aload_0 (4, 4)
	268 getfield (4, 4)
	269 org/apache/commons/math3/stat/regression/MillerUpdatingRegression.r:[D (4, 4)
	271 iload (4, 4)
	272 #22 (4, 4)
	273 dload (4, 4)
	274 #7 (4, 4)
	275 dastore (4, 4)
	276 iinc (4, 4)
	277 #22 (4, 4)
	278 -124 (4, 4)
	279 iinc (4, 4)
	280 #29 (4, 4)
	281 -89 (4, 4)
	282 goto (4, 4)
	283 -50 (4, 4)
	285 aload_0 (3, 1)
	286 getfield (3, 1)
	287 org/apache/commons/math3/stat/regression/MillerUpdatingRegression.rhs:[D (3, 1)
	289 iload (3, 1)
	290 #27 (3, 1)
	291 daload (3, 1)
	292 dstore (3, 1)
	293 #7 (3, 1)
	294 aload_0 (3, 1)
	295 getfield (3, 1)
	296 org/apache/commons/math3/stat/regression/MillerUpdatingRegression.rhs:[D (3, 1)
	298 iload (3, 1)
	299 #27 (3, 1)
	300 aload_0 (3, 1)
	301 getfield (3, 1)
	302 org/apache/commons/math3/stat/regression/MillerUpdatingRegression.rhs:[D (3, 1)
	304 iload (3, 1)
	305 #23 (3, 1)
	306 daload (3, 1)
	307 dastore (3, 1)
	308 aload_0 (3, 1)
	309 getfield (3, 1)
	310 org/apache/commons/math3/stat/regression/MillerUpdatingRegression.rhs:[D (3, 1)
	312 iload (3, 1)
	313 #23 (3, 1)
	314 dload (3, 1)
	315 #7 (3, 1)
	316 dastore (3, 1)
	317 iconst_1 (3, 1)
	318 istore (3, 1)
	319 #25 (3, 1)
	320 goto (3, 1)
	321 94 (3, 1)
	323 dload (4, 1)
	324 #5 (4, 1)
	325 aload_0 (4, 1)
	326 getfield (4, 1)
	327 org/apache/commons/math3/stat/regression/MillerUpdatingRegression.epsilon:D (4, 1)
	329 dcmpg (4, 1)
	330 ifge (4, 1)
	331 84 (4, 1)
	333 aload_0 (4, 1)
	334 getfield (4, 1)
	335 org/apache/commons/math3/stat/regression/MillerUpdatingRegression.d:[D (4, 1)
	337 iload (4, 1)
	338 #27 (4, 1)
	339 dload_3 (4, 1)
	340 dload (4, 1)
	341 #7 (4, 1)
	342 dmul (4, 1)
	343 dload (4, 1)
	344 #7 (4, 1)
	345 dmul (4, 1)
	346 dastore (4, 1)
	347 aload_0 (4, 1)
	348 getfield (4, 1)
	349 org/apache/commons/math3/stat/regression/MillerUpdatingRegression.r:[D (4, 1)
	351 iload (4, 1)
	352 #21 (4, 1)
	353 dconst_1 (4, 1)
	354 dload (4, 1)
	355 #7 (4, 1)
	356 ddiv (4, 1)
	357 dastore (4, 1)
	358 iload (5, 4)
	359 #21 (5, 4)
	360 iconst_1 (5, 4)
	361 iadd (5, 4)
	362 istore (5, 4)
	363 #29 (5, 4)
	364 iload (5, 4)
	365 #29 (5, 4)
	366 iload (5, 4)
	367 #21 (5, 4)
	368 aload_0 (5, 4)
	369 getfield (5, 4)
	370 org/apache/commons/math3/stat/regression/MillerUpdatingRegression.nvars:I (5, 4)
	372 iadd (5, 4)
	373 iload (5, 4)
	374 #27 (5, 4)
	375 isub (5, 4)
	376 iconst_1 (5, 4)
	377 isub (5, 4)
	378 if_icmpge (5, 4)
	379 21 (5, 4)
	381 aload_0 (5, 4)
	382 getfield (5, 4)
	383 org/apache/commons/math3/stat/regression/MillerUpdatingRegression.r:[D (5, 4)
	385 iload (5, 4)
	386 #29 (5, 4)
	387 dup2 (5, 4)
	388 daload (5, 4)
	389 dload (5, 4)
	390 #7 (5, 4)
	391 ddiv (5, 4)
	392 dastore (5, 4)
	393 iinc (5, 4)
	394 #29 (5, 4)
	395 -89 (5, 4)
	396 goto (5, 4)
	397 -32 (5, 4)
	399 aload_0 (4, 1)
	400 getfield (4, 1)
	401 org/apache/commons/math3/stat/regression/MillerUpdatingRegression.rhs:[D (4, 1)
	403 iload (4, 1)
	404 #27 (4, 1)
	405 dup2 (4, 1)
	406 daload (4, 1)
	407 dload (4, 1)
	408 #7 (4, 1)
	409 ddiv (4, 1)
	410 dastore (4, 1)
	411 iconst_1 (4, 1)
	412 istore (4, 1)
	413 #25 (4, 1)
	414 iload (3, 1)
	415 #25 (3, 1)
	416 ifne (3, 1)
	417 195 (3, 1)
	419 dload (3, 1)
	420 #5 (3, 1)
	421 dload_3 (3, 1)
	422 dload (3, 1)
	423 #7 (3, 1)
	424 dmul (3, 1)
	425 dload (3, 1)
	426 #7 (3, 1)
	427 dmul (3, 1)
	428 dadd (3, 1)
	429 dstore (3, 1)
	430 #9 (3, 1)
	431 dload (3, 1)
	432 #5 (3, 1)
	433 dload (3, 1)
	434 #9 (3, 1)
	435 ddiv (3, 1)
	436 dstore (3, 1)
	437 #13 (3, 1)
	438 dload (3, 1)
	439 #7 (3, 1)
	440 dload_3 (3, 1)
	441 dmul (3, 1)
	442 dload (3, 1)
	443 #9 (3, 1)
	444 ddiv (3, 1)
	445 dstore (3, 1)
	446 #15 (3, 1)
	447 dload_3 (3, 1)
	448 dload (3, 1)
	449 #13 (3, 1)
	450 dmul (3, 1)
	451 dstore (3, 1)
	452 #11 (3, 1)
	453 aload_0 (3, 1)
	454 getfield (3, 1)
	455 org/apache/commons/math3/stat/regression/MillerUpdatingRegression.d:[D (3, 1)
	457 iload (3, 1)
	458 #27 (3, 1)
	459 dload (3, 1)
	460 #9 (3, 1)
	461 dastore (3, 1)
	462 aload_0 (3, 1)
	463 getfield (3, 1)
	464 org/apache/commons/math3/stat/regression/MillerUpdatingRegression.d:[D (3, 1)
	466 iload (3, 1)
	467 #23 (3, 1)
	468 dload (3, 1)
	469 #11 (3, 1)
	470 dastore (3, 1)
	471 aload_0 (3, 1)
	472 getfield (3, 1)
	473 org/apache/commons/math3/stat/regression/MillerUpdatingRegression.r:[D (3, 1)
	475 iload (3, 1)
	476 #21 (3, 1)
	477 dload (3, 1)
	478 #15 (3, 1)
	479 dastore (3, 1)
	480 iload (4, 4)
	481 #27 (4, 4)
	482 iconst_2 (4, 4)
	483 iadd (4, 4)
	484 istore (4, 4)
	485 #29 (4, 4)
	486 iload (4, 4)
	487 #29 (4, 4)
	488 aload_0 (4, 4)
	489 getfield (4, 4)
	490 org/apache/commons/math3/stat/regression/MillerUpdatingRegression.nvars:I (4, 4)
	492 if_icmpge (4, 4)
	493 67 (4, 4)
	495 iinc (4, 4)
	496 #21 (4, 4)
	497 42 (4, 4)
	498 aload_0 (4, 4)
	499 getfield (4, 4)
	500 org/apache/commons/math3/stat/regression/MillerUpdatingRegression.r:[D (4, 4)
	502 iload (4, 4)
	503 #21 (4, 4)
	504 daload (4, 4)
	505 dstore (4, 4)
	506 #17 (4, 4)
	507 aload_0 (4, 4)
	508 getfield (4, 4)
	509 org/apache/commons/math3/stat/regression/MillerUpdatingRegression.r:[D (4, 4)
	511 iload (4, 4)
	512 #21 (4, 4)
	513 dload (4, 4)
	514 #13 (4, 4)
	515 aload_0 (4, 4)
	516 getfield (4, 4)
	517 org/apache/commons/math3/stat/regression/MillerUpdatingRegression.r:[D (4, 4)
	519 iload (4, 4)
	520 #22 (4, 4)
	521 daload (4, 4)
	522 dmul (4, 4)
	523 dload (4, 4)
	524 #15 (4, 4)
	525 dload (4, 4)
	526 #17 (4, 4)
	527 dmul (4, 4)
	528 dadd (4, 4)
	529 dastore (4, 4)
	530 aload_0 (4, 4)
	531 getfield (4, 4)
	532 org/apache/commons/math3/stat/regression/MillerUpdatingRegression.r:[D (4, 4)
	534 iload (4, 4)
	535 #22 (4, 4)
	536 dload (4, 4)
	537 #17 (4, 4)
	538 dload (4, 4)
	539 #7 (4, 4)
	540 aload_0 (4, 4)
	541 getfield (4, 4)
	542 org/apache/commons/math3/stat/regression/MillerUpdatingRegression.r:[D (4, 4)
	544 iload (4, 4)
	545 #22 (4, 4)
	546 daload (4, 4)
	547 dmul (4, 4)
	548 dsub (4, 4)
	549 dastore (4, 4)
	550 iinc (4, 4)
	551 #22 (4, 4)
	552 -124 (4, 4)
	553 iinc (4, 4)
	554 #29 (4, 4)
	555 -89 (4, 4)
	556 goto (4, 4)
	557 -70 (4, 4)
	559 aload_0 (3, 1)
	560 getfield (3, 1)
	561 org/apache/commons/math3/stat/regression/MillerUpdatingRegression.rhs:[D (3, 1)
	563 iload (3, 1)
	564 #27 (3, 1)
	565 daload (3, 1)
	566 dstore (3, 1)
	567 #17 (3, 1)
	568 aload_0 (3, 1)
	569 getfield (3, 1)
	570 org/apache/commons/math3/stat/regression/MillerUpdatingRegression.rhs:[D (3, 1)
	572 iload (3, 1)
	573 #27 (3, 1)
	574 dload (3, 1)
	575 #13 (3, 1)
	576 aload_0 (3, 1)
	577 getfield (3, 1)
	578 org/apache/commons/math3/stat/regression/MillerUpdatingRegression.rhs:[D (3, 1)
	580 iload (3, 1)
	581 #23 (3, 1)
	582 daload (3, 1)
	583 dmul (3, 1)
	584 dload (3, 1)
	585 #15 (3, 1)
	586 dload (3, 1)
	587 #17 (3, 1)
	588 dmul (3, 1)
	589 dadd (3, 1)
	590 dastore (3, 1)
	591 aload_0 (3, 1)
	592 getfield (3, 1)
	593 org/apache/commons/math3/stat/regression/MillerUpdatingRegression.rhs:[D (3, 1)
	595 iload (3, 1)
	596 #23 (3, 1)
	597 dload (3, 1)
	598 #17 (3, 1)
	599 dload (3, 1)
	600 #7 (3, 1)
	601 aload_0 (3, 1)
	602 getfield (3, 1)
	603 org/apache/commons/math3/stat/regression/MillerUpdatingRegression.rhs:[D (3, 1)
	605 iload (3, 1)
	606 #23 (3, 1)
	607 daload (3, 1)
	608 dmul (3, 1)
	609 dsub (3, 1)
	610 dastore (3, 1)
	611 iload (2, 1)
	612 #27 (2, 1)
	613 ifle (2, 1)
	614 73 (2, 1)
	616 iload (2, 1)
	617 #27 (2, 1)
	618 istore (2, 1)
	619 #24 (2, 1)
	620 iconst_0 (3, 4)
	621 istore (3, 4)
	622 #29 (3, 4)
	623 iload (3, 4)
	624 #29 (3, 4)
	625 iload (3, 4)
	626 #27 (3, 4)
	627 if_icmpge (3, 4)
	628 59 (3, 4)
	630 aload_0 (3, 4)
	631 getfield (3, 4)
	632 org/apache/commons/math3/stat/regression/MillerUpdatingRegression.r:[D (3, 4)
	634 iload (3, 4)
	635 #24 (3, 4)
	636 daload (3, 4)
	637 dstore (3, 4)
	638 #7 (3, 4)
	639 aload_0 (3, 4)
	640 getfield (3, 4)
	641 org/apache/commons/math3/stat/regression/MillerUpdatingRegression.r:[D (3, 4)
	643 iload (3, 4)
	644 #24 (3, 4)
	645 aload_0 (3, 4)
	646 getfield (3, 4)
	647 org/apache/commons/math3/stat/regression/MillerUpdatingRegression.r:[D (3, 4)
	649 iload (3, 4)
	650 #24 (3, 4)
	651 iconst_1 (3, 4)
	652 isub (3, 4)
	653 daload (3, 4)
	654 dastore (3, 4)
	655 aload_0 (3, 4)
	656 getfield (3, 4)
	657 org/apache/commons/math3/stat/regression/MillerUpdatingRegression.r:[D (3, 4)
	659 iload (3, 4)
	660 #24 (3, 4)
	661 iconst_1 (3, 4)
	662 isub (3, 4)
	663 dload (3, 4)
	664 #7 (3, 4)
	665 dastore (3, 4)
	666 iload (3, 4)
	667 #24 (3, 4)
	668 aload_0 (3, 4)
	669 getfield (3, 4)
	670 org/apache/commons/math3/stat/regression/MillerUpdatingRegression.nvars:I (3, 4)
	672 iload (3, 4)
	673 #29 (3, 4)
	674 isub (3, 4)
	675 iconst_2 (3, 4)
	676 isub (3, 4)
	677 iadd (3, 4)
	678 istore (3, 4)
	679 #24 (3, 4)
	680 iinc (3, 4)
	681 #29 (3, 4)
	682 -89 (3, 4)
	683 goto (3, 4)
	684 -60 (3, 4)
	686 aload_0 (1, 3)
	687 getfield (1, 3)
	688 org/apache/commons/math3/stat/regression/MillerUpdatingRegression.vorder:[I (1, 3)
	690 iload (1, 3)
	691 #27 (1, 3)
	692 iaload (1, 3)
	693 istore (1, 3)
	694 #21 (1, 3)
	695 aload_0 (1, 3)
	696 getfield (1, 3)
	697 org/apache/commons/math3/stat/regression/MillerUpdatingRegression.vorder:[I (1, 3)
	699 iload (1, 3)
	700 #27 (1, 3)
	701 aload_0 (1, 3)
	702 getfield (1, 3)
	703 org/apache/commons/math3/stat/regression/MillerUpdatingRegression.vorder:[I (1, 3)
	705 iload (1, 3)
	706 #23 (1, 3)
	707 iaload (1, 3)
	708 iastore (1, 3)
	709 aload_0 (1, 3)
	710 getfield (1, 3)
	711 org/apache/commons/math3/stat/regression/MillerUpdatingRegression.vorder:[I (1, 3)
	713 iload (1, 3)
	714 #23 (1, 3)
	715 iload (1, 3)
	716 #21 (1, 3)
	717 iastore (1, 3)
	718 aload_0 (1, 3)
	719 getfield (1, 3)
	720 org/apache/commons/math3/stat/regression/MillerUpdatingRegression.tol:[D (1, 3)
	722 iload (1, 3)
	723 #27 (1, 3)
	724 daload (1, 3)
	725 dstore (1, 3)
	726 #7 (1, 3)
	727 aload_0 (1, 3)
	728 getfield (1, 3)
	729 org/apache/commons/math3/stat/regression/MillerUpdatingRegression.tol:[D (1, 3)
	731 iload (1, 3)
	732 #27 (1, 3)
	733 aload_0 (1, 3)
	734 getfield (1, 3)
	735 org/apache/commons/math3/stat/regression/MillerUpdatingRegression.tol:[D (1, 3)
	737 iload (1, 3)
	738 #23 (1, 3)
	739 daload (1, 3)
	740 dastore (1, 3)
	741 aload_0 (1, 3)
	742 getfield (1, 3)
	743 org/apache/commons/math3/stat/regression/MillerUpdatingRegression.tol:[D (1, 3)
	745 iload (1, 3)
	746 #23 (1, 3)
	747 dload (1, 3)
	748 #7 (1, 3)
	749 dastore (1, 3)
	750 aload_0 (1, 3)
	751 getfield (1, 3)
	752 org/apache/commons/math3/stat/regression/MillerUpdatingRegression.rss:[D (1, 3)
	754 iload (1, 3)
	755 #27 (1, 3)
	756 aload_0 (1, 3)
	757 getfield (1, 3)
	758 org/apache/commons/math3/stat/regression/MillerUpdatingRegression.rss:[D (1, 3)
	760 iload (1, 3)
	761 #23 (1, 3)
	762 daload (1, 3)
	763 aload_0 (1, 3)
	764 getfield (1, 3)
	765 org/apache/commons/math3/stat/regression/MillerUpdatingRegression.d:[D (1, 3)
	767 iload (1, 3)
	768 #23 (1, 3)
	769 daload (1, 3)
	770 aload_0 (1, 3)
	771 getfield (1, 3)
	772 org/apache/commons/math3/stat/regression/MillerUpdatingRegression.rhs:[D (1, 3)
	774 iload (1, 3)
	775 #23 (1, 3)
	776 daload (1, 3)
	777 dmul (1, 3)
	778 aload_0 (1, 3)
	779 getfield (1, 3)
	780 org/apache/commons/math3/stat/regression/MillerUpdatingRegression.rhs:[D (1, 3)
	782 iload (1, 3)
	783 #23 (1, 3)
	784 daload (1, 3)
	785 dmul (1, 3)
	786 dadd (1, 3)
	787 dastore (1, 3)
	788 iload (1, 3)
	789 #27 (1, 3)
	790 iload (1, 3)
	791 #20 (1, 3)
	792 iadd (1, 3)
	793 istore (1, 3)
	794 #27 (1, 3)
	795 iinc (1, 3)
	796 #28 (1, 3)
	797 -89 (1, 3)
	798 goto (1, 3)
	799 -736 (1, 3)
	801 return (0, 0)

Method: reorderRegressors
	0 aload_1 (1, 1)
	1 arraylength (1, 1)
	2 iconst_1 (1, 1)
	3 if_icmplt (1, 1)
	4 16 (1, 1)
	6 aload_1 (1, 1)
	7 arraylength (1, 1)
	8 aload_0 (1, 1)
	9 getfield (1, 1)
	10 org/apache/commons/math3/stat/regression/MillerUpdatingRegression.nvars:I (1, 1)
	12 iconst_1 (1, 1)
	13 iadd (1, 1)
	14 iload_2 (1, 1)
	15 isub (1, 1)
	16 if_icmple (1, 1)
	17 5 (1, 1)
	19 iconst_m1 (1, 1)
	20 ireturn (1, 1)
	21 iload_2 (0, 0)
	22 istore_3 (0, 0)
	23 iload_2 (0, 0)
	24 istore (0, 0)
	25 #4 (0, 0)
	26 iload (1, 3)
	27 #4 (1, 3)
	28 aload_0 (1, 3)
	29 getfield (1, 3)
	30 org/apache/commons/math3/stat/regression/MillerUpdatingRegression.nvars:I (1, 3)
	32 if_icmpge (1, 3)
	33 69 (1, 3)
	35 aload_0 (1, 3)
	36 getfield (1, 3)
	37 org/apache/commons/math3/stat/regression/MillerUpdatingRegression.vorder:[I (1, 3)
	39 iload (1, 3)
	40 #4 (1, 3)
	41 iaload (1, 3)
	42 istore (1, 3)
	43 #5 (1, 3)
	44 iconst_0 (2, 4)
	45 istore (2, 4)
	46 #6 (2, 4)
	47 iload (2, 4)
	48 #6 (2, 4)
	49 aload_1 (2, 4)
	50 arraylength (2, 4)
	51 if_icmpge (2, 4)
	52 44 (2, 4)
	54 iload (3, 1)
	55 #5 (3, 1)
	56 aload_1 (3, 1)
	57 iload (3, 1)
	58 #6 (3, 1)
	59 iaload (3, 1)
	60 if_icmpne (3, 1)
	61 29 (3, 1)
	63 iload (3, 1)
	64 #4 (3, 1)
	65 iload_3 (3, 1)
	66 if_icmple (3, 1)
	67 23 (3, 1)
	69 aload_0 (3, 1)
	70 iload (3, 1)
	71 #4 (3, 1)
	72 iload_3 (3, 1)
	73 invokespecial (3, 1)
	74 org/apache/commons/math3/stat/regression/MillerUpdatingRegression.vmove:(II)V (3, 1)
	76 iinc (3, 1)
	77 #3 (3, 1)
	78 29 (3, 1)
	79 iload_3 (4, 1)
	80 aload_1 (4, 1)
	81 arraylength (4, 1)
	82 iload_2 (4, 1)
	83 iadd (4, 1)
	84 if_icmplt (4, 1)
	85 11 (4, 1)
	87 iconst_0 (4, 1)
	88 ireturn (4, 1)
	89 iinc (4, 1)
	90 #6 (4, 1)
	91 -89 (4, 1)
	92 goto (4, 1)
	93 -45 (4, 1)
	95 iinc (3, 1)
	96 #4 (3, 1)
	97 -89 (3, 1)
	98 goto (3, 1)
	99 -72 (3, 1)
	101 iconst_0 (2, 4)
	102 ireturn (2, 4)

Method: getDiagonalOfHatMatrix
	0 aload_0 (0, 0)
	1 getfield (0, 0)
	2 org/apache/commons/math3/stat/regression/MillerUpdatingRegression.nvars:I (0, 0)
	4 newarray (0, 0)
	5 7 (0, 0)
	6 astore_2 (0, 0)
	7 aload_1 (1, 1)
	8 arraylength (1, 1)
	9 aload_0 (1, 1)
	10 getfield (1, 1)
	11 org/apache/commons/math3/stat/regression/MillerUpdatingRegression.nvars:I (1, 1)
	13 if_icmple (1, 1)
	14 7 (1, 1)
	16 ldc2_w (1, 1)
	17 nan (1, 1)
	19 dreturn (1, 1)
	20 aload_0 (1, 1)
	21 getfield (1, 1)
	22 org/apache/commons/math3/stat/regression/MillerUpdatingRegression.hasIntercept:Z (1, 1)
	24 ifeq (1, 1)
	25 29 (1, 1)
	27 aload_1 (1, 1)
	28 arraylength (1, 1)
	29 iconst_1 (1, 1)
	30 iadd (1, 1)
	31 newarray (1, 1)
	32 7 (1, 1)
	33 astore (1, 1)
	34 #6 (1, 1)
	35 aload (1, 1)
	36 #6 (1, 1)
	37 iconst_0 (1, 1)
	38 dconst_1 (1, 1)
	39 dastore (1, 1)
	40 aload_1 (1, 1)
	41 iconst_0 (1, 1)
	42 aload (1, 1)
	43 #6 (1, 1)
	44 iconst_1 (1, 1)
	45 aload_1 (1, 1)
	46 arraylength (1, 1)
	47 invokestatic (1, 1)
	48 java/lang/System.arraycopy:(Ljava/lang/Object;ILjava/lang/Object;II)V (1, 1)
	50 goto (1, 1)
	51 6 (1, 1)
	53 aload_1 (2, 2)
	54 astore (2, 2)
	55 #6 (2, 2)
	56 dconst_0 (0, 0)
	57 dstore (0, 0)
	58 #7 (0, 0)
	59 iconst_0 (1, 4)
	60 istore (1, 4)
	61 #9 (1, 4)
	62 iload (1, 4)
	63 #9 (1, 4)
	64 aload (1, 4)
	65 #6 (1, 4)
	66 arraylength (1, 4)
	67 if_icmpge (1, 4)
	68 125 (1, 4)
	70 aload_0 (2, 1)
	71 getfield (2, 1)
	72 org/apache/commons/math3/stat/regression/MillerUpdatingRegression.d:[D (2, 1)
	74 iload (2, 1)
	75 #9 (2, 1)
	76 daload (2, 1)
	77 invokestatic (2, 1)
	78 org/apache/commons/math3/util/FastMath.sqrt:(D)D (2, 1)
	80 aload_0 (2, 1)
	81 getfield (2, 1)
	82 org/apache/commons/math3/stat/regression/MillerUpdatingRegression.tol:[D (2, 1)
	84 iload (2, 1)
	85 #9 (2, 1)
	86 daload (2, 1)
	87 dcmpg (2, 1)
	88 ifge (2, 1)
	89 11 (2, 1)
	91 aload_2 (2, 1)
	92 iload (2, 1)
	93 #9 (2, 1)
	94 dconst_0 (2, 1)
	95 dastore (2, 1)
	96 goto (2, 1)
	97 90 (2, 1)
	99 iload (3, 2)
	100 #9 (3, 2)
	101 iconst_1 (3, 2)
	102 isub (3, 2)
	103 istore_3 (3, 2)
	104 aload (3, 2)
	105 #6 (3, 2)
	106 iload (3, 2)
	107 #9 (3, 2)
	108 daload (3, 2)
	109 dstore (3, 2)
	110 #4 (3, 2)
	111 iconst_0 (4, 4)
	112 istore (4, 4)
	113 #10 (4, 4)
	114 iload (4, 4)
	115 #10 (4, 4)
	116 iload (4, 4)
	117 #9 (4, 4)
	118 if_icmpge (4, 4)
	119 41 (4, 4)
	121 aload_0 (4, 4)
	122 dload (4, 4)
	123 #4 (4, 4)
	124 aload_2 (4, 4)
	125 iload (4, 4)
	126 #10 (4, 4)
	127 daload (4, 4)
	128 dneg (4, 4)
	129 aload_0 (4, 4)
	130 getfield (4, 4)
	131 org/apache/commons/math3/stat/regression/MillerUpdatingRegression.r:[D (4, 4)
	133 iload_3 (4, 4)
	134 daload (4, 4)
	135 dmul (4, 4)
	136 invokespecial (4, 4)
	137 org/apache/commons/math3/stat/regression/MillerUpdatingRegression.smartAdd:(DD)D (4, 4)
	139 dstore (4, 4)
	140 #4 (4, 4)
	141 iload_3 (4, 4)
	142 aload_0 (4, 4)
	143 getfield (4, 4)
	144 org/apache/commons/math3/stat/regression/MillerUpdatingRegression.nvars:I (4, 4)
	146 iload (4, 4)
	147 #10 (4, 4)
	148 isub (4, 4)
	149 iconst_2 (4, 4)
	150 isub (4, 4)
	151 iadd (4, 4)
	152 istore_3 (4, 4)
	153 iinc (4, 4)
	154 #10 (4, 4)
	155 -89 (4, 4)
	156 goto (4, 4)
	157 -42 (4, 4)
	159 aload_2 (3, 2)
	160 iload (3, 2)
	161 #9 (3, 2)
	162 dload (3, 2)
	163 #4 (3, 2)
	164 dastore (3, 2)
	165 aload_0 (3, 2)
	166 dload (3, 2)
	167 #7 (3, 2)
	168 dload (3, 2)
	169 #4 (3, 2)
	170 dload (3, 2)
	171 #4 (3, 2)
	172 dmul (3, 2)
	173 aload_0 (3, 2)
	174 getfield (3, 2)
	175 org/apache/commons/math3/stat/regression/MillerUpdatingRegression.d:[D (3, 2)
	177 iload (3, 2)
	178 #9 (3, 2)
	179 daload (3, 2)
	180 ddiv (3, 2)
	181 invokespecial (3, 2)
	182 org/apache/commons/math3/stat/regression/MillerUpdatingRegression.smartAdd:(DD)D (3, 2)
	184 dstore (3, 2)
	185 #7 (3, 2)
	186 iinc (3, 2)
	187 #9 (3, 2)
	188 -89 (3, 2)
	189 goto (3, 2)
	190 -127 (3, 2)
	192 dload (1, 4)
	193 #7 (1, 4)
	194 dreturn (1, 4)

Method: getOrderOfRegressors
	0 aload_0 (0, 0)
	1 getfield (0, 0)
	2 org/apache/commons/math3/stat/regression/MillerUpdatingRegression.vorder:[I (0, 0)
	4 invokestatic (0, 0)
	5 org/apache/commons/math3/util/MathArrays.copyOf:([I)[I (0, 0)
	7 areturn (0, 0)

Method: regress
	0 aload_1 (1, 1)
	1 arraylength (1, 1)
	2 aload_0 (1, 1)
	3 getfield (1, 1)
	4 org/apache/commons/math3/stat/regression/MillerUpdatingRegression.nvars:I (1, 1)
	6 if_icmple (1, 1)
	7 36 (1, 1)
	9 new (2, 1)
	10 org/apache/commons/math3/stat/regression/ModelSpecificationException (2, 1)
	12 dup (2, 1)
	13 getstatic (2, 1)
	14 org/apache/commons/math3/exception/util/LocalizedFormats.TOO_MANY_REGRESSORS:Lorg/apache/commons/math3/exception/util/LocalizedFormats; (2, 1)
	16 iconst_2 (2, 1)
	17 anewarray (2, 1)
	18 java/lang/Object (2, 1)
	20 dup (2, 1)
	21 iconst_0 (2, 1)
	22 aload_1 (2, 1)
	23 arraylength (2, 1)
	24 invokestatic (2, 1)
	25 java/lang/Integer.valueOf:(I)Ljava/lang/Integer; (2, 1)
	27 aastore (2, 1)
	28 dup (2, 1)
	29 iconst_1 (2, 1)
	30 aload_0 (2, 1)
	31 getfield (2, 1)
	32 org/apache/commons/math3/stat/regression/MillerUpdatingRegression.nvars:I (2, 1)
	34 invokestatic (2, 1)
	35 java/lang/Integer.valueOf:(I)Ljava/lang/Integer; (2, 1)
	37 aastore (2, 1)
	38 invokespecial (2, 1)
	39 org/apache/commons/math3/stat/regression/ModelSpecificationException.<init>:(Lorg/apache/commons/math3/exception/util/Localizable;[Ljava/lang/Object;)V (2, 1)
	41 athrow (2, 1)
	42 aload_0 (1, 1)
	43 getfield (1, 1)
	44 org/apache/commons/math3/stat/regression/MillerUpdatingRegression.nobs:J (1, 1)
	46 aload_0 (1, 1)
	47 getfield (1, 1)
	48 org/apache/commons/math3/stat/regression/MillerUpdatingRegression.nvars:I (1, 1)
	50 i2l (1, 1)
	51 lcmp (1, 1)
	52 ifgt (1, 1)
	53 38 (1, 1)
	55 new (2, 1)
	56 org/apache/commons/math3/stat/regression/ModelSpecificationException (2, 1)
	58 dup (2, 1)
	59 getstatic (2, 1)
	60 org/apache/commons/math3/exception/util/LocalizedFormats.NOT_ENOUGH_DATA_FOR_NUMBER_OF_PREDICTORS:Lorg/apache/commons/math3/exception/util/LocalizedFormats; (2, 1)
	62 iconst_2 (2, 1)
	63 anewarray (2, 1)
	64 java/lang/Object (2, 1)
	66 dup (2, 1)
	67 iconst_0 (2, 1)
	68 aload_0 (2, 1)
	69 getfield (2, 1)
	70 org/apache/commons/math3/stat/regression/MillerUpdatingRegression.nobs:J (2, 1)
	72 invokestatic (2, 1)
	73 java/lang/Long.valueOf:(J)Ljava/lang/Long; (2, 1)
	75 aastore (2, 1)
	76 dup (2, 1)
	77 iconst_1 (2, 1)
	78 aload_0 (2, 1)
	79 getfield (2, 1)
	80 org/apache/commons/math3/stat/regression/MillerUpdatingRegression.nvars:I (2, 1)
	82 invokestatic (2, 1)
	83 java/lang/Integer.valueOf:(I)Ljava/lang/Integer; (2, 1)
	85 aastore (2, 1)
	86 invokespecial (2, 1)
	87 org/apache/commons/math3/stat/regression/ModelSpecificationException.<init>:(Lorg/apache/commons/math3/exception/util/Localizable;[Ljava/lang/Object;)V (2, 1)
	89 athrow (2, 1)
	90 aload_1 (0, 0)
	91 invokestatic (0, 0)
	92 java/util/Arrays.sort:([I)V (0, 0)
	94 iconst_0 (0, 0)
	95 istore_2 (0, 0)
	96 iconst_0 (1, 4)
	97 istore_3 (1, 4)
	98 iload_3 (1, 4)
	99 aload_1 (1, 4)
	100 arraylength (1, 4)
	101 if_icmpge (1, 4)
	102 71 (1, 4)
	104 iload_3 (2, 1)
	105 aload_0 (2, 1)
	106 getfield (2, 1)
	107 org/apache/commons/math3/stat/regression/MillerUpdatingRegression.nvars:I (2, 1)
	109 if_icmplt (2, 1)
	110 35 (2, 1)
	112 new (3, 1)
	113 org/apache/commons/math3/stat/regression/ModelSpecificationException (3, 1)
	115 dup (3, 1)
	116 getstatic (3, 1)
	117 org/apache/commons/math3/exception/util/LocalizedFormats.INDEX_LARGER_THAN_MAX:Lorg/apache/commons/math3/exception/util/LocalizedFormats; (3, 1)
	119 iconst_2 (3, 1)
	120 anewarray (3, 1)
	121 java/lang/Object (3, 1)
	123 dup (3, 1)
	124 iconst_0 (3, 1)
	125 iload_3 (3, 1)
	126 invokestatic (3, 1)
	127 java/lang/Integer.valueOf:(I)Ljava/lang/Integer; (3, 1)
	129 aastore (3, 1)
	130 dup (3, 1)
	131 iconst_1 (3, 1)
	132 aload_0 (3, 1)
	133 getfield (3, 1)
	134 org/apache/commons/math3/stat/regression/MillerUpdatingRegression.nvars:I (3, 1)
	136 invokestatic (3, 1)
	137 java/lang/Integer.valueOf:(I)Ljava/lang/Integer; (3, 1)
	139 aastore (3, 1)
	140 invokespecial (3, 1)
	141 org/apache/commons/math3/stat/regression/ModelSpecificationException.<init>:(Lorg/apache/commons/math3/exception/util/Localizable;[Ljava/lang/Object;)V (3, 1)
	143 athrow (3, 1)
	144 iload_3 (2, 1)
	145 ifle (2, 1)
	146 21 (2, 1)
	148 aload_1 (2, 1)
	149 iload_3 (2, 1)
	150 iaload (2, 1)
	151 aload_1 (2, 1)
	152 iload_3 (2, 1)
	153 iconst_1 (2, 1)
	154 isub (2, 1)
	155 iaload (2, 1)
	156 if_icmpne (2, 1)
	157 10 (2, 1)
	159 aload_1 (2, 1)
	160 iload_3 (2, 1)
	161 iconst_m1 (2, 1)
	162 iastore (2, 1)
	163 iinc (2, 1)
	164 #2 (2, 1)
	165 -124 (2, 1)
	166 iinc (2, 1)
	167 #3 (2, 1)
	168 -89 (2, 1)
	169 goto (2, 1)
	170 -71 (2, 1)
	172 iload_2 (2, 1)
	173 ifle (2, 1)
	174 51 (2, 1)
	176 iconst_0 (2, 1)
	177 istore (2, 1)
	178 #4 (2, 1)
	179 aload_1 (2, 1)
	180 arraylength (2, 1)
	181 iload_2 (2, 1)
	182 isub (2, 1)
	183 newarray (2, 1)
	184 10 (2, 1)
	185 astore_3 (2, 1)
	186 iconst_0 (3, 4)
	187 istore (3, 4)
	188 #5 (3, 4)
	189 iload (3, 4)
	190 #5 (3, 4)
	191 aload_1 (3, 4)
	192 arraylength (3, 4)
	193 if_icmpge (3, 4)
	194 28 (3, 4)
	196 aload_1 (4, 1)
	197 iload (4, 1)
	198 #5 (4, 1)
	199 iaload (4, 1)
	200 iconst_m1 (4, 1)
	201 if_icmple (4, 1)
	202 14 (4, 1)
	204 aload_3 (4, 1)
	205 iload (4, 1)
	206 #4 (4, 1)
	207 aload_1 (4, 1)
	208 iload (4, 1)
	209 #5 (4, 1)
	210 iaload (4, 1)
	211 iastore (4, 1)
	212 iinc (4, 1)
	213 #4 (4, 1)
	214 -124 (4, 1)
	215 iinc (4, 1)
	216 #5 (4, 1)
	217 -89 (4, 1)
	218 goto (4, 1)
	219 -29 (4, 1)
	221 goto (4, 2)
	222 5 (4, 2)
	224 aload_1 (4, 2)
	225 astore_3 (4, 2)
	226 aload_0 (2, 1)
	227 aload_3 (2, 1)
	228 iconst_0 (2, 1)
	229 invokespecial (2, 1)
	230 org/apache/commons/math3/stat/regression/MillerUpdatingRegression.reorderRegressors:([II)I (2, 1)
	232 pop (2, 1)
	233 aload_0 (2, 1)
	234 invokespecial (2, 1)
	235 org/apache/commons/math3/stat/regression/MillerUpdatingRegression.tolset:()V (2, 1)
	237 aload_0 (2, 1)
	238 invokespecial (2, 1)
	239 org/apache/commons/math3/stat/regression/MillerUpdatingRegression.singcheck:()V (2, 1)
	241 aload_0 (2, 1)
	242 aload_3 (2, 1)
	243 arraylength (2, 1)
	244 invokespecial (2, 1)
	245 org/apache/commons/math3/stat/regression/MillerUpdatingRegression.regcf:(I)[D (2, 1)
	247 astore (2, 1)
	248 #4 (2, 1)
	249 aload_0 (2, 1)
	250 invokespecial (2, 1)
	251 org/apache/commons/math3/stat/regression/MillerUpdatingRegression.ss:()V (2, 1)
	253 aload_0 (2, 1)
	254 aload_3 (2, 1)
	255 arraylength (2, 1)
	256 invokespecial (2, 1)
	257 org/apache/commons/math3/stat/regression/MillerUpdatingRegression.cov:(I)[D (2, 1)
	259 astore (2, 1)
	260 #5 (2, 1)
	261 iconst_0 (2, 1)
	262 istore (2, 1)
	263 #6 (2, 1)
	264 iconst_0 (3, 4)
	265 istore (3, 4)
	266 #7 (3, 4)
	267 iload (3, 4)
	268 #7 (3, 4)
	269 aload_0 (3, 4)
	270 getfield (3, 4)
	271 org/apache/commons/math3/stat/regression/MillerUpdatingRegression.lindep:[Z (3, 4)
	273 arraylength (3, 4)
	274 if_icmpge (3, 4)
	275 22 (3, 4)
	277 aload_0 (4, 1)
	278 getfield (4, 1)
	279 org/apache/commons/math3/stat/regression/MillerUpdatingRegression.lindep:[Z (4, 1)
	281 iload (4, 1)
	282 #7 (4, 1)
	283 baload (4, 1)
	284 ifne (4, 1)
	285 6 (4, 1)
	287 iinc (4, 1)
	288 #6 (4, 1)
	289 -124 (4, 1)
	290 iinc (4, 1)
	291 #7 (4, 1)
	292 -89 (4, 1)
	293 goto (4, 1)
	294 -26 (4, 1)
	296 iconst_0 (3, 4)
	297 istore (3, 4)
	298 #7 (3, 4)
	299 iconst_0 (4, 4)
	300 istore (4, 4)
	301 #8 (4, 4)
	302 iload (4, 4)
	303 #8 (4, 4)
	304 aload_0 (4, 4)
	305 getfield (4, 4)
	306 org/apache/commons/math3/stat/regression/MillerUpdatingRegression.nvars:I (4, 4)
	308 if_icmpge (4, 4)
	309 29 (4, 4)
	311 aload_0 (5, 1)
	312 getfield (5, 1)
	313 org/apache/commons/math3/stat/regression/MillerUpdatingRegression.vorder:[I (5, 1)
	315 iload (5, 1)
	316 #8 (5, 1)
	317 iaload (5, 1)
	318 aload_3 (5, 1)
	319 iload (5, 1)
	320 #8 (5, 1)
	321 iaload (5, 1)
	322 if_icmpeq (5, 1)
	323 9 (5, 1)
	325 iconst_1 (5, 1)
	326 istore (5, 1)
	327 #7 (5, 1)
	328 goto (5, 1)
	329 9 (5, 1)
	331 iinc (5, 1)
	332 #8 (5, 1)
	333 -89 (5, 1)
	334 goto (5, 1)
	335 -32 (5, 1)
	337 iload (5, 1)
	338 #7 (5, 1)
	339 ifne (5, 1)
	340 46 (5, 1)
	342 new (5, 1)
	343 org/apache/commons/math3/stat/regression/RegressionResults (5, 1)
	345 dup (5, 1)
	346 aload (5, 1)
	347 #4 (5, 1)
	348 iconst_1 (5, 1)
	349 anewarray (5, 1)
	350 [D (5, 1)
	352 dup (5, 1)
	353 iconst_0 (5, 1)
	354 aload (5, 1)
	355 #5 (5, 1)
	356 aastore (5, 1)
	357 iconst_1 (5, 1)
	358 aload_0 (5, 1)
	359 getfield (5, 1)
	360 org/apache/commons/math3/stat/regression/MillerUpdatingRegression.nobs:J (5, 1)
	362 iload (5, 1)
	363 #6 (5, 1)
	364 aload_0 (5, 1)
	365 getfield (5, 1)
	366 org/apache/commons/math3/stat/regression/MillerUpdatingRegression.sumy:D (5, 1)
	368 aload_0 (5, 1)
	369 getfield (5, 1)
	370 org/apache/commons/math3/stat/regression/MillerUpdatingRegression.sumsqy:D (5, 1)
	372 aload_0 (5, 1)
	373 getfield (5, 1)
	374 org/apache/commons/math3/stat/regression/MillerUpdatingRegression.sserr:D (5, 1)
	376 aload_0 (5, 1)
	377 getfield (5, 1)
	378 org/apache/commons/math3/stat/regression/MillerUpdatingRegression.hasIntercept:Z (5, 1)
	380 iconst_0 (5, 1)
	381 invokespecial (5, 1)
	382 org/apache/commons/math3/stat/regression/RegressionResults.<init>:([D[[DZJIDDDZZ)V (5, 1)
	384 areturn (5, 1)
	385 aload (6, 2)
	386 #4 (6, 2)
	387 arraylength (6, 2)
	388 newarray (6, 2)
	389 7 (6, 2)
	390 astore (6, 2)
	391 #8 (6, 2)
	392 aload (6, 2)
	393 #4 (6, 2)
	394 arraylength (6, 2)
	395 newarray (6, 2)
	396 10 (6, 2)
	397 astore (6, 2)
	398 #9 (6, 2)
	399 iconst_0 (7, 4)
	400 istore (7, 4)
	401 #10 (7, 4)
	402 iload (7, 4)
	403 #10 (7, 4)
	404 aload_3 (7, 4)
	405 arraylength (7, 4)
	406 if_icmpge (7, 4)
	407 59 (7, 4)
	409 iconst_0 (8, 4)
	410 istore (8, 4)
	411 #11 (8, 4)
	412 iload (8, 4)
	413 #11 (8, 4)
	414 aload_0 (8, 4)
	415 getfield (8, 4)
	416 org/apache/commons/math3/stat/regression/MillerUpdatingRegression.vorder:[I (8, 4)
	418 arraylength (8, 4)
	419 if_icmpge (8, 4)
	420 40 (8, 4)
	422 aload_0 (9, 1)
	423 getfield (9, 1)
	424 org/apache/commons/math3/stat/regression/MillerUpdatingRegression.vorder:[I (9, 1)
	426 iload (9, 1)
	427 #11 (9, 1)
	428 iaload (9, 1)
	429 aload_3 (9, 1)
	430 iload (9, 1)
	431 #10 (9, 1)
	432 iaload (9, 1)
	433 if_icmpne (9, 1)
	434 20 (9, 1)
	436 aload (9, 1)
	437 #8 (9, 1)
	438 iload (9, 1)
	439 #10 (9, 1)
	440 aload (9, 1)
	441 #4 (9, 1)
	442 iload (9, 1)
	443 #11 (9, 1)
	444 daload (9, 1)
	445 dastore (9, 1)
	446 aload (9, 1)
	447 #9 (9, 1)
	448 iload (9, 1)
	449 #10 (9, 1)
	450 iload (9, 1)
	451 #11 (9, 1)
	452 iastore (9, 1)
	453 iinc (9, 1)
	454 #11 (9, 1)
	455 -89 (9, 1)
	456 goto (9, 1)
	457 -44 (9, 1)
	459 iinc (9, 1)
	460 #10 (9, 1)
	461 -89 (9, 1)
	462 goto (9, 1)
	463 -60 (9, 1)
	465 aload (8, 4)
	466 #5 (8, 4)
	467 arraylength (8, 4)
	468 newarray (8, 4)
	469 7 (8, 4)
	470 astore (8, 4)
	471 #10 (8, 4)
	472 iconst_0 (8, 4)
	473 istore (8, 4)
	474 #11 (8, 4)
	475 iconst_0 (9, 4)
	476 istore (9, 4)
	477 #15 (9, 4)
	478 iload (9, 4)
	479 #15 (9, 4)
	480 aload (9, 4)
	481 #4 (9, 4)
	482 arraylength (9, 4)
	483 if_icmpge (9, 4)
	484 90 (9, 4)
	486 aload (9, 4)
	487 #9 (9, 4)
	488 iload (9, 4)
	489 #15 (9, 4)
	490 iaload (9, 4)
	491 istore (9, 4)
	492 #13 (9, 4)
	493 iconst_0 (10, 4)
	494 istore (10, 4)
	495 #16 (10, 4)
	496 iload (10, 4)
	497 #16 (10, 4)
	498 iload (10, 4)
	499 #15 (10, 4)
	500 if_icmpgt (10, 4)
	501 67 (10, 4)
	503 aload (10, 4)
	504 #9 (10, 4)
	505 iload (10, 4)
	506 #16 (10, 4)
	507 iaload (10, 4)
	508 istore (10, 4)
	509 #14 (10, 4)
	510 iload (11, 1)
	511 #13 (11, 1)
	512 iload (11, 1)
	513 #14 (11, 1)
	514 if_icmple (11, 1)
	515 20 (11, 1)
	517 iload (11, 1)
	518 #13 (11, 1)
	519 iload (11, 1)
	520 #13 (11, 1)
	521 iconst_1 (11, 1)
	522 iadd (11, 1)
	523 imul (11, 1)
	524 iconst_2 (11, 1)
	525 idiv (11, 1)
	526 iload (11, 1)
	527 #14 (11, 1)
	528 iadd (11, 1)
	529 istore (11, 1)
	530 #12 (11, 1)
	531 goto (11, 1)
	532 17 (11, 1)
	534 iload (12, 2)
	535 #14 (12, 2)
	536 iload (12, 2)
	537 #14 (12, 2)
	538 iconst_1 (12, 2)
	539 iadd (12, 2)
	540 imul (12, 2)
	541 iconst_2 (12, 2)
	542 idiv (12, 2)
	543 iload (12, 2)
	544 #13 (12, 2)
	545 iadd (12, 2)
	546 istore (12, 2)
	547 #12 (12, 2)
	548 aload (10, 4)
	549 #10 (10, 4)
	550 iload (10, 4)
	551 #11 (10, 4)
	552 aload (10, 4)
	553 #5 (10, 4)
	554 iload (10, 4)
	555 #12 (10, 4)
	556 daload (10, 4)
	557 dastore (10, 4)
	558 iinc (10, 4)
	559 #16 (10, 4)
	560 -124 (10, 4)
	561 iinc (10, 4)
	562 #11 (10, 4)
	563 -89 (10, 4)
	564 goto (10, 4)
	565 -68 (10, 4)
	567 iinc (10, 4)
	568 #15 (10, 4)
	569 -89 (10, 4)
	570 goto (10, 4)
	571 -92 (10, 4)
	573 new (9, 4)
	574 org/apache/commons/math3/stat/regression/RegressionResults (9, 4)
	576 dup (9, 4)
	577 aload (9, 4)
	578 #8 (9, 4)
	579 iconst_1 (9, 4)
	580 anewarray (9, 4)
	581 [D (9, 4)
	583 dup (9, 4)
	584 iconst_0 (9, 4)
	585 aload (9, 4)
	586 #10 (9, 4)
	587 aastore (9, 4)
	588 iconst_1 (9, 4)
	589 aload_0 (9, 4)
	590 getfield (9, 4)
	591 org/apache/commons/math3/stat/regression/MillerUpdatingRegression.nobs:J (9, 4)
	593 iload (9, 4)
	594 #6 (9, 4)
	595 aload_0 (9, 4)
	596 getfield (9, 4)
	597 org/apache/commons/math3/stat/regression/MillerUpdatingRegression.sumy:D (9, 4)
	599 aload_0 (9, 4)
	600 getfield (9, 4)
	601 org/apache/commons/math3/stat/regression/MillerUpdatingRegression.sumsqy:D (9, 4)
	603 aload_0 (9, 4)
	604 getfield (9, 4)
	605 org/apache/commons/math3/stat/regression/MillerUpdatingRegression.sserr:D (9, 4)
	607 aload_0 (9, 4)
	608 getfield (9, 4)
	609 org/apache/commons/math3/stat/regression/MillerUpdatingRegression.hasIntercept:Z (9, 4)
	611 iconst_0 (9, 4)
	612 invokespecial (9, 4)
	613 org/apache/commons/math3/stat/regression/RegressionResults.<init>:([D[[DZJIDDDZZ)V (9, 4)
	615 areturn (8, 4)

