Method: <init>
	0 aload_0 (0, 0)
	1 invokespecial (0, 0)
	2 org/apache/commons/math3/stat/regression/AbstractMultipleLinearRegression.<init>:()V (0, 0)
	4 aload_0 (0, 0)
	5 aconst_null (0, 0)
	6 putfield (0, 0)
	7 org/apache/commons/math3/stat/regression/OLSMultipleLinearRegression.qr:Lorg/apache/commons/math3/linear/QRDecomposition; (0, 0)
	9 aload_0 (1, 4)
	10 dload_1 (1, 4)
	11 putfield (1, 4)
	12 org/apache/commons/math3/stat/regression/OLSMultipleLinearRegression.threshold:D (1, 4)
	14 return (1, 4)

Method: newSampleData
	0 aload_0 (0, 0)
	1 aload_1 (0, 0)
	2 iload_2 (0, 0)
	3 iload_3 (0, 0)
	4 invokespecial (0, 0)
	5 org/apache/commons/math3/stat/regression/AbstractMultipleLinearRegression.newSampleData:([DII)V (0, 0)
	7 aload_0 (0, 0)
	8 new (0, 0)
	9 org/apache/commons/math3/linear/QRDecomposition (0, 0)
	11 dup (0, 0)
	12 aload_0 (0, 0)
	13 invokevirtual (0, 0)
	14 org/apache/commons/math3/stat/regression/OLSMultipleLinearRegression.getX:()Lorg/apache/commons/math3/linear/RealMatrix; (0, 0)
	16 aload_0 (0, 0)
	17 getfield (0, 0)
	18 org/apache/commons/math3/stat/regression/OLSMultipleLinearRegression.threshold:D (0, 0)
	20 invokespecial (0, 0)
	21 org/apache/commons/math3/linear/QRDecomposition.<init>:(Lorg/apache/commons/math3/linear/RealMatrix;D)V (0, 0)
	23 putfield (0, 0)
	24 org/apache/commons/math3/stat/regression/OLSMultipleLinearRegression.qr:Lorg/apache/commons/math3/linear/QRDecomposition; (0, 0)
	26 return (0, 0)

Method: calculateHat
	0 aload_0 (0, 0)
	1 getfield (0, 0)
	2 org/apache/commons/math3/stat/regression/OLSMultipleLinearRegression.qr:Lorg/apache/commons/math3/linear/QRDecomposition; (0, 0)
	4 invokevirtual (0, 0)
	5 org/apache/commons/math3/linear/QRDecomposition.getQ:()Lorg/apache/commons/math3/linear/RealMatrix; (0, 0)
	7 astore_1 (0, 0)
	8 aload_0 (0, 0)
	9 getfield (0, 0)
	10 org/apache/commons/math3/stat/regression/OLSMultipleLinearRegression.qr:Lorg/apache/commons/math3/linear/QRDecomposition; (0, 0)
	12 invokevirtual (0, 0)
	13 org/apache/commons/math3/linear/QRDecomposition.getR:()Lorg/apache/commons/math3/linear/RealMatrix; (0, 0)
	15 invokeinterface (0, 0)
	16 org/apache/commons/math3/linear/RealMatrix.org/apache/commons/math3/linear/Array2DRowRealMatrix (0, 0)
	18 0 (0, 0)
	20 istore_2 (0, 0)
	21 aload_1 (0, 0)
	22 invokeinterface (0, 0)
	23 org/apache/commons/math3/linear/RealMatrix.org/apache/commons/math3/linear/Array2DRowRealMatrix (0, 0)
	25 0 (0, 0)
	27 istore_3 (0, 0)
	28 new (0, 1)
	29 org/apache/commons/math3/linear/Array2DRowRealMatrix (0, 1)
	31 dup (0, 1)
	32 iload_3 (0, 1)
	33 iload_3 (0, 1)
	34 invokespecial (0, 1)
	35 org/apache/commons/math3/linear/Array2DRowRealMatrix.<init>:(II)V (0, 1)
	37 astore (0, 1)
	38 #4 (0, 1)
	39 aload (0, 1)
	40 #4 (0, 1)
	41 invokevirtual (0, 1)
	42 org/apache/commons/math3/linear/Array2DRowRealMatrix.getDataRef:()[[D (0, 1)
	44 astore (0, 1)
	45 #5 (0, 1)
	46 iconst_0 (1, 4)
	47 istore (1, 4)
	48 #6 (1, 4)
	49 iload (1, 4)
	50 #6 (1, 4)
	51 iload_3 (1, 4)
	52 if_icmpge (1, 4)
	53 58 (1, 4)
	55 iconst_0 (2, 4)
	56 istore (2, 4)
	57 #7 (2, 4)
	58 iload (2, 4)
	59 #7 (2, 4)
	60 iload_3 (2, 4)
	61 if_icmpge (2, 4)
	62 43 (2, 4)
	64 iload (3, 1)
	65 #6 (3, 1)
	66 iload (3, 1)
	67 #7 (3, 1)
	68 if_icmpne (3, 1)
	69 21 (3, 1)
	71 iload (3, 1)
	72 #6 (3, 1)
	73 iload_2 (3, 1)
	74 if_icmpge (3, 1)
	75 15 (3, 1)
	77 aload (3, 1)
	78 #5 (3, 1)
	79 iload (3, 1)
	80 #6 (3, 1)
	81 aaload (3, 1)
	82 iload (3, 1)
	83 #7 (3, 1)
	84 dconst_1 (3, 1)
	85 dastore (3, 1)
	86 goto (3, 1)
	87 12 (3, 1)
	89 aload (3, 2)
	90 #5 (3, 2)
	91 iload (3, 2)
	92 #6 (3, 2)
	93 aaload (3, 2)
	94 iload (3, 2)
	95 #7 (3, 2)
	96 dconst_0 (3, 2)
	97 dastore (3, 2)
	98 iinc (3, 2)
	99 #7 (3, 2)
	100 -89 (3, 2)
	101 goto (3, 2)
	102 -43 (3, 2)
	104 iinc (3, 2)
	105 #6 (3, 2)
	106 -89 (3, 2)
	107 goto (3, 2)
	108 -58 (3, 2)
	110 aload_1 (2, 1)
	111 aload (2, 1)
	112 #4 (2, 1)
	113 invokeinterface (2, 1)
	114 org/apache/commons/math3/linear/RealMatrix.transpose:()Lorg/apache/commons/math3/linear/RealMatrix; (2, 1)
	116 0 (2, 1)
	118 aload_1 (2, 1)
	119 invokeinterface (2, 1)
	120 org/apache/commons/math3/linear/RealMatrix.isNoIntercept:()Z (2, 1)
	122 0 (2, 1)
	124 invokeinterface (2, 1)
	125 org/apache/commons/math3/linear/RealMatrix.transpose:()Lorg/apache/commons/math3/linear/RealMatrix; (2, 1)
	127 0 (2, 1)
	129 areturn (2, 1)

Method: calculateTotalSumOfSquares
	0 aload_0 (1, 1)
	1 invokevirtual (1, 1)
	2 org/apache/commons/math3/stat/regression/OLSMultipleLinearRegression.isNoIntercept:()Z (1, 1)
	4 ifeq (1, 1)
	5 14 (1, 1)
	7 aload_0 (1, 1)
	8 invokevirtual (1, 1)
	9 org/apache/commons/math3/stat/regression/OLSMultipleLinearRegression.getY:()Lorg/apache/commons/math3/linear/RealVector; (1, 1)
	11 invokevirtual (1, 1)
	12 org/apache/commons/math3/linear/RealVector.toArray:()[D (1, 1)
	14 invokestatic (1, 1)
	15 org/apache/commons/math3/stat/StatUtils.sumSq:([D)D (1, 1)
	17 dreturn (1, 1)
	18 new (1, 2)
	19 org/apache/commons/math3/stat/descriptive/moment/SecondMoment (1, 2)
	21 dup (1, 2)
	22 invokespecial (1, 2)
	23 org/apache/commons/math3/stat/descriptive/moment/SecondMoment.<init>:()V (1, 2)
	25 aload_0 (1, 2)
	26 invokevirtual (1, 2)
	27 org/apache/commons/math3/stat/regression/OLSMultipleLinearRegression.getY:()Lorg/apache/commons/math3/linear/RealVector; (1, 2)
	29 invokevirtual (1, 2)
	30 org/apache/commons/math3/linear/RealVector.toArray:()[D (1, 2)
	32 invokevirtual (1, 2)
	33 org/apache/commons/math3/stat/descriptive/moment/SecondMoment.evaluate:([D)D (1, 2)
	35 dreturn (1, 2)

Method: calculateResidualSumOfSquares
	0 aload_0 (0, 0)
	1 invokevirtual (0, 0)
	2 org/apache/commons/math3/stat/regression/OLSMultipleLinearRegression.calculateResiduals:()Lorg/apache/commons/math3/linear/RealVector; (0, 0)
	4 astore_1 (0, 0)
	5 aload_1 (0, 0)
	6 aload_1 (0, 0)
	7 invokevirtual (0, 0)
	8 org/apache/commons/math3/linear/RealVector.dotProduct:(Lorg/apache/commons/math3/linear/RealVector;)D (0, 0)
	10 dreturn (0, 0)

Method: calculateRSquared
	0 dconst_1 (0, 0)
	1 aload_0 (0, 0)
	2 invokevirtual (0, 0)
	3 org/apache/commons/math3/stat/regression/OLSMultipleLinearRegression.calculateResidualSumOfSquares:()D (0, 0)
	5 aload_0 (0, 0)
	6 invokevirtual (0, 0)
	7 org/apache/commons/math3/stat/regression/OLSMultipleLinearRegression.calculateTotalSumOfSquares:()D (0, 0)
	9 ddiv (0, 0)
	10 dsub (0, 0)
	11 dreturn (0, 0)

Method: calculateAdjustedRSquared
	0 aload_0 (0, 0)
	1 invokevirtual (0, 0)
	2 org/apache/commons/math3/stat/regression/OLSMultipleLinearRegression.getX:()Lorg/apache/commons/math3/linear/RealMatrix; (0, 0)
	4 invokeinterface (0, 0)
	5 org/apache/commons/math3/linear/RealMatrix.calculateRSquared:()D (0, 0)
	7 0 (0, 0)
	9 i2d (0, 0)
	10 dstore_1 (0, 0)
	11 aload_0 (1, 1)
	12 invokevirtual (1, 1)
	13 org/apache/commons/math3/stat/regression/OLSMultipleLinearRegression.isNoIntercept:()Z (1, 1)
	15 ifeq (1, 1)
	16 27 (1, 1)
	18 dconst_1 (1, 1)
	19 dconst_1 (1, 1)
	20 aload_0 (1, 1)
	21 invokevirtual (1, 1)
	22 org/apache/commons/math3/stat/regression/OLSMultipleLinearRegression.calculateRSquared:()D (1, 1)
	24 dsub (1, 1)
	25 dload_1 (1, 1)
	26 dload_1 (1, 1)
	27 aload_0 (1, 1)
	28 invokevirtual (1, 1)
	29 org/apache/commons/math3/stat/regression/OLSMultipleLinearRegression.getX:()Lorg/apache/commons/math3/linear/RealMatrix; (1, 1)
	31 invokeinterface (1, 1)
	32 org/apache/commons/math3/linear/RealMatrix.org/apache/commons/math3/linear/Array2DRowRealMatrix (1, 1)
	34 0 (1, 1)
	36 i2d (1, 1)
	37 dsub (1, 1)
	38 ddiv (1, 1)
	39 dmul (1, 1)
	40 dsub (1, 1)
	41 dreturn (1, 1)
	42 dconst_1 (1, 2)
	43 aload_0 (1, 2)
	44 invokevirtual (1, 2)
	45 org/apache/commons/math3/stat/regression/OLSMultipleLinearRegression.calculateResidualSumOfSquares:()D (1, 2)
	47 dload_1 (1, 2)
	48 dconst_1 (1, 2)
	49 dsub (1, 2)
	50 dmul (1, 2)
	51 aload_0 (1, 2)
	52 invokevirtual (1, 2)
	53 org/apache/commons/math3/stat/regression/OLSMultipleLinearRegression.calculateTotalSumOfSquares:()D (1, 2)
	55 dload_1 (1, 2)
	56 aload_0 (1, 2)
	57 invokevirtual (1, 2)
	58 org/apache/commons/math3/stat/regression/OLSMultipleLinearRegression.getX:()Lorg/apache/commons/math3/linear/RealMatrix; (1, 2)
	60 invokeinterface (1, 2)
	61 org/apache/commons/math3/linear/RealMatrix.org/apache/commons/math3/linear/Array2DRowRealMatrix (1, 2)
	63 0 (1, 2)
	65 i2d (1, 2)
	66 dsub (1, 2)
	67 dmul (1, 2)
	68 ddiv (1, 2)
	69 dsub (1, 2)
	70 dreturn (1, 2)

Method: newXSampleData
	0 aload_0 (0, 0)
	1 aload_1 (0, 0)
	2 invokespecial (0, 0)
	3 org/apache/commons/math3/stat/regression/AbstractMultipleLinearRegression.newXSampleData:([[D)V (0, 0)
	5 aload_0 (0, 0)
	6 new (0, 0)
	7 org/apache/commons/math3/linear/QRDecomposition (0, 0)
	9 dup (0, 0)
	10 aload_0 (0, 0)
	11 invokevirtual (0, 0)
	12 org/apache/commons/math3/stat/regression/OLSMultipleLinearRegression.getX:()Lorg/apache/commons/math3/linear/RealMatrix; (0, 0)
	14 aload_0 (0, 0)
	15 getfield (0, 0)
	16 org/apache/commons/math3/stat/regression/OLSMultipleLinearRegression.threshold:D (0, 0)
	18 invokespecial (0, 0)
	19 org/apache/commons/math3/linear/QRDecomposition.<init>:(Lorg/apache/commons/math3/linear/RealMatrix;D)V (0, 0)
	21 putfield (0, 0)
	22 org/apache/commons/math3/stat/regression/OLSMultipleLinearRegression.qr:Lorg/apache/commons/math3/linear/QRDecomposition; (0, 0)
	24 return (0, 0)

Method: calculateBeta
	0 aload_0 (0, 0)
	1 getfield (0, 0)
	2 org/apache/commons/math3/stat/regression/OLSMultipleLinearRegression.qr:Lorg/apache/commons/math3/linear/QRDecomposition; (0, 0)
	4 invokevirtual (0, 0)
	5 org/apache/commons/math3/linear/QRDecomposition.getSolver:()Lorg/apache/commons/math3/linear/DecompositionSolver; (0, 0)
	7 aload_0 (0, 0)
	8 invokevirtual (0, 0)
	9 org/apache/commons/math3/stat/regression/OLSMultipleLinearRegression.getY:()Lorg/apache/commons/math3/linear/RealVector; (0, 0)
	11 invokeinterface (0, 0)
	12 org/apache/commons/math3/linear/DecompositionSolver.getSubMatrix:(IIII)Lorg/apache/commons/math3/linear/RealMatrix; (0, 0)
	14 0 (0, 0)
	16 areturn (0, 0)

Method: calculateBetaVariance
	0 aload_0 (0, 0)
	1 invokevirtual (0, 0)
	2 org/apache/commons/math3/stat/regression/OLSMultipleLinearRegression.getX:()Lorg/apache/commons/math3/linear/RealMatrix; (0, 0)
	4 invokeinterface (0, 0)
	5 org/apache/commons/math3/linear/RealMatrix.org/apache/commons/math3/linear/Array2DRowRealMatrix (0, 0)
	7 0 (0, 0)
	9 istore_1 (0, 0)
	10 aload_0 (0, 0)
	11 getfield (0, 0)
	12 org/apache/commons/math3/stat/regression/OLSMultipleLinearRegression.qr:Lorg/apache/commons/math3/linear/QRDecomposition; (0, 0)
	14 invokevirtual (0, 0)
	15 org/apache/commons/math3/linear/QRDecomposition.getR:()Lorg/apache/commons/math3/linear/RealMatrix; (0, 0)
	17 iconst_0 (0, 0)
	18 iload_1 (0, 0)
	19 iconst_1 (0, 0)
	20 isub (0, 0)
	21 iconst_0 (0, 0)
	22 iload_1 (0, 0)
	23 iconst_1 (0, 0)
	24 isub (0, 0)
	25 invokeinterface (0, 0)
	26 org/apache/commons/math3/linear/RealMatrix.org/apache/commons/math3/linear/LUDecomposition (0, 0)
	28 0 (0, 0)
	30 astore_2 (0, 0)
	31 new (0, 0)
	32 org/apache/commons/math3/linear/LUDecomposition (0, 0)
	34 dup (0, 0)
	35 aload_2 (0, 0)
	36 invokespecial (0, 0)
	37 org/apache/commons/math3/linear/LUDecomposition.<init>:(Lorg/apache/commons/math3/linear/RealMatrix;)V (0, 0)
	39 invokevirtual (0, 0)
	40 org/apache/commons/math3/linear/LUDecomposition.getSolver:()Lorg/apache/commons/math3/linear/DecompositionSolver; (0, 0)
	42 invokeinterface (0, 0)
	43 org/apache/commons/math3/linear/DecompositionSolver.org/apache/commons/math3/stat/regression/OLSMultipleLinearRegression (0, 0)
	45 0 (0, 0)
	47 astore_3 (0, 0)
	48 aload_3 (0, 0)
	49 aload_3 (0, 0)
	50 invokeinterface (0, 0)
	51 org/apache/commons/math3/linear/RealMatrix.isNoIntercept:()Z (0, 0)
	53 0 (0, 0)
	55 invokeinterface (0, 0)
	56 org/apache/commons/math3/linear/RealMatrix.transpose:()Lorg/apache/commons/math3/linear/RealMatrix; (0, 0)
	58 0 (0, 0)
	60 areturn (0, 0)

