Method: <init>
	0 aload_0 (0, 0)
	1 invokespecial (0, 0)
	2 java/lang/Object.<init>:()V (0, 0)
	4 iload (2, 1)
	5 #14 (2, 1)
	6 ifeq (2, 1)
	7 53 (2, 1)
	9 aload_0 (2, 1)
	10 aload_1 (2, 1)
	11 invokestatic (2, 1)
	12 org/apache/commons/math3/util/MathArrays.copyOf:([D)[D (2, 1)
	14 putfield (2, 1)
	15 org/apache/commons/math3/stat/regression/RegressionResults.parameters:[D (2, 1)
	17 aload_0 (2, 1)
	18 aload_2 (2, 1)
	19 arraylength (2, 1)
	20 anewarray (2, 1)
	21 [D (2, 1)
	23 putfield (2, 1)
	24 org/apache/commons/math3/stat/regression/RegressionResults.varCovData:[[D (2, 1)
	26 iconst_0 (3, 4)
	27 istore (3, 4)
	28 #15 (3, 4)
	29 iload (3, 4)
	30 #15 (3, 4)
	31 aload_2 (3, 4)
	32 arraylength (3, 4)
	33 if_icmpge (3, 4)
	34 23 (3, 4)
	36 aload_0 (3, 4)
	37 getfield (3, 4)
	38 org/apache/commons/math3/stat/regression/RegressionResults.varCovData:[[D (3, 4)
	40 iload (3, 4)
	41 #15 (3, 4)
	42 aload_2 (3, 4)
	43 iload (3, 4)
	44 #15 (3, 4)
	45 aaload (3, 4)
	46 invokestatic (3, 4)
	47 org/apache/commons/math3/util/MathArrays.copyOf:([D)[D (3, 4)
	49 aastore (3, 4)
	50 iinc (3, 4)
	51 #15 (3, 4)
	52 -89 (3, 4)
	53 goto (3, 4)
	54 -24 (3, 4)
	56 goto (3, 4)
	57 13 (3, 4)
	59 aload_0 (2, 2)
	60 aload_1 (2, 2)
	61 putfield (2, 2)
	62 org/apache/commons/math3/stat/regression/RegressionResults.parameters:[D (2, 2)
	64 aload_0 (2, 2)
	65 aload_2 (2, 2)
	66 putfield (2, 2)
	67 org/apache/commons/math3/stat/regression/RegressionResults.varCovData:[[D (2, 2)
	69 aload_0 (0, 0)
	70 iload_3 (0, 0)
	71 putfield (0, 0)
	72 org/apache/commons/math3/stat/regression/RegressionResults.isSymmetricVCD:Z (0, 0)
	74 aload_0 (0, 0)
	75 lload (0, 0)
	76 #4 (0, 0)
	77 putfield (0, 0)
	78 org/apache/commons/math3/stat/regression/RegressionResults.nobs:J (0, 0)
	80 aload_0 (0, 0)
	81 iload (0, 0)
	82 #6 (0, 0)
	83 putfield (0, 0)
	84 org/apache/commons/math3/stat/regression/RegressionResults.rank:I (0, 0)
	86 aload_0 (0, 0)
	87 iload (0, 0)
	88 #13 (0, 0)
	89 putfield (0, 0)
	90 org/apache/commons/math3/stat/regression/RegressionResults.containsConstant:Z (0, 0)
	92 aload_0 (0, 0)
	93 iconst_5 (0, 0)
	94 newarray (0, 0)
	95 7 (0, 0)
	96 putfield (0, 0)
	97 org/apache/commons/math3/stat/regression/RegressionResults.globalFitInfo:[D (0, 0)
	99 aload_0 (0, 0)
	100 getfield (0, 0)
	101 org/apache/commons/math3/stat/regression/RegressionResults.globalFitInfo:[D (0, 0)
	103 ldc2_w (0, 0)
	104 nan (0, 0)
	106 invokestatic (0, 0)
	107 java/util/Arrays.fill:([DD)V (0, 0)
	109 iload (2, 1)
	110 #6 (2, 1)
	111 ifle (2, 1)
	112 31 (2, 1)
	114 aload_0 (2, 1)
	115 getfield (2, 1)
	116 org/apache/commons/math3/stat/regression/RegressionResults.globalFitInfo:[D (2, 1)
	118 iconst_1 (2, 1)
	119 iload (2, 1)
	120 #13 (2, 1)
	121 ifeq (2, 1)
	122 18 (2, 1)
	124 dload (2, 1)
	125 #9 (2, 1)
	126 dload (2, 1)
	127 #7 (2, 1)
	128 dload (2, 1)
	129 #7 (2, 1)
	130 dmul (2, 1)
	131 lload (2, 1)
	132 #4 (2, 1)
	133 l2d (2, 1)
	134 ddiv (2, 1)
	135 dsub (2, 1)
	136 goto (2, 1)
	137 5 (2, 1)
	139 dload (2, 1)
	140 #9 (2, 1)
	141 dastore (2, 1)
	142 aload_0 (0, 0)
	143 getfield (0, 0)
	144 org/apache/commons/math3/stat/regression/RegressionResults.globalFitInfo:[D (0, 0)
	146 iconst_0 (0, 0)
	147 dload (0, 0)
	148 #11 (0, 0)
	149 dastore (0, 0)
	150 aload_0 (0, 0)
	151 getfield (0, 0)
	152 org/apache/commons/math3/stat/regression/RegressionResults.globalFitInfo:[D (0, 0)
	154 iconst_3 (0, 0)
	155 aload_0 (0, 0)
	156 getfield (0, 0)
	157 org/apache/commons/math3/stat/regression/RegressionResults.globalFitInfo:[D (0, 0)
	159 iconst_0 (0, 0)
	160 daload (0, 0)
	161 lload (0, 0)
	162 #4 (0, 0)
	163 iload (0, 0)
	164 #6 (0, 0)
	165 i2l (0, 0)
	166 lsub (0, 0)
	167 l2d (0, 0)
	168 ddiv (0, 0)
	169 dastore (0, 0)
	170 aload_0 (0, 0)
	171 getfield (0, 0)
	172 org/apache/commons/math3/stat/regression/RegressionResults.globalFitInfo:[D (0, 0)
	174 iconst_2 (0, 0)
	175 dconst_1 (0, 0)
	176 aload_0 (0, 0)
	177 getfield (0, 0)
	178 org/apache/commons/math3/stat/regression/RegressionResults.globalFitInfo:[D (0, 0)
	180 iconst_0 (0, 0)
	181 daload (0, 0)
	182 aload_0 (0, 0)
	183 getfield (0, 0)
	184 org/apache/commons/math3/stat/regression/RegressionResults.globalFitInfo:[D (0, 0)
	186 iconst_1 (0, 0)
	187 daload (0, 0)
	188 ddiv (0, 0)
	189 dsub (0, 0)
	190 dastore (0, 0)
	191 iload (2, 1)
	192 #13 (2, 1)
	193 ifne (2, 1)
	194 34 (2, 1)
	196 aload_0 (2, 1)
	197 getfield (2, 1)
	198 org/apache/commons/math3/stat/regression/RegressionResults.globalFitInfo:[D (2, 1)
	200 iconst_4 (2, 1)
	201 dconst_1 (2, 1)
	202 dconst_1 (2, 1)
	203 aload_0 (2, 1)
	204 getfield (2, 1)
	205 org/apache/commons/math3/stat/regression/RegressionResults.globalFitInfo:[D (2, 1)
	207 iconst_2 (2, 1)
	208 daload (2, 1)
	209 dsub (2, 1)
	210 lload (2, 1)
	211 #4 (2, 1)
	212 l2d (2, 1)
	213 lload (2, 1)
	214 #4 (2, 1)
	215 iload (2, 1)
	216 #6 (2, 1)
	217 i2l (2, 1)
	218 lsub (2, 1)
	219 l2d (2, 1)
	220 ddiv (2, 1)
	221 dmul (2, 1)
	222 dsub (2, 1)
	223 dastore (2, 1)
	224 goto (2, 1)
	225 34 (2, 1)
	227 aload_0 (2, 2)
	228 getfield (2, 2)
	229 org/apache/commons/math3/stat/regression/RegressionResults.globalFitInfo:[D (2, 2)
	231 iconst_4 (2, 2)
	232 dconst_1 (2, 2)
	233 dload (2, 2)
	234 #11 (2, 2)
	235 lload (2, 2)
	236 #4 (2, 2)
	237 l2d (2, 2)
	238 dconst_1 (2, 2)
	239 dsub (2, 2)
	240 dmul (2, 2)
	241 aload_0 (2, 2)
	242 getfield (2, 2)
	243 org/apache/commons/math3/stat/regression/RegressionResults.globalFitInfo:[D (2, 2)
	245 iconst_1 (2, 2)
	246 daload (2, 2)
	247 lload (2, 2)
	248 #4 (2, 2)
	249 iload (2, 2)
	250 #6 (2, 2)
	251 i2l (2, 2)
	252 lsub (2, 2)
	253 l2d (2, 2)
	254 dmul (2, 2)
	255 ddiv (2, 2)
	256 dsub (2, 2)
	257 dastore (2, 2)
	258 return (0, 0)

Method: getParameterEstimate
	0 aload_0 (1, 1)
	1 getfield (1, 1)
	2 org/apache/commons/math3/stat/regression/RegressionResults.parameters:[D (1, 1)
	4 ifnonnull (1, 1)
	5 7 (1, 1)
	7 ldc2_w (1, 1)
	8 nan (1, 1)
	10 dreturn (1, 1)
	11 iload_1 (1, 1)
	12 iflt (1, 1)
	13 12 (1, 1)
	15 iload_1 (1, 1)
	16 aload_0 (1, 1)
	17 getfield (1, 1)
	18 org/apache/commons/math3/stat/regression/RegressionResults.parameters:[D (1, 1)
	20 arraylength (1, 1)
	21 if_icmplt (1, 1)
	22 29 (1, 1)
	24 new (1, 1)
	25 org/apache/commons/math3/exception/OutOfRangeException (1, 1)
	27 dup (1, 1)
	28 iload_1 (1, 1)
	29 invokestatic (1, 1)
	30 java/lang/Integer.valueOf:(I)Ljava/lang/Integer; (1, 1)
	32 iconst_0 (1, 1)
	33 invokestatic (1, 1)
	34 java/lang/Integer.valueOf:(I)Ljava/lang/Integer; (1, 1)
	36 aload_0 (1, 1)
	37 getfield (1, 1)
	38 org/apache/commons/math3/stat/regression/RegressionResults.parameters:[D (1, 1)
	40 arraylength (1, 1)
	41 iconst_1 (1, 1)
	42 isub (1, 1)
	43 invokestatic (1, 1)
	44 java/lang/Integer.valueOf:(I)Ljava/lang/Integer; (1, 1)
	46 invokespecial (1, 1)
	47 org/apache/commons/math3/exception/OutOfRangeException.<init>:(Ljava/lang/Number;Ljava/lang/Number;Ljava/lang/Number;)V (1, 1)
	49 athrow (1, 1)
	50 aload_0 (0, 0)
	51 getfield (0, 0)
	52 org/apache/commons/math3/stat/regression/RegressionResults.parameters:[D (0, 0)
	54 iload_1 (0, 0)
	55 daload (0, 0)
	56 dreturn (0, 0)

Method: getParameterEstimates
	0 aload_0 (1, 1)
	1 getfield (1, 1)
	2 org/apache/commons/math3/stat/regression/RegressionResults.parameters:[D (1, 1)
	4 ifnonnull (1, 1)
	5 5 (1, 1)
	7 aconst_null (1, 1)
	8 areturn (1, 1)
	9 aload_0 (0, 0)
	10 getfield (0, 0)
	11 org/apache/commons/math3/stat/regression/RegressionResults.parameters:[D (0, 0)
	13 invokestatic (0, 0)
	14 org/apache/commons/math3/util/MathArrays.copyOf:([D)[D (0, 0)
	16 areturn (0, 0)

Method: getStdErrorOfEstimate
	0 aload_0 (1, 1)
	1 getfield (1, 1)
	2 org/apache/commons/math3/stat/regression/RegressionResults.parameters:[D (1, 1)
	4 ifnonnull (1, 1)
	5 7 (1, 1)
	7 ldc2_w (1, 1)
	8 nan (1, 1)
	10 dreturn (1, 1)
	11 iload_1 (1, 1)
	12 iflt (1, 1)
	13 12 (1, 1)
	15 iload_1 (1, 1)
	16 aload_0 (1, 1)
	17 getfield (1, 1)
	18 org/apache/commons/math3/stat/regression/RegressionResults.parameters:[D (1, 1)
	20 arraylength (1, 1)
	21 if_icmplt (1, 1)
	22 29 (1, 1)
	24 new (1, 1)
	25 org/apache/commons/math3/exception/OutOfRangeException (1, 1)
	27 dup (1, 1)
	28 iload_1 (1, 1)
	29 invokestatic (1, 1)
	30 java/lang/Integer.valueOf:(I)Ljava/lang/Integer; (1, 1)
	32 iconst_0 (1, 1)
	33 invokestatic (1, 1)
	34 java/lang/Integer.valueOf:(I)Ljava/lang/Integer; (1, 1)
	36 aload_0 (1, 1)
	37 getfield (1, 1)
	38 org/apache/commons/math3/stat/regression/RegressionResults.parameters:[D (1, 1)
	40 arraylength (1, 1)
	41 iconst_1 (1, 1)
	42 isub (1, 1)
	43 invokestatic (1, 1)
	44 java/lang/Integer.valueOf:(I)Ljava/lang/Integer; (1, 1)
	46 invokespecial (1, 1)
	47 org/apache/commons/math3/exception/OutOfRangeException.<init>:(Ljava/lang/Number;Ljava/lang/Number;Ljava/lang/Number;)V (1, 1)
	49 athrow (1, 1)
	50 aload_0 (0, 0)
	51 iload_1 (0, 0)
	52 iload_1 (0, 0)
	53 invokespecial (0, 0)
	54 org/apache/commons/math3/stat/regression/RegressionResults.getVcvElement:(II)D (0, 0)
	56 dstore_2 (0, 0)
	57 dload_2 (1, 1)
	58 invokestatic (1, 1)
	59 java/lang/Double.isNaN:(D)Z (1, 1)
	61 ifne (1, 1)
	62 16 (1, 1)
	64 dload_2 (1, 1)
	65 ldc2_w (1, 1)
	66 5e-324 (1, 1)
	68 dcmpl (1, 1)
	69 ifle (1, 1)
	70 8 (1, 1)
	72 dload_2 (1, 1)
	73 invokestatic (1, 1)
	74 org/apache/commons/math3/util/FastMath.sqrt:(D)D (1, 1)
	76 dreturn (1, 1)
	77 ldc2_w (0, 0)
	78 nan (0, 0)
	80 dreturn (0, 0)

Method: getStdErrorOfEstimates
	0 aload_0 (1, 1)
	1 getfield (1, 1)
	2 org/apache/commons/math3/stat/regression/RegressionResults.parameters:[D (1, 1)
	4 ifnonnull (1, 1)
	5 5 (1, 1)
	7 aconst_null (1, 1)
	8 areturn (1, 1)
	9 aload_0 (0, 0)
	10 getfield (0, 0)
	11 org/apache/commons/math3/stat/regression/RegressionResults.parameters:[D (0, 0)
	13 arraylength (0, 0)
	14 newarray (0, 0)
	15 7 (0, 0)
	16 astore_1 (0, 0)
	17 iconst_0 (1, 4)
	18 istore_2 (1, 4)
	19 iload_2 (1, 4)
	20 aload_0 (1, 4)
	21 getfield (1, 4)
	22 org/apache/commons/math3/stat/regression/RegressionResults.parameters:[D (1, 4)
	24 arraylength (1, 4)
	25 if_icmpge (1, 4)
	26 47 (1, 4)
	28 aload_0 (1, 4)
	29 iload_2 (1, 4)
	30 iload_2 (1, 4)
	31 invokespecial (1, 4)
	32 org/apache/commons/math3/stat/regression/RegressionResults.getVcvElement:(II)D (1, 4)
	34 dstore_3 (1, 4)
	35 dload_3 (2, 1)
	36 invokestatic (2, 1)
	37 java/lang/Double.isNaN:(D)Z (2, 1)
	39 ifne (2, 1)
	40 21 (2, 1)
	42 dload_3 (2, 1)
	43 ldc2_w (2, 1)
	44 5e-324 (2, 1)
	46 dcmpl (2, 1)
	47 ifle (2, 1)
	48 13 (2, 1)
	50 aload_1 (2, 1)
	51 iload_2 (2, 1)
	52 dload_3 (2, 1)
	53 invokestatic (2, 1)
	54 org/apache/commons/math3/util/FastMath.sqrt:(D)D (2, 1)
	56 dastore (2, 1)
	57 goto (2, 1)
	58 9 (2, 1)
	60 aload_1 (1, 4)
	61 iload_2 (1, 4)
	62 ldc2_w (1, 4)
	63 nan (1, 4)
	65 dastore (1, 4)
	66 iinc (1, 4)
	67 #2 (1, 4)
	68 -89 (1, 4)
	69 goto (1, 4)
	70 -50 (1, 4)
	72 aload_1 (0, 0)
	73 areturn (0, 0)

Method: getCovarianceOfParameters
	0 aload_0 (1, 1)
	1 getfield (1, 1)
	2 org/apache/commons/math3/stat/regression/RegressionResults.parameters:[D (1, 1)
	4 ifnonnull (1, 1)
	5 7 (1, 1)
	7 ldc2_w (1, 1)
	8 nan (1, 1)
	10 dreturn (1, 1)
	11 iload_1 (1, 1)
	12 iflt (1, 1)
	13 12 (1, 1)
	15 iload_1 (1, 1)
	16 aload_0 (1, 1)
	17 getfield (1, 1)
	18 org/apache/commons/math3/stat/regression/RegressionResults.parameters:[D (1, 1)
	20 arraylength (1, 1)
	21 if_icmplt (1, 1)
	22 29 (1, 1)
	24 new (1, 1)
	25 org/apache/commons/math3/exception/OutOfRangeException (1, 1)
	27 dup (1, 1)
	28 iload_1 (1, 1)
	29 invokestatic (1, 1)
	30 java/lang/Integer.valueOf:(I)Ljava/lang/Integer; (1, 1)
	32 iconst_0 (1, 1)
	33 invokestatic (1, 1)
	34 java/lang/Integer.valueOf:(I)Ljava/lang/Integer; (1, 1)
	36 aload_0 (1, 1)
	37 getfield (1, 1)
	38 org/apache/commons/math3/stat/regression/RegressionResults.parameters:[D (1, 1)
	40 arraylength (1, 1)
	41 iconst_1 (1, 1)
	42 isub (1, 1)
	43 invokestatic (1, 1)
	44 java/lang/Integer.valueOf:(I)Ljava/lang/Integer; (1, 1)
	46 invokespecial (1, 1)
	47 org/apache/commons/math3/exception/OutOfRangeException.<init>:(Ljava/lang/Number;Ljava/lang/Number;Ljava/lang/Number;)V (1, 1)
	49 athrow (1, 1)
	50 iload_2 (1, 1)
	51 iflt (1, 1)
	52 12 (1, 1)
	54 iload_2 (1, 1)
	55 aload_0 (1, 1)
	56 getfield (1, 1)
	57 org/apache/commons/math3/stat/regression/RegressionResults.parameters:[D (1, 1)
	59 arraylength (1, 1)
	60 if_icmplt (1, 1)
	61 29 (1, 1)
	63 new (1, 1)
	64 org/apache/commons/math3/exception/OutOfRangeException (1, 1)
	66 dup (1, 1)
	67 iload_2 (1, 1)
	68 invokestatic (1, 1)
	69 java/lang/Integer.valueOf:(I)Ljava/lang/Integer; (1, 1)
	71 iconst_0 (1, 1)
	72 invokestatic (1, 1)
	73 java/lang/Integer.valueOf:(I)Ljava/lang/Integer; (1, 1)
	75 aload_0 (1, 1)
	76 getfield (1, 1)
	77 org/apache/commons/math3/stat/regression/RegressionResults.parameters:[D (1, 1)
	79 arraylength (1, 1)
	80 iconst_1 (1, 1)
	81 isub (1, 1)
	82 invokestatic (1, 1)
	83 java/lang/Integer.valueOf:(I)Ljava/lang/Integer; (1, 1)
	85 invokespecial (1, 1)
	86 org/apache/commons/math3/exception/OutOfRangeException.<init>:(Ljava/lang/Number;Ljava/lang/Number;Ljava/lang/Number;)V (1, 1)
	88 athrow (1, 1)
	89 aload_0 (0, 0)
	90 iload_1 (0, 0)
	91 iload_2 (0, 0)
	92 invokespecial (0, 0)
	93 org/apache/commons/math3/stat/regression/RegressionResults.getVcvElement:(II)D (0, 0)
	95 dreturn (0, 0)

Method: getNumberOfParameters
	0 aload_0 (1, 1)
	1 getfield (1, 1)
	2 org/apache/commons/math3/stat/regression/RegressionResults.parameters:[D (1, 1)
	4 ifnonnull (1, 1)
	5 5 (1, 1)
	7 iconst_m1 (1, 1)
	8 ireturn (1, 1)
	9 aload_0 (0, 0)
	10 getfield (0, 0)
	11 org/apache/commons/math3/stat/regression/RegressionResults.parameters:[D (0, 0)
	13 arraylength (0, 0)
	14 ireturn (0, 0)

Method: getN
	0 aload_0 (0, 0)
	1 getfield (0, 0)
	2 org/apache/commons/math3/stat/regression/RegressionResults.nobs:J (0, 0)
	4 lreturn (0, 0)

Method: getTotalSumSquares
	0 aload_0 (0, 0)
	1 getfield (0, 0)
	2 org/apache/commons/math3/stat/regression/RegressionResults.globalFitInfo:[D (0, 0)
	4 iconst_1 (0, 0)
	5 daload (0, 0)
	6 dreturn (0, 0)

Method: getRegressionSumSquares
	0 aload_0 (0, 0)
	1 getfield (0, 0)
	2 org/apache/commons/math3/stat/regression/RegressionResults.globalFitInfo:[D (0, 0)
	4 iconst_1 (0, 0)
	5 daload (0, 0)
	6 aload_0 (0, 0)
	7 getfield (0, 0)
	8 org/apache/commons/math3/stat/regression/RegressionResults.globalFitInfo:[D (0, 0)
	10 iconst_0 (0, 0)
	11 daload (0, 0)
	12 dsub (0, 0)
	13 dreturn (0, 0)

Method: getErrorSumSquares
	0 aload_0 (0, 0)
	1 getfield (0, 0)
	2 org/apache/commons/math3/stat/regression/RegressionResults.globalFitInfo:[D (0, 0)
	4 iconst_0 (0, 0)
	5 daload (0, 0)
	6 dreturn (0, 0)

Method: getMeanSquareError
	0 aload_0 (0, 0)
	1 getfield (0, 0)
	2 org/apache/commons/math3/stat/regression/RegressionResults.globalFitInfo:[D (0, 0)
	4 iconst_3 (0, 0)
	5 daload (0, 0)
	6 dreturn (0, 0)

Method: getRSquared
	0 aload_0 (0, 0)
	1 getfield (0, 0)
	2 org/apache/commons/math3/stat/regression/RegressionResults.globalFitInfo:[D (0, 0)
	4 iconst_2 (0, 0)
	5 daload (0, 0)
	6 dreturn (0, 0)

Method: getAdjustedRSquared
	0 aload_0 (0, 0)
	1 getfield (0, 0)
	2 org/apache/commons/math3/stat/regression/RegressionResults.globalFitInfo:[D (0, 0)
	4 iconst_4 (0, 0)
	5 daload (0, 0)
	6 dreturn (0, 0)

Method: hasIntercept
	0 aload_0 (0, 0)
	1 getfield (0, 0)
	2 org/apache/commons/math3/stat/regression/RegressionResults.containsConstant:Z (0, 0)
	4 ireturn (0, 0)

Method: getVcvElement
	0 aload_0 (1, 1)
	1 getfield (1, 1)
	2 org/apache/commons/math3/stat/regression/RegressionResults.isSymmetricVCD:Z (1, 1)
	4 ifeq (1, 1)
	5 94 (1, 1)
	7 aload_0 (2, 1)
	8 getfield (2, 1)
	9 org/apache/commons/math3/stat/regression/RegressionResults.varCovData:[[D (2, 1)
	11 arraylength (2, 1)
	12 iconst_1 (2, 1)
	13 if_icmple (2, 1)
	14 46 (2, 1)
	16 iload_1 (3, 1)
	17 iload_2 (3, 1)
	18 if_icmpne (3, 1)
	19 12 (3, 1)
	21 aload_0 (3, 1)
	22 getfield (3, 1)
	23 org/apache/commons/math3/stat/regression/RegressionResults.varCovData:[[D (3, 1)
	25 iload_1 (3, 1)
	26 aaload (3, 1)
	27 iload_1 (3, 1)
	28 daload (3, 1)
	29 dreturn (3, 1)
	30 iload_1 (3, 1)
	31 aload_0 (3, 1)
	32 getfield (3, 1)
	33 org/apache/commons/math3/stat/regression/RegressionResults.varCovData:[[D (3, 1)
	35 iload_2 (3, 1)
	36 aaload (3, 1)
	37 arraylength (3, 1)
	38 if_icmplt (3, 1)
	39 12 (3, 1)
	41 aload_0 (3, 1)
	42 getfield (3, 1)
	43 org/apache/commons/math3/stat/regression/RegressionResults.varCovData:[[D (3, 1)
	45 iload_1 (3, 1)
	46 aaload (3, 1)
	47 iload_2 (3, 1)
	48 daload (3, 1)
	49 dreturn (3, 1)
	50 aload_0 (3, 2)
	51 getfield (3, 2)
	52 org/apache/commons/math3/stat/regression/RegressionResults.varCovData:[[D (3, 2)
	54 iload_2 (3, 2)
	55 aaload (3, 2)
	56 iload_1 (3, 2)
	57 daload (3, 2)
	58 dreturn (3, 2)
	59 iload_1 (3, 1)
	60 iload_2 (3, 1)
	61 if_icmple (3, 1)
	62 20 (3, 1)
	64 aload_0 (3, 1)
	65 getfield (3, 1)
	66 org/apache/commons/math3/stat/regression/RegressionResults.varCovData:[[D (3, 1)
	68 iconst_0 (3, 1)
	69 aaload (3, 1)
	70 iload_1 (3, 1)
	71 iconst_1 (3, 1)
	72 iadd (3, 1)
	73 iload_1 (3, 1)
	74 imul (3, 1)
	75 iconst_2 (3, 1)
	76 idiv (3, 1)
	77 iload_2 (3, 1)
	78 iadd (3, 1)
	79 daload (3, 1)
	80 dreturn (3, 1)
	81 aload_0 (3, 2)
	82 getfield (3, 2)
	83 org/apache/commons/math3/stat/regression/RegressionResults.varCovData:[[D (3, 2)
	85 iconst_0 (3, 2)
	86 aaload (3, 2)
	87 iload_2 (3, 2)
	88 iconst_1 (3, 2)
	89 iadd (3, 2)
	90 iload_2 (3, 2)
	91 imul (3, 2)
	92 iconst_2 (3, 2)
	93 idiv (3, 2)
	94 iload_1 (3, 2)
	95 iadd (3, 2)
	96 daload (3, 2)
	97 dreturn (3, 2)
	98 aload_0 (1, 2)
	99 getfield (1, 2)
	100 org/apache/commons/math3/stat/regression/RegressionResults.varCovData:[[D (1, 2)
	102 iload_1 (1, 2)
	103 aaload (1, 2)
	104 iload_2 (1, 2)
	105 daload (1, 2)
	106 dreturn (1, 2)

