Method: <init>
	0 aload_0 (0, 0)
	1 invokespecial (0, 0)
	2 java/lang/Object.<init>:()V (0, 0)
	4 aload_0 (0, 0)
	5 dconst_0 (0, 0)
	6 putfield (0, 0)
	7 org/apache/commons/math3/stat/regression/SimpleRegression.sumX:D (0, 0)
	9 aload_0 (0, 0)
	10 dconst_0 (0, 0)
	11 putfield (0, 0)
	12 org/apache/commons/math3/stat/regression/SimpleRegression.sumXX:D (0, 0)
	14 aload_0 (0, 0)
	15 dconst_0 (0, 0)
	16 putfield (0, 0)
	17 org/apache/commons/math3/stat/regression/SimpleRegression.sumY:D (0, 0)
	19 aload_0 (0, 0)
	20 dconst_0 (0, 0)
	21 putfield (0, 0)
	22 org/apache/commons/math3/stat/regression/SimpleRegression.sumYY:D (0, 0)
	24 aload_0 (0, 0)
	25 dconst_0 (0, 0)
	26 putfield (0, 0)
	27 org/apache/commons/math3/stat/regression/SimpleRegression.sumXY:D (0, 0)
	29 aload_0 (0, 0)
	30 lconst_0 (0, 0)
	31 putfield (0, 0)
	32 org/apache/commons/math3/stat/regression/SimpleRegression.n:J (0, 0)
	34 aload_0 (0, 4)
	35 dconst_0 (0, 4)
	36 putfield (0, 4)
	37 org/apache/commons/math3/stat/regression/SimpleRegression.xbar:D (0, 4)
	39 aload_0 (0, 4)
	40 dconst_0 (0, 4)
	41 putfield (0, 4)
	42 org/apache/commons/math3/stat/regression/SimpleRegression.ybar:D (0, 4)
	44 aload_0 (0, 1)
	45 iload_1 (0, 1)
	46 putfield (0, 1)
	47 org/apache/commons/math3/stat/regression/SimpleRegression.hasIntercept:Z (0, 1)
	49 return (0, 1)

Method: addData
	0 iconst_0 (1, 4)
	1 istore_2 (1, 4)
	2 iload_2 (1, 4)
	3 aload_1 (1, 4)
	4 arraylength (1, 4)
	5 if_icmpge (1, 4)
	6 63 (1, 4)
	8 aload_1 (2, 1)
	9 iload_2 (2, 1)
	10 aaload (2, 1)
	11 arraylength (2, 1)
	12 iconst_2 (2, 1)
	13 if_icmpge (2, 1)
	14 35 (2, 1)
	16 new (2, 1)
	17 org/apache/commons/math3/stat/regression/ModelSpecificationException (2, 1)
	19 dup (2, 1)
	20 getstatic (2, 1)
	21 org/apache/commons/math3/exception/util/LocalizedFormats.INVALID_REGRESSION_OBSERVATION:Lorg/apache/commons/math3/exception/util/LocalizedFormats; (2, 1)
	23 iconst_2 (2, 1)
	24 anewarray (2, 1)
	25 java/lang/Object (2, 1)
	27 dup (2, 1)
	28 iconst_0 (2, 1)
	29 aload_1 (2, 1)
	30 iload_2 (2, 1)
	31 aaload (2, 1)
	32 arraylength (2, 1)
	33 invokestatic (2, 1)
	34 java/lang/Integer.valueOf:(I)Ljava/lang/Integer; (2, 1)
	36 aastore (2, 1)
	37 dup (2, 1)
	38 iconst_1 (2, 1)
	39 iconst_2 (2, 1)
	40 invokestatic (2, 1)
	41 java/lang/Integer.valueOf:(I)Ljava/lang/Integer; (2, 1)
	43 aastore (2, 1)
	44 invokespecial (2, 1)
	45 org/apache/commons/math3/stat/regression/ModelSpecificationException.<init>:(Lorg/apache/commons/math3/exception/util/Localizable;[Ljava/lang/Object;)V (2, 1)
	47 athrow (2, 1)
	48 aload_0 (1, 4)
	49 aload_1 (1, 4)
	50 iload_2 (1, 4)
	51 aaload (1, 4)
	52 iconst_0 (1, 4)
	53 daload (1, 4)
	54 aload_1 (1, 4)
	55 iload_2 (1, 4)
	56 aaload (1, 4)
	57 iconst_1 (1, 4)
	58 daload (1, 4)
	59 invokevirtual (1, 4)
	60 org/apache/commons/math3/stat/regression/SimpleRegression.addData:(DD)V (1, 4)
	62 iinc (1, 4)
	63 #2 (1, 4)
	64 -89 (1, 4)
	65 goto (1, 4)
	66 -63 (1, 4)
	68 return (0, 0)

Method: append
	0 aload_0 (1, 1)
	1 getfield (1, 1)
	2 org/apache/commons/math3/stat/regression/SimpleRegression.n:J (1, 1)
	4 lconst_0 (1, 1)
	5 lcmp (1, 1)
	6 ifne (1, 1)
	7 46 (1, 1)
	9 aload_0 (1, 1)
	10 aload_1 (1, 1)
	11 getfield (1, 1)
	12 org/apache/commons/math3/stat/regression/SimpleRegression.xbar:D (1, 1)
	14 putfield (1, 1)
	15 org/apache/commons/math3/stat/regression/SimpleRegression.xbar:D (1, 1)
	17 aload_0 (1, 1)
	18 aload_1 (1, 1)
	19 getfield (1, 1)
	20 org/apache/commons/math3/stat/regression/SimpleRegression.ybar:D (1, 1)
	22 putfield (1, 1)
	23 org/apache/commons/math3/stat/regression/SimpleRegression.ybar:D (1, 1)
	25 aload_0 (1, 1)
	26 aload_1 (1, 1)
	27 getfield (1, 1)
	28 org/apache/commons/math3/stat/regression/SimpleRegression.sumXX:D (1, 1)
	30 putfield (1, 1)
	31 org/apache/commons/math3/stat/regression/SimpleRegression.sumXX:D (1, 1)
	33 aload_0 (1, 1)
	34 aload_1 (1, 1)
	35 getfield (1, 1)
	36 org/apache/commons/math3/stat/regression/SimpleRegression.sumYY:D (1, 1)
	38 putfield (1, 1)
	39 org/apache/commons/math3/stat/regression/SimpleRegression.sumYY:D (1, 1)
	41 aload_0 (1, 1)
	42 aload_1 (1, 1)
	43 getfield (1, 1)
	44 org/apache/commons/math3/stat/regression/SimpleRegression.sumXY:D (1, 1)
	46 putfield (1, 1)
	47 org/apache/commons/math3/stat/regression/SimpleRegression.sumXY:D (1, 1)
	49 goto (1, 1)
	50 206 (1, 1)
	52 aload_0 (2, 1)
	53 getfield (2, 1)
	54 org/apache/commons/math3/stat/regression/SimpleRegression.hasIntercept:Z (2, 1)
	56 ifeq (2, 1)
	57 160 (2, 1)
	59 aload_1 (2, 1)
	60 getfield (2, 1)
	61 org/apache/commons/math3/stat/regression/SimpleRegression.n:J (2, 1)
	63 l2d (2, 1)
	64 aload_1 (2, 1)
	65 getfield (2, 1)
	66 org/apache/commons/math3/stat/regression/SimpleRegression.n:J (2, 1)
	68 aload_0 (2, 1)
	69 getfield (2, 1)
	70 org/apache/commons/math3/stat/regression/SimpleRegression.n:J (2, 1)
	72 ladd (2, 1)
	73 l2d (2, 1)
	74 ddiv (2, 1)
	75 dstore_2 (2, 1)
	76 aload_0 (2, 1)
	77 getfield (2, 1)
	78 org/apache/commons/math3/stat/regression/SimpleRegression.n:J (2, 1)
	80 aload_1 (2, 1)
	81 getfield (2, 1)
	82 org/apache/commons/math3/stat/regression/SimpleRegression.n:J (2, 1)
	84 lmul (2, 1)
	85 l2d (2, 1)
	86 aload_1 (2, 1)
	87 getfield (2, 1)
	88 org/apache/commons/math3/stat/regression/SimpleRegression.n:J (2, 1)
	90 aload_0 (2, 1)
	91 getfield (2, 1)
	92 org/apache/commons/math3/stat/regression/SimpleRegression.n:J (2, 1)
	94 ladd (2, 1)
	95 l2d (2, 1)
	96 ddiv (2, 1)
	97 dstore (2, 1)
	98 #4 (2, 1)
	99 aload_1 (2, 1)
	100 getfield (2, 1)
	101 org/apache/commons/math3/stat/regression/SimpleRegression.xbar:D (2, 1)
	103 aload_0 (2, 1)
	104 getfield (2, 1)
	105 org/apache/commons/math3/stat/regression/SimpleRegression.xbar:D (2, 1)
	107 dsub (2, 1)
	108 dstore (2, 1)
	109 #6 (2, 1)
	110 aload_1 (2, 1)
	111 getfield (2, 1)
	112 org/apache/commons/math3/stat/regression/SimpleRegression.ybar:D (2, 1)
	114 aload_0 (2, 1)
	115 getfield (2, 1)
	116 org/apache/commons/math3/stat/regression/SimpleRegression.ybar:D (2, 1)
	118 dsub (2, 1)
	119 dstore (2, 1)
	120 #8 (2, 1)
	121 aload_0 (2, 1)
	122 dup (2, 1)
	123 getfield (2, 1)
	124 org/apache/commons/math3/stat/regression/SimpleRegression.sumXX:D (2, 1)
	126 aload_1 (2, 1)
	127 getfield (2, 1)
	128 org/apache/commons/math3/stat/regression/SimpleRegression.sumXX:D (2, 1)
	130 dload (2, 1)
	131 #6 (2, 1)
	132 dload (2, 1)
	133 #6 (2, 1)
	134 dmul (2, 1)
	135 dload (2, 1)
	136 #4 (2, 1)
	137 dmul (2, 1)
	138 dadd (2, 1)
	139 dadd (2, 1)
	140 putfield (2, 1)
	141 org/apache/commons/math3/stat/regression/SimpleRegression.sumXX:D (2, 1)
	143 aload_0 (2, 1)
	144 dup (2, 1)
	145 getfield (2, 1)
	146 org/apache/commons/math3/stat/regression/SimpleRegression.sumYY:D (2, 1)
	148 aload_1 (2, 1)
	149 getfield (2, 1)
	150 org/apache/commons/math3/stat/regression/SimpleRegression.sumYY:D (2, 1)
	152 dload (2, 1)
	153 #8 (2, 1)
	154 dload (2, 1)
	155 #8 (2, 1)
	156 dmul (2, 1)
	157 dload (2, 1)
	158 #4 (2, 1)
	159 dmul (2, 1)
	160 dadd (2, 1)
	161 dadd (2, 1)
	162 putfield (2, 1)
	163 org/apache/commons/math3/stat/regression/SimpleRegression.sumYY:D (2, 1)
	165 aload_0 (2, 1)
	166 dup (2, 1)
	167 getfield (2, 1)
	168 org/apache/commons/math3/stat/regression/SimpleRegression.sumXY:D (2, 1)
	170 aload_1 (2, 1)
	171 getfield (2, 1)
	172 org/apache/commons/math3/stat/regression/SimpleRegression.sumXY:D (2, 1)
	174 dload (2, 1)
	175 #6 (2, 1)
	176 dload (2, 1)
	177 #8 (2, 1)
	178 dmul (2, 1)
	179 dload (2, 1)
	180 #4 (2, 1)
	181 dmul (2, 1)
	182 dadd (2, 1)
	183 dadd (2, 1)
	184 putfield (2, 1)
	185 org/apache/commons/math3/stat/regression/SimpleRegression.sumXY:D (2, 1)
	187 aload_0 (2, 1)
	188 dup (2, 1)
	189 getfield (2, 1)
	190 org/apache/commons/math3/stat/regression/SimpleRegression.xbar:D (2, 1)
	192 dload (2, 1)
	193 #6 (2, 1)
	194 dload_2 (2, 1)
	195 dmul (2, 1)
	196 dadd (2, 1)
	197 putfield (2, 1)
	198 org/apache/commons/math3/stat/regression/SimpleRegression.xbar:D (2, 1)
	200 aload_0 (2, 1)
	201 dup (2, 1)
	202 getfield (2, 1)
	203 org/apache/commons/math3/stat/regression/SimpleRegression.ybar:D (2, 1)
	205 dload (2, 1)
	206 #8 (2, 1)
	207 dload_2 (2, 1)
	208 dmul (2, 1)
	209 dadd (2, 1)
	210 putfield (2, 1)
	211 org/apache/commons/math3/stat/regression/SimpleRegression.ybar:D (2, 1)
	213 goto (2, 2)
	214 42 (2, 2)
	216 aload_0 (2, 2)
	217 dup (2, 2)
	218 getfield (2, 2)
	219 org/apache/commons/math3/stat/regression/SimpleRegression.sumXX:D (2, 2)
	221 aload_1 (2, 2)
	222 getfield (2, 2)
	223 org/apache/commons/math3/stat/regression/SimpleRegression.sumXX:D (2, 2)
	225 dadd (2, 2)
	226 putfield (2, 2)
	227 org/apache/commons/math3/stat/regression/SimpleRegression.sumXX:D (2, 2)
	229 aload_0 (2, 2)
	230 dup (2, 2)
	231 getfield (2, 2)
	232 org/apache/commons/math3/stat/regression/SimpleRegression.sumYY:D (2, 2)
	234 aload_1 (2, 2)
	235 getfield (2, 2)
	236 org/apache/commons/math3/stat/regression/SimpleRegression.sumYY:D (2, 2)
	238 dadd (2, 2)
	239 putfield (2, 2)
	240 org/apache/commons/math3/stat/regression/SimpleRegression.sumYY:D (2, 2)
	242 aload_0 (2, 2)
	243 dup (2, 2)
	244 getfield (2, 2)
	245 org/apache/commons/math3/stat/regression/SimpleRegression.sumXY:D (2, 2)
	247 aload_1 (2, 2)
	248 getfield (2, 2)
	249 org/apache/commons/math3/stat/regression/SimpleRegression.sumXY:D (2, 2)
	251 dadd (2, 2)
	252 putfield (2, 2)
	253 org/apache/commons/math3/stat/regression/SimpleRegression.sumXY:D (2, 2)
	255 aload_0 (0, 0)
	256 dup (0, 0)
	257 getfield (0, 0)
	258 org/apache/commons/math3/stat/regression/SimpleRegression.sumX:D (0, 0)
	260 aload_1 (0, 0)
	261 getfield (0, 0)
	262 org/apache/commons/math3/stat/regression/SimpleRegression.sumX:D (0, 0)
	264 dadd (0, 0)
	265 putfield (0, 0)
	266 org/apache/commons/math3/stat/regression/SimpleRegression.sumX:D (0, 0)
	268 aload_0 (0, 0)
	269 dup (0, 0)
	270 getfield (0, 0)
	271 org/apache/commons/math3/stat/regression/SimpleRegression.sumY:D (0, 0)
	273 aload_1 (0, 0)
	274 getfield (0, 0)
	275 org/apache/commons/math3/stat/regression/SimpleRegression.sumY:D (0, 0)
	277 dadd (0, 0)
	278 putfield (0, 0)
	279 org/apache/commons/math3/stat/regression/SimpleRegression.sumY:D (0, 0)
	281 aload_0 (0, 0)
	282 dup (0, 0)
	283 getfield (0, 0)
	284 org/apache/commons/math3/stat/regression/SimpleRegression.n:J (0, 0)
	286 aload_1 (0, 0)
	287 getfield (0, 0)
	288 org/apache/commons/math3/stat/regression/SimpleRegression.n:J (0, 0)
	290 ladd (0, 0)
	291 putfield (0, 0)
	292 org/apache/commons/math3/stat/regression/SimpleRegression.n:J (0, 0)
	294 return (0, 0)

Method: removeData
	0 iconst_0 (1, 4)
	1 istore_2 (1, 4)
	2 iload_2 (1, 4)
	3 aload_1 (1, 4)
	4 arraylength (1, 4)
	5 if_icmpge (1, 4)
	6 32 (1, 4)
	8 aload_0 (1, 4)
	9 getfield (1, 4)
	10 org/apache/commons/math3/stat/regression/SimpleRegression.n:J (1, 4)
	12 lconst_0 (1, 4)
	13 lcmp (1, 4)
	14 ifle (1, 4)
	15 23 (1, 4)
	17 aload_0 (1, 4)
	18 aload_1 (1, 4)
	19 iload_2 (1, 4)
	20 aaload (1, 4)
	21 iconst_0 (1, 4)
	22 daload (1, 4)
	23 aload_1 (1, 4)
	24 iload_2 (1, 4)
	25 aaload (1, 4)
	26 iconst_1 (1, 4)
	27 daload (1, 4)
	28 invokevirtual (1, 4)
	29 org/apache/commons/math3/stat/regression/SimpleRegression.removeData:(DD)V (1, 4)
	31 iinc (1, 4)
	32 #2 (1, 4)
	33 -89 (1, 4)
	34 goto (1, 4)
	35 -32 (1, 4)
	37 return (0, 0)

Method: addObservation
	0 aload_1 (1, 1)
	1 ifnull (1, 1)
	2 8 (1, 1)
	4 aload_1 (1, 1)
	5 arraylength (1, 1)
	6 ifne (1, 1)
	7 41 (1, 1)
	9 new (1, 1)
	10 org/apache/commons/math3/stat/regression/ModelSpecificationException (1, 1)
	12 dup (1, 1)
	13 getstatic (1, 1)
	14 org/apache/commons/math3/exception/util/LocalizedFormats.INVALID_REGRESSION_OBSERVATION:Lorg/apache/commons/math3/exception/util/LocalizedFormats; (1, 1)
	16 iconst_2 (1, 1)
	17 anewarray (1, 1)
	18 java/lang/Object (1, 1)
	20 dup (1, 1)
	21 iconst_0 (1, 1)
	22 aload_1 (1, 1)
	23 ifnull (1, 1)
	24 8 (1, 1)
	26 aload_1 (1, 1)
	27 arraylength (1, 1)
	28 goto (1, 1)
	29 4 (1, 1)
	31 iconst_0 (1, 1)
	32 invokestatic (1, 1)
	33 java/lang/Integer.valueOf:(I)Ljava/lang/Integer; (1, 1)
	35 aastore (1, 1)
	36 dup (1, 1)
	37 iconst_1 (1, 1)
	38 iconst_1 (1, 1)
	39 invokestatic (1, 1)
	40 java/lang/Integer.valueOf:(I)Ljava/lang/Integer; (1, 1)
	42 aastore (1, 1)
	43 invokespecial (1, 1)
	44 org/apache/commons/math3/stat/regression/ModelSpecificationException.<init>:(Lorg/apache/commons/math3/exception/util/Localizable;[Ljava/lang/Object;)V (1, 1)
	46 athrow (1, 1)
	47 aload_0 (0, 0)
	48 aload_1 (0, 0)
	49 iconst_0 (0, 0)
	50 daload (0, 0)
	51 dload_2 (0, 0)
	52 invokevirtual (0, 0)
	53 org/apache/commons/math3/stat/regression/SimpleRegression.addData:(DD)V (0, 0)
	55 return (0, 0)

Method: addObservations
	0 aload_1 (1, 1)
	1 ifnull (1, 1)
	2 14 (1, 1)
	4 aload_2 (1, 1)
	5 ifnull (1, 1)
	6 10 (1, 1)
	8 aload_1 (1, 1)
	9 arraylength (1, 1)
	10 aload_2 (1, 1)
	11 arraylength (1, 1)
	12 if_icmpeq (1, 1)
	13 50 (1, 1)
	15 new (1, 1)
	16 org/apache/commons/math3/stat/regression/ModelSpecificationException (1, 1)
	18 dup (1, 1)
	19 getstatic (1, 1)
	20 org/apache/commons/math3/exception/util/LocalizedFormats.DIMENSIONS_MISMATCH_SIMPLE:Lorg/apache/commons/math3/exception/util/LocalizedFormats; (1, 1)
	22 iconst_2 (1, 1)
	23 anewarray (1, 1)
	24 java/lang/Object (1, 1)
	26 dup (1, 1)
	27 iconst_0 (1, 1)
	28 aload_1 (1, 1)
	29 ifnonnull (1, 1)
	30 7 (1, 1)
	32 iconst_0 (1, 1)
	33 goto (1, 1)
	34 5 (1, 1)
	36 aload_1 (1, 1)
	37 arraylength (1, 1)
	38 invokestatic (1, 1)
	39 java/lang/Integer.valueOf:(I)Ljava/lang/Integer; (1, 1)
	41 aastore (1, 1)
	42 dup (1, 1)
	43 iconst_1 (1, 1)
	44 aload_2 (1, 1)
	45 ifnonnull (1, 1)
	46 7 (1, 1)
	48 iconst_0 (1, 1)
	49 goto (1, 1)
	50 5 (1, 1)
	52 aload_2 (1, 1)
	53 arraylength (1, 1)
	54 invokestatic (1, 1)
	55 java/lang/Integer.valueOf:(I)Ljava/lang/Integer; (1, 1)
	57 aastore (1, 1)
	58 invokespecial (1, 1)
	59 org/apache/commons/math3/stat/regression/ModelSpecificationException.<init>:(Lorg/apache/commons/math3/exception/util/Localizable;[Ljava/lang/Object;)V (1, 1)
	61 athrow (1, 1)
	62 iconst_1 (0, 0)
	63 istore_3 (0, 0)
	64 iconst_0 (1, 4)
	65 istore (1, 4)
	66 #4 (1, 4)
	67 iload (1, 4)
	68 #4 (1, 4)
	69 aload_1 (1, 4)
	70 arraylength (1, 4)
	71 if_icmpge (1, 4)
	72 26 (1, 4)
	74 aload_1 (2, 1)
	75 iload (2, 1)
	76 #4 (2, 1)
	77 aaload (2, 1)
	78 ifnull (2, 1)
	79 11 (2, 1)
	81 aload_1 (2, 1)
	82 iload (2, 1)
	83 #4 (2, 1)
	84 aaload (2, 1)
	85 arraylength (2, 1)
	86 ifne (2, 1)
	87 5 (2, 1)
	89 iconst_0 (2, 1)
	90 istore_3 (2, 1)
	91 iinc (2, 1)
	92 #4 (2, 1)
	93 -89 (2, 1)
	94 goto (2, 1)
	95 -27 (2, 1)
	97 iload_3 (2, 1)
	98 ifne (2, 1)
	99 32 (2, 1)
	101 new (2, 1)
	102 org/apache/commons/math3/stat/regression/ModelSpecificationException (2, 1)
	104 dup (2, 1)
	105 getstatic (2, 1)
	106 org/apache/commons/math3/exception/util/LocalizedFormats.NOT_ENOUGH_DATA_FOR_NUMBER_OF_PREDICTORS:Lorg/apache/commons/math3/exception/util/LocalizedFormats; (2, 1)
	108 iconst_2 (2, 1)
	109 anewarray (2, 1)
	110 java/lang/Object (2, 1)
	112 dup (2, 1)
	113 iconst_0 (2, 1)
	114 iconst_0 (2, 1)
	115 invokestatic (2, 1)
	116 java/lang/Integer.valueOf:(I)Ljava/lang/Integer; (2, 1)
	118 aastore (2, 1)
	119 dup (2, 1)
	120 iconst_1 (2, 1)
	121 iconst_1 (2, 1)
	122 invokestatic (2, 1)
	123 java/lang/Integer.valueOf:(I)Ljava/lang/Integer; (2, 1)
	125 aastore (2, 1)
	126 invokespecial (2, 1)
	127 org/apache/commons/math3/stat/regression/ModelSpecificationException.<init>:(Lorg/apache/commons/math3/exception/util/Localizable;[Ljava/lang/Object;)V (2, 1)
	129 athrow (2, 1)
	130 iconst_0 (2, 4)
	131 istore (2, 4)
	132 #4 (2, 4)
	133 iload (2, 4)
	134 #4 (2, 4)
	135 aload_1 (2, 4)
	136 arraylength (2, 4)
	137 if_icmpge (2, 4)
	138 23 (2, 4)
	140 aload_0 (2, 4)
	141 aload_1 (2, 4)
	142 iload (2, 4)
	143 #4 (2, 4)
	144 aaload (2, 4)
	145 iconst_0 (2, 4)
	146 daload (2, 4)
	147 aload_2 (2, 4)
	148 iload (2, 4)
	149 #4 (2, 4)
	150 daload (2, 4)
	151 invokevirtual (2, 4)
	152 org/apache/commons/math3/stat/regression/SimpleRegression.addData:(DD)V (2, 4)
	154 iinc (2, 4)
	155 #4 (2, 4)
	156 -89 (2, 4)
	157 goto (2, 4)
	158 -24 (2, 4)
	160 return (0, 0)

Method: clear
	0 aload_0 (0, 0)
	1 dconst_0 (0, 0)
	2 putfield (0, 0)
	3 org/apache/commons/math3/stat/regression/SimpleRegression.sumX:D (0, 0)
	5 aload_0 (0, 0)
	6 dconst_0 (0, 0)
	7 putfield (0, 0)
	8 org/apache/commons/math3/stat/regression/SimpleRegression.sumXX:D (0, 0)
	10 aload_0 (0, 0)
	11 dconst_0 (0, 0)
	12 putfield (0, 0)
	13 org/apache/commons/math3/stat/regression/SimpleRegression.sumY:D (0, 0)
	15 aload_0 (0, 0)
	16 dconst_0 (0, 0)
	17 putfield (0, 0)
	18 org/apache/commons/math3/stat/regression/SimpleRegression.sumYY:D (0, 0)
	20 aload_0 (0, 0)
	21 dconst_0 (0, 0)
	22 putfield (0, 0)
	23 org/apache/commons/math3/stat/regression/SimpleRegression.sumXY:D (0, 0)
	25 aload_0 (0, 0)
	26 lconst_0 (0, 0)
	27 putfield (0, 0)
	28 org/apache/commons/math3/stat/regression/SimpleRegression.n:J (0, 0)
	30 return (0, 0)

Method: getN
	0 aload_0 (0, 0)
	1 getfield (0, 0)
	2 org/apache/commons/math3/stat/regression/SimpleRegression.n:J (0, 0)
	4 lreturn (0, 0)

Method: predict
	0 aload_0 (0, 0)
	1 invokevirtual (0, 0)
	2 org/apache/commons/math3/stat/regression/SimpleRegression.getSlope:()D (0, 0)
	4 dstore_3 (0, 0)
	5 aload_0 (1, 1)
	6 getfield (1, 1)
	7 org/apache/commons/math3/stat/regression/SimpleRegression.hasIntercept:Z (1, 1)
	9 ifeq (1, 1)
	10 13 (1, 1)
	12 aload_0 (1, 1)
	13 dload_3 (1, 1)
	14 invokespecial (1, 1)
	15 org/apache/commons/math3/stat/regression/SimpleRegression.getIntercept:(D)D (1, 1)
	17 dload_3 (1, 1)
	18 dload_1 (1, 1)
	19 dmul (1, 1)
	20 dadd (1, 1)
	21 dreturn (1, 1)
	22 dload_3 (0, 0)
	23 dload_1 (0, 0)
	24 dmul (0, 0)
	25 dreturn (0, 0)

Method: getIntercept
	0 aload_0 (1, 1)
	1 getfield (1, 1)
	2 org/apache/commons/math3/stat/regression/SimpleRegression.hasIntercept:Z (1, 1)
	4 ifeq (1, 1)
	5 21 (1, 1)
	7 aload_0 (1, 1)
	8 getfield (1, 1)
	9 org/apache/commons/math3/stat/regression/SimpleRegression.sumY:D (1, 1)
	11 dload_1 (1, 1)
	12 aload_0 (1, 1)
	13 getfield (1, 1)
	14 org/apache/commons/math3/stat/regression/SimpleRegression.sumX:D (1, 1)
	16 dmul (1, 1)
	17 dsub (1, 1)
	18 aload_0 (1, 1)
	19 getfield (1, 1)
	20 org/apache/commons/math3/stat/regression/SimpleRegression.n:J (1, 1)
	22 l2d (1, 1)
	23 ddiv (1, 1)
	24 dreturn (1, 1)
	25 dconst_0 (0, 0)
	26 dreturn (0, 0)

Method: hasIntercept
	0 aload_0 (0, 0)
	1 getfield (0, 0)
	2 org/apache/commons/math3/stat/regression/SimpleRegression.hasIntercept:Z (0, 0)
	4 ireturn (0, 0)

Method: getSlope
	0 aload_0 (1, 1)
	1 getfield (1, 1)
	2 org/apache/commons/math3/stat/regression/SimpleRegression.n:J (1, 1)
	4 ldc2_w (1, 1)
	5 2 (1, 1)
	7 lcmp (1, 1)
	8 ifge (1, 1)
	9 7 (1, 1)
	11 ldc2_w (1, 1)
	12 nan (1, 1)
	14 dreturn (1, 1)
	15 aload_0 (1, 1)
	16 getfield (1, 1)
	17 org/apache/commons/math3/stat/regression/SimpleRegression.sumXX:D (1, 1)
	19 invokestatic (1, 1)
	20 org/apache/commons/math3/util/FastMath.abs:(D)D (1, 1)
	22 ldc2_w (1, 1)
	23 5e-323 (1, 1)
	25 dcmpg (1, 1)
	26 ifge (1, 1)
	27 7 (1, 1)
	29 ldc2_w (1, 1)
	30 nan (1, 1)
	32 dreturn (1, 1)
	33 aload_0 (0, 0)
	34 getfield (0, 0)
	35 org/apache/commons/math3/stat/regression/SimpleRegression.sumXY:D (0, 0)
	37 aload_0 (0, 0)
	38 getfield (0, 0)
	39 org/apache/commons/math3/stat/regression/SimpleRegression.sumXX:D (0, 0)
	41 ddiv (0, 0)
	42 dreturn (0, 0)

Method: getSumSquaredErrors
	0 dconst_0 (0, 0)
	1 aload_0 (0, 0)
	2 getfield (0, 0)
	3 org/apache/commons/math3/stat/regression/SimpleRegression.sumYY:D (0, 0)
	5 aload_0 (0, 0)
	6 getfield (0, 0)
	7 org/apache/commons/math3/stat/regression/SimpleRegression.sumXY:D (0, 0)
	9 aload_0 (0, 0)
	10 getfield (0, 0)
	11 org/apache/commons/math3/stat/regression/SimpleRegression.sumXY:D (0, 0)
	13 dmul (0, 0)
	14 aload_0 (0, 0)
	15 getfield (0, 0)
	16 org/apache/commons/math3/stat/regression/SimpleRegression.sumXX:D (0, 0)
	18 ddiv (0, 0)
	19 dsub (0, 0)
	20 invokestatic (0, 0)
	21 org/apache/commons/math3/util/FastMath.max:(DD)D (0, 0)
	23 dreturn (0, 0)

Method: getTotalSumSquares
	0 aload_0 (1, 1)
	1 getfield (1, 1)
	2 org/apache/commons/math3/stat/regression/SimpleRegression.n:J (1, 1)
	4 ldc2_w (1, 1)
	5 2 (1, 1)
	7 lcmp (1, 1)
	8 ifge (1, 1)
	9 7 (1, 1)
	11 ldc2_w (1, 1)
	12 nan (1, 1)
	14 dreturn (1, 1)
	15 aload_0 (0, 0)
	16 getfield (0, 0)
	17 org/apache/commons/math3/stat/regression/SimpleRegression.sumYY:D (0, 0)
	19 dreturn (0, 0)

Method: getXSumSquares
	0 aload_0 (1, 1)
	1 getfield (1, 1)
	2 org/apache/commons/math3/stat/regression/SimpleRegression.n:J (1, 1)
	4 ldc2_w (1, 1)
	5 2 (1, 1)
	7 lcmp (1, 1)
	8 ifge (1, 1)
	9 7 (1, 1)
	11 ldc2_w (1, 1)
	12 nan (1, 1)
	14 dreturn (1, 1)
	15 aload_0 (0, 0)
	16 getfield (0, 0)
	17 org/apache/commons/math3/stat/regression/SimpleRegression.sumXX:D (0, 0)
	19 dreturn (0, 0)

Method: getSumOfCrossProducts
	0 aload_0 (0, 0)
	1 getfield (0, 0)
	2 org/apache/commons/math3/stat/regression/SimpleRegression.sumXY:D (0, 0)
	4 dreturn (0, 0)

Method: getRegressionSumSquares
	0 dload_1 (0, 0)
	1 dload_1 (0, 0)
	2 dmul (0, 0)
	3 aload_0 (0, 0)
	4 getfield (0, 0)
	5 org/apache/commons/math3/stat/regression/SimpleRegression.sumXX:D (0, 0)
	7 dmul (0, 0)
	8 dreturn (0, 0)

Method: getMeanSquareError
	0 aload_0 (1, 1)
	1 getfield (1, 1)
	2 org/apache/commons/math3/stat/regression/SimpleRegression.n:J (1, 1)
	4 ldc2_w (1, 1)
	5 3 (1, 1)
	7 lcmp (1, 1)
	8 ifge (1, 1)
	9 7 (1, 1)
	11 ldc2_w (1, 1)
	12 nan (1, 1)
	14 dreturn (1, 1)
	15 aload_0 (0, 0)
	16 getfield (0, 0)
	17 org/apache/commons/math3/stat/regression/SimpleRegression.hasIntercept:Z (0, 0)
	19 ifeq (0, 0)
	20 20 (0, 0)
	22 aload_0 (0, 0)
	23 invokevirtual (0, 0)
	24 org/apache/commons/math3/stat/regression/SimpleRegression.getSumSquaredErrors:()D (0, 0)
	26 aload_0 (0, 0)
	27 getfield (0, 0)
	28 org/apache/commons/math3/stat/regression/SimpleRegression.n:J (0, 0)
	30 ldc2_w (0, 0)
	31 2 (0, 0)
	33 lsub (0, 0)
	34 l2d (0, 0)
	35 ddiv (0, 0)
	36 goto (0, 0)
	37 15 (0, 0)
	39 aload_0 (0, 0)
	40 invokevirtual (0, 0)
	41 org/apache/commons/math3/stat/regression/SimpleRegression.getSumSquaredErrors:()D (0, 0)
	43 aload_0 (0, 0)
	44 getfield (0, 0)
	45 org/apache/commons/math3/stat/regression/SimpleRegression.n:J (0, 0)
	47 lconst_1 (0, 0)
	48 lsub (0, 0)
	49 l2d (0, 0)
	50 ddiv (0, 0)
	51 dreturn (0, 0)

Method: getR
	0 aload_0 (0, 0)
	1 invokevirtual (0, 0)
	2 org/apache/commons/math3/stat/regression/SimpleRegression.getSlope:()D (0, 0)
	4 dstore_1 (0, 0)
	5 aload_0 (0, 0)
	6 invokevirtual (0, 0)
	7 org/apache/commons/math3/stat/regression/SimpleRegression.getRSquare:()D (0, 0)
	9 invokestatic (0, 0)
	10 org/apache/commons/math3/util/FastMath.sqrt:(D)D (0, 0)
	12 dstore_3 (0, 0)
	13 dload_1 (1, 1)
	14 dconst_0 (1, 1)
	15 dcmpg (1, 1)
	16 ifge (1, 1)
	17 6 (1, 1)
	19 dload_3 (1, 1)
	20 dneg (1, 1)
	21 dstore_3 (1, 1)
	22 dload_3 (0, 0)
	23 dreturn (0, 0)

Method: getRSquare
	0 aload_0 (0, 0)
	1 invokevirtual (0, 0)
	2 org/apache/commons/math3/stat/regression/SimpleRegression.getTotalSumSquares:()D (0, 0)
	4 dstore_1 (0, 0)
	5 dload_1 (0, 0)
	6 aload_0 (0, 0)
	7 invokevirtual (0, 0)
	8 org/apache/commons/math3/stat/regression/SimpleRegression.getSumSquaredErrors:()D (0, 0)
	10 dsub (0, 0)
	11 dload_1 (0, 0)
	12 ddiv (0, 0)
	13 dreturn (0, 0)

Method: getInterceptStdErr
	0 aload_0 (1, 1)
	1 getfield (1, 1)
	2 org/apache/commons/math3/stat/regression/SimpleRegression.hasIntercept:Z (1, 1)
	4 ifne (1, 1)
	5 7 (1, 1)
	7 ldc2_w (1, 1)
	8 nan (1, 1)
	10 dreturn (1, 1)
	11 aload_0 (0, 0)
	12 invokevirtual (0, 0)
	13 org/apache/commons/math3/stat/regression/SimpleRegression.getMeanSquareError:()D (0, 0)
	15 dconst_1 (0, 0)
	16 aload_0 (0, 0)
	17 getfield (0, 0)
	18 org/apache/commons/math3/stat/regression/SimpleRegression.n:J (0, 0)
	20 l2d (0, 0)
	21 ddiv (0, 0)
	22 aload_0 (0, 0)
	23 getfield (0, 0)
	24 org/apache/commons/math3/stat/regression/SimpleRegression.xbar:D (0, 0)
	26 aload_0 (0, 0)
	27 getfield (0, 0)
	28 org/apache/commons/math3/stat/regression/SimpleRegression.xbar:D (0, 0)
	30 dmul (0, 0)
	31 aload_0 (0, 0)
	32 getfield (0, 0)
	33 org/apache/commons/math3/stat/regression/SimpleRegression.sumXX:D (0, 0)
	35 ddiv (0, 0)
	36 dadd (0, 0)
	37 dmul (0, 0)
	38 invokestatic (0, 0)
	39 org/apache/commons/math3/util/FastMath.sqrt:(D)D (0, 0)
	41 dreturn (0, 0)

Method: getSlopeStdErr
	0 aload_0 (0, 0)
	1 invokevirtual (0, 0)
	2 org/apache/commons/math3/stat/regression/SimpleRegression.getMeanSquareError:()D (0, 0)
	4 aload_0 (0, 0)
	5 getfield (0, 0)
	6 org/apache/commons/math3/stat/regression/SimpleRegression.sumXX:D (0, 0)
	8 ddiv (0, 0)
	9 invokestatic (0, 0)
	10 org/apache/commons/math3/util/FastMath.sqrt:(D)D (0, 0)
	12 dreturn (0, 0)

Method: getSlopeConfidenceInterval
	0 aload_0 (1, 1)
	1 getfield (1, 1)
	2 org/apache/commons/math3/stat/regression/SimpleRegression.n:J (1, 1)
	4 ldc2_w (1, 1)
	5 3 (1, 1)
	7 lcmp (1, 1)
	8 ifge (1, 1)
	9 7 (1, 1)
	11 ldc2_w (1, 1)
	12 nan (1, 1)
	14 dreturn (1, 1)
	15 dload_1 (1, 1)
	16 dconst_1 (1, 1)
	17 dcmpl (1, 1)
	18 ifge (1, 1)
	19 9 (1, 1)
	21 dload_1 (1, 1)
	22 dconst_0 (1, 1)
	23 dcmpg (1, 1)
	24 ifgt (1, 1)
	25 26 (1, 1)
	27 new (1, 1)
	28 org/apache/commons/math3/exception/OutOfRangeException (1, 1)
	30 dup (1, 1)
	31 getstatic (1, 1)
	32 org/apache/commons/math3/exception/util/LocalizedFormats.SIGNIFICANCE_LEVEL:Lorg/apache/commons/math3/exception/util/LocalizedFormats; (1, 1)
	34 dload_1 (1, 1)
	35 invokestatic (1, 1)
	36 java/lang/Double.valueOf:(D)Ljava/lang/Double; (1, 1)
	38 iconst_0 (1, 1)
	39 invokestatic (1, 1)
	40 java/lang/Integer.valueOf:(I)Ljava/lang/Integer; (1, 1)
	42 iconst_1 (1, 1)
	43 invokestatic (1, 1)
	44 java/lang/Integer.valueOf:(I)Ljava/lang/Integer; (1, 1)
	46 invokespecial (1, 1)
	47 org/apache/commons/math3/exception/OutOfRangeException.<init>:(Lorg/apache/commons/math3/exception/util/Localizable;Ljava/lang/Number;Ljava/lang/Number;Ljava/lang/Number;)V (1, 1)
	49 athrow (1, 1)
	50 new (0, 0)
	51 org/apache/commons/math3/distribution/TDistribution (0, 0)
	53 dup (0, 0)
	54 aload_0 (0, 0)
	55 getfield (0, 0)
	56 org/apache/commons/math3/stat/regression/SimpleRegression.n:J (0, 0)
	58 ldc2_w (0, 0)
	59 2 (0, 0)
	61 lsub (0, 0)
	62 l2d (0, 0)
	63 invokespecial (0, 0)
	64 org/apache/commons/math3/distribution/TDistribution.<init>:(D)V (0, 0)
	66 astore_3 (0, 0)
	67 aload_0 (0, 0)
	68 invokevirtual (0, 0)
	69 org/apache/commons/math3/stat/regression/SimpleRegression.getSlopeStdErr:()D (0, 0)
	71 aload_3 (0, 0)
	72 dconst_1 (0, 0)
	73 dload_1 (0, 0)
	74 ldc2_w (0, 0)
	75 2.0 (0, 0)
	77 ddiv (0, 0)
	78 dsub (0, 0)
	79 invokevirtual (0, 0)
	80 org/apache/commons/math3/distribution/TDistribution.inverseCumulativeProbability:(D)D (0, 0)
	82 dmul (0, 0)
	83 dreturn (0, 0)

Method: getSignificance
	0 aload_0 (1, 1)
	1 getfield (1, 1)
	2 org/apache/commons/math3/stat/regression/SimpleRegression.n:J (1, 1)
	4 ldc2_w (1, 1)
	5 3 (1, 1)
	7 lcmp (1, 1)
	8 ifge (1, 1)
	9 7 (1, 1)
	11 ldc2_w (1, 1)
	12 nan (1, 1)
	14 dreturn (1, 1)
	15 new (0, 0)
	16 org/apache/commons/math3/distribution/TDistribution (0, 0)
	18 dup (0, 0)
	19 aload_0 (0, 0)
	20 getfield (0, 0)
	21 org/apache/commons/math3/stat/regression/SimpleRegression.n:J (0, 0)
	23 ldc2_w (0, 0)
	24 2 (0, 0)
	26 lsub (0, 0)
	27 l2d (0, 0)
	28 invokespecial (0, 0)
	29 org/apache/commons/math3/distribution/TDistribution.<init>:(D)V (0, 0)
	31 astore_1 (0, 0)
	32 ldc2_w (0, 0)
	33 2.0 (0, 0)
	35 dconst_1 (0, 0)
	36 aload_1 (0, 0)
	37 aload_0 (0, 0)
	38 invokevirtual (0, 0)
	39 org/apache/commons/math3/stat/regression/SimpleRegression.getSlope:()D (0, 0)
	41 invokestatic (0, 0)
	42 org/apache/commons/math3/util/FastMath.abs:(D)D (0, 0)
	44 aload_0 (0, 0)
	45 invokevirtual (0, 0)
	46 org/apache/commons/math3/stat/regression/SimpleRegression.getSlopeStdErr:()D (0, 0)
	48 ddiv (0, 0)
	49 invokevirtual (0, 0)
	50 org/apache/commons/math3/distribution/TDistribution.cumulativeProbability:(D)D (0, 0)
	52 dsub (0, 0)
	53 dmul (0, 0)
	54 dreturn (0, 0)

Method: regress
	0 aload_1 (1, 1)
	1 ifnull (1, 1)
	2 8 (1, 1)
	4 aload_1 (1, 1)
	5 arraylength (1, 1)
	6 ifne (1, 1)
	7 18 (1, 1)
	9 new (1, 1)
	10 org/apache/commons/math3/exception/MathIllegalArgumentException (1, 1)
	12 dup (1, 1)
	13 getstatic (1, 1)
	14 org/apache/commons/math3/exception/util/LocalizedFormats.ARRAY_ZERO_LENGTH_OR_NULL_NOT_ALLOWED:Lorg/apache/commons/math3/exception/util/LocalizedFormats; (1, 1)
	16 iconst_0 (1, 1)
	17 anewarray (1, 1)
	18 java/lang/Object (1, 1)
	20 invokespecial (1, 1)
	21 org/apache/commons/math3/exception/MathIllegalArgumentException.<init>:(Lorg/apache/commons/math3/exception/util/Localizable;[Ljava/lang/Object;)V (1, 1)
	23 athrow (1, 1)
	24 aload_1 (1, 1)
	25 arraylength (1, 1)
	26 iconst_2 (1, 1)
	27 if_icmpgt (1, 1)
	28 16 (1, 1)
	30 aload_1 (1, 1)
	31 arraylength (1, 1)
	32 iconst_1 (1, 1)
	33 if_icmple (1, 1)
	34 49 (1, 1)
	36 aload_0 (1, 1)
	37 getfield (1, 1)
	38 org/apache/commons/math3/stat/regression/SimpleRegression.hasIntercept:Z (1, 1)
	40 ifne (1, 1)
	41 42 (1, 1)
	43 new (1, 1)
	44 org/apache/commons/math3/stat/regression/ModelSpecificationException (1, 1)
	46 dup (1, 1)
	47 getstatic (1, 1)
	48 org/apache/commons/math3/exception/util/LocalizedFormats.ARRAY_SIZE_EXCEEDS_MAX_VARIABLES:Lorg/apache/commons/math3/exception/util/LocalizedFormats; (1, 1)
	50 iconst_1 (1, 1)
	51 anewarray (1, 1)
	52 java/lang/Object (1, 1)
	54 dup (1, 1)
	55 iconst_0 (1, 1)
	56 aload_1 (1, 1)
	57 arraylength (1, 1)
	58 iconst_1 (1, 1)
	59 if_icmple (1, 1)
	60 14 (1, 1)
	62 aload_0 (1, 1)
	63 getfield (1, 1)
	64 org/apache/commons/math3/stat/regression/SimpleRegression.hasIntercept:Z (1, 1)
	66 ifne (1, 1)
	67 7 (1, 1)
	69 iconst_1 (1, 1)
	70 goto (1, 1)
	71 4 (1, 1)
	73 iconst_2 (1, 1)
	74 invokestatic (1, 1)
	75 java/lang/Integer.valueOf:(I)Ljava/lang/Integer; (1, 1)
	77 aastore (1, 1)
	78 invokespecial (1, 1)
	79 org/apache/commons/math3/stat/regression/ModelSpecificationException.<init>:(Lorg/apache/commons/math3/exception/util/Localizable;[Ljava/lang/Object;)V (1, 1)
	81 athrow (1, 1)
	82 aload_0 (1, 1)
	83 getfield (1, 1)
	84 org/apache/commons/math3/stat/regression/SimpleRegression.hasIntercept:Z (1, 1)
	86 ifeq (1, 1)
	87 444 (1, 1)
	89 aload_1 (2, 1)
	90 arraylength (2, 1)
	91 iconst_2 (2, 1)
	92 if_icmpne (2, 1)
	93 87 (2, 1)
	95 aload_1 (3, 1)
	96 iconst_0 (3, 1)
	97 iaload (3, 1)
	98 iconst_1 (3, 1)
	99 if_icmpne (3, 1)
	100 18 (3, 1)
	102 new (3, 1)
	103 org/apache/commons/math3/stat/regression/ModelSpecificationException (3, 1)
	105 dup (3, 1)
	106 getstatic (3, 1)
	107 org/apache/commons/math3/exception/util/LocalizedFormats.NOT_INCREASING_SEQUENCE:Lorg/apache/commons/math3/exception/util/LocalizedFormats; (3, 1)
	109 iconst_0 (3, 1)
	110 anewarray (3, 1)
	111 java/lang/Object (3, 1)
	113 invokespecial (3, 1)
	114 org/apache/commons/math3/stat/regression/ModelSpecificationException.<init>:(Lorg/apache/commons/math3/exception/util/Localizable;[Ljava/lang/Object;)V (3, 1)
	116 athrow (3, 1)
	117 aload_1 (3, 1)
	118 iconst_0 (3, 1)
	119 iaload (3, 1)
	120 ifeq (3, 1)
	121 25 (3, 1)
	123 new (3, 1)
	124 org/apache/commons/math3/exception/OutOfRangeException (3, 1)
	126 dup (3, 1)
	127 aload_1 (3, 1)
	128 iconst_0 (3, 1)
	129 iaload (3, 1)
	130 invokestatic (3, 1)
	131 java/lang/Integer.valueOf:(I)Ljava/lang/Integer; (3, 1)
	133 iconst_0 (3, 1)
	134 invokestatic (3, 1)
	135 java/lang/Integer.valueOf:(I)Ljava/lang/Integer; (3, 1)
	137 iconst_1 (3, 1)
	138 invokestatic (3, 1)
	139 java/lang/Integer.valueOf:(I)Ljava/lang/Integer; (3, 1)
	141 invokespecial (3, 1)
	142 org/apache/commons/math3/exception/OutOfRangeException.<init>:(Ljava/lang/Number;Ljava/lang/Number;Ljava/lang/Number;)V (3, 1)
	144 athrow (3, 1)
	145 aload_1 (3, 1)
	146 iconst_1 (3, 1)
	147 iaload (3, 1)
	148 iconst_1 (3, 1)
	149 if_icmpeq (3, 1)
	150 25 (3, 1)
	152 new (3, 1)
	153 org/apache/commons/math3/exception/OutOfRangeException (3, 1)
	155 dup (3, 1)
	156 aload_1 (3, 1)
	157 iconst_0 (3, 1)
	158 iaload (3, 1)
	159 invokestatic (3, 1)
	160 java/lang/Integer.valueOf:(I)Ljava/lang/Integer; (3, 1)
	162 iconst_0 (3, 1)
	163 invokestatic (3, 1)
	164 java/lang/Integer.valueOf:(I)Ljava/lang/Integer; (3, 1)
	166 iconst_1 (3, 1)
	167 invokestatic (3, 1)
	168 java/lang/Integer.valueOf:(I)Ljava/lang/Integer; (3, 1)
	170 invokespecial (3, 1)
	171 org/apache/commons/math3/exception/OutOfRangeException.<init>:(Ljava/lang/Number;Ljava/lang/Number;Ljava/lang/Number;)V (3, 1)
	173 athrow (3, 1)
	174 aload_0 (2, 1)
	175 invokevirtual (2, 1)
	176 org/apache/commons/math3/stat/regression/SimpleRegression.regress:()Lorg/apache/commons/math3/stat/regression/RegressionResults; (2, 1)
	178 areturn (2, 1)
	179 aload_1 (3, 1)
	180 iconst_0 (3, 1)
	181 iaload (3, 1)
	182 iconst_1 (3, 1)
	183 if_icmpeq (3, 1)
	184 31 (3, 1)
	186 aload_1 (3, 1)
	187 iconst_0 (3, 1)
	188 iaload (3, 1)
	189 ifeq (3, 1)
	190 25 (3, 1)
	192 new (3, 1)
	193 org/apache/commons/math3/exception/OutOfRangeException (3, 1)
	195 dup (3, 1)
	196 aload_1 (3, 1)
	197 iconst_0 (3, 1)
	198 iaload (3, 1)
	199 invokestatic (3, 1)
	200 java/lang/Integer.valueOf:(I)Ljava/lang/Integer; (3, 1)
	202 iconst_0 (3, 1)
	203 invokestatic (3, 1)
	204 java/lang/Integer.valueOf:(I)Ljava/lang/Integer; (3, 1)
	206 iconst_1 (3, 1)
	207 invokestatic (3, 1)
	208 java/lang/Integer.valueOf:(I)Ljava/lang/Integer; (3, 1)
	210 invokespecial (3, 1)
	211 org/apache/commons/math3/exception/OutOfRangeException.<init>:(Ljava/lang/Number;Ljava/lang/Number;Ljava/lang/Number;)V (3, 1)
	213 athrow (3, 1)
	214 aload_0 (2, 2)
	215 getfield (2, 2)
	216 org/apache/commons/math3/stat/regression/SimpleRegression.sumY:D (2, 2)
	218 aload_0 (2, 2)
	219 getfield (2, 2)
	220 org/apache/commons/math3/stat/regression/SimpleRegression.sumY:D (2, 2)
	222 dmul (2, 2)
	223 aload_0 (2, 2)
	224 getfield (2, 2)
	225 org/apache/commons/math3/stat/regression/SimpleRegression.n:J (2, 2)
	227 l2d (2, 2)
	228 ddiv (2, 2)
	229 dstore_2 (2, 2)
	230 aload_0 (2, 2)
	231 getfield (2, 2)
	232 org/apache/commons/math3/stat/regression/SimpleRegression.sumYY:D (2, 2)
	234 dload_2 (2, 2)
	235 dadd (2, 2)
	236 dstore (2, 2)
	237 #4 (2, 2)
	238 aload_1 (3, 1)
	239 iconst_0 (3, 1)
	240 iaload (3, 1)
	241 ifne (3, 1)
	242 79 (3, 1)
	244 iconst_1 (3, 1)
	245 newarray (3, 1)
	246 7 (3, 1)
	247 dup (3, 1)
	248 iconst_0 (3, 1)
	249 aload_0 (3, 1)
	250 getfield (3, 1)
	251 org/apache/commons/math3/stat/regression/SimpleRegression.sumYY:D (3, 1)
	253 aload_0 (3, 1)
	254 getfield (3, 1)
	255 org/apache/commons/math3/stat/regression/SimpleRegression.n:J (3, 1)
	257 lconst_1 (3, 1)
	258 lsub (3, 1)
	259 aload_0 (3, 1)
	260 getfield (3, 1)
	261 org/apache/commons/math3/stat/regression/SimpleRegression.n:J (3, 1)
	263 lmul (3, 1)
	264 l2d (3, 1)
	265 ddiv (3, 1)
	266 dastore (3, 1)
	267 astore (3, 1)
	268 #6 (3, 1)
	269 iconst_1 (3, 1)
	270 newarray (3, 1)
	271 7 (3, 1)
	272 dup (3, 1)
	273 iconst_0 (3, 1)
	274 aload_0 (3, 1)
	275 getfield (3, 1)
	276 org/apache/commons/math3/stat/regression/SimpleRegression.ybar:D (3, 1)
	278 dastore (3, 1)
	279 astore (3, 1)
	280 #7 (3, 1)
	281 new (3, 1)
	282 org/apache/commons/math3/stat/regression/RegressionResults (3, 1)
	284 dup (3, 1)
	285 aload (3, 1)
	286 #7 (3, 1)
	287 iconst_1 (3, 1)
	288 anewarray (3, 1)
	289 [D (3, 1)
	291 dup (3, 1)
	292 iconst_0 (3, 1)
	293 aload (3, 1)
	294 #6 (3, 1)
	295 aastore (3, 1)
	296 iconst_1 (3, 1)
	297 aload_0 (3, 1)
	298 getfield (3, 1)
	299 org/apache/commons/math3/stat/regression/SimpleRegression.n:J (3, 1)
	301 iconst_1 (3, 1)
	302 aload_0 (3, 1)
	303 getfield (3, 1)
	304 org/apache/commons/math3/stat/regression/SimpleRegression.sumY:D (3, 1)
	306 dload (3, 1)
	307 #4 (3, 1)
	308 dload_2 (3, 1)
	309 dadd (3, 1)
	310 aload_0 (3, 1)
	311 getfield (3, 1)
	312 org/apache/commons/math3/stat/regression/SimpleRegression.sumYY:D (3, 1)
	314 iconst_1 (3, 1)
	315 iconst_0 (3, 1)
	316 invokespecial (3, 1)
	317 org/apache/commons/math3/stat/regression/RegressionResults.<init>:([D[[DZJIDDDZZ)V (3, 1)
	319 areturn (3, 1)
	320 aload_1 (3, 1)
	321 iconst_0 (3, 1)
	322 iaload (3, 1)
	323 iconst_1 (3, 1)
	324 if_icmpne (3, 1)
	325 203 (3, 1)
	327 aload_0 (3, 1)
	328 getfield (3, 1)
	329 org/apache/commons/math3/stat/regression/SimpleRegression.sumXX:D (3, 1)
	331 aload_0 (3, 1)
	332 getfield (3, 1)
	333 org/apache/commons/math3/stat/regression/SimpleRegression.sumX:D (3, 1)
	335 aload_0 (3, 1)
	336 getfield (3, 1)
	337 org/apache/commons/math3/stat/regression/SimpleRegression.sumX:D (3, 1)
	339 dmul (3, 1)
	340 aload_0 (3, 1)
	341 getfield (3, 1)
	342 org/apache/commons/math3/stat/regression/SimpleRegression.n:J (3, 1)
	344 l2d (3, 1)
	345 ddiv (3, 1)
	346 dadd (3, 1)
	347 dstore (3, 1)
	348 #6 (3, 1)
	349 aload_0 (3, 1)
	350 getfield (3, 1)
	351 org/apache/commons/math3/stat/regression/SimpleRegression.sumXY:D (3, 1)
	353 aload_0 (3, 1)
	354 getfield (3, 1)
	355 org/apache/commons/math3/stat/regression/SimpleRegression.sumX:D (3, 1)
	357 aload_0 (3, 1)
	358 getfield (3, 1)
	359 org/apache/commons/math3/stat/regression/SimpleRegression.sumY:D (3, 1)
	361 dmul (3, 1)
	362 aload_0 (3, 1)
	363 getfield (3, 1)
	364 org/apache/commons/math3/stat/regression/SimpleRegression.n:J (3, 1)
	366 l2d (3, 1)
	367 ddiv (3, 1)
	368 dadd (3, 1)
	369 dstore (3, 1)
	370 #8 (3, 1)
	371 dconst_0 (3, 1)
	372 dload (3, 1)
	373 #4 (3, 1)
	374 dload (3, 1)
	375 #8 (3, 1)
	376 dload (3, 1)
	377 #8 (3, 1)
	378 dmul (3, 1)
	379 dload (3, 1)
	380 #6 (3, 1)
	381 ddiv (3, 1)
	382 dsub (3, 1)
	383 invokestatic (3, 1)
	384 org/apache/commons/math3/util/FastMath.max:(DD)D (3, 1)
	386 dstore (3, 1)
	387 #10 (3, 1)
	388 dload (3, 1)
	389 #10 (3, 1)
	390 aload_0 (3, 1)
	391 getfield (3, 1)
	392 org/apache/commons/math3/stat/regression/SimpleRegression.n:J (3, 1)
	394 lconst_1 (3, 1)
	395 lsub (3, 1)
	396 l2d (3, 1)
	397 ddiv (3, 1)
	398 dstore (3, 1)
	399 #12 (3, 1)
	400 dload (4, 1)
	401 #6 (4, 1)
	402 invokestatic (4, 1)
	403 java/lang/Double.isNaN:(D)Z (4, 1)
	405 ifne (4, 1)
	406 64 (4, 1)
	408 iconst_1 (4, 1)
	409 newarray (4, 1)
	410 7 (4, 1)
	411 dup (4, 1)
	412 iconst_0 (4, 1)
	413 dload (4, 1)
	414 #12 (4, 1)
	415 dload (4, 1)
	416 #6 (4, 1)
	417 ddiv (4, 1)
	418 dastore (4, 1)
	419 astore (4, 1)
	420 #14 (4, 1)
	421 iconst_1 (4, 1)
	422 newarray (4, 1)
	423 7 (4, 1)
	424 dup (4, 1)
	425 iconst_0 (4, 1)
	426 dload (4, 1)
	427 #8 (4, 1)
	428 dload (4, 1)
	429 #6 (4, 1)
	430 ddiv (4, 1)
	431 dastore (4, 1)
	432 astore (4, 1)
	433 #15 (4, 1)
	434 new (4, 1)
	435 org/apache/commons/math3/stat/regression/RegressionResults (4, 1)
	437 dup (4, 1)
	438 aload (4, 1)
	439 #15 (4, 1)
	440 iconst_1 (4, 1)
	441 anewarray (4, 1)
	442 [D (4, 1)
	444 dup (4, 1)
	445 iconst_0 (4, 1)
	446 aload (4, 1)
	447 #14 (4, 1)
	448 aastore (4, 1)
	449 iconst_1 (4, 1)
	450 aload_0 (4, 1)
	451 getfield (4, 1)
	452 org/apache/commons/math3/stat/regression/SimpleRegression.n:J (4, 1)
	454 iconst_1 (4, 1)
	455 aload_0 (4, 1)
	456 getfield (4, 1)
	457 org/apache/commons/math3/stat/regression/SimpleRegression.sumY:D (4, 1)
	459 dload (4, 1)
	460 #4 (4, 1)
	461 dload (4, 1)
	462 #10 (4, 1)
	463 iconst_0 (4, 1)
	464 iconst_0 (4, 1)
	465 invokespecial (4, 1)
	466 org/apache/commons/math3/stat/regression/RegressionResults.<init>:([D[[DZJIDDDZZ)V (4, 1)
	468 areturn (4, 1)
	469 iconst_1 (4, 2)
	470 newarray (4, 2)
	471 7 (4, 2)
	472 dup (4, 2)
	473 iconst_0 (4, 2)
	474 ldc2_w (4, 2)
	475 nan (4, 2)
	477 dastore (4, 2)
	478 astore (4, 2)
	479 #14 (4, 2)
	480 iconst_1 (4, 2)
	481 newarray (4, 2)
	482 7 (4, 2)
	483 dup (4, 2)
	484 iconst_0 (4, 2)
	485 ldc2_w (4, 2)
	486 nan (4, 2)
	488 dastore (4, 2)
	489 astore (4, 2)
	490 #15 (4, 2)
	491 new (4, 2)
	492 org/apache/commons/math3/stat/regression/RegressionResults (4, 2)
	494 dup (4, 2)
	495 aload (4, 2)
	496 #15 (4, 2)
	497 iconst_1 (4, 2)
	498 anewarray (4, 2)
	499 [D (4, 2)
	501 dup (4, 2)
	502 iconst_0 (4, 2)
	503 aload (4, 2)
	504 #14 (4, 2)
	505 aastore (4, 2)
	506 iconst_1 (4, 2)
	507 aload_0 (4, 2)
	508 getfield (4, 2)
	509 org/apache/commons/math3/stat/regression/SimpleRegression.n:J (4, 2)
	511 iconst_1 (4, 2)
	512 ldc2_w (4, 2)
	513 nan (4, 2)
	515 ldc2_w (4, 2)
	516 nan (4, 2)
	518 ldc2_w (4, 2)
	519 nan (4, 2)
	521 iconst_0 (4, 2)
	522 iconst_0 (4, 2)
	523 invokespecial (4, 2)
	524 org/apache/commons/math3/stat/regression/RegressionResults.<init>:([D[[DZJIDDDZZ)V (4, 2)
	526 areturn (4, 2)
	527 goto (1, 1)
	528 36 (1, 1)
	530 aload_1 (2, 1)
	531 iconst_0 (2, 1)
	532 iaload (2, 1)
	533 ifeq (2, 1)
	534 25 (2, 1)
	536 new (2, 1)
	537 org/apache/commons/math3/exception/OutOfRangeException (2, 1)
	539 dup (2, 1)
	540 aload_1 (2, 1)
	541 iconst_0 (2, 1)
	542 iaload (2, 1)
	543 invokestatic (2, 1)
	544 java/lang/Integer.valueOf:(I)Ljava/lang/Integer; (2, 1)
	546 iconst_0 (2, 1)
	547 invokestatic (2, 1)
	548 java/lang/Integer.valueOf:(I)Ljava/lang/Integer; (2, 1)
	550 iconst_0 (2, 1)
	551 invokestatic (2, 1)
	552 java/lang/Integer.valueOf:(I)Ljava/lang/Integer; (2, 1)
	554 invokespecial (2, 1)
	555 org/apache/commons/math3/exception/OutOfRangeException.<init>:(Ljava/lang/Number;Ljava/lang/Number;Ljava/lang/Number;)V (2, 1)
	557 athrow (2, 1)
	558 aload_0 (1, 2)
	559 invokevirtual (1, 2)
	560 org/apache/commons/math3/stat/regression/SimpleRegression.regress:()Lorg/apache/commons/math3/stat/regression/RegressionResults; (1, 2)
	562 areturn (1, 2)
	563 aconst_null (0, 0)
	564 areturn (0, 0)

