Method: <init>
	0 aload_0 (0, 0)
	1 invokespecial (0, 0)
	2 java/lang/Object.<init>:()V (0, 0)
	4 aload_0 (0, 0)
	5 aload_1 (0, 0)
	6 putfield (0, 0)
	7 org/apache/commons/math3/filter/DefaultMeasurementModel.measurementMatrix:Lorg/apache/commons/math3/linear/RealMatrix; (0, 0)
	9 aload_0 (0, 0)
	10 aload_2 (0, 0)
	11 putfield (0, 0)
	12 org/apache/commons/math3/filter/DefaultMeasurementModel.measurementNoise:Lorg/apache/commons/math3/linear/RealMatrix; (0, 0)
	14 return (0, 0)

Method: getMeasurementMatrix
	0 aload_0 (0, 0)
	1 getfield (0, 0)
	2 org/apache/commons/math3/filter/DefaultMeasurementModel.measurementMatrix:Lorg/apache/commons/math3/linear/RealMatrix; (0, 0)
	4 areturn (0, 0)

Method: getMeasurementNoise
	0 aload_0 (0, 0)
	1 getfield (0, 0)
	2 org/apache/commons/math3/filter/DefaultMeasurementModel.measurementNoise:Lorg/apache/commons/math3/linear/RealMatrix; (0, 0)
	4 areturn (0, 0)

