Method: <init>
	0 aload_0 (0, 0)
	1 invokespecial (0, 0)
	4 aload_0 (0, 0)
	5 aload_1 (0, 0)
	6 putfield (0, 0)
	9 aload_0 (0, 0)
	10 aload_2 (0, 0)
	11 putfield (0, 0)
	14 aload_0 (0, 0)
	15 aload_3 (0, 0)
	16 putfield (0, 0)
	19 aload_0 (0, 0)
	20 aload (0, 0)
	22 putfield (0, 0)
	25 aload_0 (0, 0)
	26 aload (0, 0)
	28 putfield (0, 0)
	31 return (0, 0)

Method: getStateTransitionMatrix
	0 aload_0 (0, 0)
	1 getfield (0, 0)
	4 areturn (0, 0)

Method: getControlMatrix
	0 aload_0 (0, 0)
	1 getfield (0, 0)
	4 areturn (0, 0)

Method: getProcessNoise
	0 aload_0 (0, 0)
	1 getfield (0, 0)
	4 areturn (0, 0)

Method: getInitialStateEstimate
	0 aload_0 (0, 0)
	1 getfield (0, 0)
	4 areturn (0, 0)

Method: getInitialErrorCovariance
	0 aload_0 (0, 0)
	1 getfield (0, 0)
	4 areturn (0, 0)

