Method: <init>
	0 aload_0 (0, 0)
	1 invokespecial (0, 0)
	4 aload_1 (0, 0)
	5 invokestatic (0, 0)
	8 aload_2 (0, 0)
	9 invokestatic (0, 0)
	12 aload_0 (0, 0)
	13 aload_1 (0, 0)
	14 putfield (0, 0)
	17 aload_0 (0, 0)
	18 aload_2 (0, 0)
	19 putfield (0, 0)
	22 aload_0 (0, 0)
	23 aload_0 (0, 0)
	24 getfield (0, 0)
	27 invokeinterface (0, 0)
	32 putfield (0, 0)
	35 aload_0 (0, 0)
	36 getfield (0, 0)
	39 invokestatic (0, 0)
	42 aload_0 (0, 0)
	43 aload_0 (0, 0)
	44 getfield (0, 0)
	47 invokeinterface (0, 0)
	52 putfield (0, 0)
	55 aload_0 (1, 1)
	56 getfield (1, 1)
	59 invokeinterface (1, 1)
	64 ifnonnull (1, 1)
	67 aload_0 (1, 1)
	68 new (1, 1)
	71 dup (1, 1)
	72 invokespecial (1, 1)
	75 putfield (1, 1)
	78 goto (1, 1)
	81 aload_0 (1, 2)
	82 aload_0 (1, 2)
	83 getfield (1, 2)
	86 invokeinterface (1, 2)
	91 putfield (1, 2)
	94 aload_0 (0, 1)
	95 aload_0 (0, 1)
	96 getfield (0, 1)
	99 invokeinterface (0, 1)
	104 putfield (0, 1)
	107 aload_0 (0, 1)
	108 getfield (0, 1)
	111 invokestatic (0, 1)
	114 aload_0 (0, 1)
	115 aload_0 (0, 1)
	116 getfield (0, 1)
	119 invokeinterface (0, 1)
	124 putfield (0, 1)
	127 aload_0 (0, 1)
	128 getfield (0, 1)
	131 invokeinterface (0, 1)
	136 astore_3 (0, 1)
	137 aload_3 (0, 1)
	138 invokestatic (0, 1)
	141 aload_0 (0, 1)
	142 getfield (0, 1)
	145 invokeinterface (0, 1)
	150 astore (0, 1)
	152 aload (0, 1)
	154 invokestatic (0, 1)
	157 aload_0 (1, 1)
	158 getfield (1, 1)
	161 invokeinterface (1, 1)
	166 ifnonnull (1, 1)
	169 aload_0 (1, 1)
	170 new (1, 1)
	173 dup (1, 1)
	174 aload_0 (1, 1)
	175 getfield (1, 1)
	178 invokeinterface (1, 1)
	183 invokespecial (1, 1)
	186 putfield (1, 1)
	189 goto (1, 1)
	192 aload_0 (1, 2)
	193 aload_0 (1, 2)
	194 getfield (1, 2)
	197 invokeinterface (1, 2)
	202 putfield (1, 2)
	205 aload_0 (1, 1)
	206 getfield (1, 1)
	209 invokeinterface (1, 1)
	214 aload_0 (1, 1)
	215 getfield (1, 1)
	218 invokevirtual (1, 1)
	221 if_icmpeq (1, 1)
	224 new (1, 1)
	227 dup (1, 1)
	228 aload_0 (1, 1)
	229 getfield (1, 1)
	232 invokeinterface (1, 1)
	237 aload_0 (1, 1)
	238 getfield (1, 1)
	241 invokevirtual (1, 1)
	244 invokespecial (1, 1)
	247 athrow (1, 1)
	248 aload_0 (1, 1)
	249 getfield (1, 1)
	252 invokeinterface (1, 1)
	257 ifnonnull (1, 1)
	260 aload_0 (1, 1)
	261 aload_3 (1, 1)
	262 invokeinterface (1, 1)
	267 putfield (1, 1)
	270 goto (1, 1)
	273 aload_0 (1, 2)
	274 aload_0 (1, 2)
	275 getfield (1, 2)
	278 invokeinterface (1, 2)
	283 putfield (1, 2)
	286 aload_0 (1, 1)
	287 getfield (1, 1)
	290 invokeinterface (1, 1)
	295 ifne (1, 1)
	298 new (1, 1)
	301 dup (1, 1)
	302 aload_0 (1, 1)
	303 getfield (1, 1)
	306 invokeinterface (1, 1)
	311 aload_0 (1, 1)
	312 getfield (1, 1)
	315 invokeinterface (1, 1)
	320 invokespecial (1, 1)
	323 athrow (1, 1)
	324 aload_0 (0, 1)
	325 getfield (0, 1)
	328 ifnull (0, 1)
	331 aload_0 (0, 1)
	332 getfield (0, 1)
	335 invokeinterface (0, 1)
	340 ifle (0, 1)
	343 aload_0 (0, 1)
	344 getfield (0, 1)
	347 invokeinterface (0, 1)
	352 ifle (0, 1)
	355 aload_0 (0, 1)
	356 getfield (0, 1)
	359 invokeinterface (1, 1)
	364 aload_0 (1, 1)
	365 getfield (1, 1)
	368 invokeinterface (1, 1)
	373 if_icmpeq (1, 1)
	376 new (1, 1)
	379 dup (1, 1)
	380 aload_0 (1, 1)
	381 getfield (1, 1)
	384 invokeinterface (1, 1)
	389 aload_0 (1, 1)
	390 getfield (1, 1)
	393 invokeinterface (1, 1)
	398 aload_0 (1, 1)
	399 getfield (1, 1)
	402 invokeinterface (1, 1)
	407 aload_0 (1, 1)
	408 getfield (1, 1)
	411 invokeinterface (1, 1)
	416 invokespecial (1, 1)
	419 athrow (1, 1)
	420 aload_0 (0, 1)
	421 getfield (0, 1)
	424 aload_3 (0, 1)
	425 invokestatic (0, 1)
	428 aload_0 (1, 1)
	429 getfield (1, 1)
	432 invokeinterface (1, 1)
	437 aload_0 (1, 1)
	438 getfield (1, 1)
	441 invokeinterface (1, 1)
	446 if_icmpeq (1, 1)
	449 new (1, 1)
	452 dup (1, 1)
	453 aload_0 (1, 1)
	454 getfield (1, 1)
	457 invokeinterface (1, 1)
	462 aload_0 (1, 1)
	463 getfield (1, 1)
	466 invokeinterface (1, 1)
	471 aload_0 (1, 1)
	472 getfield (1, 1)
	475 invokeinterface (1, 1)
	480 aload_0 (1, 1)
	481 getfield (1, 1)
	484 invokeinterface (1, 1)
	489 invokespecial (1, 1)
	492 athrow (1, 1)
	493 aload (1, 1)
	495 invokeinterface (1, 1)
	500 aload_0 (1, 1)
	501 getfield (1, 1)
	504 invokeinterface (1, 1)
	509 if_icmpeq (1, 1)
	512 new (1, 1)
	515 dup (1, 1)
	516 aload (1, 1)
	518 invokeinterface (1, 1)
	523 aload (1, 1)
	525 invokeinterface (1, 1)
	530 aload_0 (1, 1)
	531 getfield (1, 1)
	534 invokeinterface (1, 1)
	539 aload (1, 1)
	541 invokeinterface (1, 1)
	546 invokespecial (1, 1)
	549 athrow (1, 1)
	550 return (0, 1)

Method: getStateDimension
	0 aload_0 (0, 0)
	1 getfield (0, 0)
	4 invokevirtual (0, 0)
	7 ireturn (0, 0)

Method: getMeasurementDimension
	0 aload_0 (0, 0)
	1 getfield (0, 0)
	4 invokeinterface (0, 0)
	9 ireturn (0, 0)

Method: getStateEstimation
	0 aload_0 (0, 0)
	1 getfield (0, 0)
	4 invokevirtual (0, 0)
	7 areturn (0, 0)

Method: getStateEstimationVector
	0 aload_0 (0, 0)
	1 getfield (0, 0)
	4 invokevirtual (0, 0)
	7 areturn (0, 0)

Method: getErrorCovariance
	0 aload_0 (0, 0)
	1 getfield (0, 0)
	4 invokeinterface (0, 0)
	9 areturn (0, 0)

Method: getErrorCovarianceMatrix
	0 aload_0 (0, 0)
	1 getfield (0, 0)
	4 invokeinterface (0, 0)
	9 areturn (0, 0)

Method: predict
	0 aload_1 (0, 1)
	1 ifnull (0, 1)
	4 aload_1 (0, 1)
	5 invokevirtual (1, 1)
	8 aload_0 (1, 1)
	9 getfield (1, 1)
	12 invokeinterface (1, 1)
	17 if_icmpeq (1, 1)
	20 new (1, 1)
	23 dup (1, 1)
	24 aload_1 (1, 1)
	25 invokevirtual (1, 1)
	28 aload_0 (1, 1)
	29 getfield (1, 1)
	32 invokeinterface (1, 1)
	37 invokespecial (1, 1)
	40 athrow (1, 1)
	41 aload_0 (0, 0)
	42 aload_0 (0, 0)
	43 getfield (0, 0)
	46 aload_0 (0, 0)
	47 getfield (0, 0)
	50 invokeinterface (0, 0)
	55 putfield (0, 0)
	58 aload_1 (1, 1)
	59 ifnull (1, 1)
	62 aload_0 (1, 1)
	63 aload_0 (1, 1)
	64 getfield (1, 1)
	67 aload_0 (1, 1)
	68 getfield (1, 1)
	71 aload_1 (1, 1)
	72 invokeinterface (1, 1)
	77 invokevirtual (1, 1)
	80 putfield (1, 1)
	83 aload_0 (0, 1)
	84 aload_0 (0, 1)
	85 getfield (0, 1)
	88 aload_0 (0, 1)
	89 getfield (0, 1)
	92 invokeinterface (0, 1)
	97 aload_0 (0, 1)
	98 getfield (0, 1)
	101 invokeinterface (0, 1)
	106 aload_0 (0, 1)
	107 getfield (0, 1)
	110 invokeinterface (0, 1)
	115 invokeinterface (0, 1)
	120 putfield (0, 1)
	123 return (0, 0)

Method: correct
	0 aload_1 (0, 0)
	1 invokestatic (0, 0)
	4 aload_1 (1, 1)
	5 invokevirtual (1, 1)
	8 aload_0 (1, 1)
	9 getfield (1, 1)
	12 invokeinterface (1, 1)
	17 if_icmpeq (1, 1)
	20 new (1, 1)
	23 dup (1, 1)
	24 aload_1 (1, 1)
	25 invokevirtual (1, 1)
	28 aload_0 (1, 1)
	29 getfield (1, 1)
	32 invokeinterface (1, 1)
	37 invokespecial (1, 1)
	40 athrow (1, 1)
	41 aload_0 (0, 0)
	42 getfield (0, 0)
	45 aload_0 (0, 0)
	46 getfield (0, 0)
	49 invokeinterface (0, 0)
	54 aload_0 (0, 0)
	55 getfield (0, 0)
	58 invokeinterface (0, 0)
	63 aload_0 (0, 0)
	64 getfield (0, 0)
	67 invokeinterface (0, 0)
	72 invokeinterface (0, 0)
	77 astore_2 (0, 0)
	78 aload_1 (0, 0)
	79 aload_0 (0, 0)
	80 getfield (0, 0)
	83 aload_0 (0, 0)
	84 getfield (0, 0)
	87 invokeinterface (0, 0)
	92 invokevirtual (0, 0)
	95 astore_3 (0, 0)
	96 new (0, 4)
	99 dup (0, 4)
	100 aload_2 (0, 4)
	101 invokespecial (0, 4)
	104 invokevirtual (0, 4)
	107 aload_0 (0, 4)
	108 getfield (0, 4)
	111 aload_0 (0, 4)
	112 getfield (0, 4)
	115 invokeinterface (0, 4)
	120 invokeinterface (0, 4)
	125 invokeinterface (0, 4)
	130 invokeinterface (0, 4)
	135 astore (0, 4)
	137 aload_0 (0, 4)
	138 aload_0 (0, 4)
	139 getfield (0, 4)
	142 aload (0, 4)
	144 aload_3 (0, 4)
	145 invokeinterface (0, 4)
	150 invokevirtual (0, 4)
	153 putfield (0, 4)
	156 aload (0, 4)
	158 invokeinterface (0, 4)
	163 invokestatic (0, 4)
	166 astore (0, 4)
	168 aload_0 (0, 4)
	169 aload (0, 4)
	171 aload (0, 4)
	173 aload_0 (0, 4)
	174 getfield (0, 4)
	177 invokeinterface (0, 4)
	182 invokeinterface (0, 4)
	187 aload_0 (0, 4)
	188 getfield (0, 4)
	191 invokeinterface (0, 4)
	196 putfield (0, 4)
	199 return (0, 0)

