Method: <init>
	0 aload_0 (0, 0)
	1 invokespecial (0, 0)
	2 java/lang/Object.<init>:()V (0, 0)
	4 aload_1 (0, 0)
	5 invokestatic (0, 0)
	6 org/apache/commons/math3/util/MathUtils.checkNotNull:(Ljava/lang/Object;)V (0, 0)
	8 aload_2 (0, 0)
	9 invokestatic (0, 0)
	10 org/apache/commons/math3/util/MathUtils.checkNotNull:(Ljava/lang/Object;)V (0, 0)
	12 aload_0 (0, 0)
	13 aload_1 (0, 0)
	14 putfield (0, 0)
	15 org/apache/commons/math3/filter/KalmanFilter.processModel:Lorg/apache/commons/math3/filter/ProcessModel; (0, 0)
	17 aload_0 (0, 0)
	18 aload_2 (0, 0)
	19 putfield (0, 0)
	20 org/apache/commons/math3/filter/KalmanFilter.measurementModel:Lorg/apache/commons/math3/filter/MeasurementModel; (0, 0)
	22 aload_0 (0, 0)
	23 aload_0 (0, 0)
	24 getfield (0, 0)
	25 org/apache/commons/math3/filter/KalmanFilter.processModel:Lorg/apache/commons/math3/filter/ProcessModel; (0, 0)
	27 invokeinterface (0, 0)
	28 org/apache/commons/math3/filter/ProcessModel.transitionMatrix:Lorg/apache/commons/math3/linear/RealMatrix; (0, 0)
	30 0 (0, 0)
	32 putfield (0, 0)
	33 org/apache/commons/math3/filter/KalmanFilter.transitionMatrix:Lorg/apache/commons/math3/linear/RealMatrix; (0, 0)
	35 aload_0 (0, 0)
	36 getfield (0, 0)
	37 org/apache/commons/math3/filter/KalmanFilter.transitionMatrix:Lorg/apache/commons/math3/linear/RealMatrix; (0, 0)
	39 invokestatic (0, 0)
	40 org/apache/commons/math3/util/MathUtils.checkNotNull:(Ljava/lang/Object;)V (0, 0)
	42 aload_0 (0, 0)
	43 aload_0 (0, 0)
	44 getfield (0, 0)
	45 org/apache/commons/math3/filter/KalmanFilter.transitionMatrix:Lorg/apache/commons/math3/linear/RealMatrix; (0, 0)
	47 invokeinterface (0, 0)
	48 org/apache/commons/math3/linear/RealMatrix.transitionMatrixT:Lorg/apache/commons/math3/linear/RealMatrix; (0, 0)
	50 0 (0, 0)
	52 putfield (0, 0)
	53 org/apache/commons/math3/filter/KalmanFilter.transitionMatrixT:Lorg/apache/commons/math3/linear/RealMatrix; (0, 0)
	55 aload_0 (2, 1)
	56 getfield (2, 1)
	57 org/apache/commons/math3/filter/KalmanFilter.processModel:Lorg/apache/commons/math3/filter/ProcessModel; (2, 1)
	59 invokeinterface (2, 1)
	60 org/apache/commons/math3/filter/ProcessModel.org/apache/commons/math3/linear/Array2DRowRealMatrix (2, 1)
	62 0 (2, 1)
	64 ifnonnull (2, 1)
	65 17 (2, 1)
	67 aload_0 (2, 1)
	68 new (2, 1)
	69 org/apache/commons/math3/linear/Array2DRowRealMatrix (2, 1)
	71 dup (2, 1)
	72 invokespecial (2, 1)
	73 org/apache/commons/math3/linear/Array2DRowRealMatrix.<init>:()V (2, 1)
	75 putfield (2, 1)
	76 org/apache/commons/math3/filter/KalmanFilter.controlMatrix:Lorg/apache/commons/math3/linear/RealMatrix; (2, 1)
	78 goto (2, 1)
	79 16 (2, 1)
	81 aload_0 (2, 2)
	82 aload_0 (2, 2)
	83 getfield (2, 2)
	84 org/apache/commons/math3/filter/KalmanFilter.processModel:Lorg/apache/commons/math3/filter/ProcessModel; (2, 2)
	86 invokeinterface (2, 2)
	87 org/apache/commons/math3/filter/ProcessModel.org/apache/commons/math3/linear/Array2DRowRealMatrix (2, 2)
	89 0 (2, 2)
	91 putfield (2, 2)
	92 org/apache/commons/math3/filter/KalmanFilter.controlMatrix:Lorg/apache/commons/math3/linear/RealMatrix; (2, 2)
	94 aload_0 (1, 1)
	95 aload_0 (1, 1)
	96 getfield (1, 1)
	97 org/apache/commons/math3/filter/KalmanFilter.measurementModel:Lorg/apache/commons/math3/filter/MeasurementModel; (1, 1)
	99 invokeinterface (1, 1)
	100 org/apache/commons/math3/filter/MeasurementModel.measurementMatrix:Lorg/apache/commons/math3/linear/RealMatrix; (1, 1)
	102 0 (1, 1)
	104 putfield (1, 1)
	105 org/apache/commons/math3/filter/KalmanFilter.measurementMatrix:Lorg/apache/commons/math3/linear/RealMatrix; (1, 1)
	107 aload_0 (1, 1)
	108 getfield (1, 1)
	109 org/apache/commons/math3/filter/KalmanFilter.measurementMatrix:Lorg/apache/commons/math3/linear/RealMatrix; (1, 1)
	111 invokestatic (1, 1)
	112 org/apache/commons/math3/util/MathUtils.checkNotNull:(Ljava/lang/Object;)V (1, 1)
	114 aload_0 (1, 1)
	115 aload_0 (1, 1)
	116 getfield (1, 1)
	117 org/apache/commons/math3/filter/KalmanFilter.measurementMatrix:Lorg/apache/commons/math3/linear/RealMatrix; (1, 1)
	119 invokeinterface (1, 1)
	120 org/apache/commons/math3/linear/RealMatrix.transitionMatrixT:Lorg/apache/commons/math3/linear/RealMatrix; (1, 1)
	122 0 (1, 1)
	124 putfield (1, 1)
	125 org/apache/commons/math3/filter/KalmanFilter.measurementMatrixT:Lorg/apache/commons/math3/linear/RealMatrix; (1, 1)
	127 aload_0 (1, 1)
	128 getfield (1, 1)
	129 org/apache/commons/math3/filter/KalmanFilter.processModel:Lorg/apache/commons/math3/filter/ProcessModel; (1, 1)
	131 invokeinterface (1, 1)
	132 org/apache/commons/math3/filter/ProcessModel.getMeasurementNoise:()Lorg/apache/commons/math3/linear/RealMatrix; (1, 1)
	134 0 (1, 1)
	136 astore_3 (1, 1)
	137 aload_3 (1, 1)
	138 invokestatic (1, 1)
	139 org/apache/commons/math3/util/MathUtils.checkNotNull:(Ljava/lang/Object;)V (1, 1)
	141 aload_0 (1, 1)
	142 getfield (1, 1)
	143 org/apache/commons/math3/filter/KalmanFilter.measurementModel:Lorg/apache/commons/math3/filter/MeasurementModel; (1, 1)
	145 invokeinterface (1, 1)
	146 org/apache/commons/math3/filter/MeasurementModel.getInitialStateEstimate:()Lorg/apache/commons/math3/linear/RealVector; (1, 1)
	148 0 (1, 1)
	150 astore (1, 1)
	151 #4 (1, 1)
	152 aload (1, 1)
	153 #4 (1, 1)
	154 invokestatic (1, 1)
	155 org/apache/commons/math3/util/MathUtils.checkNotNull:(Ljava/lang/Object;)V (1, 1)
	157 aload_0 (2, 1)
	158 getfield (2, 1)
	159 org/apache/commons/math3/filter/KalmanFilter.processModel:Lorg/apache/commons/math3/filter/ProcessModel; (2, 1)
	161 invokeinterface (2, 1)
	162 org/apache/commons/math3/filter/ProcessModel.org/apache/commons/math3/linear/ArrayRealVector (2, 1)
	164 0 (2, 1)
	166 ifnonnull (2, 1)
	167 26 (2, 1)
	169 aload_0 (2, 1)
	170 new (2, 1)
	171 org/apache/commons/math3/linear/ArrayRealVector (2, 1)
	173 dup (2, 1)
	174 aload_0 (2, 1)
	175 getfield (2, 1)
	176 org/apache/commons/math3/filter/KalmanFilter.transitionMatrix:Lorg/apache/commons/math3/linear/RealMatrix; (2, 1)
	178 invokeinterface (2, 1)
	179 org/apache/commons/math3/linear/RealMatrix.<init>:(I)V (2, 1)
	181 0 (2, 1)
	183 invokespecial (2, 1)
	184 org/apache/commons/math3/linear/ArrayRealVector.<init>:(I)V (2, 1)
	186 putfield (2, 1)
	187 org/apache/commons/math3/filter/KalmanFilter.stateEstimation:Lorg/apache/commons/math3/linear/RealVector; (2, 1)
	189 goto (2, 1)
	190 16 (2, 1)
	192 aload_0 (2, 2)
	193 aload_0 (2, 2)
	194 getfield (2, 2)
	195 org/apache/commons/math3/filter/KalmanFilter.processModel:Lorg/apache/commons/math3/filter/ProcessModel; (2, 2)
	197 invokeinterface (2, 2)
	198 org/apache/commons/math3/filter/ProcessModel.org/apache/commons/math3/linear/ArrayRealVector (2, 2)
	200 0 (2, 2)
	202 putfield (2, 2)
	203 org/apache/commons/math3/filter/KalmanFilter.stateEstimation:Lorg/apache/commons/math3/linear/RealVector; (2, 2)
	205 aload_0 (2, 1)
	206 getfield (2, 1)
	207 org/apache/commons/math3/filter/KalmanFilter.transitionMatrix:Lorg/apache/commons/math3/linear/RealMatrix; (2, 1)
	209 invokeinterface (2, 1)
	210 org/apache/commons/math3/linear/RealMatrix.<init>:(I)V (2, 1)
	212 0 (2, 1)
	214 aload_0 (2, 1)
	215 getfield (2, 1)
	216 org/apache/commons/math3/filter/KalmanFilter.stateEstimation:Lorg/apache/commons/math3/linear/RealVector; (2, 1)
	218 invokevirtual (2, 1)
	219 org/apache/commons/math3/linear/RealVector.getDimension:()I (2, 1)
	221 if_icmpeq (2, 1)
	222 27 (2, 1)
	224 new (2, 1)
	225 org/apache/commons/math3/exception/DimensionMismatchException (2, 1)
	227 dup (2, 1)
	228 aload_0 (2, 1)
	229 getfield (2, 1)
	230 org/apache/commons/math3/filter/KalmanFilter.transitionMatrix:Lorg/apache/commons/math3/linear/RealMatrix; (2, 1)
	232 invokeinterface (2, 1)
	233 org/apache/commons/math3/linear/RealMatrix.<init>:(I)V (2, 1)
	235 0 (2, 1)
	237 aload_0 (2, 1)
	238 getfield (2, 1)
	239 org/apache/commons/math3/filter/KalmanFilter.stateEstimation:Lorg/apache/commons/math3/linear/RealVector; (2, 1)
	241 invokevirtual (2, 1)
	242 org/apache/commons/math3/linear/RealVector.getDimension:()I (2, 1)
	244 invokespecial (2, 1)
	245 org/apache/commons/math3/exception/DimensionMismatchException.<init>:(II)V (2, 1)
	247 athrow (2, 1)
	248 aload_0 (2, 1)
	249 getfield (2, 1)
	250 org/apache/commons/math3/filter/KalmanFilter.processModel:Lorg/apache/commons/math3/filter/ProcessModel; (2, 1)
	252 invokeinterface (2, 1)
	253 org/apache/commons/math3/filter/ProcessModel.copy:()Lorg/apache/commons/math3/linear/RealMatrix; (2, 1)
	255 0 (2, 1)
	257 ifnonnull (2, 1)
	258 16 (2, 1)
	260 aload_0 (2, 1)
	261 aload_3 (2, 1)
	262 invokeinterface (2, 1)
	263 org/apache/commons/math3/linear/RealMatrix.errorCovariance:Lorg/apache/commons/math3/linear/RealMatrix; (2, 1)
	265 0 (2, 1)
	267 putfield (2, 1)
	268 org/apache/commons/math3/filter/KalmanFilter.errorCovariance:Lorg/apache/commons/math3/linear/RealMatrix; (2, 1)
	270 goto (2, 1)
	271 16 (2, 1)
	273 aload_0 (2, 2)
	274 aload_0 (2, 2)
	275 getfield (2, 2)
	276 org/apache/commons/math3/filter/KalmanFilter.processModel:Lorg/apache/commons/math3/filter/ProcessModel; (2, 2)
	278 invokeinterface (2, 2)
	279 org/apache/commons/math3/filter/ProcessModel.copy:()Lorg/apache/commons/math3/linear/RealMatrix; (2, 2)
	281 0 (2, 2)
	283 putfield (2, 2)
	284 org/apache/commons/math3/filter/KalmanFilter.errorCovariance:Lorg/apache/commons/math3/linear/RealMatrix; (2, 2)
	286 aload_0 (2, 1)
	287 getfield (2, 1)
	288 org/apache/commons/math3/filter/KalmanFilter.transitionMatrix:Lorg/apache/commons/math3/linear/RealMatrix; (2, 1)
	290 invokeinterface (2, 1)
	291 org/apache/commons/math3/linear/RealMatrix.org/apache/commons/math3/linear/NonSquareMatrixException (2, 1)
	293 0 (2, 1)
	295 ifne (2, 1)
	296 29 (2, 1)
	298 new (2, 1)
	299 org/apache/commons/math3/linear/NonSquareMatrixException (2, 1)
	301 dup (2, 1)
	302 aload_0 (2, 1)
	303 getfield (2, 1)
	304 org/apache/commons/math3/filter/KalmanFilter.transitionMatrix:Lorg/apache/commons/math3/linear/RealMatrix; (2, 1)
	306 invokeinterface (2, 1)
	307 org/apache/commons/math3/linear/RealMatrix.org/apache/commons/math3/linear/MatrixDimensionMismatchException (2, 1)
	309 0 (2, 1)
	311 aload_0 (2, 1)
	312 getfield (2, 1)
	313 org/apache/commons/math3/filter/KalmanFilter.transitionMatrix:Lorg/apache/commons/math3/linear/RealMatrix; (2, 1)
	315 invokeinterface (2, 1)
	316 org/apache/commons/math3/linear/RealMatrix.<init>:(I)V (2, 1)
	318 0 (2, 1)
	320 invokespecial (2, 1)
	321 org/apache/commons/math3/linear/NonSquareMatrixException.<init>:(II)V (2, 1)
	323 athrow (2, 1)
	324 aload_0 (1, 1)
	325 getfield (1, 1)
	326 org/apache/commons/math3/filter/KalmanFilter.controlMatrix:Lorg/apache/commons/math3/linear/RealMatrix; (1, 1)
	328 ifnull (1, 1)
	329 92 (1, 1)
	331 aload_0 (1, 1)
	332 getfield (1, 1)
	333 org/apache/commons/math3/filter/KalmanFilter.controlMatrix:Lorg/apache/commons/math3/linear/RealMatrix; (1, 1)
	335 invokeinterface (1, 1)
	336 org/apache/commons/math3/linear/RealMatrix.org/apache/commons/math3/linear/MatrixDimensionMismatchException (1, 1)
	338 0 (1, 1)
	340 ifle (1, 1)
	341 80 (1, 1)
	343 aload_0 (1, 1)
	344 getfield (1, 1)
	345 org/apache/commons/math3/filter/KalmanFilter.controlMatrix:Lorg/apache/commons/math3/linear/RealMatrix; (1, 1)
	347 invokeinterface (1, 1)
	348 org/apache/commons/math3/linear/RealMatrix.<init>:(I)V (1, 1)
	350 0 (1, 1)
	352 ifle (1, 1)
	353 68 (1, 1)
	355 aload_0 (1, 1)
	356 getfield (1, 1)
	357 org/apache/commons/math3/filter/KalmanFilter.controlMatrix:Lorg/apache/commons/math3/linear/RealMatrix; (1, 1)
	359 invokeinterface (1, 1)
	360 org/apache/commons/math3/linear/RealMatrix.org/apache/commons/math3/linear/MatrixDimensionMismatchException (1, 1)
	362 0 (1, 1)
	364 aload_0 (1, 1)
	365 getfield (1, 1)
	366 org/apache/commons/math3/filter/KalmanFilter.transitionMatrix:Lorg/apache/commons/math3/linear/RealMatrix; (1, 1)
	368 invokeinterface (1, 1)
	369 org/apache/commons/math3/linear/RealMatrix.org/apache/commons/math3/linear/MatrixDimensionMismatchException (1, 1)
	371 0 (1, 1)
	373 if_icmpeq (1, 1)
	374 47 (1, 1)
	376 new (1, 1)
	377 org/apache/commons/math3/linear/MatrixDimensionMismatchException (1, 1)
	379 dup (1, 1)
	380 aload_0 (1, 1)
	381 getfield (1, 1)
	382 org/apache/commons/math3/filter/KalmanFilter.controlMatrix:Lorg/apache/commons/math3/linear/RealMatrix; (1, 1)
	384 invokeinterface (1, 1)
	385 org/apache/commons/math3/linear/RealMatrix.org/apache/commons/math3/linear/MatrixDimensionMismatchException (1, 1)
	387 0 (1, 1)
	389 aload_0 (1, 1)
	390 getfield (1, 1)
	391 org/apache/commons/math3/filter/KalmanFilter.controlMatrix:Lorg/apache/commons/math3/linear/RealMatrix; (1, 1)
	393 invokeinterface (1, 1)
	394 org/apache/commons/math3/linear/RealMatrix.<init>:(I)V (1, 1)
	396 0 (1, 1)
	398 aload_0 (1, 1)
	399 getfield (1, 1)
	400 org/apache/commons/math3/filter/KalmanFilter.transitionMatrix:Lorg/apache/commons/math3/linear/RealMatrix; (1, 1)
	402 invokeinterface (1, 1)
	403 org/apache/commons/math3/linear/RealMatrix.org/apache/commons/math3/linear/MatrixDimensionMismatchException (1, 1)
	405 0 (1, 1)
	407 aload_0 (1, 1)
	408 getfield (1, 1)
	409 org/apache/commons/math3/filter/KalmanFilter.controlMatrix:Lorg/apache/commons/math3/linear/RealMatrix; (1, 1)
	411 invokeinterface (1, 1)
	412 org/apache/commons/math3/linear/RealMatrix.<init>:(I)V (1, 1)
	414 0 (1, 1)
	416 invokespecial (1, 1)
	417 org/apache/commons/math3/linear/MatrixDimensionMismatchException.<init>:(IIII)V (1, 1)
	419 athrow (1, 1)
	420 aload_0 (1, 1)
	421 getfield (1, 1)
	422 org/apache/commons/math3/filter/KalmanFilter.transitionMatrix:Lorg/apache/commons/math3/linear/RealMatrix; (1, 1)
	424 aload_3 (1, 1)
	425 invokestatic (1, 1)
	426 org/apache/commons/math3/linear/MatrixUtils.checkAdditionCompatible:(Lorg/apache/commons/math3/linear/AnyMatrix;Lorg/apache/commons/math3/linear/AnyMatrix;)V (1, 1)
	428 aload_0 (2, 1)
	429 getfield (2, 1)
	430 org/apache/commons/math3/filter/KalmanFilter.measurementMatrix:Lorg/apache/commons/math3/linear/RealMatrix; (2, 1)
	432 invokeinterface (2, 1)
	433 org/apache/commons/math3/linear/RealMatrix.<init>:(I)V (2, 1)
	435 0 (2, 1)
	437 aload_0 (2, 1)
	438 getfield (2, 1)
	439 org/apache/commons/math3/filter/KalmanFilter.transitionMatrix:Lorg/apache/commons/math3/linear/RealMatrix; (2, 1)
	441 invokeinterface (2, 1)
	442 org/apache/commons/math3/linear/RealMatrix.org/apache/commons/math3/linear/MatrixDimensionMismatchException (2, 1)
	444 0 (2, 1)
	446 if_icmpeq (2, 1)
	447 47 (2, 1)
	449 new (2, 1)
	450 org/apache/commons/math3/linear/MatrixDimensionMismatchException (2, 1)
	452 dup (2, 1)
	453 aload_0 (2, 1)
	454 getfield (2, 1)
	455 org/apache/commons/math3/filter/KalmanFilter.measurementMatrix:Lorg/apache/commons/math3/linear/RealMatrix; (2, 1)
	457 invokeinterface (2, 1)
	458 org/apache/commons/math3/linear/RealMatrix.org/apache/commons/math3/linear/MatrixDimensionMismatchException (2, 1)
	460 0 (2, 1)
	462 aload_0 (2, 1)
	463 getfield (2, 1)
	464 org/apache/commons/math3/filter/KalmanFilter.measurementMatrix:Lorg/apache/commons/math3/linear/RealMatrix; (2, 1)
	466 invokeinterface (2, 1)
	467 org/apache/commons/math3/linear/RealMatrix.<init>:(I)V (2, 1)
	469 0 (2, 1)
	471 aload_0 (2, 1)
	472 getfield (2, 1)
	473 org/apache/commons/math3/filter/KalmanFilter.measurementMatrix:Lorg/apache/commons/math3/linear/RealMatrix; (2, 1)
	475 invokeinterface (2, 1)
	476 org/apache/commons/math3/linear/RealMatrix.org/apache/commons/math3/linear/MatrixDimensionMismatchException (2, 1)
	478 0 (2, 1)
	480 aload_0 (2, 1)
	481 getfield (2, 1)
	482 org/apache/commons/math3/filter/KalmanFilter.transitionMatrix:Lorg/apache/commons/math3/linear/RealMatrix; (2, 1)
	484 invokeinterface (2, 1)
	485 org/apache/commons/math3/linear/RealMatrix.org/apache/commons/math3/linear/MatrixDimensionMismatchException (2, 1)
	487 0 (2, 1)
	489 invokespecial (2, 1)
	490 org/apache/commons/math3/linear/MatrixDimensionMismatchException.<init>:(IIII)V (2, 1)
	492 athrow (2, 1)
	493 aload (2, 1)
	494 #4 (2, 1)
	495 invokeinterface (2, 1)
	496 org/apache/commons/math3/linear/RealMatrix.org/apache/commons/math3/linear/MatrixDimensionMismatchException (2, 1)
	498 0 (2, 1)
	500 aload_0 (2, 1)
	501 getfield (2, 1)
	502 org/apache/commons/math3/filter/KalmanFilter.measurementMatrix:Lorg/apache/commons/math3/linear/RealMatrix; (2, 1)
	504 invokeinterface (2, 1)
	505 org/apache/commons/math3/linear/RealMatrix.org/apache/commons/math3/linear/MatrixDimensionMismatchException (2, 1)
	507 0 (2, 1)
	509 if_icmpeq (2, 1)
	510 41 (2, 1)
	512 new (2, 1)
	513 org/apache/commons/math3/linear/MatrixDimensionMismatchException (2, 1)
	515 dup (2, 1)
	516 aload (2, 1)
	517 #4 (2, 1)
	518 invokeinterface (2, 1)
	519 org/apache/commons/math3/linear/RealMatrix.org/apache/commons/math3/linear/MatrixDimensionMismatchException (2, 1)
	521 0 (2, 1)
	523 aload (2, 1)
	524 #4 (2, 1)
	525 invokeinterface (2, 1)
	526 org/apache/commons/math3/linear/RealMatrix.<init>:(I)V (2, 1)
	528 0 (2, 1)
	530 aload_0 (2, 1)
	531 getfield (2, 1)
	532 org/apache/commons/math3/filter/KalmanFilter.measurementMatrix:Lorg/apache/commons/math3/linear/RealMatrix; (2, 1)
	534 invokeinterface (2, 1)
	535 org/apache/commons/math3/linear/RealMatrix.org/apache/commons/math3/linear/MatrixDimensionMismatchException (2, 1)
	537 0 (2, 1)
	539 aload (2, 1)
	540 #4 (2, 1)
	541 invokeinterface (2, 1)
	542 org/apache/commons/math3/linear/RealMatrix.<init>:(I)V (2, 1)
	544 0 (2, 1)
	546 invokespecial (2, 1)
	547 org/apache/commons/math3/linear/MatrixDimensionMismatchException.<init>:(IIII)V (2, 1)
	549 athrow (2, 1)
	550 return (0, 0)

Method: getStateDimension
	0 aload_0 (0, 0)
	1 getfield (0, 0)
	2 org/apache/commons/math3/filter/KalmanFilter.stateEstimation:Lorg/apache/commons/math3/linear/RealVector; (0, 0)
	4 invokevirtual (0, 0)
	5 org/apache/commons/math3/linear/RealVector.getDimension:()I (0, 0)
	7 ireturn (0, 0)

Method: getMeasurementDimension
	0 aload_0 (0, 0)
	1 getfield (0, 0)
	2 org/apache/commons/math3/filter/KalmanFilter.measurementMatrix:Lorg/apache/commons/math3/linear/RealMatrix; (0, 0)
	4 invokeinterface (0, 0)
	5 org/apache/commons/math3/linear/RealMatrix.org/apache/commons/math3/linear/MatrixDimensionMismatchException (0, 0)
	7 0 (0, 0)
	9 ireturn (0, 0)

Method: getStateEstimation
	0 aload_0 (0, 0)
	1 getfield (0, 0)
	2 org/apache/commons/math3/filter/KalmanFilter.stateEstimation:Lorg/apache/commons/math3/linear/RealVector; (0, 0)
	4 invokevirtual (0, 0)
	5 org/apache/commons/math3/linear/RealVector.toArray:()[D (0, 0)
	7 areturn (0, 0)

Method: getStateEstimationVector
	0 aload_0 (0, 0)
	1 getfield (0, 0)
	2 org/apache/commons/math3/filter/KalmanFilter.stateEstimation:Lorg/apache/commons/math3/linear/RealVector; (0, 0)
	4 invokevirtual (0, 0)
	5 org/apache/commons/math3/linear/RealVector.copy:()Lorg/apache/commons/math3/linear/RealVector; (0, 0)
	7 areturn (0, 0)

Method: getErrorCovariance
	0 aload_0 (0, 0)
	1 getfield (0, 0)
	2 org/apache/commons/math3/filter/KalmanFilter.errorCovariance:Lorg/apache/commons/math3/linear/RealMatrix; (0, 0)
	4 invokeinterface (0, 0)
	5 org/apache/commons/math3/linear/RealMatrix.org/apache/commons/math3/linear/RealVector (0, 0)
	7 0 (0, 0)
	9 areturn (0, 0)

Method: getErrorCovarianceMatrix
	0 aload_0 (0, 0)
	1 getfield (0, 0)
	2 org/apache/commons/math3/filter/KalmanFilter.errorCovariance:Lorg/apache/commons/math3/linear/RealMatrix; (0, 0)
	4 invokeinterface (0, 0)
	5 org/apache/commons/math3/linear/RealMatrix.errorCovariance:Lorg/apache/commons/math3/linear/RealMatrix; (0, 0)
	7 0 (0, 0)
	9 areturn (0, 0)

Method: predict
	0 aload_1 (0, 1)
	1 ifnull (0, 1)
	2 40 (0, 1)
	4 aload_1 (0, 1)
	5 invokevirtual (0, 1)
	6 org/apache/commons/math3/linear/RealVector.getDimension:()I (0, 1)
	8 aload_0 (0, 1)
	9 getfield (0, 1)
	10 org/apache/commons/math3/filter/KalmanFilter.controlMatrix:Lorg/apache/commons/math3/linear/RealMatrix; (0, 1)
	12 invokeinterface (0, 1)
	13 org/apache/commons/math3/linear/RealMatrix.<init>:(I)V (0, 1)
	15 0 (0, 1)
	17 if_icmpeq (0, 1)
	18 24 (0, 1)
	20 new (0, 1)
	21 org/apache/commons/math3/exception/DimensionMismatchException (0, 1)
	23 dup (0, 1)
	24 aload_1 (0, 1)
	25 invokevirtual (0, 1)
	26 org/apache/commons/math3/linear/RealVector.getDimension:()I (0, 1)
	28 aload_0 (0, 1)
	29 getfield (0, 1)
	30 org/apache/commons/math3/filter/KalmanFilter.controlMatrix:Lorg/apache/commons/math3/linear/RealMatrix; (0, 1)
	32 invokeinterface (0, 1)
	33 org/apache/commons/math3/linear/RealMatrix.<init>:(I)V (0, 1)
	35 0 (0, 1)
	37 invokespecial (0, 1)
	38 org/apache/commons/math3/exception/DimensionMismatchException.<init>:(II)V (0, 1)
	40 athrow (0, 1)
	41 aload_0 (0, 1)
	42 aload_0 (0, 1)
	43 getfield (0, 1)
	44 org/apache/commons/math3/filter/KalmanFilter.transitionMatrix:Lorg/apache/commons/math3/linear/RealMatrix; (0, 1)
	46 aload_0 (0, 1)
	47 getfield (0, 1)
	48 org/apache/commons/math3/filter/KalmanFilter.stateEstimation:Lorg/apache/commons/math3/linear/RealVector; (0, 1)
	50 invokeinterface (0, 1)
	51 org/apache/commons/math3/linear/RealMatrix.add:(Lorg/apache/commons/math3/linear/RealVector;)Lorg/apache/commons/math3/linear/RealVector; (0, 1)
	53 0 (0, 1)
	55 putfield (0, 1)
	56 org/apache/commons/math3/filter/KalmanFilter.stateEstimation:Lorg/apache/commons/math3/linear/RealVector; (0, 1)
	58 aload_1 (1, 1)
	59 ifnull (1, 1)
	60 24 (1, 1)
	62 aload_0 (1, 1)
	63 aload_0 (1, 1)
	64 getfield (1, 1)
	65 org/apache/commons/math3/filter/KalmanFilter.stateEstimation:Lorg/apache/commons/math3/linear/RealVector; (1, 1)
	67 aload_0 (1, 1)
	68 getfield (1, 1)
	69 org/apache/commons/math3/filter/KalmanFilter.controlMatrix:Lorg/apache/commons/math3/linear/RealMatrix; (1, 1)
	71 aload_1 (1, 1)
	72 invokeinterface (1, 1)
	73 org/apache/commons/math3/linear/RealMatrix.add:(Lorg/apache/commons/math3/linear/RealVector;)Lorg/apache/commons/math3/linear/RealVector; (1, 1)
	75 0 (1, 1)
	77 invokevirtual (1, 1)
	78 org/apache/commons/math3/linear/RealVector.add:(Lorg/apache/commons/math3/linear/RealVector;)Lorg/apache/commons/math3/linear/RealVector; (1, 1)
	80 putfield (1, 1)
	81 org/apache/commons/math3/filter/KalmanFilter.stateEstimation:Lorg/apache/commons/math3/linear/RealVector; (1, 1)
	83 aload_0 (0, 1)
	84 aload_0 (0, 1)
	85 getfield (0, 1)
	86 org/apache/commons/math3/filter/KalmanFilter.transitionMatrix:Lorg/apache/commons/math3/linear/RealMatrix; (0, 1)
	88 aload_0 (0, 1)
	89 getfield (0, 1)
	90 org/apache/commons/math3/filter/KalmanFilter.errorCovariance:Lorg/apache/commons/math3/linear/RealMatrix; (0, 1)
	92 invokeinterface (0, 1)
	93 org/apache/commons/math3/linear/RealMatrix.add:(Lorg/apache/commons/math3/linear/RealMatrix;)Lorg/apache/commons/math3/linear/RealMatrix; (0, 1)
	95 0 (0, 1)
	97 aload_0 (0, 1)
	98 getfield (0, 1)
	99 org/apache/commons/math3/filter/KalmanFilter.transitionMatrixT:Lorg/apache/commons/math3/linear/RealMatrix; (0, 1)
	101 invokeinterface (0, 1)
	102 org/apache/commons/math3/linear/RealMatrix.add:(Lorg/apache/commons/math3/linear/RealMatrix;)Lorg/apache/commons/math3/linear/RealMatrix; (0, 1)
	104 0 (0, 1)
	106 aload_0 (0, 1)
	107 getfield (0, 1)
	108 org/apache/commons/math3/filter/KalmanFilter.processModel:Lorg/apache/commons/math3/filter/ProcessModel; (0, 1)
	110 invokeinterface (0, 1)
	111 org/apache/commons/math3/filter/ProcessModel.getMeasurementNoise:()Lorg/apache/commons/math3/linear/RealMatrix; (0, 1)
	113 0 (0, 1)
	115 invokeinterface (0, 1)
	116 org/apache/commons/math3/linear/RealMatrix.correct:(Lorg/apache/commons/math3/linear/RealVector;)V (0, 1)
	118 0 (0, 1)
	120 putfield (0, 1)
	121 org/apache/commons/math3/filter/KalmanFilter.errorCovariance:Lorg/apache/commons/math3/linear/RealMatrix; (0, 1)
	123 return (0, 1)

Method: correct
	0 aload_1 (0, 0)
	1 invokestatic (0, 0)
	2 org/apache/commons/math3/util/MathUtils.checkNotNull:(Ljava/lang/Object;)V (0, 0)
	4 aload_1 (1, 1)
	5 invokevirtual (1, 1)
	6 org/apache/commons/math3/linear/RealVector.getDimension:()I (1, 1)
	8 aload_0 (1, 1)
	9 getfield (1, 1)
	10 org/apache/commons/math3/filter/KalmanFilter.measurementMatrix:Lorg/apache/commons/math3/linear/RealMatrix; (1, 1)
	12 invokeinterface (1, 1)
	13 org/apache/commons/math3/linear/RealMatrix.org/apache/commons/math3/linear/MatrixDimensionMismatchException (1, 1)
	15 0 (1, 1)
	17 if_icmpeq (1, 1)
	18 24 (1, 1)
	20 new (1, 1)
	21 org/apache/commons/math3/exception/DimensionMismatchException (1, 1)
	23 dup (1, 1)
	24 aload_1 (1, 1)
	25 invokevirtual (1, 1)
	26 org/apache/commons/math3/linear/RealVector.getDimension:()I (1, 1)
	28 aload_0 (1, 1)
	29 getfield (1, 1)
	30 org/apache/commons/math3/filter/KalmanFilter.measurementMatrix:Lorg/apache/commons/math3/linear/RealMatrix; (1, 1)
	32 invokeinterface (1, 1)
	33 org/apache/commons/math3/linear/RealMatrix.org/apache/commons/math3/linear/MatrixDimensionMismatchException (1, 1)
	35 0 (1, 1)
	37 invokespecial (1, 1)
	38 org/apache/commons/math3/exception/DimensionMismatchException.<init>:(II)V (1, 1)
	40 athrow (1, 1)
	41 aload_0 (0, 0)
	42 getfield (0, 0)
	43 org/apache/commons/math3/filter/KalmanFilter.measurementMatrix:Lorg/apache/commons/math3/linear/RealMatrix; (0, 0)
	45 aload_0 (0, 0)
	46 getfield (0, 0)
	47 org/apache/commons/math3/filter/KalmanFilter.errorCovariance:Lorg/apache/commons/math3/linear/RealMatrix; (0, 0)
	49 invokeinterface (0, 0)
	50 org/apache/commons/math3/linear/RealMatrix.add:(Lorg/apache/commons/math3/linear/RealMatrix;)Lorg/apache/commons/math3/linear/RealMatrix; (0, 0)
	52 0 (0, 0)
	54 aload_0 (0, 0)
	55 getfield (0, 0)
	56 org/apache/commons/math3/filter/KalmanFilter.measurementMatrixT:Lorg/apache/commons/math3/linear/RealMatrix; (0, 0)
	58 invokeinterface (0, 0)
	59 org/apache/commons/math3/linear/RealMatrix.add:(Lorg/apache/commons/math3/linear/RealMatrix;)Lorg/apache/commons/math3/linear/RealMatrix; (0, 0)
	61 0 (0, 0)
	63 aload_0 (0, 0)
	64 getfield (0, 0)
	65 org/apache/commons/math3/filter/KalmanFilter.measurementModel:Lorg/apache/commons/math3/filter/MeasurementModel; (0, 0)
	67 invokeinterface (0, 0)
	68 org/apache/commons/math3/filter/MeasurementModel.getInitialStateEstimate:()Lorg/apache/commons/math3/linear/RealVector; (0, 0)
	70 0 (0, 0)
	72 invokeinterface (0, 0)
	73 org/apache/commons/math3/linear/RealMatrix.correct:(Lorg/apache/commons/math3/linear/RealVector;)V (0, 0)
	75 0 (0, 0)
	77 astore_2 (0, 0)
	78 aload_1 (0, 0)
	79 aload_0 (0, 0)
	80 getfield (0, 0)
	81 org/apache/commons/math3/filter/KalmanFilter.measurementMatrix:Lorg/apache/commons/math3/linear/RealMatrix; (0, 0)
	83 aload_0 (0, 0)
	84 getfield (0, 0)
	85 org/apache/commons/math3/filter/KalmanFilter.stateEstimation:Lorg/apache/commons/math3/linear/RealVector; (0, 0)
	87 invokeinterface (0, 0)
	88 org/apache/commons/math3/linear/RealMatrix.add:(Lorg/apache/commons/math3/linear/RealVector;)Lorg/apache/commons/math3/linear/RealVector; (0, 0)
	90 0 (0, 0)
	92 invokevirtual (0, 0)
	93 org/apache/commons/math3/linear/RealVector.subtract:(Lorg/apache/commons/math3/linear/RealVector;)Lorg/apache/commons/math3/linear/RealVector; (0, 0)
	95 astore_3 (0, 0)
	96 new (0, 4)
	97 org/apache/commons/math3/linear/CholeskyDecomposition (0, 4)
	99 dup (0, 4)
	100 aload_2 (0, 4)
	101 invokespecial (0, 4)
	102 org/apache/commons/math3/linear/CholeskyDecomposition.<init>:(Lorg/apache/commons/math3/linear/RealMatrix;)V (0, 4)
	104 invokevirtual (0, 4)
	105 org/apache/commons/math3/linear/CholeskyDecomposition.getSolver:()Lorg/apache/commons/math3/linear/DecompositionSolver; (0, 4)
	107 aload_0 (0, 4)
	108 getfield (0, 4)
	109 org/apache/commons/math3/filter/KalmanFilter.measurementMatrix:Lorg/apache/commons/math3/linear/RealMatrix; (0, 4)
	111 aload_0 (0, 4)
	112 getfield (0, 4)
	113 org/apache/commons/math3/filter/KalmanFilter.errorCovariance:Lorg/apache/commons/math3/linear/RealMatrix; (0, 4)
	115 invokeinterface (0, 4)
	116 org/apache/commons/math3/linear/RealMatrix.transitionMatrixT:Lorg/apache/commons/math3/linear/RealMatrix; (0, 4)
	118 0 (0, 4)
	120 invokeinterface (0, 4)
	121 org/apache/commons/math3/linear/RealMatrix.add:(Lorg/apache/commons/math3/linear/RealMatrix;)Lorg/apache/commons/math3/linear/RealMatrix; (0, 4)
	123 0 (0, 4)
	125 invokeinterface (0, 4)
	126 org/apache/commons/math3/linear/DecompositionSolver.createRealIdentityMatrix:(I)Lorg/apache/commons/math3/linear/RealMatrix; (0, 4)
	128 0 (0, 4)
	130 invokeinterface (0, 4)
	131 org/apache/commons/math3/linear/RealMatrix.transitionMatrixT:Lorg/apache/commons/math3/linear/RealMatrix; (0, 4)
	133 0 (0, 4)
	135 astore (0, 4)
	136 #4 (0, 4)
	137 aload_0 (0, 4)
	138 aload_0 (0, 4)
	139 getfield (0, 4)
	140 org/apache/commons/math3/filter/KalmanFilter.stateEstimation:Lorg/apache/commons/math3/linear/RealVector; (0, 4)
	142 aload (0, 4)
	143 #4 (0, 4)
	144 aload_3 (0, 4)
	145 invokeinterface (0, 4)
	146 org/apache/commons/math3/linear/RealMatrix.add:(Lorg/apache/commons/math3/linear/RealVector;)Lorg/apache/commons/math3/linear/RealVector; (0, 4)
	148 0 (0, 4)
	150 invokevirtual (0, 4)
	151 org/apache/commons/math3/linear/RealVector.add:(Lorg/apache/commons/math3/linear/RealVector;)Lorg/apache/commons/math3/linear/RealVector; (0, 4)
	153 putfield (0, 4)
	154 org/apache/commons/math3/filter/KalmanFilter.stateEstimation:Lorg/apache/commons/math3/linear/RealVector; (0, 4)
	156 aload (0, 4)
	157 #4 (0, 4)
	158 invokeinterface (0, 4)
	159 org/apache/commons/math3/linear/RealMatrix.org/apache/commons/math3/linear/MatrixDimensionMismatchException (0, 4)
	161 0 (0, 4)
	163 invokestatic (0, 4)
	164 org/apache/commons/math3/linear/MatrixUtils.createRealIdentityMatrix:(I)Lorg/apache/commons/math3/linear/RealMatrix; (0, 4)
	166 astore (0, 4)
	167 #5 (0, 4)
	168 aload_0 (0, 4)
	169 aload (0, 4)
	170 #5 (0, 4)
	171 aload (0, 4)
	172 #4 (0, 4)
	173 aload_0 (0, 4)
	174 getfield (0, 4)
	175 org/apache/commons/math3/filter/KalmanFilter.measurementMatrix:Lorg/apache/commons/math3/linear/RealMatrix; (0, 4)
	177 invokeinterface (0, 4)
	178 org/apache/commons/math3/linear/RealMatrix.add:(Lorg/apache/commons/math3/linear/RealMatrix;)Lorg/apache/commons/math3/linear/RealMatrix; (0, 4)
	180 0 (0, 4)
	182 invokeinterface (0, 4)
	183 org/apache/commons/math3/linear/RealMatrix.org/apache/commons/math3/filter/KalmanFilter (0, 4)
	185 0 (0, 4)
	187 aload_0 (0, 4)
	188 getfield (0, 4)
	189 org/apache/commons/math3/filter/KalmanFilter.errorCovariance:Lorg/apache/commons/math3/linear/RealMatrix; (0, 4)
	191 invokeinterface (0, 4)
	192 org/apache/commons/math3/linear/RealMatrix.add:(Lorg/apache/commons/math3/linear/RealMatrix;)Lorg/apache/commons/math3/linear/RealMatrix; (0, 4)
	194 0 (0, 4)
	196 putfield (0, 4)
	197 org/apache/commons/math3/filter/KalmanFilter.errorCovariance:Lorg/apache/commons/math3/linear/RealMatrix; (0, 4)
	199 return (0, 4)

