Method: <init>
	0 aload_0 (0, 0)
	1 invokespecial (0, 0)
	2 java/lang/Object.<init>:()V (0, 0)
	4 aload_0 (0, 0)
	5 aload_1 (0, 0)
	6 putfield (0, 0)
	7 org/apache/commons/math3/ode/events/EventState.handler:Lorg/apache/commons/math3/ode/events/EventHandler; (0, 0)
	9 aload_0 (0, 0)
	10 dload_2 (0, 0)
	11 putfield (0, 0)
	12 org/apache/commons/math3/ode/events/EventState.maxCheckInterval:D (0, 0)
	14 aload_0 (0, 0)
	15 dload (0, 0)
	16 #4 (0, 0)
	17 invokestatic (0, 0)
	18 org/apache/commons/math3/util/FastMath.abs:(D)D (0, 0)
	20 putfield (0, 0)
	21 org/apache/commons/math3/ode/events/EventState.convergence:D (0, 0)
	23 aload_0 (0, 0)
	24 iload (0, 0)
	25 #6 (0, 0)
	26 putfield (0, 0)
	27 org/apache/commons/math3/ode/events/EventState.maxIterationCount:I (0, 0)
	29 aload_0 (0, 0)
	30 aload (0, 0)
	31 #7 (0, 0)
	32 putfield (0, 0)
	33 org/apache/commons/math3/ode/events/EventState.solver:Lorg/apache/commons/math3/analysis/solvers/UnivariateSolver; (0, 0)
	35 aload_0 (0, 0)
	36 aconst_null (0, 0)
	37 putfield (0, 0)
	38 org/apache/commons/math3/ode/events/EventState.expandable:Lorg/apache/commons/math3/ode/ExpandableStatefulODE; (0, 0)
	40 aload_0 (0, 0)
	41 ldc2_w (0, 0)
	42 nan (0, 0)
	44 putfield (0, 0)
	45 org/apache/commons/math3/ode/events/EventState.t0:D (0, 0)
	47 aload_0 (0, 0)
	48 ldc2_w (0, 0)
	49 nan (0, 0)
	51 putfield (0, 0)
	52 org/apache/commons/math3/ode/events/EventState.g0:D (0, 0)
	54 aload_0 (0, 0)
	55 iconst_1 (0, 0)
	56 putfield (0, 0)
	57 org/apache/commons/math3/ode/events/EventState.g0Positive:Z (0, 0)
	59 aload_0 (0, 0)
	60 iconst_0 (0, 0)
	61 putfield (0, 0)
	62 org/apache/commons/math3/ode/events/EventState.pendingEvent:Z (0, 0)
	64 aload_0 (0, 0)
	65 ldc2_w (0, 0)
	66 nan (0, 0)
	68 putfield (0, 0)
	69 org/apache/commons/math3/ode/events/EventState.pendingEventTime:D (0, 0)
	71 aload_0 (0, 0)
	72 ldc2_w (0, 0)
	73 nan (0, 0)
	75 putfield (0, 0)
	76 org/apache/commons/math3/ode/events/EventState.previousEventTime:D (0, 0)
	78 aload_0 (0, 0)
	79 iconst_1 (0, 0)
	80 putfield (0, 0)
	81 org/apache/commons/math3/ode/events/EventState.increasing:Z (0, 0)
	83 aload_0 (0, 0)
	84 getstatic (0, 0)
	85 org/apache/commons/math3/ode/events/EventHandler$Action.CONTINUE:Lorg/apache/commons/math3/ode/events/EventHandler$Action; (0, 0)
	87 putfield (0, 0)
	88 org/apache/commons/math3/ode/events/EventState.nextAction:Lorg/apache/commons/math3/ode/events/EventHandler$Action; (0, 0)
	90 return (0, 0)

Method: getEventHandler
	0 aload_0 (0, 0)
	1 getfield (0, 0)
	2 org/apache/commons/math3/ode/events/EventState.handler:Lorg/apache/commons/math3/ode/events/EventHandler; (0, 0)
	4 areturn (0, 0)

Method: setExpandable
	0 aload_0 (0, 0)
	1 aload_1 (0, 0)
	2 putfield (0, 0)
	3 org/apache/commons/math3/ode/events/EventState.expandable:Lorg/apache/commons/math3/ode/ExpandableStatefulODE; (0, 0)
	5 return (0, 0)

Method: getMaxCheckInterval
	0 aload_0 (0, 0)
	1 getfield (0, 0)
	2 org/apache/commons/math3/ode/events/EventState.maxCheckInterval:D (0, 0)
	4 dreturn (0, 0)

Method: getConvergence
	0 aload_0 (0, 0)
	1 getfield (0, 0)
	2 org/apache/commons/math3/ode/events/EventState.convergence:D (0, 0)
	4 dreturn (0, 0)

Method: getMaxIterationCount
	0 aload_0 (0, 0)
	1 getfield (0, 0)
	2 org/apache/commons/math3/ode/events/EventState.maxIterationCount:I (0, 0)
	4 ireturn (0, 0)

Method: reinitializeBegin
	0 aload_0 (0, 0)
	1 aload_1 (0, 0)
	2 invokeinterface (0, 0)
	3 org/apache/commons/math3/ode/sampling/StepInterpolator.setInterpolatedTime:(D)V (0, 0)
	5 0 (0, 0)
	7 putfield (0, 0)
	8 org/apache/commons/math3/ode/events/EventState.t0:D (0, 0)
	10 aload_1 (0, 0)
	11 aload_0 (0, 0)
	12 getfield (0, 0)
	13 org/apache/commons/math3/ode/events/EventState.t0:D (0, 0)
	15 invokeinterface (0, 0)
	16 org/apache/commons/math3/ode/sampling/StepInterpolator.org/apache/commons/math3/ode/events/EventHandler (0, 0)
	18 0 (0, 0)
	20 aload_0 (0, 0)
	21 aload_0 (0, 0)
	22 getfield (0, 0)
	23 org/apache/commons/math3/ode/events/EventState.handler:Lorg/apache/commons/math3/ode/events/EventHandler; (0, 0)
	25 aload_0 (0, 0)
	26 getfield (0, 0)
	27 org/apache/commons/math3/ode/events/EventState.t0:D (0, 0)
	29 aload_0 (0, 0)
	30 aload_1 (0, 0)
	31 invokespecial (0, 0)
	32 org/apache/commons/math3/ode/events/EventState.getCompleteState:(Lorg/apache/commons/math3/ode/sampling/StepInterpolator;)[D (0, 0)
	34 invokeinterface (0, 0)
	35 org/apache/commons/math3/ode/events/EventHandler.org/apache/commons/math3/analysis/solvers/UnivariateSolver (0, 0)
	37 0 (0, 0)
	39 putfield (0, 0)
	40 org/apache/commons/math3/ode/events/EventState.g0:D (0, 0)
	42 aload_0 (1, 1)
	43 getfield (1, 1)
	44 org/apache/commons/math3/ode/events/EventState.g0:D (1, 1)
	46 dconst_0 (1, 1)
	47 dcmpl (1, 1)
	48 ifne (1, 1)
	49 73 (1, 1)
	51 aload_0 (3, 4)
	52 getfield (3, 4)
	53 org/apache/commons/math3/ode/events/EventState.solver:Lorg/apache/commons/math3/analysis/solvers/UnivariateSolver; (3, 4)
	55 invokeinterface (3, 4)
	56 org/apache/commons/math3/analysis/solvers/UnivariateSolver.getRelativeAccuracy:()D (3, 4)
	58 0 (3, 4)
	60 aload_0 (3, 4)
	61 getfield (3, 4)
	62 org/apache/commons/math3/ode/events/EventState.solver:Lorg/apache/commons/math3/analysis/solvers/UnivariateSolver; (3, 4)
	64 invokeinterface (3, 4)
	65 org/apache/commons/math3/analysis/solvers/UnivariateSolver.max:(DD)D (3, 4)
	67 0 (3, 4)
	69 aload_0 (3, 4)
	70 getfield (3, 4)
	71 org/apache/commons/math3/ode/events/EventState.t0:D (3, 4)
	73 dmul (3, 4)
	74 invokestatic (3, 4)
	75 org/apache/commons/math3/util/FastMath.abs:(D)D (3, 4)
	77 invokestatic (3, 4)
	78 org/apache/commons/math3/util/FastMath.max:(DD)D (3, 4)
	80 dstore_2 (3, 4)
	81 aload_0 (3, 4)
	82 getfield (3, 4)
	83 org/apache/commons/math3/ode/events/EventState.t0:D (3, 4)
	85 ldc2_w (3, 4)
	86 0.5 (3, 4)
	88 dload_2 (3, 4)
	89 dmul (3, 4)
	90 dadd (3, 4)
	91 dstore (3, 4)
	92 #4 (3, 4)
	93 aload_1 (3, 4)
	94 dload (3, 4)
	95 #4 (3, 4)
	96 invokeinterface (3, 4)
	97 org/apache/commons/math3/ode/sampling/StepInterpolator.org/apache/commons/math3/ode/events/EventHandler (3, 4)
	99 0 (3, 4)
	101 aload_0 (3, 4)
	102 aload_0 (3, 4)
	103 getfield (3, 4)
	104 org/apache/commons/math3/ode/events/EventState.handler:Lorg/apache/commons/math3/ode/events/EventHandler; (3, 4)
	106 dload (3, 4)
	107 #4 (3, 4)
	108 aload_0 (3, 4)
	109 aload_1 (3, 4)
	110 invokespecial (3, 4)
	111 org/apache/commons/math3/ode/events/EventState.getCompleteState:(Lorg/apache/commons/math3/ode/sampling/StepInterpolator;)[D (3, 4)
	113 invokeinterface (3, 4)
	114 org/apache/commons/math3/ode/events/EventHandler.org/apache/commons/math3/analysis/solvers/UnivariateSolver (3, 4)
	116 0 (3, 4)
	118 putfield (3, 4)
	119 org/apache/commons/math3/ode/events/EventState.g0:D (3, 4)
	121 aload_0 (0, 0)
	122 aload_0 (0, 0)
	123 getfield (0, 0)
	124 org/apache/commons/math3/ode/events/EventState.g0:D (0, 0)
	126 dconst_0 (0, 0)
	127 dcmpl (0, 0)
	128 iflt (0, 0)
	129 7 (0, 0)
	131 iconst_1 (0, 0)
	132 goto (0, 0)
	133 4 (0, 0)
	135 iconst_0 (0, 0)
	136 putfield (0, 0)
	137 org/apache/commons/math3/ode/events/EventState.g0Positive:Z (0, 0)
	139 return (0, 0)

Method: getCompleteState
	0 aload_0 (0, 0)
	1 getfield (0, 0)
	2 org/apache/commons/math3/ode/events/EventState.expandable:Lorg/apache/commons/math3/ode/ExpandableStatefulODE; (0, 0)
	4 invokevirtual (0, 0)
	5 org/apache/commons/math3/ode/ExpandableStatefulODE.getTotalDimension:()I (0, 0)
	7 newarray (0, 0)
	8 7 (0, 0)
	9 astore_2 (0, 0)
	10 aload_0 (0, 0)
	11 getfield (0, 0)
	12 org/apache/commons/math3/ode/events/EventState.expandable:Lorg/apache/commons/math3/ode/ExpandableStatefulODE; (0, 0)
	14 invokevirtual (0, 0)
	15 org/apache/commons/math3/ode/ExpandableStatefulODE.getPrimaryMapper:()Lorg/apache/commons/math3/ode/EquationsMapper; (0, 0)
	17 aload_1 (0, 0)
	18 invokeinterface (0, 0)
	19 org/apache/commons/math3/ode/sampling/StepInterpolator.org/apache/commons/math3/ode/EquationsMapper (0, 0)
	21 0 (0, 0)
	23 aload_2 (0, 0)
	24 invokevirtual (0, 0)
	25 org/apache/commons/math3/ode/EquationsMapper.insertEquationData:([D[D)V (0, 0)
	27 iconst_0 (0, 0)
	28 istore_3 (0, 0)
	29 aload_0 (1, 4)
	30 getfield (1, 4)
	31 org/apache/commons/math3/ode/events/EventState.expandable:Lorg/apache/commons/math3/ode/ExpandableStatefulODE; (1, 4)
	33 invokevirtual (1, 4)
	34 org/apache/commons/math3/ode/ExpandableStatefulODE.getSecondaryMappers:()[Lorg/apache/commons/math3/ode/EquationsMapper; (1, 4)
	36 astore (1, 4)
	37 #4 (1, 4)
	38 aload (1, 4)
	39 #4 (1, 4)
	40 arraylength (1, 4)
	41 istore (1, 4)
	42 #5 (1, 4)
	43 iconst_0 (1, 4)
	44 istore (1, 4)
	45 #6 (1, 4)
	46 iload (1, 4)
	47 #6 (1, 4)
	48 iload (1, 4)
	49 #5 (1, 4)
	50 if_icmpge (1, 4)
	51 32 (1, 4)
	53 aload (1, 4)
	54 #4 (1, 4)
	55 iload (1, 4)
	56 #6 (1, 4)
	57 aaload (1, 4)
	58 astore (1, 4)
	59 #7 (1, 4)
	60 aload (1, 4)
	61 #7 (1, 4)
	62 aload_1 (1, 4)
	63 iload_3 (1, 4)
	64 iinc (1, 4)
	65 #3 (1, 4)
	66 -71 (1, 4)
	67 invokeinterface (1, 4)
	68 org/apache/commons/math3/ode/sampling/StepInterpolator.isForward:()Z (1, 4)
	70 0 (1, 4)
	72 aload_2 (1, 4)
	73 invokevirtual (1, 4)
	74 org/apache/commons/math3/ode/EquationsMapper.insertEquationData:([D[D)V (1, 4)
	76 iinc (1, 4)
	77 #6 (1, 4)
	78 -89 (1, 4)
	79 goto (1, 4)
	80 -33 (1, 4)
	82 aload_2 (0, 0)
	83 areturn (0, 0)

Method: evaluateStep
	0 aload_0 (1, 4)
	1 aload_1 (1, 4)
	2 invokeinterface (1, 4)
	3 org/apache/commons/math3/ode/sampling/StepInterpolator.forward:Z (1, 4)
	5 0 (1, 4)
	7 putfield (1, 4)
	8 org/apache/commons/math3/ode/events/EventState.forward:Z (1, 4)
	10 aload_1 (1, 4)
	11 invokeinterface (1, 4)
	12 org/apache/commons/math3/ode/sampling/StepInterpolator.ceil:(D)D (1, 4)
	14 0 (1, 4)
	16 dstore_2 (1, 4)
	17 dload_2 (1, 4)
	18 aload_0 (1, 4)
	19 getfield (1, 4)
	20 org/apache/commons/math3/ode/events/EventState.t0:D (1, 4)
	22 dsub (1, 4)
	23 dstore (1, 4)
	24 #4 (1, 4)
	25 dload (2, 1)
	26 #4 (2, 1)
	27 invokestatic (2, 1)
	28 org/apache/commons/math3/util/FastMath.abs:(D)D (2, 1)
	30 aload_0 (2, 1)
	31 getfield (2, 1)
	32 org/apache/commons/math3/ode/events/EventState.convergence:D (2, 1)
	34 dcmpg (2, 1)
	35 ifge (2, 1)
	36 5 (2, 1)
	38 iconst_0 (2, 1)
	39 ireturn (2, 1)
	40 iconst_1 (1, 4)
	41 dload (1, 4)
	42 #4 (1, 4)
	43 invokestatic (1, 4)
	44 org/apache/commons/math3/util/FastMath.abs:(D)D (1, 4)
	46 aload_0 (1, 4)
	47 getfield (1, 4)
	48 org/apache/commons/math3/ode/events/EventState.maxCheckInterval:D (1, 4)
	50 ddiv (1, 4)
	51 invokestatic (1, 4)
	52 org/apache/commons/math3/util/FastMath.ceil:(D)D (1, 4)
	54 d2i (1, 4)
	55 invokestatic (1, 4)
	56 org/apache/commons/math3/util/FastMath.max:(II)I (1, 4)
	58 istore (1, 4)
	59 #6 (1, 4)
	60 dload (1, 4)
	61 #4 (1, 4)
	62 iload (1, 4)
	63 #6 (1, 4)
	64 i2d (1, 4)
	65 ddiv (1, 4)
	66 dstore (1, 4)
	67 #7 (1, 4)
	68 new (1, 4)
	69 org/apache/commons/math3/ode/events/EventState$1 (1, 4)
	71 dup (1, 4)
	72 aload_0 (1, 4)
	73 aload_1 (1, 4)
	74 invokespecial (1, 4)
	75 org/apache/commons/math3/ode/events/EventState$1.<init>:(Lorg/apache/commons/math3/ode/events/EventState;Lorg/apache/commons/math3/ode/sampling/StepInterpolator;)V (1, 4)
	77 astore (1, 4)
	78 #9 (1, 4)
	79 aload_0 (1, 4)
	80 getfield (1, 4)
	81 org/apache/commons/math3/ode/events/EventState.t0:D (1, 4)
	83 dstore (1, 4)
	84 #10 (1, 4)
	85 aload_0 (1, 4)
	86 getfield (1, 4)
	87 org/apache/commons/math3/ode/events/EventState.g0:D (1, 4)
	89 dstore (1, 4)
	90 #12 (1, 4)
	91 iconst_0 (2, 4)
	92 istore (2, 4)
	93 #14 (2, 4)
	94 iload (2, 4)
	95 #14 (2, 4)
	96 iload (2, 4)
	97 #6 (2, 4)
	98 if_icmpge (2, 4)
	99 537 (2, 4)
	101 iload (2, 4)
	102 #14 (2, 4)
	103 iload (2, 4)
	104 #6 (2, 4)
	105 iconst_1 (2, 4)
	106 isub (2, 4)
	107 if_icmpne (2, 4)
	108 7 (2, 4)
	110 dload_2 (2, 4)
	111 goto (2, 4)
	112 16 (2, 4)
	114 aload_0 (2, 4)
	115 getfield (2, 4)
	116 org/apache/commons/math3/ode/events/EventState.t0:D (2, 4)
	118 iload (2, 4)
	119 #14 (2, 4)
	120 iconst_1 (2, 4)
	121 iadd (2, 4)
	122 i2d (2, 4)
	123 dload (2, 4)
	124 #7 (2, 4)
	125 dmul (2, 4)
	126 dadd (2, 4)
	127 dstore (2, 4)
	128 #15 (2, 4)
	129 aload_1 (2, 4)
	130 dload (2, 4)
	131 #15 (2, 4)
	132 invokeinterface (2, 4)
	133 org/apache/commons/math3/ode/sampling/StepInterpolator.org/apache/commons/math3/ode/events/EventHandler (2, 4)
	135 0 (2, 4)
	137 aload_0 (2, 4)
	138 getfield (2, 4)
	139 org/apache/commons/math3/ode/events/EventState.handler:Lorg/apache/commons/math3/ode/events/EventHandler; (2, 4)
	141 dload (2, 4)
	142 #15 (2, 4)
	143 aload_0 (2, 4)
	144 aload_1 (2, 4)
	145 invokespecial (2, 4)
	146 org/apache/commons/math3/ode/events/EventState.getCompleteState:(Lorg/apache/commons/math3/ode/sampling/StepInterpolator;)[D (2, 4)
	148 invokeinterface (2, 4)
	149 org/apache/commons/math3/ode/events/EventHandler.org/apache/commons/math3/analysis/solvers/UnivariateSolver (2, 4)
	151 0 (2, 4)
	153 dstore (2, 4)
	154 #17 (2, 4)
	155 aload_0 (3, 1)
	156 getfield (3, 1)
	157 org/apache/commons/math3/ode/events/EventState.g0Positive:Z (3, 1)
	159 dload (3, 1)
	160 #17 (3, 1)
	161 dconst_0 (3, 1)
	162 dcmpl (3, 1)
	163 iflt (3, 1)
	164 7 (3, 1)
	166 iconst_1 (3, 1)
	167 goto (3, 1)
	168 4 (3, 1)
	170 iconst_0 (3, 1)
	171 ixor (3, 1)
	172 ifeq (3, 1)
	173 449 (3, 1)
	175 aload_0 (3, 1)
	176 dload (3, 1)
	177 #17 (3, 1)
	178 dload (3, 1)
	179 #12 (3, 1)
	180 dcmpl (3, 1)
	181 iflt (3, 1)
	182 7 (3, 1)
	184 iconst_1 (3, 1)
	185 goto (3, 1)
	186 4 (3, 1)
	188 iconst_0 (3, 1)
	189 putfield (3, 1)
	190 org/apache/commons/math3/ode/events/EventState.increasing:Z (3, 1)
	192 aload_0 (4, 1)
	193 getfield (4, 1)
	194 org/apache/commons/math3/ode/events/EventState.solver:Lorg/apache/commons/math3/analysis/solvers/UnivariateSolver; (4, 1)
	196 instanceof (4, 1)
	197 org/apache/commons/math3/analysis/solvers/BracketedUnivariateSolver (4, 1)
	199 ifeq (4, 1)
	200 67 (4, 1)
	202 aload_0 (4, 1)
	203 getfield (4, 1)
	204 org/apache/commons/math3/ode/events/EventState.solver:Lorg/apache/commons/math3/analysis/solvers/UnivariateSolver; (4, 1)
	206 checkcast (4, 1)
	207 org/apache/commons/math3/analysis/solvers/BracketedUnivariateSolver (4, 1)
	209 astore (4, 1)
	210 #21 (4, 1)
	211 aload_0 (5, 4)
	212 getfield (5, 4)
	213 org/apache/commons/math3/ode/events/EventState.forward:Z (5, 4)
	215 ifeq (5, 4)
	216 26 (5, 4)
	218 aload (5, 4)
	219 #21 (5, 4)
	220 aload_0 (5, 4)
	221 getfield (5, 4)
	222 org/apache/commons/math3/ode/events/EventState.maxIterationCount:I (5, 4)
	224 aload (5, 4)
	225 #9 (5, 4)
	226 dload (5, 4)
	227 #10 (5, 4)
	228 dload (5, 4)
	229 #15 (5, 4)
	230 getstatic (5, 4)
	231 org/apache/commons/math3/analysis/solvers/AllowedSolution.RIGHT_SIDE:Lorg/apache/commons/math3/analysis/solvers/AllowedSolution; (5, 4)
	233 invokeinterface (5, 4)
	234 org/apache/commons/math3/analysis/solvers/BracketedUnivariateSolver.LEFT_SIDE:Lorg/apache/commons/math3/analysis/solvers/AllowedSolution; (5, 4)
	236 0 (5, 4)
	238 goto (5, 4)
	239 23 (5, 4)
	241 aload (5, 4)
	242 #21 (5, 4)
	243 aload_0 (5, 4)
	244 getfield (5, 4)
	245 org/apache/commons/math3/ode/events/EventState.maxIterationCount:I (5, 4)
	247 aload (5, 4)
	248 #9 (5, 4)
	249 dload (5, 4)
	250 #15 (5, 4)
	251 dload (5, 4)
	252 #10 (5, 4)
	253 getstatic (5, 4)
	254 org/apache/commons/math3/analysis/solvers/AllowedSolution.LEFT_SIDE:Lorg/apache/commons/math3/analysis/solvers/AllowedSolution; (5, 4)
	256 invokeinterface (5, 4)
	257 org/apache/commons/math3/analysis/solvers/BracketedUnivariateSolver.LEFT_SIDE:Lorg/apache/commons/math3/analysis/solvers/AllowedSolution; (5, 4)
	259 0 (5, 4)
	261 dstore (5, 4)
	262 #19 (5, 4)
	263 goto (6, 2)
	264 144 (6, 2)
	266 aload_0 (7, 4)
	267 getfield (7, 4)
	268 org/apache/commons/math3/ode/events/EventState.forward:Z (7, 4)
	270 ifeq (7, 4)
	271 25 (7, 4)
	273 aload_0 (7, 4)
	274 getfield (7, 4)
	275 org/apache/commons/math3/ode/events/EventState.solver:Lorg/apache/commons/math3/analysis/solvers/UnivariateSolver; (7, 4)
	277 aload_0 (7, 4)
	278 getfield (7, 4)
	279 org/apache/commons/math3/ode/events/EventState.maxIterationCount:I (7, 4)
	281 aload (7, 4)
	282 #9 (7, 4)
	283 dload (7, 4)
	284 #10 (7, 4)
	285 dload (7, 4)
	286 #15 (7, 4)
	287 invokeinterface (7, 4)
	288 org/apache/commons/math3/analysis/solvers/UnivariateSolver.getEvaluations:()I (7, 4)
	290 0 (7, 4)
	292 goto (7, 4)
	293 22 (7, 4)
	295 aload_0 (7, 4)
	296 getfield (7, 4)
	297 org/apache/commons/math3/ode/events/EventState.solver:Lorg/apache/commons/math3/analysis/solvers/UnivariateSolver; (7, 4)
	299 aload_0 (7, 4)
	300 getfield (7, 4)
	301 org/apache/commons/math3/ode/events/EventState.maxIterationCount:I (7, 4)
	303 aload (7, 4)
	304 #9 (7, 4)
	305 dload (7, 4)
	306 #15 (7, 4)
	307 dload (7, 4)
	308 #10 (7, 4)
	309 invokeinterface (7, 4)
	310 org/apache/commons/math3/analysis/solvers/UnivariateSolver.getEvaluations:()I (7, 4)
	312 0 (7, 4)
	314 dstore (7, 4)
	315 #21 (7, 4)
	316 aload_0 (7, 4)
	317 getfield (7, 4)
	318 org/apache/commons/math3/ode/events/EventState.maxIterationCount:I (7, 4)
	320 aload_0 (7, 4)
	321 getfield (7, 4)
	322 org/apache/commons/math3/ode/events/EventState.solver:Lorg/apache/commons/math3/analysis/solvers/UnivariateSolver; (7, 4)
	324 invokeinterface (7, 4)
	325 org/apache/commons/math3/analysis/solvers/UnivariateSolver.org/apache/commons/math3/analysis/solvers/PegasusSolver (7, 4)
	327 0 (7, 4)
	329 isub (7, 4)
	330 istore (7, 4)
	331 #23 (7, 4)
	332 new (7, 4)
	333 org/apache/commons/math3/analysis/solvers/PegasusSolver (7, 4)
	335 dup (7, 4)
	336 aload_0 (7, 4)
	337 getfield (7, 4)
	338 org/apache/commons/math3/ode/events/EventState.solver:Lorg/apache/commons/math3/analysis/solvers/UnivariateSolver; (7, 4)
	340 invokeinterface (7, 4)
	341 org/apache/commons/math3/analysis/solvers/UnivariateSolver.max:(DD)D (7, 4)
	343 0 (7, 4)
	345 aload_0 (7, 4)
	346 getfield (7, 4)
	347 org/apache/commons/math3/ode/events/EventState.solver:Lorg/apache/commons/math3/analysis/solvers/UnivariateSolver; (7, 4)
	349 invokeinterface (7, 4)
	350 org/apache/commons/math3/analysis/solvers/UnivariateSolver.getRelativeAccuracy:()D (7, 4)
	352 0 (7, 4)
	354 invokespecial (7, 4)
	355 org/apache/commons/math3/analysis/solvers/PegasusSolver.<init>:(DD)V (7, 4)
	357 astore (7, 4)
	358 #24 (7, 4)
	359 aload_0 (8, 4)
	360 getfield (8, 4)
	361 org/apache/commons/math3/ode/events/EventState.forward:Z (8, 4)
	363 ifeq (8, 4)
	364 24 (8, 4)
	366 iload (8, 4)
	367 #23 (8, 4)
	368 aload (8, 4)
	369 #9 (8, 4)
	370 aload (8, 4)
	371 #24 (8, 4)
	372 dload (8, 4)
	373 #21 (8, 4)
	374 dload (8, 4)
	375 #10 (8, 4)
	376 dload (8, 4)
	377 #15 (8, 4)
	378 getstatic (8, 4)
	379 org/apache/commons/math3/analysis/solvers/AllowedSolution.RIGHT_SIDE:Lorg/apache/commons/math3/analysis/solvers/AllowedSolution; (8, 4)
	381 invokestatic (9, 4)
	382 org/apache/commons/math3/analysis/solvers/UnivariateSolverUtils.forceSide:(ILorg/apache/commons/math3/analysis/UnivariateFunction;Lorg/apache/commons/math3/analysis/solvers/BracketedUnivariateSolver;DDDLorg/apache/commons/math3/analysis/solvers/AllowedSolution;)D (9, 4)
	384 goto (9, 4)
	385 21 (9, 4)
	387 iload (9, 4)
	388 #23 (9, 4)
	389 aload (9, 4)
	390 #9 (9, 4)
	391 aload (9, 4)
	392 #24 (9, 4)
	393 dload (9, 4)
	394 #21 (9, 4)
	395 dload (9, 4)
	396 #15 (9, 4)
	397 dload (9, 4)
	398 #10 (9, 4)
	399 getstatic (9, 4)
	400 org/apache/commons/math3/analysis/solvers/AllowedSolution.LEFT_SIDE:Lorg/apache/commons/math3/analysis/solvers/AllowedSolution; (9, 4)
	402 invokestatic (10, 4)
	403 org/apache/commons/math3/analysis/solvers/UnivariateSolverUtils.forceSide:(ILorg/apache/commons/math3/analysis/UnivariateFunction;Lorg/apache/commons/math3/analysis/solvers/BracketedUnivariateSolver;DDDLorg/apache/commons/math3/analysis/solvers/AllowedSolution;)D (10, 4)
	405 dstore (10, 4)
	406 #19 (10, 4)
	407 aload_0 (4, 1)
	408 getfield (4, 1)
	409 org/apache/commons/math3/ode/events/EventState.previousEventTime:D (4, 1)
	411 invokestatic (4, 1)
	412 java/lang/Double.isNaN:(D)Z (4, 1)
	414 ifne (4, 1)
	415 155 (4, 1)
	417 dload (4, 1)
	418 #19 (4, 1)
	419 dload (4, 1)
	420 #10 (4, 1)
	421 dsub (4, 1)
	422 invokestatic (4, 1)
	423 org/apache/commons/math3/util/FastMath.abs:(D)D (4, 1)
	425 aload_0 (4, 1)
	426 getfield (4, 1)
	427 org/apache/commons/math3/ode/events/EventState.convergence:D (4, 1)
	429 dcmpg (4, 1)
	430 ifgt (4, 1)
	431 139 (4, 1)
	433 dload (4, 1)
	434 #19 (4, 1)
	435 aload_0 (4, 1)
	436 getfield (4, 1)
	437 org/apache/commons/math3/ode/events/EventState.previousEventTime:D (4, 1)
	439 dsub (4, 1)
	440 invokestatic (4, 1)
	441 org/apache/commons/math3/util/FastMath.abs:(D)D (4, 1)
	443 aload_0 (4, 1)
	444 getfield (4, 1)
	445 org/apache/commons/math3/ode/events/EventState.convergence:D (4, 1)
	447 dcmpg (4, 1)
	448 ifgt (4, 1)
	449 121 (4, 1)
	451 aload_0 (5, 4)
	452 getfield (5, 4)
	453 org/apache/commons/math3/ode/events/EventState.forward:Z (5, 4)
	455 ifeq (5, 4)
	456 13 (5, 4)
	458 dload (5, 4)
	459 #10 (5, 4)
	460 aload_0 (5, 4)
	461 getfield (5, 4)
	462 org/apache/commons/math3/ode/events/EventState.convergence:D (5, 4)
	464 dadd (5, 4)
	465 goto (5, 4)
	466 10 (5, 4)
	468 dload (5, 4)
	469 #10 (5, 4)
	470 aload_0 (5, 4)
	471 getfield (5, 4)
	472 org/apache/commons/math3/ode/events/EventState.convergence:D (5, 4)
	474 dsub (5, 4)
	475 dstore (5, 4)
	476 #10 (5, 4)
	477 aload (5, 4)
	478 #9 (5, 4)
	479 dload (5, 4)
	480 #10 (5, 4)
	481 invokeinterface (5, 4)
	482 org/apache/commons/math3/analysis/UnivariateFunction.org/apache/commons/math3/ode/events/EventState$LocalMaxCountExceededException (5, 4)
	484 0 (5, 4)
	486 dstore (5, 4)
	487 #12 (5, 4)
	488 aload_0 (6, 3)
	489 getfield (6, 3)
	490 org/apache/commons/math3/ode/events/EventState.g0Positive:Z (6, 3)
	492 dload (6, 3)
	493 #12 (6, 3)
	494 dconst_0 (6, 3)
	495 dcmpl (6, 3)
	496 iflt (6, 3)
	497 7 (6, 3)
	499 iconst_1 (6, 3)
	500 goto (6, 3)
	501 4 (6, 3)
	503 iconst_0 (6, 3)
	504 ixor (6, 3)
	505 ifeq (6, 3)
	506 24 (6, 3)
	508 aload_0 (6, 3)
	509 getfield (6, 3)
	510 org/apache/commons/math3/ode/events/EventState.forward:Z (6, 3)
	512 dload (6, 3)
	513 #10 (6, 3)
	514 dload (6, 3)
	515 #15 (6, 3)
	516 dcmpl (6, 3)
	517 iflt (6, 3)
	518 7 (6, 3)
	520 iconst_1 (6, 3)
	521 goto (6, 3)
	522 4 (6, 3)
	524 iconst_0 (6, 3)
	525 ixor (6, 3)
	526 ifne (6, 3)
	527 -75 (6, 3)
	529 aload_0 (7, 1)
	530 getfield (7, 1)
	531 org/apache/commons/math3/ode/events/EventState.forward:Z (7, 1)
	533 dload (7, 1)
	534 #10 (7, 1)
	535 dload (7, 1)
	536 #15 (7, 1)
	537 dcmpl (7, 1)
	538 iflt (7, 1)
	539 7 (7, 1)
	541 iconst_1 (7, 1)
	542 goto (7, 1)
	543 4 (7, 1)
	545 iconst_0 (7, 1)
	546 ixor (7, 1)
	547 ifeq (7, 1)
	548 9 (7, 1)
	550 iinc (7, 1)
	551 #14 (7, 1)
	552 -89 (7, 1)
	553 goto (7, 1)
	554 65 (7, 1)
	556 aload_0 (10, 4)
	557 dload (10, 4)
	558 #19 (10, 4)
	559 putfield (10, 4)
	560 org/apache/commons/math3/ode/events/EventState.pendingEventTime:D (10, 4)
	562 aload_0 (10, 4)
	563 iconst_1 (10, 4)
	564 putfield (10, 4)
	565 org/apache/commons/math3/ode/events/EventState.pendingEvent:Z (10, 4)
	567 iconst_1 (10, 4)
	568 ireturn (10, 4)
	569 aload_0 (7, 1)
	570 getfield (7, 1)
	571 org/apache/commons/math3/ode/events/EventState.previousEventTime:D (7, 1)
	573 invokestatic (7, 1)
	574 java/lang/Double.isNaN:(D)Z (7, 1)
	576 ifne (7, 1)
	577 21 (7, 1)
	579 aload_0 (7, 1)
	580 getfield (7, 1)
	581 org/apache/commons/math3/ode/events/EventState.previousEventTime:D (7, 1)
	583 dload (7, 1)
	584 #19 (7, 1)
	585 dsub (7, 1)
	586 invokestatic (7, 1)
	587 org/apache/commons/math3/util/FastMath.abs:(D)D (7, 1)
	589 aload_0 (7, 1)
	590 getfield (7, 1)
	591 org/apache/commons/math3/ode/events/EventState.convergence:D (7, 1)
	593 dcmpl (7, 1)
	594 ifle (7, 1)
	595 16 (7, 1)
	597 aload_0 (7, 1)
	598 dload (7, 1)
	599 #19 (7, 1)
	600 putfield (7, 1)
	601 org/apache/commons/math3/ode/events/EventState.pendingEventTime:D (7, 1)
	603 aload_0 (7, 1)
	604 iconst_1 (7, 1)
	605 putfield (7, 1)
	606 org/apache/commons/math3/ode/events/EventState.pendingEvent:Z (7, 1)
	608 iconst_1 (7, 1)
	609 ireturn (7, 1)
	610 dload (9, 4)
	611 #15 (9, 4)
	612 dstore (9, 4)
	613 #10 (9, 4)
	614 dload (9, 4)
	615 #17 (9, 4)
	616 dstore (9, 4)
	617 #12 (9, 4)
	618 goto (8, 2)
	619 11 (8, 2)
	621 dload (9, 4)
	622 #15 (9, 4)
	623 dstore (9, 4)
	624 #10 (9, 4)
	625 dload (9, 4)
	626 #17 (9, 4)
	627 dstore (9, 4)
	628 #12 (9, 4)
	629 iinc (9, 4)
	630 #14 (9, 4)
	631 -89 (9, 4)
	632 goto (9, 4)
	633 -538 (9, 4)
	635 aload_0 (2, 4)
	636 iconst_0 (2, 4)
	637 putfield (2, 4)
	638 org/apache/commons/math3/ode/events/EventState.pendingEvent:Z (2, 4)
	640 aload_0 (2, 4)
	641 ldc2_w (2, 4)
	642 nan (2, 4)
	644 putfield (2, 4)
	645 org/apache/commons/math3/ode/events/EventState.pendingEventTime:D (2, 4)
	647 iconst_0 (2, 4)
	648 ireturn (2, 4)
	649 astore_2 (2, 4)
	650 aload_2 (2, 4)
	651 invokevirtual (2, 4)
	652 org/apache/commons/math3/ode/events/EventState$LocalMaxCountExceededException.getException:()Lorg/apache/commons/math3/exception/MaxCountExceededException; (2, 4)
	654 athrow (1, 4)

Method: getEventTime
	0 aload_0 (0, 0)
	1 getfield (0, 0)
	2 org/apache/commons/math3/ode/events/EventState.pendingEvent:Z (0, 0)
	4 ifeq (0, 0)
	5 10 (0, 0)
	7 aload_0 (0, 0)
	8 getfield (0, 0)
	9 org/apache/commons/math3/ode/events/EventState.pendingEventTime:D (0, 0)
	11 goto (0, 0)
	12 19 (0, 0)
	14 aload_0 (0, 0)
	15 getfield (0, 0)
	16 org/apache/commons/math3/ode/events/EventState.forward:Z (0, 0)
	18 ifeq (0, 0)
	19 9 (0, 0)
	21 ldc2_w (0, 0)
	22 inf (0, 0)
	24 goto (0, 0)
	25 6 (0, 0)
	27 ldc2_w (0, 0)
	28 -inf (0, 0)
	30 dreturn (0, 0)

Method: stepAccepted
	0 aload_0 (0, 0)
	1 dload_1 (0, 0)
	2 putfield (0, 0)
	3 org/apache/commons/math3/ode/events/EventState.t0:D (0, 0)
	5 aload_0 (0, 0)
	6 aload_0 (0, 0)
	7 getfield (0, 0)
	8 org/apache/commons/math3/ode/events/EventState.handler:Lorg/apache/commons/math3/ode/events/EventHandler; (0, 0)
	10 dload_1 (0, 0)
	11 aload_3 (0, 0)
	12 invokeinterface (0, 0)
	13 org/apache/commons/math3/ode/events/EventHandler.org/apache/commons/math3/analysis/solvers/UnivariateSolver (0, 0)
	15 0 (0, 0)
	17 putfield (0, 0)
	18 org/apache/commons/math3/ode/events/EventState.g0:D (0, 0)
	20 aload_0 (1, 1)
	21 getfield (1, 1)
	22 org/apache/commons/math3/ode/events/EventState.pendingEvent:Z (1, 1)
	24 ifeq (1, 1)
	25 68 (1, 1)
	27 aload_0 (1, 1)
	28 getfield (1, 1)
	29 org/apache/commons/math3/ode/events/EventState.pendingEventTime:D (1, 1)
	31 dload_1 (1, 1)
	32 dsub (1, 1)
	33 invokestatic (1, 1)
	34 org/apache/commons/math3/util/FastMath.abs:(D)D (1, 1)
	36 aload_0 (1, 1)
	37 getfield (1, 1)
	38 org/apache/commons/math3/ode/events/EventState.convergence:D (1, 1)
	40 dcmpg (1, 1)
	41 ifgt (1, 1)
	42 51 (1, 1)
	44 aload_0 (2, 4)
	45 dload_1 (2, 4)
	46 putfield (2, 4)
	47 org/apache/commons/math3/ode/events/EventState.previousEventTime:D (2, 4)
	49 aload_0 (2, 4)
	50 aload_0 (2, 4)
	51 getfield (2, 4)
	52 org/apache/commons/math3/ode/events/EventState.increasing:Z (2, 4)
	54 putfield (2, 4)
	55 org/apache/commons/math3/ode/events/EventState.g0Positive:Z (2, 4)
	57 aload_0 (3, 4)
	58 aload_0 (3, 4)
	59 getfield (3, 4)
	60 org/apache/commons/math3/ode/events/EventState.handler:Lorg/apache/commons/math3/ode/events/EventHandler; (3, 4)
	62 dload_1 (3, 4)
	63 aload_3 (3, 4)
	64 aload_0 (3, 4)
	65 getfield (3, 4)
	66 org/apache/commons/math3/ode/events/EventState.increasing:Z (3, 4)
	68 aload_0 (3, 4)
	69 getfield (3, 4)
	70 org/apache/commons/math3/ode/events/EventState.forward:Z (3, 4)
	72 ixor (3, 4)
	73 ifne (3, 4)
	74 7 (3, 4)
	76 iconst_1 (3, 4)
	77 goto (3, 4)
	78 4 (3, 4)
	80 iconst_0 (3, 4)
	81 invokeinterface (3, 4)
	82 org/apache/commons/math3/ode/events/EventHandler.STOP:Lorg/apache/commons/math3/ode/events/EventHandler$Action; (3, 4)
	84 0 (3, 4)
	86 putfield (3, 4)
	87 org/apache/commons/math3/ode/events/EventState.nextAction:Lorg/apache/commons/math3/ode/events/EventHandler$Action; (3, 4)
	89 goto (3, 4)
	90 28 (3, 4)
	92 aload_0 (4, 2)
	93 aload_0 (4, 2)
	94 getfield (4, 2)
	95 org/apache/commons/math3/ode/events/EventState.g0:D (4, 2)
	97 dconst_0 (4, 2)
	98 dcmpl (4, 2)
	99 iflt (4, 2)
	100 7 (4, 2)
	102 iconst_1 (4, 2)
	103 goto (4, 2)
	104 4 (4, 2)
	106 iconst_0 (4, 2)
	107 putfield (4, 2)
	108 org/apache/commons/math3/ode/events/EventState.g0Positive:Z (4, 2)
	110 aload_0 (4, 2)
	111 getstatic (4, 2)
	112 org/apache/commons/math3/ode/events/EventHandler$Action.CONTINUE:Lorg/apache/commons/math3/ode/events/EventHandler$Action; (4, 2)
	114 putfield (4, 2)
	115 org/apache/commons/math3/ode/events/EventState.nextAction:Lorg/apache/commons/math3/ode/events/EventHandler$Action; (4, 2)
	117 return (0, 0)

Method: stop
	0 aload_0 (0, 0)
	1 getfield (0, 0)
	2 org/apache/commons/math3/ode/events/EventState.nextAction:Lorg/apache/commons/math3/ode/events/EventHandler$Action; (0, 0)
	4 getstatic (0, 0)
	5 org/apache/commons/math3/ode/events/EventHandler$Action.STOP:Lorg/apache/commons/math3/ode/events/EventHandler$Action; (0, 0)
	7 if_acmpne (0, 0)
	8 7 (0, 0)
	10 iconst_1 (0, 0)
	11 goto (0, 0)
	12 4 (0, 0)
	14 iconst_0 (0, 0)
	15 ireturn (0, 0)

Method: reset
	0 aload_0 (1, 1)
	1 getfield (1, 1)
	2 org/apache/commons/math3/ode/events/EventState.pendingEvent:Z (1, 1)
	4 ifeq (1, 1)
	5 20 (1, 1)
	7 aload_0 (1, 1)
	8 getfield (1, 1)
	9 org/apache/commons/math3/ode/events/EventState.pendingEventTime:D (1, 1)
	11 dload_1 (1, 1)
	12 dsub (1, 1)
	13 invokestatic (1, 1)
	14 org/apache/commons/math3/util/FastMath.abs:(D)D (1, 1)
	16 aload_0 (1, 1)
	17 getfield (1, 1)
	18 org/apache/commons/math3/ode/events/EventState.convergence:D (1, 1)
	20 dcmpg (1, 1)
	21 ifle (1, 1)
	22 5 (1, 1)
	24 iconst_0 (1, 1)
	25 ireturn (1, 1)
	26 aload_0 (1, 1)
	27 getfield (1, 1)
	28 org/apache/commons/math3/ode/events/EventState.nextAction:Lorg/apache/commons/math3/ode/events/EventHandler$Action; (1, 1)
	30 getstatic (1, 1)
	31 org/apache/commons/math3/ode/events/EventHandler$Action.RESET_STATE:Lorg/apache/commons/math3/ode/events/EventHandler$Action; (1, 1)
	33 if_acmpne (1, 1)
	34 14 (1, 1)
	36 aload_0 (1, 1)
	37 getfield (1, 1)
	38 org/apache/commons/math3/ode/events/EventState.handler:Lorg/apache/commons/math3/ode/events/EventHandler; (1, 1)
	40 dload_1 (1, 1)
	41 aload_3 (1, 1)
	42 invokeinterface (1, 1)
	43 org/apache/commons/math3/ode/events/EventHandler.RESET_DERIVATIVES:Lorg/apache/commons/math3/ode/events/EventHandler$Action; (1, 1)
	45 0 (1, 1)
	47 aload_0 (0, 0)
	48 iconst_0 (0, 0)
	49 putfield (0, 0)
	50 org/apache/commons/math3/ode/events/EventState.pendingEvent:Z (0, 0)
	52 aload_0 (0, 0)
	53 ldc2_w (0, 0)
	54 nan (0, 0)
	56 putfield (0, 0)
	57 org/apache/commons/math3/ode/events/EventState.pendingEventTime:D (0, 0)
	59 aload_0 (0, 0)
	60 getfield (0, 0)
	61 org/apache/commons/math3/ode/events/EventState.nextAction:Lorg/apache/commons/math3/ode/events/EventHandler$Action; (0, 0)
	63 getstatic (0, 0)
	64 org/apache/commons/math3/ode/events/EventHandler$Action.RESET_STATE:Lorg/apache/commons/math3/ode/events/EventHandler$Action; (0, 0)
	66 if_acmpeq (0, 0)
	67 13 (0, 0)
	69 aload_0 (0, 0)
	70 getfield (0, 0)
	71 org/apache/commons/math3/ode/events/EventState.nextAction:Lorg/apache/commons/math3/ode/events/EventHandler$Action; (0, 0)
	73 getstatic (0, 0)
	74 org/apache/commons/math3/ode/events/EventHandler$Action.RESET_DERIVATIVES:Lorg/apache/commons/math3/ode/events/EventHandler$Action; (0, 0)
	76 if_acmpne (0, 0)
	77 7 (0, 0)
	79 iconst_1 (0, 0)
	80 goto (0, 0)
	81 4 (0, 0)
	83 iconst_0 (0, 0)
	84 ireturn (0, 0)

Method: access$000
	0 aload_0 (0, 0)
	1 aload_1 (0, 0)
	2 invokespecial (0, 0)
	3 org/apache/commons/math3/ode/events/EventState.getCompleteState:(Lorg/apache/commons/math3/ode/sampling/StepInterpolator;)[D (0, 0)
	5 areturn (0, 0)

Method: access$100
	0 aload_0 (0, 0)
	1 getfield (0, 0)
	2 org/apache/commons/math3/ode/events/EventState.handler:Lorg/apache/commons/math3/ode/events/EventHandler; (0, 0)
	4 areturn (0, 0)

