Method: <init>
	0 aload_0 (0, 0)
	1 invokespecial (0, 0)
	2 java/lang/Object.<init>:()V (0, 0)
	4 aload_0 (0, 0)
	5 aload_1 (0, 0)
	6 putfield (0, 0)
	7 org/apache/commons/math3/ode/events/EventFilter.rawHandler:Lorg/apache/commons/math3/ode/events/EventHandler; (0, 0)
	9 aload_0 (0, 0)
	10 aload_2 (0, 0)
	11 putfield (0, 0)
	12 org/apache/commons/math3/ode/events/EventFilter.filter:Lorg/apache/commons/math3/ode/events/FilterType; (0, 0)
	14 aload_0 (1, 4)
	15 bipush (1, 4)
	16 100 (1, 4)
	17 anewarray (1, 4)
	18 org/apache/commons/math3/ode/events/Transformer (1, 4)
	20 putfield (1, 4)
	21 org/apache/commons/math3/ode/events/EventFilter.transformers:[Lorg/apache/commons/math3/ode/events/Transformer; (1, 4)
	23 aload_0 (1, 4)
	24 bipush (1, 4)
	25 100 (1, 4)
	26 newarray (1, 4)
	27 7 (1, 4)
	28 putfield (1, 4)
	29 org/apache/commons/math3/ode/events/EventFilter.updates:[D (1, 4)
	31 return (0, 0)

Method: init
	0 aload_0 (0, 0)
	1 getfield (0, 0)
	2 org/apache/commons/math3/ode/events/EventFilter.rawHandler:Lorg/apache/commons/math3/ode/events/EventHandler; (0, 0)
	4 dload_1 (0, 0)
	5 aload_3 (0, 0)
	6 dload (0, 0)
	7 #4 (0, 0)
	8 invokeinterface (0, 0)
	9 org/apache/commons/math3/ode/events/EventHandler.forward:Z (0, 0)
	11 0 (0, 0)
	13 aload_0 (1, 4)
	14 dload (1, 4)
	15 #4 (1, 4)
	16 dload_1 (1, 4)
	17 dcmpl (1, 4)
	18 iflt (1, 4)
	19 7 (1, 4)
	21 iconst_1 (1, 4)
	22 goto (1, 4)
	23 4 (1, 4)
	25 iconst_0 (1, 4)
	26 putfield (1, 4)
	27 org/apache/commons/math3/ode/events/EventFilter.forward:Z (1, 4)
	29 aload_0 (2, 4)
	30 aload_0 (2, 4)
	31 getfield (2, 4)
	32 org/apache/commons/math3/ode/events/EventFilter.forward:Z (2, 4)
	34 ifeq (2, 4)
	35 9 (2, 4)
	37 ldc2_w (2, 4)
	38 -inf (2, 4)
	40 goto (2, 4)
	41 6 (2, 4)
	43 ldc2_w (2, 4)
	44 inf (2, 4)
	46 putfield (2, 4)
	47 org/apache/commons/math3/ode/events/EventFilter.extremeT:D (2, 4)
	49 aload_0 (3, 4)
	50 getfield (3, 4)
	51 org/apache/commons/math3/ode/events/EventFilter.transformers:[Lorg/apache/commons/math3/ode/events/Transformer; (3, 4)
	53 getstatic (3, 4)
	54 org/apache/commons/math3/ode/events/Transformer.UNINITIALIZED:Lorg/apache/commons/math3/ode/events/Transformer; (3, 4)
	56 invokestatic (3, 4)
	57 java/util/Arrays.fill:([Ljava/lang/Object;Ljava/lang/Object;)V (3, 4)
	59 aload_0 (3, 4)
	60 getfield (3, 4)
	61 org/apache/commons/math3/ode/events/EventFilter.updates:[D (3, 4)
	63 aload_0 (3, 4)
	64 getfield (3, 4)
	65 org/apache/commons/math3/ode/events/EventFilter.extremeT:D (3, 4)
	67 invokestatic (3, 4)
	68 java/util/Arrays.fill:([DD)V (3, 4)
	70 return (0, 4)

Method: g
	0 aload_0 (0, 0)
	1 getfield (0, 0)
	2 org/apache/commons/math3/ode/events/EventFilter.rawHandler:Lorg/apache/commons/math3/ode/events/EventHandler; (0, 0)
	4 dload_1 (0, 0)
	5 aload_3 (0, 0)
	6 invokeinterface (0, 0)
	7 org/apache/commons/math3/ode/events/EventHandler.org/apache/commons/math3/ode/events/FilterType (0, 0)
	9 0 (0, 0)
	11 dstore (0, 0)
	12 #4 (0, 0)
	13 aload_0 (2, 1)
	14 getfield (2, 1)
	15 org/apache/commons/math3/ode/events/EventFilter.forward:Z (2, 1)
	17 ifeq (2, 1)
	18 169 (2, 1)
	20 aload_0 (3, 4)
	21 getfield (3, 4)
	22 org/apache/commons/math3/ode/events/EventFilter.transformers:[Lorg/apache/commons/math3/ode/events/Transformer; (3, 4)
	24 arraylength (3, 4)
	25 iconst_1 (3, 4)
	26 isub (3, 4)
	27 istore (3, 4)
	28 #6 (3, 4)
	29 aload_0 (4, 1)
	30 getfield (4, 1)
	31 org/apache/commons/math3/ode/events/EventFilter.extremeT:D (4, 1)
	33 dload_1 (4, 1)
	34 dcmpg (4, 1)
	35 ifge (4, 1)
	36 99 (4, 1)
	38 aload_0 (7, 4)
	39 getfield (7, 4)
	40 org/apache/commons/math3/ode/events/EventFilter.transformers:[Lorg/apache/commons/math3/ode/events/Transformer; (7, 4)
	42 iload (7, 4)
	43 #6 (7, 4)
	44 aaload (7, 4)
	45 astore (7, 4)
	46 #7 (7, 4)
	47 aload_0 (8, 4)
	48 getfield (8, 4)
	49 org/apache/commons/math3/ode/events/EventFilter.filter:Lorg/apache/commons/math3/ode/events/FilterType; (8, 4)
	51 aload (8, 4)
	52 #7 (8, 4)
	53 dload (8, 4)
	54 #4 (8, 4)
	55 aload_0 (8, 4)
	56 getfield (8, 4)
	57 org/apache/commons/math3/ode/events/EventFilter.forward:Z (8, 4)
	59 invokevirtual (8, 4)
	60 org/apache/commons/math3/ode/events/FilterType.selectTransformer:(Lorg/apache/commons/math3/ode/events/Transformer;DZ)Lorg/apache/commons/math3/ode/events/Transformer; (8, 4)
	62 astore (8, 4)
	63 #8 (8, 4)
	64 aload (9, 1)
	65 #8 (9, 1)
	66 aload (9, 1)
	67 #7 (9, 1)
	68 if_acmpeq (9, 1)
	69 53 (9, 1)
	71 aload_0 (12, 4)
	72 getfield (12, 4)
	73 org/apache/commons/math3/ode/events/EventFilter.updates:[D (12, 4)
	75 iconst_1 (12, 4)
	76 aload_0 (12, 4)
	77 getfield (12, 4)
	78 org/apache/commons/math3/ode/events/EventFilter.updates:[D (12, 4)
	80 iconst_0 (12, 4)
	81 iload (12, 4)
	82 #6 (12, 4)
	83 invokestatic (12, 4)
	84 java/lang/System.arraycopy:(Ljava/lang/Object;ILjava/lang/Object;II)V (12, 4)
	86 aload_0 (13, 4)
	87 getfield (13, 4)
	88 org/apache/commons/math3/ode/events/EventFilter.transformers:[Lorg/apache/commons/math3/ode/events/Transformer; (13, 4)
	90 iconst_1 (13, 4)
	91 aload_0 (13, 4)
	92 getfield (13, 4)
	93 org/apache/commons/math3/ode/events/EventFilter.transformers:[Lorg/apache/commons/math3/ode/events/Transformer; (13, 4)
	95 iconst_0 (13, 4)
	96 iload (13, 4)
	97 #6 (13, 4)
	98 invokestatic (13, 4)
	99 java/lang/System.arraycopy:(Ljava/lang/Object;ILjava/lang/Object;II)V (13, 4)
	101 aload_0 (13, 4)
	102 getfield (13, 4)
	103 org/apache/commons/math3/ode/events/EventFilter.updates:[D (13, 4)
	105 iload (13, 4)
	106 #6 (13, 4)
	107 aload_0 (13, 4)
	108 getfield (13, 4)
	109 org/apache/commons/math3/ode/events/EventFilter.extremeT:D (13, 4)
	111 dastore (13, 4)
	112 aload_0 (14, 4)
	113 getfield (14, 4)
	114 org/apache/commons/math3/ode/events/EventFilter.transformers:[Lorg/apache/commons/math3/ode/events/Transformer; (14, 4)
	116 iload (14, 4)
	117 #6 (14, 4)
	118 aload (14, 4)
	119 #8 (14, 4)
	120 aastore (14, 4)
	121 aload_0 (8, 4)
	122 dload_1 (8, 4)
	123 putfield (8, 4)
	124 org/apache/commons/math3/ode/events/EventFilter.extremeT:D (8, 4)
	126 aload (10, 4)
	127 #8 (10, 4)
	128 dload (10, 4)
	129 #4 (10, 4)
	130 invokevirtual (10, 4)
	131 org/apache/commons/math3/ode/events/Transformer.transformed:(D)D (10, 4)
	133 dreturn (10, 4)
	134 iload (13, 4)
	135 #6 (13, 4)
	136 istore (13, 4)
	137 #7 (13, 4)
	138 iload (13, 4)
	139 #7 (13, 4)
	140 ifle (13, 4)
	141 34 (13, 4)
	143 aload_0 (14, 1)
	144 getfield (14, 1)
	145 org/apache/commons/math3/ode/events/EventFilter.updates:[D (14, 1)
	147 iload (14, 1)
	148 #7 (14, 1)
	149 daload (14, 1)
	150 dload_1 (14, 1)
	151 dcmpg (14, 1)
	152 ifgt (14, 1)
	153 16 (14, 1)
	155 aload_0 (16, 4)
	156 getfield (16, 4)
	157 org/apache/commons/math3/ode/events/EventFilter.transformers:[Lorg/apache/commons/math3/ode/events/Transformer; (16, 4)
	159 iload (16, 4)
	160 #7 (16, 4)
	161 aaload (16, 4)
	162 dload (16, 4)
	163 #4 (16, 4)
	164 invokevirtual (16, 4)
	165 org/apache/commons/math3/ode/events/Transformer.transformed:(D)D (16, 4)
	167 dreturn (16, 4)
	168 iinc (16, 4)
	169 #7 (16, 4)
	170 -89 (16, 4)
	171 goto (16, 4)
	172 -33 (16, 4)
	174 aload_0 (14, 4)
	175 getfield (14, 4)
	176 org/apache/commons/math3/ode/events/EventFilter.transformers:[Lorg/apache/commons/math3/ode/events/Transformer; (14, 4)
	178 iconst_0 (14, 4)
	179 aaload (14, 4)
	180 dload (14, 4)
	181 #4 (14, 4)
	182 invokevirtual (14, 4)
	183 org/apache/commons/math3/ode/events/Transformer.transformed:(D)D (14, 4)
	185 dreturn (14, 4)
	186 dload_1 (14, 1)
	187 aload_0 (14, 1)
	188 getfield (14, 1)
	189 org/apache/commons/math3/ode/events/EventFilter.extremeT:D (14, 1)
	191 dcmpg (14, 1)
	192 ifge (14, 1)
	193 106 (14, 1)
	195 aload_0 (16, 4)
	196 getfield (16, 4)
	197 org/apache/commons/math3/ode/events/EventFilter.transformers:[Lorg/apache/commons/math3/ode/events/Transformer; (16, 4)
	199 iconst_0 (16, 4)
	200 aaload (16, 4)
	201 astore (16, 4)
	202 #6 (16, 4)
	203 aload_0 (17, 4)
	204 getfield (17, 4)
	205 org/apache/commons/math3/ode/events/EventFilter.filter:Lorg/apache/commons/math3/ode/events/FilterType; (17, 4)
	207 aload (17, 4)
	208 #6 (17, 4)
	209 dload (17, 4)
	210 #4 (17, 4)
	211 aload_0 (17, 4)
	212 getfield (17, 4)
	213 org/apache/commons/math3/ode/events/EventFilter.forward:Z (17, 4)
	215 invokevirtual (17, 4)
	216 org/apache/commons/math3/ode/events/FilterType.selectTransformer:(Lorg/apache/commons/math3/ode/events/Transformer;DZ)Lorg/apache/commons/math3/ode/events/Transformer; (17, 4)
	218 astore (17, 4)
	219 #7 (17, 4)
	220 aload (18, 1)
	221 #7 (18, 1)
	222 aload (18, 1)
	223 #6 (18, 1)
	224 if_acmpeq (18, 1)
	225 61 (18, 1)
	227 aload_0 (21, 4)
	228 getfield (21, 4)
	229 org/apache/commons/math3/ode/events/EventFilter.updates:[D (21, 4)
	231 iconst_0 (21, 4)
	232 aload_0 (21, 4)
	233 getfield (21, 4)
	234 org/apache/commons/math3/ode/events/EventFilter.updates:[D (21, 4)
	236 iconst_1 (21, 4)
	237 aload_0 (21, 4)
	238 getfield (21, 4)
	239 org/apache/commons/math3/ode/events/EventFilter.updates:[D (21, 4)
	241 arraylength (21, 4)
	242 iconst_1 (21, 4)
	243 isub (21, 4)
	244 invokestatic (21, 4)
	245 java/lang/System.arraycopy:(Ljava/lang/Object;ILjava/lang/Object;II)V (21, 4)
	247 aload_0 (22, 4)
	248 getfield (22, 4)
	249 org/apache/commons/math3/ode/events/EventFilter.transformers:[Lorg/apache/commons/math3/ode/events/Transformer; (22, 4)
	251 iconst_0 (22, 4)
	252 aload_0 (22, 4)
	253 getfield (22, 4)
	254 org/apache/commons/math3/ode/events/EventFilter.transformers:[Lorg/apache/commons/math3/ode/events/Transformer; (22, 4)
	256 iconst_1 (22, 4)
	257 aload_0 (22, 4)
	258 getfield (22, 4)
	259 org/apache/commons/math3/ode/events/EventFilter.transformers:[Lorg/apache/commons/math3/ode/events/Transformer; (22, 4)
	261 arraylength (22, 4)
	262 iconst_1 (22, 4)
	263 isub (22, 4)
	264 invokestatic (22, 4)
	265 java/lang/System.arraycopy:(Ljava/lang/Object;ILjava/lang/Object;II)V (22, 4)
	267 aload_0 (22, 4)
	268 getfield (22, 4)
	269 org/apache/commons/math3/ode/events/EventFilter.updates:[D (22, 4)
	271 iconst_0 (22, 4)
	272 aload_0 (22, 4)
	273 getfield (22, 4)
	274 org/apache/commons/math3/ode/events/EventFilter.extremeT:D (22, 4)
	276 dastore (22, 4)
	277 aload_0 (23, 4)
	278 getfield (23, 4)
	279 org/apache/commons/math3/ode/events/EventFilter.transformers:[Lorg/apache/commons/math3/ode/events/Transformer; (23, 4)
	281 iconst_0 (23, 4)
	282 aload (23, 4)
	283 #7 (23, 4)
	284 aastore (23, 4)
	285 aload_0 (17, 4)
	286 dload_1 (17, 4)
	287 putfield (17, 4)
	288 org/apache/commons/math3/ode/events/EventFilter.extremeT:D (17, 4)
	290 aload (19, 4)
	291 #7 (19, 4)
	292 dload (19, 4)
	293 #4 (19, 4)
	294 invokevirtual (19, 4)
	295 org/apache/commons/math3/ode/events/Transformer.transformed:(D)D (19, 4)
	297 dreturn (19, 4)
	298 iconst_0 (22, 4)
	299 istore (22, 4)
	300 #6 (22, 4)
	301 iload (22, 4)
	302 #6 (22, 4)
	303 aload_0 (22, 4)
	304 getfield (22, 4)
	305 org/apache/commons/math3/ode/events/EventFilter.updates:[D (22, 4)
	307 arraylength (22, 4)
	308 iconst_1 (22, 4)
	309 isub (22, 4)
	310 if_icmpge (22, 4)
	311 34 (22, 4)
	313 dload_1 (23, 1)
	314 aload_0 (23, 1)
	315 getfield (23, 1)
	316 org/apache/commons/math3/ode/events/EventFilter.updates:[D (23, 1)
	318 iload (23, 1)
	319 #6 (23, 1)
	320 daload (23, 1)
	321 dcmpg (23, 1)
	322 ifgt (23, 1)
	323 16 (23, 1)
	325 aload_0 (25, 4)
	326 getfield (25, 4)
	327 org/apache/commons/math3/ode/events/EventFilter.transformers:[Lorg/apache/commons/math3/ode/events/Transformer; (25, 4)
	329 iload (25, 4)
	330 #6 (25, 4)
	331 aaload (25, 4)
	332 dload (25, 4)
	333 #4 (25, 4)
	334 invokevirtual (25, 4)
	335 org/apache/commons/math3/ode/events/Transformer.transformed:(D)D (25, 4)
	337 dreturn (25, 4)
	338 iinc (25, 4)
	339 #6 (25, 4)
	340 -89 (25, 4)
	341 goto (25, 4)
	342 -40 (25, 4)
	344 aload_0 (23, 4)
	345 getfield (23, 4)
	346 org/apache/commons/math3/ode/events/EventFilter.transformers:[Lorg/apache/commons/math3/ode/events/Transformer; (23, 4)
	348 aload_0 (23, 4)
	349 getfield (23, 4)
	350 org/apache/commons/math3/ode/events/EventFilter.updates:[D (23, 4)
	352 arraylength (23, 4)
	353 iconst_1 (23, 4)
	354 isub (23, 4)
	355 aaload (23, 4)
	356 dload (23, 4)
	357 #4 (23, 4)
	358 invokevirtual (23, 4)
	359 org/apache/commons/math3/ode/events/Transformer.transformed:(D)D (23, 4)
	361 dreturn (4, 4)

Method: eventOccurred
	0 aload_0 (0, 0)
	1 getfield (0, 0)
	2 org/apache/commons/math3/ode/events/EventFilter.rawHandler:Lorg/apache/commons/math3/ode/events/EventHandler; (0, 0)
	4 dload_1 (0, 0)
	5 aload_3 (0, 0)
	6 aload_0 (0, 0)
	7 getfield (0, 0)
	8 org/apache/commons/math3/ode/events/EventFilter.filter:Lorg/apache/commons/math3/ode/events/FilterType; (0, 0)
	10 invokevirtual (0, 0)
	11 org/apache/commons/math3/ode/events/FilterType.getTriggeredIncreasing:()Z (0, 0)
	13 invokeinterface (0, 0)
	14 org/apache/commons/math3/ode/events/EventHandler.resetState:(D[D)V (0, 0)
	16 0 (0, 0)
	18 areturn (0, 0)

Method: resetState
	0 aload_0 (0, 0)
	1 getfield (0, 0)
	2 org/apache/commons/math3/ode/events/EventFilter.rawHandler:Lorg/apache/commons/math3/ode/events/EventHandler; (0, 0)
	4 dload_1 (0, 0)
	5 aload_3 (0, 0)
	6 invokeinterface (0, 0)
	7 org/apache/commons/math3/ode/events/EventHandler.java/lang/Object (0, 0)
	9 0 (0, 0)
	11 return (0, 0)

