Method: <init>
	0 aload_0 (0, 0)
	1 invokespecial (0, 0)
	2 java/lang/Object.<init>:()V (0, 0)
	4 aload_0 (0, 0)
	5 aload_1 (0, 0)
	6 putfield (0, 0)
	7 org/apache/commons/math3/ode/events/FieldEventState.handler:Lorg/apache/commons/math3/ode/events/FieldEventHandler; (0, 0)
	9 aload_0 (0, 0)
	10 dload_2 (0, 0)
	11 putfield (0, 0)
	12 org/apache/commons/math3/ode/events/FieldEventState.maxCheckInterval:D (0, 0)
	14 aload_0 (0, 0)
	15 aload (0, 0)
	16 #4 (0, 0)
	17 invokeinterface (0, 0)
	18 org/apache/commons/math3/RealFieldElement.org/apache/commons/math3/RealFieldElement (0, 0)
	20 0 (0, 0)
	22 checkcast (0, 0)
	23 org/apache/commons/math3/RealFieldElement (0, 0)
	25 putfield (0, 0)
	26 org/apache/commons/math3/ode/events/FieldEventState.convergence:Lorg/apache/commons/math3/RealFieldElement; (0, 0)
	28 aload_0 (0, 0)
	29 iload (0, 0)
	30 #5 (0, 0)
	31 putfield (0, 0)
	32 org/apache/commons/math3/ode/events/FieldEventState.maxIterationCount:I (0, 0)
	34 aload_0 (0, 0)
	35 aload (0, 0)
	36 #6 (0, 0)
	37 putfield (0, 0)
	38 org/apache/commons/math3/ode/events/FieldEventState.solver:Lorg/apache/commons/math3/analysis/solvers/BracketedRealFieldUnivariateSolver; (0, 0)
	40 aload_0 (0, 0)
	41 aconst_null (0, 0)
	42 putfield (0, 0)
	43 org/apache/commons/math3/ode/events/FieldEventState.t0:Lorg/apache/commons/math3/RealFieldElement; (0, 0)
	45 aload_0 (0, 0)
	46 aconst_null (0, 0)
	47 putfield (0, 0)
	48 org/apache/commons/math3/ode/events/FieldEventState.g0:Lorg/apache/commons/math3/RealFieldElement; (0, 0)
	50 aload_0 (0, 0)
	51 iconst_1 (0, 0)
	52 putfield (0, 0)
	53 org/apache/commons/math3/ode/events/FieldEventState.g0Positive:Z (0, 0)
	55 aload_0 (0, 0)
	56 iconst_0 (0, 0)
	57 putfield (0, 0)
	58 org/apache/commons/math3/ode/events/FieldEventState.pendingEvent:Z (0, 0)
	60 aload_0 (0, 0)
	61 aconst_null (0, 0)
	62 putfield (0, 0)
	63 org/apache/commons/math3/ode/events/FieldEventState.pendingEventTime:Lorg/apache/commons/math3/RealFieldElement; (0, 0)
	65 aload_0 (0, 0)
	66 aconst_null (0, 0)
	67 putfield (0, 0)
	68 org/apache/commons/math3/ode/events/FieldEventState.previousEventTime:Lorg/apache/commons/math3/RealFieldElement; (0, 0)
	70 aload_0 (0, 0)
	71 iconst_1 (0, 0)
	72 putfield (0, 0)
	73 org/apache/commons/math3/ode/events/FieldEventState.increasing:Z (0, 0)
	75 aload_0 (0, 0)
	76 getstatic (0, 0)
	77 org/apache/commons/math3/ode/events/Action.CONTINUE:Lorg/apache/commons/math3/ode/events/Action; (0, 0)
	79 putfield (0, 0)
	80 org/apache/commons/math3/ode/events/FieldEventState.nextAction:Lorg/apache/commons/math3/ode/events/Action; (0, 0)
	82 return (0, 0)

Method: getEventHandler
	0 aload_0 (0, 0)
	1 getfield (0, 0)
	2 org/apache/commons/math3/ode/events/FieldEventState.handler:Lorg/apache/commons/math3/ode/events/FieldEventHandler; (0, 0)
	4 areturn (0, 0)

Method: getMaxCheckInterval
	0 aload_0 (0, 0)
	1 getfield (0, 0)
	2 org/apache/commons/math3/ode/events/FieldEventState.maxCheckInterval:D (0, 0)
	4 dreturn (0, 0)

Method: getConvergence
	0 aload_0 (0, 0)
	1 getfield (0, 0)
	2 org/apache/commons/math3/ode/events/FieldEventState.convergence:Lorg/apache/commons/math3/RealFieldElement; (0, 0)
	4 areturn (0, 0)

Method: getMaxIterationCount
	0 aload_0 (0, 0)
	1 getfield (0, 0)
	2 org/apache/commons/math3/ode/events/FieldEventState.maxIterationCount:I (0, 0)
	4 ireturn (0, 0)

Method: reinitializeBegin
	0 aload_1 (0, 0)
	1 invokeinterface (0, 0)
	2 org/apache/commons/math3/ode/sampling/FieldStepInterpolator.org/apache/commons/math3/ode/FieldODEStateAndDerivative (0, 0)
	4 0 (0, 0)
	6 astore_2 (0, 0)
	7 aload_0 (0, 0)
	8 aload_2 (0, 0)
	9 invokevirtual (0, 0)
	10 org/apache/commons/math3/ode/FieldODEStateAndDerivative.getTime:()Lorg/apache/commons/math3/RealFieldElement; (0, 0)
	12 putfield (0, 0)
	13 org/apache/commons/math3/ode/events/FieldEventState.t0:Lorg/apache/commons/math3/RealFieldElement; (0, 0)
	15 aload_0 (0, 0)
	16 aload_0 (0, 0)
	17 getfield (0, 0)
	18 org/apache/commons/math3/ode/events/FieldEventState.handler:Lorg/apache/commons/math3/ode/events/FieldEventHandler; (0, 0)
	20 aload_2 (0, 0)
	21 invokeinterface (0, 0)
	22 org/apache/commons/math3/ode/events/FieldEventHandler.getReal:()D (0, 0)
	24 0 (0, 0)
	26 putfield (0, 0)
	27 org/apache/commons/math3/ode/events/FieldEventState.g0:Lorg/apache/commons/math3/RealFieldElement; (0, 0)
	29 aload_0 (1, 1)
	30 getfield (1, 1)
	31 org/apache/commons/math3/ode/events/FieldEventState.g0:Lorg/apache/commons/math3/RealFieldElement; (1, 1)
	33 invokeinterface (1, 1)
	34 org/apache/commons/math3/RealFieldElement.org/apache/commons/math3/analysis/solvers/BracketedRealFieldUnivariateSolver (1, 1)
	36 0 (1, 1)
	38 dconst_0 (1, 1)
	39 dcmpl (1, 1)
	40 ifne (1, 1)
	41 90 (1, 1)
	43 aload_0 (3, 4)
	44 getfield (3, 4)
	45 org/apache/commons/math3/ode/events/FieldEventState.solver:Lorg/apache/commons/math3/analysis/solvers/BracketedRealFieldUnivariateSolver; (3, 4)
	47 invokeinterface (3, 4)
	48 org/apache/commons/math3/analysis/solvers/BracketedRealFieldUnivariateSolver.getRelativeAccuracy:()Lorg/apache/commons/math3/RealFieldElement; (3, 4)
	50 0 (3, 4)
	52 invokeinterface (3, 4)
	53 org/apache/commons/math3/RealFieldElement.org/apache/commons/math3/analysis/solvers/BracketedRealFieldUnivariateSolver (3, 4)
	55 0 (3, 4)
	57 aload_0 (3, 4)
	58 getfield (3, 4)
	59 org/apache/commons/math3/ode/events/FieldEventState.solver:Lorg/apache/commons/math3/analysis/solvers/BracketedRealFieldUnivariateSolver; (3, 4)
	61 invokeinterface (3, 4)
	62 org/apache/commons/math3/analysis/solvers/BracketedRealFieldUnivariateSolver.multiply:(Ljava/lang/Object;)Ljava/lang/Object; (3, 4)
	64 0 (3, 4)
	66 aload_0 (3, 4)
	67 getfield (3, 4)
	68 org/apache/commons/math3/ode/events/FieldEventState.t0:Lorg/apache/commons/math3/RealFieldElement; (3, 4)
	70 invokeinterface (3, 4)
	71 org/apache/commons/math3/RealFieldElement.org/apache/commons/math3/util/FastMath (3, 4)
	73 0 (3, 4)
	75 checkcast (3, 4)
	76 org/apache/commons/math3/RealFieldElement (3, 4)
	78 invokeinterface (3, 4)
	79 org/apache/commons/math3/RealFieldElement.org/apache/commons/math3/analysis/solvers/BracketedRealFieldUnivariateSolver (3, 4)
	81 0 (3, 4)
	83 invokestatic (3, 4)
	84 org/apache/commons/math3/util/FastMath.abs:(D)D (3, 4)
	86 invokestatic (3, 4)
	87 org/apache/commons/math3/util/FastMath.max:(DD)D (3, 4)
	89 dstore_3 (3, 4)
	90 aload_0 (3, 4)
	91 getfield (3, 4)
	92 org/apache/commons/math3/ode/events/FieldEventState.t0:Lorg/apache/commons/math3/RealFieldElement; (3, 4)
	94 ldc2_w (3, 4)
	95 0.5 (3, 4)
	97 dload_3 (3, 4)
	98 dmul (3, 4)
	99 invokeinterface (3, 4)
	100 org/apache/commons/math3/RealFieldElement.getInterpolatedState:(Lorg/apache/commons/math3/RealFieldElement;)Lorg/apache/commons/math3/ode/FieldODEStateAndDerivative; (3, 4)
	102 0 (3, 4)
	104 checkcast (3, 4)
	105 org/apache/commons/math3/RealFieldElement (3, 4)
	107 astore (3, 4)
	108 #5 (3, 4)
	109 aload_0 (3, 4)
	110 aload_0 (3, 4)
	111 getfield (3, 4)
	112 org/apache/commons/math3/ode/events/FieldEventState.handler:Lorg/apache/commons/math3/ode/events/FieldEventHandler; (3, 4)
	114 aload_1 (3, 4)
	115 aload (3, 4)
	116 #5 (3, 4)
	117 invokeinterface (3, 4)
	118 org/apache/commons/math3/ode/sampling/FieldStepInterpolator.isForward:()Z (3, 4)
	120 0 (3, 4)
	122 invokeinterface (3, 4)
	123 org/apache/commons/math3/ode/events/FieldEventHandler.getReal:()D (3, 4)
	125 0 (3, 4)
	127 putfield (3, 4)
	128 org/apache/commons/math3/ode/events/FieldEventState.g0:Lorg/apache/commons/math3/RealFieldElement; (3, 4)
	130 aload_0 (0, 0)
	131 aload_0 (0, 0)
	132 getfield (0, 0)
	133 org/apache/commons/math3/ode/events/FieldEventState.g0:Lorg/apache/commons/math3/RealFieldElement; (0, 0)
	135 invokeinterface (0, 0)
	136 org/apache/commons/math3/RealFieldElement.org/apache/commons/math3/analysis/solvers/BracketedRealFieldUnivariateSolver (0, 0)
	138 0 (0, 0)
	140 dconst_0 (0, 0)
	141 dcmpl (0, 0)
	142 iflt (0, 0)
	143 7 (0, 0)
	145 iconst_1 (0, 0)
	146 goto (0, 0)
	147 4 (0, 0)
	149 iconst_0 (0, 0)
	150 putfield (0, 0)
	151 org/apache/commons/math3/ode/events/FieldEventState.g0Positive:Z (0, 0)
	153 return (0, 0)

Method: evaluateStep
	0 aload_0 (1, 4)
	1 aload_1 (1, 4)
	2 invokeinterface (1, 4)
	3 org/apache/commons/math3/ode/sampling/FieldStepInterpolator.forward:Z (1, 4)
	5 0 (1, 4)
	7 putfield (1, 4)
	8 org/apache/commons/math3/ode/events/FieldEventState.forward:Z (1, 4)
	10 aload_1 (1, 4)
	11 invokeinterface (1, 4)
	12 org/apache/commons/math3/ode/sampling/FieldStepInterpolator.subtract:(Ljava/lang/Object;)Ljava/lang/Object; (1, 4)
	14 0 (1, 4)
	16 astore_2 (1, 4)
	17 aload_2 (1, 4)
	18 invokevirtual (1, 4)
	19 org/apache/commons/math3/ode/FieldODEStateAndDerivative.getTime:()Lorg/apache/commons/math3/RealFieldElement; (1, 4)
	21 astore_3 (1, 4)
	22 aload_3 (1, 4)
	23 aload_0 (1, 4)
	24 getfield (1, 4)
	25 org/apache/commons/math3/ode/events/FieldEventState.t0:Lorg/apache/commons/math3/RealFieldElement; (1, 4)
	27 invokeinterface (1, 4)
	28 org/apache/commons/math3/RealFieldElement.ceil:(D)D (1, 4)
	30 0 (1, 4)
	32 checkcast (1, 4)
	33 org/apache/commons/math3/RealFieldElement (1, 4)
	35 astore (1, 4)
	36 #4 (1, 4)
	37 aload (2, 1)
	38 #4 (2, 1)
	39 invokeinterface (2, 1)
	40 org/apache/commons/math3/RealFieldElement.org/apache/commons/math3/RealFieldElement (2, 1)
	42 0 (2, 1)
	44 checkcast (2, 1)
	45 org/apache/commons/math3/RealFieldElement (2, 1)
	47 aload_0 (2, 1)
	48 getfield (2, 1)
	49 org/apache/commons/math3/ode/events/FieldEventState.convergence:Lorg/apache/commons/math3/RealFieldElement; (2, 1)
	51 invokeinterface (2, 1)
	52 org/apache/commons/math3/RealFieldElement.ceil:(D)D (2, 1)
	54 0 (2, 1)
	56 checkcast (2, 1)
	57 org/apache/commons/math3/RealFieldElement (2, 1)
	59 invokeinterface (2, 1)
	60 org/apache/commons/math3/RealFieldElement.org/apache/commons/math3/analysis/solvers/BracketedRealFieldUnivariateSolver (2, 1)
	62 0 (2, 1)
	64 dconst_0 (2, 1)
	65 dcmpg (2, 1)
	66 ifge (2, 1)
	67 5 (2, 1)
	69 iconst_0 (2, 1)
	70 ireturn (2, 1)
	71 iconst_1 (1, 4)
	72 aload (1, 4)
	73 #4 (1, 4)
	74 invokeinterface (1, 4)
	75 org/apache/commons/math3/RealFieldElement.org/apache/commons/math3/analysis/solvers/BracketedRealFieldUnivariateSolver (1, 4)
	77 0 (1, 4)
	79 invokestatic (1, 4)
	80 org/apache/commons/math3/util/FastMath.abs:(D)D (1, 4)
	82 aload_0 (1, 4)
	83 getfield (1, 4)
	84 org/apache/commons/math3/ode/events/FieldEventState.maxCheckInterval:D (1, 4)
	86 ddiv (1, 4)
	87 invokestatic (1, 4)
	88 org/apache/commons/math3/util/FastMath.ceil:(D)D (1, 4)
	90 d2i (1, 4)
	91 invokestatic (1, 4)
	92 org/apache/commons/math3/util/FastMath.max:(II)I (1, 4)
	94 istore (1, 4)
	95 #5 (1, 4)
	96 aload (1, 4)
	97 #4 (1, 4)
	98 iload (1, 4)
	99 #5 (1, 4)
	100 i2d (1, 4)
	101 invokeinterface (1, 4)
	102 org/apache/commons/math3/RealFieldElement.org/apache/commons/math3/ode/events/FieldEventState$1 (1, 4)
	104 0 (1, 4)
	106 checkcast (1, 4)
	107 org/apache/commons/math3/RealFieldElement (1, 4)
	109 astore (1, 4)
	110 #6 (1, 4)
	111 new (1, 4)
	112 org/apache/commons/math3/ode/events/FieldEventState$1 (1, 4)
	114 dup (1, 4)
	115 aload_0 (1, 4)
	116 aload_1 (1, 4)
	117 invokespecial (1, 4)
	118 org/apache/commons/math3/ode/events/FieldEventState$1.<init>:(Lorg/apache/commons/math3/ode/events/FieldEventState;Lorg/apache/commons/math3/ode/sampling/FieldStepInterpolator;)V (1, 4)
	120 astore (1, 4)
	121 #7 (1, 4)
	122 aload_0 (1, 4)
	123 getfield (1, 4)
	124 org/apache/commons/math3/ode/events/FieldEventState.t0:Lorg/apache/commons/math3/RealFieldElement; (1, 4)
	126 astore (1, 4)
	127 #8 (1, 4)
	128 aload_0 (1, 4)
	129 getfield (1, 4)
	130 org/apache/commons/math3/ode/events/FieldEventState.g0:Lorg/apache/commons/math3/RealFieldElement; (1, 4)
	132 astore (1, 4)
	133 #9 (1, 4)
	134 iconst_0 (2, 4)
	135 istore (2, 4)
	136 #10 (2, 4)
	137 iload (2, 4)
	138 #10 (2, 4)
	139 iload (2, 4)
	140 #5 (2, 4)
	141 if_icmpge (2, 4)
	142 519 (2, 4)
	144 iload (2, 4)
	145 #10 (2, 4)
	146 iload (2, 4)
	147 #5 (2, 4)
	148 iconst_1 (2, 4)
	149 isub (2, 4)
	150 if_icmpne (2, 4)
	151 7 (2, 4)
	153 aload_3 (2, 4)
	154 goto (2, 4)
	155 26 (2, 4)
	157 aload_0 (2, 4)
	158 getfield (2, 4)
	159 org/apache/commons/math3/ode/events/FieldEventState.t0:Lorg/apache/commons/math3/RealFieldElement; (2, 4)
	161 aload (2, 4)
	162 #6 (2, 4)
	163 iload (2, 4)
	164 #10 (2, 4)
	165 iconst_1 (2, 4)
	166 iadd (2, 4)
	167 invokeinterface (2, 4)
	168 org/apache/commons/math3/RealFieldElement.add:(Ljava/lang/Object;)Ljava/lang/Object; (2, 4)
	170 0 (2, 4)
	172 invokeinterface (2, 4)
	173 org/apache/commons/math3/RealFieldElement.org/apache/commons/math3/analysis/solvers/AllowedSolution (2, 4)
	175 0 (2, 4)
	177 checkcast (2, 4)
	178 org/apache/commons/math3/RealFieldElement (2, 4)
	180 astore (2, 4)
	181 #11 (2, 4)
	182 aload_0 (2, 4)
	183 getfield (2, 4)
	184 org/apache/commons/math3/ode/events/FieldEventState.handler:Lorg/apache/commons/math3/ode/events/FieldEventHandler; (2, 4)
	186 aload_1 (2, 4)
	187 aload (2, 4)
	188 #11 (2, 4)
	189 invokeinterface (2, 4)
	190 org/apache/commons/math3/ode/sampling/FieldStepInterpolator.isForward:()Z (2, 4)
	192 0 (2, 4)
	194 invokeinterface (2, 4)
	195 org/apache/commons/math3/ode/events/FieldEventHandler.getReal:()D (2, 4)
	197 0 (2, 4)
	199 astore (2, 4)
	200 #12 (2, 4)
	201 aload_0 (3, 1)
	202 getfield (3, 1)
	203 org/apache/commons/math3/ode/events/FieldEventState.g0Positive:Z (3, 1)
	205 aload (3, 1)
	206 #12 (3, 1)
	207 invokeinterface (3, 1)
	208 org/apache/commons/math3/RealFieldElement.org/apache/commons/math3/analysis/solvers/BracketedRealFieldUnivariateSolver (3, 1)
	210 0 (3, 1)
	212 dconst_0 (3, 1)
	213 dcmpl (3, 1)
	214 iflt (3, 1)
	215 7 (3, 1)
	217 iconst_1 (3, 1)
	218 goto (3, 1)
	219 4 (3, 1)
	221 iconst_0 (3, 1)
	222 ixor (3, 1)
	223 ifeq (3, 1)
	224 423 (3, 1)
	226 aload_0 (3, 1)
	227 aload (3, 1)
	228 #12 (3, 1)
	229 aload (3, 1)
	230 #9 (3, 1)
	231 invokeinterface (3, 1)
	232 org/apache/commons/math3/RealFieldElement.ceil:(D)D (3, 1)
	234 0 (3, 1)
	236 checkcast (3, 1)
	237 org/apache/commons/math3/RealFieldElement (3, 1)
	239 invokeinterface (3, 1)
	240 org/apache/commons/math3/RealFieldElement.org/apache/commons/math3/analysis/solvers/BracketedRealFieldUnivariateSolver (3, 1)
	242 0 (3, 1)
	244 dconst_0 (3, 1)
	245 dcmpl (3, 1)
	246 iflt (3, 1)
	247 7 (3, 1)
	249 iconst_1 (3, 1)
	250 goto (3, 1)
	251 4 (3, 1)
	253 iconst_0 (3, 1)
	254 putfield (3, 1)
	255 org/apache/commons/math3/ode/events/FieldEventState.increasing:Z (3, 1)
	257 aload_0 (4, 4)
	258 getfield (4, 4)
	259 org/apache/commons/math3/ode/events/FieldEventState.forward:Z (4, 4)
	261 ifeq (4, 4)
	262 28 (4, 4)
	264 aload_0 (4, 4)
	265 getfield (4, 4)
	266 org/apache/commons/math3/ode/events/FieldEventState.solver:Lorg/apache/commons/math3/analysis/solvers/BracketedRealFieldUnivariateSolver; (4, 4)
	268 aload_0 (4, 4)
	269 getfield (4, 4)
	270 org/apache/commons/math3/ode/events/FieldEventState.maxIterationCount:I (4, 4)
	272 aload (4, 4)
	273 #7 (4, 4)
	274 aload (4, 4)
	275 #8 (4, 4)
	276 aload (4, 4)
	277 #11 (4, 4)
	278 getstatic (4, 4)
	279 org/apache/commons/math3/analysis/solvers/AllowedSolution.RIGHT_SIDE:Lorg/apache/commons/math3/analysis/solvers/AllowedSolution; (4, 4)
	281 invokeinterface (4, 4)
	282 org/apache/commons/math3/analysis/solvers/BracketedRealFieldUnivariateSolver.LEFT_SIDE:Lorg/apache/commons/math3/analysis/solvers/AllowedSolution; (4, 4)
	284 0 (4, 4)
	286 goto (4, 4)
	287 25 (4, 4)
	289 aload_0 (4, 4)
	290 getfield (4, 4)
	291 org/apache/commons/math3/ode/events/FieldEventState.solver:Lorg/apache/commons/math3/analysis/solvers/BracketedRealFieldUnivariateSolver; (4, 4)
	293 aload_0 (4, 4)
	294 getfield (4, 4)
	295 org/apache/commons/math3/ode/events/FieldEventState.maxIterationCount:I (4, 4)
	297 aload (4, 4)
	298 #7 (4, 4)
	299 aload (4, 4)
	300 #11 (4, 4)
	301 aload (4, 4)
	302 #8 (4, 4)
	303 getstatic (4, 4)
	304 org/apache/commons/math3/analysis/solvers/AllowedSolution.LEFT_SIDE:Lorg/apache/commons/math3/analysis/solvers/AllowedSolution; (4, 4)
	306 invokeinterface (4, 4)
	307 org/apache/commons/math3/analysis/solvers/BracketedRealFieldUnivariateSolver.LEFT_SIDE:Lorg/apache/commons/math3/analysis/solvers/AllowedSolution; (4, 4)
	309 0 (4, 4)
	311 astore (4, 4)
	312 #13 (4, 4)
	313 aload_0 (5, 1)
	314 getfield (5, 1)
	315 org/apache/commons/math3/ode/events/FieldEventState.previousEventTime:Lorg/apache/commons/math3/RealFieldElement; (5, 1)
	317 ifnull (5, 1)
	318 254 (5, 1)
	320 aload (5, 1)
	321 #13 (5, 1)
	322 aload (5, 1)
	323 #8 (5, 1)
	324 invokeinterface (5, 1)
	325 org/apache/commons/math3/RealFieldElement.ceil:(D)D (5, 1)
	327 0 (5, 1)
	329 checkcast (5, 1)
	330 org/apache/commons/math3/RealFieldElement (5, 1)
	332 invokeinterface (5, 1)
	333 org/apache/commons/math3/RealFieldElement.org/apache/commons/math3/RealFieldElement (5, 1)
	335 0 (5, 1)
	337 checkcast (5, 1)
	338 org/apache/commons/math3/RealFieldElement (5, 1)
	340 aload_0 (5, 1)
	341 getfield (5, 1)
	342 org/apache/commons/math3/ode/events/FieldEventState.convergence:Lorg/apache/commons/math3/RealFieldElement; (5, 1)
	344 invokeinterface (5, 1)
	345 org/apache/commons/math3/RealFieldElement.ceil:(D)D (5, 1)
	347 0 (5, 1)
	349 checkcast (5, 1)
	350 org/apache/commons/math3/RealFieldElement (5, 1)
	352 invokeinterface (5, 1)
	353 org/apache/commons/math3/RealFieldElement.org/apache/commons/math3/analysis/solvers/BracketedRealFieldUnivariateSolver (5, 1)
	355 0 (5, 1)
	357 dconst_0 (5, 1)
	358 dcmpg (5, 1)
	359 ifgt (5, 1)
	360 212 (5, 1)
	362 aload (5, 1)
	363 #13 (5, 1)
	364 aload_0 (5, 1)
	365 getfield (5, 1)
	366 org/apache/commons/math3/ode/events/FieldEventState.previousEventTime:Lorg/apache/commons/math3/RealFieldElement; (5, 1)
	368 invokeinterface (5, 1)
	369 org/apache/commons/math3/RealFieldElement.ceil:(D)D (5, 1)
	371 0 (5, 1)
	373 checkcast (5, 1)
	374 org/apache/commons/math3/RealFieldElement (5, 1)
	376 invokeinterface (5, 1)
	377 org/apache/commons/math3/RealFieldElement.org/apache/commons/math3/RealFieldElement (5, 1)
	379 0 (5, 1)
	381 checkcast (5, 1)
	382 org/apache/commons/math3/RealFieldElement (5, 1)
	384 aload_0 (5, 1)
	385 getfield (5, 1)
	386 org/apache/commons/math3/ode/events/FieldEventState.convergence:Lorg/apache/commons/math3/RealFieldElement; (5, 1)
	388 invokeinterface (5, 1)
	389 org/apache/commons/math3/RealFieldElement.ceil:(D)D (5, 1)
	391 0 (5, 1)
	393 checkcast (5, 1)
	394 org/apache/commons/math3/RealFieldElement (5, 1)
	396 invokeinterface (5, 1)
	397 org/apache/commons/math3/RealFieldElement.org/apache/commons/math3/analysis/solvers/BracketedRealFieldUnivariateSolver (5, 1)
	399 0 (5, 1)
	401 dconst_0 (5, 1)
	402 dcmpg (5, 1)
	403 ifgt (5, 1)
	404 168 (5, 1)
	406 aload_0 (6, 4)
	407 getfield (6, 4)
	408 org/apache/commons/math3/ode/events/FieldEventState.forward:Z (6, 4)
	410 ifeq (6, 4)
	411 20 (6, 4)
	413 aload (6, 4)
	414 #8 (6, 4)
	415 aload_0 (6, 4)
	416 getfield (6, 4)
	417 org/apache/commons/math3/ode/events/FieldEventState.convergence:Lorg/apache/commons/math3/RealFieldElement; (6, 4)
	419 invokeinterface (6, 4)
	420 org/apache/commons/math3/RealFieldElement.org/apache/commons/math3/analysis/solvers/AllowedSolution (6, 4)
	422 0 (6, 4)
	424 checkcast (6, 4)
	425 org/apache/commons/math3/RealFieldElement (6, 4)
	427 goto (6, 4)
	428 17 (6, 4)
	430 aload (6, 4)
	431 #8 (6, 4)
	432 aload_0 (6, 4)
	433 getfield (6, 4)
	434 org/apache/commons/math3/ode/events/FieldEventState.convergence:Lorg/apache/commons/math3/RealFieldElement; (6, 4)
	436 invokeinterface (6, 4)
	437 org/apache/commons/math3/RealFieldElement.ceil:(D)D (6, 4)
	439 0 (6, 4)
	441 checkcast (6, 4)
	442 org/apache/commons/math3/RealFieldElement (6, 4)
	444 astore (6, 4)
	445 #8 (6, 4)
	446 aload (6, 4)
	447 #7 (6, 4)
	448 aload (6, 4)
	449 #8 (6, 4)
	450 invokeinterface (6, 4)
	451 org/apache/commons/math3/analysis/RealFieldUnivariateFunction.getField:()Lorg/apache/commons/math3/Field; (6, 4)
	453 0 (6, 4)
	455 astore (6, 4)
	456 #9 (6, 4)
	457 aload_0 (7, 3)
	458 getfield (7, 3)
	459 org/apache/commons/math3/ode/events/FieldEventState.g0Positive:Z (7, 3)
	461 aload (7, 3)
	462 #9 (7, 3)
	463 invokeinterface (7, 3)
	464 org/apache/commons/math3/RealFieldElement.org/apache/commons/math3/analysis/solvers/BracketedRealFieldUnivariateSolver (7, 3)
	466 0 (7, 3)
	468 dconst_0 (7, 3)
	469 dcmpl (7, 3)
	470 iflt (7, 3)
	471 7 (7, 3)
	473 iconst_1 (7, 3)
	474 goto (7, 3)
	475 4 (7, 3)
	477 iconst_0 (7, 3)
	478 ixor (7, 3)
	479 ifeq (7, 3)
	480 38 (7, 3)
	482 aload_0 (7, 3)
	483 getfield (7, 3)
	484 org/apache/commons/math3/ode/events/FieldEventState.forward:Z (7, 3)
	486 aload (7, 3)
	487 #8 (7, 3)
	488 aload (7, 3)
	489 #11 (7, 3)
	490 invokeinterface (7, 3)
	491 org/apache/commons/math3/RealFieldElement.ceil:(D)D (7, 3)
	493 0 (7, 3)
	495 checkcast (7, 3)
	496 org/apache/commons/math3/RealFieldElement (7, 3)
	498 invokeinterface (7, 3)
	499 org/apache/commons/math3/RealFieldElement.org/apache/commons/math3/analysis/solvers/BracketedRealFieldUnivariateSolver (7, 3)
	501 0 (7, 3)
	503 dconst_0 (7, 3)
	504 dcmpl (7, 3)
	505 iflt (7, 3)
	506 7 (7, 3)
	508 iconst_1 (7, 3)
	509 goto (7, 3)
	510 4 (7, 3)
	512 iconst_0 (7, 3)
	513 ixor (7, 3)
	514 ifne (7, 3)
	515 -108 (7, 3)
	517 aload_0 (8, 1)
	518 getfield (8, 1)
	519 org/apache/commons/math3/ode/events/FieldEventState.forward:Z (8, 1)
	521 aload (8, 1)
	522 #8 (8, 1)
	523 aload (8, 1)
	524 #11 (8, 1)
	525 invokeinterface (8, 1)
	526 org/apache/commons/math3/RealFieldElement.ceil:(D)D (8, 1)
	528 0 (8, 1)
	530 checkcast (8, 1)
	531 org/apache/commons/math3/RealFieldElement (8, 1)
	533 invokeinterface (8, 1)
	534 org/apache/commons/math3/RealFieldElement.org/apache/commons/math3/analysis/solvers/BracketedRealFieldUnivariateSolver (8, 1)
	536 0 (8, 1)
	538 dconst_0 (8, 1)
	539 dcmpl (8, 1)
	540 iflt (8, 1)
	541 7 (8, 1)
	543 iconst_1 (8, 1)
	544 goto (8, 1)
	545 4 (8, 1)
	547 iconst_0 (8, 1)
	548 ixor (8, 1)
	549 ifeq (8, 1)
	550 9 (8, 1)
	552 iinc (8, 1)
	553 #10 (8, 1)
	554 -89 (8, 1)
	555 goto (8, 1)
	556 88 (8, 1)
	558 aload_0 (11, 4)
	559 aload (11, 4)
	560 #13 (11, 4)
	561 putfield (11, 4)
	562 org/apache/commons/math3/ode/events/FieldEventState.pendingEventTime:Lorg/apache/commons/math3/RealFieldElement; (11, 4)
	564 aload_0 (11, 4)
	565 iconst_1 (11, 4)
	566 putfield (11, 4)
	567 org/apache/commons/math3/ode/events/FieldEventState.pendingEvent:Z (11, 4)
	569 iconst_1 (11, 4)
	570 ireturn (11, 4)
	571 aload_0 (8, 1)
	572 getfield (8, 1)
	573 org/apache/commons/math3/ode/events/FieldEventState.previousEventTime:Lorg/apache/commons/math3/RealFieldElement; (8, 1)
	575 ifnull (8, 1)
	576 47 (8, 1)
	578 aload_0 (8, 1)
	579 getfield (8, 1)
	580 org/apache/commons/math3/ode/events/FieldEventState.previousEventTime:Lorg/apache/commons/math3/RealFieldElement; (8, 1)
	582 aload (8, 1)
	583 #13 (8, 1)
	584 invokeinterface (8, 1)
	585 org/apache/commons/math3/RealFieldElement.ceil:(D)D (8, 1)
	587 0 (8, 1)
	589 checkcast (8, 1)
	590 org/apache/commons/math3/RealFieldElement (8, 1)
	592 invokeinterface (8, 1)
	593 org/apache/commons/math3/RealFieldElement.org/apache/commons/math3/RealFieldElement (8, 1)
	595 0 (8, 1)
	597 checkcast (8, 1)
	598 org/apache/commons/math3/RealFieldElement (8, 1)
	600 aload_0 (8, 1)
	601 getfield (8, 1)
	602 org/apache/commons/math3/ode/events/FieldEventState.convergence:Lorg/apache/commons/math3/RealFieldElement; (8, 1)
	604 invokeinterface (8, 1)
	605 org/apache/commons/math3/RealFieldElement.ceil:(D)D (8, 1)
	607 0 (8, 1)
	609 checkcast (8, 1)
	610 org/apache/commons/math3/RealFieldElement (8, 1)
	612 invokeinterface (8, 1)
	613 org/apache/commons/math3/RealFieldElement.org/apache/commons/math3/analysis/solvers/BracketedRealFieldUnivariateSolver (8, 1)
	615 0 (8, 1)
	617 dconst_0 (8, 1)
	618 dcmpl (8, 1)
	619 ifle (8, 1)
	620 16 (8, 1)
	622 aload_0 (8, 1)
	623 aload (8, 1)
	624 #13 (8, 1)
	625 putfield (8, 1)
	626 org/apache/commons/math3/ode/events/FieldEventState.pendingEventTime:Lorg/apache/commons/math3/RealFieldElement; (8, 1)
	628 aload_0 (8, 1)
	629 iconst_1 (8, 1)
	630 putfield (8, 1)
	631 org/apache/commons/math3/ode/events/FieldEventState.pendingEvent:Z (8, 1)
	633 iconst_1 (8, 1)
	634 ireturn (8, 1)
	635 aload (10, 4)
	636 #11 (10, 4)
	637 astore (10, 4)
	638 #8 (10, 4)
	639 aload (10, 4)
	640 #12 (10, 4)
	641 astore (10, 4)
	642 #9 (10, 4)
	643 goto (9, 2)
	644 11 (9, 2)
	646 aload (10, 4)
	647 #11 (10, 4)
	648 astore (10, 4)
	649 #8 (10, 4)
	650 aload (10, 4)
	651 #12 (10, 4)
	652 astore (10, 4)
	653 #9 (10, 4)
	654 iinc (10, 4)
	655 #10 (10, 4)
	656 -89 (10, 4)
	657 goto (10, 4)
	658 -520 (10, 4)
	660 aload_0 (2, 4)
	661 iconst_0 (2, 4)
	662 putfield (2, 4)
	663 org/apache/commons/math3/ode/events/FieldEventState.pendingEvent:Z (2, 4)
	665 aload_0 (2, 4)
	666 aconst_null (2, 4)
	667 putfield (2, 4)
	668 org/apache/commons/math3/ode/events/FieldEventState.pendingEventTime:Lorg/apache/commons/math3/RealFieldElement; (2, 4)
	670 iconst_0 (2, 4)
	671 ireturn (1, 4)

Method: getEventTime
	0 aload_0 (0, 0)
	1 getfield (0, 0)
	2 org/apache/commons/math3/ode/events/FieldEventState.pendingEvent:Z (0, 0)
	4 ifeq (0, 0)
	5 10 (0, 0)
	7 aload_0 (0, 0)
	8 getfield (0, 0)
	9 org/apache/commons/math3/ode/events/FieldEventState.pendingEventTime:Lorg/apache/commons/math3/RealFieldElement; (0, 0)
	11 goto (0, 0)
	12 44 (0, 0)
	14 aload_0 (0, 0)
	15 getfield (0, 0)
	16 org/apache/commons/math3/ode/events/FieldEventState.t0:Lorg/apache/commons/math3/RealFieldElement; (0, 0)
	18 invokeinterface (1, 4)
	19 org/apache/commons/math3/RealFieldElement.org/apache/commons/math3/Field (1, 4)
	21 0 (1, 4)
	23 invokeinterface (1, 4)
	24 org/apache/commons/math3/Field.java/lang/Double (1, 4)
	26 0 (1, 4)
	28 checkcast (1, 4)
	29 org/apache/commons/math3/RealFieldElement (1, 4)
	31 aload_0 (1, 4)
	32 getfield (1, 4)
	33 org/apache/commons/math3/ode/events/FieldEventState.forward:Z (1, 4)
	35 ifeq (1, 4)
	36 9 (1, 4)
	38 ldc2_w (1, 4)
	39 inf (1, 4)
	41 goto (1, 4)
	42 6 (1, 4)
	44 ldc2_w (1, 4)
	45 -inf (1, 4)
	47 invokeinterface (1, 4)
	48 org/apache/commons/math3/RealFieldElement.getInterpolatedState:(Lorg/apache/commons/math3/RealFieldElement;)Lorg/apache/commons/math3/ode/FieldODEStateAndDerivative; (1, 4)
	50 0 (1, 4)
	52 checkcast (1, 4)
	53 org/apache/commons/math3/RealFieldElement (1, 4)
	55 areturn (0, 4)

Method: stepAccepted
	0 aload_0 (0, 0)
	1 aload_1 (0, 0)
	2 invokevirtual (0, 0)
	3 org/apache/commons/math3/ode/FieldODEStateAndDerivative.getTime:()Lorg/apache/commons/math3/RealFieldElement; (0, 0)
	5 putfield (0, 0)
	6 org/apache/commons/math3/ode/events/FieldEventState.t0:Lorg/apache/commons/math3/RealFieldElement; (0, 0)
	8 aload_0 (0, 0)
	9 aload_0 (0, 0)
	10 getfield (0, 0)
	11 org/apache/commons/math3/ode/events/FieldEventState.handler:Lorg/apache/commons/math3/ode/events/FieldEventHandler; (0, 0)
	13 aload_1 (0, 0)
	14 invokeinterface (0, 0)
	15 org/apache/commons/math3/ode/events/FieldEventHandler.getReal:()D (0, 0)
	17 0 (0, 0)
	19 putfield (0, 0)
	20 org/apache/commons/math3/ode/events/FieldEventState.g0:Lorg/apache/commons/math3/RealFieldElement; (0, 0)
	22 aload_0 (1, 1)
	23 getfield (1, 1)
	24 org/apache/commons/math3/ode/events/FieldEventState.pendingEvent:Z (1, 1)
	26 ifeq (1, 1)
	27 99 (1, 1)
	29 aload_0 (1, 1)
	30 getfield (1, 1)
	31 org/apache/commons/math3/ode/events/FieldEventState.pendingEventTime:Lorg/apache/commons/math3/RealFieldElement; (1, 1)
	33 aload_1 (1, 1)
	34 invokevirtual (1, 1)
	35 org/apache/commons/math3/ode/FieldODEStateAndDerivative.getTime:()Lorg/apache/commons/math3/RealFieldElement; (1, 1)
	37 invokeinterface (1, 1)
	38 org/apache/commons/math3/RealFieldElement.ceil:(D)D (1, 1)
	40 0 (1, 1)
	42 checkcast (1, 1)
	43 org/apache/commons/math3/RealFieldElement (1, 1)
	45 invokeinterface (1, 1)
	46 org/apache/commons/math3/RealFieldElement.org/apache/commons/math3/RealFieldElement (1, 1)
	48 0 (1, 1)
	50 checkcast (1, 1)
	51 org/apache/commons/math3/RealFieldElement (1, 1)
	53 aload_0 (1, 1)
	54 getfield (1, 1)
	55 org/apache/commons/math3/ode/events/FieldEventState.convergence:Lorg/apache/commons/math3/RealFieldElement; (1, 1)
	57 invokeinterface (1, 1)
	58 org/apache/commons/math3/RealFieldElement.ceil:(D)D (1, 1)
	60 0 (1, 1)
	62 checkcast (1, 1)
	63 org/apache/commons/math3/RealFieldElement (1, 1)
	65 invokeinterface (1, 1)
	66 org/apache/commons/math3/RealFieldElement.org/apache/commons/math3/analysis/solvers/BracketedRealFieldUnivariateSolver (1, 1)
	68 0 (1, 1)
	70 dconst_0 (1, 1)
	71 dcmpg (1, 1)
	72 ifgt (1, 1)
	73 53 (1, 1)
	75 aload_0 (2, 4)
	76 aload_1 (2, 4)
	77 invokevirtual (2, 4)
	78 org/apache/commons/math3/ode/FieldODEStateAndDerivative.getTime:()Lorg/apache/commons/math3/RealFieldElement; (2, 4)
	80 putfield (2, 4)
	81 org/apache/commons/math3/ode/events/FieldEventState.previousEventTime:Lorg/apache/commons/math3/RealFieldElement; (2, 4)
	83 aload_0 (2, 4)
	84 aload_0 (2, 4)
	85 getfield (2, 4)
	86 org/apache/commons/math3/ode/events/FieldEventState.increasing:Z (2, 4)
	88 putfield (2, 4)
	89 org/apache/commons/math3/ode/events/FieldEventState.g0Positive:Z (2, 4)
	91 aload_0 (3, 4)
	92 aload_0 (3, 4)
	93 getfield (3, 4)
	94 org/apache/commons/math3/ode/events/FieldEventState.handler:Lorg/apache/commons/math3/ode/events/FieldEventHandler; (3, 4)
	96 aload_1 (3, 4)
	97 aload_0 (3, 4)
	98 getfield (3, 4)
	99 org/apache/commons/math3/ode/events/FieldEventState.increasing:Z (3, 4)
	101 aload_0 (3, 4)
	102 getfield (3, 4)
	103 org/apache/commons/math3/ode/events/FieldEventState.forward:Z (3, 4)
	105 ixor (3, 4)
	106 ifne (3, 4)
	107 7 (3, 4)
	109 iconst_1 (3, 4)
	110 goto (3, 4)
	111 4 (3, 4)
	113 iconst_0 (3, 4)
	114 invokeinterface (3, 4)
	115 org/apache/commons/math3/ode/events/FieldEventHandler.STOP:Lorg/apache/commons/math3/ode/events/Action; (3, 4)
	117 0 (3, 4)
	119 putfield (3, 4)
	120 org/apache/commons/math3/ode/events/FieldEventState.nextAction:Lorg/apache/commons/math3/ode/events/Action; (3, 4)
	122 goto (3, 4)
	123 33 (3, 4)
	125 aload_0 (4, 2)
	126 aload_0 (4, 2)
	127 getfield (4, 2)
	128 org/apache/commons/math3/ode/events/FieldEventState.g0:Lorg/apache/commons/math3/RealFieldElement; (4, 2)
	130 invokeinterface (4, 2)
	131 org/apache/commons/math3/RealFieldElement.org/apache/commons/math3/analysis/solvers/BracketedRealFieldUnivariateSolver (4, 2)
	133 0 (4, 2)
	135 dconst_0 (4, 2)
	136 dcmpl (4, 2)
	137 iflt (4, 2)
	138 7 (4, 2)
	140 iconst_1 (4, 2)
	141 goto (4, 2)
	142 4 (4, 2)
	144 iconst_0 (4, 2)
	145 putfield (4, 2)
	146 org/apache/commons/math3/ode/events/FieldEventState.g0Positive:Z (4, 2)
	148 aload_0 (4, 2)
	149 getstatic (4, 2)
	150 org/apache/commons/math3/ode/events/Action.CONTINUE:Lorg/apache/commons/math3/ode/events/Action; (4, 2)
	152 putfield (4, 2)
	153 org/apache/commons/math3/ode/events/FieldEventState.nextAction:Lorg/apache/commons/math3/ode/events/Action; (4, 2)
	155 return (0, 0)

Method: stop
	0 aload_0 (0, 0)
	1 getfield (0, 0)
	2 org/apache/commons/math3/ode/events/FieldEventState.nextAction:Lorg/apache/commons/math3/ode/events/Action; (0, 0)
	4 getstatic (0, 0)
	5 org/apache/commons/math3/ode/events/Action.STOP:Lorg/apache/commons/math3/ode/events/Action; (0, 0)
	7 if_acmpne (0, 0)
	8 7 (0, 0)
	10 iconst_1 (0, 0)
	11 goto (0, 0)
	12 4 (0, 0)
	14 iconst_0 (0, 0)
	15 ireturn (0, 0)

Method: reset
	0 aload_0 (1, 1)
	1 getfield (1, 1)
	2 org/apache/commons/math3/ode/events/FieldEventState.pendingEvent:Z (1, 1)
	4 ifeq (1, 1)
	5 49 (1, 1)
	7 aload_0 (1, 1)
	8 getfield (1, 1)
	9 org/apache/commons/math3/ode/events/FieldEventState.pendingEventTime:Lorg/apache/commons/math3/RealFieldElement; (1, 1)
	11 aload_1 (1, 1)
	12 invokevirtual (1, 1)
	13 org/apache/commons/math3/ode/FieldODEStateAndDerivative.getTime:()Lorg/apache/commons/math3/RealFieldElement; (1, 1)
	15 invokeinterface (1, 1)
	16 org/apache/commons/math3/RealFieldElement.ceil:(D)D (1, 1)
	18 0 (1, 1)
	20 checkcast (1, 1)
	21 org/apache/commons/math3/RealFieldElement (1, 1)
	23 invokeinterface (1, 1)
	24 org/apache/commons/math3/RealFieldElement.org/apache/commons/math3/RealFieldElement (1, 1)
	26 0 (1, 1)
	28 checkcast (1, 1)
	29 org/apache/commons/math3/RealFieldElement (1, 1)
	31 aload_0 (1, 1)
	32 getfield (1, 1)
	33 org/apache/commons/math3/ode/events/FieldEventState.convergence:Lorg/apache/commons/math3/RealFieldElement; (1, 1)
	35 invokeinterface (1, 1)
	36 org/apache/commons/math3/RealFieldElement.ceil:(D)D (1, 1)
	38 0 (1, 1)
	40 checkcast (1, 1)
	41 org/apache/commons/math3/RealFieldElement (1, 1)
	43 invokeinterface (1, 1)
	44 org/apache/commons/math3/RealFieldElement.org/apache/commons/math3/analysis/solvers/BracketedRealFieldUnivariateSolver (1, 1)
	46 0 (1, 1)
	48 dconst_0 (1, 1)
	49 dcmpg (1, 1)
	50 ifle (1, 1)
	51 5 (1, 1)
	53 aconst_null (1, 1)
	54 areturn (1, 1)
	55 aload_0 (1, 1)
	56 getfield (1, 1)
	57 org/apache/commons/math3/ode/events/FieldEventState.nextAction:Lorg/apache/commons/math3/ode/events/Action; (1, 1)
	59 getstatic (1, 1)
	60 org/apache/commons/math3/ode/events/Action.RESET_STATE:Lorg/apache/commons/math3/ode/events/Action; (1, 1)
	62 if_acmpne (1, 1)
	63 17 (1, 1)
	65 aload_0 (1, 1)
	66 getfield (1, 1)
	67 org/apache/commons/math3/ode/events/FieldEventState.handler:Lorg/apache/commons/math3/ode/events/FieldEventHandler; (1, 1)
	69 aload_1 (1, 1)
	70 invokeinterface (1, 1)
	71 org/apache/commons/math3/ode/events/FieldEventHandler.RESET_DERIVATIVES:Lorg/apache/commons/math3/ode/events/Action; (1, 1)
	73 0 (1, 1)
	75 astore_2 (1, 1)
	76 goto (1, 1)
	77 20 (1, 1)
	79 aload_0 (2, 1)
	80 getfield (2, 1)
	81 org/apache/commons/math3/ode/events/FieldEventState.nextAction:Lorg/apache/commons/math3/ode/events/Action; (2, 1)
	83 getstatic (2, 1)
	84 org/apache/commons/math3/ode/events/Action.RESET_DERIVATIVES:Lorg/apache/commons/math3/ode/events/Action; (2, 1)
	86 if_acmpne (2, 1)
	87 8 (2, 1)
	89 aload_1 (2, 1)
	90 astore_2 (2, 1)
	91 goto (2, 1)
	92 5 (2, 1)
	94 aconst_null (3, 2)
	95 astore_2 (3, 2)
	96 aload_0 (0, 0)
	97 iconst_0 (0, 0)
	98 putfield (0, 0)
	99 org/apache/commons/math3/ode/events/FieldEventState.pendingEvent:Z (0, 0)
	101 aload_0 (0, 0)
	102 aconst_null (0, 0)
	103 putfield (0, 0)
	104 org/apache/commons/math3/ode/events/FieldEventState.pendingEventTime:Lorg/apache/commons/math3/RealFieldElement; (0, 0)
	106 aload_2 (0, 0)
	107 areturn (0, 0)

Method: access$000
	0 aload_0 (0, 0)
	1 getfield (0, 0)
	2 org/apache/commons/math3/ode/events/FieldEventState.handler:Lorg/apache/commons/math3/ode/events/FieldEventHandler; (0, 0)
	4 areturn (0, 0)

