Method: value
	0 aload_0 (0, 0)
	1 getfield (0, 0)
	2 org/apache/commons/math3/ode/events/FieldEventState$1.this$0:Lorg/apache/commons/math3/ode/events/FieldEventState; (0, 0)
	4 invokestatic (0, 0)
	5 org/apache/commons/math3/ode/events/FieldEventState.access$000:(Lorg/apache/commons/math3/ode/events/FieldEventState;)Lorg/apache/commons/math3/ode/events/FieldEventHandler; (0, 0)
	7 aload_0 (0, 0)
	8 getfield (0, 0)
	9 org/apache/commons/math3/ode/events/FieldEventState$1.val$interpolator:Lorg/apache/commons/math3/ode/sampling/FieldStepInterpolator; (0, 0)
	11 aload_1 (0, 0)
	12 invokeinterface (0, 0)
	13 org/apache/commons/math3/ode/sampling/FieldStepInterpolator.org/apache/commons/math3/ode/events/FieldEventHandler (0, 0)
	15 0 (0, 0)
	17 invokeinterface (0, 0)
	18 org/apache/commons/math3/ode/events/FieldEventHandler.org/apache/commons/math3/ode/events/FieldEventState$1 (0, 0)
	20 0 (0, 0)
	22 areturn (0, 0)

