Method: getTriggeredIncreasing
	0 iconst_1 (0, 0)
	1 ireturn (0, 0)

Method: selectTransformer
	0 iload (1, 1)
	1 #4 (1, 1)
	2 ifeq (1, 1)
	3 126 (1, 1)
	5 getstatic (2, 5)
	6 org/apache/commons/math3/ode/events/FilterType$3.$SwitchMap$org$apache$commons$math3$ode$events$Transformer:[I (2, 5)
	8 aload_1 (2, 5)
	9 invokevirtual (2, 5)
	10 org/apache/commons/math3/ode/events/Transformer.ordinal:()I (2, 5)
	12 iaload (2, 5)
	13 tableswitch (2, 5)
	14 1 48 (2, 5)
	18 2 72 (2, 5)
	22 3 84 (2, 5)
	26 4 96 (2, 5)
	30 5 108 (2, 5)
	48 dload_2 (3, 1)
	49 dconst_0 (3, 1)
	50 dcmpl (3, 1)
	51 ifle (3, 1)
	52 7 (3, 1)
	54 getstatic (5, 4)
	55 org/apache/commons/math3/ode/events/Transformer.PLUS:Lorg/apache/commons/math3/ode/events/Transformer; (5, 4)
	57 areturn (5, 4)
	58 dload_2 (6, 1)
	59 dconst_0 (6, 1)
	60 dcmpg (6, 1)
	61 ifge (6, 1)
	62 7 (6, 1)
	64 getstatic (8, 4)
	65 org/apache/commons/math3/ode/events/Transformer.MIN:Lorg/apache/commons/math3/ode/events/Transformer; (8, 4)
	67 areturn (8, 4)
	68 getstatic (11, 4)
	69 org/apache/commons/math3/ode/events/Transformer.UNINITIALIZED:Lorg/apache/commons/math3/ode/events/Transformer; (11, 4)
	71 areturn (11, 4)
	72 dload_2 (3, 1)
	73 dconst_0 (3, 1)
	74 dcmpg (3, 1)
	75 ifgt (3, 1)
	76 7 (3, 1)
	78 getstatic (5, 4)
	79 org/apache/commons/math3/ode/events/Transformer.MAX:Lorg/apache/commons/math3/ode/events/Transformer; (5, 4)
	81 areturn (5, 4)
	82 aload_1 (6, 2)
	83 areturn (6, 2)
	84 dload_2 (3, 1)
	85 dconst_0 (3, 1)
	86 dcmpg (3, 1)
	87 ifgt (3, 1)
	88 7 (3, 1)
	90 getstatic (5, 4)
	91 org/apache/commons/math3/ode/events/Transformer.MIN:Lorg/apache/commons/math3/ode/events/Transformer; (5, 4)
	93 areturn (5, 4)
	94 aload_1 (6, 2)
	95 areturn (6, 2)
	96 dload_2 (3, 1)
	97 dconst_0 (3, 1)
	98 dcmpl (3, 1)
	99 iflt (3, 1)
	100 7 (3, 1)
	102 getstatic (5, 4)
	103 org/apache/commons/math3/ode/events/Transformer.PLUS:Lorg/apache/commons/math3/ode/events/Transformer; (5, 4)
	105 areturn (5, 4)
	106 aload_1 (6, 2)
	107 areturn (6, 2)
	108 dload_2 (3, 1)
	109 dconst_0 (3, 1)
	110 dcmpl (3, 1)
	111 iflt (3, 1)
	112 7 (3, 1)
	114 getstatic (5, 4)
	115 org/apache/commons/math3/ode/events/Transformer.MINUS:Lorg/apache/commons/math3/ode/events/Transformer; (5, 4)
	117 areturn (5, 4)
	118 aload_1 (6, 2)
	119 areturn (6, 2)
	120 new (2, 5)
	121 org/apache/commons/math3/exception/MathInternalError (2, 5)
	123 dup (2, 5)
	124 invokespecial (2, 5)
	125 org/apache/commons/math3/exception/MathInternalError.<init>:()V (2, 5)
	127 athrow (2, 5)
	128 getstatic (3, 5)
	129 org/apache/commons/math3/ode/events/FilterType$3.$SwitchMap$org$apache$commons$math3$ode$events$Transformer:[I (3, 5)
	131 aload_1 (3, 5)
	132 invokevirtual (3, 5)
	133 org/apache/commons/math3/ode/events/Transformer.ordinal:()I (3, 5)
	135 iaload (3, 5)
	136 tableswitch (3, 5)
	137 1 172 (3, 5)
	141 2 196 (3, 5)
	145 3 208 (3, 5)
	149 4 220 (3, 5)
	153 5 232 (3, 5)
	172 dload_2 (4, 1)
	173 dconst_0 (4, 1)
	174 dcmpl (4, 1)
	175 ifle (4, 1)
	176 7 (4, 1)
	178 getstatic (6, 4)
	179 org/apache/commons/math3/ode/events/Transformer.MAX:Lorg/apache/commons/math3/ode/events/Transformer; (6, 4)
	181 areturn (6, 4)
	182 dload_2 (7, 1)
	183 dconst_0 (7, 1)
	184 dcmpg (7, 1)
	185 ifge (7, 1)
	186 7 (7, 1)
	188 getstatic (9, 4)
	189 org/apache/commons/math3/ode/events/Transformer.MINUS:Lorg/apache/commons/math3/ode/events/Transformer; (9, 4)
	191 areturn (9, 4)
	192 getstatic (12, 4)
	193 org/apache/commons/math3/ode/events/Transformer.UNINITIALIZED:Lorg/apache/commons/math3/ode/events/Transformer; (12, 4)
	195 areturn (12, 4)
	196 dload_2 (4, 1)
	197 dconst_0 (4, 1)
	198 dcmpl (4, 1)
	199 iflt (4, 1)
	200 7 (4, 1)
	202 getstatic (6, 4)
	203 org/apache/commons/math3/ode/events/Transformer.MIN:Lorg/apache/commons/math3/ode/events/Transformer; (6, 4)
	205 areturn (6, 4)
	206 aload_1 (7, 2)
	207 areturn (7, 2)
	208 dload_2 (4, 1)
	209 dconst_0 (4, 1)
	210 dcmpl (4, 1)
	211 iflt (4, 1)
	212 7 (4, 1)
	214 getstatic (6, 4)
	215 org/apache/commons/math3/ode/events/Transformer.MAX:Lorg/apache/commons/math3/ode/events/Transformer; (6, 4)
	217 areturn (6, 4)
	218 aload_1 (7, 2)
	219 areturn (7, 2)
	220 dload_2 (4, 1)
	221 dconst_0 (4, 1)
	222 dcmpg (4, 1)
	223 ifgt (4, 1)
	224 7 (4, 1)
	226 getstatic (6, 4)
	227 org/apache/commons/math3/ode/events/Transformer.MINUS:Lorg/apache/commons/math3/ode/events/Transformer; (6, 4)
	229 areturn (6, 4)
	230 aload_1 (7, 2)
	231 areturn (7, 2)
	232 dload_2 (4, 1)
	233 dconst_0 (4, 1)
	234 dcmpg (4, 1)
	235 ifgt (4, 1)
	236 7 (4, 1)
	238 getstatic (6, 4)
	239 org/apache/commons/math3/ode/events/Transformer.PLUS:Lorg/apache/commons/math3/ode/events/Transformer; (6, 4)
	241 areturn (6, 4)
	242 aload_1 (7, 2)
	243 areturn (7, 2)
	244 new (3, 5)
	245 org/apache/commons/math3/exception/MathInternalError (3, 5)
	247 dup (3, 5)
	248 invokespecial (3, 5)
	249 org/apache/commons/math3/exception/MathInternalError.<init>:()V (3, 5)
	251 athrow (2, 5)

