Method: <clinit>
	0 invokestatic (1, 5)
	1 org/apache/commons/math3/ode/events/Transformer.values:()[Lorg/apache/commons/math3/ode/events/Transformer; (1, 5)
	3 arraylength (1, 5)
	4 newarray (1, 5)
	5 10 (1, 5)
	6 putstatic (1, 5)
	7 org/apache/commons/math3/ode/events/FilterType$3.$SwitchMap$org$apache$commons$math3$ode$events$Transformer:[I (1, 5)
	9 getstatic (1, 5)
	10 org/apache/commons/math3/ode/events/FilterType$3.$SwitchMap$org$apache$commons$math3$ode$events$Transformer:[I (1, 5)
	12 getstatic (1, 5)
	13 org/apache/commons/math3/ode/events/Transformer.UNINITIALIZED:Lorg/apache/commons/math3/ode/events/Transformer; (1, 5)
	15 invokevirtual (1, 5)
	16 org/apache/commons/math3/ode/events/Transformer.ordinal:()I (1, 5)
	18 iconst_1 (1, 5)
	19 iastore (1, 5)
	20 goto (1, 5)
	21 4 (1, 5)
	23 astore_0 (1, 5)
	24 getstatic (1, 5)
	25 org/apache/commons/math3/ode/events/FilterType$3.$SwitchMap$org$apache$commons$math3$ode$events$Transformer:[I (1, 5)
	27 getstatic (1, 5)
	28 org/apache/commons/math3/ode/events/Transformer.PLUS:Lorg/apache/commons/math3/ode/events/Transformer; (1, 5)
	30 invokevirtual (1, 5)
	31 org/apache/commons/math3/ode/events/Transformer.ordinal:()I (1, 5)
	33 iconst_2 (1, 5)
	34 iastore (1, 5)
	35 goto (1, 5)
	36 4 (1, 5)
	38 astore_0 (1, 5)
	39 getstatic (1, 5)
	40 org/apache/commons/math3/ode/events/FilterType$3.$SwitchMap$org$apache$commons$math3$ode$events$Transformer:[I (1, 5)
	42 getstatic (1, 5)
	43 org/apache/commons/math3/ode/events/Transformer.MINUS:Lorg/apache/commons/math3/ode/events/Transformer; (1, 5)
	45 invokevirtual (1, 5)
	46 org/apache/commons/math3/ode/events/Transformer.ordinal:()I (1, 5)
	48 iconst_3 (1, 5)
	49 iastore (1, 5)
	50 goto (1, 5)
	51 4 (1, 5)
	53 astore_0 (1, 5)
	54 getstatic (1, 5)
	55 org/apache/commons/math3/ode/events/FilterType$3.$SwitchMap$org$apache$commons$math3$ode$events$Transformer:[I (1, 5)
	57 getstatic (1, 5)
	58 org/apache/commons/math3/ode/events/Transformer.MIN:Lorg/apache/commons/math3/ode/events/Transformer; (1, 5)
	60 invokevirtual (1, 5)
	61 org/apache/commons/math3/ode/events/Transformer.ordinal:()I (1, 5)
	63 iconst_4 (1, 5)
	64 iastore (1, 5)
	65 goto (1, 5)
	66 4 (1, 5)
	68 astore_0 (1, 5)
	69 getstatic (1, 5)
	70 org/apache/commons/math3/ode/events/FilterType$3.$SwitchMap$org$apache$commons$math3$ode$events$Transformer:[I (1, 5)
	72 getstatic (1, 5)
	73 org/apache/commons/math3/ode/events/Transformer.MAX:Lorg/apache/commons/math3/ode/events/Transformer; (1, 5)
	75 invokevirtual (1, 5)
	76 org/apache/commons/math3/ode/events/Transformer.ordinal:()I (1, 5)
	78 iconst_5 (1, 5)
	79 iastore (1, 5)
	80 goto (1, 5)
	81 4 (1, 5)
	83 astore_0 (1, 5)
	84 return (1, 5)

