Method: values
	0 getstatic (1, 4)
	1 org/apache/commons/math3/ode/events/Transformer.$VALUES:[Lorg/apache/commons/math3/ode/events/Transformer; (1, 4)
	3 invokevirtual (1, 4)
	4 [Lorg/apache/commons/math3/ode/events/Transformer;.clone:()Ljava/lang/Object; (1, 4)
	6 checkcast (1, 4)
	7 [Lorg/apache/commons/math3/ode/events/Transformer; (1, 4)
	9 areturn (1, 4)

Method: valueOf
	0 ldc (1, 4)
	1 org/apache/commons/math3/ode/events/Transformer (1, 4)
	2 aload_0 (1, 4)
	3 invokestatic (1, 4)
	4 java/lang/Enum.valueOf:(Ljava/lang/Class;Ljava/lang/String;)Ljava/lang/Enum; (1, 4)
	6 checkcast (1, 4)
	7 org/apache/commons/math3/ode/events/Transformer (1, 4)
	9 areturn (1, 4)

Method: <clinit>
	0 new (0, 0)
	1 org/apache/commons/math3/ode/events/Transformer$1 (0, 0)
	3 dup (0, 0)
	4 ldc (0, 0)
	5 UNINITIALIZED (0, 0)
	6 iconst_0 (0, 0)
	7 invokespecial (0, 0)
	8 org/apache/commons/math3/ode/events/Transformer$1.<init>:(Ljava/lang/String;I)V (0, 0)
	10 putstatic (0, 0)
	11 org/apache/commons/math3/ode/events/Transformer.UNINITIALIZED:Lorg/apache/commons/math3/ode/events/Transformer; (0, 0)
	13 new (2, 4)
	14 org/apache/commons/math3/ode/events/Transformer$2 (2, 4)
	16 dup (2, 4)
	17 ldc (2, 4)
	18 PLUS (2, 4)
	19 iconst_1 (2, 4)
	20 invokespecial (2, 4)
	21 org/apache/commons/math3/ode/events/Transformer$2.<init>:(Ljava/lang/String;I)V (2, 4)
	23 putstatic (2, 4)
	24 org/apache/commons/math3/ode/events/Transformer.PLUS:Lorg/apache/commons/math3/ode/events/Transformer; (2, 4)
	26 new (4, 4)
	27 org/apache/commons/math3/ode/events/Transformer$3 (4, 4)
	29 dup (4, 4)
	30 ldc (4, 4)
	31 MINUS (4, 4)
	32 iconst_2 (4, 4)
	33 invokespecial (4, 4)
	34 org/apache/commons/math3/ode/events/Transformer$3.<init>:(Ljava/lang/String;I)V (4, 4)
	36 putstatic (4, 4)
	37 org/apache/commons/math3/ode/events/Transformer.MINUS:Lorg/apache/commons/math3/ode/events/Transformer; (4, 4)
	39 new (6, 4)
	40 org/apache/commons/math3/ode/events/Transformer$4 (6, 4)
	42 dup (6, 4)
	43 ldc (6, 4)
	44 MIN (6, 4)
	45 iconst_3 (6, 4)
	46 invokespecial (6, 4)
	47 org/apache/commons/math3/ode/events/Transformer$4.<init>:(Ljava/lang/String;I)V (6, 4)
	49 putstatic (6, 4)
	50 org/apache/commons/math3/ode/events/Transformer.MIN:Lorg/apache/commons/math3/ode/events/Transformer; (6, 4)
	52 new (8, 4)
	53 org/apache/commons/math3/ode/events/Transformer$5 (8, 4)
	55 dup (8, 4)
	56 ldc (8, 4)
	57 MAX (8, 4)
	58 iconst_4 (8, 4)
	59 invokespecial (8, 4)
	60 org/apache/commons/math3/ode/events/Transformer$5.<init>:(Ljava/lang/String;I)V (8, 4)
	62 putstatic (8, 4)
	63 org/apache/commons/math3/ode/events/Transformer.MAX:Lorg/apache/commons/math3/ode/events/Transformer; (8, 4)
	65 iconst_5 (8, 4)
	66 anewarray (8, 4)
	67 org/apache/commons/math3/ode/events/Transformer (8, 4)
	69 dup (8, 4)
	70 iconst_0 (8, 4)
	71 getstatic (8, 4)
	72 org/apache/commons/math3/ode/events/Transformer.UNINITIALIZED:Lorg/apache/commons/math3/ode/events/Transformer; (8, 4)
	74 aastore (8, 4)
	75 dup (8, 4)
	76 iconst_1 (8, 4)
	77 getstatic (8, 4)
	78 org/apache/commons/math3/ode/events/Transformer.PLUS:Lorg/apache/commons/math3/ode/events/Transformer; (8, 4)
	80 aastore (8, 4)
	81 dup (8, 4)
	82 iconst_2 (8, 4)
	83 getstatic (8, 4)
	84 org/apache/commons/math3/ode/events/Transformer.MINUS:Lorg/apache/commons/math3/ode/events/Transformer; (8, 4)
	86 aastore (8, 4)
	87 dup (8, 4)
	88 iconst_3 (8, 4)
	89 getstatic (8, 4)
	90 org/apache/commons/math3/ode/events/Transformer.MIN:Lorg/apache/commons/math3/ode/events/Transformer; (8, 4)
	92 aastore (8, 4)
	93 dup (8, 4)
	94 iconst_4 (8, 4)
	95 getstatic (8, 4)
	96 org/apache/commons/math3/ode/events/Transformer.MAX:Lorg/apache/commons/math3/ode/events/Transformer; (8, 4)
	98 aastore (8, 4)
	99 putstatic (8, 4)
	100 org/apache/commons/math3/ode/events/Transformer.$VALUES:[Lorg/apache/commons/math3/ode/events/Transformer; (8, 4)
	102 return (0, 4)

