Method: <init>
	0 aload_0 (0, 0)
	1 invokespecial (0, 0)
	2 java/lang/Object.<init>:()V (0, 0)
	4 aload_0 (0, 0)
	5 aload (0, 0)
	6 #5 (0, 0)
	7 arraylength (0, 0)
	8 putfield (0, 0)
	9 org/apache/commons/math3/ml/neuralnet/twod/NeuronSquareMesh2D.numberOfRows:I (0, 0)
	11 aload_0 (0, 0)
	12 aload (0, 0)
	13 #5 (0, 0)
	14 iconst_0 (0, 0)
	15 aaload (0, 0)
	16 arraylength (0, 0)
	17 putfield (0, 0)
	18 org/apache/commons/math3/ml/neuralnet/twod/NeuronSquareMesh2D.numberOfColumns:I (0, 0)
	20 aload_0 (0, 0)
	21 iload_1 (0, 0)
	22 putfield (0, 0)
	23 org/apache/commons/math3/ml/neuralnet/twod/NeuronSquareMesh2D.wrapRows:Z (0, 0)
	25 aload_0 (0, 0)
	26 iload_2 (0, 0)
	27 putfield (0, 0)
	28 org/apache/commons/math3/ml/neuralnet/twod/NeuronSquareMesh2D.wrapColumns:Z (0, 0)
	30 aload_0 (0, 0)
	31 aload_3 (0, 0)
	32 putfield (0, 0)
	33 org/apache/commons/math3/ml/neuralnet/twod/NeuronSquareMesh2D.neighbourhood:Lorg/apache/commons/math3/ml/neuralnet/SquareNeighbourhood; (0, 0)
	35 aload_0 (0, 0)
	36 aload (0, 0)
	37 #4 (0, 0)
	38 putfield (0, 0)
	39 org/apache/commons/math3/ml/neuralnet/twod/NeuronSquareMesh2D.network:Lorg/apache/commons/math3/ml/neuralnet/Network; (0, 0)
	41 aload_0 (1, 1)
	42 aload (1, 1)
	43 #5 (1, 1)
	44 putfield (1, 1)
	45 org/apache/commons/math3/ml/neuralnet/twod/NeuronSquareMesh2D.identifiers:[[J (1, 1)
	47 return (0, 0)

Method: copy
	0 aload_0 (0, 0)
	1 getfield (0, 0)
	2 org/apache/commons/math3/ml/neuralnet/twod/NeuronSquareMesh2D.numberOfRows:I (0, 0)
	4 aload_0 (0, 0)
	5 getfield (0, 0)
	6 org/apache/commons/math3/ml/neuralnet/twod/NeuronSquareMesh2D.numberOfColumns:I (0, 0)
	8 multianewarray (0, 0)
	9 [[J (0, 0)
	11 76 (0, 0)
	12 astore_1 (0, 0)
	13 iconst_0 (1, 4)
	14 istore_2 (1, 4)
	15 iload_2 (1, 4)
	16 aload_0 (1, 4)
	17 getfield (1, 4)
	18 org/apache/commons/math3/ml/neuralnet/twod/NeuronSquareMesh2D.numberOfRows:I (1, 4)
	20 if_icmpge (1, 4)
	21 38 (1, 4)
	23 iconst_0 (2, 4)
	24 istore_3 (2, 4)
	25 iload_3 (2, 4)
	26 aload_0 (2, 4)
	27 getfield (2, 4)
	28 org/apache/commons/math3/ml/neuralnet/twod/NeuronSquareMesh2D.numberOfColumns:I (2, 4)
	30 if_icmpge (2, 4)
	31 22 (2, 4)
	33 aload_1 (3, 1)
	34 iload_2 (3, 1)
	35 aaload (3, 1)
	36 iload_3 (3, 1)
	37 aload_0 (3, 1)
	38 getfield (3, 1)
	39 org/apache/commons/math3/ml/neuralnet/twod/NeuronSquareMesh2D.identifiers:[[J (3, 1)
	41 iload_2 (3, 1)
	42 aaload (3, 1)
	43 iload_3 (3, 1)
	44 laload (3, 1)
	45 lastore (3, 1)
	46 iinc (3, 1)
	47 #3 (3, 1)
	48 -89 (3, 1)
	49 goto (3, 1)
	50 -24 (3, 1)
	52 iinc (3, 1)
	53 #2 (3, 1)
	54 -89 (3, 1)
	55 goto (3, 1)
	56 -40 (3, 1)
	58 new (1, 4)
	59 org/apache/commons/math3/ml/neuralnet/twod/NeuronSquareMesh2D (1, 4)
	61 dup (1, 4)
	62 aload_0 (1, 4)
	63 getfield (1, 4)
	64 org/apache/commons/math3/ml/neuralnet/twod/NeuronSquareMesh2D.wrapRows:Z (1, 4)
	66 aload_0 (1, 4)
	67 getfield (1, 4)
	68 org/apache/commons/math3/ml/neuralnet/twod/NeuronSquareMesh2D.wrapColumns:Z (1, 4)
	70 aload_0 (1, 4)
	71 getfield (1, 4)
	72 org/apache/commons/math3/ml/neuralnet/twod/NeuronSquareMesh2D.neighbourhood:Lorg/apache/commons/math3/ml/neuralnet/SquareNeighbourhood; (1, 4)
	74 aload_0 (1, 4)
	75 getfield (1, 4)
	76 org/apache/commons/math3/ml/neuralnet/twod/NeuronSquareMesh2D.network:Lorg/apache/commons/math3/ml/neuralnet/Network; (1, 4)
	78 invokevirtual (1, 4)
	79 org/apache/commons/math3/ml/neuralnet/Network.copy:()Lorg/apache/commons/math3/ml/neuralnet/Network; (1, 4)
	81 aload_1 (1, 4)
	82 invokespecial (1, 4)
	83 org/apache/commons/math3/ml/neuralnet/twod/NeuronSquareMesh2D.<init>:(ZZLorg/apache/commons/math3/ml/neuralnet/SquareNeighbourhood;Lorg/apache/commons/math3/ml/neuralnet/Network;[[J)V (1, 4)
	85 areturn (1, 4)

Method: iterator
	0 aload_0 (0, 0)
	1 getfield (0, 0)
	2 org/apache/commons/math3/ml/neuralnet/twod/NeuronSquareMesh2D.network:Lorg/apache/commons/math3/ml/neuralnet/Network; (0, 0)
	4 invokevirtual (0, 0)
	5 org/apache/commons/math3/ml/neuralnet/Network.iterator:()Ljava/util/Iterator; (0, 0)
	7 areturn (0, 0)

Method: getNetwork
	0 aload_0 (0, 0)
	1 getfield (0, 0)
	2 org/apache/commons/math3/ml/neuralnet/twod/NeuronSquareMesh2D.network:Lorg/apache/commons/math3/ml/neuralnet/Network; (0, 0)
	4 areturn (0, 0)

Method: getNumberOfRows
	0 aload_0 (0, 0)
	1 getfield (0, 0)
	2 org/apache/commons/math3/ml/neuralnet/twod/NeuronSquareMesh2D.numberOfRows:I (0, 0)
	4 ireturn (0, 0)

Method: getNumberOfColumns
	0 aload_0 (0, 0)
	1 getfield (0, 0)
	2 org/apache/commons/math3/ml/neuralnet/twod/NeuronSquareMesh2D.numberOfColumns:I (0, 0)
	4 ireturn (0, 0)

Method: getNeuron
	0 aload_0 (0, 0)
	1 iload_1 (0, 0)
	2 iload_2 (0, 0)
	3 aload_3 (0, 0)
	4 aload (0, 0)
	5 #4 (0, 0)
	6 invokespecial (0, 0)
	7 org/apache/commons/math3/ml/neuralnet/twod/NeuronSquareMesh2D.getLocation:(IILorg/apache/commons/math3/ml/neuralnet/twod/NeuronSquareMesh2D$HorizontalDirection;Lorg/apache/commons/math3/ml/neuralnet/twod/NeuronSquareMesh2D$VerticalDirection;)[I (0, 0)
	9 astore (0, 0)
	10 #5 (0, 0)
	11 aload (0, 0)
	12 #5 (0, 0)
	13 ifnonnull (0, 0)
	14 7 (0, 0)
	16 aconst_null (0, 0)
	17 goto (0, 0)
	18 15 (0, 0)
	20 aload_0 (0, 0)
	21 aload (0, 0)
	22 #5 (0, 0)
	23 iconst_0 (0, 0)
	24 iaload (0, 0)
	25 aload (0, 0)
	26 #5 (0, 0)
	27 iconst_1 (0, 0)
	28 iaload (0, 0)
	29 invokevirtual (0, 0)
	30 org/apache/commons/math3/ml/neuralnet/twod/NeuronSquareMesh2D.getNeuron:(II)Lorg/apache/commons/math3/ml/neuralnet/Neuron; (0, 0)
	32 areturn (0, 0)

Method: getLocation
	0 getstatic (1, 5)
	1 org/apache/commons/math3/ml/neuralnet/twod/NeuronSquareMesh2D$1.$SwitchMap$org$apache$commons$math3$ml$neuralnet$twod$NeuronSquareMesh2D$HorizontalDirection:[I (1, 5)
	3 aload_3 (1, 5)
	4 invokevirtual (1, 5)
	5 org/apache/commons/math3/ml/neuralnet/twod/NeuronSquareMesh2D$HorizontalDirection.ordinal:()I (1, 5)
	7 iaload (1, 5)
	8 tableswitch (1, 5)
	9 1 36 (1, 5)
	13 2 42 (1, 5)
	17 3 48 (1, 5)
	36 iconst_m1 (1, 5)
	37 istore (1, 5)
	38 #5 (1, 5)
	39 goto (1, 5)
	40 23 (1, 5)
	42 iconst_1 (1, 5)
	43 istore (1, 5)
	44 #5 (1, 5)
	45 goto (1, 5)
	46 17 (1, 5)
	48 iconst_0 (1, 5)
	49 istore (1, 5)
	50 #5 (1, 5)
	51 goto (1, 5)
	52 11 (1, 5)
	54 new (1, 5)
	55 org/apache/commons/math3/exception/MathInternalError (1, 5)
	57 dup (1, 5)
	58 invokespecial (1, 5)
	59 org/apache/commons/math3/exception/MathInternalError.<init>:()V (1, 5)
	61 athrow (1, 5)
	62 iload_2 (0, 0)
	63 iload (0, 0)
	64 #5 (0, 0)
	65 iadd (0, 0)
	66 istore (0, 0)
	67 #6 (0, 0)
	68 aload_0 (1, 1)
	69 getfield (1, 1)
	70 org/apache/commons/math3/ml/neuralnet/twod/NeuronSquareMesh2D.wrapColumns:Z (1, 1)
	72 ifeq (1, 1)
	73 29 (1, 1)
	75 iload (2, 1)
	76 #6 (2, 1)
	77 ifge (2, 1)
	78 15 (2, 1)
	80 iload (2, 1)
	81 #6 (2, 1)
	82 aload_0 (2, 1)
	83 getfield (2, 1)
	84 org/apache/commons/math3/ml/neuralnet/twod/NeuronSquareMesh2D.numberOfColumns:I (2, 1)
	86 iadd (2, 1)
	87 istore (2, 1)
	88 #6 (2, 1)
	89 goto (2, 1)
	90 12 (2, 1)
	92 iload (3, 2)
	93 #6 (3, 2)
	94 aload_0 (3, 2)
	95 getfield (3, 2)
	96 org/apache/commons/math3/ml/neuralnet/twod/NeuronSquareMesh2D.numberOfColumns:I (3, 2)
	98 irem (3, 2)
	99 istore (3, 2)
	100 #6 (3, 2)
	101 getstatic (1, 5)
	102 org/apache/commons/math3/ml/neuralnet/twod/NeuronSquareMesh2D$1.$SwitchMap$org$apache$commons$math3$ml$neuralnet$twod$NeuronSquareMesh2D$VerticalDirection:[I (1, 5)
	104 aload (1, 5)
	105 #4 (1, 5)
	106 invokevirtual (1, 5)
	107 org/apache/commons/math3/ml/neuralnet/twod/NeuronSquareMesh2D$VerticalDirection.ordinal:()I (1, 5)
	109 iaload (1, 5)
	110 tableswitch (1, 5)
	111 1 136 (1, 5)
	115 2 142 (1, 5)
	119 3 148 (1, 5)
	136 iconst_m1 (1, 5)
	137 istore (1, 5)
	138 #7 (1, 5)
	139 goto (1, 5)
	140 23 (1, 5)
	142 iconst_1 (1, 5)
	143 istore (1, 5)
	144 #7 (1, 5)
	145 goto (1, 5)
	146 17 (1, 5)
	148 iconst_0 (1, 5)
	149 istore (1, 5)
	150 #7 (1, 5)
	151 goto (1, 5)
	152 11 (1, 5)
	154 new (1, 5)
	155 org/apache/commons/math3/exception/MathInternalError (1, 5)
	157 dup (1, 5)
	158 invokespecial (1, 5)
	159 org/apache/commons/math3/exception/MathInternalError.<init>:()V (1, 5)
	161 athrow (1, 5)
	162 iload_1 (0, 0)
	163 iload (0, 0)
	164 #7 (0, 0)
	165 iadd (0, 0)
	166 istore (0, 0)
	167 #8 (0, 0)
	168 aload_0 (1, 1)
	169 getfield (1, 1)
	170 org/apache/commons/math3/ml/neuralnet/twod/NeuronSquareMesh2D.wrapRows:Z (1, 1)
	172 ifeq (1, 1)
	173 29 (1, 1)
	175 iload (2, 1)
	176 #8 (2, 1)
	177 ifge (2, 1)
	178 15 (2, 1)
	180 iload (2, 1)
	181 #8 (2, 1)
	182 aload_0 (2, 1)
	183 getfield (2, 1)
	184 org/apache/commons/math3/ml/neuralnet/twod/NeuronSquareMesh2D.numberOfRows:I (2, 1)
	186 iadd (2, 1)
	187 istore (2, 1)
	188 #8 (2, 1)
	189 goto (2, 1)
	190 12 (2, 1)
	192 iload (3, 2)
	193 #8 (3, 2)
	194 aload_0 (3, 2)
	195 getfield (3, 2)
	196 org/apache/commons/math3/ml/neuralnet/twod/NeuronSquareMesh2D.numberOfRows:I (3, 2)
	198 irem (3, 2)
	199 istore (3, 2)
	200 #8 (3, 2)
	201 iload (1, 1)
	202 #8 (1, 1)
	203 iflt (1, 1)
	204 26 (1, 1)
	206 iload (1, 1)
	207 #8 (1, 1)
	208 aload_0 (1, 1)
	209 getfield (1, 1)
	210 org/apache/commons/math3/ml/neuralnet/twod/NeuronSquareMesh2D.numberOfRows:I (1, 1)
	212 if_icmpge (1, 1)
	213 17 (1, 1)
	215 iload (1, 1)
	216 #6 (1, 1)
	217 iflt (1, 1)
	218 12 (1, 1)
	220 iload (1, 1)
	221 #6 (1, 1)
	222 aload_0 (1, 1)
	223 getfield (1, 1)
	224 org/apache/commons/math3/ml/neuralnet/twod/NeuronSquareMesh2D.numberOfColumns:I (1, 1)
	226 if_icmplt (1, 1)
	227 5 (1, 1)
	229 aconst_null (1, 1)
	230 areturn (1, 1)
	231 iconst_2 (2, 2)
	232 newarray (2, 2)
	233 10 (2, 2)
	234 dup (2, 2)
	235 iconst_0 (2, 2)
	236 iload (2, 2)
	237 #8 (2, 2)
	238 iastore (2, 2)
	239 dup (2, 2)
	240 iconst_1 (2, 2)
	241 iload (2, 2)
	242 #6 (2, 2)
	243 iastore (2, 2)
	244 areturn (1, 2)

Method: createLinks
	0 new (0, 0)
	1 java/util/ArrayList (0, 0)
	3 dup (0, 0)
	4 invokespecial (0, 0)
	5 java/util/ArrayList.<init>:()V (0, 0)
	7 astore_1 (0, 0)
	8 aload_0 (0, 0)
	9 getfield (0, 0)
	10 org/apache/commons/math3/ml/neuralnet/twod/NeuronSquareMesh2D.numberOfRows:I (0, 0)
	12 iconst_1 (0, 0)
	13 isub (0, 0)
	14 istore_2 (0, 0)
	15 aload_0 (0, 0)
	16 getfield (0, 0)
	17 org/apache/commons/math3/ml/neuralnet/twod/NeuronSquareMesh2D.numberOfColumns:I (0, 0)
	19 iconst_1 (0, 0)
	20 isub (0, 0)
	21 istore_3 (0, 0)
	22 iconst_0 (1, 4)
	23 istore (1, 4)
	24 #4 (1, 4)
	25 iload (1, 4)
	26 #4 (1, 4)
	27 aload_0 (1, 4)
	28 getfield (1, 4)
	29 org/apache/commons/math3/ml/neuralnet/twod/NeuronSquareMesh2D.numberOfRows:I (1, 4)
	31 if_icmpge (1, 4)
	32 907 (1, 4)
	34 iconst_0 (2, 4)
	35 istore (2, 4)
	36 #5 (2, 4)
	37 iload (2, 4)
	38 #5 (2, 4)
	39 aload_0 (2, 4)
	40 getfield (2, 4)
	41 org/apache/commons/math3/ml/neuralnet/twod/NeuronSquareMesh2D.numberOfColumns:I (2, 4)
	43 if_icmpge (2, 4)
	44 889 (2, 4)
	46 aload_1 (2, 4)
	47 invokeinterface (2, 4)
	48 java/util/List.$SwitchMap$org$apache$commons$math3$ml$neuralnet$SquareNeighbourhood:[I (2, 4)
	50 0 (2, 4)
	52 getstatic (3, 5)
	53 org/apache/commons/math3/ml/neuralnet/twod/NeuronSquareMesh2D$1.$SwitchMap$org$apache$commons$math3$ml$neuralnet$SquareNeighbourhood:[I (3, 5)
	55 aload_0 (3, 5)
	56 getfield (3, 5)
	57 org/apache/commons/math3/ml/neuralnet/twod/NeuronSquareMesh2D.neighbourhood:Lorg/apache/commons/math3/ml/neuralnet/SquareNeighbourhood; (3, 5)
	59 invokevirtual (3, 5)
	60 org/apache/commons/math3/ml/neuralnet/SquareNeighbourhood.ordinal:()I (3, 5)
	62 iaload (3, 5)
	63 lookupswitch (3, 5)
	64 1: 88 (3, 5)
	68 2: 610 (3, 5)
	88 iload (4, 1)
	89 #4 (4, 1)
	90 ifle (4, 1)
	91 62 (4, 1)
	93 iload (5, 1)
	94 #5 (5, 1)
	95 ifle (5, 1)
	96 27 (5, 1)
	98 aload_1 (6, 1)
	99 aload_0 (6, 1)
	100 getfield (6, 1)
	101 org/apache/commons/math3/ml/neuralnet/twod/NeuronSquareMesh2D.identifiers:[[J (6, 1)
	103 iload (6, 1)
	104 #4 (6, 1)
	105 iconst_1 (6, 1)
	106 isub (6, 1)
	107 aaload (6, 1)
	108 iload (6, 1)
	109 #5 (6, 1)
	110 iconst_1 (6, 1)
	111 isub (6, 1)
	112 laload (6, 1)
	113 invokestatic (6, 1)
	114 java/lang/Long.valueOf:(J)Ljava/lang/Long; (6, 1)
	116 invokeinterface (6, 1)
	117 java/util/List.java/util/Iterator (6, 1)
	119 0 (6, 1)
	121 pop (6, 1)
	122 iload (5, 1)
	123 #5 (5, 1)
	124 iload_3 (5, 1)
	125 if_icmpge (5, 1)
	126 27 (5, 1)
	128 aload_1 (6, 1)
	129 aload_0 (6, 1)
	130 getfield (6, 1)
	131 org/apache/commons/math3/ml/neuralnet/twod/NeuronSquareMesh2D.identifiers:[[J (6, 1)
	133 iload (6, 1)
	134 #4 (6, 1)
	135 iconst_1 (6, 1)
	136 isub (6, 1)
	137 aaload (6, 1)
	138 iload (6, 1)
	139 #5 (6, 1)
	140 iconst_1 (6, 1)
	141 iadd (6, 1)
	142 laload (6, 1)
	143 invokestatic (6, 1)
	144 java/lang/Long.valueOf:(J)Ljava/lang/Long; (6, 1)
	146 invokeinterface (6, 1)
	147 java/util/List.java/util/Iterator (6, 1)
	149 0 (6, 1)
	151 pop (6, 1)
	152 iload (4, 1)
	153 #4 (4, 1)
	154 iload_2 (4, 1)
	155 if_icmpge (4, 1)
	156 62 (4, 1)
	158 iload (5, 1)
	159 #5 (5, 1)
	160 ifle (5, 1)
	161 27 (5, 1)
	163 aload_1 (6, 1)
	164 aload_0 (6, 1)
	165 getfield (6, 1)
	166 org/apache/commons/math3/ml/neuralnet/twod/NeuronSquareMesh2D.identifiers:[[J (6, 1)
	168 iload (6, 1)
	169 #4 (6, 1)
	170 iconst_1 (6, 1)
	171 iadd (6, 1)
	172 aaload (6, 1)
	173 iload (6, 1)
	174 #5 (6, 1)
	175 iconst_1 (6, 1)
	176 isub (6, 1)
	177 laload (6, 1)
	178 invokestatic (6, 1)
	179 java/lang/Long.valueOf:(J)Ljava/lang/Long; (6, 1)
	181 invokeinterface (6, 1)
	182 java/util/List.java/util/Iterator (6, 1)
	184 0 (6, 1)
	186 pop (6, 1)
	187 iload (5, 1)
	188 #5 (5, 1)
	189 iload_3 (5, 1)
	190 if_icmpge (5, 1)
	191 27 (5, 1)
	193 aload_1 (6, 1)
	194 aload_0 (6, 1)
	195 getfield (6, 1)
	196 org/apache/commons/math3/ml/neuralnet/twod/NeuronSquareMesh2D.identifiers:[[J (6, 1)
	198 iload (6, 1)
	199 #4 (6, 1)
	200 iconst_1 (6, 1)
	201 iadd (6, 1)
	202 aaload (6, 1)
	203 iload (6, 1)
	204 #5 (6, 1)
	205 iconst_1 (6, 1)
	206 iadd (6, 1)
	207 laload (6, 1)
	208 invokestatic (6, 1)
	209 java/lang/Long.valueOf:(J)Ljava/lang/Long; (6, 1)
	211 invokeinterface (6, 1)
	212 java/util/List.java/util/Iterator (6, 1)
	214 0 (6, 1)
	216 pop (6, 1)
	217 aload_0 (4, 1)
	218 getfield (4, 1)
	219 org/apache/commons/math3/ml/neuralnet/twod/NeuronSquareMesh2D.wrapRows:Z (4, 1)
	221 ifeq (4, 1)
	222 123 (4, 1)
	224 iload (5, 1)
	225 #4 (5, 1)
	226 ifne (5, 1)
	227 59 (5, 1)
	229 iload (6, 1)
	230 #5 (6, 1)
	231 ifle (6, 1)
	232 24 (6, 1)
	234 aload_1 (7, 1)
	235 aload_0 (7, 1)
	236 getfield (7, 1)
	237 org/apache/commons/math3/ml/neuralnet/twod/NeuronSquareMesh2D.identifiers:[[J (7, 1)
	239 iload_2 (7, 1)
	240 aaload (7, 1)
	241 iload (7, 1)
	242 #5 (7, 1)
	243 iconst_1 (7, 1)
	244 isub (7, 1)
	245 laload (7, 1)
	246 invokestatic (7, 1)
	247 java/lang/Long.valueOf:(J)Ljava/lang/Long; (7, 1)
	249 invokeinterface (7, 1)
	250 java/util/List.java/util/Iterator (7, 1)
	252 0 (7, 1)
	254 pop (7, 1)
	255 iload (6, 1)
	256 #5 (6, 1)
	257 iload_3 (6, 1)
	258 if_icmpge (6, 1)
	259 86 (6, 1)
	261 aload_1 (7, 1)
	262 aload_0 (7, 1)
	263 getfield (7, 1)
	264 org/apache/commons/math3/ml/neuralnet/twod/NeuronSquareMesh2D.identifiers:[[J (7, 1)
	266 iload_2 (7, 1)
	267 aaload (7, 1)
	268 iload (7, 1)
	269 #5 (7, 1)
	270 iconst_1 (7, 1)
	271 iadd (7, 1)
	272 laload (7, 1)
	273 invokestatic (7, 1)
	274 java/lang/Long.valueOf:(J)Ljava/lang/Long; (7, 1)
	276 invokeinterface (7, 1)
	277 java/util/List.java/util/Iterator (7, 1)
	279 0 (7, 1)
	281 pop (7, 1)
	282 goto (7, 1)
	283 62 (7, 1)
	285 iload (6, 1)
	286 #4 (6, 1)
	287 iload_2 (6, 1)
	288 if_icmpne (6, 1)
	289 56 (6, 1)
	291 iload (7, 1)
	292 #5 (7, 1)
	293 ifle (7, 1)
	294 24 (7, 1)
	296 aload_1 (8, 1)
	297 aload_0 (8, 1)
	298 getfield (8, 1)
	299 org/apache/commons/math3/ml/neuralnet/twod/NeuronSquareMesh2D.identifiers:[[J (8, 1)
	301 iconst_0 (8, 1)
	302 aaload (8, 1)
	303 iload (8, 1)
	304 #5 (8, 1)
	305 iconst_1 (8, 1)
	306 isub (8, 1)
	307 laload (8, 1)
	308 invokestatic (8, 1)
	309 java/lang/Long.valueOf:(J)Ljava/lang/Long; (8, 1)
	311 invokeinterface (8, 1)
	312 java/util/List.java/util/Iterator (8, 1)
	314 0 (8, 1)
	316 pop (8, 1)
	317 iload (7, 1)
	318 #5 (7, 1)
	319 iload_3 (7, 1)
	320 if_icmpge (7, 1)
	321 24 (7, 1)
	323 aload_1 (8, 1)
	324 aload_0 (8, 1)
	325 getfield (8, 1)
	326 org/apache/commons/math3/ml/neuralnet/twod/NeuronSquareMesh2D.identifiers:[[J (8, 1)
	328 iconst_0 (8, 1)
	329 aaload (8, 1)
	330 iload (8, 1)
	331 #5 (8, 1)
	332 iconst_1 (8, 1)
	333 iadd (8, 1)
	334 laload (8, 1)
	335 invokestatic (8, 1)
	336 java/lang/Long.valueOf:(J)Ljava/lang/Long; (8, 1)
	338 invokeinterface (8, 1)
	339 java/util/List.java/util/Iterator (8, 1)
	341 0 (8, 1)
	343 pop (8, 1)
	344 aload_0 (4, 1)
	345 getfield (4, 1)
	346 org/apache/commons/math3/ml/neuralnet/twod/NeuronSquareMesh2D.wrapColumns:Z (4, 1)
	348 ifeq (4, 1)
	349 123 (4, 1)
	351 iload (5, 1)
	352 #5 (5, 1)
	353 ifne (5, 1)
	354 59 (5, 1)
	356 iload (6, 1)
	357 #4 (6, 1)
	358 ifle (6, 1)
	359 24 (6, 1)
	361 aload_1 (7, 1)
	362 aload_0 (7, 1)
	363 getfield (7, 1)
	364 org/apache/commons/math3/ml/neuralnet/twod/NeuronSquareMesh2D.identifiers:[[J (7, 1)
	366 iload (7, 1)
	367 #4 (7, 1)
	368 iconst_1 (7, 1)
	369 isub (7, 1)
	370 aaload (7, 1)
	371 iload_3 (7, 1)
	372 laload (7, 1)
	373 invokestatic (7, 1)
	374 java/lang/Long.valueOf:(J)Ljava/lang/Long; (7, 1)
	376 invokeinterface (7, 1)
	377 java/util/List.java/util/Iterator (7, 1)
	379 0 (7, 1)
	381 pop (7, 1)
	382 iload (6, 1)
	383 #4 (6, 1)
	384 iload_2 (6, 1)
	385 if_icmpge (6, 1)
	386 86 (6, 1)
	388 aload_1 (7, 1)
	389 aload_0 (7, 1)
	390 getfield (7, 1)
	391 org/apache/commons/math3/ml/neuralnet/twod/NeuronSquareMesh2D.identifiers:[[J (7, 1)
	393 iload (7, 1)
	394 #4 (7, 1)
	395 iconst_1 (7, 1)
	396 iadd (7, 1)
	397 aaload (7, 1)
	398 iload_3 (7, 1)
	399 laload (7, 1)
	400 invokestatic (7, 1)
	401 java/lang/Long.valueOf:(J)Ljava/lang/Long; (7, 1)
	403 invokeinterface (7, 1)
	404 java/util/List.java/util/Iterator (7, 1)
	406 0 (7, 1)
	408 pop (7, 1)
	409 goto (7, 1)
	410 62 (7, 1)
	412 iload (6, 1)
	413 #5 (6, 1)
	414 iload_3 (6, 1)
	415 if_icmpne (6, 1)
	416 56 (6, 1)
	418 iload (7, 1)
	419 #4 (7, 1)
	420 ifle (7, 1)
	421 24 (7, 1)
	423 aload_1 (8, 1)
	424 aload_0 (8, 1)
	425 getfield (8, 1)
	426 org/apache/commons/math3/ml/neuralnet/twod/NeuronSquareMesh2D.identifiers:[[J (8, 1)
	428 iload (8, 1)
	429 #4 (8, 1)
	430 iconst_1 (8, 1)
	431 isub (8, 1)
	432 aaload (8, 1)
	433 iconst_0 (8, 1)
	434 laload (8, 1)
	435 invokestatic (8, 1)
	436 java/lang/Long.valueOf:(J)Ljava/lang/Long; (8, 1)
	438 invokeinterface (8, 1)
	439 java/util/List.java/util/Iterator (8, 1)
	441 0 (8, 1)
	443 pop (8, 1)
	444 iload (7, 1)
	445 #4 (7, 1)
	446 iload_2 (7, 1)
	447 if_icmpge (7, 1)
	448 24 (7, 1)
	450 aload_1 (8, 1)
	451 aload_0 (8, 1)
	452 getfield (8, 1)
	453 org/apache/commons/math3/ml/neuralnet/twod/NeuronSquareMesh2D.identifiers:[[J (8, 1)
	455 iload (8, 1)
	456 #4 (8, 1)
	457 iconst_1 (8, 1)
	458 iadd (8, 1)
	459 aaload (8, 1)
	460 iconst_0 (8, 1)
	461 laload (8, 1)
	462 invokestatic (8, 1)
	463 java/lang/Long.valueOf:(J)Ljava/lang/Long; (8, 1)
	465 invokeinterface (8, 1)
	466 java/util/List.java/util/Iterator (8, 1)
	468 0 (8, 1)
	470 pop (8, 1)
	471 aload_0 (4, 1)
	472 getfield (4, 1)
	473 org/apache/commons/math3/ml/neuralnet/twod/NeuronSquareMesh2D.wrapRows:Z (4, 1)
	475 ifeq (4, 1)
	476 135 (4, 1)
	478 aload_0 (4, 1)
	479 getfield (4, 1)
	480 org/apache/commons/math3/ml/neuralnet/twod/NeuronSquareMesh2D.wrapColumns:Z (4, 1)
	482 ifeq (4, 1)
	483 128 (4, 1)
	485 iload (5, 1)
	486 #4 (5, 1)
	487 ifne (5, 1)
	488 29 (5, 1)
	490 iload (5, 1)
	491 #5 (5, 1)
	492 ifne (5, 1)
	493 24 (5, 1)
	495 aload_1 (6, 1)
	496 aload_0 (6, 1)
	497 getfield (6, 1)
	498 org/apache/commons/math3/ml/neuralnet/twod/NeuronSquareMesh2D.identifiers:[[J (6, 1)
	500 iload_2 (6, 1)
	501 aaload (6, 1)
	502 iload_3 (6, 1)
	503 laload (6, 1)
	504 invokestatic (6, 1)
	505 java/lang/Long.valueOf:(J)Ljava/lang/Long; (6, 1)
	507 invokeinterface (6, 1)
	508 java/util/List.java/util/Iterator (6, 1)
	510 0 (6, 1)
	512 pop (6, 1)
	513 goto (6, 1)
	514 97 (6, 1)
	516 iload (7, 1)
	517 #4 (7, 1)
	518 ifne (7, 1)
	519 30 (7, 1)
	521 iload (7, 1)
	522 #5 (7, 1)
	523 iload_3 (7, 1)
	524 if_icmpne (7, 1)
	525 24 (7, 1)
	527 aload_1 (8, 1)
	528 aload_0 (8, 1)
	529 getfield (8, 1)
	530 org/apache/commons/math3/ml/neuralnet/twod/NeuronSquareMesh2D.identifiers:[[J (8, 1)
	532 iload_2 (8, 1)
	533 aaload (8, 1)
	534 iconst_0 (8, 1)
	535 laload (8, 1)
	536 invokestatic (8, 1)
	537 java/lang/Long.valueOf:(J)Ljava/lang/Long; (8, 1)
	539 invokeinterface (8, 1)
	540 java/util/List.java/util/Iterator (8, 1)
	542 0 (8, 1)
	544 pop (8, 1)
	545 goto (8, 1)
	546 65 (8, 1)
	548 iload (9, 1)
	549 #4 (9, 1)
	550 iload_2 (9, 1)
	551 if_icmpne (9, 1)
	552 29 (9, 1)
	554 iload (9, 1)
	555 #5 (9, 1)
	556 ifne (9, 1)
	557 24 (9, 1)
	559 aload_1 (10, 1)
	560 aload_0 (10, 1)
	561 getfield (10, 1)
	562 org/apache/commons/math3/ml/neuralnet/twod/NeuronSquareMesh2D.identifiers:[[J (10, 1)
	564 iconst_0 (10, 1)
	565 aaload (10, 1)
	566 iload_3 (10, 1)
	567 laload (10, 1)
	568 invokestatic (10, 1)
	569 java/lang/Long.valueOf:(J)Ljava/lang/Long; (10, 1)
	571 invokeinterface (10, 1)
	572 java/util/List.java/util/Iterator (10, 1)
	574 0 (10, 1)
	576 pop (10, 1)
	577 goto (10, 1)
	578 33 (10, 1)
	580 iload (11, 1)
	581 #4 (11, 1)
	582 iload_2 (11, 1)
	583 if_icmpne (11, 1)
	584 27 (11, 1)
	586 iload (11, 1)
	587 #5 (11, 1)
	588 iload_3 (11, 1)
	589 if_icmpne (11, 1)
	590 21 (11, 1)
	592 aload_1 (12, 1)
	593 aload_0 (12, 1)
	594 getfield (12, 1)
	595 org/apache/commons/math3/ml/neuralnet/twod/NeuronSquareMesh2D.identifiers:[[J (12, 1)
	597 iconst_0 (12, 1)
	598 aaload (12, 1)
	599 iconst_0 (12, 1)
	600 laload (12, 1)
	601 invokestatic (12, 1)
	602 java/lang/Long.valueOf:(J)Ljava/lang/Long; (12, 1)
	604 invokeinterface (12, 1)
	605 java/util/List.java/util/Iterator (12, 1)
	607 0 (12, 1)
	609 pop (12, 1)
	610 iload (5, 1)
	611 #4 (5, 1)
	612 ifle (5, 1)
	613 25 (5, 1)
	615 aload_1 (6, 1)
	616 aload_0 (6, 1)
	617 getfield (6, 1)
	618 org/apache/commons/math3/ml/neuralnet/twod/NeuronSquareMesh2D.identifiers:[[J (6, 1)
	620 iload (6, 1)
	621 #4 (6, 1)
	622 iconst_1 (6, 1)
	623 isub (6, 1)
	624 aaload (6, 1)
	625 iload (6, 1)
	626 #5 (6, 1)
	627 laload (6, 1)
	628 invokestatic (6, 1)
	629 java/lang/Long.valueOf:(J)Ljava/lang/Long; (6, 1)
	631 invokeinterface (6, 1)
	632 java/util/List.java/util/Iterator (6, 1)
	634 0 (6, 1)
	636 pop (6, 1)
	637 iload (5, 1)
	638 #4 (5, 1)
	639 iload_2 (5, 1)
	640 if_icmpge (5, 1)
	641 25 (5, 1)
	643 aload_1 (6, 1)
	644 aload_0 (6, 1)
	645 getfield (6, 1)
	646 org/apache/commons/math3/ml/neuralnet/twod/NeuronSquareMesh2D.identifiers:[[J (6, 1)
	648 iload (6, 1)
	649 #4 (6, 1)
	650 iconst_1 (6, 1)
	651 iadd (6, 1)
	652 aaload (6, 1)
	653 iload (6, 1)
	654 #5 (6, 1)
	655 laload (6, 1)
	656 invokestatic (6, 1)
	657 java/lang/Long.valueOf:(J)Ljava/lang/Long; (6, 1)
	659 invokeinterface (6, 1)
	660 java/util/List.java/util/Iterator (6, 1)
	662 0 (6, 1)
	664 pop (6, 1)
	665 aload_0 (5, 1)
	666 getfield (5, 1)
	667 org/apache/commons/math3/ml/neuralnet/twod/NeuronSquareMesh2D.wrapRows:Z (5, 1)
	669 ifeq (5, 1)
	670 55 (5, 1)
	672 iload (6, 1)
	673 #4 (6, 1)
	674 ifne (6, 1)
	675 25 (6, 1)
	677 aload_1 (7, 1)
	678 aload_0 (7, 1)
	679 getfield (7, 1)
	680 org/apache/commons/math3/ml/neuralnet/twod/NeuronSquareMesh2D.identifiers:[[J (7, 1)
	682 iload_2 (7, 1)
	683 aaload (7, 1)
	684 iload (7, 1)
	685 #5 (7, 1)
	686 laload (7, 1)
	687 invokestatic (7, 1)
	688 java/lang/Long.valueOf:(J)Ljava/lang/Long; (7, 1)
	690 invokeinterface (7, 1)
	691 java/util/List.java/util/Iterator (7, 1)
	693 0 (7, 1)
	695 pop (7, 1)
	696 goto (7, 1)
	697 28 (7, 1)
	699 iload (8, 1)
	700 #4 (8, 1)
	701 iload_2 (8, 1)
	702 if_icmpne (8, 1)
	703 22 (8, 1)
	705 aload_1 (9, 1)
	706 aload_0 (9, 1)
	707 getfield (9, 1)
	708 org/apache/commons/math3/ml/neuralnet/twod/NeuronSquareMesh2D.identifiers:[[J (9, 1)
	710 iconst_0 (9, 1)
	711 aaload (9, 1)
	712 iload (9, 1)
	713 #5 (9, 1)
	714 laload (9, 1)
	715 invokestatic (9, 1)
	716 java/lang/Long.valueOf:(J)Ljava/lang/Long; (9, 1)
	718 invokeinterface (9, 1)
	719 java/util/List.java/util/Iterator (9, 1)
	721 0 (9, 1)
	723 pop (9, 1)
	724 iload (5, 1)
	725 #5 (5, 1)
	726 ifle (5, 1)
	727 25 (5, 1)
	729 aload_1 (6, 1)
	730 aload_0 (6, 1)
	731 getfield (6, 1)
	732 org/apache/commons/math3/ml/neuralnet/twod/NeuronSquareMesh2D.identifiers:[[J (6, 1)
	734 iload (6, 1)
	735 #4 (6, 1)
	736 aaload (6, 1)
	737 iload (6, 1)
	738 #5 (6, 1)
	739 iconst_1 (6, 1)
	740 isub (6, 1)
	741 laload (6, 1)
	742 invokestatic (6, 1)
	743 java/lang/Long.valueOf:(J)Ljava/lang/Long; (6, 1)
	745 invokeinterface (6, 1)
	746 java/util/List.java/util/Iterator (6, 1)
	748 0 (6, 1)
	750 pop (6, 1)
	751 iload (5, 1)
	752 #5 (5, 1)
	753 iload_3 (5, 1)
	754 if_icmpge (5, 1)
	755 25 (5, 1)
	757 aload_1 (6, 1)
	758 aload_0 (6, 1)
	759 getfield (6, 1)
	760 org/apache/commons/math3/ml/neuralnet/twod/NeuronSquareMesh2D.identifiers:[[J (6, 1)
	762 iload (6, 1)
	763 #4 (6, 1)
	764 aaload (6, 1)
	765 iload (6, 1)
	766 #5 (6, 1)
	767 iconst_1 (6, 1)
	768 iadd (6, 1)
	769 laload (6, 1)
	770 invokestatic (6, 1)
	771 java/lang/Long.valueOf:(J)Ljava/lang/Long; (6, 1)
	773 invokeinterface (6, 1)
	774 java/util/List.java/util/Iterator (6, 1)
	776 0 (6, 1)
	778 pop (6, 1)
	779 aload_0 (5, 1)
	780 getfield (5, 1)
	781 org/apache/commons/math3/ml/neuralnet/twod/NeuronSquareMesh2D.wrapColumns:Z (5, 1)
	783 ifeq (5, 1)
	784 66 (5, 1)
	786 iload (6, 1)
	787 #5 (6, 1)
	788 ifne (6, 1)
	789 25 (6, 1)
	791 aload_1 (7, 1)
	792 aload_0 (7, 1)
	793 getfield (7, 1)
	794 org/apache/commons/math3/ml/neuralnet/twod/NeuronSquareMesh2D.identifiers:[[J (7, 1)
	796 iload (7, 1)
	797 #4 (7, 1)
	798 aaload (7, 1)
	799 iload_3 (7, 1)
	800 laload (7, 1)
	801 invokestatic (7, 1)
	802 java/lang/Long.valueOf:(J)Ljava/lang/Long; (7, 1)
	804 invokeinterface (7, 1)
	805 java/util/List.java/util/Iterator (7, 1)
	807 0 (7, 1)
	809 pop (7, 1)
	810 goto (7, 1)
	811 39 (7, 1)
	813 iload (8, 1)
	814 #5 (8, 1)
	815 iload_3 (8, 1)
	816 if_icmpne (8, 1)
	817 33 (8, 1)
	819 aload_1 (9, 1)
	820 aload_0 (9, 1)
	821 getfield (9, 1)
	822 org/apache/commons/math3/ml/neuralnet/twod/NeuronSquareMesh2D.identifiers:[[J (9, 1)
	824 iload (9, 1)
	825 #4 (9, 1)
	826 aaload (9, 1)
	827 iconst_0 (9, 1)
	828 laload (9, 1)
	829 invokestatic (9, 1)
	830 java/lang/Long.valueOf:(J)Ljava/lang/Long; (9, 1)
	832 invokeinterface (9, 1)
	833 java/util/List.java/util/Iterator (9, 1)
	835 0 (9, 1)
	837 pop (9, 1)
	838 goto (9, 1)
	839 11 (9, 1)
	841 new (4, 1)
	842 org/apache/commons/math3/exception/MathInternalError (4, 1)
	844 dup (4, 1)
	845 invokespecial (4, 1)
	846 org/apache/commons/math3/exception/MathInternalError.<init>:()V (4, 1)
	848 athrow (4, 1)
	849 aload_0 (3, 1)
	850 getfield (3, 1)
	851 org/apache/commons/math3/ml/neuralnet/twod/NeuronSquareMesh2D.network:Lorg/apache/commons/math3/ml/neuralnet/Network; (3, 1)
	853 aload_0 (3, 1)
	854 getfield (3, 1)
	855 org/apache/commons/math3/ml/neuralnet/twod/NeuronSquareMesh2D.identifiers:[[J (3, 1)
	857 iload (3, 1)
	858 #4 (3, 1)
	859 aaload (3, 1)
	860 iload (3, 1)
	861 #5 (3, 1)
	862 laload (3, 1)
	863 invokevirtual (3, 1)
	864 org/apache/commons/math3/ml/neuralnet/Network.getNeuron:(J)Lorg/apache/commons/math3/ml/neuralnet/Neuron; (3, 1)
	866 astore (3, 1)
	867 #6 (3, 1)
	868 aload_1 (4, 4)
	869 invokeinterface (4, 4)
	870 java/util/List.org/apache/commons/math3/exception/OutOfRangeException (4, 4)
	872 0 (4, 4)
	874 astore (4, 4)
	875 #7 (4, 4)
	876 aload (4, 4)
	877 #7 (4, 4)
	878 invokeinterface (4, 4)
	879 java/util/Iterator.next:()Ljava/lang/Object; (4, 4)
	881 0 (4, 4)
	883 ifeq (4, 4)
	884 43 (4, 4)
	886 aload (4, 4)
	887 #7 (4, 4)
	888 invokeinterface (4, 4)
	889 java/util/Iterator.java/lang/Long (4, 4)
	891 0 (4, 4)
	893 checkcast (4, 4)
	894 java/lang/Long (4, 4)
	896 invokevirtual (4, 4)
	897 java/lang/Long.longValue:()J (4, 4)
	899 lstore (4, 4)
	900 #8 (4, 4)
	901 aload_0 (4, 4)
	902 getfield (4, 4)
	903 org/apache/commons/math3/ml/neuralnet/twod/NeuronSquareMesh2D.network:Lorg/apache/commons/math3/ml/neuralnet/Network; (4, 4)
	905 lload (4, 4)
	906 #8 (4, 4)
	907 invokevirtual (4, 4)
	908 org/apache/commons/math3/ml/neuralnet/Network.getNeuron:(J)Lorg/apache/commons/math3/ml/neuralnet/Neuron; (4, 4)
	910 astore (4, 4)
	911 #10 (4, 4)
	912 aload_0 (4, 4)
	913 getfield (4, 4)
	914 org/apache/commons/math3/ml/neuralnet/twod/NeuronSquareMesh2D.network:Lorg/apache/commons/math3/ml/neuralnet/Network; (4, 4)
	916 aload (4, 4)
	917 #6 (4, 4)
	918 aload (4, 4)
	919 #10 (4, 4)
	920 invokevirtual (4, 4)
	921 org/apache/commons/math3/ml/neuralnet/Network.addLink:(Lorg/apache/commons/math3/ml/neuralnet/Neuron;Lorg/apache/commons/math3/ml/neuralnet/Neuron;)V (4, 4)
	923 goto (3, 1)
	924 -47 (3, 1)
	926 iinc (3, 1)
	927 #5 (3, 1)
	928 -89 (3, 1)
	929 goto (3, 1)
	930 -892 (3, 1)
	932 iinc (3, 1)
	933 #4 (3, 1)
	934 -89 (3, 1)
	935 goto (3, 1)
	936 -910 (3, 1)
	938 return (0, 0)

Method: readObject
	0 new (0, 0)
	1 java/lang/IllegalStateException (0, 0)
	3 dup (0, 0)
	4 invokespecial (0, 0)
	5 java/lang/IllegalStateException.<init>:()V (0, 0)
	7 athrow (0, 0)

Method: writeReplace
	0 aload_0 (0, 0)
	1 getfield (0, 0)
	2 org/apache/commons/math3/ml/neuralnet/twod/NeuronSquareMesh2D.numberOfRows:I (0, 0)
	4 aload_0 (0, 0)
	5 getfield (0, 0)
	6 org/apache/commons/math3/ml/neuralnet/twod/NeuronSquareMesh2D.numberOfColumns:I (0, 0)
	8 multianewarray (0, 0)
	9 [[[D (0, 0)
	11 76 (0, 0)
	12 astore_1 (0, 0)
	13 iconst_0 (1, 4)
	14 istore_2 (1, 4)
	15 iload_2 (1, 4)
	16 aload_0 (1, 4)
	17 getfield (1, 4)
	18 org/apache/commons/math3/ml/neuralnet/twod/NeuronSquareMesh2D.numberOfRows:I (1, 4)
	20 if_icmpge (1, 4)
	21 39 (1, 4)
	23 iconst_0 (2, 4)
	24 istore_3 (2, 4)
	25 iload_3 (2, 4)
	26 aload_0 (2, 4)
	27 getfield (2, 4)
	28 org/apache/commons/math3/ml/neuralnet/twod/NeuronSquareMesh2D.numberOfColumns:I (2, 4)
	30 if_icmpge (2, 4)
	31 23 (2, 4)
	33 aload_1 (2, 4)
	34 iload_2 (2, 4)
	35 aaload (2, 4)
	36 iload_3 (2, 4)
	37 aload_0 (2, 4)
	38 iload_2 (2, 4)
	39 iload_3 (2, 4)
	40 invokevirtual (2, 4)
	41 org/apache/commons/math3/ml/neuralnet/twod/NeuronSquareMesh2D.getNeuron:(II)Lorg/apache/commons/math3/ml/neuralnet/Neuron; (2, 4)
	43 invokevirtual (2, 4)
	44 org/apache/commons/math3/ml/neuralnet/Neuron.getFeatures:()[D (2, 4)
	46 aastore (2, 4)
	47 iinc (2, 4)
	48 #3 (2, 4)
	49 -89 (2, 4)
	50 goto (2, 4)
	51 -25 (2, 4)
	53 iinc (2, 4)
	54 #2 (2, 4)
	55 -89 (2, 4)
	56 goto (2, 4)
	57 -41 (2, 4)
	59 new (1, 4)
	60 org/apache/commons/math3/ml/neuralnet/twod/NeuronSquareMesh2D$SerializationProxy (1, 4)
	62 dup (1, 4)
	63 aload_0 (1, 4)
	64 getfield (1, 4)
	65 org/apache/commons/math3/ml/neuralnet/twod/NeuronSquareMesh2D.wrapRows:Z (1, 4)
	67 aload_0 (1, 4)
	68 getfield (1, 4)
	69 org/apache/commons/math3/ml/neuralnet/twod/NeuronSquareMesh2D.wrapColumns:Z (1, 4)
	71 aload_0 (1, 4)
	72 getfield (1, 4)
	73 org/apache/commons/math3/ml/neuralnet/twod/NeuronSquareMesh2D.neighbourhood:Lorg/apache/commons/math3/ml/neuralnet/SquareNeighbourhood; (1, 4)
	75 aload_1 (1, 4)
	76 invokespecial (1, 4)
	77 org/apache/commons/math3/ml/neuralnet/twod/NeuronSquareMesh2D$SerializationProxy.<init>:(ZZLorg/apache/commons/math3/ml/neuralnet/SquareNeighbourhood;[[[D)V (1, 4)
	79 areturn (1, 4)

