Method: <init>
	0 aload_0 (0, 0)
	1 invokespecial (0, 0)
	4 aload_0 (0, 0)
	5 aload (0, 0)
	7 arraylength (0, 0)
	8 putfield (0, 0)
	11 aload_0 (0, 0)
	12 aload (0, 0)
	14 iconst_0 (0, 0)
	15 aaload (0, 0)
	16 arraylength (0, 0)
	17 putfield (0, 0)
	20 aload_0 (0, 0)
	21 iload_1 (0, 0)
	22 putfield (0, 0)
	25 aload_0 (0, 0)
	26 iload_2 (0, 0)
	27 putfield (0, 0)
	30 aload_0 (0, 0)
	31 aload_3 (0, 0)
	32 putfield (0, 0)
	35 aload_0 (0, 0)
	36 aload (0, 0)
	38 putfield (0, 0)
	41 aload_0 (0, 1)
	42 aload (0, 1)
	44 putfield (0, 1)
	47 return (0, 0)

Method: copy
	0 aload_0 (0, 0)
	1 getfield (0, 0)
	4 aload_0 (0, 0)
	5 getfield (0, 0)
	8 multianewarray (0, 0)
	12 astore_1 (0, 0)
	13 iconst_0 (1, 4)
	14 istore_2 (1, 4)
	15 iload_2 (1, 4)
	16 aload_0 (1, 4)
	17 getfield (1, 4)
	20 if_icmpge (1, 4)
	23 iconst_0 (2, 4)
	24 istore_3 (2, 4)
	25 iload_3 (2, 4)
	26 aload_0 (2, 4)
	27 getfield (2, 4)
	30 if_icmpge (2, 4)
	33 aload_1 (2, 1)
	34 iload_2 (2, 1)
	35 aaload (2, 1)
	36 iload_3 (2, 1)
	37 aload_0 (2, 1)
	38 getfield (2, 1)
	41 iload_2 (2, 1)
	42 aaload (2, 1)
	43 iload_3 (2, 1)
	44 laload (2, 1)
	45 lastore (2, 1)
	46 iinc (2, 1)
	49 goto (2, 1)
	52 iinc (2, 1)
	55 goto (2, 1)
	58 new (1, 1)
	61 dup (1, 1)
	62 aload_0 (1, 1)
	63 getfield (1, 1)
	66 aload_0 (1, 1)
	67 getfield (1, 1)
	70 aload_0 (1, 1)
	71 getfield (1, 1)
	74 aload_0 (1, 1)
	75 getfield (1, 1)
	78 invokevirtual (1, 1)
	81 aload_1 (1, 1)
	82 invokespecial (1, 1)
	85 areturn (1, 1)

Method: iterator
	0 aload_0 (0, 0)
	1 getfield (0, 0)
	4 invokevirtual (0, 0)
	7 areturn (0, 0)

Method: getNetwork
	0 aload_0 (0, 0)
	1 getfield (0, 0)
	4 areturn (0, 0)

Method: getNumberOfRows
	0 aload_0 (0, 0)
	1 getfield (0, 0)
	4 ireturn (0, 0)

Method: getNumberOfColumns
	0 aload_0 (0, 0)
	1 getfield (0, 0)
	4 ireturn (0, 0)

Method: getNeuron
	0 aload_0 (0, 0)
	1 iload_1 (0, 0)
	2 iload_2 (0, 0)
	3 aload_3 (0, 0)
	4 aload (0, 0)
	6 invokespecial (0, 0)
	9 astore (0, 0)
	11 aload (0, 0)
	13 ifnonnull (0, 0)
	16 aconst_null (0, 0)
	17 goto (0, 0)
	20 aload_0 (0, 0)
	21 aload (0, 0)
	23 iconst_0 (0, 0)
	24 iaload (0, 0)
	25 aload (0, 0)
	27 iconst_1 (0, 0)
	28 iaload (0, 0)
	29 invokevirtual (0, 0)
	32 areturn (0, 0)

Method: getLocation
	0 getstatic (1, 5)
	3 aload_3 (1, 5)
	4 invokevirtual (1, 5)
	7 iaload (1, 5)
	8 tableswitch (1, 5)
	36 iconst_m1 (1, 5)
	37 istore (1, 5)
	39 goto (1, 5)
	42 iconst_1 (1, 5)
	43 istore (1, 5)
	45 goto (1, 5)
	48 iconst_0 (1, 5)
	49 istore (1, 5)
	51 goto (1, 5)
	54 new (1, 5)
	57 dup (1, 5)
	58 invokespecial (1, 5)
	61 athrow (1, 5)
	62 iload_2 (0, 0)
	63 iload (0, 0)
	65 iadd (0, 0)
	66 istore (0, 0)
	68 aload_0 (1, 1)
	69 getfield (1, 1)
	72 ifeq (1, 1)
	75 iload (2, 1)
	77 ifge (2, 1)
	80 iload (2, 1)
	82 aload_0 (2, 1)
	83 getfield (2, 1)
	86 iadd (2, 1)
	87 istore (2, 1)
	89 goto (2, 1)
	92 iload (2, 2)
	94 aload_0 (2, 2)
	95 getfield (2, 2)
	98 irem (2, 2)
	99 istore (2, 2)
	101 getstatic (1, 5)
	104 aload (1, 5)
	106 invokevirtual (1, 5)
	109 iaload (1, 5)
	110 tableswitch (1, 5)
	136 iconst_m1 (1, 5)
	137 istore (1, 5)
	139 goto (1, 5)
	142 iconst_1 (1, 5)
	143 istore (1, 5)
	145 goto (1, 5)
	148 iconst_0 (1, 5)
	149 istore (1, 5)
	151 goto (1, 5)
	154 new (1, 5)
	157 dup (1, 5)
	158 invokespecial (1, 5)
	161 athrow (1, 5)
	162 iload_1 (0, 1)
	163 iload (0, 1)
	165 iadd (0, 1)
	166 istore (0, 1)
	168 aload_0 (1, 1)
	169 getfield (1, 1)
	172 ifeq (1, 1)
	175 iload (2, 1)
	177 ifge (2, 1)
	180 iload (2, 1)
	182 aload_0 (2, 1)
	183 getfield (2, 1)
	186 iadd (2, 1)
	187 istore (2, 1)
	189 goto (2, 1)
	192 iload (2, 2)
	194 aload_0 (2, 2)
	195 getfield (2, 2)
	198 irem (2, 2)
	199 istore (2, 2)
	201 iload (0, 1)
	203 iflt (0, 1)
	206 iload (0, 1)
	208 aload_0 (0, 1)
	209 getfield (0, 1)
	212 if_icmpge (0, 1)
	215 iload (0, 1)
	217 iflt (0, 1)
	220 iload (0, 1)
	222 aload_0 (0, 1)
	223 getfield (0, 1)
	226 if_icmplt (0, 1)
	229 aconst_null (1, 1)
	230 areturn (1, 1)
	231 iconst_2 (1, 2)
	232 newarray (1, 2)
	234 dup (1, 2)
	235 iconst_0 (1, 2)
	236 iload (1, 2)
	238 iastore (1, 2)
	239 dup (1, 2)
	240 iconst_1 (1, 2)
	241 iload (1, 2)
	243 iastore (1, 2)
	244 areturn (1, 2)

Method: createLinks
	0 new (0, 0)
	3 dup (0, 0)
	4 invokespecial (0, 0)
	7 astore_1 (0, 0)
	8 aload_0 (0, 0)
	9 getfield (0, 0)
	12 iconst_1 (0, 0)
	13 isub (0, 0)
	14 istore_2 (0, 0)
	15 aload_0 (0, 0)
	16 getfield (0, 0)
	19 iconst_1 (0, 0)
	20 isub (0, 0)
	21 istore_3 (0, 0)
	22 iconst_0 (1, 4)
	23 istore (1, 4)
	25 iload (1, 4)
	27 aload_0 (1, 4)
	28 getfield (1, 4)
	31 if_icmpge (1, 4)
	34 iconst_0 (2, 4)
	35 istore (2, 4)
	37 iload (2, 4)
	39 aload_0 (2, 4)
	40 getfield (2, 4)
	43 if_icmpge (2, 4)
	46 aload_1 (2, 4)
	47 invokeinterface (2, 4)
	52 getstatic (3, 5)
	55 aload_0 (3, 5)
	56 getfield (3, 5)
	59 invokevirtual (3, 5)
	62 iaload (3, 5)
	63 lookupswitch (3, 5)
	88 iload (4, 1)
	90 ifle (4, 1)
	93 iload (5, 1)
	95 ifle (5, 1)
	98 aload_1 (5, 1)
	99 aload_0 (5, 1)
	100 getfield (5, 1)
	103 iload (5, 1)
	105 iconst_1 (5, 1)
	106 isub (5, 1)
	107 aaload (5, 1)
	108 iload (5, 1)
	110 iconst_1 (5, 1)
	111 isub (5, 1)
	112 laload (5, 1)
	113 invokestatic (5, 1)
	116 invokeinterface (5, 1)
	121 pop (5, 1)
	122 iload (5, 1)
	124 iload_3 (5, 1)
	125 if_icmpge (5, 1)
	128 aload_1 (5, 1)
	129 aload_0 (5, 1)
	130 getfield (5, 1)
	133 iload (5, 1)
	135 iconst_1 (5, 1)
	136 isub (5, 1)
	137 aaload (5, 1)
	138 iload (5, 1)
	140 iconst_1 (5, 1)
	141 iadd (5, 1)
	142 laload (5, 1)
	143 invokestatic (5, 1)
	146 invokeinterface (5, 1)
	151 pop (5, 1)
	152 iload (4, 1)
	154 iload_2 (4, 1)
	155 if_icmpge (4, 1)
	158 iload (5, 1)
	160 ifle (5, 1)
	163 aload_1 (5, 1)
	164 aload_0 (5, 1)
	165 getfield (5, 1)
	168 iload (5, 1)
	170 iconst_1 (5, 1)
	171 iadd (5, 1)
	172 aaload (5, 1)
	173 iload (5, 1)
	175 iconst_1 (5, 1)
	176 isub (5, 1)
	177 laload (5, 1)
	178 invokestatic (5, 1)
	181 invokeinterface (5, 1)
	186 pop (5, 1)
	187 iload (5, 1)
	189 iload_3 (5, 1)
	190 if_icmpge (5, 1)
	193 aload_1 (5, 1)
	194 aload_0 (5, 1)
	195 getfield (5, 1)
	198 iload (5, 1)
	200 iconst_1 (5, 1)
	201 iadd (5, 1)
	202 aaload (5, 1)
	203 iload (5, 1)
	205 iconst_1 (5, 1)
	206 iadd (5, 1)
	207 laload (5, 1)
	208 invokestatic (5, 1)
	211 invokeinterface (5, 1)
	216 pop (5, 1)
	217 aload_0 (4, 1)
	218 getfield (4, 1)
	221 ifeq (4, 1)
	224 iload (5, 1)
	226 ifne (5, 1)
	229 iload (6, 1)
	231 ifle (6, 1)
	234 aload_1 (6, 1)
	235 aload_0 (6, 1)
	236 getfield (6, 1)
	239 iload_2 (6, 1)
	240 aaload (6, 1)
	241 iload (6, 1)
	243 iconst_1 (6, 1)
	244 isub (6, 1)
	245 laload (6, 1)
	246 invokestatic (6, 1)
	249 invokeinterface (6, 1)
	254 pop (6, 1)
	255 iload (6, 1)
	257 iload_3 (6, 1)
	258 if_icmpge (6, 1)
	261 aload_1 (6, 1)
	262 aload_0 (6, 1)
	263 getfield (6, 1)
	266 iload_2 (6, 1)
	267 aaload (6, 1)
	268 iload (6, 1)
	270 iconst_1 (6, 1)
	271 iadd (6, 1)
	272 laload (6, 1)
	273 invokestatic (6, 1)
	276 invokeinterface (6, 1)
	281 pop (6, 1)
	282 goto (6, 1)
	285 iload (5, 1)
	287 iload_2 (5, 1)
	288 if_icmpne (5, 1)
	291 iload (6, 1)
	293 ifle (6, 1)
	296 aload_1 (6, 1)
	297 aload_0 (6, 1)
	298 getfield (6, 1)
	301 iconst_0 (6, 1)
	302 aaload (6, 1)
	303 iload (6, 1)
	305 iconst_1 (6, 1)
	306 isub (6, 1)
	307 laload (6, 1)
	308 invokestatic (6, 1)
	311 invokeinterface (6, 1)
	316 pop (6, 1)
	317 iload (6, 1)
	319 iload_3 (6, 1)
	320 if_icmpge (6, 1)
	323 aload_1 (6, 1)
	324 aload_0 (6, 1)
	325 getfield (6, 1)
	328 iconst_0 (6, 1)
	329 aaload (6, 1)
	330 iload (6, 1)
	332 iconst_1 (6, 1)
	333 iadd (6, 1)
	334 laload (6, 1)
	335 invokestatic (6, 1)
	338 invokeinterface (6, 1)
	343 pop (6, 1)
	344 aload_0 (4, 1)
	345 getfield (4, 1)
	348 ifeq (4, 1)
	351 iload (5, 1)
	353 ifne (5, 1)
	356 iload (6, 1)
	358 ifle (6, 1)
	361 aload_1 (6, 1)
	362 aload_0 (6, 1)
	363 getfield (6, 1)
	366 iload (6, 1)
	368 iconst_1 (6, 1)
	369 isub (6, 1)
	370 aaload (6, 1)
	371 iload_3 (6, 1)
	372 laload (6, 1)
	373 invokestatic (6, 1)
	376 invokeinterface (6, 1)
	381 pop (6, 1)
	382 iload (6, 1)
	384 iload_2 (6, 1)
	385 if_icmpge (6, 1)
	388 aload_1 (6, 1)
	389 aload_0 (6, 1)
	390 getfield (6, 1)
	393 iload (6, 1)
	395 iconst_1 (6, 1)
	396 iadd (6, 1)
	397 aaload (6, 1)
	398 iload_3 (6, 1)
	399 laload (6, 1)
	400 invokestatic (6, 1)
	403 invokeinterface (6, 1)
	408 pop (6, 1)
	409 goto (6, 1)
	412 iload (5, 1)
	414 iload_3 (5, 1)
	415 if_icmpne (5, 1)
	418 iload (6, 1)
	420 ifle (6, 1)
	423 aload_1 (6, 1)
	424 aload_0 (6, 1)
	425 getfield (6, 1)
	428 iload (6, 1)
	430 iconst_1 (6, 1)
	431 isub (6, 1)
	432 aaload (6, 1)
	433 iconst_0 (6, 1)
	434 laload (6, 1)
	435 invokestatic (6, 1)
	438 invokeinterface (6, 1)
	443 pop (6, 1)
	444 iload (6, 1)
	446 iload_2 (6, 1)
	447 if_icmpge (6, 1)
	450 aload_1 (6, 1)
	451 aload_0 (6, 1)
	452 getfield (6, 1)
	455 iload (6, 1)
	457 iconst_1 (6, 1)
	458 iadd (6, 1)
	459 aaload (6, 1)
	460 iconst_0 (6, 1)
	461 laload (6, 1)
	462 invokestatic (6, 1)
	465 invokeinterface (6, 1)
	470 pop (6, 1)
	471 aload_0 (3, 1)
	472 getfield (3, 1)
	475 ifeq (3, 1)
	478 aload_0 (3, 1)
	479 getfield (3, 1)
	482 ifeq (3, 1)
	485 iload (4, 1)
	487 ifne (4, 1)
	490 iload (4, 1)
	492 ifne (4, 1)
	495 aload_1 (5, 1)
	496 aload_0 (5, 1)
	497 getfield (5, 1)
	500 iload_2 (5, 1)
	501 aaload (5, 1)
	502 iload_3 (5, 1)
	503 laload (5, 1)
	504 invokestatic (5, 1)
	507 invokeinterface (5, 1)
	512 pop (5, 1)
	513 goto (5, 1)
	516 iload (4, 1)
	518 ifne (4, 1)
	521 iload (4, 1)
	523 iload_3 (4, 1)
	524 if_icmpne (4, 1)
	527 aload_1 (5, 1)
	528 aload_0 (5, 1)
	529 getfield (5, 1)
	532 iload_2 (5, 1)
	533 aaload (5, 1)
	534 iconst_0 (5, 1)
	535 laload (5, 1)
	536 invokestatic (5, 1)
	539 invokeinterface (5, 1)
	544 pop (5, 1)
	545 goto (5, 1)
	548 iload (4, 1)
	550 iload_2 (4, 1)
	551 if_icmpne (4, 1)
	554 iload (4, 1)
	556 ifne (4, 1)
	559 aload_1 (5, 1)
	560 aload_0 (5, 1)
	561 getfield (5, 1)
	564 iconst_0 (5, 1)
	565 aaload (5, 1)
	566 iload_3 (5, 1)
	567 laload (5, 1)
	568 invokestatic (5, 1)
	571 invokeinterface (5, 1)
	576 pop (5, 1)
	577 goto (5, 1)
	580 iload (4, 1)
	582 iload_2 (4, 1)
	583 if_icmpne (4, 1)
	586 iload (4, 1)
	588 iload_3 (4, 1)
	589 if_icmpne (4, 1)
	592 aload_1 (5, 1)
	593 aload_0 (5, 1)
	594 getfield (5, 1)
	597 iconst_0 (5, 1)
	598 aaload (5, 1)
	599 iconst_0 (5, 1)
	600 laload (5, 1)
	601 invokestatic (5, 1)
	604 invokeinterface (5, 1)
	609 pop (5, 1)
	610 iload (4, 1)
	612 ifle (4, 1)
	615 aload_1 (4, 1)
	616 aload_0 (4, 1)
	617 getfield (4, 1)
	620 iload (4, 1)
	622 iconst_1 (4, 1)
	623 isub (4, 1)
	624 aaload (4, 1)
	625 iload (4, 1)
	627 laload (4, 1)
	628 invokestatic (4, 1)
	631 invokeinterface (4, 1)
	636 pop (4, 1)
	637 iload (4, 1)
	639 iload_2 (4, 1)
	640 if_icmpge (4, 1)
	643 aload_1 (4, 1)
	644 aload_0 (4, 1)
	645 getfield (4, 1)
	648 iload (4, 1)
	650 iconst_1 (4, 1)
	651 iadd (4, 1)
	652 aaload (4, 1)
	653 iload (4, 1)
	655 laload (4, 1)
	656 invokestatic (4, 1)
	659 invokeinterface (4, 1)
	664 pop (4, 1)
	665 aload_0 (4, 1)
	666 getfield (4, 1)
	669 ifeq (4, 1)
	672 iload (5, 1)
	674 ifne (5, 1)
	677 aload_1 (5, 1)
	678 aload_0 (5, 1)
	679 getfield (5, 1)
	682 iload_2 (5, 1)
	683 aaload (5, 1)
	684 iload (5, 1)
	686 laload (5, 1)
	687 invokestatic (5, 1)
	690 invokeinterface (5, 1)
	695 pop (5, 1)
	696 goto (5, 1)
	699 iload (5, 1)
	701 iload_2 (5, 1)
	702 if_icmpne (5, 1)
	705 aload_1 (5, 1)
	706 aload_0 (5, 1)
	707 getfield (5, 1)
	710 iconst_0 (5, 1)
	711 aaload (5, 1)
	712 iload (5, 1)
	714 laload (5, 1)
	715 invokestatic (5, 1)
	718 invokeinterface (5, 1)
	723 pop (5, 1)
	724 iload (4, 1)
	726 ifle (4, 1)
	729 aload_1 (4, 1)
	730 aload_0 (4, 1)
	731 getfield (4, 1)
	734 iload (4, 1)
	736 aaload (4, 1)
	737 iload (4, 1)
	739 iconst_1 (4, 1)
	740 isub (4, 1)
	741 laload (4, 1)
	742 invokestatic (4, 1)
	745 invokeinterface (4, 1)
	750 pop (4, 1)
	751 iload (4, 1)
	753 iload_3 (4, 1)
	754 if_icmpge (4, 1)
	757 aload_1 (4, 1)
	758 aload_0 (4, 1)
	759 getfield (4, 1)
	762 iload (4, 1)
	764 aaload (4, 1)
	765 iload (4, 1)
	767 iconst_1 (4, 1)
	768 iadd (4, 1)
	769 laload (4, 1)
	770 invokestatic (4, 1)
	773 invokeinterface (4, 1)
	778 pop (4, 1)
	779 aload_0 (4, 1)
	780 getfield (4, 1)
	783 ifeq (4, 1)
	786 iload (5, 1)
	788 ifne (5, 1)
	791 aload_1 (5, 1)
	792 aload_0 (5, 1)
	793 getfield (5, 1)
	796 iload (5, 1)
	798 aaload (5, 1)
	799 iload_3 (5, 1)
	800 laload (5, 1)
	801 invokestatic (5, 1)
	804 invokeinterface (5, 1)
	809 pop (5, 1)
	810 goto (5, 1)
	813 iload (5, 1)
	815 iload_3 (5, 1)
	816 if_icmpne (5, 1)
	819 aload_1 (5, 1)
	820 aload_0 (5, 1)
	821 getfield (5, 1)
	824 iload (5, 1)
	826 aaload (5, 1)
	827 iconst_0 (5, 1)
	828 laload (5, 1)
	829 invokestatic (5, 1)
	832 invokeinterface (5, 1)
	837 pop (5, 1)
	838 goto (5, 1)
	841 new (3, 1)
	844 dup (3, 1)
	845 invokespecial (3, 1)
	848 athrow (3, 1)
	849 aload_0 (2, 1)
	850 getfield (2, 1)
	853 aload_0 (2, 1)
	854 getfield (2, 1)
	857 iload (2, 1)
	859 aaload (2, 1)
	860 iload (2, 1)
	862 laload (2, 1)
	863 invokevirtual (2, 1)
	866 astore (2, 1)
	868 aload_1 (3, 4)
	869 invokeinterface (3, 4)
	874 astore (3, 4)
	876 aload (3, 4)
	878 invokeinterface (3, 4)
	883 ifeq (3, 4)
	886 aload (3, 4)
	888 invokeinterface (3, 4)
	893 checkcast (3, 4)
	896 invokevirtual (3, 4)
	899 lstore (3, 4)
	901 aload_0 (3, 4)
	902 getfield (3, 4)
	905 lload (3, 4)
	907 invokevirtual (3, 4)
	910 astore (3, 4)
	912 aload_0 (3, 4)
	913 getfield (3, 4)
	916 aload (3, 4)
	918 aload (3, 4)
	920 invokevirtual (3, 4)
	923 goto (2, 1)
	926 iinc (2, 1)
	929 goto (2, 1)
	932 iinc (2, 1)
	935 goto (2, 1)
	938 return (0, 1)

Method: readObject
	0 new (0, 0)
	3 dup (0, 0)
	4 invokespecial (0, 0)
	7 athrow (0, 0)

Method: writeReplace
	0 aload_0 (0, 0)
	1 getfield (0, 0)
	4 aload_0 (0, 0)
	5 getfield (0, 0)
	8 multianewarray (0, 0)
	12 astore_1 (0, 0)
	13 iconst_0 (1, 4)
	14 istore_2 (1, 4)
	15 iload_2 (1, 4)
	16 aload_0 (1, 4)
	17 getfield (1, 4)
	20 if_icmpge (1, 4)
	23 iconst_0 (2, 4)
	24 istore_3 (2, 4)
	25 iload_3 (2, 4)
	26 aload_0 (2, 4)
	27 getfield (2, 4)
	30 if_icmpge (2, 4)
	33 aload_1 (2, 4)
	34 iload_2 (2, 4)
	35 aaload (2, 4)
	36 iload_3 (2, 4)
	37 aload_0 (2, 4)
	38 iload_2 (2, 4)
	39 iload_3 (2, 4)
	40 invokevirtual (2, 4)
	43 invokevirtual (2, 4)
	46 aastore (2, 4)
	47 iinc (2, 4)
	50 goto (2, 4)
	53 iinc (2, 4)
	56 goto (2, 4)
	59 new (1, 4)
	62 dup (1, 4)
	63 aload_0 (1, 4)
	64 getfield (1, 4)
	67 aload_0 (1, 4)
	68 getfield (1, 4)
	71 aload_0 (1, 4)
	72 getfield (1, 4)
	75 aload_1 (1, 4)
	76 invokespecial (1, 4)
	79 areturn (1, 4)

