Method: visitOrder
	0 getstatic (0, 0)
	1 org/apache/commons/math3/geometry/partitioning/BSPTreeVisitor$Order.PLUS_SUB_MINUS:Lorg/apache/commons/math3/geometry/partitioning/BSPTreeVisitor$Order; (0, 0)
	3 areturn (0, 0)

Method: visitInternalNode
	0 return (0, 0)

Method: visitLeafNode
	0 aload_1 (1, 1)
	1 invokevirtual (1, 1)
	2 org/apache/commons/math3/geometry/partitioning/BSPTree.getParent:()Lorg/apache/commons/math3/geometry/partitioning/BSPTree; (1, 1)
	4 ifnull (1, 1)
	5 14 (1, 1)
	7 aload_1 (1, 1)
	8 aload_1 (1, 1)
	9 invokevirtual (1, 1)
	10 org/apache/commons/math3/geometry/partitioning/BSPTree.getParent:()Lorg/apache/commons/math3/geometry/partitioning/BSPTree; (1, 1)
	12 invokevirtual (1, 1)
	13 org/apache/commons/math3/geometry/partitioning/BSPTree.getMinus:()Lorg/apache/commons/math3/geometry/partitioning/BSPTree; (1, 1)
	15 if_acmpne (1, 1)
	16 13 (1, 1)
	18 aload_1 (1, 1)
	19 getstatic (1, 1)
	20 java/lang/Boolean.TRUE:Ljava/lang/Boolean; (1, 1)
	22 invokevirtual (1, 1)
	23 org/apache/commons/math3/geometry/partitioning/BSPTree.setAttribute:(Ljava/lang/Object;)V (1, 1)
	25 goto (1, 1)
	26 10 (1, 1)
	28 aload_1 (1, 2)
	29 getstatic (1, 2)
	30 java/lang/Boolean.FALSE:Ljava/lang/Boolean; (1, 2)
	32 invokevirtual (1, 2)
	33 org/apache/commons/math3/geometry/partitioning/BSPTree.setAttribute:(Ljava/lang/Object;)V (1, 2)
	35 return (0, 0)

