Method: <init>
	0 aload_0 (0, 0)
	1 invokespecial (0, 0)
	4 aload_0 (0, 0)
	5 dload_2 (0, 0)
	6 putfield (0, 0)
	9 aload_1 (1, 1)
	10 ifnull (1, 1)
	13 aload_1 (1, 1)
	14 arraylength (1, 1)
	15 ifne (1, 1)
	18 aload_0 (1, 1)
	19 new (1, 1)
	22 dup (1, 1)
	23 getstatic (1, 1)
	26 invokespecial (1, 1)
	29 putfield (1, 1)
	32 goto (1, 1)
	35 aload_0 (1, 2)
	36 aload_1 (1, 2)
	37 iconst_0 (1, 2)
	38 aaload (1, 2)
	39 invokeinterface (1, 2)
	44 iconst_0 (1, 2)
	45 invokeinterface (1, 2)
	50 putfield (1, 2)
	53 aload_0 (1, 2)
	54 getfield (1, 2)
	57 astore (1, 2)
	59 aload (1, 2)
	61 getstatic (1, 2)
	64 invokevirtual (1, 2)
	67 aload_1 (2, 4)
	68 astore (2, 4)
	70 aload (2, 4)
	72 arraylength (2, 4)
	73 istore (2, 4)
	75 iconst_0 (2, 4)
	76 istore (2, 4)
	78 iload (2, 4)
	80 iload (2, 4)
	82 if_icmpge (2, 4)
	85 aload (2, 4)
	87 iload (2, 4)
	89 aaload (2, 4)
	90 astore (2, 4)
	92 aload (3, 1)
	94 aload (3, 1)
	96 invokevirtual (3, 1)
	99 ifeq (3, 1)
	102 aload (3, 1)
	104 aconst_null (3, 1)
	105 invokevirtual (3, 1)
	108 aload (3, 1)
	110 invokevirtual (3, 1)
	113 getstatic (3, 1)
	116 invokevirtual (3, 1)
	119 aload (3, 1)
	121 invokevirtual (3, 1)
	124 astore (3, 1)
	126 aload (3, 1)
	128 getstatic (3, 1)
	131 invokevirtual (3, 1)
	134 iinc (3, 1)
	137 goto (3, 1)
	140 return (0, 1)

Method: getTolerance
	0 aload_0 (0, 0)
	1 getfield (0, 0)
	4 dreturn (0, 0)

Method: insertCuts
	0 aload_2 (0, 0)
	1 invokeinterface (0, 0)
	6 astore_3 (0, 0)
	7 aconst_null (0, 0)
	8 astore (0, 0)
	10 aload (1, 3)
	12 ifnonnull (1, 3)
	15 aload_3 (1, 3)
	16 invokeinterface (1, 3)
	21 ifeq (1, 3)
	24 aload_3 (1, 3)
	25 invokeinterface (1, 3)
	30 checkcast (1, 3)
	33 invokeinterface (1, 3)
	38 astore (1, 3)
	40 aload_1 (2, 1)
	41 aload (2, 1)
	43 invokeinterface (2, 1)
	48 invokevirtual (2, 1)
	51 ifne (2, 1)
	54 aconst_null (2, 1)
	55 astore (2, 1)
	57 goto (2, 1)
	60 aload_3 (1, 1)
	61 invokeinterface (1, 1)
	66 ifne (1, 1)
	69 return (1, 1)
	70 new (0, 0)
	73 dup (0, 0)
	74 invokespecial (0, 0)
	77 astore (0, 0)
	79 new (0, 0)
	82 dup (0, 0)
	83 invokespecial (0, 0)
	86 astore (0, 0)
	88 aload_3 (1, 3)
	89 invokeinterface (1, 3)
	94 ifeq (1, 3)
	97 aload_3 (1, 3)
	98 invokeinterface (1, 3)
	103 checkcast (1, 3)
	106 astore (1, 3)
	108 aload (1, 3)
	110 aload (1, 3)
	112 invokeinterface (1, 3)
	117 astore (1, 3)
	119 getstatic (2, 5)
	122 aload (2, 5)
	124 invokevirtual (2, 5)
	127 invokevirtual (2, 5)
	130 iaload (2, 5)
	131 tableswitch (2, 5)
	156 aload (2, 5)
	158 aload (2, 5)
	160 invokevirtual (2, 5)
	163 pop (2, 5)
	164 goto (2, 5)
	167 aload (2, 5)
	169 aload (2, 5)
	171 invokevirtual (2, 5)
	174 pop (2, 5)
	175 goto (2, 5)
	178 aload (2, 5)
	180 aload (2, 5)
	182 invokevirtual (2, 5)
	185 invokevirtual (2, 5)
	188 pop (2, 5)
	189 aload (2, 5)
	191 aload (2, 5)
	193 invokevirtual (2, 5)
	196 invokevirtual (2, 5)
	199 pop (2, 5)
	200 goto (2, 5)
	203 goto (0, 0)
	206 aload_0 (0, 0)
	207 aload_1 (0, 0)
	208 invokevirtual (0, 0)
	211 aload (0, 0)
	213 invokespecial (0, 0)
	216 aload_0 (0, 0)
	217 aload_1 (0, 0)
	218 invokevirtual (0, 0)
	221 aload (0, 0)
	223 invokespecial (0, 0)
	226 return (0, 0)

Method: copySelf
	0 aload_0 (0, 0)
	1 invokevirtual (0, 0)
	4 areturn (0, 0)

Method: isEmpty
	0 aload_1 (1, 1)
	1 invokevirtual (1, 1)
	4 ifnonnull (1, 1)
	7 aload_1 (1, 1)
	8 invokevirtual (1, 1)
	11 checkcast (1, 1)
	14 invokevirtual (1, 1)
	17 ifne (1, 1)
	20 iconst_1 (1, 1)
	21 goto (1, 1)
	24 iconst_0 (1, 1)
	25 ireturn (1, 1)
	26 aload_0 (0, 1)
	27 aload_1 (0, 1)
	28 invokevirtual (0, 1)
	31 invokevirtual (0, 1)
	34 ifeq (0, 1)
	37 aload_0 (0, 1)
	38 aload_1 (0, 1)
	39 invokevirtual (0, 1)
	42 invokevirtual (0, 1)
	45 ifeq (0, 1)
	48 iconst_1 (0, 1)
	49 goto (0, 1)
	52 iconst_0 (0, 1)
	53 ireturn (0, 1)

Method: isFull
	0 aload_1 (1, 1)
	1 invokevirtual (1, 1)
	4 ifnonnull (1, 1)
	7 aload_1 (1, 1)
	8 invokevirtual (1, 1)
	11 checkcast (1, 1)
	14 invokevirtual (1, 1)
	17 ireturn (1, 1)
	18 aload_0 (0, 1)
	19 aload_1 (0, 1)
	20 invokevirtual (0, 1)
	23 invokevirtual (0, 1)
	26 ifeq (0, 1)
	29 aload_0 (0, 1)
	30 aload_1 (0, 1)
	31 invokevirtual (0, 1)
	34 invokevirtual (0, 1)
	37 ifeq (0, 1)
	40 iconst_1 (0, 1)
	41 goto (0, 1)
	44 iconst_0 (0, 1)
	45 ireturn (0, 1)

Method: contains
	0 new (0, 1)
	3 dup (0, 1)
	4 invokespecial (0, 1)
	7 aload_1 (0, 1)
	8 aload_0 (0, 1)
	9 invokevirtual (0, 1)
	12 invokeinterface (0, 1)
	17 ireturn (0, 1)

Method: projectToBoundary
	0 new (0, 0)
	3 dup (0, 0)
	4 aload_1 (0, 0)
	5 invokespecial (0, 0)
	8 astore_2 (0, 0)
	9 aload_0 (0, 0)
	10 iconst_1 (0, 0)
	11 invokevirtual (0, 0)
	14 aload_2 (0, 0)
	15 invokevirtual (0, 0)
	18 aload_2 (0, 0)
	19 invokevirtual (0, 0)
	22 areturn (0, 0)

Method: checkPoint
	0 aload_1 (0, 0)
	1 aload_2 (0, 0)
	2 aload_0 (0, 0)
	3 getfield (0, 0)
	6 invokevirtual (0, 0)
	9 astore_3 (0, 0)
	10 aload_3 (1, 1)
	11 invokevirtual (1, 1)
	14 ifnonnull (1, 1)
	17 aload_3 (1, 1)
	18 invokevirtual (1, 1)
	21 checkcast (1, 1)
	24 invokevirtual (1, 1)
	27 ifeq (1, 1)
	30 getstatic (1, 1)
	33 goto (1, 1)
	36 getstatic (1, 1)
	39 areturn (1, 1)
	40 aload_0 (0, 0)
	41 aload_3 (0, 0)
	42 invokevirtual (0, 0)
	45 aload_2 (0, 0)
	46 invokevirtual (0, 0)
	49 astore (0, 0)
	51 aload_0 (0, 0)
	52 aload_3 (0, 0)
	53 invokevirtual (0, 0)
	56 aload_2 (0, 0)
	57 invokevirtual (0, 0)
	60 astore (0, 0)
	62 aload (0, 0)
	64 aload (0, 0)
	66 if_acmpne (0, 0)
	69 aload (0, 0)
	71 goto (0, 0)
	74 getstatic (0, 0)
	77 areturn (0, 0)

Method: getTree
	0 iload_1 (1, 1)
	1 ifeq (1, 1)
	4 aload_0 (1, 1)
	5 getfield (1, 1)
	8 invokevirtual (1, 1)
	11 ifnull (1, 1)
	14 aload_0 (1, 1)
	15 getfield (1, 1)
	18 invokevirtual (1, 1)
	21 ifnonnull (1, 1)
	24 aload_0 (1, 1)
	25 getfield (1, 1)
	28 new (1, 1)
	31 dup (1, 1)
	32 invokespecial (1, 1)
	35 invokevirtual (1, 1)
	38 aload_0 (0, 0)
	39 getfield (0, 0)
	42 areturn (0, 0)

Method: getBoundarySize
	0 new (0, 0)
	3 dup (0, 0)
	4 invokespecial (0, 0)
	7 astore_1 (0, 0)
	8 aload_0 (0, 0)
	9 iconst_1 (0, 0)
	10 invokevirtual (0, 0)
	13 aload_1 (0, 0)
	14 invokevirtual (0, 0)
	17 aload_1 (0, 0)
	18 invokevirtual (0, 0)
	21 dreturn (0, 0)

Method: getSize
	0 aload_0 (1, 1)
	1 getfield (1, 1)
	4 ifnonnull (1, 1)
	7 aload_0 (1, 1)
	8 invokevirtual (1, 1)
	11 aload_0 (0, 0)
	12 getfield (0, 0)
	15 dreturn (0, 0)

Method: setSize
	0 aload_0 (0, 0)
	1 dload_1 (0, 0)
	2 putfield (0, 0)
	5 return (0, 0)

Method: getBarycenter
	0 aload_0 (1, 1)
	1 getfield (1, 1)
	4 ifnonnull (1, 1)
	7 aload_0 (1, 1)
	8 invokevirtual (1, 1)
	11 aload_0 (0, 0)
	12 getfield (0, 0)
	15 areturn (0, 0)

Method: setBarycenter
	0 aload_0 (0, 0)
	1 aload_1 (0, 0)
	2 putfield (0, 0)
	5 return (0, 0)

Method: side
	0 new (0, 0)
	3 dup (0, 0)
	4 aload_0 (0, 0)
	5 invokespecial (0, 0)
	8 astore_2 (0, 0)
	9 aload_2 (0, 0)
	10 aload_0 (0, 0)
	11 getfield (0, 0)
	14 aload_1 (0, 0)
	15 invokeinterface (0, 0)
	20 invokevirtual (0, 0)
	23 aload_2 (0, 0)
	24 invokevirtual (0, 0)
	27 ifeq (0, 0)
	30 aload_2 (0, 0)
	31 invokevirtual (0, 0)
	34 ifeq (0, 0)
	37 getstatic (0, 0)
	40 goto (0, 0)
	43 getstatic (0, 0)
	46 goto (0, 0)
	49 aload_2 (0, 0)
	50 invokevirtual (0, 0)
	53 ifeq (0, 0)
	56 getstatic (0, 0)
	59 goto (0, 0)
	62 getstatic (0, 0)
	65 areturn (0, 0)

Method: intersection
	0 aload_0 (0, 0)
	1 aload_0 (0, 0)
	2 getfield (0, 0)
	5 aload_1 (0, 0)
	6 invokespecial (0, 0)
	9 areturn (0, 0)

Method: recurseIntersection
	0 aload_1 (1, 1)
	1 invokevirtual (1, 1)
	4 ifnonnull (1, 1)
	7 aload_1 (1, 1)
	8 invokevirtual (1, 1)
	11 checkcast (1, 1)
	14 invokevirtual (1, 1)
	17 ifeq (1, 1)
	20 aload_2 (1, 1)
	21 invokeinterface (1, 1)
	26 goto (1, 1)
	29 aconst_null (1, 1)
	30 areturn (1, 1)
	31 aload_1 (0, 0)
	32 invokevirtual (0, 0)
	35 invokeinterface (0, 0)
	40 astore_3 (0, 0)
	41 aload_2 (0, 0)
	42 aload_3 (0, 0)
	43 invokeinterface (0, 0)
	48 astore (0, 0)
	50 aload (1, 1)
	52 invokevirtual (1, 1)
	55 ifnull (1, 1)
	58 aload (2, 1)
	60 invokevirtual (2, 1)
	63 ifnull (2, 1)
	66 aload_0 (2, 1)
	67 aload_1 (2, 1)
	68 invokevirtual (2, 1)
	71 aload (2, 1)
	73 invokevirtual (2, 1)
	76 invokespecial (2, 1)
	79 astore (2, 1)
	81 aload_0 (2, 1)
	82 aload_1 (2, 1)
	83 invokevirtual (2, 1)
	86 aload (2, 1)
	88 invokevirtual (2, 1)
	91 invokespecial (2, 1)
	94 astore (2, 1)
	96 aload (3, 1)
	98 ifnonnull (3, 1)
	101 aload (3, 1)
	103 areturn (3, 1)
	104 aload (3, 1)
	106 ifnonnull (3, 1)
	109 aload (3, 1)
	111 areturn (3, 1)
	112 aload (3, 2)
	114 aload (3, 2)
	116 invokeinterface (3, 2)
	121 areturn (3, 2)
	122 aload_0 (2, 2)
	123 aload_1 (2, 2)
	124 invokevirtual (2, 2)
	127 aload_2 (2, 2)
	128 invokespecial (2, 2)
	131 areturn (2, 2)
	132 aload (1, 1)
	134 invokevirtual (1, 1)
	137 ifnull (1, 1)
	140 aload_0 (1, 1)
	141 aload_1 (1, 1)
	142 invokevirtual (1, 1)
	145 aload_2 (1, 1)
	146 invokespecial (1, 1)
	149 areturn (1, 1)
	150 aload_0 (1, 2)
	151 aload_1 (1, 2)
	152 invokevirtual (1, 2)
	155 aload_0 (1, 2)
	156 aload_1 (1, 2)
	157 invokevirtual (1, 2)
	160 aload_2 (1, 2)
	161 invokespecial (1, 2)
	164 invokespecial (1, 2)
	167 areturn (1, 2)

Method: applyTransform
	0 new (0, 0)
	3 dup (0, 0)
	4 invokespecial (0, 0)
	7 astore_2 (0, 0)
	8 aload_0 (0, 4)
	9 aload_0 (0, 4)
	10 iconst_0 (0, 4)
	11 invokevirtual (0, 4)
	14 aload_1 (0, 4)
	15 aload_2 (0, 4)
	16 invokespecial (0, 4)
	19 astore_3 (0, 4)
	20 aload_2 (1, 4)
	21 invokeinterface (1, 4)
	26 invokeinterface (1, 4)
	31 astore (1, 4)
	33 aload (1, 4)
	35 invokeinterface (1, 4)
	40 ifeq (1, 4)
	43 aload (1, 4)
	45 invokeinterface (1, 4)
	50 checkcast (1, 4)
	53 astore (1, 4)
	55 aload (2, 1)
	57 invokeinterface (2, 1)
	62 checkcast (2, 1)
	65 invokevirtual (2, 1)
	68 ifnull (2, 1)
	71 aload (2, 1)
	73 invokeinterface (2, 1)
	78 checkcast (2, 1)
	81 invokevirtual (2, 1)
	84 checkcast (2, 1)
	87 astore (2, 1)
	89 aload (3, 1)
	91 ifnull (3, 1)
	94 aload (3, 4)
	96 invokeinterface (3, 4)
	101 checkcast (3, 4)
	104 invokevirtual (3, 4)
	107 checkcast (3, 4)
	110 astore (3, 4)
	112 aload (4, 4)
	114 invokevirtual (4, 4)
	117 invokevirtual (4, 4)
	120 astore (4, 4)
	122 aload (4, 4)
	124 invokeinterface (4, 4)
	129 ifeq (4, 4)
	132 aload (4, 4)
	134 invokeinterface (4, 4)
	139 checkcast (4, 4)
	142 astore (4, 4)
	144 aload (4, 4)
	146 invokevirtual (4, 4)
	149 aload_2 (4, 4)
	150 aload (4, 4)
	152 invokeinterface (4, 4)
	157 checkcast (4, 4)
	160 invokevirtual (4, 4)
	163 goto (3, 4)
	166 goto (0, 1)
	169 aload_0 (0, 4)
	170 aload_3 (0, 4)
	171 invokevirtual (0, 4)
	174 areturn (0, 4)

Method: recurseTransform
	0 aload_1 (1, 1)
	1 invokevirtual (1, 1)
	4 ifnonnull (1, 1)
	7 new (1, 4)
	10 dup (1, 4)
	11 aload_1 (1, 4)
	12 invokevirtual (1, 4)
	15 invokespecial (1, 4)
	18 astore (1, 4)
	20 goto (1, 4)
	23 aload_1 (1, 2)
	24 invokevirtual (1, 2)
	27 astore (1, 2)
	29 aload (1, 4)
	31 checkcast (1, 4)
	34 aload_2 (1, 4)
	35 invokevirtual (1, 4)
	38 astore (1, 4)
	40 aload_1 (1, 4)
	41 invokevirtual (1, 4)
	44 checkcast (1, 4)
	47 astore (1, 4)
	49 aload (2, 1)
	51 ifnull (2, 1)
	54 aload (2, 1)
	56 invokevirtual (2, 1)
	59 ifnonnull (2, 1)
	62 aconst_null (2, 1)
	63 goto (2, 1)
	66 aload (2, 1)
	68 invokevirtual (2, 4)
	71 checkcast (2, 4)
	74 aload_2 (2, 4)
	75 invokevirtual (2, 4)
	78 astore (2, 4)
	80 aload (2, 4)
	82 invokevirtual (2, 4)
	85 ifnonnull (2, 4)
	88 aconst_null (2, 4)
	89 goto (2, 4)
	92 aload (2, 4)
	94 invokevirtual (2, 4)
	97 checkcast (2, 4)
	100 aload_2 (2, 4)
	101 invokevirtual (2, 4)
	104 astore (2, 4)
	106 new (2, 4)
	109 dup (2, 4)
	110 aload (2, 4)
	112 aload (2, 4)
	114 new (2, 4)
	117 dup (2, 4)
	118 invokespecial (2, 4)
	121 invokespecial (2, 4)
	124 astore (2, 4)
	126 new (1, 4)
	129 dup (1, 4)
	130 aload (1, 4)
	132 aload_0 (1, 4)
	133 aload_1 (1, 4)
	134 invokevirtual (1, 4)
	137 aload_2 (1, 4)
	138 aload_3 (1, 4)
	139 invokespecial (1, 4)
	142 aload_0 (1, 4)
	143 aload_1 (1, 4)
	144 invokevirtual (1, 4)
	147 aload_2 (1, 4)
	148 aload_3 (1, 4)
	149 invokespecial (1, 4)
	152 aload (1, 4)
	154 invokespecial (1, 4)
	157 astore (1, 4)
	159 aload_3 (0, 4)
	160 aload_1 (0, 4)
	161 aload (0, 4)
	163 invokeinterface (0, 4)
	168 pop (0, 4)
	169 aload (0, 4)
	171 areturn (0, 4)

Method: buildNew
	0 aload_0 (0, 0)
	1 aload_1 (0, 0)
	2 invokevirtual (0, 0)
	5 areturn (0, 0)

