Method: <init>
	0 aload_0 (0, 0)
	1 invokespecial (0, 0)
	4 aload_0 (0, 0)
	5 aload_1 (0, 0)
	6 putfield (0, 0)
	9 aload_0 (0, 0)
	10 aload_2 (0, 0)
	11 putfield (0, 0)
	14 return (0, 0)

Method: copySelf
	0 aload_0 (0, 0)
	1 invokevirtual (0, 0)
	4 areturn (0, 0)

Method: getHyperplane
	0 aload_0 (0, 0)
	1 getfield (0, 0)
	4 areturn (0, 0)

Method: getRemainingRegion
	0 aload_0 (0, 0)
	1 getfield (0, 0)
	4 areturn (0, 0)

Method: getSize
	0 aload_0 (0, 0)
	1 getfield (0, 0)
	4 invokeinterface (0, 0)
	9 dreturn (0, 0)

Method: reunite
	0 aload_0 (0, 0)
	1 aload_1 (0, 0)
	2 invokevirtual (0, 0)
	5 areturn (0, 0)

Method: applyTransform
	0 aload_1 (0, 4)
	1 aload_0 (0, 4)
	2 getfield (0, 4)
	5 invokeinterface (0, 4)
	10 astore_2 (0, 4)
	11 new (0, 4)
	14 dup (0, 4)
	15 invokespecial (0, 4)
	18 astore_3 (0, 4)
	19 aload_0 (0, 4)
	20 aload_0 (0, 4)
	21 getfield (0, 4)
	24 iconst_0 (0, 4)
	25 invokeinterface (0, 4)
	30 aload_2 (0, 4)
	31 aload_1 (0, 4)
	32 aload_3 (0, 4)
	33 invokespecial (0, 4)
	36 astore (0, 4)
	38 aload_3 (1, 4)
	39 invokeinterface (1, 4)
	44 invokeinterface (1, 4)
	49 astore (1, 4)
	51 aload (1, 4)
	53 invokeinterface (1, 4)
	58 ifeq (1, 4)
	61 aload (1, 4)
	63 invokeinterface (1, 4)
	68 checkcast (1, 4)
	71 astore (1, 4)
	73 aload (2, 1)
	75 invokeinterface (2, 1)
	80 checkcast (2, 1)
	83 invokevirtual (2, 1)
	86 ifnull (2, 1)
	89 aload (2, 1)
	91 invokeinterface (2, 1)
	96 checkcast (2, 1)
	99 invokevirtual (2, 1)
	102 checkcast (2, 1)
	105 astore (2, 1)
	107 aload (3, 1)
	109 ifnull (3, 1)
	112 aload (3, 4)
	114 invokeinterface (3, 4)
	119 checkcast (3, 4)
	122 invokevirtual (3, 4)
	125 checkcast (3, 4)
	128 astore (3, 4)
	130 aload (4, 4)
	132 invokevirtual (4, 4)
	135 invokevirtual (4, 4)
	138 astore (4, 4)
	140 aload (4, 4)
	142 invokeinterface (4, 4)
	147 ifeq (4, 4)
	150 aload (4, 4)
	152 invokeinterface (4, 4)
	157 checkcast (4, 4)
	160 astore (4, 4)
	162 aload (4, 4)
	164 invokevirtual (4, 4)
	167 aload_3 (4, 4)
	168 aload (4, 4)
	170 invokeinterface (4, 4)
	175 checkcast (4, 4)
	178 invokevirtual (4, 4)
	181 goto (3, 4)
	184 goto (0, 1)
	187 aload_0 (0, 1)
	188 aload_2 (0, 1)
	189 aload_0 (0, 1)
	190 getfield (0, 1)
	193 aload (0, 1)
	195 invokeinterface (0, 1)
	200 invokevirtual (0, 1)
	203 areturn (0, 1)

Method: recurseTransform
	0 aload_1 (1, 1)
	1 invokevirtual (1, 1)
	4 ifnonnull (1, 1)
	7 new (1, 4)
	10 dup (1, 4)
	11 aload_1 (1, 4)
	12 invokevirtual (1, 4)
	15 invokespecial (1, 4)
	18 astore (1, 4)
	20 goto (1, 4)
	23 aload_1 (1, 2)
	24 invokevirtual (1, 2)
	27 checkcast (1, 2)
	30 astore (1, 2)
	32 aload (2, 1)
	34 ifnull (2, 1)
	37 aload (2, 1)
	39 invokevirtual (2, 1)
	42 ifnonnull (2, 1)
	45 aconst_null (2, 1)
	46 goto (2, 1)
	49 aload_3 (2, 1)
	50 aload (2, 1)
	52 invokevirtual (2, 4)
	55 aload_0 (2, 4)
	56 getfield (2, 4)
	59 aload_2 (2, 4)
	60 invokeinterface (2, 4)
	65 astore (2, 4)
	67 aload (2, 4)
	69 invokevirtual (2, 4)
	72 ifnonnull (2, 4)
	75 aconst_null (2, 4)
	76 goto (2, 4)
	79 aload_3 (2, 4)
	80 aload (2, 4)
	82 invokevirtual (2, 4)
	85 aload_0 (2, 4)
	86 getfield (2, 4)
	89 aload_2 (2, 4)
	90 invokeinterface (2, 4)
	95 astore (2, 4)
	97 new (2, 4)
	100 dup (2, 4)
	101 aload (2, 4)
	103 aload (2, 4)
	105 new (2, 4)
	108 dup (2, 4)
	109 invokespecial (2, 4)
	112 invokespecial (2, 4)
	115 astore (2, 4)
	117 new (1, 4)
	120 dup (1, 4)
	121 aload_3 (1, 4)
	122 aload_1 (1, 4)
	123 invokevirtual (1, 4)
	126 aload_0 (1, 4)
	127 getfield (1, 4)
	130 aload_2 (1, 4)
	131 invokeinterface (1, 4)
	136 aload_0 (1, 4)
	137 aload_1 (1, 4)
	138 invokevirtual (1, 4)
	141 aload_2 (1, 4)
	142 aload_3 (1, 4)
	143 aload (1, 4)
	145 invokespecial (1, 4)
	148 aload_0 (1, 4)
	149 aload_1 (1, 4)
	150 invokevirtual (1, 4)
	153 aload_2 (1, 4)
	154 aload_3 (1, 4)
	155 aload (1, 4)
	157 invokespecial (1, 4)
	160 aload (1, 4)
	162 invokespecial (1, 4)
	165 astore (1, 4)
	167 aload (0, 4)
	169 aload_1 (0, 4)
	170 aload (0, 4)
	172 invokeinterface (0, 4)
	177 pop (0, 4)
	178 aload (0, 4)
	180 areturn (0, 4)

Method: side
	0 aload_0 (0, 0)
	1 aload_1 (0, 0)
	2 invokevirtual (0, 0)
	5 invokevirtual (0, 0)
	8 areturn (0, 0)

Method: isEmpty
	0 aload_0 (0, 0)
	1 getfield (0, 0)
	4 invokeinterface (0, 0)
	9 ireturn (0, 0)

