Method: <init>
	0 aload_0 (0, 0)
	1 invokespecial (0, 0)
	2 java/lang/Object.<init>:()V (0, 0)
	4 aload_0 (0, 0)
	5 dload_2 (0, 0)
	6 putfield (0, 0)
	7 org/apache/commons/math3/geometry/partitioning/AbstractRegion.tolerance:D (0, 0)
	9 aload_1 (2, 1)
	10 ifnull (2, 1)
	11 8 (2, 1)
	13 aload_1 (2, 1)
	14 arraylength (2, 1)
	15 ifne (2, 1)
	16 20 (2, 1)
	18 aload_0 (2, 1)
	19 new (2, 1)
	20 org/apache/commons/math3/geometry/partitioning/BSPTree (2, 1)
	22 dup (2, 1)
	23 getstatic (2, 1)
	24 java/lang/Boolean.FALSE:Ljava/lang/Boolean; (2, 1)
	26 invokespecial (2, 1)
	27 org/apache/commons/math3/geometry/partitioning/BSPTree.<init>:(Ljava/lang/Object;)V (2, 1)
	29 putfield (2, 1)
	30 org/apache/commons/math3/geometry/partitioning/AbstractRegion.tree:Lorg/apache/commons/math3/geometry/partitioning/BSPTree; (2, 1)
	32 goto (2, 1)
	33 108 (2, 1)
	35 aload_0 (2, 2)
	36 aload_1 (2, 2)
	37 iconst_0 (2, 2)
	38 aaload (2, 2)
	39 invokeinterface (2, 2)
	40 org/apache/commons/math3/geometry/partitioning/Hyperplane.getTree:(Z)Lorg/apache/commons/math3/geometry/partitioning/BSPTree; (2, 2)
	42 0 (2, 2)
	44 iconst_0 (2, 2)
	45 invokeinterface (2, 2)
	46 org/apache/commons/math3/geometry/partitioning/Region.setAttribute:(Ljava/lang/Object;)V (2, 2)
	48 0 (2, 2)
	50 putfield (2, 2)
	51 org/apache/commons/math3/geometry/partitioning/AbstractRegion.tree:Lorg/apache/commons/math3/geometry/partitioning/BSPTree; (2, 2)
	53 aload_0 (2, 2)
	54 getfield (2, 2)
	55 org/apache/commons/math3/geometry/partitioning/AbstractRegion.tree:Lorg/apache/commons/math3/geometry/partitioning/BSPTree; (2, 2)
	57 astore (2, 2)
	58 #4 (2, 2)
	59 aload (2, 2)
	60 #4 (2, 2)
	61 getstatic (2, 2)
	62 java/lang/Boolean.TRUE:Ljava/lang/Boolean; (2, 2)
	64 invokevirtual (2, 2)
	65 org/apache/commons/math3/geometry/partitioning/BSPTree.setAttribute:(Ljava/lang/Object;)V (2, 2)
	67 aload_1 (3, 4)
	68 astore (3, 4)
	69 #5 (3, 4)
	70 aload (3, 4)
	71 #5 (3, 4)
	72 arraylength (3, 4)
	73 istore (3, 4)
	74 #6 (3, 4)
	75 iconst_0 (3, 4)
	76 istore (3, 4)
	77 #7 (3, 4)
	78 iload (3, 4)
	79 #7 (3, 4)
	80 iload (3, 4)
	81 #6 (3, 4)
	82 if_icmpge (3, 4)
	83 58 (3, 4)
	85 aload (3, 4)
	86 #5 (3, 4)
	87 iload (3, 4)
	88 #7 (3, 4)
	89 aaload (3, 4)
	90 astore (3, 4)
	91 #8 (3, 4)
	92 aload (4, 1)
	93 #4 (4, 1)
	94 aload (4, 1)
	95 #8 (4, 1)
	96 invokevirtual (4, 1)
	97 org/apache/commons/math3/geometry/partitioning/BSPTree.insertCut:(Lorg/apache/commons/math3/geometry/partitioning/Hyperplane;)Z (4, 1)
	99 ifeq (4, 1)
	100 35 (4, 1)
	102 aload (4, 1)
	103 #4 (4, 1)
	104 aconst_null (4, 1)
	105 invokevirtual (4, 1)
	106 org/apache/commons/math3/geometry/partitioning/BSPTree.setAttribute:(Ljava/lang/Object;)V (4, 1)
	108 aload (4, 1)
	109 #4 (4, 1)
	110 invokevirtual (4, 1)
	111 org/apache/commons/math3/geometry/partitioning/BSPTree.getPlus:()Lorg/apache/commons/math3/geometry/partitioning/BSPTree; (4, 1)
	113 getstatic (4, 1)
	114 java/lang/Boolean.FALSE:Ljava/lang/Boolean; (4, 1)
	116 invokevirtual (4, 1)
	117 org/apache/commons/math3/geometry/partitioning/BSPTree.setAttribute:(Ljava/lang/Object;)V (4, 1)
	119 aload (4, 1)
	120 #4 (4, 1)
	121 invokevirtual (4, 1)
	122 org/apache/commons/math3/geometry/partitioning/BSPTree.getMinus:()Lorg/apache/commons/math3/geometry/partitioning/BSPTree; (4, 1)
	124 astore (4, 1)
	125 #4 (4, 1)
	126 aload (4, 1)
	127 #4 (4, 1)
	128 getstatic (4, 1)
	129 java/lang/Boolean.TRUE:Ljava/lang/Boolean; (4, 1)
	131 invokevirtual (4, 1)
	132 org/apache/commons/math3/geometry/partitioning/BSPTree.setAttribute:(Ljava/lang/Object;)V (4, 1)
	134 iinc (4, 1)
	135 #7 (4, 1)
	136 -89 (4, 1)
	137 goto (4, 1)
	138 -59 (4, 1)
	140 return (0, 0)

Method: getTolerance
	0 aload_0 (0, 0)
	1 getfield (0, 0)
	2 org/apache/commons/math3/geometry/partitioning/AbstractRegion.tolerance:D (0, 0)
	4 dreturn (0, 0)

Method: insertCuts
	0 aload_2 (0, 0)
	1 invokeinterface (0, 0)
	2 java/util/Collection.java/util/Iterator (0, 0)
	4 0 (0, 0)
	6 astore_3 (0, 0)
	7 aconst_null (0, 0)
	8 astore (0, 0)
	9 #4 (0, 0)
	10 aload (1, 3)
	11 #4 (1, 3)
	12 ifnonnull (1, 3)
	13 48 (1, 3)
	15 aload_3 (1, 3)
	16 invokeinterface (1, 3)
	17 java/util/Iterator.next:()Ljava/lang/Object; (1, 3)
	19 0 (1, 3)
	21 ifeq (1, 3)
	22 39 (1, 3)
	24 aload_3 (1, 3)
	25 invokeinterface (1, 3)
	26 java/util/Iterator.org/apache/commons/math3/geometry/partitioning/SubHyperplane (1, 3)
	28 0 (1, 3)
	30 checkcast (1, 3)
	31 org/apache/commons/math3/geometry/partitioning/SubHyperplane (1, 3)
	33 invokeinterface (1, 3)
	34 org/apache/commons/math3/geometry/partitioning/SubHyperplane.copySelf:()Lorg/apache/commons/math3/geometry/partitioning/Hyperplane; (1, 3)
	36 0 (1, 3)
	38 astore (1, 3)
	39 #4 (1, 3)
	40 aload_1 (2, 1)
	41 aload (2, 1)
	42 #4 (2, 1)
	43 invokeinterface (2, 1)
	44 org/apache/commons/math3/geometry/partitioning/Hyperplane.java/util/ArrayList (2, 1)
	46 0 (2, 1)
	48 invokevirtual (2, 1)
	49 org/apache/commons/math3/geometry/partitioning/BSPTree.insertCut:(Lorg/apache/commons/math3/geometry/partitioning/Hyperplane;)Z (2, 1)
	51 ifne (2, 1)
	52 -41 (2, 1)
	54 aconst_null (2, 1)
	55 astore (2, 1)
	56 #4 (2, 1)
	57 goto (2, 1)
	58 -47 (2, 1)
	60 aload_3 (1, 1)
	61 invokeinterface (1, 1)
	62 java/util/Iterator.next:()Ljava/lang/Object; (1, 1)
	64 0 (1, 1)
	66 ifne (1, 1)
	67 4 (1, 1)
	69 return (1, 1)
	70 new (0, 0)
	71 java/util/ArrayList (0, 0)
	73 dup (0, 0)
	74 invokespecial (0, 0)
	75 java/util/ArrayList.<init>:()V (0, 0)
	77 astore (0, 0)
	78 #5 (0, 0)
	79 new (0, 0)
	80 java/util/ArrayList (0, 0)
	82 dup (0, 0)
	83 invokespecial (0, 0)
	84 java/util/ArrayList.<init>:()V (0, 0)
	86 astore (0, 0)
	87 #6 (0, 0)
	88 aload_3 (1, 3)
	89 invokeinterface (1, 3)
	90 java/util/Iterator.next:()Ljava/lang/Object; (1, 3)
	92 0 (1, 3)
	94 ifeq (1, 3)
	95 112 (1, 3)
	97 aload_3 (1, 3)
	98 invokeinterface (1, 3)
	99 java/util/Iterator.org/apache/commons/math3/geometry/partitioning/SubHyperplane (1, 3)
	101 0 (1, 3)
	103 checkcast (1, 3)
	104 org/apache/commons/math3/geometry/partitioning/SubHyperplane (1, 3)
	106 astore (1, 3)
	107 #7 (1, 3)
	108 aload (1, 3)
	109 #7 (1, 3)
	110 aload (1, 3)
	111 #4 (1, 3)
	112 invokeinterface (1, 3)
	113 org/apache/commons/math3/geometry/partitioning/SubHyperplane.$SwitchMap$org$apache$commons$math3$geometry$partitioning$Side:[I (1, 3)
	115 0 (1, 3)
	117 astore (1, 3)
	118 #8 (1, 3)
	119 getstatic (2, 5)
	120 org/apache/commons/math3/geometry/partitioning/AbstractRegion$3.$SwitchMap$org$apache$commons$math3$geometry$partitioning$Side:[I (2, 5)
	122 aload (2, 5)
	123 #8 (2, 5)
	124 invokevirtual (2, 5)
	125 org/apache/commons/math3/geometry/partitioning/SubHyperplane$SplitSubHyperplane.getSide:()Lorg/apache/commons/math3/geometry/partitioning/Side; (2, 5)
	127 invokevirtual (2, 5)
	128 org/apache/commons/math3/geometry/partitioning/Side.ordinal:()I (2, 5)
	130 iaload (2, 5)
	131 tableswitch (2, 5)
	132 1 156 (2, 5)
	136 2 167 (2, 5)
	140 3 178 (2, 5)
	156 aload (2, 5)
	157 #5 (2, 5)
	158 aload (2, 5)
	159 #7 (2, 5)
	160 invokevirtual (2, 5)
	161 java/util/ArrayList.add:(Ljava/lang/Object;)Z (2, 5)
	163 pop (2, 5)
	164 goto (2, 5)
	165 39 (2, 5)
	167 aload (2, 5)
	168 #6 (2, 5)
	169 aload (2, 5)
	170 #7 (2, 5)
	171 invokevirtual (2, 5)
	172 java/util/ArrayList.add:(Ljava/lang/Object;)Z (2, 5)
	174 pop (2, 5)
	175 goto (2, 5)
	176 28 (2, 5)
	178 aload (2, 5)
	179 #5 (2, 5)
	180 aload (2, 5)
	181 #8 (2, 5)
	182 invokevirtual (2, 5)
	183 org/apache/commons/math3/geometry/partitioning/SubHyperplane$SplitSubHyperplane.getPlus:()Lorg/apache/commons/math3/geometry/partitioning/SubHyperplane; (2, 5)
	185 invokevirtual (2, 5)
	186 java/util/ArrayList.add:(Ljava/lang/Object;)Z (2, 5)
	188 pop (2, 5)
	189 aload (2, 5)
	190 #6 (2, 5)
	191 aload (2, 5)
	192 #8 (2, 5)
	193 invokevirtual (2, 5)
	194 org/apache/commons/math3/geometry/partitioning/SubHyperplane$SplitSubHyperplane.getMinus:()Lorg/apache/commons/math3/geometry/partitioning/SubHyperplane; (2, 5)
	196 invokevirtual (2, 5)
	197 java/util/ArrayList.add:(Ljava/lang/Object;)Z (2, 5)
	199 pop (2, 5)
	200 goto (2, 5)
	201 3 (2, 5)
	203 goto (0, 0)
	204 -115 (0, 0)
	206 aload_0 (0, 0)
	207 aload_1 (0, 0)
	208 invokevirtual (0, 0)
	209 org/apache/commons/math3/geometry/partitioning/BSPTree.getPlus:()Lorg/apache/commons/math3/geometry/partitioning/BSPTree; (0, 0)
	211 aload (0, 0)
	212 #5 (0, 0)
	213 invokespecial (0, 0)
	214 org/apache/commons/math3/geometry/partitioning/AbstractRegion.insertCuts:(Lorg/apache/commons/math3/geometry/partitioning/BSPTree;Ljava/util/Collection;)V (0, 0)
	216 aload_0 (0, 0)
	217 aload_1 (0, 0)
	218 invokevirtual (0, 0)
	219 org/apache/commons/math3/geometry/partitioning/BSPTree.getMinus:()Lorg/apache/commons/math3/geometry/partitioning/BSPTree; (0, 0)
	221 aload (0, 0)
	222 #6 (0, 0)
	223 invokespecial (0, 0)
	224 org/apache/commons/math3/geometry/partitioning/AbstractRegion.insertCuts:(Lorg/apache/commons/math3/geometry/partitioning/BSPTree;Ljava/util/Collection;)V (0, 0)
	226 return (0, 0)

Method: copySelf
	0 aload_0 (0, 0)
	1 invokevirtual (0, 0)
	2 org/apache/commons/math3/geometry/partitioning/AbstractRegion.copySelf:()Lorg/apache/commons/math3/geometry/partitioning/AbstractRegion; (0, 0)
	4 areturn (0, 0)

Method: isEmpty
	0 aload_1 (1, 1)
	1 invokevirtual (1, 1)
	2 org/apache/commons/math3/geometry/partitioning/BSPTree.getCut:()Lorg/apache/commons/math3/geometry/partitioning/SubHyperplane; (1, 1)
	4 ifnonnull (1, 1)
	5 22 (1, 1)
	7 aload_1 (1, 1)
	8 invokevirtual (1, 1)
	9 org/apache/commons/math3/geometry/partitioning/BSPTree.getAttribute:()Ljava/lang/Object; (1, 1)
	11 checkcast (1, 1)
	12 java/lang/Boolean (1, 1)
	14 invokevirtual (1, 1)
	15 java/lang/Boolean.booleanValue:()Z (1, 1)
	17 ifne (1, 1)
	18 7 (1, 1)
	20 iconst_1 (1, 1)
	21 goto (1, 1)
	22 4 (1, 1)
	24 iconst_0 (1, 1)
	25 ireturn (1, 1)
	26 aload_0 (0, 0)
	27 aload_1 (0, 0)
	28 invokevirtual (0, 0)
	29 org/apache/commons/math3/geometry/partitioning/BSPTree.getMinus:()Lorg/apache/commons/math3/geometry/partitioning/BSPTree; (0, 0)
	31 invokevirtual (0, 0)
	32 org/apache/commons/math3/geometry/partitioning/AbstractRegion.isEmpty:(Lorg/apache/commons/math3/geometry/partitioning/BSPTree;)Z (0, 0)
	34 ifeq (0, 0)
	35 18 (0, 0)
	37 aload_0 (0, 0)
	38 aload_1 (0, 0)
	39 invokevirtual (0, 0)
	40 org/apache/commons/math3/geometry/partitioning/BSPTree.getPlus:()Lorg/apache/commons/math3/geometry/partitioning/BSPTree; (0, 0)
	42 invokevirtual (0, 0)
	43 org/apache/commons/math3/geometry/partitioning/AbstractRegion.isEmpty:(Lorg/apache/commons/math3/geometry/partitioning/BSPTree;)Z (0, 0)
	45 ifeq (0, 0)
	46 7 (0, 0)
	48 iconst_1 (0, 0)
	49 goto (0, 0)
	50 4 (0, 0)
	52 iconst_0 (0, 0)
	53 ireturn (0, 0)

Method: isFull
	0 aload_1 (1, 1)
	1 invokevirtual (1, 1)
	2 org/apache/commons/math3/geometry/partitioning/BSPTree.getCut:()Lorg/apache/commons/math3/geometry/partitioning/SubHyperplane; (1, 1)
	4 ifnonnull (1, 1)
	5 14 (1, 1)
	7 aload_1 (1, 1)
	8 invokevirtual (1, 1)
	9 org/apache/commons/math3/geometry/partitioning/BSPTree.getAttribute:()Ljava/lang/Object; (1, 1)
	11 checkcast (1, 1)
	12 java/lang/Boolean (1, 1)
	14 invokevirtual (1, 1)
	15 java/lang/Boolean.booleanValue:()Z (1, 1)
	17 ireturn (1, 1)
	18 aload_0 (0, 0)
	19 aload_1 (0, 0)
	20 invokevirtual (0, 0)
	21 org/apache/commons/math3/geometry/partitioning/BSPTree.getMinus:()Lorg/apache/commons/math3/geometry/partitioning/BSPTree; (0, 0)
	23 invokevirtual (0, 0)
	24 org/apache/commons/math3/geometry/partitioning/AbstractRegion.isFull:(Lorg/apache/commons/math3/geometry/partitioning/BSPTree;)Z (0, 0)
	26 ifeq (0, 0)
	27 18 (0, 0)
	29 aload_0 (0, 0)
	30 aload_1 (0, 0)
	31 invokevirtual (0, 0)
	32 org/apache/commons/math3/geometry/partitioning/BSPTree.getPlus:()Lorg/apache/commons/math3/geometry/partitioning/BSPTree; (0, 0)
	34 invokevirtual (0, 0)
	35 org/apache/commons/math3/geometry/partitioning/AbstractRegion.isFull:(Lorg/apache/commons/math3/geometry/partitioning/BSPTree;)Z (0, 0)
	37 ifeq (0, 0)
	38 7 (0, 0)
	40 iconst_1 (0, 0)
	41 goto (0, 0)
	42 4 (0, 0)
	44 iconst_0 (0, 0)
	45 ireturn (0, 0)

Method: contains
	0 new (0, 1)
	1 org/apache/commons/math3/geometry/partitioning/RegionFactory (0, 1)
	3 dup (0, 1)
	4 invokespecial (0, 1)
	5 org/apache/commons/math3/geometry/partitioning/RegionFactory.<init>:()V (0, 1)
	7 aload_1 (0, 1)
	8 aload_0 (0, 1)
	9 invokevirtual (0, 1)
	10 org/apache/commons/math3/geometry/partitioning/RegionFactory.difference:(Lorg/apache/commons/math3/geometry/partitioning/Region;Lorg/apache/commons/math3/geometry/partitioning/Region;)Lorg/apache/commons/math3/geometry/partitioning/Region; (0, 1)
	12 invokeinterface (0, 1)
	13 org/apache/commons/math3/geometry/partitioning/Region.org/apache/commons/math3/geometry/partitioning/BoundaryProjector (0, 1)
	15 0 (0, 1)
	17 ireturn (0, 1)

Method: projectToBoundary
	0 new (0, 0)
	1 org/apache/commons/math3/geometry/partitioning/BoundaryProjector (0, 0)
	3 dup (0, 0)
	4 aload_1 (0, 0)
	5 invokespecial (0, 0)
	6 org/apache/commons/math3/geometry/partitioning/BoundaryProjector.<init>:(Lorg/apache/commons/math3/geometry/Point;)V (0, 0)
	8 astore_2 (0, 0)
	9 aload_0 (0, 0)
	10 iconst_1 (0, 0)
	11 invokevirtual (0, 0)
	12 org/apache/commons/math3/geometry/partitioning/AbstractRegion.getTree:(Z)Lorg/apache/commons/math3/geometry/partitioning/BSPTree; (0, 0)
	14 aload_2 (0, 0)
	15 invokevirtual (0, 0)
	16 org/apache/commons/math3/geometry/partitioning/BSPTree.visit:(Lorg/apache/commons/math3/geometry/partitioning/BSPTreeVisitor;)V (0, 0)
	18 aload_2 (0, 0)
	19 invokevirtual (0, 0)
	20 org/apache/commons/math3/geometry/partitioning/BoundaryProjector.getProjection:()Lorg/apache/commons/math3/geometry/partitioning/BoundaryProjection; (0, 0)
	22 areturn (0, 0)

Method: checkPoint
	0 aload_1 (0, 0)
	1 aload_2 (0, 0)
	2 aload_0 (0, 0)
	3 getfield (0, 0)
	4 org/apache/commons/math3/geometry/partitioning/AbstractRegion.tolerance:D (0, 0)
	6 invokevirtual (0, 0)
	7 org/apache/commons/math3/geometry/partitioning/BSPTree.getCell:(Lorg/apache/commons/math3/geometry/Point;D)Lorg/apache/commons/math3/geometry/partitioning/BSPTree; (0, 0)
	9 astore_3 (0, 0)
	10 aload_3 (1, 1)
	11 invokevirtual (1, 1)
	12 org/apache/commons/math3/geometry/partitioning/BSPTree.getCut:()Lorg/apache/commons/math3/geometry/partitioning/SubHyperplane; (1, 1)
	14 ifnonnull (1, 1)
	15 26 (1, 1)
	17 aload_3 (1, 1)
	18 invokevirtual (1, 1)
	19 org/apache/commons/math3/geometry/partitioning/BSPTree.getAttribute:()Ljava/lang/Object; (1, 1)
	21 checkcast (1, 1)
	22 java/lang/Boolean (1, 1)
	24 invokevirtual (1, 1)
	25 java/lang/Boolean.booleanValue:()Z (1, 1)
	27 ifeq (1, 1)
	28 9 (1, 1)
	30 getstatic (1, 1)
	31 org/apache/commons/math3/geometry/partitioning/Region$Location.INSIDE:Lorg/apache/commons/math3/geometry/partitioning/Region$Location; (1, 1)
	33 goto (1, 1)
	34 6 (1, 1)
	36 getstatic (1, 1)
	37 org/apache/commons/math3/geometry/partitioning/Region$Location.OUTSIDE:Lorg/apache/commons/math3/geometry/partitioning/Region$Location; (1, 1)
	39 areturn (1, 1)
	40 aload_0 (0, 0)
	41 aload_3 (0, 0)
	42 invokevirtual (0, 0)
	43 org/apache/commons/math3/geometry/partitioning/BSPTree.getMinus:()Lorg/apache/commons/math3/geometry/partitioning/BSPTree; (0, 0)
	45 aload_2 (0, 0)
	46 invokevirtual (0, 0)
	47 org/apache/commons/math3/geometry/partitioning/AbstractRegion.checkPoint:(Lorg/apache/commons/math3/geometry/partitioning/BSPTree;Lorg/apache/commons/math3/geometry/Point;)Lorg/apache/commons/math3/geometry/partitioning/Region$Location; (0, 0)
	49 astore (0, 0)
	50 #4 (0, 0)
	51 aload_0 (0, 0)
	52 aload_3 (0, 0)
	53 invokevirtual (0, 0)
	54 org/apache/commons/math3/geometry/partitioning/BSPTree.getPlus:()Lorg/apache/commons/math3/geometry/partitioning/BSPTree; (0, 0)
	56 aload_2 (0, 0)
	57 invokevirtual (0, 0)
	58 org/apache/commons/math3/geometry/partitioning/AbstractRegion.checkPoint:(Lorg/apache/commons/math3/geometry/partitioning/BSPTree;Lorg/apache/commons/math3/geometry/Point;)Lorg/apache/commons/math3/geometry/partitioning/Region$Location; (0, 0)
	60 astore (0, 0)
	61 #5 (0, 0)
	62 aload (0, 0)
	63 #4 (0, 0)
	64 aload (0, 0)
	65 #5 (0, 0)
	66 if_acmpne (0, 0)
	67 8 (0, 0)
	69 aload (0, 0)
	70 #4 (0, 0)
	71 goto (0, 0)
	72 6 (0, 0)
	74 getstatic (0, 0)
	75 org/apache/commons/math3/geometry/partitioning/Region$Location.BOUNDARY:Lorg/apache/commons/math3/geometry/partitioning/Region$Location; (0, 0)
	77 areturn (0, 0)

Method: getTree
	0 iload_1 (1, 1)
	1 ifeq (1, 1)
	2 37 (1, 1)
	4 aload_0 (1, 1)
	5 getfield (1, 1)
	6 org/apache/commons/math3/geometry/partitioning/AbstractRegion.tree:Lorg/apache/commons/math3/geometry/partitioning/BSPTree; (1, 1)
	8 invokevirtual (1, 1)
	9 org/apache/commons/math3/geometry/partitioning/BSPTree.getCut:()Lorg/apache/commons/math3/geometry/partitioning/SubHyperplane; (1, 1)
	11 ifnull (1, 1)
	12 27 (1, 1)
	14 aload_0 (1, 1)
	15 getfield (1, 1)
	16 org/apache/commons/math3/geometry/partitioning/AbstractRegion.tree:Lorg/apache/commons/math3/geometry/partitioning/BSPTree; (1, 1)
	18 invokevirtual (1, 1)
	19 org/apache/commons/math3/geometry/partitioning/BSPTree.getAttribute:()Ljava/lang/Object; (1, 1)
	21 ifnonnull (1, 1)
	22 17 (1, 1)
	24 aload_0 (1, 1)
	25 getfield (1, 1)
	26 org/apache/commons/math3/geometry/partitioning/AbstractRegion.tree:Lorg/apache/commons/math3/geometry/partitioning/BSPTree; (1, 1)
	28 new (1, 1)
	29 org/apache/commons/math3/geometry/partitioning/BoundaryBuilder (1, 1)
	31 dup (1, 1)
	32 invokespecial (1, 1)
	33 org/apache/commons/math3/geometry/partitioning/BoundaryBuilder.<init>:()V (1, 1)
	35 invokevirtual (1, 1)
	36 org/apache/commons/math3/geometry/partitioning/BSPTree.visit:(Lorg/apache/commons/math3/geometry/partitioning/BSPTreeVisitor;)V (1, 1)
	38 aload_0 (0, 0)
	39 getfield (0, 0)
	40 org/apache/commons/math3/geometry/partitioning/AbstractRegion.tree:Lorg/apache/commons/math3/geometry/partitioning/BSPTree; (0, 0)
	42 areturn (0, 0)

Method: getBoundarySize
	0 new (0, 0)
	1 org/apache/commons/math3/geometry/partitioning/BoundarySizeVisitor (0, 0)
	3 dup (0, 0)
	4 invokespecial (0, 0)
	5 org/apache/commons/math3/geometry/partitioning/BoundarySizeVisitor.<init>:()V (0, 0)
	7 astore_1 (0, 0)
	8 aload_0 (0, 0)
	9 iconst_1 (0, 0)
	10 invokevirtual (0, 0)
	11 org/apache/commons/math3/geometry/partitioning/AbstractRegion.getTree:(Z)Lorg/apache/commons/math3/geometry/partitioning/BSPTree; (0, 0)
	13 aload_1 (0, 0)
	14 invokevirtual (0, 0)
	15 org/apache/commons/math3/geometry/partitioning/BSPTree.visit:(Lorg/apache/commons/math3/geometry/partitioning/BSPTreeVisitor;)V (0, 0)
	17 aload_1 (0, 0)
	18 invokevirtual (0, 0)
	19 org/apache/commons/math3/geometry/partitioning/BoundarySizeVisitor.getSize:()D (0, 0)
	21 dreturn (0, 0)

Method: getSize
	0 aload_0 (1, 1)
	1 getfield (1, 1)
	2 org/apache/commons/math3/geometry/partitioning/AbstractRegion.barycenter:Lorg/apache/commons/math3/geometry/Point; (1, 1)
	4 ifnonnull (1, 1)
	5 7 (1, 1)
	7 aload_0 (1, 1)
	8 invokevirtual (1, 1)
	9 org/apache/commons/math3/geometry/partitioning/AbstractRegion.computeGeometricalProperties:()V (1, 1)
	11 aload_0 (0, 0)
	12 getfield (0, 0)
	13 org/apache/commons/math3/geometry/partitioning/AbstractRegion.size:D (0, 0)
	15 dreturn (0, 0)

Method: setSize
	0 aload_0 (0, 0)
	1 dload_1 (0, 0)
	2 putfield (0, 0)
	3 org/apache/commons/math3/geometry/partitioning/AbstractRegion.size:D (0, 0)
	5 return (0, 0)

Method: getBarycenter
	0 aload_0 (1, 1)
	1 getfield (1, 1)
	2 org/apache/commons/math3/geometry/partitioning/AbstractRegion.barycenter:Lorg/apache/commons/math3/geometry/Point; (1, 1)
	4 ifnonnull (1, 1)
	5 7 (1, 1)
	7 aload_0 (1, 1)
	8 invokevirtual (1, 1)
	9 org/apache/commons/math3/geometry/partitioning/AbstractRegion.computeGeometricalProperties:()V (1, 1)
	11 aload_0 (0, 0)
	12 getfield (0, 0)
	13 org/apache/commons/math3/geometry/partitioning/AbstractRegion.barycenter:Lorg/apache/commons/math3/geometry/Point; (0, 0)
	15 areturn (0, 0)

Method: setBarycenter
	0 aload_0 (0, 0)
	1 aload_1 (0, 0)
	2 putfield (0, 0)
	3 org/apache/commons/math3/geometry/partitioning/AbstractRegion.barycenter:Lorg/apache/commons/math3/geometry/Point; (0, 0)
	5 return (0, 0)

Method: side
	0 new (0, 0)
	1 org/apache/commons/math3/geometry/partitioning/InsideFinder (0, 0)
	3 dup (0, 0)
	4 aload_0 (0, 0)
	5 invokespecial (0, 0)
	6 org/apache/commons/math3/geometry/partitioning/InsideFinder.<init>:(Lorg/apache/commons/math3/geometry/partitioning/Region;)V (0, 0)
	8 astore_2 (0, 0)
	9 aload_2 (0, 0)
	10 aload_0 (0, 0)
	11 getfield (0, 0)
	12 org/apache/commons/math3/geometry/partitioning/AbstractRegion.tree:Lorg/apache/commons/math3/geometry/partitioning/BSPTree; (0, 0)
	14 aload_1 (0, 0)
	15 invokeinterface (0, 0)
	16 org/apache/commons/math3/geometry/partitioning/Hyperplane.recurseSides:(Lorg/apache/commons/math3/geometry/partitioning/BSPTree;Lorg/apache/commons/math3/geometry/partitioning/SubHyperplane;)V (0, 0)
	18 0 (0, 0)
	20 invokevirtual (0, 0)
	21 org/apache/commons/math3/geometry/partitioning/InsideFinder.recurseSides:(Lorg/apache/commons/math3/geometry/partitioning/BSPTree;Lorg/apache/commons/math3/geometry/partitioning/SubHyperplane;)V (0, 0)
	23 aload_2 (0, 0)
	24 invokevirtual (0, 0)
	25 org/apache/commons/math3/geometry/partitioning/InsideFinder.plusFound:()Z (0, 0)
	27 ifeq (0, 0)
	28 22 (0, 0)
	30 aload_2 (0, 0)
	31 invokevirtual (0, 0)
	32 org/apache/commons/math3/geometry/partitioning/InsideFinder.minusFound:()Z (0, 0)
	34 ifeq (0, 0)
	35 9 (0, 0)
	37 getstatic (0, 0)
	38 org/apache/commons/math3/geometry/partitioning/Side.BOTH:Lorg/apache/commons/math3/geometry/partitioning/Side; (0, 0)
	40 goto (0, 0)
	41 25 (0, 0)
	43 getstatic (0, 0)
	44 org/apache/commons/math3/geometry/partitioning/Side.PLUS:Lorg/apache/commons/math3/geometry/partitioning/Side; (0, 0)
	46 goto (0, 0)
	47 19 (0, 0)
	49 aload_2 (0, 0)
	50 invokevirtual (0, 0)
	51 org/apache/commons/math3/geometry/partitioning/InsideFinder.minusFound:()Z (0, 0)
	53 ifeq (0, 0)
	54 9 (0, 0)
	56 getstatic (0, 0)
	57 org/apache/commons/math3/geometry/partitioning/Side.MINUS:Lorg/apache/commons/math3/geometry/partitioning/Side; (0, 0)
	59 goto (0, 0)
	60 6 (0, 0)
	62 getstatic (0, 0)
	63 org/apache/commons/math3/geometry/partitioning/Side.HYPER:Lorg/apache/commons/math3/geometry/partitioning/Side; (0, 0)
	65 areturn (0, 0)

Method: intersection
	0 aload_0 (0, 0)
	1 aload_0 (0, 0)
	2 getfield (0, 0)
	3 org/apache/commons/math3/geometry/partitioning/AbstractRegion.tree:Lorg/apache/commons/math3/geometry/partitioning/BSPTree; (0, 0)
	5 aload_1 (0, 0)
	6 invokespecial (0, 0)
	7 org/apache/commons/math3/geometry/partitioning/AbstractRegion.recurseIntersection:(Lorg/apache/commons/math3/geometry/partitioning/BSPTree;Lorg/apache/commons/math3/geometry/partitioning/SubHyperplane;)Lorg/apache/commons/math3/geometry/partitioning/SubHyperplane; (0, 0)
	9 areturn (0, 0)

Method: recurseIntersection
	0 aload_1 (1, 1)
	1 invokevirtual (1, 1)
	2 org/apache/commons/math3/geometry/partitioning/BSPTree.getCut:()Lorg/apache/commons/math3/geometry/partitioning/SubHyperplane; (1, 1)
	4 ifnonnull (1, 1)
	5 27 (1, 1)
	7 aload_1 (1, 1)
	8 invokevirtual (1, 1)
	9 org/apache/commons/math3/geometry/partitioning/BSPTree.getAttribute:()Ljava/lang/Object; (1, 1)
	11 checkcast (1, 1)
	12 java/lang/Boolean (1, 1)
	14 invokevirtual (1, 1)
	15 java/lang/Boolean.booleanValue:()Z (1, 1)
	17 ifeq (1, 1)
	18 12 (1, 1)
	20 aload_2 (1, 1)
	21 invokeinterface (1, 1)
	22 org/apache/commons/math3/geometry/partitioning/SubHyperplane.reunite:(Lorg/apache/commons/math3/geometry/partitioning/SubHyperplane;)Lorg/apache/commons/math3/geometry/partitioning/SubHyperplane; (1, 1)
	24 0 (1, 1)
	26 goto (1, 1)
	27 4 (1, 1)
	29 aconst_null (1, 1)
	30 areturn (1, 1)
	31 aload_1 (0, 0)
	32 invokevirtual (0, 0)
	33 org/apache/commons/math3/geometry/partitioning/BSPTree.getCut:()Lorg/apache/commons/math3/geometry/partitioning/SubHyperplane; (0, 0)
	35 invokeinterface (0, 0)
	36 org/apache/commons/math3/geometry/partitioning/SubHyperplane.copySelf:()Lorg/apache/commons/math3/geometry/partitioning/Hyperplane; (0, 0)
	38 0 (0, 0)
	40 astore_3 (0, 0)
	41 aload_2 (0, 0)
	42 aload_3 (0, 0)
	43 invokeinterface (0, 0)
	44 org/apache/commons/math3/geometry/partitioning/SubHyperplane.$SwitchMap$org$apache$commons$math3$geometry$partitioning$Side:[I (0, 0)
	46 0 (0, 0)
	48 astore (0, 0)
	49 #4 (0, 0)
	50 aload (1, 1)
	51 #4 (1, 1)
	52 invokevirtual (1, 1)
	53 org/apache/commons/math3/geometry/partitioning/SubHyperplane$SplitSubHyperplane.getPlus:()Lorg/apache/commons/math3/geometry/partitioning/SubHyperplane; (1, 1)
	55 ifnull (1, 1)
	56 77 (1, 1)
	58 aload (2, 1)
	59 #4 (2, 1)
	60 invokevirtual (2, 1)
	61 org/apache/commons/math3/geometry/partitioning/SubHyperplane$SplitSubHyperplane.getMinus:()Lorg/apache/commons/math3/geometry/partitioning/SubHyperplane; (2, 1)
	63 ifnull (2, 1)
	64 59 (2, 1)
	66 aload_0 (2, 1)
	67 aload_1 (2, 1)
	68 invokevirtual (2, 1)
	69 org/apache/commons/math3/geometry/partitioning/BSPTree.getPlus:()Lorg/apache/commons/math3/geometry/partitioning/BSPTree; (2, 1)
	71 aload (2, 1)
	72 #4 (2, 1)
	73 invokevirtual (2, 1)
	74 org/apache/commons/math3/geometry/partitioning/SubHyperplane$SplitSubHyperplane.getPlus:()Lorg/apache/commons/math3/geometry/partitioning/SubHyperplane; (2, 1)
	76 invokespecial (2, 1)
	77 org/apache/commons/math3/geometry/partitioning/AbstractRegion.recurseIntersection:(Lorg/apache/commons/math3/geometry/partitioning/BSPTree;Lorg/apache/commons/math3/geometry/partitioning/SubHyperplane;)Lorg/apache/commons/math3/geometry/partitioning/SubHyperplane; (2, 1)
	79 astore (2, 1)
	80 #5 (2, 1)
	81 aload_0 (2, 1)
	82 aload_1 (2, 1)
	83 invokevirtual (2, 1)
	84 org/apache/commons/math3/geometry/partitioning/BSPTree.getMinus:()Lorg/apache/commons/math3/geometry/partitioning/BSPTree; (2, 1)
	86 aload (2, 1)
	87 #4 (2, 1)
	88 invokevirtual (2, 1)
	89 org/apache/commons/math3/geometry/partitioning/SubHyperplane$SplitSubHyperplane.getMinus:()Lorg/apache/commons/math3/geometry/partitioning/SubHyperplane; (2, 1)
	91 invokespecial (2, 1)
	92 org/apache/commons/math3/geometry/partitioning/AbstractRegion.recurseIntersection:(Lorg/apache/commons/math3/geometry/partitioning/BSPTree;Lorg/apache/commons/math3/geometry/partitioning/SubHyperplane;)Lorg/apache/commons/math3/geometry/partitioning/SubHyperplane; (2, 1)
	94 astore (2, 1)
	95 #6 (2, 1)
	96 aload (3, 1)
	97 #5 (3, 1)
	98 ifnonnull (3, 1)
	99 6 (3, 1)
	101 aload (3, 1)
	102 #6 (3, 1)
	103 areturn (3, 1)
	104 aload (3, 1)
	105 #6 (3, 1)
	106 ifnonnull (3, 1)
	107 6 (3, 1)
	109 aload (3, 1)
	110 #5 (3, 1)
	111 areturn (3, 1)
	112 aload (3, 2)
	113 #5 (3, 2)
	114 aload (3, 2)
	115 #6 (3, 2)
	116 invokeinterface (3, 2)
	117 org/apache/commons/math3/geometry/partitioning/SubHyperplane.java/util/HashMap (3, 2)
	119 0 (3, 2)
	121 areturn (3, 2)
	122 aload_0 (2, 2)
	123 aload_1 (2, 2)
	124 invokevirtual (2, 2)
	125 org/apache/commons/math3/geometry/partitioning/BSPTree.getPlus:()Lorg/apache/commons/math3/geometry/partitioning/BSPTree; (2, 2)
	127 aload_2 (2, 2)
	128 invokespecial (2, 2)
	129 org/apache/commons/math3/geometry/partitioning/AbstractRegion.recurseIntersection:(Lorg/apache/commons/math3/geometry/partitioning/BSPTree;Lorg/apache/commons/math3/geometry/partitioning/SubHyperplane;)Lorg/apache/commons/math3/geometry/partitioning/SubHyperplane; (2, 2)
	131 areturn (2, 2)
	132 aload (1, 1)
	133 #4 (1, 1)
	134 invokevirtual (1, 1)
	135 org/apache/commons/math3/geometry/partitioning/SubHyperplane$SplitSubHyperplane.getMinus:()Lorg/apache/commons/math3/geometry/partitioning/SubHyperplane; (1, 1)
	137 ifnull (1, 1)
	138 13 (1, 1)
	140 aload_0 (1, 1)
	141 aload_1 (1, 1)
	142 invokevirtual (1, 1)
	143 org/apache/commons/math3/geometry/partitioning/BSPTree.getMinus:()Lorg/apache/commons/math3/geometry/partitioning/BSPTree; (1, 1)
	145 aload_2 (1, 1)
	146 invokespecial (1, 1)
	147 org/apache/commons/math3/geometry/partitioning/AbstractRegion.recurseIntersection:(Lorg/apache/commons/math3/geometry/partitioning/BSPTree;Lorg/apache/commons/math3/geometry/partitioning/SubHyperplane;)Lorg/apache/commons/math3/geometry/partitioning/SubHyperplane; (1, 1)
	149 areturn (1, 1)
	150 aload_0 (1, 2)
	151 aload_1 (1, 2)
	152 invokevirtual (1, 2)
	153 org/apache/commons/math3/geometry/partitioning/BSPTree.getPlus:()Lorg/apache/commons/math3/geometry/partitioning/BSPTree; (1, 2)
	155 aload_0 (1, 2)
	156 aload_1 (1, 2)
	157 invokevirtual (1, 2)
	158 org/apache/commons/math3/geometry/partitioning/BSPTree.getMinus:()Lorg/apache/commons/math3/geometry/partitioning/BSPTree; (1, 2)
	160 aload_2 (1, 2)
	161 invokespecial (1, 2)
	162 org/apache/commons/math3/geometry/partitioning/AbstractRegion.recurseIntersection:(Lorg/apache/commons/math3/geometry/partitioning/BSPTree;Lorg/apache/commons/math3/geometry/partitioning/SubHyperplane;)Lorg/apache/commons/math3/geometry/partitioning/SubHyperplane; (1, 2)
	164 invokespecial (1, 2)
	165 org/apache/commons/math3/geometry/partitioning/AbstractRegion.recurseIntersection:(Lorg/apache/commons/math3/geometry/partitioning/BSPTree;Lorg/apache/commons/math3/geometry/partitioning/SubHyperplane;)Lorg/apache/commons/math3/geometry/partitioning/SubHyperplane; (1, 2)
	167 areturn (1, 2)

Method: applyTransform
	0 new (0, 0)
	1 java/util/HashMap (0, 0)
	3 dup (0, 0)
	4 invokespecial (0, 0)
	5 java/util/HashMap.<init>:()V (0, 0)
	7 astore_2 (0, 0)
	8 aload_0 (0, 4)
	9 aload_0 (0, 4)
	10 iconst_0 (0, 4)
	11 invokevirtual (0, 4)
	12 org/apache/commons/math3/geometry/partitioning/AbstractRegion.getTree:(Z)Lorg/apache/commons/math3/geometry/partitioning/BSPTree; (0, 4)
	14 aload_1 (0, 4)
	15 aload_2 (0, 4)
	16 invokespecial (0, 4)
	17 org/apache/commons/math3/geometry/partitioning/AbstractRegion.recurseTransform:(Lorg/apache/commons/math3/geometry/partitioning/BSPTree;Lorg/apache/commons/math3/geometry/partitioning/Transform;Ljava/util/Map;)Lorg/apache/commons/math3/geometry/partitioning/BSPTree; (0, 4)
	19 astore_3 (0, 4)
	20 aload_2 (1, 4)
	21 invokeinterface (1, 4)
	22 java/util/Map.java/util/Set (1, 4)
	24 0 (1, 4)
	26 invokeinterface (1, 4)
	27 java/util/Set.java/util/Iterator (1, 4)
	29 0 (1, 4)
	31 astore (1, 4)
	32 #4 (1, 4)
	33 aload (1, 4)
	34 #4 (1, 4)
	35 invokeinterface (1, 4)
	36 java/util/Iterator.next:()Ljava/lang/Object; (1, 4)
	38 0 (1, 4)
	40 ifeq (1, 4)
	41 129 (1, 4)
	43 aload (1, 4)
	44 #4 (1, 4)
	45 invokeinterface (1, 4)
	46 java/util/Iterator.org/apache/commons/math3/geometry/partitioning/SubHyperplane (1, 4)
	48 0 (1, 4)
	50 checkcast (1, 4)
	51 java/util/Map$Entry (1, 4)
	53 astore (1, 4)
	54 #5 (1, 4)
	55 aload (2, 1)
	56 #5 (2, 1)
	57 invokeinterface (2, 1)
	58 java/util/Map$Entry.org/apache/commons/math3/geometry/partitioning/BoundaryAttribute (2, 1)
	60 0 (2, 1)
	62 checkcast (2, 1)
	63 org/apache/commons/math3/geometry/partitioning/BSPTree (2, 1)
	65 invokevirtual (2, 1)
	66 org/apache/commons/math3/geometry/partitioning/BSPTree.getCut:()Lorg/apache/commons/math3/geometry/partitioning/SubHyperplane; (2, 1)
	68 ifnull (2, 1)
	69 98 (2, 1)
	71 aload (2, 1)
	72 #5 (2, 1)
	73 invokeinterface (2, 1)
	74 java/util/Map$Entry.org/apache/commons/math3/geometry/partitioning/BoundaryAttribute (2, 1)
	76 0 (2, 1)
	78 checkcast (2, 1)
	79 org/apache/commons/math3/geometry/partitioning/BSPTree (2, 1)
	81 invokevirtual (2, 1)
	82 org/apache/commons/math3/geometry/partitioning/BSPTree.getAttribute:()Ljava/lang/Object; (2, 1)
	84 checkcast (2, 1)
	85 org/apache/commons/math3/geometry/partitioning/BoundaryAttribute (2, 1)
	87 astore (2, 1)
	88 #6 (2, 1)
	89 aload (3, 1)
	90 #6 (3, 1)
	91 ifnull (3, 1)
	92 75 (3, 1)
	94 aload (3, 4)
	95 #5 (3, 4)
	96 invokeinterface (3, 4)
	97 java/util/Map$Entry.getSplitters:()Lorg/apache/commons/math3/geometry/partitioning/NodesSet; (3, 4)
	99 0 (3, 4)
	101 checkcast (3, 4)
	102 org/apache/commons/math3/geometry/partitioning/BSPTree (3, 4)
	104 invokevirtual (3, 4)
	105 org/apache/commons/math3/geometry/partitioning/BSPTree.getAttribute:()Ljava/lang/Object; (3, 4)
	107 checkcast (3, 4)
	108 org/apache/commons/math3/geometry/partitioning/BoundaryAttribute (3, 4)
	110 astore (3, 4)
	111 #7 (3, 4)
	112 aload (4, 4)
	113 #6 (4, 4)
	114 invokevirtual (4, 4)
	115 org/apache/commons/math3/geometry/partitioning/BoundaryAttribute.getSplitters:()Lorg/apache/commons/math3/geometry/partitioning/NodesSet; (4, 4)
	117 invokevirtual (4, 4)
	118 org/apache/commons/math3/geometry/partitioning/NodesSet.iterator:()Ljava/util/Iterator; (4, 4)
	120 astore (4, 4)
	121 #8 (4, 4)
	122 aload (4, 4)
	123 #8 (4, 4)
	124 invokeinterface (4, 4)
	125 java/util/Iterator.next:()Ljava/lang/Object; (4, 4)
	127 0 (4, 4)
	129 ifeq (4, 4)
	130 37 (4, 4)
	132 aload (4, 4)
	133 #8 (4, 4)
	134 invokeinterface (4, 4)
	135 java/util/Iterator.org/apache/commons/math3/geometry/partitioning/SubHyperplane (4, 4)
	137 0 (4, 4)
	139 checkcast (4, 4)
	140 org/apache/commons/math3/geometry/partitioning/BSPTree (4, 4)
	142 astore (4, 4)
	143 #9 (4, 4)
	144 aload (4, 4)
	145 #7 (4, 4)
	146 invokevirtual (4, 4)
	147 org/apache/commons/math3/geometry/partitioning/BoundaryAttribute.getSplitters:()Lorg/apache/commons/math3/geometry/partitioning/NodesSet; (4, 4)
	149 aload_2 (4, 4)
	150 aload (4, 4)
	151 #9 (4, 4)
	152 invokeinterface (4, 4)
	153 java/util/Map.add:(Lorg/apache/commons/math3/geometry/partitioning/BSPTree;)V (4, 4)
	155 0 (4, 4)
	157 checkcast (4, 4)
	158 org/apache/commons/math3/geometry/partitioning/BSPTree (4, 4)
	160 invokevirtual (4, 4)
	161 org/apache/commons/math3/geometry/partitioning/NodesSet.add:(Lorg/apache/commons/math3/geometry/partitioning/BSPTree;)V (4, 4)
	163 goto (3, 4)
	164 -41 (3, 4)
	166 goto (0, 4)
	167 -133 (0, 4)
	169 aload_0 (0, 4)
	170 aload_3 (0, 4)
	171 invokevirtual (0, 4)
	172 org/apache/commons/math3/geometry/partitioning/AbstractRegion.buildNew:(Lorg/apache/commons/math3/geometry/partitioning/BSPTree;)Lorg/apache/commons/math3/geometry/partitioning/AbstractRegion; (0, 4)
	174 areturn (0, 4)

Method: recurseTransform
	0 aload_1 (1, 1)
	1 invokevirtual (1, 1)
	2 org/apache/commons/math3/geometry/partitioning/BSPTree.getCut:()Lorg/apache/commons/math3/geometry/partitioning/SubHyperplane; (1, 1)
	4 ifnonnull (1, 1)
	5 19 (1, 1)
	7 new (1, 4)
	8 org/apache/commons/math3/geometry/partitioning/BSPTree (1, 4)
	10 dup (1, 4)
	11 aload_1 (1, 4)
	12 invokevirtual (1, 4)
	13 org/apache/commons/math3/geometry/partitioning/BSPTree.getAttribute:()Ljava/lang/Object; (1, 4)
	15 invokespecial (1, 4)
	16 org/apache/commons/math3/geometry/partitioning/BSPTree.<init>:(Ljava/lang/Object;)V (1, 4)
	18 astore (1, 4)
	19 #4 (1, 4)
	20 goto (1, 4)
	21 139 (1, 4)
	23 aload_1 (1, 2)
	24 invokevirtual (1, 2)
	25 org/apache/commons/math3/geometry/partitioning/BSPTree.getCut:()Lorg/apache/commons/math3/geometry/partitioning/SubHyperplane; (1, 2)
	27 astore (1, 2)
	28 #5 (1, 2)
	29 aload (1, 4)
	30 #5 (1, 4)
	31 checkcast (1, 4)
	32 org/apache/commons/math3/geometry/partitioning/AbstractSubHyperplane (1, 4)
	34 aload_2 (1, 4)
	35 invokevirtual (1, 4)
	36 org/apache/commons/math3/geometry/partitioning/AbstractSubHyperplane.applyTransform:(Lorg/apache/commons/math3/geometry/partitioning/Transform;)Lorg/apache/commons/math3/geometry/partitioning/AbstractSubHyperplane; (1, 4)
	38 astore (1, 4)
	39 #6 (1, 4)
	40 aload_1 (1, 4)
	41 invokevirtual (1, 4)
	42 org/apache/commons/math3/geometry/partitioning/BSPTree.getAttribute:()Ljava/lang/Object; (1, 4)
	44 checkcast (1, 4)
	45 org/apache/commons/math3/geometry/partitioning/BoundaryAttribute (1, 4)
	47 astore (1, 4)
	48 #7 (1, 4)
	49 aload (2, 1)
	50 #7 (2, 1)
	51 ifnull (2, 1)
	52 75 (2, 1)
	54 aload (2, 1)
	55 #7 (2, 1)
	56 invokevirtual (2, 1)
	57 org/apache/commons/math3/geometry/partitioning/BoundaryAttribute.getPlusOutside:()Lorg/apache/commons/math3/geometry/partitioning/SubHyperplane; (2, 1)
	59 ifnonnull (2, 1)
	60 7 (2, 1)
	62 aconst_null (2, 1)
	63 goto (2, 1)
	64 15 (2, 1)
	66 aload (2, 1)
	67 #7 (2, 1)
	68 invokevirtual (2, 4)
	69 org/apache/commons/math3/geometry/partitioning/BoundaryAttribute.getPlusOutside:()Lorg/apache/commons/math3/geometry/partitioning/SubHyperplane; (2, 4)
	71 checkcast (2, 4)
	72 org/apache/commons/math3/geometry/partitioning/AbstractSubHyperplane (2, 4)
	74 aload_2 (2, 4)
	75 invokevirtual (2, 4)
	76 org/apache/commons/math3/geometry/partitioning/AbstractSubHyperplane.applyTransform:(Lorg/apache/commons/math3/geometry/partitioning/Transform;)Lorg/apache/commons/math3/geometry/partitioning/AbstractSubHyperplane; (2, 4)
	78 astore (2, 4)
	79 #8 (2, 4)
	80 aload (2, 4)
	81 #7 (2, 4)
	82 invokevirtual (2, 4)
	83 org/apache/commons/math3/geometry/partitioning/BoundaryAttribute.getPlusInside:()Lorg/apache/commons/math3/geometry/partitioning/SubHyperplane; (2, 4)
	85 ifnonnull (2, 4)
	86 7 (2, 4)
	88 aconst_null (2, 4)
	89 goto (2, 4)
	90 15 (2, 4)
	92 aload (2, 4)
	93 #7 (2, 4)
	94 invokevirtual (2, 4)
	95 org/apache/commons/math3/geometry/partitioning/BoundaryAttribute.getPlusInside:()Lorg/apache/commons/math3/geometry/partitioning/SubHyperplane; (2, 4)
	97 checkcast (2, 4)
	98 org/apache/commons/math3/geometry/partitioning/AbstractSubHyperplane (2, 4)
	100 aload_2 (2, 4)
	101 invokevirtual (2, 4)
	102 org/apache/commons/math3/geometry/partitioning/AbstractSubHyperplane.applyTransform:(Lorg/apache/commons/math3/geometry/partitioning/Transform;)Lorg/apache/commons/math3/geometry/partitioning/AbstractSubHyperplane; (2, 4)
	104 astore (2, 4)
	105 #9 (2, 4)
	106 new (2, 4)
	107 org/apache/commons/math3/geometry/partitioning/BoundaryAttribute (2, 4)
	109 dup (2, 4)
	110 aload (2, 4)
	111 #8 (2, 4)
	112 aload (2, 4)
	113 #9 (2, 4)
	114 new (2, 4)
	115 org/apache/commons/math3/geometry/partitioning/NodesSet (2, 4)
	117 dup (2, 4)
	118 invokespecial (2, 4)
	119 org/apache/commons/math3/geometry/partitioning/NodesSet.<init>:()V (2, 4)
	121 invokespecial (2, 4)
	122 org/apache/commons/math3/geometry/partitioning/BoundaryAttribute.<init>:(Lorg/apache/commons/math3/geometry/partitioning/SubHyperplane;Lorg/apache/commons/math3/geometry/partitioning/SubHyperplane;Lorg/apache/commons/math3/geometry/partitioning/NodesSet;)V (2, 4)
	124 astore (2, 4)
	125 #7 (2, 4)
	126 new (1, 4)
	127 org/apache/commons/math3/geometry/partitioning/BSPTree (1, 4)
	129 dup (1, 4)
	130 aload (1, 4)
	131 #6 (1, 4)
	132 aload_0 (1, 4)
	133 aload_1 (1, 4)
	134 invokevirtual (1, 4)
	135 org/apache/commons/math3/geometry/partitioning/BSPTree.getPlus:()Lorg/apache/commons/math3/geometry/partitioning/BSPTree; (1, 4)
	137 aload_2 (1, 4)
	138 aload_3 (1, 4)
	139 invokespecial (1, 4)
	140 org/apache/commons/math3/geometry/partitioning/AbstractRegion.recurseTransform:(Lorg/apache/commons/math3/geometry/partitioning/BSPTree;Lorg/apache/commons/math3/geometry/partitioning/Transform;Ljava/util/Map;)Lorg/apache/commons/math3/geometry/partitioning/BSPTree; (1, 4)
	142 aload_0 (1, 4)
	143 aload_1 (1, 4)
	144 invokevirtual (1, 4)
	145 org/apache/commons/math3/geometry/partitioning/BSPTree.getMinus:()Lorg/apache/commons/math3/geometry/partitioning/BSPTree; (1, 4)
	147 aload_2 (1, 4)
	148 aload_3 (1, 4)
	149 invokespecial (1, 4)
	150 org/apache/commons/math3/geometry/partitioning/AbstractRegion.recurseTransform:(Lorg/apache/commons/math3/geometry/partitioning/BSPTree;Lorg/apache/commons/math3/geometry/partitioning/Transform;Ljava/util/Map;)Lorg/apache/commons/math3/geometry/partitioning/BSPTree; (1, 4)
	152 aload (1, 4)
	153 #7 (1, 4)
	154 invokespecial (1, 4)
	155 org/apache/commons/math3/geometry/partitioning/BSPTree.<init>:(Lorg/apache/commons/math3/geometry/partitioning/SubHyperplane;Lorg/apache/commons/math3/geometry/partitioning/BSPTree;Lorg/apache/commons/math3/geometry/partitioning/BSPTree;Ljava/lang/Object;)V (1, 4)
	157 astore (1, 4)
	158 #4 (1, 4)
	159 aload_3 (0, 4)
	160 aload_1 (0, 4)
	161 aload (0, 4)
	162 #4 (0, 4)
	163 invokeinterface (0, 4)
	164 java/util/Map.copySelf:()Lorg/apache/commons/math3/geometry/partitioning/AbstractRegion; (0, 4)
	166 0 (0, 4)
	168 pop (0, 4)
	169 aload (0, 4)
	170 #4 (0, 4)
	171 areturn (0, 4)

Method: buildNew
	0 aload_0 (0, 0)
	1 aload_1 (0, 0)
	2 invokevirtual (0, 0)
	3 org/apache/commons/math3/geometry/partitioning/AbstractRegion.buildNew:(Lorg/apache/commons/math3/geometry/partitioning/BSPTree;)Lorg/apache/commons/math3/geometry/partitioning/AbstractRegion; (0, 0)
	5 areturn (0, 0)

