Method: <init>
	0 aload_0 (0, 0)
	1 invokespecial (0, 0)
	2 java/lang/Object.<init>:()V (0, 0)
	4 aload_0 (0, 0)
	5 aload_1 (0, 0)
	6 putfield (0, 0)
	7 org/apache/commons/math3/geometry/partitioning/AbstractSubHyperplane.hyperplane:Lorg/apache/commons/math3/geometry/partitioning/Hyperplane; (0, 0)
	9 aload_0 (0, 0)
	10 aload_2 (0, 0)
	11 putfield (0, 0)
	12 org/apache/commons/math3/geometry/partitioning/AbstractSubHyperplane.remainingRegion:Lorg/apache/commons/math3/geometry/partitioning/Region; (0, 0)
	14 return (0, 0)

Method: copySelf
	0 aload_0 (0, 0)
	1 invokevirtual (0, 0)
	2 org/apache/commons/math3/geometry/partitioning/AbstractSubHyperplane.copySelf:()Lorg/apache/commons/math3/geometry/partitioning/AbstractSubHyperplane; (0, 0)
	4 areturn (0, 0)

Method: getHyperplane
	0 aload_0 (0, 0)
	1 getfield (0, 0)
	2 org/apache/commons/math3/geometry/partitioning/AbstractSubHyperplane.hyperplane:Lorg/apache/commons/math3/geometry/partitioning/Hyperplane; (0, 0)
	4 areturn (0, 0)

Method: getRemainingRegion
	0 aload_0 (0, 0)
	1 getfield (0, 0)
	2 org/apache/commons/math3/geometry/partitioning/AbstractSubHyperplane.remainingRegion:Lorg/apache/commons/math3/geometry/partitioning/Region; (0, 0)
	4 areturn (0, 0)

Method: getSize
	0 aload_0 (0, 0)
	1 getfield (0, 0)
	2 org/apache/commons/math3/geometry/partitioning/AbstractSubHyperplane.remainingRegion:Lorg/apache/commons/math3/geometry/partitioning/Region; (0, 0)
	4 invokeinterface (0, 0)
	5 org/apache/commons/math3/geometry/partitioning/Region.org/apache/commons/math3/geometry/partitioning/AbstractSubHyperplane (0, 0)
	7 0 (0, 0)
	9 dreturn (0, 0)

Method: reunite
	0 aload_0 (0, 0)
	1 aload_1 (0, 0)
	2 invokevirtual (0, 0)
	3 org/apache/commons/math3/geometry/partitioning/AbstractSubHyperplane.reunite:(Lorg/apache/commons/math3/geometry/partitioning/SubHyperplane;)Lorg/apache/commons/math3/geometry/partitioning/AbstractSubHyperplane; (0, 0)
	5 areturn (0, 0)

Method: applyTransform
	0 aload_1 (0, 4)
	1 aload_0 (0, 4)
	2 getfield (0, 4)
	3 org/apache/commons/math3/geometry/partitioning/AbstractSubHyperplane.hyperplane:Lorg/apache/commons/math3/geometry/partitioning/Hyperplane; (0, 4)
	5 invokeinterface (0, 4)
	6 org/apache/commons/math3/geometry/partitioning/Transform.java/util/HashMap (0, 4)
	8 0 (0, 4)
	10 astore_2 (0, 4)
	11 new (0, 4)
	12 java/util/HashMap (0, 4)
	14 dup (0, 4)
	15 invokespecial (0, 4)
	16 java/util/HashMap.<init>:()V (0, 4)
	18 astore_3 (0, 4)
	19 aload_0 (0, 4)
	20 aload_0 (0, 4)
	21 getfield (0, 4)
	22 org/apache/commons/math3/geometry/partitioning/AbstractSubHyperplane.remainingRegion:Lorg/apache/commons/math3/geometry/partitioning/Region; (0, 4)
	24 iconst_0 (0, 4)
	25 invokeinterface (0, 4)
	26 org/apache/commons/math3/geometry/partitioning/Region.recurseTransform:(Lorg/apache/commons/math3/geometry/partitioning/BSPTree;Lorg/apache/commons/math3/geometry/partitioning/Hyperplane;Lorg/apache/commons/math3/geometry/partitioning/Transform;Ljava/util/Map;)Lorg/apache/commons/math3/geometry/partitioning/BSPTree; (0, 4)
	28 0 (0, 4)
	30 aload_2 (0, 4)
	31 aload_1 (0, 4)
	32 aload_3 (0, 4)
	33 invokespecial (0, 4)
	34 org/apache/commons/math3/geometry/partitioning/AbstractSubHyperplane.recurseTransform:(Lorg/apache/commons/math3/geometry/partitioning/BSPTree;Lorg/apache/commons/math3/geometry/partitioning/Hyperplane;Lorg/apache/commons/math3/geometry/partitioning/Transform;Ljava/util/Map;)Lorg/apache/commons/math3/geometry/partitioning/BSPTree; (0, 4)
	36 astore (0, 4)
	37 #4 (0, 4)
	38 aload_3 (1, 4)
	39 invokeinterface (1, 4)
	40 java/util/Map.java/util/Set (1, 4)
	42 0 (1, 4)
	44 invokeinterface (1, 4)
	45 java/util/Set.java/util/Iterator (1, 4)
	47 0 (1, 4)
	49 astore (1, 4)
	50 #5 (1, 4)
	51 aload (1, 4)
	52 #5 (1, 4)
	53 invokeinterface (1, 4)
	54 java/util/Iterator.next:()Ljava/lang/Object; (1, 4)
	56 0 (1, 4)
	58 ifeq (1, 4)
	59 129 (1, 4)
	61 aload (1, 4)
	62 #5 (1, 4)
	63 invokeinterface (1, 4)
	64 java/util/Iterator.java/util/Map$Entry (1, 4)
	66 0 (1, 4)
	68 checkcast (1, 4)
	69 java/util/Map$Entry (1, 4)
	71 astore (1, 4)
	72 #6 (1, 4)
	73 aload (2, 1)
	74 #6 (2, 1)
	75 invokeinterface (2, 1)
	76 java/util/Map$Entry.org/apache/commons/math3/geometry/partitioning/BSPTree (2, 1)
	78 0 (2, 1)
	80 checkcast (2, 1)
	81 org/apache/commons/math3/geometry/partitioning/BSPTree (2, 1)
	83 invokevirtual (2, 1)
	84 org/apache/commons/math3/geometry/partitioning/BSPTree.getCut:()Lorg/apache/commons/math3/geometry/partitioning/SubHyperplane; (2, 1)
	86 ifnull (2, 1)
	87 98 (2, 1)
	89 aload (2, 1)
	90 #6 (2, 1)
	91 invokeinterface (2, 1)
	92 java/util/Map$Entry.org/apache/commons/math3/geometry/partitioning/BSPTree (2, 1)
	94 0 (2, 1)
	96 checkcast (2, 1)
	97 org/apache/commons/math3/geometry/partitioning/BSPTree (2, 1)
	99 invokevirtual (2, 1)
	100 org/apache/commons/math3/geometry/partitioning/BSPTree.getAttribute:()Ljava/lang/Object; (2, 1)
	102 checkcast (2, 1)
	103 org/apache/commons/math3/geometry/partitioning/BoundaryAttribute (2, 1)
	105 astore (2, 1)
	106 #7 (2, 1)
	107 aload (3, 1)
	108 #7 (3, 1)
	109 ifnull (3, 1)
	110 75 (3, 1)
	112 aload (3, 4)
	113 #6 (3, 4)
	114 invokeinterface (3, 4)
	115 java/util/Map$Entry.getSplitters:()Lorg/apache/commons/math3/geometry/partitioning/NodesSet; (3, 4)
	117 0 (3, 4)
	119 checkcast (3, 4)
	120 org/apache/commons/math3/geometry/partitioning/BSPTree (3, 4)
	122 invokevirtual (3, 4)
	123 org/apache/commons/math3/geometry/partitioning/BSPTree.getAttribute:()Ljava/lang/Object; (3, 4)
	125 checkcast (3, 4)
	126 org/apache/commons/math3/geometry/partitioning/BoundaryAttribute (3, 4)
	128 astore (3, 4)
	129 #8 (3, 4)
	130 aload (4, 4)
	131 #7 (4, 4)
	132 invokevirtual (4, 4)
	133 org/apache/commons/math3/geometry/partitioning/BoundaryAttribute.getSplitters:()Lorg/apache/commons/math3/geometry/partitioning/NodesSet; (4, 4)
	135 invokevirtual (4, 4)
	136 org/apache/commons/math3/geometry/partitioning/NodesSet.iterator:()Ljava/util/Iterator; (4, 4)
	138 astore (4, 4)
	139 #9 (4, 4)
	140 aload (4, 4)
	141 #9 (4, 4)
	142 invokeinterface (4, 4)
	143 java/util/Iterator.next:()Ljava/lang/Object; (4, 4)
	145 0 (4, 4)
	147 ifeq (4, 4)
	148 37 (4, 4)
	150 aload (4, 4)
	151 #9 (4, 4)
	152 invokeinterface (4, 4)
	153 java/util/Iterator.java/util/Map$Entry (4, 4)
	155 0 (4, 4)
	157 checkcast (4, 4)
	158 org/apache/commons/math3/geometry/partitioning/BSPTree (4, 4)
	160 astore (4, 4)
	161 #10 (4, 4)
	162 aload (4, 4)
	163 #8 (4, 4)
	164 invokevirtual (4, 4)
	165 org/apache/commons/math3/geometry/partitioning/BoundaryAttribute.getSplitters:()Lorg/apache/commons/math3/geometry/partitioning/NodesSet; (4, 4)
	167 aload_3 (4, 4)
	168 aload (4, 4)
	169 #10 (4, 4)
	170 invokeinterface (4, 4)
	171 java/util/Map.add:(Lorg/apache/commons/math3/geometry/partitioning/BSPTree;)V (4, 4)
	173 0 (4, 4)
	175 checkcast (4, 4)
	176 org/apache/commons/math3/geometry/partitioning/BSPTree (4, 4)
	178 invokevirtual (4, 4)
	179 org/apache/commons/math3/geometry/partitioning/NodesSet.add:(Lorg/apache/commons/math3/geometry/partitioning/BSPTree;)V (4, 4)
	181 goto (3, 4)
	182 -41 (3, 4)
	184 goto (0, 4)
	185 -133 (0, 4)
	187 aload_0 (0, 4)
	188 aload_2 (0, 4)
	189 aload_0 (0, 4)
	190 getfield (0, 4)
	191 org/apache/commons/math3/geometry/partitioning/AbstractSubHyperplane.remainingRegion:Lorg/apache/commons/math3/geometry/partitioning/Region; (0, 4)
	193 aload (0, 4)
	194 #4 (0, 4)
	195 invokeinterface (0, 4)
	196 org/apache/commons/math3/geometry/partitioning/Region.<init>:(Ljava/lang/Object;)V (0, 4)
	198 0 (0, 4)
	200 invokevirtual (0, 4)
	201 org/apache/commons/math3/geometry/partitioning/AbstractSubHyperplane.buildNew:(Lorg/apache/commons/math3/geometry/partitioning/Hyperplane;Lorg/apache/commons/math3/geometry/partitioning/Region;)Lorg/apache/commons/math3/geometry/partitioning/AbstractSubHyperplane; (0, 4)
	203 areturn (0, 4)

Method: recurseTransform
	0 aload_1 (1, 1)
	1 invokevirtual (1, 1)
	2 org/apache/commons/math3/geometry/partitioning/BSPTree.getCut:()Lorg/apache/commons/math3/geometry/partitioning/SubHyperplane; (1, 1)
	4 ifnonnull (1, 1)
	5 19 (1, 1)
	7 new (1, 4)
	8 org/apache/commons/math3/geometry/partitioning/BSPTree (1, 4)
	10 dup (1, 4)
	11 aload_1 (1, 4)
	12 invokevirtual (1, 4)
	13 org/apache/commons/math3/geometry/partitioning/BSPTree.getAttribute:()Ljava/lang/Object; (1, 4)
	15 invokespecial (1, 4)
	16 org/apache/commons/math3/geometry/partitioning/BSPTree.<init>:(Ljava/lang/Object;)V (1, 4)
	18 astore (1, 4)
	19 #5 (1, 4)
	20 goto (1, 4)
	21 147 (1, 4)
	23 aload_1 (1, 2)
	24 invokevirtual (1, 2)
	25 org/apache/commons/math3/geometry/partitioning/BSPTree.getAttribute:()Ljava/lang/Object; (1, 2)
	27 checkcast (1, 2)
	28 org/apache/commons/math3/geometry/partitioning/BoundaryAttribute (1, 2)
	30 astore (1, 2)
	31 #6 (1, 2)
	32 aload (2, 1)
	33 #6 (2, 1)
	34 ifnull (2, 1)
	35 83 (2, 1)
	37 aload (2, 1)
	38 #6 (2, 1)
	39 invokevirtual (2, 1)
	40 org/apache/commons/math3/geometry/partitioning/BoundaryAttribute.getPlusOutside:()Lorg/apache/commons/math3/geometry/partitioning/SubHyperplane; (2, 1)
	42 ifnonnull (2, 1)
	43 7 (2, 1)
	45 aconst_null (2, 1)
	46 goto (2, 1)
	47 19 (2, 1)
	49 aload_3 (2, 1)
	50 aload (2, 1)
	51 #6 (2, 1)
	52 invokevirtual (2, 4)
	53 org/apache/commons/math3/geometry/partitioning/BoundaryAttribute.getPlusOutside:()Lorg/apache/commons/math3/geometry/partitioning/SubHyperplane; (2, 4)
	55 aload_0 (2, 4)
	56 getfield (2, 4)
	57 org/apache/commons/math3/geometry/partitioning/AbstractSubHyperplane.hyperplane:Lorg/apache/commons/math3/geometry/partitioning/Hyperplane; (2, 4)
	59 aload_2 (2, 4)
	60 invokeinterface (2, 4)
	61 org/apache/commons/math3/geometry/partitioning/Transform.getPlusInside:()Lorg/apache/commons/math3/geometry/partitioning/SubHyperplane; (2, 4)
	63 0 (2, 4)
	65 astore (2, 4)
	66 #7 (2, 4)
	67 aload (2, 4)
	68 #6 (2, 4)
	69 invokevirtual (2, 4)
	70 org/apache/commons/math3/geometry/partitioning/BoundaryAttribute.getPlusInside:()Lorg/apache/commons/math3/geometry/partitioning/SubHyperplane; (2, 4)
	72 ifnonnull (2, 4)
	73 7 (2, 4)
	75 aconst_null (2, 4)
	76 goto (2, 4)
	77 19 (2, 4)
	79 aload_3 (2, 4)
	80 aload (2, 4)
	81 #6 (2, 4)
	82 invokevirtual (2, 4)
	83 org/apache/commons/math3/geometry/partitioning/BoundaryAttribute.getPlusInside:()Lorg/apache/commons/math3/geometry/partitioning/SubHyperplane; (2, 4)
	85 aload_0 (2, 4)
	86 getfield (2, 4)
	87 org/apache/commons/math3/geometry/partitioning/AbstractSubHyperplane.hyperplane:Lorg/apache/commons/math3/geometry/partitioning/Hyperplane; (2, 4)
	89 aload_2 (2, 4)
	90 invokeinterface (2, 4)
	91 org/apache/commons/math3/geometry/partitioning/Transform.getPlusInside:()Lorg/apache/commons/math3/geometry/partitioning/SubHyperplane; (2, 4)
	93 0 (2, 4)
	95 astore (2, 4)
	96 #8 (2, 4)
	97 new (2, 4)
	98 org/apache/commons/math3/geometry/partitioning/BoundaryAttribute (2, 4)
	100 dup (2, 4)
	101 aload (2, 4)
	102 #7 (2, 4)
	103 aload (2, 4)
	104 #8 (2, 4)
	105 new (2, 4)
	106 org/apache/commons/math3/geometry/partitioning/NodesSet (2, 4)
	108 dup (2, 4)
	109 invokespecial (2, 4)
	110 org/apache/commons/math3/geometry/partitioning/NodesSet.<init>:()V (2, 4)
	112 invokespecial (2, 4)
	113 org/apache/commons/math3/geometry/partitioning/BoundaryAttribute.<init>:(Lorg/apache/commons/math3/geometry/partitioning/SubHyperplane;Lorg/apache/commons/math3/geometry/partitioning/SubHyperplane;Lorg/apache/commons/math3/geometry/partitioning/NodesSet;)V (2, 4)
	115 astore (2, 4)
	116 #6 (2, 4)
	117 new (1, 4)
	118 org/apache/commons/math3/geometry/partitioning/BSPTree (1, 4)
	120 dup (1, 4)
	121 aload_3 (1, 4)
	122 aload_1 (1, 4)
	123 invokevirtual (1, 4)
	124 org/apache/commons/math3/geometry/partitioning/BSPTree.getCut:()Lorg/apache/commons/math3/geometry/partitioning/SubHyperplane; (1, 4)
	126 aload_0 (1, 4)
	127 getfield (1, 4)
	128 org/apache/commons/math3/geometry/partitioning/AbstractSubHyperplane.hyperplane:Lorg/apache/commons/math3/geometry/partitioning/Hyperplane; (1, 4)
	130 aload_2 (1, 4)
	131 invokeinterface (1, 4)
	132 org/apache/commons/math3/geometry/partitioning/Transform.getPlusInside:()Lorg/apache/commons/math3/geometry/partitioning/SubHyperplane; (1, 4)
	134 0 (1, 4)
	136 aload_0 (1, 4)
	137 aload_1 (1, 4)
	138 invokevirtual (1, 4)
	139 org/apache/commons/math3/geometry/partitioning/BSPTree.getPlus:()Lorg/apache/commons/math3/geometry/partitioning/BSPTree; (1, 4)
	141 aload_2 (1, 4)
	142 aload_3 (1, 4)
	143 aload (1, 4)
	144 #4 (1, 4)
	145 invokespecial (1, 4)
	146 org/apache/commons/math3/geometry/partitioning/AbstractSubHyperplane.recurseTransform:(Lorg/apache/commons/math3/geometry/partitioning/BSPTree;Lorg/apache/commons/math3/geometry/partitioning/Hyperplane;Lorg/apache/commons/math3/geometry/partitioning/Transform;Ljava/util/Map;)Lorg/apache/commons/math3/geometry/partitioning/BSPTree; (1, 4)
	148 aload_0 (1, 4)
	149 aload_1 (1, 4)
	150 invokevirtual (1, 4)
	151 org/apache/commons/math3/geometry/partitioning/BSPTree.getMinus:()Lorg/apache/commons/math3/geometry/partitioning/BSPTree; (1, 4)
	153 aload_2 (1, 4)
	154 aload_3 (1, 4)
	155 aload (1, 4)
	156 #4 (1, 4)
	157 invokespecial (1, 4)
	158 org/apache/commons/math3/geometry/partitioning/AbstractSubHyperplane.recurseTransform:(Lorg/apache/commons/math3/geometry/partitioning/BSPTree;Lorg/apache/commons/math3/geometry/partitioning/Hyperplane;Lorg/apache/commons/math3/geometry/partitioning/Transform;Ljava/util/Map;)Lorg/apache/commons/math3/geometry/partitioning/BSPTree; (1, 4)
	160 aload (1, 4)
	161 #6 (1, 4)
	162 invokespecial (1, 4)
	163 org/apache/commons/math3/geometry/partitioning/BSPTree.<init>:(Lorg/apache/commons/math3/geometry/partitioning/SubHyperplane;Lorg/apache/commons/math3/geometry/partitioning/BSPTree;Lorg/apache/commons/math3/geometry/partitioning/BSPTree;Ljava/lang/Object;)V (1, 4)
	165 astore (1, 4)
	166 #5 (1, 4)
	167 aload (0, 4)
	168 #4 (0, 4)
	169 aload_1 (0, 4)
	170 aload (0, 4)
	171 #5 (0, 4)
	172 invokeinterface (0, 4)
	173 java/util/Map.split:(Lorg/apache/commons/math3/geometry/partitioning/Hyperplane;)Lorg/apache/commons/math3/geometry/partitioning/SubHyperplane$SplitSubHyperplane; (0, 4)
	175 0 (0, 4)
	177 pop (0, 4)
	178 aload (0, 4)
	179 #5 (0, 4)
	180 areturn (0, 4)

Method: side
	0 aload_0 (0, 0)
	1 aload_1 (0, 0)
	2 invokevirtual (0, 0)
	3 org/apache/commons/math3/geometry/partitioning/AbstractSubHyperplane.split:(Lorg/apache/commons/math3/geometry/partitioning/Hyperplane;)Lorg/apache/commons/math3/geometry/partitioning/SubHyperplane$SplitSubHyperplane; (0, 0)
	5 invokevirtual (0, 0)
	6 org/apache/commons/math3/geometry/partitioning/SubHyperplane$SplitSubHyperplane.getSide:()Lorg/apache/commons/math3/geometry/partitioning/Side; (0, 0)
	8 areturn (0, 0)

Method: isEmpty
	0 aload_0 (0, 0)
	1 getfield (0, 0)
	2 org/apache/commons/math3/geometry/partitioning/AbstractSubHyperplane.remainingRegion:Lorg/apache/commons/math3/geometry/partitioning/Region; (0, 0)
	4 invokeinterface (0, 0)
	5 org/apache/commons/math3/geometry/partitioning/Region.reunite:(Lorg/apache/commons/math3/geometry/partitioning/SubHyperplane;)Lorg/apache/commons/math3/geometry/partitioning/AbstractSubHyperplane; (0, 0)
	7 0 (0, 0)
	9 ireturn (0, 0)

