Method: <init>
	0 aload_0 (0, 0)
	1 invokespecial (0, 0)
	2 java/lang/Object.<init>:()V (0, 0)
	4 aload_0 (0, 0)
	5 aload_1 (0, 0)
	6 putfield (0, 0)
	7 org/apache/commons/math3/geometry/partitioning/BoundaryProjector.original:Lorg/apache/commons/math3/geometry/Point; (0, 0)
	9 aload_0 (0, 0)
	10 aconst_null (0, 0)
	11 putfield (0, 0)
	12 org/apache/commons/math3/geometry/partitioning/BoundaryProjector.projected:Lorg/apache/commons/math3/geometry/Point; (0, 0)
	14 aload_0 (0, 0)
	15 aconst_null (0, 0)
	16 putfield (0, 0)
	17 org/apache/commons/math3/geometry/partitioning/BoundaryProjector.leaf:Lorg/apache/commons/math3/geometry/partitioning/BSPTree; (0, 0)
	19 aload_0 (0, 0)
	20 ldc2_w (0, 0)
	21 inf (0, 0)
	23 putfield (0, 0)
	24 org/apache/commons/math3/geometry/partitioning/BoundaryProjector.offset:D (0, 0)
	26 return (0, 0)

Method: visitOrder
	0 aload_1 (1, 1)
	1 invokevirtual (1, 1)
	2 org/apache/commons/math3/geometry/partitioning/BSPTree.getCut:()Lorg/apache/commons/math3/geometry/partitioning/SubHyperplane; (1, 1)
	4 invokeinterface (1, 1)
	5 org/apache/commons/math3/geometry/partitioning/SubHyperplane.org/apache/commons/math3/geometry/partitioning/Hyperplane (1, 1)
	7 0 (1, 1)
	9 aload_0 (1, 1)
	10 getfield (1, 1)
	11 org/apache/commons/math3/geometry/partitioning/BoundaryProjector.original:Lorg/apache/commons/math3/geometry/Point; (1, 1)
	13 invokeinterface (1, 1)
	14 org/apache/commons/math3/geometry/partitioning/Hyperplane.MINUS_SUB_PLUS:Lorg/apache/commons/math3/geometry/partitioning/BSPTreeVisitor$Order; (1, 1)
	16 0 (1, 1)
	18 dconst_0 (1, 1)
	19 dcmpg (1, 1)
	20 ifgt (1, 1)
	21 7 (1, 1)
	23 getstatic (1, 1)
	24 org/apache/commons/math3/geometry/partitioning/BSPTreeVisitor$Order.MINUS_SUB_PLUS:Lorg/apache/commons/math3/geometry/partitioning/BSPTreeVisitor$Order; (1, 1)
	26 areturn (1, 1)
	27 getstatic (1, 2)
	28 org/apache/commons/math3/geometry/partitioning/BSPTreeVisitor$Order.PLUS_SUB_MINUS:Lorg/apache/commons/math3/geometry/partitioning/BSPTreeVisitor$Order; (1, 2)
	30 areturn (1, 2)

Method: visitInternalNode
	0 aload_1 (0, 0)
	1 invokevirtual (0, 0)
	2 org/apache/commons/math3/geometry/partitioning/BSPTree.getCut:()Lorg/apache/commons/math3/geometry/partitioning/SubHyperplane; (0, 0)
	4 invokeinterface (0, 0)
	5 org/apache/commons/math3/geometry/partitioning/SubHyperplane.org/apache/commons/math3/geometry/partitioning/Hyperplane (0, 0)
	7 0 (0, 0)
	9 astore_2 (0, 0)
	10 aload_2 (0, 0)
	11 aload_0 (0, 0)
	12 getfield (0, 0)
	13 org/apache/commons/math3/geometry/partitioning/BoundaryProjector.original:Lorg/apache/commons/math3/geometry/Point; (0, 0)
	15 invokeinterface (0, 0)
	16 org/apache/commons/math3/geometry/partitioning/Hyperplane.MINUS_SUB_PLUS:Lorg/apache/commons/math3/geometry/partitioning/BSPTreeVisitor$Order; (0, 0)
	18 0 (0, 0)
	20 dstore_3 (0, 0)
	21 dload_3 (1, 1)
	22 invokestatic (1, 1)
	23 org/apache/commons/math3/util/FastMath.abs:(D)D (1, 1)
	25 aload_0 (1, 1)
	26 getfield (1, 1)
	27 org/apache/commons/math3/geometry/partitioning/BoundaryProjector.offset:D (1, 1)
	29 dcmpg (1, 1)
	30 ifge (1, 1)
	31 183 (1, 1)
	33 aload_2 (1, 1)
	34 aload_0 (1, 1)
	35 getfield (1, 1)
	36 org/apache/commons/math3/geometry/partitioning/BoundaryProjector.original:Lorg/apache/commons/math3/geometry/Point; (1, 1)
	38 invokeinterface (1, 1)
	39 org/apache/commons/math3/geometry/partitioning/Hyperplane.boundaryRegions:(Lorg/apache/commons/math3/geometry/partitioning/BSPTree;)Ljava/util/List; (1, 1)
	41 0 (1, 1)
	43 astore (1, 1)
	44 #5 (1, 1)
	45 aload_0 (1, 1)
	46 aload_1 (1, 1)
	47 invokespecial (1, 1)
	48 org/apache/commons/math3/geometry/partitioning/BoundaryProjector.boundaryRegions:(Lorg/apache/commons/math3/geometry/partitioning/BSPTree;)Ljava/util/List; (1, 1)
	50 astore (1, 1)
	51 #6 (1, 1)
	52 iconst_0 (1, 1)
	53 istore (1, 1)
	54 #7 (1, 1)
	55 aload (2, 4)
	56 #6 (2, 4)
	57 invokeinterface (2, 4)
	58 java/util/List.java/util/Iterator (2, 4)
	60 0 (2, 4)
	62 astore (2, 4)
	63 #8 (2, 4)
	64 aload (2, 4)
	65 #8 (2, 4)
	66 invokeinterface (2, 4)
	67 java/util/Iterator.next:()Ljava/lang/Object; (2, 4)
	69 0 (2, 4)
	71 ifeq (2, 4)
	72 52 (2, 4)
	74 aload (2, 4)
	75 #8 (2, 4)
	76 invokeinterface (2, 4)
	77 java/util/Iterator.org/apache/commons/math3/geometry/partitioning/Region (2, 4)
	79 0 (2, 4)
	81 checkcast (2, 4)
	82 org/apache/commons/math3/geometry/partitioning/Region (2, 4)
	84 astore (2, 4)
	85 #9 (2, 4)
	86 iload (3, 1)
	87 #7 (3, 1)
	88 ifne (3, 1)
	89 32 (3, 1)
	91 aload_0 (3, 1)
	92 aload (3, 1)
	93 #5 (3, 1)
	94 aload_2 (3, 1)
	95 aload (3, 1)
	96 #9 (3, 1)
	97 invokespecial (3, 1)
	98 org/apache/commons/math3/geometry/partitioning/BoundaryProjector.belongsToPart:(Lorg/apache/commons/math3/geometry/Point;Lorg/apache/commons/math3/geometry/partitioning/Hyperplane;Lorg/apache/commons/math3/geometry/partitioning/Region;)Z (3, 1)
	100 ifeq (3, 1)
	101 20 (3, 1)
	103 aload_0 (3, 1)
	104 aload (3, 1)
	105 #5 (3, 1)
	106 putfield (3, 1)
	107 org/apache/commons/math3/geometry/partitioning/BoundaryProjector.projected:Lorg/apache/commons/math3/geometry/Point; (3, 1)
	109 aload_0 (3, 1)
	110 dload_3 (3, 1)
	111 invokestatic (3, 1)
	112 org/apache/commons/math3/util/FastMath.abs:(D)D (3, 1)
	114 putfield (3, 1)
	115 org/apache/commons/math3/geometry/partitioning/BoundaryProjector.offset:D (3, 1)
	117 iconst_1 (3, 1)
	118 istore (3, 1)
	119 #7 (3, 1)
	120 goto (1, 1)
	121 -56 (1, 1)
	123 iload (2, 1)
	124 #7 (2, 1)
	125 ifne (2, 1)
	126 88 (2, 1)
	128 aload (3, 4)
	129 #6 (3, 4)
	130 invokeinterface (3, 4)
	131 java/util/List.java/util/Iterator (3, 4)
	133 0 (3, 4)
	135 astore (3, 4)
	136 #8 (3, 4)
	137 aload (3, 4)
	138 #8 (3, 4)
	139 invokeinterface (3, 4)
	140 java/util/Iterator.next:()Ljava/lang/Object; (3, 4)
	142 0 (3, 4)
	144 ifeq (3, 4)
	145 69 (3, 4)
	147 aload (3, 4)
	148 #8 (3, 4)
	149 invokeinterface (3, 4)
	150 java/util/Iterator.org/apache/commons/math3/geometry/partitioning/Region (3, 4)
	152 0 (3, 4)
	154 checkcast (3, 4)
	155 org/apache/commons/math3/geometry/partitioning/Region (3, 4)
	157 astore (3, 4)
	158 #9 (3, 4)
	159 aload_0 (3, 4)
	160 aload (3, 4)
	161 #5 (3, 4)
	162 aload_2 (3, 4)
	163 aload (3, 4)
	164 #9 (3, 4)
	165 invokespecial (3, 4)
	166 org/apache/commons/math3/geometry/partitioning/BoundaryProjector.singularProjection:(Lorg/apache/commons/math3/geometry/Point;Lorg/apache/commons/math3/geometry/partitioning/Hyperplane;Lorg/apache/commons/math3/geometry/partitioning/Region;)Lorg/apache/commons/math3/geometry/Point; (3, 4)
	168 astore (3, 4)
	169 #10 (3, 4)
	170 aload (4, 1)
	171 #10 (4, 1)
	172 ifnull (4, 1)
	173 38 (4, 1)
	175 aload_0 (4, 1)
	176 getfield (4, 1)
	177 org/apache/commons/math3/geometry/partitioning/BoundaryProjector.original:Lorg/apache/commons/math3/geometry/Point; (4, 1)
	179 aload (4, 1)
	180 #10 (4, 1)
	181 invokeinterface (4, 1)
	182 org/apache/commons/math3/geometry/Point.getAttribute:()Ljava/lang/Object; (4, 1)
	184 0 (4, 1)
	186 dstore (4, 1)
	187 #11 (4, 1)
	188 dload (5, 1)
	189 #11 (5, 1)
	190 aload_0 (5, 1)
	191 getfield (5, 1)
	192 org/apache/commons/math3/geometry/partitioning/BoundaryProjector.offset:D (5, 1)
	194 dcmpg (5, 1)
	195 ifge (5, 1)
	196 15 (5, 1)
	198 aload_0 (5, 1)
	199 aload (5, 1)
	200 #10 (5, 1)
	201 putfield (5, 1)
	202 org/apache/commons/math3/geometry/partitioning/BoundaryProjector.projected:Lorg/apache/commons/math3/geometry/Point; (5, 1)
	204 aload_0 (5, 1)
	205 dload (5, 1)
	206 #11 (5, 1)
	207 putfield (5, 1)
	208 org/apache/commons/math3/geometry/partitioning/BoundaryProjector.offset:D (5, 1)
	210 goto (2, 1)
	211 -73 (2, 1)
	213 return (0, 0)

Method: visitLeafNode
	0 aload_0 (1, 1)
	1 getfield (1, 1)
	2 org/apache/commons/math3/geometry/partitioning/BoundaryProjector.leaf:Lorg/apache/commons/math3/geometry/partitioning/BSPTree; (1, 1)
	4 ifnonnull (1, 1)
	5 8 (1, 1)
	7 aload_0 (1, 1)
	8 aload_1 (1, 1)
	9 putfield (1, 1)
	10 org/apache/commons/math3/geometry/partitioning/BoundaryProjector.leaf:Lorg/apache/commons/math3/geometry/partitioning/BSPTree; (1, 1)
	12 return (0, 0)

Method: getProjection
	0 aload_0 (0, 0)
	1 aload_0 (0, 0)
	2 getfield (0, 0)
	3 org/apache/commons/math3/geometry/partitioning/BoundaryProjector.offset:D (0, 0)
	5 aload_0 (0, 0)
	6 getfield (0, 0)
	7 org/apache/commons/math3/geometry/partitioning/BoundaryProjector.leaf:Lorg/apache/commons/math3/geometry/partitioning/BSPTree; (0, 0)
	9 invokevirtual (0, 0)
	10 org/apache/commons/math3/geometry/partitioning/BSPTree.getAttribute:()Ljava/lang/Object; (0, 0)
	12 checkcast (0, 0)
	13 java/lang/Boolean (0, 0)
	15 invokevirtual (0, 0)
	16 java/lang/Boolean.booleanValue:()Z (0, 0)
	18 ifeq (0, 0)
	19 9 (0, 0)
	21 ldc2_w (0, 0)
	22 -1.0 (0, 0)
	24 goto (0, 0)
	25 4 (0, 0)
	27 dconst_1 (0, 0)
	28 invokestatic (0, 0)
	29 org/apache/commons/math3/util/FastMath.copySign:(DD)D (0, 0)
	31 putfield (0, 0)
	32 org/apache/commons/math3/geometry/partitioning/BoundaryProjector.offset:D (0, 0)
	34 new (0, 0)
	35 org/apache/commons/math3/geometry/partitioning/BoundaryProjection (0, 0)
	37 dup (0, 0)
	38 aload_0 (0, 0)
	39 getfield (0, 0)
	40 org/apache/commons/math3/geometry/partitioning/BoundaryProjector.original:Lorg/apache/commons/math3/geometry/Point; (0, 0)
	42 aload_0 (0, 0)
	43 getfield (0, 0)
	44 org/apache/commons/math3/geometry/partitioning/BoundaryProjector.projected:Lorg/apache/commons/math3/geometry/Point; (0, 0)
	46 aload_0 (0, 0)
	47 getfield (0, 0)
	48 org/apache/commons/math3/geometry/partitioning/BoundaryProjector.offset:D (0, 0)
	50 invokespecial (0, 0)
	51 org/apache/commons/math3/geometry/partitioning/BoundaryProjection.<init>:(Lorg/apache/commons/math3/geometry/Point;Lorg/apache/commons/math3/geometry/Point;D)V (0, 0)
	53 areturn (0, 0)

Method: boundaryRegions
	0 new (0, 0)
	1 java/util/ArrayList (0, 0)
	3 dup (0, 0)
	4 iconst_2 (0, 0)
	5 invokespecial (0, 0)
	6 java/util/ArrayList.<init>:(I)V (0, 0)
	8 astore_2 (0, 0)
	9 aload_1 (0, 0)
	10 invokevirtual (0, 0)
	11 org/apache/commons/math3/geometry/partitioning/BSPTree.getAttribute:()Ljava/lang/Object; (0, 0)
	13 checkcast (0, 0)
	14 org/apache/commons/math3/geometry/partitioning/BoundaryAttribute (0, 0)
	16 astore_3 (0, 0)
	17 aload_0 (0, 0)
	18 aload_3 (0, 0)
	19 invokevirtual (0, 0)
	20 org/apache/commons/math3/geometry/partitioning/BoundaryAttribute.getPlusInside:()Lorg/apache/commons/math3/geometry/partitioning/SubHyperplane; (0, 0)
	22 aload_2 (0, 0)
	23 invokespecial (0, 0)
	24 org/apache/commons/math3/geometry/partitioning/BoundaryProjector.addRegion:(Lorg/apache/commons/math3/geometry/partitioning/SubHyperplane;Ljava/util/List;)V (0, 0)
	26 aload_0 (0, 0)
	27 aload_3 (0, 0)
	28 invokevirtual (0, 0)
	29 org/apache/commons/math3/geometry/partitioning/BoundaryAttribute.getPlusOutside:()Lorg/apache/commons/math3/geometry/partitioning/SubHyperplane; (0, 0)
	31 aload_2 (0, 0)
	32 invokespecial (0, 0)
	33 org/apache/commons/math3/geometry/partitioning/BoundaryProjector.addRegion:(Lorg/apache/commons/math3/geometry/partitioning/SubHyperplane;Ljava/util/List;)V (0, 0)
	35 aload_2 (0, 0)
	36 areturn (0, 0)

Method: addRegion
	0 aload_1 (1, 1)
	1 ifnull (1, 1)
	2 23 (1, 1)
	4 aload_1 (1, 1)
	5 checkcast (1, 1)
	6 org/apache/commons/math3/geometry/partitioning/AbstractSubHyperplane (1, 1)
	8 invokevirtual (1, 1)
	9 org/apache/commons/math3/geometry/partitioning/AbstractSubHyperplane.getRemainingRegion:()Lorg/apache/commons/math3/geometry/partitioning/Region; (1, 1)
	11 astore_3 (1, 1)
	12 aload_3 (2, 1)
	13 ifnull (2, 1)
	14 11 (2, 1)
	16 aload_2 (2, 1)
	17 aload_3 (2, 1)
	18 invokeinterface (2, 1)
	19 java/util/List.org/apache/commons/math3/geometry/partitioning/Embedding (2, 1)
	21 0 (2, 1)
	23 pop (2, 1)
	24 return (0, 0)

Method: belongsToPart
	0 aload_2 (0, 0)
	1 checkcast (0, 0)
	2 org/apache/commons/math3/geometry/partitioning/Embedding (0, 0)
	4 astore (0, 0)
	5 #4 (0, 0)
	6 aload_3 (0, 0)
	7 aload (0, 0)
	8 #4 (0, 0)
	9 aload_1 (0, 0)
	10 invokeinterface (0, 0)
	11 org/apache/commons/math3/geometry/partitioning/Embedding.checkPoint:(Lorg/apache/commons/math3/geometry/Point;)Lorg/apache/commons/math3/geometry/partitioning/Region$Location; (0, 0)
	13 0 (0, 0)
	15 invokeinterface (0, 0)
	16 org/apache/commons/math3/geometry/partitioning/Region.org/apache/commons/math3/geometry/partitioning/Region$Location (0, 0)
	18 0 (0, 0)
	20 getstatic (0, 0)
	21 org/apache/commons/math3/geometry/partitioning/Region$Location.OUTSIDE:Lorg/apache/commons/math3/geometry/partitioning/Region$Location; (0, 0)
	23 if_acmpeq (0, 0)
	24 7 (0, 0)
	26 iconst_1 (0, 0)
	27 goto (0, 0)
	28 4 (0, 0)
	30 iconst_0 (0, 0)
	31 ireturn (0, 0)

Method: singularProjection
	0 aload_2 (0, 0)
	1 checkcast (0, 0)
	2 org/apache/commons/math3/geometry/partitioning/Embedding (0, 0)
	4 astore (0, 0)
	5 #4 (0, 0)
	6 aload_3 (0, 0)
	7 aload (0, 0)
	8 #4 (0, 0)
	9 aload_1 (0, 0)
	10 invokeinterface (0, 0)
	11 org/apache/commons/math3/geometry/partitioning/Embedding.checkPoint:(Lorg/apache/commons/math3/geometry/Point;)Lorg/apache/commons/math3/geometry/partitioning/Region$Location; (0, 0)
	13 0 (0, 0)
	15 invokeinterface (0, 0)
	16 org/apache/commons/math3/geometry/partitioning/Region.getProjected:()Lorg/apache/commons/math3/geometry/Point; (0, 0)
	18 0 (0, 0)
	20 astore (0, 0)
	21 #5 (0, 0)
	22 aload (0, 0)
	23 #5 (0, 0)
	24 invokevirtual (0, 0)
	25 org/apache/commons/math3/geometry/partitioning/BoundaryProjection.getProjected:()Lorg/apache/commons/math3/geometry/Point; (0, 0)
	27 ifnonnull (0, 0)
	28 7 (0, 0)
	30 aconst_null (0, 0)
	31 goto (0, 0)
	32 15 (0, 0)
	34 aload (0, 0)
	35 #4 (0, 0)
	36 aload (0, 0)
	37 #5 (0, 0)
	38 invokevirtual (0, 0)
	39 org/apache/commons/math3/geometry/partitioning/BoundaryProjection.getProjected:()Lorg/apache/commons/math3/geometry/Point; (0, 0)
	41 invokeinterface (0, 0)
	42 org/apache/commons/math3/geometry/partitioning/Embedding.org/apache/commons/math3/geometry/partitioning/BoundaryProjector (0, 0)
	44 0 (0, 0)
	46 areturn (0, 0)

