Method: <init>
	0 aload_0 (0, 0)
	1 invokespecial (0, 0)
	2 java/lang/Object.<init>:()V (0, 0)
	4 aload_0 (0, 0)
	5 dconst_0 (0, 0)
	6 putfield (0, 0)
	7 org/apache/commons/math3/geometry/partitioning/BoundarySizeVisitor.boundarySize:D (0, 0)
	9 return (0, 0)

Method: visitOrder
	0 getstatic (0, 0)
	1 org/apache/commons/math3/geometry/partitioning/BSPTreeVisitor$Order.MINUS_SUB_PLUS:Lorg/apache/commons/math3/geometry/partitioning/BSPTreeVisitor$Order; (0, 0)
	3 areturn (0, 0)

Method: visitInternalNode
	0 aload_1 (0, 0)
	1 invokevirtual (0, 0)
	2 org/apache/commons/math3/geometry/partitioning/BSPTree.getAttribute:()Ljava/lang/Object; (0, 0)
	4 checkcast (0, 0)
	5 org/apache/commons/math3/geometry/partitioning/BoundaryAttribute (0, 0)
	7 astore_2 (0, 0)
	8 aload_2 (1, 1)
	9 invokevirtual (1, 1)
	10 org/apache/commons/math3/geometry/partitioning/BoundaryAttribute.getPlusOutside:()Lorg/apache/commons/math3/geometry/partitioning/SubHyperplane; (1, 1)
	12 ifnull (1, 1)
	13 21 (1, 1)
	15 aload_0 (1, 1)
	16 dup (1, 1)
	17 getfield (1, 1)
	18 org/apache/commons/math3/geometry/partitioning/BoundarySizeVisitor.boundarySize:D (1, 1)
	20 aload_2 (1, 1)
	21 invokevirtual (1, 1)
	22 org/apache/commons/math3/geometry/partitioning/BoundaryAttribute.getPlusOutside:()Lorg/apache/commons/math3/geometry/partitioning/SubHyperplane; (1, 1)
	24 invokeinterface (1, 1)
	25 org/apache/commons/math3/geometry/partitioning/SubHyperplane.getPlusInside:()Lorg/apache/commons/math3/geometry/partitioning/SubHyperplane; (1, 1)
	27 0 (1, 1)
	29 dadd (1, 1)
	30 putfield (1, 1)
	31 org/apache/commons/math3/geometry/partitioning/BoundarySizeVisitor.boundarySize:D (1, 1)
	33 aload_2 (1, 1)
	34 invokevirtual (1, 1)
	35 org/apache/commons/math3/geometry/partitioning/BoundaryAttribute.getPlusInside:()Lorg/apache/commons/math3/geometry/partitioning/SubHyperplane; (1, 1)
	37 ifnull (1, 1)
	38 21 (1, 1)
	40 aload_0 (1, 1)
	41 dup (1, 1)
	42 getfield (1, 1)
	43 org/apache/commons/math3/geometry/partitioning/BoundarySizeVisitor.boundarySize:D (1, 1)
	45 aload_2 (1, 1)
	46 invokevirtual (1, 1)
	47 org/apache/commons/math3/geometry/partitioning/BoundaryAttribute.getPlusInside:()Lorg/apache/commons/math3/geometry/partitioning/SubHyperplane; (1, 1)
	49 invokeinterface (1, 1)
	50 org/apache/commons/math3/geometry/partitioning/SubHyperplane.getPlusInside:()Lorg/apache/commons/math3/geometry/partitioning/SubHyperplane; (1, 1)
	52 0 (1, 1)
	54 dadd (1, 1)
	55 putfield (1, 1)
	56 org/apache/commons/math3/geometry/partitioning/BoundarySizeVisitor.boundarySize:D (1, 1)
	58 return (0, 0)

Method: visitLeafNode
	0 return (0, 0)

Method: getSize
	0 aload_0 (0, 0)
	1 getfield (0, 0)
	2 org/apache/commons/math3/geometry/partitioning/BoundarySizeVisitor.boundarySize:D (0, 0)
	4 dreturn (0, 0)

