Method: values
	0 getstatic (0, 0)
	1 org/apache/commons/math3/geometry/partitioning/BSPTreeVisitor$Order.$VALUES:[Lorg/apache/commons/math3/geometry/partitioning/BSPTreeVisitor$Order; (0, 0)
	3 invokevirtual (0, 0)
	4 [Lorg/apache/commons/math3/geometry/partitioning/BSPTreeVisitor$Order;.clone:()Ljava/lang/Object; (0, 0)
	6 checkcast (0, 0)
	7 [Lorg/apache/commons/math3/geometry/partitioning/BSPTreeVisitor$Order; (0, 0)
	9 areturn (0, 0)

Method: valueOf
	0 ldc (0, 0)
	1 org/apache/commons/math3/geometry/partitioning/BSPTreeVisitor$Order (0, 0)
	2 aload_0 (0, 0)
	3 invokestatic (0, 0)
	4 java/lang/Enum.valueOf:(Ljava/lang/Class;Ljava/lang/String;)Ljava/lang/Enum; (0, 0)
	6 checkcast (0, 0)
	7 org/apache/commons/math3/geometry/partitioning/BSPTreeVisitor$Order (0, 0)
	9 areturn (0, 0)

Method: <clinit>
	0 new (0, 0)
	1 org/apache/commons/math3/geometry/partitioning/BSPTreeVisitor$Order (0, 0)
	3 dup (0, 0)
	4 ldc (0, 0)
	5 PLUS_MINUS_SUB (0, 0)
	6 iconst_0 (0, 0)
	7 invokespecial (0, 0)
	8 org/apache/commons/math3/geometry/partitioning/BSPTreeVisitor$Order.<init>:(Ljava/lang/String;I)V (0, 0)
	10 putstatic (0, 0)
	11 org/apache/commons/math3/geometry/partitioning/BSPTreeVisitor$Order.PLUS_MINUS_SUB:Lorg/apache/commons/math3/geometry/partitioning/BSPTreeVisitor$Order; (0, 0)
	13 new (1, 4)
	14 org/apache/commons/math3/geometry/partitioning/BSPTreeVisitor$Order (1, 4)
	16 dup (1, 4)
	17 ldc (1, 4)
	18 PLUS_SUB_MINUS (1, 4)
	19 iconst_1 (1, 4)
	20 invokespecial (1, 4)
	21 org/apache/commons/math3/geometry/partitioning/BSPTreeVisitor$Order.<init>:(Ljava/lang/String;I)V (1, 4)
	23 putstatic (1, 4)
	24 org/apache/commons/math3/geometry/partitioning/BSPTreeVisitor$Order.PLUS_SUB_MINUS:Lorg/apache/commons/math3/geometry/partitioning/BSPTreeVisitor$Order; (1, 4)
	26 new (2, 4)
	27 org/apache/commons/math3/geometry/partitioning/BSPTreeVisitor$Order (2, 4)
	29 dup (2, 4)
	30 ldc (2, 4)
	31 MINUS_PLUS_SUB (2, 4)
	32 iconst_2 (2, 4)
	33 invokespecial (2, 4)
	34 org/apache/commons/math3/geometry/partitioning/BSPTreeVisitor$Order.<init>:(Ljava/lang/String;I)V (2, 4)
	36 putstatic (2, 4)
	37 org/apache/commons/math3/geometry/partitioning/BSPTreeVisitor$Order.MINUS_PLUS_SUB:Lorg/apache/commons/math3/geometry/partitioning/BSPTreeVisitor$Order; (2, 4)
	39 new (3, 4)
	40 org/apache/commons/math3/geometry/partitioning/BSPTreeVisitor$Order (3, 4)
	42 dup (3, 4)
	43 ldc (3, 4)
	44 MINUS_SUB_PLUS (3, 4)
	45 iconst_3 (3, 4)
	46 invokespecial (3, 4)
	47 org/apache/commons/math3/geometry/partitioning/BSPTreeVisitor$Order.<init>:(Ljava/lang/String;I)V (3, 4)
	49 putstatic (3, 4)
	50 org/apache/commons/math3/geometry/partitioning/BSPTreeVisitor$Order.MINUS_SUB_PLUS:Lorg/apache/commons/math3/geometry/partitioning/BSPTreeVisitor$Order; (3, 4)
	52 new (4, 4)
	53 org/apache/commons/math3/geometry/partitioning/BSPTreeVisitor$Order (4, 4)
	55 dup (4, 4)
	56 ldc (4, 4)
	57 SUB_PLUS_MINUS (4, 4)
	58 iconst_4 (4, 4)
	59 invokespecial (4, 4)
	60 org/apache/commons/math3/geometry/partitioning/BSPTreeVisitor$Order.<init>:(Ljava/lang/String;I)V (4, 4)
	62 putstatic (4, 4)
	63 org/apache/commons/math3/geometry/partitioning/BSPTreeVisitor$Order.SUB_PLUS_MINUS:Lorg/apache/commons/math3/geometry/partitioning/BSPTreeVisitor$Order; (4, 4)
	65 new (5, 4)
	66 org/apache/commons/math3/geometry/partitioning/BSPTreeVisitor$Order (5, 4)
	68 dup (5, 4)
	69 ldc (5, 4)
	70 SUB_MINUS_PLUS (5, 4)
	71 iconst_5 (5, 4)
	72 invokespecial (5, 4)
	73 org/apache/commons/math3/geometry/partitioning/BSPTreeVisitor$Order.<init>:(Ljava/lang/String;I)V (5, 4)
	75 putstatic (5, 4)
	76 org/apache/commons/math3/geometry/partitioning/BSPTreeVisitor$Order.SUB_MINUS_PLUS:Lorg/apache/commons/math3/geometry/partitioning/BSPTreeVisitor$Order; (5, 4)
	78 bipush (5, 4)
	79 6 (5, 4)
	80 anewarray (5, 4)
	81 org/apache/commons/math3/geometry/partitioning/BSPTreeVisitor$Order (5, 4)
	83 dup (5, 4)
	84 iconst_0 (5, 4)
	85 getstatic (5, 4)
	86 org/apache/commons/math3/geometry/partitioning/BSPTreeVisitor$Order.PLUS_MINUS_SUB:Lorg/apache/commons/math3/geometry/partitioning/BSPTreeVisitor$Order; (5, 4)
	88 aastore (5, 4)
	89 dup (5, 4)
	90 iconst_1 (5, 4)
	91 getstatic (5, 4)
	92 org/apache/commons/math3/geometry/partitioning/BSPTreeVisitor$Order.PLUS_SUB_MINUS:Lorg/apache/commons/math3/geometry/partitioning/BSPTreeVisitor$Order; (5, 4)
	94 aastore (5, 4)
	95 dup (5, 4)
	96 iconst_2 (5, 4)
	97 getstatic (5, 4)
	98 org/apache/commons/math3/geometry/partitioning/BSPTreeVisitor$Order.MINUS_PLUS_SUB:Lorg/apache/commons/math3/geometry/partitioning/BSPTreeVisitor$Order; (5, 4)
	100 aastore (5, 4)
	101 dup (5, 4)
	102 iconst_3 (5, 4)
	103 getstatic (5, 4)
	104 org/apache/commons/math3/geometry/partitioning/BSPTreeVisitor$Order.MINUS_SUB_PLUS:Lorg/apache/commons/math3/geometry/partitioning/BSPTreeVisitor$Order; (5, 4)
	106 aastore (5, 4)
	107 dup (5, 4)
	108 iconst_4 (5, 4)
	109 getstatic (5, 4)
	110 org/apache/commons/math3/geometry/partitioning/BSPTreeVisitor$Order.SUB_PLUS_MINUS:Lorg/apache/commons/math3/geometry/partitioning/BSPTreeVisitor$Order; (5, 4)
	112 aastore (5, 4)
	113 dup (5, 4)
	114 iconst_5 (5, 4)
	115 getstatic (5, 4)
	116 org/apache/commons/math3/geometry/partitioning/BSPTreeVisitor$Order.SUB_MINUS_PLUS:Lorg/apache/commons/math3/geometry/partitioning/BSPTreeVisitor$Order; (5, 4)
	118 aastore (5, 4)
	119 putstatic (5, 4)
	120 org/apache/commons/math3/geometry/partitioning/BSPTreeVisitor$Order.$VALUES:[Lorg/apache/commons/math3/geometry/partitioning/BSPTreeVisitor$Order; (5, 4)
	122 return (0, 4)

