Method: <init>
	0 aload_0 (0, 0)
	1 invokespecial (0, 0)
	2 java/lang/Object.<init>:()V (0, 0)
	4 aload_0 (0, 0)
	5 aconst_null (0, 0)
	6 putfield (0, 0)
	7 org/apache/commons/math3/geometry/partitioning/BSPTree.cut:Lorg/apache/commons/math3/geometry/partitioning/SubHyperplane; (0, 0)
	9 aload_0 (0, 0)
	10 aconst_null (0, 0)
	11 putfield (0, 0)
	12 org/apache/commons/math3/geometry/partitioning/BSPTree.plus:Lorg/apache/commons/math3/geometry/partitioning/BSPTree; (0, 0)
	14 aload_0 (1, 4)
	15 aconst_null (1, 4)
	16 putfield (1, 4)
	17 org/apache/commons/math3/geometry/partitioning/BSPTree.minus:Lorg/apache/commons/math3/geometry/partitioning/BSPTree; (1, 4)
	19 aload_0 (2, 4)
	20 aconst_null (2, 4)
	21 putfield (2, 4)
	22 org/apache/commons/math3/geometry/partitioning/BSPTree.parent:Lorg/apache/commons/math3/geometry/partitioning/BSPTree; (2, 4)
	24 aload_0 (2, 4)
	25 aload_1 (2, 4)
	26 putfield (2, 4)
	27 org/apache/commons/math3/geometry/partitioning/BSPTree.attribute:Ljava/lang/Object; (2, 4)
	29 return (0, 4)

