Method: <init>
	0 aload_0 (0, 0)
	1 invokespecial (0, 0)
	4 aload_0 (0, 0)
	5 aconst_null (0, 0)
	6 putfield (0, 0)
	9 aload_0 (0, 0)
	10 aconst_null (0, 0)
	11 putfield (0, 0)
	14 aload_0 (0, 0)
	15 new (0, 0)
	18 dup (0, 0)
	19 invokespecial (0, 0)
	22 putfield (0, 0)
	25 aload_0 (0, 0)
	26 new (0, 0)
	29 dup (0, 0)
	30 invokespecial (0, 0)
	33 putfield (0, 0)
	36 aload_0 (0, 0)
	37 aload_1 (0, 0)
	38 aload_2 (0, 0)
	39 new (0, 0)
	42 dup (0, 0)
	43 invokespecial (0, 0)
	46 invokespecial (0, 0)
	49 return (0, 0)

Method: characterize
	0 aload_1 (1, 1)
	1 invokevirtual (1, 1)
	4 ifnonnull (1, 1)
	7 aload_1 (1, 1)
	8 invokevirtual (1, 1)
	11 checkcast (1, 1)
	14 invokevirtual (1, 1)
	17 istore (1, 1)
	19 iload (2, 1)
	21 ifeq (2, 1)
	24 aload_0 (2, 1)
	25 aload_2 (2, 1)
	26 aload_3 (2, 1)
	27 invokespecial (2, 1)
	30 goto (2, 1)
	33 aload_0 (2, 2)
	34 aload_2 (2, 2)
	35 aload_3 (2, 2)
	36 invokespecial (2, 2)
	39 goto (1, 2)
	42 aload_1 (1, 2)
	43 invokevirtual (1, 2)
	46 invokeinterface (1, 2)
	51 astore (1, 2)
	53 aload_2 (1, 2)
	54 aload (1, 2)
	56 invokeinterface (1, 2)
	61 astore (1, 2)
	63 getstatic (2, 5)
	66 aload (2, 5)
	68 invokevirtual (2, 5)
	71 invokevirtual (2, 5)
	74 iaload (2, 5)
	75 tableswitch (2, 5)
	100 aload_0 (2, 5)
	101 aload_1 (2, 5)
	102 invokevirtual (2, 5)
	105 aload_2 (2, 5)
	106 aload_3 (2, 5)
	107 invokespecial (2, 5)
	110 goto (2, 5)
	113 aload_0 (2, 5)
	114 aload_1 (2, 5)
	115 invokevirtual (2, 5)
	118 aload_2 (2, 5)
	119 aload_3 (2, 5)
	120 invokespecial (2, 5)
	123 goto (2, 5)
	126 aload_3 (2, 5)
	127 aload_1 (2, 5)
	128 invokeinterface (2, 5)
	133 pop (2, 5)
	134 aload_0 (2, 5)
	135 aload_1 (2, 5)
	136 invokevirtual (2, 5)
	139 aload (2, 5)
	141 invokevirtual (2, 5)
	144 aload_3 (2, 5)
	145 invokespecial (2, 5)
	148 aload_0 (2, 5)
	149 aload_1 (2, 5)
	150 invokevirtual (2, 5)
	153 aload (2, 5)
	155 invokevirtual (2, 5)
	158 aload_3 (2, 5)
	159 invokespecial (2, 5)
	162 aload_3 (2, 5)
	163 aload_3 (2, 5)
	164 invokeinterface (2, 5)
	169 iconst_1 (2, 5)
	170 isub (2, 5)
	171 invokeinterface (2, 5)
	176 pop (2, 5)
	177 goto (2, 5)
	180 new (2, 5)
	183 dup (2, 5)
	184 invokespecial (2, 5)
	187 athrow (2, 5)
	188 return (0, 1)

Method: addOutsideTouching
	0 aload_0 (1, 1)
	1 getfield (1, 1)
	4 ifnonnull (1, 1)
	7 aload_0 (1, 1)
	8 aload_1 (1, 1)
	9 putfield (1, 1)
	12 goto (1, 1)
	15 aload_0 (1, 2)
	16 aload_0 (1, 2)
	17 getfield (1, 2)
	20 aload_1 (1, 2)
	21 invokeinterface (1, 2)
	26 putfield (1, 2)
	29 aload_0 (0, 1)
	30 getfield (0, 1)
	33 aload_2 (0, 1)
	34 invokevirtual (0, 1)
	37 return (0, 0)

Method: addInsideTouching
	0 aload_0 (1, 1)
	1 getfield (1, 1)
	4 ifnonnull (1, 1)
	7 aload_0 (1, 1)
	8 aload_1 (1, 1)
	9 putfield (1, 1)
	12 goto (1, 1)
	15 aload_0 (1, 2)
	16 aload_0 (1, 2)
	17 getfield (1, 2)
	20 aload_1 (1, 2)
	21 invokeinterface (1, 2)
	26 putfield (1, 2)
	29 aload_0 (0, 1)
	30 getfield (0, 1)
	33 aload_2 (0, 1)
	34 invokevirtual (0, 1)
	37 return (0, 0)

Method: touchOutside
	0 aload_0 (0, 0)
	1 getfield (0, 0)
	4 ifnull (0, 0)
	7 aload_0 (0, 0)
	8 getfield (0, 0)
	11 invokeinterface (0, 0)
	16 ifne (0, 0)
	19 iconst_1 (0, 0)
	20 goto (0, 0)
	23 iconst_0 (0, 0)
	24 ireturn (0, 0)

Method: outsideTouching
	0 aload_0 (0, 0)
	1 getfield (0, 0)
	4 areturn (0, 0)

Method: getOutsideSplitters
	0 aload_0 (0, 0)
	1 getfield (0, 0)
	4 areturn (0, 0)

Method: touchInside
	0 aload_0 (0, 0)
	1 getfield (0, 0)
	4 ifnull (0, 0)
	7 aload_0 (0, 0)
	8 getfield (0, 0)
	11 invokeinterface (0, 0)
	16 ifne (0, 0)
	19 iconst_1 (0, 0)
	20 goto (0, 0)
	23 iconst_0 (0, 0)
	24 ireturn (0, 0)

Method: insideTouching
	0 aload_0 (0, 0)
	1 getfield (0, 0)
	4 areturn (0, 0)

Method: getInsideSplitters
	0 aload_0 (0, 0)
	1 getfield (0, 0)
	4 areturn (0, 0)

