Method: <init>
	0 aload_0 (0, 0)
	1 invokespecial (0, 0)
	2 java/lang/Object.<init>:()V (0, 0)
	4 aload_0 (0, 0)
	5 aconst_null (0, 0)
	6 putfield (0, 0)
	7 org/apache/commons/math3/geometry/partitioning/Characterization.outsideTouching:Lorg/apache/commons/math3/geometry/partitioning/SubHyperplane; (0, 0)
	9 aload_0 (0, 0)
	10 aconst_null (0, 0)
	11 putfield (0, 0)
	12 org/apache/commons/math3/geometry/partitioning/Characterization.insideTouching:Lorg/apache/commons/math3/geometry/partitioning/SubHyperplane; (0, 0)
	14 aload_0 (0, 0)
	15 new (0, 0)
	16 org/apache/commons/math3/geometry/partitioning/NodesSet (0, 0)
	18 dup (0, 0)
	19 invokespecial (0, 0)
	20 org/apache/commons/math3/geometry/partitioning/NodesSet.<init>:()V (0, 0)
	22 putfield (0, 0)
	23 org/apache/commons/math3/geometry/partitioning/Characterization.outsideSplitters:Lorg/apache/commons/math3/geometry/partitioning/NodesSet; (0, 0)
	25 aload_0 (0, 0)
	26 new (0, 0)
	27 org/apache/commons/math3/geometry/partitioning/NodesSet (0, 0)
	29 dup (0, 0)
	30 invokespecial (0, 0)
	31 org/apache/commons/math3/geometry/partitioning/NodesSet.<init>:()V (0, 0)
	33 putfield (0, 0)
	34 org/apache/commons/math3/geometry/partitioning/Characterization.insideSplitters:Lorg/apache/commons/math3/geometry/partitioning/NodesSet; (0, 0)
	36 aload_0 (0, 0)
	37 aload_1 (0, 0)
	38 aload_2 (0, 0)
	39 new (0, 0)
	40 java/util/ArrayList (0, 0)
	42 dup (0, 0)
	43 invokespecial (0, 0)
	44 java/util/ArrayList.<init>:()V (0, 0)
	46 invokespecial (0, 0)
	47 org/apache/commons/math3/geometry/partitioning/Characterization.characterize:(Lorg/apache/commons/math3/geometry/partitioning/BSPTree;Lorg/apache/commons/math3/geometry/partitioning/SubHyperplane;Ljava/util/List;)V (0, 0)
	49 return (0, 0)

Method: characterize
	0 aload_1 (1, 1)
	1 invokevirtual (1, 1)
	2 org/apache/commons/math3/geometry/partitioning/BSPTree.getCut:()Lorg/apache/commons/math3/geometry/partitioning/SubHyperplane; (1, 1)
	4 ifnonnull (1, 1)
	5 38 (1, 1)
	7 aload_1 (1, 1)
	8 invokevirtual (1, 1)
	9 org/apache/commons/math3/geometry/partitioning/BSPTree.getAttribute:()Ljava/lang/Object; (1, 1)
	11 checkcast (1, 1)
	12 java/lang/Boolean (1, 1)
	14 invokevirtual (1, 1)
	15 java/lang/Boolean.booleanValue:()Z (1, 1)
	17 istore (1, 1)
	18 #4 (1, 1)
	19 iload (2, 1)
	20 #4 (2, 1)
	21 ifeq (2, 1)
	22 12 (2, 1)
	24 aload_0 (2, 1)
	25 aload_2 (2, 1)
	26 aload_3 (2, 1)
	27 invokespecial (2, 1)
	28 org/apache/commons/math3/geometry/partitioning/Characterization.addInsideTouching:(Lorg/apache/commons/math3/geometry/partitioning/SubHyperplane;Ljava/util/List;)V (2, 1)
	30 goto (2, 1)
	31 9 (2, 1)
	33 aload_0 (3, 2)
	34 aload_2 (3, 2)
	35 aload_3 (3, 2)
	36 invokespecial (3, 2)
	37 org/apache/commons/math3/geometry/partitioning/Characterization.addOutsideTouching:(Lorg/apache/commons/math3/geometry/partitioning/SubHyperplane;Ljava/util/List;)V (3, 2)
	39 goto (2, 2)
	40 149 (2, 2)
	42 aload_1 (2, 2)
	43 invokevirtual (2, 2)
	44 org/apache/commons/math3/geometry/partitioning/BSPTree.getCut:()Lorg/apache/commons/math3/geometry/partitioning/SubHyperplane; (2, 2)
	46 invokeinterface (2, 2)
	47 org/apache/commons/math3/geometry/partitioning/SubHyperplane.split:(Lorg/apache/commons/math3/geometry/partitioning/Hyperplane;)Lorg/apache/commons/math3/geometry/partitioning/SubHyperplane$SplitSubHyperplane; (2, 2)
	49 0 (2, 2)
	51 astore (2, 2)
	52 #4 (2, 2)
	53 aload_2 (2, 2)
	54 aload (2, 2)
	55 #4 (2, 2)
	56 invokeinterface (2, 2)
	57 org/apache/commons/math3/geometry/partitioning/SubHyperplane.$SwitchMap$org$apache$commons$math3$geometry$partitioning$Side:[I (2, 2)
	59 0 (2, 2)
	61 astore (2, 2)
	62 #5 (2, 2)
	63 getstatic (3, 5)
	64 org/apache/commons/math3/geometry/partitioning/Characterization$1.$SwitchMap$org$apache$commons$math3$geometry$partitioning$Side:[I (3, 5)
	66 aload (3, 5)
	67 #5 (3, 5)
	68 invokevirtual (3, 5)
	69 org/apache/commons/math3/geometry/partitioning/SubHyperplane$SplitSubHyperplane.getSide:()Lorg/apache/commons/math3/geometry/partitioning/Side; (3, 5)
	71 invokevirtual (3, 5)
	72 org/apache/commons/math3/geometry/partitioning/Side.ordinal:()I (3, 5)
	74 iaload (3, 5)
	75 tableswitch (3, 5)
	76 1 100 (3, 5)
	80 2 113 (3, 5)
	84 3 126 (3, 5)
	100 aload_0 (3, 5)
	101 aload_1 (3, 5)
	102 invokevirtual (3, 5)
	103 org/apache/commons/math3/geometry/partitioning/BSPTree.getPlus:()Lorg/apache/commons/math3/geometry/partitioning/BSPTree; (3, 5)
	105 aload_2 (3, 5)
	106 aload_3 (3, 5)
	107 invokespecial (3, 5)
	108 org/apache/commons/math3/geometry/partitioning/Characterization.characterize:(Lorg/apache/commons/math3/geometry/partitioning/BSPTree;Lorg/apache/commons/math3/geometry/partitioning/SubHyperplane;Ljava/util/List;)V (3, 5)
	110 goto (3, 5)
	111 78 (3, 5)
	113 aload_0 (3, 5)
	114 aload_1 (3, 5)
	115 invokevirtual (3, 5)
	116 org/apache/commons/math3/geometry/partitioning/BSPTree.getMinus:()Lorg/apache/commons/math3/geometry/partitioning/BSPTree; (3, 5)
	118 aload_2 (3, 5)
	119 aload_3 (3, 5)
	120 invokespecial (3, 5)
	121 org/apache/commons/math3/geometry/partitioning/Characterization.characterize:(Lorg/apache/commons/math3/geometry/partitioning/BSPTree;Lorg/apache/commons/math3/geometry/partitioning/SubHyperplane;Ljava/util/List;)V (3, 5)
	123 goto (3, 5)
	124 65 (3, 5)
	126 aload_3 (3, 5)
	127 aload_1 (3, 5)
	128 invokeinterface (3, 5)
	129 java/util/List.getPlus:()Lorg/apache/commons/math3/geometry/partitioning/SubHyperplane; (3, 5)
	131 0 (3, 5)
	133 pop (3, 5)
	134 aload_0 (3, 5)
	135 aload_1 (3, 5)
	136 invokevirtual (3, 5)
	137 org/apache/commons/math3/geometry/partitioning/BSPTree.getPlus:()Lorg/apache/commons/math3/geometry/partitioning/BSPTree; (3, 5)
	139 aload (3, 5)
	140 #5 (3, 5)
	141 invokevirtual (3, 5)
	142 org/apache/commons/math3/geometry/partitioning/SubHyperplane$SplitSubHyperplane.getPlus:()Lorg/apache/commons/math3/geometry/partitioning/SubHyperplane; (3, 5)
	144 aload_3 (3, 5)
	145 invokespecial (3, 5)
	146 org/apache/commons/math3/geometry/partitioning/Characterization.characterize:(Lorg/apache/commons/math3/geometry/partitioning/BSPTree;Lorg/apache/commons/math3/geometry/partitioning/SubHyperplane;Ljava/util/List;)V (3, 5)
	148 aload_0 (3, 5)
	149 aload_1 (3, 5)
	150 invokevirtual (3, 5)
	151 org/apache/commons/math3/geometry/partitioning/BSPTree.getMinus:()Lorg/apache/commons/math3/geometry/partitioning/BSPTree; (3, 5)
	153 aload (3, 5)
	154 #5 (3, 5)
	155 invokevirtual (3, 5)
	156 org/apache/commons/math3/geometry/partitioning/SubHyperplane$SplitSubHyperplane.getMinus:()Lorg/apache/commons/math3/geometry/partitioning/SubHyperplane; (3, 5)
	158 aload_3 (3, 5)
	159 invokespecial (3, 5)
	160 org/apache/commons/math3/geometry/partitioning/Characterization.characterize:(Lorg/apache/commons/math3/geometry/partitioning/BSPTree;Lorg/apache/commons/math3/geometry/partitioning/SubHyperplane;Ljava/util/List;)V (3, 5)
	162 aload_3 (3, 5)
	163 aload_3 (3, 5)
	164 invokeinterface (3, 5)
	165 java/util/List.remove:(I)Ljava/lang/Object; (3, 5)
	167 0 (3, 5)
	169 iconst_1 (3, 5)
	170 isub (3, 5)
	171 invokeinterface (3, 5)
	172 java/util/List.org/apache/commons/math3/exception/MathInternalError (3, 5)
	174 0 (3, 5)
	176 pop (3, 5)
	177 goto (3, 5)
	178 11 (3, 5)
	180 new (3, 5)
	181 org/apache/commons/math3/exception/MathInternalError (3, 5)
	183 dup (3, 5)
	184 invokespecial (3, 5)
	185 org/apache/commons/math3/exception/MathInternalError.<init>:()V (3, 5)
	187 athrow (3, 5)
	188 return (0, 0)

Method: addOutsideTouching
	0 aload_0 (1, 1)
	1 getfield (1, 1)
	2 org/apache/commons/math3/geometry/partitioning/Characterization.outsideTouching:Lorg/apache/commons/math3/geometry/partitioning/SubHyperplane; (1, 1)
	4 ifnonnull (1, 1)
	5 11 (1, 1)
	7 aload_0 (1, 1)
	8 aload_1 (1, 1)
	9 putfield (1, 1)
	10 org/apache/commons/math3/geometry/partitioning/Characterization.outsideTouching:Lorg/apache/commons/math3/geometry/partitioning/SubHyperplane; (1, 1)
	12 goto (1, 1)
	13 17 (1, 1)
	15 aload_0 (2, 2)
	16 aload_0 (2, 2)
	17 getfield (2, 2)
	18 org/apache/commons/math3/geometry/partitioning/Characterization.outsideTouching:Lorg/apache/commons/math3/geometry/partitioning/SubHyperplane; (2, 2)
	20 aload_1 (2, 2)
	21 invokeinterface (2, 2)
	22 org/apache/commons/math3/geometry/partitioning/SubHyperplane.addAll:(Ljava/lang/Iterable;)V (2, 2)
	24 0 (2, 2)
	26 putfield (2, 2)
	27 org/apache/commons/math3/geometry/partitioning/Characterization.outsideTouching:Lorg/apache/commons/math3/geometry/partitioning/SubHyperplane; (2, 2)
	29 aload_0 (0, 0)
	30 getfield (0, 0)
	31 org/apache/commons/math3/geometry/partitioning/Characterization.outsideSplitters:Lorg/apache/commons/math3/geometry/partitioning/NodesSet; (0, 0)
	33 aload_2 (0, 0)
	34 invokevirtual (0, 0)
	35 org/apache/commons/math3/geometry/partitioning/NodesSet.addAll:(Ljava/lang/Iterable;)V (0, 0)
	37 return (0, 0)

Method: addInsideTouching
	0 aload_0 (1, 1)
	1 getfield (1, 1)
	2 org/apache/commons/math3/geometry/partitioning/Characterization.insideTouching:Lorg/apache/commons/math3/geometry/partitioning/SubHyperplane; (1, 1)
	4 ifnonnull (1, 1)
	5 11 (1, 1)
	7 aload_0 (1, 1)
	8 aload_1 (1, 1)
	9 putfield (1, 1)
	10 org/apache/commons/math3/geometry/partitioning/Characterization.insideTouching:Lorg/apache/commons/math3/geometry/partitioning/SubHyperplane; (1, 1)
	12 goto (1, 1)
	13 17 (1, 1)
	15 aload_0 (2, 2)
	16 aload_0 (2, 2)
	17 getfield (2, 2)
	18 org/apache/commons/math3/geometry/partitioning/Characterization.insideTouching:Lorg/apache/commons/math3/geometry/partitioning/SubHyperplane; (2, 2)
	20 aload_1 (2, 2)
	21 invokeinterface (2, 2)
	22 org/apache/commons/math3/geometry/partitioning/SubHyperplane.addAll:(Ljava/lang/Iterable;)V (2, 2)
	24 0 (2, 2)
	26 putfield (2, 2)
	27 org/apache/commons/math3/geometry/partitioning/Characterization.insideTouching:Lorg/apache/commons/math3/geometry/partitioning/SubHyperplane; (2, 2)
	29 aload_0 (0, 0)
	30 getfield (0, 0)
	31 org/apache/commons/math3/geometry/partitioning/Characterization.insideSplitters:Lorg/apache/commons/math3/geometry/partitioning/NodesSet; (0, 0)
	33 aload_2 (0, 0)
	34 invokevirtual (0, 0)
	35 org/apache/commons/math3/geometry/partitioning/NodesSet.addAll:(Ljava/lang/Iterable;)V (0, 0)
	37 return (0, 0)

Method: touchOutside
	0 aload_0 (0, 0)
	1 getfield (0, 0)
	2 org/apache/commons/math3/geometry/partitioning/Characterization.outsideTouching:Lorg/apache/commons/math3/geometry/partitioning/SubHyperplane; (0, 0)
	4 ifnull (0, 0)
	5 19 (0, 0)
	7 aload_0 (0, 0)
	8 getfield (0, 0)
	9 org/apache/commons/math3/geometry/partitioning/Characterization.outsideTouching:Lorg/apache/commons/math3/geometry/partitioning/SubHyperplane; (0, 0)
	11 invokeinterface (0, 0)
	12 org/apache/commons/math3/geometry/partitioning/SubHyperplane.org/apache/commons/math3/geometry/partitioning/Characterization (0, 0)
	14 0 (0, 0)
	16 ifne (0, 0)
	17 7 (0, 0)
	19 iconst_1 (0, 0)
	20 goto (0, 0)
	21 4 (0, 0)
	23 iconst_0 (0, 0)
	24 ireturn (0, 0)

Method: outsideTouching
	0 aload_0 (0, 0)
	1 getfield (0, 0)
	2 org/apache/commons/math3/geometry/partitioning/Characterization.outsideTouching:Lorg/apache/commons/math3/geometry/partitioning/SubHyperplane; (0, 0)
	4 areturn (0, 0)

Method: getOutsideSplitters
	0 aload_0 (0, 0)
	1 getfield (0, 0)
	2 org/apache/commons/math3/geometry/partitioning/Characterization.outsideSplitters:Lorg/apache/commons/math3/geometry/partitioning/NodesSet; (0, 0)
	4 areturn (0, 0)

Method: touchInside
	0 aload_0 (0, 0)
	1 getfield (0, 0)
	2 org/apache/commons/math3/geometry/partitioning/Characterization.insideTouching:Lorg/apache/commons/math3/geometry/partitioning/SubHyperplane; (0, 0)
	4 ifnull (0, 0)
	5 19 (0, 0)
	7 aload_0 (0, 0)
	8 getfield (0, 0)
	9 org/apache/commons/math3/geometry/partitioning/Characterization.insideTouching:Lorg/apache/commons/math3/geometry/partitioning/SubHyperplane; (0, 0)
	11 invokeinterface (0, 0)
	12 org/apache/commons/math3/geometry/partitioning/SubHyperplane.org/apache/commons/math3/geometry/partitioning/Characterization (0, 0)
	14 0 (0, 0)
	16 ifne (0, 0)
	17 7 (0, 0)
	19 iconst_1 (0, 0)
	20 goto (0, 0)
	21 4 (0, 0)
	23 iconst_0 (0, 0)
	24 ireturn (0, 0)

Method: insideTouching
	0 aload_0 (0, 0)
	1 getfield (0, 0)
	2 org/apache/commons/math3/geometry/partitioning/Characterization.insideTouching:Lorg/apache/commons/math3/geometry/partitioning/SubHyperplane; (0, 0)
	4 areturn (0, 0)

Method: getInsideSplitters
	0 aload_0 (0, 0)
	1 getfield (0, 0)
	2 org/apache/commons/math3/geometry/partitioning/Characterization.insideSplitters:Lorg/apache/commons/math3/geometry/partitioning/NodesSet; (0, 0)
	4 areturn (0, 0)

