Method: <init>
	0 aload_0 (0, 0)
	1 invokespecial (0, 0)
	4 aload_0 (0, 0)
	5 aload_1 (0, 0)
	6 putfield (0, 0)
	9 aload_0 (0, 0)
	10 iconst_0 (0, 0)
	11 putfield (0, 0)
	14 aload_0 (0, 0)
	15 iconst_0 (0, 0)
	16 putfield (0, 0)
	19 return (0, 0)

Method: recurseSides
	0 aload_1 (1, 1)
	1 invokevirtual (1, 1)
	4 ifnonnull (1, 1)
	7 aload_1 (2, 1)
	8 invokevirtual (2, 1)
	11 checkcast (2, 1)
	14 invokevirtual (2, 1)
	17 ifeq (2, 1)
	20 aload_0 (2, 1)
	21 iconst_1 (2, 1)
	22 putfield (2, 1)
	25 aload_0 (2, 1)
	26 iconst_1 (2, 1)
	27 putfield (2, 1)
	30 return (1, 1)
	31 aload_1 (0, 0)
	32 invokevirtual (0, 0)
	35 invokeinterface (0, 0)
	40 astore_3 (0, 0)
	41 aload_2 (0, 0)
	42 aload_3 (0, 0)
	43 invokeinterface (0, 0)
	48 astore (0, 0)
	50 getstatic (1, 5)
	53 aload (1, 5)
	55 invokevirtual (1, 5)
	58 invokevirtual (1, 5)
	61 iaload (1, 5)
	62 tableswitch (1, 5)
	88 aload_1 (2, 1)
	89 invokevirtual (2, 1)
	92 aload_2 (2, 1)
	93 invokeinterface (2, 1)
	98 invokeinterface (2, 1)
	103 invokevirtual (2, 1)
	106 getstatic (2, 1)
	109 if_acmpne (2, 1)
	112 aload_0 (3, 1)
	113 getfield (3, 1)
	116 aload_1 (3, 1)
	117 invokevirtual (3, 1)
	120 invokeinterface (3, 1)
	125 ifne (3, 1)
	128 aload_0 (3, 1)
	129 iconst_1 (3, 1)
	130 putfield (3, 1)
	133 goto (3, 1)
	136 aload_0 (3, 1)
	137 getfield (3, 1)
	140 aload_1 (3, 1)
	141 invokevirtual (3, 1)
	144 invokeinterface (3, 1)
	149 ifne (3, 1)
	152 aload_0 (3, 1)
	153 iconst_1 (3, 1)
	154 putfield (3, 1)
	157 aload_0 (2, 1)
	158 getfield (2, 1)
	161 ifeq (2, 1)
	164 aload_0 (2, 1)
	165 getfield (2, 1)
	168 ifne (2, 1)
	171 aload_0 (2, 1)
	172 aload_1 (2, 1)
	173 invokevirtual (2, 1)
	176 aload_2 (2, 1)
	177 invokevirtual (2, 1)
	180 goto (2, 1)
	183 aload_1 (2, 1)
	184 invokevirtual (2, 1)
	187 aload_2 (2, 1)
	188 invokeinterface (2, 1)
	193 invokeinterface (2, 1)
	198 invokevirtual (2, 1)
	201 getstatic (2, 1)
	204 if_acmpne (2, 1)
	207 aload_0 (3, 1)
	208 getfield (3, 1)
	211 aload_1 (3, 1)
	212 invokevirtual (3, 1)
	215 invokeinterface (3, 1)
	220 ifne (3, 1)
	223 aload_0 (3, 1)
	224 iconst_1 (3, 1)
	225 putfield (3, 1)
	228 goto (3, 1)
	231 aload_0 (3, 1)
	232 getfield (3, 1)
	235 aload_1 (3, 1)
	236 invokevirtual (3, 1)
	239 invokeinterface (3, 1)
	244 ifne (3, 1)
	247 aload_0 (3, 1)
	248 iconst_1 (3, 1)
	249 putfield (3, 1)
	252 aload_0 (2, 1)
	253 getfield (2, 1)
	256 ifeq (2, 1)
	259 aload_0 (2, 1)
	260 getfield (2, 1)
	263 ifne (2, 1)
	266 aload_0 (2, 1)
	267 aload_1 (2, 1)
	268 invokevirtual (2, 1)
	271 aload_2 (2, 1)
	272 invokevirtual (2, 1)
	275 goto (2, 1)
	278 aload_0 (1, 1)
	279 aload_1 (1, 1)
	280 invokevirtual (1, 1)
	283 aload (1, 1)
	285 invokevirtual (1, 1)
	288 invokevirtual (1, 1)
	291 aload_0 (2, 1)
	292 getfield (2, 1)
	295 ifeq (2, 1)
	298 aload_0 (2, 1)
	299 getfield (2, 1)
	302 ifne (2, 1)
	305 aload_0 (2, 1)
	306 aload_1 (2, 1)
	307 invokevirtual (2, 1)
	310 aload (2, 1)
	312 invokevirtual (2, 1)
	315 invokevirtual (2, 1)
	318 goto (2, 1)
	321 aload_1 (2, 1)
	322 invokevirtual (2, 1)
	325 invokeinterface (2, 1)
	330 aload_2 (2, 1)
	331 invokeinterface (2, 1)
	336 invokeinterface (2, 1)
	341 ifeq (2, 1)
	344 aload_1 (3, 1)
	345 invokevirtual (3, 1)
	348 invokevirtual (3, 1)
	351 ifnonnull (3, 1)
	354 aload_1 (3, 1)
	355 invokevirtual (3, 1)
	358 invokevirtual (3, 1)
	361 checkcast (3, 1)
	364 invokevirtual (3, 1)
	367 ifeq (3, 1)
	370 aload_0 (3, 1)
	371 iconst_1 (3, 1)
	372 putfield (3, 1)
	375 aload_1 (3, 1)
	376 invokevirtual (3, 1)
	379 invokevirtual (3, 1)
	382 ifnonnull (3, 1)
	385 aload_1 (3, 1)
	386 invokevirtual (3, 1)
	389 invokevirtual (3, 1)
	392 checkcast (3, 1)
	395 invokevirtual (3, 1)
	398 ifeq (3, 1)
	401 aload_0 (3, 1)
	402 iconst_1 (3, 1)
	403 putfield (3, 1)
	406 goto (3, 1)
	409 aload_1 (3, 1)
	410 invokevirtual (3, 1)
	413 invokevirtual (3, 1)
	416 ifnonnull (3, 1)
	419 aload_1 (3, 1)
	420 invokevirtual (3, 1)
	423 invokevirtual (3, 1)
	426 checkcast (3, 1)
	429 invokevirtual (3, 1)
	432 ifeq (3, 1)
	435 aload_0 (3, 1)
	436 iconst_1 (3, 1)
	437 putfield (3, 1)
	440 aload_1 (3, 1)
	441 invokevirtual (3, 1)
	444 invokevirtual (3, 1)
	447 ifnonnull (3, 1)
	450 aload_1 (3, 1)
	451 invokevirtual (3, 1)
	454 invokevirtual (3, 1)
	457 checkcast (3, 1)
	460 invokevirtual (3, 1)
	463 ifeq (3, 1)
	466 aload_0 (3, 1)
	467 iconst_1 (3, 1)
	468 putfield (3, 1)
	471 return (0, 1)

Method: plusFound
	0 aload_0 (0, 0)
	1 getfield (0, 0)
	4 ireturn (0, 0)

Method: minusFound
	0 aload_0 (0, 0)
	1 getfield (0, 0)
	4 ireturn (0, 0)

