Method: <init>
	0 aload_0 (0, 0)
	1 invokespecial (0, 0)
	2 java/lang/Object.<init>:()V (0, 0)
	4 aload_0 (0, 0)
	5 aload_1 (0, 0)
	6 putfield (0, 0)
	7 org/apache/commons/math3/geometry/partitioning/InsideFinder.region:Lorg/apache/commons/math3/geometry/partitioning/Region; (0, 0)
	9 aload_0 (0, 0)
	10 iconst_0 (0, 0)
	11 putfield (0, 0)
	12 org/apache/commons/math3/geometry/partitioning/InsideFinder.plusFound:Z (0, 0)
	14 aload_0 (0, 0)
	15 iconst_0 (0, 0)
	16 putfield (0, 0)
	17 org/apache/commons/math3/geometry/partitioning/InsideFinder.minusFound:Z (0, 0)
	19 return (0, 0)

Method: recurseSides
	0 aload_1 (1, 1)
	1 invokevirtual (1, 1)
	2 org/apache/commons/math3/geometry/partitioning/BSPTree.getCut:()Lorg/apache/commons/math3/geometry/partitioning/SubHyperplane; (1, 1)
	4 ifnonnull (1, 1)
	5 27 (1, 1)
	7 aload_1 (2, 1)
	8 invokevirtual (2, 1)
	9 org/apache/commons/math3/geometry/partitioning/BSPTree.getAttribute:()Ljava/lang/Object; (2, 1)
	11 checkcast (2, 1)
	12 java/lang/Boolean (2, 1)
	14 invokevirtual (2, 1)
	15 java/lang/Boolean.booleanValue:()Z (2, 1)
	17 ifeq (2, 1)
	18 13 (2, 1)
	20 aload_0 (2, 1)
	21 iconst_1 (2, 1)
	22 putfield (2, 1)
	23 org/apache/commons/math3/geometry/partitioning/InsideFinder.plusFound:Z (2, 1)
	25 aload_0 (2, 1)
	26 iconst_1 (2, 1)
	27 putfield (2, 1)
	28 org/apache/commons/math3/geometry/partitioning/InsideFinder.minusFound:Z (2, 1)
	30 return (1, 1)
	31 aload_1 (0, 0)
	32 invokevirtual (0, 0)
	33 org/apache/commons/math3/geometry/partitioning/BSPTree.getCut:()Lorg/apache/commons/math3/geometry/partitioning/SubHyperplane; (0, 0)
	35 invokeinterface (0, 0)
	36 org/apache/commons/math3/geometry/partitioning/SubHyperplane.split:(Lorg/apache/commons/math3/geometry/partitioning/Hyperplane;)Lorg/apache/commons/math3/geometry/partitioning/SubHyperplane$SplitSubHyperplane; (0, 0)
	38 0 (0, 0)
	40 astore_3 (0, 0)
	41 aload_2 (0, 0)
	42 aload_3 (0, 0)
	43 invokeinterface (0, 0)
	44 org/apache/commons/math3/geometry/partitioning/SubHyperplane.$SwitchMap$org$apache$commons$math3$geometry$partitioning$Side:[I (0, 0)
	46 0 (0, 0)
	48 astore (0, 0)
	49 #4 (0, 0)
	50 getstatic (1, 5)
	51 org/apache/commons/math3/geometry/partitioning/InsideFinder$1.$SwitchMap$org$apache$commons$math3$geometry$partitioning$Side:[I (1, 5)
	53 aload (1, 5)
	54 #4 (1, 5)
	55 invokevirtual (1, 5)
	56 org/apache/commons/math3/geometry/partitioning/SubHyperplane$SplitSubHyperplane.getSide:()Lorg/apache/commons/math3/geometry/partitioning/Side; (1, 5)
	58 invokevirtual (1, 5)
	59 org/apache/commons/math3/geometry/partitioning/Side.ordinal:()I (1, 5)
	61 iaload (1, 5)
	62 tableswitch (1, 5)
	63 1 88 (1, 5)
	67 2 183 (1, 5)
	71 3 278 (1, 5)
	88 aload_1 (2, 1)
	89 invokevirtual (2, 1)
	90 org/apache/commons/math3/geometry/partitioning/BSPTree.getCut:()Lorg/apache/commons/math3/geometry/partitioning/SubHyperplane; (2, 1)
	92 aload_2 (2, 1)
	93 invokeinterface (2, 1)
	94 org/apache/commons/math3/geometry/partitioning/SubHyperplane.split:(Lorg/apache/commons/math3/geometry/partitioning/Hyperplane;)Lorg/apache/commons/math3/geometry/partitioning/SubHyperplane$SplitSubHyperplane; (2, 1)
	96 0 (2, 1)
	98 invokeinterface (2, 1)
	99 org/apache/commons/math3/geometry/partitioning/SubHyperplane.$SwitchMap$org$apache$commons$math3$geometry$partitioning$Side:[I (2, 1)
	101 0 (2, 1)
	103 invokevirtual (2, 1)
	104 org/apache/commons/math3/geometry/partitioning/SubHyperplane$SplitSubHyperplane.getSide:()Lorg/apache/commons/math3/geometry/partitioning/Side; (2, 1)
	106 getstatic (2, 1)
	107 org/apache/commons/math3/geometry/partitioning/Side.PLUS:Lorg/apache/commons/math3/geometry/partitioning/Side; (2, 1)
	109 if_acmpne (2, 1)
	110 27 (2, 1)
	112 aload_0 (3, 1)
	113 getfield (3, 1)
	114 org/apache/commons/math3/geometry/partitioning/InsideFinder.region:Lorg/apache/commons/math3/geometry/partitioning/Region; (3, 1)
	116 aload_1 (3, 1)
	117 invokevirtual (3, 1)
	118 org/apache/commons/math3/geometry/partitioning/BSPTree.getMinus:()Lorg/apache/commons/math3/geometry/partitioning/BSPTree; (3, 1)
	120 invokeinterface (3, 1)
	121 org/apache/commons/math3/geometry/partitioning/Region.getPlus:()Lorg/apache/commons/math3/geometry/partitioning/BSPTree; (3, 1)
	123 0 (3, 1)
	125 ifne (3, 1)
	126 32 (3, 1)
	128 aload_0 (3, 1)
	129 iconst_1 (3, 1)
	130 putfield (3, 1)
	131 org/apache/commons/math3/geometry/partitioning/InsideFinder.plusFound:Z (3, 1)
	133 goto (3, 1)
	134 24 (3, 1)
	136 aload_0 (3, 1)
	137 getfield (3, 1)
	138 org/apache/commons/math3/geometry/partitioning/InsideFinder.region:Lorg/apache/commons/math3/geometry/partitioning/Region; (3, 1)
	140 aload_1 (3, 1)
	141 invokevirtual (3, 1)
	142 org/apache/commons/math3/geometry/partitioning/BSPTree.getMinus:()Lorg/apache/commons/math3/geometry/partitioning/BSPTree; (3, 1)
	144 invokeinterface (3, 1)
	145 org/apache/commons/math3/geometry/partitioning/Region.getPlus:()Lorg/apache/commons/math3/geometry/partitioning/BSPTree; (3, 1)
	147 0 (3, 1)
	149 ifne (3, 1)
	150 8 (3, 1)
	152 aload_0 (3, 1)
	153 iconst_1 (3, 1)
	154 putfield (3, 1)
	155 org/apache/commons/math3/geometry/partitioning/InsideFinder.minusFound:Z (3, 1)
	157 aload_0 (2, 1)
	158 getfield (2, 1)
	159 org/apache/commons/math3/geometry/partitioning/InsideFinder.plusFound:Z (2, 1)
	161 ifeq (2, 1)
	162 10 (2, 1)
	164 aload_0 (2, 1)
	165 getfield (2, 1)
	166 org/apache/commons/math3/geometry/partitioning/InsideFinder.minusFound:Z (2, 1)
	168 ifne (2, 1)
	169 303 (2, 1)
	171 aload_0 (2, 1)
	172 aload_1 (2, 1)
	173 invokevirtual (2, 1)
	174 org/apache/commons/math3/geometry/partitioning/BSPTree.getPlus:()Lorg/apache/commons/math3/geometry/partitioning/BSPTree; (2, 1)
	176 aload_2 (2, 1)
	177 invokevirtual (2, 1)
	178 org/apache/commons/math3/geometry/partitioning/InsideFinder.recurseSides:(Lorg/apache/commons/math3/geometry/partitioning/BSPTree;Lorg/apache/commons/math3/geometry/partitioning/SubHyperplane;)V (2, 1)
	180 goto (2, 1)
	181 291 (2, 1)
	183 aload_1 (2, 1)
	184 invokevirtual (2, 1)
	185 org/apache/commons/math3/geometry/partitioning/BSPTree.getCut:()Lorg/apache/commons/math3/geometry/partitioning/SubHyperplane; (2, 1)
	187 aload_2 (2, 1)
	188 invokeinterface (2, 1)
	189 org/apache/commons/math3/geometry/partitioning/SubHyperplane.split:(Lorg/apache/commons/math3/geometry/partitioning/Hyperplane;)Lorg/apache/commons/math3/geometry/partitioning/SubHyperplane$SplitSubHyperplane; (2, 1)
	191 0 (2, 1)
	193 invokeinterface (2, 1)
	194 org/apache/commons/math3/geometry/partitioning/SubHyperplane.$SwitchMap$org$apache$commons$math3$geometry$partitioning$Side:[I (2, 1)
	196 0 (2, 1)
	198 invokevirtual (2, 1)
	199 org/apache/commons/math3/geometry/partitioning/SubHyperplane$SplitSubHyperplane.getSide:()Lorg/apache/commons/math3/geometry/partitioning/Side; (2, 1)
	201 getstatic (2, 1)
	202 org/apache/commons/math3/geometry/partitioning/Side.PLUS:Lorg/apache/commons/math3/geometry/partitioning/Side; (2, 1)
	204 if_acmpne (2, 1)
	205 27 (2, 1)
	207 aload_0 (3, 1)
	208 getfield (3, 1)
	209 org/apache/commons/math3/geometry/partitioning/InsideFinder.region:Lorg/apache/commons/math3/geometry/partitioning/Region; (3, 1)
	211 aload_1 (3, 1)
	212 invokevirtual (3, 1)
	213 org/apache/commons/math3/geometry/partitioning/BSPTree.getPlus:()Lorg/apache/commons/math3/geometry/partitioning/BSPTree; (3, 1)
	215 invokeinterface (3, 1)
	216 org/apache/commons/math3/geometry/partitioning/Region.getPlus:()Lorg/apache/commons/math3/geometry/partitioning/BSPTree; (3, 1)
	218 0 (3, 1)
	220 ifne (3, 1)
	221 32 (3, 1)
	223 aload_0 (3, 1)
	224 iconst_1 (3, 1)
	225 putfield (3, 1)
	226 org/apache/commons/math3/geometry/partitioning/InsideFinder.plusFound:Z (3, 1)
	228 goto (3, 1)
	229 24 (3, 1)
	231 aload_0 (3, 1)
	232 getfield (3, 1)
	233 org/apache/commons/math3/geometry/partitioning/InsideFinder.region:Lorg/apache/commons/math3/geometry/partitioning/Region; (3, 1)
	235 aload_1 (3, 1)
	236 invokevirtual (3, 1)
	237 org/apache/commons/math3/geometry/partitioning/BSPTree.getPlus:()Lorg/apache/commons/math3/geometry/partitioning/BSPTree; (3, 1)
	239 invokeinterface (3, 1)
	240 org/apache/commons/math3/geometry/partitioning/Region.getPlus:()Lorg/apache/commons/math3/geometry/partitioning/BSPTree; (3, 1)
	242 0 (3, 1)
	244 ifne (3, 1)
	245 8 (3, 1)
	247 aload_0 (3, 1)
	248 iconst_1 (3, 1)
	249 putfield (3, 1)
	250 org/apache/commons/math3/geometry/partitioning/InsideFinder.minusFound:Z (3, 1)
	252 aload_0 (2, 1)
	253 getfield (2, 1)
	254 org/apache/commons/math3/geometry/partitioning/InsideFinder.plusFound:Z (2, 1)
	256 ifeq (2, 1)
	257 10 (2, 1)
	259 aload_0 (2, 1)
	260 getfield (2, 1)
	261 org/apache/commons/math3/geometry/partitioning/InsideFinder.minusFound:Z (2, 1)
	263 ifne (2, 1)
	264 208 (2, 1)
	266 aload_0 (2, 1)
	267 aload_1 (2, 1)
	268 invokevirtual (2, 1)
	269 org/apache/commons/math3/geometry/partitioning/BSPTree.getMinus:()Lorg/apache/commons/math3/geometry/partitioning/BSPTree; (2, 1)
	271 aload_2 (2, 1)
	272 invokevirtual (2, 1)
	273 org/apache/commons/math3/geometry/partitioning/InsideFinder.recurseSides:(Lorg/apache/commons/math3/geometry/partitioning/BSPTree;Lorg/apache/commons/math3/geometry/partitioning/SubHyperplane;)V (2, 1)
	275 goto (2, 1)
	276 196 (2, 1)
	278 aload_0 (1, 5)
	279 aload_1 (1, 5)
	280 invokevirtual (1, 5)
	281 org/apache/commons/math3/geometry/partitioning/BSPTree.getPlus:()Lorg/apache/commons/math3/geometry/partitioning/BSPTree; (1, 5)
	283 aload (1, 5)
	284 #4 (1, 5)
	285 invokevirtual (1, 5)
	286 org/apache/commons/math3/geometry/partitioning/SubHyperplane$SplitSubHyperplane.getPlus:()Lorg/apache/commons/math3/geometry/partitioning/SubHyperplane; (1, 5)
	288 invokevirtual (1, 5)
	289 org/apache/commons/math3/geometry/partitioning/InsideFinder.recurseSides:(Lorg/apache/commons/math3/geometry/partitioning/BSPTree;Lorg/apache/commons/math3/geometry/partitioning/SubHyperplane;)V (1, 5)
	291 aload_0 (2, 1)
	292 getfield (2, 1)
	293 org/apache/commons/math3/geometry/partitioning/InsideFinder.plusFound:Z (2, 1)
	295 ifeq (2, 1)
	296 10 (2, 1)
	298 aload_0 (2, 1)
	299 getfield (2, 1)
	300 org/apache/commons/math3/geometry/partitioning/InsideFinder.minusFound:Z (2, 1)
	302 ifne (2, 1)
	303 169 (2, 1)
	305 aload_0 (2, 1)
	306 aload_1 (2, 1)
	307 invokevirtual (2, 1)
	308 org/apache/commons/math3/geometry/partitioning/BSPTree.getMinus:()Lorg/apache/commons/math3/geometry/partitioning/BSPTree; (2, 1)
	310 aload (2, 1)
	311 #4 (2, 1)
	312 invokevirtual (2, 1)
	313 org/apache/commons/math3/geometry/partitioning/SubHyperplane$SplitSubHyperplane.getMinus:()Lorg/apache/commons/math3/geometry/partitioning/SubHyperplane; (2, 1)
	315 invokevirtual (2, 1)
	316 org/apache/commons/math3/geometry/partitioning/InsideFinder.recurseSides:(Lorg/apache/commons/math3/geometry/partitioning/BSPTree;Lorg/apache/commons/math3/geometry/partitioning/SubHyperplane;)V (2, 1)
	318 goto (2, 1)
	319 153 (2, 1)
	321 aload_1 (2, 1)
	322 invokevirtual (2, 1)
	323 org/apache/commons/math3/geometry/partitioning/BSPTree.getCut:()Lorg/apache/commons/math3/geometry/partitioning/SubHyperplane; (2, 1)
	325 invokeinterface (2, 1)
	326 org/apache/commons/math3/geometry/partitioning/SubHyperplane.split:(Lorg/apache/commons/math3/geometry/partitioning/Hyperplane;)Lorg/apache/commons/math3/geometry/partitioning/SubHyperplane$SplitSubHyperplane; (2, 1)
	328 0 (2, 1)
	330 aload_2 (2, 1)
	331 invokeinterface (2, 1)
	332 org/apache/commons/math3/geometry/partitioning/SubHyperplane.split:(Lorg/apache/commons/math3/geometry/partitioning/Hyperplane;)Lorg/apache/commons/math3/geometry/partitioning/SubHyperplane$SplitSubHyperplane; (2, 1)
	334 0 (2, 1)
	336 invokeinterface (2, 1)
	337 org/apache/commons/math3/geometry/partitioning/Hyperplane.org/apache/commons/math3/geometry/partitioning/InsideFinder (2, 1)
	339 0 (2, 1)
	341 ifeq (2, 1)
	342 68 (2, 1)
	344 aload_1 (3, 1)
	345 invokevirtual (3, 1)
	346 org/apache/commons/math3/geometry/partitioning/BSPTree.getPlus:()Lorg/apache/commons/math3/geometry/partitioning/BSPTree; (3, 1)
	348 invokevirtual (3, 1)
	349 org/apache/commons/math3/geometry/partitioning/BSPTree.getCut:()Lorg/apache/commons/math3/geometry/partitioning/SubHyperplane; (3, 1)
	351 ifnonnull (3, 1)
	352 19 (3, 1)
	354 aload_1 (3, 1)
	355 invokevirtual (3, 1)
	356 org/apache/commons/math3/geometry/partitioning/BSPTree.getPlus:()Lorg/apache/commons/math3/geometry/partitioning/BSPTree; (3, 1)
	358 invokevirtual (3, 1)
	359 org/apache/commons/math3/geometry/partitioning/BSPTree.getAttribute:()Ljava/lang/Object; (3, 1)
	361 checkcast (3, 1)
	362 java/lang/Boolean (3, 1)
	364 invokevirtual (3, 1)
	365 java/lang/Boolean.booleanValue:()Z (3, 1)
	367 ifeq (3, 1)
	368 8 (3, 1)
	370 aload_0 (3, 1)
	371 iconst_1 (3, 1)
	372 putfield (3, 1)
	373 org/apache/commons/math3/geometry/partitioning/InsideFinder.plusFound:Z (3, 1)
	375 aload_1 (3, 1)
	376 invokevirtual (3, 1)
	377 org/apache/commons/math3/geometry/partitioning/BSPTree.getMinus:()Lorg/apache/commons/math3/geometry/partitioning/BSPTree; (3, 1)
	379 invokevirtual (3, 1)
	380 org/apache/commons/math3/geometry/partitioning/BSPTree.getCut:()Lorg/apache/commons/math3/geometry/partitioning/SubHyperplane; (3, 1)
	382 ifnonnull (3, 1)
	383 19 (3, 1)
	385 aload_1 (3, 1)
	386 invokevirtual (3, 1)
	387 org/apache/commons/math3/geometry/partitioning/BSPTree.getMinus:()Lorg/apache/commons/math3/geometry/partitioning/BSPTree; (3, 1)
	389 invokevirtual (3, 1)
	390 org/apache/commons/math3/geometry/partitioning/BSPTree.getAttribute:()Ljava/lang/Object; (3, 1)
	392 checkcast (3, 1)
	393 java/lang/Boolean (3, 1)
	395 invokevirtual (3, 1)
	396 java/lang/Boolean.booleanValue:()Z (3, 1)
	398 ifeq (3, 1)
	399 73 (3, 1)
	401 aload_0 (3, 1)
	402 iconst_1 (3, 1)
	403 putfield (3, 1)
	404 org/apache/commons/math3/geometry/partitioning/InsideFinder.minusFound:Z (3, 1)
	406 goto (3, 1)
	407 65 (3, 1)
	409 aload_1 (3, 1)
	410 invokevirtual (3, 1)
	411 org/apache/commons/math3/geometry/partitioning/BSPTree.getPlus:()Lorg/apache/commons/math3/geometry/partitioning/BSPTree; (3, 1)
	413 invokevirtual (3, 1)
	414 org/apache/commons/math3/geometry/partitioning/BSPTree.getCut:()Lorg/apache/commons/math3/geometry/partitioning/SubHyperplane; (3, 1)
	416 ifnonnull (3, 1)
	417 19 (3, 1)
	419 aload_1 (3, 1)
	420 invokevirtual (3, 1)
	421 org/apache/commons/math3/geometry/partitioning/BSPTree.getPlus:()Lorg/apache/commons/math3/geometry/partitioning/BSPTree; (3, 1)
	423 invokevirtual (3, 1)
	424 org/apache/commons/math3/geometry/partitioning/BSPTree.getAttribute:()Ljava/lang/Object; (3, 1)
	426 checkcast (3, 1)
	427 java/lang/Boolean (3, 1)
	429 invokevirtual (3, 1)
	430 java/lang/Boolean.booleanValue:()Z (3, 1)
	432 ifeq (3, 1)
	433 8 (3, 1)
	435 aload_0 (3, 1)
	436 iconst_1 (3, 1)
	437 putfield (3, 1)
	438 org/apache/commons/math3/geometry/partitioning/InsideFinder.minusFound:Z (3, 1)
	440 aload_1 (3, 1)
	441 invokevirtual (3, 1)
	442 org/apache/commons/math3/geometry/partitioning/BSPTree.getMinus:()Lorg/apache/commons/math3/geometry/partitioning/BSPTree; (3, 1)
	444 invokevirtual (3, 1)
	445 org/apache/commons/math3/geometry/partitioning/BSPTree.getCut:()Lorg/apache/commons/math3/geometry/partitioning/SubHyperplane; (3, 1)
	447 ifnonnull (3, 1)
	448 19 (3, 1)
	450 aload_1 (3, 1)
	451 invokevirtual (3, 1)
	452 org/apache/commons/math3/geometry/partitioning/BSPTree.getMinus:()Lorg/apache/commons/math3/geometry/partitioning/BSPTree; (3, 1)
	454 invokevirtual (3, 1)
	455 org/apache/commons/math3/geometry/partitioning/BSPTree.getAttribute:()Ljava/lang/Object; (3, 1)
	457 checkcast (3, 1)
	458 java/lang/Boolean (3, 1)
	460 invokevirtual (3, 1)
	461 java/lang/Boolean.booleanValue:()Z (3, 1)
	463 ifeq (3, 1)
	464 8 (3, 1)
	466 aload_0 (3, 1)
	467 iconst_1 (3, 1)
	468 putfield (3, 1)
	469 org/apache/commons/math3/geometry/partitioning/InsideFinder.plusFound:Z (3, 1)
	471 return (0, 0)

Method: plusFound
	0 aload_0 (0, 0)
	1 getfield (0, 0)
	2 org/apache/commons/math3/geometry/partitioning/InsideFinder.plusFound:Z (0, 0)
	4 ireturn (0, 0)

Method: minusFound
	0 aload_0 (0, 0)
	1 getfield (0, 0)
	2 org/apache/commons/math3/geometry/partitioning/InsideFinder.minusFound:Z (0, 0)
	4 ireturn (0, 0)

