Method: <init>
	0 aload_0 (0, 0)
	1 aload_1 (0, 0)
	2 putfield (0, 0)
	3 org/apache/commons/math3/geometry/partitioning/RegionFactory$VanishingToLeaf.this$0:Lorg/apache/commons/math3/geometry/partitioning/RegionFactory; (0, 0)
	5 aload_0 (0, 0)
	6 invokespecial (0, 0)
	7 java/lang/Object.<init>:()V (0, 0)
	9 aload_0 (0, 0)
	10 iload_2 (0, 0)
	11 putfield (0, 0)
	12 org/apache/commons/math3/geometry/partitioning/RegionFactory$VanishingToLeaf.inside:Z (0, 0)
	14 return (0, 0)

Method: fixNode
	0 aload_1 (1, 1)
	1 invokevirtual (1, 1)
	2 org/apache/commons/math3/geometry/partitioning/BSPTree.getPlus:()Lorg/apache/commons/math3/geometry/partitioning/BSPTree; (1, 1)
	4 invokevirtual (1, 1)
	5 org/apache/commons/math3/geometry/partitioning/BSPTree.getAttribute:()Ljava/lang/Object; (1, 1)
	7 aload_1 (1, 1)
	8 invokevirtual (1, 1)
	9 org/apache/commons/math3/geometry/partitioning/BSPTree.getMinus:()Lorg/apache/commons/math3/geometry/partitioning/BSPTree; (1, 1)
	11 invokevirtual (1, 1)
	12 org/apache/commons/math3/geometry/partitioning/BSPTree.getAttribute:()Ljava/lang/Object; (1, 1)
	14 invokevirtual (1, 1)
	15 java/lang/Object.equals:(Ljava/lang/Object;)Z (1, 1)
	17 ifeq (1, 1)
	18 18 (1, 1)
	20 new (1, 1)
	21 org/apache/commons/math3/geometry/partitioning/BSPTree (1, 1)
	23 dup (1, 1)
	24 aload_1 (1, 1)
	25 invokevirtual (1, 1)
	26 org/apache/commons/math3/geometry/partitioning/BSPTree.getPlus:()Lorg/apache/commons/math3/geometry/partitioning/BSPTree; (1, 1)
	28 invokevirtual (1, 1)
	29 org/apache/commons/math3/geometry/partitioning/BSPTree.getAttribute:()Ljava/lang/Object; (1, 1)
	31 invokespecial (1, 1)
	32 org/apache/commons/math3/geometry/partitioning/BSPTree.<init>:(Ljava/lang/Object;)V (1, 1)
	34 areturn (1, 1)
	35 new (2, 2)
	36 org/apache/commons/math3/geometry/partitioning/BSPTree (2, 2)
	38 dup (2, 2)
	39 aload_0 (2, 2)
	40 getfield (2, 2)
	41 org/apache/commons/math3/geometry/partitioning/RegionFactory$VanishingToLeaf.inside:Z (2, 2)
	43 invokestatic (2, 2)
	44 java/lang/Boolean.valueOf:(Z)Ljava/lang/Boolean; (2, 2)
	46 invokespecial (2, 2)
	47 org/apache/commons/math3/geometry/partitioning/BSPTree.<init>:(Ljava/lang/Object;)V (2, 2)
	49 areturn (1, 2)

