Method: merge
	0 aload_1 (1, 1)
	1 invokevirtual (1, 1)
	4 checkcast (1, 1)
	7 invokevirtual (1, 1)
	10 ifeq (1, 1)
	13 aload_2 (1, 1)
	14 aload_3 (1, 1)
	15 iload (1, 1)
	17 new (1, 1)
	20 dup (1, 1)
	21 aload_0 (1, 1)
	22 getfield (1, 1)
	25 iconst_1 (1, 1)
	26 invokespecial (1, 1)
	29 invokevirtual (1, 1)
	32 aload_2 (1, 1)
	33 areturn (1, 1)
	34 aload_1 (0, 0)
	35 aload_3 (0, 0)
	36 iload (0, 0)
	38 new (0, 0)
	41 dup (0, 0)
	42 aload_0 (0, 0)
	43 getfield (0, 0)
	46 iconst_0 (0, 0)
	47 invokespecial (0, 0)
	50 invokevirtual (0, 0)
	53 aload_1 (0, 0)
	54 areturn (0, 0)

