Method: <init>
	0 aload_0 (0, 0)
	1 invokespecial (0, 0)
	2 java/lang/Object.<init>:()V (0, 0)
	4 aload_0 (0, 0)
	5 new (0, 0)
	6 org/apache/commons/math3/geometry/partitioning/RegionFactory$NodesCleaner (0, 0)
	8 dup (0, 0)
	9 aload_0 (0, 0)
	10 aconst_null (0, 0)
	11 invokespecial (0, 0)
	12 org/apache/commons/math3/geometry/partitioning/RegionFactory$NodesCleaner.<init>:(Lorg/apache/commons/math3/geometry/partitioning/RegionFactory;Lorg/apache/commons/math3/geometry/partitioning/RegionFactory$1;)V (0, 0)
	14 putfield (0, 0)
	15 org/apache/commons/math3/geometry/partitioning/RegionFactory.nodeCleaner:Lorg/apache/commons/math3/geometry/partitioning/RegionFactory$NodesCleaner; (0, 0)
	17 return (0, 0)

Method: buildConvex
	0 aload_1 (1, 1)
	1 ifnull (1, 1)
	2 8 (1, 1)
	4 aload_1 (1, 1)
	5 arraylength (1, 1)
	6 ifne (1, 1)
	7 5 (1, 1)
	9 aconst_null (1, 1)
	10 areturn (1, 1)
	11 aload_1 (0, 0)
	12 iconst_0 (0, 0)
	13 aaload (0, 0)
	14 invokeinterface (0, 0)
	15 org/apache/commons/math3/geometry/partitioning/Hyperplane.org/apache/commons/math3/geometry/partitioning/Region (0, 0)
	17 0 (0, 0)
	19 astore_2 (0, 0)
	20 aload_2 (0, 0)
	21 iconst_0 (0, 0)
	22 invokeinterface (0, 0)
	23 org/apache/commons/math3/geometry/partitioning/Region.TRUE:Ljava/lang/Boolean; (0, 0)
	25 0 (0, 0)
	27 astore_3 (0, 0)
	28 aload_3 (0, 0)
	29 getstatic (0, 0)
	30 java/lang/Boolean.TRUE:Ljava/lang/Boolean; (0, 0)
	32 invokevirtual (0, 0)
	33 org/apache/commons/math3/geometry/partitioning/BSPTree.setAttribute:(Ljava/lang/Object;)V (0, 0)
	35 aload_1 (1, 4)
	36 astore (1, 4)
	37 #4 (1, 4)
	38 aload (1, 4)
	39 #4 (1, 4)
	40 arraylength (1, 4)
	41 istore (1, 4)
	42 #5 (1, 4)
	43 iconst_0 (1, 4)
	44 istore (1, 4)
	45 #6 (1, 4)
	46 iload (1, 4)
	47 #6 (1, 4)
	48 iload (1, 4)
	49 #5 (1, 4)
	50 if_icmpge (1, 4)
	51 201 (1, 4)
	53 aload (1, 4)
	54 #4 (1, 4)
	55 iload (1, 4)
	56 #6 (1, 4)
	57 aaload (1, 4)
	58 astore (1, 4)
	59 #7 (1, 4)
	60 aload_3 (2, 1)
	61 aload (2, 1)
	62 #7 (2, 1)
	63 invokevirtual (2, 1)
	64 org/apache/commons/math3/geometry/partitioning/BSPTree.insertCut:(Lorg/apache/commons/math3/geometry/partitioning/Hyperplane;)Z (2, 1)
	66 ifeq (2, 1)
	67 33 (2, 1)
	69 aload_3 (2, 1)
	70 aconst_null (2, 1)
	71 invokevirtual (2, 1)
	72 org/apache/commons/math3/geometry/partitioning/BSPTree.setAttribute:(Ljava/lang/Object;)V (2, 1)
	74 aload_3 (2, 1)
	75 invokevirtual (2, 1)
	76 org/apache/commons/math3/geometry/partitioning/BSPTree.getPlus:()Lorg/apache/commons/math3/geometry/partitioning/BSPTree; (2, 1)
	78 getstatic (2, 1)
	79 java/lang/Boolean.FALSE:Ljava/lang/Boolean; (2, 1)
	81 invokevirtual (2, 1)
	82 org/apache/commons/math3/geometry/partitioning/BSPTree.setAttribute:(Ljava/lang/Object;)V (2, 1)
	84 aload_3 (2, 1)
	85 invokevirtual (2, 1)
	86 org/apache/commons/math3/geometry/partitioning/BSPTree.getMinus:()Lorg/apache/commons/math3/geometry/partitioning/BSPTree; (2, 1)
	88 astore_3 (2, 1)
	89 aload_3 (2, 1)
	90 getstatic (2, 1)
	91 java/lang/Boolean.TRUE:Ljava/lang/Boolean; (2, 1)
	93 invokevirtual (2, 1)
	94 org/apache/commons/math3/geometry/partitioning/BSPTree.setAttribute:(Ljava/lang/Object;)V (2, 1)
	96 goto (2, 1)
	97 149 (2, 1)
	99 aload (3, 2)
	100 #7 (3, 2)
	101 invokeinterface (3, 2)
	102 org/apache/commons/math3/geometry/partitioning/Hyperplane.getParent:()Lorg/apache/commons/math3/geometry/partitioning/BSPTree; (3, 2)
	104 0 (3, 2)
	106 astore (3, 2)
	107 #8 (3, 2)
	108 aload_3 (4, 4)
	109 astore (4, 4)
	110 #9 (4, 4)
	111 aload (4, 4)
	112 #9 (4, 4)
	113 invokevirtual (4, 4)
	114 org/apache/commons/math3/geometry/partitioning/BSPTree.getParent:()Lorg/apache/commons/math3/geometry/partitioning/BSPTree; (4, 4)
	116 ifnull (4, 4)
	117 129 (4, 4)
	119 aload (4, 4)
	120 #8 (4, 4)
	121 ifnull (4, 4)
	122 124 (4, 4)
	124 aload (4, 4)
	125 #9 (4, 4)
	126 invokevirtual (4, 4)
	127 org/apache/commons/math3/geometry/partitioning/BSPTree.getParent:()Lorg/apache/commons/math3/geometry/partitioning/BSPTree; (4, 4)
	129 invokevirtual (4, 4)
	130 org/apache/commons/math3/geometry/partitioning/BSPTree.getCut:()Lorg/apache/commons/math3/geometry/partitioning/SubHyperplane; (4, 4)
	132 invokeinterface (4, 4)
	133 org/apache/commons/math3/geometry/partitioning/SubHyperplane.split:(Lorg/apache/commons/math3/geometry/partitioning/Hyperplane;)Lorg/apache/commons/math3/geometry/partitioning/SubHyperplane$SplitSubHyperplane; (4, 4)
	135 0 (4, 4)
	137 astore (4, 4)
	138 #10 (4, 4)
	139 aload (4, 4)
	140 #8 (4, 4)
	141 aload (4, 4)
	142 #10 (4, 4)
	143 invokeinterface (4, 4)
	144 org/apache/commons/math3/geometry/partitioning/SubHyperplane.$SwitchMap$org$apache$commons$math3$geometry$partitioning$Side:[I (4, 4)
	146 0 (4, 4)
	148 astore (4, 4)
	149 #11 (4, 4)
	150 getstatic (5, 5)
	151 org/apache/commons/math3/geometry/partitioning/RegionFactory$1.$SwitchMap$org$apache$commons$math3$geometry$partitioning$Side:[I (5, 5)
	153 aload (5, 5)
	154 #11 (5, 5)
	155 invokevirtual (5, 5)
	156 org/apache/commons/math3/geometry/partitioning/SubHyperplane$SplitSubHyperplane.getSide:()Lorg/apache/commons/math3/geometry/partitioning/Side; (5, 5)
	158 invokevirtual (5, 5)
	159 org/apache/commons/math3/geometry/partitioning/Side.ordinal:()I (5, 5)
	161 iaload (5, 5)
	162 lookupswitch (5, 5)
	163 1: 188 (5, 5)
	167 2: 213 (5, 5)
	188 aload (6, 1)
	189 #7 (6, 1)
	190 aload (6, 1)
	191 #10 (6, 1)
	192 invokeinterface (6, 1)
	193 org/apache/commons/math3/geometry/partitioning/Hyperplane.getComplement:(Lorg/apache/commons/math3/geometry/partitioning/Region;)Lorg/apache/commons/math3/geometry/partitioning/Region; (6, 1)
	195 0 (6, 1)
	197 ifne (6, 1)
	198 38 (6, 1)
	200 aload_0 (6, 1)
	201 aload_1 (6, 1)
	202 iconst_0 (6, 1)
	203 aaload (6, 1)
	204 invokeinterface (6, 1)
	205 org/apache/commons/math3/geometry/partitioning/Hyperplane.org/apache/commons/math3/geometry/partitioning/Region (6, 1)
	207 0 (6, 1)
	209 invokevirtual (6, 1)
	210 org/apache/commons/math3/geometry/partitioning/RegionFactory.getComplement:(Lorg/apache/commons/math3/geometry/partitioning/Region;)Lorg/apache/commons/math3/geometry/partitioning/Region; (6, 1)
	212 areturn (6, 1)
	213 new (5, 5)
	214 org/apache/commons/math3/exception/MathIllegalArgumentException (5, 5)
	216 dup (5, 5)
	217 getstatic (5, 5)
	218 org/apache/commons/math3/exception/util/LocalizedFormats.NOT_CONVEX_HYPERPLANES:Lorg/apache/commons/math3/exception/util/LocalizedFormats; (5, 5)
	220 iconst_0 (5, 5)
	221 anewarray (5, 5)
	222 java/lang/Object (5, 5)
	224 invokespecial (5, 5)
	225 org/apache/commons/math3/exception/MathIllegalArgumentException.<init>:(Lorg/apache/commons/math3/exception/util/Localizable;[Ljava/lang/Object;)V (5, 5)
	227 athrow (5, 5)
	228 aload (5, 5)
	229 #11 (5, 5)
	230 invokevirtual (5, 5)
	231 org/apache/commons/math3/geometry/partitioning/SubHyperplane$SplitSubHyperplane.getMinus:()Lorg/apache/commons/math3/geometry/partitioning/SubHyperplane; (5, 5)
	233 astore (5, 5)
	234 #8 (5, 5)
	235 aload (5, 5)
	236 #9 (5, 5)
	237 invokevirtual (5, 5)
	238 org/apache/commons/math3/geometry/partitioning/BSPTree.getParent:()Lorg/apache/commons/math3/geometry/partitioning/BSPTree; (5, 5)
	240 astore (5, 5)
	241 #9 (5, 5)
	242 goto (5, 5)
	243 -131 (5, 5)
	245 iinc (5, 5)
	246 #6 (5, 5)
	247 -89 (5, 5)
	248 goto (5, 5)
	249 -202 (5, 5)
	251 aload_2 (4, 4)
	252 areturn (3, 4)

Method: union
	0 aload_1 (0, 0)
	1 iconst_0 (0, 0)
	2 invokeinterface (0, 0)
	3 org/apache/commons/math3/geometry/partitioning/Region.TRUE:Ljava/lang/Boolean; (0, 0)
	5 0 (0, 0)
	7 aload_2 (0, 0)
	8 iconst_0 (0, 0)
	9 invokeinterface (0, 0)
	10 org/apache/commons/math3/geometry/partitioning/Region.TRUE:Ljava/lang/Boolean; (0, 0)
	12 0 (0, 0)
	14 new (0, 0)
	15 org/apache/commons/math3/geometry/partitioning/RegionFactory$UnionMerger (0, 0)
	17 dup (0, 0)
	18 aload_0 (0, 0)
	19 aconst_null (0, 0)
	20 invokespecial (0, 0)
	21 org/apache/commons/math3/geometry/partitioning/RegionFactory$UnionMerger.<init>:(Lorg/apache/commons/math3/geometry/partitioning/RegionFactory;Lorg/apache/commons/math3/geometry/partitioning/RegionFactory$1;)V (0, 0)
	23 invokevirtual (0, 0)
	24 org/apache/commons/math3/geometry/partitioning/BSPTree.merge:(Lorg/apache/commons/math3/geometry/partitioning/BSPTree;Lorg/apache/commons/math3/geometry/partitioning/BSPTree$LeafMerger;)Lorg/apache/commons/math3/geometry/partitioning/BSPTree; (0, 0)
	26 astore_3 (0, 0)
	27 aload_3 (0, 0)
	28 aload_0 (0, 0)
	29 getfield (0, 0)
	30 org/apache/commons/math3/geometry/partitioning/RegionFactory.nodeCleaner:Lorg/apache/commons/math3/geometry/partitioning/RegionFactory$NodesCleaner; (0, 0)
	32 invokevirtual (0, 0)
	33 org/apache/commons/math3/geometry/partitioning/BSPTree.visit:(Lorg/apache/commons/math3/geometry/partitioning/BSPTreeVisitor;)V (0, 0)
	35 aload_1 (0, 0)
	36 aload_3 (0, 0)
	37 invokeinterface (0, 0)
	38 org/apache/commons/math3/geometry/partitioning/Region.org/apache/commons/math3/geometry/partitioning/RegionFactory$IntersectionMerger (0, 0)
	40 0 (0, 0)
	42 areturn (0, 0)

Method: intersection
	0 aload_1 (0, 0)
	1 iconst_0 (0, 0)
	2 invokeinterface (0, 0)
	3 org/apache/commons/math3/geometry/partitioning/Region.TRUE:Ljava/lang/Boolean; (0, 0)
	5 0 (0, 0)
	7 aload_2 (0, 0)
	8 iconst_0 (0, 0)
	9 invokeinterface (0, 0)
	10 org/apache/commons/math3/geometry/partitioning/Region.TRUE:Ljava/lang/Boolean; (0, 0)
	12 0 (0, 0)
	14 new (0, 0)
	15 org/apache/commons/math3/geometry/partitioning/RegionFactory$IntersectionMerger (0, 0)
	17 dup (0, 0)
	18 aload_0 (0, 0)
	19 aconst_null (0, 0)
	20 invokespecial (0, 0)
	21 org/apache/commons/math3/geometry/partitioning/RegionFactory$IntersectionMerger.<init>:(Lorg/apache/commons/math3/geometry/partitioning/RegionFactory;Lorg/apache/commons/math3/geometry/partitioning/RegionFactory$1;)V (0, 0)
	23 invokevirtual (0, 0)
	24 org/apache/commons/math3/geometry/partitioning/BSPTree.merge:(Lorg/apache/commons/math3/geometry/partitioning/BSPTree;Lorg/apache/commons/math3/geometry/partitioning/BSPTree$LeafMerger;)Lorg/apache/commons/math3/geometry/partitioning/BSPTree; (0, 0)
	26 astore_3 (0, 0)
	27 aload_3 (0, 0)
	28 aload_0 (0, 0)
	29 getfield (0, 0)
	30 org/apache/commons/math3/geometry/partitioning/RegionFactory.nodeCleaner:Lorg/apache/commons/math3/geometry/partitioning/RegionFactory$NodesCleaner; (0, 0)
	32 invokevirtual (0, 0)
	33 org/apache/commons/math3/geometry/partitioning/BSPTree.visit:(Lorg/apache/commons/math3/geometry/partitioning/BSPTreeVisitor;)V (0, 0)
	35 aload_1 (0, 0)
	36 aload_3 (0, 0)
	37 invokeinterface (0, 0)
	38 org/apache/commons/math3/geometry/partitioning/Region.org/apache/commons/math3/geometry/partitioning/RegionFactory$IntersectionMerger (0, 0)
	40 0 (0, 0)
	42 areturn (0, 0)

Method: xor
	0 aload_1 (0, 0)
	1 iconst_0 (0, 0)
	2 invokeinterface (0, 0)
	3 org/apache/commons/math3/geometry/partitioning/Region.TRUE:Ljava/lang/Boolean; (0, 0)
	5 0 (0, 0)
	7 aload_2 (0, 0)
	8 iconst_0 (0, 0)
	9 invokeinterface (0, 0)
	10 org/apache/commons/math3/geometry/partitioning/Region.TRUE:Ljava/lang/Boolean; (0, 0)
	12 0 (0, 0)
	14 new (0, 0)
	15 org/apache/commons/math3/geometry/partitioning/RegionFactory$XorMerger (0, 0)
	17 dup (0, 0)
	18 aload_0 (0, 0)
	19 aconst_null (0, 0)
	20 invokespecial (0, 0)
	21 org/apache/commons/math3/geometry/partitioning/RegionFactory$XorMerger.<init>:(Lorg/apache/commons/math3/geometry/partitioning/RegionFactory;Lorg/apache/commons/math3/geometry/partitioning/RegionFactory$1;)V (0, 0)
	23 invokevirtual (0, 0)
	24 org/apache/commons/math3/geometry/partitioning/BSPTree.merge:(Lorg/apache/commons/math3/geometry/partitioning/BSPTree;Lorg/apache/commons/math3/geometry/partitioning/BSPTree$LeafMerger;)Lorg/apache/commons/math3/geometry/partitioning/BSPTree; (0, 0)
	26 astore_3 (0, 0)
	27 aload_3 (0, 0)
	28 aload_0 (0, 0)
	29 getfield (0, 0)
	30 org/apache/commons/math3/geometry/partitioning/RegionFactory.nodeCleaner:Lorg/apache/commons/math3/geometry/partitioning/RegionFactory$NodesCleaner; (0, 0)
	32 invokevirtual (0, 0)
	33 org/apache/commons/math3/geometry/partitioning/BSPTree.visit:(Lorg/apache/commons/math3/geometry/partitioning/BSPTreeVisitor;)V (0, 0)
	35 aload_1 (0, 0)
	36 aload_3 (0, 0)
	37 invokeinterface (0, 0)
	38 org/apache/commons/math3/geometry/partitioning/Region.org/apache/commons/math3/geometry/partitioning/RegionFactory$IntersectionMerger (0, 0)
	40 0 (0, 0)
	42 areturn (0, 0)

Method: difference
	0 aload_1 (0, 0)
	1 iconst_0 (0, 0)
	2 invokeinterface (1, 1)
	3 org/apache/commons/math3/geometry/partitioning/Region.TRUE:Ljava/lang/Boolean; (1, 1)
	5 0 (1, 1)
	7 aload_2 (1, 1)
	8 iconst_0 (1, 1)
	9 invokeinterface (1, 1)
	10 org/apache/commons/math3/geometry/partitioning/Region.TRUE:Ljava/lang/Boolean; (1, 1)
	12 0 (1, 1)
	14 new (1, 1)
	15 org/apache/commons/math3/geometry/partitioning/RegionFactory$DifferenceMerger (1, 1)
	17 dup (1, 1)
	18 aload_0 (1, 1)
	19 aload_1 (1, 1)
	20 aload_2 (1, 1)
	21 invokespecial (1, 1)
	22 org/apache/commons/math3/geometry/partitioning/RegionFactory$DifferenceMerger.<init>:(Lorg/apache/commons/math3/geometry/partitioning/RegionFactory;Lorg/apache/commons/math3/geometry/partitioning/Region;Lorg/apache/commons/math3/geometry/partitioning/Region;)V (1, 1)
	24 invokevirtual (1, 1)
	25 org/apache/commons/math3/geometry/partitioning/BSPTree.merge:(Lorg/apache/commons/math3/geometry/partitioning/BSPTree;Lorg/apache/commons/math3/geometry/partitioning/BSPTree$LeafMerger;)Lorg/apache/commons/math3/geometry/partitioning/BSPTree; (1, 1)
	27 astore_3 (1, 1)
	28 aload_3 (1, 1)
	29 aload_0 (1, 1)
	30 getfield (1, 1)
	31 org/apache/commons/math3/geometry/partitioning/RegionFactory.nodeCleaner:Lorg/apache/commons/math3/geometry/partitioning/RegionFactory$NodesCleaner; (1, 1)
	33 invokevirtual (1, 1)
	34 org/apache/commons/math3/geometry/partitioning/BSPTree.visit:(Lorg/apache/commons/math3/geometry/partitioning/BSPTreeVisitor;)V (1, 1)
	36 aload_1 (1, 1)
	37 aload_3 (1, 1)
	38 invokeinterface (1, 1)
	39 org/apache/commons/math3/geometry/partitioning/Region.org/apache/commons/math3/geometry/partitioning/RegionFactory$IntersectionMerger (1, 1)
	41 0 (1, 1)
	43 areturn (0, 1)

Method: getComplement
	0 aload_1 (0, 0)
	1 aload_0 (0, 0)
	2 aload_1 (0, 0)
	3 iconst_0 (0, 0)
	4 invokeinterface (0, 0)
	5 org/apache/commons/math3/geometry/partitioning/Region.TRUE:Ljava/lang/Boolean; (0, 0)
	7 0 (0, 0)
	9 invokespecial (0, 0)
	10 org/apache/commons/math3/geometry/partitioning/RegionFactory.recurseComplement:(Lorg/apache/commons/math3/geometry/partitioning/BSPTree;)Lorg/apache/commons/math3/geometry/partitioning/BSPTree; (0, 0)
	12 invokeinterface (0, 0)
	13 org/apache/commons/math3/geometry/partitioning/Region.org/apache/commons/math3/geometry/partitioning/RegionFactory$IntersectionMerger (0, 0)
	15 0 (0, 0)
	17 areturn (0, 0)

Method: recurseComplement
	0 aload_1 (1, 1)
	1 invokevirtual (1, 1)
	2 org/apache/commons/math3/geometry/partitioning/BSPTree.getCut:()Lorg/apache/commons/math3/geometry/partitioning/SubHyperplane; (1, 1)
	4 ifnonnull (1, 1)
	5 36 (1, 1)
	7 new (2, 4)
	8 org/apache/commons/math3/geometry/partitioning/BSPTree (2, 4)
	10 dup (2, 4)
	11 aload_1 (2, 4)
	12 invokevirtual (2, 4)
	13 org/apache/commons/math3/geometry/partitioning/BSPTree.getAttribute:()Ljava/lang/Object; (2, 4)
	15 checkcast (2, 4)
	16 java/lang/Boolean (2, 4)
	18 invokevirtual (2, 4)
	19 java/lang/Boolean.booleanValue:()Z (2, 4)
	21 ifeq (2, 4)
	22 9 (2, 4)
	24 getstatic (2, 4)
	25 java/lang/Boolean.FALSE:Ljava/lang/Boolean; (2, 4)
	27 goto (2, 4)
	28 6 (2, 4)
	30 getstatic (2, 4)
	31 java/lang/Boolean.TRUE:Ljava/lang/Boolean; (2, 4)
	33 invokespecial (2, 4)
	34 org/apache/commons/math3/geometry/partitioning/BSPTree.<init>:(Ljava/lang/Object;)V (2, 4)
	36 astore_3 (2, 4)
	37 goto (2, 4)
	38 122 (2, 4)
	40 aload_1 (3, 2)
	41 invokevirtual (3, 2)
	42 org/apache/commons/math3/geometry/partitioning/BSPTree.getAttribute:()Ljava/lang/Object; (3, 2)
	44 checkcast (3, 2)
	45 org/apache/commons/math3/geometry/partitioning/BoundaryAttribute (3, 2)
	47 astore (3, 2)
	48 #4 (3, 2)
	49 aload (4, 1)
	50 #4 (4, 1)
	51 ifnull (4, 1)
	52 71 (4, 1)
	54 aload (4, 1)
	55 #4 (4, 1)
	56 invokevirtual (4, 1)
	57 org/apache/commons/math3/geometry/partitioning/BoundaryAttribute.getPlusInside:()Lorg/apache/commons/math3/geometry/partitioning/SubHyperplane; (4, 1)
	59 ifnonnull (4, 1)
	60 7 (4, 1)
	62 aconst_null (4, 1)
	63 goto (4, 1)
	64 13 (4, 1)
	66 aload (4, 1)
	67 #4 (4, 1)
	68 invokevirtual (4, 1)
	69 org/apache/commons/math3/geometry/partitioning/BoundaryAttribute.getPlusInside:()Lorg/apache/commons/math3/geometry/partitioning/SubHyperplane; (4, 1)
	71 invokeinterface (4, 1)
	72 org/apache/commons/math3/geometry/partitioning/SubHyperplane.getPlusOutside:()Lorg/apache/commons/math3/geometry/partitioning/SubHyperplane; (4, 1)
	74 0 (4, 1)
	76 astore (4, 1)
	77 #5 (4, 1)
	78 aload (4, 1)
	79 #4 (4, 1)
	80 invokevirtual (4, 1)
	81 org/apache/commons/math3/geometry/partitioning/BoundaryAttribute.getPlusOutside:()Lorg/apache/commons/math3/geometry/partitioning/SubHyperplane; (4, 1)
	83 ifnonnull (4, 1)
	84 7 (4, 1)
	86 aconst_null (4, 1)
	87 goto (4, 1)
	88 13 (4, 1)
	90 aload (4, 1)
	91 #4 (4, 1)
	92 invokevirtual (4, 1)
	93 org/apache/commons/math3/geometry/partitioning/BoundaryAttribute.getPlusOutside:()Lorg/apache/commons/math3/geometry/partitioning/SubHyperplane; (4, 1)
	95 invokeinterface (4, 1)
	96 org/apache/commons/math3/geometry/partitioning/SubHyperplane.getPlusOutside:()Lorg/apache/commons/math3/geometry/partitioning/SubHyperplane; (4, 1)
	98 0 (4, 1)
	100 astore (4, 1)
	101 #6 (4, 1)
	102 new (4, 1)
	103 org/apache/commons/math3/geometry/partitioning/BoundaryAttribute (4, 1)
	105 dup (4, 1)
	106 aload (4, 1)
	107 #5 (4, 1)
	108 aload (4, 1)
	109 #6 (4, 1)
	110 new (4, 1)
	111 org/apache/commons/math3/geometry/partitioning/NodesSet (4, 1)
	113 dup (4, 1)
	114 invokespecial (4, 1)
	115 org/apache/commons/math3/geometry/partitioning/NodesSet.<init>:()V (4, 1)
	117 invokespecial (4, 1)
	118 org/apache/commons/math3/geometry/partitioning/BoundaryAttribute.<init>:(Lorg/apache/commons/math3/geometry/partitioning/SubHyperplane;Lorg/apache/commons/math3/geometry/partitioning/SubHyperplane;Lorg/apache/commons/math3/geometry/partitioning/NodesSet;)V (4, 1)
	120 astore (4, 1)
	121 #4 (4, 1)
	122 new (4, 4)
	123 org/apache/commons/math3/geometry/partitioning/BSPTree (4, 4)
	125 dup (4, 4)
	126 aload_1 (4, 4)
	127 invokevirtual (4, 4)
	128 org/apache/commons/math3/geometry/partitioning/BSPTree.getCut:()Lorg/apache/commons/math3/geometry/partitioning/SubHyperplane; (4, 4)
	130 invokeinterface (4, 4)
	131 org/apache/commons/math3/geometry/partitioning/SubHyperplane.getPlusOutside:()Lorg/apache/commons/math3/geometry/partitioning/SubHyperplane; (4, 4)
	133 0 (4, 4)
	135 aload_0 (4, 4)
	136 aload_1 (4, 4)
	137 invokevirtual (4, 4)
	138 org/apache/commons/math3/geometry/partitioning/BSPTree.getPlus:()Lorg/apache/commons/math3/geometry/partitioning/BSPTree; (4, 4)
	140 aload_2 (4, 4)
	141 invokespecial (4, 4)
	142 org/apache/commons/math3/geometry/partitioning/RegionFactory.recurseComplement:(Lorg/apache/commons/math3/geometry/partitioning/BSPTree;Ljava/util/Map;)Lorg/apache/commons/math3/geometry/partitioning/BSPTree; (4, 4)
	144 aload_0 (4, 4)
	145 aload_1 (4, 4)
	146 invokevirtual (4, 4)
	147 org/apache/commons/math3/geometry/partitioning/BSPTree.getMinus:()Lorg/apache/commons/math3/geometry/partitioning/BSPTree; (4, 4)
	149 aload_2 (4, 4)
	150 invokespecial (4, 4)
	151 org/apache/commons/math3/geometry/partitioning/RegionFactory.recurseComplement:(Lorg/apache/commons/math3/geometry/partitioning/BSPTree;Ljava/util/Map;)Lorg/apache/commons/math3/geometry/partitioning/BSPTree; (4, 4)
	153 aload (4, 4)
	154 #4 (4, 4)
	155 invokespecial (4, 4)
	156 org/apache/commons/math3/geometry/partitioning/BSPTree.<init>:(Lorg/apache/commons/math3/geometry/partitioning/SubHyperplane;Lorg/apache/commons/math3/geometry/partitioning/BSPTree;Lorg/apache/commons/math3/geometry/partitioning/BSPTree;Ljava/lang/Object;)V (4, 4)
	158 astore_3 (4, 4)
	159 aload_2 (1, 4)
	160 aload_1 (1, 4)
	161 aload_3 (1, 4)
	162 invokeinterface (1, 4)
	163 java/util/Map.org/apache/commons/math3/geometry/partitioning/RegionFactory (1, 4)
	165 0 (1, 4)
	167 pop (1, 4)
	168 aload_3 (2, 4)
	169 areturn (0, 4)

Method: access$400
	0 aload_0 (0, 0)
	1 aload_1 (0, 0)
	2 invokespecial (0, 0)
	3 org/apache/commons/math3/geometry/partitioning/RegionFactory.recurseComplement:(Lorg/apache/commons/math3/geometry/partitioning/BSPTree;)Lorg/apache/commons/math3/geometry/partitioning/BSPTree; (0, 0)
	5 areturn (0, 0)

