Method: <init>
	0 aload_0 (0, 0)
	1 invokespecial (0, 0)
	2 java/lang/Object.<init>:()V (0, 0)
	4 aload_0 (0, 0)
	5 aload_1 (0, 0)
	6 putfield (0, 0)
	7 org/apache/commons/math3/geometry/partitioning/SubHyperplane$SplitSubHyperplane.plus:Lorg/apache/commons/math3/geometry/partitioning/SubHyperplane; (0, 0)
	9 aload_0 (0, 0)
	10 aload_2 (0, 0)
	11 putfield (0, 0)
	12 org/apache/commons/math3/geometry/partitioning/SubHyperplane$SplitSubHyperplane.minus:Lorg/apache/commons/math3/geometry/partitioning/SubHyperplane; (0, 0)
	14 return (0, 0)

Method: getPlus
	0 aload_0 (0, 0)
	1 getfield (0, 0)
	2 org/apache/commons/math3/geometry/partitioning/SubHyperplane$SplitSubHyperplane.plus:Lorg/apache/commons/math3/geometry/partitioning/SubHyperplane; (0, 0)
	4 areturn (0, 0)

Method: getMinus
	0 aload_0 (0, 0)
	1 getfield (0, 0)
	2 org/apache/commons/math3/geometry/partitioning/SubHyperplane$SplitSubHyperplane.minus:Lorg/apache/commons/math3/geometry/partitioning/SubHyperplane; (0, 0)
	4 areturn (0, 0)

Method: getSide
	0 aload_0 (1, 1)
	1 getfield (1, 1)
	2 org/apache/commons/math3/geometry/partitioning/SubHyperplane$SplitSubHyperplane.plus:Lorg/apache/commons/math3/geometry/partitioning/SubHyperplane; (1, 1)
	4 ifnull (1, 1)
	5 42 (1, 1)
	7 aload_0 (1, 1)
	8 getfield (1, 1)
	9 org/apache/commons/math3/geometry/partitioning/SubHyperplane$SplitSubHyperplane.plus:Lorg/apache/commons/math3/geometry/partitioning/SubHyperplane; (1, 1)
	11 invokeinterface (1, 1)
	12 org/apache/commons/math3/geometry/partitioning/SubHyperplane.org/apache/commons/math3/geometry/partitioning/Side (1, 1)
	14 0 (1, 1)
	16 ifne (1, 1)
	17 30 (1, 1)
	19 aload_0 (2, 1)
	20 getfield (2, 1)
	21 org/apache/commons/math3/geometry/partitioning/SubHyperplane$SplitSubHyperplane.minus:Lorg/apache/commons/math3/geometry/partitioning/SubHyperplane; (2, 1)
	23 ifnull (2, 1)
	24 19 (2, 1)
	26 aload_0 (2, 1)
	27 getfield (2, 1)
	28 org/apache/commons/math3/geometry/partitioning/SubHyperplane$SplitSubHyperplane.minus:Lorg/apache/commons/math3/geometry/partitioning/SubHyperplane; (2, 1)
	30 invokeinterface (2, 1)
	31 org/apache/commons/math3/geometry/partitioning/SubHyperplane.org/apache/commons/math3/geometry/partitioning/Side (2, 1)
	33 0 (2, 1)
	35 ifne (2, 1)
	36 7 (2, 1)
	38 getstatic (2, 1)
	39 org/apache/commons/math3/geometry/partitioning/Side.BOTH:Lorg/apache/commons/math3/geometry/partitioning/Side; (2, 1)
	41 areturn (2, 1)
	42 getstatic (2, 2)
	43 org/apache/commons/math3/geometry/partitioning/Side.PLUS:Lorg/apache/commons/math3/geometry/partitioning/Side; (2, 2)
	45 areturn (2, 2)
	46 aload_0 (1, 1)
	47 getfield (1, 1)
	48 org/apache/commons/math3/geometry/partitioning/SubHyperplane$SplitSubHyperplane.minus:Lorg/apache/commons/math3/geometry/partitioning/SubHyperplane; (1, 1)
	50 ifnull (1, 1)
	51 19 (1, 1)
	53 aload_0 (1, 1)
	54 getfield (1, 1)
	55 org/apache/commons/math3/geometry/partitioning/SubHyperplane$SplitSubHyperplane.minus:Lorg/apache/commons/math3/geometry/partitioning/SubHyperplane; (1, 1)
	57 invokeinterface (1, 1)
	58 org/apache/commons/math3/geometry/partitioning/SubHyperplane.org/apache/commons/math3/geometry/partitioning/Side (1, 1)
	60 0 (1, 1)
	62 ifne (1, 1)
	63 7 (1, 1)
	65 getstatic (1, 1)
	66 org/apache/commons/math3/geometry/partitioning/Side.MINUS:Lorg/apache/commons/math3/geometry/partitioning/Side; (1, 1)
	68 areturn (1, 1)
	69 getstatic (1, 2)
	70 org/apache/commons/math3/geometry/partitioning/Side.HYPER:Lorg/apache/commons/math3/geometry/partitioning/Side; (1, 2)
	72 areturn (1, 2)

