Method: <init>
	0 aload_0 (0, 0)
	1 invokespecial (0, 0)
	4 aload_0 (0, 0)
	5 aload_1 (0, 0)
	6 putfield (0, 0)
	9 aload_0 (0, 0)
	10 aload_2 (0, 0)
	11 putfield (0, 0)
	14 return (0, 0)

Method: getPlus
	0 aload_0 (0, 0)
	1 getfield (0, 0)
	4 areturn (0, 0)

Method: getMinus
	0 aload_0 (0, 0)
	1 getfield (0, 0)
	4 areturn (0, 0)

Method: getSide
	0 aload_0 (1, 1)
	1 getfield (1, 1)
	4 ifnull (1, 1)
	7 aload_0 (1, 1)
	8 getfield (1, 1)
	11 invokeinterface (1, 1)
	16 ifne (1, 1)
	19 aload_0 (2, 1)
	20 getfield (2, 1)
	23 ifnull (2, 1)
	26 aload_0 (2, 1)
	27 getfield (2, 1)
	30 invokeinterface (2, 1)
	35 ifne (2, 1)
	38 getstatic (2, 1)
	41 areturn (2, 1)
	42 getstatic (2, 2)
	45 areturn (2, 2)
	46 aload_0 (1, 1)
	47 getfield (1, 1)
	50 ifnull (1, 1)
	53 aload_0 (1, 1)
	54 getfield (1, 1)
	57 invokeinterface (1, 1)
	62 ifne (1, 1)
	65 getstatic (1, 1)
	68 areturn (1, 1)
	69 getstatic (1, 2)
	72 areturn (1, 2)

