Method: <init>
	0 aload_0 (0, 0)
	1 aconst_null (0, 0)
	2 invokespecial (0, 0)
	3 org/apache/commons/math3/ode/AbstractIntegrator.<init>:(Ljava/lang/String;)V (0, 0)
	5 return (0, 0)

Method: getName
	0 aload_0 (0, 0)
	1 getfield (0, 0)
	2 org/apache/commons/math3/ode/AbstractIntegrator.name:Ljava/lang/String; (0, 0)
	4 areturn (0, 0)

Method: addStepHandler
	0 aload_0 (0, 0)
	1 getfield (0, 0)
	2 org/apache/commons/math3/ode/AbstractIntegrator.stepHandlers:Ljava/util/Collection; (0, 0)
	4 aload_1 (0, 0)
	5 invokeinterface (0, 0)
	6 java/util/Collection.java/util/Collections (0, 0)
	8 0 (0, 0)
	10 pop (0, 0)
	11 return (0, 0)

Method: getStepHandlers
	0 aload_0 (0, 1)
	1 getfield (0, 1)
	2 org/apache/commons/math3/ode/AbstractIntegrator.stepHandlers:Ljava/util/Collection; (0, 1)
	4 invokestatic (0, 1)
	5 java/util/Collections.unmodifiableCollection:(Ljava/util/Collection;)Ljava/util/Collection; (0, 1)
	7 areturn (0, 1)

Method: clearStepHandlers
	0 aload_0 (0, 0)
	1 getfield (0, 0)
	2 org/apache/commons/math3/ode/AbstractIntegrator.stepHandlers:Ljava/util/Collection; (0, 0)
	4 invokeinterface (0, 0)
	5 java/util/Collection.org/apache/commons/math3/analysis/solvers/BracketingNthOrderBrentSolver (0, 0)
	7 0 (0, 0)
	9 return (0, 0)

Method: addEventHandler
	0 aload_0 (0, 0)
	1 getfield (0, 0)
	2 org/apache/commons/math3/ode/AbstractIntegrator.eventsStates:Ljava/util/Collection; (0, 0)
	4 new (0, 0)
	5 org/apache/commons/math3/ode/events/EventState (0, 0)
	7 dup (0, 0)
	8 aload_1 (0, 0)
	9 dload_2 (0, 0)
	10 dload (0, 0)
	11 #4 (0, 0)
	12 iload (0, 0)
	13 #6 (0, 0)
	14 aload (0, 0)
	15 #7 (0, 0)
	16 invokespecial (0, 0)
	17 org/apache/commons/math3/ode/events/EventState.<init>:(Lorg/apache/commons/math3/ode/events/EventHandler;DDILorg/apache/commons/math3/analysis/solvers/UnivariateSolver;)V (0, 0)
	19 invokeinterface (0, 0)
	20 java/util/Collection.java/util/Collections (0, 0)
	22 0 (0, 0)
	24 pop (0, 0)
	25 return (0, 0)

Method: getEventHandlers
	0 new (0, 0)
	1 java/util/ArrayList (0, 0)
	3 dup (0, 0)
	4 aload_0 (0, 0)
	5 getfield (0, 0)
	6 org/apache/commons/math3/ode/AbstractIntegrator.eventsStates:Ljava/util/Collection; (0, 0)
	8 invokeinterface (0, 0)
	9 java/util/Collection.<init>:(I)V (0, 0)
	11 0 (0, 0)
	13 invokespecial (0, 0)
	14 java/util/ArrayList.<init>:(I)V (0, 0)
	16 astore_1 (0, 0)
	17 aload_0 (1, 4)
	18 getfield (1, 4)
	19 org/apache/commons/math3/ode/AbstractIntegrator.eventsStates:Ljava/util/Collection; (1, 4)
	21 invokeinterface (1, 4)
	22 java/util/Collection.java/util/Iterator (1, 4)
	24 0 (1, 4)
	26 astore_2 (1, 4)
	27 aload_2 (1, 4)
	28 invokeinterface (1, 4)
	29 java/util/Iterator.next:()Ljava/lang/Object; (1, 4)
	31 0 (1, 4)
	33 ifeq (1, 4)
	34 27 (1, 4)
	36 aload_2 (1, 4)
	37 invokeinterface (1, 4)
	38 java/util/Iterator.getEventHandler:()Lorg/apache/commons/math3/ode/events/EventHandler; (1, 4)
	40 0 (1, 4)
	42 checkcast (1, 4)
	43 org/apache/commons/math3/ode/events/EventState (1, 4)
	45 astore_3 (1, 4)
	46 aload_1 (1, 4)
	47 aload_3 (1, 4)
	48 invokevirtual (1, 4)
	49 org/apache/commons/math3/ode/events/EventState.getEventHandler:()Lorg/apache/commons/math3/ode/events/EventHandler; (1, 4)
	51 invokeinterface (1, 4)
	52 java/util/List.java/util/Collections (1, 4)
	54 0 (1, 4)
	56 pop (1, 4)
	57 goto (0, 0)
	58 -30 (0, 0)
	60 aload_1 (0, 1)
	61 invokestatic (0, 1)
	62 java/util/Collections.unmodifiableCollection:(Ljava/util/Collection;)Ljava/util/Collection; (0, 1)
	64 areturn (0, 1)

Method: clearEventHandlers
	0 aload_0 (0, 0)
	1 getfield (0, 0)
	2 org/apache/commons/math3/ode/AbstractIntegrator.eventsStates:Ljava/util/Collection; (0, 0)
	4 invokeinterface (0, 0)
	5 java/util/Collection.org/apache/commons/math3/analysis/solvers/BracketingNthOrderBrentSolver (0, 0)
	7 0 (0, 0)
	9 return (0, 0)

Method: getCurrentStepStart
	0 aload_0 (0, 0)
	1 getfield (0, 0)
	2 org/apache/commons/math3/ode/AbstractIntegrator.stepStart:D (0, 0)
	4 dreturn (0, 0)

Method: getCurrentSignedStepsize
	0 aload_0 (0, 0)
	1 getfield (0, 0)
	2 org/apache/commons/math3/ode/AbstractIntegrator.stepSize:D (0, 0)
	4 dreturn (0, 0)

Method: setMaxEvaluations
	0 aload_0 (0, 0)
	1 aload_0 (0, 0)
	2 getfield (0, 0)
	3 org/apache/commons/math3/ode/AbstractIntegrator.evaluations:Lorg/apache/commons/math3/util/IntegerSequence$Incrementor; (0, 0)
	5 iload_1 (0, 0)
	6 ifge (0, 0)
	7 8 (0, 0)
	9 ldc (0, 0)
	10 2147483647 (0, 0)
	11 goto (0, 0)
	12 4 (0, 0)
	14 iload_1 (0, 0)
	15 invokevirtual (0, 0)
	16 org/apache/commons/math3/util/IntegerSequence$Incrementor.withMaximalCount:(I)Lorg/apache/commons/math3/util/IntegerSequence$Incrementor; (0, 0)
	18 putfield (0, 0)
	19 org/apache/commons/math3/ode/AbstractIntegrator.evaluations:Lorg/apache/commons/math3/util/IntegerSequence$Incrementor; (0, 0)
	21 return (0, 0)

Method: getMaxEvaluations
	0 aload_0 (0, 0)
	1 getfield (0, 0)
	2 org/apache/commons/math3/ode/AbstractIntegrator.evaluations:Lorg/apache/commons/math3/util/IntegerSequence$Incrementor; (0, 0)
	4 invokevirtual (0, 0)
	5 org/apache/commons/math3/util/IntegerSequence$Incrementor.getMaximalCount:()I (0, 0)
	7 ireturn (0, 0)

Method: getEvaluations
	0 aload_0 (0, 0)
	1 getfield (0, 0)
	2 org/apache/commons/math3/ode/AbstractIntegrator.evaluations:Lorg/apache/commons/math3/util/IntegerSequence$Incrementor; (0, 0)
	4 invokevirtual (0, 0)
	5 org/apache/commons/math3/util/IntegerSequence$Incrementor.getCount:()I (0, 0)
	7 ireturn (0, 0)

Method: initIntegration
	0 aload_0 (0, 0)
	1 aload_0 (0, 0)
	2 getfield (0, 0)
	3 org/apache/commons/math3/ode/AbstractIntegrator.evaluations:Lorg/apache/commons/math3/util/IntegerSequence$Incrementor; (0, 0)
	5 iconst_0 (0, 0)
	6 invokevirtual (0, 0)
	7 org/apache/commons/math3/util/IntegerSequence$Incrementor.withStart:(I)Lorg/apache/commons/math3/util/IntegerSequence$Incrementor; (0, 0)
	9 putfield (0, 0)
	10 org/apache/commons/math3/ode/AbstractIntegrator.evaluations:Lorg/apache/commons/math3/util/IntegerSequence$Incrementor; (0, 0)
	12 aload_0 (1, 4)
	13 getfield (1, 4)
	14 org/apache/commons/math3/ode/AbstractIntegrator.eventsStates:Ljava/util/Collection; (1, 4)
	16 invokeinterface (1, 4)
	17 java/util/Collection.java/util/Iterator (1, 4)
	19 0 (1, 4)
	21 astore (1, 4)
	22 #6 (1, 4)
	23 aload (1, 4)
	24 #6 (1, 4)
	25 invokeinterface (1, 4)
	26 java/util/Iterator.next:()Ljava/lang/Object; (1, 4)
	28 0 (1, 4)
	30 ifeq (1, 4)
	31 41 (1, 4)
	33 aload (1, 4)
	34 #6 (1, 4)
	35 invokeinterface (1, 4)
	36 java/util/Iterator.getEventHandler:()Lorg/apache/commons/math3/ode/events/EventHandler; (1, 4)
	38 0 (1, 4)
	40 checkcast (1, 4)
	41 org/apache/commons/math3/ode/events/EventState (1, 4)
	43 astore (1, 4)
	44 #7 (1, 4)
	45 aload (1, 4)
	46 #7 (1, 4)
	47 aload_0 (1, 4)
	48 getfield (1, 4)
	49 org/apache/commons/math3/ode/AbstractIntegrator.expandable:Lorg/apache/commons/math3/ode/ExpandableStatefulODE; (1, 4)
	51 invokevirtual (1, 4)
	52 org/apache/commons/math3/ode/events/EventState.setExpandable:(Lorg/apache/commons/math3/ode/ExpandableStatefulODE;)V (1, 4)
	54 aload (1, 4)
	55 #7 (1, 4)
	56 invokevirtual (1, 4)
	57 org/apache/commons/math3/ode/events/EventState.getEventHandler:()Lorg/apache/commons/math3/ode/events/EventHandler; (1, 4)
	59 dload_1 (1, 4)
	60 aload_3 (1, 4)
	61 dload (1, 4)
	62 #4 (1, 4)
	63 invokeinterface (1, 4)
	64 org/apache/commons/math3/ode/events/EventHandler.org/apache/commons/math3/ode/sampling/StepHandler (1, 4)
	66 0 (1, 4)
	68 goto (0, 0)
	69 -45 (0, 0)
	71 aload_0 (1, 4)
	72 getfield (1, 4)
	73 org/apache/commons/math3/ode/AbstractIntegrator.stepHandlers:Ljava/util/Collection; (1, 4)
	75 invokeinterface (1, 4)
	76 java/util/Collection.java/util/Iterator (1, 4)
	78 0 (1, 4)
	80 astore (1, 4)
	81 #6 (1, 4)
	82 aload (1, 4)
	83 #6 (1, 4)
	84 invokeinterface (1, 4)
	85 java/util/Iterator.next:()Ljava/lang/Object; (1, 4)
	87 0 (1, 4)
	89 ifeq (1, 4)
	90 29 (1, 4)
	92 aload (1, 4)
	93 #6 (1, 4)
	94 invokeinterface (1, 4)
	95 java/util/Iterator.getEventHandler:()Lorg/apache/commons/math3/ode/events/EventHandler; (1, 4)
	97 0 (1, 4)
	99 checkcast (1, 4)
	100 org/apache/commons/math3/ode/sampling/StepHandler (1, 4)
	102 astore (1, 4)
	103 #7 (1, 4)
	104 aload (1, 4)
	105 #7 (1, 4)
	106 dload_1 (1, 4)
	107 aload_3 (1, 4)
	108 dload (1, 4)
	109 #4 (1, 4)
	110 invokeinterface (1, 4)
	111 org/apache/commons/math3/ode/sampling/StepHandler.org/apache/commons/math3/ode/sampling/StepHandler (1, 4)
	113 0 (1, 4)
	115 goto (0, 0)
	116 -33 (0, 0)
	118 aload_0 (0, 0)
	119 iconst_0 (0, 0)
	120 invokevirtual (0, 0)
	121 org/apache/commons/math3/ode/AbstractIntegrator.setStateInitialized:(Z)V (0, 0)
	123 return (0, 0)

Method: setEquations
	0 aload_0 (0, 0)
	1 aload_1 (0, 0)
	2 putfield (0, 0)
	3 org/apache/commons/math3/ode/AbstractIntegrator.expandable:Lorg/apache/commons/math3/ode/ExpandableStatefulODE; (0, 0)
	5 return (0, 0)

Method: getExpandable
	0 aload_0 (0, 0)
	1 getfield (0, 0)
	2 org/apache/commons/math3/ode/AbstractIntegrator.expandable:Lorg/apache/commons/math3/ode/ExpandableStatefulODE; (0, 0)
	4 areturn (0, 0)

Method: getEvaluationsCounter
	0 aload_0 (0, 0)
	1 getfield (0, 0)
	2 org/apache/commons/math3/ode/AbstractIntegrator.evaluations:Lorg/apache/commons/math3/util/IntegerSequence$Incrementor; (0, 0)
	4 invokestatic (0, 0)
	5 org/apache/commons/math3/util/Incrementor.wrap:(Lorg/apache/commons/math3/util/IntegerSequence$Incrementor;)Lorg/apache/commons/math3/util/Incrementor; (0, 0)
	7 areturn (0, 0)

Method: getCounter
	0 aload_0 (0, 0)
	1 getfield (0, 0)
	2 org/apache/commons/math3/ode/AbstractIntegrator.evaluations:Lorg/apache/commons/math3/util/IntegerSequence$Incrementor; (0, 0)
	4 areturn (0, 0)

Method: integrate
	0 aload (1, 1)
	1 #4 (1, 1)
	2 arraylength (1, 1)
	3 aload_1 (1, 1)
	4 invokeinterface (1, 1)
	5 org/apache/commons/math3/ode/FirstOrderDifferentialEquations.org/apache/commons/math3/exception/DimensionMismatchException (1, 1)
	7 0 (1, 1)
	9 if_icmpeq (1, 1)
	10 20 (1, 1)
	12 new (1, 1)
	13 org/apache/commons/math3/exception/DimensionMismatchException (1, 1)
	15 dup (1, 1)
	16 aload (1, 1)
	17 #4 (1, 1)
	18 arraylength (1, 1)
	19 aload_1 (1, 1)
	20 invokeinterface (1, 1)
	21 org/apache/commons/math3/ode/FirstOrderDifferentialEquations.org/apache/commons/math3/exception/DimensionMismatchException (1, 1)
	23 0 (1, 1)
	25 invokespecial (1, 1)
	26 org/apache/commons/math3/exception/DimensionMismatchException.<init>:(II)V (1, 1)
	28 athrow (1, 1)
	29 aload (1, 1)
	30 #7 (1, 1)
	31 arraylength (1, 1)
	32 aload_1 (1, 1)
	33 invokeinterface (1, 1)
	34 org/apache/commons/math3/ode/FirstOrderDifferentialEquations.org/apache/commons/math3/exception/DimensionMismatchException (1, 1)
	36 0 (1, 1)
	38 if_icmpeq (1, 1)
	39 20 (1, 1)
	41 new (1, 1)
	42 org/apache/commons/math3/exception/DimensionMismatchException (1, 1)
	44 dup (1, 1)
	45 aload (1, 1)
	46 #7 (1, 1)
	47 arraylength (1, 1)
	48 aload_1 (1, 1)
	49 invokeinterface (1, 1)
	50 org/apache/commons/math3/ode/FirstOrderDifferentialEquations.org/apache/commons/math3/exception/DimensionMismatchException (1, 1)
	52 0 (1, 1)
	54 invokespecial (1, 1)
	55 org/apache/commons/math3/exception/DimensionMismatchException.<init>:(II)V (1, 1)
	57 athrow (1, 1)
	58 new (0, 0)
	59 org/apache/commons/math3/ode/ExpandableStatefulODE (0, 0)
	61 dup (0, 0)
	62 aload_1 (0, 0)
	63 invokespecial (0, 0)
	64 org/apache/commons/math3/ode/ExpandableStatefulODE.<init>:(Lorg/apache/commons/math3/ode/FirstOrderDifferentialEquations;)V (0, 0)
	66 astore (0, 0)
	67 #8 (0, 0)
	68 aload (0, 0)
	69 #8 (0, 0)
	70 dload_2 (0, 0)
	71 invokevirtual (0, 0)
	72 org/apache/commons/math3/ode/ExpandableStatefulODE.setTime:(D)V (0, 0)
	74 aload (0, 0)
	75 #8 (0, 0)
	76 aload (0, 0)
	77 #4 (0, 0)
	78 invokevirtual (0, 0)
	79 org/apache/commons/math3/ode/ExpandableStatefulODE.setPrimaryState:([D)V (0, 0)
	81 aload_0 (0, 4)
	82 aload (0, 4)
	83 #8 (0, 4)
	84 dload (0, 4)
	85 #5 (0, 4)
	86 invokevirtual (0, 4)
	87 org/apache/commons/math3/ode/AbstractIntegrator.integrate:(Lorg/apache/commons/math3/ode/ExpandableStatefulODE;D)V (0, 4)
	89 aload (0, 4)
	90 #8 (0, 4)
	91 invokevirtual (0, 4)
	92 org/apache/commons/math3/ode/ExpandableStatefulODE.getPrimaryState:()[D (0, 4)
	94 iconst_0 (0, 4)
	95 aload (0, 4)
	96 #7 (0, 4)
	97 iconst_0 (0, 4)
	98 aload (0, 4)
	99 #7 (0, 4)
	100 arraylength (0, 4)
	101 invokestatic (0, 4)
	102 java/lang/System.arraycopy:(Ljava/lang/Object;ILjava/lang/Object;II)V (0, 4)
	104 aload (0, 4)
	105 #8 (0, 4)
	106 invokevirtual (0, 4)
	107 org/apache/commons/math3/ode/ExpandableStatefulODE.getTime:()D (0, 4)
	109 dreturn (0, 4)

Method: computeDerivatives
	0 aload_0 (0, 0)
	1 getfield (0, 0)
	2 org/apache/commons/math3/ode/AbstractIntegrator.evaluations:Lorg/apache/commons/math3/util/IntegerSequence$Incrementor; (0, 0)
	4 invokevirtual (0, 0)
	5 org/apache/commons/math3/util/IntegerSequence$Incrementor.increment:()V (0, 0)
	7 aload_0 (0, 0)
	8 getfield (0, 0)
	9 org/apache/commons/math3/ode/AbstractIntegrator.expandable:Lorg/apache/commons/math3/ode/ExpandableStatefulODE; (0, 0)
	11 dload_1 (0, 0)
	12 aload_3 (0, 0)
	13 aload (0, 0)
	14 #4 (0, 0)
	15 invokevirtual (0, 0)
	16 org/apache/commons/math3/ode/ExpandableStatefulODE.computeDerivatives:(D[D[D)V (0, 0)
	18 return (0, 0)

Method: setStateInitialized
	0 aload_0 (0, 0)
	1 iload_1 (0, 0)
	2 putfield (0, 0)
	3 org/apache/commons/math3/ode/AbstractIntegrator.statesInitialized:Z (0, 0)
	5 return (0, 0)

Method: acceptStep
	0 aload_1 (0, 0)
	1 invokevirtual (0, 0)
	2 org/apache/commons/math3/ode/sampling/AbstractStepInterpolator.getGlobalPreviousTime:()D (0, 0)
	4 dstore (0, 0)
	5 #6 (0, 0)
	6 aload_1 (0, 0)
	7 invokevirtual (0, 0)
	8 org/apache/commons/math3/ode/sampling/AbstractStepInterpolator.getGlobalCurrentTime:()D (0, 0)
	10 dstore (0, 0)
	11 #8 (0, 0)
	12 aload_0 (1, 1)
	13 getfield (1, 1)
	14 org/apache/commons/math3/ode/AbstractIntegrator.statesInitialized:Z (1, 1)
	16 ifne (1, 1)
	17 50 (1, 1)
	19 aload_0 (2, 4)
	20 getfield (2, 4)
	21 org/apache/commons/math3/ode/AbstractIntegrator.eventsStates:Ljava/util/Collection; (2, 4)
	23 invokeinterface (2, 4)
	24 java/util/Collection.java/util/Iterator (2, 4)
	26 0 (2, 4)
	28 astore (2, 4)
	29 #10 (2, 4)
	30 aload (2, 4)
	31 #10 (2, 4)
	32 invokeinterface (2, 4)
	33 java/util/Iterator.next:()Ljava/lang/Object; (2, 4)
	35 0 (2, 4)
	37 ifeq (2, 4)
	38 24 (2, 4)
	40 aload (2, 4)
	41 #10 (2, 4)
	42 invokeinterface (2, 4)
	43 java/util/Iterator.getEventHandler:()Lorg/apache/commons/math3/ode/events/EventHandler; (2, 4)
	45 0 (2, 4)
	47 checkcast (2, 4)
	48 org/apache/commons/math3/ode/events/EventState (2, 4)
	50 astore (2, 4)
	51 #11 (2, 4)
	52 aload (2, 4)
	53 #11 (2, 4)
	54 aload_1 (2, 4)
	55 invokevirtual (2, 4)
	56 org/apache/commons/math3/ode/events/EventState.reinitializeBegin:(Lorg/apache/commons/math3/ode/sampling/StepInterpolator;)V (2, 4)
	58 goto (1, 1)
	59 -28 (1, 1)
	61 aload_0 (1, 1)
	62 iconst_1 (1, 1)
	63 putfield (1, 1)
	64 org/apache/commons/math3/ode/AbstractIntegrator.statesInitialized:Z (1, 1)
	66 aload_1 (0, 4)
	67 invokevirtual (0, 4)
	68 org/apache/commons/math3/ode/sampling/AbstractStepInterpolator.isForward:()Z (0, 4)
	70 ifeq (0, 4)
	71 7 (0, 4)
	73 iconst_1 (0, 4)
	74 goto (0, 4)
	75 4 (0, 4)
	77 iconst_m1 (0, 4)
	78 istore (0, 4)
	79 #10 (0, 4)
	80 new (0, 4)
	81 java/util/TreeSet (0, 4)
	83 dup (0, 4)
	84 new (0, 4)
	85 org/apache/commons/math3/ode/AbstractIntegrator$1 (0, 4)
	87 dup (0, 4)
	88 aload_0 (0, 4)
	89 iload (0, 4)
	90 #10 (0, 4)
	91 invokespecial (0, 4)
	92 org/apache/commons/math3/ode/AbstractIntegrator$1.<init>:(Lorg/apache/commons/math3/ode/AbstractIntegrator;I)V (0, 4)
	94 invokespecial (0, 4)
	95 java/util/TreeSet.<init>:(Ljava/util/Comparator;)V (0, 4)
	97 astore (0, 4)
	98 #11 (0, 4)
	99 aload_0 (1, 4)
	100 getfield (1, 4)
	101 org/apache/commons/math3/ode/AbstractIntegrator.eventsStates:Ljava/util/Collection; (1, 4)
	103 invokeinterface (1, 4)
	104 java/util/Collection.java/util/Iterator (1, 4)
	106 0 (1, 4)
	108 astore (1, 4)
	109 #12 (1, 4)
	110 aload (1, 4)
	111 #12 (1, 4)
	112 invokeinterface (1, 4)
	113 java/util/Iterator.next:()Ljava/lang/Object; (1, 4)
	115 0 (1, 4)
	117 ifeq (1, 4)
	118 37 (1, 4)
	120 aload (1, 4)
	121 #12 (1, 4)
	122 invokeinterface (1, 4)
	123 java/util/Iterator.getEventHandler:()Lorg/apache/commons/math3/ode/events/EventHandler; (1, 4)
	125 0 (1, 4)
	127 checkcast (1, 4)
	128 org/apache/commons/math3/ode/events/EventState (1, 4)
	130 astore (1, 4)
	131 #13 (1, 4)
	132 aload (2, 1)
	133 #13 (2, 1)
	134 aload_1 (2, 1)
	135 invokevirtual (2, 1)
	136 org/apache/commons/math3/ode/events/EventState.evaluateStep:(Lorg/apache/commons/math3/ode/sampling/StepInterpolator;)Z (2, 1)
	138 ifeq (2, 1)
	139 13 (2, 1)
	141 aload (2, 1)
	142 #11 (2, 1)
	143 aload (2, 1)
	144 #13 (2, 1)
	145 invokeinterface (2, 1)
	146 java/util/SortedSet.java/util/Collections (2, 1)
	148 0 (2, 1)
	150 pop (2, 1)
	151 goto (0, 4)
	152 -41 (0, 4)
	154 aload (1, 3)
	155 #11 (1, 3)
	156 invokeinterface (1, 3)
	157 java/util/SortedSet.remove:()V (1, 3)
	159 0 (1, 3)
	161 ifne (1, 3)
	162 365 (1, 3)
	164 aload (1, 3)
	165 #11 (1, 3)
	166 invokeinterface (1, 3)
	167 java/util/SortedSet.java/util/Iterator (1, 3)
	169 0 (1, 3)
	171 astore (1, 3)
	172 #12 (1, 3)
	173 aload (1, 3)
	174 #12 (1, 3)
	175 invokeinterface (1, 3)
	176 java/util/Iterator.getEventHandler:()Lorg/apache/commons/math3/ode/events/EventHandler; (1, 3)
	178 0 (1, 3)
	180 checkcast (1, 3)
	181 org/apache/commons/math3/ode/events/EventState (1, 3)
	183 astore (1, 3)
	184 #13 (1, 3)
	185 aload (1, 3)
	186 #12 (1, 3)
	187 invokeinterface (1, 3)
	188 java/util/Iterator.getEventTime:()D (1, 3)
	190 0 (1, 3)
	192 aload (1, 3)
	193 #13 (1, 3)
	194 invokevirtual (1, 3)
	195 org/apache/commons/math3/ode/events/EventState.getEventTime:()D (1, 3)
	197 dstore (1, 3)
	198 #14 (1, 3)
	199 aload_1 (1, 3)
	200 dload (1, 3)
	201 #6 (1, 3)
	202 invokevirtual (1, 3)
	203 org/apache/commons/math3/ode/sampling/AbstractStepInterpolator.setSoftPreviousTime:(D)V (1, 3)
	205 aload_1 (1, 3)
	206 dload (1, 3)
	207 #14 (1, 3)
	208 invokevirtual (1, 3)
	209 org/apache/commons/math3/ode/sampling/AbstractStepInterpolator.setSoftCurrentTime:(D)V (1, 3)
	211 aload_1 (1, 3)
	212 dload (1, 3)
	213 #14 (1, 3)
	214 invokevirtual (1, 3)
	215 org/apache/commons/math3/ode/sampling/AbstractStepInterpolator.setInterpolatedTime:(D)V (1, 3)
	217 aload_2 (1, 3)
	218 arraylength (1, 3)
	219 newarray (1, 3)
	220 7 (1, 3)
	221 astore (1, 3)
	222 #16 (1, 3)
	223 aload_0 (1, 3)
	224 getfield (1, 3)
	225 org/apache/commons/math3/ode/AbstractIntegrator.expandable:Lorg/apache/commons/math3/ode/ExpandableStatefulODE; (1, 3)
	227 invokevirtual (1, 3)
	228 org/apache/commons/math3/ode/ExpandableStatefulODE.getPrimaryMapper:()Lorg/apache/commons/math3/ode/EquationsMapper; (1, 3)
	230 aload_1 (1, 3)
	231 invokevirtual (1, 3)
	232 org/apache/commons/math3/ode/sampling/AbstractStepInterpolator.getInterpolatedState:()[D (1, 3)
	234 aload (1, 3)
	235 #16 (1, 3)
	236 invokevirtual (1, 3)
	237 org/apache/commons/math3/ode/EquationsMapper.insertEquationData:([D[D)V (1, 3)
	239 iconst_0 (1, 3)
	240 istore (1, 3)
	241 #17 (1, 3)
	242 aload_0 (2, 4)
	243 getfield (2, 4)
	244 org/apache/commons/math3/ode/AbstractIntegrator.expandable:Lorg/apache/commons/math3/ode/ExpandableStatefulODE; (2, 4)
	246 invokevirtual (2, 4)
	247 org/apache/commons/math3/ode/ExpandableStatefulODE.getSecondaryMappers:()[Lorg/apache/commons/math3/ode/EquationsMapper; (2, 4)
	249 astore (2, 4)
	250 #18 (2, 4)
	251 aload (2, 4)
	252 #18 (2, 4)
	253 arraylength (2, 4)
	254 istore (2, 4)
	255 #19 (2, 4)
	256 iconst_0 (2, 4)
	257 istore (2, 4)
	258 #20 (2, 4)
	259 iload (2, 4)
	260 #20 (2, 4)
	261 iload (2, 4)
	262 #19 (2, 4)
	263 if_icmpge (2, 4)
	264 32 (2, 4)
	266 aload (2, 4)
	267 #18 (2, 4)
	268 iload (2, 4)
	269 #20 (2, 4)
	270 aaload (2, 4)
	271 astore (2, 4)
	272 #21 (2, 4)
	273 aload (2, 4)
	274 #21 (2, 4)
	275 aload_1 (2, 4)
	276 iload (2, 4)
	277 #17 (2, 4)
	278 iinc (2, 4)
	279 #17 (2, 4)
	280 -74 (2, 4)
	281 invokevirtual (2, 4)
	282 org/apache/commons/math3/ode/sampling/AbstractStepInterpolator.getInterpolatedSecondaryState:(I)[D (2, 4)
	284 aload (2, 4)
	285 #16 (2, 4)
	286 invokevirtual (2, 4)
	287 org/apache/commons/math3/ode/EquationsMapper.insertEquationData:([D[D)V (2, 4)
	289 iinc (2, 4)
	290 #20 (2, 4)
	291 -89 (2, 4)
	292 goto (2, 4)
	293 -33 (2, 4)
	295 aload_0 (2, 4)
	296 getfield (2, 4)
	297 org/apache/commons/math3/ode/AbstractIntegrator.eventsStates:Ljava/util/Collection; (2, 4)
	299 invokeinterface (2, 4)
	300 java/util/Collection.java/util/Iterator (2, 4)
	302 0 (2, 4)
	304 astore (2, 4)
	305 #18 (2, 4)
	306 aload (2, 4)
	307 #18 (2, 4)
	308 invokeinterface (2, 4)
	309 java/util/Iterator.next:()Ljava/lang/Object; (2, 4)
	311 0 (2, 4)
	313 ifeq (2, 4)
	314 51 (2, 4)
	316 aload (2, 4)
	317 #18 (2, 4)
	318 invokeinterface (2, 4)
	319 java/util/Iterator.getEventHandler:()Lorg/apache/commons/math3/ode/events/EventHandler; (2, 4)
	321 0 (2, 4)
	323 checkcast (2, 4)
	324 org/apache/commons/math3/ode/events/EventState (2, 4)
	326 astore (2, 4)
	327 #19 (2, 4)
	328 aload (2, 4)
	329 #19 (2, 4)
	330 dload (2, 4)
	331 #14 (2, 4)
	332 aload (2, 4)
	333 #16 (2, 4)
	334 invokevirtual (2, 4)
	335 org/apache/commons/math3/ode/events/EventState.stepAccepted:(D[D)V (2, 4)
	337 aload_0 (2, 4)
	338 aload_0 (2, 4)
	339 getfield (2, 4)
	340 org/apache/commons/math3/ode/AbstractIntegrator.isLastStep:Z (2, 4)
	342 ifne (2, 4)
	343 11 (2, 4)
	345 aload (2, 4)
	346 #19 (2, 4)
	347 invokevirtual (2, 4)
	348 org/apache/commons/math3/ode/events/EventState.stop:()Z (2, 4)
	350 ifeq (2, 4)
	351 7 (2, 4)
	353 iconst_1 (2, 4)
	354 goto (2, 4)
	355 4 (2, 4)
	357 iconst_0 (2, 4)
	358 putfield (2, 4)
	359 org/apache/commons/math3/ode/AbstractIntegrator.isLastStep:Z (2, 4)
	361 goto (1, 3)
	362 -55 (1, 3)
	364 aload_0 (2, 4)
	365 getfield (2, 4)
	366 org/apache/commons/math3/ode/AbstractIntegrator.stepHandlers:Ljava/util/Collection; (2, 4)
	368 invokeinterface (2, 4)
	369 java/util/Collection.java/util/Iterator (2, 4)
	371 0 (2, 4)
	373 astore (2, 4)
	374 #18 (2, 4)
	375 aload (2, 4)
	376 #18 (2, 4)
	377 invokeinterface (2, 4)
	378 java/util/Iterator.next:()Ljava/lang/Object; (2, 4)
	380 0 (2, 4)
	382 ifeq (2, 4)
	383 30 (2, 4)
	385 aload (2, 4)
	386 #18 (2, 4)
	387 invokeinterface (2, 4)
	388 java/util/Iterator.getEventHandler:()Lorg/apache/commons/math3/ode/events/EventHandler; (2, 4)
	390 0 (2, 4)
	392 checkcast (2, 4)
	393 org/apache/commons/math3/ode/sampling/StepHandler (2, 4)
	395 astore (2, 4)
	396 #19 (2, 4)
	397 aload (2, 4)
	398 #19 (2, 4)
	399 aload_1 (2, 4)
	400 aload_0 (2, 4)
	401 getfield (2, 4)
	402 org/apache/commons/math3/ode/AbstractIntegrator.isLastStep:Z (2, 4)
	404 invokeinterface (2, 4)
	405 org/apache/commons/math3/ode/sampling/StepHandler.resetOccurred:Z (2, 4)
	407 0 (2, 4)
	409 goto (1, 3)
	410 -34 (1, 3)
	412 aload_0 (2, 1)
	413 getfield (2, 1)
	414 org/apache/commons/math3/ode/AbstractIntegrator.isLastStep:Z (2, 1)
	416 ifeq (2, 1)
	417 16 (2, 1)
	419 aload (2, 1)
	420 #16 (2, 1)
	421 iconst_0 (2, 1)
	422 aload_2 (2, 1)
	423 iconst_0 (2, 1)
	424 aload_2 (2, 1)
	425 arraylength (2, 1)
	426 invokestatic (2, 1)
	427 java/lang/System.arraycopy:(Ljava/lang/Object;ILjava/lang/Object;II)V (2, 1)
	429 dload (2, 1)
	430 #14 (2, 1)
	431 dreturn (2, 1)
	432 iconst_0 (1, 3)
	433 istore (1, 3)
	434 #18 (1, 3)
	435 aload_0 (1, 3)
	436 iconst_0 (1, 3)
	437 putfield (1, 3)
	438 org/apache/commons/math3/ode/AbstractIntegrator.resetOccurred:Z (1, 3)
	440 aload (1, 3)
	441 #13 (1, 3)
	442 dload (1, 3)
	443 #14 (1, 3)
	444 aload (1, 3)
	445 #16 (1, 3)
	446 invokevirtual (1, 3)
	447 org/apache/commons/math3/ode/events/EventState.reset:(D[D)Z (1, 3)
	449 istore (1, 3)
	450 #18 (1, 3)
	451 iload (2, 1)
	452 #18 (2, 1)
	453 ifeq (2, 1)
	454 35 (2, 1)
	456 aload_1 (2, 1)
	457 dload (2, 1)
	458 #14 (2, 1)
	459 invokevirtual (2, 1)
	460 org/apache/commons/math3/ode/sampling/AbstractStepInterpolator.setInterpolatedTime:(D)V (2, 1)
	462 aload (2, 1)
	463 #16 (2, 1)
	464 iconst_0 (2, 1)
	465 aload_2 (2, 1)
	466 iconst_0 (2, 1)
	467 aload_2 (2, 1)
	468 arraylength (2, 1)
	469 invokestatic (2, 1)
	470 java/lang/System.arraycopy:(Ljava/lang/Object;ILjava/lang/Object;II)V (2, 1)
	472 aload_0 (2, 1)
	473 dload (2, 1)
	474 #14 (2, 1)
	475 aload_2 (2, 1)
	476 aload_3 (2, 1)
	477 invokevirtual (2, 1)
	478 org/apache/commons/math3/ode/AbstractIntegrator.computeDerivatives:(D[D[D)V (2, 1)
	480 aload_0 (2, 1)
	481 iconst_1 (2, 1)
	482 putfield (2, 1)
	483 org/apache/commons/math3/ode/AbstractIntegrator.resetOccurred:Z (2, 1)
	485 dload (2, 1)
	486 #14 (2, 1)
	487 dreturn (2, 1)
	488 dload (1, 3)
	489 #14 (1, 3)
	490 dstore (1, 3)
	491 #6 (1, 3)
	492 aload_1 (1, 3)
	493 dload (1, 3)
	494 #14 (1, 3)
	495 invokevirtual (1, 3)
	496 org/apache/commons/math3/ode/sampling/AbstractStepInterpolator.setSoftPreviousTime:(D)V (1, 3)
	498 aload_1 (1, 3)
	499 dload (1, 3)
	500 #8 (1, 3)
	501 invokevirtual (1, 3)
	502 org/apache/commons/math3/ode/sampling/AbstractStepInterpolator.setSoftCurrentTime:(D)V (1, 3)
	504 aload (2, 1)
	505 #13 (2, 1)
	506 aload_1 (2, 1)
	507 invokevirtual (2, 1)
	508 org/apache/commons/math3/ode/events/EventState.evaluateStep:(Lorg/apache/commons/math3/ode/sampling/StepInterpolator;)Z (2, 1)
	510 ifeq (2, 1)
	511 13 (2, 1)
	513 aload (2, 1)
	514 #11 (2, 1)
	515 aload (2, 1)
	516 #13 (2, 1)
	517 invokeinterface (2, 1)
	518 java/util/SortedSet.java/util/Collections (2, 1)
	520 0 (2, 1)
	522 pop (2, 1)
	523 goto (0, 4)
	524 -369 (0, 4)
	526 aload_1 (0, 4)
	527 dload (0, 4)
	528 #8 (0, 4)
	529 invokevirtual (0, 4)
	530 org/apache/commons/math3/ode/sampling/AbstractStepInterpolator.setInterpolatedTime:(D)V (0, 4)
	532 aload_2 (0, 4)
	533 arraylength (0, 4)
	534 newarray (0, 4)
	535 7 (0, 4)
	536 astore (0, 4)
	537 #12 (0, 4)
	538 aload_0 (0, 4)
	539 getfield (0, 4)
	540 org/apache/commons/math3/ode/AbstractIntegrator.expandable:Lorg/apache/commons/math3/ode/ExpandableStatefulODE; (0, 4)
	542 invokevirtual (0, 4)
	543 org/apache/commons/math3/ode/ExpandableStatefulODE.getPrimaryMapper:()Lorg/apache/commons/math3/ode/EquationsMapper; (0, 4)
	545 aload_1 (0, 4)
	546 invokevirtual (0, 4)
	547 org/apache/commons/math3/ode/sampling/AbstractStepInterpolator.getInterpolatedState:()[D (0, 4)
	549 aload (0, 4)
	550 #12 (0, 4)
	551 invokevirtual (0, 4)
	552 org/apache/commons/math3/ode/EquationsMapper.insertEquationData:([D[D)V (0, 4)
	554 iconst_0 (0, 4)
	555 istore (0, 4)
	556 #13 (0, 4)
	557 aload_0 (1, 4)
	558 getfield (1, 4)
	559 org/apache/commons/math3/ode/AbstractIntegrator.expandable:Lorg/apache/commons/math3/ode/ExpandableStatefulODE; (1, 4)
	561 invokevirtual (1, 4)
	562 org/apache/commons/math3/ode/ExpandableStatefulODE.getSecondaryMappers:()[Lorg/apache/commons/math3/ode/EquationsMapper; (1, 4)
	564 astore (1, 4)
	565 #14 (1, 4)
	566 aload (1, 4)
	567 #14 (1, 4)
	568 arraylength (1, 4)
	569 istore (1, 4)
	570 #15 (1, 4)
	571 iconst_0 (1, 4)
	572 istore (1, 4)
	573 #16 (1, 4)
	574 iload (1, 4)
	575 #16 (1, 4)
	576 iload (1, 4)
	577 #15 (1, 4)
	578 if_icmpge (1, 4)
	579 32 (1, 4)
	581 aload (1, 4)
	582 #14 (1, 4)
	583 iload (1, 4)
	584 #16 (1, 4)
	585 aaload (1, 4)
	586 astore (1, 4)
	587 #17 (1, 4)
	588 aload (1, 4)
	589 #17 (1, 4)
	590 aload_1 (1, 4)
	591 iload (1, 4)
	592 #13 (1, 4)
	593 iinc (1, 4)
	594 #13 (1, 4)
	595 -74 (1, 4)
	596 invokevirtual (1, 4)
	597 org/apache/commons/math3/ode/sampling/AbstractStepInterpolator.getInterpolatedSecondaryState:(I)[D (1, 4)
	599 aload (1, 4)
	600 #12 (1, 4)
	601 invokevirtual (1, 4)
	602 org/apache/commons/math3/ode/EquationsMapper.insertEquationData:([D[D)V (1, 4)
	604 iinc (1, 4)
	605 #16 (1, 4)
	606 -89 (1, 4)
	607 goto (1, 4)
	608 -33 (1, 4)
	610 aload_0 (1, 4)
	611 getfield (1, 4)
	612 org/apache/commons/math3/ode/AbstractIntegrator.eventsStates:Ljava/util/Collection; (1, 4)
	614 invokeinterface (1, 4)
	615 java/util/Collection.java/util/Iterator (1, 4)
	617 0 (1, 4)
	619 astore (1, 4)
	620 #14 (1, 4)
	621 aload (1, 4)
	622 #14 (1, 4)
	623 invokeinterface (1, 4)
	624 java/util/Iterator.next:()Ljava/lang/Object; (1, 4)
	626 0 (1, 4)
	628 ifeq (1, 4)
	629 51 (1, 4)
	631 aload (1, 4)
	632 #14 (1, 4)
	633 invokeinterface (1, 4)
	634 java/util/Iterator.getEventHandler:()Lorg/apache/commons/math3/ode/events/EventHandler; (1, 4)
	636 0 (1, 4)
	638 checkcast (1, 4)
	639 org/apache/commons/math3/ode/events/EventState (1, 4)
	641 astore (1, 4)
	642 #15 (1, 4)
	643 aload (1, 4)
	644 #15 (1, 4)
	645 dload (1, 4)
	646 #8 (1, 4)
	647 aload (1, 4)
	648 #12 (1, 4)
	649 invokevirtual (1, 4)
	650 org/apache/commons/math3/ode/events/EventState.stepAccepted:(D[D)V (1, 4)
	652 aload_0 (1, 4)
	653 aload_0 (1, 4)
	654 getfield (1, 4)
	655 org/apache/commons/math3/ode/AbstractIntegrator.isLastStep:Z (1, 4)
	657 ifne (1, 4)
	658 11 (1, 4)
	660 aload (1, 4)
	661 #15 (1, 4)
	662 invokevirtual (1, 4)
	663 org/apache/commons/math3/ode/events/EventState.stop:()Z (1, 4)
	665 ifeq (1, 4)
	666 7 (1, 4)
	668 iconst_1 (1, 4)
	669 goto (1, 4)
	670 4 (1, 4)
	672 iconst_0 (1, 4)
	673 putfield (1, 4)
	674 org/apache/commons/math3/ode/AbstractIntegrator.isLastStep:Z (1, 4)
	676 goto (0, 4)
	677 -55 (0, 4)
	679 aload_0 (0, 4)
	680 aload_0 (0, 4)
	681 getfield (0, 4)
	682 org/apache/commons/math3/ode/AbstractIntegrator.isLastStep:Z (0, 4)
	684 ifne (0, 4)
	685 14 (0, 4)
	687 dload (0, 4)
	688 #8 (0, 4)
	689 dload (0, 4)
	690 #4 (0, 4)
	691 iconst_1 (0, 4)
	692 invokestatic (0, 4)
	693 org/apache/commons/math3/util/Precision.equals:(DDI)Z (0, 4)
	695 ifeq (0, 4)
	696 7 (0, 4)
	698 iconst_1 (0, 4)
	699 goto (0, 4)
	700 4 (0, 4)
	702 iconst_0 (0, 4)
	703 putfield (0, 4)
	704 org/apache/commons/math3/ode/AbstractIntegrator.isLastStep:Z (0, 4)
	706 aload_0 (1, 4)
	707 getfield (1, 4)
	708 org/apache/commons/math3/ode/AbstractIntegrator.stepHandlers:Ljava/util/Collection; (1, 4)
	710 invokeinterface (1, 4)
	711 java/util/Collection.java/util/Iterator (1, 4)
	713 0 (1, 4)
	715 astore (1, 4)
	716 #14 (1, 4)
	717 aload (1, 4)
	718 #14 (1, 4)
	719 invokeinterface (1, 4)
	720 java/util/Iterator.next:()Ljava/lang/Object; (1, 4)
	722 0 (1, 4)
	724 ifeq (1, 4)
	725 30 (1, 4)
	727 aload (1, 4)
	728 #14 (1, 4)
	729 invokeinterface (1, 4)
	730 java/util/Iterator.getEventHandler:()Lorg/apache/commons/math3/ode/events/EventHandler; (1, 4)
	732 0 (1, 4)
	734 checkcast (1, 4)
	735 org/apache/commons/math3/ode/sampling/StepHandler (1, 4)
	737 astore (1, 4)
	738 #15 (1, 4)
	739 aload (1, 4)
	740 #15 (1, 4)
	741 aload_1 (1, 4)
	742 aload_0 (1, 4)
	743 getfield (1, 4)
	744 org/apache/commons/math3/ode/AbstractIntegrator.isLastStep:Z (1, 4)
	746 invokeinterface (1, 4)
	747 org/apache/commons/math3/ode/sampling/StepHandler.resetOccurred:Z (1, 4)
	749 0 (1, 4)
	751 goto (0, 1)
	752 -34 (0, 1)
	754 dload (0, 1)
	755 #8 (0, 1)
	756 dreturn (0, 1)

Method: sanityChecks
	0 ldc2_w (0, 0)
	1 1000.0 (0, 0)
	3 aload_1 (0, 0)
	4 invokevirtual (0, 0)
	5 org/apache/commons/math3/ode/ExpandableStatefulODE.getTime:()D (0, 0)
	7 invokestatic (0, 0)
	8 org/apache/commons/math3/util/FastMath.abs:(D)D (0, 0)
	10 dload_2 (0, 0)
	11 invokestatic (0, 0)
	12 org/apache/commons/math3/util/FastMath.abs:(D)D (0, 0)
	14 invokestatic (0, 0)
	15 org/apache/commons/math3/util/FastMath.max:(DD)D (0, 0)
	17 invokestatic (0, 0)
	18 org/apache/commons/math3/util/FastMath.ulp:(D)D (0, 0)
	20 dmul (0, 0)
	21 dstore (0, 0)
	22 #4 (0, 0)
	23 aload_1 (0, 0)
	24 invokevirtual (0, 0)
	25 org/apache/commons/math3/ode/ExpandableStatefulODE.getTime:()D (0, 0)
	27 dload_2 (0, 0)
	28 dsub (0, 0)
	29 invokestatic (0, 0)
	30 org/apache/commons/math3/util/FastMath.abs:(D)D (0, 0)
	32 dstore (0, 0)
	33 #6 (0, 0)
	34 dload (1, 1)
	35 #6 (1, 1)
	36 dload (1, 1)
	37 #4 (1, 1)
	38 dcmpg (1, 1)
	39 ifgt (1, 1)
	40 25 (1, 1)
	42 new (1, 1)
	43 org/apache/commons/math3/exception/NumberIsTooSmallException (1, 1)
	45 dup (1, 1)
	46 getstatic (1, 1)
	47 org/apache/commons/math3/exception/util/LocalizedFormats.TOO_SMALL_INTEGRATION_INTERVAL:Lorg/apache/commons/math3/exception/util/LocalizedFormats; (1, 1)
	49 dload (1, 1)
	50 #6 (1, 1)
	51 invokestatic (1, 1)
	52 java/lang/Double.valueOf:(D)Ljava/lang/Double; (1, 1)
	54 dload (1, 1)
	55 #4 (1, 1)
	56 invokestatic (1, 1)
	57 java/lang/Double.valueOf:(D)Ljava/lang/Double; (1, 1)
	59 iconst_0 (1, 1)
	60 invokespecial (1, 1)
	61 org/apache/commons/math3/exception/NumberIsTooSmallException.<init>:(Lorg/apache/commons/math3/exception/util/Localizable;Ljava/lang/Number;Ljava/lang/Number;Z)V (1, 1)
	63 athrow (1, 1)
	64 return (0, 0)

