Method: <init>
	0 aload_0 (0, 0)
	1 invokespecial (0, 0)
	4 aload_0 (0, 0)
	5 aload_1 (0, 0)
	6 putfield (0, 0)
	9 aload_0 (0, 0)
	10 aload_2 (0, 0)
	11 putfield (0, 0)
	14 aload_0 (0, 0)
	15 new (0, 0)
	18 dup (0, 0)
	19 invokespecial (0, 0)
	22 putfield (0, 0)
	25 aload_0 (0, 0)
	26 aconst_null (0, 0)
	27 putfield (0, 0)
	30 aload_0 (0, 0)
	31 aconst_null (0, 0)
	32 putfield (0, 0)
	35 aload_0 (0, 0)
	36 new (0, 0)
	39 dup (0, 0)
	40 invokespecial (0, 0)
	43 putfield (0, 0)
	46 aload_0 (0, 0)
	47 iconst_0 (0, 0)
	48 putfield (0, 0)
	51 aload_0 (0, 0)
	52 invokestatic (0, 0)
	55 ldc (0, 0)
	57 invokevirtual (0, 0)
	60 putfield (0, 0)
	63 return (0, 0)

Method: getField
	0 aload_0 (0, 0)
	1 getfield (0, 0)
	4 areturn (0, 0)

Method: getName
	0 aload_0 (0, 0)
	1 getfield (0, 0)
	4 areturn (0, 0)

Method: addStepHandler
	0 aload_0 (0, 0)
	1 getfield (0, 0)
	4 aload_1 (0, 0)
	5 invokeinterface (0, 0)
	10 pop (0, 0)
	11 return (0, 0)

Method: getStepHandlers
	0 aload_0 (0, 1)
	1 getfield (0, 1)
	4 invokestatic (0, 1)
	7 areturn (0, 1)

Method: clearStepHandlers
	0 aload_0 (0, 0)
	1 getfield (0, 0)
	4 invokeinterface (0, 0)
	9 return (0, 0)

Method: addEventHandler
	0 aload_0 (0, 0)
	1 getfield (0, 0)
	4 new (0, 0)
	7 dup (0, 0)
	8 aload_1 (0, 0)
	9 dload_2 (0, 0)
	10 aload_0 (0, 0)
	11 getfield (0, 0)
	14 invokeinterface (0, 0)
	19 checkcast (0, 0)
	22 dload (0, 0)
	24 invokeinterface (0, 0)
	29 checkcast (0, 0)
	32 iload (0, 0)
	34 aload (0, 0)
	36 invokespecial (0, 0)
	39 invokeinterface (0, 0)
	44 pop (0, 0)
	45 return (0, 0)

Method: getEventHandlers
	0 new (0, 0)
	3 dup (0, 0)
	4 aload_0 (0, 0)
	5 getfield (0, 0)
	8 invokeinterface (0, 0)
	13 invokespecial (0, 0)
	16 astore_1 (0, 0)
	17 aload_0 (1, 4)
	18 getfield (1, 4)
	21 invokeinterface (1, 4)
	26 astore_2 (1, 4)
	27 aload_2 (1, 4)
	28 invokeinterface (1, 4)
	33 ifeq (1, 4)
	36 aload_2 (1, 4)
	37 invokeinterface (1, 4)
	42 checkcast (1, 4)
	45 astore_3 (1, 4)
	46 aload_1 (1, 4)
	47 aload_3 (1, 4)
	48 invokevirtual (1, 4)
	51 invokeinterface (1, 4)
	56 pop (1, 4)
	57 goto (0, 0)
	60 aload_1 (0, 1)
	61 invokestatic (0, 1)
	64 areturn (0, 1)

Method: clearEventHandlers
	0 aload_0 (0, 0)
	1 getfield (0, 0)
	4 invokeinterface (0, 0)
	9 return (0, 0)

Method: getCurrentStepStart
	0 aload_0 (0, 0)
	1 getfield (0, 0)
	4 areturn (0, 0)

Method: getCurrentSignedStepsize
	0 aload_0 (0, 0)
	1 getfield (0, 0)
	4 areturn (0, 0)

Method: setMaxEvaluations
	0 aload_0 (0, 0)
	1 aload_0 (0, 0)
	2 getfield (0, 0)
	5 iload_1 (0, 0)
	6 ifge (0, 0)
	9 ldc (0, 0)
	11 goto (0, 0)
	14 iload_1 (0, 0)
	15 invokevirtual (0, 0)
	18 putfield (0, 0)
	21 return (0, 0)

Method: getMaxEvaluations
	0 aload_0 (0, 0)
	1 getfield (0, 0)
	4 invokevirtual (0, 0)
	7 ireturn (0, 0)

Method: getEvaluations
	0 aload_0 (0, 0)
	1 getfield (0, 0)
	4 invokevirtual (0, 0)
	7 ireturn (0, 0)

Method: initIntegration
	0 aload_0 (0, 0)
	1 aload_1 (0, 0)
	2 putfield (0, 0)
	5 aload_0 (0, 0)
	6 aload_0 (0, 0)
	7 getfield (0, 0)
	10 iconst_0 (0, 0)
	11 invokevirtual (0, 0)
	14 putfield (0, 0)
	17 aload_1 (0, 0)
	18 aload_2 (0, 0)
	19 aload_3 (0, 0)
	20 aload (0, 0)
	22 invokevirtual (0, 0)
	25 aload_0 (0, 0)
	26 aload_2 (0, 0)
	27 aload_3 (0, 0)
	28 invokevirtual (0, 0)
	31 astore (0, 0)
	33 new (0, 0)
	36 dup (0, 0)
	37 aload_2 (0, 0)
	38 aload_3 (0, 0)
	39 aload (0, 0)
	41 invokespecial (0, 0)
	44 astore (0, 0)
	46 aload_0 (1, 4)
	47 getfield (1, 4)
	50 invokeinterface (1, 4)
	55 astore (1, 4)
	57 aload (1, 4)
	59 invokeinterface (1, 4)
	64 ifeq (1, 4)
	67 aload (1, 4)
	69 invokeinterface (1, 4)
	74 checkcast (1, 4)
	77 astore (1, 4)
	79 aload (1, 4)
	81 invokevirtual (1, 4)
	84 aload (1, 4)
	86 aload (1, 4)
	88 invokeinterface (1, 4)
	93 goto (0, 0)
	96 aload_0 (1, 4)
	97 getfield (1, 4)
	100 invokeinterface (1, 4)
	105 astore (1, 4)
	107 aload (1, 4)
	109 invokeinterface (1, 4)
	114 ifeq (1, 4)
	117 aload (1, 4)
	119 invokeinterface (1, 4)
	124 checkcast (1, 4)
	127 astore (1, 4)
	129 aload (1, 4)
	131 aload (1, 4)
	133 aload (1, 4)
	135 invokeinterface (1, 4)
	140 goto (0, 0)
	143 aload_0 (0, 0)
	144 iconst_0 (0, 0)
	145 invokevirtual (0, 0)
	148 aload (0, 0)
	150 areturn (0, 0)

Method: getEquations
	0 aload_0 (0, 0)
	1 getfield (0, 0)
	4 areturn (0, 0)

Method: getEvaluationsCounter
	0 aload_0 (0, 0)
	1 getfield (0, 0)
	4 areturn (0, 0)

Method: computeDerivatives
	0 aload_0 (0, 0)
	1 getfield (0, 0)
	4 invokevirtual (0, 0)
	7 aload_0 (0, 0)
	8 getfield (0, 0)
	11 aload_1 (0, 0)
	12 aload_2 (0, 0)
	13 invokevirtual (0, 0)
	16 areturn (0, 0)

Method: setStateInitialized
	0 aload_0 (0, 0)
	1 iload_1 (0, 0)
	2 putfield (0, 0)
	5 return (0, 0)

Method: acceptStep
	0 aload_1 (0, 0)
	1 invokevirtual (0, 0)
	4 astore_3 (0, 0)
	5 aload_1 (0, 0)
	6 invokevirtual (0, 0)
	9 astore (0, 0)
	11 aload_0 (1, 1)
	12 getfield (1, 1)
	15 ifne (1, 1)
	18 aload_0 (2, 4)
	19 getfield (2, 4)
	22 invokeinterface (2, 4)
	27 astore (2, 4)
	29 aload (2, 4)
	31 invokeinterface (2, 4)
	36 ifeq (2, 4)
	39 aload (2, 4)
	41 invokeinterface (2, 4)
	46 checkcast (2, 4)
	49 astore (2, 4)
	51 aload (2, 4)
	53 aload_1 (2, 4)
	54 invokevirtual (2, 4)
	57 goto (1, 1)
	60 aload_0 (1, 1)
	61 iconst_1 (1, 1)
	62 putfield (1, 1)
	65 aload_1 (0, 4)
	66 invokevirtual (0, 4)
	69 ifeq (0, 4)
	72 iconst_1 (0, 4)
	73 goto (0, 4)
	76 iconst_m1 (0, 4)
	77 istore (0, 4)
	79 new (1, 4)
	82 dup (1, 4)
	83 new (1, 4)
	86 dup (1, 4)
	87 aload_0 (1, 4)
	88 iload (1, 4)
	90 invokespecial (1, 4)
	93 invokespecial (1, 4)
	96 astore (1, 4)
	98 aload_0 (1, 4)
	99 getfield (1, 4)
	102 invokeinterface (1, 4)
	107 astore (1, 4)
	109 aload (1, 4)
	111 invokeinterface (1, 4)
	116 ifeq (1, 4)
	119 aload (1, 4)
	121 invokeinterface (1, 4)
	126 checkcast (1, 4)
	129 astore (1, 4)
	131 aload (2, 1)
	133 aload_1 (2, 1)
	134 invokevirtual (2, 1)
	137 ifeq (2, 1)
	140 aload (2, 1)
	142 aload (2, 1)
	144 invokeinterface (2, 1)
	149 pop (2, 1)
	150 goto (0, 0)
	153 aload_1 (0, 0)
	154 astore (0, 0)
	156 aload (1, 3)
	158 invokeinterface (1, 3)
	163 ifne (1, 3)
	166 aload (1, 3)
	168 invokeinterface (1, 3)
	173 astore (1, 3)
	175 aload (1, 3)
	177 invokeinterface (1, 3)
	182 checkcast (1, 3)
	185 astore (1, 3)
	187 aload (1, 3)
	189 invokeinterface (1, 3)
	194 aload (1, 3)
	196 aload (1, 3)
	198 invokevirtual (1, 3)
	201 invokevirtual (1, 3)
	204 astore (1, 3)
	206 aload (1, 3)
	208 aload_3 (1, 3)
	209 aload (1, 3)
	211 invokevirtual (1, 3)
	214 astore (1, 3)
	216 aload_0 (2, 4)
	217 getfield (2, 4)
	220 invokeinterface (2, 4)
	225 astore (2, 4)
	227 aload (2, 4)
	229 invokeinterface (2, 4)
	234 ifeq (2, 4)
	237 aload (2, 4)
	239 invokeinterface (2, 4)
	244 checkcast (2, 4)
	247 astore (2, 4)
	249 aload (2, 4)
	251 aload (2, 4)
	253 invokevirtual (2, 4)
	256 aload_0 (2, 4)
	257 aload_0 (2, 4)
	258 getfield (2, 4)
	261 ifne (2, 4)
	264 aload (2, 4)
	266 invokevirtual (2, 4)
	269 ifeq (2, 4)
	272 iconst_1 (2, 4)
	273 goto (2, 4)
	276 iconst_0 (2, 4)
	277 putfield (2, 4)
	280 goto (1, 3)
	283 aload_0 (2, 4)
	284 getfield (2, 4)
	287 invokeinterface (2, 4)
	292 astore (2, 4)
	294 aload (2, 4)
	296 invokeinterface (2, 4)
	301 ifeq (2, 4)
	304 aload (2, 4)
	306 invokeinterface (2, 4)
	311 checkcast (2, 4)
	314 astore (2, 4)
	316 aload (2, 4)
	318 aload (2, 4)
	320 aload_0 (2, 4)
	321 getfield (2, 4)
	324 invokeinterface (2, 4)
	329 goto (1, 3)
	332 aload_0 (2, 1)
	333 getfield (2, 1)
	336 ifeq (2, 1)
	339 aload (2, 1)
	341 areturn (2, 1)
	342 aconst_null (1, 3)
	343 astore (1, 3)
	345 aload_0 (1, 3)
	346 iconst_0 (1, 3)
	347 putfield (1, 3)
	350 aload_0 (2, 4)
	351 getfield (2, 4)
	354 invokeinterface (2, 4)
	359 astore (2, 4)
	361 aload (2, 4)
	363 invokeinterface (2, 4)
	368 ifeq (2, 4)
	371 aload (2, 4)
	373 invokeinterface (2, 4)
	378 checkcast (2, 4)
	381 astore (2, 4)
	383 aload (2, 4)
	385 aload (2, 4)
	387 invokevirtual (2, 4)
	390 astore (2, 4)
	392 aload (3, 1)
	394 ifnull (3, 1)
	397 aload_0 (3, 1)
	398 getfield (3, 1)
	401 invokevirtual (3, 1)
	404 aload (3, 1)
	406 invokevirtual (3, 1)
	409 astore (3, 1)
	411 aload_0 (3, 1)
	412 aload (3, 1)
	414 invokevirtual (3, 1)
	417 aload (3, 1)
	419 invokevirtual (3, 1)
	422 astore (3, 1)
	424 aload_0 (3, 1)
	425 iconst_1 (3, 1)
	426 putfield (3, 1)
	429 aload_0 (3, 1)
	430 getfield (3, 1)
	433 invokevirtual (3, 1)
	436 aload (3, 1)
	438 invokevirtual (3, 1)
	441 aload (3, 1)
	443 aload (3, 1)
	445 invokevirtual (3, 1)
	448 areturn (3, 1)
	449 goto (1, 3)
	452 aload (1, 3)
	454 astore_3 (1, 3)
	455 aload (1, 3)
	457 aload (1, 3)
	459 aload (1, 3)
	461 invokevirtual (1, 3)
	464 astore (1, 3)
	466 aload (2, 1)
	468 aload (2, 1)
	470 invokevirtual (2, 1)
	473 ifeq (2, 1)
	476 aload (2, 1)
	478 aload (2, 1)
	480 invokeinterface (2, 1)
	485 pop (2, 1)
	486 goto (0, 3)
	489 aload_0 (1, 4)
	490 getfield (1, 4)
	493 invokeinterface (1, 4)
	498 astore (1, 4)
	500 aload (1, 4)
	502 invokeinterface (1, 4)
	507 ifeq (1, 4)
	510 aload (1, 4)
	512 invokeinterface (1, 4)
	517 checkcast (1, 4)
	520 astore (1, 4)
	522 aload (1, 4)
	524 aload (1, 4)
	526 invokevirtual (1, 4)
	529 aload_0 (1, 4)
	530 aload_0 (1, 4)
	531 getfield (1, 4)
	534 ifne (1, 4)
	537 aload (1, 4)
	539 invokevirtual (1, 4)
	542 ifeq (1, 4)
	545 iconst_1 (1, 4)
	546 goto (1, 4)
	549 iconst_0 (1, 4)
	550 putfield (1, 4)
	553 goto (0, 3)
	556 aload_0 (0, 3)
	557 aload_0 (0, 3)
	558 getfield (0, 3)
	561 ifne (0, 3)
	564 aload (0, 3)
	566 invokevirtual (0, 3)
	569 aload_2 (0, 3)
	570 invokeinterface (0, 3)
	575 checkcast (0, 3)
	578 invokeinterface (0, 3)
	583 checkcast (0, 3)
	586 invokeinterface (0, 3)
	591 aload_2 (0, 3)
	592 invokeinterface (0, 3)
	597 invokestatic (0, 3)
	600 dcmpg (0, 3)
	601 ifgt (0, 3)
	604 iconst_1 (0, 3)
	605 goto (0, 3)
	608 iconst_0 (0, 3)
	609 putfield (0, 3)
	612 aload_0 (1, 4)
	613 getfield (1, 4)
	616 invokeinterface (1, 4)
	621 astore (1, 4)
	623 aload (1, 4)
	625 invokeinterface (1, 4)
	630 ifeq (1, 4)
	633 aload (1, 4)
	635 invokeinterface (1, 4)
	640 checkcast (1, 4)
	643 astore (1, 4)
	645 aload (1, 4)
	647 aload (1, 4)
	649 aload_0 (1, 4)
	650 getfield (1, 4)
	653 invokeinterface (1, 4)
	658 goto (0, 1)
	661 aload (0, 1)
	663 areturn (0, 1)

Method: sanityChecks
	0 ldc2_w (0, 0)
	3 aload_1 (0, 0)
	4 invokevirtual (0, 0)
	7 invokeinterface (0, 0)
	12 invokestatic (0, 0)
	15 aload_2 (0, 0)
	16 invokeinterface (0, 0)
	21 invokestatic (0, 0)
	24 invokestatic (0, 0)
	27 invokestatic (0, 0)
	30 dmul (0, 0)
	31 dstore_3 (0, 0)
	32 aload_1 (0, 0)
	33 invokevirtual (0, 0)
	36 aload_2 (0, 0)
	37 invokeinterface (0, 0)
	42 checkcast (0, 0)
	45 invokeinterface (0, 0)
	50 checkcast (0, 0)
	53 invokeinterface (0, 0)
	58 dstore (0, 0)
	60 dload (1, 1)
	62 dload_3 (1, 1)
	63 dcmpg (1, 1)
	64 ifgt (1, 1)
	67 new (1, 1)
	70 dup (1, 1)
	71 getstatic (1, 1)
	74 dload (1, 1)
	76 invokestatic (1, 1)
	79 dload_3 (1, 1)
	80 invokestatic (1, 1)
	83 iconst_0 (1, 1)
	84 invokespecial (1, 1)
	87 athrow (1, 1)
	88 return (0, 0)

Method: resetOccurred
	0 aload_0 (0, 0)
	1 getfield (0, 0)
	4 ireturn (0, 0)

Method: setStepSize
	0 aload_0 (0, 0)
	1 aload_1 (0, 0)
	2 putfield (0, 0)
	5 return (0, 0)

Method: getStepSize
	0 aload_0 (0, 0)
	1 getfield (0, 0)
	4 areturn (0, 0)

Method: setStepStart
	0 aload_0 (0, 0)
	1 aload_1 (0, 0)
	2 putfield (0, 0)
	5 return (0, 0)

Method: getStepStart
	0 aload_0 (0, 0)
	1 getfield (0, 0)
	4 areturn (0, 0)

Method: setIsLastStep
	0 aload_0 (0, 0)
	1 iload_1 (0, 0)
	2 putfield (0, 0)
	5 return (0, 0)

Method: isLastStep
	0 aload_0 (0, 0)
	1 getfield (0, 0)
	4 ireturn (0, 0)

