Method: <init>
	0 aload_0 (0, 0)
	1 aconst_null (0, 0)
	2 invokespecial (0, 0)
	5 return (0, 0)

Method: getName
	0 aload_0 (0, 0)
	1 getfield (0, 0)
	4 areturn (0, 0)

Method: addStepHandler
	0 aload_0 (0, 0)
	1 getfield (0, 0)
	4 aload_1 (0, 0)
	5 invokeinterface (0, 0)
	10 pop (0, 0)
	11 return (0, 0)

Method: getStepHandlers
	0 aload_0 (0, 1)
	1 getfield (0, 1)
	4 invokestatic (0, 1)
	7 areturn (0, 1)

Method: clearStepHandlers
	0 aload_0 (0, 0)
	1 getfield (0, 0)
	4 invokeinterface (0, 0)
	9 return (0, 0)

Method: addEventHandler
	0 aload_0 (0, 0)
	1 getfield (0, 0)
	4 new (0, 0)
	7 dup (0, 0)
	8 aload_1 (0, 0)
	9 dload_2 (0, 0)
	10 dload (0, 0)
	12 iload (0, 0)
	14 aload (0, 0)
	16 invokespecial (0, 0)
	19 invokeinterface (0, 0)
	24 pop (0, 0)
	25 return (0, 0)

Method: getEventHandlers
	0 new (0, 0)
	3 dup (0, 0)
	4 aload_0 (0, 0)
	5 getfield (0, 0)
	8 invokeinterface (0, 0)
	13 invokespecial (0, 0)
	16 astore_1 (0, 0)
	17 aload_0 (1, 4)
	18 getfield (1, 4)
	21 invokeinterface (1, 4)
	26 astore_2 (1, 4)
	27 aload_2 (1, 4)
	28 invokeinterface (1, 4)
	33 ifeq (1, 4)
	36 aload_2 (1, 4)
	37 invokeinterface (1, 4)
	42 checkcast (1, 4)
	45 astore_3 (1, 4)
	46 aload_1 (1, 4)
	47 aload_3 (1, 4)
	48 invokevirtual (1, 4)
	51 invokeinterface (1, 4)
	56 pop (1, 4)
	57 goto (0, 0)
	60 aload_1 (0, 1)
	61 invokestatic (0, 1)
	64 areturn (0, 1)

Method: clearEventHandlers
	0 aload_0 (0, 0)
	1 getfield (0, 0)
	4 invokeinterface (0, 0)
	9 return (0, 0)

Method: getCurrentStepStart
	0 aload_0 (0, 0)
	1 getfield (0, 0)
	4 dreturn (0, 0)

Method: getCurrentSignedStepsize
	0 aload_0 (0, 0)
	1 getfield (0, 0)
	4 dreturn (0, 0)

Method: setMaxEvaluations
	0 aload_0 (0, 0)
	1 aload_0 (0, 0)
	2 getfield (0, 0)
	5 iload_1 (0, 0)
	6 ifge (0, 0)
	9 ldc (0, 0)
	11 goto (0, 0)
	14 iload_1 (0, 0)
	15 invokevirtual (0, 0)
	18 putfield (0, 0)
	21 return (0, 0)

Method: getMaxEvaluations
	0 aload_0 (0, 0)
	1 getfield (0, 0)
	4 invokevirtual (0, 0)
	7 ireturn (0, 0)

Method: getEvaluations
	0 aload_0 (0, 0)
	1 getfield (0, 0)
	4 invokevirtual (0, 0)
	7 ireturn (0, 0)

Method: initIntegration
	0 aload_0 (0, 0)
	1 aload_0 (0, 0)
	2 getfield (0, 0)
	5 iconst_0 (0, 0)
	6 invokevirtual (0, 0)
	9 putfield (0, 0)
	12 aload_0 (1, 4)
	13 getfield (1, 4)
	16 invokeinterface (1, 4)
	21 astore (1, 4)
	23 aload (1, 4)
	25 invokeinterface (1, 4)
	30 ifeq (1, 4)
	33 aload (1, 4)
	35 invokeinterface (1, 4)
	40 checkcast (1, 4)
	43 astore (1, 4)
	45 aload (1, 4)
	47 aload_0 (1, 4)
	48 getfield (1, 4)
	51 invokevirtual (1, 4)
	54 aload (1, 4)
	56 invokevirtual (1, 4)
	59 dload_1 (1, 4)
	60 aload_3 (1, 4)
	61 dload (1, 4)
	63 invokeinterface (1, 4)
	68 goto (0, 0)
	71 aload_0 (1, 4)
	72 getfield (1, 4)
	75 invokeinterface (1, 4)
	80 astore (1, 4)
	82 aload (1, 4)
	84 invokeinterface (1, 4)
	89 ifeq (1, 4)
	92 aload (1, 4)
	94 invokeinterface (1, 4)
	99 checkcast (1, 4)
	102 astore (1, 4)
	104 aload (1, 4)
	106 dload_1 (1, 4)
	107 aload_3 (1, 4)
	108 dload (1, 4)
	110 invokeinterface (1, 4)
	115 goto (0, 0)
	118 aload_0 (0, 0)
	119 iconst_0 (0, 0)
	120 invokevirtual (0, 0)
	123 return (0, 0)

Method: setEquations
	0 aload_0 (0, 0)
	1 aload_1 (0, 0)
	2 putfield (0, 0)
	5 return (0, 0)

Method: getExpandable
	0 aload_0 (0, 0)
	1 getfield (0, 0)
	4 areturn (0, 0)

Method: getEvaluationsCounter
	0 aload_0 (0, 0)
	1 getfield (0, 0)
	4 invokestatic (0, 0)
	7 areturn (0, 0)

Method: getCounter
	0 aload_0 (0, 0)
	1 getfield (0, 0)
	4 areturn (0, 0)

Method: integrate
	0 aload (1, 1)
	2 arraylength (1, 1)
	3 aload_1 (1, 1)
	4 invokeinterface (1, 1)
	9 if_icmpeq (1, 1)
	12 new (1, 1)
	15 dup (1, 1)
	16 aload (1, 1)
	18 arraylength (1, 1)
	19 aload_1 (1, 1)
	20 invokeinterface (1, 1)
	25 invokespecial (1, 1)
	28 athrow (1, 1)
	29 aload (1, 1)
	31 arraylength (1, 1)
	32 aload_1 (1, 1)
	33 invokeinterface (1, 1)
	38 if_icmpeq (1, 1)
	41 new (1, 1)
	44 dup (1, 1)
	45 aload (1, 1)
	47 arraylength (1, 1)
	48 aload_1 (1, 1)
	49 invokeinterface (1, 1)
	54 invokespecial (1, 1)
	57 athrow (1, 1)
	58 new (0, 0)
	61 dup (0, 0)
	62 aload_1 (0, 0)
	63 invokespecial (0, 0)
	66 astore (0, 0)
	68 aload (0, 0)
	70 dload_2 (0, 0)
	71 invokevirtual (0, 0)
	74 aload (0, 0)
	76 aload (0, 0)
	78 invokevirtual (0, 0)
	81 aload_0 (0, 4)
	82 aload (0, 4)
	84 dload (0, 4)
	86 invokevirtual (0, 4)
	89 aload (0, 4)
	91 invokevirtual (0, 4)
	94 iconst_0 (0, 4)
	95 aload (0, 4)
	97 iconst_0 (0, 4)
	98 aload (0, 4)
	100 arraylength (0, 4)
	101 invokestatic (0, 4)
	104 aload (0, 4)
	106 invokevirtual (0, 4)
	109 dreturn (0, 4)

Method: computeDerivatives
	0 aload_0 (0, 0)
	1 getfield (0, 0)
	4 invokevirtual (0, 0)
	7 aload_0 (0, 0)
	8 getfield (0, 0)
	11 dload_1 (0, 0)
	12 aload_3 (0, 0)
	13 aload (0, 0)
	15 invokevirtual (0, 0)
	18 return (0, 0)

Method: setStateInitialized
	0 aload_0 (0, 0)
	1 iload_1 (0, 0)
	2 putfield (0, 0)
	5 return (0, 0)

Method: acceptStep
	0 aload_1 (0, 0)
	1 invokevirtual (0, 0)
	4 dstore (0, 0)
	6 aload_1 (0, 0)
	7 invokevirtual (0, 0)
	10 dstore (0, 0)
	12 aload_0 (1, 1)
	13 getfield (1, 1)
	16 ifne (1, 1)
	19 aload_0 (2, 4)
	20 getfield (2, 4)
	23 invokeinterface (2, 4)
	28 astore (2, 4)
	30 aload (2, 4)
	32 invokeinterface (2, 4)
	37 ifeq (2, 4)
	40 aload (2, 4)
	42 invokeinterface (2, 4)
	47 checkcast (2, 4)
	50 astore (2, 4)
	52 aload (2, 4)
	54 aload_1 (2, 4)
	55 invokevirtual (2, 4)
	58 goto (1, 1)
	61 aload_0 (1, 1)
	62 iconst_1 (1, 1)
	63 putfield (1, 1)
	66 aload_1 (0, 4)
	67 invokevirtual (0, 4)
	70 ifeq (0, 4)
	73 iconst_1 (0, 4)
	74 goto (0, 4)
	77 iconst_m1 (0, 4)
	78 istore (0, 4)
	80 new (1, 4)
	83 dup (1, 4)
	84 new (1, 4)
	87 dup (1, 4)
	88 aload_0 (1, 4)
	89 iload (1, 4)
	91 invokespecial (1, 4)
	94 invokespecial (1, 4)
	97 astore (1, 4)
	99 aload_0 (1, 4)
	100 getfield (1, 4)
	103 invokeinterface (1, 4)
	108 astore (1, 4)
	110 aload (1, 4)
	112 invokeinterface (1, 4)
	117 ifeq (1, 4)
	120 aload (1, 4)
	122 invokeinterface (1, 4)
	127 checkcast (1, 4)
	130 astore (1, 4)
	132 aload (2, 1)
	134 aload_1 (2, 1)
	135 invokevirtual (2, 1)
	138 ifeq (2, 1)
	141 aload (2, 1)
	143 aload (2, 1)
	145 invokeinterface (2, 1)
	150 pop (2, 1)
	151 goto (0, 0)
	154 aload (1, 3)
	156 invokeinterface (1, 3)
	161 ifne (1, 3)
	164 aload (1, 3)
	166 invokeinterface (1, 3)
	171 astore (1, 3)
	173 aload (1, 3)
	175 invokeinterface (1, 3)
	180 checkcast (1, 3)
	183 astore (1, 3)
	185 aload (1, 3)
	187 invokeinterface (1, 3)
	192 aload (1, 3)
	194 invokevirtual (1, 3)
	197 dstore (1, 3)
	199 aload_1 (1, 3)
	200 dload (1, 3)
	202 invokevirtual (1, 3)
	205 aload_1 (1, 3)
	206 dload (1, 3)
	208 invokevirtual (1, 3)
	211 aload_1 (1, 3)
	212 dload (1, 3)
	214 invokevirtual (1, 3)
	217 aload_2 (1, 3)
	218 arraylength (1, 3)
	219 newarray (1, 3)
	221 astore (1, 3)
	223 aload_0 (1, 3)
	224 getfield (1, 3)
	227 invokevirtual (1, 3)
	230 aload_1 (1, 3)
	231 invokevirtual (1, 3)
	234 aload (1, 3)
	236 invokevirtual (1, 3)
	239 iconst_0 (1, 3)
	240 istore (1, 3)
	242 aload_0 (2, 4)
	243 getfield (2, 4)
	246 invokevirtual (2, 4)
	249 astore (2, 4)
	251 aload (2, 4)
	253 arraylength (2, 4)
	254 istore (2, 4)
	256 iconst_0 (2, 4)
	257 istore (2, 4)
	259 iload (2, 4)
	261 iload (2, 4)
	263 if_icmpge (2, 4)
	266 aload (2, 4)
	268 iload (2, 4)
	270 aaload (2, 4)
	271 astore (2, 4)
	273 aload (2, 4)
	275 aload_1 (2, 4)
	276 iload (2, 4)
	278 iinc (2, 4)
	281 invokevirtual (2, 4)
	284 aload (2, 4)
	286 invokevirtual (2, 4)
	289 iinc (2, 4)
	292 goto (2, 4)
	295 aload_0 (2, 4)
	296 getfield (2, 4)
	299 invokeinterface (2, 4)
	304 astore (2, 4)
	306 aload (2, 4)
	308 invokeinterface (2, 4)
	313 ifeq (2, 4)
	316 aload (2, 4)
	318 invokeinterface (2, 4)
	323 checkcast (2, 4)
	326 astore (2, 4)
	328 aload (2, 4)
	330 dload (2, 4)
	332 aload (2, 4)
	334 invokevirtual (2, 4)
	337 aload_0 (2, 4)
	338 aload_0 (2, 4)
	339 getfield (2, 4)
	342 ifne (2, 4)
	345 aload (2, 4)
	347 invokevirtual (2, 4)
	350 ifeq (2, 4)
	353 iconst_1 (2, 4)
	354 goto (2, 4)
	357 iconst_0 (2, 4)
	358 putfield (2, 4)
	361 goto (1, 3)
	364 aload_0 (2, 4)
	365 getfield (2, 4)
	368 invokeinterface (2, 4)
	373 astore (2, 4)
	375 aload (2, 4)
	377 invokeinterface (2, 4)
	382 ifeq (2, 4)
	385 aload (2, 4)
	387 invokeinterface (2, 4)
	392 checkcast (2, 4)
	395 astore (2, 4)
	397 aload (2, 4)
	399 aload_1 (2, 4)
	400 aload_0 (2, 4)
	401 getfield (2, 4)
	404 invokeinterface (2, 4)
	409 goto (1, 3)
	412 aload_0 (2, 1)
	413 getfield (2, 1)
	416 ifeq (2, 1)
	419 aload (2, 1)
	421 iconst_0 (2, 1)
	422 aload_2 (2, 1)
	423 iconst_0 (2, 1)
	424 aload_2 (2, 1)
	425 arraylength (2, 1)
	426 invokestatic (2, 1)
	429 dload (2, 1)
	431 dreturn (2, 1)
	432 iconst_0 (1, 3)
	433 istore (1, 3)
	435 aload_0 (1, 3)
	436 iconst_0 (1, 3)
	437 putfield (1, 3)
	440 aload (1, 3)
	442 dload (1, 3)
	444 aload (1, 3)
	446 invokevirtual (1, 3)
	449 istore (1, 3)
	451 iload (2, 1)
	453 ifeq (2, 1)
	456 aload_1 (2, 1)
	457 dload (2, 1)
	459 invokevirtual (2, 1)
	462 aload (2, 1)
	464 iconst_0 (2, 1)
	465 aload_2 (2, 1)
	466 iconst_0 (2, 1)
	467 aload_2 (2, 1)
	468 arraylength (2, 1)
	469 invokestatic (2, 1)
	472 aload_0 (2, 1)
	473 dload (2, 1)
	475 aload_2 (2, 1)
	476 aload_3 (2, 1)
	477 invokevirtual (2, 1)
	480 aload_0 (2, 1)
	481 iconst_1 (2, 1)
	482 putfield (2, 1)
	485 dload (2, 1)
	487 dreturn (2, 1)
	488 dload (1, 3)
	490 dstore (1, 3)
	492 aload_1 (1, 3)
	493 dload (1, 3)
	495 invokevirtual (1, 3)
	498 aload_1 (1, 3)
	499 dload (1, 3)
	501 invokevirtual (1, 3)
	504 aload (2, 1)
	506 aload_1 (2, 1)
	507 invokevirtual (2, 1)
	510 ifeq (2, 1)
	513 aload (2, 1)
	515 aload (2, 1)
	517 invokeinterface (2, 1)
	522 pop (2, 1)
	523 goto (0, 3)
	526 aload_1 (0, 3)
	527 dload (0, 3)
	529 invokevirtual (0, 3)
	532 aload_2 (0, 3)
	533 arraylength (0, 3)
	534 newarray (0, 3)
	536 astore (0, 3)
	538 aload_0 (0, 3)
	539 getfield (0, 3)
	542 invokevirtual (0, 3)
	545 aload_1 (0, 3)
	546 invokevirtual (0, 3)
	549 aload (0, 3)
	551 invokevirtual (0, 3)
	554 iconst_0 (0, 3)
	555 istore (0, 3)
	557 aload_0 (1, 4)
	558 getfield (1, 4)
	561 invokevirtual (1, 4)
	564 astore (1, 4)
	566 aload (1, 4)
	568 arraylength (1, 4)
	569 istore (1, 4)
	571 iconst_0 (1, 4)
	572 istore (1, 4)
	574 iload (1, 4)
	576 iload (1, 4)
	578 if_icmpge (1, 4)
	581 aload (1, 4)
	583 iload (1, 4)
	585 aaload (1, 4)
	586 astore (1, 4)
	588 aload (1, 4)
	590 aload_1 (1, 4)
	591 iload (1, 4)
	593 iinc (1, 4)
	596 invokevirtual (1, 4)
	599 aload (1, 4)
	601 invokevirtual (1, 4)
	604 iinc (1, 4)
	607 goto (1, 4)
	610 aload_0 (1, 4)
	611 getfield (1, 4)
	614 invokeinterface (1, 4)
	619 astore (1, 4)
	621 aload (1, 4)
	623 invokeinterface (1, 4)
	628 ifeq (1, 4)
	631 aload (1, 4)
	633 invokeinterface (1, 4)
	638 checkcast (1, 4)
	641 astore (1, 4)
	643 aload (1, 4)
	645 dload (1, 4)
	647 aload (1, 4)
	649 invokevirtual (1, 4)
	652 aload_0 (1, 4)
	653 aload_0 (1, 4)
	654 getfield (1, 4)
	657 ifne (1, 4)
	660 aload (1, 4)
	662 invokevirtual (1, 4)
	665 ifeq (1, 4)
	668 iconst_1 (1, 4)
	669 goto (1, 4)
	672 iconst_0 (1, 4)
	673 putfield (1, 4)
	676 goto (0, 3)
	679 aload_0 (0, 3)
	680 aload_0 (0, 3)
	681 getfield (0, 3)
	684 ifne (0, 3)
	687 dload (0, 3)
	689 dload (0, 3)
	691 iconst_1 (0, 3)
	692 invokestatic (0, 3)
	695 ifeq (0, 3)
	698 iconst_1 (0, 3)
	699 goto (0, 3)
	702 iconst_0 (0, 3)
	703 putfield (0, 3)
	706 aload_0 (1, 4)
	707 getfield (1, 4)
	710 invokeinterface (1, 4)
	715 astore (1, 4)
	717 aload (1, 4)
	719 invokeinterface (1, 4)
	724 ifeq (1, 4)
	727 aload (1, 4)
	729 invokeinterface (1, 4)
	734 checkcast (1, 4)
	737 astore (1, 4)
	739 aload (1, 4)
	741 aload_1 (1, 4)
	742 aload_0 (1, 4)
	743 getfield (1, 4)
	746 invokeinterface (1, 4)
	751 goto (0, 1)
	754 dload (0, 1)
	756 dreturn (0, 1)

Method: sanityChecks
	0 ldc2_w (0, 0)
	3 aload_1 (0, 0)
	4 invokevirtual (0, 0)
	7 invokestatic (0, 0)
	10 dload_2 (0, 0)
	11 invokestatic (0, 0)
	14 invokestatic (0, 0)
	17 invokestatic (0, 0)
	20 dmul (0, 0)
	21 dstore (0, 0)
	23 aload_1 (0, 0)
	24 invokevirtual (0, 0)
	27 dload_2 (0, 0)
	28 dsub (0, 0)
	29 invokestatic (0, 0)
	32 dstore (0, 0)
	34 dload (1, 1)
	36 dload (1, 1)
	38 dcmpg (1, 1)
	39 ifgt (1, 1)
	42 new (1, 1)
	45 dup (1, 1)
	46 getstatic (1, 1)
	49 dload (1, 1)
	51 invokestatic (1, 1)
	54 dload (1, 1)
	56 invokestatic (1, 1)
	59 iconst_0 (1, 1)
	60 invokespecial (1, 1)
	63 athrow (1, 1)
	64 return (0, 0)

