Method: <init>
	0 aload_0 (0, 0)
	1 invokespecial (0, 0)
	2 java/lang/Object.<init>:()V (0, 0)
	4 aload_0 (0, 0)
	5 new (0, 0)
	6 java/util/ArrayList (0, 0)
	8 dup (0, 0)
	9 invokespecial (0, 0)
	10 java/util/ArrayList.<init>:()V (0, 0)
	12 putfield (0, 0)
	13 org/apache/commons/math3/ode/AbstractParameterizable.parametersNames:Ljava/util/Collection; (0, 0)
	15 aload_0 (0, 0)
	16 getfield (0, 0)
	17 org/apache/commons/math3/ode/AbstractParameterizable.parametersNames:Ljava/util/Collection; (0, 0)
	19 aload_1 (0, 0)
	20 invokeinterface (0, 0)
	21 java/util/Collection.iterator:()Ljava/util/Iterator; (0, 0)
	23 0 (0, 0)
	25 pop (0, 0)
	26 return (0, 0)

Method: getParametersNames
	0 aload_0 (0, 0)
	1 getfield (0, 0)
	2 org/apache/commons/math3/ode/AbstractParameterizable.parametersNames:Ljava/util/Collection; (0, 0)
	4 areturn (0, 0)

Method: isSupported
	0 aload_0 (1, 4)
	1 getfield (1, 4)
	2 org/apache/commons/math3/ode/AbstractParameterizable.parametersNames:Ljava/util/Collection; (1, 4)
	4 invokeinterface (1, 4)
	5 java/util/Collection.java/util/Iterator (1, 4)
	7 0 (1, 4)
	9 astore_2 (1, 4)
	10 aload_2 (1, 4)
	11 invokeinterface (1, 4)
	12 java/util/Iterator.next:()Ljava/lang/Object; (1, 4)
	14 0 (1, 4)
	16 ifeq (1, 4)
	17 26 (1, 4)
	19 aload_2 (1, 4)
	20 invokeinterface (1, 4)
	21 java/util/Iterator.java/lang/String (1, 4)
	23 0 (1, 4)
	25 checkcast (1, 4)
	26 java/lang/String (1, 4)
	28 astore_3 (1, 4)
	29 aload_3 (2, 1)
	30 aload_1 (2, 1)
	31 invokevirtual (2, 1)
	32 java/lang/String.equals:(Ljava/lang/Object;)Z (2, 1)
	34 ifeq (2, 1)
	35 5 (2, 1)
	37 iconst_1 (2, 1)
	38 ireturn (2, 1)
	39 goto (0, 0)
	40 -29 (0, 0)
	42 iconst_0 (0, 0)
	43 ireturn (0, 0)

Method: complainIfNotSupported
	0 aload_0 (1, 1)
	1 aload_1 (1, 1)
	2 invokevirtual (1, 1)
	3 org/apache/commons/math3/ode/AbstractParameterizable.isSupported:(Ljava/lang/String;)Z (1, 1)
	5 ifne (1, 1)
	6 12 (1, 1)
	8 new (1, 1)
	9 org/apache/commons/math3/ode/UnknownParameterException (1, 1)
	11 dup (1, 1)
	12 aload_1 (1, 1)
	13 invokespecial (1, 1)
	14 org/apache/commons/math3/ode/UnknownParameterException.<init>:(Ljava/lang/String;)V (1, 1)
	16 athrow (1, 1)
	17 return (0, 0)

