Method: <init>
	0 aload_0 (0, 0)
	1 invokespecial (0, 0)
	2 java/lang/Object.<init>:()V (0, 0)
	4 aload_0 (0, 0)
	5 aload_1 (0, 0)
	6 putfield (0, 0)
	7 org/apache/commons/math3/ode/AbstractFieldIntegrator.field:Lorg/apache/commons/math3/Field; (0, 0)
	9 aload_0 (0, 0)
	10 aload_2 (0, 0)
	11 putfield (0, 0)
	12 org/apache/commons/math3/ode/AbstractFieldIntegrator.name:Ljava/lang/String; (0, 0)
	14 aload_0 (0, 0)
	15 new (0, 0)
	16 java/util/ArrayList (0, 0)
	18 dup (0, 0)
	19 invokespecial (0, 0)
	20 java/util/ArrayList.<init>:()V (0, 0)
	22 putfield (0, 0)
	23 org/apache/commons/math3/ode/AbstractFieldIntegrator.stepHandlers:Ljava/util/Collection; (0, 0)
	25 aload_0 (0, 0)
	26 aconst_null (0, 0)
	27 putfield (0, 0)
	28 org/apache/commons/math3/ode/AbstractFieldIntegrator.stepStart:Lorg/apache/commons/math3/ode/FieldODEStateAndDerivative; (0, 0)
	30 aload_0 (0, 0)
	31 aconst_null (0, 0)
	32 putfield (0, 0)
	33 org/apache/commons/math3/ode/AbstractFieldIntegrator.stepSize:Lorg/apache/commons/math3/RealFieldElement; (0, 0)
	35 aload_0 (0, 0)
	36 new (0, 0)
	37 java/util/ArrayList (0, 0)
	39 dup (0, 0)
	40 invokespecial (0, 0)
	41 java/util/ArrayList.<init>:()V (0, 0)
	43 putfield (0, 0)
	44 org/apache/commons/math3/ode/AbstractFieldIntegrator.eventsStates:Ljava/util/Collection; (0, 0)
	46 aload_0 (0, 0)
	47 iconst_0 (0, 0)
	48 putfield (0, 0)
	49 org/apache/commons/math3/ode/AbstractFieldIntegrator.statesInitialized:Z (0, 0)
	51 aload_0 (0, 0)
	52 invokestatic (0, 0)
	53 org/apache/commons/math3/util/IntegerSequence$Incrementor.create:()Lorg/apache/commons/math3/util/IntegerSequence$Incrementor; (0, 0)
	55 ldc (0, 0)
	56 2147483647 (0, 0)
	57 invokevirtual (0, 0)
	58 org/apache/commons/math3/util/IntegerSequence$Incrementor.withMaximalCount:(I)Lorg/apache/commons/math3/util/IntegerSequence$Incrementor; (0, 0)
	60 putfield (0, 0)
	61 org/apache/commons/math3/ode/AbstractFieldIntegrator.evaluations:Lorg/apache/commons/math3/util/IntegerSequence$Incrementor; (0, 0)
	63 return (0, 0)

Method: getField
	0 aload_0 (0, 0)
	1 getfield (0, 0)
	2 org/apache/commons/math3/ode/AbstractFieldIntegrator.field:Lorg/apache/commons/math3/Field; (0, 0)
	4 areturn (0, 0)

Method: getName
	0 aload_0 (0, 0)
	1 getfield (0, 0)
	2 org/apache/commons/math3/ode/AbstractFieldIntegrator.name:Ljava/lang/String; (0, 0)
	4 areturn (0, 0)

Method: addStepHandler
	0 aload_0 (0, 0)
	1 getfield (0, 0)
	2 org/apache/commons/math3/ode/AbstractFieldIntegrator.stepHandlers:Ljava/util/Collection; (0, 0)
	4 aload_1 (0, 0)
	5 invokeinterface (0, 0)
	6 java/util/Collection.java/util/Collections (0, 0)
	8 0 (0, 0)
	10 pop (0, 0)
	11 return (0, 0)

Method: getStepHandlers
	0 aload_0 (0, 1)
	1 getfield (0, 1)
	2 org/apache/commons/math3/ode/AbstractFieldIntegrator.stepHandlers:Ljava/util/Collection; (0, 1)
	4 invokestatic (0, 1)
	5 java/util/Collections.unmodifiableCollection:(Ljava/util/Collection;)Ljava/util/Collection; (0, 1)
	7 areturn (0, 1)

Method: clearStepHandlers
	0 aload_0 (0, 0)
	1 getfield (0, 0)
	2 org/apache/commons/math3/ode/AbstractFieldIntegrator.stepHandlers:Ljava/util/Collection; (0, 0)
	4 invokeinterface (0, 0)
	5 java/util/Collection.org/apache/commons/math3/analysis/solvers/FieldBracketingNthOrderBrentSolver (0, 0)
	7 0 (0, 0)
	9 return (0, 0)

Method: addEventHandler
	0 aload_0 (0, 0)
	1 getfield (0, 0)
	2 org/apache/commons/math3/ode/AbstractFieldIntegrator.eventsStates:Ljava/util/Collection; (0, 0)
	4 new (0, 0)
	5 org/apache/commons/math3/ode/events/FieldEventState (0, 0)
	7 dup (0, 0)
	8 aload_1 (0, 0)
	9 dload_2 (0, 0)
	10 aload_0 (0, 0)
	11 getfield (0, 0)
	12 org/apache/commons/math3/ode/AbstractFieldIntegrator.field:Lorg/apache/commons/math3/Field; (0, 0)
	14 invokeinterface (0, 0)
	15 org/apache/commons/math3/Field.org/apache/commons/math3/RealFieldElement (0, 0)
	17 0 (0, 0)
	19 checkcast (0, 0)
	20 org/apache/commons/math3/RealFieldElement (0, 0)
	22 dload (0, 0)
	23 #4 (0, 0)
	24 invokeinterface (0, 0)
	25 org/apache/commons/math3/RealFieldElement.<init>:(Lorg/apache/commons/math3/RealFieldElement;Lorg/apache/commons/math3/RealFieldElement;Lorg/apache/commons/math3/RealFieldElement;I)V (0, 0)
	27 0 (0, 0)
	29 checkcast (0, 0)
	30 org/apache/commons/math3/RealFieldElement (0, 0)
	32 iload (0, 0)
	33 #6 (0, 0)
	34 aload (0, 0)
	35 #7 (0, 0)
	36 invokespecial (0, 0)
	37 org/apache/commons/math3/ode/events/FieldEventState.<init>:(Lorg/apache/commons/math3/ode/events/FieldEventHandler;DLorg/apache/commons/math3/RealFieldElement;ILorg/apache/commons/math3/analysis/solvers/BracketedRealFieldUnivariateSolver;)V (0, 0)
	39 invokeinterface (0, 0)
	40 java/util/Collection.java/util/Collections (0, 0)
	42 0 (0, 0)
	44 pop (0, 0)
	45 return (0, 0)

Method: getEventHandlers
	0 new (0, 0)
	1 java/util/ArrayList (0, 0)
	3 dup (0, 0)
	4 aload_0 (0, 0)
	5 getfield (0, 0)
	6 org/apache/commons/math3/ode/AbstractFieldIntegrator.eventsStates:Ljava/util/Collection; (0, 0)
	8 invokeinterface (0, 0)
	9 java/util/Collection.<init>:(I)V (0, 0)
	11 0 (0, 0)
	13 invokespecial (0, 0)
	14 java/util/ArrayList.<init>:(I)V (0, 0)
	16 astore_1 (0, 0)
	17 aload_0 (1, 4)
	18 getfield (1, 4)
	19 org/apache/commons/math3/ode/AbstractFieldIntegrator.eventsStates:Ljava/util/Collection; (1, 4)
	21 invokeinterface (1, 4)
	22 java/util/Collection.java/util/Iterator (1, 4)
	24 0 (1, 4)
	26 astore_2 (1, 4)
	27 aload_2 (1, 4)
	28 invokeinterface (1, 4)
	29 java/util/Iterator.next:()Ljava/lang/Object; (1, 4)
	31 0 (1, 4)
	33 ifeq (1, 4)
	34 27 (1, 4)
	36 aload_2 (1, 4)
	37 invokeinterface (1, 4)
	38 java/util/Iterator.getEventHandler:()Lorg/apache/commons/math3/ode/events/FieldEventHandler; (1, 4)
	40 0 (1, 4)
	42 checkcast (1, 4)
	43 org/apache/commons/math3/ode/events/FieldEventState (1, 4)
	45 astore_3 (1, 4)
	46 aload_1 (1, 4)
	47 aload_3 (1, 4)
	48 invokevirtual (1, 4)
	49 org/apache/commons/math3/ode/events/FieldEventState.getEventHandler:()Lorg/apache/commons/math3/ode/events/FieldEventHandler; (1, 4)
	51 invokeinterface (1, 4)
	52 java/util/List.java/util/Collections (1, 4)
	54 0 (1, 4)
	56 pop (1, 4)
	57 goto (0, 0)
	58 -30 (0, 0)
	60 aload_1 (0, 1)
	61 invokestatic (0, 1)
	62 java/util/Collections.unmodifiableCollection:(Ljava/util/Collection;)Ljava/util/Collection; (0, 1)
	64 areturn (0, 1)

Method: clearEventHandlers
	0 aload_0 (0, 0)
	1 getfield (0, 0)
	2 org/apache/commons/math3/ode/AbstractFieldIntegrator.eventsStates:Ljava/util/Collection; (0, 0)
	4 invokeinterface (0, 0)
	5 java/util/Collection.org/apache/commons/math3/analysis/solvers/FieldBracketingNthOrderBrentSolver (0, 0)
	7 0 (0, 0)
	9 return (0, 0)

Method: getCurrentStepStart
	0 aload_0 (0, 0)
	1 getfield (0, 0)
	2 org/apache/commons/math3/ode/AbstractFieldIntegrator.stepStart:Lorg/apache/commons/math3/ode/FieldODEStateAndDerivative; (0, 0)
	4 areturn (0, 0)

Method: getCurrentSignedStepsize
	0 aload_0 (0, 0)
	1 getfield (0, 0)
	2 org/apache/commons/math3/ode/AbstractFieldIntegrator.stepSize:Lorg/apache/commons/math3/RealFieldElement; (0, 0)
	4 areturn (0, 0)

Method: setMaxEvaluations
	0 aload_0 (0, 0)
	1 aload_0 (0, 0)
	2 getfield (0, 0)
	3 org/apache/commons/math3/ode/AbstractFieldIntegrator.evaluations:Lorg/apache/commons/math3/util/IntegerSequence$Incrementor; (0, 0)
	5 iload_1 (0, 0)
	6 ifge (0, 0)
	7 8 (0, 0)
	9 ldc (0, 0)
	10 2147483647 (0, 0)
	11 goto (0, 0)
	12 4 (0, 0)
	14 iload_1 (0, 0)
	15 invokevirtual (0, 0)
	16 org/apache/commons/math3/util/IntegerSequence$Incrementor.withMaximalCount:(I)Lorg/apache/commons/math3/util/IntegerSequence$Incrementor; (0, 0)
	18 putfield (0, 0)
	19 org/apache/commons/math3/ode/AbstractFieldIntegrator.evaluations:Lorg/apache/commons/math3/util/IntegerSequence$Incrementor; (0, 0)
	21 return (0, 0)

Method: getMaxEvaluations
	0 aload_0 (0, 0)
	1 getfield (0, 0)
	2 org/apache/commons/math3/ode/AbstractFieldIntegrator.evaluations:Lorg/apache/commons/math3/util/IntegerSequence$Incrementor; (0, 0)
	4 invokevirtual (0, 0)
	5 org/apache/commons/math3/util/IntegerSequence$Incrementor.getMaximalCount:()I (0, 0)
	7 ireturn (0, 0)

Method: getEvaluations
	0 aload_0 (0, 0)
	1 getfield (0, 0)
	2 org/apache/commons/math3/ode/AbstractFieldIntegrator.evaluations:Lorg/apache/commons/math3/util/IntegerSequence$Incrementor; (0, 0)
	4 invokevirtual (0, 0)
	5 org/apache/commons/math3/util/IntegerSequence$Incrementor.getCount:()I (0, 0)
	7 ireturn (0, 0)

Method: initIntegration
	0 aload_0 (0, 0)
	1 aload_1 (0, 0)
	2 putfield (0, 0)
	3 org/apache/commons/math3/ode/AbstractFieldIntegrator.equations:Lorg/apache/commons/math3/ode/FieldExpandableODE; (0, 0)
	5 aload_0 (0, 0)
	6 aload_0 (0, 0)
	7 getfield (0, 0)
	8 org/apache/commons/math3/ode/AbstractFieldIntegrator.evaluations:Lorg/apache/commons/math3/util/IntegerSequence$Incrementor; (0, 0)
	10 iconst_0 (0, 0)
	11 invokevirtual (0, 0)
	12 org/apache/commons/math3/util/IntegerSequence$Incrementor.withStart:(I)Lorg/apache/commons/math3/util/IntegerSequence$Incrementor; (0, 0)
	14 putfield (0, 0)
	15 org/apache/commons/math3/ode/AbstractFieldIntegrator.evaluations:Lorg/apache/commons/math3/util/IntegerSequence$Incrementor; (0, 0)
	17 aload_1 (0, 0)
	18 aload_2 (0, 0)
	19 aload_3 (0, 0)
	20 aload (0, 0)
	21 #4 (0, 0)
	22 invokevirtual (0, 0)
	23 org/apache/commons/math3/ode/FieldExpandableODE.init:(Lorg/apache/commons/math3/RealFieldElement;[Lorg/apache/commons/math3/RealFieldElement;Lorg/apache/commons/math3/RealFieldElement;)V (0, 0)
	25 aload_0 (0, 0)
	26 aload_2 (0, 0)
	27 aload_3 (0, 0)
	28 invokevirtual (0, 0)
	29 org/apache/commons/math3/ode/AbstractFieldIntegrator.computeDerivatives:(Lorg/apache/commons/math3/RealFieldElement;[Lorg/apache/commons/math3/RealFieldElement;)[Lorg/apache/commons/math3/RealFieldElement; (0, 0)
	31 astore (0, 0)
	32 #5 (0, 0)
	33 new (0, 0)
	34 org/apache/commons/math3/ode/FieldODEStateAndDerivative (0, 0)
	36 dup (0, 0)
	37 aload_2 (0, 0)
	38 aload_3 (0, 0)
	39 aload (0, 0)
	40 #5 (0, 0)
	41 invokespecial (0, 0)
	42 org/apache/commons/math3/ode/FieldODEStateAndDerivative.<init>:(Lorg/apache/commons/math3/RealFieldElement;[Lorg/apache/commons/math3/RealFieldElement;[Lorg/apache/commons/math3/RealFieldElement;)V (0, 0)
	44 astore (0, 0)
	45 #6 (0, 0)
	46 aload_0 (1, 4)
	47 getfield (1, 4)
	48 org/apache/commons/math3/ode/AbstractFieldIntegrator.eventsStates:Ljava/util/Collection; (1, 4)
	50 invokeinterface (1, 4)
	51 java/util/Collection.java/util/Iterator (1, 4)
	53 0 (1, 4)
	55 astore (1, 4)
	56 #7 (1, 4)
	57 aload (1, 4)
	58 #7 (1, 4)
	59 invokeinterface (1, 4)
	60 java/util/Iterator.next:()Ljava/lang/Object; (1, 4)
	62 0 (1, 4)
	64 ifeq (1, 4)
	65 32 (1, 4)
	67 aload (1, 4)
	68 #7 (1, 4)
	69 invokeinterface (1, 4)
	70 java/util/Iterator.getEventHandler:()Lorg/apache/commons/math3/ode/events/FieldEventHandler; (1, 4)
	72 0 (1, 4)
	74 checkcast (1, 4)
	75 org/apache/commons/math3/ode/events/FieldEventState (1, 4)
	77 astore (1, 4)
	78 #8 (1, 4)
	79 aload (1, 4)
	80 #8 (1, 4)
	81 invokevirtual (1, 4)
	82 org/apache/commons/math3/ode/events/FieldEventState.getEventHandler:()Lorg/apache/commons/math3/ode/events/FieldEventHandler; (1, 4)
	84 aload (1, 4)
	85 #6 (1, 4)
	86 aload (1, 4)
	87 #4 (1, 4)
	88 invokeinterface (1, 4)
	89 org/apache/commons/math3/ode/events/FieldEventHandler.org/apache/commons/math3/ode/sampling/FieldStepHandler (1, 4)
	91 0 (1, 4)
	93 goto (0, 0)
	94 -36 (0, 0)
	96 aload_0 (1, 4)
	97 getfield (1, 4)
	98 org/apache/commons/math3/ode/AbstractFieldIntegrator.stepHandlers:Ljava/util/Collection; (1, 4)
	100 invokeinterface (1, 4)
	101 java/util/Collection.java/util/Iterator (1, 4)
	103 0 (1, 4)
	105 astore (1, 4)
	106 #7 (1, 4)
	107 aload (1, 4)
	108 #7 (1, 4)
	109 invokeinterface (1, 4)
	110 java/util/Iterator.next:()Ljava/lang/Object; (1, 4)
	112 0 (1, 4)
	114 ifeq (1, 4)
	115 29 (1, 4)
	117 aload (1, 4)
	118 #7 (1, 4)
	119 invokeinterface (1, 4)
	120 java/util/Iterator.getEventHandler:()Lorg/apache/commons/math3/ode/events/FieldEventHandler; (1, 4)
	122 0 (1, 4)
	124 checkcast (1, 4)
	125 org/apache/commons/math3/ode/sampling/FieldStepHandler (1, 4)
	127 astore (1, 4)
	128 #8 (1, 4)
	129 aload (1, 4)
	130 #8 (1, 4)
	131 aload (1, 4)
	132 #6 (1, 4)
	133 aload (1, 4)
	134 #4 (1, 4)
	135 invokeinterface (1, 4)
	136 org/apache/commons/math3/ode/sampling/FieldStepHandler.org/apache/commons/math3/ode/sampling/FieldStepHandler (1, 4)
	138 0 (1, 4)
	140 goto (0, 0)
	141 -33 (0, 0)
	143 aload_0 (0, 0)
	144 iconst_0 (0, 0)
	145 invokevirtual (0, 0)
	146 org/apache/commons/math3/ode/AbstractFieldIntegrator.setStateInitialized:(Z)V (0, 0)
	148 aload (0, 0)
	149 #6 (0, 0)
	150 areturn (0, 0)

Method: getEquations
	0 aload_0 (0, 0)
	1 getfield (0, 0)
	2 org/apache/commons/math3/ode/AbstractFieldIntegrator.equations:Lorg/apache/commons/math3/ode/FieldExpandableODE; (0, 0)
	4 areturn (0, 0)

Method: getEvaluationsCounter
	0 aload_0 (0, 0)
	1 getfield (0, 0)
	2 org/apache/commons/math3/ode/AbstractFieldIntegrator.evaluations:Lorg/apache/commons/math3/util/IntegerSequence$Incrementor; (0, 0)
	4 areturn (0, 0)

Method: computeDerivatives
	0 aload_0 (0, 0)
	1 getfield (0, 0)
	2 org/apache/commons/math3/ode/AbstractFieldIntegrator.evaluations:Lorg/apache/commons/math3/util/IntegerSequence$Incrementor; (0, 0)
	4 invokevirtual (0, 0)
	5 org/apache/commons/math3/util/IntegerSequence$Incrementor.increment:()V (0, 0)
	7 aload_0 (0, 0)
	8 getfield (0, 0)
	9 org/apache/commons/math3/ode/AbstractFieldIntegrator.equations:Lorg/apache/commons/math3/ode/FieldExpandableODE; (0, 0)
	11 aload_1 (0, 0)
	12 aload_2 (0, 0)
	13 invokevirtual (0, 0)
	14 org/apache/commons/math3/ode/FieldExpandableODE.computeDerivatives:(Lorg/apache/commons/math3/RealFieldElement;[Lorg/apache/commons/math3/RealFieldElement;)[Lorg/apache/commons/math3/RealFieldElement; (0, 0)
	16 areturn (0, 0)

Method: setStateInitialized
	0 aload_0 (0, 0)
	1 iload_1 (0, 0)
	2 putfield (0, 0)
	3 org/apache/commons/math3/ode/AbstractFieldIntegrator.statesInitialized:Z (0, 0)
	5 return (0, 0)

Method: acceptStep
	0 aload_1 (0, 0)
	1 invokevirtual (0, 0)
	2 org/apache/commons/math3/ode/sampling/AbstractFieldStepInterpolator.getGlobalPreviousState:()Lorg/apache/commons/math3/ode/FieldODEStateAndDerivative; (0, 0)
	4 astore_3 (0, 0)
	5 aload_1 (0, 0)
	6 invokevirtual (0, 0)
	7 org/apache/commons/math3/ode/sampling/AbstractFieldStepInterpolator.getGlobalCurrentState:()Lorg/apache/commons/math3/ode/FieldODEStateAndDerivative; (0, 0)
	9 astore (0, 0)
	10 #4 (0, 0)
	11 aload_0 (1, 1)
	12 getfield (1, 1)
	13 org/apache/commons/math3/ode/AbstractFieldIntegrator.statesInitialized:Z (1, 1)
	15 ifne (1, 1)
	16 50 (1, 1)
	18 aload_0 (2, 4)
	19 getfield (2, 4)
	20 org/apache/commons/math3/ode/AbstractFieldIntegrator.eventsStates:Ljava/util/Collection; (2, 4)
	22 invokeinterface (2, 4)
	23 java/util/Collection.java/util/Iterator (2, 4)
	25 0 (2, 4)
	27 astore (2, 4)
	28 #5 (2, 4)
	29 aload (2, 4)
	30 #5 (2, 4)
	31 invokeinterface (2, 4)
	32 java/util/Iterator.next:()Ljava/lang/Object; (2, 4)
	34 0 (2, 4)
	36 ifeq (2, 4)
	37 24 (2, 4)
	39 aload (2, 4)
	40 #5 (2, 4)
	41 invokeinterface (2, 4)
	42 java/util/Iterator.getEventHandler:()Lorg/apache/commons/math3/ode/events/FieldEventHandler; (2, 4)
	44 0 (2, 4)
	46 checkcast (2, 4)
	47 org/apache/commons/math3/ode/events/FieldEventState (2, 4)
	49 astore (2, 4)
	50 #6 (2, 4)
	51 aload (2, 4)
	52 #6 (2, 4)
	53 aload_1 (2, 4)
	54 invokevirtual (2, 4)
	55 org/apache/commons/math3/ode/events/FieldEventState.reinitializeBegin:(Lorg/apache/commons/math3/ode/sampling/FieldStepInterpolator;)V (2, 4)
	57 goto (1, 1)
	58 -28 (1, 1)
	60 aload_0 (1, 1)
	61 iconst_1 (1, 1)
	62 putfield (1, 1)
	63 org/apache/commons/math3/ode/AbstractFieldIntegrator.statesInitialized:Z (1, 1)
	65 aload_1 (0, 4)
	66 invokevirtual (0, 4)
	67 org/apache/commons/math3/ode/sampling/AbstractFieldStepInterpolator.isForward:()Z (0, 4)
	69 ifeq (0, 4)
	70 7 (0, 4)
	72 iconst_1 (0, 4)
	73 goto (0, 4)
	74 4 (0, 4)
	76 iconst_m1 (0, 4)
	77 istore (0, 4)
	78 #5 (0, 4)
	79 new (0, 4)
	80 java/util/TreeSet (0, 4)
	82 dup (0, 4)
	83 new (0, 4)
	84 org/apache/commons/math3/ode/AbstractFieldIntegrator$1 (0, 4)
	86 dup (0, 4)
	87 aload_0 (0, 4)
	88 iload (0, 4)
	89 #5 (0, 4)
	90 invokespecial (0, 4)
	91 org/apache/commons/math3/ode/AbstractFieldIntegrator$1.<init>:(Lorg/apache/commons/math3/ode/AbstractFieldIntegrator;I)V (0, 4)
	93 invokespecial (0, 4)
	94 java/util/TreeSet.<init>:(Ljava/util/Comparator;)V (0, 4)
	96 astore (0, 4)
	97 #6 (0, 4)
	98 aload_0 (1, 4)
	99 getfield (1, 4)
	100 org/apache/commons/math3/ode/AbstractFieldIntegrator.eventsStates:Ljava/util/Collection; (1, 4)
	102 invokeinterface (1, 4)
	103 java/util/Collection.java/util/Iterator (1, 4)
	105 0 (1, 4)
	107 astore (1, 4)
	108 #7 (1, 4)
	109 aload (1, 4)
	110 #7 (1, 4)
	111 invokeinterface (1, 4)
	112 java/util/Iterator.next:()Ljava/lang/Object; (1, 4)
	114 0 (1, 4)
	116 ifeq (1, 4)
	117 37 (1, 4)
	119 aload (1, 4)
	120 #7 (1, 4)
	121 invokeinterface (1, 4)
	122 java/util/Iterator.getEventHandler:()Lorg/apache/commons/math3/ode/events/FieldEventHandler; (1, 4)
	124 0 (1, 4)
	126 checkcast (1, 4)
	127 org/apache/commons/math3/ode/events/FieldEventState (1, 4)
	129 astore (1, 4)
	130 #8 (1, 4)
	131 aload (2, 1)
	132 #8 (2, 1)
	133 aload_1 (2, 1)
	134 invokevirtual (2, 1)
	135 org/apache/commons/math3/ode/events/FieldEventState.evaluateStep:(Lorg/apache/commons/math3/ode/sampling/FieldStepInterpolator;)Z (2, 1)
	137 ifeq (2, 1)
	138 13 (2, 1)
	140 aload (2, 1)
	141 #6 (2, 1)
	142 aload (2, 1)
	143 #8 (2, 1)
	144 invokeinterface (2, 1)
	145 java/util/SortedSet.java/util/Collections (2, 1)
	147 0 (2, 1)
	149 pop (2, 1)
	150 goto (0, 4)
	151 -41 (0, 4)
	153 aload_1 (0, 4)
	154 astore (0, 4)
	155 #7 (0, 4)
	156 aload (1, 3)
	157 #6 (1, 3)
	158 invokeinterface (1, 3)
	159 java/util/SortedSet.remove:()V (1, 3)
	161 0 (1, 3)
	163 ifne (1, 3)
	164 326 (1, 3)
	166 aload (1, 3)
	167 #6 (1, 3)
	168 invokeinterface (1, 3)
	169 java/util/SortedSet.java/util/Iterator (1, 3)
	171 0 (1, 3)
	173 astore (1, 3)
	174 #8 (1, 3)
	175 aload (1, 3)
	176 #8 (1, 3)
	177 invokeinterface (1, 3)
	178 java/util/Iterator.getEventHandler:()Lorg/apache/commons/math3/ode/events/FieldEventHandler; (1, 3)
	180 0 (1, 3)
	182 checkcast (1, 3)
	183 org/apache/commons/math3/ode/events/FieldEventState (1, 3)
	185 astore (1, 3)
	186 #9 (1, 3)
	187 aload (1, 3)
	188 #8 (1, 3)
	189 invokeinterface (1, 3)
	190 java/util/Iterator.getEventTime:()Lorg/apache/commons/math3/RealFieldElement; (1, 3)
	192 0 (1, 3)
	194 aload (1, 3)
	195 #7 (1, 3)
	196 aload (1, 3)
	197 #9 (1, 3)
	198 invokevirtual (1, 3)
	199 org/apache/commons/math3/ode/events/FieldEventState.getEventTime:()Lorg/apache/commons/math3/RealFieldElement; (1, 3)
	201 invokevirtual (1, 3)
	202 org/apache/commons/math3/ode/sampling/AbstractFieldStepInterpolator.getInterpolatedState:(Lorg/apache/commons/math3/RealFieldElement;)Lorg/apache/commons/math3/ode/FieldODEStateAndDerivative; (1, 3)
	204 astore (1, 3)
	205 #10 (1, 3)
	206 aload (1, 3)
	207 #7 (1, 3)
	208 aload_3 (1, 3)
	209 aload (1, 3)
	210 #10 (1, 3)
	211 invokevirtual (1, 3)
	212 org/apache/commons/math3/ode/sampling/AbstractFieldStepInterpolator.restrictStep:(Lorg/apache/commons/math3/ode/FieldODEStateAndDerivative;Lorg/apache/commons/math3/ode/FieldODEStateAndDerivative;)Lorg/apache/commons/math3/ode/sampling/AbstractFieldStepInterpolator; (1, 3)
	214 astore (1, 3)
	215 #7 (1, 3)
	216 aload_0 (2, 4)
	217 getfield (2, 4)
	218 org/apache/commons/math3/ode/AbstractFieldIntegrator.eventsStates:Ljava/util/Collection; (2, 4)
	220 invokeinterface (2, 4)
	221 java/util/Collection.java/util/Iterator (2, 4)
	223 0 (2, 4)
	225 astore (2, 4)
	226 #11 (2, 4)
	227 aload (2, 4)
	228 #11 (2, 4)
	229 invokeinterface (2, 4)
	230 java/util/Iterator.next:()Ljava/lang/Object; (2, 4)
	232 0 (2, 4)
	234 ifeq (2, 4)
	235 49 (2, 4)
	237 aload (2, 4)
	238 #11 (2, 4)
	239 invokeinterface (2, 4)
	240 java/util/Iterator.getEventHandler:()Lorg/apache/commons/math3/ode/events/FieldEventHandler; (2, 4)
	242 0 (2, 4)
	244 checkcast (2, 4)
	245 org/apache/commons/math3/ode/events/FieldEventState (2, 4)
	247 astore (2, 4)
	248 #12 (2, 4)
	249 aload (2, 4)
	250 #12 (2, 4)
	251 aload (2, 4)
	252 #10 (2, 4)
	253 invokevirtual (2, 4)
	254 org/apache/commons/math3/ode/events/FieldEventState.stepAccepted:(Lorg/apache/commons/math3/ode/FieldODEStateAndDerivative;)V (2, 4)
	256 aload_0 (2, 4)
	257 aload_0 (2, 4)
	258 getfield (2, 4)
	259 org/apache/commons/math3/ode/AbstractFieldIntegrator.isLastStep:Z (2, 4)
	261 ifne (2, 4)
	262 11 (2, 4)
	264 aload (2, 4)
	265 #12 (2, 4)
	266 invokevirtual (2, 4)
	267 org/apache/commons/math3/ode/events/FieldEventState.stop:()Z (2, 4)
	269 ifeq (2, 4)
	270 7 (2, 4)
	272 iconst_1 (2, 4)
	273 goto (2, 4)
	274 4 (2, 4)
	276 iconst_0 (2, 4)
	277 putfield (2, 4)
	278 org/apache/commons/math3/ode/AbstractFieldIntegrator.isLastStep:Z (2, 4)
	280 goto (1, 3)
	281 -53 (1, 3)
	283 aload_0 (2, 4)
	284 getfield (2, 4)
	285 org/apache/commons/math3/ode/AbstractFieldIntegrator.stepHandlers:Ljava/util/Collection; (2, 4)
	287 invokeinterface (2, 4)
	288 java/util/Collection.java/util/Iterator (2, 4)
	290 0 (2, 4)
	292 astore (2, 4)
	293 #11 (2, 4)
	294 aload (2, 4)
	295 #11 (2, 4)
	296 invokeinterface (2, 4)
	297 java/util/Iterator.next:()Ljava/lang/Object; (2, 4)
	299 0 (2, 4)
	301 ifeq (2, 4)
	302 31 (2, 4)
	304 aload (2, 4)
	305 #11 (2, 4)
	306 invokeinterface (2, 4)
	307 java/util/Iterator.getEventHandler:()Lorg/apache/commons/math3/ode/events/FieldEventHandler; (2, 4)
	309 0 (2, 4)
	311 checkcast (2, 4)
	312 org/apache/commons/math3/ode/sampling/FieldStepHandler (2, 4)
	314 astore (2, 4)
	315 #12 (2, 4)
	316 aload (2, 4)
	317 #12 (2, 4)
	318 aload (2, 4)
	319 #7 (2, 4)
	320 aload_0 (2, 4)
	321 getfield (2, 4)
	322 org/apache/commons/math3/ode/AbstractFieldIntegrator.isLastStep:Z (2, 4)
	324 invokeinterface (2, 4)
	325 org/apache/commons/math3/ode/sampling/FieldStepHandler.resetOccurred:Z (2, 4)
	327 0 (2, 4)
	329 goto (1, 3)
	330 -35 (1, 3)
	332 aload_0 (2, 1)
	333 getfield (2, 1)
	334 org/apache/commons/math3/ode/AbstractFieldIntegrator.isLastStep:Z (2, 1)
	336 ifeq (2, 1)
	337 6 (2, 1)
	339 aload (2, 1)
	340 #10 (2, 1)
	341 areturn (2, 1)
	342 aconst_null (1, 3)
	343 astore (1, 3)
	344 #11 (1, 3)
	345 aload_0 (1, 3)
	346 iconst_0 (1, 3)
	347 putfield (1, 3)
	348 org/apache/commons/math3/ode/AbstractFieldIntegrator.resetOccurred:Z (1, 3)
	350 aload_0 (2, 4)
	351 getfield (2, 4)
	352 org/apache/commons/math3/ode/AbstractFieldIntegrator.eventsStates:Ljava/util/Collection; (2, 4)
	354 invokeinterface (2, 4)
	355 java/util/Collection.java/util/Iterator (2, 4)
	357 0 (2, 4)
	359 astore (2, 4)
	360 #12 (2, 4)
	361 aload (2, 4)
	362 #12 (2, 4)
	363 invokeinterface (2, 4)
	364 java/util/Iterator.next:()Ljava/lang/Object; (2, 4)
	366 0 (2, 4)
	368 ifeq (2, 4)
	369 84 (2, 4)
	371 aload (2, 4)
	372 #12 (2, 4)
	373 invokeinterface (2, 4)
	374 java/util/Iterator.getEventHandler:()Lorg/apache/commons/math3/ode/events/FieldEventHandler; (2, 4)
	376 0 (2, 4)
	378 checkcast (2, 4)
	379 org/apache/commons/math3/ode/events/FieldEventState (2, 4)
	381 astore (2, 4)
	382 #13 (2, 4)
	383 aload (2, 4)
	384 #13 (2, 4)
	385 aload (2, 4)
	386 #10 (2, 4)
	387 invokevirtual (2, 4)
	388 org/apache/commons/math3/ode/events/FieldEventState.reset:(Lorg/apache/commons/math3/ode/FieldODEStateAndDerivative;)Lorg/apache/commons/math3/ode/FieldODEState; (2, 4)
	390 astore (2, 4)
	391 #11 (2, 4)
	392 aload (3, 1)
	393 #11 (3, 1)
	394 ifnull (3, 1)
	395 55 (3, 1)
	397 aload_0 (3, 1)
	398 getfield (3, 1)
	399 org/apache/commons/math3/ode/AbstractFieldIntegrator.equations:Lorg/apache/commons/math3/ode/FieldExpandableODE; (3, 1)
	401 invokevirtual (3, 1)
	402 org/apache/commons/math3/ode/FieldExpandableODE.getMapper:()Lorg/apache/commons/math3/ode/FieldEquationsMapper; (3, 1)
	404 aload (3, 1)
	405 #11 (3, 1)
	406 invokevirtual (3, 1)
	407 org/apache/commons/math3/ode/FieldEquationsMapper.mapState:(Lorg/apache/commons/math3/ode/FieldODEState;)[Lorg/apache/commons/math3/RealFieldElement; (3, 1)
	409 astore (3, 1)
	410 #14 (3, 1)
	411 aload_0 (3, 1)
	412 aload (3, 1)
	413 #11 (3, 1)
	414 invokevirtual (3, 1)
	415 org/apache/commons/math3/ode/FieldODEState.getTime:()Lorg/apache/commons/math3/RealFieldElement; (3, 1)
	417 aload (3, 1)
	418 #14 (3, 1)
	419 invokevirtual (3, 1)
	420 org/apache/commons/math3/ode/AbstractFieldIntegrator.computeDerivatives:(Lorg/apache/commons/math3/RealFieldElement;[Lorg/apache/commons/math3/RealFieldElement;)[Lorg/apache/commons/math3/RealFieldElement; (3, 1)
	422 astore (3, 1)
	423 #15 (3, 1)
	424 aload_0 (3, 1)
	425 iconst_1 (3, 1)
	426 putfield (3, 1)
	427 org/apache/commons/math3/ode/AbstractFieldIntegrator.resetOccurred:Z (3, 1)
	429 aload_0 (3, 1)
	430 getfield (3, 1)
	431 org/apache/commons/math3/ode/AbstractFieldIntegrator.equations:Lorg/apache/commons/math3/ode/FieldExpandableODE; (3, 1)
	433 invokevirtual (3, 1)
	434 org/apache/commons/math3/ode/FieldExpandableODE.getMapper:()Lorg/apache/commons/math3/ode/FieldEquationsMapper; (3, 1)
	436 aload (3, 1)
	437 #11 (3, 1)
	438 invokevirtual (3, 1)
	439 org/apache/commons/math3/ode/FieldODEState.getTime:()Lorg/apache/commons/math3/RealFieldElement; (3, 1)
	441 aload (3, 1)
	442 #14 (3, 1)
	443 aload (3, 1)
	444 #15 (3, 1)
	445 invokevirtual (3, 1)
	446 org/apache/commons/math3/ode/FieldEquationsMapper.mapStateAndDerivative:(Lorg/apache/commons/math3/RealFieldElement;[Lorg/apache/commons/math3/RealFieldElement;[Lorg/apache/commons/math3/RealFieldElement;)Lorg/apache/commons/math3/ode/FieldODEStateAndDerivative; (3, 1)
	448 areturn (3, 1)
	449 goto (1, 3)
	450 -88 (1, 3)
	452 aload (1, 3)
	453 #10 (1, 3)
	454 astore_3 (1, 3)
	455 aload (1, 3)
	456 #7 (1, 3)
	457 aload (1, 3)
	458 #10 (1, 3)
	459 aload (1, 3)
	460 #4 (1, 3)
	461 invokevirtual (1, 3)
	462 org/apache/commons/math3/ode/sampling/AbstractFieldStepInterpolator.restrictStep:(Lorg/apache/commons/math3/ode/FieldODEStateAndDerivative;Lorg/apache/commons/math3/ode/FieldODEStateAndDerivative;)Lorg/apache/commons/math3/ode/sampling/AbstractFieldStepInterpolator; (1, 3)
	464 astore (1, 3)
	465 #7 (1, 3)
	466 aload (2, 1)
	467 #9 (2, 1)
	468 aload (2, 1)
	469 #7 (2, 1)
	470 invokevirtual (2, 1)
	471 org/apache/commons/math3/ode/events/FieldEventState.evaluateStep:(Lorg/apache/commons/math3/ode/sampling/FieldStepInterpolator;)Z (2, 1)
	473 ifeq (2, 1)
	474 13 (2, 1)
	476 aload (2, 1)
	477 #6 (2, 1)
	478 aload (2, 1)
	479 #9 (2, 1)
	480 invokeinterface (2, 1)
	481 java/util/SortedSet.java/util/Collections (2, 1)
	483 0 (2, 1)
	485 pop (2, 1)
	486 goto (0, 4)
	487 -330 (0, 4)
	489 aload_0 (1, 4)
	490 getfield (1, 4)
	491 org/apache/commons/math3/ode/AbstractFieldIntegrator.eventsStates:Ljava/util/Collection; (1, 4)
	493 invokeinterface (1, 4)
	494 java/util/Collection.java/util/Iterator (1, 4)
	496 0 (1, 4)
	498 astore (1, 4)
	499 #8 (1, 4)
	500 aload (1, 4)
	501 #8 (1, 4)
	502 invokeinterface (1, 4)
	503 java/util/Iterator.next:()Ljava/lang/Object; (1, 4)
	505 0 (1, 4)
	507 ifeq (1, 4)
	508 49 (1, 4)
	510 aload (1, 4)
	511 #8 (1, 4)
	512 invokeinterface (1, 4)
	513 java/util/Iterator.getEventHandler:()Lorg/apache/commons/math3/ode/events/FieldEventHandler; (1, 4)
	515 0 (1, 4)
	517 checkcast (1, 4)
	518 org/apache/commons/math3/ode/events/FieldEventState (1, 4)
	520 astore (1, 4)
	521 #9 (1, 4)
	522 aload (1, 4)
	523 #9 (1, 4)
	524 aload (1, 4)
	525 #4 (1, 4)
	526 invokevirtual (1, 4)
	527 org/apache/commons/math3/ode/events/FieldEventState.stepAccepted:(Lorg/apache/commons/math3/ode/FieldODEStateAndDerivative;)V (1, 4)
	529 aload_0 (1, 4)
	530 aload_0 (1, 4)
	531 getfield (1, 4)
	532 org/apache/commons/math3/ode/AbstractFieldIntegrator.isLastStep:Z (1, 4)
	534 ifne (1, 4)
	535 11 (1, 4)
	537 aload (1, 4)
	538 #9 (1, 4)
	539 invokevirtual (1, 4)
	540 org/apache/commons/math3/ode/events/FieldEventState.stop:()Z (1, 4)
	542 ifeq (1, 4)
	543 7 (1, 4)
	545 iconst_1 (1, 4)
	546 goto (1, 4)
	547 4 (1, 4)
	549 iconst_0 (1, 4)
	550 putfield (1, 4)
	551 org/apache/commons/math3/ode/AbstractFieldIntegrator.isLastStep:Z (1, 4)
	553 goto (0, 4)
	554 -53 (0, 4)
	556 aload_0 (0, 4)
	557 aload_0 (0, 4)
	558 getfield (0, 4)
	559 org/apache/commons/math3/ode/AbstractFieldIntegrator.isLastStep:Z (0, 4)
	561 ifne (0, 4)
	562 43 (0, 4)
	564 aload (0, 4)
	565 #4 (0, 4)
	566 invokevirtual (0, 4)
	567 org/apache/commons/math3/ode/FieldODEStateAndDerivative.getTime:()Lorg/apache/commons/math3/RealFieldElement; (0, 4)
	569 aload_2 (0, 4)
	570 invokeinterface (0, 4)
	571 org/apache/commons/math3/RealFieldElement.abs:()Ljava/lang/Object; (0, 4)
	573 0 (0, 4)
	575 checkcast (0, 4)
	576 org/apache/commons/math3/RealFieldElement (0, 4)
	578 invokeinterface (0, 4)
	579 org/apache/commons/math3/RealFieldElement.getReal:()D (0, 4)
	581 0 (0, 4)
	583 checkcast (0, 4)
	584 org/apache/commons/math3/RealFieldElement (0, 4)
	586 invokeinterface (0, 4)
	587 org/apache/commons/math3/RealFieldElement.org/apache/commons/math3/util/FastMath (0, 4)
	589 0 (0, 4)
	591 aload_2 (0, 4)
	592 invokeinterface (0, 4)
	593 org/apache/commons/math3/RealFieldElement.org/apache/commons/math3/util/FastMath (0, 4)
	595 0 (0, 4)
	597 invokestatic (0, 4)
	598 org/apache/commons/math3/util/FastMath.ulp:(D)D (0, 4)
	600 dcmpg (0, 4)
	601 ifgt (0, 4)
	602 7 (0, 4)
	604 iconst_1 (0, 4)
	605 goto (0, 4)
	606 4 (0, 4)
	608 iconst_0 (0, 4)
	609 putfield (0, 4)
	610 org/apache/commons/math3/ode/AbstractFieldIntegrator.isLastStep:Z (0, 4)
	612 aload_0 (1, 4)
	613 getfield (1, 4)
	614 org/apache/commons/math3/ode/AbstractFieldIntegrator.stepHandlers:Ljava/util/Collection; (1, 4)
	616 invokeinterface (1, 4)
	617 java/util/Collection.java/util/Iterator (1, 4)
	619 0 (1, 4)
	621 astore (1, 4)
	622 #8 (1, 4)
	623 aload (1, 4)
	624 #8 (1, 4)
	625 invokeinterface (1, 4)
	626 java/util/Iterator.next:()Ljava/lang/Object; (1, 4)
	628 0 (1, 4)
	630 ifeq (1, 4)
	631 31 (1, 4)
	633 aload (1, 4)
	634 #8 (1, 4)
	635 invokeinterface (1, 4)
	636 java/util/Iterator.getEventHandler:()Lorg/apache/commons/math3/ode/events/FieldEventHandler; (1, 4)
	638 0 (1, 4)
	640 checkcast (1, 4)
	641 org/apache/commons/math3/ode/sampling/FieldStepHandler (1, 4)
	643 astore (1, 4)
	644 #9 (1, 4)
	645 aload (1, 4)
	646 #9 (1, 4)
	647 aload (1, 4)
	648 #7 (1, 4)
	649 aload_0 (1, 4)
	650 getfield (1, 4)
	651 org/apache/commons/math3/ode/AbstractFieldIntegrator.isLastStep:Z (1, 4)
	653 invokeinterface (1, 4)
	654 org/apache/commons/math3/ode/sampling/FieldStepHandler.resetOccurred:Z (1, 4)
	656 0 (1, 4)
	658 goto (0, 1)
	659 -35 (0, 1)
	661 aload (0, 1)
	662 #4 (0, 1)
	663 areturn (0, 1)

Method: sanityChecks
	0 ldc2_w (0, 0)
	1 1000.0 (0, 0)
	3 aload_1 (0, 0)
	4 invokevirtual (0, 0)
	5 org/apache/commons/math3/ode/FieldODEState.getTime:()Lorg/apache/commons/math3/RealFieldElement; (0, 0)
	7 invokeinterface (0, 0)
	8 org/apache/commons/math3/RealFieldElement.org/apache/commons/math3/util/FastMath (0, 0)
	10 0 (0, 0)
	12 invokestatic (0, 0)
	13 org/apache/commons/math3/util/FastMath.abs:(D)D (0, 0)
	15 aload_2 (0, 0)
	16 invokeinterface (0, 0)
	17 org/apache/commons/math3/RealFieldElement.org/apache/commons/math3/util/FastMath (0, 0)
	19 0 (0, 0)
	21 invokestatic (0, 0)
	22 org/apache/commons/math3/util/FastMath.abs:(D)D (0, 0)
	24 invokestatic (0, 0)
	25 org/apache/commons/math3/util/FastMath.max:(DD)D (0, 0)
	27 invokestatic (0, 0)
	28 org/apache/commons/math3/util/FastMath.ulp:(D)D (0, 0)
	30 dmul (0, 0)
	31 dstore_3 (0, 0)
	32 aload_1 (0, 0)
	33 invokevirtual (0, 0)
	34 org/apache/commons/math3/ode/FieldODEState.getTime:()Lorg/apache/commons/math3/RealFieldElement; (0, 0)
	36 aload_2 (0, 0)
	37 invokeinterface (0, 0)
	38 org/apache/commons/math3/RealFieldElement.abs:()Ljava/lang/Object; (0, 0)
	40 0 (0, 0)
	42 checkcast (0, 0)
	43 org/apache/commons/math3/RealFieldElement (0, 0)
	45 invokeinterface (0, 0)
	46 org/apache/commons/math3/RealFieldElement.getReal:()D (0, 0)
	48 0 (0, 0)
	50 checkcast (0, 0)
	51 org/apache/commons/math3/RealFieldElement (0, 0)
	53 invokeinterface (0, 0)
	54 org/apache/commons/math3/RealFieldElement.org/apache/commons/math3/util/FastMath (0, 0)
	56 0 (0, 0)
	58 dstore (0, 0)
	59 #5 (0, 0)
	60 dload (1, 1)
	61 #5 (1, 1)
	62 dload_3 (1, 1)
	63 dcmpg (1, 1)
	64 ifgt (1, 1)
	65 24 (1, 1)
	67 new (1, 1)
	68 org/apache/commons/math3/exception/NumberIsTooSmallException (1, 1)
	70 dup (1, 1)
	71 getstatic (1, 1)
	72 org/apache/commons/math3/exception/util/LocalizedFormats.TOO_SMALL_INTEGRATION_INTERVAL:Lorg/apache/commons/math3/exception/util/LocalizedFormats; (1, 1)
	74 dload (1, 1)
	75 #5 (1, 1)
	76 invokestatic (1, 1)
	77 java/lang/Double.valueOf:(D)Ljava/lang/Double; (1, 1)
	79 dload_3 (1, 1)
	80 invokestatic (1, 1)
	81 java/lang/Double.valueOf:(D)Ljava/lang/Double; (1, 1)
	83 iconst_0 (1, 1)
	84 invokespecial (1, 1)
	85 org/apache/commons/math3/exception/NumberIsTooSmallException.<init>:(Lorg/apache/commons/math3/exception/util/Localizable;Ljava/lang/Number;Ljava/lang/Number;Z)V (1, 1)
	87 athrow (1, 1)
	88 return (0, 0)

Method: resetOccurred
	0 aload_0 (0, 0)
	1 getfield (0, 0)
	2 org/apache/commons/math3/ode/AbstractFieldIntegrator.resetOccurred:Z (0, 0)
	4 ireturn (0, 0)

Method: setStepSize
	0 aload_0 (0, 0)
	1 aload_1 (0, 0)
	2 putfield (0, 0)
	3 org/apache/commons/math3/ode/AbstractFieldIntegrator.stepSize:Lorg/apache/commons/math3/RealFieldElement; (0, 0)
	5 return (0, 0)

Method: getStepSize
	0 aload_0 (0, 0)
	1 getfield (0, 0)
	2 org/apache/commons/math3/ode/AbstractFieldIntegrator.stepSize:Lorg/apache/commons/math3/RealFieldElement; (0, 0)
	4 areturn (0, 0)

Method: setStepStart
	0 aload_0 (0, 0)
	1 aload_1 (0, 0)
	2 putfield (0, 0)
	3 org/apache/commons/math3/ode/AbstractFieldIntegrator.stepStart:Lorg/apache/commons/math3/ode/FieldODEStateAndDerivative; (0, 0)
	5 return (0, 0)

Method: getStepStart
	0 aload_0 (0, 0)
	1 getfield (0, 0)
	2 org/apache/commons/math3/ode/AbstractFieldIntegrator.stepStart:Lorg/apache/commons/math3/ode/FieldODEStateAndDerivative; (0, 0)
	4 areturn (0, 0)

Method: setIsLastStep
	0 aload_0 (0, 0)
	1 iload_1 (0, 0)
	2 putfield (0, 0)
	3 org/apache/commons/math3/ode/AbstractFieldIntegrator.isLastStep:Z (0, 0)
	5 return (0, 0)

Method: isLastStep
	0 aload_0 (0, 0)
	1 getfield (0, 0)
	2 org/apache/commons/math3/ode/AbstractFieldIntegrator.isLastStep:Z (0, 0)
	4 ireturn (0, 0)

