Method: <init>
	0 aload_0 (0, 0)
	1 invokespecial (0, 0)
	2 java/lang/Object.<init>:()V (0, 0)
	4 aload_0 (0, 0)
	5 new (0, 0)
	6 java/util/ArrayList (0, 0)
	8 dup (0, 0)
	9 invokespecial (0, 0)
	10 java/util/ArrayList.<init>:()V (0, 0)
	12 putfield (0, 0)
	13 org/apache/commons/math3/ode/ContinuousOutputFieldModel.steps:Ljava/util/List; (0, 0)
	15 aload_0 (0, 0)
	16 aconst_null (0, 0)
	17 putfield (0, 0)
	18 org/apache/commons/math3/ode/ContinuousOutputFieldModel.initialTime:Lorg/apache/commons/math3/RealFieldElement; (0, 0)
	20 aload_0 (0, 0)
	21 aconst_null (0, 0)
	22 putfield (0, 0)
	23 org/apache/commons/math3/ode/ContinuousOutputFieldModel.finalTime:Lorg/apache/commons/math3/RealFieldElement; (0, 0)
	25 aload_0 (1, 4)
	26 iconst_1 (1, 4)
	27 putfield (1, 4)
	28 org/apache/commons/math3/ode/ContinuousOutputFieldModel.forward:Z (1, 4)
	30 aload_0 (1, 4)
	31 iconst_0 (1, 4)
	32 putfield (1, 4)
	33 org/apache/commons/math3/ode/ContinuousOutputFieldModel.index:I (1, 4)
	35 return (0, 0)

Method: append
	0 aload_1 (1, 1)
	1 getfield (1, 1)
	2 org/apache/commons/math3/ode/ContinuousOutputFieldModel.steps:Ljava/util/List; (1, 1)
	4 invokeinterface (1, 1)
	5 java/util/List.get:(I)Ljava/lang/Object; (1, 1)
	7 0 (1, 1)
	9 ifne (1, 1)
	10 4 (1, 1)
	12 return (1, 1)
	13 aload_0 (1, 1)
	14 getfield (1, 1)
	15 org/apache/commons/math3/ode/ContinuousOutputFieldModel.steps:Ljava/util/List; (1, 1)
	17 invokeinterface (1, 1)
	18 java/util/List.get:(I)Ljava/lang/Object; (1, 1)
	20 0 (1, 1)
	22 ifne (1, 1)
	23 22 (1, 1)
	25 aload_0 (1, 1)
	26 aload_1 (1, 1)
	27 getfield (1, 1)
	28 org/apache/commons/math3/ode/ContinuousOutputFieldModel.initialTime:Lorg/apache/commons/math3/RealFieldElement; (1, 1)
	30 putfield (1, 1)
	31 org/apache/commons/math3/ode/ContinuousOutputFieldModel.initialTime:Lorg/apache/commons/math3/RealFieldElement; (1, 1)
	33 aload_0 (2, 4)
	34 aload_1 (2, 4)
	35 getfield (2, 4)
	36 org/apache/commons/math3/ode/ContinuousOutputFieldModel.forward:Z (2, 4)
	38 putfield (2, 4)
	39 org/apache/commons/math3/ode/ContinuousOutputFieldModel.forward:Z (2, 4)
	41 goto (2, 4)
	42 280 (2, 4)
	44 aload_0 (3, 2)
	45 getfield (3, 2)
	46 org/apache/commons/math3/ode/ContinuousOutputFieldModel.steps:Ljava/util/List; (3, 2)
	48 iconst_0 (3, 2)
	49 invokeinterface (3, 2)
	50 java/util/List.org/apache/commons/math3/ode/sampling/FieldStepInterpolator (3, 2)
	52 0 (3, 2)
	54 checkcast (3, 2)
	55 org/apache/commons/math3/ode/sampling/FieldStepInterpolator (3, 2)
	57 invokeinterface (3, 2)
	58 org/apache/commons/math3/ode/sampling/FieldStepInterpolator.org/apache/commons/math3/ode/FieldODEStateAndDerivative (3, 2)
	60 0 (3, 2)
	62 astore_2 (3, 2)
	63 aload_1 (3, 2)
	64 getfield (3, 2)
	65 org/apache/commons/math3/ode/ContinuousOutputFieldModel.steps:Ljava/util/List; (3, 2)
	67 iconst_0 (3, 2)
	68 invokeinterface (3, 2)
	69 java/util/List.org/apache/commons/math3/ode/sampling/FieldStepInterpolator (3, 2)
	71 0 (3, 2)
	73 checkcast (3, 2)
	74 org/apache/commons/math3/ode/sampling/FieldStepInterpolator (3, 2)
	76 invokeinterface (3, 2)
	77 org/apache/commons/math3/ode/sampling/FieldStepInterpolator.org/apache/commons/math3/ode/FieldODEStateAndDerivative (3, 2)
	79 0 (3, 2)
	81 astore_3 (3, 2)
	82 aload_0 (3, 2)
	83 aload_2 (3, 2)
	84 invokevirtual (3, 2)
	85 org/apache/commons/math3/ode/FieldODEStateAndDerivative.getStateDimension:()I (3, 2)
	87 aload_3 (3, 2)
	88 invokevirtual (3, 2)
	89 org/apache/commons/math3/ode/FieldODEStateAndDerivative.getStateDimension:()I (3, 2)
	91 invokespecial (3, 2)
	92 org/apache/commons/math3/ode/ContinuousOutputFieldModel.checkDimensionsEquality:(II)V (3, 2)
	94 aload_0 (3, 2)
	95 aload_2 (3, 2)
	96 invokevirtual (3, 2)
	97 org/apache/commons/math3/ode/FieldODEStateAndDerivative.getNumberOfSecondaryStates:()I (3, 2)
	99 aload_3 (3, 2)
	100 invokevirtual (3, 2)
	101 org/apache/commons/math3/ode/FieldODEStateAndDerivative.getNumberOfSecondaryStates:()I (3, 2)
	103 invokespecial (3, 2)
	104 org/apache/commons/math3/ode/ContinuousOutputFieldModel.checkDimensionsEquality:(II)V (3, 2)
	106 iconst_0 (4, 4)
	107 istore (4, 4)
	108 #4 (4, 4)
	109 iload (4, 4)
	110 #4 (4, 4)
	111 aload_2 (4, 4)
	112 invokevirtual (4, 4)
	113 org/apache/commons/math3/ode/FieldODEStateAndDerivative.getNumberOfSecondaryStates:()I (4, 4)
	115 if_icmpge (4, 4)
	116 25 (4, 4)
	118 aload_0 (4, 4)
	119 aload_2 (4, 4)
	120 iload (4, 4)
	121 #4 (4, 4)
	122 invokevirtual (4, 4)
	123 org/apache/commons/math3/ode/FieldODEStateAndDerivative.getSecondaryStateDimension:(I)I (4, 4)
	125 aload_3 (4, 4)
	126 iload (4, 4)
	127 #4 (4, 4)
	128 invokevirtual (4, 4)
	129 org/apache/commons/math3/ode/FieldODEStateAndDerivative.getSecondaryStateDimension:(I)I (4, 4)
	131 invokespecial (4, 4)
	132 org/apache/commons/math3/ode/ContinuousOutputFieldModel.checkDimensionsEquality:(II)V (4, 4)
	134 iinc (4, 4)
	135 #4 (4, 4)
	136 -89 (4, 4)
	137 goto (4, 4)
	138 -28 (4, 4)
	140 aload_0 (4, 1)
	141 getfield (4, 1)
	142 org/apache/commons/math3/ode/ContinuousOutputFieldModel.forward:Z (4, 1)
	144 aload_1 (4, 1)
	145 getfield (4, 1)
	146 org/apache/commons/math3/ode/ContinuousOutputFieldModel.forward:Z (4, 1)
	148 ixor (4, 1)
	149 ifeq (4, 1)
	150 18 (4, 1)
	152 new (4, 1)
	153 org/apache/commons/math3/exception/MathIllegalArgumentException (4, 1)
	155 dup (4, 1)
	156 getstatic (4, 1)
	157 org/apache/commons/math3/exception/util/LocalizedFormats.PROPAGATION_DIRECTION_MISMATCH:Lorg/apache/commons/math3/exception/util/LocalizedFormats; (4, 1)
	159 iconst_0 (4, 1)
	160 anewarray (4, 1)
	161 java/lang/Object (4, 1)
	163 invokespecial (4, 1)
	164 org/apache/commons/math3/exception/MathIllegalArgumentException.<init>:(Lorg/apache/commons/math3/exception/util/Localizable;[Ljava/lang/Object;)V (4, 1)
	166 athrow (4, 1)
	167 aload_0 (3, 2)
	168 getfield (3, 2)
	169 org/apache/commons/math3/ode/ContinuousOutputFieldModel.steps:Ljava/util/List; (3, 2)
	171 aload_0 (3, 2)
	172 getfield (3, 2)
	173 org/apache/commons/math3/ode/ContinuousOutputFieldModel.index:I (3, 2)
	175 invokeinterface (3, 2)
	176 java/util/List.org/apache/commons/math3/ode/sampling/FieldStepInterpolator (3, 2)
	178 0 (3, 2)
	180 checkcast (3, 2)
	181 org/apache/commons/math3/ode/sampling/FieldStepInterpolator (3, 2)
	183 astore (3, 2)
	184 #4 (3, 2)
	185 aload (3, 2)
	186 #4 (3, 2)
	187 invokeinterface (3, 2)
	188 org/apache/commons/math3/ode/sampling/FieldStepInterpolator.getTime:()Lorg/apache/commons/math3/RealFieldElement; (3, 2)
	190 0 (3, 2)
	192 invokevirtual (3, 2)
	193 org/apache/commons/math3/ode/FieldODEStateAndDerivative.getTime:()Lorg/apache/commons/math3/RealFieldElement; (3, 2)
	195 astore (3, 2)
	196 #5 (3, 2)
	197 aload (3, 2)
	198 #4 (3, 2)
	199 invokeinterface (3, 2)
	200 org/apache/commons/math3/ode/sampling/FieldStepInterpolator.org/apache/commons/math3/ode/FieldODEStateAndDerivative (3, 2)
	202 0 (3, 2)
	204 invokevirtual (3, 2)
	205 org/apache/commons/math3/ode/FieldODEStateAndDerivative.getTime:()Lorg/apache/commons/math3/RealFieldElement; (3, 2)
	207 astore (3, 2)
	208 #6 (3, 2)
	209 aload (3, 2)
	210 #5 (3, 2)
	211 aload (3, 2)
	212 #6 (3, 2)
	213 invokeinterface (3, 2)
	214 org/apache/commons/math3/RealFieldElement.org/apache/commons/math3/RealFieldElement (3, 2)
	216 0 (3, 2)
	218 checkcast (3, 2)
	219 org/apache/commons/math3/RealFieldElement (3, 2)
	221 astore (3, 2)
	222 #7 (3, 2)
	223 aload_1 (3, 2)
	224 invokevirtual (3, 2)
	225 org/apache/commons/math3/ode/ContinuousOutputFieldModel.getInitialTime:()Lorg/apache/commons/math3/RealFieldElement; (3, 2)
	227 aload (3, 2)
	228 #5 (3, 2)
	229 invokeinterface (3, 2)
	230 org/apache/commons/math3/RealFieldElement.org/apache/commons/math3/RealFieldElement (3, 2)
	232 0 (3, 2)
	234 checkcast (3, 2)
	235 org/apache/commons/math3/RealFieldElement (3, 2)
	237 astore (3, 2)
	238 #8 (3, 2)
	239 aload (4, 1)
	240 #8 (4, 1)
	241 invokeinterface (4, 1)
	242 org/apache/commons/math3/RealFieldElement.multiply:(D)Ljava/lang/Object; (4, 1)
	244 0 (4, 1)
	246 checkcast (4, 1)
	247 org/apache/commons/math3/RealFieldElement (4, 1)
	249 aload (4, 1)
	250 #7 (4, 1)
	251 invokeinterface (4, 1)
	252 org/apache/commons/math3/RealFieldElement.multiply:(D)Ljava/lang/Object; (4, 1)
	254 0 (4, 1)
	256 checkcast (4, 1)
	257 org/apache/commons/math3/RealFieldElement (4, 1)
	259 ldc2_w (4, 1)
	260 0.001 (4, 1)
	262 invokeinterface (4, 1)
	263 org/apache/commons/math3/RealFieldElement.getReal:()D (4, 1)
	265 0 (4, 1)
	267 invokeinterface (4, 1)
	268 org/apache/commons/math3/RealFieldElement.org/apache/commons/math3/RealFieldElement (4, 1)
	270 0 (4, 1)
	272 checkcast (4, 1)
	273 org/apache/commons/math3/RealFieldElement (4, 1)
	275 invokeinterface (4, 1)
	276 org/apache/commons/math3/RealFieldElement.HOLE_BETWEEN_MODELS_TIME_RANGES:Lorg/apache/commons/math3/exception/util/LocalizedFormats; (4, 1)
	278 0 (4, 1)
	280 dconst_0 (4, 1)
	281 dcmpl (4, 1)
	282 ifle (4, 1)
	283 39 (4, 1)
	285 new (4, 1)
	286 org/apache/commons/math3/exception/MathIllegalArgumentException (4, 1)
	288 dup (4, 1)
	289 getstatic (4, 1)
	290 org/apache/commons/math3/exception/util/LocalizedFormats.HOLE_BETWEEN_MODELS_TIME_RANGES:Lorg/apache/commons/math3/exception/util/LocalizedFormats; (4, 1)
	292 iconst_1 (4, 1)
	293 anewarray (4, 1)
	294 java/lang/Object (4, 1)
	296 dup (4, 1)
	297 iconst_0 (4, 1)
	298 aload (4, 1)
	299 #8 (4, 1)
	300 invokeinterface (4, 1)
	301 org/apache/commons/math3/RealFieldElement.multiply:(D)Ljava/lang/Object; (4, 1)
	303 0 (4, 1)
	305 checkcast (4, 1)
	306 org/apache/commons/math3/RealFieldElement (4, 1)
	308 invokeinterface (4, 1)
	309 org/apache/commons/math3/RealFieldElement.HOLE_BETWEEN_MODELS_TIME_RANGES:Lorg/apache/commons/math3/exception/util/LocalizedFormats; (4, 1)
	311 0 (4, 1)
	313 invokestatic (4, 1)
	314 java/lang/Double.valueOf:(D)Ljava/lang/Double; (4, 1)
	316 aastore (4, 1)
	317 invokespecial (4, 1)
	318 org/apache/commons/math3/exception/MathIllegalArgumentException.<init>:(Lorg/apache/commons/math3/exception/util/Localizable;[Ljava/lang/Object;)V (4, 1)
	320 athrow (4, 1)
	321 aload_1 (1, 4)
	322 getfield (1, 4)
	323 org/apache/commons/math3/ode/ContinuousOutputFieldModel.steps:Ljava/util/List; (1, 4)
	325 invokeinterface (1, 4)
	326 java/util/List.java/util/Iterator (1, 4)
	328 0 (1, 4)
	330 astore_2 (1, 4)
	331 aload_2 (1, 4)
	332 invokeinterface (1, 4)
	333 java/util/Iterator.next:()Ljava/lang/Object; (1, 4)
	335 0 (1, 4)
	337 ifeq (1, 4)
	338 27 (1, 4)
	340 aload_2 (1, 4)
	341 invokeinterface (1, 4)
	342 java/util/Iterator.add:(Ljava/lang/Object;)Z (1, 4)
	344 0 (1, 4)
	346 checkcast (1, 4)
	347 org/apache/commons/math3/ode/sampling/FieldStepInterpolator (1, 4)
	349 astore_3 (1, 4)
	350 aload_0 (1, 4)
	351 getfield (1, 4)
	352 org/apache/commons/math3/ode/ContinuousOutputFieldModel.steps:Ljava/util/List; (1, 4)
	354 aload_3 (1, 4)
	355 invokeinterface (1, 4)
	356 java/util/List.org/apache/commons/math3/exception/DimensionMismatchException (1, 4)
	358 0 (1, 4)
	360 pop (1, 4)
	361 goto (0, 0)
	362 -30 (0, 0)
	364 aload_0 (0, 0)
	365 aload_0 (0, 0)
	366 getfield (0, 0)
	367 org/apache/commons/math3/ode/ContinuousOutputFieldModel.steps:Ljava/util/List; (0, 0)
	369 invokeinterface (0, 0)
	370 java/util/List.get:(I)Ljava/lang/Object; (0, 0)
	372 0 (0, 0)
	374 iconst_1 (0, 0)
	375 isub (0, 0)
	376 putfield (0, 0)
	377 org/apache/commons/math3/ode/ContinuousOutputFieldModel.index:I (0, 0)
	379 aload_0 (0, 0)
	380 aload_0 (0, 0)
	381 getfield (0, 0)
	382 org/apache/commons/math3/ode/ContinuousOutputFieldModel.steps:Ljava/util/List; (0, 0)
	384 aload_0 (0, 0)
	385 getfield (0, 0)
	386 org/apache/commons/math3/ode/ContinuousOutputFieldModel.index:I (0, 0)
	388 invokeinterface (0, 0)
	389 java/util/List.org/apache/commons/math3/ode/sampling/FieldStepInterpolator (0, 0)
	391 0 (0, 0)
	393 checkcast (0, 0)
	394 org/apache/commons/math3/ode/sampling/FieldStepInterpolator (0, 0)
	396 invokeinterface (0, 0)
	397 org/apache/commons/math3/ode/sampling/FieldStepInterpolator.getTime:()Lorg/apache/commons/math3/RealFieldElement; (0, 0)
	399 0 (0, 0)
	401 invokevirtual (0, 0)
	402 org/apache/commons/math3/ode/FieldODEStateAndDerivative.getTime:()Lorg/apache/commons/math3/RealFieldElement; (0, 0)
	404 putfield (0, 0)
	405 org/apache/commons/math3/ode/ContinuousOutputFieldModel.finalTime:Lorg/apache/commons/math3/RealFieldElement; (0, 0)
	407 return (0, 0)

Method: checkDimensionsEquality
	0 iload_1 (1, 1)
	1 iload_2 (1, 1)
	2 if_icmpeq (1, 1)
	3 13 (1, 1)
	5 new (1, 1)
	6 org/apache/commons/math3/exception/DimensionMismatchException (1, 1)
	8 dup (1, 1)
	9 iload_2 (1, 1)
	10 iload_1 (1, 1)
	11 invokespecial (1, 1)
	12 org/apache/commons/math3/exception/DimensionMismatchException.<init>:(II)V (1, 1)
	14 athrow (1, 1)
	15 return (0, 0)

Method: init
	0 aload_0 (0, 0)
	1 aload_1 (0, 0)
	2 invokevirtual (0, 0)
	3 org/apache/commons/math3/ode/FieldODEStateAndDerivative.getTime:()Lorg/apache/commons/math3/RealFieldElement; (0, 0)
	5 putfield (0, 0)
	6 org/apache/commons/math3/ode/ContinuousOutputFieldModel.initialTime:Lorg/apache/commons/math3/RealFieldElement; (0, 0)
	8 aload_0 (0, 0)
	9 aload_2 (0, 0)
	10 putfield (0, 0)
	11 org/apache/commons/math3/ode/ContinuousOutputFieldModel.finalTime:Lorg/apache/commons/math3/RealFieldElement; (0, 0)
	13 aload_0 (1, 4)
	14 iconst_1 (1, 4)
	15 putfield (1, 4)
	16 org/apache/commons/math3/ode/ContinuousOutputFieldModel.forward:Z (1, 4)
	18 aload_0 (1, 4)
	19 iconst_0 (1, 4)
	20 putfield (1, 4)
	21 org/apache/commons/math3/ode/ContinuousOutputFieldModel.index:I (1, 4)
	23 aload_0 (1, 4)
	24 getfield (1, 4)
	25 org/apache/commons/math3/ode/ContinuousOutputFieldModel.steps:Ljava/util/List; (1, 4)
	27 invokeinterface (1, 4)
	28 java/util/List.isForward:()Z (1, 4)
	30 0 (1, 4)
	32 return (0, 4)

Method: handleStep
	0 aload_0 (1, 1)
	1 getfield (1, 1)
	2 org/apache/commons/math3/ode/ContinuousOutputFieldModel.steps:Ljava/util/List; (1, 1)
	4 invokeinterface (1, 1)
	5 java/util/List.get:(I)Ljava/lang/Object; (1, 1)
	7 0 (1, 1)
	9 ifne (1, 1)
	10 26 (1, 1)
	12 aload_0 (1, 1)
	13 aload_1 (1, 1)
	14 invokeinterface (1, 1)
	15 org/apache/commons/math3/ode/sampling/FieldStepInterpolator.org/apache/commons/math3/ode/FieldODEStateAndDerivative (1, 1)
	17 0 (1, 1)
	19 invokevirtual (1, 1)
	20 org/apache/commons/math3/ode/FieldODEStateAndDerivative.getTime:()Lorg/apache/commons/math3/RealFieldElement; (1, 1)
	22 putfield (1, 1)
	23 org/apache/commons/math3/ode/ContinuousOutputFieldModel.initialTime:Lorg/apache/commons/math3/RealFieldElement; (1, 1)
	25 aload_0 (2, 4)
	26 aload_1 (2, 4)
	27 invokeinterface (2, 4)
	28 org/apache/commons/math3/ode/sampling/FieldStepInterpolator.add:(Ljava/lang/Object;)Ljava/lang/Object; (2, 4)
	30 0 (2, 4)
	32 putfield (2, 4)
	33 org/apache/commons/math3/ode/ContinuousOutputFieldModel.forward:Z (2, 4)
	35 aload_0 (0, 0)
	36 getfield (0, 0)
	37 org/apache/commons/math3/ode/ContinuousOutputFieldModel.steps:Ljava/util/List; (0, 0)
	39 aload_1 (0, 0)
	40 invokeinterface (0, 0)
	41 java/util/List.org/apache/commons/math3/exception/DimensionMismatchException (0, 0)
	43 0 (0, 0)
	45 pop (0, 0)
	46 iload_2 (1, 1)
	47 ifeq (1, 1)
	48 31 (1, 1)
	50 aload_0 (1, 1)
	51 aload_1 (1, 1)
	52 invokeinterface (1, 1)
	53 org/apache/commons/math3/ode/sampling/FieldStepInterpolator.getTime:()Lorg/apache/commons/math3/RealFieldElement; (1, 1)
	55 0 (1, 1)
	57 invokevirtual (1, 1)
	58 org/apache/commons/math3/ode/FieldODEStateAndDerivative.getTime:()Lorg/apache/commons/math3/RealFieldElement; (1, 1)
	60 putfield (1, 1)
	61 org/apache/commons/math3/ode/ContinuousOutputFieldModel.finalTime:Lorg/apache/commons/math3/RealFieldElement; (1, 1)
	63 aload_0 (1, 1)
	64 aload_0 (1, 1)
	65 getfield (1, 1)
	66 org/apache/commons/math3/ode/ContinuousOutputFieldModel.steps:Ljava/util/List; (1, 1)
	68 invokeinterface (1, 1)
	69 java/util/List.get:(I)Ljava/lang/Object; (1, 1)
	71 0 (1, 1)
	73 iconst_1 (1, 1)
	74 isub (1, 1)
	75 putfield (1, 1)
	76 org/apache/commons/math3/ode/ContinuousOutputFieldModel.index:I (1, 1)
	78 return (0, 0)

Method: getInitialTime
	0 aload_0 (0, 0)
	1 getfield (0, 0)
	2 org/apache/commons/math3/ode/ContinuousOutputFieldModel.initialTime:Lorg/apache/commons/math3/RealFieldElement; (0, 0)
	4 areturn (0, 0)

Method: getFinalTime
	0 aload_0 (0, 0)
	1 getfield (0, 0)
	2 org/apache/commons/math3/ode/ContinuousOutputFieldModel.finalTime:Lorg/apache/commons/math3/RealFieldElement; (0, 0)
	4 areturn (0, 0)

Method: getInterpolatedState
	0 iconst_0 (0, 0)
	1 istore_2 (0, 0)
	2 aload_0 (0, 0)
	3 getfield (0, 0)
	4 org/apache/commons/math3/ode/ContinuousOutputFieldModel.steps:Ljava/util/List; (0, 0)
	6 iload_2 (0, 0)
	7 invokeinterface (0, 0)
	8 java/util/List.org/apache/commons/math3/ode/sampling/FieldStepInterpolator (0, 0)
	10 0 (0, 0)
	12 checkcast (0, 0)
	13 org/apache/commons/math3/ode/sampling/FieldStepInterpolator (0, 0)
	15 astore_3 (0, 0)
	16 aload_3 (0, 0)
	17 invokeinterface (0, 0)
	18 org/apache/commons/math3/ode/sampling/FieldStepInterpolator.org/apache/commons/math3/ode/FieldODEStateAndDerivative (0, 0)
	20 0 (0, 0)
	22 invokevirtual (0, 0)
	23 org/apache/commons/math3/ode/FieldODEStateAndDerivative.getTime:()Lorg/apache/commons/math3/RealFieldElement; (0, 0)
	25 aload_3 (0, 0)
	26 invokeinterface (0, 0)
	27 org/apache/commons/math3/ode/sampling/FieldStepInterpolator.getTime:()Lorg/apache/commons/math3/RealFieldElement; (0, 0)
	29 0 (0, 0)
	31 invokevirtual (0, 0)
	32 org/apache/commons/math3/ode/FieldODEStateAndDerivative.getTime:()Lorg/apache/commons/math3/RealFieldElement; (0, 0)
	34 invokeinterface (0, 0)
	35 org/apache/commons/math3/RealFieldElement.locatePoint:(Lorg/apache/commons/math3/RealFieldElement;Lorg/apache/commons/math3/ode/sampling/FieldStepInterpolator;)I (0, 0)
	37 0 (0, 0)
	39 checkcast (0, 0)
	40 org/apache/commons/math3/RealFieldElement (0, 0)
	42 ldc2_w (0, 0)
	43 0.5 (0, 0)
	45 invokeinterface (0, 0)
	46 org/apache/commons/math3/RealFieldElement.getReal:()D (0, 0)
	48 0 (0, 0)
	50 checkcast (0, 0)
	51 org/apache/commons/math3/RealFieldElement (0, 0)
	53 astore (0, 0)
	54 #4 (0, 0)
	55 aload_0 (0, 0)
	56 getfield (0, 0)
	57 org/apache/commons/math3/ode/ContinuousOutputFieldModel.steps:Ljava/util/List; (0, 0)
	59 invokeinterface (0, 0)
	60 java/util/List.get:(I)Ljava/lang/Object; (0, 0)
	62 0 (0, 0)
	64 iconst_1 (0, 0)
	65 isub (0, 0)
	66 istore (0, 0)
	67 #5 (0, 0)
	68 aload_0 (0, 0)
	69 getfield (0, 0)
	70 org/apache/commons/math3/ode/ContinuousOutputFieldModel.steps:Ljava/util/List; (0, 0)
	72 iload (0, 0)
	73 #5 (0, 0)
	74 invokeinterface (0, 0)
	75 java/util/List.org/apache/commons/math3/ode/sampling/FieldStepInterpolator (0, 0)
	77 0 (0, 0)
	79 checkcast (0, 0)
	80 org/apache/commons/math3/ode/sampling/FieldStepInterpolator (0, 0)
	82 astore (0, 0)
	83 #6 (0, 0)
	84 aload (0, 0)
	85 #6 (0, 0)
	86 invokeinterface (0, 0)
	87 org/apache/commons/math3/ode/sampling/FieldStepInterpolator.org/apache/commons/math3/ode/FieldODEStateAndDerivative (0, 0)
	89 0 (0, 0)
	91 invokevirtual (0, 0)
	92 org/apache/commons/math3/ode/FieldODEStateAndDerivative.getTime:()Lorg/apache/commons/math3/RealFieldElement; (0, 0)
	94 aload (0, 0)
	95 #6 (0, 0)
	96 invokeinterface (0, 0)
	97 org/apache/commons/math3/ode/sampling/FieldStepInterpolator.getTime:()Lorg/apache/commons/math3/RealFieldElement; (0, 0)
	99 0 (0, 0)
	101 invokevirtual (0, 0)
	102 org/apache/commons/math3/ode/FieldODEStateAndDerivative.getTime:()Lorg/apache/commons/math3/RealFieldElement; (0, 0)
	104 invokeinterface (0, 0)
	105 org/apache/commons/math3/RealFieldElement.locatePoint:(Lorg/apache/commons/math3/RealFieldElement;Lorg/apache/commons/math3/ode/sampling/FieldStepInterpolator;)I (0, 0)
	107 0 (0, 0)
	109 checkcast (0, 0)
	110 org/apache/commons/math3/RealFieldElement (0, 0)
	112 ldc2_w (0, 0)
	113 0.5 (0, 0)
	115 invokeinterface (0, 0)
	116 org/apache/commons/math3/RealFieldElement.getReal:()D (0, 0)
	118 0 (0, 0)
	120 checkcast (0, 0)
	121 org/apache/commons/math3/RealFieldElement (0, 0)
	123 astore (0, 0)
	124 #7 (0, 0)
	125 aload_0 (1, 1)
	126 aload_1 (1, 1)
	127 aload_3 (1, 1)
	128 invokespecial (1, 1)
	129 org/apache/commons/math3/ode/ContinuousOutputFieldModel.locatePoint:(Lorg/apache/commons/math3/RealFieldElement;Lorg/apache/commons/math3/ode/sampling/FieldStepInterpolator;)I (1, 1)
	131 ifgt (1, 1)
	132 16 (1, 1)
	134 aload_0 (1, 1)
	135 iload_2 (1, 1)
	136 putfield (1, 1)
	137 org/apache/commons/math3/ode/ContinuousOutputFieldModel.index:I (1, 1)
	139 aload_3 (1, 1)
	140 aload_1 (1, 1)
	141 invokeinterface (1, 1)
	142 org/apache/commons/math3/ode/sampling/FieldStepInterpolator.subtract:(D)Ljava/lang/Object; (1, 1)
	144 0 (1, 1)
	146 areturn (1, 1)
	147 aload_0 (1, 1)
	148 aload_1 (1, 1)
	149 aload (1, 1)
	150 #6 (1, 1)
	151 invokespecial (1, 1)
	152 org/apache/commons/math3/ode/ContinuousOutputFieldModel.locatePoint:(Lorg/apache/commons/math3/RealFieldElement;Lorg/apache/commons/math3/ode/sampling/FieldStepInterpolator;)I (1, 1)
	154 iflt (1, 1)
	155 18 (1, 1)
	157 aload_0 (1, 1)
	158 iload (1, 1)
	159 #5 (1, 1)
	160 putfield (1, 1)
	161 org/apache/commons/math3/ode/ContinuousOutputFieldModel.index:I (1, 1)
	163 aload (1, 1)
	164 #6 (1, 1)
	165 aload_1 (1, 1)
	166 invokeinterface (1, 1)
	167 org/apache/commons/math3/ode/sampling/FieldStepInterpolator.subtract:(D)Ljava/lang/Object; (1, 1)
	169 0 (1, 1)
	171 areturn (1, 1)
	172 iload (1, 3)
	173 #5 (1, 3)
	174 iload_2 (1, 3)
	175 isub (1, 3)
	176 iconst_5 (1, 3)
	177 if_icmple (1, 3)
	178 607 (1, 3)
	180 aload_0 (1, 3)
	181 getfield (1, 3)
	182 org/apache/commons/math3/ode/ContinuousOutputFieldModel.steps:Ljava/util/List; (1, 3)
	184 aload_0 (1, 3)
	185 getfield (1, 3)
	186 org/apache/commons/math3/ode/ContinuousOutputFieldModel.index:I (1, 3)
	188 invokeinterface (1, 3)
	189 java/util/List.org/apache/commons/math3/ode/sampling/FieldStepInterpolator (1, 3)
	191 0 (1, 3)
	193 checkcast (1, 3)
	194 org/apache/commons/math3/ode/sampling/FieldStepInterpolator (1, 3)
	196 astore (1, 3)
	197 #8 (1, 3)
	198 aload_0 (1, 3)
	199 aload_1 (1, 3)
	200 aload (1, 3)
	201 #8 (1, 3)
	202 invokespecial (1, 3)
	203 org/apache/commons/math3/ode/ContinuousOutputFieldModel.locatePoint:(Lorg/apache/commons/math3/RealFieldElement;Lorg/apache/commons/math3/ode/sampling/FieldStepInterpolator;)I (1, 3)
	205 istore (1, 3)
	206 #9 (1, 3)
	207 iload (2, 1)
	208 #9 (2, 1)
	209 ifge (2, 1)
	210 53 (2, 1)
	212 aload_0 (2, 1)
	213 getfield (2, 1)
	214 org/apache/commons/math3/ode/ContinuousOutputFieldModel.index:I (2, 1)
	216 istore (2, 1)
	217 #5 (2, 1)
	218 aload (2, 1)
	219 #8 (2, 1)
	220 invokeinterface (2, 1)
	221 org/apache/commons/math3/ode/sampling/FieldStepInterpolator.org/apache/commons/math3/ode/FieldODEStateAndDerivative (2, 1)
	223 0 (2, 1)
	225 invokevirtual (2, 1)
	226 org/apache/commons/math3/ode/FieldODEStateAndDerivative.getTime:()Lorg/apache/commons/math3/RealFieldElement; (2, 1)
	228 aload (2, 1)
	229 #8 (2, 1)
	230 invokeinterface (2, 1)
	231 org/apache/commons/math3/ode/sampling/FieldStepInterpolator.getTime:()Lorg/apache/commons/math3/RealFieldElement; (2, 1)
	233 0 (2, 1)
	235 invokevirtual (2, 1)
	236 org/apache/commons/math3/ode/FieldODEStateAndDerivative.getTime:()Lorg/apache/commons/math3/RealFieldElement; (2, 1)
	238 invokeinterface (2, 1)
	239 org/apache/commons/math3/RealFieldElement.locatePoint:(Lorg/apache/commons/math3/RealFieldElement;Lorg/apache/commons/math3/ode/sampling/FieldStepInterpolator;)I (2, 1)
	241 0 (2, 1)
	243 checkcast (2, 1)
	244 org/apache/commons/math3/RealFieldElement (2, 1)
	246 ldc2_w (2, 1)
	247 0.5 (2, 1)
	249 invokeinterface (2, 1)
	250 org/apache/commons/math3/RealFieldElement.getReal:()D (2, 1)
	252 0 (2, 1)
	254 checkcast (2, 1)
	255 org/apache/commons/math3/RealFieldElement (2, 1)
	257 astore (2, 1)
	258 #7 (2, 1)
	259 goto (2, 1)
	260 66 (2, 1)
	262 iload (3, 1)
	263 #9 (3, 1)
	264 ifle (3, 1)
	265 52 (3, 1)
	267 aload_0 (3, 1)
	268 getfield (3, 1)
	269 org/apache/commons/math3/ode/ContinuousOutputFieldModel.index:I (3, 1)
	271 istore_2 (3, 1)
	272 aload (3, 1)
	273 #8 (3, 1)
	274 invokeinterface (3, 1)
	275 org/apache/commons/math3/ode/sampling/FieldStepInterpolator.org/apache/commons/math3/ode/FieldODEStateAndDerivative (3, 1)
	277 0 (3, 1)
	279 invokevirtual (3, 1)
	280 org/apache/commons/math3/ode/FieldODEStateAndDerivative.getTime:()Lorg/apache/commons/math3/RealFieldElement; (3, 1)
	282 aload (3, 1)
	283 #8 (3, 1)
	284 invokeinterface (3, 1)
	285 org/apache/commons/math3/ode/sampling/FieldStepInterpolator.getTime:()Lorg/apache/commons/math3/RealFieldElement; (3, 1)
	287 0 (3, 1)
	289 invokevirtual (3, 1)
	290 org/apache/commons/math3/ode/FieldODEStateAndDerivative.getTime:()Lorg/apache/commons/math3/RealFieldElement; (3, 1)
	292 invokeinterface (3, 1)
	293 org/apache/commons/math3/RealFieldElement.locatePoint:(Lorg/apache/commons/math3/RealFieldElement;Lorg/apache/commons/math3/ode/sampling/FieldStepInterpolator;)I (3, 1)
	295 0 (3, 1)
	297 checkcast (3, 1)
	298 org/apache/commons/math3/RealFieldElement (3, 1)
	300 ldc2_w (3, 1)
	301 0.5 (3, 1)
	303 invokeinterface (3, 1)
	304 org/apache/commons/math3/RealFieldElement.getReal:()D (3, 1)
	306 0 (3, 1)
	308 checkcast (3, 1)
	309 org/apache/commons/math3/RealFieldElement (3, 1)
	311 astore (3, 1)
	312 #4 (3, 1)
	313 goto (3, 1)
	314 12 (3, 1)
	316 aload (4, 2)
	317 #8 (4, 2)
	318 aload_1 (4, 2)
	319 invokeinterface (4, 2)
	320 org/apache/commons/math3/ode/sampling/FieldStepInterpolator.subtract:(D)Ljava/lang/Object; (4, 2)
	322 0 (4, 2)
	324 areturn (4, 2)
	325 iload_2 (1, 3)
	326 iload (1, 3)
	327 #5 (1, 3)
	328 iadd (1, 3)
	329 iconst_2 (1, 3)
	330 idiv (1, 3)
	331 istore (1, 3)
	332 #10 (1, 3)
	333 aload_0 (1, 3)
	334 getfield (1, 3)
	335 org/apache/commons/math3/ode/ContinuousOutputFieldModel.steps:Ljava/util/List; (1, 3)
	337 iload (1, 3)
	338 #10 (1, 3)
	339 invokeinterface (1, 3)
	340 java/util/List.org/apache/commons/math3/ode/sampling/FieldStepInterpolator (1, 3)
	342 0 (1, 3)
	344 checkcast (1, 3)
	345 org/apache/commons/math3/ode/sampling/FieldStepInterpolator (1, 3)
	347 astore (1, 3)
	348 #11 (1, 3)
	349 aload (1, 3)
	350 #11 (1, 3)
	351 invokeinterface (1, 3)
	352 org/apache/commons/math3/ode/sampling/FieldStepInterpolator.org/apache/commons/math3/ode/FieldODEStateAndDerivative (1, 3)
	354 0 (1, 3)
	356 invokevirtual (1, 3)
	357 org/apache/commons/math3/ode/FieldODEStateAndDerivative.getTime:()Lorg/apache/commons/math3/RealFieldElement; (1, 3)
	359 aload (1, 3)
	360 #11 (1, 3)
	361 invokeinterface (1, 3)
	362 org/apache/commons/math3/ode/sampling/FieldStepInterpolator.getTime:()Lorg/apache/commons/math3/RealFieldElement; (1, 3)
	364 0 (1, 3)
	366 invokevirtual (1, 3)
	367 org/apache/commons/math3/ode/FieldODEStateAndDerivative.getTime:()Lorg/apache/commons/math3/RealFieldElement; (1, 3)
	369 invokeinterface (1, 3)
	370 org/apache/commons/math3/RealFieldElement.locatePoint:(Lorg/apache/commons/math3/RealFieldElement;Lorg/apache/commons/math3/ode/sampling/FieldStepInterpolator;)I (1, 3)
	372 0 (1, 3)
	374 checkcast (1, 3)
	375 org/apache/commons/math3/RealFieldElement (1, 3)
	377 ldc2_w (1, 3)
	378 0.5 (1, 3)
	380 invokeinterface (1, 3)
	381 org/apache/commons/math3/RealFieldElement.getReal:()D (1, 3)
	383 0 (1, 3)
	385 checkcast (1, 3)
	386 org/apache/commons/math3/RealFieldElement (1, 3)
	388 astore (1, 3)
	389 #12 (1, 3)
	390 aload (2, 1)
	391 #12 (2, 1)
	392 aload (2, 1)
	393 #4 (2, 1)
	394 invokeinterface (2, 1)
	395 org/apache/commons/math3/RealFieldElement.org/apache/commons/math3/RealFieldElement (2, 1)
	397 0 (2, 1)
	399 checkcast (2, 1)
	400 org/apache/commons/math3/RealFieldElement (2, 1)
	402 invokeinterface (2, 1)
	403 org/apache/commons/math3/RealFieldElement.multiply:(D)Ljava/lang/Object; (2, 1)
	405 0 (2, 1)
	407 checkcast (2, 1)
	408 org/apache/commons/math3/RealFieldElement (2, 1)
	410 ldc2_w (2, 1)
	411 1e-06 (2, 1)
	413 invokeinterface (2, 1)
	414 org/apache/commons/math3/RealFieldElement.multiply:(Ljava/lang/Object;)Ljava/lang/Object; (2, 1)
	416 0 (2, 1)
	418 checkcast (2, 1)
	419 org/apache/commons/math3/RealFieldElement (2, 1)
	421 invokeinterface (2, 1)
	422 org/apache/commons/math3/RealFieldElement.HOLE_BETWEEN_MODELS_TIME_RANGES:Lorg/apache/commons/math3/exception/util/LocalizedFormats; (2, 1)
	424 0 (2, 1)
	426 dconst_0 (2, 1)
	427 dcmpg (2, 1)
	428 iflt (2, 1)
	429 44 (2, 1)
	431 aload (2, 1)
	432 #7 (2, 1)
	433 aload (2, 1)
	434 #12 (2, 1)
	435 invokeinterface (2, 1)
	436 org/apache/commons/math3/RealFieldElement.org/apache/commons/math3/RealFieldElement (2, 1)
	438 0 (2, 1)
	440 checkcast (2, 1)
	441 org/apache/commons/math3/RealFieldElement (2, 1)
	443 invokeinterface (2, 1)
	444 org/apache/commons/math3/RealFieldElement.multiply:(D)Ljava/lang/Object; (2, 1)
	446 0 (2, 1)
	448 checkcast (2, 1)
	449 org/apache/commons/math3/RealFieldElement (2, 1)
	451 ldc2_w (2, 1)
	452 1e-06 (2, 1)
	454 invokeinterface (2, 1)
	455 org/apache/commons/math3/RealFieldElement.multiply:(Ljava/lang/Object;)Ljava/lang/Object; (2, 1)
	457 0 (2, 1)
	459 checkcast (2, 1)
	460 org/apache/commons/math3/RealFieldElement (2, 1)
	462 invokeinterface (2, 1)
	463 org/apache/commons/math3/RealFieldElement.HOLE_BETWEEN_MODELS_TIME_RANGES:Lorg/apache/commons/math3/exception/util/LocalizedFormats; (2, 1)
	465 0 (2, 1)
	467 dconst_0 (2, 1)
	468 dcmpg (2, 1)
	469 ifge (2, 1)
	470 12 (2, 1)
	472 aload_0 (2, 1)
	473 iload (2, 1)
	474 #10 (2, 1)
	475 putfield (2, 1)
	476 org/apache/commons/math3/ode/ContinuousOutputFieldModel.index:I (2, 1)
	478 goto (2, 1)
	479 233 (2, 1)
	481 aload (3, 2)
	482 #7 (3, 2)
	483 aload (3, 2)
	484 #12 (3, 2)
	485 invokeinterface (3, 2)
	486 org/apache/commons/math3/RealFieldElement.org/apache/commons/math3/RealFieldElement (3, 2)
	488 0 (3, 2)
	490 checkcast (3, 2)
	491 org/apache/commons/math3/RealFieldElement (3, 2)
	493 astore (3, 2)
	494 #13 (3, 2)
	495 aload (3, 2)
	496 #12 (3, 2)
	497 aload (3, 2)
	498 #4 (3, 2)
	499 invokeinterface (3, 2)
	500 org/apache/commons/math3/RealFieldElement.org/apache/commons/math3/RealFieldElement (3, 2)
	502 0 (3, 2)
	504 checkcast (3, 2)
	505 org/apache/commons/math3/RealFieldElement (3, 2)
	507 astore (3, 2)
	508 #14 (3, 2)
	509 aload (3, 2)
	510 #7 (3, 2)
	511 aload (3, 2)
	512 #4 (3, 2)
	513 invokeinterface (3, 2)
	514 org/apache/commons/math3/RealFieldElement.org/apache/commons/math3/RealFieldElement (3, 2)
	516 0 (3, 2)
	518 checkcast (3, 2)
	519 org/apache/commons/math3/RealFieldElement (3, 2)
	521 astore (3, 2)
	522 #15 (3, 2)
	523 aload_1 (3, 2)
	524 aload (3, 2)
	525 #7 (3, 2)
	526 invokeinterface (3, 2)
	527 org/apache/commons/math3/RealFieldElement.org/apache/commons/math3/RealFieldElement (3, 2)
	529 0 (3, 2)
	531 checkcast (3, 2)
	532 org/apache/commons/math3/RealFieldElement (3, 2)
	534 astore (3, 2)
	535 #16 (3, 2)
	536 aload_1 (3, 2)
	537 aload (3, 2)
	538 #12 (3, 2)
	539 invokeinterface (3, 2)
	540 org/apache/commons/math3/RealFieldElement.org/apache/commons/math3/RealFieldElement (3, 2)
	542 0 (3, 2)
	544 checkcast (3, 2)
	545 org/apache/commons/math3/RealFieldElement (3, 2)
	547 astore (3, 2)
	548 #17 (3, 2)
	549 aload_1 (3, 2)
	550 aload (3, 2)
	551 #4 (3, 2)
	552 invokeinterface (3, 2)
	553 org/apache/commons/math3/RealFieldElement.org/apache/commons/math3/RealFieldElement (3, 2)
	555 0 (3, 2)
	557 checkcast (3, 2)
	558 org/apache/commons/math3/RealFieldElement (3, 2)
	560 astore (3, 2)
	561 #18 (3, 2)
	562 aload (3, 2)
	563 #17 (3, 2)
	564 aload (3, 2)
	565 #18 (3, 2)
	566 invokeinterface (3, 2)
	567 org/apache/commons/math3/RealFieldElement.multiply:(I)Ljava/lang/Object; (3, 2)
	569 0 (3, 2)
	571 checkcast (3, 2)
	572 org/apache/commons/math3/RealFieldElement (3, 2)
	574 aload (3, 2)
	575 #14 (3, 2)
	576 invokeinterface (3, 2)
	577 org/apache/commons/math3/RealFieldElement.multiply:(I)Ljava/lang/Object; (3, 2)
	579 0 (3, 2)
	581 checkcast (3, 2)
	582 org/apache/commons/math3/RealFieldElement (3, 2)
	584 iload (3, 2)
	585 #5 (3, 2)
	586 invokeinterface (3, 2)
	587 org/apache/commons/math3/RealFieldElement.divide:(Ljava/lang/Object;)Ljava/lang/Object; (3, 2)
	589 0 (3, 2)
	591 checkcast (3, 2)
	592 org/apache/commons/math3/RealFieldElement (3, 2)
	594 aload (3, 2)
	595 #16 (3, 2)
	596 aload (3, 2)
	597 #18 (3, 2)
	598 invokeinterface (3, 2)
	599 org/apache/commons/math3/RealFieldElement.multiply:(I)Ljava/lang/Object; (3, 2)
	601 0 (3, 2)
	603 checkcast (3, 2)
	604 org/apache/commons/math3/RealFieldElement (3, 2)
	606 aload (3, 2)
	607 #15 (3, 2)
	608 invokeinterface (3, 2)
	609 org/apache/commons/math3/RealFieldElement.multiply:(I)Ljava/lang/Object; (3, 2)
	611 0 (3, 2)
	613 checkcast (3, 2)
	614 org/apache/commons/math3/RealFieldElement (3, 2)
	616 iload (3, 2)
	617 #10 (3, 2)
	618 invokeinterface (3, 2)
	619 org/apache/commons/math3/RealFieldElement.divide:(Ljava/lang/Object;)Ljava/lang/Object; (3, 2)
	621 0 (3, 2)
	623 invokeinterface (3, 2)
	624 org/apache/commons/math3/RealFieldElement.org/apache/commons/math3/RealFieldElement (3, 2)
	626 0 (3, 2)
	628 checkcast (3, 2)
	629 org/apache/commons/math3/RealFieldElement (3, 2)
	631 aload (3, 2)
	632 #16 (3, 2)
	633 aload (3, 2)
	634 #17 (3, 2)
	635 invokeinterface (3, 2)
	636 org/apache/commons/math3/RealFieldElement.multiply:(I)Ljava/lang/Object; (3, 2)
	638 0 (3, 2)
	640 checkcast (3, 2)
	641 org/apache/commons/math3/RealFieldElement (3, 2)
	643 aload (3, 2)
	644 #13 (3, 2)
	645 invokeinterface (3, 2)
	646 org/apache/commons/math3/RealFieldElement.multiply:(I)Ljava/lang/Object; (3, 2)
	648 0 (3, 2)
	650 checkcast (3, 2)
	651 org/apache/commons/math3/RealFieldElement (3, 2)
	653 iload_2 (3, 2)
	654 invokeinterface (3, 2)
	655 org/apache/commons/math3/RealFieldElement.divide:(Ljava/lang/Object;)Ljava/lang/Object; (3, 2)
	657 0 (3, 2)
	659 invokeinterface (3, 2)
	660 org/apache/commons/math3/RealFieldElement.locatePoint:(Lorg/apache/commons/math3/RealFieldElement;Lorg/apache/commons/math3/ode/sampling/FieldStepInterpolator;)I (3, 2)
	662 0 (3, 2)
	664 checkcast (3, 2)
	665 org/apache/commons/math3/RealFieldElement (3, 2)
	667 aload (3, 2)
	668 #13 (3, 2)
	669 aload (3, 2)
	670 #14 (3, 2)
	671 invokeinterface (3, 2)
	672 org/apache/commons/math3/RealFieldElement.multiply:(I)Ljava/lang/Object; (3, 2)
	674 0 (3, 2)
	676 checkcast (3, 2)
	677 org/apache/commons/math3/RealFieldElement (3, 2)
	679 aload (3, 2)
	680 #15 (3, 2)
	681 invokeinterface (3, 2)
	682 org/apache/commons/math3/RealFieldElement.multiply:(I)Ljava/lang/Object; (3, 2)
	684 0 (3, 2)
	686 invokeinterface (3, 2)
	687 org/apache/commons/math3/RealFieldElement.org/apache/commons/math3/util/FastMath (3, 2)
	689 0 (3, 2)
	691 checkcast (3, 2)
	692 org/apache/commons/math3/RealFieldElement (3, 2)
	694 astore (3, 2)
	695 #19 (3, 2)
	696 aload_0 (3, 2)
	697 aload (3, 2)
	698 #19 (3, 2)
	699 invokeinterface (3, 2)
	700 org/apache/commons/math3/RealFieldElement.HOLE_BETWEEN_MODELS_TIME_RANGES:Lorg/apache/commons/math3/exception/util/LocalizedFormats; (3, 2)
	702 0 (3, 2)
	704 invokestatic (3, 2)
	705 org/apache/commons/math3/util/FastMath.rint:(D)D (3, 2)
	707 d2i (3, 2)
	708 putfield (3, 2)
	709 org/apache/commons/math3/ode/ContinuousOutputFieldModel.index:I (3, 2)
	711 iload_2 (3, 4)
	712 iconst_1 (3, 4)
	713 iadd (3, 4)
	714 bipush (3, 4)
	715 9 (3, 4)
	716 iload_2 (3, 4)
	717 imul (3, 4)
	718 iload (3, 4)
	719 #5 (3, 4)
	720 iadd (3, 4)
	721 bipush (3, 4)
	722 10 (3, 4)
	723 idiv (3, 4)
	724 invokestatic (3, 4)
	725 org/apache/commons/math3/util/FastMath.max:(II)I (3, 4)
	727 istore (3, 4)
	728 #13 (3, 4)
	729 iload (3, 4)
	730 #5 (3, 4)
	731 iconst_1 (3, 4)
	732 isub (3, 4)
	733 iload_2 (3, 4)
	734 bipush (3, 4)
	735 9 (3, 4)
	736 iload (3, 4)
	737 #5 (3, 4)
	738 imul (3, 4)
	739 iadd (3, 4)
	740 bipush (3, 4)
	741 10 (3, 4)
	742 idiv (3, 4)
	743 invokestatic (3, 4)
	744 org/apache/commons/math3/util/FastMath.min:(II)I (3, 4)
	746 istore (3, 4)
	747 #14 (3, 4)
	748 aload_0 (4, 1)
	749 getfield (4, 1)
	750 org/apache/commons/math3/ode/ContinuousOutputFieldModel.index:I (4, 1)
	752 iload (4, 1)
	753 #13 (4, 1)
	754 if_icmpge (4, 1)
	755 12 (4, 1)
	757 aload_0 (4, 1)
	758 iload (4, 1)
	759 #13 (4, 1)
	760 putfield (4, 1)
	761 org/apache/commons/math3/ode/ContinuousOutputFieldModel.index:I (4, 1)
	763 goto (4, 1)
	764 18 (4, 1)
	766 aload_0 (5, 1)
	767 getfield (5, 1)
	768 org/apache/commons/math3/ode/ContinuousOutputFieldModel.index:I (5, 1)
	770 iload (5, 1)
	771 #14 (5, 1)
	772 if_icmple (5, 1)
	773 9 (5, 1)
	775 aload_0 (5, 1)
	776 iload (5, 1)
	777 #14 (5, 1)
	778 putfield (5, 1)
	779 org/apache/commons/math3/ode/ContinuousOutputFieldModel.index:I (5, 1)
	781 goto (0, 0)
	782 -609 (0, 0)
	784 aload_0 (1, 4)
	785 iload_2 (1, 4)
	786 putfield (1, 4)
	787 org/apache/commons/math3/ode/ContinuousOutputFieldModel.index:I (1, 4)
	789 aload_0 (2, 3)
	790 getfield (2, 3)
	791 org/apache/commons/math3/ode/ContinuousOutputFieldModel.index:I (2, 3)
	793 iload (2, 3)
	794 #5 (2, 3)
	795 if_icmpgt (2, 3)
	796 40 (2, 3)
	798 aload_0 (2, 3)
	799 aload_1 (2, 3)
	800 aload_0 (2, 3)
	801 getfield (2, 3)
	802 org/apache/commons/math3/ode/ContinuousOutputFieldModel.steps:Ljava/util/List; (2, 3)
	804 aload_0 (2, 3)
	805 getfield (2, 3)
	806 org/apache/commons/math3/ode/ContinuousOutputFieldModel.index:I (2, 3)
	808 invokeinterface (2, 3)
	809 java/util/List.org/apache/commons/math3/ode/sampling/FieldStepInterpolator (2, 3)
	811 0 (2, 3)
	813 checkcast (2, 3)
	814 org/apache/commons/math3/ode/sampling/FieldStepInterpolator (2, 3)
	816 invokespecial (2, 3)
	817 org/apache/commons/math3/ode/ContinuousOutputFieldModel.locatePoint:(Lorg/apache/commons/math3/RealFieldElement;Lorg/apache/commons/math3/ode/sampling/FieldStepInterpolator;)I (2, 3)
	819 ifle (2, 3)
	820 16 (2, 3)
	822 aload_0 (2, 3)
	823 dup (2, 3)
	824 getfield (2, 3)
	825 org/apache/commons/math3/ode/ContinuousOutputFieldModel.index:I (2, 3)
	827 iconst_1 (2, 3)
	828 iadd (2, 3)
	829 putfield (2, 3)
	830 org/apache/commons/math3/ode/ContinuousOutputFieldModel.index:I (2, 3)
	832 goto (2, 3)
	833 -43 (2, 3)
	835 aload_0 (1, 4)
	836 getfield (1, 4)
	837 org/apache/commons/math3/ode/ContinuousOutputFieldModel.steps:Ljava/util/List; (1, 4)
	839 aload_0 (1, 4)
	840 getfield (1, 4)
	841 org/apache/commons/math3/ode/ContinuousOutputFieldModel.index:I (1, 4)
	843 invokeinterface (1, 4)
	844 java/util/List.org/apache/commons/math3/ode/sampling/FieldStepInterpolator (1, 4)
	846 0 (1, 4)
	848 checkcast (1, 4)
	849 org/apache/commons/math3/ode/sampling/FieldStepInterpolator (1, 4)
	851 aload_1 (1, 4)
	852 invokeinterface (1, 4)
	853 org/apache/commons/math3/ode/sampling/FieldStepInterpolator.subtract:(D)Ljava/lang/Object; (1, 4)
	855 0 (1, 4)
	857 areturn (0, 4)

Method: locatePoint
	0 aload_0 (1, 1)
	1 getfield (1, 1)
	2 org/apache/commons/math3/ode/ContinuousOutputFieldModel.forward:Z (1, 1)
	4 ifeq (1, 1)
	5 65 (1, 1)
	7 aload_1 (2, 1)
	8 aload_2 (2, 1)
	9 invokeinterface (2, 1)
	10 org/apache/commons/math3/ode/sampling/FieldStepInterpolator.org/apache/commons/math3/ode/FieldODEStateAndDerivative (2, 1)
	12 0 (2, 1)
	14 invokevirtual (2, 1)
	15 org/apache/commons/math3/ode/FieldODEStateAndDerivative.getTime:()Lorg/apache/commons/math3/RealFieldElement; (2, 1)
	17 invokeinterface (2, 1)
	18 org/apache/commons/math3/RealFieldElement.org/apache/commons/math3/RealFieldElement (2, 1)
	20 0 (2, 1)
	22 checkcast (2, 1)
	23 org/apache/commons/math3/RealFieldElement (2, 1)
	25 invokeinterface (2, 1)
	26 org/apache/commons/math3/RealFieldElement.HOLE_BETWEEN_MODELS_TIME_RANGES:Lorg/apache/commons/math3/exception/util/LocalizedFormats; (2, 1)
	28 0 (2, 1)
	30 dconst_0 (2, 1)
	31 dcmpg (2, 1)
	32 ifge (2, 1)
	33 5 (2, 1)
	35 iconst_m1 (2, 1)
	36 ireturn (2, 1)
	37 aload_1 (3, 1)
	38 aload_2 (3, 1)
	39 invokeinterface (3, 1)
	40 org/apache/commons/math3/ode/sampling/FieldStepInterpolator.getTime:()Lorg/apache/commons/math3/RealFieldElement; (3, 1)
	42 0 (3, 1)
	44 invokevirtual (3, 1)
	45 org/apache/commons/math3/ode/FieldODEStateAndDerivative.getTime:()Lorg/apache/commons/math3/RealFieldElement; (3, 1)
	47 invokeinterface (3, 1)
	48 org/apache/commons/math3/RealFieldElement.org/apache/commons/math3/RealFieldElement (3, 1)
	50 0 (3, 1)
	52 checkcast (3, 1)
	53 org/apache/commons/math3/RealFieldElement (3, 1)
	55 invokeinterface (3, 1)
	56 org/apache/commons/math3/RealFieldElement.HOLE_BETWEEN_MODELS_TIME_RANGES:Lorg/apache/commons/math3/exception/util/LocalizedFormats; (3, 1)
	58 0 (3, 1)
	60 dconst_0 (3, 1)
	61 dcmpl (3, 1)
	62 ifle (3, 1)
	63 5 (3, 1)
	65 iconst_1 (3, 1)
	66 ireturn (3, 1)
	67 iconst_0 (4, 2)
	68 ireturn (4, 2)
	69 aload_1 (1, 1)
	70 aload_2 (1, 1)
	71 invokeinterface (1, 1)
	72 org/apache/commons/math3/ode/sampling/FieldStepInterpolator.org/apache/commons/math3/ode/FieldODEStateAndDerivative (1, 1)
	74 0 (1, 1)
	76 invokevirtual (1, 1)
	77 org/apache/commons/math3/ode/FieldODEStateAndDerivative.getTime:()Lorg/apache/commons/math3/RealFieldElement; (1, 1)
	79 invokeinterface (1, 1)
	80 org/apache/commons/math3/RealFieldElement.org/apache/commons/math3/RealFieldElement (1, 1)
	82 0 (1, 1)
	84 checkcast (1, 1)
	85 org/apache/commons/math3/RealFieldElement (1, 1)
	87 invokeinterface (1, 1)
	88 org/apache/commons/math3/RealFieldElement.HOLE_BETWEEN_MODELS_TIME_RANGES:Lorg/apache/commons/math3/exception/util/LocalizedFormats; (1, 1)
	90 0 (1, 1)
	92 dconst_0 (1, 1)
	93 dcmpl (1, 1)
	94 ifle (1, 1)
	95 5 (1, 1)
	97 iconst_m1 (1, 1)
	98 ireturn (1, 1)
	99 aload_1 (2, 1)
	100 aload_2 (2, 1)
	101 invokeinterface (2, 1)
	102 org/apache/commons/math3/ode/sampling/FieldStepInterpolator.getTime:()Lorg/apache/commons/math3/RealFieldElement; (2, 1)
	104 0 (2, 1)
	106 invokevirtual (2, 1)
	107 org/apache/commons/math3/ode/FieldODEStateAndDerivative.getTime:()Lorg/apache/commons/math3/RealFieldElement; (2, 1)
	109 invokeinterface (2, 1)
	110 org/apache/commons/math3/RealFieldElement.org/apache/commons/math3/RealFieldElement (2, 1)
	112 0 (2, 1)
	114 checkcast (2, 1)
	115 org/apache/commons/math3/RealFieldElement (2, 1)
	117 invokeinterface (2, 1)
	118 org/apache/commons/math3/RealFieldElement.HOLE_BETWEEN_MODELS_TIME_RANGES:Lorg/apache/commons/math3/exception/util/LocalizedFormats; (2, 1)
	120 0 (2, 1)
	122 dconst_0 (2, 1)
	123 dcmpg (2, 1)
	124 ifge (2, 1)
	125 5 (2, 1)
	127 iconst_1 (2, 1)
	128 ireturn (2, 1)
	129 iconst_0 (3, 2)
	130 ireturn (1, 2)

