Method: <init>
	0 aload_0 (0, 0)
	1 invokespecial (0, 0)
	2 java/lang/Object.<init>:()V (0, 0)
	4 aload_0 (0, 0)
	5 new (0, 0)
	6 java/util/ArrayList (0, 0)
	8 dup (0, 0)
	9 invokespecial (0, 0)
	10 java/util/ArrayList.<init>:()V (0, 0)
	12 putfield (0, 0)
	13 org/apache/commons/math3/ode/ContinuousOutputModel.steps:Ljava/util/List; (0, 0)
	15 aload_0 (0, 0)
	16 ldc2_w (0, 0)
	17 nan (0, 0)
	19 putfield (0, 0)
	20 org/apache/commons/math3/ode/ContinuousOutputModel.initialTime:D (0, 0)
	22 aload_0 (0, 0)
	23 ldc2_w (0, 0)
	24 nan (0, 0)
	26 putfield (0, 0)
	27 org/apache/commons/math3/ode/ContinuousOutputModel.finalTime:D (0, 0)
	29 aload_0 (1, 4)
	30 iconst_1 (1, 4)
	31 putfield (1, 4)
	32 org/apache/commons/math3/ode/ContinuousOutputModel.forward:Z (1, 4)
	34 aload_0 (1, 4)
	35 iconst_0 (1, 4)
	36 putfield (1, 4)
	37 org/apache/commons/math3/ode/ContinuousOutputModel.index:I (1, 4)
	39 return (0, 0)

Method: append
	0 aload_1 (1, 1)
	1 getfield (1, 1)
	2 org/apache/commons/math3/ode/ContinuousOutputModel.steps:Ljava/util/List; (1, 1)
	4 invokeinterface (1, 1)
	5 java/util/List.getInterpolatedState:()[D (1, 1)
	7 0 (1, 1)
	9 ifne (1, 1)
	10 4 (1, 1)
	12 return (1, 1)
	13 aload_0 (1, 1)
	14 getfield (1, 1)
	15 org/apache/commons/math3/ode/ContinuousOutputModel.steps:Ljava/util/List; (1, 1)
	17 invokeinterface (1, 1)
	18 java/util/List.getInterpolatedState:()[D (1, 1)
	20 0 (1, 1)
	22 ifne (1, 1)
	23 22 (1, 1)
	25 aload_0 (1, 1)
	26 aload_1 (1, 1)
	27 getfield (1, 1)
	28 org/apache/commons/math3/ode/ContinuousOutputModel.initialTime:D (1, 1)
	30 putfield (1, 1)
	31 org/apache/commons/math3/ode/ContinuousOutputModel.initialTime:D (1, 1)
	33 aload_0 (2, 4)
	34 aload_1 (2, 4)
	35 getfield (2, 4)
	36 org/apache/commons/math3/ode/ContinuousOutputModel.forward:Z (2, 4)
	38 putfield (2, 4)
	39 org/apache/commons/math3/ode/ContinuousOutputModel.forward:Z (2, 4)
	41 goto (2, 4)
	42 151 (2, 4)
	44 aload_0 (4, 1)
	45 invokevirtual (4, 1)
	46 org/apache/commons/math3/ode/ContinuousOutputModel.getInterpolatedState:()[D (4, 1)
	48 arraylength (4, 1)
	49 aload_1 (4, 1)
	50 invokevirtual (4, 1)
	51 org/apache/commons/math3/ode/ContinuousOutputModel.getInterpolatedState:()[D (4, 1)
	53 arraylength (4, 1)
	54 if_icmpeq (4, 1)
	55 21 (4, 1)
	57 new (4, 1)
	58 org/apache/commons/math3/exception/DimensionMismatchException (4, 1)
	60 dup (4, 1)
	61 aload_1 (4, 1)
	62 invokevirtual (4, 1)
	63 org/apache/commons/math3/ode/ContinuousOutputModel.getInterpolatedState:()[D (4, 1)
	65 arraylength (4, 1)
	66 aload_0 (4, 1)
	67 invokevirtual (4, 1)
	68 org/apache/commons/math3/ode/ContinuousOutputModel.getInterpolatedState:()[D (4, 1)
	70 arraylength (4, 1)
	71 invokespecial (4, 1)
	72 org/apache/commons/math3/exception/DimensionMismatchException.<init>:(II)V (4, 1)
	74 athrow (4, 1)
	75 aload_0 (4, 1)
	76 getfield (4, 1)
	77 org/apache/commons/math3/ode/ContinuousOutputModel.forward:Z (4, 1)
	79 aload_1 (4, 1)
	80 getfield (4, 1)
	81 org/apache/commons/math3/ode/ContinuousOutputModel.forward:Z (4, 1)
	83 ixor (4, 1)
	84 ifeq (4, 1)
	85 18 (4, 1)
	87 new (4, 1)
	88 org/apache/commons/math3/exception/MathIllegalArgumentException (4, 1)
	90 dup (4, 1)
	91 getstatic (4, 1)
	92 org/apache/commons/math3/exception/util/LocalizedFormats.PROPAGATION_DIRECTION_MISMATCH:Lorg/apache/commons/math3/exception/util/LocalizedFormats; (4, 1)
	94 iconst_0 (4, 1)
	95 anewarray (4, 1)
	96 java/lang/Object (4, 1)
	98 invokespecial (4, 1)
	99 org/apache/commons/math3/exception/MathIllegalArgumentException.<init>:(Lorg/apache/commons/math3/exception/util/Localizable;[Ljava/lang/Object;)V (4, 1)
	101 athrow (4, 1)
	102 aload_0 (3, 2)
	103 getfield (3, 2)
	104 org/apache/commons/math3/ode/ContinuousOutputModel.steps:Ljava/util/List; (3, 2)
	106 aload_0 (3, 2)
	107 getfield (3, 2)
	108 org/apache/commons/math3/ode/ContinuousOutputModel.index:I (3, 2)
	110 invokeinterface (3, 2)
	111 java/util/List.org/apache/commons/math3/ode/sampling/StepInterpolator (3, 2)
	113 0 (3, 2)
	115 checkcast (3, 2)
	116 org/apache/commons/math3/ode/sampling/StepInterpolator (3, 2)
	118 astore_2 (3, 2)
	119 aload_2 (3, 2)
	120 invokeinterface (3, 2)
	121 org/apache/commons/math3/ode/sampling/StepInterpolator.getPreviousTime:()D (3, 2)
	123 0 (3, 2)
	125 dstore_3 (3, 2)
	126 aload_2 (3, 2)
	127 invokeinterface (3, 2)
	128 org/apache/commons/math3/ode/sampling/StepInterpolator.getInitialTime:()D (3, 2)
	130 0 (3, 2)
	132 dstore (3, 2)
	133 #5 (3, 2)
	134 dload_3 (3, 2)
	135 dload (3, 2)
	136 #5 (3, 2)
	137 dsub (3, 2)
	138 dstore (3, 2)
	139 #7 (3, 2)
	140 aload_1 (3, 2)
	141 invokevirtual (3, 2)
	142 org/apache/commons/math3/ode/ContinuousOutputModel.getInitialTime:()D (3, 2)
	144 dload_3 (3, 2)
	145 dsub (3, 2)
	146 dstore (3, 2)
	147 #9 (3, 2)
	148 dload (4, 1)
	149 #9 (4, 1)
	150 invokestatic (4, 1)
	151 org/apache/commons/math3/util/FastMath.abs:(D)D (4, 1)
	153 ldc2_w (4, 1)
	154 0.001 (4, 1)
	156 dload (4, 1)
	157 #7 (4, 1)
	158 invokestatic (4, 1)
	159 org/apache/commons/math3/util/FastMath.abs:(D)D (4, 1)
	161 dmul (4, 1)
	162 dcmpl (4, 1)
	163 ifle (4, 1)
	164 29 (4, 1)
	166 new (4, 1)
	167 org/apache/commons/math3/exception/MathIllegalArgumentException (4, 1)
	169 dup (4, 1)
	170 getstatic (4, 1)
	171 org/apache/commons/math3/exception/util/LocalizedFormats.HOLE_BETWEEN_MODELS_TIME_RANGES:Lorg/apache/commons/math3/exception/util/LocalizedFormats; (4, 1)
	173 iconst_1 (4, 1)
	174 anewarray (4, 1)
	175 java/lang/Object (4, 1)
	177 dup (4, 1)
	178 iconst_0 (4, 1)
	179 dload (4, 1)
	180 #9 (4, 1)
	181 invokestatic (4, 1)
	182 org/apache/commons/math3/util/FastMath.abs:(D)D (4, 1)
	184 invokestatic (4, 1)
	185 java/lang/Double.valueOf:(D)Ljava/lang/Double; (4, 1)
	187 aastore (4, 1)
	188 invokespecial (4, 1)
	189 org/apache/commons/math3/exception/MathIllegalArgumentException.<init>:(Lorg/apache/commons/math3/exception/util/Localizable;[Ljava/lang/Object;)V (4, 1)
	191 athrow (4, 1)
	192 aload_1 (1, 4)
	193 getfield (1, 4)
	194 org/apache/commons/math3/ode/ContinuousOutputModel.steps:Ljava/util/List; (1, 4)
	196 invokeinterface (1, 4)
	197 java/util/List.java/util/Iterator (1, 4)
	199 0 (1, 4)
	201 astore_2 (1, 4)
	202 aload_2 (1, 4)
	203 invokeinterface (1, 4)
	204 java/util/Iterator.next:()Ljava/lang/Object; (1, 4)
	206 0 (1, 4)
	208 ifeq (1, 4)
	209 32 (1, 4)
	211 aload_2 (1, 4)
	212 invokeinterface (1, 4)
	213 java/util/Iterator.copy:()Lorg/apache/commons/math3/ode/sampling/StepInterpolator; (1, 4)
	215 0 (1, 4)
	217 checkcast (1, 4)
	218 org/apache/commons/math3/ode/sampling/StepInterpolator (1, 4)
	220 astore_3 (1, 4)
	221 aload_0 (1, 4)
	222 getfield (1, 4)
	223 org/apache/commons/math3/ode/ContinuousOutputModel.steps:Ljava/util/List; (1, 4)
	225 aload_3 (1, 4)
	226 invokeinterface (1, 4)
	227 org/apache/commons/math3/ode/sampling/StepInterpolator.add:(Ljava/lang/Object;)Z (1, 4)
	229 0 (1, 4)
	231 invokeinterface (1, 4)
	232 java/util/List.clear:()V (1, 4)
	234 0 (1, 4)
	236 pop (1, 4)
	237 goto (0, 0)
	238 -35 (0, 0)
	240 aload_0 (0, 0)
	241 aload_0 (0, 0)
	242 getfield (0, 0)
	243 org/apache/commons/math3/ode/ContinuousOutputModel.steps:Ljava/util/List; (0, 0)
	245 invokeinterface (0, 0)
	246 java/util/List.getInterpolatedState:()[D (0, 0)
	248 0 (0, 0)
	250 iconst_1 (0, 0)
	251 isub (0, 0)
	252 putfield (0, 0)
	253 org/apache/commons/math3/ode/ContinuousOutputModel.index:I (0, 0)
	255 aload_0 (0, 0)
	256 aload_0 (0, 0)
	257 getfield (0, 0)
	258 org/apache/commons/math3/ode/ContinuousOutputModel.steps:Ljava/util/List; (0, 0)
	260 aload_0 (0, 0)
	261 getfield (0, 0)
	262 org/apache/commons/math3/ode/ContinuousOutputModel.index:I (0, 0)
	264 invokeinterface (0, 0)
	265 java/util/List.org/apache/commons/math3/ode/sampling/StepInterpolator (0, 0)
	267 0 (0, 0)
	269 checkcast (0, 0)
	270 org/apache/commons/math3/ode/sampling/StepInterpolator (0, 0)
	272 invokeinterface (0, 0)
	273 org/apache/commons/math3/ode/sampling/StepInterpolator.getPreviousTime:()D (0, 0)
	275 0 (0, 0)
	277 putfield (0, 0)
	278 org/apache/commons/math3/ode/ContinuousOutputModel.finalTime:D (0, 0)
	280 return (0, 0)

Method: init
	0 aload_0 (0, 0)
	1 ldc2_w (0, 0)
	2 nan (0, 0)
	4 putfield (0, 0)
	5 org/apache/commons/math3/ode/ContinuousOutputModel.initialTime:D (0, 0)
	7 aload_0 (0, 0)
	8 ldc2_w (0, 0)
	9 nan (0, 0)
	11 putfield (0, 0)
	12 org/apache/commons/math3/ode/ContinuousOutputModel.finalTime:D (0, 0)
	14 aload_0 (1, 4)
	15 iconst_1 (1, 4)
	16 putfield (1, 4)
	17 org/apache/commons/math3/ode/ContinuousOutputModel.forward:Z (1, 4)
	19 aload_0 (1, 4)
	20 iconst_0 (1, 4)
	21 putfield (1, 4)
	22 org/apache/commons/math3/ode/ContinuousOutputModel.index:I (1, 4)
	24 aload_0 (1, 4)
	25 getfield (1, 4)
	26 org/apache/commons/math3/ode/ContinuousOutputModel.steps:Ljava/util/List; (1, 4)
	28 invokeinterface (1, 4)
	29 java/util/List.isForward:()Z (1, 4)
	31 0 (1, 4)
	33 return (0, 4)

Method: handleStep
	0 aload_0 (1, 1)
	1 getfield (1, 1)
	2 org/apache/commons/math3/ode/ContinuousOutputModel.steps:Ljava/util/List; (1, 1)
	4 invokeinterface (1, 1)
	5 java/util/List.getInterpolatedState:()[D (1, 1)
	7 0 (1, 1)
	9 ifne (1, 1)
	10 23 (1, 1)
	12 aload_0 (1, 1)
	13 aload_1 (1, 1)
	14 invokeinterface (1, 1)
	15 org/apache/commons/math3/ode/sampling/StepInterpolator.getInitialTime:()D (1, 1)
	17 0 (1, 1)
	19 putfield (1, 1)
	20 org/apache/commons/math3/ode/ContinuousOutputModel.initialTime:D (1, 1)
	22 aload_0 (2, 4)
	23 aload_1 (2, 4)
	24 invokeinterface (2, 4)
	25 org/apache/commons/math3/ode/sampling/StepInterpolator.getInterpolatedTime:()D (2, 4)
	27 0 (2, 4)
	29 putfield (2, 4)
	30 org/apache/commons/math3/ode/ContinuousOutputModel.forward:Z (2, 4)
	32 aload_0 (0, 0)
	33 getfield (0, 0)
	34 org/apache/commons/math3/ode/ContinuousOutputModel.steps:Ljava/util/List; (0, 0)
	36 aload_1 (0, 0)
	37 invokeinterface (0, 0)
	38 org/apache/commons/math3/ode/sampling/StepInterpolator.add:(Ljava/lang/Object;)Z (0, 0)
	40 0 (0, 0)
	42 invokeinterface (0, 0)
	43 java/util/List.clear:()V (0, 0)
	45 0 (0, 0)
	47 pop (0, 0)
	48 iload_2 (1, 1)
	49 ifeq (1, 1)
	50 28 (1, 1)
	52 aload_0 (1, 1)
	53 aload_1 (1, 1)
	54 invokeinterface (1, 1)
	55 org/apache/commons/math3/ode/sampling/StepInterpolator.getPreviousTime:()D (1, 1)
	57 0 (1, 1)
	59 putfield (1, 1)
	60 org/apache/commons/math3/ode/ContinuousOutputModel.finalTime:D (1, 1)
	62 aload_0 (1, 1)
	63 aload_0 (1, 1)
	64 getfield (1, 1)
	65 org/apache/commons/math3/ode/ContinuousOutputModel.steps:Ljava/util/List; (1, 1)
	67 invokeinterface (1, 1)
	68 java/util/List.getInterpolatedState:()[D (1, 1)
	70 0 (1, 1)
	72 iconst_1 (1, 1)
	73 isub (1, 1)
	74 putfield (1, 1)
	75 org/apache/commons/math3/ode/ContinuousOutputModel.index:I (1, 1)
	77 return (0, 0)

Method: getInitialTime
	0 aload_0 (0, 0)
	1 getfield (0, 0)
	2 org/apache/commons/math3/ode/ContinuousOutputModel.initialTime:D (0, 0)
	4 dreturn (0, 0)

Method: getFinalTime
	0 aload_0 (0, 0)
	1 getfield (0, 0)
	2 org/apache/commons/math3/ode/ContinuousOutputModel.finalTime:D (0, 0)
	4 dreturn (0, 0)

Method: getInterpolatedTime
	0 aload_0 (0, 0)
	1 getfield (0, 0)
	2 org/apache/commons/math3/ode/ContinuousOutputModel.steps:Ljava/util/List; (0, 0)
	4 aload_0 (0, 0)
	5 getfield (0, 0)
	6 org/apache/commons/math3/ode/ContinuousOutputModel.index:I (0, 0)
	8 invokeinterface (0, 0)
	9 java/util/List.org/apache/commons/math3/ode/sampling/StepInterpolator (0, 0)
	11 0 (0, 0)
	13 checkcast (0, 0)
	14 org/apache/commons/math3/ode/sampling/StepInterpolator (0, 0)
	16 invokeinterface (0, 0)
	17 org/apache/commons/math3/ode/sampling/StepInterpolator.locatePoint:(DLorg/apache/commons/math3/ode/sampling/StepInterpolator;)I (0, 0)
	19 0 (0, 0)
	21 dreturn (0, 0)

Method: setInterpolatedTime
	0 iconst_0 (0, 0)
	1 istore_3 (0, 0)
	2 aload_0 (0, 0)
	3 getfield (0, 0)
	4 org/apache/commons/math3/ode/ContinuousOutputModel.steps:Ljava/util/List; (0, 0)
	6 iload_3 (0, 0)
	7 invokeinterface (0, 0)
	8 java/util/List.org/apache/commons/math3/ode/sampling/StepInterpolator (0, 0)
	10 0 (0, 0)
	12 checkcast (0, 0)
	13 org/apache/commons/math3/ode/sampling/StepInterpolator (0, 0)
	15 astore (0, 0)
	16 #4 (0, 0)
	17 ldc2_w (0, 0)
	18 0.5 (0, 0)
	20 aload (0, 0)
	21 #4 (0, 0)
	22 invokeinterface (0, 0)
	23 org/apache/commons/math3/ode/sampling/StepInterpolator.getInitialTime:()D (0, 0)
	25 0 (0, 0)
	27 aload (0, 0)
	28 #4 (0, 0)
	29 invokeinterface (0, 0)
	30 org/apache/commons/math3/ode/sampling/StepInterpolator.getPreviousTime:()D (0, 0)
	32 0 (0, 0)
	34 dadd (0, 0)
	35 dmul (0, 0)
	36 dstore (0, 0)
	37 #5 (0, 0)
	38 aload_0 (0, 0)
	39 getfield (0, 0)
	40 org/apache/commons/math3/ode/ContinuousOutputModel.steps:Ljava/util/List; (0, 0)
	42 invokeinterface (0, 0)
	43 java/util/List.getInterpolatedState:()[D (0, 0)
	45 0 (0, 0)
	47 iconst_1 (0, 0)
	48 isub (0, 0)
	49 istore (0, 0)
	50 #7 (0, 0)
	51 aload_0 (0, 0)
	52 getfield (0, 0)
	53 org/apache/commons/math3/ode/ContinuousOutputModel.steps:Ljava/util/List; (0, 0)
	55 iload (0, 0)
	56 #7 (0, 0)
	57 invokeinterface (0, 0)
	58 java/util/List.org/apache/commons/math3/ode/sampling/StepInterpolator (0, 0)
	60 0 (0, 0)
	62 checkcast (0, 0)
	63 org/apache/commons/math3/ode/sampling/StepInterpolator (0, 0)
	65 astore (0, 0)
	66 #8 (0, 0)
	67 ldc2_w (0, 0)
	68 0.5 (0, 0)
	70 aload (0, 0)
	71 #8 (0, 0)
	72 invokeinterface (0, 0)
	73 org/apache/commons/math3/ode/sampling/StepInterpolator.getInitialTime:()D (0, 0)
	75 0 (0, 0)
	77 aload (0, 0)
	78 #8 (0, 0)
	79 invokeinterface (0, 0)
	80 org/apache/commons/math3/ode/sampling/StepInterpolator.getPreviousTime:()D (0, 0)
	82 0 (0, 0)
	84 dadd (0, 0)
	85 dmul (0, 0)
	86 dstore (0, 0)
	87 #9 (0, 0)
	88 aload_0 (1, 1)
	89 dload_1 (1, 1)
	90 aload (1, 1)
	91 #4 (1, 1)
	92 invokespecial (1, 1)
	93 org/apache/commons/math3/ode/ContinuousOutputModel.locatePoint:(DLorg/apache/commons/math3/ode/sampling/StepInterpolator;)I (1, 1)
	95 ifgt (1, 1)
	96 17 (1, 1)
	98 aload_0 (1, 1)
	99 iload_3 (1, 1)
	100 putfield (1, 1)
	101 org/apache/commons/math3/ode/ContinuousOutputModel.index:I (1, 1)
	103 aload (1, 1)
	104 #4 (1, 1)
	105 dload_1 (1, 1)
	106 invokeinterface (1, 1)
	107 org/apache/commons/math3/ode/sampling/StepInterpolator.rint:(D)D (1, 1)
	109 0 (1, 1)
	111 return (1, 1)
	112 aload_0 (1, 1)
	113 dload_1 (1, 1)
	114 aload (1, 1)
	115 #8 (1, 1)
	116 invokespecial (1, 1)
	117 org/apache/commons/math3/ode/ContinuousOutputModel.locatePoint:(DLorg/apache/commons/math3/ode/sampling/StepInterpolator;)I (1, 1)
	119 iflt (1, 1)
	120 18 (1, 1)
	122 aload_0 (1, 1)
	123 iload (1, 1)
	124 #7 (1, 1)
	125 putfield (1, 1)
	126 org/apache/commons/math3/ode/ContinuousOutputModel.index:I (1, 1)
	128 aload (1, 1)
	129 #8 (1, 1)
	130 dload_1 (1, 1)
	131 invokeinterface (1, 1)
	132 org/apache/commons/math3/ode/sampling/StepInterpolator.rint:(D)D (1, 1)
	134 0 (1, 1)
	136 return (1, 1)
	137 iload (1, 3)
	138 #7 (1, 3)
	139 iload_3 (1, 3)
	140 isub (1, 3)
	141 iconst_5 (1, 3)
	142 if_icmple (1, 3)
	143 362 (1, 3)
	145 aload_0 (1, 3)
	146 getfield (1, 3)
	147 org/apache/commons/math3/ode/ContinuousOutputModel.steps:Ljava/util/List; (1, 3)
	149 aload_0 (1, 3)
	150 getfield (1, 3)
	151 org/apache/commons/math3/ode/ContinuousOutputModel.index:I (1, 3)
	153 invokeinterface (1, 3)
	154 java/util/List.org/apache/commons/math3/ode/sampling/StepInterpolator (1, 3)
	156 0 (1, 3)
	158 checkcast (1, 3)
	159 org/apache/commons/math3/ode/sampling/StepInterpolator (1, 3)
	161 astore (1, 3)
	162 #11 (1, 3)
	163 aload_0 (1, 3)
	164 dload_1 (1, 3)
	165 aload (1, 3)
	166 #11 (1, 3)
	167 invokespecial (1, 3)
	168 org/apache/commons/math3/ode/ContinuousOutputModel.locatePoint:(DLorg/apache/commons/math3/ode/sampling/StepInterpolator;)I (1, 3)
	170 istore (1, 3)
	171 #12 (1, 3)
	172 iload (2, 1)
	173 #12 (2, 1)
	174 ifge (2, 1)
	175 33 (2, 1)
	177 aload_0 (2, 1)
	178 getfield (2, 1)
	179 org/apache/commons/math3/ode/ContinuousOutputModel.index:I (2, 1)
	181 istore (2, 1)
	182 #7 (2, 1)
	183 ldc2_w (2, 1)
	184 0.5 (2, 1)
	186 aload (2, 1)
	187 #11 (2, 1)
	188 invokeinterface (2, 1)
	189 org/apache/commons/math3/ode/sampling/StepInterpolator.getInitialTime:()D (2, 1)
	191 0 (2, 1)
	193 aload (2, 1)
	194 #11 (2, 1)
	195 invokeinterface (2, 1)
	196 org/apache/commons/math3/ode/sampling/StepInterpolator.getPreviousTime:()D (2, 1)
	198 0 (2, 1)
	200 dadd (2, 1)
	201 dmul (2, 1)
	202 dstore (2, 1)
	203 #9 (2, 1)
	204 goto (2, 1)
	205 46 (2, 1)
	207 iload (3, 1)
	208 #12 (3, 1)
	209 ifle (3, 1)
	210 32 (3, 1)
	212 aload_0 (3, 1)
	213 getfield (3, 1)
	214 org/apache/commons/math3/ode/ContinuousOutputModel.index:I (3, 1)
	216 istore_3 (3, 1)
	217 ldc2_w (3, 1)
	218 0.5 (3, 1)
	220 aload (3, 1)
	221 #11 (3, 1)
	222 invokeinterface (3, 1)
	223 org/apache/commons/math3/ode/sampling/StepInterpolator.getInitialTime:()D (3, 1)
	225 0 (3, 1)
	227 aload (3, 1)
	228 #11 (3, 1)
	229 invokeinterface (3, 1)
	230 org/apache/commons/math3/ode/sampling/StepInterpolator.getPreviousTime:()D (3, 1)
	232 0 (3, 1)
	234 dadd (3, 1)
	235 dmul (3, 1)
	236 dstore (3, 1)
	237 #5 (3, 1)
	238 goto (3, 1)
	239 12 (3, 1)
	241 aload (4, 2)
	242 #11 (4, 2)
	243 dload_1 (4, 2)
	244 invokeinterface (4, 2)
	245 org/apache/commons/math3/ode/sampling/StepInterpolator.rint:(D)D (4, 2)
	247 0 (4, 2)
	249 return (4, 2)
	250 iload_3 (1, 3)
	251 iload (1, 3)
	252 #7 (1, 3)
	253 iadd (1, 3)
	254 iconst_2 (1, 3)
	255 idiv (1, 3)
	256 istore (1, 3)
	257 #13 (1, 3)
	258 aload_0 (1, 3)
	259 getfield (1, 3)
	260 org/apache/commons/math3/ode/ContinuousOutputModel.steps:Ljava/util/List; (1, 3)
	262 iload (1, 3)
	263 #13 (1, 3)
	264 invokeinterface (1, 3)
	265 java/util/List.org/apache/commons/math3/ode/sampling/StepInterpolator (1, 3)
	267 0 (1, 3)
	269 checkcast (1, 3)
	270 org/apache/commons/math3/ode/sampling/StepInterpolator (1, 3)
	272 astore (1, 3)
	273 #14 (1, 3)
	274 ldc2_w (1, 3)
	275 0.5 (1, 3)
	277 aload (1, 3)
	278 #14 (1, 3)
	279 invokeinterface (1, 3)
	280 org/apache/commons/math3/ode/sampling/StepInterpolator.getInitialTime:()D (1, 3)
	282 0 (1, 3)
	284 aload (1, 3)
	285 #14 (1, 3)
	286 invokeinterface (1, 3)
	287 org/apache/commons/math3/ode/sampling/StepInterpolator.getPreviousTime:()D (1, 3)
	289 0 (1, 3)
	291 dadd (1, 3)
	292 dmul (1, 3)
	293 dstore (1, 3)
	294 #15 (1, 3)
	295 dload (2, 1)
	296 #15 (2, 1)
	297 dload (2, 1)
	298 #5 (2, 1)
	299 dsub (2, 1)
	300 invokestatic (2, 1)
	301 org/apache/commons/math3/util/FastMath.abs:(D)D (2, 1)
	303 ldc2_w (2, 1)
	304 1e-06 (2, 1)
	306 dcmpg (2, 1)
	307 iflt (2, 1)
	308 18 (2, 1)
	310 dload (2, 1)
	311 #9 (2, 1)
	312 dload (2, 1)
	313 #15 (2, 1)
	314 dsub (2, 1)
	315 invokestatic (2, 1)
	316 org/apache/commons/math3/util/FastMath.abs:(D)D (2, 1)
	318 ldc2_w (2, 1)
	319 1e-06 (2, 1)
	321 dcmpg (2, 1)
	322 ifge (2, 1)
	323 12 (2, 1)
	325 aload_0 (2, 1)
	326 iload (2, 1)
	327 #13 (2, 1)
	328 putfield (2, 1)
	329 org/apache/commons/math3/ode/ContinuousOutputModel.index:I (2, 1)
	331 goto (2, 1)
	332 100 (2, 1)
	334 dload (3, 2)
	335 #9 (3, 2)
	336 dload (3, 2)
	337 #15 (3, 2)
	338 dsub (3, 2)
	339 dstore (3, 2)
	340 #17 (3, 2)
	341 dload (3, 2)
	342 #15 (3, 2)
	343 dload (3, 2)
	344 #5 (3, 2)
	345 dsub (3, 2)
	346 dstore (3, 2)
	347 #19 (3, 2)
	348 dload (3, 2)
	349 #9 (3, 2)
	350 dload (3, 2)
	351 #5 (3, 2)
	352 dsub (3, 2)
	353 dstore (3, 2)
	354 #21 (3, 2)
	355 dload_1 (3, 2)
	356 dload (3, 2)
	357 #9 (3, 2)
	358 dsub (3, 2)
	359 dstore (3, 2)
	360 #23 (3, 2)
	361 dload_1 (3, 2)
	362 dload (3, 2)
	363 #15 (3, 2)
	364 dsub (3, 2)
	365 dstore (3, 2)
	366 #25 (3, 2)
	367 dload_1 (3, 2)
	368 dload (3, 2)
	369 #5 (3, 2)
	370 dsub (3, 2)
	371 dstore (3, 2)
	372 #27 (3, 2)
	373 dload (3, 2)
	374 #25 (3, 2)
	375 dload (3, 2)
	376 #27 (3, 2)
	377 dmul (3, 2)
	378 dload (3, 2)
	379 #19 (3, 2)
	380 dmul (3, 2)
	381 iload (3, 2)
	382 #7 (3, 2)
	383 i2d (3, 2)
	384 dmul (3, 2)
	385 dload (3, 2)
	386 #23 (3, 2)
	387 dload (3, 2)
	388 #27 (3, 2)
	389 dmul (3, 2)
	390 dload (3, 2)
	391 #21 (3, 2)
	392 dmul (3, 2)
	393 iload (3, 2)
	394 #13 (3, 2)
	395 i2d (3, 2)
	396 dmul (3, 2)
	397 dsub (3, 2)
	398 dload (3, 2)
	399 #23 (3, 2)
	400 dload (3, 2)
	401 #25 (3, 2)
	402 dmul (3, 2)
	403 dload (3, 2)
	404 #17 (3, 2)
	405 dmul (3, 2)
	406 iload_3 (3, 2)
	407 i2d (3, 2)
	408 dmul (3, 2)
	409 dadd (3, 2)
	410 dload (3, 2)
	411 #17 (3, 2)
	412 dload (3, 2)
	413 #19 (3, 2)
	414 dmul (3, 2)
	415 dload (3, 2)
	416 #21 (3, 2)
	417 dmul (3, 2)
	418 ddiv (3, 2)
	419 dstore (3, 2)
	420 #29 (3, 2)
	421 aload_0 (3, 2)
	422 dload (3, 2)
	423 #29 (3, 2)
	424 invokestatic (3, 2)
	425 org/apache/commons/math3/util/FastMath.rint:(D)D (3, 2)
	427 d2i (3, 2)
	428 putfield (3, 2)
	429 org/apache/commons/math3/ode/ContinuousOutputModel.index:I (3, 2)
	431 iload_3 (2, 4)
	432 iconst_1 (2, 4)
	433 iadd (2, 4)
	434 bipush (2, 4)
	435 9 (2, 4)
	436 iload_3 (2, 4)
	437 imul (2, 4)
	438 iload (2, 4)
	439 #7 (2, 4)
	440 iadd (2, 4)
	441 bipush (2, 4)
	442 10 (2, 4)
	443 idiv (2, 4)
	444 invokestatic (2, 4)
	445 org/apache/commons/math3/util/FastMath.max:(II)I (2, 4)
	447 istore (2, 4)
	448 #17 (2, 4)
	449 iload (2, 4)
	450 #7 (2, 4)
	451 iconst_1 (2, 4)
	452 isub (2, 4)
	453 iload_3 (2, 4)
	454 bipush (2, 4)
	455 9 (2, 4)
	456 iload (2, 4)
	457 #7 (2, 4)
	458 imul (2, 4)
	459 iadd (2, 4)
	460 bipush (2, 4)
	461 10 (2, 4)
	462 idiv (2, 4)
	463 invokestatic (2, 4)
	464 org/apache/commons/math3/util/FastMath.min:(II)I (2, 4)
	466 istore (2, 4)
	467 #18 (2, 4)
	468 aload_0 (3, 1)
	469 getfield (3, 1)
	470 org/apache/commons/math3/ode/ContinuousOutputModel.index:I (3, 1)
	472 iload (3, 1)
	473 #17 (3, 1)
	474 if_icmpge (3, 1)
	475 12 (3, 1)
	477 aload_0 (3, 1)
	478 iload (3, 1)
	479 #17 (3, 1)
	480 putfield (3, 1)
	481 org/apache/commons/math3/ode/ContinuousOutputModel.index:I (3, 1)
	483 goto (3, 1)
	484 18 (3, 1)
	486 aload_0 (4, 1)
	487 getfield (4, 1)
	488 org/apache/commons/math3/ode/ContinuousOutputModel.index:I (4, 1)
	490 iload (4, 1)
	491 #18 (4, 1)
	492 if_icmple (4, 1)
	493 9 (4, 1)
	495 aload_0 (4, 1)
	496 iload (4, 1)
	497 #18 (4, 1)
	498 putfield (4, 1)
	499 org/apache/commons/math3/ode/ContinuousOutputModel.index:I (4, 1)
	501 goto (0, 0)
	502 -364 (0, 0)
	504 aload_0 (1, 4)
	505 iload_3 (1, 4)
	506 putfield (1, 4)
	507 org/apache/commons/math3/ode/ContinuousOutputModel.index:I (1, 4)
	509 aload_0 (2, 3)
	510 getfield (2, 3)
	511 org/apache/commons/math3/ode/ContinuousOutputModel.index:I (2, 3)
	513 iload (2, 3)
	514 #7 (2, 3)
	515 if_icmpgt (2, 3)
	516 40 (2, 3)
	518 aload_0 (2, 3)
	519 dload_1 (2, 3)
	520 aload_0 (2, 3)
	521 getfield (2, 3)
	522 org/apache/commons/math3/ode/ContinuousOutputModel.steps:Ljava/util/List; (2, 3)
	524 aload_0 (2, 3)
	525 getfield (2, 3)
	526 org/apache/commons/math3/ode/ContinuousOutputModel.index:I (2, 3)
	528 invokeinterface (2, 3)
	529 java/util/List.org/apache/commons/math3/ode/sampling/StepInterpolator (2, 3)
	531 0 (2, 3)
	533 checkcast (2, 3)
	534 org/apache/commons/math3/ode/sampling/StepInterpolator (2, 3)
	536 invokespecial (2, 3)
	537 org/apache/commons/math3/ode/ContinuousOutputModel.locatePoint:(DLorg/apache/commons/math3/ode/sampling/StepInterpolator;)I (2, 3)
	539 ifle (2, 3)
	540 16 (2, 3)
	542 aload_0 (2, 3)
	543 dup (2, 3)
	544 getfield (2, 3)
	545 org/apache/commons/math3/ode/ContinuousOutputModel.index:I (2, 3)
	547 iconst_1 (2, 3)
	548 iadd (2, 3)
	549 putfield (2, 3)
	550 org/apache/commons/math3/ode/ContinuousOutputModel.index:I (2, 3)
	552 goto (2, 3)
	553 -43 (2, 3)
	555 aload_0 (1, 4)
	556 getfield (1, 4)
	557 org/apache/commons/math3/ode/ContinuousOutputModel.steps:Ljava/util/List; (1, 4)
	559 aload_0 (1, 4)
	560 getfield (1, 4)
	561 org/apache/commons/math3/ode/ContinuousOutputModel.index:I (1, 4)
	563 invokeinterface (1, 4)
	564 java/util/List.org/apache/commons/math3/ode/sampling/StepInterpolator (1, 4)
	566 0 (1, 4)
	568 checkcast (1, 4)
	569 org/apache/commons/math3/ode/sampling/StepInterpolator (1, 4)
	571 dload_1 (1, 4)
	572 invokeinterface (1, 4)
	573 org/apache/commons/math3/ode/sampling/StepInterpolator.rint:(D)D (1, 4)
	575 0 (1, 4)
	577 return (0, 4)

Method: getInterpolatedState
	0 aload_0 (0, 0)
	1 getfield (0, 0)
	2 org/apache/commons/math3/ode/ContinuousOutputModel.steps:Ljava/util/List; (0, 0)
	4 aload_0 (0, 0)
	5 getfield (0, 0)
	6 org/apache/commons/math3/ode/ContinuousOutputModel.index:I (0, 0)
	8 invokeinterface (0, 0)
	9 java/util/List.org/apache/commons/math3/ode/sampling/StepInterpolator (0, 0)
	11 0 (0, 0)
	13 checkcast (0, 0)
	14 org/apache/commons/math3/ode/sampling/StepInterpolator (0, 0)
	16 invokeinterface (0, 0)
	17 org/apache/commons/math3/ode/sampling/StepInterpolator.org/apache/commons/math3/exception/DimensionMismatchException (0, 0)
	19 0 (0, 0)
	21 areturn (0, 0)

Method: getInterpolatedDerivatives
	0 aload_0 (0, 0)
	1 getfield (0, 0)
	2 org/apache/commons/math3/ode/ContinuousOutputModel.steps:Ljava/util/List; (0, 0)
	4 aload_0 (0, 0)
	5 getfield (0, 0)
	6 org/apache/commons/math3/ode/ContinuousOutputModel.index:I (0, 0)
	8 invokeinterface (0, 0)
	9 java/util/List.org/apache/commons/math3/ode/sampling/StepInterpolator (0, 0)
	11 0 (0, 0)
	13 checkcast (0, 0)
	14 org/apache/commons/math3/ode/sampling/StepInterpolator (0, 0)
	16 invokeinterface (0, 0)
	17 org/apache/commons/math3/ode/sampling/StepInterpolator.getInterpolatedSecondaryState:(I)[D (0, 0)
	19 0 (0, 0)
	21 areturn (0, 0)

Method: getInterpolatedSecondaryState
	0 aload_0 (0, 0)
	1 getfield (0, 0)
	2 org/apache/commons/math3/ode/ContinuousOutputModel.steps:Ljava/util/List; (0, 0)
	4 aload_0 (0, 0)
	5 getfield (0, 0)
	6 org/apache/commons/math3/ode/ContinuousOutputModel.index:I (0, 0)
	8 invokeinterface (0, 0)
	9 java/util/List.org/apache/commons/math3/ode/sampling/StepInterpolator (0, 0)
	11 0 (0, 0)
	13 checkcast (0, 0)
	14 org/apache/commons/math3/ode/sampling/StepInterpolator (0, 0)
	16 iload_1 (0, 0)
	17 invokeinterface (0, 0)
	18 org/apache/commons/math3/ode/sampling/StepInterpolator.getInterpolatedSecondaryDerivatives:(I)[D (0, 0)
	20 0 (0, 0)
	22 areturn (0, 0)

Method: getInterpolatedSecondaryDerivatives
	0 aload_0 (0, 0)
	1 getfield (0, 0)
	2 org/apache/commons/math3/ode/ContinuousOutputModel.steps:Ljava/util/List; (0, 0)
	4 aload_0 (0, 0)
	5 getfield (0, 0)
	6 org/apache/commons/math3/ode/ContinuousOutputModel.index:I (0, 0)
	8 invokeinterface (0, 0)
	9 java/util/List.org/apache/commons/math3/ode/sampling/StepInterpolator (0, 0)
	11 0 (0, 0)
	13 checkcast (0, 0)
	14 org/apache/commons/math3/ode/sampling/StepInterpolator (0, 0)
	16 iload_1 (0, 0)
	17 invokeinterface (0, 0)
	18 org/apache/commons/math3/ode/sampling/StepInterpolator.org/apache/commons/math3/ode/ContinuousOutputModel (0, 0)
	20 0 (0, 0)
	22 areturn (0, 0)

Method: locatePoint
	0 aload_0 (1, 1)
	1 getfield (1, 1)
	2 org/apache/commons/math3/ode/ContinuousOutputModel.forward:Z (1, 1)
	4 ifeq (1, 1)
	5 31 (1, 1)
	7 dload_1 (2, 1)
	8 aload_3 (2, 1)
	9 invokeinterface (2, 1)
	10 org/apache/commons/math3/ode/sampling/StepInterpolator.getInitialTime:()D (2, 1)
	12 0 (2, 1)
	14 dcmpg (2, 1)
	15 ifge (2, 1)
	16 5 (2, 1)
	18 iconst_m1 (2, 1)
	19 ireturn (2, 1)
	20 dload_1 (3, 1)
	21 aload_3 (3, 1)
	22 invokeinterface (3, 1)
	23 org/apache/commons/math3/ode/sampling/StepInterpolator.getPreviousTime:()D (3, 1)
	25 0 (3, 1)
	27 dcmpl (3, 1)
	28 ifle (3, 1)
	29 5 (3, 1)
	31 iconst_1 (3, 1)
	32 ireturn (3, 1)
	33 iconst_0 (4, 2)
	34 ireturn (4, 2)
	35 dload_1 (1, 1)
	36 aload_3 (1, 1)
	37 invokeinterface (1, 1)
	38 org/apache/commons/math3/ode/sampling/StepInterpolator.getInitialTime:()D (1, 1)
	40 0 (1, 1)
	42 dcmpl (1, 1)
	43 ifle (1, 1)
	44 5 (1, 1)
	46 iconst_m1 (1, 1)
	47 ireturn (1, 1)
	48 dload_1 (2, 1)
	49 aload_3 (2, 1)
	50 invokeinterface (2, 1)
	51 org/apache/commons/math3/ode/sampling/StepInterpolator.getPreviousTime:()D (2, 1)
	53 0 (2, 1)
	55 dcmpg (2, 1)
	56 ifge (2, 1)
	57 5 (2, 1)
	59 iconst_1 (2, 1)
	60 ireturn (2, 1)
	61 iconst_0 (3, 2)
	62 ireturn (1, 2)

