Method: <init>
	0 aload_0 (0, 0)
	1 invokespecial (0, 0)
	4 aload_1 (0, 0)
	5 invokeinterface (0, 0)
	10 istore_3 (0, 0)
	11 aload_0 (0, 0)
	12 aload_1 (0, 0)
	13 putfield (0, 0)
	16 aload_0 (0, 0)
	17 new (0, 0)
	20 dup (0, 0)
	21 iload_2 (0, 0)
	22 iload_3 (0, 0)
	23 invokespecial (0, 0)
	26 putfield (0, 0)
	29 aload_0 (0, 0)
	30 iload_3 (0, 0)
	31 newarray (0, 0)
	33 putfield (0, 0)
	36 aload_0 (0, 0)
	37 iload_3 (0, 0)
	38 newarray (0, 0)
	40 putfield (0, 0)
	43 return (0, 0)

Method: access$000
	0 aload_0 (0, 0)
	1 getfield (0, 0)
	4 areturn (0, 0)

Method: access$100
	0 aload_0 (0, 0)
	1 getfield (0, 0)
	4 areturn (0, 0)

Method: access$200
	0 aload_0 (0, 0)
	1 getfield (0, 0)
	4 areturn (0, 0)

Method: access$300
	0 aload_0 (0, 0)
	1 getfield (0, 0)
	4 areturn (0, 0)

