Method: <init>
	0 aload_0 (1, 1)
	1 invokespecial (1, 1)
	2 java/lang/Object.<init>:()V (1, 1)
	4 aload_1 (1, 1)
	5 invokeinterface (1, 1)
	6 org/apache/commons/math3/ode/FirstOrderDifferentialEquations.primary:Lorg/apache/commons/math3/ode/FirstOrderDifferentialEquations; (1, 1)
	8 0 (1, 1)
	10 istore_2 (1, 1)
	11 aload_0 (1, 1)
	12 aload_1 (1, 1)
	13 putfield (1, 1)
	14 org/apache/commons/math3/ode/ExpandableStatefulODE.primary:Lorg/apache/commons/math3/ode/FirstOrderDifferentialEquations; (1, 1)
	16 aload_0 (1, 1)
	17 new (1, 1)
	18 org/apache/commons/math3/ode/EquationsMapper (1, 1)
	20 dup (1, 1)
	21 iconst_0 (1, 1)
	22 iload_2 (1, 1)
	23 invokespecial (1, 1)
	24 org/apache/commons/math3/ode/EquationsMapper.<init>:(II)V (1, 1)
	26 putfield (1, 1)
	27 org/apache/commons/math3/ode/ExpandableStatefulODE.primaryMapper:Lorg/apache/commons/math3/ode/EquationsMapper; (1, 1)
	29 aload_0 (1, 1)
	30 ldc2_w (1, 1)
	31 nan (1, 1)
	33 putfield (1, 1)
	34 org/apache/commons/math3/ode/ExpandableStatefulODE.time:D (1, 1)
	36 aload_0 (1, 1)
	37 iload_2 (1, 1)
	38 newarray (1, 1)
	39 7 (1, 1)
	40 putfield (1, 1)
	41 org/apache/commons/math3/ode/ExpandableStatefulODE.primaryState:[D (1, 1)
	43 aload_0 (1, 1)
	44 iload_2 (1, 1)
	45 newarray (1, 1)
	46 7 (1, 1)
	47 putfield (1, 1)
	48 org/apache/commons/math3/ode/ExpandableStatefulODE.primaryStateDot:[D (1, 1)
	50 aload_0 (1, 1)
	51 new (1, 1)
	52 java/util/ArrayList (1, 1)
	54 dup (1, 1)
	55 invokespecial (1, 1)
	56 java/util/ArrayList.<init>:()V (1, 1)
	58 putfield (1, 1)
	59 org/apache/commons/math3/ode/ExpandableStatefulODE.components:Ljava/util/List; (1, 1)
	61 return (0, 0)

Method: getPrimary
	0 aload_0 (0, 0)
	1 getfield (0, 0)
	2 org/apache/commons/math3/ode/ExpandableStatefulODE.primary:Lorg/apache/commons/math3/ode/FirstOrderDifferentialEquations; (0, 0)
	4 areturn (0, 0)

Method: getTotalDimension
	0 aload_0 (1, 1)
	1 getfield (1, 1)
	2 org/apache/commons/math3/ode/ExpandableStatefulODE.components:Ljava/util/List; (1, 1)
	4 invokeinterface (1, 1)
	5 java/util/List.size:()I (1, 1)
	7 0 (1, 1)
	9 ifeq (1, 1)
	10 11 (1, 1)
	12 aload_0 (1, 1)
	13 getfield (1, 1)
	14 org/apache/commons/math3/ode/ExpandableStatefulODE.primaryMapper:Lorg/apache/commons/math3/ode/EquationsMapper; (1, 1)
	16 invokevirtual (1, 1)
	17 org/apache/commons/math3/ode/EquationsMapper.getDimension:()I (1, 1)
	19 ireturn (1, 1)
	20 aload_0 (1, 2)
	21 getfield (1, 2)
	22 org/apache/commons/math3/ode/ExpandableStatefulODE.components:Ljava/util/List; (1, 2)
	24 aload_0 (1, 2)
	25 getfield (1, 2)
	26 org/apache/commons/math3/ode/ExpandableStatefulODE.components:Ljava/util/List; (1, 2)
	28 invokeinterface (1, 2)
	29 java/util/List.get:(I)Ljava/lang/Object; (1, 2)
	31 0 (1, 2)
	33 iconst_1 (1, 2)
	34 isub (1, 2)
	35 invokeinterface (1, 2)
	36 java/util/List.org/apache/commons/math3/ode/ExpandableStatefulODE$SecondaryComponent (1, 2)
	38 0 (1, 2)
	40 checkcast (1, 2)
	41 org/apache/commons/math3/ode/ExpandableStatefulODE$SecondaryComponent (1, 2)
	43 invokestatic (1, 2)
	44 org/apache/commons/math3/ode/ExpandableStatefulODE$SecondaryComponent.access$000:(Lorg/apache/commons/math3/ode/ExpandableStatefulODE$SecondaryComponent;)Lorg/apache/commons/math3/ode/EquationsMapper; (1, 2)
	46 astore_1 (1, 2)
	47 aload_1 (1, 2)
	48 invokevirtual (1, 2)
	49 org/apache/commons/math3/ode/EquationsMapper.getFirstIndex:()I (1, 2)
	51 aload_1 (1, 2)
	52 invokevirtual (1, 2)
	53 org/apache/commons/math3/ode/EquationsMapper.getDimension:()I (1, 2)
	55 iadd (1, 2)
	56 ireturn (1, 2)

Method: computeDerivatives
	0 aload_0 (0, 0)
	1 getfield (0, 0)
	2 org/apache/commons/math3/ode/ExpandableStatefulODE.primaryMapper:Lorg/apache/commons/math3/ode/EquationsMapper; (0, 0)
	4 aload_3 (0, 0)
	5 aload_0 (0, 0)
	6 getfield (0, 0)
	7 org/apache/commons/math3/ode/ExpandableStatefulODE.primaryState:[D (0, 0)
	9 invokevirtual (0, 0)
	10 org/apache/commons/math3/ode/EquationsMapper.extractEquationData:([D[D)V (0, 0)
	12 aload_0 (0, 0)
	13 getfield (0, 0)
	14 org/apache/commons/math3/ode/ExpandableStatefulODE.primary:Lorg/apache/commons/math3/ode/FirstOrderDifferentialEquations; (0, 0)
	16 dload_1 (0, 0)
	17 aload_0 (0, 0)
	18 getfield (0, 0)
	19 org/apache/commons/math3/ode/ExpandableStatefulODE.primaryState:[D (0, 0)
	21 aload_0 (0, 0)
	22 getfield (0, 0)
	23 org/apache/commons/math3/ode/ExpandableStatefulODE.primaryStateDot:[D (0, 0)
	25 invokeinterface (0, 0)
	26 org/apache/commons/math3/ode/FirstOrderDifferentialEquations.iterator:()Ljava/util/Iterator; (0, 0)
	28 0 (0, 0)
	30 aload_0 (1, 4)
	31 getfield (1, 4)
	32 org/apache/commons/math3/ode/ExpandableStatefulODE.components:Ljava/util/List; (1, 4)
	34 invokeinterface (1, 4)
	35 java/util/List.java/util/Iterator (1, 4)
	37 0 (1, 4)
	39 astore (1, 4)
	40 #5 (1, 4)
	41 aload (1, 4)
	42 #5 (1, 4)
	43 invokeinterface (1, 4)
	44 java/util/Iterator.next:()Ljava/lang/Object; (1, 4)
	46 0 (1, 4)
	48 ifeq (1, 4)
	49 76 (1, 4)
	51 aload (1, 4)
	52 #5 (1, 4)
	53 invokeinterface (1, 4)
	54 java/util/Iterator.access$100:(Lorg/apache/commons/math3/ode/ExpandableStatefulODE$SecondaryComponent;)[D (1, 4)
	56 0 (1, 4)
	58 checkcast (1, 4)
	59 org/apache/commons/math3/ode/ExpandableStatefulODE$SecondaryComponent (1, 4)
	61 astore (1, 4)
	62 #6 (1, 4)
	63 aload (1, 4)
	64 #6 (1, 4)
	65 invokestatic (1, 4)
	66 org/apache/commons/math3/ode/ExpandableStatefulODE$SecondaryComponent.access$000:(Lorg/apache/commons/math3/ode/ExpandableStatefulODE$SecondaryComponent;)Lorg/apache/commons/math3/ode/EquationsMapper; (1, 4)
	68 aload_3 (1, 4)
	69 aload (1, 4)
	70 #6 (1, 4)
	71 invokestatic (1, 4)
	72 org/apache/commons/math3/ode/ExpandableStatefulODE$SecondaryComponent.access$100:(Lorg/apache/commons/math3/ode/ExpandableStatefulODE$SecondaryComponent;)[D (1, 4)
	74 invokevirtual (1, 4)
	75 org/apache/commons/math3/ode/EquationsMapper.extractEquationData:([D[D)V (1, 4)
	77 aload (1, 4)
	78 #6 (1, 4)
	79 invokestatic (1, 4)
	80 org/apache/commons/math3/ode/ExpandableStatefulODE$SecondaryComponent.access$300:(Lorg/apache/commons/math3/ode/ExpandableStatefulODE$SecondaryComponent;)Lorg/apache/commons/math3/ode/SecondaryEquations; (1, 4)
	82 dload_1 (1, 4)
	83 aload_0 (1, 4)
	84 getfield (1, 4)
	85 org/apache/commons/math3/ode/ExpandableStatefulODE.primaryState:[D (1, 4)
	87 aload_0 (1, 4)
	88 getfield (1, 4)
	89 org/apache/commons/math3/ode/ExpandableStatefulODE.primaryStateDot:[D (1, 4)
	91 aload (1, 4)
	92 #6 (1, 4)
	93 invokestatic (1, 4)
	94 org/apache/commons/math3/ode/ExpandableStatefulODE$SecondaryComponent.access$100:(Lorg/apache/commons/math3/ode/ExpandableStatefulODE$SecondaryComponent;)[D (1, 4)
	96 aload (1, 4)
	97 #6 (1, 4)
	98 invokestatic (1, 4)
	99 org/apache/commons/math3/ode/ExpandableStatefulODE$SecondaryComponent.access$200:(Lorg/apache/commons/math3/ode/ExpandableStatefulODE$SecondaryComponent;)[D (1, 4)
	101 invokeinterface (1, 4)
	102 org/apache/commons/math3/ode/SecondaryEquations.insertEquationData:([D[D)V (1, 4)
	104 0 (1, 4)
	106 aload (1, 4)
	107 #6 (1, 4)
	108 invokestatic (1, 4)
	109 org/apache/commons/math3/ode/ExpandableStatefulODE$SecondaryComponent.access$000:(Lorg/apache/commons/math3/ode/ExpandableStatefulODE$SecondaryComponent;)Lorg/apache/commons/math3/ode/EquationsMapper; (1, 4)
	111 aload (1, 4)
	112 #6 (1, 4)
	113 invokestatic (1, 4)
	114 org/apache/commons/math3/ode/ExpandableStatefulODE$SecondaryComponent.access$200:(Lorg/apache/commons/math3/ode/ExpandableStatefulODE$SecondaryComponent;)[D (1, 4)
	116 aload (1, 4)
	117 #4 (1, 4)
	118 invokevirtual (1, 4)
	119 org/apache/commons/math3/ode/EquationsMapper.insertEquationData:([D[D)V (1, 4)
	121 goto (0, 4)
	122 -80 (0, 4)
	124 aload_0 (0, 4)
	125 getfield (0, 4)
	126 org/apache/commons/math3/ode/ExpandableStatefulODE.primaryMapper:Lorg/apache/commons/math3/ode/EquationsMapper; (0, 4)
	128 aload_0 (0, 4)
	129 getfield (0, 4)
	130 org/apache/commons/math3/ode/ExpandableStatefulODE.primaryStateDot:[D (0, 4)
	132 aload (0, 4)
	133 #4 (0, 4)
	134 invokevirtual (0, 4)
	135 org/apache/commons/math3/ode/EquationsMapper.insertEquationData:([D[D)V (0, 4)
	137 return (0, 4)

Method: addSecondaryEquations
	0 aload_0 (1, 1)
	1 getfield (1, 1)
	2 org/apache/commons/math3/ode/ExpandableStatefulODE.components:Ljava/util/List; (1, 1)
	4 invokeinterface (1, 1)
	5 java/util/List.size:()I (1, 1)
	7 0 (1, 1)
	9 ifeq (1, 1)
	10 27 (1, 1)
	12 aload_0 (1, 1)
	13 new (1, 1)
	14 java/util/ArrayList (1, 1)
	16 dup (1, 1)
	17 invokespecial (1, 1)
	18 java/util/ArrayList.<init>:()V (1, 1)
	20 putfield (1, 1)
	21 org/apache/commons/math3/ode/ExpandableStatefulODE.components:Ljava/util/List; (1, 1)
	23 aload_0 (1, 1)
	24 getfield (1, 1)
	25 org/apache/commons/math3/ode/ExpandableStatefulODE.primary:Lorg/apache/commons/math3/ode/FirstOrderDifferentialEquations; (1, 1)
	27 invokeinterface (1, 1)
	28 org/apache/commons/math3/ode/FirstOrderDifferentialEquations.primary:Lorg/apache/commons/math3/ode/FirstOrderDifferentialEquations; (1, 1)
	30 0 (1, 1)
	32 istore_2 (1, 1)
	33 goto (1, 1)
	34 43 (1, 1)
	36 aload_0 (1, 2)
	37 getfield (1, 2)
	38 org/apache/commons/math3/ode/ExpandableStatefulODE.components:Ljava/util/List; (1, 2)
	40 aload_0 (1, 2)
	41 getfield (1, 2)
	42 org/apache/commons/math3/ode/ExpandableStatefulODE.components:Ljava/util/List; (1, 2)
	44 invokeinterface (1, 2)
	45 java/util/List.get:(I)Ljava/lang/Object; (1, 2)
	47 0 (1, 2)
	49 iconst_1 (1, 2)
	50 isub (1, 2)
	51 invokeinterface (1, 2)
	52 java/util/List.org/apache/commons/math3/ode/ExpandableStatefulODE$SecondaryComponent (1, 2)
	54 0 (1, 2)
	56 checkcast (1, 2)
	57 org/apache/commons/math3/ode/ExpandableStatefulODE$SecondaryComponent (1, 2)
	59 astore_3 (1, 2)
	60 aload_3 (1, 2)
	61 invokestatic (1, 2)
	62 org/apache/commons/math3/ode/ExpandableStatefulODE$SecondaryComponent.access$000:(Lorg/apache/commons/math3/ode/ExpandableStatefulODE$SecondaryComponent;)Lorg/apache/commons/math3/ode/EquationsMapper; (1, 2)
	64 invokevirtual (1, 2)
	65 org/apache/commons/math3/ode/EquationsMapper.getFirstIndex:()I (1, 2)
	67 aload_3 (1, 2)
	68 invokestatic (1, 2)
	69 org/apache/commons/math3/ode/ExpandableStatefulODE$SecondaryComponent.access$000:(Lorg/apache/commons/math3/ode/ExpandableStatefulODE$SecondaryComponent;)Lorg/apache/commons/math3/ode/EquationsMapper; (1, 2)
	71 invokevirtual (1, 2)
	72 org/apache/commons/math3/ode/EquationsMapper.getDimension:()I (1, 2)
	74 iadd (1, 2)
	75 istore_2 (1, 2)
	76 aload_0 (0, 0)
	77 getfield (0, 0)
	78 org/apache/commons/math3/ode/ExpandableStatefulODE.components:Ljava/util/List; (0, 0)
	80 new (0, 0)
	81 org/apache/commons/math3/ode/ExpandableStatefulODE$SecondaryComponent (0, 0)
	83 dup (0, 0)
	84 aload_1 (0, 0)
	85 iload_2 (0, 0)
	86 invokespecial (0, 0)
	87 org/apache/commons/math3/ode/ExpandableStatefulODE$SecondaryComponent.<init>:(Lorg/apache/commons/math3/ode/SecondaryEquations;I)V (0, 0)
	89 invokeinterface (0, 0)
	90 java/util/List.org/apache/commons/math3/exception/DimensionMismatchException (0, 0)
	92 0 (0, 0)
	94 pop (0, 0)
	95 aload_0 (0, 0)
	96 getfield (0, 0)
	97 org/apache/commons/math3/ode/ExpandableStatefulODE.components:Ljava/util/List; (0, 0)
	99 invokeinterface (0, 0)
	100 java/util/List.get:(I)Ljava/lang/Object; (0, 0)
	102 0 (0, 0)
	104 iconst_1 (0, 0)
	105 isub (0, 0)
	106 ireturn (0, 0)

Method: getPrimaryMapper
	0 aload_0 (0, 0)
	1 getfield (0, 0)
	2 org/apache/commons/math3/ode/ExpandableStatefulODE.primaryMapper:Lorg/apache/commons/math3/ode/EquationsMapper; (0, 0)
	4 areturn (0, 0)

Method: getSecondaryMappers
	0 aload_0 (0, 0)
	1 getfield (0, 0)
	2 org/apache/commons/math3/ode/ExpandableStatefulODE.components:Ljava/util/List; (0, 0)
	4 invokeinterface (0, 0)
	5 java/util/List.get:(I)Ljava/lang/Object; (0, 0)
	7 0 (0, 0)
	9 anewarray (0, 0)
	10 org/apache/commons/math3/ode/EquationsMapper (0, 0)
	12 astore_1 (0, 0)
	13 iconst_0 (1, 4)
	14 istore_2 (1, 4)
	15 iload_2 (1, 4)
	16 aload_1 (1, 4)
	17 arraylength (1, 4)
	18 if_icmpge (1, 4)
	19 28 (1, 4)
	21 aload_1 (1, 4)
	22 iload_2 (1, 4)
	23 aload_0 (1, 4)
	24 getfield (1, 4)
	25 org/apache/commons/math3/ode/ExpandableStatefulODE.components:Ljava/util/List; (1, 4)
	27 iload_2 (1, 4)
	28 invokeinterface (1, 4)
	29 java/util/List.org/apache/commons/math3/ode/ExpandableStatefulODE$SecondaryComponent (1, 4)
	31 0 (1, 4)
	33 checkcast (1, 4)
	34 org/apache/commons/math3/ode/ExpandableStatefulODE$SecondaryComponent (1, 4)
	36 invokestatic (1, 4)
	37 org/apache/commons/math3/ode/ExpandableStatefulODE$SecondaryComponent.access$000:(Lorg/apache/commons/math3/ode/ExpandableStatefulODE$SecondaryComponent;)Lorg/apache/commons/math3/ode/EquationsMapper; (1, 4)
	39 aastore (1, 4)
	40 iinc (1, 4)
	41 #2 (1, 4)
	42 -89 (1, 4)
	43 goto (1, 4)
	44 -28 (1, 4)
	46 aload_1 (0, 0)
	47 areturn (0, 0)

Method: setTime
	0 aload_0 (0, 0)
	1 dload_1 (0, 0)
	2 putfield (0, 0)
	3 org/apache/commons/math3/ode/ExpandableStatefulODE.time:D (0, 0)
	5 return (0, 0)

Method: getTime
	0 aload_0 (0, 0)
	1 getfield (0, 0)
	2 org/apache/commons/math3/ode/ExpandableStatefulODE.time:D (0, 0)
	4 dreturn (0, 0)

Method: setPrimaryState
	0 aload_1 (1, 1)
	1 arraylength (1, 1)
	2 aload_0 (1, 1)
	3 getfield (1, 1)
	4 org/apache/commons/math3/ode/ExpandableStatefulODE.primaryState:[D (1, 1)
	6 arraylength (1, 1)
	7 if_icmpeq (1, 1)
	8 18 (1, 1)
	10 new (1, 1)
	11 org/apache/commons/math3/exception/DimensionMismatchException (1, 1)
	13 dup (1, 1)
	14 aload_1 (1, 1)
	15 arraylength (1, 1)
	16 aload_0 (1, 1)
	17 getfield (1, 1)
	18 org/apache/commons/math3/ode/ExpandableStatefulODE.primaryState:[D (1, 1)
	20 arraylength (1, 1)
	21 invokespecial (1, 1)
	22 org/apache/commons/math3/exception/DimensionMismatchException.<init>:(II)V (1, 1)
	24 athrow (1, 1)
	25 aload_1 (0, 0)
	26 iconst_0 (0, 0)
	27 aload_0 (0, 0)
	28 getfield (0, 0)
	29 org/apache/commons/math3/ode/ExpandableStatefulODE.primaryState:[D (0, 0)
	31 iconst_0 (0, 0)
	32 aload_1 (0, 0)
	33 arraylength (0, 0)
	34 invokestatic (0, 0)
	35 java/lang/System.arraycopy:(Ljava/lang/Object;ILjava/lang/Object;II)V (0, 0)
	37 return (0, 0)

Method: getPrimaryState
	0 aload_0 (0, 0)
	1 getfield (0, 0)
	2 org/apache/commons/math3/ode/ExpandableStatefulODE.primaryState:[D (0, 0)
	4 invokevirtual (0, 0)
	5 [D.clone:()Ljava/lang/Object; (0, 0)
	7 checkcast (0, 0)
	8 [D (0, 0)
	10 areturn (0, 0)

Method: getPrimaryStateDot
	0 aload_0 (0, 0)
	1 getfield (0, 0)
	2 org/apache/commons/math3/ode/ExpandableStatefulODE.primaryStateDot:[D (0, 0)
	4 invokevirtual (0, 0)
	5 [D.clone:()Ljava/lang/Object; (0, 0)
	7 checkcast (0, 0)
	8 [D (0, 0)
	10 areturn (0, 0)

Method: setSecondaryState
	0 aload_0 (0, 0)
	1 getfield (0, 0)
	2 org/apache/commons/math3/ode/ExpandableStatefulODE.components:Ljava/util/List; (0, 0)
	4 iload_1 (0, 0)
	5 invokeinterface (0, 0)
	6 java/util/List.org/apache/commons/math3/ode/ExpandableStatefulODE$SecondaryComponent (0, 0)
	8 0 (0, 0)
	10 checkcast (0, 0)
	11 org/apache/commons/math3/ode/ExpandableStatefulODE$SecondaryComponent (0, 0)
	13 invokestatic (0, 0)
	14 org/apache/commons/math3/ode/ExpandableStatefulODE$SecondaryComponent.access$100:(Lorg/apache/commons/math3/ode/ExpandableStatefulODE$SecondaryComponent;)[D (0, 0)
	16 astore_3 (0, 0)
	17 aload_2 (1, 1)
	18 arraylength (1, 1)
	19 aload_3 (1, 1)
	20 arraylength (1, 1)
	21 if_icmpeq (1, 1)
	22 15 (1, 1)
	24 new (1, 1)
	25 org/apache/commons/math3/exception/DimensionMismatchException (1, 1)
	27 dup (1, 1)
	28 aload_2 (1, 1)
	29 arraylength (1, 1)
	30 aload_3 (1, 1)
	31 arraylength (1, 1)
	32 invokespecial (1, 1)
	33 org/apache/commons/math3/exception/DimensionMismatchException.<init>:(II)V (1, 1)
	35 athrow (1, 1)
	36 aload_2 (0, 0)
	37 iconst_0 (0, 0)
	38 aload_3 (0, 0)
	39 iconst_0 (0, 0)
	40 aload_2 (0, 0)
	41 arraylength (0, 0)
	42 invokestatic (0, 0)
	43 java/lang/System.arraycopy:(Ljava/lang/Object;ILjava/lang/Object;II)V (0, 0)
	45 return (0, 0)

Method: getSecondaryState
	0 aload_0 (0, 0)
	1 getfield (0, 0)
	2 org/apache/commons/math3/ode/ExpandableStatefulODE.components:Ljava/util/List; (0, 0)
	4 iload_1 (0, 0)
	5 invokeinterface (0, 0)
	6 java/util/List.org/apache/commons/math3/ode/ExpandableStatefulODE$SecondaryComponent (0, 0)
	8 0 (0, 0)
	10 checkcast (0, 0)
	11 org/apache/commons/math3/ode/ExpandableStatefulODE$SecondaryComponent (0, 0)
	13 invokestatic (0, 0)
	14 org/apache/commons/math3/ode/ExpandableStatefulODE$SecondaryComponent.access$100:(Lorg/apache/commons/math3/ode/ExpandableStatefulODE$SecondaryComponent;)[D (0, 0)
	16 invokevirtual (0, 0)
	17 [D.clone:()Ljava/lang/Object; (0, 0)
	19 checkcast (0, 0)
	20 [D (0, 0)
	22 areturn (0, 0)

Method: getSecondaryStateDot
	0 aload_0 (0, 0)
	1 getfield (0, 0)
	2 org/apache/commons/math3/ode/ExpandableStatefulODE.components:Ljava/util/List; (0, 0)
	4 iload_1 (0, 0)
	5 invokeinterface (0, 0)
	6 java/util/List.org/apache/commons/math3/ode/ExpandableStatefulODE$SecondaryComponent (0, 0)
	8 0 (0, 0)
	10 checkcast (0, 0)
	11 org/apache/commons/math3/ode/ExpandableStatefulODE$SecondaryComponent (0, 0)
	13 invokestatic (0, 0)
	14 org/apache/commons/math3/ode/ExpandableStatefulODE$SecondaryComponent.access$200:(Lorg/apache/commons/math3/ode/ExpandableStatefulODE$SecondaryComponent;)[D (0, 0)
	16 invokevirtual (0, 0)
	17 [D.clone:()Ljava/lang/Object; (0, 0)
	19 checkcast (0, 0)
	20 [D (0, 0)
	22 areturn (0, 0)

Method: setCompleteState
	0 aload_1 (1, 1)
	1 arraylength (1, 1)
	2 aload_0 (1, 1)
	3 invokevirtual (1, 1)
	4 org/apache/commons/math3/ode/ExpandableStatefulODE.getTotalDimension:()I (1, 1)
	6 if_icmpeq (1, 1)
	7 17 (1, 1)
	9 new (1, 1)
	10 org/apache/commons/math3/exception/DimensionMismatchException (1, 1)
	12 dup (1, 1)
	13 aload_1 (1, 1)
	14 arraylength (1, 1)
	15 aload_0 (1, 1)
	16 invokevirtual (1, 1)
	17 org/apache/commons/math3/ode/ExpandableStatefulODE.getTotalDimension:()I (1, 1)
	19 invokespecial (1, 1)
	20 org/apache/commons/math3/exception/DimensionMismatchException.<init>:(II)V (1, 1)
	22 athrow (1, 1)
	23 aload_0 (0, 0)
	24 getfield (0, 0)
	25 org/apache/commons/math3/ode/ExpandableStatefulODE.primaryMapper:Lorg/apache/commons/math3/ode/EquationsMapper; (0, 0)
	27 aload_1 (0, 0)
	28 aload_0 (0, 0)
	29 getfield (0, 0)
	30 org/apache/commons/math3/ode/ExpandableStatefulODE.primaryState:[D (0, 0)
	32 invokevirtual (0, 0)
	33 org/apache/commons/math3/ode/EquationsMapper.extractEquationData:([D[D)V (0, 0)
	35 aload_0 (1, 4)
	36 getfield (1, 4)
	37 org/apache/commons/math3/ode/ExpandableStatefulODE.components:Ljava/util/List; (1, 4)
	39 invokeinterface (1, 4)
	40 java/util/List.java/util/Iterator (1, 4)
	42 0 (1, 4)
	44 astore_2 (1, 4)
	45 aload_2 (1, 4)
	46 invokeinterface (1, 4)
	47 java/util/Iterator.next:()Ljava/lang/Object; (1, 4)
	49 0 (1, 4)
	51 ifeq (1, 4)
	52 28 (1, 4)
	54 aload_2 (1, 4)
	55 invokeinterface (1, 4)
	56 java/util/Iterator.access$100:(Lorg/apache/commons/math3/ode/ExpandableStatefulODE$SecondaryComponent;)[D (1, 4)
	58 0 (1, 4)
	60 checkcast (1, 4)
	61 org/apache/commons/math3/ode/ExpandableStatefulODE$SecondaryComponent (1, 4)
	63 astore_3 (1, 4)
	64 aload_3 (1, 4)
	65 invokestatic (1, 4)
	66 org/apache/commons/math3/ode/ExpandableStatefulODE$SecondaryComponent.access$000:(Lorg/apache/commons/math3/ode/ExpandableStatefulODE$SecondaryComponent;)Lorg/apache/commons/math3/ode/EquationsMapper; (1, 4)
	68 aload_1 (1, 4)
	69 aload_3 (1, 4)
	70 invokestatic (1, 4)
	71 org/apache/commons/math3/ode/ExpandableStatefulODE$SecondaryComponent.access$100:(Lorg/apache/commons/math3/ode/ExpandableStatefulODE$SecondaryComponent;)[D (1, 4)
	73 invokevirtual (1, 4)
	74 org/apache/commons/math3/ode/EquationsMapper.extractEquationData:([D[D)V (1, 4)
	76 goto (0, 0)
	77 -31 (0, 0)
	79 return (0, 0)

Method: getCompleteState
	0 aload_0 (0, 0)
	1 invokevirtual (0, 0)
	2 org/apache/commons/math3/ode/ExpandableStatefulODE.getTotalDimension:()I (0, 0)
	4 newarray (0, 0)
	5 7 (0, 0)
	6 astore_1 (0, 0)
	7 aload_0 (0, 0)
	8 getfield (0, 0)
	9 org/apache/commons/math3/ode/ExpandableStatefulODE.primaryMapper:Lorg/apache/commons/math3/ode/EquationsMapper; (0, 0)
	11 aload_0 (0, 0)
	12 getfield (0, 0)
	13 org/apache/commons/math3/ode/ExpandableStatefulODE.primaryState:[D (0, 0)
	15 aload_1 (0, 0)
	16 invokevirtual (0, 0)
	17 org/apache/commons/math3/ode/EquationsMapper.insertEquationData:([D[D)V (0, 0)
	19 aload_0 (1, 4)
	20 getfield (1, 4)
	21 org/apache/commons/math3/ode/ExpandableStatefulODE.components:Ljava/util/List; (1, 4)
	23 invokeinterface (1, 4)
	24 java/util/List.java/util/Iterator (1, 4)
	26 0 (1, 4)
	28 astore_2 (1, 4)
	29 aload_2 (1, 4)
	30 invokeinterface (1, 4)
	31 java/util/Iterator.next:()Ljava/lang/Object; (1, 4)
	33 0 (1, 4)
	35 ifeq (1, 4)
	36 28 (1, 4)
	38 aload_2 (1, 4)
	39 invokeinterface (1, 4)
	40 java/util/Iterator.access$100:(Lorg/apache/commons/math3/ode/ExpandableStatefulODE$SecondaryComponent;)[D (1, 4)
	42 0 (1, 4)
	44 checkcast (1, 4)
	45 org/apache/commons/math3/ode/ExpandableStatefulODE$SecondaryComponent (1, 4)
	47 astore_3 (1, 4)
	48 aload_3 (1, 4)
	49 invokestatic (1, 4)
	50 org/apache/commons/math3/ode/ExpandableStatefulODE$SecondaryComponent.access$000:(Lorg/apache/commons/math3/ode/ExpandableStatefulODE$SecondaryComponent;)Lorg/apache/commons/math3/ode/EquationsMapper; (1, 4)
	52 aload_3 (1, 4)
	53 invokestatic (1, 4)
	54 org/apache/commons/math3/ode/ExpandableStatefulODE$SecondaryComponent.access$100:(Lorg/apache/commons/math3/ode/ExpandableStatefulODE$SecondaryComponent;)[D (1, 4)
	56 aload_1 (1, 4)
	57 invokevirtual (1, 4)
	58 org/apache/commons/math3/ode/EquationsMapper.insertEquationData:([D[D)V (1, 4)
	60 goto (0, 0)
	61 -31 (0, 0)
	63 aload_1 (0, 0)
	64 areturn (0, 0)

