Method: <init>
	0 aload_0 (1, 1)
	1 invokespecial (1, 1)
	2 java/lang/Object.<init>:()V (1, 1)
	4 aload_0 (1, 1)
	5 aload_1 (1, 1)
	6 putfield (1, 1)
	7 org/apache/commons/math3/ode/FieldExpandableODE.primary:Lorg/apache/commons/math3/ode/FirstOrderFieldDifferentialEquations; (1, 1)
	9 aload_0 (1, 1)
	10 new (1, 1)
	11 java/util/ArrayList (1, 1)
	13 dup (1, 1)
	14 invokespecial (1, 1)
	15 java/util/ArrayList.<init>:()V (1, 1)
	17 putfield (1, 1)
	18 org/apache/commons/math3/ode/FieldExpandableODE.components:Ljava/util/List; (1, 1)
	20 aload_0 (1, 1)
	21 new (1, 1)
	22 org/apache/commons/math3/ode/FieldEquationsMapper (1, 1)
	24 dup (1, 1)
	25 aconst_null (1, 1)
	26 aload_1 (1, 1)
	27 invokeinterface (1, 1)
	28 org/apache/commons/math3/ode/FirstOrderFieldDifferentialEquations.<init>:(Lorg/apache/commons/math3/ode/FieldEquationsMapper;I)V (1, 1)
	30 0 (1, 1)
	32 invokespecial (1, 1)
	33 org/apache/commons/math3/ode/FieldEquationsMapper.<init>:(Lorg/apache/commons/math3/ode/FieldEquationsMapper;I)V (1, 1)
	35 putfield (1, 1)
	36 org/apache/commons/math3/ode/FieldExpandableODE.mapper:Lorg/apache/commons/math3/ode/FieldEquationsMapper; (1, 1)
	38 return (0, 0)

Method: getMapper
	0 aload_0 (0, 0)
	1 getfield (0, 0)
	2 org/apache/commons/math3/ode/FieldExpandableODE.mapper:Lorg/apache/commons/math3/ode/FieldEquationsMapper; (0, 0)
	4 areturn (0, 0)

Method: addSecondaryEquations
	0 aload_0 (0, 0)
	1 getfield (0, 0)
	2 org/apache/commons/math3/ode/FieldExpandableODE.components:Ljava/util/List; (0, 0)
	4 aload_1 (0, 0)
	5 invokeinterface (0, 0)
	6 java/util/List.size:()I (0, 0)
	8 0 (0, 0)
	10 pop (0, 0)
	11 aload_0 (0, 0)
	12 new (0, 0)
	13 org/apache/commons/math3/ode/FieldEquationsMapper (0, 0)
	15 dup (0, 0)
	16 aload_0 (0, 0)
	17 getfield (0, 0)
	18 org/apache/commons/math3/ode/FieldExpandableODE.mapper:Lorg/apache/commons/math3/ode/FieldEquationsMapper; (0, 0)
	20 aload_1 (0, 0)
	21 invokeinterface (0, 0)
	22 org/apache/commons/math3/ode/FieldSecondaryEquations.<init>:(Lorg/apache/commons/math3/ode/FieldEquationsMapper;I)V (0, 0)
	24 0 (0, 0)
	26 invokespecial (0, 0)
	27 org/apache/commons/math3/ode/FieldEquationsMapper.<init>:(Lorg/apache/commons/math3/ode/FieldEquationsMapper;I)V (0, 0)
	29 putfield (0, 0)
	30 org/apache/commons/math3/ode/FieldExpandableODE.mapper:Lorg/apache/commons/math3/ode/FieldEquationsMapper; (0, 0)
	32 aload_0 (0, 0)
	33 getfield (0, 0)
	34 org/apache/commons/math3/ode/FieldExpandableODE.components:Ljava/util/List; (0, 0)
	36 invokeinterface (0, 0)
	37 java/util/List.extractEquationData:(I[Lorg/apache/commons/math3/RealFieldElement;)[Lorg/apache/commons/math3/RealFieldElement; (0, 0)
	39 0 (0, 0)
	41 ireturn (0, 0)

Method: init
	0 iconst_0 (0, 0)
	1 istore (0, 0)
	2 #4 (0, 0)
	3 aload_0 (0, 0)
	4 getfield (0, 0)
	5 org/apache/commons/math3/ode/FieldExpandableODE.mapper:Lorg/apache/commons/math3/ode/FieldEquationsMapper; (0, 0)
	7 iload (0, 0)
	8 #4 (0, 0)
	9 aload_2 (0, 0)
	10 invokevirtual (0, 0)
	11 org/apache/commons/math3/ode/FieldEquationsMapper.extractEquationData:(I[Lorg/apache/commons/math3/RealFieldElement;)[Lorg/apache/commons/math3/RealFieldElement; (0, 0)
	13 astore (0, 0)
	14 #5 (0, 0)
	15 aload_0 (0, 0)
	16 getfield (0, 0)
	17 org/apache/commons/math3/ode/FieldExpandableODE.primary:Lorg/apache/commons/math3/ode/FirstOrderFieldDifferentialEquations; (0, 0)
	19 aload_1 (0, 0)
	20 aload (0, 0)
	21 #5 (0, 0)
	22 aload_3 (0, 0)
	23 invokeinterface (0, 0)
	24 org/apache/commons/math3/ode/FirstOrderFieldDifferentialEquations.getNumberOfEquations:()I (0, 0)
	26 0 (0, 0)
	28 iinc (1, 3)
	29 #4 (1, 3)
	30 21 (1, 3)
	31 iload (1, 3)
	32 #4 (1, 3)
	33 aload_0 (1, 3)
	34 getfield (1, 3)
	35 org/apache/commons/math3/ode/FieldExpandableODE.mapper:Lorg/apache/commons/math3/ode/FieldEquationsMapper; (1, 3)
	37 invokevirtual (1, 3)
	38 org/apache/commons/math3/ode/FieldEquationsMapper.getNumberOfEquations:()I (1, 3)
	40 if_icmpge (1, 3)
	41 45 (1, 3)
	43 aload_0 (1, 3)
	44 getfield (1, 3)
	45 org/apache/commons/math3/ode/FieldExpandableODE.mapper:Lorg/apache/commons/math3/ode/FieldEquationsMapper; (1, 3)
	47 iload (1, 3)
	48 #4 (1, 3)
	49 aload_2 (1, 3)
	50 invokevirtual (1, 3)
	51 org/apache/commons/math3/ode/FieldEquationsMapper.extractEquationData:(I[Lorg/apache/commons/math3/RealFieldElement;)[Lorg/apache/commons/math3/RealFieldElement; (1, 3)
	53 astore (1, 3)
	54 #6 (1, 3)
	55 aload_0 (1, 3)
	56 getfield (1, 3)
	57 org/apache/commons/math3/ode/FieldExpandableODE.components:Ljava/util/List; (1, 3)
	59 iload (1, 3)
	60 #4 (1, 3)
	61 iconst_1 (1, 3)
	62 isub (1, 3)
	63 invokeinterface (1, 3)
	64 java/util/List.org/apache/commons/math3/ode/FieldSecondaryEquations (1, 3)
	66 0 (1, 3)
	68 checkcast (1, 3)
	69 org/apache/commons/math3/ode/FieldSecondaryEquations (1, 3)
	71 aload_1 (1, 3)
	72 aload (1, 3)
	73 #5 (1, 3)
	74 aload (1, 3)
	75 #6 (1, 3)
	76 aload_3 (1, 3)
	77 invokeinterface (1, 3)
	78 org/apache/commons/math3/ode/FieldSecondaryEquations.org/apache/commons/math3/RealFieldElement (1, 3)
	80 0 (1, 3)
	82 goto (0, 0)
	83 -54 (0, 0)
	85 return (0, 0)

Method: computeDerivatives
	0 aload_1 (0, 0)
	1 invokeinterface (0, 0)
	2 org/apache/commons/math3/RealFieldElement.getTotalDimension:()I (0, 0)
	4 0 (0, 0)
	6 aload_0 (0, 0)
	7 getfield (0, 0)
	8 org/apache/commons/math3/ode/FieldExpandableODE.mapper:Lorg/apache/commons/math3/ode/FieldEquationsMapper; (0, 0)
	10 invokevirtual (0, 0)
	11 org/apache/commons/math3/ode/FieldEquationsMapper.getTotalDimension:()I (0, 0)
	13 invokestatic (0, 0)
	14 org/apache/commons/math3/util/MathArrays.buildArray:(Lorg/apache/commons/math3/Field;I)[Ljava/lang/Object; (0, 0)
	16 checkcast (0, 0)
	17 [Lorg/apache/commons/math3/RealFieldElement; (0, 0)
	19 astore_3 (0, 0)
	20 iconst_0 (0, 0)
	21 istore (0, 0)
	22 #4 (0, 0)
	23 aload_0 (0, 0)
	24 getfield (0, 0)
	25 org/apache/commons/math3/ode/FieldExpandableODE.mapper:Lorg/apache/commons/math3/ode/FieldEquationsMapper; (0, 0)
	27 iload (0, 0)
	28 #4 (0, 0)
	29 aload_2 (0, 0)
	30 invokevirtual (0, 0)
	31 org/apache/commons/math3/ode/FieldEquationsMapper.extractEquationData:(I[Lorg/apache/commons/math3/RealFieldElement;)[Lorg/apache/commons/math3/RealFieldElement; (0, 0)
	33 astore (0, 0)
	34 #5 (0, 0)
	35 aload_0 (0, 0)
	36 getfield (0, 0)
	37 org/apache/commons/math3/ode/FieldExpandableODE.primary:Lorg/apache/commons/math3/ode/FirstOrderFieldDifferentialEquations; (0, 0)
	39 aload_1 (0, 0)
	40 aload (0, 0)
	41 #5 (0, 0)
	42 invokeinterface (0, 0)
	43 org/apache/commons/math3/ode/FirstOrderFieldDifferentialEquations.insertEquationData:(I[Lorg/apache/commons/math3/RealFieldElement;[Lorg/apache/commons/math3/RealFieldElement;)V (0, 0)
	45 0 (0, 0)
	47 astore (0, 0)
	48 #6 (0, 0)
	49 aload_0 (0, 0)
	50 getfield (0, 0)
	51 org/apache/commons/math3/ode/FieldExpandableODE.mapper:Lorg/apache/commons/math3/ode/FieldEquationsMapper; (0, 0)
	53 iload (0, 0)
	54 #4 (0, 0)
	55 aload (0, 0)
	56 #6 (0, 0)
	57 aload_3 (0, 0)
	58 invokevirtual (0, 0)
	59 org/apache/commons/math3/ode/FieldEquationsMapper.insertEquationData:(I[Lorg/apache/commons/math3/RealFieldElement;[Lorg/apache/commons/math3/RealFieldElement;)V (0, 0)
	61 iinc (2, 3)
	62 #4 (2, 3)
	63 21 (2, 3)
	64 iload (2, 3)
	65 #4 (2, 3)
	66 aload_0 (2, 3)
	67 getfield (2, 3)
	68 org/apache/commons/math3/ode/FieldExpandableODE.mapper:Lorg/apache/commons/math3/ode/FieldEquationsMapper; (2, 3)
	70 invokevirtual (2, 3)
	71 org/apache/commons/math3/ode/FieldEquationsMapper.getNumberOfEquations:()I (2, 3)
	73 if_icmpge (2, 3)
	74 60 (2, 3)
	76 aload_0 (2, 3)
	77 getfield (2, 3)
	78 org/apache/commons/math3/ode/FieldExpandableODE.mapper:Lorg/apache/commons/math3/ode/FieldEquationsMapper; (2, 3)
	80 iload (2, 3)
	81 #4 (2, 3)
	82 aload_2 (2, 3)
	83 invokevirtual (2, 3)
	84 org/apache/commons/math3/ode/FieldEquationsMapper.extractEquationData:(I[Lorg/apache/commons/math3/RealFieldElement;)[Lorg/apache/commons/math3/RealFieldElement; (2, 3)
	86 astore (2, 3)
	87 #7 (2, 3)
	88 aload_0 (2, 3)
	89 getfield (2, 3)
	90 org/apache/commons/math3/ode/FieldExpandableODE.components:Ljava/util/List; (2, 3)
	92 iload (2, 3)
	93 #4 (2, 3)
	94 iconst_1 (2, 3)
	95 isub (2, 3)
	96 invokeinterface (2, 3)
	97 java/util/List.org/apache/commons/math3/ode/FieldSecondaryEquations (2, 3)
	99 0 (2, 3)
	101 checkcast (2, 3)
	102 org/apache/commons/math3/ode/FieldSecondaryEquations (2, 3)
	104 aload_1 (2, 3)
	105 aload (2, 3)
	106 #5 (2, 3)
	107 aload (2, 3)
	108 #6 (2, 3)
	109 aload (2, 3)
	110 #7 (2, 3)
	111 invokeinterface (2, 3)
	112 org/apache/commons/math3/ode/FieldSecondaryEquations.org/apache/commons/math3/ode/FieldExpandableODE (2, 3)
	114 0 (2, 3)
	116 astore (2, 3)
	117 #8 (2, 3)
	118 aload_0 (2, 3)
	119 getfield (2, 3)
	120 org/apache/commons/math3/ode/FieldExpandableODE.mapper:Lorg/apache/commons/math3/ode/FieldEquationsMapper; (2, 3)
	122 iload (2, 3)
	123 #4 (2, 3)
	124 aload (2, 3)
	125 #8 (2, 3)
	126 aload_3 (2, 3)
	127 invokevirtual (2, 3)
	128 org/apache/commons/math3/ode/FieldEquationsMapper.insertEquationData:(I[Lorg/apache/commons/math3/RealFieldElement;[Lorg/apache/commons/math3/RealFieldElement;)V (2, 3)
	130 goto (1, 4)
	131 -69 (1, 4)
	133 aload_3 (1, 4)
	134 areturn (0, 4)

