Method: <init>
	0 aload_0 (0, 0)
	1 aload_1 (0, 0)
	2 aload_2 (0, 0)
	3 aload (0, 0)
	4 #4 (0, 0)
	5 invokespecial (0, 0)
	6 org/apache/commons/math3/ode/FieldODEState.<init>:(Lorg/apache/commons/math3/RealFieldElement;[Lorg/apache/commons/math3/RealFieldElement;[[Lorg/apache/commons/math3/RealFieldElement;)V (0, 0)
	8 aload_0 (0, 0)
	9 aload_3 (0, 0)
	10 invokevirtual (0, 0)
	11 [Lorg/apache/commons/math3/RealFieldElement;.clone:()Ljava/lang/Object; (0, 0)
	13 checkcast (0, 0)
	14 [Lorg/apache/commons/math3/RealFieldElement; (0, 0)
	16 putfield (0, 0)
	17 org/apache/commons/math3/ode/FieldODEStateAndDerivative.derivative:[Lorg/apache/commons/math3/RealFieldElement; (0, 0)
	19 aload_0 (0, 0)
	20 aload_0 (0, 0)
	21 aload_1 (0, 0)
	22 invokeinterface (0, 0)
	23 org/apache/commons/math3/RealFieldElement.copy:(Lorg/apache/commons/math3/Field;[[Lorg/apache/commons/math3/RealFieldElement;)[[Lorg/apache/commons/math3/RealFieldElement; (0, 0)
	25 0 (0, 0)
	27 aload (0, 0)
	28 #5 (0, 0)
	29 invokevirtual (0, 0)
	30 org/apache/commons/math3/ode/FieldODEStateAndDerivative.copy:(Lorg/apache/commons/math3/Field;[[Lorg/apache/commons/math3/RealFieldElement;)[[Lorg/apache/commons/math3/RealFieldElement; (0, 0)
	32 putfield (0, 0)
	33 org/apache/commons/math3/ode/FieldODEStateAndDerivative.secondaryDerivative:[[Lorg/apache/commons/math3/RealFieldElement; (0, 0)
	35 return (0, 0)

Method: getDerivative
	0 aload_0 (0, 0)
	1 getfield (0, 0)
	2 org/apache/commons/math3/ode/FieldODEStateAndDerivative.derivative:[Lorg/apache/commons/math3/RealFieldElement; (0, 0)
	4 invokevirtual (0, 0)
	5 [Lorg/apache/commons/math3/RealFieldElement;.clone:()Ljava/lang/Object; (0, 0)
	7 checkcast (0, 0)
	8 [Lorg/apache/commons/math3/RealFieldElement; (0, 0)
	10 areturn (0, 0)

Method: getSecondaryDerivative
	0 iload_1 (0, 0)
	1 ifne (0, 0)
	2 16 (0, 0)
	4 aload_0 (0, 0)
	5 getfield (0, 0)
	6 org/apache/commons/math3/ode/FieldODEStateAndDerivative.derivative:[Lorg/apache/commons/math3/RealFieldElement; (0, 0)
	8 invokevirtual (0, 0)
	9 [Lorg/apache/commons/math3/RealFieldElement;.clone:()Ljava/lang/Object; (0, 0)
	11 checkcast (0, 0)
	12 [Lorg/apache/commons/math3/RealFieldElement; (0, 0)
	14 goto (0, 0)
	15 17 (0, 0)
	17 aload_0 (0, 0)
	18 getfield (0, 0)
	19 org/apache/commons/math3/ode/FieldODEStateAndDerivative.secondaryDerivative:[[Lorg/apache/commons/math3/RealFieldElement; (0, 0)
	21 iload_1 (0, 0)
	22 iconst_1 (0, 0)
	23 isub (0, 0)
	24 aaload (0, 0)
	25 invokevirtual (0, 0)
	26 [Lorg/apache/commons/math3/RealFieldElement;.clone:()Ljava/lang/Object; (0, 0)
	28 checkcast (0, 0)
	29 [Lorg/apache/commons/math3/RealFieldElement; (0, 0)
	31 areturn (0, 0)

