Method: <init>
	0 aload_0 (1, 1)
	1 invokespecial (1, 1)
	4 aload_0 (1, 1)
	5 aload_1 (1, 1)
	6 putfield (1, 1)
	9 aload_0 (1, 1)
	10 new (1, 1)
	13 dup (1, 1)
	14 invokespecial (1, 1)
	17 putfield (1, 1)
	20 aload_0 (1, 1)
	21 new (1, 1)
	24 dup (1, 1)
	25 aconst_null (1, 1)
	26 aload_1 (1, 1)
	27 invokeinterface (1, 1)
	32 invokespecial (1, 1)
	35 putfield (1, 1)
	38 return (0, 0)

Method: getMapper
	0 aload_0 (0, 0)
	1 getfield (0, 0)
	4 areturn (0, 0)

Method: addSecondaryEquations
	0 aload_0 (0, 0)
	1 getfield (0, 0)
	4 aload_1 (0, 0)
	5 invokeinterface (0, 0)
	10 pop (0, 0)
	11 aload_0 (0, 0)
	12 new (0, 0)
	15 dup (0, 0)
	16 aload_0 (0, 0)
	17 getfield (0, 0)
	20 aload_1 (0, 0)
	21 invokeinterface (0, 0)
	26 invokespecial (0, 0)
	29 putfield (0, 0)
	32 aload_0 (0, 0)
	33 getfield (0, 0)
	36 invokeinterface (0, 0)
	41 ireturn (0, 0)

Method: init
	0 iconst_0 (0, 0)
	1 istore (0, 0)
	3 aload_0 (0, 0)
	4 getfield (0, 0)
	7 iload (0, 0)
	9 aload_2 (0, 0)
	10 invokevirtual (0, 0)
	13 astore (0, 0)
	15 aload_0 (0, 0)
	16 getfield (0, 0)
	19 aload_1 (0, 0)
	20 aload (0, 0)
	22 aload_3 (0, 0)
	23 invokeinterface (0, 0)
	28 iinc (1, 3)
	31 iload (1, 3)
	33 aload_0 (1, 3)
	34 getfield (1, 3)
	37 invokevirtual (1, 3)
	40 if_icmpge (1, 3)
	43 aload_0 (1, 3)
	44 getfield (1, 3)
	47 iload (1, 3)
	49 aload_2 (1, 3)
	50 invokevirtual (1, 3)
	53 astore (1, 3)
	55 aload_0 (1, 3)
	56 getfield (1, 3)
	59 iload (1, 3)
	61 iconst_1 (1, 3)
	62 isub (1, 3)
	63 invokeinterface (1, 3)
	68 checkcast (1, 3)
	71 aload_1 (1, 3)
	72 aload (1, 3)
	74 aload (1, 3)
	76 aload_3 (1, 3)
	77 invokeinterface (1, 3)
	82 goto (0, 0)
	85 return (0, 0)

Method: computeDerivatives
	0 aload_1 (0, 0)
	1 invokeinterface (0, 0)
	6 aload_0 (0, 0)
	7 getfield (0, 0)
	10 invokevirtual (0, 0)
	13 invokestatic (0, 0)
	16 checkcast (0, 0)
	19 astore_3 (0, 0)
	20 iconst_0 (0, 0)
	21 istore (0, 0)
	23 aload_0 (0, 0)
	24 getfield (0, 0)
	27 iload (0, 0)
	29 aload_2 (0, 0)
	30 invokevirtual (0, 0)
	33 astore (0, 0)
	35 aload_0 (0, 0)
	36 getfield (0, 0)
	39 aload_1 (0, 0)
	40 aload (0, 0)
	42 invokeinterface (0, 0)
	47 astore (0, 0)
	49 aload_0 (0, 0)
	50 getfield (0, 0)
	53 iload (0, 0)
	55 aload (0, 0)
	57 aload_3 (0, 0)
	58 invokevirtual (0, 0)
	61 iinc (1, 3)
	64 iload (1, 3)
	66 aload_0 (1, 3)
	67 getfield (1, 3)
	70 invokevirtual (1, 3)
	73 if_icmpge (1, 3)
	76 aload_0 (1, 3)
	77 getfield (1, 3)
	80 iload (1, 3)
	82 aload_2 (1, 3)
	83 invokevirtual (1, 3)
	86 astore (1, 3)
	88 aload_0 (1, 3)
	89 getfield (1, 3)
	92 iload (1, 3)
	94 iconst_1 (1, 3)
	95 isub (1, 3)
	96 invokeinterface (1, 3)
	101 checkcast (1, 3)
	104 aload_1 (1, 3)
	105 aload (1, 3)
	107 aload (1, 3)
	109 aload (1, 3)
	111 invokeinterface (1, 3)
	116 astore (1, 3)
	118 aload_0 (1, 3)
	119 getfield (1, 3)
	122 iload (1, 3)
	124 aload (1, 3)
	126 aload_3 (1, 3)
	127 invokevirtual (1, 3)
	130 goto (0, 4)
	133 aload_3 (0, 4)
	134 areturn (0, 4)

