Method: <init>
	0 aload_0 (1, 1)
	1 invokespecial (1, 1)
	4 aload_0 (1, 1)
	5 aload_1 (1, 1)
	6 putfield (1, 1)
	9 aload_0 (1, 1)
	10 aload_1 (1, 1)
	11 invokeinterface (1, 1)
	16 putfield (1, 1)
	19 aload_0 (1, 1)
	20 aload_0 (1, 1)
	21 getfield (1, 1)
	24 newarray (1, 1)
	26 putfield (1, 1)
	29 aload_0 (1, 1)
	30 aload_0 (1, 1)
	31 getfield (1, 1)
	34 newarray (1, 1)
	36 putfield (1, 1)
	39 aload_0 (1, 1)
	40 aload_0 (1, 1)
	41 getfield (1, 1)
	44 newarray (1, 1)
	46 putfield (1, 1)
	49 return (0, 0)

Method: getDimension
	0 iconst_2 (0, 0)
	1 aload_0 (0, 0)
	2 getfield (0, 0)
	5 imul (0, 0)
	6 ireturn (0, 0)

Method: computeDerivatives
	0 aload_3 (0, 0)
	1 iconst_0 (0, 0)
	2 aload_0 (0, 0)
	3 getfield (0, 0)
	6 iconst_0 (0, 0)
	7 aload_0 (0, 0)
	8 getfield (0, 0)
	11 invokestatic (0, 0)
	14 aload_3 (0, 0)
	15 aload_0 (0, 0)
	16 getfield (0, 0)
	19 aload_0 (0, 0)
	20 getfield (0, 0)
	23 iconst_0 (0, 0)
	24 aload_0 (0, 0)
	25 getfield (0, 0)
	28 invokestatic (0, 0)
	31 aload_0 (0, 0)
	32 getfield (0, 0)
	35 dload_1 (0, 0)
	36 aload_0 (0, 0)
	37 getfield (0, 0)
	40 aload_0 (0, 0)
	41 getfield (0, 0)
	44 aload_0 (0, 0)
	45 getfield (0, 0)
	48 invokeinterface (0, 0)
	53 aload_0 (0, 0)
	54 getfield (0, 0)
	57 iconst_0 (0, 0)
	58 aload (0, 0)
	60 iconst_0 (0, 0)
	61 aload_0 (0, 0)
	62 getfield (0, 0)
	65 invokestatic (0, 0)
	68 aload_0 (0, 0)
	69 getfield (0, 0)
	72 iconst_0 (0, 0)
	73 aload (0, 0)
	75 aload_0 (0, 0)
	76 getfield (0, 0)
	79 aload_0 (0, 0)
	80 getfield (0, 0)
	83 invokestatic (0, 0)
	86 return (0, 0)

