Method: <init>
	0 aload_0 (0, 0)
	1 invokespecial (0, 0)
	2 java/lang/Object.<init>:()V (0, 0)
	4 aload_0 (0, 0)
	5 aconst_null (0, 0)
	6 putfield (0, 0)
	7 org/apache/commons/math3/ode/JacobianMatrices.efode:Lorg/apache/commons/math3/ode/ExpandableStatefulODE; (0, 0)
	9 aload_0 (0, 0)
	10 iconst_m1 (0, 0)
	11 putfield (0, 0)
	12 org/apache/commons/math3/ode/JacobianMatrices.index:I (0, 0)
	14 aload_0 (0, 0)
	15 aload_1 (0, 0)
	16 putfield (0, 0)
	17 org/apache/commons/math3/ode/JacobianMatrices.jode:Lorg/apache/commons/math3/ode/MainStateJacobianProvider; (0, 0)
	19 aload_0 (0, 0)
	20 aconst_null (0, 0)
	21 putfield (0, 0)
	22 org/apache/commons/math3/ode/JacobianMatrices.pode:Lorg/apache/commons/math3/ode/ParameterizedODE; (0, 0)
	24 aload_0 (0, 0)
	25 aload_1 (0, 0)
	26 invokeinterface (0, 0)
	27 org/apache/commons/math3/ode/MainStateJacobianProvider.org/apache/commons/math3/ode/ParameterConfiguration (0, 0)
	29 0 (0, 0)
	31 putfield (0, 0)
	32 org/apache/commons/math3/ode/JacobianMatrices.stateDim:I (0, 0)
	34 aload_2 (2, 1)
	35 ifnonnull (2, 1)
	36 16 (2, 1)
	38 aload_0 (2, 1)
	39 aconst_null (2, 1)
	40 putfield (2, 1)
	41 org/apache/commons/math3/ode/JacobianMatrices.selectedParameters:[Lorg/apache/commons/math3/ode/ParameterConfiguration; (2, 1)
	43 aload_0 (2, 1)
	44 iconst_0 (2, 1)
	45 putfield (2, 1)
	46 org/apache/commons/math3/ode/JacobianMatrices.paramDim:I (2, 1)
	48 goto (2, 1)
	49 51 (2, 1)
	51 aload_0 (2, 2)
	52 aload_2 (2, 2)
	53 arraylength (2, 2)
	54 anewarray (2, 2)
	55 org/apache/commons/math3/ode/ParameterConfiguration (2, 2)
	57 putfield (2, 2)
	58 org/apache/commons/math3/ode/JacobianMatrices.selectedParameters:[Lorg/apache/commons/math3/ode/ParameterConfiguration; (2, 2)
	60 iconst_0 (3, 4)
	61 istore_3 (3, 4)
	62 iload_3 (3, 4)
	63 aload_2 (3, 4)
	64 arraylength (3, 4)
	65 if_icmpge (3, 4)
	66 28 (3, 4)
	68 aload_0 (3, 4)
	69 getfield (3, 4)
	70 org/apache/commons/math3/ode/JacobianMatrices.selectedParameters:[Lorg/apache/commons/math3/ode/ParameterConfiguration; (3, 4)
	72 iload_3 (3, 4)
	73 new (3, 4)
	74 org/apache/commons/math3/ode/ParameterConfiguration (3, 4)
	76 dup (3, 4)
	77 aload_2 (3, 4)
	78 iload_3 (3, 4)
	79 aaload (3, 4)
	80 ldc2_w (3, 4)
	81 nan (3, 4)
	83 invokespecial (3, 4)
	84 org/apache/commons/math3/ode/ParameterConfiguration.<init>:(Ljava/lang/String;D)V (3, 4)
	86 aastore (3, 4)
	87 iinc (3, 4)
	88 #3 (3, 4)
	89 -89 (3, 4)
	90 goto (3, 4)
	91 -28 (3, 4)
	93 aload_0 (2, 2)
	94 aload_2 (2, 2)
	95 arraylength (2, 2)
	96 putfield (2, 2)
	97 org/apache/commons/math3/ode/JacobianMatrices.paramDim:I (2, 2)
	99 aload_0 (0, 0)
	100 iconst_0 (0, 0)
	101 putfield (0, 0)
	102 org/apache/commons/math3/ode/JacobianMatrices.dirtyParameter:Z (0, 0)
	104 aload_0 (0, 0)
	105 new (0, 0)
	106 java/util/ArrayList (0, 0)
	108 dup (0, 0)
	109 invokespecial (0, 0)
	110 java/util/ArrayList.<init>:()V (0, 0)
	112 putfield (0, 0)
	113 org/apache/commons/math3/ode/JacobianMatrices.jacobianProviders:Ljava/util/List; (0, 0)
	115 aload_0 (0, 0)
	116 aload_0 (0, 0)
	117 getfield (0, 0)
	118 org/apache/commons/math3/ode/JacobianMatrices.stateDim:I (0, 0)
	120 aload_0 (0, 0)
	121 getfield (0, 0)
	122 org/apache/commons/math3/ode/JacobianMatrices.paramDim:I (0, 0)
	124 iadd (0, 0)
	125 aload_0 (0, 0)
	126 getfield (0, 0)
	127 org/apache/commons/math3/ode/JacobianMatrices.stateDim:I (0, 0)
	129 imul (0, 0)
	130 newarray (0, 0)
	131 7 (0, 0)
	132 putfield (0, 0)
	133 org/apache/commons/math3/ode/JacobianMatrices.matricesData:[D (0, 0)
	135 iconst_0 (2, 4)
	136 istore_3 (2, 4)
	137 iload_3 (2, 4)
	138 aload_0 (2, 4)
	139 getfield (2, 4)
	140 org/apache/commons/math3/ode/JacobianMatrices.stateDim:I (2, 4)
	142 if_icmpge (2, 4)
	143 23 (2, 4)
	145 aload_0 (2, 4)
	146 getfield (2, 4)
	147 org/apache/commons/math3/ode/JacobianMatrices.matricesData:[D (2, 4)
	149 iload_3 (2, 4)
	150 aload_0 (2, 4)
	151 getfield (2, 4)
	152 org/apache/commons/math3/ode/JacobianMatrices.stateDim:I (2, 4)
	154 iconst_1 (2, 4)
	155 iadd (2, 4)
	156 imul (2, 4)
	157 dconst_1 (2, 4)
	158 dastore (2, 4)
	159 iinc (2, 4)
	160 #3 (2, 4)
	161 -89 (2, 4)
	162 goto (2, 4)
	163 -25 (2, 4)
	165 return (0, 0)

Method: registerVariationalEquations
	0 aload_0 (0, 1)
	1 getfield (0, 1)
	2 org/apache/commons/math3/ode/JacobianMatrices.jode:Lorg/apache/commons/math3/ode/MainStateJacobianProvider; (0, 1)
	4 instanceof (0, 1)
	5 org/apache/commons/math3/ode/JacobianMatrices$MainStateJacobianWrapper (0, 1)
	7 ifeq (0, 1)
	8 16 (0, 1)
	10 aload_0 (0, 1)
	11 getfield (0, 1)
	12 org/apache/commons/math3/ode/JacobianMatrices.jode:Lorg/apache/commons/math3/ode/MainStateJacobianProvider; (0, 1)
	14 checkcast (0, 1)
	15 org/apache/commons/math3/ode/JacobianMatrices$MainStateJacobianWrapper (0, 1)
	17 invokestatic (0, 1)
	18 org/apache/commons/math3/ode/JacobianMatrices$MainStateJacobianWrapper.access$000:(Lorg/apache/commons/math3/ode/JacobianMatrices$MainStateJacobianWrapper;)Lorg/apache/commons/math3/ode/FirstOrderDifferentialEquations; (0, 1)
	20 goto (0, 1)
	21 7 (0, 1)
	23 aload_0 (0, 1)
	24 getfield (0, 1)
	25 org/apache/commons/math3/ode/JacobianMatrices.jode:Lorg/apache/commons/math3/ode/MainStateJacobianProvider; (0, 1)
	27 astore_2 (0, 1)
	28 aload_1 (1, 1)
	29 invokevirtual (1, 1)
	30 org/apache/commons/math3/ode/ExpandableStatefulODE.getPrimary:()Lorg/apache/commons/math3/ode/FirstOrderDifferentialEquations; (1, 1)
	32 aload_2 (1, 1)
	33 if_acmpeq (1, 1)
	34 11 (1, 1)
	36 new (1, 1)
	37 org/apache/commons/math3/ode/JacobianMatrices$MismatchedEquations (1, 1)
	39 dup (1, 1)
	40 invokespecial (1, 1)
	41 org/apache/commons/math3/ode/JacobianMatrices$MismatchedEquations.<init>:()V (1, 1)
	43 athrow (1, 1)
	44 aload_0 (0, 1)
	45 aload_1 (0, 1)
	46 putfield (0, 1)
	47 org/apache/commons/math3/ode/JacobianMatrices.efode:Lorg/apache/commons/math3/ode/ExpandableStatefulODE; (0, 1)
	49 aload_0 (0, 1)
	50 aload_0 (0, 1)
	51 getfield (0, 1)
	52 org/apache/commons/math3/ode/JacobianMatrices.efode:Lorg/apache/commons/math3/ode/ExpandableStatefulODE; (0, 1)
	54 new (0, 1)
	55 org/apache/commons/math3/ode/JacobianMatrices$JacobiansSecondaryEquations (0, 1)
	57 dup (0, 1)
	58 aload_0 (0, 1)
	59 aconst_null (0, 1)
	60 invokespecial (0, 1)
	61 org/apache/commons/math3/ode/JacobianMatrices$JacobiansSecondaryEquations.<init>:(Lorg/apache/commons/math3/ode/JacobianMatrices;Lorg/apache/commons/math3/ode/JacobianMatrices$1;)V (0, 1)
	63 invokevirtual (0, 1)
	64 org/apache/commons/math3/ode/ExpandableStatefulODE.addSecondaryEquations:(Lorg/apache/commons/math3/ode/SecondaryEquations;)I (0, 1)
	66 putfield (0, 1)
	67 org/apache/commons/math3/ode/JacobianMatrices.index:I (0, 1)
	69 aload_0 (0, 1)
	70 getfield (0, 1)
	71 org/apache/commons/math3/ode/JacobianMatrices.efode:Lorg/apache/commons/math3/ode/ExpandableStatefulODE; (0, 1)
	73 aload_0 (0, 1)
	74 getfield (0, 1)
	75 org/apache/commons/math3/ode/JacobianMatrices.index:I (0, 1)
	77 aload_0 (0, 1)
	78 getfield (0, 1)
	79 org/apache/commons/math3/ode/JacobianMatrices.matricesData:[D (0, 1)
	81 invokevirtual (0, 1)
	82 org/apache/commons/math3/ode/ExpandableStatefulODE.setSecondaryState:(I[D)V (0, 1)
	84 return (0, 1)

Method: addParameterJacobianProvider
	0 aload_0 (0, 0)
	1 getfield (0, 0)
	2 org/apache/commons/math3/ode/JacobianMatrices.jacobianProviders:Ljava/util/List; (0, 0)
	4 aload_1 (0, 0)
	5 invokeinterface (0, 0)
	6 java/util/List.getParameterName:()Ljava/lang/String; (0, 0)
	8 0 (0, 0)
	10 pop (0, 0)
	11 return (0, 0)

Method: setParameterizedODE
	0 aload_0 (0, 0)
	1 aload_1 (0, 0)
	2 putfield (0, 0)
	3 org/apache/commons/math3/ode/JacobianMatrices.pode:Lorg/apache/commons/math3/ode/ParameterizedODE; (0, 0)
	5 aload_0 (0, 0)
	6 iconst_1 (0, 0)
	7 putfield (0, 0)
	8 org/apache/commons/math3/ode/JacobianMatrices.dirtyParameter:Z (0, 0)
	10 return (0, 0)

Method: setParameterStep
	0 aload_0 (1, 4)
	1 getfield (1, 4)
	2 org/apache/commons/math3/ode/JacobianMatrices.selectedParameters:[Lorg/apache/commons/math3/ode/ParameterConfiguration; (1, 4)
	4 astore (1, 4)
	5 #4 (1, 4)
	6 aload (1, 4)
	7 #4 (1, 4)
	8 arraylength (1, 4)
	9 istore (1, 4)
	10 #5 (1, 4)
	11 iconst_0 (1, 4)
	12 istore (1, 4)
	13 #6 (1, 4)
	14 iload (1, 4)
	15 #6 (1, 4)
	16 iload (1, 4)
	17 #5 (1, 4)
	18 if_icmpge (1, 4)
	19 40 (1, 4)
	21 aload (1, 4)
	22 #4 (1, 4)
	23 iload (1, 4)
	24 #6 (1, 4)
	25 aaload (1, 4)
	26 astore (1, 4)
	27 #7 (1, 4)
	28 aload_1 (2, 1)
	29 aload (2, 1)
	30 #7 (2, 1)
	31 invokevirtual (2, 1)
	32 org/apache/commons/math3/ode/ParameterConfiguration.getParameterName:()Ljava/lang/String; (2, 1)
	34 invokevirtual (2, 1)
	35 java/lang/String.equals:(Ljava/lang/Object;)Z (2, 1)
	37 ifeq (2, 1)
	38 15 (2, 1)
	40 aload (2, 1)
	41 #7 (2, 1)
	42 dload_2 (2, 1)
	43 invokevirtual (2, 1)
	44 org/apache/commons/math3/ode/ParameterConfiguration.setHP:(D)V (2, 1)
	46 aload_0 (2, 1)
	47 iconst_1 (2, 1)
	48 putfield (2, 1)
	49 org/apache/commons/math3/ode/JacobianMatrices.dirtyParameter:Z (2, 1)
	51 return (2, 1)
	52 iinc (2, 1)
	53 #6 (2, 1)
	54 -89 (2, 1)
	55 goto (2, 1)
	56 -41 (2, 1)
	58 new (1, 4)
	59 org/apache/commons/math3/ode/UnknownParameterException (1, 4)
	61 dup (1, 4)
	62 aload_1 (1, 4)
	63 invokespecial (1, 4)
	64 org/apache/commons/math3/ode/UnknownParameterException.<init>:(Ljava/lang/String;)V (1, 4)
	66 athrow (1, 4)

Method: setInitialMainStateJacobian
	0 aload_0 (0, 0)
	1 aload_0 (0, 0)
	2 getfield (0, 0)
	3 org/apache/commons/math3/ode/JacobianMatrices.stateDim:I (0, 0)
	5 aload_1 (0, 0)
	6 invokespecial (0, 0)
	7 org/apache/commons/math3/ode/JacobianMatrices.checkDimension:(ILjava/lang/Object;)V (0, 0)
	9 aload_0 (0, 0)
	10 aload_0 (0, 0)
	11 getfield (0, 0)
	12 org/apache/commons/math3/ode/JacobianMatrices.stateDim:I (0, 0)
	14 aload_1 (0, 0)
	15 iconst_0 (0, 0)
	16 aaload (0, 0)
	17 invokespecial (0, 0)
	18 org/apache/commons/math3/ode/JacobianMatrices.checkDimension:(ILjava/lang/Object;)V (0, 0)
	20 iconst_0 (0, 0)
	21 istore_2 (0, 0)
	22 aload_1 (1, 4)
	23 astore_3 (1, 4)
	24 aload_3 (1, 4)
	25 arraylength (1, 4)
	26 istore (1, 4)
	27 #4 (1, 4)
	28 iconst_0 (1, 4)
	29 istore (1, 4)
	30 #5 (1, 4)
	31 iload (1, 4)
	32 #5 (1, 4)
	33 iload (1, 4)
	34 #4 (1, 4)
	35 if_icmpge (1, 4)
	36 37 (1, 4)
	38 aload_3 (1, 4)
	39 iload (1, 4)
	40 #5 (1, 4)
	41 aaload (1, 4)
	42 astore (1, 4)
	43 #6 (1, 4)
	44 aload (1, 4)
	45 #6 (1, 4)
	46 iconst_0 (1, 4)
	47 aload_0 (1, 4)
	48 getfield (1, 4)
	49 org/apache/commons/math3/ode/JacobianMatrices.matricesData:[D (1, 4)
	51 iload_2 (1, 4)
	52 aload_0 (1, 4)
	53 getfield (1, 4)
	54 org/apache/commons/math3/ode/JacobianMatrices.stateDim:I (1, 4)
	56 invokestatic (1, 4)
	57 java/lang/System.arraycopy:(Ljava/lang/Object;ILjava/lang/Object;II)V (1, 4)
	59 iload_2 (1, 4)
	60 aload_0 (1, 4)
	61 getfield (1, 4)
	62 org/apache/commons/math3/ode/JacobianMatrices.stateDim:I (1, 4)
	64 iadd (1, 4)
	65 istore_2 (1, 4)
	66 iinc (1, 4)
	67 #5 (1, 4)
	68 -89 (1, 4)
	69 goto (1, 4)
	70 -38 (1, 4)
	72 aload_0 (1, 1)
	73 getfield (1, 1)
	74 org/apache/commons/math3/ode/JacobianMatrices.efode:Lorg/apache/commons/math3/ode/ExpandableStatefulODE; (1, 1)
	76 ifnull (1, 1)
	77 18 (1, 1)
	79 aload_0 (1, 1)
	80 getfield (1, 1)
	81 org/apache/commons/math3/ode/JacobianMatrices.efode:Lorg/apache/commons/math3/ode/ExpandableStatefulODE; (1, 1)
	83 aload_0 (1, 1)
	84 getfield (1, 1)
	85 org/apache/commons/math3/ode/JacobianMatrices.index:I (1, 1)
	87 aload_0 (1, 1)
	88 getfield (1, 1)
	89 org/apache/commons/math3/ode/JacobianMatrices.matricesData:[D (1, 1)
	91 invokevirtual (1, 1)
	92 org/apache/commons/math3/ode/ExpandableStatefulODE.setSecondaryState:(I[D)V (1, 1)
	94 return (0, 0)

Method: setInitialParameterJacobian
	0 aload_0 (0, 0)
	1 aload_0 (0, 0)
	2 getfield (0, 0)
	3 org/apache/commons/math3/ode/JacobianMatrices.stateDim:I (0, 0)
	5 aload_2 (0, 0)
	6 invokespecial (0, 0)
	7 org/apache/commons/math3/ode/JacobianMatrices.checkDimension:(ILjava/lang/Object;)V (0, 0)
	9 aload_0 (0, 0)
	10 getfield (0, 0)
	11 org/apache/commons/math3/ode/JacobianMatrices.stateDim:I (0, 0)
	13 aload_0 (0, 0)
	14 getfield (0, 0)
	15 org/apache/commons/math3/ode/JacobianMatrices.stateDim:I (0, 0)
	17 imul (0, 0)
	18 istore_3 (0, 0)
	19 aload_0 (1, 4)
	20 getfield (1, 4)
	21 org/apache/commons/math3/ode/JacobianMatrices.selectedParameters:[Lorg/apache/commons/math3/ode/ParameterConfiguration; (1, 4)
	23 astore (1, 4)
	24 #4 (1, 4)
	25 aload (1, 4)
	26 #4 (1, 4)
	27 arraylength (1, 4)
	28 istore (1, 4)
	29 #5 (1, 4)
	30 iconst_0 (1, 4)
	31 istore (1, 4)
	32 #6 (1, 4)
	33 iload (1, 4)
	34 #6 (1, 4)
	35 iload (1, 4)
	36 #5 (1, 4)
	37 if_icmpge (1, 4)
	38 72 (1, 4)
	40 aload (1, 4)
	41 #4 (1, 4)
	42 iload (1, 4)
	43 #6 (1, 4)
	44 aaload (1, 4)
	45 astore (1, 4)
	46 #7 (1, 4)
	47 aload_1 (2, 1)
	48 aload (2, 1)
	49 #7 (2, 1)
	50 invokevirtual (2, 1)
	51 org/apache/commons/math3/ode/ParameterConfiguration.getParameterName:()Ljava/lang/String; (2, 1)
	53 invokevirtual (2, 1)
	54 java/lang/String.equals:(Ljava/lang/Object;)Z (2, 1)
	56 ifeq (2, 1)
	57 40 (2, 1)
	59 aload_2 (2, 1)
	60 iconst_0 (2, 1)
	61 aload_0 (2, 1)
	62 getfield (2, 1)
	63 org/apache/commons/math3/ode/JacobianMatrices.matricesData:[D (2, 1)
	65 iload_3 (2, 1)
	66 aload_0 (2, 1)
	67 getfield (2, 1)
	68 org/apache/commons/math3/ode/JacobianMatrices.stateDim:I (2, 1)
	70 invokestatic (2, 1)
	71 java/lang/System.arraycopy:(Ljava/lang/Object;ILjava/lang/Object;II)V (2, 1)
	73 aload_0 (3, 1)
	74 getfield (3, 1)
	75 org/apache/commons/math3/ode/JacobianMatrices.efode:Lorg/apache/commons/math3/ode/ExpandableStatefulODE; (3, 1)
	77 ifnull (3, 1)
	78 18 (3, 1)
	80 aload_0 (3, 1)
	81 getfield (3, 1)
	82 org/apache/commons/math3/ode/JacobianMatrices.efode:Lorg/apache/commons/math3/ode/ExpandableStatefulODE; (3, 1)
	84 aload_0 (3, 1)
	85 getfield (3, 1)
	86 org/apache/commons/math3/ode/JacobianMatrices.index:I (3, 1)
	88 aload_0 (3, 1)
	89 getfield (3, 1)
	90 org/apache/commons/math3/ode/JacobianMatrices.matricesData:[D (3, 1)
	92 invokevirtual (3, 1)
	93 org/apache/commons/math3/ode/ExpandableStatefulODE.setSecondaryState:(I[D)V (3, 1)
	95 return (2, 1)
	96 iload_3 (1, 4)
	97 aload_0 (1, 4)
	98 getfield (1, 4)
	99 org/apache/commons/math3/ode/JacobianMatrices.stateDim:I (1, 4)
	101 iadd (1, 4)
	102 istore_3 (1, 4)
	103 iinc (1, 4)
	104 #6 (1, 4)
	105 -89 (1, 4)
	106 goto (1, 4)
	107 -73 (1, 4)
	109 new (0, 0)
	110 org/apache/commons/math3/ode/UnknownParameterException (0, 0)
	112 dup (0, 0)
	113 aload_1 (0, 0)
	114 invokespecial (0, 0)
	115 org/apache/commons/math3/ode/UnknownParameterException.<init>:(Ljava/lang/String;)V (0, 0)
	117 athrow (0, 0)

Method: getCurrentMainSetJacobian
	0 aload_0 (0, 0)
	1 getfield (0, 0)
	2 org/apache/commons/math3/ode/JacobianMatrices.efode:Lorg/apache/commons/math3/ode/ExpandableStatefulODE; (0, 0)
	4 aload_0 (0, 0)
	5 getfield (0, 0)
	6 org/apache/commons/math3/ode/JacobianMatrices.index:I (0, 0)
	8 invokevirtual (0, 0)
	9 org/apache/commons/math3/ode/ExpandableStatefulODE.getSecondaryState:(I)[D (0, 0)
	11 astore_2 (0, 0)
	12 iconst_0 (0, 0)
	13 istore_3 (0, 0)
	14 iconst_0 (1, 4)
	15 istore (1, 4)
	16 #4 (1, 4)
	17 iload (1, 4)
	18 #4 (1, 4)
	19 aload_0 (1, 4)
	20 getfield (1, 4)
	21 org/apache/commons/math3/ode/JacobianMatrices.stateDim:I (1, 4)
	23 if_icmpge (1, 4)
	24 30 (1, 4)
	26 aload_2 (1, 4)
	27 iload_3 (1, 4)
	28 aload_1 (1, 4)
	29 iload (1, 4)
	30 #4 (1, 4)
	31 aaload (1, 4)
	32 iconst_0 (1, 4)
	33 aload_0 (1, 4)
	34 getfield (1, 4)
	35 org/apache/commons/math3/ode/JacobianMatrices.stateDim:I (1, 4)
	37 invokestatic (1, 4)
	38 java/lang/System.arraycopy:(Ljava/lang/Object;ILjava/lang/Object;II)V (1, 4)
	40 iload_3 (1, 4)
	41 aload_0 (1, 4)
	42 getfield (1, 4)
	43 org/apache/commons/math3/ode/JacobianMatrices.stateDim:I (1, 4)
	45 iadd (1, 4)
	46 istore_3 (1, 4)
	47 iinc (1, 4)
	48 #4 (1, 4)
	49 -89 (1, 4)
	50 goto (1, 4)
	51 -33 (1, 4)
	53 return (0, 0)

Method: getCurrentParameterJacobian
	0 aload_0 (0, 0)
	1 getfield (0, 0)
	2 org/apache/commons/math3/ode/JacobianMatrices.efode:Lorg/apache/commons/math3/ode/ExpandableStatefulODE; (0, 0)
	4 aload_0 (0, 0)
	5 getfield (0, 0)
	6 org/apache/commons/math3/ode/JacobianMatrices.index:I (0, 0)
	8 invokevirtual (0, 0)
	9 org/apache/commons/math3/ode/ExpandableStatefulODE.getSecondaryState:(I)[D (0, 0)
	11 astore_3 (0, 0)
	12 aload_0 (0, 0)
	13 getfield (0, 0)
	14 org/apache/commons/math3/ode/JacobianMatrices.stateDim:I (0, 0)
	16 aload_0 (0, 0)
	17 getfield (0, 0)
	18 org/apache/commons/math3/ode/JacobianMatrices.stateDim:I (0, 0)
	20 imul (0, 0)
	21 istore (0, 0)
	22 #4 (0, 0)
	23 aload_0 (1, 4)
	24 getfield (1, 4)
	25 org/apache/commons/math3/ode/JacobianMatrices.selectedParameters:[Lorg/apache/commons/math3/ode/ParameterConfiguration; (1, 4)
	27 astore (1, 4)
	28 #5 (1, 4)
	29 aload (1, 4)
	30 #5 (1, 4)
	31 arraylength (1, 4)
	32 istore (1, 4)
	33 #6 (1, 4)
	34 iconst_0 (1, 4)
	35 istore (1, 4)
	36 #7 (1, 4)
	37 iload (1, 4)
	38 #7 (1, 4)
	39 iload (1, 4)
	40 #6 (1, 4)
	41 if_icmpge (1, 4)
	42 50 (1, 4)
	44 aload (1, 4)
	45 #5 (1, 4)
	46 iload (1, 4)
	47 #7 (1, 4)
	48 aaload (1, 4)
	49 astore (1, 4)
	50 #8 (1, 4)
	51 aload (2, 1)
	52 #8 (2, 1)
	53 invokevirtual (2, 1)
	54 org/apache/commons/math3/ode/ParameterConfiguration.getParameterName:()Ljava/lang/String; (2, 1)
	56 aload_1 (2, 1)
	57 invokevirtual (2, 1)
	58 java/lang/String.equals:(Ljava/lang/Object;)Z (2, 1)
	60 ifeq (2, 1)
	61 16 (2, 1)
	63 aload_3 (2, 1)
	64 iload (2, 1)
	65 #4 (2, 1)
	66 aload_2 (2, 1)
	67 iconst_0 (2, 1)
	68 aload_0 (2, 1)
	69 getfield (2, 1)
	70 org/apache/commons/math3/ode/JacobianMatrices.stateDim:I (2, 1)
	72 invokestatic (2, 1)
	73 java/lang/System.arraycopy:(Ljava/lang/Object;ILjava/lang/Object;II)V (2, 1)
	75 return (2, 1)
	76 iload (1, 4)
	77 #4 (1, 4)
	78 aload_0 (1, 4)
	79 getfield (1, 4)
	80 org/apache/commons/math3/ode/JacobianMatrices.stateDim:I (1, 4)
	82 iadd (1, 4)
	83 istore (1, 4)
	84 #4 (1, 4)
	85 iinc (1, 4)
	86 #7 (1, 4)
	87 -89 (1, 4)
	88 goto (1, 4)
	89 -51 (1, 4)
	91 return (0, 0)

Method: checkDimension
	0 aload_2 (0, 0)
	1 ifnonnull (0, 0)
	2 7 (0, 0)
	4 iconst_0 (0, 0)
	5 goto (0, 0)
	6 7 (0, 0)
	8 aload_2 (0, 0)
	9 invokestatic (0, 0)
	10 java/lang/reflect/Array.getLength:(Ljava/lang/Object;)I (0, 0)
	12 istore_3 (0, 0)
	13 iload_3 (1, 1)
	14 iload_1 (1, 1)
	15 if_icmpeq (1, 1)
	16 13 (1, 1)
	18 new (1, 1)
	19 org/apache/commons/math3/exception/DimensionMismatchException (1, 1)
	21 dup (1, 1)
	22 iload_3 (1, 1)
	23 iload_1 (1, 1)
	24 invokespecial (1, 1)
	25 org/apache/commons/math3/exception/DimensionMismatchException.<init>:(II)V (1, 1)
	27 athrow (1, 1)
	28 return (0, 0)

Method: access$200
	0 aload_0 (0, 0)
	1 getfield (0, 0)
	2 org/apache/commons/math3/ode/JacobianMatrices.stateDim:I (0, 0)
	4 ireturn (0, 0)

Method: access$300
	0 aload_0 (0, 0)
	1 getfield (0, 0)
	2 org/apache/commons/math3/ode/JacobianMatrices.paramDim:I (0, 0)
	4 ireturn (0, 0)

Method: access$400
	0 aload_0 (0, 0)
	1 getfield (0, 0)
	2 org/apache/commons/math3/ode/JacobianMatrices.dirtyParameter:Z (0, 0)
	4 ireturn (0, 0)

Method: access$500
	0 aload_0 (0, 0)
	1 getfield (0, 0)
	2 org/apache/commons/math3/ode/JacobianMatrices.jode:Lorg/apache/commons/math3/ode/MainStateJacobianProvider; (0, 0)
	4 areturn (0, 0)

Method: access$600
	0 aload_0 (0, 0)
	1 getfield (0, 0)
	2 org/apache/commons/math3/ode/JacobianMatrices.pode:Lorg/apache/commons/math3/ode/ParameterizedODE; (0, 0)
	4 areturn (0, 0)

Method: access$700
	0 aload_0 (0, 0)
	1 getfield (0, 0)
	2 org/apache/commons/math3/ode/JacobianMatrices.selectedParameters:[Lorg/apache/commons/math3/ode/ParameterConfiguration; (0, 0)
	4 areturn (0, 0)

Method: access$800
	0 aload_0 (0, 0)
	1 getfield (0, 0)
	2 org/apache/commons/math3/ode/JacobianMatrices.jacobianProviders:Ljava/util/List; (0, 0)
	4 areturn (0, 0)

Method: access$402
	0 aload_0 (0, 0)
	1 iload_1 (0, 0)
	2 dup_x1 (0, 0)
	3 putfield (0, 0)
	4 org/apache/commons/math3/ode/JacobianMatrices.dirtyParameter:Z (0, 0)
	6 ireturn (0, 0)

