Method: <init>
	0 aload_0 (0, 0)
	1 invokespecial (0, 0)
	4 aload_0 (0, 0)
	5 aconst_null (0, 0)
	6 putfield (0, 0)
	9 aload_0 (0, 0)
	10 iconst_m1 (0, 0)
	11 putfield (0, 0)
	14 aload_0 (0, 0)
	15 aload_1 (0, 0)
	16 putfield (0, 0)
	19 aload_0 (0, 0)
	20 aconst_null (0, 0)
	21 putfield (0, 0)
	24 aload_0 (0, 0)
	25 aload_1 (0, 0)
	26 invokeinterface (0, 0)
	31 putfield (0, 0)
	34 aload_2 (1, 1)
	35 ifnonnull (1, 1)
	38 aload_0 (1, 1)
	39 aconst_null (1, 1)
	40 putfield (1, 1)
	43 aload_0 (1, 1)
	44 iconst_0 (1, 1)
	45 putfield (1, 1)
	48 goto (1, 1)
	51 aload_0 (1, 2)
	52 aload_2 (1, 2)
	53 arraylength (1, 2)
	54 anewarray (1, 2)
	57 putfield (1, 2)
	60 iconst_0 (2, 4)
	61 istore_3 (2, 4)
	62 iload_3 (2, 4)
	63 aload_2 (2, 4)
	64 arraylength (2, 4)
	65 if_icmpge (2, 4)
	68 aload_0 (2, 4)
	69 getfield (2, 4)
	72 iload_3 (2, 4)
	73 new (2, 4)
	76 dup (2, 4)
	77 aload_2 (2, 4)
	78 iload_3 (2, 4)
	79 aaload (2, 4)
	80 ldc2_w (2, 4)
	83 invokespecial (2, 4)
	86 aastore (2, 4)
	87 iinc (2, 4)
	90 goto (2, 4)
	93 aload_0 (1, 2)
	94 aload_2 (1, 2)
	95 arraylength (1, 2)
	96 putfield (1, 2)
	99 aload_0 (0, 1)
	100 iconst_0 (0, 1)
	101 putfield (0, 1)
	104 aload_0 (0, 1)
	105 new (0, 1)
	108 dup (0, 1)
	109 invokespecial (0, 1)
	112 putfield (0, 1)
	115 aload_0 (0, 1)
	116 aload_0 (0, 1)
	117 getfield (0, 1)
	120 aload_0 (0, 1)
	121 getfield (0, 1)
	124 iadd (0, 1)
	125 aload_0 (0, 1)
	126 getfield (0, 1)
	129 imul (0, 1)
	130 newarray (0, 1)
	132 putfield (0, 1)
	135 iconst_0 (1, 4)
	136 istore_3 (1, 4)
	137 iload_3 (1, 4)
	138 aload_0 (1, 4)
	139 getfield (1, 4)
	142 if_icmpge (1, 4)
	145 aload_0 (1, 4)
	146 getfield (1, 4)
	149 iload_3 (1, 4)
	150 aload_0 (1, 4)
	151 getfield (1, 4)
	154 iconst_1 (1, 4)
	155 iadd (1, 4)
	156 imul (1, 4)
	157 dconst_1 (1, 4)
	158 dastore (1, 4)
	159 iinc (1, 4)
	162 goto (1, 4)
	165 return (0, 0)

Method: registerVariationalEquations
	0 aload_0 (0, 1)
	1 getfield (0, 1)
	4 instanceof (0, 1)
	7 ifeq (0, 1)
	10 aload_0 (0, 1)
	11 getfield (0, 1)
	14 checkcast (0, 1)
	17 invokestatic (0, 1)
	20 goto (0, 1)
	23 aload_0 (0, 1)
	24 getfield (0, 1)
	27 astore_2 (0, 1)
	28 aload_1 (1, 1)
	29 invokevirtual (1, 1)
	32 aload_2 (1, 1)
	33 if_acmpeq (1, 1)
	36 new (1, 1)
	39 dup (1, 1)
	40 invokespecial (1, 1)
	43 athrow (1, 1)
	44 aload_0 (0, 1)
	45 aload_1 (0, 1)
	46 putfield (0, 1)
	49 aload_0 (0, 1)
	50 aload_0 (0, 1)
	51 getfield (0, 1)
	54 new (0, 1)
	57 dup (0, 1)
	58 aload_0 (0, 1)
	59 aconst_null (0, 1)
	60 invokespecial (0, 1)
	63 invokevirtual (0, 1)
	66 putfield (0, 1)
	69 aload_0 (0, 1)
	70 getfield (0, 1)
	73 aload_0 (0, 1)
	74 getfield (0, 1)
	77 aload_0 (0, 1)
	78 getfield (0, 1)
	81 invokevirtual (0, 1)
	84 return (0, 0)

Method: addParameterJacobianProvider
	0 aload_0 (0, 0)
	1 getfield (0, 0)
	4 aload_1 (0, 0)
	5 invokeinterface (0, 0)
	10 pop (0, 0)
	11 return (0, 0)

Method: setParameterizedODE
	0 aload_0 (0, 0)
	1 aload_1 (0, 0)
	2 putfield (0, 0)
	5 aload_0 (0, 0)
	6 iconst_1 (0, 0)
	7 putfield (0, 0)
	10 return (0, 0)

Method: setParameterStep
	0 aload_0 (1, 4)
	1 getfield (1, 4)
	4 astore (1, 4)
	6 aload (1, 4)
	8 arraylength (1, 4)
	9 istore (1, 4)
	11 iconst_0 (1, 4)
	12 istore (1, 4)
	14 iload (1, 4)
	16 iload (1, 4)
	18 if_icmpge (1, 4)
	21 aload (1, 4)
	23 iload (1, 4)
	25 aaload (1, 4)
	26 astore (1, 4)
	28 aload_1 (2, 1)
	29 aload (2, 1)
	31 invokevirtual (2, 1)
	34 invokevirtual (2, 1)
	37 ifeq (2, 1)
	40 aload (2, 1)
	42 dload_2 (2, 1)
	43 invokevirtual (2, 1)
	46 aload_0 (2, 1)
	47 iconst_1 (2, 1)
	48 putfield (2, 1)
	51 return (2, 1)
	52 iinc (2, 1)
	55 goto (2, 1)
	58 new (1, 4)
	61 dup (1, 4)
	62 aload_1 (1, 4)
	63 invokespecial (1, 4)
	66 athrow (1, 4)

Method: setInitialMainStateJacobian
	0 aload_0 (0, 0)
	1 aload_0 (0, 0)
	2 getfield (0, 0)
	5 aload_1 (0, 0)
	6 invokespecial (0, 0)
	9 aload_0 (0, 0)
	10 aload_0 (0, 0)
	11 getfield (0, 0)
	14 aload_1 (0, 0)
	15 iconst_0 (0, 0)
	16 aaload (0, 0)
	17 invokespecial (0, 0)
	20 iconst_0 (0, 0)
	21 istore_2 (0, 0)
	22 aload_1 (1, 4)
	23 astore_3 (1, 4)
	24 aload_3 (1, 4)
	25 arraylength (1, 4)
	26 istore (1, 4)
	28 iconst_0 (1, 4)
	29 istore (1, 4)
	31 iload (1, 4)
	33 iload (1, 4)
	35 if_icmpge (1, 4)
	38 aload_3 (1, 4)
	39 iload (1, 4)
	41 aaload (1, 4)
	42 astore (1, 4)
	44 aload (1, 4)
	46 iconst_0 (1, 4)
	47 aload_0 (1, 4)
	48 getfield (1, 4)
	51 iload_2 (1, 4)
	52 aload_0 (1, 4)
	53 getfield (1, 4)
	56 invokestatic (1, 4)
	59 iload_2 (1, 4)
	60 aload_0 (1, 4)
	61 getfield (1, 4)
	64 iadd (1, 4)
	65 istore_2 (1, 4)
	66 iinc (1, 4)
	69 goto (1, 4)
	72 aload_0 (1, 1)
	73 getfield (1, 1)
	76 ifnull (1, 1)
	79 aload_0 (1, 1)
	80 getfield (1, 1)
	83 aload_0 (1, 1)
	84 getfield (1, 1)
	87 aload_0 (1, 1)
	88 getfield (1, 1)
	91 invokevirtual (1, 1)
	94 return (0, 0)

Method: setInitialParameterJacobian
	0 aload_0 (0, 0)
	1 aload_0 (0, 0)
	2 getfield (0, 0)
	5 aload_2 (0, 0)
	6 invokespecial (0, 0)
	9 aload_0 (0, 0)
	10 getfield (0, 0)
	13 aload_0 (0, 0)
	14 getfield (0, 0)
	17 imul (0, 0)
	18 istore_3 (0, 0)
	19 aload_0 (1, 4)
	20 getfield (1, 4)
	23 astore (1, 4)
	25 aload (1, 4)
	27 arraylength (1, 4)
	28 istore (1, 4)
	30 iconst_0 (1, 4)
	31 istore (1, 4)
	33 iload (1, 4)
	35 iload (1, 4)
	37 if_icmpge (1, 4)
	40 aload (1, 4)
	42 iload (1, 4)
	44 aaload (1, 4)
	45 astore (1, 4)
	47 aload_1 (2, 1)
	48 aload (2, 1)
	50 invokevirtual (2, 1)
	53 invokevirtual (2, 1)
	56 ifeq (2, 1)
	59 aload_2 (2, 1)
	60 iconst_0 (2, 1)
	61 aload_0 (2, 1)
	62 getfield (2, 1)
	65 iload_3 (2, 1)
	66 aload_0 (2, 1)
	67 getfield (2, 1)
	70 invokestatic (2, 1)
	73 aload_0 (3, 1)
	74 getfield (3, 1)
	77 ifnull (3, 1)
	80 aload_0 (3, 1)
	81 getfield (3, 1)
	84 aload_0 (3, 1)
	85 getfield (3, 1)
	88 aload_0 (3, 1)
	89 getfield (3, 1)
	92 invokevirtual (3, 1)
	95 return (2, 1)
	96 iload_3 (1, 4)
	97 aload_0 (1, 4)
	98 getfield (1, 4)
	101 iadd (1, 4)
	102 istore_3 (1, 4)
	103 iinc (1, 4)
	106 goto (1, 4)
	109 new (0, 0)
	112 dup (0, 0)
	113 aload_1 (0, 0)
	114 invokespecial (0, 0)
	117 athrow (0, 0)

Method: getCurrentMainSetJacobian
	0 aload_0 (0, 0)
	1 getfield (0, 0)
	4 aload_0 (0, 0)
	5 getfield (0, 0)
	8 invokevirtual (0, 0)
	11 astore_2 (0, 0)
	12 iconst_0 (0, 0)
	13 istore_3 (0, 0)
	14 iconst_0 (1, 4)
	15 istore (1, 4)
	17 iload (1, 4)
	19 aload_0 (1, 4)
	20 getfield (1, 4)
	23 if_icmpge (1, 4)
	26 aload_2 (1, 4)
	27 iload_3 (1, 4)
	28 aload_1 (1, 4)
	29 iload (1, 4)
	31 aaload (1, 4)
	32 iconst_0 (1, 4)
	33 aload_0 (1, 4)
	34 getfield (1, 4)
	37 invokestatic (1, 4)
	40 iload_3 (1, 4)
	41 aload_0 (1, 4)
	42 getfield (1, 4)
	45 iadd (1, 4)
	46 istore_3 (1, 4)
	47 iinc (1, 4)
	50 goto (1, 4)
	53 return (0, 0)

Method: getCurrentParameterJacobian
	0 aload_0 (0, 0)
	1 getfield (0, 0)
	4 aload_0 (0, 0)
	5 getfield (0, 0)
	8 invokevirtual (0, 0)
	11 astore_3 (0, 0)
	12 aload_0 (0, 0)
	13 getfield (0, 0)
	16 aload_0 (0, 0)
	17 getfield (0, 0)
	20 imul (0, 0)
	21 istore (0, 0)
	23 aload_0 (1, 4)
	24 getfield (1, 4)
	27 astore (1, 4)
	29 aload (1, 4)
	31 arraylength (1, 4)
	32 istore (1, 4)
	34 iconst_0 (1, 4)
	35 istore (1, 4)
	37 iload (1, 4)
	39 iload (1, 4)
	41 if_icmpge (1, 4)
	44 aload (1, 4)
	46 iload (1, 4)
	48 aaload (1, 4)
	49 astore (1, 4)
	51 aload (2, 1)
	53 invokevirtual (2, 1)
	56 aload_1 (2, 1)
	57 invokevirtual (2, 1)
	60 ifeq (2, 1)
	63 aload_3 (2, 1)
	64 iload (2, 1)
	66 aload_2 (2, 1)
	67 iconst_0 (2, 1)
	68 aload_0 (2, 1)
	69 getfield (2, 1)
	72 invokestatic (2, 1)
	75 return (2, 1)
	76 iload (1, 4)
	78 aload_0 (1, 4)
	79 getfield (1, 4)
	82 iadd (1, 4)
	83 istore (1, 4)
	85 iinc (1, 4)
	88 goto (1, 4)
	91 return (0, 0)

Method: checkDimension
	0 aload_2 (0, 0)
	1 ifnonnull (0, 0)
	4 iconst_0 (0, 0)
	5 goto (0, 0)
	8 aload_2 (0, 0)
	9 invokestatic (0, 0)
	12 istore_3 (0, 0)
	13 iload_3 (1, 1)
	14 iload_1 (1, 1)
	15 if_icmpeq (1, 1)
	18 new (1, 1)
	21 dup (1, 1)
	22 iload_3 (1, 1)
	23 iload_1 (1, 1)
	24 invokespecial (1, 1)
	27 athrow (1, 1)
	28 return (0, 0)

Method: access$200
	0 aload_0 (0, 0)
	1 getfield (0, 0)
	4 ireturn (0, 0)

Method: access$300
	0 aload_0 (0, 0)
	1 getfield (0, 0)
	4 ireturn (0, 0)

Method: access$400
	0 aload_0 (0, 0)
	1 getfield (0, 0)
	4 ireturn (0, 0)

Method: access$500
	0 aload_0 (0, 0)
	1 getfield (0, 0)
	4 areturn (0, 0)

Method: access$600
	0 aload_0 (0, 0)
	1 getfield (0, 0)
	4 areturn (0, 0)

Method: access$700
	0 aload_0 (0, 0)
	1 getfield (0, 0)
	4 areturn (0, 0)

Method: access$800
	0 aload_0 (0, 0)
	1 getfield (0, 0)
	4 areturn (0, 0)

Method: access$402
	0 aload_0 (0, 0)
	1 iload_1 (0, 0)
	2 dup_x1 (0, 0)
	3 putfield (0, 0)
	6 ireturn (0, 0)

