Method: <init>
	0 aload_0 (0, 0)
	1 invokespecial (0, 0)
	2 java/lang/Object.<init>:()V (0, 0)
	4 aload_0 (0, 0)
	5 aload_1 (0, 0)
	6 putfield (0, 0)
	7 org/apache/commons/math3/ode/JacobianMatrices$MainStateJacobianWrapper.ode:Lorg/apache/commons/math3/ode/FirstOrderDifferentialEquations; (0, 0)
	9 aload_0 (0, 0)
	10 aload_2 (0, 0)
	11 invokevirtual (0, 0)
	12 [D.clone:()Ljava/lang/Object; (0, 0)
	14 checkcast (0, 0)
	15 [D (0, 0)
	17 putfield (0, 0)
	18 org/apache/commons/math3/ode/JacobianMatrices$MainStateJacobianWrapper.hY:[D (0, 0)
	20 aload_2 (2, 1)
	21 arraylength (2, 1)
	22 aload_1 (2, 1)
	23 invokeinterface (2, 1)
	24 org/apache/commons/math3/ode/FirstOrderDifferentialEquations.org/apache/commons/math3/exception/DimensionMismatchException (2, 1)
	26 0 (2, 1)
	28 if_icmpeq (2, 1)
	29 19 (2, 1)
	31 new (2, 1)
	32 org/apache/commons/math3/exception/DimensionMismatchException (2, 1)
	34 dup (2, 1)
	35 aload_1 (2, 1)
	36 invokeinterface (2, 1)
	37 org/apache/commons/math3/ode/FirstOrderDifferentialEquations.org/apache/commons/math3/exception/DimensionMismatchException (2, 1)
	39 0 (2, 1)
	41 aload_2 (2, 1)
	42 arraylength (2, 1)
	43 invokespecial (2, 1)
	44 org/apache/commons/math3/exception/DimensionMismatchException.<init>:(II)V (2, 1)
	46 athrow (2, 1)
	47 return (0, 0)

Method: getDimension
	0 aload_0 (0, 0)
	1 getfield (0, 0)
	2 org/apache/commons/math3/ode/JacobianMatrices$MainStateJacobianWrapper.ode:Lorg/apache/commons/math3/ode/FirstOrderDifferentialEquations; (0, 0)
	4 invokeinterface (0, 0)
	5 org/apache/commons/math3/ode/FirstOrderDifferentialEquations.org/apache/commons/math3/exception/DimensionMismatchException (0, 0)
	7 0 (0, 0)
	9 ireturn (0, 0)

Method: computeDerivatives
	0 aload_0 (0, 0)
	1 getfield (0, 0)
	2 org/apache/commons/math3/ode/JacobianMatrices$MainStateJacobianWrapper.ode:Lorg/apache/commons/math3/ode/FirstOrderDifferentialEquations; (0, 0)
	4 dload_1 (0, 0)
	5 aload_3 (0, 0)
	6 aload (0, 0)
	7 #4 (0, 0)
	8 invokeinterface (0, 0)
	9 org/apache/commons/math3/ode/FirstOrderDifferentialEquations.org/apache/commons/math3/ode/JacobianMatrices (0, 0)
	11 0 (0, 0)
	13 return (0, 0)

Method: computeMainStateJacobian
	0 aload_0 (0, 0)
	1 getfield (0, 0)
	2 org/apache/commons/math3/ode/JacobianMatrices$MainStateJacobianWrapper.ode:Lorg/apache/commons/math3/ode/FirstOrderDifferentialEquations; (0, 0)
	4 invokeinterface (0, 0)
	5 org/apache/commons/math3/ode/FirstOrderDifferentialEquations.org/apache/commons/math3/exception/DimensionMismatchException (0, 0)
	7 0 (0, 0)
	9 istore (0, 0)
	10 #6 (0, 0)
	11 iload (0, 0)
	12 #6 (0, 0)
	13 newarray (0, 0)
	14 7 (0, 0)
	15 astore (0, 0)
	16 #7 (0, 0)
	17 iconst_0 (1, 4)
	18 istore (1, 4)
	19 #8 (1, 4)
	20 iload (1, 4)
	21 #8 (1, 4)
	22 iload (1, 4)
	23 #6 (1, 4)
	24 if_icmpge (1, 4)
	25 91 (1, 4)
	27 aload_3 (1, 4)
	28 iload (1, 4)
	29 #8 (1, 4)
	30 daload (1, 4)
	31 dstore (1, 4)
	32 #9 (1, 4)
	33 aload_3 (1, 4)
	34 iload (1, 4)
	35 #8 (1, 4)
	36 dup2 (1, 4)
	37 daload (1, 4)
	38 aload_0 (1, 4)
	39 getfield (1, 4)
	40 org/apache/commons/math3/ode/JacobianMatrices$MainStateJacobianWrapper.hY:[D (1, 4)
	42 iload (1, 4)
	43 #8 (1, 4)
	44 daload (1, 4)
	45 dadd (1, 4)
	46 dastore (1, 4)
	47 aload_0 (1, 4)
	48 getfield (1, 4)
	49 org/apache/commons/math3/ode/JacobianMatrices$MainStateJacobianWrapper.ode:Lorg/apache/commons/math3/ode/FirstOrderDifferentialEquations; (1, 4)
	51 dload_1 (1, 4)
	52 aload_3 (1, 4)
	53 aload (1, 4)
	54 #7 (1, 4)
	55 invokeinterface (1, 4)
	56 org/apache/commons/math3/ode/FirstOrderDifferentialEquations.org/apache/commons/math3/ode/JacobianMatrices (1, 4)
	58 0 (1, 4)
	60 iconst_0 (2, 4)
	61 istore (2, 4)
	62 #11 (2, 4)
	63 iload (2, 4)
	64 #11 (2, 4)
	65 iload (2, 4)
	66 #6 (2, 4)
	67 if_icmpge (2, 4)
	68 36 (2, 4)
	70 aload (2, 4)
	71 #5 (2, 4)
	72 iload (2, 4)
	73 #11 (2, 4)
	74 aaload (2, 4)
	75 iload (2, 4)
	76 #8 (2, 4)
	77 aload (2, 4)
	78 #7 (2, 4)
	79 iload (2, 4)
	80 #11 (2, 4)
	81 daload (2, 4)
	82 aload (2, 4)
	83 #4 (2, 4)
	84 iload (2, 4)
	85 #11 (2, 4)
	86 daload (2, 4)
	87 dsub (2, 4)
	88 aload_0 (2, 4)
	89 getfield (2, 4)
	90 org/apache/commons/math3/ode/JacobianMatrices$MainStateJacobianWrapper.hY:[D (2, 4)
	92 iload (2, 4)
	93 #8 (2, 4)
	94 daload (2, 4)
	95 ddiv (2, 4)
	96 dastore (2, 4)
	97 iinc (2, 4)
	98 #11 (2, 4)
	99 -89 (2, 4)
	100 goto (2, 4)
	101 -37 (2, 4)
	103 aload_3 (1, 4)
	104 iload (1, 4)
	105 #8 (1, 4)
	106 dload (1, 4)
	107 #9 (1, 4)
	108 dastore (1, 4)
	109 iinc (1, 4)
	110 #8 (1, 4)
	111 -89 (1, 4)
	112 goto (1, 4)
	113 -92 (1, 4)
	115 return (0, 0)

Method: access$000
	0 aload_0 (0, 0)
	1 getfield (0, 0)
	2 org/apache/commons/math3/ode/JacobianMatrices$MainStateJacobianWrapper.ode:Lorg/apache/commons/math3/ode/FirstOrderDifferentialEquations; (0, 0)
	4 areturn (0, 0)

