Method: getDimension
	0 aload_0 (0, 0)
	1 getfield (0, 0)
	2 org/apache/commons/math3/ode/JacobianMatrices$JacobiansSecondaryEquations.this$0:Lorg/apache/commons/math3/ode/JacobianMatrices; (0, 0)
	4 invokestatic (0, 0)
	5 org/apache/commons/math3/ode/JacobianMatrices.access$200:(Lorg/apache/commons/math3/ode/JacobianMatrices;)I (0, 0)
	7 aload_0 (0, 0)
	8 getfield (0, 0)
	9 org/apache/commons/math3/ode/JacobianMatrices$JacobiansSecondaryEquations.this$0:Lorg/apache/commons/math3/ode/JacobianMatrices; (0, 0)
	11 invokestatic (0, 0)
	12 org/apache/commons/math3/ode/JacobianMatrices.access$200:(Lorg/apache/commons/math3/ode/JacobianMatrices;)I (0, 0)
	14 aload_0 (0, 0)
	15 getfield (0, 0)
	16 org/apache/commons/math3/ode/JacobianMatrices$JacobiansSecondaryEquations.this$0:Lorg/apache/commons/math3/ode/JacobianMatrices; (0, 0)
	18 invokestatic (0, 0)
	19 org/apache/commons/math3/ode/JacobianMatrices.access$300:(Lorg/apache/commons/math3/ode/JacobianMatrices;)I (0, 0)
	21 iadd (0, 0)
	22 imul (0, 0)
	23 ireturn (0, 0)

Method: computeDerivatives
	0 aload_0 (1, 1)
	1 getfield (1, 1)
	2 org/apache/commons/math3/ode/JacobianMatrices$JacobiansSecondaryEquations.this$0:Lorg/apache/commons/math3/ode/JacobianMatrices; (1, 1)
	4 invokestatic (1, 1)
	5 org/apache/commons/math3/ode/JacobianMatrices.access$400:(Lorg/apache/commons/math3/ode/JacobianMatrices;)Z (1, 1)
	7 ifeq (1, 1)
	8 63 (1, 1)
	10 aload_0 (1, 1)
	11 getfield (1, 1)
	12 org/apache/commons/math3/ode/JacobianMatrices$JacobiansSecondaryEquations.this$0:Lorg/apache/commons/math3/ode/JacobianMatrices; (1, 1)
	14 invokestatic (1, 1)
	15 org/apache/commons/math3/ode/JacobianMatrices.access$300:(Lorg/apache/commons/math3/ode/JacobianMatrices;)I (1, 1)
	17 ifeq (1, 1)
	18 53 (1, 1)
	20 aload_0 (1, 1)
	21 getfield (1, 1)
	22 org/apache/commons/math3/ode/JacobianMatrices$JacobiansSecondaryEquations.this$0:Lorg/apache/commons/math3/ode/JacobianMatrices; (1, 1)
	24 invokestatic (1, 1)
	25 org/apache/commons/math3/ode/JacobianMatrices.access$800:(Lorg/apache/commons/math3/ode/JacobianMatrices;)Ljava/util/List; (1, 1)
	27 new (1, 1)
	28 org/apache/commons/math3/ode/ParameterJacobianWrapper (1, 1)
	30 dup (1, 1)
	31 aload_0 (1, 1)
	32 getfield (1, 1)
	33 org/apache/commons/math3/ode/JacobianMatrices$JacobiansSecondaryEquations.this$0:Lorg/apache/commons/math3/ode/JacobianMatrices; (1, 1)
	35 invokestatic (1, 1)
	36 org/apache/commons/math3/ode/JacobianMatrices.access$500:(Lorg/apache/commons/math3/ode/JacobianMatrices;)Lorg/apache/commons/math3/ode/MainStateJacobianProvider; (1, 1)
	38 aload_0 (1, 1)
	39 getfield (1, 1)
	40 org/apache/commons/math3/ode/JacobianMatrices$JacobiansSecondaryEquations.this$0:Lorg/apache/commons/math3/ode/JacobianMatrices; (1, 1)
	42 invokestatic (1, 1)
	43 org/apache/commons/math3/ode/JacobianMatrices.access$600:(Lorg/apache/commons/math3/ode/JacobianMatrices;)Lorg/apache/commons/math3/ode/ParameterizedODE; (1, 1)
	45 aload_0 (1, 1)
	46 getfield (1, 1)
	47 org/apache/commons/math3/ode/JacobianMatrices$JacobiansSecondaryEquations.this$0:Lorg/apache/commons/math3/ode/JacobianMatrices; (1, 1)
	49 invokestatic (1, 1)
	50 org/apache/commons/math3/ode/JacobianMatrices.access$700:(Lorg/apache/commons/math3/ode/JacobianMatrices;)[Lorg/apache/commons/math3/ode/ParameterConfiguration; (1, 1)
	52 invokespecial (1, 1)
	53 org/apache/commons/math3/ode/ParameterJacobianWrapper.<init>:(Lorg/apache/commons/math3/ode/FirstOrderDifferentialEquations;Lorg/apache/commons/math3/ode/ParameterizedODE;[Lorg/apache/commons/math3/ode/ParameterConfiguration;)V (1, 1)
	55 invokeinterface (1, 1)
	56 java/util/List.access$402:(Lorg/apache/commons/math3/ode/JacobianMatrices;Z)Z (1, 1)
	58 0 (1, 1)
	60 pop (1, 1)
	61 aload_0 (1, 1)
	62 getfield (1, 1)
	63 org/apache/commons/math3/ode/JacobianMatrices$JacobiansSecondaryEquations.this$0:Lorg/apache/commons/math3/ode/JacobianMatrices; (1, 1)
	65 iconst_0 (1, 1)
	66 invokestatic (1, 1)
	67 org/apache/commons/math3/ode/JacobianMatrices.access$402:(Lorg/apache/commons/math3/ode/JacobianMatrices;Z)Z (1, 1)
	69 pop (1, 1)
	70 aload_0 (0, 0)
	71 getfield (0, 0)
	72 org/apache/commons/math3/ode/JacobianMatrices$JacobiansSecondaryEquations.this$0:Lorg/apache/commons/math3/ode/JacobianMatrices; (0, 0)
	74 invokestatic (0, 0)
	75 org/apache/commons/math3/ode/JacobianMatrices.access$200:(Lorg/apache/commons/math3/ode/JacobianMatrices;)I (0, 0)
	77 aload_0 (0, 0)
	78 getfield (0, 0)
	79 org/apache/commons/math3/ode/JacobianMatrices$JacobiansSecondaryEquations.this$0:Lorg/apache/commons/math3/ode/JacobianMatrices; (0, 0)
	81 invokestatic (0, 0)
	82 org/apache/commons/math3/ode/JacobianMatrices.access$200:(Lorg/apache/commons/math3/ode/JacobianMatrices;)I (0, 0)
	84 multianewarray (0, 0)
	85 [[D (0, 0)
	87 58 (0, 0)
	88 astore (0, 0)
	89 #7 (0, 0)
	90 aload_0 (0, 0)
	91 getfield (0, 0)
	92 org/apache/commons/math3/ode/JacobianMatrices$JacobiansSecondaryEquations.this$0:Lorg/apache/commons/math3/ode/JacobianMatrices; (0, 0)
	94 invokestatic (0, 0)
	95 org/apache/commons/math3/ode/JacobianMatrices.access$500:(Lorg/apache/commons/math3/ode/JacobianMatrices;)Lorg/apache/commons/math3/ode/MainStateJacobianProvider; (0, 0)
	97 dload_1 (0, 0)
	98 aload_3 (0, 0)
	99 aload (0, 0)
	100 #4 (0, 0)
	101 aload (0, 0)
	102 #7 (0, 0)
	103 invokeinterface (0, 0)
	104 org/apache/commons/math3/ode/MainStateJacobianProvider.size:()I (0, 0)
	106 0 (0, 0)
	108 iconst_0 (1, 4)
	109 istore (1, 4)
	110 #8 (1, 4)
	111 iload (1, 4)
	112 #8 (1, 4)
	113 aload_0 (1, 4)
	114 getfield (1, 4)
	115 org/apache/commons/math3/ode/JacobianMatrices$JacobiansSecondaryEquations.this$0:Lorg/apache/commons/math3/ode/JacobianMatrices; (1, 4)
	117 invokestatic (1, 4)
	118 org/apache/commons/math3/ode/JacobianMatrices.access$200:(Lorg/apache/commons/math3/ode/JacobianMatrices;)I (1, 4)
	120 if_icmpge (1, 4)
	121 115 (1, 4)
	123 aload (1, 4)
	124 #7 (1, 4)
	125 iload (1, 4)
	126 #8 (1, 4)
	127 aaload (1, 4)
	128 astore (1, 4)
	129 #9 (1, 4)
	130 iconst_0 (2, 4)
	131 istore (2, 4)
	132 #10 (2, 4)
	133 iload (2, 4)
	134 #10 (2, 4)
	135 aload_0 (2, 4)
	136 getfield (2, 4)
	137 org/apache/commons/math3/ode/JacobianMatrices$JacobiansSecondaryEquations.this$0:Lorg/apache/commons/math3/ode/JacobianMatrices; (2, 4)
	139 invokestatic (2, 4)
	140 org/apache/commons/math3/ode/JacobianMatrices.access$200:(Lorg/apache/commons/math3/ode/JacobianMatrices;)I (2, 4)
	142 if_icmpge (2, 4)
	143 87 (2, 4)
	145 dconst_0 (2, 4)
	146 dstore (2, 4)
	147 #11 (2, 4)
	148 iload (2, 4)
	149 #10 (2, 4)
	150 istore (2, 4)
	151 #13 (2, 4)
	152 iload (2, 4)
	153 #13 (2, 4)
	154 istore (2, 4)
	155 #14 (2, 4)
	156 iconst_0 (3, 4)
	157 istore (3, 4)
	158 #15 (3, 4)
	159 iload (3, 4)
	160 #15 (3, 4)
	161 aload_0 (3, 4)
	162 getfield (3, 4)
	163 org/apache/commons/math3/ode/JacobianMatrices$JacobiansSecondaryEquations.this$0:Lorg/apache/commons/math3/ode/JacobianMatrices; (3, 4)
	165 invokestatic (3, 4)
	166 org/apache/commons/math3/ode/JacobianMatrices.access$200:(Lorg/apache/commons/math3/ode/JacobianMatrices;)I (3, 4)
	168 if_icmpge (3, 4)
	169 37 (3, 4)
	171 dload (3, 4)
	172 #11 (3, 4)
	173 aload (3, 4)
	174 #9 (3, 4)
	175 iload (3, 4)
	176 #15 (3, 4)
	177 daload (3, 4)
	178 aload (3, 4)
	179 #5 (3, 4)
	180 iload (3, 4)
	181 #14 (3, 4)
	182 daload (3, 4)
	183 dmul (3, 4)
	184 dadd (3, 4)
	185 dstore (3, 4)
	186 #11 (3, 4)
	187 iload (3, 4)
	188 #14 (3, 4)
	189 aload_0 (3, 4)
	190 getfield (3, 4)
	191 org/apache/commons/math3/ode/JacobianMatrices$JacobiansSecondaryEquations.this$0:Lorg/apache/commons/math3/ode/JacobianMatrices; (3, 4)
	193 invokestatic (3, 4)
	194 org/apache/commons/math3/ode/JacobianMatrices.access$200:(Lorg/apache/commons/math3/ode/JacobianMatrices;)I (3, 4)
	196 iadd (3, 4)
	197 istore (3, 4)
	198 #14 (3, 4)
	199 iinc (3, 4)
	200 #15 (3, 4)
	201 -89 (3, 4)
	202 goto (3, 4)
	203 -43 (3, 4)
	205 aload (2, 4)
	206 #6 (2, 4)
	207 iload (2, 4)
	208 #13 (2, 4)
	209 iload (2, 4)
	210 #8 (2, 4)
	211 aload_0 (2, 4)
	212 getfield (2, 4)
	213 org/apache/commons/math3/ode/JacobianMatrices$JacobiansSecondaryEquations.this$0:Lorg/apache/commons/math3/ode/JacobianMatrices; (2, 4)
	215 invokestatic (2, 4)
	216 org/apache/commons/math3/ode/JacobianMatrices.access$200:(Lorg/apache/commons/math3/ode/JacobianMatrices;)I (2, 4)
	218 imul (2, 4)
	219 iadd (2, 4)
	220 dload (2, 4)
	221 #11 (2, 4)
	222 dastore (2, 4)
	223 iinc (2, 4)
	224 #10 (2, 4)
	225 -89 (2, 4)
	226 goto (2, 4)
	227 -93 (2, 4)
	229 iinc (2, 4)
	230 #8 (2, 4)
	231 -89 (2, 4)
	232 goto (2, 4)
	233 -121 (2, 4)
	235 aload_0 (2, 1)
	236 getfield (2, 1)
	237 org/apache/commons/math3/ode/JacobianMatrices$JacobiansSecondaryEquations.this$0:Lorg/apache/commons/math3/ode/JacobianMatrices; (2, 1)
	239 invokestatic (2, 1)
	240 org/apache/commons/math3/ode/JacobianMatrices.access$300:(Lorg/apache/commons/math3/ode/JacobianMatrices;)I (2, 1)
	242 ifeq (2, 1)
	243 281 (2, 1)
	245 aload_0 (2, 1)
	246 getfield (2, 1)
	247 org/apache/commons/math3/ode/JacobianMatrices$JacobiansSecondaryEquations.this$0:Lorg/apache/commons/math3/ode/JacobianMatrices; (2, 1)
	249 invokestatic (2, 1)
	250 org/apache/commons/math3/ode/JacobianMatrices.access$200:(Lorg/apache/commons/math3/ode/JacobianMatrices;)I (2, 1)
	252 newarray (2, 1)
	253 7 (2, 1)
	254 astore (2, 1)
	255 #8 (2, 1)
	256 aload_0 (2, 1)
	257 getfield (2, 1)
	258 org/apache/commons/math3/ode/JacobianMatrices$JacobiansSecondaryEquations.this$0:Lorg/apache/commons/math3/ode/JacobianMatrices; (2, 1)
	260 invokestatic (2, 1)
	261 org/apache/commons/math3/ode/JacobianMatrices.access$200:(Lorg/apache/commons/math3/ode/JacobianMatrices;)I (2, 1)
	263 aload_0 (2, 1)
	264 getfield (2, 1)
	265 org/apache/commons/math3/ode/JacobianMatrices$JacobiansSecondaryEquations.this$0:Lorg/apache/commons/math3/ode/JacobianMatrices; (2, 1)
	267 invokestatic (2, 1)
	268 org/apache/commons/math3/ode/JacobianMatrices.access$200:(Lorg/apache/commons/math3/ode/JacobianMatrices;)I (2, 1)
	270 imul (2, 1)
	271 istore (2, 1)
	272 #9 (2, 1)
	273 aload_0 (3, 4)
	274 getfield (3, 4)
	275 org/apache/commons/math3/ode/JacobianMatrices$JacobiansSecondaryEquations.this$0:Lorg/apache/commons/math3/ode/JacobianMatrices; (3, 4)
	277 invokestatic (3, 4)
	278 org/apache/commons/math3/ode/JacobianMatrices.access$700:(Lorg/apache/commons/math3/ode/JacobianMatrices;)[Lorg/apache/commons/math3/ode/ParameterConfiguration; (3, 4)
	280 astore (3, 4)
	281 #10 (3, 4)
	282 aload (3, 4)
	283 #10 (3, 4)
	284 arraylength (3, 4)
	285 istore (3, 4)
	286 #11 (3, 4)
	287 iconst_0 (3, 4)
	288 istore (3, 4)
	289 #12 (3, 4)
	290 iload (3, 4)
	291 #12 (3, 4)
	292 iload (3, 4)
	293 #11 (3, 4)
	294 if_icmpge (3, 4)
	295 229 (3, 4)
	297 aload (3, 4)
	298 #10 (3, 4)
	299 iload (3, 4)
	300 #12 (3, 4)
	301 aaload (3, 4)
	302 astore (3, 4)
	303 #13 (3, 4)
	304 iconst_0 (3, 4)
	305 istore (3, 4)
	306 #14 (3, 4)
	307 iconst_0 (4, 4)
	308 istore (4, 4)
	309 #15 (4, 4)
	310 iload (4, 4)
	311 #14 (4, 4)
	312 ifne (4, 4)
	313 170 (4, 4)
	315 iload (4, 4)
	316 #15 (4, 4)
	317 aload_0 (4, 4)
	318 getfield (4, 4)
	319 org/apache/commons/math3/ode/JacobianMatrices$JacobiansSecondaryEquations.this$0:Lorg/apache/commons/math3/ode/JacobianMatrices; (4, 4)
	321 invokestatic (4, 4)
	322 org/apache/commons/math3/ode/JacobianMatrices.access$800:(Lorg/apache/commons/math3/ode/JacobianMatrices;)Ljava/util/List; (4, 4)
	324 invokeinterface (4, 4)
	325 java/util/List.get:(I)Ljava/lang/Object; (4, 4)
	327 0 (4, 4)
	329 if_icmpge (4, 4)
	330 153 (4, 4)
	332 aload_0 (4, 4)
	333 getfield (4, 4)
	334 org/apache/commons/math3/ode/JacobianMatrices$JacobiansSecondaryEquations.this$0:Lorg/apache/commons/math3/ode/JacobianMatrices; (4, 4)
	336 invokestatic (4, 4)
	337 org/apache/commons/math3/ode/JacobianMatrices.access$800:(Lorg/apache/commons/math3/ode/JacobianMatrices;)Ljava/util/List; (4, 4)
	339 iload (4, 4)
	340 #15 (4, 4)
	341 invokeinterface (4, 4)
	342 java/util/List.org/apache/commons/math3/ode/ParameterJacobianProvider (4, 4)
	344 0 (4, 4)
	346 checkcast (4, 4)
	347 org/apache/commons/math3/ode/ParameterJacobianProvider (4, 4)
	349 astore (4, 4)
	350 #16 (4, 4)
	351 aload (5, 1)
	352 #16 (5, 1)
	353 aload (5, 1)
	354 #13 (5, 1)
	355 invokevirtual (5, 1)
	356 org/apache/commons/math3/ode/ParameterConfiguration.getParameterName:()Ljava/lang/String; (5, 1)
	358 invokeinterface (5, 1)
	359 org/apache/commons/math3/ode/ParameterJacobianProvider.computeParameterJacobian:(D[D[DLjava/lang/String;[D)V (5, 1)
	361 0 (5, 1)
	363 ifeq (5, 1)
	364 113 (5, 1)
	366 aload (5, 1)
	367 #16 (5, 1)
	368 dload_1 (5, 1)
	369 aload_3 (5, 1)
	370 aload (5, 1)
	371 #4 (5, 1)
	372 aload (5, 1)
	373 #13 (5, 1)
	374 invokevirtual (5, 1)
	375 org/apache/commons/math3/ode/ParameterConfiguration.getParameterName:()Ljava/lang/String; (5, 1)
	377 aload (5, 1)
	378 #8 (5, 1)
	379 invokeinterface (5, 1)
	380 org/apache/commons/math3/ode/ParameterJacobianProvider.java/util/Arrays (5, 1)
	382 0 (5, 1)
	384 iconst_0 (6, 4)
	385 istore (6, 4)
	386 #17 (6, 4)
	387 iload (6, 4)
	388 #17 (6, 4)
	389 aload_0 (6, 4)
	390 getfield (6, 4)
	391 org/apache/commons/math3/ode/JacobianMatrices$JacobiansSecondaryEquations.this$0:Lorg/apache/commons/math3/ode/JacobianMatrices; (6, 4)
	393 invokestatic (6, 4)
	394 org/apache/commons/math3/ode/JacobianMatrices.access$200:(Lorg/apache/commons/math3/ode/JacobianMatrices;)I (6, 4)
	396 if_icmpge (6, 4)
	397 77 (6, 4)
	399 aload (6, 4)
	400 #7 (6, 4)
	401 iload (6, 4)
	402 #17 (6, 4)
	403 aaload (6, 4)
	404 astore (6, 4)
	405 #18 (6, 4)
	406 iload (6, 4)
	407 #9 (6, 4)
	408 istore (6, 4)
	409 #19 (6, 4)
	410 aload (6, 4)
	411 #8 (6, 4)
	412 iload (6, 4)
	413 #17 (6, 4)
	414 daload (6, 4)
	415 dstore (6, 4)
	416 #20 (6, 4)
	417 iconst_0 (7, 4)
	418 istore (7, 4)
	419 #22 (7, 4)
	420 iload (7, 4)
	421 #22 (7, 4)
	422 aload_0 (7, 4)
	423 getfield (7, 4)
	424 org/apache/commons/math3/ode/JacobianMatrices$JacobiansSecondaryEquations.this$0:Lorg/apache/commons/math3/ode/JacobianMatrices; (7, 4)
	426 invokestatic (7, 4)
	427 org/apache/commons/math3/ode/JacobianMatrices.access$200:(Lorg/apache/commons/math3/ode/JacobianMatrices;)I (7, 4)
	429 if_icmpge (7, 4)
	430 28 (7, 4)
	432 dload (7, 4)
	433 #20 (7, 4)
	434 aload (7, 4)
	435 #18 (7, 4)
	436 iload (7, 4)
	437 #22 (7, 4)
	438 daload (7, 4)
	439 aload (7, 4)
	440 #5 (7, 4)
	441 iload (7, 4)
	442 #19 (7, 4)
	443 daload (7, 4)
	444 dmul (7, 4)
	445 dadd (7, 4)
	446 dstore (7, 4)
	447 #20 (7, 4)
	448 iinc (7, 4)
	449 #19 (7, 4)
	450 -124 (7, 4)
	451 iinc (7, 4)
	452 #22 (7, 4)
	453 -89 (7, 4)
	454 goto (7, 4)
	455 -34 (7, 4)
	457 aload (6, 4)
	458 #6 (6, 4)
	459 iload (6, 4)
	460 #9 (6, 4)
	461 iload (6, 4)
	462 #17 (6, 4)
	463 iadd (6, 4)
	464 dload (6, 4)
	465 #20 (6, 4)
	466 dastore (6, 4)
	467 iinc (6, 4)
	468 #17 (6, 4)
	469 -89 (6, 4)
	470 goto (6, 4)
	471 -83 (6, 4)
	473 iconst_1 (5, 1)
	474 istore (5, 1)
	475 #14 (5, 1)
	476 iinc (5, 1)
	477 #15 (5, 1)
	478 -89 (5, 1)
	479 goto (5, 1)
	480 -169 (5, 1)
	482 iload (5, 1)
	483 #14 (5, 1)
	484 ifne (5, 1)
	485 21 (5, 1)
	487 aload (5, 1)
	488 #6 (5, 1)
	489 iload (5, 1)
	490 #9 (5, 1)
	491 iload (5, 1)
	492 #9 (5, 1)
	493 aload_0 (5, 1)
	494 getfield (5, 1)
	495 org/apache/commons/math3/ode/JacobianMatrices$JacobiansSecondaryEquations.this$0:Lorg/apache/commons/math3/ode/JacobianMatrices; (5, 1)
	497 invokestatic (5, 1)
	498 org/apache/commons/math3/ode/JacobianMatrices.access$200:(Lorg/apache/commons/math3/ode/JacobianMatrices;)I (5, 1)
	500 iadd (5, 1)
	501 dconst_0 (5, 1)
	502 invokestatic (5, 1)
	503 java/util/Arrays.fill:([DIID)V (5, 1)
	505 iload (4, 4)
	506 #9 (4, 4)
	507 aload_0 (4, 4)
	508 getfield (4, 4)
	509 org/apache/commons/math3/ode/JacobianMatrices$JacobiansSecondaryEquations.this$0:Lorg/apache/commons/math3/ode/JacobianMatrices; (4, 4)
	511 invokestatic (4, 4)
	512 org/apache/commons/math3/ode/JacobianMatrices.access$200:(Lorg/apache/commons/math3/ode/JacobianMatrices;)I (4, 4)
	514 iadd (4, 4)
	515 istore (4, 4)
	516 #9 (4, 4)
	517 iinc (4, 4)
	518 #12 (4, 4)
	519 -89 (4, 4)
	520 goto (4, 4)
	521 -230 (4, 4)
	523 return (1, 4)

