Method: getDimension
	0 aload_0 (0, 0)
	1 getfield (0, 0)
	2 org/apache/commons/math3/ode/MultistepIntegrator$1.this$0:Lorg/apache/commons/math3/ode/MultistepIntegrator; (0, 0)
	4 invokevirtual (0, 0)
	5 org/apache/commons/math3/ode/MultistepIntegrator.getExpandable:()Lorg/apache/commons/math3/ode/ExpandableStatefulODE; (0, 0)
	7 invokevirtual (0, 0)
	8 org/apache/commons/math3/ode/ExpandableStatefulODE.getTotalDimension:()I (0, 0)
	10 ireturn (0, 0)

Method: computeDerivatives
	0 aload_0 (0, 0)
	1 getfield (0, 0)
	2 org/apache/commons/math3/ode/MultistepIntegrator$1.this$0:Lorg/apache/commons/math3/ode/MultistepIntegrator; (0, 0)
	4 invokevirtual (0, 0)
	5 org/apache/commons/math3/ode/MultistepIntegrator.getExpandable:()Lorg/apache/commons/math3/ode/ExpandableStatefulODE; (0, 0)
	7 dload_1 (0, 0)
	8 aload_3 (0, 0)
	9 aload (0, 0)
	10 #4 (0, 0)
	11 invokevirtual (0, 0)
	12 org/apache/commons/math3/ode/ExpandableStatefulODE.computeDerivatives:(D[D[D)V (0, 0)
	14 return (0, 0)

