Method: <init>
	0 aload_0 (0, 0)
	1 aload_1 (0, 0)
	2 dload (0, 0)
	3 #4 (0, 0)
	4 dload (0, 0)
	5 #6 (0, 0)
	6 aload (0, 0)
	7 #8 (0, 0)
	8 aload (0, 0)
	9 #9 (0, 0)
	10 invokespecial (0, 0)
	11 org/apache/commons/math3/ode/nonstiff/AdaptiveStepsizeIntegrator.<init>:(Ljava/lang/String;DD[D[D)V (0, 0)
	13 aload_0 (0, 0)
	14 new (0, 0)
	15 org/apache/commons/math3/ode/nonstiff/DormandPrince853Integrator (0, 0)
	17 dup (0, 0)
	18 dload (0, 0)
	19 #4 (0, 0)
	20 dload (0, 0)
	21 #6 (0, 0)
	22 aload (0, 0)
	23 #8 (0, 0)
	24 aload (0, 0)
	25 #9 (0, 0)
	26 invokespecial (0, 0)
	27 org/apache/commons/math3/ode/nonstiff/DormandPrince853Integrator.<init>:(DD[D[D)V (0, 0)
	29 putfield (0, 0)
	30 org/apache/commons/math3/ode/MultistepIntegrator.starter:Lorg/apache/commons/math3/ode/FirstOrderIntegrator; (0, 0)
	32 aload_0 (0, 0)
	33 iload_2 (0, 0)
	34 putfield (0, 0)
	35 org/apache/commons/math3/ode/MultistepIntegrator.nSteps:I (0, 0)
	37 aload_0 (0, 0)
	38 ldc2_w (0, 0)
	39 -1.0 (0, 0)
	41 iload_3 (0, 0)
	42 i2d (0, 0)
	43 ddiv (0, 0)
	44 putfield (0, 0)
	45 org/apache/commons/math3/ode/MultistepIntegrator.exp:D (0, 0)
	47 aload_0 (0, 0)
	48 ldc2_w (0, 0)
	49 0.9 (0, 0)
	51 invokevirtual (0, 0)
	52 org/apache/commons/math3/ode/MultistepIntegrator.setSafety:(D)V (0, 0)
	54 aload_0 (0, 0)
	55 ldc2_w (0, 0)
	56 0.2 (0, 0)
	58 invokevirtual (0, 0)
	59 org/apache/commons/math3/ode/MultistepIntegrator.setMinReduction:(D)V (0, 0)
	61 aload_0 (0, 0)
	62 ldc2_w (0, 0)
	63 2.0 (0, 0)
	65 aload_0 (0, 0)
	66 getfield (0, 0)
	67 org/apache/commons/math3/ode/MultistepIntegrator.exp:D (0, 0)
	69 dneg (0, 0)
	70 invokestatic (0, 0)
	71 org/apache/commons/math3/util/FastMath.pow:(DD)D (0, 0)
	73 invokevirtual (0, 0)
	74 org/apache/commons/math3/ode/MultistepIntegrator.setMaxGrowth:(D)V (0, 0)
	76 return (0, 0)

Method: getStarterIntegrator
	0 aload_0 (0, 0)
	1 getfield (0, 0)
	2 org/apache/commons/math3/ode/MultistepIntegrator.starter:Lorg/apache/commons/math3/ode/FirstOrderIntegrator; (0, 0)
	4 areturn (0, 0)

Method: setStarterIntegrator
	0 aload_0 (0, 0)
	1 aload_1 (0, 0)
	2 putfield (0, 0)
	3 org/apache/commons/math3/ode/MultistepIntegrator.starter:Lorg/apache/commons/math3/ode/FirstOrderIntegrator; (0, 0)
	5 return (0, 0)

Method: start
	0 aload_0 (0, 0)
	1 getfield (0, 0)
	2 org/apache/commons/math3/ode/MultistepIntegrator.starter:Lorg/apache/commons/math3/ode/FirstOrderIntegrator; (0, 0)
	4 invokeinterface (0, 0)
	5 org/apache/commons/math3/ode/FirstOrderIntegrator.clearStepHandlers:()V (0, 0)
	7 0 (0, 0)
	9 aload_0 (0, 0)
	10 getfield (0, 0)
	11 org/apache/commons/math3/ode/MultistepIntegrator.starter:Lorg/apache/commons/math3/ode/FirstOrderIntegrator; (0, 0)
	13 invokeinterface (0, 0)
	14 org/apache/commons/math3/ode/FirstOrderIntegrator.org/apache/commons/math3/ode/MultistepIntegrator$NordsieckInitializer (0, 0)
	16 0 (0, 0)
	18 aload_0 (1, 1)
	19 getfield (1, 1)
	20 org/apache/commons/math3/ode/MultistepIntegrator.starter:Lorg/apache/commons/math3/ode/FirstOrderIntegrator; (1, 1)
	22 new (1, 1)
	23 org/apache/commons/math3/ode/MultistepIntegrator$NordsieckInitializer (1, 1)
	25 dup (1, 1)
	26 aload_0 (1, 1)
	27 aload_0 (1, 1)
	28 getfield (1, 1)
	29 org/apache/commons/math3/ode/MultistepIntegrator.nSteps:I (1, 1)
	31 iconst_3 (1, 1)
	32 iadd (1, 1)
	33 iconst_2 (1, 1)
	34 idiv (1, 1)
	35 aload_3 (1, 1)
	36 arraylength (1, 1)
	37 invokespecial (1, 1)
	38 org/apache/commons/math3/ode/MultistepIntegrator$NordsieckInitializer.<init>:(Lorg/apache/commons/math3/ode/MultistepIntegrator;II)V (1, 1)
	40 invokeinterface (1, 1)
	41 org/apache/commons/math3/ode/FirstOrderIntegrator.org/apache/commons/math3/ode/AbstractIntegrator (1, 1)
	43 0 (1, 1)
	45 aload_0 (2, 1)
	46 getfield (2, 1)
	47 org/apache/commons/math3/ode/MultistepIntegrator.starter:Lorg/apache/commons/math3/ode/FirstOrderIntegrator; (2, 1)
	49 instanceof (2, 1)
	50 org/apache/commons/math3/ode/AbstractIntegrator (2, 1)
	52 ifeq (2, 1)
	53 22 (2, 1)
	55 aload_0 (2, 1)
	56 getfield (2, 1)
	57 org/apache/commons/math3/ode/MultistepIntegrator.starter:Lorg/apache/commons/math3/ode/FirstOrderIntegrator; (2, 1)
	59 checkcast (2, 1)
	60 org/apache/commons/math3/ode/AbstractIntegrator (2, 1)
	62 aload_0 (2, 1)
	63 invokevirtual (2, 1)
	64 org/apache/commons/math3/ode/MultistepIntegrator.getExpandable:()Lorg/apache/commons/math3/ode/ExpandableStatefulODE; (2, 1)
	66 dload (2, 1)
	67 #4 (2, 1)
	68 invokevirtual (2, 1)
	69 org/apache/commons/math3/ode/AbstractIntegrator.integrate:(Lorg/apache/commons/math3/ode/ExpandableStatefulODE;D)V (2, 1)
	71 goto (2, 1)
	72 29 (2, 1)
	74 aload_0 (4, 1)
	75 getfield (4, 1)
	76 org/apache/commons/math3/ode/MultistepIntegrator.starter:Lorg/apache/commons/math3/ode/FirstOrderIntegrator; (4, 1)
	78 new (4, 1)
	79 org/apache/commons/math3/ode/MultistepIntegrator$1 (4, 1)
	81 dup (4, 1)
	82 aload_0 (4, 1)
	83 invokespecial (4, 1)
	84 org/apache/commons/math3/ode/MultistepIntegrator$1.<init>:(Lorg/apache/commons/math3/ode/MultistepIntegrator;)V (4, 1)
	86 dload_1 (4, 1)
	87 aload_3 (4, 1)
	88 dload (4, 1)
	89 #4 (4, 1)
	90 aload_3 (4, 1)
	91 arraylength (4, 1)
	92 newarray (4, 1)
	93 7 (4, 1)
	94 invokeinterface (4, 1)
	95 org/apache/commons/math3/ode/FirstOrderIntegrator.org/apache/commons/math3/exception/MathIllegalStateException (4, 1)
	97 0 (4, 1)
	99 pop2 (4, 1)
	100 new (1, 1)
	101 org/apache/commons/math3/exception/MathIllegalStateException (1, 1)
	103 dup (1, 1)
	104 getstatic (1, 1)
	105 org/apache/commons/math3/exception/util/LocalizedFormats.MULTISTEP_STARTER_STOPPED_EARLY:Lorg/apache/commons/math3/exception/util/LocalizedFormats; (1, 1)
	107 iconst_0 (1, 1)
	108 anewarray (1, 1)
	109 java/lang/Object (1, 1)
	111 invokespecial (1, 1)
	112 org/apache/commons/math3/exception/MathIllegalStateException.<init>:(Lorg/apache/commons/math3/exception/util/Localizable;[Ljava/lang/Object;)V (1, 1)
	114 athrow (1, 1)
	115 astore (1, 1)
	116 #6 (1, 1)
	117 aload_0 (1, 1)
	118 invokevirtual (1, 1)
	119 org/apache/commons/math3/ode/MultistepIntegrator.getCounter:()Lorg/apache/commons/math3/util/IntegerSequence$Incrementor; (1, 1)
	121 aload_0 (1, 1)
	122 getfield (1, 1)
	123 org/apache/commons/math3/ode/MultistepIntegrator.starter:Lorg/apache/commons/math3/ode/FirstOrderIntegrator; (1, 1)
	125 invokeinterface (1, 1)
	126 org/apache/commons/math3/ode/FirstOrderIntegrator.org/apache/commons/math3/util/IntegerSequence$Incrementor (1, 1)
	128 0 (1, 1)
	130 invokevirtual (1, 1)
	131 org/apache/commons/math3/util/IntegerSequence$Incrementor.increment:(I)V (1, 1)
	133 aload_0 (2, 1)
	134 getfield (2, 1)
	135 org/apache/commons/math3/ode/MultistepIntegrator.starter:Lorg/apache/commons/math3/ode/FirstOrderIntegrator; (2, 1)
	137 invokeinterface (2, 1)
	138 org/apache/commons/math3/ode/FirstOrderIntegrator.org/apache/commons/math3/ode/MultistepIntegrator$NordsieckInitializer (2, 1)
	140 0 (2, 1)
	142 return (0, 1)

Method: getMinReduction
	0 aload_0 (0, 0)
	1 getfield (0, 0)
	2 org/apache/commons/math3/ode/MultistepIntegrator.minReduction:D (0, 0)
	4 dreturn (0, 0)

Method: setMinReduction
	0 aload_0 (0, 0)
	1 dload_1 (0, 0)
	2 putfield (0, 0)
	3 org/apache/commons/math3/ode/MultistepIntegrator.minReduction:D (0, 0)
	5 return (0, 0)

Method: getMaxGrowth
	0 aload_0 (0, 0)
	1 getfield (0, 0)
	2 org/apache/commons/math3/ode/MultistepIntegrator.maxGrowth:D (0, 0)
	4 dreturn (0, 0)

Method: setMaxGrowth
	0 aload_0 (0, 0)
	1 dload_1 (0, 0)
	2 putfield (0, 0)
	3 org/apache/commons/math3/ode/MultistepIntegrator.maxGrowth:D (0, 0)
	5 return (0, 0)

Method: getSafety
	0 aload_0 (0, 0)
	1 getfield (0, 0)
	2 org/apache/commons/math3/ode/MultistepIntegrator.safety:D (0, 0)
	4 dreturn (0, 0)

Method: setSafety
	0 aload_0 (0, 0)
	1 dload_1 (0, 0)
	2 putfield (0, 0)
	3 org/apache/commons/math3/ode/MultistepIntegrator.safety:D (0, 0)
	5 return (0, 0)

Method: getNSteps
	0 aload_0 (0, 0)
	1 getfield (0, 0)
	2 org/apache/commons/math3/ode/MultistepIntegrator.nSteps:I (0, 0)
	4 ireturn (0, 0)

Method: computeStepGrowShrinkFactor
	0 aload_0 (0, 0)
	1 getfield (0, 0)
	2 org/apache/commons/math3/ode/MultistepIntegrator.maxGrowth:D (0, 0)
	4 aload_0 (0, 0)
	5 getfield (0, 0)
	6 org/apache/commons/math3/ode/MultistepIntegrator.minReduction:D (0, 0)
	8 aload_0 (0, 0)
	9 getfield (0, 0)
	10 org/apache/commons/math3/ode/MultistepIntegrator.safety:D (0, 0)
	12 dload_1 (0, 0)
	13 aload_0 (0, 0)
	14 getfield (0, 0)
	15 org/apache/commons/math3/ode/MultistepIntegrator.exp:D (0, 0)
	17 invokestatic (0, 0)
	18 org/apache/commons/math3/util/FastMath.pow:(DD)D (0, 0)
	20 dmul (0, 0)
	21 invokestatic (0, 0)
	22 org/apache/commons/math3/util/FastMath.max:(DD)D (0, 0)
	24 invokestatic (0, 0)
	25 org/apache/commons/math3/util/FastMath.min:(DD)D (0, 0)
	27 dreturn (0, 0)

