Method: <init>
	0 aload_0 (0, 0)
	1 aload_1 (0, 0)
	2 aload_2 (0, 0)
	3 dload (0, 0)
	4 #5 (0, 0)
	5 dload (0, 0)
	6 #7 (0, 0)
	7 aload (0, 0)
	8 #9 (0, 0)
	9 aload (0, 0)
	10 #10 (0, 0)
	11 invokespecial (0, 0)
	12 org/apache/commons/math3/ode/nonstiff/AdaptiveStepsizeFieldIntegrator.<init>:(Lorg/apache/commons/math3/Field;Ljava/lang/String;DD[D[D)V (0, 0)
	14 aload_0 (0, 0)
	15 new (0, 0)
	16 org/apache/commons/math3/ode/nonstiff/DormandPrince853FieldIntegrator (0, 0)
	18 dup (0, 0)
	19 aload_1 (0, 0)
	20 dload (0, 0)
	21 #5 (0, 0)
	22 dload (0, 0)
	23 #7 (0, 0)
	24 aload (0, 0)
	25 #9 (0, 0)
	26 aload (0, 0)
	27 #10 (0, 0)
	28 invokespecial (0, 0)
	29 org/apache/commons/math3/ode/nonstiff/DormandPrince853FieldIntegrator.<init>:(Lorg/apache/commons/math3/Field;DD[D[D)V (0, 0)
	31 putfield (0, 0)
	32 org/apache/commons/math3/ode/MultistepFieldIntegrator.starter:Lorg/apache/commons/math3/ode/FirstOrderFieldIntegrator; (0, 0)
	34 aload_0 (0, 0)
	35 iload_3 (0, 0)
	36 putfield (0, 0)
	37 org/apache/commons/math3/ode/MultistepFieldIntegrator.nSteps:I (0, 0)
	39 aload_0 (0, 0)
	40 ldc2_w (0, 0)
	41 -1.0 (0, 0)
	43 iload (0, 0)
	44 #4 (0, 0)
	45 i2d (0, 0)
	46 ddiv (0, 0)
	47 putfield (0, 0)
	48 org/apache/commons/math3/ode/MultistepFieldIntegrator.exp:D (0, 0)
	50 aload_0 (0, 0)
	51 ldc2_w (0, 0)
	52 0.9 (0, 0)
	54 invokevirtual (0, 0)
	55 org/apache/commons/math3/ode/MultistepFieldIntegrator.setSafety:(D)V (0, 0)
	57 aload_0 (0, 0)
	58 ldc2_w (0, 0)
	59 0.2 (0, 0)
	61 invokevirtual (0, 0)
	62 org/apache/commons/math3/ode/MultistepFieldIntegrator.setMinReduction:(D)V (0, 0)
	64 aload_0 (0, 0)
	65 ldc2_w (0, 0)
	66 2.0 (0, 0)
	68 aload_0 (0, 0)
	69 getfield (0, 0)
	70 org/apache/commons/math3/ode/MultistepFieldIntegrator.exp:D (0, 0)
	72 dneg (0, 0)
	73 invokestatic (0, 0)
	74 org/apache/commons/math3/util/FastMath.pow:(DD)D (0, 0)
	76 invokevirtual (0, 0)
	77 org/apache/commons/math3/ode/MultistepFieldIntegrator.setMaxGrowth:(D)V (0, 0)
	79 return (0, 0)

Method: getStarterIntegrator
	0 aload_0 (0, 0)
	1 getfield (0, 0)
	2 org/apache/commons/math3/ode/MultistepFieldIntegrator.starter:Lorg/apache/commons/math3/ode/FirstOrderFieldIntegrator; (0, 0)
	4 areturn (0, 0)

Method: setStarterIntegrator
	0 aload_0 (0, 0)
	1 aload_1 (0, 0)
	2 putfield (0, 0)
	3 org/apache/commons/math3/ode/MultistepFieldIntegrator.starter:Lorg/apache/commons/math3/ode/FirstOrderFieldIntegrator; (0, 0)
	5 return (0, 0)

Method: start
	0 aload_0 (0, 0)
	1 getfield (0, 0)
	2 org/apache/commons/math3/ode/MultistepFieldIntegrator.starter:Lorg/apache/commons/math3/ode/FirstOrderFieldIntegrator; (0, 0)
	4 invokeinterface (0, 0)
	5 org/apache/commons/math3/ode/FirstOrderFieldIntegrator.clearStepHandlers:()V (0, 0)
	7 0 (0, 0)
	9 aload_0 (0, 0)
	10 getfield (0, 0)
	11 org/apache/commons/math3/ode/MultistepFieldIntegrator.starter:Lorg/apache/commons/math3/ode/FirstOrderFieldIntegrator; (0, 0)
	13 invokeinterface (0, 0)
	14 org/apache/commons/math3/ode/FirstOrderFieldIntegrator.org/apache/commons/math3/ode/MultistepFieldIntegrator$FieldNordsieckInitializer (0, 0)
	16 0 (0, 0)
	18 aload_0 (0, 1)
	19 getfield (0, 1)
	20 org/apache/commons/math3/ode/MultistepFieldIntegrator.starter:Lorg/apache/commons/math3/ode/FirstOrderFieldIntegrator; (0, 1)
	22 new (0, 1)
	23 org/apache/commons/math3/ode/MultistepFieldIntegrator$FieldNordsieckInitializer (0, 1)
	25 dup (0, 1)
	26 aload_0 (0, 1)
	27 aload_1 (0, 1)
	28 invokevirtual (0, 1)
	29 org/apache/commons/math3/ode/FieldExpandableODE.getMapper:()Lorg/apache/commons/math3/ode/FieldEquationsMapper; (0, 1)
	31 aload_0 (0, 1)
	32 getfield (0, 1)
	33 org/apache/commons/math3/ode/MultistepFieldIntegrator.nSteps:I (0, 1)
	35 iconst_3 (0, 1)
	36 iadd (0, 1)
	37 iconst_2 (0, 1)
	38 idiv (0, 1)
	39 invokespecial (0, 1)
	40 org/apache/commons/math3/ode/MultistepFieldIntegrator$FieldNordsieckInitializer.<init>:(Lorg/apache/commons/math3/ode/MultistepFieldIntegrator;Lorg/apache/commons/math3/ode/FieldEquationsMapper;I)V (0, 1)
	42 invokeinterface (0, 1)
	43 org/apache/commons/math3/ode/FirstOrderFieldIntegrator.integrate:(Lorg/apache/commons/math3/ode/FieldExpandableODE;Lorg/apache/commons/math3/ode/FieldODEState;Lorg/apache/commons/math3/RealFieldElement;)Lorg/apache/commons/math3/ode/FieldODEStateAndDerivative; (0, 1)
	45 0 (0, 1)
	47 aload_0 (0, 1)
	48 getfield (0, 1)
	49 org/apache/commons/math3/ode/MultistepFieldIntegrator.starter:Lorg/apache/commons/math3/ode/FirstOrderFieldIntegrator; (0, 1)
	51 aload_1 (0, 1)
	52 aload_2 (0, 1)
	53 aload_3 (0, 1)
	54 invokeinterface (0, 1)
	55 org/apache/commons/math3/ode/FirstOrderFieldIntegrator.org/apache/commons/math3/exception/MathIllegalStateException (0, 1)
	57 0 (0, 1)
	59 pop (0, 1)
	60 new (0, 1)
	61 org/apache/commons/math3/exception/MathIllegalStateException (0, 1)
	63 dup (0, 1)
	64 getstatic (0, 1)
	65 org/apache/commons/math3/exception/util/LocalizedFormats.MULTISTEP_STARTER_STOPPED_EARLY:Lorg/apache/commons/math3/exception/util/LocalizedFormats; (0, 1)
	67 iconst_0 (0, 1)
	68 anewarray (0, 1)
	69 java/lang/Object (0, 1)
	71 invokespecial (0, 1)
	72 org/apache/commons/math3/exception/MathIllegalStateException.<init>:(Lorg/apache/commons/math3/exception/util/Localizable;[Ljava/lang/Object;)V (0, 1)
	74 athrow (0, 1)
	75 astore (0, 1)
	76 #4 (0, 1)
	77 aload_0 (0, 1)
	78 invokevirtual (0, 1)
	79 org/apache/commons/math3/ode/MultistepFieldIntegrator.getEvaluationsCounter:()Lorg/apache/commons/math3/util/IntegerSequence$Incrementor; (0, 1)
	81 aload_0 (0, 1)
	82 getfield (0, 1)
	83 org/apache/commons/math3/ode/MultistepFieldIntegrator.starter:Lorg/apache/commons/math3/ode/FirstOrderFieldIntegrator; (0, 1)
	85 invokeinterface (0, 1)
	86 org/apache/commons/math3/ode/FirstOrderFieldIntegrator.org/apache/commons/math3/util/IntegerSequence$Incrementor (0, 1)
	88 0 (0, 1)
	90 invokevirtual (0, 1)
	91 org/apache/commons/math3/util/IntegerSequence$Incrementor.increment:(I)V (0, 1)
	93 aload_0 (0, 1)
	94 getfield (0, 1)
	95 org/apache/commons/math3/ode/MultistepFieldIntegrator.starter:Lorg/apache/commons/math3/ode/FirstOrderFieldIntegrator; (0, 1)
	97 invokeinterface (0, 1)
	98 org/apache/commons/math3/ode/FirstOrderFieldIntegrator.org/apache/commons/math3/ode/MultistepFieldIntegrator$FieldNordsieckInitializer (0, 1)
	100 0 (0, 1)
	102 return (0, 1)

Method: getMinReduction
	0 aload_0 (0, 0)
	1 getfield (0, 0)
	2 org/apache/commons/math3/ode/MultistepFieldIntegrator.minReduction:D (0, 0)
	4 dreturn (0, 0)

Method: setMinReduction
	0 aload_0 (0, 0)
	1 dload_1 (0, 0)
	2 putfield (0, 0)
	3 org/apache/commons/math3/ode/MultistepFieldIntegrator.minReduction:D (0, 0)
	5 return (0, 0)

Method: getMaxGrowth
	0 aload_0 (0, 0)
	1 getfield (0, 0)
	2 org/apache/commons/math3/ode/MultistepFieldIntegrator.maxGrowth:D (0, 0)
	4 dreturn (0, 0)

Method: setMaxGrowth
	0 aload_0 (0, 0)
	1 dload_1 (0, 0)
	2 putfield (0, 0)
	3 org/apache/commons/math3/ode/MultistepFieldIntegrator.maxGrowth:D (0, 0)
	5 return (0, 0)

Method: getSafety
	0 aload_0 (0, 0)
	1 getfield (0, 0)
	2 org/apache/commons/math3/ode/MultistepFieldIntegrator.safety:D (0, 0)
	4 dreturn (0, 0)

Method: setSafety
	0 aload_0 (0, 0)
	1 dload_1 (0, 0)
	2 putfield (0, 0)
	3 org/apache/commons/math3/ode/MultistepFieldIntegrator.safety:D (0, 0)
	5 return (0, 0)

Method: getNSteps
	0 aload_0 (0, 0)
	1 getfield (0, 0)
	2 org/apache/commons/math3/ode/MultistepFieldIntegrator.nSteps:I (0, 0)
	4 ireturn (0, 0)

Method: rescale
	0 aload_1 (0, 0)
	1 aload_0 (0, 0)
	2 invokevirtual (0, 0)
	3 org/apache/commons/math3/ode/MultistepFieldIntegrator.getStepSize:()Lorg/apache/commons/math3/RealFieldElement; (0, 0)
	5 invokeinterface (0, 0)
	6 org/apache/commons/math3/RealFieldElement.org/apache/commons/math3/RealFieldElement (0, 0)
	8 0 (0, 0)
	10 checkcast (0, 0)
	11 org/apache/commons/math3/RealFieldElement (0, 0)
	13 astore_2 (0, 0)
	14 iconst_0 (1, 4)
	15 istore_3 (1, 4)
	16 iload_3 (1, 4)
	17 aload_0 (1, 4)
	18 getfield (1, 4)
	19 org/apache/commons/math3/ode/MultistepFieldIntegrator.scaled:[Lorg/apache/commons/math3/RealFieldElement; (1, 4)
	21 arraylength (1, 4)
	22 if_icmpge (1, 4)
	23 30 (1, 4)
	25 aload_0 (1, 4)
	26 getfield (1, 4)
	27 org/apache/commons/math3/ode/MultistepFieldIntegrator.scaled:[Lorg/apache/commons/math3/RealFieldElement; (1, 4)
	29 iload_3 (1, 4)
	30 aload_0 (1, 4)
	31 getfield (1, 4)
	32 org/apache/commons/math3/ode/MultistepFieldIntegrator.scaled:[Lorg/apache/commons/math3/RealFieldElement; (1, 4)
	34 iload_3 (1, 4)
	35 aaload (1, 4)
	36 aload_2 (1, 4)
	37 invokeinterface (1, 4)
	38 org/apache/commons/math3/RealFieldElement.nordsieck:Lorg/apache/commons/math3/linear/Array2DRowFieldMatrix; (1, 4)
	40 0 (1, 4)
	42 checkcast (1, 4)
	43 org/apache/commons/math3/RealFieldElement (1, 4)
	45 aastore (1, 4)
	46 iinc (1, 4)
	47 #3 (1, 4)
	48 -89 (1, 4)
	49 goto (1, 4)
	50 -33 (1, 4)
	52 aload_0 (0, 0)
	53 getfield (0, 0)
	54 org/apache/commons/math3/ode/MultistepFieldIntegrator.nordsieck:Lorg/apache/commons/math3/linear/Array2DRowFieldMatrix; (0, 0)
	56 invokevirtual (0, 0)
	57 org/apache/commons/math3/linear/Array2DRowFieldMatrix.getDataRef:()[[Lorg/apache/commons/math3/FieldElement; (0, 0)
	59 checkcast (0, 0)
	60 [[Lorg/apache/commons/math3/RealFieldElement; (0, 0)
	62 astore_3 (0, 0)
	63 aload_2 (0, 0)
	64 astore (0, 0)
	65 #4 (0, 0)
	66 iconst_0 (1, 4)
	67 istore (1, 4)
	68 #5 (1, 4)
	69 iload (1, 4)
	70 #5 (1, 4)
	71 aload_3 (1, 4)
	72 arraylength (1, 4)
	73 if_icmpge (1, 4)
	74 65 (1, 4)
	76 aload (1, 4)
	77 #4 (1, 4)
	78 aload_2 (1, 4)
	79 invokeinterface (1, 4)
	80 org/apache/commons/math3/RealFieldElement.nordsieck:Lorg/apache/commons/math3/linear/Array2DRowFieldMatrix; (1, 4)
	82 0 (1, 4)
	84 checkcast (1, 4)
	85 org/apache/commons/math3/RealFieldElement (1, 4)
	87 astore (1, 4)
	88 #4 (1, 4)
	89 aload_3 (1, 4)
	90 iload (1, 4)
	91 #5 (1, 4)
	92 aaload (1, 4)
	93 astore (1, 4)
	94 #6 (1, 4)
	95 iconst_0 (2, 4)
	96 istore (2, 4)
	97 #7 (2, 4)
	98 iload (2, 4)
	99 #7 (2, 4)
	100 aload (2, 4)
	101 #6 (2, 4)
	102 arraylength (2, 4)
	103 if_icmpge (2, 4)
	104 29 (2, 4)
	106 aload (2, 4)
	107 #6 (2, 4)
	108 iload (2, 4)
	109 #7 (2, 4)
	110 aload (2, 4)
	111 #6 (2, 4)
	112 iload (2, 4)
	113 #7 (2, 4)
	114 aaload (2, 4)
	115 aload (2, 4)
	116 #4 (2, 4)
	117 invokeinterface (2, 4)
	118 org/apache/commons/math3/RealFieldElement.nordsieck:Lorg/apache/commons/math3/linear/Array2DRowFieldMatrix; (2, 4)
	120 0 (2, 4)
	122 checkcast (2, 4)
	123 org/apache/commons/math3/RealFieldElement (2, 4)
	125 aastore (2, 4)
	126 iinc (2, 4)
	127 #7 (2, 4)
	128 -89 (2, 4)
	129 goto (2, 4)
	130 -31 (2, 4)
	132 iinc (2, 4)
	133 #5 (2, 4)
	134 -89 (2, 4)
	135 goto (2, 4)
	136 -66 (2, 4)
	138 aload_0 (1, 4)
	139 aload_1 (1, 4)
	140 invokevirtual (1, 4)
	141 org/apache/commons/math3/ode/MultistepFieldIntegrator.setStepSize:(Lorg/apache/commons/math3/RealFieldElement;)V (1, 4)
	143 return (0, 0)

Method: computeStepGrowShrinkFactor
	0 aload_1 (0, 0)
	1 invokeinterface (0, 0)
	2 org/apache/commons/math3/RealFieldElement.org/apache/commons/math3/Field (0, 0)
	4 0 (0, 0)
	6 invokeinterface (0, 0)
	7 org/apache/commons/math3/Field.add:(D)Ljava/lang/Object; (0, 0)
	9 0 (0, 0)
	11 checkcast (0, 0)
	12 org/apache/commons/math3/RealFieldElement (0, 0)
	14 aload_0 (0, 0)
	15 getfield (0, 0)
	16 org/apache/commons/math3/ode/MultistepFieldIntegrator.maxGrowth:D (0, 0)
	18 invokeinterface (0, 0)
	19 org/apache/commons/math3/RealFieldElement.pow:(D)Ljava/lang/Object; (0, 0)
	21 0 (0, 0)
	23 checkcast (0, 0)
	24 org/apache/commons/math3/RealFieldElement (0, 0)
	26 aload_1 (0, 0)
	27 invokeinterface (0, 0)
	28 org/apache/commons/math3/RealFieldElement.org/apache/commons/math3/Field (0, 0)
	30 0 (0, 0)
	32 invokeinterface (0, 0)
	33 org/apache/commons/math3/Field.add:(D)Ljava/lang/Object; (0, 0)
	35 0 (0, 0)
	37 checkcast (0, 0)
	38 org/apache/commons/math3/RealFieldElement (0, 0)
	40 aload_0 (0, 0)
	41 getfield (0, 0)
	42 org/apache/commons/math3/ode/MultistepFieldIntegrator.minReduction:D (0, 0)
	44 invokeinterface (0, 0)
	45 org/apache/commons/math3/RealFieldElement.pow:(D)Ljava/lang/Object; (0, 0)
	47 0 (0, 0)
	49 checkcast (0, 0)
	50 org/apache/commons/math3/RealFieldElement (0, 0)
	52 aload_1 (0, 0)
	53 aload_0 (0, 0)
	54 getfield (0, 0)
	55 org/apache/commons/math3/ode/MultistepFieldIntegrator.exp:D (0, 0)
	57 invokeinterface (0, 0)
	58 org/apache/commons/math3/RealFieldElement.multiply:(D)Ljava/lang/Object; (0, 0)
	60 0 (0, 0)
	62 checkcast (0, 0)
	63 org/apache/commons/math3/RealFieldElement (0, 0)
	65 aload_0 (0, 0)
	66 getfield (0, 0)
	67 org/apache/commons/math3/ode/MultistepFieldIntegrator.safety:D (0, 0)
	69 invokeinterface (0, 0)
	70 org/apache/commons/math3/RealFieldElement.org/apache/commons/math3/util/MathUtils (0, 0)
	72 0 (0, 0)
	74 checkcast (0, 0)
	75 org/apache/commons/math3/RealFieldElement (0, 0)
	77 invokestatic (0, 0)
	78 org/apache/commons/math3/util/MathUtils.max:(Lorg/apache/commons/math3/RealFieldElement;Lorg/apache/commons/math3/RealFieldElement;)Lorg/apache/commons/math3/RealFieldElement; (0, 0)
	80 invokestatic (0, 0)
	81 org/apache/commons/math3/util/MathUtils.min:(Lorg/apache/commons/math3/RealFieldElement;Lorg/apache/commons/math3/RealFieldElement;)Lorg/apache/commons/math3/RealFieldElement; (0, 0)
	83 areturn (0, 0)

