Method: <init>
	0 aload_0 (0, 0)
	1 aload_1 (0, 0)
	2 putfield (0, 0)
	3 org/apache/commons/math3/ode/MultistepIntegrator$NordsieckInitializer.this$0:Lorg/apache/commons/math3/ode/MultistepIntegrator; (0, 0)
	5 aload_0 (0, 0)
	6 invokespecial (0, 0)
	7 java/lang/Object.<init>:()V (0, 0)
	9 aload_0 (0, 0)
	10 iconst_0 (0, 0)
	11 putfield (0, 0)
	12 org/apache/commons/math3/ode/MultistepIntegrator$NordsieckInitializer.count:I (0, 0)
	14 aload_0 (0, 0)
	15 iload_2 (0, 0)
	16 newarray (0, 0)
	17 7 (0, 0)
	18 putfield (0, 0)
	19 org/apache/commons/math3/ode/MultistepIntegrator$NordsieckInitializer.t:[D (0, 0)
	21 aload_0 (0, 0)
	22 iload_2 (0, 0)
	23 iload_3 (0, 0)
	24 multianewarray (0, 0)
	25 [[D (0, 0)
	27 -75 (0, 0)
	28 putfield (0, 0)
	29 org/apache/commons/math3/ode/MultistepIntegrator$NordsieckInitializer.y:[[D (0, 0)
	31 aload_0 (0, 0)
	32 iload_2 (0, 0)
	33 iload_3 (0, 0)
	34 multianewarray (0, 0)
	35 [[D (0, 0)
	37 -75 (0, 0)
	38 putfield (0, 0)
	39 org/apache/commons/math3/ode/MultistepIntegrator$NordsieckInitializer.yDot:[[D (0, 0)
	41 return (0, 0)

Method: handleStep
	0 aload_1 (0, 0)
	1 invokeinterface (0, 0)
	2 org/apache/commons/math3/ode/sampling/StepInterpolator.getCurrentTime:()D (0, 0)
	4 0 (0, 0)
	6 dstore_3 (0, 0)
	7 aload_1 (0, 0)
	8 invokeinterface (0, 0)
	9 org/apache/commons/math3/ode/sampling/StepInterpolator.setInterpolatedTime:(D)V (0, 0)
	11 0 (0, 0)
	13 dstore (0, 0)
	14 #5 (0, 0)
	15 aload_0 (1, 1)
	16 getfield (1, 1)
	17 org/apache/commons/math3/ode/MultistepIntegrator$NordsieckInitializer.count:I (1, 1)
	19 ifne (1, 1)
	20 158 (1, 1)
	22 aload_1 (1, 1)
	23 dload_3 (1, 1)
	24 invokeinterface (1, 1)
	25 org/apache/commons/math3/ode/sampling/StepInterpolator.org/apache/commons/math3/ode/MultistepIntegrator (1, 1)
	27 0 (1, 1)
	29 aload_0 (1, 1)
	30 getfield (1, 1)
	31 org/apache/commons/math3/ode/MultistepIntegrator$NordsieckInitializer.t:[D (1, 1)
	33 iconst_0 (1, 1)
	34 dload_3 (1, 1)
	35 dastore (1, 1)
	36 aload_0 (1, 1)
	37 getfield (1, 1)
	38 org/apache/commons/math3/ode/MultistepIntegrator$NordsieckInitializer.this$0:Lorg/apache/commons/math3/ode/MultistepIntegrator; (1, 1)
	40 invokevirtual (1, 1)
	41 org/apache/commons/math3/ode/MultistepIntegrator.getExpandable:()Lorg/apache/commons/math3/ode/ExpandableStatefulODE; (1, 1)
	43 astore (1, 1)
	44 #7 (1, 1)
	45 aload (1, 1)
	46 #7 (1, 1)
	47 invokevirtual (1, 1)
	48 org/apache/commons/math3/ode/ExpandableStatefulODE.getPrimaryMapper:()Lorg/apache/commons/math3/ode/EquationsMapper; (1, 1)
	50 astore (1, 1)
	51 #8 (1, 1)
	52 aload (1, 1)
	53 #8 (1, 1)
	54 aload_1 (1, 1)
	55 invokeinterface (1, 1)
	56 org/apache/commons/math3/ode/sampling/StepInterpolator.org/apache/commons/math3/ode/EquationsMapper (1, 1)
	58 0 (1, 1)
	60 aload_0 (1, 1)
	61 getfield (1, 1)
	62 org/apache/commons/math3/ode/MultistepIntegrator$NordsieckInitializer.y:[[D (1, 1)
	64 aload_0 (1, 1)
	65 getfield (1, 1)
	66 org/apache/commons/math3/ode/MultistepIntegrator$NordsieckInitializer.count:I (1, 1)
	68 aaload (1, 1)
	69 invokevirtual (1, 1)
	70 org/apache/commons/math3/ode/EquationsMapper.insertEquationData:([D[D)V (1, 1)
	72 aload (1, 1)
	73 #8 (1, 1)
	74 aload_1 (1, 1)
	75 invokeinterface (1, 1)
	76 org/apache/commons/math3/ode/sampling/StepInterpolator.getSecondaryMappers:()[Lorg/apache/commons/math3/ode/EquationsMapper; (1, 1)
	78 0 (1, 1)
	80 aload_0 (1, 1)
	81 getfield (1, 1)
	82 org/apache/commons/math3/ode/MultistepIntegrator$NordsieckInitializer.yDot:[[D (1, 1)
	84 aload_0 (1, 1)
	85 getfield (1, 1)
	86 org/apache/commons/math3/ode/MultistepIntegrator$NordsieckInitializer.count:I (1, 1)
	88 aaload (1, 1)
	89 invokevirtual (1, 1)
	90 org/apache/commons/math3/ode/EquationsMapper.insertEquationData:([D[D)V (1, 1)
	92 iconst_0 (1, 1)
	93 istore (1, 1)
	94 #9 (1, 1)
	95 aload (2, 4)
	96 #7 (2, 4)
	97 invokevirtual (2, 4)
	98 org/apache/commons/math3/ode/ExpandableStatefulODE.getSecondaryMappers:()[Lorg/apache/commons/math3/ode/EquationsMapper; (2, 4)
	100 astore (2, 4)
	101 #10 (2, 4)
	102 aload (2, 4)
	103 #10 (2, 4)
	104 arraylength (2, 4)
	105 istore (2, 4)
	106 #11 (2, 4)
	107 iconst_0 (2, 4)
	108 istore (2, 4)
	109 #12 (2, 4)
	110 iload (2, 4)
	111 #12 (2, 4)
	112 iload (2, 4)
	113 #11 (2, 4)
	114 if_icmpge (2, 4)
	115 63 (2, 4)
	117 aload (2, 4)
	118 #10 (2, 4)
	119 iload (2, 4)
	120 #12 (2, 4)
	121 aaload (2, 4)
	122 astore (2, 4)
	123 #13 (2, 4)
	124 aload (2, 4)
	125 #13 (2, 4)
	126 aload_1 (2, 4)
	127 iload (2, 4)
	128 #9 (2, 4)
	129 invokeinterface (2, 4)
	130 org/apache/commons/math3/ode/sampling/StepInterpolator.getInterpolatedSecondaryDerivatives:(I)[D (2, 4)
	132 0 (2, 4)
	134 aload_0 (2, 4)
	135 getfield (2, 4)
	136 org/apache/commons/math3/ode/MultistepIntegrator$NordsieckInitializer.y:[[D (2, 4)
	138 aload_0 (2, 4)
	139 getfield (2, 4)
	140 org/apache/commons/math3/ode/MultistepIntegrator$NordsieckInitializer.count:I (2, 4)
	142 aaload (2, 4)
	143 invokevirtual (2, 4)
	144 org/apache/commons/math3/ode/EquationsMapper.insertEquationData:([D[D)V (2, 4)
	146 aload (2, 4)
	147 #13 (2, 4)
	148 aload_1 (2, 4)
	149 iload (2, 4)
	150 #9 (2, 4)
	151 invokeinterface (2, 4)
	152 org/apache/commons/math3/ode/sampling/StepInterpolator.stepStart:D (2, 4)
	154 0 (2, 4)
	156 aload_0 (2, 4)
	157 getfield (2, 4)
	158 org/apache/commons/math3/ode/MultistepIntegrator$NordsieckInitializer.yDot:[[D (2, 4)
	160 aload_0 (2, 4)
	161 getfield (2, 4)
	162 org/apache/commons/math3/ode/MultistepIntegrator$NordsieckInitializer.count:I (2, 4)
	164 aaload (2, 4)
	165 invokevirtual (2, 4)
	166 org/apache/commons/math3/ode/EquationsMapper.insertEquationData:([D[D)V (2, 4)
	168 iinc (2, 4)
	169 #9 (2, 4)
	170 -124 (2, 4)
	171 iinc (2, 4)
	172 #12 (2, 4)
	173 -89 (2, 4)
	174 goto (2, 4)
	175 -64 (2, 4)
	177 aload_0 (0, 0)
	178 dup (0, 0)
	179 getfield (0, 0)
	180 org/apache/commons/math3/ode/MultistepIntegrator$NordsieckInitializer.count:I (0, 0)
	182 iconst_1 (0, 0)
	183 iadd (0, 0)
	184 putfield (0, 0)
	185 org/apache/commons/math3/ode/MultistepIntegrator$NordsieckInitializer.count:I (0, 0)
	187 aload_1 (0, 0)
	188 dload (0, 0)
	189 #5 (0, 0)
	190 invokeinterface (0, 0)
	191 org/apache/commons/math3/ode/sampling/StepInterpolator.org/apache/commons/math3/ode/MultistepIntegrator (0, 0)
	193 0 (0, 0)
	195 aload_0 (0, 0)
	196 getfield (0, 0)
	197 org/apache/commons/math3/ode/MultistepIntegrator$NordsieckInitializer.t:[D (0, 0)
	199 aload_0 (0, 0)
	200 getfield (0, 0)
	201 org/apache/commons/math3/ode/MultistepIntegrator$NordsieckInitializer.count:I (0, 0)
	203 dload (0, 0)
	204 #5 (0, 0)
	205 dastore (0, 0)
	206 aload_0 (0, 0)
	207 getfield (0, 0)
	208 org/apache/commons/math3/ode/MultistepIntegrator$NordsieckInitializer.this$0:Lorg/apache/commons/math3/ode/MultistepIntegrator; (0, 0)
	210 invokevirtual (0, 0)
	211 org/apache/commons/math3/ode/MultistepIntegrator.getExpandable:()Lorg/apache/commons/math3/ode/ExpandableStatefulODE; (0, 0)
	213 astore (0, 0)
	214 #7 (0, 0)
	215 aload (0, 0)
	216 #7 (0, 0)
	217 invokevirtual (0, 0)
	218 org/apache/commons/math3/ode/ExpandableStatefulODE.getPrimaryMapper:()Lorg/apache/commons/math3/ode/EquationsMapper; (0, 0)
	220 astore (0, 0)
	221 #8 (0, 0)
	222 aload (0, 0)
	223 #8 (0, 0)
	224 aload_1 (0, 0)
	225 invokeinterface (0, 0)
	226 org/apache/commons/math3/ode/sampling/StepInterpolator.org/apache/commons/math3/ode/EquationsMapper (0, 0)
	228 0 (0, 0)
	230 aload_0 (0, 0)
	231 getfield (0, 0)
	232 org/apache/commons/math3/ode/MultistepIntegrator$NordsieckInitializer.y:[[D (0, 0)
	234 aload_0 (0, 0)
	235 getfield (0, 0)
	236 org/apache/commons/math3/ode/MultistepIntegrator$NordsieckInitializer.count:I (0, 0)
	238 aaload (0, 0)
	239 invokevirtual (0, 0)
	240 org/apache/commons/math3/ode/EquationsMapper.insertEquationData:([D[D)V (0, 0)
	242 aload (0, 0)
	243 #8 (0, 0)
	244 aload_1 (0, 0)
	245 invokeinterface (0, 0)
	246 org/apache/commons/math3/ode/sampling/StepInterpolator.getSecondaryMappers:()[Lorg/apache/commons/math3/ode/EquationsMapper; (0, 0)
	248 0 (0, 0)
	250 aload_0 (0, 0)
	251 getfield (0, 0)
	252 org/apache/commons/math3/ode/MultistepIntegrator$NordsieckInitializer.yDot:[[D (0, 0)
	254 aload_0 (0, 0)
	255 getfield (0, 0)
	256 org/apache/commons/math3/ode/MultistepIntegrator$NordsieckInitializer.count:I (0, 0)
	258 aaload (0, 0)
	259 invokevirtual (0, 0)
	260 org/apache/commons/math3/ode/EquationsMapper.insertEquationData:([D[D)V (0, 0)
	262 iconst_0 (0, 0)
	263 istore (0, 0)
	264 #9 (0, 0)
	265 aload (1, 4)
	266 #7 (1, 4)
	267 invokevirtual (1, 4)
	268 org/apache/commons/math3/ode/ExpandableStatefulODE.getSecondaryMappers:()[Lorg/apache/commons/math3/ode/EquationsMapper; (1, 4)
	270 astore (1, 4)
	271 #10 (1, 4)
	272 aload (1, 4)
	273 #10 (1, 4)
	274 arraylength (1, 4)
	275 istore (1, 4)
	276 #11 (1, 4)
	277 iconst_0 (1, 4)
	278 istore (1, 4)
	279 #12 (1, 4)
	280 iload (1, 4)
	281 #12 (1, 4)
	282 iload (1, 4)
	283 #11 (1, 4)
	284 if_icmpge (1, 4)
	285 63 (1, 4)
	287 aload (1, 4)
	288 #10 (1, 4)
	289 iload (1, 4)
	290 #12 (1, 4)
	291 aaload (1, 4)
	292 astore (1, 4)
	293 #13 (1, 4)
	294 aload (1, 4)
	295 #13 (1, 4)
	296 aload_1 (1, 4)
	297 iload (1, 4)
	298 #9 (1, 4)
	299 invokeinterface (1, 4)
	300 org/apache/commons/math3/ode/sampling/StepInterpolator.getInterpolatedSecondaryDerivatives:(I)[D (1, 4)
	302 0 (1, 4)
	304 aload_0 (1, 4)
	305 getfield (1, 4)
	306 org/apache/commons/math3/ode/MultistepIntegrator$NordsieckInitializer.y:[[D (1, 4)
	308 aload_0 (1, 4)
	309 getfield (1, 4)
	310 org/apache/commons/math3/ode/MultistepIntegrator$NordsieckInitializer.count:I (1, 4)
	312 aaload (1, 4)
	313 invokevirtual (1, 4)
	314 org/apache/commons/math3/ode/EquationsMapper.insertEquationData:([D[D)V (1, 4)
	316 aload (1, 4)
	317 #13 (1, 4)
	318 aload_1 (1, 4)
	319 iload (1, 4)
	320 #9 (1, 4)
	321 invokeinterface (1, 4)
	322 org/apache/commons/math3/ode/sampling/StepInterpolator.stepStart:D (1, 4)
	324 0 (1, 4)
	326 aload_0 (1, 4)
	327 getfield (1, 4)
	328 org/apache/commons/math3/ode/MultistepIntegrator$NordsieckInitializer.yDot:[[D (1, 4)
	330 aload_0 (1, 4)
	331 getfield (1, 4)
	332 org/apache/commons/math3/ode/MultistepIntegrator$NordsieckInitializer.count:I (1, 4)
	334 aaload (1, 4)
	335 invokevirtual (1, 4)
	336 org/apache/commons/math3/ode/EquationsMapper.insertEquationData:([D[D)V (1, 4)
	338 iinc (1, 4)
	339 #9 (1, 4)
	340 -124 (1, 4)
	341 iinc (1, 4)
	342 #12 (1, 4)
	343 -89 (1, 4)
	344 goto (1, 4)
	345 -64 (1, 4)
	347 aload_0 (1, 1)
	348 getfield (1, 1)
	349 org/apache/commons/math3/ode/MultistepIntegrator$NordsieckInitializer.count:I (1, 1)
	351 aload_0 (1, 1)
	352 getfield (1, 1)
	353 org/apache/commons/math3/ode/MultistepIntegrator$NordsieckInitializer.t:[D (1, 1)
	355 arraylength (1, 1)
	356 iconst_1 (1, 1)
	357 isub (1, 1)
	358 if_icmpne (1, 1)
	359 153 (1, 1)
	361 aload_0 (1, 1)
	362 getfield (1, 1)
	363 org/apache/commons/math3/ode/MultistepIntegrator$NordsieckInitializer.this$0:Lorg/apache/commons/math3/ode/MultistepIntegrator; (1, 1)
	365 aload_0 (1, 1)
	366 getfield (1, 1)
	367 org/apache/commons/math3/ode/MultistepIntegrator$NordsieckInitializer.t:[D (1, 1)
	369 iconst_0 (1, 1)
	370 daload (1, 1)
	371 putfield (1, 1)
	372 org/apache/commons/math3/ode/MultistepIntegrator.stepStart:D (1, 1)
	374 aload_0 (1, 1)
	375 getfield (1, 1)
	376 org/apache/commons/math3/ode/MultistepIntegrator$NordsieckInitializer.this$0:Lorg/apache/commons/math3/ode/MultistepIntegrator; (1, 1)
	378 aload_0 (1, 1)
	379 getfield (1, 1)
	380 org/apache/commons/math3/ode/MultistepIntegrator$NordsieckInitializer.t:[D (1, 1)
	382 aload_0 (1, 1)
	383 getfield (1, 1)
	384 org/apache/commons/math3/ode/MultistepIntegrator$NordsieckInitializer.t:[D (1, 1)
	386 arraylength (1, 1)
	387 iconst_1 (1, 1)
	388 isub (1, 1)
	389 daload (1, 1)
	390 aload_0 (1, 1)
	391 getfield (1, 1)
	392 org/apache/commons/math3/ode/MultistepIntegrator$NordsieckInitializer.t:[D (1, 1)
	394 iconst_0 (1, 1)
	395 daload (1, 1)
	396 dsub (1, 1)
	397 aload_0 (1, 1)
	398 getfield (1, 1)
	399 org/apache/commons/math3/ode/MultistepIntegrator$NordsieckInitializer.t:[D (1, 1)
	401 arraylength (1, 1)
	402 iconst_1 (1, 1)
	403 isub (1, 1)
	404 i2d (1, 1)
	405 ddiv (1, 1)
	406 putfield (1, 1)
	407 org/apache/commons/math3/ode/MultistepIntegrator.stepSize:D (1, 1)
	409 aload_0 (1, 1)
	410 getfield (1, 1)
	411 org/apache/commons/math3/ode/MultistepIntegrator$NordsieckInitializer.this$0:Lorg/apache/commons/math3/ode/MultistepIntegrator; (1, 1)
	413 aload_0 (1, 1)
	414 getfield (1, 1)
	415 org/apache/commons/math3/ode/MultistepIntegrator$NordsieckInitializer.yDot:[[D (1, 1)
	417 iconst_0 (1, 1)
	418 aaload (1, 1)
	419 invokevirtual (1, 1)
	420 [D.clone:()Ljava/lang/Object; (1, 1)
	422 checkcast (1, 1)
	423 [D (1, 1)
	425 putfield (1, 1)
	426 org/apache/commons/math3/ode/MultistepIntegrator.scaled:[D (1, 1)
	428 iconst_0 (2, 4)
	429 istore (2, 4)
	430 #10 (2, 4)
	431 iload (2, 4)
	432 #10 (2, 4)
	433 aload_0 (2, 4)
	434 getfield (2, 4)
	435 org/apache/commons/math3/ode/MultistepIntegrator$NordsieckInitializer.this$0:Lorg/apache/commons/math3/ode/MultistepIntegrator; (2, 4)
	437 getfield (2, 4)
	438 org/apache/commons/math3/ode/MultistepIntegrator.scaled:[D (2, 4)
	440 arraylength (2, 4)
	441 if_icmpge (2, 4)
	442 29 (2, 4)
	444 aload_0 (2, 4)
	445 getfield (2, 4)
	446 org/apache/commons/math3/ode/MultistepIntegrator$NordsieckInitializer.this$0:Lorg/apache/commons/math3/ode/MultistepIntegrator; (2, 4)
	448 getfield (2, 4)
	449 org/apache/commons/math3/ode/MultistepIntegrator.scaled:[D (2, 4)
	451 iload (2, 4)
	452 #10 (2, 4)
	453 dup2 (2, 4)
	454 daload (2, 4)
	455 aload_0 (2, 4)
	456 getfield (2, 4)
	457 org/apache/commons/math3/ode/MultistepIntegrator$NordsieckInitializer.this$0:Lorg/apache/commons/math3/ode/MultistepIntegrator; (2, 4)
	459 getfield (2, 4)
	460 org/apache/commons/math3/ode/MultistepIntegrator.stepSize:D (2, 4)
	462 dmul (2, 4)
	463 dastore (2, 4)
	464 iinc (2, 4)
	465 #10 (2, 4)
	466 -89 (2, 4)
	467 goto (2, 4)
	468 -36 (2, 4)
	470 aload_0 (1, 1)
	471 getfield (1, 1)
	472 org/apache/commons/math3/ode/MultistepIntegrator$NordsieckInitializer.this$0:Lorg/apache/commons/math3/ode/MultistepIntegrator; (1, 1)
	474 aload_0 (1, 1)
	475 getfield (1, 1)
	476 org/apache/commons/math3/ode/MultistepIntegrator$NordsieckInitializer.this$0:Lorg/apache/commons/math3/ode/MultistepIntegrator; (1, 1)
	478 aload_0 (1, 1)
	479 getfield (1, 1)
	480 org/apache/commons/math3/ode/MultistepIntegrator$NordsieckInitializer.this$0:Lorg/apache/commons/math3/ode/MultistepIntegrator; (1, 1)
	482 getfield (1, 1)
	483 org/apache/commons/math3/ode/MultistepIntegrator.stepSize:D (1, 1)
	485 aload_0 (1, 1)
	486 getfield (1, 1)
	487 org/apache/commons/math3/ode/MultistepIntegrator$NordsieckInitializer.t:[D (1, 1)
	489 aload_0 (1, 1)
	490 getfield (1, 1)
	491 org/apache/commons/math3/ode/MultistepIntegrator$NordsieckInitializer.y:[[D (1, 1)
	493 aload_0 (1, 1)
	494 getfield (1, 1)
	495 org/apache/commons/math3/ode/MultistepIntegrator$NordsieckInitializer.yDot:[[D (1, 1)
	497 invokevirtual (1, 1)
	498 org/apache/commons/math3/ode/MultistepIntegrator.initializeHighOrderDerivatives:(D[D[[D[[D)Lorg/apache/commons/math3/linear/Array2DRowRealMatrix; (1, 1)
	500 putfield (1, 1)
	501 org/apache/commons/math3/ode/MultistepIntegrator.nordsieck:Lorg/apache/commons/math3/linear/Array2DRowRealMatrix; (1, 1)
	503 new (1, 1)
	504 org/apache/commons/math3/ode/MultistepIntegrator$InitializationCompletedMarkerException (1, 1)
	506 dup (1, 1)
	507 invokespecial (1, 1)
	508 org/apache/commons/math3/ode/MultistepIntegrator$InitializationCompletedMarkerException.<init>:()V (1, 1)
	510 athrow (1, 1)
	511 return (0, 0)

Method: init
	0 return (0, 0)

