Method: <init>
	0 aload_0 (0, 0)
	1 aload_1 (0, 0)
	2 putfield (0, 0)
	3 org/apache/commons/math3/ode/MultistepFieldIntegrator$FieldNordsieckInitializer.this$0:Lorg/apache/commons/math3/ode/MultistepFieldIntegrator; (0, 0)
	5 aload_0 (0, 0)
	6 invokespecial (0, 0)
	7 java/lang/Object.<init>:()V (0, 0)
	9 aload_0 (0, 0)
	10 aload_2 (0, 0)
	11 putfield (0, 0)
	12 org/apache/commons/math3/ode/MultistepFieldIntegrator$FieldNordsieckInitializer.mapper:Lorg/apache/commons/math3/ode/FieldEquationsMapper; (0, 0)
	14 aload_0 (0, 0)
	15 iconst_0 (0, 0)
	16 putfield (0, 0)
	17 org/apache/commons/math3/ode/MultistepFieldIntegrator$FieldNordsieckInitializer.count:I (0, 0)
	19 aload_0 (0, 0)
	20 aload_1 (0, 0)
	21 invokevirtual (0, 0)
	22 org/apache/commons/math3/ode/MultistepFieldIntegrator.getField:()Lorg/apache/commons/math3/Field; (0, 0)
	24 iload_3 (0, 0)
	25 invokestatic (0, 0)
	26 org/apache/commons/math3/util/MathArrays.buildArray:(Lorg/apache/commons/math3/Field;I)[Ljava/lang/Object; (0, 0)
	28 checkcast (0, 0)
	29 [Lorg/apache/commons/math3/RealFieldElement; (0, 0)
	31 putfield (0, 0)
	32 org/apache/commons/math3/ode/MultistepFieldIntegrator$FieldNordsieckInitializer.t:[Lorg/apache/commons/math3/RealFieldElement; (0, 0)
	34 aload_0 (0, 0)
	35 aload_1 (0, 0)
	36 invokevirtual (0, 0)
	37 org/apache/commons/math3/ode/MultistepFieldIntegrator.getField:()Lorg/apache/commons/math3/Field; (0, 0)
	39 iload_3 (0, 0)
	40 iconst_m1 (0, 0)
	41 invokestatic (0, 0)
	42 org/apache/commons/math3/util/MathArrays.buildArray:(Lorg/apache/commons/math3/Field;II)[[Ljava/lang/Object; (0, 0)
	44 checkcast (0, 0)
	45 [[Lorg/apache/commons/math3/RealFieldElement; (0, 0)
	47 putfield (0, 0)
	48 org/apache/commons/math3/ode/MultistepFieldIntegrator$FieldNordsieckInitializer.y:[[Lorg/apache/commons/math3/RealFieldElement; (0, 0)
	50 aload_0 (0, 0)
	51 aload_1 (0, 0)
	52 invokevirtual (0, 0)
	53 org/apache/commons/math3/ode/MultistepFieldIntegrator.getField:()Lorg/apache/commons/math3/Field; (0, 0)
	55 iload_3 (0, 0)
	56 iconst_m1 (0, 0)
	57 invokestatic (0, 0)
	58 org/apache/commons/math3/util/MathArrays.buildArray:(Lorg/apache/commons/math3/Field;II)[[Ljava/lang/Object; (0, 0)
	60 checkcast (0, 0)
	61 [[Lorg/apache/commons/math3/RealFieldElement; (0, 0)
	63 putfield (0, 0)
	64 org/apache/commons/math3/ode/MultistepFieldIntegrator$FieldNordsieckInitializer.yDot:[[Lorg/apache/commons/math3/RealFieldElement; (0, 0)
	66 return (0, 0)

Method: handleStep
	0 aload_0 (1, 1)
	1 getfield (1, 1)
	2 org/apache/commons/math3/ode/MultistepFieldIntegrator$FieldNordsieckInitializer.count:I (1, 1)
	4 ifne (1, 1)
	5 62 (1, 1)
	7 aload_1 (1, 1)
	8 invokeinterface (1, 1)
	9 org/apache/commons/math3/ode/sampling/FieldStepInterpolator.savedStart:Lorg/apache/commons/math3/ode/FieldODEStateAndDerivative; (1, 1)
	11 0 (1, 1)
	13 astore_3 (1, 1)
	14 aload_0 (1, 1)
	15 aload_3 (1, 1)
	16 putfield (1, 1)
	17 org/apache/commons/math3/ode/MultistepFieldIntegrator$FieldNordsieckInitializer.savedStart:Lorg/apache/commons/math3/ode/FieldODEStateAndDerivative; (1, 1)
	19 aload_0 (1, 1)
	20 getfield (1, 1)
	21 org/apache/commons/math3/ode/MultistepFieldIntegrator$FieldNordsieckInitializer.t:[Lorg/apache/commons/math3/RealFieldElement; (1, 1)
	23 aload_0 (1, 1)
	24 getfield (1, 1)
	25 org/apache/commons/math3/ode/MultistepFieldIntegrator$FieldNordsieckInitializer.count:I (1, 1)
	27 aload_3 (1, 1)
	28 invokevirtual (1, 1)
	29 org/apache/commons/math3/ode/FieldODEStateAndDerivative.getTime:()Lorg/apache/commons/math3/RealFieldElement; (1, 1)
	31 aastore (1, 1)
	32 aload_0 (1, 1)
	33 getfield (1, 1)
	34 org/apache/commons/math3/ode/MultistepFieldIntegrator$FieldNordsieckInitializer.y:[[Lorg/apache/commons/math3/RealFieldElement; (1, 1)
	36 aload_0 (1, 1)
	37 getfield (1, 1)
	38 org/apache/commons/math3/ode/MultistepFieldIntegrator$FieldNordsieckInitializer.count:I (1, 1)
	40 aload_0 (1, 1)
	41 getfield (1, 1)
	42 org/apache/commons/math3/ode/MultistepFieldIntegrator$FieldNordsieckInitializer.mapper:Lorg/apache/commons/math3/ode/FieldEquationsMapper; (1, 1)
	44 aload_3 (1, 1)
	45 invokevirtual (1, 1)
	46 org/apache/commons/math3/ode/FieldEquationsMapper.mapState:(Lorg/apache/commons/math3/ode/FieldODEState;)[Lorg/apache/commons/math3/RealFieldElement; (1, 1)
	48 aastore (1, 1)
	49 aload_0 (1, 1)
	50 getfield (1, 1)
	51 org/apache/commons/math3/ode/MultistepFieldIntegrator$FieldNordsieckInitializer.yDot:[[Lorg/apache/commons/math3/RealFieldElement; (1, 1)
	53 aload_0 (1, 1)
	54 getfield (1, 1)
	55 org/apache/commons/math3/ode/MultistepFieldIntegrator$FieldNordsieckInitializer.count:I (1, 1)
	57 aload_0 (1, 1)
	58 getfield (1, 1)
	59 org/apache/commons/math3/ode/MultistepFieldIntegrator$FieldNordsieckInitializer.mapper:Lorg/apache/commons/math3/ode/FieldEquationsMapper; (1, 1)
	61 aload_3 (1, 1)
	62 invokevirtual (1, 1)
	63 org/apache/commons/math3/ode/FieldEquationsMapper.mapDerivative:(Lorg/apache/commons/math3/ode/FieldODEStateAndDerivative;)[Lorg/apache/commons/math3/RealFieldElement; (1, 1)
	65 aastore (1, 1)
	66 aload_0 (0, 0)
	67 dup (0, 0)
	68 getfield (0, 0)
	69 org/apache/commons/math3/ode/MultistepFieldIntegrator$FieldNordsieckInitializer.count:I (0, 0)
	71 iconst_1 (0, 0)
	72 iadd (0, 0)
	73 putfield (0, 0)
	74 org/apache/commons/math3/ode/MultistepFieldIntegrator$FieldNordsieckInitializer.count:I (0, 0)
	76 aload_1 (0, 0)
	77 invokeinterface (0, 0)
	78 org/apache/commons/math3/ode/sampling/FieldStepInterpolator.subtract:(Ljava/lang/Object;)Ljava/lang/Object; (0, 0)
	80 0 (0, 0)
	82 astore_3 (0, 0)
	83 aload_0 (0, 0)
	84 getfield (0, 0)
	85 org/apache/commons/math3/ode/MultistepFieldIntegrator$FieldNordsieckInitializer.t:[Lorg/apache/commons/math3/RealFieldElement; (0, 0)
	87 aload_0 (0, 0)
	88 getfield (0, 0)
	89 org/apache/commons/math3/ode/MultistepFieldIntegrator$FieldNordsieckInitializer.count:I (0, 0)
	91 aload_3 (0, 0)
	92 invokevirtual (0, 0)
	93 org/apache/commons/math3/ode/FieldODEStateAndDerivative.getTime:()Lorg/apache/commons/math3/RealFieldElement; (0, 0)
	95 aastore (0, 0)
	96 aload_0 (0, 0)
	97 getfield (0, 0)
	98 org/apache/commons/math3/ode/MultistepFieldIntegrator$FieldNordsieckInitializer.y:[[Lorg/apache/commons/math3/RealFieldElement; (0, 0)
	100 aload_0 (0, 0)
	101 getfield (0, 0)
	102 org/apache/commons/math3/ode/MultistepFieldIntegrator$FieldNordsieckInitializer.count:I (0, 0)
	104 aload_0 (0, 0)
	105 getfield (0, 0)
	106 org/apache/commons/math3/ode/MultistepFieldIntegrator$FieldNordsieckInitializer.mapper:Lorg/apache/commons/math3/ode/FieldEquationsMapper; (0, 0)
	108 aload_3 (0, 0)
	109 invokevirtual (0, 0)
	110 org/apache/commons/math3/ode/FieldEquationsMapper.mapState:(Lorg/apache/commons/math3/ode/FieldODEState;)[Lorg/apache/commons/math3/RealFieldElement; (0, 0)
	112 aastore (0, 0)
	113 aload_0 (0, 0)
	114 getfield (0, 0)
	115 org/apache/commons/math3/ode/MultistepFieldIntegrator$FieldNordsieckInitializer.yDot:[[Lorg/apache/commons/math3/RealFieldElement; (0, 0)
	117 aload_0 (0, 0)
	118 getfield (0, 0)
	119 org/apache/commons/math3/ode/MultistepFieldIntegrator$FieldNordsieckInitializer.count:I (0, 0)
	121 aload_0 (0, 0)
	122 getfield (0, 0)
	123 org/apache/commons/math3/ode/MultistepFieldIntegrator$FieldNordsieckInitializer.mapper:Lorg/apache/commons/math3/ode/FieldEquationsMapper; (0, 0)
	125 aload_3 (0, 0)
	126 invokevirtual (0, 0)
	127 org/apache/commons/math3/ode/FieldEquationsMapper.mapDerivative:(Lorg/apache/commons/math3/ode/FieldODEStateAndDerivative;)[Lorg/apache/commons/math3/RealFieldElement; (0, 0)
	129 aastore (0, 0)
	130 aload_0 (1, 1)
	131 getfield (1, 1)
	132 org/apache/commons/math3/ode/MultistepFieldIntegrator$FieldNordsieckInitializer.count:I (1, 1)
	134 aload_0 (1, 1)
	135 getfield (1, 1)
	136 org/apache/commons/math3/ode/MultistepFieldIntegrator$FieldNordsieckInitializer.t:[Lorg/apache/commons/math3/RealFieldElement; (1, 1)
	138 arraylength (1, 1)
	139 iconst_1 (1, 1)
	140 isub (1, 1)
	141 if_icmpne (1, 1)
	142 187 (1, 1)
	144 aload_0 (1, 1)
	145 getfield (1, 1)
	146 org/apache/commons/math3/ode/MultistepFieldIntegrator$FieldNordsieckInitializer.this$0:Lorg/apache/commons/math3/ode/MultistepFieldIntegrator; (1, 1)
	148 aload_0 (1, 1)
	149 getfield (1, 1)
	150 org/apache/commons/math3/ode/MultistepFieldIntegrator$FieldNordsieckInitializer.t:[Lorg/apache/commons/math3/RealFieldElement; (1, 1)
	152 aload_0 (1, 1)
	153 getfield (1, 1)
	154 org/apache/commons/math3/ode/MultistepFieldIntegrator$FieldNordsieckInitializer.t:[Lorg/apache/commons/math3/RealFieldElement; (1, 1)
	156 arraylength (1, 1)
	157 iconst_1 (1, 1)
	158 isub (1, 1)
	159 aaload (1, 1)
	160 aload_0 (1, 1)
	161 getfield (1, 1)
	162 org/apache/commons/math3/ode/MultistepFieldIntegrator$FieldNordsieckInitializer.t:[Lorg/apache/commons/math3/RealFieldElement; (1, 1)
	164 iconst_0 (1, 1)
	165 aaload (1, 1)
	166 invokeinterface (1, 1)
	167 org/apache/commons/math3/RealFieldElement.org/apache/commons/math3/RealFieldElement (1, 1)
	169 0 (1, 1)
	171 checkcast (1, 1)
	172 org/apache/commons/math3/RealFieldElement (1, 1)
	174 aload_0 (1, 1)
	175 getfield (1, 1)
	176 org/apache/commons/math3/ode/MultistepFieldIntegrator$FieldNordsieckInitializer.t:[Lorg/apache/commons/math3/RealFieldElement; (1, 1)
	178 arraylength (1, 1)
	179 iconst_1 (1, 1)
	180 isub (1, 1)
	181 i2d (1, 1)
	182 invokeinterface (1, 1)
	183 org/apache/commons/math3/RealFieldElement.setStepSize:(Lorg/apache/commons/math3/RealFieldElement;)V (1, 1)
	185 0 (1, 1)
	187 checkcast (1, 1)
	188 org/apache/commons/math3/RealFieldElement (1, 1)
	190 invokevirtual (1, 1)
	191 org/apache/commons/math3/ode/MultistepFieldIntegrator.setStepSize:(Lorg/apache/commons/math3/RealFieldElement;)V (1, 1)
	193 aload_0 (1, 1)
	194 getfield (1, 1)
	195 org/apache/commons/math3/ode/MultistepFieldIntegrator$FieldNordsieckInitializer.this$0:Lorg/apache/commons/math3/ode/MultistepFieldIntegrator; (1, 1)
	197 aload_0 (1, 1)
	198 getfield (1, 1)
	199 org/apache/commons/math3/ode/MultistepFieldIntegrator$FieldNordsieckInitializer.this$0:Lorg/apache/commons/math3/ode/MultistepFieldIntegrator; (1, 1)
	201 invokevirtual (1, 1)
	202 org/apache/commons/math3/ode/MultistepFieldIntegrator.getField:()Lorg/apache/commons/math3/Field; (1, 1)
	204 aload_0 (1, 1)
	205 getfield (1, 1)
	206 org/apache/commons/math3/ode/MultistepFieldIntegrator$FieldNordsieckInitializer.yDot:[[Lorg/apache/commons/math3/RealFieldElement; (1, 1)
	208 iconst_0 (1, 1)
	209 aaload (1, 1)
	210 arraylength (1, 1)
	211 invokestatic (1, 1)
	212 org/apache/commons/math3/util/MathArrays.buildArray:(Lorg/apache/commons/math3/Field;I)[Ljava/lang/Object; (1, 1)
	214 checkcast (1, 1)
	215 [Lorg/apache/commons/math3/RealFieldElement; (1, 1)
	217 putfield (1, 1)
	218 org/apache/commons/math3/ode/MultistepFieldIntegrator.scaled:[Lorg/apache/commons/math3/RealFieldElement; (1, 1)
	220 iconst_0 (2, 4)
	221 istore (2, 4)
	222 #4 (2, 4)
	223 iload (2, 4)
	224 #4 (2, 4)
	225 aload_0 (2, 4)
	226 getfield (2, 4)
	227 org/apache/commons/math3/ode/MultistepFieldIntegrator$FieldNordsieckInitializer.this$0:Lorg/apache/commons/math3/ode/MultistepFieldIntegrator; (2, 4)
	229 getfield (2, 4)
	230 org/apache/commons/math3/ode/MultistepFieldIntegrator.scaled:[Lorg/apache/commons/math3/RealFieldElement; (2, 4)
	232 arraylength (2, 4)
	233 if_icmpge (2, 4)
	234 43 (2, 4)
	236 aload_0 (2, 4)
	237 getfield (2, 4)
	238 org/apache/commons/math3/ode/MultistepFieldIntegrator$FieldNordsieckInitializer.this$0:Lorg/apache/commons/math3/ode/MultistepFieldIntegrator; (2, 4)
	240 getfield (2, 4)
	241 org/apache/commons/math3/ode/MultistepFieldIntegrator.scaled:[Lorg/apache/commons/math3/RealFieldElement; (2, 4)
	243 iload (2, 4)
	244 #4 (2, 4)
	245 aload_0 (2, 4)
	246 getfield (2, 4)
	247 org/apache/commons/math3/ode/MultistepFieldIntegrator$FieldNordsieckInitializer.yDot:[[Lorg/apache/commons/math3/RealFieldElement; (2, 4)
	249 iconst_0 (2, 4)
	250 aaload (2, 4)
	251 iload (2, 4)
	252 #4 (2, 4)
	253 aaload (2, 4)
	254 aload_0 (2, 4)
	255 getfield (2, 4)
	256 org/apache/commons/math3/ode/MultistepFieldIntegrator$FieldNordsieckInitializer.this$0:Lorg/apache/commons/math3/ode/MultistepFieldIntegrator; (2, 4)
	258 invokevirtual (2, 4)
	259 org/apache/commons/math3/ode/MultistepFieldIntegrator.getStepSize:()Lorg/apache/commons/math3/RealFieldElement; (2, 4)
	261 invokeinterface (2, 4)
	262 org/apache/commons/math3/RealFieldElement.initializeHighOrderDerivatives:(Lorg/apache/commons/math3/RealFieldElement;[Lorg/apache/commons/math3/RealFieldElement;[[Lorg/apache/commons/math3/RealFieldElement;[[Lorg/apache/commons/math3/RealFieldElement;)Lorg/apache/commons/math3/linear/Array2DRowFieldMatrix; (2, 4)
	264 0 (2, 4)
	266 checkcast (2, 4)
	267 org/apache/commons/math3/RealFieldElement (2, 4)
	269 aastore (2, 4)
	270 iinc (2, 4)
	271 #4 (2, 4)
	272 -89 (2, 4)
	273 goto (2, 4)
	274 -50 (2, 4)
	276 aload_0 (1, 1)
	277 getfield (1, 1)
	278 org/apache/commons/math3/ode/MultistepFieldIntegrator$FieldNordsieckInitializer.this$0:Lorg/apache/commons/math3/ode/MultistepFieldIntegrator; (1, 1)
	280 aload_0 (1, 1)
	281 getfield (1, 1)
	282 org/apache/commons/math3/ode/MultistepFieldIntegrator$FieldNordsieckInitializer.this$0:Lorg/apache/commons/math3/ode/MultistepFieldIntegrator; (1, 1)
	284 aload_0 (1, 1)
	285 getfield (1, 1)
	286 org/apache/commons/math3/ode/MultistepFieldIntegrator$FieldNordsieckInitializer.this$0:Lorg/apache/commons/math3/ode/MultistepFieldIntegrator; (1, 1)
	288 invokevirtual (1, 1)
	289 org/apache/commons/math3/ode/MultistepFieldIntegrator.getStepSize:()Lorg/apache/commons/math3/RealFieldElement; (1, 1)
	291 aload_0 (1, 1)
	292 getfield (1, 1)
	293 org/apache/commons/math3/ode/MultistepFieldIntegrator$FieldNordsieckInitializer.t:[Lorg/apache/commons/math3/RealFieldElement; (1, 1)
	295 aload_0 (1, 1)
	296 getfield (1, 1)
	297 org/apache/commons/math3/ode/MultistepFieldIntegrator$FieldNordsieckInitializer.y:[[Lorg/apache/commons/math3/RealFieldElement; (1, 1)
	299 aload_0 (1, 1)
	300 getfield (1, 1)
	301 org/apache/commons/math3/ode/MultistepFieldIntegrator$FieldNordsieckInitializer.yDot:[[Lorg/apache/commons/math3/RealFieldElement; (1, 1)
	303 invokevirtual (1, 1)
	304 org/apache/commons/math3/ode/MultistepFieldIntegrator.initializeHighOrderDerivatives:(Lorg/apache/commons/math3/RealFieldElement;[Lorg/apache/commons/math3/RealFieldElement;[[Lorg/apache/commons/math3/RealFieldElement;[[Lorg/apache/commons/math3/RealFieldElement;)Lorg/apache/commons/math3/linear/Array2DRowFieldMatrix; (1, 1)
	306 putfield (1, 1)
	307 org/apache/commons/math3/ode/MultistepFieldIntegrator.nordsieck:Lorg/apache/commons/math3/linear/Array2DRowFieldMatrix; (1, 1)
	309 aload_0 (1, 1)
	310 getfield (1, 1)
	311 org/apache/commons/math3/ode/MultistepFieldIntegrator$FieldNordsieckInitializer.this$0:Lorg/apache/commons/math3/ode/MultistepFieldIntegrator; (1, 1)
	313 aload_0 (1, 1)
	314 getfield (1, 1)
	315 org/apache/commons/math3/ode/MultistepFieldIntegrator$FieldNordsieckInitializer.savedStart:Lorg/apache/commons/math3/ode/FieldODEStateAndDerivative; (1, 1)
	317 invokevirtual (1, 1)
	318 org/apache/commons/math3/ode/MultistepFieldIntegrator.setStepStart:(Lorg/apache/commons/math3/ode/FieldODEStateAndDerivative;)V (1, 1)
	320 new (1, 1)
	321 org/apache/commons/math3/ode/MultistepFieldIntegrator$InitializationCompletedMarkerException (1, 1)
	323 dup (1, 1)
	324 invokespecial (1, 1)
	325 org/apache/commons/math3/ode/MultistepFieldIntegrator$InitializationCompletedMarkerException.<init>:()V (1, 1)
	327 athrow (1, 1)
	328 return (0, 0)

Method: init
	0 return (0, 0)

