Method: <init>
	0 aload_0 (0, 0)
	1 invokespecial (0, 0)
	2 java/lang/Object.<init>:()V (0, 0)
	4 aload_0 (0, 0)
	5 aload_1 (0, 0)
	6 putfield (0, 0)
	7 org/apache/commons/math3/ode/ParameterJacobianWrapper.fode:Lorg/apache/commons/math3/ode/FirstOrderDifferentialEquations; (0, 0)
	9 aload_0 (0, 0)
	10 aload_2 (0, 0)
	11 putfield (0, 0)
	12 org/apache/commons/math3/ode/ParameterJacobianWrapper.pode:Lorg/apache/commons/math3/ode/ParameterizedODE; (0, 0)
	14 aload_0 (0, 0)
	15 new (0, 0)
	16 java/util/HashMap (0, 0)
	18 dup (0, 0)
	19 invokespecial (0, 0)
	20 java/util/HashMap.<init>:()V (0, 0)
	22 putfield (0, 0)
	23 org/apache/commons/math3/ode/ParameterJacobianWrapper.hParam:Ljava/util/Map; (0, 0)
	25 aload_3 (2, 4)
	26 astore (2, 4)
	27 #4 (2, 4)
	28 aload (2, 4)
	29 #4 (2, 4)
	30 arraylength (2, 4)
	31 istore (2, 4)
	32 #5 (2, 4)
	33 iconst_0 (2, 4)
	34 istore (2, 4)
	35 #6 (2, 4)
	36 iload (2, 4)
	37 #6 (2, 4)
	38 iload (2, 4)
	39 #5 (2, 4)
	40 if_icmpge (2, 4)
	41 54 (2, 4)
	43 aload (2, 4)
	44 #4 (2, 4)
	45 iload (2, 4)
	46 #6 (2, 4)
	47 aaload (2, 4)
	48 astore (2, 4)
	49 #7 (2, 4)
	50 aload (2, 4)
	51 #7 (2, 4)
	52 invokevirtual (2, 4)
	53 org/apache/commons/math3/ode/ParameterConfiguration.getParameterName:()Ljava/lang/String; (2, 4)
	55 astore (2, 4)
	56 #8 (2, 4)
	57 aload_2 (3, 1)
	58 aload (3, 1)
	59 #8 (3, 1)
	60 invokeinterface (3, 1)
	61 org/apache/commons/math3/ode/ParameterizedODE.getHP:()D (3, 1)
	63 0 (3, 1)
	65 ifeq (3, 1)
	66 23 (3, 1)
	68 aload_0 (3, 1)
	69 getfield (3, 1)
	70 org/apache/commons/math3/ode/ParameterJacobianWrapper.hParam:Ljava/util/Map; (3, 1)
	72 aload (3, 1)
	73 #8 (3, 1)
	74 aload (3, 1)
	75 #7 (3, 1)
	76 invokevirtual (3, 1)
	77 org/apache/commons/math3/ode/ParameterConfiguration.getHP:()D (3, 1)
	79 invokestatic (3, 1)
	80 java/lang/Double.valueOf:(D)Ljava/lang/Double; (3, 1)
	82 invokeinterface (3, 1)
	83 java/util/Map.getParametersNames:()Ljava/util/Collection; (3, 1)
	85 0 (3, 1)
	87 pop (3, 1)
	88 iinc (3, 1)
	89 #6 (3, 1)
	90 -89 (3, 1)
	91 goto (3, 1)
	92 -55 (3, 1)
	94 return (1, 4)

Method: getParametersNames
	0 aload_0 (0, 0)
	1 getfield (0, 0)
	2 org/apache/commons/math3/ode/ParameterJacobianWrapper.pode:Lorg/apache/commons/math3/ode/ParameterizedODE; (0, 0)
	4 invokeinterface (0, 0)
	5 org/apache/commons/math3/ode/ParameterizedODE.org/apache/commons/math3/ode/FirstOrderDifferentialEquations (0, 0)
	7 0 (0, 0)
	9 areturn (0, 0)

Method: isSupported
	0 aload_0 (0, 0)
	1 getfield (0, 0)
	2 org/apache/commons/math3/ode/ParameterJacobianWrapper.pode:Lorg/apache/commons/math3/ode/ParameterizedODE; (0, 0)
	4 aload_1 (0, 0)
	5 invokeinterface (0, 0)
	6 org/apache/commons/math3/ode/ParameterizedODE.getHP:()D (0, 0)
	8 0 (0, 0)
	10 ireturn (0, 0)

Method: computeParameterJacobian
	0 aload_0 (0, 0)
	1 getfield (0, 0)
	2 org/apache/commons/math3/ode/ParameterJacobianWrapper.fode:Lorg/apache/commons/math3/ode/FirstOrderDifferentialEquations; (0, 0)
	4 invokeinterface (0, 0)
	5 org/apache/commons/math3/ode/FirstOrderDifferentialEquations.getParameter:(Ljava/lang/String;)D (0, 0)
	7 0 (0, 0)
	9 istore (0, 0)
	10 #7 (0, 0)
	11 aload_0 (1, 1)
	12 getfield (1, 1)
	13 org/apache/commons/math3/ode/ParameterJacobianWrapper.pode:Lorg/apache/commons/math3/ode/ParameterizedODE; (1, 1)
	15 aload (1, 1)
	16 #5 (1, 1)
	17 invokeinterface (1, 1)
	18 org/apache/commons/math3/ode/ParameterizedODE.getHP:()D (1, 1)
	20 0 (1, 1)
	22 ifeq (1, 1)
	23 121 (1, 1)
	25 iload (1, 1)
	26 #7 (1, 1)
	27 newarray (1, 1)
	28 7 (1, 1)
	29 astore (1, 1)
	30 #8 (1, 1)
	31 aload_0 (1, 1)
	32 getfield (1, 1)
	33 org/apache/commons/math3/ode/ParameterJacobianWrapper.pode:Lorg/apache/commons/math3/ode/ParameterizedODE; (1, 1)
	35 aload (1, 1)
	36 #5 (1, 1)
	37 invokeinterface (1, 1)
	38 org/apache/commons/math3/ode/ParameterizedODE.get:(Ljava/lang/Object;)Ljava/lang/Object; (1, 1)
	40 0 (1, 1)
	42 dstore (1, 1)
	43 #9 (1, 1)
	44 aload_0 (1, 1)
	45 getfield (1, 1)
	46 org/apache/commons/math3/ode/ParameterJacobianWrapper.hParam:Ljava/util/Map; (1, 1)
	48 aload (1, 1)
	49 #5 (1, 1)
	50 invokeinterface (1, 1)
	51 java/util/Map.java/lang/Double (1, 1)
	53 0 (1, 1)
	55 checkcast (1, 1)
	56 java/lang/Double (1, 1)
	58 invokevirtual (1, 1)
	59 java/lang/Double.doubleValue:()D (1, 1)
	61 dstore (1, 1)
	62 #11 (1, 1)
	63 aload_0 (1, 1)
	64 getfield (1, 1)
	65 org/apache/commons/math3/ode/ParameterJacobianWrapper.pode:Lorg/apache/commons/math3/ode/ParameterizedODE; (1, 1)
	67 aload (1, 1)
	68 #5 (1, 1)
	69 dload (1, 1)
	70 #9 (1, 1)
	71 dload (1, 1)
	72 #11 (1, 1)
	73 dadd (1, 1)
	74 invokeinterface (1, 1)
	75 org/apache/commons/math3/ode/ParameterizedODE.computeDerivatives:(D[D[D)V (1, 1)
	77 0 (1, 1)
	79 aload_0 (1, 1)
	80 getfield (1, 1)
	81 org/apache/commons/math3/ode/ParameterJacobianWrapper.fode:Lorg/apache/commons/math3/ode/FirstOrderDifferentialEquations; (1, 1)
	83 dload_1 (1, 1)
	84 aload_3 (1, 1)
	85 aload (1, 1)
	86 #8 (1, 1)
	87 invokeinterface (1, 1)
	88 org/apache/commons/math3/ode/FirstOrderDifferentialEquations.java/util/Arrays (1, 1)
	90 0 (1, 1)
	92 iconst_0 (2, 4)
	93 istore (2, 4)
	94 #13 (2, 4)
	95 iload (2, 4)
	96 #13 (2, 4)
	97 iload (2, 4)
	98 #7 (2, 4)
	99 if_icmpge (2, 4)
	100 28 (2, 4)
	102 aload (2, 4)
	103 #6 (2, 4)
	104 iload (2, 4)
	105 #13 (2, 4)
	106 aload (2, 4)
	107 #8 (2, 4)
	108 iload (2, 4)
	109 #13 (2, 4)
	110 daload (2, 4)
	111 aload (2, 4)
	112 #4 (2, 4)
	113 iload (2, 4)
	114 #13 (2, 4)
	115 daload (2, 4)
	116 dsub (2, 4)
	117 dload (2, 4)
	118 #11 (2, 4)
	119 ddiv (2, 4)
	120 dastore (2, 4)
	121 iinc (2, 4)
	122 #13 (2, 4)
	123 -89 (2, 4)
	124 goto (2, 4)
	125 -29 (2, 4)
	127 aload_0 (1, 1)
	128 getfield (1, 1)
	129 org/apache/commons/math3/ode/ParameterJacobianWrapper.pode:Lorg/apache/commons/math3/ode/ParameterizedODE; (1, 1)
	131 aload (1, 1)
	132 #5 (1, 1)
	133 dload (1, 1)
	134 #9 (1, 1)
	135 invokeinterface (1, 1)
	136 org/apache/commons/math3/ode/ParameterizedODE.computeDerivatives:(D[D[D)V (1, 1)
	138 0 (1, 1)
	140 goto (2, 2)
	141 12 (2, 2)
	143 aload (2, 2)
	144 #6 (2, 2)
	145 iconst_0 (2, 2)
	146 iload (2, 2)
	147 #7 (2, 2)
	148 dconst_0 (2, 2)
	149 invokestatic (2, 2)
	150 java/util/Arrays.fill:([DIID)V (2, 2)
	152 return (0, 0)

