Method: <init>
	0 aload_0 (0, 0)
	1 getstatic (0, 0)
	2 org/apache/commons/math3/exception/util/LocalizedFormats.UNKNOWN_PARAMETER:Lorg/apache/commons/math3/exception/util/LocalizedFormats; (0, 0)
	4 iconst_1 (0, 0)
	5 anewarray (0, 0)
	6 java/lang/Object (0, 0)
	8 dup (0, 0)
	9 iconst_0 (0, 0)
	10 aload_1 (0, 0)
	11 aastore (0, 0)
	12 invokespecial (0, 0)
	13 org/apache/commons/math3/exception/MathIllegalArgumentException.<init>:(Lorg/apache/commons/math3/exception/util/Localizable;[Ljava/lang/Object;)V (0, 0)
	15 aload_0 (0, 0)
	16 aload_1 (0, 0)
	17 putfield (0, 0)
	18 org/apache/commons/math3/ode/UnknownParameterException.name:Ljava/lang/String; (0, 0)
	20 return (0, 0)

Method: getName
	0 aload_0 (0, 0)
	1 getfield (0, 0)
	2 org/apache/commons/math3/ode/UnknownParameterException.name:Ljava/lang/String; (0, 0)
	4 areturn (0, 0)

