Method: <init>
	0 aload_0 (0, 0)
	1 invokespecial (0, 0)
	4 aload_0 (0, 0)
	5 iload_1 (0, 0)
	6 putfield (0, 0)
	9 aload_0 (0, 0)
	10 iload_2 (0, 0)
	11 putfield (0, 0)
	14 aload_0 (0, 0)
	15 aload_3 (0, 0)
	16 putfield (0, 0)
	19 return (0, 0)

Method: getEvaluationCounter
	0 new (0, 0)
	3 dup (0, 0)
	4 aload_0 (0, 0)
	5 getfield (0, 0)
	8 getstatic (0, 0)
	11 invokespecial (0, 0)
	14 areturn (0, 0)

Method: getIterationCounter
	0 new (0, 0)
	3 dup (0, 0)
	4 aload_0 (0, 0)
	5 getfield (0, 0)
	8 getstatic (0, 0)
	11 invokespecial (0, 0)
	14 areturn (0, 0)

Method: getConvergenceChecker
	0 aload_0 (0, 0)
	1 getfield (0, 0)
	4 areturn (0, 0)

Method: <clinit>
	0 new (0, 0)
	3 dup (0, 0)
	4 aconst_null (0, 0)
	5 invokespecial (0, 0)
	8 putstatic (0, 0)
	11 new (0, 4)
	14 dup (0, 4)
	15 aconst_null (0, 4)
	16 invokespecial (0, 4)
	19 putstatic (0, 4)
	22 return (0, 4)

