Method: <init>
	0 aload_0 (0, 0)
	1 invokespecial (0, 0)
	2 java/lang/Object.<init>:()V (0, 0)
	4 aload_0 (0, 0)
	5 iload_1 (0, 0)
	6 putfield (0, 0)
	7 org/apache/commons/math3/optim/AbstractOptimizationProblem.maxEvaluations:I (0, 0)
	9 aload_0 (0, 0)
	10 iload_2 (0, 0)
	11 putfield (0, 0)
	12 org/apache/commons/math3/optim/AbstractOptimizationProblem.maxIterations:I (0, 0)
	14 aload_0 (0, 0)
	15 aload_3 (0, 0)
	16 putfield (0, 0)
	17 org/apache/commons/math3/optim/AbstractOptimizationProblem.checker:Lorg/apache/commons/math3/optim/ConvergenceChecker; (0, 0)
	19 return (0, 0)

Method: getEvaluationCounter
	0 new (0, 0)
	1 org/apache/commons/math3/util/Incrementor (0, 0)
	3 dup (0, 0)
	4 aload_0 (0, 0)
	5 getfield (0, 0)
	6 org/apache/commons/math3/optim/AbstractOptimizationProblem.maxEvaluations:I (0, 0)
	8 getstatic (0, 0)
	9 org/apache/commons/math3/optim/AbstractOptimizationProblem.MAX_EVAL_CALLBACK:Lorg/apache/commons/math3/optim/AbstractOptimizationProblem$MaxEvalCallback; (0, 0)
	11 invokespecial (0, 0)
	12 org/apache/commons/math3/util/Incrementor.<init>:(ILorg/apache/commons/math3/util/Incrementor$MaxCountExceededCallback;)V (0, 0)
	14 areturn (0, 0)

Method: getIterationCounter
	0 new (0, 0)
	1 org/apache/commons/math3/util/Incrementor (0, 0)
	3 dup (0, 0)
	4 aload_0 (0, 0)
	5 getfield (0, 0)
	6 org/apache/commons/math3/optim/AbstractOptimizationProblem.maxIterations:I (0, 0)
	8 getstatic (0, 0)
	9 org/apache/commons/math3/optim/AbstractOptimizationProblem.MAX_ITER_CALLBACK:Lorg/apache/commons/math3/optim/AbstractOptimizationProblem$MaxIterCallback; (0, 0)
	11 invokespecial (0, 0)
	12 org/apache/commons/math3/util/Incrementor.<init>:(ILorg/apache/commons/math3/util/Incrementor$MaxCountExceededCallback;)V (0, 0)
	14 areturn (0, 0)

Method: getConvergenceChecker
	0 aload_0 (0, 0)
	1 getfield (0, 0)
	2 org/apache/commons/math3/optim/AbstractOptimizationProblem.checker:Lorg/apache/commons/math3/optim/ConvergenceChecker; (0, 0)
	4 areturn (0, 0)

Method: <clinit>
	0 new (0, 0)
	1 org/apache/commons/math3/optim/AbstractOptimizationProblem$MaxEvalCallback (0, 0)
	3 dup (0, 0)
	4 aconst_null (0, 0)
	5 invokespecial (0, 0)
	6 org/apache/commons/math3/optim/AbstractOptimizationProblem$MaxEvalCallback.<init>:(Lorg/apache/commons/math3/optim/AbstractOptimizationProblem$1;)V (0, 0)
	8 putstatic (0, 0)
	9 org/apache/commons/math3/optim/AbstractOptimizationProblem.MAX_EVAL_CALLBACK:Lorg/apache/commons/math3/optim/AbstractOptimizationProblem$MaxEvalCallback; (0, 0)
	11 new (1, 4)
	12 org/apache/commons/math3/optim/AbstractOptimizationProblem$MaxIterCallback (1, 4)
	14 dup (1, 4)
	15 aconst_null (1, 4)
	16 invokespecial (1, 4)
	17 org/apache/commons/math3/optim/AbstractOptimizationProblem$MaxIterCallback.<init>:(Lorg/apache/commons/math3/optim/AbstractOptimizationProblem$1;)V (1, 4)
	19 putstatic (1, 4)
	20 org/apache/commons/math3/optim/AbstractOptimizationProblem.MAX_ITER_CALLBACK:Lorg/apache/commons/math3/optim/AbstractOptimizationProblem$MaxIterCallback; (1, 4)
	22 return (0, 4)

