Method: <init>
	0 aload_0 (0, 0)
	1 invokespecial (0, 0)
	2 java/lang/Object.<init>:()V (0, 0)
	4 aload_0 (0, 0)
	5 aload_1 (0, 0)
	6 putfield (0, 0)
	7 org/apache/commons/math3/optim/BaseOptimizer.checker:Lorg/apache/commons/math3/optim/ConvergenceChecker; (0, 0)
	9 aload_0 (0, 0)
	10 new (0, 0)
	11 org/apache/commons/math3/util/Incrementor (0, 0)
	13 dup (0, 0)
	14 iload_2 (0, 0)
	15 new (0, 0)
	16 org/apache/commons/math3/optim/BaseOptimizer$MaxEvalCallback (0, 0)
	18 dup (0, 0)
	19 aconst_null (0, 0)
	20 invokespecial (0, 0)
	21 org/apache/commons/math3/optim/BaseOptimizer$MaxEvalCallback.<init>:(Lorg/apache/commons/math3/optim/BaseOptimizer$1;)V (0, 0)
	23 invokespecial (0, 0)
	24 org/apache/commons/math3/util/Incrementor.<init>:(ILorg/apache/commons/math3/util/Incrementor$MaxCountExceededCallback;)V (0, 0)
	26 putfield (0, 0)
	27 org/apache/commons/math3/optim/BaseOptimizer.evaluations:Lorg/apache/commons/math3/util/Incrementor; (0, 0)
	29 aload_0 (0, 0)
	30 new (0, 0)
	31 org/apache/commons/math3/util/Incrementor (0, 0)
	33 dup (0, 0)
	34 iload_3 (0, 0)
	35 new (0, 0)
	36 org/apache/commons/math3/optim/BaseOptimizer$MaxIterCallback (0, 0)
	38 dup (0, 0)
	39 aconst_null (0, 0)
	40 invokespecial (0, 0)
	41 org/apache/commons/math3/optim/BaseOptimizer$MaxIterCallback.<init>:(Lorg/apache/commons/math3/optim/BaseOptimizer$1;)V (0, 0)
	43 invokespecial (0, 0)
	44 org/apache/commons/math3/util/Incrementor.<init>:(ILorg/apache/commons/math3/util/Incrementor$MaxCountExceededCallback;)V (0, 0)
	46 putfield (0, 0)
	47 org/apache/commons/math3/optim/BaseOptimizer.iterations:Lorg/apache/commons/math3/util/Incrementor; (0, 0)
	49 return (0, 0)

Method: getMaxEvaluations
	0 aload_0 (0, 0)
	1 getfield (0, 0)
	2 org/apache/commons/math3/optim/BaseOptimizer.evaluations:Lorg/apache/commons/math3/util/Incrementor; (0, 0)
	4 invokevirtual (0, 0)
	5 org/apache/commons/math3/util/Incrementor.getMaximalCount:()I (0, 0)
	7 ireturn (0, 0)

Method: getEvaluations
	0 aload_0 (0, 0)
	1 getfield (0, 0)
	2 org/apache/commons/math3/optim/BaseOptimizer.evaluations:Lorg/apache/commons/math3/util/Incrementor; (0, 0)
	4 invokevirtual (0, 0)
	5 org/apache/commons/math3/util/Incrementor.getCount:()I (0, 0)
	7 ireturn (0, 0)

Method: getMaxIterations
	0 aload_0 (0, 0)
	1 getfield (0, 0)
	2 org/apache/commons/math3/optim/BaseOptimizer.iterations:Lorg/apache/commons/math3/util/Incrementor; (0, 0)
	4 invokevirtual (0, 0)
	5 org/apache/commons/math3/util/Incrementor.getMaximalCount:()I (0, 0)
	7 ireturn (0, 0)

Method: getIterations
	0 aload_0 (0, 0)
	1 getfield (0, 0)
	2 org/apache/commons/math3/optim/BaseOptimizer.iterations:Lorg/apache/commons/math3/util/Incrementor; (0, 0)
	4 invokevirtual (0, 0)
	5 org/apache/commons/math3/util/Incrementor.getCount:()I (0, 0)
	7 ireturn (0, 0)

Method: getConvergenceChecker
	0 aload_0 (0, 0)
	1 getfield (0, 0)
	2 org/apache/commons/math3/optim/BaseOptimizer.checker:Lorg/apache/commons/math3/optim/ConvergenceChecker; (0, 0)
	4 areturn (0, 0)

Method: optimize
	0 aload_0 (0, 0)
	1 getfield (0, 0)
	2 org/apache/commons/math3/optim/BaseOptimizer.evaluations:Lorg/apache/commons/math3/util/Incrementor; (0, 0)
	4 invokevirtual (0, 0)
	5 org/apache/commons/math3/util/Incrementor.resetCount:()V (0, 0)
	7 aload_0 (0, 0)
	8 getfield (0, 0)
	9 org/apache/commons/math3/optim/BaseOptimizer.iterations:Lorg/apache/commons/math3/util/Incrementor; (0, 0)
	11 invokevirtual (0, 0)
	12 org/apache/commons/math3/util/Incrementor.resetCount:()V (0, 0)
	14 aload_0 (0, 4)
	15 invokevirtual (0, 4)
	16 org/apache/commons/math3/optim/BaseOptimizer.doOptimize:()Ljava/lang/Object; (0, 4)
	18 areturn (0, 4)

Method: incrementEvaluationCount
	0 aload_0 (0, 0)
	1 getfield (0, 0)
	2 org/apache/commons/math3/optim/BaseOptimizer.evaluations:Lorg/apache/commons/math3/util/Incrementor; (0, 0)
	4 invokevirtual (0, 0)
	5 org/apache/commons/math3/util/Incrementor.incrementCount:()V (0, 0)
	7 return (0, 0)

Method: incrementIterationCount
	0 aload_0 (0, 0)
	1 getfield (0, 0)
	2 org/apache/commons/math3/optim/BaseOptimizer.iterations:Lorg/apache/commons/math3/util/Incrementor; (0, 0)
	4 invokevirtual (0, 0)
	5 org/apache/commons/math3/util/Incrementor.incrementCount:()V (0, 0)
	7 return (0, 0)

Method: parseOptimizationData
	0 aload_1 (1, 4)
	1 astore_2 (1, 4)
	2 aload_2 (1, 4)
	3 arraylength (1, 4)
	4 istore_3 (1, 4)
	5 iconst_0 (1, 4)
	6 istore (1, 4)
	7 #4 (1, 4)
	8 iload (1, 4)
	9 #4 (1, 4)
	10 iload_3 (1, 4)
	11 if_icmpge (1, 4)
	12 67 (1, 4)
	14 aload_2 (1, 4)
	15 iload (1, 4)
	16 #4 (1, 4)
	17 aaload (1, 4)
	18 astore (1, 4)
	19 #5 (1, 4)
	20 aload (2, 1)
	21 #5 (2, 1)
	22 instanceof (2, 1)
	23 org/apache/commons/math3/optim/MaxEval (2, 1)
	25 ifeq (2, 1)
	26 21 (2, 1)
	28 aload_0 (2, 1)
	29 getfield (2, 1)
	30 org/apache/commons/math3/optim/BaseOptimizer.evaluations:Lorg/apache/commons/math3/util/Incrementor; (2, 1)
	32 aload (2, 1)
	33 #5 (2, 1)
	34 checkcast (2, 1)
	35 org/apache/commons/math3/optim/MaxEval (2, 1)
	37 invokevirtual (2, 1)
	38 org/apache/commons/math3/optim/MaxEval.getMaxEval:()I (2, 1)
	40 invokevirtual (2, 1)
	41 org/apache/commons/math3/util/Incrementor.setMaximalCount:(I)V (2, 1)
	43 goto (2, 1)
	44 29 (2, 1)
	46 aload (2, 1)
	47 #5 (2, 1)
	48 instanceof (2, 1)
	49 org/apache/commons/math3/optim/MaxIter (2, 1)
	51 ifeq (2, 1)
	52 21 (2, 1)
	54 aload_0 (2, 1)
	55 getfield (2, 1)
	56 org/apache/commons/math3/optim/BaseOptimizer.iterations:Lorg/apache/commons/math3/util/Incrementor; (2, 1)
	58 aload (2, 1)
	59 #5 (2, 1)
	60 checkcast (2, 1)
	61 org/apache/commons/math3/optim/MaxIter (2, 1)
	63 invokevirtual (2, 1)
	64 org/apache/commons/math3/optim/MaxIter.getMaxIter:()I (2, 1)
	66 invokevirtual (2, 1)
	67 org/apache/commons/math3/util/Incrementor.setMaximalCount:(I)V (2, 1)
	69 goto (2, 1)
	70 3 (2, 1)
	72 iinc (2, 1)
	73 #4 (2, 1)
	74 -89 (2, 1)
	75 goto (2, 1)
	76 -67 (2, 1)
	78 return (0, 0)

