Method: <init>
	0 aload_0 (0, 0)
	1 iload (0, 0)
	3 ifeq (0, 0)
	6 aload_1 (0, 0)
	7 ifnonnull (0, 0)
	10 aconst_null (0, 0)
	11 goto (0, 0)
	14 aload_1 (0, 0)
	15 invokevirtual (0, 0)
	18 checkcast (0, 0)
	21 goto (0, 0)
	24 aload_1 (0, 0)
	25 dload_2 (0, 0)
	26 invokestatic (0, 0)
	29 invokespecial (0, 0)
	32 return (0, 0)

Method: getPoint
	0 aload_0 (0, 0)
	1 invokevirtual (0, 0)
	4 checkcast (0, 0)
	7 astore_1 (0, 0)
	8 aload_1 (0, 0)
	9 ifnonnull (0, 0)
	12 aconst_null (0, 0)
	13 goto (0, 0)
	16 aload_1 (0, 0)
	17 invokevirtual (0, 0)
	20 checkcast (0, 0)
	23 areturn (0, 0)

Method: getPointRef
	0 aload_0 (0, 0)
	1 invokevirtual (0, 0)
	4 checkcast (0, 0)
	7 areturn (0, 0)

Method: writeReplace
	0 new (0, 0)
	3 dup (0, 0)
	4 aload_0 (0, 0)
	5 invokevirtual (0, 0)
	8 checkcast (0, 0)
	11 aload_0 (0, 0)
	12 invokevirtual (0, 0)
	15 checkcast (0, 0)
	18 invokevirtual (0, 0)
	21 invokespecial (0, 0)
	24 areturn (0, 0)

