Method: <init>
	0 aload_0 (0, 0)
	1 iload_3 (0, 0)
	2 ifeq (0, 0)
	3 21 (0, 0)
	5 aload_1 (0, 0)
	6 ifnonnull (0, 0)
	7 7 (0, 0)
	9 aconst_null (0, 0)
	10 goto (0, 0)
	11 14 (0, 0)
	13 aload_1 (0, 0)
	14 invokevirtual (0, 0)
	15 [D.clone:()Ljava/lang/Object; (0, 0)
	17 checkcast (0, 0)
	18 [D (0, 0)
	20 goto (0, 0)
	21 4 (0, 0)
	23 aload_1 (0, 0)
	24 iload_3 (0, 0)
	25 ifeq (0, 0)
	26 21 (0, 0)
	28 aload_2 (0, 0)
	29 ifnonnull (0, 0)
	30 7 (0, 0)
	32 aconst_null (0, 0)
	33 goto (0, 0)
	34 14 (0, 0)
	36 aload_2 (0, 0)
	37 invokevirtual (0, 0)
	38 [D.clone:()Ljava/lang/Object; (0, 0)
	40 checkcast (0, 0)
	41 [D (0, 0)
	43 goto (0, 0)
	44 4 (0, 0)
	46 aload_2 (0, 0)
	47 invokespecial (0, 0)
	48 org/apache/commons/math3/util/Pair.<init>:(Ljava/lang/Object;Ljava/lang/Object;)V (0, 0)
	50 return (0, 0)

Method: getPoint
	0 aload_0 (0, 0)
	1 invokevirtual (0, 0)
	2 org/apache/commons/math3/optim/PointVectorValuePair.getKey:()Ljava/lang/Object; (0, 0)
	4 checkcast (0, 0)
	5 [D (0, 0)
	7 astore_1 (0, 0)
	8 aload_1 (0, 0)
	9 ifnonnull (0, 0)
	10 7 (0, 0)
	12 aconst_null (0, 0)
	13 goto (0, 0)
	14 10 (0, 0)
	16 aload_1 (0, 0)
	17 invokevirtual (0, 0)
	18 [D.clone:()Ljava/lang/Object; (0, 0)
	20 checkcast (0, 0)
	21 [D (0, 0)
	23 areturn (0, 0)

Method: getPointRef
	0 aload_0 (0, 0)
	1 invokevirtual (0, 0)
	2 org/apache/commons/math3/optim/PointVectorValuePair.getKey:()Ljava/lang/Object; (0, 0)
	4 checkcast (0, 0)
	5 [D (0, 0)
	7 areturn (0, 0)

Method: getValue
	0 aload_0 (0, 0)
	1 invokevirtual (0, 0)
	2 org/apache/commons/math3/optim/PointVectorValuePair.getValue:()[D (0, 0)
	4 areturn (0, 0)

Method: getValueRef
	0 aload_0 (0, 0)
	1 invokespecial (0, 0)
	2 org/apache/commons/math3/util/Pair.getValue:()Ljava/lang/Object; (0, 0)
	4 checkcast (0, 0)
	5 [D (0, 0)
	7 areturn (0, 0)

Method: writeReplace
	0 new (0, 0)
	1 org/apache/commons/math3/optim/PointVectorValuePair$DataTransferObject (0, 0)
	3 dup (0, 0)
	4 aload_0 (0, 0)
	5 invokevirtual (0, 0)
	6 org/apache/commons/math3/optim/PointVectorValuePair.getKey:()Ljava/lang/Object; (0, 0)
	8 checkcast (0, 0)
	9 [D (0, 0)
	11 aload_0 (0, 0)
	12 invokevirtual (0, 0)
	13 org/apache/commons/math3/optim/PointVectorValuePair.getValue:()[D (0, 0)
	15 invokespecial (0, 0)
	16 org/apache/commons/math3/optim/PointVectorValuePair$DataTransferObject.<init>:([D[D)V (0, 0)
	18 areturn (0, 0)

