Method: <init>
	0 aload_0 (0, 0)
	1 dload_1 (0, 0)
	2 dload_3 (0, 0)
	3 invokespecial (0, 0)
	4 org/apache/commons/math3/optim/AbstractConvergenceChecker.<init>:(DD)V (0, 0)
	6 iload (1, 1)
	7 #5 (1, 1)
	8 ifgt (1, 1)
	9 16 (1, 1)
	11 new (1, 1)
	12 org/apache/commons/math3/exception/NotStrictlyPositiveException (1, 1)
	14 dup (1, 1)
	15 iload (1, 1)
	16 #5 (1, 1)
	17 invokestatic (1, 1)
	18 java/lang/Integer.valueOf:(I)Ljava/lang/Integer; (1, 1)
	20 invokespecial (1, 1)
	21 org/apache/commons/math3/exception/NotStrictlyPositiveException.<init>:(Ljava/lang/Number;)V (1, 1)
	23 athrow (1, 1)
	24 aload_0 (0, 0)
	25 iload (0, 0)
	26 #5 (0, 0)
	27 putfield (0, 0)
	28 org/apache/commons/math3/optim/SimpleValueChecker.maxIterationCount:I (0, 0)
	30 return (0, 0)

Method: converged
	0 aload_0 (0, 0)
	1 iload_1 (0, 0)
	2 aload_2 (0, 0)
	3 checkcast (0, 0)
	4 org/apache/commons/math3/optim/PointValuePair (0, 0)
	6 aload_3 (0, 0)
	7 checkcast (0, 0)
	8 org/apache/commons/math3/optim/PointValuePair (0, 0)
	10 invokevirtual (0, 0)
	11 org/apache/commons/math3/optim/SimpleValueChecker.converged:(ILorg/apache/commons/math3/optim/PointValuePair;Lorg/apache/commons/math3/optim/PointValuePair;)Z (0, 0)
	13 ireturn (0, 0)

