Method: makeSwitch
	0 getstatic (0, 0)
	1 Test.parametar:I (0, 0)
	3 lookupswitch (0, 0)
	4 1: 28 (0, 0)
	8 2: 39 (0, 0)
	28 getstatic (0, 0)
	29 java/lang/System.out:Ljava/io/PrintStream; (0, 0)
	31 ldc (0, 0)
	32 1 (0, 0)
	33 invokevirtual (0, 0)
	34 java/io/PrintStream.println:(Ljava/lang/String;)V (0, 0)
	36 goto (0, 0)
	37 22 (0, 0)
	39 getstatic (0, 0)
	40 java/lang/System.out:Ljava/io/PrintStream; (0, 0)
	42 ldc (0, 0)
	43 2 (0, 0)
	44 invokevirtual (0, 0)
	45 java/io/PrintStream.println:(Ljava/lang/String;)V (0, 0)
	47 goto (0, 0)
	48 11 (0, 0)
	50 getstatic (0, 0)
	51 java/lang/System.out:Ljava/io/PrintStream; (0, 0)
	53 ldc (0, 0)
	54 default (0, 0)
	55 invokevirtual (0, 0)
	56 java/io/PrintStream.println:(Ljava/lang/String;)V (0, 0)
	58 iconst_1 (0, 1)
	59 istore_0 (0, 1)
	60 iload_0 (0, 1)
	61 tableswitch (0, 1)
	62 1 88 (0, 1)
	66 2 91 (0, 1)
	70 3 94 (0, 1)
	88 goto (0, 1)
	89 9 (0, 1)
	91 goto (0, 1)
	92 6 (0, 1)
	94 goto (0, 1)
	95 3 (0, 1)
	97 return (0, 1)

Method: sayHello
	0 getstatic (0, 0)
	1 java/lang/System.out:Ljava/io/PrintStream; (0, 0)
	3 ldc (0, 0)
	4 Hello. (0, 0)
	5 invokevirtual (0, 0)
	6 java/io/PrintStream.println:(Ljava/lang/String;)V (0, 0)
	8 return (0, 0)

Method: main
	0 iconst_1 (0, 0)
	1 istore_1 (0, 0)
	2 getstatic (0, 0)
	3 java/lang/System.out:Ljava/io/PrintStream; (0, 0)
	5 new (0, 0)
	6 java/lang/StringBuilder (0, 0)
	8 dup (0, 0)
	9 invokespecial (0, 0)
	10 java/lang/StringBuilder.<init>:()V (0, 0)
	12 ldc (0, 0)
	13  (0, 0)
	14 invokevirtual (0, 0)
	15 java/lang/StringBuilder.append:(Ljava/lang/String;)Ljava/lang/StringBuilder; (0, 0)
	17 iload_1 (0, 0)
	18 invokevirtual (0, 0)
	19 java/lang/StringBuilder.append:(I)Ljava/lang/StringBuilder; (0, 0)
	21 invokevirtual (0, 0)
	22 java/lang/StringBuilder.toString:()Ljava/lang/String; (0, 0)
	24 invokevirtual (0, 0)
	25 java/io/PrintStream.println:(Ljava/lang/String;)V (0, 0)
	27 iload_1 (0, 0)
	28 iconst_1 (0, 0)
	29 if_icmple (0, 0)
	30 10 (0, 0)
	32 iload_1 (0, 0)
	33 iconst_1 (0, 0)
	34 iadd (0, 0)
	35 istore_1 (0, 0)
	36 goto (0, 0)
	37 5 (0, 0)
	39 iconst_0 (0, 0)
	40 istore_1 (0, 0)
	41 iload_1 (0, 0)
	42 bipush (0, 0)
	43 10 (0, 0)
	44 if_icmpge (0, 0)
	45 35 (0, 0)
	47 getstatic (0, 0)
	48 java/lang/System.out:Ljava/io/PrintStream; (0, 0)
	50 new (0, 0)
	51 java/lang/StringBuilder (0, 0)
	53 dup (0, 0)
	54 invokespecial (0, 0)
	55 java/lang/StringBuilder.<init>:()V (0, 0)
	57 ldc (0, 0)
	58 .. (0, 0)
	59 invokevirtual (0, 0)
	60 java/lang/StringBuilder.append:(Ljava/lang/String;)Ljava/lang/StringBuilder; (0, 0)
	62 iload_1 (0, 0)
	63 invokevirtual (0, 0)
	64 java/lang/StringBuilder.append:(I)Ljava/lang/StringBuilder; (0, 0)
	66 invokevirtual (0, 0)
	67 java/lang/StringBuilder.toString:()Ljava/lang/String; (0, 0)
	69 invokevirtual (0, 0)
	70 java/io/PrintStream.println:(Ljava/lang/String;)V (0, 0)
	72 iload_1 (0, 0)
	73 iconst_1 (0, 0)
	74 iadd (0, 0)
	75 istore_1 (0, 0)
	76 goto (0, 0)
	77 -35 (0, 0)
	79 invokestatic (0, 0)
	80 Test.sayHello:()V (0, 0)
	82 return (0, 0)

