Method: <init>
	0 aload_0 (0, 0)
	1 invokespecial (0, 0)
	2 org/apache/commons/math3/linear/RealLinearOperator.<init>:()V (0, 0)
	4 iload_1 (2, 1)
	5 iconst_1 (2, 1)
	6 if_icmpge (2, 1)
	7 15 (2, 1)
	9 new (2, 1)
	10 org/apache/commons/math3/exception/NotStrictlyPositiveException (2, 1)
	12 dup (2, 1)
	13 iload_1 (2, 1)
	14 invokestatic (2, 1)
	15 java/lang/Integer.valueOf:(I)Ljava/lang/Integer; (2, 1)
	17 invokespecial (2, 1)
	18 org/apache/commons/math3/exception/NotStrictlyPositiveException.<init>:(Ljava/lang/Number;)V (2, 1)
	20 athrow (2, 1)
	21 iload_2 (2, 1)
	22 iconst_1 (2, 1)
	23 if_icmpge (2, 1)
	24 15 (2, 1)
	26 new (2, 1)
	27 org/apache/commons/math3/exception/NotStrictlyPositiveException (2, 1)
	29 dup (2, 1)
	30 iload_2 (2, 1)
	31 invokestatic (2, 1)
	32 java/lang/Integer.valueOf:(I)Ljava/lang/Integer; (2, 1)
	34 invokespecial (2, 1)
	35 org/apache/commons/math3/exception/NotStrictlyPositiveException.<init>:(Ljava/lang/Number;)V (2, 1)
	37 athrow (2, 1)
	38 return (0, 0)

Method: add
	0 aload_0 (0, 0)
	1 aload_1 (0, 0)
	2 invokestatic (0, 0)
	3 org/apache/commons/math3/linear/MatrixUtils.checkAdditionCompatible:(Lorg/apache/commons/math3/linear/AnyMatrix;Lorg/apache/commons/math3/linear/AnyMatrix;)V (0, 0)
	5 aload_0 (0, 0)
	6 invokevirtual (0, 0)
	7 org/apache/commons/math3/linear/AbstractRealMatrix.getRowDimension:()I (0, 0)
	9 istore_2 (0, 0)
	10 aload_0 (0, 0)
	11 invokevirtual (0, 0)
	12 org/apache/commons/math3/linear/AbstractRealMatrix.getColumnDimension:()I (0, 0)
	14 istore_3 (0, 0)
	15 aload_0 (0, 0)
	16 iload_2 (0, 0)
	17 iload_3 (0, 0)
	18 invokevirtual (0, 0)
	19 org/apache/commons/math3/linear/AbstractRealMatrix.createMatrix:(II)Lorg/apache/commons/math3/linear/RealMatrix; (0, 0)
	21 astore (0, 0)
	22 #4 (0, 0)
	23 iconst_0 (1, 4)
	24 istore (1, 4)
	25 #5 (1, 4)
	26 iload (1, 4)
	27 #5 (1, 4)
	28 iload_2 (1, 4)
	29 if_icmpge (1, 4)
	30 54 (1, 4)
	32 iconst_0 (2, 4)
	33 istore (2, 4)
	34 #6 (2, 4)
	35 iload (2, 4)
	36 #6 (2, 4)
	37 iload_3 (2, 4)
	38 if_icmpge (2, 4)
	39 39 (2, 4)
	41 aload (2, 4)
	42 #4 (2, 4)
	43 iload (2, 4)
	44 #5 (2, 4)
	45 iload (2, 4)
	46 #6 (2, 4)
	47 aload_0 (2, 4)
	48 iload (2, 4)
	49 #5 (2, 4)
	50 iload (2, 4)
	51 #6 (2, 4)
	52 invokevirtual (2, 4)
	53 org/apache/commons/math3/linear/AbstractRealMatrix.getEntry:(II)D (2, 4)
	55 aload_1 (2, 4)
	56 iload (2, 4)
	57 #5 (2, 4)
	58 iload (2, 4)
	59 #6 (2, 4)
	60 invokeinterface (2, 4)
	61 org/apache/commons/math3/linear/RealMatrix.setEntry:(IID)V (2, 4)
	63 0 (2, 4)
	65 dadd (2, 4)
	66 invokeinterface (2, 4)
	67 org/apache/commons/math3/linear/RealMatrix.checkSubtractionCompatible:(Lorg/apache/commons/math3/linear/AnyMatrix;Lorg/apache/commons/math3/linear/AnyMatrix;)V (2, 4)
	69 0 (2, 4)
	71 iinc (2, 4)
	72 #6 (2, 4)
	73 -89 (2, 4)
	74 goto (2, 4)
	75 -39 (2, 4)
	77 iinc (2, 4)
	78 #5 (2, 4)
	79 -89 (2, 4)
	80 goto (2, 4)
	81 -54 (2, 4)
	83 aload (1, 4)
	84 #4 (1, 4)
	85 areturn (1, 4)

Method: subtract
	0 aload_0 (0, 0)
	1 aload_1 (0, 0)
	2 invokestatic (0, 0)
	3 org/apache/commons/math3/linear/MatrixUtils.checkSubtractionCompatible:(Lorg/apache/commons/math3/linear/AnyMatrix;Lorg/apache/commons/math3/linear/AnyMatrix;)V (0, 0)
	5 aload_0 (0, 0)
	6 invokevirtual (0, 0)
	7 org/apache/commons/math3/linear/AbstractRealMatrix.getRowDimension:()I (0, 0)
	9 istore_2 (0, 0)
	10 aload_0 (0, 0)
	11 invokevirtual (0, 0)
	12 org/apache/commons/math3/linear/AbstractRealMatrix.getColumnDimension:()I (0, 0)
	14 istore_3 (0, 0)
	15 aload_0 (0, 0)
	16 iload_2 (0, 0)
	17 iload_3 (0, 0)
	18 invokevirtual (0, 0)
	19 org/apache/commons/math3/linear/AbstractRealMatrix.createMatrix:(II)Lorg/apache/commons/math3/linear/RealMatrix; (0, 0)
	21 astore (0, 0)
	22 #4 (0, 0)
	23 iconst_0 (1, 4)
	24 istore (1, 4)
	25 #5 (1, 4)
	26 iload (1, 4)
	27 #5 (1, 4)
	28 iload_2 (1, 4)
	29 if_icmpge (1, 4)
	30 54 (1, 4)
	32 iconst_0 (2, 4)
	33 istore (2, 4)
	34 #6 (2, 4)
	35 iload (2, 4)
	36 #6 (2, 4)
	37 iload_3 (2, 4)
	38 if_icmpge (2, 4)
	39 39 (2, 4)
	41 aload (2, 4)
	42 #4 (2, 4)
	43 iload (2, 4)
	44 #5 (2, 4)
	45 iload (2, 4)
	46 #6 (2, 4)
	47 aload_0 (2, 4)
	48 iload (2, 4)
	49 #5 (2, 4)
	50 iload (2, 4)
	51 #6 (2, 4)
	52 invokevirtual (2, 4)
	53 org/apache/commons/math3/linear/AbstractRealMatrix.getEntry:(II)D (2, 4)
	55 aload_1 (2, 4)
	56 iload (2, 4)
	57 #5 (2, 4)
	58 iload (2, 4)
	59 #6 (2, 4)
	60 invokeinterface (2, 4)
	61 org/apache/commons/math3/linear/RealMatrix.setEntry:(IID)V (2, 4)
	63 0 (2, 4)
	65 dsub (2, 4)
	66 invokeinterface (2, 4)
	67 org/apache/commons/math3/linear/RealMatrix.checkSubtractionCompatible:(Lorg/apache/commons/math3/linear/AnyMatrix;Lorg/apache/commons/math3/linear/AnyMatrix;)V (2, 4)
	69 0 (2, 4)
	71 iinc (2, 4)
	72 #6 (2, 4)
	73 -89 (2, 4)
	74 goto (2, 4)
	75 -39 (2, 4)
	77 iinc (2, 4)
	78 #5 (2, 4)
	79 -89 (2, 4)
	80 goto (2, 4)
	81 -54 (2, 4)
	83 aload (1, 4)
	84 #4 (1, 4)
	85 areturn (1, 4)

Method: scalarAdd
	0 aload_0 (0, 0)
	1 invokevirtual (0, 0)
	2 org/apache/commons/math3/linear/AbstractRealMatrix.getRowDimension:()I (0, 0)
	4 istore_3 (0, 0)
	5 aload_0 (0, 0)
	6 invokevirtual (0, 0)
	7 org/apache/commons/math3/linear/AbstractRealMatrix.getColumnDimension:()I (0, 0)
	9 istore (0, 0)
	10 #4 (0, 0)
	11 aload_0 (0, 0)
	12 iload_3 (0, 0)
	13 iload (0, 0)
	14 #4 (0, 0)
	15 invokevirtual (0, 0)
	16 org/apache/commons/math3/linear/AbstractRealMatrix.createMatrix:(II)Lorg/apache/commons/math3/linear/RealMatrix; (0, 0)
	18 astore (0, 0)
	19 #5 (0, 0)
	20 iconst_0 (1, 4)
	21 istore (1, 4)
	22 #6 (1, 4)
	23 iload (1, 4)
	24 #6 (1, 4)
	25 iload_3 (1, 4)
	26 if_icmpge (1, 4)
	27 46 (1, 4)
	29 iconst_0 (2, 4)
	30 istore (2, 4)
	31 #7 (2, 4)
	32 iload (2, 4)
	33 #7 (2, 4)
	34 iload (2, 4)
	35 #4 (2, 4)
	36 if_icmpge (2, 4)
	37 30 (2, 4)
	39 aload (2, 4)
	40 #5 (2, 4)
	41 iload (2, 4)
	42 #6 (2, 4)
	43 iload (2, 4)
	44 #7 (2, 4)
	45 aload_0 (2, 4)
	46 iload (2, 4)
	47 #6 (2, 4)
	48 iload (2, 4)
	49 #7 (2, 4)
	50 invokevirtual (2, 4)
	51 org/apache/commons/math3/linear/AbstractRealMatrix.getEntry:(II)D (2, 4)
	53 dload_1 (2, 4)
	54 dadd (2, 4)
	55 invokeinterface (2, 4)
	56 org/apache/commons/math3/linear/RealMatrix.checkSubtractionCompatible:(Lorg/apache/commons/math3/linear/AnyMatrix;Lorg/apache/commons/math3/linear/AnyMatrix;)V (2, 4)
	58 0 (2, 4)
	60 iinc (2, 4)
	61 #7 (2, 4)
	62 -89 (2, 4)
	63 goto (2, 4)
	64 -31 (2, 4)
	66 iinc (2, 4)
	67 #6 (2, 4)
	68 -89 (2, 4)
	69 goto (2, 4)
	70 -46 (2, 4)
	72 aload (1, 4)
	73 #5 (1, 4)
	74 areturn (1, 4)

Method: scalarMultiply
	0 aload_0 (0, 0)
	1 invokevirtual (0, 0)
	2 org/apache/commons/math3/linear/AbstractRealMatrix.getRowDimension:()I (0, 0)
	4 istore_3 (0, 0)
	5 aload_0 (0, 0)
	6 invokevirtual (0, 0)
	7 org/apache/commons/math3/linear/AbstractRealMatrix.getColumnDimension:()I (0, 0)
	9 istore (0, 0)
	10 #4 (0, 0)
	11 aload_0 (0, 0)
	12 iload_3 (0, 0)
	13 iload (0, 0)
	14 #4 (0, 0)
	15 invokevirtual (0, 0)
	16 org/apache/commons/math3/linear/AbstractRealMatrix.createMatrix:(II)Lorg/apache/commons/math3/linear/RealMatrix; (0, 0)
	18 astore (0, 0)
	19 #5 (0, 0)
	20 iconst_0 (1, 4)
	21 istore (1, 4)
	22 #6 (1, 4)
	23 iload (1, 4)
	24 #6 (1, 4)
	25 iload_3 (1, 4)
	26 if_icmpge (1, 4)
	27 46 (1, 4)
	29 iconst_0 (2, 4)
	30 istore (2, 4)
	31 #7 (2, 4)
	32 iload (2, 4)
	33 #7 (2, 4)
	34 iload (2, 4)
	35 #4 (2, 4)
	36 if_icmpge (2, 4)
	37 30 (2, 4)
	39 aload (2, 4)
	40 #5 (2, 4)
	41 iload (2, 4)
	42 #6 (2, 4)
	43 iload (2, 4)
	44 #7 (2, 4)
	45 aload_0 (2, 4)
	46 iload (2, 4)
	47 #6 (2, 4)
	48 iload (2, 4)
	49 #7 (2, 4)
	50 invokevirtual (2, 4)
	51 org/apache/commons/math3/linear/AbstractRealMatrix.getEntry:(II)D (2, 4)
	53 dload_1 (2, 4)
	54 dmul (2, 4)
	55 invokeinterface (2, 4)
	56 org/apache/commons/math3/linear/RealMatrix.checkSubtractionCompatible:(Lorg/apache/commons/math3/linear/AnyMatrix;Lorg/apache/commons/math3/linear/AnyMatrix;)V (2, 4)
	58 0 (2, 4)
	60 iinc (2, 4)
	61 #7 (2, 4)
	62 -89 (2, 4)
	63 goto (2, 4)
	64 -31 (2, 4)
	66 iinc (2, 4)
	67 #6 (2, 4)
	68 -89 (2, 4)
	69 goto (2, 4)
	70 -46 (2, 4)
	72 aload (1, 4)
	73 #5 (1, 4)
	74 areturn (1, 4)

Method: multiply
	0 aload_0 (0, 0)
	1 aload_1 (0, 0)
	2 invokestatic (0, 0)
	3 org/apache/commons/math3/linear/MatrixUtils.checkMultiplicationCompatible:(Lorg/apache/commons/math3/linear/AnyMatrix;Lorg/apache/commons/math3/linear/AnyMatrix;)V (0, 0)
	5 aload_0 (0, 0)
	6 invokevirtual (0, 0)
	7 org/apache/commons/math3/linear/AbstractRealMatrix.getRowDimension:()I (0, 0)
	9 istore_2 (0, 0)
	10 aload_1 (0, 0)
	11 invokeinterface (0, 0)
	12 org/apache/commons/math3/linear/RealMatrix.createMatrix:(II)Lorg/apache/commons/math3/linear/RealMatrix; (0, 0)
	14 0 (0, 0)
	16 istore_3 (0, 0)
	17 aload_0 (0, 0)
	18 invokevirtual (0, 0)
	19 org/apache/commons/math3/linear/AbstractRealMatrix.getColumnDimension:()I (0, 0)
	21 istore (0, 0)
	22 #4 (0, 0)
	23 aload_0 (0, 0)
	24 iload_2 (0, 0)
	25 iload_3 (0, 0)
	26 invokevirtual (0, 0)
	27 org/apache/commons/math3/linear/AbstractRealMatrix.createMatrix:(II)Lorg/apache/commons/math3/linear/RealMatrix; (0, 0)
	29 astore (0, 0)
	30 #5 (0, 0)
	31 iconst_0 (1, 4)
	32 istore (1, 4)
	33 #6 (1, 4)
	34 iload (1, 4)
	35 #6 (1, 4)
	36 iload_2 (1, 4)
	37 if_icmpge (1, 4)
	38 80 (1, 4)
	40 iconst_0 (2, 4)
	41 istore (2, 4)
	42 #7 (2, 4)
	43 iload (2, 4)
	44 #7 (2, 4)
	45 iload_3 (2, 4)
	46 if_icmpge (2, 4)
	47 65 (2, 4)
	49 dconst_0 (2, 4)
	50 dstore (2, 4)
	51 #8 (2, 4)
	52 iconst_0 (3, 4)
	53 istore (3, 4)
	54 #10 (3, 4)
	55 iload (3, 4)
	56 #10 (3, 4)
	57 iload (3, 4)
	58 #4 (3, 4)
	59 if_icmpge (3, 4)
	60 33 (3, 4)
	62 dload (3, 4)
	63 #8 (3, 4)
	64 aload_0 (3, 4)
	65 iload (3, 4)
	66 #6 (3, 4)
	67 iload (3, 4)
	68 #10 (3, 4)
	69 invokevirtual (3, 4)
	70 org/apache/commons/math3/linear/AbstractRealMatrix.getEntry:(II)D (3, 4)
	72 aload_1 (3, 4)
	73 iload (3, 4)
	74 #10 (3, 4)
	75 iload (3, 4)
	76 #7 (3, 4)
	77 invokeinterface (3, 4)
	78 org/apache/commons/math3/linear/RealMatrix.setEntry:(IID)V (3, 4)
	80 0 (3, 4)
	82 dmul (3, 4)
	83 dadd (3, 4)
	84 dstore (3, 4)
	85 #8 (3, 4)
	86 iinc (3, 4)
	87 #10 (3, 4)
	88 -89 (3, 4)
	89 goto (3, 4)
	90 -34 (3, 4)
	92 aload (2, 4)
	93 #5 (2, 4)
	94 iload (2, 4)
	95 #6 (2, 4)
	96 iload (2, 4)
	97 #7 (2, 4)
	98 dload (2, 4)
	99 #8 (2, 4)
	100 invokeinterface (2, 4)
	101 org/apache/commons/math3/linear/RealMatrix.checkSubtractionCompatible:(Lorg/apache/commons/math3/linear/AnyMatrix;Lorg/apache/commons/math3/linear/AnyMatrix;)V (2, 4)
	103 0 (2, 4)
	105 iinc (2, 4)
	106 #7 (2, 4)
	107 -89 (2, 4)
	108 goto (2, 4)
	109 -65 (2, 4)
	111 iinc (2, 4)
	112 #6 (2, 4)
	113 -89 (2, 4)
	114 goto (2, 4)
	115 -80 (2, 4)
	117 aload (1, 4)
	118 #5 (1, 4)
	119 areturn (1, 4)

Method: preMultiply
	0 new (0, 0)
	1 org/apache/commons/math3/linear/ArrayRealVector (0, 0)
	3 dup (0, 0)
	4 aload_0 (0, 0)
	5 aload_1 (0, 0)
	6 checkcast (0, 0)
	7 org/apache/commons/math3/linear/ArrayRealVector (0, 0)
	9 invokevirtual (0, 0)
	10 org/apache/commons/math3/linear/ArrayRealVector.getDataRef:()[D (0, 0)
	12 invokevirtual (0, 0)
	13 org/apache/commons/math3/linear/AbstractRealMatrix.preMultiply:([D)[D (0, 0)
	15 iconst_0 (0, 0)
	16 invokespecial (0, 0)
	17 org/apache/commons/math3/linear/ArrayRealVector.<init>:([DZ)V (0, 0)
	19 areturn (0, 0)
	20 astore_2 (0, 0)
	21 aload_0 (0, 0)
	22 invokevirtual (0, 0)
	23 org/apache/commons/math3/linear/AbstractRealMatrix.getRowDimension:()I (0, 0)
	25 istore_3 (0, 0)
	26 aload_0 (0, 0)
	27 invokevirtual (0, 0)
	28 org/apache/commons/math3/linear/AbstractRealMatrix.getColumnDimension:()I (0, 0)
	30 istore (0, 0)
	31 #4 (0, 0)
	32 aload_1 (1, 1)
	33 invokevirtual (1, 1)
	34 org/apache/commons/math3/linear/RealVector.getDimension:()I (1, 1)
	36 iload_3 (1, 1)
	37 if_icmpeq (1, 1)
	38 16 (1, 1)
	40 new (1, 1)
	41 org/apache/commons/math3/exception/DimensionMismatchException (1, 1)
	43 dup (1, 1)
	44 aload_1 (1, 1)
	45 invokevirtual (1, 1)
	46 org/apache/commons/math3/linear/RealVector.getDimension:()I (1, 1)
	48 iload_3 (1, 1)
	49 invokespecial (1, 1)
	50 org/apache/commons/math3/exception/DimensionMismatchException.<init>:(II)V (1, 1)
	52 athrow (1, 1)
	53 iload (0, 0)
	54 #4 (0, 0)
	55 newarray (0, 0)
	56 7 (0, 0)
	57 astore (0, 0)
	58 #5 (0, 0)
	59 iconst_0 (1, 4)
	60 istore (1, 4)
	61 #6 (1, 4)
	62 iload (1, 4)
	63 #6 (1, 4)
	64 iload (1, 4)
	65 #4 (1, 4)
	66 if_icmpge (1, 4)
	67 54 (1, 4)
	69 dconst_0 (1, 4)
	70 dstore (1, 4)
	71 #7 (1, 4)
	72 iconst_0 (2, 4)
	73 istore (2, 4)
	74 #9 (2, 4)
	75 iload (2, 4)
	76 #9 (2, 4)
	77 iload_3 (2, 4)
	78 if_icmpge (2, 4)
	79 29 (2, 4)
	81 dload (2, 4)
	82 #7 (2, 4)
	83 aload_0 (2, 4)
	84 iload (2, 4)
	85 #9 (2, 4)
	86 iload (2, 4)
	87 #6 (2, 4)
	88 invokevirtual (2, 4)
	89 org/apache/commons/math3/linear/AbstractRealMatrix.getEntry:(II)D (2, 4)
	91 aload_1 (2, 4)
	92 iload (2, 4)
	93 #9 (2, 4)
	94 invokevirtual (2, 4)
	95 org/apache/commons/math3/linear/RealVector.getEntry:(I)D (2, 4)
	97 dmul (2, 4)
	98 dadd (2, 4)
	99 dstore (2, 4)
	100 #7 (2, 4)
	101 iinc (2, 4)
	102 #9 (2, 4)
	103 -89 (2, 4)
	104 goto (2, 4)
	105 -29 (2, 4)
	107 aload (1, 4)
	108 #5 (1, 4)
	109 iload (1, 4)
	110 #6 (1, 4)
	111 dload (1, 4)
	112 #7 (1, 4)
	113 dastore (1, 4)
	114 iinc (1, 4)
	115 #6 (1, 4)
	116 -89 (1, 4)
	117 goto (1, 4)
	118 -55 (1, 4)
	120 new (0, 0)
	121 org/apache/commons/math3/linear/ArrayRealVector (0, 0)
	123 dup (0, 0)
	124 aload (0, 0)
	125 #5 (0, 0)
	126 iconst_0 (0, 0)
	127 invokespecial (0, 0)
	128 org/apache/commons/math3/linear/ArrayRealVector.<init>:([DZ)V (0, 0)
	130 areturn (0, 0)

Method: power
	0 iload_1 (1, 1)
	1 ifge (1, 1)
	2 18 (1, 1)
	4 new (1, 1)
	5 org/apache/commons/math3/exception/NotPositiveException (1, 1)
	7 dup (1, 1)
	8 getstatic (1, 1)
	9 org/apache/commons/math3/exception/util/LocalizedFormats.NOT_POSITIVE_EXPONENT:Lorg/apache/commons/math3/exception/util/LocalizedFormats; (1, 1)
	11 iload_1 (1, 1)
	12 invokestatic (1, 1)
	13 java/lang/Integer.valueOf:(I)Ljava/lang/Integer; (1, 1)
	15 invokespecial (1, 1)
	16 org/apache/commons/math3/exception/NotPositiveException.<init>:(Lorg/apache/commons/math3/exception/util/Localizable;Ljava/lang/Number;)V (1, 1)
	18 athrow (1, 1)
	19 aload_0 (1, 1)
	20 invokevirtual (1, 1)
	21 org/apache/commons/math3/linear/AbstractRealMatrix.isSquare:()Z (1, 1)
	23 ifne (1, 1)
	24 19 (1, 1)
	26 new (1, 1)
	27 org/apache/commons/math3/linear/NonSquareMatrixException (1, 1)
	29 dup (1, 1)
	30 aload_0 (1, 1)
	31 invokevirtual (1, 1)
	32 org/apache/commons/math3/linear/AbstractRealMatrix.getRowDimension:()I (1, 1)
	34 aload_0 (1, 1)
	35 invokevirtual (1, 1)
	36 org/apache/commons/math3/linear/AbstractRealMatrix.getColumnDimension:()I (1, 1)
	38 invokespecial (1, 1)
	39 org/apache/commons/math3/linear/NonSquareMatrixException.<init>:(II)V (1, 1)
	41 athrow (1, 1)
	42 iload_1 (1, 1)
	43 ifne (1, 1)
	44 11 (1, 1)
	46 aload_0 (1, 1)
	47 invokevirtual (1, 1)
	48 org/apache/commons/math3/linear/AbstractRealMatrix.getRowDimension:()I (1, 1)
	50 invokestatic (1, 1)
	51 org/apache/commons/math3/linear/MatrixUtils.createRealIdentityMatrix:(I)Lorg/apache/commons/math3/linear/RealMatrix; (1, 1)
	53 areturn (1, 1)
	54 iload_1 (1, 1)
	55 iconst_1 (1, 1)
	56 if_icmpne (1, 1)
	57 8 (1, 1)
	59 aload_0 (1, 1)
	60 invokevirtual (1, 1)
	61 org/apache/commons/math3/linear/AbstractRealMatrix.copy:()Lorg/apache/commons/math3/linear/RealMatrix; (1, 1)
	63 areturn (1, 1)
	64 iload_1 (0, 0)
	65 iconst_1 (0, 0)
	66 isub (0, 0)
	67 istore_2 (0, 0)
	68 iload_2 (0, 4)
	69 invokestatic (0, 4)
	70 java/lang/Integer.toBinaryString:(I)Ljava/lang/String; (0, 4)
	72 invokevirtual (0, 4)
	73 java/lang/String.toCharArray:()[C (0, 4)
	75 astore_3 (0, 4)
	76 new (0, 4)
	77 java/util/ArrayList (0, 4)
	79 dup (0, 4)
	80 invokespecial (0, 4)
	81 java/util/ArrayList.<init>:()V (0, 4)
	83 astore (0, 4)
	84 #4 (0, 4)
	85 iconst_m1 (0, 4)
	86 istore (0, 4)
	87 #5 (0, 4)
	88 iconst_0 (1, 4)
	89 istore (1, 4)
	90 #6 (1, 4)
	91 iload (1, 4)
	92 #6 (1, 4)
	93 aload_3 (1, 4)
	94 arraylength (1, 4)
	95 if_icmpge (1, 4)
	96 48 (1, 4)
	98 aload_3 (2, 1)
	99 iload (2, 1)
	100 #6 (2, 1)
	101 caload (2, 1)
	102 bipush (2, 1)
	103 49 (2, 1)
	104 if_icmpne (2, 1)
	105 33 (2, 1)
	107 aload_3 (2, 1)
	108 arraylength (2, 1)
	109 iload (2, 1)
	110 #6 (2, 1)
	111 isub (2, 1)
	112 iconst_1 (2, 1)
	113 isub (2, 1)
	114 istore (2, 1)
	115 #7 (2, 1)
	116 aload (2, 1)
	117 #4 (2, 1)
	118 iload (2, 1)
	119 #7 (2, 1)
	120 invokestatic (2, 1)
	121 java/lang/Integer.valueOf:(I)Ljava/lang/Integer; (2, 1)
	123 invokevirtual (2, 1)
	124 java/util/ArrayList.add:(Ljava/lang/Object;)Z (2, 1)
	126 pop (2, 1)
	127 iload (3, 1)
	128 #5 (3, 1)
	129 iconst_m1 (3, 1)
	130 if_icmpne (3, 1)
	131 7 (3, 1)
	133 iload (3, 1)
	134 #7 (3, 1)
	135 istore (3, 1)
	136 #5 (3, 1)
	137 iinc (3, 1)
	138 #6 (3, 1)
	139 -89 (3, 1)
	140 goto (3, 1)
	141 -49 (3, 1)
	143 iload (2, 1)
	144 #5 (2, 1)
	145 iconst_1 (2, 1)
	146 iadd (2, 1)
	147 anewarray (2, 1)
	148 org/apache/commons/math3/linear/RealMatrix (2, 1)
	150 astore (2, 1)
	151 #6 (2, 1)
	152 aload (2, 1)
	153 #6 (2, 1)
	154 iconst_0 (2, 1)
	155 aload_0 (2, 1)
	156 invokevirtual (2, 1)
	157 org/apache/commons/math3/linear/AbstractRealMatrix.copy:()Lorg/apache/commons/math3/linear/RealMatrix; (2, 1)
	159 aastore (2, 1)
	160 iconst_1 (3, 4)
	161 istore (3, 4)
	162 #7 (3, 4)
	163 iload (3, 4)
	164 #7 (3, 4)
	165 iload (3, 4)
	166 #5 (3, 4)
	167 if_icmpgt (3, 4)
	168 33 (3, 4)
	170 aload (3, 4)
	171 #6 (3, 4)
	172 iload (3, 4)
	173 #7 (3, 4)
	174 aload (3, 4)
	175 #6 (3, 4)
	176 iload (3, 4)
	177 #7 (3, 4)
	178 iconst_1 (3, 4)
	179 isub (3, 4)
	180 aaload (3, 4)
	181 aload (3, 4)
	182 #6 (3, 4)
	183 iload (3, 4)
	184 #7 (3, 4)
	185 iconst_1 (3, 4)
	186 isub (3, 4)
	187 aaload (3, 4)
	188 invokeinterface (3, 4)
	189 org/apache/commons/math3/linear/RealMatrix.org/apache/commons/math3/exception/NotPositiveException (3, 4)
	191 0 (3, 4)
	193 aastore (3, 4)
	194 iinc (3, 4)
	195 #7 (3, 4)
	196 -89 (3, 4)
	197 goto (3, 4)
	198 -34 (3, 4)
	200 aload_0 (2, 1)
	201 invokevirtual (2, 1)
	202 org/apache/commons/math3/linear/AbstractRealMatrix.copy:()Lorg/apache/commons/math3/linear/RealMatrix; (2, 1)
	204 astore (2, 1)
	205 #7 (2, 1)
	206 aload (3, 4)
	207 #4 (3, 4)
	208 invokevirtual (3, 4)
	209 java/util/ArrayList.iterator:()Ljava/util/Iterator; (3, 4)
	211 astore (3, 4)
	212 #8 (3, 4)
	213 aload (3, 4)
	214 #8 (3, 4)
	215 invokeinterface (3, 4)
	216 java/util/Iterator.next:()Ljava/lang/Object; (3, 4)
	218 0 (3, 4)
	220 ifeq (3, 4)
	221 35 (3, 4)
	223 aload (3, 4)
	224 #8 (3, 4)
	225 invokeinterface (3, 4)
	226 java/util/Iterator.java/lang/Integer (3, 4)
	228 0 (3, 4)
	230 checkcast (3, 4)
	231 java/lang/Integer (3, 4)
	233 astore (3, 4)
	234 #9 (3, 4)
	235 aload (3, 4)
	236 #7 (3, 4)
	237 aload (3, 4)
	238 #6 (3, 4)
	239 aload (3, 4)
	240 #9 (3, 4)
	241 invokevirtual (3, 4)
	242 java/lang/Integer.intValue:()I (3, 4)
	244 aaload (3, 4)
	245 invokeinterface (3, 4)
	246 org/apache/commons/math3/linear/RealMatrix.org/apache/commons/math3/exception/NotPositiveException (3, 4)
	248 0 (3, 4)
	250 astore (3, 4)
	251 #7 (3, 4)
	252 goto (2, 1)
	253 -39 (2, 1)
	255 aload (2, 1)
	256 #7 (2, 1)
	257 areturn (2, 1)

Method: getData
	0 aload_0 (0, 0)
	1 invokevirtual (0, 0)
	2 org/apache/commons/math3/linear/AbstractRealMatrix.getRowDimension:()I (0, 0)
	4 aload_0 (0, 0)
	5 invokevirtual (0, 0)
	6 org/apache/commons/math3/linear/AbstractRealMatrix.getColumnDimension:()I (0, 0)
	8 multianewarray (0, 0)
	9 [[D (0, 0)
	11 76 (0, 0)
	12 astore_1 (0, 0)
	13 iconst_0 (1, 4)
	14 istore_2 (1, 4)
	15 iload_2 (1, 4)
	16 aload_1 (1, 4)
	17 arraylength (1, 4)
	18 if_icmpge (1, 4)
	19 40 (1, 4)
	21 aload_1 (1, 4)
	22 iload_2 (1, 4)
	23 aaload (1, 4)
	24 astore_3 (1, 4)
	25 iconst_0 (2, 4)
	26 istore (2, 4)
	27 #4 (2, 4)
	28 iload (2, 4)
	29 #4 (2, 4)
	30 aload_3 (2, 4)
	31 arraylength (2, 4)
	32 if_icmpge (2, 4)
	33 20 (2, 4)
	35 aload_3 (2, 4)
	36 iload (2, 4)
	37 #4 (2, 4)
	38 aload_0 (2, 4)
	39 iload_2 (2, 4)
	40 iload (2, 4)
	41 #4 (2, 4)
	42 invokevirtual (2, 4)
	43 org/apache/commons/math3/linear/AbstractRealMatrix.getEntry:(II)D (2, 4)
	45 dastore (2, 4)
	46 iinc (2, 4)
	47 #4 (2, 4)
	48 -89 (2, 4)
	49 goto (2, 4)
	50 -21 (2, 4)
	52 iinc (2, 4)
	53 #2 (2, 4)
	54 -89 (2, 4)
	55 goto (2, 4)
	56 -40 (2, 4)
	58 aload_1 (1, 4)
	59 areturn (1, 4)

Method: getNorm
	0 aload_0 (0, 0)
	1 new (0, 0)
	2 org/apache/commons/math3/linear/AbstractRealMatrix$1 (0, 0)
	4 dup (0, 0)
	5 aload_0 (0, 0)
	6 invokespecial (0, 0)
	7 org/apache/commons/math3/linear/AbstractRealMatrix$1.<init>:(Lorg/apache/commons/math3/linear/AbstractRealMatrix;)V (0, 0)
	9 invokevirtual (0, 0)
	10 org/apache/commons/math3/linear/AbstractRealMatrix.walkInColumnOrder:(Lorg/apache/commons/math3/linear/RealMatrixPreservingVisitor;)D (0, 0)
	12 dreturn (0, 0)

Method: getFrobeniusNorm
	0 aload_0 (0, 0)
	1 new (0, 0)
	2 org/apache/commons/math3/linear/AbstractRealMatrix$2 (0, 0)
	4 dup (0, 0)
	5 aload_0 (0, 0)
	6 invokespecial (0, 0)
	7 org/apache/commons/math3/linear/AbstractRealMatrix$2.<init>:(Lorg/apache/commons/math3/linear/AbstractRealMatrix;)V (0, 0)
	9 invokevirtual (0, 0)
	10 org/apache/commons/math3/linear/AbstractRealMatrix.walkInOptimizedOrder:(Lorg/apache/commons/math3/linear/RealMatrixPreservingVisitor;)D (0, 0)
	12 dreturn (0, 0)

Method: getSubMatrix
	0 aload_0 (0, 0)
	1 aload_1 (0, 0)
	2 aload_2 (0, 0)
	3 invokestatic (0, 0)
	4 org/apache/commons/math3/linear/MatrixUtils.checkSubMatrixIndex:(Lorg/apache/commons/math3/linear/AnyMatrix;[I[I)V (0, 0)
	6 aload_0 (0, 0)
	7 aload_1 (0, 0)
	8 arraylength (0, 0)
	9 aload_2 (0, 0)
	10 arraylength (0, 0)
	11 invokevirtual (0, 0)
	12 org/apache/commons/math3/linear/AbstractRealMatrix.createMatrix:(II)Lorg/apache/commons/math3/linear/RealMatrix; (0, 0)
	14 astore_3 (0, 0)
	15 aload_3 (0, 0)
	16 new (0, 0)
	17 org/apache/commons/math3/linear/AbstractRealMatrix$3 (0, 0)
	19 dup (0, 0)
	20 aload_0 (0, 0)
	21 aload_1 (0, 0)
	22 aload_2 (0, 0)
	23 invokespecial (0, 0)
	24 org/apache/commons/math3/linear/AbstractRealMatrix$3.<init>:(Lorg/apache/commons/math3/linear/AbstractRealMatrix;[I[I)V (0, 0)
	26 invokeinterface (0, 0)
	27 org/apache/commons/math3/linear/RealMatrix.org/apache/commons/math3/linear/MatrixDimensionMismatchException (0, 0)
	29 0 (0, 0)
	31 pop2 (0, 0)
	32 aload_3 (0, 0)
	33 areturn (0, 0)

Method: copySubMatrix
	0 aload_0 (0, 0)
	1 aload_1 (0, 0)
	2 aload_2 (0, 0)
	3 invokestatic (0, 0)
	4 org/apache/commons/math3/linear/MatrixUtils.checkSubMatrixIndex:(Lorg/apache/commons/math3/linear/AnyMatrix;[I[I)V (0, 0)
	6 aload_2 (0, 0)
	7 arraylength (0, 0)
	8 istore (0, 0)
	9 #4 (0, 0)
	10 aload_3 (0, 1)
	11 arraylength (0, 1)
	12 aload_1 (0, 1)
	13 arraylength (0, 1)
	14 if_icmplt (0, 1)
	15 12 (0, 1)
	17 aload_3 (0, 1)
	18 iconst_0 (0, 1)
	19 aaload (0, 1)
	20 arraylength (0, 1)
	21 iload (0, 1)
	22 #4 (0, 1)
	23 if_icmpge (0, 1)
	24 21 (0, 1)
	26 new (0, 1)
	27 org/apache/commons/math3/linear/MatrixDimensionMismatchException (0, 1)
	29 dup (0, 1)
	30 aload_3 (0, 1)
	31 arraylength (0, 1)
	32 aload_3 (0, 1)
	33 iconst_0 (0, 1)
	34 aaload (0, 1)
	35 arraylength (0, 1)
	36 aload_1 (0, 1)
	37 arraylength (0, 1)
	38 aload_2 (0, 1)
	39 arraylength (0, 1)
	40 invokespecial (0, 1)
	41 org/apache/commons/math3/linear/MatrixDimensionMismatchException.<init>:(IIII)V (0, 1)
	43 athrow (0, 1)
	44 iconst_0 (1, 4)
	45 istore (1, 4)
	46 #5 (1, 4)
	47 iload (1, 4)
	48 #5 (1, 4)
	49 aload_1 (1, 4)
	50 arraylength (1, 4)
	51 if_icmpge (1, 4)
	52 73 (1, 4)
	54 aload_3 (1, 4)
	55 iload (1, 4)
	56 #5 (1, 4)
	57 aaload (1, 4)
	58 astore (1, 4)
	59 #6 (1, 4)
	60 aload (2, 1)
	61 #6 (2, 1)
	62 arraylength (2, 1)
	63 iload (2, 1)
	64 #4 (2, 1)
	65 if_icmpge (2, 1)
	66 20 (2, 1)
	68 new (2, 1)
	69 org/apache/commons/math3/linear/MatrixDimensionMismatchException (2, 1)
	71 dup (2, 1)
	72 aload_3 (2, 1)
	73 arraylength (2, 1)
	74 aload (2, 1)
	75 #6 (2, 1)
	76 arraylength (2, 1)
	77 aload_1 (2, 1)
	78 arraylength (2, 1)
	79 aload_2 (2, 1)
	80 arraylength (2, 1)
	81 invokespecial (2, 1)
	82 org/apache/commons/math3/linear/MatrixDimensionMismatchException.<init>:(IIII)V (2, 1)
	84 athrow (2, 1)
	85 iconst_0 (2, 4)
	86 istore (2, 4)
	87 #7 (2, 4)
	88 iload (2, 4)
	89 #7 (2, 4)
	90 aload_2 (2, 4)
	91 arraylength (2, 4)
	92 if_icmpge (2, 4)
	93 26 (2, 4)
	95 aload (2, 4)
	96 #6 (2, 4)
	97 iload (2, 4)
	98 #7 (2, 4)
	99 aload_0 (2, 4)
	100 aload_1 (2, 4)
	101 iload (2, 4)
	102 #5 (2, 4)
	103 iaload (2, 4)
	104 aload_2 (2, 4)
	105 iload (2, 4)
	106 #7 (2, 4)
	107 iaload (2, 4)
	108 invokevirtual (2, 4)
	109 org/apache/commons/math3/linear/AbstractRealMatrix.getEntry:(II)D (2, 4)
	111 dastore (2, 4)
	112 iinc (2, 4)
	113 #7 (2, 4)
	114 -89 (2, 4)
	115 goto (2, 4)
	116 -27 (2, 4)
	118 iinc (2, 4)
	119 #5 (2, 4)
	120 -89 (2, 4)
	121 goto (2, 4)
	122 -74 (2, 4)
	124 return (0, 1)

Method: setSubMatrix
	0 aload_1 (0, 0)
	1 invokestatic (0, 0)
	2 org/apache/commons/math3/util/MathUtils.checkNotNull:(Ljava/lang/Object;)V (0, 0)
	4 aload_1 (0, 0)
	5 arraylength (0, 0)
	6 istore (0, 0)
	7 #4 (0, 0)
	8 iload (1, 1)
	9 #4 (1, 1)
	10 ifne (1, 1)
	11 14 (1, 1)
	13 new (1, 1)
	14 org/apache/commons/math3/exception/NoDataException (1, 1)
	16 dup (1, 1)
	17 getstatic (1, 1)
	18 org/apache/commons/math3/exception/util/LocalizedFormats.AT_LEAST_ONE_ROW:Lorg/apache/commons/math3/exception/util/LocalizedFormats; (1, 1)
	20 invokespecial (1, 1)
	21 org/apache/commons/math3/exception/NoDataException.<init>:(Lorg/apache/commons/math3/exception/util/Localizable;)V (1, 1)
	23 athrow (1, 1)
	24 aload_1 (0, 0)
	25 iconst_0 (0, 0)
	26 aaload (0, 0)
	27 arraylength (0, 0)
	28 istore (0, 0)
	29 #5 (0, 0)
	30 iload (1, 1)
	31 #5 (1, 1)
	32 ifne (1, 1)
	33 14 (1, 1)
	35 new (1, 1)
	36 org/apache/commons/math3/exception/NoDataException (1, 1)
	38 dup (1, 1)
	39 getstatic (1, 1)
	40 org/apache/commons/math3/exception/util/LocalizedFormats.AT_LEAST_ONE_COLUMN:Lorg/apache/commons/math3/exception/util/LocalizedFormats; (1, 1)
	42 invokespecial (1, 1)
	43 org/apache/commons/math3/exception/NoDataException.<init>:(Lorg/apache/commons/math3/exception/util/Localizable;)V (1, 1)
	45 athrow (1, 1)
	46 iconst_1 (1, 4)
	47 istore (1, 4)
	48 #6 (1, 4)
	49 iload (1, 4)
	50 #6 (1, 4)
	51 iload (1, 4)
	52 #4 (1, 4)
	53 if_icmpge (1, 4)
	54 34 (1, 4)
	56 aload_1 (2, 1)
	57 iload (2, 1)
	58 #6 (2, 1)
	59 aaload (2, 1)
	60 arraylength (2, 1)
	61 iload (2, 1)
	62 #5 (2, 1)
	63 if_icmpeq (2, 1)
	64 18 (2, 1)
	66 new (2, 1)
	67 org/apache/commons/math3/exception/DimensionMismatchException (2, 1)
	69 dup (2, 1)
	70 iload (2, 1)
	71 #5 (2, 1)
	72 aload_1 (2, 1)
	73 iload (2, 1)
	74 #6 (2, 1)
	75 aaload (2, 1)
	76 arraylength (2, 1)
	77 invokespecial (2, 1)
	78 org/apache/commons/math3/exception/DimensionMismatchException.<init>:(II)V (2, 1)
	80 athrow (2, 1)
	81 iinc (2, 1)
	82 #6 (2, 1)
	83 -89 (2, 1)
	84 goto (2, 1)
	85 -35 (2, 1)
	87 aload_0 (1, 4)
	88 iload_2 (1, 4)
	89 invokestatic (1, 4)
	90 org/apache/commons/math3/linear/MatrixUtils.checkRowIndex:(Lorg/apache/commons/math3/linear/AnyMatrix;I)V (1, 4)
	92 aload_0 (1, 4)
	93 iload_3 (1, 4)
	94 invokestatic (1, 4)
	95 org/apache/commons/math3/linear/MatrixUtils.checkColumnIndex:(Lorg/apache/commons/math3/linear/AnyMatrix;I)V (1, 4)
	97 aload_0 (1, 4)
	98 iload (1, 4)
	99 #4 (1, 4)
	100 iload_2 (1, 4)
	101 iadd (1, 4)
	102 iconst_1 (1, 4)
	103 isub (1, 4)
	104 invokestatic (1, 4)
	105 org/apache/commons/math3/linear/MatrixUtils.checkRowIndex:(Lorg/apache/commons/math3/linear/AnyMatrix;I)V (1, 4)
	107 aload_0 (1, 4)
	108 iload (1, 4)
	109 #5 (1, 4)
	110 iload_3 (1, 4)
	111 iadd (1, 4)
	112 iconst_1 (1, 4)
	113 isub (1, 4)
	114 invokestatic (1, 4)
	115 org/apache/commons/math3/linear/MatrixUtils.checkColumnIndex:(Lorg/apache/commons/math3/linear/AnyMatrix;I)V (1, 4)
	117 iconst_0 (2, 4)
	118 istore (2, 4)
	119 #6 (2, 4)
	120 iload (2, 4)
	121 #6 (2, 4)
	122 iload (2, 4)
	123 #4 (2, 4)
	124 if_icmpge (2, 4)
	125 44 (2, 4)
	127 iconst_0 (3, 4)
	128 istore (3, 4)
	129 #7 (3, 4)
	130 iload (3, 4)
	131 #7 (3, 4)
	132 iload (3, 4)
	133 #5 (3, 4)
	134 if_icmpge (3, 4)
	135 28 (3, 4)
	137 aload_0 (3, 4)
	138 iload_2 (3, 4)
	139 iload (3, 4)
	140 #6 (3, 4)
	141 iadd (3, 4)
	142 iload_3 (3, 4)
	143 iload (3, 4)
	144 #7 (3, 4)
	145 iadd (3, 4)
	146 aload_1 (3, 4)
	147 iload (3, 4)
	148 #6 (3, 4)
	149 aaload (3, 4)
	150 iload (3, 4)
	151 #7 (3, 4)
	152 daload (3, 4)
	153 invokevirtual (3, 4)
	154 org/apache/commons/math3/linear/AbstractRealMatrix.setEntry:(IID)V (3, 4)
	156 iinc (3, 4)
	157 #7 (3, 4)
	158 -89 (3, 4)
	159 goto (3, 4)
	160 -29 (3, 4)
	162 iinc (3, 4)
	163 #6 (3, 4)
	164 -89 (3, 4)
	165 goto (3, 4)
	166 -45 (3, 4)
	168 return (1, 4)

Method: getRowMatrix
	0 aload_0 (0, 0)
	1 iload_1 (0, 0)
	2 invokestatic (0, 0)
	3 org/apache/commons/math3/linear/MatrixUtils.checkRowIndex:(Lorg/apache/commons/math3/linear/AnyMatrix;I)V (0, 0)
	5 aload_0 (0, 0)
	6 invokevirtual (0, 0)
	7 org/apache/commons/math3/linear/AbstractRealMatrix.getColumnDimension:()I (0, 0)
	9 istore_2 (0, 0)
	10 aload_0 (0, 0)
	11 iconst_1 (0, 0)
	12 iload_2 (0, 0)
	13 invokevirtual (0, 0)
	14 org/apache/commons/math3/linear/AbstractRealMatrix.createMatrix:(II)Lorg/apache/commons/math3/linear/RealMatrix; (0, 0)
	16 astore_3 (0, 0)
	17 iconst_0 (1, 4)
	18 istore (1, 4)
	19 #4 (1, 4)
	20 iload (1, 4)
	21 #4 (1, 4)
	22 iload_2 (1, 4)
	23 if_icmpge (1, 4)
	24 25 (1, 4)
	26 aload_3 (1, 4)
	27 iconst_0 (1, 4)
	28 iload (1, 4)
	29 #4 (1, 4)
	30 aload_0 (1, 4)
	31 iload_1 (1, 4)
	32 iload (1, 4)
	33 #4 (1, 4)
	34 invokevirtual (1, 4)
	35 org/apache/commons/math3/linear/AbstractRealMatrix.getEntry:(II)D (1, 4)
	37 invokeinterface (1, 4)
	38 org/apache/commons/math3/linear/RealMatrix.checkSubtractionCompatible:(Lorg/apache/commons/math3/linear/AnyMatrix;Lorg/apache/commons/math3/linear/AnyMatrix;)V (1, 4)
	40 0 (1, 4)
	42 iinc (1, 4)
	43 #4 (1, 4)
	44 -89 (1, 4)
	45 goto (1, 4)
	46 -25 (1, 4)
	48 aload_3 (0, 0)
	49 areturn (0, 0)

Method: setRowMatrix
	0 aload_0 (0, 0)
	1 iload_1 (0, 0)
	2 invokestatic (0, 0)
	3 org/apache/commons/math3/linear/MatrixUtils.checkRowIndex:(Lorg/apache/commons/math3/linear/AnyMatrix;I)V (0, 0)
	5 aload_0 (0, 0)
	6 invokevirtual (0, 0)
	7 org/apache/commons/math3/linear/AbstractRealMatrix.getColumnDimension:()I (0, 0)
	9 istore_3 (0, 0)
	10 aload_2 (0, 1)
	11 invokeinterface (0, 1)
	12 org/apache/commons/math3/linear/RealMatrix.getColumnDimension:()I (0, 1)
	14 0 (0, 1)
	16 iconst_1 (0, 1)
	17 if_icmpne (0, 1)
	18 13 (0, 1)
	20 aload_2 (0, 1)
	21 invokeinterface (0, 1)
	22 org/apache/commons/math3/linear/RealMatrix.createMatrix:(II)Lorg/apache/commons/math3/linear/RealMatrix; (0, 1)
	24 0 (0, 1)
	26 iload_3 (0, 1)
	27 if_icmpeq (0, 1)
	28 25 (0, 1)
	30 new (0, 1)
	31 org/apache/commons/math3/linear/MatrixDimensionMismatchException (0, 1)
	33 dup (0, 1)
	34 aload_2 (0, 1)
	35 invokeinterface (0, 1)
	36 org/apache/commons/math3/linear/RealMatrix.getColumnDimension:()I (0, 1)
	38 0 (0, 1)
	40 aload_2 (0, 1)
	41 invokeinterface (0, 1)
	42 org/apache/commons/math3/linear/RealMatrix.createMatrix:(II)Lorg/apache/commons/math3/linear/RealMatrix; (0, 1)
	44 0 (0, 1)
	46 iconst_1 (0, 1)
	47 iload_3 (0, 1)
	48 invokespecial (0, 1)
	49 org/apache/commons/math3/linear/MatrixDimensionMismatchException.<init>:(IIII)V (0, 1)
	51 athrow (0, 1)
	52 iconst_0 (1, 4)
	53 istore (1, 4)
	54 #4 (1, 4)
	55 iload (1, 4)
	56 #4 (1, 4)
	57 iload_3 (1, 4)
	58 if_icmpge (1, 4)
	59 25 (1, 4)
	61 aload_0 (1, 4)
	62 iload_1 (1, 4)
	63 iload (1, 4)
	64 #4 (1, 4)
	65 aload_2 (1, 4)
	66 iconst_0 (1, 4)
	67 iload (1, 4)
	68 #4 (1, 4)
	69 invokeinterface (1, 4)
	70 org/apache/commons/math3/linear/RealMatrix.setEntry:(IID)V (1, 4)
	72 0 (1, 4)
	74 invokevirtual (1, 4)
	75 org/apache/commons/math3/linear/AbstractRealMatrix.setEntry:(IID)V (1, 4)
	77 iinc (1, 4)
	78 #4 (1, 4)
	79 -89 (1, 4)
	80 goto (1, 4)
	81 -25 (1, 4)
	83 return (0, 1)

Method: getColumnMatrix
	0 aload_0 (0, 0)
	1 iload_1 (0, 0)
	2 invokestatic (0, 0)
	3 org/apache/commons/math3/linear/MatrixUtils.checkColumnIndex:(Lorg/apache/commons/math3/linear/AnyMatrix;I)V (0, 0)
	5 aload_0 (0, 0)
	6 invokevirtual (0, 0)
	7 org/apache/commons/math3/linear/AbstractRealMatrix.getRowDimension:()I (0, 0)
	9 istore_2 (0, 0)
	10 aload_0 (0, 0)
	11 iload_2 (0, 0)
	12 iconst_1 (0, 0)
	13 invokevirtual (0, 0)
	14 org/apache/commons/math3/linear/AbstractRealMatrix.createMatrix:(II)Lorg/apache/commons/math3/linear/RealMatrix; (0, 0)
	16 astore_3 (0, 0)
	17 iconst_0 (1, 4)
	18 istore (1, 4)
	19 #4 (1, 4)
	20 iload (1, 4)
	21 #4 (1, 4)
	22 iload_2 (1, 4)
	23 if_icmpge (1, 4)
	24 25 (1, 4)
	26 aload_3 (1, 4)
	27 iload (1, 4)
	28 #4 (1, 4)
	29 iconst_0 (1, 4)
	30 aload_0 (1, 4)
	31 iload (1, 4)
	32 #4 (1, 4)
	33 iload_1 (1, 4)
	34 invokevirtual (1, 4)
	35 org/apache/commons/math3/linear/AbstractRealMatrix.getEntry:(II)D (1, 4)
	37 invokeinterface (1, 4)
	38 org/apache/commons/math3/linear/RealMatrix.checkSubtractionCompatible:(Lorg/apache/commons/math3/linear/AnyMatrix;Lorg/apache/commons/math3/linear/AnyMatrix;)V (1, 4)
	40 0 (1, 4)
	42 iinc (1, 4)
	43 #4 (1, 4)
	44 -89 (1, 4)
	45 goto (1, 4)
	46 -25 (1, 4)
	48 aload_3 (0, 0)
	49 areturn (0, 0)

Method: setColumnMatrix
	0 aload_0 (0, 0)
	1 iload_1 (0, 0)
	2 invokestatic (0, 0)
	3 org/apache/commons/math3/linear/MatrixUtils.checkColumnIndex:(Lorg/apache/commons/math3/linear/AnyMatrix;I)V (0, 0)
	5 aload_0 (0, 0)
	6 invokevirtual (0, 0)
	7 org/apache/commons/math3/linear/AbstractRealMatrix.getRowDimension:()I (0, 0)
	9 istore_3 (0, 0)
	10 aload_2 (0, 1)
	11 invokeinterface (0, 1)
	12 org/apache/commons/math3/linear/RealMatrix.getColumnDimension:()I (0, 1)
	14 0 (0, 1)
	16 iload_3 (0, 1)
	17 if_icmpne (0, 1)
	18 13 (0, 1)
	20 aload_2 (0, 1)
	21 invokeinterface (0, 1)
	22 org/apache/commons/math3/linear/RealMatrix.createMatrix:(II)Lorg/apache/commons/math3/linear/RealMatrix; (0, 1)
	24 0 (0, 1)
	26 iconst_1 (0, 1)
	27 if_icmpeq (0, 1)
	28 25 (0, 1)
	30 new (0, 1)
	31 org/apache/commons/math3/linear/MatrixDimensionMismatchException (0, 1)
	33 dup (0, 1)
	34 aload_2 (0, 1)
	35 invokeinterface (0, 1)
	36 org/apache/commons/math3/linear/RealMatrix.getColumnDimension:()I (0, 1)
	38 0 (0, 1)
	40 aload_2 (0, 1)
	41 invokeinterface (0, 1)
	42 org/apache/commons/math3/linear/RealMatrix.createMatrix:(II)Lorg/apache/commons/math3/linear/RealMatrix; (0, 1)
	44 0 (0, 1)
	46 iload_3 (0, 1)
	47 iconst_1 (0, 1)
	48 invokespecial (0, 1)
	49 org/apache/commons/math3/linear/MatrixDimensionMismatchException.<init>:(IIII)V (0, 1)
	51 athrow (0, 1)
	52 iconst_0 (1, 4)
	53 istore (1, 4)
	54 #4 (1, 4)
	55 iload (1, 4)
	56 #4 (1, 4)
	57 iload_3 (1, 4)
	58 if_icmpge (1, 4)
	59 25 (1, 4)
	61 aload_0 (1, 4)
	62 iload (1, 4)
	63 #4 (1, 4)
	64 iload_1 (1, 4)
	65 aload_2 (1, 4)
	66 iload (1, 4)
	67 #4 (1, 4)
	68 iconst_0 (1, 4)
	69 invokeinterface (1, 4)
	70 org/apache/commons/math3/linear/RealMatrix.setEntry:(IID)V (1, 4)
	72 0 (1, 4)
	74 invokevirtual (1, 4)
	75 org/apache/commons/math3/linear/AbstractRealMatrix.setEntry:(IID)V (1, 4)
	77 iinc (1, 4)
	78 #4 (1, 4)
	79 -89 (1, 4)
	80 goto (1, 4)
	81 -25 (1, 4)
	83 return (0, 1)

Method: getRowVector
	0 new (0, 0)
	1 org/apache/commons/math3/linear/ArrayRealVector (0, 0)
	3 dup (0, 0)
	4 aload_0 (0, 0)
	5 iload_1 (0, 0)
	6 invokevirtual (0, 0)
	7 org/apache/commons/math3/linear/AbstractRealMatrix.getRow:(I)[D (0, 0)
	9 iconst_0 (0, 0)
	10 invokespecial (0, 0)
	11 org/apache/commons/math3/linear/ArrayRealVector.<init>:([DZ)V (0, 0)
	13 areturn (0, 0)

Method: setRowVector
	0 aload_0 (0, 0)
	1 iload_1 (0, 0)
	2 invokestatic (0, 0)
	3 org/apache/commons/math3/linear/MatrixUtils.checkRowIndex:(Lorg/apache/commons/math3/linear/AnyMatrix;I)V (0, 0)
	5 aload_0 (0, 0)
	6 invokevirtual (0, 0)
	7 org/apache/commons/math3/linear/AbstractRealMatrix.getColumnDimension:()I (0, 0)
	9 istore_3 (0, 0)
	10 aload_2 (1, 1)
	11 invokevirtual (1, 1)
	12 org/apache/commons/math3/linear/RealVector.getDimension:()I (1, 1)
	14 iload_3 (1, 1)
	15 if_icmpeq (1, 1)
	16 18 (1, 1)
	18 new (1, 1)
	19 org/apache/commons/math3/linear/MatrixDimensionMismatchException (1, 1)
	21 dup (1, 1)
	22 iconst_1 (1, 1)
	23 aload_2 (1, 1)
	24 invokevirtual (1, 1)
	25 org/apache/commons/math3/linear/RealVector.getDimension:()I (1, 1)
	27 iconst_1 (1, 1)
	28 iload_3 (1, 1)
	29 invokespecial (1, 1)
	30 org/apache/commons/math3/linear/MatrixDimensionMismatchException.<init>:(IIII)V (1, 1)
	32 athrow (1, 1)
	33 iconst_0 (1, 4)
	34 istore (1, 4)
	35 #4 (1, 4)
	36 iload (1, 4)
	37 #4 (1, 4)
	38 iload_3 (1, 4)
	39 if_icmpge (1, 4)
	40 22 (1, 4)
	42 aload_0 (1, 4)
	43 iload_1 (1, 4)
	44 iload (1, 4)
	45 #4 (1, 4)
	46 aload_2 (1, 4)
	47 iload (1, 4)
	48 #4 (1, 4)
	49 invokevirtual (1, 4)
	50 org/apache/commons/math3/linear/RealVector.getEntry:(I)D (1, 4)
	52 invokevirtual (1, 4)
	53 org/apache/commons/math3/linear/AbstractRealMatrix.setEntry:(IID)V (1, 4)
	55 iinc (1, 4)
	56 #4 (1, 4)
	57 -89 (1, 4)
	58 goto (1, 4)
	59 -22 (1, 4)
	61 return (0, 0)

Method: getColumnVector
	0 new (0, 0)
	1 org/apache/commons/math3/linear/ArrayRealVector (0, 0)
	3 dup (0, 0)
	4 aload_0 (0, 0)
	5 iload_1 (0, 0)
	6 invokevirtual (0, 0)
	7 org/apache/commons/math3/linear/AbstractRealMatrix.getColumn:(I)[D (0, 0)
	9 iconst_0 (0, 0)
	10 invokespecial (0, 0)
	11 org/apache/commons/math3/linear/ArrayRealVector.<init>:([DZ)V (0, 0)
	13 areturn (0, 0)

Method: setColumnVector
	0 aload_0 (0, 0)
	1 iload_1 (0, 0)
	2 invokestatic (0, 0)
	3 org/apache/commons/math3/linear/MatrixUtils.checkColumnIndex:(Lorg/apache/commons/math3/linear/AnyMatrix;I)V (0, 0)
	5 aload_0 (0, 0)
	6 invokevirtual (0, 0)
	7 org/apache/commons/math3/linear/AbstractRealMatrix.getRowDimension:()I (0, 0)
	9 istore_3 (0, 0)
	10 aload_2 (1, 1)
	11 invokevirtual (1, 1)
	12 org/apache/commons/math3/linear/RealVector.getDimension:()I (1, 1)
	14 iload_3 (1, 1)
	15 if_icmpeq (1, 1)
	16 18 (1, 1)
	18 new (1, 1)
	19 org/apache/commons/math3/linear/MatrixDimensionMismatchException (1, 1)
	21 dup (1, 1)
	22 aload_2 (1, 1)
	23 invokevirtual (1, 1)
	24 org/apache/commons/math3/linear/RealVector.getDimension:()I (1, 1)
	26 iconst_1 (1, 1)
	27 iload_3 (1, 1)
	28 iconst_1 (1, 1)
	29 invokespecial (1, 1)
	30 org/apache/commons/math3/linear/MatrixDimensionMismatchException.<init>:(IIII)V (1, 1)
	32 athrow (1, 1)
	33 iconst_0 (1, 4)
	34 istore (1, 4)
	35 #4 (1, 4)
	36 iload (1, 4)
	37 #4 (1, 4)
	38 iload_3 (1, 4)
	39 if_icmpge (1, 4)
	40 22 (1, 4)
	42 aload_0 (1, 4)
	43 iload (1, 4)
	44 #4 (1, 4)
	45 iload_1 (1, 4)
	46 aload_2 (1, 4)
	47 iload (1, 4)
	48 #4 (1, 4)
	49 invokevirtual (1, 4)
	50 org/apache/commons/math3/linear/RealVector.getEntry:(I)D (1, 4)
	52 invokevirtual (1, 4)
	53 org/apache/commons/math3/linear/AbstractRealMatrix.setEntry:(IID)V (1, 4)
	55 iinc (1, 4)
	56 #4 (1, 4)
	57 -89 (1, 4)
	58 goto (1, 4)
	59 -22 (1, 4)
	61 return (0, 0)

Method: getRow
	0 aload_0 (0, 0)
	1 iload_1 (0, 0)
	2 invokestatic (0, 0)
	3 org/apache/commons/math3/linear/MatrixUtils.checkRowIndex:(Lorg/apache/commons/math3/linear/AnyMatrix;I)V (0, 0)
	5 aload_0 (0, 0)
	6 invokevirtual (0, 0)
	7 org/apache/commons/math3/linear/AbstractRealMatrix.getColumnDimension:()I (0, 0)
	9 istore_2 (0, 0)
	10 iload_2 (0, 0)
	11 newarray (0, 0)
	12 7 (0, 0)
	13 astore_3 (0, 0)
	14 iconst_0 (1, 4)
	15 istore (1, 4)
	16 #4 (1, 4)
	17 iload (1, 4)
	18 #4 (1, 4)
	19 iload_2 (1, 4)
	20 if_icmpge (1, 4)
	21 20 (1, 4)
	23 aload_3 (1, 4)
	24 iload (1, 4)
	25 #4 (1, 4)
	26 aload_0 (1, 4)
	27 iload_1 (1, 4)
	28 iload (1, 4)
	29 #4 (1, 4)
	30 invokevirtual (1, 4)
	31 org/apache/commons/math3/linear/AbstractRealMatrix.getEntry:(II)D (1, 4)
	33 dastore (1, 4)
	34 iinc (1, 4)
	35 #4 (1, 4)
	36 -89 (1, 4)
	37 goto (1, 4)
	38 -20 (1, 4)
	40 aload_3 (0, 0)
	41 areturn (0, 0)

Method: setRow
	0 aload_0 (0, 0)
	1 iload_1 (0, 0)
	2 invokestatic (0, 0)
	3 org/apache/commons/math3/linear/MatrixUtils.checkRowIndex:(Lorg/apache/commons/math3/linear/AnyMatrix;I)V (0, 0)
	5 aload_0 (0, 0)
	6 invokevirtual (0, 0)
	7 org/apache/commons/math3/linear/AbstractRealMatrix.getColumnDimension:()I (0, 0)
	9 istore_3 (0, 0)
	10 aload_2 (1, 1)
	11 arraylength (1, 1)
	12 iload_3 (1, 1)
	13 if_icmpeq (1, 1)
	14 16 (1, 1)
	16 new (1, 1)
	17 org/apache/commons/math3/linear/MatrixDimensionMismatchException (1, 1)
	19 dup (1, 1)
	20 iconst_1 (1, 1)
	21 aload_2 (1, 1)
	22 arraylength (1, 1)
	23 iconst_1 (1, 1)
	24 iload_3 (1, 1)
	25 invokespecial (1, 1)
	26 org/apache/commons/math3/linear/MatrixDimensionMismatchException.<init>:(IIII)V (1, 1)
	28 athrow (1, 1)
	29 iconst_0 (1, 4)
	30 istore (1, 4)
	31 #4 (1, 4)
	32 iload (1, 4)
	33 #4 (1, 4)
	34 iload_3 (1, 4)
	35 if_icmpge (1, 4)
	36 20 (1, 4)
	38 aload_0 (1, 4)
	39 iload_1 (1, 4)
	40 iload (1, 4)
	41 #4 (1, 4)
	42 aload_2 (1, 4)
	43 iload (1, 4)
	44 #4 (1, 4)
	45 daload (1, 4)
	46 invokevirtual (1, 4)
	47 org/apache/commons/math3/linear/AbstractRealMatrix.setEntry:(IID)V (1, 4)
	49 iinc (1, 4)
	50 #4 (1, 4)
	51 -89 (1, 4)
	52 goto (1, 4)
	53 -20 (1, 4)
	55 return (0, 0)

Method: getColumn
	0 aload_0 (0, 0)
	1 iload_1 (0, 0)
	2 invokestatic (0, 0)
	3 org/apache/commons/math3/linear/MatrixUtils.checkColumnIndex:(Lorg/apache/commons/math3/linear/AnyMatrix;I)V (0, 0)
	5 aload_0 (0, 0)
	6 invokevirtual (0, 0)
	7 org/apache/commons/math3/linear/AbstractRealMatrix.getRowDimension:()I (0, 0)
	9 istore_2 (0, 0)
	10 iload_2 (0, 0)
	11 newarray (0, 0)
	12 7 (0, 0)
	13 astore_3 (0, 0)
	14 iconst_0 (1, 4)
	15 istore (1, 4)
	16 #4 (1, 4)
	17 iload (1, 4)
	18 #4 (1, 4)
	19 iload_2 (1, 4)
	20 if_icmpge (1, 4)
	21 20 (1, 4)
	23 aload_3 (1, 4)
	24 iload (1, 4)
	25 #4 (1, 4)
	26 aload_0 (1, 4)
	27 iload (1, 4)
	28 #4 (1, 4)
	29 iload_1 (1, 4)
	30 invokevirtual (1, 4)
	31 org/apache/commons/math3/linear/AbstractRealMatrix.getEntry:(II)D (1, 4)
	33 dastore (1, 4)
	34 iinc (1, 4)
	35 #4 (1, 4)
	36 -89 (1, 4)
	37 goto (1, 4)
	38 -20 (1, 4)
	40 aload_3 (0, 0)
	41 areturn (0, 0)

Method: setColumn
	0 aload_0 (0, 0)
	1 iload_1 (0, 0)
	2 invokestatic (0, 0)
	3 org/apache/commons/math3/linear/MatrixUtils.checkColumnIndex:(Lorg/apache/commons/math3/linear/AnyMatrix;I)V (0, 0)
	5 aload_0 (0, 0)
	6 invokevirtual (0, 0)
	7 org/apache/commons/math3/linear/AbstractRealMatrix.getRowDimension:()I (0, 0)
	9 istore_3 (0, 0)
	10 aload_2 (1, 1)
	11 arraylength (1, 1)
	12 iload_3 (1, 1)
	13 if_icmpeq (1, 1)
	14 16 (1, 1)
	16 new (1, 1)
	17 org/apache/commons/math3/linear/MatrixDimensionMismatchException (1, 1)
	19 dup (1, 1)
	20 aload_2 (1, 1)
	21 arraylength (1, 1)
	22 iconst_1 (1, 1)
	23 iload_3 (1, 1)
	24 iconst_1 (1, 1)
	25 invokespecial (1, 1)
	26 org/apache/commons/math3/linear/MatrixDimensionMismatchException.<init>:(IIII)V (1, 1)
	28 athrow (1, 1)
	29 iconst_0 (1, 4)
	30 istore (1, 4)
	31 #4 (1, 4)
	32 iload (1, 4)
	33 #4 (1, 4)
	34 iload_3 (1, 4)
	35 if_icmpge (1, 4)
	36 20 (1, 4)
	38 aload_0 (1, 4)
	39 iload (1, 4)
	40 #4 (1, 4)
	41 iload_1 (1, 4)
	42 aload_2 (1, 4)
	43 iload (1, 4)
	44 #4 (1, 4)
	45 daload (1, 4)
	46 invokevirtual (1, 4)
	47 org/apache/commons/math3/linear/AbstractRealMatrix.setEntry:(IID)V (1, 4)
	49 iinc (1, 4)
	50 #4 (1, 4)
	51 -89 (1, 4)
	52 goto (1, 4)
	53 -20 (1, 4)
	55 return (0, 0)

Method: addToEntry
	0 aload_0 (0, 0)
	1 iload_1 (0, 0)
	2 iload_2 (0, 0)
	3 invokestatic (0, 0)
	4 org/apache/commons/math3/linear/MatrixUtils.checkMatrixIndex:(Lorg/apache/commons/math3/linear/AnyMatrix;II)V (0, 0)
	6 aload_0 (0, 0)
	7 iload_1 (0, 0)
	8 iload_2 (0, 0)
	9 aload_0 (0, 0)
	10 iload_1 (0, 0)
	11 iload_2 (0, 0)
	12 invokevirtual (0, 0)
	13 org/apache/commons/math3/linear/AbstractRealMatrix.getEntry:(II)D (0, 0)
	15 dload_3 (0, 0)
	16 dadd (0, 0)
	17 invokevirtual (0, 0)
	18 org/apache/commons/math3/linear/AbstractRealMatrix.setEntry:(IID)V (0, 0)
	20 return (0, 0)

Method: multiplyEntry
	0 aload_0 (0, 0)
	1 iload_1 (0, 0)
	2 iload_2 (0, 0)
	3 invokestatic (0, 0)
	4 org/apache/commons/math3/linear/MatrixUtils.checkMatrixIndex:(Lorg/apache/commons/math3/linear/AnyMatrix;II)V (0, 0)
	6 aload_0 (0, 0)
	7 iload_1 (0, 0)
	8 iload_2 (0, 0)
	9 aload_0 (0, 0)
	10 iload_1 (0, 0)
	11 iload_2 (0, 0)
	12 invokevirtual (0, 0)
	13 org/apache/commons/math3/linear/AbstractRealMatrix.getEntry:(II)D (0, 0)
	15 dload_3 (0, 0)
	16 dmul (0, 0)
	17 invokevirtual (0, 0)
	18 org/apache/commons/math3/linear/AbstractRealMatrix.setEntry:(IID)V (0, 0)
	20 return (0, 0)

Method: transpose
	0 aload_0 (0, 0)
	1 invokevirtual (0, 0)
	2 org/apache/commons/math3/linear/AbstractRealMatrix.getRowDimension:()I (0, 0)
	4 istore_1 (0, 0)
	5 aload_0 (0, 0)
	6 invokevirtual (0, 0)
	7 org/apache/commons/math3/linear/AbstractRealMatrix.getColumnDimension:()I (0, 0)
	9 istore_2 (0, 0)
	10 aload_0 (0, 0)
	11 iload_2 (0, 0)
	12 iload_1 (0, 0)
	13 invokevirtual (0, 0)
	14 org/apache/commons/math3/linear/AbstractRealMatrix.createMatrix:(II)Lorg/apache/commons/math3/linear/RealMatrix; (0, 0)
	16 astore_3 (0, 0)
	17 aload_0 (0, 0)
	18 new (0, 0)
	19 org/apache/commons/math3/linear/AbstractRealMatrix$5 (0, 0)
	21 dup (0, 0)
	22 aload_0 (0, 0)
	23 aload_3 (0, 0)
	24 invokespecial (0, 0)
	25 org/apache/commons/math3/linear/AbstractRealMatrix$5.<init>:(Lorg/apache/commons/math3/linear/AbstractRealMatrix;Lorg/apache/commons/math3/linear/RealMatrix;)V (0, 0)
	27 invokevirtual (0, 0)
	28 org/apache/commons/math3/linear/AbstractRealMatrix.walkInOptimizedOrder:(Lorg/apache/commons/math3/linear/RealMatrixPreservingVisitor;)D (0, 0)
	30 pop2 (0, 0)
	31 aload_3 (0, 0)
	32 areturn (0, 0)

Method: isSquare
	0 aload_0 (0, 0)
	1 invokevirtual (0, 0)
	2 org/apache/commons/math3/linear/AbstractRealMatrix.getColumnDimension:()I (0, 0)
	4 aload_0 (0, 0)
	5 invokevirtual (0, 0)
	6 org/apache/commons/math3/linear/AbstractRealMatrix.getRowDimension:()I (0, 0)
	8 if_icmpne (0, 0)
	9 7 (0, 0)
	11 iconst_1 (0, 0)
	12 goto (0, 0)
	13 4 (0, 0)
	15 iconst_0 (0, 0)
	16 ireturn (0, 0)

Method: getTrace
	0 aload_0 (0, 0)
	1 invokevirtual (0, 0)
	2 org/apache/commons/math3/linear/AbstractRealMatrix.getRowDimension:()I (0, 0)
	4 istore_1 (0, 0)
	5 aload_0 (0, 0)
	6 invokevirtual (0, 0)
	7 org/apache/commons/math3/linear/AbstractRealMatrix.getColumnDimension:()I (0, 0)
	9 istore_2 (0, 0)
	10 iload_1 (1, 1)
	11 iload_2 (1, 1)
	12 if_icmpeq (1, 1)
	13 13 (1, 1)
	15 new (1, 1)
	16 org/apache/commons/math3/linear/NonSquareMatrixException (1, 1)
	18 dup (1, 1)
	19 iload_1 (1, 1)
	20 iload_2 (1, 1)
	21 invokespecial (1, 1)
	22 org/apache/commons/math3/linear/NonSquareMatrixException.<init>:(II)V (1, 1)
	24 athrow (1, 1)
	25 dconst_0 (0, 0)
	26 dstore_3 (0, 0)
	27 iconst_0 (1, 4)
	28 istore (1, 4)
	29 #5 (1, 4)
	30 iload (1, 4)
	31 #5 (1, 4)
	32 iload_1 (1, 4)
	33 if_icmpge (1, 4)
	34 20 (1, 4)
	36 dload_3 (1, 4)
	37 aload_0 (1, 4)
	38 iload (1, 4)
	39 #5 (1, 4)
	40 iload (1, 4)
	41 #5 (1, 4)
	42 invokevirtual (1, 4)
	43 org/apache/commons/math3/linear/AbstractRealMatrix.getEntry:(II)D (1, 4)
	45 dadd (1, 4)
	46 dstore_3 (1, 4)
	47 iinc (1, 4)
	48 #5 (1, 4)
	49 -89 (1, 4)
	50 goto (1, 4)
	51 -20 (1, 4)
	53 dload_3 (0, 0)
	54 dreturn (0, 0)

Method: operate
	0 new (0, 0)
	1 org/apache/commons/math3/linear/ArrayRealVector (0, 0)
	3 dup (0, 0)
	4 aload_0 (0, 0)
	5 aload_1 (0, 0)
	6 checkcast (0, 0)
	7 org/apache/commons/math3/linear/ArrayRealVector (0, 0)
	9 invokevirtual (0, 0)
	10 org/apache/commons/math3/linear/ArrayRealVector.getDataRef:()[D (0, 0)
	12 invokevirtual (0, 0)
	13 org/apache/commons/math3/linear/AbstractRealMatrix.operate:([D)[D (0, 0)
	15 iconst_0 (0, 0)
	16 invokespecial (0, 0)
	17 org/apache/commons/math3/linear/ArrayRealVector.<init>:([DZ)V (0, 0)
	19 areturn (0, 0)
	20 astore_2 (0, 0)
	21 aload_0 (0, 0)
	22 invokevirtual (0, 0)
	23 org/apache/commons/math3/linear/AbstractRealMatrix.getRowDimension:()I (0, 0)
	25 istore_3 (0, 0)
	26 aload_0 (0, 0)
	27 invokevirtual (0, 0)
	28 org/apache/commons/math3/linear/AbstractRealMatrix.getColumnDimension:()I (0, 0)
	30 istore (0, 0)
	31 #4 (0, 0)
	32 aload_1 (1, 1)
	33 invokevirtual (1, 1)
	34 org/apache/commons/math3/linear/RealVector.getDimension:()I (1, 1)
	36 iload (1, 1)
	37 #4 (1, 1)
	38 if_icmpeq (1, 1)
	39 17 (1, 1)
	41 new (1, 1)
	42 org/apache/commons/math3/exception/DimensionMismatchException (1, 1)
	44 dup (1, 1)
	45 aload_1 (1, 1)
	46 invokevirtual (1, 1)
	47 org/apache/commons/math3/linear/RealVector.getDimension:()I (1, 1)
	49 iload (1, 1)
	50 #4 (1, 1)
	51 invokespecial (1, 1)
	52 org/apache/commons/math3/exception/DimensionMismatchException.<init>:(II)V (1, 1)
	54 athrow (1, 1)
	55 iload_3 (0, 0)
	56 newarray (0, 0)
	57 7 (0, 0)
	58 astore (0, 0)
	59 #5 (0, 0)
	60 iconst_0 (1, 4)
	61 istore (1, 4)
	62 #6 (1, 4)
	63 iload (1, 4)
	64 #6 (1, 4)
	65 iload_3 (1, 4)
	66 if_icmpge (1, 4)
	67 55 (1, 4)
	69 dconst_0 (1, 4)
	70 dstore (1, 4)
	71 #7 (1, 4)
	72 iconst_0 (2, 4)
	73 istore (2, 4)
	74 #9 (2, 4)
	75 iload (2, 4)
	76 #9 (2, 4)
	77 iload (2, 4)
	78 #4 (2, 4)
	79 if_icmpge (2, 4)
	80 29 (2, 4)
	82 dload (2, 4)
	83 #7 (2, 4)
	84 aload_0 (2, 4)
	85 iload (2, 4)
	86 #6 (2, 4)
	87 iload (2, 4)
	88 #9 (2, 4)
	89 invokevirtual (2, 4)
	90 org/apache/commons/math3/linear/AbstractRealMatrix.getEntry:(II)D (2, 4)
	92 aload_1 (2, 4)
	93 iload (2, 4)
	94 #9 (2, 4)
	95 invokevirtual (2, 4)
	96 org/apache/commons/math3/linear/RealVector.getEntry:(I)D (2, 4)
	98 dmul (2, 4)
	99 dadd (2, 4)
	100 dstore (2, 4)
	101 #7 (2, 4)
	102 iinc (2, 4)
	103 #9 (2, 4)
	104 -89 (2, 4)
	105 goto (2, 4)
	106 -30 (2, 4)
	108 aload (1, 4)
	109 #5 (1, 4)
	110 iload (1, 4)
	111 #6 (1, 4)
	112 dload (1, 4)
	113 #7 (1, 4)
	114 dastore (1, 4)
	115 iinc (1, 4)
	116 #6 (1, 4)
	117 -89 (1, 4)
	118 goto (1, 4)
	119 -55 (1, 4)
	121 new (0, 0)
	122 org/apache/commons/math3/linear/ArrayRealVector (0, 0)
	124 dup (0, 0)
	125 aload (0, 0)
	126 #5 (0, 0)
	127 iconst_0 (0, 0)
	128 invokespecial (0, 0)
	129 org/apache/commons/math3/linear/ArrayRealVector.<init>:([DZ)V (0, 0)
	131 areturn (0, 0)

Method: walkInRowOrder
	0 aload_0 (0, 0)
	1 iload_2 (0, 0)
	2 iload_3 (0, 0)
	3 iload (0, 0)
	4 #4 (0, 0)
	5 iload (0, 0)
	6 #5 (0, 0)
	7 invokestatic (0, 0)
	8 org/apache/commons/math3/linear/MatrixUtils.checkSubMatrixIndex:(Lorg/apache/commons/math3/linear/AnyMatrix;IIII)V (0, 0)
	10 aload_1 (0, 0)
	11 aload_0 (0, 0)
	12 invokevirtual (0, 0)
	13 org/apache/commons/math3/linear/AbstractRealMatrix.getRowDimension:()I (0, 0)
	15 aload_0 (0, 0)
	16 invokevirtual (0, 0)
	17 org/apache/commons/math3/linear/AbstractRealMatrix.getColumnDimension:()I (0, 0)
	19 iload_2 (0, 0)
	20 iload_3 (0, 0)
	21 iload (0, 0)
	22 #4 (0, 0)
	23 iload (0, 0)
	24 #5 (0, 0)
	25 invokeinterface (0, 0)
	26 org/apache/commons/math3/linear/RealMatrixPreservingVisitor.visit:(IID)D (0, 0)
	28 0 (0, 0)
	30 iload_2 (1, 4)
	31 istore (1, 4)
	32 #6 (1, 4)
	33 iload (1, 4)
	34 #6 (1, 4)
	35 iload_3 (1, 4)
	36 if_icmpgt (1, 4)
	37 44 (1, 4)
	39 iload (2, 4)
	40 #4 (2, 4)
	41 istore (2, 4)
	42 #7 (2, 4)
	43 iload (2, 4)
	44 #7 (2, 4)
	45 iload (2, 4)
	46 #5 (2, 4)
	47 if_icmpgt (2, 4)
	48 27 (2, 4)
	50 aload_1 (2, 4)
	51 iload (2, 4)
	52 #6 (2, 4)
	53 iload (2, 4)
	54 #7 (2, 4)
	55 aload_0 (2, 4)
	56 iload (2, 4)
	57 #6 (2, 4)
	58 iload (2, 4)
	59 #7 (2, 4)
	60 invokevirtual (2, 4)
	61 org/apache/commons/math3/linear/AbstractRealMatrix.getEntry:(II)D (2, 4)
	63 invokeinterface (2, 4)
	64 org/apache/commons/math3/linear/RealMatrixPreservingVisitor.walkInRowOrder:(Lorg/apache/commons/math3/linear/RealMatrixChangingVisitor;)D (2, 4)
	66 0 (2, 4)
	68 iinc (2, 4)
	69 #7 (2, 4)
	70 -89 (2, 4)
	71 goto (2, 4)
	72 -28 (2, 4)
	74 iinc (2, 4)
	75 #6 (2, 4)
	76 -89 (2, 4)
	77 goto (2, 4)
	78 -44 (2, 4)
	80 aload_1 (1, 4)
	81 invokeinterface (1, 4)
	82 org/apache/commons/math3/linear/RealMatrixPreservingVisitor.org/apache/commons/math3/linear/RealMatrixPreservingVisitor (1, 4)
	84 0 (1, 4)
	86 dreturn (1, 4)

Method: walkInColumnOrder
	0 aload_0 (0, 0)
	1 iload_2 (0, 0)
	2 iload_3 (0, 0)
	3 iload (0, 0)
	4 #4 (0, 0)
	5 iload (0, 0)
	6 #5 (0, 0)
	7 invokestatic (0, 0)
	8 org/apache/commons/math3/linear/MatrixUtils.checkSubMatrixIndex:(Lorg/apache/commons/math3/linear/AnyMatrix;IIII)V (0, 0)
	10 aload_1 (0, 0)
	11 aload_0 (0, 0)
	12 invokevirtual (0, 0)
	13 org/apache/commons/math3/linear/AbstractRealMatrix.getRowDimension:()I (0, 0)
	15 aload_0 (0, 0)
	16 invokevirtual (0, 0)
	17 org/apache/commons/math3/linear/AbstractRealMatrix.getColumnDimension:()I (0, 0)
	19 iload_2 (0, 0)
	20 iload_3 (0, 0)
	21 iload (0, 0)
	22 #4 (0, 0)
	23 iload (0, 0)
	24 #5 (0, 0)
	25 invokeinterface (0, 0)
	26 org/apache/commons/math3/linear/RealMatrixPreservingVisitor.visit:(IID)D (0, 0)
	28 0 (0, 0)
	30 iload (1, 4)
	31 #4 (1, 4)
	32 istore (1, 4)
	33 #6 (1, 4)
	34 iload (1, 4)
	35 #6 (1, 4)
	36 iload (1, 4)
	37 #5 (1, 4)
	38 if_icmpgt (1, 4)
	39 42 (1, 4)
	41 iload_2 (2, 4)
	42 istore (2, 4)
	43 #7 (2, 4)
	44 iload (2, 4)
	45 #7 (2, 4)
	46 iload_3 (2, 4)
	47 if_icmpgt (2, 4)
	48 27 (2, 4)
	50 aload_1 (2, 4)
	51 iload (2, 4)
	52 #7 (2, 4)
	53 iload (2, 4)
	54 #6 (2, 4)
	55 aload_0 (2, 4)
	56 iload (2, 4)
	57 #7 (2, 4)
	58 iload (2, 4)
	59 #6 (2, 4)
	60 invokevirtual (2, 4)
	61 org/apache/commons/math3/linear/AbstractRealMatrix.getEntry:(II)D (2, 4)
	63 invokeinterface (2, 4)
	64 org/apache/commons/math3/linear/RealMatrixPreservingVisitor.walkInRowOrder:(Lorg/apache/commons/math3/linear/RealMatrixChangingVisitor;)D (2, 4)
	66 0 (2, 4)
	68 iinc (2, 4)
	69 #7 (2, 4)
	70 -89 (2, 4)
	71 goto (2, 4)
	72 -27 (2, 4)
	74 iinc (2, 4)
	75 #6 (2, 4)
	76 -89 (2, 4)
	77 goto (2, 4)
	78 -43 (2, 4)
	80 aload_1 (1, 4)
	81 invokeinterface (1, 4)
	82 org/apache/commons/math3/linear/RealMatrixPreservingVisitor.org/apache/commons/math3/linear/RealMatrixPreservingVisitor (1, 4)
	84 0 (1, 4)
	86 dreturn (1, 4)

Method: walkInOptimizedOrder
	0 aload_0 (0, 0)
	1 aload_1 (0, 0)
	2 iload_2 (0, 0)
	3 iload_3 (0, 0)
	4 iload (0, 0)
	5 #4 (0, 0)
	6 iload (0, 0)
	7 #5 (0, 0)
	8 invokevirtual (0, 0)
	9 org/apache/commons/math3/linear/AbstractRealMatrix.walkInRowOrder:(Lorg/apache/commons/math3/linear/RealMatrixPreservingVisitor;IIII)D (0, 0)
	11 dreturn (0, 0)

Method: toString
	0 new (0, 0)
	1 java/lang/StringBuilder (0, 0)
	3 dup (0, 0)
	4 invokespecial (0, 0)
	5 java/lang/StringBuilder.<init>:()V (0, 0)
	7 astore_1 (0, 0)
	8 aload_0 (0, 0)
	9 invokevirtual (0, 0)
	10 java/lang/Object.getClass:()Ljava/lang/Class; (0, 0)
	12 invokevirtual (0, 0)
	13 java/lang/Class.getName:()Ljava/lang/String; (0, 0)
	15 astore_2 (0, 0)
	16 aload_2 (0, 0)
	17 aload_2 (0, 0)
	18 bipush (0, 0)
	19 46 (0, 0)
	20 invokevirtual (0, 0)
	21 java/lang/String.lastIndexOf:(I)I (0, 0)
	23 iconst_1 (0, 0)
	24 iadd (0, 0)
	25 invokevirtual (0, 0)
	26 java/lang/String.substring:(I)Ljava/lang/String; (0, 0)
	28 astore_3 (0, 0)
	29 aload_1 (0, 0)
	30 aload_3 (0, 0)
	31 invokevirtual (0, 0)
	32 java/lang/StringBuilder.append:(Ljava/lang/String;)Ljava/lang/StringBuilder; (0, 0)
	34 pop (0, 0)
	35 aload_1 (0, 4)
	36 getstatic (0, 4)
	37 org/apache/commons/math3/linear/AbstractRealMatrix.DEFAULT_FORMAT:Lorg/apache/commons/math3/linear/RealMatrixFormat; (0, 4)
	39 aload_0 (0, 4)
	40 invokevirtual (0, 4)
	41 org/apache/commons/math3/linear/RealMatrixFormat.format:(Lorg/apache/commons/math3/linear/RealMatrix;)Ljava/lang/String; (0, 4)
	43 invokevirtual (0, 4)
	44 java/lang/StringBuilder.append:(Ljava/lang/String;)Ljava/lang/StringBuilder; (0, 4)
	46 pop (0, 4)
	47 aload_1 (0, 4)
	48 invokevirtual (0, 4)
	49 java/lang/StringBuilder.toString:()Ljava/lang/String; (0, 4)
	51 areturn (0, 4)

Method: equals
	0 aload_1 (1, 1)
	1 aload_0 (1, 1)
	2 if_acmpne (1, 1)
	3 5 (1, 1)
	5 iconst_1 (1, 1)
	6 ireturn (1, 1)
	7 aload_1 (1, 1)
	8 instanceof (1, 1)
	9 org/apache/commons/math3/linear/RealMatrix (1, 1)
	11 ifne (1, 1)
	12 5 (1, 1)
	14 iconst_0 (1, 1)
	15 ireturn (1, 1)
	16 aload_1 (0, 0)
	17 checkcast (0, 0)
	18 org/apache/commons/math3/linear/RealMatrix (0, 0)
	20 astore_2 (0, 0)
	21 aload_0 (0, 0)
	22 invokevirtual (0, 0)
	23 org/apache/commons/math3/linear/AbstractRealMatrix.getRowDimension:()I (0, 0)
	25 istore_3 (0, 0)
	26 aload_0 (0, 0)
	27 invokevirtual (0, 0)
	28 org/apache/commons/math3/linear/AbstractRealMatrix.getColumnDimension:()I (0, 0)
	30 istore (0, 0)
	31 #4 (0, 0)
	32 aload_2 (1, 1)
	33 invokeinterface (1, 1)
	34 org/apache/commons/math3/linear/RealMatrix.createMatrix:(II)Lorg/apache/commons/math3/linear/RealMatrix; (1, 1)
	36 0 (1, 1)
	38 iload (1, 1)
	39 #4 (1, 1)
	40 if_icmpne (1, 1)
	41 13 (1, 1)
	43 aload_2 (1, 1)
	44 invokeinterface (1, 1)
	45 org/apache/commons/math3/linear/RealMatrix.getColumnDimension:()I (1, 1)
	47 0 (1, 1)
	49 iload_3 (1, 1)
	50 if_icmpeq (1, 1)
	51 5 (1, 1)
	53 iconst_0 (1, 1)
	54 ireturn (1, 1)
	55 iconst_0 (1, 4)
	56 istore (1, 4)
	57 #5 (1, 4)
	58 iload (1, 4)
	59 #5 (1, 4)
	60 iload_3 (1, 4)
	61 if_icmpge (1, 4)
	62 49 (1, 4)
	64 iconst_0 (2, 4)
	65 istore (2, 4)
	66 #6 (2, 4)
	67 iload (2, 4)
	68 #6 (2, 4)
	69 iload (2, 4)
	70 #4 (2, 4)
	71 if_icmpge (2, 4)
	72 33 (2, 4)
	74 aload_0 (3, 1)
	75 iload (3, 1)
	76 #5 (3, 1)
	77 iload (3, 1)
	78 #6 (3, 1)
	79 invokevirtual (3, 1)
	80 org/apache/commons/math3/linear/AbstractRealMatrix.getEntry:(II)D (3, 1)
	82 aload_2 (3, 1)
	83 iload (3, 1)
	84 #5 (3, 1)
	85 iload (3, 1)
	86 #6 (3, 1)
	87 invokeinterface (3, 1)
	88 org/apache/commons/math3/linear/RealMatrix.setEntry:(IID)V (3, 1)
	90 0 (3, 1)
	92 dcmpl (3, 1)
	93 ifeq (3, 1)
	94 5 (3, 1)
	96 iconst_0 (3, 1)
	97 ireturn (3, 1)
	98 iinc (3, 1)
	99 #6 (3, 1)
	100 -89 (3, 1)
	101 goto (3, 1)
	102 -34 (3, 1)
	104 iinc (3, 1)
	105 #5 (3, 1)
	106 -89 (3, 1)
	107 goto (3, 1)
	108 -49 (3, 1)
	110 iconst_1 (2, 4)
	111 ireturn (2, 4)

Method: hashCode
	0 bipush (0, 0)
	1 7 (0, 0)
	2 istore_1 (0, 0)
	3 aload_0 (0, 0)
	4 invokevirtual (0, 0)
	5 org/apache/commons/math3/linear/AbstractRealMatrix.getRowDimension:()I (0, 0)
	7 istore_2 (0, 0)
	8 aload_0 (0, 0)
	9 invokevirtual (0, 0)
	10 org/apache/commons/math3/linear/AbstractRealMatrix.getColumnDimension:()I (0, 0)
	12 istore_3 (0, 0)
	13 iload_1 (0, 0)
	14 bipush (0, 0)
	15 31 (0, 0)
	16 imul (0, 0)
	17 iload_2 (0, 0)
	18 iadd (0, 0)
	19 istore_1 (0, 0)
	20 iload_1 (0, 0)
	21 bipush (0, 0)
	22 31 (0, 0)
	23 imul (0, 0)
	24 iload_3 (0, 0)
	25 iadd (0, 0)
	26 istore_1 (0, 0)
	27 iconst_0 (1, 4)
	28 istore (1, 4)
	29 #4 (1, 4)
	30 iload (1, 4)
	31 #4 (1, 4)
	32 iload_2 (1, 4)
	33 if_icmpge (1, 4)
	34 57 (1, 4)
	36 iconst_0 (2, 4)
	37 istore (2, 4)
	38 #5 (2, 4)
	39 iload (2, 4)
	40 #5 (2, 4)
	41 iload_3 (2, 4)
	42 if_icmpge (2, 4)
	43 42 (2, 4)
	45 iload_1 (2, 4)
	46 bipush (2, 4)
	47 31 (2, 4)
	48 imul (2, 4)
	49 bipush (2, 4)
	50 11 (2, 4)
	51 iload (2, 4)
	52 #4 (2, 4)
	53 iconst_1 (2, 4)
	54 iadd (2, 4)
	55 imul (2, 4)
	56 bipush (2, 4)
	57 17 (2, 4)
	58 iload (2, 4)
	59 #5 (2, 4)
	60 iconst_1 (2, 4)
	61 iadd (2, 4)
	62 imul (2, 4)
	63 iadd (2, 4)
	64 aload_0 (2, 4)
	65 iload (2, 4)
	66 #4 (2, 4)
	67 iload (2, 4)
	68 #5 (2, 4)
	69 invokevirtual (2, 4)
	70 org/apache/commons/math3/linear/AbstractRealMatrix.getEntry:(II)D (2, 4)
	72 invokestatic (2, 4)
	73 org/apache/commons/math3/util/MathUtils.hash:(D)I (2, 4)
	75 imul (2, 4)
	76 iadd (2, 4)
	77 istore_1 (2, 4)
	78 iinc (2, 4)
	79 #5 (2, 4)
	80 -89 (2, 4)
	81 goto (2, 4)
	82 -42 (2, 4)
	84 iinc (2, 4)
	85 #4 (2, 4)
	86 -89 (2, 4)
	87 goto (2, 4)
	88 -57 (2, 4)
	90 iload_1 (1, 4)
	91 ireturn (1, 4)

Method: <clinit>
	0 getstatic (0, 0)
	1 java/util/Locale.US:Ljava/util/Locale; (0, 0)
	3 invokestatic (0, 0)
	4 org/apache/commons/math3/linear/RealMatrixFormat.getInstance:(Ljava/util/Locale;)Lorg/apache/commons/math3/linear/RealMatrixFormat; (0, 0)
	6 putstatic (0, 0)
	7 org/apache/commons/math3/linear/AbstractRealMatrix.DEFAULT_FORMAT:Lorg/apache/commons/math3/linear/RealMatrixFormat; (0, 0)
	9 getstatic (0, 0)
	10 org/apache/commons/math3/linear/AbstractRealMatrix.DEFAULT_FORMAT:Lorg/apache/commons/math3/linear/RealMatrixFormat; (0, 0)
	12 invokevirtual (0, 0)
	13 org/apache/commons/math3/linear/RealMatrixFormat.getFormat:()Ljava/text/NumberFormat; (0, 0)
	15 iconst_1 (0, 0)
	16 invokevirtual (0, 0)
	17 java/text/NumberFormat.setMinimumFractionDigits:(I)V (0, 0)
	19 return (0, 0)

