Method: start
	0 aload_0 (0, 0)
	1 iload_3 (0, 0)
	2 putfield (0, 0)
	3 org/apache/commons/math3/linear/AbstractRealMatrix$4.startRow:I (0, 0)
	5 aload_0 (0, 0)
	6 iload (0, 0)
	7 #5 (0, 0)
	8 putfield (0, 0)
	9 org/apache/commons/math3/linear/AbstractRealMatrix$4.startColumn:I (0, 0)
	11 return (0, 0)

Method: visit
	0 aload_0 (0, 0)
	1 getfield (0, 0)
	2 org/apache/commons/math3/linear/AbstractRealMatrix$4.val$destination:[[D (0, 0)
	4 iload_1 (0, 0)
	5 aload_0 (0, 0)
	6 getfield (0, 0)
	7 org/apache/commons/math3/linear/AbstractRealMatrix$4.startRow:I (0, 0)
	9 isub (0, 0)
	10 aaload (0, 0)
	11 iload_2 (0, 0)
	12 aload_0 (0, 0)
	13 getfield (0, 0)
	14 org/apache/commons/math3/linear/AbstractRealMatrix$4.startColumn:I (0, 0)
	16 isub (0, 0)
	17 dload_3 (0, 0)
	18 dastore (0, 0)
	19 return (0, 0)

