Method: <init>
	0 aload_0 (0, 0)
	1 invokespecial (0, 0)
	2 java/lang/Object.<init>:()V (0, 0)
	4 iload_2 (2, 1)
	5 ifgt (2, 1)
	6 18 (2, 1)
	8 new (2, 1)
	9 org/apache/commons/math3/exception/NotStrictlyPositiveException (2, 1)
	11 dup (2, 1)
	12 getstatic (2, 1)
	13 org/apache/commons/math3/exception/util/LocalizedFormats.DIMENSION:Lorg/apache/commons/math3/exception/util/LocalizedFormats; (2, 1)
	15 iload_2 (2, 1)
	16 invokestatic (2, 1)
	17 java/lang/Integer.valueOf:(I)Ljava/lang/Integer; (2, 1)
	19 invokespecial (2, 1)
	20 org/apache/commons/math3/exception/NotStrictlyPositiveException.<init>:(Lorg/apache/commons/math3/exception/util/Localizable;Ljava/lang/Number;)V (2, 1)
	22 athrow (2, 1)
	23 iload_3 (2, 1)
	24 ifgt (2, 1)
	25 18 (2, 1)
	27 new (2, 1)
	28 org/apache/commons/math3/exception/NotStrictlyPositiveException (2, 1)
	30 dup (2, 1)
	31 getstatic (2, 1)
	32 org/apache/commons/math3/exception/util/LocalizedFormats.DIMENSION:Lorg/apache/commons/math3/exception/util/LocalizedFormats; (2, 1)
	34 iload_3 (2, 1)
	35 invokestatic (2, 1)
	36 java/lang/Integer.valueOf:(I)Ljava/lang/Integer; (2, 1)
	38 invokespecial (2, 1)
	39 org/apache/commons/math3/exception/NotStrictlyPositiveException.<init>:(Lorg/apache/commons/math3/exception/util/Localizable;Ljava/lang/Number;)V (2, 1)
	41 athrow (2, 1)
	42 aload_0 (0, 0)
	43 aload_1 (0, 0)
	44 putfield (0, 0)
	45 org/apache/commons/math3/linear/AbstractFieldMatrix.field:Lorg/apache/commons/math3/Field; (0, 0)
	47 return (0, 0)

Method: extractField
	0 aload_0 (1, 1)
	1 arraylength (1, 1)
	2 ifne (1, 1)
	3 14 (1, 1)
	5 new (1, 1)
	6 org/apache/commons/math3/exception/NoDataException (1, 1)
	8 dup (1, 1)
	9 getstatic (1, 1)
	10 org/apache/commons/math3/exception/util/LocalizedFormats.AT_LEAST_ONE_ROW:Lorg/apache/commons/math3/exception/util/LocalizedFormats; (1, 1)
	12 invokespecial (1, 1)
	13 org/apache/commons/math3/exception/NoDataException.<init>:(Lorg/apache/commons/math3/exception/util/Localizable;)V (1, 1)
	15 athrow (1, 1)
	16 aload_0 (0, 0)
	17 iconst_0 (0, 0)
	18 aaload (0, 0)
	19 invokeinterface (0, 0)
	20 org/apache/commons/math3/FieldElement.org/apache/commons/math3/util/MathArrays (0, 0)
	22 0 (0, 0)
	24 areturn (0, 0)

Method: buildArray
	0 aload_0 (0, 0)
	1 iload_1 (0, 0)
	2 invokestatic (0, 0)
	3 org/apache/commons/math3/util/MathArrays.buildArray:(Lorg/apache/commons/math3/Field;I)[Ljava/lang/Object; (0, 0)
	5 checkcast (0, 0)
	6 [Lorg/apache/commons/math3/FieldElement; (0, 0)
	8 areturn (0, 0)

Method: getField
	0 aload_0 (0, 0)
	1 getfield (0, 0)
	2 org/apache/commons/math3/linear/AbstractFieldMatrix.field:Lorg/apache/commons/math3/Field; (0, 0)
	4 areturn (0, 0)

Method: add
	0 aload_0 (0, 0)
	1 aload_1 (0, 0)
	2 invokevirtual (0, 0)
	3 org/apache/commons/math3/linear/AbstractFieldMatrix.checkAdditionCompatible:(Lorg/apache/commons/math3/linear/FieldMatrix;)V (0, 0)
	5 aload_0 (0, 0)
	6 invokevirtual (0, 0)
	7 org/apache/commons/math3/linear/AbstractFieldMatrix.getRowDimension:()I (0, 0)
	9 istore_2 (0, 0)
	10 aload_0 (0, 0)
	11 invokevirtual (0, 0)
	12 org/apache/commons/math3/linear/AbstractFieldMatrix.getColumnDimension:()I (0, 0)
	14 istore_3 (0, 0)
	15 aload_0 (0, 0)
	16 iload_2 (0, 0)
	17 iload_3 (0, 0)
	18 invokevirtual (0, 0)
	19 org/apache/commons/math3/linear/AbstractFieldMatrix.createMatrix:(II)Lorg/apache/commons/math3/linear/FieldMatrix; (0, 0)
	21 astore (0, 0)
	22 #4 (0, 0)
	23 iconst_0 (1, 4)
	24 istore (1, 4)
	25 #5 (1, 4)
	26 iload (1, 4)
	27 #5 (1, 4)
	28 iload_2 (1, 4)
	29 if_icmpge (1, 4)
	30 61 (1, 4)
	32 iconst_0 (2, 4)
	33 istore (2, 4)
	34 #6 (2, 4)
	35 iload (2, 4)
	36 #6 (2, 4)
	37 iload_3 (2, 4)
	38 if_icmpge (2, 4)
	39 46 (2, 4)
	41 aload (2, 4)
	42 #4 (2, 4)
	43 iload (2, 4)
	44 #5 (2, 4)
	45 iload (2, 4)
	46 #6 (2, 4)
	47 aload_0 (2, 4)
	48 iload (2, 4)
	49 #5 (2, 4)
	50 iload (2, 4)
	51 #6 (2, 4)
	52 invokevirtual (2, 4)
	53 org/apache/commons/math3/linear/AbstractFieldMatrix.getEntry:(II)Lorg/apache/commons/math3/FieldElement; (2, 4)
	55 aload_1 (2, 4)
	56 iload (2, 4)
	57 #5 (2, 4)
	58 iload (2, 4)
	59 #6 (2, 4)
	60 invokeinterface (2, 4)
	61 org/apache/commons/math3/linear/FieldMatrix.add:(Ljava/lang/Object;)Ljava/lang/Object; (2, 4)
	63 0 (2, 4)
	65 invokeinterface (2, 4)
	66 org/apache/commons/math3/FieldElement.org/apache/commons/math3/FieldElement (2, 4)
	68 0 (2, 4)
	70 checkcast (2, 4)
	71 org/apache/commons/math3/FieldElement (2, 4)
	73 invokeinterface (2, 4)
	74 org/apache/commons/math3/linear/FieldMatrix.checkSubtractionCompatible:(Lorg/apache/commons/math3/linear/FieldMatrix;)V (2, 4)
	76 0 (2, 4)
	78 iinc (2, 4)
	79 #6 (2, 4)
	80 -89 (2, 4)
	81 goto (2, 4)
	82 -46 (2, 4)
	84 iinc (2, 4)
	85 #5 (2, 4)
	86 -89 (2, 4)
	87 goto (2, 4)
	88 -61 (2, 4)
	90 aload (1, 4)
	91 #4 (1, 4)
	92 areturn (1, 4)

Method: subtract
	0 aload_0 (0, 0)
	1 aload_1 (0, 0)
	2 invokevirtual (0, 0)
	3 org/apache/commons/math3/linear/AbstractFieldMatrix.checkSubtractionCompatible:(Lorg/apache/commons/math3/linear/FieldMatrix;)V (0, 0)
	5 aload_0 (0, 0)
	6 invokevirtual (0, 0)
	7 org/apache/commons/math3/linear/AbstractFieldMatrix.getRowDimension:()I (0, 0)
	9 istore_2 (0, 0)
	10 aload_0 (0, 0)
	11 invokevirtual (0, 0)
	12 org/apache/commons/math3/linear/AbstractFieldMatrix.getColumnDimension:()I (0, 0)
	14 istore_3 (0, 0)
	15 aload_0 (0, 0)
	16 iload_2 (0, 0)
	17 iload_3 (0, 0)
	18 invokevirtual (0, 0)
	19 org/apache/commons/math3/linear/AbstractFieldMatrix.createMatrix:(II)Lorg/apache/commons/math3/linear/FieldMatrix; (0, 0)
	21 astore (0, 0)
	22 #4 (0, 0)
	23 iconst_0 (1, 4)
	24 istore (1, 4)
	25 #5 (1, 4)
	26 iload (1, 4)
	27 #5 (1, 4)
	28 iload_2 (1, 4)
	29 if_icmpge (1, 4)
	30 61 (1, 4)
	32 iconst_0 (2, 4)
	33 istore (2, 4)
	34 #6 (2, 4)
	35 iload (2, 4)
	36 #6 (2, 4)
	37 iload_3 (2, 4)
	38 if_icmpge (2, 4)
	39 46 (2, 4)
	41 aload (2, 4)
	42 #4 (2, 4)
	43 iload (2, 4)
	44 #5 (2, 4)
	45 iload (2, 4)
	46 #6 (2, 4)
	47 aload_0 (2, 4)
	48 iload (2, 4)
	49 #5 (2, 4)
	50 iload (2, 4)
	51 #6 (2, 4)
	52 invokevirtual (2, 4)
	53 org/apache/commons/math3/linear/AbstractFieldMatrix.getEntry:(II)Lorg/apache/commons/math3/FieldElement; (2, 4)
	55 aload_1 (2, 4)
	56 iload (2, 4)
	57 #5 (2, 4)
	58 iload (2, 4)
	59 #6 (2, 4)
	60 invokeinterface (2, 4)
	61 org/apache/commons/math3/linear/FieldMatrix.add:(Ljava/lang/Object;)Ljava/lang/Object; (2, 4)
	63 0 (2, 4)
	65 invokeinterface (2, 4)
	66 org/apache/commons/math3/FieldElement.multiply:(Ljava/lang/Object;)Ljava/lang/Object; (2, 4)
	68 0 (2, 4)
	70 checkcast (2, 4)
	71 org/apache/commons/math3/FieldElement (2, 4)
	73 invokeinterface (2, 4)
	74 org/apache/commons/math3/linear/FieldMatrix.checkSubtractionCompatible:(Lorg/apache/commons/math3/linear/FieldMatrix;)V (2, 4)
	76 0 (2, 4)
	78 iinc (2, 4)
	79 #6 (2, 4)
	80 -89 (2, 4)
	81 goto (2, 4)
	82 -46 (2, 4)
	84 iinc (2, 4)
	85 #5 (2, 4)
	86 -89 (2, 4)
	87 goto (2, 4)
	88 -61 (2, 4)
	90 aload (1, 4)
	91 #4 (1, 4)
	92 areturn (1, 4)

Method: scalarAdd
	0 aload_0 (0, 0)
	1 invokevirtual (0, 0)
	2 org/apache/commons/math3/linear/AbstractFieldMatrix.getRowDimension:()I (0, 0)
	4 istore_2 (0, 0)
	5 aload_0 (0, 0)
	6 invokevirtual (0, 0)
	7 org/apache/commons/math3/linear/AbstractFieldMatrix.getColumnDimension:()I (0, 0)
	9 istore_3 (0, 0)
	10 aload_0 (0, 0)
	11 iload_2 (0, 0)
	12 iload_3 (0, 0)
	13 invokevirtual (0, 0)
	14 org/apache/commons/math3/linear/AbstractFieldMatrix.createMatrix:(II)Lorg/apache/commons/math3/linear/FieldMatrix; (0, 0)
	16 astore (0, 0)
	17 #4 (0, 0)
	18 iconst_0 (1, 4)
	19 istore (1, 4)
	20 #5 (1, 4)
	21 iload (1, 4)
	22 #5 (1, 4)
	23 iload_2 (1, 4)
	24 if_icmpge (1, 4)
	25 52 (1, 4)
	27 iconst_0 (2, 4)
	28 istore (2, 4)
	29 #6 (2, 4)
	30 iload (2, 4)
	31 #6 (2, 4)
	32 iload_3 (2, 4)
	33 if_icmpge (2, 4)
	34 37 (2, 4)
	36 aload (2, 4)
	37 #4 (2, 4)
	38 iload (2, 4)
	39 #5 (2, 4)
	40 iload (2, 4)
	41 #6 (2, 4)
	42 aload_0 (2, 4)
	43 iload (2, 4)
	44 #5 (2, 4)
	45 iload (2, 4)
	46 #6 (2, 4)
	47 invokevirtual (2, 4)
	48 org/apache/commons/math3/linear/AbstractFieldMatrix.getEntry:(II)Lorg/apache/commons/math3/FieldElement; (2, 4)
	50 aload_1 (2, 4)
	51 invokeinterface (2, 4)
	52 org/apache/commons/math3/FieldElement.org/apache/commons/math3/FieldElement (2, 4)
	54 0 (2, 4)
	56 checkcast (2, 4)
	57 org/apache/commons/math3/FieldElement (2, 4)
	59 invokeinterface (2, 4)
	60 org/apache/commons/math3/linear/FieldMatrix.checkSubtractionCompatible:(Lorg/apache/commons/math3/linear/FieldMatrix;)V (2, 4)
	62 0 (2, 4)
	64 iinc (2, 4)
	65 #6 (2, 4)
	66 -89 (2, 4)
	67 goto (2, 4)
	68 -37 (2, 4)
	70 iinc (2, 4)
	71 #5 (2, 4)
	72 -89 (2, 4)
	73 goto (2, 4)
	74 -52 (2, 4)
	76 aload (1, 4)
	77 #4 (1, 4)
	78 areturn (1, 4)

Method: scalarMultiply
	0 aload_0 (0, 0)
	1 invokevirtual (0, 0)
	2 org/apache/commons/math3/linear/AbstractFieldMatrix.getRowDimension:()I (0, 0)
	4 istore_2 (0, 0)
	5 aload_0 (0, 0)
	6 invokevirtual (0, 0)
	7 org/apache/commons/math3/linear/AbstractFieldMatrix.getColumnDimension:()I (0, 0)
	9 istore_3 (0, 0)
	10 aload_0 (0, 0)
	11 iload_2 (0, 0)
	12 iload_3 (0, 0)
	13 invokevirtual (0, 0)
	14 org/apache/commons/math3/linear/AbstractFieldMatrix.createMatrix:(II)Lorg/apache/commons/math3/linear/FieldMatrix; (0, 0)
	16 astore (0, 0)
	17 #4 (0, 0)
	18 iconst_0 (1, 4)
	19 istore (1, 4)
	20 #5 (1, 4)
	21 iload (1, 4)
	22 #5 (1, 4)
	23 iload_2 (1, 4)
	24 if_icmpge (1, 4)
	25 52 (1, 4)
	27 iconst_0 (2, 4)
	28 istore (2, 4)
	29 #6 (2, 4)
	30 iload (2, 4)
	31 #6 (2, 4)
	32 iload_3 (2, 4)
	33 if_icmpge (2, 4)
	34 37 (2, 4)
	36 aload (2, 4)
	37 #4 (2, 4)
	38 iload (2, 4)
	39 #5 (2, 4)
	40 iload (2, 4)
	41 #6 (2, 4)
	42 aload_0 (2, 4)
	43 iload (2, 4)
	44 #5 (2, 4)
	45 iload (2, 4)
	46 #6 (2, 4)
	47 invokevirtual (2, 4)
	48 org/apache/commons/math3/linear/AbstractFieldMatrix.getEntry:(II)Lorg/apache/commons/math3/FieldElement; (2, 4)
	50 aload_1 (2, 4)
	51 invokeinterface (2, 4)
	52 org/apache/commons/math3/FieldElement.checkMultiplicationCompatible:(Lorg/apache/commons/math3/linear/FieldMatrix;)V (2, 4)
	54 0 (2, 4)
	56 checkcast (2, 4)
	57 org/apache/commons/math3/FieldElement (2, 4)
	59 invokeinterface (2, 4)
	60 org/apache/commons/math3/linear/FieldMatrix.checkSubtractionCompatible:(Lorg/apache/commons/math3/linear/FieldMatrix;)V (2, 4)
	62 0 (2, 4)
	64 iinc (2, 4)
	65 #6 (2, 4)
	66 -89 (2, 4)
	67 goto (2, 4)
	68 -37 (2, 4)
	70 iinc (2, 4)
	71 #5 (2, 4)
	72 -89 (2, 4)
	73 goto (2, 4)
	74 -52 (2, 4)
	76 aload (1, 4)
	77 #4 (1, 4)
	78 areturn (1, 4)

Method: multiply
	0 aload_0 (0, 0)
	1 aload_1 (0, 0)
	2 invokevirtual (0, 0)
	3 org/apache/commons/math3/linear/AbstractFieldMatrix.checkMultiplicationCompatible:(Lorg/apache/commons/math3/linear/FieldMatrix;)V (0, 0)
	5 aload_0 (0, 0)
	6 invokevirtual (0, 0)
	7 org/apache/commons/math3/linear/AbstractFieldMatrix.getRowDimension:()I (0, 0)
	9 istore_2 (0, 0)
	10 aload_1 (0, 0)
	11 invokeinterface (0, 0)
	12 org/apache/commons/math3/linear/FieldMatrix.createMatrix:(II)Lorg/apache/commons/math3/linear/FieldMatrix; (0, 0)
	14 0 (0, 0)
	16 istore_3 (0, 0)
	17 aload_0 (0, 0)
	18 invokevirtual (0, 0)
	19 org/apache/commons/math3/linear/AbstractFieldMatrix.getColumnDimension:()I (0, 0)
	21 istore (0, 0)
	22 #4 (0, 0)
	23 aload_0 (0, 0)
	24 iload_2 (0, 0)
	25 iload_3 (0, 0)
	26 invokevirtual (0, 0)
	27 org/apache/commons/math3/linear/AbstractFieldMatrix.createMatrix:(II)Lorg/apache/commons/math3/linear/FieldMatrix; (0, 0)
	29 astore (0, 0)
	30 #5 (0, 0)
	31 iconst_0 (1, 4)
	32 istore (1, 4)
	33 #6 (1, 4)
	34 iload (1, 4)
	35 #6 (1, 4)
	36 iload_2 (1, 4)
	37 if_icmpge (1, 4)
	38 102 (1, 4)
	40 iconst_0 (2, 4)
	41 istore (2, 4)
	42 #7 (2, 4)
	43 iload (2, 4)
	44 #7 (2, 4)
	45 iload_3 (2, 4)
	46 if_icmpge (2, 4)
	47 87 (2, 4)
	49 aload_0 (2, 4)
	50 getfield (2, 4)
	51 org/apache/commons/math3/linear/AbstractFieldMatrix.field:Lorg/apache/commons/math3/Field; (2, 4)
	53 invokeinterface (2, 4)
	54 org/apache/commons/math3/Field.multiply:(Lorg/apache/commons/math3/linear/FieldMatrix;)Lorg/apache/commons/math3/linear/FieldMatrix; (2, 4)
	56 0 (2, 4)
	58 checkcast (2, 4)
	59 org/apache/commons/math3/FieldElement (2, 4)
	61 astore (2, 4)
	62 #8 (2, 4)
	63 iconst_0 (3, 4)
	64 istore (3, 4)
	65 #9 (3, 4)
	66 iload (3, 4)
	67 #9 (3, 4)
	68 iload (3, 4)
	69 #4 (3, 4)
	70 if_icmpge (3, 4)
	71 44 (3, 4)
	73 aload (3, 4)
	74 #8 (3, 4)
	75 aload_0 (3, 4)
	76 iload (3, 4)
	77 #6 (3, 4)
	78 iload (3, 4)
	79 #9 (3, 4)
	80 invokevirtual (3, 4)
	81 org/apache/commons/math3/linear/AbstractFieldMatrix.getEntry:(II)Lorg/apache/commons/math3/FieldElement; (3, 4)
	83 aload_1 (3, 4)
	84 iload (3, 4)
	85 #9 (3, 4)
	86 iload (3, 4)
	87 #7 (3, 4)
	88 invokeinterface (3, 4)
	89 org/apache/commons/math3/linear/FieldMatrix.add:(Ljava/lang/Object;)Ljava/lang/Object; (3, 4)
	91 0 (3, 4)
	93 invokeinterface (3, 4)
	94 org/apache/commons/math3/FieldElement.checkMultiplicationCompatible:(Lorg/apache/commons/math3/linear/FieldMatrix;)V (3, 4)
	96 0 (3, 4)
	98 invokeinterface (3, 4)
	99 org/apache/commons/math3/FieldElement.org/apache/commons/math3/FieldElement (3, 4)
	101 0 (3, 4)
	103 checkcast (3, 4)
	104 org/apache/commons/math3/FieldElement (3, 4)
	106 astore (3, 4)
	107 #8 (3, 4)
	108 iinc (3, 4)
	109 #9 (3, 4)
	110 -89 (3, 4)
	111 goto (3, 4)
	112 -45 (3, 4)
	114 aload (2, 4)
	115 #5 (2, 4)
	116 iload (2, 4)
	117 #6 (2, 4)
	118 iload (2, 4)
	119 #7 (2, 4)
	120 aload (2, 4)
	121 #8 (2, 4)
	122 invokeinterface (2, 4)
	123 org/apache/commons/math3/linear/FieldMatrix.checkSubtractionCompatible:(Lorg/apache/commons/math3/linear/FieldMatrix;)V (2, 4)
	125 0 (2, 4)
	127 iinc (2, 4)
	128 #7 (2, 4)
	129 -89 (2, 4)
	130 goto (2, 4)
	131 -87 (2, 4)
	133 iinc (2, 4)
	134 #6 (2, 4)
	135 -89 (2, 4)
	136 goto (2, 4)
	137 -102 (2, 4)
	139 aload (1, 4)
	140 #5 (1, 4)
	141 areturn (1, 4)

Method: preMultiply
	0 new (0, 0)
	1 org/apache/commons/math3/linear/ArrayFieldVector (0, 0)
	3 dup (0, 0)
	4 aload_0 (0, 0)
	5 getfield (0, 0)
	6 org/apache/commons/math3/linear/AbstractFieldMatrix.field:Lorg/apache/commons/math3/Field; (0, 0)
	8 aload_0 (0, 0)
	9 aload_1 (0, 0)
	10 checkcast (0, 0)
	11 org/apache/commons/math3/linear/ArrayFieldVector (0, 0)
	13 invokevirtual (0, 0)
	14 org/apache/commons/math3/linear/ArrayFieldVector.getDataRef:()[Lorg/apache/commons/math3/FieldElement; (0, 0)
	16 invokevirtual (0, 0)
	17 org/apache/commons/math3/linear/AbstractFieldMatrix.preMultiply:([Lorg/apache/commons/math3/FieldElement;)[Lorg/apache/commons/math3/FieldElement; (0, 0)
	19 iconst_0 (0, 0)
	20 invokespecial (0, 0)
	21 org/apache/commons/math3/linear/ArrayFieldVector.<init>:(Lorg/apache/commons/math3/Field;[Lorg/apache/commons/math3/FieldElement;Z)V (0, 0)
	23 areturn (0, 0)
	24 astore_2 (0, 0)
	25 aload_0 (0, 0)
	26 invokevirtual (0, 0)
	27 org/apache/commons/math3/linear/AbstractFieldMatrix.getRowDimension:()I (0, 0)
	29 istore_3 (0, 0)
	30 aload_0 (0, 0)
	31 invokevirtual (0, 0)
	32 org/apache/commons/math3/linear/AbstractFieldMatrix.getColumnDimension:()I (0, 0)
	34 istore (0, 0)
	35 #4 (0, 0)
	36 aload_1 (1, 1)
	37 invokeinterface (1, 1)
	38 org/apache/commons/math3/linear/FieldVector.getEntry:(I)Lorg/apache/commons/math3/FieldElement; (1, 1)
	40 0 (1, 1)
	42 iload_3 (1, 1)
	43 if_icmpeq (1, 1)
	44 18 (1, 1)
	46 new (1, 1)
	47 org/apache/commons/math3/exception/DimensionMismatchException (1, 1)
	49 dup (1, 1)
	50 aload_1 (1, 1)
	51 invokeinterface (1, 1)
	52 org/apache/commons/math3/linear/FieldVector.getEntry:(I)Lorg/apache/commons/math3/FieldElement; (1, 1)
	54 0 (1, 1)
	56 iload_3 (1, 1)
	57 invokespecial (1, 1)
	58 org/apache/commons/math3/exception/DimensionMismatchException.<init>:(II)V (1, 1)
	60 athrow (1, 1)
	61 aload_0 (0, 0)
	62 getfield (0, 0)
	63 org/apache/commons/math3/linear/AbstractFieldMatrix.field:Lorg/apache/commons/math3/Field; (0, 0)
	65 iload (0, 0)
	66 #4 (0, 0)
	67 invokestatic (0, 0)
	68 org/apache/commons/math3/util/MathArrays.buildArray:(Lorg/apache/commons/math3/Field;I)[Ljava/lang/Object; (0, 0)
	70 checkcast (0, 0)
	71 [Lorg/apache/commons/math3/FieldElement; (0, 0)
	73 astore (0, 0)
	74 #5 (0, 0)
	75 iconst_0 (1, 4)
	76 istore (1, 4)
	77 #6 (1, 4)
	78 iload (1, 4)
	79 #6 (1, 4)
	80 iload (1, 4)
	81 #4 (1, 4)
	82 if_icmpge (1, 4)
	83 78 (1, 4)
	85 aload_0 (1, 4)
	86 getfield (1, 4)
	87 org/apache/commons/math3/linear/AbstractFieldMatrix.field:Lorg/apache/commons/math3/Field; (1, 4)
	89 invokeinterface (1, 4)
	90 org/apache/commons/math3/Field.multiply:(Lorg/apache/commons/math3/linear/FieldMatrix;)Lorg/apache/commons/math3/linear/FieldMatrix; (1, 4)
	92 0 (1, 4)
	94 checkcast (1, 4)
	95 org/apache/commons/math3/FieldElement (1, 4)
	97 astore (1, 4)
	98 #7 (1, 4)
	99 iconst_0 (2, 4)
	100 istore (2, 4)
	101 #8 (2, 4)
	102 iload (2, 4)
	103 #8 (2, 4)
	104 iload_3 (2, 4)
	105 if_icmpge (2, 4)
	106 42 (2, 4)
	108 aload (2, 4)
	109 #7 (2, 4)
	110 aload_0 (2, 4)
	111 iload (2, 4)
	112 #8 (2, 4)
	113 iload (2, 4)
	114 #6 (2, 4)
	115 invokevirtual (2, 4)
	116 org/apache/commons/math3/linear/AbstractFieldMatrix.getEntry:(II)Lorg/apache/commons/math3/FieldElement; (2, 4)
	118 aload_1 (2, 4)
	119 iload (2, 4)
	120 #8 (2, 4)
	121 invokeinterface (2, 4)
	122 org/apache/commons/math3/linear/FieldVector.getColumn:(I)[Lorg/apache/commons/math3/FieldElement; (2, 4)
	124 0 (2, 4)
	126 invokeinterface (2, 4)
	127 org/apache/commons/math3/FieldElement.checkMultiplicationCompatible:(Lorg/apache/commons/math3/linear/FieldMatrix;)V (2, 4)
	129 0 (2, 4)
	131 invokeinterface (2, 4)
	132 org/apache/commons/math3/FieldElement.org/apache/commons/math3/FieldElement (2, 4)
	134 0 (2, 4)
	136 checkcast (2, 4)
	137 org/apache/commons/math3/FieldElement (2, 4)
	139 astore (2, 4)
	140 #7 (2, 4)
	141 iinc (2, 4)
	142 #8 (2, 4)
	143 -89 (2, 4)
	144 goto (2, 4)
	145 -42 (2, 4)
	147 aload (1, 4)
	148 #5 (1, 4)
	149 iload (1, 4)
	150 #6 (1, 4)
	151 aload (1, 4)
	152 #7 (1, 4)
	153 aastore (1, 4)
	154 iinc (1, 4)
	155 #6 (1, 4)
	156 -89 (1, 4)
	157 goto (1, 4)
	158 -79 (1, 4)
	160 new (0, 0)
	161 org/apache/commons/math3/linear/ArrayFieldVector (0, 0)
	163 dup (0, 0)
	164 aload_0 (0, 0)
	165 getfield (0, 0)
	166 org/apache/commons/math3/linear/AbstractFieldMatrix.field:Lorg/apache/commons/math3/Field; (0, 0)
	168 aload (0, 0)
	169 #5 (0, 0)
	170 iconst_0 (0, 0)
	171 invokespecial (0, 0)
	172 org/apache/commons/math3/linear/ArrayFieldVector.<init>:(Lorg/apache/commons/math3/Field;[Lorg/apache/commons/math3/FieldElement;Z)V (0, 0)
	174 areturn (0, 0)

Method: power
	0 iload_1 (1, 1)
	1 ifge (1, 1)
	2 15 (1, 1)
	4 new (1, 1)
	5 org/apache/commons/math3/exception/NotPositiveException (1, 1)
	7 dup (1, 1)
	8 iload_1 (1, 1)
	9 invokestatic (1, 1)
	10 java/lang/Integer.valueOf:(I)Ljava/lang/Integer; (1, 1)
	12 invokespecial (1, 1)
	13 org/apache/commons/math3/exception/NotPositiveException.<init>:(Ljava/lang/Number;)V (1, 1)
	15 athrow (1, 1)
	16 aload_0 (1, 1)
	17 invokevirtual (1, 1)
	18 org/apache/commons/math3/linear/AbstractFieldMatrix.isSquare:()Z (1, 1)
	20 ifne (1, 1)
	21 19 (1, 1)
	23 new (1, 1)
	24 org/apache/commons/math3/linear/NonSquareMatrixException (1, 1)
	26 dup (1, 1)
	27 aload_0 (1, 1)
	28 invokevirtual (1, 1)
	29 org/apache/commons/math3/linear/AbstractFieldMatrix.getRowDimension:()I (1, 1)
	31 aload_0 (1, 1)
	32 invokevirtual (1, 1)
	33 org/apache/commons/math3/linear/AbstractFieldMatrix.getColumnDimension:()I (1, 1)
	35 invokespecial (1, 1)
	36 org/apache/commons/math3/linear/NonSquareMatrixException.<init>:(II)V (1, 1)
	38 athrow (1, 1)
	39 iload_1 (1, 1)
	40 ifne (1, 1)
	41 15 (1, 1)
	43 aload_0 (1, 1)
	44 invokevirtual (1, 1)
	45 org/apache/commons/math3/linear/AbstractFieldMatrix.getField:()Lorg/apache/commons/math3/Field; (1, 1)
	47 aload_0 (1, 1)
	48 invokevirtual (1, 1)
	49 org/apache/commons/math3/linear/AbstractFieldMatrix.getRowDimension:()I (1, 1)
	51 invokestatic (1, 1)
	52 org/apache/commons/math3/linear/MatrixUtils.createFieldIdentityMatrix:(Lorg/apache/commons/math3/Field;I)Lorg/apache/commons/math3/linear/FieldMatrix; (1, 1)
	54 areturn (1, 1)
	55 iload_1 (1, 1)
	56 iconst_1 (1, 1)
	57 if_icmpne (1, 1)
	58 8 (1, 1)
	60 aload_0 (1, 1)
	61 invokevirtual (1, 1)
	62 org/apache/commons/math3/linear/AbstractFieldMatrix.copy:()Lorg/apache/commons/math3/linear/FieldMatrix; (1, 1)
	64 areturn (1, 1)
	65 iload_1 (0, 0)
	66 iconst_1 (0, 0)
	67 isub (0, 0)
	68 istore_2 (0, 0)
	69 iload_2 (0, 4)
	70 invokestatic (0, 4)
	71 java/lang/Integer.toBinaryString:(I)Ljava/lang/String; (0, 4)
	73 invokevirtual (0, 4)
	74 java/lang/String.toCharArray:()[C (0, 4)
	76 astore_3 (0, 4)
	77 new (0, 4)
	78 java/util/ArrayList (0, 4)
	80 dup (0, 4)
	81 invokespecial (0, 4)
	82 java/util/ArrayList.<init>:()V (0, 4)
	84 astore (0, 4)
	85 #4 (0, 4)
	86 iconst_0 (1, 4)
	87 istore (1, 4)
	88 #5 (1, 4)
	89 iload (1, 4)
	90 #5 (1, 4)
	91 aload_3 (1, 4)
	92 arraylength (1, 4)
	93 if_icmpge (1, 4)
	94 38 (1, 4)
	96 aload_3 (2, 1)
	97 iload (2, 1)
	98 #5 (2, 1)
	99 caload (2, 1)
	100 bipush (2, 1)
	101 49 (2, 1)
	102 if_icmpne (2, 1)
	103 23 (2, 1)
	105 aload_3 (2, 1)
	106 arraylength (2, 1)
	107 iload (2, 1)
	108 #5 (2, 1)
	109 isub (2, 1)
	110 iconst_1 (2, 1)
	111 isub (2, 1)
	112 istore (2, 1)
	113 #6 (2, 1)
	114 aload (2, 1)
	115 #4 (2, 1)
	116 iload (2, 1)
	117 #6 (2, 1)
	118 invokestatic (2, 1)
	119 java/lang/Integer.valueOf:(I)Ljava/lang/Integer; (2, 1)
	121 invokevirtual (2, 1)
	122 java/util/ArrayList.add:(Ljava/lang/Object;)Z (2, 1)
	124 pop (2, 1)
	125 iinc (2, 1)
	126 #5 (2, 1)
	127 -89 (2, 1)
	128 goto (2, 1)
	129 -39 (2, 1)
	131 new (1, 4)
	132 java/util/ArrayList (1, 4)
	134 dup (1, 4)
	135 aload_3 (1, 4)
	136 arraylength (1, 4)
	137 invokespecial (1, 4)
	138 java/util/ArrayList.<init>:(I)V (1, 4)
	140 astore (1, 4)
	141 #5 (1, 4)
	142 aload (1, 4)
	143 #5 (1, 4)
	144 iconst_0 (1, 4)
	145 aload_0 (1, 4)
	146 invokevirtual (1, 4)
	147 org/apache/commons/math3/linear/AbstractFieldMatrix.copy:()Lorg/apache/commons/math3/linear/FieldMatrix; (1, 4)
	149 invokevirtual (1, 4)
	150 java/util/ArrayList.add:(ILjava/lang/Object;)V (1, 4)
	152 iconst_1 (2, 4)
	153 istore (2, 4)
	154 #6 (2, 4)
	155 iload (2, 4)
	156 #6 (2, 4)
	157 aload_3 (2, 4)
	158 arraylength (2, 4)
	159 if_icmpge (2, 4)
	160 43 (2, 4)
	162 aload (2, 4)
	163 #5 (2, 4)
	164 iload (2, 4)
	165 #6 (2, 4)
	166 iconst_1 (2, 4)
	167 isub (2, 4)
	168 invokevirtual (2, 4)
	169 java/util/ArrayList.get:(I)Ljava/lang/Object; (2, 4)
	171 checkcast (2, 4)
	172 org/apache/commons/math3/linear/FieldMatrix (2, 4)
	174 astore (2, 4)
	175 #7 (2, 4)
	176 aload (2, 4)
	177 #7 (2, 4)
	178 aload (2, 4)
	179 #7 (2, 4)
	180 invokeinterface (2, 4)
	181 org/apache/commons/math3/linear/FieldMatrix.org/apache/commons/math3/exception/NotPositiveException (2, 4)
	183 0 (2, 4)
	185 astore (2, 4)
	186 #8 (2, 4)
	187 aload (2, 4)
	188 #5 (2, 4)
	189 iload (2, 4)
	190 #6 (2, 4)
	191 aload (2, 4)
	192 #8 (2, 4)
	193 invokevirtual (2, 4)
	194 java/util/ArrayList.add:(ILjava/lang/Object;)V (2, 4)
	196 iinc (2, 4)
	197 #6 (2, 4)
	198 -89 (2, 4)
	199 goto (2, 4)
	200 -44 (2, 4)
	202 aload_0 (1, 4)
	203 invokevirtual (1, 4)
	204 org/apache/commons/math3/linear/AbstractFieldMatrix.copy:()Lorg/apache/commons/math3/linear/FieldMatrix; (1, 4)
	206 astore (1, 4)
	207 #6 (1, 4)
	208 aload (2, 4)
	209 #4 (2, 4)
	210 invokevirtual (2, 4)
	211 java/util/ArrayList.iterator:()Ljava/util/Iterator; (2, 4)
	213 astore (2, 4)
	214 #7 (2, 4)
	215 aload (2, 4)
	216 #7 (2, 4)
	217 invokeinterface (2, 4)
	218 java/util/Iterator.next:()Ljava/lang/Object; (2, 4)
	220 0 (2, 4)
	222 ifeq (2, 4)
	223 40 (2, 4)
	225 aload (2, 4)
	226 #7 (2, 4)
	227 invokeinterface (2, 4)
	228 java/util/Iterator.java/lang/Integer (2, 4)
	230 0 (2, 4)
	232 checkcast (2, 4)
	233 java/lang/Integer (2, 4)
	235 astore (2, 4)
	236 #8 (2, 4)
	237 aload (2, 4)
	238 #6 (2, 4)
	239 aload (2, 4)
	240 #5 (2, 4)
	241 aload (2, 4)
	242 #8 (2, 4)
	243 invokevirtual (2, 4)
	244 java/lang/Integer.intValue:()I (2, 4)
	246 invokevirtual (2, 4)
	247 java/util/ArrayList.get:(I)Ljava/lang/Object; (2, 4)
	249 checkcast (2, 4)
	250 org/apache/commons/math3/linear/FieldMatrix (2, 4)
	252 invokeinterface (2, 4)
	253 org/apache/commons/math3/linear/FieldMatrix.org/apache/commons/math3/exception/NotPositiveException (2, 4)
	255 0 (2, 4)
	257 astore (2, 4)
	258 #6 (2, 4)
	259 goto (1, 4)
	260 -44 (1, 4)
	262 aload (1, 4)
	263 #6 (1, 4)
	264 areturn (1, 4)

Method: getData
	0 aload_0 (0, 0)
	1 getfield (0, 0)
	2 org/apache/commons/math3/linear/AbstractFieldMatrix.field:Lorg/apache/commons/math3/Field; (0, 0)
	4 aload_0 (0, 0)
	5 invokevirtual (0, 0)
	6 org/apache/commons/math3/linear/AbstractFieldMatrix.getRowDimension:()I (0, 0)
	8 aload_0 (0, 0)
	9 invokevirtual (0, 0)
	10 org/apache/commons/math3/linear/AbstractFieldMatrix.getColumnDimension:()I (0, 0)
	12 invokestatic (0, 0)
	13 org/apache/commons/math3/util/MathArrays.buildArray:(Lorg/apache/commons/math3/Field;II)[[Ljava/lang/Object; (0, 0)
	15 checkcast (0, 0)
	16 [[Lorg/apache/commons/math3/FieldElement; (0, 0)
	18 astore_1 (0, 0)
	19 iconst_0 (1, 4)
	20 istore_2 (1, 4)
	21 iload_2 (1, 4)
	22 aload_1 (1, 4)
	23 arraylength (1, 4)
	24 if_icmpge (1, 4)
	25 40 (1, 4)
	27 aload_1 (1, 4)
	28 iload_2 (1, 4)
	29 aaload (1, 4)
	30 astore_3 (1, 4)
	31 iconst_0 (2, 4)
	32 istore (2, 4)
	33 #4 (2, 4)
	34 iload (2, 4)
	35 #4 (2, 4)
	36 aload_3 (2, 4)
	37 arraylength (2, 4)
	38 if_icmpge (2, 4)
	39 20 (2, 4)
	41 aload_3 (2, 4)
	42 iload (2, 4)
	43 #4 (2, 4)
	44 aload_0 (2, 4)
	45 iload_2 (2, 4)
	46 iload (2, 4)
	47 #4 (2, 4)
	48 invokevirtual (2, 4)
	49 org/apache/commons/math3/linear/AbstractFieldMatrix.getEntry:(II)Lorg/apache/commons/math3/FieldElement; (2, 4)
	51 aastore (2, 4)
	52 iinc (2, 4)
	53 #4 (2, 4)
	54 -89 (2, 4)
	55 goto (2, 4)
	56 -21 (2, 4)
	58 iinc (2, 4)
	59 #2 (2, 4)
	60 -89 (2, 4)
	61 goto (2, 4)
	62 -40 (2, 4)
	64 aload_1 (1, 4)
	65 areturn (1, 4)

Method: getSubMatrix
	0 aload_0 (0, 0)
	1 aload_1 (0, 0)
	2 aload_2 (0, 0)
	3 invokevirtual (0, 0)
	4 org/apache/commons/math3/linear/AbstractFieldMatrix.checkSubMatrixIndex:([I[I)V (0, 0)
	6 aload_0 (0, 0)
	7 aload_1 (0, 0)
	8 arraylength (0, 0)
	9 aload_2 (0, 0)
	10 arraylength (0, 0)
	11 invokevirtual (0, 0)
	12 org/apache/commons/math3/linear/AbstractFieldMatrix.createMatrix:(II)Lorg/apache/commons/math3/linear/FieldMatrix; (0, 0)
	14 astore_3 (0, 0)
	15 aload_3 (0, 0)
	16 new (0, 0)
	17 org/apache/commons/math3/linear/AbstractFieldMatrix$1 (0, 0)
	19 dup (0, 0)
	20 aload_0 (0, 0)
	21 aload_0 (0, 0)
	22 getfield (0, 0)
	23 org/apache/commons/math3/linear/AbstractFieldMatrix.field:Lorg/apache/commons/math3/Field; (0, 0)
	25 invokeinterface (0, 0)
	26 org/apache/commons/math3/Field.multiply:(Lorg/apache/commons/math3/linear/FieldMatrix;)Lorg/apache/commons/math3/linear/FieldMatrix; (0, 0)
	28 0 (0, 0)
	30 checkcast (0, 0)
	31 org/apache/commons/math3/FieldElement (0, 0)
	33 aload_1 (0, 0)
	34 aload_2 (0, 0)
	35 invokespecial (0, 0)
	36 org/apache/commons/math3/linear/AbstractFieldMatrix$1.<init>:(Lorg/apache/commons/math3/linear/AbstractFieldMatrix;Lorg/apache/commons/math3/FieldElement;[I[I)V (0, 0)
	38 invokeinterface (0, 0)
	39 org/apache/commons/math3/linear/FieldMatrix.org/apache/commons/math3/linear/MatrixDimensionMismatchException (0, 0)
	41 0 (0, 0)
	43 pop (0, 0)
	44 aload_3 (0, 0)
	45 areturn (0, 0)

Method: copySubMatrix
	0 aload_0 (0, 0)
	1 aload_1 (0, 0)
	2 aload_2 (0, 0)
	3 invokevirtual (0, 0)
	4 org/apache/commons/math3/linear/AbstractFieldMatrix.checkSubMatrixIndex:([I[I)V (0, 0)
	6 aload_3 (0, 1)
	7 arraylength (0, 1)
	8 aload_1 (0, 1)
	9 arraylength (0, 1)
	10 if_icmplt (0, 1)
	11 12 (0, 1)
	13 aload_3 (0, 1)
	14 iconst_0 (0, 1)
	15 aaload (0, 1)
	16 arraylength (0, 1)
	17 aload_2 (0, 1)
	18 arraylength (0, 1)
	19 if_icmpge (0, 1)
	20 21 (0, 1)
	22 new (0, 1)
	23 org/apache/commons/math3/linear/MatrixDimensionMismatchException (0, 1)
	25 dup (0, 1)
	26 aload_3 (0, 1)
	27 arraylength (0, 1)
	28 aload_3 (0, 1)
	29 iconst_0 (0, 1)
	30 aaload (0, 1)
	31 arraylength (0, 1)
	32 aload_1 (0, 1)
	33 arraylength (0, 1)
	34 aload_2 (0, 1)
	35 arraylength (0, 1)
	36 invokespecial (0, 1)
	37 org/apache/commons/math3/linear/MatrixDimensionMismatchException.<init>:(IIII)V (0, 1)
	39 athrow (0, 1)
	40 iconst_0 (1, 4)
	41 istore (1, 4)
	42 #4 (1, 4)
	43 iload (1, 4)
	44 #4 (1, 4)
	45 aload_1 (1, 4)
	46 arraylength (1, 4)
	47 if_icmpge (1, 4)
	48 48 (1, 4)
	50 aload_3 (1, 4)
	51 iload (1, 4)
	52 #4 (1, 4)
	53 aaload (1, 4)
	54 astore (1, 4)
	55 #5 (1, 4)
	56 iconst_0 (2, 4)
	57 istore (2, 4)
	58 #6 (2, 4)
	59 iload (2, 4)
	60 #6 (2, 4)
	61 aload_2 (2, 4)
	62 arraylength (2, 4)
	63 if_icmpge (2, 4)
	64 26 (2, 4)
	66 aload (2, 4)
	67 #5 (2, 4)
	68 iload (2, 4)
	69 #6 (2, 4)
	70 aload_0 (2, 4)
	71 aload_1 (2, 4)
	72 iload (2, 4)
	73 #4 (2, 4)
	74 iaload (2, 4)
	75 aload_2 (2, 4)
	76 iload (2, 4)
	77 #6 (2, 4)
	78 iaload (2, 4)
	79 invokevirtual (2, 4)
	80 org/apache/commons/math3/linear/AbstractFieldMatrix.getEntry:(II)Lorg/apache/commons/math3/FieldElement; (2, 4)
	82 aastore (2, 4)
	83 iinc (2, 4)
	84 #6 (2, 4)
	85 -89 (2, 4)
	86 goto (2, 4)
	87 -27 (2, 4)
	89 iinc (2, 4)
	90 #4 (2, 4)
	91 -89 (2, 4)
	92 goto (2, 4)
	93 -49 (2, 4)
	95 return (0, 1)

Method: setSubMatrix
	0 aload_1 (1, 1)
	1 ifnonnull (1, 1)
	2 11 (1, 1)
	4 new (1, 1)
	5 org/apache/commons/math3/exception/NullArgumentException (1, 1)
	7 dup (1, 1)
	8 invokespecial (1, 1)
	9 org/apache/commons/math3/exception/NullArgumentException.<init>:()V (1, 1)
	11 athrow (1, 1)
	12 aload_1 (0, 0)
	13 arraylength (0, 0)
	14 istore (0, 0)
	15 #4 (0, 0)
	16 iload (1, 1)
	17 #4 (1, 1)
	18 ifne (1, 1)
	19 14 (1, 1)
	21 new (1, 1)
	22 org/apache/commons/math3/exception/NoDataException (1, 1)
	24 dup (1, 1)
	25 getstatic (1, 1)
	26 org/apache/commons/math3/exception/util/LocalizedFormats.AT_LEAST_ONE_ROW:Lorg/apache/commons/math3/exception/util/LocalizedFormats; (1, 1)
	28 invokespecial (1, 1)
	29 org/apache/commons/math3/exception/NoDataException.<init>:(Lorg/apache/commons/math3/exception/util/Localizable;)V (1, 1)
	31 athrow (1, 1)
	32 aload_1 (0, 0)
	33 iconst_0 (0, 0)
	34 aaload (0, 0)
	35 arraylength (0, 0)
	36 istore (0, 0)
	37 #5 (0, 0)
	38 iload (1, 1)
	39 #5 (1, 1)
	40 ifne (1, 1)
	41 14 (1, 1)
	43 new (1, 1)
	44 org/apache/commons/math3/exception/NoDataException (1, 1)
	46 dup (1, 1)
	47 getstatic (1, 1)
	48 org/apache/commons/math3/exception/util/LocalizedFormats.AT_LEAST_ONE_COLUMN:Lorg/apache/commons/math3/exception/util/LocalizedFormats; (1, 1)
	50 invokespecial (1, 1)
	51 org/apache/commons/math3/exception/NoDataException.<init>:(Lorg/apache/commons/math3/exception/util/Localizable;)V (1, 1)
	53 athrow (1, 1)
	54 iconst_1 (1, 4)
	55 istore (1, 4)
	56 #6 (1, 4)
	57 iload (1, 4)
	58 #6 (1, 4)
	59 iload (1, 4)
	60 #4 (1, 4)
	61 if_icmpge (1, 4)
	62 34 (1, 4)
	64 aload_1 (2, 1)
	65 iload (2, 1)
	66 #6 (2, 1)
	67 aaload (2, 1)
	68 arraylength (2, 1)
	69 iload (2, 1)
	70 #5 (2, 1)
	71 if_icmpeq (2, 1)
	72 18 (2, 1)
	74 new (2, 1)
	75 org/apache/commons/math3/exception/DimensionMismatchException (2, 1)
	77 dup (2, 1)
	78 iload (2, 1)
	79 #5 (2, 1)
	80 aload_1 (2, 1)
	81 iload (2, 1)
	82 #6 (2, 1)
	83 aaload (2, 1)
	84 arraylength (2, 1)
	85 invokespecial (2, 1)
	86 org/apache/commons/math3/exception/DimensionMismatchException.<init>:(II)V (2, 1)
	88 athrow (2, 1)
	89 iinc (2, 1)
	90 #6 (2, 1)
	91 -89 (2, 1)
	92 goto (2, 1)
	93 -35 (2, 1)
	95 aload_0 (1, 4)
	96 iload_2 (1, 4)
	97 invokevirtual (1, 4)
	98 org/apache/commons/math3/linear/AbstractFieldMatrix.checkRowIndex:(I)V (1, 4)
	100 aload_0 (1, 4)
	101 iload_3 (1, 4)
	102 invokevirtual (1, 4)
	103 org/apache/commons/math3/linear/AbstractFieldMatrix.checkColumnIndex:(I)V (1, 4)
	105 aload_0 (1, 4)
	106 iload (1, 4)
	107 #4 (1, 4)
	108 iload_2 (1, 4)
	109 iadd (1, 4)
	110 iconst_1 (1, 4)
	111 isub (1, 4)
	112 invokevirtual (1, 4)
	113 org/apache/commons/math3/linear/AbstractFieldMatrix.checkRowIndex:(I)V (1, 4)
	115 aload_0 (1, 4)
	116 iload (1, 4)
	117 #5 (1, 4)
	118 iload_3 (1, 4)
	119 iadd (1, 4)
	120 iconst_1 (1, 4)
	121 isub (1, 4)
	122 invokevirtual (1, 4)
	123 org/apache/commons/math3/linear/AbstractFieldMatrix.checkColumnIndex:(I)V (1, 4)
	125 iconst_0 (2, 4)
	126 istore (2, 4)
	127 #6 (2, 4)
	128 iload (2, 4)
	129 #6 (2, 4)
	130 iload (2, 4)
	131 #4 (2, 4)
	132 if_icmpge (2, 4)
	133 44 (2, 4)
	135 iconst_0 (3, 4)
	136 istore (3, 4)
	137 #7 (3, 4)
	138 iload (3, 4)
	139 #7 (3, 4)
	140 iload (3, 4)
	141 #5 (3, 4)
	142 if_icmpge (3, 4)
	143 28 (3, 4)
	145 aload_0 (3, 4)
	146 iload_2 (3, 4)
	147 iload (3, 4)
	148 #6 (3, 4)
	149 iadd (3, 4)
	150 iload_3 (3, 4)
	151 iload (3, 4)
	152 #7 (3, 4)
	153 iadd (3, 4)
	154 aload_1 (3, 4)
	155 iload (3, 4)
	156 #6 (3, 4)
	157 aaload (3, 4)
	158 iload (3, 4)
	159 #7 (3, 4)
	160 aaload (3, 4)
	161 invokevirtual (3, 4)
	162 org/apache/commons/math3/linear/AbstractFieldMatrix.setEntry:(IILorg/apache/commons/math3/FieldElement;)V (3, 4)
	164 iinc (3, 4)
	165 #7 (3, 4)
	166 -89 (3, 4)
	167 goto (3, 4)
	168 -29 (3, 4)
	170 iinc (3, 4)
	171 #6 (3, 4)
	172 -89 (3, 4)
	173 goto (3, 4)
	174 -45 (3, 4)
	176 return (1, 4)

Method: getRowMatrix
	0 aload_0 (0, 0)
	1 iload_1 (0, 0)
	2 invokevirtual (0, 0)
	3 org/apache/commons/math3/linear/AbstractFieldMatrix.checkRowIndex:(I)V (0, 0)
	5 aload_0 (0, 0)
	6 invokevirtual (0, 0)
	7 org/apache/commons/math3/linear/AbstractFieldMatrix.getColumnDimension:()I (0, 0)
	9 istore_2 (0, 0)
	10 aload_0 (0, 0)
	11 iconst_1 (0, 0)
	12 iload_2 (0, 0)
	13 invokevirtual (0, 0)
	14 org/apache/commons/math3/linear/AbstractFieldMatrix.createMatrix:(II)Lorg/apache/commons/math3/linear/FieldMatrix; (0, 0)
	16 astore_3 (0, 0)
	17 iconst_0 (1, 4)
	18 istore (1, 4)
	19 #4 (1, 4)
	20 iload (1, 4)
	21 #4 (1, 4)
	22 iload_2 (1, 4)
	23 if_icmpge (1, 4)
	24 25 (1, 4)
	26 aload_3 (1, 4)
	27 iconst_0 (1, 4)
	28 iload (1, 4)
	29 #4 (1, 4)
	30 aload_0 (1, 4)
	31 iload_1 (1, 4)
	32 iload (1, 4)
	33 #4 (1, 4)
	34 invokevirtual (1, 4)
	35 org/apache/commons/math3/linear/AbstractFieldMatrix.getEntry:(II)Lorg/apache/commons/math3/FieldElement; (1, 4)
	37 invokeinterface (1, 4)
	38 org/apache/commons/math3/linear/FieldMatrix.checkSubtractionCompatible:(Lorg/apache/commons/math3/linear/FieldMatrix;)V (1, 4)
	40 0 (1, 4)
	42 iinc (1, 4)
	43 #4 (1, 4)
	44 -89 (1, 4)
	45 goto (1, 4)
	46 -25 (1, 4)
	48 aload_3 (0, 0)
	49 areturn (0, 0)

Method: setRowMatrix
	0 aload_0 (0, 0)
	1 iload_1 (0, 0)
	2 invokevirtual (0, 0)
	3 org/apache/commons/math3/linear/AbstractFieldMatrix.checkRowIndex:(I)V (0, 0)
	5 aload_0 (0, 0)
	6 invokevirtual (0, 0)
	7 org/apache/commons/math3/linear/AbstractFieldMatrix.getColumnDimension:()I (0, 0)
	9 istore_3 (0, 0)
	10 aload_2 (0, 1)
	11 invokeinterface (0, 1)
	12 org/apache/commons/math3/linear/FieldMatrix.getColumnDimension:()I (0, 1)
	14 0 (0, 1)
	16 iconst_1 (0, 1)
	17 if_icmpne (0, 1)
	18 13 (0, 1)
	20 aload_2 (0, 1)
	21 invokeinterface (0, 1)
	22 org/apache/commons/math3/linear/FieldMatrix.createMatrix:(II)Lorg/apache/commons/math3/linear/FieldMatrix; (0, 1)
	24 0 (0, 1)
	26 iload_3 (0, 1)
	27 if_icmpeq (0, 1)
	28 25 (0, 1)
	30 new (0, 1)
	31 org/apache/commons/math3/linear/MatrixDimensionMismatchException (0, 1)
	33 dup (0, 1)
	34 aload_2 (0, 1)
	35 invokeinterface (0, 1)
	36 org/apache/commons/math3/linear/FieldMatrix.getColumnDimension:()I (0, 1)
	38 0 (0, 1)
	40 aload_2 (0, 1)
	41 invokeinterface (0, 1)
	42 org/apache/commons/math3/linear/FieldMatrix.createMatrix:(II)Lorg/apache/commons/math3/linear/FieldMatrix; (0, 1)
	44 0 (0, 1)
	46 iconst_1 (0, 1)
	47 iload_3 (0, 1)
	48 invokespecial (0, 1)
	49 org/apache/commons/math3/linear/MatrixDimensionMismatchException.<init>:(IIII)V (0, 1)
	51 athrow (0, 1)
	52 iconst_0 (1, 4)
	53 istore (1, 4)
	54 #4 (1, 4)
	55 iload (1, 4)
	56 #4 (1, 4)
	57 iload_3 (1, 4)
	58 if_icmpge (1, 4)
	59 25 (1, 4)
	61 aload_0 (1, 4)
	62 iload_1 (1, 4)
	63 iload (1, 4)
	64 #4 (1, 4)
	65 aload_2 (1, 4)
	66 iconst_0 (1, 4)
	67 iload (1, 4)
	68 #4 (1, 4)
	69 invokeinterface (1, 4)
	70 org/apache/commons/math3/linear/FieldMatrix.add:(Ljava/lang/Object;)Ljava/lang/Object; (1, 4)
	72 0 (1, 4)
	74 invokevirtual (1, 4)
	75 org/apache/commons/math3/linear/AbstractFieldMatrix.setEntry:(IILorg/apache/commons/math3/FieldElement;)V (1, 4)
	77 iinc (1, 4)
	78 #4 (1, 4)
	79 -89 (1, 4)
	80 goto (1, 4)
	81 -25 (1, 4)
	83 return (0, 1)

Method: getColumnMatrix
	0 aload_0 (0, 0)
	1 iload_1 (0, 0)
	2 invokevirtual (0, 0)
	3 org/apache/commons/math3/linear/AbstractFieldMatrix.checkColumnIndex:(I)V (0, 0)
	5 aload_0 (0, 0)
	6 invokevirtual (0, 0)
	7 org/apache/commons/math3/linear/AbstractFieldMatrix.getRowDimension:()I (0, 0)
	9 istore_2 (0, 0)
	10 aload_0 (0, 0)
	11 iload_2 (0, 0)
	12 iconst_1 (0, 0)
	13 invokevirtual (0, 0)
	14 org/apache/commons/math3/linear/AbstractFieldMatrix.createMatrix:(II)Lorg/apache/commons/math3/linear/FieldMatrix; (0, 0)
	16 astore_3 (0, 0)
	17 iconst_0 (1, 4)
	18 istore (1, 4)
	19 #4 (1, 4)
	20 iload (1, 4)
	21 #4 (1, 4)
	22 iload_2 (1, 4)
	23 if_icmpge (1, 4)
	24 25 (1, 4)
	26 aload_3 (1, 4)
	27 iload (1, 4)
	28 #4 (1, 4)
	29 iconst_0 (1, 4)
	30 aload_0 (1, 4)
	31 iload (1, 4)
	32 #4 (1, 4)
	33 iload_1 (1, 4)
	34 invokevirtual (1, 4)
	35 org/apache/commons/math3/linear/AbstractFieldMatrix.getEntry:(II)Lorg/apache/commons/math3/FieldElement; (1, 4)
	37 invokeinterface (1, 4)
	38 org/apache/commons/math3/linear/FieldMatrix.checkSubtractionCompatible:(Lorg/apache/commons/math3/linear/FieldMatrix;)V (1, 4)
	40 0 (1, 4)
	42 iinc (1, 4)
	43 #4 (1, 4)
	44 -89 (1, 4)
	45 goto (1, 4)
	46 -25 (1, 4)
	48 aload_3 (0, 0)
	49 areturn (0, 0)

Method: setColumnMatrix
	0 aload_0 (0, 0)
	1 iload_1 (0, 0)
	2 invokevirtual (0, 0)
	3 org/apache/commons/math3/linear/AbstractFieldMatrix.checkColumnIndex:(I)V (0, 0)
	5 aload_0 (0, 0)
	6 invokevirtual (0, 0)
	7 org/apache/commons/math3/linear/AbstractFieldMatrix.getRowDimension:()I (0, 0)
	9 istore_3 (0, 0)
	10 aload_2 (0, 1)
	11 invokeinterface (0, 1)
	12 org/apache/commons/math3/linear/FieldMatrix.getColumnDimension:()I (0, 1)
	14 0 (0, 1)
	16 iload_3 (0, 1)
	17 if_icmpne (0, 1)
	18 13 (0, 1)
	20 aload_2 (0, 1)
	21 invokeinterface (0, 1)
	22 org/apache/commons/math3/linear/FieldMatrix.createMatrix:(II)Lorg/apache/commons/math3/linear/FieldMatrix; (0, 1)
	24 0 (0, 1)
	26 iconst_1 (0, 1)
	27 if_icmpeq (0, 1)
	28 25 (0, 1)
	30 new (0, 1)
	31 org/apache/commons/math3/linear/MatrixDimensionMismatchException (0, 1)
	33 dup (0, 1)
	34 aload_2 (0, 1)
	35 invokeinterface (0, 1)
	36 org/apache/commons/math3/linear/FieldMatrix.getColumnDimension:()I (0, 1)
	38 0 (0, 1)
	40 aload_2 (0, 1)
	41 invokeinterface (0, 1)
	42 org/apache/commons/math3/linear/FieldMatrix.createMatrix:(II)Lorg/apache/commons/math3/linear/FieldMatrix; (0, 1)
	44 0 (0, 1)
	46 iload_3 (0, 1)
	47 iconst_1 (0, 1)
	48 invokespecial (0, 1)
	49 org/apache/commons/math3/linear/MatrixDimensionMismatchException.<init>:(IIII)V (0, 1)
	51 athrow (0, 1)
	52 iconst_0 (1, 4)
	53 istore (1, 4)
	54 #4 (1, 4)
	55 iload (1, 4)
	56 #4 (1, 4)
	57 iload_3 (1, 4)
	58 if_icmpge (1, 4)
	59 25 (1, 4)
	61 aload_0 (1, 4)
	62 iload (1, 4)
	63 #4 (1, 4)
	64 iload_1 (1, 4)
	65 aload_2 (1, 4)
	66 iload (1, 4)
	67 #4 (1, 4)
	68 iconst_0 (1, 4)
	69 invokeinterface (1, 4)
	70 org/apache/commons/math3/linear/FieldMatrix.add:(Ljava/lang/Object;)Ljava/lang/Object; (1, 4)
	72 0 (1, 4)
	74 invokevirtual (1, 4)
	75 org/apache/commons/math3/linear/AbstractFieldMatrix.setEntry:(IILorg/apache/commons/math3/FieldElement;)V (1, 4)
	77 iinc (1, 4)
	78 #4 (1, 4)
	79 -89 (1, 4)
	80 goto (1, 4)
	81 -25 (1, 4)
	83 return (0, 1)

Method: getRowVector
	0 new (0, 0)
	1 org/apache/commons/math3/linear/ArrayFieldVector (0, 0)
	3 dup (0, 0)
	4 aload_0 (0, 0)
	5 getfield (0, 0)
	6 org/apache/commons/math3/linear/AbstractFieldMatrix.field:Lorg/apache/commons/math3/Field; (0, 0)
	8 aload_0 (0, 0)
	9 iload_1 (0, 0)
	10 invokevirtual (0, 0)
	11 org/apache/commons/math3/linear/AbstractFieldMatrix.getRow:(I)[Lorg/apache/commons/math3/FieldElement; (0, 0)
	13 iconst_0 (0, 0)
	14 invokespecial (0, 0)
	15 org/apache/commons/math3/linear/ArrayFieldVector.<init>:(Lorg/apache/commons/math3/Field;[Lorg/apache/commons/math3/FieldElement;Z)V (0, 0)
	17 areturn (0, 0)

Method: setRowVector
	0 aload_0 (0, 0)
	1 iload_1 (0, 0)
	2 invokevirtual (0, 0)
	3 org/apache/commons/math3/linear/AbstractFieldMatrix.checkRowIndex:(I)V (0, 0)
	5 aload_0 (0, 0)
	6 invokevirtual (0, 0)
	7 org/apache/commons/math3/linear/AbstractFieldMatrix.getColumnDimension:()I (0, 0)
	9 istore_3 (0, 0)
	10 aload_2 (1, 1)
	11 invokeinterface (1, 1)
	12 org/apache/commons/math3/linear/FieldVector.getEntry:(I)Lorg/apache/commons/math3/FieldElement; (1, 1)
	14 0 (1, 1)
	16 iload_3 (1, 1)
	17 if_icmpeq (1, 1)
	18 20 (1, 1)
	20 new (1, 1)
	21 org/apache/commons/math3/linear/MatrixDimensionMismatchException (1, 1)
	23 dup (1, 1)
	24 iconst_1 (1, 1)
	25 aload_2 (1, 1)
	26 invokeinterface (1, 1)
	27 org/apache/commons/math3/linear/FieldVector.getEntry:(I)Lorg/apache/commons/math3/FieldElement; (1, 1)
	29 0 (1, 1)
	31 iconst_1 (1, 1)
	32 iload_3 (1, 1)
	33 invokespecial (1, 1)
	34 org/apache/commons/math3/linear/MatrixDimensionMismatchException.<init>:(IIII)V (1, 1)
	36 athrow (1, 1)
	37 iconst_0 (1, 4)
	38 istore (1, 4)
	39 #4 (1, 4)
	40 iload (1, 4)
	41 #4 (1, 4)
	42 iload_3 (1, 4)
	43 if_icmpge (1, 4)
	44 24 (1, 4)
	46 aload_0 (1, 4)
	47 iload_1 (1, 4)
	48 iload (1, 4)
	49 #4 (1, 4)
	50 aload_2 (1, 4)
	51 iload (1, 4)
	52 #4 (1, 4)
	53 invokeinterface (1, 4)
	54 org/apache/commons/math3/linear/FieldVector.getColumn:(I)[Lorg/apache/commons/math3/FieldElement; (1, 4)
	56 0 (1, 4)
	58 invokevirtual (1, 4)
	59 org/apache/commons/math3/linear/AbstractFieldMatrix.setEntry:(IILorg/apache/commons/math3/FieldElement;)V (1, 4)
	61 iinc (1, 4)
	62 #4 (1, 4)
	63 -89 (1, 4)
	64 goto (1, 4)
	65 -24 (1, 4)
	67 return (0, 0)

Method: getColumnVector
	0 new (0, 0)
	1 org/apache/commons/math3/linear/ArrayFieldVector (0, 0)
	3 dup (0, 0)
	4 aload_0 (0, 0)
	5 getfield (0, 0)
	6 org/apache/commons/math3/linear/AbstractFieldMatrix.field:Lorg/apache/commons/math3/Field; (0, 0)
	8 aload_0 (0, 0)
	9 iload_1 (0, 0)
	10 invokevirtual (0, 0)
	11 org/apache/commons/math3/linear/AbstractFieldMatrix.getColumn:(I)[Lorg/apache/commons/math3/FieldElement; (0, 0)
	13 iconst_0 (0, 0)
	14 invokespecial (0, 0)
	15 org/apache/commons/math3/linear/ArrayFieldVector.<init>:(Lorg/apache/commons/math3/Field;[Lorg/apache/commons/math3/FieldElement;Z)V (0, 0)
	17 areturn (0, 0)

Method: setColumnVector
	0 aload_0 (0, 0)
	1 iload_1 (0, 0)
	2 invokevirtual (0, 0)
	3 org/apache/commons/math3/linear/AbstractFieldMatrix.checkColumnIndex:(I)V (0, 0)
	5 aload_0 (0, 0)
	6 invokevirtual (0, 0)
	7 org/apache/commons/math3/linear/AbstractFieldMatrix.getRowDimension:()I (0, 0)
	9 istore_3 (0, 0)
	10 aload_2 (1, 1)
	11 invokeinterface (1, 1)
	12 org/apache/commons/math3/linear/FieldVector.getEntry:(I)Lorg/apache/commons/math3/FieldElement; (1, 1)
	14 0 (1, 1)
	16 iload_3 (1, 1)
	17 if_icmpeq (1, 1)
	18 20 (1, 1)
	20 new (1, 1)
	21 org/apache/commons/math3/linear/MatrixDimensionMismatchException (1, 1)
	23 dup (1, 1)
	24 aload_2 (1, 1)
	25 invokeinterface (1, 1)
	26 org/apache/commons/math3/linear/FieldVector.getEntry:(I)Lorg/apache/commons/math3/FieldElement; (1, 1)
	28 0 (1, 1)
	30 iconst_1 (1, 1)
	31 iload_3 (1, 1)
	32 iconst_1 (1, 1)
	33 invokespecial (1, 1)
	34 org/apache/commons/math3/linear/MatrixDimensionMismatchException.<init>:(IIII)V (1, 1)
	36 athrow (1, 1)
	37 iconst_0 (1, 4)
	38 istore (1, 4)
	39 #4 (1, 4)
	40 iload (1, 4)
	41 #4 (1, 4)
	42 iload_3 (1, 4)
	43 if_icmpge (1, 4)
	44 24 (1, 4)
	46 aload_0 (1, 4)
	47 iload (1, 4)
	48 #4 (1, 4)
	49 iload_1 (1, 4)
	50 aload_2 (1, 4)
	51 iload (1, 4)
	52 #4 (1, 4)
	53 invokeinterface (1, 4)
	54 org/apache/commons/math3/linear/FieldVector.getColumn:(I)[Lorg/apache/commons/math3/FieldElement; (1, 4)
	56 0 (1, 4)
	58 invokevirtual (1, 4)
	59 org/apache/commons/math3/linear/AbstractFieldMatrix.setEntry:(IILorg/apache/commons/math3/FieldElement;)V (1, 4)
	61 iinc (1, 4)
	62 #4 (1, 4)
	63 -89 (1, 4)
	64 goto (1, 4)
	65 -24 (1, 4)
	67 return (0, 0)

Method: getRow
	0 aload_0 (0, 0)
	1 iload_1 (0, 0)
	2 invokevirtual (0, 0)
	3 org/apache/commons/math3/linear/AbstractFieldMatrix.checkRowIndex:(I)V (0, 0)
	5 aload_0 (0, 0)
	6 invokevirtual (0, 0)
	7 org/apache/commons/math3/linear/AbstractFieldMatrix.getColumnDimension:()I (0, 0)
	9 istore_2 (0, 0)
	10 aload_0 (0, 0)
	11 getfield (0, 0)
	12 org/apache/commons/math3/linear/AbstractFieldMatrix.field:Lorg/apache/commons/math3/Field; (0, 0)
	14 iload_2 (0, 0)
	15 invokestatic (0, 0)
	16 org/apache/commons/math3/util/MathArrays.buildArray:(Lorg/apache/commons/math3/Field;I)[Ljava/lang/Object; (0, 0)
	18 checkcast (0, 0)
	19 [Lorg/apache/commons/math3/FieldElement; (0, 0)
	21 astore_3 (0, 0)
	22 iconst_0 (1, 4)
	23 istore (1, 4)
	24 #4 (1, 4)
	25 iload (1, 4)
	26 #4 (1, 4)
	27 iload_2 (1, 4)
	28 if_icmpge (1, 4)
	29 20 (1, 4)
	31 aload_3 (1, 4)
	32 iload (1, 4)
	33 #4 (1, 4)
	34 aload_0 (1, 4)
	35 iload_1 (1, 4)
	36 iload (1, 4)
	37 #4 (1, 4)
	38 invokevirtual (1, 4)
	39 org/apache/commons/math3/linear/AbstractFieldMatrix.getEntry:(II)Lorg/apache/commons/math3/FieldElement; (1, 4)
	41 aastore (1, 4)
	42 iinc (1, 4)
	43 #4 (1, 4)
	44 -89 (1, 4)
	45 goto (1, 4)
	46 -20 (1, 4)
	48 aload_3 (0, 0)
	49 areturn (0, 0)

Method: setRow
	0 aload_0 (0, 0)
	1 iload_1 (0, 0)
	2 invokevirtual (0, 0)
	3 org/apache/commons/math3/linear/AbstractFieldMatrix.checkRowIndex:(I)V (0, 0)
	5 aload_0 (0, 0)
	6 invokevirtual (0, 0)
	7 org/apache/commons/math3/linear/AbstractFieldMatrix.getColumnDimension:()I (0, 0)
	9 istore_3 (0, 0)
	10 aload_2 (1, 1)
	11 arraylength (1, 1)
	12 iload_3 (1, 1)
	13 if_icmpeq (1, 1)
	14 16 (1, 1)
	16 new (1, 1)
	17 org/apache/commons/math3/linear/MatrixDimensionMismatchException (1, 1)
	19 dup (1, 1)
	20 iconst_1 (1, 1)
	21 aload_2 (1, 1)
	22 arraylength (1, 1)
	23 iconst_1 (1, 1)
	24 iload_3 (1, 1)
	25 invokespecial (1, 1)
	26 org/apache/commons/math3/linear/MatrixDimensionMismatchException.<init>:(IIII)V (1, 1)
	28 athrow (1, 1)
	29 iconst_0 (1, 4)
	30 istore (1, 4)
	31 #4 (1, 4)
	32 iload (1, 4)
	33 #4 (1, 4)
	34 iload_3 (1, 4)
	35 if_icmpge (1, 4)
	36 20 (1, 4)
	38 aload_0 (1, 4)
	39 iload_1 (1, 4)
	40 iload (1, 4)
	41 #4 (1, 4)
	42 aload_2 (1, 4)
	43 iload (1, 4)
	44 #4 (1, 4)
	45 aaload (1, 4)
	46 invokevirtual (1, 4)
	47 org/apache/commons/math3/linear/AbstractFieldMatrix.setEntry:(IILorg/apache/commons/math3/FieldElement;)V (1, 4)
	49 iinc (1, 4)
	50 #4 (1, 4)
	51 -89 (1, 4)
	52 goto (1, 4)
	53 -20 (1, 4)
	55 return (0, 0)

Method: getColumn
	0 aload_0 (0, 0)
	1 iload_1 (0, 0)
	2 invokevirtual (0, 0)
	3 org/apache/commons/math3/linear/AbstractFieldMatrix.checkColumnIndex:(I)V (0, 0)
	5 aload_0 (0, 0)
	6 invokevirtual (0, 0)
	7 org/apache/commons/math3/linear/AbstractFieldMatrix.getRowDimension:()I (0, 0)
	9 istore_2 (0, 0)
	10 aload_0 (0, 0)
	11 getfield (0, 0)
	12 org/apache/commons/math3/linear/AbstractFieldMatrix.field:Lorg/apache/commons/math3/Field; (0, 0)
	14 iload_2 (0, 0)
	15 invokestatic (0, 0)
	16 org/apache/commons/math3/util/MathArrays.buildArray:(Lorg/apache/commons/math3/Field;I)[Ljava/lang/Object; (0, 0)
	18 checkcast (0, 0)
	19 [Lorg/apache/commons/math3/FieldElement; (0, 0)
	21 astore_3 (0, 0)
	22 iconst_0 (1, 4)
	23 istore (1, 4)
	24 #4 (1, 4)
	25 iload (1, 4)
	26 #4 (1, 4)
	27 iload_2 (1, 4)
	28 if_icmpge (1, 4)
	29 20 (1, 4)
	31 aload_3 (1, 4)
	32 iload (1, 4)
	33 #4 (1, 4)
	34 aload_0 (1, 4)
	35 iload (1, 4)
	36 #4 (1, 4)
	37 iload_1 (1, 4)
	38 invokevirtual (1, 4)
	39 org/apache/commons/math3/linear/AbstractFieldMatrix.getEntry:(II)Lorg/apache/commons/math3/FieldElement; (1, 4)
	41 aastore (1, 4)
	42 iinc (1, 4)
	43 #4 (1, 4)
	44 -89 (1, 4)
	45 goto (1, 4)
	46 -20 (1, 4)
	48 aload_3 (0, 0)
	49 areturn (0, 0)

Method: setColumn
	0 aload_0 (0, 0)
	1 iload_1 (0, 0)
	2 invokevirtual (0, 0)
	3 org/apache/commons/math3/linear/AbstractFieldMatrix.checkColumnIndex:(I)V (0, 0)
	5 aload_0 (0, 0)
	6 invokevirtual (0, 0)
	7 org/apache/commons/math3/linear/AbstractFieldMatrix.getRowDimension:()I (0, 0)
	9 istore_3 (0, 0)
	10 aload_2 (1, 1)
	11 arraylength (1, 1)
	12 iload_3 (1, 1)
	13 if_icmpeq (1, 1)
	14 16 (1, 1)
	16 new (1, 1)
	17 org/apache/commons/math3/linear/MatrixDimensionMismatchException (1, 1)
	19 dup (1, 1)
	20 aload_2 (1, 1)
	21 arraylength (1, 1)
	22 iconst_1 (1, 1)
	23 iload_3 (1, 1)
	24 iconst_1 (1, 1)
	25 invokespecial (1, 1)
	26 org/apache/commons/math3/linear/MatrixDimensionMismatchException.<init>:(IIII)V (1, 1)
	28 athrow (1, 1)
	29 iconst_0 (1, 4)
	30 istore (1, 4)
	31 #4 (1, 4)
	32 iload (1, 4)
	33 #4 (1, 4)
	34 iload_3 (1, 4)
	35 if_icmpge (1, 4)
	36 20 (1, 4)
	38 aload_0 (1, 4)
	39 iload (1, 4)
	40 #4 (1, 4)
	41 iload_1 (1, 4)
	42 aload_2 (1, 4)
	43 iload (1, 4)
	44 #4 (1, 4)
	45 aaload (1, 4)
	46 invokevirtual (1, 4)
	47 org/apache/commons/math3/linear/AbstractFieldMatrix.setEntry:(IILorg/apache/commons/math3/FieldElement;)V (1, 4)
	49 iinc (1, 4)
	50 #4 (1, 4)
	51 -89 (1, 4)
	52 goto (1, 4)
	53 -20 (1, 4)
	55 return (0, 0)

Method: transpose
	0 aload_0 (0, 0)
	1 invokevirtual (0, 0)
	2 org/apache/commons/math3/linear/AbstractFieldMatrix.getRowDimension:()I (0, 0)
	4 istore_1 (0, 0)
	5 aload_0 (0, 0)
	6 invokevirtual (0, 0)
	7 org/apache/commons/math3/linear/AbstractFieldMatrix.getColumnDimension:()I (0, 0)
	9 istore_2 (0, 0)
	10 aload_0 (0, 0)
	11 iload_2 (0, 0)
	12 iload_1 (0, 0)
	13 invokevirtual (0, 0)
	14 org/apache/commons/math3/linear/AbstractFieldMatrix.createMatrix:(II)Lorg/apache/commons/math3/linear/FieldMatrix; (0, 0)
	16 astore_3 (0, 0)
	17 aload_0 (0, 0)
	18 new (0, 0)
	19 org/apache/commons/math3/linear/AbstractFieldMatrix$3 (0, 0)
	21 dup (0, 0)
	22 aload_0 (0, 0)
	23 aload_0 (0, 0)
	24 getfield (0, 0)
	25 org/apache/commons/math3/linear/AbstractFieldMatrix.field:Lorg/apache/commons/math3/Field; (0, 0)
	27 invokeinterface (0, 0)
	28 org/apache/commons/math3/Field.multiply:(Lorg/apache/commons/math3/linear/FieldMatrix;)Lorg/apache/commons/math3/linear/FieldMatrix; (0, 0)
	30 0 (0, 0)
	32 checkcast (0, 0)
	33 org/apache/commons/math3/FieldElement (0, 0)
	35 aload_3 (0, 0)
	36 invokespecial (0, 0)
	37 org/apache/commons/math3/linear/AbstractFieldMatrix$3.<init>:(Lorg/apache/commons/math3/linear/AbstractFieldMatrix;Lorg/apache/commons/math3/FieldElement;Lorg/apache/commons/math3/linear/FieldMatrix;)V (0, 0)
	39 invokevirtual (0, 0)
	40 org/apache/commons/math3/linear/AbstractFieldMatrix.walkInOptimizedOrder:(Lorg/apache/commons/math3/linear/FieldMatrixPreservingVisitor;)Lorg/apache/commons/math3/FieldElement; (0, 0)
	42 pop (0, 0)
	43 aload_3 (0, 0)
	44 areturn (0, 0)

Method: isSquare
	0 aload_0 (0, 0)
	1 invokevirtual (0, 0)
	2 org/apache/commons/math3/linear/AbstractFieldMatrix.getColumnDimension:()I (0, 0)
	4 aload_0 (0, 0)
	5 invokevirtual (0, 0)
	6 org/apache/commons/math3/linear/AbstractFieldMatrix.getRowDimension:()I (0, 0)
	8 if_icmpne (0, 0)
	9 7 (0, 0)
	11 iconst_1 (0, 0)
	12 goto (0, 0)
	13 4 (0, 0)
	15 iconst_0 (0, 0)
	16 ireturn (0, 0)

Method: getTrace
	0 aload_0 (0, 0)
	1 invokevirtual (0, 0)
	2 org/apache/commons/math3/linear/AbstractFieldMatrix.getRowDimension:()I (0, 0)
	4 istore_1 (0, 0)
	5 aload_0 (0, 0)
	6 invokevirtual (0, 0)
	7 org/apache/commons/math3/linear/AbstractFieldMatrix.getColumnDimension:()I (0, 0)
	9 istore_2 (0, 0)
	10 iload_1 (1, 1)
	11 iload_2 (1, 1)
	12 if_icmpeq (1, 1)
	13 13 (1, 1)
	15 new (1, 1)
	16 org/apache/commons/math3/linear/NonSquareMatrixException (1, 1)
	18 dup (1, 1)
	19 iload_1 (1, 1)
	20 iload_2 (1, 1)
	21 invokespecial (1, 1)
	22 org/apache/commons/math3/linear/NonSquareMatrixException.<init>:(II)V (1, 1)
	24 athrow (1, 1)
	25 aload_0 (0, 0)
	26 getfield (0, 0)
	27 org/apache/commons/math3/linear/AbstractFieldMatrix.field:Lorg/apache/commons/math3/Field; (0, 0)
	29 invokeinterface (0, 0)
	30 org/apache/commons/math3/Field.multiply:(Lorg/apache/commons/math3/linear/FieldMatrix;)Lorg/apache/commons/math3/linear/FieldMatrix; (0, 0)
	32 0 (0, 0)
	34 checkcast (0, 0)
	35 org/apache/commons/math3/FieldElement (0, 0)
	37 astore_3 (0, 0)
	38 iconst_0 (1, 4)
	39 istore (1, 4)
	40 #4 (1, 4)
	41 iload (1, 4)
	42 #4 (1, 4)
	43 iload_1 (1, 4)
	44 if_icmpge (1, 4)
	45 27 (1, 4)
	47 aload_3 (1, 4)
	48 aload_0 (1, 4)
	49 iload (1, 4)
	50 #4 (1, 4)
	51 iload (1, 4)
	52 #4 (1, 4)
	53 invokevirtual (1, 4)
	54 org/apache/commons/math3/linear/AbstractFieldMatrix.getEntry:(II)Lorg/apache/commons/math3/FieldElement; (1, 4)
	56 invokeinterface (1, 4)
	57 org/apache/commons/math3/FieldElement.org/apache/commons/math3/FieldElement (1, 4)
	59 0 (1, 4)
	61 checkcast (1, 4)
	62 org/apache/commons/math3/FieldElement (1, 4)
	64 astore_3 (1, 4)
	65 iinc (1, 4)
	66 #4 (1, 4)
	67 -89 (1, 4)
	68 goto (1, 4)
	69 -27 (1, 4)
	71 aload_3 (0, 0)
	72 areturn (0, 0)

Method: operate
	0 new (0, 0)
	1 org/apache/commons/math3/linear/ArrayFieldVector (0, 0)
	3 dup (0, 0)
	4 aload_0 (0, 0)
	5 getfield (0, 0)
	6 org/apache/commons/math3/linear/AbstractFieldMatrix.field:Lorg/apache/commons/math3/Field; (0, 0)
	8 aload_0 (0, 0)
	9 aload_1 (0, 0)
	10 checkcast (0, 0)
	11 org/apache/commons/math3/linear/ArrayFieldVector (0, 0)
	13 invokevirtual (0, 0)
	14 org/apache/commons/math3/linear/ArrayFieldVector.getDataRef:()[Lorg/apache/commons/math3/FieldElement; (0, 0)
	16 invokevirtual (0, 0)
	17 org/apache/commons/math3/linear/AbstractFieldMatrix.operate:([Lorg/apache/commons/math3/FieldElement;)[Lorg/apache/commons/math3/FieldElement; (0, 0)
	19 iconst_0 (0, 0)
	20 invokespecial (0, 0)
	21 org/apache/commons/math3/linear/ArrayFieldVector.<init>:(Lorg/apache/commons/math3/Field;[Lorg/apache/commons/math3/FieldElement;Z)V (0, 0)
	23 areturn (0, 0)
	24 astore_2 (0, 0)
	25 aload_0 (0, 0)
	26 invokevirtual (0, 0)
	27 org/apache/commons/math3/linear/AbstractFieldMatrix.getRowDimension:()I (0, 0)
	29 istore_3 (0, 0)
	30 aload_0 (0, 0)
	31 invokevirtual (0, 0)
	32 org/apache/commons/math3/linear/AbstractFieldMatrix.getColumnDimension:()I (0, 0)
	34 istore (0, 0)
	35 #4 (0, 0)
	36 aload_1 (1, 1)
	37 invokeinterface (1, 1)
	38 org/apache/commons/math3/linear/FieldVector.getEntry:(I)Lorg/apache/commons/math3/FieldElement; (1, 1)
	40 0 (1, 1)
	42 iload (1, 1)
	43 #4 (1, 1)
	44 if_icmpeq (1, 1)
	45 19 (1, 1)
	47 new (1, 1)
	48 org/apache/commons/math3/exception/DimensionMismatchException (1, 1)
	50 dup (1, 1)
	51 aload_1 (1, 1)
	52 invokeinterface (1, 1)
	53 org/apache/commons/math3/linear/FieldVector.getEntry:(I)Lorg/apache/commons/math3/FieldElement; (1, 1)
	55 0 (1, 1)
	57 iload (1, 1)
	58 #4 (1, 1)
	59 invokespecial (1, 1)
	60 org/apache/commons/math3/exception/DimensionMismatchException.<init>:(II)V (1, 1)
	62 athrow (1, 1)
	63 aload_0 (0, 0)
	64 getfield (0, 0)
	65 org/apache/commons/math3/linear/AbstractFieldMatrix.field:Lorg/apache/commons/math3/Field; (0, 0)
	67 iload_3 (0, 0)
	68 invokestatic (0, 0)
	69 org/apache/commons/math3/util/MathArrays.buildArray:(Lorg/apache/commons/math3/Field;I)[Ljava/lang/Object; (0, 0)
	71 checkcast (0, 0)
	72 [Lorg/apache/commons/math3/FieldElement; (0, 0)
	74 astore (0, 0)
	75 #5 (0, 0)
	76 iconst_0 (1, 4)
	77 istore (1, 4)
	78 #6 (1, 4)
	79 iload (1, 4)
	80 #6 (1, 4)
	81 iload_3 (1, 4)
	82 if_icmpge (1, 4)
	83 79 (1, 4)
	85 aload_0 (1, 4)
	86 getfield (1, 4)
	87 org/apache/commons/math3/linear/AbstractFieldMatrix.field:Lorg/apache/commons/math3/Field; (1, 4)
	89 invokeinterface (1, 4)
	90 org/apache/commons/math3/Field.multiply:(Lorg/apache/commons/math3/linear/FieldMatrix;)Lorg/apache/commons/math3/linear/FieldMatrix; (1, 4)
	92 0 (1, 4)
	94 checkcast (1, 4)
	95 org/apache/commons/math3/FieldElement (1, 4)
	97 astore (1, 4)
	98 #7 (1, 4)
	99 iconst_0 (2, 4)
	100 istore (2, 4)
	101 #8 (2, 4)
	102 iload (2, 4)
	103 #8 (2, 4)
	104 iload (2, 4)
	105 #4 (2, 4)
	106 if_icmpge (2, 4)
	107 42 (2, 4)
	109 aload (2, 4)
	110 #7 (2, 4)
	111 aload_0 (2, 4)
	112 iload (2, 4)
	113 #6 (2, 4)
	114 iload (2, 4)
	115 #8 (2, 4)
	116 invokevirtual (2, 4)
	117 org/apache/commons/math3/linear/AbstractFieldMatrix.getEntry:(II)Lorg/apache/commons/math3/FieldElement; (2, 4)
	119 aload_1 (2, 4)
	120 iload (2, 4)
	121 #8 (2, 4)
	122 invokeinterface (2, 4)
	123 org/apache/commons/math3/linear/FieldVector.getColumn:(I)[Lorg/apache/commons/math3/FieldElement; (2, 4)
	125 0 (2, 4)
	127 invokeinterface (2, 4)
	128 org/apache/commons/math3/FieldElement.checkMultiplicationCompatible:(Lorg/apache/commons/math3/linear/FieldMatrix;)V (2, 4)
	130 0 (2, 4)
	132 invokeinterface (2, 4)
	133 org/apache/commons/math3/FieldElement.org/apache/commons/math3/FieldElement (2, 4)
	135 0 (2, 4)
	137 checkcast (2, 4)
	138 org/apache/commons/math3/FieldElement (2, 4)
	140 astore (2, 4)
	141 #7 (2, 4)
	142 iinc (2, 4)
	143 #8 (2, 4)
	144 -89 (2, 4)
	145 goto (2, 4)
	146 -43 (2, 4)
	148 aload (1, 4)
	149 #5 (1, 4)
	150 iload (1, 4)
	151 #6 (1, 4)
	152 aload (1, 4)
	153 #7 (1, 4)
	154 aastore (1, 4)
	155 iinc (1, 4)
	156 #6 (1, 4)
	157 -89 (1, 4)
	158 goto (1, 4)
	159 -79 (1, 4)
	161 new (0, 0)
	162 org/apache/commons/math3/linear/ArrayFieldVector (0, 0)
	164 dup (0, 0)
	165 aload_0 (0, 0)
	166 getfield (0, 0)
	167 org/apache/commons/math3/linear/AbstractFieldMatrix.field:Lorg/apache/commons/math3/Field; (0, 0)
	169 aload (0, 0)
	170 #5 (0, 0)
	171 iconst_0 (0, 0)
	172 invokespecial (0, 0)
	173 org/apache/commons/math3/linear/ArrayFieldVector.<init>:(Lorg/apache/commons/math3/Field;[Lorg/apache/commons/math3/FieldElement;Z)V (0, 0)
	175 areturn (0, 0)

Method: walkInRowOrder
	0 aload_0 (0, 0)
	1 iload_2 (0, 0)
	2 iload_3 (0, 0)
	3 iload (0, 0)
	4 #4 (0, 0)
	5 iload (0, 0)
	6 #5 (0, 0)
	7 invokevirtual (0, 0)
	8 org/apache/commons/math3/linear/AbstractFieldMatrix.checkSubMatrixIndex:(IIII)V (0, 0)
	10 aload_1 (0, 0)
	11 aload_0 (0, 0)
	12 invokevirtual (0, 0)
	13 org/apache/commons/math3/linear/AbstractFieldMatrix.getRowDimension:()I (0, 0)
	15 aload_0 (0, 0)
	16 invokevirtual (0, 0)
	17 org/apache/commons/math3/linear/AbstractFieldMatrix.getColumnDimension:()I (0, 0)
	19 iload_2 (0, 0)
	20 iload_3 (0, 0)
	21 iload (0, 0)
	22 #4 (0, 0)
	23 iload (0, 0)
	24 #5 (0, 0)
	25 invokeinterface (0, 0)
	26 org/apache/commons/math3/linear/FieldMatrixPreservingVisitor.visit:(IILorg/apache/commons/math3/FieldElement;)Lorg/apache/commons/math3/FieldElement; (0, 0)
	28 0 (0, 0)
	30 iload_2 (1, 4)
	31 istore (1, 4)
	32 #6 (1, 4)
	33 iload (1, 4)
	34 #6 (1, 4)
	35 iload_3 (1, 4)
	36 if_icmpgt (1, 4)
	37 44 (1, 4)
	39 iload (2, 4)
	40 #4 (2, 4)
	41 istore (2, 4)
	42 #7 (2, 4)
	43 iload (2, 4)
	44 #7 (2, 4)
	45 iload (2, 4)
	46 #5 (2, 4)
	47 if_icmpgt (2, 4)
	48 27 (2, 4)
	50 aload_1 (2, 4)
	51 iload (2, 4)
	52 #6 (2, 4)
	53 iload (2, 4)
	54 #7 (2, 4)
	55 aload_0 (2, 4)
	56 iload (2, 4)
	57 #6 (2, 4)
	58 iload (2, 4)
	59 #7 (2, 4)
	60 invokevirtual (2, 4)
	61 org/apache/commons/math3/linear/AbstractFieldMatrix.getEntry:(II)Lorg/apache/commons/math3/FieldElement; (2, 4)
	63 invokeinterface (2, 4)
	64 org/apache/commons/math3/linear/FieldMatrixPreservingVisitor.walkInRowOrder:(Lorg/apache/commons/math3/linear/FieldMatrixChangingVisitor;)Lorg/apache/commons/math3/FieldElement; (2, 4)
	66 0 (2, 4)
	68 iinc (2, 4)
	69 #7 (2, 4)
	70 -89 (2, 4)
	71 goto (2, 4)
	72 -28 (2, 4)
	74 iinc (2, 4)
	75 #6 (2, 4)
	76 -89 (2, 4)
	77 goto (2, 4)
	78 -44 (2, 4)
	80 aload_1 (1, 4)
	81 invokeinterface (1, 4)
	82 org/apache/commons/math3/linear/FieldMatrixPreservingVisitor.org/apache/commons/math3/linear/FieldMatrixPreservingVisitor (1, 4)
	84 0 (1, 4)
	86 areturn (1, 4)

Method: walkInColumnOrder
	0 aload_0 (0, 0)
	1 iload_2 (0, 0)
	2 iload_3 (0, 0)
	3 iload (0, 0)
	4 #4 (0, 0)
	5 iload (0, 0)
	6 #5 (0, 0)
	7 invokevirtual (0, 0)
	8 org/apache/commons/math3/linear/AbstractFieldMatrix.checkSubMatrixIndex:(IIII)V (0, 0)
	10 aload_1 (0, 0)
	11 aload_0 (0, 0)
	12 invokevirtual (0, 0)
	13 org/apache/commons/math3/linear/AbstractFieldMatrix.getRowDimension:()I (0, 0)
	15 aload_0 (0, 0)
	16 invokevirtual (0, 0)
	17 org/apache/commons/math3/linear/AbstractFieldMatrix.getColumnDimension:()I (0, 0)
	19 iload_2 (0, 0)
	20 iload_3 (0, 0)
	21 iload (0, 0)
	22 #4 (0, 0)
	23 iload (0, 0)
	24 #5 (0, 0)
	25 invokeinterface (0, 0)
	26 org/apache/commons/math3/linear/FieldMatrixPreservingVisitor.visit:(IILorg/apache/commons/math3/FieldElement;)Lorg/apache/commons/math3/FieldElement; (0, 0)
	28 0 (0, 0)
	30 iload (1, 4)
	31 #4 (1, 4)
	32 istore (1, 4)
	33 #6 (1, 4)
	34 iload (1, 4)
	35 #6 (1, 4)
	36 iload (1, 4)
	37 #5 (1, 4)
	38 if_icmpgt (1, 4)
	39 42 (1, 4)
	41 iload_2 (2, 4)
	42 istore (2, 4)
	43 #7 (2, 4)
	44 iload (2, 4)
	45 #7 (2, 4)
	46 iload_3 (2, 4)
	47 if_icmpgt (2, 4)
	48 27 (2, 4)
	50 aload_1 (2, 4)
	51 iload (2, 4)
	52 #7 (2, 4)
	53 iload (2, 4)
	54 #6 (2, 4)
	55 aload_0 (2, 4)
	56 iload (2, 4)
	57 #7 (2, 4)
	58 iload (2, 4)
	59 #6 (2, 4)
	60 invokevirtual (2, 4)
	61 org/apache/commons/math3/linear/AbstractFieldMatrix.getEntry:(II)Lorg/apache/commons/math3/FieldElement; (2, 4)
	63 invokeinterface (2, 4)
	64 org/apache/commons/math3/linear/FieldMatrixPreservingVisitor.walkInRowOrder:(Lorg/apache/commons/math3/linear/FieldMatrixChangingVisitor;)Lorg/apache/commons/math3/FieldElement; (2, 4)
	66 0 (2, 4)
	68 iinc (2, 4)
	69 #7 (2, 4)
	70 -89 (2, 4)
	71 goto (2, 4)
	72 -27 (2, 4)
	74 iinc (2, 4)
	75 #6 (2, 4)
	76 -89 (2, 4)
	77 goto (2, 4)
	78 -43 (2, 4)
	80 aload_1 (1, 4)
	81 invokeinterface (1, 4)
	82 org/apache/commons/math3/linear/FieldMatrixPreservingVisitor.org/apache/commons/math3/linear/FieldMatrixPreservingVisitor (1, 4)
	84 0 (1, 4)
	86 areturn (1, 4)

Method: walkInOptimizedOrder
	0 aload_0 (0, 0)
	1 aload_1 (0, 0)
	2 iload_2 (0, 0)
	3 iload_3 (0, 0)
	4 iload (0, 0)
	5 #4 (0, 0)
	6 iload (0, 0)
	7 #5 (0, 0)
	8 invokevirtual (0, 0)
	9 org/apache/commons/math3/linear/AbstractFieldMatrix.walkInRowOrder:(Lorg/apache/commons/math3/linear/FieldMatrixPreservingVisitor;IIII)Lorg/apache/commons/math3/FieldElement; (0, 0)
	11 areturn (0, 0)

Method: toString
	0 aload_0 (0, 0)
	1 invokevirtual (0, 0)
	2 org/apache/commons/math3/linear/AbstractFieldMatrix.getRowDimension:()I (0, 0)
	4 istore_1 (0, 0)
	5 aload_0 (0, 0)
	6 invokevirtual (0, 0)
	7 org/apache/commons/math3/linear/AbstractFieldMatrix.getColumnDimension:()I (0, 0)
	9 istore_2 (0, 0)
	10 new (0, 0)
	11 java/lang/StringBuffer (0, 0)
	13 dup (0, 0)
	14 invokespecial (0, 0)
	15 java/lang/StringBuffer.<init>:()V (0, 0)
	17 astore_3 (0, 0)
	18 aload_0 (0, 0)
	19 invokevirtual (0, 0)
	20 java/lang/Object.getClass:()Ljava/lang/Class; (0, 0)
	22 invokevirtual (0, 0)
	23 java/lang/Class.getName:()Ljava/lang/String; (0, 0)
	25 astore (0, 0)
	26 #4 (0, 0)
	27 aload (0, 0)
	28 #4 (0, 0)
	29 aload (0, 0)
	30 #4 (0, 0)
	31 bipush (0, 0)
	32 46 (0, 0)
	33 invokevirtual (0, 0)
	34 java/lang/String.lastIndexOf:(I)I (0, 0)
	36 iconst_1 (0, 0)
	37 iadd (0, 0)
	38 invokevirtual (0, 0)
	39 java/lang/String.substring:(I)Ljava/lang/String; (0, 0)
	41 astore (0, 0)
	42 #5 (0, 0)
	43 aload_3 (0, 0)
	44 aload (0, 0)
	45 #5 (0, 0)
	46 invokevirtual (0, 0)
	47 java/lang/StringBuffer.append:(Ljava/lang/String;)Ljava/lang/StringBuffer; (0, 0)
	49 ldc (0, 0)
	50 { (0, 0)
	51 invokevirtual (0, 0)
	52 java/lang/StringBuffer.append:(Ljava/lang/String;)Ljava/lang/StringBuffer; (0, 0)
	54 pop (0, 0)
	55 iconst_0 (2, 4)
	56 istore (2, 4)
	57 #6 (2, 4)
	58 iload (2, 4)
	59 #6 (2, 4)
	60 iload_1 (2, 4)
	61 if_icmpge (2, 4)
	62 75 (2, 4)
	64 iload (3, 1)
	65 #6 (3, 1)
	66 ifle (3, 1)
	67 10 (3, 1)
	69 aload_3 (3, 1)
	70 ldc (3, 1)
	71 , (3, 1)
	72 invokevirtual (3, 1)
	73 java/lang/StringBuffer.append:(Ljava/lang/String;)Ljava/lang/StringBuffer; (3, 1)
	75 pop (3, 1)
	76 aload_3 (2, 4)
	77 ldc (2, 4)
	78 { (2, 4)
	79 invokevirtual (2, 4)
	80 java/lang/StringBuffer.append:(Ljava/lang/String;)Ljava/lang/StringBuffer; (2, 4)
	82 pop (2, 4)
	83 iconst_0 (4, 4)
	84 istore (4, 4)
	85 #7 (4, 4)
	86 iload (4, 4)
	87 #7 (4, 4)
	88 iload_2 (4, 4)
	89 if_icmpge (4, 4)
	90 34 (4, 4)
	92 iload (5, 1)
	93 #7 (5, 1)
	94 ifle (5, 1)
	95 10 (5, 1)
	97 aload_3 (5, 1)
	98 ldc (5, 1)
	99 , (5, 1)
	100 invokevirtual (5, 1)
	101 java/lang/StringBuffer.append:(Ljava/lang/String;)Ljava/lang/StringBuffer; (5, 1)
	103 pop (5, 1)
	104 aload_3 (4, 4)
	105 aload_0 (4, 4)
	106 iload (4, 4)
	107 #6 (4, 4)
	108 iload (4, 4)
	109 #7 (4, 4)
	110 invokevirtual (4, 4)
	111 org/apache/commons/math3/linear/AbstractFieldMatrix.getEntry:(II)Lorg/apache/commons/math3/FieldElement; (4, 4)
	113 invokevirtual (4, 4)
	114 java/lang/StringBuffer.append:(Ljava/lang/Object;)Ljava/lang/StringBuffer; (4, 4)
	116 pop (4, 4)
	117 iinc (4, 4)
	118 #7 (4, 4)
	119 -89 (4, 4)
	120 goto (4, 4)
	121 -34 (4, 4)
	123 aload_3 (2, 4)
	124 ldc (2, 4)
	125 } (2, 4)
	126 invokevirtual (2, 4)
	127 java/lang/StringBuffer.append:(Ljava/lang/String;)Ljava/lang/StringBuffer; (2, 4)
	129 pop (2, 4)
	130 iinc (2, 4)
	131 #6 (2, 4)
	132 -89 (2, 4)
	133 goto (2, 4)
	134 -75 (2, 4)
	136 aload_3 (0, 0)
	137 ldc (0, 0)
	138 } (0, 0)
	139 invokevirtual (0, 0)
	140 java/lang/StringBuffer.append:(Ljava/lang/String;)Ljava/lang/StringBuffer; (0, 0)
	142 pop (0, 0)
	143 aload_3 (0, 0)
	144 invokevirtual (0, 0)
	145 java/lang/StringBuffer.toString:()Ljava/lang/String; (0, 0)
	147 areturn (0, 0)

Method: equals
	0 aload_1 (1, 1)
	1 aload_0 (1, 1)
	2 if_acmpne (1, 1)
	3 5 (1, 1)
	5 iconst_1 (1, 1)
	6 ireturn (1, 1)
	7 aload_1 (1, 1)
	8 instanceof (1, 1)
	9 org/apache/commons/math3/linear/FieldMatrix (1, 1)
	11 ifne (1, 1)
	12 5 (1, 1)
	14 iconst_0 (1, 1)
	15 ireturn (1, 1)
	16 aload_1 (0, 0)
	17 checkcast (0, 0)
	18 org/apache/commons/math3/linear/FieldMatrix (0, 0)
	20 astore_2 (0, 0)
	21 aload_0 (0, 0)
	22 invokevirtual (0, 0)
	23 org/apache/commons/math3/linear/AbstractFieldMatrix.getRowDimension:()I (0, 0)
	25 istore_3 (0, 0)
	26 aload_0 (0, 0)
	27 invokevirtual (0, 0)
	28 org/apache/commons/math3/linear/AbstractFieldMatrix.getColumnDimension:()I (0, 0)
	30 istore (0, 0)
	31 #4 (0, 0)
	32 aload_2 (1, 1)
	33 invokeinterface (1, 1)
	34 org/apache/commons/math3/linear/FieldMatrix.createMatrix:(II)Lorg/apache/commons/math3/linear/FieldMatrix; (1, 1)
	36 0 (1, 1)
	38 iload (1, 1)
	39 #4 (1, 1)
	40 if_icmpne (1, 1)
	41 13 (1, 1)
	43 aload_2 (1, 1)
	44 invokeinterface (1, 1)
	45 org/apache/commons/math3/linear/FieldMatrix.getColumnDimension:()I (1, 1)
	47 0 (1, 1)
	49 iload_3 (1, 1)
	50 if_icmpeq (1, 1)
	51 5 (1, 1)
	53 iconst_0 (1, 1)
	54 ireturn (1, 1)
	55 iconst_0 (1, 4)
	56 istore (1, 4)
	57 #5 (1, 4)
	58 iload (1, 4)
	59 #5 (1, 4)
	60 iload_3 (1, 4)
	61 if_icmpge (1, 4)
	62 51 (1, 4)
	64 iconst_0 (2, 4)
	65 istore (2, 4)
	66 #6 (2, 4)
	67 iload (2, 4)
	68 #6 (2, 4)
	69 iload (2, 4)
	70 #4 (2, 4)
	71 if_icmpge (2, 4)
	72 35 (2, 4)
	74 aload_0 (3, 1)
	75 iload (3, 1)
	76 #5 (3, 1)
	77 iload (3, 1)
	78 #6 (3, 1)
	79 invokevirtual (3, 1)
	80 org/apache/commons/math3/linear/AbstractFieldMatrix.getEntry:(II)Lorg/apache/commons/math3/FieldElement; (3, 1)
	82 aload_2 (3, 1)
	83 iload (3, 1)
	84 #5 (3, 1)
	85 iload (3, 1)
	86 #6 (3, 1)
	87 invokeinterface (3, 1)
	88 org/apache/commons/math3/linear/FieldMatrix.add:(Ljava/lang/Object;)Ljava/lang/Object; (3, 1)
	90 0 (3, 1)
	92 invokevirtual (3, 1)
	93 java/lang/Object.equals:(Ljava/lang/Object;)Z (3, 1)
	95 ifne (3, 1)
	96 5 (3, 1)
	98 iconst_0 (3, 1)
	99 ireturn (3, 1)
	100 iinc (3, 1)
	101 #6 (3, 1)
	102 -89 (3, 1)
	103 goto (3, 1)
	104 -36 (3, 1)
	106 iinc (3, 1)
	107 #5 (3, 1)
	108 -89 (3, 1)
	109 goto (3, 1)
	110 -51 (3, 1)
	112 iconst_1 (2, 4)
	113 ireturn (2, 4)

Method: hashCode
	0 ldc (0, 0)
	1 322562 (0, 0)
	2 istore_1 (0, 0)
	3 aload_0 (0, 0)
	4 invokevirtual (0, 0)
	5 org/apache/commons/math3/linear/AbstractFieldMatrix.getRowDimension:()I (0, 0)
	7 istore_2 (0, 0)
	8 aload_0 (0, 0)
	9 invokevirtual (0, 0)
	10 org/apache/commons/math3/linear/AbstractFieldMatrix.getColumnDimension:()I (0, 0)
	12 istore_3 (0, 0)
	13 iload_1 (0, 0)
	14 bipush (0, 0)
	15 31 (0, 0)
	16 imul (0, 0)
	17 iload_2 (0, 0)
	18 iadd (0, 0)
	19 istore_1 (0, 0)
	20 iload_1 (0, 0)
	21 bipush (0, 0)
	22 31 (0, 0)
	23 imul (0, 0)
	24 iload_3 (0, 0)
	25 iadd (0, 0)
	26 istore_1 (0, 0)
	27 iconst_0 (1, 4)
	28 istore (1, 4)
	29 #4 (1, 4)
	30 iload (1, 4)
	31 #4 (1, 4)
	32 iload_2 (1, 4)
	33 if_icmpge (1, 4)
	34 57 (1, 4)
	36 iconst_0 (2, 4)
	37 istore (2, 4)
	38 #5 (2, 4)
	39 iload (2, 4)
	40 #5 (2, 4)
	41 iload_3 (2, 4)
	42 if_icmpge (2, 4)
	43 42 (2, 4)
	45 iload_1 (2, 4)
	46 bipush (2, 4)
	47 31 (2, 4)
	48 imul (2, 4)
	49 bipush (2, 4)
	50 11 (2, 4)
	51 iload (2, 4)
	52 #4 (2, 4)
	53 iconst_1 (2, 4)
	54 iadd (2, 4)
	55 imul (2, 4)
	56 bipush (2, 4)
	57 17 (2, 4)
	58 iload (2, 4)
	59 #5 (2, 4)
	60 iconst_1 (2, 4)
	61 iadd (2, 4)
	62 imul (2, 4)
	63 iadd (2, 4)
	64 aload_0 (2, 4)
	65 iload (2, 4)
	66 #4 (2, 4)
	67 iload (2, 4)
	68 #5 (2, 4)
	69 invokevirtual (2, 4)
	70 org/apache/commons/math3/linear/AbstractFieldMatrix.getEntry:(II)Lorg/apache/commons/math3/FieldElement; (2, 4)
	72 invokevirtual (2, 4)
	73 java/lang/Object.hashCode:()I (2, 4)
	75 imul (2, 4)
	76 iadd (2, 4)
	77 istore_1 (2, 4)
	78 iinc (2, 4)
	79 #5 (2, 4)
	80 -89 (2, 4)
	81 goto (2, 4)
	82 -42 (2, 4)
	84 iinc (2, 4)
	85 #4 (2, 4)
	86 -89 (2, 4)
	87 goto (2, 4)
	88 -57 (2, 4)
	90 iload_1 (1, 4)
	91 ireturn (1, 4)

Method: checkRowIndex
	0 iload_1 (1, 1)
	1 iflt (1, 1)
	2 11 (1, 1)
	4 iload_1 (1, 1)
	5 aload_0 (1, 1)
	6 invokevirtual (1, 1)
	7 org/apache/commons/math3/linear/AbstractFieldMatrix.getRowDimension:()I (1, 1)
	9 if_icmplt (1, 1)
	10 31 (1, 1)
	12 new (1, 1)
	13 org/apache/commons/math3/exception/OutOfRangeException (1, 1)
	15 dup (1, 1)
	16 getstatic (1, 1)
	17 org/apache/commons/math3/exception/util/LocalizedFormats.ROW_INDEX:Lorg/apache/commons/math3/exception/util/LocalizedFormats; (1, 1)
	19 iload_1 (1, 1)
	20 invokestatic (1, 1)
	21 java/lang/Integer.valueOf:(I)Ljava/lang/Integer; (1, 1)
	23 iconst_0 (1, 1)
	24 invokestatic (1, 1)
	25 java/lang/Integer.valueOf:(I)Ljava/lang/Integer; (1, 1)
	27 aload_0 (1, 1)
	28 invokevirtual (1, 1)
	29 org/apache/commons/math3/linear/AbstractFieldMatrix.getRowDimension:()I (1, 1)
	31 iconst_1 (1, 1)
	32 isub (1, 1)
	33 invokestatic (1, 1)
	34 java/lang/Integer.valueOf:(I)Ljava/lang/Integer; (1, 1)
	36 invokespecial (1, 1)
	37 org/apache/commons/math3/exception/OutOfRangeException.<init>:(Lorg/apache/commons/math3/exception/util/Localizable;Ljava/lang/Number;Ljava/lang/Number;Ljava/lang/Number;)V (1, 1)
	39 athrow (1, 1)
	40 return (0, 0)

Method: checkColumnIndex
	0 iload_1 (1, 1)
	1 iflt (1, 1)
	2 11 (1, 1)
	4 iload_1 (1, 1)
	5 aload_0 (1, 1)
	6 invokevirtual (1, 1)
	7 org/apache/commons/math3/linear/AbstractFieldMatrix.getColumnDimension:()I (1, 1)
	9 if_icmplt (1, 1)
	10 31 (1, 1)
	12 new (1, 1)
	13 org/apache/commons/math3/exception/OutOfRangeException (1, 1)
	15 dup (1, 1)
	16 getstatic (1, 1)
	17 org/apache/commons/math3/exception/util/LocalizedFormats.COLUMN_INDEX:Lorg/apache/commons/math3/exception/util/LocalizedFormats; (1, 1)
	19 iload_1 (1, 1)
	20 invokestatic (1, 1)
	21 java/lang/Integer.valueOf:(I)Ljava/lang/Integer; (1, 1)
	23 iconst_0 (1, 1)
	24 invokestatic (1, 1)
	25 java/lang/Integer.valueOf:(I)Ljava/lang/Integer; (1, 1)
	27 aload_0 (1, 1)
	28 invokevirtual (1, 1)
	29 org/apache/commons/math3/linear/AbstractFieldMatrix.getColumnDimension:()I (1, 1)
	31 iconst_1 (1, 1)
	32 isub (1, 1)
	33 invokestatic (1, 1)
	34 java/lang/Integer.valueOf:(I)Ljava/lang/Integer; (1, 1)
	36 invokespecial (1, 1)
	37 org/apache/commons/math3/exception/OutOfRangeException.<init>:(Lorg/apache/commons/math3/exception/util/Localizable;Ljava/lang/Number;Ljava/lang/Number;Ljava/lang/Number;)V (1, 1)
	39 athrow (1, 1)
	40 return (0, 0)

Method: checkSubMatrixIndex
	0 aload_1 (0, 1)
	1 ifnull (0, 1)
	2 7 (0, 1)
	4 aload_2 (0, 1)
	5 ifnonnull (0, 1)
	6 11 (0, 1)
	8 new (0, 1)
	9 org/apache/commons/math3/exception/NullArgumentException (0, 1)
	11 dup (0, 1)
	12 invokespecial (0, 1)
	13 org/apache/commons/math3/exception/NullArgumentException.<init>:()V (0, 1)
	15 athrow (0, 1)
	16 aload_1 (0, 1)
	17 arraylength (0, 1)
	18 ifeq (0, 1)
	19 8 (0, 1)
	21 aload_2 (0, 1)
	22 arraylength (0, 1)
	23 ifne (0, 1)
	24 11 (0, 1)
	26 new (0, 1)
	27 org/apache/commons/math3/exception/NoDataException (0, 1)
	29 dup (0, 1)
	30 invokespecial (0, 1)
	31 org/apache/commons/math3/exception/NoDataException.<init>:()V (0, 1)
	33 athrow (0, 1)
	34 aload_1 (1, 4)
	35 astore_3 (1, 4)
	36 aload_3 (1, 4)
	37 arraylength (1, 4)
	38 istore (1, 4)
	39 #4 (1, 4)
	40 iconst_0 (1, 4)
	41 istore (1, 4)
	42 #5 (1, 4)
	43 iload (1, 4)
	44 #5 (1, 4)
	45 iload (1, 4)
	46 #4 (1, 4)
	47 if_icmpge (1, 4)
	48 21 (1, 4)
	50 aload_3 (1, 4)
	51 iload (1, 4)
	52 #5 (1, 4)
	53 iaload (1, 4)
	54 istore (1, 4)
	55 #6 (1, 4)
	56 aload_0 (1, 4)
	57 iload (1, 4)
	58 #6 (1, 4)
	59 invokevirtual (1, 4)
	60 org/apache/commons/math3/linear/AbstractFieldMatrix.checkRowIndex:(I)V (1, 4)
	62 iinc (1, 4)
	63 #5 (1, 4)
	64 -89 (1, 4)
	65 goto (1, 4)
	66 -22 (1, 4)
	68 aload_2 (1, 4)
	69 astore_3 (1, 4)
	70 aload_3 (1, 4)
	71 arraylength (1, 4)
	72 istore (1, 4)
	73 #4 (1, 4)
	74 iconst_0 (1, 4)
	75 istore (1, 4)
	76 #5 (1, 4)
	77 iload (1, 4)
	78 #5 (1, 4)
	79 iload (1, 4)
	80 #4 (1, 4)
	81 if_icmpge (1, 4)
	82 21 (1, 4)
	84 aload_3 (1, 4)
	85 iload (1, 4)
	86 #5 (1, 4)
	87 iaload (1, 4)
	88 istore (1, 4)
	89 #6 (1, 4)
	90 aload_0 (1, 4)
	91 iload (1, 4)
	92 #6 (1, 4)
	93 invokevirtual (1, 4)
	94 org/apache/commons/math3/linear/AbstractFieldMatrix.checkColumnIndex:(I)V (1, 4)
	96 iinc (1, 4)
	97 #5 (1, 4)
	98 -89 (1, 4)
	99 goto (1, 4)
	100 -22 (1, 4)
	102 return (0, 1)

Method: checkAdditionCompatible
	0 aload_0 (0, 1)
	1 invokevirtual (0, 1)
	2 org/apache/commons/math3/linear/AbstractFieldMatrix.getRowDimension:()I (0, 1)
	4 aload_1 (0, 1)
	5 invokeinterface (0, 1)
	6 org/apache/commons/math3/linear/FieldMatrix.getColumnDimension:()I (0, 1)
	8 0 (0, 1)
	10 if_icmpne (0, 1)
	11 16 (0, 1)
	13 aload_0 (0, 1)
	14 invokevirtual (0, 1)
	15 org/apache/commons/math3/linear/AbstractFieldMatrix.getColumnDimension:()I (0, 1)
	17 aload_1 (0, 1)
	18 invokeinterface (0, 1)
	19 org/apache/commons/math3/linear/FieldMatrix.createMatrix:(II)Lorg/apache/commons/math3/linear/FieldMatrix; (0, 1)
	21 0 (0, 1)
	23 if_icmpeq (0, 1)
	24 31 (0, 1)
	26 new (0, 1)
	27 org/apache/commons/math3/linear/MatrixDimensionMismatchException (0, 1)
	29 dup (0, 1)
	30 aload_1 (0, 1)
	31 invokeinterface (0, 1)
	32 org/apache/commons/math3/linear/FieldMatrix.getColumnDimension:()I (0, 1)
	34 0 (0, 1)
	36 aload_1 (0, 1)
	37 invokeinterface (0, 1)
	38 org/apache/commons/math3/linear/FieldMatrix.createMatrix:(II)Lorg/apache/commons/math3/linear/FieldMatrix; (0, 1)
	40 0 (0, 1)
	42 aload_0 (0, 1)
	43 invokevirtual (0, 1)
	44 org/apache/commons/math3/linear/AbstractFieldMatrix.getRowDimension:()I (0, 1)
	46 aload_0 (0, 1)
	47 invokevirtual (0, 1)
	48 org/apache/commons/math3/linear/AbstractFieldMatrix.getColumnDimension:()I (0, 1)
	50 invokespecial (0, 1)
	51 org/apache/commons/math3/linear/MatrixDimensionMismatchException.<init>:(IIII)V (0, 1)
	53 athrow (0, 1)
	54 return (0, 1)

Method: checkSubtractionCompatible
	0 aload_0 (0, 1)
	1 invokevirtual (0, 1)
	2 org/apache/commons/math3/linear/AbstractFieldMatrix.getRowDimension:()I (0, 1)
	4 aload_1 (0, 1)
	5 invokeinterface (0, 1)
	6 org/apache/commons/math3/linear/FieldMatrix.getColumnDimension:()I (0, 1)
	8 0 (0, 1)
	10 if_icmpne (0, 1)
	11 16 (0, 1)
	13 aload_0 (0, 1)
	14 invokevirtual (0, 1)
	15 org/apache/commons/math3/linear/AbstractFieldMatrix.getColumnDimension:()I (0, 1)
	17 aload_1 (0, 1)
	18 invokeinterface (0, 1)
	19 org/apache/commons/math3/linear/FieldMatrix.createMatrix:(II)Lorg/apache/commons/math3/linear/FieldMatrix; (0, 1)
	21 0 (0, 1)
	23 if_icmpeq (0, 1)
	24 31 (0, 1)
	26 new (0, 1)
	27 org/apache/commons/math3/linear/MatrixDimensionMismatchException (0, 1)
	29 dup (0, 1)
	30 aload_1 (0, 1)
	31 invokeinterface (0, 1)
	32 org/apache/commons/math3/linear/FieldMatrix.getColumnDimension:()I (0, 1)
	34 0 (0, 1)
	36 aload_1 (0, 1)
	37 invokeinterface (0, 1)
	38 org/apache/commons/math3/linear/FieldMatrix.createMatrix:(II)Lorg/apache/commons/math3/linear/FieldMatrix; (0, 1)
	40 0 (0, 1)
	42 aload_0 (0, 1)
	43 invokevirtual (0, 1)
	44 org/apache/commons/math3/linear/AbstractFieldMatrix.getRowDimension:()I (0, 1)
	46 aload_0 (0, 1)
	47 invokevirtual (0, 1)
	48 org/apache/commons/math3/linear/AbstractFieldMatrix.getColumnDimension:()I (0, 1)
	50 invokespecial (0, 1)
	51 org/apache/commons/math3/linear/MatrixDimensionMismatchException.<init>:(IIII)V (0, 1)
	53 athrow (0, 1)
	54 return (0, 1)

Method: checkMultiplicationCompatible
	0 aload_0 (1, 1)
	1 invokevirtual (1, 1)
	2 org/apache/commons/math3/linear/AbstractFieldMatrix.getColumnDimension:()I (1, 1)
	4 aload_1 (1, 1)
	5 invokeinterface (1, 1)
	6 org/apache/commons/math3/linear/FieldMatrix.getColumnDimension:()I (1, 1)
	8 0 (1, 1)
	10 if_icmpeq (1, 1)
	11 21 (1, 1)
	13 new (1, 1)
	14 org/apache/commons/math3/exception/DimensionMismatchException (1, 1)
	16 dup (1, 1)
	17 aload_1 (1, 1)
	18 invokeinterface (1, 1)
	19 org/apache/commons/math3/linear/FieldMatrix.getColumnDimension:()I (1, 1)
	21 0 (1, 1)
	23 aload_0 (1, 1)
	24 invokevirtual (1, 1)
	25 org/apache/commons/math3/linear/AbstractFieldMatrix.getColumnDimension:()I (1, 1)
	27 invokespecial (1, 1)
	28 org/apache/commons/math3/exception/DimensionMismatchException.<init>:(II)V (1, 1)
	30 athrow (1, 1)
	31 return (0, 0)

