Method: start
	0 aload_0 (0, 0)
	1 iload (0, 0)
	3 i2d (0, 0)
	4 putfield (0, 0)
	7 aload_0 (0, 0)
	8 dconst_0 (0, 0)
	9 putfield (0, 0)
	12 aload_0 (0, 0)
	13 dconst_0 (0, 0)
	14 putfield (0, 0)
	17 return (0, 0)

Method: visit
	0 aload_0 (0, 0)
	1 dup (0, 0)
	2 getfield (0, 0)
	5 dload_3 (0, 0)
	6 invokestatic (0, 0)
	9 dadd (0, 0)
	10 putfield (0, 0)
	13 iload_1 (1, 1)
	14 i2d (1, 1)
	15 aload_0 (1, 1)
	16 getfield (1, 1)
	19 dcmpl (1, 1)
	20 ifne (1, 1)
	23 aload_0 (1, 1)
	24 aload_0 (1, 1)
	25 getfield (1, 1)
	28 aload_0 (1, 1)
	29 getfield (1, 1)
	32 invokestatic (1, 1)
	35 putfield (1, 1)
	38 aload_0 (1, 1)
	39 dconst_0 (1, 1)
	40 putfield (1, 1)
	43 return (0, 0)

Method: end
	0 aload_0 (0, 0)
	1 getfield (0, 0)
	4 dreturn (0, 0)

