Method: <init>
	0 aload_0 (0, 0)
	1 invokespecial (0, 0)
	2 org/apache/commons/math3/linear/AbstractRealMatrix.<init>:()V (0, 0)
	4 aload_1 (0, 0)
	5 arraylength (0, 0)
	6 istore_2 (0, 0)
	7 aload_0 (0, 0)
	8 iload_2 (0, 0)
	9 iconst_1 (0, 0)
	10 multianewarray (0, 0)
	11 [[D (0, 0)
	13 -75 (0, 0)
	14 putfield (0, 0)
	15 org/apache/commons/math3/linear/Array2DRowRealMatrix.data:[[D (0, 0)
	17 iconst_0 (1, 4)
	18 istore_3 (1, 4)
	19 iload_3 (1, 4)
	20 iload_2 (1, 4)
	21 if_icmpge (1, 4)
	22 20 (1, 4)
	24 aload_0 (1, 4)
	25 getfield (1, 4)
	26 org/apache/commons/math3/linear/Array2DRowRealMatrix.data:[[D (1, 4)
	28 iload_3 (1, 4)
	29 aaload (1, 4)
	30 iconst_0 (1, 4)
	31 aload_1 (1, 4)
	32 iload_3 (1, 4)
	33 daload (1, 4)
	34 dastore (1, 4)
	35 iinc (1, 4)
	36 #3 (1, 4)
	37 -89 (1, 4)
	38 goto (1, 4)
	39 -19 (1, 4)
	41 return (0, 0)

Method: createMatrix
	0 new (0, 0)
	1 org/apache/commons/math3/linear/Array2DRowRealMatrix (0, 0)
	3 dup (0, 0)
	4 iload_1 (0, 0)
	5 iload_2 (0, 0)
	6 invokespecial (0, 0)
	7 org/apache/commons/math3/linear/Array2DRowRealMatrix.<init>:(II)V (0, 0)
	9 areturn (0, 0)

Method: copy
	0 new (0, 0)
	1 org/apache/commons/math3/linear/Array2DRowRealMatrix (0, 0)
	3 dup (0, 0)
	4 aload_0 (0, 0)
	5 invokespecial (0, 0)
	6 org/apache/commons/math3/linear/Array2DRowRealMatrix.copyOut:()[[D (0, 0)
	8 iconst_0 (0, 0)
	9 invokespecial (0, 0)
	10 org/apache/commons/math3/linear/Array2DRowRealMatrix.<init>:([[DZ)V (0, 0)
	12 areturn (0, 0)

Method: add
	0 aload_0 (0, 0)
	1 aload_1 (0, 0)
	2 invokestatic (0, 0)
	3 org/apache/commons/math3/linear/MatrixUtils.checkAdditionCompatible:(Lorg/apache/commons/math3/linear/AnyMatrix;Lorg/apache/commons/math3/linear/AnyMatrix;)V (0, 0)
	5 aload_0 (0, 0)
	6 invokevirtual (0, 0)
	7 org/apache/commons/math3/linear/Array2DRowRealMatrix.getRowDimension:()I (0, 0)
	9 istore_2 (0, 0)
	10 aload_0 (0, 0)
	11 invokevirtual (0, 0)
	12 org/apache/commons/math3/linear/Array2DRowRealMatrix.getColumnDimension:()I (0, 0)
	14 istore_3 (0, 0)
	15 iload_2 (0, 0)
	16 iload_3 (0, 0)
	17 multianewarray (0, 0)
	18 [[D (0, 0)
	20 58 (0, 0)
	21 astore (0, 0)
	22 #4 (0, 0)
	23 iconst_0 (1, 4)
	24 istore (1, 4)
	25 #5 (1, 4)
	26 iload (1, 4)
	27 #5 (1, 4)
	28 iload_2 (1, 4)
	29 if_icmpge (1, 4)
	30 65 (1, 4)
	32 aload_0 (1, 4)
	33 getfield (1, 4)
	34 org/apache/commons/math3/linear/Array2DRowRealMatrix.data:[[D (1, 4)
	36 iload (1, 4)
	37 #5 (1, 4)
	38 aaload (1, 4)
	39 astore (1, 4)
	40 #6 (1, 4)
	41 aload_1 (1, 4)
	42 getfield (1, 4)
	43 org/apache/commons/math3/linear/Array2DRowRealMatrix.data:[[D (1, 4)
	45 iload (1, 4)
	46 #5 (1, 4)
	47 aaload (1, 4)
	48 astore (1, 4)
	49 #7 (1, 4)
	50 aload (1, 4)
	51 #4 (1, 4)
	52 iload (1, 4)
	53 #5 (1, 4)
	54 aaload (1, 4)
	55 astore (1, 4)
	56 #8 (1, 4)
	57 iconst_0 (2, 4)
	58 istore (2, 4)
	59 #9 (2, 4)
	60 iload (2, 4)
	61 #9 (2, 4)
	62 iload_3 (2, 4)
	63 if_icmpge (2, 4)
	64 25 (2, 4)
	66 aload (2, 4)
	67 #8 (2, 4)
	68 iload (2, 4)
	69 #9 (2, 4)
	70 aload (2, 4)
	71 #6 (2, 4)
	72 iload (2, 4)
	73 #9 (2, 4)
	74 daload (2, 4)
	75 aload (2, 4)
	76 #7 (2, 4)
	77 iload (2, 4)
	78 #9 (2, 4)
	79 daload (2, 4)
	80 dadd (2, 4)
	81 dastore (2, 4)
	82 iinc (2, 4)
	83 #9 (2, 4)
	84 -89 (2, 4)
	85 goto (2, 4)
	86 -25 (2, 4)
	88 iinc (2, 4)
	89 #5 (2, 4)
	90 -89 (2, 4)
	91 goto (2, 4)
	92 -65 (2, 4)
	94 new (1, 4)
	95 org/apache/commons/math3/linear/Array2DRowRealMatrix (1, 4)
	97 dup (1, 4)
	98 aload (1, 4)
	99 #4 (1, 4)
	100 iconst_0 (1, 4)
	101 invokespecial (1, 4)
	102 org/apache/commons/math3/linear/Array2DRowRealMatrix.<init>:([[DZ)V (1, 4)
	104 areturn (1, 4)

Method: subtract
	0 aload_0 (0, 0)
	1 aload_1 (0, 0)
	2 invokestatic (0, 0)
	3 org/apache/commons/math3/linear/MatrixUtils.checkSubtractionCompatible:(Lorg/apache/commons/math3/linear/AnyMatrix;Lorg/apache/commons/math3/linear/AnyMatrix;)V (0, 0)
	5 aload_0 (0, 0)
	6 invokevirtual (0, 0)
	7 org/apache/commons/math3/linear/Array2DRowRealMatrix.getRowDimension:()I (0, 0)
	9 istore_2 (0, 0)
	10 aload_0 (0, 0)
	11 invokevirtual (0, 0)
	12 org/apache/commons/math3/linear/Array2DRowRealMatrix.getColumnDimension:()I (0, 0)
	14 istore_3 (0, 0)
	15 iload_2 (0, 0)
	16 iload_3 (0, 0)
	17 multianewarray (0, 0)
	18 [[D (0, 0)
	20 58 (0, 0)
	21 astore (0, 0)
	22 #4 (0, 0)
	23 iconst_0 (1, 4)
	24 istore (1, 4)
	25 #5 (1, 4)
	26 iload (1, 4)
	27 #5 (1, 4)
	28 iload_2 (1, 4)
	29 if_icmpge (1, 4)
	30 65 (1, 4)
	32 aload_0 (1, 4)
	33 getfield (1, 4)
	34 org/apache/commons/math3/linear/Array2DRowRealMatrix.data:[[D (1, 4)
	36 iload (1, 4)
	37 #5 (1, 4)
	38 aaload (1, 4)
	39 astore (1, 4)
	40 #6 (1, 4)
	41 aload_1 (1, 4)
	42 getfield (1, 4)
	43 org/apache/commons/math3/linear/Array2DRowRealMatrix.data:[[D (1, 4)
	45 iload (1, 4)
	46 #5 (1, 4)
	47 aaload (1, 4)
	48 astore (1, 4)
	49 #7 (1, 4)
	50 aload (1, 4)
	51 #4 (1, 4)
	52 iload (1, 4)
	53 #5 (1, 4)
	54 aaload (1, 4)
	55 astore (1, 4)
	56 #8 (1, 4)
	57 iconst_0 (2, 4)
	58 istore (2, 4)
	59 #9 (2, 4)
	60 iload (2, 4)
	61 #9 (2, 4)
	62 iload_3 (2, 4)
	63 if_icmpge (2, 4)
	64 25 (2, 4)
	66 aload (2, 4)
	67 #8 (2, 4)
	68 iload (2, 4)
	69 #9 (2, 4)
	70 aload (2, 4)
	71 #6 (2, 4)
	72 iload (2, 4)
	73 #9 (2, 4)
	74 daload (2, 4)
	75 aload (2, 4)
	76 #7 (2, 4)
	77 iload (2, 4)
	78 #9 (2, 4)
	79 daload (2, 4)
	80 dsub (2, 4)
	81 dastore (2, 4)
	82 iinc (2, 4)
	83 #9 (2, 4)
	84 -89 (2, 4)
	85 goto (2, 4)
	86 -25 (2, 4)
	88 iinc (2, 4)
	89 #5 (2, 4)
	90 -89 (2, 4)
	91 goto (2, 4)
	92 -65 (2, 4)
	94 new (1, 4)
	95 org/apache/commons/math3/linear/Array2DRowRealMatrix (1, 4)
	97 dup (1, 4)
	98 aload (1, 4)
	99 #4 (1, 4)
	100 iconst_0 (1, 4)
	101 invokespecial (1, 4)
	102 org/apache/commons/math3/linear/Array2DRowRealMatrix.<init>:([[DZ)V (1, 4)
	104 areturn (1, 4)

Method: multiply
	0 aload_0 (0, 0)
	1 aload_1 (0, 0)
	2 invokestatic (0, 0)
	3 org/apache/commons/math3/linear/MatrixUtils.checkMultiplicationCompatible:(Lorg/apache/commons/math3/linear/AnyMatrix;Lorg/apache/commons/math3/linear/AnyMatrix;)V (0, 0)
	5 aload_0 (0, 0)
	6 invokevirtual (0, 0)
	7 org/apache/commons/math3/linear/Array2DRowRealMatrix.getRowDimension:()I (0, 0)
	9 istore_2 (0, 0)
	10 aload_1 (0, 0)
	11 invokevirtual (0, 0)
	12 org/apache/commons/math3/linear/Array2DRowRealMatrix.getColumnDimension:()I (0, 0)
	14 istore_3 (0, 0)
	15 aload_0 (0, 0)
	16 invokevirtual (0, 0)
	17 org/apache/commons/math3/linear/Array2DRowRealMatrix.getColumnDimension:()I (0, 0)
	19 istore (0, 0)
	20 #4 (0, 0)
	21 iload_2 (0, 0)
	22 iload_3 (0, 0)
	23 multianewarray (0, 0)
	24 [[D (0, 0)
	26 58 (0, 0)
	27 astore (0, 0)
	28 #5 (0, 0)
	29 iload (0, 0)
	30 #4 (0, 0)
	31 newarray (0, 0)
	32 7 (0, 0)
	33 astore (0, 0)
	34 #6 (0, 0)
	35 aload_1 (0, 0)
	36 getfield (0, 0)
	37 org/apache/commons/math3/linear/Array2DRowRealMatrix.data:[[D (0, 0)
	39 astore (0, 0)
	40 #7 (0, 0)
	41 iconst_0 (1, 4)
	42 istore (1, 4)
	43 #8 (1, 4)
	44 iload (1, 4)
	45 #8 (1, 4)
	46 iload_3 (1, 4)
	47 if_icmpge (1, 4)
	48 107 (1, 4)
	50 iconst_0 (2, 4)
	51 istore (2, 4)
	52 #9 (2, 4)
	53 iload (2, 4)
	54 #9 (2, 4)
	55 iload (2, 4)
	56 #4 (2, 4)
	57 if_icmpge (2, 4)
	58 22 (2, 4)
	60 aload (2, 4)
	61 #6 (2, 4)
	62 iload (2, 4)
	63 #9 (2, 4)
	64 aload (2, 4)
	65 #7 (2, 4)
	66 iload (2, 4)
	67 #9 (2, 4)
	68 aaload (2, 4)
	69 iload (2, 4)
	70 #8 (2, 4)
	71 daload (2, 4)
	72 dastore (2, 4)
	73 iinc (2, 4)
	74 #9 (2, 4)
	75 -89 (2, 4)
	76 goto (2, 4)
	77 -23 (2, 4)
	79 iconst_0 (2, 4)
	80 istore (2, 4)
	81 #9 (2, 4)
	82 iload (2, 4)
	83 #9 (2, 4)
	84 iload_2 (2, 4)
	85 if_icmpge (2, 4)
	86 63 (2, 4)
	88 aload_0 (2, 4)
	89 getfield (2, 4)
	90 org/apache/commons/math3/linear/Array2DRowRealMatrix.data:[[D (2, 4)
	92 iload (2, 4)
	93 #9 (2, 4)
	94 aaload (2, 4)
	95 astore (2, 4)
	96 #10 (2, 4)
	97 dconst_0 (2, 4)
	98 dstore (2, 4)
	99 #11 (2, 4)
	100 iconst_0 (3, 4)
	101 istore (3, 4)
	102 #13 (3, 4)
	103 iload (3, 4)
	104 #13 (3, 4)
	105 iload (3, 4)
	106 #4 (3, 4)
	107 if_icmpge (3, 4)
	108 25 (3, 4)
	110 dload (3, 4)
	111 #11 (3, 4)
	112 aload (3, 4)
	113 #10 (3, 4)
	114 iload (3, 4)
	115 #13 (3, 4)
	116 daload (3, 4)
	117 aload (3, 4)
	118 #6 (3, 4)
	119 iload (3, 4)
	120 #13 (3, 4)
	121 daload (3, 4)
	122 dmul (3, 4)
	123 dadd (3, 4)
	124 dstore (3, 4)
	125 #11 (3, 4)
	126 iinc (3, 4)
	127 #13 (3, 4)
	128 -89 (3, 4)
	129 goto (3, 4)
	130 -26 (3, 4)
	132 aload (2, 4)
	133 #5 (2, 4)
	134 iload (2, 4)
	135 #9 (2, 4)
	136 aaload (2, 4)
	137 iload (2, 4)
	138 #8 (2, 4)
	139 dload (2, 4)
	140 #11 (2, 4)
	141 dastore (2, 4)
	142 iinc (2, 4)
	143 #9 (2, 4)
	144 -89 (2, 4)
	145 goto (2, 4)
	146 -63 (2, 4)
	148 iinc (2, 4)
	149 #8 (2, 4)
	150 -89 (2, 4)
	151 goto (2, 4)
	152 -107 (2, 4)
	154 new (1, 4)
	155 org/apache/commons/math3/linear/Array2DRowRealMatrix (1, 4)
	157 dup (1, 4)
	158 aload (1, 4)
	159 #5 (1, 4)
	160 iconst_0 (1, 4)
	161 invokespecial (1, 4)
	162 org/apache/commons/math3/linear/Array2DRowRealMatrix.<init>:([[DZ)V (1, 4)
	164 areturn (1, 4)

Method: getData
	0 aload_0 (0, 0)
	1 invokespecial (0, 0)
	2 org/apache/commons/math3/linear/Array2DRowRealMatrix.copyOut:()[[D (0, 0)
	4 areturn (0, 0)

Method: getDataRef
	0 aload_0 (0, 0)
	1 getfield (0, 0)
	2 org/apache/commons/math3/linear/Array2DRowRealMatrix.data:[[D (0, 0)
	4 areturn (0, 0)

Method: setSubMatrix
	0 aload_0 (1, 1)
	1 getfield (1, 1)
	2 org/apache/commons/math3/linear/Array2DRowRealMatrix.data:[[D (1, 1)
	4 ifnonnull (1, 1)
	5 180 (1, 1)
	7 iload_2 (2, 1)
	8 ifle (2, 1)
	9 25 (2, 1)
	11 new (2, 1)
	12 org/apache/commons/math3/exception/MathIllegalStateException (2, 1)
	14 dup (2, 1)
	15 getstatic (2, 1)
	16 org/apache/commons/math3/exception/util/LocalizedFormats.FIRST_ROWS_NOT_INITIALIZED_YET:Lorg/apache/commons/math3/exception/util/LocalizedFormats; (2, 1)
	18 iconst_1 (2, 1)
	19 anewarray (2, 1)
	20 java/lang/Object (2, 1)
	22 dup (2, 1)
	23 iconst_0 (2, 1)
	24 iload_2 (2, 1)
	25 invokestatic (2, 1)
	26 java/lang/Integer.valueOf:(I)Ljava/lang/Integer; (2, 1)
	28 aastore (2, 1)
	29 invokespecial (2, 1)
	30 org/apache/commons/math3/exception/MathIllegalStateException.<init>:(Lorg/apache/commons/math3/exception/util/Localizable;[Ljava/lang/Object;)V (2, 1)
	32 athrow (2, 1)
	33 iload_3 (2, 1)
	34 ifle (2, 1)
	35 25 (2, 1)
	37 new (2, 1)
	38 org/apache/commons/math3/exception/MathIllegalStateException (2, 1)
	40 dup (2, 1)
	41 getstatic (2, 1)
	42 org/apache/commons/math3/exception/util/LocalizedFormats.FIRST_COLUMNS_NOT_INITIALIZED_YET:Lorg/apache/commons/math3/exception/util/LocalizedFormats; (2, 1)
	44 iconst_1 (2, 1)
	45 anewarray (2, 1)
	46 java/lang/Object (2, 1)
	48 dup (2, 1)
	49 iconst_0 (2, 1)
	50 iload_3 (2, 1)
	51 invokestatic (2, 1)
	52 java/lang/Integer.valueOf:(I)Ljava/lang/Integer; (2, 1)
	54 aastore (2, 1)
	55 invokespecial (2, 1)
	56 org/apache/commons/math3/exception/MathIllegalStateException.<init>:(Lorg/apache/commons/math3/exception/util/Localizable;[Ljava/lang/Object;)V (2, 1)
	58 athrow (2, 1)
	59 aload_1 (1, 1)
	60 invokestatic (1, 1)
	61 org/apache/commons/math3/util/MathUtils.checkNotNull:(Ljava/lang/Object;)V (1, 1)
	63 aload_1 (1, 1)
	64 arraylength (1, 1)
	65 istore (1, 1)
	66 #4 (1, 1)
	67 iload (2, 1)
	68 #4 (2, 1)
	69 ifne (2, 1)
	70 14 (2, 1)
	72 new (2, 1)
	73 org/apache/commons/math3/exception/NoDataException (2, 1)
	75 dup (2, 1)
	76 getstatic (2, 1)
	77 org/apache/commons/math3/exception/util/LocalizedFormats.AT_LEAST_ONE_ROW:Lorg/apache/commons/math3/exception/util/LocalizedFormats; (2, 1)
	79 invokespecial (2, 1)
	80 org/apache/commons/math3/exception/NoDataException.<init>:(Lorg/apache/commons/math3/exception/util/Localizable;)V (2, 1)
	82 athrow (2, 1)
	83 aload_1 (1, 1)
	84 iconst_0 (1, 1)
	85 aaload (1, 1)
	86 arraylength (1, 1)
	87 istore (1, 1)
	88 #5 (1, 1)
	89 iload (2, 1)
	90 #5 (2, 1)
	91 ifne (2, 1)
	92 14 (2, 1)
	94 new (2, 1)
	95 org/apache/commons/math3/exception/NoDataException (2, 1)
	97 dup (2, 1)
	98 getstatic (2, 1)
	99 org/apache/commons/math3/exception/util/LocalizedFormats.AT_LEAST_ONE_COLUMN:Lorg/apache/commons/math3/exception/util/LocalizedFormats; (2, 1)
	101 invokespecial (2, 1)
	102 org/apache/commons/math3/exception/NoDataException.<init>:(Lorg/apache/commons/math3/exception/util/Localizable;)V (2, 1)
	104 athrow (2, 1)
	105 aload_0 (1, 1)
	106 aload_1 (1, 1)
	107 arraylength (1, 1)
	108 iload (1, 1)
	109 #5 (1, 1)
	110 multianewarray (1, 1)
	111 [[D (1, 1)
	113 -75 (1, 1)
	114 putfield (1, 1)
	115 org/apache/commons/math3/linear/Array2DRowRealMatrix.data:[[D (1, 1)
	117 iconst_0 (2, 4)
	118 istore (2, 4)
	119 #6 (2, 4)
	120 iload (2, 4)
	121 #6 (2, 4)
	122 aload_0 (2, 4)
	123 getfield (2, 4)
	124 org/apache/commons/math3/linear/Array2DRowRealMatrix.data:[[D (2, 4)
	126 arraylength (2, 4)
	127 if_icmpge (2, 4)
	128 54 (2, 4)
	130 aload_1 (3, 1)
	131 iload (3, 1)
	132 #6 (3, 1)
	133 aaload (3, 1)
	134 arraylength (3, 1)
	135 iload (3, 1)
	136 #5 (3, 1)
	137 if_icmpeq (3, 1)
	138 18 (3, 1)
	140 new (3, 1)
	141 org/apache/commons/math3/exception/DimensionMismatchException (3, 1)
	143 dup (3, 1)
	144 aload_1 (3, 1)
	145 iload (3, 1)
	146 #6 (3, 1)
	147 aaload (3, 1)
	148 arraylength (3, 1)
	149 iload (3, 1)
	150 #5 (3, 1)
	151 invokespecial (3, 1)
	152 org/apache/commons/math3/exception/DimensionMismatchException.<init>:(II)V (3, 1)
	154 athrow (3, 1)
	155 aload_1 (2, 4)
	156 iload (2, 4)
	157 #6 (2, 4)
	158 aaload (2, 4)
	159 iconst_0 (2, 4)
	160 aload_0 (2, 4)
	161 getfield (2, 4)
	162 org/apache/commons/math3/linear/Array2DRowRealMatrix.data:[[D (2, 4)
	164 iload (2, 4)
	165 #6 (2, 4)
	166 iload_2 (2, 4)
	167 iadd (2, 4)
	168 aaload (2, 4)
	169 iload_3 (2, 4)
	170 iload (2, 4)
	171 #5 (2, 4)
	172 invokestatic (2, 4)
	173 java/lang/System.arraycopy:(Ljava/lang/Object;ILjava/lang/Object;II)V (2, 4)
	175 iinc (2, 4)
	176 #6 (2, 4)
	177 -89 (2, 4)
	178 goto (2, 4)
	179 -58 (2, 4)
	181 goto (2, 2)
	182 10 (2, 2)
	184 aload_0 (2, 2)
	185 aload_1 (2, 2)
	186 iload_2 (2, 2)
	187 iload_3 (2, 2)
	188 invokespecial (2, 2)
	189 org/apache/commons/math3/linear/AbstractRealMatrix.setSubMatrix:([[DII)V (2, 2)
	191 return (0, 0)

Method: getEntry
	0 aload_0 (0, 0)
	1 iload_1 (0, 0)
	2 iload_2 (0, 0)
	3 invokestatic (0, 0)
	4 org/apache/commons/math3/linear/MatrixUtils.checkMatrixIndex:(Lorg/apache/commons/math3/linear/AnyMatrix;II)V (0, 0)
	6 aload_0 (0, 0)
	7 getfield (0, 0)
	8 org/apache/commons/math3/linear/Array2DRowRealMatrix.data:[[D (0, 0)
	10 iload_1 (0, 0)
	11 aaload (0, 0)
	12 iload_2 (0, 0)
	13 daload (0, 0)
	14 dreturn (0, 0)

Method: setEntry
	0 aload_0 (0, 0)
	1 iload_1 (0, 0)
	2 iload_2 (0, 0)
	3 invokestatic (0, 0)
	4 org/apache/commons/math3/linear/MatrixUtils.checkMatrixIndex:(Lorg/apache/commons/math3/linear/AnyMatrix;II)V (0, 0)
	6 aload_0 (0, 0)
	7 getfield (0, 0)
	8 org/apache/commons/math3/linear/Array2DRowRealMatrix.data:[[D (0, 0)
	10 iload_1 (0, 0)
	11 aaload (0, 0)
	12 iload_2 (0, 0)
	13 dload_3 (0, 0)
	14 dastore (0, 0)
	15 return (0, 0)

Method: addToEntry
	0 aload_0 (0, 0)
	1 iload_1 (0, 0)
	2 iload_2 (0, 0)
	3 invokestatic (0, 0)
	4 org/apache/commons/math3/linear/MatrixUtils.checkMatrixIndex:(Lorg/apache/commons/math3/linear/AnyMatrix;II)V (0, 0)
	6 aload_0 (0, 0)
	7 getfield (0, 0)
	8 org/apache/commons/math3/linear/Array2DRowRealMatrix.data:[[D (0, 0)
	10 iload_1 (0, 0)
	11 aaload (0, 0)
	12 iload_2 (0, 0)
	13 dup2 (0, 0)
	14 daload (0, 0)
	15 dload_3 (0, 0)
	16 dadd (0, 0)
	17 dastore (0, 0)
	18 return (0, 0)

Method: multiplyEntry
	0 aload_0 (0, 0)
	1 iload_1 (0, 0)
	2 iload_2 (0, 0)
	3 invokestatic (0, 0)
	4 org/apache/commons/math3/linear/MatrixUtils.checkMatrixIndex:(Lorg/apache/commons/math3/linear/AnyMatrix;II)V (0, 0)
	6 aload_0 (0, 0)
	7 getfield (0, 0)
	8 org/apache/commons/math3/linear/Array2DRowRealMatrix.data:[[D (0, 0)
	10 iload_1 (0, 0)
	11 aaload (0, 0)
	12 iload_2 (0, 0)
	13 dup2 (0, 0)
	14 daload (0, 0)
	15 dload_3 (0, 0)
	16 dmul (0, 0)
	17 dastore (0, 0)
	18 return (0, 0)

Method: getRowDimension
	0 aload_0 (0, 0)
	1 getfield (0, 0)
	2 org/apache/commons/math3/linear/Array2DRowRealMatrix.data:[[D (0, 0)
	4 ifnonnull (0, 0)
	5 7 (0, 0)
	7 iconst_0 (0, 0)
	8 goto (0, 0)
	9 8 (0, 0)
	11 aload_0 (0, 0)
	12 getfield (0, 0)
	13 org/apache/commons/math3/linear/Array2DRowRealMatrix.data:[[D (0, 0)
	15 arraylength (0, 0)
	16 ireturn (0, 0)

Method: getColumnDimension
	0 aload_0 (0, 0)
	1 getfield (0, 0)
	2 org/apache/commons/math3/linear/Array2DRowRealMatrix.data:[[D (0, 0)
	4 ifnull (0, 0)
	5 12 (0, 0)
	7 aload_0 (0, 0)
	8 getfield (0, 0)
	9 org/apache/commons/math3/linear/Array2DRowRealMatrix.data:[[D (0, 0)
	11 iconst_0 (0, 0)
	12 aaload (0, 0)
	13 ifnonnull (0, 0)
	14 7 (0, 0)
	16 iconst_0 (0, 0)
	17 goto (0, 0)
	18 10 (0, 0)
	20 aload_0 (0, 0)
	21 getfield (0, 0)
	22 org/apache/commons/math3/linear/Array2DRowRealMatrix.data:[[D (0, 0)
	24 iconst_0 (0, 0)
	25 aaload (0, 0)
	26 arraylength (0, 0)
	27 ireturn (0, 0)

Method: operate
	0 aload_0 (0, 0)
	1 invokevirtual (0, 0)
	2 org/apache/commons/math3/linear/Array2DRowRealMatrix.getRowDimension:()I (0, 0)
	4 istore_2 (0, 0)
	5 aload_0 (0, 0)
	6 invokevirtual (0, 0)
	7 org/apache/commons/math3/linear/Array2DRowRealMatrix.getColumnDimension:()I (0, 0)
	9 istore_3 (0, 0)
	10 aload_1 (1, 1)
	11 arraylength (1, 1)
	12 iload_3 (1, 1)
	13 if_icmpeq (1, 1)
	14 14 (1, 1)
	16 new (1, 1)
	17 org/apache/commons/math3/exception/DimensionMismatchException (1, 1)
	19 dup (1, 1)
	20 aload_1 (1, 1)
	21 arraylength (1, 1)
	22 iload_3 (1, 1)
	23 invokespecial (1, 1)
	24 org/apache/commons/math3/exception/DimensionMismatchException.<init>:(II)V (1, 1)
	26 athrow (1, 1)
	27 iload_2 (0, 0)
	28 newarray (0, 0)
	29 7 (0, 0)
	30 astore (0, 0)
	31 #4 (0, 0)
	32 iconst_0 (1, 4)
	33 istore (1, 4)
	34 #5 (1, 4)
	35 iload (1, 4)
	36 #5 (1, 4)
	37 iload_2 (1, 4)
	38 if_icmpge (1, 4)
	39 58 (1, 4)
	41 aload_0 (1, 4)
	42 getfield (1, 4)
	43 org/apache/commons/math3/linear/Array2DRowRealMatrix.data:[[D (1, 4)
	45 iload (1, 4)
	46 #5 (1, 4)
	47 aaload (1, 4)
	48 astore (1, 4)
	49 #6 (1, 4)
	50 dconst_0 (1, 4)
	51 dstore (1, 4)
	52 #7 (1, 4)
	53 iconst_0 (2, 4)
	54 istore (2, 4)
	55 #9 (2, 4)
	56 iload (2, 4)
	57 #9 (2, 4)
	58 iload_3 (2, 4)
	59 if_icmpge (2, 4)
	60 24 (2, 4)
	62 dload (2, 4)
	63 #7 (2, 4)
	64 aload (2, 4)
	65 #6 (2, 4)
	66 iload (2, 4)
	67 #9 (2, 4)
	68 daload (2, 4)
	69 aload_1 (2, 4)
	70 iload (2, 4)
	71 #9 (2, 4)
	72 daload (2, 4)
	73 dmul (2, 4)
	74 dadd (2, 4)
	75 dstore (2, 4)
	76 #7 (2, 4)
	77 iinc (2, 4)
	78 #9 (2, 4)
	79 -89 (2, 4)
	80 goto (2, 4)
	81 -24 (2, 4)
	83 aload (1, 4)
	84 #4 (1, 4)
	85 iload (1, 4)
	86 #5 (1, 4)
	87 dload (1, 4)
	88 #7 (1, 4)
	89 dastore (1, 4)
	90 iinc (1, 4)
	91 #5 (1, 4)
	92 -89 (1, 4)
	93 goto (1, 4)
	94 -58 (1, 4)
	96 aload (0, 0)
	97 #4 (0, 0)
	98 areturn (0, 0)

Method: preMultiply
	0 aload_0 (0, 0)
	1 invokevirtual (0, 0)
	2 org/apache/commons/math3/linear/Array2DRowRealMatrix.getRowDimension:()I (0, 0)
	4 istore_2 (0, 0)
	5 aload_0 (0, 0)
	6 invokevirtual (0, 0)
	7 org/apache/commons/math3/linear/Array2DRowRealMatrix.getColumnDimension:()I (0, 0)
	9 istore_3 (0, 0)
	10 aload_1 (1, 1)
	11 arraylength (1, 1)
	12 iload_2 (1, 1)
	13 if_icmpeq (1, 1)
	14 14 (1, 1)
	16 new (1, 1)
	17 org/apache/commons/math3/exception/DimensionMismatchException (1, 1)
	19 dup (1, 1)
	20 aload_1 (1, 1)
	21 arraylength (1, 1)
	22 iload_2 (1, 1)
	23 invokespecial (1, 1)
	24 org/apache/commons/math3/exception/DimensionMismatchException.<init>:(II)V (1, 1)
	26 athrow (1, 1)
	27 iload_3 (0, 0)
	28 newarray (0, 0)
	29 7 (0, 0)
	30 astore (0, 0)
	31 #4 (0, 0)
	32 iconst_0 (1, 4)
	33 istore (1, 4)
	34 #5 (1, 4)
	35 iload (1, 4)
	36 #5 (1, 4)
	37 iload_3 (1, 4)
	38 if_icmpge (1, 4)
	39 54 (1, 4)
	41 dconst_0 (1, 4)
	42 dstore (1, 4)
	43 #6 (1, 4)
	44 iconst_0 (2, 4)
	45 istore (2, 4)
	46 #8 (2, 4)
	47 iload (2, 4)
	48 #8 (2, 4)
	49 iload_2 (2, 4)
	50 if_icmpge (2, 4)
	51 29 (2, 4)
	53 dload (2, 4)
	54 #6 (2, 4)
	55 aload_0 (2, 4)
	56 getfield (2, 4)
	57 org/apache/commons/math3/linear/Array2DRowRealMatrix.data:[[D (2, 4)
	59 iload (2, 4)
	60 #8 (2, 4)
	61 aaload (2, 4)
	62 iload (2, 4)
	63 #5 (2, 4)
	64 daload (2, 4)
	65 aload_1 (2, 4)
	66 iload (2, 4)
	67 #8 (2, 4)
	68 daload (2, 4)
	69 dmul (2, 4)
	70 dadd (2, 4)
	71 dstore (2, 4)
	72 #6 (2, 4)
	73 iinc (2, 4)
	74 #8 (2, 4)
	75 -89 (2, 4)
	76 goto (2, 4)
	77 -29 (2, 4)
	79 aload (1, 4)
	80 #4 (1, 4)
	81 iload (1, 4)
	82 #5 (1, 4)
	83 dload (1, 4)
	84 #6 (1, 4)
	85 dastore (1, 4)
	86 iinc (1, 4)
	87 #5 (1, 4)
	88 -89 (1, 4)
	89 goto (1, 4)
	90 -54 (1, 4)
	92 aload (0, 0)
	93 #4 (0, 0)
	94 areturn (0, 0)

Method: walkInRowOrder
	0 aload_0 (0, 0)
	1 iload_2 (0, 0)
	2 iload_3 (0, 0)
	3 iload (0, 0)
	4 #4 (0, 0)
	5 iload (0, 0)
	6 #5 (0, 0)
	7 invokestatic (0, 0)
	8 org/apache/commons/math3/linear/MatrixUtils.checkSubMatrixIndex:(Lorg/apache/commons/math3/linear/AnyMatrix;IIII)V (0, 0)
	10 aload_1 (0, 0)
	11 aload_0 (0, 0)
	12 invokevirtual (0, 0)
	13 org/apache/commons/math3/linear/Array2DRowRealMatrix.getRowDimension:()I (0, 0)
	15 aload_0 (0, 0)
	16 invokevirtual (0, 0)
	17 org/apache/commons/math3/linear/Array2DRowRealMatrix.getColumnDimension:()I (0, 0)
	19 iload_2 (0, 0)
	20 iload_3 (0, 0)
	21 iload (0, 0)
	22 #4 (0, 0)
	23 iload (0, 0)
	24 #5 (0, 0)
	25 invokeinterface (0, 0)
	26 org/apache/commons/math3/linear/RealMatrixPreservingVisitor.visit:(IID)D (0, 0)
	28 0 (0, 0)
	30 iload_2 (1, 4)
	31 istore (1, 4)
	32 #6 (1, 4)
	33 iload (1, 4)
	34 #6 (1, 4)
	35 iload_3 (1, 4)
	36 if_icmpgt (1, 4)
	37 50 (1, 4)
	39 aload_0 (1, 4)
	40 getfield (1, 4)
	41 org/apache/commons/math3/linear/Array2DRowRealMatrix.data:[[D (1, 4)
	43 iload (1, 4)
	44 #6 (1, 4)
	45 aaload (1, 4)
	46 astore (1, 4)
	47 #7 (1, 4)
	48 iload (2, 4)
	49 #4 (2, 4)
	50 istore (2, 4)
	51 #8 (2, 4)
	52 iload (2, 4)
	53 #8 (2, 4)
	54 iload (2, 4)
	55 #5 (2, 4)
	56 if_icmpgt (2, 4)
	57 24 (2, 4)
	59 aload_1 (2, 4)
	60 iload (2, 4)
	61 #6 (2, 4)
	62 iload (2, 4)
	63 #8 (2, 4)
	64 aload (2, 4)
	65 #7 (2, 4)
	66 iload (2, 4)
	67 #8 (2, 4)
	68 daload (2, 4)
	69 invokeinterface (2, 4)
	70 org/apache/commons/math3/linear/RealMatrixPreservingVisitor.checkSubMatrixIndex:(Lorg/apache/commons/math3/linear/AnyMatrix;IIII)V (2, 4)
	72 0 (2, 4)
	74 iinc (2, 4)
	75 #8 (2, 4)
	76 -89 (2, 4)
	77 goto (2, 4)
	78 -25 (2, 4)
	80 iinc (2, 4)
	81 #6 (2, 4)
	82 -89 (2, 4)
	83 goto (2, 4)
	84 -50 (2, 4)
	86 aload_1 (1, 4)
	87 invokeinterface (1, 4)
	88 org/apache/commons/math3/linear/RealMatrixPreservingVisitor.org/apache/commons/math3/linear/RealMatrixPreservingVisitor (1, 4)
	90 0 (1, 4)
	92 dreturn (1, 4)

Method: walkInColumnOrder
	0 aload_0 (0, 0)
	1 iload_2 (0, 0)
	2 iload_3 (0, 0)
	3 iload (0, 0)
	4 #4 (0, 0)
	5 iload (0, 0)
	6 #5 (0, 0)
	7 invokestatic (0, 0)
	8 org/apache/commons/math3/linear/MatrixUtils.checkSubMatrixIndex:(Lorg/apache/commons/math3/linear/AnyMatrix;IIII)V (0, 0)
	10 aload_1 (0, 0)
	11 aload_0 (0, 0)
	12 invokevirtual (0, 0)
	13 org/apache/commons/math3/linear/Array2DRowRealMatrix.getRowDimension:()I (0, 0)
	15 aload_0 (0, 0)
	16 invokevirtual (0, 0)
	17 org/apache/commons/math3/linear/Array2DRowRealMatrix.getColumnDimension:()I (0, 0)
	19 iload_2 (0, 0)
	20 iload_3 (0, 0)
	21 iload (0, 0)
	22 #4 (0, 0)
	23 iload (0, 0)
	24 #5 (0, 0)
	25 invokeinterface (0, 0)
	26 org/apache/commons/math3/linear/RealMatrixPreservingVisitor.visit:(IID)D (0, 0)
	28 0 (0, 0)
	30 iload (1, 4)
	31 #4 (1, 4)
	32 istore (1, 4)
	33 #6 (1, 4)
	34 iload (1, 4)
	35 #6 (1, 4)
	36 iload (1, 4)
	37 #5 (1, 4)
	38 if_icmpgt (1, 4)
	39 44 (1, 4)
	41 iload_2 (2, 4)
	42 istore (2, 4)
	43 #7 (2, 4)
	44 iload (2, 4)
	45 #7 (2, 4)
	46 iload_3 (2, 4)
	47 if_icmpgt (2, 4)
	48 29 (2, 4)
	50 aload_1 (2, 4)
	51 iload (2, 4)
	52 #7 (2, 4)
	53 iload (2, 4)
	54 #6 (2, 4)
	55 aload_0 (2, 4)
	56 getfield (2, 4)
	57 org/apache/commons/math3/linear/Array2DRowRealMatrix.data:[[D (2, 4)
	59 iload (2, 4)
	60 #7 (2, 4)
	61 aaload (2, 4)
	62 iload (2, 4)
	63 #6 (2, 4)
	64 daload (2, 4)
	65 invokeinterface (2, 4)
	66 org/apache/commons/math3/linear/RealMatrixPreservingVisitor.checkSubMatrixIndex:(Lorg/apache/commons/math3/linear/AnyMatrix;IIII)V (2, 4)
	68 0 (2, 4)
	70 iinc (2, 4)
	71 #7 (2, 4)
	72 -89 (2, 4)
	73 goto (2, 4)
	74 -29 (2, 4)
	76 iinc (2, 4)
	77 #6 (2, 4)
	78 -89 (2, 4)
	79 goto (2, 4)
	80 -45 (2, 4)
	82 aload_1 (1, 4)
	83 invokeinterface (1, 4)
	84 org/apache/commons/math3/linear/RealMatrixPreservingVisitor.org/apache/commons/math3/linear/RealMatrixPreservingVisitor (1, 4)
	86 0 (1, 4)
	88 dreturn (1, 4)

Method: copyOut
	0 aload_0 (0, 0)
	1 invokevirtual (0, 0)
	2 org/apache/commons/math3/linear/Array2DRowRealMatrix.getRowDimension:()I (0, 0)
	4 istore_1 (0, 0)
	5 iload_1 (0, 0)
	6 aload_0 (0, 0)
	7 invokevirtual (0, 0)
	8 org/apache/commons/math3/linear/Array2DRowRealMatrix.getColumnDimension:()I (0, 0)
	10 multianewarray (0, 0)
	11 [[D (0, 0)
	13 77 (0, 0)
	14 astore_2 (0, 0)
	15 iconst_0 (1, 4)
	16 istore_3 (1, 4)
	17 iload_3 (1, 4)
	18 iload_1 (1, 4)
	19 if_icmpge (1, 4)
	20 30 (1, 4)
	22 aload_0 (1, 4)
	23 getfield (1, 4)
	24 org/apache/commons/math3/linear/Array2DRowRealMatrix.data:[[D (1, 4)
	26 iload_3 (1, 4)
	27 aaload (1, 4)
	28 iconst_0 (1, 4)
	29 aload_2 (1, 4)
	30 iload_3 (1, 4)
	31 aaload (1, 4)
	32 iconst_0 (1, 4)
	33 aload_0 (1, 4)
	34 getfield (1, 4)
	35 org/apache/commons/math3/linear/Array2DRowRealMatrix.data:[[D (1, 4)
	37 iload_3 (1, 4)
	38 aaload (1, 4)
	39 arraylength (1, 4)
	40 invokestatic (1, 4)
	41 java/lang/System.arraycopy:(Ljava/lang/Object;ILjava/lang/Object;II)V (1, 4)
	43 iinc (1, 4)
	44 #3 (1, 4)
	45 -89 (1, 4)
	46 goto (1, 4)
	47 -29 (1, 4)
	49 aload_2 (0, 0)
	50 areturn (0, 0)

Method: copyIn
	0 aload_0 (0, 0)
	1 aload_1 (0, 0)
	2 iconst_0 (0, 0)
	3 iconst_0 (0, 0)
	4 invokevirtual (0, 0)
	5 org/apache/commons/math3/linear/Array2DRowRealMatrix.setSubMatrix:([[DII)V (0, 0)
	7 return (0, 0)

