Method: <init>
	0 aload_0 (0, 0)
	1 invokespecial (0, 0)
	4 aload_2 (0, 0)
	5 invokestatic (0, 0)
	8 aload_3 (0, 0)
	9 invokestatic (0, 0)
	12 aload_2 (1, 1)
	13 arraylength (1, 1)
	14 aload_3 (1, 1)
	15 arraylength (1, 1)
	16 iadd (1, 1)
	17 ifne (1, 1)
	20 new (1, 1)
	23 dup (1, 1)
	24 getstatic (1, 1)
	27 iconst_0 (1, 1)
	28 anewarray (1, 1)
	31 invokespecial (1, 1)
	34 athrow (1, 1)
	35 aload_0 (0, 0)
	36 aload_1 (0, 0)
	37 aload_2 (0, 0)
	38 arraylength (0, 0)
	39 aload_3 (0, 0)
	40 arraylength (0, 0)
	41 iadd (0, 0)
	42 invokestatic (0, 0)
	45 checkcast (0, 0)
	48 putfield (0, 0)
	51 aload_2 (0, 0)
	52 iconst_0 (0, 0)
	53 aload_0 (0, 0)
	54 getfield (0, 0)
	57 iconst_0 (0, 0)
	58 aload_2 (0, 0)
	59 arraylength (0, 0)
	60 invokestatic (0, 0)
	63 aload_3 (0, 0)
	64 iconst_0 (0, 0)
	65 aload_0 (0, 0)
	66 getfield (0, 0)
	69 aload_2 (0, 0)
	70 arraylength (0, 0)
	71 aload_3 (0, 0)
	72 arraylength (0, 0)
	73 invokestatic (0, 0)
	76 aload_0 (0, 0)
	77 aload_1 (0, 0)
	78 putfield (0, 0)
	81 return (0, 0)

Method: getField
	0 aload_0 (0, 0)
	1 getfield (0, 0)
	4 areturn (0, 0)

Method: copy
	0 new (0, 0)
	3 dup (0, 0)
	4 aload_0 (0, 0)
	5 iconst_1 (0, 0)
	6 invokespecial (0, 0)
	9 areturn (0, 0)

Method: add
	0 aload_0 (0, 0)
	1 aload_1 (0, 0)
	2 getfield (0, 0)
	5 arraylength (0, 0)
	6 invokevirtual (0, 0)
	9 aload_0 (0, 0)
	10 getfield (0, 0)
	13 aload_0 (0, 0)
	14 getfield (0, 0)
	17 arraylength (0, 0)
	18 invokestatic (0, 0)
	21 checkcast (0, 0)
	24 astore_2 (0, 0)
	25 iconst_0 (1, 4)
	26 istore_3 (1, 4)
	27 iload_3 (1, 4)
	28 aload_0 (1, 4)
	29 getfield (1, 4)
	32 arraylength (1, 4)
	33 if_icmpge (1, 4)
	36 aload_2 (1, 4)
	37 iload_3 (1, 4)
	38 aload_0 (1, 4)
	39 getfield (1, 4)
	42 iload_3 (1, 4)
	43 aaload (1, 4)
	44 aload_1 (1, 4)
	45 getfield (1, 4)
	48 iload_3 (1, 4)
	49 aaload (1, 4)
	50 invokeinterface (1, 4)
	55 checkcast (1, 4)
	58 aastore (1, 4)
	59 iinc (1, 4)
	62 goto (1, 4)
	65 new (0, 0)
	68 dup (0, 0)
	69 aload_0 (0, 0)
	70 getfield (0, 0)
	73 aload_2 (0, 0)
	74 iconst_0 (0, 0)
	75 invokespecial (0, 0)
	78 areturn (0, 0)

Method: subtract
	0 aload_0 (0, 0)
	1 aload_1 (0, 0)
	2 getfield (0, 0)
	5 arraylength (0, 0)
	6 invokevirtual (0, 0)
	9 aload_0 (0, 0)
	10 getfield (0, 0)
	13 aload_0 (0, 0)
	14 getfield (0, 0)
	17 arraylength (0, 0)
	18 invokestatic (0, 0)
	21 checkcast (0, 0)
	24 astore_2 (0, 0)
	25 iconst_0 (1, 4)
	26 istore_3 (1, 4)
	27 iload_3 (1, 4)
	28 aload_0 (1, 4)
	29 getfield (1, 4)
	32 arraylength (1, 4)
	33 if_icmpge (1, 4)
	36 aload_2 (1, 4)
	37 iload_3 (1, 4)
	38 aload_0 (1, 4)
	39 getfield (1, 4)
	42 iload_3 (1, 4)
	43 aaload (1, 4)
	44 aload_1 (1, 4)
	45 getfield (1, 4)
	48 iload_3 (1, 4)
	49 aaload (1, 4)
	50 invokeinterface (1, 4)
	55 checkcast (1, 4)
	58 aastore (1, 4)
	59 iinc (1, 4)
	62 goto (1, 4)
	65 new (0, 0)
	68 dup (0, 0)
	69 aload_0 (0, 0)
	70 getfield (0, 0)
	73 aload_2 (0, 0)
	74 iconst_0 (0, 0)
	75 invokespecial (0, 0)
	78 areturn (0, 0)

Method: mapAdd
	0 aload_0 (0, 0)
	1 getfield (0, 0)
	4 aload_0 (0, 0)
	5 getfield (0, 0)
	8 arraylength (0, 0)
	9 invokestatic (0, 0)
	12 checkcast (0, 0)
	15 astore_2 (0, 0)
	16 iconst_0 (1, 4)
	17 istore_3 (1, 4)
	18 iload_3 (1, 4)
	19 aload_0 (1, 4)
	20 getfield (1, 4)
	23 arraylength (1, 4)
	24 if_icmpge (1, 4)
	27 aload_2 (1, 4)
	28 iload_3 (1, 4)
	29 aload_0 (1, 4)
	30 getfield (1, 4)
	33 iload_3 (1, 4)
	34 aaload (1, 4)
	35 aload_1 (1, 4)
	36 invokeinterface (1, 4)
	41 checkcast (1, 4)
	44 aastore (1, 4)
	45 iinc (1, 4)
	48 goto (1, 4)
	51 new (0, 0)
	54 dup (0, 0)
	55 aload_0 (0, 0)
	56 getfield (0, 0)
	59 aload_2 (0, 0)
	60 iconst_0 (0, 0)
	61 invokespecial (0, 0)
	64 areturn (0, 0)

Method: mapAddToSelf
	0 iconst_0 (1, 4)
	1 istore_2 (1, 4)
	2 iload_2 (1, 4)
	3 aload_0 (1, 4)
	4 getfield (1, 4)
	7 arraylength (1, 4)
	8 if_icmpge (1, 4)
	11 aload_0 (1, 4)
	12 getfield (1, 4)
	15 iload_2 (1, 4)
	16 aload_0 (1, 4)
	17 getfield (1, 4)
	20 iload_2 (1, 4)
	21 aaload (1, 4)
	22 aload_1 (1, 4)
	23 invokeinterface (1, 4)
	28 checkcast (1, 4)
	31 aastore (1, 4)
	32 iinc (1, 4)
	35 goto (1, 4)
	38 aload_0 (0, 0)
	39 areturn (0, 0)

Method: mapSubtract
	0 aload_0 (0, 0)
	1 getfield (0, 0)
	4 aload_0 (0, 0)
	5 getfield (0, 0)
	8 arraylength (0, 0)
	9 invokestatic (0, 0)
	12 checkcast (0, 0)
	15 astore_2 (0, 0)
	16 iconst_0 (1, 4)
	17 istore_3 (1, 4)
	18 iload_3 (1, 4)
	19 aload_0 (1, 4)
	20 getfield (1, 4)
	23 arraylength (1, 4)
	24 if_icmpge (1, 4)
	27 aload_2 (1, 4)
	28 iload_3 (1, 4)
	29 aload_0 (1, 4)
	30 getfield (1, 4)
	33 iload_3 (1, 4)
	34 aaload (1, 4)
	35 aload_1 (1, 4)
	36 invokeinterface (1, 4)
	41 checkcast (1, 4)
	44 aastore (1, 4)
	45 iinc (1, 4)
	48 goto (1, 4)
	51 new (0, 0)
	54 dup (0, 0)
	55 aload_0 (0, 0)
	56 getfield (0, 0)
	59 aload_2 (0, 0)
	60 iconst_0 (0, 0)
	61 invokespecial (0, 0)
	64 areturn (0, 0)

Method: mapSubtractToSelf
	0 iconst_0 (1, 4)
	1 istore_2 (1, 4)
	2 iload_2 (1, 4)
	3 aload_0 (1, 4)
	4 getfield (1, 4)
	7 arraylength (1, 4)
	8 if_icmpge (1, 4)
	11 aload_0 (1, 4)
	12 getfield (1, 4)
	15 iload_2 (1, 4)
	16 aload_0 (1, 4)
	17 getfield (1, 4)
	20 iload_2 (1, 4)
	21 aaload (1, 4)
	22 aload_1 (1, 4)
	23 invokeinterface (1, 4)
	28 checkcast (1, 4)
	31 aastore (1, 4)
	32 iinc (1, 4)
	35 goto (1, 4)
	38 aload_0 (0, 0)
	39 areturn (0, 0)

Method: mapMultiply
	0 aload_0 (0, 0)
	1 getfield (0, 0)
	4 aload_0 (0, 0)
	5 getfield (0, 0)
	8 arraylength (0, 0)
	9 invokestatic (0, 0)
	12 checkcast (0, 0)
	15 astore_2 (0, 0)
	16 iconst_0 (1, 4)
	17 istore_3 (1, 4)
	18 iload_3 (1, 4)
	19 aload_0 (1, 4)
	20 getfield (1, 4)
	23 arraylength (1, 4)
	24 if_icmpge (1, 4)
	27 aload_2 (1, 4)
	28 iload_3 (1, 4)
	29 aload_0 (1, 4)
	30 getfield (1, 4)
	33 iload_3 (1, 4)
	34 aaload (1, 4)
	35 aload_1 (1, 4)
	36 invokeinterface (1, 4)
	41 checkcast (1, 4)
	44 aastore (1, 4)
	45 iinc (1, 4)
	48 goto (1, 4)
	51 new (0, 0)
	54 dup (0, 0)
	55 aload_0 (0, 0)
	56 getfield (0, 0)
	59 aload_2 (0, 0)
	60 iconst_0 (0, 0)
	61 invokespecial (0, 0)
	64 areturn (0, 0)

Method: mapMultiplyToSelf
	0 iconst_0 (1, 4)
	1 istore_2 (1, 4)
	2 iload_2 (1, 4)
	3 aload_0 (1, 4)
	4 getfield (1, 4)
	7 arraylength (1, 4)
	8 if_icmpge (1, 4)
	11 aload_0 (1, 4)
	12 getfield (1, 4)
	15 iload_2 (1, 4)
	16 aload_0 (1, 4)
	17 getfield (1, 4)
	20 iload_2 (1, 4)
	21 aaload (1, 4)
	22 aload_1 (1, 4)
	23 invokeinterface (1, 4)
	28 checkcast (1, 4)
	31 aastore (1, 4)
	32 iinc (1, 4)
	35 goto (1, 4)
	38 aload_0 (0, 0)
	39 areturn (0, 0)

Method: mapDivide
	0 aload_1 (0, 0)
	1 invokestatic (0, 0)
	4 aload_0 (0, 0)
	5 getfield (0, 0)
	8 aload_0 (0, 0)
	9 getfield (0, 0)
	12 arraylength (0, 0)
	13 invokestatic (0, 0)
	16 checkcast (0, 0)
	19 astore_2 (0, 0)
	20 iconst_0 (1, 4)
	21 istore_3 (1, 4)
	22 iload_3 (1, 4)
	23 aload_0 (1, 4)
	24 getfield (1, 4)
	27 arraylength (1, 4)
	28 if_icmpge (1, 4)
	31 aload_2 (1, 4)
	32 iload_3 (1, 4)
	33 aload_0 (1, 4)
	34 getfield (1, 4)
	37 iload_3 (1, 4)
	38 aaload (1, 4)
	39 aload_1 (1, 4)
	40 invokeinterface (1, 4)
	45 checkcast (1, 4)
	48 aastore (1, 4)
	49 iinc (1, 4)
	52 goto (1, 4)
	55 new (0, 0)
	58 dup (0, 0)
	59 aload_0 (0, 0)
	60 getfield (0, 0)
	63 aload_2 (0, 0)
	64 iconst_0 (0, 0)
	65 invokespecial (0, 0)
	68 areturn (0, 0)

Method: mapDivideToSelf
	0 aload_1 (0, 0)
	1 invokestatic (0, 0)
	4 iconst_0 (1, 4)
	5 istore_2 (1, 4)
	6 iload_2 (1, 4)
	7 aload_0 (1, 4)
	8 getfield (1, 4)
	11 arraylength (1, 4)
	12 if_icmpge (1, 4)
	15 aload_0 (1, 4)
	16 getfield (1, 4)
	19 iload_2 (1, 4)
	20 aload_0 (1, 4)
	21 getfield (1, 4)
	24 iload_2 (1, 4)
	25 aaload (1, 4)
	26 aload_1 (1, 4)
	27 invokeinterface (1, 4)
	32 checkcast (1, 4)
	35 aastore (1, 4)
	36 iinc (1, 4)
	39 goto (1, 4)
	42 aload_0 (0, 0)
	43 areturn (0, 0)

Method: mapInv
	0 aload_0 (0, 0)
	1 getfield (0, 0)
	4 aload_0 (0, 0)
	5 getfield (0, 0)
	8 arraylength (0, 0)
	9 invokestatic (0, 0)
	12 checkcast (0, 0)
	15 astore_1 (0, 0)
	16 aload_0 (0, 0)
	17 getfield (0, 0)
	20 invokeinterface (0, 0)
	25 checkcast (0, 0)
	28 astore_2 (0, 0)
	29 iconst_0 (1, 4)
	30 istore_3 (1, 4)
	31 iload_3 (1, 4)
	32 aload_0 (1, 4)
	33 getfield (1, 4)
	36 arraylength (1, 4)
	37 if_icmpge (1, 4)
	40 aload_1 (2, 4)
	41 iload_3 (2, 4)
	42 aload_2 (2, 4)
	43 aload_0 (2, 4)
	44 getfield (2, 4)
	47 iload_3 (2, 4)
	48 aaload (2, 4)
	49 invokeinterface (2, 4)
	54 checkcast (2, 4)
	57 aastore (2, 4)
	58 goto (1, 0)
	61 astore (1, 0)
	63 new (1, 0)
	66 dup (1, 0)
	67 getstatic (1, 0)
	70 iconst_1 (1, 0)
	71 anewarray (1, 0)
	74 dup (1, 0)
	75 iconst_0 (1, 0)
	76 iload_3 (1, 0)
	77 invokestatic (1, 0)
	80 aastore (1, 0)
	81 invokespecial (1, 0)
	84 athrow (1, 0)
	85 iinc (1, 0)
	88 goto (1, 0)
	91 new (1, 0)
	94 dup (1, 0)
	95 aload_0 (1, 0)
	96 getfield (1, 0)
	99 aload_1 (1, 0)
	100 iconst_0 (1, 0)
	101 invokespecial (1, 0)
	104 areturn (1, 0)

Method: mapInvToSelf
	0 aload_0 (0, 0)
	1 getfield (0, 0)
	4 invokeinterface (0, 0)
	9 checkcast (0, 0)
	12 astore_1 (0, 0)
	13 iconst_0 (1, 4)
	14 istore_2 (1, 4)
	15 iload_2 (1, 4)
	16 aload_0 (1, 4)
	17 getfield (1, 4)
	20 arraylength (1, 4)
	21 if_icmpge (1, 4)
	24 aload_0 (2, 4)
	25 getfield (2, 4)
	28 iload_2 (2, 4)
	29 aload_1 (2, 4)
	30 aload_0 (2, 4)
	31 getfield (2, 4)
	34 iload_2 (2, 4)
	35 aaload (2, 4)
	36 invokeinterface (2, 4)
	41 checkcast (2, 4)
	44 aastore (2, 4)
	45 goto (1, 0)
	48 astore_3 (1, 0)
	49 new (1, 0)
	52 dup (1, 0)
	53 getstatic (1, 0)
	56 iconst_1 (1, 0)
	57 anewarray (1, 0)
	60 dup (1, 0)
	61 iconst_0 (1, 0)
	62 iload_2 (1, 0)
	63 invokestatic (1, 0)
	66 aastore (1, 0)
	67 invokespecial (1, 0)
	70 athrow (1, 0)
	71 iinc (1, 0)
	74 goto (1, 0)
	77 aload_0 (1, 0)
	78 areturn (1, 0)

Method: ebeMultiply
	0 aload_0 (0, 0)
	1 aload_1 (0, 0)
	2 getfield (0, 0)
	5 arraylength (0, 0)
	6 invokevirtual (0, 0)
	9 aload_0 (0, 0)
	10 getfield (0, 0)
	13 aload_0 (0, 0)
	14 getfield (0, 0)
	17 arraylength (0, 0)
	18 invokestatic (0, 0)
	21 checkcast (0, 0)
	24 astore_2 (0, 0)
	25 iconst_0 (1, 4)
	26 istore_3 (1, 4)
	27 iload_3 (1, 4)
	28 aload_0 (1, 4)
	29 getfield (1, 4)
	32 arraylength (1, 4)
	33 if_icmpge (1, 4)
	36 aload_2 (1, 4)
	37 iload_3 (1, 4)
	38 aload_0 (1, 4)
	39 getfield (1, 4)
	42 iload_3 (1, 4)
	43 aaload (1, 4)
	44 aload_1 (1, 4)
	45 getfield (1, 4)
	48 iload_3 (1, 4)
	49 aaload (1, 4)
	50 invokeinterface (1, 4)
	55 checkcast (1, 4)
	58 aastore (1, 4)
	59 iinc (1, 4)
	62 goto (1, 4)
	65 new (0, 0)
	68 dup (0, 0)
	69 aload_0 (0, 0)
	70 getfield (0, 0)
	73 aload_2 (0, 0)
	74 iconst_0 (0, 0)
	75 invokespecial (0, 0)
	78 areturn (0, 0)

Method: ebeDivide
	0 aload_0 (0, 0)
	1 aload_1 (0, 0)
	2 getfield (0, 0)
	5 arraylength (0, 0)
	6 invokevirtual (0, 0)
	9 aload_0 (0, 0)
	10 getfield (0, 0)
	13 aload_0 (0, 0)
	14 getfield (0, 0)
	17 arraylength (0, 0)
	18 invokestatic (0, 0)
	21 checkcast (0, 0)
	24 astore_2 (0, 0)
	25 iconst_0 (1, 4)
	26 istore_3 (1, 4)
	27 iload_3 (1, 4)
	28 aload_0 (1, 4)
	29 getfield (1, 4)
	32 arraylength (1, 4)
	33 if_icmpge (1, 4)
	36 aload_2 (2, 4)
	37 iload_3 (2, 4)
	38 aload_0 (2, 4)
	39 getfield (2, 4)
	42 iload_3 (2, 4)
	43 aaload (2, 4)
	44 aload_1 (2, 4)
	45 getfield (2, 4)
	48 iload_3 (2, 4)
	49 aaload (2, 4)
	50 invokeinterface (2, 4)
	55 checkcast (2, 4)
	58 aastore (2, 4)
	59 goto (1, 0)
	62 astore (1, 0)
	64 new (1, 0)
	67 dup (1, 0)
	68 getstatic (1, 0)
	71 iconst_1 (1, 0)
	72 anewarray (1, 0)
	75 dup (1, 0)
	76 iconst_0 (1, 0)
	77 iload_3 (1, 0)
	78 invokestatic (1, 0)
	81 aastore (1, 0)
	82 invokespecial (1, 0)
	85 athrow (1, 0)
	86 iinc (1, 0)
	89 goto (1, 0)
	92 new (1, 0)
	95 dup (1, 0)
	96 aload_0 (1, 0)
	97 getfield (1, 0)
	100 aload_2 (1, 0)
	101 iconst_0 (1, 0)
	102 invokespecial (1, 0)
	105 areturn (1, 0)

Method: getData
	0 aload_0 (0, 0)
	1 getfield (0, 0)
	4 invokevirtual (0, 0)
	7 checkcast (0, 0)
	10 areturn (0, 0)

Method: getDataRef
	0 aload_0 (0, 0)
	1 getfield (0, 0)
	4 areturn (0, 0)

Method: dotProduct
	0 aload_0 (0, 0)
	1 aload_1 (0, 0)
	2 getfield (0, 0)
	5 arraylength (0, 0)
	6 invokevirtual (0, 0)
	9 aload_0 (0, 0)
	10 getfield (0, 0)
	13 invokeinterface (0, 0)
	18 checkcast (0, 0)
	21 astore_2 (0, 0)
	22 iconst_0 (1, 4)
	23 istore_3 (1, 4)
	24 iload_3 (1, 4)
	25 aload_0 (1, 4)
	26 getfield (1, 4)
	29 arraylength (1, 4)
	30 if_icmpge (1, 4)
	33 aload_2 (1, 4)
	34 aload_0 (1, 4)
	35 getfield (1, 4)
	38 iload_3 (1, 4)
	39 aaload (1, 4)
	40 aload_1 (1, 4)
	41 getfield (1, 4)
	44 iload_3 (1, 4)
	45 aaload (1, 4)
	46 invokeinterface (1, 4)
	51 invokeinterface (1, 4)
	56 checkcast (1, 4)
	59 astore_2 (1, 4)
	60 iinc (1, 4)
	63 goto (1, 4)
	66 aload_2 (0, 0)
	67 areturn (0, 0)

Method: projection
	0 aload_1 (0, 0)
	1 aload_0 (0, 0)
	2 aload_1 (0, 0)
	3 invokevirtual (0, 0)
	6 aload_1 (0, 0)
	7 aload_1 (0, 0)
	8 invokevirtual (0, 0)
	11 invokeinterface (0, 0)
	16 checkcast (0, 0)
	19 invokevirtual (0, 0)
	22 checkcast (0, 0)
	25 areturn (0, 0)

Method: outerProduct
	0 aload_0 (0, 0)
	1 getfield (0, 0)
	4 arraylength (0, 0)
	5 istore_2 (0, 0)
	6 aload_1 (0, 0)
	7 getfield (0, 0)
	10 arraylength (0, 0)
	11 istore_3 (0, 0)
	12 new (0, 0)
	15 dup (0, 0)
	16 aload_0 (0, 0)
	17 getfield (0, 0)
	20 iload_2 (0, 0)
	21 iload_3 (0, 0)
	22 invokespecial (0, 0)
	25 astore (0, 0)
	27 iconst_0 (1, 4)
	28 istore (1, 4)
	30 iload (1, 4)
	32 iload_2 (1, 4)
	33 if_icmpge (1, 4)
	36 iconst_0 (2, 4)
	37 istore (2, 4)
	39 iload (2, 4)
	41 iload_3 (2, 4)
	42 if_icmpge (2, 4)
	45 aload (2, 4)
	47 iload (2, 4)
	49 iload (2, 4)
	51 aload_0 (2, 4)
	52 getfield (2, 4)
	55 iload (2, 4)
	57 aaload (2, 4)
	58 aload_1 (2, 4)
	59 getfield (2, 4)
	62 iload (2, 4)
	64 aaload (2, 4)
	65 invokeinterface (2, 4)
	70 checkcast (2, 4)
	73 invokeinterface (2, 4)
	78 iinc (2, 4)
	81 goto (2, 4)
	84 iinc (2, 4)
	87 goto (2, 4)
	90 aload (1, 4)
	92 areturn (1, 4)

Method: getEntry
	0 aload_0 (0, 0)
	1 getfield (0, 0)
	4 iload_1 (0, 0)
	5 aaload (0, 0)
	6 areturn (0, 0)

Method: getDimension
	0 aload_0 (0, 0)
	1 getfield (0, 0)
	4 arraylength (0, 0)
	5 ireturn (0, 0)

Method: append
	0 aload_0 (0, 0)
	1 getfield (0, 0)
	4 aload_0 (0, 0)
	5 getfield (0, 0)
	8 arraylength (0, 0)
	9 iconst_1 (0, 0)
	10 iadd (0, 0)
	11 invokestatic (0, 0)
	14 checkcast (0, 0)
	17 astore_2 (0, 0)
	18 aload_0 (0, 0)
	19 getfield (0, 0)
	22 iconst_0 (0, 0)
	23 aload_2 (0, 0)
	24 iconst_0 (0, 0)
	25 aload_0 (0, 0)
	26 getfield (0, 0)
	29 arraylength (0, 0)
	30 invokestatic (0, 0)
	33 aload_2 (0, 0)
	34 aload_0 (0, 0)
	35 getfield (0, 0)
	38 arraylength (0, 0)
	39 aload_1 (0, 0)
	40 aastore (0, 0)
	41 new (0, 0)
	44 dup (0, 0)
	45 aload_0 (0, 0)
	46 getfield (0, 0)
	49 aload_2 (0, 0)
	50 iconst_0 (0, 0)
	51 invokespecial (0, 0)
	54 areturn (0, 0)

Method: getSubVector
	0 iload_2 (1, 1)
	1 ifge (1, 1)
	4 new (1, 1)
	7 dup (1, 1)
	8 getstatic (1, 1)
	11 iload_2 (1, 1)
	12 invokestatic (1, 1)
	15 invokespecial (1, 1)
	18 athrow (1, 1)
	19 new (0, 0)
	22 dup (0, 0)
	23 aload_0 (0, 0)
	24 getfield (0, 0)
	27 iload_2 (0, 0)
	28 invokespecial (0, 0)
	31 astore_3 (0, 0)
	32 aload_0 (0, 0)
	33 getfield (0, 0)
	36 iload_1 (0, 0)
	37 aload_3 (0, 0)
	38 getfield (0, 0)
	41 iconst_0 (0, 0)
	42 iload_2 (0, 0)
	43 invokestatic (0, 0)
	46 goto (0, 0)
	49 astore (0, 0)
	51 aload_0 (0, 0)
	52 iload_1 (0, 0)
	53 invokespecial (0, 0)
	56 aload_0 (0, 0)
	57 iload_1 (0, 0)
	58 iload_2 (0, 0)
	59 iadd (0, 0)
	60 iconst_1 (0, 0)
	61 isub (0, 0)
	62 invokespecial (0, 0)
	65 aload_3 (0, 0)
	66 areturn (0, 0)

Method: setEntry
	0 aload_0 (0, 0)
	1 getfield (0, 0)
	4 iload_1 (0, 0)
	5 aload_2 (0, 0)
	6 aastore (0, 0)
	7 goto (0, 0)
	10 astore_3 (0, 0)
	11 aload_0 (0, 0)
	12 iload_1 (0, 0)
	13 invokespecial (0, 0)
	16 return (0, 0)

Method: setSubVector
	0 aload_0 (0, 0)
	1 iload_1 (0, 0)
	2 aload_2 (0, 0)
	3 checkcast (0, 0)
	6 invokevirtual (0, 0)
	9 goto (0, 0)
	12 astore_3 (0, 0)
	13 iload_1 (1, 4)
	14 istore (1, 4)
	16 iload (1, 4)
	18 iload_1 (1, 4)
	19 aload_2 (1, 4)
	20 invokeinterface (1, 4)
	25 iadd (1, 4)
	26 if_icmpge (1, 4)
	29 aload_0 (1, 4)
	30 getfield (1, 4)
	33 iload (1, 4)
	35 aload_2 (1, 4)
	36 iload (1, 4)
	38 iload_1 (1, 4)
	39 isub (1, 4)
	40 invokeinterface (1, 4)
	45 aastore (1, 4)
	46 iinc (1, 4)
	49 goto (1, 4)
	52 goto (0, 0)
	55 astore_3 (0, 0)
	56 aload_0 (0, 0)
	57 iload_1 (0, 0)
	58 invokespecial (0, 0)
	61 aload_0 (0, 0)
	62 iload_1 (0, 0)
	63 aload_2 (0, 0)
	64 invokeinterface (0, 0)
	69 iadd (0, 0)
	70 iconst_1 (0, 0)
	71 isub (0, 0)
	72 invokespecial (0, 0)
	75 return (0, 0)

Method: set
	0 aload_0 (0, 0)
	1 getfield (0, 0)
	4 aload_1 (0, 0)
	5 invokestatic (0, 0)
	8 return (0, 0)

Method: toArray
	0 aload_0 (0, 0)
	1 getfield (0, 0)
	4 invokevirtual (0, 0)
	7 checkcast (0, 0)
	10 areturn (0, 0)

Method: checkVectorDimensions
	0 aload_0 (1, 1)
	1 getfield (1, 1)
	4 arraylength (1, 1)
	5 iload_1 (1, 1)
	6 if_icmpeq (1, 1)
	9 new (1, 1)
	12 dup (1, 1)
	13 aload_0 (1, 1)
	14 getfield (1, 1)
	17 arraylength (1, 1)
	18 iload_1 (1, 1)
	19 invokespecial (1, 1)
	22 athrow (1, 1)
	23 return (0, 0)

Method: walkInDefaultOrder
	0 aload_0 (0, 0)
	1 iload_2 (0, 0)
	2 iload_3 (0, 0)
	3 invokespecial (0, 0)
	6 aload_1 (0, 0)
	7 aload_0 (0, 0)
	8 invokevirtual (0, 0)
	11 iload_2 (0, 0)
	12 iload_3 (0, 0)
	13 invokeinterface (0, 0)
	18 iload_2 (1, 4)
	19 istore (1, 4)
	21 iload (1, 4)
	23 iload_3 (1, 4)
	24 if_icmpgt (1, 4)
	27 aload_0 (1, 4)
	28 iload (1, 4)
	30 aload_1 (1, 4)
	31 iload (1, 4)
	33 aload_0 (1, 4)
	34 iload (1, 4)
	36 invokevirtual (1, 4)
	39 invokeinterface (1, 4)
	44 invokevirtual (1, 4)
	47 iinc (1, 4)
	50 goto (1, 4)
	53 aload_1 (0, 0)
	54 invokeinterface (0, 0)
	59 areturn (0, 0)

Method: walkInOptimizedOrder
	0 aload_0 (0, 0)
	1 aload_1 (0, 0)
	2 iload_2 (0, 0)
	3 iload_3 (0, 0)
	4 invokevirtual (0, 0)
	7 areturn (0, 0)

Method: equals
	0 aload_0 (1, 1)
	1 aload_1 (1, 1)
	2 if_acmpne (1, 1)
	5 iconst_1 (1, 1)
	6 ireturn (1, 1)
	7 aload_1 (1, 1)
	8 ifnonnull (1, 1)
	11 iconst_0 (1, 1)
	12 ireturn (1, 1)
	13 aload_1 (0, 0)
	14 checkcast (0, 0)
	17 astore_2 (0, 0)
	18 aload_0 (1, 1)
	19 getfield (1, 1)
	22 arraylength (1, 1)
	23 aload_2 (1, 1)
	24 invokeinterface (1, 1)
	29 if_icmpeq (1, 1)
	32 iconst_0 (1, 1)
	33 ireturn (1, 1)
	34 iconst_0 (1, 4)
	35 istore_3 (1, 4)
	36 iload_3 (1, 4)
	37 aload_0 (1, 4)
	38 getfield (1, 4)
	41 arraylength (1, 4)
	42 if_icmpge (1, 4)
	45 aload_0 (2, 1)
	46 getfield (2, 1)
	49 iload_3 (2, 1)
	50 aaload (2, 1)
	51 aload_2 (2, 1)
	52 iload_3 (2, 1)
	53 invokeinterface (2, 1)
	58 invokevirtual (2, 1)
	61 ifne (2, 1)
	64 iconst_0 (2, 1)
	65 ireturn (2, 1)
	66 iinc (2, 1)
	69 goto (2, 1)
	72 iconst_1 (1, 4)
	73 ireturn (1, 4)
	74 astore_2 (1, 4)
	75 iconst_0 (1, 4)
	76 ireturn (1, 4)

Method: hashCode
	0 sipush (0, 0)
	3 istore_1 (0, 0)
	4 aload_0 (1, 4)
	5 getfield (1, 4)
	8 astore_2 (1, 4)
	9 aload_2 (1, 4)
	10 arraylength (1, 4)
	11 istore_3 (1, 4)
	12 iconst_0 (1, 4)
	13 istore (1, 4)
	15 iload (1, 4)
	17 iload_3 (1, 4)
	18 if_icmpge (1, 4)
	21 aload_2 (1, 4)
	22 iload (1, 4)
	24 aaload (1, 4)
	25 astore (1, 4)
	27 iload_1 (1, 4)
	28 aload (1, 4)
	30 invokevirtual (1, 4)
	33 ixor (1, 4)
	34 istore_1 (1, 4)
	35 iinc (1, 4)
	38 goto (1, 4)
	41 iload_1 (0, 0)
	42 ireturn (0, 0)

Method: checkIndex
	0 iload_1 (1, 1)
	1 iflt (1, 1)
	4 iload_1 (1, 1)
	5 aload_0 (1, 1)
	6 invokevirtual (1, 1)
	9 if_icmplt (1, 1)
	12 new (1, 1)
	15 dup (1, 1)
	16 getstatic (1, 1)
	19 iload_1 (1, 1)
	20 invokestatic (1, 1)
	23 iconst_0 (1, 1)
	24 invokestatic (1, 1)
	27 aload_0 (1, 1)
	28 invokevirtual (1, 1)
	31 iconst_1 (1, 1)
	32 isub (1, 1)
	33 invokestatic (1, 1)
	36 invokespecial (1, 1)
	39 athrow (1, 1)
	40 return (0, 0)

Method: checkIndices
	0 aload_0 (0, 0)
	1 invokevirtual (0, 0)
	4 istore_3 (0, 0)
	5 iload_1 (1, 1)
	6 iflt (1, 1)
	9 iload_1 (1, 1)
	10 iload_3 (1, 1)
	11 if_icmplt (1, 1)
	14 new (1, 1)
	17 dup (1, 1)
	18 getstatic (1, 1)
	21 iload_1 (1, 1)
	22 invokestatic (1, 1)
	25 iconst_0 (1, 1)
	26 invokestatic (1, 1)
	29 iload_3 (1, 1)
	30 iconst_1 (1, 1)
	31 isub (1, 1)
	32 invokestatic (1, 1)
	35 invokespecial (1, 1)
	38 athrow (1, 1)
	39 iload_2 (1, 1)
	40 iflt (1, 1)
	43 iload_2 (1, 1)
	44 iload_3 (1, 1)
	45 if_icmplt (1, 1)
	48 new (1, 1)
	51 dup (1, 1)
	52 getstatic (1, 1)
	55 iload_2 (1, 1)
	56 invokestatic (1, 1)
	59 iconst_0 (1, 1)
	60 invokestatic (1, 1)
	63 iload_3 (1, 1)
	64 iconst_1 (1, 1)
	65 isub (1, 1)
	66 invokestatic (1, 1)
	69 invokespecial (1, 1)
	72 athrow (1, 1)
	73 iload_2 (1, 1)
	74 iload_1 (1, 1)
	75 if_icmpge (1, 1)
	78 new (1, 1)
	81 dup (1, 1)
	82 getstatic (1, 1)
	85 iload_2 (1, 1)
	86 invokestatic (1, 1)
	89 iload_1 (1, 1)
	90 invokestatic (1, 1)
	93 iconst_0 (1, 1)
	94 invokespecial (1, 1)
	97 athrow (1, 1)
	98 return (0, 0)

