Method: <init>
	0 aload_0 (0, 0)
	1 invokespecial (0, 0)
	2 org/apache/commons/math3/linear/RealVector.<init>:()V (0, 0)
	4 aload_1 (0, 0)
	5 arraylength (0, 0)
	6 istore_3 (0, 0)
	7 aload_2 (0, 0)
	8 arraylength (0, 0)
	9 istore (0, 0)
	10 #4 (0, 0)
	11 aload_0 (0, 0)
	12 iload_3 (0, 0)
	13 iload (0, 0)
	14 #4 (0, 0)
	15 iadd (0, 0)
	16 newarray (0, 0)
	17 7 (0, 0)
	18 putfield (0, 0)
	19 org/apache/commons/math3/linear/ArrayRealVector.data:[D (0, 0)
	21 aload_1 (0, 0)
	22 iconst_0 (0, 0)
	23 aload_0 (0, 0)
	24 getfield (0, 0)
	25 org/apache/commons/math3/linear/ArrayRealVector.data:[D (0, 0)
	27 iconst_0 (0, 0)
	28 iload_3 (0, 0)
	29 invokestatic (0, 0)
	30 java/lang/System.arraycopy:(Ljava/lang/Object;ILjava/lang/Object;II)V (0, 0)
	32 aload_2 (0, 0)
	33 iconst_0 (0, 0)
	34 aload_0 (0, 0)
	35 getfield (0, 0)
	36 org/apache/commons/math3/linear/ArrayRealVector.data:[D (0, 0)
	38 iload_3 (0, 0)
	39 iload (0, 0)
	40 #4 (0, 0)
	41 invokestatic (0, 0)
	42 java/lang/System.arraycopy:(Ljava/lang/Object;ILjava/lang/Object;II)V (0, 0)
	44 return (0, 0)

Method: copy
	0 aload_0 (0, 0)
	1 invokevirtual (0, 0)
	2 org/apache/commons/math3/linear/ArrayRealVector.copy:()Lorg/apache/commons/math3/linear/ArrayRealVector; (0, 0)
	4 areturn (0, 0)

Method: add
	0 aload_0 (0, 0)
	1 aload_1 (0, 0)
	2 invokevirtual (0, 0)
	3 org/apache/commons/math3/linear/ArrayRealVector.add:(Lorg/apache/commons/math3/linear/RealVector;)Lorg/apache/commons/math3/linear/ArrayRealVector; (0, 0)
	5 areturn (0, 0)

Method: subtract
	0 aload_0 (0, 0)
	1 aload_1 (0, 0)
	2 invokevirtual (0, 0)
	3 org/apache/commons/math3/linear/ArrayRealVector.subtract:(Lorg/apache/commons/math3/linear/RealVector;)Lorg/apache/commons/math3/linear/ArrayRealVector; (0, 0)
	5 areturn (0, 0)

Method: map
	0 aload_0 (0, 0)
	1 aload_1 (0, 0)
	2 invokevirtual (0, 0)
	3 org/apache/commons/math3/linear/ArrayRealVector.map:(Lorg/apache/commons/math3/analysis/UnivariateFunction;)Lorg/apache/commons/math3/linear/ArrayRealVector; (0, 0)
	5 areturn (0, 0)

Method: mapToSelf
	0 aload_0 (0, 0)
	1 aload_1 (0, 0)
	2 invokevirtual (0, 0)
	3 org/apache/commons/math3/linear/ArrayRealVector.mapToSelf:(Lorg/apache/commons/math3/analysis/UnivariateFunction;)Lorg/apache/commons/math3/linear/ArrayRealVector; (0, 0)
	5 areturn (0, 0)

Method: mapAddToSelf
	0 iconst_0 (1, 4)
	1 istore_3 (1, 4)
	2 iload_3 (1, 4)
	3 aload_0 (1, 4)
	4 getfield (1, 4)
	5 org/apache/commons/math3/linear/ArrayRealVector.data:[D (1, 4)
	7 arraylength (1, 4)
	8 if_icmpge (1, 4)
	9 19 (1, 4)
	11 aload_0 (1, 4)
	12 getfield (1, 4)
	13 org/apache/commons/math3/linear/ArrayRealVector.data:[D (1, 4)
	15 iload_3 (1, 4)
	16 dup2 (1, 4)
	17 daload (1, 4)
	18 dload_1 (1, 4)
	19 dadd (1, 4)
	20 dastore (1, 4)
	21 iinc (1, 4)
	22 #3 (1, 4)
	23 -89 (1, 4)
	24 goto (1, 4)
	25 -22 (1, 4)
	27 aload_0 (0, 0)
	28 areturn (0, 0)

Method: mapSubtractToSelf
	0 iconst_0 (1, 4)
	1 istore_3 (1, 4)
	2 iload_3 (1, 4)
	3 aload_0 (1, 4)
	4 getfield (1, 4)
	5 org/apache/commons/math3/linear/ArrayRealVector.data:[D (1, 4)
	7 arraylength (1, 4)
	8 if_icmpge (1, 4)
	9 19 (1, 4)
	11 aload_0 (1, 4)
	12 getfield (1, 4)
	13 org/apache/commons/math3/linear/ArrayRealVector.data:[D (1, 4)
	15 iload_3 (1, 4)
	16 dup2 (1, 4)
	17 daload (1, 4)
	18 dload_1 (1, 4)
	19 dsub (1, 4)
	20 dastore (1, 4)
	21 iinc (1, 4)
	22 #3 (1, 4)
	23 -89 (1, 4)
	24 goto (1, 4)
	25 -22 (1, 4)
	27 aload_0 (0, 0)
	28 areturn (0, 0)

Method: mapMultiplyToSelf
	0 iconst_0 (1, 4)
	1 istore_3 (1, 4)
	2 iload_3 (1, 4)
	3 aload_0 (1, 4)
	4 getfield (1, 4)
	5 org/apache/commons/math3/linear/ArrayRealVector.data:[D (1, 4)
	7 arraylength (1, 4)
	8 if_icmpge (1, 4)
	9 19 (1, 4)
	11 aload_0 (1, 4)
	12 getfield (1, 4)
	13 org/apache/commons/math3/linear/ArrayRealVector.data:[D (1, 4)
	15 iload_3 (1, 4)
	16 dup2 (1, 4)
	17 daload (1, 4)
	18 dload_1 (1, 4)
	19 dmul (1, 4)
	20 dastore (1, 4)
	21 iinc (1, 4)
	22 #3 (1, 4)
	23 -89 (1, 4)
	24 goto (1, 4)
	25 -22 (1, 4)
	27 aload_0 (0, 0)
	28 areturn (0, 0)

Method: mapDivideToSelf
	0 iconst_0 (1, 4)
	1 istore_3 (1, 4)
	2 iload_3 (1, 4)
	3 aload_0 (1, 4)
	4 getfield (1, 4)
	5 org/apache/commons/math3/linear/ArrayRealVector.data:[D (1, 4)
	7 arraylength (1, 4)
	8 if_icmpge (1, 4)
	9 19 (1, 4)
	11 aload_0 (1, 4)
	12 getfield (1, 4)
	13 org/apache/commons/math3/linear/ArrayRealVector.data:[D (1, 4)
	15 iload_3 (1, 4)
	16 dup2 (1, 4)
	17 daload (1, 4)
	18 dload_1 (1, 4)
	19 ddiv (1, 4)
	20 dastore (1, 4)
	21 iinc (1, 4)
	22 #3 (1, 4)
	23 -89 (1, 4)
	24 goto (1, 4)
	25 -22 (1, 4)
	27 aload_0 (0, 0)
	28 areturn (0, 0)

Method: ebeMultiply
	0 aload_0 (0, 0)
	1 aload_1 (0, 0)
	2 invokevirtual (0, 0)
	3 org/apache/commons/math3/linear/ArrayRealVector.ebeMultiply:(Lorg/apache/commons/math3/linear/RealVector;)Lorg/apache/commons/math3/linear/ArrayRealVector; (0, 0)
	5 areturn (0, 0)

Method: ebeDivide
	0 aload_0 (0, 0)
	1 aload_1 (0, 0)
	2 invokevirtual (0, 0)
	3 org/apache/commons/math3/linear/ArrayRealVector.ebeDivide:(Lorg/apache/commons/math3/linear/RealVector;)Lorg/apache/commons/math3/linear/ArrayRealVector; (0, 0)
	5 areturn (0, 0)

Method: getDataRef
	0 aload_0 (0, 0)
	1 getfield (0, 0)
	2 org/apache/commons/math3/linear/ArrayRealVector.data:[D (0, 0)
	4 areturn (0, 0)

Method: dotProduct
	0 aload_1 (1, 1)
	1 instanceof (1, 1)
	2 org/apache/commons/math3/linear/ArrayRealVector (1, 1)
	4 ifeq (1, 1)
	5 55 (1, 1)
	7 aload_1 (1, 1)
	8 checkcast (1, 1)
	9 org/apache/commons/math3/linear/ArrayRealVector (1, 1)
	11 getfield (1, 1)
	12 org/apache/commons/math3/linear/ArrayRealVector.data:[D (1, 1)
	14 astore_2 (1, 1)
	15 aload_0 (1, 1)
	16 aload_2 (1, 1)
	17 arraylength (1, 1)
	18 invokevirtual (1, 1)
	19 org/apache/commons/math3/linear/ArrayRealVector.checkVectorDimensions:(I)V (1, 1)
	21 dconst_0 (1, 1)
	22 dstore_3 (1, 1)
	23 iconst_0 (2, 4)
	24 istore (2, 4)
	25 #5 (2, 4)
	26 iload (2, 4)
	27 #5 (2, 4)
	28 aload_0 (2, 4)
	29 getfield (2, 4)
	30 org/apache/commons/math3/linear/ArrayRealVector.data:[D (2, 4)
	32 arraylength (2, 4)
	33 if_icmpge (2, 4)
	34 24 (2, 4)
	36 dload_3 (2, 4)
	37 aload_0 (2, 4)
	38 getfield (2, 4)
	39 org/apache/commons/math3/linear/ArrayRealVector.data:[D (2, 4)
	41 iload (2, 4)
	42 #5 (2, 4)
	43 daload (2, 4)
	44 aload_2 (2, 4)
	45 iload (2, 4)
	46 #5 (2, 4)
	47 daload (2, 4)
	48 dmul (2, 4)
	49 dadd (2, 4)
	50 dstore_3 (2, 4)
	51 iinc (2, 4)
	52 #5 (2, 4)
	53 -89 (2, 4)
	54 goto (2, 4)
	55 -28 (2, 4)
	57 dload_3 (1, 1)
	58 dreturn (1, 1)
	59 aload_0 (0, 0)
	60 aload_1 (0, 0)
	61 invokespecial (0, 0)
	62 org/apache/commons/math3/linear/RealVector.dotProduct:(Lorg/apache/commons/math3/linear/RealVector;)D (0, 0)
	64 dreturn (0, 0)

Method: getNorm
	0 dconst_0 (0, 0)
	1 dstore_1 (0, 0)
	2 aload_0 (1, 4)
	3 getfield (1, 4)
	4 org/apache/commons/math3/linear/ArrayRealVector.data:[D (1, 4)
	6 astore_3 (1, 4)
	7 aload_3 (1, 4)
	8 arraylength (1, 4)
	9 istore (1, 4)
	10 #4 (1, 4)
	11 iconst_0 (1, 4)
	12 istore (1, 4)
	13 #5 (1, 4)
	14 iload (1, 4)
	15 #5 (1, 4)
	16 iload (1, 4)
	17 #4 (1, 4)
	18 if_icmpge (1, 4)
	19 23 (1, 4)
	21 aload_3 (1, 4)
	22 iload (1, 4)
	23 #5 (1, 4)
	24 daload (1, 4)
	25 dstore (1, 4)
	26 #6 (1, 4)
	27 dload_1 (1, 4)
	28 dload (1, 4)
	29 #6 (1, 4)
	30 dload (1, 4)
	31 #6 (1, 4)
	32 dmul (1, 4)
	33 dadd (1, 4)
	34 dstore_1 (1, 4)
	35 iinc (1, 4)
	36 #5 (1, 4)
	37 -89 (1, 4)
	38 goto (1, 4)
	39 -24 (1, 4)
	41 dload_1 (0, 0)
	42 invokestatic (0, 0)
	43 org/apache/commons/math3/util/FastMath.sqrt:(D)D (0, 0)
	45 dreturn (0, 0)

Method: getL1Norm
	0 dconst_0 (0, 0)
	1 dstore_1 (0, 0)
	2 aload_0 (1, 4)
	3 getfield (1, 4)
	4 org/apache/commons/math3/linear/ArrayRealVector.data:[D (1, 4)
	6 astore_3 (1, 4)
	7 aload_3 (1, 4)
	8 arraylength (1, 4)
	9 istore (1, 4)
	10 #4 (1, 4)
	11 iconst_0 (1, 4)
	12 istore (1, 4)
	13 #5 (1, 4)
	14 iload (1, 4)
	15 #5 (1, 4)
	16 iload (1, 4)
	17 #4 (1, 4)
	18 if_icmpge (1, 4)
	19 23 (1, 4)
	21 aload_3 (1, 4)
	22 iload (1, 4)
	23 #5 (1, 4)
	24 daload (1, 4)
	25 dstore (1, 4)
	26 #6 (1, 4)
	27 dload_1 (1, 4)
	28 dload (1, 4)
	29 #6 (1, 4)
	30 invokestatic (1, 4)
	31 org/apache/commons/math3/util/FastMath.abs:(D)D (1, 4)
	33 dadd (1, 4)
	34 dstore_1 (1, 4)
	35 iinc (1, 4)
	36 #5 (1, 4)
	37 -89 (1, 4)
	38 goto (1, 4)
	39 -24 (1, 4)
	41 dload_1 (0, 0)
	42 dreturn (0, 0)

Method: getLInfNorm
	0 dconst_0 (0, 0)
	1 dstore_1 (0, 0)
	2 aload_0 (1, 4)
	3 getfield (1, 4)
	4 org/apache/commons/math3/linear/ArrayRealVector.data:[D (1, 4)
	6 astore_3 (1, 4)
	7 aload_3 (1, 4)
	8 arraylength (1, 4)
	9 istore (1, 4)
	10 #4 (1, 4)
	11 iconst_0 (1, 4)
	12 istore (1, 4)
	13 #5 (1, 4)
	14 iload (1, 4)
	15 #5 (1, 4)
	16 iload (1, 4)
	17 #4 (1, 4)
	18 if_icmpge (1, 4)
	19 25 (1, 4)
	21 aload_3 (1, 4)
	22 iload (1, 4)
	23 #5 (1, 4)
	24 daload (1, 4)
	25 dstore (1, 4)
	26 #6 (1, 4)
	27 dload_1 (1, 4)
	28 dload (1, 4)
	29 #6 (1, 4)
	30 invokestatic (1, 4)
	31 org/apache/commons/math3/util/FastMath.abs:(D)D (1, 4)
	33 invokestatic (1, 4)
	34 org/apache/commons/math3/util/FastMath.max:(DD)D (1, 4)
	36 dstore_1 (1, 4)
	37 iinc (1, 4)
	38 #5 (1, 4)
	39 -89 (1, 4)
	40 goto (1, 4)
	41 -26 (1, 4)
	43 dload_1 (0, 0)
	44 dreturn (0, 0)

Method: getDistance
	0 aload_1 (1, 1)
	1 instanceof (1, 1)
	2 org/apache/commons/math3/linear/ArrayRealVector (1, 1)
	4 ifeq (1, 1)
	5 65 (1, 1)
	7 aload_1 (1, 1)
	8 checkcast (1, 1)
	9 org/apache/commons/math3/linear/ArrayRealVector (1, 1)
	11 getfield (1, 1)
	12 org/apache/commons/math3/linear/ArrayRealVector.data:[D (1, 1)
	14 astore_2 (1, 1)
	15 aload_0 (1, 1)
	16 aload_2 (1, 1)
	17 arraylength (1, 1)
	18 invokevirtual (1, 1)
	19 org/apache/commons/math3/linear/ArrayRealVector.checkVectorDimensions:(I)V (1, 1)
	21 dconst_0 (1, 1)
	22 dstore_3 (1, 1)
	23 iconst_0 (2, 4)
	24 istore (2, 4)
	25 #5 (2, 4)
	26 iload (2, 4)
	27 #5 (2, 4)
	28 aload_0 (2, 4)
	29 getfield (2, 4)
	30 org/apache/commons/math3/linear/ArrayRealVector.data:[D (2, 4)
	32 arraylength (2, 4)
	33 if_icmpge (2, 4)
	34 31 (2, 4)
	36 aload_0 (2, 4)
	37 getfield (2, 4)
	38 org/apache/commons/math3/linear/ArrayRealVector.data:[D (2, 4)
	40 iload (2, 4)
	41 #5 (2, 4)
	42 daload (2, 4)
	43 aload_2 (2, 4)
	44 iload (2, 4)
	45 #5 (2, 4)
	46 daload (2, 4)
	47 dsub (2, 4)
	48 dstore (2, 4)
	49 #6 (2, 4)
	50 dload_3 (2, 4)
	51 dload (2, 4)
	52 #6 (2, 4)
	53 dload (2, 4)
	54 #6 (2, 4)
	55 dmul (2, 4)
	56 dadd (2, 4)
	57 dstore_3 (2, 4)
	58 iinc (2, 4)
	59 #5 (2, 4)
	60 -89 (2, 4)
	61 goto (2, 4)
	62 -35 (2, 4)
	64 dload_3 (1, 1)
	65 invokestatic (1, 1)
	66 org/apache/commons/math3/util/FastMath.sqrt:(D)D (1, 1)
	68 dreturn (1, 1)
	69 aload_0 (1, 2)
	70 aload_1 (1, 2)
	71 invokevirtual (1, 2)
	72 org/apache/commons/math3/linear/ArrayRealVector.checkVectorDimensions:(Lorg/apache/commons/math3/linear/RealVector;)V (1, 2)
	74 dconst_0 (1, 2)
	75 dstore_2 (1, 2)
	76 iconst_0 (2, 4)
	77 istore (2, 4)
	78 #4 (2, 4)
	79 iload (2, 4)
	80 #4 (2, 4)
	81 aload_0 (2, 4)
	82 getfield (2, 4)
	83 org/apache/commons/math3/linear/ArrayRealVector.data:[D (2, 4)
	85 arraylength (2, 4)
	86 if_icmpge (2, 4)
	87 33 (2, 4)
	89 aload_0 (2, 4)
	90 getfield (2, 4)
	91 org/apache/commons/math3/linear/ArrayRealVector.data:[D (2, 4)
	93 iload (2, 4)
	94 #4 (2, 4)
	95 daload (2, 4)
	96 aload_1 (2, 4)
	97 iload (2, 4)
	98 #4 (2, 4)
	99 invokevirtual (2, 4)
	100 org/apache/commons/math3/linear/RealVector.getEntry:(I)D (2, 4)
	102 dsub (2, 4)
	103 dstore (2, 4)
	104 #5 (2, 4)
	105 dload_2 (2, 4)
	106 dload (2, 4)
	107 #5 (2, 4)
	108 dload (2, 4)
	109 #5 (2, 4)
	110 dmul (2, 4)
	111 dadd (2, 4)
	112 dstore_2 (2, 4)
	113 iinc (2, 4)
	114 #4 (2, 4)
	115 -89 (2, 4)
	116 goto (2, 4)
	117 -37 (2, 4)
	119 dload_2 (1, 2)
	120 invokestatic (1, 2)
	121 org/apache/commons/math3/util/FastMath.sqrt:(D)D (1, 2)
	123 dreturn (1, 2)

Method: getL1Distance
	0 aload_1 (1, 1)
	1 instanceof (1, 1)
	2 org/apache/commons/math3/linear/ArrayRealVector (1, 1)
	4 ifeq (1, 1)
	5 62 (1, 1)
	7 aload_1 (1, 1)
	8 checkcast (1, 1)
	9 org/apache/commons/math3/linear/ArrayRealVector (1, 1)
	11 getfield (1, 1)
	12 org/apache/commons/math3/linear/ArrayRealVector.data:[D (1, 1)
	14 astore_2 (1, 1)
	15 aload_0 (1, 1)
	16 aload_2 (1, 1)
	17 arraylength (1, 1)
	18 invokevirtual (1, 1)
	19 org/apache/commons/math3/linear/ArrayRealVector.checkVectorDimensions:(I)V (1, 1)
	21 dconst_0 (1, 1)
	22 dstore_3 (1, 1)
	23 iconst_0 (2, 4)
	24 istore (2, 4)
	25 #5 (2, 4)
	26 iload (2, 4)
	27 #5 (2, 4)
	28 aload_0 (2, 4)
	29 getfield (2, 4)
	30 org/apache/commons/math3/linear/ArrayRealVector.data:[D (2, 4)
	32 arraylength (2, 4)
	33 if_icmpge (2, 4)
	34 31 (2, 4)
	36 aload_0 (2, 4)
	37 getfield (2, 4)
	38 org/apache/commons/math3/linear/ArrayRealVector.data:[D (2, 4)
	40 iload (2, 4)
	41 #5 (2, 4)
	42 daload (2, 4)
	43 aload_2 (2, 4)
	44 iload (2, 4)
	45 #5 (2, 4)
	46 daload (2, 4)
	47 dsub (2, 4)
	48 dstore (2, 4)
	49 #6 (2, 4)
	50 dload_3 (2, 4)
	51 dload (2, 4)
	52 #6 (2, 4)
	53 invokestatic (2, 4)
	54 org/apache/commons/math3/util/FastMath.abs:(D)D (2, 4)
	56 dadd (2, 4)
	57 dstore_3 (2, 4)
	58 iinc (2, 4)
	59 #5 (2, 4)
	60 -89 (2, 4)
	61 goto (2, 4)
	62 -35 (2, 4)
	64 dload_3 (1, 1)
	65 dreturn (1, 1)
	66 aload_0 (1, 2)
	67 aload_1 (1, 2)
	68 invokevirtual (1, 2)
	69 org/apache/commons/math3/linear/ArrayRealVector.checkVectorDimensions:(Lorg/apache/commons/math3/linear/RealVector;)V (1, 2)
	71 dconst_0 (1, 2)
	72 dstore_2 (1, 2)
	73 iconst_0 (2, 4)
	74 istore (2, 4)
	75 #4 (2, 4)
	76 iload (2, 4)
	77 #4 (2, 4)
	78 aload_0 (2, 4)
	79 getfield (2, 4)
	80 org/apache/commons/math3/linear/ArrayRealVector.data:[D (2, 4)
	82 arraylength (2, 4)
	83 if_icmpge (2, 4)
	84 33 (2, 4)
	86 aload_0 (2, 4)
	87 getfield (2, 4)
	88 org/apache/commons/math3/linear/ArrayRealVector.data:[D (2, 4)
	90 iload (2, 4)
	91 #4 (2, 4)
	92 daload (2, 4)
	93 aload_1 (2, 4)
	94 iload (2, 4)
	95 #4 (2, 4)
	96 invokevirtual (2, 4)
	97 org/apache/commons/math3/linear/RealVector.getEntry:(I)D (2, 4)
	99 dsub (2, 4)
	100 dstore (2, 4)
	101 #5 (2, 4)
	102 dload_2 (2, 4)
	103 dload (2, 4)
	104 #5 (2, 4)
	105 invokestatic (2, 4)
	106 org/apache/commons/math3/util/FastMath.abs:(D)D (2, 4)
	108 dadd (2, 4)
	109 dstore_2 (2, 4)
	110 iinc (2, 4)
	111 #4 (2, 4)
	112 -89 (2, 4)
	113 goto (2, 4)
	114 -37 (2, 4)
	116 dload_2 (1, 2)
	117 dreturn (1, 2)

Method: getLInfDistance
	0 aload_1 (1, 1)
	1 instanceof (1, 1)
	2 org/apache/commons/math3/linear/ArrayRealVector (1, 1)
	4 ifeq (1, 1)
	5 64 (1, 1)
	7 aload_1 (1, 1)
	8 checkcast (1, 1)
	9 org/apache/commons/math3/linear/ArrayRealVector (1, 1)
	11 getfield (1, 1)
	12 org/apache/commons/math3/linear/ArrayRealVector.data:[D (1, 1)
	14 astore_2 (1, 1)
	15 aload_0 (1, 1)
	16 aload_2 (1, 1)
	17 arraylength (1, 1)
	18 invokevirtual (1, 1)
	19 org/apache/commons/math3/linear/ArrayRealVector.checkVectorDimensions:(I)V (1, 1)
	21 dconst_0 (1, 1)
	22 dstore_3 (1, 1)
	23 iconst_0 (2, 4)
	24 istore (2, 4)
	25 #5 (2, 4)
	26 iload (2, 4)
	27 #5 (2, 4)
	28 aload_0 (2, 4)
	29 getfield (2, 4)
	30 org/apache/commons/math3/linear/ArrayRealVector.data:[D (2, 4)
	32 arraylength (2, 4)
	33 if_icmpge (2, 4)
	34 33 (2, 4)
	36 aload_0 (2, 4)
	37 getfield (2, 4)
	38 org/apache/commons/math3/linear/ArrayRealVector.data:[D (2, 4)
	40 iload (2, 4)
	41 #5 (2, 4)
	42 daload (2, 4)
	43 aload_2 (2, 4)
	44 iload (2, 4)
	45 #5 (2, 4)
	46 daload (2, 4)
	47 dsub (2, 4)
	48 dstore (2, 4)
	49 #6 (2, 4)
	50 dload_3 (2, 4)
	51 dload (2, 4)
	52 #6 (2, 4)
	53 invokestatic (2, 4)
	54 org/apache/commons/math3/util/FastMath.abs:(D)D (2, 4)
	56 invokestatic (2, 4)
	57 org/apache/commons/math3/util/FastMath.max:(DD)D (2, 4)
	59 dstore_3 (2, 4)
	60 iinc (2, 4)
	61 #5 (2, 4)
	62 -89 (2, 4)
	63 goto (2, 4)
	64 -37 (2, 4)
	66 dload_3 (1, 1)
	67 dreturn (1, 1)
	68 aload_0 (1, 2)
	69 aload_1 (1, 2)
	70 invokevirtual (1, 2)
	71 org/apache/commons/math3/linear/ArrayRealVector.checkVectorDimensions:(Lorg/apache/commons/math3/linear/RealVector;)V (1, 2)
	73 dconst_0 (1, 2)
	74 dstore_2 (1, 2)
	75 iconst_0 (2, 4)
	76 istore (2, 4)
	77 #4 (2, 4)
	78 iload (2, 4)
	79 #4 (2, 4)
	80 aload_0 (2, 4)
	81 getfield (2, 4)
	82 org/apache/commons/math3/linear/ArrayRealVector.data:[D (2, 4)
	84 arraylength (2, 4)
	85 if_icmpge (2, 4)
	86 35 (2, 4)
	88 aload_0 (2, 4)
	89 getfield (2, 4)
	90 org/apache/commons/math3/linear/ArrayRealVector.data:[D (2, 4)
	92 iload (2, 4)
	93 #4 (2, 4)
	94 daload (2, 4)
	95 aload_1 (2, 4)
	96 iload (2, 4)
	97 #4 (2, 4)
	98 invokevirtual (2, 4)
	99 org/apache/commons/math3/linear/RealVector.getEntry:(I)D (2, 4)
	101 dsub (2, 4)
	102 dstore (2, 4)
	103 #5 (2, 4)
	104 dload_2 (2, 4)
	105 dload (2, 4)
	106 #5 (2, 4)
	107 invokestatic (2, 4)
	108 org/apache/commons/math3/util/FastMath.abs:(D)D (2, 4)
	110 invokestatic (2, 4)
	111 org/apache/commons/math3/util/FastMath.max:(DD)D (2, 4)
	113 dstore_2 (2, 4)
	114 iinc (2, 4)
	115 #4 (2, 4)
	116 -89 (2, 4)
	117 goto (2, 4)
	118 -39 (2, 4)
	120 dload_2 (1, 2)
	121 dreturn (1, 2)

Method: outerProduct
	0 aload_1 (1, 1)
	1 instanceof (1, 1)
	2 org/apache/commons/math3/linear/ArrayRealVector (1, 1)
	4 ifeq (1, 1)
	5 86 (1, 1)
	7 aload_1 (1, 1)
	8 checkcast (1, 1)
	9 org/apache/commons/math3/linear/ArrayRealVector (1, 1)
	11 getfield (1, 1)
	12 org/apache/commons/math3/linear/ArrayRealVector.data:[D (1, 1)
	14 astore_2 (1, 1)
	15 aload_0 (1, 1)
	16 getfield (1, 1)
	17 org/apache/commons/math3/linear/ArrayRealVector.data:[D (1, 1)
	19 arraylength (1, 1)
	20 istore_3 (1, 1)
	21 aload_2 (1, 1)
	22 arraylength (1, 1)
	23 istore (1, 1)
	24 #4 (1, 1)
	25 iload_3 (1, 1)
	26 iload (1, 1)
	27 #4 (1, 1)
	28 invokestatic (1, 1)
	29 org/apache/commons/math3/linear/MatrixUtils.createRealMatrix:(II)Lorg/apache/commons/math3/linear/RealMatrix; (1, 1)
	31 astore (1, 1)
	32 #5 (1, 1)
	33 iconst_0 (2, 4)
	34 istore (2, 4)
	35 #6 (2, 4)
	36 iload (2, 4)
	37 #6 (2, 4)
	38 iload_3 (2, 4)
	39 if_icmpge (2, 4)
	40 48 (2, 4)
	42 iconst_0 (3, 4)
	43 istore (3, 4)
	44 #7 (3, 4)
	45 iload (3, 4)
	46 #7 (3, 4)
	47 iload (3, 4)
	48 #4 (3, 4)
	49 if_icmpge (3, 4)
	50 32 (3, 4)
	52 aload (3, 4)
	53 #5 (3, 4)
	54 iload (3, 4)
	55 #6 (3, 4)
	56 iload (3, 4)
	57 #7 (3, 4)
	58 aload_0 (3, 4)
	59 getfield (3, 4)
	60 org/apache/commons/math3/linear/ArrayRealVector.data:[D (3, 4)
	62 iload (3, 4)
	63 #6 (3, 4)
	64 daload (3, 4)
	65 aload_2 (3, 4)
	66 iload (3, 4)
	67 #7 (3, 4)
	68 daload (3, 4)
	69 dmul (3, 4)
	70 invokeinterface (3, 4)
	71 org/apache/commons/math3/linear/RealMatrix.java/lang/IndexOutOfBoundsException (3, 4)
	73 0 (3, 4)
	75 iinc (3, 4)
	76 #7 (3, 4)
	77 -89 (3, 4)
	78 goto (3, 4)
	79 -33 (3, 4)
	81 iinc (3, 4)
	82 #6 (3, 4)
	83 -89 (3, 4)
	84 goto (3, 4)
	85 -48 (3, 4)
	87 aload (2, 4)
	88 #5 (2, 4)
	89 areturn (2, 4)
	90 aload_0 (2, 2)
	91 getfield (2, 2)
	92 org/apache/commons/math3/linear/ArrayRealVector.data:[D (2, 2)
	94 arraylength (2, 2)
	95 istore_2 (2, 2)
	96 aload_1 (2, 2)
	97 invokevirtual (2, 2)
	98 org/apache/commons/math3/linear/RealVector.getDimension:()I (2, 2)
	100 istore_3 (2, 2)
	101 iload_2 (2, 2)
	102 iload_3 (2, 2)
	103 invokestatic (2, 2)
	104 org/apache/commons/math3/linear/MatrixUtils.createRealMatrix:(II)Lorg/apache/commons/math3/linear/RealMatrix; (2, 2)
	106 astore (2, 2)
	107 #4 (2, 2)
	108 iconst_0 (3, 4)
	109 istore (3, 4)
	110 #5 (3, 4)
	111 iload (3, 4)
	112 #5 (3, 4)
	113 iload_2 (3, 4)
	114 if_icmpge (3, 4)
	115 49 (3, 4)
	117 iconst_0 (4, 4)
	118 istore (4, 4)
	119 #6 (4, 4)
	120 iload (4, 4)
	121 #6 (4, 4)
	122 iload_3 (4, 4)
	123 if_icmpge (4, 4)
	124 34 (4, 4)
	126 aload (4, 4)
	127 #4 (4, 4)
	128 iload (4, 4)
	129 #5 (4, 4)
	130 iload (4, 4)
	131 #6 (4, 4)
	132 aload_0 (4, 4)
	133 getfield (4, 4)
	134 org/apache/commons/math3/linear/ArrayRealVector.data:[D (4, 4)
	136 iload (4, 4)
	137 #5 (4, 4)
	138 daload (4, 4)
	139 aload_1 (4, 4)
	140 iload (4, 4)
	141 #6 (4, 4)
	142 invokevirtual (4, 4)
	143 org/apache/commons/math3/linear/RealVector.getEntry:(I)D (4, 4)
	145 dmul (4, 4)
	146 invokeinterface (4, 4)
	147 org/apache/commons/math3/linear/RealMatrix.java/lang/IndexOutOfBoundsException (4, 4)
	149 0 (4, 4)
	151 iinc (4, 4)
	152 #6 (4, 4)
	153 -89 (4, 4)
	154 goto (4, 4)
	155 -34 (4, 4)
	157 iinc (4, 4)
	158 #5 (4, 4)
	159 -89 (4, 4)
	160 goto (4, 4)
	161 -49 (4, 4)
	163 aload (3, 4)
	164 #4 (3, 4)
	165 areturn (3, 4)

Method: getEntry
	0 aload_0 (0, 0)
	1 getfield (0, 0)
	2 org/apache/commons/math3/linear/ArrayRealVector.data:[D (0, 0)
	4 iload_1 (0, 0)
	5 daload (0, 0)
	6 dreturn (0, 0)
	7 astore_2 (0, 0)
	8 new (0, 0)
	9 org/apache/commons/math3/exception/OutOfRangeException (0, 0)
	11 dup (0, 0)
	12 getstatic (0, 0)
	13 org/apache/commons/math3/exception/util/LocalizedFormats.INDEX:Lorg/apache/commons/math3/exception/util/LocalizedFormats; (0, 0)
	15 iload_1 (0, 0)
	16 invokestatic (0, 0)
	17 java/lang/Integer.valueOf:(I)Ljava/lang/Integer; (0, 0)
	19 iconst_0 (0, 0)
	20 invokestatic (0, 0)
	21 java/lang/Integer.valueOf:(I)Ljava/lang/Integer; (0, 0)
	23 aload_0 (0, 0)
	24 invokevirtual (0, 0)
	25 org/apache/commons/math3/linear/ArrayRealVector.getDimension:()I (0, 0)
	27 iconst_1 (0, 0)
	28 isub (0, 0)
	29 invokestatic (0, 0)
	30 java/lang/Integer.valueOf:(I)Ljava/lang/Integer; (0, 0)
	32 invokespecial (0, 0)
	33 org/apache/commons/math3/exception/OutOfRangeException.<init>:(Lorg/apache/commons/math3/exception/util/Localizable;Ljava/lang/Number;Ljava/lang/Number;Ljava/lang/Number;)V (0, 0)
	35 athrow (0, 0)

Method: getDimension
	0 aload_0 (0, 0)
	1 getfield (0, 0)
	2 org/apache/commons/math3/linear/ArrayRealVector.data:[D (0, 0)
	4 arraylength (0, 0)
	5 ireturn (0, 0)

Method: append
	0 aload_0 (0, 0)
	1 getfield (0, 0)
	2 org/apache/commons/math3/linear/ArrayRealVector.data:[D (0, 0)
	4 arraylength (0, 0)
	5 iconst_1 (0, 0)
	6 iadd (0, 0)
	7 newarray (0, 0)
	8 7 (0, 0)
	9 astore_3 (0, 0)
	10 aload_0 (0, 0)
	11 getfield (0, 0)
	12 org/apache/commons/math3/linear/ArrayRealVector.data:[D (0, 0)
	14 iconst_0 (0, 0)
	15 aload_3 (0, 0)
	16 iconst_0 (0, 0)
	17 aload_0 (0, 0)
	18 getfield (0, 0)
	19 org/apache/commons/math3/linear/ArrayRealVector.data:[D (0, 0)
	21 arraylength (0, 0)
	22 invokestatic (0, 0)
	23 java/lang/System.arraycopy:(Ljava/lang/Object;ILjava/lang/Object;II)V (0, 0)
	25 aload_3 (0, 0)
	26 aload_0 (0, 0)
	27 getfield (0, 0)
	28 org/apache/commons/math3/linear/ArrayRealVector.data:[D (0, 0)
	30 arraylength (0, 0)
	31 dload_1 (0, 0)
	32 dastore (0, 0)
	33 new (0, 0)
	34 org/apache/commons/math3/linear/ArrayRealVector (0, 0)
	36 dup (0, 0)
	37 aload_3 (0, 0)
	38 iconst_0 (0, 0)
	39 invokespecial (0, 0)
	40 org/apache/commons/math3/linear/ArrayRealVector.<init>:([DZ)V (0, 0)
	42 areturn (0, 0)

Method: getSubVector
	0 iload_2 (1, 1)
	1 ifge (1, 1)
	2 18 (1, 1)
	4 new (1, 1)
	5 org/apache/commons/math3/exception/NotPositiveException (1, 1)
	7 dup (1, 1)
	8 getstatic (1, 1)
	9 org/apache/commons/math3/exception/util/LocalizedFormats.NUMBER_OF_ELEMENTS_SHOULD_BE_POSITIVE:Lorg/apache/commons/math3/exception/util/LocalizedFormats; (1, 1)
	11 iload_2 (1, 1)
	12 invokestatic (1, 1)
	13 java/lang/Integer.valueOf:(I)Ljava/lang/Integer; (1, 1)
	15 invokespecial (1, 1)
	16 org/apache/commons/math3/exception/NotPositiveException.<init>:(Lorg/apache/commons/math3/exception/util/Localizable;Ljava/lang/Number;)V (1, 1)
	18 athrow (1, 1)
	19 new (0, 0)
	20 org/apache/commons/math3/linear/ArrayRealVector (0, 0)
	22 dup (0, 0)
	23 iload_2 (0, 0)
	24 invokespecial (0, 0)
	25 org/apache/commons/math3/linear/ArrayRealVector.<init>:(I)V (0, 0)
	27 astore_3 (0, 0)
	28 aload_0 (0, 0)
	29 getfield (0, 0)
	30 org/apache/commons/math3/linear/ArrayRealVector.data:[D (0, 0)
	32 iload_1 (0, 0)
	33 aload_3 (0, 0)
	34 getfield (0, 0)
	35 org/apache/commons/math3/linear/ArrayRealVector.data:[D (0, 0)
	37 iconst_0 (0, 0)
	38 iload_2 (0, 0)
	39 invokestatic (0, 0)
	40 java/lang/System.arraycopy:(Ljava/lang/Object;ILjava/lang/Object;II)V (0, 0)
	42 goto (0, 0)
	43 19 (0, 0)
	45 astore (0, 0)
	46 #4 (0, 0)
	47 aload_0 (0, 0)
	48 iload_1 (0, 0)
	49 invokevirtual (0, 0)
	50 org/apache/commons/math3/linear/ArrayRealVector.checkIndex:(I)V (0, 0)
	52 aload_0 (0, 0)
	53 iload_1 (0, 0)
	54 iload_2 (0, 0)
	55 iadd (0, 0)
	56 iconst_1 (0, 0)
	57 isub (0, 0)
	58 invokevirtual (0, 0)
	59 org/apache/commons/math3/linear/ArrayRealVector.checkIndex:(I)V (0, 0)
	61 aload_3 (0, 0)
	62 areturn (0, 0)

Method: setEntry
	0 aload_0 (0, 0)
	1 getfield (0, 0)
	2 org/apache/commons/math3/linear/ArrayRealVector.data:[D (0, 0)
	4 iload_1 (0, 0)
	5 dload_2 (0, 0)
	6 dastore (0, 0)
	7 goto (0, 0)
	8 10 (0, 0)
	10 astore (0, 0)
	11 #4 (0, 0)
	12 aload_0 (0, 0)
	13 iload_1 (0, 0)
	14 invokevirtual (0, 0)
	15 org/apache/commons/math3/linear/ArrayRealVector.checkIndex:(I)V (0, 0)
	17 return (0, 0)

Method: addToEntry
	0 aload_0 (0, 0)
	1 getfield (0, 0)
	2 org/apache/commons/math3/linear/ArrayRealVector.data:[D (0, 0)
	4 iload_1 (0, 0)
	5 dup2 (0, 0)
	6 daload (0, 0)
	7 dload_2 (0, 0)
	8 dadd (0, 0)
	9 dastore (0, 0)
	10 goto (0, 0)
	11 34 (0, 0)
	13 astore (0, 0)
	14 #4 (0, 0)
	15 new (0, 0)
	16 org/apache/commons/math3/exception/OutOfRangeException (0, 0)
	18 dup (0, 0)
	19 getstatic (0, 0)
	20 org/apache/commons/math3/exception/util/LocalizedFormats.INDEX:Lorg/apache/commons/math3/exception/util/LocalizedFormats; (0, 0)
	22 iload_1 (0, 0)
	23 invokestatic (0, 0)
	24 java/lang/Integer.valueOf:(I)Ljava/lang/Integer; (0, 0)
	26 iconst_0 (0, 0)
	27 invokestatic (0, 0)
	28 java/lang/Integer.valueOf:(I)Ljava/lang/Integer; (0, 0)
	30 aload_0 (0, 0)
	31 getfield (0, 0)
	32 org/apache/commons/math3/linear/ArrayRealVector.data:[D (0, 0)
	34 arraylength (0, 0)
	35 iconst_1 (0, 0)
	36 isub (0, 0)
	37 invokestatic (0, 0)
	38 java/lang/Integer.valueOf:(I)Ljava/lang/Integer; (0, 0)
	40 invokespecial (0, 0)
	41 org/apache/commons/math3/exception/OutOfRangeException.<init>:(Lorg/apache/commons/math3/exception/util/Localizable;Ljava/lang/Number;Ljava/lang/Number;Ljava/lang/Number;)V (0, 0)
	43 athrow (0, 0)
	44 return (0, 0)

Method: setSubVector
	0 aload_2 (0, 0)
	1 iconst_0 (0, 0)
	2 aload_0 (0, 0)
	3 getfield (0, 0)
	4 org/apache/commons/math3/linear/ArrayRealVector.data:[D (0, 0)
	6 iload_1 (0, 0)
	7 aload_2 (0, 0)
	8 arraylength (0, 0)
	9 invokestatic (0, 0)
	10 java/lang/System.arraycopy:(Ljava/lang/Object;ILjava/lang/Object;II)V (0, 0)
	12 goto (0, 0)
	13 19 (0, 0)
	15 astore_3 (0, 0)
	16 aload_0 (0, 0)
	17 iload_1 (0, 0)
	18 invokevirtual (0, 0)
	19 org/apache/commons/math3/linear/ArrayRealVector.checkIndex:(I)V (0, 0)
	21 aload_0 (0, 0)
	22 iload_1 (0, 0)
	23 aload_2 (0, 0)
	24 arraylength (0, 0)
	25 iadd (0, 0)
	26 iconst_1 (0, 0)
	27 isub (0, 0)
	28 invokevirtual (0, 0)
	29 org/apache/commons/math3/linear/ArrayRealVector.checkIndex:(I)V (0, 0)
	31 return (0, 0)

Method: set
	0 aload_0 (0, 0)
	1 getfield (0, 0)
	2 org/apache/commons/math3/linear/ArrayRealVector.data:[D (0, 0)
	4 dload_1 (0, 0)
	5 invokestatic (0, 0)
	6 java/util/Arrays.fill:([DD)V (0, 0)
	8 return (0, 0)

Method: toArray
	0 aload_0 (0, 0)
	1 getfield (0, 0)
	2 org/apache/commons/math3/linear/ArrayRealVector.data:[D (0, 0)
	4 invokevirtual (0, 0)
	5 [D.clone:()Ljava/lang/Object; (0, 0)
	7 checkcast (0, 0)
	8 [D (0, 0)
	10 areturn (0, 0)

Method: toString
	0 getstatic (0, 4)
	1 org/apache/commons/math3/linear/ArrayRealVector.DEFAULT_FORMAT:Lorg/apache/commons/math3/linear/RealVectorFormat; (0, 4)
	3 aload_0 (0, 4)
	4 invokevirtual (0, 4)
	5 org/apache/commons/math3/linear/RealVectorFormat.format:(Lorg/apache/commons/math3/linear/RealVector;)Ljava/lang/String; (0, 4)
	7 areturn (0, 4)

Method: checkVectorDimensions
	0 aload_0 (1, 1)
	1 getfield (1, 1)
	2 org/apache/commons/math3/linear/ArrayRealVector.data:[D (1, 1)
	4 arraylength (1, 1)
	5 iload_1 (1, 1)
	6 if_icmpeq (1, 1)
	7 17 (1, 1)
	9 new (1, 1)
	10 org/apache/commons/math3/exception/DimensionMismatchException (1, 1)
	12 dup (1, 1)
	13 aload_0 (1, 1)
	14 getfield (1, 1)
	15 org/apache/commons/math3/linear/ArrayRealVector.data:[D (1, 1)
	17 arraylength (1, 1)
	18 iload_1 (1, 1)
	19 invokespecial (1, 1)
	20 org/apache/commons/math3/exception/DimensionMismatchException.<init>:(II)V (1, 1)
	22 athrow (1, 1)
	23 return (0, 0)

Method: isNaN
	0 aload_0 (1, 4)
	1 getfield (1, 4)
	2 org/apache/commons/math3/linear/ArrayRealVector.data:[D (1, 4)
	4 astore_1 (1, 4)
	5 aload_1 (1, 4)
	6 arraylength (1, 4)
	7 istore_2 (1, 4)
	8 iconst_0 (1, 4)
	9 istore_3 (1, 4)
	10 iload_3 (1, 4)
	11 iload_2 (1, 4)
	12 if_icmpge (1, 4)
	13 24 (1, 4)
	15 aload_1 (1, 4)
	16 iload_3 (1, 4)
	17 daload (1, 4)
	18 dstore (1, 4)
	19 #4 (1, 4)
	20 dload (2, 1)
	21 #4 (2, 1)
	22 invokestatic (2, 1)
	23 java/lang/Double.isNaN:(D)Z (2, 1)
	25 ifeq (2, 1)
	26 5 (2, 1)
	28 iconst_1 (2, 1)
	29 ireturn (2, 1)
	30 iinc (2, 1)
	31 #3 (2, 1)
	32 -89 (2, 1)
	33 goto (2, 1)
	34 -23 (2, 1)
	36 iconst_0 (1, 4)
	37 ireturn (1, 4)

Method: isInfinite
	0 aload_0 (1, 1)
	1 invokevirtual (1, 1)
	2 org/apache/commons/math3/linear/ArrayRealVector.isNaN:()Z (1, 1)
	4 ifeq (1, 1)
	5 5 (1, 1)
	7 iconst_0 (1, 1)
	8 ireturn (1, 1)
	9 aload_0 (1, 4)
	10 getfield (1, 4)
	11 org/apache/commons/math3/linear/ArrayRealVector.data:[D (1, 4)
	13 astore_1 (1, 4)
	14 aload_1 (1, 4)
	15 arraylength (1, 4)
	16 istore_2 (1, 4)
	17 iconst_0 (1, 4)
	18 istore_3 (1, 4)
	19 iload_3 (1, 4)
	20 iload_2 (1, 4)
	21 if_icmpge (1, 4)
	22 24 (1, 4)
	24 aload_1 (1, 4)
	25 iload_3 (1, 4)
	26 daload (1, 4)
	27 dstore (1, 4)
	28 #4 (1, 4)
	29 dload (2, 1)
	30 #4 (2, 1)
	31 invokestatic (2, 1)
	32 java/lang/Double.isInfinite:(D)Z (2, 1)
	34 ifeq (2, 1)
	35 5 (2, 1)
	37 iconst_1 (2, 1)
	38 ireturn (2, 1)
	39 iinc (2, 1)
	40 #3 (2, 1)
	41 -89 (2, 1)
	42 goto (2, 1)
	43 -23 (2, 1)
	45 iconst_0 (1, 4)
	46 ireturn (1, 4)

Method: equals
	0 aload_0 (1, 1)
	1 aload_1 (1, 1)
	2 if_acmpne (1, 1)
	3 5 (1, 1)
	5 iconst_1 (1, 1)
	6 ireturn (1, 1)
	7 aload_1 (1, 1)
	8 instanceof (1, 1)
	9 org/apache/commons/math3/linear/RealVector (1, 1)
	11 ifne (1, 1)
	12 5 (1, 1)
	14 iconst_0 (1, 1)
	15 ireturn (1, 1)
	16 aload_1 (0, 0)
	17 checkcast (0, 0)
	18 org/apache/commons/math3/linear/RealVector (0, 0)
	20 astore_2 (0, 0)
	21 aload_0 (1, 1)
	22 getfield (1, 1)
	23 org/apache/commons/math3/linear/ArrayRealVector.data:[D (1, 1)
	25 arraylength (1, 1)
	26 aload_2 (1, 1)
	27 invokevirtual (1, 1)
	28 org/apache/commons/math3/linear/RealVector.getDimension:()I (1, 1)
	30 if_icmpeq (1, 1)
	31 5 (1, 1)
	33 iconst_0 (1, 1)
	34 ireturn (1, 1)
	35 aload_2 (1, 1)
	36 invokevirtual (1, 1)
	37 org/apache/commons/math3/linear/RealVector.isNaN:()Z (1, 1)
	39 ifeq (1, 1)
	40 8 (1, 1)
	42 aload_0 (1, 1)
	43 invokevirtual (1, 1)
	44 org/apache/commons/math3/linear/ArrayRealVector.isNaN:()Z (1, 1)
	46 ireturn (1, 1)
	47 iconst_0 (1, 4)
	48 istore_3 (1, 4)
	49 iload_3 (1, 4)
	50 aload_0 (1, 4)
	51 getfield (1, 4)
	52 org/apache/commons/math3/linear/ArrayRealVector.data:[D (1, 4)
	54 arraylength (1, 4)
	55 if_icmpge (1, 4)
	56 26 (1, 4)
	58 aload_0 (2, 1)
	59 getfield (2, 1)
	60 org/apache/commons/math3/linear/ArrayRealVector.data:[D (2, 1)
	62 iload_3 (2, 1)
	63 daload (2, 1)
	64 aload_2 (2, 1)
	65 iload_3 (2, 1)
	66 invokevirtual (2, 1)
	67 org/apache/commons/math3/linear/RealVector.getEntry:(I)D (2, 1)
	69 dcmpl (2, 1)
	70 ifeq (2, 1)
	71 5 (2, 1)
	73 iconst_0 (2, 1)
	74 ireturn (2, 1)
	75 iinc (2, 1)
	76 #3 (2, 1)
	77 -89 (2, 1)
	78 goto (2, 1)
	79 -29 (2, 1)
	81 iconst_1 (1, 4)
	82 ireturn (1, 4)

Method: hashCode
	0 aload_0 (1, 1)
	1 invokevirtual (1, 1)
	2 org/apache/commons/math3/linear/ArrayRealVector.isNaN:()Z (1, 1)
	4 ifeq (1, 1)
	5 6 (1, 1)
	7 bipush (1, 1)
	8 9 (1, 1)
	9 ireturn (1, 1)
	10 aload_0 (0, 0)
	11 getfield (0, 0)
	12 org/apache/commons/math3/linear/ArrayRealVector.data:[D (0, 0)
	14 invokestatic (0, 0)
	15 org/apache/commons/math3/util/MathUtils.hash:([D)I (0, 0)
	17 ireturn (0, 0)

Method: combine
	0 aload_0 (0, 0)
	1 dload_1 (0, 0)
	2 dload_3 (0, 0)
	3 aload (0, 0)
	4 #5 (0, 0)
	5 invokevirtual (0, 0)
	6 org/apache/commons/math3/linear/ArrayRealVector.combine:(DDLorg/apache/commons/math3/linear/RealVector;)Lorg/apache/commons/math3/linear/ArrayRealVector; (0, 0)
	8 areturn (0, 0)

Method: combineToSelf
	0 aload_0 (0, 0)
	1 dload_1 (0, 0)
	2 dload_3 (0, 0)
	3 aload (0, 0)
	4 #5 (0, 0)
	5 invokevirtual (0, 0)
	6 org/apache/commons/math3/linear/ArrayRealVector.combineToSelf:(DDLorg/apache/commons/math3/linear/RealVector;)Lorg/apache/commons/math3/linear/ArrayRealVector; (0, 0)
	8 areturn (0, 0)

Method: walkInDefaultOrder
	0 aload_0 (0, 0)
	1 iload_2 (0, 0)
	2 iload_3 (0, 0)
	3 invokevirtual (0, 0)
	4 org/apache/commons/math3/linear/ArrayRealVector.checkIndices:(II)V (0, 0)
	6 aload_1 (0, 0)
	7 aload_0 (0, 0)
	8 getfield (0, 0)
	9 org/apache/commons/math3/linear/ArrayRealVector.data:[D (0, 0)
	11 arraylength (0, 0)
	12 iload_2 (0, 0)
	13 iload_3 (0, 0)
	14 invokeinterface (0, 0)
	15 org/apache/commons/math3/linear/RealVectorChangingVisitor.visit:(ID)V (0, 0)
	17 0 (0, 0)
	19 iload_2 (1, 4)
	20 istore (1, 4)
	21 #4 (1, 4)
	22 iload (1, 4)
	23 #4 (1, 4)
	24 iload_3 (1, 4)
	25 if_icmpgt (1, 4)
	26 31 (1, 4)
	28 aload_0 (1, 4)
	29 getfield (1, 4)
	30 org/apache/commons/math3/linear/ArrayRealVector.data:[D (1, 4)
	32 iload (1, 4)
	33 #4 (1, 4)
	34 aload_1 (1, 4)
	35 iload (1, 4)
	36 #4 (1, 4)
	37 aload_0 (1, 4)
	38 getfield (1, 4)
	39 org/apache/commons/math3/linear/ArrayRealVector.data:[D (1, 4)
	41 iload (1, 4)
	42 #4 (1, 4)
	43 daload (1, 4)
	44 invokeinterface (1, 4)
	45 org/apache/commons/math3/linear/RealVectorChangingVisitor.walkInDefaultOrder:(Lorg/apache/commons/math3/linear/RealVectorChangingVisitor;)D (1, 4)
	47 0 (1, 4)
	49 dastore (1, 4)
	50 iinc (1, 4)
	51 #4 (1, 4)
	52 -89 (1, 4)
	53 goto (1, 4)
	54 -31 (1, 4)
	56 aload_1 (0, 0)
	57 invokeinterface (0, 0)
	58 org/apache/commons/math3/linear/RealVectorChangingVisitor.checkIndices:(II)V (0, 0)
	60 0 (0, 0)
	62 dreturn (0, 0)

Method: walkInOptimizedOrder
	0 aload_0 (0, 0)
	1 aload_1 (0, 0)
	2 iload_2 (0, 0)
	3 iload_3 (0, 0)
	4 invokevirtual (0, 0)
	5 org/apache/commons/math3/linear/ArrayRealVector.walkInDefaultOrder:(Lorg/apache/commons/math3/linear/RealVectorChangingVisitor;II)D (0, 0)
	7 dreturn (0, 0)

Method: <clinit>
	0 invokestatic (0, 0)
	1 org/apache/commons/math3/linear/RealVectorFormat.getInstance:()Lorg/apache/commons/math3/linear/RealVectorFormat; (0, 0)
	3 putstatic (0, 0)
	4 org/apache/commons/math3/linear/ArrayRealVector.DEFAULT_FORMAT:Lorg/apache/commons/math3/linear/RealVectorFormat; (0, 0)
	6 return (0, 0)

