Method: <init>
	0 aload_0 (1, 4)
	1 invokespecial (1, 4)
	2 java/lang/Object.<init>:()V (1, 4)
	4 aload_1 (1, 4)
	5 invokeinterface (1, 4)
	6 org/apache/commons/math3/linear/RealMatrix.getColumnDimension:()I (1, 4)
	8 0 (1, 4)
	10 istore_2 (1, 4)
	11 aload_1 (1, 4)
	12 invokeinterface (1, 4)
	13 org/apache/commons/math3/linear/RealMatrix.org/apache/commons/math3/util/FastMath (1, 4)
	15 0 (1, 4)
	17 istore_3 (1, 4)
	18 iload_2 (1, 4)
	19 iload_3 (1, 4)
	20 invokestatic (1, 4)
	21 org/apache/commons/math3/util/FastMath.min:(II)I (1, 4)
	23 istore (1, 4)
	24 #4 (1, 4)
	25 aload_0 (1, 4)
	26 aload_1 (1, 4)
	27 invokeinterface (1, 4)
	28 org/apache/commons/math3/linear/RealMatrix.householderVectors:[[D (1, 4)
	30 0 (1, 4)
	32 putfield (1, 4)
	33 org/apache/commons/math3/linear/BiDiagonalTransformer.householderVectors:[[D (1, 4)
	35 aload_0 (1, 4)
	36 iload (1, 4)
	37 #4 (1, 4)
	38 newarray (1, 4)
	39 7 (1, 4)
	40 putfield (1, 4)
	41 org/apache/commons/math3/linear/BiDiagonalTransformer.main:[D (1, 4)
	43 aload_0 (1, 4)
	44 iload (1, 4)
	45 #4 (1, 4)
	46 iconst_1 (1, 4)
	47 isub (1, 4)
	48 newarray (1, 4)
	49 7 (1, 4)
	50 putfield (1, 4)
	51 org/apache/commons/math3/linear/BiDiagonalTransformer.secondary:[D (1, 4)
	53 aload_0 (1, 4)
	54 aconst_null (1, 4)
	55 putfield (1, 4)
	56 org/apache/commons/math3/linear/BiDiagonalTransformer.cachedU:Lorg/apache/commons/math3/linear/RealMatrix; (1, 4)
	58 aload_0 (1, 4)
	59 aconst_null (1, 4)
	60 putfield (1, 4)
	61 org/apache/commons/math3/linear/BiDiagonalTransformer.cachedB:Lorg/apache/commons/math3/linear/RealMatrix; (1, 4)
	63 aload_0 (1, 4)
	64 aconst_null (1, 4)
	65 putfield (1, 4)
	66 org/apache/commons/math3/linear/BiDiagonalTransformer.cachedV:Lorg/apache/commons/math3/linear/RealMatrix; (1, 4)
	68 iload_2 (3, 1)
	69 iload_3 (3, 1)
	70 if_icmplt (3, 1)
	71 10 (3, 1)
	73 aload_0 (4, 4)
	74 invokespecial (4, 4)
	75 org/apache/commons/math3/linear/BiDiagonalTransformer.transformToUpperBiDiagonal:()V (4, 4)
	77 goto (4, 4)
	78 7 (4, 4)
	80 aload_0 (6, 4)
	81 invokespecial (6, 4)
	82 org/apache/commons/math3/linear/BiDiagonalTransformer.transformToLowerBiDiagonal:()V (6, 4)
	84 return (0, 0)

Method: getU
	0 aload_0 (1, 1)
	1 getfield (1, 1)
	2 org/apache/commons/math3/linear/BiDiagonalTransformer.cachedU:Lorg/apache/commons/math3/linear/RealMatrix; (1, 1)
	4 ifnonnull (1, 1)
	5 285 (1, 1)
	7 aload_0 (1, 1)
	8 getfield (1, 1)
	9 org/apache/commons/math3/linear/BiDiagonalTransformer.householderVectors:[[D (1, 1)
	11 arraylength (1, 1)
	12 istore_1 (1, 1)
	13 aload_0 (1, 1)
	14 getfield (1, 1)
	15 org/apache/commons/math3/linear/BiDiagonalTransformer.householderVectors:[[D (1, 1)
	17 iconst_0 (1, 1)
	18 aaload (1, 1)
	19 arraylength (1, 1)
	20 istore_2 (1, 1)
	21 aload_0 (1, 1)
	22 getfield (1, 1)
	23 org/apache/commons/math3/linear/BiDiagonalTransformer.main:[D (1, 1)
	25 arraylength (1, 1)
	26 istore_3 (1, 1)
	27 iload_1 (1, 1)
	28 iload_2 (1, 1)
	29 if_icmplt (1, 1)
	30 7 (1, 1)
	32 iconst_0 (1, 1)
	33 goto (1, 1)
	34 4 (1, 1)
	36 iconst_1 (1, 1)
	37 istore (1, 1)
	38 #4 (1, 1)
	39 iload_1 (1, 1)
	40 iload_2 (1, 1)
	41 if_icmplt (1, 1)
	42 10 (1, 1)
	44 aload_0 (1, 1)
	45 getfield (1, 1)
	46 org/apache/commons/math3/linear/BiDiagonalTransformer.main:[D (1, 1)
	48 goto (1, 1)
	49 7 (1, 1)
	51 aload_0 (1, 1)
	52 getfield (1, 1)
	53 org/apache/commons/math3/linear/BiDiagonalTransformer.secondary:[D (1, 1)
	55 astore (1, 1)
	56 #5 (1, 1)
	57 iload_1 (1, 1)
	58 iload_1 (1, 1)
	59 multianewarray (1, 1)
	60 [[D (1, 1)
	62 58 (1, 1)
	63 astore (1, 1)
	64 #6 (1, 1)
	65 iload_1 (3, 4)
	66 iconst_1 (3, 4)
	67 isub (3, 4)
	68 istore (3, 4)
	69 #7 (3, 4)
	70 iload (3, 4)
	71 #7 (3, 4)
	72 iload_3 (3, 4)
	73 if_icmplt (3, 4)
	74 18 (3, 4)
	76 aload (3, 4)
	77 #6 (3, 4)
	78 iload (3, 4)
	79 #7 (3, 4)
	80 aaload (3, 4)
	81 iload (3, 4)
	82 #7 (3, 4)
	83 dconst_1 (3, 4)
	84 dastore (3, 4)
	85 iinc (3, 4)
	86 #7 (3, 4)
	87 -89 (3, 4)
	88 goto (3, 4)
	89 -18 (3, 4)
	91 iload_3 (4, 4)
	92 iconst_1 (4, 4)
	93 isub (4, 4)
	94 istore (4, 4)
	95 #7 (4, 4)
	96 iload (4, 4)
	97 #7 (4, 4)
	98 iload (4, 4)
	99 #4 (4, 4)
	100 if_icmplt (4, 4)
	101 168 (4, 4)
	103 aload_0 (4, 4)
	104 getfield (4, 4)
	105 org/apache/commons/math3/linear/BiDiagonalTransformer.householderVectors:[[D (4, 4)
	107 iload (4, 4)
	108 #7 (4, 4)
	109 aaload (4, 4)
	110 astore (4, 4)
	111 #8 (4, 4)
	112 aload (4, 4)
	113 #6 (4, 4)
	114 iload (4, 4)
	115 #7 (4, 4)
	116 aaload (4, 4)
	117 iload (4, 4)
	118 #7 (4, 4)
	119 dconst_1 (4, 4)
	120 dastore (4, 4)
	121 aload (5, 1)
	122 #8 (5, 1)
	123 iload (5, 1)
	124 #7 (5, 1)
	125 iload (5, 1)
	126 #4 (5, 1)
	127 isub (5, 1)
	128 daload (5, 1)
	129 dconst_0 (5, 1)
	130 dcmpl (5, 1)
	131 ifeq (5, 1)
	132 131 (5, 1)
	134 iload (6, 4)
	135 #7 (6, 4)
	136 istore (6, 4)
	137 #9 (6, 4)
	138 iload (6, 4)
	139 #9 (6, 4)
	140 iload_1 (6, 4)
	141 if_icmpge (6, 4)
	142 121 (6, 4)
	144 dconst_0 (6, 4)
	145 dstore (6, 4)
	146 #10 (6, 4)
	147 iload (7, 4)
	148 #7 (7, 4)
	149 istore (7, 4)
	150 #12 (7, 4)
	151 iload (7, 4)
	152 #12 (7, 4)
	153 iload_1 (7, 4)
	154 if_icmpge (7, 4)
	155 36 (7, 4)
	157 dload (7, 4)
	158 #10 (7, 4)
	159 aload (7, 4)
	160 #6 (7, 4)
	161 iload (7, 4)
	162 #12 (7, 4)
	163 aaload (7, 4)
	164 iload (7, 4)
	165 #9 (7, 4)
	166 daload (7, 4)
	167 aload_0 (7, 4)
	168 getfield (7, 4)
	169 org/apache/commons/math3/linear/BiDiagonalTransformer.householderVectors:[[D (7, 4)
	171 iload (7, 4)
	172 #12 (7, 4)
	173 aaload (7, 4)
	174 iload (7, 4)
	175 #7 (7, 4)
	176 iload (7, 4)
	177 #4 (7, 4)
	178 isub (7, 4)
	179 daload (7, 4)
	180 dmul (7, 4)
	181 dsub (7, 4)
	182 dstore (7, 4)
	183 #10 (7, 4)
	184 iinc (7, 4)
	185 #12 (7, 4)
	186 -89 (7, 4)
	187 goto (7, 4)
	188 -36 (7, 4)
	190 dload (6, 4)
	191 #10 (6, 4)
	192 aload (6, 4)
	193 #5 (6, 4)
	194 iload (6, 4)
	195 #7 (6, 4)
	196 iload (6, 4)
	197 #4 (6, 4)
	198 isub (6, 4)
	199 daload (6, 4)
	200 aload (6, 4)
	201 #8 (6, 4)
	202 iload (6, 4)
	203 #7 (6, 4)
	204 iload (6, 4)
	205 #4 (6, 4)
	206 isub (6, 4)
	207 daload (6, 4)
	208 dmul (6, 4)
	209 ddiv (6, 4)
	210 dstore (6, 4)
	211 #10 (6, 4)
	212 iload (7, 4)
	213 #7 (7, 4)
	214 istore (7, 4)
	215 #12 (7, 4)
	216 iload (7, 4)
	217 #12 (7, 4)
	218 iload_1 (7, 4)
	219 if_icmpge (7, 4)
	220 37 (7, 4)
	222 aload (7, 4)
	223 #6 (7, 4)
	224 iload (7, 4)
	225 #12 (7, 4)
	226 aaload (7, 4)
	227 iload (7, 4)
	228 #9 (7, 4)
	229 dup2 (7, 4)
	230 daload (7, 4)
	231 dload (7, 4)
	232 #10 (7, 4)
	233 dneg (7, 4)
	234 aload_0 (7, 4)
	235 getfield (7, 4)
	236 org/apache/commons/math3/linear/BiDiagonalTransformer.householderVectors:[[D (7, 4)
	238 iload (7, 4)
	239 #12 (7, 4)
	240 aaload (7, 4)
	241 iload (7, 4)
	242 #7 (7, 4)
	243 iload (7, 4)
	244 #4 (7, 4)
	245 isub (7, 4)
	246 daload (7, 4)
	247 dmul (7, 4)
	248 dadd (7, 4)
	249 dastore (7, 4)
	250 iinc (7, 4)
	251 #12 (7, 4)
	252 -89 (7, 4)
	253 goto (7, 4)
	254 -37 (7, 4)
	256 iinc (7, 4)
	257 #9 (7, 4)
	258 -89 (7, 4)
	259 goto (7, 4)
	260 -121 (7, 4)
	262 iinc (7, 4)
	263 #7 (7, 4)
	264 -89 (7, 4)
	265 goto (7, 4)
	266 -169 (7, 4)
	268 iload (7, 1)
	269 #4 (7, 1)
	270 ifle (7, 1)
	271 10 (7, 1)
	273 aload (7, 1)
	274 #6 (7, 1)
	275 iconst_0 (7, 1)
	276 aaload (7, 1)
	277 iconst_0 (7, 1)
	278 dconst_1 (7, 1)
	279 dastore (7, 1)
	280 aload_0 (6, 4)
	281 aload (6, 4)
	282 #6 (6, 4)
	283 invokestatic (6, 4)
	284 org/apache/commons/math3/linear/MatrixUtils.createRealMatrix:([[D)Lorg/apache/commons/math3/linear/RealMatrix; (6, 4)
	286 putfield (6, 4)
	287 org/apache/commons/math3/linear/BiDiagonalTransformer.cachedU:Lorg/apache/commons/math3/linear/RealMatrix; (6, 4)
	289 aload_0 (5, 1)
	290 getfield (5, 1)
	291 org/apache/commons/math3/linear/BiDiagonalTransformer.cachedU:Lorg/apache/commons/math3/linear/RealMatrix; (5, 1)
	293 areturn (3, 1)

Method: getB
	0 aload_0 (1, 1)
	1 getfield (1, 1)
	2 org/apache/commons/math3/linear/BiDiagonalTransformer.cachedB:Lorg/apache/commons/math3/linear/RealMatrix; (1, 1)
	4 ifnonnull (1, 1)
	5 124 (1, 1)
	7 aload_0 (1, 1)
	8 getfield (1, 1)
	9 org/apache/commons/math3/linear/BiDiagonalTransformer.householderVectors:[[D (1, 1)
	11 arraylength (1, 1)
	12 istore_1 (1, 1)
	13 aload_0 (1, 1)
	14 getfield (1, 1)
	15 org/apache/commons/math3/linear/BiDiagonalTransformer.householderVectors:[[D (1, 1)
	17 iconst_0 (1, 1)
	18 aaload (1, 1)
	19 arraylength (1, 1)
	20 istore_2 (1, 1)
	21 iload_1 (1, 1)
	22 iload_2 (1, 1)
	23 multianewarray (1, 1)
	24 [[D (1, 1)
	26 78 (1, 1)
	27 astore_3 (1, 1)
	28 iconst_0 (2, 4)
	29 istore (2, 4)
	30 #4 (2, 4)
	31 iload (2, 4)
	32 #4 (2, 4)
	33 aload_0 (2, 4)
	34 getfield (2, 4)
	35 org/apache/commons/math3/linear/BiDiagonalTransformer.main:[D (2, 4)
	37 arraylength (2, 4)
	38 if_icmpge (2, 4)
	39 82 (2, 4)
	41 aload_3 (2, 4)
	42 iload (2, 4)
	43 #4 (2, 4)
	44 aaload (2, 4)
	45 iload (2, 4)
	46 #4 (2, 4)
	47 aload_0 (2, 4)
	48 getfield (2, 4)
	49 org/apache/commons/math3/linear/BiDiagonalTransformer.main:[D (2, 4)
	51 iload (2, 4)
	52 #4 (2, 4)
	53 daload (2, 4)
	54 dastore (2, 4)
	55 iload_1 (3, 1)
	56 iload_2 (3, 1)
	57 if_icmpge (3, 1)
	58 29 (3, 1)
	60 iload (4, 1)
	61 #4 (4, 1)
	62 ifle (4, 1)
	63 52 (4, 1)
	65 aload_3 (4, 1)
	66 iload (4, 1)
	67 #4 (4, 1)
	68 aaload (4, 1)
	69 iload (4, 1)
	70 #4 (4, 1)
	71 iconst_1 (4, 1)
	72 isub (4, 1)
	73 aload_0 (4, 1)
	74 getfield (4, 1)
	75 org/apache/commons/math3/linear/BiDiagonalTransformer.secondary:[D (4, 1)
	77 iload (4, 1)
	78 #4 (4, 1)
	79 iconst_1 (4, 1)
	80 isub (4, 1)
	81 daload (4, 1)
	82 dastore (4, 1)
	83 goto (4, 1)
	84 31 (4, 1)
	86 iload (5, 1)
	87 #4 (5, 1)
	88 aload_0 (5, 1)
	89 getfield (5, 1)
	90 org/apache/commons/math3/linear/BiDiagonalTransformer.main:[D (5, 1)
	92 arraylength (5, 1)
	93 iconst_1 (5, 1)
	94 isub (5, 1)
	95 if_icmpge (5, 1)
	96 19 (5, 1)
	98 aload_3 (5, 1)
	99 iload (5, 1)
	100 #4 (5, 1)
	101 aaload (5, 1)
	102 iload (5, 1)
	103 #4 (5, 1)
	104 iconst_1 (5, 1)
	105 iadd (5, 1)
	106 aload_0 (5, 1)
	107 getfield (5, 1)
	108 org/apache/commons/math3/linear/BiDiagonalTransformer.secondary:[D (5, 1)
	110 iload (5, 1)
	111 #4 (5, 1)
	112 daload (5, 1)
	113 dastore (5, 1)
	114 iinc (5, 1)
	115 #4 (5, 1)
	116 -89 (5, 1)
	117 goto (5, 1)
	118 -86 (5, 1)
	120 aload_0 (4, 2)
	121 aload_3 (4, 2)
	122 invokestatic (4, 2)
	123 org/apache/commons/math3/linear/MatrixUtils.createRealMatrix:([[D)Lorg/apache/commons/math3/linear/RealMatrix; (4, 2)
	125 putfield (4, 2)
	126 org/apache/commons/math3/linear/BiDiagonalTransformer.cachedB:Lorg/apache/commons/math3/linear/RealMatrix; (4, 2)
	128 aload_0 (2, 4)
	129 getfield (2, 4)
	130 org/apache/commons/math3/linear/BiDiagonalTransformer.cachedB:Lorg/apache/commons/math3/linear/RealMatrix; (2, 4)
	132 areturn (2, 4)

Method: getV
	0 aload_0 (1, 1)
	1 getfield (1, 1)
	2 org/apache/commons/math3/linear/BiDiagonalTransformer.cachedV:Lorg/apache/commons/math3/linear/RealMatrix; (1, 1)
	4 ifnonnull (1, 1)
	5 266 (1, 1)
	7 aload_0 (1, 1)
	8 getfield (1, 1)
	9 org/apache/commons/math3/linear/BiDiagonalTransformer.householderVectors:[[D (1, 1)
	11 arraylength (1, 1)
	12 istore_1 (1, 1)
	13 aload_0 (1, 1)
	14 getfield (1, 1)
	15 org/apache/commons/math3/linear/BiDiagonalTransformer.householderVectors:[[D (1, 1)
	17 iconst_0 (1, 1)
	18 aaload (1, 1)
	19 arraylength (1, 1)
	20 istore_2 (1, 1)
	21 aload_0 (1, 1)
	22 getfield (1, 1)
	23 org/apache/commons/math3/linear/BiDiagonalTransformer.main:[D (1, 1)
	25 arraylength (1, 1)
	26 istore_3 (1, 1)
	27 iload_1 (1, 1)
	28 iload_2 (1, 1)
	29 if_icmplt (1, 1)
	30 7 (1, 1)
	32 iconst_1 (1, 1)
	33 goto (1, 1)
	34 4 (1, 1)
	36 iconst_0 (1, 1)
	37 istore (1, 1)
	38 #4 (1, 1)
	39 iload_1 (1, 1)
	40 iload_2 (1, 1)
	41 if_icmplt (1, 1)
	42 10 (1, 1)
	44 aload_0 (1, 1)
	45 getfield (1, 1)
	46 org/apache/commons/math3/linear/BiDiagonalTransformer.secondary:[D (1, 1)
	48 goto (1, 1)
	49 7 (1, 1)
	51 aload_0 (1, 1)
	52 getfield (1, 1)
	53 org/apache/commons/math3/linear/BiDiagonalTransformer.main:[D (1, 1)
	55 astore (1, 1)
	56 #5 (1, 1)
	57 iload_2 (1, 1)
	58 iload_2 (1, 1)
	59 multianewarray (1, 1)
	60 [[D (1, 1)
	62 58 (1, 1)
	63 astore (1, 1)
	64 #6 (1, 1)
	65 iload_2 (3, 4)
	66 iconst_1 (3, 4)
	67 isub (3, 4)
	68 istore (3, 4)
	69 #7 (3, 4)
	70 iload (3, 4)
	71 #7 (3, 4)
	72 iload_3 (3, 4)
	73 if_icmplt (3, 4)
	74 18 (3, 4)
	76 aload (3, 4)
	77 #6 (3, 4)
	78 iload (3, 4)
	79 #7 (3, 4)
	80 aaload (3, 4)
	81 iload (3, 4)
	82 #7 (3, 4)
	83 dconst_1 (3, 4)
	84 dastore (3, 4)
	85 iinc (3, 4)
	86 #7 (3, 4)
	87 -89 (3, 4)
	88 goto (3, 4)
	89 -18 (3, 4)
	91 iload_3 (4, 4)
	92 iconst_1 (4, 4)
	93 isub (4, 4)
	94 istore (4, 4)
	95 #7 (4, 4)
	96 iload (4, 4)
	97 #7 (4, 4)
	98 iload (4, 4)
	99 #4 (4, 4)
	100 if_icmplt (4, 4)
	101 149 (4, 4)
	103 aload_0 (4, 4)
	104 getfield (4, 4)
	105 org/apache/commons/math3/linear/BiDiagonalTransformer.householderVectors:[[D (4, 4)
	107 iload (4, 4)
	108 #7 (4, 4)
	109 iload (4, 4)
	110 #4 (4, 4)
	111 isub (4, 4)
	112 aaload (4, 4)
	113 astore (4, 4)
	114 #8 (4, 4)
	115 aload (4, 4)
	116 #6 (4, 4)
	117 iload (4, 4)
	118 #7 (4, 4)
	119 aaload (4, 4)
	120 iload (4, 4)
	121 #7 (4, 4)
	122 dconst_1 (4, 4)
	123 dastore (4, 4)
	124 aload (5, 1)
	125 #8 (5, 1)
	126 iload (5, 1)
	127 #7 (5, 1)
	128 daload (5, 1)
	129 dconst_0 (5, 1)
	130 dcmpl (5, 1)
	131 ifeq (5, 1)
	132 112 (5, 1)
	134 iload (6, 4)
	135 #7 (6, 4)
	136 istore (6, 4)
	137 #9 (6, 4)
	138 iload (6, 4)
	139 #9 (6, 4)
	140 iload_2 (6, 4)
	141 if_icmpge (6, 4)
	142 102 (6, 4)
	144 dconst_0 (6, 4)
	145 dstore (6, 4)
	146 #10 (6, 4)
	147 iload (7, 4)
	148 #7 (7, 4)
	149 istore (7, 4)
	150 #12 (7, 4)
	151 iload (7, 4)
	152 #12 (7, 4)
	153 iload_2 (7, 4)
	154 if_icmpge (7, 4)
	155 28 (7, 4)
	157 dload (7, 4)
	158 #10 (7, 4)
	159 aload (7, 4)
	160 #6 (7, 4)
	161 iload (7, 4)
	162 #12 (7, 4)
	163 aaload (7, 4)
	164 iload (7, 4)
	165 #9 (7, 4)
	166 daload (7, 4)
	167 aload (7, 4)
	168 #8 (7, 4)
	169 iload (7, 4)
	170 #12 (7, 4)
	171 daload (7, 4)
	172 dmul (7, 4)
	173 dsub (7, 4)
	174 dstore (7, 4)
	175 #10 (7, 4)
	176 iinc (7, 4)
	177 #12 (7, 4)
	178 -89 (7, 4)
	179 goto (7, 4)
	180 -28 (7, 4)
	182 dload (6, 4)
	183 #10 (6, 4)
	184 aload (6, 4)
	185 #5 (6, 4)
	186 iload (6, 4)
	187 #7 (6, 4)
	188 iload (6, 4)
	189 #4 (6, 4)
	190 isub (6, 4)
	191 daload (6, 4)
	192 aload (6, 4)
	193 #8 (6, 4)
	194 iload (6, 4)
	195 #7 (6, 4)
	196 daload (6, 4)
	197 dmul (6, 4)
	198 ddiv (6, 4)
	199 dstore (6, 4)
	200 #10 (6, 4)
	201 iload (7, 4)
	202 #7 (7, 4)
	203 istore (7, 4)
	204 #12 (7, 4)
	205 iload (7, 4)
	206 #12 (7, 4)
	207 iload_2 (7, 4)
	208 if_icmpge (7, 4)
	209 29 (7, 4)
	211 aload (7, 4)
	212 #6 (7, 4)
	213 iload (7, 4)
	214 #12 (7, 4)
	215 aaload (7, 4)
	216 iload (7, 4)
	217 #9 (7, 4)
	218 dup2 (7, 4)
	219 daload (7, 4)
	220 dload (7, 4)
	221 #10 (7, 4)
	222 dneg (7, 4)
	223 aload (7, 4)
	224 #8 (7, 4)
	225 iload (7, 4)
	226 #12 (7, 4)
	227 daload (7, 4)
	228 dmul (7, 4)
	229 dadd (7, 4)
	230 dastore (7, 4)
	231 iinc (7, 4)
	232 #12 (7, 4)
	233 -89 (7, 4)
	234 goto (7, 4)
	235 -29 (7, 4)
	237 iinc (7, 4)
	238 #9 (7, 4)
	239 -89 (7, 4)
	240 goto (7, 4)
	241 -102 (7, 4)
	243 iinc (7, 4)
	244 #7 (7, 4)
	245 -89 (7, 4)
	246 goto (7, 4)
	247 -150 (7, 4)
	249 iload (7, 1)
	250 #4 (7, 1)
	251 ifle (7, 1)
	252 10 (7, 1)
	254 aload (7, 1)
	255 #6 (7, 1)
	256 iconst_0 (7, 1)
	257 aaload (7, 1)
	258 iconst_0 (7, 1)
	259 dconst_1 (7, 1)
	260 dastore (7, 1)
	261 aload_0 (6, 4)
	262 aload (6, 4)
	263 #6 (6, 4)
	264 invokestatic (6, 4)
	265 org/apache/commons/math3/linear/MatrixUtils.createRealMatrix:([[D)Lorg/apache/commons/math3/linear/RealMatrix; (6, 4)
	267 putfield (6, 4)
	268 org/apache/commons/math3/linear/BiDiagonalTransformer.cachedV:Lorg/apache/commons/math3/linear/RealMatrix; (6, 4)
	270 aload_0 (5, 1)
	271 getfield (5, 1)
	272 org/apache/commons/math3/linear/BiDiagonalTransformer.cachedV:Lorg/apache/commons/math3/linear/RealMatrix; (5, 1)
	274 areturn (3, 1)

Method: getHouseholderVectorsRef
	0 aload_0 (0, 0)
	1 getfield (0, 0)
	2 org/apache/commons/math3/linear/BiDiagonalTransformer.householderVectors:[[D (0, 0)
	4 areturn (0, 0)

Method: getMainDiagonalRef
	0 aload_0 (0, 0)
	1 getfield (0, 0)
	2 org/apache/commons/math3/linear/BiDiagonalTransformer.main:[D (0, 0)
	4 areturn (0, 0)

Method: getSecondaryDiagonalRef
	0 aload_0 (0, 0)
	1 getfield (0, 0)
	2 org/apache/commons/math3/linear/BiDiagonalTransformer.secondary:[D (0, 0)
	4 areturn (0, 0)

Method: isUpperBiDiagonal
	0 aload_0 (0, 0)
	1 getfield (0, 0)
	2 org/apache/commons/math3/linear/BiDiagonalTransformer.householderVectors:[[D (0, 0)
	4 arraylength (0, 0)
	5 aload_0 (0, 0)
	6 getfield (0, 0)
	7 org/apache/commons/math3/linear/BiDiagonalTransformer.householderVectors:[[D (0, 0)
	9 iconst_0 (0, 0)
	10 aaload (0, 0)
	11 arraylength (0, 0)
	12 if_icmplt (0, 0)
	13 7 (0, 0)
	15 iconst_1 (0, 0)
	16 goto (0, 0)
	17 4 (0, 0)
	19 iconst_0 (0, 0)
	20 ireturn (0, 0)

Method: transformToUpperBiDiagonal
	0 aload_0 (0, 0)
	1 getfield (0, 0)
	2 org/apache/commons/math3/linear/BiDiagonalTransformer.householderVectors:[[D (0, 0)
	4 arraylength (0, 0)
	5 istore_1 (0, 0)
	6 aload_0 (0, 0)
	7 getfield (0, 0)
	8 org/apache/commons/math3/linear/BiDiagonalTransformer.householderVectors:[[D (0, 0)
	10 iconst_0 (0, 0)
	11 aaload (0, 0)
	12 arraylength (0, 0)
	13 istore_2 (0, 0)
	14 iconst_0 (1, 4)
	15 istore_3 (1, 4)
	16 iload_3 (1, 4)
	17 iload_2 (1, 4)
	18 if_icmpge (1, 4)
	19 425 (1, 4)
	21 dconst_0 (1, 4)
	22 dstore (1, 4)
	23 #4 (1, 4)
	24 iload_3 (2, 4)
	25 istore (2, 4)
	26 #6 (2, 4)
	27 iload (2, 4)
	28 #6 (2, 4)
	29 iload_1 (2, 4)
	30 if_icmpge (2, 4)
	31 30 (2, 4)
	33 aload_0 (2, 4)
	34 getfield (2, 4)
	35 org/apache/commons/math3/linear/BiDiagonalTransformer.householderVectors:[[D (2, 4)
	37 iload (2, 4)
	38 #6 (2, 4)
	39 aaload (2, 4)
	40 iload_3 (2, 4)
	41 daload (2, 4)
	42 dstore (2, 4)
	43 #7 (2, 4)
	44 dload (2, 4)
	45 #4 (2, 4)
	46 dload (2, 4)
	47 #7 (2, 4)
	48 dload (2, 4)
	49 #7 (2, 4)
	50 dmul (2, 4)
	51 dadd (2, 4)
	52 dstore (2, 4)
	53 #4 (2, 4)
	54 iinc (2, 4)
	55 #6 (2, 4)
	56 -89 (2, 4)
	57 goto (2, 4)
	58 -30 (2, 4)
	60 aload_0 (1, 4)
	61 getfield (1, 4)
	62 org/apache/commons/math3/linear/BiDiagonalTransformer.householderVectors:[[D (1, 4)
	64 iload_3 (1, 4)
	65 aaload (1, 4)
	66 astore (1, 4)
	67 #6 (1, 4)
	68 aload (1, 4)
	69 #6 (1, 4)
	70 iload_3 (1, 4)
	71 daload (1, 4)
	72 dconst_0 (1, 4)
	73 dcmpl (1, 4)
	74 ifle (1, 4)
	75 12 (1, 4)
	77 dload (1, 4)
	78 #4 (1, 4)
	79 invokestatic (1, 4)
	80 org/apache/commons/math3/util/FastMath.sqrt:(D)D (1, 4)
	82 dneg (1, 4)
	83 goto (1, 4)
	84 8 (1, 4)
	86 dload (1, 4)
	87 #4 (1, 4)
	88 invokestatic (1, 4)
	89 org/apache/commons/math3/util/FastMath.sqrt:(D)D (1, 4)
	91 dstore (1, 4)
	92 #7 (1, 4)
	93 aload_0 (1, 4)
	94 getfield (1, 4)
	95 org/apache/commons/math3/linear/BiDiagonalTransformer.main:[D (1, 4)
	97 iload_3 (1, 4)
	98 dload (1, 4)
	99 #7 (1, 4)
	100 dastore (1, 4)
	101 dload (2, 1)
	102 #7 (2, 1)
	103 dconst_0 (2, 1)
	104 dcmpl (2, 1)
	105 ifeq (2, 1)
	106 126 (2, 1)
	108 aload (2, 1)
	109 #6 (2, 1)
	110 iload_3 (2, 1)
	111 dup2 (2, 1)
	112 daload (2, 1)
	113 dload (2, 1)
	114 #7 (2, 1)
	115 dsub (2, 1)
	116 dastore (2, 1)
	117 iload_3 (3, 4)
	118 iconst_1 (3, 4)
	119 iadd (3, 4)
	120 istore (3, 4)
	121 #9 (3, 4)
	122 iload (3, 4)
	123 #9 (3, 4)
	124 iload_2 (3, 4)
	125 if_icmpge (3, 4)
	126 106 (3, 4)
	128 dconst_0 (3, 4)
	129 dstore (3, 4)
	130 #10 (3, 4)
	131 iload_3 (4, 4)
	132 istore (4, 4)
	133 #12 (4, 4)
	134 iload (4, 4)
	135 #12 (4, 4)
	136 iload_1 (4, 4)
	137 if_icmpge (4, 4)
	138 33 (4, 4)
	140 aload_0 (4, 4)
	141 getfield (4, 4)
	142 org/apache/commons/math3/linear/BiDiagonalTransformer.householderVectors:[[D (4, 4)
	144 iload (4, 4)
	145 #12 (4, 4)
	146 aaload (4, 4)
	147 astore (4, 4)
	148 #13 (4, 4)
	149 dload (4, 4)
	150 #10 (4, 4)
	151 aload (4, 4)
	152 #13 (4, 4)
	153 iload (4, 4)
	154 #9 (4, 4)
	155 daload (4, 4)
	156 aload (4, 4)
	157 #13 (4, 4)
	158 iload_3 (4, 4)
	159 daload (4, 4)
	160 dmul (4, 4)
	161 dsub (4, 4)
	162 dstore (4, 4)
	163 #10 (4, 4)
	164 iinc (4, 4)
	165 #12 (4, 4)
	166 -89 (4, 4)
	167 goto (4, 4)
	168 -33 (4, 4)
	170 dload (3, 4)
	171 #10 (3, 4)
	172 dload (3, 4)
	173 #7 (3, 4)
	174 aload_0 (3, 4)
	175 getfield (3, 4)
	176 org/apache/commons/math3/linear/BiDiagonalTransformer.householderVectors:[[D (3, 4)
	178 iload_3 (3, 4)
	179 aaload (3, 4)
	180 iload_3 (3, 4)
	181 daload (3, 4)
	182 dmul (3, 4)
	183 ddiv (3, 4)
	184 dstore (3, 4)
	185 #10 (3, 4)
	186 iload_3 (4, 4)
	187 istore (4, 4)
	188 #12 (4, 4)
	189 iload (4, 4)
	190 #12 (4, 4)
	191 iload_1 (4, 4)
	192 if_icmpge (4, 4)
	193 33 (4, 4)
	195 aload_0 (4, 4)
	196 getfield (4, 4)
	197 org/apache/commons/math3/linear/BiDiagonalTransformer.householderVectors:[[D (4, 4)
	199 iload (4, 4)
	200 #12 (4, 4)
	201 aaload (4, 4)
	202 astore (4, 4)
	203 #13 (4, 4)
	204 aload (4, 4)
	205 #13 (4, 4)
	206 iload (4, 4)
	207 #9 (4, 4)
	208 dup2 (4, 4)
	209 daload (4, 4)
	210 dload (4, 4)
	211 #10 (4, 4)
	212 aload (4, 4)
	213 #13 (4, 4)
	214 iload_3 (4, 4)
	215 daload (4, 4)
	216 dmul (4, 4)
	217 dsub (4, 4)
	218 dastore (4, 4)
	219 iinc (4, 4)
	220 #12 (4, 4)
	221 -89 (4, 4)
	222 goto (4, 4)
	223 -33 (4, 4)
	225 iinc (4, 4)
	226 #9 (4, 4)
	227 -89 (4, 4)
	228 goto (4, 4)
	229 -106 (4, 4)
	231 iload_3 (3, 1)
	232 iload_2 (3, 1)
	233 iconst_1 (3, 1)
	234 isub (3, 1)
	235 if_icmpge (3, 1)
	236 202 (3, 1)
	238 dconst_0 (3, 1)
	239 dstore (3, 1)
	240 #4 (3, 1)
	241 iload_3 (4, 4)
	242 iconst_1 (4, 4)
	243 iadd (4, 4)
	244 istore (4, 4)
	245 #9 (4, 4)
	246 iload (4, 4)
	247 #9 (4, 4)
	248 iload_2 (4, 4)
	249 if_icmpge (4, 4)
	250 26 (4, 4)
	252 aload (4, 4)
	253 #6 (4, 4)
	254 iload (4, 4)
	255 #9 (4, 4)
	256 daload (4, 4)
	257 dstore (4, 4)
	258 #10 (4, 4)
	259 dload (4, 4)
	260 #4 (4, 4)
	261 dload (4, 4)
	262 #10 (4, 4)
	263 dload (4, 4)
	264 #10 (4, 4)
	265 dmul (4, 4)
	266 dadd (4, 4)
	267 dstore (4, 4)
	268 #4 (4, 4)
	269 iinc (4, 4)
	270 #9 (4, 4)
	271 -89 (4, 4)
	272 goto (4, 4)
	273 -26 (4, 4)
	275 aload (3, 1)
	276 #6 (3, 1)
	277 iload_3 (3, 1)
	278 iconst_1 (3, 1)
	279 iadd (3, 1)
	280 daload (3, 1)
	281 dconst_0 (3, 1)
	282 dcmpl (3, 1)
	283 ifle (3, 1)
	284 12 (3, 1)
	286 dload (3, 1)
	287 #4 (3, 1)
	288 invokestatic (3, 1)
	289 org/apache/commons/math3/util/FastMath.sqrt:(D)D (3, 1)
	291 dneg (3, 1)
	292 goto (3, 1)
	293 8 (3, 1)
	295 dload (3, 1)
	296 #4 (3, 1)
	297 invokestatic (3, 1)
	298 org/apache/commons/math3/util/FastMath.sqrt:(D)D (3, 1)
	300 dstore (3, 1)
	301 #9 (3, 1)
	302 aload_0 (3, 1)
	303 getfield (3, 1)
	304 org/apache/commons/math3/linear/BiDiagonalTransformer.secondary:[D (3, 1)
	306 iload_3 (3, 1)
	307 dload (3, 1)
	308 #9 (3, 1)
	309 dastore (3, 1)
	310 dload (4, 1)
	311 #9 (4, 1)
	312 dconst_0 (4, 1)
	313 dcmpl (4, 1)
	314 ifeq (4, 1)
	315 123 (4, 1)
	317 aload (4, 1)
	318 #6 (4, 1)
	319 iload_3 (4, 1)
	320 iconst_1 (4, 1)
	321 iadd (4, 1)
	322 dup2 (4, 1)
	323 daload (4, 1)
	324 dload (4, 1)
	325 #9 (4, 1)
	326 dsub (4, 1)
	327 dastore (4, 1)
	328 iload_3 (5, 4)
	329 iconst_1 (5, 4)
	330 iadd (5, 4)
	331 istore (5, 4)
	332 #11 (5, 4)
	333 iload (5, 4)
	334 #11 (5, 4)
	335 iload_1 (5, 4)
	336 if_icmpge (5, 4)
	337 101 (5, 4)
	339 aload_0 (5, 4)
	340 getfield (5, 4)
	341 org/apache/commons/math3/linear/BiDiagonalTransformer.householderVectors:[[D (5, 4)
	343 iload (5, 4)
	344 #11 (5, 4)
	345 aaload (5, 4)
	346 astore (5, 4)
	347 #12 (5, 4)
	348 dconst_0 (5, 4)
	349 dstore (5, 4)
	350 #13 (5, 4)
	351 iload_3 (6, 4)
	352 iconst_1 (6, 4)
	353 iadd (6, 4)
	354 istore (6, 4)
	355 #15 (6, 4)
	356 iload (6, 4)
	357 #15 (6, 4)
	358 iload_2 (6, 4)
	359 if_icmpge (6, 4)
	360 25 (6, 4)
	362 dload (6, 4)
	363 #13 (6, 4)
	364 aload (6, 4)
	365 #12 (6, 4)
	366 iload (6, 4)
	367 #15 (6, 4)
	368 daload (6, 4)
	369 aload (6, 4)
	370 #6 (6, 4)
	371 iload (6, 4)
	372 #15 (6, 4)
	373 daload (6, 4)
	374 dmul (6, 4)
	375 dsub (6, 4)
	376 dstore (6, 4)
	377 #13 (6, 4)
	378 iinc (6, 4)
	379 #15 (6, 4)
	380 -89 (6, 4)
	381 goto (6, 4)
	382 -25 (6, 4)
	384 dload (5, 4)
	385 #13 (5, 4)
	386 dload (5, 4)
	387 #9 (5, 4)
	388 aload (5, 4)
	389 #6 (5, 4)
	390 iload_3 (5, 4)
	391 iconst_1 (5, 4)
	392 iadd (5, 4)
	393 daload (5, 4)
	394 dmul (5, 4)
	395 ddiv (5, 4)
	396 dstore (5, 4)
	397 #13 (5, 4)
	398 iload_3 (6, 4)
	399 iconst_1 (6, 4)
	400 iadd (6, 4)
	401 istore (6, 4)
	402 #15 (6, 4)
	403 iload (6, 4)
	404 #15 (6, 4)
	405 iload_2 (6, 4)
	406 if_icmpge (6, 4)
	407 25 (6, 4)
	409 aload (6, 4)
	410 #12 (6, 4)
	411 iload (6, 4)
	412 #15 (6, 4)
	413 dup2 (6, 4)
	414 daload (6, 4)
	415 dload (6, 4)
	416 #13 (6, 4)
	417 aload (6, 4)
	418 #6 (6, 4)
	419 iload (6, 4)
	420 #15 (6, 4)
	421 daload (6, 4)
	422 dmul (6, 4)
	423 dsub (6, 4)
	424 dastore (6, 4)
	425 iinc (6, 4)
	426 #15 (6, 4)
	427 -89 (6, 4)
	428 goto (6, 4)
	429 -25 (6, 4)
	431 iinc (6, 4)
	432 #11 (6, 4)
	433 -89 (6, 4)
	434 goto (6, 4)
	435 -101 (6, 4)
	437 iinc (6, 4)
	438 #3 (6, 4)
	439 -89 (6, 4)
	440 goto (6, 4)
	441 -424 (6, 4)
	443 return (4, 1)

Method: transformToLowerBiDiagonal
	0 aload_0 (0, 0)
	1 getfield (0, 0)
	2 org/apache/commons/math3/linear/BiDiagonalTransformer.householderVectors:[[D (0, 0)
	4 arraylength (0, 0)
	5 istore_1 (0, 0)
	6 aload_0 (0, 0)
	7 getfield (0, 0)
	8 org/apache/commons/math3/linear/BiDiagonalTransformer.householderVectors:[[D (0, 0)
	10 iconst_0 (0, 0)
	11 aaload (0, 0)
	12 arraylength (0, 0)
	13 istore_2 (0, 0)
	14 iconst_0 (1, 4)
	15 istore_3 (1, 4)
	16 iload_3 (1, 4)
	17 iload_1 (1, 4)
	18 if_icmpge (1, 4)
	19 429 (1, 4)
	21 aload_0 (1, 4)
	22 getfield (1, 4)
	23 org/apache/commons/math3/linear/BiDiagonalTransformer.householderVectors:[[D (1, 4)
	25 iload_3 (1, 4)
	26 aaload (1, 4)
	27 astore (1, 4)
	28 #4 (1, 4)
	29 dconst_0 (1, 4)
	30 dstore (1, 4)
	31 #5 (1, 4)
	32 iload_3 (2, 4)
	33 istore (2, 4)
	34 #7 (2, 4)
	35 iload (2, 4)
	36 #7 (2, 4)
	37 iload_2 (2, 4)
	38 if_icmpge (2, 4)
	39 26 (2, 4)
	41 aload (2, 4)
	42 #4 (2, 4)
	43 iload (2, 4)
	44 #7 (2, 4)
	45 daload (2, 4)
	46 dstore (2, 4)
	47 #8 (2, 4)
	48 dload (2, 4)
	49 #5 (2, 4)
	50 dload (2, 4)
	51 #8 (2, 4)
	52 dload (2, 4)
	53 #8 (2, 4)
	54 dmul (2, 4)
	55 dadd (2, 4)
	56 dstore (2, 4)
	57 #5 (2, 4)
	58 iinc (2, 4)
	59 #7 (2, 4)
	60 -89 (2, 4)
	61 goto (2, 4)
	62 -26 (2, 4)
	64 aload (1, 4)
	65 #4 (1, 4)
	66 iload_3 (1, 4)
	67 daload (1, 4)
	68 dconst_0 (1, 4)
	69 dcmpl (1, 4)
	70 ifle (1, 4)
	71 12 (1, 4)
	73 dload (1, 4)
	74 #5 (1, 4)
	75 invokestatic (1, 4)
	76 org/apache/commons/math3/util/FastMath.sqrt:(D)D (1, 4)
	78 dneg (1, 4)
	79 goto (1, 4)
	80 8 (1, 4)
	82 dload (1, 4)
	83 #5 (1, 4)
	84 invokestatic (1, 4)
	85 org/apache/commons/math3/util/FastMath.sqrt:(D)D (1, 4)
	87 dstore (1, 4)
	88 #7 (1, 4)
	89 aload_0 (1, 4)
	90 getfield (1, 4)
	91 org/apache/commons/math3/linear/BiDiagonalTransformer.main:[D (1, 4)
	93 iload_3 (1, 4)
	94 dload (1, 4)
	95 #7 (1, 4)
	96 dastore (1, 4)
	97 dload (2, 1)
	98 #7 (2, 1)
	99 dconst_0 (2, 1)
	100 dcmpl (2, 1)
	101 ifeq (2, 1)
	102 119 (2, 1)
	104 aload (2, 1)
	105 #4 (2, 1)
	106 iload_3 (2, 1)
	107 dup2 (2, 1)
	108 daload (2, 1)
	109 dload (2, 1)
	110 #7 (2, 1)
	111 dsub (2, 1)
	112 dastore (2, 1)
	113 iload_3 (3, 4)
	114 iconst_1 (3, 4)
	115 iadd (3, 4)
	116 istore (3, 4)
	117 #9 (3, 4)
	118 iload (3, 4)
	119 #9 (3, 4)
	120 iload_1 (3, 4)
	121 if_icmpge (3, 4)
	122 99 (3, 4)
	124 aload_0 (3, 4)
	125 getfield (3, 4)
	126 org/apache/commons/math3/linear/BiDiagonalTransformer.householderVectors:[[D (3, 4)
	128 iload (3, 4)
	129 #9 (3, 4)
	130 aaload (3, 4)
	131 astore (3, 4)
	132 #10 (3, 4)
	133 dconst_0 (3, 4)
	134 dstore (3, 4)
	135 #11 (3, 4)
	136 iload_3 (4, 4)
	137 istore (4, 4)
	138 #13 (4, 4)
	139 iload (4, 4)
	140 #13 (4, 4)
	141 iload_2 (4, 4)
	142 if_icmpge (4, 4)
	143 25 (4, 4)
	145 dload (4, 4)
	146 #11 (4, 4)
	147 aload (4, 4)
	148 #10 (4, 4)
	149 iload (4, 4)
	150 #13 (4, 4)
	151 daload (4, 4)
	152 aload (4, 4)
	153 #4 (4, 4)
	154 iload (4, 4)
	155 #13 (4, 4)
	156 daload (4, 4)
	157 dmul (4, 4)
	158 dsub (4, 4)
	159 dstore (4, 4)
	160 #11 (4, 4)
	161 iinc (4, 4)
	162 #13 (4, 4)
	163 -89 (4, 4)
	164 goto (4, 4)
	165 -25 (4, 4)
	167 dload (3, 4)
	168 #11 (3, 4)
	169 dload (3, 4)
	170 #7 (3, 4)
	171 aload_0 (3, 4)
	172 getfield (3, 4)
	173 org/apache/commons/math3/linear/BiDiagonalTransformer.householderVectors:[[D (3, 4)
	175 iload_3 (3, 4)
	176 aaload (3, 4)
	177 iload_3 (3, 4)
	178 daload (3, 4)
	179 dmul (3, 4)
	180 ddiv (3, 4)
	181 dstore (3, 4)
	182 #11 (3, 4)
	183 iload_3 (4, 4)
	184 istore (4, 4)
	185 #13 (4, 4)
	186 iload (4, 4)
	187 #13 (4, 4)
	188 iload_2 (4, 4)
	189 if_icmpge (4, 4)
	190 25 (4, 4)
	192 aload (4, 4)
	193 #10 (4, 4)
	194 iload (4, 4)
	195 #13 (4, 4)
	196 dup2 (4, 4)
	197 daload (4, 4)
	198 dload (4, 4)
	199 #11 (4, 4)
	200 aload (4, 4)
	201 #4 (4, 4)
	202 iload (4, 4)
	203 #13 (4, 4)
	204 daload (4, 4)
	205 dmul (4, 4)
	206 dsub (4, 4)
	207 dastore (4, 4)
	208 iinc (4, 4)
	209 #13 (4, 4)
	210 -89 (4, 4)
	211 goto (4, 4)
	212 -25 (4, 4)
	214 iinc (4, 4)
	215 #9 (4, 4)
	216 -89 (4, 4)
	217 goto (4, 4)
	218 -99 (4, 4)
	220 iload_3 (3, 1)
	221 iload_1 (3, 1)
	222 iconst_1 (3, 1)
	223 isub (3, 1)
	224 if_icmpge (3, 1)
	225 217 (3, 1)
	227 aload_0 (3, 1)
	228 getfield (3, 1)
	229 org/apache/commons/math3/linear/BiDiagonalTransformer.householderVectors:[[D (3, 1)
	231 iload_3 (3, 1)
	232 iconst_1 (3, 1)
	233 iadd (3, 1)
	234 aaload (3, 1)
	235 astore (3, 1)
	236 #9 (3, 1)
	237 dconst_0 (3, 1)
	238 dstore (3, 1)
	239 #5 (3, 1)
	240 iload_3 (4, 4)
	241 iconst_1 (4, 4)
	242 iadd (4, 4)
	243 istore (4, 4)
	244 #10 (4, 4)
	245 iload (4, 4)
	246 #10 (4, 4)
	247 iload_1 (4, 4)
	248 if_icmpge (4, 4)
	249 30 (4, 4)
	251 aload_0 (4, 4)
	252 getfield (4, 4)
	253 org/apache/commons/math3/linear/BiDiagonalTransformer.householderVectors:[[D (4, 4)
	255 iload (4, 4)
	256 #10 (4, 4)
	257 aaload (4, 4)
	258 iload_3 (4, 4)
	259 daload (4, 4)
	260 dstore (4, 4)
	261 #11 (4, 4)
	262 dload (4, 4)
	263 #5 (4, 4)
	264 dload (4, 4)
	265 #11 (4, 4)
	266 dload (4, 4)
	267 #11 (4, 4)
	268 dmul (4, 4)
	269 dadd (4, 4)
	270 dstore (4, 4)
	271 #5 (4, 4)
	272 iinc (4, 4)
	273 #10 (4, 4)
	274 -89 (4, 4)
	275 goto (4, 4)
	276 -30 (4, 4)
	278 aload (3, 1)
	279 #9 (3, 1)
	280 iload_3 (3, 1)
	281 daload (3, 1)
	282 dconst_0 (3, 1)
	283 dcmpl (3, 1)
	284 ifle (3, 1)
	285 12 (3, 1)
	287 dload (3, 1)
	288 #5 (3, 1)
	289 invokestatic (3, 1)
	290 org/apache/commons/math3/util/FastMath.sqrt:(D)D (3, 1)
	292 dneg (3, 1)
	293 goto (3, 1)
	294 8 (3, 1)
	296 dload (3, 1)
	297 #5 (3, 1)
	298 invokestatic (3, 1)
	299 org/apache/commons/math3/util/FastMath.sqrt:(D)D (3, 1)
	301 dstore (3, 1)
	302 #10 (3, 1)
	303 aload_0 (3, 1)
	304 getfield (3, 1)
	305 org/apache/commons/math3/linear/BiDiagonalTransformer.secondary:[D (3, 1)
	307 iload_3 (3, 1)
	308 dload (3, 1)
	309 #10 (3, 1)
	310 dastore (3, 1)
	311 dload (4, 1)
	312 #10 (4, 1)
	313 dconst_0 (4, 1)
	314 dcmpl (4, 1)
	315 ifeq (4, 1)
	316 126 (4, 1)
	318 aload (4, 1)
	319 #9 (4, 1)
	320 iload_3 (4, 1)
	321 dup2 (4, 1)
	322 daload (4, 1)
	323 dload (4, 1)
	324 #10 (4, 1)
	325 dsub (4, 1)
	326 dastore (4, 1)
	327 iload_3 (5, 4)
	328 iconst_1 (5, 4)
	329 iadd (5, 4)
	330 istore (5, 4)
	331 #12 (5, 4)
	332 iload (5, 4)
	333 #12 (5, 4)
	334 iload_2 (5, 4)
	335 if_icmpge (5, 4)
	336 106 (5, 4)
	338 dconst_0 (5, 4)
	339 dstore (5, 4)
	340 #13 (5, 4)
	341 iload_3 (6, 4)
	342 iconst_1 (6, 4)
	343 iadd (6, 4)
	344 istore (6, 4)
	345 #15 (6, 4)
	346 iload (6, 4)
	347 #15 (6, 4)
	348 iload_1 (6, 4)
	349 if_icmpge (6, 4)
	350 33 (6, 4)
	352 aload_0 (6, 4)
	353 getfield (6, 4)
	354 org/apache/commons/math3/linear/BiDiagonalTransformer.householderVectors:[[D (6, 4)
	356 iload (6, 4)
	357 #15 (6, 4)
	358 aaload (6, 4)
	359 astore (6, 4)
	360 #16 (6, 4)
	361 dload (6, 4)
	362 #13 (6, 4)
	363 aload (6, 4)
	364 #16 (6, 4)
	365 iload (6, 4)
	366 #12 (6, 4)
	367 daload (6, 4)
	368 aload (6, 4)
	369 #16 (6, 4)
	370 iload_3 (6, 4)
	371 daload (6, 4)
	372 dmul (6, 4)
	373 dsub (6, 4)
	374 dstore (6, 4)
	375 #13 (6, 4)
	376 iinc (6, 4)
	377 #15 (6, 4)
	378 -89 (6, 4)
	379 goto (6, 4)
	380 -33 (6, 4)
	382 dload (5, 4)
	383 #13 (5, 4)
	384 dload (5, 4)
	385 #10 (5, 4)
	386 aload (5, 4)
	387 #9 (5, 4)
	388 iload_3 (5, 4)
	389 daload (5, 4)
	390 dmul (5, 4)
	391 ddiv (5, 4)
	392 dstore (5, 4)
	393 #13 (5, 4)
	394 iload_3 (6, 4)
	395 iconst_1 (6, 4)
	396 iadd (6, 4)
	397 istore (6, 4)
	398 #15 (6, 4)
	399 iload (6, 4)
	400 #15 (6, 4)
	401 iload_1 (6, 4)
	402 if_icmpge (6, 4)
	403 33 (6, 4)
	405 aload_0 (6, 4)
	406 getfield (6, 4)
	407 org/apache/commons/math3/linear/BiDiagonalTransformer.householderVectors:[[D (6, 4)
	409 iload (6, 4)
	410 #15 (6, 4)
	411 aaload (6, 4)
	412 astore (6, 4)
	413 #16 (6, 4)
	414 aload (6, 4)
	415 #16 (6, 4)
	416 iload (6, 4)
	417 #12 (6, 4)
	418 dup2 (6, 4)
	419 daload (6, 4)
	420 dload (6, 4)
	421 #13 (6, 4)
	422 aload (6, 4)
	423 #16 (6, 4)
	424 iload_3 (6, 4)
	425 daload (6, 4)
	426 dmul (6, 4)
	427 dsub (6, 4)
	428 dastore (6, 4)
	429 iinc (6, 4)
	430 #15 (6, 4)
	431 -89 (6, 4)
	432 goto (6, 4)
	433 -33 (6, 4)
	435 iinc (6, 4)
	436 #12 (6, 4)
	437 -89 (6, 4)
	438 goto (6, 4)
	439 -106 (6, 4)
	441 iinc (6, 4)
	442 #3 (6, 4)
	443 -89 (6, 4)
	444 goto (6, 4)
	445 -428 (6, 4)
	447 return (4, 1)

