Method: <init>
	0 aload_0 (0, 0)
	1 aload_3 (0, 0)
	2 invokestatic (0, 0)
	3 org/apache/commons/math3/linear/BlockFieldMatrix.extractField:([[Lorg/apache/commons/math3/FieldElement;)Lorg/apache/commons/math3/Field; (0, 0)
	5 iload_1 (0, 0)
	6 iload_2 (0, 0)
	7 invokespecial (0, 0)
	8 org/apache/commons/math3/linear/AbstractFieldMatrix.<init>:(Lorg/apache/commons/math3/Field;II)V (0, 0)
	10 aload_0 (0, 0)
	11 iload_1 (0, 0)
	12 putfield (0, 0)
	13 org/apache/commons/math3/linear/BlockFieldMatrix.rows:I (0, 0)
	15 aload_0 (0, 0)
	16 iload_2 (0, 0)
	17 putfield (0, 0)
	18 org/apache/commons/math3/linear/BlockFieldMatrix.columns:I (0, 0)
	20 aload_0 (0, 0)
	21 iload_1 (0, 0)
	22 bipush (0, 0)
	23 36 (0, 0)
	24 iadd (0, 0)
	25 iconst_1 (0, 0)
	26 isub (0, 0)
	27 bipush (0, 0)
	28 36 (0, 0)
	29 idiv (0, 0)
	30 putfield (0, 0)
	31 org/apache/commons/math3/linear/BlockFieldMatrix.blockRows:I (0, 0)
	33 aload_0 (0, 0)
	34 iload_2 (0, 0)
	35 bipush (0, 0)
	36 36 (0, 0)
	37 iadd (0, 0)
	38 iconst_1 (0, 0)
	39 isub (0, 0)
	40 bipush (0, 0)
	41 36 (0, 0)
	42 idiv (0, 0)
	43 putfield (0, 0)
	44 org/apache/commons/math3/linear/BlockFieldMatrix.blockColumns:I (0, 0)
	46 iload (1, 1)
	47 #4 (1, 1)
	48 ifeq (1, 1)
	49 30 (1, 1)
	51 aload_0 (1, 1)
	52 aload_0 (1, 1)
	53 invokevirtual (1, 1)
	54 org/apache/commons/math3/linear/BlockFieldMatrix.getField:()Lorg/apache/commons/math3/Field; (1, 1)
	56 aload_0 (1, 1)
	57 getfield (1, 1)
	58 org/apache/commons/math3/linear/BlockFieldMatrix.blockRows:I (1, 1)
	60 aload_0 (1, 1)
	61 getfield (1, 1)
	62 org/apache/commons/math3/linear/BlockFieldMatrix.blockColumns:I (1, 1)
	64 imul (1, 1)
	65 iconst_m1 (1, 1)
	66 invokestatic (1, 1)
	67 org/apache/commons/math3/util/MathArrays.buildArray:(Lorg/apache/commons/math3/Field;II)[[Ljava/lang/Object; (1, 1)
	69 checkcast (1, 1)
	70 [[Lorg/apache/commons/math3/FieldElement; (1, 1)
	72 putfield (1, 1)
	73 org/apache/commons/math3/linear/BlockFieldMatrix.blocks:[[Lorg/apache/commons/math3/FieldElement; (1, 1)
	75 goto (1, 1)
	76 8 (1, 1)
	78 aload_0 (2, 2)
	79 aload_3 (2, 2)
	80 putfield (2, 2)
	81 org/apache/commons/math3/linear/BlockFieldMatrix.blocks:[[Lorg/apache/commons/math3/FieldElement; (2, 2)
	83 iconst_0 (0, 0)
	84 istore (0, 0)
	85 #5 (0, 0)
	86 iconst_0 (1, 4)
	87 istore (1, 4)
	88 #6 (1, 4)
	89 iload (1, 4)
	90 #6 (1, 4)
	91 aload_0 (1, 4)
	92 getfield (1, 4)
	93 org/apache/commons/math3/linear/BlockFieldMatrix.blockRows:I (1, 4)
	95 if_icmpge (1, 4)
	96 99 (1, 4)
	98 aload_0 (1, 4)
	99 iload (1, 4)
	100 #6 (1, 4)
	101 invokespecial (1, 4)
	102 org/apache/commons/math3/linear/BlockFieldMatrix.blockHeight:(I)I (1, 4)
	104 istore (1, 4)
	105 #7 (1, 4)
	106 iconst_0 (2, 4)
	107 istore (2, 4)
	108 #8 (2, 4)
	109 iload (2, 4)
	110 #8 (2, 4)
	111 aload_0 (2, 4)
	112 getfield (2, 4)
	113 org/apache/commons/math3/linear/BlockFieldMatrix.blockColumns:I (2, 4)
	115 if_icmpge (2, 4)
	116 73 (2, 4)
	118 aload_3 (3, 1)
	119 iload (3, 1)
	120 #5 (3, 1)
	121 aaload (3, 1)
	122 arraylength (3, 1)
	123 iload (3, 1)
	124 #7 (3, 1)
	125 aload_0 (3, 1)
	126 iload (3, 1)
	127 #8 (3, 1)
	128 invokespecial (3, 1)
	129 org/apache/commons/math3/linear/BlockFieldMatrix.blockWidth:(I)I (3, 1)
	131 imul (3, 1)
	132 if_icmpeq (3, 1)
	133 25 (3, 1)
	135 new (3, 1)
	136 org/apache/commons/math3/exception/DimensionMismatchException (3, 1)
	138 dup (3, 1)
	139 aload_3 (3, 1)
	140 iload (3, 1)
	141 #5 (3, 1)
	142 aaload (3, 1)
	143 arraylength (3, 1)
	144 iload (3, 1)
	145 #7 (3, 1)
	146 aload_0 (3, 1)
	147 iload (3, 1)
	148 #8 (3, 1)
	149 invokespecial (3, 1)
	150 org/apache/commons/math3/linear/BlockFieldMatrix.blockWidth:(I)I (3, 1)
	152 imul (3, 1)
	153 invokespecial (3, 1)
	154 org/apache/commons/math3/exception/DimensionMismatchException.<init>:(II)V (3, 1)
	156 athrow (3, 1)
	157 iload (3, 1)
	158 #4 (3, 1)
	159 ifeq (3, 1)
	160 20 (3, 1)
	162 aload_0 (3, 1)
	163 getfield (3, 1)
	164 org/apache/commons/math3/linear/BlockFieldMatrix.blocks:[[Lorg/apache/commons/math3/FieldElement; (3, 1)
	166 iload (3, 1)
	167 #5 (3, 1)
	168 aload_3 (3, 1)
	169 iload (3, 1)
	170 #5 (3, 1)
	171 aaload (3, 1)
	172 invokevirtual (3, 1)
	173 [Lorg/apache/commons/math3/FieldElement;.clone:()Ljava/lang/Object; (3, 1)
	175 checkcast (3, 1)
	176 [Lorg/apache/commons/math3/FieldElement; (3, 1)
	178 aastore (3, 1)
	179 iinc (3, 1)
	180 #8 (3, 1)
	181 -124 (3, 1)
	182 iinc (3, 1)
	183 #5 (3, 1)
	184 -89 (3, 1)
	185 goto (3, 1)
	186 -76 (3, 1)
	188 iinc (3, 1)
	189 #6 (3, 1)
	190 -89 (3, 1)
	191 goto (3, 1)
	192 -102 (3, 1)
	194 return (1, 4)

Method: toBlocksLayout
	0 aload_0 (0, 0)
	1 arraylength (0, 0)
	2 istore_1 (0, 0)
	3 aload_0 (0, 0)
	4 iconst_0 (0, 0)
	5 aaload (0, 0)
	6 arraylength (0, 0)
	7 istore_2 (0, 0)
	8 iload_1 (0, 0)
	9 bipush (0, 0)
	10 36 (0, 0)
	11 iadd (0, 0)
	12 iconst_1 (0, 0)
	13 isub (0, 0)
	14 bipush (0, 0)
	15 36 (0, 0)
	16 idiv (0, 0)
	17 istore_3 (0, 0)
	18 iload_2 (0, 0)
	19 bipush (0, 0)
	20 36 (0, 0)
	21 iadd (0, 0)
	22 iconst_1 (0, 0)
	23 isub (0, 0)
	24 bipush (0, 0)
	25 36 (0, 0)
	26 idiv (0, 0)
	27 istore (0, 0)
	28 #4 (0, 0)
	29 iconst_0 (1, 4)
	30 istore (1, 4)
	31 #5 (1, 4)
	32 iload (1, 4)
	33 #5 (1, 4)
	34 aload_0 (1, 4)
	35 arraylength (1, 4)
	36 if_icmpge (1, 4)
	37 33 (1, 4)
	39 aload_0 (1, 4)
	40 iload (1, 4)
	41 #5 (1, 4)
	42 aaload (1, 4)
	43 arraylength (1, 4)
	44 istore (1, 4)
	45 #6 (1, 4)
	46 iload (2, 1)
	47 #6 (2, 1)
	48 iload_2 (2, 1)
	49 if_icmpeq (2, 1)
	50 14 (2, 1)
	52 new (2, 1)
	53 org/apache/commons/math3/exception/DimensionMismatchException (2, 1)
	55 dup (2, 1)
	56 iload_2 (2, 1)
	57 iload (2, 1)
	58 #6 (2, 1)
	59 invokespecial (2, 1)
	60 org/apache/commons/math3/exception/DimensionMismatchException.<init>:(II)V (2, 1)
	62 athrow (2, 1)
	63 iinc (2, 1)
	64 #5 (2, 1)
	65 -89 (2, 1)
	66 goto (2, 1)
	67 -34 (2, 1)
	69 aload_0 (1, 4)
	70 invokestatic (1, 4)
	71 org/apache/commons/math3/linear/BlockFieldMatrix.extractField:([[Lorg/apache/commons/math3/FieldElement;)Lorg/apache/commons/math3/Field; (1, 4)
	73 astore (1, 4)
	74 #5 (1, 4)
	75 aload (1, 4)
	76 #5 (1, 4)
	77 iload_3 (1, 4)
	78 iload (1, 4)
	79 #4 (1, 4)
	80 imul (1, 4)
	81 iconst_m1 (1, 4)
	82 invokestatic (1, 4)
	83 org/apache/commons/math3/util/MathArrays.buildArray:(Lorg/apache/commons/math3/Field;II)[[Ljava/lang/Object; (1, 4)
	85 checkcast (1, 4)
	86 [[Lorg/apache/commons/math3/FieldElement; (1, 4)
	88 astore (1, 4)
	89 #6 (1, 4)
	90 iconst_0 (1, 4)
	91 istore (1, 4)
	92 #7 (1, 4)
	93 iconst_0 (2, 4)
	94 istore (2, 4)
	95 #8 (2, 4)
	96 iload (2, 4)
	97 #8 (2, 4)
	98 iload_3 (2, 4)
	99 if_icmpge (2, 4)
	100 142 (2, 4)
	102 iload (2, 4)
	103 #8 (2, 4)
	104 bipush (2, 4)
	105 36 (2, 4)
	106 imul (2, 4)
	107 istore (2, 4)
	108 #9 (2, 4)
	109 iload (2, 4)
	110 #9 (2, 4)
	111 bipush (2, 4)
	112 36 (2, 4)
	113 iadd (2, 4)
	114 iload_1 (2, 4)
	115 invokestatic (2, 4)
	116 org/apache/commons/math3/util/FastMath.min:(II)I (2, 4)
	118 istore (2, 4)
	119 #10 (2, 4)
	120 iload (2, 4)
	121 #10 (2, 4)
	122 iload (2, 4)
	123 #9 (2, 4)
	124 isub (2, 4)
	125 istore (2, 4)
	126 #11 (2, 4)
	127 iconst_0 (3, 4)
	128 istore (3, 4)
	129 #12 (3, 4)
	130 iload (3, 4)
	131 #12 (3, 4)
	132 iload (3, 4)
	133 #4 (3, 4)
	134 if_icmpge (3, 4)
	135 101 (3, 4)
	137 iload (3, 4)
	138 #12 (3, 4)
	139 bipush (3, 4)
	140 36 (3, 4)
	141 imul (3, 4)
	142 istore (3, 4)
	143 #13 (3, 4)
	144 iload (3, 4)
	145 #13 (3, 4)
	146 bipush (3, 4)
	147 36 (3, 4)
	148 iadd (3, 4)
	149 iload_2 (3, 4)
	150 invokestatic (3, 4)
	151 org/apache/commons/math3/util/FastMath.min:(II)I (3, 4)
	153 istore (3, 4)
	154 #14 (3, 4)
	155 iload (3, 4)
	156 #14 (3, 4)
	157 iload (3, 4)
	158 #13 (3, 4)
	159 isub (3, 4)
	160 istore (3, 4)
	161 #15 (3, 4)
	162 aload (3, 4)
	163 #5 (3, 4)
	164 iload (3, 4)
	165 #11 (3, 4)
	166 iload (3, 4)
	167 #15 (3, 4)
	168 imul (3, 4)
	169 invokestatic (3, 4)
	170 org/apache/commons/math3/util/MathArrays.buildArray:(Lorg/apache/commons/math3/Field;I)[Ljava/lang/Object; (3, 4)
	172 checkcast (3, 4)
	173 [Lorg/apache/commons/math3/FieldElement; (3, 4)
	175 astore (3, 4)
	176 #16 (3, 4)
	177 aload (3, 4)
	178 #6 (3, 4)
	179 iload (3, 4)
	180 #7 (3, 4)
	181 aload (3, 4)
	182 #16 (3, 4)
	183 aastore (3, 4)
	184 iconst_0 (3, 4)
	185 istore (3, 4)
	186 #17 (3, 4)
	187 iload (4, 4)
	188 #9 (4, 4)
	189 istore (4, 4)
	190 #18 (4, 4)
	191 iload (4, 4)
	192 #18 (4, 4)
	193 iload (4, 4)
	194 #10 (4, 4)
	195 if_icmpge (4, 4)
	196 31 (4, 4)
	198 aload_0 (4, 4)
	199 iload (4, 4)
	200 #18 (4, 4)
	201 aaload (4, 4)
	202 iload (4, 4)
	203 #13 (4, 4)
	204 aload (4, 4)
	205 #16 (4, 4)
	206 iload (4, 4)
	207 #17 (4, 4)
	208 iload (4, 4)
	209 #15 (4, 4)
	210 invokestatic (4, 4)
	211 java/lang/System.arraycopy:(Ljava/lang/Object;ILjava/lang/Object;II)V (4, 4)
	213 iload (4, 4)
	214 #17 (4, 4)
	215 iload (4, 4)
	216 #15 (4, 4)
	217 iadd (4, 4)
	218 istore (4, 4)
	219 #17 (4, 4)
	220 iinc (4, 4)
	221 #18 (4, 4)
	222 -89 (4, 4)
	223 goto (4, 4)
	224 -32 (4, 4)
	226 iinc (3, 4)
	227 #7 (3, 4)
	228 -124 (3, 4)
	229 iinc (3, 4)
	230 #12 (3, 4)
	231 -89 (3, 4)
	232 goto (3, 4)
	233 -102 (3, 4)
	235 iinc (3, 4)
	236 #8 (3, 4)
	237 -89 (3, 4)
	238 goto (3, 4)
	239 -142 (3, 4)
	241 aload (2, 4)
	242 #6 (2, 4)
	243 areturn (2, 4)

Method: createBlocksLayout
	0 iload_1 (0, 0)
	1 bipush (0, 0)
	2 36 (0, 0)
	3 iadd (0, 0)
	4 iconst_1 (0, 0)
	5 isub (0, 0)
	6 bipush (0, 0)
	7 36 (0, 0)
	8 idiv (0, 0)
	9 istore_3 (0, 0)
	10 iload_2 (0, 0)
	11 bipush (0, 0)
	12 36 (0, 0)
	13 iadd (0, 0)
	14 iconst_1 (0, 0)
	15 isub (0, 0)
	16 bipush (0, 0)
	17 36 (0, 0)
	18 idiv (0, 0)
	19 istore (0, 0)
	20 #4 (0, 0)
	21 aload_0 (0, 0)
	22 iload_3 (0, 0)
	23 iload (0, 0)
	24 #4 (0, 0)
	25 imul (0, 0)
	26 iconst_m1 (0, 0)
	27 invokestatic (0, 0)
	28 org/apache/commons/math3/util/MathArrays.buildArray:(Lorg/apache/commons/math3/Field;II)[[Ljava/lang/Object; (0, 0)
	30 checkcast (0, 0)
	31 [[Lorg/apache/commons/math3/FieldElement; (0, 0)
	33 astore (0, 0)
	34 #5 (0, 0)
	35 iconst_0 (0, 0)
	36 istore (0, 0)
	37 #6 (0, 0)
	38 iconst_0 (1, 4)
	39 istore (1, 4)
	40 #7 (1, 4)
	41 iload (1, 4)
	42 #7 (1, 4)
	43 iload_3 (1, 4)
	44 if_icmpge (1, 4)
	45 95 (1, 4)
	47 iload (1, 4)
	48 #7 (1, 4)
	49 bipush (1, 4)
	50 36 (1, 4)
	51 imul (1, 4)
	52 istore (1, 4)
	53 #8 (1, 4)
	54 iload (1, 4)
	55 #8 (1, 4)
	56 bipush (1, 4)
	57 36 (1, 4)
	58 iadd (1, 4)
	59 iload_1 (1, 4)
	60 invokestatic (1, 4)
	61 org/apache/commons/math3/util/FastMath.min:(II)I (1, 4)
	63 istore (1, 4)
	64 #9 (1, 4)
	65 iload (1, 4)
	66 #9 (1, 4)
	67 iload (1, 4)
	68 #8 (1, 4)
	69 isub (1, 4)
	70 istore (1, 4)
	71 #10 (1, 4)
	72 iconst_0 (2, 4)
	73 istore (2, 4)
	74 #11 (2, 4)
	75 iload (2, 4)
	76 #11 (2, 4)
	77 iload (2, 4)
	78 #4 (2, 4)
	79 if_icmpge (2, 4)
	80 54 (2, 4)
	82 iload (2, 4)
	83 #11 (2, 4)
	84 bipush (2, 4)
	85 36 (2, 4)
	86 imul (2, 4)
	87 istore (2, 4)
	88 #12 (2, 4)
	89 iload (2, 4)
	90 #12 (2, 4)
	91 bipush (2, 4)
	92 36 (2, 4)
	93 iadd (2, 4)
	94 iload_2 (2, 4)
	95 invokestatic (2, 4)
	96 org/apache/commons/math3/util/FastMath.min:(II)I (2, 4)
	98 istore (2, 4)
	99 #13 (2, 4)
	100 iload (2, 4)
	101 #13 (2, 4)
	102 iload (2, 4)
	103 #12 (2, 4)
	104 isub (2, 4)
	105 istore (2, 4)
	106 #14 (2, 4)
	107 aload (2, 4)
	108 #5 (2, 4)
	109 iload (2, 4)
	110 #6 (2, 4)
	111 aload_0 (2, 4)
	112 iload (2, 4)
	113 #10 (2, 4)
	114 iload (2, 4)
	115 #14 (2, 4)
	116 imul (2, 4)
	117 invokestatic (2, 4)
	118 org/apache/commons/math3/util/MathArrays.buildArray:(Lorg/apache/commons/math3/Field;I)[Ljava/lang/Object; (2, 4)
	120 checkcast (2, 4)
	121 [Lorg/apache/commons/math3/FieldElement; (2, 4)
	123 aastore (2, 4)
	124 iinc (2, 4)
	125 #6 (2, 4)
	126 -124 (2, 4)
	127 iinc (2, 4)
	128 #11 (2, 4)
	129 -89 (2, 4)
	130 goto (2, 4)
	131 -55 (2, 4)
	133 iinc (2, 4)
	134 #7 (2, 4)
	135 -89 (2, 4)
	136 goto (2, 4)
	137 -95 (2, 4)
	139 aload (1, 4)
	140 #5 (1, 4)
	141 areturn (1, 4)

Method: createMatrix
	0 new (0, 0)
	1 org/apache/commons/math3/linear/BlockFieldMatrix (0, 0)
	3 dup (0, 0)
	4 aload_0 (0, 0)
	5 invokevirtual (0, 0)
	6 org/apache/commons/math3/linear/BlockFieldMatrix.getField:()Lorg/apache/commons/math3/Field; (0, 0)
	8 iload_1 (0, 0)
	9 iload_2 (0, 0)
	10 invokespecial (0, 0)
	11 org/apache/commons/math3/linear/BlockFieldMatrix.<init>:(Lorg/apache/commons/math3/Field;II)V (0, 0)
	13 areturn (0, 0)

Method: copy
	0 new (0, 0)
	1 org/apache/commons/math3/linear/BlockFieldMatrix (0, 0)
	3 dup (0, 0)
	4 aload_0 (0, 0)
	5 invokevirtual (0, 0)
	6 org/apache/commons/math3/linear/BlockFieldMatrix.getField:()Lorg/apache/commons/math3/Field; (0, 0)
	8 aload_0 (0, 0)
	9 getfield (0, 0)
	10 org/apache/commons/math3/linear/BlockFieldMatrix.rows:I (0, 0)
	12 aload_0 (0, 0)
	13 getfield (0, 0)
	14 org/apache/commons/math3/linear/BlockFieldMatrix.columns:I (0, 0)
	16 invokespecial (0, 0)
	17 org/apache/commons/math3/linear/BlockFieldMatrix.<init>:(Lorg/apache/commons/math3/Field;II)V (0, 0)
	19 astore_1 (0, 0)
	20 iconst_0 (1, 4)
	21 istore_2 (1, 4)
	22 iload_2 (1, 4)
	23 aload_0 (1, 4)
	24 getfield (1, 4)
	25 org/apache/commons/math3/linear/BlockFieldMatrix.blocks:[[Lorg/apache/commons/math3/FieldElement; (1, 4)
	27 arraylength (1, 4)
	28 if_icmpge (1, 4)
	29 33 (1, 4)
	31 aload_0 (1, 4)
	32 getfield (1, 4)
	33 org/apache/commons/math3/linear/BlockFieldMatrix.blocks:[[Lorg/apache/commons/math3/FieldElement; (1, 4)
	35 iload_2 (1, 4)
	36 aaload (1, 4)
	37 iconst_0 (1, 4)
	38 aload_1 (1, 4)
	39 getfield (1, 4)
	40 org/apache/commons/math3/linear/BlockFieldMatrix.blocks:[[Lorg/apache/commons/math3/FieldElement; (1, 4)
	42 iload_2 (1, 4)
	43 aaload (1, 4)
	44 iconst_0 (1, 4)
	45 aload_0 (1, 4)
	46 getfield (1, 4)
	47 org/apache/commons/math3/linear/BlockFieldMatrix.blocks:[[Lorg/apache/commons/math3/FieldElement; (1, 4)
	49 iload_2 (1, 4)
	50 aaload (1, 4)
	51 arraylength (1, 4)
	52 invokestatic (1, 4)
	53 java/lang/System.arraycopy:(Ljava/lang/Object;ILjava/lang/Object;II)V (1, 4)
	55 iinc (1, 4)
	56 #2 (1, 4)
	57 -89 (1, 4)
	58 goto (1, 4)
	59 -36 (1, 4)
	61 aload_1 (0, 0)
	62 areturn (0, 0)

Method: add
	0 aload_0 (0, 0)
	1 aload_1 (0, 0)
	2 invokevirtual (0, 0)
	3 org/apache/commons/math3/linear/BlockFieldMatrix.checkAdditionCompatible:(Lorg/apache/commons/math3/linear/FieldMatrix;)V (0, 0)
	5 new (0, 0)
	6 org/apache/commons/math3/linear/BlockFieldMatrix (0, 0)
	8 dup (0, 0)
	9 aload_0 (0, 0)
	10 invokevirtual (0, 0)
	11 org/apache/commons/math3/linear/BlockFieldMatrix.getField:()Lorg/apache/commons/math3/Field; (0, 0)
	13 aload_0 (0, 0)
	14 getfield (0, 0)
	15 org/apache/commons/math3/linear/BlockFieldMatrix.rows:I (0, 0)
	17 aload_0 (0, 0)
	18 getfield (0, 0)
	19 org/apache/commons/math3/linear/BlockFieldMatrix.columns:I (0, 0)
	21 invokespecial (0, 0)
	22 org/apache/commons/math3/linear/BlockFieldMatrix.<init>:(Lorg/apache/commons/math3/Field;II)V (0, 0)
	24 astore_2 (0, 0)
	25 iconst_0 (2, 4)
	26 istore_3 (2, 4)
	27 iload_3 (2, 4)
	28 aload_2 (2, 4)
	29 getfield (2, 4)
	30 org/apache/commons/math3/linear/BlockFieldMatrix.blocks:[[Lorg/apache/commons/math3/FieldElement; (2, 4)
	32 arraylength (2, 4)
	33 if_icmpge (2, 4)
	34 73 (2, 4)
	36 aload_2 (2, 4)
	37 getfield (2, 4)
	38 org/apache/commons/math3/linear/BlockFieldMatrix.blocks:[[Lorg/apache/commons/math3/FieldElement; (2, 4)
	40 iload_3 (2, 4)
	41 aaload (2, 4)
	42 astore (2, 4)
	43 #4 (2, 4)
	44 aload_0 (2, 4)
	45 getfield (2, 4)
	46 org/apache/commons/math3/linear/BlockFieldMatrix.blocks:[[Lorg/apache/commons/math3/FieldElement; (2, 4)
	48 iload_3 (2, 4)
	49 aaload (2, 4)
	50 astore (2, 4)
	51 #5 (2, 4)
	52 aload_1 (2, 4)
	53 getfield (2, 4)
	54 org/apache/commons/math3/linear/BlockFieldMatrix.blocks:[[Lorg/apache/commons/math3/FieldElement; (2, 4)
	56 iload_3 (2, 4)
	57 aaload (2, 4)
	58 astore (2, 4)
	59 #6 (2, 4)
	60 iconst_0 (3, 4)
	61 istore (3, 4)
	62 #7 (3, 4)
	63 iload (3, 4)
	64 #7 (3, 4)
	65 aload (3, 4)
	66 #4 (3, 4)
	67 arraylength (3, 4)
	68 if_icmpge (3, 4)
	69 32 (3, 4)
	71 aload (3, 4)
	72 #4 (3, 4)
	73 iload (3, 4)
	74 #7 (3, 4)
	75 aload (3, 4)
	76 #5 (3, 4)
	77 iload (3, 4)
	78 #7 (3, 4)
	79 aaload (3, 4)
	80 aload (3, 4)
	81 #6 (3, 4)
	82 iload (3, 4)
	83 #7 (3, 4)
	84 aaload (3, 4)
	85 invokeinterface (3, 4)
	86 org/apache/commons/math3/FieldElement.org/apache/commons/math3/FieldElement (3, 4)
	88 0 (3, 4)
	90 checkcast (3, 4)
	91 org/apache/commons/math3/FieldElement (3, 4)
	93 aastore (3, 4)
	94 iinc (3, 4)
	95 #7 (3, 4)
	96 -89 (3, 4)
	97 goto (3, 4)
	98 -34 (3, 4)
	100 iinc (3, 4)
	101 #3 (3, 4)
	102 -89 (3, 4)
	103 goto (3, 4)
	104 -76 (3, 4)
	106 aload_2 (2, 4)
	107 areturn (1, 4)

Method: subtract
	0 aload_0 (0, 0)
	1 aload_1 (0, 0)
	2 invokevirtual (0, 0)
	3 org/apache/commons/math3/linear/BlockFieldMatrix.checkSubtractionCompatible:(Lorg/apache/commons/math3/linear/FieldMatrix;)V (0, 0)
	5 new (0, 0)
	6 org/apache/commons/math3/linear/BlockFieldMatrix (0, 0)
	8 dup (0, 0)
	9 aload_0 (0, 0)
	10 invokevirtual (0, 0)
	11 org/apache/commons/math3/linear/BlockFieldMatrix.getField:()Lorg/apache/commons/math3/Field; (0, 0)
	13 aload_0 (0, 0)
	14 getfield (0, 0)
	15 org/apache/commons/math3/linear/BlockFieldMatrix.rows:I (0, 0)
	17 aload_0 (0, 0)
	18 getfield (0, 0)
	19 org/apache/commons/math3/linear/BlockFieldMatrix.columns:I (0, 0)
	21 invokespecial (0, 0)
	22 org/apache/commons/math3/linear/BlockFieldMatrix.<init>:(Lorg/apache/commons/math3/Field;II)V (0, 0)
	24 astore_2 (0, 0)
	25 iconst_0 (2, 4)
	26 istore_3 (2, 4)
	27 iload_3 (2, 4)
	28 aload_2 (2, 4)
	29 getfield (2, 4)
	30 org/apache/commons/math3/linear/BlockFieldMatrix.blocks:[[Lorg/apache/commons/math3/FieldElement; (2, 4)
	32 arraylength (2, 4)
	33 if_icmpge (2, 4)
	34 73 (2, 4)
	36 aload_2 (2, 4)
	37 getfield (2, 4)
	38 org/apache/commons/math3/linear/BlockFieldMatrix.blocks:[[Lorg/apache/commons/math3/FieldElement; (2, 4)
	40 iload_3 (2, 4)
	41 aaload (2, 4)
	42 astore (2, 4)
	43 #4 (2, 4)
	44 aload_0 (2, 4)
	45 getfield (2, 4)
	46 org/apache/commons/math3/linear/BlockFieldMatrix.blocks:[[Lorg/apache/commons/math3/FieldElement; (2, 4)
	48 iload_3 (2, 4)
	49 aaload (2, 4)
	50 astore (2, 4)
	51 #5 (2, 4)
	52 aload_1 (2, 4)
	53 getfield (2, 4)
	54 org/apache/commons/math3/linear/BlockFieldMatrix.blocks:[[Lorg/apache/commons/math3/FieldElement; (2, 4)
	56 iload_3 (2, 4)
	57 aaload (2, 4)
	58 astore (2, 4)
	59 #6 (2, 4)
	60 iconst_0 (3, 4)
	61 istore (3, 4)
	62 #7 (3, 4)
	63 iload (3, 4)
	64 #7 (3, 4)
	65 aload (3, 4)
	66 #4 (3, 4)
	67 arraylength (3, 4)
	68 if_icmpge (3, 4)
	69 32 (3, 4)
	71 aload (3, 4)
	72 #4 (3, 4)
	73 iload (3, 4)
	74 #7 (3, 4)
	75 aload (3, 4)
	76 #5 (3, 4)
	77 iload (3, 4)
	78 #7 (3, 4)
	79 aaload (3, 4)
	80 aload (3, 4)
	81 #6 (3, 4)
	82 iload (3, 4)
	83 #7 (3, 4)
	84 aaload (3, 4)
	85 invokeinterface (3, 4)
	86 org/apache/commons/math3/FieldElement.multiply:(Ljava/lang/Object;)Ljava/lang/Object; (3, 4)
	88 0 (3, 4)
	90 checkcast (3, 4)
	91 org/apache/commons/math3/FieldElement (3, 4)
	93 aastore (3, 4)
	94 iinc (3, 4)
	95 #7 (3, 4)
	96 -89 (3, 4)
	97 goto (3, 4)
	98 -34 (3, 4)
	100 iinc (3, 4)
	101 #3 (3, 4)
	102 -89 (3, 4)
	103 goto (3, 4)
	104 -76 (3, 4)
	106 aload_2 (2, 4)
	107 areturn (1, 4)

Method: scalarAdd
	0 new (0, 0)
	1 org/apache/commons/math3/linear/BlockFieldMatrix (0, 0)
	3 dup (0, 0)
	4 aload_0 (0, 0)
	5 invokevirtual (0, 0)
	6 org/apache/commons/math3/linear/BlockFieldMatrix.getField:()Lorg/apache/commons/math3/Field; (0, 0)
	8 aload_0 (0, 0)
	9 getfield (0, 0)
	10 org/apache/commons/math3/linear/BlockFieldMatrix.rows:I (0, 0)
	12 aload_0 (0, 0)
	13 getfield (0, 0)
	14 org/apache/commons/math3/linear/BlockFieldMatrix.columns:I (0, 0)
	16 invokespecial (0, 0)
	17 org/apache/commons/math3/linear/BlockFieldMatrix.<init>:(Lorg/apache/commons/math3/Field;II)V (0, 0)
	19 astore_2 (0, 0)
	20 iconst_0 (2, 4)
	21 istore_3 (2, 4)
	22 iload_3 (2, 4)
	23 aload_2 (2, 4)
	24 getfield (2, 4)
	25 org/apache/commons/math3/linear/BlockFieldMatrix.blocks:[[Lorg/apache/commons/math3/FieldElement; (2, 4)
	27 arraylength (2, 4)
	28 if_icmpge (2, 4)
	29 61 (2, 4)
	31 aload_2 (2, 4)
	32 getfield (2, 4)
	33 org/apache/commons/math3/linear/BlockFieldMatrix.blocks:[[Lorg/apache/commons/math3/FieldElement; (2, 4)
	35 iload_3 (2, 4)
	36 aaload (2, 4)
	37 astore (2, 4)
	38 #4 (2, 4)
	39 aload_0 (2, 4)
	40 getfield (2, 4)
	41 org/apache/commons/math3/linear/BlockFieldMatrix.blocks:[[Lorg/apache/commons/math3/FieldElement; (2, 4)
	43 iload_3 (2, 4)
	44 aaload (2, 4)
	45 astore (2, 4)
	46 #5 (2, 4)
	47 iconst_0 (3, 4)
	48 istore (3, 4)
	49 #6 (3, 4)
	50 iload (3, 4)
	51 #6 (3, 4)
	52 aload (3, 4)
	53 #4 (3, 4)
	54 arraylength (3, 4)
	55 if_icmpge (3, 4)
	56 28 (3, 4)
	58 aload (3, 4)
	59 #4 (3, 4)
	60 iload (3, 4)
	61 #6 (3, 4)
	62 aload (3, 4)
	63 #5 (3, 4)
	64 iload (3, 4)
	65 #6 (3, 4)
	66 aaload (3, 4)
	67 aload_1 (3, 4)
	68 invokeinterface (3, 4)
	69 org/apache/commons/math3/FieldElement.org/apache/commons/math3/FieldElement (3, 4)
	71 0 (3, 4)
	73 checkcast (3, 4)
	74 org/apache/commons/math3/FieldElement (3, 4)
	76 aastore (3, 4)
	77 iinc (3, 4)
	78 #6 (3, 4)
	79 -89 (3, 4)
	80 goto (3, 4)
	81 -30 (3, 4)
	83 iinc (3, 4)
	84 #3 (3, 4)
	85 -89 (3, 4)
	86 goto (3, 4)
	87 -64 (3, 4)
	89 aload_2 (2, 4)
	90 areturn (1, 4)

Method: scalarMultiply
	0 new (0, 0)
	1 org/apache/commons/math3/linear/BlockFieldMatrix (0, 0)
	3 dup (0, 0)
	4 aload_0 (0, 0)
	5 invokevirtual (0, 0)
	6 org/apache/commons/math3/linear/BlockFieldMatrix.getField:()Lorg/apache/commons/math3/Field; (0, 0)
	8 aload_0 (0, 0)
	9 getfield (0, 0)
	10 org/apache/commons/math3/linear/BlockFieldMatrix.rows:I (0, 0)
	12 aload_0 (0, 0)
	13 getfield (0, 0)
	14 org/apache/commons/math3/linear/BlockFieldMatrix.columns:I (0, 0)
	16 invokespecial (0, 0)
	17 org/apache/commons/math3/linear/BlockFieldMatrix.<init>:(Lorg/apache/commons/math3/Field;II)V (0, 0)
	19 astore_2 (0, 0)
	20 iconst_0 (2, 4)
	21 istore_3 (2, 4)
	22 iload_3 (2, 4)
	23 aload_2 (2, 4)
	24 getfield (2, 4)
	25 org/apache/commons/math3/linear/BlockFieldMatrix.blocks:[[Lorg/apache/commons/math3/FieldElement; (2, 4)
	27 arraylength (2, 4)
	28 if_icmpge (2, 4)
	29 61 (2, 4)
	31 aload_2 (2, 4)
	32 getfield (2, 4)
	33 org/apache/commons/math3/linear/BlockFieldMatrix.blocks:[[Lorg/apache/commons/math3/FieldElement; (2, 4)
	35 iload_3 (2, 4)
	36 aaload (2, 4)
	37 astore (2, 4)
	38 #4 (2, 4)
	39 aload_0 (2, 4)
	40 getfield (2, 4)
	41 org/apache/commons/math3/linear/BlockFieldMatrix.blocks:[[Lorg/apache/commons/math3/FieldElement; (2, 4)
	43 iload_3 (2, 4)
	44 aaload (2, 4)
	45 astore (2, 4)
	46 #5 (2, 4)
	47 iconst_0 (3, 4)
	48 istore (3, 4)
	49 #6 (3, 4)
	50 iload (3, 4)
	51 #6 (3, 4)
	52 aload (3, 4)
	53 #4 (3, 4)
	54 arraylength (3, 4)
	55 if_icmpge (3, 4)
	56 28 (3, 4)
	58 aload (3, 4)
	59 #4 (3, 4)
	60 iload (3, 4)
	61 #6 (3, 4)
	62 aload (3, 4)
	63 #5 (3, 4)
	64 iload (3, 4)
	65 #6 (3, 4)
	66 aaload (3, 4)
	67 aload_1 (3, 4)
	68 invokeinterface (3, 4)
	69 org/apache/commons/math3/FieldElement.multiply:(Lorg/apache/commons/math3/linear/BlockFieldMatrix;)Lorg/apache/commons/math3/linear/BlockFieldMatrix; (3, 4)
	71 0 (3, 4)
	73 checkcast (3, 4)
	74 org/apache/commons/math3/FieldElement (3, 4)
	76 aastore (3, 4)
	77 iinc (3, 4)
	78 #6 (3, 4)
	79 -89 (3, 4)
	80 goto (3, 4)
	81 -30 (3, 4)
	83 iinc (3, 4)
	84 #3 (3, 4)
	85 -89 (3, 4)
	86 goto (3, 4)
	87 -64 (3, 4)
	89 aload_2 (2, 4)
	90 areturn (1, 4)

Method: multiply
	0 aload_0 (0, 0)
	1 aload_1 (0, 0)
	2 invokevirtual (0, 0)
	3 org/apache/commons/math3/linear/BlockFieldMatrix.checkMultiplicationCompatible:(Lorg/apache/commons/math3/linear/FieldMatrix;)V (0, 0)
	5 new (0, 0)
	6 org/apache/commons/math3/linear/BlockFieldMatrix (0, 0)
	8 dup (0, 0)
	9 aload_0 (0, 0)
	10 invokevirtual (0, 0)
	11 org/apache/commons/math3/linear/BlockFieldMatrix.getField:()Lorg/apache/commons/math3/Field; (0, 0)
	13 aload_0 (0, 0)
	14 getfield (0, 0)
	15 org/apache/commons/math3/linear/BlockFieldMatrix.rows:I (0, 0)
	17 aload_1 (0, 0)
	18 getfield (0, 0)
	19 org/apache/commons/math3/linear/BlockFieldMatrix.columns:I (0, 0)
	21 invokespecial (0, 0)
	22 org/apache/commons/math3/linear/BlockFieldMatrix.<init>:(Lorg/apache/commons/math3/Field;II)V (0, 0)
	24 astore_2 (0, 0)
	25 aload_0 (0, 0)
	26 invokevirtual (0, 0)
	27 org/apache/commons/math3/linear/BlockFieldMatrix.getField:()Lorg/apache/commons/math3/Field; (0, 0)
	29 invokeinterface (0, 0)
	30 org/apache/commons/math3/Field.getRowDimension:()I (0, 0)
	32 0 (0, 0)
	34 checkcast (0, 0)
	35 org/apache/commons/math3/FieldElement (0, 0)
	37 astore_3 (0, 0)
	38 iconst_0 (1, 4)
	39 istore (1, 4)
	40 #4 (1, 4)
	41 iconst_0 (2, 4)
	42 istore (2, 4)
	43 #5 (2, 4)
	44 iload (2, 4)
	45 #5 (2, 4)
	46 aload_2 (2, 4)
	47 getfield (2, 4)
	48 org/apache/commons/math3/linear/BlockFieldMatrix.blockRows:I (2, 4)
	50 if_icmpge (2, 4)
	51 416 (2, 4)
	53 iload (2, 4)
	54 #5 (2, 4)
	55 bipush (2, 4)
	56 36 (2, 4)
	57 imul (2, 4)
	58 istore (2, 4)
	59 #6 (2, 4)
	60 iload (2, 4)
	61 #6 (2, 4)
	62 bipush (2, 4)
	63 36 (2, 4)
	64 iadd (2, 4)
	65 aload_0 (2, 4)
	66 getfield (2, 4)
	67 org/apache/commons/math3/linear/BlockFieldMatrix.rows:I (2, 4)
	69 invokestatic (2, 4)
	70 org/apache/commons/math3/util/FastMath.min:(II)I (2, 4)
	72 istore (2, 4)
	73 #7 (2, 4)
	74 iconst_0 (3, 4)
	75 istore (3, 4)
	76 #8 (3, 4)
	77 iload (3, 4)
	78 #8 (3, 4)
	79 aload_2 (3, 4)
	80 getfield (3, 4)
	81 org/apache/commons/math3/linear/BlockFieldMatrix.blockColumns:I (3, 4)
	83 if_icmpge (3, 4)
	84 377 (3, 4)
	86 aload_2 (3, 4)
	87 iload (3, 4)
	88 #8 (3, 4)
	89 invokespecial (3, 4)
	90 org/apache/commons/math3/linear/BlockFieldMatrix.blockWidth:(I)I (3, 4)
	92 istore (3, 4)
	93 #9 (3, 4)
	94 iload (3, 4)
	95 #9 (3, 4)
	96 iload (3, 4)
	97 #9 (3, 4)
	98 iadd (3, 4)
	99 istore (3, 4)
	100 #10 (3, 4)
	101 iload (3, 4)
	102 #10 (3, 4)
	103 iload (3, 4)
	104 #9 (3, 4)
	105 iadd (3, 4)
	106 istore (3, 4)
	107 #11 (3, 4)
	108 iload (3, 4)
	109 #11 (3, 4)
	110 iload (3, 4)
	111 #9 (3, 4)
	112 iadd (3, 4)
	113 istore (3, 4)
	114 #12 (3, 4)
	115 aload_2 (3, 4)
	116 getfield (3, 4)
	117 org/apache/commons/math3/linear/BlockFieldMatrix.blocks:[[Lorg/apache/commons/math3/FieldElement; (3, 4)
	119 iload (3, 4)
	120 #4 (3, 4)
	121 aaload (3, 4)
	122 astore (3, 4)
	123 #13 (3, 4)
	124 iconst_0 (5, 4)
	125 istore (5, 4)
	126 #14 (5, 4)
	127 iload (5, 4)
	128 #14 (5, 4)
	129 aload_0 (5, 4)
	130 getfield (5, 4)
	131 org/apache/commons/math3/linear/BlockFieldMatrix.blockColumns:I (5, 4)
	133 if_icmpge (5, 4)
	134 318 (5, 4)
	136 aload_0 (5, 4)
	137 iload (5, 4)
	138 #14 (5, 4)
	139 invokespecial (5, 4)
	140 org/apache/commons/math3/linear/BlockFieldMatrix.blockWidth:(I)I (5, 4)
	142 istore (5, 4)
	143 #15 (5, 4)
	144 aload_0 (5, 4)
	145 getfield (5, 4)
	146 org/apache/commons/math3/linear/BlockFieldMatrix.blocks:[[Lorg/apache/commons/math3/FieldElement; (5, 4)
	148 iload (5, 4)
	149 #5 (5, 4)
	150 aload_0 (5, 4)
	151 getfield (5, 4)
	152 org/apache/commons/math3/linear/BlockFieldMatrix.blockColumns:I (5, 4)
	154 imul (5, 4)
	155 iload (5, 4)
	156 #14 (5, 4)
	157 iadd (5, 4)
	158 aaload (5, 4)
	159 astore (5, 4)
	160 #16 (5, 4)
	161 aload_1 (5, 4)
	162 getfield (5, 4)
	163 org/apache/commons/math3/linear/BlockFieldMatrix.blocks:[[Lorg/apache/commons/math3/FieldElement; (5, 4)
	165 iload (5, 4)
	166 #14 (5, 4)
	167 aload_1 (5, 4)
	168 getfield (5, 4)
	169 org/apache/commons/math3/linear/BlockFieldMatrix.blockColumns:I (5, 4)
	171 imul (5, 4)
	172 iload (5, 4)
	173 #8 (5, 4)
	174 iadd (5, 4)
	175 aaload (5, 4)
	176 astore (5, 4)
	177 #17 (5, 4)
	178 iconst_0 (5, 4)
	179 istore (5, 4)
	180 #18 (5, 4)
	181 iload (6, 4)
	182 #6 (6, 4)
	183 istore (6, 4)
	184 #19 (6, 4)
	185 iload (6, 4)
	186 #19 (6, 4)
	187 iload (6, 4)
	188 #7 (6, 4)
	189 if_icmpge (6, 4)
	190 256 (6, 4)
	192 iload (6, 4)
	193 #19 (6, 4)
	194 iload (6, 4)
	195 #6 (6, 4)
	196 isub (6, 4)
	197 iload (6, 4)
	198 #15 (6, 4)
	199 imul (6, 4)
	200 istore (6, 4)
	201 #20 (6, 4)
	202 iload (6, 4)
	203 #20 (6, 4)
	204 iload (6, 4)
	205 #15 (6, 4)
	206 iadd (6, 4)
	207 istore (6, 4)
	208 #21 (6, 4)
	209 iconst_0 (7, 4)
	210 istore (7, 4)
	211 #22 (7, 4)
	212 iload (7, 4)
	213 #22 (7, 4)
	214 iload (7, 4)
	215 #9 (7, 4)
	216 if_icmpge (7, 4)
	217 223 (7, 4)
	219 aload_3 (7, 4)
	220 astore (7, 4)
	221 #23 (7, 4)
	222 iload (7, 4)
	223 #20 (7, 4)
	224 istore (7, 4)
	225 #24 (7, 4)
	226 iload (7, 4)
	227 #22 (7, 4)
	228 istore (7, 4)
	229 #25 (7, 4)
	230 iload (8, 3)
	231 #24 (8, 3)
	232 iload (8, 3)
	233 #21 (8, 3)
	234 iconst_3 (8, 3)
	235 isub (8, 3)
	236 if_icmpge (8, 3)
	237 127 (8, 3)
	239 aload (8, 3)
	240 #23 (8, 3)
	241 aload (8, 3)
	242 #16 (8, 3)
	243 iload (8, 3)
	244 #24 (8, 3)
	245 aaload (8, 3)
	246 aload (8, 3)
	247 #17 (8, 3)
	248 iload (8, 3)
	249 #25 (8, 3)
	250 aaload (8, 3)
	251 invokeinterface (8, 3)
	252 org/apache/commons/math3/FieldElement.multiply:(Lorg/apache/commons/math3/linear/BlockFieldMatrix;)Lorg/apache/commons/math3/linear/BlockFieldMatrix; (8, 3)
	254 0 (8, 3)
	256 invokeinterface (8, 3)
	257 org/apache/commons/math3/FieldElement.org/apache/commons/math3/FieldElement (8, 3)
	259 0 (8, 3)
	261 checkcast (8, 3)
	262 org/apache/commons/math3/FieldElement (8, 3)
	264 aload (8, 3)
	265 #16 (8, 3)
	266 iload (8, 3)
	267 #24 (8, 3)
	268 iconst_1 (8, 3)
	269 iadd (8, 3)
	270 aaload (8, 3)
	271 aload (8, 3)
	272 #17 (8, 3)
	273 iload (8, 3)
	274 #25 (8, 3)
	275 iload (8, 3)
	276 #9 (8, 3)
	277 iadd (8, 3)
	278 aaload (8, 3)
	279 invokeinterface (8, 3)
	280 org/apache/commons/math3/FieldElement.multiply:(Lorg/apache/commons/math3/linear/BlockFieldMatrix;)Lorg/apache/commons/math3/linear/BlockFieldMatrix; (8, 3)
	282 0 (8, 3)
	284 invokeinterface (8, 3)
	285 org/apache/commons/math3/FieldElement.org/apache/commons/math3/FieldElement (8, 3)
	287 0 (8, 3)
	289 checkcast (8, 3)
	290 org/apache/commons/math3/FieldElement (8, 3)
	292 aload (8, 3)
	293 #16 (8, 3)
	294 iload (8, 3)
	295 #24 (8, 3)
	296 iconst_2 (8, 3)
	297 iadd (8, 3)
	298 aaload (8, 3)
	299 aload (8, 3)
	300 #17 (8, 3)
	301 iload (8, 3)
	302 #25 (8, 3)
	303 iload (8, 3)
	304 #10 (8, 3)
	305 iadd (8, 3)
	306 aaload (8, 3)
	307 invokeinterface (8, 3)
	308 org/apache/commons/math3/FieldElement.multiply:(Lorg/apache/commons/math3/linear/BlockFieldMatrix;)Lorg/apache/commons/math3/linear/BlockFieldMatrix; (8, 3)
	310 0 (8, 3)
	312 invokeinterface (8, 3)
	313 org/apache/commons/math3/FieldElement.org/apache/commons/math3/FieldElement (8, 3)
	315 0 (8, 3)
	317 checkcast (8, 3)
	318 org/apache/commons/math3/FieldElement (8, 3)
	320 aload (8, 3)
	321 #16 (8, 3)
	322 iload (8, 3)
	323 #24 (8, 3)
	324 iconst_3 (8, 3)
	325 iadd (8, 3)
	326 aaload (8, 3)
	327 aload (8, 3)
	328 #17 (8, 3)
	329 iload (8, 3)
	330 #25 (8, 3)
	331 iload (8, 3)
	332 #11 (8, 3)
	333 iadd (8, 3)
	334 aaload (8, 3)
	335 invokeinterface (8, 3)
	336 org/apache/commons/math3/FieldElement.multiply:(Lorg/apache/commons/math3/linear/BlockFieldMatrix;)Lorg/apache/commons/math3/linear/BlockFieldMatrix; (8, 3)
	338 0 (8, 3)
	340 invokeinterface (8, 3)
	341 org/apache/commons/math3/FieldElement.org/apache/commons/math3/FieldElement (8, 3)
	343 0 (8, 3)
	345 checkcast (8, 3)
	346 org/apache/commons/math3/FieldElement (8, 3)
	348 astore (8, 3)
	349 #23 (8, 3)
	350 iinc (8, 3)
	351 #24 (8, 3)
	352 21 (8, 3)
	353 iload (8, 3)
	354 #25 (8, 3)
	355 iload (8, 3)
	356 #12 (8, 3)
	357 iadd (8, 3)
	358 istore (8, 3)
	359 #25 (8, 3)
	360 goto (8, 3)
	361 -130 (8, 3)
	363 iload (8, 3)
	364 #24 (8, 3)
	365 iload (8, 3)
	366 #21 (8, 3)
	367 if_icmpge (8, 3)
	368 43 (8, 3)
	370 aload (8, 3)
	371 #23 (8, 3)
	372 aload (8, 3)
	373 #16 (8, 3)
	374 iload (8, 3)
	375 #24 (8, 3)
	376 iinc (8, 3)
	377 #24 (8, 3)
	378 50 (8, 3)
	379 aaload (8, 3)
	380 aload (8, 3)
	381 #17 (8, 3)
	382 iload (8, 3)
	383 #25 (8, 3)
	384 aaload (8, 3)
	385 invokeinterface (8, 3)
	386 org/apache/commons/math3/FieldElement.multiply:(Lorg/apache/commons/math3/linear/BlockFieldMatrix;)Lorg/apache/commons/math3/linear/BlockFieldMatrix; (8, 3)
	388 0 (8, 3)
	390 invokeinterface (8, 3)
	391 org/apache/commons/math3/FieldElement.org/apache/commons/math3/FieldElement (8, 3)
	393 0 (8, 3)
	395 checkcast (8, 3)
	396 org/apache/commons/math3/FieldElement (8, 3)
	398 astore (8, 3)
	399 #23 (8, 3)
	400 iload (8, 3)
	401 #25 (8, 3)
	402 iload (8, 3)
	403 #9 (8, 3)
	404 iadd (8, 3)
	405 istore (8, 3)
	406 #25 (8, 3)
	407 goto (8, 3)
	408 -44 (8, 3)
	410 aload (7, 4)
	411 #13 (7, 4)
	412 iload (7, 4)
	413 #18 (7, 4)
	414 aload (7, 4)
	415 #13 (7, 4)
	416 iload (7, 4)
	417 #18 (7, 4)
	418 aaload (7, 4)
	419 aload (7, 4)
	420 #23 (7, 4)
	421 invokeinterface (7, 4)
	422 org/apache/commons/math3/FieldElement.org/apache/commons/math3/FieldElement (7, 4)
	424 0 (7, 4)
	426 checkcast (7, 4)
	427 org/apache/commons/math3/FieldElement (7, 4)
	429 aastore (7, 4)
	430 iinc (7, 4)
	431 #18 (7, 4)
	432 -124 (7, 4)
	433 iinc (7, 4)
	434 #22 (7, 4)
	435 -89 (7, 4)
	436 goto (7, 4)
	437 -224 (7, 4)
	439 iinc (7, 4)
	440 #19 (7, 4)
	441 -89 (7, 4)
	442 goto (7, 4)
	443 -257 (7, 4)
	445 iinc (7, 4)
	446 #14 (7, 4)
	447 -89 (7, 4)
	448 goto (7, 4)
	449 -321 (7, 4)
	451 iinc (6, 4)
	452 #4 (6, 4)
	453 -124 (6, 4)
	454 iinc (6, 4)
	455 #8 (6, 4)
	456 -89 (6, 4)
	457 goto (6, 4)
	458 -380 (6, 4)
	460 iinc (6, 4)
	461 #5 (6, 4)
	462 -89 (6, 4)
	463 goto (6, 4)
	464 -419 (6, 4)
	466 aload_2 (5, 4)
	467 areturn (3, 4)

Method: getData
	0 aload_0 (0, 0)
	1 invokevirtual (0, 0)
	2 org/apache/commons/math3/linear/BlockFieldMatrix.getField:()Lorg/apache/commons/math3/Field; (0, 0)
	4 aload_0 (0, 0)
	5 invokevirtual (0, 0)
	6 org/apache/commons/math3/linear/BlockFieldMatrix.getRowDimension:()I (0, 0)
	8 aload_0 (0, 0)
	9 invokevirtual (0, 0)
	10 org/apache/commons/math3/linear/BlockFieldMatrix.getColumnDimension:()I (0, 0)
	12 invokestatic (0, 0)
	13 org/apache/commons/math3/util/MathArrays.buildArray:(Lorg/apache/commons/math3/Field;II)[[Ljava/lang/Object; (0, 0)
	15 checkcast (0, 0)
	16 [[Lorg/apache/commons/math3/FieldElement; (0, 0)
	18 astore_1 (0, 0)
	19 aload_0 (0, 0)
	20 getfield (0, 0)
	21 org/apache/commons/math3/linear/BlockFieldMatrix.columns:I (0, 0)
	23 aload_0 (0, 0)
	24 getfield (0, 0)
	25 org/apache/commons/math3/linear/BlockFieldMatrix.blockColumns:I (0, 0)
	27 iconst_1 (0, 0)
	28 isub (0, 0)
	29 bipush (0, 0)
	30 36 (0, 0)
	31 imul (0, 0)
	32 isub (0, 0)
	33 istore_2 (0, 0)
	34 iconst_0 (1, 4)
	35 istore_3 (1, 4)
	36 iload_3 (1, 4)
	37 aload_0 (1, 4)
	38 getfield (1, 4)
	39 org/apache/commons/math3/linear/BlockFieldMatrix.blockRows:I (1, 4)
	41 if_icmpge (1, 4)
	42 139 (1, 4)
	44 iload_3 (1, 4)
	45 bipush (1, 4)
	46 36 (1, 4)
	47 imul (1, 4)
	48 istore (1, 4)
	49 #4 (1, 4)
	50 iload (1, 4)
	51 #4 (1, 4)
	52 bipush (1, 4)
	53 36 (1, 4)
	54 iadd (1, 4)
	55 aload_0 (1, 4)
	56 getfield (1, 4)
	57 org/apache/commons/math3/linear/BlockFieldMatrix.rows:I (1, 4)
	59 invokestatic (1, 4)
	60 org/apache/commons/math3/util/FastMath.min:(II)I (1, 4)
	62 istore (1, 4)
	63 #5 (1, 4)
	64 iconst_0 (1, 4)
	65 istore (1, 4)
	66 #6 (1, 4)
	67 iconst_0 (1, 4)
	68 istore (1, 4)
	69 #7 (1, 4)
	70 iload (2, 4)
	71 #4 (2, 4)
	72 istore (2, 4)
	73 #8 (2, 4)
	74 iload (2, 4)
	75 #8 (2, 4)
	76 iload (2, 4)
	77 #5 (2, 4)
	78 if_icmpge (2, 4)
	79 96 (2, 4)
	81 aload_1 (2, 4)
	82 iload (2, 4)
	83 #8 (2, 4)
	84 aaload (2, 4)
	85 astore (2, 4)
	86 #9 (2, 4)
	87 iload_3 (2, 4)
	88 aload_0 (2, 4)
	89 getfield (2, 4)
	90 org/apache/commons/math3/linear/BlockFieldMatrix.blockColumns:I (2, 4)
	92 imul (2, 4)
	93 istore (2, 4)
	94 #10 (2, 4)
	95 iconst_0 (2, 4)
	96 istore (2, 4)
	97 #11 (2, 4)
	98 iconst_0 (3, 4)
	99 istore (3, 4)
	100 #12 (3, 4)
	101 iload (3, 4)
	102 #12 (3, 4)
	103 aload_0 (3, 4)
	104 getfield (3, 4)
	105 org/apache/commons/math3/linear/BlockFieldMatrix.blockColumns:I (3, 4)
	107 iconst_1 (3, 4)
	108 isub (3, 4)
	109 if_icmpge (3, 4)
	110 33 (3, 4)
	112 aload_0 (3, 4)
	113 getfield (3, 4)
	114 org/apache/commons/math3/linear/BlockFieldMatrix.blocks:[[Lorg/apache/commons/math3/FieldElement; (3, 4)
	116 iload (3, 4)
	117 #10 (3, 4)
	118 iinc (3, 4)
	119 #10 (3, 4)
	120 50 (3, 4)
	121 aaload (3, 4)
	122 iload (3, 4)
	123 #6 (3, 4)
	124 aload (3, 4)
	125 #9 (3, 4)
	126 iload (3, 4)
	127 #11 (3, 4)
	128 bipush (3, 4)
	129 36 (3, 4)
	130 invokestatic (3, 4)
	131 java/lang/System.arraycopy:(Ljava/lang/Object;ILjava/lang/Object;II)V (3, 4)
	133 iinc (3, 4)
	134 #11 (3, 4)
	135 -124 (3, 4)
	136 iinc (3, 4)
	137 #12 (3, 4)
	138 -89 (3, 4)
	139 goto (3, 4)
	140 -38 (3, 4)
	142 aload_0 (2, 4)
	143 getfield (2, 4)
	144 org/apache/commons/math3/linear/BlockFieldMatrix.blocks:[[Lorg/apache/commons/math3/FieldElement; (2, 4)
	146 iload (2, 4)
	147 #10 (2, 4)
	148 aaload (2, 4)
	149 iload (2, 4)
	150 #7 (2, 4)
	151 aload (2, 4)
	152 #9 (2, 4)
	153 iload (2, 4)
	154 #11 (2, 4)
	155 iload_2 (2, 4)
	156 invokestatic (2, 4)
	157 java/lang/System.arraycopy:(Ljava/lang/Object;ILjava/lang/Object;II)V (2, 4)
	159 iinc (2, 4)
	160 #6 (2, 4)
	161 21 (2, 4)
	162 iload (2, 4)
	163 #7 (2, 4)
	164 iload_2 (2, 4)
	165 iadd (2, 4)
	166 istore (2, 4)
	167 #7 (2, 4)
	168 iinc (2, 4)
	169 #8 (2, 4)
	170 -89 (2, 4)
	171 goto (2, 4)
	172 -97 (2, 4)
	174 iinc (2, 4)
	175 #3 (2, 4)
	176 -89 (2, 4)
	177 goto (2, 4)
	178 -141 (2, 4)
	180 aload_1 (1, 4)
	181 areturn (1, 4)

Method: getSubMatrix
	0 aload_0 (0, 0)
	1 iload_1 (0, 0)
	2 iload_2 (0, 0)
	3 iload_3 (0, 0)
	4 iload (0, 0)
	5 #4 (0, 0)
	6 invokevirtual (0, 0)
	7 org/apache/commons/math3/linear/BlockFieldMatrix.checkSubMatrixIndex:(IIII)V (0, 0)
	9 new (0, 0)
	10 org/apache/commons/math3/linear/BlockFieldMatrix (0, 0)
	12 dup (0, 0)
	13 aload_0 (0, 0)
	14 invokevirtual (0, 0)
	15 org/apache/commons/math3/linear/BlockFieldMatrix.getField:()Lorg/apache/commons/math3/Field; (0, 0)
	17 iload_2 (0, 0)
	18 iload_1 (0, 0)
	19 isub (0, 0)
	20 iconst_1 (0, 0)
	21 iadd (0, 0)
	22 iload (0, 0)
	23 #4 (0, 0)
	24 iload_3 (0, 0)
	25 isub (0, 0)
	26 iconst_1 (0, 0)
	27 iadd (0, 0)
	28 invokespecial (0, 0)
	29 org/apache/commons/math3/linear/BlockFieldMatrix.<init>:(Lorg/apache/commons/math3/Field;II)V (0, 0)
	31 astore (0, 0)
	32 #5 (0, 0)
	33 iload_1 (1, 1)
	34 bipush (1, 1)
	35 36 (1, 1)
	36 idiv (1, 1)
	37 istore (1, 1)
	38 #6 (1, 1)
	39 iload_1 (2, 1)
	40 bipush (2, 1)
	41 36 (2, 1)
	42 irem (2, 1)
	43 istore (2, 1)
	44 #7 (2, 1)
	45 iload_3 (2, 1)
	46 bipush (2, 1)
	47 36 (2, 1)
	48 idiv (2, 1)
	49 istore (2, 1)
	50 #8 (2, 1)
	51 iload_3 (3, 1)
	52 bipush (3, 1)
	53 36 (3, 1)
	54 irem (3, 1)
	55 istore (3, 1)
	56 #9 (3, 1)
	57 iload (4, 4)
	58 #6 (4, 4)
	59 istore (4, 4)
	60 #10 (4, 4)
	61 iconst_0 (5, 4)
	62 istore (5, 4)
	63 #11 (5, 4)
	64 iload (5, 4)
	65 #11 (5, 4)
	66 aload (5, 4)
	67 #5 (5, 4)
	68 getfield (5, 4)
	69 org/apache/commons/math3/linear/BlockFieldMatrix.blockRows:I (5, 4)
	71 if_icmpge (5, 4)
	72 463 (5, 4)
	74 aload (5, 4)
	75 #5 (5, 4)
	76 iload (5, 4)
	77 #11 (5, 4)
	78 invokespecial (5, 4)
	79 org/apache/commons/math3/linear/BlockFieldMatrix.blockHeight:(I)I (5, 4)
	81 istore (5, 4)
	82 #12 (5, 4)
	83 iload (5, 4)
	84 #8 (5, 4)
	85 istore (5, 4)
	86 #13 (5, 4)
	87 iconst_0 (6, 4)
	88 istore (6, 4)
	89 #14 (6, 4)
	90 iload (6, 4)
	91 #14 (6, 4)
	92 aload (6, 4)
	93 #5 (6, 4)
	94 getfield (6, 4)
	95 org/apache/commons/math3/linear/BlockFieldMatrix.blockColumns:I (6, 4)
	97 if_icmpge (6, 4)
	98 428 (6, 4)
	100 aload (6, 4)
	101 #5 (6, 4)
	102 iload (6, 4)
	103 #14 (6, 4)
	104 invokespecial (6, 4)
	105 org/apache/commons/math3/linear/BlockFieldMatrix.blockWidth:(I)I (6, 4)
	107 istore (6, 4)
	108 #15 (6, 4)
	109 iload (6, 4)
	110 #11 (6, 4)
	111 aload (6, 4)
	112 #5 (6, 4)
	113 getfield (6, 4)
	114 org/apache/commons/math3/linear/BlockFieldMatrix.blockColumns:I (6, 4)
	116 imul (6, 4)
	117 iload (6, 4)
	118 #14 (6, 4)
	119 iadd (6, 4)
	120 istore (6, 4)
	121 #16 (6, 4)
	122 aload (6, 4)
	123 #5 (6, 4)
	124 getfield (6, 4)
	125 org/apache/commons/math3/linear/BlockFieldMatrix.blocks:[[Lorg/apache/commons/math3/FieldElement; (6, 4)
	127 iload (6, 4)
	128 #16 (6, 4)
	129 aaload (6, 4)
	130 astore (6, 4)
	131 #17 (6, 4)
	132 iload (6, 4)
	133 #10 (6, 4)
	134 aload_0 (6, 4)
	135 getfield (6, 4)
	136 org/apache/commons/math3/linear/BlockFieldMatrix.blockColumns:I (6, 4)
	138 imul (6, 4)
	139 iload (6, 4)
	140 #13 (6, 4)
	141 iadd (6, 4)
	142 istore (6, 4)
	143 #18 (6, 4)
	144 aload_0 (6, 4)
	145 iload (6, 4)
	146 #13 (6, 4)
	147 invokespecial (6, 4)
	148 org/apache/commons/math3/linear/BlockFieldMatrix.blockWidth:(I)I (6, 4)
	150 istore (6, 4)
	151 #19 (6, 4)
	152 iload (7, 1)
	153 #12 (7, 1)
	154 iload (7, 1)
	155 #7 (7, 1)
	156 iadd (7, 1)
	157 bipush (7, 1)
	158 36 (7, 1)
	159 isub (7, 1)
	160 istore (7, 1)
	161 #20 (7, 1)
	162 iload (8, 1)
	163 #15 (8, 1)
	164 iload (8, 1)
	165 #9 (8, 1)
	166 iadd (8, 1)
	167 bipush (8, 1)
	168 36 (8, 1)
	169 isub (8, 1)
	170 istore (8, 1)
	171 #21 (8, 1)
	172 iload (9, 1)
	173 #20 (9, 1)
	174 ifle (9, 1)
	175 226 (9, 1)
	177 iload (10, 1)
	178 #21 (10, 1)
	179 ifle (10, 1)
	180 150 (10, 1)
	182 aload_0 (10, 1)
	183 iload (10, 1)
	184 #13 (10, 1)
	185 iconst_1 (10, 1)
	186 iadd (10, 1)
	187 invokespecial (10, 1)
	188 org/apache/commons/math3/linear/BlockFieldMatrix.blockWidth:(I)I (10, 1)
	190 istore (10, 1)
	191 #22 (10, 1)
	192 aload_0 (10, 1)
	193 aload_0 (10, 1)
	194 getfield (10, 1)
	195 org/apache/commons/math3/linear/BlockFieldMatrix.blocks:[[Lorg/apache/commons/math3/FieldElement; (10, 1)
	197 iload (10, 1)
	198 #18 (10, 1)
	199 aaload (10, 1)
	200 iload (10, 1)
	201 #19 (10, 1)
	202 iload (10, 1)
	203 #7 (10, 1)
	204 bipush (10, 1)
	205 36 (10, 1)
	206 iload (10, 1)
	207 #9 (10, 1)
	208 bipush (10, 1)
	209 36 (10, 1)
	210 aload (10, 1)
	211 #17 (10, 1)
	212 iload (10, 1)
	213 #15 (10, 1)
	214 iconst_0 (10, 1)
	215 iconst_0 (10, 1)
	216 invokespecial (10, 1)
	217 org/apache/commons/math3/linear/BlockFieldMatrix.copyBlockPart:([Lorg/apache/commons/math3/FieldElement;IIIII[Lorg/apache/commons/math3/FieldElement;III)V (10, 1)
	219 aload_0 (12, 1)
	220 aload_0 (12, 1)
	221 getfield (12, 1)
	222 org/apache/commons/math3/linear/BlockFieldMatrix.blocks:[[Lorg/apache/commons/math3/FieldElement; (12, 1)
	224 iload (12, 1)
	225 #18 (12, 1)
	226 iconst_1 (12, 1)
	227 iadd (12, 1)
	228 aaload (12, 1)
	229 iload (12, 1)
	230 #22 (12, 1)
	231 iload (12, 1)
	232 #7 (12, 1)
	233 bipush (12, 1)
	234 36 (12, 1)
	235 iconst_0 (12, 1)
	236 iload (12, 1)
	237 #21 (12, 1)
	238 aload (12, 1)
	239 #17 (12, 1)
	240 iload (12, 1)
	241 #15 (12, 1)
	242 iconst_0 (12, 1)
	243 iload (12, 1)
	244 #15 (12, 1)
	245 iload (12, 1)
	246 #21 (12, 1)
	247 isub (12, 1)
	248 invokespecial (12, 1)
	249 org/apache/commons/math3/linear/BlockFieldMatrix.copyBlockPart:([Lorg/apache/commons/math3/FieldElement;IIIII[Lorg/apache/commons/math3/FieldElement;III)V (12, 1)
	251 aload_0 (13, 1)
	252 aload_0 (13, 1)
	253 getfield (13, 1)
	254 org/apache/commons/math3/linear/BlockFieldMatrix.blocks:[[Lorg/apache/commons/math3/FieldElement; (13, 1)
	256 iload (13, 1)
	257 #18 (13, 1)
	258 aload_0 (13, 1)
	259 getfield (13, 1)
	260 org/apache/commons/math3/linear/BlockFieldMatrix.blockColumns:I (13, 1)
	262 iadd (13, 1)
	263 aaload (13, 1)
	264 iload (13, 1)
	265 #19 (13, 1)
	266 iconst_0 (13, 1)
	267 iload (13, 1)
	268 #20 (13, 1)
	269 iload (13, 1)
	270 #9 (13, 1)
	271 bipush (13, 1)
	272 36 (13, 1)
	273 aload (13, 1)
	274 #17 (13, 1)
	275 iload (13, 1)
	276 #15 (13, 1)
	277 iload (13, 1)
	278 #12 (13, 1)
	279 iload (13, 1)
	280 #20 (13, 1)
	281 isub (13, 1)
	282 iconst_0 (13, 1)
	283 invokespecial (13, 1)
	284 org/apache/commons/math3/linear/BlockFieldMatrix.copyBlockPart:([Lorg/apache/commons/math3/FieldElement;IIIII[Lorg/apache/commons/math3/FieldElement;III)V (13, 1)
	286 aload_0 (14, 1)
	287 aload_0 (14, 1)
	288 getfield (14, 1)
	289 org/apache/commons/math3/linear/BlockFieldMatrix.blocks:[[Lorg/apache/commons/math3/FieldElement; (14, 1)
	291 iload (14, 1)
	292 #18 (14, 1)
	293 aload_0 (14, 1)
	294 getfield (14, 1)
	295 org/apache/commons/math3/linear/BlockFieldMatrix.blockColumns:I (14, 1)
	297 iadd (14, 1)
	298 iconst_1 (14, 1)
	299 iadd (14, 1)
	300 aaload (14, 1)
	301 iload (14, 1)
	302 #22 (14, 1)
	303 iconst_0 (14, 1)
	304 iload (14, 1)
	305 #20 (14, 1)
	306 iconst_0 (14, 1)
	307 iload (14, 1)
	308 #21 (14, 1)
	309 aload (14, 1)
	310 #17 (14, 1)
	311 iload (14, 1)
	312 #15 (14, 1)
	313 iload (14, 1)
	314 #12 (14, 1)
	315 iload (14, 1)
	316 #20 (14, 1)
	317 isub (14, 1)
	318 iload (14, 1)
	319 #15 (14, 1)
	320 iload (14, 1)
	321 #21 (14, 1)
	322 isub (14, 1)
	323 invokespecial (14, 1)
	324 org/apache/commons/math3/linear/BlockFieldMatrix.copyBlockPart:([Lorg/apache/commons/math3/FieldElement;IIIII[Lorg/apache/commons/math3/FieldElement;III)V (14, 1)
	326 goto (15, 2)
	327 190 (15, 2)
	329 aload_0 (15, 2)
	330 aload_0 (15, 2)
	331 getfield (15, 2)
	332 org/apache/commons/math3/linear/BlockFieldMatrix.blocks:[[Lorg/apache/commons/math3/FieldElement; (15, 2)
	334 iload (15, 2)
	335 #18 (15, 2)
	336 aaload (15, 2)
	337 iload (15, 2)
	338 #19 (15, 2)
	339 iload (15, 2)
	340 #7 (15, 2)
	341 bipush (15, 2)
	342 36 (15, 2)
	343 iload (15, 2)
	344 #9 (15, 2)
	345 iload (15, 2)
	346 #15 (15, 2)
	347 iload (15, 2)
	348 #9 (15, 2)
	349 iadd (15, 2)
	350 aload (15, 2)
	351 #17 (15, 2)
	352 iload (15, 2)
	353 #15 (15, 2)
	354 iconst_0 (15, 2)
	355 iconst_0 (15, 2)
	356 invokespecial (15, 2)
	357 org/apache/commons/math3/linear/BlockFieldMatrix.copyBlockPart:([Lorg/apache/commons/math3/FieldElement;IIIII[Lorg/apache/commons/math3/FieldElement;III)V (15, 2)
	359 aload_0 (17, 1)
	360 aload_0 (17, 1)
	361 getfield (17, 1)
	362 org/apache/commons/math3/linear/BlockFieldMatrix.blocks:[[Lorg/apache/commons/math3/FieldElement; (17, 1)
	364 iload (17, 1)
	365 #18 (17, 1)
	366 aload_0 (17, 1)
	367 getfield (17, 1)
	368 org/apache/commons/math3/linear/BlockFieldMatrix.blockColumns:I (17, 1)
	370 iadd (17, 1)
	371 aaload (17, 1)
	372 iload (17, 1)
	373 #19 (17, 1)
	374 iconst_0 (17, 1)
	375 iload (17, 1)
	376 #20 (17, 1)
	377 iload (17, 1)
	378 #9 (17, 1)
	379 iload (17, 1)
	380 #15 (17, 1)
	381 iload (17, 1)
	382 #9 (17, 1)
	383 iadd (17, 1)
	384 aload (17, 1)
	385 #17 (17, 1)
	386 iload (17, 1)
	387 #15 (17, 1)
	388 iload (17, 1)
	389 #12 (17, 1)
	390 iload (17, 1)
	391 #20 (17, 1)
	392 isub (17, 1)
	393 iconst_0 (17, 1)
	394 invokespecial (17, 1)
	395 org/apache/commons/math3/linear/BlockFieldMatrix.copyBlockPart:([Lorg/apache/commons/math3/FieldElement;IIIII[Lorg/apache/commons/math3/FieldElement;III)V (17, 1)
	397 goto (17, 1)
	398 119 (17, 1)
	400 iload (11, 1)
	401 #21 (11, 1)
	402 ifle (11, 1)
	403 81 (11, 1)
	405 aload_0 (11, 1)
	406 iload (11, 1)
	407 #13 (11, 1)
	408 iconst_1 (11, 1)
	409 iadd (11, 1)
	410 invokespecial (11, 1)
	411 org/apache/commons/math3/linear/BlockFieldMatrix.blockWidth:(I)I (11, 1)
	413 istore (11, 1)
	414 #22 (11, 1)
	415 aload_0 (11, 1)
	416 aload_0 (11, 1)
	417 getfield (11, 1)
	418 org/apache/commons/math3/linear/BlockFieldMatrix.blocks:[[Lorg/apache/commons/math3/FieldElement; (11, 1)
	420 iload (11, 1)
	421 #18 (11, 1)
	422 aaload (11, 1)
	423 iload (11, 1)
	424 #19 (11, 1)
	425 iload (11, 1)
	426 #7 (11, 1)
	427 iload (11, 1)
	428 #12 (11, 1)
	429 iload (11, 1)
	430 #7 (11, 1)
	431 iadd (11, 1)
	432 iload (11, 1)
	433 #9 (11, 1)
	434 bipush (11, 1)
	435 36 (11, 1)
	436 aload (11, 1)
	437 #17 (11, 1)
	438 iload (11, 1)
	439 #15 (11, 1)
	440 iconst_0 (11, 1)
	441 iconst_0 (11, 1)
	442 invokespecial (11, 1)
	443 org/apache/commons/math3/linear/BlockFieldMatrix.copyBlockPart:([Lorg/apache/commons/math3/FieldElement;IIIII[Lorg/apache/commons/math3/FieldElement;III)V (11, 1)
	445 aload_0 (13, 1)
	446 aload_0 (13, 1)
	447 getfield (13, 1)
	448 org/apache/commons/math3/linear/BlockFieldMatrix.blocks:[[Lorg/apache/commons/math3/FieldElement; (13, 1)
	450 iload (13, 1)
	451 #18 (13, 1)
	452 iconst_1 (13, 1)
	453 iadd (13, 1)
	454 aaload (13, 1)
	455 iload (13, 1)
	456 #22 (13, 1)
	457 iload (13, 1)
	458 #7 (13, 1)
	459 iload (13, 1)
	460 #12 (13, 1)
	461 iload (13, 1)
	462 #7 (13, 1)
	463 iadd (13, 1)
	464 iconst_0 (13, 1)
	465 iload (13, 1)
	466 #21 (13, 1)
	467 aload (13, 1)
	468 #17 (13, 1)
	469 iload (13, 1)
	470 #15 (13, 1)
	471 iconst_0 (13, 1)
	472 iload (13, 1)
	473 #15 (13, 1)
	474 iload (13, 1)
	475 #21 (13, 1)
	476 isub (13, 1)
	477 invokespecial (13, 1)
	478 org/apache/commons/math3/linear/BlockFieldMatrix.copyBlockPart:([Lorg/apache/commons/math3/FieldElement;IIIII[Lorg/apache/commons/math3/FieldElement;III)V (13, 1)
	480 goto (15, 2)
	481 36 (15, 2)
	483 aload_0 (15, 2)
	484 aload_0 (15, 2)
	485 getfield (15, 2)
	486 org/apache/commons/math3/linear/BlockFieldMatrix.blocks:[[Lorg/apache/commons/math3/FieldElement; (15, 2)
	488 iload (15, 2)
	489 #18 (15, 2)
	490 aaload (15, 2)
	491 iload (15, 2)
	492 #19 (15, 2)
	493 iload (15, 2)
	494 #7 (15, 2)
	495 iload (15, 2)
	496 #12 (15, 2)
	497 iload (15, 2)
	498 #7 (15, 2)
	499 iadd (15, 2)
	500 iload (15, 2)
	501 #9 (15, 2)
	502 iload (15, 2)
	503 #15 (15, 2)
	504 iload (15, 2)
	505 #9 (15, 2)
	506 iadd (15, 2)
	507 aload (15, 2)
	508 #17 (15, 2)
	509 iload (15, 2)
	510 #15 (15, 2)
	511 iconst_0 (15, 2)
	512 iconst_0 (15, 2)
	513 invokespecial (15, 2)
	514 org/apache/commons/math3/linear/BlockFieldMatrix.copyBlockPart:([Lorg/apache/commons/math3/FieldElement;IIIII[Lorg/apache/commons/math3/FieldElement;III)V (15, 2)
	516 iinc (8, 1)
	517 #13 (8, 1)
	518 -124 (8, 1)
	519 iinc (8, 1)
	520 #14 (8, 1)
	521 -89 (8, 1)
	522 goto (8, 1)
	523 -432 (8, 1)
	525 iinc (5, 4)
	526 #10 (5, 4)
	527 -124 (5, 4)
	528 iinc (5, 4)
	529 #11 (5, 4)
	530 -89 (5, 4)
	531 goto (5, 4)
	532 -467 (5, 4)
	534 aload (4, 4)
	535 #5 (4, 4)
	536 areturn (0, 4)

Method: copyBlockPart
	0 iload (0, 0)
	1 #6 (0, 0)
	2 iload (0, 0)
	3 #5 (0, 0)
	4 isub (0, 0)
	5 istore (0, 0)
	6 #11 (0, 0)
	7 iload_3 (0, 0)
	8 iload_2 (0, 0)
	9 imul (0, 0)
	10 iload (0, 0)
	11 #5 (0, 0)
	12 iadd (0, 0)
	13 istore (0, 0)
	14 #12 (0, 0)
	15 iload (0, 0)
	16 #9 (0, 0)
	17 iload (0, 0)
	18 #8 (0, 0)
	19 imul (0, 0)
	20 iload (0, 0)
	21 #10 (0, 0)
	22 iadd (0, 0)
	23 istore (0, 0)
	24 #13 (0, 0)
	25 iload_3 (1, 4)
	26 istore (1, 4)
	27 #14 (1, 4)
	28 iload (1, 4)
	29 #14 (1, 4)
	30 iload (1, 4)
	31 #4 (1, 4)
	32 if_icmpge (1, 4)
	33 34 (1, 4)
	35 aload_1 (1, 4)
	36 iload (1, 4)
	37 #12 (1, 4)
	38 aload (1, 4)
	39 #7 (1, 4)
	40 iload (1, 4)
	41 #13 (1, 4)
	42 iload (1, 4)
	43 #11 (1, 4)
	44 invokestatic (1, 4)
	45 java/lang/System.arraycopy:(Ljava/lang/Object;ILjava/lang/Object;II)V (1, 4)
	47 iload (1, 4)
	48 #12 (1, 4)
	49 iload_2 (1, 4)
	50 iadd (1, 4)
	51 istore (1, 4)
	52 #12 (1, 4)
	53 iload (1, 4)
	54 #13 (1, 4)
	55 iload (1, 4)
	56 #8 (1, 4)
	57 iadd (1, 4)
	58 istore (1, 4)
	59 #13 (1, 4)
	60 iinc (1, 4)
	61 #14 (1, 4)
	62 -89 (1, 4)
	63 goto (1, 4)
	64 -35 (1, 4)
	66 return (0, 0)

Method: setSubMatrix
	0 aload_1 (0, 0)
	1 invokestatic (0, 0)
	2 org/apache/commons/math3/util/MathUtils.checkNotNull:(Ljava/lang/Object;)V (0, 0)
	4 aload_1 (0, 0)
	5 iconst_0 (0, 0)
	6 aaload (0, 0)
	7 arraylength (0, 0)
	8 istore (0, 0)
	9 #4 (0, 0)
	10 iload (1, 1)
	11 #4 (1, 1)
	12 ifne (1, 1)
	13 14 (1, 1)
	15 new (1, 1)
	16 org/apache/commons/math3/exception/NoDataException (1, 1)
	18 dup (1, 1)
	19 getstatic (1, 1)
	20 org/apache/commons/math3/exception/util/LocalizedFormats.AT_LEAST_ONE_COLUMN:Lorg/apache/commons/math3/exception/util/LocalizedFormats; (1, 1)
	22 invokespecial (1, 1)
	23 org/apache/commons/math3/exception/NoDataException.<init>:(Lorg/apache/commons/math3/exception/util/Localizable;)V (1, 1)
	25 athrow (1, 1)
	26 iload_2 (0, 0)
	27 aload_1 (0, 0)
	28 arraylength (0, 0)
	29 iadd (0, 0)
	30 iconst_1 (0, 0)
	31 isub (0, 0)
	32 istore (0, 0)
	33 #5 (0, 0)
	34 iload_3 (0, 0)
	35 iload (0, 0)
	36 #4 (0, 0)
	37 iadd (0, 0)
	38 iconst_1 (0, 0)
	39 isub (0, 0)
	40 istore (0, 0)
	41 #6 (0, 0)
	42 aload_0 (0, 0)
	43 iload_2 (0, 0)
	44 iload (0, 0)
	45 #5 (0, 0)
	46 iload_3 (0, 0)
	47 iload (0, 0)
	48 #6 (0, 0)
	49 invokevirtual (0, 0)
	50 org/apache/commons/math3/linear/BlockFieldMatrix.checkSubMatrixIndex:(IIII)V (0, 0)
	52 aload_1 (1, 4)
	53 astore (1, 4)
	54 #7 (1, 4)
	55 aload (1, 4)
	56 #7 (1, 4)
	57 arraylength (1, 4)
	58 istore (1, 4)
	59 #8 (1, 4)
	60 iconst_0 (1, 4)
	61 istore (1, 4)
	62 #9 (1, 4)
	63 iload (1, 4)
	64 #9 (1, 4)
	65 iload (1, 4)
	66 #8 (1, 4)
	67 if_icmpge (1, 4)
	68 37 (1, 4)
	70 aload (1, 4)
	71 #7 (1, 4)
	72 iload (1, 4)
	73 #9 (1, 4)
	74 aaload (1, 4)
	75 astore (1, 4)
	76 #10 (1, 4)
	77 aload (2, 1)
	78 #10 (2, 1)
	79 arraylength (2, 1)
	80 iload (2, 1)
	81 #4 (2, 1)
	82 if_icmpeq (2, 1)
	83 16 (2, 1)
	85 new (2, 1)
	86 org/apache/commons/math3/exception/DimensionMismatchException (2, 1)
	88 dup (2, 1)
	89 iload (2, 1)
	90 #4 (2, 1)
	91 aload (2, 1)
	92 #10 (2, 1)
	93 arraylength (2, 1)
	94 invokespecial (2, 1)
	95 org/apache/commons/math3/exception/DimensionMismatchException.<init>:(II)V (2, 1)
	97 athrow (2, 1)
	98 iinc (2, 1)
	99 #9 (2, 1)
	100 -89 (2, 1)
	101 goto (2, 1)
	102 -38 (2, 1)
	104 iload_2 (1, 4)
	105 bipush (1, 4)
	106 36 (1, 4)
	107 idiv (1, 4)
	108 istore (1, 4)
	109 #7 (1, 4)
	110 iload (1, 4)
	111 #5 (1, 4)
	112 bipush (1, 4)
	113 36 (1, 4)
	114 iadd (1, 4)
	115 bipush (1, 4)
	116 36 (1, 4)
	117 idiv (1, 4)
	118 istore (1, 4)
	119 #8 (1, 4)
	120 iload_3 (1, 4)
	121 bipush (1, 4)
	122 36 (1, 4)
	123 idiv (1, 4)
	124 istore (1, 4)
	125 #9 (1, 4)
	126 iload (1, 4)
	127 #6 (1, 4)
	128 bipush (1, 4)
	129 36 (1, 4)
	130 iadd (1, 4)
	131 bipush (1, 4)
	132 36 (1, 4)
	133 idiv (1, 4)
	134 istore (1, 4)
	135 #10 (1, 4)
	136 iload (3, 4)
	137 #7 (3, 4)
	138 istore (3, 4)
	139 #11 (3, 4)
	140 iload (3, 4)
	141 #11 (3, 4)
	142 iload (3, 4)
	143 #8 (3, 4)
	144 if_icmpge (3, 4)
	145 172 (3, 4)
	147 aload_0 (3, 4)
	148 iload (3, 4)
	149 #11 (3, 4)
	150 invokespecial (3, 4)
	151 org/apache/commons/math3/linear/BlockFieldMatrix.blockHeight:(I)I (3, 4)
	153 istore (3, 4)
	154 #12 (3, 4)
	155 iload (3, 4)
	156 #11 (3, 4)
	157 bipush (3, 4)
	158 36 (3, 4)
	159 imul (3, 4)
	160 istore (3, 4)
	161 #13 (3, 4)
	162 iload_2 (3, 4)
	163 iload (3, 4)
	164 #13 (3, 4)
	165 invokestatic (3, 4)
	166 org/apache/commons/math3/util/FastMath.max:(II)I (3, 4)
	168 istore (3, 4)
	169 #14 (3, 4)
	170 iload (3, 4)
	171 #5 (3, 4)
	172 iconst_1 (3, 4)
	173 iadd (3, 4)
	174 iload (3, 4)
	175 #13 (3, 4)
	176 iload (3, 4)
	177 #12 (3, 4)
	178 iadd (3, 4)
	179 invokestatic (3, 4)
	180 org/apache/commons/math3/util/FastMath.min:(II)I (3, 4)
	182 istore (3, 4)
	183 #15 (3, 4)
	184 iload (4, 4)
	185 #9 (4, 4)
	186 istore (4, 4)
	187 #16 (4, 4)
	188 iload (4, 4)
	189 #16 (4, 4)
	190 iload (4, 4)
	191 #10 (4, 4)
	192 if_icmpge (4, 4)
	193 118 (4, 4)
	195 aload_0 (4, 4)
	196 iload (4, 4)
	197 #16 (4, 4)
	198 invokespecial (4, 4)
	199 org/apache/commons/math3/linear/BlockFieldMatrix.blockWidth:(I)I (4, 4)
	201 istore (4, 4)
	202 #17 (4, 4)
	203 iload (4, 4)
	204 #16 (4, 4)
	205 bipush (4, 4)
	206 36 (4, 4)
	207 imul (4, 4)
	208 istore (4, 4)
	209 #18 (4, 4)
	210 iload_3 (4, 4)
	211 iload (4, 4)
	212 #18 (4, 4)
	213 invokestatic (4, 4)
	214 org/apache/commons/math3/util/FastMath.max:(II)I (4, 4)
	216 istore (4, 4)
	217 #19 (4, 4)
	218 iload (4, 4)
	219 #6 (4, 4)
	220 iconst_1 (4, 4)
	221 iadd (4, 4)
	222 iload (4, 4)
	223 #18 (4, 4)
	224 iload (4, 4)
	225 #17 (4, 4)
	226 iadd (4, 4)
	227 invokestatic (4, 4)
	228 org/apache/commons/math3/util/FastMath.min:(II)I (4, 4)
	230 istore (4, 4)
	231 #20 (4, 4)
	232 iload (4, 4)
	233 #20 (4, 4)
	234 iload (4, 4)
	235 #19 (4, 4)
	236 isub (4, 4)
	237 istore (4, 4)
	238 #21 (4, 4)
	239 aload_0 (4, 4)
	240 getfield (4, 4)
	241 org/apache/commons/math3/linear/BlockFieldMatrix.blocks:[[Lorg/apache/commons/math3/FieldElement; (4, 4)
	243 iload (4, 4)
	244 #11 (4, 4)
	245 aload_0 (4, 4)
	246 getfield (4, 4)
	247 org/apache/commons/math3/linear/BlockFieldMatrix.blockColumns:I (4, 4)
	249 imul (4, 4)
	250 iload (4, 4)
	251 #16 (4, 4)
	252 iadd (4, 4)
	253 aaload (4, 4)
	254 astore (4, 4)
	255 #22 (4, 4)
	256 iload (5, 4)
	257 #14 (5, 4)
	258 istore (5, 4)
	259 #23 (5, 4)
	260 iload (5, 4)
	261 #23 (5, 4)
	262 iload (5, 4)
	263 #15 (5, 4)
	264 if_icmpge (5, 4)
	265 40 (5, 4)
	267 aload_1 (5, 4)
	268 iload (5, 4)
	269 #23 (5, 4)
	270 iload_2 (5, 4)
	271 isub (5, 4)
	272 aaload (5, 4)
	273 iload (5, 4)
	274 #19 (5, 4)
	275 iload_3 (5, 4)
	276 isub (5, 4)
	277 aload (5, 4)
	278 #22 (5, 4)
	279 iload (5, 4)
	280 #23 (5, 4)
	281 iload (5, 4)
	282 #13 (5, 4)
	283 isub (5, 4)
	284 iload (5, 4)
	285 #17 (5, 4)
	286 imul (5, 4)
	287 iload (5, 4)
	288 #19 (5, 4)
	289 iload (5, 4)
	290 #18 (5, 4)
	291 isub (5, 4)
	292 iadd (5, 4)
	293 iload (5, 4)
	294 #21 (5, 4)
	295 invokestatic (5, 4)
	296 java/lang/System.arraycopy:(Ljava/lang/Object;ILjava/lang/Object;II)V (5, 4)
	298 iinc (5, 4)
	299 #23 (5, 4)
	300 -89 (5, 4)
	301 goto (5, 4)
	302 -41 (5, 4)
	304 iinc (5, 4)
	305 #16 (5, 4)
	306 -89 (5, 4)
	307 goto (5, 4)
	308 -119 (5, 4)
	310 iinc (5, 4)
	311 #11 (5, 4)
	312 -89 (5, 4)
	313 goto (5, 4)
	314 -173 (5, 4)
	316 return (2, 4)

Method: getRowMatrix
	0 aload_0 (0, 0)
	1 iload_1 (0, 0)
	2 invokevirtual (0, 0)
	3 org/apache/commons/math3/linear/BlockFieldMatrix.checkRowIndex:(I)V (0, 0)
	5 new (0, 0)
	6 org/apache/commons/math3/linear/BlockFieldMatrix (0, 0)
	8 dup (0, 0)
	9 aload_0 (0, 0)
	10 invokevirtual (0, 0)
	11 org/apache/commons/math3/linear/BlockFieldMatrix.getField:()Lorg/apache/commons/math3/Field; (0, 0)
	13 iconst_1 (0, 0)
	14 aload_0 (0, 0)
	15 getfield (0, 0)
	16 org/apache/commons/math3/linear/BlockFieldMatrix.columns:I (0, 0)
	18 invokespecial (0, 0)
	19 org/apache/commons/math3/linear/BlockFieldMatrix.<init>:(Lorg/apache/commons/math3/Field;II)V (0, 0)
	21 astore_2 (0, 0)
	22 iload_1 (1, 4)
	23 bipush (1, 4)
	24 36 (1, 4)
	25 idiv (1, 4)
	26 istore_3 (1, 4)
	27 iload_1 (1, 4)
	28 iload_3 (1, 4)
	29 bipush (1, 4)
	30 36 (1, 4)
	31 imul (1, 4)
	32 isub (1, 4)
	33 istore (1, 4)
	34 #4 (1, 4)
	35 iconst_0 (1, 4)
	36 istore (1, 4)
	37 #5 (1, 4)
	38 iconst_0 (1, 4)
	39 istore (1, 4)
	40 #6 (1, 4)
	41 aload_2 (1, 4)
	42 getfield (1, 4)
	43 org/apache/commons/math3/linear/BlockFieldMatrix.blocks:[[Lorg/apache/commons/math3/FieldElement; (1, 4)
	45 iload (1, 4)
	46 #5 (1, 4)
	47 aaload (1, 4)
	48 astore (1, 4)
	49 #7 (1, 4)
	50 iconst_0 (2, 4)
	51 istore (2, 4)
	52 #8 (2, 4)
	53 iload (2, 4)
	54 #8 (2, 4)
	55 aload_0 (2, 4)
	56 getfield (2, 4)
	57 org/apache/commons/math3/linear/BlockFieldMatrix.blockColumns:I (2, 4)
	59 if_icmpge (2, 4)
	60 127 (2, 4)
	62 aload_0 (2, 4)
	63 iload (2, 4)
	64 #8 (2, 4)
	65 invokespecial (2, 4)
	66 org/apache/commons/math3/linear/BlockFieldMatrix.blockWidth:(I)I (2, 4)
	68 istore (2, 4)
	69 #9 (2, 4)
	70 aload_0 (2, 4)
	71 getfield (2, 4)
	72 org/apache/commons/math3/linear/BlockFieldMatrix.blocks:[[Lorg/apache/commons/math3/FieldElement; (2, 4)
	74 iload_3 (2, 4)
	75 aload_0 (2, 4)
	76 getfield (2, 4)
	77 org/apache/commons/math3/linear/BlockFieldMatrix.blockColumns:I (2, 4)
	79 imul (2, 4)
	80 iload (2, 4)
	81 #8 (2, 4)
	82 iadd (2, 4)
	83 aaload (2, 4)
	84 astore (2, 4)
	85 #10 (2, 4)
	86 aload (2, 4)
	87 #7 (2, 4)
	88 arraylength (2, 4)
	89 iload (2, 4)
	90 #6 (2, 4)
	91 isub (2, 4)
	92 istore (2, 4)
	93 #11 (2, 4)
	94 iload (3, 1)
	95 #9 (3, 1)
	96 iload (3, 1)
	97 #11 (3, 1)
	98 if_icmple (3, 1)
	99 59 (3, 1)
	101 aload (3, 1)
	102 #10 (3, 1)
	103 iload (3, 1)
	104 #4 (3, 1)
	105 iload (3, 1)
	106 #9 (3, 1)
	107 imul (3, 1)
	108 aload (3, 1)
	109 #7 (3, 1)
	110 iload (3, 1)
	111 #6 (3, 1)
	112 iload (3, 1)
	113 #11 (3, 1)
	114 invokestatic (3, 1)
	115 java/lang/System.arraycopy:(Ljava/lang/Object;ILjava/lang/Object;II)V (3, 1)
	117 aload_2 (3, 1)
	118 getfield (3, 1)
	119 org/apache/commons/math3/linear/BlockFieldMatrix.blocks:[[Lorg/apache/commons/math3/FieldElement; (3, 1)
	121 iinc (3, 1)
	122 #5 (3, 1)
	123 21 (3, 1)
	124 iload (3, 1)
	125 #5 (3, 1)
	126 aaload (3, 1)
	127 astore (3, 1)
	128 #7 (3, 1)
	129 aload (3, 1)
	130 #10 (3, 1)
	131 iload (3, 1)
	132 #4 (3, 1)
	133 iload (3, 1)
	134 #9 (3, 1)
	135 imul (3, 1)
	136 aload (3, 1)
	137 #7 (3, 1)
	138 iconst_0 (3, 1)
	139 iload (3, 1)
	140 #9 (3, 1)
	141 iload (3, 1)
	142 #11 (3, 1)
	143 isub (3, 1)
	144 invokestatic (3, 1)
	145 java/lang/System.arraycopy:(Ljava/lang/Object;ILjava/lang/Object;II)V (3, 1)
	147 iload (3, 1)
	148 #9 (3, 1)
	149 iload (3, 1)
	150 #11 (3, 1)
	151 isub (3, 1)
	152 istore (3, 1)
	153 #6 (3, 1)
	154 goto (3, 1)
	155 26 (3, 1)
	157 aload (4, 2)
	158 #10 (4, 2)
	159 iload (4, 2)
	160 #4 (4, 2)
	161 iload (4, 2)
	162 #9 (4, 2)
	163 imul (4, 2)
	164 aload (4, 2)
	165 #7 (4, 2)
	166 iload (4, 2)
	167 #6 (4, 2)
	168 iload (4, 2)
	169 #9 (4, 2)
	170 invokestatic (4, 2)
	171 java/lang/System.arraycopy:(Ljava/lang/Object;ILjava/lang/Object;II)V (4, 2)
	173 iload (4, 2)
	174 #6 (4, 2)
	175 iload (4, 2)
	176 #9 (4, 2)
	177 iadd (4, 2)
	178 istore (4, 2)
	179 #6 (4, 2)
	180 iinc (4, 2)
	181 #8 (4, 2)
	182 -89 (4, 2)
	183 goto (4, 2)
	184 -130 (4, 2)
	186 aload_2 (2, 4)
	187 areturn (1, 4)

Method: setRowMatrix
	0 aload_0 (0, 0)
	1 iload_1 (0, 0)
	2 invokevirtual (0, 0)
	3 org/apache/commons/math3/linear/BlockFieldMatrix.checkRowIndex:(I)V (0, 0)
	5 aload_0 (0, 0)
	6 invokevirtual (0, 0)
	7 org/apache/commons/math3/linear/BlockFieldMatrix.getColumnDimension:()I (0, 0)
	9 istore_3 (0, 0)
	10 aload_2 (1, 1)
	11 invokevirtual (1, 1)
	12 org/apache/commons/math3/linear/BlockFieldMatrix.getRowDimension:()I (1, 1)
	14 iconst_1 (1, 1)
	15 if_icmpne (1, 1)
	16 11 (1, 1)
	18 aload_2 (1, 1)
	19 invokevirtual (1, 1)
	20 org/apache/commons/math3/linear/BlockFieldMatrix.getColumnDimension:()I (1, 1)
	22 iload_3 (1, 1)
	23 if_icmpeq (1, 1)
	24 21 (1, 1)
	26 new (1, 1)
	27 org/apache/commons/math3/linear/MatrixDimensionMismatchException (1, 1)
	29 dup (1, 1)
	30 aload_2 (1, 1)
	31 invokevirtual (1, 1)
	32 org/apache/commons/math3/linear/BlockFieldMatrix.getRowDimension:()I (1, 1)
	34 aload_2 (1, 1)
	35 invokevirtual (1, 1)
	36 org/apache/commons/math3/linear/BlockFieldMatrix.getColumnDimension:()I (1, 1)
	38 iconst_1 (1, 1)
	39 iload_3 (1, 1)
	40 invokespecial (1, 1)
	41 org/apache/commons/math3/linear/MatrixDimensionMismatchException.<init>:(IIII)V (1, 1)
	43 athrow (1, 1)
	44 iload_1 (2, 4)
	45 bipush (2, 4)
	46 36 (2, 4)
	47 idiv (2, 4)
	48 istore (2, 4)
	49 #4 (2, 4)
	50 iload_1 (2, 4)
	51 iload (2, 4)
	52 #4 (2, 4)
	53 bipush (2, 4)
	54 36 (2, 4)
	55 imul (2, 4)
	56 isub (2, 4)
	57 istore (2, 4)
	58 #5 (2, 4)
	59 iconst_0 (2, 4)
	60 istore (2, 4)
	61 #6 (2, 4)
	62 iconst_0 (2, 4)
	63 istore (2, 4)
	64 #7 (2, 4)
	65 aload_2 (2, 4)
	66 getfield (2, 4)
	67 org/apache/commons/math3/linear/BlockFieldMatrix.blocks:[[Lorg/apache/commons/math3/FieldElement; (2, 4)
	69 iload (2, 4)
	70 #6 (2, 4)
	71 aaload (2, 4)
	72 astore (2, 4)
	73 #8 (2, 4)
	74 iconst_0 (3, 4)
	75 istore (3, 4)
	76 #9 (3, 4)
	77 iload (3, 4)
	78 #9 (3, 4)
	79 aload_0 (3, 4)
	80 getfield (3, 4)
	81 org/apache/commons/math3/linear/BlockFieldMatrix.blockColumns:I (3, 4)
	83 if_icmpge (3, 4)
	84 128 (3, 4)
	86 aload_0 (3, 4)
	87 iload (3, 4)
	88 #9 (3, 4)
	89 invokespecial (3, 4)
	90 org/apache/commons/math3/linear/BlockFieldMatrix.blockWidth:(I)I (3, 4)
	92 istore (3, 4)
	93 #10 (3, 4)
	94 aload_0 (3, 4)
	95 getfield (3, 4)
	96 org/apache/commons/math3/linear/BlockFieldMatrix.blocks:[[Lorg/apache/commons/math3/FieldElement; (3, 4)
	98 iload (3, 4)
	99 #4 (3, 4)
	100 aload_0 (3, 4)
	101 getfield (3, 4)
	102 org/apache/commons/math3/linear/BlockFieldMatrix.blockColumns:I (3, 4)
	104 imul (3, 4)
	105 iload (3, 4)
	106 #9 (3, 4)
	107 iadd (3, 4)
	108 aaload (3, 4)
	109 astore (3, 4)
	110 #11 (3, 4)
	111 aload (3, 4)
	112 #8 (3, 4)
	113 arraylength (3, 4)
	114 iload (3, 4)
	115 #7 (3, 4)
	116 isub (3, 4)
	117 istore (3, 4)
	118 #12 (3, 4)
	119 iload (4, 1)
	120 #10 (4, 1)
	121 iload (4, 1)
	122 #12 (4, 1)
	123 if_icmple (4, 1)
	124 59 (4, 1)
	126 aload (4, 1)
	127 #8 (4, 1)
	128 iload (4, 1)
	129 #7 (4, 1)
	130 aload (4, 1)
	131 #11 (4, 1)
	132 iload (4, 1)
	133 #5 (4, 1)
	134 iload (4, 1)
	135 #10 (4, 1)
	136 imul (4, 1)
	137 iload (4, 1)
	138 #12 (4, 1)
	139 invokestatic (4, 1)
	140 java/lang/System.arraycopy:(Ljava/lang/Object;ILjava/lang/Object;II)V (4, 1)
	142 aload_2 (4, 1)
	143 getfield (4, 1)
	144 org/apache/commons/math3/linear/BlockFieldMatrix.blocks:[[Lorg/apache/commons/math3/FieldElement; (4, 1)
	146 iinc (4, 1)
	147 #6 (4, 1)
	148 21 (4, 1)
	149 iload (4, 1)
	150 #6 (4, 1)
	151 aaload (4, 1)
	152 astore (4, 1)
	153 #8 (4, 1)
	154 aload (4, 1)
	155 #8 (4, 1)
	156 iconst_0 (4, 1)
	157 aload (4, 1)
	158 #11 (4, 1)
	159 iload (4, 1)
	160 #5 (4, 1)
	161 iload (4, 1)
	162 #10 (4, 1)
	163 imul (4, 1)
	164 iload (4, 1)
	165 #10 (4, 1)
	166 iload (4, 1)
	167 #12 (4, 1)
	168 isub (4, 1)
	169 invokestatic (4, 1)
	170 java/lang/System.arraycopy:(Ljava/lang/Object;ILjava/lang/Object;II)V (4, 1)
	172 iload (4, 1)
	173 #10 (4, 1)
	174 iload (4, 1)
	175 #12 (4, 1)
	176 isub (4, 1)
	177 istore (4, 1)
	178 #7 (4, 1)
	179 goto (4, 1)
	180 26 (4, 1)
	182 aload (5, 2)
	183 #8 (5, 2)
	184 iload (5, 2)
	185 #7 (5, 2)
	186 aload (5, 2)
	187 #11 (5, 2)
	188 iload (5, 2)
	189 #5 (5, 2)
	190 iload (5, 2)
	191 #10 (5, 2)
	192 imul (5, 2)
	193 iload (5, 2)
	194 #10 (5, 2)
	195 invokestatic (5, 2)
	196 java/lang/System.arraycopy:(Ljava/lang/Object;ILjava/lang/Object;II)V (5, 2)
	198 iload (5, 2)
	199 #7 (5, 2)
	200 iload (5, 2)
	201 #10 (5, 2)
	202 iadd (5, 2)
	203 istore (5, 2)
	204 #7 (5, 2)
	205 iinc (5, 2)
	206 #9 (5, 2)
	207 -89 (5, 2)
	208 goto (5, 2)
	209 -131 (5, 2)
	211 return (0, 4)

Method: getColumnMatrix
	0 aload_0 (0, 0)
	1 iload_1 (0, 0)
	2 invokevirtual (0, 0)
	3 org/apache/commons/math3/linear/BlockFieldMatrix.checkColumnIndex:(I)V (0, 0)
	5 new (0, 0)
	6 org/apache/commons/math3/linear/BlockFieldMatrix (0, 0)
	8 dup (0, 0)
	9 aload_0 (0, 0)
	10 invokevirtual (0, 0)
	11 org/apache/commons/math3/linear/BlockFieldMatrix.getField:()Lorg/apache/commons/math3/Field; (0, 0)
	13 aload_0 (0, 0)
	14 getfield (0, 0)
	15 org/apache/commons/math3/linear/BlockFieldMatrix.rows:I (0, 0)
	17 iconst_1 (0, 0)
	18 invokespecial (0, 0)
	19 org/apache/commons/math3/linear/BlockFieldMatrix.<init>:(Lorg/apache/commons/math3/Field;II)V (0, 0)
	21 astore_2 (0, 0)
	22 iload_1 (1, 4)
	23 bipush (1, 4)
	24 36 (1, 4)
	25 idiv (1, 4)
	26 istore_3 (1, 4)
	27 iload_1 (1, 4)
	28 iload_3 (1, 4)
	29 bipush (1, 4)
	30 36 (1, 4)
	31 imul (1, 4)
	32 isub (1, 4)
	33 istore (1, 4)
	34 #4 (1, 4)
	35 aload_0 (1, 4)
	36 iload_3 (1, 4)
	37 invokespecial (1, 4)
	38 org/apache/commons/math3/linear/BlockFieldMatrix.blockWidth:(I)I (1, 4)
	40 istore (1, 4)
	41 #5 (1, 4)
	42 iconst_0 (1, 4)
	43 istore (1, 4)
	44 #6 (1, 4)
	45 iconst_0 (1, 4)
	46 istore (1, 4)
	47 #7 (1, 4)
	48 aload_2 (1, 4)
	49 getfield (1, 4)
	50 org/apache/commons/math3/linear/BlockFieldMatrix.blocks:[[Lorg/apache/commons/math3/FieldElement; (1, 4)
	52 iload (1, 4)
	53 #6 (1, 4)
	54 aaload (1, 4)
	55 astore (1, 4)
	56 #8 (1, 4)
	57 iconst_0 (2, 4)
	58 istore (2, 4)
	59 #9 (2, 4)
	60 iload (2, 4)
	61 #9 (2, 4)
	62 aload_0 (2, 4)
	63 getfield (2, 4)
	64 org/apache/commons/math3/linear/BlockFieldMatrix.blockRows:I (2, 4)
	66 if_icmpge (2, 4)
	67 91 (2, 4)
	69 aload_0 (2, 4)
	70 iload (2, 4)
	71 #9 (2, 4)
	72 invokespecial (2, 4)
	73 org/apache/commons/math3/linear/BlockFieldMatrix.blockHeight:(I)I (2, 4)
	75 istore (2, 4)
	76 #10 (2, 4)
	77 aload_0 (2, 4)
	78 getfield (2, 4)
	79 org/apache/commons/math3/linear/BlockFieldMatrix.blocks:[[Lorg/apache/commons/math3/FieldElement; (2, 4)
	81 iload (2, 4)
	82 #9 (2, 4)
	83 aload_0 (2, 4)
	84 getfield (2, 4)
	85 org/apache/commons/math3/linear/BlockFieldMatrix.blockColumns:I (2, 4)
	87 imul (2, 4)
	88 iload_3 (2, 4)
	89 iadd (2, 4)
	90 aaload (2, 4)
	91 astore (2, 4)
	92 #11 (2, 4)
	93 iconst_0 (3, 4)
	94 istore (3, 4)
	95 #12 (3, 4)
	96 iload (3, 4)
	97 #12 (3, 4)
	98 iload (3, 4)
	99 #10 (3, 4)
	100 if_icmpge (3, 4)
	101 51 (3, 4)
	103 iload (4, 1)
	104 #7 (4, 1)
	105 aload (4, 1)
	106 #8 (4, 1)
	107 arraylength (4, 1)
	108 if_icmplt (4, 1)
	109 18 (4, 1)
	111 aload_2 (4, 1)
	112 getfield (4, 1)
	113 org/apache/commons/math3/linear/BlockFieldMatrix.blocks:[[Lorg/apache/commons/math3/FieldElement; (4, 1)
	115 iinc (4, 1)
	116 #6 (4, 1)
	117 21 (4, 1)
	118 iload (4, 1)
	119 #6 (4, 1)
	120 aaload (4, 1)
	121 astore (4, 1)
	122 #8 (4, 1)
	123 iconst_0 (4, 1)
	124 istore (4, 1)
	125 #7 (4, 1)
	126 aload (3, 4)
	127 #8 (3, 4)
	128 iload (3, 4)
	129 #7 (3, 4)
	130 iinc (3, 4)
	131 #7 (3, 4)
	132 25 (3, 4)
	133 aload (3, 4)
	134 #11 (3, 4)
	135 iload (3, 4)
	136 #12 (3, 4)
	137 iload (3, 4)
	138 #5 (3, 4)
	139 imul (3, 4)
	140 iload (3, 4)
	141 #4 (3, 4)
	142 iadd (3, 4)
	143 aaload (3, 4)
	144 aastore (3, 4)
	145 iinc (3, 4)
	146 #12 (3, 4)
	147 -89 (3, 4)
	148 goto (3, 4)
	149 -52 (3, 4)
	151 iinc (3, 4)
	152 #9 (3, 4)
	153 -89 (3, 4)
	154 goto (3, 4)
	155 -94 (3, 4)
	157 aload_2 (2, 4)
	158 areturn (1, 4)

Method: setColumnMatrix
	0 aload_0 (0, 0)
	1 iload_1 (0, 0)
	2 invokevirtual (0, 0)
	3 org/apache/commons/math3/linear/BlockFieldMatrix.checkColumnIndex:(I)V (0, 0)
	5 aload_0 (0, 0)
	6 invokevirtual (0, 0)
	7 org/apache/commons/math3/linear/BlockFieldMatrix.getRowDimension:()I (0, 0)
	9 istore_3 (0, 0)
	10 aload_2 (1, 1)
	11 invokevirtual (1, 1)
	12 org/apache/commons/math3/linear/BlockFieldMatrix.getRowDimension:()I (1, 1)
	14 iload_3 (1, 1)
	15 if_icmpne (1, 1)
	16 11 (1, 1)
	18 aload_2 (1, 1)
	19 invokevirtual (1, 1)
	20 org/apache/commons/math3/linear/BlockFieldMatrix.getColumnDimension:()I (1, 1)
	22 iconst_1 (1, 1)
	23 if_icmpeq (1, 1)
	24 21 (1, 1)
	26 new (1, 1)
	27 org/apache/commons/math3/linear/MatrixDimensionMismatchException (1, 1)
	29 dup (1, 1)
	30 aload_2 (1, 1)
	31 invokevirtual (1, 1)
	32 org/apache/commons/math3/linear/BlockFieldMatrix.getRowDimension:()I (1, 1)
	34 aload_2 (1, 1)
	35 invokevirtual (1, 1)
	36 org/apache/commons/math3/linear/BlockFieldMatrix.getColumnDimension:()I (1, 1)
	38 iload_3 (1, 1)
	39 iconst_1 (1, 1)
	40 invokespecial (1, 1)
	41 org/apache/commons/math3/linear/MatrixDimensionMismatchException.<init>:(IIII)V (1, 1)
	43 athrow (1, 1)
	44 iload_1 (2, 4)
	45 bipush (2, 4)
	46 36 (2, 4)
	47 idiv (2, 4)
	48 istore (2, 4)
	49 #4 (2, 4)
	50 iload_1 (2, 4)
	51 iload (2, 4)
	52 #4 (2, 4)
	53 bipush (2, 4)
	54 36 (2, 4)
	55 imul (2, 4)
	56 isub (2, 4)
	57 istore (2, 4)
	58 #5 (2, 4)
	59 aload_0 (2, 4)
	60 iload (2, 4)
	61 #4 (2, 4)
	62 invokespecial (2, 4)
	63 org/apache/commons/math3/linear/BlockFieldMatrix.blockWidth:(I)I (2, 4)
	65 istore (2, 4)
	66 #6 (2, 4)
	67 iconst_0 (2, 4)
	68 istore (2, 4)
	69 #7 (2, 4)
	70 iconst_0 (2, 4)
	71 istore (2, 4)
	72 #8 (2, 4)
	73 aload_2 (2, 4)
	74 getfield (2, 4)
	75 org/apache/commons/math3/linear/BlockFieldMatrix.blocks:[[Lorg/apache/commons/math3/FieldElement; (2, 4)
	77 iload (2, 4)
	78 #7 (2, 4)
	79 aaload (2, 4)
	80 astore (2, 4)
	81 #9 (2, 4)
	82 iconst_0 (3, 4)
	83 istore (3, 4)
	84 #10 (3, 4)
	85 iload (3, 4)
	86 #10 (3, 4)
	87 aload_0 (3, 4)
	88 getfield (3, 4)
	89 org/apache/commons/math3/linear/BlockFieldMatrix.blockRows:I (3, 4)
	91 if_icmpge (3, 4)
	92 92 (3, 4)
	94 aload_0 (3, 4)
	95 iload (3, 4)
	96 #10 (3, 4)
	97 invokespecial (3, 4)
	98 org/apache/commons/math3/linear/BlockFieldMatrix.blockHeight:(I)I (3, 4)
	100 istore (3, 4)
	101 #11 (3, 4)
	102 aload_0 (3, 4)
	103 getfield (3, 4)
	104 org/apache/commons/math3/linear/BlockFieldMatrix.blocks:[[Lorg/apache/commons/math3/FieldElement; (3, 4)
	106 iload (3, 4)
	107 #10 (3, 4)
	108 aload_0 (3, 4)
	109 getfield (3, 4)
	110 org/apache/commons/math3/linear/BlockFieldMatrix.blockColumns:I (3, 4)
	112 imul (3, 4)
	113 iload (3, 4)
	114 #4 (3, 4)
	115 iadd (3, 4)
	116 aaload (3, 4)
	117 astore (3, 4)
	118 #12 (3, 4)
	119 iconst_0 (4, 4)
	120 istore (4, 4)
	121 #13 (4, 4)
	122 iload (4, 4)
	123 #13 (4, 4)
	124 iload (4, 4)
	125 #11 (4, 4)
	126 if_icmpge (4, 4)
	127 51 (4, 4)
	129 iload (5, 1)
	130 #8 (5, 1)
	131 aload (5, 1)
	132 #9 (5, 1)
	133 arraylength (5, 1)
	134 if_icmplt (5, 1)
	135 18 (5, 1)
	137 aload_2 (5, 1)
	138 getfield (5, 1)
	139 org/apache/commons/math3/linear/BlockFieldMatrix.blocks:[[Lorg/apache/commons/math3/FieldElement; (5, 1)
	141 iinc (5, 1)
	142 #7 (5, 1)
	143 21 (5, 1)
	144 iload (5, 1)
	145 #7 (5, 1)
	146 aaload (5, 1)
	147 astore (5, 1)
	148 #9 (5, 1)
	149 iconst_0 (5, 1)
	150 istore (5, 1)
	151 #8 (5, 1)
	152 aload (4, 4)
	153 #12 (4, 4)
	154 iload (4, 4)
	155 #13 (4, 4)
	156 iload (4, 4)
	157 #6 (4, 4)
	158 imul (4, 4)
	159 iload (4, 4)
	160 #5 (4, 4)
	161 iadd (4, 4)
	162 aload (4, 4)
	163 #9 (4, 4)
	164 iload (4, 4)
	165 #8 (4, 4)
	166 iinc (4, 4)
	167 #8 (4, 4)
	168 50 (4, 4)
	169 aaload (4, 4)
	170 aastore (4, 4)
	171 iinc (4, 4)
	172 #13 (4, 4)
	173 -89 (4, 4)
	174 goto (4, 4)
	175 -52 (4, 4)
	177 iinc (4, 4)
	178 #10 (4, 4)
	179 -89 (4, 4)
	180 goto (4, 4)
	181 -95 (4, 4)
	183 return (0, 4)

Method: getRowVector
	0 aload_0 (0, 0)
	1 iload_1 (0, 0)
	2 invokevirtual (0, 0)
	3 org/apache/commons/math3/linear/BlockFieldMatrix.checkRowIndex:(I)V (0, 0)
	5 aload_0 (0, 0)
	6 invokevirtual (0, 0)
	7 org/apache/commons/math3/linear/BlockFieldMatrix.getField:()Lorg/apache/commons/math3/Field; (0, 0)
	9 aload_0 (0, 0)
	10 getfield (0, 0)
	11 org/apache/commons/math3/linear/BlockFieldMatrix.columns:I (0, 0)
	13 invokestatic (0, 0)
	14 org/apache/commons/math3/util/MathArrays.buildArray:(Lorg/apache/commons/math3/Field;I)[Ljava/lang/Object; (0, 0)
	16 checkcast (0, 0)
	17 [Lorg/apache/commons/math3/FieldElement; (0, 0)
	19 astore_2 (0, 0)
	20 iload_1 (1, 4)
	21 bipush (1, 4)
	22 36 (1, 4)
	23 idiv (1, 4)
	24 istore_3 (1, 4)
	25 iload_1 (1, 4)
	26 iload_3 (1, 4)
	27 bipush (1, 4)
	28 36 (1, 4)
	29 imul (1, 4)
	30 isub (1, 4)
	31 istore (1, 4)
	32 #4 (1, 4)
	33 iconst_0 (1, 4)
	34 istore (1, 4)
	35 #5 (1, 4)
	36 iconst_0 (2, 4)
	37 istore (2, 4)
	38 #6 (2, 4)
	39 iload (2, 4)
	40 #6 (2, 4)
	41 aload_0 (2, 4)
	42 getfield (2, 4)
	43 org/apache/commons/math3/linear/BlockFieldMatrix.blockColumns:I (2, 4)
	45 if_icmpge (2, 4)
	46 55 (2, 4)
	48 aload_0 (2, 4)
	49 iload (2, 4)
	50 #6 (2, 4)
	51 invokespecial (2, 4)
	52 org/apache/commons/math3/linear/BlockFieldMatrix.blockWidth:(I)I (2, 4)
	54 istore (2, 4)
	55 #7 (2, 4)
	56 aload_0 (2, 4)
	57 getfield (2, 4)
	58 org/apache/commons/math3/linear/BlockFieldMatrix.blocks:[[Lorg/apache/commons/math3/FieldElement; (2, 4)
	60 iload_3 (2, 4)
	61 aload_0 (2, 4)
	62 getfield (2, 4)
	63 org/apache/commons/math3/linear/BlockFieldMatrix.blockColumns:I (2, 4)
	65 imul (2, 4)
	66 iload (2, 4)
	67 #6 (2, 4)
	68 iadd (2, 4)
	69 aaload (2, 4)
	70 astore (2, 4)
	71 #8 (2, 4)
	72 aload (2, 4)
	73 #8 (2, 4)
	74 iload (2, 4)
	75 #4 (2, 4)
	76 iload (2, 4)
	77 #7 (2, 4)
	78 imul (2, 4)
	79 aload_2 (2, 4)
	80 iload (2, 4)
	81 #5 (2, 4)
	82 iload (2, 4)
	83 #7 (2, 4)
	84 invokestatic (2, 4)
	85 java/lang/System.arraycopy:(Ljava/lang/Object;ILjava/lang/Object;II)V (2, 4)
	87 iload (2, 4)
	88 #5 (2, 4)
	89 iload (2, 4)
	90 #7 (2, 4)
	91 iadd (2, 4)
	92 istore (2, 4)
	93 #5 (2, 4)
	94 iinc (2, 4)
	95 #6 (2, 4)
	96 -89 (2, 4)
	97 goto (2, 4)
	98 -58 (2, 4)
	100 new (1, 4)
	101 org/apache/commons/math3/linear/ArrayFieldVector (1, 4)
	103 dup (1, 4)
	104 aload_0 (1, 4)
	105 invokevirtual (1, 4)
	106 org/apache/commons/math3/linear/BlockFieldMatrix.getField:()Lorg/apache/commons/math3/Field; (1, 4)
	108 aload_2 (1, 4)
	109 iconst_0 (1, 4)
	110 invokespecial (1, 4)
	111 org/apache/commons/math3/linear/ArrayFieldVector.<init>:(Lorg/apache/commons/math3/Field;[Lorg/apache/commons/math3/FieldElement;Z)V (1, 4)
	113 areturn (0, 4)

Method: setRowVector
	0 aload_0 (0, 0)
	1 iload_1 (0, 0)
	2 aload_2 (0, 0)
	3 checkcast (0, 0)
	4 org/apache/commons/math3/linear/ArrayFieldVector (0, 0)
	6 invokevirtual (0, 0)
	7 org/apache/commons/math3/linear/ArrayFieldVector.getDataRef:()[Lorg/apache/commons/math3/FieldElement; (0, 0)
	9 invokevirtual (0, 0)
	10 org/apache/commons/math3/linear/BlockFieldMatrix.setRow:(I[Lorg/apache/commons/math3/FieldElement;)V (0, 0)
	12 goto (0, 0)
	13 10 (0, 0)
	15 astore_3 (0, 0)
	16 aload_0 (0, 0)
	17 iload_1 (0, 0)
	18 aload_2 (0, 0)
	19 invokespecial (0, 0)
	20 org/apache/commons/math3/linear/AbstractFieldMatrix.setRowVector:(ILorg/apache/commons/math3/linear/FieldVector;)V (0, 0)
	22 return (0, 0)

Method: getColumnVector
	0 aload_0 (0, 0)
	1 iload_1 (0, 0)
	2 invokevirtual (0, 0)
	3 org/apache/commons/math3/linear/BlockFieldMatrix.checkColumnIndex:(I)V (0, 0)
	5 aload_0 (0, 0)
	6 invokevirtual (0, 0)
	7 org/apache/commons/math3/linear/BlockFieldMatrix.getField:()Lorg/apache/commons/math3/Field; (0, 0)
	9 aload_0 (0, 0)
	10 getfield (0, 0)
	11 org/apache/commons/math3/linear/BlockFieldMatrix.rows:I (0, 0)
	13 invokestatic (0, 0)
	14 org/apache/commons/math3/util/MathArrays.buildArray:(Lorg/apache/commons/math3/Field;I)[Ljava/lang/Object; (0, 0)
	16 checkcast (0, 0)
	17 [Lorg/apache/commons/math3/FieldElement; (0, 0)
	19 astore_2 (0, 0)
	20 iload_1 (1, 4)
	21 bipush (1, 4)
	22 36 (1, 4)
	23 idiv (1, 4)
	24 istore_3 (1, 4)
	25 iload_1 (1, 4)
	26 iload_3 (1, 4)
	27 bipush (1, 4)
	28 36 (1, 4)
	29 imul (1, 4)
	30 isub (1, 4)
	31 istore (1, 4)
	32 #4 (1, 4)
	33 aload_0 (1, 4)
	34 iload_3 (1, 4)
	35 invokespecial (1, 4)
	36 org/apache/commons/math3/linear/BlockFieldMatrix.blockWidth:(I)I (1, 4)
	38 istore (1, 4)
	39 #5 (1, 4)
	40 iconst_0 (1, 4)
	41 istore (1, 4)
	42 #6 (1, 4)
	43 iconst_0 (2, 4)
	44 istore (2, 4)
	45 #7 (2, 4)
	46 iload (2, 4)
	47 #7 (2, 4)
	48 aload_0 (2, 4)
	49 getfield (2, 4)
	50 org/apache/commons/math3/linear/BlockFieldMatrix.blockRows:I (2, 4)
	52 if_icmpge (2, 4)
	53 67 (2, 4)
	55 aload_0 (2, 4)
	56 iload (2, 4)
	57 #7 (2, 4)
	58 invokespecial (2, 4)
	59 org/apache/commons/math3/linear/BlockFieldMatrix.blockHeight:(I)I (2, 4)
	61 istore (2, 4)
	62 #8 (2, 4)
	63 aload_0 (2, 4)
	64 getfield (2, 4)
	65 org/apache/commons/math3/linear/BlockFieldMatrix.blocks:[[Lorg/apache/commons/math3/FieldElement; (2, 4)
	67 iload (2, 4)
	68 #7 (2, 4)
	69 aload_0 (2, 4)
	70 getfield (2, 4)
	71 org/apache/commons/math3/linear/BlockFieldMatrix.blockColumns:I (2, 4)
	73 imul (2, 4)
	74 iload_3 (2, 4)
	75 iadd (2, 4)
	76 aaload (2, 4)
	77 astore (2, 4)
	78 #9 (2, 4)
	79 iconst_0 (3, 4)
	80 istore (3, 4)
	81 #10 (3, 4)
	82 iload (3, 4)
	83 #10 (3, 4)
	84 iload (3, 4)
	85 #8 (3, 4)
	86 if_icmpge (3, 4)
	87 27 (3, 4)
	89 aload_2 (3, 4)
	90 iload (3, 4)
	91 #6 (3, 4)
	92 iinc (3, 4)
	93 #6 (3, 4)
	94 25 (3, 4)
	95 aload (3, 4)
	96 #9 (3, 4)
	97 iload (3, 4)
	98 #10 (3, 4)
	99 iload (3, 4)
	100 #5 (3, 4)
	101 imul (3, 4)
	102 iload (3, 4)
	103 #4 (3, 4)
	104 iadd (3, 4)
	105 aaload (3, 4)
	106 aastore (3, 4)
	107 iinc (3, 4)
	108 #10 (3, 4)
	109 -89 (3, 4)
	110 goto (3, 4)
	111 -28 (3, 4)
	113 iinc (3, 4)
	114 #7 (3, 4)
	115 -89 (3, 4)
	116 goto (3, 4)
	117 -70 (3, 4)
	119 new (2, 4)
	120 org/apache/commons/math3/linear/ArrayFieldVector (2, 4)
	122 dup (2, 4)
	123 aload_0 (2, 4)
	124 invokevirtual (2, 4)
	125 org/apache/commons/math3/linear/BlockFieldMatrix.getField:()Lorg/apache/commons/math3/Field; (2, 4)
	127 aload_2 (2, 4)
	128 iconst_0 (2, 4)
	129 invokespecial (2, 4)
	130 org/apache/commons/math3/linear/ArrayFieldVector.<init>:(Lorg/apache/commons/math3/Field;[Lorg/apache/commons/math3/FieldElement;Z)V (2, 4)
	132 areturn (1, 4)

Method: setColumnVector
	0 aload_0 (0, 0)
	1 iload_1 (0, 0)
	2 aload_2 (0, 0)
	3 checkcast (0, 0)
	4 org/apache/commons/math3/linear/ArrayFieldVector (0, 0)
	6 invokevirtual (0, 0)
	7 org/apache/commons/math3/linear/ArrayFieldVector.getDataRef:()[Lorg/apache/commons/math3/FieldElement; (0, 0)
	9 invokevirtual (0, 0)
	10 org/apache/commons/math3/linear/BlockFieldMatrix.setColumn:(I[Lorg/apache/commons/math3/FieldElement;)V (0, 0)
	12 goto (0, 0)
	13 10 (0, 0)
	15 astore_3 (0, 0)
	16 aload_0 (0, 0)
	17 iload_1 (0, 0)
	18 aload_2 (0, 0)
	19 invokespecial (0, 0)
	20 org/apache/commons/math3/linear/AbstractFieldMatrix.setColumnVector:(ILorg/apache/commons/math3/linear/FieldVector;)V (0, 0)
	22 return (0, 0)

Method: getRow
	0 aload_0 (0, 0)
	1 iload_1 (0, 0)
	2 invokevirtual (0, 0)
	3 org/apache/commons/math3/linear/BlockFieldMatrix.checkRowIndex:(I)V (0, 0)
	5 aload_0 (0, 0)
	6 invokevirtual (0, 0)
	7 org/apache/commons/math3/linear/BlockFieldMatrix.getField:()Lorg/apache/commons/math3/Field; (0, 0)
	9 aload_0 (0, 0)
	10 getfield (0, 0)
	11 org/apache/commons/math3/linear/BlockFieldMatrix.columns:I (0, 0)
	13 invokestatic (0, 0)
	14 org/apache/commons/math3/util/MathArrays.buildArray:(Lorg/apache/commons/math3/Field;I)[Ljava/lang/Object; (0, 0)
	16 checkcast (0, 0)
	17 [Lorg/apache/commons/math3/FieldElement; (0, 0)
	19 astore_2 (0, 0)
	20 iload_1 (1, 4)
	21 bipush (1, 4)
	22 36 (1, 4)
	23 idiv (1, 4)
	24 istore_3 (1, 4)
	25 iload_1 (1, 4)
	26 iload_3 (1, 4)
	27 bipush (1, 4)
	28 36 (1, 4)
	29 imul (1, 4)
	30 isub (1, 4)
	31 istore (1, 4)
	32 #4 (1, 4)
	33 iconst_0 (1, 4)
	34 istore (1, 4)
	35 #5 (1, 4)
	36 iconst_0 (2, 4)
	37 istore (2, 4)
	38 #6 (2, 4)
	39 iload (2, 4)
	40 #6 (2, 4)
	41 aload_0 (2, 4)
	42 getfield (2, 4)
	43 org/apache/commons/math3/linear/BlockFieldMatrix.blockColumns:I (2, 4)
	45 if_icmpge (2, 4)
	46 55 (2, 4)
	48 aload_0 (2, 4)
	49 iload (2, 4)
	50 #6 (2, 4)
	51 invokespecial (2, 4)
	52 org/apache/commons/math3/linear/BlockFieldMatrix.blockWidth:(I)I (2, 4)
	54 istore (2, 4)
	55 #7 (2, 4)
	56 aload_0 (2, 4)
	57 getfield (2, 4)
	58 org/apache/commons/math3/linear/BlockFieldMatrix.blocks:[[Lorg/apache/commons/math3/FieldElement; (2, 4)
	60 iload_3 (2, 4)
	61 aload_0 (2, 4)
	62 getfield (2, 4)
	63 org/apache/commons/math3/linear/BlockFieldMatrix.blockColumns:I (2, 4)
	65 imul (2, 4)
	66 iload (2, 4)
	67 #6 (2, 4)
	68 iadd (2, 4)
	69 aaload (2, 4)
	70 astore (2, 4)
	71 #8 (2, 4)
	72 aload (2, 4)
	73 #8 (2, 4)
	74 iload (2, 4)
	75 #4 (2, 4)
	76 iload (2, 4)
	77 #7 (2, 4)
	78 imul (2, 4)
	79 aload_2 (2, 4)
	80 iload (2, 4)
	81 #5 (2, 4)
	82 iload (2, 4)
	83 #7 (2, 4)
	84 invokestatic (2, 4)
	85 java/lang/System.arraycopy:(Ljava/lang/Object;ILjava/lang/Object;II)V (2, 4)
	87 iload (2, 4)
	88 #5 (2, 4)
	89 iload (2, 4)
	90 #7 (2, 4)
	91 iadd (2, 4)
	92 istore (2, 4)
	93 #5 (2, 4)
	94 iinc (2, 4)
	95 #6 (2, 4)
	96 -89 (2, 4)
	97 goto (2, 4)
	98 -58 (2, 4)
	100 aload_2 (1, 4)
	101 areturn (0, 4)

Method: setRow
	0 aload_0 (0, 0)
	1 iload_1 (0, 0)
	2 invokevirtual (0, 0)
	3 org/apache/commons/math3/linear/BlockFieldMatrix.checkRowIndex:(I)V (0, 0)
	5 aload_0 (0, 0)
	6 invokevirtual (0, 0)
	7 org/apache/commons/math3/linear/BlockFieldMatrix.getColumnDimension:()I (0, 0)
	9 istore_3 (0, 0)
	10 aload_2 (1, 1)
	11 arraylength (1, 1)
	12 iload_3 (1, 1)
	13 if_icmpeq (1, 1)
	14 16 (1, 1)
	16 new (1, 1)
	17 org/apache/commons/math3/linear/MatrixDimensionMismatchException (1, 1)
	19 dup (1, 1)
	20 iconst_1 (1, 1)
	21 aload_2 (1, 1)
	22 arraylength (1, 1)
	23 iconst_1 (1, 1)
	24 iload_3 (1, 1)
	25 invokespecial (1, 1)
	26 org/apache/commons/math3/linear/MatrixDimensionMismatchException.<init>:(IIII)V (1, 1)
	28 athrow (1, 1)
	29 iload_1 (1, 4)
	30 bipush (1, 4)
	31 36 (1, 4)
	32 idiv (1, 4)
	33 istore (1, 4)
	34 #4 (1, 4)
	35 iload_1 (1, 4)
	36 iload (1, 4)
	37 #4 (1, 4)
	38 bipush (1, 4)
	39 36 (1, 4)
	40 imul (1, 4)
	41 isub (1, 4)
	42 istore (1, 4)
	43 #5 (1, 4)
	44 iconst_0 (1, 4)
	45 istore (1, 4)
	46 #6 (1, 4)
	47 iconst_0 (2, 4)
	48 istore (2, 4)
	49 #7 (2, 4)
	50 iload (2, 4)
	51 #7 (2, 4)
	52 aload_0 (2, 4)
	53 getfield (2, 4)
	54 org/apache/commons/math3/linear/BlockFieldMatrix.blockColumns:I (2, 4)
	56 if_icmpge (2, 4)
	57 56 (2, 4)
	59 aload_0 (2, 4)
	60 iload (2, 4)
	61 #7 (2, 4)
	62 invokespecial (2, 4)
	63 org/apache/commons/math3/linear/BlockFieldMatrix.blockWidth:(I)I (2, 4)
	65 istore (2, 4)
	66 #8 (2, 4)
	67 aload_0 (2, 4)
	68 getfield (2, 4)
	69 org/apache/commons/math3/linear/BlockFieldMatrix.blocks:[[Lorg/apache/commons/math3/FieldElement; (2, 4)
	71 iload (2, 4)
	72 #4 (2, 4)
	73 aload_0 (2, 4)
	74 getfield (2, 4)
	75 org/apache/commons/math3/linear/BlockFieldMatrix.blockColumns:I (2, 4)
	77 imul (2, 4)
	78 iload (2, 4)
	79 #7 (2, 4)
	80 iadd (2, 4)
	81 aaload (2, 4)
	82 astore (2, 4)
	83 #9 (2, 4)
	84 aload_2 (2, 4)
	85 iload (2, 4)
	86 #6 (2, 4)
	87 aload (2, 4)
	88 #9 (2, 4)
	89 iload (2, 4)
	90 #5 (2, 4)
	91 iload (2, 4)
	92 #8 (2, 4)
	93 imul (2, 4)
	94 iload (2, 4)
	95 #8 (2, 4)
	96 invokestatic (2, 4)
	97 java/lang/System.arraycopy:(Ljava/lang/Object;ILjava/lang/Object;II)V (2, 4)
	99 iload (2, 4)
	100 #6 (2, 4)
	101 iload (2, 4)
	102 #8 (2, 4)
	103 iadd (2, 4)
	104 istore (2, 4)
	105 #6 (2, 4)
	106 iinc (2, 4)
	107 #7 (2, 4)
	108 -89 (2, 4)
	109 goto (2, 4)
	110 -59 (2, 4)
	112 return (0, 4)

Method: getColumn
	0 aload_0 (0, 0)
	1 iload_1 (0, 0)
	2 invokevirtual (0, 0)
	3 org/apache/commons/math3/linear/BlockFieldMatrix.checkColumnIndex:(I)V (0, 0)
	5 aload_0 (0, 0)
	6 invokevirtual (0, 0)
	7 org/apache/commons/math3/linear/BlockFieldMatrix.getField:()Lorg/apache/commons/math3/Field; (0, 0)
	9 aload_0 (0, 0)
	10 getfield (0, 0)
	11 org/apache/commons/math3/linear/BlockFieldMatrix.rows:I (0, 0)
	13 invokestatic (0, 0)
	14 org/apache/commons/math3/util/MathArrays.buildArray:(Lorg/apache/commons/math3/Field;I)[Ljava/lang/Object; (0, 0)
	16 checkcast (0, 0)
	17 [Lorg/apache/commons/math3/FieldElement; (0, 0)
	19 astore_2 (0, 0)
	20 iload_1 (1, 4)
	21 bipush (1, 4)
	22 36 (1, 4)
	23 idiv (1, 4)
	24 istore_3 (1, 4)
	25 iload_1 (1, 4)
	26 iload_3 (1, 4)
	27 bipush (1, 4)
	28 36 (1, 4)
	29 imul (1, 4)
	30 isub (1, 4)
	31 istore (1, 4)
	32 #4 (1, 4)
	33 aload_0 (1, 4)
	34 iload_3 (1, 4)
	35 invokespecial (1, 4)
	36 org/apache/commons/math3/linear/BlockFieldMatrix.blockWidth:(I)I (1, 4)
	38 istore (1, 4)
	39 #5 (1, 4)
	40 iconst_0 (1, 4)
	41 istore (1, 4)
	42 #6 (1, 4)
	43 iconst_0 (2, 4)
	44 istore (2, 4)
	45 #7 (2, 4)
	46 iload (2, 4)
	47 #7 (2, 4)
	48 aload_0 (2, 4)
	49 getfield (2, 4)
	50 org/apache/commons/math3/linear/BlockFieldMatrix.blockRows:I (2, 4)
	52 if_icmpge (2, 4)
	53 67 (2, 4)
	55 aload_0 (2, 4)
	56 iload (2, 4)
	57 #7 (2, 4)
	58 invokespecial (2, 4)
	59 org/apache/commons/math3/linear/BlockFieldMatrix.blockHeight:(I)I (2, 4)
	61 istore (2, 4)
	62 #8 (2, 4)
	63 aload_0 (2, 4)
	64 getfield (2, 4)
	65 org/apache/commons/math3/linear/BlockFieldMatrix.blocks:[[Lorg/apache/commons/math3/FieldElement; (2, 4)
	67 iload (2, 4)
	68 #7 (2, 4)
	69 aload_0 (2, 4)
	70 getfield (2, 4)
	71 org/apache/commons/math3/linear/BlockFieldMatrix.blockColumns:I (2, 4)
	73 imul (2, 4)
	74 iload_3 (2, 4)
	75 iadd (2, 4)
	76 aaload (2, 4)
	77 astore (2, 4)
	78 #9 (2, 4)
	79 iconst_0 (3, 4)
	80 istore (3, 4)
	81 #10 (3, 4)
	82 iload (3, 4)
	83 #10 (3, 4)
	84 iload (3, 4)
	85 #8 (3, 4)
	86 if_icmpge (3, 4)
	87 27 (3, 4)
	89 aload_2 (3, 4)
	90 iload (3, 4)
	91 #6 (3, 4)
	92 iinc (3, 4)
	93 #6 (3, 4)
	94 25 (3, 4)
	95 aload (3, 4)
	96 #9 (3, 4)
	97 iload (3, 4)
	98 #10 (3, 4)
	99 iload (3, 4)
	100 #5 (3, 4)
	101 imul (3, 4)
	102 iload (3, 4)
	103 #4 (3, 4)
	104 iadd (3, 4)
	105 aaload (3, 4)
	106 aastore (3, 4)
	107 iinc (3, 4)
	108 #10 (3, 4)
	109 -89 (3, 4)
	110 goto (3, 4)
	111 -28 (3, 4)
	113 iinc (3, 4)
	114 #7 (3, 4)
	115 -89 (3, 4)
	116 goto (3, 4)
	117 -70 (3, 4)
	119 aload_2 (2, 4)
	120 areturn (1, 4)

Method: setColumn
	0 aload_0 (0, 0)
	1 iload_1 (0, 0)
	2 invokevirtual (0, 0)
	3 org/apache/commons/math3/linear/BlockFieldMatrix.checkColumnIndex:(I)V (0, 0)
	5 aload_0 (0, 0)
	6 invokevirtual (0, 0)
	7 org/apache/commons/math3/linear/BlockFieldMatrix.getRowDimension:()I (0, 0)
	9 istore_3 (0, 0)
	10 aload_2 (1, 1)
	11 arraylength (1, 1)
	12 iload_3 (1, 1)
	13 if_icmpeq (1, 1)
	14 16 (1, 1)
	16 new (1, 1)
	17 org/apache/commons/math3/linear/MatrixDimensionMismatchException (1, 1)
	19 dup (1, 1)
	20 aload_2 (1, 1)
	21 arraylength (1, 1)
	22 iconst_1 (1, 1)
	23 iload_3 (1, 1)
	24 iconst_1 (1, 1)
	25 invokespecial (1, 1)
	26 org/apache/commons/math3/linear/MatrixDimensionMismatchException.<init>:(IIII)V (1, 1)
	28 athrow (1, 1)
	29 iload_1 (1, 4)
	30 bipush (1, 4)
	31 36 (1, 4)
	32 idiv (1, 4)
	33 istore (1, 4)
	34 #4 (1, 4)
	35 iload_1 (1, 4)
	36 iload (1, 4)
	37 #4 (1, 4)
	38 bipush (1, 4)
	39 36 (1, 4)
	40 imul (1, 4)
	41 isub (1, 4)
	42 istore (1, 4)
	43 #5 (1, 4)
	44 aload_0 (1, 4)
	45 iload (1, 4)
	46 #4 (1, 4)
	47 invokespecial (1, 4)
	48 org/apache/commons/math3/linear/BlockFieldMatrix.blockWidth:(I)I (1, 4)
	50 istore (1, 4)
	51 #6 (1, 4)
	52 iconst_0 (1, 4)
	53 istore (1, 4)
	54 #7 (1, 4)
	55 iconst_0 (2, 4)
	56 istore (2, 4)
	57 #8 (2, 4)
	58 iload (2, 4)
	59 #8 (2, 4)
	60 aload_0 (2, 4)
	61 getfield (2, 4)
	62 org/apache/commons/math3/linear/BlockFieldMatrix.blockRows:I (2, 4)
	64 if_icmpge (2, 4)
	65 68 (2, 4)
	67 aload_0 (2, 4)
	68 iload (2, 4)
	69 #8 (2, 4)
	70 invokespecial (2, 4)
	71 org/apache/commons/math3/linear/BlockFieldMatrix.blockHeight:(I)I (2, 4)
	73 istore (2, 4)
	74 #9 (2, 4)
	75 aload_0 (2, 4)
	76 getfield (2, 4)
	77 org/apache/commons/math3/linear/BlockFieldMatrix.blocks:[[Lorg/apache/commons/math3/FieldElement; (2, 4)
	79 iload (2, 4)
	80 #8 (2, 4)
	81 aload_0 (2, 4)
	82 getfield (2, 4)
	83 org/apache/commons/math3/linear/BlockFieldMatrix.blockColumns:I (2, 4)
	85 imul (2, 4)
	86 iload (2, 4)
	87 #4 (2, 4)
	88 iadd (2, 4)
	89 aaload (2, 4)
	90 astore (2, 4)
	91 #10 (2, 4)
	92 iconst_0 (3, 4)
	93 istore (3, 4)
	94 #11 (3, 4)
	95 iload (3, 4)
	96 #11 (3, 4)
	97 iload (3, 4)
	98 #9 (3, 4)
	99 if_icmpge (3, 4)
	100 27 (3, 4)
	102 aload (3, 4)
	103 #10 (3, 4)
	104 iload (3, 4)
	105 #11 (3, 4)
	106 iload (3, 4)
	107 #6 (3, 4)
	108 imul (3, 4)
	109 iload (3, 4)
	110 #5 (3, 4)
	111 iadd (3, 4)
	112 aload_2 (3, 4)
	113 iload (3, 4)
	114 #7 (3, 4)
	115 iinc (3, 4)
	116 #7 (3, 4)
	117 50 (3, 4)
	118 aaload (3, 4)
	119 aastore (3, 4)
	120 iinc (3, 4)
	121 #11 (3, 4)
	122 -89 (3, 4)
	123 goto (3, 4)
	124 -28 (3, 4)
	126 iinc (3, 4)
	127 #8 (3, 4)
	128 -89 (3, 4)
	129 goto (3, 4)
	130 -71 (3, 4)
	132 return (0, 4)

Method: getEntry
	0 aload_0 (0, 0)
	1 iload_1 (0, 0)
	2 invokevirtual (0, 0)
	3 org/apache/commons/math3/linear/BlockFieldMatrix.checkRowIndex:(I)V (0, 0)
	5 aload_0 (0, 0)
	6 iload_2 (0, 0)
	7 invokevirtual (0, 0)
	8 org/apache/commons/math3/linear/BlockFieldMatrix.checkColumnIndex:(I)V (0, 0)
	10 iload_1 (0, 0)
	11 bipush (0, 0)
	12 36 (0, 0)
	13 idiv (0, 0)
	14 istore_3 (0, 0)
	15 iload_2 (0, 0)
	16 bipush (0, 0)
	17 36 (0, 0)
	18 idiv (0, 0)
	19 istore (0, 0)
	20 #4 (0, 0)
	21 iload_1 (0, 0)
	22 iload_3 (0, 0)
	23 bipush (0, 0)
	24 36 (0, 0)
	25 imul (0, 0)
	26 isub (0, 0)
	27 aload_0 (0, 0)
	28 iload (0, 0)
	29 #4 (0, 0)
	30 invokespecial (0, 0)
	31 org/apache/commons/math3/linear/BlockFieldMatrix.blockWidth:(I)I (0, 0)
	33 imul (0, 0)
	34 iload_2 (0, 0)
	35 iload (0, 0)
	36 #4 (0, 0)
	37 bipush (0, 0)
	38 36 (0, 0)
	39 imul (0, 0)
	40 isub (0, 0)
	41 iadd (0, 0)
	42 istore (0, 0)
	43 #5 (0, 0)
	44 aload_0 (0, 0)
	45 getfield (0, 0)
	46 org/apache/commons/math3/linear/BlockFieldMatrix.blocks:[[Lorg/apache/commons/math3/FieldElement; (0, 0)
	48 iload_3 (0, 0)
	49 aload_0 (0, 0)
	50 getfield (0, 0)
	51 org/apache/commons/math3/linear/BlockFieldMatrix.blockColumns:I (0, 0)
	53 imul (0, 0)
	54 iload (0, 0)
	55 #4 (0, 0)
	56 iadd (0, 0)
	57 aaload (0, 0)
	58 iload (0, 0)
	59 #5 (0, 0)
	60 aaload (0, 0)
	61 areturn (0, 0)

Method: setEntry
	0 aload_0 (0, 0)
	1 iload_1 (0, 0)
	2 invokevirtual (0, 0)
	3 org/apache/commons/math3/linear/BlockFieldMatrix.checkRowIndex:(I)V (0, 0)
	5 aload_0 (0, 0)
	6 iload_2 (0, 0)
	7 invokevirtual (0, 0)
	8 org/apache/commons/math3/linear/BlockFieldMatrix.checkColumnIndex:(I)V (0, 0)
	10 iload_1 (0, 0)
	11 bipush (0, 0)
	12 36 (0, 0)
	13 idiv (0, 0)
	14 istore (0, 0)
	15 #4 (0, 0)
	16 iload_2 (0, 0)
	17 bipush (0, 0)
	18 36 (0, 0)
	19 idiv (0, 0)
	20 istore (0, 0)
	21 #5 (0, 0)
	22 iload_1 (0, 0)
	23 iload (0, 0)
	24 #4 (0, 0)
	25 bipush (0, 0)
	26 36 (0, 0)
	27 imul (0, 0)
	28 isub (0, 0)
	29 aload_0 (0, 0)
	30 iload (0, 0)
	31 #5 (0, 0)
	32 invokespecial (0, 0)
	33 org/apache/commons/math3/linear/BlockFieldMatrix.blockWidth:(I)I (0, 0)
	35 imul (0, 0)
	36 iload_2 (0, 0)
	37 iload (0, 0)
	38 #5 (0, 0)
	39 bipush (0, 0)
	40 36 (0, 0)
	41 imul (0, 0)
	42 isub (0, 0)
	43 iadd (0, 0)
	44 istore (0, 0)
	45 #6 (0, 0)
	46 aload_0 (0, 0)
	47 getfield (0, 0)
	48 org/apache/commons/math3/linear/BlockFieldMatrix.blocks:[[Lorg/apache/commons/math3/FieldElement; (0, 0)
	50 iload (0, 0)
	51 #4 (0, 0)
	52 aload_0 (0, 0)
	53 getfield (0, 0)
	54 org/apache/commons/math3/linear/BlockFieldMatrix.blockColumns:I (0, 0)
	56 imul (0, 0)
	57 iload (0, 0)
	58 #5 (0, 0)
	59 iadd (0, 0)
	60 aaload (0, 0)
	61 iload (0, 0)
	62 #6 (0, 0)
	63 aload_3 (0, 0)
	64 aastore (0, 0)
	65 return (0, 0)

Method: addToEntry
	0 aload_0 (0, 0)
	1 iload_1 (0, 0)
	2 invokevirtual (0, 0)
	3 org/apache/commons/math3/linear/BlockFieldMatrix.checkRowIndex:(I)V (0, 0)
	5 aload_0 (0, 0)
	6 iload_2 (0, 0)
	7 invokevirtual (0, 0)
	8 org/apache/commons/math3/linear/BlockFieldMatrix.checkColumnIndex:(I)V (0, 0)
	10 iload_1 (0, 0)
	11 bipush (0, 0)
	12 36 (0, 0)
	13 idiv (0, 0)
	14 istore (0, 0)
	15 #4 (0, 0)
	16 iload_2 (0, 0)
	17 bipush (0, 0)
	18 36 (0, 0)
	19 idiv (0, 0)
	20 istore (0, 0)
	21 #5 (0, 0)
	22 iload_1 (0, 0)
	23 iload (0, 0)
	24 #4 (0, 0)
	25 bipush (0, 0)
	26 36 (0, 0)
	27 imul (0, 0)
	28 isub (0, 0)
	29 aload_0 (0, 0)
	30 iload (0, 0)
	31 #5 (0, 0)
	32 invokespecial (0, 0)
	33 org/apache/commons/math3/linear/BlockFieldMatrix.blockWidth:(I)I (0, 0)
	35 imul (0, 0)
	36 iload_2 (0, 0)
	37 iload (0, 0)
	38 #5 (0, 0)
	39 bipush (0, 0)
	40 36 (0, 0)
	41 imul (0, 0)
	42 isub (0, 0)
	43 iadd (0, 0)
	44 istore (0, 0)
	45 #6 (0, 0)
	46 aload_0 (0, 0)
	47 getfield (0, 0)
	48 org/apache/commons/math3/linear/BlockFieldMatrix.blocks:[[Lorg/apache/commons/math3/FieldElement; (0, 0)
	50 iload (0, 0)
	51 #4 (0, 0)
	52 aload_0 (0, 0)
	53 getfield (0, 0)
	54 org/apache/commons/math3/linear/BlockFieldMatrix.blockColumns:I (0, 0)
	56 imul (0, 0)
	57 iload (0, 0)
	58 #5 (0, 0)
	59 iadd (0, 0)
	60 aaload (0, 0)
	61 astore (0, 0)
	62 #7 (0, 0)
	63 aload (0, 0)
	64 #7 (0, 0)
	65 iload (0, 0)
	66 #6 (0, 0)
	67 aload (0, 0)
	68 #7 (0, 0)
	69 iload (0, 0)
	70 #6 (0, 0)
	71 aaload (0, 0)
	72 aload_3 (0, 0)
	73 invokeinterface (0, 0)
	74 org/apache/commons/math3/FieldElement.org/apache/commons/math3/FieldElement (0, 0)
	76 0 (0, 0)
	78 checkcast (0, 0)
	79 org/apache/commons/math3/FieldElement (0, 0)
	81 aastore (0, 0)
	82 return (0, 0)

Method: multiplyEntry
	0 aload_0 (0, 0)
	1 iload_1 (0, 0)
	2 invokevirtual (0, 0)
	3 org/apache/commons/math3/linear/BlockFieldMatrix.checkRowIndex:(I)V (0, 0)
	5 aload_0 (0, 0)
	6 iload_2 (0, 0)
	7 invokevirtual (0, 0)
	8 org/apache/commons/math3/linear/BlockFieldMatrix.checkColumnIndex:(I)V (0, 0)
	10 iload_1 (0, 0)
	11 bipush (0, 0)
	12 36 (0, 0)
	13 idiv (0, 0)
	14 istore (0, 0)
	15 #4 (0, 0)
	16 iload_2 (0, 0)
	17 bipush (0, 0)
	18 36 (0, 0)
	19 idiv (0, 0)
	20 istore (0, 0)
	21 #5 (0, 0)
	22 iload_1 (0, 0)
	23 iload (0, 0)
	24 #4 (0, 0)
	25 bipush (0, 0)
	26 36 (0, 0)
	27 imul (0, 0)
	28 isub (0, 0)
	29 aload_0 (0, 0)
	30 iload (0, 0)
	31 #5 (0, 0)
	32 invokespecial (0, 0)
	33 org/apache/commons/math3/linear/BlockFieldMatrix.blockWidth:(I)I (0, 0)
	35 imul (0, 0)
	36 iload_2 (0, 0)
	37 iload (0, 0)
	38 #5 (0, 0)
	39 bipush (0, 0)
	40 36 (0, 0)
	41 imul (0, 0)
	42 isub (0, 0)
	43 iadd (0, 0)
	44 istore (0, 0)
	45 #6 (0, 0)
	46 aload_0 (0, 0)
	47 getfield (0, 0)
	48 org/apache/commons/math3/linear/BlockFieldMatrix.blocks:[[Lorg/apache/commons/math3/FieldElement; (0, 0)
	50 iload (0, 0)
	51 #4 (0, 0)
	52 aload_0 (0, 0)
	53 getfield (0, 0)
	54 org/apache/commons/math3/linear/BlockFieldMatrix.blockColumns:I (0, 0)
	56 imul (0, 0)
	57 iload (0, 0)
	58 #5 (0, 0)
	59 iadd (0, 0)
	60 aaload (0, 0)
	61 astore (0, 0)
	62 #7 (0, 0)
	63 aload (0, 0)
	64 #7 (0, 0)
	65 iload (0, 0)
	66 #6 (0, 0)
	67 aload (0, 0)
	68 #7 (0, 0)
	69 iload (0, 0)
	70 #6 (0, 0)
	71 aaload (0, 0)
	72 aload_3 (0, 0)
	73 invokeinterface (0, 0)
	74 org/apache/commons/math3/FieldElement.multiply:(Lorg/apache/commons/math3/linear/BlockFieldMatrix;)Lorg/apache/commons/math3/linear/BlockFieldMatrix; (0, 0)
	76 0 (0, 0)
	78 checkcast (0, 0)
	79 org/apache/commons/math3/FieldElement (0, 0)
	81 aastore (0, 0)
	82 return (0, 0)

Method: transpose
	0 aload_0 (0, 0)
	1 invokevirtual (0, 0)
	2 org/apache/commons/math3/linear/BlockFieldMatrix.getRowDimension:()I (0, 0)
	4 istore_1 (0, 0)
	5 aload_0 (0, 0)
	6 invokevirtual (0, 0)
	7 org/apache/commons/math3/linear/BlockFieldMatrix.getColumnDimension:()I (0, 0)
	9 istore_2 (0, 0)
	10 new (0, 0)
	11 org/apache/commons/math3/linear/BlockFieldMatrix (0, 0)
	13 dup (0, 0)
	14 aload_0 (0, 0)
	15 invokevirtual (0, 0)
	16 org/apache/commons/math3/linear/BlockFieldMatrix.getField:()Lorg/apache/commons/math3/Field; (0, 0)
	18 iload_2 (0, 0)
	19 iload_1 (0, 0)
	20 invokespecial (0, 0)
	21 org/apache/commons/math3/linear/BlockFieldMatrix.<init>:(Lorg/apache/commons/math3/Field;II)V (0, 0)
	23 astore_3 (0, 0)
	24 iconst_0 (1, 4)
	25 istore (1, 4)
	26 #4 (1, 4)
	27 iconst_0 (2, 4)
	28 istore (2, 4)
	29 #5 (2, 4)
	30 iload (2, 4)
	31 #5 (2, 4)
	32 aload_0 (2, 4)
	33 getfield (2, 4)
	34 org/apache/commons/math3/linear/BlockFieldMatrix.blockColumns:I (2, 4)
	36 if_icmpge (2, 4)
	37 169 (2, 4)
	39 iconst_0 (3, 4)
	40 istore (3, 4)
	41 #6 (3, 4)
	42 iload (3, 4)
	43 #6 (3, 4)
	44 aload_0 (3, 4)
	45 getfield (3, 4)
	46 org/apache/commons/math3/linear/BlockFieldMatrix.blockRows:I (3, 4)
	48 if_icmpge (3, 4)
	49 151 (3, 4)
	51 aload_3 (3, 4)
	52 getfield (3, 4)
	53 org/apache/commons/math3/linear/BlockFieldMatrix.blocks:[[Lorg/apache/commons/math3/FieldElement; (3, 4)
	55 iload (3, 4)
	56 #4 (3, 4)
	57 aaload (3, 4)
	58 astore (3, 4)
	59 #7 (3, 4)
	60 aload_0 (3, 4)
	61 getfield (3, 4)
	62 org/apache/commons/math3/linear/BlockFieldMatrix.blocks:[[Lorg/apache/commons/math3/FieldElement; (3, 4)
	64 iload (3, 4)
	65 #6 (3, 4)
	66 aload_0 (3, 4)
	67 getfield (3, 4)
	68 org/apache/commons/math3/linear/BlockFieldMatrix.blockColumns:I (3, 4)
	70 imul (3, 4)
	71 iload (3, 4)
	72 #5 (3, 4)
	73 iadd (3, 4)
	74 aaload (3, 4)
	75 astore (3, 4)
	76 #8 (3, 4)
	77 iload (3, 4)
	78 #5 (3, 4)
	79 bipush (3, 4)
	80 36 (3, 4)
	81 imul (3, 4)
	82 istore (3, 4)
	83 #9 (3, 4)
	84 iload (3, 4)
	85 #9 (3, 4)
	86 bipush (3, 4)
	87 36 (3, 4)
	88 iadd (3, 4)
	89 aload_0 (3, 4)
	90 getfield (3, 4)
	91 org/apache/commons/math3/linear/BlockFieldMatrix.columns:I (3, 4)
	93 invokestatic (3, 4)
	94 org/apache/commons/math3/util/FastMath.min:(II)I (3, 4)
	96 istore (3, 4)
	97 #10 (3, 4)
	98 iload (3, 4)
	99 #6 (3, 4)
	100 bipush (3, 4)
	101 36 (3, 4)
	102 imul (3, 4)
	103 istore (3, 4)
	104 #11 (3, 4)
	105 iload (3, 4)
	106 #11 (3, 4)
	107 bipush (3, 4)
	108 36 (3, 4)
	109 iadd (3, 4)
	110 aload_0 (3, 4)
	111 getfield (3, 4)
	112 org/apache/commons/math3/linear/BlockFieldMatrix.rows:I (3, 4)
	114 invokestatic (3, 4)
	115 org/apache/commons/math3/util/FastMath.min:(II)I (3, 4)
	117 istore (3, 4)
	118 #12 (3, 4)
	119 iconst_0 (3, 4)
	120 istore (3, 4)
	121 #13 (3, 4)
	122 iload (4, 4)
	123 #9 (4, 4)
	124 istore (4, 4)
	125 #14 (4, 4)
	126 iload (4, 4)
	127 #14 (4, 4)
	128 iload (4, 4)
	129 #10 (4, 4)
	130 if_icmpge (4, 4)
	131 60 (4, 4)
	133 iload (4, 4)
	134 #10 (4, 4)
	135 iload (4, 4)
	136 #9 (4, 4)
	137 isub (4, 4)
	138 istore (4, 4)
	139 #15 (4, 4)
	140 iload (4, 4)
	141 #14 (4, 4)
	142 iload (4, 4)
	143 #9 (4, 4)
	144 isub (4, 4)
	145 istore (4, 4)
	146 #16 (4, 4)
	147 iload (5, 4)
	148 #11 (5, 4)
	149 istore (5, 4)
	150 #17 (5, 4)
	151 iload (5, 4)
	152 #17 (5, 4)
	153 iload (5, 4)
	154 #12 (5, 4)
	155 if_icmpge (5, 4)
	156 29 (5, 4)
	158 aload (5, 4)
	159 #7 (5, 4)
	160 iload (5, 4)
	161 #13 (5, 4)
	162 aload (5, 4)
	163 #8 (5, 4)
	164 iload (5, 4)
	165 #16 (5, 4)
	166 aaload (5, 4)
	167 aastore (5, 4)
	168 iinc (5, 4)
	169 #13 (5, 4)
	170 21 (5, 4)
	171 iload (5, 4)
	172 #16 (5, 4)
	173 iload (5, 4)
	174 #15 (5, 4)
	175 iadd (5, 4)
	176 istore (5, 4)
	177 #16 (5, 4)
	178 iinc (5, 4)
	179 #17 (5, 4)
	180 -89 (5, 4)
	181 goto (5, 4)
	182 -30 (5, 4)
	184 iinc (5, 4)
	185 #14 (5, 4)
	186 -89 (5, 4)
	187 goto (5, 4)
	188 -61 (5, 4)
	190 iinc (4, 4)
	191 #4 (4, 4)
	192 -124 (4, 4)
	193 iinc (4, 4)
	194 #6 (4, 4)
	195 -89 (4, 4)
	196 goto (4, 4)
	197 -154 (4, 4)
	199 iinc (4, 4)
	200 #5 (4, 4)
	201 -89 (4, 4)
	202 goto (4, 4)
	203 -172 (4, 4)
	205 aload_3 (3, 4)
	206 areturn (2, 4)

Method: getRowDimension
	0 aload_0 (0, 0)
	1 getfield (0, 0)
	2 org/apache/commons/math3/linear/BlockFieldMatrix.rows:I (0, 0)
	4 ireturn (0, 0)

Method: getColumnDimension
	0 aload_0 (0, 0)
	1 getfield (0, 0)
	2 org/apache/commons/math3/linear/BlockFieldMatrix.columns:I (0, 0)
	4 ireturn (0, 0)

Method: operate
	0 aload_1 (1, 1)
	1 arraylength (1, 1)
	2 aload_0 (1, 1)
	3 getfield (1, 1)
	4 org/apache/commons/math3/linear/BlockFieldMatrix.columns:I (1, 1)
	6 if_icmpeq (1, 1)
	7 17 (1, 1)
	9 new (1, 1)
	10 org/apache/commons/math3/exception/DimensionMismatchException (1, 1)
	12 dup (1, 1)
	13 aload_1 (1, 1)
	14 arraylength (1, 1)
	15 aload_0 (1, 1)
	16 getfield (1, 1)
	17 org/apache/commons/math3/linear/BlockFieldMatrix.columns:I (1, 1)
	19 invokespecial (1, 1)
	20 org/apache/commons/math3/exception/DimensionMismatchException.<init>:(II)V (1, 1)
	22 athrow (1, 1)
	23 aload_0 (0, 0)
	24 invokevirtual (0, 0)
	25 org/apache/commons/math3/linear/BlockFieldMatrix.getField:()Lorg/apache/commons/math3/Field; (0, 0)
	27 aload_0 (0, 0)
	28 getfield (0, 0)
	29 org/apache/commons/math3/linear/BlockFieldMatrix.rows:I (0, 0)
	31 invokestatic (0, 0)
	32 org/apache/commons/math3/util/MathArrays.buildArray:(Lorg/apache/commons/math3/Field;I)[Ljava/lang/Object; (0, 0)
	34 checkcast (0, 0)
	35 [Lorg/apache/commons/math3/FieldElement; (0, 0)
	37 astore_2 (0, 0)
	38 aload_0 (0, 0)
	39 invokevirtual (0, 0)
	40 org/apache/commons/math3/linear/BlockFieldMatrix.getField:()Lorg/apache/commons/math3/Field; (0, 0)
	42 invokeinterface (0, 0)
	43 org/apache/commons/math3/Field.getRowDimension:()I (0, 0)
	45 0 (0, 0)
	47 checkcast (0, 0)
	48 org/apache/commons/math3/FieldElement (0, 0)
	50 astore_3 (0, 0)
	51 iconst_0 (2, 4)
	52 istore (2, 4)
	53 #4 (2, 4)
	54 iload (2, 4)
	55 #4 (2, 4)
	56 aload_0 (2, 4)
	57 getfield (2, 4)
	58 org/apache/commons/math3/linear/BlockFieldMatrix.blockRows:I (2, 4)
	60 if_icmpge (2, 4)
	61 295 (2, 4)
	63 iload (2, 4)
	64 #4 (2, 4)
	65 bipush (2, 4)
	66 36 (2, 4)
	67 imul (2, 4)
	68 istore (2, 4)
	69 #5 (2, 4)
	70 iload (2, 4)
	71 #5 (2, 4)
	72 bipush (2, 4)
	73 36 (2, 4)
	74 iadd (2, 4)
	75 aload_0 (2, 4)
	76 getfield (2, 4)
	77 org/apache/commons/math3/linear/BlockFieldMatrix.rows:I (2, 4)
	79 invokestatic (2, 4)
	80 org/apache/commons/math3/util/FastMath.min:(II)I (2, 4)
	82 istore (2, 4)
	83 #6 (2, 4)
	84 iconst_0 (3, 4)
	85 istore (3, 4)
	86 #7 (3, 4)
	87 iload (3, 4)
	88 #7 (3, 4)
	89 aload_0 (3, 4)
	90 getfield (3, 4)
	91 org/apache/commons/math3/linear/BlockFieldMatrix.blockColumns:I (3, 4)
	93 if_icmpge (3, 4)
	94 256 (3, 4)
	96 aload_0 (3, 4)
	97 getfield (3, 4)
	98 org/apache/commons/math3/linear/BlockFieldMatrix.blocks:[[Lorg/apache/commons/math3/FieldElement; (3, 4)
	100 iload (3, 4)
	101 #4 (3, 4)
	102 aload_0 (3, 4)
	103 getfield (3, 4)
	104 org/apache/commons/math3/linear/BlockFieldMatrix.blockColumns:I (3, 4)
	106 imul (3, 4)
	107 iload (3, 4)
	108 #7 (3, 4)
	109 iadd (3, 4)
	110 aaload (3, 4)
	111 astore (3, 4)
	112 #8 (3, 4)
	113 iload (3, 4)
	114 #7 (3, 4)
	115 bipush (3, 4)
	116 36 (3, 4)
	117 imul (3, 4)
	118 istore (3, 4)
	119 #9 (3, 4)
	120 iload (3, 4)
	121 #9 (3, 4)
	122 bipush (3, 4)
	123 36 (3, 4)
	124 iadd (3, 4)
	125 aload_0 (3, 4)
	126 getfield (3, 4)
	127 org/apache/commons/math3/linear/BlockFieldMatrix.columns:I (3, 4)
	129 invokestatic (3, 4)
	130 org/apache/commons/math3/util/FastMath.min:(II)I (3, 4)
	132 istore (3, 4)
	133 #10 (3, 4)
	134 iconst_0 (3, 4)
	135 istore (3, 4)
	136 #11 (3, 4)
	137 iload (4, 4)
	138 #5 (4, 4)
	139 istore (4, 4)
	140 #12 (4, 4)
	141 iload (4, 4)
	142 #12 (4, 4)
	143 iload (4, 4)
	144 #6 (4, 4)
	145 if_icmpge (4, 4)
	146 198 (4, 4)
	148 aload_3 (4, 4)
	149 astore (4, 4)
	150 #13 (4, 4)
	151 iload (4, 4)
	152 #9 (4, 4)
	153 istore (4, 4)
	154 #14 (4, 4)
	155 iload (5, 3)
	156 #14 (5, 3)
	157 iload (5, 3)
	158 #10 (5, 3)
	159 iconst_3 (5, 3)
	160 isub (5, 3)
	161 if_icmpge (5, 3)
	162 116 (5, 3)
	164 aload (5, 3)
	165 #13 (5, 3)
	166 aload (5, 3)
	167 #8 (5, 3)
	168 iload (5, 3)
	169 #11 (5, 3)
	170 aaload (5, 3)
	171 aload_1 (5, 3)
	172 iload (5, 3)
	173 #14 (5, 3)
	174 aaload (5, 3)
	175 invokeinterface (5, 3)
	176 org/apache/commons/math3/FieldElement.multiply:(Lorg/apache/commons/math3/linear/BlockFieldMatrix;)Lorg/apache/commons/math3/linear/BlockFieldMatrix; (5, 3)
	178 0 (5, 3)
	180 invokeinterface (5, 3)
	181 org/apache/commons/math3/FieldElement.org/apache/commons/math3/FieldElement (5, 3)
	183 0 (5, 3)
	185 checkcast (5, 3)
	186 org/apache/commons/math3/FieldElement (5, 3)
	188 aload (5, 3)
	189 #8 (5, 3)
	190 iload (5, 3)
	191 #11 (5, 3)
	192 iconst_1 (5, 3)
	193 iadd (5, 3)
	194 aaload (5, 3)
	195 aload_1 (5, 3)
	196 iload (5, 3)
	197 #14 (5, 3)
	198 iconst_1 (5, 3)
	199 iadd (5, 3)
	200 aaload (5, 3)
	201 invokeinterface (5, 3)
	202 org/apache/commons/math3/FieldElement.multiply:(Lorg/apache/commons/math3/linear/BlockFieldMatrix;)Lorg/apache/commons/math3/linear/BlockFieldMatrix; (5, 3)
	204 0 (5, 3)
	206 invokeinterface (5, 3)
	207 org/apache/commons/math3/FieldElement.org/apache/commons/math3/FieldElement (5, 3)
	209 0 (5, 3)
	211 checkcast (5, 3)
	212 org/apache/commons/math3/FieldElement (5, 3)
	214 aload (5, 3)
	215 #8 (5, 3)
	216 iload (5, 3)
	217 #11 (5, 3)
	218 iconst_2 (5, 3)
	219 iadd (5, 3)
	220 aaload (5, 3)
	221 aload_1 (5, 3)
	222 iload (5, 3)
	223 #14 (5, 3)
	224 iconst_2 (5, 3)
	225 iadd (5, 3)
	226 aaload (5, 3)
	227 invokeinterface (5, 3)
	228 org/apache/commons/math3/FieldElement.multiply:(Lorg/apache/commons/math3/linear/BlockFieldMatrix;)Lorg/apache/commons/math3/linear/BlockFieldMatrix; (5, 3)
	230 0 (5, 3)
	232 invokeinterface (5, 3)
	233 org/apache/commons/math3/FieldElement.org/apache/commons/math3/FieldElement (5, 3)
	235 0 (5, 3)
	237 checkcast (5, 3)
	238 org/apache/commons/math3/FieldElement (5, 3)
	240 aload (5, 3)
	241 #8 (5, 3)
	242 iload (5, 3)
	243 #11 (5, 3)
	244 iconst_3 (5, 3)
	245 iadd (5, 3)
	246 aaload (5, 3)
	247 aload_1 (5, 3)
	248 iload (5, 3)
	249 #14 (5, 3)
	250 iconst_3 (5, 3)
	251 iadd (5, 3)
	252 aaload (5, 3)
	253 invokeinterface (5, 3)
	254 org/apache/commons/math3/FieldElement.multiply:(Lorg/apache/commons/math3/linear/BlockFieldMatrix;)Lorg/apache/commons/math3/linear/BlockFieldMatrix; (5, 3)
	256 0 (5, 3)
	258 invokeinterface (5, 3)
	259 org/apache/commons/math3/FieldElement.org/apache/commons/math3/FieldElement (5, 3)
	261 0 (5, 3)
	263 checkcast (5, 3)
	264 org/apache/commons/math3/FieldElement (5, 3)
	266 astore (5, 3)
	267 #13 (5, 3)
	268 iinc (5, 3)
	269 #11 (5, 3)
	270 -124 (5, 3)
	271 iinc (5, 3)
	272 #14 (5, 3)
	273 -89 (5, 3)
	274 goto (5, 3)
	275 -119 (5, 3)
	277 iload (5, 3)
	278 #14 (5, 3)
	279 iload (5, 3)
	280 #10 (5, 3)
	281 if_icmpge (5, 3)
	282 38 (5, 3)
	284 aload (5, 3)
	285 #13 (5, 3)
	286 aload (5, 3)
	287 #8 (5, 3)
	288 iload (5, 3)
	289 #11 (5, 3)
	290 iinc (5, 3)
	291 #11 (5, 3)
	292 50 (5, 3)
	293 aaload (5, 3)
	294 aload_1 (5, 3)
	295 iload (5, 3)
	296 #14 (5, 3)
	297 iinc (5, 3)
	298 #14 (5, 3)
	299 50 (5, 3)
	300 aaload (5, 3)
	301 invokeinterface (5, 3)
	302 org/apache/commons/math3/FieldElement.multiply:(Lorg/apache/commons/math3/linear/BlockFieldMatrix;)Lorg/apache/commons/math3/linear/BlockFieldMatrix; (5, 3)
	304 0 (5, 3)
	306 invokeinterface (5, 3)
	307 org/apache/commons/math3/FieldElement.org/apache/commons/math3/FieldElement (5, 3)
	309 0 (5, 3)
	311 checkcast (5, 3)
	312 org/apache/commons/math3/FieldElement (5, 3)
	314 astore (5, 3)
	315 #13 (5, 3)
	316 goto (5, 3)
	317 -39 (5, 3)
	319 aload_2 (4, 4)
	320 iload (4, 4)
	321 #12 (4, 4)
	322 aload_2 (4, 4)
	323 iload (4, 4)
	324 #12 (4, 4)
	325 aaload (4, 4)
	326 aload (4, 4)
	327 #13 (4, 4)
	328 invokeinterface (4, 4)
	329 org/apache/commons/math3/FieldElement.org/apache/commons/math3/FieldElement (4, 4)
	331 0 (4, 4)
	333 checkcast (4, 4)
	334 org/apache/commons/math3/FieldElement (4, 4)
	336 aastore (4, 4)
	337 iinc (4, 4)
	338 #12 (4, 4)
	339 -89 (4, 4)
	340 goto (4, 4)
	341 -199 (4, 4)
	343 iinc (4, 4)
	344 #7 (4, 4)
	345 -89 (4, 4)
	346 goto (4, 4)
	347 -259 (4, 4)
	349 iinc (4, 4)
	350 #4 (4, 4)
	351 -89 (4, 4)
	352 goto (4, 4)
	353 -298 (4, 4)
	355 aload_2 (3, 4)
	356 areturn (2, 4)

Method: preMultiply
	0 aload_1 (1, 1)
	1 arraylength (1, 1)
	2 aload_0 (1, 1)
	3 getfield (1, 1)
	4 org/apache/commons/math3/linear/BlockFieldMatrix.rows:I (1, 1)
	6 if_icmpeq (1, 1)
	7 17 (1, 1)
	9 new (1, 1)
	10 org/apache/commons/math3/exception/DimensionMismatchException (1, 1)
	12 dup (1, 1)
	13 aload_1 (1, 1)
	14 arraylength (1, 1)
	15 aload_0 (1, 1)
	16 getfield (1, 1)
	17 org/apache/commons/math3/linear/BlockFieldMatrix.rows:I (1, 1)
	19 invokespecial (1, 1)
	20 org/apache/commons/math3/exception/DimensionMismatchException.<init>:(II)V (1, 1)
	22 athrow (1, 1)
	23 aload_0 (0, 0)
	24 invokevirtual (0, 0)
	25 org/apache/commons/math3/linear/BlockFieldMatrix.getField:()Lorg/apache/commons/math3/Field; (0, 0)
	27 aload_0 (0, 0)
	28 getfield (0, 0)
	29 org/apache/commons/math3/linear/BlockFieldMatrix.columns:I (0, 0)
	31 invokestatic (0, 0)
	32 org/apache/commons/math3/util/MathArrays.buildArray:(Lorg/apache/commons/math3/Field;I)[Ljava/lang/Object; (0, 0)
	34 checkcast (0, 0)
	35 [Lorg/apache/commons/math3/FieldElement; (0, 0)
	37 astore_2 (0, 0)
	38 aload_0 (0, 0)
	39 invokevirtual (0, 0)
	40 org/apache/commons/math3/linear/BlockFieldMatrix.getField:()Lorg/apache/commons/math3/Field; (0, 0)
	42 invokeinterface (0, 0)
	43 org/apache/commons/math3/Field.getRowDimension:()I (0, 0)
	45 0 (0, 0)
	47 checkcast (0, 0)
	48 org/apache/commons/math3/FieldElement (0, 0)
	50 astore_3 (0, 0)
	51 iconst_0 (2, 4)
	52 istore (2, 4)
	53 #4 (2, 4)
	54 iload (2, 4)
	55 #4 (2, 4)
	56 aload_0 (2, 4)
	57 getfield (2, 4)
	58 org/apache/commons/math3/linear/BlockFieldMatrix.blockColumns:I (2, 4)
	60 if_icmpge (2, 4)
	61 339 (2, 4)
	63 aload_0 (2, 4)
	64 iload (2, 4)
	65 #4 (2, 4)
	66 invokespecial (2, 4)
	67 org/apache/commons/math3/linear/BlockFieldMatrix.blockWidth:(I)I (2, 4)
	69 istore (2, 4)
	70 #5 (2, 4)
	71 iload (2, 4)
	72 #5 (2, 4)
	73 iload (2, 4)
	74 #5 (2, 4)
	75 iadd (2, 4)
	76 istore (2, 4)
	77 #6 (2, 4)
	78 iload (2, 4)
	79 #6 (2, 4)
	80 iload (2, 4)
	81 #5 (2, 4)
	82 iadd (2, 4)
	83 istore (2, 4)
	84 #7 (2, 4)
	85 iload (2, 4)
	86 #7 (2, 4)
	87 iload (2, 4)
	88 #5 (2, 4)
	89 iadd (2, 4)
	90 istore (2, 4)
	91 #8 (2, 4)
	92 iload (2, 4)
	93 #4 (2, 4)
	94 bipush (2, 4)
	95 36 (2, 4)
	96 imul (2, 4)
	97 istore (2, 4)
	98 #9 (2, 4)
	99 iload (2, 4)
	100 #9 (2, 4)
	101 bipush (2, 4)
	102 36 (2, 4)
	103 iadd (2, 4)
	104 aload_0 (2, 4)
	105 getfield (2, 4)
	106 org/apache/commons/math3/linear/BlockFieldMatrix.columns:I (2, 4)
	108 invokestatic (2, 4)
	109 org/apache/commons/math3/util/FastMath.min:(II)I (2, 4)
	111 istore (2, 4)
	112 #10 (2, 4)
	113 iconst_0 (3, 4)
	114 istore (3, 4)
	115 #11 (3, 4)
	116 iload (3, 4)
	117 #11 (3, 4)
	118 aload_0 (3, 4)
	119 getfield (3, 4)
	120 org/apache/commons/math3/linear/BlockFieldMatrix.blockRows:I (3, 4)
	122 if_icmpge (3, 4)
	123 271 (3, 4)
	125 aload_0 (3, 4)
	126 getfield (3, 4)
	127 org/apache/commons/math3/linear/BlockFieldMatrix.blocks:[[Lorg/apache/commons/math3/FieldElement; (3, 4)
	129 iload (3, 4)
	130 #11 (3, 4)
	131 aload_0 (3, 4)
	132 getfield (3, 4)
	133 org/apache/commons/math3/linear/BlockFieldMatrix.blockColumns:I (3, 4)
	135 imul (3, 4)
	136 iload (3, 4)
	137 #4 (3, 4)
	138 iadd (3, 4)
	139 aaload (3, 4)
	140 astore (3, 4)
	141 #12 (3, 4)
	142 iload (3, 4)
	143 #11 (3, 4)
	144 bipush (3, 4)
	145 36 (3, 4)
	146 imul (3, 4)
	147 istore (3, 4)
	148 #13 (3, 4)
	149 iload (3, 4)
	150 #13 (3, 4)
	151 bipush (3, 4)
	152 36 (3, 4)
	153 iadd (3, 4)
	154 aload_0 (3, 4)
	155 getfield (3, 4)
	156 org/apache/commons/math3/linear/BlockFieldMatrix.rows:I (3, 4)
	158 invokestatic (3, 4)
	159 org/apache/commons/math3/util/FastMath.min:(II)I (3, 4)
	161 istore (3, 4)
	162 #14 (3, 4)
	163 iload (4, 4)
	164 #9 (4, 4)
	165 istore (4, 4)
	166 #15 (4, 4)
	167 iload (4, 4)
	168 #15 (4, 4)
	169 iload (4, 4)
	170 #10 (4, 4)
	171 if_icmpge (4, 4)
	172 216 (4, 4)
	174 iload (4, 4)
	175 #15 (4, 4)
	176 iload (4, 4)
	177 #9 (4, 4)
	178 isub (4, 4)
	179 istore (4, 4)
	180 #16 (4, 4)
	181 aload_3 (4, 4)
	182 astore (4, 4)
	183 #17 (4, 4)
	184 iload (4, 4)
	185 #13 (4, 4)
	186 istore (4, 4)
	187 #18 (4, 4)
	188 iload (5, 3)
	189 #18 (5, 3)
	190 iload (5, 3)
	191 #14 (5, 3)
	192 iconst_3 (5, 3)
	193 isub (5, 3)
	194 if_icmpge (5, 3)
	195 123 (5, 3)
	197 aload (5, 3)
	198 #17 (5, 3)
	199 aload (5, 3)
	200 #12 (5, 3)
	201 iload (5, 3)
	202 #16 (5, 3)
	203 aaload (5, 3)
	204 aload_1 (5, 3)
	205 iload (5, 3)
	206 #18 (5, 3)
	207 aaload (5, 3)
	208 invokeinterface (5, 3)
	209 org/apache/commons/math3/FieldElement.multiply:(Lorg/apache/commons/math3/linear/BlockFieldMatrix;)Lorg/apache/commons/math3/linear/BlockFieldMatrix; (5, 3)
	211 0 (5, 3)
	213 invokeinterface (5, 3)
	214 org/apache/commons/math3/FieldElement.org/apache/commons/math3/FieldElement (5, 3)
	216 0 (5, 3)
	218 checkcast (5, 3)
	219 org/apache/commons/math3/FieldElement (5, 3)
	221 aload (5, 3)
	222 #12 (5, 3)
	223 iload (5, 3)
	224 #16 (5, 3)
	225 iload (5, 3)
	226 #5 (5, 3)
	227 iadd (5, 3)
	228 aaload (5, 3)
	229 aload_1 (5, 3)
	230 iload (5, 3)
	231 #18 (5, 3)
	232 iconst_1 (5, 3)
	233 iadd (5, 3)
	234 aaload (5, 3)
	235 invokeinterface (5, 3)
	236 org/apache/commons/math3/FieldElement.multiply:(Lorg/apache/commons/math3/linear/BlockFieldMatrix;)Lorg/apache/commons/math3/linear/BlockFieldMatrix; (5, 3)
	238 0 (5, 3)
	240 invokeinterface (5, 3)
	241 org/apache/commons/math3/FieldElement.org/apache/commons/math3/FieldElement (5, 3)
	243 0 (5, 3)
	245 checkcast (5, 3)
	246 org/apache/commons/math3/FieldElement (5, 3)
	248 aload (5, 3)
	249 #12 (5, 3)
	250 iload (5, 3)
	251 #16 (5, 3)
	252 iload (5, 3)
	253 #6 (5, 3)
	254 iadd (5, 3)
	255 aaload (5, 3)
	256 aload_1 (5, 3)
	257 iload (5, 3)
	258 #18 (5, 3)
	259 iconst_2 (5, 3)
	260 iadd (5, 3)
	261 aaload (5, 3)
	262 invokeinterface (5, 3)
	263 org/apache/commons/math3/FieldElement.multiply:(Lorg/apache/commons/math3/linear/BlockFieldMatrix;)Lorg/apache/commons/math3/linear/BlockFieldMatrix; (5, 3)
	265 0 (5, 3)
	267 invokeinterface (5, 3)
	268 org/apache/commons/math3/FieldElement.org/apache/commons/math3/FieldElement (5, 3)
	270 0 (5, 3)
	272 checkcast (5, 3)
	273 org/apache/commons/math3/FieldElement (5, 3)
	275 aload (5, 3)
	276 #12 (5, 3)
	277 iload (5, 3)
	278 #16 (5, 3)
	279 iload (5, 3)
	280 #7 (5, 3)
	281 iadd (5, 3)
	282 aaload (5, 3)
	283 aload_1 (5, 3)
	284 iload (5, 3)
	285 #18 (5, 3)
	286 iconst_3 (5, 3)
	287 iadd (5, 3)
	288 aaload (5, 3)
	289 invokeinterface (5, 3)
	290 org/apache/commons/math3/FieldElement.multiply:(Lorg/apache/commons/math3/linear/BlockFieldMatrix;)Lorg/apache/commons/math3/linear/BlockFieldMatrix; (5, 3)
	292 0 (5, 3)
	294 invokeinterface (5, 3)
	295 org/apache/commons/math3/FieldElement.org/apache/commons/math3/FieldElement (5, 3)
	297 0 (5, 3)
	299 checkcast (5, 3)
	300 org/apache/commons/math3/FieldElement (5, 3)
	302 astore (5, 3)
	303 #17 (5, 3)
	304 iload (5, 3)
	305 #16 (5, 3)
	306 iload (5, 3)
	307 #8 (5, 3)
	308 iadd (5, 3)
	309 istore (5, 3)
	310 #16 (5, 3)
	311 iinc (5, 3)
	312 #18 (5, 3)
	313 -89 (5, 3)
	314 goto (5, 3)
	315 -126 (5, 3)
	317 iload (5, 3)
	318 #18 (5, 3)
	319 iload (5, 3)
	320 #14 (5, 3)
	321 if_icmpge (5, 3)
	322 42 (5, 3)
	324 aload (5, 3)
	325 #17 (5, 3)
	326 aload (5, 3)
	327 #12 (5, 3)
	328 iload (5, 3)
	329 #16 (5, 3)
	330 aaload (5, 3)
	331 aload_1 (5, 3)
	332 iload (5, 3)
	333 #18 (5, 3)
	334 iinc (5, 3)
	335 #18 (5, 3)
	336 50 (5, 3)
	337 aaload (5, 3)
	338 invokeinterface (5, 3)
	339 org/apache/commons/math3/FieldElement.multiply:(Lorg/apache/commons/math3/linear/BlockFieldMatrix;)Lorg/apache/commons/math3/linear/BlockFieldMatrix; (5, 3)
	341 0 (5, 3)
	343 invokeinterface (5, 3)
	344 org/apache/commons/math3/FieldElement.org/apache/commons/math3/FieldElement (5, 3)
	346 0 (5, 3)
	348 checkcast (5, 3)
	349 org/apache/commons/math3/FieldElement (5, 3)
	351 astore (5, 3)
	352 #17 (5, 3)
	353 iload (5, 3)
	354 #16 (5, 3)
	355 iload (5, 3)
	356 #5 (5, 3)
	357 iadd (5, 3)
	358 istore (5, 3)
	359 #16 (5, 3)
	360 goto (5, 3)
	361 -43 (5, 3)
	363 aload_2 (4, 4)
	364 iload (4, 4)
	365 #15 (4, 4)
	366 aload_2 (4, 4)
	367 iload (4, 4)
	368 #15 (4, 4)
	369 aaload (4, 4)
	370 aload (4, 4)
	371 #17 (4, 4)
	372 invokeinterface (4, 4)
	373 org/apache/commons/math3/FieldElement.org/apache/commons/math3/FieldElement (4, 4)
	375 0 (4, 4)
	377 checkcast (4, 4)
	378 org/apache/commons/math3/FieldElement (4, 4)
	380 aastore (4, 4)
	381 iinc (4, 4)
	382 #15 (4, 4)
	383 -89 (4, 4)
	384 goto (4, 4)
	385 -217 (4, 4)
	387 iinc (4, 4)
	388 #11 (4, 4)
	389 -89 (4, 4)
	390 goto (4, 4)
	391 -274 (4, 4)
	393 iinc (4, 4)
	394 #4 (4, 4)
	395 -89 (4, 4)
	396 goto (4, 4)
	397 -342 (4, 4)
	399 aload_2 (3, 4)
	400 areturn (2, 4)

Method: walkInRowOrder
	0 aload_0 (0, 0)
	1 iload_2 (0, 0)
	2 iload_3 (0, 0)
	3 iload (0, 0)
	4 #4 (0, 0)
	5 iload (0, 0)
	6 #5 (0, 0)
	7 invokevirtual (0, 0)
	8 org/apache/commons/math3/linear/BlockFieldMatrix.checkSubMatrixIndex:(IIII)V (0, 0)
	10 aload_1 (0, 0)
	11 aload_0 (0, 0)
	12 getfield (0, 0)
	13 org/apache/commons/math3/linear/BlockFieldMatrix.rows:I (0, 0)
	15 aload_0 (0, 0)
	16 getfield (0, 0)
	17 org/apache/commons/math3/linear/BlockFieldMatrix.columns:I (0, 0)
	19 iload_2 (0, 0)
	20 iload_3 (0, 0)
	21 iload (0, 0)
	22 #4 (0, 0)
	23 iload (0, 0)
	24 #5 (0, 0)
	25 invokeinterface (0, 0)
	26 org/apache/commons/math3/linear/FieldMatrixPreservingVisitor.visit:(IILorg/apache/commons/math3/FieldElement;)Lorg/apache/commons/math3/FieldElement; (0, 0)
	28 0 (0, 0)
	30 iload_2 (1, 4)
	31 bipush (1, 4)
	32 36 (1, 4)
	33 idiv (1, 4)
	34 istore (1, 4)
	35 #6 (1, 4)
	36 iload (1, 4)
	37 #6 (1, 4)
	38 iconst_1 (1, 4)
	39 iload_3 (1, 4)
	40 bipush (1, 4)
	41 36 (1, 4)
	42 idiv (1, 4)
	43 iadd (1, 4)
	44 if_icmpge (1, 4)
	45 189 (1, 4)
	47 iload (1, 4)
	48 #6 (1, 4)
	49 bipush (1, 4)
	50 36 (1, 4)
	51 imul (1, 4)
	52 istore (1, 4)
	53 #7 (1, 4)
	54 iload_2 (1, 4)
	55 iload (1, 4)
	56 #7 (1, 4)
	57 invokestatic (1, 4)
	58 org/apache/commons/math3/util/FastMath.max:(II)I (1, 4)
	60 istore (1, 4)
	61 #8 (1, 4)
	62 iload (1, 4)
	63 #6 (1, 4)
	64 iconst_1 (1, 4)
	65 iadd (1, 4)
	66 bipush (1, 4)
	67 36 (1, 4)
	68 imul (1, 4)
	69 iconst_1 (1, 4)
	70 iload_3 (1, 4)
	71 iadd (1, 4)
	72 invokestatic (1, 4)
	73 org/apache/commons/math3/util/FastMath.min:(II)I (1, 4)
	75 istore (1, 4)
	76 #9 (1, 4)
	77 iload (2, 4)
	78 #8 (2, 4)
	79 istore (2, 4)
	80 #10 (2, 4)
	81 iload (2, 4)
	82 #10 (2, 4)
	83 iload (2, 4)
	84 #9 (2, 4)
	85 if_icmpge (2, 4)
	86 142 (2, 4)
	88 iload (3, 4)
	89 #4 (3, 4)
	90 bipush (3, 4)
	91 36 (3, 4)
	92 idiv (3, 4)
	93 istore (3, 4)
	94 #11 (3, 4)
	95 iload (3, 4)
	96 #11 (3, 4)
	97 iconst_1 (3, 4)
	98 iload (3, 4)
	99 #5 (3, 4)
	100 bipush (3, 4)
	101 36 (3, 4)
	102 idiv (3, 4)
	103 iadd (3, 4)
	104 if_icmpge (3, 4)
	105 117 (3, 4)
	107 aload_0 (3, 4)
	108 iload (3, 4)
	109 #11 (3, 4)
	110 invokespecial (3, 4)
	111 org/apache/commons/math3/linear/BlockFieldMatrix.blockWidth:(I)I (3, 4)
	113 istore (3, 4)
	114 #12 (3, 4)
	115 iload (3, 4)
	116 #11 (3, 4)
	117 bipush (3, 4)
	118 36 (3, 4)
	119 imul (3, 4)
	120 istore (3, 4)
	121 #13 (3, 4)
	122 iload (3, 4)
	123 #4 (3, 4)
	124 iload (3, 4)
	125 #13 (3, 4)
	126 invokestatic (3, 4)
	127 org/apache/commons/math3/util/FastMath.max:(II)I (3, 4)
	129 istore (3, 4)
	130 #14 (3, 4)
	131 iload (3, 4)
	132 #11 (3, 4)
	133 iconst_1 (3, 4)
	134 iadd (3, 4)
	135 bipush (3, 4)
	136 36 (3, 4)
	137 imul (3, 4)
	138 iconst_1 (3, 4)
	139 iload (3, 4)
	140 #5 (3, 4)
	141 iadd (3, 4)
	142 invokestatic (3, 4)
	143 org/apache/commons/math3/util/FastMath.min:(II)I (3, 4)
	145 istore (3, 4)
	146 #15 (3, 4)
	147 aload_0 (3, 4)
	148 getfield (3, 4)
	149 org/apache/commons/math3/linear/BlockFieldMatrix.blocks:[[Lorg/apache/commons/math3/FieldElement; (3, 4)
	151 iload (3, 4)
	152 #6 (3, 4)
	153 aload_0 (3, 4)
	154 getfield (3, 4)
	155 org/apache/commons/math3/linear/BlockFieldMatrix.blockColumns:I (3, 4)
	157 imul (3, 4)
	158 iload (3, 4)
	159 #11 (3, 4)
	160 iadd (3, 4)
	161 aaload (3, 4)
	162 astore (3, 4)
	163 #16 (3, 4)
	164 iload (3, 4)
	165 #10 (3, 4)
	166 iload (3, 4)
	167 #7 (3, 4)
	168 isub (3, 4)
	169 iload (3, 4)
	170 #12 (3, 4)
	171 imul (3, 4)
	172 iload (3, 4)
	173 #14 (3, 4)
	174 iadd (3, 4)
	175 iload (3, 4)
	176 #13 (3, 4)
	177 isub (3, 4)
	178 istore (3, 4)
	179 #17 (3, 4)
	180 iload (4, 4)
	181 #14 (4, 4)
	182 istore (4, 4)
	183 #18 (4, 4)
	184 iload (4, 4)
	185 #18 (4, 4)
	186 iload (4, 4)
	187 #15 (4, 4)
	188 if_icmpge (4, 4)
	189 27 (4, 4)
	191 aload_1 (4, 4)
	192 iload (4, 4)
	193 #10 (4, 4)
	194 iload (4, 4)
	195 #18 (4, 4)
	196 aload (4, 4)
	197 #16 (4, 4)
	198 iload (4, 4)
	199 #17 (4, 4)
	200 aaload (4, 4)
	201 invokeinterface (4, 4)
	202 org/apache/commons/math3/linear/FieldMatrixPreservingVisitor.org/apache/commons/math3/linear/AbstractFieldMatrix (4, 4)
	204 0 (4, 4)
	206 iinc (4, 4)
	207 #17 (4, 4)
	208 -124 (4, 4)
	209 iinc (4, 4)
	210 #18 (4, 4)
	211 -89 (4, 4)
	212 goto (4, 4)
	213 -28 (4, 4)
	215 iinc (4, 4)
	216 #11 (4, 4)
	217 -89 (4, 4)
	218 goto (4, 4)
	219 -123 (4, 4)
	221 iinc (4, 4)
	222 #10 (4, 4)
	223 -89 (4, 4)
	224 goto (4, 4)
	225 -143 (4, 4)
	227 iinc (4, 4)
	228 #6 (4, 4)
	229 -89 (4, 4)
	230 goto (4, 4)
	231 -194 (4, 4)
	233 aload_1 (3, 4)
	234 invokeinterface (3, 4)
	235 org/apache/commons/math3/linear/FieldMatrixPreservingVisitor.org/apache/commons/math3/linear/FieldMatrixPreservingVisitor (3, 4)
	237 0 (3, 4)
	239 areturn (3, 4)

Method: walkInOptimizedOrder
	0 aload_0 (0, 0)
	1 iload_2 (0, 0)
	2 iload_3 (0, 0)
	3 iload (0, 0)
	4 #4 (0, 0)
	5 iload (0, 0)
	6 #5 (0, 0)
	7 invokevirtual (0, 0)
	8 org/apache/commons/math3/linear/BlockFieldMatrix.checkSubMatrixIndex:(IIII)V (0, 0)
	10 aload_1 (0, 0)
	11 aload_0 (0, 0)
	12 getfield (0, 0)
	13 org/apache/commons/math3/linear/BlockFieldMatrix.rows:I (0, 0)
	15 aload_0 (0, 0)
	16 getfield (0, 0)
	17 org/apache/commons/math3/linear/BlockFieldMatrix.columns:I (0, 0)
	19 iload_2 (0, 0)
	20 iload_3 (0, 0)
	21 iload (0, 0)
	22 #4 (0, 0)
	23 iload (0, 0)
	24 #5 (0, 0)
	25 invokeinterface (0, 0)
	26 org/apache/commons/math3/linear/FieldMatrixPreservingVisitor.visit:(IILorg/apache/commons/math3/FieldElement;)Lorg/apache/commons/math3/FieldElement; (0, 0)
	28 0 (0, 0)
	30 iload_2 (1, 4)
	31 bipush (1, 4)
	32 36 (1, 4)
	33 idiv (1, 4)
	34 istore (1, 4)
	35 #6 (1, 4)
	36 iload (1, 4)
	37 #6 (1, 4)
	38 iconst_1 (1, 4)
	39 iload_3 (1, 4)
	40 bipush (1, 4)
	41 36 (1, 4)
	42 idiv (1, 4)
	43 iadd (1, 4)
	44 if_icmpge (1, 4)
	45 189 (1, 4)
	47 iload (1, 4)
	48 #6 (1, 4)
	49 bipush (1, 4)
	50 36 (1, 4)
	51 imul (1, 4)
	52 istore (1, 4)
	53 #7 (1, 4)
	54 iload_2 (1, 4)
	55 iload (1, 4)
	56 #7 (1, 4)
	57 invokestatic (1, 4)
	58 org/apache/commons/math3/util/FastMath.max:(II)I (1, 4)
	60 istore (1, 4)
	61 #8 (1, 4)
	62 iload (1, 4)
	63 #6 (1, 4)
	64 iconst_1 (1, 4)
	65 iadd (1, 4)
	66 bipush (1, 4)
	67 36 (1, 4)
	68 imul (1, 4)
	69 iconst_1 (1, 4)
	70 iload_3 (1, 4)
	71 iadd (1, 4)
	72 invokestatic (1, 4)
	73 org/apache/commons/math3/util/FastMath.min:(II)I (1, 4)
	75 istore (1, 4)
	76 #9 (1, 4)
	77 iload (2, 4)
	78 #4 (2, 4)
	79 bipush (2, 4)
	80 36 (2, 4)
	81 idiv (2, 4)
	82 istore (2, 4)
	83 #10 (2, 4)
	84 iload (2, 4)
	85 #10 (2, 4)
	86 iconst_1 (2, 4)
	87 iload (2, 4)
	88 #5 (2, 4)
	89 bipush (2, 4)
	90 36 (2, 4)
	91 idiv (2, 4)
	92 iadd (2, 4)
	93 if_icmpge (2, 4)
	94 134 (2, 4)
	96 aload_0 (2, 4)
	97 iload (2, 4)
	98 #10 (2, 4)
	99 invokespecial (2, 4)
	100 org/apache/commons/math3/linear/BlockFieldMatrix.blockWidth:(I)I (2, 4)
	102 istore (2, 4)
	103 #11 (2, 4)
	104 iload (2, 4)
	105 #10 (2, 4)
	106 bipush (2, 4)
	107 36 (2, 4)
	108 imul (2, 4)
	109 istore (2, 4)
	110 #12 (2, 4)
	111 iload (2, 4)
	112 #4 (2, 4)
	113 iload (2, 4)
	114 #12 (2, 4)
	115 invokestatic (2, 4)
	116 org/apache/commons/math3/util/FastMath.max:(II)I (2, 4)
	118 istore (2, 4)
	119 #13 (2, 4)
	120 iload (2, 4)
	121 #10 (2, 4)
	122 iconst_1 (2, 4)
	123 iadd (2, 4)
	124 bipush (2, 4)
	125 36 (2, 4)
	126 imul (2, 4)
	127 iconst_1 (2, 4)
	128 iload (2, 4)
	129 #5 (2, 4)
	130 iadd (2, 4)
	131 invokestatic (2, 4)
	132 org/apache/commons/math3/util/FastMath.min:(II)I (2, 4)
	134 istore (2, 4)
	135 #14 (2, 4)
	136 aload_0 (2, 4)
	137 getfield (2, 4)
	138 org/apache/commons/math3/linear/BlockFieldMatrix.blocks:[[Lorg/apache/commons/math3/FieldElement; (2, 4)
	140 iload (2, 4)
	141 #6 (2, 4)
	142 aload_0 (2, 4)
	143 getfield (2, 4)
	144 org/apache/commons/math3/linear/BlockFieldMatrix.blockColumns:I (2, 4)
	146 imul (2, 4)
	147 iload (2, 4)
	148 #10 (2, 4)
	149 iadd (2, 4)
	150 aaload (2, 4)
	151 astore (2, 4)
	152 #15 (2, 4)
	153 iload (3, 4)
	154 #8 (3, 4)
	155 istore (3, 4)
	156 #16 (3, 4)
	157 iload (3, 4)
	158 #16 (3, 4)
	159 iload (3, 4)
	160 #9 (3, 4)
	161 if_icmpge (3, 4)
	162 60 (3, 4)
	164 iload (3, 4)
	165 #16 (3, 4)
	166 iload (3, 4)
	167 #7 (3, 4)
	168 isub (3, 4)
	169 iload (3, 4)
	170 #11 (3, 4)
	171 imul (3, 4)
	172 iload (3, 4)
	173 #13 (3, 4)
	174 iadd (3, 4)
	175 iload (3, 4)
	176 #12 (3, 4)
	177 isub (3, 4)
	178 istore (3, 4)
	179 #17 (3, 4)
	180 iload (4, 4)
	181 #13 (4, 4)
	182 istore (4, 4)
	183 #18 (4, 4)
	184 iload (4, 4)
	185 #18 (4, 4)
	186 iload (4, 4)
	187 #14 (4, 4)
	188 if_icmpge (4, 4)
	189 27 (4, 4)
	191 aload_1 (4, 4)
	192 iload (4, 4)
	193 #16 (4, 4)
	194 iload (4, 4)
	195 #18 (4, 4)
	196 aload (4, 4)
	197 #15 (4, 4)
	198 iload (4, 4)
	199 #17 (4, 4)
	200 aaload (4, 4)
	201 invokeinterface (4, 4)
	202 org/apache/commons/math3/linear/FieldMatrixPreservingVisitor.org/apache/commons/math3/linear/AbstractFieldMatrix (4, 4)
	204 0 (4, 4)
	206 iinc (4, 4)
	207 #17 (4, 4)
	208 -124 (4, 4)
	209 iinc (4, 4)
	210 #18 (4, 4)
	211 -89 (4, 4)
	212 goto (4, 4)
	213 -28 (4, 4)
	215 iinc (4, 4)
	216 #16 (4, 4)
	217 -89 (4, 4)
	218 goto (4, 4)
	219 -61 (4, 4)
	221 iinc (4, 4)
	222 #10 (4, 4)
	223 -89 (4, 4)
	224 goto (4, 4)
	225 -140 (4, 4)
	227 iinc (4, 4)
	228 #6 (4, 4)
	229 -89 (4, 4)
	230 goto (4, 4)
	231 -194 (4, 4)
	233 aload_1 (3, 4)
	234 invokeinterface (3, 4)
	235 org/apache/commons/math3/linear/FieldMatrixPreservingVisitor.org/apache/commons/math3/linear/FieldMatrixPreservingVisitor (3, 4)
	237 0 (3, 4)
	239 areturn (3, 4)

Method: blockHeight
	0 iload_1 (0, 0)
	1 aload_0 (0, 0)
	2 getfield (0, 0)
	3 org/apache/commons/math3/linear/BlockFieldMatrix.blockRows:I (0, 0)
	5 iconst_1 (0, 0)
	6 isub (0, 0)
	7 if_icmpne (0, 0)
	8 15 (0, 0)
	10 aload_0 (0, 0)
	11 getfield (0, 0)
	12 org/apache/commons/math3/linear/BlockFieldMatrix.rows:I (0, 0)
	14 iload_1 (0, 0)
	15 bipush (0, 0)
	16 36 (0, 0)
	17 imul (0, 0)
	18 isub (0, 0)
	19 goto (0, 0)
	20 5 (0, 0)
	22 bipush (0, 0)
	23 36 (0, 0)
	24 ireturn (0, 0)

Method: blockWidth
	0 iload_1 (0, 0)
	1 aload_0 (0, 0)
	2 getfield (0, 0)
	3 org/apache/commons/math3/linear/BlockFieldMatrix.blockColumns:I (0, 0)
	5 iconst_1 (0, 0)
	6 isub (0, 0)
	7 if_icmpne (0, 0)
	8 15 (0, 0)
	10 aload_0 (0, 0)
	11 getfield (0, 0)
	12 org/apache/commons/math3/linear/BlockFieldMatrix.columns:I (0, 0)
	14 iload_1 (0, 0)
	15 bipush (0, 0)
	16 36 (0, 0)
	17 imul (0, 0)
	18 isub (0, 0)
	19 goto (0, 0)
	20 5 (0, 0)
	22 bipush (0, 0)
	23 36 (0, 0)
	24 ireturn (0, 0)

