Method: <init>
	0 aload_0 (0, 0)
	1 iload_1 (0, 0)
	2 iload_2 (0, 0)
	3 invokespecial (0, 0)
	4 org/apache/commons/math3/linear/AbstractRealMatrix.<init>:(II)V (0, 0)
	6 aload_0 (0, 0)
	7 iload_1 (0, 0)
	8 putfield (0, 0)
	9 org/apache/commons/math3/linear/BlockRealMatrix.rows:I (0, 0)
	11 aload_0 (0, 0)
	12 iload_2 (0, 0)
	13 putfield (0, 0)
	14 org/apache/commons/math3/linear/BlockRealMatrix.columns:I (0, 0)
	16 aload_0 (0, 0)
	17 iload_1 (0, 0)
	18 bipush (0, 0)
	19 52 (0, 0)
	20 iadd (0, 0)
	21 iconst_1 (0, 0)
	22 isub (0, 0)
	23 bipush (0, 0)
	24 52 (0, 0)
	25 idiv (0, 0)
	26 putfield (0, 0)
	27 org/apache/commons/math3/linear/BlockRealMatrix.blockRows:I (0, 0)
	29 aload_0 (0, 0)
	30 iload_2 (0, 0)
	31 bipush (0, 0)
	32 52 (0, 0)
	33 iadd (0, 0)
	34 iconst_1 (0, 0)
	35 isub (0, 0)
	36 bipush (0, 0)
	37 52 (0, 0)
	38 idiv (0, 0)
	39 putfield (0, 0)
	40 org/apache/commons/math3/linear/BlockRealMatrix.blockColumns:I (0, 0)
	42 iload (1, 1)
	43 #4 (1, 1)
	44 ifeq (1, 1)
	45 22 (1, 1)
	47 aload_0 (1, 1)
	48 aload_0 (1, 1)
	49 getfield (1, 1)
	50 org/apache/commons/math3/linear/BlockRealMatrix.blockRows:I (1, 1)
	52 aload_0 (1, 1)
	53 getfield (1, 1)
	54 org/apache/commons/math3/linear/BlockRealMatrix.blockColumns:I (1, 1)
	56 imul (1, 1)
	57 anewarray (1, 1)
	58 [D (1, 1)
	60 putfield (1, 1)
	61 org/apache/commons/math3/linear/BlockRealMatrix.blocks:[[D (1, 1)
	63 goto (1, 1)
	64 8 (1, 1)
	66 aload_0 (2, 2)
	67 aload_3 (2, 2)
	68 putfield (2, 2)
	69 org/apache/commons/math3/linear/BlockRealMatrix.blocks:[[D (2, 2)
	71 iconst_0 (0, 0)
	72 istore (0, 0)
	73 #5 (0, 0)
	74 iconst_0 (1, 4)
	75 istore (1, 4)
	76 #6 (1, 4)
	77 iload (1, 4)
	78 #6 (1, 4)
	79 aload_0 (1, 4)
	80 getfield (1, 4)
	81 org/apache/commons/math3/linear/BlockRealMatrix.blockRows:I (1, 4)
	83 if_icmpge (1, 4)
	84 99 (1, 4)
	86 aload_0 (1, 4)
	87 iload (1, 4)
	88 #6 (1, 4)
	89 invokespecial (1, 4)
	90 org/apache/commons/math3/linear/BlockRealMatrix.blockHeight:(I)I (1, 4)
	92 istore (1, 4)
	93 #7 (1, 4)
	94 iconst_0 (2, 4)
	95 istore (2, 4)
	96 #8 (2, 4)
	97 iload (2, 4)
	98 #8 (2, 4)
	99 aload_0 (2, 4)
	100 getfield (2, 4)
	101 org/apache/commons/math3/linear/BlockRealMatrix.blockColumns:I (2, 4)
	103 if_icmpge (2, 4)
	104 73 (2, 4)
	106 aload_3 (3, 1)
	107 iload (3, 1)
	108 #5 (3, 1)
	109 aaload (3, 1)
	110 arraylength (3, 1)
	111 iload (3, 1)
	112 #7 (3, 1)
	113 aload_0 (3, 1)
	114 iload (3, 1)
	115 #8 (3, 1)
	116 invokespecial (3, 1)
	117 org/apache/commons/math3/linear/BlockRealMatrix.blockWidth:(I)I (3, 1)
	119 imul (3, 1)
	120 if_icmpeq (3, 1)
	121 25 (3, 1)
	123 new (3, 1)
	124 org/apache/commons/math3/exception/DimensionMismatchException (3, 1)
	126 dup (3, 1)
	127 aload_3 (3, 1)
	128 iload (3, 1)
	129 #5 (3, 1)
	130 aaload (3, 1)
	131 arraylength (3, 1)
	132 iload (3, 1)
	133 #7 (3, 1)
	134 aload_0 (3, 1)
	135 iload (3, 1)
	136 #8 (3, 1)
	137 invokespecial (3, 1)
	138 org/apache/commons/math3/linear/BlockRealMatrix.blockWidth:(I)I (3, 1)
	140 imul (3, 1)
	141 invokespecial (3, 1)
	142 org/apache/commons/math3/exception/DimensionMismatchException.<init>:(II)V (3, 1)
	144 athrow (3, 1)
	145 iload (3, 1)
	146 #4 (3, 1)
	147 ifeq (3, 1)
	148 20 (3, 1)
	150 aload_0 (3, 1)
	151 getfield (3, 1)
	152 org/apache/commons/math3/linear/BlockRealMatrix.blocks:[[D (3, 1)
	154 iload (3, 1)
	155 #5 (3, 1)
	156 aload_3 (3, 1)
	157 iload (3, 1)
	158 #5 (3, 1)
	159 aaload (3, 1)
	160 invokevirtual (3, 1)
	161 [D.clone:()Ljava/lang/Object; (3, 1)
	163 checkcast (3, 1)
	164 [D (3, 1)
	166 aastore (3, 1)
	167 iinc (3, 1)
	168 #8 (3, 1)
	169 -124 (3, 1)
	170 iinc (3, 1)
	171 #5 (3, 1)
	172 -89 (3, 1)
	173 goto (3, 1)
	174 -76 (3, 1)
	176 iinc (3, 1)
	177 #6 (3, 1)
	178 -89 (3, 1)
	179 goto (3, 1)
	180 -102 (3, 1)
	182 return (1, 4)

Method: toBlocksLayout
	0 aload_0 (0, 0)
	1 arraylength (0, 0)
	2 istore_1 (0, 0)
	3 aload_0 (0, 0)
	4 iconst_0 (0, 0)
	5 aaload (0, 0)
	6 arraylength (0, 0)
	7 istore_2 (0, 0)
	8 iload_1 (0, 0)
	9 bipush (0, 0)
	10 52 (0, 0)
	11 iadd (0, 0)
	12 iconst_1 (0, 0)
	13 isub (0, 0)
	14 bipush (0, 0)
	15 52 (0, 0)
	16 idiv (0, 0)
	17 istore_3 (0, 0)
	18 iload_2 (0, 0)
	19 bipush (0, 0)
	20 52 (0, 0)
	21 iadd (0, 0)
	22 iconst_1 (0, 0)
	23 isub (0, 0)
	24 bipush (0, 0)
	25 52 (0, 0)
	26 idiv (0, 0)
	27 istore (0, 0)
	28 #4 (0, 0)
	29 iconst_0 (1, 4)
	30 istore (1, 4)
	31 #5 (1, 4)
	32 iload (1, 4)
	33 #5 (1, 4)
	34 aload_0 (1, 4)
	35 arraylength (1, 4)
	36 if_icmpge (1, 4)
	37 33 (1, 4)
	39 aload_0 (1, 4)
	40 iload (1, 4)
	41 #5 (1, 4)
	42 aaload (1, 4)
	43 arraylength (1, 4)
	44 istore (1, 4)
	45 #6 (1, 4)
	46 iload (2, 1)
	47 #6 (2, 1)
	48 iload_2 (2, 1)
	49 if_icmpeq (2, 1)
	50 14 (2, 1)
	52 new (2, 1)
	53 org/apache/commons/math3/exception/DimensionMismatchException (2, 1)
	55 dup (2, 1)
	56 iload_2 (2, 1)
	57 iload (2, 1)
	58 #6 (2, 1)
	59 invokespecial (2, 1)
	60 org/apache/commons/math3/exception/DimensionMismatchException.<init>:(II)V (2, 1)
	62 athrow (2, 1)
	63 iinc (2, 1)
	64 #5 (2, 1)
	65 -89 (2, 1)
	66 goto (2, 1)
	67 -34 (2, 1)
	69 iload_3 (1, 4)
	70 iload (1, 4)
	71 #4 (1, 4)
	72 imul (1, 4)
	73 anewarray (1, 4)
	74 [D (1, 4)
	76 astore (1, 4)
	77 #5 (1, 4)
	78 iconst_0 (1, 4)
	79 istore (1, 4)
	80 #6 (1, 4)
	81 iconst_0 (2, 4)
	82 istore (2, 4)
	83 #7 (2, 4)
	84 iload (2, 4)
	85 #7 (2, 4)
	86 iload_3 (2, 4)
	87 if_icmpge (2, 4)
	88 136 (2, 4)
	90 iload (2, 4)
	91 #7 (2, 4)
	92 bipush (2, 4)
	93 52 (2, 4)
	94 imul (2, 4)
	95 istore (2, 4)
	96 #8 (2, 4)
	97 iload (2, 4)
	98 #8 (2, 4)
	99 bipush (2, 4)
	100 52 (2, 4)
	101 iadd (2, 4)
	102 iload_1 (2, 4)
	103 invokestatic (2, 4)
	104 org/apache/commons/math3/util/FastMath.min:(II)I (2, 4)
	106 istore (2, 4)
	107 #9 (2, 4)
	108 iload (2, 4)
	109 #9 (2, 4)
	110 iload (2, 4)
	111 #8 (2, 4)
	112 isub (2, 4)
	113 istore (2, 4)
	114 #10 (2, 4)
	115 iconst_0 (3, 4)
	116 istore (3, 4)
	117 #11 (3, 4)
	118 iload (3, 4)
	119 #11 (3, 4)
	120 iload (3, 4)
	121 #4 (3, 4)
	122 if_icmpge (3, 4)
	123 95 (3, 4)
	125 iload (3, 4)
	126 #11 (3, 4)
	127 bipush (3, 4)
	128 52 (3, 4)
	129 imul (3, 4)
	130 istore (3, 4)
	131 #12 (3, 4)
	132 iload (3, 4)
	133 #12 (3, 4)
	134 bipush (3, 4)
	135 52 (3, 4)
	136 iadd (3, 4)
	137 iload_2 (3, 4)
	138 invokestatic (3, 4)
	139 org/apache/commons/math3/util/FastMath.min:(II)I (3, 4)
	141 istore (3, 4)
	142 #13 (3, 4)
	143 iload (3, 4)
	144 #13 (3, 4)
	145 iload (3, 4)
	146 #12 (3, 4)
	147 isub (3, 4)
	148 istore (3, 4)
	149 #14 (3, 4)
	150 iload (3, 4)
	151 #10 (3, 4)
	152 iload (3, 4)
	153 #14 (3, 4)
	154 imul (3, 4)
	155 newarray (3, 4)
	156 7 (3, 4)
	157 astore (3, 4)
	158 #15 (3, 4)
	159 aload (3, 4)
	160 #5 (3, 4)
	161 iload (3, 4)
	162 #6 (3, 4)
	163 aload (3, 4)
	164 #15 (3, 4)
	165 aastore (3, 4)
	166 iconst_0 (3, 4)
	167 istore (3, 4)
	168 #16 (3, 4)
	169 iload (4, 4)
	170 #8 (4, 4)
	171 istore (4, 4)
	172 #17 (4, 4)
	173 iload (4, 4)
	174 #17 (4, 4)
	175 iload (4, 4)
	176 #9 (4, 4)
	177 if_icmpge (4, 4)
	178 31 (4, 4)
	180 aload_0 (4, 4)
	181 iload (4, 4)
	182 #17 (4, 4)
	183 aaload (4, 4)
	184 iload (4, 4)
	185 #12 (4, 4)
	186 aload (4, 4)
	187 #15 (4, 4)
	188 iload (4, 4)
	189 #16 (4, 4)
	190 iload (4, 4)
	191 #14 (4, 4)
	192 invokestatic (4, 4)
	193 java/lang/System.arraycopy:(Ljava/lang/Object;ILjava/lang/Object;II)V (4, 4)
	195 iload (4, 4)
	196 #16 (4, 4)
	197 iload (4, 4)
	198 #14 (4, 4)
	199 iadd (4, 4)
	200 istore (4, 4)
	201 #16 (4, 4)
	202 iinc (4, 4)
	203 #17 (4, 4)
	204 -89 (4, 4)
	205 goto (4, 4)
	206 -32 (4, 4)
	208 iinc (3, 4)
	209 #6 (3, 4)
	210 -124 (3, 4)
	211 iinc (3, 4)
	212 #11 (3, 4)
	213 -89 (3, 4)
	214 goto (3, 4)
	215 -96 (3, 4)
	217 iinc (3, 4)
	218 #7 (3, 4)
	219 -89 (3, 4)
	220 goto (3, 4)
	221 -136 (3, 4)
	223 aload (2, 4)
	224 #5 (2, 4)
	225 areturn (2, 4)

Method: createBlocksLayout
	0 iload_0 (0, 0)
	1 bipush (0, 0)
	2 52 (0, 0)
	3 iadd (0, 0)
	4 iconst_1 (0, 0)
	5 isub (0, 0)
	6 bipush (0, 0)
	7 52 (0, 0)
	8 idiv (0, 0)
	9 istore_2 (0, 0)
	10 iload_1 (0, 0)
	11 bipush (0, 0)
	12 52 (0, 0)
	13 iadd (0, 0)
	14 iconst_1 (0, 0)
	15 isub (0, 0)
	16 bipush (0, 0)
	17 52 (0, 0)
	18 idiv (0, 0)
	19 istore_3 (0, 0)
	20 iload_2 (0, 0)
	21 iload_3 (0, 0)
	22 imul (0, 0)
	23 anewarray (0, 0)
	24 [D (0, 0)
	26 astore (0, 0)
	27 #4 (0, 0)
	28 iconst_0 (0, 0)
	29 istore (0, 0)
	30 #5 (0, 0)
	31 iconst_0 (1, 4)
	32 istore (1, 4)
	33 #6 (1, 4)
	34 iload (1, 4)
	35 #6 (1, 4)
	36 iload_2 (1, 4)
	37 if_icmpge (1, 4)
	38 89 (1, 4)
	40 iload (1, 4)
	41 #6 (1, 4)
	42 bipush (1, 4)
	43 52 (1, 4)
	44 imul (1, 4)
	45 istore (1, 4)
	46 #7 (1, 4)
	47 iload (1, 4)
	48 #7 (1, 4)
	49 bipush (1, 4)
	50 52 (1, 4)
	51 iadd (1, 4)
	52 iload_0 (1, 4)
	53 invokestatic (1, 4)
	54 org/apache/commons/math3/util/FastMath.min:(II)I (1, 4)
	56 istore (1, 4)
	57 #8 (1, 4)
	58 iload (1, 4)
	59 #8 (1, 4)
	60 iload (1, 4)
	61 #7 (1, 4)
	62 isub (1, 4)
	63 istore (1, 4)
	64 #9 (1, 4)
	65 iconst_0 (2, 4)
	66 istore (2, 4)
	67 #10 (2, 4)
	68 iload (2, 4)
	69 #10 (2, 4)
	70 iload_3 (2, 4)
	71 if_icmpge (2, 4)
	72 49 (2, 4)
	74 iload (2, 4)
	75 #10 (2, 4)
	76 bipush (2, 4)
	77 52 (2, 4)
	78 imul (2, 4)
	79 istore (2, 4)
	80 #11 (2, 4)
	81 iload (2, 4)
	82 #11 (2, 4)
	83 bipush (2, 4)
	84 52 (2, 4)
	85 iadd (2, 4)
	86 iload_1 (2, 4)
	87 invokestatic (2, 4)
	88 org/apache/commons/math3/util/FastMath.min:(II)I (2, 4)
	90 istore (2, 4)
	91 #12 (2, 4)
	92 iload (2, 4)
	93 #12 (2, 4)
	94 iload (2, 4)
	95 #11 (2, 4)
	96 isub (2, 4)
	97 istore (2, 4)
	98 #13 (2, 4)
	99 aload (2, 4)
	100 #4 (2, 4)
	101 iload (2, 4)
	102 #5 (2, 4)
	103 iload (2, 4)
	104 #9 (2, 4)
	105 iload (2, 4)
	106 #13 (2, 4)
	107 imul (2, 4)
	108 newarray (2, 4)
	109 7 (2, 4)
	110 aastore (2, 4)
	111 iinc (2, 4)
	112 #5 (2, 4)
	113 -124 (2, 4)
	114 iinc (2, 4)
	115 #10 (2, 4)
	116 -89 (2, 4)
	117 goto (2, 4)
	118 -49 (2, 4)
	120 iinc (2, 4)
	121 #6 (2, 4)
	122 -89 (2, 4)
	123 goto (2, 4)
	124 -89 (2, 4)
	126 aload (1, 4)
	127 #4 (1, 4)
	128 areturn (1, 4)

Method: createMatrix
	0 aload_0 (0, 0)
	1 iload_1 (0, 0)
	2 iload_2 (0, 0)
	3 invokevirtual (0, 0)
	4 org/apache/commons/math3/linear/BlockRealMatrix.createMatrix:(II)Lorg/apache/commons/math3/linear/BlockRealMatrix; (0, 0)
	6 areturn (0, 0)

Method: copy
	0 aload_0 (0, 0)
	1 invokevirtual (0, 0)
	2 org/apache/commons/math3/linear/BlockRealMatrix.copy:()Lorg/apache/commons/math3/linear/BlockRealMatrix; (0, 0)
	4 areturn (0, 0)

Method: add
	0 aload_0 (0, 0)
	1 aload_1 (0, 0)
	2 invokevirtual (0, 0)
	3 org/apache/commons/math3/linear/BlockRealMatrix.add:(Lorg/apache/commons/math3/linear/RealMatrix;)Lorg/apache/commons/math3/linear/BlockRealMatrix; (0, 0)
	5 areturn (0, 0)

Method: subtract
	0 aload_0 (0, 0)
	1 aload_1 (0, 0)
	2 invokevirtual (0, 0)
	3 org/apache/commons/math3/linear/BlockRealMatrix.subtract:(Lorg/apache/commons/math3/linear/RealMatrix;)Lorg/apache/commons/math3/linear/BlockRealMatrix; (0, 0)
	5 areturn (0, 0)

Method: scalarAdd
	0 aload_0 (0, 0)
	1 dload_1 (0, 0)
	2 invokevirtual (0, 0)
	3 org/apache/commons/math3/linear/BlockRealMatrix.scalarAdd:(D)Lorg/apache/commons/math3/linear/BlockRealMatrix; (0, 0)
	5 areturn (0, 0)

Method: scalarMultiply
	0 new (0, 0)
	1 org/apache/commons/math3/linear/BlockRealMatrix (0, 0)
	3 dup (0, 0)
	4 aload_0 (0, 0)
	5 getfield (0, 0)
	6 org/apache/commons/math3/linear/BlockRealMatrix.rows:I (0, 0)
	8 aload_0 (0, 0)
	9 getfield (0, 0)
	10 org/apache/commons/math3/linear/BlockRealMatrix.columns:I (0, 0)
	12 invokespecial (0, 0)
	13 org/apache/commons/math3/linear/BlockRealMatrix.<init>:(II)V (0, 0)
	15 astore_3 (0, 0)
	16 iconst_0 (2, 4)
	17 istore (2, 4)
	18 #4 (2, 4)
	19 iload (2, 4)
	20 #4 (2, 4)
	21 aload_3 (2, 4)
	22 getfield (2, 4)
	23 org/apache/commons/math3/linear/BlockRealMatrix.blocks:[[D (2, 4)
	25 arraylength (2, 4)
	26 if_icmpge (2, 4)
	27 56 (2, 4)
	29 aload_3 (2, 4)
	30 getfield (2, 4)
	31 org/apache/commons/math3/linear/BlockRealMatrix.blocks:[[D (2, 4)
	33 iload (2, 4)
	34 #4 (2, 4)
	35 aaload (2, 4)
	36 astore (2, 4)
	37 #5 (2, 4)
	38 aload_0 (2, 4)
	39 getfield (2, 4)
	40 org/apache/commons/math3/linear/BlockRealMatrix.blocks:[[D (2, 4)
	42 iload (2, 4)
	43 #4 (2, 4)
	44 aaload (2, 4)
	45 astore (2, 4)
	46 #6 (2, 4)
	47 iconst_0 (3, 4)
	48 istore (3, 4)
	49 #7 (3, 4)
	50 iload (3, 4)
	51 #7 (3, 4)
	52 aload (3, 4)
	53 #5 (3, 4)
	54 arraylength (3, 4)
	55 if_icmpge (3, 4)
	56 21 (3, 4)
	58 aload (3, 4)
	59 #5 (3, 4)
	60 iload (3, 4)
	61 #7 (3, 4)
	62 aload (3, 4)
	63 #6 (3, 4)
	64 iload (3, 4)
	65 #7 (3, 4)
	66 daload (3, 4)
	67 dload_1 (3, 4)
	68 dmul (3, 4)
	69 dastore (3, 4)
	70 iinc (3, 4)
	71 #7 (3, 4)
	72 -89 (3, 4)
	73 goto (3, 4)
	74 -23 (3, 4)
	76 iinc (3, 4)
	77 #4 (3, 4)
	78 -89 (3, 4)
	79 goto (3, 4)
	80 -60 (3, 4)
	82 aload_3 (2, 4)
	83 areturn (1, 4)

Method: multiply
	0 aload_0 (0, 0)
	1 aload_1 (0, 0)
	2 invokevirtual (0, 0)
	3 org/apache/commons/math3/linear/BlockRealMatrix.multiply:(Lorg/apache/commons/math3/linear/RealMatrix;)Lorg/apache/commons/math3/linear/BlockRealMatrix; (0, 0)
	5 areturn (0, 0)

Method: getData
	0 aload_0 (0, 0)
	1 invokevirtual (0, 0)
	2 org/apache/commons/math3/linear/BlockRealMatrix.getRowDimension:()I (0, 0)
	4 aload_0 (0, 0)
	5 invokevirtual (0, 0)
	6 org/apache/commons/math3/linear/BlockRealMatrix.getColumnDimension:()I (0, 0)
	8 multianewarray (0, 0)
	9 [[D (0, 0)
	11 76 (0, 0)
	12 astore_1 (0, 0)
	13 aload_0 (0, 0)
	14 getfield (0, 0)
	15 org/apache/commons/math3/linear/BlockRealMatrix.columns:I (0, 0)
	17 aload_0 (0, 0)
	18 getfield (0, 0)
	19 org/apache/commons/math3/linear/BlockRealMatrix.blockColumns:I (0, 0)
	21 iconst_1 (0, 0)
	22 isub (0, 0)
	23 bipush (0, 0)
	24 52 (0, 0)
	25 imul (0, 0)
	26 isub (0, 0)
	27 istore_2 (0, 0)
	28 iconst_0 (1, 4)
	29 istore_3 (1, 4)
	30 iload_3 (1, 4)
	31 aload_0 (1, 4)
	32 getfield (1, 4)
	33 org/apache/commons/math3/linear/BlockRealMatrix.blockRows:I (1, 4)
	35 if_icmpge (1, 4)
	36 139 (1, 4)
	38 iload_3 (1, 4)
	39 bipush (1, 4)
	40 52 (1, 4)
	41 imul (1, 4)
	42 istore (1, 4)
	43 #4 (1, 4)
	44 iload (1, 4)
	45 #4 (1, 4)
	46 bipush (1, 4)
	47 52 (1, 4)
	48 iadd (1, 4)
	49 aload_0 (1, 4)
	50 getfield (1, 4)
	51 org/apache/commons/math3/linear/BlockRealMatrix.rows:I (1, 4)
	53 invokestatic (1, 4)
	54 org/apache/commons/math3/util/FastMath.min:(II)I (1, 4)
	56 istore (1, 4)
	57 #5 (1, 4)
	58 iconst_0 (1, 4)
	59 istore (1, 4)
	60 #6 (1, 4)
	61 iconst_0 (1, 4)
	62 istore (1, 4)
	63 #7 (1, 4)
	64 iload (2, 4)
	65 #4 (2, 4)
	66 istore (2, 4)
	67 #8 (2, 4)
	68 iload (2, 4)
	69 #8 (2, 4)
	70 iload (2, 4)
	71 #5 (2, 4)
	72 if_icmpge (2, 4)
	73 96 (2, 4)
	75 aload_1 (2, 4)
	76 iload (2, 4)
	77 #8 (2, 4)
	78 aaload (2, 4)
	79 astore (2, 4)
	80 #9 (2, 4)
	81 iload_3 (2, 4)
	82 aload_0 (2, 4)
	83 getfield (2, 4)
	84 org/apache/commons/math3/linear/BlockRealMatrix.blockColumns:I (2, 4)
	86 imul (2, 4)
	87 istore (2, 4)
	88 #10 (2, 4)
	89 iconst_0 (2, 4)
	90 istore (2, 4)
	91 #11 (2, 4)
	92 iconst_0 (3, 4)
	93 istore (3, 4)
	94 #12 (3, 4)
	95 iload (3, 4)
	96 #12 (3, 4)
	97 aload_0 (3, 4)
	98 getfield (3, 4)
	99 org/apache/commons/math3/linear/BlockRealMatrix.blockColumns:I (3, 4)
	101 iconst_1 (3, 4)
	102 isub (3, 4)
	103 if_icmpge (3, 4)
	104 33 (3, 4)
	106 aload_0 (3, 4)
	107 getfield (3, 4)
	108 org/apache/commons/math3/linear/BlockRealMatrix.blocks:[[D (3, 4)
	110 iload (3, 4)
	111 #10 (3, 4)
	112 iinc (3, 4)
	113 #10 (3, 4)
	114 50 (3, 4)
	115 aaload (3, 4)
	116 iload (3, 4)
	117 #6 (3, 4)
	118 aload (3, 4)
	119 #9 (3, 4)
	120 iload (3, 4)
	121 #11 (3, 4)
	122 bipush (3, 4)
	123 52 (3, 4)
	124 invokestatic (3, 4)
	125 java/lang/System.arraycopy:(Ljava/lang/Object;ILjava/lang/Object;II)V (3, 4)
	127 iinc (3, 4)
	128 #11 (3, 4)
	129 -124 (3, 4)
	130 iinc (3, 4)
	131 #12 (3, 4)
	132 -89 (3, 4)
	133 goto (3, 4)
	134 -38 (3, 4)
	136 aload_0 (2, 4)
	137 getfield (2, 4)
	138 org/apache/commons/math3/linear/BlockRealMatrix.blocks:[[D (2, 4)
	140 iload (2, 4)
	141 #10 (2, 4)
	142 aaload (2, 4)
	143 iload (2, 4)
	144 #7 (2, 4)
	145 aload (2, 4)
	146 #9 (2, 4)
	147 iload (2, 4)
	148 #11 (2, 4)
	149 iload_2 (2, 4)
	150 invokestatic (2, 4)
	151 java/lang/System.arraycopy:(Ljava/lang/Object;ILjava/lang/Object;II)V (2, 4)
	153 iinc (2, 4)
	154 #6 (2, 4)
	155 21 (2, 4)
	156 iload (2, 4)
	157 #7 (2, 4)
	158 iload_2 (2, 4)
	159 iadd (2, 4)
	160 istore (2, 4)
	161 #7 (2, 4)
	162 iinc (2, 4)
	163 #8 (2, 4)
	164 -89 (2, 4)
	165 goto (2, 4)
	166 -97 (2, 4)
	168 iinc (2, 4)
	169 #3 (2, 4)
	170 -89 (2, 4)
	171 goto (2, 4)
	172 -141 (2, 4)
	174 aload_1 (1, 4)
	175 areturn (1, 4)

Method: getNorm
	0 bipush (0, 0)
	1 52 (0, 0)
	2 newarray (0, 0)
	3 7 (0, 0)
	4 astore_1 (0, 0)
	5 dconst_0 (0, 0)
	6 dstore_2 (0, 0)
	7 iconst_0 (1, 4)
	8 istore (1, 4)
	9 #4 (1, 4)
	10 iload (1, 4)
	11 #4 (1, 4)
	12 aload_0 (1, 4)
	13 getfield (1, 4)
	14 org/apache/commons/math3/linear/BlockRealMatrix.blockColumns:I (1, 4)
	16 if_icmpge (1, 4)
	17 156 (1, 4)
	19 aload_0 (1, 4)
	20 iload (1, 4)
	21 #4 (1, 4)
	22 invokespecial (1, 4)
	23 org/apache/commons/math3/linear/BlockRealMatrix.blockWidth:(I)I (1, 4)
	25 istore (1, 4)
	26 #5 (1, 4)
	27 aload_1 (1, 4)
	28 iconst_0 (1, 4)
	29 iload (1, 4)
	30 #5 (1, 4)
	31 dconst_0 (1, 4)
	32 invokestatic (1, 4)
	33 java/util/Arrays.fill:([DIID)V (1, 4)
	35 iconst_0 (2, 4)
	36 istore (2, 4)
	37 #6 (2, 4)
	38 iload (2, 4)
	39 #6 (2, 4)
	40 aload_0 (2, 4)
	41 getfield (2, 4)
	42 org/apache/commons/math3/linear/BlockRealMatrix.blockRows:I (2, 4)
	44 if_icmpge (2, 4)
	45 97 (2, 4)
	47 aload_0 (2, 4)
	48 iload (2, 4)
	49 #6 (2, 4)
	50 invokespecial (2, 4)
	51 org/apache/commons/math3/linear/BlockRealMatrix.blockHeight:(I)I (2, 4)
	53 istore (2, 4)
	54 #7 (2, 4)
	55 aload_0 (2, 4)
	56 getfield (2, 4)
	57 org/apache/commons/math3/linear/BlockRealMatrix.blocks:[[D (2, 4)
	59 iload (2, 4)
	60 #6 (2, 4)
	61 aload_0 (2, 4)
	62 getfield (2, 4)
	63 org/apache/commons/math3/linear/BlockRealMatrix.blockColumns:I (2, 4)
	65 imul (2, 4)
	66 iload (2, 4)
	67 #4 (2, 4)
	68 iadd (2, 4)
	69 aaload (2, 4)
	70 astore (2, 4)
	71 #8 (2, 4)
	72 iconst_0 (3, 4)
	73 istore (3, 4)
	74 #9 (3, 4)
	75 iload (3, 4)
	76 #9 (3, 4)
	77 iload (3, 4)
	78 #5 (3, 4)
	79 if_icmpge (3, 4)
	80 56 (3, 4)
	82 dconst_0 (3, 4)
	83 dstore (3, 4)
	84 #10 (3, 4)
	85 iconst_0 (4, 4)
	86 istore (4, 4)
	87 #12 (4, 4)
	88 iload (4, 4)
	89 #12 (4, 4)
	90 iload (4, 4)
	91 #7 (4, 4)
	92 if_icmpge (4, 4)
	93 28 (4, 4)
	95 dload (4, 4)
	96 #10 (4, 4)
	97 aload (4, 4)
	98 #8 (4, 4)
	99 iload (4, 4)
	100 #12 (4, 4)
	101 iload (4, 4)
	102 #5 (4, 4)
	103 imul (4, 4)
	104 iload (4, 4)
	105 #9 (4, 4)
	106 iadd (4, 4)
	107 daload (4, 4)
	108 invokestatic (4, 4)
	109 org/apache/commons/math3/util/FastMath.abs:(D)D (4, 4)
	111 dadd (4, 4)
	112 dstore (4, 4)
	113 #10 (4, 4)
	114 iinc (4, 4)
	115 #12 (4, 4)
	116 -89 (4, 4)
	117 goto (4, 4)
	118 -29 (4, 4)
	120 aload_1 (3, 4)
	121 iload (3, 4)
	122 #9 (3, 4)
	123 dup2 (3, 4)
	124 daload (3, 4)
	125 dload (3, 4)
	126 #10 (3, 4)
	127 dadd (3, 4)
	128 dastore (3, 4)
	129 iinc (3, 4)
	130 #9 (3, 4)
	131 -89 (3, 4)
	132 goto (3, 4)
	133 -57 (3, 4)
	135 iinc (3, 4)
	136 #6 (3, 4)
	137 -89 (3, 4)
	138 goto (3, 4)
	139 -100 (3, 4)
	141 iconst_0 (3, 4)
	142 istore (3, 4)
	143 #6 (3, 4)
	144 iload (3, 4)
	145 #6 (3, 4)
	146 iload (3, 4)
	147 #5 (3, 4)
	148 if_icmpge (3, 4)
	149 18 (3, 4)
	151 dload_2 (3, 4)
	152 aload_1 (3, 4)
	153 iload (3, 4)
	154 #6 (3, 4)
	155 daload (3, 4)
	156 invokestatic (3, 4)
	157 org/apache/commons/math3/util/FastMath.max:(DD)D (3, 4)
	159 dstore_2 (3, 4)
	160 iinc (3, 4)
	161 #6 (3, 4)
	162 -89 (3, 4)
	163 goto (3, 4)
	164 -19 (3, 4)
	166 iinc (3, 4)
	167 #4 (3, 4)
	168 -89 (3, 4)
	169 goto (3, 4)
	170 -159 (3, 4)
	172 dload_2 (2, 4)
	173 dreturn (2, 4)

Method: getFrobeniusNorm
	0 dconst_0 (0, 0)
	1 dstore_1 (0, 0)
	2 iconst_0 (1, 4)
	3 istore_3 (1, 4)
	4 iload_3 (1, 4)
	5 aload_0 (1, 4)
	6 getfield (1, 4)
	7 org/apache/commons/math3/linear/BlockRealMatrix.blocks:[[D (1, 4)
	9 arraylength (1, 4)
	10 if_icmpge (1, 4)
	11 53 (1, 4)
	13 aload_0 (2, 4)
	14 getfield (2, 4)
	15 org/apache/commons/math3/linear/BlockRealMatrix.blocks:[[D (2, 4)
	17 iload_3 (2, 4)
	18 aaload (2, 4)
	19 astore (2, 4)
	20 #4 (2, 4)
	21 aload (2, 4)
	22 #4 (2, 4)
	23 arraylength (2, 4)
	24 istore (2, 4)
	25 #5 (2, 4)
	26 iconst_0 (2, 4)
	27 istore (2, 4)
	28 #6 (2, 4)
	29 iload (2, 4)
	30 #6 (2, 4)
	31 iload (2, 4)
	32 #5 (2, 4)
	33 if_icmpge (2, 4)
	34 24 (2, 4)
	36 aload (2, 4)
	37 #4 (2, 4)
	38 iload (2, 4)
	39 #6 (2, 4)
	40 daload (2, 4)
	41 dstore (2, 4)
	42 #7 (2, 4)
	43 dload_1 (2, 4)
	44 dload (2, 4)
	45 #7 (2, 4)
	46 dload (2, 4)
	47 #7 (2, 4)
	48 dmul (2, 4)
	49 dadd (2, 4)
	50 dstore_1 (2, 4)
	51 iinc (2, 4)
	52 #6 (2, 4)
	53 -89 (2, 4)
	54 goto (2, 4)
	55 -25 (2, 4)
	57 iinc (2, 4)
	58 #3 (2, 4)
	59 -89 (2, 4)
	60 goto (2, 4)
	61 -56 (2, 4)
	63 dload_1 (1, 4)
	64 invokestatic (1, 4)
	65 org/apache/commons/math3/util/FastMath.sqrt:(D)D (1, 4)
	67 dreturn (1, 4)

Method: getSubMatrix
	0 aload_0 (0, 0)
	1 iload_1 (0, 0)
	2 iload_2 (0, 0)
	3 iload_3 (0, 0)
	4 iload (0, 0)
	5 #4 (0, 0)
	6 invokevirtual (0, 0)
	7 org/apache/commons/math3/linear/BlockRealMatrix.getSubMatrix:(IIII)Lorg/apache/commons/math3/linear/BlockRealMatrix; (0, 0)
	9 areturn (0, 0)

Method: copyBlockPart
	0 iload (0, 0)
	1 #6 (0, 0)
	2 iload (0, 0)
	3 #5 (0, 0)
	4 isub (0, 0)
	5 istore (0, 0)
	6 #11 (0, 0)
	7 iload_3 (0, 0)
	8 iload_2 (0, 0)
	9 imul (0, 0)
	10 iload (0, 0)
	11 #5 (0, 0)
	12 iadd (0, 0)
	13 istore (0, 0)
	14 #12 (0, 0)
	15 iload (0, 0)
	16 #9 (0, 0)
	17 iload (0, 0)
	18 #8 (0, 0)
	19 imul (0, 0)
	20 iload (0, 0)
	21 #10 (0, 0)
	22 iadd (0, 0)
	23 istore (0, 0)
	24 #13 (0, 0)
	25 iload_3 (1, 4)
	26 istore (1, 4)
	27 #14 (1, 4)
	28 iload (1, 4)
	29 #14 (1, 4)
	30 iload (1, 4)
	31 #4 (1, 4)
	32 if_icmpge (1, 4)
	33 34 (1, 4)
	35 aload_1 (1, 4)
	36 iload (1, 4)
	37 #12 (1, 4)
	38 aload (1, 4)
	39 #7 (1, 4)
	40 iload (1, 4)
	41 #13 (1, 4)
	42 iload (1, 4)
	43 #11 (1, 4)
	44 invokestatic (1, 4)
	45 java/lang/System.arraycopy:(Ljava/lang/Object;ILjava/lang/Object;II)V (1, 4)
	47 iload (1, 4)
	48 #12 (1, 4)
	49 iload_2 (1, 4)
	50 iadd (1, 4)
	51 istore (1, 4)
	52 #12 (1, 4)
	53 iload (1, 4)
	54 #13 (1, 4)
	55 iload (1, 4)
	56 #8 (1, 4)
	57 iadd (1, 4)
	58 istore (1, 4)
	59 #13 (1, 4)
	60 iinc (1, 4)
	61 #14 (1, 4)
	62 -89 (1, 4)
	63 goto (1, 4)
	64 -35 (1, 4)
	66 return (0, 0)

Method: setSubMatrix
	0 aload_1 (0, 0)
	1 invokestatic (0, 0)
	2 org/apache/commons/math3/util/MathUtils.checkNotNull:(Ljava/lang/Object;)V (0, 0)
	4 aload_1 (0, 0)
	5 iconst_0 (0, 0)
	6 aaload (0, 0)
	7 arraylength (0, 0)
	8 istore (0, 0)
	9 #4 (0, 0)
	10 iload (1, 1)
	11 #4 (1, 1)
	12 ifne (1, 1)
	13 14 (1, 1)
	15 new (1, 1)
	16 org/apache/commons/math3/exception/NoDataException (1, 1)
	18 dup (1, 1)
	19 getstatic (1, 1)
	20 org/apache/commons/math3/exception/util/LocalizedFormats.AT_LEAST_ONE_COLUMN:Lorg/apache/commons/math3/exception/util/LocalizedFormats; (1, 1)
	22 invokespecial (1, 1)
	23 org/apache/commons/math3/exception/NoDataException.<init>:(Lorg/apache/commons/math3/exception/util/Localizable;)V (1, 1)
	25 athrow (1, 1)
	26 iload_2 (0, 0)
	27 aload_1 (0, 0)
	28 arraylength (0, 0)
	29 iadd (0, 0)
	30 iconst_1 (0, 0)
	31 isub (0, 0)
	32 istore (0, 0)
	33 #5 (0, 0)
	34 iload_3 (0, 0)
	35 iload (0, 0)
	36 #4 (0, 0)
	37 iadd (0, 0)
	38 iconst_1 (0, 0)
	39 isub (0, 0)
	40 istore (0, 0)
	41 #6 (0, 0)
	42 aload_0 (0, 0)
	43 iload_2 (0, 0)
	44 iload (0, 0)
	45 #5 (0, 0)
	46 iload_3 (0, 0)
	47 iload (0, 0)
	48 #6 (0, 0)
	49 invokestatic (0, 0)
	50 org/apache/commons/math3/linear/MatrixUtils.checkSubMatrixIndex:(Lorg/apache/commons/math3/linear/AnyMatrix;IIII)V (0, 0)
	52 aload_1 (1, 4)
	53 astore (1, 4)
	54 #7 (1, 4)
	55 aload (1, 4)
	56 #7 (1, 4)
	57 arraylength (1, 4)
	58 istore (1, 4)
	59 #8 (1, 4)
	60 iconst_0 (1, 4)
	61 istore (1, 4)
	62 #9 (1, 4)
	63 iload (1, 4)
	64 #9 (1, 4)
	65 iload (1, 4)
	66 #8 (1, 4)
	67 if_icmpge (1, 4)
	68 37 (1, 4)
	70 aload (1, 4)
	71 #7 (1, 4)
	72 iload (1, 4)
	73 #9 (1, 4)
	74 aaload (1, 4)
	75 astore (1, 4)
	76 #10 (1, 4)
	77 aload (2, 1)
	78 #10 (2, 1)
	79 arraylength (2, 1)
	80 iload (2, 1)
	81 #4 (2, 1)
	82 if_icmpeq (2, 1)
	83 16 (2, 1)
	85 new (2, 1)
	86 org/apache/commons/math3/exception/DimensionMismatchException (2, 1)
	88 dup (2, 1)
	89 iload (2, 1)
	90 #4 (2, 1)
	91 aload (2, 1)
	92 #10 (2, 1)
	93 arraylength (2, 1)
	94 invokespecial (2, 1)
	95 org/apache/commons/math3/exception/DimensionMismatchException.<init>:(II)V (2, 1)
	97 athrow (2, 1)
	98 iinc (2, 1)
	99 #9 (2, 1)
	100 -89 (2, 1)
	101 goto (2, 1)
	102 -38 (2, 1)
	104 iload_2 (1, 4)
	105 bipush (1, 4)
	106 52 (1, 4)
	107 idiv (1, 4)
	108 istore (1, 4)
	109 #7 (1, 4)
	110 iload (1, 4)
	111 #5 (1, 4)
	112 bipush (1, 4)
	113 52 (1, 4)
	114 iadd (1, 4)
	115 bipush (1, 4)
	116 52 (1, 4)
	117 idiv (1, 4)
	118 istore (1, 4)
	119 #8 (1, 4)
	120 iload_3 (1, 4)
	121 bipush (1, 4)
	122 52 (1, 4)
	123 idiv (1, 4)
	124 istore (1, 4)
	125 #9 (1, 4)
	126 iload (1, 4)
	127 #6 (1, 4)
	128 bipush (1, 4)
	129 52 (1, 4)
	130 iadd (1, 4)
	131 bipush (1, 4)
	132 52 (1, 4)
	133 idiv (1, 4)
	134 istore (1, 4)
	135 #10 (1, 4)
	136 iload (3, 4)
	137 #7 (3, 4)
	138 istore (3, 4)
	139 #11 (3, 4)
	140 iload (3, 4)
	141 #11 (3, 4)
	142 iload (3, 4)
	143 #8 (3, 4)
	144 if_icmpge (3, 4)
	145 172 (3, 4)
	147 aload_0 (3, 4)
	148 iload (3, 4)
	149 #11 (3, 4)
	150 invokespecial (3, 4)
	151 org/apache/commons/math3/linear/BlockRealMatrix.blockHeight:(I)I (3, 4)
	153 istore (3, 4)
	154 #12 (3, 4)
	155 iload (3, 4)
	156 #11 (3, 4)
	157 bipush (3, 4)
	158 52 (3, 4)
	159 imul (3, 4)
	160 istore (3, 4)
	161 #13 (3, 4)
	162 iload_2 (3, 4)
	163 iload (3, 4)
	164 #13 (3, 4)
	165 invokestatic (3, 4)
	166 org/apache/commons/math3/util/FastMath.max:(II)I (3, 4)
	168 istore (3, 4)
	169 #14 (3, 4)
	170 iload (3, 4)
	171 #5 (3, 4)
	172 iconst_1 (3, 4)
	173 iadd (3, 4)
	174 iload (3, 4)
	175 #13 (3, 4)
	176 iload (3, 4)
	177 #12 (3, 4)
	178 iadd (3, 4)
	179 invokestatic (3, 4)
	180 org/apache/commons/math3/util/FastMath.min:(II)I (3, 4)
	182 istore (3, 4)
	183 #15 (3, 4)
	184 iload (4, 4)
	185 #9 (4, 4)
	186 istore (4, 4)
	187 #16 (4, 4)
	188 iload (4, 4)
	189 #16 (4, 4)
	190 iload (4, 4)
	191 #10 (4, 4)
	192 if_icmpge (4, 4)
	193 118 (4, 4)
	195 aload_0 (4, 4)
	196 iload (4, 4)
	197 #16 (4, 4)
	198 invokespecial (4, 4)
	199 org/apache/commons/math3/linear/BlockRealMatrix.blockWidth:(I)I (4, 4)
	201 istore (4, 4)
	202 #17 (4, 4)
	203 iload (4, 4)
	204 #16 (4, 4)
	205 bipush (4, 4)
	206 52 (4, 4)
	207 imul (4, 4)
	208 istore (4, 4)
	209 #18 (4, 4)
	210 iload_3 (4, 4)
	211 iload (4, 4)
	212 #18 (4, 4)
	213 invokestatic (4, 4)
	214 org/apache/commons/math3/util/FastMath.max:(II)I (4, 4)
	216 istore (4, 4)
	217 #19 (4, 4)
	218 iload (4, 4)
	219 #6 (4, 4)
	220 iconst_1 (4, 4)
	221 iadd (4, 4)
	222 iload (4, 4)
	223 #18 (4, 4)
	224 iload (4, 4)
	225 #17 (4, 4)
	226 iadd (4, 4)
	227 invokestatic (4, 4)
	228 org/apache/commons/math3/util/FastMath.min:(II)I (4, 4)
	230 istore (4, 4)
	231 #20 (4, 4)
	232 iload (4, 4)
	233 #20 (4, 4)
	234 iload (4, 4)
	235 #19 (4, 4)
	236 isub (4, 4)
	237 istore (4, 4)
	238 #21 (4, 4)
	239 aload_0 (4, 4)
	240 getfield (4, 4)
	241 org/apache/commons/math3/linear/BlockRealMatrix.blocks:[[D (4, 4)
	243 iload (4, 4)
	244 #11 (4, 4)
	245 aload_0 (4, 4)
	246 getfield (4, 4)
	247 org/apache/commons/math3/linear/BlockRealMatrix.blockColumns:I (4, 4)
	249 imul (4, 4)
	250 iload (4, 4)
	251 #16 (4, 4)
	252 iadd (4, 4)
	253 aaload (4, 4)
	254 astore (4, 4)
	255 #22 (4, 4)
	256 iload (5, 4)
	257 #14 (5, 4)
	258 istore (5, 4)
	259 #23 (5, 4)
	260 iload (5, 4)
	261 #23 (5, 4)
	262 iload (5, 4)
	263 #15 (5, 4)
	264 if_icmpge (5, 4)
	265 40 (5, 4)
	267 aload_1 (5, 4)
	268 iload (5, 4)
	269 #23 (5, 4)
	270 iload_2 (5, 4)
	271 isub (5, 4)
	272 aaload (5, 4)
	273 iload (5, 4)
	274 #19 (5, 4)
	275 iload_3 (5, 4)
	276 isub (5, 4)
	277 aload (5, 4)
	278 #22 (5, 4)
	279 iload (5, 4)
	280 #23 (5, 4)
	281 iload (5, 4)
	282 #13 (5, 4)
	283 isub (5, 4)
	284 iload (5, 4)
	285 #17 (5, 4)
	286 imul (5, 4)
	287 iload (5, 4)
	288 #19 (5, 4)
	289 iload (5, 4)
	290 #18 (5, 4)
	291 isub (5, 4)
	292 iadd (5, 4)
	293 iload (5, 4)
	294 #21 (5, 4)
	295 invokestatic (5, 4)
	296 java/lang/System.arraycopy:(Ljava/lang/Object;ILjava/lang/Object;II)V (5, 4)
	298 iinc (5, 4)
	299 #23 (5, 4)
	300 -89 (5, 4)
	301 goto (5, 4)
	302 -41 (5, 4)
	304 iinc (5, 4)
	305 #16 (5, 4)
	306 -89 (5, 4)
	307 goto (5, 4)
	308 -119 (5, 4)
	310 iinc (5, 4)
	311 #11 (5, 4)
	312 -89 (5, 4)
	313 goto (5, 4)
	314 -173 (5, 4)
	316 return (2, 4)

Method: getRowMatrix
	0 aload_0 (0, 0)
	1 iload_1 (0, 0)
	2 invokevirtual (0, 0)
	3 org/apache/commons/math3/linear/BlockRealMatrix.getRowMatrix:(I)Lorg/apache/commons/math3/linear/BlockRealMatrix; (0, 0)
	5 areturn (0, 0)

Method: setRowMatrix
	0 aload_0 (0, 0)
	1 iload_1 (0, 0)
	2 invokestatic (0, 0)
	3 org/apache/commons/math3/linear/MatrixUtils.checkRowIndex:(Lorg/apache/commons/math3/linear/AnyMatrix;I)V (0, 0)
	5 aload_0 (0, 0)
	6 invokevirtual (0, 0)
	7 org/apache/commons/math3/linear/BlockRealMatrix.getColumnDimension:()I (0, 0)
	9 istore_3 (0, 0)
	10 aload_2 (1, 1)
	11 invokevirtual (1, 1)
	12 org/apache/commons/math3/linear/BlockRealMatrix.getRowDimension:()I (1, 1)
	14 iconst_1 (1, 1)
	15 if_icmpne (1, 1)
	16 11 (1, 1)
	18 aload_2 (1, 1)
	19 invokevirtual (1, 1)
	20 org/apache/commons/math3/linear/BlockRealMatrix.getColumnDimension:()I (1, 1)
	22 iload_3 (1, 1)
	23 if_icmpeq (1, 1)
	24 21 (1, 1)
	26 new (1, 1)
	27 org/apache/commons/math3/linear/MatrixDimensionMismatchException (1, 1)
	29 dup (1, 1)
	30 aload_2 (1, 1)
	31 invokevirtual (1, 1)
	32 org/apache/commons/math3/linear/BlockRealMatrix.getRowDimension:()I (1, 1)
	34 aload_2 (1, 1)
	35 invokevirtual (1, 1)
	36 org/apache/commons/math3/linear/BlockRealMatrix.getColumnDimension:()I (1, 1)
	38 iconst_1 (1, 1)
	39 iload_3 (1, 1)
	40 invokespecial (1, 1)
	41 org/apache/commons/math3/linear/MatrixDimensionMismatchException.<init>:(IIII)V (1, 1)
	43 athrow (1, 1)
	44 iload_1 (2, 4)
	45 bipush (2, 4)
	46 52 (2, 4)
	47 idiv (2, 4)
	48 istore (2, 4)
	49 #4 (2, 4)
	50 iload_1 (2, 4)
	51 iload (2, 4)
	52 #4 (2, 4)
	53 bipush (2, 4)
	54 52 (2, 4)
	55 imul (2, 4)
	56 isub (2, 4)
	57 istore (2, 4)
	58 #5 (2, 4)
	59 iconst_0 (2, 4)
	60 istore (2, 4)
	61 #6 (2, 4)
	62 iconst_0 (2, 4)
	63 istore (2, 4)
	64 #7 (2, 4)
	65 aload_2 (2, 4)
	66 getfield (2, 4)
	67 org/apache/commons/math3/linear/BlockRealMatrix.blocks:[[D (2, 4)
	69 iload (2, 4)
	70 #6 (2, 4)
	71 aaload (2, 4)
	72 astore (2, 4)
	73 #8 (2, 4)
	74 iconst_0 (3, 4)
	75 istore (3, 4)
	76 #9 (3, 4)
	77 iload (3, 4)
	78 #9 (3, 4)
	79 aload_0 (3, 4)
	80 getfield (3, 4)
	81 org/apache/commons/math3/linear/BlockRealMatrix.blockColumns:I (3, 4)
	83 if_icmpge (3, 4)
	84 128 (3, 4)
	86 aload_0 (3, 4)
	87 iload (3, 4)
	88 #9 (3, 4)
	89 invokespecial (3, 4)
	90 org/apache/commons/math3/linear/BlockRealMatrix.blockWidth:(I)I (3, 4)
	92 istore (3, 4)
	93 #10 (3, 4)
	94 aload_0 (3, 4)
	95 getfield (3, 4)
	96 org/apache/commons/math3/linear/BlockRealMatrix.blocks:[[D (3, 4)
	98 iload (3, 4)
	99 #4 (3, 4)
	100 aload_0 (3, 4)
	101 getfield (3, 4)
	102 org/apache/commons/math3/linear/BlockRealMatrix.blockColumns:I (3, 4)
	104 imul (3, 4)
	105 iload (3, 4)
	106 #9 (3, 4)
	107 iadd (3, 4)
	108 aaload (3, 4)
	109 astore (3, 4)
	110 #11 (3, 4)
	111 aload (3, 4)
	112 #8 (3, 4)
	113 arraylength (3, 4)
	114 iload (3, 4)
	115 #7 (3, 4)
	116 isub (3, 4)
	117 istore (3, 4)
	118 #12 (3, 4)
	119 iload (4, 1)
	120 #10 (4, 1)
	121 iload (4, 1)
	122 #12 (4, 1)
	123 if_icmple (4, 1)
	124 59 (4, 1)
	126 aload (4, 1)
	127 #8 (4, 1)
	128 iload (4, 1)
	129 #7 (4, 1)
	130 aload (4, 1)
	131 #11 (4, 1)
	132 iload (4, 1)
	133 #5 (4, 1)
	134 iload (4, 1)
	135 #10 (4, 1)
	136 imul (4, 1)
	137 iload (4, 1)
	138 #12 (4, 1)
	139 invokestatic (4, 1)
	140 java/lang/System.arraycopy:(Ljava/lang/Object;ILjava/lang/Object;II)V (4, 1)
	142 aload_2 (4, 1)
	143 getfield (4, 1)
	144 org/apache/commons/math3/linear/BlockRealMatrix.blocks:[[D (4, 1)
	146 iinc (4, 1)
	147 #6 (4, 1)
	148 21 (4, 1)
	149 iload (4, 1)
	150 #6 (4, 1)
	151 aaload (4, 1)
	152 astore (4, 1)
	153 #8 (4, 1)
	154 aload (4, 1)
	155 #8 (4, 1)
	156 iconst_0 (4, 1)
	157 aload (4, 1)
	158 #11 (4, 1)
	159 iload (4, 1)
	160 #5 (4, 1)
	161 iload (4, 1)
	162 #10 (4, 1)
	163 imul (4, 1)
	164 iload (4, 1)
	165 #10 (4, 1)
	166 iload (4, 1)
	167 #12 (4, 1)
	168 isub (4, 1)
	169 invokestatic (4, 1)
	170 java/lang/System.arraycopy:(Ljava/lang/Object;ILjava/lang/Object;II)V (4, 1)
	172 iload (4, 1)
	173 #10 (4, 1)
	174 iload (4, 1)
	175 #12 (4, 1)
	176 isub (4, 1)
	177 istore (4, 1)
	178 #7 (4, 1)
	179 goto (4, 1)
	180 26 (4, 1)
	182 aload (5, 2)
	183 #8 (5, 2)
	184 iload (5, 2)
	185 #7 (5, 2)
	186 aload (5, 2)
	187 #11 (5, 2)
	188 iload (5, 2)
	189 #5 (5, 2)
	190 iload (5, 2)
	191 #10 (5, 2)
	192 imul (5, 2)
	193 iload (5, 2)
	194 #10 (5, 2)
	195 invokestatic (5, 2)
	196 java/lang/System.arraycopy:(Ljava/lang/Object;ILjava/lang/Object;II)V (5, 2)
	198 iload (5, 2)
	199 #7 (5, 2)
	200 iload (5, 2)
	201 #10 (5, 2)
	202 iadd (5, 2)
	203 istore (5, 2)
	204 #7 (5, 2)
	205 iinc (5, 2)
	206 #9 (5, 2)
	207 -89 (5, 2)
	208 goto (5, 2)
	209 -131 (5, 2)
	211 return (0, 4)

Method: getColumnMatrix
	0 aload_0 (0, 0)
	1 iload_1 (0, 0)
	2 invokevirtual (0, 0)
	3 org/apache/commons/math3/linear/BlockRealMatrix.getColumnMatrix:(I)Lorg/apache/commons/math3/linear/BlockRealMatrix; (0, 0)
	5 areturn (0, 0)

Method: setColumnMatrix
	0 aload_0 (0, 0)
	1 iload_1 (0, 0)
	2 invokestatic (0, 0)
	3 org/apache/commons/math3/linear/MatrixUtils.checkColumnIndex:(Lorg/apache/commons/math3/linear/AnyMatrix;I)V (0, 0)
	5 aload_0 (0, 0)
	6 invokevirtual (0, 0)
	7 org/apache/commons/math3/linear/BlockRealMatrix.getRowDimension:()I (0, 0)
	9 istore_3 (0, 0)
	10 aload_2 (1, 1)
	11 invokevirtual (1, 1)
	12 org/apache/commons/math3/linear/BlockRealMatrix.getRowDimension:()I (1, 1)
	14 iload_3 (1, 1)
	15 if_icmpne (1, 1)
	16 11 (1, 1)
	18 aload_2 (1, 1)
	19 invokevirtual (1, 1)
	20 org/apache/commons/math3/linear/BlockRealMatrix.getColumnDimension:()I (1, 1)
	22 iconst_1 (1, 1)
	23 if_icmpeq (1, 1)
	24 21 (1, 1)
	26 new (1, 1)
	27 org/apache/commons/math3/linear/MatrixDimensionMismatchException (1, 1)
	29 dup (1, 1)
	30 aload_2 (1, 1)
	31 invokevirtual (1, 1)
	32 org/apache/commons/math3/linear/BlockRealMatrix.getRowDimension:()I (1, 1)
	34 aload_2 (1, 1)
	35 invokevirtual (1, 1)
	36 org/apache/commons/math3/linear/BlockRealMatrix.getColumnDimension:()I (1, 1)
	38 iload_3 (1, 1)
	39 iconst_1 (1, 1)
	40 invokespecial (1, 1)
	41 org/apache/commons/math3/linear/MatrixDimensionMismatchException.<init>:(IIII)V (1, 1)
	43 athrow (1, 1)
	44 iload_1 (2, 4)
	45 bipush (2, 4)
	46 52 (2, 4)
	47 idiv (2, 4)
	48 istore (2, 4)
	49 #4 (2, 4)
	50 iload_1 (2, 4)
	51 iload (2, 4)
	52 #4 (2, 4)
	53 bipush (2, 4)
	54 52 (2, 4)
	55 imul (2, 4)
	56 isub (2, 4)
	57 istore (2, 4)
	58 #5 (2, 4)
	59 aload_0 (2, 4)
	60 iload (2, 4)
	61 #4 (2, 4)
	62 invokespecial (2, 4)
	63 org/apache/commons/math3/linear/BlockRealMatrix.blockWidth:(I)I (2, 4)
	65 istore (2, 4)
	66 #6 (2, 4)
	67 iconst_0 (2, 4)
	68 istore (2, 4)
	69 #7 (2, 4)
	70 iconst_0 (2, 4)
	71 istore (2, 4)
	72 #8 (2, 4)
	73 aload_2 (2, 4)
	74 getfield (2, 4)
	75 org/apache/commons/math3/linear/BlockRealMatrix.blocks:[[D (2, 4)
	77 iload (2, 4)
	78 #7 (2, 4)
	79 aaload (2, 4)
	80 astore (2, 4)
	81 #9 (2, 4)
	82 iconst_0 (3, 4)
	83 istore (3, 4)
	84 #10 (3, 4)
	85 iload (3, 4)
	86 #10 (3, 4)
	87 aload_0 (3, 4)
	88 getfield (3, 4)
	89 org/apache/commons/math3/linear/BlockRealMatrix.blockRows:I (3, 4)
	91 if_icmpge (3, 4)
	92 92 (3, 4)
	94 aload_0 (3, 4)
	95 iload (3, 4)
	96 #10 (3, 4)
	97 invokespecial (3, 4)
	98 org/apache/commons/math3/linear/BlockRealMatrix.blockHeight:(I)I (3, 4)
	100 istore (3, 4)
	101 #11 (3, 4)
	102 aload_0 (3, 4)
	103 getfield (3, 4)
	104 org/apache/commons/math3/linear/BlockRealMatrix.blocks:[[D (3, 4)
	106 iload (3, 4)
	107 #10 (3, 4)
	108 aload_0 (3, 4)
	109 getfield (3, 4)
	110 org/apache/commons/math3/linear/BlockRealMatrix.blockColumns:I (3, 4)
	112 imul (3, 4)
	113 iload (3, 4)
	114 #4 (3, 4)
	115 iadd (3, 4)
	116 aaload (3, 4)
	117 astore (3, 4)
	118 #12 (3, 4)
	119 iconst_0 (4, 4)
	120 istore (4, 4)
	121 #13 (4, 4)
	122 iload (4, 4)
	123 #13 (4, 4)
	124 iload (4, 4)
	125 #11 (4, 4)
	126 if_icmpge (4, 4)
	127 51 (4, 4)
	129 iload (5, 1)
	130 #8 (5, 1)
	131 aload (5, 1)
	132 #9 (5, 1)
	133 arraylength (5, 1)
	134 if_icmplt (5, 1)
	135 18 (5, 1)
	137 aload_2 (5, 1)
	138 getfield (5, 1)
	139 org/apache/commons/math3/linear/BlockRealMatrix.blocks:[[D (5, 1)
	141 iinc (5, 1)
	142 #7 (5, 1)
	143 21 (5, 1)
	144 iload (5, 1)
	145 #7 (5, 1)
	146 aaload (5, 1)
	147 astore (5, 1)
	148 #9 (5, 1)
	149 iconst_0 (5, 1)
	150 istore (5, 1)
	151 #8 (5, 1)
	152 aload (4, 4)
	153 #12 (4, 4)
	154 iload (4, 4)
	155 #13 (4, 4)
	156 iload (4, 4)
	157 #6 (4, 4)
	158 imul (4, 4)
	159 iload (4, 4)
	160 #5 (4, 4)
	161 iadd (4, 4)
	162 aload (4, 4)
	163 #9 (4, 4)
	164 iload (4, 4)
	165 #8 (4, 4)
	166 iinc (4, 4)
	167 #8 (4, 4)
	168 49 (4, 4)
	169 daload (4, 4)
	170 dastore (4, 4)
	171 iinc (4, 4)
	172 #13 (4, 4)
	173 -89 (4, 4)
	174 goto (4, 4)
	175 -52 (4, 4)
	177 iinc (4, 4)
	178 #10 (4, 4)
	179 -89 (4, 4)
	180 goto (4, 4)
	181 -95 (4, 4)
	183 return (0, 4)

Method: getRowVector
	0 aload_0 (0, 0)
	1 iload_1 (0, 0)
	2 invokestatic (0, 0)
	3 org/apache/commons/math3/linear/MatrixUtils.checkRowIndex:(Lorg/apache/commons/math3/linear/AnyMatrix;I)V (0, 0)
	5 aload_0 (0, 0)
	6 getfield (0, 0)
	7 org/apache/commons/math3/linear/BlockRealMatrix.columns:I (0, 0)
	9 newarray (0, 0)
	10 7 (0, 0)
	11 astore_2 (0, 0)
	12 iload_1 (1, 4)
	13 bipush (1, 4)
	14 52 (1, 4)
	15 idiv (1, 4)
	16 istore_3 (1, 4)
	17 iload_1 (1, 4)
	18 iload_3 (1, 4)
	19 bipush (1, 4)
	20 52 (1, 4)
	21 imul (1, 4)
	22 isub (1, 4)
	23 istore (1, 4)
	24 #4 (1, 4)
	25 iconst_0 (1, 4)
	26 istore (1, 4)
	27 #5 (1, 4)
	28 iconst_0 (2, 4)
	29 istore (2, 4)
	30 #6 (2, 4)
	31 iload (2, 4)
	32 #6 (2, 4)
	33 aload_0 (2, 4)
	34 getfield (2, 4)
	35 org/apache/commons/math3/linear/BlockRealMatrix.blockColumns:I (2, 4)
	37 if_icmpge (2, 4)
	38 55 (2, 4)
	40 aload_0 (2, 4)
	41 iload (2, 4)
	42 #6 (2, 4)
	43 invokespecial (2, 4)
	44 org/apache/commons/math3/linear/BlockRealMatrix.blockWidth:(I)I (2, 4)
	46 istore (2, 4)
	47 #7 (2, 4)
	48 aload_0 (2, 4)
	49 getfield (2, 4)
	50 org/apache/commons/math3/linear/BlockRealMatrix.blocks:[[D (2, 4)
	52 iload_3 (2, 4)
	53 aload_0 (2, 4)
	54 getfield (2, 4)
	55 org/apache/commons/math3/linear/BlockRealMatrix.blockColumns:I (2, 4)
	57 imul (2, 4)
	58 iload (2, 4)
	59 #6 (2, 4)
	60 iadd (2, 4)
	61 aaload (2, 4)
	62 astore (2, 4)
	63 #8 (2, 4)
	64 aload (2, 4)
	65 #8 (2, 4)
	66 iload (2, 4)
	67 #4 (2, 4)
	68 iload (2, 4)
	69 #7 (2, 4)
	70 imul (2, 4)
	71 aload_2 (2, 4)
	72 iload (2, 4)
	73 #5 (2, 4)
	74 iload (2, 4)
	75 #7 (2, 4)
	76 invokestatic (2, 4)
	77 java/lang/System.arraycopy:(Ljava/lang/Object;ILjava/lang/Object;II)V (2, 4)
	79 iload (2, 4)
	80 #5 (2, 4)
	81 iload (2, 4)
	82 #7 (2, 4)
	83 iadd (2, 4)
	84 istore (2, 4)
	85 #5 (2, 4)
	86 iinc (2, 4)
	87 #6 (2, 4)
	88 -89 (2, 4)
	89 goto (2, 4)
	90 -58 (2, 4)
	92 new (1, 4)
	93 org/apache/commons/math3/linear/ArrayRealVector (1, 4)
	95 dup (1, 4)
	96 aload_2 (1, 4)
	97 iconst_0 (1, 4)
	98 invokespecial (1, 4)
	99 org/apache/commons/math3/linear/ArrayRealVector.<init>:([DZ)V (1, 4)
	101 areturn (0, 4)

Method: setRowVector
	0 aload_0 (0, 0)
	1 iload_1 (0, 0)
	2 aload_2 (0, 0)
	3 checkcast (0, 0)
	4 org/apache/commons/math3/linear/ArrayRealVector (0, 0)
	6 invokevirtual (0, 0)
	7 org/apache/commons/math3/linear/ArrayRealVector.getDataRef:()[D (0, 0)
	9 invokevirtual (0, 0)
	10 org/apache/commons/math3/linear/BlockRealMatrix.setRow:(I[D)V (0, 0)
	12 goto (0, 0)
	13 10 (0, 0)
	15 astore_3 (0, 0)
	16 aload_0 (0, 0)
	17 iload_1 (0, 0)
	18 aload_2 (0, 0)
	19 invokespecial (0, 0)
	20 org/apache/commons/math3/linear/AbstractRealMatrix.setRowVector:(ILorg/apache/commons/math3/linear/RealVector;)V (0, 0)
	22 return (0, 0)

Method: getColumnVector
	0 aload_0 (0, 0)
	1 iload_1 (0, 0)
	2 invokestatic (0, 0)
	3 org/apache/commons/math3/linear/MatrixUtils.checkColumnIndex:(Lorg/apache/commons/math3/linear/AnyMatrix;I)V (0, 0)
	5 aload_0 (0, 0)
	6 getfield (0, 0)
	7 org/apache/commons/math3/linear/BlockRealMatrix.rows:I (0, 0)
	9 newarray (0, 0)
	10 7 (0, 0)
	11 astore_2 (0, 0)
	12 iload_1 (1, 4)
	13 bipush (1, 4)
	14 52 (1, 4)
	15 idiv (1, 4)
	16 istore_3 (1, 4)
	17 iload_1 (1, 4)
	18 iload_3 (1, 4)
	19 bipush (1, 4)
	20 52 (1, 4)
	21 imul (1, 4)
	22 isub (1, 4)
	23 istore (1, 4)
	24 #4 (1, 4)
	25 aload_0 (1, 4)
	26 iload_3 (1, 4)
	27 invokespecial (1, 4)
	28 org/apache/commons/math3/linear/BlockRealMatrix.blockWidth:(I)I (1, 4)
	30 istore (1, 4)
	31 #5 (1, 4)
	32 iconst_0 (1, 4)
	33 istore (1, 4)
	34 #6 (1, 4)
	35 iconst_0 (2, 4)
	36 istore (2, 4)
	37 #7 (2, 4)
	38 iload (2, 4)
	39 #7 (2, 4)
	40 aload_0 (2, 4)
	41 getfield (2, 4)
	42 org/apache/commons/math3/linear/BlockRealMatrix.blockRows:I (2, 4)
	44 if_icmpge (2, 4)
	45 67 (2, 4)
	47 aload_0 (2, 4)
	48 iload (2, 4)
	49 #7 (2, 4)
	50 invokespecial (2, 4)
	51 org/apache/commons/math3/linear/BlockRealMatrix.blockHeight:(I)I (2, 4)
	53 istore (2, 4)
	54 #8 (2, 4)
	55 aload_0 (2, 4)
	56 getfield (2, 4)
	57 org/apache/commons/math3/linear/BlockRealMatrix.blocks:[[D (2, 4)
	59 iload (2, 4)
	60 #7 (2, 4)
	61 aload_0 (2, 4)
	62 getfield (2, 4)
	63 org/apache/commons/math3/linear/BlockRealMatrix.blockColumns:I (2, 4)
	65 imul (2, 4)
	66 iload_3 (2, 4)
	67 iadd (2, 4)
	68 aaload (2, 4)
	69 astore (2, 4)
	70 #9 (2, 4)
	71 iconst_0 (3, 4)
	72 istore (3, 4)
	73 #10 (3, 4)
	74 iload (3, 4)
	75 #10 (3, 4)
	76 iload (3, 4)
	77 #8 (3, 4)
	78 if_icmpge (3, 4)
	79 27 (3, 4)
	81 aload_2 (3, 4)
	82 iload (3, 4)
	83 #6 (3, 4)
	84 iinc (3, 4)
	85 #6 (3, 4)
	86 25 (3, 4)
	87 aload (3, 4)
	88 #9 (3, 4)
	89 iload (3, 4)
	90 #10 (3, 4)
	91 iload (3, 4)
	92 #5 (3, 4)
	93 imul (3, 4)
	94 iload (3, 4)
	95 #4 (3, 4)
	96 iadd (3, 4)
	97 daload (3, 4)
	98 dastore (3, 4)
	99 iinc (3, 4)
	100 #10 (3, 4)
	101 -89 (3, 4)
	102 goto (3, 4)
	103 -28 (3, 4)
	105 iinc (3, 4)
	106 #7 (3, 4)
	107 -89 (3, 4)
	108 goto (3, 4)
	109 -70 (3, 4)
	111 new (2, 4)
	112 org/apache/commons/math3/linear/ArrayRealVector (2, 4)
	114 dup (2, 4)
	115 aload_2 (2, 4)
	116 iconst_0 (2, 4)
	117 invokespecial (2, 4)
	118 org/apache/commons/math3/linear/ArrayRealVector.<init>:([DZ)V (2, 4)
	120 areturn (1, 4)

Method: setColumnVector
	0 aload_0 (0, 0)
	1 iload_1 (0, 0)
	2 aload_2 (0, 0)
	3 checkcast (0, 0)
	4 org/apache/commons/math3/linear/ArrayRealVector (0, 0)
	6 invokevirtual (0, 0)
	7 org/apache/commons/math3/linear/ArrayRealVector.getDataRef:()[D (0, 0)
	9 invokevirtual (0, 0)
	10 org/apache/commons/math3/linear/BlockRealMatrix.setColumn:(I[D)V (0, 0)
	12 goto (0, 0)
	13 10 (0, 0)
	15 astore_3 (0, 0)
	16 aload_0 (0, 0)
	17 iload_1 (0, 0)
	18 aload_2 (0, 0)
	19 invokespecial (0, 0)
	20 org/apache/commons/math3/linear/AbstractRealMatrix.setColumnVector:(ILorg/apache/commons/math3/linear/RealVector;)V (0, 0)
	22 return (0, 0)

Method: getRow
	0 aload_0 (0, 0)
	1 iload_1 (0, 0)
	2 invokestatic (0, 0)
	3 org/apache/commons/math3/linear/MatrixUtils.checkRowIndex:(Lorg/apache/commons/math3/linear/AnyMatrix;I)V (0, 0)
	5 aload_0 (0, 0)
	6 getfield (0, 0)
	7 org/apache/commons/math3/linear/BlockRealMatrix.columns:I (0, 0)
	9 newarray (0, 0)
	10 7 (0, 0)
	11 astore_2 (0, 0)
	12 iload_1 (1, 4)
	13 bipush (1, 4)
	14 52 (1, 4)
	15 idiv (1, 4)
	16 istore_3 (1, 4)
	17 iload_1 (1, 4)
	18 iload_3 (1, 4)
	19 bipush (1, 4)
	20 52 (1, 4)
	21 imul (1, 4)
	22 isub (1, 4)
	23 istore (1, 4)
	24 #4 (1, 4)
	25 iconst_0 (1, 4)
	26 istore (1, 4)
	27 #5 (1, 4)
	28 iconst_0 (2, 4)
	29 istore (2, 4)
	30 #6 (2, 4)
	31 iload (2, 4)
	32 #6 (2, 4)
	33 aload_0 (2, 4)
	34 getfield (2, 4)
	35 org/apache/commons/math3/linear/BlockRealMatrix.blockColumns:I (2, 4)
	37 if_icmpge (2, 4)
	38 55 (2, 4)
	40 aload_0 (2, 4)
	41 iload (2, 4)
	42 #6 (2, 4)
	43 invokespecial (2, 4)
	44 org/apache/commons/math3/linear/BlockRealMatrix.blockWidth:(I)I (2, 4)
	46 istore (2, 4)
	47 #7 (2, 4)
	48 aload_0 (2, 4)
	49 getfield (2, 4)
	50 org/apache/commons/math3/linear/BlockRealMatrix.blocks:[[D (2, 4)
	52 iload_3 (2, 4)
	53 aload_0 (2, 4)
	54 getfield (2, 4)
	55 org/apache/commons/math3/linear/BlockRealMatrix.blockColumns:I (2, 4)
	57 imul (2, 4)
	58 iload (2, 4)
	59 #6 (2, 4)
	60 iadd (2, 4)
	61 aaload (2, 4)
	62 astore (2, 4)
	63 #8 (2, 4)
	64 aload (2, 4)
	65 #8 (2, 4)
	66 iload (2, 4)
	67 #4 (2, 4)
	68 iload (2, 4)
	69 #7 (2, 4)
	70 imul (2, 4)
	71 aload_2 (2, 4)
	72 iload (2, 4)
	73 #5 (2, 4)
	74 iload (2, 4)
	75 #7 (2, 4)
	76 invokestatic (2, 4)
	77 java/lang/System.arraycopy:(Ljava/lang/Object;ILjava/lang/Object;II)V (2, 4)
	79 iload (2, 4)
	80 #5 (2, 4)
	81 iload (2, 4)
	82 #7 (2, 4)
	83 iadd (2, 4)
	84 istore (2, 4)
	85 #5 (2, 4)
	86 iinc (2, 4)
	87 #6 (2, 4)
	88 -89 (2, 4)
	89 goto (2, 4)
	90 -58 (2, 4)
	92 aload_2 (1, 4)
	93 areturn (0, 4)

Method: setRow
	0 aload_0 (0, 0)
	1 iload_1 (0, 0)
	2 invokestatic (0, 0)
	3 org/apache/commons/math3/linear/MatrixUtils.checkRowIndex:(Lorg/apache/commons/math3/linear/AnyMatrix;I)V (0, 0)
	5 aload_0 (0, 0)
	6 invokevirtual (0, 0)
	7 org/apache/commons/math3/linear/BlockRealMatrix.getColumnDimension:()I (0, 0)
	9 istore_3 (0, 0)
	10 aload_2 (1, 1)
	11 arraylength (1, 1)
	12 iload_3 (1, 1)
	13 if_icmpeq (1, 1)
	14 16 (1, 1)
	16 new (1, 1)
	17 org/apache/commons/math3/linear/MatrixDimensionMismatchException (1, 1)
	19 dup (1, 1)
	20 iconst_1 (1, 1)
	21 aload_2 (1, 1)
	22 arraylength (1, 1)
	23 iconst_1 (1, 1)
	24 iload_3 (1, 1)
	25 invokespecial (1, 1)
	26 org/apache/commons/math3/linear/MatrixDimensionMismatchException.<init>:(IIII)V (1, 1)
	28 athrow (1, 1)
	29 iload_1 (1, 4)
	30 bipush (1, 4)
	31 52 (1, 4)
	32 idiv (1, 4)
	33 istore (1, 4)
	34 #4 (1, 4)
	35 iload_1 (1, 4)
	36 iload (1, 4)
	37 #4 (1, 4)
	38 bipush (1, 4)
	39 52 (1, 4)
	40 imul (1, 4)
	41 isub (1, 4)
	42 istore (1, 4)
	43 #5 (1, 4)
	44 iconst_0 (1, 4)
	45 istore (1, 4)
	46 #6 (1, 4)
	47 iconst_0 (2, 4)
	48 istore (2, 4)
	49 #7 (2, 4)
	50 iload (2, 4)
	51 #7 (2, 4)
	52 aload_0 (2, 4)
	53 getfield (2, 4)
	54 org/apache/commons/math3/linear/BlockRealMatrix.blockColumns:I (2, 4)
	56 if_icmpge (2, 4)
	57 56 (2, 4)
	59 aload_0 (2, 4)
	60 iload (2, 4)
	61 #7 (2, 4)
	62 invokespecial (2, 4)
	63 org/apache/commons/math3/linear/BlockRealMatrix.blockWidth:(I)I (2, 4)
	65 istore (2, 4)
	66 #8 (2, 4)
	67 aload_0 (2, 4)
	68 getfield (2, 4)
	69 org/apache/commons/math3/linear/BlockRealMatrix.blocks:[[D (2, 4)
	71 iload (2, 4)
	72 #4 (2, 4)
	73 aload_0 (2, 4)
	74 getfield (2, 4)
	75 org/apache/commons/math3/linear/BlockRealMatrix.blockColumns:I (2, 4)
	77 imul (2, 4)
	78 iload (2, 4)
	79 #7 (2, 4)
	80 iadd (2, 4)
	81 aaload (2, 4)
	82 astore (2, 4)
	83 #9 (2, 4)
	84 aload_2 (2, 4)
	85 iload (2, 4)
	86 #6 (2, 4)
	87 aload (2, 4)
	88 #9 (2, 4)
	89 iload (2, 4)
	90 #5 (2, 4)
	91 iload (2, 4)
	92 #8 (2, 4)
	93 imul (2, 4)
	94 iload (2, 4)
	95 #8 (2, 4)
	96 invokestatic (2, 4)
	97 java/lang/System.arraycopy:(Ljava/lang/Object;ILjava/lang/Object;II)V (2, 4)
	99 iload (2, 4)
	100 #6 (2, 4)
	101 iload (2, 4)
	102 #8 (2, 4)
	103 iadd (2, 4)
	104 istore (2, 4)
	105 #6 (2, 4)
	106 iinc (2, 4)
	107 #7 (2, 4)
	108 -89 (2, 4)
	109 goto (2, 4)
	110 -59 (2, 4)
	112 return (0, 4)

Method: getColumn
	0 aload_0 (0, 0)
	1 iload_1 (0, 0)
	2 invokestatic (0, 0)
	3 org/apache/commons/math3/linear/MatrixUtils.checkColumnIndex:(Lorg/apache/commons/math3/linear/AnyMatrix;I)V (0, 0)
	5 aload_0 (0, 0)
	6 getfield (0, 0)
	7 org/apache/commons/math3/linear/BlockRealMatrix.rows:I (0, 0)
	9 newarray (0, 0)
	10 7 (0, 0)
	11 astore_2 (0, 0)
	12 iload_1 (1, 4)
	13 bipush (1, 4)
	14 52 (1, 4)
	15 idiv (1, 4)
	16 istore_3 (1, 4)
	17 iload_1 (1, 4)
	18 iload_3 (1, 4)
	19 bipush (1, 4)
	20 52 (1, 4)
	21 imul (1, 4)
	22 isub (1, 4)
	23 istore (1, 4)
	24 #4 (1, 4)
	25 aload_0 (1, 4)
	26 iload_3 (1, 4)
	27 invokespecial (1, 4)
	28 org/apache/commons/math3/linear/BlockRealMatrix.blockWidth:(I)I (1, 4)
	30 istore (1, 4)
	31 #5 (1, 4)
	32 iconst_0 (1, 4)
	33 istore (1, 4)
	34 #6 (1, 4)
	35 iconst_0 (2, 4)
	36 istore (2, 4)
	37 #7 (2, 4)
	38 iload (2, 4)
	39 #7 (2, 4)
	40 aload_0 (2, 4)
	41 getfield (2, 4)
	42 org/apache/commons/math3/linear/BlockRealMatrix.blockRows:I (2, 4)
	44 if_icmpge (2, 4)
	45 67 (2, 4)
	47 aload_0 (2, 4)
	48 iload (2, 4)
	49 #7 (2, 4)
	50 invokespecial (2, 4)
	51 org/apache/commons/math3/linear/BlockRealMatrix.blockHeight:(I)I (2, 4)
	53 istore (2, 4)
	54 #8 (2, 4)
	55 aload_0 (2, 4)
	56 getfield (2, 4)
	57 org/apache/commons/math3/linear/BlockRealMatrix.blocks:[[D (2, 4)
	59 iload (2, 4)
	60 #7 (2, 4)
	61 aload_0 (2, 4)
	62 getfield (2, 4)
	63 org/apache/commons/math3/linear/BlockRealMatrix.blockColumns:I (2, 4)
	65 imul (2, 4)
	66 iload_3 (2, 4)
	67 iadd (2, 4)
	68 aaload (2, 4)
	69 astore (2, 4)
	70 #9 (2, 4)
	71 iconst_0 (3, 4)
	72 istore (3, 4)
	73 #10 (3, 4)
	74 iload (3, 4)
	75 #10 (3, 4)
	76 iload (3, 4)
	77 #8 (3, 4)
	78 if_icmpge (3, 4)
	79 27 (3, 4)
	81 aload_2 (3, 4)
	82 iload (3, 4)
	83 #6 (3, 4)
	84 iinc (3, 4)
	85 #6 (3, 4)
	86 25 (3, 4)
	87 aload (3, 4)
	88 #9 (3, 4)
	89 iload (3, 4)
	90 #10 (3, 4)
	91 iload (3, 4)
	92 #5 (3, 4)
	93 imul (3, 4)
	94 iload (3, 4)
	95 #4 (3, 4)
	96 iadd (3, 4)
	97 daload (3, 4)
	98 dastore (3, 4)
	99 iinc (3, 4)
	100 #10 (3, 4)
	101 -89 (3, 4)
	102 goto (3, 4)
	103 -28 (3, 4)
	105 iinc (3, 4)
	106 #7 (3, 4)
	107 -89 (3, 4)
	108 goto (3, 4)
	109 -70 (3, 4)
	111 aload_2 (2, 4)
	112 areturn (1, 4)

Method: setColumn
	0 aload_0 (0, 0)
	1 iload_1 (0, 0)
	2 invokestatic (0, 0)
	3 org/apache/commons/math3/linear/MatrixUtils.checkColumnIndex:(Lorg/apache/commons/math3/linear/AnyMatrix;I)V (0, 0)
	5 aload_0 (0, 0)
	6 invokevirtual (0, 0)
	7 org/apache/commons/math3/linear/BlockRealMatrix.getRowDimension:()I (0, 0)
	9 istore_3 (0, 0)
	10 aload_2 (1, 1)
	11 arraylength (1, 1)
	12 iload_3 (1, 1)
	13 if_icmpeq (1, 1)
	14 16 (1, 1)
	16 new (1, 1)
	17 org/apache/commons/math3/linear/MatrixDimensionMismatchException (1, 1)
	19 dup (1, 1)
	20 aload_2 (1, 1)
	21 arraylength (1, 1)
	22 iconst_1 (1, 1)
	23 iload_3 (1, 1)
	24 iconst_1 (1, 1)
	25 invokespecial (1, 1)
	26 org/apache/commons/math3/linear/MatrixDimensionMismatchException.<init>:(IIII)V (1, 1)
	28 athrow (1, 1)
	29 iload_1 (1, 4)
	30 bipush (1, 4)
	31 52 (1, 4)
	32 idiv (1, 4)
	33 istore (1, 4)
	34 #4 (1, 4)
	35 iload_1 (1, 4)
	36 iload (1, 4)
	37 #4 (1, 4)
	38 bipush (1, 4)
	39 52 (1, 4)
	40 imul (1, 4)
	41 isub (1, 4)
	42 istore (1, 4)
	43 #5 (1, 4)
	44 aload_0 (1, 4)
	45 iload (1, 4)
	46 #4 (1, 4)
	47 invokespecial (1, 4)
	48 org/apache/commons/math3/linear/BlockRealMatrix.blockWidth:(I)I (1, 4)
	50 istore (1, 4)
	51 #6 (1, 4)
	52 iconst_0 (1, 4)
	53 istore (1, 4)
	54 #7 (1, 4)
	55 iconst_0 (2, 4)
	56 istore (2, 4)
	57 #8 (2, 4)
	58 iload (2, 4)
	59 #8 (2, 4)
	60 aload_0 (2, 4)
	61 getfield (2, 4)
	62 org/apache/commons/math3/linear/BlockRealMatrix.blockRows:I (2, 4)
	64 if_icmpge (2, 4)
	65 68 (2, 4)
	67 aload_0 (2, 4)
	68 iload (2, 4)
	69 #8 (2, 4)
	70 invokespecial (2, 4)
	71 org/apache/commons/math3/linear/BlockRealMatrix.blockHeight:(I)I (2, 4)
	73 istore (2, 4)
	74 #9 (2, 4)
	75 aload_0 (2, 4)
	76 getfield (2, 4)
	77 org/apache/commons/math3/linear/BlockRealMatrix.blocks:[[D (2, 4)
	79 iload (2, 4)
	80 #8 (2, 4)
	81 aload_0 (2, 4)
	82 getfield (2, 4)
	83 org/apache/commons/math3/linear/BlockRealMatrix.blockColumns:I (2, 4)
	85 imul (2, 4)
	86 iload (2, 4)
	87 #4 (2, 4)
	88 iadd (2, 4)
	89 aaload (2, 4)
	90 astore (2, 4)
	91 #10 (2, 4)
	92 iconst_0 (3, 4)
	93 istore (3, 4)
	94 #11 (3, 4)
	95 iload (3, 4)
	96 #11 (3, 4)
	97 iload (3, 4)
	98 #9 (3, 4)
	99 if_icmpge (3, 4)
	100 27 (3, 4)
	102 aload (3, 4)
	103 #10 (3, 4)
	104 iload (3, 4)
	105 #11 (3, 4)
	106 iload (3, 4)
	107 #6 (3, 4)
	108 imul (3, 4)
	109 iload (3, 4)
	110 #5 (3, 4)
	111 iadd (3, 4)
	112 aload_2 (3, 4)
	113 iload (3, 4)
	114 #7 (3, 4)
	115 iinc (3, 4)
	116 #7 (3, 4)
	117 49 (3, 4)
	118 daload (3, 4)
	119 dastore (3, 4)
	120 iinc (3, 4)
	121 #11 (3, 4)
	122 -89 (3, 4)
	123 goto (3, 4)
	124 -28 (3, 4)
	126 iinc (3, 4)
	127 #8 (3, 4)
	128 -89 (3, 4)
	129 goto (3, 4)
	130 -71 (3, 4)
	132 return (0, 4)

Method: getEntry
	0 aload_0 (0, 0)
	1 iload_1 (0, 0)
	2 iload_2 (0, 0)
	3 invokestatic (0, 0)
	4 org/apache/commons/math3/linear/MatrixUtils.checkMatrixIndex:(Lorg/apache/commons/math3/linear/AnyMatrix;II)V (0, 0)
	6 iload_1 (0, 0)
	7 bipush (0, 0)
	8 52 (0, 0)
	9 idiv (0, 0)
	10 istore_3 (0, 0)
	11 iload_2 (0, 0)
	12 bipush (0, 0)
	13 52 (0, 0)
	14 idiv (0, 0)
	15 istore (0, 0)
	16 #4 (0, 0)
	17 iload_1 (0, 0)
	18 iload_3 (0, 0)
	19 bipush (0, 0)
	20 52 (0, 0)
	21 imul (0, 0)
	22 isub (0, 0)
	23 aload_0 (0, 0)
	24 iload (0, 0)
	25 #4 (0, 0)
	26 invokespecial (0, 0)
	27 org/apache/commons/math3/linear/BlockRealMatrix.blockWidth:(I)I (0, 0)
	29 imul (0, 0)
	30 iload_2 (0, 0)
	31 iload (0, 0)
	32 #4 (0, 0)
	33 bipush (0, 0)
	34 52 (0, 0)
	35 imul (0, 0)
	36 isub (0, 0)
	37 iadd (0, 0)
	38 istore (0, 0)
	39 #5 (0, 0)
	40 aload_0 (0, 0)
	41 getfield (0, 0)
	42 org/apache/commons/math3/linear/BlockRealMatrix.blocks:[[D (0, 0)
	44 iload_3 (0, 0)
	45 aload_0 (0, 0)
	46 getfield (0, 0)
	47 org/apache/commons/math3/linear/BlockRealMatrix.blockColumns:I (0, 0)
	49 imul (0, 0)
	50 iload (0, 0)
	51 #4 (0, 0)
	52 iadd (0, 0)
	53 aaload (0, 0)
	54 iload (0, 0)
	55 #5 (0, 0)
	56 daload (0, 0)
	57 dreturn (0, 0)

Method: setEntry
	0 aload_0 (0, 0)
	1 iload_1 (0, 0)
	2 iload_2 (0, 0)
	3 invokestatic (0, 0)
	4 org/apache/commons/math3/linear/MatrixUtils.checkMatrixIndex:(Lorg/apache/commons/math3/linear/AnyMatrix;II)V (0, 0)
	6 iload_1 (0, 0)
	7 bipush (0, 0)
	8 52 (0, 0)
	9 idiv (0, 0)
	10 istore (0, 0)
	11 #5 (0, 0)
	12 iload_2 (0, 0)
	13 bipush (0, 0)
	14 52 (0, 0)
	15 idiv (0, 0)
	16 istore (0, 0)
	17 #6 (0, 0)
	18 iload_1 (0, 0)
	19 iload (0, 0)
	20 #5 (0, 0)
	21 bipush (0, 0)
	22 52 (0, 0)
	23 imul (0, 0)
	24 isub (0, 0)
	25 aload_0 (0, 0)
	26 iload (0, 0)
	27 #6 (0, 0)
	28 invokespecial (0, 0)
	29 org/apache/commons/math3/linear/BlockRealMatrix.blockWidth:(I)I (0, 0)
	31 imul (0, 0)
	32 iload_2 (0, 0)
	33 iload (0, 0)
	34 #6 (0, 0)
	35 bipush (0, 0)
	36 52 (0, 0)
	37 imul (0, 0)
	38 isub (0, 0)
	39 iadd (0, 0)
	40 istore (0, 0)
	41 #7 (0, 0)
	42 aload_0 (0, 0)
	43 getfield (0, 0)
	44 org/apache/commons/math3/linear/BlockRealMatrix.blocks:[[D (0, 0)
	46 iload (0, 0)
	47 #5 (0, 0)
	48 aload_0 (0, 0)
	49 getfield (0, 0)
	50 org/apache/commons/math3/linear/BlockRealMatrix.blockColumns:I (0, 0)
	52 imul (0, 0)
	53 iload (0, 0)
	54 #6 (0, 0)
	55 iadd (0, 0)
	56 aaload (0, 0)
	57 iload (0, 0)
	58 #7 (0, 0)
	59 dload_3 (0, 0)
	60 dastore (0, 0)
	61 return (0, 0)

Method: addToEntry
	0 aload_0 (0, 0)
	1 iload_1 (0, 0)
	2 iload_2 (0, 0)
	3 invokestatic (0, 0)
	4 org/apache/commons/math3/linear/MatrixUtils.checkMatrixIndex:(Lorg/apache/commons/math3/linear/AnyMatrix;II)V (0, 0)
	6 iload_1 (0, 0)
	7 bipush (0, 0)
	8 52 (0, 0)
	9 idiv (0, 0)
	10 istore (0, 0)
	11 #5 (0, 0)
	12 iload_2 (0, 0)
	13 bipush (0, 0)
	14 52 (0, 0)
	15 idiv (0, 0)
	16 istore (0, 0)
	17 #6 (0, 0)
	18 iload_1 (0, 0)
	19 iload (0, 0)
	20 #5 (0, 0)
	21 bipush (0, 0)
	22 52 (0, 0)
	23 imul (0, 0)
	24 isub (0, 0)
	25 aload_0 (0, 0)
	26 iload (0, 0)
	27 #6 (0, 0)
	28 invokespecial (0, 0)
	29 org/apache/commons/math3/linear/BlockRealMatrix.blockWidth:(I)I (0, 0)
	31 imul (0, 0)
	32 iload_2 (0, 0)
	33 iload (0, 0)
	34 #6 (0, 0)
	35 bipush (0, 0)
	36 52 (0, 0)
	37 imul (0, 0)
	38 isub (0, 0)
	39 iadd (0, 0)
	40 istore (0, 0)
	41 #7 (0, 0)
	42 aload_0 (0, 0)
	43 getfield (0, 0)
	44 org/apache/commons/math3/linear/BlockRealMatrix.blocks:[[D (0, 0)
	46 iload (0, 0)
	47 #5 (0, 0)
	48 aload_0 (0, 0)
	49 getfield (0, 0)
	50 org/apache/commons/math3/linear/BlockRealMatrix.blockColumns:I (0, 0)
	52 imul (0, 0)
	53 iload (0, 0)
	54 #6 (0, 0)
	55 iadd (0, 0)
	56 aaload (0, 0)
	57 iload (0, 0)
	58 #7 (0, 0)
	59 dup2 (0, 0)
	60 daload (0, 0)
	61 dload_3 (0, 0)
	62 dadd (0, 0)
	63 dastore (0, 0)
	64 return (0, 0)

Method: multiplyEntry
	0 aload_0 (0, 0)
	1 iload_1 (0, 0)
	2 iload_2 (0, 0)
	3 invokestatic (0, 0)
	4 org/apache/commons/math3/linear/MatrixUtils.checkMatrixIndex:(Lorg/apache/commons/math3/linear/AnyMatrix;II)V (0, 0)
	6 iload_1 (0, 0)
	7 bipush (0, 0)
	8 52 (0, 0)
	9 idiv (0, 0)
	10 istore (0, 0)
	11 #5 (0, 0)
	12 iload_2 (0, 0)
	13 bipush (0, 0)
	14 52 (0, 0)
	15 idiv (0, 0)
	16 istore (0, 0)
	17 #6 (0, 0)
	18 iload_1 (0, 0)
	19 iload (0, 0)
	20 #5 (0, 0)
	21 bipush (0, 0)
	22 52 (0, 0)
	23 imul (0, 0)
	24 isub (0, 0)
	25 aload_0 (0, 0)
	26 iload (0, 0)
	27 #6 (0, 0)
	28 invokespecial (0, 0)
	29 org/apache/commons/math3/linear/BlockRealMatrix.blockWidth:(I)I (0, 0)
	31 imul (0, 0)
	32 iload_2 (0, 0)
	33 iload (0, 0)
	34 #6 (0, 0)
	35 bipush (0, 0)
	36 52 (0, 0)
	37 imul (0, 0)
	38 isub (0, 0)
	39 iadd (0, 0)
	40 istore (0, 0)
	41 #7 (0, 0)
	42 aload_0 (0, 0)
	43 getfield (0, 0)
	44 org/apache/commons/math3/linear/BlockRealMatrix.blocks:[[D (0, 0)
	46 iload (0, 0)
	47 #5 (0, 0)
	48 aload_0 (0, 0)
	49 getfield (0, 0)
	50 org/apache/commons/math3/linear/BlockRealMatrix.blockColumns:I (0, 0)
	52 imul (0, 0)
	53 iload (0, 0)
	54 #6 (0, 0)
	55 iadd (0, 0)
	56 aaload (0, 0)
	57 iload (0, 0)
	58 #7 (0, 0)
	59 dup2 (0, 0)
	60 daload (0, 0)
	61 dload_3 (0, 0)
	62 dmul (0, 0)
	63 dastore (0, 0)
	64 return (0, 0)

Method: transpose
	0 aload_0 (0, 0)
	1 invokevirtual (0, 0)
	2 org/apache/commons/math3/linear/BlockRealMatrix.transpose:()Lorg/apache/commons/math3/linear/BlockRealMatrix; (0, 0)
	4 areturn (0, 0)

Method: getRowDimension
	0 aload_0 (0, 0)
	1 getfield (0, 0)
	2 org/apache/commons/math3/linear/BlockRealMatrix.rows:I (0, 0)
	4 ireturn (0, 0)

Method: getColumnDimension
	0 aload_0 (0, 0)
	1 getfield (0, 0)
	2 org/apache/commons/math3/linear/BlockRealMatrix.columns:I (0, 0)
	4 ireturn (0, 0)

Method: operate
	0 aload_1 (1, 1)
	1 arraylength (1, 1)
	2 aload_0 (1, 1)
	3 getfield (1, 1)
	4 org/apache/commons/math3/linear/BlockRealMatrix.columns:I (1, 1)
	6 if_icmpeq (1, 1)
	7 17 (1, 1)
	9 new (1, 1)
	10 org/apache/commons/math3/exception/DimensionMismatchException (1, 1)
	12 dup (1, 1)
	13 aload_1 (1, 1)
	14 arraylength (1, 1)
	15 aload_0 (1, 1)
	16 getfield (1, 1)
	17 org/apache/commons/math3/linear/BlockRealMatrix.columns:I (1, 1)
	19 invokespecial (1, 1)
	20 org/apache/commons/math3/exception/DimensionMismatchException.<init>:(II)V (1, 1)
	22 athrow (1, 1)
	23 aload_0 (0, 0)
	24 getfield (0, 0)
	25 org/apache/commons/math3/linear/BlockRealMatrix.rows:I (0, 0)
	27 newarray (0, 0)
	28 7 (0, 0)
	29 astore_2 (0, 0)
	30 iconst_0 (2, 4)
	31 istore_3 (2, 4)
	32 iload_3 (2, 4)
	33 aload_0 (2, 4)
	34 getfield (2, 4)
	35 org/apache/commons/math3/linear/BlockRealMatrix.blockRows:I (2, 4)
	37 if_icmpge (2, 4)
	38 229 (2, 4)
	40 iload_3 (2, 4)
	41 bipush (2, 4)
	42 52 (2, 4)
	43 imul (2, 4)
	44 istore (2, 4)
	45 #4 (2, 4)
	46 iload (2, 4)
	47 #4 (2, 4)
	48 bipush (2, 4)
	49 52 (2, 4)
	50 iadd (2, 4)
	51 aload_0 (2, 4)
	52 getfield (2, 4)
	53 org/apache/commons/math3/linear/BlockRealMatrix.rows:I (2, 4)
	55 invokestatic (2, 4)
	56 org/apache/commons/math3/util/FastMath.min:(II)I (2, 4)
	58 istore (2, 4)
	59 #5 (2, 4)
	60 iconst_0 (3, 4)
	61 istore (3, 4)
	62 #6 (3, 4)
	63 iload (3, 4)
	64 #6 (3, 4)
	65 aload_0 (3, 4)
	66 getfield (3, 4)
	67 org/apache/commons/math3/linear/BlockRealMatrix.blockColumns:I (3, 4)
	69 if_icmpge (3, 4)
	70 191 (3, 4)
	72 aload_0 (3, 4)
	73 getfield (3, 4)
	74 org/apache/commons/math3/linear/BlockRealMatrix.blocks:[[D (3, 4)
	76 iload_3 (3, 4)
	77 aload_0 (3, 4)
	78 getfield (3, 4)
	79 org/apache/commons/math3/linear/BlockRealMatrix.blockColumns:I (3, 4)
	81 imul (3, 4)
	82 iload (3, 4)
	83 #6 (3, 4)
	84 iadd (3, 4)
	85 aaload (3, 4)
	86 astore (3, 4)
	87 #7 (3, 4)
	88 iload (3, 4)
	89 #6 (3, 4)
	90 bipush (3, 4)
	91 52 (3, 4)
	92 imul (3, 4)
	93 istore (3, 4)
	94 #8 (3, 4)
	95 iload (3, 4)
	96 #8 (3, 4)
	97 bipush (3, 4)
	98 52 (3, 4)
	99 iadd (3, 4)
	100 aload_0 (3, 4)
	101 getfield (3, 4)
	102 org/apache/commons/math3/linear/BlockRealMatrix.columns:I (3, 4)
	104 invokestatic (3, 4)
	105 org/apache/commons/math3/util/FastMath.min:(II)I (3, 4)
	107 istore (3, 4)
	108 #9 (3, 4)
	109 iconst_0 (3, 4)
	110 istore (3, 4)
	111 #10 (3, 4)
	112 iload (4, 4)
	113 #4 (4, 4)
	114 istore (4, 4)
	115 #11 (4, 4)
	116 iload (4, 4)
	117 #11 (4, 4)
	118 iload (4, 4)
	119 #5 (4, 4)
	120 if_icmpge (4, 4)
	121 134 (4, 4)
	123 dconst_0 (4, 4)
	124 dstore (4, 4)
	125 #12 (4, 4)
	126 iload (4, 4)
	127 #8 (4, 4)
	128 istore (4, 4)
	129 #14 (4, 4)
	130 iload (5, 3)
	131 #14 (5, 3)
	132 iload (5, 3)
	133 #9 (5, 3)
	134 iconst_3 (5, 3)
	135 isub (5, 3)
	136 if_icmpge (5, 3)
	137 72 (5, 3)
	139 dload (5, 3)
	140 #12 (5, 3)
	141 aload (5, 3)
	142 #7 (5, 3)
	143 iload (5, 3)
	144 #10 (5, 3)
	145 daload (5, 3)
	146 aload_1 (5, 3)
	147 iload (5, 3)
	148 #14 (5, 3)
	149 daload (5, 3)
	150 dmul (5, 3)
	151 aload (5, 3)
	152 #7 (5, 3)
	153 iload (5, 3)
	154 #10 (5, 3)
	155 iconst_1 (5, 3)
	156 iadd (5, 3)
	157 daload (5, 3)
	158 aload_1 (5, 3)
	159 iload (5, 3)
	160 #14 (5, 3)
	161 iconst_1 (5, 3)
	162 iadd (5, 3)
	163 daload (5, 3)
	164 dmul (5, 3)
	165 dadd (5, 3)
	166 aload (5, 3)
	167 #7 (5, 3)
	168 iload (5, 3)
	169 #10 (5, 3)
	170 iconst_2 (5, 3)
	171 iadd (5, 3)
	172 daload (5, 3)
	173 aload_1 (5, 3)
	174 iload (5, 3)
	175 #14 (5, 3)
	176 iconst_2 (5, 3)
	177 iadd (5, 3)
	178 daload (5, 3)
	179 dmul (5, 3)
	180 dadd (5, 3)
	181 aload (5, 3)
	182 #7 (5, 3)
	183 iload (5, 3)
	184 #10 (5, 3)
	185 iconst_3 (5, 3)
	186 iadd (5, 3)
	187 daload (5, 3)
	188 aload_1 (5, 3)
	189 iload (5, 3)
	190 #14 (5, 3)
	191 iconst_3 (5, 3)
	192 iadd (5, 3)
	193 daload (5, 3)
	194 dmul (5, 3)
	195 dadd (5, 3)
	196 dadd (5, 3)
	197 dstore (5, 3)
	198 #12 (5, 3)
	199 iinc (5, 3)
	200 #10 (5, 3)
	201 -124 (5, 3)
	202 iinc (5, 3)
	203 #14 (5, 3)
	204 -89 (5, 3)
	205 goto (5, 3)
	206 -75 (5, 3)
	208 iload (5, 3)
	209 #14 (5, 3)
	210 iload (5, 3)
	211 #9 (5, 3)
	212 if_icmpge (5, 3)
	213 27 (5, 3)
	215 dload (5, 3)
	216 #12 (5, 3)
	217 aload (5, 3)
	218 #7 (5, 3)
	219 iload (5, 3)
	220 #10 (5, 3)
	221 iinc (5, 3)
	222 #10 (5, 3)
	223 49 (5, 3)
	224 daload (5, 3)
	225 aload_1 (5, 3)
	226 iload (5, 3)
	227 #14 (5, 3)
	228 iinc (5, 3)
	229 #14 (5, 3)
	230 49 (5, 3)
	231 daload (5, 3)
	232 dmul (5, 3)
	233 dadd (5, 3)
	234 dstore (5, 3)
	235 #12 (5, 3)
	236 goto (5, 3)
	237 -28 (5, 3)
	239 aload_2 (4, 4)
	240 iload (4, 4)
	241 #11 (4, 4)
	242 dup2 (4, 4)
	243 daload (4, 4)
	244 dload (4, 4)
	245 #12 (4, 4)
	246 dadd (4, 4)
	247 dastore (4, 4)
	248 iinc (4, 4)
	249 #11 (4, 4)
	250 -89 (4, 4)
	251 goto (4, 4)
	252 -135 (4, 4)
	254 iinc (4, 4)
	255 #6 (4, 4)
	256 -89 (4, 4)
	257 goto (4, 4)
	258 -194 (4, 4)
	260 iinc (4, 4)
	261 #3 (4, 4)
	262 -89 (4, 4)
	263 goto (4, 4)
	264 -231 (4, 4)
	266 aload_2 (3, 4)
	267 areturn (2, 4)

Method: preMultiply
	0 aload_1 (1, 1)
	1 arraylength (1, 1)
	2 aload_0 (1, 1)
	3 getfield (1, 1)
	4 org/apache/commons/math3/linear/BlockRealMatrix.rows:I (1, 1)
	6 if_icmpeq (1, 1)
	7 17 (1, 1)
	9 new (1, 1)
	10 org/apache/commons/math3/exception/DimensionMismatchException (1, 1)
	12 dup (1, 1)
	13 aload_1 (1, 1)
	14 arraylength (1, 1)
	15 aload_0 (1, 1)
	16 getfield (1, 1)
	17 org/apache/commons/math3/linear/BlockRealMatrix.rows:I (1, 1)
	19 invokespecial (1, 1)
	20 org/apache/commons/math3/exception/DimensionMismatchException.<init>:(II)V (1, 1)
	22 athrow (1, 1)
	23 aload_0 (0, 0)
	24 getfield (0, 0)
	25 org/apache/commons/math3/linear/BlockRealMatrix.columns:I (0, 0)
	27 newarray (0, 0)
	28 7 (0, 0)
	29 astore_2 (0, 0)
	30 iconst_0 (2, 4)
	31 istore_3 (2, 4)
	32 iload_3 (2, 4)
	33 aload_0 (2, 4)
	34 getfield (2, 4)
	35 org/apache/commons/math3/linear/BlockRealMatrix.blockColumns:I (2, 4)
	37 if_icmpge (2, 4)
	38 272 (2, 4)
	40 aload_0 (2, 4)
	41 iload_3 (2, 4)
	42 invokespecial (2, 4)
	43 org/apache/commons/math3/linear/BlockRealMatrix.blockWidth:(I)I (2, 4)
	45 istore (2, 4)
	46 #4 (2, 4)
	47 iload (2, 4)
	48 #4 (2, 4)
	49 iload (2, 4)
	50 #4 (2, 4)
	51 iadd (2, 4)
	52 istore (2, 4)
	53 #5 (2, 4)
	54 iload (2, 4)
	55 #5 (2, 4)
	56 iload (2, 4)
	57 #4 (2, 4)
	58 iadd (2, 4)
	59 istore (2, 4)
	60 #6 (2, 4)
	61 iload (2, 4)
	62 #6 (2, 4)
	63 iload (2, 4)
	64 #4 (2, 4)
	65 iadd (2, 4)
	66 istore (2, 4)
	67 #7 (2, 4)
	68 iload_3 (2, 4)
	69 bipush (2, 4)
	70 52 (2, 4)
	71 imul (2, 4)
	72 istore (2, 4)
	73 #8 (2, 4)
	74 iload (2, 4)
	75 #8 (2, 4)
	76 bipush (2, 4)
	77 52 (2, 4)
	78 iadd (2, 4)
	79 aload_0 (2, 4)
	80 getfield (2, 4)
	81 org/apache/commons/math3/linear/BlockRealMatrix.columns:I (2, 4)
	83 invokestatic (2, 4)
	84 org/apache/commons/math3/util/FastMath.min:(II)I (2, 4)
	86 istore (2, 4)
	87 #9 (2, 4)
	88 iconst_0 (3, 4)
	89 istore (3, 4)
	90 #10 (3, 4)
	91 iload (3, 4)
	92 #10 (3, 4)
	93 aload_0 (3, 4)
	94 getfield (3, 4)
	95 org/apache/commons/math3/linear/BlockRealMatrix.blockRows:I (3, 4)
	97 if_icmpge (3, 4)
	98 206 (3, 4)
	100 aload_0 (3, 4)
	101 getfield (3, 4)
	102 org/apache/commons/math3/linear/BlockRealMatrix.blocks:[[D (3, 4)
	104 iload (3, 4)
	105 #10 (3, 4)
	106 aload_0 (3, 4)
	107 getfield (3, 4)
	108 org/apache/commons/math3/linear/BlockRealMatrix.blockColumns:I (3, 4)
	110 imul (3, 4)
	111 iload_3 (3, 4)
	112 iadd (3, 4)
	113 aaload (3, 4)
	114 astore (3, 4)
	115 #11 (3, 4)
	116 iload (3, 4)
	117 #10 (3, 4)
	118 bipush (3, 4)
	119 52 (3, 4)
	120 imul (3, 4)
	121 istore (3, 4)
	122 #12 (3, 4)
	123 iload (3, 4)
	124 #12 (3, 4)
	125 bipush (3, 4)
	126 52 (3, 4)
	127 iadd (3, 4)
	128 aload_0 (3, 4)
	129 getfield (3, 4)
	130 org/apache/commons/math3/linear/BlockRealMatrix.rows:I (3, 4)
	132 invokestatic (3, 4)
	133 org/apache/commons/math3/util/FastMath.min:(II)I (3, 4)
	135 istore (3, 4)
	136 #13 (3, 4)
	137 iload (4, 4)
	138 #8 (4, 4)
	139 istore (4, 4)
	140 #14 (4, 4)
	141 iload (4, 4)
	142 #14 (4, 4)
	143 iload (4, 4)
	144 #9 (4, 4)
	145 if_icmpge (4, 4)
	146 152 (4, 4)
	148 iload (4, 4)
	149 #14 (4, 4)
	150 iload (4, 4)
	151 #8 (4, 4)
	152 isub (4, 4)
	153 istore (4, 4)
	154 #15 (4, 4)
	155 dconst_0 (4, 4)
	156 dstore (4, 4)
	157 #16 (4, 4)
	158 iload (4, 4)
	159 #12 (4, 4)
	160 istore (4, 4)
	161 #18 (4, 4)
	162 iload (5, 3)
	163 #18 (5, 3)
	164 iload (5, 3)
	165 #13 (5, 3)
	166 iconst_3 (5, 3)
	167 isub (5, 3)
	168 if_icmpge (5, 3)
	169 79 (5, 3)
	171 dload (5, 3)
	172 #16 (5, 3)
	173 aload (5, 3)
	174 #11 (5, 3)
	175 iload (5, 3)
	176 #15 (5, 3)
	177 daload (5, 3)
	178 aload_1 (5, 3)
	179 iload (5, 3)
	180 #18 (5, 3)
	181 daload (5, 3)
	182 dmul (5, 3)
	183 aload (5, 3)
	184 #11 (5, 3)
	185 iload (5, 3)
	186 #15 (5, 3)
	187 iload (5, 3)
	188 #4 (5, 3)
	189 iadd (5, 3)
	190 daload (5, 3)
	191 aload_1 (5, 3)
	192 iload (5, 3)
	193 #18 (5, 3)
	194 iconst_1 (5, 3)
	195 iadd (5, 3)
	196 daload (5, 3)
	197 dmul (5, 3)
	198 dadd (5, 3)
	199 aload (5, 3)
	200 #11 (5, 3)
	201 iload (5, 3)
	202 #15 (5, 3)
	203 iload (5, 3)
	204 #5 (5, 3)
	205 iadd (5, 3)
	206 daload (5, 3)
	207 aload_1 (5, 3)
	208 iload (5, 3)
	209 #18 (5, 3)
	210 iconst_2 (5, 3)
	211 iadd (5, 3)
	212 daload (5, 3)
	213 dmul (5, 3)
	214 dadd (5, 3)
	215 aload (5, 3)
	216 #11 (5, 3)
	217 iload (5, 3)
	218 #15 (5, 3)
	219 iload (5, 3)
	220 #6 (5, 3)
	221 iadd (5, 3)
	222 daload (5, 3)
	223 aload_1 (5, 3)
	224 iload (5, 3)
	225 #18 (5, 3)
	226 iconst_3 (5, 3)
	227 iadd (5, 3)
	228 daload (5, 3)
	229 dmul (5, 3)
	230 dadd (5, 3)
	231 dadd (5, 3)
	232 dstore (5, 3)
	233 #16 (5, 3)
	234 iload (5, 3)
	235 #15 (5, 3)
	236 iload (5, 3)
	237 #7 (5, 3)
	238 iadd (5, 3)
	239 istore (5, 3)
	240 #15 (5, 3)
	241 iinc (5, 3)
	242 #18 (5, 3)
	243 -89 (5, 3)
	244 goto (5, 3)
	245 -82 (5, 3)
	247 iload (5, 3)
	248 #18 (5, 3)
	249 iload (5, 3)
	250 #13 (5, 3)
	251 if_icmpge (5, 3)
	252 31 (5, 3)
	254 dload (5, 3)
	255 #16 (5, 3)
	256 aload (5, 3)
	257 #11 (5, 3)
	258 iload (5, 3)
	259 #15 (5, 3)
	260 daload (5, 3)
	261 aload_1 (5, 3)
	262 iload (5, 3)
	263 #18 (5, 3)
	264 iinc (5, 3)
	265 #18 (5, 3)
	266 49 (5, 3)
	267 daload (5, 3)
	268 dmul (5, 3)
	269 dadd (5, 3)
	270 dstore (5, 3)
	271 #16 (5, 3)
	272 iload (5, 3)
	273 #15 (5, 3)
	274 iload (5, 3)
	275 #4 (5, 3)
	276 iadd (5, 3)
	277 istore (5, 3)
	278 #15 (5, 3)
	279 goto (5, 3)
	280 -32 (5, 3)
	282 aload_2 (4, 4)
	283 iload (4, 4)
	284 #14 (4, 4)
	285 dup2 (4, 4)
	286 daload (4, 4)
	287 dload (4, 4)
	288 #16 (4, 4)
	289 dadd (4, 4)
	290 dastore (4, 4)
	291 iinc (4, 4)
	292 #14 (4, 4)
	293 -89 (4, 4)
	294 goto (4, 4)
	295 -153 (4, 4)
	297 iinc (4, 4)
	298 #10 (4, 4)
	299 -89 (4, 4)
	300 goto (4, 4)
	301 -209 (4, 4)
	303 iinc (4, 4)
	304 #3 (4, 4)
	305 -89 (4, 4)
	306 goto (4, 4)
	307 -274 (4, 4)
	309 aload_2 (3, 4)
	310 areturn (2, 4)

Method: walkInRowOrder
	0 aload_0 (0, 0)
	1 iload_2 (0, 0)
	2 iload_3 (0, 0)
	3 iload (0, 0)
	4 #4 (0, 0)
	5 iload (0, 0)
	6 #5 (0, 0)
	7 invokestatic (0, 0)
	8 org/apache/commons/math3/linear/MatrixUtils.checkSubMatrixIndex:(Lorg/apache/commons/math3/linear/AnyMatrix;IIII)V (0, 0)
	10 aload_1 (0, 0)
	11 aload_0 (0, 0)
	12 getfield (0, 0)
	13 org/apache/commons/math3/linear/BlockRealMatrix.rows:I (0, 0)
	15 aload_0 (0, 0)
	16 getfield (0, 0)
	17 org/apache/commons/math3/linear/BlockRealMatrix.columns:I (0, 0)
	19 iload_2 (0, 0)
	20 iload_3 (0, 0)
	21 iload (0, 0)
	22 #4 (0, 0)
	23 iload (0, 0)
	24 #5 (0, 0)
	25 invokeinterface (0, 0)
	26 org/apache/commons/math3/linear/RealMatrixPreservingVisitor.visit:(IID)D (0, 0)
	28 0 (0, 0)
	30 iload_2 (1, 4)
	31 bipush (1, 4)
	32 52 (1, 4)
	33 idiv (1, 4)
	34 istore (1, 4)
	35 #6 (1, 4)
	36 iload (1, 4)
	37 #6 (1, 4)
	38 iconst_1 (1, 4)
	39 iload_3 (1, 4)
	40 bipush (1, 4)
	41 52 (1, 4)
	42 idiv (1, 4)
	43 iadd (1, 4)
	44 if_icmpge (1, 4)
	45 189 (1, 4)
	47 iload (1, 4)
	48 #6 (1, 4)
	49 bipush (1, 4)
	50 52 (1, 4)
	51 imul (1, 4)
	52 istore (1, 4)
	53 #7 (1, 4)
	54 iload_2 (1, 4)
	55 iload (1, 4)
	56 #7 (1, 4)
	57 invokestatic (1, 4)
	58 org/apache/commons/math3/util/FastMath.max:(II)I (1, 4)
	60 istore (1, 4)
	61 #8 (1, 4)
	62 iload (1, 4)
	63 #6 (1, 4)
	64 iconst_1 (1, 4)
	65 iadd (1, 4)
	66 bipush (1, 4)
	67 52 (1, 4)
	68 imul (1, 4)
	69 iconst_1 (1, 4)
	70 iload_3 (1, 4)
	71 iadd (1, 4)
	72 invokestatic (1, 4)
	73 org/apache/commons/math3/util/FastMath.min:(II)I (1, 4)
	75 istore (1, 4)
	76 #9 (1, 4)
	77 iload (2, 4)
	78 #8 (2, 4)
	79 istore (2, 4)
	80 #10 (2, 4)
	81 iload (2, 4)
	82 #10 (2, 4)
	83 iload (2, 4)
	84 #9 (2, 4)
	85 if_icmpge (2, 4)
	86 142 (2, 4)
	88 iload (3, 4)
	89 #4 (3, 4)
	90 bipush (3, 4)
	91 52 (3, 4)
	92 idiv (3, 4)
	93 istore (3, 4)
	94 #11 (3, 4)
	95 iload (3, 4)
	96 #11 (3, 4)
	97 iconst_1 (3, 4)
	98 iload (3, 4)
	99 #5 (3, 4)
	100 bipush (3, 4)
	101 52 (3, 4)
	102 idiv (3, 4)
	103 iadd (3, 4)
	104 if_icmpge (3, 4)
	105 117 (3, 4)
	107 aload_0 (3, 4)
	108 iload (3, 4)
	109 #11 (3, 4)
	110 invokespecial (3, 4)
	111 org/apache/commons/math3/linear/BlockRealMatrix.blockWidth:(I)I (3, 4)
	113 istore (3, 4)
	114 #12 (3, 4)
	115 iload (3, 4)
	116 #11 (3, 4)
	117 bipush (3, 4)
	118 52 (3, 4)
	119 imul (3, 4)
	120 istore (3, 4)
	121 #13 (3, 4)
	122 iload (3, 4)
	123 #4 (3, 4)
	124 iload (3, 4)
	125 #13 (3, 4)
	126 invokestatic (3, 4)
	127 org/apache/commons/math3/util/FastMath.max:(II)I (3, 4)
	129 istore (3, 4)
	130 #14 (3, 4)
	131 iload (3, 4)
	132 #11 (3, 4)
	133 iconst_1 (3, 4)
	134 iadd (3, 4)
	135 bipush (3, 4)
	136 52 (3, 4)
	137 imul (3, 4)
	138 iconst_1 (3, 4)
	139 iload (3, 4)
	140 #5 (3, 4)
	141 iadd (3, 4)
	142 invokestatic (3, 4)
	143 org/apache/commons/math3/util/FastMath.min:(II)I (3, 4)
	145 istore (3, 4)
	146 #15 (3, 4)
	147 aload_0 (3, 4)
	148 getfield (3, 4)
	149 org/apache/commons/math3/linear/BlockRealMatrix.blocks:[[D (3, 4)
	151 iload (3, 4)
	152 #6 (3, 4)
	153 aload_0 (3, 4)
	154 getfield (3, 4)
	155 org/apache/commons/math3/linear/BlockRealMatrix.blockColumns:I (3, 4)
	157 imul (3, 4)
	158 iload (3, 4)
	159 #11 (3, 4)
	160 iadd (3, 4)
	161 aaload (3, 4)
	162 astore (3, 4)
	163 #16 (3, 4)
	164 iload (3, 4)
	165 #10 (3, 4)
	166 iload (3, 4)
	167 #7 (3, 4)
	168 isub (3, 4)
	169 iload (3, 4)
	170 #12 (3, 4)
	171 imul (3, 4)
	172 iload (3, 4)
	173 #14 (3, 4)
	174 iadd (3, 4)
	175 iload (3, 4)
	176 #13 (3, 4)
	177 isub (3, 4)
	178 istore (3, 4)
	179 #17 (3, 4)
	180 iload (4, 4)
	181 #14 (4, 4)
	182 istore (4, 4)
	183 #18 (4, 4)
	184 iload (4, 4)
	185 #18 (4, 4)
	186 iload (4, 4)
	187 #15 (4, 4)
	188 if_icmpge (4, 4)
	189 27 (4, 4)
	191 aload_1 (4, 4)
	192 iload (4, 4)
	193 #10 (4, 4)
	194 iload (4, 4)
	195 #18 (4, 4)
	196 aload (4, 4)
	197 #16 (4, 4)
	198 iload (4, 4)
	199 #17 (4, 4)
	200 daload (4, 4)
	201 invokeinterface (4, 4)
	202 org/apache/commons/math3/linear/RealMatrixPreservingVisitor.copy:()Lorg/apache/commons/math3/linear/BlockRealMatrix; (4, 4)
	204 0 (4, 4)
	206 iinc (4, 4)
	207 #17 (4, 4)
	208 -124 (4, 4)
	209 iinc (4, 4)
	210 #18 (4, 4)
	211 -89 (4, 4)
	212 goto (4, 4)
	213 -28 (4, 4)
	215 iinc (4, 4)
	216 #11 (4, 4)
	217 -89 (4, 4)
	218 goto (4, 4)
	219 -123 (4, 4)
	221 iinc (4, 4)
	222 #10 (4, 4)
	223 -89 (4, 4)
	224 goto (4, 4)
	225 -143 (4, 4)
	227 iinc (4, 4)
	228 #6 (4, 4)
	229 -89 (4, 4)
	230 goto (4, 4)
	231 -194 (4, 4)
	233 aload_1 (3, 4)
	234 invokeinterface (3, 4)
	235 org/apache/commons/math3/linear/RealMatrixPreservingVisitor.org/apache/commons/math3/linear/RealMatrixPreservingVisitor (3, 4)
	237 0 (3, 4)
	239 dreturn (3, 4)

Method: walkInOptimizedOrder
	0 aload_0 (0, 0)
	1 iload_2 (0, 0)
	2 iload_3 (0, 0)
	3 iload (0, 0)
	4 #4 (0, 0)
	5 iload (0, 0)
	6 #5 (0, 0)
	7 invokestatic (0, 0)
	8 org/apache/commons/math3/linear/MatrixUtils.checkSubMatrixIndex:(Lorg/apache/commons/math3/linear/AnyMatrix;IIII)V (0, 0)
	10 aload_1 (0, 0)
	11 aload_0 (0, 0)
	12 getfield (0, 0)
	13 org/apache/commons/math3/linear/BlockRealMatrix.rows:I (0, 0)
	15 aload_0 (0, 0)
	16 getfield (0, 0)
	17 org/apache/commons/math3/linear/BlockRealMatrix.columns:I (0, 0)
	19 iload_2 (0, 0)
	20 iload_3 (0, 0)
	21 iload (0, 0)
	22 #4 (0, 0)
	23 iload (0, 0)
	24 #5 (0, 0)
	25 invokeinterface (0, 0)
	26 org/apache/commons/math3/linear/RealMatrixPreservingVisitor.visit:(IID)D (0, 0)
	28 0 (0, 0)
	30 iload_2 (1, 4)
	31 bipush (1, 4)
	32 52 (1, 4)
	33 idiv (1, 4)
	34 istore (1, 4)
	35 #6 (1, 4)
	36 iload (1, 4)
	37 #6 (1, 4)
	38 iconst_1 (1, 4)
	39 iload_3 (1, 4)
	40 bipush (1, 4)
	41 52 (1, 4)
	42 idiv (1, 4)
	43 iadd (1, 4)
	44 if_icmpge (1, 4)
	45 189 (1, 4)
	47 iload (1, 4)
	48 #6 (1, 4)
	49 bipush (1, 4)
	50 52 (1, 4)
	51 imul (1, 4)
	52 istore (1, 4)
	53 #7 (1, 4)
	54 iload_2 (1, 4)
	55 iload (1, 4)
	56 #7 (1, 4)
	57 invokestatic (1, 4)
	58 org/apache/commons/math3/util/FastMath.max:(II)I (1, 4)
	60 istore (1, 4)
	61 #8 (1, 4)
	62 iload (1, 4)
	63 #6 (1, 4)
	64 iconst_1 (1, 4)
	65 iadd (1, 4)
	66 bipush (1, 4)
	67 52 (1, 4)
	68 imul (1, 4)
	69 iconst_1 (1, 4)
	70 iload_3 (1, 4)
	71 iadd (1, 4)
	72 invokestatic (1, 4)
	73 org/apache/commons/math3/util/FastMath.min:(II)I (1, 4)
	75 istore (1, 4)
	76 #9 (1, 4)
	77 iload (2, 4)
	78 #4 (2, 4)
	79 bipush (2, 4)
	80 52 (2, 4)
	81 idiv (2, 4)
	82 istore (2, 4)
	83 #10 (2, 4)
	84 iload (2, 4)
	85 #10 (2, 4)
	86 iconst_1 (2, 4)
	87 iload (2, 4)
	88 #5 (2, 4)
	89 bipush (2, 4)
	90 52 (2, 4)
	91 idiv (2, 4)
	92 iadd (2, 4)
	93 if_icmpge (2, 4)
	94 134 (2, 4)
	96 aload_0 (2, 4)
	97 iload (2, 4)
	98 #10 (2, 4)
	99 invokespecial (2, 4)
	100 org/apache/commons/math3/linear/BlockRealMatrix.blockWidth:(I)I (2, 4)
	102 istore (2, 4)
	103 #11 (2, 4)
	104 iload (2, 4)
	105 #10 (2, 4)
	106 bipush (2, 4)
	107 52 (2, 4)
	108 imul (2, 4)
	109 istore (2, 4)
	110 #12 (2, 4)
	111 iload (2, 4)
	112 #4 (2, 4)
	113 iload (2, 4)
	114 #12 (2, 4)
	115 invokestatic (2, 4)
	116 org/apache/commons/math3/util/FastMath.max:(II)I (2, 4)
	118 istore (2, 4)
	119 #13 (2, 4)
	120 iload (2, 4)
	121 #10 (2, 4)
	122 iconst_1 (2, 4)
	123 iadd (2, 4)
	124 bipush (2, 4)
	125 52 (2, 4)
	126 imul (2, 4)
	127 iconst_1 (2, 4)
	128 iload (2, 4)
	129 #5 (2, 4)
	130 iadd (2, 4)
	131 invokestatic (2, 4)
	132 org/apache/commons/math3/util/FastMath.min:(II)I (2, 4)
	134 istore (2, 4)
	135 #14 (2, 4)
	136 aload_0 (2, 4)
	137 getfield (2, 4)
	138 org/apache/commons/math3/linear/BlockRealMatrix.blocks:[[D (2, 4)
	140 iload (2, 4)
	141 #6 (2, 4)
	142 aload_0 (2, 4)
	143 getfield (2, 4)
	144 org/apache/commons/math3/linear/BlockRealMatrix.blockColumns:I (2, 4)
	146 imul (2, 4)
	147 iload (2, 4)
	148 #10 (2, 4)
	149 iadd (2, 4)
	150 aaload (2, 4)
	151 astore (2, 4)
	152 #15 (2, 4)
	153 iload (3, 4)
	154 #8 (3, 4)
	155 istore (3, 4)
	156 #16 (3, 4)
	157 iload (3, 4)
	158 #16 (3, 4)
	159 iload (3, 4)
	160 #9 (3, 4)
	161 if_icmpge (3, 4)
	162 60 (3, 4)
	164 iload (3, 4)
	165 #16 (3, 4)
	166 iload (3, 4)
	167 #7 (3, 4)
	168 isub (3, 4)
	169 iload (3, 4)
	170 #11 (3, 4)
	171 imul (3, 4)
	172 iload (3, 4)
	173 #13 (3, 4)
	174 iadd (3, 4)
	175 iload (3, 4)
	176 #12 (3, 4)
	177 isub (3, 4)
	178 istore (3, 4)
	179 #17 (3, 4)
	180 iload (4, 4)
	181 #13 (4, 4)
	182 istore (4, 4)
	183 #18 (4, 4)
	184 iload (4, 4)
	185 #18 (4, 4)
	186 iload (4, 4)
	187 #14 (4, 4)
	188 if_icmpge (4, 4)
	189 27 (4, 4)
	191 aload_1 (4, 4)
	192 iload (4, 4)
	193 #16 (4, 4)
	194 iload (4, 4)
	195 #18 (4, 4)
	196 aload (4, 4)
	197 #15 (4, 4)
	198 iload (4, 4)
	199 #17 (4, 4)
	200 daload (4, 4)
	201 invokeinterface (4, 4)
	202 org/apache/commons/math3/linear/RealMatrixPreservingVisitor.copy:()Lorg/apache/commons/math3/linear/BlockRealMatrix; (4, 4)
	204 0 (4, 4)
	206 iinc (4, 4)
	207 #17 (4, 4)
	208 -124 (4, 4)
	209 iinc (4, 4)
	210 #18 (4, 4)
	211 -89 (4, 4)
	212 goto (4, 4)
	213 -28 (4, 4)
	215 iinc (4, 4)
	216 #16 (4, 4)
	217 -89 (4, 4)
	218 goto (4, 4)
	219 -61 (4, 4)
	221 iinc (4, 4)
	222 #10 (4, 4)
	223 -89 (4, 4)
	224 goto (4, 4)
	225 -140 (4, 4)
	227 iinc (4, 4)
	228 #6 (4, 4)
	229 -89 (4, 4)
	230 goto (4, 4)
	231 -194 (4, 4)
	233 aload_1 (3, 4)
	234 invokeinterface (3, 4)
	235 org/apache/commons/math3/linear/RealMatrixPreservingVisitor.org/apache/commons/math3/linear/RealMatrixPreservingVisitor (3, 4)
	237 0 (3, 4)
	239 dreturn (3, 4)

Method: blockHeight
	0 iload_1 (0, 0)
	1 aload_0 (0, 0)
	2 getfield (0, 0)
	3 org/apache/commons/math3/linear/BlockRealMatrix.blockRows:I (0, 0)
	5 iconst_1 (0, 0)
	6 isub (0, 0)
	7 if_icmpne (0, 0)
	8 15 (0, 0)
	10 aload_0 (0, 0)
	11 getfield (0, 0)
	12 org/apache/commons/math3/linear/BlockRealMatrix.rows:I (0, 0)
	14 iload_1 (0, 0)
	15 bipush (0, 0)
	16 52 (0, 0)
	17 imul (0, 0)
	18 isub (0, 0)
	19 goto (0, 0)
	20 5 (0, 0)
	22 bipush (0, 0)
	23 52 (0, 0)
	24 ireturn (0, 0)

Method: blockWidth
	0 iload_1 (0, 0)
	1 aload_0 (0, 0)
	2 getfield (0, 0)
	3 org/apache/commons/math3/linear/BlockRealMatrix.blockColumns:I (0, 0)
	5 iconst_1 (0, 0)
	6 isub (0, 0)
	7 if_icmpne (0, 0)
	8 15 (0, 0)
	10 aload_0 (0, 0)
	11 getfield (0, 0)
	12 org/apache/commons/math3/linear/BlockRealMatrix.columns:I (0, 0)
	14 iload_1 (0, 0)
	15 bipush (0, 0)
	16 52 (0, 0)
	17 imul (0, 0)
	18 isub (0, 0)
	19 goto (0, 0)
	20 5 (0, 0)
	22 bipush (0, 0)
	23 52 (0, 0)
	24 ireturn (0, 0)

