Method: <init>
	0 aload_0 (0, 0)
	1 aload_1 (0, 0)
	2 invokespecial (0, 0)
	5 aload_0 (0, 0)
	6 dload_2 (0, 0)
	7 putfield (0, 0)
	10 aload_0 (0, 0)
	11 iload (0, 0)
	13 putfield (0, 0)
	16 return (0, 0)

Method: getCheck
	0 aload_0 (0, 0)
	1 getfield (0, 0)
	4 ireturn (0, 0)

Method: solveInPlace
	0 aload_1 (0, 0)
	1 aload_2 (0, 0)
	2 aload_3 (0, 0)
	3 aload (0, 0)
	5 invokestatic (0, 0)
	8 aload_0 (0, 0)
	9 invokevirtual (0, 0)
	12 astore (0, 0)
	14 aload (0, 0)
	16 invokevirtual (0, 0)
	19 aload_0 (0, 0)
	20 getfield (0, 0)
	23 aload_3 (0, 0)
	24 invokevirtual (0, 0)
	27 dmul (0, 0)
	28 dstore (0, 0)
	30 aload_3 (0, 1)
	31 invokestatic (0, 1)
	34 astore (0, 1)
	36 aload (0, 1)
	38 invokevirtual (0, 1)
	41 aload (0, 4)
	43 astore (0, 4)
	45 aload (0, 1)
	47 invokestatic (0, 1)
	50 astore (0, 1)
	52 aload (0, 1)
	54 invokevirtual (0, 1)
	57 astore (0, 1)
	59 aload_1 (0, 1)
	60 aload (0, 1)
	62 invokevirtual (0, 1)
	65 astore (0, 1)
	67 aload_3 (0, 1)
	68 dconst_1 (0, 1)
	69 ldc2_w (0, 1)
	72 aload (0, 1)
	74 invokevirtual (0, 1)
	77 astore (0, 1)
	79 aload (0, 1)
	81 invokestatic (0, 1)
	84 astore (0, 1)
	86 aload (0, 1)
	88 invokevirtual (0, 1)
	91 dstore (0, 1)
	93 aload_2 (1, 1)
	94 ifnonnull (1, 1)
	97 aload (1, 1)
	99 astore (1, 1)
	101 goto (1, 1)
	104 aconst_null (1, 2)
	105 astore (1, 2)
	107 new (0, 1)
	110 dup (0, 1)
	111 aload_0 (0, 1)
	112 aload (0, 1)
	114 invokevirtual (0, 1)
	117 aload (0, 1)
	119 aload (0, 1)
	121 aload (0, 1)
	123 dload (0, 1)
	125 invokespecial (0, 1)
	128 astore (0, 1)
	130 aload (0, 1)
	132 aload (0, 1)
	134 invokevirtual (0, 1)
	137 dload (1, 1)
	139 dload (1, 1)
	141 dcmpg (1, 1)
	142 ifgt (1, 1)
	145 aload (1, 1)
	147 aload (1, 1)
	149 invokevirtual (1, 1)
	152 aload (1, 1)
	154 areturn (1, 1)
	155 dconst_0 (0, 1)
	156 dstore (0, 1)
	158 aload (1, 3)
	160 invokevirtual (1, 3)
	163 new (1, 3)
	166 dup (1, 3)
	167 aload_0 (1, 3)
	168 aload (1, 3)
	170 invokevirtual (1, 3)
	173 aload (1, 3)
	175 aload (1, 3)
	177 aload (1, 3)
	179 dload (1, 3)
	181 invokespecial (1, 3)
	184 astore (1, 3)
	186 aload (1, 3)
	188 aload (1, 3)
	190 invokevirtual (1, 3)
	193 aload_2 (2, 1)
	194 ifnull (2, 1)
	197 aload_2 (2, 1)
	198 aload (2, 1)
	200 invokevirtual (2, 1)
	203 astore (2, 1)
	205 aload (1, 3)
	207 aload (1, 3)
	209 invokevirtual (1, 3)
	212 dstore (1, 3)
	214 aload_0 (2, 1)
	215 getfield (2, 1)
	218 ifeq (2, 1)
	221 dload (2, 1)
	223 dconst_0 (2, 1)
	224 dcmpg (2, 1)
	225 ifgt (2, 1)
	228 new (2, 1)
	231 dup (2, 1)
	232 invokespecial (2, 1)
	235 astore (2, 1)
	237 aload (2, 1)
	239 invokevirtual (2, 1)
	242 astore (2, 1)
	244 aload (2, 1)
	246 ldc (2, 1)
	248 aload_2 (2, 1)
	249 invokevirtual (2, 1)
	252 aload (2, 1)
	254 ldc (2, 1)
	256 aload (2, 1)
	258 invokevirtual (2, 1)
	261 aload (2, 1)
	263 athrow (2, 1)
	264 aload (2, 1)
	266 invokevirtual (2, 1)
	269 iconst_2 (2, 1)
	270 if_icmpne (2, 1)
	273 aload (2, 1)
	275 iconst_0 (2, 1)
	276 aload (2, 1)
	278 invokevirtual (2, 1)
	281 goto (2, 1)
	284 aload (2, 2)
	286 dload (2, 2)
	288 dload (2, 2)
	290 ddiv (2, 2)
	291 dconst_1 (2, 2)
	292 aload (2, 2)
	294 invokevirtual (2, 2)
	297 pop (2, 2)
	298 aload_1 (1, 1)
	299 aload (1, 1)
	301 invokevirtual (1, 1)
	304 astore (1, 1)
	306 aload (1, 1)
	308 aload (1, 1)
	310 invokevirtual (1, 1)
	313 dstore (1, 1)
	315 aload_0 (2, 1)
	316 getfield (2, 1)
	319 ifeq (2, 1)
	322 dload (2, 1)
	324 dconst_0 (2, 1)
	325 dcmpg (2, 1)
	326 ifgt (2, 1)
	329 new (2, 1)
	332 dup (2, 1)
	333 invokespecial (2, 1)
	336 astore (2, 1)
	338 aload (2, 1)
	340 invokevirtual (2, 1)
	343 astore (2, 1)
	345 aload (2, 1)
	347 ldc (2, 1)
	349 aload_1 (2, 1)
	350 invokevirtual (2, 1)
	353 aload (2, 1)
	355 ldc (2, 1)
	357 aload (2, 1)
	359 invokevirtual (2, 1)
	362 aload (2, 1)
	364 athrow (2, 1)
	365 dload (1, 1)
	367 dload (1, 1)
	369 ddiv (1, 1)
	370 dstore (1, 1)
	372 aload (1, 1)
	374 dconst_1 (1, 1)
	375 dload (1, 1)
	377 aload (1, 1)
	379 invokevirtual (1, 1)
	382 pop (1, 1)
	383 aload (1, 1)
	385 dconst_1 (1, 1)
	386 dload (1, 1)
	388 dneg (1, 1)
	389 aload (1, 1)
	391 invokevirtual (1, 1)
	394 pop (1, 1)
	395 dload (1, 1)
	397 dstore (1, 1)
	399 aload (1, 1)
	401 invokevirtual (1, 1)
	404 dstore (1, 1)
	406 new (1, 1)
	409 dup (1, 1)
	410 aload_0 (1, 1)
	411 aload (1, 1)
	413 invokevirtual (1, 1)
	416 aload (1, 1)
	418 aload (1, 1)
	420 aload (1, 1)
	422 dload (1, 1)
	424 invokespecial (1, 1)
	427 astore (1, 1)
	429 aload (1, 4)
	431 aload (1, 4)
	433 invokevirtual (1, 4)
	436 dload (2, 1)
	438 dload (2, 1)
	440 dcmpg (2, 1)
	441 ifgt (2, 1)
	444 aload (2, 1)
	446 aload (2, 1)
	448 invokevirtual (2, 1)
	451 aload (2, 1)
	453 areturn (2, 1)
	454 goto (0, 1)

