Method: <init>
	0 aload_0 (0, 0)
	1 aload_1 (0, 0)
	2 invokespecial (0, 0)
	3 org/apache/commons/math3/linear/PreconditionedIterativeLinearSolver.<init>:(Lorg/apache/commons/math3/util/IterationManager;)V (0, 0)
	5 aload_0 (0, 0)
	6 dload_2 (0, 0)
	7 putfield (0, 0)
	8 org/apache/commons/math3/linear/ConjugateGradient.delta:D (0, 0)
	10 aload_0 (0, 0)
	11 iload (0, 0)
	12 #4 (0, 0)
	13 putfield (0, 0)
	14 org/apache/commons/math3/linear/ConjugateGradient.check:Z (0, 0)
	16 return (0, 0)

Method: getCheck
	0 aload_0 (0, 0)
	1 getfield (0, 0)
	2 org/apache/commons/math3/linear/ConjugateGradient.check:Z (0, 0)
	4 ireturn (0, 0)

Method: solveInPlace
	0 aload_1 (0, 0)
	1 aload_2 (0, 0)
	2 aload_3 (0, 0)
	3 aload (0, 0)
	4 #4 (0, 0)
	5 invokestatic (0, 0)
	6 org/apache/commons/math3/linear/ConjugateGradient.checkParameters:(Lorg/apache/commons/math3/linear/RealLinearOperator;Lorg/apache/commons/math3/linear/RealLinearOperator;Lorg/apache/commons/math3/linear/RealVector;Lorg/apache/commons/math3/linear/RealVector;)V (0, 0)
	8 aload_0 (0, 0)
	9 invokevirtual (0, 0)
	10 org/apache/commons/math3/linear/ConjugateGradient.getIterationManager:()Lorg/apache/commons/math3/util/IterationManager; (0, 0)
	12 astore (0, 0)
	13 #5 (0, 0)
	14 aload (0, 0)
	15 #5 (0, 0)
	16 invokevirtual (0, 0)
	17 org/apache/commons/math3/util/IterationManager.resetIterationCount:()V (0, 0)
	19 aload_0 (0, 0)
	20 getfield (0, 0)
	21 org/apache/commons/math3/linear/ConjugateGradient.delta:D (0, 0)
	23 aload_3 (0, 0)
	24 invokevirtual (0, 0)
	25 org/apache/commons/math3/linear/RealVector.getNorm:()D (0, 0)
	27 dmul (0, 0)
	28 dstore (0, 0)
	29 #6 (0, 0)
	30 aload_3 (1, 1)
	31 invokestatic (1, 1)
	32 org/apache/commons/math3/linear/RealVector.unmodifiableRealVector:(Lorg/apache/commons/math3/linear/RealVector;)Lorg/apache/commons/math3/linear/RealVector; (1, 1)
	34 astore (1, 1)
	35 #8 (1, 1)
	36 aload (1, 1)
	37 #5 (1, 1)
	38 invokevirtual (1, 1)
	39 org/apache/commons/math3/util/IterationManager.incrementIterationCount:()V (1, 1)
	41 aload (2, 4)
	42 #4 (2, 4)
	43 astore (2, 4)
	44 #9 (2, 4)
	45 aload (3, 1)
	46 #9 (3, 1)
	47 invokestatic (3, 1)
	48 org/apache/commons/math3/linear/RealVector.unmodifiableRealVector:(Lorg/apache/commons/math3/linear/RealVector;)Lorg/apache/commons/math3/linear/RealVector; (3, 1)
	50 astore (3, 1)
	51 #10 (3, 1)
	52 aload (3, 1)
	53 #9 (3, 1)
	54 invokevirtual (3, 1)
	55 org/apache/commons/math3/linear/RealVector.copy:()Lorg/apache/commons/math3/linear/RealVector; (3, 1)
	57 astore (3, 1)
	58 #11 (3, 1)
	59 aload_1 (3, 1)
	60 aload (3, 1)
	61 #11 (3, 1)
	62 invokevirtual (3, 1)
	63 org/apache/commons/math3/linear/RealLinearOperator.operate:(Lorg/apache/commons/math3/linear/RealVector;)Lorg/apache/commons/math3/linear/RealVector; (3, 1)
	65 astore (3, 1)
	66 #12 (3, 1)
	67 aload_3 (3, 1)
	68 dconst_1 (3, 1)
	69 ldc2_w (3, 1)
	70 -1.0 (3, 1)
	72 aload (3, 1)
	73 #12 (3, 1)
	74 invokevirtual (3, 1)
	75 org/apache/commons/math3/linear/RealVector.combine:(DDLorg/apache/commons/math3/linear/RealVector;)Lorg/apache/commons/math3/linear/RealVector; (3, 1)
	77 astore (3, 1)
	78 #13 (3, 1)
	79 aload (4, 1)
	80 #13 (4, 1)
	81 invokestatic (4, 1)
	82 org/apache/commons/math3/linear/RealVector.unmodifiableRealVector:(Lorg/apache/commons/math3/linear/RealVector;)Lorg/apache/commons/math3/linear/RealVector; (4, 1)
	84 astore (4, 1)
	85 #14 (4, 1)
	86 aload (4, 1)
	87 #13 (4, 1)
	88 invokevirtual (4, 1)
	89 org/apache/commons/math3/linear/RealVector.getNorm:()D (4, 1)
	91 dstore (4, 1)
	92 #15 (4, 1)
	93 aload_2 (5, 1)
	94 ifnonnull (5, 1)
	95 10 (5, 1)
	97 aload (5, 1)
	98 #13 (5, 1)
	99 astore (5, 1)
	100 #17 (5, 1)
	101 goto (5, 1)
	102 6 (5, 1)
	104 aconst_null (6, 2)
	105 astore (6, 2)
	106 #17 (6, 2)
	107 new (4, 1)
	108 org/apache/commons/math3/linear/DefaultIterativeLinearSolverEvent (4, 1)
	110 dup (4, 1)
	111 aload_0 (4, 1)
	112 aload (4, 1)
	113 #5 (4, 1)
	114 invokevirtual (4, 1)
	115 org/apache/commons/math3/util/IterationManager.getIterations:()I (4, 1)
	117 aload (4, 1)
	118 #10 (4, 1)
	119 aload (4, 1)
	120 #8 (4, 1)
	121 aload (4, 1)
	122 #14 (4, 1)
	123 dload (4, 1)
	124 #15 (4, 1)
	125 invokespecial (4, 1)
	126 org/apache/commons/math3/linear/DefaultIterativeLinearSolverEvent.<init>:(Ljava/lang/Object;ILorg/apache/commons/math3/linear/RealVector;Lorg/apache/commons/math3/linear/RealVector;Lorg/apache/commons/math3/linear/RealVector;D)V (4, 1)
	128 astore (4, 1)
	129 #18 (4, 1)
	130 aload (4, 1)
	131 #5 (4, 1)
	132 aload (4, 1)
	133 #18 (4, 1)
	134 invokevirtual (4, 1)
	135 org/apache/commons/math3/util/IterationManager.fireInitializationEvent:(Lorg/apache/commons/math3/util/IterationEvent;)V (4, 1)
	137 dload (5, 1)
	138 #15 (5, 1)
	139 dload (5, 1)
	140 #6 (5, 1)
	141 dcmpg (5, 1)
	142 ifgt (5, 1)
	143 13 (5, 1)
	145 aload (5, 1)
	146 #5 (5, 1)
	147 aload (5, 1)
	148 #18 (5, 1)
	149 invokevirtual (5, 1)
	150 org/apache/commons/math3/util/IterationManager.fireTerminationEvent:(Lorg/apache/commons/math3/util/IterationEvent;)V (5, 1)
	152 aload (5, 1)
	153 #9 (5, 1)
	154 areturn (5, 1)
	155 dconst_0 (4, 1)
	156 dstore (4, 1)
	157 #19 (4, 1)
	158 aload (5, 3)
	159 #5 (5, 3)
	160 invokevirtual (5, 3)
	161 org/apache/commons/math3/util/IterationManager.incrementIterationCount:()V (5, 3)
	163 new (5, 3)
	164 org/apache/commons/math3/linear/DefaultIterativeLinearSolverEvent (5, 3)
	166 dup (5, 3)
	167 aload_0 (5, 3)
	168 aload (5, 3)
	169 #5 (5, 3)
	170 invokevirtual (5, 3)
	171 org/apache/commons/math3/util/IterationManager.getIterations:()I (5, 3)
	173 aload (5, 3)
	174 #10 (5, 3)
	175 aload (5, 3)
	176 #8 (5, 3)
	177 aload (5, 3)
	178 #14 (5, 3)
	179 dload (5, 3)
	180 #15 (5, 3)
	181 invokespecial (5, 3)
	182 org/apache/commons/math3/linear/DefaultIterativeLinearSolverEvent.<init>:(Ljava/lang/Object;ILorg/apache/commons/math3/linear/RealVector;Lorg/apache/commons/math3/linear/RealVector;Lorg/apache/commons/math3/linear/RealVector;D)V (5, 3)
	184 astore (5, 3)
	185 #18 (5, 3)
	186 aload (5, 3)
	187 #5 (5, 3)
	188 aload (5, 3)
	189 #18 (5, 3)
	190 invokevirtual (5, 3)
	191 org/apache/commons/math3/util/IterationManager.fireIterationStartedEvent:(Lorg/apache/commons/math3/util/IterationEvent;)V (5, 3)
	193 aload_2 (6, 1)
	194 ifnull (6, 1)
	195 11 (6, 1)
	197 aload_2 (6, 1)
	198 aload (6, 1)
	199 #13 (6, 1)
	200 invokevirtual (6, 1)
	201 org/apache/commons/math3/linear/RealLinearOperator.operate:(Lorg/apache/commons/math3/linear/RealVector;)Lorg/apache/commons/math3/linear/RealVector; (6, 1)
	203 astore (6, 1)
	204 #17 (6, 1)
	205 aload (5, 3)
	206 #13 (5, 3)
	207 aload (5, 3)
	208 #17 (5, 3)
	209 invokevirtual (5, 3)
	210 org/apache/commons/math3/linear/RealVector.dotProduct:(Lorg/apache/commons/math3/linear/RealVector;)D (5, 3)
	212 dstore (5, 3)
	213 #21 (5, 3)
	214 aload_0 (6, 1)
	215 getfield (6, 1)
	216 org/apache/commons/math3/linear/ConjugateGradient.check:Z (6, 1)
	218 ifeq (6, 1)
	219 46 (6, 1)
	221 dload (6, 1)
	222 #21 (6, 1)
	223 dconst_0 (6, 1)
	224 dcmpg (6, 1)
	225 ifgt (6, 1)
	226 39 (6, 1)
	228 new (6, 1)
	229 org/apache/commons/math3/linear/NonPositiveDefiniteOperatorException (6, 1)
	231 dup (6, 1)
	232 invokespecial (6, 1)
	233 org/apache/commons/math3/linear/NonPositiveDefiniteOperatorException.<init>:()V (6, 1)
	235 astore (6, 1)
	236 #23 (6, 1)
	237 aload (6, 1)
	238 #23 (6, 1)
	239 invokevirtual (6, 1)
	240 org/apache/commons/math3/linear/NonPositiveDefiniteOperatorException.getContext:()Lorg/apache/commons/math3/exception/util/ExceptionContext; (6, 1)
	242 astore (6, 1)
	243 #24 (6, 1)
	244 aload (6, 1)
	245 #24 (6, 1)
	246 ldc (6, 1)
	247 operator (6, 1)
	248 aload_2 (6, 1)
	249 invokevirtual (6, 1)
	250 org/apache/commons/math3/exception/util/ExceptionContext.setValue:(Ljava/lang/String;Ljava/lang/Object;)V (6, 1)
	252 aload (6, 1)
	253 #24 (6, 1)
	254 ldc (6, 1)
	255 vector (6, 1)
	256 aload (6, 1)
	257 #13 (6, 1)
	258 invokevirtual (6, 1)
	259 org/apache/commons/math3/exception/util/ExceptionContext.setValue:(Ljava/lang/String;Ljava/lang/Object;)V (6, 1)
	261 aload (6, 1)
	262 #23 (6, 1)
	263 athrow (6, 1)
	264 aload (6, 1)
	265 #5 (6, 1)
	266 invokevirtual (6, 1)
	267 org/apache/commons/math3/util/IterationManager.getIterations:()I (6, 1)
	269 iconst_2 (6, 1)
	270 if_icmpne (6, 1)
	271 14 (6, 1)
	273 aload (6, 1)
	274 #11 (6, 1)
	275 iconst_0 (6, 1)
	276 aload (6, 1)
	277 #17 (6, 1)
	278 invokevirtual (6, 1)
	279 org/apache/commons/math3/linear/RealVector.setSubVector:(ILorg/apache/commons/math3/linear/RealVector;)V (6, 1)
	281 goto (6, 1)
	282 17 (6, 1)
	284 aload (7, 2)
	285 #11 (7, 2)
	286 dload (7, 2)
	287 #21 (7, 2)
	288 dload (7, 2)
	289 #19 (7, 2)
	290 ddiv (7, 2)
	291 dconst_1 (7, 2)
	292 aload (7, 2)
	293 #17 (7, 2)
	294 invokevirtual (7, 2)
	295 org/apache/commons/math3/linear/RealVector.combineToSelf:(DDLorg/apache/commons/math3/linear/RealVector;)Lorg/apache/commons/math3/linear/RealVector; (7, 2)
	297 pop (7, 2)
	298 aload_1 (5, 3)
	299 aload (5, 3)
	300 #11 (5, 3)
	301 invokevirtual (5, 3)
	302 org/apache/commons/math3/linear/RealLinearOperator.operate:(Lorg/apache/commons/math3/linear/RealVector;)Lorg/apache/commons/math3/linear/RealVector; (5, 3)
	304 astore (5, 3)
	305 #12 (5, 3)
	306 aload (5, 3)
	307 #11 (5, 3)
	308 aload (5, 3)
	309 #12 (5, 3)
	310 invokevirtual (5, 3)
	311 org/apache/commons/math3/linear/RealVector.dotProduct:(Lorg/apache/commons/math3/linear/RealVector;)D (5, 3)
	313 dstore (5, 3)
	314 #23 (5, 3)
	315 aload_0 (6, 1)
	316 getfield (6, 1)
	317 org/apache/commons/math3/linear/ConjugateGradient.check:Z (6, 1)
	319 ifeq (6, 1)
	320 46 (6, 1)
	322 dload (6, 1)
	323 #23 (6, 1)
	324 dconst_0 (6, 1)
	325 dcmpg (6, 1)
	326 ifgt (6, 1)
	327 39 (6, 1)
	329 new (6, 1)
	330 org/apache/commons/math3/linear/NonPositiveDefiniteOperatorException (6, 1)
	332 dup (6, 1)
	333 invokespecial (6, 1)
	334 org/apache/commons/math3/linear/NonPositiveDefiniteOperatorException.<init>:()V (6, 1)
	336 astore (6, 1)
	337 #25 (6, 1)
	338 aload (6, 1)
	339 #25 (6, 1)
	340 invokevirtual (6, 1)
	341 org/apache/commons/math3/linear/NonPositiveDefiniteOperatorException.getContext:()Lorg/apache/commons/math3/exception/util/ExceptionContext; (6, 1)
	343 astore (6, 1)
	344 #26 (6, 1)
	345 aload (6, 1)
	346 #26 (6, 1)
	347 ldc (6, 1)
	348 operator (6, 1)
	349 aload_1 (6, 1)
	350 invokevirtual (6, 1)
	351 org/apache/commons/math3/exception/util/ExceptionContext.setValue:(Ljava/lang/String;Ljava/lang/Object;)V (6, 1)
	353 aload (6, 1)
	354 #26 (6, 1)
	355 ldc (6, 1)
	356 vector (6, 1)
	357 aload (6, 1)
	358 #11 (6, 1)
	359 invokevirtual (6, 1)
	360 org/apache/commons/math3/exception/util/ExceptionContext.setValue:(Ljava/lang/String;Ljava/lang/Object;)V (6, 1)
	362 aload (6, 1)
	363 #25 (6, 1)
	364 athrow (6, 1)
	365 dload (5, 3)
	366 #21 (5, 3)
	367 dload (5, 3)
	368 #23 (5, 3)
	369 ddiv (5, 3)
	370 dstore (5, 3)
	371 #25 (5, 3)
	372 aload (5, 3)
	373 #9 (5, 3)
	374 dconst_1 (5, 3)
	375 dload (5, 3)
	376 #25 (5, 3)
	377 aload (5, 3)
	378 #11 (5, 3)
	379 invokevirtual (5, 3)
	380 org/apache/commons/math3/linear/RealVector.combineToSelf:(DDLorg/apache/commons/math3/linear/RealVector;)Lorg/apache/commons/math3/linear/RealVector; (5, 3)
	382 pop (5, 3)
	383 aload (5, 3)
	384 #13 (5, 3)
	385 dconst_1 (5, 3)
	386 dload (5, 3)
	387 #25 (5, 3)
	388 dneg (5, 3)
	389 aload (5, 3)
	390 #12 (5, 3)
	391 invokevirtual (5, 3)
	392 org/apache/commons/math3/linear/RealVector.combineToSelf:(DDLorg/apache/commons/math3/linear/RealVector;)Lorg/apache/commons/math3/linear/RealVector; (5, 3)
	394 pop (5, 3)
	395 dload (5, 3)
	396 #21 (5, 3)
	397 dstore (5, 3)
	398 #19 (5, 3)
	399 aload (5, 3)
	400 #13 (5, 3)
	401 invokevirtual (5, 3)
	402 org/apache/commons/math3/linear/RealVector.getNorm:()D (5, 3)
	404 dstore (5, 3)
	405 #15 (5, 3)
	406 new (5, 3)
	407 org/apache/commons/math3/linear/DefaultIterativeLinearSolverEvent (5, 3)
	409 dup (5, 3)
	410 aload_0 (5, 3)
	411 aload (5, 3)
	412 #5 (5, 3)
	413 invokevirtual (5, 3)
	414 org/apache/commons/math3/util/IterationManager.getIterations:()I (5, 3)
	416 aload (5, 3)
	417 #10 (5, 3)
	418 aload (5, 3)
	419 #8 (5, 3)
	420 aload (5, 3)
	421 #14 (5, 3)
	422 dload (5, 3)
	423 #15 (5, 3)
	424 invokespecial (5, 3)
	425 org/apache/commons/math3/linear/DefaultIterativeLinearSolverEvent.<init>:(Ljava/lang/Object;ILorg/apache/commons/math3/linear/RealVector;Lorg/apache/commons/math3/linear/RealVector;Lorg/apache/commons/math3/linear/RealVector;D)V (5, 3)
	427 astore (5, 3)
	428 #18 (5, 3)
	429 aload (6, 4)
	430 #5 (6, 4)
	431 aload (6, 4)
	432 #18 (6, 4)
	433 invokevirtual (6, 4)
	434 org/apache/commons/math3/util/IterationManager.fireIterationPerformedEvent:(Lorg/apache/commons/math3/util/IterationEvent;)V (6, 4)
	436 dload (7, 1)
	437 #15 (7, 1)
	438 dload (7, 1)
	439 #6 (7, 1)
	440 dcmpg (7, 1)
	441 ifgt (7, 1)
	442 13 (7, 1)
	444 aload (7, 1)
	445 #5 (7, 1)
	446 aload (7, 1)
	447 #18 (7, 1)
	448 invokevirtual (7, 1)
	449 org/apache/commons/math3/util/IterationManager.fireTerminationEvent:(Lorg/apache/commons/math3/util/IterationEvent;)V (7, 1)
	451 aload (7, 1)
	452 #9 (7, 1)
	453 areturn (7, 1)
	454 goto (0, 1)
	455 -296 (4, 1)

