Method: <init>
	0 aload_0 (0, 0)
	1 aload_1 (0, 0)
	2 iload_2 (0, 0)
	3 invokespecial (0, 0)
	4 org/apache/commons/math3/linear/IterativeLinearSolverEvent.<init>:(Ljava/lang/Object;I)V (0, 0)
	6 aload_0 (0, 0)
	7 aload_3 (0, 0)
	8 putfield (0, 0)
	9 org/apache/commons/math3/linear/DefaultIterativeLinearSolverEvent.x:Lorg/apache/commons/math3/linear/RealVector; (0, 0)
	11 aload_0 (0, 0)
	12 aload (0, 0)
	13 #4 (0, 0)
	14 putfield (0, 0)
	15 org/apache/commons/math3/linear/DefaultIterativeLinearSolverEvent.b:Lorg/apache/commons/math3/linear/RealVector; (0, 0)
	17 aload_0 (0, 0)
	18 aconst_null (0, 0)
	19 putfield (0, 0)
	20 org/apache/commons/math3/linear/DefaultIterativeLinearSolverEvent.r:Lorg/apache/commons/math3/linear/RealVector; (0, 0)
	22 aload_0 (0, 0)
	23 dload (0, 0)
	24 #5 (0, 0)
	25 putfield (0, 0)
	26 org/apache/commons/math3/linear/DefaultIterativeLinearSolverEvent.rnorm:D (0, 0)
	28 return (0, 0)

Method: getNormOfResidual
	0 aload_0 (0, 0)
	1 getfield (0, 0)
	2 org/apache/commons/math3/linear/DefaultIterativeLinearSolverEvent.rnorm:D (0, 0)
	4 dreturn (0, 0)

Method: getResidual
	0 aload_0 (1, 1)
	1 getfield (1, 1)
	2 org/apache/commons/math3/linear/DefaultIterativeLinearSolverEvent.r:Lorg/apache/commons/math3/linear/RealVector; (1, 1)
	4 ifnull (1, 1)
	5 8 (1, 1)
	7 aload_0 (1, 1)
	8 getfield (1, 1)
	9 org/apache/commons/math3/linear/DefaultIterativeLinearSolverEvent.r:Lorg/apache/commons/math3/linear/RealVector; (1, 1)
	11 areturn (1, 1)
	12 new (0, 0)
	13 org/apache/commons/math3/exception/MathUnsupportedOperationException (0, 0)
	15 dup (0, 0)
	16 invokespecial (0, 0)
	17 org/apache/commons/math3/exception/MathUnsupportedOperationException.<init>:()V (0, 0)
	19 athrow (0, 0)

Method: getRightHandSideVector
	0 aload_0 (0, 0)
	1 getfield (0, 0)
	2 org/apache/commons/math3/linear/DefaultIterativeLinearSolverEvent.b:Lorg/apache/commons/math3/linear/RealVector; (0, 0)
	4 areturn (0, 0)

Method: getSolution
	0 aload_0 (0, 0)
	1 getfield (0, 0)
	2 org/apache/commons/math3/linear/DefaultIterativeLinearSolverEvent.x:Lorg/apache/commons/math3/linear/RealVector; (0, 0)
	4 areturn (0, 0)

Method: providesResidual
	0 aload_0 (0, 0)
	1 getfield (0, 0)
	2 org/apache/commons/math3/linear/DefaultIterativeLinearSolverEvent.r:Lorg/apache/commons/math3/linear/RealVector; (0, 0)
	4 ifnull (0, 0)
	5 7 (0, 0)
	7 iconst_1 (0, 0)
	8 goto (0, 0)
	9 4 (0, 0)
	11 iconst_0 (0, 0)
	12 ireturn (0, 0)

