Method: <init>
	0 aload_0 (0, 0)
	1 invokespecial (0, 0)
	2 org/apache/commons/math3/linear/AbstractRealMatrix.<init>:()V (0, 0)
	4 aload_1 (0, 0)
	5 invokestatic (0, 0)
	6 org/apache/commons/math3/util/MathUtils.checkNotNull:(Ljava/lang/Object;)V (0, 0)
	8 aload_0 (0, 0)
	9 iload_2 (0, 0)
	10 ifeq (0, 0)
	11 13 (0, 0)
	13 aload_1 (0, 0)
	14 invokevirtual (0, 0)
	15 [D.clone:()Ljava/lang/Object; (0, 0)
	17 checkcast (0, 0)
	18 [D (0, 0)
	20 goto (0, 0)
	21 4 (0, 0)
	23 aload_1 (0, 0)
	24 putfield (0, 0)
	25 org/apache/commons/math3/linear/DiagonalMatrix.data:[D (0, 0)
	27 return (0, 0)

Method: createMatrix
	0 iload_1 (1, 1)
	1 iload_2 (1, 1)
	2 if_icmpeq (1, 1)
	3 13 (1, 1)
	5 new (1, 1)
	6 org/apache/commons/math3/exception/DimensionMismatchException (1, 1)
	8 dup (1, 1)
	9 iload_1 (1, 1)
	10 iload_2 (1, 1)
	11 invokespecial (1, 1)
	12 org/apache/commons/math3/exception/DimensionMismatchException.<init>:(II)V (1, 1)
	14 athrow (1, 1)
	15 new (0, 0)
	16 org/apache/commons/math3/linear/DiagonalMatrix (0, 0)
	18 dup (0, 0)
	19 iload_1 (0, 0)
	20 invokespecial (0, 0)
	21 org/apache/commons/math3/linear/DiagonalMatrix.<init>:(I)V (0, 0)
	23 areturn (0, 0)

Method: copy
	0 new (0, 0)
	1 org/apache/commons/math3/linear/DiagonalMatrix (0, 0)
	3 dup (0, 0)
	4 aload_0 (0, 0)
	5 getfield (0, 0)
	6 org/apache/commons/math3/linear/DiagonalMatrix.data:[D (0, 0)
	8 invokespecial (0, 0)
	9 org/apache/commons/math3/linear/DiagonalMatrix.<init>:([D)V (0, 0)
	11 areturn (0, 0)

Method: add
	0 aload_0 (0, 0)
	1 aload_1 (0, 0)
	2 invokestatic (0, 0)
	3 org/apache/commons/math3/linear/MatrixUtils.checkAdditionCompatible:(Lorg/apache/commons/math3/linear/AnyMatrix;Lorg/apache/commons/math3/linear/AnyMatrix;)V (0, 0)
	5 aload_0 (0, 0)
	6 invokevirtual (0, 0)
	7 org/apache/commons/math3/linear/DiagonalMatrix.getRowDimension:()I (0, 0)
	9 istore_2 (0, 0)
	10 iload_2 (0, 0)
	11 newarray (0, 0)
	12 7 (0, 0)
	13 astore_3 (0, 0)
	14 iconst_0 (1, 4)
	15 istore (1, 4)
	16 #4 (1, 4)
	17 iload (1, 4)
	18 #4 (1, 4)
	19 iload_2 (1, 4)
	20 if_icmpge (1, 4)
	21 28 (1, 4)
	23 aload_3 (1, 4)
	24 iload (1, 4)
	25 #4 (1, 4)
	26 aload_0 (1, 4)
	27 getfield (1, 4)
	28 org/apache/commons/math3/linear/DiagonalMatrix.data:[D (1, 4)
	30 iload (1, 4)
	31 #4 (1, 4)
	32 daload (1, 4)
	33 aload_1 (1, 4)
	34 getfield (1, 4)
	35 org/apache/commons/math3/linear/DiagonalMatrix.data:[D (1, 4)
	37 iload (1, 4)
	38 #4 (1, 4)
	39 daload (1, 4)
	40 dadd (1, 4)
	41 dastore (1, 4)
	42 iinc (1, 4)
	43 #4 (1, 4)
	44 -89 (1, 4)
	45 goto (1, 4)
	46 -28 (1, 4)
	48 new (0, 0)
	49 org/apache/commons/math3/linear/DiagonalMatrix (0, 0)
	51 dup (0, 0)
	52 aload_3 (0, 0)
	53 iconst_0 (0, 0)
	54 invokespecial (0, 0)
	55 org/apache/commons/math3/linear/DiagonalMatrix.<init>:([DZ)V (0, 0)
	57 areturn (0, 0)

Method: subtract
	0 aload_0 (0, 0)
	1 aload_1 (0, 0)
	2 invokestatic (0, 0)
	3 org/apache/commons/math3/linear/MatrixUtils.checkSubtractionCompatible:(Lorg/apache/commons/math3/linear/AnyMatrix;Lorg/apache/commons/math3/linear/AnyMatrix;)V (0, 0)
	5 aload_0 (0, 0)
	6 invokevirtual (0, 0)
	7 org/apache/commons/math3/linear/DiagonalMatrix.getRowDimension:()I (0, 0)
	9 istore_2 (0, 0)
	10 iload_2 (0, 0)
	11 newarray (0, 0)
	12 7 (0, 0)
	13 astore_3 (0, 0)
	14 iconst_0 (1, 4)
	15 istore (1, 4)
	16 #4 (1, 4)
	17 iload (1, 4)
	18 #4 (1, 4)
	19 iload_2 (1, 4)
	20 if_icmpge (1, 4)
	21 28 (1, 4)
	23 aload_3 (1, 4)
	24 iload (1, 4)
	25 #4 (1, 4)
	26 aload_0 (1, 4)
	27 getfield (1, 4)
	28 org/apache/commons/math3/linear/DiagonalMatrix.data:[D (1, 4)
	30 iload (1, 4)
	31 #4 (1, 4)
	32 daload (1, 4)
	33 aload_1 (1, 4)
	34 getfield (1, 4)
	35 org/apache/commons/math3/linear/DiagonalMatrix.data:[D (1, 4)
	37 iload (1, 4)
	38 #4 (1, 4)
	39 daload (1, 4)
	40 dsub (1, 4)
	41 dastore (1, 4)
	42 iinc (1, 4)
	43 #4 (1, 4)
	44 -89 (1, 4)
	45 goto (1, 4)
	46 -28 (1, 4)
	48 new (0, 0)
	49 org/apache/commons/math3/linear/DiagonalMatrix (0, 0)
	51 dup (0, 0)
	52 aload_3 (0, 0)
	53 iconst_0 (0, 0)
	54 invokespecial (0, 0)
	55 org/apache/commons/math3/linear/DiagonalMatrix.<init>:([DZ)V (0, 0)
	57 areturn (0, 0)

Method: multiply
	0 aload_1 (1, 1)
	1 instanceof (1, 1)
	2 org/apache/commons/math3/linear/DiagonalMatrix (1, 1)
	4 ifeq (1, 1)
	5 12 (1, 1)
	7 aload_0 (1, 1)
	8 aload_1 (1, 1)
	9 checkcast (1, 1)
	10 org/apache/commons/math3/linear/DiagonalMatrix (1, 1)
	12 invokevirtual (1, 1)
	13 org/apache/commons/math3/linear/DiagonalMatrix.multiply:(Lorg/apache/commons/math3/linear/DiagonalMatrix;)Lorg/apache/commons/math3/linear/DiagonalMatrix; (1, 1)
	15 areturn (1, 1)
	16 aload_0 (1, 2)
	17 aload_1 (1, 2)
	18 invokestatic (1, 2)
	19 org/apache/commons/math3/linear/MatrixUtils.checkMultiplicationCompatible:(Lorg/apache/commons/math3/linear/AnyMatrix;Lorg/apache/commons/math3/linear/AnyMatrix;)V (1, 2)
	21 aload_1 (1, 2)
	22 invokeinterface (1, 2)
	23 org/apache/commons/math3/linear/RealMatrix.checkSubtractionCompatible:(Lorg/apache/commons/math3/linear/AnyMatrix;Lorg/apache/commons/math3/linear/AnyMatrix;)V (1, 2)
	25 0 (1, 2)
	27 istore_2 (1, 2)
	28 aload_1 (1, 2)
	29 invokeinterface (1, 2)
	30 org/apache/commons/math3/linear/RealMatrix.getEntry:(II)D (1, 2)
	32 0 (1, 2)
	34 istore_3 (1, 2)
	35 iload_2 (1, 2)
	36 iload_3 (1, 2)
	37 multianewarray (1, 2)
	38 [[D (1, 2)
	40 58 (1, 2)
	41 astore (1, 2)
	42 #4 (1, 2)
	43 iconst_0 (2, 4)
	44 istore (2, 4)
	45 #5 (2, 4)
	46 iload (2, 4)
	47 #5 (2, 4)
	48 iload_2 (2, 4)
	49 if_icmpge (2, 4)
	50 50 (2, 4)
	52 iconst_0 (3, 4)
	53 istore (3, 4)
	54 #6 (3, 4)
	55 iload (3, 4)
	56 #6 (3, 4)
	57 iload_3 (3, 4)
	58 if_icmpge (3, 4)
	59 35 (3, 4)
	61 aload (3, 4)
	62 #4 (3, 4)
	63 iload (3, 4)
	64 #5 (3, 4)
	65 aaload (3, 4)
	66 iload (3, 4)
	67 #6 (3, 4)
	68 aload_0 (3, 4)
	69 getfield (3, 4)
	70 org/apache/commons/math3/linear/DiagonalMatrix.data:[D (3, 4)
	72 iload (3, 4)
	73 #5 (3, 4)
	74 daload (3, 4)
	75 aload_1 (3, 4)
	76 iload (3, 4)
	77 #5 (3, 4)
	78 iload (3, 4)
	79 #6 (3, 4)
	80 invokeinterface (3, 4)
	81 org/apache/commons/math3/linear/RealMatrix.org/apache/commons/math3/linear/Array2DRowRealMatrix (3, 4)
	83 0 (3, 4)
	85 dmul (3, 4)
	86 dastore (3, 4)
	87 iinc (3, 4)
	88 #6 (3, 4)
	89 -89 (3, 4)
	90 goto (3, 4)
	91 -35 (3, 4)
	93 iinc (3, 4)
	94 #5 (3, 4)
	95 -89 (3, 4)
	96 goto (3, 4)
	97 -50 (3, 4)
	99 new (2, 4)
	100 org/apache/commons/math3/linear/Array2DRowRealMatrix (2, 4)
	102 dup (2, 4)
	103 aload (2, 4)
	104 #4 (2, 4)
	105 iconst_0 (2, 4)
	106 invokespecial (2, 4)
	107 org/apache/commons/math3/linear/Array2DRowRealMatrix.<init>:([[DZ)V (2, 4)
	109 areturn (2, 4)

Method: getData
	0 aload_0 (0, 0)
	1 invokevirtual (0, 0)
	2 org/apache/commons/math3/linear/DiagonalMatrix.getRowDimension:()I (0, 0)
	4 istore_1 (0, 0)
	5 iload_1 (0, 0)
	6 iload_1 (0, 0)
	7 multianewarray (0, 0)
	8 [[D (0, 0)
	10 77 (0, 0)
	11 astore_2 (0, 0)
	12 iconst_0 (1, 4)
	13 istore_3 (1, 4)
	14 iload_3 (1, 4)
	15 iload_1 (1, 4)
	16 if_icmpge (1, 4)
	17 20 (1, 4)
	19 aload_2 (1, 4)
	20 iload_3 (1, 4)
	21 aaload (1, 4)
	22 iload_3 (1, 4)
	23 aload_0 (1, 4)
	24 getfield (1, 4)
	25 org/apache/commons/math3/linear/DiagonalMatrix.data:[D (1, 4)
	27 iload_3 (1, 4)
	28 daload (1, 4)
	29 dastore (1, 4)
	30 iinc (1, 4)
	31 #3 (1, 4)
	32 -89 (1, 4)
	33 goto (1, 4)
	34 -19 (1, 4)
	36 aload_2 (0, 0)
	37 areturn (0, 0)

Method: getDataRef
	0 aload_0 (0, 0)
	1 getfield (0, 0)
	2 org/apache/commons/math3/linear/DiagonalMatrix.data:[D (0, 0)
	4 areturn (0, 0)

Method: getEntry
	0 aload_0 (0, 0)
	1 iload_1 (0, 0)
	2 iload_2 (0, 0)
	3 invokestatic (0, 0)
	4 org/apache/commons/math3/linear/MatrixUtils.checkMatrixIndex:(Lorg/apache/commons/math3/linear/AnyMatrix;II)V (0, 0)
	6 iload_1 (0, 0)
	7 iload_2 (0, 0)
	8 if_icmpne (0, 0)
	9 12 (0, 0)
	11 aload_0 (0, 0)
	12 getfield (0, 0)
	13 org/apache/commons/math3/linear/DiagonalMatrix.data:[D (0, 0)
	15 iload_1 (0, 0)
	16 daload (0, 0)
	17 goto (0, 0)
	18 4 (0, 0)
	20 dconst_0 (0, 0)
	21 dreturn (0, 0)

Method: setEntry
	0 iload_1 (1, 1)
	1 iload_2 (1, 1)
	2 if_icmpne (1, 1)
	3 18 (1, 1)
	5 aload_0 (1, 1)
	6 iload_1 (1, 1)
	7 invokestatic (1, 1)
	8 org/apache/commons/math3/linear/MatrixUtils.checkRowIndex:(Lorg/apache/commons/math3/linear/AnyMatrix;I)V (1, 1)
	10 aload_0 (1, 1)
	11 getfield (1, 1)
	12 org/apache/commons/math3/linear/DiagonalMatrix.data:[D (1, 1)
	14 iload_1 (1, 1)
	15 dload_3 (1, 1)
	16 dastore (1, 1)
	17 goto (1, 1)
	18 8 (1, 1)
	20 aload_0 (1, 2)
	21 dload_3 (1, 2)
	22 invokespecial (1, 2)
	23 org/apache/commons/math3/linear/DiagonalMatrix.ensureZero:(D)V (1, 2)
	25 return (0, 0)

Method: addToEntry
	0 iload_1 (1, 1)
	1 iload_2 (1, 1)
	2 if_icmpne (1, 1)
	3 21 (1, 1)
	5 aload_0 (1, 1)
	6 iload_1 (1, 1)
	7 invokestatic (1, 1)
	8 org/apache/commons/math3/linear/MatrixUtils.checkRowIndex:(Lorg/apache/commons/math3/linear/AnyMatrix;I)V (1, 1)
	10 aload_0 (1, 1)
	11 getfield (1, 1)
	12 org/apache/commons/math3/linear/DiagonalMatrix.data:[D (1, 1)
	14 iload_1 (1, 1)
	15 dup2 (1, 1)
	16 daload (1, 1)
	17 dload_3 (1, 1)
	18 dadd (1, 1)
	19 dastore (1, 1)
	20 goto (1, 1)
	21 8 (1, 1)
	23 aload_0 (1, 2)
	24 dload_3 (1, 2)
	25 invokespecial (1, 2)
	26 org/apache/commons/math3/linear/DiagonalMatrix.ensureZero:(D)V (1, 2)
	28 return (0, 0)

Method: multiplyEntry
	0 iload_1 (1, 1)
	1 iload_2 (1, 1)
	2 if_icmpne (1, 1)
	3 18 (1, 1)
	5 aload_0 (1, 1)
	6 iload_1 (1, 1)
	7 invokestatic (1, 1)
	8 org/apache/commons/math3/linear/MatrixUtils.checkRowIndex:(Lorg/apache/commons/math3/linear/AnyMatrix;I)V (1, 1)
	10 aload_0 (1, 1)
	11 getfield (1, 1)
	12 org/apache/commons/math3/linear/DiagonalMatrix.data:[D (1, 1)
	14 iload_1 (1, 1)
	15 dup2 (1, 1)
	16 daload (1, 1)
	17 dload_3 (1, 1)
	18 dmul (1, 1)
	19 dastore (1, 1)
	20 return (0, 0)

Method: getRowDimension
	0 aload_0 (0, 0)
	1 getfield (0, 0)
	2 org/apache/commons/math3/linear/DiagonalMatrix.data:[D (0, 0)
	4 arraylength (0, 0)
	5 ireturn (0, 0)

Method: getColumnDimension
	0 aload_0 (0, 0)
	1 getfield (0, 0)
	2 org/apache/commons/math3/linear/DiagonalMatrix.data:[D (0, 0)
	4 arraylength (0, 0)
	5 ireturn (0, 0)

Method: operate
	0 aload_0 (0, 0)
	1 new (0, 0)
	2 org/apache/commons/math3/linear/DiagonalMatrix (0, 0)
	4 dup (0, 0)
	5 aload_1 (0, 0)
	6 iconst_0 (0, 0)
	7 invokespecial (0, 0)
	8 org/apache/commons/math3/linear/DiagonalMatrix.<init>:([DZ)V (0, 0)
	10 invokevirtual (0, 0)
	11 org/apache/commons/math3/linear/DiagonalMatrix.multiply:(Lorg/apache/commons/math3/linear/DiagonalMatrix;)Lorg/apache/commons/math3/linear/DiagonalMatrix; (0, 0)
	13 invokevirtual (0, 0)
	14 org/apache/commons/math3/linear/DiagonalMatrix.getDataRef:()[D (0, 0)
	16 areturn (0, 0)

Method: preMultiply
	0 aload_1 (1, 1)
	1 instanceof (1, 1)
	2 org/apache/commons/math3/linear/ArrayRealVector (1, 1)
	4 ifeq (1, 1)
	5 14 (1, 1)
	7 aload_1 (1, 1)
	8 checkcast (1, 1)
	9 org/apache/commons/math3/linear/ArrayRealVector (1, 1)
	11 invokevirtual (1, 1)
	12 org/apache/commons/math3/linear/ArrayRealVector.getDataRef:()[D (1, 1)
	14 astore_2 (1, 1)
	15 goto (1, 1)
	16 8 (1, 1)
	18 aload_1 (1, 2)
	19 invokevirtual (1, 2)
	20 org/apache/commons/math3/linear/RealVector.toArray:()[D (1, 2)
	22 astore_2 (1, 2)
	23 aload_0 (0, 0)
	24 aload_2 (0, 0)
	25 invokevirtual (0, 0)
	26 org/apache/commons/math3/linear/DiagonalMatrix.preMultiply:([D)[D (0, 0)
	28 invokestatic (0, 0)
	29 org/apache/commons/math3/linear/MatrixUtils.createRealVector:([D)Lorg/apache/commons/math3/linear/RealVector; (0, 0)
	31 areturn (0, 0)

Method: ensureZero
	0 dconst_0 (1, 1)
	1 dload_1 (1, 1)
	2 iconst_1 (1, 1)
	3 invokestatic (1, 1)
	4 org/apache/commons/math3/util/Precision.equals:(DDI)Z (1, 1)
	6 ifne (1, 1)
	7 23 (1, 1)
	9 new (1, 1)
	10 org/apache/commons/math3/exception/NumberIsTooLargeException (1, 1)
	12 dup (1, 1)
	13 dload_1 (1, 1)
	14 invokestatic (1, 1)
	15 org/apache/commons/math3/util/FastMath.abs:(D)D (1, 1)
	17 invokestatic (1, 1)
	18 java/lang/Double.valueOf:(D)Ljava/lang/Double; (1, 1)
	20 iconst_0 (1, 1)
	21 invokestatic (1, 1)
	22 java/lang/Integer.valueOf:(I)Ljava/lang/Integer; (1, 1)
	24 iconst_1 (1, 1)
	25 invokespecial (1, 1)
	26 org/apache/commons/math3/exception/NumberIsTooLargeException.<init>:(Ljava/lang/Number;Ljava/lang/Number;Z)V (1, 1)
	28 athrow (1, 1)
	29 return (0, 0)

Method: inverse
	0 aload_0 (1, 1)
	1 dload_1 (1, 1)
	2 invokevirtual (1, 1)
	3 org/apache/commons/math3/linear/DiagonalMatrix.isSingular:(D)Z (1, 1)
	5 ifeq (1, 1)
	6 11 (1, 1)
	8 new (1, 1)
	9 org/apache/commons/math3/linear/SingularMatrixException (1, 1)
	11 dup (1, 1)
	12 invokespecial (1, 1)
	13 org/apache/commons/math3/linear/SingularMatrixException.<init>:()V (1, 1)
	15 athrow (1, 1)
	16 aload_0 (0, 0)
	17 getfield (0, 0)
	18 org/apache/commons/math3/linear/DiagonalMatrix.data:[D (0, 0)
	20 arraylength (0, 0)
	21 newarray (0, 0)
	22 7 (0, 0)
	23 astore_3 (0, 0)
	24 iconst_0 (1, 4)
	25 istore (1, 4)
	26 #4 (1, 4)
	27 iload (1, 4)
	28 #4 (1, 4)
	29 aload_0 (1, 4)
	30 getfield (1, 4)
	31 org/apache/commons/math3/linear/DiagonalMatrix.data:[D (1, 4)
	33 arraylength (1, 4)
	34 if_icmpge (1, 4)
	35 22 (1, 4)
	37 aload_3 (1, 4)
	38 iload (1, 4)
	39 #4 (1, 4)
	40 dconst_1 (1, 4)
	41 aload_0 (1, 4)
	42 getfield (1, 4)
	43 org/apache/commons/math3/linear/DiagonalMatrix.data:[D (1, 4)
	45 iload (1, 4)
	46 #4 (1, 4)
	47 daload (1, 4)
	48 ddiv (1, 4)
	49 dastore (1, 4)
	50 iinc (1, 4)
	51 #4 (1, 4)
	52 -89 (1, 4)
	53 goto (1, 4)
	54 -26 (1, 4)
	56 new (0, 0)
	57 org/apache/commons/math3/linear/DiagonalMatrix (0, 0)
	59 dup (0, 0)
	60 aload_3 (0, 0)
	61 iconst_0 (0, 0)
	62 invokespecial (0, 0)
	63 org/apache/commons/math3/linear/DiagonalMatrix.<init>:([DZ)V (0, 0)
	65 areturn (0, 0)

Method: isSingular
	0 iconst_0 (1, 4)
	1 istore_3 (1, 4)
	2 iload_3 (1, 4)
	3 aload_0 (1, 4)
	4 getfield (1, 4)
	5 org/apache/commons/math3/linear/DiagonalMatrix.data:[D (1, 4)
	7 arraylength (1, 4)
	8 if_icmpge (1, 4)
	9 25 (1, 4)
	11 aload_0 (2, 1)
	12 getfield (2, 1)
	13 org/apache/commons/math3/linear/DiagonalMatrix.data:[D (2, 1)
	15 iload_3 (2, 1)
	16 daload (2, 1)
	17 dconst_0 (2, 1)
	18 dload_1 (2, 1)
	19 invokestatic (2, 1)
	20 org/apache/commons/math3/util/Precision.equals:(DDD)Z (2, 1)
	22 ifeq (2, 1)
	23 5 (2, 1)
	25 iconst_1 (2, 1)
	26 ireturn (2, 1)
	27 iinc (2, 1)
	28 #3 (2, 1)
	29 -89 (2, 1)
	30 goto (2, 1)
	31 -28 (2, 1)
	33 iconst_0 (1, 4)
	34 ireturn (1, 4)

