Method: <init>
	0 aload_0 (0, 0)
	1 invokespecial (0, 0)
	2 java/lang/Object.<init>:()V (0, 0)
	4 aload_0 (0, 0)
	5 aload_1 (0, 0)
	6 putfield (0, 0)
	7 org/apache/commons/math3/linear/EigenDecomposition$Solver.realEigenvalues:[D (0, 0)
	9 aload_0 (0, 0)
	10 aload_2 (0, 0)
	11 putfield (0, 0)
	12 org/apache/commons/math3/linear/EigenDecomposition$Solver.imagEigenvalues:[D (0, 0)
	14 aload_0 (0, 0)
	15 aload_3 (0, 0)
	16 putfield (0, 0)
	17 org/apache/commons/math3/linear/EigenDecomposition$Solver.eigenvectors:[Lorg/apache/commons/math3/linear/ArrayRealVector; (0, 0)
	19 return (0, 0)

Method: solve
	0 aload_0 (1, 1)
	1 invokevirtual (1, 1)
	2 org/apache/commons/math3/linear/EigenDecomposition$Solver.isNonSingular:()Z (1, 1)
	4 ifne (1, 1)
	5 11 (1, 1)
	7 new (1, 1)
	8 org/apache/commons/math3/linear/SingularMatrixException (1, 1)
	10 dup (1, 1)
	11 invokespecial (1, 1)
	12 org/apache/commons/math3/linear/SingularMatrixException.<init>:()V (1, 1)
	14 athrow (1, 1)
	15 aload_0 (0, 0)
	16 getfield (0, 0)
	17 org/apache/commons/math3/linear/EigenDecomposition$Solver.realEigenvalues:[D (0, 0)
	19 arraylength (0, 0)
	20 istore_2 (0, 0)
	21 aload_1 (1, 1)
	22 invokeinterface (1, 1)
	23 org/apache/commons/math3/linear/RealMatrix.getColumnDimension:()I (1, 1)
	25 0 (1, 1)
	27 iload_2 (1, 1)
	28 if_icmpeq (1, 1)
	29 18 (1, 1)
	31 new (1, 1)
	32 org/apache/commons/math3/exception/DimensionMismatchException (1, 1)
	34 dup (1, 1)
	35 aload_1 (1, 1)
	36 invokeinterface (1, 1)
	37 org/apache/commons/math3/linear/RealMatrix.getColumnDimension:()I (1, 1)
	39 0 (1, 1)
	41 iload_2 (1, 1)
	42 invokespecial (1, 1)
	43 org/apache/commons/math3/exception/DimensionMismatchException.<init>:(II)V (1, 1)
	45 athrow (1, 1)
	46 aload_1 (0, 0)
	47 invokeinterface (0, 0)
	48 org/apache/commons/math3/linear/RealMatrix.getEntry:(II)D (0, 0)
	50 0 (0, 0)
	52 istore_3 (0, 0)
	53 iload_2 (0, 0)
	54 iload_3 (0, 0)
	55 multianewarray (0, 0)
	56 [[D (0, 0)
	58 58 (0, 0)
	59 astore (0, 0)
	60 #4 (0, 0)
	61 iload_2 (0, 0)
	62 newarray (0, 0)
	63 7 (0, 0)
	64 astore (0, 0)
	65 #5 (0, 0)
	66 iconst_0 (1, 4)
	67 istore (1, 4)
	68 #6 (1, 4)
	69 iload (1, 4)
	70 #6 (1, 4)
	71 iload_3 (1, 4)
	72 if_icmpge (1, 4)
	73 161 (1, 4)
	75 iconst_0 (2, 4)
	76 istore (2, 4)
	77 #7 (2, 4)
	78 iload (2, 4)
	79 #7 (2, 4)
	80 iload_2 (2, 4)
	81 if_icmpge (2, 4)
	82 33 (2, 4)
	84 aload (2, 4)
	85 #5 (2, 4)
	86 iload (2, 4)
	87 #7 (2, 4)
	88 aload_1 (2, 4)
	89 iload (2, 4)
	90 #7 (2, 4)
	91 iload (2, 4)
	92 #6 (2, 4)
	93 invokeinterface (2, 4)
	94 org/apache/commons/math3/linear/RealMatrix.getEntry:(I)D (2, 4)
	96 0 (2, 4)
	98 dastore (2, 4)
	99 aload (2, 4)
	100 #4 (2, 4)
	101 iload (2, 4)
	102 #7 (2, 4)
	103 aaload (2, 4)
	104 iload (2, 4)
	105 #6 (2, 4)
	106 dconst_0 (2, 4)
	107 dastore (2, 4)
	108 iinc (2, 4)
	109 #7 (2, 4)
	110 -89 (2, 4)
	111 goto (2, 4)
	112 -33 (2, 4)
	114 iconst_0 (2, 4)
	115 istore (2, 4)
	116 #7 (2, 4)
	117 iload (2, 4)
	118 #7 (2, 4)
	119 iload_2 (2, 4)
	120 if_icmpge (2, 4)
	121 107 (2, 4)
	123 aload_0 (2, 4)
	124 getfield (2, 4)
	125 org/apache/commons/math3/linear/EigenDecomposition$Solver.eigenvectors:[Lorg/apache/commons/math3/linear/ArrayRealVector; (2, 4)
	127 iload (2, 4)
	128 #7 (2, 4)
	129 aaload (2, 4)
	130 astore (2, 4)
	131 #8 (2, 4)
	132 aload (2, 4)
	133 #8 (2, 4)
	134 invokevirtual (2, 4)
	135 org/apache/commons/math3/linear/ArrayRealVector.getDataRef:()[D (2, 4)
	137 astore (2, 4)
	138 #9 (2, 4)
	139 dconst_0 (2, 4)
	140 dstore (2, 4)
	141 #10 (2, 4)
	142 iconst_0 (3, 4)
	143 istore (3, 4)
	144 #12 (3, 4)
	145 iload (3, 4)
	146 #12 (3, 4)
	147 iload_2 (3, 4)
	148 if_icmpge (3, 4)
	149 27 (3, 4)
	151 dload (3, 4)
	152 #10 (3, 4)
	153 aload (3, 4)
	154 #8 (3, 4)
	155 iload (3, 4)
	156 #12 (3, 4)
	157 invokevirtual (3, 4)
	158 org/apache/commons/math3/linear/ArrayRealVector.getEntry:(I)D (3, 4)
	160 aload (3, 4)
	161 #5 (3, 4)
	162 iload (3, 4)
	163 #12 (3, 4)
	164 daload (3, 4)
	165 dmul (3, 4)
	166 dadd (3, 4)
	167 dstore (3, 4)
	168 #10 (3, 4)
	169 iinc (3, 4)
	170 #12 (3, 4)
	171 -89 (3, 4)
	172 goto (3, 4)
	173 -27 (3, 4)
	175 dload (2, 4)
	176 #10 (2, 4)
	177 aload_0 (2, 4)
	178 getfield (2, 4)
	179 org/apache/commons/math3/linear/EigenDecomposition$Solver.realEigenvalues:[D (2, 4)
	181 iload (2, 4)
	182 #7 (2, 4)
	183 daload (2, 4)
	184 ddiv (2, 4)
	185 dstore (2, 4)
	186 #10 (2, 4)
	187 iconst_0 (3, 4)
	188 istore (3, 4)
	189 #12 (3, 4)
	190 iload (3, 4)
	191 #12 (3, 4)
	192 iload_2 (3, 4)
	193 if_icmpge (3, 4)
	194 28 (3, 4)
	196 aload (3, 4)
	197 #4 (3, 4)
	198 iload (3, 4)
	199 #12 (3, 4)
	200 aaload (3, 4)
	201 iload (3, 4)
	202 #6 (3, 4)
	203 dup2 (3, 4)
	204 daload (3, 4)
	205 dload (3, 4)
	206 #10 (3, 4)
	207 aload (3, 4)
	208 #9 (3, 4)
	209 iload (3, 4)
	210 #12 (3, 4)
	211 daload (3, 4)
	212 dmul (3, 4)
	213 dadd (3, 4)
	214 dastore (3, 4)
	215 iinc (3, 4)
	216 #12 (3, 4)
	217 -89 (3, 4)
	218 goto (3, 4)
	219 -28 (3, 4)
	221 iinc (3, 4)
	222 #7 (3, 4)
	223 -89 (3, 4)
	224 goto (3, 4)
	225 -107 (3, 4)
	227 iinc (3, 4)
	228 #6 (3, 4)
	229 -89 (3, 4)
	230 goto (3, 4)
	231 -161 (3, 4)
	233 new (2, 4)
	234 org/apache/commons/math3/linear/Array2DRowRealMatrix (2, 4)
	236 dup (2, 4)
	237 aload (2, 4)
	238 #4 (2, 4)
	239 iconst_0 (2, 4)
	240 invokespecial (2, 4)
	241 org/apache/commons/math3/linear/Array2DRowRealMatrix.<init>:([[DZ)V (2, 4)
	243 areturn (2, 4)

Method: isNonSingular
	0 dconst_0 (0, 0)
	1 dstore_1 (0, 0)
	2 iconst_0 (1, 4)
	3 istore_3 (1, 4)
	4 iload_3 (1, 4)
	5 aload_0 (1, 4)
	6 getfield (1, 4)
	7 org/apache/commons/math3/linear/EigenDecomposition$Solver.realEigenvalues:[D (1, 4)
	9 arraylength (1, 4)
	10 if_icmpge (1, 4)
	11 19 (1, 4)
	13 dload_1 (1, 4)
	14 aload_0 (1, 4)
	15 iload_3 (1, 4)
	16 invokespecial (1, 4)
	17 org/apache/commons/math3/linear/EigenDecomposition$Solver.eigenvalueNorm:(I)D (1, 4)
	19 invokestatic (1, 4)
	20 org/apache/commons/math3/util/FastMath.max:(DD)D (1, 4)
	22 dstore_1 (1, 4)
	23 iinc (1, 4)
	24 #3 (1, 4)
	25 -89 (1, 4)
	26 goto (1, 4)
	27 -22 (1, 4)
	29 dload_1 (1, 1)
	30 dconst_0 (1, 1)
	31 dcmpl (1, 1)
	32 ifne (1, 1)
	33 5 (1, 1)
	35 iconst_0 (1, 1)
	36 ireturn (1, 1)
	37 iconst_0 (1, 4)
	38 istore_3 (1, 4)
	39 iload_3 (1, 4)
	40 aload_0 (1, 4)
	41 getfield (1, 4)
	42 org/apache/commons/math3/linear/EigenDecomposition$Solver.realEigenvalues:[D (1, 4)
	44 arraylength (1, 4)
	45 if_icmpge (1, 4)
	46 28 (1, 4)
	48 aload_0 (3, 1)
	49 iload_3 (3, 1)
	50 invokespecial (3, 1)
	51 org/apache/commons/math3/linear/EigenDecomposition$Solver.eigenvalueNorm:(I)D (3, 1)
	53 dload_1 (3, 1)
	54 ddiv (3, 1)
	55 dconst_0 (3, 1)
	56 ldc2_w (3, 1)
	57 1e-12 (3, 1)
	59 invokestatic (3, 1)
	60 org/apache/commons/math3/util/Precision.equals:(DDD)Z (3, 1)
	62 ifeq (3, 1)
	63 5 (3, 1)
	65 iconst_0 (3, 1)
	66 ireturn (3, 1)
	67 iinc (3, 1)
	68 #3 (3, 1)
	69 -89 (3, 1)
	70 goto (3, 1)
	71 -31 (3, 1)
	73 iconst_1 (2, 4)
	74 ireturn (1, 4)

Method: eigenvalueNorm
	0 aload_0 (0, 0)
	1 getfield (0, 0)
	2 org/apache/commons/math3/linear/EigenDecomposition$Solver.realEigenvalues:[D (0, 0)
	4 iload_1 (0, 0)
	5 daload (0, 0)
	6 dstore_2 (0, 0)
	7 aload_0 (0, 0)
	8 getfield (0, 0)
	9 org/apache/commons/math3/linear/EigenDecomposition$Solver.imagEigenvalues:[D (0, 0)
	11 iload_1 (0, 0)
	12 daload (0, 0)
	13 dstore (0, 0)
	14 #4 (0, 0)
	15 dload_2 (0, 0)
	16 dload_2 (0, 0)
	17 dmul (0, 0)
	18 dload (0, 0)
	19 #4 (0, 0)
	20 dload (0, 0)
	21 #4 (0, 0)
	22 dmul (0, 0)
	23 dadd (0, 0)
	24 invokestatic (0, 0)
	25 org/apache/commons/math3/util/FastMath.sqrt:(D)D (0, 0)
	27 dreturn (0, 0)

Method: getInverse
	0 aload_0 (1, 1)
	1 invokevirtual (1, 1)
	2 org/apache/commons/math3/linear/EigenDecomposition$Solver.isNonSingular:()Z (1, 1)
	4 ifne (1, 1)
	5 11 (1, 1)
	7 new (1, 1)
	8 org/apache/commons/math3/linear/SingularMatrixException (1, 1)
	10 dup (1, 1)
	11 invokespecial (1, 1)
	12 org/apache/commons/math3/linear/SingularMatrixException.<init>:()V (1, 1)
	14 athrow (1, 1)
	15 aload_0 (0, 0)
	16 getfield (0, 0)
	17 org/apache/commons/math3/linear/EigenDecomposition$Solver.realEigenvalues:[D (0, 0)
	19 arraylength (0, 0)
	20 istore_1 (0, 0)
	21 iload_1 (0, 0)
	22 iload_1 (0, 0)
	23 multianewarray (0, 0)
	24 [[D (0, 0)
	26 77 (0, 0)
	27 astore_2 (0, 0)
	28 iconst_0 (1, 4)
	29 istore_3 (1, 4)
	30 iload_3 (1, 4)
	31 iload_1 (1, 4)
	32 if_icmpge (1, 4)
	33 89 (1, 4)
	35 aload_2 (1, 4)
	36 iload_3 (1, 4)
	37 aaload (1, 4)
	38 astore (1, 4)
	39 #4 (1, 4)
	40 iconst_0 (2, 4)
	41 istore (2, 4)
	42 #5 (2, 4)
	43 iload (2, 4)
	44 #5 (2, 4)
	45 iload_1 (2, 4)
	46 if_icmpge (2, 4)
	47 69 (2, 4)
	49 dconst_0 (2, 4)
	50 dstore (2, 4)
	51 #6 (2, 4)
	52 iconst_0 (3, 4)
	53 istore (3, 4)
	54 #8 (3, 4)
	55 iload (3, 4)
	56 #8 (3, 4)
	57 iload_1 (3, 4)
	58 if_icmpge (3, 4)
	59 44 (3, 4)
	61 aload_0 (3, 4)
	62 getfield (3, 4)
	63 org/apache/commons/math3/linear/EigenDecomposition$Solver.eigenvectors:[Lorg/apache/commons/math3/linear/ArrayRealVector; (3, 4)
	65 iload (3, 4)
	66 #8 (3, 4)
	67 aaload (3, 4)
	68 invokevirtual (3, 4)
	69 org/apache/commons/math3/linear/ArrayRealVector.getDataRef:()[D (3, 4)
	71 astore (3, 4)
	72 #9 (3, 4)
	73 dload (3, 4)
	74 #6 (3, 4)
	75 aload (3, 4)
	76 #9 (3, 4)
	77 iload_3 (3, 4)
	78 daload (3, 4)
	79 aload (3, 4)
	80 #9 (3, 4)
	81 iload (3, 4)
	82 #5 (3, 4)
	83 daload (3, 4)
	84 dmul (3, 4)
	85 aload_0 (3, 4)
	86 getfield (3, 4)
	87 org/apache/commons/math3/linear/EigenDecomposition$Solver.realEigenvalues:[D (3, 4)
	89 iload (3, 4)
	90 #8 (3, 4)
	91 daload (3, 4)
	92 ddiv (3, 4)
	93 dadd (3, 4)
	94 dstore (3, 4)
	95 #6 (3, 4)
	96 iinc (3, 4)
	97 #8 (3, 4)
	98 -89 (3, 4)
	99 goto (3, 4)
	100 -44 (3, 4)
	102 aload (2, 4)
	103 #4 (2, 4)
	104 iload (2, 4)
	105 #5 (2, 4)
	106 dload (2, 4)
	107 #6 (2, 4)
	108 dastore (2, 4)
	109 iinc (2, 4)
	110 #5 (2, 4)
	111 -89 (2, 4)
	112 goto (2, 4)
	113 -69 (2, 4)
	115 iinc (2, 4)
	116 #3 (2, 4)
	117 -89 (2, 4)
	118 goto (2, 4)
	119 -88 (2, 4)
	121 aload_2 (1, 4)
	122 invokestatic (1, 4)
	123 org/apache/commons/math3/linear/MatrixUtils.createRealMatrix:([[D)Lorg/apache/commons/math3/linear/RealMatrix; (1, 4)
	125 areturn (1, 4)

