Method: <init>
	0 aload_0 (0, 0)
	1 aload_1 (0, 0)
	2 aload_2 (0, 0)
	3 invokespecial (0, 0)
	4 org/apache/commons/math3/linear/EigenDecomposition.<init>:([D[D)V (0, 0)
	6 return (0, 0)

Method: getV
	0 aload_0 (1, 1)
	1 getfield (1, 1)
	2 org/apache/commons/math3/linear/EigenDecomposition.cachedV:Lorg/apache/commons/math3/linear/RealMatrix; (1, 1)
	4 ifnonnull (1, 1)
	5 47 (1, 1)
	7 aload_0 (1, 1)
	8 getfield (1, 1)
	9 org/apache/commons/math3/linear/EigenDecomposition.eigenvectors:[Lorg/apache/commons/math3/linear/ArrayRealVector; (1, 1)
	11 arraylength (1, 1)
	12 istore_1 (1, 1)
	13 aload_0 (1, 1)
	14 iload_1 (1, 1)
	15 iload_1 (1, 1)
	16 invokestatic (1, 1)
	17 org/apache/commons/math3/linear/MatrixUtils.createRealMatrix:(II)Lorg/apache/commons/math3/linear/RealMatrix; (1, 1)
	19 putfield (1, 1)
	20 org/apache/commons/math3/linear/EigenDecomposition.cachedV:Lorg/apache/commons/math3/linear/RealMatrix; (1, 1)
	22 iconst_0 (2, 4)
	23 istore_2 (2, 4)
	24 iload_2 (2, 4)
	25 iload_1 (2, 4)
	26 if_icmpge (2, 4)
	27 25 (2, 4)
	29 aload_0 (2, 4)
	30 getfield (2, 4)
	31 org/apache/commons/math3/linear/EigenDecomposition.cachedV:Lorg/apache/commons/math3/linear/RealMatrix; (2, 4)
	33 iload_2 (2, 4)
	34 aload_0 (2, 4)
	35 getfield (2, 4)
	36 org/apache/commons/math3/linear/EigenDecomposition.eigenvectors:[Lorg/apache/commons/math3/linear/ArrayRealVector; (2, 4)
	38 iload_2 (2, 4)
	39 aaload (2, 4)
	40 invokeinterface (2, 4)
	41 org/apache/commons/math3/linear/RealMatrix.cachedD:Lorg/apache/commons/math3/linear/RealMatrix; (2, 4)
	43 0 (2, 4)
	45 iinc (2, 4)
	46 #2 (2, 4)
	47 -89 (2, 4)
	48 goto (2, 4)
	49 -24 (2, 4)
	51 aload_0 (0, 0)
	52 getfield (0, 0)
	53 org/apache/commons/math3/linear/EigenDecomposition.cachedV:Lorg/apache/commons/math3/linear/RealMatrix; (0, 0)
	55 areturn (0, 0)

Method: getD
	0 aload_0 (1, 1)
	1 getfield (1, 1)
	2 org/apache/commons/math3/linear/EigenDecomposition.cachedD:Lorg/apache/commons/math3/linear/RealMatrix; (1, 1)
	4 ifnonnull (1, 1)
	5 104 (1, 1)
	7 aload_0 (2, 4)
	8 aload_0 (2, 4)
	9 getfield (2, 4)
	10 org/apache/commons/math3/linear/EigenDecomposition.realEigenvalues:[D (2, 4)
	12 invokestatic (2, 4)
	13 org/apache/commons/math3/linear/MatrixUtils.createRealDiagonalMatrix:([D)Lorg/apache/commons/math3/linear/RealMatrix; (2, 4)
	15 putfield (2, 4)
	16 org/apache/commons/math3/linear/EigenDecomposition.cachedD:Lorg/apache/commons/math3/linear/RealMatrix; (2, 4)
	18 iconst_0 (3, 4)
	19 istore_1 (3, 4)
	20 iload_1 (3, 4)
	21 aload_0 (3, 4)
	22 getfield (3, 4)
	23 org/apache/commons/math3/linear/EigenDecomposition.imagEigenvalues:[D (3, 4)
	25 arraylength (3, 4)
	26 if_icmpge (3, 4)
	27 82 (3, 4)
	29 aload_0 (4, 1)
	30 getfield (4, 1)
	31 org/apache/commons/math3/linear/EigenDecomposition.imagEigenvalues:[D (4, 1)
	33 iload_1 (4, 1)
	34 daload (4, 1)
	35 dconst_0 (4, 1)
	36 ldc2_w (4, 1)
	37 1e-12 (4, 1)
	39 invokestatic (4, 1)
	40 org/apache/commons/math3/util/Precision.compareTo:(DDD)I (4, 1)
	42 ifle (4, 1)
	43 25 (4, 1)
	45 aload_0 (4, 1)
	46 getfield (4, 1)
	47 org/apache/commons/math3/linear/EigenDecomposition.cachedD:Lorg/apache/commons/math3/linear/RealMatrix; (4, 1)
	49 iload_1 (4, 1)
	50 iload_1 (4, 1)
	51 iconst_1 (4, 1)
	52 iadd (4, 1)
	53 aload_0 (4, 1)
	54 getfield (4, 1)
	55 org/apache/commons/math3/linear/EigenDecomposition.imagEigenvalues:[D (4, 1)
	57 iload_1 (4, 1)
	58 daload (4, 1)
	59 invokeinterface (4, 1)
	60 org/apache/commons/math3/linear/RealMatrix.cachedVt:Lorg/apache/commons/math3/linear/RealMatrix; (4, 1)
	62 0 (4, 1)
	64 goto (4, 1)
	65 38 (4, 1)
	67 aload_0 (5, 1)
	68 getfield (5, 1)
	69 org/apache/commons/math3/linear/EigenDecomposition.imagEigenvalues:[D (5, 1)
	71 iload_1 (5, 1)
	72 daload (5, 1)
	73 dconst_0 (5, 1)
	74 ldc2_w (5, 1)
	75 1e-12 (5, 1)
	77 invokestatic (5, 1)
	78 org/apache/commons/math3/util/Precision.compareTo:(DDD)I (5, 1)
	80 ifge (5, 1)
	81 22 (5, 1)
	83 aload_0 (5, 1)
	84 getfield (5, 1)
	85 org/apache/commons/math3/linear/EigenDecomposition.cachedD:Lorg/apache/commons/math3/linear/RealMatrix; (5, 1)
	87 iload_1 (5, 1)
	88 iload_1 (5, 1)
	89 iconst_1 (5, 1)
	90 isub (5, 1)
	91 aload_0 (5, 1)
	92 getfield (5, 1)
	93 org/apache/commons/math3/linear/EigenDecomposition.imagEigenvalues:[D (5, 1)
	95 iload_1 (5, 1)
	96 daload (5, 1)
	97 invokeinterface (5, 1)
	98 org/apache/commons/math3/linear/RealMatrix.cachedVt:Lorg/apache/commons/math3/linear/RealMatrix; (5, 1)
	100 0 (5, 1)
	102 iinc (5, 1)
	103 #1 (5, 1)
	104 -89 (5, 1)
	105 goto (5, 1)
	106 -85 (5, 1)
	108 aload_0 (2, 4)
	109 getfield (2, 4)
	110 org/apache/commons/math3/linear/EigenDecomposition.cachedD:Lorg/apache/commons/math3/linear/RealMatrix; (2, 4)
	112 areturn (1, 4)

Method: getVT
	0 aload_0 (1, 1)
	1 getfield (1, 1)
	2 org/apache/commons/math3/linear/EigenDecomposition.cachedVt:Lorg/apache/commons/math3/linear/RealMatrix; (1, 1)
	4 ifnonnull (1, 1)
	5 47 (1, 1)
	7 aload_0 (1, 1)
	8 getfield (1, 1)
	9 org/apache/commons/math3/linear/EigenDecomposition.eigenvectors:[Lorg/apache/commons/math3/linear/ArrayRealVector; (1, 1)
	11 arraylength (1, 1)
	12 istore_1 (1, 1)
	13 aload_0 (1, 1)
	14 iload_1 (1, 1)
	15 iload_1 (1, 1)
	16 invokestatic (1, 1)
	17 org/apache/commons/math3/linear/MatrixUtils.createRealMatrix:(II)Lorg/apache/commons/math3/linear/RealMatrix; (1, 1)
	19 putfield (1, 1)
	20 org/apache/commons/math3/linear/EigenDecomposition.cachedVt:Lorg/apache/commons/math3/linear/RealMatrix; (1, 1)
	22 iconst_0 (2, 4)
	23 istore_2 (2, 4)
	24 iload_2 (2, 4)
	25 iload_1 (2, 4)
	26 if_icmpge (2, 4)
	27 25 (2, 4)
	29 aload_0 (2, 4)
	30 getfield (2, 4)
	31 org/apache/commons/math3/linear/EigenDecomposition.cachedVt:Lorg/apache/commons/math3/linear/RealMatrix; (2, 4)
	33 iload_2 (2, 4)
	34 aload_0 (2, 4)
	35 getfield (2, 4)
	36 org/apache/commons/math3/linear/EigenDecomposition.eigenvectors:[Lorg/apache/commons/math3/linear/ArrayRealVector; (2, 4)
	38 iload_2 (2, 4)
	39 aaload (2, 4)
	40 invokeinterface (2, 4)
	41 org/apache/commons/math3/linear/RealMatrix.equals:(DDD)Z (2, 4)
	43 0 (2, 4)
	45 iinc (2, 4)
	46 #2 (2, 4)
	47 -89 (2, 4)
	48 goto (2, 4)
	49 -24 (2, 4)
	51 aload_0 (0, 0)
	52 getfield (0, 0)
	53 org/apache/commons/math3/linear/EigenDecomposition.cachedVt:Lorg/apache/commons/math3/linear/RealMatrix; (0, 0)
	55 areturn (0, 0)

Method: hasComplexEigenvalues
	0 iconst_0 (1, 4)
	1 istore_1 (1, 4)
	2 iload_1 (1, 4)
	3 aload_0 (1, 4)
	4 getfield (1, 4)
	5 org/apache/commons/math3/linear/EigenDecomposition.imagEigenvalues:[D (1, 4)
	7 arraylength (1, 4)
	8 if_icmpge (1, 4)
	9 27 (1, 4)
	11 aload_0 (2, 1)
	12 getfield (2, 1)
	13 org/apache/commons/math3/linear/EigenDecomposition.imagEigenvalues:[D (2, 1)
	15 iload_1 (2, 1)
	16 daload (2, 1)
	17 dconst_0 (2, 1)
	18 ldc2_w (2, 1)
	19 1e-12 (2, 1)
	21 invokestatic (2, 1)
	22 org/apache/commons/math3/util/Precision.equals:(DDD)Z (2, 1)
	24 ifne (2, 1)
	25 5 (2, 1)
	27 iconst_1 (2, 1)
	28 ireturn (2, 1)
	29 iinc (2, 1)
	30 #1 (2, 1)
	31 -89 (2, 1)
	32 goto (2, 1)
	33 -30 (2, 1)
	35 iconst_0 (1, 4)
	36 ireturn (1, 4)

Method: getRealEigenvalues
	0 aload_0 (0, 0)
	1 getfield (0, 0)
	2 org/apache/commons/math3/linear/EigenDecomposition.realEigenvalues:[D (0, 0)
	4 invokevirtual (0, 0)
	5 [D.clone:()Ljava/lang/Object; (0, 0)
	7 checkcast (0, 0)
	8 [D (0, 0)
	10 areturn (0, 0)

Method: getRealEigenvalue
	0 aload_0 (0, 0)
	1 getfield (0, 0)
	2 org/apache/commons/math3/linear/EigenDecomposition.realEigenvalues:[D (0, 0)
	4 iload_1 (0, 0)
	5 daload (0, 0)
	6 dreturn (0, 0)

Method: getImagEigenvalues
	0 aload_0 (0, 0)
	1 getfield (0, 0)
	2 org/apache/commons/math3/linear/EigenDecomposition.imagEigenvalues:[D (0, 0)
	4 invokevirtual (0, 0)
	5 [D.clone:()Ljava/lang/Object; (0, 0)
	7 checkcast (0, 0)
	8 [D (0, 0)
	10 areturn (0, 0)

Method: getImagEigenvalue
	0 aload_0 (0, 0)
	1 getfield (0, 0)
	2 org/apache/commons/math3/linear/EigenDecomposition.imagEigenvalues:[D (0, 0)
	4 iload_1 (0, 0)
	5 daload (0, 0)
	6 dreturn (0, 0)

Method: getEigenvector
	0 aload_0 (0, 0)
	1 getfield (0, 0)
	2 org/apache/commons/math3/linear/EigenDecomposition.eigenvectors:[Lorg/apache/commons/math3/linear/ArrayRealVector; (0, 0)
	4 iload_1 (0, 0)
	5 aaload (0, 0)
	6 invokevirtual (0, 0)
	7 org/apache/commons/math3/linear/ArrayRealVector.copy:()Lorg/apache/commons/math3/linear/ArrayRealVector; (0, 0)
	9 areturn (0, 0)

Method: getDeterminant
	0 dconst_1 (0, 0)
	1 dstore_1 (0, 0)
	2 aload_0 (1, 4)
	3 getfield (1, 4)
	4 org/apache/commons/math3/linear/EigenDecomposition.realEigenvalues:[D (1, 4)
	6 astore_3 (1, 4)
	7 aload_3 (1, 4)
	8 arraylength (1, 4)
	9 istore (1, 4)
	10 #4 (1, 4)
	11 iconst_0 (1, 4)
	12 istore (1, 4)
	13 #5 (1, 4)
	14 iload (1, 4)
	15 #5 (1, 4)
	16 iload (1, 4)
	17 #4 (1, 4)
	18 if_icmpge (1, 4)
	19 20 (1, 4)
	21 aload_3 (1, 4)
	22 iload (1, 4)
	23 #5 (1, 4)
	24 daload (1, 4)
	25 dstore (1, 4)
	26 #6 (1, 4)
	27 dload_1 (1, 4)
	28 dload (1, 4)
	29 #6 (1, 4)
	30 dmul (1, 4)
	31 dstore_1 (1, 4)
	32 iinc (1, 4)
	33 #5 (1, 4)
	34 -89 (1, 4)
	35 goto (1, 4)
	36 -21 (1, 4)
	38 dload_1 (0, 0)
	39 dreturn (0, 0)

Method: getSquareRoot
	0 aload_0 (1, 1)
	1 getfield (1, 1)
	2 org/apache/commons/math3/linear/EigenDecomposition.isSymmetric:Z (1, 1)
	4 ifne (1, 1)
	5 11 (1, 1)
	7 new (1, 1)
	8 org/apache/commons/math3/exception/MathUnsupportedOperationException (1, 1)
	10 dup (1, 1)
	11 invokespecial (1, 1)
	12 org/apache/commons/math3/exception/MathUnsupportedOperationException.<init>:()V (1, 1)
	14 athrow (1, 1)
	15 aload_0 (0, 0)
	16 getfield (0, 0)
	17 org/apache/commons/math3/linear/EigenDecomposition.realEigenvalues:[D (0, 0)
	19 arraylength (0, 0)
	20 newarray (0, 0)
	21 7 (0, 0)
	22 astore_1 (0, 0)
	23 iconst_0 (1, 4)
	24 istore_2 (1, 4)
	25 iload_2 (1, 4)
	26 aload_0 (1, 4)
	27 getfield (1, 4)
	28 org/apache/commons/math3/linear/EigenDecomposition.realEigenvalues:[D (1, 4)
	30 arraylength (1, 4)
	31 if_icmpge (1, 4)
	32 37 (1, 4)
	34 aload_0 (1, 4)
	35 getfield (1, 4)
	36 org/apache/commons/math3/linear/EigenDecomposition.realEigenvalues:[D (1, 4)
	38 iload_2 (1, 4)
	39 daload (1, 4)
	40 dstore_3 (1, 4)
	41 dload_3 (2, 1)
	42 dconst_0 (2, 1)
	43 dcmpg (2, 1)
	44 ifgt (2, 1)
	45 11 (2, 1)
	47 new (2, 1)
	48 org/apache/commons/math3/exception/MathUnsupportedOperationException (2, 1)
	50 dup (2, 1)
	51 invokespecial (2, 1)
	52 org/apache/commons/math3/exception/MathUnsupportedOperationException.<init>:()V (2, 1)
	54 athrow (2, 1)
	55 aload_1 (1, 4)
	56 iload_2 (1, 4)
	57 dload_3 (1, 4)
	58 invokestatic (1, 4)
	59 org/apache/commons/math3/util/FastMath.sqrt:(D)D (1, 4)
	61 dastore (1, 4)
	62 iinc (1, 4)
	63 #2 (1, 4)
	64 -89 (1, 4)
	65 goto (1, 4)
	66 -40 (1, 4)
	68 aload_1 (0, 0)
	69 invokestatic (0, 0)
	70 org/apache/commons/math3/linear/MatrixUtils.createRealDiagonalMatrix:([D)Lorg/apache/commons/math3/linear/RealMatrix; (0, 0)
	72 astore_2 (0, 0)
	73 aload_0 (0, 0)
	74 invokevirtual (0, 0)
	75 org/apache/commons/math3/linear/EigenDecomposition.getV:()Lorg/apache/commons/math3/linear/RealMatrix; (0, 0)
	77 astore_3 (0, 0)
	78 aload_0 (0, 0)
	79 invokevirtual (0, 0)
	80 org/apache/commons/math3/linear/EigenDecomposition.getVT:()Lorg/apache/commons/math3/linear/RealMatrix; (0, 0)
	82 astore (0, 0)
	83 #4 (0, 0)
	84 aload_3 (0, 0)
	85 aload_2 (0, 0)
	86 invokeinterface (0, 0)
	87 org/apache/commons/math3/linear/RealMatrix.hasComplexEigenvalues:()Z (0, 0)
	89 0 (0, 0)
	91 aload (0, 0)
	92 #4 (0, 0)
	93 invokeinterface (0, 0)
	94 org/apache/commons/math3/linear/RealMatrix.hasComplexEigenvalues:()Z (0, 0)
	96 0 (0, 0)
	98 areturn (0, 0)

Method: getSolver
	0 aload_0 (1, 1)
	1 invokevirtual (1, 1)
	2 org/apache/commons/math3/linear/EigenDecomposition.hasComplexEigenvalues:()Z (1, 1)
	4 ifeq (1, 1)
	5 11 (1, 1)
	7 new (1, 1)
	8 org/apache/commons/math3/exception/MathUnsupportedOperationException (1, 1)
	10 dup (1, 1)
	11 invokespecial (1, 1)
	12 org/apache/commons/math3/exception/MathUnsupportedOperationException.<init>:()V (1, 1)
	14 athrow (1, 1)
	15 new (0, 0)
	16 org/apache/commons/math3/linear/EigenDecomposition$Solver (0, 0)
	18 dup (0, 0)
	19 aload_0 (0, 0)
	20 getfield (0, 0)
	21 org/apache/commons/math3/linear/EigenDecomposition.realEigenvalues:[D (0, 0)
	23 aload_0 (0, 0)
	24 getfield (0, 0)
	25 org/apache/commons/math3/linear/EigenDecomposition.imagEigenvalues:[D (0, 0)
	27 aload_0 (0, 0)
	28 getfield (0, 0)
	29 org/apache/commons/math3/linear/EigenDecomposition.eigenvectors:[Lorg/apache/commons/math3/linear/ArrayRealVector; (0, 0)
	31 aconst_null (0, 0)
	32 invokespecial (0, 0)
	33 org/apache/commons/math3/linear/EigenDecomposition$Solver.<init>:([D[D[Lorg/apache/commons/math3/linear/ArrayRealVector;Lorg/apache/commons/math3/linear/EigenDecomposition$1;)V (0, 0)
	35 areturn (0, 0)

Method: transformToTridiagonal
	0 aload_0 (1, 4)
	1 new (1, 4)
	2 org/apache/commons/math3/linear/TriDiagonalTransformer (1, 4)
	4 dup (1, 4)
	5 aload_1 (1, 4)
	6 invokespecial (1, 4)
	7 org/apache/commons/math3/linear/TriDiagonalTransformer.<init>:(Lorg/apache/commons/math3/linear/RealMatrix;)V (1, 4)
	9 putfield (1, 4)
	10 org/apache/commons/math3/linear/EigenDecomposition.transformer:Lorg/apache/commons/math3/linear/TriDiagonalTransformer; (1, 4)
	12 aload_0 (2, 4)
	13 aload_0 (2, 4)
	14 getfield (2, 4)
	15 org/apache/commons/math3/linear/EigenDecomposition.transformer:Lorg/apache/commons/math3/linear/TriDiagonalTransformer; (2, 4)
	17 invokevirtual (2, 4)
	18 org/apache/commons/math3/linear/TriDiagonalTransformer.getMainDiagonalRef:()[D (2, 4)
	20 putfield (2, 4)
	21 org/apache/commons/math3/linear/EigenDecomposition.main:[D (2, 4)
	23 aload_0 (3, 4)
	24 aload_0 (3, 4)
	25 getfield (3, 4)
	26 org/apache/commons/math3/linear/EigenDecomposition.transformer:Lorg/apache/commons/math3/linear/TriDiagonalTransformer; (3, 4)
	28 invokevirtual (3, 4)
	29 org/apache/commons/math3/linear/TriDiagonalTransformer.getSecondaryDiagonalRef:()[D (3, 4)
	31 putfield (3, 4)
	32 org/apache/commons/math3/linear/EigenDecomposition.secondary:[D (3, 4)
	34 return (0, 4)

Method: findEigenVectors
	0 aload_1 (0, 0)
	1 invokevirtual (0, 0)
	2 [[D.clone:()Ljava/lang/Object; (0, 0)
	4 checkcast (0, 0)
	5 [[D (0, 0)
	7 astore_2 (0, 0)
	8 aload_0 (0, 0)
	9 getfield (0, 0)
	10 org/apache/commons/math3/linear/EigenDecomposition.main:[D (0, 0)
	12 arraylength (0, 0)
	13 istore_3 (0, 0)
	14 aload_0 (0, 0)
	15 iload_3 (0, 0)
	16 newarray (0, 0)
	17 7 (0, 0)
	18 putfield (0, 0)
	19 org/apache/commons/math3/linear/EigenDecomposition.realEigenvalues:[D (0, 0)
	21 aload_0 (0, 0)
	22 iload_3 (0, 0)
	23 newarray (0, 0)
	24 7 (0, 0)
	25 putfield (0, 0)
	26 org/apache/commons/math3/linear/EigenDecomposition.imagEigenvalues:[D (0, 0)
	28 iload_3 (0, 0)
	29 newarray (0, 0)
	30 7 (0, 0)
	31 astore (0, 0)
	32 #4 (0, 0)
	33 iconst_0 (1, 4)
	34 istore (1, 4)
	35 #5 (1, 4)
	36 iload (1, 4)
	37 #5 (1, 4)
	38 iload_3 (1, 4)
	39 iconst_1 (1, 4)
	40 isub (1, 4)
	41 if_icmpge (1, 4)
	42 35 (1, 4)
	44 aload_0 (1, 4)
	45 getfield (1, 4)
	46 org/apache/commons/math3/linear/EigenDecomposition.realEigenvalues:[D (1, 4)
	48 iload (1, 4)
	49 #5 (1, 4)
	50 aload_0 (1, 4)
	51 getfield (1, 4)
	52 org/apache/commons/math3/linear/EigenDecomposition.main:[D (1, 4)
	54 iload (1, 4)
	55 #5 (1, 4)
	56 daload (1, 4)
	57 dastore (1, 4)
	58 aload (1, 4)
	59 #4 (1, 4)
	60 iload (1, 4)
	61 #5 (1, 4)
	62 aload_0 (1, 4)
	63 getfield (1, 4)
	64 org/apache/commons/math3/linear/EigenDecomposition.secondary:[D (1, 4)
	66 iload (1, 4)
	67 #5 (1, 4)
	68 daload (1, 4)
	69 dastore (1, 4)
	70 iinc (1, 4)
	71 #5 (1, 4)
	72 -89 (1, 4)
	73 goto (1, 4)
	74 -37 (1, 4)
	76 aload_0 (0, 0)
	77 getfield (0, 0)
	78 org/apache/commons/math3/linear/EigenDecomposition.realEigenvalues:[D (0, 0)
	80 iload_3 (0, 0)
	81 iconst_1 (0, 0)
	82 isub (0, 0)
	83 aload_0 (0, 0)
	84 getfield (0, 0)
	85 org/apache/commons/math3/linear/EigenDecomposition.main:[D (0, 0)
	87 iload_3 (0, 0)
	88 iconst_1 (0, 0)
	89 isub (0, 0)
	90 daload (0, 0)
	91 dastore (0, 0)
	92 aload (0, 0)
	93 #4 (0, 0)
	94 iload_3 (0, 0)
	95 iconst_1 (0, 0)
	96 isub (0, 0)
	97 dconst_0 (0, 0)
	98 dastore (0, 0)
	99 dconst_0 (0, 0)
	100 dstore (0, 0)
	101 #5 (0, 0)
	102 iconst_0 (1, 4)
	103 istore (1, 4)
	104 #7 (1, 4)
	105 iload (1, 4)
	106 #7 (1, 4)
	107 iload_3 (1, 4)
	108 if_icmpge (1, 4)
	109 61 (1, 4)
	111 aload_0 (2, 1)
	112 getfield (2, 1)
	113 org/apache/commons/math3/linear/EigenDecomposition.realEigenvalues:[D (2, 1)
	115 iload (2, 1)
	116 #7 (2, 1)
	117 daload (2, 1)
	118 invokestatic (2, 1)
	119 org/apache/commons/math3/util/FastMath.abs:(D)D (2, 1)
	121 dload (2, 1)
	122 #5 (2, 1)
	123 dcmpl (2, 1)
	124 ifle (2, 1)
	125 15 (2, 1)
	127 aload_0 (2, 1)
	128 getfield (2, 1)
	129 org/apache/commons/math3/linear/EigenDecomposition.realEigenvalues:[D (2, 1)
	131 iload (2, 1)
	132 #7 (2, 1)
	133 daload (2, 1)
	134 invokestatic (2, 1)
	135 org/apache/commons/math3/util/FastMath.abs:(D)D (2, 1)
	137 dstore (2, 1)
	138 #5 (2, 1)
	139 aload (2, 1)
	140 #4 (2, 1)
	141 iload (2, 1)
	142 #7 (2, 1)
	143 daload (2, 1)
	144 invokestatic (2, 1)
	145 org/apache/commons/math3/util/FastMath.abs:(D)D (2, 1)
	147 dload (2, 1)
	148 #5 (2, 1)
	149 dcmpl (2, 1)
	150 ifle (2, 1)
	151 13 (2, 1)
	153 aload (2, 1)
	154 #4 (2, 1)
	155 iload (2, 1)
	156 #7 (2, 1)
	157 daload (2, 1)
	158 invokestatic (2, 1)
	159 org/apache/commons/math3/util/FastMath.abs:(D)D (2, 1)
	161 dstore (2, 1)
	162 #5 (2, 1)
	163 iinc (2, 1)
	164 #7 (2, 1)
	165 -89 (2, 1)
	166 goto (2, 1)
	167 -61 (2, 1)
	169 dload (3, 1)
	170 #5 (3, 1)
	171 dconst_0 (3, 1)
	172 dcmpl (3, 1)
	173 ifeq (3, 1)
	174 70 (3, 1)
	176 iconst_0 (4, 4)
	177 istore (4, 4)
	178 #7 (4, 4)
	179 iload (4, 4)
	180 #7 (4, 4)
	181 iload_3 (4, 4)
	182 if_icmpge (4, 4)
	183 61 (4, 4)
	185 aload_0 (5, 1)
	186 getfield (5, 1)
	187 org/apache/commons/math3/linear/EigenDecomposition.realEigenvalues:[D (5, 1)
	189 iload (5, 1)
	190 #7 (5, 1)
	191 daload (5, 1)
	192 invokestatic (5, 1)
	193 org/apache/commons/math3/util/FastMath.abs:(D)D (5, 1)
	195 getstatic (5, 1)
	196 org/apache/commons/math3/util/Precision.EPSILON:D (5, 1)
	198 dload (5, 1)
	199 #5 (5, 1)
	200 dmul (5, 1)
	201 dcmpg (5, 1)
	202 ifgt (5, 1)
	203 11 (5, 1)
	205 aload_0 (5, 1)
	206 getfield (5, 1)
	207 org/apache/commons/math3/linear/EigenDecomposition.realEigenvalues:[D (5, 1)
	209 iload (5, 1)
	210 #7 (5, 1)
	211 dconst_0 (5, 1)
	212 dastore (5, 1)
	213 aload (5, 1)
	214 #4 (5, 1)
	215 iload (5, 1)
	216 #7 (5, 1)
	217 daload (5, 1)
	218 invokestatic (5, 1)
	219 org/apache/commons/math3/util/FastMath.abs:(D)D (5, 1)
	221 getstatic (5, 1)
	222 org/apache/commons/math3/util/Precision.EPSILON:D (5, 1)
	224 dload (5, 1)
	225 #5 (5, 1)
	226 dmul (5, 1)
	227 dcmpg (5, 1)
	228 ifgt (5, 1)
	229 9 (5, 1)
	231 aload (5, 1)
	232 #4 (5, 1)
	233 iload (5, 1)
	234 #7 (5, 1)
	235 dconst_0 (5, 1)
	236 dastore (5, 1)
	237 iinc (5, 1)
	238 #7 (5, 1)
	239 -89 (5, 1)
	240 goto (5, 1)
	241 -61 (5, 1)
	243 iconst_0 (4, 4)
	244 istore (4, 4)
	245 #7 (4, 4)
	246 iload (4, 4)
	247 #7 (4, 4)
	248 iload_3 (4, 4)
	249 if_icmpge (4, 4)
	250 606 (4, 4)
	252 iconst_0 (4, 4)
	253 istore (4, 4)
	254 #8 (4, 4)
	255 iload (5, 4)
	256 #7 (5, 4)
	257 istore (5, 4)
	258 #9 (5, 4)
	259 iload (5, 4)
	260 #9 (5, 4)
	261 iload_3 (5, 4)
	262 iconst_1 (5, 4)
	263 isub (5, 4)
	264 if_icmpge (5, 4)
	265 54 (5, 4)
	267 aload_0 (5, 4)
	268 getfield (5, 4)
	269 org/apache/commons/math3/linear/EigenDecomposition.realEigenvalues:[D (5, 4)
	271 iload (5, 4)
	272 #9 (5, 4)
	273 daload (5, 4)
	274 invokestatic (5, 4)
	275 org/apache/commons/math3/util/FastMath.abs:(D)D (5, 4)
	277 aload_0 (5, 4)
	278 getfield (5, 4)
	279 org/apache/commons/math3/linear/EigenDecomposition.realEigenvalues:[D (5, 4)
	281 iload (5, 4)
	282 #9 (5, 4)
	283 iconst_1 (5, 4)
	284 iadd (5, 4)
	285 daload (5, 4)
	286 invokestatic (5, 4)
	287 org/apache/commons/math3/util/FastMath.abs:(D)D (5, 4)
	289 dadd (5, 4)
	290 dstore (5, 4)
	291 #10 (5, 4)
	292 aload (6, 1)
	293 #4 (6, 1)
	294 iload (6, 1)
	295 #9 (6, 1)
	296 daload (6, 1)
	297 invokestatic (6, 1)
	298 org/apache/commons/math3/util/FastMath.abs:(D)D (6, 1)
	300 dload (6, 1)
	301 #10 (6, 1)
	302 dadd (6, 1)
	303 dload (6, 1)
	304 #10 (6, 1)
	305 dcmpl (6, 1)
	306 ifne (6, 1)
	307 6 (6, 1)
	309 goto (6, 1)
	310 9 (6, 1)
	312 iinc (6, 1)
	313 #9 (6, 1)
	314 -89 (6, 1)
	315 goto (6, 1)
	316 -56 (6, 1)
	318 iload (6, 1)
	319 #9 (6, 1)
	320 iload (6, 1)
	321 #7 (6, 1)
	322 if_icmpeq (6, 1)
	323 520 (6, 1)
	325 iload (7, 1)
	326 #8 (7, 1)
	327 aload_0 (7, 1)
	328 getfield (7, 1)
	329 org/apache/commons/math3/linear/EigenDecomposition.maxIter:B (7, 1)
	331 if_icmpne (7, 1)
	332 25 (7, 1)
	334 new (7, 1)
	335 org/apache/commons/math3/exception/MaxCountExceededException (7, 1)
	337 dup (7, 1)
	338 getstatic (7, 1)
	339 org/apache/commons/math3/exception/util/LocalizedFormats.CONVERGENCE_FAILED:Lorg/apache/commons/math3/exception/util/LocalizedFormats; (7, 1)
	341 aload_0 (7, 1)
	342 getfield (7, 1)
	343 org/apache/commons/math3/linear/EigenDecomposition.maxIter:B (7, 1)
	345 invokestatic (7, 1)
	346 java/lang/Byte.valueOf:(B)Ljava/lang/Byte; (7, 1)
	348 iconst_0 (7, 1)
	349 anewarray (7, 1)
	350 java/lang/Object (7, 1)
	352 invokespecial (7, 1)
	353 org/apache/commons/math3/exception/MaxCountExceededException.<init>:(Lorg/apache/commons/math3/exception/util/Localizable;Ljava/lang/Number;[Ljava/lang/Object;)V (7, 1)
	355 athrow (7, 1)
	356 iinc (6, 1)
	357 #8 (6, 1)
	358 42 (6, 1)
	359 aload_0 (6, 1)
	360 getfield (6, 1)
	361 org/apache/commons/math3/linear/EigenDecomposition.realEigenvalues:[D (6, 1)
	363 iload (6, 1)
	364 #7 (6, 1)
	365 iconst_1 (6, 1)
	366 iadd (6, 1)
	367 daload (6, 1)
	368 aload_0 (6, 1)
	369 getfield (6, 1)
	370 org/apache/commons/math3/linear/EigenDecomposition.realEigenvalues:[D (6, 1)
	372 iload (6, 1)
	373 #7 (6, 1)
	374 daload (6, 1)
	375 dsub (6, 1)
	376 ldc2_w (6, 1)
	377 2.0 (6, 1)
	379 aload (6, 1)
	380 #4 (6, 1)
	381 iload (6, 1)
	382 #7 (6, 1)
	383 daload (6, 1)
	384 dmul (6, 1)
	385 ddiv (6, 1)
	386 dstore (6, 1)
	387 #10 (6, 1)
	388 dconst_1 (6, 1)
	389 dload (6, 1)
	390 #10 (6, 1)
	391 dload (6, 1)
	392 #10 (6, 1)
	393 dmul (6, 1)
	394 dadd (6, 1)
	395 invokestatic (6, 1)
	396 org/apache/commons/math3/util/FastMath.sqrt:(D)D (6, 1)
	398 dstore (6, 1)
	399 #12 (6, 1)
	400 dload (7, 1)
	401 #10 (7, 1)
	402 dconst_0 (7, 1)
	403 dcmpg (7, 1)
	404 ifge (7, 1)
	405 35 (7, 1)
	407 aload_0 (7, 1)
	408 getfield (7, 1)
	409 org/apache/commons/math3/linear/EigenDecomposition.realEigenvalues:[D (7, 1)
	411 iload (7, 1)
	412 #9 (7, 1)
	413 daload (7, 1)
	414 aload_0 (7, 1)
	415 getfield (7, 1)
	416 org/apache/commons/math3/linear/EigenDecomposition.realEigenvalues:[D (7, 1)
	418 iload (7, 1)
	419 #7 (7, 1)
	420 daload (7, 1)
	421 dsub (7, 1)
	422 aload (7, 1)
	423 #4 (7, 1)
	424 iload (7, 1)
	425 #7 (7, 1)
	426 daload (7, 1)
	427 dload (7, 1)
	428 #10 (7, 1)
	429 dload (7, 1)
	430 #12 (7, 1)
	431 dsub (7, 1)
	432 ddiv (7, 1)
	433 dadd (7, 1)
	434 dstore (7, 1)
	435 #10 (7, 1)
	436 goto (7, 1)
	437 32 (7, 1)
	439 aload_0 (8, 2)
	440 getfield (8, 2)
	441 org/apache/commons/math3/linear/EigenDecomposition.realEigenvalues:[D (8, 2)
	443 iload (8, 2)
	444 #9 (8, 2)
	445 daload (8, 2)
	446 aload_0 (8, 2)
	447 getfield (8, 2)
	448 org/apache/commons/math3/linear/EigenDecomposition.realEigenvalues:[D (8, 2)
	450 iload (8, 2)
	451 #7 (8, 2)
	452 daload (8, 2)
	453 dsub (8, 2)
	454 aload (8, 2)
	455 #4 (8, 2)
	456 iload (8, 2)
	457 #7 (8, 2)
	458 daload (8, 2)
	459 dload (8, 2)
	460 #10 (8, 2)
	461 dload (8, 2)
	462 #12 (8, 2)
	463 dadd (8, 2)
	464 ddiv (8, 2)
	465 dadd (8, 2)
	466 dstore (8, 2)
	467 #10 (8, 2)
	468 dconst_0 (6, 1)
	469 dstore (6, 1)
	470 #14 (6, 1)
	471 dconst_1 (6, 1)
	472 dstore (6, 1)
	473 #16 (6, 1)
	474 dconst_1 (6, 1)
	475 dstore (6, 1)
	476 #18 (6, 1)
	477 iload (7, 4)
	478 #9 (7, 4)
	479 iconst_1 (7, 4)
	480 isub (7, 4)
	481 istore (7, 4)
	482 #20 (7, 4)
	483 iload (7, 4)
	484 #20 (7, 4)
	485 iload (7, 4)
	486 #7 (7, 4)
	487 if_icmplt (7, 4)
	488 313 (7, 4)
	490 dload (7, 4)
	491 #16 (7, 4)
	492 aload (7, 4)
	493 #4 (7, 4)
	494 iload (7, 4)
	495 #20 (7, 4)
	496 daload (7, 4)
	497 dmul (7, 4)
	498 dstore (7, 4)
	499 #21 (7, 4)
	500 dload (7, 4)
	501 #18 (7, 4)
	502 aload (7, 4)
	503 #4 (7, 4)
	504 iload (7, 4)
	505 #20 (7, 4)
	506 daload (7, 4)
	507 dmul (7, 4)
	508 dstore (7, 4)
	509 #23 (7, 4)
	510 dload (8, 1)
	511 #21 (8, 1)
	512 invokestatic (8, 1)
	513 org/apache/commons/math3/util/FastMath.abs:(D)D (8, 1)
	515 dload (8, 1)
	516 #10 (8, 1)
	517 invokestatic (8, 1)
	518 org/apache/commons/math3/util/FastMath.abs:(D)D (8, 1)
	520 dcmpl (8, 1)
	521 iflt (8, 1)
	522 50 (8, 1)
	524 dload (8, 1)
	525 #10 (8, 1)
	526 dload (8, 1)
	527 #21 (8, 1)
	528 ddiv (8, 1)
	529 dstore (8, 1)
	530 #18 (8, 1)
	531 dload (8, 1)
	532 #18 (8, 1)
	533 dload (8, 1)
	534 #18 (8, 1)
	535 dmul (8, 1)
	536 dconst_1 (8, 1)
	537 dadd (8, 1)
	538 invokestatic (8, 1)
	539 org/apache/commons/math3/util/FastMath.sqrt:(D)D (8, 1)
	541 dstore (8, 1)
	542 #12 (8, 1)
	543 aload (8, 1)
	544 #4 (8, 1)
	545 iload (8, 1)
	546 #20 (8, 1)
	547 iconst_1 (8, 1)
	548 iadd (8, 1)
	549 dload (8, 1)
	550 #21 (8, 1)
	551 dload (8, 1)
	552 #12 (8, 1)
	553 dmul (8, 1)
	554 dastore (8, 1)
	555 dconst_1 (8, 1)
	556 dload (8, 1)
	557 #12 (8, 1)
	558 ddiv (8, 1)
	559 dstore (8, 1)
	560 #16 (8, 1)
	561 dload (8, 1)
	562 #18 (8, 1)
	563 dload (8, 1)
	564 #16 (8, 1)
	565 dmul (8, 1)
	566 dstore (8, 1)
	567 #18 (8, 1)
	568 goto (8, 1)
	569 47 (8, 1)
	571 dload (9, 2)
	572 #21 (9, 2)
	573 dload (9, 2)
	574 #10 (9, 2)
	575 ddiv (9, 2)
	576 dstore (9, 2)
	577 #16 (9, 2)
	578 dload (9, 2)
	579 #16 (9, 2)
	580 dload (9, 2)
	581 #16 (9, 2)
	582 dmul (9, 2)
	583 dconst_1 (9, 2)
	584 dadd (9, 2)
	585 invokestatic (9, 2)
	586 org/apache/commons/math3/util/FastMath.sqrt:(D)D (9, 2)
	588 dstore (9, 2)
	589 #12 (9, 2)
	590 aload (9, 2)
	591 #4 (9, 2)
	592 iload (9, 2)
	593 #20 (9, 2)
	594 iconst_1 (9, 2)
	595 iadd (9, 2)
	596 dload (9, 2)
	597 #10 (9, 2)
	598 dload (9, 2)
	599 #12 (9, 2)
	600 dmul (9, 2)
	601 dastore (9, 2)
	602 dconst_1 (9, 2)
	603 dload (9, 2)
	604 #12 (9, 2)
	605 ddiv (9, 2)
	606 dstore (9, 2)
	607 #18 (9, 2)
	608 dload (9, 2)
	609 #16 (9, 2)
	610 dload (9, 2)
	611 #18 (9, 2)
	612 dmul (9, 2)
	613 dstore (9, 2)
	614 #16 (9, 2)
	615 aload (8, 1)
	616 #4 (8, 1)
	617 iload (8, 1)
	618 #20 (8, 1)
	619 iconst_1 (8, 1)
	620 iadd (8, 1)
	621 daload (8, 1)
	622 dconst_0 (8, 1)
	623 dcmpl (8, 1)
	624 ifne (8, 1)
	625 26 (8, 1)
	627 aload_0 (8, 1)
	628 getfield (8, 1)
	629 org/apache/commons/math3/linear/EigenDecomposition.realEigenvalues:[D (8, 1)
	631 iload (8, 1)
	632 #20 (8, 1)
	633 iconst_1 (8, 1)
	634 iadd (8, 1)
	635 dup2 (8, 1)
	636 daload (8, 1)
	637 dload (8, 1)
	638 #14 (8, 1)
	639 dsub (8, 1)
	640 dastore (8, 1)
	641 aload (8, 1)
	642 #4 (8, 1)
	643 iload (8, 1)
	644 #9 (8, 1)
	645 dconst_0 (8, 1)
	646 dastore (8, 1)
	647 goto (8, 1)
	648 153 (8, 1)
	650 aload_0 (7, 4)
	651 getfield (7, 4)
	652 org/apache/commons/math3/linear/EigenDecomposition.realEigenvalues:[D (7, 4)
	654 iload (7, 4)
	655 #20 (7, 4)
	656 iconst_1 (7, 4)
	657 iadd (7, 4)
	658 daload (7, 4)
	659 dload (7, 4)
	660 #14 (7, 4)
	661 dsub (7, 4)
	662 dstore (7, 4)
	663 #10 (7, 4)
	664 aload_0 (7, 4)
	665 getfield (7, 4)
	666 org/apache/commons/math3/linear/EigenDecomposition.realEigenvalues:[D (7, 4)
	668 iload (7, 4)
	669 #20 (7, 4)
	670 daload (7, 4)
	671 dload (7, 4)
	672 #10 (7, 4)
	673 dsub (7, 4)
	674 dload (7, 4)
	675 #16 (7, 4)
	676 dmul (7, 4)
	677 ldc2_w (7, 4)
	678 2.0 (7, 4)
	680 dload (7, 4)
	681 #18 (7, 4)
	682 dmul (7, 4)
	683 dload (7, 4)
	684 #23 (7, 4)
	685 dmul (7, 4)
	686 dadd (7, 4)
	687 dstore (7, 4)
	688 #12 (7, 4)
	689 dload (7, 4)
	690 #16 (7, 4)
	691 dload (7, 4)
	692 #12 (7, 4)
	693 dmul (7, 4)
	694 dstore (7, 4)
	695 #14 (7, 4)
	696 aload_0 (7, 4)
	697 getfield (7, 4)
	698 org/apache/commons/math3/linear/EigenDecomposition.realEigenvalues:[D (7, 4)
	700 iload (7, 4)
	701 #20 (7, 4)
	702 iconst_1 (7, 4)
	703 iadd (7, 4)
	704 dload (7, 4)
	705 #10 (7, 4)
	706 dload (7, 4)
	707 #14 (7, 4)
	708 dadd (7, 4)
	709 dastore (7, 4)
	710 dload (7, 4)
	711 #18 (7, 4)
	712 dload (7, 4)
	713 #12 (7, 4)
	714 dmul (7, 4)
	715 dload (7, 4)
	716 #23 (7, 4)
	717 dsub (7, 4)
	718 dstore (7, 4)
	719 #10 (7, 4)
	720 iconst_0 (8, 4)
	721 istore (8, 4)
	722 #25 (8, 4)
	723 iload (8, 4)
	724 #25 (8, 4)
	725 iload_3 (8, 4)
	726 if_icmpge (8, 4)
	727 68 (8, 4)
	729 aload_2 (8, 4)
	730 iload (8, 4)
	731 #25 (8, 4)
	732 aaload (8, 4)
	733 iload (8, 4)
	734 #20 (8, 4)
	735 iconst_1 (8, 4)
	736 iadd (8, 4)
	737 daload (8, 4)
	738 dstore (8, 4)
	739 #21 (8, 4)
	740 aload_2 (8, 4)
	741 iload (8, 4)
	742 #25 (8, 4)
	743 aaload (8, 4)
	744 iload (8, 4)
	745 #20 (8, 4)
	746 iconst_1 (8, 4)
	747 iadd (8, 4)
	748 dload (8, 4)
	749 #16 (8, 4)
	750 aload_2 (8, 4)
	751 iload (8, 4)
	752 #25 (8, 4)
	753 aaload (8, 4)
	754 iload (8, 4)
	755 #20 (8, 4)
	756 daload (8, 4)
	757 dmul (8, 4)
	758 dload (8, 4)
	759 #18 (8, 4)
	760 dload (8, 4)
	761 #21 (8, 4)
	762 dmul (8, 4)
	763 dadd (8, 4)
	764 dastore (8, 4)
	765 aload_2 (8, 4)
	766 iload (8, 4)
	767 #25 (8, 4)
	768 aaload (8, 4)
	769 iload (8, 4)
	770 #20 (8, 4)
	771 dload (8, 4)
	772 #18 (8, 4)
	773 aload_2 (8, 4)
	774 iload (8, 4)
	775 #25 (8, 4)
	776 aaload (8, 4)
	777 iload (8, 4)
	778 #20 (8, 4)
	779 daload (8, 4)
	780 dmul (8, 4)
	781 dload (8, 4)
	782 #16 (8, 4)
	783 dload (8, 4)
	784 #21 (8, 4)
	785 dmul (8, 4)
	786 dsub (8, 4)
	787 dastore (8, 4)
	788 iinc (8, 4)
	789 #25 (8, 4)
	790 -89 (8, 4)
	791 goto (8, 4)
	792 -68 (8, 4)
	794 iinc (8, 4)
	795 #20 (8, 4)
	796 -89 (8, 4)
	797 goto (8, 4)
	798 -314 (8, 4)
	800 dload (8, 1)
	801 #12 (8, 1)
	802 dconst_0 (8, 1)
	803 dcmpl (8, 1)
	804 ifne (8, 1)
	805 13 (8, 1)
	807 iload (8, 1)
	808 #20 (8, 1)
	809 iload (8, 1)
	810 #7 (8, 1)
	811 if_icmplt (8, 1)
	812 6 (8, 1)
	814 goto (8, 1)
	815 28 (8, 1)
	817 aload_0 (7, 4)
	818 getfield (7, 4)
	819 org/apache/commons/math3/linear/EigenDecomposition.realEigenvalues:[D (7, 4)
	821 iload (7, 4)
	822 #7 (7, 4)
	823 dup2 (7, 4)
	824 daload (7, 4)
	825 dload (7, 4)
	826 #14 (7, 4)
	827 dsub (7, 4)
	828 dastore (7, 4)
	829 aload (7, 4)
	830 #4 (7, 4)
	831 iload (7, 4)
	832 #7 (7, 4)
	833 dload (7, 4)
	834 #10 (7, 4)
	835 dastore (7, 4)
	836 aload (7, 4)
	837 #4 (7, 4)
	838 iload (7, 4)
	839 #9 (7, 4)
	840 dconst_0 (7, 4)
	841 dastore (7, 4)
	842 iload (7, 3)
	843 #9 (7, 3)
	844 iload (7, 3)
	845 #7 (7, 3)
	846 if_icmpne (7, 3)
	847 -591 (7, 3)
	849 iinc (7, 3)
	850 #7 (7, 3)
	851 -89 (7, 3)
	852 goto (7, 3)
	853 -606 (7, 3)
	855 iconst_0 (5, 4)
	856 istore (5, 4)
	857 #7 (5, 4)
	858 iload (5, 4)
	859 #7 (5, 4)
	860 iload_3 (5, 4)
	861 if_icmpge (5, 4)
	862 143 (5, 4)
	864 iload (5, 4)
	865 #7 (5, 4)
	866 istore (5, 4)
	867 #8 (5, 4)
	868 aload_0 (5, 4)
	869 getfield (5, 4)
	870 org/apache/commons/math3/linear/EigenDecomposition.realEigenvalues:[D (5, 4)
	872 iload (5, 4)
	873 #7 (5, 4)
	874 daload (5, 4)
	875 dstore (5, 4)
	876 #9 (5, 4)
	877 iload (6, 4)
	878 #7 (6, 4)
	879 iconst_1 (6, 4)
	880 iadd (6, 4)
	881 istore (6, 4)
	882 #11 (6, 4)
	883 iload (6, 4)
	884 #11 (6, 4)
	885 iload_3 (6, 4)
	886 if_icmpge (6, 4)
	887 35 (6, 4)
	889 aload_0 (7, 1)
	890 getfield (7, 1)
	891 org/apache/commons/math3/linear/EigenDecomposition.realEigenvalues:[D (7, 1)
	893 iload (7, 1)
	894 #11 (7, 1)
	895 daload (7, 1)
	896 dload (7, 1)
	897 #9 (7, 1)
	898 dcmpl (7, 1)
	899 ifle (7, 1)
	900 16 (7, 1)
	902 iload (7, 1)
	903 #11 (7, 1)
	904 istore (7, 1)
	905 #8 (7, 1)
	906 aload_0 (7, 1)
	907 getfield (7, 1)
	908 org/apache/commons/math3/linear/EigenDecomposition.realEigenvalues:[D (7, 1)
	910 iload (7, 1)
	911 #11 (7, 1)
	912 daload (7, 1)
	913 dstore (7, 1)
	914 #9 (7, 1)
	915 iinc (7, 1)
	916 #11 (7, 1)
	917 -89 (7, 1)
	918 goto (7, 1)
	919 -35 (7, 1)
	921 iload (7, 1)
	922 #8 (7, 1)
	923 iload (7, 1)
	924 #7 (7, 1)
	925 if_icmpeq (7, 1)
	926 73 (7, 1)
	928 aload_0 (7, 1)
	929 getfield (7, 1)
	930 org/apache/commons/math3/linear/EigenDecomposition.realEigenvalues:[D (7, 1)
	932 iload (7, 1)
	933 #8 (7, 1)
	934 aload_0 (7, 1)
	935 getfield (7, 1)
	936 org/apache/commons/math3/linear/EigenDecomposition.realEigenvalues:[D (7, 1)
	938 iload (7, 1)
	939 #7 (7, 1)
	940 daload (7, 1)
	941 dastore (7, 1)
	942 aload_0 (7, 1)
	943 getfield (7, 1)
	944 org/apache/commons/math3/linear/EigenDecomposition.realEigenvalues:[D (7, 1)
	946 iload (7, 1)
	947 #7 (7, 1)
	948 dload (7, 1)
	949 #9 (7, 1)
	950 dastore (7, 1)
	951 iconst_0 (8, 4)
	952 istore (8, 4)
	953 #11 (8, 4)
	954 iload (8, 4)
	955 #11 (8, 4)
	956 iload_3 (8, 4)
	957 if_icmpge (8, 4)
	958 41 (8, 4)
	960 aload_2 (8, 4)
	961 iload (8, 4)
	962 #11 (8, 4)
	963 aaload (8, 4)
	964 iload (8, 4)
	965 #7 (8, 4)
	966 daload (8, 4)
	967 dstore (8, 4)
	968 #9 (8, 4)
	969 aload_2 (8, 4)
	970 iload (8, 4)
	971 #11 (8, 4)
	972 aaload (8, 4)
	973 iload (8, 4)
	974 #7 (8, 4)
	975 aload_2 (8, 4)
	976 iload (8, 4)
	977 #11 (8, 4)
	978 aaload (8, 4)
	979 iload (8, 4)
	980 #8 (8, 4)
	981 daload (8, 4)
	982 dastore (8, 4)
	983 aload_2 (8, 4)
	984 iload (8, 4)
	985 #11 (8, 4)
	986 aaload (8, 4)
	987 iload (8, 4)
	988 #8 (8, 4)
	989 dload (8, 4)
	990 #9 (8, 4)
	991 dastore (8, 4)
	992 iinc (8, 4)
	993 #11 (8, 4)
	994 -89 (8, 4)
	995 goto (8, 4)
	996 -41 (8, 4)
	998 iinc (8, 4)
	999 #7 (8, 4)
	1000 -89 (8, 4)
	1001 goto (8, 4)
	1002 -143 (8, 4)
	1004 dconst_0 (7, 1)
	1005 dstore (7, 1)
	1006 #5 (7, 1)
	1007 iconst_0 (8, 4)
	1008 istore (8, 4)
	1009 #7 (8, 4)
	1010 iload (8, 4)
	1011 #7 (8, 4)
	1012 iload_3 (8, 4)
	1013 if_icmpge (8, 4)
	1014 37 (8, 4)
	1016 aload_0 (9, 1)
	1017 getfield (9, 1)
	1018 org/apache/commons/math3/linear/EigenDecomposition.realEigenvalues:[D (9, 1)
	1020 iload (9, 1)
	1021 #7 (9, 1)
	1022 daload (9, 1)
	1023 invokestatic (9, 1)
	1024 org/apache/commons/math3/util/FastMath.abs:(D)D (9, 1)
	1026 dload (9, 1)
	1027 #5 (9, 1)
	1028 dcmpl (9, 1)
	1029 ifle (9, 1)
	1030 15 (9, 1)
	1032 aload_0 (9, 1)
	1033 getfield (9, 1)
	1034 org/apache/commons/math3/linear/EigenDecomposition.realEigenvalues:[D (9, 1)
	1036 iload (9, 1)
	1037 #7 (9, 1)
	1038 daload (9, 1)
	1039 invokestatic (9, 1)
	1040 org/apache/commons/math3/util/FastMath.abs:(D)D (9, 1)
	1042 dstore (9, 1)
	1043 #5 (9, 1)
	1044 iinc (9, 1)
	1045 #7 (9, 1)
	1046 -89 (9, 1)
	1047 goto (9, 1)
	1048 -37 (9, 1)
	1050 dload (10, 1)
	1051 #5 (10, 1)
	1052 dconst_0 (10, 1)
	1053 dcmpl (10, 1)
	1054 ifeq (10, 1)
	1055 46 (10, 1)
	1057 iconst_0 (11, 4)
	1058 istore (11, 4)
	1059 #7 (11, 4)
	1060 iload (11, 4)
	1061 #7 (11, 4)
	1062 iload_3 (11, 4)
	1063 if_icmpge (11, 4)
	1064 37 (11, 4)
	1066 aload_0 (12, 1)
	1067 getfield (12, 1)
	1068 org/apache/commons/math3/linear/EigenDecomposition.realEigenvalues:[D (12, 1)
	1070 iload (12, 1)
	1071 #7 (12, 1)
	1072 daload (12, 1)
	1073 invokestatic (12, 1)
	1074 org/apache/commons/math3/util/FastMath.abs:(D)D (12, 1)
	1076 getstatic (12, 1)
	1077 org/apache/commons/math3/util/Precision.EPSILON:D (12, 1)
	1079 dload (12, 1)
	1080 #5 (12, 1)
	1081 dmul (12, 1)
	1082 dcmpg (12, 1)
	1083 ifge (12, 1)
	1084 11 (12, 1)
	1086 aload_0 (12, 1)
	1087 getfield (12, 1)
	1088 org/apache/commons/math3/linear/EigenDecomposition.realEigenvalues:[D (12, 1)
	1090 iload (12, 1)
	1091 #7 (12, 1)
	1092 dconst_0 (12, 1)
	1093 dastore (12, 1)
	1094 iinc (12, 1)
	1095 #7 (12, 1)
	1096 -89 (12, 1)
	1097 goto (12, 1)
	1098 -37 (12, 1)
	1100 aload_0 (10, 1)
	1101 iload_3 (10, 1)
	1102 anewarray (10, 1)
	1103 org/apache/commons/math3/linear/ArrayRealVector (10, 1)
	1105 putfield (10, 1)
	1106 org/apache/commons/math3/linear/EigenDecomposition.eigenvectors:[Lorg/apache/commons/math3/linear/ArrayRealVector; (10, 1)
	1108 iload_3 (10, 1)
	1109 newarray (10, 1)
	1110 7 (10, 1)
	1111 astore (10, 1)
	1112 #7 (10, 1)
	1113 iconst_0 (11, 4)
	1114 istore (11, 4)
	1115 #8 (11, 4)
	1116 iload (11, 4)
	1117 #8 (11, 4)
	1118 iload_3 (11, 4)
	1119 if_icmpge (11, 4)
	1120 52 (11, 4)
	1122 iconst_0 (12, 4)
	1123 istore (12, 4)
	1124 #9 (12, 4)
	1125 iload (12, 4)
	1126 #9 (12, 4)
	1127 iload_3 (12, 4)
	1128 if_icmpge (12, 4)
	1129 21 (12, 4)
	1131 aload (12, 4)
	1132 #7 (12, 4)
	1133 iload (12, 4)
	1134 #9 (12, 4)
	1135 aload_2 (12, 4)
	1136 iload (12, 4)
	1137 #9 (12, 4)
	1138 aaload (12, 4)
	1139 iload (12, 4)
	1140 #8 (12, 4)
	1141 daload (12, 4)
	1142 dastore (12, 4)
	1143 iinc (12, 4)
	1144 #9 (12, 4)
	1145 -89 (12, 4)
	1146 goto (12, 4)
	1147 -21 (12, 4)
	1149 aload_0 (11, 4)
	1150 getfield (11, 4)
	1151 org/apache/commons/math3/linear/EigenDecomposition.eigenvectors:[Lorg/apache/commons/math3/linear/ArrayRealVector; (11, 4)
	1153 iload (11, 4)
	1154 #8 (11, 4)
	1155 new (11, 4)
	1156 org/apache/commons/math3/linear/ArrayRealVector (11, 4)
	1158 dup (11, 4)
	1159 aload (11, 4)
	1160 #7 (11, 4)
	1161 invokespecial (11, 4)
	1162 org/apache/commons/math3/linear/ArrayRealVector.<init>:([D)V (11, 4)
	1164 aastore (11, 4)
	1165 iinc (11, 4)
	1166 #8 (11, 4)
	1167 -89 (11, 4)
	1168 goto (11, 4)
	1169 -52 (11, 4)
	1171 return (8, 1)

Method: transformToSchur
	0 new (1, 4)
	1 org/apache/commons/math3/linear/SchurTransformer (1, 4)
	3 dup (1, 4)
	4 aload_1 (1, 4)
	5 invokespecial (1, 4)
	6 org/apache/commons/math3/linear/SchurTransformer.<init>:(Lorg/apache/commons/math3/linear/RealMatrix;)V (1, 4)
	8 astore_2 (1, 4)
	9 aload_2 (2, 4)
	10 invokevirtual (2, 4)
	11 org/apache/commons/math3/linear/SchurTransformer.getT:()Lorg/apache/commons/math3/linear/RealMatrix; (2, 4)
	13 invokeinterface (2, 4)
	14 org/apache/commons/math3/linear/RealMatrix.findEigenVectors:([[D)V (2, 4)
	16 0 (2, 4)
	18 astore_3 (2, 4)
	19 aload_0 (2, 4)
	20 aload_3 (2, 4)
	21 arraylength (2, 4)
	22 newarray (2, 4)
	23 7 (2, 4)
	24 putfield (2, 4)
	25 org/apache/commons/math3/linear/EigenDecomposition.realEigenvalues:[D (2, 4)
	27 aload_0 (2, 4)
	28 aload_3 (2, 4)
	29 arraylength (2, 4)
	30 newarray (2, 4)
	31 7 (2, 4)
	32 putfield (2, 4)
	33 org/apache/commons/math3/linear/EigenDecomposition.imagEigenvalues:[D (2, 4)
	35 iconst_0 (3, 4)
	36 istore (3, 4)
	37 #4 (3, 4)
	38 iload (3, 4)
	39 #4 (3, 4)
	40 aload_0 (3, 4)
	41 getfield (3, 4)
	42 org/apache/commons/math3/linear/EigenDecomposition.realEigenvalues:[D (3, 4)
	44 arraylength (3, 4)
	45 if_icmpge (3, 4)
	46 169 (3, 4)
	48 iload (4, 1)
	49 #4 (4, 1)
	50 aload_0 (4, 1)
	51 getfield (4, 1)
	52 org/apache/commons/math3/linear/EigenDecomposition.realEigenvalues:[D (4, 1)
	54 arraylength (4, 1)
	55 iconst_1 (4, 1)
	56 isub (4, 1)
	57 if_icmpeq (4, 1)
	58 22 (4, 1)
	60 aload_3 (4, 1)
	61 iload (4, 1)
	62 #4 (4, 1)
	63 iconst_1 (4, 1)
	64 iadd (4, 1)
	65 aaload (4, 1)
	66 iload (4, 1)
	67 #4 (4, 1)
	68 daload (4, 1)
	69 dconst_0 (4, 1)
	70 ldc2_w (4, 1)
	71 1e-12 (4, 1)
	73 invokestatic (4, 1)
	74 org/apache/commons/math3/util/Precision.equals:(DDD)Z (4, 1)
	76 ifeq (4, 1)
	77 20 (4, 1)
	79 aload_0 (4, 1)
	80 getfield (4, 1)
	81 org/apache/commons/math3/linear/EigenDecomposition.realEigenvalues:[D (4, 1)
	83 iload (4, 1)
	84 #4 (4, 1)
	85 aload_3 (4, 1)
	86 iload (4, 1)
	87 #4 (4, 1)
	88 aaload (4, 1)
	89 iload (4, 1)
	90 #4 (4, 1)
	91 daload (4, 1)
	92 dastore (4, 1)
	93 goto (4, 1)
	94 115 (4, 1)
	96 aload_3 (5, 2)
	97 iload (5, 2)
	98 #4 (5, 2)
	99 iconst_1 (5, 2)
	100 iadd (5, 2)
	101 aaload (5, 2)
	102 iload (5, 2)
	103 #4 (5, 2)
	104 iconst_1 (5, 2)
	105 iadd (5, 2)
	106 daload (5, 2)
	107 dstore (5, 2)
	108 #5 (5, 2)
	109 ldc2_w (5, 2)
	110 0.5 (5, 2)
	112 aload_3 (5, 2)
	113 iload (5, 2)
	114 #4 (5, 2)
	115 aaload (5, 2)
	116 iload (5, 2)
	117 #4 (5, 2)
	118 daload (5, 2)
	119 dload (5, 2)
	120 #5 (5, 2)
	121 dsub (5, 2)
	122 dmul (5, 2)
	123 dstore (5, 2)
	124 #7 (5, 2)
	125 dload (5, 2)
	126 #7 (5, 2)
	127 dload (5, 2)
	128 #7 (5, 2)
	129 dmul (5, 2)
	130 aload_3 (5, 2)
	131 iload (5, 2)
	132 #4 (5, 2)
	133 iconst_1 (5, 2)
	134 iadd (5, 2)
	135 aaload (5, 2)
	136 iload (5, 2)
	137 #4 (5, 2)
	138 daload (5, 2)
	139 aload_3 (5, 2)
	140 iload (5, 2)
	141 #4 (5, 2)
	142 aaload (5, 2)
	143 iload (5, 2)
	144 #4 (5, 2)
	145 iconst_1 (5, 2)
	146 iadd (5, 2)
	147 daload (5, 2)
	148 dmul (5, 2)
	149 dadd (5, 2)
	150 invokestatic (5, 2)
	151 org/apache/commons/math3/util/FastMath.abs:(D)D (5, 2)
	153 invokestatic (5, 2)
	154 org/apache/commons/math3/util/FastMath.sqrt:(D)D (5, 2)
	156 dstore (5, 2)
	157 #9 (5, 2)
	158 aload_0 (5, 2)
	159 getfield (5, 2)
	160 org/apache/commons/math3/linear/EigenDecomposition.realEigenvalues:[D (5, 2)
	162 iload (5, 2)
	163 #4 (5, 2)
	164 dload (5, 2)
	165 #5 (5, 2)
	166 dload (5, 2)
	167 #7 (5, 2)
	168 dadd (5, 2)
	169 dastore (5, 2)
	170 aload_0 (5, 2)
	171 getfield (5, 2)
	172 org/apache/commons/math3/linear/EigenDecomposition.imagEigenvalues:[D (5, 2)
	174 iload (5, 2)
	175 #4 (5, 2)
	176 dload (5, 2)
	177 #9 (5, 2)
	178 dastore (5, 2)
	179 aload_0 (5, 2)
	180 getfield (5, 2)
	181 org/apache/commons/math3/linear/EigenDecomposition.realEigenvalues:[D (5, 2)
	183 iload (5, 2)
	184 #4 (5, 2)
	185 iconst_1 (5, 2)
	186 iadd (5, 2)
	187 dload (5, 2)
	188 #5 (5, 2)
	189 dload (5, 2)
	190 #7 (5, 2)
	191 dadd (5, 2)
	192 dastore (5, 2)
	193 aload_0 (5, 2)
	194 getfield (5, 2)
	195 org/apache/commons/math3/linear/EigenDecomposition.imagEigenvalues:[D (5, 2)
	197 iload (5, 2)
	198 #4 (5, 2)
	199 iconst_1 (5, 2)
	200 iadd (5, 2)
	201 dload (5, 2)
	202 #9 (5, 2)
	203 dneg (5, 2)
	204 dastore (5, 2)
	205 iinc (5, 2)
	206 #4 (5, 2)
	207 -124 (5, 2)
	208 iinc (5, 2)
	209 #4 (5, 2)
	210 -89 (5, 2)
	211 goto (5, 2)
	212 -173 (5, 2)
	214 aload_2 (5, 4)
	215 areturn (1, 4)

Method: cdiv
	0 new (0, 0)
	1 org/apache/commons/math3/complex/Complex (0, 0)
	3 dup (0, 0)
	4 dload_1 (0, 0)
	5 dload_3 (0, 0)
	6 invokespecial (0, 0)
	7 org/apache/commons/math3/complex/Complex.<init>:(DD)V (0, 0)
	9 new (0, 0)
	10 org/apache/commons/math3/complex/Complex (0, 0)
	12 dup (0, 0)
	13 dload (0, 0)
	14 #5 (0, 0)
	15 dload (0, 0)
	16 #7 (0, 0)
	17 invokespecial (0, 0)
	18 org/apache/commons/math3/complex/Complex.<init>:(DD)V (0, 0)
	20 invokevirtual (0, 0)
	21 org/apache/commons/math3/complex/Complex.divide:(Lorg/apache/commons/math3/complex/Complex;)Lorg/apache/commons/math3/complex/Complex; (0, 0)
	23 areturn (0, 0)

Method: findEigenVectorsFromSchur
	0 aload_1 (0, 0)
	1 invokevirtual (0, 0)
	2 org/apache/commons/math3/linear/SchurTransformer.getT:()Lorg/apache/commons/math3/linear/RealMatrix; (0, 0)
	4 invokeinterface (0, 0)
	5 org/apache/commons/math3/linear/RealMatrix.findEigenVectors:([[D)V (0, 0)
	7 0 (0, 0)
	9 astore_2 (0, 0)
	10 aload_1 (0, 0)
	11 invokevirtual (0, 0)
	12 org/apache/commons/math3/linear/SchurTransformer.getP:()Lorg/apache/commons/math3/linear/RealMatrix; (0, 0)
	14 invokeinterface (0, 0)
	15 org/apache/commons/math3/linear/RealMatrix.findEigenVectors:([[D)V (0, 0)
	17 0 (0, 0)
	19 astore_3 (0, 0)
	20 aload_2 (0, 0)
	21 arraylength (0, 0)
	22 istore (0, 0)
	23 #4 (0, 0)
	24 dconst_0 (0, 0)
	25 dstore (0, 0)
	26 #5 (0, 0)
	27 iconst_0 (1, 4)
	28 istore (1, 4)
	29 #7 (1, 4)
	30 iload (1, 4)
	31 #7 (1, 4)
	32 iload (1, 4)
	33 #4 (1, 4)
	34 if_icmpge (1, 4)
	35 47 (1, 4)
	37 iload (2, 4)
	38 #7 (2, 4)
	39 iconst_1 (2, 4)
	40 isub (2, 4)
	41 iconst_0 (2, 4)
	42 invokestatic (2, 4)
	43 org/apache/commons/math3/util/FastMath.max:(II)I (2, 4)
	45 istore (2, 4)
	46 #8 (2, 4)
	47 iload (2, 4)
	48 #8 (2, 4)
	49 iload (2, 4)
	50 #4 (2, 4)
	51 if_icmpge (2, 4)
	52 24 (2, 4)
	54 dload (2, 4)
	55 #5 (2, 4)
	56 aload_2 (2, 4)
	57 iload (2, 4)
	58 #7 (2, 4)
	59 aaload (2, 4)
	60 iload (2, 4)
	61 #8 (2, 4)
	62 daload (2, 4)
	63 invokestatic (2, 4)
	64 org/apache/commons/math3/util/FastMath.abs:(D)D (2, 4)
	66 dadd (2, 4)
	67 dstore (2, 4)
	68 #5 (2, 4)
	69 iinc (2, 4)
	70 #8 (2, 4)
	71 -89 (2, 4)
	72 goto (2, 4)
	73 -25 (2, 4)
	75 iinc (2, 4)
	76 #7 (2, 4)
	77 -89 (2, 4)
	78 goto (2, 4)
	79 -48 (2, 4)
	81 dload (2, 1)
	82 #5 (2, 1)
	83 dconst_0 (2, 1)
	84 ldc2_w (2, 1)
	85 1e-12 (2, 1)
	87 invokestatic (2, 1)
	88 org/apache/commons/math3/util/Precision.equals:(DDD)Z (2, 1)
	90 ifeq (2, 1)
	91 18 (2, 1)
	93 new (2, 1)
	94 org/apache/commons/math3/exception/MathArithmeticException (2, 1)
	96 dup (2, 1)
	97 getstatic (2, 1)
	98 org/apache/commons/math3/exception/util/LocalizedFormats.ZERO_NORM:Lorg/apache/commons/math3/exception/util/LocalizedFormats; (2, 1)
	100 iconst_0 (2, 1)
	101 anewarray (2, 1)
	102 java/lang/Object (2, 1)
	104 invokespecial (2, 1)
	105 org/apache/commons/math3/exception/MathArithmeticException.<init>:(Lorg/apache/commons/math3/exception/util/Localizable;[Ljava/lang/Object;)V (2, 1)
	107 athrow (2, 1)
	108 dconst_0 (2, 4)
	109 dstore (2, 4)
	110 #7 (2, 4)
	111 dconst_0 (2, 4)
	112 dstore (2, 4)
	113 #9 (2, 4)
	114 dconst_0 (2, 4)
	115 dstore (2, 4)
	116 #11 (2, 4)
	117 iload (3, 4)
	118 #4 (3, 4)
	119 iconst_1 (3, 4)
	120 isub (3, 4)
	121 istore (3, 4)
	122 #13 (3, 4)
	123 iload (3, 4)
	124 #13 (3, 4)
	125 iflt (3, 4)
	126 1245 (3, 4)
	128 aload_0 (3, 4)
	129 getfield (3, 4)
	130 org/apache/commons/math3/linear/EigenDecomposition.realEigenvalues:[D (3, 4)
	132 iload (3, 4)
	133 #13 (3, 4)
	134 daload (3, 4)
	135 dstore (3, 4)
	136 #14 (3, 4)
	137 aload_0 (3, 4)
	138 getfield (3, 4)
	139 org/apache/commons/math3/linear/EigenDecomposition.imagEigenvalues:[D (3, 4)
	141 iload (3, 4)
	142 #13 (3, 4)
	143 daload (3, 4)
	144 dstore (3, 4)
	145 #16 (3, 4)
	146 dload (4, 1)
	147 #16 (4, 1)
	148 dconst_0 (4, 1)
	149 invokestatic (4, 1)
	150 org/apache/commons/math3/util/Precision.equals:(DD)Z (4, 1)
	152 ifeq (4, 1)
	153 376 (4, 1)
	155 iload (4, 1)
	156 #13 (4, 1)
	157 istore (4, 1)
	158 #18 (4, 1)
	159 aload_2 (4, 1)
	160 iload (4, 1)
	161 #13 (4, 1)
	162 aaload (4, 1)
	163 iload (4, 1)
	164 #13 (4, 1)
	165 dconst_1 (4, 1)
	166 dastore (4, 1)
	167 iload (5, 4)
	168 #13 (5, 4)
	169 iconst_1 (5, 4)
	170 isub (5, 4)
	171 istore (5, 4)
	172 #19 (5, 4)
	173 iload (5, 4)
	174 #19 (5, 4)
	175 iflt (5, 4)
	176 350 (5, 4)
	178 aload_2 (5, 4)
	179 iload (5, 4)
	180 #19 (5, 4)
	181 aaload (5, 4)
	182 iload (5, 4)
	183 #19 (5, 4)
	184 daload (5, 4)
	185 dload (5, 4)
	186 #14 (5, 4)
	187 dsub (5, 4)
	188 dstore (5, 4)
	189 #20 (5, 4)
	190 dconst_0 (5, 4)
	191 dstore (5, 4)
	192 #7 (5, 4)
	193 iload (6, 4)
	194 #18 (6, 4)
	195 istore (6, 4)
	196 #22 (6, 4)
	197 iload (6, 4)
	198 #22 (6, 4)
	199 iload (6, 4)
	200 #13 (6, 4)
	201 if_icmpgt (6, 4)
	202 29 (6, 4)
	204 dload (6, 4)
	205 #7 (6, 4)
	206 aload_2 (6, 4)
	207 iload (6, 4)
	208 #19 (6, 4)
	209 aaload (6, 4)
	210 iload (6, 4)
	211 #22 (6, 4)
	212 daload (6, 4)
	213 aload_2 (6, 4)
	214 iload (6, 4)
	215 #22 (6, 4)
	216 aaload (6, 4)
	217 iload (6, 4)
	218 #13 (6, 4)
	219 daload (6, 4)
	220 dmul (6, 4)
	221 dadd (6, 4)
	222 dstore (6, 4)
	223 #7 (6, 4)
	224 iinc (6, 4)
	225 #22 (6, 4)
	226 -89 (6, 4)
	227 goto (6, 4)
	228 -30 (6, 4)
	230 aload_0 (6, 1)
	231 getfield (6, 1)
	232 org/apache/commons/math3/linear/EigenDecomposition.imagEigenvalues:[D (6, 1)
	234 iload (6, 1)
	235 #19 (6, 1)
	236 daload (6, 1)
	237 dconst_0 (6, 1)
	238 ldc2_w (6, 1)
	239 1e-12 (6, 1)
	241 invokestatic (6, 1)
	242 org/apache/commons/math3/util/Precision.compareTo:(DDD)I (6, 1)
	244 ifge (6, 1)
	245 14 (6, 1)
	247 dload (6, 1)
	248 #20 (6, 1)
	249 dstore (6, 1)
	250 #11 (6, 1)
	251 dload (6, 1)
	252 #7 (6, 1)
	253 dstore (6, 1)
	254 #9 (6, 1)
	255 goto (6, 1)
	256 264 (6, 1)
	258 iload (7, 2)
	259 #19 (7, 2)
	260 istore (7, 2)
	261 #18 (7, 2)
	262 aload_0 (8, 1)
	263 getfield (8, 1)
	264 org/apache/commons/math3/linear/EigenDecomposition.imagEigenvalues:[D (8, 1)
	266 iload (8, 1)
	267 #19 (8, 1)
	268 daload (8, 1)
	269 dconst_0 (8, 1)
	270 invokestatic (8, 1)
	271 org/apache/commons/math3/util/Precision.equals:(DD)Z (8, 1)
	273 ifeq (8, 1)
	274 46 (8, 1)
	276 dload (9, 1)
	277 #20 (9, 1)
	278 dconst_0 (9, 1)
	279 dcmpl (9, 1)
	280 ifeq (9, 1)
	281 19 (9, 1)
	283 aload_2 (9, 1)
	284 iload (9, 1)
	285 #19 (9, 1)
	286 aaload (9, 1)
	287 iload (9, 1)
	288 #13 (9, 1)
	289 dload (9, 1)
	290 #7 (9, 1)
	291 dneg (9, 1)
	292 dload (9, 1)
	293 #20 (9, 1)
	294 ddiv (9, 1)
	295 dastore (9, 1)
	296 goto (9, 1)
	297 168 (9, 1)
	299 aload_2 (10, 2)
	300 iload (10, 2)
	301 #19 (10, 2)
	302 aaload (10, 2)
	303 iload (10, 2)
	304 #13 (10, 2)
	305 dload (10, 2)
	306 #7 (10, 2)
	307 dneg (10, 2)
	308 getstatic (10, 2)
	309 org/apache/commons/math3/util/Precision.EPSILON:D (10, 2)
	311 dload (10, 2)
	312 #5 (10, 2)
	313 dmul (10, 2)
	314 ddiv (10, 2)
	315 dastore (10, 2)
	316 goto (10, 2)
	317 148 (10, 2)
	319 aload_2 (9, 2)
	320 iload (9, 2)
	321 #19 (9, 2)
	322 aaload (9, 2)
	323 iload (9, 2)
	324 #19 (9, 2)
	325 iconst_1 (9, 2)
	326 iadd (9, 2)
	327 daload (9, 2)
	328 dstore (9, 2)
	329 #22 (9, 2)
	330 aload_2 (9, 2)
	331 iload (9, 2)
	332 #19 (9, 2)
	333 iconst_1 (9, 2)
	334 iadd (9, 2)
	335 aaload (9, 2)
	336 iload (9, 2)
	337 #19 (9, 2)
	338 daload (9, 2)
	339 dstore (9, 2)
	340 #24 (9, 2)
	341 aload_0 (9, 2)
	342 getfield (9, 2)
	343 org/apache/commons/math3/linear/EigenDecomposition.realEigenvalues:[D (9, 2)
	345 iload (9, 2)
	346 #19 (9, 2)
	347 daload (9, 2)
	348 dload (9, 2)
	349 #14 (9, 2)
	350 dsub (9, 2)
	351 aload_0 (9, 2)
	352 getfield (9, 2)
	353 org/apache/commons/math3/linear/EigenDecomposition.realEigenvalues:[D (9, 2)
	355 iload (9, 2)
	356 #19 (9, 2)
	357 daload (9, 2)
	358 dload (9, 2)
	359 #14 (9, 2)
	360 dsub (9, 2)
	361 dmul (9, 2)
	362 aload_0 (9, 2)
	363 getfield (9, 2)
	364 org/apache/commons/math3/linear/EigenDecomposition.imagEigenvalues:[D (9, 2)
	366 iload (9, 2)
	367 #19 (9, 2)
	368 daload (9, 2)
	369 aload_0 (9, 2)
	370 getfield (9, 2)
	371 org/apache/commons/math3/linear/EigenDecomposition.imagEigenvalues:[D (9, 2)
	373 iload (9, 2)
	374 #19 (9, 2)
	375 daload (9, 2)
	376 dmul (9, 2)
	377 dadd (9, 2)
	378 dstore (9, 2)
	379 #16 (9, 2)
	380 dload (9, 2)
	381 #22 (9, 2)
	382 dload (9, 2)
	383 #9 (9, 2)
	384 dmul (9, 2)
	385 dload (9, 2)
	386 #11 (9, 2)
	387 dload (9, 2)
	388 #7 (9, 2)
	389 dmul (9, 2)
	390 dsub (9, 2)
	391 dload (9, 2)
	392 #16 (9, 2)
	393 ddiv (9, 2)
	394 dstore (9, 2)
	395 #26 (9, 2)
	396 aload_2 (9, 2)
	397 iload (9, 2)
	398 #19 (9, 2)
	399 aaload (9, 2)
	400 iload (9, 2)
	401 #13 (9, 2)
	402 dload (9, 2)
	403 #26 (9, 2)
	404 dastore (9, 2)
	405 dload (10, 1)
	406 #22 (10, 1)
	407 invokestatic (10, 1)
	408 org/apache/commons/math3/util/FastMath.abs:(D)D (10, 1)
	410 dload (10, 1)
	411 #11 (10, 1)
	412 invokestatic (10, 1)
	413 org/apache/commons/math3/util/FastMath.abs:(D)D (10, 1)
	415 dcmpl (10, 1)
	416 ifle (10, 1)
	417 27 (10, 1)
	419 aload_2 (10, 1)
	420 iload (10, 1)
	421 #19 (10, 1)
	422 iconst_1 (10, 1)
	423 iadd (10, 1)
	424 aaload (10, 1)
	425 iload (10, 1)
	426 #13 (10, 1)
	427 dload (10, 1)
	428 #7 (10, 1)
	429 dneg (10, 1)
	430 dload (10, 1)
	431 #20 (10, 1)
	432 dload (10, 1)
	433 #26 (10, 1)
	434 dmul (10, 1)
	435 dsub (10, 1)
	436 dload (10, 1)
	437 #22 (10, 1)
	438 ddiv (10, 1)
	439 dastore (10, 1)
	440 goto (10, 1)
	441 24 (10, 1)
	443 aload_2 (11, 2)
	444 iload (11, 2)
	445 #19 (11, 2)
	446 iconst_1 (11, 2)
	447 iadd (11, 2)
	448 aaload (11, 2)
	449 iload (11, 2)
	450 #13 (11, 2)
	451 dload (11, 2)
	452 #9 (11, 2)
	453 dneg (11, 2)
	454 dload (11, 2)
	455 #24 (11, 2)
	456 dload (11, 2)
	457 #26 (11, 2)
	458 dmul (11, 2)
	459 dsub (11, 2)
	460 dload (11, 2)
	461 #11 (11, 2)
	462 ddiv (11, 2)
	463 dastore (11, 2)
	464 aload_2 (7, 2)
	465 iload (7, 2)
	466 #19 (7, 2)
	467 aaload (7, 2)
	468 iload (7, 2)
	469 #13 (7, 2)
	470 daload (7, 2)
	471 invokestatic (7, 2)
	472 org/apache/commons/math3/util/FastMath.abs:(D)D (7, 2)
	474 dstore (7, 2)
	475 #22 (7, 2)
	476 getstatic (8, 1)
	477 org/apache/commons/math3/util/Precision.EPSILON:D (8, 1)
	479 dload (8, 1)
	480 #22 (8, 1)
	481 dmul (8, 1)
	482 dload (8, 1)
	483 #22 (8, 1)
	484 dmul (8, 1)
	485 dconst_1 (8, 1)
	486 dcmpl (8, 1)
	487 ifle (8, 1)
	488 32 (8, 1)
	490 iload (9, 4)
	491 #19 (9, 4)
	492 istore (9, 4)
	493 #24 (9, 4)
	494 iload (9, 4)
	495 #24 (9, 4)
	496 iload (9, 4)
	497 #13 (9, 4)
	498 if_icmpgt (9, 4)
	499 21 (9, 4)
	501 aload_2 (9, 4)
	502 iload (9, 4)
	503 #24 (9, 4)
	504 aaload (9, 4)
	505 iload (9, 4)
	506 #13 (9, 4)
	507 dup2 (9, 4)
	508 daload (9, 4)
	509 dload (9, 4)
	510 #22 (9, 4)
	511 ddiv (9, 4)
	512 dastore (9, 4)
	513 iinc (9, 4)
	514 #24 (9, 4)
	515 -89 (9, 4)
	516 goto (9, 4)
	517 -22 (9, 4)
	519 iinc (9, 4)
	520 #19 (9, 4)
	521 -89 (9, 4)
	522 goto (9, 4)
	523 -349 (9, 4)
	525 goto (9, 1)
	526 839 (9, 1)
	528 dload (9, 1)
	529 #16 (9, 1)
	530 dconst_0 (9, 1)
	531 dcmpg (9, 1)
	532 ifge (9, 1)
	533 832 (9, 1)
	535 iload (9, 1)
	536 #13 (9, 1)
	537 iconst_1 (9, 1)
	538 isub (9, 1)
	539 istore (9, 1)
	540 #18 (9, 1)
	541 aload_2 (10, 1)
	542 iload (10, 1)
	543 #13 (10, 1)
	544 aaload (10, 1)
	545 iload (10, 1)
	546 #13 (10, 1)
	547 iconst_1 (10, 1)
	548 isub (10, 1)
	549 daload (10, 1)
	550 invokestatic (10, 1)
	551 org/apache/commons/math3/util/FastMath.abs:(D)D (10, 1)
	553 aload_2 (10, 1)
	554 iload (10, 1)
	555 #13 (10, 1)
	556 iconst_1 (10, 1)
	557 isub (10, 1)
	558 aaload (10, 1)
	559 iload (10, 1)
	560 #13 (10, 1)
	561 daload (10, 1)
	562 invokestatic (10, 1)
	563 org/apache/commons/math3/util/FastMath.abs:(D)D (10, 1)
	565 dcmpl (10, 1)
	566 ifle (10, 1)
	567 59 (10, 1)
	569 aload_2 (10, 1)
	570 iload (10, 1)
	571 #13 (10, 1)
	572 iconst_1 (10, 1)
	573 isub (10, 1)
	574 aaload (10, 1)
	575 iload (10, 1)
	576 #13 (10, 1)
	577 iconst_1 (10, 1)
	578 isub (10, 1)
	579 dload (10, 1)
	580 #16 (10, 1)
	581 aload_2 (10, 1)
	582 iload (10, 1)
	583 #13 (10, 1)
	584 aaload (10, 1)
	585 iload (10, 1)
	586 #13 (10, 1)
	587 iconst_1 (10, 1)
	588 isub (10, 1)
	589 daload (10, 1)
	590 ddiv (10, 1)
	591 dastore (10, 1)
	592 aload_2 (10, 1)
	593 iload (10, 1)
	594 #13 (10, 1)
	595 iconst_1 (10, 1)
	596 isub (10, 1)
	597 aaload (10, 1)
	598 iload (10, 1)
	599 #13 (10, 1)
	600 aload_2 (10, 1)
	601 iload (10, 1)
	602 #13 (10, 1)
	603 aaload (10, 1)
	604 iload (10, 1)
	605 #13 (10, 1)
	606 daload (10, 1)
	607 dload (10, 1)
	608 #14 (10, 1)
	609 dsub (10, 1)
	610 dneg (10, 1)
	611 aload_2 (10, 1)
	612 iload (10, 1)
	613 #13 (10, 1)
	614 aaload (10, 1)
	615 iload (10, 1)
	616 #13 (10, 1)
	617 iconst_1 (10, 1)
	618 isub (10, 1)
	619 daload (10, 1)
	620 ddiv (10, 1)
	621 dastore (10, 1)
	622 goto (10, 1)
	623 66 (10, 1)
	625 aload_0 (11, 2)
	626 dconst_0 (11, 2)
	627 aload_2 (11, 2)
	628 iload (11, 2)
	629 #13 (11, 2)
	630 iconst_1 (11, 2)
	631 isub (11, 2)
	632 aaload (11, 2)
	633 iload (11, 2)
	634 #13 (11, 2)
	635 daload (11, 2)
	636 dneg (11, 2)
	637 aload_2 (11, 2)
	638 iload (11, 2)
	639 #13 (11, 2)
	640 iconst_1 (11, 2)
	641 isub (11, 2)
	642 aaload (11, 2)
	643 iload (11, 2)
	644 #13 (11, 2)
	645 iconst_1 (11, 2)
	646 isub (11, 2)
	647 daload (11, 2)
	648 dload (11, 2)
	649 #14 (11, 2)
	650 dsub (11, 2)
	651 dload (11, 2)
	652 #16 (11, 2)
	653 invokespecial (11, 2)
	654 org/apache/commons/math3/linear/EigenDecomposition.cdiv:(DDDD)Lorg/apache/commons/math3/complex/Complex; (11, 2)
	656 astore (11, 2)
	657 #19 (11, 2)
	658 aload_2 (11, 2)
	659 iload (11, 2)
	660 #13 (11, 2)
	661 iconst_1 (11, 2)
	662 isub (11, 2)
	663 aaload (11, 2)
	664 iload (11, 2)
	665 #13 (11, 2)
	666 iconst_1 (11, 2)
	667 isub (11, 2)
	668 aload (11, 2)
	669 #19 (11, 2)
	670 invokevirtual (11, 2)
	671 org/apache/commons/math3/complex/Complex.getReal:()D (11, 2)
	673 dastore (11, 2)
	674 aload_2 (11, 2)
	675 iload (11, 2)
	676 #13 (11, 2)
	677 iconst_1 (11, 2)
	678 isub (11, 2)
	679 aaload (11, 2)
	680 iload (11, 2)
	681 #13 (11, 2)
	682 aload (11, 2)
	683 #19 (11, 2)
	684 invokevirtual (11, 2)
	685 org/apache/commons/math3/complex/Complex.getImaginary:()D (11, 2)
	687 dastore (11, 2)
	688 aload_2 (9, 1)
	689 iload (9, 1)
	690 #13 (9, 1)
	691 aaload (9, 1)
	692 iload (9, 1)
	693 #13 (9, 1)
	694 iconst_1 (9, 1)
	695 isub (9, 1)
	696 dconst_0 (9, 1)
	697 dastore (9, 1)
	698 aload_2 (9, 1)
	699 iload (9, 1)
	700 #13 (9, 1)
	701 aaload (9, 1)
	702 iload (9, 1)
	703 #13 (9, 1)
	704 dconst_1 (9, 1)
	705 dastore (9, 1)
	706 iload (10, 4)
	707 #13 (10, 4)
	708 iconst_2 (10, 4)
	709 isub (10, 4)
	710 istore (10, 4)
	711 #19 (10, 4)
	712 iload (10, 4)
	713 #19 (10, 4)
	714 iflt (10, 4)
	715 650 (10, 4)
	717 dconst_0 (10, 4)
	718 dstore (10, 4)
	719 #20 (10, 4)
	720 dconst_0 (10, 4)
	721 dstore (10, 4)
	722 #22 (10, 4)
	723 iload (11, 4)
	724 #18 (11, 4)
	725 istore (11, 4)
	726 #24 (11, 4)
	727 iload (11, 4)
	728 #24 (11, 4)
	729 iload (11, 4)
	730 #13 (11, 4)
	731 if_icmpgt (11, 4)
	732 51 (11, 4)
	734 dload (11, 4)
	735 #20 (11, 4)
	736 aload_2 (11, 4)
	737 iload (11, 4)
	738 #19 (11, 4)
	739 aaload (11, 4)
	740 iload (11, 4)
	741 #24 (11, 4)
	742 daload (11, 4)
	743 aload_2 (11, 4)
	744 iload (11, 4)
	745 #24 (11, 4)
	746 aaload (11, 4)
	747 iload (11, 4)
	748 #13 (11, 4)
	749 iconst_1 (11, 4)
	750 isub (11, 4)
	751 daload (11, 4)
	752 dmul (11, 4)
	753 dadd (11, 4)
	754 dstore (11, 4)
	755 #20 (11, 4)
	756 dload (11, 4)
	757 #22 (11, 4)
	758 aload_2 (11, 4)
	759 iload (11, 4)
	760 #19 (11, 4)
	761 aaload (11, 4)
	762 iload (11, 4)
	763 #24 (11, 4)
	764 daload (11, 4)
	765 aload_2 (11, 4)
	766 iload (11, 4)
	767 #24 (11, 4)
	768 aaload (11, 4)
	769 iload (11, 4)
	770 #13 (11, 4)
	771 daload (11, 4)
	772 dmul (11, 4)
	773 dadd (11, 4)
	774 dstore (11, 4)
	775 #22 (11, 4)
	776 iinc (11, 4)
	777 #24 (11, 4)
	778 -89 (11, 4)
	779 goto (11, 4)
	780 -52 (11, 4)
	782 aload_2 (10, 4)
	783 iload (10, 4)
	784 #19 (10, 4)
	785 aaload (10, 4)
	786 iload (10, 4)
	787 #19 (10, 4)
	788 daload (10, 4)
	789 dload (10, 4)
	790 #14 (10, 4)
	791 dsub (10, 4)
	792 dstore (10, 4)
	793 #24 (10, 4)
	794 aload_0 (11, 1)
	795 getfield (11, 1)
	796 org/apache/commons/math3/linear/EigenDecomposition.imagEigenvalues:[D (11, 1)
	798 iload (11, 1)
	799 #19 (11, 1)
	800 daload (11, 1)
	801 dconst_0 (11, 1)
	802 ldc2_w (11, 1)
	803 1e-12 (11, 1)
	805 invokestatic (11, 1)
	806 org/apache/commons/math3/util/Precision.compareTo:(DDD)I (11, 1)
	808 ifge (11, 1)
	809 18 (11, 1)
	811 dload (11, 1)
	812 #24 (11, 1)
	813 dstore (11, 1)
	814 #11 (11, 1)
	815 dload (11, 1)
	816 #20 (11, 1)
	817 dstore (11, 1)
	818 #7 (11, 1)
	819 dload (11, 1)
	820 #22 (11, 1)
	821 dstore (11, 1)
	822 #9 (11, 1)
	823 goto (11, 1)
	824 535 (11, 1)
	826 iload (12, 2)
	827 #19 (12, 2)
	828 istore (12, 2)
	829 #18 (12, 2)
	830 aload_0 (13, 1)
	831 getfield (13, 1)
	832 org/apache/commons/math3/linear/EigenDecomposition.imagEigenvalues:[D (13, 1)
	834 iload (13, 1)
	835 #19 (13, 1)
	836 daload (13, 1)
	837 dconst_0 (13, 1)
	838 invokestatic (13, 1)
	839 org/apache/commons/math3/util/Precision.equals:(DD)Z (13, 1)
	841 ifeq (13, 1)
	842 48 (13, 1)
	844 aload_0 (13, 1)
	845 dload (13, 1)
	846 #20 (13, 1)
	847 dneg (13, 1)
	848 dload (13, 1)
	849 #22 (13, 1)
	850 dneg (13, 1)
	851 dload (13, 1)
	852 #24 (13, 1)
	853 dload (13, 1)
	854 #16 (13, 1)
	855 invokespecial (13, 1)
	856 org/apache/commons/math3/linear/EigenDecomposition.cdiv:(DDDD)Lorg/apache/commons/math3/complex/Complex; (13, 1)
	858 astore (13, 1)
	859 #26 (13, 1)
	860 aload_2 (13, 1)
	861 iload (13, 1)
	862 #19 (13, 1)
	863 aaload (13, 1)
	864 iload (13, 1)
	865 #13 (13, 1)
	866 iconst_1 (13, 1)
	867 isub (13, 1)
	868 aload (13, 1)
	869 #26 (13, 1)
	870 invokevirtual (13, 1)
	871 org/apache/commons/math3/complex/Complex.getReal:()D (13, 1)
	873 dastore (13, 1)
	874 aload_2 (13, 1)
	875 iload (13, 1)
	876 #19 (13, 1)
	877 aaload (13, 1)
	878 iload (13, 1)
	879 #13 (13, 1)
	880 aload (13, 1)
	881 #26 (13, 1)
	882 invokevirtual (13, 1)
	883 org/apache/commons/math3/complex/Complex.getImaginary:()D (13, 1)
	885 dastore (13, 1)
	886 goto (14, 2)
	887 388 (14, 2)
	889 aload_2 (14, 2)
	890 iload (14, 2)
	891 #19 (14, 2)
	892 aaload (14, 2)
	893 iload (14, 2)
	894 #19 (14, 2)
	895 iconst_1 (14, 2)
	896 iadd (14, 2)
	897 daload (14, 2)
	898 dstore (14, 2)
	899 #26 (14, 2)
	900 aload_2 (14, 2)
	901 iload (14, 2)
	902 #19 (14, 2)
	903 iconst_1 (14, 2)
	904 iadd (14, 2)
	905 aaload (14, 2)
	906 iload (14, 2)
	907 #19 (14, 2)
	908 daload (14, 2)
	909 dstore (14, 2)
	910 #28 (14, 2)
	911 aload_0 (14, 2)
	912 getfield (14, 2)
	913 org/apache/commons/math3/linear/EigenDecomposition.realEigenvalues:[D (14, 2)
	915 iload (14, 2)
	916 #19 (14, 2)
	917 daload (14, 2)
	918 dload (14, 2)
	919 #14 (14, 2)
	920 dsub (14, 2)
	921 aload_0 (14, 2)
	922 getfield (14, 2)
	923 org/apache/commons/math3/linear/EigenDecomposition.realEigenvalues:[D (14, 2)
	925 iload (14, 2)
	926 #19 (14, 2)
	927 daload (14, 2)
	928 dload (14, 2)
	929 #14 (14, 2)
	930 dsub (14, 2)
	931 dmul (14, 2)
	932 aload_0 (14, 2)
	933 getfield (14, 2)
	934 org/apache/commons/math3/linear/EigenDecomposition.imagEigenvalues:[D (14, 2)
	936 iload (14, 2)
	937 #19 (14, 2)
	938 daload (14, 2)
	939 aload_0 (14, 2)
	940 getfield (14, 2)
	941 org/apache/commons/math3/linear/EigenDecomposition.imagEigenvalues:[D (14, 2)
	943 iload (14, 2)
	944 #19 (14, 2)
	945 daload (14, 2)
	946 dmul (14, 2)
	947 dadd (14, 2)
	948 dload (14, 2)
	949 #16 (14, 2)
	950 dload (14, 2)
	951 #16 (14, 2)
	952 dmul (14, 2)
	953 dsub (14, 2)
	954 dstore (14, 2)
	955 #30 (14, 2)
	956 aload_0 (14, 2)
	957 getfield (14, 2)
	958 org/apache/commons/math3/linear/EigenDecomposition.realEigenvalues:[D (14, 2)
	960 iload (14, 2)
	961 #19 (14, 2)
	962 daload (14, 2)
	963 dload (14, 2)
	964 #14 (14, 2)
	965 dsub (14, 2)
	966 ldc2_w (14, 2)
	967 2.0 (14, 2)
	969 dmul (14, 2)
	970 dload (14, 2)
	971 #16 (14, 2)
	972 dmul (14, 2)
	973 dstore (14, 2)
	974 #32 (14, 2)
	975 dload (15, 1)
	976 #30 (15, 1)
	977 dconst_0 (15, 1)
	978 invokestatic (15, 1)
	979 org/apache/commons/math3/util/Precision.equals:(DD)Z (15, 1)
	981 ifeq (15, 1)
	982 50 (15, 1)
	984 dload (15, 1)
	985 #32 (15, 1)
	986 dconst_0 (15, 1)
	987 invokestatic (15, 1)
	988 org/apache/commons/math3/util/Precision.equals:(DD)Z (15, 1)
	990 ifeq (15, 1)
	991 41 (15, 1)
	993 getstatic (15, 1)
	994 org/apache/commons/math3/util/Precision.EPSILON:D (15, 1)
	996 dload (15, 1)
	997 #5 (15, 1)
	998 dmul (15, 1)
	999 dload (15, 1)
	1000 #24 (15, 1)
	1001 invokestatic (15, 1)
	1002 org/apache/commons/math3/util/FastMath.abs:(D)D (15, 1)
	1004 dload (15, 1)
	1005 #16 (15, 1)
	1006 invokestatic (15, 1)
	1007 org/apache/commons/math3/util/FastMath.abs:(D)D (15, 1)
	1009 dadd (15, 1)
	1010 dload (15, 1)
	1011 #26 (15, 1)
	1012 invokestatic (15, 1)
	1013 org/apache/commons/math3/util/FastMath.abs:(D)D (15, 1)
	1015 dadd (15, 1)
	1016 dload (15, 1)
	1017 #28 (15, 1)
	1018 invokestatic (15, 1)
	1019 org/apache/commons/math3/util/FastMath.abs:(D)D (15, 1)
	1021 dadd (15, 1)
	1022 dload (15, 1)
	1023 #11 (15, 1)
	1024 invokestatic (15, 1)
	1025 org/apache/commons/math3/util/FastMath.abs:(D)D (15, 1)
	1027 dadd (15, 1)
	1028 dmul (15, 1)
	1029 dstore (15, 1)
	1030 #30 (15, 1)
	1031 aload_0 (14, 2)
	1032 dload (14, 2)
	1033 #26 (14, 2)
	1034 dload (14, 2)
	1035 #7 (14, 2)
	1036 dmul (14, 2)
	1037 dload (14, 2)
	1038 #11 (14, 2)
	1039 dload (14, 2)
	1040 #20 (14, 2)
	1041 dmul (14, 2)
	1042 dsub (14, 2)
	1043 dload (14, 2)
	1044 #16 (14, 2)
	1045 dload (14, 2)
	1046 #22 (14, 2)
	1047 dmul (14, 2)
	1048 dadd (14, 2)
	1049 dload (14, 2)
	1050 #26 (14, 2)
	1051 dload (14, 2)
	1052 #9 (14, 2)
	1053 dmul (14, 2)
	1054 dload (14, 2)
	1055 #11 (14, 2)
	1056 dload (14, 2)
	1057 #22 (14, 2)
	1058 dmul (14, 2)
	1059 dsub (14, 2)
	1060 dload (14, 2)
	1061 #16 (14, 2)
	1062 dload (14, 2)
	1063 #20 (14, 2)
	1064 dmul (14, 2)
	1065 dsub (14, 2)
	1066 dload (14, 2)
	1067 #30 (14, 2)
	1068 dload (14, 2)
	1069 #32 (14, 2)
	1070 invokespecial (14, 2)
	1071 org/apache/commons/math3/linear/EigenDecomposition.cdiv:(DDDD)Lorg/apache/commons/math3/complex/Complex; (14, 2)
	1073 astore (14, 2)
	1074 #34 (14, 2)
	1075 aload_2 (14, 2)
	1076 iload (14, 2)
	1077 #19 (14, 2)
	1078 aaload (14, 2)
	1079 iload (14, 2)
	1080 #13 (14, 2)
	1081 iconst_1 (14, 2)
	1082 isub (14, 2)
	1083 aload (14, 2)
	1084 #34 (14, 2)
	1085 invokevirtual (14, 2)
	1086 org/apache/commons/math3/complex/Complex.getReal:()D (14, 2)
	1088 dastore (14, 2)
	1089 aload_2 (14, 2)
	1090 iload (14, 2)
	1091 #19 (14, 2)
	1092 aaload (14, 2)
	1093 iload (14, 2)
	1094 #13 (14, 2)
	1095 aload (14, 2)
	1096 #34 (14, 2)
	1097 invokevirtual (14, 2)
	1098 org/apache/commons/math3/complex/Complex.getImaginary:()D (14, 2)
	1100 dastore (14, 2)
	1101 dload (15, 1)
	1102 #26 (15, 1)
	1103 invokestatic (15, 1)
	1104 org/apache/commons/math3/util/FastMath.abs:(D)D (15, 1)
	1106 dload (15, 1)
	1107 #11 (15, 1)
	1108 invokestatic (15, 1)
	1109 org/apache/commons/math3/util/FastMath.abs:(D)D (15, 1)
	1111 dload (15, 1)
	1112 #16 (15, 1)
	1113 invokestatic (15, 1)
	1114 org/apache/commons/math3/util/FastMath.abs:(D)D (15, 1)
	1116 dadd (15, 1)
	1117 dcmpl (15, 1)
	1118 ifle (15, 1)
	1119 86 (15, 1)
	1121 aload_2 (15, 1)
	1122 iload (15, 1)
	1123 #19 (15, 1)
	1124 iconst_1 (15, 1)
	1125 iadd (15, 1)
	1126 aaload (15, 1)
	1127 iload (15, 1)
	1128 #13 (15, 1)
	1129 iconst_1 (15, 1)
	1130 isub (15, 1)
	1131 dload (15, 1)
	1132 #20 (15, 1)
	1133 dneg (15, 1)
	1134 dload (15, 1)
	1135 #24 (15, 1)
	1136 aload_2 (15, 1)
	1137 iload (15, 1)
	1138 #19 (15, 1)
	1139 aaload (15, 1)
	1140 iload (15, 1)
	1141 #13 (15, 1)
	1142 iconst_1 (15, 1)
	1143 isub (15, 1)
	1144 daload (15, 1)
	1145 dmul (15, 1)
	1146 dsub (15, 1)
	1147 dload (15, 1)
	1148 #16 (15, 1)
	1149 aload_2 (15, 1)
	1150 iload (15, 1)
	1151 #19 (15, 1)
	1152 aaload (15, 1)
	1153 iload (15, 1)
	1154 #13 (15, 1)
	1155 daload (15, 1)
	1156 dmul (15, 1)
	1157 dadd (15, 1)
	1158 dload (15, 1)
	1159 #26 (15, 1)
	1160 ddiv (15, 1)
	1161 dastore (15, 1)
	1162 aload_2 (15, 1)
	1163 iload (15, 1)
	1164 #19 (15, 1)
	1165 iconst_1 (15, 1)
	1166 iadd (15, 1)
	1167 aaload (15, 1)
	1168 iload (15, 1)
	1169 #13 (15, 1)
	1170 dload (15, 1)
	1171 #22 (15, 1)
	1172 dneg (15, 1)
	1173 dload (15, 1)
	1174 #24 (15, 1)
	1175 aload_2 (15, 1)
	1176 iload (15, 1)
	1177 #19 (15, 1)
	1178 aaload (15, 1)
	1179 iload (15, 1)
	1180 #13 (15, 1)
	1181 daload (15, 1)
	1182 dmul (15, 1)
	1183 dsub (15, 1)
	1184 dload (15, 1)
	1185 #16 (15, 1)
	1186 aload_2 (15, 1)
	1187 iload (15, 1)
	1188 #19 (15, 1)
	1189 aaload (15, 1)
	1190 iload (15, 1)
	1191 #13 (15, 1)
	1192 iconst_1 (15, 1)
	1193 isub (15, 1)
	1194 daload (15, 1)
	1195 dmul (15, 1)
	1196 dsub (15, 1)
	1197 dload (15, 1)
	1198 #26 (15, 1)
	1199 ddiv (15, 1)
	1200 dastore (15, 1)
	1201 goto (15, 1)
	1202 73 (15, 1)
	1204 aload_0 (16, 2)
	1205 dload (16, 2)
	1206 #7 (16, 2)
	1207 dneg (16, 2)
	1208 dload (16, 2)
	1209 #28 (16, 2)
	1210 aload_2 (16, 2)
	1211 iload (16, 2)
	1212 #19 (16, 2)
	1213 aaload (16, 2)
	1214 iload (16, 2)
	1215 #13 (16, 2)
	1216 iconst_1 (16, 2)
	1217 isub (16, 2)
	1218 daload (16, 2)
	1219 dmul (16, 2)
	1220 dsub (16, 2)
	1221 dload (16, 2)
	1222 #9 (16, 2)
	1223 dneg (16, 2)
	1224 dload (16, 2)
	1225 #28 (16, 2)
	1226 aload_2 (16, 2)
	1227 iload (16, 2)
	1228 #19 (16, 2)
	1229 aaload (16, 2)
	1230 iload (16, 2)
	1231 #13 (16, 2)
	1232 daload (16, 2)
	1233 dmul (16, 2)
	1234 dsub (16, 2)
	1235 dload (16, 2)
	1236 #11 (16, 2)
	1237 dload (16, 2)
	1238 #16 (16, 2)
	1239 invokespecial (16, 2)
	1240 org/apache/commons/math3/linear/EigenDecomposition.cdiv:(DDDD)Lorg/apache/commons/math3/complex/Complex; (16, 2)
	1242 astore (16, 2)
	1243 #35 (16, 2)
	1244 aload_2 (16, 2)
	1245 iload (16, 2)
	1246 #19 (16, 2)
	1247 iconst_1 (16, 2)
	1248 iadd (16, 2)
	1249 aaload (16, 2)
	1250 iload (16, 2)
	1251 #13 (16, 2)
	1252 iconst_1 (16, 2)
	1253 isub (16, 2)
	1254 aload (16, 2)
	1255 #35 (16, 2)
	1256 invokevirtual (16, 2)
	1257 org/apache/commons/math3/complex/Complex.getReal:()D (16, 2)
	1259 dastore (16, 2)
	1260 aload_2 (16, 2)
	1261 iload (16, 2)
	1262 #19 (16, 2)
	1263 iconst_1 (16, 2)
	1264 iadd (16, 2)
	1265 aaload (16, 2)
	1266 iload (16, 2)
	1267 #13 (16, 2)
	1268 aload (16, 2)
	1269 #35 (16, 2)
	1270 invokevirtual (16, 2)
	1271 org/apache/commons/math3/complex/Complex.getImaginary:()D (16, 2)
	1273 dastore (16, 2)
	1274 aload_2 (12, 2)
	1275 iload (12, 2)
	1276 #19 (12, 2)
	1277 aaload (12, 2)
	1278 iload (12, 2)
	1279 #13 (12, 2)
	1280 iconst_1 (12, 2)
	1281 isub (12, 2)
	1282 daload (12, 2)
	1283 invokestatic (12, 2)
	1284 org/apache/commons/math3/util/FastMath.abs:(D)D (12, 2)
	1286 aload_2 (12, 2)
	1287 iload (12, 2)
	1288 #19 (12, 2)
	1289 aaload (12, 2)
	1290 iload (12, 2)
	1291 #13 (12, 2)
	1292 daload (12, 2)
	1293 invokestatic (12, 2)
	1294 org/apache/commons/math3/util/FastMath.abs:(D)D (12, 2)
	1296 invokestatic (12, 2)
	1297 org/apache/commons/math3/util/FastMath.max:(DD)D (12, 2)
	1299 dstore (12, 2)
	1300 #26 (12, 2)
	1301 getstatic (13, 1)
	1302 org/apache/commons/math3/util/Precision.EPSILON:D (13, 1)
	1304 dload (13, 1)
	1305 #26 (13, 1)
	1306 dmul (13, 1)
	1307 dload (13, 1)
	1308 #26 (13, 1)
	1309 dmul (13, 1)
	1310 dconst_1 (13, 1)
	1311 dcmpl (13, 1)
	1312 ifle (13, 1)
	1313 46 (13, 1)
	1315 iload (14, 4)
	1316 #19 (14, 4)
	1317 istore (14, 4)
	1318 #28 (14, 4)
	1319 iload (14, 4)
	1320 #28 (14, 4)
	1321 iload (14, 4)
	1322 #13 (14, 4)
	1323 if_icmpgt (14, 4)
	1324 35 (14, 4)
	1326 aload_2 (14, 4)
	1327 iload (14, 4)
	1328 #28 (14, 4)
	1329 aaload (14, 4)
	1330 iload (14, 4)
	1331 #13 (14, 4)
	1332 iconst_1 (14, 4)
	1333 isub (14, 4)
	1334 dup2 (14, 4)
	1335 daload (14, 4)
	1336 dload (14, 4)
	1337 #26 (14, 4)
	1338 ddiv (14, 4)
	1339 dastore (14, 4)
	1340 aload_2 (14, 4)
	1341 iload (14, 4)
	1342 #28 (14, 4)
	1343 aaload (14, 4)
	1344 iload (14, 4)
	1345 #13 (14, 4)
	1346 dup2 (14, 4)
	1347 daload (14, 4)
	1348 dload (14, 4)
	1349 #26 (14, 4)
	1350 ddiv (14, 4)
	1351 dastore (14, 4)
	1352 iinc (14, 4)
	1353 #28 (14, 4)
	1354 -89 (14, 4)
	1355 goto (14, 4)
	1356 -36 (14, 4)
	1358 iinc (14, 4)
	1359 #19 (14, 4)
	1360 -89 (14, 4)
	1361 goto (14, 4)
	1362 -649 (14, 4)
	1364 iinc (14, 4)
	1365 #13 (14, 4)
	1366 -89 (14, 4)
	1367 goto (14, 4)
	1368 -1244 (14, 4)
	1370 iload (15, 4)
	1371 #4 (15, 4)
	1372 iconst_1 (15, 4)
	1373 isub (15, 4)
	1374 istore (15, 4)
	1375 #13 (15, 4)
	1376 iload (15, 4)
	1377 #13 (15, 4)
	1378 iflt (15, 4)
	1379 82 (15, 4)
	1381 iconst_0 (16, 4)
	1382 istore (16, 4)
	1383 #14 (16, 4)
	1384 iload (16, 4)
	1385 #14 (16, 4)
	1386 iload (16, 4)
	1387 #4 (16, 4)
	1388 iconst_1 (16, 4)
	1389 isub (16, 4)
	1390 if_icmpgt (16, 4)
	1391 64 (16, 4)
	1393 dconst_0 (16, 4)
	1394 dstore (16, 4)
	1395 #11 (16, 4)
	1396 iconst_0 (17, 4)
	1397 istore (17, 4)
	1398 #15 (17, 4)
	1399 iload (17, 4)
	1400 #15 (17, 4)
	1401 iload (17, 4)
	1402 #13 (17, 4)
	1403 iload (17, 4)
	1404 #4 (17, 4)
	1405 iconst_1 (17, 4)
	1406 isub (17, 4)
	1407 invokestatic (17, 4)
	1408 org/apache/commons/math3/util/FastMath.min:(II)I (17, 4)
	1410 if_icmpgt (17, 4)
	1411 29 (17, 4)
	1413 dload (17, 4)
	1414 #11 (17, 4)
	1415 aload_3 (17, 4)
	1416 iload (17, 4)
	1417 #14 (17, 4)
	1418 aaload (17, 4)
	1419 iload (17, 4)
	1420 #15 (17, 4)
	1421 daload (17, 4)
	1422 aload_2 (17, 4)
	1423 iload (17, 4)
	1424 #15 (17, 4)
	1425 aaload (17, 4)
	1426 iload (17, 4)
	1427 #13 (17, 4)
	1428 daload (17, 4)
	1429 dmul (17, 4)
	1430 dadd (17, 4)
	1431 dstore (17, 4)
	1432 #11 (17, 4)
	1433 iinc (17, 4)
	1434 #15 (17, 4)
	1435 -89 (17, 4)
	1436 goto (17, 4)
	1437 -37 (17, 4)
	1439 aload_3 (16, 4)
	1440 iload (16, 4)
	1441 #14 (16, 4)
	1442 aaload (16, 4)
	1443 iload (16, 4)
	1444 #13 (16, 4)
	1445 dload (16, 4)
	1446 #11 (16, 4)
	1447 dastore (16, 4)
	1448 iinc (16, 4)
	1449 #14 (16, 4)
	1450 -89 (16, 4)
	1451 goto (16, 4)
	1452 -67 (16, 4)
	1454 iinc (16, 4)
	1455 #13 (16, 4)
	1456 -89 (16, 4)
	1457 goto (16, 4)
	1458 -81 (16, 4)
	1460 aload_0 (15, 4)
	1461 iload (15, 4)
	1462 #4 (15, 4)
	1463 anewarray (15, 4)
	1464 org/apache/commons/math3/linear/ArrayRealVector (15, 4)
	1466 putfield (15, 4)
	1467 org/apache/commons/math3/linear/EigenDecomposition.eigenvectors:[Lorg/apache/commons/math3/linear/ArrayRealVector; (15, 4)
	1469 iload (15, 4)
	1470 #4 (15, 4)
	1471 newarray (15, 4)
	1472 7 (15, 4)
	1473 astore (15, 4)
	1474 #13 (15, 4)
	1475 iconst_0 (16, 4)
	1476 istore (16, 4)
	1477 #14 (16, 4)
	1478 iload (16, 4)
	1479 #14 (16, 4)
	1480 iload (16, 4)
	1481 #4 (16, 4)
	1482 if_icmpge (16, 4)
	1483 53 (16, 4)
	1485 iconst_0 (17, 4)
	1486 istore (17, 4)
	1487 #15 (17, 4)
	1488 iload (17, 4)
	1489 #15 (17, 4)
	1490 iload (17, 4)
	1491 #4 (17, 4)
	1492 if_icmpge (17, 4)
	1493 21 (17, 4)
	1495 aload (17, 4)
	1496 #13 (17, 4)
	1497 iload (17, 4)
	1498 #15 (17, 4)
	1499 aload_3 (17, 4)
	1500 iload (17, 4)
	1501 #15 (17, 4)
	1502 aaload (17, 4)
	1503 iload (17, 4)
	1504 #14 (17, 4)
	1505 daload (17, 4)
	1506 dastore (17, 4)
	1507 iinc (17, 4)
	1508 #15 (17, 4)
	1509 -89 (17, 4)
	1510 goto (17, 4)
	1511 -22 (17, 4)
	1513 aload_0 (16, 4)
	1514 getfield (16, 4)
	1515 org/apache/commons/math3/linear/EigenDecomposition.eigenvectors:[Lorg/apache/commons/math3/linear/ArrayRealVector; (16, 4)
	1517 iload (16, 4)
	1518 #14 (16, 4)
	1519 new (16, 4)
	1520 org/apache/commons/math3/linear/ArrayRealVector (16, 4)
	1522 dup (16, 4)
	1523 aload (16, 4)
	1524 #13 (16, 4)
	1525 invokespecial (16, 4)
	1526 org/apache/commons/math3/linear/ArrayRealVector.<init>:([D)V (16, 4)
	1528 aastore (16, 4)
	1529 iinc (16, 4)
	1530 #14 (16, 4)
	1531 -89 (16, 4)
	1532 goto (16, 4)
	1533 -54 (16, 4)
	1535 return (9, 4)

