Method: <init>
	0 aload_0 (0, 0)
	1 invokespecial (0, 0)
	2 java/lang/Object.<init>:()V (0, 0)
	4 aload_0 (0, 0)
	5 aload_1 (0, 0)
	6 putfield (0, 0)
	7 org/apache/commons/math3/linear/FieldLUDecomposition$Solver.field:Lorg/apache/commons/math3/Field; (0, 0)
	9 aload_0 (0, 0)
	10 aload_2 (0, 0)
	11 putfield (0, 0)
	12 org/apache/commons/math3/linear/FieldLUDecomposition$Solver.lu:[[Lorg/apache/commons/math3/FieldElement; (0, 0)
	14 aload_0 (0, 0)
	15 aload_3 (0, 0)
	16 putfield (0, 0)
	17 org/apache/commons/math3/linear/FieldLUDecomposition$Solver.pivot:[I (0, 0)
	19 aload_0 (0, 0)
	20 iload (0, 0)
	21 #4 (0, 0)
	22 putfield (0, 0)
	23 org/apache/commons/math3/linear/FieldLUDecomposition$Solver.singular:Z (0, 0)
	25 return (0, 0)

Method: isNonSingular
	0 aload_0 (0, 0)
	1 getfield (0, 0)
	2 org/apache/commons/math3/linear/FieldLUDecomposition$Solver.singular:Z (0, 0)
	4 ifne (0, 0)
	5 7 (0, 0)
	7 iconst_1 (0, 0)
	8 goto (0, 0)
	9 4 (0, 0)
	11 iconst_0 (0, 0)
	12 ireturn (0, 0)

Method: solve
	0 aload_0 (0, 0)
	1 getfield (0, 0)
	2 org/apache/commons/math3/linear/FieldLUDecomposition$Solver.pivot:[I (0, 0)
	4 arraylength (0, 0)
	5 istore_2 (0, 0)
	6 aload_1 (1, 1)
	7 invokeinterface (1, 1)
	8 org/apache/commons/math3/linear/FieldMatrix.getColumnDimension:()I (1, 1)
	10 0 (1, 1)
	12 iload_2 (1, 1)
	13 if_icmpeq (1, 1)
	14 18 (1, 1)
	16 new (1, 1)
	17 org/apache/commons/math3/exception/DimensionMismatchException (1, 1)
	19 dup (1, 1)
	20 aload_1 (1, 1)
	21 invokeinterface (1, 1)
	22 org/apache/commons/math3/linear/FieldMatrix.getColumnDimension:()I (1, 1)
	24 0 (1, 1)
	26 iload_2 (1, 1)
	27 invokespecial (1, 1)
	28 org/apache/commons/math3/exception/DimensionMismatchException.<init>:(II)V (1, 1)
	30 athrow (1, 1)
	31 aload_0 (1, 1)
	32 getfield (1, 1)
	33 org/apache/commons/math3/linear/FieldLUDecomposition$Solver.singular:Z (1, 1)
	35 ifeq (1, 1)
	36 11 (1, 1)
	38 new (1, 1)
	39 org/apache/commons/math3/linear/SingularMatrixException (1, 1)
	41 dup (1, 1)
	42 invokespecial (1, 1)
	43 org/apache/commons/math3/linear/SingularMatrixException.<init>:()V (1, 1)
	45 athrow (1, 1)
	46 aload_1 (0, 0)
	47 invokeinterface (0, 0)
	48 org/apache/commons/math3/linear/FieldMatrix.buildArray:(Lorg/apache/commons/math3/Field;II)[[Ljava/lang/Object; (0, 0)
	50 0 (0, 0)
	52 istore_3 (0, 0)
	53 aload_0 (0, 0)
	54 getfield (0, 0)
	55 org/apache/commons/math3/linear/FieldLUDecomposition$Solver.field:Lorg/apache/commons/math3/Field; (0, 0)
	57 iload_2 (0, 0)
	58 iload_3 (0, 0)
	59 invokestatic (0, 0)
	60 org/apache/commons/math3/util/MathArrays.buildArray:(Lorg/apache/commons/math3/Field;II)[[Ljava/lang/Object; (0, 0)
	62 checkcast (0, 0)
	63 [[Lorg/apache/commons/math3/FieldElement; (0, 0)
	65 astore (0, 0)
	66 #4 (0, 0)
	67 iconst_0 (1, 4)
	68 istore (1, 4)
	69 #5 (1, 4)
	70 iload (1, 4)
	71 #5 (1, 4)
	72 iload_2 (1, 4)
	73 if_icmpge (1, 4)
	74 55 (1, 4)
	76 aload (1, 4)
	77 #4 (1, 4)
	78 iload (1, 4)
	79 #5 (1, 4)
	80 aaload (1, 4)
	81 astore (1, 4)
	82 #6 (1, 4)
	83 aload_0 (1, 4)
	84 getfield (1, 4)
	85 org/apache/commons/math3/linear/FieldLUDecomposition$Solver.pivot:[I (1, 4)
	87 iload (1, 4)
	88 #5 (1, 4)
	89 iaload (1, 4)
	90 istore (1, 4)
	91 #7 (1, 4)
	92 iconst_0 (2, 4)
	93 istore (2, 4)
	94 #8 (2, 4)
	95 iload (2, 4)
	96 #8 (2, 4)
	97 iload_3 (2, 4)
	98 if_icmpge (2, 4)
	99 24 (2, 4)
	101 aload (2, 4)
	102 #6 (2, 4)
	103 iload (2, 4)
	104 #8 (2, 4)
	105 aload_1 (2, 4)
	106 iload (2, 4)
	107 #7 (2, 4)
	108 iload (2, 4)
	109 #8 (2, 4)
	110 invokeinterface (2, 4)
	111 org/apache/commons/math3/linear/FieldMatrix.org/apache/commons/math3/linear/Array2DRowFieldMatrix (2, 4)
	113 0 (2, 4)
	115 aastore (2, 4)
	116 iinc (2, 4)
	117 #8 (2, 4)
	118 -89 (2, 4)
	119 goto (2, 4)
	120 -24 (2, 4)
	122 iinc (2, 4)
	123 #5 (2, 4)
	124 -89 (2, 4)
	125 goto (2, 4)
	126 -55 (2, 4)
	128 iconst_0 (2, 4)
	129 istore (2, 4)
	130 #5 (2, 4)
	131 iload (2, 4)
	132 #5 (2, 4)
	133 iload_2 (2, 4)
	134 if_icmpge (2, 4)
	135 98 (2, 4)
	137 aload (2, 4)
	138 #4 (2, 4)
	139 iload (2, 4)
	140 #5 (2, 4)
	141 aaload (2, 4)
	142 astore (2, 4)
	143 #6 (2, 4)
	144 iload (3, 4)
	145 #5 (3, 4)
	146 iconst_1 (3, 4)
	147 iadd (3, 4)
	148 istore (3, 4)
	149 #7 (3, 4)
	150 iload (3, 4)
	151 #7 (3, 4)
	152 iload_2 (3, 4)
	153 if_icmpge (3, 4)
	154 73 (3, 4)
	156 aload (3, 4)
	157 #4 (3, 4)
	158 iload (3, 4)
	159 #7 (3, 4)
	160 aaload (3, 4)
	161 astore (3, 4)
	162 #8 (3, 4)
	163 aload_0 (3, 4)
	164 getfield (3, 4)
	165 org/apache/commons/math3/linear/FieldLUDecomposition$Solver.lu:[[Lorg/apache/commons/math3/FieldElement; (3, 4)
	167 iload (3, 4)
	168 #7 (3, 4)
	169 aaload (3, 4)
	170 iload (3, 4)
	171 #5 (3, 4)
	172 aaload (3, 4)
	173 astore (3, 4)
	174 #9 (3, 4)
	175 iconst_0 (4, 4)
	176 istore (4, 4)
	177 #10 (4, 4)
	178 iload (4, 4)
	179 #10 (4, 4)
	180 iload_3 (4, 4)
	181 if_icmpge (4, 4)
	182 39 (4, 4)
	184 aload (4, 4)
	185 #8 (4, 4)
	186 iload (4, 4)
	187 #10 (4, 4)
	188 aload (4, 4)
	189 #8 (4, 4)
	190 iload (4, 4)
	191 #10 (4, 4)
	192 aaload (4, 4)
	193 aload (4, 4)
	194 #6 (4, 4)
	195 iload (4, 4)
	196 #10 (4, 4)
	197 aaload (4, 4)
	198 aload (4, 4)
	199 #9 (4, 4)
	200 invokeinterface (4, 4)
	201 org/apache/commons/math3/FieldElement.subtract:(Ljava/lang/Object;)Ljava/lang/Object; (4, 4)
	203 0 (4, 4)
	205 invokeinterface (4, 4)
	206 org/apache/commons/math3/FieldElement.org/apache/commons/math3/FieldElement (4, 4)
	208 0 (4, 4)
	210 checkcast (4, 4)
	211 org/apache/commons/math3/FieldElement (4, 4)
	213 aastore (4, 4)
	214 iinc (4, 4)
	215 #10 (4, 4)
	216 -89 (4, 4)
	217 goto (4, 4)
	218 -39 (4, 4)
	220 iinc (4, 4)
	221 #7 (4, 4)
	222 -89 (4, 4)
	223 goto (4, 4)
	224 -73 (4, 4)
	226 iinc (4, 4)
	227 #5 (4, 4)
	228 -89 (4, 4)
	229 goto (4, 4)
	230 -98 (4, 4)
	232 iload_2 (4, 4)
	233 iconst_1 (4, 4)
	234 isub (4, 4)
	235 istore (4, 4)
	236 #5 (4, 4)
	237 iload (4, 4)
	238 #5 (4, 4)
	239 iflt (4, 4)
	240 143 (4, 4)
	242 aload (4, 4)
	243 #4 (4, 4)
	244 iload (4, 4)
	245 #5 (4, 4)
	246 aaload (4, 4)
	247 astore (4, 4)
	248 #6 (4, 4)
	249 aload_0 (4, 4)
	250 getfield (4, 4)
	251 org/apache/commons/math3/linear/FieldLUDecomposition$Solver.lu:[[Lorg/apache/commons/math3/FieldElement; (4, 4)
	253 iload (4, 4)
	254 #5 (4, 4)
	255 aaload (4, 4)
	256 iload (4, 4)
	257 #5 (4, 4)
	258 aaload (4, 4)
	259 astore (4, 4)
	260 #7 (4, 4)
	261 iconst_0 (5, 4)
	262 istore (5, 4)
	263 #8 (5, 4)
	264 iload (5, 4)
	265 #8 (5, 4)
	266 iload_3 (5, 4)
	267 if_icmpge (5, 4)
	268 29 (5, 4)
	270 aload (5, 4)
	271 #6 (5, 4)
	272 iload (5, 4)
	273 #8 (5, 4)
	274 aload (5, 4)
	275 #6 (5, 4)
	276 iload (5, 4)
	277 #8 (5, 4)
	278 aaload (5, 4)
	279 aload (5, 4)
	280 #7 (5, 4)
	281 invokeinterface (5, 4)
	282 org/apache/commons/math3/FieldElement.<init>:(Lorg/apache/commons/math3/Field;[Lorg/apache/commons/math3/FieldElement;Z)V (5, 4)
	284 0 (5, 4)
	286 checkcast (5, 4)
	287 org/apache/commons/math3/FieldElement (5, 4)
	289 aastore (5, 4)
	290 iinc (5, 4)
	291 #8 (5, 4)
	292 -89 (5, 4)
	293 goto (5, 4)
	294 -29 (5, 4)
	296 iconst_0 (5, 4)
	297 istore (5, 4)
	298 #8 (5, 4)
	299 iload (5, 4)
	300 #8 (5, 4)
	301 iload (5, 4)
	302 #5 (5, 4)
	303 if_icmpge (5, 4)
	304 73 (5, 4)
	306 aload (5, 4)
	307 #4 (5, 4)
	308 iload (5, 4)
	309 #8 (5, 4)
	310 aaload (5, 4)
	311 astore (5, 4)
	312 #9 (5, 4)
	313 aload_0 (5, 4)
	314 getfield (5, 4)
	315 org/apache/commons/math3/linear/FieldLUDecomposition$Solver.lu:[[Lorg/apache/commons/math3/FieldElement; (5, 4)
	317 iload (5, 4)
	318 #8 (5, 4)
	319 aaload (5, 4)
	320 iload (5, 4)
	321 #5 (5, 4)
	322 aaload (5, 4)
	323 astore (5, 4)
	324 #10 (5, 4)
	325 iconst_0 (6, 4)
	326 istore (6, 4)
	327 #11 (6, 4)
	328 iload (6, 4)
	329 #11 (6, 4)
	330 iload_3 (6, 4)
	331 if_icmpge (6, 4)
	332 39 (6, 4)
	334 aload (6, 4)
	335 #9 (6, 4)
	336 iload (6, 4)
	337 #11 (6, 4)
	338 aload (6, 4)
	339 #9 (6, 4)
	340 iload (6, 4)
	341 #11 (6, 4)
	342 aaload (6, 4)
	343 aload (6, 4)
	344 #6 (6, 4)
	345 iload (6, 4)
	346 #11 (6, 4)
	347 aaload (6, 4)
	348 aload (6, 4)
	349 #10 (6, 4)
	350 invokeinterface (6, 4)
	351 org/apache/commons/math3/FieldElement.subtract:(Ljava/lang/Object;)Ljava/lang/Object; (6, 4)
	353 0 (6, 4)
	355 invokeinterface (6, 4)
	356 org/apache/commons/math3/FieldElement.org/apache/commons/math3/FieldElement (6, 4)
	358 0 (6, 4)
	360 checkcast (6, 4)
	361 org/apache/commons/math3/FieldElement (6, 4)
	363 aastore (6, 4)
	364 iinc (6, 4)
	365 #11 (6, 4)
	366 -89 (6, 4)
	367 goto (6, 4)
	368 -39 (6, 4)
	370 iinc (6, 4)
	371 #8 (6, 4)
	372 -89 (6, 4)
	373 goto (6, 4)
	374 -74 (6, 4)
	376 iinc (6, 4)
	377 #5 (6, 4)
	378 -89 (6, 4)
	379 goto (6, 4)
	380 -142 (6, 4)
	382 new (5, 4)
	383 org/apache/commons/math3/linear/Array2DRowFieldMatrix (5, 4)
	385 dup (5, 4)
	386 aload_0 (5, 4)
	387 getfield (5, 4)
	388 org/apache/commons/math3/linear/FieldLUDecomposition$Solver.field:Lorg/apache/commons/math3/Field; (5, 4)
	390 aload (5, 4)
	391 #4 (5, 4)
	392 iconst_0 (5, 4)
	393 invokespecial (5, 4)
	394 org/apache/commons/math3/linear/Array2DRowFieldMatrix.<init>:(Lorg/apache/commons/math3/Field;[[Lorg/apache/commons/math3/FieldElement;Z)V (5, 4)
	396 areturn (5, 4)

Method: getInverse
	0 aload_0 (0, 0)
	1 getfield (0, 0)
	2 org/apache/commons/math3/linear/FieldLUDecomposition$Solver.pivot:[I (0, 0)
	4 arraylength (0, 0)
	5 istore_1 (0, 0)
	6 aload_0 (0, 0)
	7 getfield (0, 0)
	8 org/apache/commons/math3/linear/FieldLUDecomposition$Solver.field:Lorg/apache/commons/math3/Field; (0, 0)
	10 invokeinterface (0, 0)
	11 org/apache/commons/math3/Field.<init>:(Lorg/apache/commons/math3/Field;II)V (0, 0)
	13 0 (0, 0)
	15 checkcast (0, 0)
	16 org/apache/commons/math3/FieldElement (0, 0)
	18 astore_2 (0, 0)
	19 new (0, 0)
	20 org/apache/commons/math3/linear/Array2DRowFieldMatrix (0, 0)
	22 dup (0, 0)
	23 aload_0 (0, 0)
	24 getfield (0, 0)
	25 org/apache/commons/math3/linear/FieldLUDecomposition$Solver.field:Lorg/apache/commons/math3/Field; (0, 0)
	27 iload_1 (0, 0)
	28 iload_1 (0, 0)
	29 invokespecial (0, 0)
	30 org/apache/commons/math3/linear/Array2DRowFieldMatrix.<init>:(Lorg/apache/commons/math3/Field;II)V (0, 0)
	32 astore_3 (0, 0)
	33 iconst_0 (1, 4)
	34 istore (1, 4)
	35 #4 (1, 4)
	36 iload (1, 4)
	37 #4 (1, 4)
	38 iload_1 (1, 4)
	39 if_icmpge (1, 4)
	40 20 (1, 4)
	42 aload_3 (1, 4)
	43 iload (1, 4)
	44 #4 (1, 4)
	45 iload (1, 4)
	46 #4 (1, 4)
	47 aload_2 (1, 4)
	48 invokeinterface (1, 4)
	49 org/apache/commons/math3/linear/FieldMatrix.solve:(Lorg/apache/commons/math3/linear/FieldMatrix;)Lorg/apache/commons/math3/linear/FieldMatrix; (1, 4)
	51 0 (1, 4)
	53 iinc (1, 4)
	54 #4 (1, 4)
	55 -89 (1, 4)
	56 goto (1, 4)
	57 -20 (1, 4)
	59 aload_0 (0, 0)
	60 aload_3 (0, 0)
	61 invokevirtual (0, 0)
	62 org/apache/commons/math3/linear/FieldLUDecomposition$Solver.solve:(Lorg/apache/commons/math3/linear/FieldMatrix;)Lorg/apache/commons/math3/linear/FieldMatrix; (0, 0)
	64 areturn (0, 0)

