Method: <init>
	0 aload_0 (0, 0)
	1 invokespecial (0, 0)
	4 aload_1 (1, 1)
	5 invokeinterface (1, 1)
	10 ifne (1, 1)
	13 new (1, 1)
	16 dup (1, 1)
	17 aload_1 (1, 1)
	18 invokeinterface (1, 1)
	23 aload_1 (1, 1)
	24 invokeinterface (1, 1)
	29 invokespecial (1, 1)
	32 athrow (1, 1)
	33 aload_1 (0, 0)
	34 invokeinterface (0, 0)
	39 istore_2 (0, 0)
	40 aload_0 (0, 0)
	41 aload_1 (0, 0)
	42 invokeinterface (0, 0)
	47 putfield (0, 0)
	50 aload_0 (0, 0)
	51 aload_1 (0, 0)
	52 invokeinterface (0, 0)
	57 putfield (0, 0)
	60 aload_0 (0, 0)
	61 iload_2 (0, 0)
	62 newarray (0, 0)
	64 putfield (0, 0)
	67 aload_0 (0, 0)
	68 aconst_null (0, 0)
	69 putfield (0, 0)
	72 aload_0 (0, 0)
	73 aconst_null (0, 0)
	74 putfield (0, 0)
	77 aload_0 (0, 0)
	78 aconst_null (0, 0)
	79 putfield (0, 0)
	82 iconst_0 (1, 4)
	83 istore_3 (1, 4)
	84 iload_3 (1, 4)
	85 iload_2 (1, 4)
	86 if_icmpge (1, 4)
	89 aload_0 (1, 4)
	90 getfield (1, 4)
	93 iload_3 (1, 4)
	94 iload_3 (1, 4)
	95 iastore (1, 4)
	96 iinc (1, 4)
	99 goto (1, 4)
	102 aload_0 (0, 0)
	103 iconst_1 (0, 0)
	104 putfield (0, 0)
	107 aload_0 (0, 0)
	108 iconst_0 (0, 0)
	109 putfield (0, 0)
	112 iconst_0 (1, 4)
	113 istore_3 (1, 4)
	114 iload_3 (1, 4)
	115 iload_2 (1, 4)
	116 if_icmpge (1, 4)
	119 aload_0 (1, 4)
	120 getfield (1, 4)
	123 invokeinterface (1, 4)
	128 checkcast (1, 4)
	131 astore (1, 4)
	133 iconst_0 (2, 4)
	134 istore (2, 4)
	136 iload (2, 4)
	138 iload_3 (2, 4)
	139 if_icmpge (2, 4)
	142 aload_0 (2, 4)
	143 getfield (2, 4)
	146 iload (2, 4)
	148 aaload (2, 4)
	149 astore (2, 4)
	151 aload (2, 4)
	153 iload_3 (2, 4)
	154 aaload (2, 4)
	155 astore (2, 4)
	157 iconst_0 (3, 4)
	158 istore (3, 4)
	160 iload (3, 4)
	162 iload (3, 4)
	164 if_icmpge (3, 4)
	167 aload (3, 4)
	169 aload (3, 4)
	171 iload (3, 4)
	173 aaload (3, 4)
	174 aload_0 (3, 4)
	175 getfield (3, 4)
	178 iload (3, 4)
	180 aaload (3, 4)
	181 iload_3 (3, 4)
	182 aaload (3, 4)
	183 invokeinterface (3, 4)
	188 invokeinterface (3, 4)
	193 checkcast (3, 4)
	196 astore (3, 4)
	198 iinc (3, 4)
	201 goto (3, 4)
	204 aload (2, 4)
	206 iload_3 (2, 4)
	207 aload (2, 4)
	209 aastore (2, 4)
	210 iinc (2, 4)
	213 goto (2, 4)
	216 iload_3 (1, 4)
	217 istore (1, 4)
	219 iload_3 (2, 4)
	220 istore (2, 4)
	222 iload (2, 4)
	224 iload_2 (2, 4)
	225 if_icmpge (2, 4)
	228 aload_0 (2, 4)
	229 getfield (2, 4)
	232 iload (2, 4)
	234 aaload (2, 4)
	235 astore (2, 4)
	237 aload (2, 4)
	239 iload_3 (2, 4)
	240 aaload (2, 4)
	241 astore (2, 4)
	243 iconst_0 (3, 4)
	244 istore (3, 4)
	246 iload (3, 4)
	248 iload_3 (3, 4)
	249 if_icmpge (3, 4)
	252 aload (3, 4)
	254 aload (3, 4)
	256 iload (3, 4)
	258 aaload (3, 4)
	259 aload_0 (3, 4)
	260 getfield (3, 4)
	263 iload (3, 4)
	265 aaload (3, 4)
	266 iload_3 (3, 4)
	267 aaload (3, 4)
	268 invokeinterface (3, 4)
	273 invokeinterface (3, 4)
	278 checkcast (3, 4)
	281 astore (3, 4)
	283 iinc (3, 4)
	286 goto (3, 4)
	289 aload (2, 4)
	291 iload_3 (2, 4)
	292 aload (2, 4)
	294 aastore (2, 4)
	295 aload_0 (3, 1)
	296 getfield (3, 1)
	299 iload (3, 1)
	301 aaload (3, 1)
	302 iload_3 (3, 1)
	303 aaload (3, 1)
	304 aload_0 (3, 1)
	305 getfield (3, 1)
	308 invokeinterface (3, 1)
	313 invokevirtual (3, 1)
	316 ifeq (3, 1)
	319 iinc (3, 1)
	322 iinc (3, 1)
	325 goto (3, 1)
	328 iload (3, 1)
	330 iload_2 (3, 1)
	331 if_icmplt (3, 1)
	334 aload_0 (3, 1)
	335 iconst_1 (3, 1)
	336 putfield (3, 1)
	339 return (3, 1)
	340 iload (3, 1)
	342 iload_3 (3, 1)
	343 if_icmpeq (3, 1)
	346 aload_0 (3, 1)
	347 getfield (3, 1)
	350 invokeinterface (3, 1)
	355 checkcast (3, 1)
	358 astore (3, 1)
	360 iconst_0 (4, 4)
	361 istore (4, 4)
	363 iload (4, 4)
	365 iload_2 (4, 4)
	366 if_icmpge (4, 4)
	369 aload_0 (4, 4)
	370 getfield (4, 4)
	373 iload (4, 4)
	375 aaload (4, 4)
	376 iload (4, 4)
	378 aaload (4, 4)
	379 astore (4, 4)
	381 aload_0 (4, 4)
	382 getfield (4, 4)
	385 iload (4, 4)
	387 aaload (4, 4)
	388 iload (4, 4)
	390 aload_0 (4, 4)
	391 getfield (4, 4)
	394 iload_3 (4, 4)
	395 aaload (4, 4)
	396 iload (4, 4)
	398 aaload (4, 4)
	399 aastore (4, 4)
	400 aload_0 (4, 4)
	401 getfield (4, 4)
	404 iload_3 (4, 4)
	405 aaload (4, 4)
	406 iload (4, 4)
	408 aload (4, 4)
	410 aastore (4, 4)
	411 iinc (4, 4)
	414 goto (4, 4)
	417 aload_0 (3, 1)
	418 getfield (3, 1)
	421 iload (3, 1)
	423 iaload (3, 1)
	424 istore (3, 1)
	426 aload_0 (3, 1)
	427 getfield (3, 1)
	430 iload (3, 1)
	432 aload_0 (3, 1)
	433 getfield (3, 1)
	436 iload_3 (3, 1)
	437 iaload (3, 1)
	438 iastore (3, 1)
	439 aload_0 (3, 1)
	440 getfield (3, 1)
	443 iload_3 (3, 1)
	444 iload (3, 1)
	446 iastore (3, 1)
	447 aload_0 (3, 1)
	448 aload_0 (3, 1)
	449 getfield (3, 1)
	452 ifne (3, 1)
	455 iconst_1 (3, 1)
	456 goto (3, 1)
	459 iconst_0 (3, 1)
	460 putfield (3, 1)
	463 aload_0 (2, 1)
	464 getfield (2, 1)
	467 iload_3 (2, 1)
	468 aaload (2, 1)
	469 iload_3 (2, 1)
	470 aaload (2, 1)
	471 astore (2, 1)
	473 iload_3 (3, 4)
	474 iconst_1 (3, 4)
	475 iadd (3, 4)
	476 istore (3, 4)
	478 iload (3, 4)
	480 iload_2 (3, 4)
	481 if_icmpge (3, 4)
	484 aload_0 (3, 4)
	485 getfield (3, 4)
	488 iload (3, 4)
	490 aaload (3, 4)
	491 astore (3, 4)
	493 aload (3, 4)
	495 iload_3 (3, 4)
	496 aload (3, 4)
	498 iload_3 (3, 4)
	499 aaload (3, 4)
	500 aload (3, 4)
	502 invokeinterface (3, 4)
	507 checkcast (3, 4)
	510 aastore (3, 4)
	511 iinc (3, 4)
	514 goto (3, 4)
	517 iinc (3, 4)
	520 goto (3, 4)
	523 return (1, 1)

Method: getL
	0 aload_0 (1, 1)
	1 getfield (1, 1)
	4 ifnonnull (1, 1)
	7 aload_0 (1, 1)
	8 getfield (1, 1)
	11 ifne (1, 1)
	14 aload_0 (1, 1)
	15 getfield (1, 1)
	18 arraylength (1, 1)
	19 istore_1 (1, 1)
	20 aload_0 (1, 1)
	21 new (1, 1)
	24 dup (1, 1)
	25 aload_0 (1, 1)
	26 getfield (1, 1)
	29 iload_1 (1, 1)
	30 iload_1 (1, 1)
	31 invokespecial (1, 1)
	34 putfield (1, 1)
	37 iconst_0 (2, 4)
	38 istore_2 (2, 4)
	39 iload_2 (2, 4)
	40 iload_1 (2, 4)
	41 if_icmpge (2, 4)
	44 aload_0 (2, 4)
	45 getfield (2, 4)
	48 iload_2 (2, 4)
	49 aaload (2, 4)
	50 astore_3 (2, 4)
	51 iconst_0 (3, 4)
	52 istore (3, 4)
	54 iload (3, 4)
	56 iload_2 (3, 4)
	57 if_icmpge (3, 4)
	60 aload_0 (3, 4)
	61 getfield (3, 4)
	64 iload_2 (3, 4)
	65 iload (3, 4)
	67 aload_3 (3, 4)
	68 iload (3, 4)
	70 aaload (3, 4)
	71 invokeinterface (3, 4)
	76 iinc (3, 4)
	79 goto (3, 4)
	82 aload_0 (2, 4)
	83 getfield (2, 4)
	86 iload_2 (2, 4)
	87 iload_2 (2, 4)
	88 aload_0 (2, 4)
	89 getfield (2, 4)
	92 invokeinterface (2, 4)
	97 checkcast (2, 4)
	100 invokeinterface (2, 4)
	105 iinc (2, 4)
	108 goto (2, 4)
	111 aload_0 (0, 0)
	112 getfield (0, 0)
	115 areturn (0, 0)

Method: getU
	0 aload_0 (1, 1)
	1 getfield (1, 1)
	4 ifnonnull (1, 1)
	7 aload_0 (1, 1)
	8 getfield (1, 1)
	11 ifne (1, 1)
	14 aload_0 (1, 1)
	15 getfield (1, 1)
	18 arraylength (1, 1)
	19 istore_1 (1, 1)
	20 aload_0 (1, 1)
	21 new (1, 1)
	24 dup (1, 1)
	25 aload_0 (1, 1)
	26 getfield (1, 1)
	29 iload_1 (1, 1)
	30 iload_1 (1, 1)
	31 invokespecial (1, 1)
	34 putfield (1, 1)
	37 iconst_0 (2, 4)
	38 istore_2 (2, 4)
	39 iload_2 (2, 4)
	40 iload_1 (2, 4)
	41 if_icmpge (2, 4)
	44 aload_0 (2, 4)
	45 getfield (2, 4)
	48 iload_2 (2, 4)
	49 aaload (2, 4)
	50 astore_3 (2, 4)
	51 iload_2 (3, 4)
	52 istore (3, 4)
	54 iload (3, 4)
	56 iload_1 (3, 4)
	57 if_icmpge (3, 4)
	60 aload_0 (3, 4)
	61 getfield (3, 4)
	64 iload_2 (3, 4)
	65 iload (3, 4)
	67 aload_3 (3, 4)
	68 iload (3, 4)
	70 aaload (3, 4)
	71 invokeinterface (3, 4)
	76 iinc (3, 4)
	79 goto (3, 4)
	82 iinc (3, 4)
	85 goto (3, 4)
	88 aload_0 (1, 1)
	89 getfield (1, 1)
	92 areturn (1, 1)

Method: getP
	0 aload_0 (1, 1)
	1 getfield (1, 1)
	4 ifnonnull (1, 1)
	7 aload_0 (1, 1)
	8 getfield (1, 1)
	11 ifne (1, 1)
	14 aload_0 (1, 1)
	15 getfield (1, 1)
	18 arraylength (1, 1)
	19 istore_1 (1, 1)
	20 aload_0 (1, 1)
	21 new (1, 1)
	24 dup (1, 1)
	25 aload_0 (1, 1)
	26 getfield (1, 1)
	29 iload_1 (1, 1)
	30 iload_1 (1, 1)
	31 invokespecial (1, 1)
	34 putfield (1, 1)
	37 iconst_0 (2, 4)
	38 istore_2 (2, 4)
	39 iload_2 (2, 4)
	40 iload_1 (2, 4)
	41 if_icmpge (2, 4)
	44 aload_0 (2, 4)
	45 getfield (2, 4)
	48 iload_2 (2, 4)
	49 aload_0 (2, 4)
	50 getfield (2, 4)
	53 iload_2 (2, 4)
	54 iaload (2, 4)
	55 aload_0 (2, 4)
	56 getfield (2, 4)
	59 invokeinterface (2, 4)
	64 checkcast (2, 4)
	67 invokeinterface (2, 4)
	72 iinc (2, 4)
	75 goto (2, 4)
	78 aload_0 (0, 0)
	79 getfield (0, 0)
	82 areturn (0, 0)

Method: getPivot
	0 aload_0 (0, 0)
	1 getfield (0, 0)
	4 invokevirtual (0, 0)
	7 checkcast (0, 0)
	10 areturn (0, 0)

Method: getDeterminant
	0 aload_0 (1, 1)
	1 getfield (1, 1)
	4 ifeq (1, 1)
	7 aload_0 (1, 1)
	8 getfield (1, 1)
	11 invokeinterface (1, 1)
	16 checkcast (1, 1)
	19 areturn (1, 1)
	20 aload_0 (1, 2)
	21 getfield (1, 2)
	24 arraylength (1, 2)
	25 istore_1 (1, 2)
	26 aload_0 (1, 2)
	27 getfield (1, 2)
	30 ifeq (1, 2)
	33 aload_0 (1, 2)
	34 getfield (1, 2)
	37 invokeinterface (1, 2)
	42 checkcast (1, 2)
	45 goto (1, 2)
	48 aload_0 (1, 2)
	49 getfield (1, 2)
	52 invokeinterface (1, 2)
	57 checkcast (1, 2)
	60 aload_0 (1, 2)
	61 getfield (1, 2)
	64 invokeinterface (1, 2)
	69 invokeinterface (1, 2)
	74 checkcast (1, 2)
	77 astore_2 (1, 2)
	78 iconst_0 (2, 4)
	79 istore_3 (2, 4)
	80 iload_3 (2, 4)
	81 iload_1 (2, 4)
	82 if_icmpge (2, 4)
	85 aload_2 (2, 4)
	86 aload_0 (2, 4)
	87 getfield (2, 4)
	90 iload_3 (2, 4)
	91 aaload (2, 4)
	92 iload_3 (2, 4)
	93 aaload (2, 4)
	94 invokeinterface (2, 4)
	99 checkcast (2, 4)
	102 astore_2 (2, 4)
	103 iinc (2, 4)
	106 goto (2, 4)
	109 aload_2 (1, 2)
	110 areturn (1, 2)

Method: getSolver
	0 new (0, 0)
	3 dup (0, 0)
	4 aload_0 (0, 0)
	5 getfield (0, 0)
	8 aload_0 (0, 0)
	9 getfield (0, 0)
	12 aload_0 (0, 0)
	13 getfield (0, 0)
	16 aload_0 (0, 0)
	17 getfield (0, 0)
	20 aconst_null (0, 0)
	21 invokespecial (0, 0)
	24 areturn (0, 0)

