Method: <init>
	0 aload_0 (0, 0)
	1 invokespecial (0, 0)
	2 java/lang/Object.<init>:()V (0, 0)
	4 aload_1 (2, 1)
	5 invokeinterface (2, 1)
	6 org/apache/commons/math3/linear/FieldMatrix.org/apache/commons/math3/linear/NonSquareMatrixException (2, 1)
	8 0 (2, 1)
	10 ifne (2, 1)
	11 23 (2, 1)
	13 new (2, 1)
	14 org/apache/commons/math3/linear/NonSquareMatrixException (2, 1)
	16 dup (2, 1)
	17 aload_1 (2, 1)
	18 invokeinterface (2, 1)
	19 org/apache/commons/math3/linear/FieldMatrix.getColumnDimension:()I (2, 1)
	21 0 (2, 1)
	23 aload_1 (2, 1)
	24 invokeinterface (2, 1)
	25 org/apache/commons/math3/linear/FieldMatrix.<init>:(II)V (2, 1)
	27 0 (2, 1)
	29 invokespecial (2, 1)
	30 org/apache/commons/math3/linear/NonSquareMatrixException.<init>:(II)V (2, 1)
	32 athrow (2, 1)
	33 aload_1 (0, 0)
	34 invokeinterface (0, 0)
	35 org/apache/commons/math3/linear/FieldMatrix.<init>:(II)V (0, 0)
	37 0 (0, 0)
	39 istore_2 (0, 0)
	40 aload_0 (0, 0)
	41 aload_1 (0, 0)
	42 invokeinterface (0, 0)
	43 org/apache/commons/math3/linear/FieldMatrix.field:Lorg/apache/commons/math3/Field; (0, 0)
	45 0 (0, 0)
	47 putfield (0, 0)
	48 org/apache/commons/math3/linear/FieldLUDecomposition.field:Lorg/apache/commons/math3/Field; (0, 0)
	50 aload_0 (0, 0)
	51 aload_1 (0, 0)
	52 invokeinterface (0, 0)
	53 org/apache/commons/math3/linear/FieldMatrix.lu:[[Lorg/apache/commons/math3/FieldElement; (0, 0)
	55 0 (0, 0)
	57 putfield (0, 0)
	58 org/apache/commons/math3/linear/FieldLUDecomposition.lu:[[Lorg/apache/commons/math3/FieldElement; (0, 0)
	60 aload_0 (0, 0)
	61 iload_2 (0, 0)
	62 newarray (0, 0)
	63 10 (0, 0)
	64 putfield (0, 0)
	65 org/apache/commons/math3/linear/FieldLUDecomposition.pivot:[I (0, 0)
	67 aload_0 (0, 0)
	68 aconst_null (0, 0)
	69 putfield (0, 0)
	70 org/apache/commons/math3/linear/FieldLUDecomposition.cachedL:Lorg/apache/commons/math3/linear/FieldMatrix; (0, 0)
	72 aload_0 (0, 0)
	73 aconst_null (0, 0)
	74 putfield (0, 0)
	75 org/apache/commons/math3/linear/FieldLUDecomposition.cachedU:Lorg/apache/commons/math3/linear/FieldMatrix; (0, 0)
	77 aload_0 (0, 0)
	78 aconst_null (0, 0)
	79 putfield (0, 0)
	80 org/apache/commons/math3/linear/FieldLUDecomposition.cachedP:Lorg/apache/commons/math3/linear/FieldMatrix; (0, 0)
	82 iconst_0 (2, 4)
	83 istore_3 (2, 4)
	84 iload_3 (2, 4)
	85 iload_2 (2, 4)
	86 if_icmpge (2, 4)
	87 16 (2, 4)
	89 aload_0 (2, 4)
	90 getfield (2, 4)
	91 org/apache/commons/math3/linear/FieldLUDecomposition.pivot:[I (2, 4)
	93 iload_3 (2, 4)
	94 iload_3 (2, 4)
	95 iastore (2, 4)
	96 iinc (2, 4)
	97 #3 (2, 4)
	98 -89 (2, 4)
	99 goto (2, 4)
	100 -15 (2, 4)
	102 aload_0 (0, 0)
	103 iconst_1 (0, 0)
	104 putfield (0, 0)
	105 org/apache/commons/math3/linear/FieldLUDecomposition.even:Z (0, 0)
	107 aload_0 (0, 0)
	108 iconst_0 (0, 0)
	109 putfield (0, 0)
	110 org/apache/commons/math3/linear/FieldLUDecomposition.singular:Z (0, 0)
	112 iconst_0 (2, 4)
	113 istore_3 (2, 4)
	114 iload_3 (2, 4)
	115 iload_2 (2, 4)
	116 if_icmpge (2, 4)
	117 407 (2, 4)
	119 aload_0 (2, 4)
	120 getfield (2, 4)
	121 org/apache/commons/math3/linear/FieldLUDecomposition.field:Lorg/apache/commons/math3/Field; (2, 4)
	123 invokeinterface (2, 4)
	124 org/apache/commons/math3/Field.org/apache/commons/math3/FieldElement (2, 4)
	126 0 (2, 4)
	128 checkcast (2, 4)
	129 org/apache/commons/math3/FieldElement (2, 4)
	131 astore (2, 4)
	132 #4 (2, 4)
	133 iconst_0 (3, 4)
	134 istore (3, 4)
	135 #5 (3, 4)
	136 iload (3, 4)
	137 #5 (3, 4)
	138 iload_3 (3, 4)
	139 if_icmpge (3, 4)
	140 77 (3, 4)
	142 aload_0 (3, 4)
	143 getfield (3, 4)
	144 org/apache/commons/math3/linear/FieldLUDecomposition.lu:[[Lorg/apache/commons/math3/FieldElement; (3, 4)
	146 iload (3, 4)
	147 #5 (3, 4)
	148 aaload (3, 4)
	149 astore (3, 4)
	150 #6 (3, 4)
	151 aload (3, 4)
	152 #6 (3, 4)
	153 iload_3 (3, 4)
	154 aaload (3, 4)
	155 astore (3, 4)
	156 #4 (3, 4)
	157 iconst_0 (4, 4)
	158 istore (4, 4)
	159 #7 (4, 4)
	160 iload (4, 4)
	161 #7 (4, 4)
	162 iload (4, 4)
	163 #5 (4, 4)
	164 if_icmpge (4, 4)
	165 40 (4, 4)
	167 aload (4, 4)
	168 #4 (4, 4)
	169 aload (4, 4)
	170 #6 (4, 4)
	171 iload (4, 4)
	172 #7 (4, 4)
	173 aaload (4, 4)
	174 aload_0 (4, 4)
	175 getfield (4, 4)
	176 org/apache/commons/math3/linear/FieldLUDecomposition.lu:[[Lorg/apache/commons/math3/FieldElement; (4, 4)
	178 iload (4, 4)
	179 #7 (4, 4)
	180 aaload (4, 4)
	181 iload_3 (4, 4)
	182 aaload (4, 4)
	183 invokeinterface (4, 4)
	184 org/apache/commons/math3/FieldElement.subtract:(Ljava/lang/Object;)Ljava/lang/Object; (4, 4)
	186 0 (4, 4)
	188 invokeinterface (4, 4)
	189 org/apache/commons/math3/FieldElement.equals:(Ljava/lang/Object;)Z (4, 4)
	191 0 (4, 4)
	193 checkcast (4, 4)
	194 org/apache/commons/math3/FieldElement (4, 4)
	196 astore (4, 4)
	197 #4 (4, 4)
	198 iinc (4, 4)
	199 #7 (4, 4)
	200 -89 (4, 4)
	201 goto (4, 4)
	202 -41 (4, 4)
	204 aload (3, 4)
	205 #6 (3, 4)
	206 iload_3 (3, 4)
	207 aload (3, 4)
	208 #4 (3, 4)
	209 aastore (3, 4)
	210 iinc (3, 4)
	211 #5 (3, 4)
	212 -89 (3, 4)
	213 goto (3, 4)
	214 -77 (3, 4)
	216 iload_3 (2, 4)
	217 istore (2, 4)
	218 #5 (2, 4)
	219 iload_3 (3, 4)
	220 istore (3, 4)
	221 #6 (3, 4)
	222 iload (3, 4)
	223 #6 (3, 4)
	224 iload_2 (3, 4)
	225 if_icmpge (3, 4)
	226 103 (3, 4)
	228 aload_0 (3, 4)
	229 getfield (3, 4)
	230 org/apache/commons/math3/linear/FieldLUDecomposition.lu:[[Lorg/apache/commons/math3/FieldElement; (3, 4)
	232 iload (3, 4)
	233 #6 (3, 4)
	234 aaload (3, 4)
	235 astore (3, 4)
	236 #7 (3, 4)
	237 aload (3, 4)
	238 #7 (3, 4)
	239 iload_3 (3, 4)
	240 aaload (3, 4)
	241 astore (3, 4)
	242 #4 (3, 4)
	243 iconst_0 (4, 4)
	244 istore (4, 4)
	245 #8 (4, 4)
	246 iload (4, 4)
	247 #8 (4, 4)
	248 iload_3 (4, 4)
	249 if_icmpge (4, 4)
	250 40 (4, 4)
	252 aload (4, 4)
	253 #4 (4, 4)
	254 aload (4, 4)
	255 #7 (4, 4)
	256 iload (4, 4)
	257 #8 (4, 4)
	258 aaload (4, 4)
	259 aload_0 (4, 4)
	260 getfield (4, 4)
	261 org/apache/commons/math3/linear/FieldLUDecomposition.lu:[[Lorg/apache/commons/math3/FieldElement; (4, 4)
	263 iload (4, 4)
	264 #8 (4, 4)
	265 aaload (4, 4)
	266 iload_3 (4, 4)
	267 aaload (4, 4)
	268 invokeinterface (4, 4)
	269 org/apache/commons/math3/FieldElement.subtract:(Ljava/lang/Object;)Ljava/lang/Object; (4, 4)
	271 0 (4, 4)
	273 invokeinterface (4, 4)
	274 org/apache/commons/math3/FieldElement.equals:(Ljava/lang/Object;)Z (4, 4)
	276 0 (4, 4)
	278 checkcast (4, 4)
	279 org/apache/commons/math3/FieldElement (4, 4)
	281 astore (4, 4)
	282 #4 (4, 4)
	283 iinc (4, 4)
	284 #8 (4, 4)
	285 -89 (4, 4)
	286 goto (4, 4)
	287 -40 (4, 4)
	289 aload (3, 4)
	290 #7 (3, 4)
	291 iload_3 (3, 4)
	292 aload (3, 4)
	293 #4 (3, 4)
	294 aastore (3, 4)
	295 aload_0 (4, 1)
	296 getfield (4, 1)
	297 org/apache/commons/math3/linear/FieldLUDecomposition.lu:[[Lorg/apache/commons/math3/FieldElement; (4, 1)
	299 iload (4, 1)
	300 #5 (4, 1)
	301 aaload (4, 1)
	302 iload_3 (4, 1)
	303 aaload (4, 1)
	304 aload_0 (4, 1)
	305 getfield (4, 1)
	306 org/apache/commons/math3/linear/FieldLUDecomposition.field:Lorg/apache/commons/math3/Field; (4, 1)
	308 invokeinterface (4, 1)
	309 org/apache/commons/math3/Field.org/apache/commons/math3/FieldElement (4, 1)
	311 0 (4, 1)
	313 invokevirtual (4, 1)
	314 java/lang/Object.equals:(Ljava/lang/Object;)Z (4, 1)
	316 ifeq (4, 1)
	317 6 (4, 1)
	319 iinc (4, 1)
	320 #5 (4, 1)
	321 -124 (4, 1)
	322 iinc (4, 1)
	323 #6 (4, 1)
	324 -89 (4, 1)
	325 goto (4, 1)
	326 -103 (4, 1)
	328 iload (4, 1)
	329 #5 (4, 1)
	330 iload_2 (4, 1)
	331 if_icmplt (4, 1)
	332 9 (4, 1)
	334 aload_0 (4, 1)
	335 iconst_1 (4, 1)
	336 putfield (4, 1)
	337 org/apache/commons/math3/linear/FieldLUDecomposition.singular:Z (4, 1)
	339 return (4, 1)
	340 iload (4, 1)
	341 #5 (4, 1)
	342 iload_3 (4, 1)
	343 if_icmpeq (4, 1)
	344 120 (4, 1)
	346 aload_0 (4, 1)
	347 getfield (4, 1)
	348 org/apache/commons/math3/linear/FieldLUDecomposition.field:Lorg/apache/commons/math3/Field; (4, 1)
	350 invokeinterface (4, 1)
	351 org/apache/commons/math3/Field.org/apache/commons/math3/FieldElement (4, 1)
	353 0 (4, 1)
	355 checkcast (4, 1)
	356 org/apache/commons/math3/FieldElement (4, 1)
	358 astore (4, 1)
	359 #6 (4, 1)
	360 iconst_0 (5, 4)
	361 istore (5, 4)
	362 #7 (5, 4)
	363 iload (5, 4)
	364 #7 (5, 4)
	365 iload_2 (5, 4)
	366 if_icmpge (5, 4)
	367 51 (5, 4)
	369 aload_0 (5, 4)
	370 getfield (5, 4)
	371 org/apache/commons/math3/linear/FieldLUDecomposition.lu:[[Lorg/apache/commons/math3/FieldElement; (5, 4)
	373 iload (5, 4)
	374 #5 (5, 4)
	375 aaload (5, 4)
	376 iload (5, 4)
	377 #7 (5, 4)
	378 aaload (5, 4)
	379 astore (5, 4)
	380 #6 (5, 4)
	381 aload_0 (5, 4)
	382 getfield (5, 4)
	383 org/apache/commons/math3/linear/FieldLUDecomposition.lu:[[Lorg/apache/commons/math3/FieldElement; (5, 4)
	385 iload (5, 4)
	386 #5 (5, 4)
	387 aaload (5, 4)
	388 iload (5, 4)
	389 #7 (5, 4)
	390 aload_0 (5, 4)
	391 getfield (5, 4)
	392 org/apache/commons/math3/linear/FieldLUDecomposition.lu:[[Lorg/apache/commons/math3/FieldElement; (5, 4)
	394 iload_3 (5, 4)
	395 aaload (5, 4)
	396 iload (5, 4)
	397 #7 (5, 4)
	398 aaload (5, 4)
	399 aastore (5, 4)
	400 aload_0 (5, 4)
	401 getfield (5, 4)
	402 org/apache/commons/math3/linear/FieldLUDecomposition.lu:[[Lorg/apache/commons/math3/FieldElement; (5, 4)
	404 iload_3 (5, 4)
	405 aaload (5, 4)
	406 iload (5, 4)
	407 #7 (5, 4)
	408 aload (5, 4)
	409 #6 (5, 4)
	410 aastore (5, 4)
	411 iinc (5, 4)
	412 #7 (5, 4)
	413 -89 (5, 4)
	414 goto (5, 4)
	415 -51 (5, 4)
	417 aload_0 (4, 1)
	418 getfield (4, 1)
	419 org/apache/commons/math3/linear/FieldLUDecomposition.pivot:[I (4, 1)
	421 iload (4, 1)
	422 #5 (4, 1)
	423 iaload (4, 1)
	424 istore (4, 1)
	425 #7 (4, 1)
	426 aload_0 (4, 1)
	427 getfield (4, 1)
	428 org/apache/commons/math3/linear/FieldLUDecomposition.pivot:[I (4, 1)
	430 iload (4, 1)
	431 #5 (4, 1)
	432 aload_0 (4, 1)
	433 getfield (4, 1)
	434 org/apache/commons/math3/linear/FieldLUDecomposition.pivot:[I (4, 1)
	436 iload_3 (4, 1)
	437 iaload (4, 1)
	438 iastore (4, 1)
	439 aload_0 (4, 1)
	440 getfield (4, 1)
	441 org/apache/commons/math3/linear/FieldLUDecomposition.pivot:[I (4, 1)
	443 iload_3 (4, 1)
	444 iload (4, 1)
	445 #7 (4, 1)
	446 iastore (4, 1)
	447 aload_0 (4, 1)
	448 aload_0 (4, 1)
	449 getfield (4, 1)
	450 org/apache/commons/math3/linear/FieldLUDecomposition.even:Z (4, 1)
	452 ifne (4, 1)
	453 7 (4, 1)
	455 iconst_1 (4, 1)
	456 goto (4, 1)
	457 4 (4, 1)
	459 iconst_0 (4, 1)
	460 putfield (4, 1)
	461 org/apache/commons/math3/linear/FieldLUDecomposition.even:Z (4, 1)
	463 aload_0 (3, 1)
	464 getfield (3, 1)
	465 org/apache/commons/math3/linear/FieldLUDecomposition.lu:[[Lorg/apache/commons/math3/FieldElement; (3, 1)
	467 iload_3 (3, 1)
	468 aaload (3, 1)
	469 iload_3 (3, 1)
	470 aaload (3, 1)
	471 astore (3, 1)
	472 #6 (3, 1)
	473 iload_3 (4, 4)
	474 iconst_1 (4, 4)
	475 iadd (4, 4)
	476 istore (4, 4)
	477 #7 (4, 4)
	478 iload (4, 4)
	479 #7 (4, 4)
	480 iload_2 (4, 4)
	481 if_icmpge (4, 4)
	482 36 (4, 4)
	484 aload_0 (4, 4)
	485 getfield (4, 4)
	486 org/apache/commons/math3/linear/FieldLUDecomposition.lu:[[Lorg/apache/commons/math3/FieldElement; (4, 4)
	488 iload (4, 4)
	489 #7 (4, 4)
	490 aaload (4, 4)
	491 astore (4, 4)
	492 #8 (4, 4)
	493 aload (4, 4)
	494 #8 (4, 4)
	495 iload_3 (4, 4)
	496 aload (4, 4)
	497 #8 (4, 4)
	498 iload_3 (4, 4)
	499 aaload (4, 4)
	500 aload (4, 4)
	501 #6 (4, 4)
	502 invokeinterface (4, 4)
	503 org/apache/commons/math3/FieldElement.org/apache/commons/math3/linear/Array2DRowFieldMatrix (4, 4)
	505 0 (4, 4)
	507 checkcast (4, 4)
	508 org/apache/commons/math3/FieldElement (4, 4)
	510 aastore (4, 4)
	511 iinc (4, 4)
	512 #7 (4, 4)
	513 -89 (4, 4)
	514 goto (4, 4)
	515 -36 (4, 4)
	517 iinc (4, 4)
	518 #3 (4, 4)
	519 -89 (4, 4)
	520 goto (4, 4)
	521 -406 (4, 4)
	523 return (2, 4)

Method: getL
	0 aload_0 (1, 1)
	1 getfield (1, 1)
	2 org/apache/commons/math3/linear/FieldLUDecomposition.cachedL:Lorg/apache/commons/math3/linear/FieldMatrix; (1, 1)
	4 ifnonnull (1, 1)
	5 107 (1, 1)
	7 aload_0 (1, 1)
	8 getfield (1, 1)
	9 org/apache/commons/math3/linear/FieldLUDecomposition.singular:Z (1, 1)
	11 ifne (1, 1)
	12 100 (1, 1)
	14 aload_0 (1, 1)
	15 getfield (1, 1)
	16 org/apache/commons/math3/linear/FieldLUDecomposition.pivot:[I (1, 1)
	18 arraylength (1, 1)
	19 istore_1 (1, 1)
	20 aload_0 (1, 1)
	21 new (1, 1)
	22 org/apache/commons/math3/linear/Array2DRowFieldMatrix (1, 1)
	24 dup (1, 1)
	25 aload_0 (1, 1)
	26 getfield (1, 1)
	27 org/apache/commons/math3/linear/FieldLUDecomposition.field:Lorg/apache/commons/math3/Field; (1, 1)
	29 iload_1 (1, 1)
	30 iload_1 (1, 1)
	31 invokespecial (1, 1)
	32 org/apache/commons/math3/linear/Array2DRowFieldMatrix.<init>:(Lorg/apache/commons/math3/Field;II)V (1, 1)
	34 putfield (1, 1)
	35 org/apache/commons/math3/linear/FieldLUDecomposition.cachedL:Lorg/apache/commons/math3/linear/FieldMatrix; (1, 1)
	37 iconst_0 (2, 4)
	38 istore_2 (2, 4)
	39 iload_2 (2, 4)
	40 iload_1 (2, 4)
	41 if_icmpge (2, 4)
	42 70 (2, 4)
	44 aload_0 (2, 4)
	45 getfield (2, 4)
	46 org/apache/commons/math3/linear/FieldLUDecomposition.lu:[[Lorg/apache/commons/math3/FieldElement; (2, 4)
	48 iload_2 (2, 4)
	49 aaload (2, 4)
	50 astore_3 (2, 4)
	51 iconst_0 (3, 4)
	52 istore (3, 4)
	53 #4 (3, 4)
	54 iload (3, 4)
	55 #4 (3, 4)
	56 iload_2 (3, 4)
	57 if_icmpge (3, 4)
	58 25 (3, 4)
	60 aload_0 (3, 4)
	61 getfield (3, 4)
	62 org/apache/commons/math3/linear/FieldLUDecomposition.cachedL:Lorg/apache/commons/math3/linear/FieldMatrix; (3, 4)
	64 iload_2 (3, 4)
	65 iload (3, 4)
	66 #4 (3, 4)
	67 aload_3 (3, 4)
	68 iload (3, 4)
	69 #4 (3, 4)
	70 aaload (3, 4)
	71 invokeinterface (3, 4)
	72 org/apache/commons/math3/linear/FieldMatrix.getOne:()Ljava/lang/Object; (3, 4)
	74 0 (3, 4)
	76 iinc (3, 4)
	77 #4 (3, 4)
	78 -89 (3, 4)
	79 goto (3, 4)
	80 -25 (3, 4)
	82 aload_0 (2, 4)
	83 getfield (2, 4)
	84 org/apache/commons/math3/linear/FieldLUDecomposition.cachedL:Lorg/apache/commons/math3/linear/FieldMatrix; (2, 4)
	86 iload_2 (2, 4)
	87 iload_2 (2, 4)
	88 aload_0 (2, 4)
	89 getfield (2, 4)
	90 org/apache/commons/math3/linear/FieldLUDecomposition.field:Lorg/apache/commons/math3/Field; (2, 4)
	92 invokeinterface (2, 4)
	93 org/apache/commons/math3/Field.[I (2, 4)
	95 0 (2, 4)
	97 checkcast (2, 4)
	98 org/apache/commons/math3/FieldElement (2, 4)
	100 invokeinterface (2, 4)
	101 org/apache/commons/math3/linear/FieldMatrix.getOne:()Ljava/lang/Object; (2, 4)
	103 0 (2, 4)
	105 iinc (2, 4)
	106 #2 (2, 4)
	107 -89 (2, 4)
	108 goto (2, 4)
	109 -69 (2, 4)
	111 aload_0 (0, 0)
	112 getfield (0, 0)
	113 org/apache/commons/math3/linear/FieldLUDecomposition.cachedL:Lorg/apache/commons/math3/linear/FieldMatrix; (0, 0)
	115 areturn (0, 0)

Method: getU
	0 aload_0 (1, 1)
	1 getfield (1, 1)
	2 org/apache/commons/math3/linear/FieldLUDecomposition.cachedU:Lorg/apache/commons/math3/linear/FieldMatrix; (1, 1)
	4 ifnonnull (1, 1)
	5 84 (1, 1)
	7 aload_0 (1, 1)
	8 getfield (1, 1)
	9 org/apache/commons/math3/linear/FieldLUDecomposition.singular:Z (1, 1)
	11 ifne (1, 1)
	12 77 (1, 1)
	14 aload_0 (1, 1)
	15 getfield (1, 1)
	16 org/apache/commons/math3/linear/FieldLUDecomposition.pivot:[I (1, 1)
	18 arraylength (1, 1)
	19 istore_1 (1, 1)
	20 aload_0 (1, 1)
	21 new (1, 1)
	22 org/apache/commons/math3/linear/Array2DRowFieldMatrix (1, 1)
	24 dup (1, 1)
	25 aload_0 (1, 1)
	26 getfield (1, 1)
	27 org/apache/commons/math3/linear/FieldLUDecomposition.field:Lorg/apache/commons/math3/Field; (1, 1)
	29 iload_1 (1, 1)
	30 iload_1 (1, 1)
	31 invokespecial (1, 1)
	32 org/apache/commons/math3/linear/Array2DRowFieldMatrix.<init>:(Lorg/apache/commons/math3/Field;II)V (1, 1)
	34 putfield (1, 1)
	35 org/apache/commons/math3/linear/FieldLUDecomposition.cachedU:Lorg/apache/commons/math3/linear/FieldMatrix; (1, 1)
	37 iconst_0 (2, 4)
	38 istore_2 (2, 4)
	39 iload_2 (2, 4)
	40 iload_1 (2, 4)
	41 if_icmpge (2, 4)
	42 47 (2, 4)
	44 aload_0 (2, 4)
	45 getfield (2, 4)
	46 org/apache/commons/math3/linear/FieldLUDecomposition.lu:[[Lorg/apache/commons/math3/FieldElement; (2, 4)
	48 iload_2 (2, 4)
	49 aaload (2, 4)
	50 astore_3 (2, 4)
	51 iload_2 (3, 4)
	52 istore (3, 4)
	53 #4 (3, 4)
	54 iload (3, 4)
	55 #4 (3, 4)
	56 iload_1 (3, 4)
	57 if_icmpge (3, 4)
	58 25 (3, 4)
	60 aload_0 (3, 4)
	61 getfield (3, 4)
	62 org/apache/commons/math3/linear/FieldLUDecomposition.cachedU:Lorg/apache/commons/math3/linear/FieldMatrix; (3, 4)
	64 iload_2 (3, 4)
	65 iload (3, 4)
	66 #4 (3, 4)
	67 aload_3 (3, 4)
	68 iload (3, 4)
	69 #4 (3, 4)
	70 aaload (3, 4)
	71 invokeinterface (3, 4)
	72 org/apache/commons/math3/linear/FieldMatrix.getOne:()Ljava/lang/Object; (3, 4)
	74 0 (3, 4)
	76 iinc (3, 4)
	77 #4 (3, 4)
	78 -89 (3, 4)
	79 goto (3, 4)
	80 -25 (3, 4)
	82 iinc (3, 4)
	83 #2 (3, 4)
	84 -89 (3, 4)
	85 goto (3, 4)
	86 -46 (3, 4)
	88 aload_0 (1, 1)
	89 getfield (1, 1)
	90 org/apache/commons/math3/linear/FieldLUDecomposition.cachedU:Lorg/apache/commons/math3/linear/FieldMatrix; (1, 1)
	92 areturn (1, 1)

Method: getP
	0 aload_0 (1, 1)
	1 getfield (1, 1)
	2 org/apache/commons/math3/linear/FieldLUDecomposition.cachedP:Lorg/apache/commons/math3/linear/FieldMatrix; (1, 1)
	4 ifnonnull (1, 1)
	5 74 (1, 1)
	7 aload_0 (1, 1)
	8 getfield (1, 1)
	9 org/apache/commons/math3/linear/FieldLUDecomposition.singular:Z (1, 1)
	11 ifne (1, 1)
	12 67 (1, 1)
	14 aload_0 (1, 1)
	15 getfield (1, 1)
	16 org/apache/commons/math3/linear/FieldLUDecomposition.pivot:[I (1, 1)
	18 arraylength (1, 1)
	19 istore_1 (1, 1)
	20 aload_0 (1, 1)
	21 new (1, 1)
	22 org/apache/commons/math3/linear/Array2DRowFieldMatrix (1, 1)
	24 dup (1, 1)
	25 aload_0 (1, 1)
	26 getfield (1, 1)
	27 org/apache/commons/math3/linear/FieldLUDecomposition.field:Lorg/apache/commons/math3/Field; (1, 1)
	29 iload_1 (1, 1)
	30 iload_1 (1, 1)
	31 invokespecial (1, 1)
	32 org/apache/commons/math3/linear/Array2DRowFieldMatrix.<init>:(Lorg/apache/commons/math3/Field;II)V (1, 1)
	34 putfield (1, 1)
	35 org/apache/commons/math3/linear/FieldLUDecomposition.cachedP:Lorg/apache/commons/math3/linear/FieldMatrix; (1, 1)
	37 iconst_0 (2, 4)
	38 istore_2 (2, 4)
	39 iload_2 (2, 4)
	40 iload_1 (2, 4)
	41 if_icmpge (2, 4)
	42 37 (2, 4)
	44 aload_0 (2, 4)
	45 getfield (2, 4)
	46 org/apache/commons/math3/linear/FieldLUDecomposition.cachedP:Lorg/apache/commons/math3/linear/FieldMatrix; (2, 4)
	48 iload_2 (2, 4)
	49 aload_0 (2, 4)
	50 getfield (2, 4)
	51 org/apache/commons/math3/linear/FieldLUDecomposition.pivot:[I (2, 4)
	53 iload_2 (2, 4)
	54 iaload (2, 4)
	55 aload_0 (2, 4)
	56 getfield (2, 4)
	57 org/apache/commons/math3/linear/FieldLUDecomposition.field:Lorg/apache/commons/math3/Field; (2, 4)
	59 invokeinterface (2, 4)
	60 org/apache/commons/math3/Field.[I (2, 4)
	62 0 (2, 4)
	64 checkcast (2, 4)
	65 org/apache/commons/math3/FieldElement (2, 4)
	67 invokeinterface (2, 4)
	68 org/apache/commons/math3/linear/FieldMatrix.getOne:()Ljava/lang/Object; (2, 4)
	70 0 (2, 4)
	72 iinc (2, 4)
	73 #2 (2, 4)
	74 -89 (2, 4)
	75 goto (2, 4)
	76 -36 (2, 4)
	78 aload_0 (0, 0)
	79 getfield (0, 0)
	80 org/apache/commons/math3/linear/FieldLUDecomposition.cachedP:Lorg/apache/commons/math3/linear/FieldMatrix; (0, 0)
	82 areturn (0, 0)

Method: getPivot
	0 aload_0 (0, 0)
	1 getfield (0, 0)
	2 org/apache/commons/math3/linear/FieldLUDecomposition.pivot:[I (0, 0)
	4 invokevirtual (0, 0)
	5 [I.clone:()Ljava/lang/Object; (0, 0)
	7 checkcast (0, 0)
	8 [I (0, 0)
	10 areturn (0, 0)

Method: getDeterminant
	0 aload_0 (1, 1)
	1 getfield (1, 1)
	2 org/apache/commons/math3/linear/FieldLUDecomposition.singular:Z (1, 1)
	4 ifeq (1, 1)
	5 16 (1, 1)
	7 aload_0 (1, 1)
	8 getfield (1, 1)
	9 org/apache/commons/math3/linear/FieldLUDecomposition.field:Lorg/apache/commons/math3/Field; (1, 1)
	11 invokeinterface (1, 1)
	12 org/apache/commons/math3/Field.org/apache/commons/math3/FieldElement (1, 1)
	14 0 (1, 1)
	16 checkcast (1, 1)
	17 org/apache/commons/math3/FieldElement (1, 1)
	19 areturn (1, 1)
	20 aload_0 (1, 2)
	21 getfield (1, 2)
	22 org/apache/commons/math3/linear/FieldLUDecomposition.pivot:[I (1, 2)
	24 arraylength (1, 2)
	25 istore_1 (1, 2)
	26 aload_0 (1, 2)
	27 getfield (1, 2)
	28 org/apache/commons/math3/linear/FieldLUDecomposition.even:Z (1, 2)
	30 ifeq (1, 2)
	31 18 (1, 2)
	33 aload_0 (1, 2)
	34 getfield (1, 2)
	35 org/apache/commons/math3/linear/FieldLUDecomposition.field:Lorg/apache/commons/math3/Field; (1, 2)
	37 invokeinterface (1, 2)
	38 org/apache/commons/math3/Field.[I (1, 2)
	40 0 (1, 2)
	42 checkcast (1, 2)
	43 org/apache/commons/math3/FieldElement (1, 2)
	45 goto (1, 2)
	46 32 (1, 2)
	48 aload_0 (1, 2)
	49 getfield (1, 2)
	50 org/apache/commons/math3/linear/FieldLUDecomposition.field:Lorg/apache/commons/math3/Field; (1, 2)
	52 invokeinterface (1, 2)
	53 org/apache/commons/math3/Field.org/apache/commons/math3/FieldElement (1, 2)
	55 0 (1, 2)
	57 checkcast (1, 2)
	58 org/apache/commons/math3/FieldElement (1, 2)
	60 aload_0 (1, 2)
	61 getfield (1, 2)
	62 org/apache/commons/math3/linear/FieldLUDecomposition.field:Lorg/apache/commons/math3/Field; (1, 2)
	64 invokeinterface (1, 2)
	65 org/apache/commons/math3/Field.[I (1, 2)
	67 0 (1, 2)
	69 invokeinterface (1, 2)
	70 org/apache/commons/math3/FieldElement.equals:(Ljava/lang/Object;)Z (1, 2)
	72 0 (1, 2)
	74 checkcast (1, 2)
	75 org/apache/commons/math3/FieldElement (1, 2)
	77 astore_2 (1, 2)
	78 iconst_0 (2, 4)
	79 istore_3 (2, 4)
	80 iload_3 (2, 4)
	81 iload_1 (2, 4)
	82 if_icmpge (2, 4)
	83 27 (2, 4)
	85 aload_2 (2, 4)
	86 aload_0 (2, 4)
	87 getfield (2, 4)
	88 org/apache/commons/math3/linear/FieldLUDecomposition.lu:[[Lorg/apache/commons/math3/FieldElement; (2, 4)
	90 iload_3 (2, 4)
	91 aaload (2, 4)
	92 iload_3 (2, 4)
	93 aaload (2, 4)
	94 invokeinterface (2, 4)
	95 org/apache/commons/math3/FieldElement.subtract:(Ljava/lang/Object;)Ljava/lang/Object; (2, 4)
	97 0 (2, 4)
	99 checkcast (2, 4)
	100 org/apache/commons/math3/FieldElement (2, 4)
	102 astore_2 (2, 4)
	103 iinc (2, 4)
	104 #3 (2, 4)
	105 -89 (2, 4)
	106 goto (2, 4)
	107 -26 (2, 4)
	109 aload_2 (1, 2)
	110 areturn (1, 2)

Method: getSolver
	0 new (0, 0)
	1 org/apache/commons/math3/linear/FieldLUDecomposition$Solver (0, 0)
	3 dup (0, 0)
	4 aload_0 (0, 0)
	5 getfield (0, 0)
	6 org/apache/commons/math3/linear/FieldLUDecomposition.field:Lorg/apache/commons/math3/Field; (0, 0)
	8 aload_0 (0, 0)
	9 getfield (0, 0)
	10 org/apache/commons/math3/linear/FieldLUDecomposition.lu:[[Lorg/apache/commons/math3/FieldElement; (0, 0)
	12 aload_0 (0, 0)
	13 getfield (0, 0)
	14 org/apache/commons/math3/linear/FieldLUDecomposition.pivot:[I (0, 0)
	16 aload_0 (0, 0)
	17 getfield (0, 0)
	18 org/apache/commons/math3/linear/FieldLUDecomposition.singular:Z (0, 0)
	20 aconst_null (0, 0)
	21 invokespecial (0, 0)
	22 org/apache/commons/math3/linear/FieldLUDecomposition$Solver.<init>:(Lorg/apache/commons/math3/Field;[[Lorg/apache/commons/math3/FieldElement;[IZLorg/apache/commons/math3/linear/FieldLUDecomposition$1;)V (0, 0)
	24 areturn (0, 0)

