Method: <init>
	0 aload_0 (0, 0)
	1 invokespecial (0, 0)
	2 java/lang/Object.<init>:()V (0, 0)
	4 aload_1 (0, 0)
	5 invokestatic (0, 0)
	6 org/apache/commons/math3/util/MathUtils.checkNotNull:(Ljava/lang/Object;)V (0, 0)
	8 aload_0 (0, 0)
	9 aload_1 (0, 0)
	10 putfield (0, 0)
	11 org/apache/commons/math3/linear/IterativeLinearSolver.manager:Lorg/apache/commons/math3/util/IterationManager; (0, 0)
	13 return (0, 0)

Method: checkParameters
	0 aload_0 (0, 0)
	1 invokestatic (0, 0)
	2 org/apache/commons/math3/util/MathUtils.checkNotNull:(Ljava/lang/Object;)V (0, 0)
	4 aload_1 (0, 0)
	5 invokestatic (0, 0)
	6 org/apache/commons/math3/util/MathUtils.checkNotNull:(Ljava/lang/Object;)V (0, 0)
	8 aload_2 (0, 0)
	9 invokestatic (0, 0)
	10 org/apache/commons/math3/util/MathUtils.checkNotNull:(Ljava/lang/Object;)V (0, 0)
	12 aload_0 (0, 0)
	13 invokevirtual (0, 0)
	14 org/apache/commons/math3/linear/RealLinearOperator.getRowDimension:()I (0, 0)
	16 aload_0 (0, 0)
	17 invokevirtual (0, 0)
	18 org/apache/commons/math3/linear/RealLinearOperator.getColumnDimension:()I (0, 0)
	20 if_icmpeq (0, 0)
	21 19 (0, 0)
	23 new (0, 0)
	24 org/apache/commons/math3/linear/NonSquareOperatorException (0, 0)
	26 dup (0, 0)
	27 aload_0 (0, 0)
	28 invokevirtual (0, 0)
	29 org/apache/commons/math3/linear/RealLinearOperator.getRowDimension:()I (0, 0)
	31 aload_0 (0, 0)
	32 invokevirtual (0, 0)
	33 org/apache/commons/math3/linear/RealLinearOperator.getColumnDimension:()I (0, 0)
	35 invokespecial (0, 0)
	36 org/apache/commons/math3/linear/NonSquareOperatorException.<init>:(II)V (0, 0)
	38 athrow (0, 0)
	39 aload_1 (0, 0)
	40 invokevirtual (0, 0)
	41 org/apache/commons/math3/linear/RealVector.getDimension:()I (0, 0)
	43 aload_0 (0, 0)
	44 invokevirtual (0, 0)
	45 org/apache/commons/math3/linear/RealLinearOperator.getRowDimension:()I (0, 0)
	47 if_icmpeq (0, 0)
	48 19 (0, 0)
	50 new (0, 0)
	51 org/apache/commons/math3/exception/DimensionMismatchException (0, 0)
	53 dup (0, 0)
	54 aload_1 (0, 0)
	55 invokevirtual (0, 0)
	56 org/apache/commons/math3/linear/RealVector.getDimension:()I (0, 0)
	58 aload_0 (0, 0)
	59 invokevirtual (0, 0)
	60 org/apache/commons/math3/linear/RealLinearOperator.getRowDimension:()I (0, 0)
	62 invokespecial (0, 0)
	63 org/apache/commons/math3/exception/DimensionMismatchException.<init>:(II)V (0, 0)
	65 athrow (0, 0)
	66 aload_2 (0, 0)
	67 invokevirtual (0, 0)
	68 org/apache/commons/math3/linear/RealVector.getDimension:()I (0, 0)
	70 aload_0 (0, 0)
	71 invokevirtual (0, 0)
	72 org/apache/commons/math3/linear/RealLinearOperator.getColumnDimension:()I (0, 0)
	74 if_icmpeq (0, 0)
	75 19 (0, 0)
	77 new (0, 0)
	78 org/apache/commons/math3/exception/DimensionMismatchException (0, 0)
	80 dup (0, 0)
	81 aload_2 (0, 0)
	82 invokevirtual (0, 0)
	83 org/apache/commons/math3/linear/RealVector.getDimension:()I (0, 0)
	85 aload_0 (0, 0)
	86 invokevirtual (0, 0)
	87 org/apache/commons/math3/linear/RealLinearOperator.getColumnDimension:()I (0, 0)
	89 invokespecial (0, 0)
	90 org/apache/commons/math3/exception/DimensionMismatchException.<init>:(II)V (0, 0)
	92 athrow (0, 0)
	93 return (0, 0)

Method: getIterationManager
	0 aload_0 (0, 0)
	1 getfield (0, 0)
	2 org/apache/commons/math3/linear/IterativeLinearSolver.manager:Lorg/apache/commons/math3/util/IterationManager; (0, 0)
	4 areturn (0, 0)

