Method: <init>
	0 aload_0 (0, 0)
	1 aload_1 (0, 0)
	2 iload_2 (0, 0)
	3 invokespecial (0, 0)
	4 org/apache/commons/math3/util/IterationEvent.<init>:(Ljava/lang/Object;I)V (0, 0)
	6 return (0, 0)

Method: getResidual
	0 new (0, 0)
	1 org/apache/commons/math3/exception/MathUnsupportedOperationException (0, 0)
	3 dup (0, 0)
	4 invokespecial (0, 0)
	5 org/apache/commons/math3/exception/MathUnsupportedOperationException.<init>:()V (0, 0)
	7 athrow (0, 0)

Method: providesResidual
	0 iconst_0 (0, 0)
	1 ireturn (0, 0)

