Method: operate
	0 new (0, 0)
	1 org/apache/commons/math3/linear/ArrayRealVector (0, 0)
	3 dup (0, 0)
	4 aload_1 (0, 0)
	5 invokevirtual (0, 0)
	6 org/apache/commons/math3/linear/RealVector.toArray:()[D (0, 0)
	8 aload_0 (0, 0)
	9 getfield (0, 0)
	10 org/apache/commons/math3/linear/JacobiPreconditioner$1.val$sqrtDiag:Lorg/apache/commons/math3/linear/RealVector; (0, 0)
	12 invokevirtual (0, 0)
	13 org/apache/commons/math3/linear/RealVector.toArray:()[D (0, 0)
	15 invokestatic (0, 0)
	16 org/apache/commons/math3/util/MathArrays.ebeDivide:([D[D)[D (0, 0)
	18 iconst_0 (0, 0)
	19 invokespecial (0, 0)
	20 org/apache/commons/math3/linear/ArrayRealVector.<init>:([DZ)V (0, 0)
	22 areturn (0, 0)

Method: getRowDimension
	0 aload_0 (0, 0)
	1 getfield (0, 0)
	2 org/apache/commons/math3/linear/JacobiPreconditioner$1.val$sqrtDiag:Lorg/apache/commons/math3/linear/RealVector; (0, 0)
	4 invokevirtual (0, 0)
	5 org/apache/commons/math3/linear/RealVector.getDimension:()I (0, 0)
	7 ireturn (0, 0)

Method: getColumnDimension
	0 aload_0 (0, 0)
	1 getfield (0, 0)
	2 org/apache/commons/math3/linear/JacobiPreconditioner$1.val$sqrtDiag:Lorg/apache/commons/math3/linear/RealVector; (0, 0)
	4 invokevirtual (0, 0)
	5 org/apache/commons/math3/linear/RealVector.getDimension:()I (0, 0)
	7 ireturn (0, 0)

