Method: <init>
	0 aload_0 (0, 0)
	1 invokespecial (0, 0)
	4 aload_0 (0, 0)
	5 new (0, 0)
	8 dup (0, 0)
	9 aload_1 (0, 0)
	10 iload_2 (0, 0)
	11 invokespecial (0, 0)
	14 putfield (0, 0)
	17 return (0, 0)

Method: create
	0 aload_0 (0, 0)
	1 invokevirtual (0, 0)
	4 istore_1 (0, 0)
	5 aload_0 (1, 1)
	6 invokevirtual (1, 1)
	9 iload_1 (1, 1)
	10 if_icmpeq (1, 1)
	13 new (1, 1)
	16 dup (1, 1)
	17 aload_0 (1, 1)
	18 invokevirtual (1, 1)
	21 iload_1 (1, 1)
	22 invokespecial (1, 1)
	25 athrow (1, 1)
	26 iload_1 (0, 0)
	27 newarray (0, 0)
	29 astore_2 (0, 0)
	30 aload_0 (1, 1)
	31 instanceof (1, 1)
	34 ifeq (1, 1)
	37 aload_0 (1, 1)
	38 checkcast (1, 1)
	41 astore_3 (1, 1)
	42 iconst_0 (2, 4)
	43 istore (2, 4)
	45 iload (2, 4)
	47 iload_1 (2, 4)
	48 if_icmpge (2, 4)
	51 aload_2 (2, 4)
	52 iload (2, 4)
	54 aload_3 (2, 4)
	55 iload (2, 4)
	57 iload (2, 4)
	59 invokevirtual (2, 4)
	62 dastore (2, 4)
	63 iinc (2, 4)
	66 goto (2, 4)
	69 goto (1, 2)
	72 new (1, 2)
	75 dup (1, 2)
	76 iload_1 (1, 2)
	77 invokespecial (1, 2)
	80 astore_3 (1, 2)
	81 iconst_0 (2, 4)
	82 istore (2, 4)
	84 iload (2, 4)
	86 iload_1 (2, 4)
	87 if_icmpge (2, 4)
	90 aload_3 (2, 4)
	91 dconst_0 (2, 4)
	92 invokevirtual (2, 4)
	95 aload_3 (2, 4)
	96 iload (2, 4)
	98 dconst_1 (2, 4)
	99 invokevirtual (2, 4)
	102 aload_2 (2, 4)
	103 iload (2, 4)
	105 aload_0 (2, 4)
	106 aload_3 (2, 4)
	107 invokevirtual (2, 4)
	110 iload (2, 4)
	112 invokevirtual (2, 4)
	115 dastore (2, 4)
	116 iinc (2, 4)
	119 goto (2, 4)
	122 new (0, 1)
	125 dup (0, 1)
	126 aload_2 (0, 1)
	127 iconst_0 (0, 1)
	128 invokespecial (0, 1)
	131 areturn (0, 1)

Method: getColumnDimension
	0 aload_0 (0, 0)
	1 getfield (0, 0)
	4 invokevirtual (0, 0)
	7 ireturn (0, 0)

Method: getRowDimension
	0 aload_0 (0, 0)
	1 getfield (0, 0)
	4 invokevirtual (0, 0)
	7 ireturn (0, 0)

Method: operate
	0 new (0, 0)
	3 dup (0, 0)
	4 aload_1 (0, 0)
	5 invokevirtual (0, 0)
	8 aload_0 (0, 0)
	9 getfield (0, 0)
	12 invokevirtual (0, 0)
	15 invokestatic (0, 0)
	18 iconst_0 (0, 0)
	19 invokespecial (0, 0)
	22 areturn (0, 0)

Method: sqrt
	0 aload_0 (0, 0)
	1 getfield (0, 0)
	4 new (0, 0)
	7 dup (0, 0)
	8 invokespecial (0, 0)
	11 invokevirtual (0, 0)
	14 astore_1 (0, 0)
	15 new (0, 0)
	18 dup (0, 0)
	19 aload_0 (0, 0)
	20 aload_1 (0, 0)
	21 invokespecial (0, 0)
	24 areturn (0, 0)

