Method: <init>
	0 aload_0 (0, 0)
	1 invokespecial (0, 0)
	2 java/lang/Object.<init>:()V (0, 0)
	4 aload_1 (2, 1)
	5 invokeinterface (2, 1)
	6 org/apache/commons/math3/linear/RealMatrix.org/apache/commons/math3/linear/NonSquareMatrixException (2, 1)
	8 0 (2, 1)
	10 ifne (2, 1)
	11 23 (2, 1)
	13 new (2, 1)
	14 org/apache/commons/math3/linear/NonSquareMatrixException (2, 1)
	16 dup (2, 1)
	17 aload_1 (2, 1)
	18 invokeinterface (2, 1)
	19 org/apache/commons/math3/linear/RealMatrix.getColumnDimension:()I (2, 1)
	21 0 (2, 1)
	23 aload_1 (2, 1)
	24 invokeinterface (2, 1)
	25 org/apache/commons/math3/linear/RealMatrix.<init>:(II)V (2, 1)
	27 0 (2, 1)
	29 invokespecial (2, 1)
	30 org/apache/commons/math3/linear/NonSquareMatrixException.<init>:(II)V (2, 1)
	32 athrow (2, 1)
	33 aload_1 (0, 0)
	34 invokeinterface (0, 0)
	35 org/apache/commons/math3/linear/RealMatrix.<init>:(II)V (0, 0)
	37 0 (0, 0)
	39 istore (0, 0)
	40 #4 (0, 0)
	41 aload_0 (0, 0)
	42 aload_1 (0, 0)
	43 invokeinterface (0, 0)
	44 org/apache/commons/math3/linear/RealMatrix.lu:[[D (0, 0)
	46 0 (0, 0)
	48 putfield (0, 0)
	49 org/apache/commons/math3/linear/LUDecomposition.lu:[[D (0, 0)
	51 aload_0 (0, 0)
	52 iload (0, 0)
	53 #4 (0, 0)
	54 newarray (0, 0)
	55 10 (0, 0)
	56 putfield (0, 0)
	57 org/apache/commons/math3/linear/LUDecomposition.pivot:[I (0, 0)
	59 aload_0 (0, 0)
	60 aconst_null (0, 0)
	61 putfield (0, 0)
	62 org/apache/commons/math3/linear/LUDecomposition.cachedL:Lorg/apache/commons/math3/linear/RealMatrix; (0, 0)
	64 aload_0 (0, 0)
	65 aconst_null (0, 0)
	66 putfield (0, 0)
	67 org/apache/commons/math3/linear/LUDecomposition.cachedU:Lorg/apache/commons/math3/linear/RealMatrix; (0, 0)
	69 aload_0 (0, 0)
	70 aconst_null (0, 0)
	71 putfield (0, 0)
	72 org/apache/commons/math3/linear/LUDecomposition.cachedP:Lorg/apache/commons/math3/linear/RealMatrix; (0, 0)
	74 iconst_0 (2, 4)
	75 istore (2, 4)
	76 #5 (2, 4)
	77 iload (2, 4)
	78 #5 (2, 4)
	79 iload (2, 4)
	80 #4 (2, 4)
	81 if_icmpge (2, 4)
	82 18 (2, 4)
	84 aload_0 (2, 4)
	85 getfield (2, 4)
	86 org/apache/commons/math3/linear/LUDecomposition.pivot:[I (2, 4)
	88 iload (2, 4)
	89 #5 (2, 4)
	90 iload (2, 4)
	91 #5 (2, 4)
	92 iastore (2, 4)
	93 iinc (2, 4)
	94 #5 (2, 4)
	95 -89 (2, 4)
	96 goto (2, 4)
	97 -19 (2, 4)
	99 aload_0 (0, 0)
	100 iconst_1 (0, 0)
	101 putfield (0, 0)
	102 org/apache/commons/math3/linear/LUDecomposition.even:Z (0, 0)
	104 aload_0 (0, 0)
	105 iconst_0 (0, 0)
	106 putfield (0, 0)
	107 org/apache/commons/math3/linear/LUDecomposition.singular:Z (0, 0)
	109 iconst_0 (2, 4)
	110 istore (2, 4)
	111 #5 (2, 4)
	112 iload (2, 4)
	113 #5 (2, 4)
	114 iload (2, 4)
	115 #4 (2, 4)
	116 if_icmpge (2, 4)
	117 379 (2, 4)
	119 iconst_0 (3, 4)
	120 istore (3, 4)
	121 #6 (3, 4)
	122 iload (3, 4)
	123 #6 (3, 4)
	124 iload (3, 4)
	125 #5 (3, 4)
	126 if_icmpge (3, 4)
	127 69 (3, 4)
	129 aload_0 (3, 4)
	130 getfield (3, 4)
	131 org/apache/commons/math3/linear/LUDecomposition.lu:[[D (3, 4)
	133 iload (3, 4)
	134 #6 (3, 4)
	135 aaload (3, 4)
	136 astore (3, 4)
	137 #7 (3, 4)
	138 aload (3, 4)
	139 #7 (3, 4)
	140 iload (3, 4)
	141 #5 (3, 4)
	142 daload (3, 4)
	143 dstore (3, 4)
	144 #8 (3, 4)
	145 iconst_0 (4, 4)
	146 istore (4, 4)
	147 #10 (4, 4)
	148 iload (4, 4)
	149 #10 (4, 4)
	150 iload (4, 4)
	151 #6 (4, 4)
	152 if_icmpge (4, 4)
	153 30 (4, 4)
	155 dload (4, 4)
	156 #8 (4, 4)
	157 aload (4, 4)
	158 #7 (4, 4)
	159 iload (4, 4)
	160 #10 (4, 4)
	161 daload (4, 4)
	162 aload_0 (4, 4)
	163 getfield (4, 4)
	164 org/apache/commons/math3/linear/LUDecomposition.lu:[[D (4, 4)
	166 iload (4, 4)
	167 #10 (4, 4)
	168 aaload (4, 4)
	169 iload (4, 4)
	170 #5 (4, 4)
	171 daload (4, 4)
	172 dmul (4, 4)
	173 dsub (4, 4)
	174 dstore (4, 4)
	175 #8 (4, 4)
	176 iinc (4, 4)
	177 #10 (4, 4)
	178 -89 (4, 4)
	179 goto (4, 4)
	180 -31 (4, 4)
	182 aload (3, 4)
	183 #7 (3, 4)
	184 iload (3, 4)
	185 #5 (3, 4)
	186 dload (3, 4)
	187 #8 (3, 4)
	188 dastore (3, 4)
	189 iinc (3, 4)
	190 #6 (3, 4)
	191 -89 (3, 4)
	192 goto (3, 4)
	193 -70 (3, 4)
	195 iload (2, 4)
	196 #5 (2, 4)
	197 istore (2, 4)
	198 #6 (2, 4)
	199 ldc2_w (2, 4)
	200 -inf (2, 4)
	202 dstore (2, 4)
	203 #7 (2, 4)
	204 iload (3, 4)
	205 #5 (3, 4)
	206 istore (3, 4)
	207 #9 (3, 4)
	208 iload (3, 4)
	209 #9 (3, 4)
	210 iload (3, 4)
	211 #4 (3, 4)
	212 if_icmpge (3, 4)
	213 91 (3, 4)
	215 aload_0 (3, 4)
	216 getfield (3, 4)
	217 org/apache/commons/math3/linear/LUDecomposition.lu:[[D (3, 4)
	219 iload (3, 4)
	220 #9 (3, 4)
	221 aaload (3, 4)
	222 astore (3, 4)
	223 #10 (3, 4)
	224 aload (3, 4)
	225 #10 (3, 4)
	226 iload (3, 4)
	227 #5 (3, 4)
	228 daload (3, 4)
	229 dstore (3, 4)
	230 #11 (3, 4)
	231 iconst_0 (4, 4)
	232 istore (4, 4)
	233 #13 (4, 4)
	234 iload (4, 4)
	235 #13 (4, 4)
	236 iload (4, 4)
	237 #5 (4, 4)
	238 if_icmpge (4, 4)
	239 30 (4, 4)
	241 dload (4, 4)
	242 #11 (4, 4)
	243 aload (4, 4)
	244 #10 (4, 4)
	245 iload (4, 4)
	246 #13 (4, 4)
	247 daload (4, 4)
	248 aload_0 (4, 4)
	249 getfield (4, 4)
	250 org/apache/commons/math3/linear/LUDecomposition.lu:[[D (4, 4)
	252 iload (4, 4)
	253 #13 (4, 4)
	254 aaload (4, 4)
	255 iload (4, 4)
	256 #5 (4, 4)
	257 daload (4, 4)
	258 dmul (4, 4)
	259 dsub (4, 4)
	260 dstore (4, 4)
	261 #11 (4, 4)
	262 iinc (4, 4)
	263 #13 (4, 4)
	264 -89 (4, 4)
	265 goto (4, 4)
	266 -31 (4, 4)
	268 aload (3, 4)
	269 #10 (3, 4)
	270 iload (3, 4)
	271 #5 (3, 4)
	272 dload (3, 4)
	273 #11 (3, 4)
	274 dastore (3, 4)
	275 dload (4, 1)
	276 #11 (4, 1)
	277 invokestatic (4, 1)
	278 org/apache/commons/math3/util/FastMath.abs:(D)D (4, 1)
	280 dload (4, 1)
	281 #7 (4, 1)
	282 dcmpl (4, 1)
	283 ifle (4, 1)
	284 14 (4, 1)
	286 dload (4, 1)
	287 #11 (4, 1)
	288 invokestatic (4, 1)
	289 org/apache/commons/math3/util/FastMath.abs:(D)D (4, 1)
	291 dstore (4, 1)
	292 #7 (4, 1)
	293 iload (4, 1)
	294 #9 (4, 1)
	295 istore (4, 1)
	296 #6 (4, 1)
	297 iinc (4, 1)
	298 #9 (4, 1)
	299 -89 (4, 1)
	300 goto (4, 1)
	301 -92 (4, 1)
	303 aload_0 (4, 1)
	304 getfield (4, 1)
	305 org/apache/commons/math3/linear/LUDecomposition.lu:[[D (4, 1)
	307 iload (4, 1)
	308 #6 (4, 1)
	309 aaload (4, 1)
	310 iload (4, 1)
	311 #5 (4, 1)
	312 daload (4, 1)
	313 invokestatic (4, 1)
	314 org/apache/commons/math3/util/FastMath.abs:(D)D (4, 1)
	316 dload_2 (4, 1)
	317 dcmpg (4, 1)
	318 ifge (4, 1)
	319 9 (4, 1)
	321 aload_0 (4, 1)
	322 iconst_1 (4, 1)
	323 putfield (4, 1)
	324 org/apache/commons/math3/linear/LUDecomposition.singular:Z (4, 1)
	326 return (4, 1)
	327 iload (4, 1)
	328 #6 (4, 1)
	329 iload (4, 1)
	330 #5 (4, 1)
	331 if_icmpeq (4, 1)
	332 112 (4, 1)
	334 dconst_0 (4, 1)
	335 dstore (4, 1)
	336 #9 (4, 1)
	337 aload_0 (4, 1)
	338 getfield (4, 1)
	339 org/apache/commons/math3/linear/LUDecomposition.lu:[[D (4, 1)
	341 iload (4, 1)
	342 #6 (4, 1)
	343 aaload (4, 1)
	344 astore (4, 1)
	345 #11 (4, 1)
	346 aload_0 (4, 1)
	347 getfield (4, 1)
	348 org/apache/commons/math3/linear/LUDecomposition.lu:[[D (4, 1)
	350 iload (4, 1)
	351 #5 (4, 1)
	352 aaload (4, 1)
	353 astore (4, 1)
	354 #12 (4, 1)
	355 iconst_0 (5, 4)
	356 istore (5, 4)
	357 #13 (5, 4)
	358 iload (5, 4)
	359 #13 (5, 4)
	360 iload (5, 4)
	361 #4 (5, 4)
	362 if_icmpge (5, 4)
	363 33 (5, 4)
	365 aload (5, 4)
	366 #11 (5, 4)
	367 iload (5, 4)
	368 #13 (5, 4)
	369 daload (5, 4)
	370 dstore (5, 4)
	371 #9 (5, 4)
	372 aload (5, 4)
	373 #11 (5, 4)
	374 iload (5, 4)
	375 #13 (5, 4)
	376 aload (5, 4)
	377 #12 (5, 4)
	378 iload (5, 4)
	379 #13 (5, 4)
	380 daload (5, 4)
	381 dastore (5, 4)
	382 aload (5, 4)
	383 #12 (5, 4)
	384 iload (5, 4)
	385 #13 (5, 4)
	386 dload (5, 4)
	387 #9 (5, 4)
	388 dastore (5, 4)
	389 iinc (5, 4)
	390 #13 (5, 4)
	391 -89 (5, 4)
	392 goto (5, 4)
	393 -34 (5, 4)
	395 aload_0 (4, 1)
	396 getfield (4, 1)
	397 org/apache/commons/math3/linear/LUDecomposition.pivot:[I (4, 1)
	399 iload (4, 1)
	400 #6 (4, 1)
	401 iaload (4, 1)
	402 istore (4, 1)
	403 #13 (4, 1)
	404 aload_0 (4, 1)
	405 getfield (4, 1)
	406 org/apache/commons/math3/linear/LUDecomposition.pivot:[I (4, 1)
	408 iload (4, 1)
	409 #6 (4, 1)
	410 aload_0 (4, 1)
	411 getfield (4, 1)
	412 org/apache/commons/math3/linear/LUDecomposition.pivot:[I (4, 1)
	414 iload (4, 1)
	415 #5 (4, 1)
	416 iaload (4, 1)
	417 iastore (4, 1)
	418 aload_0 (4, 1)
	419 getfield (4, 1)
	420 org/apache/commons/math3/linear/LUDecomposition.pivot:[I (4, 1)
	422 iload (4, 1)
	423 #5 (4, 1)
	424 iload (4, 1)
	425 #13 (4, 1)
	426 iastore (4, 1)
	427 aload_0 (4, 1)
	428 aload_0 (4, 1)
	429 getfield (4, 1)
	430 org/apache/commons/math3/linear/LUDecomposition.even:Z (4, 1)
	432 ifne (4, 1)
	433 7 (4, 1)
	435 iconst_1 (4, 1)
	436 goto (4, 1)
	437 4 (4, 1)
	439 iconst_0 (4, 1)
	440 putfield (4, 1)
	441 org/apache/commons/math3/linear/LUDecomposition.even:Z (4, 1)
	443 aload_0 (3, 1)
	444 getfield (3, 1)
	445 org/apache/commons/math3/linear/LUDecomposition.lu:[[D (3, 1)
	447 iload (3, 1)
	448 #5 (3, 1)
	449 aaload (3, 1)
	450 iload (3, 1)
	451 #5 (3, 1)
	452 daload (3, 1)
	453 dstore (3, 1)
	454 #9 (3, 1)
	455 iload (4, 4)
	456 #5 (4, 4)
	457 iconst_1 (4, 4)
	458 iadd (4, 4)
	459 istore (4, 4)
	460 #11 (4, 4)
	461 iload (4, 4)
	462 #11 (4, 4)
	463 iload (4, 4)
	464 #4 (4, 4)
	465 if_icmpge (4, 4)
	466 24 (4, 4)
	468 aload_0 (4, 4)
	469 getfield (4, 4)
	470 org/apache/commons/math3/linear/LUDecomposition.lu:[[D (4, 4)
	472 iload (4, 4)
	473 #11 (4, 4)
	474 aaload (4, 4)
	475 iload (4, 4)
	476 #5 (4, 4)
	477 dup2 (4, 4)
	478 daload (4, 4)
	479 dload (4, 4)
	480 #9 (4, 4)
	481 ddiv (4, 4)
	482 dastore (4, 4)
	483 iinc (4, 4)
	484 #11 (4, 4)
	485 -89 (4, 4)
	486 goto (4, 4)
	487 -25 (4, 4)
	489 iinc (4, 4)
	490 #5 (4, 4)
	491 -89 (4, 4)
	492 goto (4, 4)
	493 -380 (4, 4)
	495 return (2, 4)

Method: getL
	0 aload_0 (1, 1)
	1 getfield (1, 1)
	2 org/apache/commons/math3/linear/LUDecomposition.cachedL:Lorg/apache/commons/math3/linear/RealMatrix; (1, 1)
	4 ifnonnull (1, 1)
	5 88 (1, 1)
	7 aload_0 (1, 1)
	8 getfield (1, 1)
	9 org/apache/commons/math3/linear/LUDecomposition.singular:Z (1, 1)
	11 ifne (1, 1)
	12 81 (1, 1)
	14 aload_0 (1, 1)
	15 getfield (1, 1)
	16 org/apache/commons/math3/linear/LUDecomposition.pivot:[I (1, 1)
	18 arraylength (1, 1)
	19 istore_1 (1, 1)
	20 aload_0 (1, 1)
	21 iload_1 (1, 1)
	22 iload_1 (1, 1)
	23 invokestatic (1, 1)
	24 org/apache/commons/math3/linear/MatrixUtils.createRealMatrix:(II)Lorg/apache/commons/math3/linear/RealMatrix; (1, 1)
	26 putfield (1, 1)
	27 org/apache/commons/math3/linear/LUDecomposition.cachedL:Lorg/apache/commons/math3/linear/RealMatrix; (1, 1)
	29 iconst_0 (2, 4)
	30 istore_2 (2, 4)
	31 iload_2 (2, 4)
	32 iload_1 (2, 4)
	33 if_icmpge (2, 4)
	34 59 (2, 4)
	36 aload_0 (2, 4)
	37 getfield (2, 4)
	38 org/apache/commons/math3/linear/LUDecomposition.lu:[[D (2, 4)
	40 iload_2 (2, 4)
	41 aaload (2, 4)
	42 astore_3 (2, 4)
	43 iconst_0 (3, 4)
	44 istore (3, 4)
	45 #4 (3, 4)
	46 iload (3, 4)
	47 #4 (3, 4)
	48 iload_2 (3, 4)
	49 if_icmpge (3, 4)
	50 25 (3, 4)
	52 aload_0 (3, 4)
	53 getfield (3, 4)
	54 org/apache/commons/math3/linear/LUDecomposition.cachedL:Lorg/apache/commons/math3/linear/RealMatrix; (3, 4)
	56 iload_2 (3, 4)
	57 iload (3, 4)
	58 #4 (3, 4)
	59 aload_3 (3, 4)
	60 iload (3, 4)
	61 #4 (3, 4)
	62 daload (3, 4)
	63 invokeinterface (3, 4)
	64 org/apache/commons/math3/linear/RealMatrix.[I (3, 4)
	66 0 (3, 4)
	68 iinc (3, 4)
	69 #4 (3, 4)
	70 -89 (3, 4)
	71 goto (3, 4)
	72 -25 (3, 4)
	74 aload_0 (2, 4)
	75 getfield (2, 4)
	76 org/apache/commons/math3/linear/LUDecomposition.cachedL:Lorg/apache/commons/math3/linear/RealMatrix; (2, 4)
	78 iload_2 (2, 4)
	79 iload_2 (2, 4)
	80 dconst_1 (2, 4)
	81 invokeinterface (2, 4)
	82 org/apache/commons/math3/linear/RealMatrix.[I (2, 4)
	84 0 (2, 4)
	86 iinc (2, 4)
	87 #2 (2, 4)
	88 -89 (2, 4)
	89 goto (2, 4)
	90 -58 (2, 4)
	92 aload_0 (0, 0)
	93 getfield (0, 0)
	94 org/apache/commons/math3/linear/LUDecomposition.cachedL:Lorg/apache/commons/math3/linear/RealMatrix; (0, 0)
	96 areturn (0, 0)

Method: getU
	0 aload_0 (1, 1)
	1 getfield (1, 1)
	2 org/apache/commons/math3/linear/LUDecomposition.cachedU:Lorg/apache/commons/math3/linear/RealMatrix; (1, 1)
	4 ifnonnull (1, 1)
	5 76 (1, 1)
	7 aload_0 (1, 1)
	8 getfield (1, 1)
	9 org/apache/commons/math3/linear/LUDecomposition.singular:Z (1, 1)
	11 ifne (1, 1)
	12 69 (1, 1)
	14 aload_0 (1, 1)
	15 getfield (1, 1)
	16 org/apache/commons/math3/linear/LUDecomposition.pivot:[I (1, 1)
	18 arraylength (1, 1)
	19 istore_1 (1, 1)
	20 aload_0 (1, 1)
	21 iload_1 (1, 1)
	22 iload_1 (1, 1)
	23 invokestatic (1, 1)
	24 org/apache/commons/math3/linear/MatrixUtils.createRealMatrix:(II)Lorg/apache/commons/math3/linear/RealMatrix; (1, 1)
	26 putfield (1, 1)
	27 org/apache/commons/math3/linear/LUDecomposition.cachedU:Lorg/apache/commons/math3/linear/RealMatrix; (1, 1)
	29 iconst_0 (2, 4)
	30 istore_2 (2, 4)
	31 iload_2 (2, 4)
	32 iload_1 (2, 4)
	33 if_icmpge (2, 4)
	34 47 (2, 4)
	36 aload_0 (2, 4)
	37 getfield (2, 4)
	38 org/apache/commons/math3/linear/LUDecomposition.lu:[[D (2, 4)
	40 iload_2 (2, 4)
	41 aaload (2, 4)
	42 astore_3 (2, 4)
	43 iload_2 (3, 4)
	44 istore (3, 4)
	45 #4 (3, 4)
	46 iload (3, 4)
	47 #4 (3, 4)
	48 iload_1 (3, 4)
	49 if_icmpge (3, 4)
	50 25 (3, 4)
	52 aload_0 (3, 4)
	53 getfield (3, 4)
	54 org/apache/commons/math3/linear/LUDecomposition.cachedU:Lorg/apache/commons/math3/linear/RealMatrix; (3, 4)
	56 iload_2 (3, 4)
	57 iload (3, 4)
	58 #4 (3, 4)
	59 aload_3 (3, 4)
	60 iload (3, 4)
	61 #4 (3, 4)
	62 daload (3, 4)
	63 invokeinterface (3, 4)
	64 org/apache/commons/math3/linear/RealMatrix.[I (3, 4)
	66 0 (3, 4)
	68 iinc (3, 4)
	69 #4 (3, 4)
	70 -89 (3, 4)
	71 goto (3, 4)
	72 -25 (3, 4)
	74 iinc (3, 4)
	75 #2 (3, 4)
	76 -89 (3, 4)
	77 goto (3, 4)
	78 -46 (3, 4)
	80 aload_0 (1, 1)
	81 getfield (1, 1)
	82 org/apache/commons/math3/linear/LUDecomposition.cachedU:Lorg/apache/commons/math3/linear/RealMatrix; (1, 1)
	84 areturn (1, 1)

Method: getP
	0 aload_0 (1, 1)
	1 getfield (1, 1)
	2 org/apache/commons/math3/linear/LUDecomposition.cachedP:Lorg/apache/commons/math3/linear/RealMatrix; (1, 1)
	4 ifnonnull (1, 1)
	5 55 (1, 1)
	7 aload_0 (1, 1)
	8 getfield (1, 1)
	9 org/apache/commons/math3/linear/LUDecomposition.singular:Z (1, 1)
	11 ifne (1, 1)
	12 48 (1, 1)
	14 aload_0 (1, 1)
	15 getfield (1, 1)
	16 org/apache/commons/math3/linear/LUDecomposition.pivot:[I (1, 1)
	18 arraylength (1, 1)
	19 istore_1 (1, 1)
	20 aload_0 (1, 1)
	21 iload_1 (1, 1)
	22 iload_1 (1, 1)
	23 invokestatic (1, 1)
	24 org/apache/commons/math3/linear/MatrixUtils.createRealMatrix:(II)Lorg/apache/commons/math3/linear/RealMatrix; (1, 1)
	26 putfield (1, 1)
	27 org/apache/commons/math3/linear/LUDecomposition.cachedP:Lorg/apache/commons/math3/linear/RealMatrix; (1, 1)
	29 iconst_0 (2, 4)
	30 istore_2 (2, 4)
	31 iload_2 (2, 4)
	32 iload_1 (2, 4)
	33 if_icmpge (2, 4)
	34 26 (2, 4)
	36 aload_0 (2, 4)
	37 getfield (2, 4)
	38 org/apache/commons/math3/linear/LUDecomposition.cachedP:Lorg/apache/commons/math3/linear/RealMatrix; (2, 4)
	40 iload_2 (2, 4)
	41 aload_0 (2, 4)
	42 getfield (2, 4)
	43 org/apache/commons/math3/linear/LUDecomposition.pivot:[I (2, 4)
	45 iload_2 (2, 4)
	46 iaload (2, 4)
	47 dconst_1 (2, 4)
	48 invokeinterface (2, 4)
	49 org/apache/commons/math3/linear/RealMatrix.[I (2, 4)
	51 0 (2, 4)
	53 iinc (2, 4)
	54 #2 (2, 4)
	55 -89 (2, 4)
	56 goto (2, 4)
	57 -25 (2, 4)
	59 aload_0 (0, 0)
	60 getfield (0, 0)
	61 org/apache/commons/math3/linear/LUDecomposition.cachedP:Lorg/apache/commons/math3/linear/RealMatrix; (0, 0)
	63 areturn (0, 0)

Method: getPivot
	0 aload_0 (0, 0)
	1 getfield (0, 0)
	2 org/apache/commons/math3/linear/LUDecomposition.pivot:[I (0, 0)
	4 invokevirtual (0, 0)
	5 [I.clone:()Ljava/lang/Object; (0, 0)
	7 checkcast (0, 0)
	8 [I (0, 0)
	10 areturn (0, 0)

Method: getDeterminant
	0 aload_0 (1, 1)
	1 getfield (1, 1)
	2 org/apache/commons/math3/linear/LUDecomposition.singular:Z (1, 1)
	4 ifeq (1, 1)
	5 5 (1, 1)
	7 dconst_0 (1, 1)
	8 dreturn (1, 1)
	9 aload_0 (1, 2)
	10 getfield (1, 2)
	11 org/apache/commons/math3/linear/LUDecomposition.pivot:[I (1, 2)
	13 arraylength (1, 2)
	14 istore_1 (1, 2)
	15 aload_0 (1, 2)
	16 getfield (1, 2)
	17 org/apache/commons/math3/linear/LUDecomposition.even:Z (1, 2)
	19 ifeq (1, 2)
	20 7 (1, 2)
	22 dconst_1 (1, 2)
	23 goto (1, 2)
	24 6 (1, 2)
	26 ldc2_w (1, 2)
	27 -1.0 (1, 2)
	29 dstore_2 (1, 2)
	30 iconst_0 (2, 4)
	31 istore (2, 4)
	32 #4 (2, 4)
	33 iload (2, 4)
	34 #4 (2, 4)
	35 iload_1 (2, 4)
	36 if_icmpge (2, 4)
	37 22 (2, 4)
	39 dload_2 (2, 4)
	40 aload_0 (2, 4)
	41 getfield (2, 4)
	42 org/apache/commons/math3/linear/LUDecomposition.lu:[[D (2, 4)
	44 iload (2, 4)
	45 #4 (2, 4)
	46 aaload (2, 4)
	47 iload (2, 4)
	48 #4 (2, 4)
	49 daload (2, 4)
	50 dmul (2, 4)
	51 dstore_2 (2, 4)
	52 iinc (2, 4)
	53 #4 (2, 4)
	54 -89 (2, 4)
	55 goto (2, 4)
	56 -22 (2, 4)
	58 dload_2 (1, 2)
	59 dreturn (1, 2)

Method: getSolver
	0 new (0, 0)
	1 org/apache/commons/math3/linear/LUDecomposition$Solver (0, 0)
	3 dup (0, 0)
	4 aload_0 (0, 0)
	5 getfield (0, 0)
	6 org/apache/commons/math3/linear/LUDecomposition.lu:[[D (0, 0)
	8 aload_0 (0, 0)
	9 getfield (0, 0)
	10 org/apache/commons/math3/linear/LUDecomposition.pivot:[I (0, 0)
	12 aload_0 (0, 0)
	13 getfield (0, 0)
	14 org/apache/commons/math3/linear/LUDecomposition.singular:Z (0, 0)
	16 aconst_null (0, 0)
	17 invokespecial (0, 0)
	18 org/apache/commons/math3/linear/LUDecomposition$Solver.<init>:([[D[IZLorg/apache/commons/math3/linear/LUDecomposition$1;)V (0, 0)
	20 areturn (0, 0)

