Method: <init>
	0 aload_0 (0, 0)
	1 invokespecial (0, 0)
	4 return (0, 0)

Method: createRealMatrix
	0 aload_0 (0, 1)
	1 ifnull (0, 1)
	4 aload_0 (0, 1)
	5 iconst_0 (0, 1)
	6 aaload (0, 1)
	7 ifnonnull (0, 1)
	10 new (1, 1)
	13 dup (1, 1)
	14 invokespecial (1, 1)
	17 athrow (1, 1)
	18 aload_0 (0, 0)
	19 arraylength (0, 0)
	20 aload_0 (0, 0)
	21 iconst_0 (0, 0)
	22 aaload (0, 0)
	23 arraylength (0, 0)
	24 imul (0, 0)
	25 sipush (0, 0)
	28 if_icmpgt (0, 0)
	31 new (0, 0)
	34 dup (0, 0)
	35 aload_0 (0, 0)
	36 invokespecial (0, 0)
	39 goto (0, 0)
	42 new (0, 0)
	45 dup (0, 0)
	46 aload_0 (0, 0)
	47 invokespecial (0, 0)
	50 areturn (0, 0)

Method: createFieldMatrix
	0 aload_0 (0, 1)
	1 ifnull (0, 1)
	4 aload_0 (0, 1)
	5 iconst_0 (0, 1)
	6 aaload (0, 1)
	7 ifnonnull (0, 1)
	10 new (1, 1)
	13 dup (1, 1)
	14 invokespecial (1, 1)
	17 athrow (1, 1)
	18 aload_0 (0, 0)
	19 arraylength (0, 0)
	20 aload_0 (0, 0)
	21 iconst_0 (0, 0)
	22 aaload (0, 0)
	23 arraylength (0, 0)
	24 imul (0, 0)
	25 sipush (0, 0)
	28 if_icmpgt (0, 0)
	31 new (0, 0)
	34 dup (0, 0)
	35 aload_0 (0, 0)
	36 invokespecial (0, 0)
	39 goto (0, 0)
	42 new (0, 0)
	45 dup (0, 0)
	46 aload_0 (0, 0)
	47 invokespecial (0, 0)
	50 areturn (0, 0)

Method: createRealIdentityMatrix
	0 iload_0 (0, 0)
	1 iload_0 (0, 0)
	2 invokestatic (0, 0)
	5 astore_1 (0, 0)
	6 iconst_0 (1, 4)
	7 istore_2 (1, 4)
	8 iload_2 (1, 4)
	9 iload_0 (1, 4)
	10 if_icmpge (1, 4)
	13 aload_1 (1, 4)
	14 iload_2 (1, 4)
	15 iload_2 (1, 4)
	16 dconst_1 (1, 4)
	17 invokeinterface (1, 4)
	22 iinc (1, 4)
	25 goto (1, 4)
	28 aload_1 (0, 0)
	29 areturn (0, 0)

Method: createFieldIdentityMatrix
	0 aload_0 (0, 0)
	1 invokeinterface (0, 0)
	6 checkcast (0, 0)
	9 astore_2 (0, 0)
	10 aload_0 (0, 0)
	11 invokeinterface (0, 0)
	16 checkcast (0, 0)
	19 astore_3 (0, 0)
	20 aload_0 (0, 0)
	21 iload_1 (0, 0)
	22 iload_1 (0, 0)
	23 invokestatic (0, 0)
	26 checkcast (0, 0)
	29 astore (0, 0)
	31 iconst_0 (1, 4)
	32 istore (1, 4)
	34 iload (1, 4)
	36 iload_1 (1, 4)
	37 if_icmpge (1, 4)
	40 aload (1, 4)
	42 iload (1, 4)
	44 aaload (1, 4)
	45 astore (1, 4)
	47 aload (1, 4)
	49 aload_2 (1, 4)
	50 invokestatic (1, 4)
	53 aload (1, 4)
	55 iload (1, 4)
	57 aload_3 (1, 4)
	58 aastore (1, 4)
	59 iinc (1, 4)
	62 goto (1, 4)
	65 new (0, 0)
	68 dup (0, 0)
	69 aload_0 (0, 0)
	70 aload (0, 0)
	72 iconst_0 (0, 0)
	73 invokespecial (0, 0)
	76 areturn (0, 0)

Method: createRealDiagonalMatrix
	0 aload_0 (0, 0)
	1 arraylength (0, 0)
	2 aload_0 (0, 0)
	3 arraylength (0, 0)
	4 invokestatic (0, 0)
	7 astore_1 (0, 0)
	8 iconst_0 (1, 4)
	9 istore_2 (1, 4)
	10 iload_2 (1, 4)
	11 aload_0 (1, 4)
	12 arraylength (1, 4)
	13 if_icmpge (1, 4)
	16 aload_1 (1, 4)
	17 iload_2 (1, 4)
	18 iload_2 (1, 4)
	19 aload_0 (1, 4)
	20 iload_2 (1, 4)
	21 daload (1, 4)
	22 invokeinterface (1, 4)
	27 iinc (1, 4)
	30 goto (1, 4)
	33 aload_1 (0, 0)
	34 areturn (0, 0)

Method: createFieldDiagonalMatrix
	0 aload_0 (0, 0)
	1 iconst_0 (0, 0)
	2 aaload (0, 0)
	3 invokeinterface (0, 0)
	8 aload_0 (0, 0)
	9 arraylength (0, 0)
	10 aload_0 (0, 0)
	11 arraylength (0, 0)
	12 invokestatic (0, 0)
	15 astore_1 (0, 0)
	16 iconst_0 (1, 4)
	17 istore_2 (1, 4)
	18 iload_2 (1, 4)
	19 aload_0 (1, 4)
	20 arraylength (1, 4)
	21 if_icmpge (1, 4)
	24 aload_1 (1, 4)
	25 iload_2 (1, 4)
	26 iload_2 (1, 4)
	27 aload_0 (1, 4)
	28 iload_2 (1, 4)
	29 aaload (1, 4)
	30 invokeinterface (1, 4)
	35 iinc (1, 4)
	38 goto (1, 4)
	41 aload_1 (0, 0)
	42 areturn (0, 0)

Method: createRealVector
	0 aload_0 (1, 1)
	1 ifnonnull (1, 1)
	4 new (1, 1)
	7 dup (1, 1)
	8 invokespecial (1, 1)
	11 athrow (1, 1)
	12 new (0, 0)
	15 dup (0, 0)
	16 aload_0 (0, 0)
	17 iconst_1 (0, 0)
	18 invokespecial (0, 0)
	21 areturn (0, 0)

Method: createFieldVector
	0 aload_0 (1, 1)
	1 ifnonnull (1, 1)
	4 new (1, 1)
	7 dup (1, 1)
	8 invokespecial (1, 1)
	11 athrow (1, 1)
	12 aload_0 (1, 1)
	13 arraylength (1, 1)
	14 ifne (1, 1)
	17 new (1, 1)
	20 dup (1, 1)
	21 getstatic (1, 1)
	24 iconst_0 (1, 1)
	25 anewarray (1, 1)
	28 invokespecial (1, 1)
	31 athrow (1, 1)
	32 new (0, 0)
	35 dup (0, 0)
	36 aload_0 (0, 0)
	37 iconst_0 (0, 0)
	38 aaload (0, 0)
	39 invokeinterface (0, 0)
	44 aload_0 (0, 0)
	45 iconst_1 (0, 0)
	46 invokespecial (0, 0)
	49 areturn (0, 0)

Method: createRowRealMatrix
	0 aload_0 (1, 1)
	1 ifnonnull (1, 1)
	4 new (1, 1)
	7 dup (1, 1)
	8 invokespecial (1, 1)
	11 athrow (1, 1)
	12 aload_0 (0, 0)
	13 arraylength (0, 0)
	14 istore_1 (0, 0)
	15 iconst_1 (0, 0)
	16 iload_1 (0, 0)
	17 invokestatic (0, 0)
	20 astore_2 (0, 0)
	21 iconst_0 (1, 4)
	22 istore_3 (1, 4)
	23 iload_3 (1, 4)
	24 iload_1 (1, 4)
	25 if_icmpge (1, 4)
	28 aload_2 (1, 4)
	29 iconst_0 (1, 4)
	30 iload_3 (1, 4)
	31 aload_0 (1, 4)
	32 iload_3 (1, 4)
	33 daload (1, 4)
	34 invokeinterface (1, 4)
	39 iinc (1, 4)
	42 goto (1, 4)
	45 aload_2 (0, 0)
	46 areturn (0, 0)

Method: createRowFieldMatrix
	0 aload_0 (1, 1)
	1 ifnonnull (1, 1)
	4 new (1, 1)
	7 dup (1, 1)
	8 invokespecial (1, 1)
	11 athrow (1, 1)
	12 aload_0 (0, 0)
	13 arraylength (0, 0)
	14 istore_1 (0, 0)
	15 iload_1 (1, 1)
	16 ifne (1, 1)
	19 new (1, 1)
	22 dup (1, 1)
	23 getstatic (1, 1)
	26 invokespecial (1, 1)
	29 athrow (1, 1)
	30 aload_0 (0, 0)
	31 iconst_0 (0, 0)
	32 aaload (0, 0)
	33 invokeinterface (0, 0)
	38 iconst_1 (0, 0)
	39 iload_1 (0, 0)
	40 invokestatic (0, 0)
	43 astore_2 (0, 0)
	44 iconst_0 (1, 4)
	45 istore_3 (1, 4)
	46 iload_3 (1, 4)
	47 iload_1 (1, 4)
	48 if_icmpge (1, 4)
	51 aload_2 (1, 4)
	52 iconst_0 (1, 4)
	53 iload_3 (1, 4)
	54 aload_0 (1, 4)
	55 iload_3 (1, 4)
	56 aaload (1, 4)
	57 invokeinterface (1, 4)
	62 iinc (1, 4)
	65 goto (1, 4)
	68 aload_2 (0, 0)
	69 areturn (0, 0)

Method: createColumnRealMatrix
	0 aload_0 (1, 1)
	1 ifnonnull (1, 1)
	4 new (1, 1)
	7 dup (1, 1)
	8 invokespecial (1, 1)
	11 athrow (1, 1)
	12 aload_0 (0, 0)
	13 arraylength (0, 0)
	14 istore_1 (0, 0)
	15 iload_1 (0, 0)
	16 iconst_1 (0, 0)
	17 invokestatic (0, 0)
	20 astore_2 (0, 0)
	21 iconst_0 (1, 4)
	22 istore_3 (1, 4)
	23 iload_3 (1, 4)
	24 iload_1 (1, 4)
	25 if_icmpge (1, 4)
	28 aload_2 (1, 4)
	29 iload_3 (1, 4)
	30 iconst_0 (1, 4)
	31 aload_0 (1, 4)
	32 iload_3 (1, 4)
	33 daload (1, 4)
	34 invokeinterface (1, 4)
	39 iinc (1, 4)
	42 goto (1, 4)
	45 aload_2 (0, 0)
	46 areturn (0, 0)

Method: createColumnFieldMatrix
	0 aload_0 (1, 1)
	1 ifnonnull (1, 1)
	4 new (1, 1)
	7 dup (1, 1)
	8 invokespecial (1, 1)
	11 athrow (1, 1)
	12 aload_0 (0, 0)
	13 arraylength (0, 0)
	14 istore_1 (0, 0)
	15 iload_1 (1, 1)
	16 ifne (1, 1)
	19 new (1, 1)
	22 dup (1, 1)
	23 getstatic (1, 1)
	26 invokespecial (1, 1)
	29 athrow (1, 1)
	30 aload_0 (0, 0)
	31 iconst_0 (0, 0)
	32 aaload (0, 0)
	33 invokeinterface (0, 0)
	38 iload_1 (0, 0)
	39 iconst_1 (0, 0)
	40 invokestatic (0, 0)
	43 astore_2 (0, 0)
	44 iconst_0 (1, 4)
	45 istore_3 (1, 4)
	46 iload_3 (1, 4)
	47 iload_1 (1, 4)
	48 if_icmpge (1, 4)
	51 aload_2 (1, 4)
	52 iload_3 (1, 4)
	53 iconst_0 (1, 4)
	54 aload_0 (1, 4)
	55 iload_3 (1, 4)
	56 aaload (1, 4)
	57 invokeinterface (1, 4)
	62 iinc (1, 4)
	65 goto (1, 4)
	68 aload_2 (0, 0)
	69 areturn (0, 0)

Method: isSymmetricInternal
	0 aload_0 (0, 0)
	1 invokeinterface (0, 0)
	6 istore (0, 0)
	8 iload (1, 1)
	10 aload_0 (1, 1)
	11 invokeinterface (1, 1)
	16 if_icmpeq (1, 1)
	19 iload_3 (2, 1)
	20 ifeq (2, 1)
	23 new (2, 1)
	26 dup (2, 1)
	27 iload (2, 1)
	29 aload_0 (2, 1)
	30 invokeinterface (2, 1)
	35 invokespecial (2, 1)
	38 athrow (2, 1)
	39 iconst_0 (2, 2)
	40 ireturn (2, 2)
	41 iconst_0 (1, 4)
	42 istore (1, 4)
	44 iload (1, 4)
	46 iload (1, 4)
	48 if_icmpge (1, 4)
	51 iload (2, 4)
	53 iconst_1 (2, 4)
	54 iadd (2, 4)
	55 istore (2, 4)
	57 iload (2, 4)
	59 iload (2, 4)
	61 if_icmpge (2, 4)
	64 aload_0 (2, 4)
	65 iload (2, 4)
	67 iload (2, 4)
	69 invokeinterface (2, 4)
	74 dstore (2, 4)
	76 aload_0 (2, 4)
	77 iload (2, 4)
	79 iload (2, 4)
	81 invokeinterface (2, 4)
	86 dstore (2, 4)
	88 dload (2, 1)
	90 dload (2, 1)
	92 dsub (2, 1)
	93 invokestatic (2, 1)
	96 dload (2, 1)
	98 invokestatic (3, 1)
	101 dload (3, 1)
	103 invokestatic (3, 1)
	106 invokestatic (3, 1)
	109 dload_1 (3, 1)
	110 dmul (3, 1)
	111 dcmpl (3, 1)
	112 ifle (3, 1)
	115 iload_3 (4, 1)
	116 ifeq (4, 1)
	119 new (4, 1)
	122 dup (4, 1)
	123 iload (4, 1)
	125 iload (4, 1)
	127 dload_1 (4, 1)
	128 invokespecial (4, 1)
	131 athrow (4, 1)
	132 iconst_0 (4, 2)
	133 ireturn (4, 2)
	134 iinc (4, 2)
	137 goto (4, 2)
	140 iinc (4, 2)
	143 goto (4, 2)
	146 iconst_1 (3, 2)
	147 ireturn (3, 2)

Method: checkSymmetric
	0 aload_0 (0, 0)
	1 dload_1 (0, 0)
	2 iconst_1 (0, 0)
	3 invokestatic (0, 0)
	6 pop (0, 0)
	7 return (0, 0)

Method: isSymmetric
	0 aload_0 (0, 0)
	1 dload_1 (0, 0)
	2 iconst_0 (0, 0)
	3 invokestatic (0, 0)
	6 ireturn (0, 0)

Method: checkMatrixIndex
	0 aload_0 (0, 0)
	1 iload_1 (0, 0)
	2 invokestatic (0, 0)
	5 aload_0 (0, 0)
	6 iload_2 (0, 0)
	7 invokestatic (0, 0)
	10 return (0, 0)

Method: checkRowIndex
	0 iload_1 (0, 1)
	1 iflt (0, 1)
	4 iload_1 (0, 1)
	5 aload_0 (0, 1)
	6 invokeinterface (1, 1)
	11 if_icmplt (1, 1)
	14 new (1, 1)
	17 dup (1, 1)
	18 getstatic (1, 1)
	21 iload_1 (1, 1)
	22 invokestatic (1, 1)
	25 iconst_0 (1, 1)
	26 invokestatic (1, 1)
	29 aload_0 (1, 1)
	30 invokeinterface (1, 1)
	35 iconst_1 (1, 1)
	36 isub (1, 1)
	37 invokestatic (1, 1)
	40 invokespecial (1, 1)
	43 athrow (1, 1)
	44 return (0, 0)

Method: checkColumnIndex
	0 iload_1 (1, 1)
	1 iflt (1, 1)
	4 iload_1 (1, 1)
	5 aload_0 (1, 1)
	6 invokeinterface (1, 1)
	11 if_icmplt (1, 1)
	14 new (1, 1)
	17 dup (1, 1)
	18 getstatic (1, 1)
	21 iload_1 (1, 1)
	22 invokestatic (1, 1)
	25 iconst_0 (1, 1)
	26 invokestatic (1, 1)
	29 aload_0 (1, 1)
	30 invokeinterface (1, 1)
	35 iconst_1 (1, 1)
	36 isub (1, 1)
	37 invokestatic (1, 1)
	40 invokespecial (1, 1)
	43 athrow (1, 1)
	44 return (0, 0)

Method: checkSubMatrixIndex
	0 aload_1 (1, 1)
	1 ifnonnull (1, 1)
	4 new (1, 1)
	7 dup (1, 1)
	8 invokespecial (1, 1)
	11 athrow (1, 1)
	12 aload_2 (1, 1)
	13 ifnonnull (1, 1)
	16 new (1, 1)
	19 dup (1, 1)
	20 invokespecial (1, 1)
	23 athrow (1, 1)
	24 aload_1 (1, 1)
	25 arraylength (1, 1)
	26 ifne (1, 1)
	29 new (1, 1)
	32 dup (1, 1)
	33 getstatic (1, 1)
	36 invokespecial (1, 1)
	39 athrow (1, 1)
	40 aload_2 (1, 1)
	41 arraylength (1, 1)
	42 ifne (1, 1)
	45 new (1, 1)
	48 dup (1, 1)
	49 getstatic (1, 1)
	52 invokespecial (1, 1)
	55 athrow (1, 1)
	56 aload_1 (1, 4)
	57 astore_3 (1, 4)
	58 aload_3 (1, 4)
	59 arraylength (1, 4)
	60 istore (1, 4)
	62 iconst_0 (1, 4)
	63 istore (1, 4)
	65 iload (1, 4)
	67 iload (1, 4)
	69 if_icmpge (1, 4)
	72 aload_3 (1, 4)
	73 iload (1, 4)
	75 iaload (1, 4)
	76 istore (1, 4)
	78 aload_0 (1, 4)
	79 iload (1, 4)
	81 invokestatic (1, 4)
	84 iinc (1, 4)
	87 goto (1, 4)
	90 aload_2 (1, 4)
	91 astore_3 (1, 4)
	92 aload_3 (1, 4)
	93 arraylength (1, 4)
	94 istore (1, 4)
	96 iconst_0 (1, 4)
	97 istore (1, 4)
	99 iload (1, 4)
	101 iload (1, 4)
	103 if_icmpge (1, 4)
	106 aload_3 (1, 4)
	107 iload (1, 4)
	109 iaload (1, 4)
	110 istore (1, 4)
	112 aload_0 (1, 4)
	113 iload (1, 4)
	115 invokestatic (1, 4)
	118 iinc (1, 4)
	121 goto (1, 4)
	124 return (0, 0)

Method: checkAdditionCompatible
	0 aload_0 (0, 1)
	1 invokeinterface (0, 1)
	6 aload_1 (0, 1)
	7 invokeinterface (0, 1)
	12 if_icmpne (0, 1)
	15 aload_0 (0, 1)
	16 invokeinterface (1, 1)
	21 aload_1 (1, 1)
	22 invokeinterface (1, 1)
	27 if_icmpeq (1, 1)
	30 new (1, 1)
	33 dup (1, 1)
	34 aload_0 (1, 1)
	35 invokeinterface (1, 1)
	40 aload_0 (1, 1)
	41 invokeinterface (1, 1)
	46 aload_1 (1, 1)
	47 invokeinterface (1, 1)
	52 aload_1 (1, 1)
	53 invokeinterface (1, 1)
	58 invokespecial (1, 1)
	61 athrow (1, 1)
	62 return (0, 0)

Method: checkSubtractionCompatible
	0 aload_0 (0, 1)
	1 invokeinterface (0, 1)
	6 aload_1 (0, 1)
	7 invokeinterface (0, 1)
	12 if_icmpne (0, 1)
	15 aload_0 (0, 1)
	16 invokeinterface (1, 1)
	21 aload_1 (1, 1)
	22 invokeinterface (1, 1)
	27 if_icmpeq (1, 1)
	30 new (1, 1)
	33 dup (1, 1)
	34 aload_0 (1, 1)
	35 invokeinterface (1, 1)
	40 aload_0 (1, 1)
	41 invokeinterface (1, 1)
	46 aload_1 (1, 1)
	47 invokeinterface (1, 1)
	52 aload_1 (1, 1)
	53 invokeinterface (1, 1)
	58 invokespecial (1, 1)
	61 athrow (1, 1)
	62 return (0, 0)

Method: checkMultiplicationCompatible
	0 aload_0 (1, 1)
	1 invokeinterface (1, 1)
	6 aload_1 (1, 1)
	7 invokeinterface (1, 1)
	12 if_icmpeq (1, 1)
	15 new (1, 1)
	18 dup (1, 1)
	19 aload_0 (1, 1)
	20 invokeinterface (1, 1)
	25 aload_1 (1, 1)
	26 invokeinterface (1, 1)
	31 invokespecial (1, 1)
	34 athrow (1, 1)
	35 return (0, 0)

Method: fractionMatrixToRealMatrix
	0 new (0, 0)
	3 dup (0, 0)
	4 invokespecial (0, 0)
	7 astore_1 (0, 0)
	8 aload_0 (0, 0)
	9 aload_1 (0, 0)
	10 invokeinterface (0, 0)
	15 pop (0, 0)
	16 aload_1 (0, 0)
	17 invokevirtual (0, 0)
	20 areturn (0, 0)

Method: bigFractionMatrixToRealMatrix
	0 new (0, 0)
	3 dup (0, 0)
	4 invokespecial (0, 0)
	7 astore_1 (0, 0)
	8 aload_0 (0, 0)
	9 aload_1 (0, 0)
	10 invokeinterface (0, 0)
	15 pop (0, 0)
	16 aload_1 (0, 0)
	17 invokevirtual (0, 0)
	20 areturn (0, 0)

Method: serializeRealVector
	0 aload_0 (0, 0)
	1 invokevirtual (0, 0)
	4 istore_2 (0, 0)
	5 aload_1 (0, 0)
	6 iload_2 (0, 0)
	7 invokevirtual (0, 0)
	10 iconst_0 (1, 4)
	11 istore_3 (1, 4)
	12 iload_3 (1, 4)
	13 iload_2 (1, 4)
	14 if_icmpge (1, 4)
	17 aload_1 (1, 4)
	18 aload_0 (1, 4)
	19 iload_3 (1, 4)
	20 invokevirtual (1, 4)
	23 invokevirtual (1, 4)
	26 iinc (1, 4)
	29 goto (1, 4)
	32 return (0, 0)

Method: deserializeRealVector
	0 aload_2 (0, 0)
	1 invokevirtual (0, 0)
	4 istore_3 (0, 0)
	5 iload_3 (0, 0)
	6 newarray (0, 0)
	8 astore (0, 0)
	10 iconst_0 (1, 4)
	11 istore (1, 4)
	13 iload (1, 4)
	15 iload_3 (1, 4)
	16 if_icmpge (1, 4)
	19 aload (1, 4)
	21 iload (1, 4)
	23 aload_2 (1, 4)
	24 invokevirtual (1, 4)
	27 dastore (1, 4)
	28 iinc (1, 4)
	31 goto (1, 4)
	34 new (0, 0)
	37 dup (0, 0)
	38 aload (0, 0)
	40 iconst_0 (0, 0)
	41 invokespecial (0, 0)
	44 astore (0, 0)
	46 aload_0 (0, 0)
	47 invokevirtual (0, 0)
	50 aload_1 (0, 0)
	51 invokevirtual (0, 0)
	54 astore (0, 0)
	56 aload (0, 0)
	58 iconst_1 (0, 0)
	59 invokevirtual (0, 0)
	62 aload (0, 0)
	64 aload_0 (0, 0)
	65 aload (0, 0)
	67 invokevirtual (0, 0)
	70 goto (0, 0)
	73 astore_3 (0, 0)
	74 new (0, 0)
	77 dup (0, 0)
	78 invokespecial (0, 0)
	81 astore (0, 0)
	83 aload (0, 0)
	85 aload_3 (0, 0)
	86 invokevirtual (0, 0)
	89 pop (0, 0)
	90 aload (0, 0)
	92 athrow (0, 0)
	93 astore_3 (0, 0)
	94 new (0, 0)
	97 dup (0, 0)
	98 invokespecial (0, 0)
	101 astore (0, 0)
	103 aload (0, 0)
	105 aload_3 (0, 0)
	106 invokevirtual (0, 0)
	109 pop (0, 0)
	110 aload (0, 0)
	112 athrow (0, 0)
	113 return (0, 0)

Method: serializeRealMatrix
	0 aload_0 (0, 0)
	1 invokeinterface (0, 0)
	6 istore_2 (0, 0)
	7 aload_0 (0, 0)
	8 invokeinterface (0, 0)
	13 istore_3 (0, 0)
	14 aload_1 (0, 0)
	15 iload_2 (0, 0)
	16 invokevirtual (0, 0)
	19 aload_1 (0, 0)
	20 iload_3 (0, 0)
	21 invokevirtual (0, 0)
	24 iconst_0 (1, 4)
	25 istore (1, 4)
	27 iload (1, 4)
	29 iload_2 (1, 4)
	30 if_icmpge (1, 4)
	33 iconst_0 (2, 4)
	34 istore (2, 4)
	36 iload (2, 4)
	38 iload_3 (2, 4)
	39 if_icmpge (2, 4)
	42 aload_1 (2, 4)
	43 aload_0 (2, 4)
	44 iload (2, 4)
	46 iload (2, 4)
	48 invokeinterface (2, 4)
	53 invokevirtual (2, 4)
	56 iinc (2, 4)
	59 goto (2, 4)
	62 iinc (2, 4)
	65 goto (2, 4)
	68 return (0, 0)

Method: deserializeRealMatrix
	0 aload_2 (0, 0)
	1 invokevirtual (0, 0)
	4 istore_3 (0, 0)
	5 aload_2 (0, 0)
	6 invokevirtual (0, 0)
	9 istore (0, 0)
	11 iload_3 (0, 0)
	12 iload (0, 0)
	14 multianewarray (0, 0)
	18 astore (0, 0)
	20 iconst_0 (1, 4)
	21 istore (1, 4)
	23 iload (1, 4)
	25 iload_3 (1, 4)
	26 if_icmpge (1, 4)
	29 aload (1, 4)
	31 iload (1, 4)
	33 aaload (1, 4)
	34 astore (1, 4)
	36 iconst_0 (2, 4)
	37 istore (2, 4)
	39 iload (2, 4)
	41 iload (2, 4)
	43 if_icmpge (2, 4)
	46 aload (2, 4)
	48 iload (2, 4)
	50 aload_2 (2, 4)
	51 invokevirtual (2, 4)
	54 dastore (2, 4)
	55 iinc (2, 4)
	58 goto (2, 4)
	61 iinc (2, 4)
	64 goto (2, 4)
	67 new (1, 4)
	70 dup (1, 4)
	71 aload (1, 4)
	73 iconst_0 (1, 4)
	74 invokespecial (1, 4)
	77 astore (1, 4)
	79 aload_0 (1, 4)
	80 invokevirtual (1, 4)
	83 aload_1 (1, 4)
	84 invokevirtual (1, 4)
	87 astore (1, 4)
	89 aload (1, 4)
	91 iconst_1 (1, 4)
	92 invokevirtual (1, 4)
	95 aload (1, 4)
	97 aload_0 (1, 4)
	98 aload (1, 4)
	100 invokevirtual (1, 4)
	103 goto (0, 0)
	106 astore_3 (0, 0)
	107 new (0, 0)
	110 dup (0, 0)
	111 invokespecial (0, 0)
	114 astore (0, 0)
	116 aload (0, 0)
	118 aload_3 (0, 0)
	119 invokevirtual (0, 0)
	122 pop (0, 0)
	123 aload (0, 0)
	125 athrow (0, 0)
	126 astore_3 (0, 0)
	127 new (0, 0)
	130 dup (0, 0)
	131 invokespecial (0, 0)
	134 astore (0, 0)
	136 aload (0, 0)
	138 aload_3 (0, 0)
	139 invokevirtual (0, 0)
	142 pop (0, 0)
	143 aload (0, 0)
	145 athrow (0, 0)
	146 return (0, 0)

Method: solveLowerTriangularSystem
	0 aload_0 (1, 1)
	1 ifnull (1, 1)
	4 aload_1 (1, 1)
	5 ifnull (1, 1)
	8 aload_0 (1, 1)
	9 invokeinterface (1, 1)
	14 aload_1 (1, 1)
	15 invokevirtual (1, 1)
	18 if_icmpeq (1, 1)
	21 new (1, 1)
	24 dup (1, 1)
	25 aload_0 (1, 1)
	26 ifnonnull (1, 1)
	29 iconst_0 (1, 1)
	30 goto (1, 1)
	33 aload_0 (1, 1)
	34 invokeinterface (1, 1)
	39 aload_1 (1, 1)
	40 ifnonnull (1, 1)
	43 iconst_0 (1, 1)
	44 goto (1, 1)
	47 aload_1 (1, 1)
	48 invokevirtual (1, 1)
	51 invokespecial (1, 1)
	54 athrow (1, 1)
	55 aload_0 (1, 1)
	56 invokeinterface (1, 1)
	61 aload_0 (1, 1)
	62 invokeinterface (1, 1)
	67 if_icmpeq (1, 1)
	70 new (1, 1)
	73 dup (1, 1)
	74 aload_0 (1, 1)
	75 invokeinterface (1, 1)
	80 aload_0 (1, 1)
	81 invokeinterface (1, 1)
	86 invokespecial (1, 1)
	89 athrow (1, 1)
	90 aload_0 (0, 0)
	91 invokeinterface (0, 0)
	96 istore_2 (0, 0)
	97 iconst_0 (1, 4)
	98 istore_3 (1, 4)
	99 iload_3 (1, 4)
	100 iload_2 (1, 4)
	101 if_icmpge (1, 4)
	104 aload_0 (1, 4)
	105 iload_3 (1, 4)
	106 iload_3 (1, 4)
	107 invokeinterface (1, 4)
	112 dstore (1, 4)
	114 dload (2, 1)
	116 invokestatic (2, 1)
	119 getstatic (2, 1)
	122 dcmpg (2, 1)
	123 ifge (2, 1)
	126 new (2, 1)
	129 dup (2, 1)
	130 getstatic (2, 1)
	133 iconst_0 (2, 1)
	134 anewarray (2, 1)
	137 invokespecial (2, 1)
	140 athrow (2, 1)
	141 aload_1 (1, 4)
	142 iload_3 (1, 4)
	143 invokevirtual (1, 4)
	146 dload (1, 4)
	148 ddiv (1, 4)
	149 dstore (1, 4)
	151 aload_1 (1, 4)
	152 iload_3 (1, 4)
	153 dload (1, 4)
	155 invokevirtual (1, 4)
	158 iload_3 (2, 4)
	159 iconst_1 (2, 4)
	160 iadd (2, 4)
	161 istore (2, 4)
	163 iload (2, 4)
	165 iload_2 (2, 4)
	166 if_icmpge (2, 4)
	169 aload_1 (2, 4)
	170 iload (2, 4)
	172 aload_1 (2, 4)
	173 iload (2, 4)
	175 invokevirtual (2, 4)
	178 dload (2, 4)
	180 aload_0 (2, 4)
	181 iload (2, 4)
	183 iload_3 (2, 4)
	184 invokeinterface (2, 4)
	189 dmul (2, 4)
	190 dsub (2, 4)
	191 invokevirtual (2, 4)
	194 iinc (2, 4)
	197 goto (2, 4)
	200 iinc (2, 4)
	203 goto (2, 4)
	206 return (0, 0)

Method: solveUpperTriangularSystem
	0 aload_0 (1, 1)
	1 ifnull (1, 1)
	4 aload_1 (1, 1)
	5 ifnull (1, 1)
	8 aload_0 (1, 1)
	9 invokeinterface (1, 1)
	14 aload_1 (1, 1)
	15 invokevirtual (1, 1)
	18 if_icmpeq (1, 1)
	21 new (1, 1)
	24 dup (1, 1)
	25 aload_0 (1, 1)
	26 ifnonnull (1, 1)
	29 iconst_0 (1, 1)
	30 goto (1, 1)
	33 aload_0 (1, 1)
	34 invokeinterface (1, 1)
	39 aload_1 (1, 1)
	40 ifnonnull (1, 1)
	43 iconst_0 (1, 1)
	44 goto (1, 1)
	47 aload_1 (1, 1)
	48 invokevirtual (1, 1)
	51 invokespecial (1, 1)
	54 athrow (1, 1)
	55 aload_0 (1, 1)
	56 invokeinterface (1, 1)
	61 aload_0 (1, 1)
	62 invokeinterface (1, 1)
	67 if_icmpeq (1, 1)
	70 new (1, 1)
	73 dup (1, 1)
	74 aload_0 (1, 1)
	75 invokeinterface (1, 1)
	80 aload_0 (1, 1)
	81 invokeinterface (1, 1)
	86 invokespecial (1, 1)
	89 athrow (1, 1)
	90 aload_0 (0, 0)
	91 invokeinterface (0, 0)
	96 istore_2 (0, 0)
	97 iload_2 (1, 4)
	98 iconst_1 (1, 4)
	99 isub (1, 4)
	100 istore_3 (1, 4)
	101 iload_3 (1, 4)
	102 iconst_m1 (1, 4)
	103 if_icmple (1, 4)
	106 aload_0 (1, 4)
	107 iload_3 (1, 4)
	108 iload_3 (1, 4)
	109 invokeinterface (1, 4)
	114 dstore (1, 4)
	116 dload (2, 1)
	118 invokestatic (2, 1)
	121 getstatic (2, 1)
	124 dcmpg (2, 1)
	125 ifge (2, 1)
	128 new (2, 1)
	131 dup (2, 1)
	132 getstatic (2, 1)
	135 iconst_0 (2, 1)
	136 anewarray (2, 1)
	139 invokespecial (2, 1)
	142 athrow (2, 1)
	143 aload_1 (1, 4)
	144 iload_3 (1, 4)
	145 invokevirtual (1, 4)
	148 dload (1, 4)
	150 ddiv (1, 4)
	151 dstore (1, 4)
	153 aload_1 (1, 4)
	154 iload_3 (1, 4)
	155 dload (1, 4)
	157 invokevirtual (1, 4)
	160 iload_3 (2, 4)
	161 iconst_1 (2, 4)
	162 isub (2, 4)
	163 istore (2, 4)
	165 iload (2, 4)
	167 iconst_m1 (2, 4)
	168 if_icmple (2, 4)
	171 aload_1 (2, 4)
	172 iload (2, 4)
	174 aload_1 (2, 4)
	175 iload (2, 4)
	177 invokevirtual (2, 4)
	180 dload (2, 4)
	182 aload_0 (2, 4)
	183 iload (2, 4)
	185 iload_3 (2, 4)
	186 invokeinterface (2, 4)
	191 dmul (2, 4)
	192 dsub (2, 4)
	193 invokevirtual (2, 4)
	196 iinc (2, 4)
	199 goto (2, 4)
	202 iinc (2, 4)
	205 goto (2, 4)
	208 return (0, 0)

Method: blockInverse
	0 aload_0 (0, 0)
	1 invokeinterface (0, 0)
	6 istore_2 (0, 0)
	7 aload_0 (1, 1)
	8 invokeinterface (1, 1)
	13 iload_2 (1, 1)
	14 if_icmpeq (1, 1)
	17 new (1, 1)
	20 dup (1, 1)
	21 aload_0 (1, 1)
	22 invokeinterface (1, 1)
	27 aload_0 (1, 1)
	28 invokeinterface (1, 1)
	33 invokespecial (1, 1)
	36 athrow (1, 1)
	37 iload_1 (0, 0)
	38 iconst_1 (0, 0)
	39 iadd (0, 0)
	40 istore_3 (0, 0)
	41 aload_0 (0, 0)
	42 iconst_0 (0, 0)
	43 iload_1 (0, 0)
	44 iconst_0 (0, 0)
	45 iload_1 (0, 0)
	46 invokeinterface (0, 0)
	51 astore (0, 0)
	53 aload_0 (0, 0)
	54 iconst_0 (0, 0)
	55 iload_1 (0, 0)
	56 iload_3 (0, 0)
	57 iload_2 (0, 0)
	58 iconst_1 (0, 0)
	59 isub (0, 0)
	60 invokeinterface (0, 0)
	65 astore (0, 0)
	67 aload_0 (0, 0)
	68 iload_3 (0, 0)
	69 iload_2 (0, 0)
	70 iconst_1 (0, 0)
	71 isub (0, 0)
	72 iconst_0 (0, 0)
	73 iload_1 (0, 0)
	74 invokeinterface (0, 0)
	79 astore (0, 0)
	81 aload_0 (0, 0)
	82 iload_3 (0, 0)
	83 iload_2 (0, 0)
	84 iconst_1 (0, 0)
	85 isub (0, 0)
	86 iload_3 (0, 0)
	87 iload_2 (0, 0)
	88 iconst_1 (0, 0)
	89 isub (0, 0)
	90 invokeinterface (0, 0)
	95 astore (0, 0)
	97 new (0, 0)
	100 dup (0, 0)
	101 aload (0, 0)
	103 invokespecial (0, 0)
	106 astore (0, 0)
	108 aload (0, 0)
	110 invokevirtual (0, 0)
	113 astore (0, 0)
	115 aload (1, 1)
	117 invokeinterface (1, 1)
	122 ifne (1, 1)
	125 new (1, 1)
	128 dup (1, 1)
	129 invokespecial (1, 1)
	132 athrow (1, 1)
	133 aload (0, 0)
	135 invokeinterface (0, 0)
	140 astore (0, 0)
	142 new (0, 0)
	145 dup (0, 0)
	146 aload (0, 0)
	148 invokespecial (0, 0)
	151 astore (0, 0)
	153 aload (0, 0)
	155 invokevirtual (0, 0)
	158 astore (0, 0)
	160 aload (1, 1)
	162 invokeinterface (1, 1)
	167 ifne (1, 1)
	170 new (1, 1)
	173 dup (1, 1)
	174 invokespecial (1, 1)
	177 athrow (1, 1)
	178 aload (0, 0)
	180 invokeinterface (0, 0)
	185 astore (0, 0)
	187 aload (0, 0)
	189 aload (0, 0)
	191 aload (0, 0)
	193 invokeinterface (0, 0)
	198 aload (0, 0)
	200 invokeinterface (0, 0)
	205 invokeinterface (0, 0)
	210 astore (0, 0)
	212 new (0, 0)
	215 dup (0, 0)
	216 aload (0, 0)
	218 invokespecial (0, 0)
	221 astore (0, 0)
	223 aload (0, 0)
	225 invokevirtual (0, 0)
	228 astore (0, 0)
	230 aload (1, 1)
	232 invokeinterface (1, 1)
	237 ifne (1, 1)
	240 new (1, 1)
	243 dup (1, 1)
	244 invokespecial (1, 1)
	247 athrow (1, 1)
	248 aload (0, 0)
	250 invokeinterface (0, 0)
	255 astore (0, 0)
	257 aload (0, 0)
	259 aload (0, 0)
	261 aload (0, 0)
	263 invokeinterface (0, 0)
	268 aload (0, 0)
	270 invokeinterface (0, 0)
	275 invokeinterface (0, 0)
	280 astore (0, 0)
	282 new (0, 0)
	285 dup (0, 0)
	286 aload (0, 0)
	288 invokespecial (0, 0)
	291 astore (0, 0)
	293 aload (0, 0)
	295 invokevirtual (0, 0)
	298 astore (0, 0)
	300 aload (1, 1)
	302 invokeinterface (1, 1)
	307 ifne (1, 1)
	310 new (1, 1)
	313 dup (1, 1)
	314 invokespecial (1, 1)
	317 athrow (1, 1)
	318 aload (0, 0)
	320 invokeinterface (0, 0)
	325 astore (0, 0)
	327 aload (0, 0)
	329 aload (0, 0)
	331 invokeinterface (0, 0)
	336 aload (0, 0)
	338 invokeinterface (0, 0)
	343 ldc2_w (0, 0)
	346 invokeinterface (0, 0)
	351 astore (0, 0)
	353 aload (0, 0)
	355 aload (0, 0)
	357 invokeinterface (0, 0)
	362 aload (0, 0)
	364 invokeinterface (0, 0)
	369 ldc2_w (0, 0)
	372 invokeinterface (0, 0)
	377 astore (0, 0)
	379 new (0, 0)
	382 dup (0, 0)
	383 iload_2 (0, 0)
	384 iload_2 (0, 0)
	385 invokespecial (0, 0)
	388 astore (0, 0)
	390 aload (0, 0)
	392 aload (0, 0)
	394 invokeinterface (0, 0)
	399 iconst_0 (0, 0)
	400 iconst_0 (0, 0)
	401 invokeinterface (0, 0)
	406 aload (0, 0)
	408 aload (0, 0)
	410 invokeinterface (0, 0)
	415 iconst_0 (0, 0)
	416 iload_3 (0, 0)
	417 invokeinterface (0, 0)
	422 aload (0, 0)
	424 aload (0, 0)
	426 invokeinterface (0, 0)
	431 iload_3 (0, 0)
	432 iconst_0 (0, 0)
	433 invokeinterface (0, 0)
	438 aload (0, 0)
	440 aload (0, 0)
	442 invokeinterface (0, 0)
	447 iload_3 (0, 0)
	448 iload_3 (0, 0)
	449 invokeinterface (0, 0)
	454 aload (0, 0)
	456 areturn (0, 0)

Method: inverse
	0 aload_0 (0, 0)
	1 invokestatic (0, 0)
	4 aload_0 (1, 1)
	5 invokeinterface (1, 1)
	10 ifne (1, 1)
	13 new (1, 1)
	16 dup (1, 1)
	17 aload_0 (1, 1)
	18 invokeinterface (1, 1)
	23 aload_0 (1, 1)
	24 invokeinterface (1, 1)
	29 invokespecial (1, 1)
	32 athrow (1, 1)
	33 aload_0 (1, 1)
	34 instanceof (1, 1)
	37 ifeq (1, 1)
	40 aload_0 (1, 1)
	41 checkcast (1, 1)
	44 dload_1 (1, 1)
	45 invokevirtual (1, 1)
	48 areturn (1, 1)
	49 new (1, 2)
	52 dup (1, 2)
	53 aload_0 (1, 2)
	54 dload_1 (1, 2)
	55 invokespecial (1, 2)
	58 astore_3 (1, 2)
	59 aload_3 (1, 2)
	60 invokevirtual (1, 2)
	63 invokeinterface (1, 2)
	68 areturn (1, 2)

Method: <clinit>
	0 invokestatic (0, 0)
	3 putstatic (0, 0)
	6 new (0, 4)
	9 dup (0, 4)
	10 ldc (0, 4)
	12 ldc (0, 4)
	14 ldc (0, 4)
	16 ldc (0, 4)
	18 ldc (0, 4)
	20 ldc (0, 4)
	22 invokespecial (0, 4)
	25 putstatic (0, 4)
	28 return (0, 4)

