Method: <init>
	0 aload_0 (0, 0)
	1 getstatic (0, 0)
	2 org/apache/commons/math3/fraction/Fraction.ZERO:Lorg/apache/commons/math3/fraction/Fraction; (0, 0)
	4 invokespecial (0, 0)
	5 org/apache/commons/math3/linear/DefaultFieldMatrixPreservingVisitor.<init>:(Lorg/apache/commons/math3/FieldElement;)V (0, 0)
	7 return (0, 0)

Method: start
	0 aload_0 (0, 0)
	1 iload_1 (0, 0)
	2 iload_2 (0, 0)
	3 multianewarray (0, 0)
	4 [[D (0, 0)
	6 -75 (0, 0)
	7 putfield (0, 0)
	8 org/apache/commons/math3/linear/MatrixUtils$FractionMatrixConverter.data:[[D (0, 0)
	10 return (0, 0)

Method: visit
	0 aload_0 (0, 0)
	1 iload_1 (0, 0)
	2 iload_2 (0, 0)
	3 aload_3 (0, 0)
	4 checkcast (0, 0)
	5 org/apache/commons/math3/fraction/Fraction (0, 0)
	7 invokevirtual (0, 0)
	8 org/apache/commons/math3/linear/MatrixUtils$FractionMatrixConverter.visit:(IILorg/apache/commons/math3/fraction/Fraction;)V (0, 0)
	10 return (0, 0)

Method: getConvertedMatrix
	0 new (0, 0)
	1 org/apache/commons/math3/linear/Array2DRowRealMatrix (0, 0)
	3 dup (0, 0)
	4 aload_0 (0, 0)
	5 getfield (0, 0)
	6 org/apache/commons/math3/linear/MatrixUtils$FractionMatrixConverter.data:[[D (0, 0)
	8 iconst_0 (0, 0)
	9 invokespecial (0, 0)
	10 org/apache/commons/math3/linear/Array2DRowRealMatrix.<init>:([[DZ)V (0, 0)
	12 areturn (0, 0)

