Method: <init>
	0 aload_0 (0, 0)
	1 dload_1 (0, 0)
	2 invokestatic (0, 0)
	3 java/lang/Double.valueOf:(D)Ljava/lang/Double; (0, 0)
	5 dload (0, 0)
	6 #4 (0, 0)
	7 invokestatic (0, 0)
	8 java/lang/Double.valueOf:(D)Ljava/lang/Double; (0, 0)
	10 iconst_0 (0, 0)
	11 invokespecial (0, 0)
	12 org/apache/commons/math3/exception/NumberIsTooSmallException.<init>:(Ljava/lang/Number;Ljava/lang/Number;Z)V (0, 0)
	14 aload_0 (0, 0)
	15 iload_3 (0, 0)
	16 putfield (0, 0)
	17 org/apache/commons/math3/linear/NonPositiveDefiniteMatrixException.index:I (0, 0)
	19 aload_0 (0, 0)
	20 dload (0, 0)
	21 #4 (0, 0)
	22 putfield (0, 0)
	23 org/apache/commons/math3/linear/NonPositiveDefiniteMatrixException.threshold:D (0, 0)
	25 aload_0 (0, 0)
	26 invokevirtual (0, 0)
	27 org/apache/commons/math3/linear/NonPositiveDefiniteMatrixException.getContext:()Lorg/apache/commons/math3/exception/util/ExceptionContext; (0, 0)
	29 astore (0, 0)
	30 #6 (0, 0)
	31 aload (0, 0)
	32 #6 (0, 0)
	33 getstatic (0, 0)
	34 org/apache/commons/math3/exception/util/LocalizedFormats.NOT_POSITIVE_DEFINITE_MATRIX:Lorg/apache/commons/math3/exception/util/LocalizedFormats; (0, 0)
	36 iconst_0 (0, 0)
	37 anewarray (0, 0)
	38 java/lang/Object (0, 0)
	40 invokevirtual (0, 0)
	41 org/apache/commons/math3/exception/util/ExceptionContext.addMessage:(Lorg/apache/commons/math3/exception/util/Localizable;[Ljava/lang/Object;)V (0, 0)
	43 aload (0, 0)
	44 #6 (0, 0)
	45 getstatic (0, 0)
	46 org/apache/commons/math3/exception/util/LocalizedFormats.ARRAY_ELEMENT:Lorg/apache/commons/math3/exception/util/LocalizedFormats; (0, 0)
	48 iconst_2 (0, 0)
	49 anewarray (0, 0)
	50 java/lang/Object (0, 0)
	52 dup (0, 0)
	53 iconst_0 (0, 0)
	54 dload_1 (0, 0)
	55 invokestatic (0, 0)
	56 java/lang/Double.valueOf:(D)Ljava/lang/Double; (0, 0)
	58 aastore (0, 0)
	59 dup (0, 0)
	60 iconst_1 (0, 0)
	61 iload_3 (0, 0)
	62 invokestatic (0, 0)
	63 java/lang/Integer.valueOf:(I)Ljava/lang/Integer; (0, 0)
	65 aastore (0, 0)
	66 invokevirtual (0, 0)
	67 org/apache/commons/math3/exception/util/ExceptionContext.addMessage:(Lorg/apache/commons/math3/exception/util/Localizable;[Ljava/lang/Object;)V (0, 0)
	69 return (0, 0)

Method: getRow
	0 aload_0 (0, 0)
	1 getfield (0, 0)
	2 org/apache/commons/math3/linear/NonPositiveDefiniteMatrixException.index:I (0, 0)
	4 ireturn (0, 0)

Method: getColumn
	0 aload_0 (0, 0)
	1 getfield (0, 0)
	2 org/apache/commons/math3/linear/NonPositiveDefiniteMatrixException.index:I (0, 0)
	4 ireturn (0, 0)

Method: getThreshold
	0 aload_0 (0, 0)
	1 getfield (0, 0)
	2 org/apache/commons/math3/linear/NonPositiveDefiniteMatrixException.threshold:D (0, 0)
	4 dreturn (0, 0)

