Method: <init>
	0 aload_0 (0, 0)
	1 invokespecial (0, 0)
	2 org/apache/commons/math3/linear/AbstractRealMatrix.<init>:()V (0, 0)
	4 aload_0 (0, 0)
	5 aload_1 (0, 0)
	6 getfield (0, 0)
	7 org/apache/commons/math3/linear/OpenMapRealMatrix.rows:I (0, 0)
	9 putfield (0, 0)
	10 org/apache/commons/math3/linear/OpenMapRealMatrix.rows:I (0, 0)
	12 aload_0 (0, 0)
	13 aload_1 (0, 0)
	14 getfield (0, 0)
	15 org/apache/commons/math3/linear/OpenMapRealMatrix.columns:I (0, 0)
	17 putfield (0, 0)
	18 org/apache/commons/math3/linear/OpenMapRealMatrix.columns:I (0, 0)
	20 aload_0 (0, 0)
	21 new (0, 0)
	22 org/apache/commons/math3/util/OpenIntToDoubleHashMap (0, 0)
	24 dup (0, 0)
	25 aload_1 (0, 0)
	26 getfield (0, 0)
	27 org/apache/commons/math3/linear/OpenMapRealMatrix.entries:Lorg/apache/commons/math3/util/OpenIntToDoubleHashMap; (0, 0)
	29 invokespecial (0, 0)
	30 org/apache/commons/math3/util/OpenIntToDoubleHashMap.<init>:(Lorg/apache/commons/math3/util/OpenIntToDoubleHashMap;)V (0, 0)
	32 putfield (0, 0)
	33 org/apache/commons/math3/linear/OpenMapRealMatrix.entries:Lorg/apache/commons/math3/util/OpenIntToDoubleHashMap; (0, 0)
	35 return (0, 0)

Method: copy
	0 aload_0 (0, 0)
	1 invokevirtual (0, 0)
	2 org/apache/commons/math3/linear/OpenMapRealMatrix.copy:()Lorg/apache/commons/math3/linear/OpenMapRealMatrix; (0, 0)
	4 areturn (0, 0)

Method: createMatrix
	0 aload_0 (0, 0)
	1 iload_1 (0, 0)
	2 iload_2 (0, 0)
	3 invokevirtual (0, 0)
	4 org/apache/commons/math3/linear/OpenMapRealMatrix.createMatrix:(II)Lorg/apache/commons/math3/linear/OpenMapRealMatrix; (0, 0)
	6 areturn (0, 0)

Method: getColumnDimension
	0 aload_0 (0, 0)
	1 getfield (0, 0)
	2 org/apache/commons/math3/linear/OpenMapRealMatrix.columns:I (0, 0)
	4 ireturn (0, 0)

Method: add
	0 aload_0 (0, 0)
	1 aload_1 (0, 0)
	2 invokestatic (0, 0)
	3 org/apache/commons/math3/linear/MatrixUtils.checkAdditionCompatible:(Lorg/apache/commons/math3/linear/AnyMatrix;Lorg/apache/commons/math3/linear/AnyMatrix;)V (0, 0)
	5 new (0, 0)
	6 org/apache/commons/math3/linear/OpenMapRealMatrix (0, 0)
	8 dup (0, 0)
	9 aload_0 (0, 0)
	10 invokespecial (0, 0)
	11 org/apache/commons/math3/linear/OpenMapRealMatrix.<init>:(Lorg/apache/commons/math3/linear/OpenMapRealMatrix;)V (0, 0)
	13 astore_2 (0, 0)
	14 aload_1 (1, 4)
	15 getfield (1, 4)
	16 org/apache/commons/math3/linear/OpenMapRealMatrix.entries:Lorg/apache/commons/math3/util/OpenIntToDoubleHashMap; (1, 4)
	18 invokevirtual (1, 4)
	19 org/apache/commons/math3/util/OpenIntToDoubleHashMap.iterator:()Lorg/apache/commons/math3/util/OpenIntToDoubleHashMap$Iterator; (1, 4)
	21 astore_3 (1, 4)
	22 aload_3 (1, 4)
	23 invokevirtual (1, 4)
	24 org/apache/commons/math3/util/OpenIntToDoubleHashMap$Iterator.hasNext:()Z (1, 4)
	26 ifeq (1, 4)
	27 56 (1, 4)
	29 aload_3 (1, 4)
	30 invokevirtual (1, 4)
	31 org/apache/commons/math3/util/OpenIntToDoubleHashMap$Iterator.advance:()V (1, 4)
	33 aload_3 (1, 4)
	34 invokevirtual (1, 4)
	35 org/apache/commons/math3/util/OpenIntToDoubleHashMap$Iterator.key:()I (1, 4)
	37 aload_0 (1, 4)
	38 getfield (1, 4)
	39 org/apache/commons/math3/linear/OpenMapRealMatrix.columns:I (1, 4)
	41 idiv (1, 4)
	42 istore (1, 4)
	43 #4 (1, 4)
	44 aload_3 (1, 4)
	45 invokevirtual (1, 4)
	46 org/apache/commons/math3/util/OpenIntToDoubleHashMap$Iterator.key:()I (1, 4)
	48 iload (1, 4)
	49 #4 (1, 4)
	50 aload_0 (1, 4)
	51 getfield (1, 4)
	52 org/apache/commons/math3/linear/OpenMapRealMatrix.columns:I (1, 4)
	54 imul (1, 4)
	55 isub (1, 4)
	56 istore (1, 4)
	57 #5 (1, 4)
	58 aload_2 (1, 4)
	59 iload (1, 4)
	60 #4 (1, 4)
	61 iload (1, 4)
	62 #5 (1, 4)
	63 aload_0 (1, 4)
	64 iload (1, 4)
	65 #4 (1, 4)
	66 iload (1, 4)
	67 #5 (1, 4)
	68 invokevirtual (1, 4)
	69 org/apache/commons/math3/linear/OpenMapRealMatrix.getEntry:(II)D (1, 4)
	71 aload_3 (1, 4)
	72 invokevirtual (1, 4)
	73 org/apache/commons/math3/util/OpenIntToDoubleHashMap$Iterator.value:()D (1, 4)
	75 dadd (1, 4)
	76 invokevirtual (1, 4)
	77 org/apache/commons/math3/linear/OpenMapRealMatrix.setEntry:(IID)V (1, 4)
	79 goto (0, 0)
	80 -57 (0, 0)
	82 aload_2 (0, 0)
	83 areturn (0, 0)

Method: subtract
	0 aload_0 (0, 0)
	1 aload_1 (0, 0)
	2 invokevirtual (0, 0)
	3 org/apache/commons/math3/linear/OpenMapRealMatrix.subtract:(Lorg/apache/commons/math3/linear/RealMatrix;)Lorg/apache/commons/math3/linear/OpenMapRealMatrix; (0, 0)
	5 areturn (0, 0)

Method: multiply
	0 aload_0 (0, 0)
	1 aload_1 (0, 0)
	2 invokestatic (0, 0)
	3 org/apache/commons/math3/linear/MatrixUtils.checkMultiplicationCompatible:(Lorg/apache/commons/math3/linear/AnyMatrix;Lorg/apache/commons/math3/linear/AnyMatrix;)V (0, 0)
	5 aload_1 (0, 0)
	6 invokevirtual (0, 0)
	7 org/apache/commons/math3/linear/OpenMapRealMatrix.getColumnDimension:()I (0, 0)
	9 istore_2 (0, 0)
	10 new (0, 0)
	11 org/apache/commons/math3/linear/OpenMapRealMatrix (0, 0)
	13 dup (0, 0)
	14 aload_0 (0, 0)
	15 getfield (0, 0)
	16 org/apache/commons/math3/linear/OpenMapRealMatrix.rows:I (0, 0)
	18 iload_2 (0, 0)
	19 invokespecial (0, 0)
	20 org/apache/commons/math3/linear/OpenMapRealMatrix.<init>:(II)V (0, 0)
	22 astore_3 (0, 0)
	23 aload_0 (1, 4)
	24 getfield (1, 4)
	25 org/apache/commons/math3/linear/OpenMapRealMatrix.entries:Lorg/apache/commons/math3/util/OpenIntToDoubleHashMap; (1, 4)
	27 invokevirtual (1, 4)
	28 org/apache/commons/math3/util/OpenIntToDoubleHashMap.iterator:()Lorg/apache/commons/math3/util/OpenIntToDoubleHashMap$Iterator; (1, 4)
	30 astore (1, 4)
	31 #4 (1, 4)
	32 aload (1, 4)
	33 #4 (1, 4)
	34 invokevirtual (1, 4)
	35 org/apache/commons/math3/util/OpenIntToDoubleHashMap$Iterator.hasNext:()Z (1, 4)
	37 ifeq (1, 4)
	38 146 (1, 4)
	40 aload (1, 4)
	41 #4 (1, 4)
	42 invokevirtual (1, 4)
	43 org/apache/commons/math3/util/OpenIntToDoubleHashMap$Iterator.advance:()V (1, 4)
	45 aload (1, 4)
	46 #4 (1, 4)
	47 invokevirtual (1, 4)
	48 org/apache/commons/math3/util/OpenIntToDoubleHashMap$Iterator.value:()D (1, 4)
	50 dstore (1, 4)
	51 #5 (1, 4)
	52 aload (1, 4)
	53 #4 (1, 4)
	54 invokevirtual (1, 4)
	55 org/apache/commons/math3/util/OpenIntToDoubleHashMap$Iterator.key:()I (1, 4)
	57 istore (1, 4)
	58 #7 (1, 4)
	59 iload (1, 4)
	60 #7 (1, 4)
	61 aload_0 (1, 4)
	62 getfield (1, 4)
	63 org/apache/commons/math3/linear/OpenMapRealMatrix.columns:I (1, 4)
	65 idiv (1, 4)
	66 istore (1, 4)
	67 #8 (1, 4)
	68 iload (1, 4)
	69 #7 (1, 4)
	70 aload_0 (1, 4)
	71 getfield (1, 4)
	72 org/apache/commons/math3/linear/OpenMapRealMatrix.columns:I (1, 4)
	74 irem (1, 4)
	75 istore (1, 4)
	76 #9 (1, 4)
	77 iconst_0 (2, 4)
	78 istore (2, 4)
	79 #10 (2, 4)
	80 iload (2, 4)
	81 #10 (2, 4)
	82 iload_2 (2, 4)
	83 if_icmpge (2, 4)
	84 97 (2, 4)
	86 aload_1 (2, 4)
	87 iload (2, 4)
	88 #9 (2, 4)
	89 iload (2, 4)
	90 #10 (2, 4)
	91 invokespecial (2, 4)
	92 org/apache/commons/math3/linear/OpenMapRealMatrix.computeKey:(II)I (2, 4)
	94 istore (2, 4)
	95 #11 (2, 4)
	96 aload_1 (3, 1)
	97 getfield (3, 1)
	98 org/apache/commons/math3/linear/OpenMapRealMatrix.entries:Lorg/apache/commons/math3/util/OpenIntToDoubleHashMap; (3, 1)
	100 iload (3, 1)
	101 #11 (3, 1)
	102 invokevirtual (3, 1)
	103 org/apache/commons/math3/util/OpenIntToDoubleHashMap.containsKey:(I)Z (3, 1)
	105 ifeq (3, 1)
	106 69 (3, 1)
	108 aload_3 (3, 1)
	109 iload (3, 1)
	110 #8 (3, 1)
	111 iload (3, 1)
	112 #10 (3, 1)
	113 invokespecial (3, 1)
	114 org/apache/commons/math3/linear/OpenMapRealMatrix.computeKey:(II)I (3, 1)
	116 istore (3, 1)
	117 #12 (3, 1)
	118 aload_3 (3, 1)
	119 getfield (3, 1)
	120 org/apache/commons/math3/linear/OpenMapRealMatrix.entries:Lorg/apache/commons/math3/util/OpenIntToDoubleHashMap; (3, 1)
	122 iload (3, 1)
	123 #12 (3, 1)
	124 invokevirtual (3, 1)
	125 org/apache/commons/math3/util/OpenIntToDoubleHashMap.get:(I)D (3, 1)
	127 dload (3, 1)
	128 #5 (3, 1)
	129 aload_1 (3, 1)
	130 getfield (3, 1)
	131 org/apache/commons/math3/linear/OpenMapRealMatrix.entries:Lorg/apache/commons/math3/util/OpenIntToDoubleHashMap; (3, 1)
	133 iload (3, 1)
	134 #11 (3, 1)
	135 invokevirtual (3, 1)
	136 org/apache/commons/math3/util/OpenIntToDoubleHashMap.get:(I)D (3, 1)
	138 dmul (3, 1)
	139 dadd (3, 1)
	140 dstore (3, 1)
	141 #13 (3, 1)
	142 dload (4, 1)
	143 #13 (4, 1)
	144 dconst_0 (4, 1)
	145 dcmpl (4, 1)
	146 ifne (4, 1)
	147 16 (4, 1)
	149 aload_3 (4, 1)
	150 getfield (4, 1)
	151 org/apache/commons/math3/linear/OpenMapRealMatrix.entries:Lorg/apache/commons/math3/util/OpenIntToDoubleHashMap; (4, 1)
	153 iload (4, 1)
	154 #12 (4, 1)
	155 invokevirtual (4, 1)
	156 org/apache/commons/math3/util/OpenIntToDoubleHashMap.remove:(I)D (4, 1)
	158 pop2 (4, 1)
	159 goto (4, 1)
	160 15 (4, 1)
	162 aload_3 (5, 2)
	163 getfield (5, 2)
	164 org/apache/commons/math3/linear/OpenMapRealMatrix.entries:Lorg/apache/commons/math3/util/OpenIntToDoubleHashMap; (5, 2)
	166 iload (5, 2)
	167 #12 (5, 2)
	168 dload (5, 2)
	169 #13 (5, 2)
	170 invokevirtual (5, 2)
	171 org/apache/commons/math3/util/OpenIntToDoubleHashMap.put:(ID)D (5, 2)
	173 pop2 (5, 2)
	174 iinc (5, 2)
	175 #10 (5, 2)
	176 -89 (5, 2)
	177 goto (5, 2)
	178 -97 (5, 2)
	180 goto (2, 4)
	181 -148 (2, 4)
	183 aload_3 (2, 4)
	184 areturn (2, 4)

Method: getEntry
	0 aload_0 (0, 0)
	1 iload_1 (0, 0)
	2 invokestatic (0, 0)
	3 org/apache/commons/math3/linear/MatrixUtils.checkRowIndex:(Lorg/apache/commons/math3/linear/AnyMatrix;I)V (0, 0)
	5 aload_0 (0, 0)
	6 iload_2 (0, 0)
	7 invokestatic (0, 0)
	8 org/apache/commons/math3/linear/MatrixUtils.checkColumnIndex:(Lorg/apache/commons/math3/linear/AnyMatrix;I)V (0, 0)
	10 aload_0 (0, 0)
	11 getfield (0, 0)
	12 org/apache/commons/math3/linear/OpenMapRealMatrix.entries:Lorg/apache/commons/math3/util/OpenIntToDoubleHashMap; (0, 0)
	14 aload_0 (0, 0)
	15 iload_1 (0, 0)
	16 iload_2 (0, 0)
	17 invokespecial (0, 0)
	18 org/apache/commons/math3/linear/OpenMapRealMatrix.computeKey:(II)I (0, 0)
	20 invokevirtual (0, 0)
	21 org/apache/commons/math3/util/OpenIntToDoubleHashMap.get:(I)D (0, 0)
	23 dreturn (0, 0)

Method: getRowDimension
	0 aload_0 (0, 0)
	1 getfield (0, 0)
	2 org/apache/commons/math3/linear/OpenMapRealMatrix.rows:I (0, 0)
	4 ireturn (0, 0)

Method: setEntry
	0 aload_0 (0, 0)
	1 iload_1 (0, 0)
	2 invokestatic (0, 0)
	3 org/apache/commons/math3/linear/MatrixUtils.checkRowIndex:(Lorg/apache/commons/math3/linear/AnyMatrix;I)V (0, 0)
	5 aload_0 (0, 0)
	6 iload_2 (0, 0)
	7 invokestatic (0, 0)
	8 org/apache/commons/math3/linear/MatrixUtils.checkColumnIndex:(Lorg/apache/commons/math3/linear/AnyMatrix;I)V (0, 0)
	10 dload_3 (1, 1)
	11 dconst_0 (1, 1)
	12 dcmpl (1, 1)
	13 ifne (1, 1)
	14 20 (1, 1)
	16 aload_0 (1, 1)
	17 getfield (1, 1)
	18 org/apache/commons/math3/linear/OpenMapRealMatrix.entries:Lorg/apache/commons/math3/util/OpenIntToDoubleHashMap; (1, 1)
	20 aload_0 (1, 1)
	21 iload_1 (1, 1)
	22 iload_2 (1, 1)
	23 invokespecial (1, 1)
	24 org/apache/commons/math3/linear/OpenMapRealMatrix.computeKey:(II)I (1, 1)
	26 invokevirtual (1, 1)
	27 org/apache/commons/math3/util/OpenIntToDoubleHashMap.remove:(I)D (1, 1)
	29 pop2 (1, 1)
	30 goto (1, 1)
	31 18 (1, 1)
	33 aload_0 (2, 2)
	34 getfield (2, 2)
	35 org/apache/commons/math3/linear/OpenMapRealMatrix.entries:Lorg/apache/commons/math3/util/OpenIntToDoubleHashMap; (2, 2)
	37 aload_0 (2, 2)
	38 iload_1 (2, 2)
	39 iload_2 (2, 2)
	40 invokespecial (2, 2)
	41 org/apache/commons/math3/linear/OpenMapRealMatrix.computeKey:(II)I (2, 2)
	43 dload_3 (2, 2)
	44 invokevirtual (2, 2)
	45 org/apache/commons/math3/util/OpenIntToDoubleHashMap.put:(ID)D (2, 2)
	47 pop2 (2, 2)
	48 return (0, 0)

Method: addToEntry
	0 aload_0 (0, 0)
	1 iload_1 (0, 0)
	2 invokestatic (0, 0)
	3 org/apache/commons/math3/linear/MatrixUtils.checkRowIndex:(Lorg/apache/commons/math3/linear/AnyMatrix;I)V (0, 0)
	5 aload_0 (0, 0)
	6 iload_2 (0, 0)
	7 invokestatic (0, 0)
	8 org/apache/commons/math3/linear/MatrixUtils.checkColumnIndex:(Lorg/apache/commons/math3/linear/AnyMatrix;I)V (0, 0)
	10 aload_0 (0, 0)
	11 iload_1 (0, 0)
	12 iload_2 (0, 0)
	13 invokespecial (0, 0)
	14 org/apache/commons/math3/linear/OpenMapRealMatrix.computeKey:(II)I (0, 0)
	16 istore (0, 0)
	17 #5 (0, 0)
	18 aload_0 (0, 0)
	19 getfield (0, 0)
	20 org/apache/commons/math3/linear/OpenMapRealMatrix.entries:Lorg/apache/commons/math3/util/OpenIntToDoubleHashMap; (0, 0)
	22 iload (0, 0)
	23 #5 (0, 0)
	24 invokevirtual (0, 0)
	25 org/apache/commons/math3/util/OpenIntToDoubleHashMap.get:(I)D (0, 0)
	27 dload_3 (0, 0)
	28 dadd (0, 0)
	29 dstore (0, 0)
	30 #6 (0, 0)
	31 dload (1, 1)
	32 #6 (1, 1)
	33 dconst_0 (1, 1)
	34 dcmpl (1, 1)
	35 ifne (1, 1)
	36 16 (1, 1)
	38 aload_0 (1, 1)
	39 getfield (1, 1)
	40 org/apache/commons/math3/linear/OpenMapRealMatrix.entries:Lorg/apache/commons/math3/util/OpenIntToDoubleHashMap; (1, 1)
	42 iload (1, 1)
	43 #5 (1, 1)
	44 invokevirtual (1, 1)
	45 org/apache/commons/math3/util/OpenIntToDoubleHashMap.remove:(I)D (1, 1)
	47 pop2 (1, 1)
	48 goto (1, 1)
	49 15 (1, 1)
	51 aload_0 (2, 2)
	52 getfield (2, 2)
	53 org/apache/commons/math3/linear/OpenMapRealMatrix.entries:Lorg/apache/commons/math3/util/OpenIntToDoubleHashMap; (2, 2)
	55 iload (2, 2)
	56 #5 (2, 2)
	57 dload (2, 2)
	58 #6 (2, 2)
	59 invokevirtual (2, 2)
	60 org/apache/commons/math3/util/OpenIntToDoubleHashMap.put:(ID)D (2, 2)
	62 pop2 (2, 2)
	63 return (0, 0)

Method: multiplyEntry
	0 aload_0 (0, 0)
	1 iload_1 (0, 0)
	2 invokestatic (0, 0)
	3 org/apache/commons/math3/linear/MatrixUtils.checkRowIndex:(Lorg/apache/commons/math3/linear/AnyMatrix;I)V (0, 0)
	5 aload_0 (0, 0)
	6 iload_2 (0, 0)
	7 invokestatic (0, 0)
	8 org/apache/commons/math3/linear/MatrixUtils.checkColumnIndex:(Lorg/apache/commons/math3/linear/AnyMatrix;I)V (0, 0)
	10 aload_0 (0, 0)
	11 iload_1 (0, 0)
	12 iload_2 (0, 0)
	13 invokespecial (0, 0)
	14 org/apache/commons/math3/linear/OpenMapRealMatrix.computeKey:(II)I (0, 0)
	16 istore (0, 0)
	17 #5 (0, 0)
	18 aload_0 (0, 0)
	19 getfield (0, 0)
	20 org/apache/commons/math3/linear/OpenMapRealMatrix.entries:Lorg/apache/commons/math3/util/OpenIntToDoubleHashMap; (0, 0)
	22 iload (0, 0)
	23 #5 (0, 0)
	24 invokevirtual (0, 0)
	25 org/apache/commons/math3/util/OpenIntToDoubleHashMap.get:(I)D (0, 0)
	27 dload_3 (0, 0)
	28 dmul (0, 0)
	29 dstore (0, 0)
	30 #6 (0, 0)
	31 dload (1, 1)
	32 #6 (1, 1)
	33 dconst_0 (1, 1)
	34 dcmpl (1, 1)
	35 ifne (1, 1)
	36 16 (1, 1)
	38 aload_0 (1, 1)
	39 getfield (1, 1)
	40 org/apache/commons/math3/linear/OpenMapRealMatrix.entries:Lorg/apache/commons/math3/util/OpenIntToDoubleHashMap; (1, 1)
	42 iload (1, 1)
	43 #5 (1, 1)
	44 invokevirtual (1, 1)
	45 org/apache/commons/math3/util/OpenIntToDoubleHashMap.remove:(I)D (1, 1)
	47 pop2 (1, 1)
	48 goto (1, 1)
	49 15 (1, 1)
	51 aload_0 (2, 2)
	52 getfield (2, 2)
	53 org/apache/commons/math3/linear/OpenMapRealMatrix.entries:Lorg/apache/commons/math3/util/OpenIntToDoubleHashMap; (2, 2)
	55 iload (2, 2)
	56 #5 (2, 2)
	57 dload (2, 2)
	58 #6 (2, 2)
	59 invokevirtual (2, 2)
	60 org/apache/commons/math3/util/OpenIntToDoubleHashMap.put:(ID)D (2, 2)
	62 pop2 (2, 2)
	63 return (0, 0)

Method: computeKey
	0 iload_1 (0, 0)
	1 aload_0 (0, 0)
	2 getfield (0, 0)
	3 org/apache/commons/math3/linear/OpenMapRealMatrix.columns:I (0, 0)
	5 imul (0, 0)
	6 iload_2 (0, 0)
	7 iadd (0, 0)
	8 ireturn (0, 0)

