Method: <init>
	0 aload_0 (0, 0)
	1 invokespecial (0, 0)
	2 org/apache/commons/math3/linear/SparseRealVector.<init>:()V (0, 0)
	4 aload_0 (0, 0)
	5 aload_1 (0, 0)
	6 invokevirtual (0, 0)
	7 org/apache/commons/math3/linear/RealVector.getDimension:()I (0, 0)
	9 putfield (0, 0)
	10 org/apache/commons/math3/linear/OpenMapRealVector.virtualSize:I (0, 0)
	12 aload_0 (0, 0)
	13 new (0, 0)
	14 org/apache/commons/math3/util/OpenIntToDoubleHashMap (0, 0)
	16 dup (0, 0)
	17 dconst_0 (0, 0)
	18 invokespecial (0, 0)
	19 org/apache/commons/math3/util/OpenIntToDoubleHashMap.<init>:(D)V (0, 0)
	21 putfield (0, 0)
	22 org/apache/commons/math3/linear/OpenMapRealVector.entries:Lorg/apache/commons/math3/util/OpenIntToDoubleHashMap; (0, 0)
	24 aload_0 (0, 0)
	25 ldc2_w (0, 0)
	26 1e-12 (0, 0)
	28 putfield (0, 0)
	29 org/apache/commons/math3/linear/OpenMapRealVector.epsilon:D (0, 0)
	31 iconst_0 (1, 4)
	32 istore_2 (1, 4)
	33 iload_2 (1, 4)
	34 aload_0 (1, 4)
	35 getfield (1, 4)
	36 org/apache/commons/math3/linear/OpenMapRealVector.virtualSize:I (1, 4)
	38 if_icmpge (1, 4)
	39 33 (1, 4)
	41 aload_1 (1, 4)
	42 iload_2 (1, 4)
	43 invokevirtual (1, 4)
	44 org/apache/commons/math3/linear/RealVector.getEntry:(I)D (1, 4)
	46 dstore_3 (1, 4)
	47 aload_0 (2, 1)
	48 dload_3 (2, 1)
	49 invokevirtual (2, 1)
	50 org/apache/commons/math3/linear/OpenMapRealVector.isDefaultValue:(D)Z (2, 1)
	52 ifne (2, 1)
	53 13 (2, 1)
	55 aload_0 (2, 1)
	56 getfield (2, 1)
	57 org/apache/commons/math3/linear/OpenMapRealVector.entries:Lorg/apache/commons/math3/util/OpenIntToDoubleHashMap; (2, 1)
	59 iload_2 (2, 1)
	60 dload_3 (2, 1)
	61 invokevirtual (2, 1)
	62 org/apache/commons/math3/util/OpenIntToDoubleHashMap.put:(ID)D (2, 1)
	64 pop2 (2, 1)
	65 iinc (2, 1)
	66 #2 (2, 1)
	67 -89 (2, 1)
	68 goto (2, 1)
	69 -35 (2, 1)
	71 return (0, 0)

Method: getEntries
	0 aload_0 (0, 0)
	1 getfield (0, 0)
	2 org/apache/commons/math3/linear/OpenMapRealVector.entries:Lorg/apache/commons/math3/util/OpenIntToDoubleHashMap; (0, 0)
	4 areturn (0, 0)

Method: isDefaultValue
	0 dload_1 (0, 0)
	1 invokestatic (0, 0)
	2 org/apache/commons/math3/util/FastMath.abs:(D)D (0, 0)
	4 aload_0 (0, 0)
	5 getfield (0, 0)
	6 org/apache/commons/math3/linear/OpenMapRealVector.epsilon:D (0, 0)
	8 dcmpg (0, 0)
	9 ifge (0, 0)
	10 7 (0, 0)
	12 iconst_1 (0, 0)
	13 goto (0, 0)
	14 4 (0, 0)
	16 iconst_0 (0, 0)
	17 ireturn (0, 0)

Method: add
	0 aload_0 (0, 0)
	1 aload_1 (0, 0)
	2 invokevirtual (0, 0)
	3 org/apache/commons/math3/linear/OpenMapRealVector.getDimension:()I (0, 0)
	5 invokevirtual (0, 0)
	6 org/apache/commons/math3/linear/OpenMapRealVector.checkVectorDimensions:(I)V (0, 0)
	8 aload_0 (0, 0)
	9 getfield (0, 0)
	10 org/apache/commons/math3/linear/OpenMapRealVector.entries:Lorg/apache/commons/math3/util/OpenIntToDoubleHashMap; (0, 0)
	12 invokevirtual (0, 0)
	13 org/apache/commons/math3/util/OpenIntToDoubleHashMap.size:()I (0, 0)
	15 aload_1 (0, 0)
	16 getfield (0, 0)
	17 org/apache/commons/math3/linear/OpenMapRealVector.entries:Lorg/apache/commons/math3/util/OpenIntToDoubleHashMap; (0, 0)
	19 invokevirtual (0, 0)
	20 org/apache/commons/math3/util/OpenIntToDoubleHashMap.size:()I (0, 0)
	22 if_icmple (0, 0)
	23 7 (0, 0)
	25 iconst_1 (0, 0)
	26 goto (0, 0)
	27 4 (0, 0)
	29 iconst_0 (0, 0)
	30 istore_2 (0, 0)
	31 iload_2 (0, 0)
	32 ifeq (0, 0)
	33 10 (0, 0)
	35 aload_0 (0, 0)
	36 invokevirtual (0, 0)
	37 org/apache/commons/math3/linear/OpenMapRealVector.copy:()Lorg/apache/commons/math3/linear/OpenMapRealVector; (0, 0)
	39 goto (0, 0)
	40 7 (0, 0)
	42 aload_1 (0, 0)
	43 invokevirtual (0, 0)
	44 org/apache/commons/math3/linear/OpenMapRealVector.copy:()Lorg/apache/commons/math3/linear/OpenMapRealVector; (0, 0)
	46 astore_3 (0, 0)
	47 iload_2 (0, 0)
	48 ifeq (0, 0)
	49 13 (0, 0)
	51 aload_1 (0, 0)
	52 getfield (0, 0)
	53 org/apache/commons/math3/linear/OpenMapRealVector.entries:Lorg/apache/commons/math3/util/OpenIntToDoubleHashMap; (0, 0)
	55 invokevirtual (0, 0)
	56 org/apache/commons/math3/util/OpenIntToDoubleHashMap.iterator:()Lorg/apache/commons/math3/util/OpenIntToDoubleHashMap$Iterator; (0, 0)
	58 goto (0, 0)
	59 10 (0, 0)
	61 aload_0 (0, 0)
	62 getfield (0, 0)
	63 org/apache/commons/math3/linear/OpenMapRealVector.entries:Lorg/apache/commons/math3/util/OpenIntToDoubleHashMap; (0, 0)
	65 invokevirtual (0, 0)
	66 org/apache/commons/math3/util/OpenIntToDoubleHashMap.iterator:()Lorg/apache/commons/math3/util/OpenIntToDoubleHashMap$Iterator; (0, 0)
	68 astore (0, 0)
	69 #4 (0, 0)
	70 iload_2 (0, 0)
	71 ifeq (0, 0)
	72 10 (0, 0)
	74 aload_0 (0, 0)
	75 getfield (0, 0)
	76 org/apache/commons/math3/linear/OpenMapRealVector.entries:Lorg/apache/commons/math3/util/OpenIntToDoubleHashMap; (0, 0)
	78 goto (0, 0)
	79 7 (0, 0)
	81 aload_1 (0, 0)
	82 getfield (0, 0)
	83 org/apache/commons/math3/linear/OpenMapRealVector.entries:Lorg/apache/commons/math3/util/OpenIntToDoubleHashMap; (0, 0)
	85 astore (0, 0)
	86 #5 (0, 0)
	87 aload (1, 3)
	88 #4 (1, 3)
	89 invokevirtual (1, 3)
	90 org/apache/commons/math3/util/OpenIntToDoubleHashMap$Iterator.hasNext:()Z (1, 3)
	92 ifeq (1, 3)
	93 61 (1, 3)
	95 aload (1, 3)
	96 #4 (1, 3)
	97 invokevirtual (1, 3)
	98 org/apache/commons/math3/util/OpenIntToDoubleHashMap$Iterator.advance:()V (1, 3)
	100 aload (1, 3)
	101 #4 (1, 3)
	102 invokevirtual (1, 3)
	103 org/apache/commons/math3/util/OpenIntToDoubleHashMap$Iterator.key:()I (1, 3)
	105 istore (1, 3)
	106 #6 (1, 3)
	107 aload (2, 1)
	108 #5 (2, 1)
	109 iload (2, 1)
	110 #6 (2, 1)
	111 invokevirtual (2, 1)
	112 org/apache/commons/math3/util/OpenIntToDoubleHashMap.containsKey:(I)Z (2, 1)
	114 ifeq (2, 1)
	115 25 (2, 1)
	117 aload_3 (2, 1)
	118 iload (2, 1)
	119 #6 (2, 1)
	120 aload (2, 1)
	121 #5 (2, 1)
	122 iload (2, 1)
	123 #6 (2, 1)
	124 invokevirtual (2, 1)
	125 org/apache/commons/math3/util/OpenIntToDoubleHashMap.get:(I)D (2, 1)
	127 aload (2, 1)
	128 #4 (2, 1)
	129 invokevirtual (2, 1)
	130 org/apache/commons/math3/util/OpenIntToDoubleHashMap$Iterator.value:()D (2, 1)
	132 dadd (2, 1)
	133 invokevirtual (2, 1)
	134 org/apache/commons/math3/linear/OpenMapRealVector.setEntry:(ID)V (2, 1)
	136 goto (2, 1)
	137 14 (2, 1)
	139 aload_3 (3, 2)
	140 iload (3, 2)
	141 #6 (3, 2)
	142 aload (3, 2)
	143 #4 (3, 2)
	144 invokevirtual (3, 2)
	145 org/apache/commons/math3/util/OpenIntToDoubleHashMap$Iterator.value:()D (3, 2)
	147 invokevirtual (3, 2)
	148 org/apache/commons/math3/linear/OpenMapRealVector.setEntry:(ID)V (3, 2)
	150 goto (0, 0)
	151 -63 (0, 0)
	153 aload_3 (0, 0)
	154 areturn (0, 0)

Method: append
	0 aload_0 (0, 0)
	1 aload_1 (0, 0)
	2 invokevirtual (0, 0)
	3 org/apache/commons/math3/linear/OpenMapRealVector.append:(Lorg/apache/commons/math3/linear/RealVector;)Lorg/apache/commons/math3/linear/OpenMapRealVector; (0, 0)
	5 areturn (0, 0)

Method: copy
	0 aload_0 (0, 0)
	1 invokevirtual (0, 0)
	2 org/apache/commons/math3/linear/OpenMapRealVector.copy:()Lorg/apache/commons/math3/linear/OpenMapRealVector; (0, 0)
	4 areturn (0, 0)

Method: dotProduct
	0 aload_0 (0, 0)
	1 aload_1 (0, 0)
	2 invokevirtual (0, 0)
	3 org/apache/commons/math3/linear/OpenMapRealVector.dotProduct:(Lorg/apache/commons/math3/linear/RealVector;)D (0, 0)
	5 dreturn (0, 0)

Method: ebeDivide
	0 aload_0 (0, 0)
	1 aload_1 (0, 0)
	2 invokevirtual (0, 0)
	3 org/apache/commons/math3/linear/OpenMapRealVector.ebeDivide:(Lorg/apache/commons/math3/linear/RealVector;)Lorg/apache/commons/math3/linear/OpenMapRealVector; (0, 0)
	5 areturn (0, 0)

Method: ebeMultiply
	0 aload_0 (0, 0)
	1 aload_1 (0, 0)
	2 invokevirtual (0, 0)
	3 org/apache/commons/math3/linear/OpenMapRealVector.ebeMultiply:(Lorg/apache/commons/math3/linear/RealVector;)Lorg/apache/commons/math3/linear/OpenMapRealVector; (0, 0)
	5 areturn (0, 0)

Method: getSubVector
	0 aload_0 (0, 0)
	1 iload_1 (0, 0)
	2 iload_2 (0, 0)
	3 invokevirtual (0, 0)
	4 org/apache/commons/math3/linear/OpenMapRealVector.getSubVector:(II)Lorg/apache/commons/math3/linear/OpenMapRealVector; (0, 0)
	6 areturn (0, 0)

Method: getDimension
	0 aload_0 (0, 0)
	1 getfield (0, 0)
	2 org/apache/commons/math3/linear/OpenMapRealVector.virtualSize:I (0, 0)
	4 ireturn (0, 0)

Method: getDistance
	0 aload_0 (0, 0)
	1 aload_1 (0, 0)
	2 invokevirtual (0, 0)
	3 org/apache/commons/math3/linear/RealVector.getDimension:()I (0, 0)
	5 invokevirtual (0, 0)
	6 org/apache/commons/math3/linear/OpenMapRealVector.checkVectorDimensions:(I)V (0, 0)
	8 aload_1 (1, 1)
	9 instanceof (1, 1)
	10 org/apache/commons/math3/linear/OpenMapRealVector (1, 1)
	12 ifeq (1, 1)
	13 12 (1, 1)
	15 aload_0 (1, 1)
	16 aload_1 (1, 1)
	17 checkcast (1, 1)
	18 org/apache/commons/math3/linear/OpenMapRealVector (1, 1)
	20 invokevirtual (1, 1)
	21 org/apache/commons/math3/linear/OpenMapRealVector.getDistance:(Lorg/apache/commons/math3/linear/OpenMapRealVector;)D (1, 1)
	23 dreturn (1, 1)
	24 aload_0 (2, 2)
	25 aload_1 (2, 2)
	26 invokespecial (2, 2)
	27 org/apache/commons/math3/linear/SparseRealVector.getDistance:(Lorg/apache/commons/math3/linear/RealVector;)D (2, 2)
	29 dreturn (1, 2)

Method: getEntry
	0 aload_0 (0, 0)
	1 iload_1 (0, 0)
	2 invokevirtual (0, 0)
	3 org/apache/commons/math3/linear/OpenMapRealVector.checkIndex:(I)V (0, 0)
	5 aload_0 (0, 0)
	6 getfield (0, 0)
	7 org/apache/commons/math3/linear/OpenMapRealVector.entries:Lorg/apache/commons/math3/util/OpenIntToDoubleHashMap; (0, 0)
	9 iload_1 (0, 0)
	10 invokevirtual (0, 0)
	11 org/apache/commons/math3/util/OpenIntToDoubleHashMap.get:(I)D (0, 0)
	13 dreturn (0, 0)

Method: getL1Distance
	0 aload_0 (0, 0)
	1 aload_1 (0, 0)
	2 invokevirtual (0, 0)
	3 org/apache/commons/math3/linear/RealVector.getDimension:()I (0, 0)
	5 invokevirtual (0, 0)
	6 org/apache/commons/math3/linear/OpenMapRealVector.checkVectorDimensions:(I)V (0, 0)
	8 aload_1 (1, 1)
	9 instanceof (1, 1)
	10 org/apache/commons/math3/linear/OpenMapRealVector (1, 1)
	12 ifeq (1, 1)
	13 12 (1, 1)
	15 aload_0 (1, 1)
	16 aload_1 (1, 1)
	17 checkcast (1, 1)
	18 org/apache/commons/math3/linear/OpenMapRealVector (1, 1)
	20 invokevirtual (1, 1)
	21 org/apache/commons/math3/linear/OpenMapRealVector.getL1Distance:(Lorg/apache/commons/math3/linear/OpenMapRealVector;)D (1, 1)
	23 dreturn (1, 1)
	24 aload_0 (2, 2)
	25 aload_1 (2, 2)
	26 invokespecial (2, 2)
	27 org/apache/commons/math3/linear/SparseRealVector.getL1Distance:(Lorg/apache/commons/math3/linear/RealVector;)D (2, 2)
	29 dreturn (1, 2)

Method: getLInfDistance
	0 aload_0 (0, 0)
	1 aload_1 (0, 0)
	2 invokevirtual (0, 0)
	3 org/apache/commons/math3/linear/RealVector.getDimension:()I (0, 0)
	5 invokevirtual (0, 0)
	6 org/apache/commons/math3/linear/OpenMapRealVector.checkVectorDimensions:(I)V (0, 0)
	8 aload_1 (1, 1)
	9 instanceof (1, 1)
	10 org/apache/commons/math3/linear/OpenMapRealVector (1, 1)
	12 ifeq (1, 1)
	13 12 (1, 1)
	15 aload_0 (1, 1)
	16 aload_1 (1, 1)
	17 checkcast (1, 1)
	18 org/apache/commons/math3/linear/OpenMapRealVector (1, 1)
	20 invokespecial (1, 1)
	21 org/apache/commons/math3/linear/OpenMapRealVector.getLInfDistance:(Lorg/apache/commons/math3/linear/OpenMapRealVector;)D (1, 1)
	23 dreturn (1, 1)
	24 aload_0 (2, 2)
	25 aload_1 (2, 2)
	26 invokespecial (2, 2)
	27 org/apache/commons/math3/linear/SparseRealVector.getLInfDistance:(Lorg/apache/commons/math3/linear/RealVector;)D (2, 2)
	29 dreturn (1, 2)

Method: isInfinite
	0 iconst_0 (0, 0)
	1 istore_1 (0, 0)
	2 aload_0 (0, 0)
	3 getfield (0, 0)
	4 org/apache/commons/math3/linear/OpenMapRealVector.entries:Lorg/apache/commons/math3/util/OpenIntToDoubleHashMap; (0, 0)
	6 invokevirtual (0, 0)
	7 org/apache/commons/math3/util/OpenIntToDoubleHashMap.iterator:()Lorg/apache/commons/math3/util/OpenIntToDoubleHashMap$Iterator; (0, 0)
	9 astore_2 (0, 0)
	10 aload_2 (1, 3)
	11 invokevirtual (1, 3)
	12 org/apache/commons/math3/util/OpenIntToDoubleHashMap$Iterator.hasNext:()Z (1, 3)
	14 ifeq (1, 3)
	15 33 (1, 3)
	17 aload_2 (1, 3)
	18 invokevirtual (1, 3)
	19 org/apache/commons/math3/util/OpenIntToDoubleHashMap$Iterator.advance:()V (1, 3)
	21 aload_2 (1, 3)
	22 invokevirtual (1, 3)
	23 org/apache/commons/math3/util/OpenIntToDoubleHashMap$Iterator.value:()D (1, 3)
	25 dstore_3 (1, 3)
	26 dload_3 (2, 1)
	27 invokestatic (2, 1)
	28 java/lang/Double.isNaN:(D)Z (2, 1)
	30 ifeq (2, 1)
	31 5 (2, 1)
	33 iconst_0 (2, 1)
	34 ireturn (2, 1)
	35 dload_3 (2, 1)
	36 invokestatic (2, 1)
	37 java/lang/Double.isInfinite:(D)Z (2, 1)
	39 ifeq (2, 1)
	40 5 (2, 1)
	42 iconst_1 (2, 1)
	43 istore_1 (2, 1)
	44 goto (0, 0)
	45 -34 (0, 0)
	47 iload_1 (0, 0)
	48 ireturn (0, 0)

Method: isNaN
	0 aload_0 (0, 0)
	1 getfield (0, 0)
	2 org/apache/commons/math3/linear/OpenMapRealVector.entries:Lorg/apache/commons/math3/util/OpenIntToDoubleHashMap; (0, 0)
	4 invokevirtual (0, 0)
	5 org/apache/commons/math3/util/OpenIntToDoubleHashMap.iterator:()Lorg/apache/commons/math3/util/OpenIntToDoubleHashMap$Iterator; (0, 0)
	7 astore_1 (0, 0)
	8 aload_1 (1, 3)
	9 invokevirtual (1, 3)
	10 org/apache/commons/math3/util/OpenIntToDoubleHashMap$Iterator.hasNext:()Z (1, 3)
	12 ifeq (1, 3)
	13 19 (1, 3)
	15 aload_1 (1, 3)
	16 invokevirtual (1, 3)
	17 org/apache/commons/math3/util/OpenIntToDoubleHashMap$Iterator.advance:()V (1, 3)
	19 aload_1 (2, 1)
	20 invokevirtual (2, 1)
	21 org/apache/commons/math3/util/OpenIntToDoubleHashMap$Iterator.value:()D (2, 1)
	23 invokestatic (2, 1)
	24 java/lang/Double.isNaN:(D)Z (2, 1)
	26 ifeq (2, 1)
	27 -18 (2, 1)
	29 iconst_1 (2, 1)
	30 ireturn (2, 1)
	31 iconst_0 (0, 0)
	32 ireturn (0, 0)

Method: mapAdd
	0 aload_0 (0, 0)
	1 dload_1 (0, 0)
	2 invokevirtual (0, 0)
	3 org/apache/commons/math3/linear/OpenMapRealVector.mapAdd:(D)Lorg/apache/commons/math3/linear/OpenMapRealVector; (0, 0)
	5 areturn (0, 0)

Method: mapAddToSelf
	0 aload_0 (0, 0)
	1 dload_1 (0, 0)
	2 invokevirtual (0, 0)
	3 org/apache/commons/math3/linear/OpenMapRealVector.mapAddToSelf:(D)Lorg/apache/commons/math3/linear/OpenMapRealVector; (0, 0)
	5 areturn (0, 0)

Method: setEntry
	0 aload_0 (0, 0)
	1 iload_1 (0, 0)
	2 invokevirtual (0, 0)
	3 org/apache/commons/math3/linear/OpenMapRealVector.checkIndex:(I)V (0, 0)
	5 aload_0 (1, 1)
	6 dload_2 (1, 1)
	7 invokevirtual (1, 1)
	8 org/apache/commons/math3/linear/OpenMapRealVector.isDefaultValue:(D)Z (1, 1)
	10 ifne (1, 1)
	11 16 (1, 1)
	13 aload_0 (1, 1)
	14 getfield (1, 1)
	15 org/apache/commons/math3/linear/OpenMapRealVector.entries:Lorg/apache/commons/math3/util/OpenIntToDoubleHashMap; (1, 1)
	17 iload_1 (1, 1)
	18 dload_2 (1, 1)
	19 invokevirtual (1, 1)
	20 org/apache/commons/math3/util/OpenIntToDoubleHashMap.put:(ID)D (1, 1)
	22 pop2 (1, 1)
	23 goto (1, 1)
	24 23 (1, 1)
	26 aload_0 (2, 1)
	27 getfield (2, 1)
	28 org/apache/commons/math3/linear/OpenMapRealVector.entries:Lorg/apache/commons/math3/util/OpenIntToDoubleHashMap; (2, 1)
	30 iload_1 (2, 1)
	31 invokevirtual (2, 1)
	32 org/apache/commons/math3/util/OpenIntToDoubleHashMap.containsKey:(I)Z (2, 1)
	34 ifeq (2, 1)
	35 12 (2, 1)
	37 aload_0 (2, 1)
	38 getfield (2, 1)
	39 org/apache/commons/math3/linear/OpenMapRealVector.entries:Lorg/apache/commons/math3/util/OpenIntToDoubleHashMap; (2, 1)
	41 iload_1 (2, 1)
	42 invokevirtual (2, 1)
	43 org/apache/commons/math3/util/OpenIntToDoubleHashMap.remove:(I)D (2, 1)
	45 pop2 (2, 1)
	46 return (0, 0)

Method: setSubVector
	0 aload_0 (0, 0)
	1 iload_1 (0, 0)
	2 invokevirtual (0, 0)
	3 org/apache/commons/math3/linear/OpenMapRealVector.checkIndex:(I)V (0, 0)
	5 aload_0 (0, 0)
	6 iload_1 (0, 0)
	7 aload_2 (0, 0)
	8 invokevirtual (0, 0)
	9 org/apache/commons/math3/linear/RealVector.getDimension:()I (0, 0)
	11 iadd (0, 0)
	12 iconst_1 (0, 0)
	13 isub (0, 0)
	14 invokevirtual (0, 0)
	15 org/apache/commons/math3/linear/OpenMapRealVector.checkIndex:(I)V (0, 0)
	17 iconst_0 (1, 4)
	18 istore_3 (1, 4)
	19 iload_3 (1, 4)
	20 aload_2 (1, 4)
	21 invokevirtual (1, 4)
	22 org/apache/commons/math3/linear/RealVector.getDimension:()I (1, 4)
	24 if_icmpge (1, 4)
	25 21 (1, 4)
	27 aload_0 (1, 4)
	28 iload_3 (1, 4)
	29 iload_1 (1, 4)
	30 iadd (1, 4)
	31 aload_2 (1, 4)
	32 iload_3 (1, 4)
	33 invokevirtual (1, 4)
	34 org/apache/commons/math3/linear/RealVector.getEntry:(I)D (1, 4)
	36 invokevirtual (1, 4)
	37 org/apache/commons/math3/linear/OpenMapRealVector.setEntry:(ID)V (1, 4)
	39 iinc (1, 4)
	40 #3 (1, 4)
	41 -89 (1, 4)
	42 goto (1, 4)
	43 -23 (1, 4)
	45 return (0, 0)

Method: set
	0 iconst_0 (1, 4)
	1 istore_3 (1, 4)
	2 iload_3 (1, 4)
	3 aload_0 (1, 4)
	4 getfield (1, 4)
	5 org/apache/commons/math3/linear/OpenMapRealVector.virtualSize:I (1, 4)
	7 if_icmpge (1, 4)
	8 15 (1, 4)
	10 aload_0 (1, 4)
	11 iload_3 (1, 4)
	12 dload_1 (1, 4)
	13 invokevirtual (1, 4)
	14 org/apache/commons/math3/linear/OpenMapRealVector.setEntry:(ID)V (1, 4)
	16 iinc (1, 4)
	17 #3 (1, 4)
	18 -89 (1, 4)
	19 goto (1, 4)
	20 -17 (1, 4)
	22 return (0, 0)

Method: subtract
	0 aload_0 (0, 0)
	1 aload_1 (0, 0)
	2 invokevirtual (0, 0)
	3 org/apache/commons/math3/linear/RealVector.getDimension:()I (0, 0)
	5 invokevirtual (0, 0)
	6 org/apache/commons/math3/linear/OpenMapRealVector.checkVectorDimensions:(I)V (0, 0)
	8 aload_1 (1, 1)
	9 instanceof (1, 1)
	10 org/apache/commons/math3/linear/OpenMapRealVector (1, 1)
	12 ifeq (1, 1)
	13 12 (1, 1)
	15 aload_0 (1, 1)
	16 aload_1 (1, 1)
	17 checkcast (1, 1)
	18 org/apache/commons/math3/linear/OpenMapRealVector (1, 1)
	20 invokevirtual (1, 1)
	21 org/apache/commons/math3/linear/OpenMapRealVector.subtract:(Lorg/apache/commons/math3/linear/OpenMapRealVector;)Lorg/apache/commons/math3/linear/OpenMapRealVector; (1, 1)
	23 areturn (1, 1)
	24 aload_0 (2, 2)
	25 aload_1 (2, 2)
	26 invokespecial (2, 2)
	27 org/apache/commons/math3/linear/SparseRealVector.subtract:(Lorg/apache/commons/math3/linear/RealVector;)Lorg/apache/commons/math3/linear/RealVector; (2, 2)
	29 areturn (1, 2)

Method: unitVector
	0 aload_0 (0, 0)
	1 invokevirtual (0, 0)
	2 org/apache/commons/math3/linear/OpenMapRealVector.unitVector:()Lorg/apache/commons/math3/linear/OpenMapRealVector; (0, 0)
	4 areturn (0, 0)

Method: unitize
	0 aload_0 (0, 0)
	1 invokevirtual (0, 0)
	2 org/apache/commons/math3/linear/OpenMapRealVector.getNorm:()D (0, 0)
	4 dstore_1 (0, 0)
	5 aload_0 (1, 1)
	6 dload_1 (1, 1)
	7 invokevirtual (1, 1)
	8 org/apache/commons/math3/linear/OpenMapRealVector.isDefaultValue:(D)Z (1, 1)
	10 ifeq (1, 1)
	11 18 (1, 1)
	13 new (1, 1)
	14 org/apache/commons/math3/exception/MathArithmeticException (1, 1)
	16 dup (1, 1)
	17 getstatic (1, 1)
	18 org/apache/commons/math3/exception/util/LocalizedFormats.ZERO_NORM:Lorg/apache/commons/math3/exception/util/LocalizedFormats; (1, 1)
	20 iconst_0 (1, 1)
	21 anewarray (1, 1)
	22 java/lang/Object (1, 1)
	24 invokespecial (1, 1)
	25 org/apache/commons/math3/exception/MathArithmeticException.<init>:(Lorg/apache/commons/math3/exception/util/Localizable;[Ljava/lang/Object;)V (1, 1)
	27 athrow (1, 1)
	28 aload_0 (0, 0)
	29 getfield (0, 0)
	30 org/apache/commons/math3/linear/OpenMapRealVector.entries:Lorg/apache/commons/math3/util/OpenIntToDoubleHashMap; (0, 0)
	32 invokevirtual (0, 0)
	33 org/apache/commons/math3/util/OpenIntToDoubleHashMap.iterator:()Lorg/apache/commons/math3/util/OpenIntToDoubleHashMap$Iterator; (0, 0)
	35 astore_3 (0, 0)
	36 aload_3 (1, 3)
	37 invokevirtual (1, 3)
	38 org/apache/commons/math3/util/OpenIntToDoubleHashMap$Iterator.hasNext:()Z (1, 3)
	40 ifeq (1, 3)
	41 28 (1, 3)
	43 aload_3 (1, 3)
	44 invokevirtual (1, 3)
	45 org/apache/commons/math3/util/OpenIntToDoubleHashMap$Iterator.advance:()V (1, 3)
	47 aload_0 (1, 3)
	48 getfield (1, 3)
	49 org/apache/commons/math3/linear/OpenMapRealVector.entries:Lorg/apache/commons/math3/util/OpenIntToDoubleHashMap; (1, 3)
	51 aload_3 (1, 3)
	52 invokevirtual (1, 3)
	53 org/apache/commons/math3/util/OpenIntToDoubleHashMap$Iterator.key:()I (1, 3)
	55 aload_3 (1, 3)
	56 invokevirtual (1, 3)
	57 org/apache/commons/math3/util/OpenIntToDoubleHashMap$Iterator.value:()D (1, 3)
	59 dload_1 (1, 3)
	60 ddiv (1, 3)
	61 invokevirtual (1, 3)
	62 org/apache/commons/math3/util/OpenIntToDoubleHashMap.put:(ID)D (1, 3)
	64 pop2 (1, 3)
	65 goto (1, 3)
	66 -29 (1, 3)
	68 return (0, 0)

Method: toArray
	0 aload_0 (0, 0)
	1 getfield (0, 0)
	2 org/apache/commons/math3/linear/OpenMapRealVector.virtualSize:I (0, 0)
	4 newarray (0, 0)
	5 7 (0, 0)
	6 astore_1 (0, 0)
	7 aload_0 (0, 0)
	8 getfield (0, 0)
	9 org/apache/commons/math3/linear/OpenMapRealVector.entries:Lorg/apache/commons/math3/util/OpenIntToDoubleHashMap; (0, 0)
	11 invokevirtual (0, 0)
	12 org/apache/commons/math3/util/OpenIntToDoubleHashMap.iterator:()Lorg/apache/commons/math3/util/OpenIntToDoubleHashMap$Iterator; (0, 0)
	14 astore_2 (0, 0)
	15 aload_2 (1, 3)
	16 invokevirtual (1, 3)
	17 org/apache/commons/math3/util/OpenIntToDoubleHashMap$Iterator.hasNext:()Z (1, 3)
	19 ifeq (1, 3)
	20 20 (1, 3)
	22 aload_2 (1, 3)
	23 invokevirtual (1, 3)
	24 org/apache/commons/math3/util/OpenIntToDoubleHashMap$Iterator.advance:()V (1, 3)
	26 aload_1 (1, 3)
	27 aload_2 (1, 3)
	28 invokevirtual (1, 3)
	29 org/apache/commons/math3/util/OpenIntToDoubleHashMap$Iterator.key:()I (1, 3)
	31 aload_2 (1, 3)
	32 invokevirtual (1, 3)
	33 org/apache/commons/math3/util/OpenIntToDoubleHashMap$Iterator.value:()D (1, 3)
	35 dastore (1, 3)
	36 goto (1, 3)
	37 -21 (1, 3)
	39 aload_1 (0, 0)
	40 areturn (0, 0)

Method: hashCode
	0 bipush (0, 0)
	1 31 (0, 0)
	2 istore_1 (0, 0)
	3 iconst_1 (0, 0)
	4 istore_2 (0, 0)
	5 aload_0 (0, 0)
	6 getfield (0, 0)
	7 org/apache/commons/math3/linear/OpenMapRealVector.epsilon:D (0, 0)
	9 invokestatic (0, 0)
	10 java/lang/Double.doubleToLongBits:(D)J (0, 0)
	12 lstore_3 (0, 0)
	13 bipush (0, 0)
	14 31 (0, 0)
	15 iload_2 (0, 0)
	16 imul (0, 0)
	17 lload_3 (0, 0)
	18 lload_3 (0, 0)
	19 bipush (0, 0)
	20 32 (0, 0)
	21 lushr (0, 0)
	22 lxor (0, 0)
	23 l2i (0, 0)
	24 iadd (0, 0)
	25 istore_2 (0, 0)
	26 bipush (0, 0)
	27 31 (0, 0)
	28 iload_2 (0, 0)
	29 imul (0, 0)
	30 aload_0 (0, 0)
	31 getfield (0, 0)
	32 org/apache/commons/math3/linear/OpenMapRealVector.virtualSize:I (0, 0)
	34 iadd (0, 0)
	35 istore_2 (0, 0)
	36 aload_0 (0, 0)
	37 getfield (0, 0)
	38 org/apache/commons/math3/linear/OpenMapRealVector.entries:Lorg/apache/commons/math3/util/OpenIntToDoubleHashMap; (0, 0)
	40 invokevirtual (0, 0)
	41 org/apache/commons/math3/util/OpenIntToDoubleHashMap.iterator:()Lorg/apache/commons/math3/util/OpenIntToDoubleHashMap$Iterator; (0, 0)
	43 astore (0, 0)
	44 #5 (0, 0)
	45 aload (1, 3)
	46 #5 (1, 3)
	47 invokevirtual (1, 3)
	48 org/apache/commons/math3/util/OpenIntToDoubleHashMap$Iterator.hasNext:()Z (1, 3)
	50 ifeq (1, 3)
	51 33 (1, 3)
	53 aload (1, 3)
	54 #5 (1, 3)
	55 invokevirtual (1, 3)
	56 org/apache/commons/math3/util/OpenIntToDoubleHashMap$Iterator.advance:()V (1, 3)
	58 aload (1, 3)
	59 #5 (1, 3)
	60 invokevirtual (1, 3)
	61 org/apache/commons/math3/util/OpenIntToDoubleHashMap$Iterator.value:()D (1, 3)
	63 invokestatic (1, 3)
	64 java/lang/Double.doubleToLongBits:(D)J (1, 3)
	66 lstore_3 (1, 3)
	67 bipush (1, 3)
	68 31 (1, 3)
	69 iload_2 (1, 3)
	70 imul (1, 3)
	71 lload_3 (1, 3)
	72 lload_3 (1, 3)
	73 bipush (1, 3)
	74 32 (1, 3)
	75 lshr (1, 3)
	76 lxor (1, 3)
	77 l2i (1, 3)
	78 iadd (1, 3)
	79 istore_2 (1, 3)
	80 goto (1, 3)
	81 -35 (1, 3)
	83 iload_2 (0, 0)
	84 ireturn (0, 0)

Method: equals
	0 aload_0 (1, 1)
	1 aload_1 (1, 1)
	2 if_acmpne (1, 1)
	3 5 (1, 1)
	5 iconst_1 (1, 1)
	6 ireturn (1, 1)
	7 aload_1 (1, 1)
	8 instanceof (1, 1)
	9 org/apache/commons/math3/linear/OpenMapRealVector (1, 1)
	11 ifne (1, 1)
	12 5 (1, 1)
	14 iconst_0 (1, 1)
	15 ireturn (1, 1)
	16 aload_1 (0, 0)
	17 checkcast (0, 0)
	18 org/apache/commons/math3/linear/OpenMapRealVector (0, 0)
	20 astore_2 (0, 0)
	21 aload_0 (1, 1)
	22 getfield (1, 1)
	23 org/apache/commons/math3/linear/OpenMapRealVector.virtualSize:I (1, 1)
	25 aload_2 (1, 1)
	26 getfield (1, 1)
	27 org/apache/commons/math3/linear/OpenMapRealVector.virtualSize:I (1, 1)
	29 if_icmpeq (1, 1)
	30 5 (1, 1)
	32 iconst_0 (1, 1)
	33 ireturn (1, 1)
	34 aload_0 (1, 1)
	35 getfield (1, 1)
	36 org/apache/commons/math3/linear/OpenMapRealVector.epsilon:D (1, 1)
	38 invokestatic (1, 1)
	39 java/lang/Double.doubleToLongBits:(D)J (1, 1)
	41 aload_2 (1, 1)
	42 getfield (1, 1)
	43 org/apache/commons/math3/linear/OpenMapRealVector.epsilon:D (1, 1)
	45 invokestatic (1, 1)
	46 java/lang/Double.doubleToLongBits:(D)J (1, 1)
	48 lcmp (1, 1)
	49 ifeq (1, 1)
	50 5 (1, 1)
	52 iconst_0 (1, 1)
	53 ireturn (1, 1)
	54 aload_0 (1, 1)
	55 getfield (1, 1)
	56 org/apache/commons/math3/linear/OpenMapRealVector.entries:Lorg/apache/commons/math3/util/OpenIntToDoubleHashMap; (1, 1)
	58 invokevirtual (1, 1)
	59 org/apache/commons/math3/util/OpenIntToDoubleHashMap.iterator:()Lorg/apache/commons/math3/util/OpenIntToDoubleHashMap$Iterator; (1, 1)
	61 astore_3 (1, 1)
	62 aload_3 (2, 3)
	63 invokevirtual (2, 3)
	64 org/apache/commons/math3/util/OpenIntToDoubleHashMap$Iterator.hasNext:()Z (2, 3)
	66 ifeq (2, 3)
	67 38 (2, 3)
	69 aload_3 (2, 3)
	70 invokevirtual (2, 3)
	71 org/apache/commons/math3/util/OpenIntToDoubleHashMap$Iterator.advance:()V (2, 3)
	73 aload_2 (2, 3)
	74 aload_3 (2, 3)
	75 invokevirtual (2, 3)
	76 org/apache/commons/math3/util/OpenIntToDoubleHashMap$Iterator.key:()I (2, 3)
	78 invokevirtual (2, 3)
	79 org/apache/commons/math3/linear/OpenMapRealVector.getEntry:(I)D (2, 3)
	81 dstore (2, 3)
	82 #4 (2, 3)
	83 dload (3, 1)
	84 #4 (3, 1)
	85 invokestatic (3, 1)
	86 java/lang/Double.doubleToLongBits:(D)J (3, 1)
	88 aload_3 (3, 1)
	89 invokevirtual (3, 1)
	90 org/apache/commons/math3/util/OpenIntToDoubleHashMap$Iterator.value:()D (3, 1)
	92 invokestatic (3, 1)
	93 java/lang/Double.doubleToLongBits:(D)J (3, 1)
	95 lcmp (3, 1)
	96 ifeq (3, 1)
	97 5 (3, 1)
	99 iconst_0 (3, 1)
	100 ireturn (3, 1)
	101 goto (1, 1)
	102 -39 (1, 1)
	104 aload_2 (1, 1)
	105 invokespecial (1, 1)
	106 org/apache/commons/math3/linear/OpenMapRealVector.getEntries:()Lorg/apache/commons/math3/util/OpenIntToDoubleHashMap; (1, 1)
	108 invokevirtual (1, 1)
	109 org/apache/commons/math3/util/OpenIntToDoubleHashMap.iterator:()Lorg/apache/commons/math3/util/OpenIntToDoubleHashMap$Iterator; (1, 1)
	111 astore_3 (1, 1)
	112 aload_3 (2, 3)
	113 invokevirtual (2, 3)
	114 org/apache/commons/math3/util/OpenIntToDoubleHashMap$Iterator.hasNext:()Z (2, 3)
	116 ifeq (2, 3)
	117 38 (2, 3)
	119 aload_3 (2, 3)
	120 invokevirtual (2, 3)
	121 org/apache/commons/math3/util/OpenIntToDoubleHashMap$Iterator.advance:()V (2, 3)
	123 aload_3 (2, 3)
	124 invokevirtual (2, 3)
	125 org/apache/commons/math3/util/OpenIntToDoubleHashMap$Iterator.value:()D (2, 3)
	127 dstore (2, 3)
	128 #4 (2, 3)
	129 dload (3, 1)
	130 #4 (3, 1)
	131 invokestatic (3, 1)
	132 java/lang/Double.doubleToLongBits:(D)J (3, 1)
	134 aload_0 (3, 1)
	135 aload_3 (3, 1)
	136 invokevirtual (3, 1)
	137 org/apache/commons/math3/util/OpenIntToDoubleHashMap$Iterator.key:()I (3, 1)
	139 invokevirtual (3, 1)
	140 org/apache/commons/math3/linear/OpenMapRealVector.getEntry:(I)D (3, 1)
	142 invokestatic (3, 1)
	143 java/lang/Double.doubleToLongBits:(D)J (3, 1)
	145 lcmp (3, 1)
	146 ifeq (3, 1)
	147 5 (3, 1)
	149 iconst_0 (3, 1)
	150 ireturn (3, 1)
	151 goto (1, 1)
	152 -39 (1, 1)
	154 iconst_1 (1, 1)
	155 ireturn (0, 1)

Method: getSparsity
	0 aload_0 (0, 0)
	1 getfield (0, 0)
	2 org/apache/commons/math3/linear/OpenMapRealVector.entries:Lorg/apache/commons/math3/util/OpenIntToDoubleHashMap; (0, 0)
	4 invokevirtual (0, 0)
	5 org/apache/commons/math3/util/OpenIntToDoubleHashMap.size:()I (0, 0)
	7 i2d (0, 0)
	8 aload_0 (0, 0)
	9 invokevirtual (0, 0)
	10 org/apache/commons/math3/linear/OpenMapRealVector.getDimension:()I (0, 0)
	12 i2d (0, 0)
	13 ddiv (0, 0)
	14 dreturn (0, 0)

Method: sparseIterator
	0 new (0, 0)
	1 org/apache/commons/math3/linear/OpenMapRealVector$OpenMapSparseIterator (0, 0)
	3 dup (0, 0)
	4 aload_0 (0, 0)
	5 invokespecial (0, 0)
	6 org/apache/commons/math3/linear/OpenMapRealVector$OpenMapSparseIterator.<init>:(Lorg/apache/commons/math3/linear/OpenMapRealVector;)V (0, 0)
	8 areturn (0, 0)

Method: access$000
	0 aload_0 (0, 0)
	1 getfield (0, 0)
	2 org/apache/commons/math3/linear/OpenMapRealVector.entries:Lorg/apache/commons/math3/util/OpenIntToDoubleHashMap; (0, 0)
	4 areturn (0, 0)

