Method: <init>
	0 aload_0 (0, 0)
	1 aload_1 (0, 0)
	2 putfield (0, 0)
	3 org/apache/commons/math3/linear/OpenMapRealVector$OpenMapEntry.this$0:Lorg/apache/commons/math3/linear/OpenMapRealVector; (0, 0)
	5 aload_0 (0, 0)
	6 aload_1 (0, 0)
	7 invokespecial (0, 0)
	8 org/apache/commons/math3/linear/RealVector$Entry.<init>:(Lorg/apache/commons/math3/linear/RealVector;)V (0, 0)
	10 aload_0 (0, 0)
	11 aload_2 (0, 0)
	12 putfield (0, 0)
	13 org/apache/commons/math3/linear/OpenMapRealVector$OpenMapEntry.iter:Lorg/apache/commons/math3/util/OpenIntToDoubleHashMap$Iterator; (0, 0)
	15 return (0, 0)

Method: getValue
	0 aload_0 (0, 0)
	1 getfield (0, 0)
	2 org/apache/commons/math3/linear/OpenMapRealVector$OpenMapEntry.iter:Lorg/apache/commons/math3/util/OpenIntToDoubleHashMap$Iterator; (0, 0)
	4 invokevirtual (0, 0)
	5 org/apache/commons/math3/util/OpenIntToDoubleHashMap$Iterator.value:()D (0, 0)
	7 dreturn (0, 0)

Method: setValue
	0 aload_0 (0, 0)
	1 getfield (0, 0)
	2 org/apache/commons/math3/linear/OpenMapRealVector$OpenMapEntry.this$0:Lorg/apache/commons/math3/linear/OpenMapRealVector; (0, 0)
	4 invokestatic (0, 0)
	5 org/apache/commons/math3/linear/OpenMapRealVector.access$000:(Lorg/apache/commons/math3/linear/OpenMapRealVector;)Lorg/apache/commons/math3/util/OpenIntToDoubleHashMap; (0, 0)
	7 aload_0 (0, 0)
	8 getfield (0, 0)
	9 org/apache/commons/math3/linear/OpenMapRealVector$OpenMapEntry.iter:Lorg/apache/commons/math3/util/OpenIntToDoubleHashMap$Iterator; (0, 0)
	11 invokevirtual (0, 0)
	12 org/apache/commons/math3/util/OpenIntToDoubleHashMap$Iterator.key:()I (0, 0)
	14 dload_1 (0, 0)
	15 invokevirtual (0, 0)
	16 org/apache/commons/math3/util/OpenIntToDoubleHashMap.put:(ID)D (0, 0)
	18 pop2 (0, 0)
	19 return (0, 0)

Method: getIndex
	0 aload_0 (0, 0)
	1 getfield (0, 0)
	2 org/apache/commons/math3/linear/OpenMapRealVector$OpenMapEntry.iter:Lorg/apache/commons/math3/util/OpenIntToDoubleHashMap$Iterator; (0, 0)
	4 invokevirtual (0, 0)
	5 org/apache/commons/math3/util/OpenIntToDoubleHashMap$Iterator.key:()I (0, 0)
	7 ireturn (0, 0)

