Method: <init>
	0 aload_0 (0, 0)
	1 aload_1 (0, 0)
	2 putfield (0, 0)
	3 org/apache/commons/math3/linear/OpenMapRealVector$OpenMapSparseIterator.this$0:Lorg/apache/commons/math3/linear/OpenMapRealVector; (0, 0)
	5 aload_0 (0, 0)
	6 invokespecial (0, 0)
	7 java/lang/Object.<init>:()V (0, 0)
	9 aload_0 (0, 0)
	10 aload_1 (0, 0)
	11 invokestatic (0, 0)
	12 org/apache/commons/math3/linear/OpenMapRealVector.access$000:(Lorg/apache/commons/math3/linear/OpenMapRealVector;)Lorg/apache/commons/math3/util/OpenIntToDoubleHashMap; (0, 0)
	14 invokevirtual (0, 0)
	15 org/apache/commons/math3/util/OpenIntToDoubleHashMap.iterator:()Lorg/apache/commons/math3/util/OpenIntToDoubleHashMap$Iterator; (0, 0)
	17 putfield (0, 0)
	18 org/apache/commons/math3/linear/OpenMapRealVector$OpenMapSparseIterator.iter:Lorg/apache/commons/math3/util/OpenIntToDoubleHashMap$Iterator; (0, 0)
	20 aload_0 (0, 0)
	21 new (0, 0)
	22 org/apache/commons/math3/linear/OpenMapRealVector$OpenMapEntry (0, 0)
	24 dup (0, 0)
	25 aload_1 (0, 0)
	26 aload_0 (0, 0)
	27 getfield (0, 0)
	28 org/apache/commons/math3/linear/OpenMapRealVector$OpenMapSparseIterator.iter:Lorg/apache/commons/math3/util/OpenIntToDoubleHashMap$Iterator; (0, 0)
	30 invokespecial (0, 0)
	31 org/apache/commons/math3/linear/OpenMapRealVector$OpenMapEntry.<init>:(Lorg/apache/commons/math3/linear/OpenMapRealVector;Lorg/apache/commons/math3/util/OpenIntToDoubleHashMap$Iterator;)V (0, 0)
	33 putfield (0, 0)
	34 org/apache/commons/math3/linear/OpenMapRealVector$OpenMapSparseIterator.current:Lorg/apache/commons/math3/linear/RealVector$Entry; (0, 0)
	36 return (0, 0)

Method: hasNext
	0 aload_0 (0, 0)
	1 getfield (0, 0)
	2 org/apache/commons/math3/linear/OpenMapRealVector$OpenMapSparseIterator.iter:Lorg/apache/commons/math3/util/OpenIntToDoubleHashMap$Iterator; (0, 0)
	4 invokevirtual (0, 0)
	5 org/apache/commons/math3/util/OpenIntToDoubleHashMap$Iterator.hasNext:()Z (0, 0)
	7 ireturn (0, 0)

Method: next
	0 aload_0 (0, 0)
	1 invokevirtual (0, 0)
	2 org/apache/commons/math3/linear/OpenMapRealVector$OpenMapSparseIterator.next:()Lorg/apache/commons/math3/linear/RealVector$Entry; (0, 0)
	4 areturn (0, 0)

Method: remove
	0 new (0, 0)
	1 java/lang/UnsupportedOperationException (0, 0)
	3 dup (0, 0)
	4 ldc (0, 0)
	5 Not supported (0, 0)
	6 invokespecial (0, 0)
	7 java/lang/UnsupportedOperationException.<init>:(Ljava/lang/String;)V (0, 0)
	9 athrow (0, 0)

