Method: <init>
	0 aload_0 (0, 0)
	1 aload_1 (0, 0)
	2 invokespecial (0, 0)
	5 return (0, 0)

Method: solve
	0 aload_1 (0, 0)
	1 invokestatic (0, 0)
	4 new (0, 0)
	7 dup (0, 0)
	8 aload_1 (0, 0)
	9 invokevirtual (0, 0)
	12 invokespecial (0, 0)
	15 astore (0, 0)
	17 aload_0 (0, 0)
	18 aload_1 (0, 0)
	19 aload_2 (0, 0)
	20 aload_3 (0, 0)
	21 aload (0, 0)
	23 invokevirtual (0, 0)
	26 areturn (0, 0)

Method: checkParameters
	0 aload_0 (0, 0)
	1 aload_2 (0, 0)
	2 aload_3 (0, 0)
	3 invokestatic (0, 0)
	6 aload_1 (1, 1)
	7 ifnull (1, 1)
	10 aload_1 (2, 1)
	11 invokevirtual (2, 1)
	14 aload_1 (2, 1)
	15 invokevirtual (2, 1)
	18 if_icmpeq (2, 1)
	21 new (2, 1)
	24 dup (2, 1)
	25 aload_1 (2, 1)
	26 invokevirtual (2, 1)
	29 aload_1 (2, 1)
	30 invokevirtual (2, 1)
	33 invokespecial (2, 1)
	36 athrow (2, 1)
	37 aload_1 (2, 1)
	38 invokevirtual (2, 1)
	41 aload_0 (2, 1)
	42 invokevirtual (2, 1)
	45 if_icmpeq (2, 1)
	48 new (2, 1)
	51 dup (2, 1)
	52 aload_1 (2, 1)
	53 invokevirtual (2, 1)
	56 aload_0 (2, 1)
	57 invokevirtual (2, 1)
	60 invokespecial (2, 1)
	63 athrow (2, 1)
	64 return (0, 0)

Method: solveInPlace
	0 aload_0 (0, 0)
	1 aload_1 (0, 0)
	2 aconst_null (0, 0)
	3 aload_2 (0, 0)
	4 aload_3 (0, 0)
	5 invokevirtual (0, 0)
	8 areturn (0, 0)

