Method: <init>
	0 aload_0 (0, 0)
	1 invokespecial (0, 0)
	2 java/lang/Object.<init>:()V (0, 0)
	4 aload_0 (0, 0)
	5 aload_1 (0, 0)
	6 putfield (0, 0)
	7 org/apache/commons/math3/linear/QRDecomposition$Solver.qrt:[[D (0, 0)
	9 aload_0 (0, 0)
	10 aload_2 (0, 0)
	11 putfield (0, 0)
	12 org/apache/commons/math3/linear/QRDecomposition$Solver.rDiag:[D (0, 0)
	14 aload_0 (0, 0)
	15 dload_3 (0, 0)
	16 putfield (0, 0)
	17 org/apache/commons/math3/linear/QRDecomposition$Solver.threshold:D (0, 0)
	19 return (0, 0)

Method: isNonSingular
	0 aload_0 (1, 4)
	1 getfield (1, 4)
	2 org/apache/commons/math3/linear/QRDecomposition$Solver.rDiag:[D (1, 4)
	4 astore_1 (1, 4)
	5 aload_1 (1, 4)
	6 arraylength (1, 4)
	7 istore_2 (1, 4)
	8 iconst_0 (1, 4)
	9 istore_3 (1, 4)
	10 iload_3 (1, 4)
	11 iload_2 (1, 4)
	12 if_icmpge (1, 4)
	13 29 (1, 4)
	15 aload_1 (1, 4)
	16 iload_3 (1, 4)
	17 daload (1, 4)
	18 dstore (1, 4)
	19 #4 (1, 4)
	20 dload (2, 1)
	21 #4 (2, 1)
	22 invokestatic (2, 1)
	23 org/apache/commons/math3/util/FastMath.abs:(D)D (2, 1)
	25 aload_0 (2, 1)
	26 getfield (2, 1)
	27 org/apache/commons/math3/linear/QRDecomposition$Solver.threshold:D (2, 1)
	29 dcmpg (2, 1)
	30 ifgt (2, 1)
	31 5 (2, 1)
	33 iconst_0 (2, 1)
	34 ireturn (2, 1)
	35 iinc (2, 1)
	36 #3 (2, 1)
	37 -89 (2, 1)
	38 goto (2, 1)
	39 -28 (2, 1)
	41 iconst_1 (1, 4)
	42 ireturn (1, 4)

Method: solve
	0 aload_0 (0, 0)
	1 getfield (0, 0)
	2 org/apache/commons/math3/linear/QRDecomposition$Solver.qrt:[[D (0, 0)
	4 arraylength (0, 0)
	5 istore_2 (0, 0)
	6 aload_0 (0, 0)
	7 getfield (0, 0)
	8 org/apache/commons/math3/linear/QRDecomposition$Solver.qrt:[[D (0, 0)
	10 iconst_0 (0, 0)
	11 aaload (0, 0)
	12 arraylength (0, 0)
	13 istore_3 (0, 0)
	14 aload_1 (1, 1)
	15 invokeinterface (1, 1)
	16 org/apache/commons/math3/linear/RealMatrix.getColumnDimension:()I (1, 1)
	18 0 (1, 1)
	20 iload_3 (1, 1)
	21 if_icmpeq (1, 1)
	22 18 (1, 1)
	24 new (1, 1)
	25 org/apache/commons/math3/exception/DimensionMismatchException (1, 1)
	27 dup (1, 1)
	28 aload_1 (1, 1)
	29 invokeinterface (1, 1)
	30 org/apache/commons/math3/linear/RealMatrix.getColumnDimension:()I (1, 1)
	32 0 (1, 1)
	34 iload_3 (1, 1)
	35 invokespecial (1, 1)
	36 org/apache/commons/math3/exception/DimensionMismatchException.<init>:(II)V (1, 1)
	38 athrow (1, 1)
	39 aload_0 (1, 1)
	40 invokevirtual (1, 1)
	41 org/apache/commons/math3/linear/QRDecomposition$Solver.isNonSingular:()Z (1, 1)
	43 ifne (1, 1)
	44 11 (1, 1)
	46 new (1, 1)
	47 org/apache/commons/math3/linear/SingularMatrixException (1, 1)
	49 dup (1, 1)
	50 invokespecial (1, 1)
	51 org/apache/commons/math3/linear/SingularMatrixException.<init>:()V (1, 1)
	53 athrow (1, 1)
	54 aload_1 (0, 0)
	55 invokeinterface (0, 0)
	56 org/apache/commons/math3/linear/RealMatrix.org/apache/commons/math3/linear/BlockRealMatrix (0, 0)
	58 0 (0, 0)
	60 istore (0, 0)
	61 #4 (0, 0)
	62 bipush (0, 0)
	63 52 (0, 0)
	64 istore (0, 0)
	65 #5 (0, 0)
	66 iload (0, 0)
	67 #4 (0, 0)
	68 bipush (0, 0)
	69 52 (0, 0)
	70 iadd (0, 0)
	71 iconst_1 (0, 0)
	72 isub (0, 0)
	73 bipush (0, 0)
	74 52 (0, 0)
	75 idiv (0, 0)
	76 istore (0, 0)
	77 #6 (0, 0)
	78 iload_2 (0, 0)
	79 iload (0, 0)
	80 #4 (0, 0)
	81 invokestatic (0, 0)
	82 org/apache/commons/math3/linear/BlockRealMatrix.createBlocksLayout:(II)[[D (0, 0)
	84 astore (0, 0)
	85 #7 (0, 0)
	86 aload_1 (0, 0)
	87 invokeinterface (0, 0)
	88 org/apache/commons/math3/linear/RealMatrix.getColumnDimension:()I (0, 0)
	90 0 (0, 0)
	92 bipush (0, 0)
	93 52 (0, 0)
	94 multianewarray (0, 0)
	95 [[D (0, 0)
	97 58 (0, 0)
	98 astore (0, 0)
	99 #8 (0, 0)
	100 bipush (0, 0)
	101 52 (0, 0)
	102 newarray (0, 0)
	103 7 (0, 0)
	104 astore (0, 0)
	105 #9 (0, 0)
	106 iconst_0 (1, 4)
	107 istore (1, 4)
	108 #10 (1, 4)
	109 iload (1, 4)
	110 #10 (1, 4)
	111 iload (1, 4)
	112 #6 (1, 4)
	113 if_icmpge (1, 4)
	114 442 (1, 4)
	116 iload (1, 4)
	117 #10 (1, 4)
	118 bipush (1, 4)
	119 52 (1, 4)
	120 imul (1, 4)
	121 istore (1, 4)
	122 #11 (1, 4)
	123 iload (1, 4)
	124 #11 (1, 4)
	125 bipush (1, 4)
	126 52 (1, 4)
	127 iadd (1, 4)
	128 iload (1, 4)
	129 #4 (1, 4)
	130 invokestatic (1, 4)
	131 org/apache/commons/math3/util/FastMath.min:(II)I (1, 4)
	133 istore (1, 4)
	134 #12 (1, 4)
	135 iload (1, 4)
	136 #12 (1, 4)
	137 iload (1, 4)
	138 #11 (1, 4)
	139 isub (1, 4)
	140 istore (1, 4)
	141 #13 (1, 4)
	142 aload_1 (1, 4)
	143 iconst_0 (1, 4)
	144 iload_3 (1, 4)
	145 iconst_1 (1, 4)
	146 isub (1, 4)
	147 iload (1, 4)
	148 #11 (1, 4)
	149 iload (1, 4)
	150 #12 (1, 4)
	151 iconst_1 (1, 4)
	152 isub (1, 4)
	153 aload (1, 4)
	154 #8 (1, 4)
	155 invokeinterface (1, 4)
	156 org/apache/commons/math3/linear/RealMatrix.java/util/Arrays (1, 4)
	158 0 (1, 4)
	160 iconst_0 (3, 4)
	161 istore (3, 4)
	162 #14 (3, 4)
	163 iload (3, 4)
	164 #14 (3, 4)
	165 iload_3 (3, 4)
	166 iload_2 (3, 4)
	167 invokestatic (3, 4)
	168 org/apache/commons/math3/util/FastMath.min:(II)I (3, 4)
	170 if_icmpge (3, 4)
	171 194 (3, 4)
	173 aload_0 (3, 4)
	174 getfield (3, 4)
	175 org/apache/commons/math3/linear/QRDecomposition$Solver.qrt:[[D (3, 4)
	177 iload (3, 4)
	178 #14 (3, 4)
	179 aaload (3, 4)
	180 astore (3, 4)
	181 #15 (3, 4)
	182 dconst_1 (3, 4)
	183 aload_0 (3, 4)
	184 getfield (3, 4)
	185 org/apache/commons/math3/linear/QRDecomposition$Solver.rDiag:[D (3, 4)
	187 iload (3, 4)
	188 #14 (3, 4)
	189 daload (3, 4)
	190 aload (3, 4)
	191 #15 (3, 4)
	192 iload (3, 4)
	193 #14 (3, 4)
	194 daload (3, 4)
	195 dmul (3, 4)
	196 ddiv (3, 4)
	197 dstore (3, 4)
	198 #16 (3, 4)
	199 aload (3, 4)
	200 #9 (3, 4)
	201 iconst_0 (3, 4)
	202 iload (3, 4)
	203 #13 (3, 4)
	204 dconst_0 (3, 4)
	205 invokestatic (3, 4)
	206 java/util/Arrays.fill:([DIID)V (3, 4)
	208 iload (4, 4)
	209 #14 (4, 4)
	210 istore (4, 4)
	211 #18 (4, 4)
	212 iload (4, 4)
	213 #18 (4, 4)
	214 iload_3 (4, 4)
	215 if_icmpge (4, 4)
	216 55 (4, 4)
	218 aload (4, 4)
	219 #15 (4, 4)
	220 iload (4, 4)
	221 #18 (4, 4)
	222 daload (4, 4)
	223 dstore (4, 4)
	224 #19 (4, 4)
	225 aload (4, 4)
	226 #8 (4, 4)
	227 iload (4, 4)
	228 #18 (4, 4)
	229 aaload (4, 4)
	230 astore (4, 4)
	231 #21 (4, 4)
	232 iconst_0 (5, 4)
	233 istore (5, 4)
	234 #22 (5, 4)
	235 iload (5, 4)
	236 #22 (5, 4)
	237 iload (5, 4)
	238 #13 (5, 4)
	239 if_icmpge (5, 4)
	240 25 (5, 4)
	242 aload (5, 4)
	243 #9 (5, 4)
	244 iload (5, 4)
	245 #22 (5, 4)
	246 dup2 (5, 4)
	247 daload (5, 4)
	248 dload (5, 4)
	249 #19 (5, 4)
	250 aload (5, 4)
	251 #21 (5, 4)
	252 iload (5, 4)
	253 #22 (5, 4)
	254 daload (5, 4)
	255 dmul (5, 4)
	256 dadd (5, 4)
	257 dastore (5, 4)
	258 iinc (5, 4)
	259 #22 (5, 4)
	260 -89 (5, 4)
	261 goto (5, 4)
	262 -26 (5, 4)
	264 iinc (5, 4)
	265 #18 (5, 4)
	266 -89 (5, 4)
	267 goto (5, 4)
	268 -55 (5, 4)
	270 iconst_0 (5, 4)
	271 istore (5, 4)
	272 #18 (5, 4)
	273 iload (5, 4)
	274 #18 (5, 4)
	275 iload (5, 4)
	276 #13 (5, 4)
	277 if_icmpge (5, 4)
	278 19 (5, 4)
	280 aload (5, 4)
	281 #9 (5, 4)
	282 iload (5, 4)
	283 #18 (5, 4)
	284 dup2 (5, 4)
	285 daload (5, 4)
	286 dload (5, 4)
	287 #16 (5, 4)
	288 dmul (5, 4)
	289 dastore (5, 4)
	290 iinc (5, 4)
	291 #18 (5, 4)
	292 -89 (5, 4)
	293 goto (5, 4)
	294 -20 (5, 4)
	296 iload (5, 4)
	297 #14 (5, 4)
	298 istore (5, 4)
	299 #18 (5, 4)
	300 iload (5, 4)
	301 #18 (5, 4)
	302 iload_3 (5, 4)
	303 if_icmpge (5, 4)
	304 55 (5, 4)
	306 aload (5, 4)
	307 #15 (5, 4)
	308 iload (5, 4)
	309 #18 (5, 4)
	310 daload (5, 4)
	311 dstore (5, 4)
	312 #19 (5, 4)
	313 aload (5, 4)
	314 #8 (5, 4)
	315 iload (5, 4)
	316 #18 (5, 4)
	317 aaload (5, 4)
	318 astore (5, 4)
	319 #21 (5, 4)
	320 iconst_0 (6, 4)
	321 istore (6, 4)
	322 #22 (6, 4)
	323 iload (6, 4)
	324 #22 (6, 4)
	325 iload (6, 4)
	326 #13 (6, 4)
	327 if_icmpge (6, 4)
	328 25 (6, 4)
	330 aload (6, 4)
	331 #21 (6, 4)
	332 iload (6, 4)
	333 #22 (6, 4)
	334 dup2 (6, 4)
	335 daload (6, 4)
	336 aload (6, 4)
	337 #9 (6, 4)
	338 iload (6, 4)
	339 #22 (6, 4)
	340 daload (6, 4)
	341 dload (6, 4)
	342 #19 (6, 4)
	343 dmul (6, 4)
	344 dadd (6, 4)
	345 dastore (6, 4)
	346 iinc (6, 4)
	347 #22 (6, 4)
	348 -89 (6, 4)
	349 goto (6, 4)
	350 -26 (6, 4)
	352 iinc (6, 4)
	353 #18 (6, 4)
	354 -89 (6, 4)
	355 goto (6, 4)
	356 -55 (6, 4)
	358 iinc (6, 4)
	359 #14 (6, 4)
	360 -89 (6, 4)
	361 goto (6, 4)
	362 -198 (6, 4)
	364 aload_0 (6, 4)
	365 getfield (6, 4)
	366 org/apache/commons/math3/linear/QRDecomposition$Solver.rDiag:[D (6, 4)
	368 arraylength (6, 4)
	369 iconst_1 (6, 4)
	370 isub (6, 4)
	371 istore (6, 4)
	372 #14 (6, 4)
	373 iload (6, 4)
	374 #14 (6, 4)
	375 iflt (6, 4)
	376 174 (6, 4)
	378 iload (6, 4)
	379 #14 (6, 4)
	380 bipush (6, 4)
	381 52 (6, 4)
	382 idiv (6, 4)
	383 istore (6, 4)
	384 #15 (6, 4)
	385 iload (6, 4)
	386 #15 (6, 4)
	387 bipush (6, 4)
	388 52 (6, 4)
	389 imul (6, 4)
	390 istore (6, 4)
	391 #16 (6, 4)
	392 dconst_1 (6, 4)
	393 aload_0 (6, 4)
	394 getfield (6, 4)
	395 org/apache/commons/math3/linear/QRDecomposition$Solver.rDiag:[D (6, 4)
	397 iload (6, 4)
	398 #14 (6, 4)
	399 daload (6, 4)
	400 ddiv (6, 4)
	401 dstore (6, 4)
	402 #17 (6, 4)
	403 aload (6, 4)
	404 #8 (6, 4)
	405 iload (6, 4)
	406 #14 (6, 4)
	407 aaload (6, 4)
	408 astore (6, 4)
	409 #19 (6, 4)
	410 aload (6, 4)
	411 #7 (6, 4)
	412 iload (6, 4)
	413 #15 (6, 4)
	414 iload (6, 4)
	415 #6 (6, 4)
	416 imul (6, 4)
	417 iload (6, 4)
	418 #10 (6, 4)
	419 iadd (6, 4)
	420 aaload (6, 4)
	421 astore (6, 4)
	422 #20 (6, 4)
	423 iload (6, 4)
	424 #14 (6, 4)
	425 iload (6, 4)
	426 #16 (6, 4)
	427 isub (6, 4)
	428 iload (6, 4)
	429 #13 (6, 4)
	430 imul (6, 4)
	431 istore (6, 4)
	432 #21 (6, 4)
	433 iconst_0 (7, 4)
	434 istore (7, 4)
	435 #22 (7, 4)
	436 iload (7, 4)
	437 #22 (7, 4)
	438 iload (7, 4)
	439 #13 (7, 4)
	440 if_icmpge (7, 4)
	441 32 (7, 4)
	443 aload (7, 4)
	444 #19 (7, 4)
	445 iload (7, 4)
	446 #22 (7, 4)
	447 dup2 (7, 4)
	448 daload (7, 4)
	449 dload (7, 4)
	450 #17 (7, 4)
	451 dmul (7, 4)
	452 dastore (7, 4)
	453 aload (7, 4)
	454 #20 (7, 4)
	455 iload (7, 4)
	456 #21 (7, 4)
	457 iinc (7, 4)
	458 #21 (7, 4)
	459 25 (7, 4)
	460 aload (7, 4)
	461 #19 (7, 4)
	462 iload (7, 4)
	463 #22 (7, 4)
	464 daload (7, 4)
	465 dastore (7, 4)
	466 iinc (7, 4)
	467 #22 (7, 4)
	468 -89 (7, 4)
	469 goto (7, 4)
	470 -33 (7, 4)
	472 aload_0 (6, 4)
	473 getfield (6, 4)
	474 org/apache/commons/math3/linear/QRDecomposition$Solver.qrt:[[D (6, 4)
	476 iload (6, 4)
	477 #14 (6, 4)
	478 aaload (6, 4)
	479 astore (6, 4)
	480 #22 (6, 4)
	481 iconst_0 (7, 4)
	482 istore (7, 4)
	483 #23 (7, 4)
	484 iload (7, 4)
	485 #23 (7, 4)
	486 iload (7, 4)
	487 #14 (7, 4)
	488 if_icmpge (7, 4)
	489 55 (7, 4)
	491 aload (7, 4)
	492 #22 (7, 4)
	493 iload (7, 4)
	494 #23 (7, 4)
	495 daload (7, 4)
	496 dstore (7, 4)
	497 #24 (7, 4)
	498 aload (7, 4)
	499 #8 (7, 4)
	500 iload (7, 4)
	501 #23 (7, 4)
	502 aaload (7, 4)
	503 astore (7, 4)
	504 #26 (7, 4)
	505 iconst_0 (8, 4)
	506 istore (8, 4)
	507 #27 (8, 4)
	508 iload (8, 4)
	509 #27 (8, 4)
	510 iload (8, 4)
	511 #13 (8, 4)
	512 if_icmpge (8, 4)
	513 25 (8, 4)
	515 aload (8, 4)
	516 #26 (8, 4)
	517 iload (8, 4)
	518 #27 (8, 4)
	519 dup2 (8, 4)
	520 daload (8, 4)
	521 aload (8, 4)
	522 #19 (8, 4)
	523 iload (8, 4)
	524 #27 (8, 4)
	525 daload (8, 4)
	526 dload (8, 4)
	527 #24 (8, 4)
	528 dmul (8, 4)
	529 dsub (8, 4)
	530 dastore (8, 4)
	531 iinc (8, 4)
	532 #27 (8, 4)
	533 -89 (8, 4)
	534 goto (8, 4)
	535 -26 (8, 4)
	537 iinc (8, 4)
	538 #23 (8, 4)
	539 -89 (8, 4)
	540 goto (8, 4)
	541 -56 (8, 4)
	543 iinc (8, 4)
	544 #14 (8, 4)
	545 -89 (8, 4)
	546 goto (8, 4)
	547 -173 (8, 4)
	549 iinc (8, 4)
	550 #10 (8, 4)
	551 -89 (8, 4)
	552 goto (8, 4)
	553 -443 (8, 4)
	555 new (7, 4)
	556 org/apache/commons/math3/linear/BlockRealMatrix (7, 4)
	558 dup (7, 4)
	559 iload_2 (7, 4)
	560 iload (7, 4)
	561 #4 (7, 4)
	562 aload (7, 4)
	563 #7 (7, 4)
	564 iconst_0 (7, 4)
	565 invokespecial (7, 4)
	566 org/apache/commons/math3/linear/BlockRealMatrix.<init>:(II[[DZ)V (7, 4)
	568 areturn (6, 4)

Method: getInverse
	0 aload_0 (0, 0)
	1 aload_0 (0, 0)
	2 getfield (0, 0)
	3 org/apache/commons/math3/linear/QRDecomposition$Solver.qrt:[[D (0, 0)
	5 iconst_0 (0, 0)
	6 aaload (0, 0)
	7 arraylength (0, 0)
	8 invokestatic (0, 0)
	9 org/apache/commons/math3/linear/MatrixUtils.createRealIdentityMatrix:(I)Lorg/apache/commons/math3/linear/RealMatrix; (0, 0)
	11 invokevirtual (0, 0)
	12 org/apache/commons/math3/linear/QRDecomposition$Solver.solve:(Lorg/apache/commons/math3/linear/RealMatrix;)Lorg/apache/commons/math3/linear/RealMatrix; (0, 0)
	14 areturn (0, 0)

