Method: <init>
	0 aload_0 (1, 4)
	1 invokespecial (1, 4)
	2 java/lang/Object.<init>:()V (1, 4)
	4 aload_0 (1, 4)
	5 aload_1 (1, 4)
	6 putfield (1, 4)
	7 org/apache/commons/math3/linear/RealVectorFormat.prefix:Ljava/lang/String; (1, 4)
	9 aload_0 (1, 4)
	10 aload_2 (1, 4)
	11 putfield (1, 4)
	12 org/apache/commons/math3/linear/RealVectorFormat.suffix:Ljava/lang/String; (1, 4)
	14 aload_0 (1, 4)
	15 aload_3 (1, 4)
	16 putfield (1, 4)
	17 org/apache/commons/math3/linear/RealVectorFormat.separator:Ljava/lang/String; (1, 4)
	19 aload_0 (1, 4)
	20 aload_1 (1, 4)
	21 invokevirtual (1, 4)
	22 java/lang/String.trim:()Ljava/lang/String; (1, 4)
	24 putfield (1, 4)
	25 org/apache/commons/math3/linear/RealVectorFormat.trimmedPrefix:Ljava/lang/String; (1, 4)
	27 aload_0 (1, 4)
	28 aload_2 (1, 4)
	29 invokevirtual (1, 4)
	30 java/lang/String.trim:()Ljava/lang/String; (1, 4)
	32 putfield (1, 4)
	33 org/apache/commons/math3/linear/RealVectorFormat.trimmedSuffix:Ljava/lang/String; (1, 4)
	35 aload_0 (1, 4)
	36 aload_3 (1, 4)
	37 invokevirtual (1, 4)
	38 java/lang/String.trim:()Ljava/lang/String; (1, 4)
	40 putfield (1, 4)
	41 org/apache/commons/math3/linear/RealVectorFormat.trimmedSeparator:Ljava/lang/String; (1, 4)
	43 aload_0 (2, 4)
	44 aload (2, 4)
	45 #4 (2, 4)
	46 putfield (2, 4)
	47 org/apache/commons/math3/linear/RealVectorFormat.format:Ljava/text/NumberFormat; (2, 4)
	49 return (0, 0)

Method: getAvailableLocales
	0 invokestatic (0, 0)
	1 java/text/NumberFormat.getAvailableLocales:()[Ljava/util/Locale; (0, 0)
	3 areturn (0, 0)

Method: getPrefix
	0 aload_0 (0, 0)
	1 getfield (0, 0)
	2 org/apache/commons/math3/linear/RealVectorFormat.prefix:Ljava/lang/String; (0, 0)
	4 areturn (0, 0)

Method: getSuffix
	0 aload_0 (0, 0)
	1 getfield (0, 0)
	2 org/apache/commons/math3/linear/RealVectorFormat.suffix:Ljava/lang/String; (0, 0)
	4 areturn (0, 0)

Method: getSeparator
	0 aload_0 (0, 0)
	1 getfield (0, 0)
	2 org/apache/commons/math3/linear/RealVectorFormat.separator:Ljava/lang/String; (0, 0)
	4 areturn (0, 0)

Method: getFormat
	0 aload_0 (1, 4)
	1 getfield (1, 4)
	2 org/apache/commons/math3/linear/RealVectorFormat.format:Ljava/text/NumberFormat; (1, 4)
	4 areturn (0, 4)

Method: getInstance
	0 new (0, 0)
	1 org/apache/commons/math3/linear/RealVectorFormat (0, 0)
	3 dup (0, 0)
	4 aload_0 (0, 0)
	5 invokestatic (0, 0)
	6 org/apache/commons/math3/util/CompositeFormat.getDefaultNumberFormat:(Ljava/util/Locale;)Ljava/text/NumberFormat; (0, 0)
	8 invokespecial (0, 0)
	9 org/apache/commons/math3/linear/RealVectorFormat.<init>:(Ljava/text/NumberFormat;)V (0, 0)
	11 areturn (0, 0)

Method: format
	0 aload_3 (0, 0)
	1 iconst_0 (0, 0)
	2 invokevirtual (0, 0)
	3 java/text/FieldPosition.setBeginIndex:(I)V (0, 0)
	5 aload_3 (0, 0)
	6 iconst_0 (0, 0)
	7 invokevirtual (0, 0)
	8 java/text/FieldPosition.setEndIndex:(I)V (0, 0)
	10 aload_2 (1, 4)
	11 aload_0 (1, 4)
	12 getfield (1, 4)
	13 org/apache/commons/math3/linear/RealVectorFormat.prefix:Ljava/lang/String; (1, 4)
	15 invokevirtual (1, 4)
	16 java/lang/StringBuffer.append:(Ljava/lang/String;)Ljava/lang/StringBuffer; (1, 4)
	18 pop (1, 4)
	19 iconst_0 (3, 4)
	20 istore (3, 4)
	21 #4 (3, 4)
	22 iload (3, 4)
	23 #4 (3, 4)
	24 aload_1 (3, 4)
	25 invokevirtual (3, 4)
	26 org/apache/commons/math3/linear/RealVector.getDimension:()I (3, 4)
	28 if_icmpge (3, 4)
	29 39 (3, 4)
	31 iload (4, 1)
	32 #4 (4, 1)
	33 ifle (4, 1)
	34 12 (4, 1)
	36 aload_2 (4, 1)
	37 aload_0 (4, 1)
	38 getfield (4, 1)
	39 org/apache/commons/math3/linear/RealVectorFormat.separator:Ljava/lang/String; (4, 1)
	41 invokevirtual (4, 1)
	42 java/lang/StringBuffer.append:(Ljava/lang/String;)Ljava/lang/StringBuffer; (4, 1)
	44 pop (4, 1)
	45 aload_1 (4, 4)
	46 iload (4, 4)
	47 #4 (4, 4)
	48 invokevirtual (4, 4)
	49 org/apache/commons/math3/linear/RealVector.getEntry:(I)D (4, 4)
	51 aload_0 (4, 4)
	52 getfield (4, 4)
	53 org/apache/commons/math3/linear/RealVectorFormat.format:Ljava/text/NumberFormat; (4, 4)
	55 aload_2 (4, 4)
	56 aload_3 (4, 4)
	57 invokestatic (4, 4)
	58 org/apache/commons/math3/util/CompositeFormat.formatDouble:(DLjava/text/NumberFormat;Ljava/lang/StringBuffer;Ljava/text/FieldPosition;)Ljava/lang/StringBuffer; (4, 4)
	60 pop (4, 4)
	61 iinc (4, 4)
	62 #4 (4, 4)
	63 -89 (4, 4)
	64 goto (4, 4)
	65 -42 (4, 4)
	67 aload_2 (3, 4)
	68 aload_0 (3, 4)
	69 getfield (3, 4)
	70 org/apache/commons/math3/linear/RealVectorFormat.suffix:Ljava/lang/String; (3, 4)
	72 invokevirtual (3, 4)
	73 java/lang/StringBuffer.append:(Ljava/lang/String;)Ljava/lang/StringBuffer; (3, 4)
	75 pop (3, 4)
	76 aload_2 (3, 4)
	77 areturn (0, 4)

Method: parse
	0 aload_2 (0, 0)
	1 invokevirtual (0, 0)
	2 java/text/ParsePosition.getIndex:()I (0, 0)
	4 istore_3 (0, 0)
	5 aload_1 (0, 0)
	6 aload_2 (0, 0)
	7 invokestatic (0, 0)
	8 org/apache/commons/math3/util/CompositeFormat.parseAndIgnoreWhitespace:(Ljava/lang/String;Ljava/text/ParsePosition;)V (0, 0)
	10 aload_1 (1, 1)
	11 aload_0 (1, 1)
	12 getfield (1, 1)
	13 org/apache/commons/math3/linear/RealVectorFormat.trimmedPrefix:Ljava/lang/String; (1, 1)
	15 aload_2 (1, 1)
	16 invokestatic (1, 1)
	17 org/apache/commons/math3/util/CompositeFormat.parseFixedstring:(Ljava/lang/String;Ljava/lang/String;Ljava/text/ParsePosition;)Z (1, 1)
	19 ifne (1, 1)
	20 5 (1, 1)
	22 aconst_null (1, 1)
	23 areturn (1, 1)
	24 new (0, 0)
	25 java/util/ArrayList (0, 0)
	27 dup (0, 0)
	28 invokespecial (0, 0)
	29 java/util/ArrayList.<init>:()V (0, 0)
	31 astore (0, 0)
	32 #4 (0, 0)
	33 iconst_1 (1, 4)
	34 istore (1, 4)
	35 #5 (1, 4)
	36 iload (1, 4)
	37 #5 (1, 4)
	38 ifeq (1, 4)
	39 82 (1, 4)
	41 aload (2, 1)
	42 #4 (2, 1)
	43 invokeinterface (2, 1)
	44 java/util/List.parseNumber:(Ljava/lang/String;Ljava/text/NumberFormat;Ljava/text/ParsePosition;)Ljava/lang/Number; (2, 1)
	46 0 (2, 1)
	48 ifne (2, 1)
	49 23 (2, 1)
	51 aload_1 (2, 1)
	52 aload_2 (2, 1)
	53 invokestatic (2, 1)
	54 org/apache/commons/math3/util/CompositeFormat.parseAndIgnoreWhitespace:(Ljava/lang/String;Ljava/text/ParsePosition;)V (2, 1)
	56 aload_1 (3, 1)
	57 aload_0 (3, 1)
	58 getfield (3, 1)
	59 org/apache/commons/math3/linear/RealVectorFormat.trimmedSeparator:Ljava/lang/String; (3, 1)
	61 aload_2 (3, 1)
	62 invokestatic (3, 1)
	63 org/apache/commons/math3/util/CompositeFormat.parseFixedstring:(Ljava/lang/String;Ljava/lang/String;Ljava/text/ParsePosition;)Z (3, 1)
	65 ifne (3, 1)
	66 6 (3, 1)
	68 iconst_0 (3, 1)
	69 istore (3, 1)
	70 #5 (3, 1)
	71 iload (2, 1)
	72 #5 (2, 1)
	73 ifeq (2, 1)
	74 -37 (2, 1)
	76 aload_1 (2, 1)
	77 aload_2 (2, 1)
	78 invokestatic (2, 1)
	79 org/apache/commons/math3/util/CompositeFormat.parseAndIgnoreWhitespace:(Ljava/lang/String;Ljava/text/ParsePosition;)V (2, 1)
	81 aload_1 (3, 4)
	82 aload_0 (3, 4)
	83 getfield (3, 4)
	84 org/apache/commons/math3/linear/RealVectorFormat.format:Ljava/text/NumberFormat; (3, 4)
	86 aload_2 (3, 4)
	87 invokestatic (3, 4)
	88 org/apache/commons/math3/util/CompositeFormat.parseNumber:(Ljava/lang/String;Ljava/text/NumberFormat;Ljava/text/ParsePosition;)Ljava/lang/Number; (3, 4)
	90 astore (3, 4)
	91 #6 (3, 4)
	92 aload (4, 1)
	93 #6 (4, 1)
	94 ifnull (4, 1)
	95 16 (4, 1)
	97 aload (4, 1)
	98 #4 (4, 1)
	99 aload (4, 1)
	100 #6 (4, 1)
	101 invokeinterface (4, 1)
	102 java/util/List.setIndex:(I)V (4, 1)
	104 0 (4, 1)
	106 pop (4, 1)
	107 goto (4, 1)
	108 10 (4, 1)
	110 aload_2 (5, 2)
	111 iload_3 (5, 2)
	112 invokevirtual (5, 2)
	113 java/text/ParsePosition.setIndex:(I)V (5, 2)
	115 aconst_null (5, 2)
	116 areturn (5, 2)
	117 goto (1, 4)
	118 -81 (1, 4)
	120 aload_1 (0, 0)
	121 aload_2 (0, 0)
	122 invokestatic (0, 0)
	123 org/apache/commons/math3/util/CompositeFormat.parseAndIgnoreWhitespace:(Ljava/lang/String;Ljava/text/ParsePosition;)V (0, 0)
	125 aload_1 (1, 1)
	126 aload_0 (1, 1)
	127 getfield (1, 1)
	128 org/apache/commons/math3/linear/RealVectorFormat.trimmedSuffix:Ljava/lang/String; (1, 1)
	130 aload_2 (1, 1)
	131 invokestatic (1, 1)
	132 org/apache/commons/math3/util/CompositeFormat.parseFixedstring:(Ljava/lang/String;Ljava/lang/String;Ljava/text/ParsePosition;)Z (1, 1)
	134 ifne (1, 1)
	135 5 (1, 1)
	137 aconst_null (1, 1)
	138 areturn (1, 1)
	139 aload (0, 0)
	140 #4 (0, 0)
	141 invokeinterface (0, 0)
	142 java/util/List.get:(I)Ljava/lang/Object; (0, 0)
	144 0 (0, 0)
	146 newarray (0, 0)
	147 7 (0, 0)
	148 astore (0, 0)
	149 #5 (0, 0)
	150 iconst_0 (1, 4)
	151 istore (1, 4)
	152 #6 (1, 4)
	153 iload (1, 4)
	154 #6 (1, 4)
	155 aload (1, 4)
	156 #5 (1, 4)
	157 arraylength (1, 4)
	158 if_icmpge (1, 4)
	159 29 (1, 4)
	161 aload (1, 4)
	162 #5 (1, 4)
	163 iload (1, 4)
	164 #6 (1, 4)
	165 aload (1, 4)
	166 #4 (1, 4)
	167 iload (1, 4)
	168 #6 (1, 4)
	169 invokeinterface (1, 4)
	170 java/util/List.java/lang/Number (1, 4)
	172 0 (1, 4)
	174 checkcast (1, 4)
	175 java/lang/Number (1, 4)
	177 invokevirtual (1, 4)
	178 java/lang/Number.doubleValue:()D (1, 4)
	180 dastore (1, 4)
	181 iinc (1, 4)
	182 #6 (1, 4)
	183 -89 (1, 4)
	184 goto (1, 4)
	185 -31 (1, 4)
	187 new (0, 0)
	188 org/apache/commons/math3/linear/ArrayRealVector (0, 0)
	190 dup (0, 0)
	191 aload (0, 0)
	192 #5 (0, 0)
	193 iconst_0 (0, 0)
	194 invokespecial (0, 0)
	195 org/apache/commons/math3/linear/ArrayRealVector.<init>:([DZ)V (0, 0)
	197 areturn (0, 0)

