Method: getValue
	0 aload_0 (0, 0)
	1 getfield (0, 0)
	2 org/apache/commons/math3/linear/RealVector$2$UnmodifiableEntry.this$0:Lorg/apache/commons/math3/linear/RealVector$2; (0, 0)
	4 getfield (0, 0)
	5 org/apache/commons/math3/linear/RealVector$2.val$v:Lorg/apache/commons/math3/linear/RealVector; (0, 0)
	7 aload_0 (0, 0)
	8 invokevirtual (0, 0)
	9 org/apache/commons/math3/linear/RealVector$2$UnmodifiableEntry.getIndex:()I (0, 0)
	11 invokevirtual (0, 0)
	12 org/apache/commons/math3/linear/RealVector.getEntry:(I)D (0, 0)
	14 dreturn (0, 0)

Method: setValue
	0 new (0, 0)
	1 org/apache/commons/math3/exception/MathUnsupportedOperationException (0, 0)
	3 dup (0, 0)
	4 invokespecial (0, 0)
	5 org/apache/commons/math3/exception/MathUnsupportedOperationException.<init>:()V (0, 0)
	7 athrow (0, 0)

