Method: <init>
	0 aload_0 (0, 0)
	1 aload_1 (0, 0)
	2 putfield (0, 0)
	5 aload_0 (0, 0)
	6 invokespecial (0, 0)
	9 aload_0 (0, 0)
	10 aload_1 (0, 0)
	11 invokevirtual (0, 0)
	14 putfield (0, 0)
	17 aload_0 (0, 0)
	18 new (0, 0)
	21 dup (0, 0)
	22 aload_1 (0, 0)
	23 invokespecial (0, 0)
	26 putfield (0, 0)
	29 aload_0 (0, 0)
	30 new (0, 0)
	33 dup (0, 0)
	34 aload_1 (0, 0)
	35 invokespecial (0, 0)
	38 putfield (0, 0)
	41 aload_0 (1, 1)
	42 getfield (1, 1)
	45 invokevirtual (1, 1)
	48 dconst_0 (1, 1)
	49 dcmpl (1, 1)
	50 ifne (1, 1)
	53 aload_0 (1, 1)
	54 aload_0 (1, 1)
	55 getfield (1, 1)
	58 invokevirtual (1, 1)
	61 return (0, 0)

Method: advance
	0 aload_1 (1, 1)
	1 ifnonnull (1, 1)
	4 return (1, 1)
	5 aload_1 (0, 0)
	6 aload_1 (0, 0)
	7 invokevirtual (0, 0)
	10 iconst_1 (0, 0)
	11 iadd (0, 0)
	12 invokevirtual (0, 0)
	15 aload_1 (-1, 0)
	16 invokevirtual (-1, 0)
	19 aload_0 (-1, 0)
	20 getfield (-1, 0)
	23 if_icmpge (-1, 0)
	26 aload_1 (-1, 0)
	27 invokevirtual (-1, 0)
	30 dconst_0 (-1, 0)
	31 dcmpl (-1, 0)
	32 ifeq (-1, 0)
	35 aload_1 (0, 1)
	36 invokevirtual (0, 1)
	39 aload_0 (0, 1)
	40 getfield (0, 1)
	43 if_icmplt (0, 1)
	46 aload_1 (0, 1)
	47 iconst_m1 (0, 1)
	48 invokevirtual (0, 1)
	51 return (0, 0)

Method: hasNext
	0 aload_0 (0, 0)
	1 getfield (0, 0)
	4 invokevirtual (0, 0)
	7 iflt (0, 0)
	10 iconst_1 (0, 0)
	11 goto (0, 0)
	14 iconst_0 (0, 0)
	15 ireturn (0, 0)

Method: next
	0 aload_0 (0, 0)
	1 invokevirtual (0, 0)
	4 areturn (0, 0)

Method: remove
	0 new (0, 0)
	3 dup (0, 0)
	4 invokespecial (0, 0)
	7 athrow (0, 0)

