Method: <init>
	0 aload_0 (0, 0)
	1 aload_1 (0, 0)
	2 putfield (0, 0)
	3 org/apache/commons/math3/linear/RealVector$2$2.this$0:Lorg/apache/commons/math3/linear/RealVector$2; (0, 0)
	5 aload_0 (0, 0)
	6 aload_2 (0, 0)
	7 putfield (0, 0)
	8 org/apache/commons/math3/linear/RealVector$2$2.val$i:Ljava/util/Iterator; (0, 0)
	10 aload_0 (0, 0)
	11 invokespecial (0, 0)
	12 java/lang/Object.<init>:()V (0, 0)
	14 aload_0 (1, 1)
	15 new (1, 1)
	16 org/apache/commons/math3/linear/RealVector$2$UnmodifiableEntry (1, 1)
	18 dup (1, 1)
	19 aload_0 (1, 1)
	20 getfield (1, 1)
	21 org/apache/commons/math3/linear/RealVector$2$2.this$0:Lorg/apache/commons/math3/linear/RealVector$2; (1, 1)
	23 invokespecial (1, 1)
	24 org/apache/commons/math3/linear/RealVector$2$UnmodifiableEntry.<init>:(Lorg/apache/commons/math3/linear/RealVector$2;)V (1, 1)
	26 putfield (1, 1)
	27 org/apache/commons/math3/linear/RealVector$2$2.e:Lorg/apache/commons/math3/linear/RealVector$2$UnmodifiableEntry; (1, 1)
	29 return (1, 1)

Method: hasNext
	0 aload_0 (0, 0)
	1 getfield (0, 0)
	2 org/apache/commons/math3/linear/RealVector$2$2.val$i:Ljava/util/Iterator; (0, 0)
	4 invokeinterface (0, 0)
	5 java/util/Iterator.next:()Ljava/lang/Object; (0, 0)
	7 0 (0, 0)
	9 ireturn (0, 0)

Method: next
	0 aload_0 (0, 0)
	1 invokevirtual (0, 0)
	2 org/apache/commons/math3/linear/RealVector$2$2.next:()Lorg/apache/commons/math3/linear/RealVector$Entry; (0, 0)
	4 areturn (0, 0)

Method: remove
	0 new (0, 0)
	1 org/apache/commons/math3/exception/MathUnsupportedOperationException (0, 0)
	3 dup (0, 0)
	4 invokespecial (0, 0)
	5 org/apache/commons/math3/exception/MathUnsupportedOperationException.<init>:()V (0, 0)
	7 athrow (0, 0)

