Method: addToEntry
	0 aload_0 (0, 0)
	1 iload_1 (0, 0)
	2 aload_0 (0, 0)
	3 iload_1 (0, 0)
	4 invokevirtual (0, 0)
	5 org/apache/commons/math3/linear/RealVector.getEntry:(I)D (0, 0)
	7 dload_2 (0, 0)
	8 dadd (0, 0)
	9 invokevirtual (0, 0)
	10 org/apache/commons/math3/linear/RealVector.setEntry:(ID)V (0, 0)
	12 return (0, 0)

Method: checkVectorDimensions
	0 aload_0 (0, 0)
	1 invokevirtual (0, 0)
	2 org/apache/commons/math3/linear/RealVector.getDimension:()I (0, 0)
	4 istore_2 (0, 0)
	5 iload_2 (1, 1)
	6 iload_1 (1, 1)
	7 if_icmpeq (1, 1)
	8 13 (1, 1)
	10 new (1, 1)
	11 org/apache/commons/math3/exception/DimensionMismatchException (1, 1)
	13 dup (1, 1)
	14 iload_2 (1, 1)
	15 iload_1 (1, 1)
	16 invokespecial (1, 1)
	17 org/apache/commons/math3/exception/DimensionMismatchException.<init>:(II)V (1, 1)
	19 athrow (1, 1)
	20 return (0, 0)

Method: checkIndex
	0 iload_1 (1, 1)
	1 iflt (1, 1)
	2 11 (1, 1)
	4 iload_1 (1, 1)
	5 aload_0 (1, 1)
	6 invokevirtual (1, 1)
	7 org/apache/commons/math3/linear/RealVector.getDimension:()I (1, 1)
	9 if_icmplt (1, 1)
	10 31 (1, 1)
	12 new (1, 1)
	13 org/apache/commons/math3/exception/OutOfRangeException (1, 1)
	15 dup (1, 1)
	16 getstatic (1, 1)
	17 org/apache/commons/math3/exception/util/LocalizedFormats.INDEX:Lorg/apache/commons/math3/exception/util/LocalizedFormats; (1, 1)
	19 iload_1 (1, 1)
	20 invokestatic (1, 1)
	21 java/lang/Integer.valueOf:(I)Ljava/lang/Integer; (1, 1)
	23 iconst_0 (1, 1)
	24 invokestatic (1, 1)
	25 java/lang/Integer.valueOf:(I)Ljava/lang/Integer; (1, 1)
	27 aload_0 (1, 1)
	28 invokevirtual (1, 1)
	29 org/apache/commons/math3/linear/RealVector.getDimension:()I (1, 1)
	31 iconst_1 (1, 1)
	32 isub (1, 1)
	33 invokestatic (1, 1)
	34 java/lang/Integer.valueOf:(I)Ljava/lang/Integer; (1, 1)
	36 invokespecial (1, 1)
	37 org/apache/commons/math3/exception/OutOfRangeException.<init>:(Lorg/apache/commons/math3/exception/util/Localizable;Ljava/lang/Number;Ljava/lang/Number;Ljava/lang/Number;)V (1, 1)
	39 athrow (1, 1)
	40 return (0, 1)

Method: checkIndices
	0 aload_0 (0, 0)
	1 invokevirtual (0, 0)
	2 org/apache/commons/math3/linear/RealVector.getDimension:()I (0, 0)
	4 istore_3 (0, 0)
	5 iload_1 (1, 1)
	6 iflt (1, 1)
	7 8 (1, 1)
	9 iload_1 (1, 1)
	10 iload_3 (1, 1)
	11 if_icmplt (1, 1)
	12 28 (1, 1)
	14 new (1, 1)
	15 org/apache/commons/math3/exception/OutOfRangeException (1, 1)
	17 dup (1, 1)
	18 getstatic (1, 1)
	19 org/apache/commons/math3/exception/util/LocalizedFormats.INDEX:Lorg/apache/commons/math3/exception/util/LocalizedFormats; (1, 1)
	21 iload_1 (1, 1)
	22 invokestatic (1, 1)
	23 java/lang/Integer.valueOf:(I)Ljava/lang/Integer; (1, 1)
	25 iconst_0 (1, 1)
	26 invokestatic (1, 1)
	27 java/lang/Integer.valueOf:(I)Ljava/lang/Integer; (1, 1)
	29 iload_3 (1, 1)
	30 iconst_1 (1, 1)
	31 isub (1, 1)
	32 invokestatic (1, 1)
	33 java/lang/Integer.valueOf:(I)Ljava/lang/Integer; (1, 1)
	35 invokespecial (1, 1)
	36 org/apache/commons/math3/exception/OutOfRangeException.<init>:(Lorg/apache/commons/math3/exception/util/Localizable;Ljava/lang/Number;Ljava/lang/Number;Ljava/lang/Number;)V (1, 1)
	38 athrow (1, 1)
	39 iload_2 (1, 1)
	40 iflt (1, 1)
	41 8 (1, 1)
	43 iload_2 (1, 1)
	44 iload_3 (1, 1)
	45 if_icmplt (1, 1)
	46 28 (1, 1)
	48 new (1, 1)
	49 org/apache/commons/math3/exception/OutOfRangeException (1, 1)
	51 dup (1, 1)
	52 getstatic (1, 1)
	53 org/apache/commons/math3/exception/util/LocalizedFormats.INDEX:Lorg/apache/commons/math3/exception/util/LocalizedFormats; (1, 1)
	55 iload_2 (1, 1)
	56 invokestatic (1, 1)
	57 java/lang/Integer.valueOf:(I)Ljava/lang/Integer; (1, 1)
	59 iconst_0 (1, 1)
	60 invokestatic (1, 1)
	61 java/lang/Integer.valueOf:(I)Ljava/lang/Integer; (1, 1)
	63 iload_3 (1, 1)
	64 iconst_1 (1, 1)
	65 isub (1, 1)
	66 invokestatic (1, 1)
	67 java/lang/Integer.valueOf:(I)Ljava/lang/Integer; (1, 1)
	69 invokespecial (1, 1)
	70 org/apache/commons/math3/exception/OutOfRangeException.<init>:(Lorg/apache/commons/math3/exception/util/Localizable;Ljava/lang/Number;Ljava/lang/Number;Ljava/lang/Number;)V (1, 1)
	72 athrow (1, 1)
	73 iload_2 (1, 1)
	74 iload_1 (1, 1)
	75 if_icmpge (1, 1)
	76 23 (1, 1)
	78 new (2, 1)
	79 org/apache/commons/math3/exception/NumberIsTooSmallException (2, 1)
	81 dup (2, 1)
	82 getstatic (2, 1)
	83 org/apache/commons/math3/exception/util/LocalizedFormats.INITIAL_ROW_AFTER_FINAL_ROW:Lorg/apache/commons/math3/exception/util/LocalizedFormats; (2, 1)
	85 iload_2 (2, 1)
	86 invokestatic (2, 1)
	87 java/lang/Integer.valueOf:(I)Ljava/lang/Integer; (2, 1)
	89 iload_1 (2, 1)
	90 invokestatic (2, 1)
	91 java/lang/Integer.valueOf:(I)Ljava/lang/Integer; (2, 1)
	93 iconst_0 (2, 1)
	94 invokespecial (2, 1)
	95 org/apache/commons/math3/exception/NumberIsTooSmallException.<init>:(Lorg/apache/commons/math3/exception/util/Localizable;Ljava/lang/Number;Ljava/lang/Number;Z)V (2, 1)
	97 athrow (2, 1)
	98 return (0, 0)

Method: add
	0 aload_0 (0, 0)
	1 aload_1 (0, 0)
	2 invokevirtual (0, 0)
	3 org/apache/commons/math3/linear/RealVector.checkVectorDimensions:(Lorg/apache/commons/math3/linear/RealVector;)V (0, 0)
	5 aload_1 (0, 0)
	6 invokevirtual (0, 0)
	7 org/apache/commons/math3/linear/RealVector.copy:()Lorg/apache/commons/math3/linear/RealVector; (0, 0)
	9 astore_2 (0, 0)
	10 aload_0 (0, 0)
	11 invokevirtual (0, 0)
	12 org/apache/commons/math3/linear/RealVector.iterator:()Ljava/util/Iterator; (0, 0)
	14 astore_3 (0, 0)
	15 aload_3 (1, 3)
	16 invokeinterface (1, 3)
	17 java/util/Iterator.next:()Ljava/lang/Object; (1, 3)
	19 0 (1, 3)
	21 ifeq (1, 3)
	22 42 (1, 3)
	24 aload_3 (1, 3)
	25 invokeinterface (1, 3)
	26 java/util/Iterator.org/apache/commons/math3/linear/RealVector$Entry (1, 3)
	28 0 (1, 3)
	30 checkcast (1, 3)
	31 org/apache/commons/math3/linear/RealVector$Entry (1, 3)
	33 astore (1, 3)
	34 #4 (1, 3)
	35 aload (1, 3)
	36 #4 (1, 3)
	37 invokevirtual (1, 3)
	38 org/apache/commons/math3/linear/RealVector$Entry.getIndex:()I (1, 3)
	40 istore (1, 3)
	41 #5 (1, 3)
	42 aload_2 (1, 3)
	43 iload (1, 3)
	44 #5 (1, 3)
	45 aload (1, 3)
	46 #4 (1, 3)
	47 invokevirtual (1, 3)
	48 org/apache/commons/math3/linear/RealVector$Entry.getValue:()D (1, 3)
	50 aload_2 (1, 3)
	51 iload (1, 3)
	52 #5 (1, 3)
	53 invokevirtual (1, 3)
	54 org/apache/commons/math3/linear/RealVector.getEntry:(I)D (1, 3)
	56 dadd (1, 3)
	57 invokevirtual (1, 3)
	58 org/apache/commons/math3/linear/RealVector.setEntry:(ID)V (1, 3)
	60 goto (0, 0)
	61 -45 (0, 0)
	63 aload_2 (0, 0)
	64 areturn (0, 0)

Method: subtract
	0 aload_0 (0, 0)
	1 aload_1 (0, 0)
	2 invokevirtual (0, 0)
	3 org/apache/commons/math3/linear/RealVector.checkVectorDimensions:(Lorg/apache/commons/math3/linear/RealVector;)V (0, 0)
	5 aload_1 (0, 0)
	6 ldc2_w (0, 0)
	7 -1.0 (0, 0)
	9 invokevirtual (0, 0)
	10 org/apache/commons/math3/linear/RealVector.mapMultiply:(D)Lorg/apache/commons/math3/linear/RealVector; (0, 0)
	12 astore_2 (0, 0)
	13 aload_0 (0, 0)
	14 invokevirtual (0, 0)
	15 org/apache/commons/math3/linear/RealVector.iterator:()Ljava/util/Iterator; (0, 0)
	17 astore_3 (0, 0)
	18 aload_3 (1, 3)
	19 invokeinterface (1, 3)
	20 java/util/Iterator.next:()Ljava/lang/Object; (1, 3)
	22 0 (1, 3)
	24 ifeq (1, 3)
	25 42 (1, 3)
	27 aload_3 (1, 3)
	28 invokeinterface (1, 3)
	29 java/util/Iterator.org/apache/commons/math3/linear/RealVector$Entry (1, 3)
	31 0 (1, 3)
	33 checkcast (1, 3)
	34 org/apache/commons/math3/linear/RealVector$Entry (1, 3)
	36 astore (1, 3)
	37 #4 (1, 3)
	38 aload (1, 3)
	39 #4 (1, 3)
	40 invokevirtual (1, 3)
	41 org/apache/commons/math3/linear/RealVector$Entry.getIndex:()I (1, 3)
	43 istore (1, 3)
	44 #5 (1, 3)
	45 aload_2 (1, 3)
	46 iload (1, 3)
	47 #5 (1, 3)
	48 aload (1, 3)
	49 #4 (1, 3)
	50 invokevirtual (1, 3)
	51 org/apache/commons/math3/linear/RealVector$Entry.getValue:()D (1, 3)
	53 aload_2 (1, 3)
	54 iload (1, 3)
	55 #5 (1, 3)
	56 invokevirtual (1, 3)
	57 org/apache/commons/math3/linear/RealVector.getEntry:(I)D (1, 3)
	59 dadd (1, 3)
	60 invokevirtual (1, 3)
	61 org/apache/commons/math3/linear/RealVector.setEntry:(ID)V (1, 3)
	63 goto (0, 0)
	64 -45 (0, 0)
	66 aload_2 (0, 0)
	67 areturn (0, 0)

Method: mapAdd
	0 aload_0 (0, 0)
	1 invokevirtual (0, 0)
	2 org/apache/commons/math3/linear/RealVector.copy:()Lorg/apache/commons/math3/linear/RealVector; (0, 0)
	4 dload_1 (0, 0)
	5 invokevirtual (0, 0)
	6 org/apache/commons/math3/linear/RealVector.mapAddToSelf:(D)Lorg/apache/commons/math3/linear/RealVector; (0, 0)
	8 areturn (0, 0)

Method: mapAddToSelf
	0 dload_1 (1, 1)
	1 dconst_0 (1, 1)
	2 dcmpl (1, 1)
	3 ifeq (1, 1)
	4 19 (1, 1)
	6 aload_0 (1, 1)
	7 new (1, 1)
	8 org/apache/commons/math3/analysis/function/Add (1, 1)
	10 dup (1, 1)
	11 invokespecial (1, 1)
	12 org/apache/commons/math3/analysis/function/Add.<init>:()V (1, 1)
	14 dload_1 (1, 1)
	15 invokestatic (1, 1)
	16 org/apache/commons/math3/analysis/FunctionUtils.fix2ndArgument:(Lorg/apache/commons/math3/analysis/BivariateFunction;D)Lorg/apache/commons/math3/analysis/UnivariateFunction; (1, 1)
	18 invokevirtual (1, 1)
	19 org/apache/commons/math3/linear/RealVector.mapToSelf:(Lorg/apache/commons/math3/analysis/UnivariateFunction;)Lorg/apache/commons/math3/linear/RealVector; (1, 1)
	21 areturn (1, 1)
	22 aload_0 (0, 0)
	23 areturn (0, 0)

Method: dotProduct
	0 aload_0 (0, 0)
	1 aload_1 (0, 0)
	2 invokevirtual (0, 0)
	3 org/apache/commons/math3/linear/RealVector.checkVectorDimensions:(Lorg/apache/commons/math3/linear/RealVector;)V (0, 0)
	5 dconst_0 (0, 0)
	6 dstore_2 (0, 0)
	7 aload_0 (0, 0)
	8 invokevirtual (0, 0)
	9 org/apache/commons/math3/linear/RealVector.getDimension:()I (0, 0)
	11 istore (0, 0)
	12 #4 (0, 0)
	13 iconst_0 (1, 4)
	14 istore (1, 4)
	15 #5 (1, 4)
	16 iload (1, 4)
	17 #5 (1, 4)
	18 iload (1, 4)
	19 #4 (1, 4)
	20 if_icmpge (1, 4)
	21 25 (1, 4)
	23 dload_2 (1, 4)
	24 aload_0 (1, 4)
	25 iload (1, 4)
	26 #5 (1, 4)
	27 invokevirtual (1, 4)
	28 org/apache/commons/math3/linear/RealVector.getEntry:(I)D (1, 4)
	30 aload_1 (1, 4)
	31 iload (1, 4)
	32 #5 (1, 4)
	33 invokevirtual (1, 4)
	34 org/apache/commons/math3/linear/RealVector.getEntry:(I)D (1, 4)
	36 dmul (1, 4)
	37 dadd (1, 4)
	38 dstore_2 (1, 4)
	39 iinc (1, 4)
	40 #5 (1, 4)
	41 -89 (1, 4)
	42 goto (1, 4)
	43 -26 (1, 4)
	45 dload_2 (0, 0)
	46 dreturn (0, 0)

Method: cosine
	0 aload_0 (0, 0)
	1 invokevirtual (0, 0)
	2 org/apache/commons/math3/linear/RealVector.getNorm:()D (0, 0)
	4 dstore_2 (0, 0)
	5 aload_1 (0, 0)
	6 invokevirtual (0, 0)
	7 org/apache/commons/math3/linear/RealVector.getNorm:()D (0, 0)
	9 dstore (0, 0)
	10 #4 (0, 0)
	11 dload_2 (1, 1)
	12 dconst_0 (1, 1)
	13 dcmpl (1, 1)
	14 ifeq (1, 1)
	15 10 (1, 1)
	17 dload (1, 1)
	18 #4 (1, 1)
	19 dconst_0 (1, 1)
	20 dcmpl (1, 1)
	21 ifne (1, 1)
	22 18 (1, 1)
	24 new (1, 1)
	25 org/apache/commons/math3/exception/MathArithmeticException (1, 1)
	27 dup (1, 1)
	28 getstatic (1, 1)
	29 org/apache/commons/math3/exception/util/LocalizedFormats.ZERO_NORM:Lorg/apache/commons/math3/exception/util/LocalizedFormats; (1, 1)
	31 iconst_0 (1, 1)
	32 anewarray (1, 1)
	33 java/lang/Object (1, 1)
	35 invokespecial (1, 1)
	36 org/apache/commons/math3/exception/MathArithmeticException.<init>:(Lorg/apache/commons/math3/exception/util/Localizable;[Ljava/lang/Object;)V (1, 1)
	38 athrow (1, 1)
	39 aload_0 (1, 1)
	40 aload_1 (1, 1)
	41 invokevirtual (1, 1)
	42 org/apache/commons/math3/linear/RealVector.dotProduct:(Lorg/apache/commons/math3/linear/RealVector;)D (1, 1)
	44 dload_2 (1, 1)
	45 dload (1, 1)
	46 #4 (1, 1)
	47 dmul (1, 1)
	48 ddiv (1, 1)
	49 dreturn (0, 1)

Method: getDistance
	0 aload_0 (0, 0)
	1 aload_1 (0, 0)
	2 invokevirtual (0, 0)
	3 org/apache/commons/math3/linear/RealVector.checkVectorDimensions:(Lorg/apache/commons/math3/linear/RealVector;)V (0, 0)
	5 dconst_0 (0, 0)
	6 dstore_2 (0, 0)
	7 aload_0 (0, 0)
	8 invokevirtual (0, 0)
	9 org/apache/commons/math3/linear/RealVector.iterator:()Ljava/util/Iterator; (0, 0)
	11 astore (0, 0)
	12 #4 (0, 0)
	13 aload (1, 3)
	14 #4 (1, 3)
	15 invokeinterface (1, 3)
	16 java/util/Iterator.next:()Ljava/lang/Object; (1, 3)
	18 0 (1, 3)
	20 ifeq (1, 3)
	21 43 (1, 3)
	23 aload (1, 3)
	24 #4 (1, 3)
	25 invokeinterface (1, 3)
	26 java/util/Iterator.org/apache/commons/math3/linear/RealVector$Entry (1, 3)
	28 0 (1, 3)
	30 checkcast (1, 3)
	31 org/apache/commons/math3/linear/RealVector$Entry (1, 3)
	33 astore (1, 3)
	34 #5 (1, 3)
	35 aload (2, 1)
	36 #5 (2, 1)
	37 invokevirtual (2, 1)
	38 org/apache/commons/math3/linear/RealVector$Entry.getValue:()D (2, 1)
	40 aload_1 (2, 1)
	41 aload (2, 1)
	42 #5 (2, 1)
	43 invokevirtual (2, 1)
	44 org/apache/commons/math3/linear/RealVector$Entry.getIndex:()I (2, 1)
	46 invokevirtual (2, 1)
	47 org/apache/commons/math3/linear/RealVector.getEntry:(I)D (2, 1)
	49 dsub (2, 1)
	50 dstore (2, 1)
	51 #6 (2, 1)
	52 dload_2 (3, 1)
	53 dload (3, 1)
	54 #6 (3, 1)
	55 dload (3, 1)
	56 #6 (3, 1)
	57 dmul (3, 1)
	58 dadd (3, 1)
	59 dstore_2 (3, 1)
	60 goto (0, 0)
	61 -47 (0, 0)
	63 dload_2 (0, 0)
	64 invokestatic (0, 0)
	65 org/apache/commons/math3/util/FastMath.sqrt:(D)D (0, 0)
	67 dreturn (0, 0)

Method: getNorm
	0 dconst_0 (0, 0)
	1 dstore_1 (0, 0)
	2 aload_0 (0, 0)
	3 invokevirtual (0, 0)
	4 org/apache/commons/math3/linear/RealVector.iterator:()Ljava/util/Iterator; (0, 0)
	6 astore_3 (0, 0)
	7 aload_3 (1, 3)
	8 invokeinterface (1, 3)
	9 java/util/Iterator.next:()Ljava/lang/Object; (1, 3)
	11 0 (1, 3)
	13 ifeq (1, 3)
	14 32 (1, 3)
	16 aload_3 (1, 3)
	17 invokeinterface (1, 3)
	18 java/util/Iterator.org/apache/commons/math3/linear/RealVector$Entry (1, 3)
	20 0 (1, 3)
	22 checkcast (1, 3)
	23 org/apache/commons/math3/linear/RealVector$Entry (1, 3)
	25 astore (1, 3)
	26 #4 (1, 3)
	27 aload (1, 3)
	28 #4 (1, 3)
	29 invokevirtual (1, 3)
	30 org/apache/commons/math3/linear/RealVector$Entry.getValue:()D (1, 3)
	32 dstore (1, 3)
	33 #5 (1, 3)
	34 dload_1 (1, 3)
	35 dload (1, 3)
	36 #5 (1, 3)
	37 dload (1, 3)
	38 #5 (1, 3)
	39 dmul (1, 3)
	40 dadd (1, 3)
	41 dstore_1 (1, 3)
	42 goto (0, 0)
	43 -35 (0, 0)
	45 dload_1 (0, 0)
	46 invokestatic (0, 0)
	47 org/apache/commons/math3/util/FastMath.sqrt:(D)D (0, 0)
	49 dreturn (0, 0)

Method: getL1Norm
	0 dconst_0 (0, 0)
	1 dstore_1 (0, 0)
	2 aload_0 (0, 0)
	3 invokevirtual (0, 0)
	4 org/apache/commons/math3/linear/RealVector.iterator:()Ljava/util/Iterator; (0, 0)
	6 astore_3 (0, 0)
	7 aload_3 (1, 3)
	8 invokeinterface (1, 3)
	9 java/util/Iterator.next:()Ljava/lang/Object; (1, 3)
	11 0 (1, 3)
	13 ifeq (1, 3)
	14 28 (1, 3)
	16 aload_3 (1, 3)
	17 invokeinterface (1, 3)
	18 java/util/Iterator.org/apache/commons/math3/linear/RealVector$Entry (1, 3)
	20 0 (1, 3)
	22 checkcast (1, 3)
	23 org/apache/commons/math3/linear/RealVector$Entry (1, 3)
	25 astore (1, 3)
	26 #4 (1, 3)
	27 dload_1 (1, 3)
	28 aload (1, 3)
	29 #4 (1, 3)
	30 invokevirtual (1, 3)
	31 org/apache/commons/math3/linear/RealVector$Entry.getValue:()D (1, 3)
	33 invokestatic (1, 3)
	34 org/apache/commons/math3/util/FastMath.abs:(D)D (1, 3)
	36 dadd (1, 3)
	37 dstore_1 (1, 3)
	38 goto (0, 0)
	39 -31 (0, 0)
	41 dload_1 (0, 0)
	42 dreturn (0, 0)

Method: getLInfNorm
	0 dconst_0 (0, 0)
	1 dstore_1 (0, 0)
	2 aload_0 (0, 0)
	3 invokevirtual (0, 0)
	4 org/apache/commons/math3/linear/RealVector.iterator:()Ljava/util/Iterator; (0, 0)
	6 astore_3 (0, 0)
	7 aload_3 (1, 3)
	8 invokeinterface (1, 3)
	9 java/util/Iterator.next:()Ljava/lang/Object; (1, 3)
	11 0 (1, 3)
	13 ifeq (1, 3)
	14 30 (1, 3)
	16 aload_3 (1, 3)
	17 invokeinterface (1, 3)
	18 java/util/Iterator.org/apache/commons/math3/linear/RealVector$Entry (1, 3)
	20 0 (1, 3)
	22 checkcast (1, 3)
	23 org/apache/commons/math3/linear/RealVector$Entry (1, 3)
	25 astore (1, 3)
	26 #4 (1, 3)
	27 dload_1 (1, 3)
	28 aload (1, 3)
	29 #4 (1, 3)
	30 invokevirtual (1, 3)
	31 org/apache/commons/math3/linear/RealVector$Entry.getValue:()D (1, 3)
	33 invokestatic (1, 3)
	34 org/apache/commons/math3/util/FastMath.abs:(D)D (1, 3)
	36 invokestatic (1, 3)
	37 org/apache/commons/math3/util/FastMath.max:(DD)D (1, 3)
	39 dstore_1 (1, 3)
	40 goto (0, 0)
	41 -33 (0, 0)
	43 dload_1 (0, 0)
	44 dreturn (0, 0)

Method: getL1Distance
	0 aload_0 (0, 0)
	1 aload_1 (0, 0)
	2 invokevirtual (0, 0)
	3 org/apache/commons/math3/linear/RealVector.checkVectorDimensions:(Lorg/apache/commons/math3/linear/RealVector;)V (0, 0)
	5 dconst_0 (0, 0)
	6 dstore_2 (0, 0)
	7 aload_0 (0, 0)
	8 invokevirtual (0, 0)
	9 org/apache/commons/math3/linear/RealVector.iterator:()Ljava/util/Iterator; (0, 0)
	11 astore (0, 0)
	12 #4 (0, 0)
	13 aload (1, 3)
	14 #4 (1, 3)
	15 invokeinterface (1, 3)
	16 java/util/Iterator.next:()Ljava/lang/Object; (1, 3)
	18 0 (1, 3)
	20 ifeq (1, 3)
	21 39 (1, 3)
	23 aload (1, 3)
	24 #4 (1, 3)
	25 invokeinterface (1, 3)
	26 java/util/Iterator.org/apache/commons/math3/linear/RealVector$Entry (1, 3)
	28 0 (1, 3)
	30 checkcast (1, 3)
	31 org/apache/commons/math3/linear/RealVector$Entry (1, 3)
	33 astore (1, 3)
	34 #5 (1, 3)
	35 dload_2 (1, 3)
	36 aload (1, 3)
	37 #5 (1, 3)
	38 invokevirtual (1, 3)
	39 org/apache/commons/math3/linear/RealVector$Entry.getValue:()D (1, 3)
	41 aload_1 (1, 3)
	42 aload (1, 3)
	43 #5 (1, 3)
	44 invokevirtual (1, 3)
	45 org/apache/commons/math3/linear/RealVector$Entry.getIndex:()I (1, 3)
	47 invokevirtual (1, 3)
	48 org/apache/commons/math3/linear/RealVector.getEntry:(I)D (1, 3)
	50 dsub (1, 3)
	51 invokestatic (1, 3)
	52 org/apache/commons/math3/util/FastMath.abs:(D)D (1, 3)
	54 dadd (1, 3)
	55 dstore_2 (1, 3)
	56 goto (0, 0)
	57 -43 (0, 0)
	59 dload_2 (0, 0)
	60 dreturn (0, 0)

Method: getLInfDistance
	0 aload_0 (0, 0)
	1 aload_1 (0, 0)
	2 invokevirtual (0, 0)
	3 org/apache/commons/math3/linear/RealVector.checkVectorDimensions:(Lorg/apache/commons/math3/linear/RealVector;)V (0, 0)
	5 dconst_0 (0, 0)
	6 dstore_2 (0, 0)
	7 aload_0 (0, 0)
	8 invokevirtual (0, 0)
	9 org/apache/commons/math3/linear/RealVector.iterator:()Ljava/util/Iterator; (0, 0)
	11 astore (0, 0)
	12 #4 (0, 0)
	13 aload (1, 3)
	14 #4 (1, 3)
	15 invokeinterface (1, 3)
	16 java/util/Iterator.next:()Ljava/lang/Object; (1, 3)
	18 0 (1, 3)
	20 ifeq (1, 3)
	21 41 (1, 3)
	23 aload (1, 3)
	24 #4 (1, 3)
	25 invokeinterface (1, 3)
	26 java/util/Iterator.org/apache/commons/math3/linear/RealVector$Entry (1, 3)
	28 0 (1, 3)
	30 checkcast (1, 3)
	31 org/apache/commons/math3/linear/RealVector$Entry (1, 3)
	33 astore (1, 3)
	34 #5 (1, 3)
	35 aload (1, 3)
	36 #5 (1, 3)
	37 invokevirtual (1, 3)
	38 org/apache/commons/math3/linear/RealVector$Entry.getValue:()D (1, 3)
	40 aload_1 (1, 3)
	41 aload (1, 3)
	42 #5 (1, 3)
	43 invokevirtual (1, 3)
	44 org/apache/commons/math3/linear/RealVector$Entry.getIndex:()I (1, 3)
	46 invokevirtual (1, 3)
	47 org/apache/commons/math3/linear/RealVector.getEntry:(I)D (1, 3)
	49 dsub (1, 3)
	50 invokestatic (1, 3)
	51 org/apache/commons/math3/util/FastMath.abs:(D)D (1, 3)
	53 dload_2 (1, 3)
	54 invokestatic (1, 3)
	55 org/apache/commons/math3/util/FastMath.max:(DD)D (1, 3)
	57 dstore_2 (1, 3)
	58 goto (0, 0)
	59 -45 (0, 0)
	61 dload_2 (0, 0)
	62 dreturn (0, 0)

Method: getMinIndex
	0 iconst_m1 (0, 0)
	1 istore_1 (0, 0)
	2 ldc2_w (0, 0)
	3 inf (0, 0)
	5 dstore_2 (0, 0)
	6 aload_0 (0, 0)
	7 invokevirtual (0, 0)
	8 org/apache/commons/math3/linear/RealVector.iterator:()Ljava/util/Iterator; (0, 0)
	10 astore (0, 0)
	11 #4 (0, 0)
	12 aload (1, 3)
	13 #4 (1, 3)
	14 invokeinterface (1, 3)
	15 java/util/Iterator.next:()Ljava/lang/Object; (1, 3)
	17 0 (1, 3)
	19 ifeq (1, 3)
	20 40 (1, 3)
	22 aload (1, 3)
	23 #4 (1, 3)
	24 invokeinterface (1, 3)
	25 java/util/Iterator.org/apache/commons/math3/linear/RealVector$Entry (1, 3)
	27 0 (1, 3)
	29 checkcast (1, 3)
	30 org/apache/commons/math3/linear/RealVector$Entry (1, 3)
	32 astore (1, 3)
	33 #5 (1, 3)
	34 aload (2, 1)
	35 #5 (2, 1)
	36 invokevirtual (2, 1)
	37 org/apache/commons/math3/linear/RealVector$Entry.getValue:()D (2, 1)
	39 dload_2 (2, 1)
	40 dcmpg (2, 1)
	41 ifgt (2, 1)
	42 15 (2, 1)
	44 aload (2, 1)
	45 #5 (2, 1)
	46 invokevirtual (2, 1)
	47 org/apache/commons/math3/linear/RealVector$Entry.getIndex:()I (2, 1)
	49 istore_1 (2, 1)
	50 aload (2, 1)
	51 #5 (2, 1)
	52 invokevirtual (2, 1)
	53 org/apache/commons/math3/linear/RealVector$Entry.getValue:()D (2, 1)
	55 dstore_2 (2, 1)
	56 goto (0, 0)
	57 -44 (0, 0)
	59 iload_1 (0, 0)
	60 ireturn (0, 0)

Method: getMinValue
	0 aload_0 (0, 0)
	1 invokevirtual (0, 0)
	2 org/apache/commons/math3/linear/RealVector.getMinIndex:()I (0, 0)
	4 istore_1 (0, 0)
	5 iload_1 (0, 0)
	6 ifge (0, 0)
	7 9 (0, 0)
	9 ldc2_w (0, 0)
	10 nan (0, 0)
	12 goto (0, 0)
	13 8 (0, 0)
	15 aload_0 (0, 0)
	16 iload_1 (0, 0)
	17 invokevirtual (0, 0)
	18 org/apache/commons/math3/linear/RealVector.getEntry:(I)D (0, 0)
	20 dreturn (0, 0)

Method: getMaxIndex
	0 iconst_m1 (0, 0)
	1 istore_1 (0, 0)
	2 ldc2_w (0, 0)
	3 -inf (0, 0)
	5 dstore_2 (0, 0)
	6 aload_0 (0, 0)
	7 invokevirtual (0, 0)
	8 org/apache/commons/math3/linear/RealVector.iterator:()Ljava/util/Iterator; (0, 0)
	10 astore (0, 0)
	11 #4 (0, 0)
	12 aload (1, 3)
	13 #4 (1, 3)
	14 invokeinterface (1, 3)
	15 java/util/Iterator.next:()Ljava/lang/Object; (1, 3)
	17 0 (1, 3)
	19 ifeq (1, 3)
	20 40 (1, 3)
	22 aload (1, 3)
	23 #4 (1, 3)
	24 invokeinterface (1, 3)
	25 java/util/Iterator.org/apache/commons/math3/linear/RealVector$Entry (1, 3)
	27 0 (1, 3)
	29 checkcast (1, 3)
	30 org/apache/commons/math3/linear/RealVector$Entry (1, 3)
	32 astore (1, 3)
	33 #5 (1, 3)
	34 aload (2, 1)
	35 #5 (2, 1)
	36 invokevirtual (2, 1)
	37 org/apache/commons/math3/linear/RealVector$Entry.getValue:()D (2, 1)
	39 dload_2 (2, 1)
	40 dcmpl (2, 1)
	41 iflt (2, 1)
	42 15 (2, 1)
	44 aload (2, 1)
	45 #5 (2, 1)
	46 invokevirtual (2, 1)
	47 org/apache/commons/math3/linear/RealVector$Entry.getIndex:()I (2, 1)
	49 istore_1 (2, 1)
	50 aload (2, 1)
	51 #5 (2, 1)
	52 invokevirtual (2, 1)
	53 org/apache/commons/math3/linear/RealVector$Entry.getValue:()D (2, 1)
	55 dstore_2 (2, 1)
	56 goto (0, 0)
	57 -44 (0, 0)
	59 iload_1 (0, 0)
	60 ireturn (0, 0)

Method: getMaxValue
	0 aload_0 (0, 0)
	1 invokevirtual (0, 0)
	2 org/apache/commons/math3/linear/RealVector.getMaxIndex:()I (0, 0)
	4 istore_1 (0, 0)
	5 iload_1 (0, 0)
	6 ifge (0, 0)
	7 9 (0, 0)
	9 ldc2_w (0, 0)
	10 nan (0, 0)
	12 goto (0, 0)
	13 8 (0, 0)
	15 aload_0 (0, 0)
	16 iload_1 (0, 0)
	17 invokevirtual (0, 0)
	18 org/apache/commons/math3/linear/RealVector.getEntry:(I)D (0, 0)
	20 dreturn (0, 0)

Method: mapMultiply
	0 aload_0 (0, 0)
	1 invokevirtual (0, 0)
	2 org/apache/commons/math3/linear/RealVector.copy:()Lorg/apache/commons/math3/linear/RealVector; (0, 0)
	4 dload_1 (0, 0)
	5 invokevirtual (0, 0)
	6 org/apache/commons/math3/linear/RealVector.mapMultiplyToSelf:(D)Lorg/apache/commons/math3/linear/RealVector; (0, 0)
	8 areturn (0, 0)

Method: mapMultiplyToSelf
	0 aload_0 (0, 0)
	1 new (0, 0)
	2 org/apache/commons/math3/analysis/function/Multiply (0, 0)
	4 dup (0, 0)
	5 invokespecial (0, 0)
	6 org/apache/commons/math3/analysis/function/Multiply.<init>:()V (0, 0)
	8 dload_1 (0, 0)
	9 invokestatic (0, 0)
	10 org/apache/commons/math3/analysis/FunctionUtils.fix2ndArgument:(Lorg/apache/commons/math3/analysis/BivariateFunction;D)Lorg/apache/commons/math3/analysis/UnivariateFunction; (0, 0)
	12 invokevirtual (0, 0)
	13 org/apache/commons/math3/linear/RealVector.mapToSelf:(Lorg/apache/commons/math3/analysis/UnivariateFunction;)Lorg/apache/commons/math3/linear/RealVector; (0, 0)
	15 areturn (0, 0)

Method: mapSubtract
	0 aload_0 (0, 0)
	1 invokevirtual (0, 0)
	2 org/apache/commons/math3/linear/RealVector.copy:()Lorg/apache/commons/math3/linear/RealVector; (0, 0)
	4 dload_1 (0, 0)
	5 invokevirtual (0, 0)
	6 org/apache/commons/math3/linear/RealVector.mapSubtractToSelf:(D)Lorg/apache/commons/math3/linear/RealVector; (0, 0)
	8 areturn (0, 0)

Method: mapSubtractToSelf
	0 aload_0 (0, 0)
	1 dload_1 (0, 0)
	2 dneg (0, 0)
	3 invokevirtual (0, 0)
	4 org/apache/commons/math3/linear/RealVector.mapAddToSelf:(D)Lorg/apache/commons/math3/linear/RealVector; (0, 0)
	6 areturn (0, 0)

Method: mapDivide
	0 aload_0 (0, 0)
	1 invokevirtual (0, 0)
	2 org/apache/commons/math3/linear/RealVector.copy:()Lorg/apache/commons/math3/linear/RealVector; (0, 0)
	4 dload_1 (0, 0)
	5 invokevirtual (0, 0)
	6 org/apache/commons/math3/linear/RealVector.mapDivideToSelf:(D)Lorg/apache/commons/math3/linear/RealVector; (0, 0)
	8 areturn (0, 0)

Method: mapDivideToSelf
	0 aload_0 (0, 0)
	1 new (0, 0)
	2 org/apache/commons/math3/analysis/function/Divide (0, 0)
	4 dup (0, 0)
	5 invokespecial (0, 0)
	6 org/apache/commons/math3/analysis/function/Divide.<init>:()V (0, 0)
	8 dload_1 (0, 0)
	9 invokestatic (0, 0)
	10 org/apache/commons/math3/analysis/FunctionUtils.fix2ndArgument:(Lorg/apache/commons/math3/analysis/BivariateFunction;D)Lorg/apache/commons/math3/analysis/UnivariateFunction; (0, 0)
	12 invokevirtual (0, 0)
	13 org/apache/commons/math3/linear/RealVector.mapToSelf:(Lorg/apache/commons/math3/analysis/UnivariateFunction;)Lorg/apache/commons/math3/linear/RealVector; (0, 0)
	15 areturn (0, 0)

Method: outerProduct
	0 aload_0 (0, 0)
	1 invokevirtual (0, 0)
	2 org/apache/commons/math3/linear/RealVector.getDimension:()I (0, 0)
	4 istore_2 (0, 0)
	5 aload_1 (0, 0)
	6 invokevirtual (0, 0)
	7 org/apache/commons/math3/linear/RealVector.getDimension:()I (0, 0)
	9 istore_3 (0, 0)
	10 aload_1 (1, 1)
	11 instanceof (1, 1)
	12 org/apache/commons/math3/linear/SparseRealVector (1, 1)
	14 ifne (1, 1)
	15 10 (1, 1)
	17 aload_0 (1, 1)
	18 instanceof (1, 1)
	19 org/apache/commons/math3/linear/SparseRealVector (1, 1)
	21 ifeq (1, 1)
	22 17 (1, 1)
	24 new (1, 1)
	25 org/apache/commons/math3/linear/OpenMapRealMatrix (1, 1)
	27 dup (1, 1)
	28 iload_2 (1, 1)
	29 iload_3 (1, 1)
	30 invokespecial (1, 1)
	31 org/apache/commons/math3/linear/OpenMapRealMatrix.<init>:(II)V (1, 1)
	33 astore (1, 1)
	34 #4 (1, 1)
	35 goto (1, 1)
	36 14 (1, 1)
	38 new (2, 2)
	39 org/apache/commons/math3/linear/Array2DRowRealMatrix (2, 2)
	41 dup (2, 2)
	42 iload_2 (2, 2)
	43 iload_3 (2, 2)
	44 invokespecial (2, 2)
	45 org/apache/commons/math3/linear/Array2DRowRealMatrix.<init>:(II)V (2, 2)
	47 astore (2, 2)
	48 #4 (2, 2)
	49 iconst_0 (1, 4)
	50 istore (1, 4)
	51 #5 (1, 4)
	52 iload (1, 4)
	53 #5 (1, 4)
	54 iload_2 (1, 4)
	55 if_icmpge (1, 4)
	56 48 (1, 4)
	58 iconst_0 (2, 4)
	59 istore (2, 4)
	60 #6 (2, 4)
	61 iload (2, 4)
	62 #6 (2, 4)
	63 iload_3 (2, 4)
	64 if_icmpge (2, 4)
	65 33 (2, 4)
	67 aload (2, 4)
	68 #4 (2, 4)
	69 iload (2, 4)
	70 #5 (2, 4)
	71 iload (2, 4)
	72 #6 (2, 4)
	73 aload_0 (2, 4)
	74 iload (2, 4)
	75 #5 (2, 4)
	76 invokevirtual (2, 4)
	77 org/apache/commons/math3/linear/RealVector.getEntry:(I)D (2, 4)
	79 aload_1 (2, 4)
	80 iload (2, 4)
	81 #6 (2, 4)
	82 invokevirtual (2, 4)
	83 org/apache/commons/math3/linear/RealVector.getEntry:(I)D (2, 4)
	85 dmul (2, 4)
	86 invokeinterface (2, 4)
	87 org/apache/commons/math3/linear/RealMatrix.setValue:(D)V (2, 4)
	89 0 (2, 4)
	91 iinc (2, 4)
	92 #6 (2, 4)
	93 -89 (2, 4)
	94 goto (2, 4)
	95 -33 (2, 4)
	97 iinc (2, 4)
	98 #5 (2, 4)
	99 -89 (2, 4)
	100 goto (2, 4)
	101 -48 (2, 4)
	103 aload (1, 4)
	104 #4 (1, 4)
	105 areturn (1, 4)

Method: projection
	0 aload_1 (0, 0)
	1 aload_1 (0, 0)
	2 invokevirtual (0, 0)
	3 org/apache/commons/math3/linear/RealVector.dotProduct:(Lorg/apache/commons/math3/linear/RealVector;)D (0, 0)
	5 dstore_2 (0, 0)
	6 dload_2 (1, 1)
	7 dconst_0 (1, 1)
	8 dcmpl (1, 1)
	9 ifne (1, 1)
	10 18 (1, 1)
	12 new (1, 1)
	13 org/apache/commons/math3/exception/MathArithmeticException (1, 1)
	15 dup (1, 1)
	16 getstatic (1, 1)
	17 org/apache/commons/math3/exception/util/LocalizedFormats.ZERO_NORM:Lorg/apache/commons/math3/exception/util/LocalizedFormats; (1, 1)
	19 iconst_0 (1, 1)
	20 anewarray (1, 1)
	21 java/lang/Object (1, 1)
	23 invokespecial (1, 1)
	24 org/apache/commons/math3/exception/MathArithmeticException.<init>:(Lorg/apache/commons/math3/exception/util/Localizable;[Ljava/lang/Object;)V (1, 1)
	26 athrow (1, 1)
	27 aload_1 (0, 0)
	28 aload_0 (0, 0)
	29 aload_1 (0, 0)
	30 invokevirtual (0, 0)
	31 org/apache/commons/math3/linear/RealVector.dotProduct:(Lorg/apache/commons/math3/linear/RealVector;)D (0, 0)
	33 aload_1 (0, 0)
	34 aload_1 (0, 0)
	35 invokevirtual (0, 0)
	36 org/apache/commons/math3/linear/RealVector.dotProduct:(Lorg/apache/commons/math3/linear/RealVector;)D (0, 0)
	38 ddiv (0, 0)
	39 invokevirtual (0, 0)
	40 org/apache/commons/math3/linear/RealVector.mapMultiply:(D)Lorg/apache/commons/math3/linear/RealVector; (0, 0)
	42 areturn (0, 0)

Method: set
	0 aload_0 (0, 0)
	1 invokevirtual (0, 0)
	2 org/apache/commons/math3/linear/RealVector.iterator:()Ljava/util/Iterator; (0, 0)
	4 astore_3 (0, 0)
	5 aload_3 (1, 3)
	6 invokeinterface (1, 3)
	7 java/util/Iterator.next:()Ljava/lang/Object; (1, 3)
	9 0 (1, 3)
	11 ifeq (1, 3)
	12 23 (1, 3)
	14 aload_3 (1, 3)
	15 invokeinterface (1, 3)
	16 java/util/Iterator.org/apache/commons/math3/linear/RealVector$Entry (1, 3)
	18 0 (1, 3)
	20 checkcast (1, 3)
	21 org/apache/commons/math3/linear/RealVector$Entry (1, 3)
	23 astore (1, 3)
	24 #4 (1, 3)
	25 aload (1, 3)
	26 #4 (1, 3)
	27 dload_1 (1, 3)
	28 invokevirtual (1, 3)
	29 org/apache/commons/math3/linear/RealVector$Entry.setValue:(D)V (1, 3)
	31 goto (0, 0)
	32 -26 (0, 0)
	34 return (0, 0)

Method: toArray
	0 aload_0 (0, 0)
	1 invokevirtual (0, 0)
	2 org/apache/commons/math3/linear/RealVector.getDimension:()I (0, 0)
	4 istore_1 (0, 0)
	5 iload_1 (0, 0)
	6 newarray (0, 0)
	7 7 (0, 0)
	8 astore_2 (0, 0)
	9 iconst_0 (1, 4)
	10 istore_3 (1, 4)
	11 iload_3 (1, 4)
	12 iload_1 (1, 4)
	13 if_icmpge (1, 4)
	14 17 (1, 4)
	16 aload_2 (1, 4)
	17 iload_3 (1, 4)
	18 aload_0 (1, 4)
	19 iload_3 (1, 4)
	20 invokevirtual (1, 4)
	21 org/apache/commons/math3/linear/RealVector.getEntry:(I)D (1, 4)
	23 dastore (1, 4)
	24 iinc (1, 4)
	25 #3 (1, 4)
	26 -89 (1, 4)
	27 goto (1, 4)
	28 -16 (1, 4)
	30 aload_2 (0, 0)
	31 areturn (0, 0)

Method: unitVector
	0 aload_0 (0, 0)
	1 invokevirtual (0, 0)
	2 org/apache/commons/math3/linear/RealVector.getNorm:()D (0, 0)
	4 dstore_1 (0, 0)
	5 dload_1 (1, 1)
	6 dconst_0 (1, 1)
	7 dcmpl (1, 1)
	8 ifne (1, 1)
	9 18 (1, 1)
	11 new (1, 1)
	12 org/apache/commons/math3/exception/MathArithmeticException (1, 1)
	14 dup (1, 1)
	15 getstatic (1, 1)
	16 org/apache/commons/math3/exception/util/LocalizedFormats.ZERO_NORM:Lorg/apache/commons/math3/exception/util/LocalizedFormats; (1, 1)
	18 iconst_0 (1, 1)
	19 anewarray (1, 1)
	20 java/lang/Object (1, 1)
	22 invokespecial (1, 1)
	23 org/apache/commons/math3/exception/MathArithmeticException.<init>:(Lorg/apache/commons/math3/exception/util/Localizable;[Ljava/lang/Object;)V (1, 1)
	25 athrow (1, 1)
	26 aload_0 (0, 0)
	27 dload_1 (0, 0)
	28 invokevirtual (0, 0)
	29 org/apache/commons/math3/linear/RealVector.mapDivide:(D)Lorg/apache/commons/math3/linear/RealVector; (0, 0)
	31 areturn (0, 0)

Method: unitize
	0 aload_0 (0, 0)
	1 invokevirtual (0, 0)
	2 org/apache/commons/math3/linear/RealVector.getNorm:()D (0, 0)
	4 dstore_1 (0, 0)
	5 dload_1 (1, 1)
	6 dconst_0 (1, 1)
	7 dcmpl (1, 1)
	8 ifne (1, 1)
	9 18 (1, 1)
	11 new (1, 1)
	12 org/apache/commons/math3/exception/MathArithmeticException (1, 1)
	14 dup (1, 1)
	15 getstatic (1, 1)
	16 org/apache/commons/math3/exception/util/LocalizedFormats.ZERO_NORM:Lorg/apache/commons/math3/exception/util/LocalizedFormats; (1, 1)
	18 iconst_0 (1, 1)
	19 anewarray (1, 1)
	20 java/lang/Object (1, 1)
	22 invokespecial (1, 1)
	23 org/apache/commons/math3/exception/MathArithmeticException.<init>:(Lorg/apache/commons/math3/exception/util/Localizable;[Ljava/lang/Object;)V (1, 1)
	25 athrow (1, 1)
	26 aload_0 (0, 0)
	27 aload_0 (0, 0)
	28 invokevirtual (0, 0)
	29 org/apache/commons/math3/linear/RealVector.getNorm:()D (0, 0)
	31 invokevirtual (0, 0)
	32 org/apache/commons/math3/linear/RealVector.mapDivideToSelf:(D)Lorg/apache/commons/math3/linear/RealVector; (0, 0)
	34 pop (0, 0)
	35 return (0, 0)

Method: sparseIterator
	0 new (0, 0)
	1 org/apache/commons/math3/linear/RealVector$SparseEntryIterator (0, 0)
	3 dup (0, 0)
	4 aload_0 (0, 0)
	5 invokespecial (0, 0)
	6 org/apache/commons/math3/linear/RealVector$SparseEntryIterator.<init>:(Lorg/apache/commons/math3/linear/RealVector;)V (0, 0)
	8 areturn (0, 0)

Method: iterator
	0 aload_0 (0, 0)
	1 invokevirtual (0, 0)
	2 org/apache/commons/math3/linear/RealVector.getDimension:()I (0, 0)
	4 istore_1 (0, 0)
	5 new (0, 0)
	6 org/apache/commons/math3/linear/RealVector$1 (0, 0)
	8 dup (0, 0)
	9 aload_0 (0, 0)
	10 iload_1 (0, 0)
	11 invokespecial (0, 0)
	12 org/apache/commons/math3/linear/RealVector$1.<init>:(Lorg/apache/commons/math3/linear/RealVector;I)V (0, 0)
	14 areturn (0, 0)

Method: map
	0 aload_0 (0, 0)
	1 invokevirtual (0, 0)
	2 org/apache/commons/math3/linear/RealVector.copy:()Lorg/apache/commons/math3/linear/RealVector; (0, 0)
	4 aload_1 (0, 0)
	5 invokevirtual (0, 0)
	6 org/apache/commons/math3/linear/RealVector.mapToSelf:(Lorg/apache/commons/math3/analysis/UnivariateFunction;)Lorg/apache/commons/math3/linear/RealVector; (0, 0)
	8 areturn (0, 0)

Method: mapToSelf
	0 aload_0 (0, 0)
	1 invokevirtual (0, 0)
	2 org/apache/commons/math3/linear/RealVector.iterator:()Ljava/util/Iterator; (0, 0)
	4 astore_2 (0, 0)
	5 aload_2 (1, 3)
	6 invokeinterface (1, 3)
	7 java/util/Iterator.next:()Ljava/lang/Object; (1, 3)
	9 0 (1, 3)
	11 ifeq (1, 3)
	12 30 (1, 3)
	14 aload_2 (1, 3)
	15 invokeinterface (1, 3)
	16 java/util/Iterator.org/apache/commons/math3/linear/RealVector$Entry (1, 3)
	18 0 (1, 3)
	20 checkcast (1, 3)
	21 org/apache/commons/math3/linear/RealVector$Entry (1, 3)
	23 astore_3 (1, 3)
	24 aload_3 (1, 3)
	25 aload_1 (1, 3)
	26 aload_3 (1, 3)
	27 invokevirtual (1, 3)
	28 org/apache/commons/math3/linear/RealVector$Entry.getValue:()D (1, 3)
	30 invokeinterface (1, 3)
	31 org/apache/commons/math3/analysis/UnivariateFunction.combineToSelf:(DDLorg/apache/commons/math3/linear/RealVector;)Lorg/apache/commons/math3/linear/RealVector; (1, 3)
	33 0 (1, 3)
	35 invokevirtual (1, 3)
	36 org/apache/commons/math3/linear/RealVector$Entry.setValue:(D)V (1, 3)
	38 goto (0, 0)
	39 -33 (0, 0)
	41 aload_0 (0, 0)
	42 areturn (0, 0)

Method: combine
	0 aload_0 (0, 0)
	1 invokevirtual (0, 0)
	2 org/apache/commons/math3/linear/RealVector.copy:()Lorg/apache/commons/math3/linear/RealVector; (0, 0)
	4 dload_1 (0, 0)
	5 dload_3 (0, 0)
	6 aload (0, 0)
	7 #5 (0, 0)
	8 invokevirtual (0, 0)
	9 org/apache/commons/math3/linear/RealVector.combineToSelf:(DDLorg/apache/commons/math3/linear/RealVector;)Lorg/apache/commons/math3/linear/RealVector; (0, 0)
	11 areturn (0, 0)

Method: combineToSelf
	0 aload_0 (0, 0)
	1 aload (0, 0)
	2 #5 (0, 0)
	3 invokevirtual (0, 0)
	4 org/apache/commons/math3/linear/RealVector.checkVectorDimensions:(Lorg/apache/commons/math3/linear/RealVector;)V (0, 0)
	6 iconst_0 (1, 4)
	7 istore (1, 4)
	8 #6 (1, 4)
	9 iload (1, 4)
	10 #6 (1, 4)
	11 aload_0 (1, 4)
	12 invokevirtual (1, 4)
	13 org/apache/commons/math3/linear/RealVector.getDimension:()I (1, 4)
	15 if_icmpge (1, 4)
	16 41 (1, 4)
	18 aload_0 (1, 4)
	19 iload (1, 4)
	20 #6 (1, 4)
	21 invokevirtual (1, 4)
	22 org/apache/commons/math3/linear/RealVector.getEntry:(I)D (1, 4)
	24 dstore (1, 4)
	25 #7 (1, 4)
	26 aload (1, 4)
	27 #5 (1, 4)
	28 iload (1, 4)
	29 #6 (1, 4)
	30 invokevirtual (1, 4)
	31 org/apache/commons/math3/linear/RealVector.getEntry:(I)D (1, 4)
	33 dstore (1, 4)
	34 #9 (1, 4)
	35 aload_0 (1, 4)
	36 iload (1, 4)
	37 #6 (1, 4)
	38 dload_1 (1, 4)
	39 dload (1, 4)
	40 #7 (1, 4)
	41 dmul (1, 4)
	42 dload_3 (1, 4)
	43 dload (1, 4)
	44 #9 (1, 4)
	45 dmul (1, 4)
	46 dadd (1, 4)
	47 invokevirtual (1, 4)
	48 org/apache/commons/math3/linear/RealVector.setEntry:(ID)V (1, 4)
	50 iinc (1, 4)
	51 #6 (1, 4)
	52 -89 (1, 4)
	53 goto (1, 4)
	54 -44 (1, 4)
	56 aload_0 (0, 0)
	57 areturn (0, 0)

Method: walkInDefaultOrder
	0 aload_0 (0, 0)
	1 iload_2 (0, 0)
	2 iload_3 (0, 0)
	3 invokevirtual (0, 0)
	4 org/apache/commons/math3/linear/RealVector.checkIndices:(II)V (0, 0)
	6 aload_1 (0, 0)
	7 aload_0 (0, 0)
	8 invokevirtual (0, 0)
	9 org/apache/commons/math3/linear/RealVector.getDimension:()I (0, 0)
	11 iload_2 (0, 0)
	12 iload_3 (0, 0)
	13 invokeinterface (0, 0)
	14 org/apache/commons/math3/linear/RealVectorChangingVisitor.visit:(ID)V (0, 0)
	16 0 (0, 0)
	18 iload_2 (1, 4)
	19 istore (1, 4)
	20 #4 (1, 4)
	21 iload (1, 4)
	22 #4 (1, 4)
	23 iload_3 (1, 4)
	24 if_icmpgt (1, 4)
	25 29 (1, 4)
	27 aload_0 (1, 4)
	28 iload (1, 4)
	29 #4 (1, 4)
	30 aload_1 (1, 4)
	31 iload (1, 4)
	32 #4 (1, 4)
	33 aload_0 (1, 4)
	34 iload (1, 4)
	35 #4 (1, 4)
	36 invokevirtual (1, 4)
	37 org/apache/commons/math3/linear/RealVector.getEntry:(I)D (1, 4)
	39 invokeinterface (1, 4)
	40 org/apache/commons/math3/linear/RealVectorChangingVisitor.walkInDefaultOrder:(Lorg/apache/commons/math3/linear/RealVectorChangingVisitor;)D (1, 4)
	42 0 (1, 4)
	44 invokevirtual (1, 4)
	45 org/apache/commons/math3/linear/RealVector.setEntry:(ID)V (1, 4)
	47 iinc (1, 4)
	48 #4 (1, 4)
	49 -89 (1, 4)
	50 goto (1, 4)
	51 -29 (1, 4)
	53 aload_1 (0, 0)
	54 invokeinterface (0, 0)
	55 org/apache/commons/math3/linear/RealVectorChangingVisitor.checkIndices:(II)V (0, 0)
	57 0 (0, 0)
	59 dreturn (0, 0)

Method: walkInOptimizedOrder
	0 aload_0 (0, 0)
	1 aload_1 (0, 0)
	2 iload_2 (0, 0)
	3 iload_3 (0, 0)
	4 invokevirtual (0, 0)
	5 org/apache/commons/math3/linear/RealVector.walkInDefaultOrder:(Lorg/apache/commons/math3/linear/RealVectorChangingVisitor;II)D (0, 0)
	7 dreturn (0, 0)

Method: equals
	0 new (0, 0)
	1 org/apache/commons/math3/exception/MathUnsupportedOperationException (0, 0)
	3 dup (0, 0)
	4 invokespecial (0, 0)
	5 org/apache/commons/math3/exception/MathUnsupportedOperationException.<init>:()V (0, 0)
	7 athrow (0, 0)

Method: hashCode
	0 new (0, 0)
	1 org/apache/commons/math3/exception/MathUnsupportedOperationException (0, 0)
	3 dup (0, 0)
	4 invokespecial (0, 0)
	5 org/apache/commons/math3/exception/MathUnsupportedOperationException.<init>:()V (0, 0)
	7 athrow (0, 0)

Method: unmodifiableRealVector
	0 new (0, 0)
	1 org/apache/commons/math3/linear/RealVector$2 (0, 0)
	3 dup (0, 0)
	4 aload_0 (0, 0)
	5 invokespecial (0, 0)
	6 org/apache/commons/math3/linear/RealVector$2.<init>:(Lorg/apache/commons/math3/linear/RealVector;)V (0, 0)
	8 areturn (0, 0)

