Method: <init>
	0 aload_0 (0, 0)
	1 invokespecial (0, 0)
	2 java/lang/Object.<init>:()V (0, 0)
	4 aload_1 (0, 0)
	5 invokeinterface (0, 0)
	6 org/apache/commons/math3/linear/RealMatrix.getData:()[[D (0, 0)
	8 0 (0, 0)
	10 istore (0, 0)
	11 #4 (0, 0)
	12 aload_1 (0, 0)
	13 invokeinterface (0, 0)
	14 org/apache/commons/math3/linear/RealMatrix.org/apache/commons/math3/linear/NonPositiveDefiniteMatrixException (0, 0)
	16 0 (0, 0)
	18 astore (0, 0)
	19 #5 (0, 0)
	20 iload (0, 0)
	21 #4 (0, 0)
	22 iload (0, 0)
	23 #4 (0, 0)
	24 multianewarray (0, 0)
	25 [[D (0, 0)
	27 58 (0, 0)
	28 astore (0, 0)
	29 #6 (0, 0)
	30 iload (0, 0)
	31 #4 (0, 0)
	32 newarray (0, 0)
	33 10 (0, 0)
	34 astore (0, 0)
	35 #7 (0, 0)
	36 iconst_0 (2, 4)
	37 istore (2, 4)
	38 #8 (2, 4)
	39 iload (2, 4)
	40 #8 (2, 4)
	41 iload (2, 4)
	42 #4 (2, 4)
	43 if_icmpge (2, 4)
	44 16 (2, 4)
	46 aload (2, 4)
	47 #7 (2, 4)
	48 iload (2, 4)
	49 #8 (2, 4)
	50 iload (2, 4)
	51 #8 (2, 4)
	52 iastore (2, 4)
	53 iinc (2, 4)
	54 #8 (2, 4)
	55 -89 (2, 4)
	56 goto (2, 4)
	57 -17 (2, 4)
	59 iconst_0 (0, 0)
	60 istore (0, 0)
	61 #8 (0, 0)
	62 iconst_1 (2, 4)
	63 istore (2, 4)
	64 #9 (2, 4)
	65 iload (2, 4)
	66 #9 (2, 4)
	67 ifeq (2, 4)
	68 440 (2, 4)
	70 iload (2, 4)
	71 #8 (2, 4)
	72 istore (2, 4)
	73 #10 (2, 4)
	74 iload (3, 4)
	75 #8 (3, 4)
	76 iconst_1 (3, 4)
	77 iadd (3, 4)
	78 istore (3, 4)
	79 #11 (3, 4)
	80 iload (3, 4)
	81 #11 (3, 4)
	82 iload (3, 4)
	83 #4 (3, 4)
	84 if_icmpge (3, 4)
	85 47 (3, 4)
	87 aload (3, 4)
	88 #7 (3, 4)
	89 iload (3, 4)
	90 #11 (3, 4)
	91 iaload (3, 4)
	92 istore (3, 4)
	93 #12 (3, 4)
	94 aload (3, 4)
	95 #7 (3, 4)
	96 iload (3, 4)
	97 #10 (3, 4)
	98 iaload (3, 4)
	99 istore (3, 4)
	100 #13 (3, 4)
	101 aload (4, 1)
	102 #5 (4, 1)
	103 iload (4, 1)
	104 #12 (4, 1)
	105 aaload (4, 1)
	106 iload (4, 1)
	107 #12 (4, 1)
	108 daload (4, 1)
	109 aload (4, 1)
	110 #5 (4, 1)
	111 iload (4, 1)
	112 #13 (4, 1)
	113 aaload (4, 1)
	114 iload (4, 1)
	115 #13 (4, 1)
	116 daload (4, 1)
	117 dcmpl (4, 1)
	118 ifle (4, 1)
	119 7 (4, 1)
	121 iload (4, 1)
	122 #11 (4, 1)
	123 istore (4, 1)
	124 #10 (4, 1)
	125 iinc (4, 1)
	126 #11 (4, 1)
	127 -89 (4, 1)
	128 goto (4, 1)
	129 -48 (4, 1)
	131 iload (4, 1)
	132 #10 (4, 1)
	133 iload (4, 1)
	134 #8 (4, 1)
	135 if_icmpeq (4, 1)
	136 51 (4, 1)
	138 aload (4, 1)
	139 #7 (4, 1)
	140 iload (4, 1)
	141 #8 (4, 1)
	142 iaload (4, 1)
	143 istore (4, 1)
	144 #11 (4, 1)
	145 aload (4, 1)
	146 #7 (4, 1)
	147 iload (4, 1)
	148 #8 (4, 1)
	149 aload (4, 1)
	150 #7 (4, 1)
	151 iload (4, 1)
	152 #10 (4, 1)
	153 iaload (4, 1)
	154 iastore (4, 1)
	155 aload (4, 1)
	156 #7 (4, 1)
	157 iload (4, 1)
	158 #10 (4, 1)
	159 iload (4, 1)
	160 #11 (4, 1)
	161 iastore (4, 1)
	162 aload (4, 1)
	163 #6 (4, 1)
	164 iload (4, 1)
	165 #8 (4, 1)
	166 aaload (4, 1)
	167 astore (4, 1)
	168 #12 (4, 1)
	169 aload (4, 1)
	170 #6 (4, 1)
	171 iload (4, 1)
	172 #8 (4, 1)
	173 aload (4, 1)
	174 #6 (4, 1)
	175 iload (4, 1)
	176 #10 (4, 1)
	177 aaload (4, 1)
	178 aastore (4, 1)
	179 aload (4, 1)
	180 #6 (4, 1)
	181 iload (4, 1)
	182 #10 (4, 1)
	183 aload (4, 1)
	184 #12 (4, 1)
	185 aastore (4, 1)
	186 aload (3, 4)
	187 #7 (3, 4)
	188 iload (3, 4)
	189 #8 (3, 4)
	190 iaload (3, 4)
	191 istore (3, 4)
	192 #11 (3, 4)
	193 aload (4, 1)
	194 #5 (4, 1)
	195 iload (4, 1)
	196 #11 (4, 1)
	197 aaload (4, 1)
	198 iload (4, 1)
	199 #11 (4, 1)
	200 daload (4, 1)
	201 dload_2 (4, 1)
	202 dcmpg (4, 1)
	203 ifgt (4, 1)
	204 95 (4, 1)
	206 iload (5, 1)
	207 #8 (5, 1)
	208 ifne (5, 1)
	209 22 (5, 1)
	211 new (5, 1)
	212 org/apache/commons/math3/linear/NonPositiveDefiniteMatrixException (5, 1)
	214 dup (5, 1)
	215 aload (5, 1)
	216 #5 (5, 1)
	217 iload (5, 1)
	218 #11 (5, 1)
	219 aaload (5, 1)
	220 iload (5, 1)
	221 #11 (5, 1)
	222 daload (5, 1)
	223 iload (5, 1)
	224 #11 (5, 1)
	225 dload_2 (5, 1)
	226 invokespecial (5, 1)
	227 org/apache/commons/math3/linear/NonPositiveDefiniteMatrixException.<init>:(DID)V (5, 1)
	229 athrow (5, 1)
	230 iload (5, 4)
	231 #8 (5, 4)
	232 istore (5, 4)
	233 #12 (5, 4)
	234 iload (5, 4)
	235 #12 (5, 4)
	236 iload (5, 4)
	237 #4 (5, 4)
	238 if_icmpge (5, 4)
	239 54 (5, 4)
	241 aload (6, 1)
	242 #5 (6, 1)
	243 aload (6, 1)
	244 #7 (6, 1)
	245 iload (6, 1)
	246 #12 (6, 1)
	247 iaload (6, 1)
	248 aaload (6, 1)
	249 aload (6, 1)
	250 #7 (6, 1)
	251 iload (6, 1)
	252 #12 (6, 1)
	253 iaload (6, 1)
	254 daload (6, 1)
	255 dload_2 (6, 1)
	256 dneg (6, 1)
	257 dcmpg (6, 1)
	258 ifge (6, 1)
	259 28 (6, 1)
	261 new (6, 1)
	262 org/apache/commons/math3/linear/NonPositiveDefiniteMatrixException (6, 1)
	264 dup (6, 1)
	265 aload (6, 1)
	266 #5 (6, 1)
	267 aload (6, 1)
	268 #7 (6, 1)
	269 iload (6, 1)
	270 #12 (6, 1)
	271 iaload (6, 1)
	272 aaload (6, 1)
	273 aload (6, 1)
	274 #7 (6, 1)
	275 iload (6, 1)
	276 #12 (6, 1)
	277 iaload (6, 1)
	278 daload (6, 1)
	279 iload (6, 1)
	280 #12 (6, 1)
	281 dload_2 (6, 1)
	282 invokespecial (6, 1)
	283 org/apache/commons/math3/linear/NonPositiveDefiniteMatrixException.<init>:(DID)V (6, 1)
	285 athrow (6, 1)
	286 iinc (6, 1)
	287 #12 (6, 1)
	288 -89 (6, 1)
	289 goto (6, 1)
	290 -55 (6, 1)
	292 iconst_0 (5, 4)
	293 istore (5, 4)
	294 #9 (5, 4)
	295 goto (5, 4)
	296 209 (5, 4)
	298 aload (5, 4)
	299 #5 (5, 4)
	300 iload (5, 4)
	301 #11 (5, 4)
	302 aaload (5, 4)
	303 iload (5, 4)
	304 #11 (5, 4)
	305 daload (5, 4)
	306 invokestatic (5, 4)
	307 org/apache/commons/math3/util/FastMath.sqrt:(D)D (5, 4)
	309 dstore (5, 4)
	310 #12 (5, 4)
	311 aload (5, 4)
	312 #6 (5, 4)
	313 iload (5, 4)
	314 #8 (5, 4)
	315 aaload (5, 4)
	316 iload (5, 4)
	317 #8 (5, 4)
	318 dload (5, 4)
	319 #12 (5, 4)
	320 dastore (5, 4)
	321 dconst_1 (5, 4)
	322 dload (5, 4)
	323 #12 (5, 4)
	324 ddiv (5, 4)
	325 dstore (5, 4)
	326 #14 (5, 4)
	327 dconst_1 (5, 4)
	328 aload (5, 4)
	329 #5 (5, 4)
	330 iload (5, 4)
	331 #11 (5, 4)
	332 aaload (5, 4)
	333 iload (5, 4)
	334 #11 (5, 4)
	335 daload (5, 4)
	336 ddiv (5, 4)
	337 dstore (5, 4)
	338 #16 (5, 4)
	339 iload (6, 4)
	340 #8 (6, 4)
	341 iconst_1 (6, 4)
	342 iadd (6, 4)
	343 istore (6, 4)
	344 #18 (6, 4)
	345 iload (6, 4)
	346 #18 (6, 4)
	347 iload (6, 4)
	348 #4 (6, 4)
	349 if_icmpge (6, 4)
	350 138 (6, 4)
	352 aload (6, 4)
	353 #7 (6, 4)
	354 iload (6, 4)
	355 #18 (6, 4)
	356 iaload (6, 4)
	357 istore (6, 4)
	358 #19 (6, 4)
	359 dload (6, 4)
	360 #14 (6, 4)
	361 aload (6, 4)
	362 #5 (6, 4)
	363 iload (6, 4)
	364 #19 (6, 4)
	365 aaload (6, 4)
	366 iload (6, 4)
	367 #11 (6, 4)
	368 daload (6, 4)
	369 dmul (6, 4)
	370 dstore (6, 4)
	371 #20 (6, 4)
	372 aload (6, 4)
	373 #6 (6, 4)
	374 iload (6, 4)
	375 #18 (6, 4)
	376 aaload (6, 4)
	377 iload (6, 4)
	378 #8 (6, 4)
	379 dload (6, 4)
	380 #20 (6, 4)
	381 dastore (6, 4)
	382 aload (6, 4)
	383 #5 (6, 4)
	384 iload (6, 4)
	385 #19 (6, 4)
	386 aaload (6, 4)
	387 iload (6, 4)
	388 #19 (6, 4)
	389 dup2 (6, 4)
	390 daload (6, 4)
	391 aload (6, 4)
	392 #5 (6, 4)
	393 iload (6, 4)
	394 #19 (6, 4)
	395 aaload (6, 4)
	396 iload (6, 4)
	397 #11 (6, 4)
	398 daload (6, 4)
	399 aload (6, 4)
	400 #5 (6, 4)
	401 iload (6, 4)
	402 #19 (6, 4)
	403 aaload (6, 4)
	404 iload (6, 4)
	405 #11 (6, 4)
	406 daload (6, 4)
	407 dmul (6, 4)
	408 dload (6, 4)
	409 #16 (6, 4)
	410 dmul (6, 4)
	411 dsub (6, 4)
	412 dastore (6, 4)
	413 iload (7, 4)
	414 #8 (7, 4)
	415 iconst_1 (7, 4)
	416 iadd (7, 4)
	417 istore (7, 4)
	418 #22 (7, 4)
	419 iload (7, 4)
	420 #22 (7, 4)
	421 iload (7, 4)
	422 #18 (7, 4)
	423 if_icmpge (7, 4)
	424 58 (7, 4)
	426 aload (7, 4)
	427 #7 (7, 4)
	428 iload (7, 4)
	429 #22 (7, 4)
	430 iaload (7, 4)
	431 istore (7, 4)
	432 #23 (7, 4)
	433 aload (7, 4)
	434 #5 (7, 4)
	435 iload (7, 4)
	436 #19 (7, 4)
	437 aaload (7, 4)
	438 iload (7, 4)
	439 #23 (7, 4)
	440 daload (7, 4)
	441 dload (7, 4)
	442 #20 (7, 4)
	443 aload (7, 4)
	444 #6 (7, 4)
	445 iload (7, 4)
	446 #22 (7, 4)
	447 aaload (7, 4)
	448 iload (7, 4)
	449 #8 (7, 4)
	450 daload (7, 4)
	451 dmul (7, 4)
	452 dsub (7, 4)
	453 dstore (7, 4)
	454 #24 (7, 4)
	455 aload (7, 4)
	456 #5 (7, 4)
	457 iload (7, 4)
	458 #19 (7, 4)
	459 aaload (7, 4)
	460 iload (7, 4)
	461 #23 (7, 4)
	462 dload (7, 4)
	463 #24 (7, 4)
	464 dastore (7, 4)
	465 aload (7, 4)
	466 #5 (7, 4)
	467 iload (7, 4)
	468 #23 (7, 4)
	469 aaload (7, 4)
	470 iload (7, 4)
	471 #19 (7, 4)
	472 dload (7, 4)
	473 #24 (7, 4)
	474 dastore (7, 4)
	475 iinc (7, 4)
	476 #22 (7, 4)
	477 -89 (7, 4)
	478 goto (7, 4)
	479 -59 (7, 4)
	481 iinc (7, 4)
	482 #18 (7, 4)
	483 -89 (7, 4)
	484 goto (7, 4)
	485 -139 (7, 4)
	487 iinc (6, 4)
	488 #8 (6, 4)
	489 21 (6, 4)
	490 iload (6, 4)
	491 #8 (6, 4)
	492 iload (6, 4)
	493 #4 (6, 4)
	494 if_icmpge (6, 4)
	495 7 (6, 4)
	497 iconst_1 (6, 4)
	498 goto (6, 4)
	499 4 (6, 4)
	501 iconst_0 (6, 4)
	502 istore (6, 4)
	503 #9 (6, 4)
	504 goto (4, 1)
	505 -439 (4, 1)
	507 aload_0 (4, 1)
	508 iload (4, 1)
	509 #8 (4, 1)
	510 putfield (4, 1)
	511 org/apache/commons/math3/linear/RectangularCholeskyDecomposition.rank:I (4, 1)
	513 aload_0 (4, 1)
	514 iload (4, 1)
	515 #4 (4, 1)
	516 iload (4, 1)
	517 #8 (4, 1)
	518 invokestatic (4, 1)
	519 org/apache/commons/math3/linear/MatrixUtils.createRealMatrix:(II)Lorg/apache/commons/math3/linear/RealMatrix; (4, 1)
	521 putfield (4, 1)
	522 org/apache/commons/math3/linear/RectangularCholeskyDecomposition.root:Lorg/apache/commons/math3/linear/RealMatrix; (4, 1)
	524 iconst_0 (5, 4)
	525 istore (5, 4)
	526 #9 (5, 4)
	527 iload (5, 4)
	528 #9 (5, 4)
	529 iload (5, 4)
	530 #4 (5, 4)
	531 if_icmpge (5, 4)
	532 49 (5, 4)
	534 iconst_0 (6, 4)
	535 istore (6, 4)
	536 #10 (6, 4)
	537 iload (6, 4)
	538 #10 (6, 4)
	539 iload (6, 4)
	540 #8 (6, 4)
	541 if_icmpge (6, 4)
	542 33 (6, 4)
	544 aload_0 (6, 4)
	545 getfield (6, 4)
	546 org/apache/commons/math3/linear/RectangularCholeskyDecomposition.root:Lorg/apache/commons/math3/linear/RealMatrix; (6, 4)
	548 aload (6, 4)
	549 #7 (6, 4)
	550 iload (6, 4)
	551 #9 (6, 4)
	552 iaload (6, 4)
	553 iload (6, 4)
	554 #10 (6, 4)
	555 aload (6, 4)
	556 #6 (6, 4)
	557 iload (6, 4)
	558 #9 (6, 4)
	559 aaload (6, 4)
	560 iload (6, 4)
	561 #10 (6, 4)
	562 daload (6, 4)
	563 invokeinterface (6, 4)
	564 org/apache/commons/math3/linear/RealMatrix.org/apache/commons/math3/linear/RectangularCholeskyDecomposition (6, 4)
	566 0 (6, 4)
	568 iinc (6, 4)
	569 #10 (6, 4)
	570 -89 (6, 4)
	571 goto (6, 4)
	572 -34 (6, 4)
	574 iinc (6, 4)
	575 #9 (6, 4)
	576 -89 (6, 4)
	577 goto (6, 4)
	578 -50 (6, 4)
	580 return (4, 1)

Method: getRootMatrix
	0 aload_0 (0, 0)
	1 getfield (0, 0)
	2 org/apache/commons/math3/linear/RectangularCholeskyDecomposition.root:Lorg/apache/commons/math3/linear/RealMatrix; (0, 0)
	4 areturn (0, 0)

Method: getRank
	0 aload_0 (0, 0)
	1 getfield (0, 0)
	2 org/apache/commons/math3/linear/RectangularCholeskyDecomposition.rank:I (0, 0)
	4 ireturn (0, 0)

