Method: <init>
	0 aload_0 (0, 0)
	1 aload_1 (0, 0)
	2 dload_2 (0, 0)
	3 invokespecial (0, 0)
	4 org/apache/commons/math3/linear/QRDecomposition.<init>:(Lorg/apache/commons/math3/linear/RealMatrix;D)V (0, 0)
	6 return (0, 0)

Method: decompose
	0 aload_0 (0, 0)
	1 aload_1 (0, 0)
	2 arraylength (0, 0)
	3 newarray (0, 0)
	4 10 (0, 0)
	5 putfield (0, 0)
	6 org/apache/commons/math3/linear/RRQRDecomposition.p:[I (0, 0)
	8 iconst_0 (1, 4)
	9 istore_2 (1, 4)
	10 iload_2 (1, 4)
	11 aload_0 (1, 4)
	12 getfield (1, 4)
	13 org/apache/commons/math3/linear/RRQRDecomposition.p:[I (1, 4)
	15 arraylength (1, 4)
	16 if_icmpge (1, 4)
	17 16 (1, 4)
	19 aload_0 (1, 4)
	20 getfield (1, 4)
	21 org/apache/commons/math3/linear/RRQRDecomposition.p:[I (1, 4)
	23 iload_2 (1, 4)
	24 iload_2 (1, 4)
	25 iastore (1, 4)
	26 iinc (1, 4)
	27 #2 (1, 4)
	28 -89 (1, 4)
	29 goto (1, 4)
	30 -19 (1, 4)
	32 aload_0 (0, 0)
	33 aload_1 (0, 0)
	34 invokespecial (0, 0)
	35 org/apache/commons/math3/linear/QRDecomposition.decompose:([[D)V (0, 0)
	37 return (0, 0)

Method: performHouseholderReflection
	0 dconst_0 (0, 0)
	1 dstore_3 (0, 0)
	2 iload_1 (0, 0)
	3 istore (0, 0)
	4 #5 (0, 0)
	5 iload_1 (1, 4)
	6 istore (1, 4)
	7 #6 (1, 4)
	8 iload (1, 4)
	9 #6 (1, 4)
	10 aload_2 (1, 4)
	11 arraylength (1, 4)
	12 if_icmpge (1, 4)
	13 65 (1, 4)
	15 dconst_0 (1, 4)
	16 dstore (1, 4)
	17 #7 (1, 4)
	18 iconst_0 (2, 4)
	19 istore (2, 4)
	20 #9 (2, 4)
	21 iload (2, 4)
	22 #9 (2, 4)
	23 aload_2 (2, 4)
	24 iload (2, 4)
	25 #6 (2, 4)
	26 aaload (2, 4)
	27 arraylength (2, 4)
	28 if_icmpge (2, 4)
	29 29 (2, 4)
	31 dload (2, 4)
	32 #7 (2, 4)
	33 aload_2 (2, 4)
	34 iload (2, 4)
	35 #6 (2, 4)
	36 aaload (2, 4)
	37 iload (2, 4)
	38 #9 (2, 4)
	39 daload (2, 4)
	40 aload_2 (2, 4)
	41 iload (2, 4)
	42 #6 (2, 4)
	43 aaload (2, 4)
	44 iload (2, 4)
	45 #9 (2, 4)
	46 daload (2, 4)
	47 dmul (2, 4)
	48 dadd (2, 4)
	49 dstore (2, 4)
	50 #7 (2, 4)
	51 iinc (2, 4)
	52 #9 (2, 4)
	53 -89 (2, 4)
	54 goto (2, 4)
	55 -33 (2, 4)
	57 dload (2, 1)
	58 #7 (2, 1)
	59 dload_3 (2, 1)
	60 dcmpl (2, 1)
	61 ifle (2, 1)
	62 10 (2, 1)
	64 dload (2, 1)
	65 #7 (2, 1)
	66 dstore_3 (2, 1)
	67 iload (2, 1)
	68 #6 (2, 1)
	69 istore (2, 1)
	70 #5 (2, 1)
	71 iinc (2, 1)
	72 #6 (2, 1)
	73 -89 (2, 1)
	74 goto (2, 1)
	75 -66 (2, 1)
	77 iload (2, 1)
	78 #5 (2, 1)
	79 iload_1 (2, 1)
	80 if_icmpeq (2, 1)
	81 51 (2, 1)
	83 aload_2 (2, 1)
	84 iload_1 (2, 1)
	85 aaload (2, 1)
	86 astore (2, 1)
	87 #6 (2, 1)
	88 aload_2 (2, 1)
	89 iload_1 (2, 1)
	90 aload_2 (2, 1)
	91 iload (2, 1)
	92 #5 (2, 1)
	93 aaload (2, 1)
	94 aastore (2, 1)
	95 aload_2 (2, 1)
	96 iload (2, 1)
	97 #5 (2, 1)
	98 aload (2, 1)
	99 #6 (2, 1)
	100 aastore (2, 1)
	101 aload_0 (2, 1)
	102 getfield (2, 1)
	103 org/apache/commons/math3/linear/RRQRDecomposition.p:[I (2, 1)
	105 iload_1 (2, 1)
	106 iaload (2, 1)
	107 istore (2, 1)
	108 #7 (2, 1)
	109 aload_0 (2, 1)
	110 getfield (2, 1)
	111 org/apache/commons/math3/linear/RRQRDecomposition.p:[I (2, 1)
	113 iload_1 (2, 1)
	114 aload_0 (2, 1)
	115 getfield (2, 1)
	116 org/apache/commons/math3/linear/RRQRDecomposition.p:[I (2, 1)
	118 iload (2, 1)
	119 #5 (2, 1)
	120 iaload (2, 1)
	121 iastore (2, 1)
	122 aload_0 (2, 1)
	123 getfield (2, 1)
	124 org/apache/commons/math3/linear/RRQRDecomposition.p:[I (2, 1)
	126 iload (2, 1)
	127 #5 (2, 1)
	128 iload (2, 1)
	129 #7 (2, 1)
	130 iastore (2, 1)
	131 aload_0 (1, 4)
	132 iload_1 (1, 4)
	133 aload_2 (1, 4)
	134 invokespecial (1, 4)
	135 org/apache/commons/math3/linear/QRDecomposition.performHouseholderReflection:(I[[D)V (1, 4)
	137 return (0, 0)

Method: getP
	0 aload_0 (1, 1)
	1 getfield (1, 1)
	2 org/apache/commons/math3/linear/RRQRDecomposition.cachedP:Lorg/apache/commons/math3/linear/RealMatrix; (1, 1)
	4 ifnonnull (1, 1)
	5 48 (1, 1)
	7 aload_0 (1, 1)
	8 getfield (1, 1)
	9 org/apache/commons/math3/linear/RRQRDecomposition.p:[I (1, 1)
	11 arraylength (1, 1)
	12 istore_1 (1, 1)
	13 aload_0 (1, 1)
	14 iload_1 (1, 1)
	15 iload_1 (1, 1)
	16 invokestatic (1, 1)
	17 org/apache/commons/math3/linear/MatrixUtils.createRealMatrix:(II)Lorg/apache/commons/math3/linear/RealMatrix; (1, 1)
	19 putfield (1, 1)
	20 org/apache/commons/math3/linear/RRQRDecomposition.cachedP:Lorg/apache/commons/math3/linear/RealMatrix; (1, 1)
	22 iconst_0 (2, 4)
	23 istore_2 (2, 4)
	24 iload_2 (2, 4)
	25 iload_1 (2, 4)
	26 if_icmpge (2, 4)
	27 26 (2, 4)
	29 aload_0 (2, 4)
	30 getfield (2, 4)
	31 org/apache/commons/math3/linear/RRQRDecomposition.cachedP:Lorg/apache/commons/math3/linear/RealMatrix; (2, 4)
	33 aload_0 (2, 4)
	34 getfield (2, 4)
	35 org/apache/commons/math3/linear/RRQRDecomposition.p:[I (2, 4)
	37 iload_2 (2, 4)
	38 iaload (2, 4)
	39 iload_2 (2, 4)
	40 dconst_1 (2, 4)
	41 invokeinterface (2, 4)
	42 org/apache/commons/math3/linear/RealMatrix.getR:()Lorg/apache/commons/math3/linear/RealMatrix; (2, 4)
	44 0 (2, 4)
	46 iinc (2, 4)
	47 #2 (2, 4)
	48 -89 (2, 4)
	49 goto (2, 4)
	50 -25 (2, 4)
	52 aload_0 (0, 0)
	53 getfield (0, 0)
	54 org/apache/commons/math3/linear/RRQRDecomposition.cachedP:Lorg/apache/commons/math3/linear/RealMatrix; (0, 0)
	56 areturn (0, 0)

Method: getRank
	0 aload_0 (0, 0)
	1 invokevirtual (0, 0)
	2 org/apache/commons/math3/linear/RRQRDecomposition.getR:()Lorg/apache/commons/math3/linear/RealMatrix; (0, 0)
	4 astore_3 (0, 0)
	5 aload_3 (0, 0)
	6 invokeinterface (0, 0)
	7 org/apache/commons/math3/linear/RealMatrix.getColumnDimension:()I (0, 0)
	9 0 (0, 0)
	11 istore (0, 0)
	12 #4 (0, 0)
	13 aload_3 (0, 0)
	14 invokeinterface (0, 0)
	15 org/apache/commons/math3/linear/RealMatrix.getFrobeniusNorm:()D (0, 0)
	17 0 (0, 0)
	19 istore (0, 0)
	20 #5 (0, 0)
	21 iconst_1 (0, 0)
	22 istore (0, 0)
	23 #6 (0, 0)
	24 aload_3 (0, 0)
	25 invokeinterface (0, 0)
	26 org/apache/commons/math3/linear/RealMatrix.org/apache/commons/math3/util/FastMath (0, 0)
	28 0 (0, 0)
	30 dstore (0, 0)
	31 #7 (0, 0)
	32 dload (0, 0)
	33 #7 (0, 0)
	34 dstore (0, 0)
	35 #9 (0, 0)
	36 iload (1, 3)
	37 #6 (1, 3)
	38 iload (1, 3)
	39 #4 (1, 3)
	40 iload (1, 3)
	41 #5 (1, 3)
	42 invokestatic (1, 3)
	43 org/apache/commons/math3/util/FastMath.min:(II)I (1, 3)
	45 if_icmpge (1, 3)
	46 61 (1, 3)
	48 aload_3 (1, 3)
	49 iload (1, 3)
	50 #6 (1, 3)
	51 iload (1, 3)
	52 #4 (1, 3)
	53 iconst_1 (1, 3)
	54 isub (1, 3)
	55 iload (1, 3)
	56 #6 (1, 3)
	57 iload (1, 3)
	58 #5 (1, 3)
	59 iconst_1 (1, 3)
	60 isub (1, 3)
	61 invokeinterface (1, 3)
	62 org/apache/commons/math3/linear/RealMatrix.org/apache/commons/math3/linear/RRQRDecomposition$Solver (1, 3)
	64 0 (1, 3)
	66 invokeinterface (1, 3)
	67 org/apache/commons/math3/linear/RealMatrix.org/apache/commons/math3/util/FastMath (1, 3)
	69 0 (1, 3)
	71 dstore (1, 3)
	72 #11 (1, 3)
	73 dload (2, 1)
	74 #11 (2, 1)
	75 dconst_0 (2, 1)
	76 dcmpl (2, 1)
	77 ifeq (2, 1)
	78 29 (2, 1)
	80 dload (2, 1)
	81 #11 (2, 1)
	82 dload (2, 1)
	83 #7 (2, 1)
	84 ddiv (2, 1)
	85 dload (2, 1)
	86 #9 (2, 1)
	87 dmul (2, 1)
	88 dload_1 (2, 1)
	89 dcmpg (2, 1)
	90 ifge (2, 1)
	91 6 (2, 1)
	93 goto (2, 1)
	94 13 (2, 1)
	96 dload (1, 3)
	97 #11 (1, 3)
	98 dstore (1, 3)
	99 #7 (1, 3)
	100 iinc (1, 3)
	101 #6 (1, 3)
	102 -89 (1, 3)
	103 goto (0, 0)
	104 -67 (0, 0)
	106 iload (0, 0)
	107 #6 (0, 0)
	108 ireturn (0, 0)

Method: getSolver
	0 new (0, 0)
	1 org/apache/commons/math3/linear/RRQRDecomposition$Solver (0, 0)
	3 dup (0, 0)
	4 aload_0 (0, 0)
	5 invokespecial (0, 0)
	6 org/apache/commons/math3/linear/QRDecomposition.getSolver:()Lorg/apache/commons/math3/linear/DecompositionSolver; (0, 0)
	8 aload_0 (0, 0)
	9 invokevirtual (0, 0)
	10 org/apache/commons/math3/linear/RRQRDecomposition.getP:()Lorg/apache/commons/math3/linear/RealMatrix; (0, 0)
	12 aconst_null (0, 0)
	13 invokespecial (0, 0)
	14 org/apache/commons/math3/linear/RRQRDecomposition$Solver.<init>:(Lorg/apache/commons/math3/linear/DecompositionSolver;Lorg/apache/commons/math3/linear/RealMatrix;Lorg/apache/commons/math3/linear/RRQRDecomposition$1;)V (0, 0)
	16 areturn (0, 0)

