Method: <init>
	0 aload_0 (0, 0)
	1 invokespecial (0, 0)
	2 java/lang/Object.<init>:()V (0, 0)
	4 aload_0 (0, 0)
	5 aload_1 (0, 0)
	6 putfield (0, 0)
	7 org/apache/commons/math3/linear/RRQRDecomposition$Solver.upper:Lorg/apache/commons/math3/linear/DecompositionSolver; (0, 0)
	9 aload_0 (0, 0)
	10 aload_2 (0, 0)
	11 putfield (0, 0)
	12 org/apache/commons/math3/linear/RRQRDecomposition$Solver.p:Lorg/apache/commons/math3/linear/RealMatrix; (0, 0)
	14 return (0, 0)

Method: isNonSingular
	0 aload_0 (0, 0)
	1 getfield (0, 0)
	2 org/apache/commons/math3/linear/RRQRDecomposition$Solver.upper:Lorg/apache/commons/math3/linear/DecompositionSolver; (0, 0)
	4 invokeinterface (0, 0)
	5 org/apache/commons/math3/linear/DecompositionSolver.solve:(Lorg/apache/commons/math3/linear/RealVector;)Lorg/apache/commons/math3/linear/RealVector; (0, 0)
	7 0 (0, 0)
	9 ireturn (0, 0)

Method: solve
	0 aload_0 (0, 0)
	1 getfield (0, 0)
	2 org/apache/commons/math3/linear/RRQRDecomposition$Solver.p:Lorg/apache/commons/math3/linear/RealMatrix; (0, 0)
	4 aload_0 (0, 0)
	5 getfield (0, 0)
	6 org/apache/commons/math3/linear/RRQRDecomposition$Solver.upper:Lorg/apache/commons/math3/linear/DecompositionSolver; (0, 0)
	8 aload_1 (0, 0)
	9 invokeinterface (0, 0)
	10 org/apache/commons/math3/linear/DecompositionSolver.multiply:(Lorg/apache/commons/math3/linear/RealMatrix;)Lorg/apache/commons/math3/linear/RealMatrix; (0, 0)
	12 0 (0, 0)
	14 invokeinterface (0, 0)
	15 org/apache/commons/math3/linear/RealMatrix.getRowDimension:()I (0, 0)
	17 0 (0, 0)
	19 areturn (0, 0)

Method: getInverse
	0 aload_0 (0, 0)
	1 aload_0 (0, 0)
	2 getfield (0, 0)
	3 org/apache/commons/math3/linear/RRQRDecomposition$Solver.p:Lorg/apache/commons/math3/linear/RealMatrix; (0, 0)
	5 invokeinterface (0, 0)
	6 org/apache/commons/math3/linear/RealMatrix.org/apache/commons/math3/linear/MatrixUtils (0, 0)
	8 0 (0, 0)
	10 invokestatic (0, 0)
	11 org/apache/commons/math3/linear/MatrixUtils.createRealIdentityMatrix:(I)Lorg/apache/commons/math3/linear/RealMatrix; (0, 0)
	13 invokevirtual (0, 0)
	14 org/apache/commons/math3/linear/RRQRDecomposition$Solver.solve:(Lorg/apache/commons/math3/linear/RealMatrix;)Lorg/apache/commons/math3/linear/RealMatrix; (0, 0)
	16 areturn (0, 0)

