Method: <init>
	0 aload_0 (1, 4)
	1 invokespecial (1, 4)
	2 java/lang/Object.<init>:()V (1, 4)
	4 aload_0 (1, 4)
	5 getstatic (1, 4)
	6 org/apache/commons/math3/util/Precision.EPSILON:D (1, 4)
	8 putfield (1, 4)
	9 org/apache/commons/math3/linear/SchurTransformer.epsilon:D (1, 4)
	11 aload_1 (6, 1)
	12 invokeinterface (6, 1)
	13 org/apache/commons/math3/linear/RealMatrix.org/apache/commons/math3/linear/NonSquareMatrixException (6, 1)
	15 0 (6, 1)
	17 ifne (6, 1)
	18 23 (6, 1)
	20 new (6, 1)
	21 org/apache/commons/math3/linear/NonSquareMatrixException (6, 1)
	23 dup (6, 1)
	24 aload_1 (6, 1)
	25 invokeinterface (6, 1)
	26 org/apache/commons/math3/linear/RealMatrix.getColumnDimension:()I (6, 1)
	28 0 (6, 1)
	30 aload_1 (6, 1)
	31 invokeinterface (6, 1)
	32 org/apache/commons/math3/linear/RealMatrix.<init>:(II)V (6, 1)
	34 0 (6, 1)
	36 invokespecial (6, 1)
	37 org/apache/commons/math3/linear/NonSquareMatrixException.<init>:(II)V (6, 1)
	39 athrow (6, 1)
	40 new (6, 4)
	41 org/apache/commons/math3/linear/HessenbergTransformer (6, 4)
	43 dup (6, 4)
	44 aload_1 (6, 4)
	45 invokespecial (6, 4)
	46 org/apache/commons/math3/linear/HessenbergTransformer.<init>:(Lorg/apache/commons/math3/linear/RealMatrix;)V (6, 4)
	48 astore_2 (6, 4)
	49 aload_0 (7, 4)
	50 aload_2 (7, 4)
	51 invokevirtual (7, 4)
	52 org/apache/commons/math3/linear/HessenbergTransformer.getH:()Lorg/apache/commons/math3/linear/RealMatrix; (7, 4)
	54 invokeinterface (7, 4)
	55 org/apache/commons/math3/linear/RealMatrix.matrixT:[[D (7, 4)
	57 0 (7, 4)
	59 putfield (7, 4)
	60 org/apache/commons/math3/linear/SchurTransformer.matrixT:[[D (7, 4)
	62 aload_0 (8, 4)
	63 aload_2 (8, 4)
	64 invokevirtual (8, 4)
	65 org/apache/commons/math3/linear/HessenbergTransformer.getP:()Lorg/apache/commons/math3/linear/RealMatrix; (8, 4)
	67 invokeinterface (8, 4)
	68 org/apache/commons/math3/linear/RealMatrix.matrixT:[[D (8, 4)
	70 0 (8, 4)
	72 putfield (8, 4)
	73 org/apache/commons/math3/linear/SchurTransformer.matrixP:[[D (8, 4)
	75 aload_0 (8, 4)
	76 aconst_null (8, 4)
	77 putfield (8, 4)
	78 org/apache/commons/math3/linear/SchurTransformer.cachedT:Lorg/apache/commons/math3/linear/RealMatrix; (8, 4)
	80 aload_0 (8, 4)
	81 aconst_null (8, 4)
	82 putfield (8, 4)
	83 org/apache/commons/math3/linear/SchurTransformer.cachedP:Lorg/apache/commons/math3/linear/RealMatrix; (8, 4)
	85 aload_0 (8, 4)
	86 aconst_null (8, 4)
	87 putfield (8, 4)
	88 org/apache/commons/math3/linear/SchurTransformer.cachedPt:Lorg/apache/commons/math3/linear/RealMatrix; (8, 4)
	90 aload_0 (10, 4)
	91 invokespecial (10, 4)
	92 org/apache/commons/math3/linear/SchurTransformer.transform:()V (10, 4)
	94 return (1, 1)

Method: getP
	0 aload_0 (1, 1)
	1 getfield (1, 1)
	2 org/apache/commons/math3/linear/SchurTransformer.cachedP:Lorg/apache/commons/math3/linear/RealMatrix; (1, 1)
	4 ifnonnull (1, 1)
	5 14 (1, 1)
	7 aload_0 (1, 1)
	8 aload_0 (1, 1)
	9 getfield (1, 1)
	10 org/apache/commons/math3/linear/SchurTransformer.matrixP:[[D (1, 1)
	12 invokestatic (1, 1)
	13 org/apache/commons/math3/linear/MatrixUtils.createRealMatrix:([[D)Lorg/apache/commons/math3/linear/RealMatrix; (1, 1)
	15 putfield (1, 1)
	16 org/apache/commons/math3/linear/SchurTransformer.cachedP:Lorg/apache/commons/math3/linear/RealMatrix; (1, 1)
	18 aload_0 (0, 0)
	19 getfield (0, 0)
	20 org/apache/commons/math3/linear/SchurTransformer.cachedP:Lorg/apache/commons/math3/linear/RealMatrix; (0, 0)
	22 areturn (0, 0)

Method: getPT
	0 aload_0 (1, 1)
	1 getfield (1, 1)
	2 org/apache/commons/math3/linear/SchurTransformer.cachedPt:Lorg/apache/commons/math3/linear/RealMatrix; (1, 1)
	4 ifnonnull (1, 1)
	5 16 (1, 1)
	7 aload_0 (1, 1)
	8 aload_0 (1, 1)
	9 invokevirtual (1, 1)
	10 org/apache/commons/math3/linear/SchurTransformer.getP:()Lorg/apache/commons/math3/linear/RealMatrix; (1, 1)
	12 invokeinterface (1, 1)
	13 org/apache/commons/math3/linear/RealMatrix.getNorm:()D (1, 1)
	15 0 (1, 1)
	17 putfield (1, 1)
	18 org/apache/commons/math3/linear/SchurTransformer.cachedPt:Lorg/apache/commons/math3/linear/RealMatrix; (1, 1)
	20 aload_0 (0, 0)
	21 getfield (0, 0)
	22 org/apache/commons/math3/linear/SchurTransformer.cachedPt:Lorg/apache/commons/math3/linear/RealMatrix; (0, 0)
	24 areturn (0, 0)

Method: getT
	0 aload_0 (1, 1)
	1 getfield (1, 1)
	2 org/apache/commons/math3/linear/SchurTransformer.cachedT:Lorg/apache/commons/math3/linear/RealMatrix; (1, 1)
	4 ifnonnull (1, 1)
	5 14 (1, 1)
	7 aload_0 (1, 1)
	8 aload_0 (1, 1)
	9 getfield (1, 1)
	10 org/apache/commons/math3/linear/SchurTransformer.matrixT:[[D (1, 1)
	12 invokestatic (1, 1)
	13 org/apache/commons/math3/linear/MatrixUtils.createRealMatrix:([[D)Lorg/apache/commons/math3/linear/RealMatrix; (1, 1)
	15 putfield (1, 1)
	16 org/apache/commons/math3/linear/SchurTransformer.cachedT:Lorg/apache/commons/math3/linear/RealMatrix; (1, 1)
	18 aload_0 (0, 0)
	19 getfield (0, 0)
	20 org/apache/commons/math3/linear/SchurTransformer.cachedT:Lorg/apache/commons/math3/linear/RealMatrix; (0, 0)
	22 areturn (0, 0)

Method: transform
	0 aload_0 (0, 0)
	1 getfield (0, 0)
	2 org/apache/commons/math3/linear/SchurTransformer.matrixT:[[D (0, 0)
	4 arraylength (0, 0)
	5 istore_1 (0, 0)
	6 aload_0 (0, 0)
	7 invokespecial (0, 0)
	8 org/apache/commons/math3/linear/SchurTransformer.getNorm:()D (0, 0)
	10 dstore_2 (0, 0)
	11 new (2, 1)
	12 org/apache/commons/math3/linear/SchurTransformer$ShiftInfo (2, 1)
	14 dup (2, 1)
	15 aconst_null (2, 1)
	16 invokespecial (2, 1)
	17 org/apache/commons/math3/linear/SchurTransformer$ShiftInfo.<init>:(Lorg/apache/commons/math3/linear/SchurTransformer$1;)V (2, 1)
	19 astore (2, 1)
	20 #4 (2, 1)
	21 iconst_0 (2, 1)
	22 istore (2, 1)
	23 #5 (2, 1)
	24 iload_1 (2, 1)
	25 iconst_1 (2, 1)
	26 isub (2, 1)
	27 istore (2, 1)
	28 #6 (2, 1)
	29 iload (3, 3)
	30 #6 (3, 3)
	31 iflt (3, 3)
	32 631 (3, 3)
	34 aload_0 (4, 4)
	35 iload (4, 4)
	36 #6 (4, 4)
	37 dload_2 (4, 4)
	38 invokespecial (4, 4)
	39 org/apache/commons/math3/linear/SchurTransformer.findSmallSubDiagonalElement:(ID)I (4, 4)
	41 istore (4, 4)
	42 #7 (4, 4)
	43 iload (6, 1)
	44 #7 (6, 1)
	45 iload (6, 1)
	46 #6 (6, 1)
	47 if_icmpne (6, 1)
	48 30 (6, 1)
	50 aload_0 (7, 1)
	51 getfield (7, 1)
	52 org/apache/commons/math3/linear/SchurTransformer.matrixT:[[D (7, 1)
	54 iload (7, 1)
	55 #6 (7, 1)
	56 aaload (7, 1)
	57 iload (7, 1)
	58 #6 (7, 1)
	59 dup2 (7, 1)
	60 daload (7, 1)
	61 aload (7, 1)
	62 #4 (7, 1)
	63 getfield (7, 1)
	64 org/apache/commons/math3/linear/SchurTransformer$ShiftInfo.exShift:D (7, 1)
	66 dadd (7, 1)
	67 dastore (7, 1)
	68 iinc (7, 1)
	69 #6 (7, 1)
	70 3 (7, 1)
	71 iconst_0 (7, 1)
	72 istore (7, 1)
	73 #5 (7, 1)
	74 goto (7, 1)
	75 585 (7, 1)
	77 iload (8, 1)
	78 #7 (8, 1)
	79 iload (8, 1)
	80 #6 (8, 1)
	81 iconst_1 (8, 1)
	82 isub (8, 1)
	83 if_icmpne (8, 1)
	84 501 (8, 1)
	86 aload_0 (8, 1)
	87 getfield (8, 1)
	88 org/apache/commons/math3/linear/SchurTransformer.matrixT:[[D (8, 1)
	90 iload (8, 1)
	91 #6 (8, 1)
	92 iconst_1 (8, 1)
	93 isub (8, 1)
	94 aaload (8, 1)
	95 iload (8, 1)
	96 #6 (8, 1)
	97 iconst_1 (8, 1)
	98 isub (8, 1)
	99 daload (8, 1)
	100 aload_0 (8, 1)
	101 getfield (8, 1)
	102 org/apache/commons/math3/linear/SchurTransformer.matrixT:[[D (8, 1)
	104 iload (8, 1)
	105 #6 (8, 1)
	106 aaload (8, 1)
	107 iload (8, 1)
	108 #6 (8, 1)
	109 daload (8, 1)
	110 dsub (8, 1)
	111 ldc2_w (8, 1)
	112 2.0 (8, 1)
	114 ddiv (8, 1)
	115 dstore (8, 1)
	116 #8 (8, 1)
	117 dload (8, 1)
	118 #8 (8, 1)
	119 dload (8, 1)
	120 #8 (8, 1)
	121 dmul (8, 1)
	122 aload_0 (8, 1)
	123 getfield (8, 1)
	124 org/apache/commons/math3/linear/SchurTransformer.matrixT:[[D (8, 1)
	126 iload (8, 1)
	127 #6 (8, 1)
	128 aaload (8, 1)
	129 iload (8, 1)
	130 #6 (8, 1)
	131 iconst_1 (8, 1)
	132 isub (8, 1)
	133 daload (8, 1)
	134 aload_0 (8, 1)
	135 getfield (8, 1)
	136 org/apache/commons/math3/linear/SchurTransformer.matrixT:[[D (8, 1)
	138 iload (8, 1)
	139 #6 (8, 1)
	140 iconst_1 (8, 1)
	141 isub (8, 1)
	142 aaload (8, 1)
	143 iload (8, 1)
	144 #6 (8, 1)
	145 daload (8, 1)
	146 dmul (8, 1)
	147 dadd (8, 1)
	148 dstore (8, 1)
	149 #10 (8, 1)
	150 aload_0 (9, 1)
	151 getfield (9, 1)
	152 org/apache/commons/math3/linear/SchurTransformer.matrixT:[[D (9, 1)
	154 iload (9, 1)
	155 #6 (9, 1)
	156 aaload (9, 1)
	157 iload (9, 1)
	158 #6 (9, 1)
	159 dup2 (9, 1)
	160 daload (9, 1)
	161 aload (9, 1)
	162 #4 (9, 1)
	163 getfield (9, 1)
	164 org/apache/commons/math3/linear/SchurTransformer$ShiftInfo.exShift:D (9, 1)
	166 dadd (9, 1)
	167 dastore (9, 1)
	168 aload_0 (10, 1)
	169 getfield (10, 1)
	170 org/apache/commons/math3/linear/SchurTransformer.matrixT:[[D (10, 1)
	172 iload (10, 1)
	173 #6 (10, 1)
	174 iconst_1 (10, 1)
	175 isub (10, 1)
	176 aaload (10, 1)
	177 iload (10, 1)
	178 #6 (10, 1)
	179 iconst_1 (10, 1)
	180 isub (10, 1)
	181 dup2 (10, 1)
	182 daload (10, 1)
	183 aload (10, 1)
	184 #4 (10, 1)
	185 getfield (10, 1)
	186 org/apache/commons/math3/linear/SchurTransformer$ShiftInfo.exShift:D (10, 1)
	188 dadd (10, 1)
	189 dastore (10, 1)
	190 dload (11, 1)
	191 #10 (11, 1)
	192 dconst_0 (11, 1)
	193 dcmpl (11, 1)
	194 iflt (11, 1)
	195 381 (11, 1)
	197 dload (11, 1)
	198 #10 (11, 1)
	199 invokestatic (11, 1)
	200 org/apache/commons/math3/util/FastMath.abs:(D)D (11, 1)
	202 invokestatic (11, 1)
	203 org/apache/commons/math3/util/FastMath.sqrt:(D)D (11, 1)
	205 dstore (11, 1)
	206 #12 (11, 1)
	207 dload (12, 1)
	208 #8 (12, 1)
	209 dconst_0 (12, 1)
	210 dcmpl (12, 1)
	211 iflt (12, 1)
	212 13 (12, 1)
	214 dload (12, 1)
	215 #8 (12, 1)
	216 dload (12, 1)
	217 #12 (12, 1)
	218 dadd (12, 1)
	219 dstore (12, 1)
	220 #12 (12, 1)
	221 goto (12, 1)
	222 10 (12, 1)
	224 dload (13, 2)
	225 #8 (13, 2)
	226 dload (13, 2)
	227 #12 (13, 2)
	228 dsub (13, 2)
	229 dstore (13, 2)
	230 #12 (13, 2)
	231 aload_0 (11, 1)
	232 getfield (11, 1)
	233 org/apache/commons/math3/linear/SchurTransformer.matrixT:[[D (11, 1)
	235 iload (11, 1)
	236 #6 (11, 1)
	237 aaload (11, 1)
	238 iload (11, 1)
	239 #6 (11, 1)
	240 iconst_1 (11, 1)
	241 isub (11, 1)
	242 daload (11, 1)
	243 dstore (11, 1)
	244 #14 (11, 1)
	245 dload (11, 1)
	246 #14 (11, 1)
	247 invokestatic (11, 1)
	248 org/apache/commons/math3/util/FastMath.abs:(D)D (11, 1)
	250 dload (11, 1)
	251 #12 (11, 1)
	252 invokestatic (11, 1)
	253 org/apache/commons/math3/util/FastMath.abs:(D)D (11, 1)
	255 dadd (11, 1)
	256 dstore (11, 1)
	257 #16 (11, 1)
	258 dload (11, 1)
	259 #14 (11, 1)
	260 dload (11, 1)
	261 #16 (11, 1)
	262 ddiv (11, 1)
	263 dstore (11, 1)
	264 #8 (11, 1)
	265 dload (11, 1)
	266 #12 (11, 1)
	267 dload (11, 1)
	268 #16 (11, 1)
	269 ddiv (11, 1)
	270 dstore (11, 1)
	271 #10 (11, 1)
	272 dload (11, 1)
	273 #8 (11, 1)
	274 dload (11, 1)
	275 #8 (11, 1)
	276 dmul (11, 1)
	277 dload (11, 1)
	278 #10 (11, 1)
	279 dload (11, 1)
	280 #10 (11, 1)
	281 dmul (11, 1)
	282 dadd (11, 1)
	283 invokestatic (11, 1)
	284 org/apache/commons/math3/util/FastMath.sqrt:(D)D (11, 1)
	286 dstore (11, 1)
	287 #18 (11, 1)
	288 dload (11, 1)
	289 #8 (11, 1)
	290 dload (11, 1)
	291 #18 (11, 1)
	292 ddiv (11, 1)
	293 dstore (11, 1)
	294 #8 (11, 1)
	295 dload (11, 1)
	296 #10 (11, 1)
	297 dload (11, 1)
	298 #18 (11, 1)
	299 ddiv (11, 1)
	300 dstore (11, 1)
	301 #10 (11, 1)
	302 iload (13, 4)
	303 #6 (13, 4)
	304 iconst_1 (13, 4)
	305 isub (13, 4)
	306 istore (13, 4)
	307 #20 (13, 4)
	308 iload (13, 4)
	309 #20 (13, 4)
	310 iload_1 (13, 4)
	311 if_icmpge (13, 4)
	312 83 (13, 4)
	314 aload_0 (13, 4)
	315 getfield (13, 4)
	316 org/apache/commons/math3/linear/SchurTransformer.matrixT:[[D (13, 4)
	318 iload (13, 4)
	319 #6 (13, 4)
	320 iconst_1 (13, 4)
	321 isub (13, 4)
	322 aaload (13, 4)
	323 iload (13, 4)
	324 #20 (13, 4)
	325 daload (13, 4)
	326 dstore (13, 4)
	327 #12 (13, 4)
	328 aload_0 (13, 4)
	329 getfield (13, 4)
	330 org/apache/commons/math3/linear/SchurTransformer.matrixT:[[D (13, 4)
	332 iload (13, 4)
	333 #6 (13, 4)
	334 iconst_1 (13, 4)
	335 isub (13, 4)
	336 aaload (13, 4)
	337 iload (13, 4)
	338 #20 (13, 4)
	339 dload (13, 4)
	340 #10 (13, 4)
	341 dload (13, 4)
	342 #12 (13, 4)
	343 dmul (13, 4)
	344 dload (13, 4)
	345 #8 (13, 4)
	346 aload_0 (13, 4)
	347 getfield (13, 4)
	348 org/apache/commons/math3/linear/SchurTransformer.matrixT:[[D (13, 4)
	350 iload (13, 4)
	351 #6 (13, 4)
	352 aaload (13, 4)
	353 iload (13, 4)
	354 #20 (13, 4)
	355 daload (13, 4)
	356 dmul (13, 4)
	357 dadd (13, 4)
	358 dastore (13, 4)
	359 aload_0 (13, 4)
	360 getfield (13, 4)
	361 org/apache/commons/math3/linear/SchurTransformer.matrixT:[[D (13, 4)
	363 iload (13, 4)
	364 #6 (13, 4)
	365 aaload (13, 4)
	366 iload (13, 4)
	367 #20 (13, 4)
	368 dload (13, 4)
	369 #10 (13, 4)
	370 aload_0 (13, 4)
	371 getfield (13, 4)
	372 org/apache/commons/math3/linear/SchurTransformer.matrixT:[[D (13, 4)
	374 iload (13, 4)
	375 #6 (13, 4)
	376 aaload (13, 4)
	377 iload (13, 4)
	378 #20 (13, 4)
	379 daload (13, 4)
	380 dmul (13, 4)
	381 dload (13, 4)
	382 #8 (13, 4)
	383 dload (13, 4)
	384 #12 (13, 4)
	385 dmul (13, 4)
	386 dsub (13, 4)
	387 dastore (13, 4)
	388 iinc (13, 4)
	389 #20 (13, 4)
	390 -89 (13, 4)
	391 goto (13, 4)
	392 -83 (13, 4)
	394 iconst_0 (14, 4)
	395 istore (14, 4)
	396 #20 (14, 4)
	397 iload (14, 4)
	398 #20 (14, 4)
	399 iload (14, 4)
	400 #6 (14, 4)
	401 if_icmpgt (14, 4)
	402 83 (14, 4)
	404 aload_0 (14, 4)
	405 getfield (14, 4)
	406 org/apache/commons/math3/linear/SchurTransformer.matrixT:[[D (14, 4)
	408 iload (14, 4)
	409 #20 (14, 4)
	410 aaload (14, 4)
	411 iload (14, 4)
	412 #6 (14, 4)
	413 iconst_1 (14, 4)
	414 isub (14, 4)
	415 daload (14, 4)
	416 dstore (14, 4)
	417 #12 (14, 4)
	418 aload_0 (14, 4)
	419 getfield (14, 4)
	420 org/apache/commons/math3/linear/SchurTransformer.matrixT:[[D (14, 4)
	422 iload (14, 4)
	423 #20 (14, 4)
	424 aaload (14, 4)
	425 iload (14, 4)
	426 #6 (14, 4)
	427 iconst_1 (14, 4)
	428 isub (14, 4)
	429 dload (14, 4)
	430 #10 (14, 4)
	431 dload (14, 4)
	432 #12 (14, 4)
	433 dmul (14, 4)
	434 dload (14, 4)
	435 #8 (14, 4)
	436 aload_0 (14, 4)
	437 getfield (14, 4)
	438 org/apache/commons/math3/linear/SchurTransformer.matrixT:[[D (14, 4)
	440 iload (14, 4)
	441 #20 (14, 4)
	442 aaload (14, 4)
	443 iload (14, 4)
	444 #6 (14, 4)
	445 daload (14, 4)
	446 dmul (14, 4)
	447 dadd (14, 4)
	448 dastore (14, 4)
	449 aload_0 (14, 4)
	450 getfield (14, 4)
	451 org/apache/commons/math3/linear/SchurTransformer.matrixT:[[D (14, 4)
	453 iload (14, 4)
	454 #20 (14, 4)
	455 aaload (14, 4)
	456 iload (14, 4)
	457 #6 (14, 4)
	458 dload (14, 4)
	459 #10 (14, 4)
	460 aload_0 (14, 4)
	461 getfield (14, 4)
	462 org/apache/commons/math3/linear/SchurTransformer.matrixT:[[D (14, 4)
	464 iload (14, 4)
	465 #20 (14, 4)
	466 aaload (14, 4)
	467 iload (14, 4)
	468 #6 (14, 4)
	469 daload (14, 4)
	470 dmul (14, 4)
	471 dload (14, 4)
	472 #8 (14, 4)
	473 dload (14, 4)
	474 #12 (14, 4)
	475 dmul (14, 4)
	476 dsub (14, 4)
	477 dastore (14, 4)
	478 iinc (14, 4)
	479 #20 (14, 4)
	480 -89 (14, 4)
	481 goto (14, 4)
	482 -84 (14, 4)
	484 iconst_0 (15, 4)
	485 istore (15, 4)
	486 #20 (15, 4)
	487 iload (15, 4)
	488 #20 (15, 4)
	489 iload_1 (15, 4)
	490 iconst_1 (15, 4)
	491 isub (15, 4)
	492 if_icmpgt (15, 4)
	493 83 (15, 4)
	495 aload_0 (15, 4)
	496 getfield (15, 4)
	497 org/apache/commons/math3/linear/SchurTransformer.matrixP:[[D (15, 4)
	499 iload (15, 4)
	500 #20 (15, 4)
	501 aaload (15, 4)
	502 iload (15, 4)
	503 #6 (15, 4)
	504 iconst_1 (15, 4)
	505 isub (15, 4)
	506 daload (15, 4)
	507 dstore (15, 4)
	508 #12 (15, 4)
	509 aload_0 (15, 4)
	510 getfield (15, 4)
	511 org/apache/commons/math3/linear/SchurTransformer.matrixP:[[D (15, 4)
	513 iload (15, 4)
	514 #20 (15, 4)
	515 aaload (15, 4)
	516 iload (15, 4)
	517 #6 (15, 4)
	518 iconst_1 (15, 4)
	519 isub (15, 4)
	520 dload (15, 4)
	521 #10 (15, 4)
	522 dload (15, 4)
	523 #12 (15, 4)
	524 dmul (15, 4)
	525 dload (15, 4)
	526 #8 (15, 4)
	527 aload_0 (15, 4)
	528 getfield (15, 4)
	529 org/apache/commons/math3/linear/SchurTransformer.matrixP:[[D (15, 4)
	531 iload (15, 4)
	532 #20 (15, 4)
	533 aaload (15, 4)
	534 iload (15, 4)
	535 #6 (15, 4)
	536 daload (15, 4)
	537 dmul (15, 4)
	538 dadd (15, 4)
	539 dastore (15, 4)
	540 aload_0 (15, 4)
	541 getfield (15, 4)
	542 org/apache/commons/math3/linear/SchurTransformer.matrixP:[[D (15, 4)
	544 iload (15, 4)
	545 #20 (15, 4)
	546 aaload (15, 4)
	547 iload (15, 4)
	548 #6 (15, 4)
	549 dload (15, 4)
	550 #10 (15, 4)
	551 aload_0 (15, 4)
	552 getfield (15, 4)
	553 org/apache/commons/math3/linear/SchurTransformer.matrixP:[[D (15, 4)
	555 iload (15, 4)
	556 #20 (15, 4)
	557 aaload (15, 4)
	558 iload (15, 4)
	559 #6 (15, 4)
	560 daload (15, 4)
	561 dmul (15, 4)
	562 dload (15, 4)
	563 #8 (15, 4)
	564 dload (15, 4)
	565 #12 (15, 4)
	566 dmul (15, 4)
	567 dsub (15, 4)
	568 dastore (15, 4)
	569 iinc (15, 4)
	570 #20 (15, 4)
	571 -89 (15, 4)
	572 goto (15, 4)
	573 -85 (15, 4)
	575 iinc (10, 1)
	576 #6 (10, 1)
	577 3 (10, 1)
	578 iconst_0 (10, 1)
	579 istore (10, 1)
	580 #5 (10, 1)
	581 goto (11, 2)
	582 78 (11, 2)
	584 aload_0 (12, 1)
	585 iload (12, 1)
	586 #7 (12, 1)
	587 iload (12, 1)
	588 #6 (12, 1)
	589 iload (12, 1)
	590 #5 (12, 1)
	591 aload (12, 1)
	592 #4 (12, 1)
	593 invokespecial (12, 1)
	594 org/apache/commons/math3/linear/SchurTransformer.computeShift:(IIILorg/apache/commons/math3/linear/SchurTransformer$ShiftInfo;)V (12, 1)
	596 iinc (14, 1)
	597 #5 (14, 1)
	598 21 (14, 1)
	599 iload (14, 1)
	600 #5 (14, 1)
	601 bipush (14, 1)
	602 100 (14, 1)
	603 if_icmple (14, 1)
	604 23 (14, 1)
	606 new (14, 1)
	607 org/apache/commons/math3/exception/MaxCountExceededException (14, 1)
	609 dup (14, 1)
	610 getstatic (14, 1)
	611 org/apache/commons/math3/exception/util/LocalizedFormats.CONVERGENCE_FAILED:Lorg/apache/commons/math3/exception/util/LocalizedFormats; (14, 1)
	613 bipush (14, 1)
	614 100 (14, 1)
	615 invokestatic (14, 1)
	616 java/lang/Integer.valueOf:(I)Ljava/lang/Integer; (14, 1)
	618 iconst_0 (14, 1)
	619 anewarray (14, 1)
	620 java/lang/Object (14, 1)
	622 invokespecial (14, 1)
	623 org/apache/commons/math3/exception/MaxCountExceededException.<init>:(Lorg/apache/commons/math3/exception/util/Localizable;Ljava/lang/Number;[Ljava/lang/Object;)V (14, 1)
	625 athrow (14, 1)
	626 iconst_3 (14, 4)
	627 newarray (14, 4)
	628 7 (14, 4)
	629 astore (14, 4)
	630 #8 (14, 4)
	631 aload_0 (15, 1)
	632 iload (15, 1)
	633 #7 (15, 1)
	634 iload (15, 1)
	635 #6 (15, 1)
	636 aload (15, 1)
	637 #4 (15, 1)
	638 aload (15, 1)
	639 #8 (15, 1)
	640 invokespecial (15, 1)
	641 org/apache/commons/math3/linear/SchurTransformer.initQRStep:(IILorg/apache/commons/math3/linear/SchurTransformer$ShiftInfo;[D)I (15, 1)
	643 istore (15, 1)
	644 #9 (15, 1)
	645 aload_0 (16, 1)
	646 iload (16, 1)
	647 #7 (16, 1)
	648 iload (16, 1)
	649 #9 (16, 1)
	650 iload (16, 1)
	651 #6 (16, 1)
	652 aload (16, 1)
	653 #4 (16, 1)
	654 aload (16, 1)
	655 #8 (16, 1)
	656 invokespecial (16, 1)
	657 org/apache/commons/math3/linear/SchurTransformer.performDoubleQRStep:(IIILorg/apache/commons/math3/linear/SchurTransformer$ShiftInfo;[D)V (16, 1)
	659 goto (2, 1)
	660 -630 (2, 1)
	662 return (0, 1)

Method: getNorm
	0 dconst_0 (0, 0)
	1 dstore_1 (0, 0)
	2 iconst_0 (1, 4)
	3 istore_3 (1, 4)
	4 iload_3 (1, 4)
	5 aload_0 (1, 4)
	6 getfield (1, 4)
	7 org/apache/commons/math3/linear/SchurTransformer.matrixT:[[D (1, 4)
	9 arraylength (1, 4)
	10 if_icmpge (1, 4)
	11 49 (1, 4)
	13 iload_3 (2, 4)
	14 iconst_1 (2, 4)
	15 isub (2, 4)
	16 iconst_0 (2, 4)
	17 invokestatic (2, 4)
	18 org/apache/commons/math3/util/FastMath.max:(II)I (2, 4)
	20 istore (2, 4)
	21 #4 (2, 4)
	22 iload (2, 4)
	23 #4 (2, 4)
	24 aload_0 (2, 4)
	25 getfield (2, 4)
	26 org/apache/commons/math3/linear/SchurTransformer.matrixT:[[D (2, 4)
	28 arraylength (2, 4)
	29 if_icmpge (2, 4)
	30 24 (2, 4)
	32 dload_1 (2, 4)
	33 aload_0 (2, 4)
	34 getfield (2, 4)
	35 org/apache/commons/math3/linear/SchurTransformer.matrixT:[[D (2, 4)
	37 iload_3 (2, 4)
	38 aaload (2, 4)
	39 iload (2, 4)
	40 #4 (2, 4)
	41 daload (2, 4)
	42 invokestatic (2, 4)
	43 org/apache/commons/math3/util/FastMath.abs:(D)D (2, 4)
	45 dadd (2, 4)
	46 dstore_1 (2, 4)
	47 iinc (2, 4)
	48 #4 (2, 4)
	49 -89 (2, 4)
	50 goto (2, 4)
	51 -28 (2, 4)
	53 iinc (2, 4)
	54 #3 (2, 4)
	55 -89 (2, 4)
	56 goto (2, 4)
	57 -52 (2, 4)
	59 dload_1 (1, 4)
	60 dreturn (1, 4)

Method: findSmallSubDiagonalElement
	0 iload_1 (0, 0)
	1 istore (0, 0)
	2 #4 (0, 0)
	3 iload (1, 3)
	4 #4 (1, 3)
	5 ifle (1, 3)
	6 81 (1, 3)
	8 aload_0 (1, 3)
	9 getfield (1, 3)
	10 org/apache/commons/math3/linear/SchurTransformer.matrixT:[[D (1, 3)
	12 iload (1, 3)
	13 #4 (1, 3)
	14 iconst_1 (1, 3)
	15 isub (1, 3)
	16 aaload (1, 3)
	17 iload (1, 3)
	18 #4 (1, 3)
	19 iconst_1 (1, 3)
	20 isub (1, 3)
	21 daload (1, 3)
	22 invokestatic (1, 3)
	23 org/apache/commons/math3/util/FastMath.abs:(D)D (1, 3)
	25 aload_0 (1, 3)
	26 getfield (1, 3)
	27 org/apache/commons/math3/linear/SchurTransformer.matrixT:[[D (1, 3)
	29 iload (1, 3)
	30 #4 (1, 3)
	31 aaload (1, 3)
	32 iload (1, 3)
	33 #4 (1, 3)
	34 daload (1, 3)
	35 invokestatic (1, 3)
	36 org/apache/commons/math3/util/FastMath.abs:(D)D (1, 3)
	38 dadd (1, 3)
	39 dstore (1, 3)
	40 #5 (1, 3)
	41 dload (2, 1)
	42 #5 (2, 1)
	43 dconst_0 (2, 1)
	44 dcmpl (2, 1)
	45 ifne (2, 1)
	46 6 (2, 1)
	48 dload_2 (2, 1)
	49 dstore (2, 1)
	50 #5 (2, 1)
	51 aload_0 (2, 1)
	52 getfield (2, 1)
	53 org/apache/commons/math3/linear/SchurTransformer.matrixT:[[D (2, 1)
	55 iload (2, 1)
	56 #4 (2, 1)
	57 aaload (2, 1)
	58 iload (2, 1)
	59 #4 (2, 1)
	60 iconst_1 (2, 1)
	61 isub (2, 1)
	62 daload (2, 1)
	63 invokestatic (2, 1)
	64 org/apache/commons/math3/util/FastMath.abs:(D)D (2, 1)
	66 aload_0 (2, 1)
	67 getfield (2, 1)
	68 org/apache/commons/math3/linear/SchurTransformer.epsilon:D (2, 1)
	70 dload (2, 1)
	71 #5 (2, 1)
	72 dmul (2, 1)
	73 dcmpg (2, 1)
	74 ifge (2, 1)
	75 6 (2, 1)
	77 goto (2, 1)
	78 9 (2, 1)
	80 iinc (1, 3)
	81 #4 (1, 3)
	82 -89 (1, 3)
	83 goto (0, 0)
	84 -80 (0, 0)
	86 iload (0, 0)
	87 #4 (0, 0)
	88 ireturn (0, 0)

Method: computeShift
	0 aload (1, 1)
	1 #4 (1, 1)
	2 aload_0 (1, 1)
	3 getfield (1, 1)
	4 org/apache/commons/math3/linear/SchurTransformer.matrixT:[[D (1, 1)
	6 iload_2 (1, 1)
	7 aaload (1, 1)
	8 iload_2 (1, 1)
	9 daload (1, 1)
	10 putfield (1, 1)
	11 org/apache/commons/math3/linear/SchurTransformer$ShiftInfo.x:D (1, 1)
	13 aload (2, 1)
	14 #4 (2, 1)
	15 aload (2, 1)
	16 #4 (2, 1)
	17 dconst_0 (2, 1)
	18 dup2_x1 (2, 1)
	19 putfield (2, 1)
	20 org/apache/commons/math3/linear/SchurTransformer$ShiftInfo.w:D (2, 1)
	22 putfield (2, 1)
	23 org/apache/commons/math3/linear/SchurTransformer$ShiftInfo.y:D (2, 1)
	25 iload_1 (3, 1)
	26 iload_2 (3, 1)
	27 if_icmpge (3, 1)
	28 46 (3, 1)
	30 aload (4, 1)
	31 #4 (4, 1)
	32 aload_0 (4, 1)
	33 getfield (4, 1)
	34 org/apache/commons/math3/linear/SchurTransformer.matrixT:[[D (4, 1)
	36 iload_2 (4, 1)
	37 iconst_1 (4, 1)
	38 isub (4, 1)
	39 aaload (4, 1)
	40 iload_2 (4, 1)
	41 iconst_1 (4, 1)
	42 isub (4, 1)
	43 daload (4, 1)
	44 putfield (4, 1)
	45 org/apache/commons/math3/linear/SchurTransformer$ShiftInfo.y:D (4, 1)
	47 aload (5, 1)
	48 #4 (5, 1)
	49 aload_0 (5, 1)
	50 getfield (5, 1)
	51 org/apache/commons/math3/linear/SchurTransformer.matrixT:[[D (5, 1)
	53 iload_2 (5, 1)
	54 aaload (5, 1)
	55 iload_2 (5, 1)
	56 iconst_1 (5, 1)
	57 isub (5, 1)
	58 daload (5, 1)
	59 aload_0 (5, 1)
	60 getfield (5, 1)
	61 org/apache/commons/math3/linear/SchurTransformer.matrixT:[[D (5, 1)
	63 iload_2 (5, 1)
	64 iconst_1 (5, 1)
	65 isub (5, 1)
	66 aaload (5, 1)
	67 iload_2 (5, 1)
	68 daload (5, 1)
	69 dmul (5, 1)
	70 putfield (5, 1)
	71 org/apache/commons/math3/linear/SchurTransformer$ShiftInfo.w:D (5, 1)
	73 iload_3 (4, 1)
	74 bipush (4, 1)
	75 10 (4, 1)
	76 if_icmpne (4, 1)
	77 118 (4, 1)
	79 aload (5, 1)
	80 #4 (5, 1)
	81 dup (5, 1)
	82 getfield (5, 1)
	83 org/apache/commons/math3/linear/SchurTransformer$ShiftInfo.exShift:D (5, 1)
	85 aload (5, 1)
	86 #4 (5, 1)
	87 getfield (5, 1)
	88 org/apache/commons/math3/linear/SchurTransformer$ShiftInfo.x:D (5, 1)
	90 dadd (5, 1)
	91 putfield (5, 1)
	92 org/apache/commons/math3/linear/SchurTransformer$ShiftInfo.exShift:D (5, 1)
	94 iconst_0 (6, 4)
	95 istore (6, 4)
	96 #5 (6, 4)
	97 iload (6, 4)
	98 #5 (6, 4)
	99 iload_2 (6, 4)
	100 if_icmpgt (6, 4)
	101 27 (6, 4)
	103 aload_0 (7, 1)
	104 getfield (7, 1)
	105 org/apache/commons/math3/linear/SchurTransformer.matrixT:[[D (7, 1)
	107 iload (7, 1)
	108 #5 (7, 1)
	109 aaload (7, 1)
	110 iload (7, 1)
	111 #5 (7, 1)
	112 dup2 (7, 1)
	113 daload (7, 1)
	114 aload (7, 1)
	115 #4 (7, 1)
	116 getfield (7, 1)
	117 org/apache/commons/math3/linear/SchurTransformer$ShiftInfo.x:D (7, 1)
	119 dsub (7, 1)
	120 dastore (7, 1)
	121 iinc (7, 1)
	122 #5 (7, 1)
	123 -89 (7, 1)
	124 goto (7, 1)
	125 -27 (7, 1)
	127 aload_0 (5, 1)
	128 getfield (5, 1)
	129 org/apache/commons/math3/linear/SchurTransformer.matrixT:[[D (5, 1)
	131 iload_2 (5, 1)
	132 aaload (5, 1)
	133 iload_2 (5, 1)
	134 iconst_1 (5, 1)
	135 isub (5, 1)
	136 daload (5, 1)
	137 invokestatic (5, 1)
	138 org/apache/commons/math3/util/FastMath.abs:(D)D (5, 1)
	140 aload_0 (5, 1)
	141 getfield (5, 1)
	142 org/apache/commons/math3/linear/SchurTransformer.matrixT:[[D (5, 1)
	144 iload_2 (5, 1)
	145 iconst_1 (5, 1)
	146 isub (5, 1)
	147 aaload (5, 1)
	148 iload_2 (5, 1)
	149 iconst_2 (5, 1)
	150 isub (5, 1)
	151 daload (5, 1)
	152 invokestatic (5, 1)
	153 org/apache/commons/math3/util/FastMath.abs:(D)D (5, 1)
	155 dadd (5, 1)
	156 dstore (5, 1)
	157 #5 (5, 1)
	158 aload (6, 1)
	159 #4 (6, 1)
	160 ldc2_w (6, 1)
	161 0.75 (6, 1)
	163 dload (6, 1)
	164 #5 (6, 1)
	165 dmul (6, 1)
	166 putfield (6, 1)
	167 org/apache/commons/math3/linear/SchurTransformer$ShiftInfo.x:D (6, 1)
	169 aload (7, 1)
	170 #4 (7, 1)
	171 ldc2_w (7, 1)
	172 0.75 (7, 1)
	174 dload (7, 1)
	175 #5 (7, 1)
	176 dmul (7, 1)
	177 putfield (7, 1)
	178 org/apache/commons/math3/linear/SchurTransformer$ShiftInfo.y:D (7, 1)
	180 aload (8, 1)
	181 #4 (8, 1)
	182 ldc2_w (8, 1)
	183 -0.4375 (8, 1)
	185 dload (8, 1)
	186 #5 (8, 1)
	187 dmul (8, 1)
	188 dload (8, 1)
	189 #5 (8, 1)
	190 dmul (8, 1)
	191 putfield (8, 1)
	192 org/apache/commons/math3/linear/SchurTransformer$ShiftInfo.w:D (8, 1)
	194 iload_3 (5, 1)
	195 bipush (5, 1)
	196 30 (5, 1)
	197 if_icmpne (5, 1)
	198 160 (5, 1)
	200 aload (6, 1)
	201 #4 (6, 1)
	202 getfield (6, 1)
	203 org/apache/commons/math3/linear/SchurTransformer$ShiftInfo.y:D (6, 1)
	205 aload (6, 1)
	206 #4 (6, 1)
	207 getfield (6, 1)
	208 org/apache/commons/math3/linear/SchurTransformer$ShiftInfo.x:D (6, 1)
	210 dsub (6, 1)
	211 ldc2_w (6, 1)
	212 2.0 (6, 1)
	214 ddiv (6, 1)
	215 dstore (6, 1)
	216 #5 (6, 1)
	217 dload (7, 1)
	218 #5 (7, 1)
	219 dload (7, 1)
	220 #5 (7, 1)
	221 dmul (7, 1)
	222 aload (7, 1)
	223 #4 (7, 1)
	224 getfield (7, 1)
	225 org/apache/commons/math3/linear/SchurTransformer$ShiftInfo.w:D (7, 1)
	227 dadd (7, 1)
	228 dstore (7, 1)
	229 #5 (7, 1)
	230 dload (8, 1)
	231 #5 (8, 1)
	232 dconst_0 (8, 1)
	233 dcmpl (8, 1)
	234 ifle (8, 1)
	235 123 (8, 1)
	237 dload (8, 1)
	238 #5 (8, 1)
	239 invokestatic (8, 1)
	240 org/apache/commons/math3/util/FastMath.sqrt:(D)D (8, 1)
	242 dstore (8, 1)
	243 #5 (8, 1)
	244 aload (9, 1)
	245 #4 (9, 1)
	246 getfield (9, 1)
	247 org/apache/commons/math3/linear/SchurTransformer$ShiftInfo.y:D (9, 1)
	249 aload (9, 1)
	250 #4 (9, 1)
	251 getfield (9, 1)
	252 org/apache/commons/math3/linear/SchurTransformer$ShiftInfo.x:D (9, 1)
	254 dcmpg (9, 1)
	255 ifge (9, 1)
	256 8 (9, 1)
	258 dload (9, 1)
	259 #5 (9, 1)
	260 dneg (9, 1)
	261 dstore (9, 1)
	262 #5 (9, 1)
	263 aload (9, 1)
	264 #4 (9, 1)
	265 getfield (9, 1)
	266 org/apache/commons/math3/linear/SchurTransformer$ShiftInfo.x:D (9, 1)
	268 aload (9, 1)
	269 #4 (9, 1)
	270 getfield (9, 1)
	271 org/apache/commons/math3/linear/SchurTransformer$ShiftInfo.w:D (9, 1)
	273 aload (9, 1)
	274 #4 (9, 1)
	275 getfield (9, 1)
	276 org/apache/commons/math3/linear/SchurTransformer$ShiftInfo.y:D (9, 1)
	278 aload (9, 1)
	279 #4 (9, 1)
	280 getfield (9, 1)
	281 org/apache/commons/math3/linear/SchurTransformer$ShiftInfo.x:D (9, 1)
	283 dsub (9, 1)
	284 ldc2_w (9, 1)
	285 2.0 (9, 1)
	287 ddiv (9, 1)
	288 dload (9, 1)
	289 #5 (9, 1)
	290 dadd (9, 1)
	291 ddiv (9, 1)
	292 dsub (9, 1)
	293 dstore (9, 1)
	294 #5 (9, 1)
	295 iconst_0 (10, 4)
	296 istore (10, 4)
	297 #7 (10, 4)
	298 iload (10, 4)
	299 #7 (10, 4)
	300 iload_2 (10, 4)
	301 if_icmpgt (10, 4)
	302 24 (10, 4)
	304 aload_0 (10, 4)
	305 getfield (10, 4)
	306 org/apache/commons/math3/linear/SchurTransformer.matrixT:[[D (10, 4)
	308 iload (10, 4)
	309 #7 (10, 4)
	310 aaload (10, 4)
	311 iload (10, 4)
	312 #7 (10, 4)
	313 dup2 (10, 4)
	314 daload (10, 4)
	315 dload (10, 4)
	316 #5 (10, 4)
	317 dsub (10, 4)
	318 dastore (10, 4)
	319 iinc (10, 4)
	320 #7 (10, 4)
	321 -89 (10, 4)
	322 goto (10, 4)
	323 -24 (10, 4)
	325 aload (10, 1)
	326 #4 (10, 1)
	327 dup (10, 1)
	328 getfield (10, 1)
	329 org/apache/commons/math3/linear/SchurTransformer$ShiftInfo.exShift:D (10, 1)
	331 dload (10, 1)
	332 #5 (10, 1)
	333 dadd (10, 1)
	334 putfield (10, 1)
	335 org/apache/commons/math3/linear/SchurTransformer$ShiftInfo.exShift:D (10, 1)
	337 aload (11, 1)
	338 #4 (11, 1)
	339 aload (11, 1)
	340 #4 (11, 1)
	341 aload (11, 1)
	342 #4 (11, 1)
	343 ldc2_w (11, 1)
	344 0.964 (11, 1)
	346 dup2_x1 (11, 1)
	347 putfield (11, 1)
	348 org/apache/commons/math3/linear/SchurTransformer$ShiftInfo.w:D (11, 1)
	350 dup2_x1 (11, 1)
	351 putfield (11, 1)
	352 org/apache/commons/math3/linear/SchurTransformer$ShiftInfo.y:D (11, 1)
	354 putfield (11, 1)
	355 org/apache/commons/math3/linear/SchurTransformer$ShiftInfo.x:D (11, 1)
	357 return (0, 1)

Method: initQRStep
	0 iload_2 (0, 0)
	1 iconst_2 (0, 0)
	2 isub (0, 0)
	3 istore (0, 0)
	4 #5 (0, 0)
	5 iload (1, 3)
	6 #5 (1, 3)
	7 iload_1 (1, 3)
	8 if_icmplt (1, 3)
	9 233 (1, 3)
	11 aload_0 (1, 3)
	12 getfield (1, 3)
	13 org/apache/commons/math3/linear/SchurTransformer.matrixT:[[D (1, 3)
	15 iload (1, 3)
	16 #5 (1, 3)
	17 aaload (1, 3)
	18 iload (1, 3)
	19 #5 (1, 3)
	20 daload (1, 3)
	21 dstore (1, 3)
	22 #6 (1, 3)
	23 aload_3 (2, 1)
	24 getfield (2, 1)
	25 org/apache/commons/math3/linear/SchurTransformer$ShiftInfo.x:D (2, 1)
	27 dload (2, 1)
	28 #6 (2, 1)
	29 dsub (2, 1)
	30 dstore (2, 1)
	31 #8 (2, 1)
	32 aload_3 (3, 1)
	33 getfield (3, 1)
	34 org/apache/commons/math3/linear/SchurTransformer$ShiftInfo.y:D (3, 1)
	36 dload (3, 1)
	37 #6 (3, 1)
	38 dsub (3, 1)
	39 dstore (3, 1)
	40 #10 (3, 1)
	41 aload (4, 1)
	42 #4 (4, 1)
	43 iconst_0 (4, 1)
	44 dload (4, 1)
	45 #8 (4, 1)
	46 dload (4, 1)
	47 #10 (4, 1)
	48 dmul (4, 1)
	49 aload_3 (4, 1)
	50 getfield (4, 1)
	51 org/apache/commons/math3/linear/SchurTransformer$ShiftInfo.w:D (4, 1)
	53 dsub (4, 1)
	54 aload_0 (4, 1)
	55 getfield (4, 1)
	56 org/apache/commons/math3/linear/SchurTransformer.matrixT:[[D (4, 1)
	58 iload (4, 1)
	59 #5 (4, 1)
	60 iconst_1 (4, 1)
	61 iadd (4, 1)
	62 aaload (4, 1)
	63 iload (4, 1)
	64 #5 (4, 1)
	65 daload (4, 1)
	66 ddiv (4, 1)
	67 aload_0 (4, 1)
	68 getfield (4, 1)
	69 org/apache/commons/math3/linear/SchurTransformer.matrixT:[[D (4, 1)
	71 iload (4, 1)
	72 #5 (4, 1)
	73 aaload (4, 1)
	74 iload (4, 1)
	75 #5 (4, 1)
	76 iconst_1 (4, 1)
	77 iadd (4, 1)
	78 daload (4, 1)
	79 dadd (4, 1)
	80 dastore (4, 1)
	81 aload (4, 1)
	82 #4 (4, 1)
	83 iconst_1 (4, 1)
	84 aload_0 (4, 1)
	85 getfield (4, 1)
	86 org/apache/commons/math3/linear/SchurTransformer.matrixT:[[D (4, 1)
	88 iload (4, 1)
	89 #5 (4, 1)
	90 iconst_1 (4, 1)
	91 iadd (4, 1)
	92 aaload (4, 1)
	93 iload (4, 1)
	94 #5 (4, 1)
	95 iconst_1 (4, 1)
	96 iadd (4, 1)
	97 daload (4, 1)
	98 dload (4, 1)
	99 #6 (4, 1)
	100 dsub (4, 1)
	101 dload (4, 1)
	102 #8 (4, 1)
	103 dsub (4, 1)
	104 dload (4, 1)
	105 #10 (4, 1)
	106 dsub (4, 1)
	107 dastore (4, 1)
	108 aload (4, 1)
	109 #4 (4, 1)
	110 iconst_2 (4, 1)
	111 aload_0 (4, 1)
	112 getfield (4, 1)
	113 org/apache/commons/math3/linear/SchurTransformer.matrixT:[[D (4, 1)
	115 iload (4, 1)
	116 #5 (4, 1)
	117 iconst_2 (4, 1)
	118 iadd (4, 1)
	119 aaload (4, 1)
	120 iload (4, 1)
	121 #5 (4, 1)
	122 iconst_1 (4, 1)
	123 iadd (4, 1)
	124 daload (4, 1)
	125 dastore (4, 1)
	126 iload (5, 1)
	127 #5 (5, 1)
	128 iload_1 (5, 1)
	129 if_icmpne (5, 1)
	130 6 (5, 1)
	132 goto (5, 1)
	133 109 (5, 1)
	135 aload_0 (4, 1)
	136 getfield (4, 1)
	137 org/apache/commons/math3/linear/SchurTransformer.matrixT:[[D (4, 1)
	139 iload (4, 1)
	140 #5 (4, 1)
	141 aaload (4, 1)
	142 iload (4, 1)
	143 #5 (4, 1)
	144 iconst_1 (4, 1)
	145 isub (4, 1)
	146 daload (4, 1)
	147 invokestatic (4, 1)
	148 org/apache/commons/math3/util/FastMath.abs:(D)D (4, 1)
	150 aload (4, 1)
	151 #4 (4, 1)
	152 iconst_1 (4, 1)
	153 daload (4, 1)
	154 invokestatic (4, 1)
	155 org/apache/commons/math3/util/FastMath.abs:(D)D (4, 1)
	157 aload (4, 1)
	158 #4 (4, 1)
	159 iconst_2 (4, 1)
	160 daload (4, 1)
	161 invokestatic (4, 1)
	162 org/apache/commons/math3/util/FastMath.abs:(D)D (4, 1)
	164 dadd (4, 1)
	165 dmul (4, 1)
	166 dstore (4, 1)
	167 #12 (4, 1)
	168 aload (4, 1)
	169 #4 (4, 1)
	170 iconst_0 (4, 1)
	171 daload (4, 1)
	172 invokestatic (4, 1)
	173 org/apache/commons/math3/util/FastMath.abs:(D)D (4, 1)
	175 aload_0 (4, 1)
	176 getfield (4, 1)
	177 org/apache/commons/math3/linear/SchurTransformer.matrixT:[[D (4, 1)
	179 iload (4, 1)
	180 #5 (4, 1)
	181 iconst_1 (4, 1)
	182 isub (4, 1)
	183 aaload (4, 1)
	184 iload (4, 1)
	185 #5 (4, 1)
	186 iconst_1 (4, 1)
	187 isub (4, 1)
	188 daload (4, 1)
	189 invokestatic (4, 1)
	190 org/apache/commons/math3/util/FastMath.abs:(D)D (4, 1)
	192 dload (4, 1)
	193 #6 (4, 1)
	194 invokestatic (4, 1)
	195 org/apache/commons/math3/util/FastMath.abs:(D)D (4, 1)
	197 dadd (4, 1)
	198 aload_0 (4, 1)
	199 getfield (4, 1)
	200 org/apache/commons/math3/linear/SchurTransformer.matrixT:[[D (4, 1)
	202 iload (4, 1)
	203 #5 (4, 1)
	204 iconst_1 (4, 1)
	205 iadd (4, 1)
	206 aaload (4, 1)
	207 iload (4, 1)
	208 #5 (4, 1)
	209 iconst_1 (4, 1)
	210 iadd (4, 1)
	211 daload (4, 1)
	212 invokestatic (4, 1)
	213 org/apache/commons/math3/util/FastMath.abs:(D)D (4, 1)
	215 dadd (4, 1)
	216 dmul (4, 1)
	217 dstore (4, 1)
	218 #14 (4, 1)
	219 dload (5, 1)
	220 #12 (5, 1)
	221 aload_0 (5, 1)
	222 getfield (5, 1)
	223 org/apache/commons/math3/linear/SchurTransformer.epsilon:D (5, 1)
	225 dload (5, 1)
	226 #14 (5, 1)
	227 dmul (5, 1)
	228 dcmpg (5, 1)
	229 ifge (5, 1)
	230 6 (5, 1)
	232 goto (5, 1)
	233 9 (5, 1)
	235 iinc (4, 1)
	236 #5 (4, 1)
	237 -89 (4, 1)
	238 goto (0, 0)
	239 -233 (0, 0)
	241 iload (0, 0)
	242 #5 (0, 0)
	243 ireturn (0, 0)

Method: performDoubleQRStep
	0 aload_0 (0, 0)
	1 getfield (0, 0)
	2 org/apache/commons/math3/linear/SchurTransformer.matrixT:[[D (0, 0)
	4 arraylength (0, 0)
	5 istore (0, 0)
	6 #6 (0, 0)
	7 aload (0, 0)
	8 #5 (0, 0)
	9 iconst_0 (0, 0)
	10 daload (0, 0)
	11 dstore (0, 0)
	12 #7 (0, 0)
	13 aload (0, 0)
	14 #5 (0, 0)
	15 iconst_1 (0, 0)
	16 daload (0, 0)
	17 dstore (0, 0)
	18 #9 (0, 0)
	19 aload (0, 0)
	20 #5 (0, 0)
	21 iconst_2 (0, 0)
	22 daload (0, 0)
	23 dstore (0, 0)
	24 #11 (0, 0)
	25 iload_2 (1, 4)
	26 istore (1, 4)
	27 #13 (1, 4)
	28 iload (1, 4)
	29 #13 (1, 4)
	30 iload_3 (1, 4)
	31 iconst_1 (1, 4)
	32 isub (1, 4)
	33 if_icmpgt (1, 4)
	34 720 (1, 4)
	36 iload (1, 4)
	37 #13 (1, 4)
	38 iload_3 (1, 4)
	39 iconst_1 (1, 4)
	40 isub (1, 4)
	41 if_icmpeq (1, 4)
	42 7 (1, 4)
	44 iconst_1 (1, 4)
	45 goto (1, 4)
	46 4 (1, 4)
	48 iconst_0 (1, 4)
	49 istore (1, 4)
	50 #14 (1, 4)
	51 iload (2, 1)
	52 #13 (2, 1)
	53 iload_2 (2, 1)
	54 if_icmpeq (2, 1)
	55 129 (2, 1)
	57 aload_0 (2, 1)
	58 getfield (2, 1)
	59 org/apache/commons/math3/linear/SchurTransformer.matrixT:[[D (2, 1)
	61 iload (2, 1)
	62 #13 (2, 1)
	63 aaload (2, 1)
	64 iload (2, 1)
	65 #13 (2, 1)
	66 iconst_1 (2, 1)
	67 isub (2, 1)
	68 daload (2, 1)
	69 dstore (2, 1)
	70 #7 (2, 1)
	71 aload_0 (2, 1)
	72 getfield (2, 1)
	73 org/apache/commons/math3/linear/SchurTransformer.matrixT:[[D (2, 1)
	75 iload (2, 1)
	76 #13 (2, 1)
	77 iconst_1 (2, 1)
	78 iadd (2, 1)
	79 aaload (2, 1)
	80 iload (2, 1)
	81 #13 (2, 1)
	82 iconst_1 (2, 1)
	83 isub (2, 1)
	84 daload (2, 1)
	85 dstore (2, 1)
	86 #9 (2, 1)
	87 iload (2, 1)
	88 #14 (2, 1)
	89 ifeq (2, 1)
	90 20 (2, 1)
	92 aload_0 (2, 1)
	93 getfield (2, 1)
	94 org/apache/commons/math3/linear/SchurTransformer.matrixT:[[D (2, 1)
	96 iload (2, 1)
	97 #13 (2, 1)
	98 iconst_2 (2, 1)
	99 iadd (2, 1)
	100 aaload (2, 1)
	101 iload (2, 1)
	102 #13 (2, 1)
	103 iconst_1 (2, 1)
	104 isub (2, 1)
	105 daload (2, 1)
	106 goto (2, 1)
	107 4 (2, 1)
	109 dconst_0 (2, 1)
	110 dstore (2, 1)
	111 #11 (2, 1)
	112 aload (3, 1)
	113 #4 (3, 1)
	114 dload (3, 1)
	115 #7 (3, 1)
	116 invokestatic (3, 1)
	117 org/apache/commons/math3/util/FastMath.abs:(D)D (3, 1)
	119 dload (3, 1)
	120 #9 (3, 1)
	121 invokestatic (3, 1)
	122 org/apache/commons/math3/util/FastMath.abs:(D)D (3, 1)
	124 dadd (3, 1)
	125 dload (3, 1)
	126 #11 (3, 1)
	127 invokestatic (3, 1)
	128 org/apache/commons/math3/util/FastMath.abs:(D)D (3, 1)
	130 dadd (3, 1)
	131 putfield (3, 1)
	132 org/apache/commons/math3/linear/SchurTransformer$ShiftInfo.x:D (3, 1)
	134 aload (4, 1)
	135 #4 (4, 1)
	136 getfield (4, 1)
	137 org/apache/commons/math3/linear/SchurTransformer$ShiftInfo.x:D (4, 1)
	139 dconst_0 (4, 1)
	140 aload_0 (4, 1)
	141 getfield (4, 1)
	142 org/apache/commons/math3/linear/SchurTransformer.epsilon:D (4, 1)
	144 invokestatic (4, 1)
	145 org/apache/commons/math3/util/Precision.equals:(DDD)Z (4, 1)
	147 ifeq (4, 1)
	148 6 (4, 1)
	150 goto (4, 1)
	151 597 (4, 1)
	153 dload (4, 1)
	154 #7 (4, 1)
	155 aload (4, 1)
	156 #4 (4, 1)
	157 getfield (4, 1)
	158 org/apache/commons/math3/linear/SchurTransformer$ShiftInfo.x:D (4, 1)
	160 ddiv (4, 1)
	161 dstore (4, 1)
	162 #7 (4, 1)
	163 dload (5, 1)
	164 #9 (5, 1)
	165 aload (5, 1)
	166 #4 (5, 1)
	167 getfield (5, 1)
	168 org/apache/commons/math3/linear/SchurTransformer$ShiftInfo.x:D (5, 1)
	170 ddiv (5, 1)
	171 dstore (5, 1)
	172 #9 (5, 1)
	173 dload (6, 1)
	174 #11 (6, 1)
	175 aload (6, 1)
	176 #4 (6, 1)
	177 getfield (6, 1)
	178 org/apache/commons/math3/linear/SchurTransformer$ShiftInfo.x:D (6, 1)
	180 ddiv (6, 1)
	181 dstore (6, 1)
	182 #11 (6, 1)
	183 dload (1, 4)
	184 #7 (1, 4)
	185 dload (1, 4)
	186 #7 (1, 4)
	187 dmul (1, 4)
	188 dload (1, 4)
	189 #9 (1, 4)
	190 dload (1, 4)
	191 #9 (1, 4)
	192 dmul (1, 4)
	193 dadd (1, 4)
	194 dload (1, 4)
	195 #11 (1, 4)
	196 dload (1, 4)
	197 #11 (1, 4)
	198 dmul (1, 4)
	199 dadd (1, 4)
	200 invokestatic (1, 4)
	201 org/apache/commons/math3/util/FastMath.sqrt:(D)D (1, 4)
	203 dstore (1, 4)
	204 #15 (1, 4)
	205 dload (2, 1)
	206 #7 (2, 1)
	207 dconst_0 (2, 1)
	208 dcmpg (2, 1)
	209 ifge (2, 1)
	210 8 (2, 1)
	212 dload (2, 1)
	213 #15 (2, 1)
	214 dneg (2, 1)
	215 dstore (2, 1)
	216 #15 (2, 1)
	217 dload (2, 1)
	218 #15 (2, 1)
	219 dconst_0 (2, 1)
	220 dcmpl (2, 1)
	221 ifeq (2, 1)
	222 526 (2, 1)
	224 iload (3, 1)
	225 #13 (3, 1)
	226 iload_2 (3, 1)
	227 if_icmpeq (3, 1)
	228 27 (3, 1)
	230 aload_0 (4, 1)
	231 getfield (4, 1)
	232 org/apache/commons/math3/linear/SchurTransformer.matrixT:[[D (4, 1)
	234 iload (4, 1)
	235 #13 (4, 1)
	236 aaload (4, 1)
	237 iload (4, 1)
	238 #13 (4, 1)
	239 iconst_1 (4, 1)
	240 isub (4, 1)
	241 dload (4, 1)
	242 #15 (4, 1)
	243 dneg (4, 1)
	244 aload (4, 1)
	245 #4 (4, 1)
	246 getfield (4, 1)
	247 org/apache/commons/math3/linear/SchurTransformer$ShiftInfo.x:D (4, 1)
	249 dmul (4, 1)
	250 dastore (4, 1)
	251 goto (4, 1)
	252 33 (4, 1)
	254 iload_1 (5, 1)
	255 iload_2 (5, 1)
	256 if_icmpeq (5, 1)
	257 28 (5, 1)
	259 aload_0 (5, 1)
	260 getfield (5, 1)
	261 org/apache/commons/math3/linear/SchurTransformer.matrixT:[[D (5, 1)
	263 iload (5, 1)
	264 #13 (5, 1)
	265 aaload (5, 1)
	266 iload (5, 1)
	267 #13 (5, 1)
	268 iconst_1 (5, 1)
	269 isub (5, 1)
	270 aload_0 (5, 1)
	271 getfield (5, 1)
	272 org/apache/commons/math3/linear/SchurTransformer.matrixT:[[D (5, 1)
	274 iload (5, 1)
	275 #13 (5, 1)
	276 aaload (5, 1)
	277 iload (5, 1)
	278 #13 (5, 1)
	279 iconst_1 (5, 1)
	280 isub (5, 1)
	281 daload (5, 1)
	282 dneg (5, 1)
	283 dastore (5, 1)
	284 dload (2, 1)
	285 #7 (2, 1)
	286 dload (2, 1)
	287 #15 (2, 1)
	288 dadd (2, 1)
	289 dstore (2, 1)
	290 #7 (2, 1)
	291 aload (3, 1)
	292 #4 (3, 1)
	293 dload (3, 1)
	294 #7 (3, 1)
	295 dload (3, 1)
	296 #15 (3, 1)
	297 ddiv (3, 1)
	298 putfield (3, 1)
	299 org/apache/commons/math3/linear/SchurTransformer$ShiftInfo.x:D (3, 1)
	301 aload (4, 1)
	302 #4 (4, 1)
	303 dload (4, 1)
	304 #9 (4, 1)
	305 dload (4, 1)
	306 #15 (4, 1)
	307 ddiv (4, 1)
	308 putfield (4, 1)
	309 org/apache/commons/math3/linear/SchurTransformer$ShiftInfo.y:D (4, 1)
	311 dload (4, 1)
	312 #11 (4, 1)
	313 dload (4, 1)
	314 #15 (4, 1)
	315 ddiv (4, 1)
	316 dstore (4, 1)
	317 #17 (4, 1)
	318 dload (4, 1)
	319 #9 (4, 1)
	320 dload (4, 1)
	321 #7 (4, 1)
	322 ddiv (4, 1)
	323 dstore (4, 1)
	324 #9 (4, 1)
	325 dload (4, 1)
	326 #11 (4, 1)
	327 dload (4, 1)
	328 #7 (4, 1)
	329 ddiv (4, 1)
	330 dstore (4, 1)
	331 #11 (4, 1)
	332 iload (6, 4)
	333 #13 (6, 4)
	334 istore (6, 4)
	335 #19 (6, 4)
	336 iload (6, 4)
	337 #19 (6, 4)
	338 iload (6, 4)
	339 #6 (6, 4)
	340 if_icmpge (6, 4)
	341 126 (6, 4)
	343 aload_0 (6, 4)
	344 getfield (6, 4)
	345 org/apache/commons/math3/linear/SchurTransformer.matrixT:[[D (6, 4)
	347 iload (6, 4)
	348 #13 (6, 4)
	349 aaload (6, 4)
	350 iload (6, 4)
	351 #19 (6, 4)
	352 daload (6, 4)
	353 dload (6, 4)
	354 #9 (6, 4)
	355 aload_0 (6, 4)
	356 getfield (6, 4)
	357 org/apache/commons/math3/linear/SchurTransformer.matrixT:[[D (6, 4)
	359 iload (6, 4)
	360 #13 (6, 4)
	361 iconst_1 (6, 4)
	362 iadd (6, 4)
	363 aaload (6, 4)
	364 iload (6, 4)
	365 #19 (6, 4)
	366 daload (6, 4)
	367 dmul (6, 4)
	368 dadd (6, 4)
	369 dstore (6, 4)
	370 #7 (6, 4)
	371 iload (7, 1)
	372 #14 (7, 1)
	373 ifeq (7, 1)
	374 43 (7, 1)
	376 dload (7, 1)
	377 #7 (7, 1)
	378 dload (7, 1)
	379 #11 (7, 1)
	380 aload_0 (7, 1)
	381 getfield (7, 1)
	382 org/apache/commons/math3/linear/SchurTransformer.matrixT:[[D (7, 1)
	384 iload (7, 1)
	385 #13 (7, 1)
	386 iconst_2 (7, 1)
	387 iadd (7, 1)
	388 aaload (7, 1)
	389 iload (7, 1)
	390 #19 (7, 1)
	391 daload (7, 1)
	392 dmul (7, 1)
	393 dadd (7, 1)
	394 dstore (7, 1)
	395 #7 (7, 1)
	396 aload_0 (7, 1)
	397 getfield (7, 1)
	398 org/apache/commons/math3/linear/SchurTransformer.matrixT:[[D (7, 1)
	400 iload (7, 1)
	401 #13 (7, 1)
	402 iconst_2 (7, 1)
	403 iadd (7, 1)
	404 aaload (7, 1)
	405 iload (7, 1)
	406 #19 (7, 1)
	407 dup2 (7, 1)
	408 daload (7, 1)
	409 dload (7, 1)
	410 #7 (7, 1)
	411 dload (7, 1)
	412 #17 (7, 1)
	413 dmul (7, 1)
	414 dsub (7, 1)
	415 dastore (7, 1)
	416 aload_0 (7, 1)
	417 getfield (7, 1)
	418 org/apache/commons/math3/linear/SchurTransformer.matrixT:[[D (7, 1)
	420 iload (7, 1)
	421 #13 (7, 1)
	422 aaload (7, 1)
	423 iload (7, 1)
	424 #19 (7, 1)
	425 dup2 (7, 1)
	426 daload (7, 1)
	427 dload (7, 1)
	428 #7 (7, 1)
	429 aload (7, 1)
	430 #4 (7, 1)
	431 getfield (7, 1)
	432 org/apache/commons/math3/linear/SchurTransformer$ShiftInfo.x:D (7, 1)
	434 dmul (7, 1)
	435 dsub (7, 1)
	436 dastore (7, 1)
	437 aload_0 (8, 1)
	438 getfield (8, 1)
	439 org/apache/commons/math3/linear/SchurTransformer.matrixT:[[D (8, 1)
	441 iload (8, 1)
	442 #13 (8, 1)
	443 iconst_1 (8, 1)
	444 iadd (8, 1)
	445 aaload (8, 1)
	446 iload (8, 1)
	447 #19 (8, 1)
	448 dup2 (8, 1)
	449 daload (8, 1)
	450 dload (8, 1)
	451 #7 (8, 1)
	452 aload (8, 1)
	453 #4 (8, 1)
	454 getfield (8, 1)
	455 org/apache/commons/math3/linear/SchurTransformer$ShiftInfo.y:D (8, 1)
	457 dmul (8, 1)
	458 dsub (8, 1)
	459 dastore (8, 1)
	460 iinc (8, 1)
	461 #19 (8, 1)
	462 -89 (8, 1)
	463 goto (8, 1)
	464 -127 (8, 1)
	466 iconst_0 (7, 4)
	467 istore (7, 4)
	468 #19 (7, 4)
	469 iload (7, 4)
	470 #19 (7, 4)
	471 iload_3 (7, 4)
	472 iload (7, 4)
	473 #13 (7, 4)
	474 iconst_3 (7, 4)
	475 iadd (7, 4)
	476 invokestatic (7, 4)
	477 org/apache/commons/math3/util/FastMath.min:(II)I (7, 4)
	479 if_icmpgt (7, 4)
	480 126 (7, 4)
	482 aload (8, 1)
	483 #4 (8, 1)
	484 getfield (8, 1)
	485 org/apache/commons/math3/linear/SchurTransformer$ShiftInfo.x:D (8, 1)
	487 aload_0 (8, 1)
	488 getfield (8, 1)
	489 org/apache/commons/math3/linear/SchurTransformer.matrixT:[[D (8, 1)
	491 iload (8, 1)
	492 #19 (8, 1)
	493 aaload (8, 1)
	494 iload (8, 1)
	495 #13 (8, 1)
	496 daload (8, 1)
	497 dmul (8, 1)
	498 aload (8, 1)
	499 #4 (8, 1)
	500 getfield (8, 1)
	501 org/apache/commons/math3/linear/SchurTransformer$ShiftInfo.y:D (8, 1)
	503 aload_0 (8, 1)
	504 getfield (8, 1)
	505 org/apache/commons/math3/linear/SchurTransformer.matrixT:[[D (8, 1)
	507 iload (8, 1)
	508 #19 (8, 1)
	509 aaload (8, 1)
	510 iload (8, 1)
	511 #13 (8, 1)
	512 iconst_1 (8, 1)
	513 iadd (8, 1)
	514 daload (8, 1)
	515 dmul (8, 1)
	516 dadd (8, 1)
	517 dstore (8, 1)
	518 #7 (8, 1)
	519 iload (9, 1)
	520 #14 (9, 1)
	521 ifeq (9, 1)
	522 43 (9, 1)
	524 dload (9, 1)
	525 #7 (9, 1)
	526 dload (9, 1)
	527 #17 (9, 1)
	528 aload_0 (9, 1)
	529 getfield (9, 1)
	530 org/apache/commons/math3/linear/SchurTransformer.matrixT:[[D (9, 1)
	532 iload (9, 1)
	533 #19 (9, 1)
	534 aaload (9, 1)
	535 iload (9, 1)
	536 #13 (9, 1)
	537 iconst_2 (9, 1)
	538 iadd (9, 1)
	539 daload (9, 1)
	540 dmul (9, 1)
	541 dadd (9, 1)
	542 dstore (9, 1)
	543 #7 (9, 1)
	544 aload_0 (9, 1)
	545 getfield (9, 1)
	546 org/apache/commons/math3/linear/SchurTransformer.matrixT:[[D (9, 1)
	548 iload (9, 1)
	549 #19 (9, 1)
	550 aaload (9, 1)
	551 iload (9, 1)
	552 #13 (9, 1)
	553 iconst_2 (9, 1)
	554 iadd (9, 1)
	555 dup2 (9, 1)
	556 daload (9, 1)
	557 dload (9, 1)
	558 #7 (9, 1)
	559 dload (9, 1)
	560 #11 (9, 1)
	561 dmul (9, 1)
	562 dsub (9, 1)
	563 dastore (9, 1)
	564 aload_0 (8, 1)
	565 getfield (8, 1)
	566 org/apache/commons/math3/linear/SchurTransformer.matrixT:[[D (8, 1)
	568 iload (8, 1)
	569 #19 (8, 1)
	570 aaload (8, 1)
	571 iload (8, 1)
	572 #13 (8, 1)
	573 dup2 (8, 1)
	574 daload (8, 1)
	575 dload (8, 1)
	576 #7 (8, 1)
	577 dsub (8, 1)
	578 dastore (8, 1)
	579 aload_0 (8, 1)
	580 getfield (8, 1)
	581 org/apache/commons/math3/linear/SchurTransformer.matrixT:[[D (8, 1)
	583 iload (8, 1)
	584 #19 (8, 1)
	585 aaload (8, 1)
	586 iload (8, 1)
	587 #13 (8, 1)
	588 iconst_1 (8, 1)
	589 iadd (8, 1)
	590 dup2 (8, 1)
	591 daload (8, 1)
	592 dload (8, 1)
	593 #7 (8, 1)
	594 dload (8, 1)
	595 #9 (8, 1)
	596 dmul (8, 1)
	597 dsub (8, 1)
	598 dastore (8, 1)
	599 iinc (8, 1)
	600 #19 (8, 1)
	601 -89 (8, 1)
	602 goto (8, 1)
	603 -133 (8, 1)
	605 aload_0 (7, 4)
	606 getfield (7, 4)
	607 org/apache/commons/math3/linear/SchurTransformer.matrixT:[[D (7, 4)
	609 arraylength (7, 4)
	610 iconst_1 (7, 4)
	611 isub (7, 4)
	612 istore (7, 4)
	613 #19 (7, 4)
	614 iconst_0 (8, 4)
	615 istore (8, 4)
	616 #20 (8, 4)
	617 iload (8, 4)
	618 #20 (8, 4)
	619 iload (8, 4)
	620 #19 (8, 4)
	621 if_icmpgt (8, 4)
	622 126 (8, 4)
	624 aload (9, 1)
	625 #4 (9, 1)
	626 getfield (9, 1)
	627 org/apache/commons/math3/linear/SchurTransformer$ShiftInfo.x:D (9, 1)
	629 aload_0 (9, 1)
	630 getfield (9, 1)
	631 org/apache/commons/math3/linear/SchurTransformer.matrixP:[[D (9, 1)
	633 iload (9, 1)
	634 #20 (9, 1)
	635 aaload (9, 1)
	636 iload (9, 1)
	637 #13 (9, 1)
	638 daload (9, 1)
	639 dmul (9, 1)
	640 aload (9, 1)
	641 #4 (9, 1)
	642 getfield (9, 1)
	643 org/apache/commons/math3/linear/SchurTransformer$ShiftInfo.y:D (9, 1)
	645 aload_0 (9, 1)
	646 getfield (9, 1)
	647 org/apache/commons/math3/linear/SchurTransformer.matrixP:[[D (9, 1)
	649 iload (9, 1)
	650 #20 (9, 1)
	651 aaload (9, 1)
	652 iload (9, 1)
	653 #13 (9, 1)
	654 iconst_1 (9, 1)
	655 iadd (9, 1)
	656 daload (9, 1)
	657 dmul (9, 1)
	658 dadd (9, 1)
	659 dstore (9, 1)
	660 #7 (9, 1)
	661 iload (10, 1)
	662 #14 (10, 1)
	663 ifeq (10, 1)
	664 43 (10, 1)
	666 dload (10, 1)
	667 #7 (10, 1)
	668 dload (10, 1)
	669 #17 (10, 1)
	670 aload_0 (10, 1)
	671 getfield (10, 1)
	672 org/apache/commons/math3/linear/SchurTransformer.matrixP:[[D (10, 1)
	674 iload (10, 1)
	675 #20 (10, 1)
	676 aaload (10, 1)
	677 iload (10, 1)
	678 #13 (10, 1)
	679 iconst_2 (10, 1)
	680 iadd (10, 1)
	681 daload (10, 1)
	682 dmul (10, 1)
	683 dadd (10, 1)
	684 dstore (10, 1)
	685 #7 (10, 1)
	686 aload_0 (10, 1)
	687 getfield (10, 1)
	688 org/apache/commons/math3/linear/SchurTransformer.matrixP:[[D (10, 1)
	690 iload (10, 1)
	691 #20 (10, 1)
	692 aaload (10, 1)
	693 iload (10, 1)
	694 #13 (10, 1)
	695 iconst_2 (10, 1)
	696 iadd (10, 1)
	697 dup2 (10, 1)
	698 daload (10, 1)
	699 dload (10, 1)
	700 #7 (10, 1)
	701 dload (10, 1)
	702 #11 (10, 1)
	703 dmul (10, 1)
	704 dsub (10, 1)
	705 dastore (10, 1)
	706 aload_0 (9, 1)
	707 getfield (9, 1)
	708 org/apache/commons/math3/linear/SchurTransformer.matrixP:[[D (9, 1)
	710 iload (9, 1)
	711 #20 (9, 1)
	712 aaload (9, 1)
	713 iload (9, 1)
	714 #13 (9, 1)
	715 dup2 (9, 1)
	716 daload (9, 1)
	717 dload (9, 1)
	718 #7 (9, 1)
	719 dsub (9, 1)
	720 dastore (9, 1)
	721 aload_0 (9, 1)
	722 getfield (9, 1)
	723 org/apache/commons/math3/linear/SchurTransformer.matrixP:[[D (9, 1)
	725 iload (9, 1)
	726 #20 (9, 1)
	727 aaload (9, 1)
	728 iload (9, 1)
	729 #13 (9, 1)
	730 iconst_1 (9, 1)
	731 iadd (9, 1)
	732 dup2 (9, 1)
	733 daload (9, 1)
	734 dload (9, 1)
	735 #7 (9, 1)
	736 dload (9, 1)
	737 #9 (9, 1)
	738 dmul (9, 1)
	739 dsub (9, 1)
	740 dastore (9, 1)
	741 iinc (9, 1)
	742 #20 (9, 1)
	743 -89 (9, 1)
	744 goto (9, 1)
	745 -127 (9, 1)
	747 iinc (9, 1)
	748 #13 (9, 1)
	749 -89 (9, 1)
	750 goto (9, 1)
	751 -722 (9, 1)
	753 iload_2 (8, 4)
	754 iconst_2 (8, 4)
	755 iadd (8, 4)
	756 istore (8, 4)
	757 #13 (8, 4)
	758 iload (8, 4)
	759 #13 (8, 4)
	760 iload_3 (8, 4)
	761 if_icmpgt (8, 4)
	762 43 (8, 4)
	764 aload_0 (8, 4)
	765 getfield (8, 4)
	766 org/apache/commons/math3/linear/SchurTransformer.matrixT:[[D (8, 4)
	768 iload (8, 4)
	769 #13 (8, 4)
	770 aaload (8, 4)
	771 iload (8, 4)
	772 #13 (8, 4)
	773 iconst_2 (8, 4)
	774 isub (8, 4)
	775 dconst_0 (8, 4)
	776 dastore (8, 4)
	777 iload (9, 1)
	778 #13 (9, 1)
	779 iload_2 (9, 1)
	780 iconst_2 (9, 1)
	781 iadd (9, 1)
	782 if_icmple (9, 1)
	783 16 (9, 1)
	785 aload_0 (9, 1)
	786 getfield (9, 1)
	787 org/apache/commons/math3/linear/SchurTransformer.matrixT:[[D (9, 1)
	789 iload (9, 1)
	790 #13 (9, 1)
	791 aaload (9, 1)
	792 iload (9, 1)
	793 #13 (9, 1)
	794 iconst_3 (9, 1)
	795 isub (9, 1)
	796 dconst_0 (9, 1)
	797 dastore (9, 1)
	798 iinc (9, 1)
	799 #13 (9, 1)
	800 -89 (9, 1)
	801 goto (9, 1)
	802 -43 (9, 1)
	804 return (2, 4)

