Method: visit
	0 aload_0 (0, 0)
	1 getfield (0, 0)
	2 org/apache/commons/math3/linear/SingularValueDecomposition$1.val$data:[[D (0, 0)
	4 iload_1 (0, 0)
	5 aaload (0, 0)
	6 iload_2 (0, 0)
	7 dload_3 (0, 0)
	8 aload_0 (0, 0)
	9 getfield (0, 0)
	10 org/apache/commons/math3/linear/SingularValueDecomposition$1.this$0:Lorg/apache/commons/math3/linear/SingularValueDecomposition; (0, 0)
	12 invokestatic (0, 0)
	13 org/apache/commons/math3/linear/SingularValueDecomposition.access$000:(Lorg/apache/commons/math3/linear/SingularValueDecomposition;)[D (0, 0)
	15 iload_1 (0, 0)
	16 daload (0, 0)
	17 ddiv (0, 0)
	18 dastore (0, 0)
	19 return (0, 0)

