Method: <init>
	0 aload_0 (0, 0)
	1 invokespecial (0, 0)
	2 java/lang/Object.<init>:()V (0, 0)
	4 aload_1 (1, 1)
	5 invokeinterface (1, 1)
	6 org/apache/commons/math3/linear/RealMatrix.getColumnDimension:()I (1, 1)
	8 0 (1, 1)
	10 aload_1 (1, 1)
	11 invokeinterface (1, 1)
	12 org/apache/commons/math3/linear/RealMatrix.transposed:Z (1, 1)
	14 0 (1, 1)
	16 if_icmpge (1, 1)
	17 43 (1, 1)
	19 aload_0 (1, 1)
	20 iconst_1 (1, 1)
	21 putfield (1, 1)
	22 org/apache/commons/math3/linear/SingularValueDecomposition.transposed:Z (1, 1)
	24 aload_1 (1, 1)
	25 invokeinterface (1, 1)
	26 org/apache/commons/math3/linear/RealMatrix.getData:()[[D (1, 1)
	28 0 (1, 1)
	30 invokeinterface (1, 1)
	31 org/apache/commons/math3/linear/RealMatrix.m:I (1, 1)
	33 0 (1, 1)
	35 astore_2 (1, 1)
	36 aload_0 (1, 1)
	37 aload_1 (1, 1)
	38 invokeinterface (1, 1)
	39 org/apache/commons/math3/linear/RealMatrix.transposed:Z (1, 1)
	41 0 (1, 1)
	43 putfield (1, 1)
	44 org/apache/commons/math3/linear/SingularValueDecomposition.m:I (1, 1)
	46 aload_0 (1, 1)
	47 aload_1 (1, 1)
	48 invokeinterface (1, 1)
	49 org/apache/commons/math3/linear/RealMatrix.getColumnDimension:()I (1, 1)
	51 0 (1, 1)
	53 putfield (1, 1)
	54 org/apache/commons/math3/linear/SingularValueDecomposition.n:I (1, 1)
	56 goto (1, 1)
	57 35 (1, 1)
	59 aload_0 (2, 2)
	60 iconst_0 (2, 2)
	61 putfield (2, 2)
	62 org/apache/commons/math3/linear/SingularValueDecomposition.transposed:Z (2, 2)
	64 aload_1 (2, 2)
	65 invokeinterface (2, 2)
	66 org/apache/commons/math3/linear/RealMatrix.m:I (2, 2)
	68 0 (2, 2)
	70 astore_2 (2, 2)
	71 aload_0 (2, 2)
	72 aload_1 (2, 2)
	73 invokeinterface (2, 2)
	74 org/apache/commons/math3/linear/RealMatrix.getColumnDimension:()I (2, 2)
	76 0 (2, 2)
	78 putfield (2, 2)
	79 org/apache/commons/math3/linear/SingularValueDecomposition.m:I (2, 2)
	81 aload_0 (2, 2)
	82 aload_1 (2, 2)
	83 invokeinterface (2, 2)
	84 org/apache/commons/math3/linear/RealMatrix.transposed:Z (2, 2)
	86 0 (2, 2)
	88 putfield (2, 2)
	89 org/apache/commons/math3/linear/SingularValueDecomposition.n:I (2, 2)
	91 aload_0 (0, 0)
	92 aload_0 (0, 0)
	93 getfield (0, 0)
	94 org/apache/commons/math3/linear/SingularValueDecomposition.n:I (0, 0)
	96 newarray (0, 0)
	97 7 (0, 0)
	98 putfield (0, 0)
	99 org/apache/commons/math3/linear/SingularValueDecomposition.singularValues:[D (0, 0)
	101 aload_0 (0, 0)
	102 getfield (0, 0)
	103 org/apache/commons/math3/linear/SingularValueDecomposition.m:I (0, 0)
	105 aload_0 (0, 0)
	106 getfield (0, 0)
	107 org/apache/commons/math3/linear/SingularValueDecomposition.n:I (0, 0)
	109 multianewarray (0, 0)
	110 [[D (0, 0)
	112 78 (0, 0)
	113 astore_3 (0, 0)
	114 aload_0 (0, 0)
	115 getfield (0, 0)
	116 org/apache/commons/math3/linear/SingularValueDecomposition.n:I (0, 0)
	118 aload_0 (0, 0)
	119 getfield (0, 0)
	120 org/apache/commons/math3/linear/SingularValueDecomposition.n:I (0, 0)
	122 multianewarray (0, 0)
	123 [[D (0, 0)
	125 58 (0, 0)
	126 astore (0, 0)
	127 #4 (0, 0)
	128 aload_0 (0, 0)
	129 getfield (0, 0)
	130 org/apache/commons/math3/linear/SingularValueDecomposition.n:I (0, 0)
	132 newarray (0, 0)
	133 7 (0, 0)
	134 astore (0, 0)
	135 #5 (0, 0)
	136 aload_0 (0, 0)
	137 getfield (0, 0)
	138 org/apache/commons/math3/linear/SingularValueDecomposition.m:I (0, 0)
	140 newarray (0, 0)
	141 7 (0, 0)
	142 astore (0, 0)
	143 #6 (0, 0)
	144 aload_0 (1, 4)
	145 getfield (1, 4)
	146 org/apache/commons/math3/linear/SingularValueDecomposition.m:I (1, 4)
	148 iconst_1 (1, 4)
	149 isub (1, 4)
	150 aload_0 (1, 4)
	151 getfield (1, 4)
	152 org/apache/commons/math3/linear/SingularValueDecomposition.n:I (1, 4)
	154 invokestatic (1, 4)
	155 org/apache/commons/math3/util/FastMath.min:(II)I (1, 4)
	157 istore (1, 4)
	158 #7 (1, 4)
	159 iconst_0 (1, 4)
	160 aload_0 (1, 4)
	161 getfield (1, 4)
	162 org/apache/commons/math3/linear/SingularValueDecomposition.n:I (1, 4)
	164 iconst_2 (1, 4)
	165 isub (1, 4)
	166 invokestatic (1, 4)
	167 org/apache/commons/math3/util/FastMath.max:(II)I (1, 4)
	169 istore (1, 4)
	170 #8 (1, 4)
	171 iconst_0 (2, 4)
	172 istore (2, 4)
	173 #9 (2, 4)
	174 iload (2, 4)
	175 #9 (2, 4)
	176 iload (2, 4)
	177 #7 (2, 4)
	178 iload (2, 4)
	179 #8 (2, 4)
	180 invokestatic (2, 4)
	181 org/apache/commons/math3/util/FastMath.max:(II)I (2, 4)
	183 if_icmpge (2, 4)
	184 716 (2, 4)
	186 iload (3, 1)
	187 #9 (3, 1)
	188 iload (3, 1)
	189 #7 (3, 1)
	190 if_icmpge (3, 1)
	191 155 (3, 1)
	193 aload_0 (4, 4)
	194 getfield (4, 4)
	195 org/apache/commons/math3/linear/SingularValueDecomposition.singularValues:[D (4, 4)
	197 iload (4, 4)
	198 #9 (4, 4)
	199 dconst_0 (4, 4)
	200 dastore (4, 4)
	201 iload (5, 4)
	202 #9 (5, 4)
	203 istore (5, 4)
	204 #10 (5, 4)
	205 iload (5, 4)
	206 #10 (5, 4)
	207 aload_0 (5, 4)
	208 getfield (5, 4)
	209 org/apache/commons/math3/linear/SingularValueDecomposition.m:I (5, 4)
	211 if_icmpge (5, 4)
	212 33 (5, 4)
	214 aload_0 (5, 4)
	215 getfield (5, 4)
	216 org/apache/commons/math3/linear/SingularValueDecomposition.singularValues:[D (5, 4)
	218 iload (5, 4)
	219 #9 (5, 4)
	220 aload_0 (5, 4)
	221 getfield (5, 4)
	222 org/apache/commons/math3/linear/SingularValueDecomposition.singularValues:[D (5, 4)
	224 iload (5, 4)
	225 #9 (5, 4)
	226 daload (5, 4)
	227 aload_2 (5, 4)
	228 iload (5, 4)
	229 #10 (5, 4)
	230 aaload (5, 4)
	231 iload (5, 4)
	232 #9 (5, 4)
	233 daload (5, 4)
	234 invokestatic (5, 4)
	235 org/apache/commons/math3/util/FastMath.hypot:(DD)D (5, 4)
	237 dastore (5, 4)
	238 iinc (5, 4)
	239 #10 (5, 4)
	240 -89 (5, 4)
	241 goto (5, 4)
	242 -36 (5, 4)
	244 aload_0 (5, 1)
	245 getfield (5, 1)
	246 org/apache/commons/math3/linear/SingularValueDecomposition.singularValues:[D (5, 1)
	248 iload (5, 1)
	249 #9 (5, 1)
	250 daload (5, 1)
	251 dconst_0 (5, 1)
	252 dcmpl (5, 1)
	253 ifeq (5, 1)
	254 77 (5, 1)
	256 aload_2 (6, 1)
	257 iload (6, 1)
	258 #9 (6, 1)
	259 aaload (6, 1)
	260 iload (6, 1)
	261 #9 (6, 1)
	262 daload (6, 1)
	263 dconst_0 (6, 1)
	264 dcmpg (6, 1)
	265 ifge (6, 1)
	266 18 (6, 1)
	268 aload_0 (6, 1)
	269 getfield (6, 1)
	270 org/apache/commons/math3/linear/SingularValueDecomposition.singularValues:[D (6, 1)
	272 iload (6, 1)
	273 #9 (6, 1)
	274 aload_0 (6, 1)
	275 getfield (6, 1)
	276 org/apache/commons/math3/linear/SingularValueDecomposition.singularValues:[D (6, 1)
	278 iload (6, 1)
	279 #9 (6, 1)
	280 daload (6, 1)
	281 dneg (6, 1)
	282 dastore (6, 1)
	283 iload (6, 4)
	284 #9 (6, 4)
	285 istore (6, 4)
	286 #10 (6, 4)
	287 iload (6, 4)
	288 #10 (6, 4)
	289 aload_0 (6, 4)
	290 getfield (6, 4)
	291 org/apache/commons/math3/linear/SingularValueDecomposition.m:I (6, 4)
	293 if_icmpge (6, 4)
	294 26 (6, 4)
	296 aload_2 (6, 4)
	297 iload (6, 4)
	298 #10 (6, 4)
	299 aaload (6, 4)
	300 iload (6, 4)
	301 #9 (6, 4)
	302 dup2 (6, 4)
	303 daload (6, 4)
	304 aload_0 (6, 4)
	305 getfield (6, 4)
	306 org/apache/commons/math3/linear/SingularValueDecomposition.singularValues:[D (6, 4)
	308 iload (6, 4)
	309 #9 (6, 4)
	310 daload (6, 4)
	311 ddiv (6, 4)
	312 dastore (6, 4)
	313 iinc (6, 4)
	314 #10 (6, 4)
	315 -89 (6, 4)
	316 goto (6, 4)
	317 -29 (6, 4)
	319 aload_2 (5, 1)
	320 iload (5, 1)
	321 #9 (5, 1)
	322 aaload (5, 1)
	323 iload (5, 1)
	324 #9 (5, 1)
	325 dup2 (5, 1)
	326 daload (5, 1)
	327 dconst_1 (5, 1)
	328 dadd (5, 1)
	329 dastore (5, 1)
	330 aload_0 (4, 4)
	331 getfield (4, 4)
	332 org/apache/commons/math3/linear/SingularValueDecomposition.singularValues:[D (4, 4)
	334 iload (4, 4)
	335 #9 (4, 4)
	336 aload_0 (4, 4)
	337 getfield (4, 4)
	338 org/apache/commons/math3/linear/SingularValueDecomposition.singularValues:[D (4, 4)
	340 iload (4, 4)
	341 #9 (4, 4)
	342 daload (4, 4)
	343 dneg (4, 4)
	344 dastore (4, 4)
	345 iload (3, 4)
	346 #9 (3, 4)
	347 iconst_1 (3, 4)
	348 iadd (3, 4)
	349 istore (3, 4)
	350 #10 (3, 4)
	351 iload (3, 4)
	352 #10 (3, 4)
	353 aload_0 (3, 4)
	354 getfield (3, 4)
	355 org/apache/commons/math3/linear/SingularValueDecomposition.n:I (3, 4)
	357 if_icmpge (3, 4)
	358 134 (3, 4)
	360 iload (4, 1)
	361 #9 (4, 1)
	362 iload (4, 1)
	363 #7 (4, 1)
	364 if_icmpge (4, 1)
	365 109 (4, 1)
	367 aload_0 (4, 1)
	368 getfield (4, 1)
	369 org/apache/commons/math3/linear/SingularValueDecomposition.singularValues:[D (4, 1)
	371 iload (4, 1)
	372 #9 (4, 1)
	373 daload (4, 1)
	374 dconst_0 (4, 1)
	375 dcmpl (4, 1)
	376 ifeq (4, 1)
	377 97 (4, 1)
	379 dconst_0 (5, 4)
	380 dstore (5, 4)
	381 #11 (5, 4)
	382 iload (6, 4)
	383 #9 (6, 4)
	384 istore (6, 4)
	385 #13 (6, 4)
	386 iload (6, 4)
	387 #13 (6, 4)
	388 aload_0 (6, 4)
	389 getfield (6, 4)
	390 org/apache/commons/math3/linear/SingularValueDecomposition.m:I (6, 4)
	392 if_icmpge (6, 4)
	393 29 (6, 4)
	395 dload (6, 4)
	396 #11 (6, 4)
	397 aload_2 (6, 4)
	398 iload (6, 4)
	399 #13 (6, 4)
	400 aaload (6, 4)
	401 iload (6, 4)
	402 #9 (6, 4)
	403 daload (6, 4)
	404 aload_2 (6, 4)
	405 iload (6, 4)
	406 #13 (6, 4)
	407 aaload (6, 4)
	408 iload (6, 4)
	409 #10 (6, 4)
	410 daload (6, 4)
	411 dmul (6, 4)
	412 dadd (6, 4)
	413 dstore (6, 4)
	414 #11 (6, 4)
	415 iinc (6, 4)
	416 #13 (6, 4)
	417 -89 (6, 4)
	418 goto (6, 4)
	419 -32 (6, 4)
	421 dload (5, 4)
	422 #11 (5, 4)
	423 dneg (5, 4)
	424 aload_2 (5, 4)
	425 iload (5, 4)
	426 #9 (5, 4)
	427 aaload (5, 4)
	428 iload (5, 4)
	429 #9 (5, 4)
	430 daload (5, 4)
	431 ddiv (5, 4)
	432 dstore (5, 4)
	433 #11 (5, 4)
	434 iload (6, 4)
	435 #9 (6, 4)
	436 istore (6, 4)
	437 #13 (6, 4)
	438 iload (6, 4)
	439 #13 (6, 4)
	440 aload_0 (6, 4)
	441 getfield (6, 4)
	442 org/apache/commons/math3/linear/SingularValueDecomposition.m:I (6, 4)
	444 if_icmpge (6, 4)
	445 29 (6, 4)
	447 aload_2 (6, 4)
	448 iload (6, 4)
	449 #13 (6, 4)
	450 aaload (6, 4)
	451 iload (6, 4)
	452 #10 (6, 4)
	453 dup2 (6, 4)
	454 daload (6, 4)
	455 dload (6, 4)
	456 #11 (6, 4)
	457 aload_2 (6, 4)
	458 iload (6, 4)
	459 #13 (6, 4)
	460 aaload (6, 4)
	461 iload (6, 4)
	462 #9 (6, 4)
	463 daload (6, 4)
	464 dmul (6, 4)
	465 dadd (6, 4)
	466 dastore (6, 4)
	467 iinc (6, 4)
	468 #13 (6, 4)
	469 -89 (6, 4)
	470 goto (6, 4)
	471 -32 (6, 4)
	473 aload (6, 4)
	474 #5 (6, 4)
	475 iload (6, 4)
	476 #10 (6, 4)
	477 aload_2 (6, 4)
	478 iload (6, 4)
	479 #9 (6, 4)
	480 aaload (6, 4)
	481 iload (6, 4)
	482 #10 (6, 4)
	483 daload (6, 4)
	484 dastore (6, 4)
	485 iinc (6, 4)
	486 #10 (6, 4)
	487 -89 (6, 4)
	488 goto (6, 4)
	489 -137 (6, 4)
	491 iload (3, 1)
	492 #9 (3, 1)
	493 iload (3, 1)
	494 #7 (3, 1)
	495 if_icmpge (3, 1)
	496 36 (3, 1)
	498 iload (5, 4)
	499 #9 (5, 4)
	500 istore (5, 4)
	501 #10 (5, 4)
	502 iload (5, 4)
	503 #10 (5, 4)
	504 aload_0 (5, 4)
	505 getfield (5, 4)
	506 org/apache/commons/math3/linear/SingularValueDecomposition.m:I (5, 4)
	508 if_icmpge (5, 4)
	509 23 (5, 4)
	511 aload_3 (5, 4)
	512 iload (5, 4)
	513 #10 (5, 4)
	514 aaload (5, 4)
	515 iload (5, 4)
	516 #9 (5, 4)
	517 aload_2 (5, 4)
	518 iload (5, 4)
	519 #10 (5, 4)
	520 aaload (5, 4)
	521 iload (5, 4)
	522 #9 (5, 4)
	523 daload (5, 4)
	524 dastore (5, 4)
	525 iinc (5, 4)
	526 #10 (5, 4)
	527 -89 (5, 4)
	528 goto (5, 4)
	529 -26 (5, 4)
	531 iload (3, 1)
	532 #9 (3, 1)
	533 iload (3, 1)
	534 #8 (3, 1)
	535 if_icmpge (3, 1)
	536 358 (3, 1)
	538 aload (4, 4)
	539 #5 (4, 4)
	540 iload (4, 4)
	541 #9 (4, 4)
	542 dconst_0 (4, 4)
	543 dastore (4, 4)
	544 iload (5, 4)
	545 #9 (5, 4)
	546 iconst_1 (5, 4)
	547 iadd (5, 4)
	548 istore (5, 4)
	549 #10 (5, 4)
	550 iload (5, 4)
	551 #10 (5, 4)
	552 aload_0 (5, 4)
	553 getfield (5, 4)
	554 org/apache/commons/math3/linear/SingularValueDecomposition.n:I (5, 4)
	556 if_icmpge (5, 4)
	557 27 (5, 4)
	559 aload (5, 4)
	560 #5 (5, 4)
	561 iload (5, 4)
	562 #9 (5, 4)
	563 aload (5, 4)
	564 #5 (5, 4)
	565 iload (5, 4)
	566 #9 (5, 4)
	567 daload (5, 4)
	568 aload (5, 4)
	569 #5 (5, 4)
	570 iload (5, 4)
	571 #10 (5, 4)
	572 daload (5, 4)
	573 invokestatic (5, 4)
	574 org/apache/commons/math3/util/FastMath.hypot:(DD)D (5, 4)
	576 dastore (5, 4)
	577 iinc (5, 4)
	578 #10 (5, 4)
	579 -89 (5, 4)
	580 goto (5, 4)
	581 -30 (5, 4)
	583 aload (5, 1)
	584 #5 (5, 1)
	585 iload (5, 1)
	586 #9 (5, 1)
	587 daload (5, 1)
	588 dconst_0 (5, 1)
	589 dcmpl (5, 1)
	590 ifeq (5, 1)
	591 71 (5, 1)
	593 aload (6, 1)
	594 #5 (6, 1)
	595 iload (6, 1)
	596 #9 (6, 1)
	597 iconst_1 (6, 1)
	598 iadd (6, 1)
	599 daload (6, 1)
	600 dconst_0 (6, 1)
	601 dcmpg (6, 1)
	602 ifge (6, 1)
	603 14 (6, 1)
	605 aload (6, 1)
	606 #5 (6, 1)
	607 iload (6, 1)
	608 #9 (6, 1)
	609 aload (6, 1)
	610 #5 (6, 1)
	611 iload (6, 1)
	612 #9 (6, 1)
	613 daload (6, 1)
	614 dneg (6, 1)
	615 dastore (6, 1)
	616 iload (6, 4)
	617 #9 (6, 4)
	618 iconst_1 (6, 4)
	619 iadd (6, 4)
	620 istore (6, 4)
	621 #10 (6, 4)
	622 iload (6, 4)
	623 #10 (6, 4)
	624 aload_0 (6, 4)
	625 getfield (6, 4)
	626 org/apache/commons/math3/linear/SingularValueDecomposition.n:I (6, 4)
	628 if_icmpge (6, 4)
	629 22 (6, 4)
	631 aload (6, 4)
	632 #5 (6, 4)
	633 iload (6, 4)
	634 #10 (6, 4)
	635 dup2 (6, 4)
	636 daload (6, 4)
	637 aload (6, 4)
	638 #5 (6, 4)
	639 iload (6, 4)
	640 #9 (6, 4)
	641 daload (6, 4)
	642 ddiv (6, 4)
	643 dastore (6, 4)
	644 iinc (6, 4)
	645 #10 (6, 4)
	646 -89 (6, 4)
	647 goto (6, 4)
	648 -25 (6, 4)
	650 aload (5, 1)
	651 #5 (5, 1)
	652 iload (5, 1)
	653 #9 (5, 1)
	654 iconst_1 (5, 1)
	655 iadd (5, 1)
	656 dup2 (5, 1)
	657 daload (5, 1)
	658 dconst_1 (5, 1)
	659 dadd (5, 1)
	660 dastore (5, 1)
	661 aload (4, 4)
	662 #5 (4, 4)
	663 iload (4, 4)
	664 #9 (4, 4)
	665 aload (4, 4)
	666 #5 (4, 4)
	667 iload (4, 4)
	668 #9 (4, 4)
	669 daload (4, 4)
	670 dneg (4, 4)
	671 dastore (4, 4)
	672 iload (5, 1)
	673 #9 (5, 1)
	674 iconst_1 (5, 1)
	675 iadd (5, 1)
	676 aload_0 (5, 1)
	677 getfield (5, 1)
	678 org/apache/commons/math3/linear/SingularValueDecomposition.m:I (5, 1)
	680 if_icmpge (5, 1)
	681 179 (5, 1)
	683 aload (5, 1)
	684 #5 (5, 1)
	685 iload (5, 1)
	686 #9 (5, 1)
	687 daload (5, 1)
	688 dconst_0 (5, 1)
	689 dcmpl (5, 1)
	690 ifeq (5, 1)
	691 169 (5, 1)
	693 iload (7, 4)
	694 #9 (7, 4)
	695 iconst_1 (7, 4)
	696 iadd (7, 4)
	697 istore (7, 4)
	698 #10 (7, 4)
	699 iload (7, 4)
	700 #10 (7, 4)
	701 aload_0 (7, 4)
	702 getfield (7, 4)
	703 org/apache/commons/math3/linear/SingularValueDecomposition.m:I (7, 4)
	705 if_icmpge (7, 4)
	706 15 (7, 4)
	708 aload (7, 4)
	709 #6 (7, 4)
	710 iload (7, 4)
	711 #10 (7, 4)
	712 dconst_0 (7, 4)
	713 dastore (7, 4)
	714 iinc (7, 4)
	715 #10 (7, 4)
	716 -89 (7, 4)
	717 goto (7, 4)
	718 -18 (7, 4)
	720 iload (7, 4)
	721 #9 (7, 4)
	722 iconst_1 (7, 4)
	723 iadd (7, 4)
	724 istore (7, 4)
	725 #10 (7, 4)
	726 iload (7, 4)
	727 #10 (7, 4)
	728 aload_0 (7, 4)
	729 getfield (7, 4)
	730 org/apache/commons/math3/linear/SingularValueDecomposition.n:I (7, 4)
	732 if_icmpge (7, 4)
	733 51 (7, 4)
	735 iload (8, 4)
	736 #9 (8, 4)
	737 iconst_1 (8, 4)
	738 iadd (8, 4)
	739 istore (8, 4)
	740 #11 (8, 4)
	741 iload (8, 4)
	742 #11 (8, 4)
	743 aload_0 (8, 4)
	744 getfield (8, 4)
	745 org/apache/commons/math3/linear/SingularValueDecomposition.m:I (8, 4)
	747 if_icmpge (8, 4)
	748 30 (8, 4)
	750 aload (8, 4)
	751 #6 (8, 4)
	752 iload (8, 4)
	753 #11 (8, 4)
	754 dup2 (8, 4)
	755 daload (8, 4)
	756 aload (8, 4)
	757 #5 (8, 4)
	758 iload (8, 4)
	759 #10 (8, 4)
	760 daload (8, 4)
	761 aload_2 (8, 4)
	762 iload (8, 4)
	763 #11 (8, 4)
	764 aaload (8, 4)
	765 iload (8, 4)
	766 #10 (8, 4)
	767 daload (8, 4)
	768 dmul (8, 4)
	769 dadd (8, 4)
	770 dastore (8, 4)
	771 iinc (8, 4)
	772 #11 (8, 4)
	773 -89 (8, 4)
	774 goto (8, 4)
	775 -33 (8, 4)
	777 iinc (8, 4)
	778 #10 (8, 4)
	779 -89 (8, 4)
	780 goto (8, 4)
	781 -54 (8, 4)
	783 iload (8, 4)
	784 #9 (8, 4)
	785 iconst_1 (8, 4)
	786 iadd (8, 4)
	787 istore (8, 4)
	788 #10 (8, 4)
	789 iload (8, 4)
	790 #10 (8, 4)
	791 aload_0 (8, 4)
	792 getfield (8, 4)
	793 org/apache/commons/math3/linear/SingularValueDecomposition.n:I (8, 4)
	795 if_icmpge (8, 4)
	796 64 (8, 4)
	798 aload (8, 4)
	799 #5 (8, 4)
	800 iload (8, 4)
	801 #10 (8, 4)
	802 daload (8, 4)
	803 dneg (8, 4)
	804 aload (8, 4)
	805 #5 (8, 4)
	806 iload (8, 4)
	807 #9 (8, 4)
	808 iconst_1 (8, 4)
	809 iadd (8, 4)
	810 daload (8, 4)
	811 ddiv (8, 4)
	812 dstore (8, 4)
	813 #11 (8, 4)
	814 iload (9, 4)
	815 #9 (9, 4)
	816 iconst_1 (9, 4)
	817 iadd (9, 4)
	818 istore (9, 4)
	819 #13 (9, 4)
	820 iload (9, 4)
	821 #13 (9, 4)
	822 aload_0 (9, 4)
	823 getfield (9, 4)
	824 org/apache/commons/math3/linear/SingularValueDecomposition.m:I (9, 4)
	826 if_icmpge (9, 4)
	827 27 (9, 4)
	829 aload_2 (9, 4)
	830 iload (9, 4)
	831 #13 (9, 4)
	832 aaload (9, 4)
	833 iload (9, 4)
	834 #10 (9, 4)
	835 dup2 (9, 4)
	836 daload (9, 4)
	837 dload (9, 4)
	838 #11 (9, 4)
	839 aload (9, 4)
	840 #6 (9, 4)
	841 iload (9, 4)
	842 #13 (9, 4)
	843 daload (9, 4)
	844 dmul (9, 4)
	845 dadd (9, 4)
	846 dastore (9, 4)
	847 iinc (9, 4)
	848 #13 (9, 4)
	849 -89 (9, 4)
	850 goto (9, 4)
	851 -30 (9, 4)
	853 iinc (9, 4)
	854 #10 (9, 4)
	855 -89 (9, 4)
	856 goto (9, 4)
	857 -67 (9, 4)
	859 iload (9, 4)
	860 #9 (9, 4)
	861 iconst_1 (9, 4)
	862 iadd (9, 4)
	863 istore (9, 4)
	864 #10 (9, 4)
	865 iload (9, 4)
	866 #10 (9, 4)
	867 aload_0 (9, 4)
	868 getfield (9, 4)
	869 org/apache/commons/math3/linear/SingularValueDecomposition.n:I (9, 4)
	871 if_icmpge (9, 4)
	872 22 (9, 4)
	874 aload (9, 4)
	875 #4 (9, 4)
	876 iload (9, 4)
	877 #10 (9, 4)
	878 aaload (9, 4)
	879 iload (9, 4)
	880 #9 (9, 4)
	881 aload (9, 4)
	882 #5 (9, 4)
	883 iload (9, 4)
	884 #10 (9, 4)
	885 daload (9, 4)
	886 dastore (9, 4)
	887 iinc (9, 4)
	888 #10 (9, 4)
	889 -89 (9, 4)
	890 goto (9, 4)
	891 -25 (9, 4)
	893 iinc (9, 4)
	894 #9 (9, 4)
	895 -89 (9, 4)
	896 goto (9, 4)
	897 -722 (9, 4)
	899 aload_0 (8, 4)
	900 getfield (8, 4)
	901 org/apache/commons/math3/linear/SingularValueDecomposition.n:I (8, 4)
	903 istore (8, 4)
	904 #9 (8, 4)
	905 iload (9, 1)
	906 #7 (9, 1)
	907 aload_0 (9, 1)
	908 getfield (9, 1)
	909 org/apache/commons/math3/linear/SingularValueDecomposition.n:I (9, 1)
	911 if_icmpge (9, 1)
	912 17 (9, 1)
	914 aload_0 (9, 1)
	915 getfield (9, 1)
	916 org/apache/commons/math3/linear/SingularValueDecomposition.singularValues:[D (9, 1)
	918 iload (9, 1)
	919 #7 (9, 1)
	920 aload_2 (9, 1)
	921 iload (9, 1)
	922 #7 (9, 1)
	923 aaload (9, 1)
	924 iload (9, 1)
	925 #7 (9, 1)
	926 daload (9, 1)
	927 dastore (9, 1)
	928 aload_0 (9, 1)
	929 getfield (9, 1)
	930 org/apache/commons/math3/linear/SingularValueDecomposition.m:I (9, 1)
	932 iload (9, 1)
	933 #9 (9, 1)
	934 if_icmpge (9, 1)
	935 13 (9, 1)
	937 aload_0 (9, 1)
	938 getfield (9, 1)
	939 org/apache/commons/math3/linear/SingularValueDecomposition.singularValues:[D (9, 1)
	941 iload (9, 1)
	942 #9 (9, 1)
	943 iconst_1 (9, 1)
	944 isub (9, 1)
	945 dconst_0 (9, 1)
	946 dastore (9, 1)
	947 iload (9, 1)
	948 #8 (9, 1)
	949 iconst_1 (9, 1)
	950 iadd (9, 1)
	951 iload (9, 1)
	952 #9 (9, 1)
	953 if_icmpge (9, 1)
	954 17 (9, 1)
	956 aload (9, 1)
	957 #5 (9, 1)
	958 iload (9, 1)
	959 #8 (9, 1)
	960 aload_2 (9, 1)
	961 iload (9, 1)
	962 #8 (9, 1)
	963 aaload (9, 1)
	964 iload (9, 1)
	965 #9 (9, 1)
	966 iconst_1 (9, 1)
	967 isub (9, 1)
	968 daload (9, 1)
	969 dastore (9, 1)
	970 aload (8, 4)
	971 #5 (8, 4)
	972 iload (8, 4)
	973 #9 (8, 4)
	974 iconst_1 (8, 4)
	975 isub (8, 4)
	976 dconst_0 (8, 4)
	977 dastore (8, 4)
	978 iload (9, 4)
	979 #7 (9, 4)
	980 istore (9, 4)
	981 #10 (9, 4)
	982 iload (9, 4)
	983 #10 (9, 4)
	984 aload_0 (9, 4)
	985 getfield (9, 4)
	986 org/apache/commons/math3/linear/SingularValueDecomposition.n:I (9, 4)
	988 if_icmpge (9, 4)
	989 43 (9, 4)
	991 iconst_0 (10, 4)
	992 istore (10, 4)
	993 #11 (10, 4)
	994 iload (10, 4)
	995 #11 (10, 4)
	996 aload_0 (10, 4)
	997 getfield (10, 4)
	998 org/apache/commons/math3/linear/SingularValueDecomposition.m:I (10, 4)
	1000 if_icmpge (10, 4)
	1001 17 (10, 4)
	1003 aload_3 (10, 4)
	1004 iload (10, 4)
	1005 #11 (10, 4)
	1006 aaload (10, 4)
	1007 iload (10, 4)
	1008 #10 (10, 4)
	1009 dconst_0 (10, 4)
	1010 dastore (10, 4)
	1011 iinc (10, 4)
	1012 #11 (10, 4)
	1013 -89 (10, 4)
	1014 goto (10, 4)
	1015 -20 (10, 4)
	1017 aload_3 (9, 4)
	1018 iload (9, 4)
	1019 #10 (9, 4)
	1020 aaload (9, 4)
	1021 iload (9, 4)
	1022 #10 (9, 4)
	1023 dconst_1 (9, 4)
	1024 dastore (9, 4)
	1025 iinc (9, 4)
	1026 #10 (9, 4)
	1027 -89 (9, 4)
	1028 goto (9, 4)
	1029 -46 (9, 4)
	1031 iload (9, 4)
	1032 #7 (9, 4)
	1033 iconst_1 (9, 4)
	1034 isub (9, 4)
	1035 istore (9, 4)
	1036 #10 (9, 4)
	1037 iload (9, 4)
	1038 #10 (9, 4)
	1039 iflt (9, 4)
	1040 249 (9, 4)
	1042 aload_0 (10, 1)
	1043 getfield (10, 1)
	1044 org/apache/commons/math3/linear/SingularValueDecomposition.singularValues:[D (10, 1)
	1046 iload (10, 1)
	1047 #10 (10, 1)
	1048 daload (10, 1)
	1049 dconst_0 (10, 1)
	1050 dcmpl (10, 1)
	1051 ifeq (10, 1)
	1052 197 (10, 1)
	1054 iload (11, 4)
	1055 #10 (11, 4)
	1056 iconst_1 (11, 4)
	1057 iadd (11, 4)
	1058 istore (11, 4)
	1059 #11 (11, 4)
	1060 iload (11, 4)
	1061 #11 (11, 4)
	1062 aload_0 (11, 4)
	1063 getfield (11, 4)
	1064 org/apache/commons/math3/linear/SingularValueDecomposition.n:I (11, 4)
	1066 if_icmpge (11, 4)
	1067 103 (11, 4)
	1069 dconst_0 (11, 4)
	1070 dstore (11, 4)
	1071 #12 (11, 4)
	1072 iload (12, 4)
	1073 #10 (12, 4)
	1074 istore (12, 4)
	1075 #14 (12, 4)
	1076 iload (12, 4)
	1077 #14 (12, 4)
	1078 aload_0 (12, 4)
	1079 getfield (12, 4)
	1080 org/apache/commons/math3/linear/SingularValueDecomposition.m:I (12, 4)
	1082 if_icmpge (12, 4)
	1083 29 (12, 4)
	1085 dload (12, 4)
	1086 #12 (12, 4)
	1087 aload_3 (12, 4)
	1088 iload (12, 4)
	1089 #14 (12, 4)
	1090 aaload (12, 4)
	1091 iload (12, 4)
	1092 #10 (12, 4)
	1093 daload (12, 4)
	1094 aload_3 (12, 4)
	1095 iload (12, 4)
	1096 #14 (12, 4)
	1097 aaload (12, 4)
	1098 iload (12, 4)
	1099 #11 (12, 4)
	1100 daload (12, 4)
	1101 dmul (12, 4)
	1102 dadd (12, 4)
	1103 dstore (12, 4)
	1104 #12 (12, 4)
	1105 iinc (12, 4)
	1106 #14 (12, 4)
	1107 -89 (12, 4)
	1108 goto (12, 4)
	1109 -32 (12, 4)
	1111 dload (11, 4)
	1112 #12 (11, 4)
	1113 dneg (11, 4)
	1114 aload_3 (11, 4)
	1115 iload (11, 4)
	1116 #10 (11, 4)
	1117 aaload (11, 4)
	1118 iload (11, 4)
	1119 #10 (11, 4)
	1120 daload (11, 4)
	1121 ddiv (11, 4)
	1122 dstore (11, 4)
	1123 #12 (11, 4)
	1124 iload (12, 4)
	1125 #10 (12, 4)
	1126 istore (12, 4)
	1127 #14 (12, 4)
	1128 iload (12, 4)
	1129 #14 (12, 4)
	1130 aload_0 (12, 4)
	1131 getfield (12, 4)
	1132 org/apache/commons/math3/linear/SingularValueDecomposition.m:I (12, 4)
	1134 if_icmpge (12, 4)
	1135 29 (12, 4)
	1137 aload_3 (12, 4)
	1138 iload (12, 4)
	1139 #14 (12, 4)
	1140 aaload (12, 4)
	1141 iload (12, 4)
	1142 #11 (12, 4)
	1143 dup2 (12, 4)
	1144 daload (12, 4)
	1145 dload (12, 4)
	1146 #12 (12, 4)
	1147 aload_3 (12, 4)
	1148 iload (12, 4)
	1149 #14 (12, 4)
	1150 aaload (12, 4)
	1151 iload (12, 4)
	1152 #10 (12, 4)
	1153 daload (12, 4)
	1154 dmul (12, 4)
	1155 dadd (12, 4)
	1156 dastore (12, 4)
	1157 iinc (12, 4)
	1158 #14 (12, 4)
	1159 -89 (12, 4)
	1160 goto (12, 4)
	1161 -32 (12, 4)
	1163 iinc (12, 4)
	1164 #11 (12, 4)
	1165 -89 (12, 4)
	1166 goto (12, 4)
	1167 -106 (12, 4)
	1169 iload (12, 4)
	1170 #10 (12, 4)
	1171 istore (12, 4)
	1172 #11 (12, 4)
	1173 iload (12, 4)
	1174 #11 (12, 4)
	1175 aload_0 (12, 4)
	1176 getfield (12, 4)
	1177 org/apache/commons/math3/linear/SingularValueDecomposition.m:I (12, 4)
	1179 if_icmpge (12, 4)
	1180 24 (12, 4)
	1182 aload_3 (12, 4)
	1183 iload (12, 4)
	1184 #11 (12, 4)
	1185 aaload (12, 4)
	1186 iload (12, 4)
	1187 #10 (12, 4)
	1188 aload_3 (12, 4)
	1189 iload (12, 4)
	1190 #11 (12, 4)
	1191 aaload (12, 4)
	1192 iload (12, 4)
	1193 #10 (12, 4)
	1194 daload (12, 4)
	1195 dneg (12, 4)
	1196 dastore (12, 4)
	1197 iinc (12, 4)
	1198 #11 (12, 4)
	1199 -89 (12, 4)
	1200 goto (12, 4)
	1201 -27 (12, 4)
	1203 aload_3 (11, 4)
	1204 iload (11, 4)
	1205 #10 (11, 4)
	1206 aaload (11, 4)
	1207 iload (11, 4)
	1208 #10 (11, 4)
	1209 dconst_1 (11, 4)
	1210 aload_3 (11, 4)
	1211 iload (11, 4)
	1212 #10 (11, 4)
	1213 aaload (11, 4)
	1214 iload (11, 4)
	1215 #10 (11, 4)
	1216 daload (11, 4)
	1217 dadd (11, 4)
	1218 dastore (11, 4)
	1219 iconst_0 (12, 4)
	1220 istore (12, 4)
	1221 #11 (12, 4)
	1222 iload (12, 4)
	1223 #11 (12, 4)
	1224 iload (12, 4)
	1225 #10 (12, 4)
	1226 iconst_1 (12, 4)
	1227 isub (12, 4)
	1228 if_icmpge (12, 4)
	1229 17 (12, 4)
	1231 aload_3 (12, 4)
	1232 iload (12, 4)
	1233 #11 (12, 4)
	1234 aaload (12, 4)
	1235 iload (12, 4)
	1236 #10 (12, 4)
	1237 dconst_0 (12, 4)
	1238 dastore (12, 4)
	1239 iinc (12, 4)
	1240 #11 (12, 4)
	1241 -89 (12, 4)
	1242 goto (12, 4)
	1243 -20 (12, 4)
	1245 goto (12, 4)
	1246 37 (12, 4)
	1248 iconst_0 (13, 4)
	1249 istore (13, 4)
	1250 #11 (13, 4)
	1251 iload (13, 4)
	1252 #11 (13, 4)
	1253 aload_0 (13, 4)
	1254 getfield (13, 4)
	1255 org/apache/commons/math3/linear/SingularValueDecomposition.m:I (13, 4)
	1257 if_icmpge (13, 4)
	1258 17 (13, 4)
	1260 aload_3 (13, 4)
	1261 iload (13, 4)
	1262 #11 (13, 4)
	1263 aaload (13, 4)
	1264 iload (13, 4)
	1265 #10 (13, 4)
	1266 dconst_0 (13, 4)
	1267 dastore (13, 4)
	1268 iinc (13, 4)
	1269 #11 (13, 4)
	1270 -89 (13, 4)
	1271 goto (13, 4)
	1272 -20 (13, 4)
	1274 aload_3 (12, 2)
	1275 iload (12, 2)
	1276 #10 (12, 2)
	1277 aaload (12, 2)
	1278 iload (12, 2)
	1279 #10 (12, 2)
	1280 dconst_1 (12, 2)
	1281 dastore (12, 2)
	1282 iinc (12, 2)
	1283 #10 (12, 2)
	1284 -89 (12, 2)
	1285 goto (12, 2)
	1286 -248 (12, 2)
	1288 aload_0 (11, 4)
	1289 getfield (11, 4)
	1290 org/apache/commons/math3/linear/SingularValueDecomposition.n:I (11, 4)
	1292 iconst_1 (11, 4)
	1293 isub (11, 4)
	1294 istore (11, 4)
	1295 #10 (11, 4)
	1296 iload (11, 4)
	1297 #10 (11, 4)
	1298 iflt (11, 4)
	1299 188 (11, 4)
	1301 iload (12, 1)
	1302 #10 (12, 1)
	1303 iload (12, 1)
	1304 #8 (12, 1)
	1305 if_icmpge (12, 1)
	1306 139 (12, 1)
	1308 aload (12, 1)
	1309 #5 (12, 1)
	1310 iload (12, 1)
	1311 #10 (12, 1)
	1312 daload (12, 1)
	1313 dconst_0 (12, 1)
	1314 dcmpl (12, 1)
	1315 ifeq (12, 1)
	1316 129 (12, 1)
	1318 iload (13, 4)
	1319 #10 (13, 4)
	1320 iconst_1 (13, 4)
	1321 iadd (13, 4)
	1322 istore (13, 4)
	1323 #11 (13, 4)
	1324 iload (13, 4)
	1325 #11 (13, 4)
	1326 aload_0 (13, 4)
	1327 getfield (13, 4)
	1328 org/apache/commons/math3/linear/SingularValueDecomposition.n:I (13, 4)
	1330 if_icmpge (13, 4)
	1331 114 (13, 4)
	1333 dconst_0 (13, 4)
	1334 dstore (13, 4)
	1335 #12 (13, 4)
	1336 iload (14, 4)
	1337 #10 (14, 4)
	1338 iconst_1 (14, 4)
	1339 iadd (14, 4)
	1340 istore (14, 4)
	1341 #14 (14, 4)
	1342 iload (14, 4)
	1343 #14 (14, 4)
	1344 aload_0 (14, 4)
	1345 getfield (14, 4)
	1346 org/apache/commons/math3/linear/SingularValueDecomposition.n:I (14, 4)
	1348 if_icmpge (14, 4)
	1349 31 (14, 4)
	1351 dload (14, 4)
	1352 #12 (14, 4)
	1353 aload (14, 4)
	1354 #4 (14, 4)
	1355 iload (14, 4)
	1356 #14 (14, 4)
	1357 aaload (14, 4)
	1358 iload (14, 4)
	1359 #10 (14, 4)
	1360 daload (14, 4)
	1361 aload (14, 4)
	1362 #4 (14, 4)
	1363 iload (14, 4)
	1364 #14 (14, 4)
	1365 aaload (14, 4)
	1366 iload (14, 4)
	1367 #11 (14, 4)
	1368 daload (14, 4)
	1369 dmul (14, 4)
	1370 dadd (14, 4)
	1371 dstore (14, 4)
	1372 #12 (14, 4)
	1373 iinc (14, 4)
	1374 #14 (14, 4)
	1375 -89 (14, 4)
	1376 goto (14, 4)
	1377 -34 (14, 4)
	1379 dload (13, 4)
	1380 #12 (13, 4)
	1381 dneg (13, 4)
	1382 aload (13, 4)
	1383 #4 (13, 4)
	1384 iload (13, 4)
	1385 #10 (13, 4)
	1386 iconst_1 (13, 4)
	1387 iadd (13, 4)
	1388 aaload (13, 4)
	1389 iload (13, 4)
	1390 #10 (13, 4)
	1391 daload (13, 4)
	1392 ddiv (13, 4)
	1393 dstore (13, 4)
	1394 #12 (13, 4)
	1395 iload (14, 4)
	1396 #10 (14, 4)
	1397 iconst_1 (14, 4)
	1398 iadd (14, 4)
	1399 istore (14, 4)
	1400 #14 (14, 4)
	1401 iload (14, 4)
	1402 #14 (14, 4)
	1403 aload_0 (14, 4)
	1404 getfield (14, 4)
	1405 org/apache/commons/math3/linear/SingularValueDecomposition.n:I (14, 4)
	1407 if_icmpge (14, 4)
	1408 31 (14, 4)
	1410 aload (14, 4)
	1411 #4 (14, 4)
	1412 iload (14, 4)
	1413 #14 (14, 4)
	1414 aaload (14, 4)
	1415 iload (14, 4)
	1416 #11 (14, 4)
	1417 dup2 (14, 4)
	1418 daload (14, 4)
	1419 dload (14, 4)
	1420 #12 (14, 4)
	1421 aload (14, 4)
	1422 #4 (14, 4)
	1423 iload (14, 4)
	1424 #14 (14, 4)
	1425 aaload (14, 4)
	1426 iload (14, 4)
	1427 #10 (14, 4)
	1428 daload (14, 4)
	1429 dmul (14, 4)
	1430 dadd (14, 4)
	1431 dastore (14, 4)
	1432 iinc (14, 4)
	1433 #14 (14, 4)
	1434 -89 (14, 4)
	1435 goto (14, 4)
	1436 -34 (14, 4)
	1438 iinc (14, 4)
	1439 #11 (14, 4)
	1440 -89 (14, 4)
	1441 goto (14, 4)
	1442 -117 (14, 4)
	1444 iconst_0 (13, 4)
	1445 istore (13, 4)
	1446 #11 (13, 4)
	1447 iload (13, 4)
	1448 #11 (13, 4)
	1449 aload_0 (13, 4)
	1450 getfield (13, 4)
	1451 org/apache/commons/math3/linear/SingularValueDecomposition.n:I (13, 4)
	1453 if_icmpge (13, 4)
	1454 18 (13, 4)
	1456 aload (13, 4)
	1457 #4 (13, 4)
	1458 iload (13, 4)
	1459 #11 (13, 4)
	1460 aaload (13, 4)
	1461 iload (13, 4)
	1462 #10 (13, 4)
	1463 dconst_0 (13, 4)
	1464 dastore (13, 4)
	1465 iinc (13, 4)
	1466 #11 (13, 4)
	1467 -89 (13, 4)
	1468 goto (13, 4)
	1469 -21 (13, 4)
	1471 aload (12, 1)
	1472 #4 (12, 1)
	1473 iload (12, 1)
	1474 #10 (12, 1)
	1475 aaload (12, 1)
	1476 iload (12, 1)
	1477 #10 (12, 1)
	1478 dconst_1 (12, 1)
	1479 dastore (12, 1)
	1480 iinc (12, 1)
	1481 #10 (12, 1)
	1482 -89 (12, 1)
	1483 goto (12, 1)
	1484 -187 (12, 1)
	1486 iload (13, 4)
	1487 #9 (13, 4)
	1488 iconst_1 (13, 4)
	1489 isub (13, 4)
	1490 istore (13, 4)
	1491 #10 (13, 4)
	1492 iload (14, 3)
	1493 #9 (14, 3)
	1494 ifle (14, 3)
	1495 1646 (14, 3)
	1497 iload (21, 4)
	1498 #9 (21, 4)
	1499 iconst_2 (21, 4)
	1500 isub (21, 4)
	1501 istore (21, 4)
	1502 #11 (21, 4)
	1503 iload (21, 4)
	1504 #11 (21, 4)
	1505 iflt (21, 4)
	1506 65 (21, 4)
	1508 ldc2_w (21, 4)
	1509 1.6033346880071782e-291 (21, 4)
	1511 ldc2_w (21, 4)
	1512 2.220446049250313e-16 (21, 4)
	1514 aload_0 (21, 4)
	1515 getfield (21, 4)
	1516 org/apache/commons/math3/linear/SingularValueDecomposition.singularValues:[D (21, 4)
	1518 iload (21, 4)
	1519 #11 (21, 4)
	1520 daload (21, 4)
	1521 invokestatic (21, 4)
	1522 org/apache/commons/math3/util/FastMath.abs:(D)D (21, 4)
	1524 aload_0 (21, 4)
	1525 getfield (21, 4)
	1526 org/apache/commons/math3/linear/SingularValueDecomposition.singularValues:[D (21, 4)
	1528 iload (21, 4)
	1529 #11 (21, 4)
	1530 iconst_1 (21, 4)
	1531 iadd (21, 4)
	1532 daload (21, 4)
	1533 invokestatic (21, 4)
	1534 org/apache/commons/math3/util/FastMath.abs:(D)D (21, 4)
	1536 dadd (21, 4)
	1537 dmul (21, 4)
	1538 dadd (21, 4)
	1539 dstore (21, 4)
	1540 #13 (21, 4)
	1541 aload (23, 1)
	1542 #5 (23, 1)
	1543 iload (23, 1)
	1544 #11 (23, 1)
	1545 daload (23, 1)
	1546 invokestatic (23, 1)
	1547 org/apache/commons/math3/util/FastMath.abs:(D)D (23, 1)
	1549 dload (23, 1)
	1550 #13 (23, 1)
	1551 dcmpl (23, 1)
	1552 ifgt (23, 1)
	1553 12 (23, 1)
	1555 aload (23, 1)
	1556 #5 (23, 1)
	1557 iload (23, 1)
	1558 #11 (23, 1)
	1559 dconst_0 (23, 1)
	1560 dastore (23, 1)
	1561 goto (23, 1)
	1562 9 (23, 1)
	1564 iinc (23, 1)
	1565 #11 (23, 1)
	1566 -89 (23, 1)
	1567 goto (23, 1)
	1568 -64 (23, 1)
	1570 iload (23, 1)
	1571 #11 (23, 1)
	1572 iload (23, 1)
	1573 #9 (23, 1)
	1574 iconst_2 (23, 1)
	1575 isub (23, 1)
	1576 if_icmpne (23, 1)
	1577 9 (23, 1)
	1579 iconst_4 (23, 1)
	1580 istore (23, 1)
	1581 #12 (23, 1)
	1582 goto (23, 1)
	1583 147 (23, 1)
	1585 iload (25, 4)
	1586 #9 (25, 4)
	1587 iconst_1 (25, 4)
	1588 isub (25, 4)
	1589 istore (25, 4)
	1590 #13 (25, 4)
	1591 iload (25, 4)
	1592 #13 (25, 4)
	1593 iload (25, 4)
	1594 #11 (25, 4)
	1595 if_icmplt (25, 4)
	1596 99 (25, 4)
	1598 iload (26, 1)
	1599 #13 (26, 1)
	1600 iload (26, 1)
	1601 #11 (26, 1)
	1602 if_icmpne (26, 1)
	1603 6 (26, 1)
	1605 goto (26, 1)
	1606 89 (26, 1)
	1608 iload (25, 4)
	1609 #13 (25, 4)
	1610 iload (25, 4)
	1611 #9 (25, 4)
	1612 if_icmpeq (25, 4)
	1613 14 (25, 4)
	1615 aload (25, 4)
	1616 #5 (25, 4)
	1617 iload (25, 4)
	1618 #13 (25, 4)
	1619 daload (25, 4)
	1620 invokestatic (25, 4)
	1621 org/apache/commons/math3/util/FastMath.abs:(D)D (25, 4)
	1623 goto (25, 4)
	1624 4 (25, 4)
	1626 dconst_0 (25, 4)
	1627 iload (25, 4)
	1628 #13 (25, 4)
	1629 iload (25, 4)
	1630 #11 (25, 4)
	1631 iconst_1 (25, 4)
	1632 iadd (25, 4)
	1633 if_icmpeq (25, 4)
	1634 16 (25, 4)
	1636 aload (25, 4)
	1637 #5 (25, 4)
	1638 iload (25, 4)
	1639 #13 (25, 4)
	1640 iconst_1 (25, 4)
	1641 isub (25, 4)
	1642 daload (25, 4)
	1643 invokestatic (25, 4)
	1644 org/apache/commons/math3/util/FastMath.abs:(D)D (25, 4)
	1646 goto (25, 4)
	1647 4 (25, 4)
	1649 dconst_0 (25, 4)
	1650 dadd (25, 4)
	1651 dstore (25, 4)
	1652 #14 (25, 4)
	1653 aload_0 (26, 1)
	1654 getfield (26, 1)
	1655 org/apache/commons/math3/linear/SingularValueDecomposition.singularValues:[D (26, 1)
	1657 iload (26, 1)
	1658 #13 (26, 1)
	1659 daload (26, 1)
	1660 invokestatic (26, 1)
	1661 org/apache/commons/math3/util/FastMath.abs:(D)D (26, 1)
	1663 ldc2_w (26, 1)
	1664 1.6033346880071782e-291 (26, 1)
	1666 ldc2_w (26, 1)
	1667 2.220446049250313e-16 (26, 1)
	1669 dload (26, 1)
	1670 #14 (26, 1)
	1671 dmul (26, 1)
	1672 dadd (26, 1)
	1673 dcmpg (26, 1)
	1674 ifgt (26, 1)
	1675 14 (26, 1)
	1677 aload_0 (26, 1)
	1678 getfield (26, 1)
	1679 org/apache/commons/math3/linear/SingularValueDecomposition.singularValues:[D (26, 1)
	1681 iload (26, 1)
	1682 #13 (26, 1)
	1683 dconst_0 (26, 1)
	1684 dastore (26, 1)
	1685 goto (26, 1)
	1686 9 (26, 1)
	1688 iinc (26, 1)
	1689 #13 (26, 1)
	1690 -89 (26, 1)
	1691 goto (26, 1)
	1692 -100 (26, 1)
	1694 iload (26, 1)
	1695 #13 (26, 1)
	1696 iload (26, 1)
	1697 #11 (26, 1)
	1698 if_icmpne (26, 1)
	1699 9 (26, 1)
	1701 iconst_3 (26, 1)
	1702 istore (26, 1)
	1703 #12 (26, 1)
	1704 goto (26, 1)
	1705 25 (26, 1)
	1707 iload (27, 1)
	1708 #13 (27, 1)
	1709 iload (27, 1)
	1710 #9 (27, 1)
	1711 iconst_1 (27, 1)
	1712 isub (27, 1)
	1713 if_icmpne (27, 1)
	1714 9 (27, 1)
	1716 iconst_1 (27, 1)
	1717 istore (27, 1)
	1718 #12 (27, 1)
	1719 goto (27, 1)
	1720 10 (27, 1)
	1722 iconst_2 (28, 2)
	1723 istore (28, 2)
	1724 #12 (28, 2)
	1725 iload (28, 2)
	1726 #13 (28, 2)
	1727 istore (28, 2)
	1728 #11 (28, 2)
	1729 iinc (24, 2)
	1730 #11 (24, 2)
	1731 21 (24, 2)
	1732 iload (26, 5)
	1733 #12 (26, 5)
	1734 tableswitch (26, 5)
	1735 1 1760 (26, 5)
	1739 2 1969 (26, 5)
	1743 3 2157 (26, 5)
	1760 aload (26, 5)
	1761 #5 (26, 5)
	1762 iload (26, 5)
	1763 #9 (26, 5)
	1764 iconst_2 (26, 5)
	1765 isub (26, 5)
	1766 daload (26, 5)
	1767 dstore (26, 5)
	1768 #13 (26, 5)
	1769 aload (26, 5)
	1770 #5 (26, 5)
	1771 iload (26, 5)
	1772 #9 (26, 5)
	1773 iconst_2 (26, 5)
	1774 isub (26, 5)
	1775 dconst_0 (26, 5)
	1776 dastore (26, 5)
	1777 iload (27, 4)
	1778 #9 (27, 4)
	1779 iconst_2 (27, 4)
	1780 isub (27, 4)
	1781 istore (27, 4)
	1782 #15 (27, 4)
	1783 iload (27, 4)
	1784 #15 (27, 4)
	1785 iload (27, 4)
	1786 #11 (27, 4)
	1787 if_icmplt (27, 4)
	1788 179 (27, 4)
	1790 aload_0 (27, 4)
	1791 getfield (27, 4)
	1792 org/apache/commons/math3/linear/SingularValueDecomposition.singularValues:[D (27, 4)
	1794 iload (27, 4)
	1795 #15 (27, 4)
	1796 daload (27, 4)
	1797 dload (27, 4)
	1798 #13 (27, 4)
	1799 invokestatic (27, 4)
	1800 org/apache/commons/math3/util/FastMath.hypot:(DD)D (27, 4)
	1802 dstore (27, 4)
	1803 #16 (27, 4)
	1804 aload_0 (27, 4)
	1805 getfield (27, 4)
	1806 org/apache/commons/math3/linear/SingularValueDecomposition.singularValues:[D (27, 4)
	1808 iload (27, 4)
	1809 #15 (27, 4)
	1810 daload (27, 4)
	1811 dload (27, 4)
	1812 #16 (27, 4)
	1813 ddiv (27, 4)
	1814 dstore (27, 4)
	1815 #18 (27, 4)
	1816 dload (27, 4)
	1817 #13 (27, 4)
	1818 dload (27, 4)
	1819 #16 (27, 4)
	1820 ddiv (27, 4)
	1821 dstore (27, 4)
	1822 #20 (27, 4)
	1823 aload_0 (27, 4)
	1824 getfield (27, 4)
	1825 org/apache/commons/math3/linear/SingularValueDecomposition.singularValues:[D (27, 4)
	1827 iload (27, 4)
	1828 #15 (27, 4)
	1829 dload (27, 4)
	1830 #16 (27, 4)
	1831 dastore (27, 4)
	1832 iload (28, 1)
	1833 #15 (28, 1)
	1834 iload (28, 1)
	1835 #11 (28, 1)
	1836 if_icmpeq (28, 1)
	1837 33 (28, 1)
	1839 dload (28, 1)
	1840 #20 (28, 1)
	1841 dneg (28, 1)
	1842 aload (28, 1)
	1843 #5 (28, 1)
	1844 iload (28, 1)
	1845 #15 (28, 1)
	1846 iconst_1 (28, 1)
	1847 isub (28, 1)
	1848 daload (28, 1)
	1849 dmul (28, 1)
	1850 dstore (28, 1)
	1851 #13 (28, 1)
	1852 aload (28, 1)
	1853 #5 (28, 1)
	1854 iload (28, 1)
	1855 #15 (28, 1)
	1856 iconst_1 (28, 1)
	1857 isub (28, 1)
	1858 dload (28, 1)
	1859 #18 (28, 1)
	1860 aload (28, 1)
	1861 #5 (28, 1)
	1862 iload (28, 1)
	1863 #15 (28, 1)
	1864 iconst_1 (28, 1)
	1865 isub (28, 1)
	1866 daload (28, 1)
	1867 dmul (28, 1)
	1868 dastore (28, 1)
	1869 iconst_0 (28, 4)
	1870 istore (28, 4)
	1871 #22 (28, 4)
	1872 iload (28, 4)
	1873 #22 (28, 4)
	1874 aload_0 (28, 4)
	1875 getfield (28, 4)
	1876 org/apache/commons/math3/linear/SingularValueDecomposition.n:I (28, 4)
	1878 if_icmpge (28, 4)
	1879 82 (28, 4)
	1881 dload (28, 4)
	1882 #18 (28, 4)
	1883 aload (28, 4)
	1884 #4 (28, 4)
	1885 iload (28, 4)
	1886 #22 (28, 4)
	1887 aaload (28, 4)
	1888 iload (28, 4)
	1889 #15 (28, 4)
	1890 daload (28, 4)
	1891 dmul (28, 4)
	1892 dload (28, 4)
	1893 #20 (28, 4)
	1894 aload (28, 4)
	1895 #4 (28, 4)
	1896 iload (28, 4)
	1897 #22 (28, 4)
	1898 aaload (28, 4)
	1899 iload (28, 4)
	1900 #9 (28, 4)
	1901 iconst_1 (28, 4)
	1902 isub (28, 4)
	1903 daload (28, 4)
	1904 dmul (28, 4)
	1905 dadd (28, 4)
	1906 dstore (28, 4)
	1907 #16 (28, 4)
	1908 aload (28, 4)
	1909 #4 (28, 4)
	1910 iload (28, 4)
	1911 #22 (28, 4)
	1912 aaload (28, 4)
	1913 iload (28, 4)
	1914 #9 (28, 4)
	1915 iconst_1 (28, 4)
	1916 isub (28, 4)
	1917 dload (28, 4)
	1918 #20 (28, 4)
	1919 dneg (28, 4)
	1920 aload (28, 4)
	1921 #4 (28, 4)
	1922 iload (28, 4)
	1923 #22 (28, 4)
	1924 aaload (28, 4)
	1925 iload (28, 4)
	1926 #15 (28, 4)
	1927 daload (28, 4)
	1928 dmul (28, 4)
	1929 dload (28, 4)
	1930 #18 (28, 4)
	1931 aload (28, 4)
	1932 #4 (28, 4)
	1933 iload (28, 4)
	1934 #22 (28, 4)
	1935 aaload (28, 4)
	1936 iload (28, 4)
	1937 #9 (28, 4)
	1938 iconst_1 (28, 4)
	1939 isub (28, 4)
	1940 daload (28, 4)
	1941 dmul (28, 4)
	1942 dadd (28, 4)
	1943 dastore (28, 4)
	1944 aload (28, 4)
	1945 #4 (28, 4)
	1946 iload (28, 4)
	1947 #22 (28, 4)
	1948 aaload (28, 4)
	1949 iload (28, 4)
	1950 #15 (28, 4)
	1951 dload (28, 4)
	1952 #16 (28, 4)
	1953 dastore (28, 4)
	1954 iinc (28, 4)
	1955 #22 (28, 4)
	1956 -89 (28, 4)
	1957 goto (28, 4)
	1958 -85 (28, 4)
	1960 iinc (28, 4)
	1961 #15 (28, 4)
	1962 -89 (28, 4)
	1963 goto (28, 4)
	1964 -180 (28, 4)
	1966 goto (26, 5)
	1967 1171 (26, 5)
	1969 aload (26, 5)
	1970 #5 (26, 5)
	1971 iload (26, 5)
	1972 #11 (26, 5)
	1973 iconst_1 (26, 5)
	1974 isub (26, 5)
	1975 daload (26, 5)
	1976 dstore (26, 5)
	1977 #13 (26, 5)
	1978 aload (26, 5)
	1979 #5 (26, 5)
	1980 iload (26, 5)
	1981 #11 (26, 5)
	1982 iconst_1 (26, 5)
	1983 isub (26, 5)
	1984 dconst_0 (26, 5)
	1985 dastore (26, 5)
	1986 iload (27, 4)
	1987 #11 (27, 4)
	1988 istore (27, 4)
	1989 #15 (27, 4)
	1990 iload (27, 4)
	1991 #15 (27, 4)
	1992 iload (27, 4)
	1993 #9 (27, 4)
	1994 if_icmpge (27, 4)
	1995 160 (27, 4)
	1997 aload_0 (27, 4)
	1998 getfield (27, 4)
	1999 org/apache/commons/math3/linear/SingularValueDecomposition.singularValues:[D (27, 4)
	2001 iload (27, 4)
	2002 #15 (27, 4)
	2003 daload (27, 4)
	2004 dload (27, 4)
	2005 #13 (27, 4)
	2006 invokestatic (27, 4)
	2007 org/apache/commons/math3/util/FastMath.hypot:(DD)D (27, 4)
	2009 dstore (27, 4)
	2010 #16 (27, 4)
	2011 aload_0 (27, 4)
	2012 getfield (27, 4)
	2013 org/apache/commons/math3/linear/SingularValueDecomposition.singularValues:[D (27, 4)
	2015 iload (27, 4)
	2016 #15 (27, 4)
	2017 daload (27, 4)
	2018 dload (27, 4)
	2019 #16 (27, 4)
	2020 ddiv (27, 4)
	2021 dstore (27, 4)
	2022 #18 (27, 4)
	2023 dload (27, 4)
	2024 #13 (27, 4)
	2025 dload (27, 4)
	2026 #16 (27, 4)
	2027 ddiv (27, 4)
	2028 dstore (27, 4)
	2029 #20 (27, 4)
	2030 aload_0 (27, 4)
	2031 getfield (27, 4)
	2032 org/apache/commons/math3/linear/SingularValueDecomposition.singularValues:[D (27, 4)
	2034 iload (27, 4)
	2035 #15 (27, 4)
	2036 dload (27, 4)
	2037 #16 (27, 4)
	2038 dastore (27, 4)
	2039 dload (27, 4)
	2040 #20 (27, 4)
	2041 dneg (27, 4)
	2042 aload (27, 4)
	2043 #5 (27, 4)
	2044 iload (27, 4)
	2045 #15 (27, 4)
	2046 daload (27, 4)
	2047 dmul (27, 4)
	2048 dstore (27, 4)
	2049 #13 (27, 4)
	2050 aload (27, 4)
	2051 #5 (27, 4)
	2052 iload (27, 4)
	2053 #15 (27, 4)
	2054 dload (27, 4)
	2055 #18 (27, 4)
	2056 aload (27, 4)
	2057 #5 (27, 4)
	2058 iload (27, 4)
	2059 #15 (27, 4)
	2060 daload (27, 4)
	2061 dmul (27, 4)
	2062 dastore (27, 4)
	2063 iconst_0 (28, 4)
	2064 istore (28, 4)
	2065 #22 (28, 4)
	2066 iload (28, 4)
	2067 #22 (28, 4)
	2068 aload_0 (28, 4)
	2069 getfield (28, 4)
	2070 org/apache/commons/math3/linear/SingularValueDecomposition.m:I (28, 4)
	2072 if_icmpge (28, 4)
	2073 76 (28, 4)
	2075 dload (28, 4)
	2076 #18 (28, 4)
	2077 aload_3 (28, 4)
	2078 iload (28, 4)
	2079 #22 (28, 4)
	2080 aaload (28, 4)
	2081 iload (28, 4)
	2082 #15 (28, 4)
	2083 daload (28, 4)
	2084 dmul (28, 4)
	2085 dload (28, 4)
	2086 #20 (28, 4)
	2087 aload_3 (28, 4)
	2088 iload (28, 4)
	2089 #22 (28, 4)
	2090 aaload (28, 4)
	2091 iload (28, 4)
	2092 #11 (28, 4)
	2093 iconst_1 (28, 4)
	2094 isub (28, 4)
	2095 daload (28, 4)
	2096 dmul (28, 4)
	2097 dadd (28, 4)
	2098 dstore (28, 4)
	2099 #16 (28, 4)
	2100 aload_3 (28, 4)
	2101 iload (28, 4)
	2102 #22 (28, 4)
	2103 aaload (28, 4)
	2104 iload (28, 4)
	2105 #11 (28, 4)
	2106 iconst_1 (28, 4)
	2107 isub (28, 4)
	2108 dload (28, 4)
	2109 #20 (28, 4)
	2110 dneg (28, 4)
	2111 aload_3 (28, 4)
	2112 iload (28, 4)
	2113 #22 (28, 4)
	2114 aaload (28, 4)
	2115 iload (28, 4)
	2116 #15 (28, 4)
	2117 daload (28, 4)
	2118 dmul (28, 4)
	2119 dload (28, 4)
	2120 #18 (28, 4)
	2121 aload_3 (28, 4)
	2122 iload (28, 4)
	2123 #22 (28, 4)
	2124 aaload (28, 4)
	2125 iload (28, 4)
	2126 #11 (28, 4)
	2127 iconst_1 (28, 4)
	2128 isub (28, 4)
	2129 daload (28, 4)
	2130 dmul (28, 4)
	2131 dadd (28, 4)
	2132 dastore (28, 4)
	2133 aload_3 (28, 4)
	2134 iload (28, 4)
	2135 #22 (28, 4)
	2136 aaload (28, 4)
	2137 iload (28, 4)
	2138 #15 (28, 4)
	2139 dload (28, 4)
	2140 #16 (28, 4)
	2141 dastore (28, 4)
	2142 iinc (28, 4)
	2143 #22 (28, 4)
	2144 -89 (28, 4)
	2145 goto (28, 4)
	2146 -79 (28, 4)
	2148 iinc (28, 4)
	2149 #15 (28, 4)
	2150 -89 (28, 4)
	2151 goto (28, 4)
	2152 -161 (28, 4)
	2154 goto (26, 5)
	2155 983 (26, 5)
	2157 aload_0 (28, 1)
	2158 getfield (28, 1)
	2159 org/apache/commons/math3/linear/SingularValueDecomposition.singularValues:[D (28, 1)
	2161 iload (28, 1)
	2162 #9 (28, 1)
	2163 iconst_1 (28, 1)
	2164 isub (28, 1)
	2165 daload (28, 1)
	2166 invokestatic (28, 1)
	2167 org/apache/commons/math3/util/FastMath.abs:(D)D (28, 1)
	2169 aload_0 (28, 1)
	2170 getfield (28, 1)
	2171 org/apache/commons/math3/linear/SingularValueDecomposition.singularValues:[D (28, 1)
	2173 iload (28, 1)
	2174 #9 (28, 1)
	2175 iconst_2 (28, 1)
	2176 isub (28, 1)
	2177 daload (28, 1)
	2178 invokestatic (28, 1)
	2179 org/apache/commons/math3/util/FastMath.abs:(D)D (28, 1)
	2181 invokestatic (28, 1)
	2182 org/apache/commons/math3/util/FastMath.max:(DD)D (28, 1)
	2184 dstore (28, 1)
	2185 #13 (28, 1)
	2186 dload (28, 1)
	2187 #13 (28, 1)
	2188 aload (28, 1)
	2189 #5 (28, 1)
	2190 iload (28, 1)
	2191 #9 (28, 1)
	2192 iconst_2 (28, 1)
	2193 isub (28, 1)
	2194 daload (28, 1)
	2195 invokestatic (28, 1)
	2196 org/apache/commons/math3/util/FastMath.abs:(D)D (28, 1)
	2198 invokestatic (28, 1)
	2199 org/apache/commons/math3/util/FastMath.max:(DD)D (28, 1)
	2201 aload_0 (28, 1)
	2202 getfield (28, 1)
	2203 org/apache/commons/math3/linear/SingularValueDecomposition.singularValues:[D (28, 1)
	2205 iload (28, 1)
	2206 #11 (28, 1)
	2207 daload (28, 1)
	2208 invokestatic (28, 1)
	2209 org/apache/commons/math3/util/FastMath.abs:(D)D (28, 1)
	2211 invokestatic (28, 1)
	2212 org/apache/commons/math3/util/FastMath.max:(DD)D (28, 1)
	2214 aload (28, 1)
	2215 #5 (28, 1)
	2216 iload (28, 1)
	2217 #11 (28, 1)
	2218 daload (28, 1)
	2219 invokestatic (28, 1)
	2220 org/apache/commons/math3/util/FastMath.abs:(D)D (28, 1)
	2222 invokestatic (28, 1)
	2223 org/apache/commons/math3/util/FastMath.max:(DD)D (28, 1)
	2225 dstore (28, 1)
	2226 #15 (28, 1)
	2227 aload_0 (28, 1)
	2228 getfield (28, 1)
	2229 org/apache/commons/math3/linear/SingularValueDecomposition.singularValues:[D (28, 1)
	2231 iload (28, 1)
	2232 #9 (28, 1)
	2233 iconst_1 (28, 1)
	2234 isub (28, 1)
	2235 daload (28, 1)
	2236 dload (28, 1)
	2237 #15 (28, 1)
	2238 ddiv (28, 1)
	2239 dstore (28, 1)
	2240 #17 (28, 1)
	2241 aload_0 (28, 1)
	2242 getfield (28, 1)
	2243 org/apache/commons/math3/linear/SingularValueDecomposition.singularValues:[D (28, 1)
	2245 iload (28, 1)
	2246 #9 (28, 1)
	2247 iconst_2 (28, 1)
	2248 isub (28, 1)
	2249 daload (28, 1)
	2250 dload (28, 1)
	2251 #15 (28, 1)
	2252 ddiv (28, 1)
	2253 dstore (28, 1)
	2254 #19 (28, 1)
	2255 aload (28, 1)
	2256 #5 (28, 1)
	2257 iload (28, 1)
	2258 #9 (28, 1)
	2259 iconst_2 (28, 1)
	2260 isub (28, 1)
	2261 daload (28, 1)
	2262 dload (28, 1)
	2263 #15 (28, 1)
	2264 ddiv (28, 1)
	2265 dstore (28, 1)
	2266 #21 (28, 1)
	2267 aload_0 (28, 1)
	2268 getfield (28, 1)
	2269 org/apache/commons/math3/linear/SingularValueDecomposition.singularValues:[D (28, 1)
	2271 iload (28, 1)
	2272 #11 (28, 1)
	2273 daload (28, 1)
	2274 dload (28, 1)
	2275 #15 (28, 1)
	2276 ddiv (28, 1)
	2277 dstore (28, 1)
	2278 #23 (28, 1)
	2279 aload (28, 1)
	2280 #5 (28, 1)
	2281 iload (28, 1)
	2282 #11 (28, 1)
	2283 daload (28, 1)
	2284 dload (28, 1)
	2285 #15 (28, 1)
	2286 ddiv (28, 1)
	2287 dstore (28, 1)
	2288 #25 (28, 1)
	2289 dload (28, 1)
	2290 #19 (28, 1)
	2291 dload (28, 1)
	2292 #17 (28, 1)
	2293 dadd (28, 1)
	2294 dload (28, 1)
	2295 #19 (28, 1)
	2296 dload (28, 1)
	2297 #17 (28, 1)
	2298 dsub (28, 1)
	2299 dmul (28, 1)
	2300 dload (28, 1)
	2301 #21 (28, 1)
	2302 dload (28, 1)
	2303 #21 (28, 1)
	2304 dmul (28, 1)
	2305 dadd (28, 1)
	2306 ldc2_w (28, 1)
	2307 2.0 (28, 1)
	2309 ddiv (28, 1)
	2310 dstore (28, 1)
	2311 #27 (28, 1)
	2312 dload (28, 1)
	2313 #17 (28, 1)
	2314 dload (28, 1)
	2315 #21 (28, 1)
	2316 dmul (28, 1)
	2317 dload (28, 1)
	2318 #17 (28, 1)
	2319 dload (28, 1)
	2320 #21 (28, 1)
	2321 dmul (28, 1)
	2322 dmul (28, 1)
	2323 dstore (28, 1)
	2324 #29 (28, 1)
	2325 dconst_0 (29, 1)
	2326 dstore (29, 1)
	2327 #31 (29, 1)
	2328 dload (30, 1)
	2329 #27 (30, 1)
	2330 dconst_0 (30, 1)
	2331 dcmpl (30, 1)
	2332 ifne (30, 1)
	2333 10 (30, 1)
	2335 dload (30, 1)
	2336 #29 (30, 1)
	2337 dconst_0 (30, 1)
	2338 dcmpl (30, 1)
	2339 ifeq (30, 1)
	2340 38 (30, 1)
	2342 dload (31, 1)
	2343 #27 (31, 1)
	2344 dload (31, 1)
	2345 #27 (31, 1)
	2346 dmul (31, 1)
	2347 dload (31, 1)
	2348 #29 (31, 1)
	2349 dadd (31, 1)
	2350 invokestatic (31, 1)
	2351 org/apache/commons/math3/util/FastMath.sqrt:(D)D (31, 1)
	2353 dstore (31, 1)
	2354 #31 (31, 1)
	2355 dload (32, 1)
	2356 #27 (32, 1)
	2357 dconst_0 (32, 1)
	2358 dcmpg (32, 1)
	2359 ifge (32, 1)
	2360 8 (32, 1)
	2362 dload (33, 1)
	2363 #31 (33, 1)
	2364 dneg (33, 1)
	2365 dstore (33, 1)
	2366 #31 (33, 1)
	2367 dload (32, 1)
	2368 #29 (32, 1)
	2369 dload (32, 1)
	2370 #27 (32, 1)
	2371 dload (32, 1)
	2372 #31 (32, 1)
	2373 dadd (32, 1)
	2374 ddiv (32, 1)
	2375 dstore (32, 1)
	2376 #31 (32, 1)
	2377 dload (31, 1)
	2378 #23 (31, 1)
	2379 dload (31, 1)
	2380 #17 (31, 1)
	2381 dadd (31, 1)
	2382 dload (31, 1)
	2383 #23 (31, 1)
	2384 dload (31, 1)
	2385 #17 (31, 1)
	2386 dsub (31, 1)
	2387 dmul (31, 1)
	2388 dload (31, 1)
	2389 #31 (31, 1)
	2390 dadd (31, 1)
	2391 dstore (31, 1)
	2392 #33 (31, 1)
	2393 dload (31, 1)
	2394 #23 (31, 1)
	2395 dload (31, 1)
	2396 #25 (31, 1)
	2397 dmul (31, 1)
	2398 dstore (31, 1)
	2399 #35 (31, 1)
	2400 iload (32, 4)
	2401 #11 (32, 4)
	2402 istore (32, 4)
	2403 #37 (32, 4)
	2404 iload (32, 4)
	2405 #37 (32, 4)
	2406 iload (32, 4)
	2407 #9 (32, 4)
	2408 iconst_1 (32, 4)
	2409 isub (32, 4)
	2410 if_icmpge (32, 4)
	2411 430 (32, 4)
	2413 dload (32, 4)
	2414 #33 (32, 4)
	2415 dload (32, 4)
	2416 #35 (32, 4)
	2417 invokestatic (32, 4)
	2418 org/apache/commons/math3/util/FastMath.hypot:(DD)D (32, 4)
	2420 dstore (32, 4)
	2421 #38 (32, 4)
	2422 dload (32, 4)
	2423 #33 (32, 4)
	2424 dload (32, 4)
	2425 #38 (32, 4)
	2426 ddiv (32, 4)
	2427 dstore (32, 4)
	2428 #40 (32, 4)
	2429 dload (32, 4)
	2430 #35 (32, 4)
	2431 dload (32, 4)
	2432 #38 (32, 4)
	2433 ddiv (32, 4)
	2434 dstore (32, 4)
	2435 #42 (32, 4)
	2436 iload (33, 1)
	2437 #37 (33, 1)
	2438 iload (33, 1)
	2439 #11 (33, 1)
	2440 if_icmpeq (33, 1)
	2441 12 (33, 1)
	2443 aload (33, 1)
	2444 #5 (33, 1)
	2445 iload (33, 1)
	2446 #37 (33, 1)
	2447 iconst_1 (33, 1)
	2448 isub (33, 1)
	2449 dload (33, 1)
	2450 #38 (33, 1)
	2451 dastore (33, 1)
	2452 dload (32, 4)
	2453 #40 (32, 4)
	2454 aload_0 (32, 4)
	2455 getfield (32, 4)
	2456 org/apache/commons/math3/linear/SingularValueDecomposition.singularValues:[D (32, 4)
	2458 iload (32, 4)
	2459 #37 (32, 4)
	2460 daload (32, 4)
	2461 dmul (32, 4)
	2462 dload (32, 4)
	2463 #42 (32, 4)
	2464 aload (32, 4)
	2465 #5 (32, 4)
	2466 iload (32, 4)
	2467 #37 (32, 4)
	2468 daload (32, 4)
	2469 dmul (32, 4)
	2470 dadd (32, 4)
	2471 dstore (32, 4)
	2472 #33 (32, 4)
	2473 aload (32, 4)
	2474 #5 (32, 4)
	2475 iload (32, 4)
	2476 #37 (32, 4)
	2477 dload (32, 4)
	2478 #40 (32, 4)
	2479 aload (32, 4)
	2480 #5 (32, 4)
	2481 iload (32, 4)
	2482 #37 (32, 4)
	2483 daload (32, 4)
	2484 dmul (32, 4)
	2485 dload (32, 4)
	2486 #42 (32, 4)
	2487 aload_0 (32, 4)
	2488 getfield (32, 4)
	2489 org/apache/commons/math3/linear/SingularValueDecomposition.singularValues:[D (32, 4)
	2491 iload (32, 4)
	2492 #37 (32, 4)
	2493 daload (32, 4)
	2494 dmul (32, 4)
	2495 dsub (32, 4)
	2496 dastore (32, 4)
	2497 dload (32, 4)
	2498 #42 (32, 4)
	2499 aload_0 (32, 4)
	2500 getfield (32, 4)
	2501 org/apache/commons/math3/linear/SingularValueDecomposition.singularValues:[D (32, 4)
	2503 iload (32, 4)
	2504 #37 (32, 4)
	2505 iconst_1 (32, 4)
	2506 iadd (32, 4)
	2507 daload (32, 4)
	2508 dmul (32, 4)
	2509 dstore (32, 4)
	2510 #35 (32, 4)
	2511 aload_0 (32, 4)
	2512 getfield (32, 4)
	2513 org/apache/commons/math3/linear/SingularValueDecomposition.singularValues:[D (32, 4)
	2515 iload (32, 4)
	2516 #37 (32, 4)
	2517 iconst_1 (32, 4)
	2518 iadd (32, 4)
	2519 dload (32, 4)
	2520 #40 (32, 4)
	2521 aload_0 (32, 4)
	2522 getfield (32, 4)
	2523 org/apache/commons/math3/linear/SingularValueDecomposition.singularValues:[D (32, 4)
	2525 iload (32, 4)
	2526 #37 (32, 4)
	2527 iconst_1 (32, 4)
	2528 iadd (32, 4)
	2529 daload (32, 4)
	2530 dmul (32, 4)
	2531 dastore (32, 4)
	2532 iconst_0 (33, 4)
	2533 istore (33, 4)
	2534 #44 (33, 4)
	2535 iload (33, 4)
	2536 #44 (33, 4)
	2537 aload_0 (33, 4)
	2538 getfield (33, 4)
	2539 org/apache/commons/math3/linear/SingularValueDecomposition.n:I (33, 4)
	2541 if_icmpge (33, 4)
	2542 82 (33, 4)
	2544 dload (33, 4)
	2545 #40 (33, 4)
	2546 aload (33, 4)
	2547 #4 (33, 4)
	2548 iload (33, 4)
	2549 #44 (33, 4)
	2550 aaload (33, 4)
	2551 iload (33, 4)
	2552 #37 (33, 4)
	2553 daload (33, 4)
	2554 dmul (33, 4)
	2555 dload (33, 4)
	2556 #42 (33, 4)
	2557 aload (33, 4)
	2558 #4 (33, 4)
	2559 iload (33, 4)
	2560 #44 (33, 4)
	2561 aaload (33, 4)
	2562 iload (33, 4)
	2563 #37 (33, 4)
	2564 iconst_1 (33, 4)
	2565 iadd (33, 4)
	2566 daload (33, 4)
	2567 dmul (33, 4)
	2568 dadd (33, 4)
	2569 dstore (33, 4)
	2570 #38 (33, 4)
	2571 aload (33, 4)
	2572 #4 (33, 4)
	2573 iload (33, 4)
	2574 #44 (33, 4)
	2575 aaload (33, 4)
	2576 iload (33, 4)
	2577 #37 (33, 4)
	2578 iconst_1 (33, 4)
	2579 iadd (33, 4)
	2580 dload (33, 4)
	2581 #42 (33, 4)
	2582 dneg (33, 4)
	2583 aload (33, 4)
	2584 #4 (33, 4)
	2585 iload (33, 4)
	2586 #44 (33, 4)
	2587 aaload (33, 4)
	2588 iload (33, 4)
	2589 #37 (33, 4)
	2590 daload (33, 4)
	2591 dmul (33, 4)
	2592 dload (33, 4)
	2593 #40 (33, 4)
	2594 aload (33, 4)
	2595 #4 (33, 4)
	2596 iload (33, 4)
	2597 #44 (33, 4)
	2598 aaload (33, 4)
	2599 iload (33, 4)
	2600 #37 (33, 4)
	2601 iconst_1 (33, 4)
	2602 iadd (33, 4)
	2603 daload (33, 4)
	2604 dmul (33, 4)
	2605 dadd (33, 4)
	2606 dastore (33, 4)
	2607 aload (33, 4)
	2608 #4 (33, 4)
	2609 iload (33, 4)
	2610 #44 (33, 4)
	2611 aaload (33, 4)
	2612 iload (33, 4)
	2613 #37 (33, 4)
	2614 dload (33, 4)
	2615 #38 (33, 4)
	2616 dastore (33, 4)
	2617 iinc (33, 4)
	2618 #44 (33, 4)
	2619 -89 (33, 4)
	2620 goto (33, 4)
	2621 -85 (33, 4)
	2623 dload (32, 4)
	2624 #33 (32, 4)
	2625 dload (32, 4)
	2626 #35 (32, 4)
	2627 invokestatic (32, 4)
	2628 org/apache/commons/math3/util/FastMath.hypot:(DD)D (32, 4)
	2630 dstore (32, 4)
	2631 #38 (32, 4)
	2632 dload (32, 4)
	2633 #33 (32, 4)
	2634 dload (32, 4)
	2635 #38 (32, 4)
	2636 ddiv (32, 4)
	2637 dstore (32, 4)
	2638 #40 (32, 4)
	2639 dload (32, 4)
	2640 #35 (32, 4)
	2641 dload (32, 4)
	2642 #38 (32, 4)
	2643 ddiv (32, 4)
	2644 dstore (32, 4)
	2645 #42 (32, 4)
	2646 aload_0 (32, 4)
	2647 getfield (32, 4)
	2648 org/apache/commons/math3/linear/SingularValueDecomposition.singularValues:[D (32, 4)
	2650 iload (32, 4)
	2651 #37 (32, 4)
	2652 dload (32, 4)
	2653 #38 (32, 4)
	2654 dastore (32, 4)
	2655 dload (32, 4)
	2656 #40 (32, 4)
	2657 aload (32, 4)
	2658 #5 (32, 4)
	2659 iload (32, 4)
	2660 #37 (32, 4)
	2661 daload (32, 4)
	2662 dmul (32, 4)
	2663 dload (32, 4)
	2664 #42 (32, 4)
	2665 aload_0 (32, 4)
	2666 getfield (32, 4)
	2667 org/apache/commons/math3/linear/SingularValueDecomposition.singularValues:[D (32, 4)
	2669 iload (32, 4)
	2670 #37 (32, 4)
	2671 iconst_1 (32, 4)
	2672 iadd (32, 4)
	2673 daload (32, 4)
	2674 dmul (32, 4)
	2675 dadd (32, 4)
	2676 dstore (32, 4)
	2677 #33 (32, 4)
	2678 aload_0 (32, 4)
	2679 getfield (32, 4)
	2680 org/apache/commons/math3/linear/SingularValueDecomposition.singularValues:[D (32, 4)
	2682 iload (32, 4)
	2683 #37 (32, 4)
	2684 iconst_1 (32, 4)
	2685 iadd (32, 4)
	2686 dload (32, 4)
	2687 #42 (32, 4)
	2688 dneg (32, 4)
	2689 aload (32, 4)
	2690 #5 (32, 4)
	2691 iload (32, 4)
	2692 #37 (32, 4)
	2693 daload (32, 4)
	2694 dmul (32, 4)
	2695 dload (32, 4)
	2696 #40 (32, 4)
	2697 aload_0 (32, 4)
	2698 getfield (32, 4)
	2699 org/apache/commons/math3/linear/SingularValueDecomposition.singularValues:[D (32, 4)
	2701 iload (32, 4)
	2702 #37 (32, 4)
	2703 iconst_1 (32, 4)
	2704 iadd (32, 4)
	2705 daload (32, 4)
	2706 dmul (32, 4)
	2707 dadd (32, 4)
	2708 dastore (32, 4)
	2709 dload (32, 4)
	2710 #42 (32, 4)
	2711 aload (32, 4)
	2712 #5 (32, 4)
	2713 iload (32, 4)
	2714 #37 (32, 4)
	2715 iconst_1 (32, 4)
	2716 iadd (32, 4)
	2717 daload (32, 4)
	2718 dmul (32, 4)
	2719 dstore (32, 4)
	2720 #35 (32, 4)
	2721 aload (32, 4)
	2722 #5 (32, 4)
	2723 iload (32, 4)
	2724 #37 (32, 4)
	2725 iconst_1 (32, 4)
	2726 iadd (32, 4)
	2727 dload (32, 4)
	2728 #40 (32, 4)
	2729 aload (32, 4)
	2730 #5 (32, 4)
	2731 iload (32, 4)
	2732 #37 (32, 4)
	2733 iconst_1 (32, 4)
	2734 iadd (32, 4)
	2735 daload (32, 4)
	2736 dmul (32, 4)
	2737 dastore (32, 4)
	2738 iload (33, 1)
	2739 #37 (33, 1)
	2740 aload_0 (33, 1)
	2741 getfield (33, 1)
	2742 org/apache/commons/math3/linear/SingularValueDecomposition.m:I (33, 1)
	2744 iconst_1 (33, 1)
	2745 isub (33, 1)
	2746 if_icmpge (33, 1)
	2747 88 (33, 1)
	2749 iconst_0 (34, 4)
	2750 istore (34, 4)
	2751 #44 (34, 4)
	2752 iload (34, 4)
	2753 #44 (34, 4)
	2754 aload_0 (34, 4)
	2755 getfield (34, 4)
	2756 org/apache/commons/math3/linear/SingularValueDecomposition.m:I (34, 4)
	2758 if_icmpge (34, 4)
	2759 76 (34, 4)
	2761 dload (34, 4)
	2762 #40 (34, 4)
	2763 aload_3 (34, 4)
	2764 iload (34, 4)
	2765 #44 (34, 4)
	2766 aaload (34, 4)
	2767 iload (34, 4)
	2768 #37 (34, 4)
	2769 daload (34, 4)
	2770 dmul (34, 4)
	2771 dload (34, 4)
	2772 #42 (34, 4)
	2773 aload_3 (34, 4)
	2774 iload (34, 4)
	2775 #44 (34, 4)
	2776 aaload (34, 4)
	2777 iload (34, 4)
	2778 #37 (34, 4)
	2779 iconst_1 (34, 4)
	2780 iadd (34, 4)
	2781 daload (34, 4)
	2782 dmul (34, 4)
	2783 dadd (34, 4)
	2784 dstore (34, 4)
	2785 #38 (34, 4)
	2786 aload_3 (34, 4)
	2787 iload (34, 4)
	2788 #44 (34, 4)
	2789 aaload (34, 4)
	2790 iload (34, 4)
	2791 #37 (34, 4)
	2792 iconst_1 (34, 4)
	2793 iadd (34, 4)
	2794 dload (34, 4)
	2795 #42 (34, 4)
	2796 dneg (34, 4)
	2797 aload_3 (34, 4)
	2798 iload (34, 4)
	2799 #44 (34, 4)
	2800 aaload (34, 4)
	2801 iload (34, 4)
	2802 #37 (34, 4)
	2803 daload (34, 4)
	2804 dmul (34, 4)
	2805 dload (34, 4)
	2806 #40 (34, 4)
	2807 aload_3 (34, 4)
	2808 iload (34, 4)
	2809 #44 (34, 4)
	2810 aaload (34, 4)
	2811 iload (34, 4)
	2812 #37 (34, 4)
	2813 iconst_1 (34, 4)
	2814 iadd (34, 4)
	2815 daload (34, 4)
	2816 dmul (34, 4)
	2817 dadd (34, 4)
	2818 dastore (34, 4)
	2819 aload_3 (34, 4)
	2820 iload (34, 4)
	2821 #44 (34, 4)
	2822 aaload (34, 4)
	2823 iload (34, 4)
	2824 #37 (34, 4)
	2825 dload (34, 4)
	2826 #38 (34, 4)
	2827 dastore (34, 4)
	2828 iinc (34, 4)
	2829 #44 (34, 4)
	2830 -89 (34, 4)
	2831 goto (34, 4)
	2832 -79 (34, 4)
	2834 iinc (34, 4)
	2835 #37 (34, 4)
	2836 -89 (34, 4)
	2837 goto (34, 4)
	2838 -433 (34, 4)
	2840 aload (33, 1)
	2841 #5 (33, 1)
	2842 iload (33, 1)
	2843 #9 (33, 1)
	2844 iconst_2 (33, 1)
	2845 isub (33, 1)
	2846 dload (33, 1)
	2847 #33 (33, 1)
	2848 dastore (33, 1)
	2849 goto (32, 4)
	2850 288 (32, 4)
	2852 aload_0 (33, 1)
	2853 getfield (33, 1)
	2854 org/apache/commons/math3/linear/SingularValueDecomposition.singularValues:[D (33, 1)
	2856 iload (33, 1)
	2857 #11 (33, 1)
	2858 daload (33, 1)
	2859 dconst_0 (33, 1)
	2860 dcmpg (33, 1)
	2861 ifgt (33, 1)
	2862 67 (33, 1)
	2864 aload_0 (33, 1)
	2865 getfield (33, 1)
	2866 org/apache/commons/math3/linear/SingularValueDecomposition.singularValues:[D (33, 1)
	2868 iload (33, 1)
	2869 #11 (33, 1)
	2870 aload_0 (33, 1)
	2871 getfield (33, 1)
	2872 org/apache/commons/math3/linear/SingularValueDecomposition.singularValues:[D (33, 1)
	2874 iload (33, 1)
	2875 #11 (33, 1)
	2876 daload (33, 1)
	2877 dconst_0 (33, 1)
	2878 dcmpg (33, 1)
	2879 ifge (33, 1)
	2880 14 (33, 1)
	2882 aload_0 (33, 1)
	2883 getfield (33, 1)
	2884 org/apache/commons/math3/linear/SingularValueDecomposition.singularValues:[D (33, 1)
	2886 iload (33, 1)
	2887 #11 (33, 1)
	2888 daload (33, 1)
	2889 dneg (33, 1)
	2890 goto (33, 1)
	2891 4 (33, 1)
	2893 dconst_0 (33, 1)
	2894 dastore (33, 1)
	2895 iconst_0 (34, 4)
	2896 istore (34, 4)
	2897 #13 (34, 4)
	2898 iload (34, 4)
	2899 #13 (34, 4)
	2900 iload (34, 4)
	2901 #10 (34, 4)
	2902 if_icmpgt (34, 4)
	2903 26 (34, 4)
	2905 aload (34, 4)
	2906 #4 (34, 4)
	2907 iload (34, 4)
	2908 #13 (34, 4)
	2909 aaload (34, 4)
	2910 iload (34, 4)
	2911 #11 (34, 4)
	2912 aload (34, 4)
	2913 #4 (34, 4)
	2914 iload (34, 4)
	2915 #13 (34, 4)
	2916 aaload (34, 4)
	2917 iload (34, 4)
	2918 #11 (34, 4)
	2919 daload (34, 4)
	2920 dneg (34, 4)
	2921 dastore (34, 4)
	2922 iinc (34, 4)
	2923 #13 (34, 4)
	2924 -89 (34, 4)
	2925 goto (34, 4)
	2926 -27 (34, 4)
	2928 iload (33, 3)
	2929 #11 (33, 3)
	2930 iload (33, 3)
	2931 #10 (33, 3)
	2932 if_icmpge (33, 3)
	2933 202 (33, 3)
	2935 aload_0 (34, 1)
	2936 getfield (34, 1)
	2937 org/apache/commons/math3/linear/SingularValueDecomposition.singularValues:[D (34, 1)
	2939 iload (34, 1)
	2940 #11 (34, 1)
	2941 daload (34, 1)
	2942 aload_0 (34, 1)
	2943 getfield (34, 1)
	2944 org/apache/commons/math3/linear/SingularValueDecomposition.singularValues:[D (34, 1)
	2946 iload (34, 1)
	2947 #11 (34, 1)
	2948 iconst_1 (34, 1)
	2949 iadd (34, 1)
	2950 daload (34, 1)
	2951 dcmpl (34, 1)
	2952 iflt (34, 1)
	2953 6 (34, 1)
	2955 goto (34, 1)
	2956 179 (34, 1)
	2958 aload_0 (33, 3)
	2959 getfield (33, 3)
	2960 org/apache/commons/math3/linear/SingularValueDecomposition.singularValues:[D (33, 3)
	2962 iload (33, 3)
	2963 #11 (33, 3)
	2964 daload (33, 3)
	2965 dstore (33, 3)
	2966 #13 (33, 3)
	2967 aload_0 (33, 3)
	2968 getfield (33, 3)
	2969 org/apache/commons/math3/linear/SingularValueDecomposition.singularValues:[D (33, 3)
	2971 iload (33, 3)
	2972 #11 (33, 3)
	2973 aload_0 (33, 3)
	2974 getfield (33, 3)
	2975 org/apache/commons/math3/linear/SingularValueDecomposition.singularValues:[D (33, 3)
	2977 iload (33, 3)
	2978 #11 (33, 3)
	2979 iconst_1 (33, 3)
	2980 iadd (33, 3)
	2981 daload (33, 3)
	2982 dastore (33, 3)
	2983 aload_0 (33, 3)
	2984 getfield (33, 3)
	2985 org/apache/commons/math3/linear/SingularValueDecomposition.singularValues:[D (33, 3)
	2987 iload (33, 3)
	2988 #11 (33, 3)
	2989 iconst_1 (33, 3)
	2990 iadd (33, 3)
	2991 dload (33, 3)
	2992 #13 (33, 3)
	2993 dastore (33, 3)
	2994 iload (34, 1)
	2995 #11 (34, 1)
	2996 aload_0 (34, 1)
	2997 getfield (34, 1)
	2998 org/apache/commons/math3/linear/SingularValueDecomposition.n:I (34, 1)
	3000 iconst_1 (34, 1)
	3001 isub (34, 1)
	3002 if_icmpge (34, 1)
	3003 61 (34, 1)
	3005 iconst_0 (35, 4)
	3006 istore (35, 4)
	3007 #15 (35, 4)
	3008 iload (35, 4)
	3009 #15 (35, 4)
	3010 aload_0 (35, 4)
	3011 getfield (35, 4)
	3012 org/apache/commons/math3/linear/SingularValueDecomposition.n:I (35, 4)
	3014 if_icmpge (35, 4)
	3015 49 (35, 4)
	3017 aload (35, 4)
	3018 #4 (35, 4)
	3019 iload (35, 4)
	3020 #15 (35, 4)
	3021 aaload (35, 4)
	3022 iload (35, 4)
	3023 #11 (35, 4)
	3024 iconst_1 (35, 4)
	3025 iadd (35, 4)
	3026 daload (35, 4)
	3027 dstore (35, 4)
	3028 #13 (35, 4)
	3029 aload (35, 4)
	3030 #4 (35, 4)
	3031 iload (35, 4)
	3032 #15 (35, 4)
	3033 aaload (35, 4)
	3034 iload (35, 4)
	3035 #11 (35, 4)
	3036 iconst_1 (35, 4)
	3037 iadd (35, 4)
	3038 aload (35, 4)
	3039 #4 (35, 4)
	3040 iload (35, 4)
	3041 #15 (35, 4)
	3042 aaload (35, 4)
	3043 iload (35, 4)
	3044 #11 (35, 4)
	3045 daload (35, 4)
	3046 dastore (35, 4)
	3047 aload (35, 4)
	3048 #4 (35, 4)
	3049 iload (35, 4)
	3050 #15 (35, 4)
	3051 aaload (35, 4)
	3052 iload (35, 4)
	3053 #11 (35, 4)
	3054 dload (35, 4)
	3055 #13 (35, 4)
	3056 dastore (35, 4)
	3057 iinc (35, 4)
	3058 #15 (35, 4)
	3059 -89 (35, 4)
	3060 goto (35, 4)
	3061 -52 (35, 4)
	3063 iload (34, 1)
	3064 #11 (34, 1)
	3065 aload_0 (34, 1)
	3066 getfield (34, 1)
	3067 org/apache/commons/math3/linear/SingularValueDecomposition.m:I (34, 1)
	3069 iconst_1 (34, 1)
	3070 isub (34, 1)
	3071 if_icmpge (34, 1)
	3072 57 (34, 1)
	3074 iconst_0 (35, 4)
	3075 istore (35, 4)
	3076 #15 (35, 4)
	3077 iload (35, 4)
	3078 #15 (35, 4)
	3079 aload_0 (35, 4)
	3080 getfield (35, 4)
	3081 org/apache/commons/math3/linear/SingularValueDecomposition.m:I (35, 4)
	3083 if_icmpge (35, 4)
	3084 45 (35, 4)
	3086 aload_3 (35, 4)
	3087 iload (35, 4)
	3088 #15 (35, 4)
	3089 aaload (35, 4)
	3090 iload (35, 4)
	3091 #11 (35, 4)
	3092 iconst_1 (35, 4)
	3093 iadd (35, 4)
	3094 daload (35, 4)
	3095 dstore (35, 4)
	3096 #13 (35, 4)
	3097 aload_3 (35, 4)
	3098 iload (35, 4)
	3099 #15 (35, 4)
	3100 aaload (35, 4)
	3101 iload (35, 4)
	3102 #11 (35, 4)
	3103 iconst_1 (35, 4)
	3104 iadd (35, 4)
	3105 aload_3 (35, 4)
	3106 iload (35, 4)
	3107 #15 (35, 4)
	3108 aaload (35, 4)
	3109 iload (35, 4)
	3110 #11 (35, 4)
	3111 daload (35, 4)
	3112 dastore (35, 4)
	3113 aload_3 (35, 4)
	3114 iload (35, 4)
	3115 #15 (35, 4)
	3116 aaload (35, 4)
	3117 iload (35, 4)
	3118 #11 (35, 4)
	3119 dload (35, 4)
	3120 #13 (35, 4)
	3121 dastore (35, 4)
	3122 iinc (35, 4)
	3123 #15 (35, 4)
	3124 -89 (35, 4)
	3125 goto (35, 4)
	3126 -48 (35, 4)
	3128 iinc (33, 3)
	3129 #11 (33, 3)
	3130 -89 (33, 3)
	3131 goto (32, 4)
	3132 -203 (32, 4)
	3134 iinc (32, 4)
	3135 #9 (32, 4)
	3136 -89 (32, 4)
	3137 goto (27, 4)
	3138 -1645 (27, 4)
	3140 aload_0 (27, 4)
	3141 aload_0 (27, 4)
	3142 getfield (27, 4)
	3143 org/apache/commons/math3/linear/SingularValueDecomposition.m:I (27, 4)
	3145 i2d (27, 4)
	3146 aload_0 (27, 4)
	3147 getfield (27, 4)
	3148 org/apache/commons/math3/linear/SingularValueDecomposition.singularValues:[D (27, 4)
	3150 iconst_0 (27, 4)
	3151 daload (27, 4)
	3152 dmul (27, 4)
	3153 ldc2_w (27, 4)
	3154 2.220446049250313e-16 (27, 4)
	3156 dmul (27, 4)
	3157 getstatic (27, 4)
	3158 org/apache/commons/math3/util/Precision.SAFE_MIN:D (27, 4)
	3160 invokestatic (27, 4)
	3161 org/apache/commons/math3/util/FastMath.sqrt:(D)D (27, 4)
	3163 invokestatic (27, 4)
	3164 org/apache/commons/math3/util/FastMath.max:(DD)D (27, 4)
	3166 putfield (27, 4)
	3167 org/apache/commons/math3/linear/SingularValueDecomposition.tol:D (27, 4)
	3169 aload_0 (28, 1)
	3170 getfield (28, 1)
	3171 org/apache/commons/math3/linear/SingularValueDecomposition.transposed:Z (28, 1)
	3173 ifne (28, 1)
	3174 23 (28, 1)
	3176 aload_0 (28, 1)
	3177 aload_3 (28, 1)
	3178 invokestatic (28, 1)
	3179 org/apache/commons/math3/linear/MatrixUtils.createRealMatrix:([[D)Lorg/apache/commons/math3/linear/RealMatrix; (28, 1)
	3181 putfield (28, 1)
	3182 org/apache/commons/math3/linear/SingularValueDecomposition.cachedU:Lorg/apache/commons/math3/linear/RealMatrix; (28, 1)
	3184 aload_0 (28, 1)
	3185 aload (28, 1)
	3186 #4 (28, 1)
	3187 invokestatic (28, 1)
	3188 org/apache/commons/math3/linear/MatrixUtils.createRealMatrix:([[D)Lorg/apache/commons/math3/linear/RealMatrix; (28, 1)
	3190 putfield (28, 1)
	3191 org/apache/commons/math3/linear/SingularValueDecomposition.cachedV:Lorg/apache/commons/math3/linear/RealMatrix; (28, 1)
	3193 goto (28, 1)
	3194 20 (28, 1)
	3196 aload_0 (29, 2)
	3197 aload (29, 2)
	3198 #4 (29, 2)
	3199 invokestatic (29, 2)
	3200 org/apache/commons/math3/linear/MatrixUtils.createRealMatrix:([[D)Lorg/apache/commons/math3/linear/RealMatrix; (29, 2)
	3202 putfield (29, 2)
	3203 org/apache/commons/math3/linear/SingularValueDecomposition.cachedU:Lorg/apache/commons/math3/linear/RealMatrix; (29, 2)
	3205 aload_0 (29, 2)
	3206 aload_3 (29, 2)
	3207 invokestatic (29, 2)
	3208 org/apache/commons/math3/linear/MatrixUtils.createRealMatrix:([[D)Lorg/apache/commons/math3/linear/RealMatrix; (29, 2)
	3210 putfield (29, 2)
	3211 org/apache/commons/math3/linear/SingularValueDecomposition.cachedV:Lorg/apache/commons/math3/linear/RealMatrix; (29, 2)
	3213 return (12, 5)

Method: getU
	0 aload_0 (0, 0)
	1 getfield (0, 0)
	2 org/apache/commons/math3/linear/SingularValueDecomposition.cachedU:Lorg/apache/commons/math3/linear/RealMatrix; (0, 0)
	4 areturn (0, 0)

Method: getUT
	0 aload_0 (1, 1)
	1 getfield (1, 1)
	2 org/apache/commons/math3/linear/SingularValueDecomposition.cachedUt:Lorg/apache/commons/math3/linear/RealMatrix; (1, 1)
	4 ifnonnull (1, 1)
	5 16 (1, 1)
	7 aload_0 (1, 1)
	8 aload_0 (1, 1)
	9 invokevirtual (1, 1)
	10 org/apache/commons/math3/linear/SingularValueDecomposition.getU:()Lorg/apache/commons/math3/linear/RealMatrix; (1, 1)
	12 invokeinterface (1, 1)
	13 org/apache/commons/math3/linear/RealMatrix.getData:()[[D (1, 1)
	15 0 (1, 1)
	17 putfield (1, 1)
	18 org/apache/commons/math3/linear/SingularValueDecomposition.cachedUt:Lorg/apache/commons/math3/linear/RealMatrix; (1, 1)
	20 aload_0 (0, 0)
	21 getfield (0, 0)
	22 org/apache/commons/math3/linear/SingularValueDecomposition.cachedUt:Lorg/apache/commons/math3/linear/RealMatrix; (0, 0)
	24 areturn (0, 0)

Method: getS
	0 aload_0 (1, 1)
	1 getfield (1, 1)
	2 org/apache/commons/math3/linear/SingularValueDecomposition.cachedS:Lorg/apache/commons/math3/linear/RealMatrix; (1, 1)
	4 ifnonnull (1, 1)
	5 14 (1, 1)
	7 aload_0 (2, 4)
	8 aload_0 (2, 4)
	9 getfield (2, 4)
	10 org/apache/commons/math3/linear/SingularValueDecomposition.singularValues:[D (2, 4)
	12 invokestatic (2, 4)
	13 org/apache/commons/math3/linear/MatrixUtils.createRealDiagonalMatrix:([D)Lorg/apache/commons/math3/linear/RealMatrix; (2, 4)
	15 putfield (2, 4)
	16 org/apache/commons/math3/linear/SingularValueDecomposition.cachedS:Lorg/apache/commons/math3/linear/RealMatrix; (2, 4)
	18 aload_0 (0, 0)
	19 getfield (0, 0)
	20 org/apache/commons/math3/linear/SingularValueDecomposition.cachedS:Lorg/apache/commons/math3/linear/RealMatrix; (0, 0)
	22 areturn (0, 0)

Method: getSingularValues
	0 aload_0 (0, 0)
	1 getfield (0, 0)
	2 org/apache/commons/math3/linear/SingularValueDecomposition.singularValues:[D (0, 0)
	4 invokevirtual (0, 0)
	5 [D.clone:()Ljava/lang/Object; (0, 0)
	7 checkcast (0, 0)
	8 [D (0, 0)
	10 areturn (0, 0)

Method: getV
	0 aload_0 (0, 0)
	1 getfield (0, 0)
	2 org/apache/commons/math3/linear/SingularValueDecomposition.cachedV:Lorg/apache/commons/math3/linear/RealMatrix; (0, 0)
	4 areturn (0, 0)

Method: getVT
	0 aload_0 (1, 1)
	1 getfield (1, 1)
	2 org/apache/commons/math3/linear/SingularValueDecomposition.cachedVt:Lorg/apache/commons/math3/linear/RealMatrix; (1, 1)
	4 ifnonnull (1, 1)
	5 16 (1, 1)
	7 aload_0 (1, 1)
	8 aload_0 (1, 1)
	9 invokevirtual (1, 1)
	10 org/apache/commons/math3/linear/SingularValueDecomposition.getV:()Lorg/apache/commons/math3/linear/RealMatrix; (1, 1)
	12 invokeinterface (1, 1)
	13 org/apache/commons/math3/linear/RealMatrix.getData:()[[D (1, 1)
	15 0 (1, 1)
	17 putfield (1, 1)
	18 org/apache/commons/math3/linear/SingularValueDecomposition.cachedVt:Lorg/apache/commons/math3/linear/RealMatrix; (1, 1)
	20 aload_0 (0, 0)
	21 getfield (0, 0)
	22 org/apache/commons/math3/linear/SingularValueDecomposition.cachedVt:Lorg/apache/commons/math3/linear/RealMatrix; (0, 0)
	24 areturn (0, 0)

Method: getCovariance
	0 aload_0 (0, 0)
	1 getfield (0, 0)
	2 org/apache/commons/math3/linear/SingularValueDecomposition.singularValues:[D (0, 0)
	4 arraylength (0, 0)
	5 istore_3 (0, 0)
	6 iconst_0 (0, 0)
	7 istore (0, 0)
	8 #4 (0, 0)
	9 iload (1, 3)
	10 #4 (1, 3)
	11 iload_3 (1, 3)
	12 if_icmpge (1, 3)
	13 21 (1, 3)
	15 aload_0 (1, 3)
	16 getfield (1, 3)
	17 org/apache/commons/math3/linear/SingularValueDecomposition.singularValues:[D (1, 3)
	19 iload (1, 3)
	20 #4 (1, 3)
	21 daload (1, 3)
	22 dload_1 (1, 3)
	23 dcmpl (1, 3)
	24 iflt (1, 3)
	25 9 (1, 3)
	27 iinc (1, 3)
	28 #4 (1, 3)
	29 -89 (1, 3)
	30 goto (1, 3)
	31 -21 (1, 3)
	33 iload (2, 1)
	34 #4 (2, 1)
	35 ifne (2, 1)
	36 28 (2, 1)
	38 new (2, 1)
	39 org/apache/commons/math3/exception/NumberIsTooLargeException (2, 1)
	41 dup (2, 1)
	42 getstatic (2, 1)
	43 org/apache/commons/math3/exception/util/LocalizedFormats.TOO_LARGE_CUTOFF_SINGULAR_VALUE:Lorg/apache/commons/math3/exception/util/LocalizedFormats; (2, 1)
	45 dload_1 (2, 1)
	46 invokestatic (2, 1)
	47 java/lang/Double.valueOf:(D)Ljava/lang/Double; (2, 1)
	49 aload_0 (2, 1)
	50 getfield (2, 1)
	51 org/apache/commons/math3/linear/SingularValueDecomposition.singularValues:[D (2, 1)
	53 iconst_0 (2, 1)
	54 daload (2, 1)
	55 invokestatic (2, 1)
	56 java/lang/Double.valueOf:(D)Ljava/lang/Double; (2, 1)
	58 iconst_1 (2, 1)
	59 invokespecial (2, 1)
	60 org/apache/commons/math3/exception/NumberIsTooLargeException.<init>:(Lorg/apache/commons/math3/exception/util/Localizable;Ljava/lang/Number;Ljava/lang/Number;Z)V (2, 1)
	62 athrow (2, 1)
	63 iload (1, 3)
	64 #4 (1, 3)
	65 iload_3 (1, 3)
	66 multianewarray (1, 3)
	67 [[D (1, 3)
	69 58 (1, 3)
	70 astore (1, 3)
	71 #5 (1, 3)
	72 aload_0 (1, 3)
	73 invokevirtual (1, 3)
	74 org/apache/commons/math3/linear/SingularValueDecomposition.getVT:()Lorg/apache/commons/math3/linear/RealMatrix; (1, 3)
	76 new (1, 3)
	77 org/apache/commons/math3/linear/SingularValueDecomposition$1 (1, 3)
	79 dup (1, 3)
	80 aload_0 (1, 3)
	81 aload (1, 3)
	82 #5 (1, 3)
	83 invokespecial (1, 3)
	84 org/apache/commons/math3/linear/SingularValueDecomposition$1.<init>:(Lorg/apache/commons/math3/linear/SingularValueDecomposition;[[D)V (1, 3)
	86 iconst_0 (1, 3)
	87 iload (1, 3)
	88 #4 (1, 3)
	89 iconst_1 (1, 3)
	90 isub (1, 3)
	91 iconst_0 (1, 3)
	92 iload_3 (1, 3)
	93 iconst_1 (1, 3)
	94 isub (1, 3)
	95 invokeinterface (1, 3)
	96 org/apache/commons/math3/linear/RealMatrix.org/apache/commons/math3/linear/Array2DRowRealMatrix (1, 3)
	98 0 (1, 3)
	100 pop2 (1, 3)
	101 new (1, 3)
	102 org/apache/commons/math3/linear/Array2DRowRealMatrix (1, 3)
	104 dup (1, 3)
	105 aload (1, 3)
	106 #5 (1, 3)
	107 iconst_0 (1, 3)
	108 invokespecial (1, 3)
	109 org/apache/commons/math3/linear/Array2DRowRealMatrix.<init>:([[DZ)V (1, 3)
	111 astore (1, 3)
	112 #6 (1, 3)
	113 aload (1, 3)
	114 #6 (1, 3)
	115 invokeinterface (1, 3)
	116 org/apache/commons/math3/linear/RealMatrix.getData:()[[D (1, 3)
	118 0 (1, 3)
	120 aload (1, 3)
	121 #6 (1, 3)
	122 invokeinterface (1, 3)
	123 org/apache/commons/math3/linear/RealMatrix.org/apache/commons/math3/linear/SingularValueDecomposition$Solver (1, 3)
	125 0 (1, 3)
	127 areturn (0, 3)

Method: getNorm
	0 aload_0 (0, 0)
	1 getfield (0, 0)
	2 org/apache/commons/math3/linear/SingularValueDecomposition.singularValues:[D (0, 0)
	4 iconst_0 (0, 0)
	5 daload (0, 0)
	6 dreturn (0, 0)

Method: getConditionNumber
	0 aload_0 (0, 0)
	1 getfield (0, 0)
	2 org/apache/commons/math3/linear/SingularValueDecomposition.singularValues:[D (0, 0)
	4 iconst_0 (0, 0)
	5 daload (0, 0)
	6 aload_0 (0, 0)
	7 getfield (0, 0)
	8 org/apache/commons/math3/linear/SingularValueDecomposition.singularValues:[D (0, 0)
	10 aload_0 (0, 0)
	11 getfield (0, 0)
	12 org/apache/commons/math3/linear/SingularValueDecomposition.n:I (0, 0)
	14 iconst_1 (0, 0)
	15 isub (0, 0)
	16 daload (0, 0)
	17 ddiv (0, 0)
	18 dreturn (0, 0)

Method: getInverseConditionNumber
	0 aload_0 (0, 0)
	1 getfield (0, 0)
	2 org/apache/commons/math3/linear/SingularValueDecomposition.singularValues:[D (0, 0)
	4 aload_0 (0, 0)
	5 getfield (0, 0)
	6 org/apache/commons/math3/linear/SingularValueDecomposition.n:I (0, 0)
	8 iconst_1 (0, 0)
	9 isub (0, 0)
	10 daload (0, 0)
	11 aload_0 (0, 0)
	12 getfield (0, 0)
	13 org/apache/commons/math3/linear/SingularValueDecomposition.singularValues:[D (0, 0)
	15 iconst_0 (0, 0)
	16 daload (0, 0)
	17 ddiv (0, 0)
	18 dreturn (0, 0)

Method: getRank
	0 iconst_0 (0, 0)
	1 istore_1 (0, 0)
	2 iconst_0 (1, 4)
	3 istore_2 (1, 4)
	4 iload_2 (1, 4)
	5 aload_0 (1, 4)
	6 getfield (1, 4)
	7 org/apache/commons/math3/linear/SingularValueDecomposition.singularValues:[D (1, 4)
	9 arraylength (1, 4)
	10 if_icmpge (1, 4)
	11 26 (1, 4)
	13 aload_0 (2, 1)
	14 getfield (2, 1)
	15 org/apache/commons/math3/linear/SingularValueDecomposition.singularValues:[D (2, 1)
	17 iload_2 (2, 1)
	18 daload (2, 1)
	19 aload_0 (2, 1)
	20 getfield (2, 1)
	21 org/apache/commons/math3/linear/SingularValueDecomposition.tol:D (2, 1)
	23 dcmpl (2, 1)
	24 ifle (2, 1)
	25 6 (2, 1)
	27 iinc (2, 1)
	28 #1 (2, 1)
	29 -124 (2, 1)
	30 iinc (2, 1)
	31 #2 (2, 1)
	32 -89 (2, 1)
	33 goto (2, 1)
	34 -29 (2, 1)
	36 iload_1 (1, 4)
	37 ireturn (1, 4)

Method: getSolver
	0 new (0, 0)
	1 org/apache/commons/math3/linear/SingularValueDecomposition$Solver (0, 0)
	3 dup (0, 0)
	4 aload_0 (0, 0)
	5 getfield (0, 0)
	6 org/apache/commons/math3/linear/SingularValueDecomposition.singularValues:[D (0, 0)
	8 aload_0 (0, 0)
	9 invokevirtual (0, 0)
	10 org/apache/commons/math3/linear/SingularValueDecomposition.getUT:()Lorg/apache/commons/math3/linear/RealMatrix; (0, 0)
	12 aload_0 (0, 0)
	13 invokevirtual (0, 0)
	14 org/apache/commons/math3/linear/SingularValueDecomposition.getV:()Lorg/apache/commons/math3/linear/RealMatrix; (0, 0)
	16 aload_0 (0, 0)
	17 invokevirtual (0, 0)
	18 org/apache/commons/math3/linear/SingularValueDecomposition.getRank:()I (0, 0)
	20 aload_0 (0, 0)
	21 getfield (0, 0)
	22 org/apache/commons/math3/linear/SingularValueDecomposition.m:I (0, 0)
	24 if_icmpne (0, 0)
	25 7 (0, 0)
	27 iconst_1 (0, 0)
	28 goto (0, 0)
	29 4 (0, 0)
	31 iconst_0 (0, 0)
	32 aload_0 (0, 0)
	33 getfield (0, 0)
	34 org/apache/commons/math3/linear/SingularValueDecomposition.tol:D (0, 0)
	36 aconst_null (0, 0)
	37 invokespecial (0, 0)
	38 org/apache/commons/math3/linear/SingularValueDecomposition$Solver.<init>:([DLorg/apache/commons/math3/linear/RealMatrix;Lorg/apache/commons/math3/linear/RealMatrix;ZDLorg/apache/commons/math3/linear/SingularValueDecomposition$1;)V (0, 0)
	40 areturn (0, 0)

Method: access$000
	0 aload_0 (0, 0)
	1 getfield (0, 0)
	2 org/apache/commons/math3/linear/SingularValueDecomposition.singularValues:[D (0, 0)
	4 areturn (0, 0)

