Method: <init>
	0 aload_0 (0, 0)
	1 invokespecial (0, 0)
	2 java/lang/Object.<init>:()V (0, 0)
	4 aload_2 (0, 0)
	5 invokeinterface (0, 0)
	6 org/apache/commons/math3/linear/RealMatrix.org/apache/commons/math3/linear/Array2DRowRealMatrix (0, 0)
	8 0 (0, 0)
	10 astore (0, 0)
	11 #7 (0, 0)
	12 iconst_0 (2, 4)
	13 istore (2, 4)
	14 #8 (2, 4)
	15 iload (2, 4)
	16 #8 (2, 4)
	17 aload_1 (2, 4)
	18 arraylength (2, 4)
	19 if_icmpge (2, 4)
	20 67 (2, 4)
	22 aload_1 (3, 1)
	23 iload (3, 1)
	24 #8 (3, 1)
	25 daload (3, 1)
	26 dload (3, 1)
	27 #5 (3, 1)
	28 dcmpl (3, 1)
	29 ifle (3, 1)
	30 14 (3, 1)
	32 dconst_1 (3, 1)
	33 aload_1 (3, 1)
	34 iload (3, 1)
	35 #8 (3, 1)
	36 daload (3, 1)
	37 ddiv (3, 1)
	38 dstore (3, 1)
	39 #9 (3, 1)
	40 goto (3, 1)
	41 6 (3, 1)
	43 dconst_0 (3, 2)
	44 dstore (3, 2)
	45 #9 (3, 2)
	46 aload (2, 4)
	47 #7 (2, 4)
	48 iload (2, 4)
	49 #8 (2, 4)
	50 aaload (2, 4)
	51 astore (2, 4)
	52 #11 (2, 4)
	53 iconst_0 (3, 4)
	54 istore (3, 4)
	55 #12 (3, 4)
	56 iload (3, 4)
	57 #12 (3, 4)
	58 aload (3, 4)
	59 #11 (3, 4)
	60 arraylength (3, 4)
	61 if_icmpge (3, 4)
	62 19 (3, 4)
	64 aload (3, 4)
	65 #11 (3, 4)
	66 iload (3, 4)
	67 #12 (3, 4)
	68 dup2 (3, 4)
	69 daload (3, 4)
	70 dload (3, 4)
	71 #9 (3, 4)
	72 dmul (3, 4)
	73 dastore (3, 4)
	74 iinc (3, 4)
	75 #12 (3, 4)
	76 -89 (3, 4)
	77 goto (3, 4)
	78 -21 (3, 4)
	80 iinc (3, 4)
	81 #8 (3, 4)
	82 -89 (3, 4)
	83 goto (3, 4)
	84 -68 (3, 4)
	86 aload_0 (2, 4)
	87 aload_3 (2, 4)
	88 new (2, 4)
	89 org/apache/commons/math3/linear/Array2DRowRealMatrix (2, 4)
	91 dup (2, 4)
	92 aload (2, 4)
	93 #7 (2, 4)
	94 iconst_0 (2, 4)
	95 invokespecial (2, 4)
	96 org/apache/commons/math3/linear/Array2DRowRealMatrix.<init>:([[DZ)V (2, 4)
	98 invokeinterface (2, 4)
	99 org/apache/commons/math3/linear/RealMatrix.pseudoInverse:Lorg/apache/commons/math3/linear/RealMatrix; (2, 4)
	101 0 (2, 4)
	103 putfield (2, 4)
	104 org/apache/commons/math3/linear/SingularValueDecomposition$Solver.pseudoInverse:Lorg/apache/commons/math3/linear/RealMatrix; (2, 4)
	106 aload_0 (2, 4)
	107 iload (2, 4)
	108 #4 (2, 4)
	109 putfield (2, 4)
	110 org/apache/commons/math3/linear/SingularValueDecomposition$Solver.nonSingular:Z (2, 4)
	112 return (0, 0)

Method: solve
	0 aload_0 (0, 0)
	1 getfield (0, 0)
	2 org/apache/commons/math3/linear/SingularValueDecomposition$Solver.pseudoInverse:Lorg/apache/commons/math3/linear/RealMatrix; (0, 0)
	4 aload_1 (0, 0)
	5 invokeinterface (0, 0)
	6 org/apache/commons/math3/linear/RealMatrix.pseudoInverse:Lorg/apache/commons/math3/linear/RealMatrix; (0, 0)
	8 0 (0, 0)
	10 areturn (0, 0)

Method: isNonSingular
	0 aload_0 (0, 0)
	1 getfield (0, 0)
	2 org/apache/commons/math3/linear/SingularValueDecomposition$Solver.nonSingular:Z (0, 0)
	4 ireturn (0, 0)

Method: getInverse
	0 aload_0 (0, 0)
	1 getfield (0, 0)
	2 org/apache/commons/math3/linear/SingularValueDecomposition$Solver.pseudoInverse:Lorg/apache/commons/math3/linear/RealMatrix; (0, 0)
	4 areturn (0, 0)

