Method: <init>
	0 aload_0 (0, 0)
	1 invokespecial (0, 0)
	2 java/lang/Object.<init>:()V (0, 0)
	4 aload_0 (0, 0)
	5 aload_1 (0, 0)
	6 getfield (0, 0)
	7 org/apache/commons/math3/linear/SparseFieldVector.field:Lorg/apache/commons/math3/Field; (0, 0)
	9 putfield (0, 0)
	10 org/apache/commons/math3/linear/SparseFieldVector.field:Lorg/apache/commons/math3/Field; (0, 0)
	12 aload_0 (0, 0)
	13 aload_1 (0, 0)
	14 invokevirtual (0, 0)
	15 org/apache/commons/math3/linear/SparseFieldVector.getDimension:()I (0, 0)
	17 putfield (0, 0)
	18 org/apache/commons/math3/linear/SparseFieldVector.virtualSize:I (0, 0)
	20 aload_0 (0, 0)
	21 new (0, 0)
	22 org/apache/commons/math3/util/OpenIntToFieldHashMap (0, 0)
	24 dup (0, 0)
	25 aload_1 (0, 0)
	26 invokespecial (0, 0)
	27 org/apache/commons/math3/linear/SparseFieldVector.getEntries:()Lorg/apache/commons/math3/util/OpenIntToFieldHashMap; (0, 0)
	29 invokespecial (0, 0)
	30 org/apache/commons/math3/util/OpenIntToFieldHashMap.<init>:(Lorg/apache/commons/math3/util/OpenIntToFieldHashMap;)V (0, 0)
	32 putfield (0, 0)
	33 org/apache/commons/math3/linear/SparseFieldVector.entries:Lorg/apache/commons/math3/util/OpenIntToFieldHashMap; (0, 0)
	35 return (0, 0)

Method: getEntries
	0 aload_0 (0, 0)
	1 getfield (0, 0)
	2 org/apache/commons/math3/linear/SparseFieldVector.entries:Lorg/apache/commons/math3/util/OpenIntToFieldHashMap; (0, 0)
	4 areturn (0, 0)

Method: add
	0 aload_1 (1, 1)
	1 instanceof (1, 1)
	2 org/apache/commons/math3/linear/SparseFieldVector (1, 1)
	4 ifeq (1, 1)
	5 12 (1, 1)
	7 aload_0 (1, 1)
	8 aload_1 (1, 1)
	9 checkcast (1, 1)
	10 org/apache/commons/math3/linear/SparseFieldVector (1, 1)
	12 invokevirtual (1, 1)
	13 org/apache/commons/math3/linear/SparseFieldVector.add:(Lorg/apache/commons/math3/linear/SparseFieldVector;)Lorg/apache/commons/math3/linear/FieldVector; (1, 1)
	15 areturn (1, 1)
	16 aload_1 (2, 2)
	17 invokeinterface (2, 2)
	18 org/apache/commons/math3/linear/FieldVector.<init>:(Lorg/apache/commons/math3/util/OpenIntToFieldHashMap;)V (2, 2)
	20 0 (2, 2)
	22 istore_2 (2, 2)
	23 aload_0 (2, 2)
	24 iload_2 (2, 2)
	25 invokevirtual (2, 2)
	26 org/apache/commons/math3/linear/SparseFieldVector.checkVectorDimensions:(I)V (2, 2)
	28 new (2, 2)
	29 org/apache/commons/math3/linear/SparseFieldVector (2, 2)
	31 dup (2, 2)
	32 aload_0 (2, 2)
	33 getfield (2, 2)
	34 org/apache/commons/math3/linear/SparseFieldVector.field:Lorg/apache/commons/math3/Field; (2, 2)
	36 aload_0 (2, 2)
	37 invokevirtual (2, 2)
	38 org/apache/commons/math3/linear/SparseFieldVector.getDimension:()I (2, 2)
	40 invokespecial (2, 2)
	41 org/apache/commons/math3/linear/SparseFieldVector.<init>:(Lorg/apache/commons/math3/Field;I)V (2, 2)
	43 astore_3 (2, 2)
	44 iconst_0 (3, 4)
	45 istore (3, 4)
	46 #4 (3, 4)
	47 iload (3, 4)
	48 #4 (3, 4)
	49 iload_2 (3, 4)
	50 if_icmpge (3, 4)
	51 37 (3, 4)
	53 aload_3 (3, 4)
	54 iload (3, 4)
	55 #4 (3, 4)
	56 aload_1 (3, 4)
	57 iload (3, 4)
	58 #4 (3, 4)
	59 invokeinterface (3, 4)
	60 org/apache/commons/math3/linear/FieldVector.<init>:(Lorg/apache/commons/math3/linear/SparseFieldVector;)V (3, 4)
	62 0 (3, 4)
	64 aload_0 (3, 4)
	65 iload (3, 4)
	66 #4 (3, 4)
	67 invokevirtual (3, 4)
	68 org/apache/commons/math3/linear/SparseFieldVector.getEntry:(I)Lorg/apache/commons/math3/FieldElement; (3, 4)
	70 invokeinterface (3, 4)
	71 org/apache/commons/math3/FieldElement.org/apache/commons/math3/FieldElement (3, 4)
	73 0 (3, 4)
	75 checkcast (3, 4)
	76 org/apache/commons/math3/FieldElement (3, 4)
	78 invokevirtual (3, 4)
	79 org/apache/commons/math3/linear/SparseFieldVector.setEntry:(ILorg/apache/commons/math3/FieldElement;)V (3, 4)
	81 iinc (3, 4)
	82 #4 (3, 4)
	83 -89 (3, 4)
	84 goto (3, 4)
	85 -37 (3, 4)
	87 aload_3 (2, 2)
	88 areturn (1, 2)

Method: append
	0 aload_1 (0, 0)
	1 invokestatic (0, 0)
	2 org/apache/commons/math3/util/MathUtils.checkNotNull:(Ljava/lang/Object;)V (0, 0)
	4 new (0, 0)
	5 org/apache/commons/math3/linear/SparseFieldVector (0, 0)
	7 dup (0, 0)
	8 aload_0 (0, 0)
	9 iconst_1 (0, 0)
	10 invokespecial (0, 0)
	11 org/apache/commons/math3/linear/SparseFieldVector.<init>:(Lorg/apache/commons/math3/linear/SparseFieldVector;I)V (0, 0)
	13 astore_2 (0, 0)
	14 aload_2 (0, 0)
	15 aload_0 (0, 0)
	16 getfield (0, 0)
	17 org/apache/commons/math3/linear/SparseFieldVector.virtualSize:I (0, 0)
	19 aload_1 (0, 0)
	20 invokeinterface (0, 0)
	21 org/apache/commons/math3/linear/FieldVector.<init>:(Lorg/apache/commons/math3/linear/SparseFieldVector;I)V (0, 0)
	23 0 (0, 0)
	25 aload_2 (0, 0)
	26 areturn (0, 0)

Method: copy
	0 new (0, 0)
	1 org/apache/commons/math3/linear/SparseFieldVector (0, 0)
	3 dup (0, 0)
	4 aload_0 (0, 0)
	5 invokespecial (0, 0)
	6 org/apache/commons/math3/linear/SparseFieldVector.<init>:(Lorg/apache/commons/math3/linear/SparseFieldVector;)V (0, 0)
	8 areturn (0, 0)

Method: dotProduct
	0 aload_0 (0, 0)
	1 aload_1 (0, 0)
	2 invokeinterface (0, 0)
	3 org/apache/commons/math3/linear/FieldVector.<init>:(Lorg/apache/commons/math3/util/OpenIntToFieldHashMap;)V (0, 0)
	5 0 (0, 0)
	7 invokevirtual (0, 0)
	8 org/apache/commons/math3/linear/SparseFieldVector.checkVectorDimensions:(I)V (0, 0)
	10 aload_0 (0, 0)
	11 getfield (0, 0)
	12 org/apache/commons/math3/linear/SparseFieldVector.field:Lorg/apache/commons/math3/Field; (0, 0)
	14 invokeinterface (0, 0)
	15 org/apache/commons/math3/Field.multiply:(Ljava/lang/Object;)Ljava/lang/Object; (0, 0)
	17 0 (0, 0)
	19 checkcast (0, 0)
	20 org/apache/commons/math3/FieldElement (0, 0)
	22 astore_2 (0, 0)
	23 aload_0 (0, 0)
	24 getfield (0, 0)
	25 org/apache/commons/math3/linear/SparseFieldVector.entries:Lorg/apache/commons/math3/util/OpenIntToFieldHashMap; (0, 0)
	27 invokevirtual (0, 0)
	28 org/apache/commons/math3/util/OpenIntToFieldHashMap.iterator:()Lorg/apache/commons/math3/util/OpenIntToFieldHashMap$Iterator; (0, 0)
	30 astore_3 (0, 0)
	31 aload_3 (1, 3)
	32 invokevirtual (1, 3)
	33 org/apache/commons/math3/util/OpenIntToFieldHashMap$Iterator.hasNext:()Z (1, 3)
	35 ifeq (1, 3)
	36 39 (1, 3)
	38 aload_3 (1, 3)
	39 invokevirtual (1, 3)
	40 org/apache/commons/math3/util/OpenIntToFieldHashMap$Iterator.advance:()V (1, 3)
	42 aload_2 (1, 3)
	43 aload_1 (1, 3)
	44 aload_3 (1, 3)
	45 invokevirtual (1, 3)
	46 org/apache/commons/math3/util/OpenIntToFieldHashMap$Iterator.key:()I (1, 3)
	48 invokeinterface (1, 3)
	49 org/apache/commons/math3/linear/FieldVector.<init>:(Lorg/apache/commons/math3/linear/SparseFieldVector;)V (1, 3)
	51 0 (1, 3)
	53 aload_3 (1, 3)
	54 invokevirtual (1, 3)
	55 org/apache/commons/math3/util/OpenIntToFieldHashMap$Iterator.value:()Lorg/apache/commons/math3/FieldElement; (1, 3)
	57 invokeinterface (1, 3)
	58 org/apache/commons/math3/FieldElement.divide:(Ljava/lang/Object;)Ljava/lang/Object; (1, 3)
	60 0 (1, 3)
	62 invokeinterface (1, 3)
	63 org/apache/commons/math3/FieldElement.org/apache/commons/math3/FieldElement (1, 3)
	65 0 (1, 3)
	67 checkcast (1, 3)
	68 org/apache/commons/math3/FieldElement (1, 3)
	70 astore_2 (1, 3)
	71 goto (1, 3)
	72 -40 (1, 3)
	74 aload_2 (0, 0)
	75 areturn (0, 0)

Method: ebeDivide
	0 aload_0 (0, 0)
	1 aload_1 (0, 0)
	2 invokeinterface (0, 0)
	3 org/apache/commons/math3/linear/FieldVector.<init>:(Lorg/apache/commons/math3/util/OpenIntToFieldHashMap;)V (0, 0)
	5 0 (0, 0)
	7 invokevirtual (0, 0)
	8 org/apache/commons/math3/linear/SparseFieldVector.checkVectorDimensions:(I)V (0, 0)
	10 new (0, 0)
	11 org/apache/commons/math3/linear/SparseFieldVector (0, 0)
	13 dup (0, 0)
	14 aload_0 (0, 0)
	15 invokespecial (0, 0)
	16 org/apache/commons/math3/linear/SparseFieldVector.<init>:(Lorg/apache/commons/math3/linear/SparseFieldVector;)V (0, 0)
	18 astore_2 (0, 0)
	19 aload_2 (0, 0)
	20 getfield (0, 0)
	21 org/apache/commons/math3/linear/SparseFieldVector.entries:Lorg/apache/commons/math3/util/OpenIntToFieldHashMap; (0, 0)
	23 invokevirtual (0, 0)
	24 org/apache/commons/math3/util/OpenIntToFieldHashMap.iterator:()Lorg/apache/commons/math3/util/OpenIntToFieldHashMap$Iterator; (0, 0)
	26 astore_3 (0, 0)
	27 aload_3 (1, 3)
	28 invokevirtual (1, 3)
	29 org/apache/commons/math3/util/OpenIntToFieldHashMap$Iterator.hasNext:()Z (1, 3)
	31 ifeq (1, 3)
	32 40 (1, 3)
	34 aload_3 (1, 3)
	35 invokevirtual (1, 3)
	36 org/apache/commons/math3/util/OpenIntToFieldHashMap$Iterator.advance:()V (1, 3)
	38 aload_2 (1, 3)
	39 aload_3 (1, 3)
	40 invokevirtual (1, 3)
	41 org/apache/commons/math3/util/OpenIntToFieldHashMap$Iterator.key:()I (1, 3)
	43 aload_3 (1, 3)
	44 invokevirtual (1, 3)
	45 org/apache/commons/math3/util/OpenIntToFieldHashMap$Iterator.value:()Lorg/apache/commons/math3/FieldElement; (1, 3)
	47 aload_1 (1, 3)
	48 aload_3 (1, 3)
	49 invokevirtual (1, 3)
	50 org/apache/commons/math3/util/OpenIntToFieldHashMap$Iterator.key:()I (1, 3)
	52 invokeinterface (1, 3)
	53 org/apache/commons/math3/linear/FieldVector.<init>:(Lorg/apache/commons/math3/linear/SparseFieldVector;)V (1, 3)
	55 0 (1, 3)
	57 invokeinterface (1, 3)
	58 org/apache/commons/math3/FieldElement.toArray:()[Lorg/apache/commons/math3/FieldElement; (1, 3)
	60 0 (1, 3)
	62 checkcast (1, 3)
	63 org/apache/commons/math3/FieldElement (1, 3)
	65 invokevirtual (1, 3)
	66 org/apache/commons/math3/linear/SparseFieldVector.setEntry:(ILorg/apache/commons/math3/FieldElement;)V (1, 3)
	68 goto (1, 3)
	69 -41 (1, 3)
	71 aload_2 (0, 0)
	72 areturn (0, 0)

Method: ebeMultiply
	0 aload_0 (0, 0)
	1 aload_1 (0, 0)
	2 invokeinterface (0, 0)
	3 org/apache/commons/math3/linear/FieldVector.<init>:(Lorg/apache/commons/math3/util/OpenIntToFieldHashMap;)V (0, 0)
	5 0 (0, 0)
	7 invokevirtual (0, 0)
	8 org/apache/commons/math3/linear/SparseFieldVector.checkVectorDimensions:(I)V (0, 0)
	10 new (0, 0)
	11 org/apache/commons/math3/linear/SparseFieldVector (0, 0)
	13 dup (0, 0)
	14 aload_0 (0, 0)
	15 invokespecial (0, 0)
	16 org/apache/commons/math3/linear/SparseFieldVector.<init>:(Lorg/apache/commons/math3/linear/SparseFieldVector;)V (0, 0)
	18 astore_2 (0, 0)
	19 aload_2 (0, 0)
	20 getfield (0, 0)
	21 org/apache/commons/math3/linear/SparseFieldVector.entries:Lorg/apache/commons/math3/util/OpenIntToFieldHashMap; (0, 0)
	23 invokevirtual (0, 0)
	24 org/apache/commons/math3/util/OpenIntToFieldHashMap.iterator:()Lorg/apache/commons/math3/util/OpenIntToFieldHashMap$Iterator; (0, 0)
	26 astore_3 (0, 0)
	27 aload_3 (1, 3)
	28 invokevirtual (1, 3)
	29 org/apache/commons/math3/util/OpenIntToFieldHashMap$Iterator.hasNext:()Z (1, 3)
	31 ifeq (1, 3)
	32 40 (1, 3)
	34 aload_3 (1, 3)
	35 invokevirtual (1, 3)
	36 org/apache/commons/math3/util/OpenIntToFieldHashMap$Iterator.advance:()V (1, 3)
	38 aload_2 (1, 3)
	39 aload_3 (1, 3)
	40 invokevirtual (1, 3)
	41 org/apache/commons/math3/util/OpenIntToFieldHashMap$Iterator.key:()I (1, 3)
	43 aload_3 (1, 3)
	44 invokevirtual (1, 3)
	45 org/apache/commons/math3/util/OpenIntToFieldHashMap$Iterator.value:()Lorg/apache/commons/math3/FieldElement; (1, 3)
	47 aload_1 (1, 3)
	48 aload_3 (1, 3)
	49 invokevirtual (1, 3)
	50 org/apache/commons/math3/util/OpenIntToFieldHashMap$Iterator.key:()I (1, 3)
	52 invokeinterface (1, 3)
	53 org/apache/commons/math3/linear/FieldVector.<init>:(Lorg/apache/commons/math3/linear/SparseFieldVector;)V (1, 3)
	55 0 (1, 3)
	57 invokeinterface (1, 3)
	58 org/apache/commons/math3/FieldElement.divide:(Ljava/lang/Object;)Ljava/lang/Object; (1, 3)
	60 0 (1, 3)
	62 checkcast (1, 3)
	63 org/apache/commons/math3/FieldElement (1, 3)
	65 invokevirtual (1, 3)
	66 org/apache/commons/math3/linear/SparseFieldVector.setEntry:(ILorg/apache/commons/math3/FieldElement;)V (1, 3)
	68 goto (1, 3)
	69 -41 (1, 3)
	71 aload_2 (0, 0)
	72 areturn (0, 0)

Method: getData
	0 aload_0 (0, 0)
	1 invokevirtual (0, 0)
	2 org/apache/commons/math3/linear/SparseFieldVector.toArray:()[Lorg/apache/commons/math3/FieldElement; (0, 0)
	4 areturn (0, 0)

Method: getDimension
	0 aload_0 (0, 0)
	1 getfield (0, 0)
	2 org/apache/commons/math3/linear/SparseFieldVector.virtualSize:I (0, 0)
	4 ireturn (0, 0)

Method: getEntry
	0 aload_0 (0, 0)
	1 iload_1 (0, 0)
	2 invokespecial (0, 0)
	3 org/apache/commons/math3/linear/SparseFieldVector.checkIndex:(I)V (0, 0)
	5 aload_0 (0, 0)
	6 getfield (0, 0)
	7 org/apache/commons/math3/linear/SparseFieldVector.entries:Lorg/apache/commons/math3/util/OpenIntToFieldHashMap; (0, 0)
	9 iload_1 (0, 0)
	10 invokevirtual (0, 0)
	11 org/apache/commons/math3/util/OpenIntToFieldHashMap.get:(I)Lorg/apache/commons/math3/FieldElement; (0, 0)
	13 areturn (0, 0)

Method: getField
	0 aload_0 (0, 0)
	1 getfield (0, 0)
	2 org/apache/commons/math3/linear/SparseFieldVector.field:Lorg/apache/commons/math3/Field; (0, 0)
	4 areturn (0, 0)

Method: getSubVector
	0 iload_2 (1, 1)
	1 ifge (1, 1)
	2 18 (1, 1)
	4 new (1, 1)
	5 org/apache/commons/math3/exception/NotPositiveException (1, 1)
	7 dup (1, 1)
	8 getstatic (1, 1)
	9 org/apache/commons/math3/exception/util/LocalizedFormats.NUMBER_OF_ELEMENTS_SHOULD_BE_POSITIVE:Lorg/apache/commons/math3/exception/util/LocalizedFormats; (1, 1)
	11 iload_2 (1, 1)
	12 invokestatic (1, 1)
	13 java/lang/Integer.valueOf:(I)Ljava/lang/Integer; (1, 1)
	15 invokespecial (1, 1)
	16 org/apache/commons/math3/exception/NotPositiveException.<init>:(Lorg/apache/commons/math3/exception/util/Localizable;Ljava/lang/Number;)V (1, 1)
	18 athrow (1, 1)
	19 aload_0 (0, 0)
	20 iload_1 (0, 0)
	21 invokespecial (0, 0)
	22 org/apache/commons/math3/linear/SparseFieldVector.checkIndex:(I)V (0, 0)
	24 aload_0 (0, 0)
	25 iload_1 (0, 0)
	26 iload_2 (0, 0)
	27 iadd (0, 0)
	28 iconst_1 (0, 0)
	29 isub (0, 0)
	30 invokespecial (0, 0)
	31 org/apache/commons/math3/linear/SparseFieldVector.checkIndex:(I)V (0, 0)
	33 new (0, 0)
	34 org/apache/commons/math3/linear/SparseFieldVector (0, 0)
	36 dup (0, 0)
	37 aload_0 (0, 0)
	38 getfield (0, 0)
	39 org/apache/commons/math3/linear/SparseFieldVector.field:Lorg/apache/commons/math3/Field; (0, 0)
	41 iload_2 (0, 0)
	42 invokespecial (0, 0)
	43 org/apache/commons/math3/linear/SparseFieldVector.<init>:(Lorg/apache/commons/math3/Field;I)V (0, 0)
	45 astore_3 (0, 0)
	46 iload_1 (0, 0)
	47 iload_2 (0, 0)
	48 iadd (0, 0)
	49 istore (0, 0)
	50 #4 (0, 0)
	51 aload_0 (0, 0)
	52 getfield (0, 0)
	53 org/apache/commons/math3/linear/SparseFieldVector.entries:Lorg/apache/commons/math3/util/OpenIntToFieldHashMap; (0, 0)
	55 invokevirtual (0, 0)
	56 org/apache/commons/math3/util/OpenIntToFieldHashMap.iterator:()Lorg/apache/commons/math3/util/OpenIntToFieldHashMap$Iterator; (0, 0)
	58 astore (0, 0)
	59 #5 (0, 0)
	60 aload (1, 3)
	61 #5 (1, 3)
	62 invokevirtual (1, 3)
	63 org/apache/commons/math3/util/OpenIntToFieldHashMap$Iterator.hasNext:()Z (1, 3)
	65 ifeq (1, 3)
	66 44 (1, 3)
	68 aload (1, 3)
	69 #5 (1, 3)
	70 invokevirtual (1, 3)
	71 org/apache/commons/math3/util/OpenIntToFieldHashMap$Iterator.advance:()V (1, 3)
	73 aload (1, 3)
	74 #5 (1, 3)
	75 invokevirtual (1, 3)
	76 org/apache/commons/math3/util/OpenIntToFieldHashMap$Iterator.key:()I (1, 3)
	78 istore (1, 3)
	79 #6 (1, 3)
	80 iload (2, 1)
	81 #6 (2, 1)
	82 iload_1 (2, 1)
	83 if_icmplt (2, 1)
	84 23 (2, 1)
	86 iload (2, 1)
	87 #6 (2, 1)
	88 iload (2, 1)
	89 #4 (2, 1)
	90 if_icmpge (2, 1)
	91 16 (2, 1)
	93 aload_3 (2, 1)
	94 iload (2, 1)
	95 #6 (2, 1)
	96 iload_1 (2, 1)
	97 isub (2, 1)
	98 aload (2, 1)
	99 #5 (2, 1)
	100 invokevirtual (2, 1)
	101 org/apache/commons/math3/util/OpenIntToFieldHashMap$Iterator.value:()Lorg/apache/commons/math3/FieldElement; (2, 1)
	103 invokevirtual (2, 1)
	104 org/apache/commons/math3/linear/SparseFieldVector.setEntry:(ILorg/apache/commons/math3/FieldElement;)V (2, 1)
	106 goto (0, 0)
	107 -46 (0, 0)
	109 aload_3 (0, 0)
	110 areturn (0, 0)

Method: mapAdd
	0 aload_0 (0, 0)
	1 invokevirtual (0, 0)
	2 org/apache/commons/math3/linear/SparseFieldVector.copy:()Lorg/apache/commons/math3/linear/FieldVector; (0, 0)
	4 aload_1 (0, 0)
	5 invokeinterface (0, 0)
	6 org/apache/commons/math3/linear/FieldVector.mapDivideToSelf:(Lorg/apache/commons/math3/FieldElement;)Lorg/apache/commons/math3/linear/FieldVector; (0, 0)
	8 0 (0, 0)
	10 areturn (0, 0)

Method: mapAddToSelf
	0 iconst_0 (1, 4)
	1 istore_2 (1, 4)
	2 iload_2 (1, 4)
	3 aload_0 (1, 4)
	4 getfield (1, 4)
	5 org/apache/commons/math3/linear/SparseFieldVector.virtualSize:I (1, 4)
	7 if_icmpge (1, 4)
	8 28 (1, 4)
	10 aload_0 (1, 4)
	11 iload_2 (1, 4)
	12 aload_0 (1, 4)
	13 iload_2 (1, 4)
	14 invokevirtual (1, 4)
	15 org/apache/commons/math3/linear/SparseFieldVector.getEntry:(I)Lorg/apache/commons/math3/FieldElement; (1, 4)
	17 aload_1 (1, 4)
	18 invokeinterface (1, 4)
	19 org/apache/commons/math3/FieldElement.org/apache/commons/math3/FieldElement (1, 4)
	21 0 (1, 4)
	23 checkcast (1, 4)
	24 org/apache/commons/math3/FieldElement (1, 4)
	26 invokevirtual (1, 4)
	27 org/apache/commons/math3/linear/SparseFieldVector.setEntry:(ILorg/apache/commons/math3/FieldElement;)V (1, 4)
	29 iinc (1, 4)
	30 #2 (1, 4)
	31 -89 (1, 4)
	32 goto (1, 4)
	33 -30 (1, 4)
	35 aload_0 (0, 0)
	36 areturn (0, 0)

Method: mapDivide
	0 aload_0 (0, 0)
	1 invokevirtual (0, 0)
	2 org/apache/commons/math3/linear/SparseFieldVector.copy:()Lorg/apache/commons/math3/linear/FieldVector; (0, 0)
	4 aload_1 (0, 0)
	5 invokeinterface (0, 0)
	6 org/apache/commons/math3/linear/FieldVector.mapInvToSelf:()Lorg/apache/commons/math3/linear/FieldVector; (0, 0)
	8 0 (0, 0)
	10 areturn (0, 0)

Method: mapDivideToSelf
	0 aload_0 (0, 0)
	1 getfield (0, 0)
	2 org/apache/commons/math3/linear/SparseFieldVector.entries:Lorg/apache/commons/math3/util/OpenIntToFieldHashMap; (0, 0)
	4 invokevirtual (0, 0)
	5 org/apache/commons/math3/util/OpenIntToFieldHashMap.iterator:()Lorg/apache/commons/math3/util/OpenIntToFieldHashMap$Iterator; (0, 0)
	7 astore_2 (0, 0)
	8 aload_2 (1, 3)
	9 invokevirtual (1, 3)
	10 org/apache/commons/math3/util/OpenIntToFieldHashMap$Iterator.hasNext:()Z (1, 3)
	12 ifeq (1, 3)
	13 35 (1, 3)
	15 aload_2 (1, 3)
	16 invokevirtual (1, 3)
	17 org/apache/commons/math3/util/OpenIntToFieldHashMap$Iterator.advance:()V (1, 3)
	19 aload_0 (1, 3)
	20 getfield (1, 3)
	21 org/apache/commons/math3/linear/SparseFieldVector.entries:Lorg/apache/commons/math3/util/OpenIntToFieldHashMap; (1, 3)
	23 aload_2 (1, 3)
	24 invokevirtual (1, 3)
	25 org/apache/commons/math3/util/OpenIntToFieldHashMap$Iterator.key:()I (1, 3)
	27 aload_2 (1, 3)
	28 invokevirtual (1, 3)
	29 org/apache/commons/math3/util/OpenIntToFieldHashMap$Iterator.value:()Lorg/apache/commons/math3/FieldElement; (1, 3)
	31 aload_1 (1, 3)
	32 invokeinterface (1, 3)
	33 org/apache/commons/math3/FieldElement.toArray:()[Lorg/apache/commons/math3/FieldElement; (1, 3)
	35 0 (1, 3)
	37 checkcast (1, 3)
	38 org/apache/commons/math3/FieldElement (1, 3)
	40 invokevirtual (1, 3)
	41 org/apache/commons/math3/util/OpenIntToFieldHashMap.put:(ILorg/apache/commons/math3/FieldElement;)Lorg/apache/commons/math3/FieldElement; (1, 3)
	43 pop (1, 3)
	44 goto (1, 3)
	45 -36 (1, 3)
	47 aload_0 (0, 0)
	48 areturn (0, 0)

Method: mapInv
	0 aload_0 (0, 0)
	1 invokevirtual (0, 0)
	2 org/apache/commons/math3/linear/SparseFieldVector.copy:()Lorg/apache/commons/math3/linear/FieldVector; (0, 0)
	4 invokeinterface (0, 0)
	5 org/apache/commons/math3/linear/FieldVector.getOne:()Ljava/lang/Object; (0, 0)
	7 0 (0, 0)
	9 areturn (0, 0)

Method: mapInvToSelf
	0 iconst_0 (1, 4)
	1 istore_1 (1, 4)
	2 iload_1 (1, 4)
	3 aload_0 (1, 4)
	4 getfield (1, 4)
	5 org/apache/commons/math3/linear/SparseFieldVector.virtualSize:I (1, 4)
	7 if_icmpge (1, 4)
	8 39 (1, 4)
	10 aload_0 (1, 4)
	11 iload_1 (1, 4)
	12 aload_0 (1, 4)
	13 getfield (1, 4)
	14 org/apache/commons/math3/linear/SparseFieldVector.field:Lorg/apache/commons/math3/Field; (1, 4)
	16 invokeinterface (1, 4)
	17 org/apache/commons/math3/Field.mapMultiplyToSelf:(Lorg/apache/commons/math3/FieldElement;)Lorg/apache/commons/math3/linear/FieldVector; (1, 4)
	19 0 (1, 4)
	21 checkcast (1, 4)
	22 org/apache/commons/math3/FieldElement (1, 4)
	24 aload_0 (1, 4)
	25 iload_1 (1, 4)
	26 invokevirtual (1, 4)
	27 org/apache/commons/math3/linear/SparseFieldVector.getEntry:(I)Lorg/apache/commons/math3/FieldElement; (1, 4)
	29 invokeinterface (1, 4)
	30 org/apache/commons/math3/FieldElement.toArray:()[Lorg/apache/commons/math3/FieldElement; (1, 4)
	32 0 (1, 4)
	34 checkcast (1, 4)
	35 org/apache/commons/math3/FieldElement (1, 4)
	37 invokevirtual (1, 4)
	38 org/apache/commons/math3/linear/SparseFieldVector.setEntry:(ILorg/apache/commons/math3/FieldElement;)V (1, 4)
	40 iinc (1, 4)
	41 #1 (1, 4)
	42 -89 (1, 4)
	43 goto (1, 4)
	44 -41 (1, 4)
	46 aload_0 (0, 0)
	47 areturn (0, 0)

Method: mapMultiply
	0 aload_0 (0, 0)
	1 invokevirtual (0, 0)
	2 org/apache/commons/math3/linear/SparseFieldVector.copy:()Lorg/apache/commons/math3/linear/FieldVector; (0, 0)
	4 aload_1 (0, 0)
	5 invokeinterface (0, 0)
	6 org/apache/commons/math3/linear/FieldVector.mapSubtractToSelf:(Lorg/apache/commons/math3/FieldElement;)Lorg/apache/commons/math3/linear/FieldVector; (0, 0)
	8 0 (0, 0)
	10 areturn (0, 0)

Method: mapMultiplyToSelf
	0 aload_0 (0, 0)
	1 getfield (0, 0)
	2 org/apache/commons/math3/linear/SparseFieldVector.entries:Lorg/apache/commons/math3/util/OpenIntToFieldHashMap; (0, 0)
	4 invokevirtual (0, 0)
	5 org/apache/commons/math3/util/OpenIntToFieldHashMap.iterator:()Lorg/apache/commons/math3/util/OpenIntToFieldHashMap$Iterator; (0, 0)
	7 astore_2 (0, 0)
	8 aload_2 (1, 3)
	9 invokevirtual (1, 3)
	10 org/apache/commons/math3/util/OpenIntToFieldHashMap$Iterator.hasNext:()Z (1, 3)
	12 ifeq (1, 3)
	13 35 (1, 3)
	15 aload_2 (1, 3)
	16 invokevirtual (1, 3)
	17 org/apache/commons/math3/util/OpenIntToFieldHashMap$Iterator.advance:()V (1, 3)
	19 aload_0 (1, 3)
	20 getfield (1, 3)
	21 org/apache/commons/math3/linear/SparseFieldVector.entries:Lorg/apache/commons/math3/util/OpenIntToFieldHashMap; (1, 3)
	23 aload_2 (1, 3)
	24 invokevirtual (1, 3)
	25 org/apache/commons/math3/util/OpenIntToFieldHashMap$Iterator.key:()I (1, 3)
	27 aload_2 (1, 3)
	28 invokevirtual (1, 3)
	29 org/apache/commons/math3/util/OpenIntToFieldHashMap$Iterator.value:()Lorg/apache/commons/math3/FieldElement; (1, 3)
	31 aload_1 (1, 3)
	32 invokeinterface (1, 3)
	33 org/apache/commons/math3/FieldElement.divide:(Ljava/lang/Object;)Ljava/lang/Object; (1, 3)
	35 0 (1, 3)
	37 checkcast (1, 3)
	38 org/apache/commons/math3/FieldElement (1, 3)
	40 invokevirtual (1, 3)
	41 org/apache/commons/math3/util/OpenIntToFieldHashMap.put:(ILorg/apache/commons/math3/FieldElement;)Lorg/apache/commons/math3/FieldElement; (1, 3)
	43 pop (1, 3)
	44 goto (1, 3)
	45 -36 (1, 3)
	47 aload_0 (0, 0)
	48 areturn (0, 0)

Method: mapSubtract
	0 aload_0 (0, 0)
	1 invokevirtual (0, 0)
	2 org/apache/commons/math3/linear/SparseFieldVector.copy:()Lorg/apache/commons/math3/linear/FieldVector; (0, 0)
	4 aload_1 (0, 0)
	5 invokeinterface (0, 0)
	6 org/apache/commons/math3/linear/FieldVector.subtract:(Ljava/lang/Object;)Ljava/lang/Object; (0, 0)
	8 0 (0, 0)
	10 areturn (0, 0)

Method: mapSubtractToSelf
	0 aload_0 (0, 0)
	1 aload_0 (0, 0)
	2 getfield (0, 0)
	3 org/apache/commons/math3/linear/SparseFieldVector.field:Lorg/apache/commons/math3/Field; (0, 0)
	5 invokeinterface (0, 0)
	6 org/apache/commons/math3/Field.multiply:(Ljava/lang/Object;)Ljava/lang/Object; (0, 0)
	8 0 (0, 0)
	10 checkcast (0, 0)
	11 org/apache/commons/math3/FieldElement (0, 0)
	13 aload_1 (0, 0)
	14 invokeinterface (0, 0)
	15 org/apache/commons/math3/FieldElement.org/apache/commons/math3/linear/SparseFieldMatrix (0, 0)
	17 0 (0, 0)
	19 checkcast (0, 0)
	20 org/apache/commons/math3/FieldElement (0, 0)
	22 invokevirtual (0, 0)
	23 org/apache/commons/math3/linear/SparseFieldVector.mapAddToSelf:(Lorg/apache/commons/math3/FieldElement;)Lorg/apache/commons/math3/linear/FieldVector; (0, 0)
	25 areturn (0, 0)

Method: outerProduct
	0 aload_1 (1, 1)
	1 instanceof (1, 1)
	2 org/apache/commons/math3/linear/SparseFieldVector (1, 1)
	4 ifeq (1, 1)
	5 12 (1, 1)
	7 aload_0 (1, 1)
	8 aload_1 (1, 1)
	9 checkcast (1, 1)
	10 org/apache/commons/math3/linear/SparseFieldVector (1, 1)
	12 invokevirtual (1, 1)
	13 org/apache/commons/math3/linear/SparseFieldVector.outerProduct:(Lorg/apache/commons/math3/linear/SparseFieldVector;)Lorg/apache/commons/math3/linear/FieldMatrix; (1, 1)
	15 areturn (1, 1)
	16 aload_1 (2, 2)
	17 invokeinterface (2, 2)
	18 org/apache/commons/math3/linear/FieldVector.<init>:(Lorg/apache/commons/math3/util/OpenIntToFieldHashMap;)V (2, 2)
	20 0 (2, 2)
	22 istore_2 (2, 2)
	23 new (2, 2)
	24 org/apache/commons/math3/linear/SparseFieldMatrix (2, 2)
	26 dup (2, 2)
	27 aload_0 (2, 2)
	28 getfield (2, 2)
	29 org/apache/commons/math3/linear/SparseFieldVector.field:Lorg/apache/commons/math3/Field; (2, 2)
	31 aload_0 (2, 2)
	32 getfield (2, 2)
	33 org/apache/commons/math3/linear/SparseFieldVector.virtualSize:I (2, 2)
	35 iload_2 (2, 2)
	36 invokespecial (2, 2)
	37 org/apache/commons/math3/linear/SparseFieldMatrix.<init>:(Lorg/apache/commons/math3/Field;II)V (2, 2)
	39 astore_3 (2, 2)
	40 aload_0 (2, 2)
	41 getfield (2, 2)
	42 org/apache/commons/math3/linear/SparseFieldVector.entries:Lorg/apache/commons/math3/util/OpenIntToFieldHashMap; (2, 2)
	44 invokevirtual (2, 2)
	45 org/apache/commons/math3/util/OpenIntToFieldHashMap.iterator:()Lorg/apache/commons/math3/util/OpenIntToFieldHashMap$Iterator; (2, 2)
	47 astore (2, 2)
	48 #4 (2, 2)
	49 aload (3, 3)
	50 #4 (3, 3)
	51 invokevirtual (3, 3)
	52 org/apache/commons/math3/util/OpenIntToFieldHashMap$Iterator.hasNext:()Z (3, 3)
	54 ifeq (3, 3)
	55 68 (3, 3)
	57 aload (3, 3)
	58 #4 (3, 3)
	59 invokevirtual (3, 3)
	60 org/apache/commons/math3/util/OpenIntToFieldHashMap$Iterator.advance:()V (3, 3)
	62 aload (3, 3)
	63 #4 (3, 3)
	64 invokevirtual (3, 3)
	65 org/apache/commons/math3/util/OpenIntToFieldHashMap$Iterator.key:()I (3, 3)
	67 istore (3, 3)
	68 #5 (3, 3)
	69 aload (3, 3)
	70 #4 (3, 3)
	71 invokevirtual (3, 3)
	72 org/apache/commons/math3/util/OpenIntToFieldHashMap$Iterator.value:()Lorg/apache/commons/math3/FieldElement; (3, 3)
	74 astore (3, 3)
	75 #6 (3, 3)
	76 iconst_0 (4, 4)
	77 istore (4, 4)
	78 #7 (4, 4)
	79 iload (4, 4)
	80 #7 (4, 4)
	81 iload_2 (4, 4)
	82 if_icmpge (4, 4)
	83 37 (4, 4)
	85 aload_3 (4, 4)
	86 iload (4, 4)
	87 #5 (4, 4)
	88 iload (4, 4)
	89 #7 (4, 4)
	90 aload (4, 4)
	91 #6 (4, 4)
	92 aload_1 (4, 4)
	93 iload (4, 4)
	94 #7 (4, 4)
	95 invokeinterface (4, 4)
	96 org/apache/commons/math3/linear/FieldVector.<init>:(Lorg/apache/commons/math3/linear/SparseFieldVector;)V (4, 4)
	98 0 (4, 4)
	100 invokeinterface (4, 4)
	101 org/apache/commons/math3/FieldElement.divide:(Ljava/lang/Object;)Ljava/lang/Object; (4, 4)
	103 0 (4, 4)
	105 checkcast (4, 4)
	106 org/apache/commons/math3/FieldElement (4, 4)
	108 invokeinterface (4, 4)
	109 org/apache/commons/math3/linear/FieldMatrix.outerProduct:(Lorg/apache/commons/math3/linear/SparseFieldVector;)Lorg/apache/commons/math3/linear/FieldMatrix; (4, 4)
	111 0 (4, 4)
	113 iinc (4, 4)
	114 #7 (4, 4)
	115 -89 (4, 4)
	116 goto (4, 4)
	117 -37 (4, 4)
	119 goto (2, 2)
	120 -70 (2, 2)
	122 aload_3 (2, 2)
	123 areturn (1, 2)

Method: projection
	0 aload_0 (0, 0)
	1 aload_1 (0, 0)
	2 invokeinterface (0, 0)
	3 org/apache/commons/math3/linear/FieldVector.<init>:(Lorg/apache/commons/math3/util/OpenIntToFieldHashMap;)V (0, 0)
	5 0 (0, 0)
	7 invokevirtual (0, 0)
	8 org/apache/commons/math3/linear/SparseFieldVector.checkVectorDimensions:(I)V (0, 0)
	10 aload_1 (0, 0)
	11 aload_0 (0, 0)
	12 aload_1 (0, 0)
	13 invokevirtual (0, 0)
	14 org/apache/commons/math3/linear/SparseFieldVector.dotProduct:(Lorg/apache/commons/math3/linear/FieldVector;)Lorg/apache/commons/math3/FieldElement; (0, 0)
	16 aload_1 (0, 0)
	17 aload_1 (0, 0)
	18 invokeinterface (0, 0)
	19 org/apache/commons/math3/linear/FieldVector.mapMultiply:(Lorg/apache/commons/math3/FieldElement;)Lorg/apache/commons/math3/linear/FieldVector; (0, 0)
	21 0 (0, 0)
	23 invokeinterface (0, 0)
	24 org/apache/commons/math3/FieldElement.toArray:()[Lorg/apache/commons/math3/FieldElement; (0, 0)
	26 0 (0, 0)
	28 checkcast (0, 0)
	29 org/apache/commons/math3/FieldElement (0, 0)
	31 invokeinterface (0, 0)
	32 org/apache/commons/math3/linear/FieldVector.subtract:(Lorg/apache/commons/math3/linear/SparseFieldVector;)Lorg/apache/commons/math3/linear/SparseFieldVector; (0, 0)
	34 0 (0, 0)
	36 areturn (0, 0)

Method: set
	0 aload_1 (0, 0)
	1 invokestatic (0, 0)
	2 org/apache/commons/math3/util/MathUtils.checkNotNull:(Ljava/lang/Object;)V (0, 0)
	4 iconst_0 (1, 4)
	5 istore_2 (1, 4)
	6 iload_2 (1, 4)
	7 aload_0 (1, 4)
	8 getfield (1, 4)
	9 org/apache/commons/math3/linear/SparseFieldVector.virtualSize:I (1, 4)
	11 if_icmpge (1, 4)
	12 15 (1, 4)
	14 aload_0 (1, 4)
	15 iload_2 (1, 4)
	16 aload_1 (1, 4)
	17 invokevirtual (1, 4)
	18 org/apache/commons/math3/linear/SparseFieldVector.setEntry:(ILorg/apache/commons/math3/FieldElement;)V (1, 4)
	20 iinc (1, 4)
	21 #2 (1, 4)
	22 -89 (1, 4)
	23 goto (1, 4)
	24 -17 (1, 4)
	26 return (0, 0)

Method: setEntry
	0 aload_2 (0, 0)
	1 invokestatic (0, 0)
	2 org/apache/commons/math3/util/MathUtils.checkNotNull:(Ljava/lang/Object;)V (0, 0)
	4 aload_0 (0, 0)
	5 iload_1 (0, 0)
	6 invokespecial (0, 0)
	7 org/apache/commons/math3/linear/SparseFieldVector.checkIndex:(I)V (0, 0)
	9 aload_0 (0, 0)
	10 getfield (0, 0)
	11 org/apache/commons/math3/linear/SparseFieldVector.entries:Lorg/apache/commons/math3/util/OpenIntToFieldHashMap; (0, 0)
	13 iload_1 (0, 0)
	14 aload_2 (0, 0)
	15 invokevirtual (0, 0)
	16 org/apache/commons/math3/util/OpenIntToFieldHashMap.put:(ILorg/apache/commons/math3/FieldElement;)Lorg/apache/commons/math3/FieldElement; (0, 0)
	18 pop (0, 0)
	19 return (0, 0)

Method: setSubVector
	0 aload_0 (0, 0)
	1 iload_1 (0, 0)
	2 invokespecial (0, 0)
	3 org/apache/commons/math3/linear/SparseFieldVector.checkIndex:(I)V (0, 0)
	5 aload_0 (0, 0)
	6 iload_1 (0, 0)
	7 aload_2 (0, 0)
	8 invokeinterface (0, 0)
	9 org/apache/commons/math3/linear/FieldVector.<init>:(Lorg/apache/commons/math3/util/OpenIntToFieldHashMap;)V (0, 0)
	11 0 (0, 0)
	13 iadd (0, 0)
	14 iconst_1 (0, 0)
	15 isub (0, 0)
	16 invokespecial (0, 0)
	17 org/apache/commons/math3/linear/SparseFieldVector.checkIndex:(I)V (0, 0)
	19 aload_2 (0, 0)
	20 invokeinterface (0, 0)
	21 org/apache/commons/math3/linear/FieldVector.<init>:(Lorg/apache/commons/math3/util/OpenIntToFieldHashMap;)V (0, 0)
	23 0 (0, 0)
	25 istore_3 (0, 0)
	26 iconst_0 (1, 4)
	27 istore (1, 4)
	28 #4 (1, 4)
	29 iload (1, 4)
	30 #4 (1, 4)
	31 iload_3 (1, 4)
	32 if_icmpge (1, 4)
	33 25 (1, 4)
	35 aload_0 (1, 4)
	36 iload (1, 4)
	37 #4 (1, 4)
	38 iload_1 (1, 4)
	39 iadd (1, 4)
	40 aload_2 (1, 4)
	41 iload (1, 4)
	42 #4 (1, 4)
	43 invokeinterface (1, 4)
	44 org/apache/commons/math3/linear/FieldVector.<init>:(Lorg/apache/commons/math3/linear/SparseFieldVector;)V (1, 4)
	46 0 (1, 4)
	48 invokevirtual (1, 4)
	49 org/apache/commons/math3/linear/SparseFieldVector.setEntry:(ILorg/apache/commons/math3/FieldElement;)V (1, 4)
	51 iinc (1, 4)
	52 #4 (1, 4)
	53 -89 (1, 4)
	54 goto (1, 4)
	55 -25 (1, 4)
	57 return (0, 0)

Method: subtract
	0 aload_1 (1, 1)
	1 instanceof (1, 1)
	2 org/apache/commons/math3/linear/SparseFieldVector (1, 1)
	4 ifeq (1, 1)
	5 12 (1, 1)
	7 aload_0 (1, 1)
	8 aload_1 (1, 1)
	9 checkcast (1, 1)
	10 org/apache/commons/math3/linear/SparseFieldVector (1, 1)
	12 invokevirtual (1, 1)
	13 org/apache/commons/math3/linear/SparseFieldVector.subtract:(Lorg/apache/commons/math3/linear/SparseFieldVector;)Lorg/apache/commons/math3/linear/SparseFieldVector; (1, 1)
	15 areturn (1, 1)
	16 aload_1 (2, 2)
	17 invokeinterface (2, 2)
	18 org/apache/commons/math3/linear/FieldVector.<init>:(Lorg/apache/commons/math3/util/OpenIntToFieldHashMap;)V (2, 2)
	20 0 (2, 2)
	22 istore_2 (2, 2)
	23 aload_0 (2, 2)
	24 iload_2 (2, 2)
	25 invokevirtual (2, 2)
	26 org/apache/commons/math3/linear/SparseFieldVector.checkVectorDimensions:(I)V (2, 2)
	28 new (2, 2)
	29 org/apache/commons/math3/linear/SparseFieldVector (2, 2)
	31 dup (2, 2)
	32 aload_0 (2, 2)
	33 invokespecial (2, 2)
	34 org/apache/commons/math3/linear/SparseFieldVector.<init>:(Lorg/apache/commons/math3/linear/SparseFieldVector;)V (2, 2)
	36 astore_3 (2, 2)
	37 iconst_0 (3, 4)
	38 istore (3, 4)
	39 #4 (3, 4)
	40 iload (3, 4)
	41 #4 (3, 4)
	42 iload_2 (3, 4)
	43 if_icmpge (3, 4)
	44 89 (3, 4)
	46 aload_0 (4, 1)
	47 getfield (4, 1)
	48 org/apache/commons/math3/linear/SparseFieldVector.entries:Lorg/apache/commons/math3/util/OpenIntToFieldHashMap; (4, 1)
	50 iload (4, 1)
	51 #4 (4, 1)
	52 invokevirtual (4, 1)
	53 org/apache/commons/math3/util/OpenIntToFieldHashMap.containsKey:(I)Z (4, 1)
	55 ifeq (4, 1)
	56 37 (4, 1)
	58 aload_3 (4, 1)
	59 iload (4, 1)
	60 #4 (4, 1)
	61 aload_0 (4, 1)
	62 getfield (4, 1)
	63 org/apache/commons/math3/linear/SparseFieldVector.entries:Lorg/apache/commons/math3/util/OpenIntToFieldHashMap; (4, 1)
	65 iload (4, 1)
	66 #4 (4, 1)
	67 invokevirtual (4, 1)
	68 org/apache/commons/math3/util/OpenIntToFieldHashMap.get:(I)Lorg/apache/commons/math3/FieldElement; (4, 1)
	70 aload_1 (4, 1)
	71 iload (4, 1)
	72 #4 (4, 1)
	73 invokeinterface (4, 1)
	74 org/apache/commons/math3/linear/FieldVector.<init>:(Lorg/apache/commons/math3/linear/SparseFieldVector;)V (4, 1)
	76 0 (4, 1)
	78 invokeinterface (4, 1)
	79 org/apache/commons/math3/FieldElement.org/apache/commons/math3/linear/SparseFieldMatrix (4, 1)
	81 0 (4, 1)
	83 checkcast (4, 1)
	84 org/apache/commons/math3/FieldElement (4, 1)
	86 invokevirtual (4, 1)
	87 org/apache/commons/math3/linear/SparseFieldVector.setEntry:(ILorg/apache/commons/math3/FieldElement;)V (4, 1)
	89 goto (4, 1)
	90 37 (4, 1)
	92 aload_3 (5, 2)
	93 iload (5, 2)
	94 #4 (5, 2)
	95 aload_0 (5, 2)
	96 getfield (5, 2)
	97 org/apache/commons/math3/linear/SparseFieldVector.field:Lorg/apache/commons/math3/Field; (5, 2)
	99 invokeinterface (5, 2)
	100 org/apache/commons/math3/Field.multiply:(Ljava/lang/Object;)Ljava/lang/Object; (5, 2)
	102 0 (5, 2)
	104 checkcast (5, 2)
	105 org/apache/commons/math3/FieldElement (5, 2)
	107 aload_1 (5, 2)
	108 iload (5, 2)
	109 #4 (5, 2)
	110 invokeinterface (5, 2)
	111 org/apache/commons/math3/linear/FieldVector.<init>:(Lorg/apache/commons/math3/linear/SparseFieldVector;)V (5, 2)
	113 0 (5, 2)
	115 invokeinterface (5, 2)
	116 org/apache/commons/math3/FieldElement.org/apache/commons/math3/linear/SparseFieldMatrix (5, 2)
	118 0 (5, 2)
	120 checkcast (5, 2)
	121 org/apache/commons/math3/FieldElement (5, 2)
	123 invokevirtual (5, 2)
	124 org/apache/commons/math3/linear/SparseFieldVector.setEntry:(ILorg/apache/commons/math3/FieldElement;)V (5, 2)
	126 iinc (5, 2)
	127 #4 (5, 2)
	128 -89 (5, 2)
	129 goto (5, 2)
	130 -89 (5, 2)
	132 aload_3 (3, 4)
	133 areturn (2, 4)

Method: toArray
	0 aload_0 (0, 0)
	1 getfield (0, 0)
	2 org/apache/commons/math3/linear/SparseFieldVector.field:Lorg/apache/commons/math3/Field; (0, 0)
	4 aload_0 (0, 0)
	5 getfield (0, 0)
	6 org/apache/commons/math3/linear/SparseFieldVector.virtualSize:I (0, 0)
	8 invokestatic (0, 0)
	9 org/apache/commons/math3/util/MathArrays.buildArray:(Lorg/apache/commons/math3/Field;I)[Ljava/lang/Object; (0, 0)
	11 checkcast (0, 0)
	12 [Lorg/apache/commons/math3/FieldElement; (0, 0)
	14 astore_1 (0, 0)
	15 aload_0 (0, 0)
	16 getfield (0, 0)
	17 org/apache/commons/math3/linear/SparseFieldVector.entries:Lorg/apache/commons/math3/util/OpenIntToFieldHashMap; (0, 0)
	19 invokevirtual (0, 0)
	20 org/apache/commons/math3/util/OpenIntToFieldHashMap.iterator:()Lorg/apache/commons/math3/util/OpenIntToFieldHashMap$Iterator; (0, 0)
	22 astore_2 (0, 0)
	23 aload_2 (1, 3)
	24 invokevirtual (1, 3)
	25 org/apache/commons/math3/util/OpenIntToFieldHashMap$Iterator.hasNext:()Z (1, 3)
	27 ifeq (1, 3)
	28 20 (1, 3)
	30 aload_2 (1, 3)
	31 invokevirtual (1, 3)
	32 org/apache/commons/math3/util/OpenIntToFieldHashMap$Iterator.advance:()V (1, 3)
	34 aload_1 (1, 3)
	35 aload_2 (1, 3)
	36 invokevirtual (1, 3)
	37 org/apache/commons/math3/util/OpenIntToFieldHashMap$Iterator.key:()I (1, 3)
	39 aload_2 (1, 3)
	40 invokevirtual (1, 3)
	41 org/apache/commons/math3/util/OpenIntToFieldHashMap$Iterator.value:()Lorg/apache/commons/math3/FieldElement; (1, 3)
	43 aastore (1, 3)
	44 goto (1, 3)
	45 -21 (1, 3)
	47 aload_1 (0, 0)
	48 areturn (0, 0)

Method: checkIndex
	0 iload_1 (1, 1)
	1 iflt (1, 1)
	2 11 (1, 1)
	4 iload_1 (1, 1)
	5 aload_0 (1, 1)
	6 invokevirtual (1, 1)
	7 org/apache/commons/math3/linear/SparseFieldVector.getDimension:()I (1, 1)
	9 if_icmplt (1, 1)
	10 28 (1, 1)
	12 new (1, 1)
	13 org/apache/commons/math3/exception/OutOfRangeException (1, 1)
	15 dup (1, 1)
	16 iload_1 (1, 1)
	17 invokestatic (1, 1)
	18 java/lang/Integer.valueOf:(I)Ljava/lang/Integer; (1, 1)
	20 iconst_0 (1, 1)
	21 invokestatic (1, 1)
	22 java/lang/Integer.valueOf:(I)Ljava/lang/Integer; (1, 1)
	24 aload_0 (1, 1)
	25 invokevirtual (1, 1)
	26 org/apache/commons/math3/linear/SparseFieldVector.getDimension:()I (1, 1)
	28 iconst_1 (1, 1)
	29 isub (1, 1)
	30 invokestatic (1, 1)
	31 java/lang/Integer.valueOf:(I)Ljava/lang/Integer; (1, 1)
	33 invokespecial (1, 1)
	34 org/apache/commons/math3/exception/OutOfRangeException.<init>:(Ljava/lang/Number;Ljava/lang/Number;Ljava/lang/Number;)V (1, 1)
	36 athrow (1, 1)
	37 return (0, 0)

Method: checkIndices
	0 aload_0 (0, 0)
	1 invokevirtual (0, 0)
	2 org/apache/commons/math3/linear/SparseFieldVector.getDimension:()I (0, 0)
	4 istore_3 (0, 0)
	5 iload_1 (1, 1)
	6 iflt (1, 1)
	7 8 (1, 1)
	9 iload_1 (1, 1)
	10 iload_3 (1, 1)
	11 if_icmplt (1, 1)
	12 28 (1, 1)
	14 new (1, 1)
	15 org/apache/commons/math3/exception/OutOfRangeException (1, 1)
	17 dup (1, 1)
	18 getstatic (1, 1)
	19 org/apache/commons/math3/exception/util/LocalizedFormats.INDEX:Lorg/apache/commons/math3/exception/util/LocalizedFormats; (1, 1)
	21 iload_1 (1, 1)
	22 invokestatic (1, 1)
	23 java/lang/Integer.valueOf:(I)Ljava/lang/Integer; (1, 1)
	25 iconst_0 (1, 1)
	26 invokestatic (1, 1)
	27 java/lang/Integer.valueOf:(I)Ljava/lang/Integer; (1, 1)
	29 iload_3 (1, 1)
	30 iconst_1 (1, 1)
	31 isub (1, 1)
	32 invokestatic (1, 1)
	33 java/lang/Integer.valueOf:(I)Ljava/lang/Integer; (1, 1)
	35 invokespecial (1, 1)
	36 org/apache/commons/math3/exception/OutOfRangeException.<init>:(Lorg/apache/commons/math3/exception/util/Localizable;Ljava/lang/Number;Ljava/lang/Number;Ljava/lang/Number;)V (1, 1)
	38 athrow (1, 1)
	39 iload_2 (1, 1)
	40 iflt (1, 1)
	41 8 (1, 1)
	43 iload_2 (1, 1)
	44 iload_3 (1, 1)
	45 if_icmplt (1, 1)
	46 28 (1, 1)
	48 new (1, 1)
	49 org/apache/commons/math3/exception/OutOfRangeException (1, 1)
	51 dup (1, 1)
	52 getstatic (1, 1)
	53 org/apache/commons/math3/exception/util/LocalizedFormats.INDEX:Lorg/apache/commons/math3/exception/util/LocalizedFormats; (1, 1)
	55 iload_2 (1, 1)
	56 invokestatic (1, 1)
	57 java/lang/Integer.valueOf:(I)Ljava/lang/Integer; (1, 1)
	59 iconst_0 (1, 1)
	60 invokestatic (1, 1)
	61 java/lang/Integer.valueOf:(I)Ljava/lang/Integer; (1, 1)
	63 iload_3 (1, 1)
	64 iconst_1 (1, 1)
	65 isub (1, 1)
	66 invokestatic (1, 1)
	67 java/lang/Integer.valueOf:(I)Ljava/lang/Integer; (1, 1)
	69 invokespecial (1, 1)
	70 org/apache/commons/math3/exception/OutOfRangeException.<init>:(Lorg/apache/commons/math3/exception/util/Localizable;Ljava/lang/Number;Ljava/lang/Number;Ljava/lang/Number;)V (1, 1)
	72 athrow (1, 1)
	73 iload_2 (1, 1)
	74 iload_1 (1, 1)
	75 if_icmpge (1, 1)
	76 23 (1, 1)
	78 new (1, 1)
	79 org/apache/commons/math3/exception/NumberIsTooSmallException (1, 1)
	81 dup (1, 1)
	82 getstatic (1, 1)
	83 org/apache/commons/math3/exception/util/LocalizedFormats.INITIAL_ROW_AFTER_FINAL_ROW:Lorg/apache/commons/math3/exception/util/LocalizedFormats; (1, 1)
	85 iload_2 (1, 1)
	86 invokestatic (1, 1)
	87 java/lang/Integer.valueOf:(I)Ljava/lang/Integer; (1, 1)
	89 iload_1 (1, 1)
	90 invokestatic (1, 1)
	91 java/lang/Integer.valueOf:(I)Ljava/lang/Integer; (1, 1)
	93 iconst_0 (1, 1)
	94 invokespecial (1, 1)
	95 org/apache/commons/math3/exception/NumberIsTooSmallException.<init>:(Lorg/apache/commons/math3/exception/util/Localizable;Ljava/lang/Number;Ljava/lang/Number;Z)V (1, 1)
	97 athrow (1, 1)
	98 return (0, 0)

Method: checkVectorDimensions
	0 aload_0 (1, 1)
	1 invokevirtual (1, 1)
	2 org/apache/commons/math3/linear/SparseFieldVector.getDimension:()I (1, 1)
	4 iload_1 (1, 1)
	5 if_icmpeq (1, 1)
	6 16 (1, 1)
	8 new (1, 1)
	9 org/apache/commons/math3/exception/DimensionMismatchException (1, 1)
	11 dup (1, 1)
	12 aload_0 (1, 1)
	13 invokevirtual (1, 1)
	14 org/apache/commons/math3/linear/SparseFieldVector.getDimension:()I (1, 1)
	16 iload_1 (1, 1)
	17 invokespecial (1, 1)
	18 org/apache/commons/math3/exception/DimensionMismatchException.<init>:(II)V (1, 1)
	20 athrow (1, 1)
	21 return (0, 0)

Method: walkInDefaultOrder
	0 aload_0 (0, 0)
	1 iload_2 (0, 0)
	2 iload_3 (0, 0)
	3 invokespecial (0, 0)
	4 org/apache/commons/math3/linear/SparseFieldVector.checkIndices:(II)V (0, 0)
	6 aload_1 (0, 0)
	7 aload_0 (0, 0)
	8 invokevirtual (0, 0)
	9 org/apache/commons/math3/linear/SparseFieldVector.getDimension:()I (0, 0)
	11 iload_2 (0, 0)
	12 iload_3 (0, 0)
	13 invokeinterface (0, 0)
	14 org/apache/commons/math3/linear/FieldVectorChangingVisitor.visit:(ILorg/apache/commons/math3/FieldElement;)V (0, 0)
	16 0 (0, 0)
	18 iload_2 (1, 4)
	19 istore (1, 4)
	20 #4 (1, 4)
	21 iload (1, 4)
	22 #4 (1, 4)
	23 iload_3 (1, 4)
	24 if_icmpgt (1, 4)
	25 29 (1, 4)
	27 aload_0 (1, 4)
	28 iload (1, 4)
	29 #4 (1, 4)
	30 aload_1 (1, 4)
	31 iload (1, 4)
	32 #4 (1, 4)
	33 aload_0 (1, 4)
	34 iload (1, 4)
	35 #4 (1, 4)
	36 invokevirtual (1, 4)
	37 org/apache/commons/math3/linear/SparseFieldVector.getEntry:(I)Lorg/apache/commons/math3/FieldElement; (1, 4)
	39 invokeinterface (1, 4)
	40 org/apache/commons/math3/linear/FieldVectorChangingVisitor.walkInDefaultOrder:(Lorg/apache/commons/math3/linear/FieldVectorChangingVisitor;)Lorg/apache/commons/math3/FieldElement; (1, 4)
	42 0 (1, 4)
	44 invokevirtual (1, 4)
	45 org/apache/commons/math3/linear/SparseFieldVector.setEntry:(ILorg/apache/commons/math3/FieldElement;)V (1, 4)
	47 iinc (1, 4)
	48 #4 (1, 4)
	49 -89 (1, 4)
	50 goto (1, 4)
	51 -29 (1, 4)
	53 aload_1 (0, 0)
	54 invokeinterface (0, 0)
	55 org/apache/commons/math3/linear/FieldVectorChangingVisitor.checkIndices:(II)V (0, 0)
	57 0 (0, 0)
	59 areturn (0, 0)

Method: walkInOptimizedOrder
	0 aload_0 (0, 0)
	1 aload_1 (0, 0)
	2 iload_2 (0, 0)
	3 iload_3 (0, 0)
	4 invokevirtual (0, 0)
	5 org/apache/commons/math3/linear/SparseFieldVector.walkInDefaultOrder:(Lorg/apache/commons/math3/linear/FieldVectorChangingVisitor;II)Lorg/apache/commons/math3/FieldElement; (0, 0)
	7 areturn (0, 0)

Method: hashCode
	0 bipush (0, 0)
	1 31 (0, 0)
	2 istore_1 (0, 0)
	3 iconst_1 (0, 0)
	4 istore_2 (0, 0)
	5 bipush (0, 0)
	6 31 (0, 0)
	7 iload_2 (0, 0)
	8 imul (0, 0)
	9 aload_0 (0, 0)
	10 getfield (0, 0)
	11 org/apache/commons/math3/linear/SparseFieldVector.field:Lorg/apache/commons/math3/Field; (0, 0)
	13 ifnonnull (0, 0)
	14 7 (0, 0)
	16 iconst_0 (0, 0)
	17 goto (0, 0)
	18 10 (0, 0)
	20 aload_0 (0, 0)
	21 getfield (0, 0)
	22 org/apache/commons/math3/linear/SparseFieldVector.field:Lorg/apache/commons/math3/Field; (0, 0)
	24 invokevirtual (0, 0)
	25 java/lang/Object.hashCode:()I (0, 0)
	27 iadd (0, 0)
	28 istore_2 (0, 0)
	29 bipush (0, 0)
	30 31 (0, 0)
	31 iload_2 (0, 0)
	32 imul (0, 0)
	33 aload_0 (0, 0)
	34 getfield (0, 0)
	35 org/apache/commons/math3/linear/SparseFieldVector.virtualSize:I (0, 0)
	37 iadd (0, 0)
	38 istore_2 (0, 0)
	39 aload_0 (0, 0)
	40 getfield (0, 0)
	41 org/apache/commons/math3/linear/SparseFieldVector.entries:Lorg/apache/commons/math3/util/OpenIntToFieldHashMap; (0, 0)
	43 invokevirtual (0, 0)
	44 org/apache/commons/math3/util/OpenIntToFieldHashMap.iterator:()Lorg/apache/commons/math3/util/OpenIntToFieldHashMap$Iterator; (0, 0)
	46 astore_3 (0, 0)
	47 aload_3 (1, 3)
	48 invokevirtual (1, 3)
	49 org/apache/commons/math3/util/OpenIntToFieldHashMap$Iterator.hasNext:()Z (1, 3)
	51 ifeq (1, 3)
	52 27 (1, 3)
	54 aload_3 (1, 3)
	55 invokevirtual (1, 3)
	56 org/apache/commons/math3/util/OpenIntToFieldHashMap$Iterator.advance:()V (1, 3)
	58 aload_3 (1, 3)
	59 invokevirtual (1, 3)
	60 org/apache/commons/math3/util/OpenIntToFieldHashMap$Iterator.value:()Lorg/apache/commons/math3/FieldElement; (1, 3)
	62 invokevirtual (1, 3)
	63 java/lang/Object.hashCode:()I (1, 3)
	65 istore (1, 3)
	66 #4 (1, 3)
	67 bipush (1, 3)
	68 31 (1, 3)
	69 iload_2 (1, 3)
	70 imul (1, 3)
	71 iload (1, 3)
	72 #4 (1, 3)
	73 iadd (1, 3)
	74 istore_2 (1, 3)
	75 goto (0, 0)
	76 -28 (0, 0)
	78 iload_2 (0, 0)
	79 ireturn (0, 0)

Method: equals
	0 aload_0 (1, 1)
	1 aload_1 (1, 1)
	2 if_acmpne (1, 1)
	3 5 (1, 1)
	5 iconst_1 (1, 1)
	6 ireturn (1, 1)
	7 aload_1 (1, 1)
	8 instanceof (1, 1)
	9 org/apache/commons/math3/linear/SparseFieldVector (1, 1)
	11 ifne (1, 1)
	12 5 (1, 1)
	14 iconst_0 (1, 1)
	15 ireturn (1, 1)
	16 aload_1 (1, 1)
	17 checkcast (1, 1)
	18 org/apache/commons/math3/linear/SparseFieldVector (1, 1)
	20 astore_2 (1, 1)
	21 aload_0 (2, 1)
	22 getfield (2, 1)
	23 org/apache/commons/math3/linear/SparseFieldVector.field:Lorg/apache/commons/math3/Field; (2, 1)
	25 ifnonnull (2, 1)
	26 12 (2, 1)
	28 aload_2 (3, 1)
	29 getfield (3, 1)
	30 org/apache/commons/math3/linear/SparseFieldVector.field:Lorg/apache/commons/math3/Field; (3, 1)
	32 ifnull (3, 1)
	33 21 (3, 1)
	35 iconst_0 (3, 1)
	36 ireturn (3, 1)
	37 aload_0 (3, 1)
	38 getfield (3, 1)
	39 org/apache/commons/math3/linear/SparseFieldVector.field:Lorg/apache/commons/math3/Field; (3, 1)
	41 aload_2 (3, 1)
	42 getfield (3, 1)
	43 org/apache/commons/math3/linear/SparseFieldVector.field:Lorg/apache/commons/math3/Field; (3, 1)
	45 invokevirtual (3, 1)
	46 java/lang/Object.equals:(Ljava/lang/Object;)Z (3, 1)
	48 ifne (3, 1)
	49 5 (3, 1)
	51 iconst_0 (3, 1)
	52 ireturn (3, 1)
	53 aload_0 (2, 1)
	54 getfield (2, 1)
	55 org/apache/commons/math3/linear/SparseFieldVector.virtualSize:I (2, 1)
	57 aload_2 (2, 1)
	58 getfield (2, 1)
	59 org/apache/commons/math3/linear/SparseFieldVector.virtualSize:I (2, 1)
	61 if_icmpeq (2, 1)
	62 5 (2, 1)
	64 iconst_0 (2, 1)
	65 ireturn (2, 1)
	66 aload_0 (1, 1)
	67 getfield (1, 1)
	68 org/apache/commons/math3/linear/SparseFieldVector.entries:Lorg/apache/commons/math3/util/OpenIntToFieldHashMap; (1, 1)
	70 invokevirtual (1, 1)
	71 org/apache/commons/math3/util/OpenIntToFieldHashMap.iterator:()Lorg/apache/commons/math3/util/OpenIntToFieldHashMap$Iterator; (1, 1)
	73 astore_3 (1, 1)
	74 aload_3 (2, 3)
	75 invokevirtual (2, 3)
	76 org/apache/commons/math3/util/OpenIntToFieldHashMap$Iterator.hasNext:()Z (2, 3)
	78 ifeq (2, 3)
	79 34 (2, 3)
	81 aload_3 (2, 3)
	82 invokevirtual (2, 3)
	83 org/apache/commons/math3/util/OpenIntToFieldHashMap$Iterator.advance:()V (2, 3)
	85 aload_2 (2, 3)
	86 aload_3 (2, 3)
	87 invokevirtual (2, 3)
	88 org/apache/commons/math3/util/OpenIntToFieldHashMap$Iterator.key:()I (2, 3)
	90 invokevirtual (2, 3)
	91 org/apache/commons/math3/linear/SparseFieldVector.getEntry:(I)Lorg/apache/commons/math3/FieldElement; (2, 3)
	93 astore (2, 3)
	94 #4 (2, 3)
	95 aload (3, 1)
	96 #4 (3, 1)
	97 aload_3 (3, 1)
	98 invokevirtual (3, 1)
	99 org/apache/commons/math3/util/OpenIntToFieldHashMap$Iterator.value:()Lorg/apache/commons/math3/FieldElement; (3, 1)
	101 invokevirtual (3, 1)
	102 java/lang/Object.equals:(Ljava/lang/Object;)Z (3, 1)
	104 ifne (3, 1)
	105 5 (3, 1)
	107 iconst_0 (3, 1)
	108 ireturn (3, 1)
	109 goto (1, 1)
	110 -35 (1, 1)
	112 aload_2 (1, 1)
	113 invokespecial (1, 1)
	114 org/apache/commons/math3/linear/SparseFieldVector.getEntries:()Lorg/apache/commons/math3/util/OpenIntToFieldHashMap; (1, 1)
	116 invokevirtual (1, 1)
	117 org/apache/commons/math3/util/OpenIntToFieldHashMap.iterator:()Lorg/apache/commons/math3/util/OpenIntToFieldHashMap$Iterator; (1, 1)
	119 astore_3 (1, 1)
	120 aload_3 (2, 3)
	121 invokevirtual (2, 3)
	122 org/apache/commons/math3/util/OpenIntToFieldHashMap$Iterator.hasNext:()Z (2, 3)
	124 ifeq (2, 3)
	125 34 (2, 3)
	127 aload_3 (2, 3)
	128 invokevirtual (2, 3)
	129 org/apache/commons/math3/util/OpenIntToFieldHashMap$Iterator.advance:()V (2, 3)
	131 aload_3 (2, 3)
	132 invokevirtual (2, 3)
	133 org/apache/commons/math3/util/OpenIntToFieldHashMap$Iterator.value:()Lorg/apache/commons/math3/FieldElement; (2, 3)
	135 astore (2, 3)
	136 #4 (2, 3)
	137 aload (3, 1)
	138 #4 (3, 1)
	139 aload_0 (3, 1)
	140 aload_3 (3, 1)
	141 invokevirtual (3, 1)
	142 org/apache/commons/math3/util/OpenIntToFieldHashMap$Iterator.key:()I (3, 1)
	144 invokevirtual (3, 1)
	145 org/apache/commons/math3/linear/SparseFieldVector.getEntry:(I)Lorg/apache/commons/math3/FieldElement; (3, 1)
	147 invokevirtual (3, 1)
	148 java/lang/Object.equals:(Ljava/lang/Object;)Z (3, 1)
	150 ifne (3, 1)
	151 5 (3, 1)
	153 iconst_0 (3, 1)
	154 ireturn (3, 1)
	155 goto (1, 1)
	156 -35 (1, 1)
	158 iconst_1 (1, 1)
	159 ireturn (0, 1)

