Method: <init>
	0 aload_0 (0, 0)
	1 invokespecial (0, 0)
	4 aload_0 (0, 0)
	5 aload_1 (0, 0)
	6 putfield (0, 0)
	9 aload_0 (0, 0)
	10 aload_2 (0, 0)
	11 putfield (0, 0)
	14 aload_0 (0, 0)
	15 aload_3 (0, 0)
	16 putfield (0, 0)
	19 aload_0 (0, 0)
	20 new (0, 0)
	23 dup (0, 0)
	24 aload_3 (0, 0)
	25 invokevirtual (0, 0)
	28 invokespecial (0, 0)
	31 putfield (0, 0)
	34 aload_0 (0, 0)
	35 iload (0, 0)
	37 putfield (0, 0)
	40 aload_0 (0, 1)
	41 dload (0, 1)
	43 putfield (0, 1)
	46 aload_0 (0, 1)
	47 aload_2 (0, 1)
	48 ifnonnull (0, 1)
	51 aload_3 (0, 1)
	52 goto (0, 1)
	55 aload_2 (0, 1)
	56 aload_3 (0, 1)
	57 invokevirtual (0, 1)
	60 putfield (0, 1)
	63 aload_0 (0, 1)
	64 iconst_0 (0, 1)
	65 putfield (0, 1)
	68 aload_0 (0, 1)
	69 iload (0, 1)
	71 putfield (0, 1)
	74 aload_0 (0, 1)
	75 dload (0, 1)
	77 putfield (0, 1)
	80 return (0, 0)

Method: checkSymmetry
	0 aload_2 (0, 0)
	1 aload_2 (0, 0)
	2 invokevirtual (0, 0)
	5 dstore (0, 0)
	7 aload_1 (0, 0)
	8 aload_3 (0, 0)
	9 invokevirtual (0, 0)
	12 dstore (0, 0)
	14 dload (0, 0)
	16 getstatic (0, 0)
	19 dadd (0, 0)
	20 getstatic (0, 0)
	23 dmul (0, 0)
	24 dstore (0, 0)
	26 dload (1, 1)
	28 dload (1, 1)
	30 dsub (1, 1)
	31 invokestatic (1, 1)
	34 dload (1, 1)
	36 dcmpl (1, 1)
	37 ifle (1, 1)
	40 new (1, 1)
	43 dup (1, 1)
	44 invokespecial (1, 1)
	47 astore (1, 1)
	49 aload (1, 1)
	51 invokevirtual (1, 1)
	54 astore (1, 1)
	56 aload (1, 1)
	58 ldc (1, 1)
	60 aload_0 (1, 1)
	61 invokevirtual (1, 1)
	64 aload (1, 1)
	66 ldc (1, 1)
	68 aload_1 (1, 1)
	69 invokevirtual (1, 1)
	72 aload (1, 1)
	74 ldc (1, 1)
	76 aload_2 (1, 1)
	77 invokevirtual (1, 1)
	80 aload (1, 1)
	82 ldc (1, 1)
	84 dload (1, 1)
	86 invokestatic (1, 1)
	89 invokevirtual (1, 1)
	92 aload (1, 1)
	94 athrow (1, 1)
	95 return (0, 0)

Method: throwNPDLOException
	0 new (0, 0)
	3 dup (0, 0)
	4 invokespecial (0, 0)
	7 astore_2 (0, 0)
	8 aload_2 (0, 0)
	9 invokevirtual (0, 0)
	12 astore_3 (0, 0)
	13 aload_3 (0, 0)
	14 ldc (0, 0)
	16 aload_0 (0, 0)
	17 invokevirtual (0, 0)
	20 aload_3 (0, 0)
	21 ldc (0, 0)
	23 aload_1 (0, 0)
	24 invokevirtual (0, 0)
	27 aload_2 (0, 0)
	28 athrow (0, 0)

Method: daxpy
	0 aload_2 (0, 0)
	1 invokevirtual (0, 0)
	4 istore (0, 0)
	6 iconst_0 (1, 4)
	7 istore (1, 4)
	9 iload (1, 4)
	11 iload (1, 4)
	13 if_icmpge (1, 4)
	16 aload_3 (1, 4)
	17 iload (1, 4)
	19 dload_0 (1, 4)
	20 aload_2 (1, 4)
	21 iload (1, 4)
	23 invokevirtual (1, 4)
	26 dmul (1, 4)
	27 aload_3 (1, 4)
	28 iload (1, 4)
	30 invokevirtual (1, 4)
	33 dadd (1, 4)
	34 invokevirtual (1, 4)
	37 iinc (1, 4)
	40 goto (1, 4)
	43 return (0, 0)

Method: daxpbypz
	0 aload (0, 0)
	2 invokevirtual (0, 0)
	5 istore (0, 0)
	7 iconst_0 (1, 4)
	8 istore (1, 4)
	10 iload (1, 4)
	12 iload (1, 4)
	14 if_icmpge (1, 4)
	17 dload_0 (1, 4)
	18 aload_2 (1, 4)
	19 iload (1, 4)
	21 invokevirtual (1, 4)
	24 dmul (1, 4)
	25 dload_3 (1, 4)
	26 aload (1, 4)
	28 iload (1, 4)
	30 invokevirtual (1, 4)
	33 dmul (1, 4)
	34 dadd (1, 4)
	35 aload (1, 4)
	37 iload (1, 4)
	39 invokevirtual (1, 4)
	42 dadd (1, 4)
	43 dstore (1, 4)
	45 aload (1, 4)
	47 iload (1, 4)
	49 dload (1, 4)
	51 invokevirtual (1, 4)
	54 iinc (1, 4)
	57 goto (1, 4)
	60 return (0, 0)

Method: refineSolution
	0 aload_0 (0, 0)
	1 getfield (0, 0)
	4 invokevirtual (0, 0)
	7 istore_2 (0, 0)
	8 aload_0 (1, 1)
	9 getfield (1, 1)
	12 aload_0 (1, 1)
	13 getfield (1, 1)
	16 dcmpg (1, 1)
	17 ifge (1, 1)
	20 aload_0 (2, 1)
	21 getfield (2, 1)
	24 ifne (2, 1)
	27 aload_1 (2, 1)
	28 iconst_0 (2, 1)
	29 aload_0 (2, 1)
	30 getfield (2, 1)
	33 invokevirtual (2, 1)
	36 goto (2, 1)
	39 aload_0 (2, 2)
	40 getfield (2, 2)
	43 aload_0 (2, 2)
	44 getfield (2, 2)
	47 ddiv (2, 2)
	48 dstore_3 (2, 2)
	49 iconst_0 (3, 4)
	50 istore (3, 4)
	52 iload (3, 4)
	54 iload_2 (3, 4)
	55 if_icmpge (3, 4)
	58 aload_0 (3, 4)
	59 getfield (3, 4)
	62 iload (3, 4)
	64 invokevirtual (3, 4)
	67 dstore (3, 4)
	69 aload_0 (3, 4)
	70 getfield (3, 4)
	73 iload (3, 4)
	75 invokevirtual (3, 4)
	78 dstore (3, 4)
	80 aload_1 (3, 4)
	81 iload (3, 4)
	83 dload (3, 4)
	85 dload_3 (3, 4)
	86 dload (3, 4)
	88 dmul (3, 4)
	89 dadd (3, 4)
	90 invokevirtual (3, 4)
	93 iinc (3, 4)
	96 goto (3, 4)
	99 goto (1, 1)
	102 aload_0 (1, 2)
	103 getfield (1, 2)
	106 invokestatic (1, 2)
	109 dstore_3 (1, 2)
	110 aload_0 (1, 2)
	111 getfield (1, 2)
	114 dconst_0 (1, 2)
	115 dcmpl (1, 2)
	116 ifne (1, 2)
	119 dload_3 (1, 2)
	120 getstatic (1, 2)
	123 dmul (1, 2)
	124 goto (1, 2)
	127 aload_0 (1, 2)
	128 getfield (1, 2)
	131 dstore (1, 2)
	133 aload_0 (1, 2)
	134 getfield (1, 2)
	137 dload (1, 2)
	139 ddiv (1, 2)
	140 dstore (1, 2)
	142 aload_0 (1, 2)
	143 getfield (1, 2)
	146 aload_0 (1, 2)
	147 getfield (1, 2)
	150 dload (1, 2)
	152 dmul (1, 2)
	153 dadd (1, 2)
	154 aload_0 (1, 2)
	155 getfield (1, 2)
	158 ddiv (1, 2)
	159 dstore (1, 2)
	161 aload_0 (2, 1)
	162 getfield (2, 1)
	165 ifne (2, 1)
	168 iconst_0 (3, 4)
	169 istore (3, 4)
	171 iload (3, 4)
	173 iload_2 (3, 4)
	174 if_icmpge (3, 4)
	177 aload_0 (3, 4)
	178 getfield (3, 4)
	181 iload (3, 4)
	183 invokevirtual (3, 4)
	186 dstore (3, 4)
	188 aload_0 (3, 4)
	189 getfield (3, 4)
	192 iload (3, 4)
	194 invokevirtual (3, 4)
	197 dstore (3, 4)
	199 aload_1 (3, 4)
	200 iload (3, 4)
	202 dload (3, 4)
	204 dload (3, 4)
	206 dload (3, 4)
	208 dmul (3, 4)
	209 dadd (3, 4)
	210 invokevirtual (3, 4)
	213 iinc (3, 4)
	216 goto (3, 4)
	219 goto (3, 4)
	222 iconst_0 (3, 4)
	223 istore (3, 4)
	225 iload (3, 4)
	227 iload_2 (3, 4)
	228 if_icmpge (3, 4)
	231 aload_0 (3, 4)
	232 getfield (3, 4)
	235 iload (3, 4)
	237 invokevirtual (3, 4)
	240 dstore (3, 4)
	242 aload_0 (3, 4)
	243 getfield (3, 4)
	246 iload (3, 4)
	248 invokevirtual (3, 4)
	251 dstore (3, 4)
	253 aload_0 (3, 4)
	254 getfield (3, 4)
	257 iload (3, 4)
	259 invokevirtual (3, 4)
	262 dstore (3, 4)
	264 aload_1 (3, 4)
	265 iload (3, 4)
	267 dload (3, 4)
	269 dload (3, 4)
	271 dload (3, 4)
	273 dmul (3, 4)
	274 dadd (3, 4)
	275 dload (3, 4)
	277 dload (3, 4)
	279 dmul (3, 4)
	280 dadd (3, 4)
	281 invokevirtual (3, 4)
	284 iinc (3, 4)
	287 goto (3, 4)
	290 return (0, 1)

Method: init
	0 aload_0 (0, 0)
	1 getfield (0, 0)
	4 dconst_0 (0, 0)
	5 invokevirtual (0, 0)
	8 aload_0 (0, 1)
	9 aload_0 (0, 1)
	10 getfield (0, 1)
	13 invokevirtual (0, 1)
	16 putfield (0, 1)
	19 aload_0 (0, 1)
	20 aload_0 (0, 1)
	21 getfield (0, 1)
	24 ifnonnull (0, 1)
	27 aload_0 (0, 1)
	28 getfield (0, 1)
	31 invokevirtual (0, 1)
	34 goto (0, 1)
	37 aload_0 (0, 1)
	38 getfield (0, 1)
	41 aload_0 (0, 1)
	42 getfield (0, 1)
	45 invokevirtual (0, 1)
	48 putfield (0, 1)
	51 aload_0 (1, 1)
	52 getfield (1, 1)
	55 ifnull (1, 1)
	58 aload_0 (1, 1)
	59 getfield (1, 1)
	62 ifeq (1, 1)
	65 aload_0 (1, 1)
	66 getfield (1, 1)
	69 aload_0 (1, 1)
	70 getfield (1, 1)
	73 aload_0 (1, 1)
	74 getfield (1, 1)
	77 aload_0 (1, 1)
	78 getfield (1, 1)
	81 aload_0 (1, 1)
	82 getfield (1, 1)
	85 invokevirtual (1, 1)
	88 invokestatic (1, 1)
	91 aload_0 (0, 1)
	92 aload_0 (0, 1)
	93 getfield (0, 1)
	96 aload_0 (0, 1)
	97 getfield (0, 1)
	100 invokevirtual (0, 1)
	103 putfield (0, 1)
	106 aload_0 (1, 1)
	107 getfield (1, 1)
	110 dconst_0 (1, 1)
	111 dcmpg (1, 1)
	112 ifge (1, 1)
	115 aload_0 (1, 1)
	116 getfield (1, 1)
	119 aload_0 (1, 1)
	120 getfield (1, 1)
	123 invokestatic (1, 1)
	126 aload_0 (1, 1)
	127 getfield (1, 1)
	130 dconst_0 (1, 1)
	131 dcmpl (1, 1)
	132 ifne (1, 1)
	135 aload_0 (1, 1)
	136 iconst_1 (1, 1)
	137 putfield (1, 1)
	140 return (1, 1)
	141 aload_0 (0, 1)
	142 iconst_0 (0, 1)
	143 putfield (0, 1)
	146 aload_0 (0, 1)
	147 aload_0 (0, 1)
	148 getfield (0, 1)
	151 invokestatic (0, 1)
	154 putfield (0, 1)
	157 aload_0 (0, 1)
	158 getfield (0, 1)
	161 dconst_1 (0, 1)
	162 aload_0 (0, 1)
	163 getfield (0, 1)
	166 ddiv (0, 1)
	167 invokevirtual (0, 1)
	170 astore_1 (0, 1)
	171 aload_0 (0, 1)
	172 aload_0 (0, 1)
	173 getfield (0, 1)
	176 aload_1 (0, 1)
	177 invokevirtual (0, 1)
	180 putfield (0, 1)
	183 aload_0 (1, 1)
	184 getfield (1, 1)
	187 ifeq (1, 1)
	190 aload_0 (1, 1)
	191 getfield (1, 1)
	194 aload_1 (1, 1)
	195 aload_0 (1, 1)
	196 getfield (1, 1)
	199 aload_0 (1, 1)
	200 getfield (1, 1)
	203 aload_0 (1, 1)
	204 getfield (1, 1)
	207 invokevirtual (1, 1)
	210 invokestatic (1, 1)
	213 aload_0 (0, 1)
	214 getfield (0, 1)
	217 dneg (0, 1)
	218 aload_1 (0, 1)
	219 aload_0 (0, 1)
	220 getfield (0, 1)
	223 invokestatic (0, 1)
	226 aload_1 (0, 1)
	227 aload_0 (0, 1)
	228 getfield (0, 1)
	231 invokevirtual (0, 1)
	234 dstore_2 (0, 1)
	235 dload_2 (0, 1)
	236 dneg (0, 1)
	237 aload_0 (0, 1)
	238 getfield (0, 1)
	241 ddiv (0, 1)
	242 aload_0 (0, 1)
	243 getfield (0, 1)
	246 aload_0 (0, 1)
	247 getfield (0, 1)
	250 invokestatic (0, 1)
	253 aload_1 (0, 1)
	254 aload_0 (0, 1)
	255 getfield (0, 1)
	258 invokevirtual (0, 1)
	261 dstore (0, 1)
	263 aload_1 (0, 1)
	264 aload_1 (0, 1)
	265 invokevirtual (0, 1)
	268 dstore (0, 1)
	270 dload (0, 1)
	272 dneg (0, 1)
	273 dload (0, 1)
	275 ddiv (0, 1)
	276 aload_1 (0, 1)
	277 aload_0 (0, 1)
	278 getfield (0, 1)
	281 invokestatic (0, 1)
	284 aload_0 (0, 1)
	285 aload_0 (0, 1)
	286 getfield (0, 1)
	289 invokevirtual (0, 1)
	292 putfield (0, 1)
	295 aload_0 (1, 1)
	296 getfield (1, 1)
	299 ifnull (1, 1)
	302 aload_0 (1, 1)
	303 aload_0 (1, 1)
	304 getfield (1, 1)
	307 aload_0 (1, 1)
	308 getfield (1, 1)
	311 invokevirtual (1, 1)
	314 putfield (1, 1)
	317 aload_0 (0, 1)
	318 aload_0 (0, 1)
	319 getfield (0, 1)
	322 putfield (0, 1)
	325 aload_0 (0, 1)
	326 aload_0 (0, 1)
	327 getfield (0, 1)
	330 aload_0 (0, 1)
	331 getfield (0, 1)
	334 invokevirtual (0, 1)
	337 putfield (0, 1)
	340 aload_0 (1, 1)
	341 getfield (1, 1)
	344 dconst_0 (1, 1)
	345 dcmpg (1, 1)
	346 ifge (1, 1)
	349 aload_0 (1, 1)
	350 getfield (1, 1)
	353 aload_0 (1, 1)
	354 getfield (1, 1)
	357 invokestatic (1, 1)
	360 aload_0 (0, 1)
	361 aload_0 (0, 1)
	362 getfield (0, 1)
	365 invokestatic (0, 1)
	368 putfield (0, 1)
	371 aload_0 (0, 1)
	372 aload_0 (0, 1)
	373 getfield (0, 1)
	376 putfield (0, 1)
	379 aload_0 (0, 1)
	380 dload_2 (0, 1)
	381 putfield (0, 1)
	384 aload_0 (0, 1)
	385 aload_0 (0, 1)
	386 getfield (0, 1)
	389 putfield (0, 1)
	392 aload_0 (0, 1)
	393 aload_0 (0, 1)
	394 getfield (0, 1)
	397 putfield (0, 1)
	400 aload_0 (0, 1)
	401 dconst_0 (0, 1)
	402 putfield (0, 1)
	405 aload_0 (0, 1)
	406 dconst_0 (0, 1)
	407 putfield (0, 1)
	410 aload_0 (0, 1)
	411 dconst_1 (0, 1)
	412 putfield (0, 1)
	415 aload_0 (0, 1)
	416 dload_2 (0, 1)
	417 dload_2 (0, 1)
	418 dmul (0, 1)
	419 aload_0 (0, 1)
	420 getfield (0, 1)
	423 aload_0 (0, 1)
	424 getfield (0, 1)
	427 dmul (0, 1)
	428 dadd (0, 1)
	429 putfield (0, 1)
	432 aload_0 (0, 1)
	433 dconst_0 (0, 1)
	434 putfield (0, 1)
	437 aload_0 (0, 1)
	438 dload_2 (0, 1)
	439 invokestatic (0, 1)
	442 getstatic (0, 1)
	445 dadd (0, 1)
	446 putfield (0, 1)
	449 aload_0 (0, 1)
	450 aload_0 (0, 1)
	451 getfield (0, 1)
	454 putfield (0, 1)
	457 aload_0 (1, 1)
	458 getfield (1, 1)
	461 ifeq (1, 1)
	464 aload_0 (1, 1)
	465 new (1, 1)
	468 dup (1, 1)
	469 aload_0 (1, 1)
	470 getfield (1, 1)
	473 invokevirtual (1, 1)
	476 invokespecial (1, 1)
	479 putfield (1, 1)
	482 aload_0 (1, 1)
	483 getfield (1, 1)
	486 dconst_0 (1, 1)
	487 invokevirtual (1, 1)
	490 goto (1, 1)
	493 aload_0 (1, 2)
	494 aload_1 (1, 2)
	495 putfield (1, 2)
	498 aload_0 (0, 1)
	499 invokespecial (0, 1)
	502 return (0, 1)

Method: update
	0 aload_0 (0, 0)
	1 getfield (0, 0)
	4 dconst_1 (0, 0)
	5 aload_0 (0, 0)
	6 getfield (0, 0)
	9 ddiv (0, 0)
	10 invokevirtual (0, 0)
	13 astore_1 (0, 0)
	14 aload_0 (0, 0)
	15 aload_0 (0, 0)
	16 getfield (0, 0)
	19 aload_1 (0, 0)
	20 invokevirtual (0, 0)
	23 putfield (0, 0)
	26 aload_0 (0, 1)
	27 getfield (0, 1)
	30 dneg (0, 1)
	31 aload_1 (0, 1)
	32 aload_0 (0, 1)
	33 getfield (0, 1)
	36 dneg (0, 1)
	37 aload_0 (0, 1)
	38 getfield (0, 1)
	41 ddiv (0, 1)
	42 aload_0 (0, 1)
	43 getfield (0, 1)
	46 aload_0 (0, 1)
	47 getfield (0, 1)
	50 invokestatic (0, 1)
	53 aload_1 (0, 1)
	54 aload_0 (0, 1)
	55 getfield (0, 1)
	58 invokevirtual (0, 1)
	61 dstore_2 (0, 1)
	62 dload_2 (0, 1)
	63 dneg (0, 1)
	64 aload_0 (0, 1)
	65 getfield (0, 1)
	68 ddiv (0, 1)
	69 aload_0 (0, 1)
	70 getfield (0, 1)
	73 aload_0 (0, 1)
	74 getfield (0, 1)
	77 invokestatic (0, 1)
	80 aload_0 (0, 1)
	81 aload_0 (0, 1)
	82 getfield (0, 1)
	85 putfield (0, 1)
	88 aload_0 (0, 1)
	89 aload_0 (0, 1)
	90 getfield (0, 1)
	93 putfield (0, 1)
	96 aload_0 (1, 1)
	97 getfield (1, 1)
	100 ifnull (1, 1)
	103 aload_0 (1, 1)
	104 aload_0 (1, 1)
	105 getfield (1, 1)
	108 aload_0 (1, 1)
	109 getfield (1, 1)
	112 invokevirtual (1, 1)
	115 putfield (1, 1)
	118 aload_0 (0, 1)
	119 aload_0 (0, 1)
	120 getfield (0, 1)
	123 putfield (0, 1)
	126 aload_0 (0, 1)
	127 aload_0 (0, 1)
	128 getfield (0, 1)
	131 aload_0 (0, 1)
	132 getfield (0, 1)
	135 invokevirtual (0, 1)
	138 putfield (0, 1)
	141 aload_0 (1, 1)
	142 getfield (1, 1)
	145 dconst_0 (1, 1)
	146 dcmpg (1, 1)
	147 ifge (1, 1)
	150 aload_0 (1, 1)
	151 getfield (1, 1)
	154 aload_0 (1, 1)
	155 getfield (1, 1)
	158 invokestatic (1, 1)
	161 aload_0 (0, 1)
	162 aload_0 (0, 1)
	163 getfield (0, 1)
	166 invokestatic (0, 1)
	169 putfield (0, 1)
	172 aload_0 (0, 1)
	173 dup (0, 1)
	174 getfield (0, 1)
	177 dload_2 (0, 1)
	178 dload_2 (0, 1)
	179 dmul (0, 1)
	180 aload_0 (0, 1)
	181 getfield (0, 1)
	184 aload_0 (0, 1)
	185 getfield (0, 1)
	188 dmul (0, 1)
	189 dadd (0, 1)
	190 aload_0 (0, 1)
	191 getfield (0, 1)
	194 aload_0 (0, 1)
	195 getfield (0, 1)
	198 dmul (0, 1)
	199 dadd (0, 1)
	200 dadd (0, 1)
	201 putfield (0, 1)
	204 aload_0 (0, 4)
	205 getfield (0, 4)
	208 aload_0 (0, 4)
	209 getfield (0, 4)
	212 dmul (0, 4)
	213 aload_0 (0, 4)
	214 getfield (0, 4)
	217 aload_0 (0, 4)
	218 getfield (0, 4)
	221 dmul (0, 4)
	222 dadd (0, 4)
	223 invokestatic (0, 4)
	226 dstore (0, 4)
	228 aload_0 (0, 4)
	229 getfield (0, 4)
	232 dload (0, 4)
	234 ddiv (0, 4)
	235 dstore (0, 4)
	237 aload_0 (0, 4)
	238 getfield (0, 4)
	241 dload (0, 4)
	243 ddiv (0, 4)
	244 dstore (0, 4)
	246 dload (0, 4)
	248 aload_0 (0, 4)
	249 getfield (0, 4)
	252 dmul (0, 4)
	253 dload (0, 4)
	255 dload_2 (0, 4)
	256 dmul (0, 4)
	257 dadd (0, 4)
	258 dstore (0, 4)
	260 aload_0 (0, 4)
	261 dload (0, 4)
	263 aload_0 (0, 4)
	264 getfield (0, 4)
	267 dmul (0, 4)
	268 dload (0, 4)
	270 dload_2 (0, 4)
	271 dmul (0, 4)
	272 dsub (0, 4)
	273 putfield (0, 4)
	276 dload (0, 4)
	278 aload_0 (0, 4)
	279 getfield (0, 4)
	282 dmul (0, 4)
	283 dstore (0, 4)
	285 aload_0 (0, 4)
	286 dload (0, 4)
	288 dneg (0, 4)
	289 aload_0 (0, 4)
	290 getfield (0, 4)
	293 dmul (0, 4)
	294 putfield (0, 4)
	297 aload_0 (0, 4)
	298 getfield (0, 4)
	301 dload (0, 4)
	303 ddiv (0, 4)
	304 dstore (0, 4)
	306 dload (0, 4)
	308 dload (0, 4)
	310 dmul (0, 4)
	311 dstore (0, 4)
	313 dload (0, 4)
	315 dload (0, 4)
	317 dmul (0, 4)
	318 dstore (0, 4)
	320 aload_0 (0, 4)
	321 getfield (0, 4)
	324 invokevirtual (0, 4)
	327 istore (0, 4)
	329 iconst_0 (1, 4)
	330 istore (1, 4)
	332 iload (1, 4)
	334 iload (1, 4)
	336 if_icmpge (1, 4)
	339 aload_0 (1, 4)
	340 getfield (1, 4)
	343 iload (1, 4)
	345 invokevirtual (1, 4)
	348 dstore (1, 4)
	350 aload_1 (1, 4)
	351 iload (1, 4)
	353 invokevirtual (1, 4)
	356 dstore (1, 4)
	358 aload_0 (1, 4)
	359 getfield (1, 4)
	362 iload (1, 4)
	364 invokevirtual (1, 4)
	367 dstore (1, 4)
	369 aload_0 (1, 4)
	370 getfield (1, 4)
	373 iload (1, 4)
	375 dload (1, 4)
	377 dload (1, 4)
	379 dload (1, 4)
	381 dmul (1, 4)
	382 dadd (1, 4)
	383 dload (1, 4)
	385 dload (1, 4)
	387 dmul (1, 4)
	388 dadd (1, 4)
	389 invokevirtual (1, 4)
	392 aload_0 (1, 4)
	393 getfield (1, 4)
	396 iload (1, 4)
	398 dload (1, 4)
	400 dload (1, 4)
	402 dmul (1, 4)
	403 dload (1, 4)
	405 dload (1, 4)
	407 dmul (1, 4)
	408 dsub (1, 4)
	409 invokevirtual (1, 4)
	412 iinc (1, 4)
	415 goto (1, 4)
	418 aload_0 (0, 4)
	419 dup (0, 4)
	420 getfield (0, 4)
	423 aload_0 (0, 4)
	424 getfield (0, 4)
	427 dload (0, 4)
	429 dmul (0, 4)
	430 dload (0, 4)
	432 dmul (0, 4)
	433 dadd (0, 4)
	434 putfield (0, 4)
	437 aload_0 (0, 4)
	438 dup (0, 4)
	439 getfield (0, 4)
	442 dload (0, 4)
	444 dmul (0, 4)
	445 putfield (0, 4)
	448 aload_0 (0, 4)
	449 aload_0 (0, 4)
	450 getfield (0, 4)
	453 dload (0, 4)
	455 invokestatic (0, 4)
	458 putfield (0, 4)
	461 aload_0 (0, 4)
	462 aload_0 (0, 4)
	463 getfield (0, 4)
	466 dload (0, 4)
	468 invokestatic (0, 4)
	471 putfield (0, 4)
	474 aload_0 (0, 4)
	475 dup (0, 4)
	476 getfield (0, 4)
	479 dload (0, 4)
	481 dload (0, 4)
	483 dmul (0, 4)
	484 dadd (0, 4)
	485 putfield (0, 4)
	488 aload_0 (0, 4)
	489 aload_0 (0, 4)
	490 getfield (0, 4)
	493 dload (0, 4)
	495 dload (0, 4)
	497 dmul (0, 4)
	498 dsub (0, 4)
	499 putfield (0, 4)
	502 aload_0 (0, 4)
	503 dload (0, 4)
	505 dneg (0, 4)
	506 dload (0, 4)
	508 dmul (0, 4)
	509 putfield (0, 4)
	512 aload_0 (0, 4)
	513 invokespecial (0, 4)
	516 return (0, 4)

Method: updateNorms
	0 aload_0 (0, 0)
	1 getfield (0, 0)
	4 invokestatic (0, 0)
	7 dstore_1 (0, 0)
	8 aload_0 (0, 0)
	9 getfield (0, 0)
	12 invokestatic (0, 0)
	15 dstore_3 (0, 0)
	16 dload_1 (0, 0)
	17 getstatic (0, 0)
	20 dmul (0, 0)
	21 dstore (0, 0)
	23 dload_1 (0, 0)
	24 dload_3 (0, 0)
	25 dmul (0, 0)
	26 getstatic (0, 0)
	29 dmul (0, 0)
	30 dstore (0, 0)
	32 dload_1 (0, 0)
	33 dload_3 (0, 0)
	34 dmul (0, 0)
	35 aload_0 (0, 0)
	36 getfield (0, 0)
	39 dmul (0, 0)
	40 dstore (0, 0)
	42 aload_0 (0, 0)
	43 getfield (0, 0)
	46 dconst_0 (0, 0)
	47 dcmpl (0, 0)
	48 ifne (0, 0)
	51 dload (0, 0)
	53 goto (0, 0)
	56 aload_0 (0, 0)
	57 getfield (0, 0)
	60 dstore (0, 0)
	62 aload_0 (0, 0)
	63 aload_0 (0, 0)
	64 getfield (0, 0)
	67 aload_0 (0, 0)
	68 getfield (0, 0)
	71 dmul (0, 0)
	72 aload_0 (0, 0)
	73 getfield (0, 0)
	76 aload_0 (0, 0)
	77 getfield (0, 0)
	80 dmul (0, 0)
	81 dadd (0, 0)
	82 invokestatic (0, 0)
	85 putfield (0, 0)
	88 aload_0 (0, 0)
	89 getfield (0, 0)
	92 aload_0 (0, 0)
	93 getfield (0, 0)
	96 dmul (0, 0)
	97 dstore (0, 0)
	99 aload_0 (0, 0)
	100 dload (0, 0)
	102 aload_0 (0, 0)
	103 getfield (0, 0)
	106 dmul (0, 0)
	107 dload (0, 0)
	109 invokestatic (0, 0)
	112 ddiv (0, 0)
	113 putfield (0, 0)
	116 aload_0 (1, 1)
	117 getfield (1, 1)
	120 aload_0 (1, 1)
	121 getfield (1, 1)
	124 dcmpg (1, 1)
	125 ifgt (1, 1)
	128 aload_0 (1, 1)
	129 getfield (1, 1)
	132 aload_0 (1, 1)
	133 getfield (1, 1)
	136 ddiv (1, 1)
	137 dstore (1, 1)
	139 goto (1, 1)
	142 aload_0 (1, 2)
	143 getfield (1, 2)
	146 aload_0 (1, 2)
	147 getfield (1, 2)
	150 dload (1, 2)
	152 invokestatic (1, 2)
	155 invokestatic (1, 2)
	158 ddiv (1, 2)
	159 dstore (1, 2)
	161 dload (1, 1)
	163 getstatic (1, 1)
	166 dmul (1, 1)
	167 ldc2_w (1, 1)
	170 dcmpl (1, 1)
	171 iflt (1, 1)
	174 new (1, 1)
	177 dup (1, 1)
	178 dload (1, 1)
	180 invokespecial (1, 1)
	183 athrow (1, 1)
	184 aload_0 (1, 1)
	185 getfield (1, 1)
	188 dload (1, 1)
	190 dcmpg (1, 1)
	191 ifgt (1, 1)
	194 new (1, 1)
	197 dup (1, 1)
	198 invokespecial (1, 1)
	201 athrow (1, 1)
	202 aload_0 (0, 1)
	203 aload_0 (0, 1)
	204 getfield (0, 1)
	207 aload_0 (0, 1)
	208 getfield (0, 1)
	211 invokestatic (0, 1)
	214 putfield (0, 1)
	217 aload_0 (0, 1)
	218 aload_0 (0, 1)
	219 getfield (0, 1)
	222 dload (0, 1)
	224 dcmpg (0, 1)
	225 ifle (0, 1)
	228 aload_0 (0, 1)
	229 getfield (0, 1)
	232 dload (0, 1)
	234 dcmpg (0, 1)
	235 ifgt (0, 1)
	238 iconst_1 (0, 1)
	239 goto (0, 1)
	242 iconst_0 (0, 1)
	243 putfield (0, 1)
	246 return (0, 1)

Method: hasConverged
	0 aload_0 (0, 0)
	1 getfield (0, 0)
	4 ireturn (0, 0)

Method: bEqualsNullVector
	0 aload_0 (0, 0)
	1 getfield (0, 0)
	4 ireturn (0, 0)

Method: betaEqualsZero
	0 aload_0 (0, 0)
	1 getfield (0, 0)
	4 getstatic (0, 0)
	7 dcmpg (0, 0)
	8 ifge (0, 0)
	11 iconst_1 (0, 0)
	12 goto (0, 0)
	15 iconst_0 (0, 0)
	16 ireturn (0, 0)

Method: getNormOfResidual
	0 aload_0 (0, 0)
	1 getfield (0, 0)
	4 dreturn (0, 0)

Method: <clinit>
	0 dconst_1 (0, 0)
	1 invokestatic (0, 0)
	4 putstatic (0, 0)
	7 getstatic (0, 0)
	10 invokestatic (0, 0)
	13 putstatic (0, 0)
	16 return (0, 0)

