Method: <init>
	0 aload_0 (0, 0)
	1 aload_1 (0, 0)
	2 invokespecial (0, 0)
	3 org/apache/commons/math3/linear/PreconditionedIterativeLinearSolver.<init>:(Lorg/apache/commons/math3/util/IterationManager;)V (0, 0)
	5 aload_0 (0, 0)
	6 dload_2 (0, 0)
	7 putfield (0, 0)
	8 org/apache/commons/math3/linear/SymmLQ.delta:D (0, 0)
	10 aload_0 (0, 0)
	11 iload (0, 0)
	12 #4 (0, 0)
	13 putfield (0, 0)
	14 org/apache/commons/math3/linear/SymmLQ.check:Z (0, 0)
	16 return (0, 0)

Method: getCheck
	0 aload_0 (0, 0)
	1 getfield (0, 0)
	2 org/apache/commons/math3/linear/SymmLQ.check:Z (0, 0)
	4 ireturn (0, 0)

Method: solve
	0 aload_3 (0, 0)
	1 invokestatic (0, 0)
	2 org/apache/commons/math3/util/MathUtils.checkNotNull:(Ljava/lang/Object;)V (0, 0)
	4 aload_0 (0, 0)
	5 aload_1 (0, 0)
	6 aconst_null (0, 0)
	7 aload_2 (0, 0)
	8 aload_3 (0, 0)
	9 invokevirtual (0, 0)
	10 org/apache/commons/math3/linear/RealVector.copy:()Lorg/apache/commons/math3/linear/RealVector; (0, 0)
	12 iconst_0 (0, 0)
	13 dconst_0 (0, 0)
	14 invokevirtual (0, 0)
	15 org/apache/commons/math3/linear/SymmLQ.solveInPlace:(Lorg/apache/commons/math3/linear/RealLinearOperator;Lorg/apache/commons/math3/linear/RealLinearOperator;Lorg/apache/commons/math3/linear/RealVector;Lorg/apache/commons/math3/linear/RealVector;ZD)Lorg/apache/commons/math3/linear/RealVector; (0, 0)
	17 areturn (0, 0)

Method: solveInPlace
	0 aload_0 (0, 0)
	1 aload_1 (0, 0)
	2 aconst_null (0, 0)
	3 aload_2 (0, 0)
	4 aload_3 (0, 0)
	5 iconst_0 (0, 0)
	6 dconst_0 (0, 0)
	7 invokevirtual (0, 0)
	8 org/apache/commons/math3/linear/SymmLQ.solveInPlace:(Lorg/apache/commons/math3/linear/RealLinearOperator;Lorg/apache/commons/math3/linear/RealLinearOperator;Lorg/apache/commons/math3/linear/RealVector;Lorg/apache/commons/math3/linear/RealVector;ZD)Lorg/apache/commons/math3/linear/RealVector; (0, 0)
	10 areturn (0, 0)

