Method: <init>
	0 aload_0 (1, 4)
	1 invokespecial (1, 4)
	2 java/lang/Object.<init>:()V (1, 4)
	4 aload_1 (2, 1)
	5 invokeinterface (2, 1)
	6 org/apache/commons/math3/linear/RealMatrix.org/apache/commons/math3/linear/NonSquareMatrixException (2, 1)
	8 0 (2, 1)
	10 ifne (2, 1)
	11 23 (2, 1)
	13 new (2, 1)
	14 org/apache/commons/math3/linear/NonSquareMatrixException (2, 1)
	16 dup (2, 1)
	17 aload_1 (2, 1)
	18 invokeinterface (2, 1)
	19 org/apache/commons/math3/linear/RealMatrix.getColumnDimension:()I (2, 1)
	21 0 (2, 1)
	23 aload_1 (2, 1)
	24 invokeinterface (2, 1)
	25 org/apache/commons/math3/linear/RealMatrix.<init>:(II)V (2, 1)
	27 0 (2, 1)
	29 invokespecial (2, 1)
	30 org/apache/commons/math3/linear/NonSquareMatrixException.<init>:(II)V (2, 1)
	32 athrow (2, 1)
	33 aload_1 (1, 4)
	34 invokeinterface (1, 4)
	35 org/apache/commons/math3/linear/RealMatrix.getColumnDimension:()I (1, 4)
	37 0 (1, 4)
	39 istore_2 (1, 4)
	40 aload_0 (1, 4)
	41 aload_1 (1, 4)
	42 invokeinterface (1, 4)
	43 org/apache/commons/math3/linear/RealMatrix.householderVectors:[[D (1, 4)
	45 0 (1, 4)
	47 putfield (1, 4)
	48 org/apache/commons/math3/linear/TriDiagonalTransformer.householderVectors:[[D (1, 4)
	50 aload_0 (1, 4)
	51 iload_2 (1, 4)
	52 newarray (1, 4)
	53 7 (1, 4)
	54 putfield (1, 4)
	55 org/apache/commons/math3/linear/TriDiagonalTransformer.main:[D (1, 4)
	57 aload_0 (1, 4)
	58 iload_2 (1, 4)
	59 iconst_1 (1, 4)
	60 isub (1, 4)
	61 newarray (1, 4)
	62 7 (1, 4)
	63 putfield (1, 4)
	64 org/apache/commons/math3/linear/TriDiagonalTransformer.secondary:[D (1, 4)
	66 aload_0 (1, 4)
	67 aconst_null (1, 4)
	68 putfield (1, 4)
	69 org/apache/commons/math3/linear/TriDiagonalTransformer.cachedQ:Lorg/apache/commons/math3/linear/RealMatrix; (1, 4)
	71 aload_0 (1, 4)
	72 aconst_null (1, 4)
	73 putfield (1, 4)
	74 org/apache/commons/math3/linear/TriDiagonalTransformer.cachedQt:Lorg/apache/commons/math3/linear/RealMatrix; (1, 4)
	76 aload_0 (1, 4)
	77 aconst_null (1, 4)
	78 putfield (1, 4)
	79 org/apache/commons/math3/linear/TriDiagonalTransformer.cachedT:Lorg/apache/commons/math3/linear/RealMatrix; (1, 4)
	81 aload_0 (1, 4)
	82 invokespecial (1, 4)
	83 org/apache/commons/math3/linear/TriDiagonalTransformer.transform:()V (1, 4)
	85 return (0, 0)

Method: getQ
	0 aload_0 (1, 1)
	1 getfield (1, 1)
	2 org/apache/commons/math3/linear/TriDiagonalTransformer.cachedQ:Lorg/apache/commons/math3/linear/RealMatrix; (1, 1)
	4 ifnonnull (1, 1)
	5 16 (1, 1)
	7 aload_0 (1, 1)
	8 aload_0 (1, 1)
	9 invokevirtual (1, 1)
	10 org/apache/commons/math3/linear/TriDiagonalTransformer.getQT:()Lorg/apache/commons/math3/linear/RealMatrix; (1, 1)
	12 invokeinterface (1, 1)
	13 org/apache/commons/math3/linear/RealMatrix.org/apache/commons/math3/linear/MatrixUtils (1, 1)
	15 0 (1, 1)
	17 putfield (1, 1)
	18 org/apache/commons/math3/linear/TriDiagonalTransformer.cachedQ:Lorg/apache/commons/math3/linear/RealMatrix; (1, 1)
	20 aload_0 (0, 0)
	21 getfield (0, 0)
	22 org/apache/commons/math3/linear/TriDiagonalTransformer.cachedQ:Lorg/apache/commons/math3/linear/RealMatrix; (0, 0)
	24 areturn (0, 0)

Method: getQT
	0 aload_0 (1, 1)
	1 getfield (1, 1)
	2 org/apache/commons/math3/linear/TriDiagonalTransformer.cachedQt:Lorg/apache/commons/math3/linear/RealMatrix; (1, 1)
	4 ifnonnull (1, 1)
	5 254 (1, 1)
	7 aload_0 (1, 1)
	8 getfield (1, 1)
	9 org/apache/commons/math3/linear/TriDiagonalTransformer.householderVectors:[[D (1, 1)
	11 arraylength (1, 1)
	12 istore_1 (1, 1)
	13 iload_1 (1, 1)
	14 iload_1 (1, 1)
	15 multianewarray (1, 1)
	16 [[D (1, 1)
	18 77 (1, 1)
	19 astore_2 (1, 1)
	20 iload_1 (2, 4)
	21 iconst_1 (2, 4)
	22 isub (2, 4)
	23 istore_3 (2, 4)
	24 iload_3 (2, 4)
	25 iconst_1 (2, 4)
	26 if_icmplt (2, 4)
	27 218 (2, 4)
	29 aload_0 (2, 4)
	30 getfield (2, 4)
	31 org/apache/commons/math3/linear/TriDiagonalTransformer.householderVectors:[[D (2, 4)
	33 iload_3 (2, 4)
	34 iconst_1 (2, 4)
	35 isub (2, 4)
	36 aaload (2, 4)
	37 astore (2, 4)
	38 #4 (2, 4)
	39 aload_2 (2, 4)
	40 iload_3 (2, 4)
	41 aaload (2, 4)
	42 iload_3 (2, 4)
	43 dconst_1 (2, 4)
	44 dastore (2, 4)
	45 aload (3, 1)
	46 #4 (3, 1)
	47 iload_3 (3, 1)
	48 daload (3, 1)
	49 dconst_0 (3, 1)
	50 dcmpl (3, 1)
	51 ifeq (3, 1)
	52 187 (3, 1)
	54 dconst_1 (3, 1)
	55 aload_0 (3, 1)
	56 getfield (3, 1)
	57 org/apache/commons/math3/linear/TriDiagonalTransformer.secondary:[D (3, 1)
	59 iload_3 (3, 1)
	60 iconst_1 (3, 1)
	61 isub (3, 1)
	62 daload (3, 1)
	63 aload (3, 1)
	64 #4 (3, 1)
	65 iload_3 (3, 1)
	66 daload (3, 1)
	67 dmul (3, 1)
	68 ddiv (3, 1)
	69 dstore (3, 1)
	70 #5 (3, 1)
	71 dconst_1 (3, 1)
	72 aload_0 (3, 1)
	73 getfield (3, 1)
	74 org/apache/commons/math3/linear/TriDiagonalTransformer.secondary:[D (3, 1)
	76 iload_3 (3, 1)
	77 iconst_1 (3, 1)
	78 isub (3, 1)
	79 daload (3, 1)
	80 ddiv (3, 1)
	81 dstore (3, 1)
	82 #7 (3, 1)
	83 aload_2 (3, 1)
	84 iload_3 (3, 1)
	85 aaload (3, 1)
	86 iload_3 (3, 1)
	87 dconst_1 (3, 1)
	88 dload (3, 1)
	89 #7 (3, 1)
	90 aload (3, 1)
	91 #4 (3, 1)
	92 iload_3 (3, 1)
	93 daload (3, 1)
	94 dmul (3, 1)
	95 dadd (3, 1)
	96 dastore (3, 1)
	97 iload_3 (4, 4)
	98 iconst_1 (4, 4)
	99 iadd (4, 4)
	100 istore (4, 4)
	101 #9 (4, 4)
	102 iload (4, 4)
	103 #9 (4, 4)
	104 iload_1 (4, 4)
	105 if_icmpge (4, 4)
	106 23 (4, 4)
	108 aload_2 (4, 4)
	109 iload_3 (4, 4)
	110 aaload (4, 4)
	111 iload (4, 4)
	112 #9 (4, 4)
	113 dload (4, 4)
	114 #7 (4, 4)
	115 aload (4, 4)
	116 #4 (4, 4)
	117 iload (4, 4)
	118 #9 (4, 4)
	119 daload (4, 4)
	120 dmul (4, 4)
	121 dastore (4, 4)
	122 iinc (4, 4)
	123 #9 (4, 4)
	124 -89 (4, 4)
	125 goto (4, 4)
	126 -23 (4, 4)
	128 iload_3 (4, 4)
	129 iconst_1 (4, 4)
	130 iadd (4, 4)
	131 istore (4, 4)
	132 #9 (4, 4)
	133 iload (4, 4)
	134 #9 (4, 4)
	135 iload_1 (4, 4)
	136 if_icmpge (4, 4)
	137 102 (4, 4)
	139 dconst_0 (4, 4)
	140 dstore (4, 4)
	141 #7 (4, 4)
	142 iload_3 (5, 4)
	143 iconst_1 (5, 4)
	144 iadd (5, 4)
	145 istore (5, 4)
	146 #10 (5, 4)
	147 iload (5, 4)
	148 #10 (5, 4)
	149 iload_1 (5, 4)
	150 if_icmpge (5, 4)
	151 27 (5, 4)
	153 dload (5, 4)
	154 #7 (5, 4)
	155 aload_2 (5, 4)
	156 iload (5, 4)
	157 #9 (5, 4)
	158 aaload (5, 4)
	159 iload (5, 4)
	160 #10 (5, 4)
	161 daload (5, 4)
	162 aload (5, 4)
	163 #4 (5, 4)
	164 iload (5, 4)
	165 #10 (5, 4)
	166 daload (5, 4)
	167 dmul (5, 4)
	168 dadd (5, 4)
	169 dstore (5, 4)
	170 #7 (5, 4)
	171 iinc (5, 4)
	172 #10 (5, 4)
	173 -89 (5, 4)
	174 goto (5, 4)
	175 -27 (5, 4)
	177 dload (4, 4)
	178 #7 (4, 4)
	179 dload (4, 4)
	180 #5 (4, 4)
	181 dmul (4, 4)
	182 dstore (4, 4)
	183 #7 (4, 4)
	184 aload_2 (4, 4)
	185 iload (4, 4)
	186 #9 (4, 4)
	187 aaload (4, 4)
	188 iload_3 (4, 4)
	189 dload (4, 4)
	190 #7 (4, 4)
	191 aload (4, 4)
	192 #4 (4, 4)
	193 iload_3 (4, 4)
	194 daload (4, 4)
	195 dmul (4, 4)
	196 dastore (4, 4)
	197 iload_3 (5, 4)
	198 iconst_1 (5, 4)
	199 iadd (5, 4)
	200 istore (5, 4)
	201 #10 (5, 4)
	202 iload (5, 4)
	203 #10 (5, 4)
	204 iload_1 (5, 4)
	205 if_icmpge (5, 4)
	206 27 (5, 4)
	208 aload_2 (5, 4)
	209 iload (5, 4)
	210 #9 (5, 4)
	211 aaload (5, 4)
	212 iload (5, 4)
	213 #10 (5, 4)
	214 dup2 (5, 4)
	215 daload (5, 4)
	216 dload (5, 4)
	217 #7 (5, 4)
	218 aload (5, 4)
	219 #4 (5, 4)
	220 iload (5, 4)
	221 #10 (5, 4)
	222 daload (5, 4)
	223 dmul (5, 4)
	224 dadd (5, 4)
	225 dastore (5, 4)
	226 iinc (5, 4)
	227 #10 (5, 4)
	228 -89 (5, 4)
	229 goto (5, 4)
	230 -27 (5, 4)
	232 iinc (5, 4)
	233 #9 (5, 4)
	234 -89 (5, 4)
	235 goto (5, 4)
	236 -102 (5, 4)
	238 iinc (5, 4)
	239 #3 (5, 4)
	240 -89 (5, 4)
	241 goto (5, 4)
	242 -217 (5, 4)
	244 aload_2 (4, 4)
	245 iconst_0 (4, 4)
	246 aaload (4, 4)
	247 iconst_0 (4, 4)
	248 dconst_1 (4, 4)
	249 dastore (4, 4)
	250 aload_0 (4, 4)
	251 aload_2 (4, 4)
	252 invokestatic (4, 4)
	253 org/apache/commons/math3/linear/MatrixUtils.createRealMatrix:([[D)Lorg/apache/commons/math3/linear/RealMatrix; (4, 4)
	255 putfield (4, 4)
	256 org/apache/commons/math3/linear/TriDiagonalTransformer.cachedQt:Lorg/apache/commons/math3/linear/RealMatrix; (4, 4)
	258 aload_0 (3, 1)
	259 getfield (3, 1)
	260 org/apache/commons/math3/linear/TriDiagonalTransformer.cachedQt:Lorg/apache/commons/math3/linear/RealMatrix; (3, 1)
	262 areturn (3, 1)

Method: getT
	0 aload_0 (1, 1)
	1 getfield (1, 1)
	2 org/apache/commons/math3/linear/TriDiagonalTransformer.cachedT:Lorg/apache/commons/math3/linear/RealMatrix; (1, 1)
	4 ifnonnull (1, 1)
	5 91 (1, 1)
	7 aload_0 (1, 1)
	8 getfield (1, 1)
	9 org/apache/commons/math3/linear/TriDiagonalTransformer.main:[D (1, 1)
	11 arraylength (1, 1)
	12 istore_1 (1, 1)
	13 iload_1 (1, 1)
	14 iload_1 (1, 1)
	15 multianewarray (1, 1)
	16 [[D (1, 1)
	18 77 (1, 1)
	19 astore_2 (1, 1)
	20 iconst_0 (2, 4)
	21 istore_3 (2, 4)
	22 iload_3 (2, 4)
	23 iload_1 (2, 4)
	24 if_icmpge (2, 4)
	25 63 (2, 4)
	27 aload_2 (2, 4)
	28 iload_3 (2, 4)
	29 aaload (2, 4)
	30 iload_3 (2, 4)
	31 aload_0 (2, 4)
	32 getfield (2, 4)
	33 org/apache/commons/math3/linear/TriDiagonalTransformer.main:[D (2, 4)
	35 iload_3 (2, 4)
	36 daload (2, 4)
	37 dastore (2, 4)
	38 iload_3 (3, 1)
	39 ifle (3, 1)
	40 18 (3, 1)
	42 aload_2 (3, 1)
	43 iload_3 (3, 1)
	44 aaload (3, 1)
	45 iload_3 (3, 1)
	46 iconst_1 (3, 1)
	47 isub (3, 1)
	48 aload_0 (3, 1)
	49 getfield (3, 1)
	50 org/apache/commons/math3/linear/TriDiagonalTransformer.secondary:[D (3, 1)
	52 iload_3 (3, 1)
	53 iconst_1 (3, 1)
	54 isub (3, 1)
	55 daload (3, 1)
	56 dastore (3, 1)
	57 iload_3 (3, 1)
	58 aload_0 (3, 1)
	59 getfield (3, 1)
	60 org/apache/commons/math3/linear/TriDiagonalTransformer.main:[D (3, 1)
	62 arraylength (3, 1)
	63 iconst_1 (3, 1)
	64 isub (3, 1)
	65 if_icmpge (3, 1)
	66 16 (3, 1)
	68 aload_2 (3, 1)
	69 iload_3 (3, 1)
	70 aaload (3, 1)
	71 iload_3 (3, 1)
	72 iconst_1 (3, 1)
	73 iadd (3, 1)
	74 aload_0 (3, 1)
	75 getfield (3, 1)
	76 org/apache/commons/math3/linear/TriDiagonalTransformer.secondary:[D (3, 1)
	78 iload_3 (3, 1)
	79 daload (3, 1)
	80 dastore (3, 1)
	81 iinc (3, 1)
	82 #3 (3, 1)
	83 -89 (3, 1)
	84 goto (3, 1)
	85 -62 (3, 1)
	87 aload_0 (2, 4)
	88 aload_2 (2, 4)
	89 invokestatic (2, 4)
	90 org/apache/commons/math3/linear/MatrixUtils.createRealMatrix:([[D)Lorg/apache/commons/math3/linear/RealMatrix; (2, 4)
	92 putfield (2, 4)
	93 org/apache/commons/math3/linear/TriDiagonalTransformer.cachedT:Lorg/apache/commons/math3/linear/RealMatrix; (2, 4)
	95 aload_0 (1, 1)
	96 getfield (1, 1)
	97 org/apache/commons/math3/linear/TriDiagonalTransformer.cachedT:Lorg/apache/commons/math3/linear/RealMatrix; (1, 1)
	99 areturn (1, 1)

Method: getHouseholderVectorsRef
	0 aload_0 (0, 0)
	1 getfield (0, 0)
	2 org/apache/commons/math3/linear/TriDiagonalTransformer.householderVectors:[[D (0, 0)
	4 areturn (0, 0)

Method: getMainDiagonalRef
	0 aload_0 (0, 0)
	1 getfield (0, 0)
	2 org/apache/commons/math3/linear/TriDiagonalTransformer.main:[D (0, 0)
	4 areturn (0, 0)

Method: getSecondaryDiagonalRef
	0 aload_0 (0, 0)
	1 getfield (0, 0)
	2 org/apache/commons/math3/linear/TriDiagonalTransformer.secondary:[D (0, 0)
	4 areturn (0, 0)

Method: transform
	0 aload_0 (0, 0)
	1 getfield (0, 0)
	2 org/apache/commons/math3/linear/TriDiagonalTransformer.householderVectors:[[D (0, 0)
	4 arraylength (0, 0)
	5 istore_1 (0, 0)
	6 iload_1 (0, 0)
	7 newarray (0, 0)
	8 7 (0, 0)
	9 astore_2 (0, 0)
	10 iconst_0 (1, 4)
	11 istore_3 (1, 4)
	12 iload_3 (1, 4)
	13 iload_1 (1, 4)
	14 iconst_1 (1, 4)
	15 isub (1, 4)
	16 if_icmpge (1, 4)
	17 397 (1, 4)
	19 aload_0 (1, 4)
	20 getfield (1, 4)
	21 org/apache/commons/math3/linear/TriDiagonalTransformer.householderVectors:[[D (1, 4)
	23 iload_3 (1, 4)
	24 aaload (1, 4)
	25 astore (1, 4)
	26 #4 (1, 4)
	27 aload_0 (1, 4)
	28 getfield (1, 4)
	29 org/apache/commons/math3/linear/TriDiagonalTransformer.main:[D (1, 4)
	31 iload_3 (1, 4)
	32 aload (1, 4)
	33 #4 (1, 4)
	34 iload_3 (1, 4)
	35 daload (1, 4)
	36 dastore (1, 4)
	37 dconst_0 (1, 4)
	38 dstore (1, 4)
	39 #5 (1, 4)
	40 iload_3 (2, 4)
	41 iconst_1 (2, 4)
	42 iadd (2, 4)
	43 istore (2, 4)
	44 #7 (2, 4)
	45 iload (2, 4)
	46 #7 (2, 4)
	47 iload_1 (2, 4)
	48 if_icmpge (2, 4)
	49 26 (2, 4)
	51 aload (2, 4)
	52 #4 (2, 4)
	53 iload (2, 4)
	54 #7 (2, 4)
	55 daload (2, 4)
	56 dstore (2, 4)
	57 #8 (2, 4)
	58 dload (2, 4)
	59 #5 (2, 4)
	60 dload (2, 4)
	61 #8 (2, 4)
	62 dload (2, 4)
	63 #8 (2, 4)
	64 dmul (2, 4)
	65 dadd (2, 4)
	66 dstore (2, 4)
	67 #5 (2, 4)
	68 iinc (2, 4)
	69 #7 (2, 4)
	70 -89 (2, 4)
	71 goto (2, 4)
	72 -26 (2, 4)
	74 aload (1, 4)
	75 #4 (1, 4)
	76 iload_3 (1, 4)
	77 iconst_1 (1, 4)
	78 iadd (1, 4)
	79 daload (1, 4)
	80 dconst_0 (1, 4)
	81 dcmpl (1, 4)
	82 ifle (1, 4)
	83 12 (1, 4)
	85 dload (1, 4)
	86 #5 (1, 4)
	87 invokestatic (1, 4)
	88 org/apache/commons/math3/util/FastMath.sqrt:(D)D (1, 4)
	90 dneg (1, 4)
	91 goto (1, 4)
	92 8 (1, 4)
	94 dload (1, 4)
	95 #5 (1, 4)
	96 invokestatic (1, 4)
	97 org/apache/commons/math3/util/FastMath.sqrt:(D)D (1, 4)
	99 dstore (1, 4)
	100 #7 (1, 4)
	101 aload_0 (1, 4)
	102 getfield (1, 4)
	103 org/apache/commons/math3/linear/TriDiagonalTransformer.secondary:[D (1, 4)
	105 iload_3 (1, 4)
	106 dload (1, 4)
	107 #7 (1, 4)
	108 dastore (1, 4)
	109 dload (2, 1)
	110 #7 (2, 1)
	111 dconst_0 (2, 1)
	112 dcmpl (2, 1)
	113 ifeq (2, 1)
	114 294 (2, 1)
	116 aload (2, 4)
	117 #4 (2, 4)
	118 iload_3 (2, 4)
	119 iconst_1 (2, 4)
	120 iadd (2, 4)
	121 dup2 (2, 4)
	122 daload (2, 4)
	123 dload (2, 4)
	124 #7 (2, 4)
	125 dsub (2, 4)
	126 dastore (2, 4)
	127 ldc2_w (2, 4)
	128 -1.0 (2, 4)
	130 dload (2, 4)
	131 #7 (2, 4)
	132 aload (2, 4)
	133 #4 (2, 4)
	134 iload_3 (2, 4)
	135 iconst_1 (2, 4)
	136 iadd (2, 4)
	137 daload (2, 4)
	138 dmul (2, 4)
	139 ddiv (2, 4)
	140 dstore (2, 4)
	141 #9 (2, 4)
	142 aload_2 (2, 4)
	143 iload_3 (2, 4)
	144 iconst_1 (2, 4)
	145 iadd (2, 4)
	146 iload_1 (2, 4)
	147 dconst_0 (2, 4)
	148 invokestatic (2, 4)
	149 java/util/Arrays.fill:([DIID)V (2, 4)
	151 iload_3 (3, 4)
	152 iconst_1 (3, 4)
	153 iadd (3, 4)
	154 istore (3, 4)
	155 #11 (3, 4)
	156 iload (3, 4)
	157 #11 (3, 4)
	158 iload_1 (3, 4)
	159 if_icmpge (3, 4)
	160 99 (3, 4)
	162 aload_0 (3, 4)
	163 getfield (3, 4)
	164 org/apache/commons/math3/linear/TriDiagonalTransformer.householderVectors:[[D (3, 4)
	166 iload (3, 4)
	167 #11 (3, 4)
	168 aaload (3, 4)
	169 astore (3, 4)
	170 #12 (3, 4)
	171 aload (3, 4)
	172 #4 (3, 4)
	173 iload (3, 4)
	174 #11 (3, 4)
	175 daload (3, 4)
	176 dstore (3, 4)
	177 #13 (3, 4)
	178 aload (3, 4)
	179 #12 (3, 4)
	180 iload (3, 4)
	181 #11 (3, 4)
	182 daload (3, 4)
	183 dload (3, 4)
	184 #13 (3, 4)
	185 dmul (3, 4)
	186 dstore (3, 4)
	187 #15 (3, 4)
	188 iload (4, 4)
	189 #11 (4, 4)
	190 iconst_1 (4, 4)
	191 iadd (4, 4)
	192 istore (4, 4)
	193 #17 (4, 4)
	194 iload (4, 4)
	195 #17 (4, 4)
	196 iload_1 (4, 4)
	197 if_icmpge (4, 4)
	198 41 (4, 4)
	200 aload (4, 4)
	201 #12 (4, 4)
	202 iload (4, 4)
	203 #17 (4, 4)
	204 daload (4, 4)
	205 dstore (4, 4)
	206 #18 (4, 4)
	207 dload (4, 4)
	208 #15 (4, 4)
	209 dload (4, 4)
	210 #18 (4, 4)
	211 aload (4, 4)
	212 #4 (4, 4)
	213 iload (4, 4)
	214 #17 (4, 4)
	215 daload (4, 4)
	216 dmul (4, 4)
	217 dadd (4, 4)
	218 dstore (4, 4)
	219 #15 (4, 4)
	220 aload_2 (4, 4)
	221 iload (4, 4)
	222 #17 (4, 4)
	223 dup2 (4, 4)
	224 daload (4, 4)
	225 dload (4, 4)
	226 #18 (4, 4)
	227 dload (4, 4)
	228 #13 (4, 4)
	229 dmul (4, 4)
	230 dadd (4, 4)
	231 dastore (4, 4)
	232 iinc (4, 4)
	233 #17 (4, 4)
	234 -89 (4, 4)
	235 goto (4, 4)
	236 -41 (4, 4)
	238 aload_2 (3, 4)
	239 iload (3, 4)
	240 #11 (3, 4)
	241 dload (3, 4)
	242 #9 (3, 4)
	243 aload_2 (3, 4)
	244 iload (3, 4)
	245 #11 (3, 4)
	246 daload (3, 4)
	247 dload (3, 4)
	248 #15 (3, 4)
	249 dadd (3, 4)
	250 dmul (3, 4)
	251 dastore (3, 4)
	252 iinc (3, 4)
	253 #11 (3, 4)
	254 -89 (3, 4)
	255 goto (3, 4)
	256 -99 (3, 4)
	258 dconst_0 (2, 4)
	259 dstore (2, 4)
	260 #11 (2, 4)
	261 iload_3 (3, 4)
	262 iconst_1 (3, 4)
	263 iadd (3, 4)
	264 istore (3, 4)
	265 #13 (3, 4)
	266 iload (3, 4)
	267 #13 (3, 4)
	268 iload_1 (3, 4)
	269 if_icmpge (3, 4)
	270 24 (3, 4)
	272 dload (3, 4)
	273 #11 (3, 4)
	274 aload_2 (3, 4)
	275 iload (3, 4)
	276 #13 (3, 4)
	277 daload (3, 4)
	278 aload (3, 4)
	279 #4 (3, 4)
	280 iload (3, 4)
	281 #13 (3, 4)
	282 daload (3, 4)
	283 dmul (3, 4)
	284 dadd (3, 4)
	285 dstore (3, 4)
	286 #11 (3, 4)
	287 iinc (3, 4)
	288 #13 (3, 4)
	289 -89 (3, 4)
	290 goto (3, 4)
	291 -24 (3, 4)
	293 dload (2, 4)
	294 #11 (2, 4)
	295 dload (2, 4)
	296 #9 (2, 4)
	297 ldc2_w (2, 4)
	298 2.0 (2, 4)
	300 ddiv (2, 4)
	301 dmul (2, 4)
	302 dstore (2, 4)
	303 #11 (2, 4)
	304 iload_3 (3, 4)
	305 iconst_1 (3, 4)
	306 iadd (3, 4)
	307 istore (3, 4)
	308 #13 (3, 4)
	309 iload (3, 4)
	310 #13 (3, 4)
	311 iload_1 (3, 4)
	312 if_icmpge (3, 4)
	313 24 (3, 4)
	315 aload_2 (3, 4)
	316 iload (3, 4)
	317 #13 (3, 4)
	318 dup2 (3, 4)
	319 daload (3, 4)
	320 dload (3, 4)
	321 #11 (3, 4)
	322 aload (3, 4)
	323 #4 (3, 4)
	324 iload (3, 4)
	325 #13 (3, 4)
	326 daload (3, 4)
	327 dmul (3, 4)
	328 dsub (3, 4)
	329 dastore (3, 4)
	330 iinc (3, 4)
	331 #13 (3, 4)
	332 -89 (3, 4)
	333 goto (3, 4)
	334 -24 (3, 4)
	336 iload_3 (3, 4)
	337 iconst_1 (3, 4)
	338 iadd (3, 4)
	339 istore (3, 4)
	340 #13 (3, 4)
	341 iload (3, 4)
	342 #13 (3, 4)
	343 iload_1 (3, 4)
	344 if_icmpge (3, 4)
	345 63 (3, 4)
	347 aload_0 (3, 4)
	348 getfield (3, 4)
	349 org/apache/commons/math3/linear/TriDiagonalTransformer.householderVectors:[[D (3, 4)
	351 iload (3, 4)
	352 #13 (3, 4)
	353 aaload (3, 4)
	354 astore (3, 4)
	355 #14 (3, 4)
	356 iload (4, 4)
	357 #13 (4, 4)
	358 istore (4, 4)
	359 #15 (4, 4)
	360 iload (4, 4)
	361 #15 (4, 4)
	362 iload_1 (4, 4)
	363 if_icmpge (4, 4)
	364 38 (4, 4)
	366 aload (4, 4)
	367 #14 (4, 4)
	368 iload (4, 4)
	369 #15 (4, 4)
	370 dup2 (4, 4)
	371 daload (4, 4)
	372 aload (4, 4)
	373 #4 (4, 4)
	374 iload (4, 4)
	375 #13 (4, 4)
	376 daload (4, 4)
	377 aload_2 (4, 4)
	378 iload (4, 4)
	379 #15 (4, 4)
	380 daload (4, 4)
	381 dmul (4, 4)
	382 aload_2 (4, 4)
	383 iload (4, 4)
	384 #13 (4, 4)
	385 daload (4, 4)
	386 aload (4, 4)
	387 #4 (4, 4)
	388 iload (4, 4)
	389 #15 (4, 4)
	390 daload (4, 4)
	391 dmul (4, 4)
	392 dadd (4, 4)
	393 dsub (4, 4)
	394 dastore (4, 4)
	395 iinc (4, 4)
	396 #15 (4, 4)
	397 -89 (4, 4)
	398 goto (4, 4)
	399 -38 (4, 4)
	401 iinc (4, 4)
	402 #13 (4, 4)
	403 -89 (4, 4)
	404 goto (4, 4)
	405 -63 (4, 4)
	407 iinc (4, 4)
	408 #3 (4, 4)
	409 -89 (4, 4)
	410 goto (4, 4)
	411 -398 (4, 4)
	413 aload_0 (3, 4)
	414 getfield (3, 4)
	415 org/apache/commons/math3/linear/TriDiagonalTransformer.main:[D (3, 4)
	417 iload_1 (3, 4)
	418 iconst_1 (3, 4)
	419 isub (3, 4)
	420 aload_0 (3, 4)
	421 getfield (3, 4)
	422 org/apache/commons/math3/linear/TriDiagonalTransformer.householderVectors:[[D (3, 4)
	424 iload_1 (3, 4)
	425 iconst_1 (3, 4)
	426 isub (3, 4)
	427 aaload (3, 4)
	428 iload_1 (3, 4)
	429 iconst_1 (3, 4)
	430 isub (3, 4)
	431 daload (3, 4)
	432 dastore (3, 4)
	433 return (2, 4)

