Method: <init>
	0 aload_0 (0, 0)
	1 invokespecial (0, 0)
	4 aload_0 (0, 0)
	5 new (0, 0)
	8 dup (0, 0)
	9 lconst_0 (0, 0)
	10 invokespecial (0, 0)
	13 putfield (0, 0)
	16 aload_0 (0, 0)
	17 aload_1 (0, 0)
	18 putfield (0, 0)
	21 aload_0 (0, 0)
	22 aload_2 (0, 0)
	23 putfield (0, 0)
	26 aload_0 (0, 0)
	27 aload_3 (0, 0)
	28 putfield (0, 0)
	31 return (0, 0)

Method: update
	0 aload_0 (0, 0)
	1 getfield (0, 0)
	4 invokevirtual (0, 0)
	7 lconst_1 (0, 0)
	8 lsub (0, 0)
	9 lstore_3 (0, 0)
	10 aload_0 (0, 0)
	11 getfield (0, 0)
	14 lload_3 (0, 0)
	15 invokeinterface (0, 0)
	20 dstore (0, 0)
	22 aload_0 (0, 0)
	23 aload_1 (0, 0)
	24 aload_2 (0, 0)
	25 dload (0, 0)
	27 invokespecial (0, 0)
	30 astore (0, 0)
	32 aload_0 (0, 0)
	33 getfield (0, 0)
	36 lload_3 (0, 0)
	37 invokeinterface (0, 0)
	42 istore (0, 0)
	44 new (0, 0)
	47 dup (0, 0)
	48 dload (0, 0)
	50 dconst_0 (0, 0)
	51 iload (0, 0)
	53 i2d (0, 0)
	54 invokespecial (0, 0)
	57 astore (0, 0)
	59 iload (1, 1)
	61 ifle (1, 1)
	64 new (1, 1)
	67 dup (1, 1)
	68 invokespecial (1, 1)
	71 astore (1, 1)
	73 aload (1, 1)
	75 aload (1, 1)
	77 invokeinterface (1, 1)
	82 pop (1, 1)
	83 new (1, 1)
	86 dup (1, 1)
	87 invokespecial (1, 1)
	90 astore (1, 1)
	92 aload (1, 1)
	94 aload (1, 1)
	96 invokevirtual (1, 1)
	99 pop (1, 1)
	100 iconst_1 (1, 1)
	101 istore (1, 1)
	103 aload_1 (2, 1)
	104 aload (2, 1)
	106 aload (2, 1)
	108 invokevirtual (2, 1)
	111 astore (2, 1)
	113 aload (3, 4)
	115 invokeinterface (3, 4)
	120 astore (3, 4)
	122 aload (3, 4)
	124 invokeinterface (3, 4)
	129 ifeq (3, 4)
	132 aload (3, 4)
	134 invokeinterface (3, 4)
	139 checkcast (3, 4)
	142 astore (3, 4)
	144 aload_0 (3, 4)
	145 aload (3, 4)
	147 aload_2 (3, 4)
	148 aload (3, 4)
	150 iload (3, 4)
	152 i2d (3, 4)
	153 invokevirtual (3, 4)
	156 invokespecial (3, 4)
	159 goto (2, 1)
	162 aload (2, 1)
	164 aload (2, 1)
	166 invokevirtual (2, 1)
	169 pop (2, 1)
	170 iinc (2, 1)
	173 iload (1, 1)
	175 iload (1, 1)
	177 if_icmple (1, 1)
	180 return (0, 0)

Method: getNumberOfCalls
	0 aload_0 (0, 0)
	1 getfield (0, 0)
	4 invokevirtual (0, 0)
	7 lreturn (0, 0)

Method: attemptNeuronUpdate
	0 aload_1 (0, 0)
	1 invokevirtual (0, 0)
	4 astore (0, 0)
	6 aload_0 (0, 0)
	7 aload (0, 0)
	9 aload_2 (0, 0)
	10 dload_3 (0, 0)
	11 invokespecial (0, 0)
	14 astore (0, 0)
	16 aload_1 (0, 0)
	17 aload (0, 0)
	19 aload (0, 0)
	21 invokevirtual (0, 0)
	24 ireturn (0, 0)

Method: updateNeighbouringNeuron
	0 aload_0 (1, 1)
	1 aload_1 (1, 1)
	2 aload_2 (1, 1)
	3 dload_3 (1, 1)
	4 invokespecial (1, 1)
	7 ifeq (1, 1)
	10 goto (1, 1)
	13 return (0, 0)

Method: findAndUpdateBestNeuron
	0 aload_2 (0, 0)
	1 aload_1 (0, 0)
	2 aload_0 (0, 0)
	3 getfield (0, 0)
	6 invokestatic (0, 0)
	9 astore (0, 0)
	11 aload_0 (1, 1)
	12 aload (1, 1)
	14 aload_2 (1, 1)
	15 dload_3 (1, 1)
	16 invokespecial (1, 1)
	19 ifeq (1, 1)
	22 aload (1, 1)
	24 areturn (1, 1)
	25 goto (0, 4)

Method: computeFeatures
	0 new (0, 0)
	3 dup (0, 0)
	4 aload_1 (0, 0)
	5 iconst_0 (0, 0)
	6 invokespecial (0, 0)
	9 astore (0, 0)
	11 new (0, 0)
	14 dup (0, 0)
	15 aload_2 (0, 0)
	16 iconst_0 (0, 0)
	17 invokespecial (0, 0)
	20 astore (0, 0)
	22 aload (0, 0)
	24 aload (0, 0)
	26 invokevirtual (0, 0)
	29 dload_3 (0, 0)
	30 invokevirtual (0, 0)
	33 aload (0, 0)
	35 invokevirtual (0, 0)
	38 invokevirtual (0, 0)
	41 areturn (0, 0)

