Method: <init>
	0 aload_0 (0, 0)
	1 invokespecial (0, 0)
	4 aload_0 (0, 0)
	5 aload_1 (0, 0)
	6 putfield (0, 0)
	9 aload_0 (0, 0)
	10 aload_2 (0, 0)
	11 putfield (0, 0)
	14 aload_0 (0, 0)
	15 aload_3 (0, 0)
	16 putfield (0, 0)
	19 return (0, 0)

Method: run
	0 aload_0 (1, 3)
	1 getfield (1, 3)
	4 invokeinterface (1, 3)
	9 ifeq (1, 3)
	12 aload_0 (1, 3)
	13 getfield (1, 3)
	16 aload_0 (1, 3)
	17 getfield (1, 3)
	20 aload_0 (1, 3)
	21 getfield (1, 3)
	24 invokeinterface (1, 3)
	29 checkcast (1, 3)
	32 invokevirtual (1, 3)
	35 goto (1, 3)
	38 return (0, 0)

