Method: <init>
	0 aload_0 (0, 0)
	1 invokespecial (0, 0)
	2 java/lang/Object.<init>:()V (0, 0)
	4 aload_0 (0, 0)
	5 aload_1 (0, 0)
	6 putfield (0, 0)
	7 org/apache/commons/math3/ml/neuralnet/sofm/KohonenTrainingTask.net:Lorg/apache/commons/math3/ml/neuralnet/Network; (0, 0)
	9 aload_0 (0, 0)
	10 aload_2 (0, 0)
	11 putfield (0, 0)
	12 org/apache/commons/math3/ml/neuralnet/sofm/KohonenTrainingTask.featuresIterator:Ljava/util/Iterator; (0, 0)
	14 aload_0 (0, 0)
	15 aload_3 (0, 0)
	16 putfield (0, 0)
	17 org/apache/commons/math3/ml/neuralnet/sofm/KohonenTrainingTask.updateAction:Lorg/apache/commons/math3/ml/neuralnet/sofm/KohonenUpdateAction; (0, 0)
	19 return (0, 0)

Method: run
	0 aload_0 (1, 3)
	1 getfield (1, 3)
	2 org/apache/commons/math3/ml/neuralnet/sofm/KohonenTrainingTask.featuresIterator:Ljava/util/Iterator; (1, 3)
	4 invokeinterface (1, 3)
	5 java/util/Iterator.next:()Ljava/lang/Object; (1, 3)
	7 0 (1, 3)
	9 ifeq (1, 3)
	10 29 (1, 3)
	12 aload_0 (1, 3)
	13 getfield (1, 3)
	14 org/apache/commons/math3/ml/neuralnet/sofm/KohonenTrainingTask.updateAction:Lorg/apache/commons/math3/ml/neuralnet/sofm/KohonenUpdateAction; (1, 3)
	16 aload_0 (1, 3)
	17 getfield (1, 3)
	18 org/apache/commons/math3/ml/neuralnet/sofm/KohonenTrainingTask.net:Lorg/apache/commons/math3/ml/neuralnet/Network; (1, 3)
	20 aload_0 (1, 3)
	21 getfield (1, 3)
	22 org/apache/commons/math3/ml/neuralnet/sofm/KohonenTrainingTask.featuresIterator:Ljava/util/Iterator; (1, 3)
	24 invokeinterface (1, 3)
	25 java/util/Iterator.[D (1, 3)
	27 0 (1, 3)
	29 checkcast (1, 3)
	30 [D (1, 3)
	32 invokevirtual (1, 3)
	33 org/apache/commons/math3/ml/neuralnet/sofm/KohonenUpdateAction.update:(Lorg/apache/commons/math3/ml/neuralnet/Network;[D)V (1, 3)
	35 goto (1, 3)
	36 -35 (1, 3)
	38 return (0, 0)

