Method: exponentialDecay
	0 new (0, 0)
	1 org/apache/commons/math3/ml/neuralnet/sofm/NeighbourhoodSizeFunctionFactory$1 (0, 0)
	3 dup (0, 0)
	4 dload_0 (0, 0)
	5 dload_2 (0, 0)
	6 lload (0, 0)
	7 #4 (0, 0)
	8 invokespecial (0, 0)
	9 org/apache/commons/math3/ml/neuralnet/sofm/NeighbourhoodSizeFunctionFactory$1.<init>:(DDJ)V (0, 0)
	11 areturn (0, 0)

Method: quasiSigmoidDecay
	0 new (0, 0)
	1 org/apache/commons/math3/ml/neuralnet/sofm/NeighbourhoodSizeFunctionFactory$2 (0, 0)
	3 dup (0, 0)
	4 dload_0 (0, 0)
	5 dload_2 (0, 0)
	6 lload (0, 0)
	7 #4 (0, 0)
	8 invokespecial (0, 0)
	9 org/apache/commons/math3/ml/neuralnet/sofm/NeighbourhoodSizeFunctionFactory$2.<init>:(DDJ)V (0, 0)
	11 areturn (0, 0)

