Method: <init>
	0 aload_0 (0, 0)
	1 invokespecial (0, 0)
	2 java/lang/Object.<init>:()V (0, 0)
	4 aload_0 (0, 0)
	5 new (0, 0)
	6 org/apache/commons/math3/optim/univariate/BracketFinder (0, 0)
	8 dup (0, 0)
	9 invokespecial (0, 0)
	10 org/apache/commons/math3/optim/univariate/BracketFinder.<init>:()V (0, 0)
	12 putfield (0, 0)
	13 org/apache/commons/math3/optim/nonlinear/scalar/LineSearch.bracket:Lorg/apache/commons/math3/optim/univariate/BracketFinder; (0, 0)
	15 aload_0 (4, 1)
	16 aload_1 (4, 1)
	17 putfield (4, 1)
	18 org/apache/commons/math3/optim/nonlinear/scalar/LineSearch.mainOptimizer:Lorg/apache/commons/math3/optim/nonlinear/scalar/MultivariateOptimizer; (4, 1)
	20 aload_0 (4, 1)
	21 new (4, 1)
	22 org/apache/commons/math3/optim/univariate/BrentOptimizer (4, 1)
	24 dup (4, 1)
	25 ldc2_w (4, 1)
	26 1e-15 (4, 1)
	28 ldc2_w (4, 1)
	29 5e-324 (4, 1)
	31 new (4, 1)
	32 org/apache/commons/math3/optim/univariate/SimpleUnivariateValueChecker (4, 1)
	34 dup (4, 1)
	35 dload_2 (4, 1)
	36 dload (4, 1)
	37 #4 (4, 1)
	38 invokespecial (4, 1)
	39 org/apache/commons/math3/optim/univariate/SimpleUnivariateValueChecker.<init>:(DD)V (4, 1)
	41 invokespecial (4, 1)
	42 org/apache/commons/math3/optim/univariate/BrentOptimizer.<init>:(DDLorg/apache/commons/math3/optim/ConvergenceChecker;)V (4, 1)
	44 putfield (4, 1)
	45 org/apache/commons/math3/optim/nonlinear/scalar/LineSearch.lineOptimizer:Lorg/apache/commons/math3/optim/univariate/UnivariateOptimizer; (4, 1)
	47 aload_0 (4, 1)
	48 dload (4, 1)
	49 #6 (4, 1)
	50 putfield (4, 1)
	51 org/apache/commons/math3/optim/nonlinear/scalar/LineSearch.initialBracketingRange:D (4, 1)
	53 return (1, 1)

Method: search
	0 aload_1 (0, 0)
	1 arraylength (0, 0)
	2 istore_3 (0, 0)
	3 new (0, 0)
	4 org/apache/commons/math3/optim/nonlinear/scalar/LineSearch$1 (0, 0)
	6 dup (0, 0)
	7 aload_0 (0, 0)
	8 iload_3 (0, 0)
	9 aload_1 (0, 0)
	10 aload_2 (0, 0)
	11 invokespecial (0, 0)
	12 org/apache/commons/math3/optim/nonlinear/scalar/LineSearch$1.<init>:(Lorg/apache/commons/math3/optim/nonlinear/scalar/LineSearch;I[D[D)V (0, 0)
	14 astore (0, 0)
	15 #4 (0, 0)
	16 aload_0 (0, 0)
	17 getfield (0, 0)
	18 org/apache/commons/math3/optim/nonlinear/scalar/LineSearch.mainOptimizer:Lorg/apache/commons/math3/optim/nonlinear/scalar/MultivariateOptimizer; (0, 0)
	20 invokevirtual (0, 0)
	21 org/apache/commons/math3/optim/nonlinear/scalar/MultivariateOptimizer.getGoalType:()Lorg/apache/commons/math3/optim/nonlinear/scalar/GoalType; (0, 0)
	23 astore (0, 0)
	24 #5 (0, 0)
	25 aload_0 (0, 0)
	26 getfield (0, 0)
	27 org/apache/commons/math3/optim/nonlinear/scalar/LineSearch.bracket:Lorg/apache/commons/math3/optim/univariate/BracketFinder; (0, 0)
	29 aload (0, 0)
	30 #4 (0, 0)
	31 aload (0, 0)
	32 #5 (0, 0)
	33 dconst_0 (0, 0)
	34 aload_0 (0, 0)
	35 getfield (0, 0)
	36 org/apache/commons/math3/optim/nonlinear/scalar/LineSearch.initialBracketingRange:D (0, 0)
	38 invokevirtual (0, 0)
	39 org/apache/commons/math3/optim/univariate/BracketFinder.search:(Lorg/apache/commons/math3/analysis/UnivariateFunction;Lorg/apache/commons/math3/optim/nonlinear/scalar/GoalType;DD)V (0, 0)
	41 aload_0 (0, 0)
	42 getfield (0, 0)
	43 org/apache/commons/math3/optim/nonlinear/scalar/LineSearch.lineOptimizer:Lorg/apache/commons/math3/optim/univariate/UnivariateOptimizer; (0, 0)
	45 iconst_4 (0, 0)
	46 anewarray (0, 0)
	47 org/apache/commons/math3/optim/OptimizationData (0, 0)
	49 dup (0, 0)
	50 iconst_0 (0, 0)
	51 new (0, 0)
	52 org/apache/commons/math3/optim/MaxEval (0, 0)
	54 dup (0, 0)
	55 ldc (0, 0)
	56 2147483647 (0, 0)
	57 invokespecial (0, 0)
	58 org/apache/commons/math3/optim/MaxEval.<init>:(I)V (0, 0)
	60 aastore (0, 0)
	61 dup (0, 0)
	62 iconst_1 (0, 0)
	63 new (0, 0)
	64 org/apache/commons/math3/optim/univariate/UnivariateObjectiveFunction (0, 0)
	66 dup (0, 0)
	67 aload (0, 0)
	68 #4 (0, 0)
	69 invokespecial (0, 0)
	70 org/apache/commons/math3/optim/univariate/UnivariateObjectiveFunction.<init>:(Lorg/apache/commons/math3/analysis/UnivariateFunction;)V (0, 0)
	72 aastore (0, 0)
	73 dup (0, 0)
	74 iconst_2 (0, 0)
	75 aload (0, 0)
	76 #5 (0, 0)
	77 aastore (0, 0)
	78 dup (0, 0)
	79 iconst_3 (0, 0)
	80 new (0, 0)
	81 org/apache/commons/math3/optim/univariate/SearchInterval (0, 0)
	83 dup (0, 0)
	84 aload_0 (0, 0)
	85 getfield (0, 0)
	86 org/apache/commons/math3/optim/nonlinear/scalar/LineSearch.bracket:Lorg/apache/commons/math3/optim/univariate/BracketFinder; (0, 0)
	88 invokevirtual (0, 0)
	89 org/apache/commons/math3/optim/univariate/BracketFinder.getLo:()D (0, 0)
	91 aload_0 (0, 0)
	92 getfield (0, 0)
	93 org/apache/commons/math3/optim/nonlinear/scalar/LineSearch.bracket:Lorg/apache/commons/math3/optim/univariate/BracketFinder; (0, 0)
	95 invokevirtual (0, 0)
	96 org/apache/commons/math3/optim/univariate/BracketFinder.getHi:()D (0, 0)
	98 aload_0 (0, 0)
	99 getfield (0, 0)
	100 org/apache/commons/math3/optim/nonlinear/scalar/LineSearch.bracket:Lorg/apache/commons/math3/optim/univariate/BracketFinder; (0, 0)
	102 invokevirtual (0, 0)
	103 org/apache/commons/math3/optim/univariate/BracketFinder.getMid:()D (0, 0)
	105 invokespecial (0, 0)
	106 org/apache/commons/math3/optim/univariate/SearchInterval.<init>:(DDD)V (0, 0)
	108 aastore (0, 0)
	109 invokevirtual (0, 0)
	110 org/apache/commons/math3/optim/univariate/UnivariateOptimizer.optimize:([Lorg/apache/commons/math3/optim/OptimizationData;)Lorg/apache/commons/math3/optim/univariate/UnivariatePointValuePair; (0, 0)
	112 areturn (0, 0)

Method: access$000
	0 aload_0 (0, 0)
	1 getfield (0, 0)
	2 org/apache/commons/math3/optim/nonlinear/scalar/LineSearch.mainOptimizer:Lorg/apache/commons/math3/optim/nonlinear/scalar/MultivariateOptimizer; (0, 0)
	4 areturn (0, 0)

