Method: <init>
	0 aload_0 (0, 0)
	1 invokespecial (0, 0)
	4 aload_0 (0, 0)
	5 new (0, 0)
	8 dup (0, 0)
	9 invokespecial (0, 0)
	12 putfield (0, 0)
	15 aload_0 (1, 1)
	16 aload_1 (1, 1)
	17 putfield (1, 1)
	20 aload_0 (1, 1)
	21 new (1, 1)
	24 dup (1, 1)
	25 ldc2_w (1, 1)
	28 ldc2_w (1, 1)
	31 new (1, 1)
	34 dup (1, 1)
	35 dload_2 (1, 1)
	36 dload (1, 1)
	38 invokespecial (1, 1)
	41 invokespecial (1, 1)
	44 putfield (1, 1)
	47 aload_0 (1, 1)
	48 dload (1, 1)
	50 putfield (1, 1)
	53 return (0, 1)

Method: search
	0 aload_1 (0, 0)
	1 arraylength (0, 0)
	2 istore_3 (0, 0)
	3 new (0, 0)
	6 dup (0, 0)
	7 aload_0 (0, 0)
	8 iload_3 (0, 0)
	9 aload_1 (0, 0)
	10 aload_2 (0, 0)
	11 invokespecial (0, 0)
	14 astore (0, 0)
	16 aload_0 (0, 0)
	17 getfield (0, 0)
	20 invokevirtual (0, 0)
	23 astore (0, 0)
	25 aload_0 (0, 0)
	26 getfield (0, 0)
	29 aload (0, 0)
	31 aload (0, 0)
	33 dconst_0 (0, 0)
	34 aload_0 (0, 0)
	35 getfield (0, 0)
	38 invokevirtual (0, 0)
	41 aload_0 (0, 0)
	42 getfield (0, 0)
	45 iconst_4 (0, 0)
	46 anewarray (0, 0)
	49 dup (0, 0)
	50 iconst_0 (0, 0)
	51 new (0, 0)
	54 dup (0, 0)
	55 ldc (0, 0)
	57 invokespecial (0, 0)
	60 aastore (0, 0)
	61 dup (0, 0)
	62 iconst_1 (0, 0)
	63 new (0, 0)
	66 dup (0, 0)
	67 aload (0, 0)
	69 invokespecial (0, 0)
	72 aastore (0, 0)
	73 dup (0, 0)
	74 iconst_2 (0, 0)
	75 aload (0, 0)
	77 aastore (0, 0)
	78 dup (0, 0)
	79 iconst_3 (0, 0)
	80 new (0, 0)
	83 dup (0, 0)
	84 aload_0 (0, 0)
	85 getfield (0, 0)
	88 invokevirtual (0, 0)
	91 aload_0 (0, 0)
	92 getfield (0, 0)
	95 invokevirtual (0, 0)
	98 aload_0 (0, 0)
	99 getfield (0, 0)
	102 invokevirtual (0, 0)
	105 invokespecial (0, 0)
	108 aastore (0, 0)
	109 invokevirtual (0, 0)
	112 areturn (0, 0)

Method: access$000
	0 aload_0 (0, 0)
	1 getfield (0, 0)
	4 areturn (0, 0)

