Method: <init>
	0 aload_0 (0, 0)
	1 invokespecial (0, 0)
	2 java/lang/Object.<init>:()V (0, 0)
	4 aload_2 (0, 0)
	5 invokestatic (0, 0)
	6 org/apache/commons/math3/util/MathUtils.checkNotNull:(Ljava/lang/Object;)V (0, 0)
	8 aload_3 (0, 0)
	9 invokestatic (0, 0)
	10 org/apache/commons/math3/util/MathUtils.checkNotNull:(Ljava/lang/Object;)V (0, 0)
	12 aload (0, 0)
	13 #6 (0, 0)
	14 invokestatic (0, 0)
	15 org/apache/commons/math3/util/MathUtils.checkNotNull:(Ljava/lang/Object;)V (0, 0)
	17 aload_2 (2, 1)
	18 arraylength (2, 1)
	19 aload_3 (2, 1)
	20 arraylength (2, 1)
	21 if_icmpeq (2, 1)
	22 15 (2, 1)
	24 new (2, 1)
	25 org/apache/commons/math3/exception/DimensionMismatchException (2, 1)
	27 dup (2, 1)
	28 aload_2 (2, 1)
	29 arraylength (2, 1)
	30 aload_3 (2, 1)
	31 arraylength (2, 1)
	32 invokespecial (2, 1)
	33 org/apache/commons/math3/exception/DimensionMismatchException.<init>:(II)V (2, 1)
	35 athrow (2, 1)
	36 aload_2 (2, 1)
	37 arraylength (2, 1)
	38 aload (2, 1)
	39 #6 (2, 1)
	40 arraylength (2, 1)
	41 if_icmpeq (2, 1)
	42 16 (2, 1)
	44 new (2, 1)
	45 org/apache/commons/math3/exception/DimensionMismatchException (2, 1)
	47 dup (2, 1)
	48 aload_2 (2, 1)
	49 arraylength (2, 1)
	50 aload (2, 1)
	51 #6 (2, 1)
	52 arraylength (2, 1)
	53 invokespecial (2, 1)
	54 org/apache/commons/math3/exception/DimensionMismatchException.<init>:(II)V (2, 1)
	56 athrow (2, 1)
	57 iconst_0 (2, 4)
	58 istore (2, 4)
	59 #7 (2, 4)
	60 iload (2, 4)
	61 #7 (2, 4)
	62 aload_2 (2, 4)
	63 arraylength (2, 4)
	64 if_icmpge (2, 4)
	65 44 (2, 4)
	67 aload_3 (3, 1)
	68 iload (3, 1)
	69 #7 (3, 1)
	70 daload (3, 1)
	71 aload_2 (3, 1)
	72 iload (3, 1)
	73 #7 (3, 1)
	74 daload (3, 1)
	75 dcmpl (3, 1)
	76 ifge (3, 1)
	77 26 (3, 1)
	79 new (3, 1)
	80 org/apache/commons/math3/exception/NumberIsTooSmallException (3, 1)
	82 dup (3, 1)
	83 aload_3 (3, 1)
	84 iload (3, 1)
	85 #7 (3, 1)
	86 daload (3, 1)
	87 invokestatic (3, 1)
	88 java/lang/Double.valueOf:(D)Ljava/lang/Double; (3, 1)
	90 aload_2 (3, 1)
	91 iload (3, 1)
	92 #7 (3, 1)
	93 daload (3, 1)
	94 invokestatic (3, 1)
	95 java/lang/Double.valueOf:(D)Ljava/lang/Double; (3, 1)
	97 iconst_1 (3, 1)
	98 invokespecial (3, 1)
	99 org/apache/commons/math3/exception/NumberIsTooSmallException.<init>:(Ljava/lang/Number;Ljava/lang/Number;Z)V (3, 1)
	101 athrow (3, 1)
	102 iinc (3, 1)
	103 #7 (3, 1)
	104 -89 (3, 1)
	105 goto (3, 1)
	106 -45 (3, 1)
	108 aload_0 (2, 4)
	109 aload_1 (2, 4)
	110 putfield (2, 4)
	111 org/apache/commons/math3/optim/nonlinear/scalar/MultivariateFunctionPenaltyAdapter.bounded:Lorg/apache/commons/math3/analysis/MultivariateFunction; (2, 4)
	113 aload_0 (2, 4)
	114 aload_2 (2, 4)
	115 invokevirtual (2, 4)
	116 [D.clone:()Ljava/lang/Object; (2, 4)
	118 checkcast (2, 4)
	119 [D (2, 4)
	121 putfield (2, 4)
	122 org/apache/commons/math3/optim/nonlinear/scalar/MultivariateFunctionPenaltyAdapter.lower:[D (2, 4)
	124 aload_0 (2, 4)
	125 aload_3 (2, 4)
	126 invokevirtual (2, 4)
	127 [D.clone:()Ljava/lang/Object; (2, 4)
	129 checkcast (2, 4)
	130 [D (2, 4)
	132 putfield (2, 4)
	133 org/apache/commons/math3/optim/nonlinear/scalar/MultivariateFunctionPenaltyAdapter.upper:[D (2, 4)
	135 aload_0 (2, 4)
	136 dload (2, 4)
	137 #4 (2, 4)
	138 putfield (2, 4)
	139 org/apache/commons/math3/optim/nonlinear/scalar/MultivariateFunctionPenaltyAdapter.offset:D (2, 4)
	141 aload_0 (2, 4)
	142 aload (2, 4)
	143 #6 (2, 4)
	144 invokevirtual (2, 4)
	145 [D.clone:()Ljava/lang/Object; (2, 4)
	147 checkcast (2, 4)
	148 [D (2, 4)
	150 putfield (2, 4)
	151 org/apache/commons/math3/optim/nonlinear/scalar/MultivariateFunctionPenaltyAdapter.scale:[D (2, 4)
	153 return (0, 0)

Method: value
	0 iconst_0 (1, 4)
	1 istore_2 (1, 4)
	2 iload_2 (1, 4)
	3 aload_0 (1, 4)
	4 getfield (1, 4)
	5 org/apache/commons/math3/optim/nonlinear/scalar/MultivariateFunctionPenaltyAdapter.scale:[D (1, 4)
	7 arraylength (1, 4)
	8 if_icmpge (1, 4)
	9 154 (1, 4)
	11 aload_1 (2, 1)
	12 iload_2 (2, 1)
	13 daload (2, 1)
	14 aload_0 (2, 1)
	15 getfield (2, 1)
	16 org/apache/commons/math3/optim/nonlinear/scalar/MultivariateFunctionPenaltyAdapter.lower:[D (2, 1)
	18 iload_2 (2, 1)
	19 daload (2, 1)
	20 dcmpg (2, 1)
	21 iflt (2, 1)
	22 16 (2, 1)
	24 aload_1 (2, 1)
	25 iload_2 (2, 1)
	26 daload (2, 1)
	27 aload_0 (2, 1)
	28 getfield (2, 1)
	29 org/apache/commons/math3/optim/nonlinear/scalar/MultivariateFunctionPenaltyAdapter.upper:[D (2, 1)
	31 iload_2 (2, 1)
	32 daload (2, 1)
	33 dcmpl (2, 1)
	34 ifle (2, 1)
	35 122 (2, 1)
	37 dconst_0 (2, 1)
	38 dstore_3 (2, 1)
	39 iload_2 (3, 4)
	40 istore (3, 4)
	41 #5 (3, 4)
	42 iload (3, 4)
	43 #5 (3, 4)
	44 aload_0 (3, 4)
	45 getfield (3, 4)
	46 org/apache/commons/math3/optim/nonlinear/scalar/MultivariateFunctionPenaltyAdapter.scale:[D (3, 4)
	48 arraylength (3, 4)
	49 if_icmpge (3, 4)
	50 100 (3, 4)
	52 aload_1 (4, 1)
	53 iload (4, 1)
	54 #5 (4, 1)
	55 daload (4, 1)
	56 aload_0 (4, 1)
	57 getfield (4, 1)
	58 org/apache/commons/math3/optim/nonlinear/scalar/MultivariateFunctionPenaltyAdapter.lower:[D (4, 1)
	60 iload (4, 1)
	61 #5 (4, 1)
	62 daload (4, 1)
	63 dcmpg (4, 1)
	64 ifge (4, 1)
	65 28 (4, 1)
	67 aload_0 (4, 1)
	68 getfield (4, 1)
	69 org/apache/commons/math3/optim/nonlinear/scalar/MultivariateFunctionPenaltyAdapter.scale:[D (4, 1)
	71 iload (4, 1)
	72 #5 (4, 1)
	73 daload (4, 1)
	74 aload_0 (4, 1)
	75 getfield (4, 1)
	76 org/apache/commons/math3/optim/nonlinear/scalar/MultivariateFunctionPenaltyAdapter.lower:[D (4, 1)
	78 iload (4, 1)
	79 #5 (4, 1)
	80 daload (4, 1)
	81 aload_1 (4, 1)
	82 iload (4, 1)
	83 #5 (4, 1)
	84 daload (4, 1)
	85 dsub (4, 1)
	86 dmul (4, 1)
	87 dstore (4, 1)
	88 #6 (4, 1)
	89 goto (4, 1)
	90 46 (4, 1)
	92 aload_1 (4, 1)
	93 iload (4, 1)
	94 #5 (4, 1)
	95 daload (4, 1)
	96 aload_0 (4, 1)
	97 getfield (4, 1)
	98 org/apache/commons/math3/optim/nonlinear/scalar/MultivariateFunctionPenaltyAdapter.upper:[D (4, 1)
	100 iload (4, 1)
	101 #5 (4, 1)
	102 daload (4, 1)
	103 dcmpl (4, 1)
	104 ifle (4, 1)
	105 28 (4, 1)
	107 aload_0 (4, 1)
	108 getfield (4, 1)
	109 org/apache/commons/math3/optim/nonlinear/scalar/MultivariateFunctionPenaltyAdapter.scale:[D (4, 1)
	111 iload (4, 1)
	112 #5 (4, 1)
	113 daload (4, 1)
	114 aload_1 (4, 1)
	115 iload (4, 1)
	116 #5 (4, 1)
	117 daload (4, 1)
	118 aload_0 (4, 1)
	119 getfield (4, 1)
	120 org/apache/commons/math3/optim/nonlinear/scalar/MultivariateFunctionPenaltyAdapter.upper:[D (4, 1)
	122 iload (4, 1)
	123 #5 (4, 1)
	124 daload (4, 1)
	125 dsub (4, 1)
	126 dmul (4, 1)
	127 dstore (4, 1)
	128 #6 (4, 1)
	129 goto (4, 1)
	130 6 (4, 1)
	132 dconst_0 (4, 2)
	133 dstore (4, 2)
	134 #6 (4, 2)
	135 dload_3 (3, 4)
	136 dload (3, 4)
	137 #6 (3, 4)
	138 invokestatic (3, 4)
	139 org/apache/commons/math3/util/FastMath.sqrt:(D)D (3, 4)
	141 dadd (3, 4)
	142 dstore_3 (3, 4)
	143 iinc (3, 4)
	144 #5 (3, 4)
	145 -89 (3, 4)
	146 goto (3, 4)
	147 -104 (3, 4)
	149 aload_0 (2, 1)
	150 getfield (2, 1)
	151 org/apache/commons/math3/optim/nonlinear/scalar/MultivariateFunctionPenaltyAdapter.offset:D (2, 1)
	153 dload_3 (2, 1)
	154 dadd (2, 1)
	155 dreturn (2, 1)
	156 iinc (2, 1)
	157 #2 (2, 1)
	158 -89 (2, 1)
	159 goto (2, 1)
	160 -157 (2, 1)
	162 aload_0 (1, 4)
	163 getfield (1, 4)
	164 org/apache/commons/math3/optim/nonlinear/scalar/MultivariateFunctionPenaltyAdapter.bounded:Lorg/apache/commons/math3/analysis/MultivariateFunction; (1, 4)
	166 aload_1 (1, 4)
	167 invokeinterface (1, 4)
	168 org/apache/commons/math3/analysis/MultivariateFunction.org/apache/commons/math3/optim/nonlinear/scalar/MultivariateFunctionPenaltyAdapter (1, 4)
	170 0 (1, 4)
	172 dreturn (1, 4)

