Method: <init>
	0 aload_0 (0, 0)
	1 invokespecial (0, 0)
	2 java/lang/Object.<init>:()V (0, 0)
	4 aload_2 (0, 0)
	5 invokestatic (0, 0)
	6 org/apache/commons/math3/util/MathUtils.checkNotNull:(Ljava/lang/Object;)V (0, 0)
	8 aload_3 (0, 0)
	9 invokestatic (0, 0)
	10 org/apache/commons/math3/util/MathUtils.checkNotNull:(Ljava/lang/Object;)V (0, 0)
	12 aload_2 (1, 1)
	13 arraylength (1, 1)
	14 aload_3 (1, 1)
	15 arraylength (1, 1)
	16 if_icmpeq (1, 1)
	17 15 (1, 1)
	19 new (1, 1)
	20 org/apache/commons/math3/exception/DimensionMismatchException (1, 1)
	22 dup (1, 1)
	23 aload_2 (1, 1)
	24 arraylength (1, 1)
	25 aload_3 (1, 1)
	26 arraylength (1, 1)
	27 invokespecial (1, 1)
	28 org/apache/commons/math3/exception/DimensionMismatchException.<init>:(II)V (1, 1)
	30 athrow (1, 1)
	31 iconst_0 (1, 4)
	32 istore (1, 4)
	33 #4 (1, 4)
	34 iload (1, 4)
	35 #4 (1, 4)
	36 aload_2 (1, 4)
	37 arraylength (1, 4)
	38 if_icmpge (1, 4)
	39 44 (1, 4)
	41 aload_3 (3, 1)
	42 iload (3, 1)
	43 #4 (3, 1)
	44 daload (3, 1)
	45 aload_2 (3, 1)
	46 iload (3, 1)
	47 #4 (3, 1)
	48 daload (3, 1)
	49 dcmpl (3, 1)
	50 ifge (3, 1)
	51 26 (3, 1)
	53 new (3, 1)
	54 org/apache/commons/math3/exception/NumberIsTooSmallException (3, 1)
	56 dup (3, 1)
	57 aload_3 (3, 1)
	58 iload (3, 1)
	59 #4 (3, 1)
	60 daload (3, 1)
	61 invokestatic (3, 1)
	62 java/lang/Double.valueOf:(D)Ljava/lang/Double; (3, 1)
	64 aload_2 (3, 1)
	65 iload (3, 1)
	66 #4 (3, 1)
	67 daload (3, 1)
	68 invokestatic (3, 1)
	69 java/lang/Double.valueOf:(D)Ljava/lang/Double; (3, 1)
	71 iconst_1 (3, 1)
	72 invokespecial (3, 1)
	73 org/apache/commons/math3/exception/NumberIsTooSmallException.<init>:(Ljava/lang/Number;Ljava/lang/Number;Z)V (3, 1)
	75 athrow (3, 1)
	76 iinc (3, 1)
	77 #4 (3, 1)
	78 -89 (3, 1)
	79 goto (3, 1)
	80 -45 (3, 1)
	82 aload_0 (2, 4)
	83 aload_1 (2, 4)
	84 putfield (2, 4)
	85 org/apache/commons/math3/optim/nonlinear/scalar/MultivariateFunctionMappingAdapter.bounded:Lorg/apache/commons/math3/analysis/MultivariateFunction; (2, 4)
	87 aload_0 (2, 4)
	88 aload_2 (2, 4)
	89 arraylength (2, 4)
	90 anewarray (2, 4)
	91 org/apache/commons/math3/optim/nonlinear/scalar/MultivariateFunctionMappingAdapter$Mapper (2, 4)
	93 putfield (2, 4)
	94 org/apache/commons/math3/optim/nonlinear/scalar/MultivariateFunctionMappingAdapter.mappers:[Lorg/apache/commons/math3/optim/nonlinear/scalar/MultivariateFunctionMappingAdapter$Mapper; (2, 4)
	96 iconst_0 (3, 4)
	97 istore (3, 4)
	98 #4 (3, 4)
	99 iload (3, 4)
	100 #4 (3, 4)
	101 aload_0 (3, 4)
	102 getfield (3, 4)
	103 org/apache/commons/math3/optim/nonlinear/scalar/MultivariateFunctionMappingAdapter.mappers:[Lorg/apache/commons/math3/optim/nonlinear/scalar/MultivariateFunctionMappingAdapter$Mapper; (3, 4)
	105 arraylength (3, 4)
	106 if_icmpge (3, 4)
	107 121 (3, 4)
	109 aload_2 (4, 1)
	110 iload (4, 1)
	111 #4 (4, 1)
	112 daload (4, 1)
	113 invokestatic (4, 1)
	114 java/lang/Double.isInfinite:(D)Z (4, 1)
	116 ifeq (4, 1)
	117 52 (4, 1)
	119 aload_3 (5, 1)
	120 iload (5, 1)
	121 #4 (5, 1)
	122 daload (5, 1)
	123 invokestatic (5, 1)
	124 java/lang/Double.isInfinite:(D)Z (5, 1)
	126 ifeq (5, 1)
	127 21 (5, 1)
	129 aload_0 (6, 4)
	130 getfield (6, 4)
	131 org/apache/commons/math3/optim/nonlinear/scalar/MultivariateFunctionMappingAdapter.mappers:[Lorg/apache/commons/math3/optim/nonlinear/scalar/MultivariateFunctionMappingAdapter$Mapper; (6, 4)
	133 iload (6, 4)
	134 #4 (6, 4)
	135 new (6, 4)
	136 org/apache/commons/math3/optim/nonlinear/scalar/MultivariateFunctionMappingAdapter$NoBoundsMapper (6, 4)
	138 dup (6, 4)
	139 aconst_null (6, 4)
	140 invokespecial (6, 4)
	141 org/apache/commons/math3/optim/nonlinear/scalar/MultivariateFunctionMappingAdapter$NoBoundsMapper.<init>:(Lorg/apache/commons/math3/optim/nonlinear/scalar/MultivariateFunctionMappingAdapter$1;)V (6, 4)
	143 aastore (6, 4)
	144 goto (6, 4)
	145 77 (6, 4)
	147 aload_0 (7, 2)
	148 getfield (7, 2)
	149 org/apache/commons/math3/optim/nonlinear/scalar/MultivariateFunctionMappingAdapter.mappers:[Lorg/apache/commons/math3/optim/nonlinear/scalar/MultivariateFunctionMappingAdapter$Mapper; (7, 2)
	151 iload (7, 2)
	152 #4 (7, 2)
	153 new (7, 2)
	154 org/apache/commons/math3/optim/nonlinear/scalar/MultivariateFunctionMappingAdapter$UpperBoundMapper (7, 2)
	156 dup (7, 2)
	157 aload_3 (7, 2)
	158 iload (7, 2)
	159 #4 (7, 2)
	160 daload (7, 2)
	161 invokespecial (7, 2)
	162 org/apache/commons/math3/optim/nonlinear/scalar/MultivariateFunctionMappingAdapter$UpperBoundMapper.<init>:(D)V (7, 2)
	164 aastore (7, 2)
	165 goto (7, 2)
	166 56 (7, 2)
	168 aload_3 (6, 1)
	169 iload (6, 1)
	170 #4 (6, 1)
	171 daload (6, 1)
	172 invokestatic (6, 1)
	173 java/lang/Double.isInfinite:(D)Z (6, 1)
	175 ifeq (6, 1)
	176 24 (6, 1)
	178 aload_0 (6, 1)
	179 getfield (6, 1)
	180 org/apache/commons/math3/optim/nonlinear/scalar/MultivariateFunctionMappingAdapter.mappers:[Lorg/apache/commons/math3/optim/nonlinear/scalar/MultivariateFunctionMappingAdapter$Mapper; (6, 1)
	182 iload (6, 1)
	183 #4 (6, 1)
	184 new (6, 1)
	185 org/apache/commons/math3/optim/nonlinear/scalar/MultivariateFunctionMappingAdapter$LowerBoundMapper (6, 1)
	187 dup (6, 1)
	188 aload_2 (6, 1)
	189 iload (6, 1)
	190 #4 (6, 1)
	191 daload (6, 1)
	192 invokespecial (6, 1)
	193 org/apache/commons/math3/optim/nonlinear/scalar/MultivariateFunctionMappingAdapter$LowerBoundMapper.<init>:(D)V (6, 1)
	195 aastore (6, 1)
	196 goto (6, 1)
	197 25 (6, 1)
	199 aload_0 (7, 2)
	200 getfield (7, 2)
	201 org/apache/commons/math3/optim/nonlinear/scalar/MultivariateFunctionMappingAdapter.mappers:[Lorg/apache/commons/math3/optim/nonlinear/scalar/MultivariateFunctionMappingAdapter$Mapper; (7, 2)
	203 iload (7, 2)
	204 #4 (7, 2)
	205 new (7, 2)
	206 org/apache/commons/math3/optim/nonlinear/scalar/MultivariateFunctionMappingAdapter$LowerUpperBoundMapper (7, 2)
	208 dup (7, 2)
	209 aload_2 (7, 2)
	210 iload (7, 2)
	211 #4 (7, 2)
	212 daload (7, 2)
	213 aload_3 (7, 2)
	214 iload (7, 2)
	215 #4 (7, 2)
	216 daload (7, 2)
	217 invokespecial (7, 2)
	218 org/apache/commons/math3/optim/nonlinear/scalar/MultivariateFunctionMappingAdapter$LowerUpperBoundMapper.<init>:(DD)V (7, 2)
	220 aastore (7, 2)
	221 iinc (7, 2)
	222 #4 (7, 2)
	223 -89 (7, 2)
	224 goto (7, 2)
	225 -125 (7, 2)
	227 return (3, 4)

Method: unboundedToBounded
	0 aload_0 (0, 0)
	1 getfield (0, 0)
	2 org/apache/commons/math3/optim/nonlinear/scalar/MultivariateFunctionMappingAdapter.mappers:[Lorg/apache/commons/math3/optim/nonlinear/scalar/MultivariateFunctionMappingAdapter$Mapper; (0, 0)
	4 arraylength (0, 0)
	5 newarray (0, 0)
	6 7 (0, 0)
	7 astore_2 (0, 0)
	8 iconst_0 (1, 4)
	9 istore_3 (1, 4)
	10 iload_3 (1, 4)
	11 aload_0 (1, 4)
	12 getfield (1, 4)
	13 org/apache/commons/math3/optim/nonlinear/scalar/MultivariateFunctionMappingAdapter.mappers:[Lorg/apache/commons/math3/optim/nonlinear/scalar/MultivariateFunctionMappingAdapter$Mapper; (1, 4)
	15 arraylength (1, 4)
	16 if_icmpge (1, 4)
	17 26 (1, 4)
	19 aload_2 (1, 4)
	20 iload_3 (1, 4)
	21 aload_0 (1, 4)
	22 getfield (1, 4)
	23 org/apache/commons/math3/optim/nonlinear/scalar/MultivariateFunctionMappingAdapter.mappers:[Lorg/apache/commons/math3/optim/nonlinear/scalar/MultivariateFunctionMappingAdapter$Mapper; (1, 4)
	25 iload_3 (1, 4)
	26 aaload (1, 4)
	27 aload_1 (1, 4)
	28 iload_3 (1, 4)
	29 daload (1, 4)
	30 invokeinterface (1, 4)
	31 org/apache/commons/math3/optim/nonlinear/scalar/MultivariateFunctionMappingAdapter$Mapper.boundedToUnbounded:(D)D (1, 4)
	33 0 (1, 4)
	35 dastore (1, 4)
	36 iinc (1, 4)
	37 #3 (1, 4)
	38 -89 (1, 4)
	39 goto (1, 4)
	40 -29 (1, 4)
	42 aload_2 (0, 0)
	43 areturn (0, 0)

Method: boundedToUnbounded
	0 aload_0 (0, 0)
	1 getfield (0, 0)
	2 org/apache/commons/math3/optim/nonlinear/scalar/MultivariateFunctionMappingAdapter.mappers:[Lorg/apache/commons/math3/optim/nonlinear/scalar/MultivariateFunctionMappingAdapter$Mapper; (0, 0)
	4 arraylength (0, 0)
	5 newarray (0, 0)
	6 7 (0, 0)
	7 astore_2 (0, 0)
	8 iconst_0 (1, 4)
	9 istore_3 (1, 4)
	10 iload_3 (1, 4)
	11 aload_0 (1, 4)
	12 getfield (1, 4)
	13 org/apache/commons/math3/optim/nonlinear/scalar/MultivariateFunctionMappingAdapter.mappers:[Lorg/apache/commons/math3/optim/nonlinear/scalar/MultivariateFunctionMappingAdapter$Mapper; (1, 4)
	15 arraylength (1, 4)
	16 if_icmpge (1, 4)
	17 26 (1, 4)
	19 aload_2 (1, 4)
	20 iload_3 (1, 4)
	21 aload_0 (1, 4)
	22 getfield (1, 4)
	23 org/apache/commons/math3/optim/nonlinear/scalar/MultivariateFunctionMappingAdapter.mappers:[Lorg/apache/commons/math3/optim/nonlinear/scalar/MultivariateFunctionMappingAdapter$Mapper; (1, 4)
	25 iload_3 (1, 4)
	26 aaload (1, 4)
	27 aload_1 (1, 4)
	28 iload_3 (1, 4)
	29 daload (1, 4)
	30 invokeinterface (1, 4)
	31 org/apache/commons/math3/optim/nonlinear/scalar/MultivariateFunctionMappingAdapter$Mapper.unboundedToBounded:([D)[D (1, 4)
	33 0 (1, 4)
	35 dastore (1, 4)
	36 iinc (1, 4)
	37 #3 (1, 4)
	38 -89 (1, 4)
	39 goto (1, 4)
	40 -29 (1, 4)
	42 aload_2 (0, 0)
	43 areturn (0, 0)

Method: value
	0 aload_0 (0, 0)
	1 getfield (0, 0)
	2 org/apache/commons/math3/optim/nonlinear/scalar/MultivariateFunctionMappingAdapter.bounded:Lorg/apache/commons/math3/analysis/MultivariateFunction; (0, 0)
	4 aload_0 (0, 0)
	5 aload_1 (0, 0)
	6 invokevirtual (0, 0)
	7 org/apache/commons/math3/optim/nonlinear/scalar/MultivariateFunctionMappingAdapter.unboundedToBounded:([D)[D (0, 0)
	9 invokeinterface (0, 0)
	10 org/apache/commons/math3/analysis/MultivariateFunction.org/apache/commons/math3/optim/nonlinear/scalar/MultivariateFunctionMappingAdapter (0, 0)
	12 0 (0, 0)
	14 dreturn (0, 0)

