Method: <init>
	0 aload_0 (0, 0)
	1 invokespecial (0, 0)
	2 java/lang/Object.<init>:()V (0, 0)
	4 aload_0 (0, 0)
	5 new (0, 0)
	6 java/util/HashMap (0, 0)
	8 dup (0, 0)
	9 invokespecial (0, 0)
	10 java/util/HashMap.<init>:()V (0, 0)
	12 putfield (0, 0)
	13 org/apache/commons/math3/ml/neuralnet/twod/util/LocationFinder.locations:Ljava/util/Map; (0, 0)
	15 aload_1 (1, 1)
	16 invokevirtual (1, 1)
	17 org/apache/commons/math3/ml/neuralnet/twod/NeuronSquareMesh2D.getNumberOfRows:()I (1, 1)
	19 istore_2 (1, 1)
	20 aload_1 (1, 1)
	21 invokevirtual (1, 1)
	22 org/apache/commons/math3/ml/neuralnet/twod/NeuronSquareMesh2D.getNumberOfColumns:()I (1, 1)
	24 istore_3 (1, 1)
	25 iconst_0 (3, 4)
	26 istore (3, 4)
	27 #4 (3, 4)
	28 iload (3, 4)
	29 #4 (3, 4)
	30 iload_2 (3, 4)
	31 if_icmpge (3, 4)
	32 85 (3, 4)
	34 iconst_0 (4, 4)
	35 istore (4, 4)
	36 #5 (4, 4)
	37 iload (4, 4)
	38 #5 (4, 4)
	39 iload_3 (4, 4)
	40 if_icmpge (4, 4)
	41 70 (4, 4)
	43 aload_1 (4, 1)
	44 iload (4, 1)
	45 #4 (4, 1)
	46 iload (4, 1)
	47 #5 (4, 1)
	48 invokevirtual (4, 1)
	49 org/apache/commons/math3/ml/neuralnet/twod/NeuronSquareMesh2D.getNeuron:(II)Lorg/apache/commons/math3/ml/neuralnet/Neuron; (4, 1)
	51 invokevirtual (4, 1)
	52 org/apache/commons/math3/ml/neuralnet/Neuron.getIdentifier:()J (4, 1)
	54 invokestatic (4, 1)
	55 java/lang/Long.valueOf:(J)Ljava/lang/Long; (4, 1)
	57 astore (4, 1)
	58 #6 (4, 1)
	59 aload_0 (5, 1)
	60 getfield (5, 1)
	61 org/apache/commons/math3/ml/neuralnet/twod/util/LocationFinder.locations:Ljava/util/Map; (5, 1)
	63 aload (5, 1)
	64 #6 (5, 1)
	65 invokeinterface (5, 1)
	66 java/util/Map.org/apache/commons/math3/exception/MathIllegalStateException (5, 1)
	68 0 (5, 1)
	70 ifnull (5, 1)
	71 11 (5, 1)
	73 new (5, 1)
	74 org/apache/commons/math3/exception/MathIllegalStateException (5, 1)
	76 dup (5, 1)
	77 invokespecial (5, 1)
	78 org/apache/commons/math3/exception/MathIllegalStateException.<init>:()V (5, 1)
	80 athrow (5, 1)
	81 aload_0 (4, 1)
	82 getfield (4, 1)
	83 org/apache/commons/math3/ml/neuralnet/twod/util/LocationFinder.locations:Ljava/util/Map; (4, 1)
	85 aload (4, 1)
	86 #6 (4, 1)
	87 new (4, 1)
	88 org/apache/commons/math3/ml/neuralnet/twod/util/LocationFinder$Location (4, 1)
	90 dup (4, 1)
	91 iload (4, 1)
	92 #4 (4, 1)
	93 iload (4, 1)
	94 #5 (4, 1)
	95 invokespecial (4, 1)
	96 org/apache/commons/math3/ml/neuralnet/twod/util/LocationFinder$Location.<init>:(II)V (4, 1)
	98 invokeinterface (4, 1)
	99 java/util/Map.org/apache/commons/math3/ml/neuralnet/twod/util/LocationFinder (4, 1)
	101 0 (4, 1)
	103 pop (4, 1)
	104 iinc (4, 1)
	105 #5 (4, 1)
	106 -89 (4, 1)
	107 goto (4, 1)
	108 -70 (4, 1)
	110 iinc (4, 1)
	111 #4 (4, 1)
	112 -89 (4, 1)
	113 goto (4, 1)
	114 -85 (4, 1)
	116 return (1, 1)

Method: getLocation
	0 aload_0 (0, 1)
	1 getfield (0, 1)
	2 org/apache/commons/math3/ml/neuralnet/twod/util/LocationFinder.locations:Ljava/util/Map; (0, 1)
	4 aload_1 (0, 1)
	5 invokevirtual (0, 1)
	6 org/apache/commons/math3/ml/neuralnet/Neuron.getIdentifier:()J (0, 1)
	8 invokestatic (0, 1)
	9 java/lang/Long.valueOf:(J)Ljava/lang/Long; (0, 1)
	11 invokeinterface (0, 1)
	12 java/util/Map.org/apache/commons/math3/exception/MathIllegalStateException (0, 1)
	14 0 (0, 1)
	16 checkcast (0, 1)
	17 org/apache/commons/math3/ml/neuralnet/twod/util/LocationFinder$Location (0, 1)
	19 areturn (0, 1)

