Method: <init>
	0 aload_0 (0, 0)
	1 invokespecial (0, 0)
	2 java/lang/Object.<init>:()V (0, 0)
	4 aload_0 (0, 0)
	5 iload_1 (0, 0)
	6 putfield (0, 0)
	7 org/apache/commons/math3/ml/neuralnet/twod/util/UnifiedDistanceMatrix.individualDistances:Z (0, 0)
	9 aload_0 (0, 0)
	10 aload_2 (0, 0)
	11 putfield (0, 0)
	12 org/apache/commons/math3/ml/neuralnet/twod/util/UnifiedDistanceMatrix.distance:Lorg/apache/commons/math3/ml/distance/DistanceMeasure; (0, 0)
	14 return (0, 0)

Method: computeImage
	0 aload_0 (1, 1)
	1 getfield (1, 1)
	2 org/apache/commons/math3/ml/neuralnet/twod/util/UnifiedDistanceMatrix.individualDistances:Z (1, 1)
	4 ifeq (1, 1)
	5 9 (1, 1)
	7 aload_0 (1, 1)
	8 aload_1 (1, 1)
	9 invokespecial (1, 1)
	10 org/apache/commons/math3/ml/neuralnet/twod/util/UnifiedDistanceMatrix.individualDistances:(Lorg/apache/commons/math3/ml/neuralnet/twod/NeuronSquareMesh2D;)[[D (1, 1)
	12 areturn (1, 1)
	13 aload_0 (1, 2)
	14 aload_1 (1, 2)
	15 invokespecial (1, 2)
	16 org/apache/commons/math3/ml/neuralnet/twod/util/UnifiedDistanceMatrix.averageDistances:(Lorg/apache/commons/math3/ml/neuralnet/twod/NeuronSquareMesh2D;)[[D (1, 2)
	18 areturn (1, 2)

Method: individualDistances
	0 aload_1 (0, 0)
	1 invokevirtual (0, 0)
	2 org/apache/commons/math3/ml/neuralnet/twod/NeuronSquareMesh2D.getNumberOfRows:()I (0, 0)
	4 istore_2 (0, 0)
	5 aload_1 (0, 0)
	6 invokevirtual (0, 0)
	7 org/apache/commons/math3/ml/neuralnet/twod/NeuronSquareMesh2D.getNumberOfColumns:()I (0, 0)
	9 istore_3 (0, 0)
	10 iload_2 (0, 0)
	11 iconst_2 (0, 0)
	12 imul (0, 0)
	13 iconst_1 (0, 0)
	14 iadd (0, 0)
	15 iload_3 (0, 0)
	16 iconst_2 (0, 0)
	17 imul (0, 0)
	18 iconst_1 (0, 0)
	19 iadd (0, 0)
	20 multianewarray (0, 0)
	21 [[D (0, 0)
	23 58 (0, 0)
	24 astore (0, 0)
	25 #4 (0, 0)
	26 iconst_0 (1, 4)
	27 istore (1, 4)
	28 #5 (1, 4)
	29 iload (1, 4)
	30 #5 (1, 4)
	31 iload_2 (1, 4)
	32 if_icmpge (1, 4)
	33 147 (1, 4)
	35 iconst_2 (1, 4)
	36 iload (1, 4)
	37 #5 (1, 4)
	38 imul (1, 4)
	39 iconst_1 (1, 4)
	40 iadd (1, 4)
	41 istore (1, 4)
	42 #6 (1, 4)
	43 iconst_0 (2, 4)
	44 istore (2, 4)
	45 #7 (2, 4)
	46 iload (2, 4)
	47 #7 (2, 4)
	48 iload_3 (2, 4)
	49 if_icmpge (2, 4)
	50 124 (2, 4)
	52 iconst_2 (2, 4)
	53 iload (2, 4)
	54 #7 (2, 4)
	55 imul (2, 4)
	56 iconst_1 (2, 4)
	57 iadd (2, 4)
	58 istore (2, 4)
	59 #8 (2, 4)
	60 aload_1 (2, 4)
	61 iload (2, 4)
	62 #5 (2, 4)
	63 iload (2, 4)
	64 #7 (2, 4)
	65 invokevirtual (2, 4)
	66 org/apache/commons/math3/ml/neuralnet/twod/NeuronSquareMesh2D.getNeuron:(II)Lorg/apache/commons/math3/ml/neuralnet/Neuron; (2, 4)
	68 invokevirtual (2, 4)
	69 org/apache/commons/math3/ml/neuralnet/Neuron.getFeatures:()[D (2, 4)
	71 astore (2, 4)
	72 #9 (2, 4)
	73 aload_1 (2, 4)
	74 iload (2, 4)
	75 #5 (2, 4)
	76 iload (2, 4)
	77 #7 (2, 4)
	78 getstatic (2, 4)
	79 org/apache/commons/math3/ml/neuralnet/twod/NeuronSquareMesh2D$HorizontalDirection.RIGHT:Lorg/apache/commons/math3/ml/neuralnet/twod/NeuronSquareMesh2D$HorizontalDirection; (2, 4)
	81 getstatic (2, 4)
	82 org/apache/commons/math3/ml/neuralnet/twod/NeuronSquareMesh2D$VerticalDirection.CENTER:Lorg/apache/commons/math3/ml/neuralnet/twod/NeuronSquareMesh2D$VerticalDirection; (2, 4)
	84 invokevirtual (2, 4)
	85 org/apache/commons/math3/ml/neuralnet/twod/NeuronSquareMesh2D.getNeuron:(IILorg/apache/commons/math3/ml/neuralnet/twod/NeuronSquareMesh2D$HorizontalDirection;Lorg/apache/commons/math3/ml/neuralnet/twod/NeuronSquareMesh2D$VerticalDirection;)Lorg/apache/commons/math3/ml/neuralnet/Neuron; (2, 4)
	87 astore (2, 4)
	88 #10 (2, 4)
	89 aload (3, 1)
	90 #10 (3, 1)
	91 ifnull (3, 1)
	92 29 (3, 1)
	94 aload (3, 1)
	95 #4 (3, 1)
	96 iload (3, 1)
	97 #6 (3, 1)
	98 aaload (3, 1)
	99 iload (3, 1)
	100 #8 (3, 1)
	101 iconst_1 (3, 1)
	102 iadd (3, 1)
	103 aload_0 (3, 1)
	104 getfield (3, 1)
	105 org/apache/commons/math3/ml/neuralnet/twod/util/UnifiedDistanceMatrix.distance:Lorg/apache/commons/math3/ml/distance/DistanceMeasure; (3, 1)
	107 aload (3, 1)
	108 #9 (3, 1)
	109 aload (3, 1)
	110 #10 (3, 1)
	111 invokevirtual (3, 1)
	112 org/apache/commons/math3/ml/neuralnet/Neuron.getFeatures:()[D (3, 1)
	114 invokeinterface (3, 1)
	115 org/apache/commons/math3/ml/distance/DistanceMeasure.CENTER:Lorg/apache/commons/math3/ml/neuralnet/twod/NeuronSquareMesh2D$HorizontalDirection; (3, 1)
	117 0 (3, 1)
	119 dastore (3, 1)
	120 aload_1 (2, 4)
	121 iload (2, 4)
	122 #5 (2, 4)
	123 iload (2, 4)
	124 #7 (2, 4)
	125 getstatic (2, 4)
	126 org/apache/commons/math3/ml/neuralnet/twod/NeuronSquareMesh2D$HorizontalDirection.CENTER:Lorg/apache/commons/math3/ml/neuralnet/twod/NeuronSquareMesh2D$HorizontalDirection; (2, 4)
	128 getstatic (2, 4)
	129 org/apache/commons/math3/ml/neuralnet/twod/NeuronSquareMesh2D$VerticalDirection.DOWN:Lorg/apache/commons/math3/ml/neuralnet/twod/NeuronSquareMesh2D$VerticalDirection; (2, 4)
	131 invokevirtual (2, 4)
	132 org/apache/commons/math3/ml/neuralnet/twod/NeuronSquareMesh2D.getNeuron:(IILorg/apache/commons/math3/ml/neuralnet/twod/NeuronSquareMesh2D$HorizontalDirection;Lorg/apache/commons/math3/ml/neuralnet/twod/NeuronSquareMesh2D$VerticalDirection;)Lorg/apache/commons/math3/ml/neuralnet/Neuron; (2, 4)
	134 astore (2, 4)
	135 #10 (2, 4)
	136 aload (3, 1)
	137 #10 (3, 1)
	138 ifnull (3, 1)
	139 29 (3, 1)
	141 aload (3, 1)
	142 #4 (3, 1)
	143 iload (3, 1)
	144 #6 (3, 1)
	145 iconst_1 (3, 1)
	146 iadd (3, 1)
	147 aaload (3, 1)
	148 iload (3, 1)
	149 #8 (3, 1)
	150 aload_0 (3, 1)
	151 getfield (3, 1)
	152 org/apache/commons/math3/ml/neuralnet/twod/util/UnifiedDistanceMatrix.distance:Lorg/apache/commons/math3/ml/distance/DistanceMeasure; (3, 1)
	154 aload (3, 1)
	155 #9 (3, 1)
	156 aload (3, 1)
	157 #10 (3, 1)
	158 invokevirtual (3, 1)
	159 org/apache/commons/math3/ml/neuralnet/Neuron.getFeatures:()[D (3, 1)
	161 invokeinterface (3, 1)
	162 org/apache/commons/math3/ml/distance/DistanceMeasure.CENTER:Lorg/apache/commons/math3/ml/neuralnet/twod/NeuronSquareMesh2D$HorizontalDirection; (3, 1)
	164 0 (3, 1)
	166 dastore (3, 1)
	167 iinc (3, 1)
	168 #7 (3, 1)
	169 -89 (3, 1)
	170 goto (3, 1)
	171 -124 (3, 1)
	173 iinc (3, 1)
	174 #5 (3, 1)
	175 -89 (3, 1)
	176 goto (3, 1)
	177 -147 (3, 1)
	179 iconst_0 (3, 4)
	180 istore (3, 4)
	181 #5 (3, 4)
	182 iload (3, 4)
	183 #5 (3, 4)
	184 iload_2 (3, 4)
	185 if_icmpge (3, 4)
	186 184 (3, 4)
	188 iconst_2 (3, 4)
	189 iload (3, 4)
	190 #5 (3, 4)
	191 imul (3, 4)
	192 iconst_1 (3, 4)
	193 iadd (3, 4)
	194 istore (3, 4)
	195 #6 (3, 4)
	196 iconst_0 (4, 4)
	197 istore (4, 4)
	198 #7 (4, 4)
	199 iload (4, 4)
	200 #7 (4, 4)
	201 iload_3 (4, 4)
	202 if_icmpge (4, 4)
	203 161 (4, 4)
	205 iconst_2 (4, 4)
	206 iload (4, 4)
	207 #7 (4, 4)
	208 imul (4, 4)
	209 iconst_1 (4, 4)
	210 iadd (4, 4)
	211 istore (4, 4)
	212 #8 (4, 4)
	213 aload_1 (4, 4)
	214 iload (4, 4)
	215 #5 (4, 4)
	216 iload (4, 4)
	217 #7 (4, 4)
	218 invokevirtual (4, 4)
	219 org/apache/commons/math3/ml/neuralnet/twod/NeuronSquareMesh2D.getNeuron:(II)Lorg/apache/commons/math3/ml/neuralnet/Neuron; (4, 4)
	221 astore (4, 4)
	222 #9 (4, 4)
	223 aload_1 (4, 4)
	224 iload (4, 4)
	225 #5 (4, 4)
	226 iload (4, 4)
	227 #7 (4, 4)
	228 getstatic (4, 4)
	229 org/apache/commons/math3/ml/neuralnet/twod/NeuronSquareMesh2D$HorizontalDirection.RIGHT:Lorg/apache/commons/math3/ml/neuralnet/twod/NeuronSquareMesh2D$HorizontalDirection; (4, 4)
	231 getstatic (4, 4)
	232 org/apache/commons/math3/ml/neuralnet/twod/NeuronSquareMesh2D$VerticalDirection.CENTER:Lorg/apache/commons/math3/ml/neuralnet/twod/NeuronSquareMesh2D$VerticalDirection; (4, 4)
	234 invokevirtual (4, 4)
	235 org/apache/commons/math3/ml/neuralnet/twod/NeuronSquareMesh2D.getNeuron:(IILorg/apache/commons/math3/ml/neuralnet/twod/NeuronSquareMesh2D$HorizontalDirection;Lorg/apache/commons/math3/ml/neuralnet/twod/NeuronSquareMesh2D$VerticalDirection;)Lorg/apache/commons/math3/ml/neuralnet/Neuron; (4, 4)
	237 astore (4, 4)
	238 #10 (4, 4)
	239 aload_1 (4, 4)
	240 iload (4, 4)
	241 #5 (4, 4)
	242 iload (4, 4)
	243 #7 (4, 4)
	244 getstatic (4, 4)
	245 org/apache/commons/math3/ml/neuralnet/twod/NeuronSquareMesh2D$HorizontalDirection.CENTER:Lorg/apache/commons/math3/ml/neuralnet/twod/NeuronSquareMesh2D$HorizontalDirection; (4, 4)
	247 getstatic (4, 4)
	248 org/apache/commons/math3/ml/neuralnet/twod/NeuronSquareMesh2D$VerticalDirection.DOWN:Lorg/apache/commons/math3/ml/neuralnet/twod/NeuronSquareMesh2D$VerticalDirection; (4, 4)
	250 invokevirtual (4, 4)
	251 org/apache/commons/math3/ml/neuralnet/twod/NeuronSquareMesh2D.getNeuron:(IILorg/apache/commons/math3/ml/neuralnet/twod/NeuronSquareMesh2D$HorizontalDirection;Lorg/apache/commons/math3/ml/neuralnet/twod/NeuronSquareMesh2D$VerticalDirection;)Lorg/apache/commons/math3/ml/neuralnet/Neuron; (4, 4)
	253 astore (4, 4)
	254 #11 (4, 4)
	255 aload_1 (4, 4)
	256 iload (4, 4)
	257 #5 (4, 4)
	258 iload (4, 4)
	259 #7 (4, 4)
	260 getstatic (4, 4)
	261 org/apache/commons/math3/ml/neuralnet/twod/NeuronSquareMesh2D$HorizontalDirection.RIGHT:Lorg/apache/commons/math3/ml/neuralnet/twod/NeuronSquareMesh2D$HorizontalDirection; (4, 4)
	263 getstatic (4, 4)
	264 org/apache/commons/math3/ml/neuralnet/twod/NeuronSquareMesh2D$VerticalDirection.DOWN:Lorg/apache/commons/math3/ml/neuralnet/twod/NeuronSquareMesh2D$VerticalDirection; (4, 4)
	266 invokevirtual (4, 4)
	267 org/apache/commons/math3/ml/neuralnet/twod/NeuronSquareMesh2D.getNeuron:(IILorg/apache/commons/math3/ml/neuralnet/twod/NeuronSquareMesh2D$HorizontalDirection;Lorg/apache/commons/math3/ml/neuralnet/twod/NeuronSquareMesh2D$VerticalDirection;)Lorg/apache/commons/math3/ml/neuralnet/Neuron; (4, 4)
	269 astore (4, 4)
	270 #12 (4, 4)
	271 aload (4, 4)
	272 #12 (4, 4)
	273 ifnonnull (4, 4)
	274 7 (4, 4)
	276 dconst_0 (4, 4)
	277 goto (4, 4)
	278 22 (4, 4)
	280 aload_0 (4, 4)
	281 getfield (4, 4)
	282 org/apache/commons/math3/ml/neuralnet/twod/util/UnifiedDistanceMatrix.distance:Lorg/apache/commons/math3/ml/distance/DistanceMeasure; (4, 4)
	284 aload (4, 4)
	285 #9 (4, 4)
	286 invokevirtual (4, 4)
	287 org/apache/commons/math3/ml/neuralnet/Neuron.getFeatures:()[D (4, 4)
	289 aload (4, 4)
	290 #12 (4, 4)
	291 invokevirtual (4, 4)
	292 org/apache/commons/math3/ml/neuralnet/Neuron.getFeatures:()[D (4, 4)
	294 invokeinterface (4, 4)
	295 org/apache/commons/math3/ml/distance/DistanceMeasure.CENTER:Lorg/apache/commons/math3/ml/neuralnet/twod/NeuronSquareMesh2D$HorizontalDirection; (4, 4)
	297 0 (4, 4)
	299 dstore (4, 4)
	300 #13 (4, 4)
	301 aload (4, 4)
	302 #10 (4, 4)
	303 ifnull (4, 4)
	304 8 (4, 4)
	306 aload (4, 4)
	307 #11 (4, 4)
	308 ifnonnull (4, 4)
	309 7 (4, 4)
	311 dconst_0 (4, 4)
	312 goto (4, 4)
	313 22 (4, 4)
	315 aload_0 (4, 4)
	316 getfield (4, 4)
	317 org/apache/commons/math3/ml/neuralnet/twod/util/UnifiedDistanceMatrix.distance:Lorg/apache/commons/math3/ml/distance/DistanceMeasure; (4, 4)
	319 aload (4, 4)
	320 #10 (4, 4)
	321 invokevirtual (4, 4)
	322 org/apache/commons/math3/ml/neuralnet/Neuron.getFeatures:()[D (4, 4)
	324 aload (4, 4)
	325 #11 (4, 4)
	326 invokevirtual (4, 4)
	327 org/apache/commons/math3/ml/neuralnet/Neuron.getFeatures:()[D (4, 4)
	329 invokeinterface (4, 4)
	330 org/apache/commons/math3/ml/distance/DistanceMeasure.CENTER:Lorg/apache/commons/math3/ml/neuralnet/twod/NeuronSquareMesh2D$HorizontalDirection; (4, 4)
	332 0 (4, 4)
	334 dstore (4, 4)
	335 #15 (4, 4)
	336 aload (4, 4)
	337 #4 (4, 4)
	338 iload (4, 4)
	339 #6 (4, 4)
	340 iconst_1 (4, 4)
	341 iadd (4, 4)
	342 aaload (4, 4)
	343 iload (4, 4)
	344 #8 (4, 4)
	345 iconst_1 (4, 4)
	346 iadd (4, 4)
	347 ldc2_w (4, 4)
	348 0.5 (4, 4)
	350 dload (4, 4)
	351 #13 (4, 4)
	352 dload (4, 4)
	353 #15 (4, 4)
	354 dadd (4, 4)
	355 dmul (4, 4)
	356 dastore (4, 4)
	357 iinc (4, 4)
	358 #7 (4, 4)
	359 -89 (4, 4)
	360 goto (4, 4)
	361 -161 (4, 4)
	363 iinc (4, 4)
	364 #5 (4, 4)
	365 -89 (4, 4)
	366 goto (4, 4)
	367 -184 (4, 4)
	369 aload (3, 4)
	370 #4 (3, 4)
	371 arraylength (3, 4)
	372 iconst_1 (3, 4)
	373 isub (3, 4)
	374 istore (3, 4)
	375 #5 (3, 4)
	376 aload (3, 4)
	377 #4 (3, 4)
	378 iconst_0 (3, 4)
	379 aload (3, 4)
	380 #4 (3, 4)
	381 iload (3, 4)
	382 #5 (3, 4)
	383 aaload (3, 4)
	384 aastore (3, 4)
	385 aload (3, 4)
	386 #4 (3, 4)
	387 iconst_0 (3, 4)
	388 aaload (3, 4)
	389 arraylength (3, 4)
	390 iconst_1 (3, 4)
	391 isub (3, 4)
	392 istore (3, 4)
	393 #6 (3, 4)
	394 iconst_0 (4, 4)
	395 istore (4, 4)
	396 #7 (4, 4)
	397 iload (4, 4)
	398 #7 (4, 4)
	399 iload (4, 4)
	400 #5 (4, 4)
	401 if_icmpge (4, 4)
	402 24 (4, 4)
	404 aload (4, 4)
	405 #4 (4, 4)
	406 iload (4, 4)
	407 #7 (4, 4)
	408 aaload (4, 4)
	409 iconst_0 (4, 4)
	410 aload (4, 4)
	411 #4 (4, 4)
	412 iload (4, 4)
	413 #7 (4, 4)
	414 aaload (4, 4)
	415 iload (4, 4)
	416 #6 (4, 4)
	417 daload (4, 4)
	418 dastore (4, 4)
	419 iinc (4, 4)
	420 #7 (4, 4)
	421 -89 (4, 4)
	422 goto (4, 4)
	423 -25 (4, 4)
	425 aload (3, 4)
	426 #4 (3, 4)
	427 areturn (3, 4)

Method: averageDistances
	0 aload_1 (0, 0)
	1 invokevirtual (0, 0)
	2 org/apache/commons/math3/ml/neuralnet/twod/NeuronSquareMesh2D.getNumberOfRows:()I (0, 0)
	4 istore_2 (0, 0)
	5 aload_1 (0, 0)
	6 invokevirtual (0, 0)
	7 org/apache/commons/math3/ml/neuralnet/twod/NeuronSquareMesh2D.getNumberOfColumns:()I (0, 0)
	9 istore_3 (0, 0)
	10 iload_2 (0, 0)
	11 iload_3 (0, 0)
	12 multianewarray (0, 0)
	13 [[D (0, 0)
	15 58 (0, 0)
	16 astore (0, 0)
	17 #4 (0, 0)
	18 aload_1 (0, 0)
	19 invokevirtual (0, 0)
	20 org/apache/commons/math3/ml/neuralnet/twod/NeuronSquareMesh2D.getNetwork:()Lorg/apache/commons/math3/ml/neuralnet/Network; (0, 0)
	22 astore (0, 0)
	23 #5 (0, 0)
	24 iconst_0 (1, 4)
	25 istore (1, 4)
	26 #6 (1, 4)
	27 iload (1, 4)
	28 #6 (1, 4)
	29 iload_2 (1, 4)
	30 if_icmpge (1, 4)
	31 128 (1, 4)
	33 iconst_0 (2, 4)
	34 istore (2, 4)
	35 #7 (2, 4)
	36 iload (2, 4)
	37 #7 (2, 4)
	38 iload_3 (2, 4)
	39 if_icmpge (2, 4)
	40 113 (2, 4)
	42 aload_1 (2, 4)
	43 iload (2, 4)
	44 #6 (2, 4)
	45 iload (2, 4)
	46 #7 (2, 4)
	47 invokevirtual (2, 4)
	48 org/apache/commons/math3/ml/neuralnet/twod/NeuronSquareMesh2D.getNeuron:(II)Lorg/apache/commons/math3/ml/neuralnet/Neuron; (2, 4)
	50 astore (2, 4)
	51 #8 (2, 4)
	52 aload (2, 4)
	53 #5 (2, 4)
	54 aload (2, 4)
	55 #8 (2, 4)
	56 invokevirtual (2, 4)
	57 org/apache/commons/math3/ml/neuralnet/Network.getNeighbours:(Lorg/apache/commons/math3/ml/neuralnet/Neuron;)Ljava/util/Collection; (2, 4)
	59 astore (2, 4)
	60 #9 (2, 4)
	61 aload (2, 4)
	62 #8 (2, 4)
	63 invokevirtual (2, 4)
	64 org/apache/commons/math3/ml/neuralnet/Neuron.getFeatures:()[D (2, 4)
	66 astore (2, 4)
	67 #10 (2, 4)
	68 dconst_0 (2, 4)
	69 dstore (2, 4)
	70 #11 (2, 4)
	71 iconst_0 (2, 4)
	72 istore (2, 4)
	73 #13 (2, 4)
	74 aload (3, 4)
	75 #9 (3, 4)
	76 invokeinterface (3, 4)
	77 java/util/Collection.java/util/Iterator (3, 4)
	79 0 (3, 4)
	81 astore (3, 4)
	82 #14 (3, 4)
	83 aload (3, 4)
	84 #14 (3, 4)
	85 invokeinterface (3, 4)
	86 java/util/Iterator.next:()Ljava/lang/Object; (3, 4)
	88 0 (3, 4)
	90 ifeq (3, 4)
	91 42 (3, 4)
	93 aload (3, 4)
	94 #14 (3, 4)
	95 invokeinterface (3, 4)
	96 java/util/Iterator.org/apache/commons/math3/ml/neuralnet/Neuron (3, 4)
	98 0 (3, 4)
	100 checkcast (3, 4)
	101 org/apache/commons/math3/ml/neuralnet/Neuron (3, 4)
	103 astore (3, 4)
	104 #15 (3, 4)
	105 iinc (3, 4)
	106 #13 (3, 4)
	107 24 (3, 4)
	108 dload (3, 4)
	109 #11 (3, 4)
	110 aload_0 (3, 4)
	111 getfield (3, 4)
	112 org/apache/commons/math3/ml/neuralnet/twod/util/UnifiedDistanceMatrix.distance:Lorg/apache/commons/math3/ml/distance/DistanceMeasure; (3, 4)
	114 aload (3, 4)
	115 #10 (3, 4)
	116 aload (3, 4)
	117 #15 (3, 4)
	118 invokevirtual (3, 4)
	119 org/apache/commons/math3/ml/neuralnet/Neuron.getFeatures:()[D (3, 4)
	121 invokeinterface (3, 4)
	122 org/apache/commons/math3/ml/distance/DistanceMeasure.CENTER:Lorg/apache/commons/math3/ml/neuralnet/twod/NeuronSquareMesh2D$HorizontalDirection; (3, 4)
	124 0 (3, 4)
	126 dadd (3, 4)
	127 dstore (3, 4)
	128 #11 (3, 4)
	129 goto (2, 4)
	130 -46 (2, 4)
	132 aload (2, 4)
	133 #4 (2, 4)
	134 iload (2, 4)
	135 #6 (2, 4)
	136 aaload (2, 4)
	137 iload (2, 4)
	138 #7 (2, 4)
	139 dload (2, 4)
	140 #11 (2, 4)
	141 iload (2, 4)
	142 #13 (2, 4)
	143 i2d (2, 4)
	144 ddiv (2, 4)
	145 dastore (2, 4)
	146 iinc (2, 4)
	147 #7 (2, 4)
	148 -89 (2, 4)
	149 goto (2, 4)
	150 -113 (2, 4)
	152 iinc (2, 4)
	153 #6 (2, 4)
	154 -89 (2, 4)
	155 goto (2, 4)
	156 -128 (2, 4)
	158 aload (1, 4)
	159 #4 (1, 4)
	160 areturn (1, 4)

