Method: <init>
	0 aload_0 (0, 0)
	1 getstatic (0, 0)
	2 org/apache/commons/math3/exception/util/LocalizedFormats.ILLEGAL_STATE:Lorg/apache/commons/math3/exception/util/LocalizedFormats; (0, 0)
	4 iconst_0 (0, 0)
	5 anewarray (0, 0)
	6 java/lang/Object (0, 0)
	8 invokespecial (0, 0)
	9 org/apache/commons/math3/exception/MathIllegalStateException.<init>:(Lorg/apache/commons/math3/exception/util/Localizable;[Ljava/lang/Object;)V (0, 0)
	11 return (0, 0)

Method: getContext
	0 aload_0 (0, 0)
	1 getfield (0, 0)
	2 org/apache/commons/math3/exception/MathIllegalStateException.context:Lorg/apache/commons/math3/exception/util/ExceptionContext; (0, 0)
	4 areturn (0, 0)

Method: getMessage
	0 aload_0 (0, 0)
	1 getfield (0, 0)
	2 org/apache/commons/math3/exception/MathIllegalStateException.context:Lorg/apache/commons/math3/exception/util/ExceptionContext; (0, 0)
	4 invokevirtual (0, 0)
	5 org/apache/commons/math3/exception/util/ExceptionContext.getMessage:()Ljava/lang/String; (0, 0)
	7 areturn (0, 0)

Method: getLocalizedMessage
	0 aload_0 (0, 0)
	1 getfield (0, 0)
	2 org/apache/commons/math3/exception/MathIllegalStateException.context:Lorg/apache/commons/math3/exception/util/ExceptionContext; (0, 0)
	4 invokevirtual (0, 0)
	5 org/apache/commons/math3/exception/util/ExceptionContext.getLocalizedMessage:()Ljava/lang/String; (0, 0)
	7 areturn (0, 0)

