Method: <init>
	0 aload_0 (0, 1)
	1 aload_1 (0, 1)
	2 iconst_2 (0, 1)
	3 anewarray (0, 1)
	6 dup (0, 1)
	7 iconst_0 (0, 1)
	8 aload_2 (0, 1)
	9 aastore (0, 1)
	10 dup (0, 1)
	11 iconst_1 (0, 1)
	12 aload_3 (0, 1)
	13 aastore (0, 1)
	14 invokespecial (0, 1)
	17 aload_0 (0, 1)
	18 aload_2 (0, 1)
	19 invokevirtual (0, 1)
	22 checkcast (0, 1)
	25 putfield (0, 1)
	28 aload_0 (0, 1)
	29 aload_3 (0, 1)
	30 invokevirtual (0, 1)
	33 checkcast (0, 1)
	36 putfield (0, 1)
	39 return (0, 0)

Method: getWrongDimensions
	0 aload_0 (0, 0)
	1 getfield (0, 0)
	4 invokevirtual (0, 0)
	7 checkcast (0, 0)
	10 areturn (0, 0)

Method: getExpectedDimensions
	0 aload_0 (0, 0)
	1 getfield (0, 0)
	4 invokevirtual (0, 0)
	7 checkcast (0, 0)
	10 areturn (0, 0)

Method: getWrongDimension
	0 aload_0 (0, 0)
	1 getfield (0, 0)
	4 iload_1 (0, 0)
	5 aaload (0, 0)
	6 invokevirtual (0, 0)
	9 ireturn (0, 0)

Method: getExpectedDimension
	0 aload_0 (0, 0)
	1 getfield (0, 0)
	4 iload_1 (0, 0)
	5 aaload (0, 0)
	6 invokevirtual (0, 0)
	9 ireturn (0, 0)

