Method: <init>
	0 aload_0 (1, 1)
	1 aload_1 (1, 1)
	2 iconst_5 (1, 1)
	3 anewarray (1, 1)
	4 java/lang/Object (1, 1)
	6 dup (1, 1)
	7 iconst_0 (1, 1)
	8 dload_2 (1, 1)
	9 invokestatic (1, 1)
	10 java/lang/Double.valueOf:(D)Ljava/lang/Double; (1, 1)
	12 aastore (1, 1)
	13 dup (1, 1)
	14 iconst_1 (1, 1)
	15 dload (1, 1)
	16 #4 (1, 1)
	17 invokestatic (1, 1)
	18 java/lang/Double.valueOf:(D)Ljava/lang/Double; (1, 1)
	20 aastore (1, 1)
	21 dup (1, 1)
	22 iconst_2 (1, 1)
	23 dload (1, 1)
	24 #6 (1, 1)
	25 invokestatic (1, 1)
	26 java/lang/Double.valueOf:(D)Ljava/lang/Double; (1, 1)
	28 aastore (1, 1)
	29 dup (1, 1)
	30 iconst_3 (1, 1)
	31 dload (1, 1)
	32 #8 (1, 1)
	33 invokestatic (1, 1)
	34 java/lang/Double.valueOf:(D)Ljava/lang/Double; (1, 1)
	36 aastore (1, 1)
	37 dup (1, 1)
	38 iconst_4 (1, 1)
	39 aload (1, 1)
	40 #10 (1, 1)
	41 aastore (1, 1)
	42 invokespecial (1, 1)
	43 org/apache/commons/math3/exception/MathIllegalArgumentException.<init>:(Lorg/apache/commons/math3/exception/util/Localizable;[Ljava/lang/Object;)V (1, 1)
	45 aload_0 (1, 1)
	46 dload_2 (1, 1)
	47 putfield (1, 1)
	48 org/apache/commons/math3/exception/NoBracketingException.lo:D (1, 1)
	50 aload_0 (1, 1)
	51 dload (1, 1)
	52 #4 (1, 1)
	53 putfield (1, 1)
	54 org/apache/commons/math3/exception/NoBracketingException.hi:D (1, 1)
	56 aload_0 (1, 1)
	57 dload (1, 1)
	58 #6 (1, 1)
	59 putfield (1, 1)
	60 org/apache/commons/math3/exception/NoBracketingException.fLo:D (1, 1)
	62 aload_0 (1, 1)
	63 dload (1, 1)
	64 #8 (1, 1)
	65 putfield (1, 1)
	66 org/apache/commons/math3/exception/NoBracketingException.fHi:D (1, 1)
	68 return (0, 1)

Method: getLo
	0 aload_0 (0, 0)
	1 getfield (0, 0)
	2 org/apache/commons/math3/exception/NoBracketingException.lo:D (0, 0)
	4 dreturn (0, 0)

Method: getHi
	0 aload_0 (0, 0)
	1 getfield (0, 0)
	2 org/apache/commons/math3/exception/NoBracketingException.hi:D (0, 0)
	4 dreturn (0, 0)

Method: getFLo
	0 aload_0 (0, 0)
	1 getfield (0, 0)
	2 org/apache/commons/math3/exception/NoBracketingException.fLo:D (0, 0)
	4 dreturn (0, 0)

Method: getFHi
	0 aload_0 (0, 0)
	1 getfield (0, 0)
	2 org/apache/commons/math3/exception/NoBracketingException.fHi:D (0, 0)
	4 dreturn (0, 0)

