Method: <init>
	0 aload_0 (0, 0)
	1 aload (0, 0)
	2 #4 (0, 0)
	3 getstatic (0, 0)
	4 org/apache/commons/math3/util/MathArrays$OrderDirection.INCREASING:Lorg/apache/commons/math3/util/MathArrays$OrderDirection; (0, 0)
	6 if_acmpne (0, 0)
	7 20 (0, 0)
	9 iload (0, 0)
	10 #5 (0, 0)
	11 ifeq (0, 0)
	12 9 (0, 0)
	14 getstatic (0, 0)
	15 org/apache/commons/math3/exception/util/LocalizedFormats.NOT_STRICTLY_INCREASING_SEQUENCE:Lorg/apache/commons/math3/exception/util/LocalizedFormats; (0, 0)
	17 goto (0, 0)
	18 23 (0, 0)
	20 getstatic (0, 0)
	21 org/apache/commons/math3/exception/util/LocalizedFormats.NOT_INCREASING_SEQUENCE:Lorg/apache/commons/math3/exception/util/LocalizedFormats; (0, 0)
	23 goto (0, 0)
	24 17 (0, 0)
	26 iload (0, 0)
	27 #5 (0, 0)
	28 ifeq (0, 0)
	29 9 (0, 0)
	31 getstatic (0, 0)
	32 org/apache/commons/math3/exception/util/LocalizedFormats.NOT_STRICTLY_DECREASING_SEQUENCE:Lorg/apache/commons/math3/exception/util/LocalizedFormats; (0, 0)
	34 goto (0, 0)
	35 6 (0, 0)
	37 getstatic (0, 0)
	38 org/apache/commons/math3/exception/util/LocalizedFormats.NOT_DECREASING_SEQUENCE:Lorg/apache/commons/math3/exception/util/LocalizedFormats; (0, 0)
	40 aload_1 (0, 0)
	41 iconst_3 (0, 0)
	42 anewarray (0, 0)
	43 java/lang/Object (0, 0)
	45 dup (0, 0)
	46 iconst_0 (0, 0)
	47 aload_2 (0, 0)
	48 aastore (0, 0)
	49 dup (0, 0)
	50 iconst_1 (0, 0)
	51 iload_3 (0, 0)
	52 invokestatic (0, 0)
	53 java/lang/Integer.valueOf:(I)Ljava/lang/Integer; (0, 0)
	55 aastore (0, 0)
	56 dup (0, 0)
	57 iconst_2 (0, 0)
	58 iload_3 (0, 0)
	59 iconst_1 (0, 0)
	60 isub (0, 0)
	61 invokestatic (0, 0)
	62 java/lang/Integer.valueOf:(I)Ljava/lang/Integer; (0, 0)
	64 aastore (0, 0)
	65 invokespecial (0, 0)
	66 org/apache/commons/math3/exception/MathIllegalNumberException.<init>:(Lorg/apache/commons/math3/exception/util/Localizable;Ljava/lang/Number;[Ljava/lang/Object;)V (0, 0)
	68 aload_0 (0, 0)
	69 aload (0, 0)
	70 #4 (0, 0)
	71 putfield (0, 0)
	72 org/apache/commons/math3/exception/NonMonotonicSequenceException.direction:Lorg/apache/commons/math3/util/MathArrays$OrderDirection; (0, 0)
	74 aload_0 (0, 0)
	75 iload (0, 0)
	76 #5 (0, 0)
	77 putfield (0, 0)
	78 org/apache/commons/math3/exception/NonMonotonicSequenceException.strict:Z (0, 0)
	80 aload_0 (0, 0)
	81 iload_3 (0, 0)
	82 putfield (0, 0)
	83 org/apache/commons/math3/exception/NonMonotonicSequenceException.index:I (0, 0)
	85 aload_0 (0, 0)
	86 aload_2 (0, 0)
	87 putfield (0, 0)
	88 org/apache/commons/math3/exception/NonMonotonicSequenceException.previous:Ljava/lang/Number; (0, 0)
	90 return (0, 0)

Method: getDirection
	0 aload_0 (0, 0)
	1 getfield (0, 0)
	2 org/apache/commons/math3/exception/NonMonotonicSequenceException.direction:Lorg/apache/commons/math3/util/MathArrays$OrderDirection; (0, 0)
	4 areturn (0, 0)

Method: getStrict
	0 aload_0 (0, 0)
	1 getfield (0, 0)
	2 org/apache/commons/math3/exception/NonMonotonicSequenceException.strict:Z (0, 0)
	4 ireturn (0, 0)

Method: getIndex
	0 aload_0 (0, 0)
	1 getfield (0, 0)
	2 org/apache/commons/math3/exception/NonMonotonicSequenceException.index:I (0, 0)
	4 ireturn (0, 0)

Method: getPrevious
	0 aload_0 (0, 0)
	1 getfield (0, 0)
	2 org/apache/commons/math3/exception/NonMonotonicSequenceException.previous:Ljava/lang/Number; (0, 0)
	4 areturn (0, 0)

