Method: <init>
	0 aload_0 (1, 1)
	1 aload_1 (1, 1)
	2 aload_2 (1, 1)
	3 iconst_2 (1, 1)
	4 anewarray (1, 1)
	5 java/lang/Object (1, 1)
	7 dup (1, 1)
	8 iconst_0 (1, 1)
	9 aload_3 (1, 1)
	10 aastore (1, 1)
	11 dup (1, 1)
	12 iconst_1 (1, 1)
	13 aload (1, 1)
	14 #4 (1, 1)
	15 aastore (1, 1)
	16 invokespecial (1, 1)
	17 org/apache/commons/math3/exception/MathIllegalNumberException.<init>:(Lorg/apache/commons/math3/exception/util/Localizable;Ljava/lang/Number;[Ljava/lang/Object;)V (1, 1)
	19 aload_0 (1, 1)
	20 aload_3 (1, 1)
	21 putfield (1, 1)
	22 org/apache/commons/math3/exception/OutOfRangeException.lo:Ljava/lang/Number; (1, 1)
	24 aload_0 (1, 1)
	25 aload (1, 1)
	26 #4 (1, 1)
	27 putfield (1, 1)
	28 org/apache/commons/math3/exception/OutOfRangeException.hi:Ljava/lang/Number; (1, 1)
	30 return (0, 1)

Method: getLo
	0 aload_0 (0, 0)
	1 getfield (0, 0)
	2 org/apache/commons/math3/exception/OutOfRangeException.lo:Ljava/lang/Number; (0, 0)
	4 areturn (0, 0)

Method: getHi
	0 aload_0 (0, 0)
	1 getfield (0, 0)
	2 org/apache/commons/math3/exception/OutOfRangeException.hi:Ljava/lang/Number; (0, 0)
	4 areturn (0, 0)

