Method: <init>
	0 aload_0 (0, 0)
	1 aload_1 (0, 0)
	2 invokespecial (0, 0)
	3 org/apache/commons/math3/exception/MaxCountExceededException.<init>:(Ljava/lang/Number;)V (0, 0)
	5 aload_0 (0, 0)
	6 invokevirtual (0, 0)
	7 org/apache/commons/math3/exception/TooManyIterationsException.getContext:()Lorg/apache/commons/math3/exception/util/ExceptionContext; (0, 0)
	9 getstatic (0, 0)
	10 org/apache/commons/math3/exception/util/LocalizedFormats.ITERATIONS:Lorg/apache/commons/math3/exception/util/LocalizedFormats; (0, 0)
	12 iconst_0 (0, 0)
	13 anewarray (0, 0)
	14 java/lang/Object (0, 0)
	16 invokevirtual (0, 0)
	17 org/apache/commons/math3/exception/util/ExceptionContext.addMessage:(Lorg/apache/commons/math3/exception/util/Localizable;[Ljava/lang/Object;)V (0, 0)
	19 return (0, 0)

