Method: <init>
	0 aload_0 (0, 0)
	1 invokespecial (0, 0)
	2 org/apache/commons/math3/genetics/Chromosome.<init>:()V (0, 0)
	4 aload_0 (0, 0)
	5 aload_1 (0, 0)
	6 invokevirtual (0, 0)
	7 org/apache/commons/math3/genetics/AbstractListChromosome.checkValidity:(Ljava/util/List;)V (0, 0)
	9 aload_0 (0, 0)
	10 iload_2 (0, 0)
	11 ifeq (0, 0)
	12 14 (0, 0)
	14 new (0, 0)
	15 java/util/ArrayList (0, 0)
	17 dup (0, 0)
	18 aload_1 (0, 0)
	19 invokespecial (0, 0)
	20 java/util/ArrayList.<init>:(Ljava/util/Collection;)V (0, 0)
	22 goto (0, 0)
	23 4 (0, 0)
	25 aload_1 (0, 0)
	26 invokestatic (1, 1)
	27 java/util/Collections.unmodifiableList:(Ljava/util/List;)Ljava/util/List; (1, 1)
	29 putfield (1, 1)
	30 org/apache/commons/math3/genetics/AbstractListChromosome.representation:Ljava/util/List; (1, 1)
	32 return (0, 0)

Method: getRepresentation
	0 aload_0 (0, 0)
	1 getfield (0, 0)
	2 org/apache/commons/math3/genetics/AbstractListChromosome.representation:Ljava/util/List; (0, 0)
	4 areturn (0, 0)

Method: getLength
	0 aload_0 (0, 0)
	1 invokevirtual (0, 0)
	2 org/apache/commons/math3/genetics/AbstractListChromosome.getRepresentation:()Ljava/util/List; (0, 0)
	4 invokeinterface (0, 0)
	5 java/util/List.(f=%s %s) (0, 0)
	7 0 (0, 0)
	9 ireturn (0, 0)

Method: toString
	0 ldc (0, 4)
	1 (f=%s %s) (0, 4)
	2 iconst_2 (0, 4)
	3 anewarray (0, 4)
	4 java/lang/Object (0, 4)
	6 dup (0, 4)
	7 iconst_0 (0, 4)
	8 aload_0 (0, 4)
	9 invokevirtual (0, 4)
	10 org/apache/commons/math3/genetics/AbstractListChromosome.getFitness:()D (0, 4)
	12 invokestatic (0, 4)
	13 java/lang/Double.valueOf:(D)Ljava/lang/Double; (0, 4)
	15 aastore (0, 4)
	16 dup (0, 4)
	17 iconst_1 (0, 4)
	18 aload_0 (0, 4)
	19 invokevirtual (0, 4)
	20 org/apache/commons/math3/genetics/AbstractListChromosome.getRepresentation:()Ljava/util/List; (0, 4)
	22 aastore (0, 4)
	23 invokestatic (0, 4)
	24 java/lang/String.format:(Ljava/lang/String;[Ljava/lang/Object;)Ljava/lang/String; (0, 4)
	26 areturn (0, 4)

