Method: <init>
	0 aload_0 (0, 0)
	1 aload_1 (0, 0)
	2 invokespecial (0, 0)
	3 org/apache/commons/math3/genetics/AbstractListChromosome.<init>:([Ljava/lang/Object;)V (0, 0)
	5 return (0, 0)

Method: checkValidity
	0 aload_1 (1, 4)
	1 invokeinterface (1, 4)
	2 java/util/List.java/util/Iterator (1, 4)
	4 0 (1, 4)
	6 astore_2 (1, 4)
	7 aload_2 (1, 4)
	8 invokeinterface (1, 4)
	9 java/util/Iterator.next:()Ljava/lang/Object; (1, 4)
	11 0 (1, 4)
	13 ifeq (1, 4)
	14 50 (1, 4)
	16 aload_2 (1, 4)
	17 invokeinterface (1, 4)
	18 java/util/Iterator.java/lang/Integer (1, 4)
	20 0 (1, 4)
	22 checkcast (1, 4)
	23 java/lang/Integer (1, 4)
	25 invokevirtual (1, 4)
	26 java/lang/Integer.intValue:()I (1, 4)
	28 istore_3 (1, 4)
	29 iload_3 (2, 1)
	30 iflt (2, 1)
	31 8 (2, 1)
	33 iload_3 (2, 1)
	34 iconst_1 (2, 1)
	35 if_icmple (2, 1)
	36 25 (2, 1)
	38 new (2, 1)
	39 org/apache/commons/math3/genetics/InvalidRepresentationException (2, 1)
	41 dup (2, 1)
	42 getstatic (2, 1)
	43 org/apache/commons/math3/exception/util/LocalizedFormats.INVALID_BINARY_DIGIT:Lorg/apache/commons/math3/exception/util/LocalizedFormats; (2, 1)
	45 iconst_1 (2, 1)
	46 anewarray (2, 1)
	47 java/lang/Object (2, 1)
	49 dup (2, 1)
	50 iconst_0 (2, 1)
	51 iload_3 (2, 1)
	52 invokestatic (2, 1)
	53 java/lang/Integer.valueOf:(I)Ljava/lang/Integer; (2, 1)
	55 aastore (2, 1)
	56 invokespecial (2, 1)
	57 org/apache/commons/math3/genetics/InvalidRepresentationException.<init>:(Lorg/apache/commons/math3/exception/util/Localizable;[Ljava/lang/Object;)V (2, 1)
	59 athrow (2, 1)
	60 goto (0, 0)
	61 -53 (0, 0)
	63 return (0, 0)

Method: randomBinaryRepresentation
	0 new (0, 0)
	1 java/util/ArrayList (0, 0)
	3 dup (0, 0)
	4 iload_0 (0, 0)
	5 invokespecial (0, 0)
	6 java/util/ArrayList.<init>:(I)V (0, 0)
	8 astore_1 (0, 0)
	9 iconst_0 (1, 4)
	10 istore_2 (1, 4)
	11 iload_2 (1, 4)
	12 iload_0 (1, 4)
	13 if_icmpge (1, 4)
	14 28 (1, 4)
	16 aload_1 (1, 4)
	17 invokestatic (1, 4)
	18 org/apache/commons/math3/genetics/GeneticAlgorithm.getRandomGenerator:()Lorg/apache/commons/math3/random/RandomGenerator; (1, 4)
	20 iconst_2 (1, 4)
	21 invokeinterface (1, 4)
	22 org/apache/commons/math3/random/RandomGenerator.add:(Ljava/lang/Object;)Z (1, 4)
	24 0 (1, 4)
	26 invokestatic (1, 4)
	27 java/lang/Integer.valueOf:(I)Ljava/lang/Integer; (1, 4)
	29 invokeinterface (1, 4)
	30 java/util/List.org/apache/commons/math3/genetics/BinaryChromosome (1, 4)
	32 0 (1, 4)
	34 pop (1, 4)
	35 iinc (1, 4)
	36 #2 (1, 4)
	37 -89 (1, 4)
	38 goto (1, 4)
	39 -27 (1, 4)
	41 aload_1 (0, 0)
	42 areturn (0, 0)

Method: isSame
	0 aload_1 (1, 1)
	1 instanceof (1, 1)
	2 org/apache/commons/math3/genetics/BinaryChromosome (1, 1)
	4 ifne (1, 1)
	5 5 (1, 1)
	7 iconst_0 (1, 1)
	8 ireturn (1, 1)
	9 aload_1 (0, 0)
	10 checkcast (0, 0)
	11 org/apache/commons/math3/genetics/BinaryChromosome (0, 0)
	13 astore_2 (0, 0)
	14 aload_0 (1, 1)
	15 invokevirtual (1, 1)
	16 org/apache/commons/math3/genetics/BinaryChromosome.getLength:()I (1, 1)
	18 aload_2 (1, 1)
	19 invokevirtual (1, 1)
	20 org/apache/commons/math3/genetics/BinaryChromosome.getLength:()I (1, 1)
	22 if_icmpeq (1, 1)
	23 5 (1, 1)
	25 iconst_0 (1, 1)
	26 ireturn (1, 1)
	27 iconst_0 (1, 4)
	28 istore_3 (1, 4)
	29 iload_3 (1, 4)
	30 aload_0 (1, 4)
	31 invokevirtual (1, 4)
	32 org/apache/commons/math3/genetics/BinaryChromosome.getRepresentation:()Ljava/util/List; (1, 4)
	34 invokeinterface (1, 4)
	35 java/util/List.get:(I)Ljava/lang/Object; (1, 4)
	37 0 (1, 4)
	39 if_icmpge (1, 4)
	40 40 (1, 4)
	42 aload_0 (2, 1)
	43 invokevirtual (2, 1)
	44 org/apache/commons/math3/genetics/BinaryChromosome.getRepresentation:()Ljava/util/List; (2, 1)
	46 iload_3 (2, 1)
	47 invokeinterface (2, 1)
	48 java/util/List.equals:(Ljava/lang/Object;)Z (2, 1)
	50 0 (2, 1)
	52 checkcast (2, 1)
	53 java/lang/Integer (2, 1)
	55 aload_2 (2, 1)
	56 invokevirtual (2, 1)
	57 org/apache/commons/math3/genetics/BinaryChromosome.getRepresentation:()Ljava/util/List; (2, 1)
	59 iload_3 (2, 1)
	60 invokeinterface (2, 1)
	61 java/util/List.equals:(Ljava/lang/Object;)Z (2, 1)
	63 0 (2, 1)
	65 invokevirtual (2, 1)
	66 java/lang/Integer.equals:(Ljava/lang/Object;)Z (2, 1)
	68 ifne (2, 1)
	69 5 (2, 1)
	71 iconst_0 (2, 1)
	72 ireturn (2, 1)
	73 iinc (2, 1)
	74 #3 (2, 1)
	75 -89 (2, 1)
	76 goto (2, 1)
	77 -47 (2, 1)
	79 iconst_1 (1, 4)
	80 ireturn (1, 4)

