Method: <init>
	0 aload_0 (0, 0)
	1 invokespecial (0, 0)
	2 java/lang/Object.<init>:()V (0, 0)
	4 aload_0 (0, 0)
	5 aload_1 (0, 0)
	6 putfield (0, 0)
	7 org/apache/commons/math3/genetics/ChromosomePair.first:Lorg/apache/commons/math3/genetics/Chromosome; (0, 0)
	9 aload_0 (0, 0)
	10 aload_2 (0, 0)
	11 putfield (0, 0)
	12 org/apache/commons/math3/genetics/ChromosomePair.second:Lorg/apache/commons/math3/genetics/Chromosome; (0, 0)
	14 return (0, 0)

Method: getFirst
	0 aload_0 (0, 0)
	1 getfield (0, 0)
	2 org/apache/commons/math3/genetics/ChromosomePair.first:Lorg/apache/commons/math3/genetics/Chromosome; (0, 0)
	4 areturn (0, 0)

Method: getSecond
	0 aload_0 (0, 0)
	1 getfield (0, 0)
	2 org/apache/commons/math3/genetics/ChromosomePair.second:Lorg/apache/commons/math3/genetics/Chromosome; (0, 0)
	4 areturn (0, 0)

Method: toString
	0 ldc (0, 4)
	1 (%s,%s) (0, 4)
	2 iconst_2 (0, 4)
	3 anewarray (0, 4)
	4 java/lang/Object (0, 4)
	6 dup (0, 4)
	7 iconst_0 (0, 4)
	8 aload_0 (0, 4)
	9 invokevirtual (0, 4)
	10 org/apache/commons/math3/genetics/ChromosomePair.getFirst:()Lorg/apache/commons/math3/genetics/Chromosome; (0, 4)
	12 aastore (0, 4)
	13 dup (0, 4)
	14 iconst_1 (0, 4)
	15 aload_0 (0, 4)
	16 invokevirtual (0, 4)
	17 org/apache/commons/math3/genetics/ChromosomePair.getSecond:()Lorg/apache/commons/math3/genetics/Chromosome; (0, 4)
	19 aastore (0, 4)
	20 invokestatic (0, 4)
	21 java/lang/String.format:(Ljava/lang/String;[Ljava/lang/Object;)Ljava/lang/String; (0, 4)
	23 areturn (0, 4)

