Method: <init>
	0 aload_0 (0, 0)
	1 invokespecial (0, 0)
	4 aload_0 (0, 0)
	5 ldc2_w (0, 0)
	8 putfield (0, 0)
	11 return (0, 0)

Method: getFitness
	0 aload_0 (0, 0)
	1 getfield (0, 0)
	4 ldc2_w (0, 0)
	7 dcmpl (0, 0)
	8 ifne (0, 0)
	11 aload_0 (0, 0)
	12 aload_0 (0, 0)
	13 invokevirtual (0, 0)
	16 putfield (0, 0)
	19 aload_0 (0, 0)
	20 getfield (0, 0)
	23 dreturn (0, 0)

Method: compareTo
	0 aload_0 (0, 0)
	1 invokevirtual (0, 0)
	4 aload_1 (0, 0)
	5 invokevirtual (0, 0)
	8 invokestatic (0, 0)
	11 ireturn (0, 0)

