Method: <init>
	0 aload_0 (0, 0)
	1 invokespecial (0, 0)
	2 java/lang/Object.<init>:()V (0, 0)
	4 aload_0 (0, 0)
	5 iload_1 (0, 0)
	6 putfield (0, 0)
	7 org/apache/commons/math3/genetics/CycleCrossover.randomStart:Z (0, 0)
	9 return (0, 0)

Method: isRandomStart
	0 aload_0 (0, 0)
	1 getfield (0, 0)
	2 org/apache/commons/math3/genetics/CycleCrossover.randomStart:Z (0, 0)
	4 ireturn (0, 0)

Method: crossover
	0 aload_1 (1, 1)
	1 instanceof (1, 1)
	2 org/apache/commons/math3/genetics/AbstractListChromosome (1, 1)
	4 ifeq (1, 1)
	5 10 (1, 1)
	7 aload_2 (1, 1)
	8 instanceof (1, 1)
	9 org/apache/commons/math3/genetics/AbstractListChromosome (1, 1)
	11 ifne (1, 1)
	12 18 (1, 1)
	14 new (1, 1)
	15 org/apache/commons/math3/exception/MathIllegalArgumentException (1, 1)
	17 dup (1, 1)
	18 getstatic (1, 1)
	19 org/apache/commons/math3/exception/util/LocalizedFormats.INVALID_FIXED_LENGTH_CHROMOSOME:Lorg/apache/commons/math3/exception/util/LocalizedFormats; (1, 1)
	21 iconst_0 (1, 1)
	22 anewarray (1, 1)
	23 java/lang/Object (1, 1)
	25 invokespecial (1, 1)
	26 org/apache/commons/math3/exception/MathIllegalArgumentException.<init>:(Lorg/apache/commons/math3/exception/util/Localizable;[Ljava/lang/Object;)V (1, 1)
	28 athrow (1, 1)
	29 aload_0 (0, 0)
	30 aload_1 (0, 0)
	31 checkcast (0, 0)
	32 org/apache/commons/math3/genetics/AbstractListChromosome (0, 0)
	34 aload_2 (0, 0)
	35 checkcast (0, 0)
	36 org/apache/commons/math3/genetics/AbstractListChromosome (0, 0)
	38 invokevirtual (0, 0)
	39 org/apache/commons/math3/genetics/CycleCrossover.mate:(Lorg/apache/commons/math3/genetics/AbstractListChromosome;Lorg/apache/commons/math3/genetics/AbstractListChromosome;)Lorg/apache/commons/math3/genetics/ChromosomePair; (0, 0)
	41 areturn (0, 0)

Method: mate
	0 aload_1 (0, 0)
	1 invokevirtual (0, 0)
	2 org/apache/commons/math3/genetics/AbstractListChromosome.getLength:()I (0, 0)
	4 istore_3 (0, 0)
	5 iload_3 (1, 1)
	6 aload_2 (1, 1)
	7 invokevirtual (1, 1)
	8 org/apache/commons/math3/genetics/AbstractListChromosome.getLength:()I (1, 1)
	10 if_icmpeq (1, 1)
	11 16 (1, 1)
	13 new (1, 1)
	14 org/apache/commons/math3/exception/DimensionMismatchException (1, 1)
	16 dup (1, 1)
	17 aload_2 (1, 1)
	18 invokevirtual (1, 1)
	19 org/apache/commons/math3/genetics/AbstractListChromosome.getLength:()I (1, 1)
	21 iload_3 (1, 1)
	22 invokespecial (1, 1)
	23 org/apache/commons/math3/exception/DimensionMismatchException.<init>:(II)V (1, 1)
	25 athrow (1, 1)
	26 aload_1 (0, 0)
	27 invokevirtual (0, 0)
	28 org/apache/commons/math3/genetics/AbstractListChromosome.getRepresentation:()Ljava/util/List; (0, 0)
	30 astore (0, 0)
	31 #4 (0, 0)
	32 aload_2 (0, 0)
	33 invokevirtual (0, 0)
	34 org/apache/commons/math3/genetics/AbstractListChromosome.getRepresentation:()Ljava/util/List; (0, 0)
	36 astore (0, 0)
	37 #5 (0, 0)
	38 new (0, 1)
	39 java/util/ArrayList (0, 1)
	41 dup (0, 1)
	42 aload_2 (0, 1)
	43 invokevirtual (0, 1)
	44 org/apache/commons/math3/genetics/AbstractListChromosome.getRepresentation:()Ljava/util/List; (0, 1)
	46 invokespecial (0, 1)
	47 java/util/ArrayList.<init>:(Ljava/util/Collection;)V (0, 1)
	49 astore (0, 1)
	50 #6 (0, 1)
	51 new (0, 1)
	52 java/util/ArrayList (0, 1)
	54 dup (0, 1)
	55 aload_1 (0, 1)
	56 invokevirtual (0, 1)
	57 org/apache/commons/math3/genetics/AbstractListChromosome.getRepresentation:()Ljava/util/List; (0, 1)
	59 invokespecial (0, 1)
	60 java/util/ArrayList.<init>:(Ljava/util/Collection;)V (0, 1)
	62 astore (0, 1)
	63 #7 (0, 1)
	64 new (0, 1)
	65 java/util/HashSet (0, 1)
	67 dup (0, 1)
	68 iload_3 (0, 1)
	69 invokespecial (0, 1)
	70 java/util/HashSet.<init>:(I)V (0, 1)
	72 astore (0, 1)
	73 #8 (0, 1)
	74 new (0, 1)
	75 java/util/ArrayList (0, 1)
	77 dup (0, 1)
	78 iload_3 (0, 1)
	79 invokespecial (0, 1)
	80 java/util/ArrayList.<init>:(I)V (0, 1)
	82 astore (0, 1)
	83 #9 (0, 1)
	84 aload_0 (0, 1)
	85 getfield (0, 1)
	86 org/apache/commons/math3/genetics/CycleCrossover.randomStart:Z (0, 1)
	88 ifeq (0, 1)
	89 15 (0, 1)
	91 invokestatic (0, 1)
	92 org/apache/commons/math3/genetics/GeneticAlgorithm.getRandomGenerator:()Lorg/apache/commons/math3/random/RandomGenerator; (0, 1)
	94 iload_3 (0, 1)
	95 invokeinterface (0, 1)
	96 org/apache/commons/math3/random/RandomGenerator.java/util/Set (0, 1)
	98 0 (0, 1)
	100 goto (0, 1)
	101 4 (0, 1)
	103 iconst_0 (0, 1)
	104 istore (0, 1)
	105 #10 (0, 1)
	106 iconst_1 (0, 1)
	107 istore (0, 1)
	108 #11 (0, 1)
	109 aload (1, 3)
	110 #8 (1, 3)
	111 invokeinterface (1, 3)
	112 java/util/Set.valueOf:(I)Ljava/lang/Integer; (1, 3)
	114 0 (1, 3)
	116 iload_3 (1, 3)
	117 if_icmpge (1, 3)
	118 265 (1, 3)
	120 aload (1, 3)
	121 #9 (1, 3)
	122 iload (1, 3)
	123 #10 (1, 3)
	124 invokestatic (1, 3)
	125 java/lang/Integer.valueOf:(I)Ljava/lang/Integer; (1, 3)
	127 invokeinterface (1, 3)
	128 java/util/List.get:(I)Ljava/lang/Object; (1, 3)
	130 0 (1, 3)
	132 pop (1, 3)
	133 aload (1, 3)
	134 #5 (1, 3)
	135 iload (1, 3)
	136 #10 (1, 3)
	137 invokeinterface (1, 3)
	138 java/util/List.indexOf:(Ljava/lang/Object;)I (1, 3)
	140 0 (1, 3)
	142 astore (1, 3)
	143 #12 (1, 3)
	144 aload (1, 3)
	145 #4 (1, 3)
	146 aload (1, 3)
	147 #12 (1, 3)
	148 invokeinterface (1, 3)
	149 java/util/List.java/lang/Integer (1, 3)
	151 0 (1, 3)
	153 istore (1, 3)
	154 #10 (1, 3)
	155 iload (2, 3)
	156 #10 (2, 3)
	157 aload (2, 3)
	158 #9 (2, 3)
	159 iconst_0 (2, 3)
	160 invokeinterface (2, 3)
	161 java/util/List.indexOf:(Ljava/lang/Object;)I (2, 3)
	163 0 (2, 3)
	165 checkcast (2, 3)
	166 java/lang/Integer (2, 3)
	168 invokevirtual (2, 3)
	169 java/lang/Integer.intValue:()I (2, 3)
	171 if_icmpeq (2, 3)
	172 41 (2, 3)
	174 aload (2, 3)
	175 #9 (2, 3)
	176 iload (2, 3)
	177 #10 (2, 3)
	178 invokestatic (2, 3)
	179 java/lang/Integer.valueOf:(I)Ljava/lang/Integer; (2, 3)
	181 invokeinterface (2, 3)
	182 java/util/List.get:(I)Ljava/lang/Object; (2, 3)
	184 0 (2, 3)
	186 pop (2, 3)
	187 aload (2, 3)
	188 #5 (2, 3)
	189 iload (2, 3)
	190 #10 (2, 3)
	191 invokeinterface (2, 3)
	192 java/util/List.indexOf:(Ljava/lang/Object;)I (2, 3)
	194 0 (2, 3)
	196 astore (2, 3)
	197 #12 (2, 3)
	198 aload (2, 3)
	199 #4 (2, 3)
	200 aload (2, 3)
	201 #12 (2, 3)
	202 invokeinterface (2, 3)
	203 java/util/List.java/lang/Integer (2, 3)
	205 0 (2, 3)
	207 istore (2, 3)
	208 #10 (2, 3)
	209 goto (2, 3)
	210 -54 (2, 3)
	212 iload (2, 1)
	213 #11 (2, 1)
	214 iinc (2, 1)
	215 #11 (2, 1)
	216 5 (2, 1)
	217 iconst_2 (2, 1)
	218 irem (2, 1)
	219 ifeq (2, 1)
	220 82 (2, 1)
	222 aload (3, 4)
	223 #9 (3, 4)
	224 invokeinterface (3, 4)
	225 java/util/List.java/util/Iterator (3, 4)
	227 0 (3, 4)
	229 astore (3, 4)
	230 #13 (3, 4)
	231 aload (3, 4)
	232 #13 (3, 4)
	233 invokeinterface (3, 4)
	234 java/util/Iterator.next:()Ljava/lang/Object; (3, 4)
	236 0 (3, 4)
	238 ifeq (3, 4)
	239 63 (3, 4)
	241 aload (3, 4)
	242 #13 (3, 4)
	243 invokeinterface (3, 4)
	244 java/util/Iterator.set:(ILjava/lang/Object;)Ljava/lang/Object; (3, 4)
	246 0 (3, 4)
	248 checkcast (3, 4)
	249 java/lang/Integer (3, 4)
	251 invokevirtual (3, 4)
	252 java/lang/Integer.intValue:()I (3, 4)
	254 istore (3, 4)
	255 #14 (3, 4)
	256 aload (3, 4)
	257 #6 (3, 4)
	258 iload (3, 4)
	259 #14 (3, 4)
	260 invokeinterface (3, 4)
	261 java/util/List.indexOf:(Ljava/lang/Object;)I (3, 4)
	263 0 (3, 4)
	265 astore (3, 4)
	266 #15 (3, 4)
	267 aload (3, 4)
	268 #6 (3, 4)
	269 iload (3, 4)
	270 #14 (3, 4)
	271 aload (3, 4)
	272 #7 (3, 4)
	273 iload (3, 4)
	274 #14 (3, 4)
	275 invokeinterface (3, 4)
	276 java/util/List.indexOf:(Ljava/lang/Object;)I (3, 4)
	278 0 (3, 4)
	280 invokeinterface (3, 4)
	281 java/util/List.addAll:(Ljava/util/Collection;)Z (3, 4)
	283 0 (3, 4)
	285 pop (3, 4)
	286 aload (3, 4)
	287 #7 (3, 4)
	288 iload (3, 4)
	289 #14 (3, 4)
	290 aload (3, 4)
	291 #15 (3, 4)
	292 invokeinterface (3, 4)
	293 java/util/List.addAll:(Ljava/util/Collection;)Z (3, 4)
	295 0 (3, 4)
	297 pop (3, 4)
	298 goto (2, 1)
	299 -67 (2, 1)
	301 aload (1, 4)
	302 #8 (1, 4)
	303 aload (1, 4)
	304 #9 (1, 4)
	305 invokeinterface (1, 4)
	306 java/util/Set.contains:(Ljava/lang/Object;)Z (1, 4)
	308 0 (1, 4)
	310 pop (1, 4)
	311 aload (1, 4)
	312 #9 (1, 4)
	313 iconst_0 (1, 4)
	314 invokeinterface (1, 4)
	315 java/util/List.indexOf:(Ljava/lang/Object;)I (1, 4)
	317 0 (1, 4)
	319 checkcast (1, 4)
	320 java/lang/Integer (1, 4)
	322 invokevirtual (1, 4)
	323 java/lang/Integer.intValue:()I (1, 4)
	325 iconst_1 (1, 4)
	326 iadd (1, 4)
	327 iload_3 (1, 4)
	328 irem (1, 4)
	329 istore (1, 4)
	330 #10 (1, 4)
	331 aload (2, 3)
	332 #8 (2, 3)
	333 iload (2, 3)
	334 #10 (2, 3)
	335 invokestatic (2, 3)
	336 java/lang/Integer.valueOf:(I)Ljava/lang/Integer; (2, 3)
	338 invokeinterface (2, 3)
	339 java/util/Set.clear:()V (2, 3)
	341 0 (2, 3)
	343 ifeq (2, 3)
	344 29 (2, 3)
	346 aload (2, 3)
	347 #8 (2, 3)
	348 invokeinterface (2, 3)
	349 java/util/Set.valueOf:(I)Ljava/lang/Integer; (2, 3)
	351 0 (2, 3)
	353 iload_3 (2, 3)
	354 if_icmpge (2, 3)
	355 18 (2, 3)
	357 iinc (2, 3)
	358 #10 (2, 3)
	359 21 (2, 3)
	360 iload (3, 1)
	361 #10 (3, 1)
	362 iload_3 (3, 1)
	363 if_icmplt (3, 1)
	364 -32 (3, 1)
	366 iconst_0 (3, 1)
	367 istore (3, 1)
	368 #10 (3, 1)
	369 goto (3, 1)
	370 -38 (3, 1)
	372 aload (1, 4)
	373 #9 (1, 4)
	374 invokeinterface (1, 4)
	375 java/util/List.org/apache/commons/math3/genetics/ChromosomePair (1, 4)
	377 0 (1, 4)
	379 goto (0, 1)
	380 -270 (0, 1)
	382 new (0, 1)
	383 org/apache/commons/math3/genetics/ChromosomePair (0, 1)
	385 dup (0, 1)
	386 aload_1 (0, 1)
	387 aload (0, 1)
	388 #6 (0, 1)
	389 invokevirtual (0, 1)
	390 org/apache/commons/math3/genetics/AbstractListChromosome.newFixedLengthChromosome:(Ljava/util/List;)Lorg/apache/commons/math3/genetics/AbstractListChromosome; (0, 1)
	392 aload_2 (0, 1)
	393 aload (0, 1)
	394 #7 (0, 1)
	395 invokevirtual (0, 1)
	396 org/apache/commons/math3/genetics/AbstractListChromosome.newFixedLengthChromosome:(Ljava/util/List;)Lorg/apache/commons/math3/genetics/AbstractListChromosome; (0, 1)
	398 invokespecial (0, 1)
	399 org/apache/commons/math3/genetics/ChromosomePair.<init>:(Lorg/apache/commons/math3/genetics/Chromosome;Lorg/apache/commons/math3/genetics/Chromosome;)V (0, 1)
	401 areturn (0, 1)

