Method: <init>
	0 aload_0 (0, 0)
	1 invokespecial (0, 0)
	2 java/lang/Object.<init>:()V (0, 0)
	4 aload_0 (0, 0)
	5 ldc2_w (0, 0)
	6 18446744073709551615 (0, 0)
	8 putfield (0, 0)
	9 org/apache/commons/math3/genetics/FixedElapsedTime.endTime:J (0, 0)
	11 lload_1 (3, 1)
	12 lconst_0 (3, 1)
	13 lcmp (3, 1)
	14 ifge (3, 1)
	15 20 (3, 1)
	17 new (3, 1)
	18 org/apache/commons/math3/exception/NumberIsTooSmallException (3, 1)
	20 dup (3, 1)
	21 lload_1 (3, 1)
	22 invokestatic (3, 1)
	23 java/lang/Long.valueOf:(J)Ljava/lang/Long; (3, 1)
	25 iconst_0 (3, 1)
	26 invokestatic (3, 1)
	27 java/lang/Integer.valueOf:(I)Ljava/lang/Integer; (3, 1)
	29 iconst_1 (3, 1)
	30 invokespecial (3, 1)
	31 org/apache/commons/math3/exception/NumberIsTooSmallException.<init>:(Ljava/lang/Number;Ljava/lang/Number;Z)V (3, 1)
	33 athrow (3, 1)
	34 aload_0 (1, 1)
	35 aload_3 (1, 1)
	36 lload_1 (1, 1)
	37 invokevirtual (1, 1)
	38 java/util/concurrent/TimeUnit.toNanos:(J)J (1, 1)
	40 putfield (1, 1)
	41 org/apache/commons/math3/genetics/FixedElapsedTime.maxTimePeriod:J (1, 1)
	43 return (1, 1)

Method: isSatisfied
	0 aload_0 (1, 1)
	1 getfield (1, 1)
	2 org/apache/commons/math3/genetics/FixedElapsedTime.endTime:J (1, 1)
	4 lconst_0 (1, 1)
	5 lcmp (1, 1)
	6 ifge (1, 1)
	7 15 (1, 1)
	9 aload_0 (1, 1)
	10 invokestatic (1, 1)
	11 java/lang/System.nanoTime:()J (1, 1)
	13 aload_0 (1, 1)
	14 getfield (1, 1)
	15 org/apache/commons/math3/genetics/FixedElapsedTime.maxTimePeriod:J (1, 1)
	17 ladd (1, 1)
	18 putfield (1, 1)
	19 org/apache/commons/math3/genetics/FixedElapsedTime.endTime:J (1, 1)
	21 invokestatic (0, 0)
	22 java/lang/System.nanoTime:()J (0, 0)
	24 aload_0 (0, 0)
	25 getfield (0, 0)
	26 org/apache/commons/math3/genetics/FixedElapsedTime.endTime:J (0, 0)
	28 lcmp (0, 0)
	29 iflt (0, 0)
	30 7 (0, 0)
	32 iconst_1 (0, 0)
	33 goto (0, 0)
	34 4 (0, 0)
	36 iconst_0 (0, 0)
	37 ireturn (0, 0)

