Method: <init>
	0 aload_0 (0, 0)
	1 invokespecial (0, 0)
	2 java/lang/Object.<init>:()V (0, 0)
	4 aload_0 (0, 0)
	5 iconst_0 (0, 0)
	6 putfield (0, 0)
	7 org/apache/commons/math3/genetics/FixedGenerationCount.numGenerations:I (0, 0)
	9 iload_1 (2, 1)
	10 ifgt (2, 1)
	11 20 (2, 1)
	13 new (2, 1)
	14 org/apache/commons/math3/exception/NumberIsTooSmallException (2, 1)
	16 dup (2, 1)
	17 iload_1 (2, 1)
	18 invokestatic (2, 1)
	19 java/lang/Integer.valueOf:(I)Ljava/lang/Integer; (2, 1)
	21 iconst_1 (2, 1)
	22 invokestatic (2, 1)
	23 java/lang/Integer.valueOf:(I)Ljava/lang/Integer; (2, 1)
	25 iconst_1 (2, 1)
	26 invokespecial (2, 1)
	27 org/apache/commons/math3/exception/NumberIsTooSmallException.<init>:(Ljava/lang/Number;Ljava/lang/Number;Z)V (2, 1)
	29 athrow (2, 1)
	30 aload_0 (1, 1)
	31 iload_1 (1, 1)
	32 putfield (1, 1)
	33 org/apache/commons/math3/genetics/FixedGenerationCount.maxGenerations:I (1, 1)
	35 return (1, 1)

Method: isSatisfied
	0 aload_0 (1, 1)
	1 getfield (1, 1)
	2 org/apache/commons/math3/genetics/FixedGenerationCount.numGenerations:I (1, 1)
	4 aload_0 (1, 1)
	5 getfield (1, 1)
	6 org/apache/commons/math3/genetics/FixedGenerationCount.maxGenerations:I (1, 1)
	8 if_icmpge (1, 1)
	9 15 (1, 1)
	11 aload_0 (1, 1)
	12 dup (1, 1)
	13 getfield (1, 1)
	14 org/apache/commons/math3/genetics/FixedGenerationCount.numGenerations:I (1, 1)
	16 iconst_1 (1, 1)
	17 iadd (1, 1)
	18 putfield (1, 1)
	19 org/apache/commons/math3/genetics/FixedGenerationCount.numGenerations:I (1, 1)
	21 iconst_0 (1, 1)
	22 ireturn (1, 1)
	23 iconst_1 (0, 0)
	24 ireturn (0, 0)

Method: getNumGenerations
	0 aload_0 (0, 0)
	1 getfield (0, 0)
	2 org/apache/commons/math3/genetics/FixedGenerationCount.numGenerations:I (0, 0)
	4 ireturn (0, 0)

