Method: <init>
	0 aload_0 (0, 0)
	1 invokespecial (0, 0)
	4 aload_0 (0, 0)
	5 iconst_0 (0, 0)
	6 putfield (0, 0)
	9 dload_2 (2, 1)
	10 dconst_0 (2, 1)
	11 dcmpg (2, 1)
	12 iflt (2, 1)
	15 dload_2 (2, 1)
	16 dconst_1 (2, 1)
	17 dcmpl (2, 1)
	18 ifle (2, 1)
	21 new (2, 1)
	24 dup (2, 1)
	25 getstatic (2, 1)
	28 dload_2 (2, 1)
	29 invokestatic (2, 1)
	32 iconst_0 (2, 1)
	33 invokestatic (2, 1)
	36 iconst_1 (2, 1)
	37 invokestatic (2, 1)
	40 invokespecial (2, 1)
	43 athrow (2, 1)
	44 dload (2, 1)
	46 dconst_0 (2, 1)
	47 dcmpg (2, 1)
	48 iflt (2, 1)
	51 dload (2, 1)
	53 dconst_1 (2, 1)
	54 dcmpl (2, 1)
	55 ifle (2, 1)
	58 new (2, 1)
	61 dup (2, 1)
	62 getstatic (2, 1)
	65 dload (2, 1)
	67 invokestatic (2, 1)
	70 iconst_0 (2, 1)
	71 invokestatic (2, 1)
	74 iconst_1 (2, 1)
	75 invokestatic (2, 1)
	78 invokespecial (2, 1)
	81 athrow (2, 1)
	82 aload_0 (1, 1)
	83 aload_1 (1, 1)
	84 putfield (1, 1)
	87 aload_0 (1, 1)
	88 dload_2 (1, 1)
	89 putfield (1, 1)
	92 aload_0 (1, 1)
	93 aload (1, 1)
	95 putfield (1, 1)
	98 aload_0 (1, 1)
	99 dload (1, 1)
	101 putfield (1, 1)
	104 aload_0 (1, 1)
	105 aload (1, 1)
	107 putfield (1, 1)
	110 return (0, 0)

Method: setRandomGenerator
	0 aload_0 (0, 0)
	1 putstatic (0, 0)
	4 return (0, 0)

Method: getRandomGenerator
	0 getstatic (0, 0)
	3 areturn (0, 0)

Method: evolve
	0 aload_1 (0, 0)
	1 astore_3 (0, 0)
	2 aload_0 (0, 0)
	3 iconst_0 (0, 0)
	4 putfield (0, 0)
	7 aload_2 (1, 3)
	8 aload_3 (1, 3)
	9 invokeinterface (1, 3)
	14 ifne (1, 3)
	17 aload_0 (1, 3)
	18 aload_3 (1, 3)
	19 invokevirtual (1, 3)
	22 astore_3 (1, 3)
	23 aload_0 (1, 3)
	24 dup (1, 3)
	25 getfield (1, 3)
	28 iconst_1 (1, 3)
	29 iadd (1, 3)
	30 putfield (1, 3)
	33 goto (1, 3)
	36 aload_3 (0, 0)
	37 areturn (0, 0)

Method: nextGeneration
	0 aload_1 (0, 0)
	1 invokeinterface (0, 0)
	6 astore_2 (0, 0)
	7 invokestatic (0, 0)
	10 astore_3 (0, 0)
	11 aload_2 (1, 3)
	12 invokeinterface (1, 3)
	17 aload_2 (1, 3)
	18 invokeinterface (1, 3)
	23 if_icmpge (1, 3)
	26 aload_0 (1, 3)
	27 invokevirtual (1, 3)
	30 aload_1 (1, 3)
	31 invokeinterface (1, 3)
	36 astore (1, 3)
	38 aload_3 (2, 1)
	39 invokeinterface (2, 1)
	44 aload_0 (2, 1)
	45 invokevirtual (2, 1)
	48 dcmpg (2, 1)
	49 ifge (2, 1)
	52 aload_0 (2, 1)
	53 invokevirtual (2, 1)
	56 aload (2, 1)
	58 invokevirtual (2, 1)
	61 aload (2, 1)
	63 invokevirtual (2, 1)
	66 invokeinterface (2, 1)
	71 astore (2, 1)
	73 aload_3 (2, 1)
	74 invokeinterface (2, 1)
	79 aload_0 (2, 1)
	80 invokevirtual (2, 1)
	83 dcmpg (2, 1)
	84 ifge (2, 1)
	87 new (2, 1)
	90 dup (2, 1)
	91 aload_0 (2, 1)
	92 invokevirtual (2, 1)
	95 aload (2, 1)
	97 invokevirtual (2, 1)
	100 invokeinterface (2, 1)
	105 aload_0 (2, 1)
	106 invokevirtual (2, 1)
	109 aload (2, 1)
	111 invokevirtual (2, 1)
	114 invokeinterface (2, 1)
	119 invokespecial (2, 1)
	122 astore (2, 1)
	124 aload_2 (1, 3)
	125 aload (1, 3)
	127 invokevirtual (1, 3)
	130 invokeinterface (1, 3)
	135 aload_2 (2, 1)
	136 invokeinterface (2, 1)
	141 aload_2 (2, 1)
	142 invokeinterface (2, 1)
	147 if_icmpge (2, 1)
	150 aload_2 (2, 1)
	151 aload (2, 1)
	153 invokevirtual (2, 1)
	156 invokeinterface (2, 1)
	161 goto (0, 3)
	164 aload_2 (0, 3)
	165 areturn (0, 3)

Method: getCrossoverPolicy
	0 aload_0 (0, 0)
	1 getfield (0, 0)
	4 areturn (0, 0)

Method: getCrossoverRate
	0 aload_0 (0, 0)
	1 getfield (0, 0)
	4 dreturn (0, 0)

Method: getMutationPolicy
	0 aload_0 (0, 0)
	1 getfield (0, 0)
	4 areturn (0, 0)

Method: getMutationRate
	0 aload_0 (0, 0)
	1 getfield (0, 0)
	4 dreturn (0, 0)

Method: getSelectionPolicy
	0 aload_0 (0, 0)
	1 getfield (0, 0)
	4 areturn (0, 0)

Method: getGenerationsEvolved
	0 aload_0 (0, 0)
	1 getfield (0, 0)
	4 ireturn (0, 0)

Method: <clinit>
	0 new (0, 0)
	3 dup (0, 0)
	4 invokespecial (0, 0)
	7 putstatic (0, 0)
	10 return (0, 0)

