Method: <init>
	0 aload_0 (0, 0)
	1 invokespecial (0, 0)
	2 java/lang/Object.<init>:()V (0, 0)
	4 aload_0 (0, 0)
	5 iconst_0 (0, 0)
	6 putfield (0, 0)
	7 org/apache/commons/math3/genetics/GeneticAlgorithm.generationsEvolved:I (0, 0)
	9 dload_2 (3, 1)
	10 dconst_0 (3, 1)
	11 dcmpg (3, 1)
	12 iflt (3, 1)
	13 9 (3, 1)
	15 dload_2 (3, 1)
	16 dconst_1 (3, 1)
	17 dcmpl (3, 1)
	18 ifle (3, 1)
	19 26 (3, 1)
	21 new (3, 1)
	22 org/apache/commons/math3/exception/OutOfRangeException (3, 1)
	24 dup (3, 1)
	25 getstatic (3, 1)
	26 org/apache/commons/math3/exception/util/LocalizedFormats.CROSSOVER_RATE:Lorg/apache/commons/math3/exception/util/LocalizedFormats; (3, 1)
	28 dload_2 (3, 1)
	29 invokestatic (3, 1)
	30 java/lang/Double.valueOf:(D)Ljava/lang/Double; (3, 1)
	32 iconst_0 (3, 1)
	33 invokestatic (3, 1)
	34 java/lang/Integer.valueOf:(I)Ljava/lang/Integer; (3, 1)
	36 iconst_1 (3, 1)
	37 invokestatic (3, 1)
	38 java/lang/Integer.valueOf:(I)Ljava/lang/Integer; (3, 1)
	40 invokespecial (3, 1)
	41 org/apache/commons/math3/exception/OutOfRangeException.<init>:(Lorg/apache/commons/math3/exception/util/Localizable;Ljava/lang/Number;Ljava/lang/Number;Ljava/lang/Number;)V (3, 1)
	43 athrow (3, 1)
	44 dload (3, 1)
	45 #5 (3, 1)
	46 dconst_0 (3, 1)
	47 dcmpg (3, 1)
	48 iflt (3, 1)
	49 10 (3, 1)
	51 dload (3, 1)
	52 #5 (3, 1)
	53 dconst_1 (3, 1)
	54 dcmpl (3, 1)
	55 ifle (3, 1)
	56 27 (3, 1)
	58 new (3, 1)
	59 org/apache/commons/math3/exception/OutOfRangeException (3, 1)
	61 dup (3, 1)
	62 getstatic (3, 1)
	63 org/apache/commons/math3/exception/util/LocalizedFormats.MUTATION_RATE:Lorg/apache/commons/math3/exception/util/LocalizedFormats; (3, 1)
	65 dload (3, 1)
	66 #5 (3, 1)
	67 invokestatic (3, 1)
	68 java/lang/Double.valueOf:(D)Ljava/lang/Double; (3, 1)
	70 iconst_0 (3, 1)
	71 invokestatic (3, 1)
	72 java/lang/Integer.valueOf:(I)Ljava/lang/Integer; (3, 1)
	74 iconst_1 (3, 1)
	75 invokestatic (3, 1)
	76 java/lang/Integer.valueOf:(I)Ljava/lang/Integer; (3, 1)
	78 invokespecial (3, 1)
	79 org/apache/commons/math3/exception/OutOfRangeException.<init>:(Lorg/apache/commons/math3/exception/util/Localizable;Ljava/lang/Number;Ljava/lang/Number;Ljava/lang/Number;)V (3, 1)
	81 athrow (3, 1)
	82 aload_0 (1, 1)
	83 aload_1 (1, 1)
	84 putfield (1, 1)
	85 org/apache/commons/math3/genetics/GeneticAlgorithm.crossoverPolicy:Lorg/apache/commons/math3/genetics/CrossoverPolicy; (1, 1)
	87 aload_0 (1, 1)
	88 dload_2 (1, 1)
	89 putfield (1, 1)
	90 org/apache/commons/math3/genetics/GeneticAlgorithm.crossoverRate:D (1, 1)
	92 aload_0 (1, 1)
	93 aload (1, 1)
	94 #4 (1, 1)
	95 putfield (1, 1)
	96 org/apache/commons/math3/genetics/GeneticAlgorithm.mutationPolicy:Lorg/apache/commons/math3/genetics/MutationPolicy; (1, 1)
	98 aload_0 (1, 1)
	99 dload (1, 1)
	100 #5 (1, 1)
	101 putfield (1, 1)
	102 org/apache/commons/math3/genetics/GeneticAlgorithm.mutationRate:D (1, 1)
	104 aload_0 (1, 1)
	105 aload (1, 1)
	106 #7 (1, 1)
	107 putfield (1, 1)
	108 org/apache/commons/math3/genetics/GeneticAlgorithm.selectionPolicy:Lorg/apache/commons/math3/genetics/SelectionPolicy; (1, 1)
	110 return (1, 1)

Method: setRandomGenerator
	0 aload_0 (0, 0)
	1 putstatic (0, 0)
	2 org/apache/commons/math3/genetics/GeneticAlgorithm.randomGenerator:Lorg/apache/commons/math3/random/RandomGenerator; (0, 0)
	4 return (0, 0)

Method: getRandomGenerator
	0 getstatic (0, 0)
	1 org/apache/commons/math3/genetics/GeneticAlgorithm.randomGenerator:Lorg/apache/commons/math3/random/RandomGenerator; (0, 0)
	3 areturn (0, 0)

Method: evolve
	0 aload_1 (0, 0)
	1 astore_3 (0, 0)
	2 aload_0 (0, 0)
	3 iconst_0 (0, 0)
	4 putfield (0, 0)
	5 org/apache/commons/math3/genetics/GeneticAlgorithm.generationsEvolved:I (0, 0)
	7 aload_2 (1, 3)
	8 aload_3 (1, 3)
	9 invokeinterface (1, 3)
	10 org/apache/commons/math3/genetics/StoppingCondition.nextGeneration:(Lorg/apache/commons/math3/genetics/Population;)Lorg/apache/commons/math3/genetics/Population; (1, 3)
	12 0 (1, 3)
	14 ifne (1, 3)
	15 22 (1, 3)
	17 aload_0 (1, 3)
	18 aload_3 (1, 3)
	19 invokevirtual (1, 3)
	20 org/apache/commons/math3/genetics/GeneticAlgorithm.nextGeneration:(Lorg/apache/commons/math3/genetics/Population;)Lorg/apache/commons/math3/genetics/Population; (1, 3)
	22 astore_3 (1, 3)
	23 aload_0 (1, 3)
	24 dup (1, 3)
	25 getfield (1, 3)
	26 org/apache/commons/math3/genetics/GeneticAlgorithm.generationsEvolved:I (1, 3)
	28 iconst_1 (1, 3)
	29 iadd (1, 3)
	30 putfield (1, 3)
	31 org/apache/commons/math3/genetics/GeneticAlgorithm.generationsEvolved:I (1, 3)
	33 goto (1, 3)
	34 -26 (1, 3)
	36 aload_3 (0, 0)
	37 areturn (0, 0)

Method: nextGeneration
	0 aload_1 (0, 0)
	1 invokeinterface (0, 0)
	2 org/apache/commons/math3/genetics/Population.getRandomGenerator:()Lorg/apache/commons/math3/random/RandomGenerator; (0, 0)
	4 0 (0, 0)
	6 astore_2 (0, 0)
	7 invokestatic (0, 0)
	8 org/apache/commons/math3/genetics/GeneticAlgorithm.getRandomGenerator:()Lorg/apache/commons/math3/random/RandomGenerator; (0, 0)
	10 astore_3 (0, 0)
	11 aload_2 (1, 3)
	12 invokeinterface (1, 3)
	13 org/apache/commons/math3/genetics/Population.getPopulationLimit:()I (1, 3)
	15 0 (1, 3)
	17 aload_2 (1, 3)
	18 invokeinterface (1, 3)
	19 org/apache/commons/math3/genetics/Population.getSelectionPolicy:()Lorg/apache/commons/math3/genetics/SelectionPolicy; (1, 3)
	21 0 (1, 3)
	23 if_icmpge (1, 3)
	24 141 (1, 3)
	26 aload_0 (1, 3)
	27 invokevirtual (1, 3)
	28 org/apache/commons/math3/genetics/GeneticAlgorithm.getSelectionPolicy:()Lorg/apache/commons/math3/genetics/SelectionPolicy; (1, 3)
	30 aload_1 (1, 3)
	31 invokeinterface (1, 3)
	32 org/apache/commons/math3/genetics/SelectionPolicy.org/apache/commons/math3/random/RandomGenerator (1, 3)
	34 0 (1, 3)
	36 astore (1, 3)
	37 #4 (1, 3)
	38 aload_3 (2, 1)
	39 invokeinterface (2, 1)
	40 org/apache/commons/math3/random/RandomGenerator.getCrossoverRate:()D (2, 1)
	42 0 (2, 1)
	44 aload_0 (2, 1)
	45 invokevirtual (2, 1)
	46 org/apache/commons/math3/genetics/GeneticAlgorithm.getCrossoverRate:()D (2, 1)
	48 dcmpg (2, 1)
	49 ifge (2, 1)
	50 24 (2, 1)
	52 aload_0 (2, 1)
	53 invokevirtual (2, 1)
	54 org/apache/commons/math3/genetics/GeneticAlgorithm.getCrossoverPolicy:()Lorg/apache/commons/math3/genetics/CrossoverPolicy; (2, 1)
	56 aload (2, 1)
	57 #4 (2, 1)
	58 invokevirtual (2, 1)
	59 org/apache/commons/math3/genetics/ChromosomePair.getFirst:()Lorg/apache/commons/math3/genetics/Chromosome; (2, 1)
	61 aload (2, 1)
	62 #4 (2, 1)
	63 invokevirtual (2, 1)
	64 org/apache/commons/math3/genetics/ChromosomePair.getSecond:()Lorg/apache/commons/math3/genetics/Chromosome; (2, 1)
	66 invokeinterface (2, 1)
	67 org/apache/commons/math3/genetics/CrossoverPolicy.getMutationRate:()D (2, 1)
	69 0 (2, 1)
	71 astore (2, 1)
	72 #4 (2, 1)
	73 aload_3 (2, 1)
	74 invokeinterface (2, 1)
	75 org/apache/commons/math3/random/RandomGenerator.getCrossoverRate:()D (2, 1)
	77 0 (2, 1)
	79 aload_0 (2, 1)
	80 invokevirtual (2, 1)
	81 org/apache/commons/math3/genetics/GeneticAlgorithm.getMutationRate:()D (2, 1)
	83 dcmpg (2, 1)
	84 ifge (2, 1)
	85 40 (2, 1)
	87 new (2, 1)
	88 org/apache/commons/math3/genetics/ChromosomePair (2, 1)
	90 dup (2, 1)
	91 aload_0 (2, 1)
	92 invokevirtual (2, 1)
	93 org/apache/commons/math3/genetics/GeneticAlgorithm.getMutationPolicy:()Lorg/apache/commons/math3/genetics/MutationPolicy; (2, 1)
	95 aload (2, 1)
	96 #4 (2, 1)
	97 invokevirtual (2, 1)
	98 org/apache/commons/math3/genetics/ChromosomePair.getFirst:()Lorg/apache/commons/math3/genetics/Chromosome; (2, 1)
	100 invokeinterface (2, 1)
	101 org/apache/commons/math3/genetics/MutationPolicy.<init>:(Lorg/apache/commons/math3/genetics/Chromosome;Lorg/apache/commons/math3/genetics/Chromosome;)V (2, 1)
	103 0 (2, 1)
	105 aload_0 (2, 1)
	106 invokevirtual (2, 1)
	107 org/apache/commons/math3/genetics/GeneticAlgorithm.getMutationPolicy:()Lorg/apache/commons/math3/genetics/MutationPolicy; (2, 1)
	109 aload (2, 1)
	110 #4 (2, 1)
	111 invokevirtual (2, 1)
	112 org/apache/commons/math3/genetics/ChromosomePair.getSecond:()Lorg/apache/commons/math3/genetics/Chromosome; (2, 1)
	114 invokeinterface (2, 1)
	115 org/apache/commons/math3/genetics/MutationPolicy.<init>:(Lorg/apache/commons/math3/genetics/Chromosome;Lorg/apache/commons/math3/genetics/Chromosome;)V (2, 1)
	117 0 (2, 1)
	119 invokespecial (2, 1)
	120 org/apache/commons/math3/genetics/ChromosomePair.<init>:(Lorg/apache/commons/math3/genetics/Chromosome;Lorg/apache/commons/math3/genetics/Chromosome;)V (2, 1)
	122 astore (2, 1)
	123 #4 (2, 1)
	124 aload_2 (1, 3)
	125 aload (1, 3)
	126 #4 (1, 3)
	127 invokevirtual (1, 3)
	128 org/apache/commons/math3/genetics/ChromosomePair.getFirst:()Lorg/apache/commons/math3/genetics/Chromosome; (1, 3)
	130 invokeinterface (1, 3)
	131 org/apache/commons/math3/genetics/Population.org/apache/commons/math3/random/JDKRandomGenerator (1, 3)
	133 0 (1, 3)
	135 aload_2 (2, 1)
	136 invokeinterface (2, 1)
	137 org/apache/commons/math3/genetics/Population.getPopulationLimit:()I (2, 1)
	139 0 (2, 1)
	141 aload_2 (2, 1)
	142 invokeinterface (2, 1)
	143 org/apache/commons/math3/genetics/Population.getSelectionPolicy:()Lorg/apache/commons/math3/genetics/SelectionPolicy; (2, 1)
	145 0 (2, 1)
	147 if_icmpge (2, 1)
	148 14 (2, 1)
	150 aload_2 (2, 1)
	151 aload (2, 1)
	152 #4 (2, 1)
	153 invokevirtual (2, 1)
	154 org/apache/commons/math3/genetics/ChromosomePair.getSecond:()Lorg/apache/commons/math3/genetics/Chromosome; (2, 1)
	156 invokeinterface (2, 1)
	157 org/apache/commons/math3/genetics/Population.org/apache/commons/math3/random/JDKRandomGenerator (2, 1)
	159 0 (2, 1)
	161 goto (0, 0)
	162 -150 (0, 0)
	164 aload_2 (0, 0)
	165 areturn (0, 0)

Method: getCrossoverPolicy
	0 aload_0 (0, 0)
	1 getfield (0, 0)
	2 org/apache/commons/math3/genetics/GeneticAlgorithm.crossoverPolicy:Lorg/apache/commons/math3/genetics/CrossoverPolicy; (0, 0)
	4 areturn (0, 0)

Method: getCrossoverRate
	0 aload_0 (0, 0)
	1 getfield (0, 0)
	2 org/apache/commons/math3/genetics/GeneticAlgorithm.crossoverRate:D (0, 0)
	4 dreturn (0, 0)

Method: getMutationPolicy
	0 aload_0 (0, 0)
	1 getfield (0, 0)
	2 org/apache/commons/math3/genetics/GeneticAlgorithm.mutationPolicy:Lorg/apache/commons/math3/genetics/MutationPolicy; (0, 0)
	4 areturn (0, 0)

Method: getMutationRate
	0 aload_0 (0, 0)
	1 getfield (0, 0)
	2 org/apache/commons/math3/genetics/GeneticAlgorithm.mutationRate:D (0, 0)
	4 dreturn (0, 0)

Method: getSelectionPolicy
	0 aload_0 (0, 0)
	1 getfield (0, 0)
	2 org/apache/commons/math3/genetics/GeneticAlgorithm.selectionPolicy:Lorg/apache/commons/math3/genetics/SelectionPolicy; (0, 0)
	4 areturn (0, 0)

Method: getGenerationsEvolved
	0 aload_0 (0, 0)
	1 getfield (0, 0)
	2 org/apache/commons/math3/genetics/GeneticAlgorithm.generationsEvolved:I (0, 0)
	4 ireturn (0, 0)

Method: <clinit>
	0 new (0, 0)
	1 org/apache/commons/math3/random/JDKRandomGenerator (0, 0)
	3 dup (0, 0)
	4 invokespecial (0, 0)
	5 org/apache/commons/math3/random/JDKRandomGenerator.<init>:()V (0, 0)
	7 putstatic (0, 0)
	8 org/apache/commons/math3/genetics/GeneticAlgorithm.randomGenerator:Lorg/apache/commons/math3/random/RandomGenerator; (0, 0)
	10 return (0, 0)

