Method: <init>
	0 aload_0 (0, 0)
	1 invokespecial (0, 0)
	2 java/lang/Object.<init>:()V (0, 0)
	4 aload_1 (2, 1)
	5 ifnonnull (2, 1)
	6 11 (2, 1)
	8 new (2, 1)
	9 org/apache/commons/math3/exception/NullArgumentException (2, 1)
	11 dup (2, 1)
	12 invokespecial (2, 1)
	13 org/apache/commons/math3/exception/NullArgumentException.<init>:()V (2, 1)
	15 athrow (2, 1)
	16 iload_2 (2, 1)
	17 ifgt (2, 1)
	18 18 (2, 1)
	20 new (2, 1)
	21 org/apache/commons/math3/exception/NotPositiveException (2, 1)
	23 dup (2, 1)
	24 getstatic (2, 1)
	25 org/apache/commons/math3/exception/util/LocalizedFormats.POPULATION_LIMIT_NOT_POSITIVE:Lorg/apache/commons/math3/exception/util/LocalizedFormats; (2, 1)
	27 iload_2 (2, 1)
	28 invokestatic (2, 1)
	29 java/lang/Integer.valueOf:(I)Ljava/lang/Integer; (2, 1)
	31 invokespecial (2, 1)
	32 org/apache/commons/math3/exception/NotPositiveException.<init>:(Lorg/apache/commons/math3/exception/util/Localizable;Ljava/lang/Number;)V (2, 1)
	34 athrow (2, 1)
	35 aload_1 (2, 1)
	36 invokeinterface (2, 1)
	37 java/util/List.org/apache/commons/math3/exception/NumberIsTooLargeException (2, 1)
	39 0 (2, 1)
	41 iload_2 (2, 1)
	42 if_icmple (2, 1)
	43 28 (2, 1)
	45 new (2, 1)
	46 org/apache/commons/math3/exception/NumberIsTooLargeException (2, 1)
	48 dup (2, 1)
	49 getstatic (2, 1)
	50 org/apache/commons/math3/exception/util/LocalizedFormats.LIST_OF_CHROMOSOMES_BIGGER_THAN_POPULATION_SIZE:Lorg/apache/commons/math3/exception/util/LocalizedFormats; (2, 1)
	52 aload_1 (2, 1)
	53 invokeinterface (2, 1)
	54 java/util/List.org/apache/commons/math3/exception/NumberIsTooLargeException (2, 1)
	56 0 (2, 1)
	58 invokestatic (2, 1)
	59 java/lang/Integer.valueOf:(I)Ljava/lang/Integer; (2, 1)
	61 iload_2 (2, 1)
	62 invokestatic (2, 1)
	63 java/lang/Integer.valueOf:(I)Ljava/lang/Integer; (2, 1)
	65 iconst_0 (2, 1)
	66 invokespecial (2, 1)
	67 org/apache/commons/math3/exception/NumberIsTooLargeException.<init>:(Lorg/apache/commons/math3/exception/util/Localizable;Ljava/lang/Number;Ljava/lang/Number;Z)V (2, 1)
	69 athrow (2, 1)
	70 aload_0 (0, 0)
	71 iload_2 (0, 0)
	72 putfield (0, 0)
	73 org/apache/commons/math3/genetics/ListPopulation.populationLimit:I (0, 0)
	75 aload_0 (0, 0)
	76 new (0, 0)
	77 java/util/ArrayList (0, 0)
	79 dup (0, 0)
	80 iload_2 (0, 0)
	81 invokespecial (0, 0)
	82 java/util/ArrayList.<init>:(I)V (0, 0)
	84 putfield (0, 0)
	85 org/apache/commons/math3/genetics/ListPopulation.chromosomes:Ljava/util/List; (0, 0)
	87 aload_0 (0, 0)
	88 getfield (0, 0)
	89 org/apache/commons/math3/genetics/ListPopulation.chromosomes:Ljava/util/List; (0, 0)
	91 aload_1 (0, 0)
	92 invokeinterface (0, 0)
	93 java/util/List.clear:()V (0, 0)
	95 0 (0, 0)
	97 pop (0, 0)
	98 return (0, 0)

Method: setChromosomes
	0 aload_1 (1, 1)
	1 ifnonnull (1, 1)
	2 11 (1, 1)
	4 new (1, 1)
	5 org/apache/commons/math3/exception/NullArgumentException (1, 1)
	7 dup (1, 1)
	8 invokespecial (1, 1)
	9 org/apache/commons/math3/exception/NullArgumentException.<init>:()V (1, 1)
	11 athrow (1, 1)
	12 aload_1 (1, 1)
	13 invokeinterface (1, 1)
	14 java/util/List.org/apache/commons/math3/exception/NumberIsTooLargeException (1, 1)
	16 0 (1, 1)
	18 aload_0 (1, 1)
	19 getfield (1, 1)
	20 org/apache/commons/math3/genetics/ListPopulation.populationLimit:I (1, 1)
	22 if_icmple (1, 1)
	23 31 (1, 1)
	25 new (1, 1)
	26 org/apache/commons/math3/exception/NumberIsTooLargeException (1, 1)
	28 dup (1, 1)
	29 getstatic (1, 1)
	30 org/apache/commons/math3/exception/util/LocalizedFormats.LIST_OF_CHROMOSOMES_BIGGER_THAN_POPULATION_SIZE:Lorg/apache/commons/math3/exception/util/LocalizedFormats; (1, 1)
	32 aload_1 (1, 1)
	33 invokeinterface (1, 1)
	34 java/util/List.org/apache/commons/math3/exception/NumberIsTooLargeException (1, 1)
	36 0 (1, 1)
	38 invokestatic (1, 1)
	39 java/lang/Integer.valueOf:(I)Ljava/lang/Integer; (1, 1)
	41 aload_0 (1, 1)
	42 getfield (1, 1)
	43 org/apache/commons/math3/genetics/ListPopulation.populationLimit:I (1, 1)
	45 invokestatic (1, 1)
	46 java/lang/Integer.valueOf:(I)Ljava/lang/Integer; (1, 1)
	48 iconst_0 (1, 1)
	49 invokespecial (1, 1)
	50 org/apache/commons/math3/exception/NumberIsTooLargeException.<init>:(Lorg/apache/commons/math3/exception/util/Localizable;Ljava/lang/Number;Ljava/lang/Number;Z)V (1, 1)
	52 athrow (1, 1)
	53 aload_0 (0, 0)
	54 getfield (0, 0)
	55 org/apache/commons/math3/genetics/ListPopulation.chromosomes:Ljava/util/List; (0, 0)
	57 invokeinterface (0, 0)
	58 java/util/List.java/util/Collection (0, 0)
	60 0 (0, 0)
	62 aload_0 (0, 0)
	63 getfield (0, 0)
	64 org/apache/commons/math3/genetics/ListPopulation.chromosomes:Ljava/util/List; (0, 0)
	66 aload_1 (0, 0)
	67 invokeinterface (0, 0)
	68 java/util/List.clear:()V (0, 0)
	70 0 (0, 0)
	72 pop (0, 0)
	73 return (0, 0)

Method: addChromosomes
	0 aload_0 (1, 1)
	1 getfield (1, 1)
	2 org/apache/commons/math3/genetics/ListPopulation.chromosomes:Ljava/util/List; (1, 1)
	4 invokeinterface (1, 1)
	5 java/util/List.org/apache/commons/math3/exception/NumberIsTooLargeException (1, 1)
	7 0 (1, 1)
	9 aload_1 (1, 1)
	10 invokeinterface (1, 1)
	11 java/util/Collection.org/apache/commons/math3/exception/NumberIsTooLargeException (1, 1)
	13 0 (1, 1)
	15 iadd (1, 1)
	16 aload_0 (1, 1)
	17 getfield (1, 1)
	18 org/apache/commons/math3/genetics/ListPopulation.populationLimit:I (1, 1)
	20 if_icmple (1, 1)
	21 34 (1, 1)
	23 new (1, 1)
	24 org/apache/commons/math3/exception/NumberIsTooLargeException (1, 1)
	26 dup (1, 1)
	27 getstatic (1, 1)
	28 org/apache/commons/math3/exception/util/LocalizedFormats.LIST_OF_CHROMOSOMES_BIGGER_THAN_POPULATION_SIZE:Lorg/apache/commons/math3/exception/util/LocalizedFormats; (1, 1)
	30 aload_0 (1, 1)
	31 getfield (1, 1)
	32 org/apache/commons/math3/genetics/ListPopulation.chromosomes:Ljava/util/List; (1, 1)
	34 invokeinterface (1, 1)
	35 java/util/List.org/apache/commons/math3/exception/NumberIsTooLargeException (1, 1)
	37 0 (1, 1)
	39 invokestatic (1, 1)
	40 java/lang/Integer.valueOf:(I)Ljava/lang/Integer; (1, 1)
	42 aload_0 (1, 1)
	43 getfield (1, 1)
	44 org/apache/commons/math3/genetics/ListPopulation.populationLimit:I (1, 1)
	46 invokestatic (1, 1)
	47 java/lang/Integer.valueOf:(I)Ljava/lang/Integer; (1, 1)
	49 iconst_0 (1, 1)
	50 invokespecial (1, 1)
	51 org/apache/commons/math3/exception/NumberIsTooLargeException.<init>:(Lorg/apache/commons/math3/exception/util/Localizable;Ljava/lang/Number;Ljava/lang/Number;Z)V (1, 1)
	53 athrow (1, 1)
	54 aload_0 (0, 0)
	55 getfield (0, 0)
	56 org/apache/commons/math3/genetics/ListPopulation.chromosomes:Ljava/util/List; (0, 0)
	58 aload_1 (0, 0)
	59 invokeinterface (0, 0)
	60 java/util/List.clear:()V (0, 0)
	62 0 (0, 0)
	64 pop (0, 0)
	65 return (0, 0)

Method: getChromosomes
	0 aload_0 (0, 1)
	1 getfield (0, 1)
	2 org/apache/commons/math3/genetics/ListPopulation.chromosomes:Ljava/util/List; (0, 1)
	4 invokestatic (0, 1)
	5 java/util/Collections.unmodifiableList:(Ljava/util/List;)Ljava/util/List; (0, 1)
	7 areturn (0, 1)

Method: getChromosomeList
	0 aload_0 (0, 0)
	1 getfield (0, 0)
	2 org/apache/commons/math3/genetics/ListPopulation.chromosomes:Ljava/util/List; (0, 0)
	4 areturn (0, 0)

Method: addChromosome
	0 aload_0 (1, 1)
	1 getfield (1, 1)
	2 org/apache/commons/math3/genetics/ListPopulation.chromosomes:Ljava/util/List; (1, 1)
	4 invokeinterface (1, 1)
	5 java/util/List.org/apache/commons/math3/exception/NumberIsTooLargeException (1, 1)
	7 0 (1, 1)
	9 aload_0 (1, 1)
	10 getfield (1, 1)
	11 org/apache/commons/math3/genetics/ListPopulation.populationLimit:I (1, 1)
	13 if_icmplt (1, 1)
	14 34 (1, 1)
	16 new (1, 1)
	17 org/apache/commons/math3/exception/NumberIsTooLargeException (1, 1)
	19 dup (1, 1)
	20 getstatic (1, 1)
	21 org/apache/commons/math3/exception/util/LocalizedFormats.LIST_OF_CHROMOSOMES_BIGGER_THAN_POPULATION_SIZE:Lorg/apache/commons/math3/exception/util/LocalizedFormats; (1, 1)
	23 aload_0 (1, 1)
	24 getfield (1, 1)
	25 org/apache/commons/math3/genetics/ListPopulation.chromosomes:Ljava/util/List; (1, 1)
	27 invokeinterface (1, 1)
	28 java/util/List.org/apache/commons/math3/exception/NumberIsTooLargeException (1, 1)
	30 0 (1, 1)
	32 invokestatic (1, 1)
	33 java/lang/Integer.valueOf:(I)Ljava/lang/Integer; (1, 1)
	35 aload_0 (1, 1)
	36 getfield (1, 1)
	37 org/apache/commons/math3/genetics/ListPopulation.populationLimit:I (1, 1)
	39 invokestatic (1, 1)
	40 java/lang/Integer.valueOf:(I)Ljava/lang/Integer; (1, 1)
	42 iconst_0 (1, 1)
	43 invokespecial (1, 1)
	44 org/apache/commons/math3/exception/NumberIsTooLargeException.<init>:(Lorg/apache/commons/math3/exception/util/Localizable;Ljava/lang/Number;Ljava/lang/Number;Z)V (1, 1)
	46 athrow (1, 1)
	47 aload_0 (0, 0)
	48 getfield (0, 0)
	49 org/apache/commons/math3/genetics/ListPopulation.chromosomes:Ljava/util/List; (0, 0)
	51 aload_1 (0, 0)
	52 invokeinterface (0, 0)
	53 java/util/List.get:(I)Ljava/lang/Object; (0, 0)
	55 0 (0, 0)
	57 pop (0, 0)
	58 return (0, 0)

Method: getFittestChromosome
	0 aload_0 (0, 0)
	1 getfield (0, 0)
	2 org/apache/commons/math3/genetics/ListPopulation.chromosomes:Ljava/util/List; (0, 0)
	4 iconst_0 (0, 0)
	5 invokeinterface (0, 0)
	6 java/util/List.org/apache/commons/math3/genetics/Chromosome (0, 0)
	8 0 (0, 0)
	10 checkcast (0, 0)
	11 org/apache/commons/math3/genetics/Chromosome (0, 0)
	13 astore_1 (0, 0)
	14 aload_0 (1, 4)
	15 getfield (1, 4)
	16 org/apache/commons/math3/genetics/ListPopulation.chromosomes:Ljava/util/List; (1, 4)
	18 invokeinterface (1, 4)
	19 java/util/List.java/util/Iterator (1, 4)
	21 0 (1, 4)
	23 astore_2 (1, 4)
	24 aload_2 (1, 4)
	25 invokeinterface (1, 4)
	26 java/util/Iterator.next:()Ljava/lang/Object; (1, 4)
	28 0 (1, 4)
	30 ifeq (1, 4)
	31 26 (1, 4)
	33 aload_2 (1, 4)
	34 invokeinterface (1, 4)
	35 java/util/Iterator.compareTo:(Lorg/apache/commons/math3/genetics/Chromosome;)I (1, 4)
	37 0 (1, 4)
	39 checkcast (1, 4)
	40 org/apache/commons/math3/genetics/Chromosome (1, 4)
	42 astore_3 (1, 4)
	43 aload_3 (2, 1)
	44 aload_1 (2, 1)
	45 invokevirtual (2, 1)
	46 org/apache/commons/math3/genetics/Chromosome.compareTo:(Lorg/apache/commons/math3/genetics/Chromosome;)I (2, 1)
	48 ifle (2, 1)
	49 5 (2, 1)
	51 aload_3 (2, 1)
	52 astore_1 (2, 1)
	53 goto (0, 0)
	54 -29 (0, 0)
	56 aload_1 (0, 0)
	57 areturn (0, 0)

Method: getPopulationLimit
	0 aload_0 (0, 0)
	1 getfield (0, 0)
	2 org/apache/commons/math3/genetics/ListPopulation.populationLimit:I (0, 0)
	4 ireturn (0, 0)

Method: setPopulationLimit
	0 iload_1 (1, 1)
	1 ifgt (1, 1)
	2 18 (1, 1)
	4 new (1, 1)
	5 org/apache/commons/math3/exception/NotPositiveException (1, 1)
	7 dup (1, 1)
	8 getstatic (1, 1)
	9 org/apache/commons/math3/exception/util/LocalizedFormats.POPULATION_LIMIT_NOT_POSITIVE:Lorg/apache/commons/math3/exception/util/LocalizedFormats; (1, 1)
	11 iload_1 (1, 1)
	12 invokestatic (1, 1)
	13 java/lang/Integer.valueOf:(I)Ljava/lang/Integer; (1, 1)
	15 invokespecial (1, 1)
	16 org/apache/commons/math3/exception/NotPositiveException.<init>:(Lorg/apache/commons/math3/exception/util/Localizable;Ljava/lang/Number;)V (1, 1)
	18 athrow (1, 1)
	19 iload_1 (1, 1)
	20 aload_0 (1, 1)
	21 getfield (1, 1)
	22 org/apache/commons/math3/genetics/ListPopulation.chromosomes:Ljava/util/List; (1, 1)
	24 invokeinterface (1, 1)
	25 java/util/List.org/apache/commons/math3/exception/NumberIsTooLargeException (1, 1)
	27 0 (1, 1)
	29 if_icmpge (1, 1)
	30 28 (1, 1)
	32 new (1, 1)
	33 org/apache/commons/math3/exception/NumberIsTooSmallException (1, 1)
	35 dup (1, 1)
	36 iload_1 (1, 1)
	37 invokestatic (1, 1)
	38 java/lang/Integer.valueOf:(I)Ljava/lang/Integer; (1, 1)
	40 aload_0 (1, 1)
	41 getfield (1, 1)
	42 org/apache/commons/math3/genetics/ListPopulation.chromosomes:Ljava/util/List; (1, 1)
	44 invokeinterface (1, 1)
	45 java/util/List.org/apache/commons/math3/exception/NumberIsTooLargeException (1, 1)
	47 0 (1, 1)
	49 invokestatic (1, 1)
	50 java/lang/Integer.valueOf:(I)Ljava/lang/Integer; (1, 1)
	52 iconst_1 (1, 1)
	53 invokespecial (1, 1)
	54 org/apache/commons/math3/exception/NumberIsTooSmallException.<init>:(Ljava/lang/Number;Ljava/lang/Number;Z)V (1, 1)
	56 athrow (1, 1)
	57 aload_0 (0, 0)
	58 iload_1 (0, 0)
	59 putfield (0, 0)
	60 org/apache/commons/math3/genetics/ListPopulation.populationLimit:I (0, 0)
	62 return (0, 0)

Method: getPopulationSize
	0 aload_0 (0, 0)
	1 getfield (0, 0)
	2 org/apache/commons/math3/genetics/ListPopulation.chromosomes:Ljava/util/List; (0, 0)
	4 invokeinterface (0, 0)
	5 java/util/List.org/apache/commons/math3/exception/NumberIsTooLargeException (0, 0)
	7 0 (0, 0)
	9 ireturn (0, 0)

Method: toString
	0 aload_0 (0, 0)
	1 getfield (0, 0)
	2 org/apache/commons/math3/genetics/ListPopulation.chromosomes:Ljava/util/List; (0, 0)
	4 invokevirtual (0, 0)
	5 java/lang/Object.toString:()Ljava/lang/String; (0, 0)
	7 areturn (0, 0)

Method: iterator
	0 aload_0 (0, 0)
	1 invokevirtual (0, 0)
	2 org/apache/commons/math3/genetics/ListPopulation.getChromosomes:()Ljava/util/List; (0, 0)
	4 invokeinterface (0, 0)
	5 java/util/List.java/util/Iterator (0, 0)
	7 0 (0, 0)
	9 areturn (0, 0)

