Method: <init>
	0 aload_0 (0, 0)
	1 invokespecial (0, 0)
	4 aload_1 (1, 1)
	5 ifnonnull (1, 1)
	8 new (1, 1)
	11 dup (1, 1)
	12 invokespecial (1, 1)
	15 athrow (1, 1)
	16 iload_2 (1, 1)
	17 ifgt (1, 1)
	20 new (1, 1)
	23 dup (1, 1)
	24 getstatic (1, 1)
	27 iload_2 (1, 1)
	28 invokestatic (1, 1)
	31 invokespecial (1, 1)
	34 athrow (1, 1)
	35 aload_1 (1, 1)
	36 invokeinterface (1, 1)
	41 iload_2 (1, 1)
	42 if_icmple (1, 1)
	45 new (1, 1)
	48 dup (1, 1)
	49 getstatic (1, 1)
	52 aload_1 (1, 1)
	53 invokeinterface (1, 1)
	58 invokestatic (1, 1)
	61 iload_2 (1, 1)
	62 invokestatic (1, 1)
	65 iconst_0 (1, 1)
	66 invokespecial (1, 1)
	69 athrow (1, 1)
	70 aload_0 (0, 0)
	71 iload_2 (0, 0)
	72 putfield (0, 0)
	75 aload_0 (0, 0)
	76 new (0, 0)
	79 dup (0, 0)
	80 iload_2 (0, 0)
	81 invokespecial (0, 0)
	84 putfield (0, 0)
	87 aload_0 (0, 0)
	88 getfield (0, 0)
	91 aload_1 (0, 0)
	92 invokeinterface (0, 0)
	97 pop (0, 0)
	98 return (0, 0)

Method: setChromosomes
	0 aload_1 (1, 1)
	1 ifnonnull (1, 1)
	4 new (1, 1)
	7 dup (1, 1)
	8 invokespecial (1, 1)
	11 athrow (1, 1)
	12 aload_1 (1, 1)
	13 invokeinterface (1, 1)
	18 aload_0 (1, 1)
	19 getfield (1, 1)
	22 if_icmple (1, 1)
	25 new (1, 1)
	28 dup (1, 1)
	29 getstatic (1, 1)
	32 aload_1 (1, 1)
	33 invokeinterface (1, 1)
	38 invokestatic (1, 1)
	41 aload_0 (1, 1)
	42 getfield (1, 1)
	45 invokestatic (1, 1)
	48 iconst_0 (1, 1)
	49 invokespecial (1, 1)
	52 athrow (1, 1)
	53 aload_0 (0, 0)
	54 getfield (0, 0)
	57 invokeinterface (0, 0)
	62 aload_0 (0, 0)
	63 getfield (0, 0)
	66 aload_1 (0, 0)
	67 invokeinterface (0, 0)
	72 pop (0, 0)
	73 return (0, 0)

Method: addChromosomes
	0 aload_0 (1, 1)
	1 getfield (1, 1)
	4 invokeinterface (1, 1)
	9 aload_1 (1, 1)
	10 invokeinterface (1, 1)
	15 iadd (1, 1)
	16 aload_0 (1, 1)
	17 getfield (1, 1)
	20 if_icmple (1, 1)
	23 new (1, 1)
	26 dup (1, 1)
	27 getstatic (1, 1)
	30 aload_0 (1, 1)
	31 getfield (1, 1)
	34 invokeinterface (1, 1)
	39 invokestatic (1, 1)
	42 aload_0 (1, 1)
	43 getfield (1, 1)
	46 invokestatic (1, 1)
	49 iconst_0 (1, 1)
	50 invokespecial (1, 1)
	53 athrow (1, 1)
	54 aload_0 (0, 0)
	55 getfield (0, 0)
	58 aload_1 (0, 0)
	59 invokeinterface (0, 0)
	64 pop (0, 0)
	65 return (0, 0)

Method: getChromosomes
	0 aload_0 (0, 1)
	1 getfield (0, 1)
	4 invokestatic (0, 1)
	7 areturn (0, 1)

Method: getChromosomeList
	0 aload_0 (0, 0)
	1 getfield (0, 0)
	4 areturn (0, 0)

Method: addChromosome
	0 aload_0 (1, 1)
	1 getfield (1, 1)
	4 invokeinterface (1, 1)
	9 aload_0 (1, 1)
	10 getfield (1, 1)
	13 if_icmplt (1, 1)
	16 new (1, 1)
	19 dup (1, 1)
	20 getstatic (1, 1)
	23 aload_0 (1, 1)
	24 getfield (1, 1)
	27 invokeinterface (1, 1)
	32 invokestatic (1, 1)
	35 aload_0 (1, 1)
	36 getfield (1, 1)
	39 invokestatic (1, 1)
	42 iconst_0 (1, 1)
	43 invokespecial (1, 1)
	46 athrow (1, 1)
	47 aload_0 (0, 0)
	48 getfield (0, 0)
	51 aload_1 (0, 0)
	52 invokeinterface (0, 0)
	57 pop (0, 0)
	58 return (0, 0)

Method: getFittestChromosome
	0 aload_0 (0, 0)
	1 getfield (0, 0)
	4 iconst_0 (0, 0)
	5 invokeinterface (0, 0)
	10 checkcast (0, 0)
	13 astore_1 (0, 0)
	14 aload_0 (1, 4)
	15 getfield (1, 4)
	18 invokeinterface (1, 4)
	23 astore_2 (1, 4)
	24 aload_2 (1, 4)
	25 invokeinterface (1, 4)
	30 ifeq (1, 4)
	33 aload_2 (1, 4)
	34 invokeinterface (1, 4)
	39 checkcast (1, 4)
	42 astore_3 (1, 4)
	43 aload_3 (2, 1)
	44 aload_1 (2, 1)
	45 invokevirtual (2, 1)
	48 ifle (2, 1)
	51 aload_3 (2, 1)
	52 astore_1 (2, 1)
	53 goto (0, 0)
	56 aload_1 (0, 0)
	57 areturn (0, 0)

Method: getPopulationLimit
	0 aload_0 (0, 0)
	1 getfield (0, 0)
	4 ireturn (0, 0)

Method: setPopulationLimit
	0 iload_1 (1, 1)
	1 ifgt (1, 1)
	4 new (1, 1)
	7 dup (1, 1)
	8 getstatic (1, 1)
	11 iload_1 (1, 1)
	12 invokestatic (1, 1)
	15 invokespecial (1, 1)
	18 athrow (1, 1)
	19 iload_1 (1, 1)
	20 aload_0 (1, 1)
	21 getfield (1, 1)
	24 invokeinterface (1, 1)
	29 if_icmpge (1, 1)
	32 new (1, 1)
	35 dup (1, 1)
	36 iload_1 (1, 1)
	37 invokestatic (1, 1)
	40 aload_0 (1, 1)
	41 getfield (1, 1)
	44 invokeinterface (1, 1)
	49 invokestatic (1, 1)
	52 iconst_1 (1, 1)
	53 invokespecial (1, 1)
	56 athrow (1, 1)
	57 aload_0 (0, 0)
	58 iload_1 (0, 0)
	59 putfield (0, 0)
	62 return (0, 0)

Method: getPopulationSize
	0 aload_0 (0, 0)
	1 getfield (0, 0)
	4 invokeinterface (0, 0)
	9 ireturn (0, 0)

Method: toString
	0 aload_0 (0, 0)
	1 getfield (0, 0)
	4 invokevirtual (0, 0)
	7 areturn (0, 0)

Method: iterator
	0 aload_0 (0, 0)
	1 invokevirtual (0, 0)
	4 invokeinterface (0, 0)
	9 areturn (0, 0)

