Method: mutate
	0 aload_1 (1, 1)
	1 instanceof (1, 1)
	2 org/apache/commons/math3/genetics/RandomKey (1, 1)
	4 ifne (1, 1)
	5 28 (1, 1)
	7 new (1, 1)
	8 org/apache/commons/math3/exception/MathIllegalArgumentException (1, 1)
	10 dup (1, 1)
	11 getstatic (1, 1)
	12 org/apache/commons/math3/exception/util/LocalizedFormats.RANDOMKEY_MUTATION_WRONG_CLASS:Lorg/apache/commons/math3/exception/util/LocalizedFormats; (1, 1)
	14 iconst_1 (1, 1)
	15 anewarray (1, 1)
	16 java/lang/Object (1, 1)
	18 dup (1, 1)
	19 iconst_0 (1, 1)
	20 aload_1 (1, 1)
	21 invokevirtual (1, 1)
	22 java/lang/Object.getClass:()Ljava/lang/Class; (1, 1)
	24 invokevirtual (1, 1)
	25 java/lang/Class.getSimpleName:()Ljava/lang/String; (1, 1)
	27 aastore (1, 1)
	28 invokespecial (1, 1)
	29 org/apache/commons/math3/exception/MathIllegalArgumentException.<init>:(Lorg/apache/commons/math3/exception/util/Localizable;[Ljava/lang/Object;)V (1, 1)
	31 athrow (1, 1)
	32 aload_1 (0, 0)
	33 checkcast (0, 0)
	34 org/apache/commons/math3/genetics/RandomKey (0, 0)
	36 astore_2 (0, 0)
	37 aload_2 (0, 0)
	38 invokevirtual (0, 0)
	39 org/apache/commons/math3/genetics/RandomKey.getRepresentation:()Ljava/util/List; (0, 0)
	41 astore_3 (0, 0)
	42 invokestatic (0, 0)
	43 org/apache/commons/math3/genetics/GeneticAlgorithm.getRandomGenerator:()Lorg/apache/commons/math3/random/RandomGenerator; (0, 0)
	45 aload_3 (0, 0)
	46 invokeinterface (0, 0)
	47 java/util/List.org/apache/commons/math3/random/RandomGenerator (0, 0)
	49 0 (0, 0)
	51 invokeinterface (0, 0)
	52 org/apache/commons/math3/random/RandomGenerator.java/util/ArrayList (0, 0)
	54 0 (0, 0)
	56 istore (0, 0)
	57 #4 (0, 0)
	58 new (0, 0)
	59 java/util/ArrayList (0, 0)
	61 dup (0, 0)
	62 aload_3 (0, 0)
	63 invokespecial (0, 0)
	64 java/util/ArrayList.<init>:(Ljava/util/Collection;)V (0, 0)
	66 astore (0, 0)
	67 #5 (0, 0)
	68 aload (0, 0)
	69 #5 (0, 0)
	70 iload (0, 0)
	71 #4 (0, 0)
	72 invokestatic (0, 0)
	73 org/apache/commons/math3/genetics/GeneticAlgorithm.getRandomGenerator:()Lorg/apache/commons/math3/random/RandomGenerator; (0, 0)
	75 invokeinterface (0, 0)
	76 org/apache/commons/math3/random/RandomGenerator.java/lang/Double (0, 0)
	78 0 (0, 0)
	80 invokestatic (0, 0)
	81 java/lang/Double.valueOf:(D)Ljava/lang/Double; (0, 0)
	83 invokeinterface (0, 0)
	84 java/util/List.newFixedLengthChromosome:(Ljava/util/List;)Lorg/apache/commons/math3/genetics/AbstractListChromosome; (0, 0)
	86 0 (0, 0)
	88 pop (0, 0)
	89 aload_2 (0, 0)
	90 aload (0, 0)
	91 #5 (0, 0)
	92 invokevirtual (0, 0)
	93 org/apache/commons/math3/genetics/RandomKey.newFixedLengthChromosome:(Ljava/util/List;)Lorg/apache/commons/math3/genetics/AbstractListChromosome; (0, 0)
	95 areturn (0, 0)

