Method: <init>
	0 aload_0 (0, 0)
	1 aload_1 (0, 0)
	2 invokestatic (0, 0)
	5 invokespecial (0, 0)
	8 return (0, 0)

Method: decode
	0 aload_1 (0, 0)
	1 aload_0 (0, 0)
	2 invokevirtual (0, 0)
	5 aload_0 (0, 0)
	6 getfield (0, 0)
	9 invokestatic (0, 0)
	12 areturn (0, 0)

Method: decodeGeneric
	0 aload_0 (0, 0)
	1 invokeinterface (0, 0)
	6 istore_3 (0, 0)
	7 aload_1 (1, 1)
	8 invokeinterface (1, 1)
	13 iload_3 (1, 1)
	14 if_icmpeq (1, 1)
	17 new (1, 1)
	20 dup (1, 1)
	21 aload_1 (1, 1)
	22 invokeinterface (1, 1)
	27 iload_3 (1, 1)
	28 invokespecial (1, 1)
	31 athrow (1, 1)
	32 aload_2 (1, 1)
	33 invokeinterface (1, 1)
	38 iload_3 (1, 1)
	39 if_icmpeq (1, 1)
	42 new (1, 1)
	45 dup (1, 1)
	46 aload_2 (1, 1)
	47 invokeinterface (1, 1)
	52 iload_3 (1, 1)
	53 invokespecial (1, 1)
	56 athrow (1, 1)
	57 new (0, 1)
	60 dup (0, 1)
	61 aload_1 (0, 1)
	62 invokespecial (0, 1)
	65 astore (0, 1)
	67 new (0, 4)
	70 dup (0, 4)
	71 iload_3 (0, 4)
	72 invokespecial (0, 4)
	75 astore (0, 4)
	77 iconst_0 (1, 4)
	78 istore (1, 4)
	80 iload (1, 4)
	82 iload_3 (1, 4)
	83 if_icmpge (1, 4)
	86 aload (1, 4)
	88 aload_2 (1, 4)
	89 iload (1, 4)
	91 invokeinterface (1, 4)
	96 invokeinterface (1, 4)
	101 istore (1, 4)
	103 aload (1, 4)
	105 aload_0 (1, 4)
	106 iload (1, 4)
	108 invokeinterface (1, 4)
	113 invokeinterface (1, 4)
	118 pop (1, 4)
	119 aload (1, 4)
	121 iload (1, 4)
	123 aconst_null (1, 4)
	124 invokeinterface (1, 4)
	129 pop (1, 4)
	130 iinc (1, 4)
	133 goto (1, 4)
	136 aload (0, 4)
	138 areturn (0, 4)

Method: isSame
	0 aload_1 (1, 1)
	1 instanceof (1, 1)
	4 ifne (1, 1)
	7 iconst_0 (1, 1)
	8 ireturn (1, 1)
	9 aload_1 (0, 0)
	10 checkcast (0, 0)
	13 astore_2 (0, 0)
	14 aload_0 (1, 1)
	15 invokevirtual (1, 1)
	18 aload_2 (1, 1)
	19 invokevirtual (1, 1)
	22 if_icmpeq (1, 1)
	25 iconst_0 (1, 1)
	26 ireturn (1, 1)
	27 aload_0 (0, 1)
	28 getfield (0, 1)
	31 astore_3 (0, 1)
	32 aload_2 (0, 1)
	33 getfield (0, 1)
	36 astore (0, 1)
	38 iconst_0 (1, 4)
	39 istore (1, 4)
	41 iload (1, 4)
	43 aload_0 (1, 4)
	44 invokevirtual (1, 4)
	47 if_icmpge (1, 4)
	50 aload_3 (2, 1)
	51 iload (2, 1)
	53 invokeinterface (2, 1)
	58 aload (2, 1)
	60 iload (2, 1)
	62 invokeinterface (2, 1)
	67 if_acmpeq (2, 1)
	70 iconst_0 (2, 1)
	71 ireturn (2, 1)
	72 iinc (2, 1)
	75 goto (2, 1)
	78 iconst_1 (1, 4)
	79 ireturn (1, 4)

Method: checkValidity
	0 aload_1 (1, 4)
	1 invokeinterface (1, 4)
	6 astore_2 (1, 4)
	7 aload_2 (1, 4)
	8 invokeinterface (1, 4)
	13 ifeq (1, 4)
	16 aload_2 (1, 4)
	17 invokeinterface (1, 4)
	22 checkcast (1, 4)
	25 invokevirtual (1, 4)
	28 dstore_3 (1, 4)
	29 dload_3 (2, 1)
	30 dconst_0 (2, 1)
	31 dcmpg (2, 1)
	32 iflt (2, 1)
	35 dload_3 (2, 1)
	36 dconst_1 (2, 1)
	37 dcmpl (2, 1)
	38 ifle (2, 1)
	41 new (2, 1)
	44 dup (2, 1)
	45 getstatic (2, 1)
	48 iconst_3 (2, 1)
	49 anewarray (2, 1)
	52 dup (2, 1)
	53 iconst_0 (2, 1)
	54 dload_3 (2, 1)
	55 invokestatic (2, 1)
	58 aastore (2, 1)
	59 dup (2, 1)
	60 iconst_1 (2, 1)
	61 iconst_0 (2, 1)
	62 invokestatic (2, 1)
	65 aastore (2, 1)
	66 dup (2, 1)
	67 iconst_2 (2, 1)
	68 iconst_1 (2, 1)
	69 invokestatic (2, 1)
	72 aastore (2, 1)
	73 invokespecial (2, 1)
	76 athrow (2, 1)
	77 goto (0, 0)
	80 return (0, 0)

Method: randomPermutation
	0 new (0, 0)
	3 dup (0, 0)
	4 iload_0 (0, 0)
	5 invokespecial (0, 0)
	8 astore_1 (0, 0)
	9 iconst_0 (1, 4)
	10 istore_2 (1, 4)
	11 iload_2 (1, 4)
	12 iload_0 (1, 4)
	13 if_icmpge (1, 4)
	16 aload_1 (1, 4)
	17 invokestatic (1, 4)
	20 invokeinterface (1, 4)
	25 invokestatic (1, 4)
	28 invokeinterface (1, 4)
	33 pop (1, 4)
	34 iinc (1, 4)
	37 goto (1, 4)
	40 aload_1 (0, 0)
	41 areturn (0, 0)

Method: identityPermutation
	0 new (0, 0)
	3 dup (0, 0)
	4 iload_0 (0, 0)
	5 invokespecial (0, 0)
	8 astore_1 (0, 0)
	9 iconst_0 (1, 4)
	10 istore_2 (1, 4)
	11 iload_2 (1, 4)
	12 iload_0 (1, 4)
	13 if_icmpge (1, 4)
	16 aload_1 (1, 4)
	17 iload_2 (1, 4)
	18 i2d (1, 4)
	19 iload_0 (1, 4)
	20 i2d (1, 4)
	21 ddiv (1, 4)
	22 invokestatic (1, 4)
	25 invokeinterface (1, 4)
	30 pop (1, 4)
	31 iinc (1, 4)
	34 goto (1, 4)
	37 aload_1 (0, 0)
	38 areturn (0, 0)

Method: comparatorPermutation
	0 new (0, 0)
	3 dup (0, 0)
	4 aload_0 (0, 0)
	5 invokespecial (0, 0)
	8 astore_2 (0, 0)
	9 aload_2 (0, 0)
	10 aload_1 (0, 0)
	11 invokestatic (0, 0)
	14 aload_0 (0, 0)
	15 aload_2 (0, 0)
	16 invokestatic (0, 0)
	19 areturn (0, 0)

Method: inducedPermutation
	0 aload_0 (1, 1)
	1 invokeinterface (1, 1)
	6 aload_1 (1, 1)
	7 invokeinterface (1, 1)
	12 if_icmpeq (1, 1)
	15 new (1, 1)
	18 dup (1, 1)
	19 aload_1 (1, 1)
	20 invokeinterface (1, 1)
	25 aload_0 (1, 1)
	26 invokeinterface (1, 1)
	31 invokespecial (1, 1)
	34 athrow (1, 1)
	35 aload_0 (0, 0)
	36 invokeinterface (0, 0)
	41 istore_2 (0, 0)
	42 new (0, 0)
	45 dup (0, 0)
	46 aload_0 (0, 0)
	47 invokespecial (0, 0)
	50 astore_3 (0, 0)
	51 iload_2 (0, 0)
	52 anewarray (0, 0)
	55 astore (0, 0)
	57 iconst_0 (1, 4)
	58 istore (1, 4)
	60 iload (1, 4)
	62 iload_2 (1, 4)
	63 if_icmpge (1, 4)
	66 aload_3 (1, 4)
	67 aload_1 (1, 4)
	68 iload (1, 4)
	70 invokeinterface (1, 4)
	75 invokeinterface (1, 4)
	80 istore (1, 4)
	82 iload (2, 1)
	84 iconst_m1 (2, 1)
	85 if_icmpne (2, 1)
	88 new (2, 1)
	91 dup (2, 1)
	92 getstatic (2, 1)
	95 iconst_0 (2, 1)
	96 anewarray (2, 1)
	99 invokespecial (2, 1)
	102 athrow (2, 1)
	103 aload (1, 4)
	105 iload (1, 4)
	107 iload (1, 4)
	109 i2d (1, 4)
	110 iload_2 (1, 4)
	111 i2d (1, 4)
	112 ddiv (1, 4)
	113 invokestatic (1, 4)
	116 aastore (1, 4)
	117 aload_3 (1, 4)
	118 iload (1, 4)
	120 aconst_null (1, 4)
	121 invokeinterface (1, 4)
	126 pop (1, 4)
	127 iinc (1, 4)
	130 goto (1, 4)
	133 aload (0, 0)
	135 invokestatic (0, 0)
	138 areturn (0, 0)

Method: toString
	0 ldc (0, 4)
	2 iconst_2 (0, 4)
	3 anewarray (0, 4)
	6 dup (0, 4)
	7 iconst_0 (0, 4)
	8 aload_0 (0, 4)
	9 invokevirtual (0, 4)
	12 invokestatic (0, 4)
	15 aastore (0, 4)
	16 dup (0, 4)
	17 iconst_1 (0, 4)
	18 aload_0 (0, 4)
	19 getfield (0, 4)
	22 aastore (0, 4)
	23 invokestatic (0, 4)
	26 areturn (0, 4)

Method: baseSequence
	0 new (0, 0)
	3 dup (0, 0)
	4 iload_0 (0, 0)
	5 invokespecial (0, 0)
	8 astore_1 (0, 0)
	9 iconst_0 (1, 4)
	10 istore_2 (1, 4)
	11 iload_2 (1, 4)
	12 iload_0 (1, 4)
	13 if_icmpge (1, 4)
	16 aload_1 (1, 4)
	17 iload_2 (1, 4)
	18 invokestatic (1, 4)
	21 invokeinterface (1, 4)
	26 pop (1, 4)
	27 iinc (1, 4)
	30 goto (1, 4)
	33 aload_1 (0, 0)
	34 areturn (0, 0)

